{
  "type": "Feature",
  "properties": {
    "iso:country":"US",
    "sg:address":"9125 North Plz",
    "sg:city":"Austin",
    "sg:classifiers":[
        {
            "category":"Real Estate",
            "subcategory":"Real Estate Operator",
            "type":"Services"
        }
    ],
    "sg:phone":"+1 512 836 2303",
    "sg:postcode":"78753",
    "sg:province":"TX",
    "sg:tags":[
        "building",
        "apartment"
    ],
    "wof:name":"North Plaza Apartments",
    "wof:placetype":"venue"
},
  "geometry": {"coordinates":[-97.684425,30.355743],"type":"Point"}
}