{
  "type": "Feature",
  "properties": {
    "iso:country":"US",
    "sg:address":"4715 Collinwood Ave",
    "sg:city":"Fort Worth",
    "sg:classifiers":[
        {
            "category":"Professional",
            "subcategory":"Accounting & Tax Preparation",
            "type":"Services"
        }
    ],
    "sg:phone":"+1 817 737 9737",
    "sg:postcode":"76107",
    "sg:province":"TX",
    "sg:tags":[
        "return"
    ],
    "wof:name":"Butler Consulting",
    "wof:placetype":"venue"
},
  "geometry": {"coordinates":[-97.39108400000001,32.737575],"type":"Point"}
}