{
  "type": "Feature",
  "properties": {
    "iso:country":"US",
    "sg:address":"2628 Timberhaven Dr",
    "sg:city":"Flower Mound",
    "sg:classifiers":[
        {
            "category":"Professional",
            "subcategory":"Management & Consulting",
            "type":"Services"
        }
    ],
    "sg:phone":"+1 972 355 6761",
    "sg:postcode":"75028",
    "sg:province":"TX",
    "sg:tags":[
        "training",
        "sales"
    ],
    "sg:website":"www.sales-academy.com",
    "wof:name":"Sales Academy",
    "wof:placetype":"venue"
},
  "geometry": {"coordinates":[-97.071628,33.055575],"type":"Point"}
}