{
  "type": "Feature",
  "properties": {
    "iso:country":"US",
    "sg:address":"1326 SW Military Dr",
    "sg:city":"San Antonio",
    "sg:classifiers":[
        {
            "category":"Insurance",
            "subcategory":"Insurance Agent",
            "type":"Services"
        }
    ],
    "sg:phone":"+1 210 924 4588",
    "sg:postcode":"78221",
    "sg:province":"TX",
    "wof:name":"State Farm Insurance",
    "wof:placetype":"venue"
},
  "geometry": {"coordinates":[-98.51390000000001,29.356595],"type":"Point"}
}