{
  "type": "Feature",
  "properties": {
    "iso:country":"US",
    "sg:address":"2802 San Augustine Ave",
    "sg:city":"Pasadena",
    "sg:classifiers":[
        {
            "category":"Wholesale",
            "subcategory":"Durable Goods & Equipment",
            "type":"Manufacturing & Wholesale Goods"
        }
    ],
    "sg:phone":"+1 713 534 7473",
    "sg:postcode":"77503",
    "sg:province":"TX",
    "wof:name":"Texas Stainless Supply",
    "wof:placetype":"venue"
},
  "geometry": {"coordinates":[-95.171907,29.688561],"type":"Point"}
}