{
  "type": "Feature",
  "properties": {
    "iso:country":"US",
    "sg:address":"2929 N Galloway Ave Ste 110",
    "sg:city":"Mesquite",
    "sg:classifiers":[
        {
            "category":"Fast Food",
            "type":"Food & Drink"
        },
        {
            "category":"Restaurant",
            "type":"Food & Drink"
        }
    ],
    "sg:phone":"+1 972 681 1110",
    "sg:postcode":"75150",
    "sg:province":"TX",
    "sg:tags":[
        "chicken",
        "wing",
        "pizza"
    ],
    "wof:name":"Wings Street",
    "wof:placetype":"venue"
},
  "geometry": {"coordinates":[-96.61143300000001,32.80577],"type":"Point"}
}