{
  "type": "Feature",
  "properties": {
    "iso:country":"US",
    "sg:address":"12911 Cluster Pine Dr",
    "sg:city":"Cypress",
    "sg:classifiers":[
        {
            "category":"Building & Trades",
            "subcategory":"Landscaping Services",
            "type":"Services"
        }
    ],
    "sg:phone":"+1 281 251 7873",
    "sg:postcode":"77429",
    "sg:province":"TX",
    "wof:name":"E&P Lawn Services",
    "wof:placetype":"venue"
},
  "geometry": {"coordinates":[-95.61559,29.997116],"type":"Point"}
}