{
  "type": "Feature",
  "properties": {
    "iso:country":"US",
    "sg:address":"2112 Wyoming Ave",
    "sg:city":"El Paso",
    "sg:classifiers":[
        {
            "category":"Wholesale",
            "subcategory":"Stationery",
            "type":"Manufacturing & Wholesale Goods"
        }
    ],
    "sg:phone":"+1 915 532 5533",
    "sg:postcode":"79903",
    "sg:province":"TX",
    "sg:tags":[
        "personal",
        "industrial",
        "paper"
    ],
    "wof:name":"Southwest Market Area",
    "wof:placetype":"venue"
},
  "geometry": {"coordinates":[-106.469154,31.775997],"type":"Point"}
}