{
  "type": "Feature",
  "properties": {
    "iso:country":"US",
    "sg:address":"2302 Fannin St",
    "sg:city":"Houston",
    "sg:classifiers":[
        {
            "category":"Professional",
            "subcategory":"Management & Consulting",
            "type":"Services"
        }
    ],
    "sg:phone":"+1 713 659 7617",
    "sg:postcode":"77002",
    "sg:province":"TX",
    "sg:tags":[
        "consultant",
        "business"
    ],
    "wof:name":"Christian & Smith",
    "wof:placetype":"venue"
},
  "geometry": {"coordinates":[-95.37232899999999,29.7461],"type":"Point"}
}