{
  "type": "Feature",
  "properties": {
    "iso:country":"US",
    "sg:address":"1900 George Dieter Dr",
    "sg:city":"El Paso",
    "sg:classifiers":[
        {
            "category":"Shopping",
            "subcategory":"Discount & Variety Stores",
            "type":"Retail Goods"
        }
    ],
    "sg:phone":"+1 915 856 6107",
    "sg:postcode":"79936",
    "sg:province":"TX",
    "wof:name":"Dollar Advance LTD",
    "wof:placetype":"venue"
},
  "geometry": {"coordinates":[-106.303349,31.77076],"type":"Point"}
}