{
  "type": "Feature",
  "properties": {
    "iso:country":"US",
    "sg:address":"3817 Cibola Dr",
    "sg:city":"Fort Worth",
    "sg:classifiers":[
        {
            "category":"Building & Trades",
            "subcategory":"Pest Control",
            "type":"Services"
        }
    ],
    "sg:phone":"+1 817 292 7554",
    "sg:postcode":"76133",
    "sg:province":"TX",
    "wof:name":"Advanced Pest Technology",
    "wof:placetype":"venue"
},
  "geometry": {"coordinates":[-97.375472,32.648948],"type":"Point"}
}