{
  "type": "Feature",
  "properties": {
    "iso:country":"US",
    "sg:address":"660 Russwood Dr",
    "sg:city":"Pottsboro",
    "sg:classifiers":[
        {
            "category":"Professional",
            "type":"Services"
        }
    ],
    "sg:phone":"+1 903 786 8830",
    "sg:postcode":"75076",
    "sg:province":"TX",
    "wof:name":"M and P Pemperton",
    "wof:placetype":"venue"
},
  "geometry": {"coordinates":[-96.74185,33.821615],"type":"Point"}
}