{
  "type": "Feature",
  "properties": {
    "iso:country":"US",
    "sg:address":"1009 E US Hwy 83",
    "sg:city":"Mcallen",
    "sg:classifiers":[
        {
            "category":"Home & Garden",
            "subcategory":"Household Appliances",
            "type":"Retail Goods"
        }
    ],
    "sg:phone":"+1 956 630 6318",
    "sg:postcode":"78501",
    "sg:province":"TX",
    "wof:name":"T & M Wholesale Super Store",
    "wof:placetype":"venue"
},
  "geometry": {"coordinates":[-98.210573,26.199866],"type":"Point"}
}