{
  "type": "Feature",
  "properties": {
    "iso:country":"US",
    "sg:address":"932 N Wilcrest Dr",
    "sg:city":"Houston",
    "sg:classifiers":[
        {
            "category":"Personal",
            "subcategory":"Barber",
            "type":"Services"
        }
    ],
    "sg:phone":"+1 281 493 4331",
    "sg:postcode":"77079",
    "sg:province":"TX",
    "wof:name":"Wolf's Barber Shop",
    "wof:placetype":"venue"
},
  "geometry": {"coordinates":[-95.575559,29.782454],"type":"Point"}
}