{
  "type": "Feature",
  "properties": {
    "iso:country":"US",
    "sg:address":"4770 Oakmont Ct",
    "sg:city":"League City",
    "sg:classifiers":[
        {
            "category":"Shopping",
            "subcategory":"Catalog Store",
            "type":"Retail Goods"
        }
    ],
    "sg:phone":"+1 281 521 0217",
    "sg:postcode":"77573",
    "sg:province":"TX",
    "sg:tags":[
        "e"
    ],
    "sg:website":"www.kitparts.com",
    "wof:name":"Kit Parts",
    "wof:placetype":"venue"
},
  "geometry": {"coordinates":[-95.049334,29.528143],"type":"Point"}
}