{
  "type": "Feature",
  "properties": {
    "iso:country":"US",
    "sg:address":"6930 Westlake Ave",
    "sg:city":"Dallas",
    "sg:classifiers":[
        {
            "category":"Professional",
            "type":"Services"
        }
    ],
    "sg:phone":"+1 214 324 8801",
    "sg:postcode":"75214",
    "sg:province":"TX",
    "wof:name":"JDM Creations",
    "wof:placetype":"venue"
},
  "geometry": {"coordinates":[-96.73920699999999,32.822496],"type":"Point"}
}