{
  "type": "Feature",
  "properties": {
    "iso:country":"US",
    "sg:address":"1451 Eastchase Pkwy",
    "sg:city":"Fort Worth",
    "sg:classifiers":[
        {
            "category":"Food & Beverages",
            "subcategory":"Liquor & Beverages",
            "type":"Retail Goods"
        }
    ],
    "sg:phone":"+1 817 265 0114",
    "sg:postcode":"76120",
    "sg:province":"TX",
    "sg:tags":[
        "store"
    ],
    "wof:name":"Fgf Inc",
    "wof:placetype":"venue"
},
  "geometry": {"coordinates":[-97.16695799999999,32.758703],"type":"Point"}
}