{
  "type": "Feature",
  "properties": {
    "iso:country":"US",
    "sg:address":"3000 W 7th St",
    "sg:city":"Fort Worth",
    "sg:classifiers":[
        {
            "category":"Restaurant",
            "type":"Food & Drink"
        }
    ],
    "sg:menulink":"http://www.allmenus.com/tx/fort-worth/222015-chipotle/menu/",
    "sg:phone":"+1 817 348 8530",
    "sg:postcode":"76107",
    "sg:province":"TX",
    "sg:tags":[
        "mexican"
    ],
    "wof:name":"Chipotle",
    "wof:placetype":"venue"
},
  "geometry": {"coordinates":[-97.36062099999999,32.751714],"type":"Point"}
}