{
  "type": "Feature",
  "properties": {
    "iso:country":"US",
    "sg:address":"7213 Owen Ct",
    "sg:city":"Corpus Christi",
    "sg:classifiers":[
        {
            "category":"Building & Trades",
            "subcategory":"Construction",
            "type":"Services"
        }
    ],
    "sg:phone":"+1 361 949 1515",
    "sg:postcode":"78413",
    "sg:province":"TX",
    "sg:tags":[
        "tile",
        "dealer"
    ],
    "wof:name":"Tile Master",
    "wof:placetype":"venue"
},
  "geometry": {"coordinates":[-97.405113,27.677201],"type":"Point"}
}