{
  "type": "Feature",
  "properties": {
    "iso:country":"US",
    "sg:address":"211 N Bolivar St",
    "sg:city":"Marshall",
    "sg:classifiers":[
        {
            "category":"Personal",
            "type":"Services"
        }
    ],
    "sg:phone":"+1 903 934 8525",
    "sg:postcode":"75670",
    "sg:province":"TX",
    "sg:tags":[
        "consultant",
        "planning",
        "wedding"
    ],
    "wof:name":"Fleur Chateau Inc",
    "wof:placetype":"venue"
},
  "geometry": {"coordinates":[-94.366303,32.545978],"type":"Point"}
}