{
  "type": "Feature",
  "properties": {
    "iso:country":"US",
    "sg:address":"411 Lakeway Dr",
    "sg:city":"Lakeway",
    "sg:classifiers":[
        {
            "category":"Professional",
            "type":"Services"
        }
    ],
    "sg:phone":"+1 512 261 6589",
    "sg:postcode":"78734",
    "sg:province":"TX",
    "sg:tags":[
        "establishment"
    ],
    "wof:name":"Move Up Texas",
    "wof:placetype":"venue"
},
  "geometry": {"coordinates":[-97.99199299999999,30.368182],"type":"Point"}
}