{
  "type": "Feature",
  "properties": {
    "iso:country":"US",
    "sg:address":"71 W Side Sq",
    "sg:city":"Cooper",
    "sg:classifiers":[
        {
            "category":"Professional",
            "subcategory":"Lawyer & Legal Services",
            "type":"Services"
        }
    ],
    "sg:phone":"+1 903 395 2210",
    "sg:postcode":"75432",
    "sg:province":"TX",
    "sg:tags":[
        "attorney"
    ],
    "wof:name":"Cynthia L Humphries",
    "wof:placetype":"venue"
},
  "geometry": {"coordinates":[-95.688799,33.374059],"type":"Point"}
}