{
  "type": "Feature",
  "properties": {
    "iso:country":"US",
    "sg:address":"2224 Colcord Ave",
    "sg:city":"Waco",
    "sg:classifiers":[
        {
            "category":"Health Services",
            "subcategory":"Podiatrist",
            "type":"Services"
        }
    ],
    "sg:phone":"+1 254 752 0526",
    "sg:postcode":"76707",
    "sg:province":"TX",
    "wof:name":"K Gittens DPM",
    "wof:placetype":"venue"
},
  "geometry": {"coordinates":[-97.15973700000001,31.554181],"type":"Point"}
}