{
  "type": "Feature",
  "properties": {
    "iso:country":"US",
    "sg:address":"2800 Collins Creek Drive",
    "sg:city":"Austin",
    "sg:classifiers":[
        {
            "category":"Real Estate",
            "subcategory":"Real Estate Operator",
            "type":"Services"
        }
    ],
    "sg:phone":"+1 512 326 5155",
    "sg:postcode":"78741",
    "sg:province":"TX",
    "sg:tags":[
        "apartment"
    ],
    "wof:name":"Rosemont At Oak Valley",
    "wof:placetype":"venue"
},
  "geometry": {"coordinates":[-97.73048799999999,30.22518],"type":"Point"}
}