{
  "type": "Feature",
  "properties": {
    "iso:country":"US",
    "sg:address":"16997 Wilson Rd",
    "sg:city":"Tyler",
    "sg:classifiers":[
        {
            "category":"Wholesale",
            "subcategory":"Chemicals & Plastics",
            "type":"Manufacturing & Wholesale Goods"
        }
    ],
    "sg:phone":"+1 903 566 5572",
    "sg:postcode":"75707",
    "sg:province":"TX",
    "wof:name":"Woman Olde Soape",
    "wof:placetype":"venue"
},
  "geometry": {"coordinates":[-95.129566,32.250772],"type":"Point"}
}