{
  "type": "Feature",
  "properties": {
    "iso:country":"US",
    "sg:address":"1415 Ulrich Rd",
    "sg:city":"Tomball",
    "sg:classifiers":[
        {
            "category":"Personal",
            "type":"Services"
        }
    ],
    "sg:phone":"+1 281 290 0998",
    "sg:postcode":"77375",
    "sg:province":"TX",
    "wof:name":"Ellas Garden",
    "wof:placetype":"venue"
},
  "geometry": {"coordinates":[-95.61928399999999,30.109072],"type":"Point"}
}