{
  "type": "Feature",
  "properties": {
    "iso:country":"US",
    "sg:address":"922 Danforth Pl",
    "sg:city":"Arlington",
    "sg:classifiers":[
        {
            "category":"Wholesale",
            "subcategory":"Construction Materials",
            "type":"Manufacturing & Wholesale Goods"
        }
    ],
    "sg:phone":"+1 817 468 4640",
    "sg:postcode":"76017",
    "sg:province":"TX",
    "sg:tags":[
        "marble"
    ],
    "wof:name":"Arlington Tile Inc",
    "wof:placetype":"venue"
},
  "geometry": {"coordinates":[-97.121933,32.649539],"type":"Point"}
}