{
  "type": "Feature",
  "properties": {
    "iso:country":"US",
    "sg:address":"6220 Curzon Ave",
    "sg:city":"Fort Worth",
    "sg:classifiers":[
        {
            "category":"Health Services",
            "subcategory":"Clinic",
            "type":"Services"
        }
    ],
    "sg:phone":"+1 817 680 0410",
    "sg:postcode":"76116",
    "sg:province":"TX",
    "wof:name":"Health Care Advisory Group",
    "wof:placetype":"venue"
},
  "geometry": {"coordinates":[-97.417648,32.729672],"type":"Point"}
}