{
  "type": "Feature",
  "properties": {
    "iso:country":"US",
    "sg:address":"1318 W Maple Ave",
    "sg:city":"Mcallen",
    "sg:classifiers":[
        {
            "category":"Professional",
            "subcategory":"Art Services",
            "type":"Services"
        },
        {
            "category":"Professional",
            "subcategory":"Business Services",
            "type":"Services"
        }
    ],
    "sg:phone":"+1 956 687 9334",
    "sg:postcode":"78501",
    "sg:province":"TX",
    "sg:tags":[
        "development",
        "product",
        "graphic",
        "designers-industrial",
        "marketing",
        "commercial",
        "designer",
        "design"
    ],
    "wof:name":"Liz Gonzalez Designs",
    "wof:placetype":"venue"
},
  "geometry": {"coordinates":[-98.23158100000001,26.215616],"type":"Point"}
}