{
  "type": "Feature",
  "properties": {
    "iso:country":"US",
    "sg:address":"2730 Agnes St",
    "sg:city":"Corpus Christi",
    "sg:classifiers":[
        {
            "category":"Food & Beverages",
            "subcategory":"Groceries & Convenience Stores",
            "type":"Retail Goods"
        }
    ],
    "sg:phone":"+1 361 888 7402",
    "sg:postcode":"78405",
    "sg:province":"TX",
    "wof:name":"Texas Star",
    "wof:placetype":"venue"
},
  "geometry": {"coordinates":[-97.419248,27.787024],"type":"Point"}
}