{
  "type": "Feature",
  "properties": {
    "iso:country":"US",
    "sg:address":"1117 S Congress Ave",
    "sg:city":"Austin",
    "sg:classifiers":[
        {
            "category":"Retail",
            "subcategory":"Laundry & Dry Cleaning",
            "type":"Services"
        }
    ],
    "sg:phone":"+1 512 444 2332",
    "sg:postcode":"78704",
    "sg:province":"TX",
    "sg:tags":[
        "drycleaning",
        "plant",
        "app"
    ],
    "wof:name":"Ace Expert Alterations & Clrs",
    "wof:placetype":"venue"
},
  "geometry": {"coordinates":[-97.74796600000001,30.254238],"type":"Point"}
}