{
  "type": "Feature",
  "properties": {
    "iso:country":"US",
    "sg:address":"18111 Preston Rd",
    "sg:city":"Dallas",
    "sg:classifiers":[
        {
            "category":"Banks & Credit Unions",
            "subcategory":"Bank",
            "type":"Services"
        }
    ],
    "sg:phone":"+1 972 732 1989",
    "sg:postcode":"75252",
    "sg:province":"TX",
    "sg:tags":[
        "full"
    ],
    "wof:name":"Pnb Financial Bank",
    "wof:placetype":"venue"
},
  "geometry": {"coordinates":[-96.79692799999999,32.999963],"type":"Point"}
}