{
  "type": "Feature",
  "properties": {
    "iso:country":"US",
    "sg:address":"910 E Houston St",
    "sg:city":"Tyler",
    "sg:classifiers":[
        {
            "category":"Health Services",
            "subcategory":"Clinic",
            "type":"Services"
        },
        {
            "category":"Health Services",
            "subcategory":"Doctor",
            "type":"Services"
        }
    ],
    "sg:phone":"+1 903 531 5300",
    "sg:postcode":"75702",
    "sg:province":"TX",
    "sg:tags":[
        "specialty",
        "outpatient"
    ],
    "wof:name":"Ross Breast Center",
    "wof:placetype":"venue"
},
  "geometry": {"coordinates":[-95.289928,32.343561],"type":"Point"}
}