{
  "type": "Feature",
  "properties": {
    "iso:country":"US",
    "sg:address":"71 W Indian Sage Cir",
    "sg:city":"Spring",
    "sg:classifiers":[
        {
            "category":"Banks & Credit Unions",
            "subcategory":"Bank",
            "type":"Services"
        }
    ],
    "sg:phone":"+1 281 364 7461",
    "sg:postcode":"77381",
    "sg:province":"TX",
    "sg:tags":[
        "federal",
        "agency"
    ],
    "wof:name":"Fusion Interamericas",
    "wof:placetype":"venue"
},
  "geometry": {"coordinates":[-95.53295199999999,30.180652],"type":"Point"}
}