{
  "type": "Feature",
  "properties": {
    "iso:country":"US",
    "sg:address":"6500 Denton Hwy",
    "sg:city":"Fort Worth",
    "sg:classifiers":[
        {
            "category":"Wholesale",
            "subcategory":"Hardware",
            "type":"Manufacturing & Wholesale Goods"
        }
    ],
    "sg:phone":"+1 817 577 0879",
    "sg:postcode":"76148",
    "sg:province":"TX",
    "sg:tags":[
        "stapler",
        "tacker",
        "staple"
    ],
    "wof:name":"Texas Tool Traders",
    "wof:placetype":"venue"
},
  "geometry": {"coordinates":[-97.263136,32.867092],"type":"Point"}
}