{
  "type": "Feature",
  "properties": {
    "iso:country":"US",
    "sg:address":"3447 Coconino Dr",
    "sg:city":"San Antonio",
    "sg:classifiers":[
        {
            "category":"Professional",
            "subcategory":"Secretarial Services",
            "type":"Services"
        }
    ],
    "sg:phone":"+1 210 977 9901",
    "sg:postcode":"78211",
    "sg:province":"TX",
    "sg:tags":[
        "machine",
        "reporting"
    ],
    "wof:name":"Justice Reporting & Video",
    "wof:placetype":"venue"
},
  "geometry": {"coordinates":[-98.562888,29.325998],"type":"Point"}
}