{
  "type": "Feature",
  "properties": {
    "iso:country":"US",
    "sg:address":"2218 W Kingsley Rd",
    "sg:city":"Garland",
    "sg:classifiers":[
        {
            "category":"Restaurant",
            "type":"Food & Drink"
        }
    ],
    "sg:menulink":"http://www.allmenus.com/tx/northeast/70378-pizza-hut/menu/",
    "sg:phone":"+1 972 271 1414",
    "sg:postcode":"75041",
    "sg:province":"TX",
    "sg:tags":[
        "american",
        "pizza"
    ],
    "wof:name":"Pizza Hut",
    "wof:placetype":"venue"
},
  "geometry": {"coordinates":[-96.661457,32.87844],"type":"Point"}
}