{
  "type": "Feature",
  "properties": {
    "iso:country":"US",
    "sg:address":"13411 Post Oak Glen Ln",
    "sg:city":"Cypress",
    "sg:classifiers":[
        {
            "category":"Professional",
            "type":"Services"
        }
    ],
    "sg:phone":"+1 832 435 0087",
    "sg:postcode":"77429",
    "sg:province":"TX",
    "wof:name":"Sp South",
    "wof:placetype":"venue"
},
  "geometry": {"coordinates":[-95.624172,30.000776],"type":"Point"}
}