{
  "type": "Feature",
  "properties": {
    "iso:country":"US",
    "sg:address":"301 East Rd",
    "sg:city":"Granbury",
    "sg:classifiers":[
        {
            "category":"Retail",
            "subcategory":"Repair Shop",
            "type":"Services"
        }
    ],
    "sg:phone":"+1 817 326 6137",
    "sg:postcode":"76049",
    "sg:province":"TX",
    "sg:tags":[
        "electrical"
    ],
    "wof:name":"Always Appliance",
    "wof:placetype":"venue"
},
  "geometry": {"coordinates":[-97.71357500000001,32.461003],"type":"Point"}
}