{
  "type": "Feature",
  "properties": {
    "iso:country":"US",
    "sg:address":"4 Savannah Ridge",
    "sg:city":"Frisco",
    "sg:classifiers":[
        {
            "category":"Professional",
            "subcategory":"Business Services",
            "type":"Services"
        }
    ],
    "sg:phone":"+1 972 624 1130",
    "sg:postcode":"75034",
    "sg:province":"TX",
    "sg:tags":[
        "interior",
        "consultant",
        "design",
        "decorator"
    ],
    "wof:name":"It Nexus Inc",
    "wof:placetype":"venue"
},
  "geometry": {"coordinates":[-96.84852600000001,33.105974],"type":"Point"}
}