{
  "type": "Feature",
  "properties": {
    "iso:country":"US",
    "sg:address":"190 N Stemmons Fwy",
    "sg:city":"Lewisville",
    "sg:classifiers":[
        {
            "category":"Professional",
            "subcategory":"Lawyer & Legal Services",
            "type":"Services"
        }
    ],
    "sg:phone":"+1 214 222 3030",
    "sg:postcode":"75067",
    "sg:province":"TX",
    "sg:tags":[
        "attorney"
    ],
    "wof:name":"Angie N'Duka Law Office",
    "wof:placetype":"venue"
},
  "geometry": {"coordinates":[-97.008436,33.047617],"type":"Point"}
}