{
  "type": "Feature",
  "properties": {
    "iso:country":"US",
    "sg:address":"227 Lake Wichita Dr",
    "sg:city":"Wylie",
    "sg:classifiers":[
        {
            "category":"Professional",
            "subcategory":"Computer Services",
            "type":"Services"
        }
    ],
    "sg:phone":"+1 972 442 1720",
    "sg:postcode":"75098",
    "sg:province":"TX",
    "sg:tags":[
        "website",
        "design"
    ],
    "wof:name":"RYONWITHANO.COM",
    "wof:placetype":"venue"
},
  "geometry": {"coordinates":[-96.53527699999999,32.998794],"type":"Point"}
}