{
  "type": "Feature",
  "properties": {
    "iso:country":"US",
    "sg:address":"6302 Frankford Ave",
    "sg:city":"Lubbock",
    "sg:classifiers":[
        {
            "category":"Restaurant",
            "type":"Food & Drink"
        }
    ],
    "sg:phone":"+1 806 687 5275",
    "sg:postcode":"79415",
    "sg:province":"TX",
    "wof:name":"Subway Sandwiches & Salads",
    "wof:placetype":"venue"
},
  "geometry": {"coordinates":[-101.93985499999999,33.658932],"type":"Point"}
}