{
  "type": "Feature",
  "properties": {
    "iso:country":"US",
    "sg:address":"2120 Hemphill St",
    "sg:city":"Greenville",
    "sg:classifiers":[
        {
            "category":"Retail",
            "subcategory":"Funeral Services",
            "type":"Services"
        }
    ],
    "sg:phone":"+1 903 455 2440",
    "sg:postcode":"75401",
    "sg:province":"TX",
    "sg:tags":[
        "director"
    ],
    "wof:name":"Grace & Mercy-Grundy Funeral",
    "wof:placetype":"venue"
},
  "geometry": {"coordinates":[-96.103756,33.133267],"type":"Point"}
}