{
  "type": "Feature",
  "properties": {
    "iso:country":"US",
    "sg:address":"1234 S Main St",
    "sg:city":"Boerne",
    "sg:classifiers":[
        {
            "category":"Professional",
            "type":"Services"
        }
    ],
    "sg:phone":"+1 830 249 6073",
    "sg:postcode":"78006",
    "sg:province":"TX",
    "sg:tags":[
        "establishment"
    ],
    "wof:name":"Family Korner",
    "wof:placetype":"venue"
},
  "geometry": {"coordinates":[-98.728066,29.778468],"type":"Point"}
}