{
  "type": "Feature",
  "properties": {
    "iso:country":"US",
    "sg:address":"1501 West Koenig Lane",
    "sg:city":"Austin",
    "sg:classifiers":[
        {
            "category":"Health Services",
            "subcategory":"Health Practitioner",
            "type":"Services"
        }
    ],
    "sg:phone":"+1 512 653 6131",
    "sg:postcode":"78756",
    "sg:province":"TX",
    "sg:tags":[
        "acupuncture"
    ],
    "sg:website":"www.ancientartsaustin.com",
    "wof:name":"Ancient Arts",
    "wof:placetype":"venue"
},
  "geometry": {"coordinates":[-97.73268400000001,30.331165],"type":"Point"}
}