{
  "type": "Feature",
  "properties": {
    "iso:country":"US",
    "sg:address":"1000 N Loop 336 E",
    "sg:city":"Conroe",
    "sg:classifiers":[
        {
            "category":"Banks & Credit Unions",
            "subcategory":"Bank",
            "type":"Services"
        }
    ],
    "sg:phone":"+1 936 756 0601",
    "sg:postcode":"77301",
    "sg:province":"TX",
    "wof:name":"Guaranty Bank",
    "wof:placetype":"venue"
},
  "geometry": {"coordinates":[-95.438907,30.339829],"type":"Point"}
}