{
  "type": "Feature",
  "properties": {
    "iso:country":"US",
    "sg:address":"1025 Lott Ave",
    "sg:city":"Austin",
    "sg:classifiers":[
        {
            "category":"Professional",
            "type":"Services"
        }
    ],
    "sg:postcode":"78721",
    "sg:province":"TX",
    "sg:tags":[
        "planning",
        "event"
    ],
    "sg:website":"www.synercorp.com",
    "wof:name":"Rez Logos Party Planners",
    "wof:placetype":"venue"
},
  "geometry": {"coordinates":[-97.682453,30.269128],"type":"Point"}
}