{
  "type": "Feature",
  "properties": {
    "iso:country":"US",
    "sg:address":"511 N Ave A",
    "sg:city":"Aransas Pass",
    "sg:classifiers":[
        {
            "category":"Freight",
            "type":"Transportation"
        }
    ],
    "sg:phone":"+1 361 758 1818",
    "sg:postcode":"78336",
    "sg:province":"TX",
    "sg:tags":[
        "commercial",
        "storage"
    ],
    "wof:name":"Sweet Bay Mini Barns",
    "wof:placetype":"venue"
},
  "geometry": {"coordinates":[-97.161519,27.919013],"type":"Point"}
}