{
  "type": "Feature",
  "properties": {
    "iso:country":"US",
    "sg:address":"18806 Turtle Creek Way",
    "sg:city":"Magnolia",
    "sg:classifiers":[
        {
            "category":"Building & Trades",
            "subcategory":"Construction",
            "type":"Services"
        }
    ],
    "sg:phone":"+1 281 356 4051",
    "sg:postcode":"77355",
    "sg:province":"TX",
    "sg:tags":[
        "residential"
    ],
    "wof:name":"Durabuilt Construction",
    "wof:placetype":"venue"
},
  "geometry": {"coordinates":[-95.730133,30.121865],"type":"Point"}
}