{
  "type": "Feature",
  "properties": {
    "iso:country":"US",
    "sg:address":"7135 Woodridge Dr",
    "sg:city":"Houston",
    "sg:classifiers":[
        {
            "category":"Restaurant",
            "type":"Food & Drink"
        }
    ],
    "sg:phone":"+1 713 644 9208",
    "sg:postcode":"77087",
    "sg:province":"TX",
    "sg:tags":[
        "eating"
    ],
    "wof:name":"Lonestar Restaurant Maintnence",
    "wof:placetype":"venue"
},
  "geometry": {"coordinates":[-95.29442299999999,29.703317],"type":"Point"}
}