{
  "type": "Feature",
  "properties": {
    "iso:country":"US",
    "sg:address":"3101 S Port Ave",
    "sg:city":"Corpus Christi",
    "sg:classifiers":[
        {
            "category":"Food & Beverages",
            "subcategory":"Groceries & Convenience Stores",
            "type":"Retail Goods"
        }
    ],
    "sg:phone":"+1 361 882 1930",
    "sg:postcode":"78416",
    "sg:province":"TX",
    "wof:name":"An's Market",
    "wof:placetype":"venue"
},
  "geometry": {"coordinates":[-97.420203,27.764799],"type":"Point"}
}