{
  "type": "Feature",
  "properties": {
    "iso:country":"US",
    "sg:address":"4750 Co Rd 301",
    "sg:city":"Bartlett",
    "sg:phone":"+1 254 527 3778",
    "sg:postcode":"76511",
    "sg:province":"TX",
    "sg:tags":[
        "farm",
        "land",
        "cash",
        "lease"
    ],
    "wof:name":"Vrabel Farms",
    "wof:placetype":"venue"
},
  "geometry": {"coordinates":[-97.46097399999999,30.781187],"type":"Point"}
}