{
  "type": "Feature",
  "properties": {
    "iso:country":"US",
    "sg:address":"1627 N Grand Ave",
    "sg:city":"Gainesville",
    "sg:classifiers":[
        {
            "category":"Health Services",
            "subcategory":"Doctor",
            "type":"Services"
        }
    ],
    "sg:phone":"+1 940 668 6878",
    "sg:postcode":"76240",
    "sg:province":"TX",
    "sg:tags":[
        "physician",
        "surgeon"
    ],
    "sg:website":"www.bskhairamd.com",
    "wof:name":"Bhupinder S Khaira MD",
    "wof:placetype":"venue"
},
  "geometry": {"coordinates":[-97.13404800000001,33.646821],"type":"Point"}
}