{
  "type": "Feature",
  "properties": {
    "iso:country":"US",
    "sg:address":"1306 Bard Ct",
    "sg:city":"Garland",
    "sg:classifiers":[
        {
            "category":"Shopping",
            "subcategory":"Clothing, Apparel, & Fashions",
            "type":"Retail Goods"
        }
    ],
    "sg:phone":"+1 972 271 3877",
    "sg:postcode":"75040",
    "sg:province":"TX",
    "sg:tags":[
        "bridal",
        "store"
    ],
    "wof:name":"Margaritas Bridal",
    "wof:placetype":"venue"
},
  "geometry": {"coordinates":[-96.611634,32.90138],"type":"Point"}
}