{
  "type": "Feature",
  "properties": {
    "iso:country":"US",
    "sg:address":"1001 Cross Timbers Rd",
    "sg:city":"Flower Mound",
    "sg:classifiers":[
        {
            "category":"Banks & Credit Unions",
            "subcategory":"Bank",
            "type":"Services"
        }
    ],
    "sg:phone":"+1 972 691 2011",
    "sg:postcode":"75028",
    "sg:province":"TX",
    "sg:tags":[
        "loan",
        "real estate"
    ],
    "wof:name":"Wells Fargo Home Mortgage Inc",
    "wof:placetype":"venue"
},
  "geometry": {"coordinates":[-97.04061799999999,33.042212],"type":"Point"}
}