{
  "type": "Feature",
  "properties": {
    "iso:country":"US",
    "sg:address":"5600 Randolph Blvd",
    "sg:city":"San Antonio",
    "sg:classifiers":[
        {
            "category":"Shopping",
            "subcategory":"Computers & Home Electronics",
            "type":"Retail Goods"
        }
    ],
    "sg:phone":"+1 210 654 0443",
    "sg:postcode":"78233",
    "sg:province":"TX",
    "sg:tags":[
        "equipment",
        "satellite",
        "system"
    ],
    "wof:name":"D F Countryman Co",
    "wof:placetype":"venue"
},
  "geometry": {"coordinates":[-98.37676399999999,29.534976],"type":"Point"}
}