{
  "type": "Feature",
  "properties": {
    "iso:country":"US",
    "sg:address":"23 Alba Rd",
    "sg:city":"Montgomery",
    "sg:classifiers":[
        {
            "category":"Professional",
            "subcategory":"Business Services",
            "type":"Services"
        }
    ],
    "sg:phone":"+1 936 582 4836",
    "sg:postcode":"77356",
    "sg:province":"TX",
    "sg:tags":[
        "interior",
        "consultant",
        "design",
        "decorator"
    ],
    "wof:name":"Stephens Interiors Inc",
    "wof:placetype":"venue"
},
  "geometry": {"coordinates":[-95.638499,30.401541],"type":"Point"}
}