{
  "type": "Feature",
  "properties": {
    "iso:country":"US",
    "sg:address":"1030 N Zang Blvd",
    "sg:city":"Dallas",
    "sg:classifiers":[
        {
            "category":"Building & Trades",
            "subcategory":"Locksmith",
            "type":"Services"
        }
    ],
    "sg:phone":"+1 214 946 9593",
    "sg:postcode":"75208",
    "sg:province":"TX",
    "sg:tags":[
        "key"
    ],
    "sg:website":"www.aocolocksmiths.com",
    "wof:name":"Aoco Locksmiths",
    "wof:placetype":"venue"
},
  "geometry": {"coordinates":[-96.823196,32.755501],"type":"Point"}
}