{
  "type": "Feature",
  "properties": {
    "iso:country":"US",
    "sg:address":"10440 N Central Expy Suite 210",
    "sg:city":"Dallas",
    "sg:classifiers":[
        {
            "category":"Retail",
            "subcategory":"Repair Shop",
            "type":"Services"
        },
        {
            "category":"Manufacturing",
            "subcategory":"Soap",
            "type":"Manufacturing & Wholesale Goods"
        }
    ],
    "sg:phone":"+1 214 369 4063",
    "sg:postcode":"75231",
    "sg:province":"TX",
    "sg:tags":[
        "watches-wholesale",
        "watch",
        "manufacturer"
    ],
    "sg:website":"http://www.timedelay.com",
    "wof:name":"Time Delay Corporation",
    "wof:placetype":"venue"
},
  "geometry": {"coordinates":[-96.769434,32.888173],"type":"Point"}
}