{
  "type": "Feature",
  "properties": {
    "iso:country":"US",
    "sg:address":"16490 N Emerson Cir",
    "sg:city":"Conroe",
    "sg:classifiers":[
        {
            "category":"Social Services",
            "type":"Services"
        }
    ],
    "sg:phone":"+1 936 264 3751",
    "sg:postcode":"77306",
    "sg:province":"TX",
    "sg:tags":[
        "fire",
        "assistance",
        "fighter",
        "family"
    ],
    "wof:name":"Hart 2 Hart",
    "wof:placetype":"venue"
},
  "geometry": {"coordinates":[-95.313467,30.330363],"type":"Point"}
}