{
  "type": "Feature",
  "properties": {
    "iso:country":"US",
    "sg:address":"802 Anderson St",
    "sg:city":"Bellaire",
    "sg:classifiers":[
        {
            "category":"Professional",
            "subcategory":"Management & Consulting",
            "type":"Services"
        }
    ],
    "sg:phone":"+1 713 665 0010",
    "sg:postcode":"77401",
    "sg:province":"TX",
    "sg:tags":[
        "consultant",
        "search",
        "executive"
    ],
    "wof:name":"Faith Executive Search, L L C",
    "wof:placetype":"venue"
},
  "geometry": {"coordinates":[-95.46386800000001,29.713045],"type":"Point"}
}