{
  "type": "Feature",
  "properties": {
    "iso:country":"US",
    "sg:address":"5815 Edgewood Dr",
    "sg:city":"Mc Kinney",
    "sg:classifiers":[
        {
            "category":"Professional",
            "subcategory":"Management & Consulting",
            "type":"Services"
        }
    ],
    "sg:phone":"+1 972 529 5328",
    "sg:postcode":"75070",
    "sg:province":"TX",
    "sg:tags":[
        "business"
    ],
    "wof:name":"Gage Business Consulting",
    "wof:placetype":"venue"
},
  "geometry": {"coordinates":[-96.69334600000001,33.182491],"type":"Point"}
}