{
  "type": "Feature",
  "properties": {
    "iso:country":"US",
    "sg:address":"3105 Stonehenge Dr",
    "sg:city":"Richardson",
    "sg:classifiers":[
        {
            "category":"Professional",
            "subcategory":"Management & Consulting",
            "type":"Services"
        }
    ],
    "sg:phone":"+1 972 994 0219",
    "sg:postcode":"75082",
    "sg:province":"TX",
    "wof:name":"Jack Edwin Counts & Associates",
    "wof:placetype":"venue"
},
  "geometry": {"coordinates":[-96.62000399999999,32.99138],"type":"Point"}
}