{
  "type": "Feature",
  "properties": {
    "iso:country":"US",
    "sg:address":"306 N Timberland Dr",
    "sg:city":"Lufkin",
    "sg:classifiers":[
        {
            "category":"Autos & Motor Vehicles",
            "subcategory":"Automobile Sales",
            "type":"Retail Goods"
        }
    ],
    "sg:phone":"+1 936 634 4488",
    "sg:postcode":"75901",
    "sg:province":"TX",
    "sg:tags":[
        "car",
        "dealer"
    ],
    "wof:name":"Mercer Nissan-Mazda Inc",
    "wof:placetype":"venue"
},
  "geometry": {"coordinates":[-94.717214,31.338739],"type":"Point"}
}