{
  "type": "Feature",
  "properties": {
    "iso:country":"US",
    "sg:address":"8811 Feland St",
    "sg:city":"Houston",
    "sg:classifiers":[
        {
            "category":"Recreation",
            "type":"Entertainment"
        }
    ],
    "sg:phone":"+1 713 636 8217",
    "sg:postcode":"77028",
    "sg:province":"TX",
    "sg:tags":[
        "hall",
        "auditorium"
    ],
    "wof:name":"Lakewood Community Ctr",
    "wof:placetype":"venue"
},
  "geometry": {"coordinates":[-95.267248,29.837108],"type":"Point"}
}