{
  "type": "Feature",
  "properties": {
    "iso:country":"US",
    "sg:address":"1801 S Mo Pac Expy Ste 100",
    "sg:city":"Austin",
    "sg:classifiers":[
        {
            "category":"Real Estate",
            "subcategory":"Real Estate Services",
            "type":"Services"
        },
        {
            "category":"Real Estate",
            "subcategory":"Real Estate Agent",
            "type":"Services"
        }
    ],
    "sg:phone":"+1 512 924 0044",
    "sg:postcode":"78746",
    "sg:province":"TX",
    "sg:tags":[
        "buyer",
        "broker"
    ],
    "wof:name":"Cat Mountain Realtor",
    "wof:placetype":"venue"
},
  "geometry": {"coordinates":[-97.793167,30.260221],"type":"Point"}
}