{
  "type": "Feature",
  "properties": {
    "iso:country":"US",
    "sg:address":"809 E Magnolia St",
    "sg:city":"Freer",
    "sg:classifiers":[
        {
            "category":"Shopping",
            "subcategory":"Gifts & Souvenirs",
            "type":"Retail Goods"
        }
    ],
    "sg:phone":"+1 361 394 6896",
    "sg:postcode":"78384",
    "sg:province":"TX",
    "sg:tags":[
        "shop"
    ],
    "wof:name":"Busy Bees",
    "wof:placetype":"venue"
},
  "geometry": {"coordinates":[-98.61175299999999,27.875838],"type":"Point"}
}