{
  "type": "Feature",
  "properties": {
    "iso:country":"US",
    "sg:address":"7208 Karen Dr",
    "sg:city":"Fort Worth",
    "sg:classifiers":[
        {
            "category":"Professional",
            "type":"Services"
        }
    ],
    "sg:phone":"+1 817 281 1494",
    "sg:postcode":"76180",
    "sg:province":"TX",
    "wof:name":"Diamondback Oil Co",
    "wof:placetype":"venue"
},
  "geometry": {"coordinates":[-97.226094,32.837134],"type":"Point"}
}