{
  "type": "Feature",
  "properties": {
    "iso:country":"US",
    "sg:address":"4209 Bordeaux Ave",
    "sg:city":"Dallas",
    "sg:classifiers":[
        {
            "category":"Shopping",
            "subcategory":"Florist",
            "type":"Retail Goods"
        }
    ],
    "sg:phone":"+1 214 528 2766",
    "sg:postcode":"75205",
    "sg:province":"TX",
    "wof:name":"Flower Road",
    "wof:placetype":"venue"
},
  "geometry": {"coordinates":[-96.80328900000001,32.824504],"type":"Point"}
}