{
  "type": "Feature",
  "properties": {
    "iso:country":"US",
    "sg:address":"6612 Alameda Ave",
    "sg:city":"El Paso",
    "sg:classifiers":[
        {
            "category":"Autos & Motor Vehicles",
            "subcategory":"Auto Supplies",
            "type":"Retail Goods"
        }
    ],
    "sg:phone":"+1 915 772 9409",
    "sg:postcode":"79905",
    "sg:province":"TX",
    "sg:tags":[
        "tire"
    ],
    "wof:name":"Blue Fox Tires",
    "wof:placetype":"venue"
},
  "geometry": {"coordinates":[-106.407554,31.764446],"type":"Point"}
}