{
  "type": "Feature",
  "properties": {
    "iso:country":"US",
    "sg:address":"1801 Eastchase Pkwy",
    "sg:city":"Fort Worth",
    "sg:classifiers":[
        {
            "category":"Banks & Credit Unions",
            "subcategory":"Bank",
            "type":"Services"
        }
    ],
    "sg:phone":"+1 817 261 8600",
    "sg:postcode":"76120",
    "sg:province":"TX",
    "sg:tags":[
        "cashing",
        "check"
    ],
    "wof:name":"Check 'n Go",
    "wof:placetype":"venue"
},
  "geometry": {"coordinates":[-97.17130299999999,32.752399],"type":"Point"}
}