{
  "type": "Feature",
  "properties": {
    "iso:country":"US",
    "sg:address":"1829 Bering Dr",
    "sg:city":"Houston",
    "sg:classifiers":[
        {
            "category":"Professional",
            "type":"Services"
        }
    ],
    "sg:phone":"+1 713 783 4541",
    "sg:postcode":"77057",
    "sg:province":"TX",
    "wof:name":"Jess L Windham",
    "wof:placetype":"venue"
},
  "geometry": {"coordinates":[-95.47942399999999,29.746454],"type":"Point"}
}