{
  "type": "Feature",
  "properties": {
    "iso:country":"US",
    "sg:address":"107 S Lanham St",
    "sg:city":"Little River",
    "sg:classifiers":[
        {
            "category":"Building & Trades",
            "subcategory":"Landscaping Services",
            "type":"Services"
        }
    ],
    "sg:phone":"+1 254 982 4031",
    "sg:postcode":"76554",
    "sg:province":"TX",
    "wof:name":"Bunker Lawn & Tree Care",
    "wof:placetype":"venue"
},
  "geometry": {"coordinates":[-97.352934,30.982717],"type":"Point"}
}