{
  "type": "Feature",
  "properties": {
    "iso:country":"US",
    "sg:address":"1907 Candlewyck Xing",
    "sg:city":"Allen",
    "sg:classifiers":[
        {
            "category":"Wholesale",
            "subcategory":"Office Equipment",
            "type":"Manufacturing & Wholesale Goods"
        },
        {
            "category":"Professional",
            "subcategory":"Accounting & Tax Preparation",
            "type":"Services"
        }
    ],
    "sg:phone":"+1 972 727 8175",
    "sg:postcode":"75013",
    "sg:province":"TX",
    "sg:tags":[
        "bookkeeping",
        "system"
    ],
    "wof:name":"World On-Line The",
    "wof:placetype":"venue"
},
  "geometry": {"coordinates":[-96.70281799999999,33.128037],"type":"Point"}
}