{
  "type": "Feature",
  "properties": {
    "iso:country":"US",
    "sg:address":"8188 Spring Valley Rd",
    "sg:city":"Dallas",
    "sg:classifiers":[
        {
            "category":"Food & Beverages",
            "subcategory":"Groceries & Convenience Stores",
            "type":"Retail Goods"
        }
    ],
    "sg:phone":"+1 972 234 2531",
    "sg:postcode":"75240",
    "sg:province":"TX",
    "sg:tags":[
        "union",
        "credit",
        "bank"
    ],
    "wof:name":"Step-N-Go",
    "wof:placetype":"venue"
},
  "geometry": {"coordinates":[-96.764702,32.939701],"type":"Point"}
}