{
  "type": "Feature",
  "properties": {
    "iso:country":"US",
    "sg:address":"19711 Faye Oaks Ct",
    "sg:city":"Humble",
    "sg:classifiers":[
        {
            "category":"Professional",
            "type":"Services"
        }
    ],
    "sg:phone":"+1 281 852 5309",
    "sg:postcode":"77346",
    "sg:province":"TX",
    "wof:name":"Walter E Dambach",
    "wof:placetype":"venue"
},
  "geometry": {"coordinates":[-95.189454,30.009345],"type":"Point"}
}