{
  "type": "Feature",
  "properties": {
    "iso:country":"US",
    "sg:address":"7415 Eastex Plaza Dr",
    "sg:city":"Beaumont",
    "sg:classifiers":[
        {
            "category":"Organizations",
            "subcategory":"Non-profit Organization",
            "type":"Services"
        },
        {
            "category":"Organizations",
            "subcategory":"Professional Association",
            "type":"Services"
        }
    ],
    "sg:phone":"+1 409 980 8800",
    "sg:postcode":"77708",
    "sg:province":"TX",
    "sg:tags":[
        "social"
    ],
    "wof:name":"American Heart Association",
    "wof:placetype":"venue"
},
  "geometry": {"coordinates":[-94.17575100000001,30.142763],"type":"Point"}
}