{
  "type": "Feature",
  "properties": {
    "iso:country":"US",
    "sg:address":"14005 N US Hwy 183",
    "sg:city":"Austin",
    "sg:classifiers":[
        {
            "category":"Personal",
            "subcategory":"Day Spa",
            "type":"Services"
        }
    ],
    "sg:phone":"+1 512 918 3223",
    "sg:postcode":"78717",
    "sg:province":"TX",
    "wof:name":"Facelogic Spa - Austin Northwest",
    "wof:placetype":"venue"
},
  "geometry": {"coordinates":[-97.798918,30.474678],"type":"Point"}
}