{
  "type": "Feature",
  "properties": {
    "iso:country":"US",
    "sg:address":"2729 Wagonwheel Dr",
    "sg:city":"Carrollton",
    "sg:classifiers":[
        {
            "category":"Building & Trades",
            "subcategory":"Equipment Rental",
            "type":"Services"
        }
    ],
    "sg:phone":"+1 972 416 3441",
    "sg:postcode":"75006",
    "sg:province":"TX",
    "sg:tags":[
        "yard",
        "leasing",
        "store"
    ],
    "wof:name":"Wil Mar Leasing Corp",
    "wof:placetype":"venue"
},
  "geometry": {"coordinates":[-96.86362,32.96292],"type":"Point"}
}