{
  "type": "Feature",
  "properties": {
    "iso:country":"US",
    "sg:address":"514 S Garland Ave",
    "sg:city":"Garland",
    "sg:classifiers":[
        {
            "category":"Education",
            "subcategory":"Music School",
            "type":"Public Place"
        }
    ],
    "sg:phone":"+1 972 272 8077",
    "sg:postcode":"75040",
    "sg:province":"TX",
    "sg:tags":[
        "instrument",
        "teacher",
        "musical"
    ],
    "wof:name":"Anderson's Dave Zoo Music",
    "wof:placetype":"venue"
},
  "geometry": {"coordinates":[-96.648201,32.908798],"type":"Point"}
}