{
  "type": "Feature",
  "properties": {
    "iso:country":"US",
    "sg:address":"104 E Franklin St",
    "sg:city":"Fayetteville",
    "sg:classifiers":[
        {
            "category":"Wholesale",
            "subcategory":"Farm Supplies",
            "type":"Manufacturing & Wholesale Goods"
        },
        {
            "category":"Shopping",
            "type":"Retail Goods"
        }
    ],
    "sg:phone":"+1 979 378 2310",
    "sg:postcode":"78940",
    "sg:province":"TX",
    "sg:tags":[
        "feed",
        "merchandise"
    ],
    "wof:name":"G & S Grain Company",
    "wof:placetype":"venue"
},
  "geometry": {"coordinates":[-96.67348800000001,29.904354],"type":"Point"}
}