{
  "type": "Feature",
  "properties": {
    "iso:country":"US",
    "sg:address":"8402 Old Stone Gate",
    "sg:city":"San Antonio",
    "sg:classifiers":[
        {
            "category":"Wholesale",
            "subcategory":"Computers",
            "type":"Manufacturing & Wholesale Goods"
        }
    ],
    "sg:phone":"+1 210 392 4635",
    "sg:postcode":"78249",
    "sg:province":"TX",
    "sg:tags":[
        "telecommunication"
    ],
    "wof:name":"Texas Wires",
    "wof:placetype":"venue"
},
  "geometry": {"coordinates":[-98.651771,29.54632],"type":"Point"}
}