{
  "type": "Feature",
  "properties": {
    "iso:country":"US",
    "sg:address":"1803 Dulles",
    "sg:city":"San Antonio",
    "sg:classifiers":[
        {
            "category":"Shopping",
            "subcategory":"Gifts & Souvenirs",
            "type":"Retail Goods"
        }
    ],
    "sg:phone":"+1 210 520 9635",
    "sg:postcode":"78251",
    "sg:province":"TX",
    "wof:name":"G & D Novelties",
    "wof:placetype":"venue"
},
  "geometry": {"coordinates":[-98.66361999999999,29.455491],"type":"Point"}
}