{
  "type": "Feature",
  "properties": {
    "iso:country":"US",
    "sg:address":"3713 Helen Ln",
    "sg:city":"Pearland",
    "sg:classifiers":[
        {
            "category":"Shopping",
            "subcategory":"Catalog Store",
            "type":"Retail Goods"
        }
    ],
    "sg:phone":"+1 281 485 2075",
    "sg:postcode":"77581",
    "sg:province":"TX",
    "sg:tags":[
        "house",
        "online",
        "order",
        "mail"
    ],
    "wof:name":"Premium Promotional Industries",
    "wof:placetype":"venue"
},
  "geometry": {"coordinates":[-95.26267199999999,29.550049],"type":"Point"}
}