{
  "type": "Feature",
  "properties": {
    "iso:country":"US",
    "sg:address":"3217 Rinehart St",
    "sg:city":"Grand Prairie",
    "sg:classifiers":[
        {
            "category":"Shopping",
            "subcategory":"News",
            "type":"Retail Goods"
        }
    ],
    "sg:phone":"+1 972 263 1203",
    "sg:postcode":"75050",
    "sg:province":"TX",
    "sg:tags":[
        "dealer"
    ],
    "wof:name":"Circulation Unlimited",
    "wof:placetype":"venue"
},
  "geometry": {"coordinates":[-96.955962,32.752579],"type":"Point"}
}