{
  "type": "Feature",
  "properties": {
    "iso:country":"US",
    "sg:address":"113 W McHarg St",
    "sg:city":"Stamford",
    "sg:classifiers":[
        {
            "category":"Manufacturing",
            "subcategory":"Printing",
            "type":"Manufacturing & Wholesale Goods"
        }
    ],
    "sg:phone":"+1 325 773 3621",
    "sg:postcode":"79553",
    "sg:province":"TX",
    "sg:tags":[
        "newspaper"
    ],
    "wof:name":"Stamford American",
    "wof:placetype":"venue"
},
  "geometry": {"coordinates":[-99.80427899999999,32.945185],"type":"Point"}
}