{
  "type": "Feature",
  "properties": {
    "iso:country":"US",
    "sg:address":"8052 Boone Rd",
    "sg:city":"Houston",
    "sg:classifiers":[
        {
            "category":"Real Estate",
            "subcategory":"Real Estate Agent",
            "type":"Services"
        }
    ],
    "sg:phone":"+1 281 988 7200",
    "sg:postcode":"77072",
    "sg:province":"TX",
    "wof:name":"VIP Realty",
    "wof:placetype":"venue"
},
  "geometry": {"coordinates":[-95.574738,29.690775],"type":"Point"}
}