{
  "type": "Feature",
  "properties": {
    "iso:country":"US",
    "sg:address":"1920 Whitney Ln",
    "sg:city":"Mc Kinney",
    "sg:classifiers":[
        {
            "category":"Professional",
            "subcategory":"Management & Consulting",
            "type":"Services"
        }
    ],
    "sg:phone":"+1 972 978 4441",
    "sg:postcode":"75070",
    "sg:province":"TX",
    "wof:name":"Design Inspiration",
    "wof:placetype":"venue"
},
  "geometry": {"coordinates":[-96.664591,33.178916],"type":"Point"}
}