{
  "type": "Feature",
  "properties": {
    "iso:country":"US",
    "sg:address":"107 Dana Dr",
    "sg:city":"Highlands",
    "sg:classifiers":[
        {
            "category":"Restaurant",
            "type":"Food & Drink"
        }
    ],
    "sg:phone":"+1 281 426 5014",
    "sg:postcode":"77562",
    "sg:province":"TX",
    "sg:tags":[
        "eating"
    ],
    "wof:name":"Soap Chick",
    "wof:placetype":"venue"
},
  "geometry": {"coordinates":[-95.04605599999999,29.812468],"type":"Point"}
}