{
  "type": "Feature",
  "properties": {
    "iso:country":"US",
    "sg:address":"1705 Sawtooth Oak Trl",
    "sg:city":"Keller",
    "sg:classifiers":[
        {
            "category":"Building & Trades",
            "subcategory":"Construction",
            "type":"Services"
        }
    ],
    "sg:phone":"+1 817 577 4854",
    "sg:postcode":"76248",
    "sg:province":"TX",
    "sg:tags":[
        "drainage",
        "contractor"
    ],
    "wof:name":"Four Seasons Drainage",
    "wof:placetype":"venue"
},
  "geometry": {"coordinates":[-97.24123899999999,32.90331],"type":"Point"}
}