{
  "type": "Feature",
  "properties": {
    "iso:country":"US",
    "sg:address":"103 State Hwy 21",
    "sg:city":"Caldwell",
    "sg:classifiers":[
        {
            "category":"Social Services",
            "type":"Services"
        }
    ],
    "sg:phone":"+1 979 567 4377",
    "sg:postcode":"77836",
    "sg:province":"TX",
    "wof:name":"Mhmr Authority of Burleson",
    "wof:placetype":"venue"
},
  "geometry": {"coordinates":[-96.695097,30.535667],"type":"Point"}
}