{
  "type": "Feature",
  "properties": {
    "iso:country":"US",
    "sg:address":"4011 Beaver Dr",
    "sg:city":"Amarillo",
    "sg:classifiers":[
        {
            "category":"Education",
            "subcategory":"School",
            "type":"Public Place"
        }
    ],
    "sg:phone":"+1 806 381 7245",
    "sg:postcode":"79107",
    "sg:province":"TX",
    "wof:name":"Mesa Verde Elementary School",
    "wof:placetype":"venue"
},
  "geometry": {"coordinates":[-101.790192,35.241948],"type":"Point"}
}