{
  "type": "Feature",
  "properties": {
    "iso:country":"US",
    "sg:address":"109 Pine St",
    "sg:city":"Lake Jackson",
    "sg:classifiers":[
        {
            "category":"Retail",
            "subcategory":"Auto Repair",
            "type":"Services"
        }
    ],
    "sg:phone":"+1 979 299 6396",
    "sg:postcode":"77566",
    "sg:province":"TX",
    "sg:tags":[
        "body"
    ],
    "wof:name":"A1 Quality Paint & Repair",
    "wof:placetype":"venue"
},
  "geometry": {"coordinates":[-95.426968,29.034293],"type":"Point"}
}