{
  "type": "Feature",
  "properties": {
    "iso:country":"US",
    "sg:address":"16030 Bear Bayou Dr",
    "sg:city":"Channelview",
    "sg:classifiers":[
        {
            "category":"Manufacturing",
            "subcategory":"Metals",
            "type":"Manufacturing & Wholesale Goods"
        }
    ],
    "sg:phone":"+1 281 862 1500",
    "sg:postcode":"77530",
    "sg:province":"TX",
    "sg:tags":[
        "industrial",
        "valve",
        "mfg"
    ],
    "wof:name":"Masoneilan / Dresser",
    "wof:placetype":"venue"
},
  "geometry": {"coordinates":[-95.117828,29.801711],"type":"Point"}
}