{
  "type": "Feature",
  "properties": {
    "iso:country":"US",
    "sg:address":"425 Troup Hwy",
    "sg:city":"Tyler",
    "sg:classifiers":[
        {
            "category":"Personal",
            "subcategory":"Beauty Salon",
            "type":"Services"
        }
    ],
    "sg:phone":"+1 903 597 3614",
    "sg:postcode":"75701",
    "sg:province":"TX",
    "sg:tags":[
        "shop"
    ],
    "wof:name":"Hair Place",
    "wof:placetype":"venue"
},
  "geometry": {"coordinates":[-95.296395,32.325716],"type":"Point"}
}