{
  "type": "Feature",
  "properties": {
    "iso:country":"US",
    "sg:address":"5121 69th St",
    "sg:city":"Lubbock",
    "sg:classifiers":[
        {
            "category":"Insurance",
            "subcategory":"Insurance Agent",
            "type":"Services"
        }
    ],
    "sg:phone":"+1 806 928 9703",
    "sg:postcode":"79424",
    "sg:province":"TX",
    "wof:name":"Universal Benefit Plans",
    "wof:placetype":"venue"
},
  "geometry": {"coordinates":[-101.920827,33.531093],"type":"Point"}
}