{
  "type": "Feature",
  "properties": {
    "iso:country":"US",
    "sg:address":"2400 W Pioneer Pkwy",
    "sg:city":"Arlington",
    "sg:classifiers":[
        {
            "category":"Education",
            "subcategory":"Dance Studio",
            "type":"Public Place"
        },
        {
            "category":"Recreation",
            "type":"Entertainment"
        }
    ],
    "sg:phone":"+1 817 861 6518",
    "sg:postcode":"76013",
    "sg:province":"TX",
    "sg:tags":[
        "instruction",
        "gymnastic"
    ],
    "wof:name":"Dance Centre",
    "wof:placetype":"venue"
},
  "geometry": {"coordinates":[-97.144414,32.709456],"type":"Point"}
}