{
  "type": "Feature",
  "properties": {
    "iso:country":"US",
    "sg:address":"3405 Bridlegate Dr",
    "sg:city":"Arlington",
    "sg:classifiers":[
        {
            "category":"Real Estate",
            "subcategory":"Real Estate Agent",
            "type":"Services"
        }
    ],
    "sg:phone":"+1 817 654 3410",
    "sg:postcode":"76016",
    "sg:province":"TX",
    "wof:name":"Independence Plaza Sarasota",
    "wof:placetype":"venue"
},
  "geometry": {"coordinates":[-97.17065100000001,32.694001],"type":"Point"}
}