{
  "type": "Feature",
  "properties": {
    "iso:country":"US",
    "sg:address":"1204 Red Oak Valley Ct",
    "sg:city":"Austin",
    "sg:classifiers":[
        {
            "category":"Travel",
            "subcategory":"Hotels & Motels",
            "type":"Entertainment"
        }
    ],
    "sg:phone":"+1 713 305 8512",
    "sg:postcode":"78732",
    "sg:province":"TX",
    "sg:website":"www.orionhotels.com",
    "wof:name":"Orion Hotels",
    "wof:placetype":"venue"
},
  "geometry": {"coordinates":[-97.892786,30.349689],"type":"Point"}
}