{
  "type": "Feature",
  "properties": {
    "iso:country":"US",
    "sg:address":"3903 Princeton Park Ct",
    "sg:city":"Houston",
    "sg:classifiers":[
        {
            "category":"Professional",
            "type":"Services"
        }
    ],
    "sg:phone":"+1 281 218 6548",
    "sg:postcode":"77058",
    "sg:province":"TX",
    "sg:tags":[
        "marine",
        "contractor"
    ],
    "wof:name":"Princeton Sovereign Maritime",
    "wof:placetype":"venue"
},
  "geometry": {"coordinates":[-95.09690999999999,29.593462],"type":"Point"}
}