{
  "type": "Feature",
  "properties": {
    "iso:country":"US",
    "sg:address":"3615 W Pioneer Pkwy",
    "sg:city":"Pantego",
    "sg:classifiers":[
        {
            "category":"Insurance",
            "subcategory":"Insurance Agent",
            "type":"Services"
        }
    ],
    "sg:phone":"+1 817 460 3233",
    "sg:postcode":"76013",
    "sg:province":"TX",
    "wof:name":"W J Meek Jr Insurance",
    "wof:placetype":"venue"
},
  "geometry": {"coordinates":[-97.164806,32.713609],"type":"Point"}
}