{
  "type": "Feature",
  "properties": {
    "iso:country":"US",
    "sg:address":"4901 Edgewater Dr",
    "sg:city":"Rowlett",
    "sg:classifiers":[
        {
            "category":"Building & Trades",
            "subcategory":"Construction",
            "type":"Services"
        }
    ],
    "sg:phone":"+1 972 412 5740",
    "sg:postcode":"75088",
    "sg:province":"TX",
    "sg:tags":[
        "contractor"
    ],
    "wof:name":"McDonalds",
    "wof:placetype":"venue"
},
  "geometry": {"coordinates":[-96.549463,32.905609],"type":"Point"}
}