{
  "type": "Feature",
  "properties": {
    "iso:country":"US",
    "sg:address":"192 Grey Thompson Rd",
    "sg:city":"Corsicana",
    "sg:classifiers":[
        {
            "category":"Shopping",
            "subcategory":"Gifts & Souvenirs",
            "type":"Retail Goods"
        }
    ],
    "sg:phone":"+1 903 354 6815",
    "sg:postcode":"75110",
    "sg:province":"TX",
    "wof:name":"Nettas Novelties",
    "wof:placetype":"venue"
},
  "geometry": {"coordinates":[-96.57418699999999,32.16126],"type":"Point"}
}