{
  "type": "Feature",
  "properties": {
    "iso:country":"US",
    "sg:address":"530 W Main St",
    "sg:city":"Brenham",
    "sg:classifiers":[
        {
            "category":"Communications",
            "subcategory":"Radio Station",
            "type":"Services"
        }
    ],
    "sg:phone":"+1 979 836 9411",
    "sg:postcode":"77833",
    "sg:province":"TX",
    "sg:tags":[
        "company",
        "broadcasting"
    ],
    "wof:name":"Fort Bend Broadcasting",
    "wof:placetype":"venue"
},
  "geometry": {"coordinates":[-96.403277,30.166301],"type":"Point"}
}