{
  "type": "Feature",
  "properties": {
    "iso:country":"US",
    "sg:address":"5506 Mount Vernon Ave",
    "sg:city":"Dallas",
    "sg:classifiers":[
        {
            "category":"Professional",
            "type":"Services"
        }
    ],
    "sg:phone":"+1 214 526 8728",
    "sg:postcode":"75205",
    "sg:province":"TX",
    "wof:name":"Benestar Corp",
    "wof:placetype":"venue"
},
  "geometry": {"coordinates":[-96.79377599999999,32.836554],"type":"Point"}
}