{
  "type": "Feature",
  "properties": {
    "iso:country":"US",
    "sg:address":"7319 Coronado Ave",
    "sg:city":"Dallas",
    "sg:classifiers":[
        {
            "category":"Arts & Performance",
            "subcategory":"Theater",
            "type":"Entertainment"
        }
    ],
    "sg:phone":"+1 214 749 4054",
    "sg:postcode":"75214",
    "sg:province":"TX",
    "sg:tags":[
        "group"
    ],
    "wof:name":"Top Spin Adio Vsual Prductions",
    "wof:placetype":"venue"
},
  "geometry": {"coordinates":[-96.732015,32.809098],"type":"Point"}
}