{
  "type": "Feature",
  "properties": {
    "iso:country":"US",
    "sg:address":"16814 Grant Rd",
    "sg:city":"Cypress",
    "sg:classifiers":[
        {
            "category":"Shopping",
            "subcategory":"Computers & Home Electronics",
            "type":"Retail Goods"
        },
        {
            "category":"Wholesale",
            "subcategory":"Computers",
            "type":"Manufacturing & Wholesale Goods"
        }
    ],
    "sg:phone":"+1 281 255 6262",
    "sg:postcode":"77429",
    "sg:province":"TX",
    "sg:tags":[
        "equipment",
        "printer",
        "supply"
    ],
    "wof:name":"Eagan Enterprises Inc",
    "wof:placetype":"venue"
},
  "geometry": {"coordinates":[-95.674741,30.02429],"type":"Point"}
}