{
  "type": "Feature",
  "properties": {
    "iso:country":"US",
    "sg:address":"400 W 7th St",
    "sg:city":"Fort Worth",
    "sg:classifiers":[
        {
            "category":"Professional",
            "subcategory":"Advertising",
            "type":"Services"
        }
    ],
    "sg:phone":"+1 817 390 7884",
    "sg:postcode":"76102",
    "sg:province":"TX",
    "sg:tags":[
        "distribution"
    ],
    "wof:name":"VIP Distribution",
    "wof:placetype":"venue"
},
  "geometry": {"coordinates":[-97.33300699999999,32.751159],"type":"Point"}
}