{
  "type": "Feature",
  "properties": {
    "iso:country":"US",
    "sg:address":"902 Mansfield Webb Rd",
    "sg:city":"Arlington",
    "sg:classifiers":[
        {
            "category":"Freight",
            "type":"Transportation"
        }
    ],
    "sg:phone":"+1 817 473 2666",
    "sg:postcode":"76002",
    "sg:province":"TX",
    "sg:tags":[
        "commercial",
        "storage"
    ],
    "wof:name":"Bufords Self Storage",
    "wof:placetype":"venue"
},
  "geometry": {"coordinates":[-97.09084300000001,32.626679],"type":"Point"}
}