{
  "type": "Feature",
  "properties": {
    "iso:country":"US",
    "sg:address":"4502 Game Creek Blvd",
    "sg:city":"Laredo",
    "sg:classifiers":[
        {
            "category":"Retail",
            "subcategory":"Storage",
            "type":"Services"
        }
    ],
    "sg:phone":"+1 956 791 9300",
    "sg:postcode":"78045",
    "sg:province":"TX",
    "sg:tags":[
        "self",
        "commercial",
        "household"
    ],
    "wof:name":"Aaa Townlake Self Storage",
    "wof:placetype":"venue"
},
  "geometry": {"coordinates":[-99.540099,27.639978],"type":"Point"}
}