{
  "type": "Feature",
  "properties": {
    "iso:country":"US",
    "sg:address":"6629 Meadowbrook Dr",
    "sg:city":"Fort Worth",
    "sg:classifiers":[
        {
            "category":"Personal",
            "subcategory":"Beauty Salon",
            "type":"Services"
        }
    ],
    "sg:phone":"+1 817 492 9240",
    "sg:postcode":"76112",
    "sg:province":"TX",
    "wof:name":"Margarita Pedraza",
    "wof:placetype":"venue"
},
  "geometry": {"coordinates":[-97.215279,32.746172],"type":"Point"}
}