{
  "type": "Feature",
  "properties": {
    "iso:country":"US",
    "sg:address":"715 Ave H E",
    "sg:city":"Arlington",
    "sg:classifiers":[
        {
            "category":"Manufacturing",
            "subcategory":"Tools & Machinery",
            "type":"Manufacturing & Wholesale Goods"
        }
    ],
    "sg:phone":"+1 817 633 3063",
    "sg:postcode":"76011",
    "sg:province":"TX",
    "sg:tags":[
        "equipment",
        "support"
    ],
    "wof:name":"Scarlet Industrial Eqp LLC",
    "wof:placetype":"venue"
},
  "geometry": {"coordinates":[-97.056876,32.761781],"type":"Point"}
}