{
  "type": "Feature",
  "properties": {
    "iso:country":"US",
    "sg:address":"1604 Forest Trl",
    "sg:city":"Austin",
    "sg:classifiers":[
        {
            "category":"Professional",
            "subcategory":"Computer Services",
            "type":"Services"
        }
    ],
    "sg:phone":"+1 512 472 0543",
    "sg:postcode":"78703",
    "sg:province":"TX",
    "sg:tags":[
        "prepackaged",
        "software"
    ],
    "wof:name":"Strategic Database Systems",
    "wof:placetype":"venue"
},
  "geometry": {"coordinates":[-97.765508,30.289096],"type":"Point"}
}