{
  "type": "Feature",
  "properties": {
    "iso:country":"US",
    "sg:address":"2885 Greenhaven Dr",
    "sg:city":"Brownsville",
    "sg:classifiers":[
        {
            "category":"Professional",
            "subcategory":"Management & Consulting",
            "type":"Services"
        }
    ],
    "sg:phone":"+1 956 592 5179",
    "sg:postcode":"78521",
    "sg:province":"TX",
    "sg:tags":[
        "packaging",
        "consultant"
    ],
    "wof:name":"Interntional Perfect Packg LLC",
    "wof:placetype":"venue"
},
  "geometry": {"coordinates":[-97.474448,25.942233],"type":"Point"}
}