{
  "type": "Feature",
  "properties": {
    "iso:country":"US",
    "sg:address":"1036 Choke Cherry Ln",
    "sg:city":"Crowley",
    "sg:classifiers":[
        {
            "category":"Freight",
            "type":"Transportation"
        }
    ],
    "sg:phone":"+1 817 295 1822",
    "sg:postcode":"76036",
    "sg:province":"TX",
    "sg:tags":[
        "distance",
        "local",
        "long",
        "trucking"
    ],
    "wof:name":"G Adjmul Services",
    "wof:placetype":"venue"
},
  "geometry": {"coordinates":[-97.351401,32.560444],"type":"Point"}
}