{
  "type": "Feature",
  "properties": {
    "iso:country":"US",
    "sg:address":"1811 E Irving Blvd",
    "sg:city":"Irving",
    "sg:classifiers":[
        {
            "category":"Retail",
            "subcategory":"Auto Repair",
            "type":"Services"
        }
    ],
    "sg:phone":"+1 972 438 8118",
    "sg:postcode":"75060",
    "sg:province":"TX",
    "sg:tags":[
        "body",
        "shop",
        "painting",
        "automobile"
    ],
    "wof:name":"A Imports Toyota",
    "wof:placetype":"venue"
},
  "geometry": {"coordinates":[-96.921204,32.806702],"type":"Point"}
}