{
  "type": "Feature",
  "properties": {
    "iso:country":"US",
    "sg:address":"1800 Bering Dr",
    "sg:city":"Houston",
    "sg:classifiers":[
        {
            "category":"Manufacturing",
            "subcategory":"Electronics",
            "type":"Manufacturing & Wholesale Goods"
        }
    ],
    "sg:phone":"+1 713 972 9191",
    "sg:postcode":"77057",
    "sg:province":"TX",
    "sg:tags":[
        "devices",
        "mfg"
    ],
    "wof:name":"US Led Ltd",
    "wof:placetype":"venue"
},
  "geometry": {"coordinates":[-95.479581,29.747051],"type":"Point"}
}