{
  "type": "Feature",
  "properties": {
    "iso:country":"US",
    "sg:address":"19838 Hwy 6",
    "sg:city":"Manvel",
    "sg:classifiers":[
        {
            "category":"Food & Beverages",
            "subcategory":"Liquor & Beverages",
            "type":"Retail Goods"
        }
    ],
    "sg:phone":"+1 281 331 3469",
    "sg:postcode":"77578",
    "sg:province":"TX",
    "wof:name":"White's Liquor Store",
    "wof:placetype":"venue"
},
  "geometry": {"coordinates":[-95.358896,29.468069],"type":"Point"}
}