{
  "type": "Feature",
  "properties": {
    "iso:country":"US",
    "sg:address":"2445 W Northwest Hwy",
    "sg:city":"Dallas",
    "sg:classifiers":[
        {
            "category":"Restaurant",
            "type":"Food & Drink"
        }
    ],
    "sg:menulink":"http://www.allmenus.com/tx/northeast/130627-subway/menu/",
    "sg:phone":"+1 214 902 8508",
    "sg:postcode":"75220",
    "sg:province":"TX",
    "sg:tags":[
        "american",
        "sandwich"
    ],
    "wof:name":"Subway",
    "wof:placetype":"venue"
},
  "geometry": {"coordinates":[-96.88216199999999,32.860717],"type":"Point"}
}