{
  "type": "Feature",
  "properties": {
    "iso:country":"US",
    "sg:address":"3905 Chisholm Trl",
    "sg:city":"Temple",
    "sg:classifiers":[
        {
            "category":"Professional",
            "type":"Services"
        }
    ],
    "sg:phone":"+1 254 773 3091",
    "sg:postcode":"76504",
    "sg:province":"TX",
    "wof:name":"D&D Service",
    "wof:placetype":"venue"
},
  "geometry": {"coordinates":[-97.383286,31.105113],"type":"Point"}
}