{
  "type": "Feature",
  "properties": {
    "iso:country":"US",
    "sg:address":"112 E Houston St",
    "sg:city":"Cleveland",
    "sg:classifiers":[
        {
            "category":"Building & Trades",
            "subcategory":"Equipment Rental",
            "type":"Services"
        }
    ],
    "sg:phone":"+1 281 592 1425",
    "sg:postcode":"77327",
    "sg:province":"TX",
    "sg:tags":[
        "repair"
    ],
    "wof:name":"Buckley and Sons Plumbing",
    "wof:placetype":"venue"
},
  "geometry": {"coordinates":[-95.08842,30.342369],"type":"Point"}
}