{
  "type": "Feature",
  "properties": {
    "iso:country":"US",
    "sg:address":"2957 S Westmoreland Rd",
    "sg:city":"Dallas",
    "sg:classifiers":[
        {
            "category":"Personal",
            "subcategory":"Beauty Salon",
            "type":"Services"
        }
    ],
    "sg:phone":"+1 214 337 0973",
    "sg:postcode":"75233",
    "sg:province":"TX",
    "wof:name":"Robinson Boutique & Floral",
    "wof:placetype":"venue"
},
  "geometry": {"coordinates":[-96.874168,32.712092],"type":"Point"}
}