{
  "type": "Feature",
  "properties": {
    "iso:country":"US",
    "sg:address":"2617 Creek Crossing Rd",
    "sg:city":"Mesquite",
    "sg:classifiers":[
        {
            "category":"Wholesale",
            "subcategory":"Non-durable Goods",
            "type":"Manufacturing & Wholesale Goods"
        }
    ],
    "sg:phone":"+1 972 222 7234",
    "sg:postcode":"75181",
    "sg:province":"TX",
    "wof:name":"Golbat International",
    "wof:placetype":"venue"
},
  "geometry": {"coordinates":[-96.5578,32.747251],"type":"Point"}
}