{
  "type": "Feature",
  "properties": {
    "iso:country":"US",
    "sg:address":"555 1st St",
    "sg:city":"Groveton",
    "sg:classifiers":[
        {
            "category":"Food & Beverages",
            "subcategory":"Groceries & Convenience Stores",
            "type":"Retail Goods"
        }
    ],
    "sg:phone":"+1 936 642 0286",
    "sg:postcode":"75845",
    "sg:province":"TX",
    "wof:name":"May Grocery & Gas",
    "wof:placetype":"venue"
},
  "geometry": {"coordinates":[-95.134794,31.059259],"type":"Point"}
}