{
  "type": "Feature",
  "properties": {
    "iso:country":"US",
    "sg:address":"10400 Westoffice Dr",
    "sg:city":"Houston",
    "sg:classifiers":[
        {
            "category":"Manufacturing",
            "subcategory":"Tools & Machinery",
            "type":"Manufacturing & Wholesale Goods"
        }
    ],
    "sg:phone":"+1 713 334 3114",
    "sg:postcode":"77042",
    "sg:province":"TX",
    "sg:tags":[
        "equipment",
        "electric"
    ],
    "sg:website":"www.micable.com",
    "wof:name":"M I Cable Co",
    "wof:placetype":"venue"
},
  "geometry": {"coordinates":[-95.550766,29.72062],"type":"Point"}
}