{
  "type": "Feature",
  "properties": {
    "iso:country":"US",
    "sg:address":"125 Keeny Ct",
    "sg:city":"El Paso",
    "sg:classifiers":[
        {
            "category":"Restaurant",
            "type":"Food & Drink"
        }
    ],
    "sg:menulink":"http://www.allmenus.com/tx/el-paso/94346-dominos-pizza/menu/",
    "sg:phone":"+1 915 852 8877",
    "sg:postcode":"79907",
    "sg:province":"TX",
    "sg:tags":[
        "american",
        "wing",
        "pizza"
    ],
    "wof:name":"Domino's Pizza",
    "wof:placetype":"venue"
},
  "geometry": {"coordinates":[-106.350352,31.716865],"type":"Point"}
}