{
  "type": "Feature",
  "properties": {
    "iso:country":"US",
    "sg:address":"8403 Colt Cir",
    "sg:city":"Orange",
    "sg:classifiers":[
        {
            "category":"Professional",
            "type":"Services"
        }
    ],
    "sg:phone":"+1 409 883 3137",
    "sg:postcode":"77632",
    "sg:province":"TX",
    "wof:name":"Msps Inc",
    "wof:placetype":"venue"
},
  "geometry": {"coordinates":[-93.797222,30.186418],"type":"Point"}
}