{
  "type": "Feature",
  "properties": {
    "iso:country":"US",
    "sg:address":"2230 1st St",
    "sg:city":"Rosenberg",
    "sg:classifiers":[
        {
            "category":"Real Estate",
            "subcategory":"Real Estate Operator",
            "type":"Services"
        }
    ],
    "sg:phone":"+1 979 543 2169",
    "sg:postcode":"77471",
    "sg:province":"TX",
    "sg:tags":[
        "mobile",
        "home",
        "site"
    ],
    "wof:name":"Country Aire Mobile Home",
    "wof:placetype":"venue"
},
  "geometry": {"coordinates":[-95.808662,29.545995],"type":"Point"}
}