{
  "type": "Feature",
  "properties": {
    "iso:country":"US",
    "sg:address":"730 Hillside Dr",
    "sg:city":"Grand Prairie",
    "sg:classifiers":[
        {
            "category":"Building & Trades",
            "subcategory":"Landscaping Services",
            "type":"Services"
        }
    ],
    "sg:phone":"+1 972 264 4815",
    "sg:postcode":"75051",
    "sg:province":"TX",
    "sg:tags":[
        "landscape",
        "contractor"
    ],
    "wof:name":"Shannon's Landscaping",
    "wof:placetype":"venue"
},
  "geometry": {"coordinates":[-96.996774,32.730226],"type":"Point"}
}