{
  "type": "Feature",
  "properties": {
    "iso:country":"US",
    "sg:address":"1104 W 34th St",
    "sg:city":"Austin",
    "sg:classifiers":[
        {
            "category":"Restaurant",
            "type":"Food & Drink"
        }
    ],
    "sg:menulink":"http://www.allmenus.com/tx/austin/53512-delaware-sub-shop/menu/",
    "sg:phone":"+1 512 458 8423",
    "sg:postcode":"78705",
    "sg:province":"TX",
    "sg:tags":[
        "wrap",
        "american",
        "sandwich"
    ],
    "wof:name":"Delaware Sub Shop",
    "wof:placetype":"venue"
},
  "geometry": {"coordinates":[-97.745921,30.303259],"type":"Point"}
}