{
  "type": "Feature",
  "properties": {
    "iso:country":"US",
    "sg:address":"1214 N Creek Cir",
    "sg:city":"Waxahachie",
    "sg:classifiers":[
        {
            "category":"Building & Trades",
            "subcategory":"Construction",
            "type":"Services"
        }
    ],
    "sg:phone":"+1 972 938 9997",
    "sg:postcode":"75165",
    "sg:province":"TX",
    "sg:tags":[
        "home",
        "builder"
    ],
    "wof:name":"Bentwood Custom Homes Inc",
    "wof:placetype":"venue"
},
  "geometry": {"coordinates":[-96.81407799999999,32.469304],"type":"Point"}
}