{
  "type": "Feature",
  "properties": {
    "iso:country":"US",
    "sg:address":"4903 Jessamine St",
    "sg:city":"Bellaire",
    "sg:classifiers":[
        {
            "category":"Professional",
            "subcategory":"Accounting & Tax Preparation",
            "type":"Services"
        }
    ],
    "sg:phone":"+1 713 662 0707",
    "sg:postcode":"77401",
    "sg:province":"TX",
    "wof:name":"Lois C Furman CPA",
    "wof:placetype":"venue"
},
  "geometry": {"coordinates":[-95.465628,29.701977],"type":"Point"}
}