{
  "type": "Feature",
  "properties": {
    "iso:country":"US",
    "sg:address":"2401 Mobile Ave",
    "sg:city":"Mcallen",
    "sg:classifiers":[
        {
            "category":"Taxi",
            "type":"Transportation"
        }
    ],
    "sg:phone":"+1 956 682 7034",
    "sg:postcode":"78501",
    "sg:province":"TX",
    "sg:tags":[
        "taxicab"
    ],
    "wof:name":"Airport Taxi",
    "wof:placetype":"venue"
},
  "geometry": {"coordinates":[-98.248204,26.194208],"type":"Point"}
}