{
  "type": "Feature",
  "properties": {
    "iso:country":"US",
    "sg:address":"21705 Long Hill Dr",
    "sg:city":"Leander",
    "sg:classifiers":[
        {
            "category":"Shopping",
            "subcategory":"Computers & Home Electronics",
            "type":"Retail Goods"
        }
    ],
    "sg:phone":"+1 512 267 3126",
    "sg:postcode":"78641",
    "sg:province":"TX",
    "sg:tags":[
        "software"
    ],
    "wof:name":"Futuristic Digital Networks",
    "wof:placetype":"venue"
},
  "geometry": {"coordinates":[-97.958045,30.529388],"type":"Point"}
}