{
  "type": "Feature",
  "properties": {
    "iso:country":"US",
    "sg:address":"479 Westpark Way",
    "sg:city":"Euless",
    "sg:classifiers":[
        {
            "category":"Professional",
            "type":"Services"
        }
    ],
    "sg:phone":"+1 817 545 6624",
    "sg:postcode":"76040",
    "sg:province":"TX",
    "sg:tags":[
        "establishment"
    ],
    "wof:name":"Net",
    "wof:placetype":"venue"
},
  "geometry": {"coordinates":[-97.119788,32.832474],"type":"Point"}
}