{
  "type": "Feature",
  "properties": {
    "iso:country":"US",
    "sg:address":"7950 Wilcox Ln",
    "sg:city":"Beaumont",
    "sg:classifiers":[
        {
            "category":"Insurance",
            "subcategory":"Insurance Agent",
            "type":"Services"
        }
    ],
    "sg:phone":"+1 409 860 1944",
    "sg:postcode":"77706",
    "sg:province":"TX",
    "sg:tags":[
        "accident"
    ],
    "wof:name":"Affordable Health Insurance",
    "wof:placetype":"venue"
},
  "geometry": {"coordinates":[-94.184904,30.097003],"type":"Point"}
}