{
  "type": "Feature",
  "properties": {
    "iso:country":"US",
    "sg:address":"6532 Dover Ter S",
    "sg:city":"Fort Worth",
    "sg:classifiers":[
        {
            "category":"Professional",
            "subcategory":"Business Services",
            "type":"Services"
        }
    ],
    "sg:phone":"+1 817 346 0361",
    "sg:postcode":"76132",
    "sg:province":"TX",
    "wof:name":"D & B Sales",
    "wof:placetype":"venue"
},
  "geometry": {"coordinates":[-97.432131,32.652299],"type":"Point"}
}