{
  "type": "Feature",
  "properties": {
    "iso:country":"US",
    "sg:address":"3806 Bus Park Dr",
    "sg:city":"Amarillo",
    "sg:classifiers":[
        {
            "category":"Recreation",
            "type":"Entertainment"
        }
    ],
    "sg:phone":"+1 806 467 2237",
    "sg:postcode":"79110",
    "sg:province":"TX",
    "sg:tags":[
        "amusement"
    ],
    "wof:name":"Amarillo Cheer Elite",
    "wof:placetype":"venue"
},
  "geometry": {"coordinates":[-101.882257,35.143975],"type":"Point"}
}