{
  "type": "Feature",
  "properties": {
    "iso:country":"US",
    "sg:address":"411 W 1st Ave",
    "sg:city":"Corsicana",
    "sg:classifiers":[
        {
            "category":"Professional",
            "subcategory":"Lawyer & Legal Services",
            "type":"Services"
        }
    ],
    "sg:phone":"+1 903 872 3024",
    "sg:postcode":"75110",
    "sg:province":"TX",
    "sg:tags":[
        "attorney"
    ],
    "wof:name":"Robert C Dunn & Assoc",
    "wof:placetype":"venue"
},
  "geometry": {"coordinates":[-96.47007600000001,32.09635],"type":"Point"}
}