{
  "type": "Feature",
  "properties": {
    "iso:country":"US",
    "sg:address":"4200 Montrose Blvd",
    "sg:city":"Houston",
    "sg:classifiers":[
        {
            "category":"Real Estate",
            "subcategory":"Architect",
            "type":"Services"
        }
    ],
    "sg:phone":"+1 713 529 2921",
    "sg:postcode":"77006",
    "sg:province":"TX",
    "wof:name":"Luhn Graham B Faia",
    "wof:placetype":"venue"
},
  "geometry": {"coordinates":[-95.39112900000001,29.734475],"type":"Point"}
}