{
  "type": "Feature",
  "properties": {
    "iso:country":"US",
    "sg:address":"3201 Military Pkwy",
    "sg:city":"Mesquite",
    "sg:classifiers":[
        {
            "category":"Wholesale",
            "subcategory":"Hardware",
            "type":"Manufacturing & Wholesale Goods"
        }
    ],
    "sg:phone":"+1 214 388 9647",
    "sg:postcode":"75149",
    "sg:province":"TX",
    "sg:tags":[
        "fastener"
    ],
    "wof:name":"Fastenal Co",
    "wof:placetype":"venue"
},
  "geometry": {"coordinates":[-96.646717,32.76831],"type":"Point"}
}