{
  "type": "Feature",
  "properties": {
    "iso:country":"US",
    "sg:address":"1822 Holly Rd",
    "sg:city":"Corpus Christi",
    "sg:classifiers":[
        {
            "category":"Retail",
            "subcategory":"Repair Shop",
            "type":"Services"
        }
    ],
    "sg:phone":"+1 361 814 9294",
    "sg:postcode":"78417",
    "sg:province":"TX",
    "sg:tags":[
        "water",
        "pressure",
        "cleaning"
    ],
    "wof:name":"American Rekrete-South Texas",
    "wof:placetype":"venue"
},
  "geometry": {"coordinates":[-97.441012,27.730145],"type":"Point"}
}