{
  "type": "Feature",
  "properties": {
    "iso:country":"US",
    "sg:address":"4700 Bosque Blvd",
    "sg:city":"Waco",
    "sg:classifiers":[
        {
            "category":"Building & Trades",
            "subcategory":"Electrical",
            "type":"Services"
        }
    ],
    "sg:phone":"+1 254 715 2873",
    "sg:postcode":"76710",
    "sg:province":"TX",
    "sg:tags":[
        "electrical",
        "contractor"
    ],
    "wof:name":"Advanctek Lighting LLC",
    "wof:placetype":"venue"
},
  "geometry": {"coordinates":[-97.18594,31.53659],"type":"Point"}
}