{
  "type": "Feature",
  "properties": {
    "iso:country":"US",
    "sg:address":"780 Rd To Six Flags W",
    "sg:city":"Arlington",
    "sg:classifiers":[
        {
            "category":"Restaurant",
            "type":"Food & Drink"
        }
    ],
    "sg:phone":"+1 817 277 3363",
    "sg:postcode":"76012",
    "sg:province":"TX",
    "sg:tags":[
        "parlor",
        "ice",
        "cream"
    ],
    "wof:name":"Marble Slab Creamery",
    "wof:placetype":"venue"
},
  "geometry": {"coordinates":[-97.114754,32.757531],"type":"Point"}
}