{
  "type": "Feature",
  "properties": {
    "iso:country":"US",
    "sg:address":"3209 Summerfield Dr",
    "sg:city":"Richardson",
    "sg:classifiers":[
        {
            "category":"Professional",
            "subcategory":"Computer Services",
            "type":"Services"
        }
    ],
    "sg:phone":"+1 972 671 4778",
    "sg:postcode":"75082",
    "sg:province":"TX",
    "sg:tags":[
        "prepackaged",
        "software"
    ],
    "wof:name":"General Software Consultants",
    "wof:placetype":"venue"
},
  "geometry": {"coordinates":[-96.64501300000001,32.993161],"type":"Point"}
}