{
  "type": "Feature",
  "properties": {
    "iso:country":"US",
    "sg:address":"1900 W Division St",
    "sg:city":"Slaton",
    "sg:classifiers":[
        {
            "category":"Fast Food",
            "type":"Food & Drink"
        },
        {
            "category":"Restaurant",
            "type":"Food & Drink"
        }
    ],
    "sg:phone":"+1 806 828 6435",
    "sg:postcode":"79364",
    "sg:province":"TX",
    "sg:tags":[
        "style",
        "hamburger",
        "family",
        "dog",
        "hot",
        "american"
    ],
    "sg:website":"http://www.sonicdrivein.com",
    "wof:name":"Sonic Drive-In",
    "wof:placetype":"venue"
},
  "geometry": {"coordinates":[-101.665909,33.43391],"type":"Point"}
}