{
  "type": "Feature",
  "properties": {
    "iso:country":"US",
    "sg:address":"3220 Broadway St",
    "sg:city":"Houston",
    "sg:classifiers":[
        {
            "category":"Shopping",
            "subcategory":"Music",
            "type":"Retail Goods"
        }
    ],
    "sg:phone":"+1 713 643 6737",
    "sg:postcode":"77017",
    "sg:province":"TX",
    "wof:name":"Puro Latino Records",
    "wof:placetype":"venue"
},
  "geometry": {"coordinates":[-95.27776,29.693782],"type":"Point"}
}