{
  "type": "Feature",
  "properties": {
    "iso:country":"US",
    "sg:address":"608 E University Ave",
    "sg:city":"Georgetown",
    "sg:classifiers":[
        {
            "category":"Shopping",
            "subcategory":"Florist",
            "type":"Retail Goods"
        }
    ],
    "sg:phone":"+1 512 863 2542",
    "sg:postcode":"78626",
    "sg:province":"TX",
    "wof:name":"Flower Nook Inc",
    "wof:placetype":"venue"
},
  "geometry": {"coordinates":[-97.671774,30.633231],"type":"Point"}
}