{
  "type": "Feature",
  "properties": {
    "iso:country":"US",
    "sg:address":"8801 Ravenswood Rd",
    "sg:city":"Granbury",
    "sg:classifiers":[
        {
            "category":"Real Estate",
            "subcategory":"Real Estate Services",
            "type":"Services"
        }
    ],
    "sg:phone":"+1 817 573 5624",
    "sg:postcode":"76049",
    "sg:province":"TX",
    "sg:tags":[
        "loan"
    ],
    "wof:name":"Phartz Phamily Enterprise",
    "wof:placetype":"venue"
},
  "geometry": {"coordinates":[-97.607156,32.351552],"type":"Point"}
}