{
  "type": "Feature",
  "properties": {
    "iso:country":"US",
    "sg:address":"1304 E Main St",
    "sg:city":"Madisonville",
    "sg:classifiers":[
        {
            "category":"Health Services",
            "subcategory":"Dentist",
            "type":"Services"
        }
    ],
    "sg:phone":"+1 936 348 5252",
    "sg:postcode":"77864",
    "sg:province":"TX",
    "wof:name":"Robert C Dorris Dds",
    "wof:placetype":"venue"
},
  "geometry": {"coordinates":[-95.901196,30.954281],"type":"Point"}
}