{
  "type": "Feature",
  "properties": {
    "iso:country":"US",
    "sg:address":"107 S Main St",
    "sg:city":"Cedar Hill",
    "sg:classifiers":[
        {
            "category":"Restaurant",
            "type":"Food & Drink"
        }
    ],
    "sg:phone":"+1 972 293 3303",
    "sg:postcode":"75104",
    "sg:province":"TX",
    "sg:tags":[
        "barbeque"
    ],
    "wof:name":"Christopher's Smokehouse Barbeque",
    "wof:placetype":"venue"
},
  "geometry": {"coordinates":[-96.955359,32.589763],"type":"Point"}
}