{
  "type": "Feature",
  "properties": {
    "iso:country":"US",
    "sg:address":"3603 Cedar Gardens Dr",
    "sg:city":"Houston",
    "sg:classifiers":[
        {
            "category":"Travel",
            "subcategory":"Travel Agent",
            "type":"Entertainment"
        }
    ],
    "sg:phone":"+1 713 752 9303",
    "sg:postcode":"77082",
    "sg:province":"TX",
    "sg:tags":[
        "agency"
    ],
    "wof:name":"Viajes Y Mas",
    "wof:placetype":"venue"
},
  "geometry": {"coordinates":[-95.65708100000001,29.715814],"type":"Point"}
}