{
  "type": "Feature",
  "properties": {
    "iso:country":"US",
    "sg:address":"4410 Burnet Rd Suite B",
    "sg:city":"Austin",
    "sg:classifiers":[
        {
            "category":"Shopping",
            "subcategory":"Clothing, Apparel, & Fashions",
            "type":"Retail Goods"
        }
    ],
    "sg:phone":"+1 512 826 2085",
    "sg:postcode":"78756",
    "sg:province":"TX",
    "sg:tags":[
        "apparel",
        "clothing",
        "store",
        "women's"
    ],
    "sg:website":"http://www.wardrobemd.com",
    "wof:name":"Wardrobe MD - Miranda Darr",
    "wof:placetype":"venue"
},
  "geometry": {"coordinates":[-97.741957,30.314715],"type":"Point"}
}