{
  "type": "Feature",
  "properties": {
    "iso:country":"US",
    "sg:address":"5741 Emerson Dr",
    "sg:city":"Fort Worth",
    "sg:classifiers":[
        {
            "category":"Social Services",
            "subcategory":"Child Care",
            "type":"Services"
        }
    ],
    "sg:phone":"+1 817 581 6115",
    "sg:postcode":"76148",
    "sg:province":"TX",
    "wof:name":"Dawn Taylor",
    "wof:placetype":"venue"
},
  "geometry": {"coordinates":[-97.258742,32.854479],"type":"Point"}
}