{
  "type": "Feature",
  "properties": {
    "iso:country":"US",
    "sg:address":"2029 S Bridge St",
    "sg:city":"Brady",
    "sg:classifiers":[
        {
            "category":"Health Services",
            "subcategory":"Nursing And Care Facility",
            "type":"Services"
        }
    ],
    "sg:phone":"+1 325 597 2947",
    "sg:postcode":"76825",
    "sg:province":"TX",
    "sg:tags":[
        "home",
        "convalescent"
    ],
    "wof:name":"Shuffield Nursing Homes II",
    "wof:placetype":"venue"
},
  "geometry": {"coordinates":[-99.335696,31.115241],"type":"Point"}
}