{
  "type": "Feature",
  "properties": {
    "iso:country":"US",
    "sg:address":"478 W Richland St",
    "sg:city":"Lewisville",
    "sg:classifiers":[
        {
            "category":"Professional",
            "subcategory":"Business Services",
            "type":"Services"
        }
    ],
    "sg:phone":"+1 972 221 8283",
    "sg:postcode":"75057",
    "sg:province":"TX",
    "wof:name":"Studio On Richland Street",
    "wof:placetype":"venue"
},
  "geometry": {"coordinates":[-97.00363400000001,33.04762],"type":"Point"}
}