{
  "type": "Feature",
  "properties": {
    "iso:country":"US",
    "sg:address":"5104 Lawndale Ave",
    "sg:city":"Orange",
    "sg:classifiers":[
        {
            "category":"Building & Trades",
            "subcategory":"Landscaping Services",
            "type":"Services"
        }
    ],
    "sg:phone":"+1 409 886 1146",
    "sg:postcode":"77630",
    "sg:province":"TX",
    "sg:tags":[
        "lawn",
        "maintenance",
        "grounds"
    ],
    "wof:name":"Discount Lawn Svc",
    "wof:placetype":"venue"
},
  "geometry": {"coordinates":[-93.78496199999999,30.084313],"type":"Point"}
}