{
  "type": "Feature",
  "properties": {
    "iso:country":"US",
    "sg:address":"922 San Pedro Ave",
    "sg:city":"San Antonio",
    "sg:classifiers":[
        {
            "category":"Social Services",
            "type":"Services"
        }
    ],
    "sg:phone":"+1 210 228 0201",
    "sg:postcode":"78212",
    "sg:province":"TX",
    "wof:name":"Esperanza Peace & Justice Ctr",
    "wof:placetype":"venue"
},
  "geometry": {"coordinates":[-98.499234,29.442576],"type":"Point"}
}