{
  "type": "Feature",
  "properties": {
    "iso:country":"US",
    "sg:address":"3011 W Michigan Ave",
    "sg:city":"Midland",
    "sg:classifiers":[
        {
            "category":"Professional",
            "subcategory":"Computer Services",
            "type":"Services"
        }
    ],
    "sg:phone":"+1 432 262 3735",
    "sg:postcode":"79701",
    "sg:province":"TX",
    "wof:name":"Dave's Computer Creations",
    "wof:placetype":"venue"
},
  "geometry": {"coordinates":[-102.10991,31.995756],"type":"Point"}
}