{
  "type": "Feature",
  "properties": {
    "iso:country":"US",
    "sg:address":"30500 I- 10 W",
    "sg:city":"Boerne",
    "sg:classifiers":[
        {
            "category":"Autos & Motor Vehicles",
            "subcategory":"Automobile Sales",
            "type":"Retail Goods"
        }
    ],
    "sg:phone":"+1 830 755 8260",
    "sg:postcode":"78006",
    "sg:province":"TX",
    "sg:tags":[
        "car",
        "dealer"
    ],
    "sg:website":"www.ancira.com",
    "wof:name":"Ancira GMC Truck",
    "wof:placetype":"venue"
},
  "geometry": {"coordinates":[-98.690113,29.740745],"type":"Point"}
}