{
  "type": "Feature",
  "properties": {
    "iso:country":"US",
    "sg:address":"4026 Summerhill Rd",
    "sg:city":"Texarkana",
    "sg:classifiers":[
        {
            "category":"Shopping",
            "subcategory":"Computers & Home Electronics",
            "type":"Retail Goods"
        }
    ],
    "sg:phone":"+1 903 792 9157",
    "sg:postcode":"75503",
    "sg:province":"TX",
    "sg:tags":[
        "equipment",
        "satellite",
        "system"
    ],
    "wof:name":"American Wireless",
    "wof:placetype":"venue"
},
  "geometry": {"coordinates":[-94.065325,33.457253],"type":"Point"}
}