{
  "type": "Feature",
  "properties": {
    "iso:country":"US",
    "sg:address":"111 N Glenwood Blvd",
    "sg:city":"Tyler",
    "sg:classifiers":[
        {
            "category":"Wholesale",
            "subcategory":"Machinery & Supplies",
            "type":"Manufacturing & Wholesale Goods"
        }
    ],
    "sg:phone":"+1 903 597 6679",
    "sg:postcode":"75702",
    "sg:province":"TX",
    "sg:tags":[
        "farm",
        "equipment"
    ],
    "wof:name":"Frank's Tractor Parts",
    "wof:placetype":"venue"
},
  "geometry": {"coordinates":[-95.31913299999999,32.351642],"type":"Point"}
}