{
  "type": "Feature",
  "properties": {
    "iso:country":"US",
    "sg:address":"16135 Preston Rd",
    "sg:city":"Dallas",
    "sg:classifiers":[
        {
            "category":"Manufacturing",
            "subcategory":"Glass & Minerals",
            "type":"Manufacturing & Wholesale Goods"
        }
    ],
    "sg:phone":"+1 214 866 0600",
    "sg:postcode":"75248",
    "sg:province":"TX",
    "wof:name":"Paladin Minerals Corp",
    "wof:placetype":"venue"
},
  "geometry": {"coordinates":[-96.804526,32.968733],"type":"Point"}
}