{
  "type": "Feature",
  "properties": {
    "iso:country":"US",
    "sg:address":"2100 Kings Dr",
    "sg:city":"Brookston",
    "sg:classifiers":[
        {
            "category":"Shopping",
            "subcategory":"Musical Instruments",
            "type":"Retail Goods"
        }
    ],
    "sg:phone":"+1 903 784 7820",
    "sg:postcode":"75421",
    "sg:province":"TX",
    "sg:tags":[
        "music",
        "dealer"
    ],
    "wof:name":"Undaground Music & More",
    "wof:placetype":"venue"
},
  "geometry": {"coordinates":[-95.64746599999999,33.654872],"type":"Point"}
}