{
  "type": "Feature",
  "properties": {
    "iso:country":"US",
    "sg:address":"14575 Tamerisk Ln",
    "sg:city":"Dallas",
    "sg:classifiers":[
        {
            "category":"Professional",
            "subcategory":"Management & Consulting",
            "type":"Services"
        }
    ],
    "sg:phone":"+1 972 247 2313",
    "sg:postcode":"75234",
    "sg:province":"TX",
    "sg:tags":[
        "business"
    ],
    "wof:name":"Fireplug Inn",
    "wof:placetype":"venue"
},
  "geometry": {"coordinates":[-96.869539,32.944941],"type":"Point"}
}