{
  "type": "Feature",
  "properties": {
    "iso:country":"US",
    "sg:address":"936 Pebblebrook Dr",
    "sg:city":"Lewisville",
    "sg:classifiers":[
        {
            "category":"Shopping",
            "subcategory":"Hobbies, Toys, & Games",
            "type":"Retail Goods"
        },
        {
            "category":"Recreation",
            "subcategory":"Gun Range",
            "type":"Entertainment"
        }
    ],
    "sg:phone":"+1 972 436 1842",
    "sg:postcode":"75067",
    "sg:province":"TX",
    "sg:tags":[
        "safety",
        "instruction",
        "marksmanship",
        "gunsmith"
    ],
    "wof:name":"Top Gun Firearms Training",
    "wof:placetype":"venue"
},
  "geometry": {"coordinates":[-97.001137,33.032509],"type":"Point"}
}