{
  "type": "Feature",
  "properties": {
    "iso:country":"US",
    "sg:address":"1040 Shady Oaks Dr",
    "sg:city":"Denton",
    "sg:classifiers":[
        {
            "category":"Wholesale",
            "subcategory":"Durable Goods & Equipment",
            "type":"Manufacturing & Wholesale Goods"
        }
    ],
    "sg:phone":"+1 940 483 9348",
    "sg:postcode":"76205",
    "sg:province":"TX",
    "wof:name":"Market Distribution",
    "wof:placetype":"venue"
},
  "geometry": {"coordinates":[-97.12020699999999,33.200155],"type":"Point"}
}