{
  "type": "Feature",
  "properties": {
    "iso:country":"US",
    "sg:address":"403 E Expy 83",
    "sg:city":"San Juan",
    "sg:classifiers":[
        {
            "category":"Home & Garden",
            "subcategory":"Building Materials",
            "type":"Retail Goods"
        }
    ],
    "sg:phone":"+1 956 682 1279",
    "sg:postcode":"78589",
    "sg:province":"TX",
    "sg:tags":[
        "glass",
        "window",
        "plate"
    ],
    "wof:name":"Risica & Sons",
    "wof:placetype":"venue"
},
  "geometry": {"coordinates":[-98.136225,26.193606],"type":"Point"}
}