{
  "type": "Feature",
  "properties": {
    "iso:country":"US",
    "sg:address":"8100 Lomo Alto Dr",
    "sg:city":"Dallas",
    "sg:classifiers":[
        {
            "category":"Health Services",
            "subcategory":"Doctor",
            "type":"Services"
        }
    ],
    "sg:phone":"+1 214 750 0336",
    "sg:postcode":"75225",
    "sg:province":"TX",
    "wof:name":"Tanner Larry S",
    "wof:placetype":"venue"
},
  "geometry": {"coordinates":[-96.81174799999999,32.861334],"type":"Point"}
}