{
  "type": "Feature",
  "properties": {
    "iso:country":"US",
    "sg:address":"4314 Princeton Drive",
    "sg:city":"Garland",
    "sg:classifiers":[
        {
            "category":"Professional",
            "subcategory":"Advertising",
            "type":"Services"
        },
        {
            "category":"Professional",
            "subcategory":"Art Services",
            "type":"Services"
        },
        {
            "category":"Communications",
            "type":"Services"
        }
    ],
    "sg:phone":"+1 214 731 4733",
    "sg:postcode":"75042",
    "sg:province":"TX",
    "sg:tags":[
        "marketing",
        "graphic",
        "design",
        "web"
    ],
    "sg:website":"www.geekartist.com",
    "wof:name":"GeekArtist Web Solutions",
    "wof:placetype":"venue"
},
  "geometry": {"coordinates":[-96.698144,32.918372],"type":"Point"}
}