{
  "type": "Feature",
  "properties": {
    "iso:country":"US",
    "sg:address":"1809 E Front St",
    "sg:city":"Midland",
    "sg:classifiers":[
        {
            "category":"Insurance",
            "subcategory":"Hazard Insurance",
            "type":"Services"
        }
    ],
    "sg:phone":"+1 432 570 4658",
    "sg:postcode":"79701",
    "sg:province":"TX",
    "sg:tags":[
        "bond"
    ],
    "wof:name":"Apache Bail Bonds",
    "wof:placetype":"venue"
},
  "geometry": {"coordinates":[-102.058453,32.003906],"type":"Point"}
}