{
  "type": "Feature",
  "properties": {
    "iso:country":"US",
    "sg:address":"9455 Skillman St",
    "sg:city":"Dallas",
    "sg:classifiers":[
        {
            "category":"Professional",
            "type":"Services"
        }
    ],
    "sg:phone":"+1 972 497 9092",
    "sg:postcode":"75243",
    "sg:province":"TX",
    "sg:tags":[
        "establishment"
    ],
    "wof:name":"H & N Petolam",
    "wof:placetype":"venue"
},
  "geometry": {"coordinates":[-96.71122200000001,32.905786],"type":"Point"}
}