{
  "type": "Feature",
  "properties": {
    "iso:country":"US",
    "sg:address":"2701 S I35 W",
    "sg:city":"Burleson",
    "sg:classifiers":[
        {
            "category":"Restaurant",
            "type":"Food & Drink"
        }
    ],
    "sg:phone":"+1 817 447 1277",
    "sg:postcode":"76028",
    "sg:province":"TX",
    "sg:tags":[
        "seafood"
    ],
    "wof:name":"Martin's Bill & Marty Famous Seafood Restaurant",
    "wof:placetype":"venue"
},
  "geometry": {"coordinates":[-97.273408,32.476569],"type":"Point"}
}