{
  "type": "Feature",
  "properties": {
    "iso:country":"US",
    "sg:address":"10905 Shadow Brook Ln",
    "sg:city":"Frisco",
    "sg:classifiers":[
        {
            "category":"Retail",
            "subcategory":"Portrait Studio",
            "type":"Services"
        }
    ],
    "sg:phone":"+1 469 633 1390",
    "sg:postcode":"75035",
    "sg:province":"TX",
    "sg:tags":[
        "photographer",
        "photographers-portrait",
        "photo"
    ],
    "sg:website":"http://www.iiphoto.com",
    "wof:name":"Impact Images",
    "wof:placetype":"venue"
},
  "geometry": {"coordinates":[-96.784205,33.113882],"type":"Point"}
}