{
  "type": "Feature",
  "properties": {
    "iso:country":"US",
    "sg:address":"5253 S Staples St",
    "sg:city":"Corpus Christi",
    "sg:classifiers":[
        {
            "category":"Education",
            "subcategory":"Special Training",
            "type":"Public Place"
        }
    ],
    "sg:phone":"+1 361 779 0086",
    "sg:postcode":"78411",
    "sg:province":"TX",
    "sg:tags":[
        "instruction",
        "music"
    ],
    "wof:name":"Debbie Dubois Piano Studio",
    "wof:placetype":"venue"
},
  "geometry": {"coordinates":[-97.370908,27.706483],"type":"Point"}
}