{
  "type": "Feature",
  "properties": {
    "iso:country":"US",
    "sg:address":"12400 Coit Rd Ste 800",
    "sg:city":"Dallas",
    "sg:classifiers":[
        {
            "category":"Shopping",
            "subcategory":"Computers & Home Electronics",
            "type":"Retail Goods"
        }
    ],
    "sg:phone":"+1 214 751 8277",
    "sg:postcode":"75251",
    "sg:province":"TX",
    "sg:tags":[
        "dvd",
        "sale"
    ],
    "wof:name":"Movie Tavern",
    "wof:placetype":"venue"
},
  "geometry": {"coordinates":[-96.769155,32.915638],"type":"Point"}
}