{
  "type": "Feature",
  "properties": {
    "iso:country":"US",
    "sg:address":"1040 Big Valley Cir",
    "sg:city":"Lipan",
    "sg:classifiers":[
        {
            "category":"Manufacturing",
            "subcategory":"Leather Goods",
            "type":"Manufacturing & Wholesale Goods"
        }
    ],
    "sg:phone":"+1 817 596 5615",
    "sg:postcode":"76462",
    "sg:province":"TX",
    "sg:tags":[
        "mfg"
    ],
    "wof:name":"Big Valley Trading Co",
    "wof:placetype":"venue"
},
  "geometry": {"coordinates":[-97.91728999999999,32.612854],"type":"Point"}
}