{
  "type": "Feature",
  "properties": {
    "iso:country":"US",
    "sg:address":"15527 Ranch Road 620 N",
    "sg:city":"Austin",
    "sg:classifiers":[
        {
            "category":"Social Services",
            "subcategory":"Adult Care",
            "type":"Services"
        }
    ],
    "sg:phone":"+1 512 244 6689",
    "sg:postcode":"78717",
    "sg:province":"TX",
    "sg:tags":[
        "calibration"
    ],
    "sg:website":"http://www.tescomusa.com",
    "wof:name":"Tescom",
    "wof:placetype":"venue"
},
  "geometry": {"coordinates":[-97.77543300000001,30.473729],"type":"Point"}
}