{
  "type": "Feature",
  "properties": {
    "iso:country":"US",
    "sg:address":"1901 Lakeview Cir",
    "sg:city":"Lewisville",
    "sg:classifiers":[
        {
            "category":"Retail",
            "subcategory":"Portrait Studio",
            "type":"Services"
        }
    ],
    "sg:phone":"+1 972 353 8179",
    "sg:postcode":"75057",
    "sg:province":"TX",
    "sg:tags":[
        "photo"
    ],
    "wof:name":"Nicholas Wright Photography",
    "wof:placetype":"venue"
},
  "geometry": {"coordinates":[-97.00957,33.073808],"type":"Point"}
}