{
  "type": "Feature",
  "properties": {
    "iso:country":"US",
    "sg:address":"4210 Seneca St",
    "sg:city":"Pasadena",
    "sg:classifiers":[
        {
            "category":"Health Services",
            "subcategory":"Chiropractor",
            "type":"Services"
        }
    ],
    "sg:phone":"+1 281 487 2076",
    "sg:postcode":"77504",
    "sg:province":"TX",
    "sg:tags":[
        "chiropractic"
    ],
    "wof:name":"Stephens Chiropractic Cli",
    "wof:placetype":"venue"
},
  "geometry": {"coordinates":[-95.175073,29.646325],"type":"Point"}
}