{
  "type": "Feature",
  "properties": {
    "iso:country":"US",
    "sg:address":"7764 Grassland Dr",
    "sg:city":"Fort Worth",
    "sg:classifiers":[
        {
            "category":"Shopping",
            "subcategory":"Gifts & Souvenirs",
            "type":"Retail Goods"
        }
    ],
    "sg:phone":"+1 817 423 9943",
    "sg:postcode":"76133",
    "sg:province":"TX",
    "wof:name":"Simple Wonders Gifts Shops",
    "wof:placetype":"venue"
},
  "geometry": {"coordinates":[-97.403053,32.63231],"type":"Point"}
}