{
  "type": "Feature",
  "properties": {
    "iso:country":"US",
    "sg:address":"5020 FM 1960 W",
    "sg:city":"Houston",
    "sg:classifiers":[
        {
            "category":"Autos & Motor Vehicles",
            "subcategory":"Motorcycle Sales",
            "type":"Retail Goods"
        }
    ],
    "sg:phone":"+1 281 440 0273",
    "sg:postcode":"77069",
    "sg:province":"TX",
    "wof:name":"Switch Motor Sports",
    "wof:placetype":"venue"
},
  "geometry": {"coordinates":[-95.505263,29.983949],"type":"Point"}
}