{
  "type": "Feature",
  "properties": {
    "iso:country":"US",
    "sg:address":"7609 Bayhill Dr",
    "sg:city":"Rowlett",
    "sg:classifiers":[
        {
            "category":"Shopping",
            "subcategory":"Clothing, Apparel, & Fashions",
            "type":"Retail Goods"
        }
    ],
    "sg:phone":"+1 972 412 9194",
    "sg:postcode":"75088",
    "sg:province":"TX",
    "wof:name":"Five Star Fashions",
    "wof:placetype":"venue"
},
  "geometry": {"coordinates":[-96.529588,32.894649],"type":"Point"}
}