{
  "type": "Feature",
  "properties": {
    "iso:country":"US",
    "sg:address":"2258 Vantage St",
    "sg:city":"Dallas",
    "sg:classifiers":[
        {
            "category":"Shopping",
            "subcategory":"Antiques",
            "type":"Retail Goods"
        }
    ],
    "sg:phone":"+1 214 748 1860",
    "sg:postcode":"75207",
    "sg:province":"TX",
    "wof:name":"Boulevard Emporium the",
    "wof:placetype":"venue"
},
  "geometry": {"coordinates":[-96.834903,32.799848],"type":"Point"}
}