{
  "type": "Feature",
  "properties": {
    "iso:country":"US",
    "sg:address":"4108 Cortina Dr",
    "sg:city":"Austin",
    "sg:classifiers":[
        {
            "category":"Professional",
            "subcategory":"Accounting & Tax Preparation",
            "type":"Services"
        }
    ],
    "sg:phone":"+1 512 280 5800",
    "sg:postcode":"78749",
    "sg:province":"TX",
    "sg:tags":[
        "billing"
    ],
    "wof:name":"JDT Billing Svc",
    "wof:placetype":"venue"
},
  "geometry": {"coordinates":[-97.850415,30.200462],"type":"Point"}
}