{
  "type": "Feature",
  "properties": {
    "iso:country":"US",
    "sg:address":"914 Mayo Shell Rd",
    "sg:city":"Galena Park",
    "sg:classifiers":[
        {
            "category":"Manufacturing",
            "subcategory":"Glass & Minerals",
            "type":"Manufacturing & Wholesale Goods"
        }
    ],
    "sg:phone":"+1 713 674 1997",
    "sg:postcode":"77547",
    "sg:province":"TX",
    "sg:tags":[
        "ready",
        "mix",
        "mfg",
        "concrete"
    ],
    "wof:name":"Campbell Concrete & Mtls LP",
    "wof:placetype":"venue"
},
  "geometry": {"coordinates":[-95.243707,29.725706],"type":"Point"}
}