{
  "type": "Feature",
  "properties": {
    "iso:country":"US",
    "sg:address":"13319 Vis Arroyo",
    "sg:city":"San Antonio",
    "sg:classifiers":[
        {
            "category":"Banks & Credit Unions",
            "subcategory":"Bank",
            "type":"Services"
        }
    ],
    "sg:phone":"+1 210 492 5133",
    "sg:postcode":"78216",
    "sg:province":"TX",
    "sg:tags":[
        "mortgage"
    ],
    "wof:name":"Executive Mortgage Services",
    "wof:placetype":"venue"
},
  "geometry": {"coordinates":[-98.51702400000001,29.566455],"type":"Point"}
}