{
  "type": "Feature",
  "properties": {
    "iso:country":"US",
    "sg:address":"5506 Loop 306 S",
    "sg:city":"San Angelo",
    "sg:classifiers":[
        {
            "category":"Manufacturing",
            "subcategory":"Tools & Machinery",
            "type":"Manufacturing & Wholesale Goods"
        }
    ],
    "sg:phone":"+1 325 651 8250",
    "sg:postcode":"76905",
    "sg:province":"TX",
    "sg:tags":[
        "machine",
        "making",
        "ice",
        "equipment"
    ],
    "wof:name":"Angelo Restaurant Equipment",
    "wof:placetype":"venue"
},
  "geometry": {"coordinates":[-100.373778,31.40084],"type":"Point"}
}