{
  "type": "Feature",
  "properties": {
    "iso:country":"US",
    "sg:address":"2024 Quail Creek Rd",
    "sg:city":"Laredo",
    "sg:classifiers":[
        {
            "category":"Real Estate",
            "subcategory":"Real Estate Operator",
            "type":"Services"
        }
    ],
    "sg:phone":"+1 956 717 3447",
    "sg:postcode":"78045",
    "sg:province":"TX",
    "sg:tags":[
        "apartment"
    ],
    "wof:name":"Quail Creek Apartments",
    "wof:placetype":"venue"
},
  "geometry": {"coordinates":[-99.516156,27.586929],"type":"Point"}
}