{
  "type": "Feature",
  "properties": {
    "iso:country":"US",
    "sg:address":"8400 Marbach Rd",
    "sg:city":"San Antonio",
    "sg:classifiers":[
        {
            "category":"Shopping",
            "subcategory":"Musical Instruments",
            "type":"Retail Goods"
        }
    ],
    "sg:phone":"+1 210 645 9981",
    "sg:postcode":"78227",
    "sg:province":"TX",
    "sg:tags":[
        "music",
        "dealer"
    ],
    "wof:name":"Que Onda Music",
    "wof:placetype":"venue"
},
  "geometry": {"coordinates":[-98.655513,29.417767],"type":"Point"}
}