{
  "type": "Feature",
  "properties": {
    "iso:country":"US",
    "sg:address":"5629 FM 1960 W",
    "sg:city":"Houston",
    "sg:classifiers":[
        {
            "category":"Banks & Credit Unions",
            "subcategory":"Investment Brokerage",
            "type":"Services"
        }
    ],
    "sg:phone":"+1 281 880 9955",
    "sg:postcode":"77069",
    "sg:province":"TX",
    "sg:tags":[
        "consultant",
        "planning",
        "financial"
    ],
    "wof:name":"Lincoln Financial Advisors",
    "wof:placetype":"venue"
},
  "geometry": {"coordinates":[-95.510127,29.981264],"type":"Point"}
}