{
  "type": "Feature",
  "properties": {
    "iso:country":"US",
    "sg:address":"2330 Everglades Rd",
    "sg:city":"Brownsville",
    "sg:classifiers":[
        {
            "category":"Recreation",
            "type":"Entertainment"
        }
    ],
    "sg:phone":"+1 956 838 1293",
    "sg:postcode":"78521",
    "sg:province":"TX",
    "wof:name":"Faga Corp",
    "wof:placetype":"venue"
},
  "geometry": {"coordinates":[-97.34058400000001,25.980724],"type":"Point"}
}