{
  "type": "Feature",
  "properties": {
    "iso:country":"US",
    "sg:address":"5206 Air Force Dr",
    "sg:city":"Wichita Falls",
    "sg:classifiers":[
        {
            "category":"Professional",
            "subcategory":"Computer Services",
            "type":"Services"
        }
    ],
    "sg:phone":"+1 940 851 9024",
    "sg:postcode":"76306",
    "sg:province":"TX",
    "sg:tags":[
        "related"
    ],
    "wof:name":"Secure Memories",
    "wof:placetype":"venue"
},
  "geometry": {"coordinates":[-98.533783,33.979397],"type":"Point"}
}