{
  "type": "Feature",
  "properties": {
    "iso:country":"US",
    "sg:address":"7944 Roundrock Rd",
    "sg:city":"Dallas",
    "sg:classifiers":[
        {
            "category":"Professional",
            "subcategory":"Business Services",
            "type":"Services"
        }
    ],
    "sg:phone":"+1 972 233 0333",
    "sg:postcode":"75248",
    "sg:province":"TX",
    "wof:name":"Present It LLC",
    "wof:placetype":"venue"
},
  "geometry": {"coordinates":[-96.770629,32.956692],"type":"Point"}
}