{
  "type": "Feature",
  "properties": {
    "iso:country":"US",
    "sg:address":"202 Van Zandt St",
    "sg:city":"San Angelo",
    "sg:classifiers":[
        {
            "category":"Shopping",
            "subcategory":"Beauty & Cosmetics",
            "type":"Retail Goods"
        }
    ],
    "sg:phone":"+1 325 651 6317",
    "sg:postcode":"76905",
    "sg:province":"TX",
    "sg:tags":[
        "house",
        "merchandise",
        "mail"
    ],
    "wof:name":"Mary Blakeley",
    "wof:placetype":"venue"
},
  "geometry": {"coordinates":[-100.41301,31.451559],"type":"Point"}
}