{
  "type": "Feature",
  "properties": {
    "iso:country":"US",
    "sg:address":"1604 Morgan Ln",
    "sg:city":"Austin",
    "sg:classifiers":[
        {
            "category":"Banks & Credit Unions",
            "subcategory":"Financial Services",
            "type":"Services"
        }
    ],
    "sg:phone":"+1 512 916 8057",
    "sg:postcode":"78704",
    "sg:province":"TX",
    "sg:tags":[
        "trust",
        "investment",
        "real estate"
    ],
    "wof:name":"Bapuji Infinity Inc",
    "wof:placetype":"venue"
},
  "geometry": {"coordinates":[-97.780252,30.228997],"type":"Point"}
}