{
  "type": "Feature",
  "properties": {
    "iso:country":"US",
    "sg:address":"1202 Dragon St",
    "sg:city":"Dallas",
    "sg:classifiers":[
        {
            "category":"Wholesale",
            "subcategory":"Electrical",
            "type":"Manufacturing & Wholesale Goods"
        }
    ],
    "sg:phone":"+1 214 413 7000",
    "sg:postcode":"75207",
    "sg:province":"TX",
    "sg:tags":[
        "equipment"
    ],
    "wof:name":"Hossley Lighting Associates",
    "wof:placetype":"venue"
},
  "geometry": {"coordinates":[-96.818932,32.790474],"type":"Point"}
}