{
  "type": "Feature",
  "properties": {
    "iso:country":"US",
    "sg:address":"224 Preston Royal Shopping Ctr",
    "sg:city":"Dallas",
    "sg:classifiers":[
        {
            "category":"Shopping",
            "subcategory":"Clothing, Apparel, & Fashions",
            "type":"Retail Goods"
        }
    ],
    "sg:phone":"+1 214 378 1101",
    "sg:postcode":"75230",
    "sg:province":"TX",
    "sg:tags":[
        "accessory",
        "clothing",
        "women's"
    ],
    "sg:website":"www.talula.com",
    "wof:name":"Talula",
    "wof:placetype":"venue"
},
  "geometry": {"coordinates":[-96.805256,32.894996],"type":"Point"}
}