{
  "type": "Feature",
  "properties": {
    "iso:country":"US",
    "sg:address":"627 Creek Dr",
    "sg:city":"New Braunfels",
    "sg:classifiers":[
        {
            "category":"Shopping",
            "subcategory":"Music",
            "type":"Retail Goods"
        }
    ],
    "sg:phone":"+1 830 626 2902",
    "sg:postcode":"78130",
    "sg:province":"TX",
    "wof:name":"Roberto Arredondo",
    "wof:placetype":"venue"
},
  "geometry": {"coordinates":[-98.13868100000001,29.69815],"type":"Point"}
}