{
  "type": "Feature",
  "properties": {
    "iso:country":"US",
    "sg:address":"417 E 10th St",
    "sg:city":"Brownsville",
    "sg:classifiers":[
        {
            "category":"Shopping",
            "subcategory":"Optical Goods",
            "type":"Retail Goods"
        }
    ],
    "sg:phone":"+1 956 547 9500",
    "sg:postcode":"78520",
    "sg:province":"TX",
    "wof:name":"Vision TEC Optical",
    "wof:placetype":"venue"
},
  "geometry": {"coordinates":[-97.49973300000001,25.902365],"type":"Point"}
}