{
  "type": "Feature",
  "properties": {
    "iso:country":"US",
    "sg:address":"2400 US Hwy 77X Bus",
    "sg:city":"San Benito",
    "sg:classifiers":[
        {
            "category":"Building & Trades",
            "subcategory":"Plumbing",
            "type":"Services"
        }
    ],
    "sg:phone":"+1 956 412 7551",
    "sg:postcode":"78586",
    "sg:province":"TX",
    "sg:tags":[
        "air",
        "heating",
        "refrigeration",
        "conditioning",
        "contractor"
    ],
    "wof:name":"Southeast Service Corp",
    "wof:placetype":"venue"
},
  "geometry": {"coordinates":[-97.662215,26.16417],"type":"Point"}
}