{
  "type": "Feature",
  "properties": {
    "iso:country":"US",
    "sg:address":"1025 Pruitt Rd",
    "sg:city":"Spring",
    "sg:classifiers":[
        {
            "category":"Shopping",
            "subcategory":"Bicycles & Sporting Goods",
            "type":"Retail Goods"
        }
    ],
    "sg:phone":"+1 281 419 8245",
    "sg:postcode":"77380",
    "sg:province":"TX",
    "sg:website":"www.texlax.com",
    "wof:name":"Texas Lacrosse Rugby & Soccer",
    "wof:placetype":"venue"
},
  "geometry": {"coordinates":[-95.449358,30.11436],"type":"Point"}
}