{
  "type": "Feature",
  "properties": {
    "iso:country":"US",
    "sg:address":"3011 N 3rd St",
    "sg:city":"Temple",
    "sg:classifiers":[
        {
            "category":"Organizations",
            "subcategory":"Membership Organization",
            "type":"Services"
        },
        {
            "category":"Museum",
            "type":"Entertainment"
        }
    ],
    "sg:phone":"+1 254 773 9926",
    "sg:postcode":"76501",
    "sg:province":"TX",
    "sg:tags":[
        "information",
        "arts"
    ],
    "wof:name":"Cultural Activities Center",
    "wof:placetype":"venue"
},
  "geometry": {"coordinates":[-97.333752,31.127697],"type":"Point"}
}