{
  "type": "Feature",
  "properties": {
    "iso:country":"US",
    "sg:address":"11085 Kingsley Rd",
    "sg:city":"Dallas",
    "sg:classifiers":[
        {
            "category":"Freight",
            "type":"Transportation"
        }
    ],
    "sg:phone":"+1 214 343 8672",
    "sg:postcode":"75238",
    "sg:province":"TX",
    "sg:tags":[
        "storage",
        "self",
        "commercial"
    ],
    "wof:name":"Public Storage",
    "wof:placetype":"venue"
},
  "geometry": {"coordinates":[-96.691704,32.878899],"type":"Point"}
}