{
  "type": "Feature",
  "properties": {
    "iso:country":"US",
    "sg:address":"902 Moreland Ave",
    "sg:city":"Dallas",
    "sg:classifiers":[
        {
            "category":"Restaurant",
            "type":"Food & Drink"
        }
    ],
    "sg:phone":"+1 214 333 3612",
    "sg:postcode":"75204",
    "sg:province":"TX",
    "wof:name":"El Tacaso",
    "wof:placetype":"venue"
},
  "geometry": {"coordinates":[-96.773917,32.798567],"type":"Point"}
}