{
  "type": "Feature",
  "properties": {
    "iso:country":"US",
    "sg:address":"6412 Englewood Ave",
    "sg:city":"Lubbock",
    "sg:classifiers":[
        {
            "category":"Real Estate",
            "subcategory":"Real Estate Agent",
            "type":"Services"
        }
    ],
    "sg:phone":"+1 806 794 3738",
    "sg:postcode":"79424",
    "sg:province":"TX",
    "wof:name":"G Garza Real Estate & Assoc",
    "wof:placetype":"venue"
},
  "geometry": {"coordinates":[-101.936851,33.534585],"type":"Point"}
}