{
  "type": "Feature",
  "properties": {
    "iso:country":"US",
    "sg:address":"2518 Mallard Dr",
    "sg:city":"Wichita Falls",
    "sg:classifiers":[
        {
            "category":"Restaurant",
            "type":"Food & Drink"
        }
    ],
    "sg:phone":"+1 940 696 2626",
    "sg:postcode":"76308",
    "sg:province":"TX",
    "sg:tags":[
        "eating"
    ],
    "wof:name":"Samurai of Tokyo",
    "wof:placetype":"venue"
},
  "geometry": {"coordinates":[-98.53288499999999,33.861559],"type":"Point"}
}