{
  "type": "Feature",
  "properties": {
    "iso:country":"US",
    "sg:address":"7613 Thomas Springs Rd",
    "sg:city":"Austin",
    "sg:classifiers":[
        {
            "category":"Shopping",
            "subcategory":"Hobbies, Toys, & Games",
            "type":"Retail Goods"
        },
        {
            "category":"Manufacturing",
            "subcategory":"Pottery",
            "type":"Manufacturing & Wholesale Goods"
        }
    ],
    "sg:phone":"+1 512 288 4281",
    "sg:postcode":"78736",
    "sg:province":"TX",
    "sg:tags":[
        "product",
        "ceramic",
        "merchandise"
    ],
    "wof:name":"Cracked Pot Ceramics Mfg Co",
    "wof:placetype":"venue"
},
  "geometry": {"coordinates":[-97.9218,30.249217],"type":"Point"}
}