{
  "type": "Feature",
  "properties": {
    "iso:country":"US",
    "sg:address":"2903 Thousand Oaks Dr",
    "sg:city":"San Antonio",
    "sg:classifiers":[
        {
            "category":"Banks & Credit Unions",
            "subcategory":"Bank",
            "type":"Services"
        }
    ],
    "sg:phone":"+1 210 494 1837",
    "sg:postcode":"78247",
    "sg:province":"TX",
    "wof:name":"Bank Of America",
    "wof:placetype":"venue"
},
  "geometry": {"coordinates":[-98.44026599999999,29.576],"type":"Point"}
}