{
  "type": "Feature",
  "properties": {
    "iso:country":"US",
    "sg:address":"10844 Sombra Verde Dr",
    "sg:city":"El Paso",
    "sg:classifiers":[
        {
            "category":"Professional",
            "subcategory":"Computer Services",
            "type":"Services"
        }
    ],
    "sg:phone":"+1 915 593 0823",
    "sg:postcode":"79935",
    "sg:province":"TX",
    "sg:tags":[
        "programing",
        "custom"
    ],
    "wof:name":"Classmate Grading Tools",
    "wof:placetype":"venue"
},
  "geometry": {"coordinates":[-106.33409399999999,31.757148],"type":"Point"}
}