{
  "type": "Feature",
  "properties": {
    "iso:country":"US",
    "sg:address":"5233 Fairmont Pkwy",
    "sg:city":"Pasadena",
    "sg:classifiers":[
        {
            "category":"Retail",
            "subcategory":"Laundry & Dry Cleaning",
            "type":"Services"
        }
    ],
    "sg:phone":"+1 281 487 8114",
    "sg:postcode":"77505",
    "sg:province":"TX",
    "sg:tags":[
        "cleaners"
    ],
    "wof:name":"D T Cleaners",
    "wof:placetype":"venue"
},
  "geometry": {"coordinates":[-95.1618,29.649683],"type":"Point"}
}