{
  "type": "Feature",
  "properties": {
    "iso:country":"US",
    "sg:address":"1113 N Velasco St",
    "sg:city":"Angleton",
    "sg:classifiers":[
        {
            "category":"Retail",
            "subcategory":"Laundry & Dry Cleaning",
            "type":"Services"
        }
    ],
    "sg:phone":"+1 979 849 8411",
    "sg:postcode":"77515",
    "sg:province":"TX",
    "sg:tags":[
        "drycleaning",
        "plant"
    ],
    "wof:name":"One Hour Martinizing",
    "wof:placetype":"venue"
},
  "geometry": {"coordinates":[-95.432839,29.180004],"type":"Point"}
}