{
  "type": "Feature",
  "properties": {
    "iso:country":"US",
    "sg:address":"902 Frost St",
    "sg:city":"Rosenberg",
    "sg:classifiers":[
        {
            "category":"Education",
            "subcategory":"Special Training",
            "type":"Public Place"
        }
    ],
    "sg:phone":"+1 281 238 9345",
    "sg:postcode":"77471",
    "sg:province":"TX",
    "sg:tags":[
        "instruction",
        "driving"
    ],
    "wof:name":"Rose Rich Driving School",
    "wof:placetype":"venue"
},
  "geometry": {"coordinates":[-95.815727,29.559087],"type":"Point"}
}