{
  "type": "Feature",
  "properties": {
    "iso:country":"US",
    "sg:address":"1900 Hawthorne Ln",
    "sg:city":"Plano",
    "sg:classifiers":[
        {
            "category":"Professional",
            "type":"Services"
        }
    ],
    "sg:phone":"+1 972 422 1284",
    "sg:postcode":"75074",
    "sg:province":"TX",
    "wof:name":"Tinkertronics Game Services",
    "wof:placetype":"venue"
},
  "geometry": {"coordinates":[-96.686252,33.033012],"type":"Point"}
}