{
  "type": "Feature",
  "properties": {
    "iso:country":"US",
    "sg:address":"602 E Lyon St",
    "sg:city":"Laredo",
    "sg:classifiers":[
        {
            "category":"Building & Trades",
            "subcategory":"Electrical",
            "type":"Services"
        }
    ],
    "sg:phone":"+1 956 724 5093",
    "sg:postcode":"78040",
    "sg:province":"TX",
    "sg:tags":[
        "electrical",
        "contractor"
    ],
    "wof:name":"Rubens Electric",
    "wof:placetype":"venue"
},
  "geometry": {"coordinates":[-99.489649,27.52236],"type":"Point"}
}