{
  "type": "Feature",
  "properties": {
    "iso:country":"US",
    "sg:address":"8555 Delfina Dr",
    "sg:city":"El Paso",
    "sg:classifiers":[
        {
            "category":"Shopping",
            "subcategory":"Used Merchandise",
            "type":"Retail Goods"
        }
    ],
    "sg:phone":"+1 915 858 2670",
    "sg:postcode":"79907",
    "sg:province":"TX",
    "wof:name":"Jose Manuel Rivera",
    "wof:placetype":"venue"
},
  "geometry": {"coordinates":[-106.348714,31.700797],"type":"Point"}
}