{
  "type": "Feature",
  "properties": {
    "iso:country":"US",
    "sg:address":"2605 Sir Percival Ln",
    "sg:city":"Lewisville",
    "sg:classifiers":[
        {
            "category":"Professional",
            "subcategory":"Employment Agencies",
            "type":"Services"
        }
    ],
    "sg:phone":"+1 972 410 1855",
    "sg:postcode":"75056",
    "sg:province":"TX",
    "wof:name":"Pamela C Fleming",
    "wof:placetype":"venue"
},
  "geometry": {"coordinates":[-96.89306000000001,33.031882],"type":"Point"}
}