{
  "type": "Feature",
  "properties": {
    "iso:country":"US",
    "sg:address":"2334 W Buckingham Rd",
    "sg:city":"Garland",
    "sg:classifiers":[
        {
            "category":"Utilities",
            "subcategory":"Mobile Phone",
            "type":"Services"
        }
    ],
    "sg:phone":"+1 214 503 6961",
    "sg:postcode":"75042",
    "sg:province":"TX",
    "sg:tags":[
        "telephone",
        "cellular"
    ],
    "wof:name":"Advanced Wireless Svc Inc",
    "wof:placetype":"venue"
},
  "geometry": {"coordinates":[-96.661492,32.930244],"type":"Point"}
}