{
  "type": "Feature",
  "properties": {
    "iso:country":"US",
    "sg:address":"1023 Lodgehill Ln",
    "sg:city":"Houston",
    "sg:classifiers":[
        {
            "category":"Real Estate",
            "subcategory":"Real Estate Agent",
            "type":"Services"
        }
    ],
    "sg:phone":"+1 281 444 1645",
    "sg:postcode":"77090",
    "sg:province":"TX",
    "wof:name":"Emery Resources Inc",
    "wof:placetype":"venue"
},
  "geometry": {"coordinates":[-95.45340400000001,30.02697],"type":"Point"}
}