{
  "type": "Feature",
  "properties": {
    "iso:country":"US",
    "sg:address":"6808 Huebner Rd",
    "sg:city":"San Antonio",
    "sg:classifiers":[
        {
            "category":"Shopping",
            "subcategory":"Gifts & Souvenirs",
            "type":"Retail Goods"
        }
    ],
    "sg:phone":"+1 210 680 6641",
    "sg:postcode":"78238",
    "sg:province":"TX",
    "sg:tags":[
        "shop"
    ],
    "wof:name":"Tuesday Morning 046",
    "wof:placetype":"venue"
},
  "geometry": {"coordinates":[-98.625765,29.496976],"type":"Point"}
}