{
  "type": "Feature",
  "properties": {
    "iso:country":"US",
    "sg:address":"2848 Trailing Vine Rd",
    "sg:city":"Spring",
    "sg:classifiers":[
        {
            "category":"Food & Beverages",
            "subcategory":"Groceries & Convenience Stores",
            "type":"Retail Goods"
        }
    ],
    "sg:phone":"+1 281 350 2035",
    "sg:postcode":"77373",
    "sg:province":"TX",
    "wof:name":"Stop N Go 2553",
    "wof:placetype":"venue"
},
  "geometry": {"coordinates":[-95.390112,30.050823],"type":"Point"}
}