{
  "type": "Feature",
  "properties": {
    "iso:country":"US",
    "sg:address":"7220 Wynnwood Ln",
    "sg:city":"Houston",
    "sg:classifiers":[
        {
            "category":"Manufacturing",
            "subcategory":"Printing",
            "type":"Manufacturing & Wholesale Goods"
        }
    ],
    "sg:phone":"+1 713 869 9990",
    "sg:postcode":"77008",
    "sg:province":"TX",
    "sg:tags":[
        "commercial",
        "offset"
    ],
    "wof:name":"Masterpiece Litho Inc",
    "wof:placetype":"venue"
},
  "geometry": {"coordinates":[-95.448644,29.793136],"type":"Point"}
}