{
  "type": "Feature",
  "properties": {
    "iso:country":"US",
    "sg:address":"2806 34th St",
    "sg:city":"Lubbock",
    "sg:classifiers":[
        {
            "category":"Manufacturing",
            "subcategory":"Printing",
            "type":"Manufacturing & Wholesale Goods"
        }
    ],
    "sg:phone":"+1 806 791 1947",
    "sg:postcode":"79410",
    "sg:province":"TX",
    "sg:tags":[
        "newspaper"
    ],
    "wof:name":"Dallas Morning News",
    "wof:placetype":"venue"
},
  "geometry": {"coordinates":[-101.876819,33.563347],"type":"Point"}
}