{
  "type": "Feature",
  "properties": {
    "iso:country":"US",
    "sg:address":"609 Grantham Rd",
    "sg:city":"Baytown",
    "sg:classifiers":[
        {
            "category":"Building & Trades",
            "subcategory":"Pest Control",
            "type":"Services"
        }
    ],
    "sg:phone":"+1 281 422 9650",
    "sg:postcode":"77521",
    "sg:province":"TX",
    "wof:name":"De Loach Pest Control",
    "wof:placetype":"venue"
},
  "geometry": {"coordinates":[-94.973069,29.751659],"type":"Point"}
}