{
  "type": "Feature",
  "properties": {
    "iso:country":"US",
    "sg:address":"1200 Smith St",
    "sg:city":"Houston",
    "sg:classifiers":[
        {
            "category":"Retail",
            "subcategory":"Repair Shop",
            "type":"Services"
        }
    ],
    "sg:phone":"+1 713 654 7187",
    "sg:postcode":"77002",
    "sg:province":"TX",
    "wof:name":"Gulf Coast Clean Water Inc",
    "wof:placetype":"venue"
},
  "geometry": {"coordinates":[-95.369884,29.757122],"type":"Point"}
}