{
  "type": "Feature",
  "properties": {
    "iso:country":"US",
    "sg:address":"420 S Mitchell St",
    "sg:city":"San Marcos",
    "sg:classifiers":[
        {
            "category":"Organizations",
            "subcategory":"Religious Organization",
            "type":"Services"
        }
    ],
    "sg:phone":"+1 512 392 3622",
    "sg:postcode":"78666",
    "sg:province":"TX",
    "sg:tags":[
        "church"
    ],
    "wof:name":"First Baptist Church N B C",
    "wof:placetype":"venue"
},
  "geometry": {"coordinates":[-97.947772,29.873859],"type":"Point"}
}