{
  "type": "Feature",
  "properties": {
    "iso:country":"US",
    "sg:address":"11711 Brittmoore Park Dr",
    "sg:city":"Houston",
    "sg:classifiers":[
        {
            "category":"Building & Trades",
            "subcategory":"Construction",
            "type":"Services"
        }
    ],
    "sg:phone":"+1 713 460 2181",
    "sg:postcode":"77041",
    "sg:province":"TX",
    "sg:tags":[
        "carport"
    ],
    "sg:website":"www.childersonline.com",
    "wof:name":"Childers Carports & Structures",
    "wof:placetype":"venue"
},
  "geometry": {"coordinates":[-95.58495499999999,29.849082],"type":"Point"}
}