{
  "type": "Feature",
  "properties": {
    "iso:country":"US",
    "sg:address":"198 Shady Grove Ln",
    "sg:city":"Weatherford",
    "sg:classifiers":[
        {
            "category":"Home & Garden",
            "subcategory":"Hardware",
            "type":"Retail Goods"
        }
    ],
    "sg:phone":"+1 817 341 2413",
    "sg:postcode":"76088",
    "sg:province":"TX",
    "wof:name":"Designer Hardware",
    "wof:placetype":"venue"
},
  "geometry": {"coordinates":[-97.87026299999999,32.806109],"type":"Point"}
}