{
  "type": "Feature",
  "properties": {
    "iso:country":"US",
    "sg:address":"1208 San Felipe St",
    "sg:city":"Angleton",
    "sg:classifiers":[
        {
            "category":"Sports & Exercise",
            "subcategory":"Gym",
            "type":"Entertainment"
        }
    ],
    "sg:phone":"+1 979 849 0454",
    "sg:postcode":"77515",
    "sg:province":"TX",
    "sg:tags":[
        "fitness",
        "physical",
        "facility"
    ],
    "wof:name":"Fitness Education Inc",
    "wof:placetype":"venue"
},
  "geometry": {"coordinates":[-95.416809,29.17412],"type":"Point"}
}