{
  "type": "Feature",
  "properties": {
    "iso:country":"US",
    "sg:address":"1210 E Mesa Park Dr",
    "sg:city":"Round Rock",
    "sg:classifiers":[
        {
            "category":"Shopping",
            "subcategory":"Jewelry",
            "type":"Retail Goods"
        }
    ],
    "sg:phone":"+1 512 255 0278",
    "sg:postcode":"78664",
    "sg:province":"TX",
    "wof:name":"Sidney Gervais",
    "wof:placetype":"venue"
},
  "geometry": {"coordinates":[-97.666433,30.521766],"type":"Point"}
}