{
  "type": "Feature",
  "properties": {
    "iso:country":"US",
    "sg:address":"2302 Country Place Dr",
    "sg:city":"Richmond",
    "sg:classifiers":[
        {
            "category":"Professional",
            "type":"Services"
        }
    ],
    "sg:phone":"+1 281 239 2030",
    "sg:postcode":"77469",
    "sg:province":"TX",
    "wof:name":"The Body Zone Inc",
    "wof:placetype":"venue"
},
  "geometry": {"coordinates":[-95.725319,29.612892],"type":"Point"}
}