{
  "type": "Feature",
  "properties": {
    "iso:country":"US",
    "sg:address":"1400 Woodloch Forest Dr",
    "sg:city":"Spring",
    "sg:classifiers":[
        {
            "category":"Professional",
            "subcategory":"Accounting & Tax Preparation",
            "type":"Services"
        }
    ],
    "sg:phone":"+1 281 364 7030",
    "sg:postcode":"77380",
    "sg:province":"TX",
    "sg:tags":[
        "accountant"
    ],
    "wof:name":"Gerald L Simpson CPA",
    "wof:placetype":"venue"
},
  "geometry": {"coordinates":[-95.473269,30.15769],"type":"Point"}
}