{
  "type": "Feature",
  "properties": {
    "iso:country":"US",
    "sg:address":"7710 Beaudelaire Cir",
    "sg:city":"Galveston",
    "sg:classifiers":[
        {
            "category":"Professional",
            "type":"Services"
        }
    ],
    "sg:phone":"+1 409 744 4514",
    "sg:postcode":"77551",
    "sg:province":"TX",
    "wof:name":"Tammy Borsellino",
    "wof:placetype":"venue"
},
  "geometry": {"coordinates":[-94.844222,29.261361],"type":"Point"}
}