{
  "type": "Feature",
  "properties": {
    "iso:country":"US",
    "sg:address":"106 E Morning Cloud Cir",
    "sg:city":"Spring",
    "sg:classifiers":[
        {
            "category":"Professional",
            "subcategory":"Business Services",
            "type":"Services"
        }
    ],
    "sg:phone":"+1 281 321 5677",
    "sg:postcode":"77381",
    "sg:province":"TX",
    "wof:name":"Rjsm Inc",
    "wof:placetype":"venue"
},
  "geometry": {"coordinates":[-95.494787,30.198027],"type":"Point"}
}