{
  "type": "Feature",
  "properties": {
    "iso:country":"US",
    "sg:address":"2058 FM 1960 W",
    "sg:city":"Houston",
    "sg:classifiers":[
        {
            "category":"Shopping",
            "type":"Retail Goods"
        }
    ],
    "sg:phone":"+1 281 583 7827",
    "sg:postcode":"77090",
    "sg:province":"TX",
    "sg:tags":[
        "merchandise"
    ],
    "wof:name":"Allstar Awards",
    "wof:placetype":"venue"
},
  "geometry": {"coordinates":[-95.463115,30.007538],"type":"Point"}
}