{
  "type": "Feature",
  "properties": {
    "iso:country":"US",
    "sg:address":"1325 Lauder Rd",
    "sg:city":"Houston",
    "sg:classifiers":[
        {
            "category":"Organizations",
            "subcategory":"Religious Organization",
            "type":"Services"
        }
    ],
    "sg:phone":"+1 281 442 3444",
    "sg:postcode":"77039",
    "sg:province":"TX",
    "sg:tags":[
        "church"
    ],
    "wof:name":"Harmony Baptist Church",
    "wof:placetype":"venue"
},
  "geometry": {"coordinates":[-95.366604,29.914114],"type":"Point"}
}