{
  "type": "Feature",
  "properties": {
    "iso:country":"US",
    "sg:address":"5705 Watauga Rd",
    "sg:city":"Fort Worth",
    "sg:classifiers":[
        {
            "category":"Building & Trades",
            "subcategory":"Landscaping Services",
            "type":"Services"
        }
    ],
    "sg:phone":"+1 817 834 9810",
    "sg:postcode":"76148",
    "sg:province":"TX",
    "wof:name":"Ballards Tree Service",
    "wof:placetype":"venue"
},
  "geometry": {"coordinates":[-97.259596,32.860586],"type":"Point"}
}