{
  "type": "Feature",
  "properties": {
    "iso:country":"US",
    "sg:address":"3869 Bentwood Ln",
    "sg:city":"Corpus Christi",
    "sg:classifiers":[
        {
            "category":"Banks & Credit Unions",
            "subcategory":"Bank",
            "type":"Services"
        }
    ],
    "sg:phone":"+1 361 814 4352",
    "sg:postcode":"78415",
    "sg:province":"TX",
    "sg:tags":[
        "national",
        "commercial"
    ],
    "wof:name":"Cenfuel NA Inc",
    "wof:placetype":"venue"
},
  "geometry": {"coordinates":[-97.40336499999999,27.720801],"type":"Point"}
}