{
  "type": "Feature",
  "properties": {
    "iso:country":"US",
    "sg:address":"5555 Fellowship Ln",
    "sg:city":"Spring",
    "sg:classifiers":[
        {
            "category":"Building & Trades",
            "subcategory":"Construction",
            "type":"Services"
        }
    ],
    "sg:phone":"+1 281 320 0666",
    "sg:postcode":"77379",
    "sg:province":"TX",
    "sg:tags":[
        "specializing",
        "c",
        "builder",
        "general",
        "home",
        "contractor"
    ],
    "wof:name":"M B Schauer Homes Inc",
    "wof:placetype":"venue"
},
  "geometry": {"coordinates":[-95.501211,30.038475],"type":"Point"}
}