{
  "type": "Feature",
  "properties": {
    "iso:country":"US",
    "sg:address":"5117 Seville Ln",
    "sg:city":"Flower Mound",
    "sg:classifiers":[
        {
            "category":"Insurance",
            "subcategory":"Insurance Agent",
            "type":"Services"
        }
    ],
    "sg:phone":"+1 972 899 1450",
    "sg:postcode":"75028",
    "sg:province":"TX",
    "sg:tags":[
        "broker",
        "mortgage"
    ],
    "wof:name":"First Patriot Mortgage",
    "wof:placetype":"venue"
},
  "geometry": {"coordinates":[-97.092208,33.057173],"type":"Point"}
}