{
  "type": "Feature",
  "properties": {
    "iso:country":"US",
    "sg:address":"4777 Edenwood Dr",
    "sg:city":"Fort Worth",
    "sg:classifiers":[
        {
            "category":"Professional",
            "type":"Services"
        }
    ],
    "sg:phone":"+1 817 370 8100",
    "sg:postcode":"76123",
    "sg:province":"TX",
    "wof:name":"Vbv Inc",
    "wof:placetype":"venue"
},
  "geometry": {"coordinates":[-97.399306,32.616847],"type":"Point"}
}