{
  "type": "Feature",
  "properties": {
    "iso:country":"US",
    "sg:address":"906 E 5th St",
    "sg:city":"Austin",
    "sg:classifiers":[
        {
            "category":"Professional",
            "subcategory":"Business Services",
            "type":"Services"
        },
        {
            "category":"Professional",
            "subcategory":"Art Services",
            "type":"Services"
        }
    ],
    "sg:phone":"+1 512 485 3066",
    "sg:postcode":"78702",
    "sg:province":"TX",
    "sg:tags":[
        "development",
        "product",
        "graphic",
        "designers-industrial",
        "artist",
        "marketing",
        "commercial",
        "designer",
        "design"
    ],
    "wof:name":"Studio 107",
    "wof:placetype":"venue"
},
  "geometry": {"coordinates":[-97.73390000000001,30.264519],"type":"Point"}
}