{
  "type": "Feature",
  "properties": {
    "iso:country":"US",
    "sg:address":"3760 Gattis School Rd",
    "sg:city":"Round Rock",
    "sg:classifiers":[
        {
            "category":"Restaurant",
            "type":"Food & Drink"
        }
    ],
    "sg:menulink":"http://www.allmenus.com/tx/georgetown-round-rock/177712-jack-in-the-box/menu/",
    "sg:phone":"+1 512 828 0380",
    "sg:postcode":"78664",
    "sg:province":"TX",
    "sg:tags":[
        "burger",
        "american"
    ],
    "wof:name":"Jack in the Box",
    "wof:placetype":"venue"
},
  "geometry": {"coordinates":[-97.614356,30.497672],"type":"Point"}
}