{
  "type": "Feature",
  "properties": {
    "iso:country":"US",
    "sg:address":"1970 Austin Hwy",
    "sg:city":"San Antonio",
    "sg:classifiers":[
        {
            "category":"Travel",
            "subcategory":"Hotels & Motels",
            "type":"Entertainment"
        }
    ],
    "sg:phone":"+1 210 655 2020",
    "sg:postcode":"78218",
    "sg:province":"TX",
    "sg:tags":[
        "operation"
    ],
    "wof:name":"Broadway Inn",
    "wof:placetype":"venue"
},
  "geometry": {"coordinates":[-98.418002,29.502449],"type":"Point"}
}