{
  "type": "Feature",
  "properties": {
    "iso:country":"US",
    "sg:address":"9122 Pembrook St",
    "sg:city":"Houston",
    "sg:classifiers":[
        {
            "category":"Restaurant",
            "type":"Food & Drink"
        }
    ],
    "sg:phone":"+1 713 633 1381",
    "sg:postcode":"77016",
    "sg:province":"TX",
    "sg:tags":[
        "eating"
    ],
    "wof:name":"Taqueria Barrera",
    "wof:placetype":"venue"
},
  "geometry": {"coordinates":[-95.298855,29.844607],"type":"Point"}
}