{
  "type": "Feature",
  "properties": {
    "iso:country":"US",
    "sg:address":"5802 Autumn Forest Dr",
    "sg:city":"Houston",
    "sg:classifiers":[
        {
            "category":"Building & Trades",
            "subcategory":"Construction",
            "type":"Services"
        }
    ],
    "sg:phone":"+1 713 686 2433",
    "sg:postcode":"77092",
    "sg:province":"TX",
    "wof:name":"Ol AG Inc",
    "wof:placetype":"venue"
},
  "geometry": {"coordinates":[-95.47624500000001,29.845424],"type":"Point"}
}