{
  "type": "Feature",
  "properties": {
    "iso:country":"US",
    "sg:address":"193 Buffalo Creek Dr",
    "sg:city":"Crandall",
    "sg:classifiers":[
        {
            "category":"Professional",
            "type":"Services"
        }
    ],
    "sg:phone":"+1 972 849 5674",
    "sg:postcode":"75114",
    "sg:province":"TX",
    "wof:name":"Vaden Service",
    "wof:placetype":"venue"
},
  "geometry": {"coordinates":[-96.452005,32.61689],"type":"Point"}
}