{
  "type": "Feature",
  "properties": {
    "iso:country":"US",
    "sg:address":"6017 Gentle Knoll Ln",
    "sg:city":"Dallas",
    "sg:classifiers":[
        {
            "category":"Professional",
            "subcategory":"Business Services",
            "type":"Services"
        }
    ],
    "sg:phone":"+1 972 931 6521",
    "sg:postcode":"75248",
    "sg:province":"TX",
    "wof:name":"Garfield Joann & Assoc",
    "wof:placetype":"venue"
},
  "geometry": {"coordinates":[-96.800719,32.980941],"type":"Point"}
}