{
  "type": "Feature",
  "properties": {
    "iso:country":"US",
    "sg:address":"10235 W Little York Rd",
    "sg:city":"Houston",
    "sg:classifiers":[
        {
            "category":"Professional",
            "type":"Services"
        }
    ],
    "sg:phone":"+1 713 690 1652",
    "sg:postcode":"77040",
    "sg:province":"TX",
    "sg:tags":[
        "establishment"
    ],
    "wof:name":"Unistrut Gulf",
    "wof:placetype":"venue"
},
  "geometry": {"coordinates":[-95.550882,29.868277],"type":"Point"}
}