{
  "type": "Feature",
  "properties": {
    "iso:country":"US",
    "sg:address":"108 N San Marcial St",
    "sg:city":"El Paso",
    "sg:classifiers":[
        {
            "category":"Retail",
            "subcategory":"Auto Repair",
            "type":"Services"
        }
    ],
    "sg:phone":"+1 915 532 8577",
    "sg:postcode":"79905",
    "sg:province":"TX",
    "sg:tags":[
        "repairing",
        "automobile"
    ],
    "wof:name":"G & D Auto Svc",
    "wof:placetype":"venue"
},
  "geometry": {"coordinates":[-106.458483,31.773505],"type":"Point"}
}