{
  "type": "Feature",
  "properties": {
    "iso:country":"US",
    "sg:address":"3636 Dan Morton Dr",
    "sg:city":"Dallas",
    "sg:classifiers":[
        {
            "category":"Wholesale",
            "subcategory":"Chemicals & Plastics",
            "type":"Manufacturing & Wholesale Goods"
        }
    ],
    "sg:phone":"+1 972 709 0136",
    "sg:postcode":"75236",
    "sg:province":"TX",
    "sg:tags":[
        "industrial"
    ],
    "wof:name":"Southwest",
    "wof:placetype":"venue"
},
  "geometry": {"coordinates":[-96.918252,32.701919],"type":"Point"}
}