{
  "type": "Feature",
  "properties": {
    "iso:country":"US",
    "sg:address":"5601 S Braeswood Blvd",
    "sg:city":"Houston",
    "sg:classifiers":[
        {
            "category":"Health Services",
            "subcategory":"Clinic",
            "type":"Services"
        }
    ],
    "sg:phone":"+1 832 203 1094",
    "sg:postcode":"77096",
    "sg:province":"TX",
    "sg:tags":[
        "specialty",
        "outpatient"
    ],
    "wof:name":"Memorial Hermann Phys Therapy",
    "wof:placetype":"venue"
},
  "geometry": {"coordinates":[-95.48313899999999,29.675072],"type":"Point"}
}