{
  "type": "Feature",
  "properties": {
    "iso:country":"US",
    "sg:address":"930 Parkview Ln",
    "sg:city":"Southlake",
    "sg:classifiers":[
        {
            "category":"Real Estate",
            "subcategory":"Real Estate Agent",
            "type":"Services"
        }
    ],
    "sg:phone":"+1 817 329 4599",
    "sg:postcode":"76092",
    "sg:province":"TX",
    "wof:name":"Wyndham Properties LTD",
    "wof:placetype":"venue"
},
  "geometry": {"coordinates":[-97.165941,32.929531],"type":"Point"}
}