{
  "type": "Feature",
  "properties": {
    "iso:country":"US",
    "sg:address":"2624 E Grant St",
    "sg:city":"Roma",
    "sg:classifiers":[
        {
            "category":"Restaurant",
            "type":"Food & Drink"
        }
    ],
    "sg:phone":"+1 956 849 7239",
    "sg:postcode":"78584",
    "sg:province":"TX",
    "sg:tags":[
        "eating"
    ],
    "wof:name":"T & T",
    "wof:placetype":"venue"
},
  "geometry": {"coordinates":[-98.983056,26.406416],"type":"Point"}
}