{
  "type": "Feature",
  "properties": {
    "iso:country":"US",
    "sg:address":"600 W Upshur Ave",
    "sg:city":"Gladewater",
    "sg:classifiers":[
        {
            "category":"Shopping",
            "subcategory":"Florist",
            "type":"Retail Goods"
        }
    ],
    "sg:phone":"+1 903 845 3738",
    "sg:postcode":"75647",
    "sg:province":"TX",
    "wof:name":"Glade Florist",
    "wof:placetype":"venue"
},
  "geometry": {"coordinates":[-94.94795999999999,32.539324],"type":"Point"}
}