{
  "type": "Feature",
  "properties": {
    "iso:country":"US",
    "sg:address":"807 S Carroll Ave",
    "sg:city":"Dallas",
    "sg:classifiers":[
        {
            "category":"Autos & Motor Vehicles",
            "subcategory":"Automobile Sales",
            "type":"Retail Goods"
        }
    ],
    "sg:phone":"+1 214 827 6175",
    "sg:postcode":"75223",
    "sg:province":"TX",
    "sg:tags":[
        "car",
        "dealer"
    ],
    "wof:name":"Dos Amigos Auto Sales",
    "wof:placetype":"venue"
},
  "geometry": {"coordinates":[-96.76282,32.787415],"type":"Point"}
}