{
  "type": "Feature",
  "properties": {
    "iso:country":"US",
    "sg:address":"1601 Van Buren Dr",
    "sg:city":"Deer Park",
    "sg:classifiers":[
        {
            "category":"Building & Trades",
            "subcategory":"Construction",
            "type":"Services"
        }
    ],
    "sg:phone":"+1 281 479 5740",
    "sg:postcode":"77536",
    "sg:province":"TX",
    "sg:tags":[
        "carpentry",
        "contractor"
    ],
    "wof:name":"Martinez R Carpenter",
    "wof:placetype":"venue"
},
  "geometry": {"coordinates":[-95.108279,29.67531],"type":"Point"}
}