{
  "type": "Feature",
  "properties": {
    "iso:country":"US",
    "sg:address":"3400 Cowden Dr",
    "sg:city":"Austin",
    "sg:classifiers":[
        {
            "category":"Home & Garden",
            "subcategory":"Garden Supply",
            "type":"Retail Goods"
        }
    ],
    "sg:phone":"+1 512 301 7680",
    "sg:postcode":"78732",
    "sg:province":"TX",
    "sg:tags":[
        "center"
    ],
    "wof:name":"S L Spaulding & Assoc",
    "wof:placetype":"venue"
},
  "geometry": {"coordinates":[-97.89816399999999,30.376714],"type":"Point"}
}