{
  "type": "Feature",
  "properties": {
    "iso:country":"US",
    "sg:address":"6411 Conley St",
    "sg:city":"Houston",
    "sg:classifiers":[
        {
            "category":"Home & Garden",
            "subcategory":"Furniture",
            "type":"Retail Goods"
        }
    ],
    "sg:phone":"+1 281 487 9130",
    "sg:postcode":"77021",
    "sg:province":"TX",
    "wof:name":"Gto Mfg Furniture",
    "wof:placetype":"venue"
},
  "geometry": {"coordinates":[-95.35632099999999,29.695048],"type":"Point"}
}