{
  "type": "Feature",
  "properties": {
    "iso:country":"US",
    "sg:address":"3288 Strawberry City Rd",
    "sg:city":"Poteet",
    "sg:phone":"+1 830 742 8045",
    "sg:postcode":"78065",
    "sg:province":"TX",
    "sg:tags":[
        "b",
        "farm",
        "cash",
        "crop",
        "field",
        "grain"
    ],
    "wof:name":"Pete Rakowitz",
    "wof:placetype":"venue"
},
  "geometry": {"coordinates":[-98.51838600000001,29.0425],"type":"Point"}
}