{
  "type": "Feature",
  "properties": {
    "iso:country":"US",
    "sg:address":"914 E Hwy 90",
    "sg:city":"Liberty",
    "sg:classifiers":[
        {
            "category":"Mining & Drilling",
            "type":"Manufacturing & Wholesale Goods"
        }
    ],
    "sg:phone":"+1 936 334 1485",
    "sg:postcode":"77575",
    "sg:province":"TX",
    "sg:tags":[
        "field",
        "oil"
    ],
    "wof:name":"Crown Well Svc LTD",
    "wof:placetype":"venue"
},
  "geometry": {"coordinates":[-94.727548,30.051014],"type":"Point"}
}