{
  "type": "Feature",
  "properties": {
    "iso:country":"US",
    "sg:address":"3005 Berkshire Dr",
    "sg:city":"Mesquite",
    "sg:classifiers":[
        {
            "category":"Professional",
            "type":"Services"
        }
    ],
    "sg:phone":"+1 972 613 6045",
    "sg:postcode":"75150",
    "sg:province":"TX",
    "wof:name":"Expedite Civil Process",
    "wof:placetype":"venue"
},
  "geometry": {"coordinates":[-96.645229,32.811257],"type":"Point"}
}