{
  "type": "Feature",
  "properties": {
    "iso:country":"US",
    "sg:address":"3286 Olive Pl",
    "sg:city":"Fort Worth",
    "sg:classifiers":[
        {
            "category":"Building & Trades",
            "subcategory":"Construction",
            "type":"Services"
        }
    ],
    "sg:phone":"+1 817 377 3286",
    "sg:postcode":"76116",
    "sg:province":"TX",
    "sg:tags":[
        "carpentry",
        "contractor"
    ],
    "wof:name":"Weather Masters",
    "wof:placetype":"venue"
},
  "geometry": {"coordinates":[-97.431978,32.724985],"type":"Point"}
}