{
  "type": "Feature",
  "properties": {
    "iso:country":"US",
    "sg:address":"3237 S Alameda St",
    "sg:city":"Corpus Christi",
    "sg:classifiers":[
        {
            "category":"Professional",
            "type":"Services"
        }
    ],
    "sg:phone":"+1 361 852 2001",
    "sg:postcode":"78404",
    "sg:province":"TX",
    "sg:tags":[
        "establishment"
    ],
    "wof:name":"Classic Cleaners",
    "wof:placetype":"venue"
},
  "geometry": {"coordinates":[-97.389673,27.756299],"type":"Point"}
}