{
  "type": "Feature",
  "properties": {
    "iso:country":"US",
    "sg:address":"2828 E Trinity Mills Rd Ste 300",
    "sg:city":"Carrollton",
    "sg:classifiers":[
        {
            "category":"Building & Trades",
            "subcategory":"Construction",
            "type":"Services"
        }
    ],
    "sg:phone":"+1 972 478 8181",
    "sg:postcode":"75006",
    "sg:province":"TX",
    "sg:tags":[
        "contractor"
    ],
    "wof:name":"Cambridge Homes Inc",
    "wof:placetype":"venue"
},
  "geometry": {"coordinates":[-96.853798,32.987],"type":"Point"}
}