{
  "type": "Feature",
  "properties": {
    "iso:country":"US",
    "sg:address":"4810 Turnback",
    "sg:city":"Leander",
    "sg:classifiers":[
        {
            "category":"Professional",
            "subcategory":"Management & Consulting",
            "type":"Services"
        }
    ],
    "sg:phone":"+1 512 267 0059",
    "sg:postcode":"78645",
    "sg:province":"TX",
    "sg:tags":[
        "public",
        "relations"
    ],
    "wof:name":"Wildey Things Productions",
    "wof:placetype":"venue"
},
  "geometry": {"coordinates":[-98.002286,30.446303],"type":"Point"}
}