{
  "type": "Feature",
  "properties": {
    "iso:country":"US",
    "sg:address":"700 Meyers Rd",
    "sg:city":"Dale",
    "sg:classifiers":[
        {
            "category":"Professional",
            "type":"Services"
        }
    ],
    "sg:phone":"+1 512 785 0134",
    "sg:postcode":"78610",
    "sg:province":"TX",
    "wof:name":"Topnotch Pipefitting and Weldi",
    "wof:placetype":"venue"
},
  "geometry": {"coordinates":[-97.787738,30.052129],"type":"Point"}
}