{
  "type": "Feature",
  "properties": {
    "iso:country":"US",
    "sg:address":"7153 Dee Cole Dr",
    "sg:city":"Lewisville",
    "sg:classifiers":[
        {
            "category":"Professional",
            "type":"Services"
        }
    ],
    "sg:phone":"+1 972 625 4822",
    "sg:postcode":"75056",
    "sg:province":"TX",
    "sg:tags":[
        "establishment"
    ],
    "wof:name":"DYM Corp",
    "wof:placetype":"venue"
},
  "geometry": {"coordinates":[-96.861215,33.099852],"type":"Point"}
}