{
  "type": "Feature",
  "properties": {
    "iso:country":"US",
    "sg:address":"1104 Harvey Rd",
    "sg:city":"College Station",
    "sg:classifiers":[
        {
            "category":"Shopping",
            "subcategory":"Used Merchandise",
            "type":"Retail Goods"
        },
        {
            "category":"Professional",
            "type":"Services"
        }
    ],
    "sg:phone":"+1 979 694 8440",
    "sg:postcode":"77840",
    "sg:province":"TX",
    "sg:tags":[
        "clothing"
    ],
    "wof:name":"Plato's Closet",
    "wof:placetype":"venue"
},
  "geometry": {"coordinates":[-96.309184,30.623571],"type":"Point"}
}