{
  "type": "Feature",
  "properties": {
    "iso:country":"US",
    "sg:address":"1706 Jennifer Dr",
    "sg:city":"Garland",
    "sg:classifiers":[
        {
            "category":"Building & Trades",
            "subcategory":"Electrical",
            "type":"Services"
        }
    ],
    "sg:phone":"+1 214 632 2689",
    "sg:postcode":"75042",
    "sg:province":"TX",
    "sg:tags":[
        "electrical",
        "contractor"
    ],
    "wof:name":"T & Y Inc",
    "wof:placetype":"venue"
},
  "geometry": {"coordinates":[-96.65945600000001,32.92778],"type":"Point"}
}