{
  "type": "Feature",
  "properties": {
    "iso:country":"US",
    "sg:address":"3501 Banbury Ct",
    "sg:city":"Fort Worth",
    "sg:classifiers":[
        {
            "category":"Social Services",
            "type":"Services"
        }
    ],
    "sg:phone":"+1 817 413 8393",
    "sg:postcode":"76119",
    "sg:province":"TX",
    "wof:name":"Four Steps Daycare",
    "wof:placetype":"venue"
},
  "geometry": {"coordinates":[-97.268793,32.663013],"type":"Point"}
}