{
  "type": "Feature",
  "properties": {
    "iso:country":"US",
    "sg:address":"203 N Conway Ave",
    "sg:city":"Mission",
    "sg:classifiers":[
        {
            "category":"Building & Trades",
            "subcategory":"Plumbing",
            "type":"Services"
        }
    ],
    "sg:phone":"+1 956 585 9653",
    "sg:postcode":"78572",
    "sg:province":"TX",
    "sg:tags":[
        "insurance",
        "contractor"
    ],
    "wof:name":"Savco Insurance",
    "wof:placetype":"venue"
},
  "geometry": {"coordinates":[-98.326966,26.208563],"type":"Point"}
}