{
  "type": "Feature",
  "properties": {
    "iso:country":"US",
    "sg:address":"2721 Sherrill Park Dr",
    "sg:city":"Richardson",
    "sg:classifiers":[
        {
            "category":"Professional",
            "subcategory":"Management & Consulting",
            "type":"Services"
        }
    ],
    "sg:phone":"+1 817 721 6761",
    "sg:postcode":"75082",
    "sg:province":"TX",
    "sg:tags":[
        "business"
    ],
    "wof:name":"Trimark Consulting",
    "wof:placetype":"venue"
},
  "geometry": {"coordinates":[-96.683485,32.988709],"type":"Point"}
}