{
  "type": "Feature",
  "properties": {
    "iso:country":"US",
    "sg:address":"1 Walden Elms",
    "sg:city":"San Antonio",
    "sg:classifiers":[
        {
            "category":"Farming",
            "subcategory":"Livestock Farm",
            "type":"Manufacturing & Wholesale Goods"
        }
    ],
    "sg:phone":"+1 210 698 3684",
    "sg:postcode":"78257",
    "sg:province":"TX",
    "sg:tags":[
        "animal",
        "general"
    ],
    "wof:name":"Sepulveda Salazar Ranch Ltd",
    "wof:placetype":"venue"
},
  "geometry": {"coordinates":[-98.610175,29.663045],"type":"Point"}
}