{
  "type": "Feature",
  "properties": {
    "iso:country":"US",
    "sg:address":"139 Lyons Rd Ste 141",
    "sg:city":"Ennis",
    "sg:classifiers":[
        {
            "category":"Restaurant",
            "type":"Food & Drink"
        }
    ],
    "sg:phone":"+1 972 875 8391",
    "sg:postcode":"75119",
    "sg:province":"TX",
    "sg:tags":[
        "house",
        "steak",
        "barbecue"
    ],
    "sg:website":"http://www.bbqwoodflavors.com",
    "wof:name":"Barbeque Wood Flavors, Inc.",
    "wof:placetype":"venue"
},
  "geometry": {"coordinates":[-96.569455,32.272474],"type":"Point"}
}