{
  "type": "Feature",
  "properties": {
    "iso:country":"US",
    "sg:address":"1230 S High St Ste B",
    "sg:city":"Longview",
    "sg:classifiers":[
        {
            "category":"Sports & Exercise",
            "subcategory":"Gym",
            "type":"Entertainment"
        },
        {
            "category":"Community Center",
            "type":"Public Place"
        },
        {
            "category":"Government",
            "subcategory":"Office",
            "type":"Public Place"
        }
    ],
    "sg:phone":"+1 903 239 5500",
    "sg:postcode":"75602",
    "sg:province":"TX",
    "sg:tags":[
        "government-city",
        "recreation",
        "township",
        "gymnasium",
        "village"
    ],
    "wof:name":"Paula Martin Jones Recreation",
    "wof:placetype":"venue"
},
  "geometry": {"coordinates":[-94.742851,32.477638],"type":"Point"}
}