{
  "type": "Feature",
  "properties": {
    "iso:country":"US",
    "sg:address":"1420 Marshall St",
    "sg:city":"Houston",
    "sg:classifiers":[
        {
            "category":"Retail",
            "subcategory":"Repair Shop",
            "type":"Services"
        }
    ],
    "sg:phone":"+1 713 524 6231",
    "sg:postcode":"77006",
    "sg:province":"TX",
    "sg:tags":[
        "reupholstery",
        "furniture"
    ],
    "wof:name":"Quang Tran Upholstery",
    "wof:placetype":"venue"
},
  "geometry": {"coordinates":[-95.39679700000001,29.7397],"type":"Point"}
}