{
  "type": "Feature",
  "properties": {
    "iso:country":"US",
    "sg:address":"2231 Singleton Blvd",
    "sg:city":"Dallas",
    "sg:classifiers":[
        {
            "category":"Restaurant",
            "type":"Food & Drink"
        }
    ],
    "sg:phone":"+1 214 689 7837",
    "sg:postcode":"75212",
    "sg:province":"TX",
    "wof:name":"Subway Sandwiches & Salads",
    "wof:placetype":"venue"
},
  "geometry": {"coordinates":[-96.86033999999999,32.778772],"type":"Point"}
}