{
  "type": "Feature",
  "properties": {
    "iso:country":"US",
    "sg:address":"605 Turner Way",
    "sg:city":"Cedar Hill",
    "sg:classifiers":[
        {
            "category":"Building & Trades",
            "subcategory":"Electrical",
            "type":"Services"
        }
    ],
    "sg:phone":"+1 972 291 1294",
    "sg:postcode":"75104",
    "sg:province":"TX",
    "sg:tags":[
        "electric",
        "contractor"
    ],
    "wof:name":"Electrical Maintenance Co",
    "wof:placetype":"venue"
},
  "geometry": {"coordinates":[-96.927555,32.578611],"type":"Point"}
}