{
  "type": "Feature",
  "properties": {
    "iso:country":"US",
    "sg:address":"3004 Philfall St",
    "sg:city":"Houston",
    "sg:classifiers":[
        {
            "category":"Food & Beverages",
            "subcategory":"Specialty",
            "type":"Retail Goods"
        }
    ],
    "sg:phone":"+1 713 522 2884",
    "sg:postcode":"77098",
    "sg:province":"TX",
    "sg:tags":[
        "gourmet",
        "mail",
        "order"
    ],
    "wof:name":"Elegant Edibles",
    "wof:placetype":"venue"
},
  "geometry": {"coordinates":[-95.422831,29.740567],"type":"Point"}
}