{
  "type": "Feature",
  "properties": {
    "iso:country":"US",
    "sg:address":"2103 E Crosby Rd",
    "sg:city":"Carrollton",
    "sg:classifiers":[
        {
            "category":"Manufacturing",
            "subcategory":"Printing",
            "type":"Manufacturing & Wholesale Goods"
        }
    ],
    "sg:phone":"+1 972 416 4356",
    "sg:postcode":"75006",
    "sg:province":"TX",
    "sg:tags":[
        "book"
    ],
    "wof:name":"Youre Star",
    "wof:placetype":"venue"
},
  "geometry": {"coordinates":[-96.884647,32.950079],"type":"Point"}
}