{
  "type": "Feature",
  "properties": {
    "iso:country":"US",
    "sg:address":"207 W Main St",
    "sg:city":"League City",
    "sg:classifiers":[
        {
            "category":"Shopping",
            "subcategory":"Discount & Variety Stores",
            "type":"Retail Goods"
        },
        {
            "category":"Shopping",
            "subcategory":"Department Store",
            "type":"Retail Goods"
        }
    ],
    "sg:phone":"+1 281 554 5479",
    "sg:postcode":"77573",
    "sg:province":"TX",
    "sg:tags":[
        "shop"
    ],
    "wof:name":"Family Dollar Stores",
    "wof:placetype":"venue"
},
  "geometry": {"coordinates":[-95.096163,29.507237],"type":"Point"}
}