{
  "type": "Feature",
  "properties": {
    "iso:country":"US",
    "sg:address":"1201 Royal Pkwy",
    "sg:city":"Euless",
    "sg:phone":"+1 817 268 5910",
    "sg:postcode":"76040",
    "sg:province":"TX",
    "sg:tags":[
        "gas",
        "temporary",
        "oil",
        "diesel",
        "t"
    ],
    "sg:website":"www.ricochetfuel.com",
    "wof:name":"Ricochet Fuel Distributors Inc",
    "wof:placetype":"venue"
},
  "geometry": {"coordinates":[-97.11879,32.819067],"type":"Point"}
}