{
  "type": "Feature",
  "properties": {
    "iso:country":"US",
    "sg:address":"6000 Pinemont Dr",
    "sg:city":"Houston",
    "sg:classifiers":[
        {
            "category":"Real Estate",
            "subcategory":"Real Estate Operator",
            "type":"Services"
        }
    ],
    "sg:phone":"+1 713 957 4430",
    "sg:postcode":"77092",
    "sg:province":"TX",
    "sg:tags":[
        "building",
        "apartment"
    ],
    "wof:name":"Pinemont The",
    "wof:placetype":"venue"
},
  "geometry": {"coordinates":[-95.477242,29.840431],"type":"Point"}
}