{
  "type": "Feature",
  "properties": {
    "iso:country":"US",
    "sg:address":"1130 Kiriaka Dr",
    "sg:city":"Eagle Pass",
    "sg:classifiers":[
        {
            "category":"Building & Trades",
            "subcategory":"Construction",
            "type":"Services"
        }
    ],
    "sg:phone":"+1 830 773 1899",
    "sg:postcode":"78852",
    "sg:province":"TX",
    "sg:tags":[
        "house"
    ],
    "wof:name":"Riojas Construction",
    "wof:placetype":"venue"
},
  "geometry": {"coordinates":[-100.482536,28.694943],"type":"Point"}
}