{
  "type": "Feature",
  "properties": {
    "iso:country":"US",
    "sg:address":"8611 Jensen Dr",
    "sg:city":"Houston",
    "sg:classifiers":[
        {
            "category":"Autos & Motor Vehicles",
            "subcategory":"Automobile Sales",
            "type":"Retail Goods"
        }
    ],
    "sg:phone":"+1 713 692 8415",
    "sg:postcode":"77093",
    "sg:province":"TX",
    "sg:tags":[
        "used"
    ],
    "wof:name":"Economy Cars",
    "wof:placetype":"venue"
},
  "geometry": {"coordinates":[-95.34286899999999,29.839259],"type":"Point"}
}