{
  "type": "Feature",
  "properties": {
    "iso:country":"US",
    "sg:address":"3424 El Benito Dr",
    "sg:city":"Dallas",
    "sg:classifiers":[
        {
            "category":"Personal",
            "subcategory":"Barber",
            "type":"Services"
        }
    ],
    "sg:phone":"+1 214 760 8602",
    "sg:postcode":"75212",
    "sg:province":"TX",
    "wof:name":"D And W Barber",
    "wof:placetype":"venue"
},
  "geometry": {"coordinates":[-96.843402,32.783648],"type":"Point"}
}