{
  "type": "Feature",
  "properties": {
    "iso:country":"US",
    "sg:address":"729 Boyd Rd",
    "sg:city":"Azle",
    "sg:classifiers":[
        {
            "category":"Retail",
            "subcategory":"Veterinary Services",
            "type":"Services"
        }
    ],
    "sg:phone":"+1 817 444 3289",
    "sg:postcode":"76020",
    "sg:province":"TX",
    "wof:name":"Eagle Mtn Veterinary Clinic",
    "wof:placetype":"venue"
},
  "geometry": {"coordinates":[-97.543592,32.905666],"type":"Point"}
}