{
  "type": "Feature",
  "properties": {
    "iso:country":"US",
    "sg:address":"3100 McKinnon St",
    "sg:city":"Dallas",
    "sg:classifiers":[
        {
            "category":"Communications",
            "subcategory":"Television Station",
            "type":"Services"
        }
    ],
    "sg:phone":"+1 888 467 2988",
    "sg:postcode":"75201",
    "sg:province":"TX",
    "wof:name":"PAX-TV KPXD-TV 68",
    "wof:placetype":"venue"
},
  "geometry": {"coordinates":[-96.810205,32.797065],"type":"Point"}
}