{
  "type": "Feature",
  "properties": {
    "iso:country":"US",
    "sg:address":"8817 Louetta Rd",
    "sg:city":"Spring",
    "sg:classifiers":[
        {
            "category":"Real Estate",
            "subcategory":"Real Estate Services",
            "type":"Services"
        },
        {
            "category":"Real Estate",
            "subcategory":"Real Estate Agent",
            "type":"Services"
        }
    ],
    "sg:phone":"+1 281 374 0013",
    "sg:postcode":"77379",
    "sg:province":"TX",
    "sg:tags":[
        "buyer",
        "broker"
    ],
    "wof:name":"Prudential Gary Greene Rltrs",
    "wof:placetype":"venue"
},
  "geometry": {"coordinates":[-95.544934,30.009408],"type":"Point"}
}