{
  "type": "Feature",
  "properties": {
    "iso:country":"US",
    "sg:address":"7808 N Navarro St",
    "sg:city":"Victoria",
    "sg:classifiers":[
        {
            "category":"Professional",
            "type":"Services"
        }
    ],
    "sg:phone":"+1 361 582 4039",
    "sg:postcode":"77904",
    "sg:province":"TX",
    "sg:tags":[
        "establishment"
    ],
    "wof:name":"Perseco Inc",
    "wof:placetype":"venue"
},
  "geometry": {"coordinates":[-96.997356,28.867743],"type":"Point"}
}