{
  "type": "Feature",
  "properties": {
    "iso:country":"US",
    "sg:address":"220 N Zang Blvd",
    "sg:city":"Dallas",
    "sg:classifiers":[
        {
            "category":"Health Services",
            "subcategory":"Chiropractor",
            "type":"Services"
        }
    ],
    "sg:phone":"+1 214 942 1212",
    "sg:postcode":"75208",
    "sg:province":"TX",
    "wof:name":"Silver Chiropractic Clinic",
    "wof:placetype":"venue"
},
  "geometry": {"coordinates":[-96.82457700000001,32.747016],"type":"Point"}
}