{
  "type": "Feature",
  "properties": {
    "iso:country":"US",
    "sg:address":"2407 Markland St",
    "sg:city":"Irving",
    "sg:classifiers":[
        {
            "category":"Building & Trades",
            "subcategory":"Equipment Rental",
            "type":"Services"
        }
    ],
    "sg:phone":"+1 972 254 3337",
    "sg:postcode":"75060",
    "sg:province":"TX",
    "wof:name":"Z M H Enterprises",
    "wof:placetype":"venue"
},
  "geometry": {"coordinates":[-96.948043,32.790931],"type":"Point"}
}