{
  "type": "Feature",
  "properties": {
    "iso:country":"US",
    "sg:address":"10300 N Central Expy Ste 170",
    "sg:city":"Dallas",
    "sg:classifiers":[
        {
            "category":"Organizations",
            "subcategory":"Religious Organization",
            "type":"Services"
        }
    ],
    "sg:phone":"+1 214 696 8844",
    "sg:postcode":"75231",
    "sg:province":"TX",
    "wof:name":"Zola Levitt Ministries",
    "wof:placetype":"venue"
},
  "geometry": {"coordinates":[-96.75129699999999,32.878399],"type":"Point"}
}