{
  "type": "Feature",
  "properties": {
    "iso:country":"US",
    "sg:address":"2900 N Belt Line Rd",
    "sg:city":"Sunnyvale",
    "sg:classifiers":[
        {
            "category":"Health Services",
            "subcategory":"Doctor",
            "type":"Services"
        }
    ],
    "sg:phone":"+1 972 226 1688",
    "sg:postcode":"75182",
    "sg:province":"TX",
    "sg:tags":[
        "throat",
        "surgeon",
        "ear",
        "cosmetic",
        "nose"
    ],
    "wof:name":"McKee J Cooper MD",
    "wof:placetype":"venue"
},
  "geometry": {"coordinates":[-96.595901,32.803902],"type":"Point"}
}