{
  "type": "Feature",
  "properties": {
    "iso:country":"US",
    "sg:address":"1005 Mae Dr",
    "sg:city":"Houston",
    "sg:classifiers":[
        {
            "category":"Manufacturing",
            "subcategory":"Tools & Machinery",
            "type":"Manufacturing & Wholesale Goods"
        }
    ],
    "sg:phone":"+1 713 453 6381",
    "sg:postcode":"77015",
    "sg:province":"TX",
    "sg:tags":[
        "machine",
        "shop",
        "welding"
    ],
    "wof:name":"Montgomery Machine Co",
    "wof:placetype":"venue"
},
  "geometry": {"coordinates":[-95.220456,29.771781],"type":"Point"}
}