{
  "type": "Feature",
  "properties": {
    "iso:country":"US",
    "sg:address":"3104 Carroll Cir",
    "sg:city":"Plano",
    "sg:classifiers":[
        {
            "category":"Restaurant",
            "type":"Food & Drink"
        }
    ],
    "sg:phone":"+1 972 618 8196",
    "sg:postcode":"75023",
    "sg:province":"TX",
    "sg:tags":[
        "eating"
    ],
    "wof:name":"Checker Burger Club Inc",
    "wof:placetype":"venue"
},
  "geometry": {"coordinates":[-96.752937,33.065814],"type":"Point"}
}