{
  "type": "Feature",
  "properties": {
    "iso:country":"US",
    "sg:address":"616 N Gulf Blvd",
    "sg:city":"Freeport",
    "sg:classifiers":[
        {
            "category":"Coffee & Tea",
            "type":"Food & Drink"
        },
        {
            "category":"Restaurant",
            "type":"Food & Drink"
        }
    ],
    "sg:phone":"+1 979 233 4854",
    "sg:postcode":"77541",
    "sg:province":"TX",
    "sg:tags":[
        "espresso"
    ],
    "wof:name":"Ar's Cafe",
    "wof:placetype":"venue"
},
  "geometry": {"coordinates":[-95.365495,28.966273],"type":"Point"}
}