{
  "type": "Feature",
  "properties": {
    "iso:country":"US",
    "sg:address":"502 S Texas Blvd",
    "sg:city":"Alice",
    "sg:classifiers":[
        {
            "category":"Food & Beverages",
            "subcategory":"Groceries & Convenience Stores",
            "type":"Retail Goods"
        }
    ],
    "sg:phone":"+1 361 664 7202",
    "sg:postcode":"78332",
    "sg:province":"TX",
    "wof:name":"Marios Meat & Market",
    "wof:placetype":"venue"
},
  "geometry": {"coordinates":[-98.064539,27.745933],"type":"Point"}
}