{
  "type": "Feature",
  "properties": {
    "iso:country":"US",
    "sg:address":"5639 Dumfries Dr",
    "sg:city":"Houston",
    "sg:classifiers":[
        {
            "category":"Professional",
            "subcategory":"Business Services",
            "type":"Services"
        }
    ],
    "sg:phone":"+1 713 729 4649",
    "sg:postcode":"77096",
    "sg:province":"TX",
    "wof:name":"L&B Designs",
    "wof:placetype":"venue"
},
  "geometry": {"coordinates":[-95.484886,29.671085],"type":"Point"}
}