{
  "type": "Feature",
  "properties": {
    "iso:country":"US",
    "sg:address":"2100 Preakness Ct",
    "sg:city":"Arlington",
    "sg:classifiers":[
        {
            "category":"Professional",
            "subcategory":"Business Services",
            "type":"Services"
        }
    ],
    "sg:phone":"+1 817 784 0238",
    "sg:postcode":"76017",
    "sg:province":"TX",
    "wof:name":"Benmart",
    "wof:placetype":"venue"
},
  "geometry": {"coordinates":[-97.139853,32.651022],"type":"Point"}
}