{
  "type": "Feature",
  "properties": {
    "iso:country":"US",
    "sg:address":"5323 Kostoryz Rd",
    "sg:city":"Corpus Christi",
    "sg:classifiers":[
        {
            "category":"Organizations",
            "subcategory":"Community Association",
            "type":"Services"
        }
    ],
    "sg:phone":"+1 361 852 9115",
    "sg:postcode":"78415",
    "sg:province":"TX",
    "wof:name":"American Legion Post 364",
    "wof:placetype":"venue"
},
  "geometry": {"coordinates":[-97.415515,27.724665],"type":"Point"}
}