{
  "type": "Feature",
  "properties": {
    "iso:country":"US",
    "sg:address":"27130 Glen Loch Dr",
    "sg:city":"Spring",
    "sg:classifiers":[
        {
            "category":"Health Services",
            "subcategory":"Chiropractor",
            "type":"Services"
        }
    ],
    "sg:phone":"+1 281 292 0808",
    "sg:postcode":"77381",
    "sg:province":"TX",
    "wof:name":"Mark Chiropractic & Wellness",
    "wof:placetype":"venue"
},
  "geometry": {"coordinates":[-95.49494900000001,30.152896],"type":"Point"}
}