{
  "type": "Feature",
  "properties": {
    "iso:country":"US",
    "sg:address":"629 NW 6th St",
    "sg:city":"Tulia",
    "sg:classifiers":[
        {
            "category":"Personal",
            "subcategory":"Beauty Salon",
            "type":"Services"
        }
    ],
    "sg:phone":"+1 806 995 4247",
    "sg:postcode":"79088",
    "sg:province":"TX",
    "sg:tags":[
        "shop",
        "barber"
    ],
    "wof:name":"Kut Hut The",
    "wof:placetype":"venue"
},
  "geometry": {"coordinates":[-101.772114,34.543762],"type":"Point"}
}