{
  "type": "Feature",
  "properties": {
    "iso:country":"US",
    "sg:address":"2302 W Walnut Hill Ln",
    "sg:city":"Irving",
    "sg:classifiers":[
        {
            "category":"Food & Beverages",
            "subcategory":"Groceries & Convenience Stores",
            "type":"Retail Goods"
        }
    ],
    "sg:phone":"+1 214 596 0869",
    "sg:postcode":"75038",
    "sg:province":"TX",
    "wof:name":"Quix",
    "wof:placetype":"venue"
},
  "geometry": {"coordinates":[-96.979179,32.866465],"type":"Point"}
}