{
  "type": "Feature",
  "properties": {
    "iso:country":"US",
    "sg:address":"558 Silicon Dr Ste 101",
    "sg:city":"Southlake",
    "sg:classifiers":[
        {
            "category":"Professional",
            "subcategory":"Computer Services",
            "type":"Services"
        }
    ],
    "sg:phone":"+1 214 432 7920",
    "sg:postcode":"76092",
    "sg:province":"TX",
    "sg:tags":[
        "publisher",
        "software",
        "developer",
        "services-wholesale"
    ],
    "sg:website":"http://www.intellimagic.net",
    "wof:name":"Intellimagic, Inc.",
    "wof:placetype":"venue"
},
  "geometry": {"coordinates":[-97.110389,32.934922],"type":"Point"}
}