{
  "type": "Feature",
  "properties": {
    "iso:country":"US",
    "sg:address":"1200 Miller Ave",
    "sg:city":"Fort Worth",
    "sg:classifiers":[
        {
            "category":"Professional",
            "subcategory":"Business Services",
            "type":"Services"
        }
    ],
    "sg:phone":"+1 817 535 0095",
    "sg:postcode":"76105",
    "sg:province":"TX",
    "wof:name":"Always Available Bail Bonds",
    "wof:placetype":"venue"
},
  "geometry": {"coordinates":[-97.262001,32.733265],"type":"Point"}
}