{
  "type": "Feature",
  "properties": {
    "iso:country":"US",
    "sg:address":"1507 Indian Shores Rd",
    "sg:city":"Crosby",
    "sg:classifiers":[
        {
            "category":"Autos & Motor Vehicles",
            "subcategory":"Automobile Sales",
            "type":"Retail Goods"
        }
    ],
    "sg:phone":"+1 281 324 2459",
    "sg:postcode":"77532",
    "sg:province":"TX",
    "sg:tags":[
        "used"
    ],
    "wof:name":"Star Bus Sales",
    "wof:placetype":"venue"
},
  "geometry": {"coordinates":[-95.11013800000001,29.972004],"type":"Point"}
}