{
  "type": "Feature",
  "properties": {
    "iso:country":"US",
    "sg:address":"4025 Griggs Rd",
    "sg:city":"Houston",
    "sg:classifiers":[
        {
            "category":"Government",
            "subcategory":"Post Office",
            "type":"Public Place"
        }
    ],
    "sg:phone":"+1 713 741 5506",
    "sg:postcode":"77021",
    "sg:province":"TX",
    "wof:name":"Foster Place Station",
    "wof:placetype":"venue"
},
  "geometry": {"coordinates":[-95.35539300000001,29.703945],"type":"Point"}
}