{
  "type": "Feature",
  "properties": {
    "iso:country":"US",
    "sg:address":"300 Pine Bluff St",
    "sg:city":"Paris",
    "sg:classifiers":[
        {
            "category":"Retail",
            "subcategory":"Auto Repair",
            "type":"Services"
        }
    ],
    "sg:phone":"+1 903 784 1646",
    "sg:postcode":"75460",
    "sg:province":"TX",
    "sg:tags":[
        "automobile",
        "lubrication",
        "automotive",
        "general"
    ],
    "wof:name":"Quick & E-Z Lube",
    "wof:placetype":"venue"
},
  "geometry": {"coordinates":[-95.55370000000001,33.664029],"type":"Point"}
}