{
  "type": "Feature",
  "properties": {
    "iso:country":"US",
    "sg:address":"2627 Rayburn Ridge Dr",
    "sg:city":"Katy",
    "sg:classifiers":[
        {
            "category":"Education",
            "subcategory":"Special Training",
            "type":"Public Place"
        }
    ],
    "sg:phone":"+1 281 615 5437",
    "sg:postcode":"77450",
    "sg:province":"TX",
    "wof:name":"Stretch-N-Grow Katy W Houston",
    "wof:placetype":"venue"
},
  "geometry": {"coordinates":[-95.73706900000001,29.744988],"type":"Point"}
}