{
  "type": "Feature",
  "properties": {
    "iso:country":"US",
    "sg:address":"2012 Agnes St",
    "sg:city":"Corpus Christi",
    "sg:classifiers":[
        {
            "category":"Organizations",
            "subcategory":"Religious Organization",
            "type":"Services"
        }
    ],
    "sg:phone":"+1 361 992 5104",
    "sg:postcode":"78405",
    "sg:province":"TX",
    "wof:name":"Faith Mission Otreach",
    "wof:placetype":"venue"
},
  "geometry": {"coordinates":[-97.412457,27.786978],"type":"Point"}
}