{
  "type": "Feature",
  "properties": {
    "iso:country":"US",
    "sg:address":"601 W Pinecrest Dr",
    "sg:city":"Marshall",
    "sg:classifiers":[
        {
            "category":"Professional",
            "subcategory":"Engineering",
            "type":"Services"
        }
    ],
    "sg:phone":"+1 903 935 9369",
    "sg:postcode":"75670",
    "sg:province":"TX",
    "sg:tags":[
        "engineer"
    ],
    "sg:website":"www.endeco.net",
    "wof:name":"Endeco Engineers Inc",
    "wof:placetype":"venue"
},
  "geometry": {"coordinates":[-94.373374,32.52676],"type":"Point"}
}