{
  "type": "Feature",
  "properties": {
    "iso:country":"US",
    "sg:address":"205 S Main St",
    "sg:city":"Elgin",
    "sg:classifiers":[
        {
            "category":"Personal",
            "subcategory":"Barber",
            "type":"Services"
        }
    ],
    "sg:phone":"+1 512 285 9445",
    "sg:postcode":"78621",
    "sg:province":"TX",
    "wof:name":"Torees Barber Shop",
    "wof:placetype":"venue"
},
  "geometry": {"coordinates":[-97.36967799999999,30.346014],"type":"Point"}
}