{
  "type": "Feature",
  "properties": {
    "iso:country":"US",
    "sg:address":"3336 Spring Stuebner Rd",
    "sg:city":"Spring",
    "sg:classifiers":[
        {
            "category":"Social Services",
            "subcategory":"Child Care",
            "type":"Services"
        },
        {
            "category":"Education",
            "subcategory":"Preschool",
            "type":"Public Place"
        }
    ],
    "sg:phone":"+1 281 907 7870",
    "sg:postcode":"77389",
    "sg:province":"TX",
    "sg:tags":[
        "school",
        "nursery",
        "day"
    ],
    "wof:name":"Growth and Guidance Child Development Center",
    "wof:placetype":"venue"
},
  "geometry": {"coordinates":[-95.467921,30.08264],"type":"Point"}
}