{
  "type": "Feature",
  "properties": {
    "iso:country":"US",
    "sg:address":"98 San Jacinto Blvd",
    "sg:city":"Austin",
    "sg:classifiers":[
        {
            "category":"Banks & Credit Unions",
            "subcategory":"Investment Brokerage",
            "type":"Services"
        }
    ],
    "sg:phone":"+1 512 498 4500",
    "sg:postcode":"78701",
    "sg:province":"TX",
    "sg:tags":[
        "advisory",
        "financial"
    ],
    "wof:name":"Duff & Boynton LLC",
    "wof:placetype":"venue"
},
  "geometry": {"coordinates":[-97.742204,30.262407],"type":"Point"}
}