{
  "type": "Feature",
  "properties": {
    "iso:country":"US",
    "sg:address":"7867 Willow Hill Ct",
    "sg:city":"Dallas",
    "sg:classifiers":[
        {
            "category":"Professional",
            "subcategory":"Management & Consulting",
            "type":"Services"
        }
    ],
    "sg:phone":"+1 214 369 1176",
    "sg:postcode":"75230",
    "sg:province":"TX",
    "sg:tags":[
        "consultant",
        "business"
    ],
    "wof:name":"Eland Concept",
    "wof:placetype":"venue"
},
  "geometry": {"coordinates":[-96.773218,32.882598],"type":"Point"}
}