{
  "type": "Feature",
  "properties": {
    "iso:country":"US",
    "sg:address":"14434 Bellaire Blvd",
    "sg:city":"Houston",
    "sg:classifiers":[
        {
            "category":"Social Services",
            "subcategory":"Child Care",
            "type":"Services"
        },
        {
            "category":"Education",
            "subcategory":"School",
            "type":"Public Place"
        }
    ],
    "sg:phone":"+1 281 498 6000",
    "sg:postcode":"77083",
    "sg:province":"TX",
    "sg:tags":[
        "montessori"
    ],
    "wof:name":"American Montessori School Inc",
    "wof:placetype":"venue"
},
  "geometry": {"coordinates":[-95.64041899999999,29.704073],"type":"Point"}
}