{
  "type": "Feature",
  "properties": {
    "iso:country":"US",
    "sg:address":"1903 Joe Stephens Ave",
    "sg:city":"Weslaco",
    "sg:classifiers":[
        {
            "category":"Wholesale",
            "subcategory":"Auto Parts",
            "type":"Manufacturing & Wholesale Goods"
        }
    ],
    "sg:phone":"+1 956 968 1913",
    "sg:postcode":"78596",
    "sg:province":"TX",
    "wof:name":"Payne R&D Center",
    "wof:placetype":"venue"
},
  "geometry": {"coordinates":[-97.96792600000001,26.175499],"type":"Point"}
}