{
  "type": "Feature",
  "properties": {
    "iso:country":"US",
    "sg:address":"4365 Southmost Rd",
    "sg:city":"Brownsville",
    "sg:classifiers":[
        {
            "category":"Manufacturing",
            "subcategory":"Glass & Minerals",
            "type":"Manufacturing & Wholesale Goods"
        },
        {
            "category":"Retail",
            "subcategory":"Auto Repair",
            "type":"Services"
        }
    ],
    "sg:phone":"+1 956 544 4305",
    "sg:postcode":"78521",
    "sg:province":"TX",
    "sg:tags":[
        "plate",
        "window",
        "windshield",
        "glass-auto"
    ],
    "wof:name":"Auto Glass Ramirez",
    "wof:placetype":"venue"
},
  "geometry": {"coordinates":[-97.44916499999999,25.895942],"type":"Point"}
}