{
  "type": "Feature",
  "properties": {
    "iso:country":"US",
    "sg:address":"678 N Glenville Dr",
    "sg:city":"Richardson",
    "sg:classifiers":[
        {
            "category":"Shopping",
            "subcategory":"Stationery & Office Supplies",
            "type":"Retail Goods"
        }
    ],
    "sg:phone":"+1 972 238 5247",
    "sg:postcode":"75081",
    "sg:province":"TX",
    "sg:tags":[
        "educational",
        "material"
    ],
    "sg:website":"www.mathusee.com",
    "wof:name":"Math U See",
    "wof:placetype":"venue"
},
  "geometry": {"coordinates":[-96.70527199999999,32.956572],"type":"Point"}
}