{
  "type": "Feature",
  "properties": {
    "iso:country":"US",
    "sg:address":"806 S Ave F",
    "sg:city":"Haskell",
    "sg:phone":"+1 940 864 3452",
    "sg:postcode":"79521",
    "sg:province":"TX",
    "sg:tags":[
        "farm",
        "cotton"
    ],
    "wof:name":"Acosta Farm",
    "wof:placetype":"venue"
},
  "geometry": {"coordinates":[-99.73541299999999,33.14939],"type":"Point"}
}