{
  "type": "Feature",
  "properties": {
    "iso:country":"US",
    "sg:address":"1112 N Greenville Ave",
    "sg:city":"Allen",
    "sg:classifiers":[
        {
            "category":"Restaurant",
            "type":"Food & Drink"
        }
    ],
    "sg:menulink":"http://www.allmenus.com/tx/plano/147166-grandys/menu/",
    "sg:phone":"+1 972 747 8289",
    "sg:postcode":"75002",
    "sg:province":"TX",
    "sg:tags":[
        "american"
    ],
    "wof:name":"Grandy's",
    "wof:placetype":"venue"
},
  "geometry": {"coordinates":[-96.65319700000001,33.114104],"type":"Point"}
}