{
  "type": "Feature",
  "properties": {
    "iso:country":"US",
    "sg:address":"3450 W Camp Wisdom Rd",
    "sg:city":"Dallas",
    "sg:classifiers":[
        {
            "category":"Health Services",
            "subcategory":"Optometrist",
            "type":"Services"
        }
    ],
    "sg:phone":"+1 972 283 9117",
    "sg:postcode":"75237",
    "sg:province":"TX",
    "wof:name":"Primary Eye Care",
    "wof:placetype":"venue"
},
  "geometry": {"coordinates":[-96.87577400000001,32.662402],"type":"Point"}
}