{
  "type": "Feature",
  "properties": {
    "iso:country":"US",
    "sg:address":"24802 Birdie Ridge",
    "sg:city":"San Antonio",
    "sg:classifiers":[
        {
            "category":"Building & Trades",
            "subcategory":"Construction",
            "type":"Services"
        }
    ],
    "sg:phone":"+1 210 408 6511",
    "sg:postcode":"78258",
    "sg:province":"TX",
    "sg:tags":[
        "home",
        "builder"
    ],
    "wof:name":"Mc Nair & Co Model Homes",
    "wof:placetype":"venue"
},
  "geometry": {"coordinates":[-98.4791,29.669779],"type":"Point"}
}