{
  "type": "Feature",
  "properties": {
    "iso:country":"US",
    "sg:address":"5309 Village Creek Dr",
    "sg:city":"Plano",
    "sg:classifiers":[
        {
            "category":"Real Estate",
            "subcategory":"Real Estate Agent",
            "type":"Services"
        }
    ],
    "sg:phone":"+1 972 385 7821",
    "sg:postcode":"75093",
    "sg:province":"TX",
    "wof:name":"Anz Co",
    "wof:placetype":"venue"
},
  "geometry": {"coordinates":[-96.806603,33.014142],"type":"Point"}
}