{
  "type": "Feature",
  "properties": {
    "iso:country":"US",
    "sg:address":"2202 Grant St",
    "sg:city":"Laredo",
    "sg:classifiers":[
        {
            "category":"Building & Trades",
            "subcategory":"Construction",
            "type":"Services"
        }
    ],
    "sg:phone":"+1 956 753 0000",
    "sg:postcode":"78040",
    "sg:province":"TX",
    "sg:tags":[
        "maker",
        "cabinet"
    ],
    "wof:name":"Montemayor Industries",
    "wof:placetype":"venue"
},
  "geometry": {"coordinates":[-99.51823,27.502999],"type":"Point"}
}