{
  "type": "Feature",
  "properties": {
    "iso:country":"US",
    "sg:address":"5817 E FM 1585",
    "sg:city":"Slaton",
    "sg:phone":"+1 806 748 1197",
    "sg:postcode":"79364",
    "sg:province":"TX",
    "sg:tags":[
        "farm",
        "cotton"
    ],
    "wof:name":"Kelly Kitchens",
    "wof:placetype":"venue"
},
  "geometry": {"coordinates":[-101.73005499999999,33.476662],"type":"Point"}
}