{
  "type": "Feature",
  "properties": {
    "iso:country":"US",
    "sg:address":"1343 W Lullwood Ave",
    "sg:city":"San Antonio",
    "sg:classifiers":[
        {
            "category":"Shopping",
            "subcategory":"Gifts & Souvenirs",
            "type":"Retail Goods"
        }
    ],
    "sg:phone":"+1 210 737 8008",
    "sg:postcode":"78201",
    "sg:province":"TX",
    "sg:tags":[
        "personal",
        "motion"
    ],
    "wof:name":"J & L Productions",
    "wof:placetype":"venue"
},
  "geometry": {"coordinates":[-98.51811600000001,29.465788],"type":"Point"}
}