{
  "type": "Feature",
  "properties": {
    "iso:country":"US",
    "sg:address":"2635 Johnson Ave",
    "sg:city":"San Angelo",
    "sg:classifiers":[
        {
            "category":"Home & Garden",
            "subcategory":"Carpets & Floor Coverings",
            "type":"Retail Goods"
        }
    ],
    "sg:phone":"+1 325 942 6195",
    "sg:postcode":"76904",
    "sg:province":"TX",
    "sg:tags":[
        "material"
    ],
    "wof:name":"Smith Floors",
    "wof:placetype":"venue"
},
  "geometry": {"coordinates":[-100.463121,31.433478],"type":"Point"}
}