{
  "type": "Feature",
  "properties": {
    "iso:country":"US",
    "sg:address":"3000 N Main St",
    "sg:city":"Baytown",
    "sg:classifiers":[
        {
            "category":"Building & Trades",
            "subcategory":"Construction",
            "type":"Services"
        }
    ],
    "sg:phone":"+1 281 422 8488",
    "sg:postcode":"77521",
    "sg:province":"TX",
    "sg:tags":[
        "home",
        "builder"
    ],
    "wof:name":"Bayshore Builders Inc",
    "wof:placetype":"venue"
},
  "geometry": {"coordinates":[-94.963784,29.754917],"type":"Point"}
}