{
  "type": "Feature",
  "properties": {
    "iso:country":"US",
    "sg:address":"5955 Highland Hills Drive",
    "sg:city":"Austin",
    "sg:classifiers":[
        {
            "category":"Personal",
            "type":"Services"
        }
    ],
    "sg:phone":"+1 512 328 1040",
    "sg:postcode":"78731",
    "sg:province":"TX",
    "sg:tags":[
        "local"
    ],
    "wof:name":"Dream Catcher Ventures, LLC",
    "wof:placetype":"venue"
},
  "geometry": {"coordinates":[-97.757131,30.347359],"type":"Point"}
}