{
  "type": "Feature",
  "properties": {
    "iso:country":"US",
    "sg:address":"405 N Adams St",
    "sg:city":"Carthage",
    "sg:classifiers":[
        {
            "category":"Building & Trades",
            "subcategory":"Plumbing",
            "type":"Services"
        }
    ],
    "sg:phone":"+1 903 693 8403",
    "sg:postcode":"75633",
    "sg:province":"TX",
    "sg:tags":[
        "sheet",
        "work",
        "metal",
        "contractor"
    ],
    "wof:name":"Allred Sheet Metal",
    "wof:placetype":"venue"
},
  "geometry": {"coordinates":[-94.351783,32.159836],"type":"Point"}
}