{
  "type": "Feature",
  "properties": {
    "iso:country":"US",
    "sg:address":"4236 Valentine St",
    "sg:city":"Fort Worth",
    "sg:classifiers":[
        {
            "category":"Building & Trades",
            "subcategory":"Landscaping Services",
            "type":"Services"
        }
    ],
    "sg:phone":"+1 817 732 1946",
    "sg:postcode":"76107",
    "sg:province":"TX",
    "wof:name":"Morris Tree Service",
    "wof:placetype":"venue"
},
  "geometry": {"coordinates":[-97.38074400000001,32.726992],"type":"Point"}
}