{
  "type": "Feature",
  "properties": {
    "iso:country":"US",
    "sg:address":"1427 N Gary Ave",
    "sg:city":"Lubbock",
    "sg:classifiers":[
        {
            "category":"Manufacturing",
            "subcategory":"Wood Products",
            "type":"Manufacturing & Wholesale Goods"
        },
        {
            "category":"Home & Garden",
            "subcategory":"Home Furnishings",
            "type":"Retail Goods"
        },
        {
            "category":"Home & Garden",
            "subcategory":"Building Materials",
            "type":"Retail Goods"
        },
        {
            "category":"Building & Trades",
            "subcategory":"Construction",
            "type":"Services"
        },
        {
            "category":"Manufacturing",
            "subcategory":"Building Materials",
            "type":"Manufacturing & Wholesale Goods"
        }
    ],
    "sg:phone":"+1 806 745 2327",
    "sg:postcode":"79415",
    "sg:province":"TX",
    "sg:tags":[
        "industrial",
        "maker",
        "cabinetmakers-commercial",
        "counter",
        "cabinet",
        "refacing",
        "resurfacing",
        "millwork",
        "top",
        "cabinets-refinishing",
        "kitchen"
    ],
    "wof:name":"T & S Millworks",
    "wof:placetype":"venue"
},
  "geometry": {"coordinates":[-101.883241,33.614383],"type":"Point"}
}