{
  "type": "Feature",
  "properties": {
    "iso:country":"US",
    "sg:address":"809 Harris Ave",
    "sg:city":"Pasadena",
    "sg:classifiers":[
        {
            "category":"Personal",
            "subcategory":"Beauty Salon",
            "type":"Services"
        }
    ],
    "sg:phone":"+1 713 534 0200",
    "sg:postcode":"77506",
    "sg:province":"TX",
    "sg:tags":[
        "shop"
    ],
    "wof:name":"Shapes Hair Studio",
    "wof:placetype":"venue"
},
  "geometry": {"coordinates":[-95.20322899999999,29.698233],"type":"Point"}
}