{
  "type": "Feature",
  "properties": {
    "iso:country":"US",
    "sg:address":"1135 Barton Hills Dr #149",
    "sg:city":"Austin",
    "sg:classifiers":[
        {
            "category":"Communications",
            "type":"Services"
        }
    ],
    "sg:phone":"+1 512 553 0331",
    "sg:postcode":"78704",
    "sg:province":"TX",
    "sg:tags":[
        "web",
        "design"
    ],
    "sg:website":"www.sundrystudio.com",
    "wof:name":"Sundry Studio",
    "wof:placetype":"venue"
},
  "geometry": {"coordinates":[-97.77265800000001,30.261744],"type":"Point"}
}