{
  "type": "Feature",
  "properties": {
    "iso:country":"US",
    "sg:address":"14515 Bois D Arc Ln",
    "sg:city":"Manor",
    "sg:classifiers":[
        {
            "category":"Shopping",
            "subcategory":"Jewelry",
            "type":"Retail Goods"
        }
    ],
    "sg:phone":"+1 512 272 4898",
    "sg:postcode":"78653",
    "sg:province":"TX",
    "wof:name":"Gold S Jewelry",
    "wof:placetype":"venue"
},
  "geometry": {"coordinates":[-97.50210300000001,30.375447],"type":"Point"}
}