{
  "type": "Feature",
  "properties": {
    "iso:country":"US",
    "sg:address":"2430 S I- 35 E",
    "sg:city":"Denton",
    "sg:classifiers":[
        {
            "category":"Restaurant",
            "type":"Food & Drink"
        }
    ],
    "sg:phone":"+1 940 891 2627",
    "sg:postcode":"76205",
    "sg:province":"TX",
    "sg:website":"www.bigtimeatbobsburgers.com",
    "wof:name":"Big Time At Bob's Burgers",
    "wof:placetype":"venue"
},
  "geometry": {"coordinates":[-97.106639,33.184903],"type":"Point"}
}