{
  "type": "Feature",
  "properties": {
    "iso:country":"US",
    "sg:address":"6215 Lafayette Way",
    "sg:city":"Dallas",
    "sg:classifiers":[
        {
            "category":"Wholesale",
            "subcategory":"Jewelry",
            "type":"Manufacturing & Wholesale Goods"
        }
    ],
    "sg:phone":"+1 214 748 8909",
    "sg:postcode":"75230",
    "sg:province":"TX",
    "sg:tags":[
        "stone"
    ],
    "wof:name":"Art In Jade",
    "wof:placetype":"venue"
},
  "geometry": {"coordinates":[-96.797597,32.920579],"type":"Point"}
}