{
  "type": "Feature",
  "properties": {
    "iso:country":"US",
    "sg:address":"811 Thrasher Dr",
    "sg:city":"San Antonio",
    "sg:classifiers":[
        {
            "category":"Communications",
            "subcategory":"Film & Video Production",
            "type":"Services"
        }
    ],
    "sg:phone":"+1 210 823 7082",
    "sg:postcode":"78245",
    "sg:province":"TX",
    "sg:tags":[
        "motion"
    ],
    "wof:name":"Foot In Door Productions",
    "wof:placetype":"venue"
},
  "geometry": {"coordinates":[-98.682056,29.43019],"type":"Point"}
}