{
  "type": "Feature",
  "properties": {
    "iso:country":"US",
    "sg:address":"8700 Brodie Ln",
    "sg:city":"Austin",
    "sg:classifiers":[
        {
            "category":"Professional",
            "subcategory":"Computer Services",
            "type":"Services"
        }
    ],
    "sg:phone":"+1 512 470 3797",
    "sg:postcode":"78745",
    "sg:province":"TX",
    "sg:tags":[
        "repair"
    ],
    "sg:website":"www.txcountrypc.com",
    "wof:name":"TX Country PC",
    "wof:placetype":"venue"
},
  "geometry": {"coordinates":[-97.841194,30.197116],"type":"Point"}
}