{
  "type": "Feature",
  "properties": {
    "iso:country":"US",
    "sg:address":"8217 Greenwood Dr",
    "sg:city":"Plano",
    "sg:classifiers":[
        {
            "category":"Professional",
            "type":"Services"
        }
    ],
    "sg:phone":"+1 972 396 7586",
    "sg:postcode":"75025",
    "sg:province":"TX",
    "wof:name":"Candy World",
    "wof:placetype":"venue"
},
  "geometry": {"coordinates":[-96.745861,33.088983],"type":"Point"}
}