{
  "type": "Feature",
  "properties": {
    "iso:country":"US",
    "sg:address":"3802 S Flores St",
    "sg:city":"San Antonio",
    "sg:classifiers":[
        {
            "category":"Retail",
            "subcategory":"Auto Repair",
            "type":"Services"
        }
    ],
    "sg:phone":"+1 210 738 8422",
    "sg:postcode":"78214",
    "sg:province":"TX",
    "sg:tags":[
        "general"
    ],
    "wof:name":"Cerified Auto Refinishing",
    "wof:placetype":"venue"
},
  "geometry": {"coordinates":[-98.503202,29.386206],"type":"Point"}
}