{
  "type": "Feature",
  "properties": {
    "iso:country":"US",
    "sg:address":"5931 Northgap Dr",
    "sg:city":"San Antonio",
    "sg:classifiers":[
        {
            "category":"Manufacturing",
            "subcategory":"Retail Goods",
            "type":"Manufacturing & Wholesale Goods"
        }
    ],
    "sg:phone":"+1 210 656 0392",
    "sg:postcode":"78239",
    "sg:province":"TX",
    "sg:tags":[
        "lead",
        "mfg"
    ],
    "wof:name":"Joe Tye Artist",
    "wof:placetype":"venue"
},
  "geometry": {"coordinates":[-98.37351099999999,29.52608],"type":"Point"}
}