{
  "type": "Feature",
  "properties": {
    "iso:country":"US",
    "sg:address":"6300 Corporate Dr",
    "sg:city":"Houston",
    "sg:classifiers":[
        {
            "category":"Real Estate",
            "subcategory":"Real Estate Agent",
            "type":"Services"
        }
    ],
    "sg:phone":"+1 713 995 4324",
    "sg:postcode":"77036",
    "sg:province":"TX",
    "sg:tags":[
        "authorities",
        "housing"
    ],
    "wof:name":"Housing Corp Of Greater Houstn",
    "wof:placetype":"venue"
},
  "geometry": {"coordinates":[-95.551597,29.710023],"type":"Point"}
}