{
  "type": "Feature",
  "properties": {
    "iso:country":"US",
    "sg:address":"1629 Richey St",
    "sg:city":"Pasadena",
    "sg:classifiers":[
        {
            "category":"Restaurant",
            "type":"Food & Drink"
        }
    ],
    "sg:phone":"+1 713 473 2808",
    "sg:postcode":"77502",
    "sg:province":"TX",
    "wof:name":"Taqueria Arandas",
    "wof:placetype":"venue"
},
  "geometry": {"coordinates":[-95.22080200000001,29.687201],"type":"Point"}
}