{
  "type": "Feature",
  "properties": {
    "iso:country":"US",
    "sg:address":"2921 N Alexander Dr",
    "sg:city":"Baytown",
    "sg:classifiers":[
        {
            "category":"Professional",
            "type":"Services"
        }
    ],
    "sg:phone":"+1 281 428 8979",
    "sg:postcode":"77520",
    "sg:province":"TX",
    "sg:tags":[
        "pipe",
        "equipment",
        "line"
    ],
    "wof:name":"J & B Pipeline Supply Co Inc",
    "wof:placetype":"venue"
},
  "geometry": {"coordinates":[-94.94337299999999,29.754401],"type":"Point"}
}