{
  "type": "Feature",
  "properties": {
    "iso:country":"US",
    "sg:address":"1830 S Travis Ave",
    "sg:city":"Denison",
    "sg:classifiers":[
        {
            "category":"Farming",
            "subcategory":"Livestock Farm",
            "type":"Manufacturing & Wholesale Goods"
        }
    ],
    "sg:phone":"+1 903 465 5050",
    "sg:postcode":"75021",
    "sg:province":"TX",
    "sg:tags":[
        "beef",
        "feedlot",
        "cattle"
    ],
    "wof:name":"Randy Reid",
    "wof:placetype":"venue"
},
  "geometry": {"coordinates":[-96.531138,33.738056],"type":"Point"}
}