{
  "type": "Feature",
  "properties": {
    "iso:country":"US",
    "sg:address":"1971 West TC Jester",
    "sg:city":"Houston",
    "sg:classifiers":[
        {
            "category":"Bars & Pubs",
            "subcategory":"Sports Bar",
            "type":"Food & Drink"
        }
    ],
    "sg:phone":"+1 713 864 3944",
    "sg:postcode":"77008",
    "sg:province":"TX",
    "sg:website":"www.tbonessportspub.com/",
    "wof:name":"T-Bones Sports Pub",
    "wof:placetype":"venue"
},
  "geometry": {"coordinates":[-95.432321,29.802695],"type":"Point"}
}