{
  "type": "Feature",
  "properties": {
    "iso:country":"US",
    "sg:address":"4921 Garth Rd",
    "sg:city":"Baytown",
    "sg:classifiers":[
        {
            "category":"Food & Beverages",
            "subcategory":"Groceries & Convenience Stores",
            "type":"Retail Goods"
        }
    ],
    "sg:phone":"+1 281 421 1948",
    "sg:postcode":"77521",
    "sg:province":"TX",
    "sg:tags":[
        "station",
        "gasoline"
    ],
    "wof:name":"Diamond Shamrock",
    "wof:placetype":"venue"
},
  "geometry": {"coordinates":[-94.97775300000001,29.77585],"type":"Point"}
}