{
  "type": "Feature",
  "properties": {
    "iso:country":"US",
    "sg:address":"3775 Stagg Dr",
    "sg:city":"Beaumont",
    "sg:classifiers":[
        {
            "category":"Banks & Credit Unions",
            "subcategory":"Investment Brokerage",
            "type":"Services"
        }
    ],
    "sg:phone":"+1 409 835 5854",
    "sg:postcode":"77701",
    "sg:province":"TX",
    "sg:tags":[
        "advisory",
        "financial"
    ],
    "wof:name":"Southeast Texas Financial Edu",
    "wof:placetype":"venue"
},
  "geometry": {"coordinates":[-94.13185,30.069986],"type":"Point"}
}