{
  "type": "Feature",
  "properties": {
    "iso:country":"US",
    "sg:address":"1090 San Jacinto Mall",
    "sg:city":"Baytown",
    "sg:classifiers":[
        {
            "category":"Cinema",
            "subcategory":"Movie Rental",
            "type":"Entertainment"
        }
    ],
    "sg:phone":"+1 281 421 2574",
    "sg:postcode":"77521",
    "sg:province":"TX",
    "sg:tags":[
        "video",
        "tape"
    ],
    "wof:name":"Blockbuster",
    "wof:placetype":"venue"
},
  "geometry": {"coordinates":[-94.984424,29.803647],"type":"Point"}
}