{
  "type": "Feature",
  "properties": {
    "iso:country":"US",
    "sg:address":"916 International Blvd",
    "sg:city":"Hidalgo",
    "sg:classifiers":[
        {
            "category":"Banks & Credit Unions",
            "subcategory":"Bank",
            "type":"Services"
        }
    ],
    "sg:phone":"+1 956 843 8353",
    "sg:postcode":"78557",
    "sg:province":"TX",
    "sg:tags":[
        "broker",
        "foreign",
        "dealer",
        "exchange"
    ],
    "wof:name":"Casa De Cambio Reynosa",
    "wof:placetype":"venue"
},
  "geometry": {"coordinates":[-98.269316,26.098916],"type":"Point"}
}