{
  "type": "Feature",
  "properties": {
    "iso:country":"US",
    "sg:address":"3320 N Hampton Rd",
    "sg:city":"Dallas",
    "sg:classifiers":[
        {
            "category":"Shopping",
            "subcategory":"Gifts & Souvenirs",
            "type":"Retail Goods"
        }
    ],
    "sg:phone":"+1 214 638 4797",
    "sg:postcode":"75212",
    "sg:province":"TX",
    "wof:name":"Holiday Preminum Foods",
    "wof:placetype":"venue"
},
  "geometry": {"coordinates":[-96.856427,32.78377],"type":"Point"}
}