{
  "type": "Feature",
  "properties": {
    "iso:country":"US",
    "sg:address":"6745 Harrisburg Blvd",
    "sg:city":"Houston",
    "sg:classifiers":[
        {
            "category":"Banks & Credit Unions",
            "subcategory":"Bank",
            "type":"Services"
        }
    ],
    "sg:phone":"+1 713 921 8301",
    "sg:postcode":"77011",
    "sg:province":"TX",
    "wof:name":"JPMorgan Chase & Co",
    "wof:placetype":"venue"
},
  "geometry": {"coordinates":[-95.307327,29.737397],"type":"Point"}
}