{
  "type": "Feature",
  "properties": {
    "iso:country":"US",
    "sg:address":"6015 S General Bruce Dr",
    "sg:city":"Temple",
    "sg:classifiers":[
        {
            "category":"Autos & Motor Vehicles",
            "subcategory":"Automobile Sales",
            "type":"Retail Goods"
        }
    ],
    "sg:phone":"+1 254 933 2860",
    "sg:postcode":"76502",
    "sg:province":"TX",
    "sg:tags":[
        "car",
        "dealer"
    ],
    "wof:name":"Auto Trends",
    "wof:placetype":"venue"
},
  "geometry": {"coordinates":[-97.416366,31.076283],"type":"Point"}
}