{
  "type": "Feature",
  "properties": {
    "iso:country":"US",
    "sg:address":"1310 Payne Ave",
    "sg:city":"Austin",
    "sg:classifiers":[
        {
            "category":"Education",
            "subcategory":"Special Training",
            "type":"Public Place"
        }
    ],
    "sg:phone":"+1 512 371 1441",
    "sg:postcode":"78757",
    "sg:province":"TX",
    "sg:tags":[
        "school",
        "language"
    ],
    "wof:name":"Mariposa Spanish School",
    "wof:placetype":"venue"
},
  "geometry": {"coordinates":[-97.72792,30.335104],"type":"Point"}
}