{
  "type": "Feature",
  "properties": {
    "iso:country":"US",
    "sg:address":"1007 Round Rock Ave",
    "sg:city":"Round Rock",
    "sg:classifiers":[
        {
            "category":"Professional",
            "subcategory":"Lawyer & Legal Services",
            "type":"Services"
        }
    ],
    "sg:phone":"+1 512 341 2277",
    "sg:postcode":"78681",
    "sg:province":"TX",
    "sg:tags":[
        "attorney"
    ],
    "wof:name":"Kristine Warren Law Office",
    "wof:placetype":"venue"
},
  "geometry": {"coordinates":[-97.693253,30.511645],"type":"Point"}
}