{
  "type": "Feature",
  "properties": {
    "iso:country":"US",
    "sg:address":"1301 McKinney St",
    "sg:city":"Houston",
    "sg:classifiers":[
        {
            "category":"Utilities",
            "subcategory":"Electric",
            "type":"Services"
        }
    ],
    "sg:phone":"+1 713 222 6080",
    "sg:postcode":"77010",
    "sg:province":"TX",
    "sg:tags":[
        "company"
    ],
    "sg:website":"www.newenergy.com",
    "wof:name":"CONSTELLATION New Energy Inc",
    "wof:placetype":"venue"
},
  "geometry": {"coordinates":[-95.36146599999999,29.75487],"type":"Point"}
}