{
  "type": "Feature",
  "properties": {
    "iso:country":"US",
    "sg:address":"12529 Carlos Bombach Ave",
    "sg:city":"El Paso",
    "sg:classifiers":[
        {
            "category":"Building & Trades",
            "subcategory":"Electrical",
            "type":"Services"
        }
    ],
    "sg:phone":"+1 915 857 2385",
    "sg:postcode":"79928",
    "sg:province":"TX",
    "sg:tags":[
        "electrical",
        "contractor"
    ],
    "wof:name":"Garcia Electric",
    "wof:placetype":"venue"
},
  "geometry": {"coordinates":[-106.254363,31.759605],"type":"Point"}
}