{
  "type": "Feature",
  "properties": {
    "iso:country":"US",
    "sg:address":"6143 Goliad Ave",
    "sg:city":"Dallas",
    "sg:classifiers":[
        {
            "category":"Education",
            "subcategory":"Special Training",
            "type":"Public Place"
        }
    ],
    "sg:phone":"+1 214 828 1745",
    "sg:postcode":"75214",
    "sg:province":"TX",
    "sg:tags":[
        "instrument",
        "musical"
    ],
    "wof:name":"Goliad Music Instruction",
    "wof:placetype":"venue"
},
  "geometry": {"coordinates":[-96.759709,32.81824],"type":"Point"}
}