{
  "type": "Feature",
  "properties": {
    "iso:country":"US",
    "sg:address":"1617 Charles Owens Dr",
    "sg:city":"El Paso",
    "sg:classifiers":[
        {
            "category":"Professional",
            "type":"Services"
        }
    ],
    "sg:phone":"+1 915 595 4668",
    "sg:postcode":"79936",
    "sg:province":"TX",
    "sg:tags":[
        "establishment"
    ],
    "wof:name":"International Hides & Skins",
    "wof:placetype":"venue"
},
  "geometry": {"coordinates":[-106.313514,31.755755],"type":"Point"}
}