{
  "type": "Feature",
  "properties": {
    "iso:country":"US",
    "sg:address":"6800 Hart Ln",
    "sg:city":"Austin",
    "sg:classifiers":[
        {
            "category":"Professional",
            "type":"Services"
        }
    ],
    "sg:phone":"+1 512 345 5913",
    "sg:postcode":"78731",
    "sg:province":"TX",
    "wof:name":"Mercury Distributing",
    "wof:placetype":"venue"
},
  "geometry": {"coordinates":[-97.757251,30.350523],"type":"Point"}
}