{
  "type": "Feature",
  "properties": {
    "iso:country":"US",
    "sg:address":"1205 N 12th St",
    "sg:city":"Alamo",
    "sg:classifiers":[
        {
            "category":"Building & Trades",
            "subcategory":"Construction",
            "type":"Services"
        }
    ],
    "sg:phone":"+1 956 783 8900",
    "sg:postcode":"78516",
    "sg:province":"TX",
    "sg:tags":[
        "general",
        "contractor"
    ],
    "wof:name":"RGF Construction",
    "wof:placetype":"venue"
},
  "geometry": {"coordinates":[-98.123167,26.199285],"type":"Point"}
}