{
  "type": "Feature",
  "properties": {
    "iso:country":"US",
    "sg:address":"606 E North Main St",
    "sg:city":"Flatonia",
    "sg:classifiers":[
        {
            "category":"Building & Trades",
            "subcategory":"Construction",
            "type":"Services"
        }
    ],
    "sg:phone":"+1 361 865 3450",
    "sg:postcode":"78941",
    "sg:province":"TX",
    "sg:tags":[
        "general",
        "contractor"
    ],
    "wof:name":"Kenneth Ponder Construction",
    "wof:placetype":"venue"
},
  "geometry": {"coordinates":[-97.100624,29.687804],"type":"Point"}
}