{
  "type": "Feature",
  "properties": {
    "iso:country":"US",
    "sg:address":"202 50th St",
    "sg:city":"Lubbock",
    "sg:classifiers":[
        {
            "category":"Food & Beverages",
            "subcategory":"Groceries & Convenience Stores",
            "type":"Retail Goods"
        }
    ],
    "sg:phone":"+1 806 763 0360",
    "sg:postcode":"79404",
    "sg:province":"TX",
    "sg:website":"www.townandcountry.com",
    "wof:name":"Town & Country Food Store 206",
    "wof:placetype":"venue"
},
  "geometry": {"coordinates":[-101.83801200000001,33.548758],"type":"Point"}
}