{
  "type": "Feature",
  "properties": {
    "iso:country":"US",
    "sg:address":"2419 Cloud Peak Ln",
    "sg:city":"Round Rock",
    "sg:classifiers":[
        {
            "category":"Professional",
            "subcategory":"Management & Consulting",
            "type":"Services"
        }
    ],
    "sg:phone":"+1 512 238 6579",
    "sg:postcode":"78681",
    "sg:province":"TX",
    "sg:tags":[
        "business"
    ],
    "wof:name":"Viraat Inc",
    "wof:placetype":"venue"
},
  "geometry": {"coordinates":[-97.71850499999999,30.516215],"type":"Point"}
}