{
  "type": "Feature",
  "properties": {
    "iso:country":"US",
    "sg:address":"12335 Kingslake Forest Dr",
    "sg:city":"Houston",
    "sg:classifiers":[
        {
            "category":"Professional",
            "type":"Services"
        }
    ],
    "sg:phone":"+1 281 459 1511",
    "sg:postcode":"77044",
    "sg:province":"TX",
    "wof:name":"United National Credit Service",
    "wof:placetype":"venue"
},
  "geometry": {"coordinates":[-95.22180299999999,29.899187],"type":"Point"}
}