{
  "type": "Feature",
  "properties": {
    "iso:country":"US",
    "sg:address":"4310 Westside Dr",
    "sg:city":"Dallas",
    "sg:classifiers":[
        {
            "category":"Real Estate",
            "subcategory":"Architect",
            "type":"Services"
        }
    ],
    "sg:phone":"+1 214 522 2887",
    "sg:postcode":"75209",
    "sg:province":"TX",
    "sg:tags":[
        "architectural"
    ],
    "wof:name":"Sally Johnson Architect",
    "wof:placetype":"venue"
},
  "geometry": {"coordinates":[-96.817502,32.823661],"type":"Point"}
}