{
  "type": "Feature",
  "properties": {
    "iso:country":"US",
    "sg:address":"1544 Tulane St",
    "sg:city":"Houston",
    "sg:classifiers":[
        {
            "category":"Professional",
            "type":"Services"
        }
    ],
    "sg:phone":"+1 713 869 1361",
    "sg:postcode":"77008",
    "sg:province":"TX",
    "wof:name":"J & V Services Inc",
    "wof:placetype":"venue"
},
  "geometry": {"coordinates":[-95.40235800000001,29.799012],"type":"Point"}
}