{
  "type": "Feature",
  "properties": {
    "iso:country":"US",
    "sg:address":"2701 Fondren Dr",
    "sg:city":"Dallas",
    "sg:classifiers":[
        {
            "category":"Home & Garden",
            "subcategory":"Furniture",
            "type":"Retail Goods"
        }
    ],
    "sg:phone":"+1 214 599 0266",
    "sg:postcode":"75206",
    "sg:province":"TX",
    "sg:tags":[
        "store"
    ],
    "wof:name":"Square One Furniture",
    "wof:placetype":"venue"
},
  "geometry": {"coordinates":[-96.77249999999999,32.844555],"type":"Point"}
}