{
  "type": "Feature",
  "properties": {
    "iso:country":"US",
    "sg:address":"31706 Spinnaker Run",
    "sg:city":"Magnolia",
    "sg:classifiers":[
        {
            "category":"Shopping",
            "subcategory":"Clothing, Apparel, & Fashions",
            "type":"Retail Goods"
        }
    ],
    "sg:phone":"+1 281 356 4747",
    "sg:postcode":"77354",
    "sg:province":"TX",
    "sg:tags":[
        "custom",
        "sport",
        "uniform"
    ],
    "wof:name":"Headsup Sports",
    "wof:placetype":"venue"
},
  "geometry": {"coordinates":[-95.64545699999999,30.197598],"type":"Point"}
}