{
  "type": "Feature",
  "properties": {
    "iso:country":"US",
    "sg:address":"7413 19th St",
    "sg:city":"Lubbock",
    "sg:classifiers":[
        {
            "category":"Building & Trades",
            "subcategory":"Construction",
            "type":"Services"
        }
    ],
    "sg:phone":"+1 806 788 0532",
    "sg:postcode":"79407",
    "sg:province":"TX",
    "sg:tags":[
        "house"
    ],
    "wof:name":"Absolute Construction",
    "wof:placetype":"venue"
},
  "geometry": {"coordinates":[-101.979686,33.577684],"type":"Point"}
}