{
  "type": "Feature",
  "properties": {
    "iso:country":"US",
    "sg:address":"200 Lone Star St",
    "sg:city":"Joshua",
    "sg:classifiers":[
        {
            "category":"Shopping",
            "subcategory":"Computers & Home Electronics",
            "type":"Retail Goods"
        }
    ],
    "sg:phone":"+1 817 343 9606",
    "sg:postcode":"76058",
    "sg:province":"TX",
    "sg:tags":[
        "audio"
    ],
    "wof:name":"Di Tech Audio Video & Hm Thtr",
    "wof:placetype":"venue"
},
  "geometry": {"coordinates":[-97.382177,32.457848],"type":"Point"}
}