{
  "type": "Feature",
  "properties": {
    "iso:country":"US",
    "sg:address":"215 N Harvey Mitchell Pkwy",
    "sg:city":"Bryan",
    "sg:classifiers":[
        {
            "category":"Real Estate",
            "subcategory":"Real Estate Agent",
            "type":"Services"
        }
    ],
    "sg:phone":"+1 979 823 8356",
    "sg:postcode":"77807",
    "sg:province":"TX",
    "wof:name":"Ellen M Weichert",
    "wof:placetype":"venue"
},
  "geometry": {"coordinates":[-96.376971,30.620973],"type":"Point"}
}