{
  "type": "Feature",
  "properties": {
    "iso:country":"US",
    "sg:address":"6823 Theall Rd",
    "sg:city":"Houston",
    "sg:classifiers":[
        {
            "category":"Utilities",
            "subcategory":"Natural Gas",
            "type":"Services"
        }
    ],
    "sg:phone":"+1 281 880 5200",
    "sg:postcode":"77066",
    "sg:province":"TX",
    "sg:tags":[
        "distribution",
        "company"
    ],
    "wof:name":"Louisiana Natural Gas Services",
    "wof:placetype":"venue"
},
  "geometry": {"coordinates":[-95.526053,29.964267],"type":"Point"}
}