{
  "type": "Feature",
  "properties": {
    "iso:country":"US",
    "sg:address":"441 State Hwy 46 W",
    "sg:city":"Boerne",
    "sg:classifiers":[
        {
            "category":"Shopping",
            "type":"Retail Goods"
        }
    ],
    "sg:phone":"+1 830 249 0303",
    "sg:postcode":"78006",
    "sg:province":"TX",
    "sg:tags":[
        "pet",
        "food",
        "supply"
    ],
    "wof:name":"Victoria's Exotic Aviary",
    "wof:placetype":"venue"
},
  "geometry": {"coordinates":[-98.79890399999999,29.755944],"type":"Point"}
}