{
  "type": "Feature",
  "properties": {
    "iso:country":"US",
    "sg:address":"2912 N Belt Line Rd",
    "sg:city":"Irving",
    "sg:classifiers":[
        {
            "category":"Manufacturing",
            "subcategory":"Furniture",
            "type":"Manufacturing & Wholesale Goods"
        }
    ],
    "sg:phone":"+1 972 252 2300",
    "sg:postcode":"75062",
    "sg:province":"TX",
    "sg:tags":[
        "fixture"
    ],
    "wof:name":"Fish Kabab & Curry",
    "wof:placetype":"venue"
},
  "geometry": {"coordinates":[-96.99222,32.847147],"type":"Point"}
}