{
  "type": "Feature",
  "properties": {
    "iso:country":"US",
    "sg:address":"5405 Andrews Hwy",
    "sg:city":"Odessa",
    "sg:classifiers":[
        {
            "category":"Wholesale",
            "subcategory":"Machinery & Supplies",
            "type":"Manufacturing & Wholesale Goods"
        }
    ],
    "sg:phone":"+1 432 366 0802",
    "sg:postcode":"79762",
    "sg:province":"TX",
    "sg:tags":[
        "equipment",
        "parts",
        "drilling",
        "repair"
    ],
    "wof:name":"Two Star Development Inc",
    "wof:placetype":"venue"
},
  "geometry": {"coordinates":[-102.38949100000001,31.896351],"type":"Point"}
}