{
  "type": "Feature",
  "properties": {
    "iso:country":"US",
    "sg:address":"13955 Murphy Rd",
    "sg:city":"Stafford",
    "sg:classifiers":[
        {
            "category":"Real Estate",
            "subcategory":"Real Estate Operator",
            "type":"Services"
        }
    ],
    "sg:phone":"+1 281 499 2509",
    "sg:postcode":"77477",
    "sg:province":"TX",
    "sg:tags":[
        "building",
        "parks"
    ],
    "wof:name":"Murphy Road Business Park",
    "wof:placetype":"venue"
},
  "geometry": {"coordinates":[-95.564592,29.620615],"type":"Point"}
}