{
  "type": "Feature",
  "properties": {
    "iso:country":"US",
    "sg:address":"5020 W US Hwy 83",
    "sg:city":"Mcallen",
    "sg:classifiers":[
        {
            "category":"Home & Garden",
            "subcategory":"Building Materials",
            "type":"Retail Goods"
        }
    ],
    "sg:phone":"+1 956 686 1762",
    "sg:postcode":"78501",
    "sg:province":"TX",
    "sg:tags":[
        "lumber"
    ],
    "wof:name":"Hope Lumber & Supply Co",
    "wof:placetype":"venue"
},
  "geometry": {"coordinates":[-98.275474,26.20944],"type":"Point"}
}