{
  "type": "Feature",
  "properties": {
    "iso:country":"US",
    "sg:address":"401 Bois Darc St",
    "sg:city":"Lockhart",
    "sg:classifiers":[
        {
            "category":"Education",
            "subcategory":"School",
            "type":"Public Place"
        }
    ],
    "sg:phone":"+1 512 398 0260",
    "sg:postcode":"78644",
    "sg:province":"TX",
    "sg:website":"www.lockhart.k12.tx.us",
    "wof:name":"Lockhart Special Education",
    "wof:placetype":"venue"
},
  "geometry": {"coordinates":[-97.676186,29.886743],"type":"Point"}
}