{
  "type": "Feature",
  "properties": {
    "iso:country":"US",
    "sg:address":"2209 Atkinson Dr",
    "sg:city":"Lufkin",
    "sg:classifiers":[
        {
            "category":"Freight",
            "type":"Transportation"
        }
    ],
    "sg:phone":"+1 936 639 8483",
    "sg:postcode":"75901",
    "sg:province":"TX",
    "sg:tags":[
        "storage"
    ],
    "wof:name":"A Atkinson Econo Storage Inc",
    "wof:placetype":"venue"
},
  "geometry": {"coordinates":[-94.701065,31.350931],"type":"Point"}
}