{
  "type": "Feature",
  "properties": {
    "iso:country":"US",
    "sg:address":"3010 S Rigsbee Dr",
    "sg:city":"Plano",
    "sg:classifiers":[
        {
            "category":"Retail",
            "subcategory":"Repair Shop",
            "type":"Services"
        }
    ],
    "sg:phone":"+1 972 422 7623",
    "sg:postcode":"75074",
    "sg:province":"TX",
    "wof:name":"Dees Trim Shop",
    "wof:placetype":"venue"
},
  "geometry": {"coordinates":[-96.67198399999999,33.015093],"type":"Point"}
}