{
  "type": "Feature",
  "properties": {
    "iso:country":"US",
    "sg:address":"9100 United Dr Ste 103",
    "sg:city":"Austin",
    "sg:classifiers":[
        {
            "category":"Building & Trades",
            "subcategory":"Cleaning & Sanitation",
            "type":"Services"
        }
    ],
    "sg:phone":"+1 512 832 8888",
    "sg:postcode":"78758",
    "sg:province":"TX",
    "sg:tags":[
        "home"
    ],
    "wof:name":"Clean As A Whistle",
    "wof:placetype":"venue"
},
  "geometry": {"coordinates":[-97.73123699999999,30.377009],"type":"Point"}
}