{
  "type": "Feature",
  "properties": {
    "iso:country":"US",
    "sg:address":"4130 Gaston Ave",
    "sg:city":"Dallas",
    "sg:classifiers":[
        {
            "category":"Restaurant",
            "type":"Food & Drink"
        }
    ],
    "sg:phone":"+1 214 828 1772",
    "sg:postcode":"75246",
    "sg:province":"TX",
    "sg:tags":[
        "pizza"
    ],
    "wof:name":"Divino's Pizzaria",
    "wof:placetype":"venue"
},
  "geometry": {"coordinates":[-96.77649700000001,32.794102],"type":"Point"}
}