{
  "type": "Feature",
  "properties": {
    "iso:country":"US",
    "sg:address":"3415 Cross Timbers Rd",
    "sg:city":"Flower Mound",
    "sg:classifiers":[
        {
            "category":"Organizations",
            "subcategory":"Religious Organization",
            "type":"Services"
        }
    ],
    "sg:phone":"+1 972 539 9341",
    "sg:postcode":"75028",
    "sg:province":"TX",
    "sg:tags":[
        "church"
    ],
    "sg:website":"www.fmcconline.org",
    "wof:name":"Flower Mound Community Church",
    "wof:placetype":"venue"
},
  "geometry": {"coordinates":[-97.082166,33.041462],"type":"Point"}
}