{
  "type": "Feature",
  "properties": {
    "iso:country":"US",
    "sg:address":"2533 Lucas Dr",
    "sg:city":"Dallas",
    "sg:classifiers":[
        {
            "category":"Organizations",
            "subcategory":"Community Association",
            "type":"Services"
        }
    ],
    "sg:phone":"+1 214 559 2556",
    "sg:postcode":"75219",
    "sg:province":"TX",
    "wof:name":"Cedar Springs Resident Council",
    "wof:placetype":"venue"
},
  "geometry": {"coordinates":[-96.821924,32.812231],"type":"Point"}
}