{
  "type": "Feature",
  "properties": {
    "iso:country":"US",
    "sg:address":"3121 W Orem Dr",
    "sg:city":"Houston",
    "sg:classifiers":[
        {
            "category":"Retail",
            "subcategory":"Laundry & Dry Cleaning",
            "type":"Services"
        }
    ],
    "sg:phone":"+1 713 433 0580",
    "sg:postcode":"77045",
    "sg:province":"TX",
    "wof:name":"Orem Dry Cleaners",
    "wof:placetype":"venue"
},
  "geometry": {"coordinates":[-95.421617,29.627851],"type":"Point"}
}