{
  "type": "Feature",
  "properties": {
    "iso:country":"US",
    "sg:address":"102 Dyna Dr",
    "sg:city":"Houston",
    "sg:classifiers":[
        {
            "category":"Food & Beverages",
            "subcategory":"Groceries & Convenience Stores",
            "type":"Retail Goods"
        }
    ],
    "sg:phone":"+1 281 272 5547",
    "sg:postcode":"77060",
    "sg:province":"TX",
    "wof:name":"Town Store Place No 2",
    "wof:placetype":"venue"
},
  "geometry": {"coordinates":[-95.40653,29.922335],"type":"Point"}
}