{
  "type": "Feature",
  "properties": {
    "iso:country":"US",
    "sg:address":"6039 45th St",
    "sg:city":"Lubbock",
    "sg:classifiers":[
        {
            "category":"Manufacturing",
            "subcategory":"Tools & Machinery",
            "type":"Manufacturing & Wholesale Goods"
        }
    ],
    "sg:phone":"+1 806 792 2493",
    "sg:postcode":"79407",
    "sg:province":"TX",
    "sg:tags":[
        "electric",
        "mfg"
    ],
    "wof:name":"Johnstone Supply",
    "wof:placetype":"venue"
},
  "geometry": {"coordinates":[-101.947292,33.553329],"type":"Point"}
}