{
  "type": "Feature",
  "properties": {
    "iso:country":"US",
    "sg:address":"2110 W Berry St",
    "sg:city":"Fort Worth",
    "sg:classifiers":[
        {
            "category":"Restaurant",
            "type":"Food & Drink"
        }
    ],
    "sg:phone":"+1 817 921 4647",
    "sg:postcode":"76110",
    "sg:province":"TX",
    "sg:tags":[
        "eating"
    ],
    "wof:name":"Alverado's Mexican Food",
    "wof:placetype":"venue"
},
  "geometry": {"coordinates":[-97.350149,32.70613],"type":"Point"}
}