{
  "type": "Feature",
  "properties": {
    "iso:country":"US",
    "sg:address":"3124 South Fwy",
    "sg:city":"Fort Worth",
    "sg:classifiers":[
        {
            "category":"Retail",
            "subcategory":"Laundry & Dry Cleaning",
            "type":"Services"
        }
    ],
    "sg:phone":"+1 817 247 7390",
    "sg:postcode":"76110",
    "sg:province":"TX",
    "sg:tags":[
        "cleaners",
        "rug",
        "carpet"
    ],
    "wof:name":"DFW Distinctive Floor Works",
    "wof:placetype":"venue"
},
  "geometry": {"coordinates":[-97.32108100000001,32.703856],"type":"Point"}
}