{
  "type": "Feature",
  "properties": {
    "iso:country":"US",
    "sg:address":"1910 Hermitage Dr",
    "sg:city":"Round Rock",
    "sg:classifiers":[
        {
            "category":"Health Services",
            "subcategory":"Doctor",
            "type":"Services"
        }
    ],
    "sg:phone":"+1 512 310 2444",
    "sg:postcode":"78681",
    "sg:province":"TX",
    "wof:name":"Joey McElhaney",
    "wof:placetype":"venue"
},
  "geometry": {"coordinates":[-97.706684,30.524289],"type":"Point"}
}