{
  "type": "Feature",
  "properties": {
    "iso:country":"US",
    "sg:address":"212 W Spring Valley Rd",
    "sg:city":"Richardson",
    "sg:classifiers":[
        {
            "category":"Professional",
            "subcategory":"Employment Agencies",
            "type":"Services"
        }
    ],
    "sg:phone":"+1 972 527 7001",
    "sg:postcode":"75081",
    "sg:province":"TX",
    "wof:name":"Apo",
    "wof:placetype":"venue"
},
  "geometry": {"coordinates":[-96.741518,32.940047],"type":"Point"}
}