{
  "type": "Feature",
  "properties": {
    "iso:country":"US",
    "sg:address":"1450 I- 45 S",
    "sg:city":"Conroe",
    "sg:classifiers":[
        {
            "category":"Retail",
            "subcategory":"Laundry & Dry Cleaning",
            "type":"Services"
        }
    ],
    "sg:phone":"+1 936 441 6091",
    "sg:postcode":"77304",
    "sg:province":"TX",
    "sg:tags":[
        "cleaners",
        "rug",
        "carpet"
    ],
    "wof:name":"Steam Works Carpet Care & Rest",
    "wof:placetype":"venue"
},
  "geometry": {"coordinates":[-95.464553,30.292522],"type":"Point"}
}