{
  "type": "Feature",
  "properties": {
    "iso:country":"US",
    "sg:address":"3135 Seymour Hwy",
    "sg:city":"Wichita Falls",
    "sg:classifiers":[
        {
            "category":"Freight",
            "type":"Transportation"
        }
    ],
    "sg:phone":"+1 940 723 4502",
    "sg:postcode":"76301",
    "sg:province":"TX",
    "sg:tags":[
        "vehicle",
        "recreational",
        "general"
    ],
    "wof:name":"A American Self Storage",
    "wof:placetype":"venue"
},
  "geometry": {"coordinates":[-98.525336,33.90963],"type":"Point"}
}