{
  "type": "Feature",
  "properties": {
    "iso:country":"US",
    "sg:address":"115 N 2nd St",
    "sg:city":"Killeen",
    "sg:classifiers":[
        {
            "category":"Professional",
            "subcategory":"Detective & Security Services",
            "type":"Services"
        }
    ],
    "sg:phone":"+1 254 526 3388",
    "sg:postcode":"76541",
    "sg:province":"TX",
    "sg:tags":[
        "bail",
        "bond"
    ],
    "wof:name":"Strike 3 Bail Bonds",
    "wof:placetype":"venue"
},
  "geometry": {"coordinates":[-97.730981,31.118275],"type":"Point"}
}