{
  "type": "Feature",
  "properties": {
    "iso:country":"US",
    "sg:address":"217 Bayside Dr",
    "sg:city":"Corpus Christi",
    "sg:classifiers":[
        {
            "category":"Real Estate",
            "subcategory":"Real Estate Agent",
            "type":"Services"
        }
    ],
    "sg:phone":"+1 361 852 2418",
    "sg:postcode":"78411",
    "sg:province":"TX",
    "sg:tags":[
        "appraiser"
    ],
    "wof:name":"Erickson John A Co & Assoc",
    "wof:placetype":"venue"
},
  "geometry": {"coordinates":[-97.37446199999999,27.743071],"type":"Point"}
}