{
  "type": "Feature",
  "properties": {
    "iso:country":"US",
    "sg:address":"13521 FM 16 W",
    "sg:city":"Lindale",
    "sg:classifiers":[
        {
            "category":"Building & Trades",
            "subcategory":"Construction",
            "type":"Services"
        }
    ],
    "sg:phone":"+1 903 882 8911",
    "sg:postcode":"75771",
    "sg:province":"TX",
    "sg:tags":[
        "general",
        "contractor"
    ],
    "wof:name":"Stacy Bateman",
    "wof:placetype":"venue"
},
  "geometry": {"coordinates":[-95.389138,32.516079],"type":"Point"}
}