{
  "type": "Feature",
  "properties": {
    "iso:country":"US",
    "sg:address":"616 Glendale St",
    "sg:city":"Queen City",
    "sg:classifiers":[
        {
            "category":"Shopping",
            "subcategory":"Discount & Variety Stores",
            "type":"Retail Goods"
        }
    ],
    "sg:phone":"+1 903 796 9333",
    "sg:postcode":"75572",
    "sg:province":"TX",
    "sg:tags":[
        "merchandise",
        "general"
    ],
    "wof:name":"Trinkets By Mac",
    "wof:placetype":"venue"
},
  "geometry": {"coordinates":[-94.166675,33.148266],"type":"Point"}
}