{
  "type": "Feature",
  "properties": {
    "iso:country":"US",
    "sg:address":"4234 Oak Shadows Dr",
    "sg:city":"Houston",
    "sg:classifiers":[
        {
            "category":"Shopping",
            "subcategory":"Clothing, Apparel, & Fashions",
            "type":"Retail Goods"
        }
    ],
    "sg:phone":"+1 713 957 1013",
    "sg:postcode":"77091",
    "sg:province":"TX",
    "wof:name":"Geris Heavenly Fashions",
    "wof:placetype":"venue"
},
  "geometry": {"coordinates":[-95.451025,29.84379],"type":"Point"}
}