{
  "type": "Feature",
  "properties": {
    "iso:country":"US",
    "sg:address":"8468 Shady Ln",
    "sg:city":"Bryan",
    "sg:classifiers":[
        {
            "category":"Wholesale",
            "subcategory":"Books, Periodicals, & Newspapers",
            "type":"Manufacturing & Wholesale Goods"
        }
    ],
    "sg:phone":"+1 979 589 3358",
    "sg:postcode":"77808",
    "sg:province":"TX",
    "sg:tags":[
        "distributor"
    ],
    "wof:name":"Times New York",
    "wof:placetype":"venue"
},
  "geometry": {"coordinates":[-96.2384,30.717382],"type":"Point"}
}