{
  "type": "Feature",
  "properties": {
    "iso:country":"US",
    "sg:address":"5915 Milwee St",
    "sg:city":"Houston",
    "sg:classifiers":[
        {
            "category":"Home & Garden",
            "subcategory":"Hardware",
            "type":"Retail Goods"
        }
    ],
    "sg:phone":"+1 713 681 4479",
    "sg:postcode":"77092",
    "sg:province":"TX",
    "sg:tags":[
        "fire",
        "sprinklers-residential",
        "industrial",
        "commercial",
        "automatic"
    ],
    "wof:name":"Texas Manufacturing Co.",
    "wof:placetype":"venue"
},
  "geometry": {"coordinates":[-95.475452,29.822186],"type":"Point"}
}