{
  "type": "Feature",
  "properties": {
    "iso:country":"US",
    "sg:address":"56 Cotton Ct",
    "sg:city":"Lake Jackson",
    "sg:classifiers":[
        {
            "category":"Wholesale",
            "subcategory":"Jewelry",
            "type":"Manufacturing & Wholesale Goods"
        }
    ],
    "sg:phone":"+1 979 285 0213",
    "sg:postcode":"77566",
    "sg:province":"TX",
    "sg:tags":[
        "stone"
    ],
    "wof:name":"Dp Ward Enterprises Inc",
    "wof:placetype":"venue"
},
  "geometry": {"coordinates":[-95.460312,29.033583],"type":"Point"}
}