{
  "type": "Feature",
  "properties": {
    "iso:country":"US",
    "sg:address":"1102 Oak St",
    "sg:city":"Jourdanton",
    "sg:classifiers":[
        {
            "category":"Retail",
            "subcategory":"Car Wash",
            "type":"Services"
        }
    ],
    "sg:phone":"+1 830 769 9191",
    "sg:postcode":"78026",
    "sg:province":"TX",
    "sg:tags":[
        "carwash"
    ],
    "wof:name":"Laser Wash Of Jourdanton",
    "wof:placetype":"venue"
},
  "geometry": {"coordinates":[-98.541241,28.921205],"type":"Point"}
}