{
  "type": "Feature",
  "properties": {
    "iso:country":"US",
    "sg:address":"6612 Antoine Dr",
    "sg:city":"Houston",
    "sg:classifiers":[
        {
            "category":"Personal",
            "subcategory":"Beauty Salon",
            "type":"Services"
        }
    ],
    "sg:phone":"+1 713 688 6245",
    "sg:postcode":"77091",
    "sg:province":"TX",
    "sg:tags":[
        "nail",
        "shop"
    ],
    "wof:name":"Unique Nails",
    "wof:placetype":"venue"
},
  "geometry": {"coordinates":[-95.473198,29.8613],"type":"Point"}
}