{
  "type": "Feature",
  "properties": {
    "iso:country":"US",
    "sg:address":"16320 Southwest Fwy",
    "sg:city":"Sugar Land",
    "sg:classifiers":[
        {
            "category":"Shopping",
            "subcategory":"Gifts & Souvenirs",
            "type":"Retail Goods"
        }
    ],
    "sg:phone":"+1 281 277 8000",
    "sg:postcode":"77479",
    "sg:province":"TX",
    "sg:tags":[
        "shop"
    ],
    "wof:name":"Tattle Tales Interiors & Gifts",
    "wof:placetype":"venue"
},
  "geometry": {"coordinates":[-95.629851,29.592011],"type":"Point"}
}