{
  "type": "Feature",
  "properties": {
    "iso:country":"US",
    "sg:address":"6935 Stearns St",
    "sg:city":"Houston",
    "sg:phone":"+1 713 748 5441",
    "sg:postcode":"77021",
    "sg:province":"TX",
    "sg:tags":[
        "equipment",
        "commercial"
    ],
    "wof:name":"Best Bakery Machines",
    "wof:placetype":"venue"
},
  "geometry": {"coordinates":[-95.36970100000001,29.694964],"type":"Point"}
}