{
  "type": "Feature",
  "properties": {
    "iso:country":"US",
    "sg:address":"1217 N Tyler St",
    "sg:city":"Dallas",
    "sg:classifiers":[
        {
            "category":"Shopping",
            "subcategory":"Clothing, Apparel, & Fashions",
            "type":"Retail Goods"
        }
    ],
    "sg:phone":"+1 214 942 0518",
    "sg:postcode":"75208",
    "sg:province":"TX",
    "wof:name":"Three Dg Environmental Graphic",
    "wof:placetype":"venue"
},
  "geometry": {"coordinates":[-96.83648700000001,32.758495],"type":"Point"}
}