{
  "type": "Feature",
  "properties": {
    "iso:country":"US",
    "sg:address":"500 W University Ave",
    "sg:city":"El Paso",
    "sg:classifiers":[
        {
            "category":"Education",
            "subcategory":"College",
            "type":"Public Place"
        }
    ],
    "sg:phone":"+1 915 747 6664",
    "sg:postcode":"79902",
    "sg:province":"TX",
    "wof:name":"Material Science & Engineering",
    "wof:placetype":"venue"
},
  "geometry": {"coordinates":[-106.50535499999999,31.769982],"type":"Point"}
}