{
  "type": "Feature",
  "properties": {
    "iso:country":"US",
    "sg:address":"11543 Raintree Cir",
    "sg:city":"Houston",
    "sg:classifiers":[
        {
            "category":"Professional",
            "type":"Services"
        }
    ],
    "sg:phone":"+1 713 782 2368",
    "sg:postcode":"77024",
    "sg:province":"TX",
    "wof:name":"Stbech LLC",
    "wof:placetype":"venue"
},
  "geometry": {"coordinates":[-95.52007,29.755378],"type":"Point"}
}