{
  "type": "Feature",
  "properties": {
    "iso:country":"US",
    "sg:address":"2412 W Wall St",
    "sg:city":"Midland",
    "sg:classifiers":[
        {
            "category":"Autos & Motor Vehicles",
            "subcategory":"Motorcycle Sales",
            "type":"Retail Goods"
        }
    ],
    "sg:phone":"+1 432 683 8468",
    "sg:postcode":"79701",
    "sg:province":"TX",
    "wof:name":"Dunns Walker Consignment Sls",
    "wof:placetype":"venue"
},
  "geometry": {"coordinates":[-102.100616,31.991996],"type":"Point"}
}