{
  "type": "Feature",
  "properties": {
    "iso:country":"US",
    "sg:address":"9802 Pso Lobo",
    "sg:city":"Texas City",
    "sg:classifiers":[
        {
            "category":"Farming",
            "subcategory":"Farm",
            "type":"Manufacturing & Wholesale Goods"
        }
    ],
    "sg:phone":"+1 409 978 2455",
    "sg:postcode":"77591",
    "sg:province":"TX",
    "sg:tags":[
        "crop",
        "general"
    ],
    "wof:name":"Nova Farms Inc",
    "wof:placetype":"venue"
},
  "geometry": {"coordinates":[-95.01838499999999,29.409245],"type":"Point"}
}