{
  "type": "Feature",
  "properties": {
    "iso:country":"US",
    "sg:address":"107 Frederick Rd",
    "sg:city":"Fredericksburg",
    "sg:classifiers":[
        {
            "category":"Communications",
            "subcategory":"Film & Video Production",
            "type":"Services"
        }
    ],
    "sg:phone":"+1 830 997 6028",
    "sg:postcode":"78624",
    "sg:province":"TX",
    "sg:tags":[
        "taping"
    ],
    "wof:name":"Bull Works Digital",
    "wof:placetype":"venue"
},
  "geometry": {"coordinates":[-98.850815,30.290805],"type":"Point"}
}