{
  "type": "Feature",
  "properties": {
    "iso:country":"US",
    "sg:address":"3195 Dowlen Rd",
    "sg:city":"Beaumont",
    "sg:classifiers":[
        {
            "category":"Shopping",
            "type":"Retail Goods"
        },
        {
            "category":"Professional",
            "subcategory":"Advertising",
            "type":"Services"
        }
    ],
    "sg:phone":"+1 409 860 0700",
    "sg:postcode":"77706",
    "sg:province":"TX",
    "sg:tags":[
        "mailing",
        "shipping",
        "merchandise"
    ],
    "sg:website":"www.ups.com",
    "wof:name":"UPS Store",
    "wof:placetype":"venue"
},
  "geometry": {"coordinates":[-94.168598,30.105684],"type":"Point"}
}