{
  "type": "Feature",
  "properties": {
    "iso:country":"US",
    "sg:address":"816 Gulf Bank Rd",
    "sg:city":"Houston",
    "sg:classifiers":[
        {
            "category":"Wholesale",
            "subcategory":"Farm Supplies",
            "type":"Manufacturing & Wholesale Goods"
        }
    ],
    "sg:phone":"+1 281 260 8373",
    "sg:postcode":"77037",
    "sg:province":"TX",
    "wof:name":"Sunset Feed Store",
    "wof:placetype":"venue"
},
  "geometry": {"coordinates":[-95.379231,29.889412],"type":"Point"}
}