{
  "type": "Feature",
  "properties": {
    "iso:country":"US",
    "sg:address":"2014 W Magnolia Ave",
    "sg:city":"San Antonio",
    "sg:classifiers":[
        {
            "category":"Home & Garden",
            "subcategory":"Building Materials",
            "type":"Retail Goods"
        }
    ],
    "sg:phone":"+1 210 731 9747",
    "sg:postcode":"78201",
    "sg:province":"TX",
    "wof:name":"Elements of Glass",
    "wof:placetype":"venue"
},
  "geometry": {"coordinates":[-98.53236099999999,29.456707],"type":"Point"}
}