{
  "type": "Feature",
  "properties": {
    "iso:country":"US",
    "sg:address":"6935 W Adams Ave",
    "sg:city":"Temple",
    "sg:classifiers":[
        {
            "category":"Banks & Credit Unions",
            "subcategory":"Bank",
            "type":"Services"
        }
    ],
    "sg:phone":"+1 254 773 8852",
    "sg:postcode":"76502",
    "sg:province":"TX",
    "wof:name":"Texas Partners Fed Cu",
    "wof:placetype":"venue"
},
  "geometry": {"coordinates":[-97.413534,31.116587],"type":"Point"}
}