{
  "type": "Feature",
  "properties": {
    "iso:country":"US",
    "sg:address":"3315 Buttercup St",
    "sg:city":"Houston",
    "sg:classifiers":[
        {
            "category":"Shopping",
            "subcategory":"Clothing, Apparel, & Fashions",
            "type":"Retail Goods"
        }
    ],
    "sg:phone":"+1 713 789 8713",
    "sg:postcode":"77063",
    "sg:province":"TX",
    "sg:tags":[
        "clothing",
        "women's"
    ],
    "wof:name":"Victoria Pappas Awning Co",
    "wof:placetype":"venue"
},
  "geometry": {"coordinates":[-95.516701,29.7288],"type":"Point"}
}