{
  "type": "Feature",
  "properties": {
    "iso:country":"US",
    "sg:address":"1320 9th Ave",
    "sg:city":"Port Arthur",
    "sg:classifiers":[
        {
            "category":"Real Estate",
            "subcategory":"Real Estate Operator",
            "type":"Services"
        }
    ],
    "sg:phone":"+1 409 984 5715",
    "sg:postcode":"77642",
    "sg:province":"TX",
    "sg:tags":[
        "apartment"
    ],
    "wof:name":"Wellington Manor Apartments",
    "wof:placetype":"venue"
},
  "geometry": {"coordinates":[-93.917526,29.905899],"type":"Point"}
}