{
  "type": "Feature",
  "properties": {
    "iso:country":"US",
    "sg:address":"100 E Elm St",
    "sg:city":"Tyler",
    "sg:classifiers":[
        {
            "category":"Government",
            "subcategory":"Office",
            "type":"Public Place"
        }
    ],
    "sg:phone":"+1 903 590 4645",
    "sg:postcode":"75702",
    "sg:province":"TX",
    "sg:tags":[
        "parish",
        "government-county"
    ],
    "wof:name":"Smith County Tyler",
    "wof:placetype":"venue"
},
  "geometry": {"coordinates":[-95.300652,32.349651],"type":"Point"}
}