{
  "type": "Feature",
  "properties": {
    "iso:country":"US",
    "sg:address":"4126 Callaghan Rd",
    "sg:city":"San Antonio",
    "sg:classifiers":[
        {
            "category":"Insurance",
            "subcategory":"Insurance Agent",
            "type":"Services"
        }
    ],
    "sg:phone":"+1 210 432 6429",
    "sg:postcode":"78228",
    "sg:province":"TX",
    "wof:name":"State Farm Insurance",
    "wof:placetype":"venue"
},
  "geometry": {"coordinates":[-98.602424,29.465496],"type":"Point"}
}