{
  "type": "Feature",
  "properties": {
    "iso:country":"US",
    "sg:address":"2155 W Southlake Blvd",
    "sg:city":"Southlake",
    "sg:classifiers":[
        {
            "category":"Restaurant",
            "type":"Food & Drink"
        }
    ],
    "sg:menulink":"http://www.allmenus.com/tx/northeast-tarrant/202318-mcdonalds/menu/",
    "sg:postcode":"76092",
    "sg:province":"TX",
    "sg:tags":[
        "burger",
        "american"
    ],
    "wof:name":"McDonald's",
    "wof:placetype":"venue"
},
  "geometry": {"coordinates":[-97.184651,32.93838],"type":"Point"}
}