{
  "type": "Feature",
  "properties": {
    "iso:country":"US",
    "sg:address":"15309 Fuchs Grove Rd",
    "sg:city":"Manor",
    "sg:phone":"+1 512 251 3232",
    "sg:postcode":"78653",
    "sg:province":"TX",
    "sg:tags":[
        "farm",
        "corn"
    ],
    "wof:name":"Clifton Gonzenbach",
    "wof:placetype":"venue"
},
  "geometry": {"coordinates":[-97.550257,30.392866],"type":"Point"}
}