{
  "type": "Feature",
  "properties": {
    "iso:country":"US",
    "sg:address":"4611 Wiseman Blvd",
    "sg:city":"San Antonio",
    "sg:classifiers":[
        {
            "category":"Manufacturing",
            "subcategory":"Apparel",
            "type":"Manufacturing & Wholesale Goods"
        }
    ],
    "sg:phone":"+1 210 250 5000",
    "sg:postcode":"78251",
    "sg:province":"TX",
    "sg:tags":[
        "textile",
        "product",
        "fabricated",
        "mfg"
    ],
    "wof:name":"Takata Seat Belts Inc",
    "wof:placetype":"venue"
},
  "geometry": {"coordinates":[-98.70166999999999,29.473183],"type":"Point"}
}