{
  "type": "Feature",
  "properties": {
    "iso:country":"US",
    "sg:address":"602 N Flamingo Dr",
    "sg:city":"Seabrook",
    "sg:classifiers":[
        {
            "category":"Professional",
            "type":"Services"
        }
    ],
    "sg:phone":"+1 281 474 5951",
    "sg:postcode":"77586",
    "sg:province":"TX",
    "wof:name":"McCoy Aviation",
    "wof:placetype":"venue"
},
  "geometry": {"coordinates":[-94.998671,29.58589],"type":"Point"}
}