{
  "type": "Feature",
  "properties": {
    "iso:country":"US",
    "sg:address":"10625 Presidential Dr",
    "sg:city":"Dallas",
    "sg:classifiers":[
        {
            "category":"Retail",
            "subcategory":"Auto Repair",
            "type":"Services"
        }
    ],
    "sg:phone":"+1 214 503 0595",
    "sg:postcode":"75243",
    "sg:province":"TX",
    "wof:name":"B N Automotive Electrical Specialist",
    "wof:placetype":"venue"
},
  "geometry": {"coordinates":[-96.702003,32.907501],"type":"Point"}
}