{
  "type": "Feature",
  "properties": {
    "iso:country":"US",
    "sg:address":"280 Dover Rd",
    "sg:city":"San Antonio",
    "sg:classifiers":[
        {
            "category":"Professional",
            "subcategory":"Business Services",
            "type":"Services"
        }
    ],
    "sg:phone":"+1 210 923 9222",
    "sg:postcode":"78209",
    "sg:province":"TX",
    "wof:name":"O G M Enterprises Inc",
    "wof:placetype":"venue"
},
  "geometry": {"coordinates":[-98.443179,29.471584],"type":"Point"}
}