{
  "type": "Feature",
  "properties": {
    "iso:country":"US",
    "sg:address":"1201 Austin Hwy",
    "sg:city":"San Antonio",
    "sg:classifiers":[
        {
            "category":"Restaurant",
            "type":"Food & Drink"
        }
    ],
    "sg:menulink":"http://www.allmenus.com/tx/san-antonio/165995-arbys/menu/",
    "sg:phone":"+1 210 826 1398",
    "sg:postcode":"78209",
    "sg:province":"TX",
    "sg:tags":[
        "burger",
        "american"
    ],
    "wof:name":"Arby's",
    "wof:placetype":"venue"
},
  "geometry": {"coordinates":[-98.446579,29.489033],"type":"Point"}
}