{
  "type": "Feature",
  "properties": {
    "iso:country":"US",
    "sg:address":"921 W Cannon St",
    "sg:city":"Fort Worth",
    "sg:classifiers":[
        {
            "category":"Health Services",
            "subcategory":"Nursing And Care Facility",
            "type":"Services"
        }
    ],
    "sg:phone":"+1 817 332 9261",
    "sg:postcode":"76104",
    "sg:province":"TX",
    "sg:tags":[
        "med",
        "skilled",
        "rest",
        "home"
    ],
    "wof:name":"Sycamore Care Center",
    "wof:placetype":"venue"
},
  "geometry": {"coordinates":[-97.33506,32.737257],"type":"Point"}
}