{
  "type": "Feature",
  "properties": {
    "iso:country":"US",
    "sg:address":"1601 Elm St Ste 3000",
    "sg:city":"Dallas",
    "sg:classifiers":[
        {
            "category":"Professional",
            "subcategory":"Lawyer & Legal Services",
            "type":"Services"
        }
    ],
    "sg:phone":"+1 214 999 3000",
    "sg:postcode":"75201",
    "sg:province":"TX",
    "sg:website":"www.gardere.com/",
    "wof:name":"Peter Vogel, Attorney",
    "wof:placetype":"venue"
},
  "geometry": {"coordinates":[-96.79804799999999,32.781754],"type":"Point"}
}