{
  "type": "Feature",
  "properties": {
    "iso:country":"US",
    "sg:address":"10312 I- 37",
    "sg:city":"Mathis",
    "sg:classifiers":[
        {
            "category":"Professional",
            "subcategory":"Business Services",
            "type":"Services"
        }
    ],
    "sg:phone":"+1 361 547 6170",
    "sg:postcode":"78368",
    "sg:province":"TX",
    "wof:name":"Gro Land Intl Co",
    "wof:placetype":"venue"
},
  "geometry": {"coordinates":[-97.800409,28.080908],"type":"Point"}
}