{
  "type": "Feature",
  "properties": {
    "iso:country":"US",
    "sg:address":"16215 Waverly Dr",
    "sg:city":"Houston",
    "sg:classifiers":[
        {
            "category":"Professional",
            "type":"Services"
        }
    ],
    "sg:phone":"+1 281 891 0507",
    "sg:postcode":"77032",
    "sg:province":"TX",
    "wof:name":"16215 Waverly LLC",
    "wof:placetype":"venue"
},
  "geometry": {"coordinates":[-95.36344099999999,29.953206],"type":"Point"}
}