{
  "type": "Feature",
  "properties": {
    "iso:country":"US",
    "sg:address":"712 N Main St",
    "sg:city":"Belton",
    "sg:classifiers":[
        {
            "category":"Insurance",
            "subcategory":"Hazard Insurance",
            "type":"Services"
        }
    ],
    "sg:phone":"+1 254 939 7745",
    "sg:postcode":"76513",
    "sg:province":"TX",
    "sg:tags":[
        "commercial",
        "business"
    ],
    "wof:name":"Haren Insurance Agency A Texas",
    "wof:placetype":"venue"
},
  "geometry": {"coordinates":[-97.461321,31.062859],"type":"Point"}
}