{
  "type": "Feature",
  "properties": {
    "iso:country":"US",
    "sg:address":"7411 Hines Pl Ste 112",
    "sg:city":"Dallas",
    "sg:classifiers":[
        {
            "category":"Shopping",
            "subcategory":"Bicycles & Sporting Goods",
            "type":"Retail Goods"
        }
    ],
    "sg:phone":"+1 214 630 8810",
    "sg:postcode":"75235",
    "sg:province":"TX",
    "sg:website":"www.sportingscene.com",
    "wof:name":"Sporting Scene the",
    "wof:placetype":"venue"
},
  "geometry": {"coordinates":[-96.858902,32.8293],"type":"Point"}
}