{
  "type": "Feature",
  "properties": {
    "iso:country":"US",
    "sg:address":"1234 Carbona Dr",
    "sg:city":"Dallas",
    "sg:classifiers":[
        {
            "category":"Government",
            "subcategory":"Fire Station",
            "type":"Public Place"
        }
    ],
    "sg:phone":"+1 214 670 5085",
    "sg:postcode":"75217",
    "sg:province":"TX",
    "sg:tags":[
        "protection"
    ],
    "wof:name":"Fire Station 34",
    "wof:placetype":"venue"
},
  "geometry": {"coordinates":[-96.69153,32.733146],"type":"Point"}
}