{
  "type": "Feature",
  "properties": {
    "iso:country":"US",
    "sg:address":"11851 Bissonnet St",
    "sg:city":"Houston",
    "sg:classifiers":[
        {
            "category":"Restaurant",
            "type":"Food & Drink"
        }
    ],
    "sg:phone":"+1 281 530 7575",
    "sg:postcode":"77099",
    "sg:province":"TX",
    "sg:tags":[
        "eating"
    ],
    "wof:name":"Oriental Cooking",
    "wof:placetype":"venue"
},
  "geometry": {"coordinates":[-95.586062,29.675075],"type":"Point"}
}