{
  "type": "Feature",
  "properties": {
    "iso:country":"US",
    "sg:address":"611 N Cherry St",
    "sg:city":"Tomball",
    "sg:classifiers":[
        {
            "category":"Building & Trades",
            "subcategory":"Cleaning & Sanitation",
            "type":"Services"
        }
    ],
    "sg:phone":"+1 281 351 8280",
    "sg:postcode":"77375",
    "sg:province":"TX",
    "sg:tags":[
        "maintenance"
    ],
    "wof:name":"Sansom Building Services",
    "wof:placetype":"venue"
},
  "geometry": {"coordinates":[-95.617698,30.100641],"type":"Point"}
}