{
  "type": "Feature",
  "properties": {
    "iso:country":"US",
    "sg:address":"110 Cypress Station Dr",
    "sg:city":"Houston",
    "sg:classifiers":[
        {
            "category":"Health Services",
            "subcategory":"Health Practitioner",
            "type":"Services"
        }
    ],
    "sg:phone":"+1 281 895 7499",
    "sg:postcode":"77090",
    "sg:province":"TX",
    "sg:tags":[
        "nurse",
        "registry"
    ],
    "wof:name":"Columbine Healthcare Systems",
    "wof:placetype":"venue"
},
  "geometry": {"coordinates":[-95.429585,30.032701],"type":"Point"}
}