{
  "type": "Feature",
  "properties": {
    "iso:country":"US",
    "sg:address":"18 Rhapsody Ln",
    "sg:city":"Wimberley",
    "sg:classifiers":[
        {
            "category":"Retail",
            "subcategory":"Laundry & Dry Cleaning",
            "type":"Services"
        },
        {
            "category":"Building & Trades",
            "subcategory":"Cleaning & Sanitation",
            "type":"Services"
        }
    ],
    "sg:phone":"+1 512 395 5666",
    "sg:postcode":"78676",
    "sg:province":"TX",
    "sg:tags":[
        "cleaner",
        "house"
    ],
    "wof:name":"Premier Cleaning Services",
    "wof:placetype":"venue"
},
  "geometry": {"coordinates":[-98.145054,30.045394],"type":"Point"}
}