{
  "type": "Feature",
  "properties": {
    "iso:country":"US",
    "sg:address":"320 S Broadway Ave",
    "sg:city":"Tyler",
    "sg:classifiers":[
        {
            "category":"Shopping",
            "subcategory":"Used Merchandise",
            "type":"Retail Goods"
        }
    ],
    "sg:phone":"+1 903 963 3207",
    "sg:postcode":"75702",
    "sg:province":"TX",
    "wof:name":"Call Faxs",
    "wof:placetype":"venue"
},
  "geometry": {"coordinates":[-95.300746,32.346696],"type":"Point"}
}