{
  "type": "Feature",
  "properties": {
    "iso:country":"US",
    "sg:address":"6700 Creekside Ln",
    "sg:city":"Plano",
    "sg:classifiers":[
        {
            "category":"Building & Trades",
            "subcategory":"Construction",
            "type":"Services"
        }
    ],
    "sg:phone":"+1 972 618 5290",
    "sg:postcode":"75023",
    "sg:province":"TX",
    "sg:tags":[
        "home",
        "builder"
    ],
    "wof:name":"Mpl Homes",
    "wof:placetype":"venue"
},
  "geometry": {"coordinates":[-96.747422,33.066969],"type":"Point"}
}