{
  "type": "Feature",
  "properties": {
    "iso:country":"US",
    "sg:address":"1010 Isuzu Pkwy",
    "sg:city":"Grand Prairie",
    "sg:classifiers":[
        {
            "category":"Wholesale",
            "subcategory":"Wine & Distilled Alcoholic Beverages",
            "type":"Manufacturing & Wholesale Goods"
        }
    ],
    "sg:phone":"+1 972 595 6100",
    "sg:postcode":"75050",
    "sg:province":"TX",
    "sg:tags":[
        "liquor"
    ],
    "sg:website":"www.republicbeverage.com",
    "wof:name":"Republic Beverage Co",
    "wof:placetype":"venue"
},
  "geometry": {"coordinates":[-97.048373,32.80002],"type":"Point"}
}