{
  "type": "Feature",
  "properties": {
    "iso:country":"US",
    "sg:address":"822 Mantooth Ave",
    "sg:city":"Lufkin",
    "sg:classifiers":[
        {
            "category":"Professional",
            "subcategory":"Business Services",
            "type":"Services"
        }
    ],
    "sg:phone":"+1 936 634 3909",
    "sg:postcode":"75904",
    "sg:province":"TX",
    "wof:name":"Daha Enterprises",
    "wof:placetype":"venue"
},
  "geometry": {"coordinates":[-94.73786800000001,31.340004],"type":"Point"}
}