{
  "type": "Feature",
  "properties": {
    "iso:country":"US",
    "sg:address":"10505 Hard Rock Rd",
    "sg:city":"Austin",
    "sg:classifiers":[
        {
            "category":"Retail",
            "subcategory":"Event Space",
            "type":"Services"
        },
        {
            "category":"Building & Trades",
            "subcategory":"Construction",
            "type":"Services"
        }
    ],
    "sg:phone":"+1 877 377 0397",
    "sg:postcode":"78750",
    "sg:province":"TX",
    "sg:tags":[
        "interior",
        "design",
        "venue"
    ],
    "sg:website":"www.colorandlightinteriors.com",
    "wof:name":"Color and Light Interiors",
    "wof:placetype":"venue"
},
  "geometry": {"coordinates":[-97.806696,30.451243],"type":"Point"}
}