{
  "type": "Feature",
  "properties": {
    "iso:country":"US",
    "sg:address":"4602 Snead Dr",
    "sg:city":"Corpus Christi",
    "sg:classifiers":[
        {
            "category":"Insurance",
            "subcategory":"Insurance Agent",
            "type":"Services"
        }
    ],
    "sg:phone":"+1 361 854 2116",
    "sg:postcode":"78413",
    "sg:province":"TX",
    "sg:tags":[
        "adjuster"
    ],
    "wof:name":"Spencer Claims Svc Inc",
    "wof:placetype":"venue"
},
  "geometry": {"coordinates":[-97.40416,27.689494],"type":"Point"}
}