{
  "type": "Feature",
  "properties": {
    "iso:country":"US",
    "sg:address":"1803 W Gramercy Pl",
    "sg:city":"San Antonio",
    "sg:classifiers":[
        {
            "category":"Real Estate",
            "subcategory":"Real Estate Operator",
            "type":"Services"
        }
    ],
    "sg:phone":"+1 210 734 7722",
    "sg:postcode":"78201",
    "sg:province":"TX",
    "sg:tags":[
        "apartment"
    ],
    "wof:name":"Tuscan Villas",
    "wof:placetype":"venue"
},
  "geometry": {"coordinates":[-98.52730200000001,29.461766],"type":"Point"}
}