{
  "type": "Feature",
  "properties": {
    "iso:country":"US",
    "sg:address":"5222 Farmer St",
    "sg:city":"Houston",
    "sg:classifiers":[
        {
            "category":"Insurance",
            "subcategory":"Insurance Agent",
            "type":"Services"
        }
    ],
    "sg:phone":"+1 281 444 1940",
    "sg:postcode":"77020",
    "sg:province":"TX",
    "wof:name":"State Farm Insurance",
    "wof:placetype":"venue"
},
  "geometry": {"coordinates":[-95.318523,29.775554],"type":"Point"}
}