{
  "type": "Feature",
  "properties": {
    "iso:country":"US",
    "sg:address":"2100 Roosevelt Dr",
    "sg:city":"Arlington",
    "sg:classifiers":[
        {
            "category":"Building & Trades",
            "subcategory":"Construction",
            "type":"Services"
        }
    ],
    "sg:phone":"+1 817 992 9122",
    "sg:postcode":"76013",
    "sg:province":"TX",
    "sg:tags":[
        "container",
        "sales"
    ],
    "wof:name":"Ocean Freight Cont Ent Inc",
    "wof:placetype":"venue"
},
  "geometry": {"coordinates":[-97.1559,32.706809],"type":"Point"}
}