{
  "type": "Feature",
  "properties": {
    "iso:country":"US",
    "sg:address":"1662 Hyland Greens Dr",
    "sg:city":"Grapevine",
    "sg:classifiers":[
        {
            "category":"Professional",
            "type":"Services"
        }
    ],
    "sg:phone":"+1 817 481 5111",
    "sg:postcode":"76051",
    "sg:province":"TX",
    "sg:tags":[
        "clergy"
    ],
    "wof:name":"Rev It Up",
    "wof:placetype":"venue"
},
  "geometry": {"coordinates":[-97.10432,32.957482],"type":"Point"}
}