{
  "type": "Feature",
  "properties": {
    "iso:country":"US",
    "sg:address":"702 N Hampton Rd",
    "sg:city":"De Soto",
    "sg:classifiers":[
        {
            "category":"Restaurant",
            "type":"Food & Drink"
        }
    ],
    "sg:phone":"+1 972 223 0069",
    "sg:postcode":"75115",
    "sg:province":"TX",
    "sg:tags":[
        "eating"
    ],
    "wof:name":"Taco Bell",
    "wof:placetype":"venue"
},
  "geometry": {"coordinates":[-96.856999,32.602358],"type":"Point"}
}