{
  "type": "Feature",
  "properties": {
    "iso:country":"US",
    "sg:address":"2516 Kelsey Dr",
    "sg:city":"Plano",
    "sg:classifiers":[
        {
            "category":"Professional",
            "type":"Services"
        }
    ],
    "sg:phone":"+1 972 423 6937",
    "sg:postcode":"75075",
    "sg:province":"TX",
    "wof:name":"Tripp Family Interests In",
    "wof:placetype":"venue"
},
  "geometry": {"coordinates":[-96.743127,33.012311],"type":"Point"}
}