{
  "type": "Feature",
  "properties": {
    "iso:country":"US",
    "sg:address":"700 Paredes Ave",
    "sg:city":"Brownsville",
    "sg:classifiers":[
        {
            "category":"Wholesale",
            "subcategory":"Machinery & Supplies",
            "type":"Manufacturing & Wholesale Goods"
        },
        {
            "category":"Manufacturing",
            "subcategory":"Tools & Machinery",
            "type":"Manufacturing & Wholesale Goods"
        }
    ],
    "sg:phone":"+1 956 542 2875",
    "sg:postcode":"78521",
    "sg:province":"TX",
    "sg:tags":[
        "equipment",
        "excavating",
        "construction",
        "mfg"
    ],
    "wof:name":"Gerardo S Cisneros",
    "wof:placetype":"venue"
},
  "geometry": {"coordinates":[-97.490163,25.915671],"type":"Point"}
}