{
  "type": "Feature",
  "properties": {
    "iso:country":"US",
    "sg:address":"8701 N Mo Pac Expy",
    "sg:city":"Austin",
    "sg:classifiers":[
        {
            "category":"Health Services",
            "subcategory":"Doctor",
            "type":"Services"
        },
        {
            "category":"Health Services",
            "subcategory":"Clinic",
            "type":"Services"
        },
        {
            "category":"Health Services",
            "subcategory":"Nursing And Care Facility",
            "type":"Services"
        },
        {
            "category":"Health Services",
            "subcategory":"Hospital",
            "type":"Services"
        }
    ],
    "sg:phone":"+1 512 464 8500",
    "sg:postcode":"78759",
    "sg:province":"TX",
    "sg:tags":[
        "physician",
        "medical",
        "practice-arnp",
        "registry",
        "nurses-advanced",
        "nurse",
        "surgeon"
    ],
    "wof:name":"Girling Health Care Inc",
    "wof:placetype":"venue"
},
  "geometry": {"coordinates":[-97.73994399999999,30.373795],"type":"Point"}
}