{
  "type": "Feature",
  "properties": {
    "iso:country":"US",
    "sg:address":"3767 Victory Cir",
    "sg:city":"Orange",
    "sg:classifiers":[
        {
            "category":"Retail",
            "subcategory":"Animal Services",
            "type":"Services"
        }
    ],
    "sg:phone":"+1 409 735 3131",
    "sg:postcode":"77630",
    "sg:province":"TX",
    "sg:tags":[
        "breeder",
        "dog"
    ],
    "wof:name":"C Cirkle",
    "wof:placetype":"venue"
},
  "geometry": {"coordinates":[-93.808492,30.052647],"type":"Point"}
}