{
  "type": "Feature",
  "properties": {
    "iso:country":"US",
    "sg:address":"606 Harold St",
    "sg:city":"Houston",
    "sg:classifiers":[
        {
            "category":"Utilities",
            "subcategory":"Telephone",
            "type":"Services"
        }
    ],
    "sg:phone":"+1 713 522 2750",
    "sg:postcode":"77006",
    "sg:province":"TX",
    "sg:tags":[
        "pay",
        "phones-equipment"
    ],
    "wof:name":"Extra Effort Payphone Co",
    "wof:placetype":"venue"
},
  "geometry": {"coordinates":[-95.386653,29.74139],"type":"Point"}
}