{
  "type": "Feature",
  "properties": {
    "iso:country":"US",
    "sg:address":"16750 Westgrove Dr",
    "sg:city":"Addison",
    "sg:classifiers":[
        {
            "category":"Banks & Credit Unions",
            "subcategory":"Financial Services",
            "type":"Services"
        }
    ],
    "sg:phone":"+1 972 386 4700",
    "sg:postcode":"75001",
    "sg:province":"TX",
    "sg:tags":[
        "investor",
        "real estate"
    ],
    "wof:name":"First Industrial Realty Trust",
    "wof:placetype":"venue"
},
  "geometry": {"coordinates":[-96.83882199999999,32.979825],"type":"Point"}
}