{
  "type": "Feature",
  "properties": {
    "iso:country":"US",
    "sg:address":"504 Cedar St",
    "sg:city":"Bastrop",
    "sg:classifiers":[
        {
            "category":"Building & Trades",
            "subcategory":"Plumbing",
            "type":"Services"
        }
    ],
    "sg:phone":"+1 512 321 7672",
    "sg:postcode":"78602",
    "sg:province":"TX",
    "sg:tags":[
        "conditioning",
        "air",
        "system",
        "contractor"
    ],
    "wof:name":"Larry's Repair Svc",
    "wof:placetype":"venue"
},
  "geometry": {"coordinates":[-97.322536,30.116851],"type":"Point"}
}