{
  "type": "Feature",
  "properties": {
    "iso:country":"US",
    "sg:address":"2910 Antoine Dr",
    "sg:city":"Houston",
    "sg:classifiers":[
        {
            "category":"Personal",
            "subcategory":"Beauty Salon",
            "type":"Services"
        }
    ],
    "sg:phone":"+1 713 956 8865",
    "sg:postcode":"77092",
    "sg:province":"TX",
    "sg:tags":[
        "shop"
    ],
    "wof:name":"Sandy Nguyen",
    "wof:placetype":"venue"
},
  "geometry": {"coordinates":[-95.473569,29.815646],"type":"Point"}
}