{
  "type": "Feature",
  "properties": {
    "iso:country":"US",
    "sg:address":"117 N 18th Ave",
    "sg:city":"Edinburg",
    "sg:classifiers":[
        {
            "category":"Retail",
            "subcategory":"Auto Repair",
            "type":"Services"
        }
    ],
    "sg:phone":"+1 956 380 2670",
    "sg:postcode":"78541",
    "sg:province":"TX",
    "sg:tags":[
        "general"
    ],
    "wof:name":"Julios Garage",
    "wof:placetype":"venue"
},
  "geometry": {"coordinates":[-98.154596,26.301263],"type":"Point"}
}