{
  "type": "Feature",
  "properties": {
    "iso:country":"US",
    "sg:address":"796 Brazosport Blvd S",
    "sg:city":"Clute",
    "sg:classifiers":[
        {
            "category":"Recreation",
            "type":"Entertainment"
        }
    ],
    "sg:phone":"+1 979 265 6516",
    "sg:postcode":"77531",
    "sg:province":"TX",
    "wof:name":"Charity Bingo",
    "wof:placetype":"venue"
},
  "geometry": {"coordinates":[-95.392588,29.012743],"type":"Point"}
}