{
  "type": "Feature",
  "properties": {
    "iso:country":"US",
    "sg:address":"530 Fairview Dr",
    "sg:city":"Richardson",
    "sg:classifiers":[
        {
            "category":"Government",
            "subcategory":"Fire Station",
            "type":"Public Place"
        }
    ],
    "sg:phone":"+1 972 480 9506",
    "sg:postcode":"75081",
    "sg:province":"TX",
    "sg:tags":[
        "equipment-emergency",
        "lighting"
    ],
    "wof:name":"Swim Evolution",
    "wof:placetype":"venue"
},
  "geometry": {"coordinates":[-96.721097,32.950001],"type":"Point"}
}