{
  "type": "Feature",
  "properties": {
    "iso:country":"US",
    "sg:address":"1101 Teakwood Trl",
    "sg:city":"Pflugerville",
    "sg:phone":"+1 512 251 1020",
    "sg:postcode":"78660",
    "sg:province":"TX",
    "sg:tags":[
        "hydrologist"
    ],
    "wof:name":"Rohne Hydrology",
    "wof:placetype":"venue"
},
  "geometry": {"coordinates":[-97.615161,30.449177],"type":"Point"}
}