{
  "type": "Feature",
  "properties": {
    "iso:country":"US",
    "sg:address":"14832 Boudreaux Rd Bldg A",
    "sg:city":"Tomball",
    "sg:classifiers":[
        {
            "category":"Home & Garden",
            "subcategory":"Household Appliances",
            "type":"Retail Goods"
        },
        {
            "category":"Wholesale",
            "subcategory":"Construction Materials",
            "type":"Manufacturing & Wholesale Goods"
        },
        {
            "category":"Home & Garden",
            "subcategory":"Building Materials",
            "type":"Retail Goods"
        },
        {
            "category":"Building & Trades",
            "subcategory":"Construction",
            "type":"Services"
        },
        {
            "category":"Utilities",
            "type":"Services"
        }
    ],
    "sg:phone":"+1 281 256 0151",
    "sg:postcode":"77377",
    "sg:province":"TX",
    "sg:tags":[
        "system",
        "systems-wholesale",
        "units-manufacturers",
        "dishwashing",
        "radiators-heating",
        "supply",
        "sales",
        "heating",
        "machine",
        "equipment",
        "distributor"
    ],
    "wof:name":"Econo-Heat Usa",
    "wof:placetype":"venue"
},
  "geometry": {"coordinates":[-95.640091,30.04566],"type":"Point"}
}