{
  "type": "Feature",
  "properties": {
    "iso:country":"US",
    "sg:address":"6220 Banning Ln",
    "sg:city":"Austin",
    "sg:classifiers":[
        {
            "category":"Freight",
            "type":"Transportation"
        }
    ],
    "sg:phone":"+1 512 928 9090",
    "sg:postcode":"78724",
    "sg:province":"TX",
    "sg:tags":[
        "forwarding"
    ],
    "wof:name":"USFreightways",
    "wof:placetype":"venue"
},
  "geometry": {"coordinates":[-97.632856,30.287775],"type":"Point"}
}