{
  "type": "Feature",
  "properties": {
    "iso:country":"US",
    "sg:address":"701 Markus Ave",
    "sg:city":"Lufkin",
    "sg:classifiers":[
        {
            "category":"Organizations",
            "subcategory":"Community Association",
            "type":"Services"
        }
    ],
    "sg:phone":"+1 936 632 8950",
    "sg:postcode":"75904",
    "sg:province":"TX",
    "wof:name":"Ameican Guild of Organization",
    "wof:placetype":"venue"
},
  "geometry": {"coordinates":[-94.73769299999999,31.333287],"type":"Point"}
}