{
  "type": "Feature",
  "properties": {
    "iso:country":"US",
    "sg:address":"4460 Trinity Mills Rd",
    "sg:city":"Dallas",
    "sg:classifiers":[
        {
            "category":"Real Estate",
            "subcategory":"Real Estate Services",
            "type":"Services"
        }
    ],
    "sg:phone":"+1 972 466 1118",
    "sg:postcode":"75287",
    "sg:province":"TX",
    "sg:tags":[
        "abstract",
        "title"
    ],
    "wof:name":"Fidelity National",
    "wof:placetype":"venue"
},
  "geometry": {"coordinates":[-96.83234,32.98973],"type":"Point"}
}