{
  "type": "Feature",
  "properties": {
    "iso:country":"US",
    "sg:address":"500 Grapevine Hwy",
    "sg:city":"Hurst",
    "sg:classifiers":[
        {
            "category":"Professional",
            "subcategory":"Management & Consulting",
            "type":"Services"
        },
        {
            "category":"Professional",
            "subcategory":"Business Services",
            "type":"Services"
        }
    ],
    "sg:phone":"+1 817 427 0960",
    "sg:postcode":"76054",
    "sg:province":"TX",
    "sg:tags":[
        "consultant",
        "educational",
        "testing"
    ],
    "wof:name":"Pearson Professional Centers",
    "wof:placetype":"venue"
},
  "geometry": {"coordinates":[-97.175927,32.864111],"type":"Point"}
}