{
  "type": "Feature",
  "properties": {
    "iso:country":"US",
    "sg:address":"8211 White Settlement Rd",
    "sg:city":"White Settlement",
    "sg:classifiers":[
        {
            "category":"Social Services",
            "type":"Services"
        }
    ],
    "sg:phone":"+1 817 246 6619",
    "sg:postcode":"76108",
    "sg:province":"TX",
    "sg:tags":[
        "senior",
        "citizen"
    ],
    "wof:name":"White Settlement Senior Ctr",
    "wof:placetype":"venue"
},
  "geometry": {"coordinates":[-97.460773,32.759694],"type":"Point"}
}