{
  "type": "Feature",
  "properties": {
    "iso:country":"US",
    "sg:address":"7611 Rolling Acres Dr",
    "sg:city":"Dallas",
    "sg:classifiers":[
        {
            "category":"Professional",
            "type":"Services"
        }
    ],
    "sg:phone":"+1 972 934 2778",
    "sg:postcode":"75248",
    "sg:province":"TX",
    "wof:name":"Marc J & Stacey C Crane",
    "wof:placetype":"venue"
},
  "geometry": {"coordinates":[-96.77542,32.953222],"type":"Point"}
}