{
  "type": "Feature",
  "properties": {
    "iso:country":"US",
    "sg:address":"4530 W 34th St",
    "sg:city":"Houston",
    "sg:classifiers":[
        {
            "category":"Wholesale",
            "subcategory":"Durable Goods & Equipment",
            "type":"Manufacturing & Wholesale Goods"
        }
    ],
    "sg:phone":"+1 713 686 0502",
    "sg:postcode":"77092",
    "sg:province":"TX",
    "sg:tags":[
        "engineering",
        "drafting",
        "supply"
    ],
    "wof:name":"A & A Graphic Supply Corp",
    "wof:placetype":"venue"
},
  "geometry": {"coordinates":[-95.45696,29.819477],"type":"Point"}
}