{
  "type": "Feature",
  "properties": {
    "iso:country":"US",
    "sg:address":"1560 Ethel Ann St",
    "sg:city":"Beaumont",
    "sg:classifiers":[
        {
            "category":"Professional",
            "type":"Services"
        }
    ],
    "sg:phone":"+1 409 752 3077",
    "sg:postcode":"77713",
    "sg:province":"TX",
    "wof:name":"Grimes",
    "wof:placetype":"venue"
},
  "geometry": {"coordinates":[-94.312512,30.055444],"type":"Point"}
}