{
  "type": "Feature",
  "properties": {
    "iso:country":"US",
    "sg:address":"209 Falls Ct",
    "sg:city":"Coppell",
    "sg:classifiers":[
        {
            "category":"Professional",
            "subcategory":"Computer Services",
            "type":"Services"
        }
    ],
    "sg:phone":"+1 972 393 2214",
    "sg:postcode":"75019",
    "sg:province":"TX",
    "sg:tags":[
        "graphic",
        "design"
    ],
    "wof:name":"Ds Designs",
    "wof:placetype":"venue"
},
  "geometry": {"coordinates":[-96.947615,32.963207],"type":"Point"}
}