{
  "type": "Feature",
  "properties": {
    "iso:country":"US",
    "sg:address":"9202 Lynne Cir",
    "sg:city":"Orange",
    "sg:classifiers":[
        {
            "category":"Manufacturing",
            "subcategory":"Toys & Sporting Goods",
            "type":"Manufacturing & Wholesale Goods"
        }
    ],
    "sg:phone":"+1 409 792 0886",
    "sg:postcode":"77630",
    "sg:province":"TX",
    "sg:tags":[
        "mfg"
    ],
    "wof:name":"Talbots Custom Fishing Rods",
    "wof:placetype":"venue"
},
  "geometry": {"coordinates":[-93.90619100000001,30.065049],"type":"Point"}
}