{
  "type": "Feature",
  "properties": {
    "iso:country":"US",
    "sg:address":"2105 50th St",
    "sg:city":"Lubbock",
    "sg:classifiers":[
        {
            "category":"Personal",
            "subcategory":"Beauty Salon",
            "type":"Services"
        }
    ],
    "sg:phone":"+1 806 765 9963",
    "sg:postcode":"79412",
    "sg:province":"TX",
    "sg:tags":[
        "shop"
    ],
    "wof:name":"Studio Hair Designer",
    "wof:placetype":"venue"
},
  "geometry": {"coordinates":[-101.863772,33.54866],"type":"Point"}
}