{
  "type": "Feature",
  "properties": {
    "iso:country":"US",
    "sg:address":"701 23rd St",
    "sg:city":"Canyon",
    "sg:classifiers":[
        {
            "category":"Food & Beverages",
            "subcategory":"Groceries & Convenience Stores",
            "type":"Retail Goods"
        }
    ],
    "sg:phone":"+1 806 655 0569",
    "sg:postcode":"79015",
    "sg:province":"TX",
    "wof:name":"Sun Country Food Mart",
    "wof:placetype":"venue"
},
  "geometry": {"coordinates":[-101.919366,34.976715],"type":"Point"}
}