{
  "type": "Feature",
  "properties": {
    "iso:country":"US",
    "sg:address":"7250 Southwest Fwy",
    "sg:city":"Houston",
    "sg:classifiers":[
        {
            "category":"Retail",
            "subcategory":"Driving School",
            "type":"Services"
        },
        {
            "category":"Autos & Motor Vehicles",
            "subcategory":"Motorcycle Sales",
            "type":"Retail Goods"
        },
        {
            "category":"Retail",
            "subcategory":"Auto Repair",
            "type":"Services"
        }
    ],
    "sg:phone":"+1 713 995 7494",
    "sg:postcode":"77074",
    "sg:province":"TX",
    "sg:tags":[
        "scooters-repairing",
        "scooters-parts",
        "instruction",
        "supply"
    ],
    "sg:website":"www.eximport.com",
    "wof:name":"Eximport Cycles",
    "wof:placetype":"venue"
},
  "geometry": {"coordinates":[-95.515068,29.703313],"type":"Point"}
}