{
  "type": "Feature",
  "properties": {
    "iso:country":"US",
    "sg:address":"1520 Foley",
    "sg:city":"Houston",
    "sg:classifiers":[
        {
            "category":"Retail",
            "subcategory":"Photofinishing",
            "type":"Services"
        }
    ],
    "sg:phone":"+1 713 983 6400",
    "sg:postcode":"77055",
    "sg:province":"TX",
    "sg:tags":[
        "photo"
    ],
    "wof:name":"Leben Consulting",
    "wof:placetype":"venue"
},
  "geometry": {"coordinates":[-95.51546999999999,29.799391],"type":"Point"}
}