{
  "type": "Feature",
  "properties": {
    "iso:country":"US",
    "sg:address":"1433 Richey St",
    "sg:city":"Pasadena",
    "sg:classifiers":[
        {
            "category":"Insurance",
            "subcategory":"Hazard Insurance",
            "type":"Services"
        }
    ],
    "sg:phone":"+1 713 473 2211",
    "sg:postcode":"77502",
    "sg:province":"TX",
    "sg:tags":[
        "carrier"
    ],
    "wof:name":"Alamo Auto Insurance",
    "wof:placetype":"venue"
},
  "geometry": {"coordinates":[-95.219691,29.68974],"type":"Point"}
}