{
  "type": "Feature",
  "properties": {
    "iso:country":"US",
    "sg:address":"2633 Conover Ave",
    "sg:city":"Odessa",
    "sg:classifiers":[
        {
            "category":"Organizations",
            "subcategory":"Religious Organization",
            "type":"Services"
        }
    ],
    "sg:phone":"+1 432 337 2084",
    "sg:postcode":"79763",
    "sg:province":"TX",
    "sg:tags":[
        "drinking",
        "church"
    ],
    "wof:name":"Holy Redeemer Catholic Church",
    "wof:placetype":"venue"
},
  "geometry": {"coordinates":[-102.407295,31.861736],"type":"Point"}
}