{
  "type": "Feature",
  "properties": {
    "iso:country":"US",
    "sg:address":"6320 Airline Dr",
    "sg:city":"Houston",
    "sg:classifiers":[
        {
            "category":"Retail",
            "subcategory":"Car Wash",
            "type":"Services"
        }
    ],
    "sg:phone":"+1 713 697 3566",
    "sg:postcode":"77076",
    "sg:province":"TX",
    "sg:tags":[
        "carwash"
    ],
    "wof:name":"Touch of Class Car Salon",
    "wof:placetype":"venue"
},
  "geometry": {"coordinates":[-95.384586,29.857286],"type":"Point"}
}