{
  "type": "Feature",
  "properties": {
    "iso:country":"US",
    "sg:address":"2906 McKinney Ave",
    "sg:city":"Dallas",
    "sg:classifiers":[
        {
            "category":"Professional",
            "subcategory":"Accounting & Tax Preparation",
            "type":"Services"
        }
    ],
    "sg:phone":"+1 214 397 0000",
    "sg:postcode":"75204",
    "sg:province":"TX",
    "sg:tags":[
        "bookkeeping",
        "general"
    ],
    "wof:name":"Restaurant Financial Services",
    "wof:placetype":"venue"
},
  "geometry": {"coordinates":[-96.800777,32.799814],"type":"Point"}
}