{
  "type": "Feature",
  "properties": {
    "iso:country":"US",
    "sg:address":"7608 Clearview Hills Ct",
    "sg:city":"Cresson",
    "sg:classifiers":[
        {
            "category":"Retail",
            "subcategory":"Repair Shop",
            "type":"Services"
        }
    ],
    "sg:phone":"+1 817 396 4211",
    "sg:postcode":"76035",
    "sg:province":"TX",
    "wof:name":"Greenseekers",
    "wof:placetype":"venue"
},
  "geometry": {"coordinates":[-97.647415,32.521773],"type":"Point"}
}