{
  "type": "Feature",
  "properties": {
    "iso:country":"US",
    "sg:address":"4037 Northview Ln",
    "sg:city":"Dallas",
    "sg:classifiers":[
        {
            "category":"Professional",
            "type":"Services"
        }
    ],
    "sg:phone":"+1 214 352 2190",
    "sg:postcode":"75229",
    "sg:province":"TX",
    "wof:name":"Glenn H Beadles Jr",
    "wof:placetype":"venue"
},
  "geometry": {"coordinates":[-96.83925000000001,32.903252],"type":"Point"}
}