{
  "type": "Feature",
  "properties": {
    "iso:country":"US",
    "sg:address":"12642 Mill Wheel Ln",
    "sg:city":"Houston",
    "sg:classifiers":[
        {
            "category":"Building & Trades",
            "subcategory":"Landscaping Services",
            "type":"Services"
        }
    ],
    "sg:phone":"+1 281 890 2476",
    "sg:postcode":"77070",
    "sg:province":"TX",
    "sg:tags":[
        "landscape"
    ],
    "wof:name":"Al Bazan Maintenance & La",
    "wof:placetype":"venue"
},
  "geometry": {"coordinates":[-95.575869,29.95778],"type":"Point"}
}