{
  "type": "Feature",
  "properties": {
    "iso:country":"US",
    "sg:address":"6818 Caulfield Dr",
    "sg:city":"Dallas",
    "sg:classifiers":[
        {
            "category":"Wholesale",
            "subcategory":"Home Furnishings",
            "type":"Manufacturing & Wholesale Goods"
        }
    ],
    "sg:phone":"+1 972 931 7722",
    "sg:postcode":"75248",
    "sg:province":"TX",
    "sg:tags":[
        "rep",
        "mfg"
    ],
    "wof:name":"Texas Forest Products",
    "wof:placetype":"venue"
},
  "geometry": {"coordinates":[-96.78832300000001,32.980938],"type":"Point"}
}