{
  "type": "Feature",
  "properties": {
    "iso:country":"US",
    "sg:address":"11028 Jollyville Rd",
    "sg:city":"Austin",
    "sg:classifiers":[
        {
            "category":"Real Estate",
            "subcategory":"Real Estate Agent",
            "type":"Services"
        }
    ],
    "sg:phone":"+1 512 527 8458",
    "sg:postcode":"78759",
    "sg:province":"TX",
    "sg:tags":[
        "management"
    ],
    "wof:name":"Lincoln Property Co",
    "wof:placetype":"venue"
},
  "geometry": {"coordinates":[-97.747951,30.406915],"type":"Point"}
}