{
  "type": "Feature",
  "properties": {
    "iso:country":"US",
    "sg:address":"4805 Kelley St",
    "sg:city":"Houston",
    "sg:classifiers":[
        {
            "category":"Building & Trades",
            "subcategory":"Cleaning & Sanitation",
            "type":"Services"
        }
    ],
    "sg:phone":"+1 713 491 2230",
    "sg:postcode":"77026",
    "sg:province":"TX",
    "sg:tags":[
        "maintenance"
    ],
    "wof:name":"Baileys 125 Cleaners",
    "wof:placetype":"venue"
},
  "geometry": {"coordinates":[-95.337895,29.813356],"type":"Point"}
}