{
  "type": "Feature",
  "properties": {
    "iso:country":"US",
    "sg:address":"524 S Meredith Ave",
    "sg:city":"Dumas",
    "sg:classifiers":[
        {
            "category":"Organizations",
            "subcategory":"Religious Organization",
            "type":"Services"
        }
    ],
    "sg:phone":"+1 806 935 2802",
    "sg:postcode":"79029",
    "sg:province":"TX",
    "wof:name":"Church Of Christ",
    "wof:placetype":"venue"
},
  "geometry": {"coordinates":[-101.97054,35.860672],"type":"Point"}
}