{
  "type": "Feature",
  "properties": {
    "iso:country":"US",
    "sg:address":"3500 Andtree Blvd",
    "sg:city":"Austin",
    "sg:classifiers":[
        {
            "category":"Bars & Pubs",
            "type":"Food & Drink"
        }
    ],
    "sg:phone":"+1 512 927 1999",
    "sg:postcode":"78724",
    "sg:province":"TX",
    "sg:tags":[
        "club",
        "night"
    ],
    "wof:name":"Area 54",
    "wof:placetype":"venue"
},
  "geometry": {"coordinates":[-97.66040599999999,30.322728],"type":"Point"}
}