{
  "type": "Feature",
  "properties": {
    "iso:country":"US",
    "sg:address":"3023 Liberty Rd",
    "sg:city":"Houston",
    "sg:classifiers":[
        {
            "category":"Personal",
            "subcategory":"Beauty Salon",
            "type":"Services"
        }
    ],
    "sg:phone":"+1 713 224 0125",
    "sg:postcode":"77026",
    "sg:province":"TX",
    "wof:name":"Hair By Lis",
    "wof:placetype":"venue"
},
  "geometry": {"coordinates":[-95.33888399999999,29.784727],"type":"Point"}
}