{
  "type": "Feature",
  "properties": {
    "iso:country":"US",
    "sg:address":"110 E 8th St",
    "sg:city":"Georgetown",
    "sg:classifiers":[
        {
            "category":"Building & Trades",
            "subcategory":"Construction",
            "type":"Services"
        }
    ],
    "sg:phone":"+1 512 869 2608",
    "sg:postcode":"78626",
    "sg:province":"TX",
    "sg:tags":[
        "home",
        "residential",
        "builder",
        "contractor"
    ],
    "wof:name":"Tim W Long Custom Homes Inc",
    "wof:placetype":"venue"
},
  "geometry": {"coordinates":[-97.67694400000001,30.636528],"type":"Point"}
}