{
  "type": "Feature",
  "properties": {
    "iso:country":"US",
    "sg:address":"10616 Janway Dr",
    "sg:city":"El Paso",
    "sg:classifiers":[
        {
            "category":"Professional",
            "type":"Services"
        },
        {
            "category":"Shopping",
            "type":"Retail Goods"
        }
    ],
    "sg:phone":"+1 915 592 6567",
    "sg:postcode":"79935",
    "sg:province":"TX",
    "sg:tags":[
        "mural"
    ],
    "wof:name":"English Artist & Co",
    "wof:placetype":"venue"
},
  "geometry": {"coordinates":[-106.33784,31.767832],"type":"Point"}
}