{
  "type": "Feature",
  "properties": {
    "iso:country":"US",
    "sg:address":"500 Co Rd 125",
    "sg:city":"Garden City",
    "sg:classifiers":[
        {
            "category":"Farming",
            "subcategory":"Livestock Farm",
            "type":"Manufacturing & Wholesale Goods"
        }
    ],
    "sg:phone":"+1 432 354 2520",
    "sg:postcode":"79739",
    "sg:province":"TX",
    "sg:tags":[
        "ranch"
    ],
    "wof:name":"Schwartz Ranch Inc",
    "wof:placetype":"venue"
},
  "geometry": {"coordinates":[-101.55935100000001,31.863384],"type":"Point"}
}