{
  "type": "Feature",
  "properties": {
    "iso:country":"US",
    "sg:address":"5614 Englewood Ave",
    "sg:city":"Lubbock",
    "sg:classifiers":[
        {
            "category":"Travel",
            "subcategory":"Hotels & Motels",
            "type":"Entertainment"
        }
    ],
    "sg:phone":"+1 806 797 9600",
    "sg:postcode":"79424",
    "sg:province":"TX",
    "sg:tags":[
        "lodging"
    ],
    "sg:website":"http://www.lubbocksouthwestsuites.hamptoninn.com",
    "wof:name":"Hampton Inn and Suites",
    "wof:placetype":"venue"
},
  "geometry": {"coordinates":[-101.93725000000001,33.542107],"type":"Point"}
}