{
  "type": "Feature",
  "properties": {
    "iso:country":"US",
    "sg:address":"1306 Bar Harbor Dr",
    "sg:city":"Dallas",
    "sg:classifiers":[
        {
            "category":"Manufacturing",
            "subcategory":"Electronics",
            "type":"Manufacturing & Wholesale Goods"
        }
    ],
    "sg:phone":"+1 214 573 7656",
    "sg:postcode":"75232",
    "sg:province":"TX",
    "sg:tags":[
        "communications",
        "equipment"
    ],
    "wof:name":"Carrier Access Corp",
    "wof:placetype":"venue"
},
  "geometry": {"coordinates":[-96.843266,32.669773],"type":"Point"}
}