{
  "type": "Feature",
  "properties": {
    "iso:country":"US",
    "sg:address":"2719 Summer Wind Dr",
    "sg:city":"Grapevine",
    "sg:classifiers":[
        {
            "category":"Building & Trades",
            "subcategory":"Cleaning & Sanitation",
            "type":"Services"
        }
    ],
    "sg:phone":"+1 817 329 9127",
    "sg:postcode":"76051",
    "sg:province":"TX",
    "sg:tags":[
        "janitor"
    ],
    "wof:name":"Live Oak Cleaning Svc",
    "wof:placetype":"venue"
},
  "geometry": {"coordinates":[-97.11344099999999,32.964658],"type":"Point"}
}