{
  "type": "Feature",
  "properties": {
    "iso:country":"US",
    "sg:address":"1519 Pagewood Ave",
    "sg:city":"Odessa",
    "sg:classifiers":[
        {
            "category":"Professional",
            "subcategory":"Business Services",
            "type":"Services"
        }
    ],
    "sg:phone":"+1 432 367 9225",
    "sg:postcode":"79761",
    "sg:province":"TX",
    "wof:name":"Fletcher Thomas Interiors",
    "wof:placetype":"venue"
},
  "geometry": {"coordinates":[-102.332274,31.876826],"type":"Point"}
}