{
  "type": "Feature",
  "properties": {
    "iso:country":"US",
    "sg:address":"7200 S R L Thornton Fwy",
    "sg:city":"Dallas",
    "sg:classifiers":[
        {
            "category":"Travel",
            "subcategory":"Campground",
            "type":"Entertainment"
        }
    ],
    "sg:phone":"+1 972 228 9864",
    "sg:postcode":"75232",
    "sg:province":"TX",
    "sg:tags":[
        "trailer"
    ],
    "wof:name":"Good Luck Rv & Trailer Park",
    "wof:placetype":"venue"
},
  "geometry": {"coordinates":[-96.822501,32.662179],"type":"Point"}
}