{
  "type": "Feature",
  "properties": {
    "iso:country":"US",
    "sg:address":"3438 Lydia St",
    "sg:city":"Houston",
    "sg:classifiers":[
        {
            "category":"Shopping",
            "subcategory":"Clothing, Apparel, & Fashions",
            "type":"Retail Goods"
        }
    ],
    "sg:phone":"+1 713 747 2632",
    "sg:postcode":"77021",
    "sg:province":"TX",
    "sg:tags":[
        "woman",
        "cosmetic"
    ],
    "wof:name":"Christines Fashions",
    "wof:placetype":"venue"
},
  "geometry": {"coordinates":[-95.375844,29.685457],"type":"Point"}
}