{
  "type": "Feature",
  "properties": {
    "iso:country":"US",
    "sg:address":"602 Rigsby Ave",
    "sg:city":"San Antonio",
    "sg:classifiers":[
        {
            "category":"Shopping",
            "subcategory":"Florist",
            "type":"Retail Goods"
        }
    ],
    "sg:phone":"+1 210 533 8836",
    "sg:postcode":"78210",
    "sg:province":"TX",
    "wof:name":"D & D Flower Shop",
    "wof:placetype":"venue"
},
  "geometry": {"coordinates":[-98.461321,29.398378],"type":"Point"}
}