{
  "type": "Feature",
  "properties": {
    "iso:country":"US",
    "sg:address":"9751 Harry Hines Blvd",
    "sg:city":"Dallas",
    "sg:classifiers":[
        {
            "category":"Personal",
            "type":"Services"
        },
        {
            "category":"Retail",
            "subcategory":"Auto Repair",
            "type":"Services"
        }
    ],
    "sg:phone":"+1 214 454 5205",
    "sg:postcode":"75220",
    "sg:province":"TX",
    "sg:tags":[
        "body",
        "repairing",
        "automobile",
        "dent",
        "towing",
        "removal",
        "painting"
    ],
    "sg:website":"http://www.gotojoes.net",
    "wof:name":"Joe's Collision & Auto Repair",
    "wof:placetype":"venue"
},
  "geometry": {"coordinates":[-96.878371,32.852275],"type":"Point"}
}