{
  "type": "Feature",
  "properties": {
    "iso:country":"US",
    "sg:address":"613 Harold St",
    "sg:city":"Houston",
    "sg:classifiers":[
        {
            "category":"Real Estate",
            "subcategory":"Real Estate Agent",
            "type":"Services"
        }
    ],
    "sg:phone":"+1 713 621 2625",
    "sg:postcode":"77006",
    "sg:province":"TX",
    "wof:name":"Charter Capital Corp",
    "wof:placetype":"venue"
},
  "geometry": {"coordinates":[-95.38879,29.741294],"type":"Point"}
}