{
  "type": "Feature",
  "properties": {
    "iso:country":"US",
    "sg:address":"6845 Dixie Dr",
    "sg:city":"Houston",
    "sg:classifiers":[
        {
            "category":"Building & Trades",
            "subcategory":"Construction",
            "type":"Services"
        }
    ],
    "sg:phone":"+1 713 495 3200",
    "sg:postcode":"77087",
    "sg:province":"TX",
    "sg:tags":[
        "contractor"
    ],
    "wof:name":"Philip Corrosion Services",
    "wof:placetype":"venue"
},
  "geometry": {"coordinates":[-95.307755,29.680994],"type":"Point"}
}