{
  "type": "Feature",
  "properties": {
    "iso:country":"US",
    "sg:address":"325 Ranch Rd 620 S",
    "sg:city":"Austin",
    "sg:classifiers":[
        {
            "category":"Food & Beverages",
            "subcategory":"Liquor & Beverages",
            "type":"Retail Goods"
        }
    ],
    "sg:phone":"+1 512 263 2129",
    "sg:postcode":"78734",
    "sg:province":"TX",
    "sg:tags":[
        "alcoholic"
    ],
    "wof:name":"Louies Liquor",
    "wof:placetype":"venue"
},
  "geometry": {"coordinates":[-97.95248599999999,30.363132],"type":"Point"}
}