{
  "type": "Feature",
  "properties": {
    "iso:country":"US",
    "sg:address":"407 Eileen Dr",
    "sg:city":"Pleasanton",
    "sg:classifiers":[
        {
            "category":"Professional",
            "subcategory":"Management & Consulting",
            "type":"Services"
        }
    ],
    "sg:phone":"+1 830 569 4594",
    "sg:postcode":"78064",
    "sg:province":"TX",
    "sg:tags":[
        "science",
        "consultant",
        "academic"
    ],
    "wof:name":"Pickens' Well Service",
    "wof:placetype":"venue"
},
  "geometry": {"coordinates":[-98.51496899999999,28.961381],"type":"Point"}
}