{
  "type": "Feature",
  "properties": {
    "iso:country":"US",
    "sg:address":"1200 Mckinney St",
    "sg:city":"Houston",
    "sg:classifiers":[
        {
            "category":"Restaurant",
            "type":"Food & Drink"
        }
    ],
    "sg:menulink":"http://www.allmenus.com/tx/houston/139467-quiznos-sub/menu/",
    "sg:phone":"+1 713 951 9425",
    "sg:postcode":"77010",
    "sg:province":"TX",
    "sg:tags":[
        "wrap",
        "american",
        "sandwich"
    ],
    "wof:name":"Quiznos Sub",
    "wof:placetype":"venue"
},
  "geometry": {"coordinates":[-95.363045,29.755273],"type":"Point"}
}