{
  "type": "Feature",
  "properties": {
    "iso:country":"US",
    "sg:address":"3330 Old Spanish Trl D",
    "sg:city":"Houston",
    "sg:classifiers":[
        {
            "category":"Government",
            "subcategory":"Office",
            "type":"Public Place"
        }
    ],
    "sg:phone":"+1 713 440 4700",
    "sg:postcode":"77021",
    "sg:province":"TX",
    "sg:website":"http://www.justex.net",
    "wof:name":"Adult Probation",
    "wof:placetype":"venue"
},
  "geometry": {"coordinates":[-95.372074,29.701477],"type":"Point"}
}