{
  "type": "Feature",
  "properties": {
    "iso:country":"US",
    "sg:address":"1928 Acton Hwy",
    "sg:city":"Granbury",
    "sg:classifiers":[
        {
            "category":"Professional",
            "subcategory":"Advertising",
            "type":"Services"
        }
    ],
    "sg:phone":"+1 817 573 5037",
    "sg:postcode":"76049",
    "sg:province":"TX",
    "wof:name":"Solutions",
    "wof:placetype":"venue"
},
  "geometry": {"coordinates":[-97.752273,32.439502],"type":"Point"}
}