{
  "type": "Feature",
  "properties": {
    "iso:country":"US",
    "sg:address":"6631 Maczali Dr",
    "sg:city":"Missouri City",
    "sg:classifiers":[
        {
            "category":"Shopping",
            "type":"Retail Goods"
        }
    ],
    "sg:phone":"+1 281 437 1955",
    "sg:postcode":"77489",
    "sg:province":"TX",
    "sg:tags":[
        "wedding",
        "supply"
    ],
    "wof:name":"Touch Of Elegance",
    "wof:placetype":"venue"
},
  "geometry": {"coordinates":[-95.48340399999999,29.594019],"type":"Point"}
}