{
  "type": "Feature",
  "properties": {
    "iso:country":"US",
    "sg:address":"333 N Ceylon St",
    "sg:city":"Eagle Pass",
    "sg:classifiers":[
        {
            "category":"Banks & Credit Unions",
            "subcategory":"Bank",
            "type":"Services"
        }
    ],
    "sg:phone":"+1 830 758 0622",
    "sg:postcode":"78852",
    "sg:province":"TX",
    "sg:tags":[
        "institution",
        "business"
    ],
    "wof:name":"Dinero Loans",
    "wof:placetype":"venue"
},
  "geometry": {"coordinates":[-100.499661,28.709446],"type":"Point"}
}