{
  "type": "Feature",
  "properties": {
    "iso:country":"US",
    "sg:address":"5202 Rittiman Rd",
    "sg:city":"San Antonio",
    "sg:classifiers":[
        {
            "category":"Wholesale",
            "subcategory":"Electrical",
            "type":"Manufacturing & Wholesale Goods"
        }
    ],
    "sg:phone":"+1 210 655 8222",
    "sg:postcode":"78209",
    "sg:province":"TX",
    "sg:tags":[
        "equipment",
        "supply",
        "automation"
    ],
    "wof:name":"Reynolds Electric Group",
    "wof:placetype":"venue"
},
  "geometry": {"coordinates":[-98.386478,29.484005],"type":"Point"}
}