{
  "type": "Feature",
  "properties": {
    "iso:country":"US",
    "sg:address":"12471 Pollan St",
    "sg:city":"Tyler",
    "sg:classifiers":[
        {
            "category":"Organizations",
            "subcategory":"Religious Organization",
            "type":"Services"
        }
    ],
    "sg:phone":"+1 903 581 4155",
    "sg:postcode":"75704",
    "sg:province":"TX",
    "sg:tags":[
        "nonprofit",
        "homeless",
        "reaching"
    ],
    "wof:name":"Community Services",
    "wof:placetype":"venue"
},
  "geometry": {"coordinates":[-95.374253,32.352831],"type":"Point"}
}