{
  "type": "Feature",
  "properties": {
    "iso:country":"US",
    "sg:address":"100 Shady Ln",
    "sg:city":"Columbus",
    "sg:phone":"+1 979 732 5940",
    "sg:postcode":"78934",
    "sg:province":"TX",
    "sg:tags":[
        "farm",
        "corn"
    ],
    "wof:name":"Matthew Hagendorf",
    "wof:placetype":"venue"
},
  "geometry": {"coordinates":[-96.56361800000001,29.700681],"type":"Point"}
}