{
  "type": "Feature",
  "properties": {
    "iso:country":"US",
    "sg:address":"1802 Shady Point Circle Dr",
    "sg:city":"San Angelo",
    "sg:classifiers":[
        {
            "category":"Freight",
            "type":"Transportation"
        }
    ],
    "sg:phone":"+1 325 949 6333",
    "sg:postcode":"76904",
    "sg:province":"TX",
    "sg:tags":[
        "operator",
        "local",
        "trucking"
    ],
    "wof:name":"J & L Trucking Inc",
    "wof:placetype":"venue"
},
  "geometry": {"coordinates":[-100.48732200000001,31.387322],"type":"Point"}
}