{
  "type": "Feature",
  "properties": {
    "iso:country":"US",
    "sg:address":"1504 W University Dr",
    "sg:city":"Mc Kinney",
    "sg:classifiers":[
        {
            "category":"Food & Beverages",
            "subcategory":"Bakery",
            "type":"Retail Goods"
        }
    ],
    "sg:phone":"+1 972 548 0379",
    "sg:postcode":"75069",
    "sg:province":"TX",
    "sg:tags":[
        "doughnut"
    ],
    "wof:name":"Shipley Do-Nuts Rdj",
    "wof:placetype":"venue"
},
  "geometry": {"coordinates":[-96.628843,33.216572],"type":"Point"}
}