{
  "type": "Feature",
  "properties": {
    "iso:country":"US",
    "sg:address":"2710 E 11th St",
    "sg:city":"Dallas",
    "sg:classifiers":[
        {
            "category":"Building & Trades",
            "subcategory":"Construction",
            "type":"Services"
        }
    ],
    "sg:phone":"+1 214 942 6880",
    "sg:postcode":"75203",
    "sg:province":"TX",
    "sg:tags":[
        "roofing",
        "contractor"
    ],
    "wof:name":"Best Texas Roofing",
    "wof:placetype":"venue"
},
  "geometry": {"coordinates":[-96.78901500000001,32.746259],"type":"Point"}
}