{
  "type": "Feature",
  "properties": {
    "iso:country":"US",
    "sg:address":"630 S Hearne St",
    "sg:city":"Waskom",
    "sg:classifiers":[
        {
            "category":"Personal",
            "subcategory":"Beauty Salon",
            "type":"Services"
        }
    ],
    "sg:phone":"+1 903 687 2506",
    "sg:postcode":"75692",
    "sg:province":"TX",
    "wof:name":"Nora's Beauty Salon",
    "wof:placetype":"venue"
},
  "geometry": {"coordinates":[-94.062653,32.471363],"type":"Point"}
}