{
  "type": "Feature",
  "properties": {
    "iso:country":"US",
    "sg:address":"12201 Merit Dr",
    "sg:city":"Dallas",
    "sg:classifiers":[
        {
            "category":"Professional",
            "subcategory":"Lawyer & Legal Services",
            "type":"Services"
        }
    ],
    "sg:phone":"+1 972 866 9900",
    "sg:postcode":"75251",
    "sg:province":"TX",
    "wof:name":"Davis David D Atty",
    "wof:placetype":"venue"
},
  "geometry": {"coordinates":[-96.772598,32.913799],"type":"Point"}
}