{
  "type": "Feature",
  "properties": {
    "iso:country":"US",
    "sg:address":"5535 Red Bird Center Dr",
    "sg:city":"Dallas",
    "sg:classifiers":[
        {
            "category":"Wholesale",
            "subcategory":"Medical Equipment & Supplies",
            "type":"Manufacturing & Wholesale Goods"
        }
    ],
    "sg:phone":"+1 972 223 7770",
    "sg:postcode":"75237",
    "sg:province":"TX",
    "wof:name":"American Lift Aids",
    "wof:placetype":"venue"
},
  "geometry": {"coordinates":[-96.880169,32.681056],"type":"Point"}
}