{
  "type": "Feature",
  "properties": {
    "iso:country":"US",
    "sg:address":"4113 W Industrial Ave",
    "sg:city":"Midland",
    "sg:classifiers":[
        {
            "category":"Wholesale",
            "subcategory":"Chemicals & Plastics",
            "type":"Manufacturing & Wholesale Goods"
        }
    ],
    "sg:phone":"+1 432 697 8171",
    "sg:postcode":"79703",
    "sg:province":"TX",
    "sg:tags":[
        "research",
        "chem",
        "physical",
        "mfg"
    ],
    "wof:name":"Benchmark Research & Tech",
    "wof:placetype":"venue"
},
  "geometry": {"coordinates":[-102.12576,31.968677],"type":"Point"}
}