{
  "type": "Feature",
  "properties": {
    "iso:country":"US",
    "sg:address":"6 W French Ave",
    "sg:city":"Temple",
    "sg:classifiers":[
        {
            "category":"Social Services",
            "type":"Services"
        }
    ],
    "sg:phone":"+1 254 778 2495",
    "sg:postcode":"76501",
    "sg:province":"TX",
    "sg:tags":[
        "organization",
        "welfare"
    ],
    "wof:name":"Central Texas Support Svc",
    "wof:placetype":"venue"
},
  "geometry": {"coordinates":[-97.33994300000001,31.102656],"type":"Point"}
}