{
  "type": "Feature",
  "properties": {
    "iso:country":"US",
    "sg:address":"3212 Montana Ave",
    "sg:city":"El Paso",
    "sg:classifiers":[
        {
            "category":"Utilities",
            "type":"Services"
        }
    ],
    "sg:phone":"+1 915 566 3974",
    "sg:postcode":"79903",
    "sg:province":"TX",
    "sg:tags":[
        "sweeping",
        "contractor"
    ],
    "wof:name":"Sweep-A-Way Inc",
    "wof:placetype":"venue"
},
  "geometry": {"coordinates":[-106.455536,31.78364],"type":"Point"}
}