{
  "type": "Feature",
  "properties": {
    "iso:country":"US",
    "sg:address":"219 Coronado Dr N",
    "sg:city":"Kerrville",
    "sg:classifiers":[
        {
            "category":"Real Estate",
            "subcategory":"Real Estate Agent",
            "type":"Services"
        }
    ],
    "sg:phone":"+1 830 896 1768",
    "sg:postcode":"78028",
    "sg:province":"TX",
    "wof:name":"Howards Rental Properties",
    "wof:placetype":"venue"
},
  "geometry": {"coordinates":[-99.17374700000001,30.071545],"type":"Point"}
}