{
  "type": "Feature",
  "properties": {
    "iso:country":"US",
    "sg:address":"1192 N Yarbrough Dr",
    "sg:city":"El Paso",
    "sg:classifiers":[
        {
            "category":"Retail",
            "subcategory":"Auto Repair",
            "type":"Services"
        }
    ],
    "sg:phone":"+1 915 592 5904",
    "sg:postcode":"79925",
    "sg:province":"TX",
    "sg:tags":[
        "muffler",
        "exhaust",
        "system"
    ],
    "wof:name":"Midas Auto Svc Experts",
    "wof:placetype":"venue"
},
  "geometry": {"coordinates":[-106.344903,31.753301],"type":"Point"}
}