{
  "type": "Feature",
  "properties": {
    "iso:country":"US",
    "sg:address":"1901 E Main St",
    "sg:city":"Grand Prairie",
    "sg:classifiers":[
        {
            "category":"Autos & Motor Vehicles",
            "subcategory":"Auto Supplies",
            "type":"Retail Goods"
        },
        {
            "category":"Wholesale",
            "subcategory":"Auto Parts",
            "type":"Manufacturing & Wholesale Goods"
        }
    ],
    "sg:phone":"+1 972 642 6080",
    "sg:postcode":"75050",
    "sg:province":"TX",
    "sg:tags":[
        "tire"
    ],
    "wof:name":"Serrato's Used Tires",
    "wof:placetype":"venue"
},
  "geometry": {"coordinates":[-96.97708299999999,32.748911],"type":"Point"}
}