{
  "type": "Feature",
  "properties": {
    "iso:country":"US",
    "sg:address":"6200 Duchess Dr",
    "sg:city":"Austin",
    "sg:classifiers":[
        {
            "category":"Professional",
            "type":"Services"
        }
    ],
    "sg:phone":"+1 512 929 5477",
    "sg:postcode":"78724",
    "sg:province":"TX",
    "wof:name":"Cynthias Sensational Creation",
    "wof:placetype":"venue"
},
  "geometry": {"coordinates":[-97.660623,30.289935],"type":"Point"}
}