{
  "type": "Feature",
  "properties": {
    "iso:country":"US",
    "sg:address":"2505 N Plano Rd",
    "sg:city":"Richardson",
    "sg:classifiers":[
        {
            "category":"Professional",
            "subcategory":"Lawyer & Legal Services",
            "type":"Services"
        }
    ],
    "sg:phone":"+1 972 680 7550",
    "sg:postcode":"75082",
    "sg:province":"TX",
    "sg:tags":[
        "attorney"
    ],
    "wof:name":"Haynes & Boone",
    "wof:placetype":"venue"
},
  "geometry": {"coordinates":[-96.699777,32.989828],"type":"Point"}
}