{
  "type": "Feature",
  "properties": {
    "iso:country":"US",
    "sg:address":"1127 Indian Autumn Trce",
    "sg:city":"Houston",
    "sg:classifiers":[
        {
            "category":"Restaurant",
            "type":"Food & Drink"
        }
    ],
    "sg:phone":"+1 281 480 6553",
    "sg:postcode":"77062",
    "sg:province":"TX",
    "sg:tags":[
        "eating"
    ],
    "wof:name":"Double Daves Paraland",
    "wof:placetype":"venue"
},
  "geometry": {"coordinates":[-95.14482,29.585419],"type":"Point"}
}