{
  "type": "Feature",
  "properties": {
    "iso:country":"US",
    "sg:address":"8610 Seawall Blvd",
    "sg:city":"Galveston",
    "sg:classifiers":[
        {
            "category":"Professional",
            "subcategory":"Engineering",
            "type":"Services"
        }
    ],
    "sg:phone":"+1 409 740 3787",
    "sg:postcode":"77554",
    "sg:province":"TX",
    "sg:tags":[
        "engineer"
    ],
    "wof:name":"Aran & Franklin Engineering",
    "wof:placetype":"venue"
},
  "geometry": {"coordinates":[-94.852665,29.251489],"type":"Point"}
}