{
  "type": "Feature",
  "properties": {
    "iso:country":"US",
    "sg:address":"5603 Tatteridge Dr",
    "sg:city":"Houston",
    "sg:classifiers":[
        {
            "category":"Professional",
            "type":"Services"
        }
    ],
    "sg:phone":"+1 281 444 3503",
    "sg:postcode":"77069",
    "sg:province":"TX",
    "wof:name":"Lapis Resources Inc",
    "wof:placetype":"venue"
},
  "geometry": {"coordinates":[-95.518677,29.99025],"type":"Point"}
}