{
  "type": "Feature",
  "properties": {
    "iso:country":"US",
    "sg:address":"16731 Tibet Rd",
    "sg:city":"Friendswood",
    "sg:classifiers":[
        {
            "category":"Manufacturing",
            "subcategory":"Metals",
            "type":"Manufacturing & Wholesale Goods"
        }
    ],
    "sg:phone":"+1 281 992 1254",
    "sg:postcode":"77546",
    "sg:province":"TX",
    "sg:tags":[
        "tool"
    ],
    "wof:name":"Snap On Tool Co",
    "wof:placetype":"venue"
},
  "geometry": {"coordinates":[-95.177431,29.528685],"type":"Point"}
}