{
  "type": "Feature",
  "properties": {
    "iso:country":"US",
    "sg:address":"4904 Sleepy Ridge Cir",
    "sg:city":"Fort Worth",
    "sg:classifiers":[
        {
            "category":"Building & Trades",
            "subcategory":"Construction",
            "type":"Services"
        }
    ],
    "sg:phone":"+1 817 370 9583",
    "sg:postcode":"76133",
    "sg:province":"TX",
    "sg:tags":[
        "contractor"
    ],
    "wof:name":"MO Install Inc",
    "wof:placetype":"venue"
},
  "geometry": {"coordinates":[-97.396959,32.636888],"type":"Point"}
}