{
  "type": "Feature",
  "properties": {
    "iso:country":"US",
    "sg:address":"3721 Tin Top Hwy",
    "sg:city":"Granbury",
    "sg:classifiers":[
        {
            "category":"Manufacturing",
            "subcategory":"Textiles",
            "type":"Manufacturing & Wholesale Goods"
        }
    ],
    "sg:phone":"+1 817 279 1851",
    "sg:postcode":"76048",
    "sg:province":"TX",
    "sg:tags":[
        "mfg"
    ],
    "wof:name":"Fast Back Rope Mfg",
    "wof:placetype":"venue"
},
  "geometry": {"coordinates":[-97.83538299999999,32.479328],"type":"Point"}
}