{
  "type": "Feature",
  "properties": {
    "iso:country":"US",
    "sg:address":"4710 Bellaire Blvd",
    "sg:city":"Bellaire",
    "sg:classifiers":[
        {
            "category":"Real Estate",
            "subcategory":"Surveying",
            "type":"Services"
        }
    ],
    "sg:phone":"+1 713 839 9181",
    "sg:postcode":"77401",
    "sg:province":"TX",
    "wof:name":"Civilsurv Land Surveying Lcc",
    "wof:placetype":"venue"
},
  "geometry": {"coordinates":[-95.462002,29.705891],"type":"Point"}
}