{
  "type": "Feature",
  "properties": {
    "iso:country":"US",
    "sg:address":"1515 Padre Blvd",
    "sg:city":"S Padre Island",
    "sg:classifiers":[
        {
            "category":"Taxi",
            "type":"Transportation"
        }
    ],
    "sg:phone":"+1 956 761 2222",
    "sg:postcode":"78597",
    "sg:province":"TX",
    "sg:tags":[
        "taxicab"
    ],
    "wof:name":"Island Cabs",
    "wof:placetype":"venue"
},
  "geometry": {"coordinates":[-97.16849000000001,26.105221],"type":"Point"}
}