{
  "type": "Feature",
  "properties": {
    "iso:country":"US",
    "sg:address":"401 Highway 71 W",
    "sg:city":"Bastrop",
    "sg:classifiers":[
        {
            "category":"Fast Food",
            "type":"Food & Drink"
        },
        {
            "category":"Restaurant",
            "type":"Food & Drink"
        }
    ],
    "sg:phone":"+1 512 321 0722",
    "sg:postcode":"78602",
    "sg:province":"TX",
    "sg:tags":[
        "american",
        "hot",
        "hamburger",
        "dog"
    ],
    "sg:website":"http://www.whataburger.com",
    "wof:name":"Whataburger Restaurants",
    "wof:placetype":"venue"
},
  "geometry": {"coordinates":[-97.33068799999999,30.105919],"type":"Point"}
}