{
  "type": "Feature",
  "properties": {
    "iso:country":"US",
    "sg:address":"408 Market St",
    "sg:city":"Orange",
    "sg:classifiers":[
        {
            "category":"Professional",
            "subcategory":"Computer Services",
            "type":"Services"
        }
    ],
    "sg:phone":"+1 409 886 0716",
    "sg:postcode":"77630",
    "sg:province":"TX",
    "sg:tags":[
        "related"
    ],
    "wof:name":"Rick Tallent",
    "wof:placetype":"venue"
},
  "geometry": {"coordinates":[-93.73591,30.084607],"type":"Point"}
}