{
  "type": "Feature",
  "properties": {
    "iso:country":"US",
    "sg:address":"1177 West Loop S",
    "sg:city":"Houston",
    "sg:classifiers":[
        {
            "category":"Professional",
            "subcategory":"Lawyer & Legal Services",
            "type":"Services"
        }
    ],
    "sg:phone":"+1 713 629 1580",
    "sg:postcode":"77027",
    "sg:province":"TX",
    "wof:name":"Sims G Byron Atty",
    "wof:placetype":"venue"
},
  "geometry": {"coordinates":[-95.4552,29.757799],"type":"Point"}
}