{
  "type": "Feature",
  "properties": {
    "iso:country":"US",
    "sg:address":"806 Meadowgate Dr",
    "sg:city":"Garland",
    "sg:classifiers":[
        {
            "category":"Home & Garden",
            "subcategory":"Building Materials",
            "type":"Retail Goods"
        }
    ],
    "sg:phone":"+1 972 530 9970",
    "sg:postcode":"75040",
    "sg:province":"TX",
    "wof:name":"Kickin Glass",
    "wof:placetype":"venue"
},
  "geometry": {"coordinates":[-96.640692,32.942515],"type":"Point"}
}