{
  "type": "Feature",
  "properties": {
    "iso:country":"US",
    "sg:address":"7720 W Montgomery Rd",
    "sg:city":"Houston",
    "sg:classifiers":[
        {
            "category":"Restaurant",
            "type":"Food & Drink"
        }
    ],
    "sg:phone":"+1 281 999 6498",
    "sg:postcode":"77088",
    "sg:province":"TX",
    "wof:name":"Chicken Shack Restaurant",
    "wof:placetype":"venue"
},
  "geometry": {"coordinates":[-95.42899300000001,29.864349],"type":"Point"}
}