{
  "type": "Feature",
  "properties": {
    "iso:country":"US",
    "sg:address":"2300 Interstate 30",
    "sg:city":"Mesquite",
    "sg:classifiers":[
        {
            "category":"Travel",
            "subcategory":"Hotels & Motels",
            "type":"Entertainment"
        }
    ],
    "sg:phone":"+1 972 681 3300",
    "sg:postcode":"75150",
    "sg:province":"TX",
    "wof:name":"Courtyard by Marriott",
    "wof:placetype":"venue"
},
  "geometry": {"coordinates":[-96.637007,32.818681],"type":"Point"}
}