{
  "type": "Feature",
  "properties": {
    "iso:country":"US",
    "sg:address":"251 SW Wilshire Blvd",
    "sg:city":"Burleson",
    "sg:classifiers":[
        {
            "category":"Restaurant",
            "type":"Food & Drink"
        }
    ],
    "sg:phone":"+1 817 426 2151",
    "sg:postcode":"76028",
    "sg:province":"TX",
    "sg:tags":[
        "eating"
    ],
    "wof:name":"Wingstop",
    "wof:placetype":"venue"
},
  "geometry": {"coordinates":[-97.32974900000001,32.542525],"type":"Point"}
}