{
  "type": "Feature",
  "properties": {
    "iso:country":"US",
    "sg:address":"17558 Matany Rd",
    "sg:city":"Justin",
    "sg:classifiers":[
        {
            "category":"Professional",
            "type":"Services"
        }
    ],
    "sg:phone":"+1 940 648 3529",
    "sg:postcode":"76247",
    "sg:province":"TX",
    "wof:name":"Russell M Goodman",
    "wof:placetype":"venue"
},
  "geometry": {"coordinates":[-97.31392700000001,33.040135],"type":"Point"}
}