{
  "type": "Feature",
  "properties": {
    "iso:country":"US",
    "sg:address":"918 State Hwy 97",
    "sg:city":"Pleasanton",
    "sg:classifiers":[
        {
            "category":"Professional",
            "subcategory":"Business Services",
            "type":"Services"
        }
    ],
    "sg:phone":"+1 830 569 2566",
    "sg:postcode":"78064",
    "sg:province":"TX",
    "wof:name":"USDA Gipsa Fgis",
    "wof:placetype":"venue"
},
  "geometry": {"coordinates":[-98.492848,28.956504],"type":"Point"}
}