{
  "type": "Feature",
  "properties": {
    "iso:country":"US",
    "sg:address":"13733 Harbor Dr",
    "sg:city":"Waco",
    "sg:classifiers":[
        {
            "category":"Home & Garden",
            "subcategory":"Building Materials",
            "type":"Retail Goods"
        }
    ],
    "sg:phone":"+1 254 772 5288",
    "sg:postcode":"76712",
    "sg:province":"TX",
    "wof:name":"Galaxy of Glass",
    "wof:placetype":"venue"
},
  "geometry": {"coordinates":[-97.243334,31.491743],"type":"Point"}
}