{
  "type": "Feature",
  "properties": {
    "iso:country":"US",
    "sg:address":"19747 Highway 59 N",
    "sg:city":"Humble",
    "sg:classifiers":[
        {
            "category":"Professional",
            "subcategory":"Accounting & Tax Preparation",
            "type":"Services"
        }
    ],
    "sg:phone":"+1 281 713 6928",
    "sg:postcode":"77338",
    "sg:province":"TX",
    "sg:tags":[
        "public",
        "representative",
        "accountants-certified",
        "taxes-consultants"
    ],
    "sg:website":"http://www.greaterhoustoncpa.com/",
    "wof:name":"Tribolet Fuller & Company PLLC",
    "wof:placetype":"venue"
},
  "geometry": {"coordinates":[-95.269638,30.002247],"type":"Point"}
}