{
  "type": "Feature",
  "properties": {
    "iso:country":"US",
    "sg:address":"145 Lake Lamond Rd",
    "sg:city":"Longview",
    "sg:phone":"+1 903 758 4446",
    "sg:postcode":"75604",
    "sg:province":"TX",
    "sg:tags":[
        "lubricating",
        "product",
        "oi",
        "petroleum",
        "diesel",
        "including"
    ],
    "wof:name":"H&W Petroleum",
    "wof:placetype":"venue"
},
  "geometry": {"coordinates":[-94.764015,32.499812],"type":"Point"}
}