{
  "type": "Feature",
  "properties": {
    "iso:country":"US",
    "sg:address":"638 W Ware Blvd",
    "sg:city":"San Antonio",
    "sg:classifiers":[
        {
            "category":"Building & Trades",
            "subcategory":"Cleaning & Sanitation",
            "type":"Services"
        }
    ],
    "sg:phone":"+1 210 590 6266",
    "sg:postcode":"78221",
    "sg:province":"TX",
    "sg:tags":[
        "maintenance",
        "merchandise"
    ],
    "wof:name":"A B C Cleaning & Restoration",
    "wof:placetype":"venue"
},
  "geometry": {"coordinates":[-98.50247299999999,29.348879],"type":"Point"}
}