{
  "type": "Feature",
  "properties": {
    "iso:country":"US",
    "sg:address":"326 Hurstgreen Ln",
    "sg:city":"Alvin",
    "sg:classifiers":[
        {
            "category":"Health Services",
            "subcategory":"Clinic",
            "type":"Services"
        }
    ],
    "sg:phone":"+1 281 331 8136",
    "sg:postcode":"77511",
    "sg:province":"TX",
    "sg:tags":[
        "specialty",
        "outpatient"
    ],
    "wof:name":"Alvin Counseling Services",
    "wof:placetype":"venue"
},
  "geometry": {"coordinates":[-95.234678,29.395239],"type":"Point"}
}