{
  "type": "Feature",
  "properties": {
    "iso:country":"US",
    "sg:address":"10515 Bellaire Blvd Ste E",
    "sg:city":"Houston",
    "sg:classifiers":[
        {
            "category":"Shopping",
            "subcategory":"Books",
            "type":"Retail Goods"
        }
    ],
    "sg:phone":"+1 281 564 1881",
    "sg:postcode":"77072",
    "sg:province":"TX",
    "sg:tags":[
        "bookstore"
    ],
    "wof:name":"Tinh Luat Book & Gift Store",
    "wof:placetype":"venue"
},
  "geometry": {"coordinates":[-95.565697,29.704],"type":"Point"}
}