{
  "type": "Feature",
  "properties": {
    "iso:country":"US",
    "sg:address":"6303 Forest Park Rd",
    "sg:city":"Dallas",
    "sg:classifiers":[
        {
            "category":"Restaurant",
            "type":"Food & Drink"
        }
    ],
    "sg:phone":"+1 214 351 4779",
    "sg:postcode":"75235",
    "sg:province":"TX",
    "sg:tags":[
        "beverage"
    ],
    "wof:name":"Beverage Spot",
    "wof:placetype":"venue"
},
  "geometry": {"coordinates":[-96.84573399999999,32.824007],"type":"Point"}
}