{
  "type": "Feature",
  "properties": {
    "iso:country":"US",
    "sg:address":"6405 Royal Oaks Dr",
    "sg:city":"Fort Worth",
    "sg:classifiers":[
        {
            "category":"Building & Trades",
            "subcategory":"Construction",
            "type":"Services"
        }
    ],
    "sg:phone":"+1 817 534 4726",
    "sg:postcode":"76119",
    "sg:province":"TX",
    "wof:name":"ME Burns Construction Inc",
    "wof:placetype":"venue"
},
  "geometry": {"coordinates":[-97.24739,32.665303],"type":"Point"}
}