{
  "type": "Feature",
  "properties": {
    "iso:country":"US",
    "sg:address":"35 Glen Knoll Dr",
    "sg:city":"Wylie",
    "sg:classifiers":[
        {
            "category":"Shopping",
            "type":"Retail Goods"
        }
    ],
    "sg:phone":"+1 972 429 8790",
    "sg:postcode":"75098",
    "sg:province":"TX",
    "sg:tags":[
        "merchandise"
    ],
    "wof:name":"J & H Collectibles",
    "wof:placetype":"venue"
},
  "geometry": {"coordinates":[-96.55715499999999,32.994153],"type":"Point"}
}