{
  "type": "Feature",
  "properties": {
    "iso:country":"US",
    "sg:address":"5353 Memorial Dr",
    "sg:city":"Houston",
    "sg:classifiers":[
        {
            "category":"Professional",
            "type":"Services"
        }
    ],
    "sg:phone":"+1 713 869 3374",
    "sg:postcode":"77007",
    "sg:province":"TX",
    "wof:name":"Ronald J Konantz Inc",
    "wof:placetype":"venue"
},
  "geometry": {"coordinates":[-95.41598999999999,29.761511],"type":"Point"}
}