{
  "type": "Feature",
  "properties": {
    "iso:country":"US",
    "sg:address":"1450 Combine Rd",
    "sg:city":"Seagoville",
    "sg:classifiers":[
        {
            "category":"Building & Trades",
            "subcategory":"Landscaping Services",
            "type":"Services"
        }
    ],
    "sg:phone":"+1 972 287 2338",
    "sg:postcode":"75159",
    "sg:province":"TX",
    "sg:tags":[
        "grass"
    ],
    "wof:name":"Landess Landscape & Nursery",
    "wof:placetype":"venue"
},
  "geometry": {"coordinates":[-96.532282,32.609259],"type":"Point"}
}