{
  "type": "Feature",
  "properties": {
    "iso:country":"US",
    "sg:address":"649 Washington Blvd",
    "sg:city":"Abilene",
    "sg:classifiers":[
        {
            "category":"Real Estate",
            "subcategory":"Real Estate Operator",
            "type":"Services"
        }
    ],
    "sg:phone":"+1 325 677 3707",
    "sg:postcode":"79601",
    "sg:province":"TX",
    "sg:tags":[
        "property",
        "lessor"
    ],
    "wof:name":"Dale King",
    "wof:placetype":"venue"
},
  "geometry": {"coordinates":[-99.710657,32.455513],"type":"Point"}
}