{
  "type": "Feature",
  "properties": {
    "iso:country":"US",
    "sg:address":"20535 Lakeside Dr",
    "sg:city":"Porter",
    "sg:classifiers":[
        {
            "category":"Professional",
            "subcategory":"Management & Consulting",
            "type":"Services"
        }
    ],
    "sg:phone":"+1 281 429 9273",
    "sg:postcode":"77365",
    "sg:province":"TX",
    "sg:tags":[
        "business"
    ],
    "wof:name":"Kriptic Designs",
    "wof:placetype":"venue"
},
  "geometry": {"coordinates":[-95.327355,30.152719],"type":"Point"}
}