{
  "type": "Feature",
  "properties": {
    "iso:country":"US",
    "sg:address":"2001 Windy Terrace #D",
    "sg:city":"Cedar Park",
    "sg:classifiers":[
        {
            "category":"Personal",
            "type":"Services"
        }
    ],
    "sg:phone":"+1 512 459 8118",
    "sg:postcode":"78613",
    "sg:province":"TX",
    "sg:tags":[
        "home"
    ],
    "sg:website":"www.austin-air-conditioning.com",
    "wof:name":"Austin Air Conditioning by Autumn",
    "wof:placetype":"venue"
},
  "geometry": {"coordinates":[-97.83340800000001,30.460841],"type":"Point"}
}