{
  "type": "Feature",
  "properties": {
    "iso:country":"US",
    "sg:address":"1685 State Hwy 100",
    "sg:city":"Port Isabel",
    "sg:classifiers":[
        {
            "category":"Food & Beverages",
            "subcategory":"Groceries & Convenience Stores",
            "type":"Retail Goods"
        }
    ],
    "sg:phone":"+1 956 943 3438",
    "sg:postcode":"78578",
    "sg:province":"TX",
    "sg:tags":[
        "station",
        "gas"
    ],
    "wof:name":"Circle K Store",
    "wof:placetype":"venue"
},
  "geometry": {"coordinates":[-97.226828,26.073177],"type":"Point"}
}