{
  "type": "Feature",
  "properties": {
    "iso:country":"US",
    "sg:address":"2428 S Stemmons Fwy",
    "sg:city":"Lewisville",
    "sg:classifiers":[
        {
            "category":"Retail",
            "subcategory":"Auto Repair",
            "type":"Services"
        }
    ],
    "sg:phone":"+1 972 459 7999",
    "sg:postcode":"75067",
    "sg:province":"TX",
    "sg:tags":[
        "repairing",
        "automobile"
    ],
    "wof:name":"Auto Clinic",
    "wof:placetype":"venue"
},
  "geometry": {"coordinates":[-96.966836,33.004476],"type":"Point"}
}