{
  "type": "Feature",
  "properties": {
    "iso:country":"US",
    "sg:address":"2404 Grant Ct",
    "sg:city":"Rockwall",
    "sg:classifiers":[
        {
            "category":"Utilities",
            "subcategory":"Mobile Phone",
            "type":"Services"
        }
    ],
    "sg:phone":"+1 972 772 5133",
    "sg:postcode":"75032",
    "sg:province":"TX",
    "sg:tags":[
        "communication",
        "radiotelephone"
    ],
    "wof:name":"Giga Wireless Inc",
    "wof:placetype":"venue"
},
  "geometry": {"coordinates":[-96.457312,32.872761],"type":"Point"}
}