{
  "type": "Feature",
  "properties": {
    "iso:country":"US",
    "sg:address":"1343 Pvt Rd 4021",
    "sg:city":"Gilmer",
    "sg:classifiers":[
        {
            "category":"Retail",
            "subcategory":"Auto Repair",
            "type":"Services"
        }
    ],
    "sg:phone":"+1 903 797 6493",
    "sg:postcode":"75644",
    "sg:province":"TX",
    "sg:tags":[
        "body"
    ],
    "wof:name":"Ritter Paint & Body",
    "wof:placetype":"venue"
},
  "geometry": {"coordinates":[-94.993962,32.743832],"type":"Point"}
}