{
  "type": "Feature",
  "properties": {
    "iso:country":"US",
    "sg:address":"1104 Pennsylvania St",
    "sg:city":"South Houston",
    "sg:classifiers":[
        {
            "category":"Shopping",
            "subcategory":"Computers & Home Electronics",
            "type":"Retail Goods"
        }
    ],
    "sg:phone":"+1 713 933 0390",
    "sg:postcode":"77587",
    "sg:province":"TX",
    "sg:tags":[
        "programing",
        "custom"
    ],
    "wof:name":"Network Systems & Solutions",
    "wof:placetype":"venue"
},
  "geometry": {"coordinates":[-95.24423400000001,29.658179],"type":"Point"}
}