{
  "type": "Feature",
  "properties": {
    "iso:country":"US",
    "sg:address":"2112 Oaks Dr",
    "sg:city":"Pasadena",
    "sg:classifiers":[
        {
            "category":"Building & Trades",
            "subcategory":"Landscaping Services",
            "type":"Services"
        }
    ],
    "sg:phone":"+1 713 589 0282",
    "sg:postcode":"77502",
    "sg:province":"TX",
    "wof:name":"Speedy Lawn Service",
    "wof:placetype":"venue"
},
  "geometry": {"coordinates":[-95.21505399999999,29.679785],"type":"Point"}
}