{
  "type": "Feature",
  "properties": {
    "iso:country":"US",
    "sg:address":"17022 Highway 3",
    "sg:city":"Webster",
    "sg:classifiers":[
        {
            "category":"Personal",
            "subcategory":"Beauty Salon",
            "type":"Services"
        }
    ],
    "sg:phone":"+1 281 338 6507",
    "sg:postcode":"77598",
    "sg:province":"TX",
    "wof:name":"Splash Hair Designs",
    "wof:placetype":"venue"
},
  "geometry": {"coordinates":[-95.125883,29.546011],"type":"Point"}
}