{
  "type": "Feature",
  "properties": {
    "iso:country":"US",
    "sg:address":"408 W Davis St",
    "sg:city":"Dallas",
    "sg:classifiers":[
        {
            "category":"Shopping",
            "subcategory":"Florist",
            "type":"Retail Goods"
        }
    ],
    "sg:phone":"+1 214 484 1325",
    "sg:postcode":"75208",
    "sg:province":"TX",
    "sg:website":"www.installationfloral.com",
    "wof:name":"Installation Floral",
    "wof:placetype":"venue"
},
  "geometry": {"coordinates":[-96.828807,32.749281],"type":"Point"}
}