{
  "type": "Feature",
  "properties": {
    "iso:country":"US",
    "sg:address":"2825 Southerland St",
    "sg:city":"Beaumont",
    "sg:classifiers":[
        {
            "category":"Personal",
            "subcategory":"Beauty Salon",
            "type":"Services"
        }
    ],
    "sg:phone":"+1 409 842 3565",
    "sg:postcode":"77705",
    "sg:province":"TX",
    "sg:tags":[
        "shop"
    ],
    "wof:name":"Cade's Beauty Shop",
    "wof:placetype":"venue"
},
  "geometry": {"coordinates":[-94.115154,30.053217],"type":"Point"}
}