{
  "type": "Feature",
  "properties": {
    "iso:country":"US",
    "sg:address":"3517 SE 8th St",
    "sg:city":"Grand Prairie",
    "sg:classifiers":[
        {
            "category":"Real Estate",
            "subcategory":"Real Estate Operator",
            "type":"Services"
        }
    ],
    "sg:phone":"+1 972 263 2901",
    "sg:postcode":"75052",
    "sg:province":"TX",
    "sg:tags":[
        "building",
        "apartment"
    ],
    "wof:name":"Highlands Of Grand Prairie",
    "wof:placetype":"venue"
},
  "geometry": {"coordinates":[-97.003114,32.692485],"type":"Point"}
}