{
  "type": "Feature",
  "properties": {
    "iso:country":"US",
    "sg:address":"2001 Deer Path Dr",
    "sg:city":"Dallas",
    "sg:classifiers":[
        {
            "category":"Education",
            "subcategory":"School",
            "type":"Public Place"
        }
    ],
    "sg:phone":"+1 972 502 8500",
    "sg:postcode":"75216",
    "sg:province":"TX",
    "sg:website":"www.dallasisd.org",
    "wof:name":"Schools",
    "wof:placetype":"venue"
},
  "geometry": {"coordinates":[-96.79602,32.710383],"type":"Point"}
}