{
  "type": "Feature",
  "properties": {
    "iso:country":"US",
    "sg:address":"4502 S 2nd Ave",
    "sg:city":"Dallas",
    "sg:classifiers":[
        {
            "category":"Shopping",
            "subcategory":"Used Merchandise",
            "type":"Retail Goods"
        }
    ],
    "sg:phone":"+1 214 421 5624",
    "sg:postcode":"75210",
    "sg:province":"TX",
    "sg:tags":[
        "furniture"
    ],
    "wof:name":"John's Used Furniture",
    "wof:placetype":"venue"
},
  "geometry": {"coordinates":[-96.747585,32.763677],"type":"Point"}
}