{
  "type": "Feature",
  "properties": {
    "iso:country":"US",
    "sg:address":"21 Palm Blvd",
    "sg:city":"Brownsville",
    "sg:classifiers":[
        {
            "category":"Shopping",
            "subcategory":"Discount & Variety Stores",
            "type":"Retail Goods"
        }
    ],
    "sg:phone":"+1 956 541 0165",
    "sg:postcode":"78520",
    "sg:province":"TX",
    "sg:tags":[
        "merchandise",
        "general"
    ],
    "wof:name":"Ninety Nine Cents Plus",
    "wof:placetype":"venue"
},
  "geometry": {"coordinates":[-97.510169,25.906345],"type":"Point"}
}