{
  "type": "Feature",
  "properties": {
    "iso:country":"US",
    "sg:address":"20703 Stone Mountain Ln",
    "sg:city":"Houston",
    "sg:classifiers":[
        {
            "category":"Building & Trades",
            "subcategory":"Construction",
            "type":"Services"
        }
    ],
    "sg:phone":"+1 281 449 9393",
    "sg:postcode":"77073",
    "sg:province":"TX",
    "sg:tags":[
        "wallpaper"
    ],
    "wof:name":"American Wallcovering",
    "wof:placetype":"venue"
},
  "geometry": {"coordinates":[-95.38724499999999,30.008872],"type":"Point"}
}