{
  "type": "Feature",
  "properties": {
    "iso:country":"US",
    "sg:address":"1300 E Whaley St",
    "sg:city":"Longview",
    "sg:classifiers":[
        {
            "category":"Wholesale",
            "subcategory":"Machinery & Supplies",
            "type":"Manufacturing & Wholesale Goods"
        }
    ],
    "sg:phone":"+1 903 758 9440",
    "sg:postcode":"75601",
    "sg:province":"TX",
    "sg:tags":[
        "transmission",
        "bearing",
        "power",
        "equipment"
    ],
    "wof:name":"Applied Industrial Tech",
    "wof:placetype":"venue"
},
  "geometry": {"coordinates":[-94.719589,32.498894],"type":"Point"}
}