{
  "type": "Feature",
  "properties": {
    "iso:country":"US",
    "sg:address":"7193 Co Rd 65",
    "sg:city":"Taft",
    "sg:classifiers":[
        {
            "category":"Professional",
            "subcategory":"Business Services",
            "type":"Services"
        }
    ],
    "sg:phone":"+1 361 528 2438",
    "sg:postcode":"78390",
    "sg:province":"TX",
    "wof:name":"Southwestern Farm Bus Svc Inc",
    "wof:placetype":"venue"
},
  "geometry": {"coordinates":[-97.44844500000001,28.003659],"type":"Point"}
}