{
  "type": "Feature",
  "properties": {
    "iso:country":"US",
    "sg:address":"2625 S 7th St",
    "sg:city":"Abilene",
    "sg:classifiers":[
        {
            "category":"Government",
            "subcategory":"Office",
            "type":"Public Place"
        }
    ],
    "sg:phone":"+1 325 673 4694",
    "sg:postcode":"79605",
    "sg:province":"TX",
    "sg:tags":[
        "village"
    ],
    "wof:name":"Abilene Senior Citizens",
    "wof:placetype":"venue"
},
  "geometry": {"coordinates":[-99.75419599999999,32.443601],"type":"Point"}
}