{
  "type": "Feature",
  "properties": {
    "iso:country":"US",
    "sg:address":"314 S 23rd St",
    "sg:city":"Mcallen",
    "sg:classifiers":[
        {
            "category":"Shopping",
            "subcategory":"Discount & Variety Stores",
            "type":"Retail Goods"
        },
        {
            "category":"Shopping",
            "subcategory":"Department Store",
            "type":"Retail Goods"
        }
    ],
    "sg:phone":"+1 956 682 8580",
    "sg:postcode":"78501",
    "sg:province":"TX",
    "sg:tags":[
        "merchandise",
        "general"
    ],
    "wof:name":"Al's Merchandise",
    "wof:placetype":"venue"
},
  "geometry": {"coordinates":[-98.245788,26.202411],"type":"Point"}
}