{
  "type": "Feature",
  "properties": {
    "iso:country":"US",
    "sg:address":"5433 Charrin Dr",
    "sg:city":"Houston",
    "sg:classifiers":[
        {
            "category":"Freight",
            "type":"Transportation"
        }
    ],
    "sg:phone":"+1 281 442 4888",
    "sg:postcode":"77032",
    "sg:province":"TX",
    "sg:tags":[
        "courier"
    ],
    "wof:name":"American Courier LLC",
    "wof:placetype":"venue"
},
  "geometry": {"coordinates":[-95.30650300000001,29.924547],"type":"Point"}
}