{
  "type": "Feature",
  "properties": {
    "iso:country":"US",
    "sg:address":"1716 Bimini Way",
    "sg:city":"Seabrook",
    "sg:classifiers":[
        {
            "category":"Shopping",
            "type":"Retail Goods"
        }
    ],
    "sg:phone":"+1 281 474 9768",
    "sg:postcode":"77586",
    "sg:province":"TX",
    "sg:tags":[
        "miscellaneous",
        "store"
    ],
    "wof:name":"Keys Unlimited",
    "wof:placetype":"venue"
},
  "geometry": {"coordinates":[-95.01894,29.568351],"type":"Point"}
}