{
  "type": "Feature",
  "properties": {
    "iso:country":"US",
    "sg:address":"102 Hillcrest Rd",
    "sg:city":"Brownwood",
    "sg:classifiers":[
        {
            "category":"Autos & Motor Vehicles",
            "subcategory":"Automobile Sales",
            "type":"Retail Goods"
        }
    ],
    "sg:phone":"+1 325 646 9644",
    "sg:postcode":"76802",
    "sg:province":"TX",
    "sg:tags":[
        "used"
    ],
    "wof:name":"Adams Auto Sales",
    "wof:placetype":"venue"
},
  "geometry": {"coordinates":[-98.95201400000001,31.738555],"type":"Point"}
}