{
  "type": "Feature",
  "properties": {
    "iso:country":"US",
    "sg:address":"9 Eastlane Pl",
    "sg:city":"Plano",
    "sg:classifiers":[
        {
            "category":"Professional",
            "subcategory":"Management & Consulting",
            "type":"Services"
        }
    ],
    "sg:phone":"+1 972 423 7362",
    "sg:postcode":"75074",
    "sg:province":"TX",
    "sg:tags":[
        "refrigeration",
        "contractor"
    ],
    "wof:name":"B T Products",
    "wof:placetype":"venue"
},
  "geometry": {"coordinates":[-96.66631700000001,33.023698],"type":"Point"}
}