{
  "type": "Feature",
  "properties": {
    "iso:country":"US",
    "sg:address":"1300 Ave H",
    "sg:city":"Bay City",
    "sg:classifiers":[
        {
            "category":"Personal",
            "subcategory":"Beauty Salon",
            "type":"Services"
        }
    ],
    "sg:phone":"+1 979 245 3737",
    "sg:postcode":"77414",
    "sg:province":"TX",
    "sg:tags":[
        "shop"
    ],
    "wof:name":"Cathy's Hair Co",
    "wof:placetype":"venue"
},
  "geometry": {"coordinates":[-95.967951,28.991352],"type":"Point"}
}