{
  "type": "Feature",
  "properties": {
    "iso:country":"US",
    "sg:address":"20534 Marilyn Ln",
    "sg:city":"Spring",
    "sg:classifiers":[
        {
            "category":"Building & Trades",
            "subcategory":"Construction",
            "type":"Services"
        }
    ],
    "sg:phone":"+1 281 350 2266",
    "sg:postcode":"77388",
    "sg:province":"TX",
    "sg:tags":[
        "nonresidential"
    ],
    "wof:name":"Dockery Construction",
    "wof:placetype":"venue"
},
  "geometry": {"coordinates":[-95.439312,30.066221],"type":"Point"}
}