{
  "type": "Feature",
  "properties": {
    "iso:country":"US",
    "sg:address":"4012 Cedar Springs Rd",
    "sg:city":"Dallas",
    "sg:classifiers":[
        {
            "category":"Organizations",
            "subcategory":"Non-profit Organization",
            "type":"Services"
        },
        {
            "category":"Science Facility",
            "type":"Public Place"
        }
    ],
    "sg:phone":"+1 214 559 0339",
    "sg:postcode":"75219",
    "sg:province":"TX",
    "sg:tags":[
        "development",
        "laboratories-research",
        "service/non-profit",
        "community"
    ],
    "wof:name":"AIDS Resource Center Of Dallas",
    "wof:placetype":"venue"
},
  "geometry": {"coordinates":[-96.81145600000001,32.811351],"type":"Point"}
}