{
  "type": "Feature",
  "properties": {
    "iso:country":"US",
    "sg:address":"6444 Westheimer Rd",
    "sg:city":"Houston",
    "sg:classifiers":[
        {
            "category":"Autos & Motor Vehicles",
            "subcategory":"Automobile Sales",
            "type":"Retail Goods"
        },
        {
            "category":"Airline",
            "type":"Transportation"
        }
    ],
    "sg:phone":"+1 832 242 5466",
    "sg:postcode":"77057",
    "sg:province":"TX",
    "sg:tags":[
        "shuttle",
        "airport",
        "limo"
    ],
    "sg:website":"www.aimlimo.com",
    "wof:name":"Aim Limousine",
    "wof:placetype":"venue"
},
  "geometry": {"coordinates":[-95.49744200000001,29.737761],"type":"Point"}
}