{
  "type": "Feature",
  "properties": {
    "iso:country":"US",
    "sg:address":"4621 Marie St",
    "sg:city":"Corpus Christi",
    "sg:classifiers":[
        {
            "category":"Education",
            "subcategory":"School",
            "type":"Public Place"
        }
    ],
    "sg:phone":"+1 361 878 1700",
    "sg:postcode":"78411",
    "sg:province":"TX",
    "wof:name":"William C Calk Elementary Schl",
    "wof:placetype":"venue"
},
  "geometry": {"coordinates":[-97.388156,27.725011],"type":"Point"}
}