{
  "type": "Feature",
  "properties": {
    "iso:country":"US",
    "sg:address":"506 W 15th St",
    "sg:city":"Austin",
    "sg:classifiers":[
        {
            "category":"Professional",
            "subcategory":"Lawyer & Legal Services",
            "type":"Services"
        }
    ],
    "sg:phone":"+1 512 476 0888",
    "sg:postcode":"78701",
    "sg:province":"TX",
    "sg:tags":[
        "attorney",
        "provides"
    ],
    "wof:name":"Greening Law Firm PC",
    "wof:placetype":"venue"
},
  "geometry": {"coordinates":[-97.745046,30.27863],"type":"Point"}
}