{
  "type": "Feature",
  "properties": {
    "iso:country":"US",
    "sg:address":"2618 Oak Lawn Ave",
    "sg:city":"Dallas",
    "sg:classifiers":[
        {
            "category":"Professional",
            "subcategory":"Lawyer & Legal Services",
            "type":"Services"
        }
    ],
    "sg:phone":"+1 214 559 3444",
    "sg:postcode":"75219",
    "sg:province":"TX",
    "sg:tags":[
        "attorney",
        "law"
    ],
    "sg:website":"www.robertsgregg.com",
    "wof:name":"Robert S Gregg PC",
    "wof:placetype":"venue"
},
  "geometry": {"coordinates":[-96.812178,32.805848],"type":"Point"}
}