{
  "type": "Feature",
  "properties": {
    "iso:country":"US",
    "sg:address":"3000 Hayes Rd",
    "sg:city":"Houston",
    "sg:classifiers":[
        {
            "category":"Wholesale",
            "subcategory":"Groceries",
            "type":"Manufacturing & Wholesale Goods"
        }
    ],
    "sg:phone":"+1 281 496 2032",
    "sg:postcode":"77082",
    "sg:province":"TX",
    "sg:tags":[
        "general"
    ],
    "wof:name":"Star Brokerage Inc",
    "wof:placetype":"venue"
},
  "geometry": {"coordinates":[-95.575722,29.730604],"type":"Point"}
}