{
  "type": "Feature",
  "properties": {
    "iso:country":"US",
    "sg:address":"16350 Park Row",
    "sg:city":"Houston",
    "sg:classifiers":[
        {
            "category":"Professional",
            "subcategory":"Lawyer & Legal Services",
            "type":"Services"
        }
    ],
    "sg:phone":"+1 281 646 1099",
    "sg:postcode":"77084",
    "sg:province":"TX",
    "wof:name":"Thiebeau L Therese Atty Counse",
    "wof:placetype":"venue"
},
  "geometry": {"coordinates":[-95.664912,29.789153],"type":"Point"}
}