{
  "type": "Feature",
  "properties": {
    "iso:country":"US",
    "sg:address":"8550 Frazier Dr",
    "sg:city":"Beaumont",
    "sg:classifiers":[
        {
            "category":"Professional",
            "type":"Services"
        }
    ],
    "sg:phone":"+1 409 860 9092",
    "sg:postcode":"77707",
    "sg:province":"TX",
    "wof:name":"Music Makers",
    "wof:placetype":"venue"
},
  "geometry": {"coordinates":[-94.190155,30.05953],"type":"Point"}
}