{
  "type": "Feature",
  "properties": {
    "iso:country":"US",
    "sg:address":"240 N Wills St",
    "sg:city":"Wills Point",
    "sg:classifiers":[
        {
            "category":"Travel",
            "subcategory":"Campground",
            "type":"Entertainment"
        }
    ],
    "sg:phone":"+1 903 560 0246",
    "sg:postcode":"75169",
    "sg:province":"TX",
    "sg:tags":[
        "camp"
    ],
    "wof:name":"Rocking L Guest Ranch",
    "wof:placetype":"venue"
},
  "geometry": {"coordinates":[-96.011101,32.710015],"type":"Point"}
}