{
  "type": "Feature",
  "properties": {
    "iso:country":"US",
    "sg:address":"11305 Alexandria Dr",
    "sg:city":"Frisco",
    "sg:classifiers":[
        {
            "category":"Insurance",
            "subcategory":"Insurance Agent",
            "type":"Services"
        }
    ],
    "sg:phone":"+1 972 712 8926",
    "sg:postcode":"75035",
    "sg:province":"TX",
    "wof:name":"AXA Fine Art Insurance Corp",
    "wof:placetype":"venue"
},
  "geometry": {"coordinates":[-96.780643,33.128279],"type":"Point"}
}