{
  "type": "Feature",
  "properties": {
    "iso:country":"US",
    "sg:address":"9216 FM 725",
    "sg:city":"Mc Queeney",
    "sg:classifiers":[
        {
            "category":"Restaurant",
            "type":"Food & Drink"
        }
    ],
    "sg:phone":"+1 830 557 6335",
    "sg:postcode":"78130",
    "sg:province":"TX",
    "wof:name":"Blake's Cafe",
    "wof:placetype":"venue"
},
  "geometry": {"coordinates":[-98.042239,29.59338],"type":"Point"}
}