{
  "type": "Feature",
  "properties": {
    "iso:country":"US",
    "sg:address":"1802 Center St",
    "sg:city":"Deer Park",
    "sg:classifiers":[
        {
            "category":"Home & Garden",
            "subcategory":"Home Furnishings",
            "type":"Retail Goods"
        }
    ],
    "sg:phone":"+1 281 479 9691",
    "sg:postcode":"77536",
    "sg:province":"TX",
    "wof:name":"Frame-It/Pasadena",
    "wof:placetype":"venue"
},
  "geometry": {"coordinates":[-95.123745,29.695402],"type":"Point"}
}