{
  "type": "Feature",
  "properties": {
    "iso:country":"US",
    "sg:address":"1340 E 7th St",
    "sg:city":"Odessa",
    "sg:classifiers":[
        {
            "category":"Social Services",
            "subcategory":"Job Training",
            "type":"Services"
        }
    ],
    "sg:phone":"+1 432 580 3331",
    "sg:postcode":"79761",
    "sg:province":"TX",
    "sg:tags":[
        "rehabilitation"
    ],
    "wof:name":"Professional Rehabilitation",
    "wof:placetype":"venue"
},
  "geometry": {"coordinates":[-102.356341,31.856888],"type":"Point"}
}