{
  "type": "Feature",
  "properties": {
    "iso:country":"US",
    "sg:address":"109 N Mesa St",
    "sg:city":"El Paso",
    "sg:classifiers":[
        {
            "category":"Shopping",
            "subcategory":"Jewelry",
            "type":"Retail Goods"
        }
    ],
    "sg:phone":"+1 915 838 6333",
    "sg:postcode":"79901",
    "sg:province":"TX",
    "sg:tags":[
        "jeweler"
    ],
    "wof:name":"Joyeria Mexico",
    "wof:placetype":"venue"
},
  "geometry": {"coordinates":[-106.487188,31.758746],"type":"Point"}
}