{
  "type": "Feature",
  "properties": {
    "iso:country":"US",
    "sg:address":"3424 Kiest Hill Dr",
    "sg:city":"Dallas",
    "sg:classifiers":[
        {
            "category":"Manufacturing",
            "subcategory":"Wood Products",
            "type":"Manufacturing & Wholesale Goods"
        }
    ],
    "sg:phone":"+1 214 339 5723",
    "sg:postcode":"75233",
    "sg:province":"TX",
    "sg:tags":[
        "reconstituted",
        "mfg"
    ],
    "wof:name":"Bulletin Board Shop",
    "wof:placetype":"venue"
},
  "geometry": {"coordinates":[-96.879158,32.703657],"type":"Point"}
}