{
  "type": "Feature",
  "properties": {
    "iso:country":"US",
    "sg:address":"8499 Greenville Ave",
    "sg:city":"Dallas",
    "sg:classifiers":[
        {
            "category":"Health Services",
            "subcategory":"Health Practitioner",
            "type":"Services"
        }
    ],
    "sg:phone":"+1 214 348 5595",
    "sg:postcode":"75231",
    "sg:province":"TX",
    "sg:tags":[
        "psychologist",
        "doctor"
    ],
    "wof:name":"Muirhead J Lawrence PHD",
    "wof:placetype":"venue"
},
  "geometry": {"coordinates":[-96.753502,32.8937],"type":"Point"}
}