{
  "type": "Feature",
  "properties": {
    "iso:country":"US",
    "sg:address":"4332 SW 45th Ave",
    "sg:city":"Amarillo",
    "sg:classifiers":[
        {
            "category":"Restaurant",
            "type":"Food & Drink"
        }
    ],
    "sg:menulink":"http://www.allmenus.com/tx/amarillo/147233-montana-mikes-steakhouse/menu/",
    "sg:phone":"+1 806 353 3339",
    "sg:postcode":"79109",
    "sg:province":"TX",
    "sg:tags":[
        "american",
        "steakhouse"
    ],
    "wof:name":"Montana Mike's Steakhouse",
    "wof:placetype":"venue"
},
  "geometry": {"coordinates":[-101.886822,35.163241],"type":"Point"}
}