{
  "type": "Feature",
  "properties": {
    "iso:country":"US",
    "sg:address":"9801 Westheimer Rd Ste 302",
    "sg:city":"Houston",
    "sg:classifiers":[
        {
            "category":"Banks & Credit Unions",
            "subcategory":"Financial Services",
            "type":"Services"
        }
    ],
    "sg:phone":"+1 713 917 6742",
    "sg:postcode":"77042",
    "sg:province":"TX",
    "sg:tags":[
        "broker",
        "mortgage"
    ],
    "sg:website":"www.somortgage.net",
    "wof:name":"Southern Mortgage",
    "wof:placetype":"venue"
},
  "geometry": {"coordinates":[-95.54209899999999,29.737101],"type":"Point"}
}