{
  "type": "Feature",
  "properties": {
    "iso:country":"US",
    "sg:address":"232 E Crosstimbers St",
    "sg:city":"Houston",
    "sg:classifiers":[
        {
            "category":"Health Services",
            "subcategory":"Doctor",
            "type":"Services"
        }
    ],
    "sg:phone":"+1 713 697 3363",
    "sg:postcode":"77022",
    "sg:province":"TX",
    "sg:tags":[
        "clinic"
    ],
    "wof:name":"Castaneda Medical & Surgical",
    "wof:placetype":"venue"
},
  "geometry": {"coordinates":[-95.3734,29.828302],"type":"Point"}
}