{
  "type": "Feature",
  "properties": {
    "iso:country":"US",
    "sg:address":"4601 W Park Blvd",
    "sg:city":"Plano",
    "sg:classifiers":[
        {
            "category":"Food & Beverages",
            "subcategory":"Groceries & Convenience Stores",
            "type":"Retail Goods"
        }
    ],
    "sg:phone":"+1 972 596 7929",
    "sg:postcode":"75093",
    "sg:province":"TX",
    "wof:name":"Friendly Lucky Lady",
    "wof:placetype":"venue"
},
  "geometry": {"coordinates":[-96.78657,33.02702],"type":"Point"}
}