{
  "type": "Feature",
  "properties": {
    "iso:country":"US",
    "sg:address":"808 China St",
    "sg:city":"El Campo",
    "sg:classifiers":[
        {
            "category":"Retail",
            "subcategory":"Auto Repair",
            "type":"Services"
        }
    ],
    "sg:phone":"+1 979 543 0002",
    "sg:postcode":"77437",
    "sg:province":"TX",
    "sg:tags":[
        "glass",
        "replacement"
    ],
    "wof:name":"C O D Mobile Auto Glass",
    "wof:placetype":"venue"
},
  "geometry": {"coordinates":[-96.281209,29.19663],"type":"Point"}
}