{
  "type": "Feature",
  "properties": {
    "iso:country":"US",
    "sg:address":"1314 S Polk St",
    "sg:city":"Amarillo",
    "sg:classifiers":[
        {
            "category":"Professional",
            "subcategory":"Management & Consulting",
            "type":"Services"
        }
    ],
    "sg:phone":"+1 806 371 2900",
    "sg:postcode":"79101",
    "sg:province":"AR",
    "wof:name":"Amarillo College",
    "wof:placetype":"venue"
},
  "geometry": {"coordinates":[-101.838618,35.199466],"type":"Point"}
}