{
  "type": "Feature",
  "properties": {
    "iso:country":"US",
    "sg:address":"3717 Ridglea Country Club Dr",
    "sg:city":"Fort Worth",
    "sg:classifiers":[
        {
            "category":"Professional",
            "subcategory":"Management & Consulting",
            "type":"Services"
        }
    ],
    "sg:phone":"+1 817 294 4942",
    "sg:postcode":"76116",
    "sg:province":"TX",
    "wof:name":"Bridges Enterprises",
    "wof:placetype":"venue"
},
  "geometry": {"coordinates":[-97.43023100000001,32.695838],"type":"Point"}
}