{
  "type": "Feature",
  "properties": {
    "iso:country":"US",
    "sg:address":"918 Pinewood Ln",
    "sg:city":"Seabrook",
    "sg:classifiers":[
        {
            "category":"Building & Trades",
            "subcategory":"Construction",
            "type":"Services"
        }
    ],
    "sg:phone":"+1 281 326 4717",
    "sg:postcode":"77586",
    "sg:province":"TX",
    "sg:tags":[
        "house"
    ],
    "wof:name":"Horton N R Custom Homes Cnstr",
    "wof:placetype":"venue"
},
  "geometry": {"coordinates":[-95.057496,29.577833],"type":"Point"}
}