{
  "type": "Feature",
  "properties": {
    "iso:country":"US",
    "sg:address":"5110 Griggs Rd",
    "sg:city":"Houston",
    "sg:classifiers":[
        {
            "category":"Wholesale",
            "subcategory":"Apparel",
            "type":"Manufacturing & Wholesale Goods"
        }
    ],
    "sg:phone":"+1 713 748 4583",
    "sg:postcode":"77021",
    "sg:province":"TX",
    "sg:tags":[
        "clothing",
        "women's"
    ],
    "wof:name":"High Fashion & Style",
    "wof:placetype":"venue"
},
  "geometry": {"coordinates":[-95.33869900000001,29.698299],"type":"Point"}
}