{
  "type": "Feature",
  "properties": {
    "iso:country":"US",
    "sg:address":"4707 Texas Blvd",
    "sg:city":"Texarkana",
    "sg:classifiers":[
        {
            "category":"Building & Trades",
            "subcategory":"Equipment Rental",
            "type":"Services"
        }
    ],
    "sg:phone":"+1 903 792 8733",
    "sg:postcode":"75503",
    "sg:province":"TX",
    "wof:name":"Rent-A-Center",
    "wof:placetype":"venue"
},
  "geometry": {"coordinates":[-94.04634900000001,33.460658],"type":"Point"}
}