{
  "type": "Feature",
  "properties": {
    "iso:country":"US",
    "sg:address":"2833 Century St",
    "sg:city":"Dallas",
    "sg:classifiers":[
        {
            "category":"Professional",
            "subcategory":"Management & Consulting",
            "type":"Services"
        }
    ],
    "sg:phone":"+1 214 350 0032",
    "sg:postcode":"75220",
    "sg:province":"TX",
    "sg:tags":[
        "investment"
    ],
    "wof:name":"M E Inc",
    "wof:placetype":"venue"
},
  "geometry": {"coordinates":[-96.879193,32.870518],"type":"Point"}
}