{
  "type": "Feature",
  "properties": {
    "iso:country":"US",
    "sg:address":"7750 N Macarthur Blvd",
    "sg:city":"Irving",
    "sg:classifiers":[
        {
            "category":"Arts & Performance",
            "subcategory":"Theater",
            "type":"Entertainment"
        }
    ],
    "sg:phone":"+1 817 705 7463",
    "sg:postcode":"75063",
    "sg:province":"TX",
    "sg:tags":[
        "karaoke"
    ],
    "wof:name":"Sabel Stars Karaoke",
    "wof:placetype":"venue"
},
  "geometry": {"coordinates":[-96.95871099999999,32.911873],"type":"Point"}
}