{
  "type": "Feature",
  "properties": {
    "iso:country":"US",
    "sg:address":"1924 Village Park Dr",
    "sg:city":"Missouri City",
    "sg:classifiers":[
        {
            "category":"Local Transit",
            "type":"Transportation"
        }
    ],
    "sg:phone":"+1 281 261 2209",
    "sg:postcode":"77489",
    "sg:province":"TX",
    "sg:tags":[
        "passenger",
        "limousine"
    ],
    "wof:name":"Pleasant Town Car Service",
    "wof:placetype":"venue"
},
  "geometry": {"coordinates":[-95.53504,29.599443],"type":"Point"}
}