{
  "type": "Feature",
  "properties": {
    "iso:country":"US",
    "sg:address":"13119 Veterans Memorial Dr",
    "sg:city":"Houston",
    "sg:classifiers":[
        {
            "category":"Health Services",
            "subcategory":"Doctor",
            "type":"Services"
        }
    ],
    "sg:phone":"+1 281 537 5300",
    "sg:postcode":"77014",
    "sg:province":"TX",
    "sg:tags":[
        "physician",
        "surgeon"
    ],
    "sg:website":"www.memorialphysicians.com",
    "wof:name":"Memorial Physician Assoc",
    "wof:placetype":"venue"
},
  "geometry": {"coordinates":[-95.49107600000001,29.978068],"type":"Point"}
}