{
  "type": "Feature",
  "properties": {
    "iso:country":"US",
    "sg:address":"114 Acacia Arch St",
    "sg:city":"Portland",
    "sg:classifiers":[
        {
            "category":"Professional",
            "type":"Services"
        }
    ],
    "sg:phone":"+1 361 643 9076",
    "sg:postcode":"78374",
    "sg:province":"TX",
    "wof:name":"Kc Services",
    "wof:placetype":"venue"
},
  "geometry": {"coordinates":[-97.31752299999999,27.873092],"type":"Point"}
}