{
  "type": "Feature",
  "properties": {
    "iso:country":"US",
    "sg:address":"13150 Stable Rd",
    "sg:city":"El Paso",
    "sg:classifiers":[
        {
            "category":"Retail",
            "subcategory":"Repair Shop",
            "type":"Services"
        }
    ],
    "sg:phone":"+1 915 855 0501",
    "sg:postcode":"79938",
    "sg:province":"TX",
    "sg:tags":[
        "taxidermist"
    ],
    "wof:name":"Upland Art",
    "wof:placetype":"venue"
},
  "geometry": {"coordinates":[-106.226916,31.820605],"type":"Point"}
}