{
  "type": "Feature",
  "properties": {
    "iso:country":"US",
    "sg:address":"4041 W Wheatland Rd",
    "sg:city":"Dallas",
    "sg:classifiers":[
        {
            "category":"Health Services",
            "subcategory":"Clinic",
            "type":"Services"
        },
        {
            "category":"Community Center",
            "type":"Public Place"
        },
        {
            "category":"Health Services",
            "subcategory":"Chiropractor",
            "type":"Services"
        }
    ],
    "sg:phone":"+1 972 283 3300",
    "sg:postcode":"75237",
    "sg:province":"TX",
    "sg:tags":[
        "medical",
        "chiropractic"
    ],
    "sg:website":"http://www.modernbackandneckclinic.com",
    "wof:name":"Texas Cellular",
    "wof:placetype":"venue"
},
  "geometry": {"coordinates":[-96.885818,32.64761],"type":"Point"}
}