{
  "type": "Feature",
  "properties": {
    "iso:country":"US",
    "sg:address":"200 N Washington St",
    "sg:city":"Seymour",
    "sg:classifiers":[
        {
            "category":"Restaurant",
            "type":"Food & Drink"
        }
    ],
    "sg:phone":"+1 940 889 8405",
    "sg:postcode":"76380",
    "sg:province":"TX",
    "sg:tags":[
        "eating"
    ],
    "wof:name":"Sandwich Shoppe",
    "wof:placetype":"venue"
},
  "geometry": {"coordinates":[-99.261698,33.590052],"type":"Point"}
}