{
  "type": "Feature",
  "properties": {
    "iso:country":"US",
    "sg:address":"3005 S Padre Island Dr",
    "sg:city":"Corpus Christi",
    "sg:classifiers":[
        {
            "category":"Autos & Motor Vehicles",
            "subcategory":"Automobile Sales",
            "type":"Retail Goods"
        }
    ],
    "sg:phone":"+1 361 387 2900",
    "sg:postcode":"78415",
    "sg:province":"TX",
    "sg:tags":[
        "car",
        "dealer"
    ],
    "wof:name":"Horizon Motors",
    "wof:placetype":"venue"
},
  "geometry": {"coordinates":[-97.41691400000001,27.7301],"type":"Point"}
}