{
  "type": "Feature",
  "properties": {
    "iso:country":"US",
    "sg:address":"2634 Parana Dr",
    "sg:city":"Houston",
    "sg:classifiers":[
        {
            "category":"Banks & Credit Unions",
            "subcategory":"Investment Brokerage",
            "type":"Services"
        }
    ],
    "sg:phone":"+1 713 461 4403",
    "sg:postcode":"77080",
    "sg:province":"TX",
    "sg:tags":[
        "security"
    ],
    "wof:name":"Davis Land & Minerals Inc",
    "wof:placetype":"venue"
},
  "geometry": {"coordinates":[-95.53505800000001,29.819662],"type":"Point"}
}