{
  "type": "Feature",
  "properties": {
    "iso:country":"US",
    "sg:address":"9342 Simmons Rd",
    "sg:city":"Austin",
    "sg:classifiers":[
        {
            "category":"Personal",
            "type":"Services"
        }
    ],
    "sg:phone":"+1 512 345 6707",
    "sg:postcode":"78759",
    "sg:province":"TX",
    "sg:tags":[
        "consultant",
        "wedding"
    ],
    "wof:name":"Gloria Galan Bridal Consulting",
    "wof:placetype":"venue"
},
  "geometry": {"coordinates":[-97.766097,30.396867],"type":"Point"}
}