{
  "type": "Feature",
  "properties": {
    "iso:country":"US",
    "sg:address":"7505 Lockheed Dr",
    "sg:city":"El Paso",
    "sg:classifiers":[
        {
            "category":"Insurance",
            "subcategory":"Insurance Agent",
            "type":"Services"
        }
    ],
    "sg:phone":"+1 915 778 2424",
    "sg:postcode":"79925",
    "sg:province":"TX",
    "wof:name":"Presi Ortega & Assoc Insurance",
    "wof:placetype":"venue"
},
  "geometry": {"coordinates":[-106.38957499999999,31.790849],"type":"Point"}
}