{
  "type": "Feature",
  "properties": {
    "iso:country":"US",
    "sg:address":"807 Rock St",
    "sg:city":"Georgetown",
    "sg:classifiers":[
        {
            "category":"Professional",
            "subcategory":"Management & Consulting",
            "type":"Services"
        }
    ],
    "sg:phone":"+1 512 930 5558",
    "sg:postcode":"78626",
    "sg:province":"TX",
    "wof:name":"Intra-Focus Inc",
    "wof:placetype":"venue"
},
  "geometry": {"coordinates":[-97.678955,30.636506],"type":"Point"}
}