{
  "type": "Feature",
  "properties": {
    "iso:country":"US",
    "sg:address":"10110 San Pedro Ave",
    "sg:city":"San Antonio",
    "sg:classifiers":[
        {
            "category":"Autos & Motor Vehicles",
            "subcategory":"Fuel & Gas Station",
            "type":"Retail Goods"
        }
    ],
    "sg:phone":"+1 210 530 0947",
    "sg:postcode":"78216",
    "sg:province":"TX",
    "sg:tags":[
        "oil"
    ],
    "wof:name":"Exxon Tiger Mart",
    "wof:placetype":"venue"
},
  "geometry": {"coordinates":[-98.49573599999999,29.533146],"type":"Point"}
}