{
  "type": "Feature",
  "properties": {
    "iso:country":"US",
    "sg:address":"406 Furr Dr",
    "sg:city":"San Antonio",
    "sg:classifiers":[
        {
            "category":"Travel",
            "subcategory":"Travel Agent",
            "type":"Entertainment"
        }
    ],
    "sg:phone":"+1 210 479 2424",
    "sg:postcode":"78201",
    "sg:province":"TX",
    "sg:tags":[
        "agency"
    ],
    "wof:name":"Prompt Travel Leaders",
    "wof:placetype":"venue"
},
  "geometry": {"coordinates":[-98.534646,29.464413],"type":"Point"}
}