{
  "type": "Feature",
  "properties": {
    "iso:country":"US",
    "sg:address":"11914 Churchill Ct",
    "sg:city":"Houston",
    "sg:classifiers":[
        {
            "category":"Banks & Credit Unions",
            "subcategory":"Investment Brokerage",
            "type":"Services"
        }
    ],
    "sg:phone":"+1 713 822 3080",
    "sg:postcode":"77024",
    "sg:province":"TX",
    "sg:tags":[
        "firm"
    ],
    "wof:name":"Irish Investment Inc",
    "wof:placetype":"venue"
},
  "geometry": {"coordinates":[-95.535358,29.767142],"type":"Point"}
}