{
  "type": "Feature",
  "properties": {
    "iso:country":"US",
    "sg:address":"4109 Celtic Dr",
    "sg:city":"Arlington",
    "sg:classifiers":[
        {
            "category":"Building & Trades",
            "subcategory":"Landscaping Services",
            "type":"Services"
        }
    ],
    "sg:phone":"+1 817 860 8819",
    "sg:postcode":"76017",
    "sg:province":"TX",
    "sg:tags":[
        "lawn",
        "maintenance",
        "grounds"
    ],
    "wof:name":"Timber-Lawn Tree Svc",
    "wof:placetype":"venue"
},
  "geometry": {"coordinates":[-97.171961,32.66534],"type":"Point"}
}