{
  "type": "Feature",
  "properties": {
    "iso:country":"US",
    "sg:address":"5845 E 14th St",
    "sg:city":"Brownsville",
    "sg:classifiers":[
        {
            "category":"Wholesale",
            "subcategory":"Auto Parts",
            "type":"Manufacturing & Wholesale Goods"
        }
    ],
    "sg:phone":"+1 956 832 0010",
    "sg:postcode":"78521",
    "sg:province":"TX",
    "sg:tags":[
        "paint",
        "coating",
        "powder"
    ],
    "wof:name":"Bright Finishing S De Rl De Cv",
    "wof:placetype":"venue"
},
  "geometry": {"coordinates":[-97.447062,25.932112],"type":"Point"}
}