{
  "type": "Feature",
  "properties": {
    "iso:country":"US",
    "sg:address":"734 Glamis Ave",
    "sg:city":"San Antonio",
    "sg:classifiers":[
        {
            "category":"Social Services",
            "type":"Services"
        }
    ],
    "sg:phone":"+1 210 924 2277",
    "sg:postcode":"78223",
    "sg:province":"TX",
    "sg:tags":[
        "youth",
        "organization",
        "center"
    ],
    "wof:name":"YMCA Of San Antonio",
    "wof:placetype":"venue"
},
  "geometry": {"coordinates":[-98.441408,29.379459],"type":"Point"}
}