{
  "type": "Feature",
  "properties": {
    "iso:country":"US",
    "sg:address":"2527 Royal Ln",
    "sg:city":"Dallas",
    "sg:classifiers":[
        {
            "category":"Shopping",
            "subcategory":"Clothing, Apparel, & Fashions",
            "type":"Retail Goods"
        }
    ],
    "sg:phone":"+1 972 243 0709",
    "sg:postcode":"75229",
    "sg:province":"TX",
    "sg:tags":[
        "lingerie"
    ],
    "wof:name":"Sleeping Beauty",
    "wof:placetype":"venue"
},
  "geometry": {"coordinates":[-96.89479799999999,32.896198],"type":"Point"}
}