{
  "type": "Feature",
  "properties": {
    "iso:country":"US",
    "sg:address":"2821 Carlisle Street",
    "sg:city":"Dallas",
    "sg:classifiers":[
        {
            "category":"Real Estate",
            "subcategory":"Real Estate Operator",
            "type":"Services"
        }
    ],
    "sg:phone":"+1 214 855 5287",
    "sg:postcode":"75204",
    "sg:province":"TX",
    "sg:tags":[
        "apartment"
    ],
    "sg:website":"www.gables.com",
    "wof:name":"Gables Katy Trail",
    "wof:placetype":"venue"
},
  "geometry": {"coordinates":[-96.804092,32.801805],"type":"Point"}
}