{
  "type": "Feature",
  "properties": {
    "iso:country":"US",
    "sg:address":"5335 Port Entry",
    "sg:city":"San Antonio",
    "sg:classifiers":[
        {
            "category":"Professional",
            "type":"Services"
        }
    ],
    "sg:phone":"+1 210 648 7300",
    "sg:postcode":"78222",
    "sg:province":"TX",
    "sg:tags":[
        "establishment"
    ],
    "wof:name":"Port San Antonio",
    "wof:placetype":"venue"
},
  "geometry": {"coordinates":[-98.389771,29.381579],"type":"Point"}
}