{
  "type": "Feature",
  "properties": {
    "iso:country":"US",
    "sg:address":"7941 King Arthur Rd",
    "sg:city":"Frisco",
    "sg:classifiers":[
        {
            "category":"Manufacturing",
            "subcategory":"Food",
            "type":"Manufacturing & Wholesale Goods"
        }
    ],
    "sg:phone":"+1 972 335 0884",
    "sg:postcode":"75035",
    "sg:province":"TX",
    "sg:tags":[
        "mfg"
    ],
    "wof:name":"Texas Candy Kitchen",
    "wof:placetype":"venue"
},
  "geometry": {"coordinates":[-96.795537,33.144766],"type":"Point"}
}