{
  "type": "Feature",
  "properties": {
    "iso:country":"US",
    "sg:address":"1308 N John Redditt Dr",
    "sg:city":"Lufkin",
    "sg:classifiers":[
        {
            "category":"Wholesale",
            "subcategory":"Machinery & Supplies",
            "type":"Manufacturing & Wholesale Goods"
        }
    ],
    "sg:phone":"+1 936 632 8900",
    "sg:postcode":"75904",
    "sg:province":"TX",
    "sg:tags":[
        "machine",
        "tool"
    ],
    "wof:name":"Ters-Tex Inc",
    "wof:placetype":"venue"
},
  "geometry": {"coordinates":[-94.763796,31.345226],"type":"Point"}
}