{
  "type": "Feature",
  "properties": {
    "iso:country":"US",
    "sg:address":"5850 Highland Hills Dr",
    "sg:city":"Dallas",
    "sg:classifiers":[
        {
            "category":"Building & Trades",
            "subcategory":"Landscaping Services",
            "type":"Services"
        }
    ],
    "sg:phone":"+1 214 375 5546",
    "sg:postcode":"75241",
    "sg:province":"TX",
    "wof:name":"Heavenly Lawns",
    "wof:placetype":"venue"
},
  "geometry": {"coordinates":[-96.765202,32.67564],"type":"Point"}
}