{
  "type": "Feature",
  "properties": {
    "iso:country":"US",
    "sg:address":"3510 US Hwy 83S Bus",
    "sg:city":"Harlingen",
    "sg:classifiers":[
        {
            "category":"Personal",
            "subcategory":"Beauty Salon",
            "type":"Services"
        }
    ],
    "sg:phone":"+1 956 428 6101",
    "sg:postcode":"78552",
    "sg:province":"TX",
    "wof:name":"Alpha & Omega Beauty Salon",
    "wof:placetype":"venue"
},
  "geometry": {"coordinates":[-97.735609,26.184728],"type":"Point"}
}