{
  "type": "Feature",
  "properties": {
    "iso:country":"US",
    "sg:address":"1101 4th St",
    "sg:city":"Graham",
    "sg:classifiers":[
        {
            "category":"Food & Beverages",
            "subcategory":"Groceries & Convenience Stores",
            "type":"Retail Goods"
        }
    ],
    "sg:phone":"+1 940 549 2061",
    "sg:postcode":"76450",
    "sg:province":"TX",
    "wof:name":"Qwik Pantry #359",
    "wof:placetype":"venue"
},
  "geometry": {"coordinates":[-98.579291,33.106955],"type":"Point"}
}