{
  "type": "Feature",
  "properties": {
    "iso:country":"US",
    "sg:address":"6326 Elmgrove Rd",
    "sg:city":"Spring",
    "sg:classifiers":[
        {
            "category":"Professional",
            "subcategory":"Business Services",
            "type":"Services"
        }
    ],
    "sg:phone":"+1 281 655 1363",
    "sg:postcode":"77389",
    "sg:province":"TX",
    "sg:tags":[
        "provide",
        "interior",
        "design",
        "accessory"
    ],
    "wof:name":"Barnett Services & Design",
    "wof:placetype":"venue"
},
  "geometry": {"coordinates":[-95.517337,30.105652],"type":"Point"}
}