{
  "type": "Feature",
  "properties": {
    "iso:country":"US",
    "sg:address":"8388 W Sam Houston Pkwy S Ste 186",
    "sg:city":"Houston",
    "sg:classifiers":[
        {
            "category":"Shopping",
            "subcategory":"Pharmacy",
            "type":"Retail Goods"
        }
    ],
    "sg:phone":"+1 281 564 5400",
    "sg:postcode":"77072",
    "sg:province":"TX",
    "sg:tags":[
        "drugstore"
    ],
    "wof:name":"Saigon Houston Pharmacy",
    "wof:placetype":"venue"
},
  "geometry": {"coordinates":[-95.558425,29.6867],"type":"Point"}
}