{
  "type": "Feature",
  "properties": {
    "iso:country":"US",
    "sg:address":"3014 W 26th Ave",
    "sg:city":"Amarillo",
    "sg:classifiers":[
        {
            "category":"Real Estate",
            "subcategory":"Real Estate Agent",
            "type":"Services"
        }
    ],
    "sg:phone":"+1 806 353 5200",
    "sg:postcode":"79109",
    "sg:province":"TX",
    "sg:website":"www.clinelandco.com",
    "wof:name":"R C Cline Land Co",
    "wof:placetype":"venue"
},
  "geometry": {"coordinates":[-101.873265,35.185837],"type":"Point"}
}