{
  "type": "Feature",
  "properties": {
    "iso:country":"US",
    "sg:address":"4642 N Loop 289",
    "sg:city":"Lubbock",
    "sg:classifiers":[
        {
            "category":"Health Services",
            "subcategory":"Health Practitioner",
            "type":"Services"
        }
    ],
    "sg:phone":"+1 806 793 7363",
    "sg:postcode":"79416",
    "sg:province":"TX",
    "sg:tags":[
        "psychologist"
    ],
    "wof:name":"Lambert Matthew E PHD",
    "wof:placetype":"venue"
},
  "geometry": {"coordinates":[-101.908947,33.605951],"type":"Point"}
}