{
  "type": "Feature",
  "properties": {
    "iso:country":"US",
    "sg:address":"612 W Commerce St",
    "sg:city":"San Antonio",
    "sg:classifiers":[
        {
            "category":"Home & Garden",
            "subcategory":"Home Furnishings",
            "type":"Retail Goods"
        }
    ],
    "sg:phone":"+1 210 224 4144",
    "sg:postcode":"78207",
    "sg:province":"TX",
    "sg:tags":[
        "pottery"
    ],
    "wof:name":"Fresh Concepts",
    "wof:placetype":"venue"
},
  "geometry": {"coordinates":[-98.500871,29.425674],"type":"Point"}
}