{
  "type": "Feature",
  "properties": {
    "iso:country":"US",
    "sg:address":"3500 I- 30",
    "sg:city":"Mesquite",
    "sg:classifiers":[
        {
            "category":"Health Services",
            "subcategory":"Doctor",
            "type":"Services"
        }
    ],
    "sg:phone":"+1 972 682 1307",
    "sg:postcode":"75150",
    "sg:province":"TX",
    "sg:tags":[
        "physician",
        "medical",
        "surgeon"
    ],
    "sg:website":"www.mitchellorthopedic.com",
    "wof:name":"Charles D Mitchell MD PA",
    "wof:placetype":"venue"
},
  "geometry": {"coordinates":[-96.6546,32.809788],"type":"Point"}
}