{
  "type": "Feature",
  "properties": {
    "iso:country":"US",
    "sg:address":"1000 Oak St",
    "sg:city":"Colmesneil",
    "sg:classifiers":[
        {
            "category":"Shopping",
            "subcategory":"Used Merchandise",
            "type":"Retail Goods"
        }
    ],
    "sg:phone":"+1 409 837 4451",
    "sg:postcode":"75938",
    "sg:province":"TX",
    "wof:name":"Lester Graham Sales",
    "wof:placetype":"venue"
},
  "geometry": {"coordinates":[-94.426354,30.911899],"type":"Point"}
}