{
  "type": "Feature",
  "properties": {
    "iso:country":"US",
    "sg:address":"1100 Silver Hill Dr",
    "sg:city":"Austin",
    "sg:classifiers":[
        {
            "category":"Wholesale",
            "subcategory":"Farm Supplies",
            "type":"Manufacturing & Wholesale Goods"
        }
    ],
    "sg:phone":"+1 512 327 2409",
    "sg:postcode":"78746",
    "sg:province":"TX",
    "sg:tags":[
        "livestock"
    ],
    "wof:name":"Dime Box Cattle Co",
    "wof:placetype":"venue"
},
  "geometry": {"coordinates":[-97.809174,30.275962],"type":"Point"}
}