{
  "type": "Feature",
  "properties": {
    "iso:country":"US",
    "sg:address":"7786 Blankenship Dr",
    "sg:city":"Houston",
    "sg:classifiers":[
        {
            "category":"Shopping",
            "type":"Retail Goods"
        }
    ],
    "sg:phone":"+1 713 862 8621",
    "sg:postcode":"77055",
    "sg:province":"TX",
    "sg:tags":[
        "merchandise"
    ],
    "wof:name":"Certified Network Engineering",
    "wof:placetype":"venue"
},
  "geometry": {"coordinates":[-95.486138,29.818374],"type":"Point"}
}