{
  "type": "Feature",
  "properties": {
    "iso:country":"US",
    "sg:address":"6324 N Navarro St",
    "sg:city":"Victoria",
    "sg:classifiers":[
        {
            "category":"Real Estate",
            "subcategory":"Real Estate Agent",
            "type":"Services"
        }
    ],
    "sg:phone":"+1 361 574 8877",
    "sg:postcode":"77904",
    "sg:province":"TX",
    "sg:tags":[
        "inspection"
    ],
    "wof:name":"AAA Inspection Svc",
    "wof:placetype":"venue"
},
  "geometry": {"coordinates":[-96.99703100000001,28.853438],"type":"Point"}
}