{
  "type": "Feature",
  "properties": {
    "iso:country":"US",
    "sg:address":"10110 Coralstone Rd",
    "sg:city":"Houston",
    "sg:classifiers":[
        {
            "category":"Social Services",
            "subcategory":"Job Training",
            "type":"Services"
        }
    ],
    "sg:phone":"+1 281 445 8992",
    "sg:postcode":"77086",
    "sg:province":"TX",
    "sg:tags":[
        "employment"
    ],
    "wof:name":"Gerald Allen Whitlow 2nd",
    "wof:placetype":"venue"
},
  "geometry": {"coordinates":[-95.486717,29.923553],"type":"Point"}
}