{
  "type": "Feature",
  "properties": {
    "iso:country":"US",
    "sg:address":"2120 N Prairie Creek Rd",
    "sg:city":"Dallas",
    "sg:classifiers":[
        {
            "category":"Education",
            "subcategory":"School",
            "type":"Public Place"
        }
    ],
    "sg:phone":"+1 469 593 6300",
    "sg:postcode":"75227",
    "sg:province":"TX",
    "sg:tags":[
        "high",
        "middle",
        "elementary"
    ],
    "sg:website":"www.risd.org",
    "wof:name":"Schools",
    "wof:placetype":"venue"
},
  "geometry": {"coordinates":[-96.66522500000001,32.749576],"type":"Point"}
}