{
  "type": "Feature",
  "properties": {
    "iso:country":"US",
    "sg:address":"301 W 47th St",
    "sg:city":"San Angelo",
    "sg:classifiers":[
        {
            "category":"Building & Trades",
            "subcategory":"Landscaping Services",
            "type":"Services"
        }
    ],
    "sg:phone":"+1 325 655 5250",
    "sg:postcode":"76903",
    "sg:province":"TX",
    "wof:name":"Four Seasons",
    "wof:placetype":"venue"
},
  "geometry": {"coordinates":[-100.464787,31.507929],"type":"Point"}
}