{
  "type": "Feature",
  "properties": {
    "iso:country":"US",
    "sg:address":"1207 Parkhaven Ln",
    "sg:city":"Houston",
    "sg:classifiers":[
        {
            "category":"Personal",
            "type":"Services"
        }
    ],
    "sg:phone":"+1 281 597 9711",
    "sg:postcode":"77077",
    "sg:province":"TX",
    "wof:name":"Peace of Mind Massage",
    "wof:placetype":"venue"
},
  "geometry": {"coordinates":[-95.633377,29.764798],"type":"Point"}
}