{
  "type": "Feature",
  "properties": {
    "iso:country":"US",
    "sg:address":"307 S L B J Dr",
    "sg:city":"San Marcos",
    "sg:classifiers":[
        {
            "category":"Shopping",
            "subcategory":"Florist",
            "type":"Retail Goods"
        },
        {
            "category":"Shopping",
            "subcategory":"Gifts & Souvenirs",
            "type":"Retail Goods"
        }
    ],
    "sg:phone":"+1 512 392 2961",
    "sg:postcode":"78666",
    "sg:province":"TX",
    "wof:name":"Flowers & Gifts",
    "wof:placetype":"venue"
},
  "geometry": {"coordinates":[-97.939385,29.879019],"type":"Point"}
}