{
  "type": "Feature",
  "properties": {
    "iso:country":"US",
    "sg:address":"7212 Latham Dr",
    "sg:city":"Richland Hills",
    "sg:classifiers":[
        {
            "category":"Utilities",
            "subcategory":"Telephone",
            "type":"Services"
        }
    ],
    "sg:phone":"+1 817 589 2424",
    "sg:postcode":"76118",
    "sg:province":"TX",
    "sg:tags":[
        "company"
    ],
    "wof:name":"SBC",
    "wof:placetype":"venue"
},
  "geometry": {"coordinates":[-97.222452,32.806917],"type":"Point"}
}