{
  "type": "Feature",
  "properties": {
    "iso:country":"US",
    "sg:address":"1402 S Dwight Ave",
    "sg:city":"Monahans",
    "sg:classifiers":[
        {
            "category":"Wholesale",
            "subcategory":"Metals & Minerals",
            "type":"Manufacturing & Wholesale Goods"
        }
    ],
    "sg:phone":"+1 432 943 6797",
    "sg:postcode":"79756",
    "sg:province":"TX",
    "sg:tags":[
        "pipe"
    ],
    "wof:name":"Crozier Pipe Co",
    "wof:placetype":"venue"
},
  "geometry": {"coordinates":[-102.88399,31.583079],"type":"Point"}
}