{
  "type": "Feature",
  "properties": {
    "iso:country":"US",
    "sg:address":"5232 S Hulen St",
    "sg:city":"Fort Worth",
    "sg:classifiers":[
        {
            "category":"Home & Garden",
            "subcategory":"Furniture",
            "type":"Retail Goods"
        }
    ],
    "sg:phone":"+1 817 292 6999",
    "sg:postcode":"76132",
    "sg:province":"TX",
    "wof:name":"Texas Patio",
    "wof:placetype":"venue"
},
  "geometry": {"coordinates":[-97.39968500000001,32.673468],"type":"Point"}
}