{
  "type": "Feature",
  "properties": {
    "iso:country":"US",
    "sg:address":"675 Bering Dr Ste 350",
    "sg:city":"Houston",
    "sg:classifiers":[
        {
            "category":"Professional",
            "subcategory":"Lawyer & Legal Services",
            "type":"Services"
        }
    ],
    "sg:phone":"+1 713 973 1497",
    "sg:postcode":"77057",
    "sg:province":"TX",
    "wof:name":"Kormeier Victor A Jr Atty",
    "wof:placetype":"venue"
},
  "geometry": {"coordinates":[-95.478836,29.761429],"type":"Point"}
}