{
  "type": "Feature",
  "properties": {
    "iso:country":"US",
    "sg:address":"3225 Creighton Ln",
    "sg:city":"Bedford",
    "sg:classifiers":[
        {
            "category":"Professional",
            "subcategory":"Business Services",
            "type":"Services"
        }
    ],
    "sg:phone":"+1 817 540 2894",
    "sg:postcode":"76021",
    "sg:province":"TX",
    "wof:name":"Gerald Atkinson",
    "wof:placetype":"venue"
},
  "geometry": {"coordinates":[-97.145943,32.859586],"type":"Point"}
}