{
  "type": "Feature",
  "properties": {
    "iso:country":"US",
    "sg:address":"9618 Val Verde St",
    "sg:city":"Houston",
    "sg:classifiers":[
        {
            "category":"Retail",
            "subcategory":"Repair Shop",
            "type":"Services"
        }
    ],
    "sg:phone":"+1 713 935 2871",
    "sg:postcode":"77063",
    "sg:province":"TX",
    "sg:tags":[
        "refrigeration"
    ],
    "wof:name":"Houston Power Savers",
    "wof:placetype":"venue"
},
  "geometry": {"coordinates":[-95.53857499999999,29.735634],"type":"Point"}
}