{
  "type": "Feature",
  "properties": {
    "iso:country":"US",
    "sg:address":"6322 Aberdeen Ave",
    "sg:city":"Dallas",
    "sg:classifiers":[
        {
            "category":"Professional",
            "subcategory":"Accounting & Tax Preparation",
            "type":"Services"
        }
    ],
    "sg:phone":"+1 214 739 9000",
    "sg:postcode":"75230",
    "sg:province":"TX",
    "wof:name":"Karen S Malone P C",
    "wof:placetype":"venue"
},
  "geometry": {"coordinates":[-96.79821200000001,32.88219],"type":"Point"}
}