{
  "type": "Feature",
  "properties": {
    "iso:country":"US",
    "sg:address":"124 Elm St",
    "sg:city":"Cibolo",
    "sg:classifiers":[
        {
            "category":"Autos & Motor Vehicles",
            "subcategory":"Automobile Sales",
            "type":"Retail Goods"
        }
    ],
    "sg:phone":"+1 210 658 3118",
    "sg:postcode":"78108",
    "sg:province":"TX",
    "sg:tags":[
        "dealers-used",
        "car",
        "used",
        "cars-wholesale"
    ],
    "sg:website":"http://www.uhaul.com/Locations/Rentals-near-Cibolo-TX-78108/040120",
    "wof:name":"U-Haul Neighborhood Dealer - Discount Autos Inc",
    "wof:placetype":"venue"
},
  "geometry": {"coordinates":[-98.23375299999999,29.560693],"type":"Point"}
}