{
  "type": "Feature",
  "properties": {
    "iso:country":"US",
    "sg:address":"500 Brooks Ct",
    "sg:city":"Southlake",
    "sg:classifiers":[
        {
            "category":"Personal",
            "type":"Services"
        }
    ],
    "sg:phone":"+1 817 430 0506",
    "sg:postcode":"76092",
    "sg:province":"TX",
    "sg:tags":[
        "counseling"
    ],
    "wof:name":"Welwood Counseling",
    "wof:placetype":"venue"
},
  "geometry": {"coordinates":[-97.144818,32.997679],"type":"Point"}
}