{
  "type": "Feature",
  "properties": {
    "iso:country":"US",
    "sg:address":"1807 N Winnetka Ave",
    "sg:city":"Dallas",
    "sg:classifiers":[
        {
            "category":"Building & Trades",
            "subcategory":"Construction",
            "type":"Services"
        }
    ],
    "sg:phone":"+1 214 752 4491",
    "sg:postcode":"75208",
    "sg:province":"TX",
    "sg:tags":[
        "carpenter"
    ],
    "wof:name":"Andres Arias Oscardgo Carpentry",
    "wof:placetype":"venue"
},
  "geometry": {"coordinates":[-96.840142,32.76846],"type":"Point"}
}