{
  "type": "Feature",
  "properties": {
    "iso:country":"US",
    "sg:address":"3219 Pasadena Blvd",
    "sg:city":"Pasadena",
    "sg:classifiers":[
        {
            "category":"Organizations",
            "subcategory":"Non-profit Organization",
            "type":"Services"
        }
    ],
    "sg:phone":"+1 713 473 6228",
    "sg:postcode":"77503",
    "sg:province":"TX",
    "wof:name":"Heat Frost Insulators & Asbsts",
    "wof:placetype":"venue"
},
  "geometry": {"coordinates":[-95.16641799999999,29.681495],"type":"Point"}
}