{
  "type": "Feature",
  "properties": {
    "iso:country":"US",
    "sg:address":"300 S Teel Dr",
    "sg:city":"Devine",
    "sg:classifiers":[
        {
            "category":"Restaurant",
            "type":"Food & Drink"
        }
    ],
    "sg:phone":"+1 830 663 2570",
    "sg:postcode":"78016",
    "sg:province":"TX",
    "sg:tags":[
        "mexican"
    ],
    "wof:name":"Los Arcos Restaurant",
    "wof:placetype":"venue"
},
  "geometry": {"coordinates":[-98.90432699999999,29.142229],"type":"Point"}
}