{
  "type": "Feature",
  "properties": {
    "iso:country":"US",
    "sg:address":"1420 Cedar Crest Dr",
    "sg:city":"Abilene",
    "sg:classifiers":[
        {
            "category":"Professional",
            "subcategory":"Computer Services",
            "type":"Services"
        }
    ],
    "sg:phone":"+1 325 674 6122",
    "sg:postcode":"79699",
    "sg:province":"TX",
    "sg:tags":[
        "home",
        "consulting",
        "page",
        "dev",
        "internet"
    ],
    "wof:name":"Foreman Web Designers",
    "wof:placetype":"venue"
},
  "geometry": {"coordinates":[-99.716588,32.465331],"type":"Point"}
}