{
  "type": "Feature",
  "properties": {
    "iso:country":"US",
    "sg:address":"3023 S Lancaster Rd",
    "sg:city":"Dallas",
    "sg:classifiers":[
        {
            "category":"Insurance",
            "subcategory":"Insurance Agent",
            "type":"Services"
        }
    ],
    "sg:phone":"+1 214 375 8887",
    "sg:postcode":"75216",
    "sg:province":"TX",
    "wof:name":"Lonestar Auto Insurance",
    "wof:placetype":"venue"
},
  "geometry": {"coordinates":[-96.803226,32.70998],"type":"Point"}
}