{
  "type": "Feature",
  "properties": {
    "iso:country":"US",
    "sg:address":"1006 Wayland Dr",
    "sg:city":"Arlington",
    "sg:classifiers":[
        {
            "category":"Professional",
            "subcategory":"Computer Services",
            "type":"Services"
        }
    ],
    "sg:phone":"+1 817 461 0465",
    "sg:postcode":"76012",
    "sg:province":"TX",
    "sg:tags":[
        "datum"
    ],
    "wof:name":"Cynthia A Turney",
    "wof:placetype":"venue"
},
  "geometry": {"coordinates":[-97.12285,32.76589],"type":"Point"}
}