{
  "type": "Feature",
  "properties": {
    "iso:country":"US",
    "sg:address":"2120 E Rancier Ave",
    "sg:city":"Killeen",
    "sg:classifiers":[
        {
            "category":"Autos & Motor Vehicles",
            "subcategory":"Automobile Sales",
            "type":"Retail Goods"
        }
    ],
    "sg:phone":"+1 254 519 7810",
    "sg:postcode":"76541",
    "sg:province":"TX",
    "sg:tags":[
        "car",
        "used"
    ],
    "sg:website":"http://www.killeenautosalesonline.com",
    "wof:name":"Killeen Auto Sales",
    "wof:placetype":"venue"
},
  "geometry": {"coordinates":[-97.71014,31.121369],"type":"Point"}
}