{
  "type": "Feature",
  "properties": {
    "iso:country":"US",
    "sg:address":"5100 State Loop 340",
    "sg:city":"Robinson",
    "sg:classifiers":[
        {
            "category":"Manufacturing",
            "subcategory":"Paper Products",
            "type":"Manufacturing & Wholesale Goods"
        },
        {
            "category":"Manufacturing",
            "subcategory":"Printing",
            "type":"Manufacturing & Wholesale Goods"
        }
    ],
    "sg:phone":"+1 254 848 5203",
    "sg:postcode":"76706",
    "sg:province":"TX",
    "sg:tags":[
        "pressure",
        "commercial",
        "mfg",
        "lithographic",
        "label",
        "sensitive"
    ],
    "wof:name":"Two-Twelve Label Co Inc",
    "wof:placetype":"venue"
},
  "geometry": {"coordinates":[-97.137677,31.49269],"type":"Point"}
}