{
  "type": "Feature",
  "properties": {
    "iso:country":"US",
    "sg:address":"908 W Duval St",
    "sg:city":"Troup",
    "sg:classifiers":[
        {
            "category":"Health Services",
            "subcategory":"Doctor",
            "type":"Services"
        }
    ],
    "sg:phone":"+1 903 842 3130",
    "sg:postcode":"75789",
    "sg:province":"TX",
    "sg:tags":[
        "dentist"
    ],
    "wof:name":"Troup Dental Clinic",
    "wof:placetype":"venue"
},
  "geometry": {"coordinates":[-95.129227,32.144491],"type":"Point"}
}