{
  "type": "Feature",
  "properties": {
    "iso:country":"US",
    "sg:address":"5407 Gulf Fwy",
    "sg:city":"La Marque",
    "sg:classifiers":[
        {
            "category":"Government",
            "subcategory":"Office",
            "type":"Public Place"
        }
    ],
    "sg:phone":"+1 409 978 2500",
    "sg:postcode":"77568",
    "sg:province":"TX",
    "sg:tags":[
        "state",
        "program"
    ],
    "wof:name":"Transportation Dept",
    "wof:placetype":"venue"
},
  "geometry": {"coordinates":[-95.023481,29.392387],"type":"Point"}
}