{
  "type": "Feature",
  "properties": {
    "iso:country":"US",
    "sg:address":"7745 Smith Dr",
    "sg:city":"Mansfield",
    "sg:classifiers":[
        {
            "category":"Building & Trades",
            "subcategory":"Construction",
            "type":"Services"
        }
    ],
    "sg:phone":"+1 817 477 3070",
    "sg:postcode":"76063",
    "sg:province":"TX",
    "sg:tags":[
        "contractor"
    ],
    "wof:name":"ACS Metro Builders Inc",
    "wof:placetype":"venue"
},
  "geometry": {"coordinates":[-97.196354,32.561845],"type":"Point"}
}