{
  "type": "Feature",
  "properties": {
    "iso:country":"US",
    "sg:address":"105 Kathryn Dr",
    "sg:city":"Lewisville",
    "sg:classifiers":[
        {
            "category":"Shopping",
            "subcategory":"Hobbies, Toys, & Games",
            "type":"Retail Goods"
        }
    ],
    "sg:phone":"+1 972 221 3046",
    "sg:postcode":"75067",
    "sg:province":"TX",
    "wof:name":"Parker Ann Nelson Lmft",
    "wof:placetype":"venue"
},
  "geometry": {"coordinates":[-97.032095,33.042056],"type":"Point"}
}