{
  "type": "Feature",
  "properties": {
    "iso:country":"US",
    "sg:address":"8730 Mount Houston Rd",
    "sg:city":"Houston",
    "sg:classifiers":[
        {
            "category":"Manufacturing",
            "subcategory":"Lumber",
            "type":"Manufacturing & Wholesale Goods"
        },
        {
            "category":"Building & Trades",
            "subcategory":"Landscaping Services",
            "type":"Services"
        }
    ],
    "sg:phone":"+1 281 459 3800",
    "sg:postcode":"77050",
    "sg:province":"TX",
    "sg:tags":[
        "forester"
    ],
    "wof:name":"Lake Forest Garden",
    "wof:placetype":"venue"
},
  "geometry": {"coordinates":[-95.260237,29.891673],"type":"Point"}
}