{
  "type": "Feature",
  "properties": {
    "iso:country":"US",
    "sg:address":"6651 S Will Rogers Blvd",
    "sg:city":"Fort Worth",
    "sg:classifiers":[
        {
            "category":"Manufacturing",
            "subcategory":"Metals",
            "type":"Manufacturing & Wholesale Goods"
        }
    ],
    "sg:phone":"+1 817 551 5511",
    "sg:postcode":"76140",
    "sg:province":"TX",
    "sg:tags":[
        "stamping",
        "sheet",
        "mfg",
        "meta",
        "stampings",
        "metalwork",
        "structural"
    ],
    "wof:name":"Essner Manufacturing Inc",
    "wof:placetype":"venue"
},
  "geometry": {"coordinates":[-97.313085,32.648612],"type":"Point"}
}