{
  "type": "Feature",
  "properties": {
    "iso:country":"US",
    "sg:address":"7054 S Central Expy",
    "sg:city":"Dallas",
    "sg:classifiers":[
        {
            "category":"Personal",
            "type":"Services"
        }
    ],
    "sg:phone":"+1 214 375 7928",
    "sg:postcode":"75216",
    "sg:province":"TX",
    "sg:tags":[
        "towing"
    ],
    "sg:website":"www.unitedtowsllc.com",
    "wof:name":"United Tows Llc",
    "wof:placetype":"venue"
},
  "geometry": {"coordinates":[-96.758301,32.723099],"type":"Point"}
}