{
  "type": "Feature",
  "properties": {
    "iso:country":"US",
    "sg:address":"5365 Spring Valley Rd",
    "sg:city":"Dallas",
    "sg:classifiers":[
        {
            "category":"Restaurant",
            "type":"Food & Drink"
        }
    ],
    "sg:phone":"+1 972 386 6640",
    "sg:postcode":"75254",
    "sg:province":"TX",
    "sg:tags":[
        "bakery",
        "eating"
    ],
    "wof:name":"Aeish Restaurant and Pastry",
    "wof:placetype":"venue"
},
  "geometry": {"coordinates":[-96.815697,32.939602],"type":"Point"}
}