{
  "type": "Feature",
  "properties": {
    "iso:country":"US",
    "sg:address":"12820 Roy Harris Loop",
    "sg:city":"Conroe",
    "sg:classifiers":[
        {
            "category":"Local Transit",
            "type":"Transportation"
        }
    ],
    "sg:phone":"+1 936 441 3933",
    "sg:postcode":"77306",
    "sg:province":"TX",
    "sg:tags":[
        "passenger"
    ],
    "wof:name":"Mountgomery Cnty Limouse Srvc",
    "wof:placetype":"venue"
},
  "geometry": {"coordinates":[-95.381579,30.301484],"type":"Point"}
}