{
  "type": "Feature",
  "properties": {
    "iso:country":"US",
    "sg:address":"903 Zacatecas Ct",
    "sg:city":"El Paso",
    "sg:classifiers":[
        {
            "category":"Organizations",
            "subcategory":"Religious Organization",
            "type":"Services"
        }
    ],
    "sg:phone":"+1 915 859 3839",
    "sg:postcode":"79907",
    "sg:province":"TX",
    "sg:tags":[
        "church"
    ],
    "wof:name":"Nueva Esperanza Iglesia Bautis",
    "wof:placetype":"venue"
},
  "geometry": {"coordinates":[-106.30670000000001,31.703527],"type":"Point"}
}