{
  "type": "Feature",
  "properties": {
    "iso:country":"US",
    "sg:address":"4810 Calhoun Rd Suite 105",
    "sg:city":"Houston",
    "sg:classifiers":[
        {
            "category":"Deli",
            "type":"Food & Drink"
        }
    ],
    "sg:phone":"+1 713 743 9921",
    "sg:postcode":"77004",
    "sg:province":"TX",
    "sg:website":"www.mcalistersdeli.com",
    "wof:name":"McAlister's Deli",
    "wof:placetype":"venue"
},
  "geometry": {"coordinates":[-95.33922200000001,29.71877],"type":"Point"}
}