{
  "type": "Feature",
  "properties": {
    "iso:country":"US",
    "sg:address":"2616 Jacksboro Hwy",
    "sg:city":"Fort Worth",
    "sg:classifiers":[
        {
            "category":"Food & Beverages",
            "subcategory":"Groceries & Convenience Stores",
            "type":"Retail Goods"
        }
    ],
    "sg:phone":"+1 817 378 0722",
    "sg:postcode":"76114",
    "sg:province":"TX",
    "wof:name":"Four Star Food Mart",
    "wof:placetype":"venue"
},
  "geometry": {"coordinates":[-97.38729600000001,32.788851],"type":"Point"}
}