{
  "type": "Feature",
  "properties": {
    "iso:country":"US",
    "sg:address":"824 W 27th St",
    "sg:city":"Houston",
    "sg:classifiers":[
        {
            "category":"Professional",
            "subcategory":"Accounting & Tax Preparation",
            "type":"Services"
        }
    ],
    "sg:phone":"+1 713 862 4332",
    "sg:postcode":"77008",
    "sg:province":"TX",
    "sg:tags":[
        "accountant"
    ],
    "wof:name":"Rodrick Dow CPA",
    "wof:placetype":"venue"
},
  "geometry": {"coordinates":[-95.4132,29.811001],"type":"Point"}
}