{
  "type": "Feature",
  "properties": {
    "iso:country":"US",
    "sg:address":"6611 Holloway Square Ln",
    "sg:city":"Richmond",
    "sg:classifiers":[
        {
            "category":"Education",
            "subcategory":"School",
            "type":"Public Place"
        }
    ],
    "sg:phone":"+1 713 773 6117",
    "sg:postcode":"77469",
    "sg:province":"TX",
    "wof:name":"Jackson Renita",
    "wof:placetype":"venue"
},
  "geometry": {"coordinates":[-95.68955,29.705702],"type":"Point"}
}