{
  "type": "Feature",
  "properties": {
    "iso:country":"US",
    "sg:address":"2701 Parker Ave",
    "sg:city":"Round Rock",
    "sg:classifiers":[
        {
            "category":"Shopping",
            "subcategory":"Clothing, Apparel, & Fashions",
            "type":"Retail Goods"
        }
    ],
    "sg:phone":"+1 512 600 0206",
    "sg:postcode":"78681",
    "sg:province":"TX",
    "wof:name":"Dress Barn",
    "wof:placetype":"venue"
},
  "geometry": {"coordinates":[-97.68121499999999,30.483203],"type":"Point"}
}