{
  "type": "Feature",
  "properties": {
    "iso:country":"US",
    "sg:address":"4550 Post Oak Place Dr",
    "sg:city":"Houston",
    "sg:classifiers":[
        {
            "category":"Shopping",
            "subcategory":"Computers & Home Electronics",
            "type":"Retail Goods"
        }
    ],
    "sg:phone":"+1 713 655 5108",
    "sg:postcode":"77027",
    "sg:province":"TX",
    "sg:tags":[
        "software"
    ],
    "wof:name":"Front Ends Inc",
    "wof:placetype":"venue"
},
  "geometry": {"coordinates":[-95.450357,29.750339],"type":"Point"}
}