{
  "type": "Feature",
  "properties": {
    "iso:country":"US",
    "sg:address":"2201 Airport Boulevard",
    "sg:city":"Austin",
    "sg:classifiers":[
        {
            "category":"Autos & Motor Vehicles",
            "subcategory":"Auto Supplies",
            "type":"Retail Goods"
        }
    ],
    "sg:phone":"+1 512 478 3412",
    "sg:postcode":"78722",
    "sg:province":"TX",
    "sg:tags":[
        "tire"
    ],
    "wof:name":"Gcr Truck Tire Center",
    "wof:placetype":"venue"
},
  "geometry": {"coordinates":[-97.705648,30.284904],"type":"Point"}
}