{
  "type": "Feature",
  "properties": {
    "iso:country":"US",
    "sg:address":"2493 S Braeswood Blvd",
    "sg:city":"Houston",
    "sg:classifiers":[
        {
            "category":"Health Services",
            "subcategory":"Dentist",
            "type":"Services"
        }
    ],
    "sg:phone":"+1 713 218 0500",
    "sg:postcode":"77030",
    "sg:province":"TX",
    "wof:name":"Texan Dental",
    "wof:placetype":"venue"
},
  "geometry": {"coordinates":[-95.41754,29.696949],"type":"Point"}
}