{
  "type": "Feature",
  "properties": {
    "iso:country":"US",
    "sg:address":"8202 Wexford Dr",
    "sg:city":"Austin",
    "sg:classifiers":[
        {
            "category":"Organizations",
            "subcategory":"Non-profit Organization",
            "type":"Services"
        }
    ],
    "sg:phone":"+1 512 832 5515",
    "sg:postcode":"78759",
    "sg:province":"TX",
    "sg:tags":[
        "information",
        "alcoholism",
        "treatment"
    ],
    "wof:name":"Covering Your Assets",
    "wof:placetype":"venue"
},
  "geometry": {"coordinates":[-97.779878,30.428372],"type":"Point"}
}