{
  "type": "Feature",
  "properties": {
    "iso:country":"US",
    "sg:address":"1900 Saint James Pl Ste 650",
    "sg:city":"Houston",
    "sg:classifiers":[
        {
            "category":"Health Services",
            "subcategory":"Doctor",
            "type":"Services"
        },
        {
            "category":"Personal",
            "subcategory":"Hair Removal",
            "type":"Services"
        }
    ],
    "sg:phone":"+1 713 850 0240",
    "sg:postcode":"77056",
    "sg:province":"TX",
    "sg:tags":[
        "dermatologist"
    ],
    "wof:name":"Center For Cosmetic Dermatology",
    "wof:placetype":"venue"
},
  "geometry": {"coordinates":[-95.473198,29.747999],"type":"Point"}
}