{
  "type": "Feature",
  "properties": {
    "iso:country":"US",
    "sg:address":"2821 Dulles Ave",
    "sg:city":"Missouri City",
    "sg:classifiers":[
        {
            "category":"Retail",
            "subcategory":"Laundry & Dry Cleaning",
            "type":"Services"
        }
    ],
    "sg:phone":"+1 281 403 4025",
    "sg:postcode":"77459",
    "sg:province":"TX",
    "sg:tags":[
        "drycleaning",
        "plant"
    ],
    "wof:name":"Pilgrim Cleaners 51",
    "wof:placetype":"venue"
},
  "geometry": {"coordinates":[-95.581885,29.582005],"type":"Point"}
}