{
  "type": "Feature",
  "properties": {
    "iso:country":"US",
    "sg:address":"601 Turtle Creek Dr",
    "sg:city":"Tyler",
    "sg:classifiers":[
        {
            "category":"Health Services",
            "subcategory":"Doctor",
            "type":"Services"
        }
    ],
    "sg:phone":"+1 903 592 6535",
    "sg:postcode":"75701",
    "sg:province":"TX",
    "wof:name":"Humphries M Wayne DDS Inc",
    "wof:placetype":"venue"
},
  "geometry": {"coordinates":[-95.293966,32.33927],"type":"Point"}
}