{
  "type": "Feature",
  "properties": {
    "iso:country":"US",
    "sg:address":"207 E 12th St",
    "sg:city":"Joshua",
    "sg:classifiers":[
        {
            "category":"Building & Trades",
            "subcategory":"Construction",
            "type":"Services"
        }
    ],
    "sg:phone":"+1 817 558 4008",
    "sg:postcode":"76058",
    "sg:province":"TX",
    "sg:tags":[
        "house"
    ],
    "wof:name":"Lloyd Browner Construction",
    "wof:placetype":"venue"
},
  "geometry": {"coordinates":[-97.378438,32.461842],"type":"Point"}
}