{
  "type": "Feature",
  "properties": {
    "iso:country":"US",
    "sg:address":"1933 E Front St",
    "sg:city":"Midland",
    "sg:classifiers":[
        {
            "category":"Wholesale",
            "subcategory":"Auto Parts",
            "type":"Manufacturing & Wholesale Goods"
        }
    ],
    "sg:phone":"+1 432 570 7923",
    "sg:postcode":"79701",
    "sg:province":"TX",
    "wof:name":"Chaparral Tire & Supply",
    "wof:placetype":"venue"
},
  "geometry": {"coordinates":[-102.05506200000001,32.005806],"type":"Point"}
}