{
  "type": "Feature",
  "properties": {
    "iso:country":"US",
    "sg:address":"2204 E Airline Rd",
    "sg:city":"Victoria",
    "sg:classifiers":[
        {
            "category":"Health Services",
            "subcategory":"Clinic",
            "type":"Services"
        }
    ],
    "sg:phone":"+1 361 576 5212",
    "sg:postcode":"77901",
    "sg:province":"TX",
    "wof:name":"Advanced Health Services",
    "wof:placetype":"venue"
},
  "geometry": {"coordinates":[-96.98092800000001,28.821868],"type":"Point"}
}