{
  "type": "Feature",
  "properties": {
    "iso:country":"US",
    "sg:address":"1008 Marlene Dr",
    "sg:city":"Fort Worth",
    "sg:classifiers":[
        {
            "category":"Restaurant",
            "type":"Food & Drink"
        }
    ],
    "sg:phone":"+1 817 551 6366",
    "sg:postcode":"76140",
    "sg:province":"TX",
    "sg:tags":[
        "eating"
    ],
    "wof:name":"The Pit Bar-B-Que",
    "wof:placetype":"venue"
},
  "geometry": {"coordinates":[-97.29882499999999,32.628649],"type":"Point"}
}