{
  "type": "Feature",
  "properties": {
    "iso:country":"US",
    "sg:address":"408 Gravis St",
    "sg:city":"San Diego",
    "sg:classifiers":[
        {
            "category":"Wholesale",
            "subcategory":"Groceries",
            "type":"Manufacturing & Wholesale Goods"
        }
    ],
    "sg:phone":"+1 361 279 2889",
    "sg:postcode":"78384",
    "sg:province":"TX",
    "sg:tags":[
        "general"
    ],
    "wof:name":"Healthy Beginnings",
    "wof:placetype":"venue"
},
  "geometry": {"coordinates":[-98.407678,27.596284],"type":"Point"}
}