{
  "type": "Feature",
  "properties": {
    "iso:country":"US",
    "sg:address":"201 W Main Dr",
    "sg:city":"El Paso",
    "sg:classifiers":[
        {
            "category":"Banks & Credit Unions",
            "subcategory":"Investment Brokerage",
            "type":"Services"
        }
    ],
    "sg:phone":"+1 915 544 2786",
    "sg:postcode":"79901",
    "sg:province":"TX",
    "sg:tags":[
        "advisory",
        "financial"
    ],
    "wof:name":"Raymond James Financial Svc",
    "wof:placetype":"venue"
},
  "geometry": {"coordinates":[-106.49101,31.758637],"type":"Point"}
}