{
  "type": "Feature",
  "properties": {
    "iso:country":"US",
    "sg:address":"2745 Valwood Pkwy",
    "sg:city":"Dallas",
    "sg:classifiers":[
        {
            "category":"Organizations",
            "subcategory":"Religious Organization",
            "type":"Services"
        }
    ],
    "sg:phone":"+1 469 522 1365",
    "sg:postcode":"75234",
    "sg:province":"TX",
    "wof:name":"Valwood Park Student Ministry",
    "wof:placetype":"venue"
},
  "geometry": {"coordinates":[-96.88867399999999,32.938485],"type":"Point"}
}