{
  "type": "Feature",
  "properties": {
    "iso:country":"US",
    "sg:address":"3006 W 26th Ave",
    "sg:city":"Amarillo",
    "sg:classifiers":[
        {
            "category":"Autos & Motor Vehicles",
            "subcategory":"Automobile Sales",
            "type":"Retail Goods"
        }
    ],
    "sg:phone":"+1 806 355 8920",
    "sg:postcode":"79109",
    "sg:province":"TX",
    "sg:tags":[
        "used"
    ],
    "wof:name":"Harvest Autos",
    "wof:placetype":"venue"
},
  "geometry": {"coordinates":[-101.873305,35.185851],"type":"Point"}
}