{
  "type": "Feature",
  "properties": {
    "iso:country":"US",
    "sg:address":"715 W Jefferson St",
    "sg:city":"Brownsville",
    "sg:classifiers":[
        {
            "category":"Health Services",
            "subcategory":"Doctor",
            "type":"Services"
        }
    ],
    "sg:phone":"+1 956 544 3300",
    "sg:postcode":"78520",
    "sg:province":"TX",
    "sg:tags":[
        "physician",
        "surgeon"
    ],
    "wof:name":"Jefferson Day & Night Clinic",
    "wof:placetype":"venue"
},
  "geometry": {"coordinates":[-97.510411,25.916104],"type":"Point"}
}