{
  "type": "Feature",
  "properties": {
    "iso:country":"US",
    "sg:address":"810 S Main St",
    "sg:city":"Weatherford",
    "sg:classifiers":[
        {
            "category":"Shopping",
            "subcategory":"Optical Goods",
            "type":"Retail Goods"
        }
    ],
    "sg:phone":"+1 817 596 5020",
    "sg:postcode":"76086",
    "sg:province":"TX",
    "sg:tags":[
        "contact",
        "lense"
    ],
    "wof:name":"Weatherford Ophthalmology Clnc",
    "wof:placetype":"venue"
},
  "geometry": {"coordinates":[-97.79753700000001,32.751218],"type":"Point"}
}