{
  "type": "Feature",
  "properties": {
    "iso:country":"US",
    "sg:address":"6610 Paso del Sol Dr",
    "sg:city":"Houston",
    "sg:classifiers":[
        {
            "category":"Building & Trades",
            "subcategory":"Construction",
            "type":"Services"
        }
    ],
    "sg:phone":"+1 281 568 4481",
    "sg:postcode":"77083",
    "sg:province":"TX",
    "sg:tags":[
        "contractor"
    ],
    "wof:name":"Vega & Assoc",
    "wof:placetype":"venue"
},
  "geometry": {"coordinates":[-95.6735,29.706158],"type":"Point"}
}