{
  "type": "Feature",
  "properties": {
    "iso:country":"US",
    "sg:address":"2202 Dallas St",
    "sg:city":"San Angelo",
    "sg:classifiers":[
        {
            "category":"Building & Trades",
            "subcategory":"Cleaning & Sanitation",
            "type":"Services"
        }
    ],
    "sg:phone":"+1 325 947 7799",
    "sg:postcode":"76901",
    "sg:province":"TX",
    "sg:tags":[
        "janitor"
    ],
    "wof:name":"Commercial Janitorial & Mntnc",
    "wof:placetype":"venue"
},
  "geometry": {"coordinates":[-100.46828600000001,31.457945],"type":"Point"}
}