{
  "type": "Feature",
  "properties": {
    "iso:country":"US",
    "sg:address":"820 51st St",
    "sg:city":"Galveston",
    "sg:phone":"+1 409 762 3329",
    "sg:postcode":"77551",
    "sg:province":"TX",
    "sg:tags":[
        "equipment",
        "commercial",
        "mfg"
    ],
    "wof:name":"DAngelos Restaurant Equipment",
    "wof:placetype":"venue"
},
  "geometry": {"coordinates":[-94.824653,29.29371],"type":"Point"}
}