{
  "type": "Feature",
  "properties": {
    "iso:country":"US",
    "sg:address":"11500 N Mo Pac Expy",
    "sg:city":"Austin",
    "sg:classifiers":[
        {
            "category":"Professional",
            "subcategory":"Computer Services",
            "type":"Services"
        }
    ],
    "sg:phone":"+1 512 433 8000",
    "sg:postcode":"78759",
    "sg:province":"TX",
    "sg:tags":[
        "prepackaged",
        "specializing",
        "provides",
        "software"
    ],
    "wof:name":"NATIONAL INSTRUMENTS",
    "wof:placetype":"venue"
},
  "geometry": {"coordinates":[-97.72846,30.403388],"type":"Point"}
}