{
  "type": "Feature",
  "properties": {
    "iso:country":"US",
    "sg:address":"3814 Carlton Dr",
    "sg:city":"Amarillo",
    "sg:classifiers":[
        {
            "category":"Real Estate",
            "subcategory":"Real Estate Services",
            "type":"Services"
        },
        {
            "category":"Industrial Area",
            "type":"Public Place"
        }
    ],
    "sg:phone":"+1 806 355 6166",
    "sg:postcode":"79109",
    "sg:province":"TX",
    "sg:tags":[
        "development",
        "management"
    ],
    "wof:name":"Marlow Woods",
    "wof:placetype":"venue"
},
  "geometry": {"coordinates":[-101.905739,35.171242],"type":"Point"}
}