{
  "type": "Feature",
  "properties": {
    "iso:country":"US",
    "sg:address":"402 Mills Ave",
    "sg:city":"Dumas",
    "sg:classifiers":[
        {
            "category":"Home & Garden",
            "subcategory":"Garden Supply",
            "type":"Retail Goods"
        }
    ],
    "sg:phone":"+1 806 935 3361",
    "sg:postcode":"79029",
    "sg:province":"TX",
    "wof:name":"Ward Gary & Mayla",
    "wof:placetype":"venue"
},
  "geometry": {"coordinates":[-101.958943,35.862243],"type":"Point"}
}