{
  "type": "Feature",
  "properties": {
    "iso:country":"US",
    "sg:address":"11230 Airline Dr",
    "sg:city":"Houston",
    "sg:classifiers":[
        {
            "category":"Health Services",
            "subcategory":"Doctor",
            "type":"Services"
        }
    ],
    "sg:phone":"+1 281 447 6334",
    "sg:postcode":"77037",
    "sg:province":"TX",
    "wof:name":"Gupta K K MD",
    "wof:placetype":"venue"
},
  "geometry": {"coordinates":[-95.406216,29.919442],"type":"Point"}
}