{
  "type": "Feature",
  "properties": {
    "iso:country":"US",
    "sg:address":"4300 Dixie Dr",
    "sg:city":"Houston",
    "sg:classifiers":[
        {
            "category":"Freight",
            "type":"Transportation"
        }
    ],
    "sg:phone":"+1 713 440 0512",
    "sg:postcode":"77021",
    "sg:province":"TX",
    "sg:tags":[
        "trucking"
    ],
    "wof:name":"Fast Track Trucking",
    "wof:placetype":"venue"
},
  "geometry": {"coordinates":[-95.3518,29.700084],"type":"Point"}
}