{
  "type": "Feature",
  "properties": {
    "iso:country":"US",
    "sg:address":"Pacific Center I 14180 Dallas Parkway, Suite 300",
    "sg:city":"Dallas",
    "sg:classifiers":[
        {
            "category":"Professional",
            "subcategory":"Computer Services",
            "type":"Services"
        }
    ],
    "sg:phone":"+1 904 273 2440",
    "sg:postcode":"75254",
    "sg:province":"TX",
    "sg:tags":[
        "apm",
        "alternative-payment-method",
        "bill-to-phone",
        "phone-bill-charges",
        "no-credit-card-required",
        "lec-billing"
    ],
    "sg:website":"http://www.ildteleservices.com",
    "wof:name":"ILD Teleservices",
    "wof:placetype":"venue"
},
  "geometry": {"coordinates":[-96.82364099999999,32.946495],"type":"Point"}
}