{
  "type": "Feature",
  "properties": {
    "iso:country":"US",
    "sg:address":"2818 W Mount Dr",
    "sg:city":"Corpus Christi",
    "sg:classifiers":[
        {
            "category":"Shopping",
            "type":"Retail Goods"
        }
    ],
    "sg:phone":"+1 361 334 2747",
    "sg:postcode":"78414",
    "sg:province":"TX",
    "sg:tags":[
        "equipment",
        "medical",
        "trading",
        "agriculture",
        "general"
    ],
    "wof:name":"St Martha Farms Trading Inc",
    "wof:placetype":"venue"
},
  "geometry": {"coordinates":[-97.348747,27.669196],"type":"Point"}
}