{
  "type": "Feature",
  "properties": {
    "iso:country":"US",
    "sg:address":"5011 Gladeview Dr",
    "sg:city":"Austin",
    "sg:classifiers":[
        {
            "category":"Building & Trades",
            "subcategory":"Landscaping Services",
            "type":"Services"
        }
    ],
    "sg:phone":"+1 512 416 7095",
    "sg:postcode":"78745",
    "sg:province":"TX",
    "wof:name":"Ladybugs Lawn & Landscaping",
    "wof:placetype":"venue"
},
  "geometry": {"coordinates":[-97.78917300000001,30.22025],"type":"Point"}
}