{
  "type": "Feature",
  "properties": {
    "iso:country":"US",
    "sg:address":"144 S Buckner Blvd",
    "sg:city":"Dallas",
    "sg:classifiers":[
        {
            "category":"Shopping",
            "subcategory":"Pawn Shop",
            "type":"Retail Goods"
        }
    ],
    "sg:phone":"+1 214 391 1103",
    "sg:postcode":"75217",
    "sg:province":"TX",
    "wof:name":"EZ Pawn Regional Office",
    "wof:placetype":"venue"
},
  "geometry": {"coordinates":[-96.68274700000001,32.714862],"type":"Point"}
}