{
  "type": "Feature",
  "properties": {
    "iso:country":"US",
    "sg:address":"4375 Coffee Port Rd",
    "sg:city":"Brownsville",
    "sg:classifiers":[
        {
            "category":"Manufacturing",
            "subcategory":"Watercraft",
            "type":"Manufacturing & Wholesale Goods"
        }
    ],
    "sg:phone":"+1 956 831 0581",
    "sg:postcode":"78521",
    "sg:province":"TX",
    "sg:tags":[
        "boat"
    ],
    "wof:name":"Lone Star Multi Hulls",
    "wof:placetype":"venue"
},
  "geometry": {"coordinates":[-97.45152899999999,25.940169],"type":"Point"}
}