{
  "type": "Feature",
  "properties": {
    "iso:country":"US",
    "sg:address":"13334 Rain Lily Ln",
    "sg:city":"Houston",
    "sg:classifiers":[
        {
            "category":"Building & Trades",
            "subcategory":"Construction",
            "type":"Services"
        }
    ],
    "sg:phone":"+1 281 820 8555",
    "sg:postcode":"77083",
    "sg:province":"TX",
    "sg:tags":[
        "residential"
    ],
    "wof:name":"I & R Construction",
    "wof:placetype":"venue"
},
  "geometry": {"coordinates":[-95.61744899999999,29.711424],"type":"Point"}
}