{
  "type": "Feature",
  "properties": {
    "iso:country":"US",
    "sg:address":"2381 Becker Dr",
    "sg:city":"Brenham",
    "sg:classifiers":[
        {
            "category":"Manufacturing",
            "subcategory":"Petroleum Products",
            "type":"Manufacturing & Wholesale Goods"
        }
    ],
    "sg:phone":"+1 979 836 8955",
    "sg:postcode":"77833",
    "sg:province":"TX",
    "wof:name":"Petroleum Leases Inc",
    "wof:placetype":"venue"
},
  "geometry": {"coordinates":[-96.38752599999999,30.147572],"type":"Point"}
}