{
  "type": "Feature",
  "properties": {
    "iso:country":"US",
    "sg:address":"5050 Tanglewood Ln",
    "sg:city":"Odessa",
    "sg:classifiers":[
        {
            "category":"Travel",
            "subcategory":"Hotels & Motels",
            "type":"Entertainment"
        }
    ],
    "sg:phone":"+1 432 362 4113",
    "sg:postcode":"79762",
    "sg:province":"TX",
    "wof:name":"Homestyle Suites Apartments",
    "wof:placetype":"venue"
},
  "geometry": {"coordinates":[-102.343971,31.898914],"type":"Point"}
}