{
  "type": "Feature",
  "properties": {
    "iso:country":"US",
    "sg:address":"1623 Lime Leaf Ln",
    "sg:city":"Duncanville",
    "sg:classifiers":[
        {
            "category":"Building & Trades",
            "subcategory":"Equipment Rental",
            "type":"Services"
        }
    ],
    "sg:phone":"+1 972 709 4188",
    "sg:postcode":"75137",
    "sg:province":"TX",
    "wof:name":"First Choice Leasing Inc",
    "wof:placetype":"venue"
},
  "geometry": {"coordinates":[-96.896716,32.629847],"type":"Point"}
}