{
  "type": "Feature",
  "properties": {
    "iso:country":"US",
    "sg:address":"12119 Old County Rd",
    "sg:city":"Willis",
    "sg:classifiers":[
        {
            "category":"Professional",
            "type":"Services"
        }
    ],
    "sg:phone":"+1 936 718 2302",
    "sg:postcode":"77378",
    "sg:province":"TX",
    "wof:name":"Sno King",
    "wof:placetype":"venue"
},
  "geometry": {"coordinates":[-95.457106,30.416049],"type":"Point"}
}