{
  "type": "Feature",
  "properties": {
    "iso:country":"US",
    "sg:address":"103 Gregory Dr",
    "sg:city":"Del Rio",
    "sg:classifiers":[
        {
            "category":"Insurance",
            "subcategory":"Hazard Insurance",
            "type":"Services"
        }
    ],
    "sg:phone":"+1 830 778 2245",
    "sg:postcode":"78840",
    "sg:province":"TX",
    "sg:tags":[
        "bond"
    ],
    "wof:name":"Rio Grande Bail Bonds",
    "wof:placetype":"venue"
},
  "geometry": {"coordinates":[-100.84619499999999,29.372773],"type":"Point"}
}