{
  "type": "Feature",
  "properties": {
    "iso:country":"US",
    "sg:address":"1009 E 11th St",
    "sg:city":"Austin",
    "sg:classifiers":[
        {
            "category":"Professional",
            "subcategory":"Management & Consulting",
            "type":"Services"
        }
    ],
    "sg:phone":"+1 512 472 1472",
    "sg:postcode":"78702",
    "sg:province":"TX",
    "sg:tags":[
        "development",
        "economic",
        "agency",
        "business"
    ],
    "wof:name":"East Austin Economic Dev Corp",
    "wof:placetype":"venue"
},
  "geometry": {"coordinates":[-97.730531,30.269605],"type":"Point"}
}