{
  "type": "Feature",
  "properties": {
    "iso:country":"US",
    "sg:address":"7111 Turtle Creek Blvd",
    "sg:city":"Dallas",
    "sg:classifiers":[
        {
            "category":"Professional",
            "type":"Services"
        }
    ],
    "sg:phone":"+1 214 369 3077",
    "sg:postcode":"75225",
    "sg:province":"TX",
    "wof:name":"SLK Designs Lolette May",
    "wof:placetype":"venue"
},
  "geometry": {"coordinates":[-96.794883,32.851977],"type":"Point"}
}