{
  "type": "Feature",
  "properties": {
    "iso:country":"US",
    "sg:address":"413 Goldfinch Dr",
    "sg:city":"Fort Worth",
    "sg:classifiers":[
        {
            "category":"Building & Trades",
            "subcategory":"Plumbing",
            "type":"Services"
        }
    ],
    "sg:phone":"+1 817 246 8399",
    "sg:postcode":"76108",
    "sg:province":"TX",
    "sg:tags":[
        "conditioning",
        "air",
        "system",
        "contractor"
    ],
    "wof:name":"Baird's Air Conditioning Inc",
    "wof:placetype":"venue"
},
  "geometry": {"coordinates":[-97.493701,32.752876],"type":"Point"}
}