{
  "type": "Feature",
  "properties": {
    "iso:country":"US",
    "sg:address":"8200 Neely Drive",
    "sg:city":"Austin",
    "sg:classifiers":[
        {
            "category":"Wholesale",
            "subcategory":"Computers",
            "type":"Manufacturing & Wholesale Goods"
        }
    ],
    "sg:phone":"+1 512 418 0303",
    "sg:postcode":"78759",
    "sg:province":"TX",
    "sg:website":"www.prospertech.com",
    "wof:name":"Prospertech Group",
    "wof:placetype":"venue"
},
  "geometry": {"coordinates":[-97.758522,30.377372],"type":"Point"}
}