{
  "type": "Feature",
  "properties": {
    "iso:country":"US",
    "sg:address":"100 San Saba Ave",
    "sg:city":"Benbrook",
    "sg:classifiers":[
        {
            "category":"Shopping",
            "subcategory":"Pharmacy",
            "type":"Retail Goods"
        },
        {
            "category":"Shopping",
            "subcategory":"Computers & Home Electronics",
            "type":"Retail Goods"
        }
    ],
    "sg:phone":"+1 817 249 2934",
    "sg:postcode":"76126",
    "sg:province":"TX",
    "sg:tags":[
        "equipment",
        "dealer"
    ],
    "wof:name":"Computer Rx",
    "wof:placetype":"venue"
},
  "geometry": {"coordinates":[-97.46041,32.681517],"type":"Point"}
}