{
  "type": "Feature",
  "properties": {
    "iso:country":"US",
    "sg:address":"221 E Main St",
    "sg:city":"Fredericksburg",
    "sg:classifiers":[
        {
            "category":"Shopping",
            "subcategory":"Used Merchandise",
            "type":"Retail Goods"
        }
    ],
    "sg:phone":"+1 830 990 9394",
    "sg:postcode":"78624",
    "sg:province":"TX",
    "sg:tags":[
        "antique"
    ],
    "wof:name":"Johnson Newman Antiques",
    "wof:placetype":"venue"
},
  "geometry": {"coordinates":[-98.87034,30.273554],"type":"Point"}
}