{
  "type": "Feature",
  "properties": {
    "iso:country":"US",
    "sg:address":"4402 Five Points Rd",
    "sg:city":"Corpus Christi",
    "sg:classifiers":[
        {
            "category":"Wholesale",
            "subcategory":"Machinery & Supplies",
            "type":"Manufacturing & Wholesale Goods"
        }
    ],
    "sg:phone":"+1 361 241 1000",
    "sg:postcode":"78410",
    "sg:province":"TX",
    "sg:tags":[
        "contractor"
    ],
    "sg:website":"www.hvequipment.com",
    "wof:name":"H & V Equipment Svc",
    "wof:placetype":"venue"
},
  "geometry": {"coordinates":[-97.620912,27.862003],"type":"Point"}
}