{
  "type": "Feature",
  "properties": {
    "iso:country":"US",
    "sg:address":"3656 Culebra Rd",
    "sg:city":"San Antonio",
    "sg:classifiers":[
        {
            "category":"Professional",
            "subcategory":"Art Services",
            "type":"Services"
        }
    ],
    "sg:phone":"+1 210 433 7920",
    "sg:postcode":"78228",
    "sg:province":"TX",
    "sg:tags":[
        "artist"
    ],
    "wof:name":"Power Grafx",
    "wof:placetype":"venue"
},
  "geometry": {"coordinates":[-98.57552099999999,29.449919],"type":"Point"}
}