{
  "type": "Feature",
  "properties": {
    "iso:country":"US",
    "sg:address":"411 E Brazos St",
    "sg:city":"Pearsall",
    "sg:classifiers":[
        {
            "category":"Social Services",
            "type":"Services"
        }
    ],
    "sg:phone":"+1 830 334 0075",
    "sg:postcode":"78061",
    "sg:province":"TX",
    "wof:name":"Camino Real Cmnty M H M R Ctr",
    "wof:placetype":"venue"
},
  "geometry": {"coordinates":[-99.092388,28.89257],"type":"Point"}
}