{
  "type": "Feature",
  "properties": {
    "iso:country":"US",
    "sg:address":"6303 N Mesa St",
    "sg:city":"El Paso",
    "sg:classifiers":[
        {
            "category":"Professional",
            "type":"Services"
        }
    ],
    "sg:phone":"+1 915 833 8301",
    "sg:postcode":"79912",
    "sg:province":"TX",
    "sg:tags":[
        "establishment"
    ],
    "wof:name":"Abolengo",
    "wof:placetype":"venue"
},
  "geometry": {"coordinates":[-106.533789,31.832088],"type":"Point"}
}