{
  "type": "Feature",
  "properties": {
    "iso:country":"US",
    "sg:address":"3015 Oklahoma St",
    "sg:city":"Houston",
    "sg:classifiers":[
        {
            "category":"Wholesale",
            "subcategory":"Stationery",
            "type":"Manufacturing & Wholesale Goods"
        }
    ],
    "sg:phone":"+1 713 695 2856",
    "sg:postcode":"77093",
    "sg:province":"TX",
    "sg:tags":[
        "paper"
    ],
    "wof:name":"Designs By Tenae",
    "wof:placetype":"venue"
},
  "geometry": {"coordinates":[-95.337746,29.822975],"type":"Point"}
}