{
  "type": "Feature",
  "properties": {
    "iso:country":"US",
    "sg:address":"5422 Ayers St",
    "sg:city":"Corpus Christi",
    "sg:classifiers":[
        {
            "category":"Wholesale",
            "subcategory":"Hardware",
            "type":"Manufacturing & Wholesale Goods"
        }
    ],
    "sg:phone":"+1 361 854 1463",
    "sg:postcode":"78415",
    "sg:province":"TX",
    "sg:tags":[
        "plumbing",
        "heating",
        "supply"
    ],
    "wof:name":"Noland Company",
    "wof:placetype":"venue"
},
  "geometry": {"coordinates":[-97.431021,27.729434],"type":"Point"}
}