{
  "type": "Feature",
  "properties": {
    "iso:country":"US",
    "sg:address":"900 Parker Square Rd",
    "sg:city":"Flower Mound",
    "sg:classifiers":[
        {
            "category":"Professional",
            "subcategory":"Employment Agencies",
            "type":"Services"
        }
    ],
    "sg:phone":"+1 972 899 8980",
    "sg:postcode":"75028",
    "sg:province":"TX",
    "wof:name":"Staffmark",
    "wof:placetype":"venue"
},
  "geometry": {"coordinates":[-97.05119500000001,33.038284],"type":"Point"}
}