{
  "type": "Feature",
  "properties": {
    "iso:country":"US",
    "sg:address":"1430 N Jim Miller Rd",
    "sg:city":"Dallas",
    "sg:classifiers":[
        {
            "category":"Organizations",
            "subcategory":"Religious Organization",
            "type":"Services"
        }
    ],
    "sg:phone":"+1 214 391 8953",
    "sg:postcode":"75217",
    "sg:province":"TX",
    "wof:name":"Jesus Limon",
    "wof:placetype":"venue"
},
  "geometry": {"coordinates":[-96.700002,32.736847],"type":"Point"}
}