{
  "type": "Feature",
  "properties": {
    "iso:country":"US",
    "sg:address":"1651 Wall St",
    "sg:city":"Garland",
    "sg:classifiers":[
        {
            "category":"Home & Garden",
            "subcategory":"Garden Supply",
            "type":"Retail Goods"
        }
    ],
    "sg:phone":"+1 972 864 1934",
    "sg:postcode":"75041",
    "sg:province":"TX",
    "sg:tags":[
        "nursery",
        "gardening"
    ],
    "wof:name":"Rhode's Nursery",
    "wof:placetype":"venue"
},
  "geometry": {"coordinates":[-96.659897,32.874802],"type":"Point"}
}