{
  "type": "Feature",
  "properties": {
    "iso:country":"US",
    "sg:address":"7502 Hershe St",
    "sg:city":"Houston",
    "sg:classifiers":[
        {
            "category":"Restaurant",
            "type":"Food & Drink"
        }
    ],
    "sg:phone":"+1 713 674 1519",
    "sg:postcode":"77020",
    "sg:province":"TX",
    "sg:tags":[
        "eating"
    ],
    "wof:name":"Taco Lady Express",
    "wof:placetype":"venue"
},
  "geometry": {"coordinates":[-95.29180599999999,29.778699],"type":"Point"}
}