{
  "type": "Feature",
  "properties": {
    "iso:country":"US",
    "sg:address":"1140 Empire Central Pl",
    "sg:city":"Dallas",
    "sg:classifiers":[
        {
            "category":"Banks & Credit Unions",
            "subcategory":"Bank",
            "type":"Services"
        }
    ],
    "sg:phone":"+1 214 637 3924",
    "sg:postcode":"75247",
    "sg:province":"TX",
    "wof:name":"Pollock Employees Credit Union",
    "wof:placetype":"venue"
},
  "geometry": {"coordinates":[-96.874622,32.823286],"type":"Point"}
}