{
  "type": "Feature",
  "properties": {
    "iso:country":"US",
    "sg:address":"2405 114th St",
    "sg:city":"Lubbock",
    "sg:classifiers":[
        {
            "category":"Wholesale",
            "subcategory":"Hardware",
            "type":"Manufacturing & Wholesale Goods"
        }
    ],
    "sg:phone":"+1 806 745 6691",
    "sg:postcode":"79423",
    "sg:province":"TX",
    "sg:tags":[
        "used",
        "boiler"
    ],
    "wof:name":"CHE Inc",
    "wof:placetype":"venue"
},
  "geometry": {"coordinates":[-101.865931,33.490717],"type":"Point"}
}