{
  "type": "Feature",
  "properties": {
    "iso:country":"US",
    "sg:address":"24310 Bear Claw",
    "sg:city":"San Antonio",
    "sg:classifiers":[
        {
            "category":"Manufacturing",
            "subcategory":"Buildings",
            "type":"Manufacturing & Wholesale Goods"
        }
    ],
    "sg:phone":"+1 830 980 5382",
    "sg:postcode":"78258",
    "sg:province":"TX",
    "sg:tags":[
        "mobile",
        "home",
        "mfg"
    ],
    "wof:name":"Clayton Homes Inc",
    "wof:placetype":"venue"
},
  "geometry": {"coordinates":[-98.457534,29.666951],"type":"Point"}
}