{
  "type": "Feature",
  "properties": {
    "iso:country":"US",
    "sg:address":"3801 Highway 35 N",
    "sg:city":"Rockport",
    "sg:classifiers":[
        {
            "category":"Personal",
            "type":"Services"
        },
        {
            "category":"Retail",
            "subcategory":"Auto Rental",
            "type":"Services"
        },
        {
            "category":"Retail",
            "subcategory":"Storage",
            "type":"Services"
        }
    ],
    "sg:phone":"+1 361 727 1529",
    "sg:postcode":"78382",
    "sg:province":"TX",
    "sg:tags":[
        "renting",
        "moving-self",
        "leasing",
        "car",
        "truck",
        "mover",
        "trailer"
    ],
    "wof:name":"U-Haul Co",
    "wof:placetype":"venue"
},
  "geometry": {"coordinates":[-97.041359,28.070043],"type":"Point"}
}