{
  "type": "Feature",
  "properties": {
    "iso:country":"US",
    "sg:address":"2000 Hwy 157 N",
    "sg:city":"Mansfield",
    "sg:classifiers":[
        {
            "category":"Shopping",
            "type":"Retail Goods"
        }
    ],
    "sg:phone":"+1 682 518 0303",
    "sg:postcode":"76063",
    "sg:province":"TX",
    "sg:tags":[
        "merchandise"
    ],
    "wof:name":"Charter Oak Coins",
    "wof:placetype":"venue"
},
  "geometry": {"coordinates":[-97.144096,32.603736],"type":"Point"}
}