{
  "type": "Feature",
  "properties": {
    "iso:country":"US",
    "sg:address":"3418 Shenandoah Dr",
    "sg:city":"Cedar Park",
    "sg:classifiers":[
        {
            "category":"Professional",
            "subcategory":"Management & Consulting",
            "type":"Services"
        }
    ],
    "sg:phone":"+1 512 258 8135",
    "sg:postcode":"78613",
    "sg:province":"TX",
    "wof:name":"Clay & Long",
    "wof:placetype":"venue"
},
  "geometry": {"coordinates":[-97.824234,30.470591],"type":"Point"}
}