{
  "type": "Feature",
  "properties": {
    "iso:country":"US",
    "sg:address":"9901 Windmill Lakes Blvd",
    "sg:city":"Houston",
    "sg:classifiers":[
        {
            "category":"Social Services",
            "subcategory":"Child Care",
            "type":"Services"
        }
    ],
    "sg:phone":"+1 713 910 0800",
    "sg:postcode":"77075",
    "sg:province":"TX",
    "sg:tags":[
        "day"
    ],
    "sg:website":"www.lifeslittleblessings.com",
    "wof:name":"Life's Little Blessings",
    "wof:placetype":"venue"
},
  "geometry": {"coordinates":[-95.240303,29.6259],"type":"Point"}
}