{
  "type": "Feature",
  "properties": {
    "iso:country":"US",
    "sg:address":"10828 Park Road 37",
    "sg:city":"Lakehills",
    "sg:classifiers":[
        {
            "category":"Building & Trades",
            "subcategory":"Construction",
            "type":"Services"
        },
        {
            "category":"Military Area",
            "subcategory":"Armory",
            "type":"Public Place"
        }
    ],
    "sg:phone":"+1 830 612 2918",
    "sg:postcode":"78063",
    "sg:province":"TX",
    "sg:tags":[
        "repair",
        "fence-sales",
        "fence",
        "contractor"
    ],
    "wof:name":"Fence Feed And More",
    "wof:placetype":"venue"
},
  "geometry": {"coordinates":[-98.893277,29.632639],"type":"Point"}
}