{
  "type": "Feature",
  "properties": {
    "iso:country":"US",
    "sg:address":"7200 Bishop Rd",
    "sg:city":"Plano",
    "sg:classifiers":[
        {
            "category":"Shopping",
            "subcategory":"Tobacco",
            "type":"Retail Goods"
        }
    ],
    "sg:phone":"+1 469 467 6653",
    "sg:postcode":"75024",
    "sg:province":"TX",
    "sg:tags":[
        "cigarette",
        "cigar",
        "dealer"
    ],
    "wof:name":"Cigary",
    "wof:placetype":"venue"
},
  "geometry": {"coordinates":[-96.821415,33.076065],"type":"Point"}
}