{
  "type": "Feature",
  "properties": {
    "iso:country":"US",
    "sg:address":"27090 State Hwy 6 S",
    "sg:city":"Navasota",
    "sg:classifiers":[
        {
            "category":"Wholesale",
            "subcategory":"Auto Parts",
            "type":"Manufacturing & Wholesale Goods"
        }
    ],
    "sg:phone":"+1 936 825 7330",
    "sg:postcode":"77868",
    "sg:province":"TX",
    "sg:tags":[
        "automobile",
        "rebuilt"
    ],
    "wof:name":"Maldonado's Junk Yard",
    "wof:placetype":"venue"
},
  "geometry": {"coordinates":[-96.12331,30.43562],"type":"Point"}
}