{
  "type": "Feature",
  "properties": {
    "iso:country":"US",
    "sg:address":"1811 Royal College Hill Rd",
    "sg:city":"Conroe",
    "sg:classifiers":[
        {
            "category":"Professional",
            "subcategory":"Computer Services",
            "type":"Services"
        }
    ],
    "sg:phone":"+1 936 441 5698",
    "sg:postcode":"77304",
    "sg:province":"TX",
    "sg:tags":[
        "related"
    ],
    "wof:name":"A&J Services",
    "wof:placetype":"venue"
},
  "geometry": {"coordinates":[-95.48196799999999,30.308395],"type":"Point"}
}