{
  "type": "Feature",
  "properties": {
    "iso:country":"US",
    "sg:address":"3513 State Hwy 158",
    "sg:city":"Midland",
    "sg:classifiers":[
        {
            "category":"Mining & Drilling",
            "type":"Manufacturing & Wholesale Goods"
        }
    ],
    "sg:phone":"+1 432 684 4463",
    "sg:postcode":"79706",
    "sg:province":"TX",
    "sg:tags":[
        "oil",
        "gas",
        "producer"
    ],
    "wof:name":"Tema",
    "wof:placetype":"venue"
},
  "geometry": {"coordinates":[-102.00898599999999,31.974559],"type":"Point"}
}