{
  "type": "Feature",
  "properties": {
    "iso:country":"US",
    "sg:address":"1448 Westbrook Ave",
    "sg:city":"Odessa",
    "sg:classifiers":[
        {
            "category":"Manufacturing",
            "subcategory":"Tools & Machinery",
            "type":"Manufacturing & Wholesale Goods"
        }
    ],
    "sg:phone":"+1 432 559 4487",
    "sg:postcode":"79761",
    "sg:province":"TX",
    "sg:tags":[
        "engine",
        "equipment",
        "electrical",
        "mfg"
    ],
    "wof:name":"Perrys Radio & Auto",
    "wof:placetype":"venue"
},
  "geometry": {"coordinates":[-102.331648,31.872515],"type":"Point"}
}