{
  "type": "Feature",
  "properties": {
    "iso:country":"US",
    "sg:address":"6013 Sleepy Hollow Ave",
    "sg:city":"Texarkana",
    "sg:classifiers":[
        {
            "category":"Personal",
            "type":"Services"
        }
    ],
    "sg:phone":"+1 903 223 0770",
    "sg:postcode":"75503",
    "sg:province":"TX",
    "sg:tags":[
        "pet",
        "exercising"
    ],
    "wof:name":"Paws-Itive Pet Care Svc",
    "wof:placetype":"venue"
},
  "geometry": {"coordinates":[-94.11726,33.479846],"type":"Point"}
}