{
  "type": "Feature",
  "properties": {
    "iso:country":"US",
    "sg:address":"1850 Central Dr",
    "sg:city":"Bedford",
    "sg:classifiers":[
        {
            "category":"Health Services",
            "subcategory":"Doctor",
            "type":"Services"
        }
    ],
    "sg:phone":"+1 817 267 1521",
    "sg:postcode":"76022",
    "sg:province":"TX",
    "sg:tags":[
        "medical"
    ],
    "wof:name":"Chung C R",
    "wof:placetype":"venue"
},
  "geometry": {"coordinates":[-97.133366,32.838146],"type":"Point"}
}