{
  "type": "Feature",
  "properties": {
    "iso:country":"US",
    "sg:address":"5137 West Ave",
    "sg:city":"San Antonio",
    "sg:classifiers":[
        {
            "category":"Building & Trades",
            "subcategory":"Cleaning & Sanitation",
            "type":"Services"
        }
    ],
    "sg:phone":"+1 210 424 0166",
    "sg:postcode":"78213",
    "sg:province":"TX",
    "sg:tags":[
        "house"
    ],
    "wof:name":"Maid Brigade",
    "wof:placetype":"venue"
},
  "geometry": {"coordinates":[-98.52601300000001,29.513217],"type":"Point"}
}