{
  "type": "Feature",
  "properties": {
    "iso:country":"US",
    "sg:address":"2562 W Pioneer Pkwy",
    "sg:city":"Arlington",
    "sg:classifiers":[
        {
            "category":"Communications",
            "subcategory":"Film & Video Production",
            "type":"Services"
        }
    ],
    "sg:phone":"+1 817 861 2662",
    "sg:postcode":"76013",
    "sg:province":"TX",
    "sg:tags":[
        "motion",
        "picture"
    ],
    "wof:name":"Movie Exchange",
    "wof:placetype":"venue"
},
  "geometry": {"coordinates":[-97.150249,32.709658],"type":"Point"}
}