{
  "type": "Feature",
  "properties": {
    "iso:country":"US",
    "sg:address":"3590 Highland Ave",
    "sg:city":"Beaumont",
    "sg:classifiers":[
        {
            "category":"Food & Beverages",
            "subcategory":"Groceries & Convenience Stores",
            "type":"Retail Goods"
        }
    ],
    "sg:phone":"+1 409 835 7611",
    "sg:postcode":"77705",
    "sg:province":"TX",
    "wof:name":"Stop In Grocery",
    "wof:placetype":"venue"
},
  "geometry": {"coordinates":[-94.086021,30.052429],"type":"Point"}
}