{
  "type": "Feature",
  "properties": {
    "iso:country":"US",
    "sg:address":"122 W Hawk Ave",
    "sg:city":"Pharr",
    "sg:classifiers":[
        {
            "category":"Organizations",
            "subcategory":"Religious Organization",
            "type":"Services"
        }
    ],
    "sg:phone":"+1 956 787 8563",
    "sg:postcode":"78577",
    "sg:province":"TX",
    "sg:tags":[
        "church"
    ],
    "wof:name":"St Margaret's Church",
    "wof:placetype":"venue"
},
  "geometry": {"coordinates":[-98.184687,26.197664],"type":"Point"}
}