{
  "type": "Feature",
  "properties": {
    "iso:country":"US",
    "sg:address":"902 Texas Ave",
    "sg:city":"Texas City",
    "sg:classifiers":[
        {
            "category":"Autos & Motor Vehicles",
            "subcategory":"Automobile Sales",
            "type":"Retail Goods"
        }
    ],
    "sg:phone":"+1 409 945 4244",
    "sg:postcode":"77590",
    "sg:province":"TX",
    "sg:tags":[
        "used"
    ],
    "wof:name":"Bay Area Cars & Trucks",
    "wof:placetype":"venue"
},
  "geometry": {"coordinates":[-94.90858299999999,29.384075],"type":"Point"}
}