{
  "type": "Feature",
  "properties": {
    "iso:country":"US",
    "sg:address":"124 Perth St",
    "sg:city":"Victoria",
    "sg:classifiers":[
        {
            "category":"Personal",
            "type":"Services"
        }
    ],
    "sg:phone":"+1 361 578 7303",
    "sg:postcode":"77904",
    "sg:province":"TX",
    "wof:name":"A Healthy Touch",
    "wof:placetype":"venue"
},
  "geometry": {"coordinates":[-97.01729899999999,28.877187],"type":"Point"}
}