{
  "type": "Feature",
  "properties": {
    "iso:country":"US",
    "sg:address":"215 W San Antonio St",
    "sg:city":"San Marcos",
    "sg:classifiers":[
        {
            "category":"Wholesale",
            "subcategory":"Electrical",
            "type":"Manufacturing & Wholesale Goods"
        }
    ],
    "sg:phone":"+1 512 396 2124",
    "sg:postcode":"78666",
    "sg:province":"TX",
    "sg:tags":[
        "alarm",
        "burglar",
        "system"
    ],
    "wof:name":"Interactive Security",
    "wof:placetype":"venue"
},
  "geometry": {"coordinates":[-97.942813,29.881874],"type":"Point"}
}