{
  "type": "Feature",
  "properties": {
    "iso:country":"US",
    "sg:address":"1540 Keller Pkwy",
    "sg:city":"Keller",
    "sg:classifiers":[
        {
            "category":"Professional",
            "subcategory":"Advertising",
            "type":"Services"
        }
    ],
    "sg:phone":"+1 817 337 0233",
    "sg:postcode":"76248",
    "sg:province":"TX",
    "sg:tags":[
        "mailing",
        "shipping"
    ],
    "wof:name":"UPS Store",
    "wof:placetype":"venue"
},
  "geometry": {"coordinates":[-97.216129,32.934559],"type":"Point"}
}