{
  "type": "Feature",
  "properties": {
    "iso:country":"US",
    "sg:address":"810 Sceyne Rd",
    "sg:city":"Kilgore",
    "sg:classifiers":[
        {
            "category":"Shopping",
            "type":"Retail Goods"
        }
    ],
    "sg:phone":"+1 903 986 0501",
    "sg:postcode":"75662",
    "sg:province":"TX",
    "sg:tags":[
        "craft",
        "gallery",
        "dealer"
    ],
    "wof:name":"Blue Treasure Chest",
    "wof:placetype":"venue"
},
  "geometry": {"coordinates":[-94.86185999999999,32.387011],"type":"Point"}
}