{
  "type": "Feature",
  "properties": {
    "iso:country":"US",
    "sg:address":"808 S Shary Rd",
    "sg:city":"Mission",
    "sg:classifiers":[
        {
            "category":"Restaurant",
            "type":"Food & Drink"
        }
    ],
    "sg:menulink":"http://www.allmenus.com/tx/mission/139572-quiznos-sub/menu/",
    "sg:phone":"+1 956 581 0043",
    "sg:postcode":"78572",
    "sg:province":"TX",
    "sg:tags":[
        "wrap",
        "american",
        "sandwich"
    ],
    "wof:name":"Quiznos Sub",
    "wof:placetype":"venue"
},
  "geometry": {"coordinates":[-98.288286,26.196444],"type":"Point"}
}