{
  "type": "Feature",
  "properties": {
    "iso:country":"US",
    "sg:address":"113 Wood Oak St",
    "sg:city":"Joshua",
    "sg:classifiers":[
        {
            "category":"Building & Trades",
            "subcategory":"Construction",
            "type":"Services"
        }
    ],
    "sg:phone":"+1 817 295 9901",
    "sg:postcode":"76058",
    "sg:province":"TX",
    "sg:tags":[
        "concrete",
        "restoration",
        "cleaning",
        "repair"
    ],
    "wof:name":"R & B Concrete Cleaners",
    "wof:placetype":"venue"
},
  "geometry": {"coordinates":[-97.378474,32.487106],"type":"Point"}
}