{
  "type": "Feature",
  "properties": {
    "iso:country":"US",
    "sg:address":"9816 Memorial Blvd",
    "sg:city":"Humble",
    "sg:classifiers":[
        {
            "category":"Professional",
            "subcategory":"Detective & Security Services",
            "type":"Services"
        }
    ],
    "sg:phone":"+1 281 540 4329",
    "sg:postcode":"77338",
    "sg:province":"TX",
    "sg:tags":[
        "car"
    ],
    "wof:name":"Fax John",
    "wof:placetype":"venue"
},
  "geometry": {"coordinates":[-95.273111,29.993654],"type":"Point"}
}