{
  "type": "Feature",
  "properties": {
    "iso:country":"US",
    "sg:address":"576 Beverly Ln",
    "sg:city":"New Braunfels",
    "sg:classifiers":[
        {
            "category":"Building & Trades",
            "subcategory":"Equipment Rental",
            "type":"Services"
        }
    ],
    "sg:phone":"+1 830 625 4136",
    "sg:postcode":"78130",
    "sg:province":"TX",
    "wof:name":"Girlando Rental",
    "wof:placetype":"venue"
},
  "geometry": {"coordinates":[-98.14406200000001,29.707024],"type":"Point"}
}