{
  "type": "Feature",
  "properties": {
    "iso:country":"US",
    "sg:address":"908 N Beverly Dr",
    "sg:city":"Wichita Falls",
    "sg:classifiers":[
        {
            "category":"Manufacturing",
            "subcategory":"Toys & Sporting Goods",
            "type":"Manufacturing & Wholesale Goods"
        }
    ],
    "sg:phone":"+1 940 322 4463",
    "sg:postcode":"76306",
    "sg:province":"TX",
    "sg:tags":[
        "equipment",
        "swimming",
        "pool",
        "supply"
    ],
    "sg:website":"www.texasrec.com",
    "wof:name":"Texas Recreation Corp",
    "wof:placetype":"venue"
},
  "geometry": {"coordinates":[-98.532079,33.925808],"type":"Point"}
}