{
  "type": "Feature",
  "properties": {
    "iso:country":"US",
    "sg:address":"3401 US Hwy 290 E",
    "sg:city":"Brenham",
    "sg:classifiers":[
        {
            "category":"Professional",
            "subcategory":"Management & Consulting",
            "type":"Services"
        }
    ],
    "sg:phone":"+1 979 836 9463",
    "sg:postcode":"77833",
    "sg:province":"TX",
    "sg:tags":[
        "party",
        "planning"
    ],
    "wof:name":"Citadel",
    "wof:placetype":"venue"
},
  "geometry": {"coordinates":[-96.363202,30.142663],"type":"Point"}
}