{
  "type": "Feature",
  "properties": {
    "iso:country":"US",
    "sg:address":"7222 Westlyn Dr",
    "sg:city":"San Antonio",
    "sg:classifiers":[
        {
            "category":"Retail",
            "subcategory":"Repair Shop",
            "type":"Services"
        },
        {
            "category":"Personal",
            "type":"Services"
        }
    ],
    "sg:phone":"+1 210 674 7472",
    "sg:postcode":"78227",
    "sg:province":"TX",
    "sg:tags":[
        "related"
    ],
    "wof:name":"Pro Handy Man Repairs",
    "wof:placetype":"venue"
},
  "geometry": {"coordinates":[-98.63479599999999,29.410611],"type":"Point"}
}