{
  "type": "Feature",
  "properties": {
    "iso:country":"US",
    "sg:address":"2525 W Bellfort St Ste 194",
    "sg:city":"Houston",
    "sg:classifiers":[
        {
            "category":"Professional",
            "subcategory":"Employment Agencies",
            "type":"Services"
        }
    ],
    "sg:phone":"+1 713 640 3600",
    "sg:postcode":"77054",
    "sg:province":"TX",
    "sg:website":"www.aerotek.com",
    "wof:name":"Aerotek",
    "wof:placetype":"venue"
},
  "geometry": {"coordinates":[-95.41860699999999,29.672924],"type":"Point"}
}