{
  "type": "Feature",
  "properties": {
    "iso:country":"US",
    "sg:address":"10500 Metric Dr",
    "sg:city":"Dallas",
    "sg:classifiers":[
        {
            "category":"Wholesale",
            "subcategory":"Electrical",
            "type":"Manufacturing & Wholesale Goods"
        }
    ],
    "sg:phone":"+1 214 342 3905",
    "sg:postcode":"75243",
    "sg:province":"TX",
    "sg:tags":[
        "equipment",
        "electronic",
        "supply"
    ],
    "wof:name":"ABL Electronics Corp",
    "wof:placetype":"venue"
},
  "geometry": {"coordinates":[-96.702513,32.907396],"type":"Point"}
}