{
  "type": "Feature",
  "properties": {
    "iso:country":"US",
    "sg:address":"2200 N Stemmons Fwy",
    "sg:city":"Dallas",
    "sg:classifiers":[
        {
            "category":"Wholesale",
            "subcategory":"Non-durable Goods",
            "type":"Manufacturing & Wholesale Goods"
        }
    ],
    "sg:phone":"+1 214 752 2877",
    "sg:postcode":"75207",
    "sg:province":"TX",
    "wof:name":"Gift Wares Company Inc",
    "wof:placetype":"venue"
},
  "geometry": {"coordinates":[-96.82784100000001,32.802178],"type":"Point"}
}