{
  "type": "Feature",
  "properties": {
    "iso:country":"US",
    "sg:address":"1209 Industrial Ave",
    "sg:city":"Kilgore",
    "sg:classifiers":[
        {
            "category":"Mining & Drilling",
            "type":"Manufacturing & Wholesale Goods"
        }
    ],
    "sg:phone":"+1 903 984 3063",
    "sg:postcode":"75662",
    "sg:province":"TX",
    "sg:tags":[
        "field",
        "oil"
    ],
    "wof:name":"East Texas Salt Water Disposal",
    "wof:placetype":"venue"
},
  "geometry": {"coordinates":[-94.88634999999999,32.375936],"type":"Point"}
}