{
  "type": "Feature",
  "properties": {
    "iso:country":"US",
    "sg:address":"5711 Pebble Springs Dr",
    "sg:city":"Houston",
    "sg:classifiers":[
        {
            "category":"Social Services",
            "subcategory":"Child Care",
            "type":"Services"
        }
    ],
    "sg:phone":"+1 281 583 7801",
    "sg:postcode":"77066",
    "sg:province":"TX",
    "sg:tags":[
        "day"
    ],
    "wof:name":"Thrifty Tots",
    "wof:placetype":"venue"
},
  "geometry": {"coordinates":[-95.509913,29.975302],"type":"Point"}
}