{
  "type": "Feature",
  "properties": {
    "iso:country":"US",
    "sg:address":"1606 Corral Dr",
    "sg:city":"Houston",
    "sg:classifiers":[
        {
            "category":"Building & Trades",
            "subcategory":"Cleaning & Sanitation",
            "type":"Services"
        }
    ],
    "sg:phone":"+1 281 587 1811",
    "sg:postcode":"77090",
    "sg:province":"TX",
    "sg:tags":[
        "maintenance"
    ],
    "wof:name":"Lupe Janitorial Services",
    "wof:placetype":"venue"
},
  "geometry": {"coordinates":[-95.459272,30.020843],"type":"Point"}
}