{
  "type": "Feature",
  "properties": {
    "iso:country":"US",
    "sg:address":"1605 Shady Ln",
    "sg:city":"Decatur",
    "sg:classifiers":[
        {
            "category":"Manufacturing",
            "subcategory":"Printing",
            "type":"Manufacturing & Wholesale Goods"
        }
    ],
    "sg:phone":"+1 940 626 4888",
    "sg:postcode":"76234",
    "sg:province":"TX",
    "sg:tags":[
        "commercial"
    ],
    "wof:name":"PBM Graphics",
    "wof:placetype":"venue"
},
  "geometry": {"coordinates":[-97.600388,33.245474],"type":"Point"}
}