{
  "type": "Feature",
  "properties": {
    "iso:country":"US",
    "sg:address":"3113 Stonehenge Dr",
    "sg:city":"Richardson",
    "sg:classifiers":[
        {
            "category":"Professional",
            "subcategory":"Management & Consulting",
            "type":"Services"
        }
    ],
    "sg:phone":"+1 214 505 9279",
    "sg:postcode":"75082",
    "sg:province":"TX",
    "sg:tags":[
        "consultant"
    ],
    "wof:name":"Moose Ridge Consulting",
    "wof:placetype":"venue"
},
  "geometry": {"coordinates":[-96.62,32.991592],"type":"Point"}
}