{
  "type": "Feature",
  "properties": {
    "iso:country":"US",
    "sg:address":"701 S Gaston St",
    "sg:city":"Crane",
    "sg:classifiers":[
        {
            "category":"Organizations",
            "subcategory":"Religious Organization",
            "type":"Services"
        }
    ],
    "sg:phone":"+1 432 558 2216",
    "sg:postcode":"79731",
    "sg:province":"TX",
    "sg:tags":[
        "church"
    ],
    "wof:name":"United Pentecostal Church",
    "wof:placetype":"venue"
},
  "geometry": {"coordinates":[-102.350008,31.39668],"type":"Point"}
}