{
  "type": "Feature",
  "properties": {
    "iso:country":"US",
    "sg:address":"2404 S Milmo Ave",
    "sg:city":"Laredo",
    "sg:classifiers":[
        {
            "category":"Autos & Motor Vehicles",
            "subcategory":"Auto Supplies",
            "type":"Retail Goods"
        }
    ],
    "sg:phone":"+1 956 722 7497",
    "sg:postcode":"78046",
    "sg:province":"TX",
    "wof:name":"Carmonas Junk Yard",
    "wof:placetype":"venue"
},
  "geometry": {"coordinates":[-99.470568,27.474967],"type":"Point"}
}