{
  "type": "Feature",
  "properties": {
    "iso:country":"US",
    "sg:address":"608 Rawhide Ct",
    "sg:city":"Plano",
    "sg:classifiers":[
        {
            "category":"Wholesale",
            "subcategory":"Metals & Minerals",
            "type":"Manufacturing & Wholesale Goods"
        }
    ],
    "sg:phone":"+1 972 509 9175",
    "sg:postcode":"75023",
    "sg:province":"TX",
    "sg:tags":[
        "steel",
        "erectors",
        "center"
    ],
    "wof:name":"Dm Moore Inc",
    "wof:placetype":"venue"
},
  "geometry": {"coordinates":[-96.701641,33.051909],"type":"Point"}
}