{
  "type": "Feature",
  "properties": {
    "iso:country":"US",
    "sg:address":"110 Brierwood St",
    "sg:city":"Borger",
    "sg:classifiers":[
        {
            "category":"Professional",
            "subcategory":"Lawyer & Legal Services",
            "type":"Services"
        }
    ],
    "sg:phone":"+1 806 274 4895",
    "sg:postcode":"79007",
    "sg:province":"TX",
    "wof:name":"J Wooldridge Atty Lw",
    "wof:placetype":"venue"
},
  "geometry": {"coordinates":[-101.44494899999999,35.648066],"type":"Point"}
}