{
  "type": "Feature",
  "properties": {
    "iso:country":"US",
    "sg:address":"333 N Sam Houston Pkwy E",
    "sg:city":"Houston",
    "sg:classifiers":[
        {
            "category":"Professional",
            "subcategory":"Business Services",
            "type":"Services"
        },
        {
            "category":"Marine",
            "type":"Transportation"
        }
    ],
    "sg:phone":"+1 281 582 9200",
    "sg:postcode":"77060",
    "sg:province":"TX",
    "sg:tags":[
        "agency",
        "shipping",
        "steamship"
    ],
    "wof:name":"Moran-Gulf Shipping Agencies",
    "wof:placetype":"venue"
},
  "geometry": {"coordinates":[-95.39979200000001,29.940285],"type":"Point"}
}