{
  "type": "Feature",
  "properties": {
    "iso:country":"US",
    "sg:address":"1104 Hunt Cutoff",
    "sg:city":"Hallsville",
    "sg:classifiers":[
        {
            "category":"Real Estate",
            "subcategory":"Real Estate Operator",
            "type":"Services"
        }
    ],
    "sg:phone":"+1 903 668 2023",
    "sg:postcode":"75650",
    "sg:province":"TX",
    "sg:tags":[
        "property",
        "lessor"
    ],
    "wof:name":"Mhr Inc",
    "wof:placetype":"venue"
},
  "geometry": {"coordinates":[-94.607894,32.581678],"type":"Point"}
}