{
  "type": "Feature",
  "properties": {
    "iso:country":"US",
    "sg:address":"1624 S Chadbourne St",
    "sg:city":"San Angelo",
    "sg:classifiers":[
        {
            "category":"Personal",
            "subcategory":"Tattoo Parlor",
            "type":"Services"
        }
    ],
    "sg:phone":"+1 325 659 4658",
    "sg:postcode":"76903",
    "sg:province":"TX",
    "sg:tags":[
        "tattooing"
    ],
    "wof:name":"Lucky 13 Tattoos",
    "wof:placetype":"venue"
},
  "geometry": {"coordinates":[-100.43456999999999,31.444063],"type":"Point"}
}