{
  "type": "Feature",
  "properties": {
    "iso:country":"US",
    "sg:address":"3500 E Illinois Ave",
    "sg:city":"Dallas",
    "sg:classifiers":[
        {
            "category":"Food & Beverages",
            "subcategory":"Groceries & Convenience Stores",
            "type":"Retail Goods"
        }
    ],
    "sg:phone":"+1 214 374 9998",
    "sg:postcode":"75216",
    "sg:province":"TX",
    "wof:name":"Hatley Brothers Mini Mart",
    "wof:placetype":"venue"
},
  "geometry": {"coordinates":[-96.762339,32.714363],"type":"Point"}
}