{
  "type": "Feature",
  "properties": {
    "iso:country":"US",
    "sg:address":"3814 Nasa Road 1",
    "sg:city":"Seabrook",
    "sg:classifiers":[
        {
            "category":"Professional",
            "subcategory":"Lawyer & Legal Services",
            "type":"Services"
        }
    ],
    "sg:phone":"+1 281 326 5800",
    "sg:postcode":"77586",
    "sg:province":"TX",
    "sg:tags":[
        "attorney"
    ],
    "wof:name":"Price Blalock",
    "wof:placetype":"venue"
},
  "geometry": {"coordinates":[-95.048022,29.564115],"type":"Point"}
}