{
  "type": "Feature",
  "properties": {
    "iso:country":"US",
    "sg:address":"3816 E Interstate 20 Svc Rd",
    "sg:city":"Weatherford",
    "sg:classifiers":[
        {
            "category":"Airport",
            "type":"Transportation"
        }
    ],
    "sg:phone":"+1 817 599 7772",
    "sg:postcode":"76087",
    "sg:province":"TX",
    "wof:name":"Parker County Airport",
    "wof:placetype":"venue"
},
  "geometry": {"coordinates":[-97.634092,32.734296],"type":"Point"}
}