{
  "type": "Feature",
  "properties": {
    "iso:country":"US",
    "sg:address":"4838 Casa Espana St",
    "sg:city":"San Antonio",
    "sg:classifiers":[
        {
            "category":"Professional",
            "subcategory":"Computer Services",
            "type":"Services"
        }
    ],
    "sg:phone":"+1 210 656 8148",
    "sg:postcode":"78233",
    "sg:province":"TX",
    "sg:tags":[
        "datum"
    ],
    "wof:name":"MCM Dela Torre Enterprises",
    "wof:placetype":"venue"
},
  "geometry": {"coordinates":[-98.394578,29.546597],"type":"Point"}
}