{
  "type": "Feature",
  "properties": {
    "iso:country":"US",
    "sg:address":"1228 E 8th St",
    "sg:city":"Odessa",
    "sg:classifiers":[
        {
            "category":"Building & Trades",
            "subcategory":"Equipment Rental",
            "type":"Services"
        }
    ],
    "sg:phone":"+1 432 582 2205",
    "sg:postcode":"79761",
    "sg:province":"TX",
    "sg:tags":[
        "yard",
        "appliance",
        "furniture"
    ],
    "wof:name":"Express Rentals",
    "wof:placetype":"venue"
},
  "geometry": {"coordinates":[-102.35961399999999,31.857051],"type":"Point"}
}