{
  "type": "Feature",
  "properties": {
    "iso:country":"US",
    "sg:address":"3615 Lost Oak Dr",
    "sg:city":"Spring",
    "sg:classifiers":[
        {
            "category":"Professional",
            "type":"Services"
        }
    ],
    "sg:phone":"+1 281 353 0477",
    "sg:postcode":"77388",
    "sg:province":"TX",
    "wof:name":"Pretty Silver & More",
    "wof:placetype":"venue"
},
  "geometry": {"coordinates":[-95.473118,30.043609],"type":"Point"}
}