{
  "type": "Feature",
  "properties": {
    "iso:country":"US",
    "sg:address":"403 Lago Verde Rd",
    "sg:city":"Austin",
    "sg:classifiers":[
        {
            "category":"Structure",
            "subcategory":"Office Building",
            "type":"Public Place"
        }
    ],
    "sg:phone":"+1 512 263 1192",
    "sg:postcode":"78734",
    "sg:province":"TX",
    "sg:tags":[
        "park"
    ],
    "wof:name":"Ryan Properties",
    "wof:placetype":"venue"
},
  "geometry": {"coordinates":[-97.919545,30.353334],"type":"Point"}
}