{
  "type": "Feature",
  "properties": {
    "iso:country":"US",
    "sg:address":"5001 Franklin Ave",
    "sg:city":"Waco",
    "sg:classifiers":[
        {
            "category":"Recreation",
            "subcategory":"Arcade",
            "type":"Entertainment"
        }
    ],
    "sg:phone":"+1 254 751 9404",
    "sg:postcode":"76710",
    "sg:province":"TX",
    "sg:tags":[
        "casino"
    ],
    "wof:name":"Reel Vegas Slots Incs",
    "wof:placetype":"venue"
},
  "geometry": {"coordinates":[-97.17698799999999,31.518746],"type":"Point"}
}