{
  "type": "Feature",
  "properties": {
    "iso:country":"US",
    "sg:address":"8 Saddle Creek",
    "sg:city":"Houston",
    "sg:classifiers":[
        {
            "category":"Utilities",
            "type":"Services"
        }
    ],
    "sg:phone":"+1 281 847 0029",
    "sg:postcode":"77024",
    "sg:province":"TX",
    "sg:tags":[
        "company",
        "holding"
    ],
    "wof:name":"Avalanche Resources Ltd",
    "wof:placetype":"venue"
},
  "geometry": {"coordinates":[-95.499584,29.767324],"type":"Point"}
}