{
  "type": "Feature",
  "properties": {
    "iso:country":"US",
    "sg:address":"3800 State Hwy 6 S",
    "sg:city":"College Station",
    "sg:classifiers":[
        {
            "category":"Professional",
            "subcategory":"Research",
            "type":"Services"
        },
        {
            "category":"Professional",
            "subcategory":"Management & Consulting",
            "type":"Services"
        }
    ],
    "sg:phone":"+1 979 268 2677",
    "sg:postcode":"77845",
    "sg:province":"TX",
    "sg:tags":[
        "environmental",
        "ecological",
        "business"
    ],
    "wof:name":"Albion Environmental",
    "wof:placetype":"venue"
},
  "geometry": {"coordinates":[-96.28635199999999,30.585241],"type":"Point"}
}