{
  "type": "Feature",
  "properties": {
    "iso:country":"US",
    "sg:address":"3610 Lohman Ford Rd",
    "sg:city":"Leander",
    "sg:classifiers":[
        {
            "category":"Wholesale",
            "subcategory":"Drugs",
            "type":"Manufacturing & Wholesale Goods"
        }
    ],
    "sg:phone":"+1 512 267 8800",
    "sg:postcode":"78645",
    "sg:province":"TX",
    "sg:tags":[
        "equipment",
        "veterinary",
        "supply"
    ],
    "wof:name":"TW Medical Vet Supply",
    "wof:placetype":"venue"
},
  "geometry": {"coordinates":[-97.974424,30.421278],"type":"Point"}
}