{
  "type": "Feature",
  "properties": {
    "iso:country":"US",
    "sg:address":"514 Brookford Dr",
    "sg:city":"Missouri City",
    "sg:classifiers":[
        {
            "category":"Professional",
            "subcategory":"Business Services",
            "type":"Services"
        }
    ],
    "sg:phone":"+1 281 438 3328",
    "sg:postcode":"77489",
    "sg:province":"TX",
    "wof:name":"A Crittentech Enterprises",
    "wof:placetype":"venue"
},
  "geometry": {"coordinates":[-95.509461,29.59666],"type":"Point"}
}