{
  "type": "Feature",
  "properties": {
    "iso:country":"US",
    "sg:address":"6341 Tillie Ln",
    "sg:city":"Sanger",
    "sg:classifiers":[
        {
            "category":"Shopping",
            "subcategory":"Clothing, Apparel, & Fashions",
            "type":"Retail Goods"
        }
    ],
    "sg:phone":"+1 940 458 4879",
    "sg:postcode":"76266",
    "sg:province":"TX",
    "sg:tags":[
        "garment"
    ],
    "wof:name":"Designs Etc",
    "wof:placetype":"venue"
},
  "geometry": {"coordinates":[-97.158941,33.303809],"type":"Point"}
}