{
  "type": "Feature",
  "properties": {
    "iso:country":"US",
    "sg:address":"5219 de Zavala Rd",
    "sg:city":"San Antonio",
    "sg:classifiers":[
        {
            "category":"Home & Garden",
            "subcategory":"Furniture",
            "type":"Retail Goods"
        }
    ],
    "sg:phone":"+1 210 690 1338",
    "sg:postcode":"78249",
    "sg:province":"TX",
    "wof:name":"Chair King",
    "wof:placetype":"venue"
},
  "geometry": {"coordinates":[-98.586332,29.56482],"type":"Point"}
}