{
  "type": "Feature",
  "properties": {
    "iso:country":"US",
    "sg:address":"801 E Ave A",
    "sg:city":"Hooks",
    "sg:classifiers":[
        {
            "category":"Retail",
            "subcategory":"Auto Repair",
            "type":"Services"
        }
    ],
    "sg:phone":"+1 903 547 6608",
    "sg:postcode":"75561",
    "sg:province":"TX",
    "sg:tags":[
        "wrecker"
    ],
    "wof:name":"LE May's Towing Svc",
    "wof:placetype":"venue"
},
  "geometry": {"coordinates":[-94.279426,33.466738],"type":"Point"}
}