{
  "type": "Feature",
  "properties": {
    "iso:country":"US",
    "sg:address":"3014 Ave E E",
    "sg:city":"Arlington",
    "sg:classifiers":[
        {
            "category":"Wholesale",
            "subcategory":"Machinery & Supplies",
            "type":"Manufacturing & Wholesale Goods"
        }
    ],
    "sg:phone":"+1 817 649 5381",
    "sg:postcode":"76011",
    "sg:province":"TX",
    "sg:tags":[
        "tool",
        "industrial"
    ],
    "wof:name":"National Tool & Manufacturing",
    "wof:placetype":"venue"
},
  "geometry": {"coordinates":[-97.052922,32.756381],"type":"Point"}
}