{
  "type": "Feature",
  "properties": {
    "iso:country":"US",
    "sg:address":"2350 Patterson Industrial Dr",
    "sg:city":"Pflugerville",
    "sg:classifiers":[
        {
            "category":"Wholesale",
            "subcategory":"Construction Materials",
            "type":"Manufacturing & Wholesale Goods"
        }
    ],
    "sg:phone":"+1 512 670 2774",
    "sg:postcode":"78660",
    "sg:province":"TX",
    "wof:name":"Calply",
    "wof:placetype":"venue"
},
  "geometry": {"coordinates":[-97.62818300000001,30.403132],"type":"Point"}
}