{
  "type": "Feature",
  "properties": {
    "iso:country":"US",
    "sg:address":"801 S Greenville Ave",
    "sg:city":"Allen",
    "sg:classifiers":[
        {
            "category":"Personal",
            "subcategory":"Beauty Salon",
            "type":"Services"
        }
    ],
    "sg:phone":"+1 972 390 8828",
    "sg:postcode":"75002",
    "sg:province":"TX",
    "sg:tags":[
        "manicuring"
    ],
    "wof:name":"Elegant Nails",
    "wof:placetype":"venue"
},
  "geometry": {"coordinates":[-96.67111800000001,33.087497],"type":"Point"}
}