{
  "type": "Feature",
  "properties": {
    "iso:country":"US",
    "sg:address":"702 Ironwood Dr",
    "sg:city":"Richmond",
    "sg:classifiers":[
        {
            "category":"Real Estate",
            "subcategory":"Real Estate Services",
            "type":"Services"
        },
        {
            "category":"Real Estate",
            "subcategory":"Real Estate Agent",
            "type":"Services"
        }
    ],
    "sg:phone":"+1 281 341 8272",
    "sg:postcode":"77406",
    "sg:province":"TX",
    "sg:tags":[
        "management"
    ],
    "wof:name":"Invertran Corp",
    "wof:placetype":"venue"
},
  "geometry": {"coordinates":[-95.739223,29.618431],"type":"Point"}
}