{
  "type": "Feature",
  "properties": {
    "iso:country":"US",
    "sg:address":"12312 Willow Bend Dr",
    "sg:city":"Austin",
    "sg:classifiers":[
        {
            "category":"Communications",
            "type":"Services"
        }
    ],
    "sg:phone":"+1 512 447 8886",
    "sg:postcode":"78758",
    "sg:province":"TX",
    "sg:tags":[
        "equipment",
        "telephone",
        "systems-repair"
    ],
    "wof:name":"Perfect Phones Inc",
    "wof:placetype":"venue"
},
  "geometry": {"coordinates":[-97.68061400000001,30.404303],"type":"Point"}
}