{
  "type": "Feature",
  "properties": {
    "iso:country":"US",
    "sg:address":"3713 Tularosa Ave",
    "sg:city":"El Paso",
    "sg:classifiers":[
        {
            "category":"Building & Trades",
            "subcategory":"Pest Control",
            "type":"Services"
        }
    ],
    "sg:phone":"+1 915 564 5997",
    "sg:postcode":"79903",
    "sg:province":"TX",
    "wof:name":"J B Exterminating Svc",
    "wof:placetype":"venue"
},
  "geometry": {"coordinates":[-106.44822000000001,31.782728],"type":"Point"}
}