{
  "type": "Feature",
  "properties": {
    "iso:country":"US",
    "sg:address":"2709 College Park Dr",
    "sg:city":"Rowlett",
    "sg:classifiers":[
        {
            "category":"Freight",
            "type":"Transportation"
        }
    ],
    "sg:phone":"+1 972 463 4373",
    "sg:postcode":"75088",
    "sg:province":"TX",
    "sg:tags":[
        "courier"
    ],
    "wof:name":"Red Courier",
    "wof:placetype":"venue"
},
  "geometry": {"coordinates":[-96.532515,32.886768],"type":"Point"}
}