{
  "type": "Feature",
  "properties": {
    "iso:country":"US",
    "sg:address":"3112 Windsor Road",
    "sg:city":"Austin",
    "sg:classifiers":[
        {
            "category":"Professional",
            "type":"Services"
        },
        {
            "category":"Professional",
            "subcategory":"Lawyer & Legal Services",
            "type":"Services"
        },
        {
            "category":"Professional",
            "subcategory":"Business Services",
            "type":"Services"
        },
        {
            "category":"Government",
            "subcategory":"Post Office",
            "type":"Public Place"
        },
        {
            "category":"Retail",
            "subcategory":"Pet Boarding",
            "type":"Services"
        }
    ],
    "sg:phone":"+1 512 478 7600",
    "sg:postcode":"78703",
    "sg:province":"TX",
    "sg:tags":[
        "crating",
        "mailbox-rental",
        "shipping",
        "packaging",
        "packing",
        "mail",
        "notary",
        "receiving"
    ],
    "sg:website":"http://www.pakmail.com",
    "wof:name":"Pak Mail",
    "wof:placetype":"venue"
},
  "geometry": {"coordinates":[-97.767937,30.296639],"type":"Point"}
}