{
  "type": "Feature",
  "properties": {
    "iso:country":"US",
    "sg:address":"1947 N New Braunfels Ave",
    "sg:city":"San Antonio",
    "sg:classifiers":[
        {
            "category":"Personal",
            "subcategory":"Beauty Salon",
            "type":"Services"
        }
    ],
    "sg:phone":"+1 210 222 1781",
    "sg:postcode":"78208",
    "sg:province":"TX",
    "sg:tags":[
        "shop",
        "cosmetic"
    ],
    "wof:name":"Hair Authority",
    "wof:placetype":"venue"
},
  "geometry": {"coordinates":[-98.46101,29.44293],"type":"Point"}
}