{
  "type": "Feature",
  "properties": {
    "iso:country":"US",
    "sg:address":"6260 Velasco Ave",
    "sg:city":"Dallas",
    "sg:classifiers":[
        {
            "category":"Professional",
            "subcategory":"Art Services",
            "type":"Services"
        }
    ],
    "sg:phone":"+1 214 824 8461",
    "sg:postcode":"75214",
    "sg:province":"TX",
    "sg:tags":[
        "photographer"
    ],
    "wof:name":"Jerry Foster & Co",
    "wof:placetype":"venue"
},
  "geometry": {"coordinates":[-96.757383,32.820973],"type":"Point"}
}