{
  "type": "Feature",
  "properties": {
    "iso:country":"US",
    "sg:address":"7406 Troulon Dr",
    "sg:city":"Houston",
    "sg:classifiers":[
        {
            "category":"Wholesale",
            "subcategory":"Vending Machines",
            "type":"Manufacturing & Wholesale Goods"
        }
    ],
    "sg:phone":"+1 713 680 1611",
    "sg:postcode":"77074",
    "sg:province":"TX",
    "sg:tags":[
        "operator"
    ],
    "wof:name":"Blueboy Vending",
    "wof:placetype":"venue"
},
  "geometry": {"coordinates":[-95.515894,29.690235],"type":"Point"}
}