{
  "type": "Feature",
  "properties": {
    "iso:country":"US",
    "sg:address":"9700 Big View Dr",
    "sg:city":"Austin",
    "sg:classifiers":[
        {
            "category":"Professional",
            "type":"Services"
        }
    ],
    "sg:phone":"+1 512 241 0955",
    "sg:postcode":"78730",
    "sg:province":"TX",
    "wof:name":"Factiva Dow Jones & Reuters",
    "wof:placetype":"venue"
},
  "geometry": {"coordinates":[-97.85175700000001,30.362669],"type":"Point"}
}