{
  "type": "Feature",
  "properties": {
    "iso:country":"US",
    "sg:address":"3419 N Main St",
    "sg:city":"Fort Worth",
    "sg:classifiers":[
        {
            "category":"Food & Beverages",
            "subcategory":"Groceries & Convenience Stores",
            "type":"Retail Goods"
        }
    ],
    "sg:phone":"+1 817 626 5803",
    "sg:postcode":"76106",
    "sg:province":"TX",
    "sg:tags":[
        "carwash",
        "station",
        "gasoline"
    ],
    "wof:name":"Libbys Food Store",
    "wof:placetype":"venue"
},
  "geometry": {"coordinates":[-97.351544,32.808191],"type":"Point"}
}