{
  "type": "Feature",
  "properties": {
    "iso:country":"US",
    "sg:address":"2202 Edgemere Dr",
    "sg:city":"Plainview",
    "sg:classifiers":[
        {
            "category":"Health Services",
            "subcategory":"Doctor",
            "type":"Services"
        }
    ],
    "sg:phone":"+1 806 293 1555",
    "sg:postcode":"79072",
    "sg:province":"TX",
    "sg:tags":[
        "physician",
        "surgeon"
    ],
    "wof:name":"Children's Rural Health Clinic",
    "wof:placetype":"venue"
},
  "geometry": {"coordinates":[-101.736492,34.204728],"type":"Point"}
}