{
  "type": "Feature",
  "properties": {
    "iso:country":"US",
    "sg:address":"2156 Sandy Ln",
    "sg:city":"Dallas",
    "sg:classifiers":[
        {
            "category":"Professional",
            "subcategory":"Detective & Security Services",
            "type":"Services"
        }
    ],
    "sg:phone":"+1 214 574 7800",
    "sg:postcode":"75220",
    "sg:province":"TX",
    "sg:tags":[
        "sell",
        "installs",
        "access",
        "closed"
    ],
    "wof:name":"Secure Options",
    "wof:placetype":"venue"
},
  "geometry": {"coordinates":[-96.90425999999999,32.86045],"type":"Point"}
}