{
  "type": "Feature",
  "properties": {
    "iso:country":"US",
    "sg:address":"1809 W Loop 281",
    "sg:city":"Longview",
    "sg:classifiers":[
        {
            "category":"Retail",
            "subcategory":"Laundry & Dry Cleaning",
            "type":"Services"
        }
    ],
    "sg:phone":"+1 903 297 7817",
    "sg:postcode":"75604",
    "sg:province":"TX",
    "sg:tags":[
        "cleaners"
    ],
    "wof:name":"Executive Cleaners & Laundry",
    "wof:placetype":"venue"
},
  "geometry": {"coordinates":[-94.79009600000001,32.517686],"type":"Point"}
}