{
  "type": "Feature",
  "properties": {
    "iso:country":"US",
    "sg:address":"1516 S Interstate 45 Svc Rd",
    "sg:city":"Lancaster",
    "sg:classifiers":[
        {
            "category":"Retail",
            "subcategory":"Auto Repair",
            "type":"Services"
        }
    ],
    "sg:phone":"+1 972 223 3103",
    "sg:postcode":"75141",
    "sg:province":"TX",
    "sg:tags":[
        "repairing",
        "automobile",
        "general"
    ],
    "wof:name":"A & K Automotive",
    "wof:placetype":"venue"
},
  "geometry": {"coordinates":[-96.695807,32.626442],"type":"Point"}
}