{
  "type": "Feature",
  "properties": {
    "iso:country":"US",
    "sg:address":"1301 S Dairy Ashford St",
    "sg:city":"Houston",
    "sg:classifiers":[
        {
            "category":"Real Estate",
            "subcategory":"Developer",
            "type":"Services"
        }
    ],
    "sg:phone":"+1 713 781 2886",
    "sg:postcode":"77077",
    "sg:province":"TX",
    "wof:name":"M & T Development Inc",
    "wof:placetype":"venue"
},
  "geometry": {"coordinates":[-95.606161,29.756967],"type":"Point"}
}