{
  "type": "Feature",
  "properties": {
    "iso:country":"US",
    "sg:address":"2520 Delaney Ter",
    "sg:city":"Flower Mound",
    "sg:classifiers":[
        {
            "category":"Professional",
            "subcategory":"Lawyer & Legal Services",
            "type":"Services"
        }
    ],
    "sg:phone":"+1 972 724 2286",
    "sg:postcode":"75028",
    "sg:province":"TX",
    "wof:name":"Law Offices of Ronald D Wren",
    "wof:placetype":"venue"
},
  "geometry": {"coordinates":[-97.066368,33.029066],"type":"Point"}
}