{
  "type": "Feature",
  "properties": {
    "iso:country":"US",
    "sg:address":"1102 Phyllis St",
    "sg:city":"Deer Park",
    "sg:classifiers":[
        {
            "category":"Shopping",
            "subcategory":"Bicycles & Sporting Goods",
            "type":"Retail Goods"
        }
    ],
    "sg:phone":"+1 281 479 2111",
    "sg:postcode":"77536",
    "sg:province":"TX",
    "wof:name":"Captains Gun Room",
    "wof:placetype":"venue"
},
  "geometry": {"coordinates":[-95.11174099999999,29.696372],"type":"Point"}
}