{
  "type": "Feature",
  "properties": {
    "iso:country":"US",
    "sg:address":"2501 Nogalitos St",
    "sg:city":"San Antonio",
    "sg:classifiers":[
        {
            "category":"Shopping",
            "subcategory":"Used Merchandise",
            "type":"Retail Goods"
        }
    ],
    "sg:phone":"+1 210 977 8531",
    "sg:postcode":"78204",
    "sg:province":"TX",
    "sg:tags":[
        "furniture"
    ],
    "wof:name":"Sharron Used Furniture",
    "wof:placetype":"venue"
},
  "geometry": {"coordinates":[-98.520962,29.389833],"type":"Point"}
}