{
  "type": "Feature",
  "properties": {
    "iso:country":"US",
    "sg:address":"107 San Saba Ave",
    "sg:city":"Eldorado",
    "sg:classifiers":[
        {
            "category":"Shopping",
            "subcategory":"Clothing, Apparel, & Fashions",
            "type":"Retail Goods"
        }
    ],
    "sg:phone":"+1 325 853 1013",
    "sg:postcode":"76936",
    "sg:province":"TX",
    "wof:name":"K T P's Clothing & Gifts",
    "wof:placetype":"venue"
},
  "geometry": {"coordinates":[-100.587369,30.869653],"type":"Point"}
}