{
  "type": "Feature",
  "properties": {
    "iso:country":"US",
    "sg:address":"9139 Olathe St",
    "sg:city":"Houston",
    "sg:classifiers":[
        {
            "category":"Professional",
            "subcategory":"Management & Consulting",
            "type":"Services"
        }
    ],
    "sg:phone":"+1 713 984 2317",
    "sg:postcode":"77055",
    "sg:province":"TX",
    "sg:tags":[
        "public",
        "relations"
    ],
    "wof:name":"Vincent Communications",
    "wof:placetype":"venue"
},
  "geometry": {"coordinates":[-95.518624,29.796799],"type":"Point"}
}