{
  "type": "Feature",
  "properties": {
    "iso:country":"US",
    "sg:address":"20710 Moss Agate Ct",
    "sg:city":"Spring",
    "sg:classifiers":[
        {
            "category":"Building & Trades",
            "subcategory":"Cleaning & Sanitation",
            "type":"Services"
        }
    ],
    "sg:phone":"+1 281 350 8677",
    "sg:postcode":"77388",
    "sg:province":"TX",
    "sg:tags":[
        "janitor"
    ],
    "wof:name":"Clean Cut Cleaning Svc",
    "wof:placetype":"venue"
},
  "geometry": {"coordinates":[-95.493762,30.06863],"type":"Point"}
}