{
  "type": "Feature",
  "properties": {
    "iso:country":"US",
    "sg:address":"12507 Scissortail Dr",
    "sg:city":"Manchaca",
    "sg:classifiers":[
        {
            "category":"Banks & Credit Unions",
            "subcategory":"Investment Brokerage",
            "type":"Services"
        }
    ],
    "sg:phone":"+1 512 292 9299",
    "sg:postcode":"78652",
    "sg:province":"TX",
    "sg:tags":[
        "security"
    ],
    "wof:name":"Brookstreet Securities",
    "wof:placetype":"venue"
},
  "geometry": {"coordinates":[-97.83039100000001,30.133289],"type":"Point"}
}