{
  "type": "Feature",
  "properties": {
    "iso:country":"US",
    "sg:address":"2800 Hirschfield Rd",
    "sg:city":"Spring",
    "sg:classifiers":[
        {
            "category":"Real Estate",
            "subcategory":"Real Estate Operator",
            "type":"Services"
        }
    ],
    "sg:phone":"+1 281 350 0254",
    "sg:postcode":"77373",
    "sg:province":"TX",
    "sg:tags":[
        "building",
        "apartment"
    ],
    "wof:name":"One Wstfeld Lk Aprtments Homes",
    "wof:placetype":"venue"
},
  "geometry": {"coordinates":[-95.385381,30.041756],"type":"Point"}
}