{
  "type": "Feature",
  "properties": {
    "iso:country":"US",
    "sg:address":"4103 Swiss Ave",
    "sg:city":"Dallas",
    "sg:classifiers":[
        {
            "category":"Health Services",
            "subcategory":"Hospital",
            "type":"Services"
        }
    ],
    "sg:phone":"+1 214 821 2001",
    "sg:postcode":"75204",
    "sg:province":"TX",
    "wof:name":"Swiss Avenue Surgicenter",
    "wof:placetype":"venue"
},
  "geometry": {"coordinates":[-96.77815099999999,32.795084],"type":"Point"}
}