{
  "type": "Feature",
  "properties": {
    "iso:country":"US",
    "sg:address":"4406 20th St",
    "sg:city":"Lubbock",
    "sg:classifiers":[
        {
            "category":"Real Estate",
            "subcategory":"Real Estate Operator",
            "type":"Services"
        }
    ],
    "sg:phone":"+1 806 792 1066",
    "sg:postcode":"79407",
    "sg:province":"TX",
    "sg:tags":[
        "building",
        "apartment"
    ],
    "wof:name":"Housing Authority The",
    "wof:placetype":"venue"
},
  "geometry": {"coordinates":[-101.907213,33.576383],"type":"Point"}
}