{
  "type": "Feature",
  "properties": {
    "iso:country":"US",
    "sg:address":"1651 Witte Rd",
    "sg:city":"Houston",
    "sg:classifiers":[
        {
            "category":"Building & Trades",
            "subcategory":"Landscaping Services",
            "type":"Services"
        }
    ],
    "sg:phone":"+1 281 358 1767",
    "sg:postcode":"77080",
    "sg:province":"TX",
    "sg:tags":[
        "landscape"
    ],
    "wof:name":"Elvia Landscaping",
    "wof:placetype":"venue"
},
  "geometry": {"coordinates":[-95.540336,29.802157],"type":"Point"}
}