{
  "type": "Feature",
  "properties": {
    "iso:country":"US",
    "sg:address":"315 Congress Avenue Suite 100",
    "sg:city":"Austin",
    "sg:classifiers":[
        {
            "category":"Shopping",
            "type":"Retail Goods"
        }
    ],
    "sg:phone":"+1 512 527 3018",
    "sg:postcode":"78701",
    "sg:province":"TX",
    "sg:website":"www.dressshopaustin.com/",
    "wof:name":"Dress Shop",
    "wof:placetype":"venue"
},
  "geometry": {"coordinates":[-97.743689,30.265643],"type":"Point"}
}