{
  "type": "Feature",
  "properties": {
    "iso:country":"US",
    "sg:address":"6700 Lakeview Ln",
    "sg:city":"Flower Mound",
    "sg:classifiers":[
        {
            "category":"Professional",
            "subcategory":"Management & Consulting",
            "type":"Services"
        }
    ],
    "sg:phone":"+1 817 430 3552",
    "sg:postcode":"75022",
    "sg:province":"TX",
    "wof:name":"Connell Business Services",
    "wof:placetype":"venue"
},
  "geometry": {"coordinates":[-97.13749,33.015609],"type":"Point"}
}