{
  "type": "Feature",
  "properties": {
    "iso:country":"US",
    "sg:address":"525 Elm St",
    "sg:city":"Pittsburg",
    "sg:classifiers":[
        {
            "category":"Organizations",
            "subcategory":"Non-profit Organization",
            "type":"Services"
        },
        {
            "category":"Social Services",
            "type":"Services"
        }
    ],
    "sg:phone":"+1 903 856 9050",
    "sg:postcode":"75686",
    "sg:province":"TX",
    "wof:name":"Camp County Senior Citizens",
    "wof:placetype":"venue"
},
  "geometry": {"coordinates":[-94.974875,33.002729],"type":"Point"}
}