{
  "type": "Feature",
  "properties": {
    "iso:country":"US",
    "sg:address":"4810 Knotty Oaks Trl",
    "sg:city":"Houston",
    "sg:classifiers":[
        {
            "category":"Restaurant",
            "type":"Food & Drink"
        }
    ],
    "sg:phone":"+1 713 433 7405",
    "sg:postcode":"77045",
    "sg:province":"TX",
    "sg:tags":[
        "eating"
    ],
    "wof:name":"S & S Catering & Bar Be Que",
    "wof:placetype":"venue"
},
  "geometry": {"coordinates":[-95.452286,29.632816],"type":"Point"}
}