{
  "type": "Feature",
  "properties": {
    "iso:country":"US",
    "sg:address":"808 County Road 331",
    "sg:city":"Rosebud",
    "sg:classifiers":[
        {
            "category":"Manufacturing",
            "subcategory":"Food",
            "type":"Manufacturing & Wholesale Goods"
        },
        {
            "category":"Farming",
            "subcategory":"Farm",
            "type":"Manufacturing & Wholesale Goods"
        }
    ],
    "sg:phone":"+1 254 583 7209",
    "sg:postcode":"76570",
    "sg:province":"TX",
    "sg:tags":[
        "corn",
        "product"
    ],
    "wof:name":"Keith Odenbach",
    "wof:placetype":"venue"
},
  "geometry": {"coordinates":[-96.888721,31.174006],"type":"Point"}
}