{
  "type": "Feature",
  "properties": {
    "iso:country":"US",
    "sg:address":"17306 Marble Oak Ct",
    "sg:city":"Spring",
    "sg:classifiers":[
        {
            "category":"Organizations",
            "subcategory":"Labor Organization",
            "type":"Services"
        }
    ],
    "sg:phone":"+1 281 251 1443",
    "sg:postcode":"77379",
    "sg:province":"TX",
    "wof:name":"United Transportation UNI",
    "wof:placetype":"venue"
},
  "geometry": {"coordinates":[-95.51141800000001,30.04096],"type":"Point"}
}