{
  "type": "Feature",
  "properties": {
    "iso:country":"US",
    "sg:address":"4970 Western Center Blvd",
    "sg:city":"Fort Worth",
    "sg:classifiers":[
        {
            "category":"Retail",
            "subcategory":"Car Wash",
            "type":"Services"
        }
    ],
    "sg:phone":"+1 817 605 1423",
    "sg:postcode":"76137",
    "sg:province":"TX",
    "sg:tags":[
        "carwash",
        "polishing",
        "washing"
    ],
    "wof:name":"Haltom City Super Wash",
    "wof:placetype":"venue"
},
  "geometry": {"coordinates":[-97.276955,32.860751],"type":"Point"}
}