{
  "type": "Feature",
  "properties": {
    "iso:country":"US",
    "sg:address":"3303 N 3rd St",
    "sg:city":"Abilene",
    "sg:classifiers":[
        {
            "category":"Professional",
            "type":"Services"
        }
    ],
    "sg:phone":"+1 325 437 2382",
    "sg:postcode":"79603",
    "sg:province":"TX",
    "sg:tags":[
        "establishment"
    ],
    "wof:name":"Freedom2go Corp Office",
    "wof:placetype":"venue"
},
  "geometry": {"coordinates":[-99.763391,32.452946],"type":"Point"}
}