{
  "type": "Feature",
  "properties": {
    "iso:country":"US",
    "sg:address":"6930 E 14th St",
    "sg:city":"Brownsville",
    "sg:classifiers":[
        {
            "category":"Retail",
            "subcategory":"Auto Repair",
            "type":"Services"
        }
    ],
    "sg:phone":"+1 956 838 5704",
    "sg:postcode":"78521",
    "sg:province":"TX",
    "sg:tags":[
        "body"
    ],
    "wof:name":"Lone Star Body Shop",
    "wof:placetype":"venue"
},
  "geometry": {"coordinates":[-97.433396,25.940066],"type":"Point"}
}