{
  "type": "Feature",
  "properties": {
    "iso:country":"US",
    "sg:address":"510 Spr 156",
    "sg:city":"Waskom",
    "sg:classifiers":[
        {
            "category":"Wholesale",
            "subcategory":"Machinery & Supplies",
            "type":"Manufacturing & Wholesale Goods"
        }
    ],
    "sg:phone":"+1 903 687 3822",
    "sg:postcode":"75692",
    "sg:province":"TX",
    "sg:tags":[
        "field",
        "oil",
        "equipment"
    ],
    "sg:website":"www.bit-tech.com",
    "wof:name":"Bit-Tech",
    "wof:placetype":"venue"
},
  "geometry": {"coordinates":[-94.053665,32.473072],"type":"Point"}
}