{
  "type": "Feature",
  "properties": {
    "iso:country":"US",
    "sg:address":"522 State Hwy 37",
    "sg:city":"Mt Vernon",
    "sg:classifiers":[
        {
            "category":"Organizations",
            "subcategory":"Religious Organization",
            "type":"Services"
        }
    ],
    "sg:phone":"+1 903 537 3616",
    "sg:postcode":"75457",
    "sg:province":"TX",
    "sg:tags":[
        "church"
    ],
    "wof:name":"First United Methodist Church",
    "wof:placetype":"venue"
},
  "geometry": {"coordinates":[-95.228115,33.188905],"type":"Point"}
}