{
  "type": "Feature",
  "properties": {
    "iso:country":"US",
    "sg:address":"11800 Braesview",
    "sg:city":"San Antonio",
    "sg:classifiers":[
        {
            "category":"Real Estate",
            "subcategory":"Real Estate Operator",
            "type":"Services"
        }
    ],
    "sg:phone":"+1 210 340 5897",
    "sg:postcode":"78213",
    "sg:province":"TX",
    "sg:tags":[
        "apartment"
    ],
    "sg:website":"www.eqr.com",
    "wof:name":"Lincoln Green Apartments",
    "wof:placetype":"venue"
},
  "geometry": {"coordinates":[-98.529444,29.544977],"type":"Point"}
}