{
  "type": "Feature",
  "properties": {
    "iso:country":"US",
    "sg:address":"2201 Montopolis Dr",
    "sg:city":"Austin",
    "sg:classifiers":[
        {
            "category":"Utilities",
            "subcategory":"Mobile Phone",
            "type":"Services"
        }
    ],
    "sg:phone":"+1 512 389 1049",
    "sg:postcode":"78741",
    "sg:province":"TX",
    "sg:tags":[
        "telephone",
        "cellular"
    ],
    "wof:name":"Ez Wireless",
    "wof:placetype":"venue"
},
  "geometry": {"coordinates":[-97.704866,30.222737],"type":"Point"}
}