{
  "type": "Feature",
  "properties": {
    "iso:country":"US",
    "sg:address":"2432 Preston Rd",
    "sg:city":"Plano",
    "sg:classifiers":[
        {
            "category":"Recreation",
            "type":"Entertainment"
        }
    ],
    "sg:phone":"+1 972 612 4141",
    "sg:postcode":"75093",
    "sg:province":"TX",
    "sg:tags":[
        "instruction",
        "gymnastic"
    ],
    "wof:name":"Gym Star",
    "wof:placetype":"venue"
},
  "geometry": {"coordinates":[-96.79473400000001,33.028863],"type":"Point"}
}