{
  "type": "Feature",
  "properties": {
    "iso:country":"US",
    "sg:address":"166 Tall Timber Trl",
    "sg:city":"Whitney",
    "sg:classifiers":[
        {
            "category":"Personal",
            "subcategory":"Beauty Salon",
            "type":"Services"
        }
    ],
    "sg:phone":"+1 254 694 2585",
    "sg:postcode":"76692",
    "sg:province":"TX",
    "wof:name":"In Hea Beauty Salon",
    "wof:placetype":"venue"
},
  "geometry": {"coordinates":[-97.328548,31.901993],"type":"Point"}
}