{
  "type": "Feature",
  "properties": {
    "iso:country":"US",
    "sg:address":"13718 Seagoville Rd",
    "sg:city":"Dallas",
    "sg:classifiers":[
        {
            "category":"Building & Trades",
            "subcategory":"Construction",
            "type":"Services"
        }
    ],
    "sg:phone":"+1 972 913 8005",
    "sg:postcode":"75253",
    "sg:province":"TX",
    "sg:tags":[
        "general"
    ],
    "wof:name":"H & S Construction",
    "wof:placetype":"venue"
},
  "geometry": {"coordinates":[-96.601787,32.699141],"type":"Point"}
}