{
  "type": "Feature",
  "properties": {
    "iso:country":"US",
    "sg:address":"6625 Bandera Ave",
    "sg:city":"Dallas",
    "sg:classifiers":[
        {
            "category":"Real Estate",
            "subcategory":"Real Estate Operator",
            "type":"Services"
        }
    ],
    "sg:phone":"+1 866 404 1813",
    "sg:postcode":"75225",
    "sg:province":"TX",
    "sg:tags":[
        "apartment"
    ],
    "sg:website":"http://local.ingenio.com/Listings/Details.aspx?NUM=a%3a10238093%3a13%3a4859924%3a14%3a0%3a7",
    "wof:name":"Drexel Park Hollow",
    "wof:placetype":"venue"
},
  "geometry": {"coordinates":[-96.79107500000001,32.867682],"type":"Point"}
}