{
  "type": "Feature",
  "properties": {
    "iso:country":"US",
    "sg:address":"1008 E Titus St",
    "sg:city":"Mexia",
    "sg:classifiers":[
        {
            "category":"Social Services",
            "subcategory":"Child Care",
            "type":"Services"
        }
    ],
    "sg:phone":"+1 254 562 6077",
    "sg:postcode":"76667",
    "sg:province":"TX",
    "sg:tags":[
        "day"
    ],
    "wof:name":"Candyland",
    "wof:placetype":"venue"
},
  "geometry": {"coordinates":[-96.469976,31.679294],"type":"Point"}
}