{
  "type": "Feature",
  "properties": {
    "iso:country":"US",
    "sg:address":"1927 E Belt Line Rd Ste 136",
    "sg:city":"Carrollton",
    "sg:classifiers":[
        {
            "category":"Food & Beverages",
            "subcategory":"Liquor & Beverages",
            "type":"Retail Goods"
        }
    ],
    "sg:phone":"+1 972 416 9100",
    "sg:postcode":"75006",
    "sg:province":"TX",
    "sg:tags":[
        "beer",
        "spirit",
        "wine"
    ],
    "wof:name":"Three Amigos Beer & Wine",
    "wof:placetype":"venue"
},
  "geometry": {"coordinates":[-96.887749,32.953856],"type":"Point"}
}