{
  "type": "Feature",
  "properties": {
    "iso:country":"US",
    "sg:address":"609 W Young St",
    "sg:city":"Llano",
    "sg:classifiers":[
        {
            "category":"Shopping",
            "subcategory":"Used Merchandise",
            "type":"Retail Goods"
        }
    ],
    "sg:phone":"+1 325 247 1910",
    "sg:postcode":"78643",
    "sg:province":"TX",
    "sg:tags":[
        "shop",
        "consignment"
    ],
    "wof:name":"Lil Britches",
    "wof:placetype":"venue"
},
  "geometry": {"coordinates":[-98.682666,30.759607],"type":"Point"}
}