{
  "type": "Feature",
  "properties": {
    "iso:country":"US",
    "sg:address":"2102 Stafford St",
    "sg:city":"Austin",
    "sg:classifiers":[
        {
            "category":"Building & Trades",
            "subcategory":"Landscaping Services",
            "type":"Services"
        }
    ],
    "sg:phone":"+1 512 494 8449",
    "sg:postcode":"78722",
    "sg:province":"TX",
    "wof:name":"Wilhite Naturalist",
    "wof:placetype":"venue"
},
  "geometry": {"coordinates":[-97.715321,30.283854],"type":"Point"}
}