{
  "type": "Feature",
  "properties": {
    "iso:country":"US",
    "sg:address":"177 S Watson Rd",
    "sg:city":"Arlington",
    "sg:classifiers":[
        {
            "category":"Manufacturing",
            "subcategory":"Metals",
            "type":"Manufacturing & Wholesale Goods"
        }
    ],
    "sg:phone":"+1 817 371 5443",
    "sg:postcode":"76010",
    "sg:province":"TX",
    "wof:name":"Avion-Vol",
    "wof:placetype":"venue"
},
  "geometry": {"coordinates":[-97.06174,32.737177],"type":"Point"}
}