{
  "type": "Feature",
  "properties": {
    "iso:country":"US",
    "sg:address":"11406 Oak Lake Point Dr",
    "sg:city":"Sugar Land",
    "sg:classifiers":[
        {
            "category":"Professional",
            "subcategory":"Business Services",
            "type":"Services"
        }
    ],
    "sg:phone":"+1 713 304 7253",
    "sg:postcode":"77478",
    "sg:province":"TX",
    "wof:name":"Mark Abshire",
    "wof:placetype":"venue"
},
  "geometry": {"coordinates":[-95.652596,29.649957],"type":"Point"}
}