{
  "type": "Feature",
  "properties": {
    "iso:country":"US",
    "sg:address":"2278 Trawood Dr",
    "sg:city":"El Paso",
    "sg:classifiers":[
        {
            "category":"Personal",
            "type":"Services"
        }
    ],
    "sg:phone":"+1 915 842 8000",
    "sg:postcode":"79935",
    "sg:province":"TX",
    "sg:tags":[
        "therapist",
        "massage"
    ],
    "wof:name":"Massage Works",
    "wof:placetype":"venue"
},
  "geometry": {"coordinates":[-106.319215,31.765031],"type":"Point"}
}