{
  "type": "Feature",
  "properties": {
    "iso:country":"US",
    "sg:address":"1508 Deepwoods Trl",
    "sg:city":"Leander",
    "sg:classifiers":[
        {
            "category":"Retail",
            "subcategory":"Laundry & Dry Cleaning",
            "type":"Services"
        }
    ],
    "sg:phone":"+1 512 327 7922",
    "sg:postcode":"78641",
    "sg:province":"TX",
    "sg:tags":[
        "cleaners",
        "rug",
        "carpet"
    ],
    "wof:name":"Advantage Chem-Dry",
    "wof:placetype":"venue"
},
  "geometry": {"coordinates":[-97.86144,30.549714],"type":"Point"}
}