{
  "type": "Feature",
  "properties": {
    "iso:country":"US",
    "sg:address":"105 N New Rd",
    "sg:city":"Waco",
    "sg:classifiers":[
        {
            "category":"Shopping",
            "subcategory":"Books",
            "type":"Retail Goods"
        }
    ],
    "sg:phone":"+1 254 772 3350",
    "sg:postcode":"76710",
    "sg:province":"TX",
    "sg:tags":[
        "cards",
        "music",
        "gift"
    ],
    "wof:name":"Family Christian Stores 89",
    "wof:placetype":"venue"
},
  "geometry": {"coordinates":[-97.17216999999999,31.52681],"type":"Point"}
}