{
  "type": "Feature",
  "properties": {
    "iso:country":"US",
    "sg:address":"630 W 26th St",
    "sg:city":"Houston",
    "sg:classifiers":[
        {
            "category":"Personal",
            "subcategory":"Barber",
            "type":"Services"
        }
    ],
    "sg:phone":"+1 713 864 0534",
    "sg:postcode":"77008",
    "sg:province":"TX",
    "sg:tags":[
        "shop"
    ],
    "wof:name":"Laespanola Barber Shop",
    "wof:placetype":"venue"
},
  "geometry": {"coordinates":[-95.409696,29.809827],"type":"Point"}
}