{
  "type": "Feature",
  "properties": {
    "iso:country":"US",
    "sg:address":"5545 NW Loop 410",
    "sg:city":"San Antonio",
    "sg:classifiers":[
        {
            "category":"Tea Room",
            "type":"Food & Drink"
        }
    ],
    "sg:menulink":"http://www.allmenus.com/tx/san-antonio/274443-chef-chan-tea-house/menu/",
    "sg:phone":"+1 210 509 7298",
    "sg:postcode":"78238",
    "sg:province":"TX",
    "sg:tags":[
        "asian",
        "chinese"
    ],
    "wof:name":"Chef Chan Tea House",
    "wof:placetype":"venue"
},
  "geometry": {"coordinates":[-98.595552,29.484769],"type":"Point"}
}