{
  "type": "Feature",
  "properties": {
    "iso:country":"US",
    "sg:address":"3812 US Hwy 281",
    "sg:city":"Mineral Wells",
    "sg:classifiers":[
        {
            "category":"Wholesale",
            "subcategory":"Construction Materials",
            "type":"Manufacturing & Wholesale Goods"
        }
    ],
    "sg:phone":"+1 940 325 2357",
    "sg:postcode":"76067",
    "sg:province":"TX",
    "sg:tags":[
        "brick",
        "common",
        "face"
    ],
    "wof:name":"Claude E Pewitt Brick-Fireplce",
    "wof:placetype":"venue"
},
  "geometry": {"coordinates":[-98.104775,32.748811],"type":"Point"}
}