{
  "type": "Feature",
  "properties": {
    "iso:country":"US",
    "sg:address":"99 Criminal Justice Dr",
    "sg:city":"Conroe",
    "sg:classifiers":[
        {
            "category":"Insurance",
            "subcategory":"Hazard Insurance",
            "type":"Services"
        },
        {
            "category":"Professional",
            "subcategory":"Business Services",
            "type":"Services"
        }
    ],
    "sg:phone":"+1 936 231 2841",
    "sg:postcode":"77301",
    "sg:province":"TX",
    "sg:tags":[
        "bond"
    ],
    "wof:name":"Daisy Bail Bond Inc",
    "wof:placetype":"venue"
},
  "geometry": {"coordinates":[-95.452834,30.335039],"type":"Point"}
}