{
  "type": "Feature",
  "properties": {
    "iso:country":"US",
    "sg:address":"3522 Liberty Dr",
    "sg:city":"Pearland",
    "sg:classifiers":[
        {
            "category":"Education",
            "subcategory":"Library",
            "type":"Public Place"
        }
    ],
    "sg:phone":"+1 281 485 4876",
    "sg:postcode":"77581",
    "sg:province":"TX",
    "sg:tags":[
        "executive"
    ],
    "wof:name":"Pearland Branch Library",
    "wof:placetype":"venue"
},
  "geometry": {"coordinates":[-95.255531,29.552182],"type":"Point"}
}