{
  "type": "Feature",
  "properties": {
    "iso:country":"US",
    "sg:address":"2440 South Blvd",
    "sg:city":"Houston",
    "sg:classifiers":[
        {
            "category":"Professional",
            "subcategory":"Business Services",
            "type":"Services"
        }
    ],
    "sg:phone":"+1 713 532 1119",
    "sg:postcode":"77098",
    "sg:province":"TX",
    "sg:tags":[
        "interior",
        "consultant",
        "design",
        "decorator"
    ],
    "wof:name":"Berkley Square",
    "wof:placetype":"venue"
},
  "geometry": {"coordinates":[-95.417976,29.726445],"type":"Point"}
}