{
  "type": "Feature",
  "properties": {
    "iso:country":"US",
    "sg:address":"14827 Cindywood Dr",
    "sg:city":"Houston",
    "sg:classifiers":[
        {
            "category":"Professional",
            "subcategory":"Management & Consulting",
            "type":"Services"
        }
    ],
    "sg:phone":"+1 713 988 0544",
    "sg:postcode":"77079",
    "sg:province":"TX",
    "wof:name":"Wkl Management LLC",
    "wof:placetype":"venue"
},
  "geometry": {"coordinates":[-95.616128,29.767303],"type":"Point"}
}