{
  "type": "Feature",
  "properties": {
    "iso:country":"US",
    "sg:address":"533 W Commerce St",
    "sg:city":"Brownwood",
    "sg:classifiers":[
        {
            "category":"Retail",
            "subcategory":"Laundry & Dry Cleaning",
            "type":"Services"
        },
        {
            "category":"Building & Trades",
            "subcategory":"Cleaning & Sanitation",
            "type":"Services"
        }
    ],
    "sg:phone":"+1 325 646 8312",
    "sg:postcode":"76801",
    "sg:province":"TX",
    "sg:tags":[
        "cleaner",
        "commercial",
        "house"
    ],
    "wof:name":"Comet One Hour Dry Cleaners",
    "wof:placetype":"venue"
},
  "geometry": {"coordinates":[-98.98539599999999,31.728997],"type":"Point"}
}