{
  "type": "Feature",
  "properties": {
    "iso:country":"US",
    "sg:address":"502 Garmon Dr",
    "sg:city":"Early",
    "sg:classifiers":[
        {
            "category":"Freight",
            "type":"Transportation"
        }
    ],
    "sg:phone":"+1 325 643 6136",
    "sg:postcode":"76802",
    "sg:province":"TX",
    "sg:tags":[
        "commercial",
        "storage"
    ],
    "wof:name":"Longhorn Mini Storage",
    "wof:placetype":"venue"
},
  "geometry": {"coordinates":[-98.93603299999999,31.737766],"type":"Point"}
}