{
  "type": "Feature",
  "properties": {
    "iso:country":"US",
    "sg:address":"4007 Eastshore St",
    "sg:city":"Missouri City",
    "sg:classifiers":[
        {
            "category":"Building & Trades",
            "subcategory":"Electrical",
            "type":"Services"
        }
    ],
    "sg:phone":"+1 281 499 6333",
    "sg:postcode":"77459",
    "sg:province":"TX",
    "sg:tags":[
        "electrical",
        "contractor"
    ],
    "wof:name":"McGuffin Tech Services",
    "wof:placetype":"venue"
},
  "geometry": {"coordinates":[-95.567357,29.588639],"type":"Point"}
}