{
  "type": "Feature",
  "properties": {
    "iso:country":"US",
    "sg:address":"3717 Admiral St",
    "sg:city":"El Paso",
    "sg:classifiers":[
        {
            "category":"Retail",
            "subcategory":"Auto Repair",
            "type":"Services"
        }
    ],
    "sg:phone":"+1 915 591 4648",
    "sg:postcode":"79925",
    "sg:province":"TX",
    "sg:tags":[
        "body",
        "automotive",
        "shop"
    ],
    "wof:name":"AAA Body Shop",
    "wof:placetype":"venue"
},
  "geometry": {"coordinates":[-106.364152,31.796557],"type":"Point"}
}