{
  "type": "Feature",
  "properties": {
    "iso:country":"US",
    "sg:address":"2424 Shetland Dr",
    "sg:city":"Lewisville",
    "sg:classifiers":[
        {
            "category":"Retail",
            "subcategory":"Auto Repair",
            "type":"Services"
        }
    ],
    "sg:phone":"+1 972 317 1001",
    "sg:postcode":"75077",
    "sg:province":"TX",
    "sg:tags":[
        "general"
    ],
    "wof:name":"Higher Authority",
    "wof:placetype":"venue"
},
  "geometry": {"coordinates":[-97.07584,33.083518],"type":"Point"}
}