{
  "type": "Feature",
  "properties": {
    "iso:country":"US",
    "sg:address":"5220 Spring Valley Rd Ste 602",
    "sg:city":"Dallas",
    "sg:classifiers":[
        {
            "category":"Communications",
            "subcategory":"Television Station",
            "type":"Services"
        }
    ],
    "sg:phone":"+1 972 687 0400",
    "sg:postcode":"75254",
    "sg:province":"TX",
    "wof:name":"Fox Station Sales",
    "wof:placetype":"venue"
},
  "geometry": {"coordinates":[-96.81975799999999,32.939301],"type":"Point"}
}