{
  "type": "Feature",
  "properties": {
    "iso:country":"US",
    "sg:address":"3109 S Belt Line Rd",
    "sg:city":"Mesquite",
    "sg:classifiers":[
        {
            "category":"Manufacturing",
            "subcategory":"Printing",
            "type":"Manufacturing & Wholesale Goods"
        }
    ],
    "sg:phone":"+1 972 222 6558",
    "sg:postcode":"75181",
    "sg:province":"TX",
    "sg:tags":[
        "screen"
    ],
    "wof:name":"Cheerco",
    "wof:placetype":"venue"
},
  "geometry": {"coordinates":[-96.600684,32.725218],"type":"Point"}
}