{
  "type": "Feature",
  "properties": {
    "iso:country":"US",
    "sg:address":"2350 Doreen St",
    "sg:city":"Grand Prairie",
    "sg:classifiers":[
        {
            "category":"Retail",
            "subcategory":"Auto Repair",
            "type":"Services"
        }
    ],
    "sg:phone":"+1 972 623 1895",
    "sg:postcode":"75050",
    "sg:province":"TX",
    "sg:tags":[
        "repairing",
        "automobile"
    ],
    "wof:name":"Mahanaim Auto Sales",
    "wof:placetype":"venue"
},
  "geometry": {"coordinates":[-97.03722500000001,32.7426],"type":"Point"}
}