{
  "type": "Feature",
  "properties": {
    "iso:country":"US",
    "sg:address":"6300 Alder Dr",
    "sg:city":"Houston",
    "sg:classifiers":[
        {
            "category":"Building & Trades",
            "subcategory":"Construction",
            "type":"Services"
        }
    ],
    "sg:phone":"+1 713 660 9449",
    "sg:postcode":"77081",
    "sg:province":"TX",
    "wof:name":"E & C Dewalt",
    "wof:placetype":"venue"
},
  "geometry": {"coordinates":[-95.48055100000001,29.712335],"type":"Point"}
}