{
  "type": "Feature",
  "properties": {
    "iso:country":"US",
    "sg:address":"825 Curtin St",
    "sg:city":"Houston",
    "sg:classifiers":[
        {
            "category":"Building & Trades",
            "subcategory":"Plumbing",
            "type":"Services"
        }
    ],
    "sg:phone":"+1 713 691 8989",
    "sg:postcode":"77018",
    "sg:province":"TX",
    "sg:website":"www.aarons-plumbing.com",
    "wof:name":"Aaron's Plumbing",
    "wof:placetype":"venue"
},
  "geometry": {"coordinates":[-95.412065,29.831239],"type":"Point"}
}