{
  "type": "Feature",
  "properties": {
    "iso:country":"US",
    "sg:address":"11000 Richmond Ave",
    "sg:city":"Houston",
    "sg:classifiers":[
        {
            "category":"Insurance",
            "subcategory":"Insurance Agent",
            "type":"Services"
        }
    ],
    "sg:phone":"+1 713 532 4111",
    "sg:postcode":"77042",
    "sg:province":"TX",
    "wof:name":"CRC of Texas",
    "wof:placetype":"venue"
},
  "geometry": {"coordinates":[-95.569401,29.727834],"type":"Point"}
}