{
  "type": "Feature",
  "properties": {
    "iso:country":"US",
    "sg:address":"6130 Iron Rock St",
    "sg:city":"Houston",
    "sg:classifiers":[
        {
            "category":"Personal",
            "type":"Services"
        }
    ],
    "sg:phone":"+1 713 641 5011",
    "sg:postcode":"77087",
    "sg:province":"TX",
    "wof:name":"Body Releases",
    "wof:placetype":"venue"
},
  "geometry": {"coordinates":[-95.321442,29.68759],"type":"Point"}
}