{
  "type": "Feature",
  "properties": {
    "iso:country":"US",
    "sg:address":"12726 Newberry St",
    "sg:city":"Sugar Land",
    "sg:classifiers":[
        {
            "category":"Retail",
            "subcategory":"Repair Shop",
            "type":"Services"
        }
    ],
    "sg:phone":"+1 281 240 7746",
    "sg:postcode":"77478",
    "sg:province":"TX",
    "wof:name":"John Butler Instrument RE",
    "wof:placetype":"venue"
},
  "geometry": {"coordinates":[-95.60740699999999,29.659013],"type":"Point"}
}