{
  "type": "Feature",
  "properties": {
    "iso:country":"US",
    "sg:address":"161 Mockingbird Ln",
    "sg:city":"Livingston",
    "sg:classifiers":[
        {
            "category":"Organizations",
            "subcategory":"Religious Organization",
            "type":"Services"
        }
    ],
    "sg:phone":"+1 936 327 5206",
    "sg:postcode":"77351",
    "sg:province":"TX",
    "sg:tags":[
        "church"
    ],
    "wof:name":"First United Methodist Chr",
    "wof:placetype":"venue"
},
  "geometry": {"coordinates":[-94.94041799999999,30.698558],"type":"Point"}
}