{
  "type": "Feature",
  "properties": {
    "iso:country":"US",
    "sg:address":"2928 Lotus Park",
    "sg:city":"Schertz",
    "sg:classifiers":[
        {
            "category":"Shopping",
            "subcategory":"Jewelry",
            "type":"Retail Goods"
        }
    ],
    "sg:phone":"+1 210 659 3295",
    "sg:postcode":"78154",
    "sg:province":"TX",
    "wof:name":"Paula A Hatcher",
    "wof:placetype":"venue"
},
  "geometry": {"coordinates":[-98.256214,29.588925],"type":"Point"}
}