{
  "type": "Feature",
  "properties": {
    "iso:country":"US",
    "sg:address":"1515 19th St",
    "sg:city":"Lubbock",
    "sg:classifiers":[
        {
            "category":"Autos & Motor Vehicles",
            "subcategory":"Auto Supplies",
            "type":"Retail Goods"
        }
    ],
    "sg:phone":"+1 806 744 7788",
    "sg:postcode":"79401",
    "sg:province":"TX",
    "wof:name":"19th St Collision Center",
    "wof:placetype":"venue"
},
  "geometry": {"coordinates":[-101.85109199999999,33.577769],"type":"Point"}
}