{
  "type": "Feature",
  "properties": {
    "iso:country":"US",
    "sg:address":"1417 S Velasco St",
    "sg:city":"Angleton",
    "sg:classifiers":[
        {
            "category":"Autos & Motor Vehicles",
            "subcategory":"Auto Supplies",
            "type":"Retail Goods"
        },
        {
            "category":"Retail",
            "subcategory":"Auto Repair",
            "type":"Services"
        }
    ],
    "sg:phone":"+1 979 849 3535",
    "sg:postcode":"77515",
    "sg:province":"TX",
    "sg:tags":[
        "body",
        "automobile",
        "truck",
        "painting",
        "repairing"
    ],
    "wof:name":"Mike's Paint & Body Shop",
    "wof:placetype":"venue"
},
  "geometry": {"coordinates":[-95.428815,29.144277],"type":"Point"}
}