{
  "type": "Feature",
  "properties": {
    "iso:country":"US",
    "sg:address":"1126 E Villa Maria Rd",
    "sg:city":"Bryan",
    "sg:classifiers":[
        {
            "category":"Health Services",
            "subcategory":"Dentist",
            "type":"Services"
        }
    ],
    "sg:phone":"+1 979 776 1976",
    "sg:postcode":"77802",
    "sg:province":"TX",
    "wof:name":"James D Moffitt",
    "wof:placetype":"venue"
},
  "geometry": {"coordinates":[-96.347801,30.649651],"type":"Point"}
}