{
  "type": "Feature",
  "properties": {
    "iso:country":"US",
    "sg:address":"2825 Ridge Rd",
    "sg:city":"Rockwall",
    "sg:classifiers":[
        {
            "category":"Shopping",
            "subcategory":"Bicycles & Sporting Goods",
            "type":"Retail Goods"
        }
    ],
    "sg:phone":"+1 972 771 2824",
    "sg:postcode":"75032",
    "sg:province":"TX",
    "wof:name":"Bicycles Plus Inc",
    "wof:placetype":"venue"
},
  "geometry": {"coordinates":[-96.47364,32.887169],"type":"Point"}
}