{
  "type": "Feature",
  "properties": {
    "iso:country":"US",
    "sg:address":"2728 Ave Q",
    "sg:city":"Galveston",
    "sg:classifiers":[
        {
            "category":"Shopping",
            "subcategory":"Bicycles & Sporting Goods",
            "type":"Retail Goods"
        }
    ],
    "sg:phone":"+1 409 763 4551",
    "sg:postcode":"77550",
    "sg:province":"TX",
    "sg:tags":[
        "equipment",
        "tennis"
    ],
    "wof:name":"Stiglich Tennis Shop",
    "wof:placetype":"venue"
},
  "geometry": {"coordinates":[-94.794245,29.289045],"type":"Point"}
}