{
  "type": "Feature",
  "properties": {
    "iso:country":"US",
    "sg:address":"1111 N Fry Rd",
    "sg:city":"Katy",
    "sg:classifiers":[
        {
            "category":"Home & Garden",
            "subcategory":"Building Materials",
            "type":"Retail Goods"
        }
    ],
    "sg:phone":"+1 281 599 9170",
    "sg:postcode":"77449",
    "sg:province":"TX",
    "wof:name":"Home Depot",
    "wof:placetype":"venue"
},
  "geometry": {"coordinates":[-95.718968,29.787919],"type":"Point"}
}