{
  "type": "Feature",
  "properties": {
    "iso:country":"US",
    "sg:address":"124 E 26th St",
    "sg:city":"Littlefield",
    "sg:classifiers":[
        {
            "category":"Professional",
            "type":"Services"
        }
    ],
    "sg:phone":"+1 806 385 6338",
    "sg:postcode":"79339",
    "sg:province":"TX",
    "wof:name":"William T Figueroa",
    "wof:placetype":"venue"
},
  "geometry": {"coordinates":[-102.335694,33.902143],"type":"Point"}
}