{
  "type": "Feature",
  "properties": {
    "iso:country":"US",
    "sg:address":"1200 Jordan St",
    "sg:city":"Longview",
    "sg:classifiers":[
        {
            "category":"Organizations",
            "subcategory":"Religious Organization",
            "type":"Services"
        }
    ],
    "sg:phone":"+1 903 753 8567",
    "sg:postcode":"75602",
    "sg:province":"TX",
    "wof:name":"Vivian Chapel Methodist Church",
    "wof:placetype":"venue"
},
  "geometry": {"coordinates":[-94.711957,32.483469],"type":"Point"}
}