{
  "type": "Feature",
  "properties": {
    "iso:country":"US",
    "sg:address":"7100 Westwind Dr",
    "sg:city":"El Paso",
    "sg:classifiers":[
        {
            "category":"Health Services",
            "subcategory":"Doctor",
            "type":"Services"
        }
    ],
    "sg:phone":"+1 915 584 1124",
    "sg:postcode":"79912",
    "sg:province":"TX",
    "wof:name":"Dillman Everett G PHD",
    "wof:placetype":"venue"
},
  "geometry": {"coordinates":[-106.541465,31.856585],"type":"Point"}
}