{
  "type": "Feature",
  "properties": {
    "iso:country":"US",
    "sg:address":"2551 S State Hwy 95",
    "sg:city":"Taylor",
    "sg:classifiers":[
        {
            "category":"Personal",
            "type":"Services"
        }
    ],
    "sg:phone":"+1 512 352 2933",
    "sg:postcode":"76574",
    "sg:province":"TX",
    "sg:tags":[
        "consultant",
        "wedding"
    ],
    "wof:name":"All About Weddings",
    "wof:placetype":"venue"
},
  "geometry": {"coordinates":[-97.42162999999999,30.612728],"type":"Point"}
}