{
  "type": "Feature",
  "properties": {
    "iso:country":"US",
    "sg:address":"3939 Briargrove Ln",
    "sg:city":"Dallas",
    "sg:classifiers":[
        {
            "category":"Professional",
            "subcategory":"Management & Consulting",
            "type":"Services"
        }
    ],
    "sg:phone":"+1 972 306 1261",
    "sg:postcode":"75287",
    "sg:province":"TX",
    "sg:tags":[
        "business"
    ],
    "wof:name":"Thanickel Consulting",
    "wof:placetype":"venue"
},
  "geometry": {"coordinates":[-96.844919,32.99281],"type":"Point"}
}