{
  "type": "Feature",
  "properties": {
    "iso:country":"US",
    "sg:address":"18800 Dee Ln",
    "sg:city":"Canyon",
    "sg:classifiers":[
        {
            "category":"Professional",
            "type":"Services"
        }
    ],
    "sg:phone":"+1 806 655 9615",
    "sg:postcode":"79015",
    "sg:province":"TX",
    "wof:name":"Rafter or Hay Service",
    "wof:placetype":"venue"
},
  "geometry": {"coordinates":[-101.948533,35.019976],"type":"Point"}
}