{
  "type": "Feature",
  "properties": {
    "iso:country":"US",
    "sg:address":"3565 Lee Blvd",
    "sg:city":"El Paso",
    "sg:classifiers":[
        {
            "category":"Retail",
            "subcategory":"Auto Repair",
            "type":"Services"
        }
    ],
    "sg:phone":"+1 915 856 9200",
    "sg:postcode":"79936",
    "sg:province":"TX",
    "sg:tags":[
        "wrecker"
    ],
    "wof:name":"A D Towing & Recovery",
    "wof:placetype":"venue"
},
  "geometry": {"coordinates":[-106.293881,31.796507],"type":"Point"}
}