{
  "type": "Feature",
  "properties": {
    "iso:country":"US",
    "sg:address":"1312 Hondo St",
    "sg:city":"Lockhart",
    "sg:classifiers":[
        {
            "category":"Building & Trades",
            "subcategory":"Equipment Rental",
            "type":"Services"
        }
    ],
    "sg:phone":"+1 512 376 6372",
    "sg:postcode":"78644",
    "sg:province":"TX",
    "sg:tags":[
        "party",
        "supply"
    ],
    "wof:name":"Mata's Bouncing Buddies",
    "wof:placetype":"venue"
},
  "geometry": {"coordinates":[-97.678831,29.894941],"type":"Point"}
}