{
  "type": "Feature",
  "properties": {
    "iso:country":"US",
    "sg:address":"5112 Knight Dr",
    "sg:city":"Fort Worth",
    "sg:classifiers":[
        {
            "category":"Building & Trades",
            "subcategory":"Construction",
            "type":"Services"
        }
    ],
    "sg:phone":"+1 817 483 8086",
    "sg:postcode":"76140",
    "sg:province":"TX",
    "sg:tags":[
        "hanging",
        "contractor"
    ],
    "wof:name":"Venzor Joaquin",
    "wof:placetype":"venue"
},
  "geometry": {"coordinates":[-97.241264,32.602343],"type":"Point"}
}