{
  "type": "Feature",
  "properties": {
    "iso:country":"US",
    "sg:address":"115 E Ave D",
    "sg:city":"San Angelo",
    "sg:classifiers":[
        {
            "category":"Social Services",
            "type":"Services"
        }
    ],
    "sg:phone":"+1 325 659 6900",
    "sg:postcode":"76903",
    "sg:province":"TX",
    "sg:tags":[
        "organization",
        "welfare"
    ],
    "wof:name":"Giant Steps For Children",
    "wof:placetype":"venue"
},
  "geometry": {"coordinates":[-100.428397,31.453439],"type":"Point"}
}