{
  "type": "Feature",
  "properties": {
    "iso:country":"US",
    "sg:address":"1332 Williams Ave",
    "sg:city":"Desoto",
    "sg:classifiers":[
        {
            "category":"Professional",
            "type":"Services"
        }
    ],
    "sg:phone":"+1 972 224 2137",
    "sg:postcode":"75115",
    "sg:province":"TX",
    "sg:tags":[
        "publication",
        "editorial"
    ],
    "wof:name":"Hnic",
    "wof:placetype":"venue"
},
  "geometry": {"coordinates":[-96.853685,32.613295],"type":"Point"}
}