{
  "type": "Feature",
  "properties": {
    "iso:country":"US",
    "sg:address":"13850 Gulf Fwy Ste 115",
    "sg:city":"Houston",
    "sg:classifiers":[
        {
            "category":"Building & Trades",
            "subcategory":"Construction",
            "type":"Services"
        }
    ],
    "sg:phone":"+1 713 574 7030",
    "sg:postcode":"77034",
    "sg:province":"TX",
    "sg:tags":[
        "contractor"
    ],
    "sg:website":"www.uscatastrophe.com",
    "wof:name":"UNITED STATES CATASTROPHE ROOFING",
    "wof:placetype":"venue"
},
  "geometry": {"coordinates":[-95.200914,29.60137],"type":"Point"}
}