{
  "type": "Feature",
  "properties": {
    "iso:country":"US",
    "sg:address":"310 Tennyson St",
    "sg:city":"Dickinson",
    "sg:classifiers":[
        {
            "category":"Insurance",
            "subcategory":"Life Insurance",
            "type":"Services"
        }
    ],
    "sg:phone":"+1 281 559 4404",
    "sg:postcode":"77539",
    "sg:province":"TX",
    "wof:name":"Exchange Underwrighting Svc",
    "wof:placetype":"venue"
},
  "geometry": {"coordinates":[-94.943478,29.497674],"type":"Point"}
}