{
  "type": "Feature",
  "properties": {
    "iso:country":"US",
    "sg:address":"617 Fairview",
    "sg:city":"Houston",
    "sg:classifiers":[
        {
            "category":"Bars & Pubs",
            "type":"Food & Drink"
        }
    ],
    "sg:phone":"+1 713 528 8102",
    "sg:postcode":"77006",
    "sg:province":"TX",
    "sg:website":"georgescountrysportsbar.com/",
    "wof:name":"George Country Sports Bar",
    "wof:placetype":"venue"
},
  "geometry": {"coordinates":[-95.388632,29.747943],"type":"Point"}
}