{
  "type": "Feature",
  "properties": {
    "iso:country":"US",
    "sg:address":"20530 Gulf Fwy",
    "sg:city":"Webster",
    "sg:classifiers":[
        {
            "category":"Shopping",
            "type":"Retail Goods"
        }
    ],
    "sg:phone":"+1 281 316 7665",
    "sg:postcode":"77598",
    "sg:province":"TX",
    "sg:tags":[
        "all",
        "deck",
        "installs",
        "plus",
        "build",
        "above"
    ],
    "wof:name":"Accent Spas Pools & Decks",
    "wof:placetype":"venue"
},
  "geometry": {"coordinates":[-95.133786,29.531354],"type":"Point"}
}