{
  "type": "Feature",
  "properties": {
    "iso:country":"US",
    "sg:address":"410 SW 2nd St",
    "sg:city":"Dimmitt",
    "sg:classifiers":[
        {
            "category":"Organizations",
            "subcategory":"Religious Organization",
            "type":"Services"
        }
    ],
    "sg:phone":"+1 806 647 5474",
    "sg:postcode":"79027",
    "sg:province":"TX",
    "sg:tags":[
        "church"
    ],
    "wof:name":"Lee Street Baptist Church",
    "wof:placetype":"venue"
},
  "geometry": {"coordinates":[-102.313974,34.547487],"type":"Point"}
}