{
  "type": "Feature",
  "properties": {
    "iso:country":"US",
    "sg:address":"4510 River Brook Dr",
    "sg:city":"San Antonio",
    "sg:classifiers":[
        {
            "category":"Organizations",
            "subcategory":"Religious Organization",
            "type":"Services"
        }
    ],
    "sg:phone":"+1 210 394 3749",
    "sg:postcode":"78244",
    "sg:province":"TX",
    "wof:name":"El Pabellon Del Jubileo",
    "wof:placetype":"venue"
},
  "geometry": {"coordinates":[-98.34381399999999,29.470466],"type":"Point"}
}