{
  "type": "Feature",
  "properties": {
    "iso:country":"US",
    "sg:address":"1402 Westshore Dr",
    "sg:city":"Houston",
    "sg:classifiers":[
        {
            "category":"Professional",
            "subcategory":"Business Services",
            "type":"Services"
        }
    ],
    "sg:phone":"+1 281 398 0032",
    "sg:postcode":"77094",
    "sg:province":"TX",
    "wof:name":"Solid Rock Group",
    "wof:placetype":"venue"
},
  "geometry": {"coordinates":[-95.701252,29.764687],"type":"Point"}
}