{
  "type": "Feature",
  "properties": {
    "iso:country":"US",
    "sg:address":"1705 Winding Hollow Ln",
    "sg:city":"Mc Kinney",
    "sg:classifiers":[
        {
            "category":"Professional",
            "subcategory":"Business Services",
            "type":"Services"
        }
    ],
    "sg:phone":"+1 972 547 0539",
    "sg:postcode":"75070",
    "sg:province":"TX",
    "wof:name":"Riggs Enterprises LLC",
    "wof:placetype":"venue"
},
  "geometry": {"coordinates":[-96.656824,33.184187],"type":"Point"}
}