{
  "type": "Feature",
  "properties": {
    "iso:country":"US",
    "sg:address":"3 Shady Oaks Ct",
    "sg:city":"Roanoke",
    "sg:classifiers":[
        {
            "category":"Shopping",
            "subcategory":"Used Merchandise",
            "type":"Retail Goods"
        }
    ],
    "sg:phone":"+1 817 430 4224",
    "sg:postcode":"76262",
    "sg:province":"TX",
    "wof:name":"Yesterday Remembered",
    "wof:placetype":"venue"
},
  "geometry": {"coordinates":[-97.16764999999999,32.99279],"type":"Point"}
}