{
  "type": "Feature",
  "properties": {
    "iso:country":"US",
    "sg:address":"3314 Gill St",
    "sg:city":"Dallas",
    "sg:classifiers":[
        {
            "category":"Wholesale",
            "subcategory":"Jewelry",
            "type":"Manufacturing & Wholesale Goods"
        }
    ],
    "sg:phone":"+1 214 381 2280",
    "sg:postcode":"75227",
    "sg:province":"TX",
    "sg:tags":[
        "stone"
    ],
    "wof:name":"Buzzzy Gamble",
    "wof:placetype":"venue"
},
  "geometry": {"coordinates":[-96.723398,32.771389],"type":"Point"}
}