{
  "type": "Feature",
  "properties": {
    "iso:country":"US",
    "sg:address":"6722 Carvel Ln",
    "sg:city":"Houston",
    "sg:classifiers":[
        {
            "category":"Manufacturing",
            "subcategory":"Food",
            "type":"Manufacturing & Wholesale Goods"
        }
    ],
    "sg:phone":"+1 713 781 2370",
    "sg:postcode":"77074",
    "sg:province":"TX",
    "sg:tags":[
        "sauce",
        "mfg"
    ],
    "wof:name":"Henrys Dream Inc",
    "wof:placetype":"venue"
},
  "geometry": {"coordinates":[-95.50381,29.696446],"type":"Point"}
}