{
  "type": "Feature",
  "properties": {
    "iso:country":"US",
    "sg:address":"14710 Koinm Rd",
    "sg:city":"Houston",
    "sg:classifiers":[
        {
            "category":"Freight",
            "type":"Transportation"
        }
    ],
    "sg:phone":"+1 281 449 8777",
    "sg:postcode":"77032",
    "sg:province":"TX",
    "wof:name":"Leeway Transportation",
    "wof:placetype":"venue"
},
  "geometry": {"coordinates":[-95.335506,29.931429],"type":"Point"}
}