{
  "type": "Feature",
  "properties": {
    "iso:country":"US",
    "sg:address":"3265 Independence Pkwy",
    "sg:city":"Plano",
    "sg:classifiers":[
        {
            "category":"Restaurant",
            "type":"Food & Drink"
        }
    ],
    "sg:phone":"+1 972 519 0345",
    "sg:postcode":"75075",
    "sg:province":"TX",
    "sg:tags":[
        "eating"
    ],
    "wof:name":"Covino's Pasta & Pizza",
    "wof:placetype":"venue"
},
  "geometry": {"coordinates":[-96.753466,33.040358],"type":"Point"}
}