{
  "type": "Feature",
  "properties": {
    "iso:country":"US",
    "sg:address":"3641 Briar Creek Dr",
    "sg:city":"Beaumont",
    "sg:classifiers":[
        {
            "category":"Shopping",
            "subcategory":"Used Merchandise",
            "type":"Retail Goods"
        }
    ],
    "sg:phone":"+1 409 898 1642",
    "sg:postcode":"77706",
    "sg:province":"TX",
    "wof:name":"Norris Cabinets",
    "wof:placetype":"venue"
},
  "geometry": {"coordinates":[-94.16401,30.114885],"type":"Point"}
}