{
  "type": "Feature",
  "properties": {
    "iso:country":"US",
    "sg:address":"15033 Nacogdoches Rd",
    "sg:city":"San Antonio",
    "sg:classifiers":[
        {
            "category":"Insurance",
            "subcategory":"Insurance Agent",
            "type":"Services"
        }
    ],
    "sg:phone":"+1 210 657 3665",
    "sg:postcode":"78247",
    "sg:province":"TX",
    "wof:name":"Aerflite Auto Rental Svcs",
    "wof:placetype":"venue"
},
  "geometry": {"coordinates":[-98.37349500000001,29.577532],"type":"Point"}
}