{
  "type": "Feature",
  "properties": {
    "iso:country":"US",
    "sg:address":"109 E 2nd St",
    "sg:city":"Cross Plains",
    "sg:classifiers":[
        {
            "category":"Health Services",
            "subcategory":"Doctor",
            "type":"Services"
        }
    ],
    "sg:phone":"+1 254 725 7106",
    "sg:postcode":"76443",
    "sg:province":"TX",
    "sg:tags":[
        "clinic"
    ],
    "wof:name":"1 Source Health Ctr",
    "wof:placetype":"venue"
},
  "geometry": {"coordinates":[-99.16551800000001,32.124314],"type":"Point"}
}