{
  "type": "Feature",
  "properties": {
    "iso:country":"US",
    "sg:address":"1117 Brookside Dr",
    "sg:city":"Hurst",
    "sg:classifiers":[
        {
            "category":"Professional",
            "subcategory":"Business Services",
            "type":"Services"
        }
    ],
    "sg:phone":"+1 817 896 4117",
    "sg:postcode":"76053",
    "sg:province":"TX",
    "wof:name":"Cool Pool Service",
    "wof:placetype":"venue"
},
  "geometry": {"coordinates":[-97.17876699999999,32.830187],"type":"Point"}
}