{
  "type": "Feature",
  "properties": {
    "iso:country":"US",
    "sg:address":"2407 Avenell Rd",
    "sg:city":"Houston",
    "sg:classifiers":[
        {
            "category":"Manufacturing",
            "subcategory":"Signs",
            "type":"Manufacturing & Wholesale Goods"
        }
    ],
    "sg:phone":"+1 713 944 7444",
    "sg:postcode":"77034",
    "sg:province":"TX",
    "wof:name":"Houtex Signs",
    "wof:placetype":"venue"
},
  "geometry": {"coordinates":[-95.224161,29.644698],"type":"Point"}
}