{
  "type": "Feature",
  "properties": {
    "iso:country":"US",
    "sg:address":"731 Bluebonnet Dr",
    "sg:city":"Allen",
    "sg:classifiers":[
        {
            "category":"Shopping",
            "subcategory":"Gifts & Souvenirs",
            "type":"Retail Goods"
        }
    ],
    "sg:phone":"+1 972 359 9292",
    "sg:postcode":"75002",
    "sg:province":"TX",
    "wof:name":"Scentsational Gifts",
    "wof:placetype":"venue"
},
  "geometry": {"coordinates":[-96.638897,33.092645],"type":"Point"}
}