{
  "type": "Feature",
  "properties": {
    "iso:country":"US",
    "sg:address":"1422 W Kingsley Rd",
    "sg:city":"Garland",
    "sg:classifiers":[
        {
            "category":"Banks & Credit Unions",
            "subcategory":"Bank",
            "type":"Services"
        }
    ],
    "sg:phone":"+1 972 271 3909",
    "sg:postcode":"75041",
    "sg:province":"TX",
    "sg:tags":[
        "money",
        "transfer"
    ],
    "wof:name":"Dolex Dollar Express",
    "wof:placetype":"venue"
},
  "geometry": {"coordinates":[-96.64909900000001,32.878613],"type":"Point"}
}