{
  "type": "Feature",
  "properties": {
    "iso:country":"US",
    "sg:address":"8709 Corran Ferry Dr",
    "sg:city":"Austin",
    "sg:classifiers":[
        {
            "category":"Building & Trades",
            "subcategory":"Landscaping Services",
            "type":"Services"
        }
    ],
    "sg:phone":"+1 512 291 0529",
    "sg:postcode":"78749",
    "sg:province":"TX",
    "sg:tags":[
        "tree"
    ],
    "wof:name":"Shane's Tree & Landscape",
    "wof:placetype":"venue"
},
  "geometry": {"coordinates":[-97.85225800000001,30.202488],"type":"Point"}
}