{
  "type": "Feature",
  "properties": {
    "iso:country":"US",
    "sg:address":"2012 W Scyene Rd",
    "sg:city":"Mesquite",
    "sg:classifiers":[
        {
            "category":"Restaurant",
            "type":"Food & Drink"
        }
    ],
    "sg:menulink":"http://www.allmenus.com/tx/northeast/202281-mcdonalds/menu/",
    "sg:postcode":"75149",
    "sg:province":"TX",
    "sg:tags":[
        "burger",
        "american"
    ],
    "wof:name":"McDonald's",
    "wof:placetype":"venue"
},
  "geometry": {"coordinates":[-96.629113,32.766521],"type":"Point"}
}