{
  "type": "Feature",
  "properties": {
    "iso:country":"US",
    "sg:address":"523 24th Street Rear",
    "sg:city":"Galveston",
    "sg:classifiers":[
        {
            "category":"Travel",
            "subcategory":"Travel Agent",
            "type":"Entertainment"
        }
    ],
    "sg:phone":"+1 409 763 8676",
    "sg:postcode":"77550",
    "sg:province":"TX",
    "sg:tags":[
        "agency"
    ],
    "wof:name":"Galvestoncruisescom Inc",
    "wof:placetype":"venue"
},
  "geometry": {"coordinates":[-94.794633,29.303998],"type":"Point"}
}