{
  "type": "Feature",
  "properties": {
    "iso:country":"US",
    "sg:address":"906 Doris St",
    "sg:city":"Kemah",
    "sg:classifiers":[
        {
            "category":"Retail",
            "subcategory":"Repair Shop",
            "type":"Services"
        }
    ],
    "sg:phone":"+1 281 535 9500",
    "sg:postcode":"77565",
    "sg:province":"TX",
    "wof:name":"A 1 Global Marine Services",
    "wof:placetype":"venue"
},
  "geometry": {"coordinates":[-95.03545,29.539655],"type":"Point"}
}