{
  "type": "Feature",
  "properties": {
    "iso:country":"US",
    "sg:address":"10319 Finnell St",
    "sg:city":"Dallas",
    "sg:classifiers":[
        {
            "category":"Restaurant",
            "type":"Food & Drink"
        }
    ],
    "sg:phone":"+1 214 358 5300",
    "sg:postcode":"75220",
    "sg:province":"TX",
    "wof:name":"Schlotzky's Inc",
    "wof:placetype":"venue"
},
  "geometry": {"coordinates":[-96.893429,32.864122],"type":"Point"}
}