{
  "type": "Feature",
  "properties": {
    "iso:country":"US",
    "sg:address":"1002 S Mesa St",
    "sg:city":"El Paso",
    "sg:classifiers":[
        {
            "category":"Wholesale",
            "subcategory":"Electrical",
            "type":"Manufacturing & Wholesale Goods"
        }
    ],
    "sg:phone":"+1 915 532 1177",
    "sg:postcode":"79901",
    "sg:province":"TX",
    "sg:tags":[
        "sound",
        "equipment",
        "electronic"
    ],
    "wof:name":"Century Sound Inc",
    "wof:placetype":"venue"
},
  "geometry": {"coordinates":[-106.484115,31.749528],"type":"Point"}
}