{
  "type": "Feature",
  "properties": {
    "iso:country":"US",
    "sg:address":"3503 Creekbend Dr",
    "sg:city":"Baytown",
    "sg:classifiers":[
        {
            "category":"Shopping",
            "subcategory":"Discount & Variety Stores",
            "type":"Retail Goods"
        }
    ],
    "sg:phone":"+1 281 422 2616",
    "sg:postcode":"77521",
    "sg:province":"TX",
    "sg:tags":[
        "merchandise",
        "general"
    ],
    "wof:name":"Cherie Amour Collectibles",
    "wof:placetype":"venue"
},
  "geometry": {"coordinates":[-94.972368,29.759005],"type":"Point"}
}