{
  "type": "Feature",
  "properties": {
    "iso:country":"US",
    "sg:address":"3209 Arthur St",
    "sg:city":"Wichita Falls",
    "sg:classifiers":[
        {
            "category":"Wholesale",
            "subcategory":"Hardware",
            "type":"Manufacturing & Wholesale Goods"
        }
    ],
    "sg:phone":"+1 940 692 8588",
    "sg:postcode":"76308",
    "sg:province":"TX",
    "wof:name":"Wichita Fasteners",
    "wof:placetype":"venue"
},
  "geometry": {"coordinates":[-98.534085,33.87948],"type":"Point"}
}