{
  "type": "Feature",
  "properties": {
    "iso:country":"US",
    "sg:address":"3115 S Cooper St",
    "sg:city":"Arlington",
    "sg:classifiers":[
        {
            "category":"Insurance",
            "subcategory":"Insurance Agent",
            "type":"Services"
        }
    ],
    "sg:phone":"+1 817 465 7766",
    "sg:postcode":"76015",
    "sg:province":"TX",
    "wof:name":"Alias Smith & Smith Insur Agcy",
    "wof:placetype":"venue"
},
  "geometry": {"coordinates":[-97.12415900000001,32.697653],"type":"Point"}
}