{
  "type": "Feature",
  "properties": {
    "iso:country":"US",
    "sg:address":"2401 W Pioneer Pkwy Ste 167",
    "sg:city":"Pantego",
    "sg:phone":"+1 817 469 8565",
    "sg:postcode":"76013",
    "sg:province":"TX",
    "wof:name":"Divine Arts Dance Center",
    "wof:placetype":"venue"
},
  "geometry": {"coordinates":[-97.14716300000001,32.709801],"type":"Point"}
}