{
  "type": "Feature",
  "properties": {
    "iso:country":"US",
    "sg:address":"1515 S Fairgrounds Rd",
    "sg:city":"Midland",
    "sg:classifiers":[
        {
            "category":"Manufacturing",
            "subcategory":"Food",
            "type":"Manufacturing & Wholesale Goods"
        }
    ],
    "sg:phone":"+1 432 570 4040",
    "sg:postcode":"79701",
    "sg:province":"TX",
    "sg:tags":[
        "confectionery",
        "candy"
    ],
    "sg:website":"www.susiessouthforty.com",
    "wof:name":"Susie's South Forty Confection",
    "wof:placetype":"venue"
},
  "geometry": {"coordinates":[-102.043548,31.988601],"type":"Point"}
}