{
  "type": "Feature",
  "properties": {
    "iso:country":"US",
    "sg:address":"7332 Staffordshire St",
    "sg:city":"Houston",
    "sg:classifiers":[
        {
            "category":"Personal",
            "subcategory":"Massage",
            "type":"Services"
        },
        {
            "category":"Health Services",
            "subcategory":"Clinic",
            "type":"Services"
        },
        {
            "category":"Health Services",
            "subcategory":"Health Practitioner",
            "type":"Services"
        }
    ],
    "sg:phone":"+1 832 545 5476",
    "sg:postcode":"77030",
    "sg:province":"TX",
    "sg:tags":[
        "therapist",
        "therapy",
        "physical"
    ],
    "wof:name":"Bratsven Randy Massage",
    "wof:placetype":"venue"
},
  "geometry": {"coordinates":[-95.39546199999999,29.697651],"type":"Point"}
}