{
  "type": "Feature",
  "properties": {
    "iso:country":"US",
    "sg:address":"8250 Whitus Dr",
    "sg:city":"El Paso",
    "sg:classifiers":[
        {
            "category":"Organizations",
            "subcategory":"Community Association",
            "type":"Services"
        }
    ],
    "sg:phone":"+1 915 778 4868",
    "sg:postcode":"79925",
    "sg:province":"TX",
    "sg:tags":[
        "club"
    ],
    "wof:name":"Blue Dolphin Swim Club",
    "wof:placetype":"venue"
},
  "geometry": {"coordinates":[-106.37699600000001,31.783979],"type":"Point"}
}