{
  "type": "Feature",
  "properties": {
    "iso:country":"US",
    "sg:address":"4806 Alma St",
    "sg:city":"Corpus Christi",
    "sg:classifiers":[
        {
            "category":"Education",
            "subcategory":"Special Training",
            "type":"Public Place"
        }
    ],
    "sg:phone":"+1 361 853 0785",
    "sg:postcode":"78411",
    "sg:province":"TX",
    "wof:name":"Casa Verde",
    "wof:placetype":"venue"
},
  "geometry": {"coordinates":[-97.392725,27.725223],"type":"Point"}
}