{
  "type": "Feature",
  "properties": {
    "iso:country":"US",
    "sg:address":"2927 Kenross St",
    "sg:city":"Houston",
    "sg:classifiers":[
        {
            "category":"Professional",
            "subcategory":"Management & Consulting",
            "type":"Services"
        }
    ],
    "sg:phone":"+1 713 690 1027",
    "sg:postcode":"77043",
    "sg:province":"TX",
    "sg:tags":[
        "consultant",
        "business"
    ],
    "wof:name":"G T Assoc Of Texas",
    "wof:placetype":"venue"
},
  "geometry": {"coordinates":[-95.551211,29.826489],"type":"Point"}
}