{
  "type": "Feature",
  "properties": {
    "iso:country":"US",
    "sg:address":"4019 Villanova St",
    "sg:city":"Dallas",
    "sg:classifiers":[
        {
            "category":"Bakery",
            "type":"Food & Drink"
        }
    ],
    "sg:menulink":"http://www.allmenus.com/tx/northeast/222883-corner-bakery/menu/",
    "sg:phone":"+1 214 368 8667",
    "sg:postcode":"75225",
    "sg:province":"TX",
    "sg:tags":[
        "sandwich",
        "salad",
        "soup",
        "american",
        "pastry",
        "wrap"
    ],
    "wof:name":"Corner Bakery",
    "wof:placetype":"venue"
},
  "geometry": {"coordinates":[-96.802182,32.864275],"type":"Point"}
}