{
  "type": "Feature",
  "properties": {
    "iso:country":"US",
    "sg:address":"1084 Grand National Blvd",
    "sg:city":"Fort Worth",
    "sg:classifiers":[
        {
            "category":"Building & Trades",
            "subcategory":"Construction",
            "type":"Services"
        }
    ],
    "sg:phone":"+1 817 232 5398",
    "sg:postcode":"76179",
    "sg:province":"TX",
    "sg:tags":[
        "home",
        "builder"
    ],
    "wof:name":"Beazer Homes",
    "wof:placetype":"venue"
},
  "geometry": {"coordinates":[-97.377315,32.84428],"type":"Point"}
}