{
  "type": "Feature",
  "properties": {
    "iso:country":"US",
    "sg:address":"10822 Mesquite Dr",
    "sg:city":"La Porte",
    "sg:classifiers":[
        {
            "category":"Professional",
            "type":"Services"
        }
    ],
    "sg:phone":"+1 281 471 3647",
    "sg:postcode":"77571",
    "sg:province":"TX",
    "wof:name":"Arthur J McGee",
    "wof:placetype":"venue"
},
  "geometry": {"coordinates":[-95.067831,29.656551],"type":"Point"}
}