{
  "type": "Feature",
  "properties": {
    "iso:country":"US",
    "sg:address":"1401 Dunn Dr",
    "sg:city":"Carrollton",
    "sg:classifiers":[
        {
            "category":"Building & Trades",
            "subcategory":"Plumbing",
            "type":"Services"
        }
    ],
    "sg:phone":"+1 972 242 7727",
    "sg:postcode":"75006",
    "sg:province":"TX",
    "sg:tags":[
        "conditioning",
        "air",
        "system",
        "contractor"
    ],
    "wof:name":"National Duct Systems",
    "wof:placetype":"venue"
},
  "geometry": {"coordinates":[-96.914064,32.947322],"type":"Point"}
}