{
  "type": "Feature",
  "properties": {
    "iso:country":"US",
    "sg:address":"2220 Co Rd 144",
    "sg:city":"Alvin",
    "sg:classifiers":[
        {
            "category":"Manufacturing",
            "subcategory":"Retail Goods",
            "type":"Manufacturing & Wholesale Goods"
        }
    ],
    "sg:phone":"+1 281 388 1014",
    "sg:postcode":"77511",
    "sg:province":"TX",
    "sg:tags":[
        "manufacturer"
    ],
    "wof:name":"ASE Industries",
    "wof:placetype":"venue"
},
  "geometry": {"coordinates":[-95.273776,29.460486],"type":"Point"}
}