{
  "type": "Feature",
  "properties": {
    "iso:country":"US",
    "sg:address":"2210 N Alexander Dr",
    "sg:city":"Baytown",
    "sg:classifiers":[
        {
            "category":"Restaurant",
            "type":"Food & Drink"
        }
    ],
    "sg:menulink":"http://www.allmenus.com/tx/baytown/177313-jack-in-the-box/menu/",
    "sg:phone":"+1 281 422 3224",
    "sg:postcode":"77520",
    "sg:province":"TX",
    "sg:tags":[
        "burger",
        "american"
    ],
    "wof:name":"Jack in the Box",
    "wof:placetype":"venue"
},
  "geometry": {"coordinates":[-94.94949099999999,29.744804],"type":"Point"}
}