{
  "type": "Feature",
  "properties": {
    "iso:country":"US",
    "sg:address":"30 E Cherry St",
    "sg:city":"Paris",
    "sg:classifiers":[
        {
            "category":"Autos & Motor Vehicles",
            "subcategory":"Automobile Sales",
            "type":"Retail Goods"
        }
    ],
    "sg:phone":"+1 903 785 7449",
    "sg:postcode":"75460",
    "sg:province":"TX",
    "sg:tags":[
        "used"
    ],
    "wof:name":"Watson Glen Used Cars",
    "wof:placetype":"venue"
},
  "geometry": {"coordinates":[-95.556015,33.665097],"type":"Point"}
}