{
  "type": "Feature",
  "properties": {
    "iso:country":"US",
    "sg:address":"606 Kinney Ave",
    "sg:city":"Austin",
    "sg:classifiers":[
        {
            "category":"Professional",
            "subcategory":"Advertising",
            "type":"Services"
        }
    ],
    "sg:phone":"+1 512 732 0040",
    "sg:postcode":"78704",
    "sg:province":"TX",
    "sg:tags":[
        "counselor"
    ],
    "wof:name":"Advertising Outpost LLC",
    "wof:placetype":"venue"
},
  "geometry": {"coordinates":[-97.763188,30.260442],"type":"Point"}
}