{
  "type": "Feature",
  "properties": {
    "iso:country":"US",
    "sg:address":"2555 Repsdorph Rd",
    "sg:city":"Seabrook",
    "sg:classifiers":[
        {
            "category":"Real Estate",
            "subcategory":"Real Estate Services",
            "type":"Services"
        },
        {
            "category":"Real Estate",
            "subcategory":"Real Estate Operator",
            "type":"Services"
        }
    ],
    "sg:phone":"+1 281 326 3344",
    "sg:postcode":"77586",
    "sg:province":"TX",
    "sg:tags":[
        "vacancy",
        "apartment",
        "rental",
        "listing"
    ],
    "wof:name":"Regatta Bay Apartments",
    "wof:placetype":"venue"
},
  "geometry": {"coordinates":[-95.03833,29.57008],"type":"Point"}
}