{
  "type": "Feature",
  "properties": {
    "iso:country":"US",
    "sg:address":"411 Ellis St",
    "sg:city":"Del Rio",
    "sg:classifiers":[
        {
            "category":"Organizations",
            "subcategory":"Religious Organization",
            "type":"Services"
        }
    ],
    "sg:phone":"+1 830 775 6423",
    "sg:postcode":"78840",
    "sg:province":"TX",
    "sg:tags":[
        "church"
    ],
    "wof:name":"Iglesia Bautista Nueva VI",
    "wof:placetype":"venue"
},
  "geometry": {"coordinates":[-100.91235500000001,29.352705],"type":"Point"}
}