{
  "type": "Feature",
  "properties": {
    "iso:country":"US",
    "sg:address":"1702 Enclave Ct",
    "sg:city":"Missouri City",
    "sg:classifiers":[
        {
            "category":"Shopping",
            "type":"Retail Goods"
        }
    ],
    "sg:phone":"+1 281 499 4305",
    "sg:postcode":"77459",
    "sg:province":"TX",
    "sg:tags":[
        "miscellaneous",
        "store"
    ],
    "wof:name":"Mudpie",
    "wof:placetype":"venue"
},
  "geometry": {"coordinates":[-95.61814200000001,29.634919],"type":"Point"}
}