{
  "type": "Feature",
  "properties": {
    "iso:country":"US",
    "sg:address":"27351 Blueberry Hill Dr",
    "sg:city":"Conroe",
    "sg:classifiers":[
        {
            "category":"Professional",
            "subcategory":"Advertising",
            "type":"Services"
        }
    ],
    "sg:phone":"+1 281 932 4471",
    "sg:postcode":"77385",
    "sg:province":"TX",
    "sg:tags":[
        "mailing",
        "shipping"
    ],
    "wof:name":"Automated Mailing Solutions",
    "wof:placetype":"venue"
},
  "geometry": {"coordinates":[-95.44037,30.164253],"type":"Point"}
}