{
  "type": "Feature",
  "properties": {
    "iso:country":"US",
    "sg:address":"405 N 7th St",
    "sg:city":"Mcallen",
    "sg:classifiers":[
        {
            "category":"Organizations",
            "subcategory":"Religious Organization",
            "type":"Services"
        }
    ],
    "sg:phone":"+1 956 687 9070",
    "sg:postcode":"78501",
    "sg:province":"TX",
    "wof:name":"Missionaries of Church Lttr St",
    "wof:placetype":"venue"
},
  "geometry": {"coordinates":[-98.22589499999999,26.208364],"type":"Point"}
}