{
  "type": "Feature",
  "properties": {
    "iso:country":"US",
    "sg:address":"1100 N 5th St",
    "sg:city":"Garland",
    "sg:classifiers":[
        {
            "category":"Building & Trades",
            "subcategory":"Construction",
            "type":"Services"
        }
    ],
    "sg:phone":"+1 972 276 9584",
    "sg:postcode":"75040",
    "sg:province":"TX",
    "sg:tags":[
        "concrete",
        "contractor"
    ],
    "sg:website":"www.garlandconcrete.com",
    "wof:name":"Garland Concrete",
    "wof:placetype":"venue"
},
  "geometry": {"coordinates":[-96.636047,32.923343],"type":"Point"}
}