{
  "type": "Feature",
  "properties": {
    "iso:country":"US",
    "sg:address":"915 Avenue N",
    "sg:city":"Grand Prairie",
    "sg:classifiers":[
        {
            "category":"Shopping",
            "type":"Retail Goods"
        }
    ],
    "sg:phone":"+1 972 988 8899",
    "sg:postcode":"75050",
    "sg:province":"TX",
    "sg:tags":[
        "product",
        "foam",
        "dist",
        "fabrication",
        "pkg"
    ],
    "wof:name":"Packtech Inc",
    "wof:placetype":"venue"
},
  "geometry": {"coordinates":[-97.049046,32.777375],"type":"Point"}
}