{
  "type": "Feature",
  "properties": {
    "iso:country":"US",
    "sg:address":"2000 W 2nd St",
    "sg:city":"Odessa",
    "sg:classifiers":[
        {
            "category":"Wholesale",
            "subcategory":"Auto Parts",
            "type":"Manufacturing & Wholesale Goods"
        }
    ],
    "sg:phone":"+1 432 335 0220",
    "sg:postcode":"79763",
    "sg:province":"TX",
    "sg:tags":[
        "tire"
    ],
    "wof:name":"Triple A's Multi-Svc",
    "wof:placetype":"venue"
},
  "geometry": {"coordinates":[-102.38949599999999,31.834394],"type":"Point"}
}