{
  "type": "Feature",
  "properties": {
    "iso:country":"US",
    "sg:address":"1111 N Midkiff Rd",
    "sg:city":"Midland",
    "sg:classifiers":[
        {
            "category":"Professional",
            "subcategory":"Accounting & Tax Preparation",
            "type":"Services"
        }
    ],
    "sg:phone":"+1 432 697 8300",
    "sg:postcode":"79701",
    "sg:province":"TX",
    "sg:tags":[
        "return",
        "filing"
    ],
    "wof:name":"Jackson Hewitt Tax Svc",
    "wof:placetype":"venue"
},
  "geometry": {"coordinates":[-102.11844600000001,31.999389],"type":"Point"}
}