{
  "type": "Feature",
  "properties": {
    "iso:country":"US",
    "sg:address":"22307 Mossy Oaks Rd",
    "sg:city":"Spring",
    "sg:classifiers":[
        {
            "category":"Building & Trades",
            "subcategory":"Construction",
            "type":"Services"
        }
    ],
    "sg:phone":"+1 281 355 6696",
    "sg:postcode":"77389",
    "sg:province":"TX",
    "sg:tags":[
        "contractor"
    ],
    "wof:name":"Texcan Services Inc",
    "wof:placetype":"venue"
},
  "geometry": {"coordinates":[-95.479457,30.08744],"type":"Point"}
}