{
  "type": "Feature",
  "properties": {
    "iso:country":"US",
    "sg:address":"4301 Town Plaza Dr",
    "sg:city":"Houston",
    "sg:classifiers":[
        {
            "category":"Manufacturing",
            "subcategory":"Tools & Machinery",
            "type":"Manufacturing & Wholesale Goods"
        }
    ],
    "sg:phone":"+1 713 723 5063",
    "sg:postcode":"77045",
    "sg:province":"TX",
    "sg:tags":[
        "machine",
        "shop",
        "precision"
    ],
    "wof:name":"Nimco Instruments",
    "wof:placetype":"venue"
},
  "geometry": {"coordinates":[-95.443445,29.645774],"type":"Point"}
}