{
  "type": "Feature",
  "properties": {
    "iso:country":"US",
    "sg:address":"15335 San Pedro Ave",
    "sg:city":"San Antonio",
    "sg:classifiers":[
        {
            "category":"Restaurant",
            "type":"Food & Drink"
        }
    ],
    "sg:phone":"+1 210 490 7137",
    "sg:postcode":"78232",
    "sg:province":"TX",
    "sg:tags":[
        "eating"
    ],
    "wof:name":"Rooty S of San Antonio In",
    "wof:placetype":"venue"
},
  "geometry": {"coordinates":[-98.476845,29.580888],"type":"Point"}
}