{
  "type": "Feature",
  "properties": {
    "iso:country":"US",
    "sg:address":"2105 Ave M",
    "sg:city":"Bay City",
    "sg:classifiers":[
        {
            "category":"Professional",
            "subcategory":"Business Services",
            "type":"Services"
        }
    ],
    "sg:phone":"+1 979 245 8929",
    "sg:postcode":"77414",
    "sg:province":"TX",
    "sg:tags":[
        "convention",
        "meeting",
        "facility"
    ],
    "wof:name":"Service Center",
    "wof:placetype":"venue"
},
  "geometry": {"coordinates":[-95.96150299999999,28.98321],"type":"Point"}
}