{
  "type": "Feature",
  "properties": {
    "iso:country":"US",
    "sg:address":"4301 Spindletree Ln",
    "sg:city":"Fort Worth",
    "sg:classifiers":[
        {
            "category":"Manufacturing",
            "subcategory":"Rubber & Plastics",
            "type":"Manufacturing & Wholesale Goods"
        }
    ],
    "sg:phone":"+1 817 232 8933",
    "sg:postcode":"76137",
    "sg:province":"TX",
    "sg:tags":[
        "product",
        "mfg"
    ],
    "wof:name":"R&S Investments",
    "wof:placetype":"venue"
},
  "geometry": {"coordinates":[-97.29264499999999,32.878963],"type":"Point"}
}