{
  "type": "Feature",
  "properties": {
    "iso:country":"US",
    "sg:address":"732 N Wills St",
    "sg:city":"Wills Point",
    "sg:classifiers":[
        {
            "category":"Retail",
            "subcategory":"Auto Repair",
            "type":"Services"
        }
    ],
    "sg:phone":"+1 903 873 5555",
    "sg:postcode":"75169",
    "sg:province":"TX",
    "sg:tags":[
        "repairing",
        "automobile"
    ],
    "wof:name":"Brother In Laws Svc Ctr",
    "wof:placetype":"venue"
},
  "geometry": {"coordinates":[-96.010554,32.715802],"type":"Point"}
}