{
  "type": "Feature",
  "properties": {
    "iso:country":"US",
    "sg:address":"601 Cypress Station Dr",
    "sg:city":"Houston",
    "sg:classifiers":[
        {
            "category":"Real Estate",
            "subcategory":"Real Estate Operator",
            "type":"Services"
        }
    ],
    "sg:phone":"+1 281 537 5863",
    "sg:postcode":"77090",
    "sg:province":"TX",
    "sg:tags":[
        "town",
        "house",
        "complex",
        "apt"
    ],
    "wof:name":"Roundhill Townhomes",
    "wof:placetype":"venue"
},
  "geometry": {"coordinates":[-95.43966899999999,30.031345],"type":"Point"}
}