{
  "type": "Feature",
  "properties": {
    "iso:country":"US",
    "sg:address":"7500 Glenview Dr",
    "sg:city":"Richland Hills",
    "sg:classifiers":[
        {
            "category":"Professional",
            "subcategory":"Engineering",
            "type":"Services"
        }
    ],
    "sg:phone":"+1 817 281 4411",
    "sg:postcode":"76180",
    "sg:province":"TX",
    "sg:tags":[
        "engineer"
    ],
    "sg:website":"www.mep-engineers.net",
    "wof:name":"MEP Consulting Engineers",
    "wof:placetype":"venue"
},
  "geometry": {"coordinates":[-97.21558400000001,32.823783],"type":"Point"}
}