{
  "type": "Feature",
  "properties": {
    "iso:country":"US",
    "sg:address":"410 Early Blvd",
    "sg:city":"Brownwood",
    "sg:classifiers":[
        {
            "category":"Manufacturing",
            "subcategory":"Tools & Machinery",
            "type":"Manufacturing & Wholesale Goods"
        }
    ],
    "sg:phone":"+1 325 646 6635",
    "sg:postcode":"76802",
    "sg:province":"TX",
    "sg:tags":[
        "mfg",
        "equipment",
        "industrial",
        "vehicle",
        "space"
    ],
    "wof:name":"Rodgers Machining",
    "wof:placetype":"venue"
},
  "geometry": {"coordinates":[-98.95781599999999,31.737419],"type":"Point"}
}