{
  "type": "Feature",
  "properties": {
    "iso:country":"US",
    "sg:address":"6405 Wallace Cove",
    "sg:city":"Austin",
    "sg:classifiers":[
        {
            "category":"Wholesale",
            "subcategory":"Medical Equipment & Supplies",
            "type":"Manufacturing & Wholesale Goods"
        }
    ],
    "sg:phone":"+1 512 502 1036",
    "sg:postcode":"78750",
    "sg:province":"TX",
    "wof:name":"Robert Warren LLC",
    "wof:placetype":"venue"
},
  "geometry": {"coordinates":[-97.79143500000001,30.37351],"type":"Point"}
}