{
  "type": "Feature",
  "properties": {
    "iso:country":"US",
    "sg:address":"1702 Austin St",
    "sg:city":"San Angelo",
    "sg:classifiers":[
        {
            "category":"Building & Trades",
            "subcategory":"Electrical",
            "type":"Services"
        }
    ],
    "sg:phone":"+1 325 655 3927",
    "sg:postcode":"76903",
    "sg:province":"TX",
    "sg:tags":[
        "electrical",
        "electric",
        "contractor"
    ],
    "wof:name":"Burklund Electric Co",
    "wof:placetype":"venue"
},
  "geometry": {"coordinates":[-100.444672,31.442855],"type":"Point"}
}