{
  "type": "Feature",
  "properties": {
    "iso:country":"US",
    "sg:address":"2908 76th St",
    "sg:city":"Lubbock",
    "sg:classifiers":[
        {
            "category":"Shopping",
            "subcategory":"Beauty & Cosmetics",
            "type":"Retail Goods"
        }
    ],
    "sg:phone":"+1 806 745 1957",
    "sg:postcode":"79423",
    "sg:province":"TX",
    "sg:tags":[
        "merchandise"
    ],
    "wof:name":"Mary Kay Consmetics",
    "wof:placetype":"venue"
},
  "geometry": {"coordinates":[-101.87894900000001,33.524865],"type":"Point"}
}