{
  "type": "Feature",
  "properties": {
    "iso:country":"US",
    "sg:address":"16990 Dallas Pkwy",
    "sg:city":"Dallas",
    "sg:classifiers":[
        {
            "category":"Personal",
            "subcategory":"Nail Salon",
            "type":"Services"
        }
    ],
    "sg:phone":"+1 972 248 3300",
    "sg:postcode":"75248",
    "sg:province":"TX",
    "wof:name":"Polished",
    "wof:placetype":"venue"
},
  "geometry": {"coordinates":[-96.827969,32.979501],"type":"Point"}
}