{
  "type": "Feature",
  "properties": {
    "iso:country":"US",
    "sg:address":"7811 N Shepherd Dr",
    "sg:city":"Houston",
    "sg:classifiers":[
        {
            "category":"Wholesale",
            "subcategory":"Home Furnishings",
            "type":"Manufacturing & Wholesale Goods"
        }
    ],
    "sg:phone":"+1 281 820 2150",
    "sg:postcode":"77088",
    "sg:province":"TX",
    "sg:tags":[
        "floor",
        "covering"
    ],
    "wof:name":"Eurolaminates LP",
    "wof:placetype":"venue"
},
  "geometry": {"coordinates":[-95.412763,29.87058],"type":"Point"}
}