{
  "type": "Feature",
  "properties": {
    "iso:country":"US",
    "sg:address":"6200 Broadway St",
    "sg:city":"Pearland",
    "sg:phone":"+1 281 997 2499",
    "sg:postcode":"77581",
    "sg:province":"TX",
    "wof:name":"L P Nails",
    "wof:placetype":"venue"
},
  "geometry": {"coordinates":[-95.31579600000001,29.559427],"type":"Point"}
}