{
  "type": "Feature",
  "properties": {
    "iso:country":"US",
    "sg:address":"1252 N Britain Rd",
    "sg:city":"Irving",
    "sg:classifiers":[
        {
            "category":"Wholesale",
            "subcategory":"Non-durable Goods",
            "type":"Manufacturing & Wholesale Goods"
        }
    ],
    "sg:phone":"+1 972 554 7620",
    "sg:postcode":"75061",
    "sg:province":"TX",
    "wof:name":"Kj Trading",
    "wof:placetype":"venue"
},
  "geometry": {"coordinates":[-96.94234899999999,32.825128],"type":"Point"}
}