{
  "type": "Feature",
  "properties": {
    "iso:country":"US",
    "sg:address":"712 N Washington Street",
    "sg:city":"Dallas",
    "sg:classifiers":[
        {
            "category":"Community Center",
            "type":"Public Place"
        }
    ],
    "sg:phone":"+1 214 515 0016",
    "sg:postcode":"75246",
    "sg:province":"TX",
    "sg:tags":[
        "resonance",
        "medical",
        "magnetic",
        "imaging",
        "mri"
    ],
    "sg:website":"www.ahicenters.com/home_dallas.htm",
    "wof:name":"American Health Imaging of Dallas",
    "wof:placetype":"venue"
},
  "geometry": {"coordinates":[-96.778051,32.791583],"type":"Point"}
}