{
  "type": "Feature",
  "properties": {
    "iso:country":"US",
    "sg:address":"1407 Cardinal St",
    "sg:city":"Nacogdoches",
    "sg:classifiers":[
        {
            "category":"Banks & Credit Unions",
            "subcategory":"Bank",
            "type":"Services"
        }
    ],
    "sg:phone":"+1 936 564 0458",
    "sg:postcode":"75961",
    "sg:province":"TX",
    "sg:tags":[
        "federal"
    ],
    "wof:name":"East Texas Professional Cr Un",
    "wof:placetype":"venue"
},
  "geometry": {"coordinates":[-94.635891,31.618483],"type":"Point"}
}