{
  "type": "Feature",
  "properties": {
    "iso:country":"US",
    "sg:address":"4200 Research Forest Dr",
    "sg:city":"Spring",
    "sg:classifiers":[
        {
            "category":"Insurance",
            "subcategory":"Insurance Agent",
            "type":"Services"
        }
    ],
    "sg:phone":"+1 281 292 2882",
    "sg:postcode":"77381",
    "sg:province":"TX",
    "wof:name":"Graylesscannon Insurance Group",
    "wof:placetype":"venue"
},
  "geometry": {"coordinates":[-95.49366000000001,30.194576],"type":"Point"}
}