{
  "type": "Feature",
  "properties": {
    "iso:country":"US",
    "sg:address":"704 E Central Pkwy",
    "sg:city":"Plano",
    "sg:classifiers":[
        {
            "category":"Social Services",
            "subcategory":"Child Care",
            "type":"Services"
        }
    ],
    "sg:phone":"+1 972 881 1900",
    "sg:postcode":"75074",
    "sg:province":"TX",
    "sg:tags":[
        "center"
    ],
    "sg:website":"www.childrenschoice.com",
    "wof:name":"Children's Choice Learning Ctr",
    "wof:placetype":"venue"
},
  "geometry": {"coordinates":[-96.706481,33.027348],"type":"Point"}
}