{
  "type": "Feature",
  "properties": {
    "iso:country":"US",
    "sg:address":"256 Kitty Hawk Rd",
    "sg:city":"Universal City",
    "sg:classifiers":[
        {
            "category":"Building & Trades",
            "subcategory":"Construction",
            "type":"Services"
        }
    ],
    "sg:phone":"+1 210 658 5364",
    "sg:postcode":"78148",
    "sg:province":"TX",
    "sg:tags":[
        "marking",
        "maintenance",
        "parking"
    ],
    "wof:name":"Universal City Public Works",
    "wof:placetype":"venue"
},
  "geometry": {"coordinates":[-98.301636,29.554915],"type":"Point"}
}