{
  "type": "Feature",
  "properties": {
    "iso:country":"US",
    "sg:address":"2504 Richmond Rd",
    "sg:city":"Texarkana",
    "sg:classifiers":[
        {
            "category":"Restaurant",
            "type":"Food & Drink"
        }
    ],
    "sg:phone":"+1 903 832 3036",
    "sg:postcode":"75503",
    "sg:province":"TX",
    "wof:name":"Bob's Smoke House",
    "wof:placetype":"venue"
},
  "geometry": {"coordinates":[-94.08924500000001,33.459018],"type":"Point"}
}