{
  "type": "Feature",
  "properties": {
    "iso:country":"US",
    "sg:address":"8425 Ley Rd",
    "sg:city":"Houston",
    "sg:classifiers":[
        {
            "category":"Freight",
            "type":"Transportation"
        }
    ],
    "sg:phone":"+1 713 491 0107",
    "sg:postcode":"77028",
    "sg:province":"TX",
    "wof:name":"Kmj Transportation Inc",
    "wof:placetype":"venue"
},
  "geometry": {"coordinates":[-95.270653,29.831518],"type":"Point"}
}