{
  "type": "Feature",
  "properties": {
    "iso:country":"US",
    "sg:address":"3206 Purdue Dr",
    "sg:city":"Corsicana",
    "sg:classifiers":[
        {
            "category":"Building & Trades",
            "subcategory":"Electrical",
            "type":"Services"
        }
    ],
    "sg:phone":"+1 903 872 1259",
    "sg:postcode":"75110",
    "sg:province":"TX",
    "sg:tags":[
        "electric",
        "contractor"
    ],
    "wof:name":"Bill Ratliff Electric",
    "wof:placetype":"venue"
},
  "geometry": {"coordinates":[-96.48370300000001,32.119388],"type":"Point"}
}