{
  "type": "Feature",
  "properties": {
    "iso:country":"US",
    "sg:address":"2912 Hickory",
    "sg:city":"Nederland",
    "sg:classifiers":[
        {
            "category":"Home & Garden",
            "subcategory":"Building Materials",
            "type":"Retail Goods"
        },
        {
            "category":"Professional",
            "subcategory":"Management & Consulting",
            "type":"Services"
        }
    ],
    "sg:phone":"+1 409 727 1720",
    "sg:postcode":"77627",
    "sg:province":"TX",
    "sg:tags":[
        "nonresidential",
        "screen",
        "sales",
        "direct",
        "window",
        "construction"
    ],
    "wof:name":"Collazo Aluminum Co",
    "wof:placetype":"venue"
},
  "geometry": {"coordinates":[-94.022066,29.981863],"type":"Point"}
}