{
  "type": "Feature",
  "properties": {
    "iso:country":"US",
    "sg:address":"4727 Timco W",
    "sg:city":"San Antonio",
    "sg:classifiers":[
        {
            "category":"Retail",
            "subcategory":"Auto Repair",
            "type":"Services"
        }
    ],
    "sg:phone":"+1 210 680 4328",
    "sg:postcode":"78238",
    "sg:province":"TX",
    "sg:tags":[
        "general"
    ],
    "wof:name":"Auto Works",
    "wof:placetype":"venue"
},
  "geometry": {"coordinates":[-98.595311,29.480215],"type":"Point"}
}