{
  "type": "Feature",
  "properties": {
    "iso:country":"US",
    "sg:address":"1326 Pennygent Ln",
    "sg:city":"Channelview",
    "sg:classifiers":[
        {
            "category":"Professional",
            "type":"Services"
        }
    ],
    "sg:phone":"+1 281 452 1771",
    "sg:postcode":"77530",
    "sg:province":"TX",
    "sg:tags":[
        "establishment"
    ],
    "wof:name":"Kattmn Millenia Productions",
    "wof:placetype":"venue"
},
  "geometry": {"coordinates":[-95.151635,29.800289],"type":"Point"}
}