{
  "type": "Feature",
  "properties": {
    "iso:country":"US",
    "sg:address":"1017 E Kingsbury St",
    "sg:city":"Seguin",
    "sg:classifiers":[
        {
            "category":"Health Services",
            "subcategory":"Doctor",
            "type":"Services"
        }
    ],
    "sg:phone":"+1 830 379 3248",
    "sg:postcode":"78155",
    "sg:province":"TX",
    "sg:tags":[
        "clinic"
    ],
    "wof:name":"Richardson Chiropractic Clinic",
    "wof:placetype":"venue"
},
  "geometry": {"coordinates":[-97.95155,29.580921],"type":"Point"}
}