{
  "type": "Feature",
  "properties": {
    "iso:country":"US",
    "sg:address":"8519 Cornwall Dr",
    "sg:city":"Austin",
    "sg:classifiers":[
        {
            "category":"Professional",
            "subcategory":"Computer Services",
            "type":"Services"
        }
    ],
    "sg:phone":"+1 512 282 9479",
    "sg:postcode":"78748",
    "sg:province":"TX",
    "sg:tags":[
        "repair",
        "programing",
        "custom"
    ],
    "wof:name":"Ed Berg Computer Consulting",
    "wof:placetype":"venue"
},
  "geometry": {"coordinates":[-97.798435,30.178301],"type":"Point"}
}