{
  "type": "Feature",
  "properties": {
    "iso:country":"US",
    "sg:address":"1345 Conant St",
    "sg:city":"Dallas",
    "sg:classifiers":[
        {
            "category":"Professional",
            "subcategory":"Art Services",
            "type":"Services"
        }
    ],
    "sg:phone":"+1 214 749 4966",
    "sg:postcode":"75207",
    "sg:province":"TX",
    "sg:tags":[
        "photographer"
    ],
    "sg:website":"www.roycrane.com",
    "wof:name":"Roy Crane Studios",
    "wof:placetype":"venue"
},
  "geometry": {"coordinates":[-96.837664,32.800375],"type":"Point"}
}