{
  "type": "Feature",
  "properties": {
    "iso:country":"US",
    "sg:address":"609 NW 14th St",
    "sg:city":"Andrews",
    "sg:classifiers":[
        {
            "category":"Professional",
            "subcategory":"Lawyer & Legal Services",
            "type":"Services"
        }
    ],
    "sg:phone":"+1 432 523 3176",
    "sg:postcode":"79714",
    "sg:province":"TX",
    "wof:name":"McCullough Trial Mgmnt",
    "wof:placetype":"venue"
},
  "geometry": {"coordinates":[-102.56520399999999,32.320125],"type":"Point"}
}