{
  "type": "Feature",
  "properties": {
    "iso:country":"US",
    "sg:address":"3060 Olmos Creek Dr",
    "sg:city":"San Antonio",
    "sg:classifiers":[
        {
            "category":"Social Services",
            "subcategory":"Child Care",
            "type":"Services"
        }
    ],
    "sg:phone":"+1 210 651 3138",
    "sg:postcode":"78230",
    "sg:province":"TX",
    "wof:name":"Joyland Christian Learning Ctr",
    "wof:placetype":"venue"
},
  "geometry": {"coordinates":[-98.546153,29.571578],"type":"Point"}
}