{
  "type": "Feature",
  "properties": {
    "iso:country":"US",
    "sg:address":"111 E 3rd St",
    "sg:city":"Arlington",
    "sg:classifiers":[
        {
            "category":"Education",
            "subcategory":"Special Training",
            "type":"Public Place"
        }
    ],
    "sg:phone":"+1 817 461 4284",
    "sg:postcode":"76010",
    "sg:province":"TX",
    "wof:name":"Rainbow of Hope Academy",
    "wof:placetype":"venue"
},
  "geometry": {"coordinates":[-97.106177,32.730168],"type":"Point"}
}