{
  "type": "Feature",
  "properties": {
    "iso:country":"US",
    "sg:address":"309 NW Renfro St",
    "sg:city":"Burleson",
    "sg:classifiers":[
        {
            "category":"Manufacturing",
            "subcategory":"Metals",
            "type":"Manufacturing & Wholesale Goods"
        }
    ],
    "sg:phone":"+1 817 295 3391",
    "sg:postcode":"76028",
    "sg:province":"TX",
    "wof:name":"Flair Trophy & Awards",
    "wof:placetype":"venue"
},
  "geometry": {"coordinates":[-97.327918,32.545507],"type":"Point"}
}