{
  "type": "Feature",
  "properties": {
    "iso:country":"US",
    "sg:address":"17603 Hamilwood Dr",
    "sg:city":"Houston",
    "sg:classifiers":[
        {
            "category":"Wholesale",
            "subcategory":"Electrical",
            "type":"Manufacturing & Wholesale Goods"
        }
    ],
    "sg:phone":"+1 281 858 8599",
    "sg:postcode":"77095",
    "sg:province":"TX",
    "sg:tags":[
        "equipment"
    ],
    "wof:name":"Tri Star Security",
    "wof:placetype":"venue"
},
  "geometry": {"coordinates":[-95.67684199999999,29.887358],"type":"Point"}
}