{
  "type": "Feature",
  "properties": {
    "iso:country":"US",
    "sg:address":"9120 Bellflower St",
    "sg:city":"Houston",
    "sg:classifiers":[
        {
            "category":"Building & Trades",
            "subcategory":"Construction",
            "type":"Services"
        }
    ],
    "sg:phone":"+1 713 977 0446",
    "sg:postcode":"77063",
    "sg:province":"TX",
    "sg:tags":[
        "contractor"
    ],
    "wof:name":"Design By Oscar",
    "wof:placetype":"venue"
},
  "geometry": {"coordinates":[-95.523899,29.726887],"type":"Point"}
}