{
  "type": "Feature",
  "properties": {
    "iso:country":"US",
    "sg:address":"196 County Road 1329",
    "sg:city":"Texarkana",
    "sg:phone":"+1 903 791 9518",
    "sg:postcode":"75501",
    "sg:province":"TX",
    "wof:name":"Mr B's Salvage",
    "wof:placetype":"venue"
},
  "geometry": {"coordinates":[-94.13574199999999,33.409096],"type":"Point"}
}