{
  "type": "Feature",
  "properties": {
    "iso:country":"US",
    "sg:address":"635 Westport Pkwy",
    "sg:city":"Grapevine",
    "sg:classifiers":[
        {
            "category":"Professional",
            "subcategory":"Business Services",
            "type":"Services"
        }
    ],
    "sg:phone":"+1 817 251 1508",
    "sg:postcode":"76051",
    "sg:province":"TX",
    "sg:tags":[
        "water",
        "treatment"
    ],
    "wof:name":"Chem Cal Inc",
    "wof:placetype":"venue"
},
  "geometry": {"coordinates":[-97.09237,32.905062],"type":"Point"}
}