{
  "type": "Feature",
  "properties": {
    "iso:country":"US",
    "sg:address":"2600 Twisted Oak Dr",
    "sg:city":"Brenham",
    "sg:classifiers":[
        {
            "category":"Communications",
            "subcategory":"Radio Station",
            "type":"Services"
        }
    ],
    "sg:phone":"+1 979 830 8335",
    "sg:postcode":"77833",
    "sg:province":"TX",
    "sg:tags":[
        "broadcast"
    ],
    "wof:name":"May Broadcasting Inc",
    "wof:placetype":"venue"
},
  "geometry": {"coordinates":[-96.40313999999999,30.190223],"type":"Point"}
}