{
  "type": "Feature",
  "properties": {
    "iso:country":"US",
    "sg:address":"1712 W. 18th St",
    "sg:city":"Houston",
    "sg:classifiers":[
        {
            "category":"Personal",
            "subcategory":"Beauty Salon",
            "type":"Services"
        }
    ],
    "sg:phone":"+1 713 864 2019",
    "sg:postcode":"77008",
    "sg:province":"TX",
    "sg:tags":[
        "hair"
    ],
    "wof:name":"J N Hair Salon",
    "wof:placetype":"venue"
},
  "geometry": {"coordinates":[-95.42995500000001,29.801547],"type":"Point"}
}