{
  "type": "Feature",
  "properties": {
    "iso:country":"US",
    "sg:address":"13913 Kershaw St",
    "sg:city":"Houston",
    "sg:classifiers":[
        {
            "category":"Wholesale",
            "subcategory":"Construction Materials",
            "type":"Manufacturing & Wholesale Goods"
        }
    ],
    "sg:phone":"+1 281 448 6200",
    "sg:postcode":"77037",
    "sg:province":"TX",
    "sg:tags":[
        "pallet",
        "skid"
    ],
    "wof:name":"Guzman Pallet Co",
    "wof:placetype":"venue"
},
  "geometry": {"coordinates":[-95.38957600000001,29.901869],"type":"Point"}
}