{
  "type": "Feature",
  "properties": {
    "iso:country":"US",
    "sg:address":"1601 W 5th St",
    "sg:city":"Austin",
    "sg:classifiers":[
        {
            "category":"Travel",
            "subcategory":"Travel Agent",
            "type":"Entertainment"
        }
    ],
    "sg:phone":"+1 512 904 7354",
    "sg:postcode":"78703",
    "sg:province":"TX",
    "sg:tags":[
        "agency",
        "services-commercial"
    ],
    "wof:name":"Andrew Harper Travel Inc",
    "wof:placetype":"venue"
},
  "geometry": {"coordinates":[-97.763397,30.273741],"type":"Point"}
}