{
  "type": "Feature",
  "properties": {
    "iso:country":"US",
    "sg:address":"4836 Garth Rd",
    "sg:city":"Baytown",
    "sg:classifiers":[
        {
            "category":"Health Services",
            "subcategory":"Clinic",
            "type":"Services"
        }
    ],
    "sg:phone":"+1 281 422 3794",
    "sg:postcode":"77521",
    "sg:province":"TX",
    "sg:tags":[
        "kidney",
        "dialysis",
        "center"
    ],
    "wof:name":"Baytown Dialysis Center 1256",
    "wof:placetype":"venue"
},
  "geometry": {"coordinates":[-94.97763999999999,29.774376],"type":"Point"}
}