{
  "type": "Feature",
  "properties": {
    "iso:country":"US",
    "sg:address":"6009 Richmond Ave",
    "sg:city":"Houston",
    "sg:classifiers":[
        {
            "category":"Shopping",
            "subcategory":"Computers & Home Electronics",
            "type":"Retail Goods"
        }
    ],
    "sg:phone":"+1 713 339 2900",
    "sg:postcode":"77057",
    "sg:province":"TX",
    "sg:tags":[
        "equipment"
    ],
    "wof:name":"Houston Texas Computer Outlet",
    "wof:placetype":"venue"
},
  "geometry": {"coordinates":[-95.484695,29.731459],"type":"Point"}
}