{
  "type": "Feature",
  "properties": {
    "iso:country":"US",
    "sg:address":"3004 Spr 325",
    "sg:city":"Wichita Falls",
    "sg:classifiers":[
        {
            "category":"Restaurant",
            "type":"Food & Drink"
        }
    ],
    "sg:phone":"+1 940 855 5931",
    "sg:postcode":"76306",
    "sg:province":"TX",
    "wof:name":"House Of Bamboo Restaurant",
    "wof:placetype":"venue"
},
  "geometry": {"coordinates":[-98.514979,33.953466],"type":"Point"}
}