{
  "type": "Feature",
  "properties": {
    "iso:country":"US",
    "sg:address":"702 E Crestwood Dr",
    "sg:city":"Victoria",
    "sg:classifiers":[
        {
            "category":"Wholesale",
            "subcategory":"Vending Machines",
            "type":"Manufacturing & Wholesale Goods"
        }
    ],
    "sg:phone":"+1 361 575 5364",
    "sg:postcode":"77901",
    "sg:province":"TX",
    "wof:name":"Stroud's Vending Co",
    "wof:placetype":"venue"
},
  "geometry": {"coordinates":[-96.997361,28.828259],"type":"Point"}
}