{
  "type": "Feature",
  "properties": {
    "iso:country":"US",
    "sg:address":"501 E Nevada St",
    "sg:city":"Seymour",
    "sg:classifiers":[
        {
            "category":"Real Estate",
            "subcategory":"Real Estate Agent",
            "type":"Services"
        }
    ],
    "sg:phone":"+1 940 888 5495",
    "sg:postcode":"76380",
    "sg:province":"TX",
    "sg:tags":[
        "agency",
        "rental"
    ],
    "wof:name":"Wallace Wrecker & Rentals",
    "wof:placetype":"venue"
},
  "geometry": {"coordinates":[-99.25660499999999,33.592195],"type":"Point"}
}