{
  "type": "Feature",
  "properties": {
    "iso:country":"US",
    "sg:address":"2020 Spacek Rd",
    "sg:city":"Richmond",
    "sg:classifiers":[
        {
            "category":"Manufacturing",
            "subcategory":"Apparel",
            "type":"Manufacturing & Wholesale Goods"
        }
    ],
    "sg:phone":"+1 281 341 9090",
    "sg:postcode":"77469",
    "sg:province":"TX",
    "sg:tags":[
        "canvas",
        "product",
        "related"
    ],
    "wof:name":"Martha's Canvas",
    "wof:placetype":"venue"
},
  "geometry": {"coordinates":[-95.75781499999999,29.534953],"type":"Point"}
}