{
  "type": "Feature",
  "properties": {
    "iso:country":"US",
    "sg:address":"333 Earl Garrett St",
    "sg:city":"Kerrville",
    "sg:classifiers":[
        {
            "category":"Social Services",
            "type":"Services"
        }
    ],
    "sg:phone":"+1 830 257 4677",
    "sg:postcode":"78028",
    "sg:province":"TX",
    "sg:tags":[
        "organization",
        "welfare"
    ],
    "wof:name":"American Red Cross",
    "wof:placetype":"venue"
},
  "geometry": {"coordinates":[-99.13833099999999,30.047428],"type":"Point"}
}