{
  "type": "Feature",
  "properties": {
    "iso:country":"US",
    "sg:address":"2204 Bennington Ave",
    "sg:city":"Flower Mound",
    "sg:classifiers":[
        {
            "category":"Professional",
            "subcategory":"Business Services",
            "type":"Services"
        }
    ],
    "sg:phone":"+1 972 355 3496",
    "sg:postcode":"75028",
    "sg:province":"TX",
    "wof:name":"Syntec Engineering Group Inc",
    "wof:placetype":"venue"
},
  "geometry": {"coordinates":[-97.061099,33.017242],"type":"Point"}
}