{
  "type": "Feature",
  "properties": {
    "iso:country":"US",
    "sg:address":"6161 Doniphan Dr",
    "sg:city":"El Paso",
    "sg:classifiers":[
        {
            "category":"Wholesale",
            "subcategory":"Machinery & Supplies",
            "type":"Manufacturing & Wholesale Goods"
        }
    ],
    "sg:phone":"+1 915 581 2406",
    "sg:postcode":"79932",
    "sg:province":"TX",
    "sg:tags":[
        "equipment",
        "establishment"
    ],
    "wof:name":"Sound Master",
    "wof:placetype":"venue"
},
  "geometry": {"coordinates":[-106.591959,31.872736],"type":"Point"}
}