{
  "type": "Feature",
  "properties": {
    "iso:country":"US",
    "sg:address":"614 E University Ave",
    "sg:city":"Georgetown",
    "sg:classifiers":[
        {
            "category":"Manufacturing",
            "subcategory":"Electronics",
            "type":"Manufacturing & Wholesale Goods"
        }
    ],
    "sg:phone":"+1 512 863 4657",
    "sg:postcode":"78626",
    "sg:province":"TX",
    "sg:tags":[
        "mfg",
        "boards",
        "circuit",
        "printed"
    ],
    "wof:name":"Georgetown Circuits Corp",
    "wof:placetype":"venue"
},
  "geometry": {"coordinates":[-97.671725,30.633232],"type":"Point"}
}