{
  "type": "Feature",
  "properties": {
    "iso:country":"US",
    "sg:address":"102 E 1st St",
    "sg:city":"Cameron",
    "sg:classifiers":[
        {
            "category":"Organizations",
            "subcategory":"Professional Association",
            "type":"Services"
        }
    ],
    "sg:phone":"+1 254 697 4979",
    "sg:postcode":"76520",
    "sg:province":"TX",
    "sg:tags":[
        "chambers",
        "commerce"
    ],
    "wof:name":"Chamber Of Commerce",
    "wof:placetype":"venue"
},
  "geometry": {"coordinates":[-96.97639100000001,30.850597],"type":"Point"}
}