{
  "type": "Feature",
  "properties": {
    "iso:country":"US",
    "sg:address":"471 N Harbin Dr",
    "sg:city":"Stephenville",
    "sg:classifiers":[
        {
            "category":"Manufacturing",
            "subcategory":"Printing",
            "type":"Manufacturing & Wholesale Goods"
        }
    ],
    "sg:phone":"+1 254 965 2255",
    "sg:postcode":"76401",
    "sg:province":"TX",
    "sg:tags":[
        "dealers-wholesale",
        "news",
        "newspaper"
    ],
    "sg:website":"http://www.texasdairy.com",
    "wof:name":"Texas Diary Review",
    "wof:placetype":"venue"
},
  "geometry": {"coordinates":[-98.22383499999999,32.212747],"type":"Point"}
}