{
  "type": "Feature",
  "properties": {
    "iso:country":"US",
    "sg:address":"1016 W Airport Fwy",
    "sg:city":"Irving",
    "sg:classifiers":[
        {
            "category":"Autos & Motor Vehicles",
            "subcategory":"Fuel & Gas Station",
            "type":"Retail Goods"
        }
    ],
    "sg:phone":"+1 972 438 9433",
    "sg:postcode":"75062",
    "sg:province":"TX",
    "sg:website":"www.chevron.com",
    "wof:name":"Chevron Products",
    "wof:placetype":"venue"
},
  "geometry": {"coordinates":[-96.95869399999999,32.836335],"type":"Point"}
}