{
  "type": "Feature",
  "properties": {
    "iso:country":"US",
    "sg:address":"6753 Buenos Aires Dr",
    "sg:city":"N Richland Hills",
    "sg:classifiers":[
        {
            "category":"Wholesale",
            "subcategory":"Vending Machines",
            "type":"Manufacturing & Wholesale Goods"
        }
    ],
    "sg:phone":"+1 817 498 8977",
    "sg:postcode":"76180",
    "sg:province":"TX",
    "wof:name":"Gardner's Goodies",
    "wof:placetype":"venue"
},
  "geometry": {"coordinates":[-97.238635,32.847763],"type":"Point"}
}