{
  "type": "Feature",
  "properties": {
    "iso:country":"US",
    "sg:address":"2345 Cardinal Ln",
    "sg:city":"Garland",
    "sg:classifiers":[
        {
            "category":"Building & Trades",
            "subcategory":"Construction",
            "type":"Services"
        }
    ],
    "sg:phone":"+1 972 494 3060",
    "sg:postcode":"75042",
    "sg:province":"TX",
    "sg:tags":[
        "housing"
    ],
    "wof:name":"Lgk Gifts/Novelties",
    "wof:placetype":"venue"
},
  "geometry": {"coordinates":[-96.66274300000001,32.903856],"type":"Point"}
}