{
  "type": "Feature",
  "properties": {
    "iso:country":"US",
    "sg:address":"4025 Maple Ave",
    "sg:city":"Dallas",
    "sg:classifiers":[
        {
            "category":"Bars & Pubs",
            "type":"Food & Drink"
        }
    ],
    "sg:phone":"+1 214 526 0887",
    "sg:postcode":"75295",
    "sg:province":"TX",
    "sg:tags":[
        "drinking",
        "gay"
    ],
    "sg:website":"www.buddiesii.com",
    "wof:name":"Buddies II",
    "wof:placetype":"venue"
},
  "geometry": {"coordinates":[-96.816299,32.806],"type":"Point"}
}