{
  "type": "Feature",
  "properties": {
    "iso:country":"US",
    "sg:address":"3609 Vandervoort Dr",
    "sg:city":"Dallas",
    "sg:classifiers":[
        {
            "category":"Shopping",
            "type":"Retail Goods"
        }
    ],
    "sg:phone":"+1 214 371 0083",
    "sg:postcode":"75216",
    "sg:province":"TX",
    "sg:tags":[
        "refinishing",
        "furniture"
    ],
    "wof:name":"Galvan Utilities",
    "wof:placetype":"venue"
},
  "geometry": {"coordinates":[-96.766547,32.719128],"type":"Point"}
}