{
  "type": "Feature",
  "properties": {
    "iso:country":"US",
    "sg:address":"3405 Milton Ave Ste 210",
    "sg:city":"Dallas",
    "sg:classifiers":[
        {
            "category":"Banks & Credit Unions",
            "subcategory":"Financial Services",
            "type":"Services"
        }
    ],
    "sg:phone":"+1 214 739 3332",
    "sg:postcode":"75205",
    "sg:province":"TX",
    "sg:tags":[
        "broker",
        "mortgage"
    ],
    "sg:website":"www.fitzgerald-mortgage.com",
    "wof:name":"Fitzgerald Mortgage",
    "wof:placetype":"venue"
},
  "geometry": {"coordinates":[-96.787069,32.848327],"type":"Point"}
}