{
  "type": "Feature",
  "properties": {
    "iso:country":"US",
    "sg:address":"4078 Westheimer Rd",
    "sg:city":"Houston",
    "sg:classifiers":[
        {
            "category":"Shopping",
            "subcategory":"Clothing, Apparel, & Fashions",
            "type":"Retail Goods"
        }
    ],
    "sg:phone":"+1 713 552 0333",
    "sg:postcode":"77098",
    "sg:province":"TX",
    "wof:name":"Billy Reid Inc",
    "wof:placetype":"venue"
},
  "geometry": {"coordinates":[-95.445486,29.7417],"type":"Point"}
}