{
  "type": "Feature",
  "properties": {
    "iso:country":"US",
    "sg:address":"1019 Friendship Ln",
    "sg:city":"Fredericksburg",
    "sg:classifiers":[
        {
            "category":"Real Estate",
            "subcategory":"Real Estate Operator",
            "type":"Services"
        }
    ],
    "sg:phone":"+1 830 990 0304",
    "sg:postcode":"78624",
    "sg:province":"TX",
    "sg:tags":[
        "building",
        "apartment"
    ],
    "wof:name":"Highland Oaks Apartments",
    "wof:placetype":"venue"
},
  "geometry": {"coordinates":[-98.85620900000001,30.256245],"type":"Point"}
}