{
  "type": "Feature",
  "properties": {
    "iso:country":"US",
    "sg:address":"4844 Whirlwind St",
    "sg:city":"San Antonio",
    "sg:classifiers":[
        {
            "category":"Wholesale",
            "subcategory":"Vending Machines",
            "type":"Manufacturing & Wholesale Goods"
        }
    ],
    "sg:phone":"+1 210 656 8804",
    "sg:postcode":"78217",
    "sg:province":"TX",
    "sg:tags":[
        "operator"
    ],
    "wof:name":"Java Jockey Vending Service Co",
    "wof:placetype":"venue"
},
  "geometry": {"coordinates":[-98.397474,29.529732],"type":"Point"}
}