{
  "type": "Feature",
  "properties": {
    "iso:country":"US",
    "sg:address":"1008 Hovey St",
    "sg:city":"Bridgeport",
    "sg:classifiers":[
        {
            "category":"Home & Garden",
            "subcategory":"Household Appliances",
            "type":"Retail Goods"
        }
    ],
    "sg:phone":"+1 940 683 4034",
    "sg:postcode":"76426",
    "sg:province":"TX",
    "sg:tags":[
        "lawn",
        "supply"
    ],
    "wof:name":"Ken's Appliances Lawn & Garden",
    "wof:placetype":"venue"
},
  "geometry": {"coordinates":[-97.754316,33.207673],"type":"Point"}
}