{
  "type": "Feature",
  "properties": {
    "iso:country":"US",
    "sg:address":"10040 Kinner Dr",
    "sg:city":"Mckinney",
    "sg:classifiers":[
        {
            "category":"Manufacturing",
            "subcategory":"Signs",
            "type":"Manufacturing & Wholesale Goods"
        }
    ],
    "sg:phone":"+1 972 346 3390",
    "sg:postcode":"75071",
    "sg:province":"TX",
    "sg:tags":[
        "advertising",
        "specialty"
    ],
    "wof:name":"DFW Sky Signs",
    "wof:placetype":"venue"
},
  "geometry": {"coordinates":[-96.74316399999999,33.208182],"type":"Point"}
}