{
  "type": "Feature",
  "properties": {
    "iso:country":"US",
    "sg:address":"410 S 4th St",
    "sg:city":"Alvin",
    "sg:classifiers":[
        {
            "category":"Organizations",
            "subcategory":"Religious Organization",
            "type":"Services"
        }
    ],
    "sg:phone":"+1 281 331 0670",
    "sg:postcode":"77511",
    "sg:province":"TX",
    "wof:name":"Apostolic Faith Church",
    "wof:placetype":"venue"
},
  "geometry": {"coordinates":[-95.257441,29.420806],"type":"Point"}
}