{
  "type": "Feature",
  "properties": {
    "iso:country":"US",
    "sg:address":"800 Sunland Park Dr",
    "sg:city":"El Paso",
    "sg:classifiers":[
        {
            "category":"Restaurant",
            "type":"Food & Drink"
        }
    ],
    "sg:menulink":"http://www.allmenus.com/tx/el-paso/127955-red-lobster/menu/",
    "sg:phone":"+1 915 833 5753",
    "sg:postcode":"79912",
    "sg:province":"TX",
    "sg:tags":[
        "seafood",
        "american"
    ],
    "wof:name":"Red Lobster",
    "wof:placetype":"venue"
},
  "geometry": {"coordinates":[-106.54680999999999,31.816329],"type":"Point"}
}