{
  "type": "Feature",
  "properties": {
    "iso:country":"US",
    "sg:address":"1009 E 40th St",
    "sg:city":"Austin",
    "sg:classifiers":[
        {
            "category":"Health Services",
            "subcategory":"Optometrist",
            "type":"Services"
        }
    ],
    "sg:phone":"+1 512 454 2020",
    "sg:postcode":"78751",
    "sg:province":"TX",
    "wof:name":"Wong Mitchell MD",
    "wof:placetype":"venue"
},
  "geometry": {"coordinates":[-97.72018799999999,30.297247],"type":"Point"}
}