{
  "type": "Feature",
  "properties": {
    "iso:country":"US",
    "sg:address":"1800 Good Shepherd Dr",
    "sg:city":"Brownwood",
    "sg:classifiers":[
        {
            "category":"Place Of Worship",
            "subcategory":"Church",
            "type":"Public Place"
        },
        {
            "category":"Place Of Worship",
            "type":"Public Place"
        },
        {
            "category":"Organizations",
            "subcategory":"Religious Organization",
            "type":"Services"
        }
    ],
    "sg:phone":"+1 325 646 8791",
    "sg:postcode":"76801",
    "sg:province":"TX",
    "sg:tags":[
        "churches-episcopal-anglican",
        "churches-episcopal"
    ],
    "wof:name":"Church Of The Good Shepherd",
    "wof:placetype":"venue"
},
  "geometry": {"coordinates":[-98.974496,31.691569],"type":"Point"}
}