{
  "type": "Feature",
  "properties": {
    "iso:country":"US",
    "sg:address":"1430 N Flores St",
    "sg:city":"San Antonio",
    "sg:classifiers":[
        {
            "category":"Professional",
            "subcategory":"Business Services",
            "type":"Services"
        },
        {
            "category":"Manufacturing",
            "subcategory":"Apparel",
            "type":"Manufacturing & Wholesale Goods"
        }
    ],
    "sg:phone":"+1 210 224 5504",
    "sg:postcode":"78212",
    "sg:province":"TX",
    "sg:tags":[
        "embroidery"
    ],
    "wof:name":"Hudson's Embroidery",
    "wof:placetype":"venue"
},
  "geometry": {"coordinates":[-98.503293,29.441025],"type":"Point"}
}