{
  "type": "Feature",
  "properties": {
    "iso:country":"US",
    "sg:address":"36019 Jennie Ln",
    "sg:city":"Pinehurst",
    "sg:classifiers":[
        {
            "category":"Autos & Motor Vehicles",
            "subcategory":"Recreational Vehicle Sales",
            "type":"Retail Goods"
        },
        {
            "category":"Retail",
            "subcategory":"Auto Repair",
            "type":"Services"
        }
    ],
    "sg:phone":"+1 281 259 2606",
    "sg:postcode":"77362",
    "sg:province":"TX",
    "sg:tags":[
        "antique",
        "automobile",
        "restoration-antique",
        "car",
        "classic"
    ],
    "wof:name":"Popular Concepts Inc",
    "wof:placetype":"venue"
},
  "geometry": {"coordinates":[-95.692268,30.184348],"type":"Point"}
}