{
  "type": "Feature",
  "properties": {
    "iso:country":"US",
    "sg:address":"8845 Leslie",
    "sg:city":"San Antonio",
    "sg:classifiers":[
        {
            "category":"Mining & Drilling",
            "type":"Manufacturing & Wholesale Goods"
        }
    ],
    "sg:phone":"+1 210 688 3413",
    "sg:postcode":"78254",
    "sg:province":"TX",
    "sg:tags":[
        "limestone",
        "crushed",
        "quarry"
    ],
    "wof:name":"Helotes Top Soil",
    "wof:placetype":"venue"
},
  "geometry": {"coordinates":[-98.692813,29.519541],"type":"Point"}
}