{
  "type": "Feature",
  "properties": {
    "iso:country":"US",
    "sg:address":"2525 SW Military Dr",
    "sg:city":"San Antonio",
    "sg:classifiers":[
        {
            "category":"Restaurant",
            "type":"Food & Drink"
        }
    ],
    "sg:phone":"+1 210 928 7300",
    "sg:postcode":"78224",
    "sg:province":"TX",
    "wof:name":"Coyote Canyon Steak Buffet",
    "wof:placetype":"venue"
},
  "geometry": {"coordinates":[-98.53599800000001,29.356717],"type":"Point"}
}