{
  "type": "Feature",
  "properties": {
    "iso:country":"US",
    "sg:address":"8920 US Hwy 87",
    "sg:city":"San Antonio",
    "sg:classifiers":[
        {
            "category":"Professional",
            "subcategory":"Accounting & Tax Preparation",
            "type":"Services"
        }
    ],
    "sg:phone":"+1 210 649 2935",
    "sg:postcode":"78263",
    "sg:province":"TX",
    "sg:tags":[
        "return",
        "filing"
    ],
    "wof:name":"Stanush Tax Svc",
    "wof:placetype":"venue"
},
  "geometry": {"coordinates":[-98.313709,29.379703],"type":"Point"}
}