{
  "type": "Feature",
  "properties": {
    "iso:country":"US",
    "sg:address":"604 E 4th St",
    "sg:city":"Georgetown",
    "sg:classifiers":[
        {
            "category":"Building & Trades",
            "subcategory":"Cleaning & Sanitation",
            "type":"Services"
        }
    ],
    "sg:phone":"+1 512 863 9020",
    "sg:postcode":"78626",
    "sg:province":"TX",
    "sg:tags":[
        "maintenance"
    ],
    "wof:name":"Absolute Cleaning Service",
    "wof:placetype":"venue"
},
  "geometry": {"coordinates":[-97.67214,30.639973],"type":"Point"}
}