{
  "type": "Feature",
  "properties": {
    "iso:country":"US",
    "sg:address":"9541 Mesa Dr",
    "sg:city":"Houston",
    "sg:classifiers":[
        {
            "category":"Bars & Pubs",
            "subcategory":"Nightclub",
            "type":"Food & Drink"
        }
    ],
    "sg:phone":"+1 713 631 0033",
    "sg:postcode":"77078",
    "sg:province":"TX",
    "sg:tags":[
        "nightlife"
    ],
    "wof:name":"Club Bmw",
    "wof:placetype":"venue"
},
  "geometry": {"coordinates":[-95.262497,29.850401],"type":"Point"}
}