{
  "type": "Feature",
  "properties": {
    "iso:country":"US",
    "sg:address":"6282 Willowgate Ln",
    "sg:city":"Dallas",
    "sg:classifiers":[
        {
            "category":"Professional",
            "subcategory":"Business Services",
            "type":"Services"
        }
    ],
    "sg:phone":"+1 972 661 5900",
    "sg:postcode":"75230",
    "sg:province":"TX",
    "sg:tags":[
        "interior",
        "consultant",
        "design",
        "decorator"
    ],
    "wof:name":"Theresa Alexander Design",
    "wof:placetype":"venue"
},
  "geometry": {"coordinates":[-96.797848,32.912993],"type":"Point"}
}