{
  "type": "Feature",
  "properties": {
    "iso:country":"US",
    "sg:address":"313 E Rundberg Ln Ste 207",
    "sg:city":"Austin",
    "sg:classifiers":[
        {
            "category":"Health Services",
            "subcategory":"Hospital",
            "type":"Services"
        }
    ],
    "sg:phone":"+1 512 653 9848",
    "sg:postcode":"78753",
    "sg:province":"TX",
    "sg:tags":[
        "equipment",
        "supply"
    ],
    "wof:name":"Goz Medical Supplies Inc",
    "wof:placetype":"venue"
},
  "geometry": {"coordinates":[-97.69179099999999,30.35996],"type":"Point"}
}