{
  "type": "Feature",
  "properties": {
    "iso:country":"US",
    "sg:address":"3919 Eastex Fwy",
    "sg:city":"Houston",
    "sg:classifiers":[
        {
            "category":"Manufacturing",
            "subcategory":"Chemicals & Compounds",
            "type":"Manufacturing & Wholesale Goods"
        }
    ],
    "sg:phone":"+1 713 224 3185",
    "sg:postcode":"77026",
    "sg:province":"TX",
    "sg:tags":[
        "rubber"
    ],
    "wof:name":"Universal Urethanes Inc",
    "wof:placetype":"venue"
},
  "geometry": {"coordinates":[-95.339974,29.804011],"type":"Point"}
}