{
  "type": "Feature",
  "properties": {
    "iso:country":"US",
    "sg:address":"643 Deer Country",
    "sg:city":"San Antonio",
    "sg:classifiers":[
        {
            "category":"Shopping",
            "subcategory":"Florist",
            "type":"Retail Goods"
        }
    ],
    "sg:phone":"+1 210 681 2890",
    "sg:postcode":"78253",
    "sg:province":"TX",
    "wof:name":"Rita Yung Txas Crtif Mstr Flor",
    "wof:placetype":"venue"
},
  "geometry": {"coordinates":[-98.76479500000001,29.430711],"type":"Point"}
}