{
  "type": "Feature",
  "properties": {
    "iso:country":"US",
    "sg:address":"2901 Chacota St",
    "sg:city":"Laredo",
    "sg:classifiers":[
        {
            "category":"Personal",
            "subcategory":"Beauty Salon",
            "type":"Services"
        }
    ],
    "sg:phone":"+1 956 723 8527",
    "sg:postcode":"78046",
    "sg:province":"TX",
    "sg:tags":[
        "shop"
    ],
    "wof:name":"Elsa's Beauty Salon",
    "wof:placetype":"venue"
},
  "geometry": {"coordinates":[-99.46535900000001,27.474055],"type":"Point"}
}