{
  "type": "Feature",
  "properties": {
    "iso:country":"US",
    "sg:address":"343 N Crisp St",
    "sg:city":"Uvalde",
    "sg:classifiers":[
        {
            "category":"Organizations",
            "subcategory":"Religious Organization",
            "type":"Services"
        }
    ],
    "sg:phone":"+1 830 278 6724",
    "sg:postcode":"78801",
    "sg:province":"TX",
    "wof:name":"Mary Lou Aldate",
    "wof:placetype":"venue"
},
  "geometry": {"coordinates":[-99.794484,29.213548],"type":"Point"}
}