{
  "type": "Feature",
  "properties": {
    "iso:country":"US",
    "sg:address":"1151 Kessler Dr",
    "sg:city":"El Paso",
    "sg:classifiers":[
        {
            "category":"Building & Trades",
            "subcategory":"Construction",
            "type":"Services"
        }
    ],
    "sg:phone":"+1 915 598 6008",
    "sg:postcode":"79907",
    "sg:province":"TX",
    "sg:tags":[
        "concrete",
        "contractor"
    ],
    "wof:name":"J & J Concrete Inc",
    "wof:placetype":"venue"
},
  "geometry": {"coordinates":[-106.317036,31.726581],"type":"Point"}
}