{
  "type": "Feature",
  "properties": {
    "iso:country":"US",
    "sg:address":"600 Crockett St",
    "sg:city":"Columbus",
    "sg:classifiers":[
        {
            "category":"Professional",
            "type":"Services"
        }
    ],
    "sg:phone":"+1 903 683 6743",
    "sg:postcode":"78934",
    "sg:province":"TX",
    "sg:tags":[
        "establishment"
    ],
    "wof:name":"Hopson & Hopson",
    "wof:placetype":"venue"
},
  "geometry": {"coordinates":[-96.543083,29.707649],"type":"Point"}
}