{
  "type": "Feature",
  "properties": {
    "iso:country":"US",
    "sg:address":"1212 N Main Ave",
    "sg:city":"Monahans",
    "sg:classifiers":[
        {
            "category":"Retail",
            "subcategory":"Repair Shop",
            "type":"Services"
        }
    ],
    "sg:phone":"+1 432 943 2830",
    "sg:postcode":"79756",
    "sg:province":"TX",
    "sg:tags":[
        "welding"
    ],
    "wof:name":"P & P Welding & Svc Co",
    "wof:placetype":"venue"
},
  "geometry": {"coordinates":[-102.898557,31.603186],"type":"Point"}
}