{
  "type": "Feature",
  "properties": {
    "iso:country":"US",
    "sg:address":"3500 Woodson Dr",
    "sg:city":"Mc Kinney",
    "sg:classifiers":[
        {
            "category":"Professional",
            "subcategory":"Management & Consulting",
            "type":"Services"
        }
    ],
    "sg:phone":"+1 214 726 9461",
    "sg:postcode":"75070",
    "sg:province":"TX",
    "sg:tags":[
        "business"
    ],
    "wof:name":"Monarch Dealer Consulting Svc",
    "wof:placetype":"venue"
},
  "geometry": {"coordinates":[-96.69026100000001,33.165191],"type":"Point"}
}