{
  "type": "Feature",
  "properties": {
    "iso:country":"US",
    "sg:address":"1560 W Wheeler Ave",
    "sg:city":"Aransas Pass",
    "sg:classifiers":[
        {
            "category":"Farming",
            "subcategory":"Farm & Veterinary Services",
            "type":"Manufacturing & Wholesale Goods"
        }
    ],
    "sg:phone":"+1 361 758 3708",
    "sg:postcode":"78336",
    "sg:province":"TX",
    "sg:tags":[
        "livestock"
    ],
    "wof:name":"Wilderness Ostrich Ranch",
    "wof:placetype":"venue"
},
  "geometry": {"coordinates":[-97.159784,27.914907],"type":"Point"}
}