{
  "type": "Feature",
  "properties": {
    "iso:country":"US",
    "sg:address":"710 N Post Oak Rd Ste 410",
    "sg:city":"Houston",
    "sg:classifiers":[
        {
            "category":"Professional",
            "subcategory":"Accounting & Tax Preparation",
            "type":"Services"
        }
    ],
    "sg:phone":"+1 713 613 2910",
    "sg:postcode":"77024",
    "sg:province":"TX",
    "sg:tags":[
        "accountant"
    ],
    "wof:name":"Weber and Associates Lc",
    "wof:placetype":"venue"
},
  "geometry": {"coordinates":[-95.456497,29.7792],"type":"Point"}
}