{
  "type": "Feature",
  "properties": {
    "iso:country":"US",
    "sg:address":"6520 N 35th St",
    "sg:city":"Mcallen",
    "sg:classifiers":[
        {
            "category":"Autos & Motor Vehicles",
            "subcategory":"Automobile Sales",
            "type":"Retail Goods"
        }
    ],
    "sg:phone":"+1 956 627 0470",
    "sg:postcode":"78504",
    "sg:province":"TX",
    "sg:tags":[
        "new",
        "used",
        "car"
    ],
    "wof:name":"Southern Motor Corp",
    "wof:placetype":"venue"
},
  "geometry": {"coordinates":[-98.24914800000001,26.265095],"type":"Point"}
}