{
  "type": "Feature",
  "properties": {
    "iso:country":"US",
    "sg:address":"1459 Ford Rd",
    "sg:city":"Bowie",
    "sg:classifiers":[
        {
            "category":"Building & Trades",
            "subcategory":"Electrical",
            "type":"Services"
        }
    ],
    "sg:phone":"+1 940 872 5750",
    "sg:postcode":"76230",
    "sg:province":"TX",
    "sg:tags":[
        "industrial",
        "electrician",
        "contractors-commercial",
        "electric"
    ],
    "wof:name":"Bk Electric",
    "wof:placetype":"venue"
},
  "geometry": {"coordinates":[-97.878817,33.494631],"type":"Point"}
}