{
  "type": "Feature",
  "properties": {
    "iso:country":"US",
    "sg:address":"1000 Pine St",
    "sg:city":"Texarkana",
    "sg:classifiers":[
        {
            "category":"Health Services",
            "subcategory":"Doctor",
            "type":"Services"
        }
    ],
    "sg:phone":"+1 903 798 8868",
    "sg:postcode":"75501",
    "sg:province":"TX",
    "sg:tags":[
        "physician",
        "surgeon"
    ],
    "wof:name":"E Med Inc",
    "wof:placetype":"venue"
},
  "geometry": {"coordinates":[-94.046723,33.427622],"type":"Point"}
}