{
  "type": "Feature",
  "properties": {
    "iso:country":"US",
    "sg:address":"149 N Willis St",
    "sg:city":"Abilene",
    "sg:classifiers":[
        {
            "category":"Professional",
            "subcategory":"Management & Consulting",
            "type":"Services"
        },
        {
            "category":"Wholesale",
            "subcategory":"Electrical",
            "type":"Manufacturing & Wholesale Goods"
        }
    ],
    "sg:phone":"+1 325 672 3509",
    "sg:postcode":"79603",
    "sg:province":"TX",
    "sg:tags":[
        "fire",
        "consultant",
        "s",
        "protection",
        "business"
    ],
    "wof:name":"Sentry Fire Protection Systems",
    "wof:placetype":"venue"
},
  "geometry": {"coordinates":[-99.76382,32.452739],"type":"Point"}
}