{
  "type": "Feature",
  "properties": {
    "iso:country":"US",
    "sg:address":"208 S Main St",
    "sg:city":"Burnet",
    "sg:classifiers":[
        {
            "category":"Personal",
            "subcategory":"Beauty Salon",
            "type":"Services"
        }
    ],
    "sg:phone":"+1 512 756 2725",
    "sg:postcode":"78611",
    "sg:province":"TX",
    "sg:tags":[
        "manicuring"
    ],
    "wof:name":"Tips & Tan",
    "wof:placetype":"venue"
},
  "geometry": {"coordinates":[-98.227563,30.757289],"type":"Point"}
}