{
  "type": "Feature",
  "properties": {
    "iso:country":"US",
    "sg:address":"8407 E County Road 6300",
    "sg:city":"Lubbock",
    "sg:classifiers":[
        {
            "category":"Building & Trades",
            "subcategory":"Plumbing",
            "type":"Services"
        }
    ],
    "sg:phone":"+1 806 892 2410",
    "sg:postcode":"79403",
    "sg:province":"TX",
    "sg:tags":[
        "plumber",
        "industrial",
        "contractors-commercial"
    ],
    "wof:name":"Double S Plumbing Co",
    "wof:placetype":"venue"
},
  "geometry": {"coordinates":[-101.686384,33.63585],"type":"Point"}
}