{
  "type": "Feature",
  "properties": {
    "iso:country":"US",
    "sg:address":"2711 W Anderson Ln",
    "sg:city":"Austin",
    "sg:classifiers":[
        {
            "category":"Real Estate",
            "subcategory":"Real Estate Agent",
            "type":"Services"
        }
    ],
    "sg:phone":"+1 512 458 1138",
    "sg:postcode":"78757",
    "sg:province":"TX",
    "sg:tags":[
        "appraiser"
    ],
    "sg:website":"www.amagtexas.com",
    "wof:name":"Austin Metropolitan Appraisal",
    "wof:placetype":"venue"
},
  "geometry": {"coordinates":[-97.737448,30.359152],"type":"Point"}
}