{
  "type": "Feature",
  "properties": {
    "iso:country":"US",
    "sg:address":"13817 Breck St",
    "sg:city":"Houston",
    "sg:classifiers":[
        {
            "category":"Home & Garden",
            "subcategory":"Home Furnishings",
            "type":"Retail Goods"
        }
    ],
    "sg:phone":"+1 281 397 0438",
    "sg:postcode":"77066",
    "sg:province":"TX",
    "sg:tags":[
        "linen",
        "store",
        "furniture"
    ],
    "sg:website":"http://AnnasLinens.com",
    "wof:name":"Anna's Linens",
    "wof:placetype":"venue"
},
  "geometry": {"coordinates":[-95.50115,29.983558],"type":"Point"}
}