{
  "type": "Feature",
  "properties": {
    "iso:country":"US",
    "sg:address":"2207 High Point Dr",
    "sg:city":"Carrollton",
    "sg:classifiers":[
        {
            "category":"Professional",
            "type":"Services"
        }
    ],
    "sg:phone":"+1 972 306 2080",
    "sg:postcode":"75007",
    "sg:province":"TX",
    "wof:name":"Lee Bradley Energy LLC",
    "wof:placetype":"venue"
},
  "geometry": {"coordinates":[-96.862702,33.019892],"type":"Point"}
}