{
  "type": "Feature",
  "properties": {
    "iso:country":"US",
    "sg:address":"903 Hayloft Ln",
    "sg:city":"San Antonio",
    "sg:classifiers":[
        {
            "category":"Professional",
            "subcategory":"Art Services",
            "type":"Services"
        }
    ],
    "sg:phone":"+1 210 674 5980",
    "sg:postcode":"78245",
    "sg:province":"TX",
    "sg:tags":[
        "graphic",
        "designer"
    ],
    "wof:name":"Ward Enterprises",
    "wof:placetype":"venue"
},
  "geometry": {"coordinates":[-98.677626,29.428919],"type":"Point"}
}