{
  "type": "Feature",
  "properties": {
    "iso:country":"US",
    "sg:address":"1908 Haversham Dr",
    "sg:city":"Flower Mound",
    "sg:classifiers":[
        {
            "category":"Professional",
            "subcategory":"Art Services",
            "type":"Services"
        }
    ],
    "sg:phone":"+1 972 355 7109",
    "sg:postcode":"75022",
    "sg:province":"TX",
    "sg:tags":[
        "photography",
        "commercial"
    ],
    "wof:name":"F & S Enterprises Inc",
    "wof:placetype":"venue"
},
  "geometry": {"coordinates":[-97.084328,33.011045],"type":"Point"}
}