{
  "type": "Feature",
  "properties": {
    "iso:country":"US",
    "sg:address":"1474 Cheyenne Rd",
    "sg:city":"Lewisville",
    "sg:classifiers":[
        {
            "category":"Professional",
            "subcategory":"Management & Consulting",
            "type":"Services"
        }
    ],
    "sg:phone":"+1 972 436 6226",
    "sg:postcode":"75077",
    "sg:province":"TX",
    "sg:tags":[
        "retail",
        "direct",
        "sales"
    ],
    "wof:name":"Green Acres",
    "wof:placetype":"venue"
},
  "geometry": {"coordinates":[-97.03017699999999,33.050646],"type":"Point"}
}