{
  "type": "Feature",
  "properties": {
    "iso:country":"US",
    "sg:address":"20 N IH 35",
    "sg:city":"Austin",
    "sg:classifiers":[
        {
            "category":"Personal",
            "type":"Services"
        }
    ],
    "sg:phone":"+1 512 699 6051",
    "sg:postcode":"78701",
    "sg:province":"TX",
    "sg:tags":[
        "local"
    ],
    "sg:website":"www.exploreaustintexas.com",
    "wof:name":"Explore Austin Texas",
    "wof:placetype":"venue"
},
  "geometry": {"coordinates":[-97.737415,30.25372],"type":"Point"}
}