{
  "type": "Feature",
  "properties": {
    "iso:country":"US",
    "sg:address":"1800 N Eastman Rd Ste A",
    "sg:city":"Longview",
    "sg:classifiers":[
        {
            "category":"Home & Garden",
            "subcategory":"Carpets & Floor Coverings",
            "type":"Retail Goods"
        }
    ],
    "sg:phone":"+1 903 753 7397",
    "sg:postcode":"75601",
    "sg:province":"TX",
    "sg:tags":[
        "material"
    ],
    "wof:name":"Best Carpet One",
    "wof:placetype":"venue"
},
  "geometry": {"coordinates":[-94.71588,32.520602],"type":"Point"}
}