{
  "type": "Feature",
  "properties": {
    "iso:country":"US",
    "sg:address":"701 S Church St",
    "sg:city":"Mc Kinney",
    "sg:classifiers":[
        {
            "category":"Organizations",
            "subcategory":"Community Association",
            "type":"Services"
        },
        {
            "category":"Social Services",
            "type":"Services"
        }
    ],
    "sg:phone":"+1 972 542 2491",
    "sg:postcode":"75069",
    "sg:province":"TX",
    "sg:tags":[
        "youth",
        "center"
    ],
    "wof:name":"Boys & Girls Club Collin Cnty",
    "wof:placetype":"venue"
},
  "geometry": {"coordinates":[-96.61799999999999,33.190745],"type":"Point"}
}