{
  "type": "Feature",
  "properties": {
    "iso:country":"US",
    "sg:address":"528 W Bay Area Blvd",
    "sg:city":"Webster",
    "sg:classifiers":[
        {
            "category":"Shopping",
            "subcategory":"Hobbies, Toys, & Games",
            "type":"Retail Goods"
        }
    ],
    "sg:phone":"+1 281 332 7674",
    "sg:postcode":"77598",
    "sg:province":"TX",
    "sg:tags":[
        "video",
        "supply"
    ],
    "sg:website":"http://www.gamestop.com/",
    "wof:name":"Gamestop",
    "wof:placetype":"venue"
},
  "geometry": {"coordinates":[-95.13291700000001,29.545779],"type":"Point"}
}