{
  "type": "Feature",
  "properties": {
    "iso:country":"US",
    "sg:address":"420 W 2nd St",
    "sg:city":"Rio Grande City",
    "sg:classifiers":[
        {
            "category":"Professional",
            "subcategory":"Advertising",
            "type":"Services"
        }
    ],
    "sg:phone":"+1 956 716 8282",
    "sg:postcode":"78582",
    "sg:province":"TX",
    "sg:tags":[
        "mailing",
        "shipping"
    ],
    "wof:name":"LPP Shipping Packing & Mail",
    "wof:placetype":"venue"
},
  "geometry": {"coordinates":[-98.82412600000001,26.38097],"type":"Point"}
}