{
  "type": "Feature",
  "properties": {
    "iso:country":"US",
    "sg:address":"1717 State Hwy 1604",
    "sg:city":"San Antonio",
    "sg:classifiers":[
        {
            "category":"Organizations",
            "subcategory":"Professional Association",
            "type":"Services"
        }
    ],
    "sg:phone":"+1 210 490 1624",
    "sg:postcode":"78232",
    "sg:province":"TX",
    "sg:tags":[
        "business"
    ],
    "wof:name":"African Amrcn Chamber Commerce",
    "wof:placetype":"venue"
},
  "geometry": {"coordinates":[-98.468092,29.609261],"type":"Point"}
}