{
  "type": "Feature",
  "properties": {
    "iso:country":"US",
    "sg:address":"10403 Horn Blvd",
    "sg:city":"San Antonio",
    "sg:classifiers":[
        {
            "category":"Freight",
            "type":"Transportation"
        }
    ],
    "sg:phone":"+1 210 690 0987",
    "sg:postcode":"78240",
    "sg:province":"TX",
    "sg:tags":[
        "hauling"
    ],
    "wof:name":"C & C Trucking",
    "wof:placetype":"venue"
},
  "geometry": {"coordinates":[-98.61368899999999,29.542805],"type":"Point"}
}