{
  "type": "Feature",
  "properties": {
    "iso:country":"US",
    "sg:address":"2425 N Central Expy",
    "sg:city":"Dallas",
    "sg:classifiers":[
        {
            "category":"Real Estate",
            "subcategory":"Real Estate Agent",
            "type":"Services"
        }
    ],
    "sg:phone":"+1 214 664 9795",
    "sg:postcode":"75205",
    "sg:province":"TX",
    "sg:tags":[
        "relocation"
    ],
    "wof:name":"Salomon & Assoc",
    "wof:placetype":"venue"
},
  "geometry": {"coordinates":[-96.793526,32.802183],"type":"Point"}
}