{
  "type": "Feature",
  "properties": {
    "iso:country":"US",
    "sg:address":"213 N Fredonia St",
    "sg:city":"Longview",
    "sg:classifiers":[
        {
            "category":"Banks & Credit Unions",
            "subcategory":"Bank",
            "type":"Services"
        }
    ],
    "sg:phone":"+1 903 753 5511",
    "sg:postcode":"75601",
    "sg:province":"TX",
    "wof:name":"Regions",
    "wof:placetype":"venue"
},
  "geometry": {"coordinates":[-94.738595,32.495261],"type":"Point"}
}