{
  "type": "Feature",
  "properties": {
    "iso:country":"US",
    "sg:address":"6706 Terryville Dr",
    "sg:city":"Amarillo",
    "sg:classifiers":[
        {
            "category":"Wholesale",
            "subcategory":"Medical Equipment & Supplies",
            "type":"Manufacturing & Wholesale Goods"
        },
        {
            "category":"Education",
            "subcategory":"Kindergarten",
            "type":"Public Place"
        },
        {
            "category":"Shopping",
            "subcategory":"Pharmacy",
            "type":"Retail Goods"
        },
        {
            "category":"Personal",
            "subcategory":"Adult",
            "type":"Services"
        }
    ],
    "sg:phone":"+1 806 677 0911",
    "sg:postcode":"79109",
    "sg:province":"TX",
    "sg:tags":[
        "midwife",
        "parenting-centers",
        "health",
        "birth",
        "home",
        "care"
    ],
    "wof:name":"Butterfly Birth",
    "wof:placetype":"venue"
},
  "geometry": {"coordinates":[-101.91034399999999,35.14832],"type":"Point"}
}