{
  "type": "Feature",
  "properties": {
    "iso:country":"US",
    "sg:address":"4220 W Vickery Blvd",
    "sg:city":"Fort Worth",
    "sg:classifiers":[
        {
            "category":"Restaurant",
            "type":"Food & Drink"
        }
    ],
    "sg:phone":"+1 817 377 2652",
    "sg:postcode":"76107",
    "sg:province":"TX",
    "sg:tags":[
        "eating"
    ],
    "wof:name":"Fernandez Cafe",
    "wof:placetype":"venue"
},
  "geometry": {"coordinates":[-97.378861,32.726079],"type":"Point"}
}