{
  "type": "Feature",
  "properties": {
    "iso:country":"US",
    "sg:address":"32831 State Hwy 249",
    "sg:city":"Pinehurst",
    "sg:classifiers":[
        {
            "category":"Building & Trades",
            "subcategory":"Landscaping Services",
            "type":"Services"
        }
    ],
    "sg:phone":"+1 281 259 8866",
    "sg:postcode":"77362",
    "sg:province":"TX",
    "sg:tags":[
        "sod",
        "sodding"
    ],
    "wof:name":"All American Grass Store",
    "wof:placetype":"venue"
},
  "geometry": {"coordinates":[-95.658095,30.139882],"type":"Point"}
}