{
  "type": "Feature",
  "properties": {
    "iso:country":"US",
    "sg:address":"10190 Old Katy Rd",
    "sg:city":"Houston",
    "sg:classifiers":[
        {
            "category":"Professional",
            "type":"Services"
        }
    ],
    "sg:phone":"+1 713 722 8868",
    "sg:postcode":"77043",
    "sg:province":"TX",
    "wof:name":"Anstone Services",
    "wof:placetype":"venue"
},
  "geometry": {"coordinates":[-95.548878,29.785036],"type":"Point"}
}