{
  "type": "Feature",
  "properties": {
    "iso:country":"US",
    "sg:address":"15731 Aberdeen Trails Dr",
    "sg:city":"Houston",
    "sg:classifiers":[
        {
            "category":"Restaurant",
            "type":"Food & Drink"
        }
    ],
    "sg:phone":"+1 281 463 2123",
    "sg:postcode":"77095",
    "sg:province":"TX",
    "sg:tags":[
        "eating"
    ],
    "wof:name":"Sarah Catering Service",
    "wof:placetype":"venue"
},
  "geometry": {"coordinates":[-95.644926,29.911023],"type":"Point"}
}