{
  "type": "Feature",
  "properties": {
    "iso:country":"US",
    "sg:address":"16419 Elmwood Point Ln",
    "sg:city":"Sugar Land",
    "sg:classifiers":[
        {
            "category":"Building & Trades",
            "subcategory":"Construction",
            "type":"Services"
        }
    ],
    "sg:phone":"+1 281 242 6091",
    "sg:postcode":"77478",
    "sg:province":"TX",
    "sg:tags":[
        "housing",
        "revitalization"
    ],
    "wof:name":"Victory Investments",
    "wof:placetype":"venue"
},
  "geometry": {"coordinates":[-95.668066,29.650083],"type":"Point"}
}