{
  "type": "Feature",
  "properties": {
    "iso:country":"US",
    "sg:address":"11409 Lake June Rd",
    "sg:city":"Mesquite",
    "sg:classifiers":[
        {
            "category":"Home & Garden",
            "subcategory":"Furniture",
            "type":"Retail Goods"
        },
        {
            "category":"Home & Garden",
            "subcategory":"Carpets & Floor Coverings",
            "type":"Retail Goods"
        }
    ],
    "sg:phone":"+1 972 329 1212",
    "sg:postcode":"75180",
    "sg:province":"TX",
    "sg:tags":[
        "store",
        "mattress"
    ],
    "wof:name":"Buy Rite Discount Furniture",
    "wof:placetype":"venue"
},
  "geometry": {"coordinates":[-96.630402,32.734299],"type":"Point"}
}