{
  "type": "Feature",
  "properties": {
    "iso:country":"US",
    "sg:address":"4902 34th St",
    "sg:city":"Lubbock",
    "sg:classifiers":[
        {
            "category":"Education",
            "subcategory":"School",
            "type":"Public Place"
        }
    ],
    "sg:phone":"+1 806 740 0811",
    "sg:postcode":"79410",
    "sg:province":"TX",
    "sg:website":"www.richardmilburnacademy.org",
    "wof:name":"Richard Milburn Academy",
    "wof:placetype":"venue"
},
  "geometry": {"coordinates":[-101.916563,33.563263],"type":"Point"}
}