{
  "type": "Feature",
  "properties": {
    "iso:country":"US",
    "sg:address":"8381 Westview Dr",
    "sg:city":"Houston",
    "sg:classifiers":[
        {
            "category":"Organizations",
            "subcategory":"Religious Organization",
            "type":"Services"
        }
    ],
    "sg:phone":"+1 713 461 0709",
    "sg:postcode":"77055",
    "sg:province":"TX",
    "sg:tags":[
        "presbyterian",
        "church"
    ],
    "wof:name":"Ye Darm Presbyterian Church",
    "wof:placetype":"venue"
},
  "geometry": {"coordinates":[-95.494348,29.794772],"type":"Point"}
}