{
  "type": "Feature",
  "properties": {
    "iso:country":"US",
    "sg:address":"5637 Overland Dr",
    "sg:city":"Lewisville",
    "sg:classifiers":[
        {
            "category":"Professional",
            "subcategory":"Computer Services",
            "type":"Services"
        }
    ],
    "sg:phone":"+1 972 668 1259",
    "sg:postcode":"75056",
    "sg:province":"TX",
    "sg:tags":[
        "datum"
    ],
    "wof:name":"James K & Anna E Procious",
    "wof:placetype":"venue"
},
  "geometry": {"coordinates":[-96.86896,33.091135],"type":"Point"}
}