{
  "type": "Feature",
  "properties": {
    "iso:country":"US",
    "sg:address":"13370 Branchview Ln",
    "sg:city":"Dallas",
    "sg:classifiers":[
        {
            "category":"Organizations",
            "subcategory":"Professional Association",
            "type":"Services"
        }
    ],
    "sg:phone":"+1 972 241 1124",
    "sg:postcode":"75234",
    "sg:province":"TX",
    "sg:tags":[
        "trade"
    ],
    "wof:name":"Independent Distributors Assn",
    "wof:placetype":"venue"
},
  "geometry": {"coordinates":[-96.903381,32.924648],"type":"Point"}
}