{
  "type": "Feature",
  "properties": {
    "iso:country":"US",
    "sg:address":"607 Brookfield Dr",
    "sg:city":"Hurst",
    "sg:classifiers":[
        {
            "category":"Building & Trades",
            "subcategory":"Construction",
            "type":"Services"
        }
    ],
    "sg:phone":"+1 817 832 8521",
    "sg:postcode":"76053",
    "sg:province":"TX",
    "wof:name":"We R Construction",
    "wof:placetype":"venue"
},
  "geometry": {"coordinates":[-97.160729,32.815502],"type":"Point"}
}