{
  "type": "Feature",
  "properties": {
    "iso:country":"US",
    "sg:address":"1410 Saddle Lakes Dr",
    "sg:city":"Abilene",
    "sg:classifiers":[
        {
            "category":"Farming",
            "subcategory":"Farm & Veterinary Services",
            "type":"Manufacturing & Wholesale Goods"
        }
    ],
    "sg:phone":"+1 325 698 5316",
    "sg:postcode":"79602",
    "sg:province":"TX",
    "sg:tags":[
        "dusting",
        "ranch",
        "wheat",
        "crop",
        "cattle"
    ],
    "wof:name":"Jackson Aerial Service",
    "wof:placetype":"venue"
},
  "geometry": {"coordinates":[-99.739592,32.346766],"type":"Point"}
}