{
  "type": "Feature",
  "properties": {
    "iso:country":"US",
    "sg:address":"2202 Green Knoll Dr",
    "sg:city":"Houston",
    "sg:classifiers":[
        {
            "category":"Building & Trades",
            "subcategory":"Construction",
            "type":"Services"
        }
    ],
    "sg:phone":"+1 281 880 8310",
    "sg:postcode":"77067",
    "sg:province":"TX",
    "sg:tags":[
        "house"
    ],
    "wof:name":"Davids Home Repairs",
    "wof:placetype":"venue"
},
  "geometry": {"coordinates":[-95.45712899999999,29.952677],"type":"Point"}
}