{
  "type": "Feature",
  "properties": {
    "iso:country":"US",
    "sg:address":"11811 Perrin Beitel Rd",
    "sg:city":"San Antonio",
    "sg:classifiers":[
        {
            "category":"Personal",
            "subcategory":"Beauty Salon",
            "type":"Services"
        }
    ],
    "sg:phone":"+1 210 590 3500",
    "sg:postcode":"78217",
    "sg:province":"TX",
    "sg:tags":[
        "shop",
        "manicuring"
    ],
    "wof:name":"Nail Talk",
    "wof:placetype":"venue"
},
  "geometry": {"coordinates":[-98.410415,29.545999],"type":"Point"}
}