{
  "type": "Feature",
  "properties": {
    "iso:country":"US",
    "sg:address":"7350 Tezel Rd",
    "sg:city":"San Antonio",
    "sg:classifiers":[
        {
            "category":"Bars & Pubs",
            "type":"Food & Drink"
        }
    ],
    "sg:phone":"+1 210 523 5338",
    "sg:postcode":"78250",
    "sg:province":"TX",
    "sg:tags":[
        "club",
        "drinking",
        "night"
    ],
    "wof:name":"Stetson Bar",
    "wof:placetype":"venue"
},
  "geometry": {"coordinates":[-98.662263,29.504529],"type":"Point"}
}