{
  "type": "Feature",
  "properties": {
    "iso:country":"US",
    "sg:address":"440 Louisiana St",
    "sg:city":"Houston",
    "sg:classifiers":[
        {
            "category":"Professional",
            "subcategory":"Business Services",
            "type":"Services"
        }
    ],
    "sg:phone":"+1 713 228 2851",
    "sg:postcode":"77002",
    "sg:province":"TX",
    "sg:tags":[
        "development",
        "economic"
    ],
    "wof:name":"Midstream Development Partners",
    "wof:placetype":"venue"
},
  "geometry": {"coordinates":[-95.364176,29.762755],"type":"Point"}
}