{
  "type": "Feature",
  "properties": {
    "iso:country":"US",
    "sg:address":"7114 Edgemoor Dr",
    "sg:city":"Houston",
    "sg:classifiers":[
        {
            "category":"Professional",
            "subcategory":"Art Services",
            "type":"Services"
        },
        {
            "category":"Professional",
            "subcategory":"Business Services",
            "type":"Services"
        }
    ],
    "sg:phone":"+1 713 772 8781",
    "sg:postcode":"77074",
    "sg:province":"TX",
    "sg:tags":[
        "development",
        "product",
        "graphic",
        "designers-industrial",
        "marketing",
        "commercial",
        "designer",
        "design"
    ],
    "wof:name":"Alan Prince & Karen Prince",
    "wof:placetype":"venue"
},
  "geometry": {"coordinates":[-95.508695,29.702026],"type":"Point"}
}