{
  "type": "Feature",
  "properties": {
    "iso:country":"US",
    "sg:address":"9149 Loma Vista Dr",
    "sg:city":"Dallas",
    "sg:classifiers":[
        {
            "category":"Shopping",
            "subcategory":"Gifts & Souvenirs",
            "type":"Retail Goods"
        }
    ],
    "sg:phone":"+1 214 340 1878",
    "sg:postcode":"75243",
    "sg:province":"TX",
    "wof:name":"Blonde & Blues",
    "wof:placetype":"venue"
},
  "geometry": {"coordinates":[-96.745786,32.89706],"type":"Point"}
}