{
  "type": "Feature",
  "properties": {
    "iso:country":"US",
    "sg:address":"3525 International Blvd",
    "sg:city":"Brownsville",
    "sg:classifiers":[
        {
            "category":"Shopping",
            "subcategory":"Clothing, Apparel, & Fashions",
            "type":"Retail Goods"
        }
    ],
    "sg:phone":"+1 956 542 1931",
    "sg:postcode":"78521",
    "sg:province":"TX",
    "sg:tags":[
        "salvage",
        "surplus",
        "merchandise"
    ],
    "wof:name":"Surplus Warehouse",
    "wof:placetype":"venue"
},
  "geometry": {"coordinates":[-97.470741,25.916387],"type":"Point"}
}