{
  "type": "Feature",
  "properties": {
    "iso:country":"US",
    "sg:address":"605 S Magnolia St",
    "sg:city":"Woodville",
    "sg:classifiers":[
        {
            "category":"Restaurant",
            "type":"Food & Drink"
        }
    ],
    "sg:phone":"+1 409 283 2976",
    "sg:postcode":"75979",
    "sg:province":"TX",
    "sg:tags":[
        "mexican"
    ],
    "wof:name":"Naomi's Tacos And More",
    "wof:placetype":"venue"
},
  "geometry": {"coordinates":[-94.41494,30.769263],"type":"Point"}
}