{
  "type": "Feature",
  "properties": {
    "iso:country":"US",
    "sg:address":"1607 N Travis Ave",
    "sg:city":"Cameron",
    "sg:classifiers":[
        {
            "category":"Retail",
            "subcategory":"Auto Repair",
            "type":"Services"
        }
    ],
    "sg:phone":"+1 254 697 8781",
    "sg:postcode":"76520",
    "sg:province":"TX",
    "sg:tags":[
        "automotive"
    ],
    "wof:name":"Porter Alternator Repair",
    "wof:placetype":"venue"
},
  "geometry": {"coordinates":[-96.97363,30.862801],"type":"Point"}
}