{
  "type": "Feature",
  "properties": {
    "iso:country":"US",
    "sg:address":"212 E College St",
    "sg:city":"Stephenville",
    "sg:classifiers":[
        {
            "category":"Recreation",
            "type":"Entertainment"
        }
    ],
    "sg:phone":"+1 254 965 5509",
    "sg:postcode":"76401",
    "sg:province":"TX",
    "sg:tags":[
        "carnival"
    ],
    "wof:name":"Fair Insurance Svc Inc",
    "wof:placetype":"venue"
},
  "geometry": {"coordinates":[-98.200281,32.220587],"type":"Point"}
}