{
  "type": "Feature",
  "properties": {
    "iso:country":"US",
    "sg:address":"6290 Southmost Rd",
    "sg:city":"Brownsville",
    "sg:classifiers":[
        {
            "category":"Education",
            "subcategory":"School",
            "type":"Public Place"
        }
    ],
    "sg:phone":"+1 956 986 5200",
    "sg:postcode":"78521",
    "sg:province":"TX",
    "sg:tags":[
        "elementary"
    ],
    "wof:name":"Aiken Elementary School",
    "wof:placetype":"venue"
},
  "geometry": {"coordinates":[-97.43779499999999,25.876687],"type":"Point"}
}