{
  "type": "Feature",
  "properties": {
    "iso:country":"US",
    "sg:address":"2901 E Division St",
    "sg:city":"Arlington",
    "sg:classifiers":[
        {
            "category":"Shopping",
            "subcategory":"Jewelry",
            "type":"Retail Goods"
        }
    ],
    "sg:phone":"+1 817 640 5944",
    "sg:postcode":"76011",
    "sg:province":"TX",
    "wof:name":"Foleys Jewelry Dept",
    "wof:placetype":"venue"
},
  "geometry": {"coordinates":[-97.056994,32.741822],"type":"Point"}
}