{
  "type": "Feature",
  "properties": {
    "iso:country":"US",
    "sg:address":"3118 N Park Dr",
    "sg:city":"Missouri City",
    "sg:classifiers":[
        {
            "category":"Wholesale",
            "subcategory":"Durable Goods & Equipment",
            "type":"Manufacturing & Wholesale Goods"
        }
    ],
    "sg:phone":"+1 281 499 0325",
    "sg:postcode":"77459",
    "sg:province":"TX",
    "sg:tags":[
        "importer"
    ],
    "wof:name":"Baron Import & Export",
    "wof:placetype":"venue"
},
  "geometry": {"coordinates":[-95.55171900000001,29.586609],"type":"Point"}
}