{
  "type": "Feature",
  "properties": {
    "iso:country":"US",
    "sg:address":"8610 Martin Luther King Jr Blvd",
    "sg:city":"Houston",
    "sg:classifiers":[
        {
            "category":"Health Services",
            "subcategory":"Clinic",
            "type":"Services"
        },
        {
            "category":"Community Center",
            "type":"Public Place"
        }
    ],
    "sg:phone":"+1 713 733 1755",
    "sg:postcode":"77033",
    "sg:province":"TX",
    "sg:tags":[
        "information",
        "medical",
        "mental"
    ],
    "sg:website":"www.tachc.org",
    "wof:name":"South Central Houston Community Health Center",
    "wof:placetype":"venue"
},
  "geometry": {"coordinates":[-95.337261,29.658141],"type":"Point"}
}