{
  "type": "Feature",
  "properties": {
    "iso:country":"US",
    "sg:address":"1221 Farr Street",
    "sg:city":"Waller",
    "sg:classifiers":[
        {
            "category":"Health Services",
            "subcategory":"Doctor",
            "type":"Services"
        }
    ],
    "sg:phone":"+1 936 372 3646",
    "sg:postcode":"77484",
    "sg:province":"TX",
    "sg:tags":[
        "physician",
        "family",
        "practice",
        "surgeons",
        "internal",
        "medicine"
    ],
    "wof:name":"Mark D. Le MD",
    "wof:placetype":"venue"
},
  "geometry": {"coordinates":[-95.924924,30.057839],"type":"Point"}
}