{
  "type": "Feature",
  "properties": {
    "iso:country":"US",
    "sg:address":"13119 Broncroft Ct",
    "sg:city":"Houston",
    "sg:classifiers":[
        {
            "category":"Building & Trades",
            "subcategory":"Construction",
            "type":"Services"
        }
    ],
    "sg:phone":"+1 713 225 3802",
    "sg:postcode":"77044",
    "sg:province":"TX",
    "sg:tags":[
        "house"
    ],
    "wof:name":"Hammond Homes Summerwood Sales",
    "wof:placetype":"venue"
},
  "geometry": {"coordinates":[-95.173355,29.933768],"type":"Point"}
}