{
  "type": "Feature",
  "properties": {
    "iso:country":"US",
    "sg:address":"2200 Regency Dr",
    "sg:city":"Irving",
    "sg:classifiers":[
        {
            "category":"Professional",
            "subcategory":"Engineering",
            "type":"Services"
        }
    ],
    "sg:phone":"+1 972 438 2722",
    "sg:postcode":"75062",
    "sg:province":"TX",
    "sg:tags":[
        "development",
        "rf",
        "camera",
        "sensor",
        "imaging"
    ],
    "wof:name":"Intelligent Machine Technology",
    "wof:placetype":"venue"
},
  "geometry": {"coordinates":[-96.89538899999999,32.83835],"type":"Point"}
}