{
  "type": "Feature",
  "properties": {
    "iso:country":"US",
    "sg:address":"6022 Windbreak Trl",
    "sg:city":"Dallas",
    "sg:classifiers":[
        {
            "category":"Wholesale",
            "subcategory":"Home Furnishings",
            "type":"Manufacturing & Wholesale Goods"
        }
    ],
    "sg:phone":"+1 972 661 3506",
    "sg:postcode":"75252",
    "sg:province":"TX",
    "sg:tags":[
        "accessory"
    ],
    "wof:name":"Irwin Shafranek Sales",
    "wof:placetype":"venue"
},
  "geometry": {"coordinates":[-96.80183599999999,33.010228],"type":"Point"}
}