{
  "type": "Feature",
  "properties": {
    "iso:country":"US",
    "sg:address":"904 W Kramer Rd",
    "sg:city":"Burkburnett",
    "sg:classifiers":[
        {
            "category":"Restaurant",
            "type":"Food & Drink"
        }
    ],
    "sg:phone":"+1 940 569 3600",
    "sg:postcode":"76354",
    "sg:province":"TX",
    "sg:tags":[
        "shop",
        "coffee"
    ],
    "wof:name":"Java Jireh",
    "wof:placetype":"venue"
},
  "geometry": {"coordinates":[-98.58248,34.079961],"type":"Point"}
}