{
  "type": "Feature",
  "properties": {
    "iso:country":"US",
    "sg:address":"1333 N 3rd St",
    "sg:city":"Abilene",
    "sg:classifiers":[
        {
            "category":"Organizations",
            "subcategory":"Religious Organization",
            "type":"Services"
        }
    ],
    "sg:phone":"+1 325 673 5031",
    "sg:postcode":"79601",
    "sg:province":"TX",
    "sg:tags":[
        "churches-baptist",
        "church"
    ],
    "sg:website":"http://www.fbcabilene.org",
    "wof:name":"First Baptist Church",
    "wof:placetype":"venue"
},
  "geometry": {"coordinates":[-99.73695499999999,32.451778],"type":"Point"}
}