{
  "type": "Feature",
  "properties": {
    "iso:country":"US",
    "sg:address":"7106 Bandera Rd",
    "sg:city":"San Antonio",
    "sg:classifiers":[
        {
            "category":"Home & Garden",
            "subcategory":"Building Materials",
            "type":"Retail Goods"
        }
    ],
    "sg:phone":"+1 210 310 7500",
    "sg:postcode":"78238",
    "sg:province":"TX",
    "sg:tags":[
        "glass",
        "window",
        "plate"
    ],
    "wof:name":"Texan Glass Express",
    "wof:placetype":"venue"
},
  "geometry": {"coordinates":[-98.62650600000001,29.503538],"type":"Point"}
}