{
  "type": "Feature",
  "properties": {
    "iso:country":"US",
    "sg:address":"10906 Ambergate Ln",
    "sg:city":"Frisco",
    "sg:classifiers":[
        {
            "category":"Shopping",
            "subcategory":"Computers & Home Electronics",
            "type":"Retail Goods"
        }
    ],
    "sg:phone":"+1 972 335 9500",
    "sg:postcode":"75035",
    "sg:province":"TX",
    "sg:tags":[
        "software"
    ],
    "wof:name":"Integrated Chipware",
    "wof:placetype":"venue"
},
  "geometry": {"coordinates":[-96.785833,33.140977],"type":"Point"}
}