{
  "type": "Feature",
  "properties": {
    "iso:country":"US",
    "sg:address":"1350 W Bridge St",
    "sg:city":"New Braunfels",
    "sg:classifiers":[
        {
            "category":"Real Estate",
            "subcategory":"Real Estate Operator",
            "type":"Services"
        }
    ],
    "sg:phone":"+1 830 625 9481",
    "sg:postcode":"78130",
    "sg:province":"TX",
    "sg:tags":[
        "property",
        "lessor"
    ],
    "wof:name":"Stanley Rosenthal",
    "wof:placetype":"venue"
},
  "geometry": {"coordinates":[-98.13750400000001,29.693222],"type":"Point"}
}