{
  "type": "Feature",
  "properties": {
    "iso:country":"US",
    "sg:address":"154 Green Fields Dr",
    "sg:city":"Bastrop",
    "sg:classifiers":[
        {
            "category":"Retail",
            "subcategory":"Laundry & Dry Cleaning",
            "type":"Services"
        }
    ],
    "sg:phone":"+1 512 581 0332",
    "sg:postcode":"78602",
    "sg:province":"TX",
    "wof:name":"Angels Little Carpet Care",
    "wof:placetype":"venue"
},
  "geometry": {"coordinates":[-97.42738,30.126666],"type":"Point"}
}