{
  "type": "Feature",
  "properties": {
    "iso:country":"US",
    "sg:address":"1134 Harbor St",
    "sg:city":"Houston",
    "sg:classifiers":[
        {
            "category":"Bars & Pubs",
            "type":"Food & Drink"
        }
    ],
    "sg:phone":"+1 713 674 9766",
    "sg:postcode":"77020",
    "sg:province":"TX",
    "sg:tags":[
        "drinking"
    ],
    "wof:name":"El Deportivo Billares",
    "wof:placetype":"venue"
},
  "geometry": {"coordinates":[-95.29473299999999,29.767739],"type":"Point"}
}