{
  "type": "Feature",
  "properties": {
    "iso:country":"US",
    "sg:address":"750 Pleasanton Rd",
    "sg:city":"San Antonio",
    "sg:classifiers":[
        {
            "category":"Retail",
            "subcategory":"Repair Shop",
            "type":"Services"
        }
    ],
    "sg:phone":"+1 210 922 1466",
    "sg:postcode":"78214",
    "sg:province":"TX",
    "wof:name":"Gueros Upholstery & Imports",
    "wof:placetype":"venue"
},
  "geometry": {"coordinates":[-98.50420099999999,29.377465],"type":"Point"}
}