{
  "type": "Feature",
  "properties": {
    "iso:country":"US",
    "sg:address":"6523 Duck Creek Dr",
    "sg:city":"Garland",
    "sg:classifiers":[
        {
            "category":"Wholesale",
            "subcategory":"Office Equipment",
            "type":"Manufacturing & Wholesale Goods"
        }
    ],
    "sg:phone":"+1 972 303 9641",
    "sg:postcode":"75043",
    "sg:province":"TX",
    "sg:tags":[
        "machine",
        "duplicating",
        "copying"
    ],
    "wof:name":"Copy Place Post & Print",
    "wof:placetype":"venue"
},
  "geometry": {"coordinates":[-96.59685899999999,32.845743],"type":"Point"}
}