{
  "type": "Feature",
  "properties": {
    "iso:country":"US",
    "sg:address":"6522 Cindy Ln",
    "sg:city":"Houston",
    "sg:classifiers":[
        {
            "category":"Real Estate",
            "subcategory":"Real Estate Services",
            "type":"Services"
        },
        {
            "category":"Real Estate",
            "subcategory":"Real Estate Agent",
            "type":"Services"
        }
    ],
    "sg:phone":"+1 713 861 3522",
    "sg:postcode":"77008",
    "sg:province":"TX",
    "sg:tags":[
        "buyer",
        "consultant",
        "broker"
    ],
    "wof:name":"EDL Properties",
    "wof:placetype":"venue"
},
  "geometry": {"coordinates":[-95.430789,29.795524],"type":"Point"}
}