{
  "type": "Feature",
  "properties": {
    "iso:country":"US",
    "sg:address":"1873 Polly Harris Dr",
    "sg:city":"El Paso",
    "sg:classifiers":[
        {
            "category":"Professional",
            "type":"Services"
        }
    ],
    "sg:phone":"+1 915 856 3608",
    "sg:postcode":"79936",
    "sg:province":"TX",
    "wof:name":"N Lambert Senovia",
    "wof:placetype":"venue"
},
  "geometry": {"coordinates":[-106.281729,31.764067],"type":"Point"}
}