{
  "type": "Feature",
  "properties": {
    "iso:country":"US",
    "sg:address":"16777 Flintrock Rd",
    "sg:city":"Austin",
    "sg:classifiers":[
        {
            "category":"Building & Trades",
            "subcategory":"Construction",
            "type":"Services"
        }
    ],
    "sg:phone":"+1 512 402 1113",
    "sg:postcode":"78738",
    "sg:province":"TX",
    "sg:tags":[
        "general",
        "contractor"
    ],
    "wof:name":"Comanche Contractors Inc",
    "wof:placetype":"venue"
},
  "geometry": {"coordinates":[-97.99045599999999,30.331114],"type":"Point"}
}