{
  "type": "Feature",
  "properties": {
    "iso:country":"US",
    "sg:address":"7226 Rancho Mission Dr",
    "sg:city":"Houston",
    "sg:classifiers":[
        {
            "category":"Manufacturing",
            "subcategory":"Apparel",
            "type":"Manufacturing & Wholesale Goods"
        }
    ],
    "sg:phone":"+1 832 741 1603",
    "sg:postcode":"77083",
    "sg:province":"TX",
    "wof:name":"Aidas Embroidery Designs",
    "wof:placetype":"venue"
},
  "geometry": {"coordinates":[-95.645984,29.699218],"type":"Point"}
}