{
  "type": "Feature",
  "properties": {
    "iso:country":"US",
    "sg:address":"855 Uvalde Rd",
    "sg:city":"Houston",
    "sg:classifiers":[
        {
            "category":"Insurance",
            "subcategory":"Insurance Agent",
            "type":"Services"
        }
    ],
    "sg:phone":"+1 713 453 3591",
    "sg:postcode":"77015",
    "sg:province":"TX",
    "wof:name":"Don Hammock Insurance",
    "wof:placetype":"venue"
},
  "geometry": {"coordinates":[-95.186656,29.779053],"type":"Point"}
}