{
  "type": "Feature",
  "properties": {
    "iso:country":"US",
    "sg:address":"3201 S Belt Line Rd",
    "sg:city":"Mesquite",
    "sg:classifiers":[
        {
            "category":"Retail",
            "subcategory":"Auto Repair",
            "type":"Services"
        }
    ],
    "sg:phone":"+1 972 288 8525",
    "sg:postcode":"75181",
    "sg:province":"TX",
    "sg:tags":[
        "repairing",
        "automobile"
    ],
    "wof:name":"What's Auto Care",
    "wof:placetype":"venue"
},
  "geometry": {"coordinates":[-96.599024,32.723867],"type":"Point"}
}