{
  "type": "Feature",
  "properties": {
    "iso:country":"US",
    "sg:address":"6935 Scyene Rd",
    "sg:city":"Dallas",
    "sg:classifiers":[
        {
            "category":"Food & Beverages",
            "subcategory":"Groceries & Convenience Stores",
            "type":"Retail Goods"
        }
    ],
    "sg:phone":"+1 214 388 5644",
    "sg:postcode":"75227",
    "sg:province":"TX",
    "wof:name":"Vecta-S Food Store",
    "wof:placetype":"venue"
},
  "geometry": {"coordinates":[-96.702003,32.7635],"type":"Point"}
}