{
  "type": "Feature",
  "properties": {
    "iso:country":"US",
    "sg:address":"13735 S Mansfield Ferry Rd",
    "sg:city":"Orange",
    "sg:classifiers":[
        {
            "category":"Utilities",
            "subcategory":"Natural Gas",
            "type":"Services"
        }
    ],
    "sg:phone":"+1 409 768 1489",
    "sg:postcode":"77630",
    "sg:province":"TX",
    "sg:tags":[
        "transmission"
    ],
    "wof:name":"Vidor Station",
    "wof:placetype":"venue"
},
  "geometry": {"coordinates":[-93.996972,30.067504],"type":"Point"}
}