{
  "type": "Feature",
  "properties": {
    "iso:country":"US",
    "sg:address":"1619 SE Military Dr",
    "sg:city":"San Antonio",
    "sg:classifiers":[
        {
            "category":"Insurance",
            "subcategory":"Insurance Agent",
            "type":"Services"
        }
    ],
    "sg:phone":"+1 210 673 4400",
    "sg:postcode":"78214",
    "sg:province":"TX",
    "sg:tags":[
        "agency"
    ],
    "wof:name":"Loya Fred Insurance Agency LP",
    "wof:placetype":"venue"
},
  "geometry": {"coordinates":[-98.47026,29.352081],"type":"Point"}
}