{
  "type": "Feature",
  "properties": {
    "iso:country":"US",
    "sg:address":"1701 E Central Texas Expy",
    "sg:city":"Killeen",
    "sg:classifiers":[
        {
            "category":"Restaurant",
            "type":"Food & Drink"
        }
    ],
    "sg:menulink":"http://www.allmenus.com/tx/killeen/7388-el-chico/menu/",
    "sg:phone":"+1 254 634 0501",
    "sg:postcode":"76541",
    "sg:province":"TX",
    "sg:tags":[
        "american",
        "mexican",
        "tex-mex"
    ],
    "wof:name":"El Chico",
    "wof:placetype":"venue"
},
  "geometry": {"coordinates":[-97.721564,31.092368],"type":"Point"}
}