{
  "type": "Feature",
  "properties": {
    "iso:country":"US",
    "sg:address":"313 W Ave N",
    "sg:city":"San Angelo",
    "sg:classifiers":[
        {
            "category":"Organizations",
            "subcategory":"Religious Organization",
            "type":"Services"
        }
    ],
    "sg:phone":"+1 325 658 1922",
    "sg:postcode":"76903",
    "sg:province":"TX",
    "sg:tags":[
        "church"
    ],
    "wof:name":"Iglesia Presbiteriana Nazareth",
    "wof:placetype":"venue"
},
  "geometry": {"coordinates":[-100.440146,31.442702],"type":"Point"}
}