{
  "type": "Feature",
  "properties": {
    "iso:country":"US",
    "sg:address":"1755 N Collins Blvd",
    "sg:city":"Richardson",
    "sg:classifiers":[
        {
            "category":"Insurance",
            "subcategory":"Health Insurance",
            "type":"Services"
        }
    ],
    "sg:phone":"+1 972 643 6300",
    "sg:postcode":"75080",
    "sg:province":"TX",
    "sg:tags":[
        "plan"
    ],
    "wof:name":"Aetna",
    "wof:placetype":"venue"
},
  "geometry": {"coordinates":[-96.72380200000001,32.972659],"type":"Point"}
}