{
  "type": "Feature",
  "properties": {
    "iso:country":"US",
    "sg:address":"151 Park Ln",
    "sg:city":"Jasper",
    "sg:classifiers":[
        {
            "category":"Education",
            "subcategory":"School",
            "type":"Public Place"
        }
    ],
    "sg:phone":"+1 409 384 2212",
    "sg:postcode":"75951",
    "sg:province":"TX",
    "wof:name":"Parnell Elementary School",
    "wof:placetype":"venue"
},
  "geometry": {"coordinates":[-94.011335,30.920917],"type":"Point"}
}