{
  "type": "Feature",
  "properties": {
    "iso:country":"US",
    "sg:address":"1144 W Pioneer Pkwy",
    "sg:city":"Arlington",
    "sg:classifiers":[
        {
            "category":"Insurance",
            "subcategory":"Insurance Agent",
            "type":"Services"
        }
    ],
    "sg:phone":"+1 817 275 4210",
    "sg:postcode":"76013",
    "sg:province":"TX",
    "wof:name":"Hines Insurance",
    "wof:placetype":"venue"
},
  "geometry": {"coordinates":[-97.119747,32.708559],"type":"Point"}
}