{
  "type": "Feature",
  "properties": {
    "iso:country":"US",
    "sg:address":"1203 W Houston St",
    "sg:city":"San Antonio",
    "sg:classifiers":[
        {
            "category":"Professional",
            "subcategory":"Lawyer & Legal Services",
            "type":"Services"
        }
    ],
    "sg:phone":"+1 210 227 6506",
    "sg:postcode":"78207",
    "sg:province":"TX",
    "sg:tags":[
        "attorney"
    ],
    "wof:name":"Blomster Jeanne Law Offices",
    "wof:placetype":"venue"
},
  "geometry": {"coordinates":[-98.508602,29.427423],"type":"Point"}
}