{
  "type": "Feature",
  "properties": {
    "iso:country":"US",
    "sg:address":"609 S Forest St",
    "sg:city":"Amarillo",
    "sg:classifiers":[
        {
            "category":"Building & Trades",
            "subcategory":"Construction",
            "type":"Services"
        }
    ],
    "sg:phone":"+1 806 376 5476",
    "sg:postcode":"79106",
    "sg:province":"TX",
    "sg:tags":[
        "contractor"
    ],
    "wof:name":"ABC Overhead Doors",
    "wof:placetype":"venue"
},
  "geometry": {"coordinates":[-101.881505,35.210331],"type":"Point"}
}