{
  "type": "Feature",
  "properties": {
    "iso:country":"US",
    "sg:address":"4449 S Staples St",
    "sg:city":"Corpus Christi",
    "sg:classifiers":[
        {
            "category":"Health Services",
            "subcategory":"Doctor",
            "type":"Services"
        }
    ],
    "sg:phone":"+1 361 992 8351",
    "sg:postcode":"78411",
    "sg:province":"TX",
    "sg:tags":[
        "dentist"
    ],
    "wof:name":"Southside Dental",
    "wof:placetype":"venue"
},
  "geometry": {"coordinates":[-97.375078,27.720283],"type":"Point"}
}