{
  "type": "Feature",
  "properties": {
    "iso:country":"US",
    "sg:address":"8949 Forest Hill Dr",
    "sg:city":"Fort Worth",
    "sg:classifiers":[
        {
            "category":"Wholesale",
            "subcategory":"Machinery & Supplies",
            "type":"Manufacturing & Wholesale Goods"
        }
    ],
    "sg:phone":"+1 817 516 7298",
    "sg:postcode":"76140",
    "sg:province":"TX",
    "sg:tags":[
        "tool"
    ],
    "wof:name":"Tools & Metals Inc",
    "wof:placetype":"venue"
},
  "geometry": {"coordinates":[-97.26997799999999,32.625082],"type":"Point"}
}