{
  "type": "Feature",
  "properties": {
    "iso:country":"US",
    "sg:address":"10141 Kemp Forest Dr",
    "sg:city":"Houston",
    "sg:classifiers":[
        {
            "category":"Professional",
            "type":"Services"
        }
    ],
    "sg:phone":"+1 713 460 8200",
    "sg:postcode":"77080",
    "sg:province":"TX",
    "sg:tags":[
        "restaurant"
    ],
    "wof:name":"Whole Hog Cookers",
    "wof:placetype":"venue"
},
  "geometry": {"coordinates":[-95.542974,29.826886],"type":"Point"}
}