{
  "type": "Feature",
  "properties": {
    "iso:country":"US",
    "sg:address":"110 Lakeway Dr",
    "sg:city":"Georgetown",
    "sg:classifiers":[
        {
            "category":"Personal",
            "subcategory":"Beauty Salon",
            "type":"Services"
        }
    ],
    "sg:phone":"+1 512 863 3805",
    "sg:postcode":"78628",
    "sg:province":"TX",
    "wof:name":"Totally You",
    "wof:placetype":"venue"
},
  "geometry": {"coordinates":[-97.692385,30.66539],"type":"Point"}
}