{
  "type": "Feature",
  "properties": {
    "iso:country":"US",
    "sg:address":"510 College St",
    "sg:city":"Ingram",
    "sg:classifiers":[
        {
            "category":"Education",
            "subcategory":"School",
            "type":"Public Place"
        }
    ],
    "sg:phone":"+1 830 367 4012",
    "sg:postcode":"78025",
    "sg:province":"TX",
    "wof:name":"Ingram Middle School",
    "wof:placetype":"venue"
},
  "geometry": {"coordinates":[-99.24376700000001,30.077459],"type":"Point"}
}