{
  "type": "Feature",
  "properties": {
    "iso:country":"US",
    "sg:address":"10841 State Hwy 159",
    "sg:city":"Bellville",
    "sg:classifiers":[
        {
            "category":"Communications",
            "type":"Services"
        }
    ],
    "sg:phone":"+1 979 865 1450",
    "sg:postcode":"77418",
    "sg:province":"TX",
    "sg:tags":[
        "carrier"
    ],
    "wof:name":"Crown Communications",
    "wof:placetype":"venue"
},
  "geometry": {"coordinates":[-96.13115999999999,30.02835],"type":"Point"}
}