{
  "type": "Feature",
  "properties": {
    "iso:country":"US",
    "sg:address":"126 E Gantt St",
    "sg:city":"Princeton",
    "sg:classifiers":[
        {
            "category":"Organizations",
            "subcategory":"Religious Organization",
            "type":"Services"
        }
    ],
    "sg:phone":"+1 972 736 3488",
    "sg:postcode":"75407",
    "sg:province":"TX",
    "wof:name":"Generic Brand Ministries",
    "wof:placetype":"venue"
},
  "geometry": {"coordinates":[-96.50035200000001,33.183877],"type":"Point"}
}