{
  "type": "Feature",
  "properties": {
    "iso:country":"US",
    "sg:address":"3115 Village Woods Dr",
    "sg:city":"Humble",
    "sg:classifiers":[
        {
            "category":"Professional",
            "type":"Services"
        }
    ],
    "sg:phone":"+1 281 360 5139",
    "sg:postcode":"77339",
    "sg:province":"TX",
    "wof:name":"Seotex Environmental Inc",
    "wof:placetype":"venue"
},
  "geometry": {"coordinates":[-95.194098,30.060126],"type":"Point"}
}