{
  "type": "Feature",
  "properties": {
    "iso:country":"US",
    "sg:address":"1701 Gateway Blvd",
    "sg:city":"Richardson",
    "sg:classifiers":[
        {
            "category":"Professional",
            "type":"Services"
        }
    ],
    "sg:phone":"+1 972 437 4600",
    "sg:postcode":"75080",
    "sg:province":"TX",
    "sg:tags":[
        "establishment"
    ],
    "wof:name":"Achievement Plus",
    "wof:placetype":"venue"
},
  "geometry": {"coordinates":[-96.721576,32.973332],"type":"Point"}
}