{
  "type": "Feature",
  "properties": {
    "iso:country":"US",
    "sg:address":"1029 Glen Rose Rd",
    "sg:city":"Stephenville",
    "sg:classifiers":[
        {
            "category":"Professional",
            "subcategory":"Business Services",
            "type":"Services"
        }
    ],
    "sg:phone":"+1 254 965 4706",
    "sg:postcode":"76401",
    "sg:province":"TX",
    "wof:name":"C & R Bail Bonds",
    "wof:placetype":"venue"
},
  "geometry": {"coordinates":[-98.190969,32.212937],"type":"Point"}
}