{
  "type": "Feature",
  "properties": {
    "iso:country":"US",
    "sg:address":"3314 Crenshaw Ave",
    "sg:city":"Fort Worth",
    "sg:classifiers":[
        {
            "category":"Organizations",
            "subcategory":"Religious Organization",
            "type":"Services"
        }
    ],
    "sg:phone":"+1 817 535 4840",
    "sg:postcode":"76105",
    "sg:province":"TX",
    "wof:name":"Friendly Fellowship Church of",
    "wof:placetype":"venue"
},
  "geometry": {"coordinates":[-97.27680599999999,32.718073],"type":"Point"}
}