{
  "type": "Feature",
  "properties": {
    "iso:country":"US",
    "sg:address":"2504 Estes Pkwy",
    "sg:city":"Longview",
    "sg:classifiers":[
        {
            "category":"Autos & Motor Vehicles",
            "subcategory":"Automobile Sales",
            "type":"Retail Goods"
        },
        {
            "category":"Autos & Motor Vehicles",
            "subcategory":"Auto Supplies",
            "type":"Retail Goods"
        },
        {
            "category":"Retail",
            "subcategory":"Auto Repair",
            "type":"Services"
        }
    ],
    "sg:phone":"+1 903 758 4093",
    "sg:postcode":"75602",
    "sg:province":"TX",
    "sg:tags":[
        "used",
        "tire",
        "car",
        "retread",
        "truck",
        "recap",
        "brake"
    ],
    "wof:name":"Moreno's Tire & Auto",
    "wof:placetype":"venue"
},
  "geometry": {"coordinates":[-94.730706,32.458766],"type":"Point"}
}