{
  "type": "Feature",
  "properties": {
    "iso:country":"US",
    "sg:address":"1100 Highway 59 Loop N",
    "sg:city":"Livingston",
    "sg:classifiers":[
        {
            "category":"Restaurant",
            "type":"Food & Drink"
        }
    ],
    "sg:phone":"+1 936 327 3503",
    "sg:postcode":"77351",
    "sg:province":"TX",
    "sg:tags":[
        "seafood"
    ],
    "sg:website":"http://www.davidbeards.com",
    "wof:name":"Catfish King",
    "wof:placetype":"venue"
},
  "geometry": {"coordinates":[-94.953192,30.695143],"type":"Point"}
}