{
  "type": "Feature",
  "properties": {
    "iso:country":"US",
    "sg:address":"3308 Canemont Dr",
    "sg:city":"Midland",
    "sg:classifiers":[
        {
            "category":"Professional",
            "type":"Services"
        }
    ],
    "sg:phone":"+1 432 694 4760",
    "sg:postcode":"79707",
    "sg:province":"TX",
    "wof:name":"Rocky Ford & Cheryl Seay",
    "wof:placetype":"venue"
},
  "geometry": {"coordinates":[-102.145993,32.016383],"type":"Point"}
}