{
  "type": "Feature",
  "properties": {
    "iso:country":"US",
    "sg:address":"1110 RM 620 N",
    "sg:city":"Lakeway",
    "sg:classifiers":[
        {
            "category":"Banks & Credit Unions",
            "subcategory":"Investment Brokerage",
            "type":"Services"
        }
    ],
    "sg:phone":"+1 512 263 3963",
    "sg:postcode":"78734",
    "sg:province":"TX",
    "wof:name":"Bearden Investment Co",
    "wof:placetype":"venue"
},
  "geometry": {"coordinates":[-97.94666700000001,30.375919],"type":"Point"}
}