{
  "type": "Feature",
  "properties": {
    "iso:country":"US",
    "sg:address":"2129 Jefferson Dr",
    "sg:city":"Port Arthur",
    "sg:classifiers":[
        {
            "category":"Restaurant",
            "type":"Food & Drink"
        }
    ],
    "sg:phone":"+1 409 962 9696",
    "sg:postcode":"77642",
    "sg:province":"TX",
    "sg:tags":[
        "eating"
    ],
    "wof:name":"Papa Johns",
    "wof:placetype":"venue"
},
  "geometry": {"coordinates":[-93.912088,29.920585],"type":"Point"}
}