{
  "type": "Feature",
  "properties": {
    "iso:country":"US",
    "sg:address":"816 W Broadway St",
    "sg:city":"Sweetwater",
    "sg:classifiers":[
        {
            "category":"Professional",
            "subcategory":"Accounting & Tax Preparation",
            "type":"Services"
        }
    ],
    "sg:phone":"+1 325 235 3577",
    "sg:postcode":"79556",
    "sg:province":"TX",
    "sg:tags":[
        "sc",
        "return"
    ],
    "wof:name":"H & R Block",
    "wof:placetype":"venue"
},
  "geometry": {"coordinates":[-100.416158,32.46647],"type":"Point"}
}