{
  "type": "Feature",
  "properties": {
    "iso:country":"US",
    "sg:address":"6131 Pinemont Dr",
    "sg:city":"Houston",
    "sg:classifiers":[
        {
            "category":"Retail",
            "subcategory":"Auto Repair",
            "type":"Services"
        }
    ],
    "sg:phone":"+1 713 682 1674",
    "sg:postcode":"77092",
    "sg:province":"TX",
    "sg:tags":[
        "muffler",
        "exhaust",
        "sp",
        "system"
    ],
    "wof:name":"Discount Muffler",
    "wof:placetype":"venue"
},
  "geometry": {"coordinates":[-95.47931199999999,29.840287],"type":"Point"}
}