{
  "type": "Feature",
  "properties": {
    "iso:country":"US",
    "sg:address":"22330 Coriander Dr",
    "sg:city":"Katy",
    "sg:classifiers":[
        {
            "category":"Shopping",
            "subcategory":"Bicycles & Sporting Goods",
            "type":"Retail Goods"
        }
    ],
    "sg:phone":"+1 281 395 6257",
    "sg:postcode":"77450",
    "sg:province":"TX",
    "wof:name":"Shal Skate Supplies",
    "wof:placetype":"venue"
},
  "geometry": {"coordinates":[-95.759237,29.783703],"type":"Point"}
}