{
  "type": "Feature",
  "properties": {
    "iso:country":"US",
    "sg:address":"4025 W FM 917",
    "sg:city":"Joshua",
    "sg:classifiers":[
        {
            "category":"Organizations",
            "subcategory":"Religious Organization",
            "type":"Services"
        }
    ],
    "sg:phone":"+1 817 645 2344",
    "sg:postcode":"76058",
    "sg:province":"TX",
    "sg:tags":[
        "church"
    ],
    "wof:name":"Blackberry Community Fllwshp",
    "wof:placetype":"venue"
},
  "geometry": {"coordinates":[-97.482365,32.455278],"type":"Point"}
}