{
  "type": "Feature",
  "properties": {
    "iso:country":"US",
    "sg:address":"820 Gessner Rd",
    "sg:city":"Houston",
    "sg:classifiers":[
        {
            "category":"Manufacturing",
            "subcategory":"Chemicals & Compounds",
            "type":"Manufacturing & Wholesale Goods"
        }
    ],
    "sg:phone":"+1 713 973 5600",
    "sg:postcode":"77024",
    "sg:province":"TX",
    "sg:tags":[
        "industrial",
        "organic",
        "mfg"
    ],
    "wof:name":"Union Carbide Corporation",
    "wof:placetype":"venue"
},
  "geometry": {"coordinates":[-95.54438399999999,29.777131],"type":"Point"}
}