{
  "type": "Feature",
  "properties": {
    "iso:country":"US",
    "sg:address":"600 Palm Dr",
    "sg:city":"Corpus Christi",
    "sg:classifiers":[
        {
            "category":"Building & Trades",
            "subcategory":"Construction",
            "type":"Services"
        }
    ],
    "sg:phone":"+1 361 887 8817",
    "sg:postcode":"78408",
    "sg:province":"TX",
    "sg:tags":[
        "general",
        "contractor"
    ],
    "wof:name":"T Mak Construction LTD",
    "wof:placetype":"venue"
},
  "geometry": {"coordinates":[-97.420986,27.796699],"type":"Point"}
}