{
  "type": "Feature",
  "properties": {
    "iso:country":"US",
    "sg:address":"10115 Alfred Ln",
    "sg:city":"Houston",
    "sg:classifiers":[
        {
            "category":"Manufacturing",
            "subcategory":"Tools & Machinery",
            "type":"Manufacturing & Wholesale Goods"
        }
    ],
    "sg:phone":"+1 713 460 4561",
    "sg:postcode":"77041",
    "sg:province":"TX",
    "sg:tags":[
        "machine",
        "shop"
    ],
    "wof:name":"Quality Precision Mch Works",
    "wof:placetype":"venue"
},
  "geometry": {"coordinates":[-95.542281,29.854257],"type":"Point"}
}