{
  "type": "Feature",
  "properties": {
    "iso:country":"US",
    "sg:address":"3032 Northpark Dr",
    "sg:city":"Kingwood",
    "sg:classifiers":[
        {
            "category":"Shopping",
            "subcategory":"Gifts & Souvenirs",
            "type":"Retail Goods"
        }
    ],
    "sg:phone":"+1 281 361 0013",
    "sg:postcode":"77339",
    "sg:province":"TX",
    "sg:tags":[
        "shop"
    ],
    "wof:name":"Best Wishes Gifts Inc",
    "wof:placetype":"venue"
},
  "geometry": {"coordinates":[-95.195635,30.068117],"type":"Point"}
}