{
  "type": "Feature",
  "properties": {
    "iso:country":"US",
    "sg:address":"825 W Bitters Rd",
    "sg:city":"San Antonio",
    "sg:classifiers":[
        {
            "category":"Real Estate",
            "subcategory":"Real Estate Agent",
            "type":"Services"
        }
    ],
    "sg:phone":"+1 210 402 0888",
    "sg:postcode":"78216",
    "sg:province":"TX",
    "sg:tags":[
        "commercial",
        "developer"
    ],
    "wof:name":"Byco Commercial Development",
    "wof:placetype":"venue"
},
  "geometry": {"coordinates":[-98.50361700000001,29.581293],"type":"Point"}
}