{
  "type": "Feature",
  "properties": {
    "iso:country":"US",
    "sg:address":"2300 Nacogdoches Rd",
    "sg:city":"San Antonio",
    "sg:classifiers":[
        {
            "category":"Arts & Performance",
            "subcategory":"Theater",
            "type":"Entertainment"
        }
    ],
    "sg:phone":"+1 210 822 0982",
    "sg:postcode":"78209",
    "sg:province":"TX",
    "sg:tags":[
        "group"
    ],
    "wof:name":"Flute & Violin",
    "wof:placetype":"venue"
},
  "geometry": {"coordinates":[-98.452324,29.515606],"type":"Point"}
}