{
  "type": "Feature",
  "properties": {
    "iso:country":"US",
    "sg:address":"10547 Rocking M Trl",
    "sg:city":"Helotes",
    "sg:classifiers":[
        {
            "category":"Professional",
            "type":"Services"
        }
    ],
    "sg:phone":"+1 210 695 5328",
    "sg:postcode":"78023",
    "sg:province":"TX",
    "wof:name":"Cynthia Massey",
    "wof:placetype":"venue"
},
  "geometry": {"coordinates":[-98.685478,29.569918],"type":"Point"}
}