{
  "type": "Feature",
  "properties": {
    "iso:country":"US",
    "sg:address":"500 S Palestine St",
    "sg:city":"Athens",
    "sg:classifiers":[
        {
            "category":"Restaurant",
            "type":"Food & Drink"
        }
    ],
    "sg:phone":"+1 903 677 4226",
    "sg:postcode":"75751",
    "sg:province":"TX",
    "sg:tags":[
        "house",
        "steak",
        "barbecue"
    ],
    "wof:name":"Cripple Creek Bbq",
    "wof:placetype":"venue"
},
  "geometry": {"coordinates":[-95.853683,32.198353],"type":"Point"}
}