{
  "type": "Feature",
  "properties": {
    "iso:country":"US",
    "sg:address":"3434 Fazzino Ln",
    "sg:city":"Bryan",
    "sg:classifiers":[
        {
            "category":"Landmark",
            "subcategory":"Monument",
            "type":"Public Place"
        }
    ],
    "sg:phone":"+1 979 779 7329",
    "sg:postcode":"77807",
    "sg:province":"TX",
    "wof:name":"Granite Works",
    "wof:placetype":"venue"
},
  "geometry": {"coordinates":[-96.495598,30.653089],"type":"Point"}
}