{
  "type": "Feature",
  "properties": {
    "iso:country":"US",
    "sg:address":"101 E 14th St",
    "sg:city":"Mission",
    "sg:classifiers":[
        {
            "category":"Wholesale",
            "subcategory":"Machinery & Supplies",
            "type":"Manufacturing & Wholesale Goods"
        }
    ],
    "sg:phone":"+1 956 585 8387",
    "sg:postcode":"78572",
    "sg:province":"TX",
    "sg:tags":[
        "equipment",
        "irrigation",
        "system"
    ],
    "wof:name":"Hidalgo County Irrigation",
    "wof:placetype":"venue"
},
  "geometry": {"coordinates":[-98.323883,26.219707],"type":"Point"}
}