{
  "type": "Feature",
  "properties": {
    "iso:country":"US",
    "sg:address":"777 Taylor St",
    "sg:city":"Fort Worth",
    "sg:classifiers":[
        {
            "category":"Banks & Credit Unions",
            "subcategory":"Investment Brokerage",
            "type":"Services"
        }
    ],
    "sg:phone":"+1 817 335 2571",
    "sg:postcode":"76102",
    "sg:province":"TX",
    "sg:tags":[
        "banker",
        "stock"
    ],
    "wof:name":"Wachovia Securities",
    "wof:placetype":"venue"
},
  "geometry": {"coordinates":[-97.332453,32.752003],"type":"Point"}
}