{
  "type": "Feature",
  "properties": {
    "iso:country":"US",
    "sg:address":"911 Houston St",
    "sg:city":"Fort Worth",
    "sg:classifiers":[
        {
            "category":"Restaurant",
            "type":"Food & Drink"
        }
    ],
    "sg:phone":"+1 817 348 0559",
    "sg:postcode":"76102",
    "sg:province":"TX",
    "sg:tags":[
        "eating"
    ],
    "wof:name":"Savannahs Cafe",
    "wof:placetype":"venue"
},
  "geometry": {"coordinates":[-97.329798,32.751151],"type":"Point"}
}