{
  "type": "Feature",
  "properties": {
    "iso:country":"US",
    "sg:address":"119 N Blair St",
    "sg:city":"Belton",
    "sg:classifiers":[
        {
            "category":"Retail",
            "subcategory":"Auto Repair",
            "type":"Services"
        }
    ],
    "sg:phone":"+1 254 939 8323",
    "sg:postcode":"76513",
    "sg:province":"TX",
    "sg:tags":[
        "automotive"
    ],
    "wof:name":"Merls Front End Service",
    "wof:placetype":"venue"
},
  "geometry": {"coordinates":[-97.45934,31.055364],"type":"Point"}
}