{
  "type": "Feature",
  "properties": {
    "iso:country":"US",
    "sg:address":"3407 Douglas Ave",
    "sg:city":"El Paso",
    "sg:classifiers":[
        {
            "category":"Professional",
            "subcategory":"Detective & Security Services",
            "type":"Services"
        }
    ],
    "sg:phone":"+1 915 772 4951",
    "sg:postcode":"79903",
    "sg:province":"TX",
    "sg:tags":[
        "guard",
        "patrol"
    ],
    "wof:name":"Texas Enforcer",
    "wof:placetype":"venue"
},
  "geometry": {"coordinates":[-106.453446,31.787439],"type":"Point"}
}