{
  "type": "Feature",
  "properties": {
    "iso:country":"US",
    "sg:address":"2505 Heather Brook Ln",
    "sg:city":"Arlington",
    "sg:classifiers":[
        {
            "category":"Shopping",
            "subcategory":"Jewelry",
            "type":"Retail Goods"
        }
    ],
    "sg:phone":"+1 817 695 6858",
    "sg:postcode":"76006",
    "sg:province":"TX",
    "wof:name":"A Griffith Kari",
    "wof:placetype":"venue"
},
  "geometry": {"coordinates":[-97.064086,32.776802],"type":"Point"}
}