{
  "type": "Feature",
  "properties": {
    "iso:country":"US",
    "sg:address":"7416 Schuller Rd",
    "sg:city":"Houston",
    "sg:classifiers":[
        {
            "category":"Shopping",
            "subcategory":"Clothing, Apparel, & Fashions",
            "type":"Retail Goods"
        }
    ],
    "sg:phone":"+1 713 696 9505",
    "sg:postcode":"77093",
    "sg:province":"TX",
    "wof:name":"Mary's T Shirts",
    "wof:placetype":"venue"
},
  "geometry": {"coordinates":[-95.34060700000001,29.826363],"type":"Point"}
}