{
  "type": "Feature",
  "properties": {
    "iso:country":"US",
    "sg:address":"10200 Richmond Ave",
    "sg:city":"Houston",
    "sg:classifiers":[
        {
            "category":"Real Estate",
            "subcategory":"Architect",
            "type":"Services"
        }
    ],
    "sg:phone":"+1 713 784 0290",
    "sg:postcode":"77042",
    "sg:province":"TX",
    "sg:tags":[
        "architectural"
    ],
    "wof:name":"Worrell Design Group Inc",
    "wof:placetype":"venue"
},
  "geometry": {"coordinates":[-95.551299,29.728469],"type":"Point"}
}