{
  "type": "Feature",
  "properties": {
    "iso:country":"US",
    "sg:address":"800 Gessner Rd",
    "sg:city":"Houston",
    "sg:classifiers":[
        {
            "category":"Mining & Drilling",
            "type":"Manufacturing & Wholesale Goods"
        }
    ],
    "sg:phone":"+1 832 657 0603",
    "sg:postcode":"77024",
    "sg:province":"TX",
    "sg:tags":[
        "development",
        "gas",
        "oil",
        "exploration"
    ],
    "wof:name":"Elf Exploration",
    "wof:placetype":"venue"
},
  "geometry": {"coordinates":[-95.544478,29.778212],"type":"Point"}
}