{
  "type": "Feature",
  "properties": {
    "iso:country":"US",
    "sg:address":"9583 Sutter Park Ln",
    "sg:city":"Houston",
    "sg:classifiers":[
        {
            "category":"Freight",
            "type":"Transportation"
        }
    ],
    "sg:phone":"+1 281 447 4677",
    "sg:postcode":"77086",
    "sg:province":"TX",
    "sg:tags":[
        "trucking"
    ],
    "wof:name":"K & P Trucking",
    "wof:placetype":"venue"
},
  "geometry": {"coordinates":[-95.49879300000001,29.918779],"type":"Point"}
}