{
  "type": "Feature",
  "properties": {
    "iso:country":"US",
    "sg:address":"1927 Arvada Dr",
    "sg:city":"Richardson",
    "sg:classifiers":[
        {
            "category":"Manufacturing",
            "subcategory":"Glass & Minerals",
            "type":"Manufacturing & Wholesale Goods"
        }
    ],
    "sg:phone":"+1 972 238 7286",
    "sg:postcode":"75081",
    "sg:province":"TX",
    "sg:tags":[
        "product",
        "mfg"
    ],
    "wof:name":"Glass Designs Et Al",
    "wof:placetype":"venue"
},
  "geometry": {"coordinates":[-96.686443,32.970551],"type":"Point"}
}