{
  "type": "Feature",
  "properties": {
    "iso:country":"US",
    "sg:address":"4001 W Green Oaks Blvd",
    "sg:city":"Arlington",
    "sg:classifiers":[
        {
            "category":"Education",
            "subcategory":"Special Training",
            "type":"Public Place"
        }
    ],
    "sg:phone":"+1 817 478 7611",
    "sg:postcode":"76016",
    "sg:province":"TX",
    "wof:name":"Austin Driving School",
    "wof:placetype":"venue"
},
  "geometry": {"coordinates":[-97.195572,32.682657],"type":"Point"}
}