{
  "type": "Feature",
  "properties": {
    "iso:country":"US",
    "sg:address":"4009 New Orleans St",
    "sg:city":"Houston",
    "sg:classifiers":[
        {
            "category":"Shopping",
            "subcategory":"Clothing, Apparel, & Fashions",
            "type":"Retail Goods"
        }
    ],
    "sg:phone":"+1 713 675 4113",
    "sg:postcode":"77020",
    "sg:province":"TX",
    "wof:name":"Tonya & Troys Fashion/Bolden",
    "wof:placetype":"venue"
},
  "geometry": {"coordinates":[-95.329626,29.777073],"type":"Point"}
}