{
  "type": "Feature",
  "properties": {
    "iso:country":"US",
    "sg:address":"1401 E 7th St",
    "sg:city":"Austin",
    "sg:classifiers":[
        {
            "category":"Real Estate",
            "subcategory":"Architect",
            "type":"Services"
        }
    ],
    "sg:phone":"+1 512 495 1556",
    "sg:postcode":"78702",
    "sg:province":"TX",
    "wof:name":"Corder Jay",
    "wof:placetype":"venue"
},
  "geometry": {"coordinates":[-97.72807,30.2645],"type":"Point"}
}