{
  "type": "Feature",
  "properties": {
    "iso:country":"US",
    "sg:address":"10829 Opal Ridge Dr",
    "sg:city":"Houston",
    "sg:classifiers":[
        {
            "category":"Professional",
            "subcategory":"Business Services",
            "type":"Services"
        }
    ],
    "sg:phone":"+1 281 256 0709",
    "sg:postcode":"77095",
    "sg:province":"TX",
    "sg:tags":[
        "auction"
    ],
    "wof:name":"Greenval",
    "wof:placetype":"venue"
},
  "geometry": {"coordinates":[-95.668119,29.926761],"type":"Point"}
}