{
  "type": "Feature",
  "properties": {
    "iso:country":"US",
    "sg:address":"3329 Perry Ln",
    "sg:city":"Austin",
    "sg:classifiers":[
        {
            "category":"Professional",
            "subcategory":"Computer Services",
            "type":"Services"
        }
    ],
    "sg:phone":"+1 512 751 9041",
    "sg:postcode":"78731",
    "sg:province":"TX",
    "sg:tags":[
        "publisher",
        "software",
        "developer"
    ],
    "wof:name":"Austin Subsurface Modeling, Inc",
    "wof:placetype":"venue"
},
  "geometry": {"coordinates":[-97.764061,30.32929],"type":"Point"}
}