{
  "type": "Feature",
  "properties": {
    "iso:country":"US",
    "sg:address":"9531 Canvasback Dr",
    "sg:city":"Laredo",
    "sg:classifiers":[
        {
            "category":"Wholesale",
            "subcategory":"Computers",
            "type":"Manufacturing & Wholesale Goods"
        }
    ],
    "sg:phone":"+1 956 727 1852",
    "sg:postcode":"78045",
    "sg:province":"TX",
    "wof:name":"NP Computers",
    "wof:placetype":"venue"
},
  "geometry": {"coordinates":[-99.526348,27.583891],"type":"Point"}
}