{
  "type": "Feature",
  "properties": {
    "iso:country":"US",
    "sg:address":"1440 Daryll Ln",
    "sg:city":"Roanoke",
    "sg:classifiers":[
        {
            "category":"Restaurant",
            "type":"Food & Drink"
        }
    ],
    "sg:phone":"+1 817 337 1301",
    "sg:postcode":"76248",
    "sg:province":"TX",
    "sg:tags":[
        "eating"
    ],
    "wof:name":"J&S Concessions Inc",
    "wof:placetype":"venue"
},
  "geometry": {"coordinates":[-97.21898899999999,32.960509],"type":"Point"}
}