{
  "type": "Feature",
  "properties": {
    "iso:country":"US",
    "sg:address":"3803 Williams Dr",
    "sg:city":"Georgetown",
    "sg:classifiers":[
        {
            "category":"Recreation",
            "type":"Entertainment"
        }
    ],
    "sg:phone":"+1 512 930 5425",
    "sg:postcode":"78628",
    "sg:province":"TX",
    "sg:tags":[
        "martial",
        "arts",
        "instruction"
    ],
    "wof:name":"Bertling's Ata Blackbelt Acad",
    "wof:placetype":"venue"
},
  "geometry": {"coordinates":[-97.70129799999999,30.673451],"type":"Point"}
}