{
  "type": "Feature",
  "properties": {
    "iso:country":"US",
    "sg:address":"11333 N Central Expy",
    "sg:city":"Dallas",
    "sg:classifiers":[
        {
            "category":"Shopping",
            "subcategory":"Computers & Home Electronics",
            "type":"Retail Goods"
        }
    ],
    "sg:phone":"+1 214 265 9200",
    "sg:postcode":"75243",
    "sg:province":"TX",
    "sg:tags":[
        "equipment",
        "dealer"
    ],
    "wof:name":"Insterstate Capital",
    "wof:placetype":"venue"
},
  "geometry": {"coordinates":[-96.76952199999999,32.901927],"type":"Point"}
}