{
  "type": "Feature",
  "properties": {
    "iso:country":"US",
    "sg:address":"1419 N Indiana Ave",
    "sg:city":"Brownsville",
    "sg:phone":"+1 956 831 4806",
    "sg:postcode":"78521",
    "sg:province":"TX",
    "sg:tags":[
        "farm"
    ],
    "wof:name":"Roy Renfrow",
    "wof:placetype":"venue"
},
  "geometry": {"coordinates":[-97.40722100000001,25.931561],"type":"Point"}
}