{
  "type": "Feature",
  "properties": {
    "iso:country":"US",
    "sg:address":"324 Cedar Ln",
    "sg:city":"Channelview",
    "sg:classifiers":[
        {
            "category":"Real Estate",
            "subcategory":"Real Estate Operator",
            "type":"Services"
        }
    ],
    "sg:phone":"+1 281 452 3587",
    "sg:postcode":"77530",
    "sg:province":"TX",
    "sg:tags":[
        "mobile",
        "home",
        "site"
    ],
    "wof:name":"S&S Trailer Park",
    "wof:placetype":"venue"
},
  "geometry": {"coordinates":[-95.106686,29.787364],"type":"Point"}
}