{
  "type": "Feature",
  "properties": {
    "iso:country":"US",
    "sg:address":"1926 FM 720",
    "sg:city":"Little Elm",
    "sg:classifiers":[
        {
            "category":"Restaurant",
            "type":"Food & Drink"
        }
    ],
    "sg:phone":"+1 972 294 3800",
    "sg:postcode":"75068",
    "sg:province":"TX",
    "wof:name":"Roadrunner Pizza & Wings",
    "wof:placetype":"venue"
},
  "geometry": {"coordinates":[-96.97438200000001,33.166981],"type":"Point"}
}