{
  "type": "Feature",
  "properties": {
    "iso:country":"US",
    "sg:address":"192 Industrial Blvd",
    "sg:city":"Mc Kinney",
    "sg:classifiers":[
        {
            "category":"Building & Trades",
            "subcategory":"Construction",
            "type":"Services"
        }
    ],
    "sg:phone":"+1 214 544 2789",
    "sg:postcode":"75069",
    "sg:province":"TX",
    "sg:tags":[
        "painter"
    ],
    "wof:name":"Signature Custom Home Painting",
    "wof:placetype":"venue"
},
  "geometry": {"coordinates":[-96.61788300000001,33.179802],"type":"Point"}
}