{
  "type": "Feature",
  "properties": {
    "iso:country":"US",
    "sg:address":"9701 Beck Cir",
    "sg:city":"Austin",
    "sg:classifiers":[
        {
            "category":"Personal",
            "type":"Services"
        }
    ],
    "sg:phone":"+1 512 418 1062",
    "sg:postcode":"78758",
    "sg:province":"TX",
    "sg:tags":[
        "mover"
    ],
    "sg:website":"www.heartoftexasmoving.com",
    "wof:name":"Heart of Texas Moving",
    "wof:placetype":"venue"
},
  "geometry": {"coordinates":[-97.71320799999999,30.375394],"type":"Point"}
}