{
  "type": "Feature",
  "properties": {
    "iso:country":"US",
    "sg:address":"2459 Southwell Rd",
    "sg:city":"Dallas",
    "sg:classifiers":[
        {
            "category":"Freight",
            "type":"Transportation"
        }
    ],
    "sg:phone":"+1 972 243 1561",
    "sg:postcode":"75229",
    "sg:province":"TX",
    "sg:tags":[
        "warehouse",
        "storage"
    ],
    "wof:name":"Ground Development",
    "wof:placetype":"venue"
},
  "geometry": {"coordinates":[-96.896129,32.886365],"type":"Point"}
}