{
  "type": "Feature",
  "properties": {
    "iso:country":"US",
    "sg:address":"2305 Crystal Dr",
    "sg:city":"Mesquite",
    "sg:classifiers":[
        {
            "category":"Wholesale",
            "subcategory":"Electrical",
            "type":"Manufacturing & Wholesale Goods"
        }
    ],
    "sg:phone":"+1 972 288 6494",
    "sg:postcode":"75180",
    "sg:province":"TX",
    "sg:tags":[
        "lighting",
        "fixture"
    ],
    "wof:name":"Home Lighting & Automation",
    "wof:placetype":"venue"
},
  "geometry": {"coordinates":[-96.634154,32.740434],"type":"Point"}
}