{
  "type": "Feature",
  "properties": {
    "iso:country":"US",
    "sg:address":"906 Churchill Dr",
    "sg:city":"Granite Shoals",
    "sg:classifiers":[
        {
            "category":"Building & Trades",
            "subcategory":"Landscaping Services",
            "type":"Services"
        }
    ],
    "sg:phone":"+1 830 598 5978",
    "sg:postcode":"78654",
    "sg:province":"TX",
    "sg:tags":[
        "tree"
    ],
    "wof:name":"Boleyn's Stump & Tree Svc",
    "wof:placetype":"venue"
},
  "geometry": {"coordinates":[-98.349625,30.601018],"type":"Point"}
}