{
  "type": "Feature",
  "properties": {
    "iso:country":"US",
    "sg:address":"315 E Ave E",
    "sg:city":"Midlothian",
    "sg:classifiers":[
        {
            "category":"Education",
            "subcategory":"Special Training",
            "type":"Public Place"
        }
    ],
    "sg:phone":"+1 972 775 8236",
    "sg:postcode":"76065",
    "sg:province":"TX",
    "sg:tags":[
        "school"
    ],
    "wof:name":"Jenkins Center",
    "wof:placetype":"venue"
},
  "geometry": {"coordinates":[-96.990146,32.484432],"type":"Point"}
}