{
  "type": "Feature",
  "properties": {
    "iso:country":"US",
    "sg:address":"1899 FM 718",
    "sg:city":"Aurora",
    "sg:classifiers":[
        {
            "category":"Building & Trades",
            "subcategory":"Construction",
            "type":"Services"
        }
    ],
    "sg:phone":"+1 817 489 5588",
    "sg:postcode":"76052",
    "sg:province":"TX",
    "sg:tags":[
        "excavating",
        "contractor"
    ],
    "wof:name":"D & M Material",
    "wof:placetype":"venue"
},
  "geometry": {"coordinates":[-97.401752,32.968809],"type":"Point"}
}