{
  "type": "Feature",
  "properties": {
    "iso:country":"US",
    "sg:address":"211 Gym St",
    "sg:city":"Taylor",
    "sg:classifiers":[
        {
            "category":"Organizations",
            "subcategory":"Religious Organization",
            "type":"Services"
        }
    ],
    "sg:phone":"+1 512 352 5170",
    "sg:postcode":"76574",
    "sg:province":"TX",
    "wof:name":"New Tstment Hlness Cmnty Chrch",
    "wof:placetype":"venue"
},
  "geometry": {"coordinates":[-97.39840700000001,30.571342],"type":"Point"}
}