{
  "type": "Feature",
  "properties": {
    "iso:country":"US",
    "sg:address":"3333 N Yarbrough Dr",
    "sg:city":"El Paso",
    "sg:classifiers":[
        {
            "category":"Education",
            "subcategory":"Dance Studio",
            "type":"Public Place"
        }
    ],
    "sg:phone":"+1 915 598 4887",
    "sg:postcode":"79925",
    "sg:province":"TX",
    "sg:tags":[
        "instruction",
        "dancing"
    ],
    "wof:name":"Ligon Ballet Ctr",
    "wof:placetype":"venue"
},
  "geometry": {"coordinates":[-106.331125,31.791754],"type":"Point"}
}