{
  "type": "Feature",
  "properties": {
    "iso:country":"US",
    "sg:address":"5005 Sugar Lake Rd",
    "sg:city":"Fort Worth",
    "sg:classifiers":[
        {
            "category":"Professional",
            "subcategory":"Business Services",
            "type":"Services"
        }
    ],
    "sg:phone":"+1 817 457 8104",
    "sg:postcode":"76103",
    "sg:province":"TX",
    "wof:name":"Donald P Goodman",
    "wof:placetype":"venue"
},
  "geometry": {"coordinates":[-97.24809999999999,32.766439],"type":"Point"}
}