{
  "type": "Feature",
  "properties": {
    "iso:country":"US",
    "sg:address":"2681 Co Rd 429",
    "sg:city":"Pleasanton",
    "sg:classifiers":[
        {
            "category":"Wholesale",
            "subcategory":"Farm Supplies",
            "type":"Manufacturing & Wholesale Goods"
        }
    ],
    "sg:phone":"+1 830 281 8359",
    "sg:postcode":"78064",
    "sg:province":"TX",
    "sg:tags":[
        "livestock"
    ],
    "wof:name":"Mathis Ranch",
    "wof:placetype":"venue"
},
  "geometry": {"coordinates":[-98.46439100000001,28.894135],"type":"Point"}
}