{
  "type": "Feature",
  "properties": {
    "iso:country":"US",
    "sg:address":"80 Fort Brown St",
    "sg:city":"Brownsville",
    "sg:classifiers":[
        {
            "category":"Social Services",
            "subcategory":"Child Care",
            "type":"Services"
        }
    ],
    "sg:phone":"+1 956 544 8238",
    "sg:postcode":"78520",
    "sg:province":"TX",
    "sg:tags":[
        "day"
    ],
    "wof:name":"TSC Raul Gerra Early Child Ctr",
    "wof:placetype":"venue"
},
  "geometry": {"coordinates":[-97.492228,25.900366],"type":"Point"}
}