{
  "type": "Feature",
  "properties": {
    "iso:country":"US",
    "sg:address":"195 E Heywood St",
    "sg:city":"San Benito",
    "sg:classifiers":[
        {
            "category":"Health Services",
            "subcategory":"Clinic",
            "type":"Services"
        }
    ],
    "sg:phone":"+1 956 399 2662",
    "sg:postcode":"78586",
    "sg:province":"TX",
    "sg:tags":[
        "agency",
        "family"
    ],
    "wof:name":"Planned Parenthood",
    "wof:placetype":"venue"
},
  "geometry": {"coordinates":[-97.63023699999999,26.133374],"type":"Point"}
}