{
  "type": "Feature",
  "properties": {
    "iso:country":"US",
    "sg:address":"7240 N Loop Dr",
    "sg:city":"El Paso",
    "sg:classifiers":[
        {
            "category":"Restaurant",
            "type":"Food & Drink"
        }
    ],
    "sg:phone":"+1 915 779 6699",
    "sg:postcode":"79915",
    "sg:province":"TX",
    "wof:name":"Lalo's Restaurant",
    "wof:placetype":"venue"
},
  "geometry": {"coordinates":[-106.37684900000001,31.752357],"type":"Point"}
}