{
  "type": "Feature",
  "properties": {
    "iso:country":"US",
    "sg:address":"3728 Gordon Ave",
    "sg:city":"Fort Worth",
    "sg:classifiers":[
        {
            "category":"Wholesale",
            "subcategory":"Construction Materials",
            "type":"Manufacturing & Wholesale Goods"
        }
    ],
    "sg:phone":"+1 817 926 2273",
    "sg:postcode":"76110",
    "sg:province":"TX",
    "wof:name":"Souder Fencing",
    "wof:placetype":"venue"
},
  "geometry": {"coordinates":[-97.348395,32.694827],"type":"Point"}
}