{
  "type": "Feature",
  "properties": {
    "iso:country":"US",
    "sg:address":"2006 Longstraw Pl",
    "sg:city":"Spring",
    "sg:classifiers":[
        {
            "category":"Professional",
            "subcategory":"Management & Consulting",
            "type":"Services"
        }
    ],
    "sg:phone":"+1 281 367 4325",
    "sg:postcode":"77380",
    "sg:province":"TX",
    "sg:tags":[
        "natural",
        "filling",
        "station",
        "gas",
        "design"
    ],
    "wof:name":"Engine & Compressor Systems",
    "wof:placetype":"venue"
},
  "geometry": {"coordinates":[-95.466813,30.140283],"type":"Point"}
}