{
  "type": "Feature",
  "properties": {
    "iso:country":"US",
    "sg:address":"6132 Village Pkwy",
    "sg:city":"Houston",
    "sg:classifiers":[
        {
            "category":"Shopping",
            "type":"Retail Goods"
        }
    ],
    "sg:phone":"+1 713 807 7222",
    "sg:postcode":"77005",
    "sg:province":"TX",
    "sg:tags":[
        "telephone",
        "cellular"
    ],
    "wof:name":"Dynasty Wireless",
    "wof:placetype":"venue"
},
  "geometry": {"coordinates":[-95.41849999999999,29.716056],"type":"Point"}
}