{
  "type": "Feature",
  "properties": {
    "iso:country":"US",
    "sg:address":"207 N Sherman St",
    "sg:city":"Mexia",
    "sg:classifiers":[
        {
            "category":"Personal",
            "subcategory":"Beauty Salon",
            "type":"Services"
        }
    ],
    "sg:phone":"+1 254 562 2277",
    "sg:postcode":"76667",
    "sg:province":"TX",
    "sg:tags":[
        "shop"
    ],
    "wof:name":"Cats Meow The",
    "wof:placetype":"venue"
},
  "geometry": {"coordinates":[-96.483874,31.681912],"type":"Point"}
}