{
  "type": "Feature",
  "properties": {
    "iso:country":"US",
    "sg:address":"3606 Plum Creek Ct",
    "sg:city":"Midlothian",
    "sg:classifiers":[
        {
            "category":"Restaurant",
            "type":"Food & Drink"
        }
    ],
    "sg:phone":"+1 972 679 4679",
    "sg:postcode":"76065",
    "sg:province":"TX",
    "wof:name":"Texas Best Smokehouse 2",
    "wof:placetype":"venue"
},
  "geometry": {"coordinates":[-96.979602,32.444525],"type":"Point"}
}