{
  "type": "Feature",
  "properties": {
    "iso:country":"US",
    "sg:address":"1922 Horne Rd",
    "sg:city":"Corpus Christi",
    "sg:classifiers":[
        {
            "category":"Retail",
            "subcategory":"Self-service Laundry",
            "type":"Services"
        }
    ],
    "sg:phone":"+1 361 855 2511",
    "sg:postcode":"78416",
    "sg:province":"TX",
    "wof:name":"Ritter Coin Laundry & Dry Clng",
    "wof:placetype":"venue"
},
  "geometry": {"coordinates":[-97.424785,27.755256],"type":"Point"}
}