{
  "type": "Feature",
  "properties": {
    "iso:country":"US",
    "sg:address":"8 Shady Ln",
    "sg:city":"Longview",
    "sg:classifiers":[
        {
            "category":"Professional",
            "type":"Services"
        }
    ],
    "sg:phone":"+1 903 295 3344",
    "sg:postcode":"75604",
    "sg:province":"TX",
    "sg:tags":[
        "establishment"
    ],
    "wof:name":"Bobby Jones & Assoc",
    "wof:placetype":"venue"
},
  "geometry": {"coordinates":[-94.779703,32.509552],"type":"Point"}
}