{
  "type": "Feature",
  "properties": {
    "iso:country":"US",
    "sg:address":"722 Grillo Way",
    "sg:city":"Rosenberg",
    "sg:classifiers":[
        {
            "category":"Professional",
            "type":"Services"
        }
    ],
    "sg:phone":"+1 281 238 0037",
    "sg:postcode":"77471",
    "sg:province":"TX",
    "wof:name":"Angeles Crest",
    "wof:placetype":"venue"
},
  "geometry": {"coordinates":[-95.78036899999999,29.569448],"type":"Point"}
}