{
  "type": "Feature",
  "properties": {
    "iso:country":"US",
    "sg:address":"303 Rambelwood Pl",
    "sg:city":"Longview",
    "sg:classifiers":[
        {
            "category":"Professional",
            "subcategory":"Engineering",
            "type":"Services"
        }
    ],
    "sg:phone":"+1 903 757 6466",
    "sg:postcode":"75605",
    "sg:province":"TX",
    "sg:tags":[
        "engineer"
    ],
    "wof:name":"Canfield Engineering Inc",
    "wof:placetype":"venue"
},
  "geometry": {"coordinates":[-94.736878,32.526201],"type":"Point"}
}