{
  "type": "Feature",
  "properties": {
    "iso:country":"US",
    "sg:address":"1717 S Lake Dr",
    "sg:city":"Texarkana",
    "sg:classifiers":[
        {
            "category":"Retail",
            "subcategory":"Auto Repair",
            "type":"Services"
        }
    ],
    "sg:phone":"+1 903 793 1073",
    "sg:postcode":"75501",
    "sg:province":"TX",
    "sg:tags":[
        "repairing",
        "automobile",
        "general"
    ],
    "wof:name":"Mc Elroy's Repair Shop",
    "wof:placetype":"venue"
},
  "geometry": {"coordinates":[-94.061722,33.405164],"type":"Point"}
}