{
  "type": "Feature",
  "properties": {
    "iso:country":"US",
    "sg:address":"3949 W Line Rd",
    "sg:city":"Whitesboro",
    "sg:classifiers":[
        {
            "category":"Insurance",
            "subcategory":"Hazard Insurance",
            "type":"Services"
        }
    ],
    "sg:phone":"+1 903 564 7281",
    "sg:postcode":"76273",
    "sg:province":"TX",
    "wof:name":"Skrs Ltd Liability Co",
    "wof:placetype":"venue"
},
  "geometry": {"coordinates":[-96.94014199999999,33.610985],"type":"Point"}
}