{
  "type": "Feature",
  "properties": {
    "iso:country":"US",
    "sg:address":"5513 Taylors Valley Rd",
    "sg:city":"Temple",
    "sg:classifiers":[
        {
            "category":"Utilities",
            "subcategory":"Refuse",
            "type":"Services"
        }
    ],
    "sg:phone":"+1 254 933 9448",
    "sg:postcode":"76513",
    "sg:province":"TX",
    "sg:tags":[
        "garbage",
        "collection"
    ],
    "wof:name":"BFI Waste Systems",
    "wof:placetype":"venue"
},
  "geometry": {"coordinates":[-97.418419,31.044643],"type":"Point"}
}