{
  "type": "Feature",
  "properties": {
    "iso:country":"US",
    "sg:address":"501 NE 39th Ave",
    "sg:city":"Mineral Wells",
    "sg:classifiers":[
        {
            "category":"Professional",
            "type":"Services"
        }
    ],
    "sg:phone":"+1 940 325 8410",
    "sg:postcode":"76067",
    "sg:province":"TX",
    "wof:name":"Monroe & Son",
    "wof:placetype":"venue"
},
  "geometry": {"coordinates":[-98.073888,32.81474],"type":"Point"}
}