{
  "type": "Feature",
  "properties": {
    "iso:country":"US",
    "sg:address":"2523 Moreland Dr",
    "sg:city":"Mesquite",
    "sg:classifiers":[
        {
            "category":"Building & Trades",
            "subcategory":"Cleaning & Sanitation",
            "type":"Services"
        }
    ],
    "sg:phone":"+1 972 279 3827",
    "sg:postcode":"75150",
    "sg:province":"TX",
    "sg:tags":[
        "carpet"
    ],
    "wof:name":"Rendell Dennis N",
    "wof:placetype":"venue"
},
  "geometry": {"coordinates":[-96.63780199999999,32.7948],"type":"Point"}
}