{
  "type": "Feature",
  "properties": {
    "iso:country":"US",
    "sg:address":"6310 Airport Fwy",
    "sg:city":"Fort Worth",
    "sg:classifiers":[
        {
            "category":"Manufacturing",
            "subcategory":"Motor Vehicles & Parts",
            "type":"Manufacturing & Wholesale Goods"
        }
    ],
    "sg:phone":"+1 817 834 7309",
    "sg:postcode":"76117",
    "sg:province":"TX",
    "sg:tags":[
        "body",
        "mfg"
    ],
    "wof:name":"Classic Motor Cars",
    "wof:placetype":"venue"
},
  "geometry": {"coordinates":[-97.24629899999999,32.791161],"type":"Point"}
}