{
  "type": "Feature",
  "properties": {
    "iso:country":"US",
    "sg:address":"8347 Park Ln",
    "sg:city":"Dallas",
    "sg:classifiers":[
        {
            "category":"Shopping",
            "subcategory":"Beauty & Cosmetics",
            "type":"Retail Goods"
        }
    ],
    "sg:phone":"+1 214 265 7899",
    "sg:postcode":"75231",
    "sg:province":"TX",
    "sg:tags":[
        "supply"
    ],
    "wof:name":"Sabrina Beauty Supply",
    "wof:placetype":"venue"
},
  "geometry": {"coordinates":[-96.761358,32.871286],"type":"Point"}
}