{
  "type": "Feature",
  "properties": {
    "iso:country":"US",
    "sg:address":"6520 University Ave",
    "sg:city":"Lubbock",
    "sg:classifiers":[
        {
            "category":"Building & Trades",
            "subcategory":"Construction",
            "type":"Services"
        }
    ],
    "sg:phone":"+1 806 438 2549",
    "sg:postcode":"79413",
    "sg:province":"TX",
    "sg:tags":[
        "repairing",
        "remodeling",
        "contractor"
    ],
    "wof:name":"First Class Tile & Remodeling",
    "wof:placetype":"venue"
},
  "geometry": {"coordinates":[-101.870504,33.535315],"type":"Point"}
}