{
  "type": "Feature",
  "properties": {
    "iso:country":"US",
    "sg:address":"512 Santa Angela St",
    "sg:city":"Pharr",
    "sg:classifiers":[
        {
            "category":"Personal",
            "subcategory":"Beauty Salon",
            "type":"Services"
        }
    ],
    "sg:phone":"+1 956 702 4003",
    "sg:postcode":"78577",
    "sg:province":"TX",
    "sg:tags":[
        "cosmetologist"
    ],
    "wof:name":"Hollywood Beauty Salon",
    "wof:placetype":"venue"
},
  "geometry": {"coordinates":[-98.186099,26.122482],"type":"Point"}
}