{
  "type": "Feature",
  "properties": {
    "iso:country":"US",
    "sg:address":"1214 Lantana Estates Ct",
    "sg:city":"Fresno",
    "sg:classifiers":[
        {
            "category":"Retail",
            "subcategory":"Auto Repair",
            "type":"Services"
        }
    ],
    "sg:phone":"+1 281 431 3065",
    "sg:postcode":"77545",
    "sg:province":"TX",
    "sg:tags":[
        "automotive",
        "tune"
    ],
    "wof:name":"Rne Automotive",
    "wof:placetype":"venue"
},
  "geometry": {"coordinates":[-95.47142100000001,29.529253],"type":"Point"}
}