{
  "type": "Feature",
  "properties": {
    "iso:country":"US",
    "sg:address":"2115 Thompson Rd",
    "sg:city":"Richmond",
    "sg:classifiers":[
        {
            "category":"Retail",
            "subcategory":"Laundry & Dry Cleaning",
            "type":"Services"
        }
    ],
    "sg:phone":"+1 281 341 0879",
    "sg:postcode":"77469",
    "sg:province":"TX",
    "sg:tags":[
        "cleaners",
        "plant",
        "drycleaning"
    ],
    "wof:name":"Holiday Cleaners",
    "wof:placetype":"venue"
},
  "geometry": {"coordinates":[-95.76074,29.56542],"type":"Point"}
}