{
  "type": "Feature",
  "properties": {
    "iso:country":"US",
    "sg:address":"10709 Gettysburg St",
    "sg:city":"Corpus Christi",
    "sg:classifiers":[
        {
            "category":"Mining & Drilling",
            "type":"Manufacturing & Wholesale Goods"
        }
    ],
    "sg:phone":"+1 361 241 8469",
    "sg:postcode":"78410",
    "sg:province":"TX",
    "sg:tags":[
        "perforating",
        "well",
        "oil",
        "logging"
    ],
    "wof:name":"Texan Mudlogging Svc",
    "wof:placetype":"venue"
},
  "geometry": {"coordinates":[-97.57520700000001,27.844625],"type":"Point"}
}