{
  "type": "Feature",
  "properties": {
    "iso:country":"US",
    "sg:address":"602 E 4th St",
    "sg:city":"Alice",
    "sg:classifiers":[
        {
            "category":"Organizations",
            "subcategory":"Religious Organization",
            "type":"Services"
        }
    ],
    "sg:phone":"+1 361 668 3120",
    "sg:postcode":"78332",
    "sg:province":"TX",
    "sg:tags":[
        "church"
    ],
    "wof:name":"Texas Mc Allen Mission",
    "wof:placetype":"venue"
},
  "geometry": {"coordinates":[-98.07110299999999,27.754044],"type":"Point"}
}