{
  "type": "Feature",
  "properties": {
    "iso:country":"US",
    "sg:address":"19 Cooper Rd",
    "sg:city":"Houston",
    "sg:classifiers":[
        {
            "category":"Professional",
            "type":"Services"
        }
    ],
    "sg:phone":"+1 713 742 9159",
    "sg:postcode":"77076",
    "sg:province":"TX",
    "wof:name":"E Garcia Gonzalo",
    "wof:placetype":"venue"
},
  "geometry": {"coordinates":[-95.379739,29.86068],"type":"Point"}
}