{
  "type": "Feature",
  "properties": {
    "iso:country":"US",
    "sg:address":"600 Watson St",
    "sg:city":"Cleveland",
    "sg:classifiers":[
        {
            "category":"Personal",
            "subcategory":"Beauty Salon",
            "type":"Services"
        }
    ],
    "sg:phone":"+1 281 659 9800",
    "sg:postcode":"77327",
    "sg:province":"TX",
    "wof:name":"P J's Salon",
    "wof:placetype":"venue"
},
  "geometry": {"coordinates":[-95.08287,30.351999],"type":"Point"}
}