{
  "type": "Feature",
  "properties": {
    "iso:country":"US",
    "sg:address":"3601 Cottonwood Springs Dr",
    "sg:city":"Lewisville",
    "sg:classifiers":[
        {
            "category":"Professional",
            "type":"Services"
        }
    ],
    "sg:phone":"+1 972 370 1303",
    "sg:postcode":"75056",
    "sg:province":"TX",
    "wof:name":"Mbconnect Inc",
    "wof:placetype":"venue"
},
  "geometry": {"coordinates":[-96.91668799999999,33.084275],"type":"Point"}
}