{
  "type": "Feature",
  "properties": {
    "iso:country":"US",
    "sg:address":"6900 Midwood Pkwy",
    "sg:city":"Austin",
    "sg:classifiers":[
        {
            "category":"Professional",
            "type":"Services"
        }
    ],
    "sg:phone":"+1 512 288 6456",
    "sg:postcode":"78736",
    "sg:province":"TX",
    "wof:name":"Judith Hargrove",
    "wof:placetype":"venue"
},
  "geometry": {"coordinates":[-97.90975299999999,30.251898],"type":"Point"}
}