{
  "type": "Feature",
  "properties": {
    "iso:country":"US",
    "sg:address":"3903 Stillview Dr",
    "sg:city":"Houston",
    "sg:classifiers":[
        {
            "category":"Professional",
            "subcategory":"Business Services",
            "type":"Services"
        }
    ],
    "sg:phone":"+1 281 580 5350",
    "sg:postcode":"77068",
    "sg:province":"TX",
    "wof:name":"Louis James Enterprises Inc",
    "wof:placetype":"venue"
},
  "geometry": {"coordinates":[-95.490914,29.996131],"type":"Point"}
}