{
  "type": "Feature",
  "properties": {
    "iso:country":"US",
    "sg:address":"5800 Tradewind St",
    "sg:city":"Amarillo",
    "sg:classifiers":[
        {
            "category":"Manufacturing",
            "subcategory":"Tools & Machinery",
            "type":"Manufacturing & Wholesale Goods"
        }
    ],
    "sg:phone":"+1 806 622 0521",
    "sg:postcode":"79118",
    "sg:province":"TX",
    "sg:tags":[
        "machine",
        "shop"
    ],
    "wof:name":"Panhandle Service Repair Inc",
    "wof:placetype":"venue"
},
  "geometry": {"coordinates":[-101.83077,35.149421],"type":"Point"}
}