{
  "type": "Feature",
  "properties": {
    "iso:country":"US",
    "sg:address":"108 N Pecan St",
    "sg:city":"Bells",
    "sg:classifiers":[
        {
            "category":"Shopping",
            "subcategory":"Clothing, Apparel, & Fashions",
            "type":"Retail Goods"
        }
    ],
    "sg:phone":"+1 903 965 4098",
    "sg:postcode":"75414",
    "sg:province":"TX",
    "sg:tags":[
        "t"
    ],
    "wof:name":"Tall Tees",
    "wof:placetype":"venue"
},
  "geometry": {"coordinates":[-96.41046,33.611182],"type":"Point"}
}