{
  "type": "Feature",
  "properties": {
    "iso:country":"US",
    "sg:address":"3010 Lyndon B Johnson Fwy Fl 1200",
    "sg:city":"Dallas",
    "sg:classifiers":[
        {
            "category":"Shopping",
            "subcategory":"Computers & Home Electronics",
            "type":"Retail Goods"
        }
    ],
    "sg:phone":"+1 972 888 6042",
    "sg:postcode":"75234",
    "sg:province":"TX",
    "wof:name":"Heavenly Home Theater",
    "wof:placetype":"venue"
},
  "geometry": {"coordinates":[-96.87799800000001,32.911499],"type":"Point"}
}