{
  "type": "Feature",
  "properties": {
    "iso:country":"US",
    "sg:address":"120 S Briery Rd",
    "sg:city":"Irving",
    "sg:classifiers":[
        {
            "category":"Professional",
            "subcategory":"Art Services",
            "type":"Services"
        }
    ],
    "sg:phone":"+1 972 790 0512",
    "sg:postcode":"75060",
    "sg:province":"TX",
    "sg:tags":[
        "photographer"
    ],
    "wof:name":"Photo Stat",
    "wof:placetype":"venue"
},
  "geometry": {"coordinates":[-96.990156,32.814017],"type":"Point"}
}