{
  "type": "Feature",
  "properties": {
    "iso:country":"US",
    "sg:address":"4901 W Pasadena Blvd",
    "sg:city":"Deer Park",
    "sg:classifiers":[
        {
            "category":"Food & Beverages",
            "subcategory":"Groceries & Convenience Stores",
            "type":"Retail Goods"
        }
    ],
    "sg:phone":"+1 281 542 1012",
    "sg:postcode":"77536",
    "sg:province":"TX",
    "wof:name":"Deer Park Coastal",
    "wof:placetype":"venue"
},
  "geometry": {"coordinates":[-95.13797099999999,29.681815],"type":"Point"}
}