{
  "type": "Feature",
  "properties": {
    "iso:country":"US",
    "sg:address":"9613 Cedardale Dr",
    "sg:city":"Houston",
    "sg:classifiers":[
        {
            "category":"Communications",
            "subcategory":"Film & Video Production",
            "type":"Services"
        }
    ],
    "sg:phone":"+1 713 463 9818",
    "sg:postcode":"77055",
    "sg:province":"TX",
    "sg:tags":[
        "motion"
    ],
    "wof:name":"Catlin On Call",
    "wof:placetype":"venue"
},
  "geometry": {"coordinates":[-95.527815,29.791932],"type":"Point"}
}