{
  "type": "Feature",
  "properties": {
    "iso:country":"US",
    "sg:address":"1174 N 1st St",
    "sg:city":"Abilene",
    "sg:classifiers":[
        {
            "category":"Education",
            "subcategory":"Dance Studio",
            "type":"Public Place"
        },
        {
            "category":"Arts & Performance",
            "subcategory":"Theater",
            "type":"Entertainment"
        }
    ],
    "sg:phone":"+1 325 676 3775",
    "sg:postcode":"79601",
    "sg:province":"TX",
    "sg:tags":[
        "theatrical",
        "instruction",
        "producer",
        "dancing"
    ],
    "wof:name":"Abilene Performing Arts Co Inc",
    "wof:placetype":"venue"
},
  "geometry": {"coordinates":[-99.734739,32.449547],"type":"Point"}
}