{
  "type": "Feature",
  "properties": {
    "iso:country":"US",
    "sg:address":"7746 Grouse",
    "sg:city":"San Antonio",
    "sg:classifiers":[
        {
            "category":"Shopping",
            "subcategory":"Gifts & Souvenirs",
            "type":"Retail Goods"
        }
    ],
    "sg:phone":"+1 210 635 8793",
    "sg:postcode":"78223",
    "sg:province":"TX",
    "wof:name":"Candles Make Scents",
    "wof:placetype":"venue"
},
  "geometry": {"coordinates":[-98.34041000000001,29.279902],"type":"Point"}
}