{
  "type": "Feature",
  "properties": {
    "iso:country":"US",
    "sg:address":"5603 S Rice Ave",
    "sg:city":"Houston",
    "sg:classifiers":[
        {
            "category":"Shopping",
            "subcategory":"Stationery & Office Supplies",
            "type":"Retail Goods"
        }
    ],
    "sg:phone":"+1 713 666 2305",
    "sg:postcode":"77081",
    "sg:province":"TX",
    "sg:tags":[
        "equipment"
    ],
    "wof:name":"Hays Information Management Inc",
    "wof:placetype":"venue"
},
  "geometry": {"coordinates":[-95.468002,29.7211],"type":"Point"}
}