{
  "type": "Feature",
  "properties": {
    "iso:country":"US",
    "sg:address":"311 E Main St",
    "sg:city":"Yorktown",
    "sg:classifiers":[
        {
            "category":"Banks & Credit Unions",
            "subcategory":"Bank",
            "type":"Services"
        },
        {
            "category":"Banks & Credit Unions",
            "subcategory":"Financial Services",
            "type":"Services"
        }
    ],
    "sg:phone":"+1 361 564 4242",
    "sg:postcode":"78164",
    "sg:province":"TX",
    "sg:tags":[
        "commercial",
        "loan",
        "saving"
    ],
    "wof:name":"Citizens Bank-Yorktown",
    "wof:placetype":"venue"
},
  "geometry": {"coordinates":[-97.499583,28.981683],"type":"Point"}
}