{
  "type": "Feature",
  "properties": {
    "iso:country":"US",
    "sg:address":"2560 Neches St",
    "sg:city":"Beaumont",
    "sg:classifiers":[
        {
            "category":"Social Services",
            "subcategory":"Child Care",
            "type":"Services"
        }
    ],
    "sg:phone":"+1 409 838 1901",
    "sg:postcode":"77701",
    "sg:province":"TX",
    "sg:tags":[
        "day"
    ],
    "wof:name":"Day Care Center",
    "wof:placetype":"venue"
},
  "geometry": {"coordinates":[-94.095195,30.061731],"type":"Point"}
}