{
  "type": "Feature",
  "properties": {
    "iso:country":"US",
    "sg:address":"901 Thackeray Ln",
    "sg:city":"Pflugerville",
    "sg:classifiers":[
        {
            "category":"Professional",
            "type":"Services"
        }
    ],
    "sg:phone":"+1 512 252 1853",
    "sg:postcode":"78660",
    "sg:province":"TX",
    "wof:name":"Charisma Designs",
    "wof:placetype":"venue"
},
  "geometry": {"coordinates":[-97.640045,30.460777],"type":"Point"}
}