{
  "type": "Feature",
  "properties": {
    "iso:country":"US",
    "sg:address":"3031 Gibbs Williams Rd",
    "sg:city":"Dallas",
    "sg:classifiers":[
        {
            "category":"Building & Trades",
            "subcategory":"Construction",
            "type":"Services"
        }
    ],
    "sg:phone":"+1 214 339 3642",
    "sg:postcode":"75233",
    "sg:province":"TX",
    "sg:tags":[
        "house"
    ],
    "wof:name":"Tfw Construction",
    "wof:placetype":"venue"
},
  "geometry": {"coordinates":[-96.87000399999999,32.698304],"type":"Point"}
}