{
  "type": "Feature",
  "properties": {
    "iso:country":"US",
    "sg:address":"10303 Northwest Fwy",
    "sg:city":"Houston",
    "sg:classifiers":[
        {
            "category":"Wholesale",
            "subcategory":"Machinery & Supplies",
            "type":"Manufacturing & Wholesale Goods"
        }
    ],
    "sg:phone":"+1 713 957 4733",
    "sg:postcode":"77092",
    "sg:province":"TX",
    "sg:tags":[
        "equipment",
        "hydraulic"
    ],
    "sg:website":"www.confluids.com",
    "wof:name":"Controlled Fluids",
    "wof:placetype":"venue"
},
  "geometry": {"coordinates":[-95.457926,29.808874],"type":"Point"}
}