{
  "type": "Feature",
  "properties": {
    "iso:country":"US",
    "sg:address":"3403 Gulf Fwy",
    "sg:city":"Dickinson",
    "sg:classifiers":[
        {
            "category":"Insurance",
            "subcategory":"Insurance Agent",
            "type":"Services"
        }
    ],
    "sg:phone":"+1 281 337 5606",
    "sg:postcode":"77539",
    "sg:province":"TX",
    "wof:name":"Dennis Cooke Insurance",
    "wof:placetype":"venue"
},
  "geometry": {"coordinates":[-95.077977,29.449596],"type":"Point"}
}