{
  "type": "Feature",
  "properties": {
    "iso:country":"US",
    "sg:address":"1010 N Lamar Blvd",
    "sg:city":"Austin",
    "sg:classifiers":[
        {
            "category":"Retail",
            "subcategory":"Photofinishing",
            "type":"Services"
        }
    ],
    "sg:phone":"+1 512 480 0821",
    "sg:postcode":"78703",
    "sg:province":"TX",
    "sg:tags":[
        "laboratory"
    ],
    "wof:name":"Photomagic",
    "wof:placetype":"venue"
},
  "geometry": {"coordinates":[-97.751935,30.275892],"type":"Point"}
}