{
  "type": "Feature",
  "properties": {
    "iso:country":"US",
    "sg:address":"2309 Berkeley Ave # 1017",
    "sg:city":"Austin",
    "sg:classifiers":[
        {
            "category":"Transit Center",
            "subcategory":"Freight",
            "type":"Transportation"
        },
        {
            "category":"Freight",
            "type":"Transportation"
        }
    ],
    "sg:phone":"+1 512 707 0711",
    "sg:postcode":"78745",
    "sg:province":"TX",
    "sg:tags":[
        "local",
        "trucking-motor",
        "trucking"
    ],
    "wof:name":"Vela Trucking Inc",
    "wof:placetype":"venue"
},
  "geometry": {"coordinates":[-97.805808,30.209312],"type":"Point"}
}