{
  "type": "Feature",
  "properties": {
    "iso:country":"US",
    "sg:address":"301 E Main St",
    "sg:city":"Bishop",
    "sg:classifiers":[
        {
            "category":"Organizations",
            "subcategory":"Religious Organization",
            "type":"Services"
        }
    ],
    "sg:phone":"+1 361 584 2873",
    "sg:postcode":"78343",
    "sg:province":"TX",
    "sg:tags":[
        "churches-lutheran",
        "church"
    ],
    "wof:name":"St Johns Lutheran Church",
    "wof:placetype":"venue"
},
  "geometry": {"coordinates":[-97.797501,27.58427],"type":"Point"}
}