{
  "type": "Feature",
  "properties": {
    "iso:country":"US",
    "sg:address":"439 W 24th St",
    "sg:city":"Houston",
    "sg:classifiers":[
        {
            "category":"Building & Trades",
            "subcategory":"Electrical",
            "type":"Services"
        }
    ],
    "sg:phone":"+1 713 869 8898",
    "sg:postcode":"77008",
    "sg:province":"TX",
    "sg:tags":[
        "electrical",
        "contractor"
    ],
    "wof:name":"Job-Ject Electric",
    "wof:placetype":"venue"
},
  "geometry": {"coordinates":[-95.40519,29.808018],"type":"Point"}
}