{
  "type": "Feature",
  "properties": {
    "iso:country":"US",
    "sg:address":"209 N Bowie Ave",
    "sg:city":"Tulia",
    "sg:classifiers":[
        {
            "category":"Professional",
            "type":"Services"
        }
    ],
    "sg:phone":"+1 806 995 3583",
    "sg:postcode":"79088",
    "sg:province":"TX",
    "wof:name":"Heartscent",
    "wof:placetype":"venue"
},
  "geometry": {"coordinates":[-101.761717,34.53968],"type":"Point"}
}