{
  "type": "Feature",
  "properties": {
    "iso:country":"US",
    "sg:address":"3100 Timmons Ste130",
    "sg:city":"Houston",
    "sg:classifiers":[
        {
            "category":"Personal",
            "subcategory":"Nail Salon",
            "type":"Services"
        }
    ],
    "sg:phone":"+1 281 851 5899",
    "sg:postcode":"77027",
    "sg:province":"TX",
    "wof:name":"SPAthena MinxHouston",
    "wof:placetype":"venue"
},
  "geometry": {"coordinates":[-95.437119,29.736561],"type":"Point"}
}