{
  "type": "Feature",
  "properties": {
    "iso:country":"US",
    "sg:address":"25222 Grogans Mill Rd",
    "sg:city":"Spring",
    "sg:classifiers":[
        {
            "category":"Shopping",
            "subcategory":"Discount & Variety Stores",
            "type":"Retail Goods"
        },
        {
            "category":"Wholesale",
            "subcategory":"Hardware",
            "type":"Manufacturing & Wholesale Goods"
        }
    ],
    "sg:phone":"+1 281 419 9088",
    "sg:postcode":"77380",
    "sg:province":"TX",
    "sg:tags":[
        "cutlery",
        "merchandise",
        "general"
    ],
    "wof:name":"Geronimo's Knife",
    "wof:placetype":"venue"
},
  "geometry": {"coordinates":[-95.456913,30.128938],"type":"Point"}
}