{
  "type": "Feature",
  "properties": {
    "iso:country":"US",
    "sg:address":"3312 Woodford Dr",
    "sg:city":"Arlington",
    "sg:classifiers":[
        {
            "category":"Professional",
            "subcategory":"Management & Consulting",
            "type":"Services"
        },
        {
            "category":"Professional",
            "subcategory":"Employment Agencies",
            "type":"Services"
        }
    ],
    "sg:phone":"+1 817 277 0888",
    "sg:postcode":"76013",
    "sg:province":"TX",
    "sg:tags":[
        "consultant",
        "search",
        "executive",
        "opportunity"
    ],
    "wof:name":"Hedman Kent R & Associates",
    "wof:placetype":"venue"
},
  "geometry": {"coordinates":[-97.162209,32.729691],"type":"Point"}
}