{
  "type": "Feature",
  "properties": {
    "iso:country":"US",
    "sg:address":"5410 S Sugar Rd",
    "sg:city":"Edinburg",
    "sg:classifiers":[
        {
            "category":"Autos & Motor Vehicles",
            "subcategory":"Automobile Sales",
            "type":"Retail Goods"
        }
    ],
    "sg:phone":"+1 956 702 0240",
    "sg:postcode":"78539",
    "sg:province":"TX",
    "sg:tags":[
        "truck"
    ],
    "wof:name":"Diesel Country",
    "wof:placetype":"venue"
},
  "geometry": {"coordinates":[-98.185928,26.255277],"type":"Point"}
}