{
  "type": "Feature",
  "properties": {
    "iso:country":"US",
    "sg:address":"14877 Hillview Rd",
    "sg:city":"Tyler",
    "sg:classifiers":[
        {
            "category":"Professional",
            "subcategory":"Art Services",
            "type":"Services"
        }
    ],
    "sg:phone":"+1 903 984 9946",
    "sg:postcode":"75703",
    "sg:province":"TX",
    "sg:tags":[
        "commercial",
        "design"
    ],
    "wof:name":"Morninglory Creations",
    "wof:placetype":"venue"
},
  "geometry": {"coordinates":[-95.42278,32.250746],"type":"Point"}
}