{
  "type": "Feature",
  "properties": {
    "iso:country":"US",
    "sg:address":"2814 Ray Lieck",
    "sg:city":"San Antonio",
    "sg:classifiers":[
        {
            "category":"Manufacturing",
            "subcategory":"Printing",
            "type":"Manufacturing & Wholesale Goods"
        }
    ],
    "sg:phone":"+1 210 679 9411",
    "sg:postcode":"78253",
    "sg:province":"TX",
    "sg:tags":[
        "lithographic",
        "commercial"
    ],
    "wof:name":"Qts Moes Printing",
    "wof:placetype":"venue"
},
  "geometry": {"coordinates":[-98.76748499999999,29.463672],"type":"Point"}
}