{
  "type": "Feature",
  "properties": {
    "iso:country":"US",
    "sg:address":"1218 W Shady Grove Rd",
    "sg:city":"Irving",
    "sg:classifiers":[
        {
            "category":"Building & Trades",
            "subcategory":"Electrical",
            "type":"Services"
        }
    ],
    "sg:phone":"+1 972 986 4330",
    "sg:postcode":"75060",
    "sg:province":"TX",
    "sg:tags":[
        "electrician"
    ],
    "wof:name":"Automated Power System",
    "wof:placetype":"venue"
},
  "geometry": {"coordinates":[-96.960403,32.802601],"type":"Point"}
}