{
  "type": "Feature",
  "properties": {
    "iso:country":"US",
    "sg:address":"13333 Northborough Dr",
    "sg:city":"Houston",
    "sg:classifiers":[
        {
            "category":"Professional",
            "subcategory":"Computer Services",
            "type":"Services"
        }
    ],
    "sg:phone":"+1 281 873 5019",
    "sg:postcode":"77067",
    "sg:province":"TX",
    "sg:tags":[
        "related"
    ],
    "wof:name":"Binary Logic",
    "wof:placetype":"venue"
},
  "geometry": {"coordinates":[-95.42365100000001,29.959451],"type":"Point"}
}