{
  "type": "Feature",
  "properties": {
    "iso:country":"US",
    "sg:address":"1714 Parklake Village",
    "sg:city":"Katy",
    "sg:classifiers":[
        {
            "category":"Building & Trades",
            "subcategory":"Construction",
            "type":"Services"
        }
    ],
    "sg:phone":"+1 281 398 1189",
    "sg:postcode":"77450",
    "sg:province":"TX",
    "sg:tags":[
        "house"
    ],
    "wof:name":"Mitchell Carroll & Associates",
    "wof:placetype":"venue"
},
  "geometry": {"coordinates":[-95.712913,29.754947],"type":"Point"}
}