{
  "type": "Feature",
  "properties": {
    "iso:country":"US",
    "sg:address":"414 Weaver St",
    "sg:city":"Cedar Hill",
    "sg:classifiers":[
        {
            "category":"Retail",
            "subcategory":"Repair Shop",
            "type":"Services"
        }
    ],
    "sg:phone":"+1 972 291 2939",
    "sg:postcode":"75104",
    "sg:province":"TX",
    "wof:name":"Horn Shop",
    "wof:placetype":"venue"
},
  "geometry": {"coordinates":[-96.937828,32.581185],"type":"Point"}
}