{
  "type": "Feature",
  "properties": {
    "iso:country":"US",
    "sg:address":"900 Coury Rd",
    "sg:city":"Fort Worth",
    "sg:classifiers":[
        {
            "category":"Social Services",
            "subcategory":"Child Care",
            "type":"Services"
        }
    ],
    "sg:phone":"+1 817 293 0277",
    "sg:postcode":"76140",
    "sg:province":"TX",
    "sg:tags":[
        "day"
    ],
    "wof:name":"Jackson's Daycare",
    "wof:placetype":"venue"
},
  "geometry": {"coordinates":[-97.294573,32.625685],"type":"Point"}
}