{
  "type": "Feature",
  "properties": {
    "iso:country":"US",
    "sg:address":"20 E 31st St",
    "sg:city":"San Angelo",
    "sg:classifiers":[
        {
            "category":"Building & Trades",
            "subcategory":"Plumbing",
            "type":"Services"
        }
    ],
    "sg:phone":"+1 325 653 1052",
    "sg:postcode":"76903",
    "sg:province":"TX",
    "sg:tags":[
        "air",
        "heating",
        "conditioning",
        "contractor"
    ],
    "wof:name":"Wade Heating & AC",
    "wof:placetype":"venue"
},
  "geometry": {"coordinates":[-100.452805,31.493054],"type":"Point"}
}