{
  "type": "Feature",
  "properties": {
    "iso:country":"US",
    "sg:address":"518 E Harrison Ave",
    "sg:city":"Harlingen",
    "sg:classifiers":[
        {
            "category":"Organizations",
            "subcategory":"Non-profit Organization",
            "type":"Services"
        }
    ],
    "sg:phone":"+1 956 421 2351",
    "sg:postcode":"78550",
    "sg:province":"TX",
    "wof:name":"Harlingen Community Dev Corp",
    "wof:placetype":"venue"
},
  "geometry": {"coordinates":[-97.69034600000001,26.190603],"type":"Point"}
}