{
  "type": "Feature",
  "properties": {
    "iso:country":"US",
    "sg:address":"602 Rio Grande Dr",
    "sg:city":"Mission",
    "sg:classifiers":[
        {
            "category":"Building & Trades",
            "subcategory":"Construction",
            "type":"Services"
        }
    ],
    "sg:phone":"+1 956 581 4256",
    "sg:postcode":"78572",
    "sg:province":"TX",
    "sg:tags":[
        "house"
    ],
    "wof:name":"Ornelas Builders Inc",
    "wof:placetype":"venue"
},
  "geometry": {"coordinates":[-98.301378,26.187217],"type":"Point"}
}