{
  "type": "Feature",
  "properties": {
    "iso:country":"US",
    "sg:address":"14330 Midway Rd Bldg 1, Ste 121",
    "sg:city":"Dallas",
    "sg:classifiers":[
        {
            "category":"Community Center",
            "type":"Public Place"
        }
    ],
    "sg:phone":"+1 972 930 0260",
    "sg:postcode":"75244",
    "sg:province":"TX",
    "sg:tags":[
        "medical"
    ],
    "sg:website":"www.livingwelldallas.com",
    "wof:name":"Living Well Health & Wellness Center",
    "wof:placetype":"venue"
},
  "geometry": {"coordinates":[-96.83785399999999,32.94642],"type":"Point"}
}