{
  "type": "Feature",
  "properties": {
    "iso:country":"US",
    "sg:address":"12710 Palm Desert Ln",
    "sg:city":"Houston",
    "sg:classifiers":[
        {
            "category":"Professional",
            "type":"Services"
        }
    ],
    "sg:phone":"+1 281 495 8599",
    "sg:postcode":"77099",
    "sg:province":"TX",
    "wof:name":"Mir Alikhan",
    "wof:placetype":"venue"
},
  "geometry": {"coordinates":[-95.608008,29.673645],"type":"Point"}
}