{
  "type": "Feature",
  "properties": {
    "iso:country":"US",
    "sg:address":"15103 Runnymede St",
    "sg:city":"Conroe",
    "sg:classifiers":[
        {
            "category":"Professional",
            "subcategory":"Computer Services",
            "type":"Services"
        }
    ],
    "sg:phone":"+1 936 321 5908",
    "sg:postcode":"77384",
    "sg:province":"TX",
    "sg:tags":[
        "related"
    ],
    "wof:name":"Lorenz Interest",
    "wof:placetype":"venue"
},
  "geometry": {"coordinates":[-95.538117,30.236688],"type":"Point"}
}