{
  "type": "Feature",
  "properties": {
    "iso:country":"US",
    "sg:address":"1420 Layton St",
    "sg:city":"Fort Worth",
    "sg:classifiers":[
        {
            "category":"Manufacturing",
            "subcategory":"Metals",
            "type":"Manufacturing & Wholesale Goods"
        }
    ],
    "sg:phone":"+1 817 831 1222",
    "sg:postcode":"76117",
    "sg:province":"TX",
    "sg:tags":[
        "tower"
    ],
    "wof:name":"Andrews Tower Inc",
    "wof:placetype":"venue"
},
  "geometry": {"coordinates":[-97.28236800000001,32.783125],"type":"Point"}
}