{
  "type": "Feature",
  "properties": {
    "iso:country":"US",
    "sg:address":"4055 Buena Vista St",
    "sg:city":"Dallas",
    "sg:classifiers":[
        {
            "category":"Shopping",
            "subcategory":"Clothing, Apparel, & Fashions",
            "type":"Retail Goods"
        }
    ],
    "sg:phone":"+1 214 336 9433",
    "sg:postcode":"75204",
    "sg:province":"TX",
    "wof:name":"Style H LLC",
    "wof:placetype":"venue"
},
  "geometry": {"coordinates":[-96.796727,32.813859],"type":"Point"}
}