{
  "type": "Feature",
  "properties": {
    "iso:country":"US",
    "sg:address":"4747 Irving Blvd Ste 223",
    "sg:city":"Dallas",
    "sg:classifiers":[
        {
            "category":"Professional",
            "subcategory":"Employment Agencies",
            "type":"Services"
        }
    ],
    "sg:phone":"+1 214 638 5601",
    "sg:postcode":"75247",
    "sg:province":"TX",
    "wof:name":"Gonzales Labor Systems",
    "wof:placetype":"venue"
},
  "geometry": {"coordinates":[-96.896961,32.809462],"type":"Point"}
}