{
  "type": "Feature",
  "properties": {
    "iso:country":"US",
    "sg:address":"15108 Oakwood Ln",
    "sg:city":"Mesquite",
    "sg:classifiers":[
        {
            "category":"Building & Trades",
            "subcategory":"Construction",
            "type":"Services"
        }
    ],
    "sg:phone":"+1 972 365 4549",
    "sg:postcode":"75180",
    "sg:province":"TX",
    "sg:tags":[
        "builder",
        "patio"
    ],
    "wof:name":"JMA Framing Projects",
    "wof:placetype":"venue"
},
  "geometry": {"coordinates":[-96.59836199999999,32.716519],"type":"Point"}
}