{
  "type": "Feature",
  "properties": {
    "iso:country":"US",
    "sg:address":"2260 W Holcombe Blvd",
    "sg:city":"Houston",
    "sg:classifiers":[
        {
            "category":"Shopping",
            "subcategory":"Musical Instruments",
            "type":"Retail Goods"
        }
    ],
    "sg:phone":"+1 713 665 2639",
    "sg:postcode":"77030",
    "sg:province":"TX",
    "wof:name":"Girls With Guitars",
    "wof:placetype":"venue"
},
  "geometry": {"coordinates":[-95.41193,29.706135],"type":"Point"}
}