{
  "type": "Feature",
  "properties": {
    "iso:country":"US",
    "sg:address":"1049 N Shepherd Dr",
    "sg:city":"Houston",
    "sg:classifiers":[
        {
            "category":"Retail",
            "subcategory":"Auto Repair",
            "type":"Services"
        }
    ],
    "sg:phone":"+1 713 864 7424",
    "sg:postcode":"77008",
    "sg:province":"TX",
    "sg:tags":[
        "station",
        "gasoline",
        "general"
    ],
    "wof:name":"Texaco",
    "wof:placetype":"venue"
},
  "geometry": {"coordinates":[-95.40996800000001,29.7904],"type":"Point"}
}