{
  "type": "Feature",
  "properties": {
    "iso:country":"US",
    "sg:address":"6921 Lake June Rd Dallas",
    "sg:city":"Dallas",
    "sg:classifiers":[
        {
            "category":"Restaurant",
            "type":"Food & Drink"
        }
    ],
    "sg:phone":"+1 214 309 1999",
    "sg:postcode":"75217",
    "sg:province":"TX",
    "sg:tags":[
        "pizza"
    ],
    "wof:name":"Divino's Pizza",
    "wof:placetype":"venue"
},
  "geometry": {"coordinates":[-96.702659,32.734409],"type":"Point"}
}