{
  "type": "Feature",
  "properties": {
    "iso:country":"US",
    "sg:address":"2930 Ave F",
    "sg:city":"Beaumont",
    "sg:classifiers":[
        {
            "category":"Organizations",
            "subcategory":"Religious Organization",
            "type":"Services"
        }
    ],
    "sg:phone":"+1 409 835 4043",
    "sg:postcode":"77701",
    "sg:province":"TX",
    "sg:tags":[
        "church"
    ],
    "wof:name":"Christ Fellowship Church",
    "wof:placetype":"venue"
},
  "geometry": {"coordinates":[-94.105358,30.057401],"type":"Point"}
}