{
  "type": "Feature",
  "properties": {
    "iso:country":"US",
    "sg:address":"318 W Main St",
    "sg:city":"Arlington",
    "sg:classifiers":[
        {
            "category":"Professional",
            "subcategory":"Accounting & Tax Preparation",
            "type":"Services"
        }
    ],
    "sg:phone":"+1 817 276 0318",
    "sg:postcode":"76010",
    "sg:province":"TX",
    "sg:tags":[
        "return",
        "filing"
    ],
    "wof:name":"Genesis Bookkeeping & Tax LLC",
    "wof:placetype":"venue"
},
  "geometry": {"coordinates":[-97.11051999999999,32.736655],"type":"Point"}
}