{
  "type": "Feature",
  "properties": {
    "iso:country":"US",
    "sg:address":"901 Center Cir",
    "sg:city":"Salado",
    "sg:classifiers":[
        {
            "category":"Travel",
            "subcategory":"Hotels & Motels",
            "type":"Entertainment"
        }
    ],
    "sg:phone":"+1 254 947 3136",
    "sg:postcode":"76571",
    "sg:province":"TX",
    "sg:tags":[
        "operation"
    ],
    "wof:name":"Phillip Ellis",
    "wof:placetype":"venue"
},
  "geometry": {"coordinates":[-97.53254699999999,30.941746],"type":"Point"}
}