{
  "type": "Feature",
  "properties": {
    "iso:country":"US",
    "sg:address":"1029 Westwood Dr",
    "sg:city":"Graham",
    "sg:classifiers":[
        {
            "category":"Farming",
            "subcategory":"Farm",
            "type":"Manufacturing & Wholesale Goods"
        }
    ],
    "sg:phone":"+1 940 521 9152",
    "sg:postcode":"76450",
    "sg:province":"TX",
    "wof:name":"Brown Farm",
    "wof:placetype":"venue"
},
  "geometry": {"coordinates":[-98.582202,33.087875],"type":"Point"}
}