{
  "type": "Feature",
  "properties": {
    "iso:country":"US",
    "sg:address":"4310 Iola Ave",
    "sg:city":"Lubbock",
    "sg:classifiers":[
        {
            "category":"Wholesale",
            "subcategory":"Medical Equipment & Supplies",
            "type":"Manufacturing & Wholesale Goods"
        }
    ],
    "sg:phone":"+1 806 792 9844",
    "sg:postcode":"79407",
    "sg:province":"TX",
    "sg:tags":[
        "hospital"
    ],
    "wof:name":"American Home Patient Inc",
    "wof:placetype":"venue"
},
  "geometry": {"coordinates":[-101.947756,33.553682],"type":"Point"}
}