{
  "type": "Feature",
  "properties": {
    "iso:country":"US",
    "sg:address":"2306 Amy Lynn Ln",
    "sg:city":"Cedar Park",
    "sg:classifiers":[
        {
            "category":"Retail",
            "subcategory":"Portrait Studio",
            "type":"Services"
        }
    ],
    "sg:phone":"+1 512 848 9585",
    "sg:postcode":"78613",
    "sg:province":"TX",
    "sg:tags":[
        "photo"
    ],
    "wof:name":"Heartfire Photography",
    "wof:placetype":"venue"
},
  "geometry": {"coordinates":[-97.857904,30.531688],"type":"Point"}
}