{
  "type": "Feature",
  "properties": {
    "iso:country":"US",
    "sg:address":"210 W Tyler Ave",
    "sg:city":"Longview",
    "sg:classifiers":[
        {
            "category":"Home & Garden",
            "subcategory":"Garden Supply",
            "type":"Retail Goods"
        }
    ],
    "sg:phone":"+1 903 753 3599",
    "sg:postcode":"75601",
    "sg:province":"TX",
    "sg:tags":[
        "sprinkler"
    ],
    "wof:name":"Rusty Tuckers Sprinkler Co",
    "wof:placetype":"venue"
},
  "geometry": {"coordinates":[-94.74316899999999,32.496115],"type":"Point"}
}