{
  "type": "Feature",
  "properties": {
    "iso:country":"US",
    "sg:address":"2068 N Valley Mills Dr",
    "sg:city":"Waco",
    "sg:classifiers":[
        {
            "category":"Professional",
            "type":"Services"
        }
    ],
    "sg:phone":"+1 254 776 7290",
    "sg:postcode":"76710",
    "sg:province":"TX",
    "wof:name":"Automated Shrimp Corp",
    "wof:placetype":"venue"
},
  "geometry": {"coordinates":[-97.20348799999999,31.5326],"type":"Point"}
}