{
  "type": "Feature",
  "properties": {
    "iso:country":"US",
    "sg:address":"1977 Main St",
    "sg:city":"Junction",
    "sg:classifiers":[
        {
            "category":"Local Transit",
            "type":"Transportation"
        }
    ],
    "sg:phone":"+1 325 446 4871",
    "sg:postcode":"76849",
    "sg:province":"TX",
    "sg:tags":[
        "bus",
        "line"
    ],
    "wof:name":"Kerrville Bus Stop",
    "wof:placetype":"venue"
},
  "geometry": {"coordinates":[-99.778222,30.497782],"type":"Point"}
}