{
  "type": "Feature",
  "properties": {
    "iso:country":"US",
    "sg:address":"4054 Drummond St",
    "sg:city":"Houston",
    "sg:classifiers":[
        {
            "category":"Retail",
            "subcategory":"Portrait Studio",
            "type":"Services"
        }
    ],
    "sg:phone":"+1 713 666 7732",
    "sg:postcode":"77025",
    "sg:province":"TX",
    "sg:tags":[
        "photo"
    ],
    "wof:name":"Tom Berwick Photography",
    "wof:placetype":"venue"
},
  "geometry": {"coordinates":[-95.441024,29.696073],"type":"Point"}
}