{
  "type": "Feature",
  "properties": {
    "iso:country":"US",
    "sg:address":"1100 Sleepy Hollow Rd",
    "sg:city":"Woodway",
    "sg:classifiers":[
        {
            "category":"Shopping",
            "subcategory":"Used Merchandise",
            "type":"Retail Goods"
        }
    ],
    "sg:phone":"+1 254 772 5315",
    "sg:postcode":"76712",
    "sg:province":"TX",
    "sg:tags":[
        "second",
        "store",
        "hand"
    ],
    "wof:name":"Benson's",
    "wof:placetype":"venue"
},
  "geometry": {"coordinates":[-97.234162,31.505606],"type":"Point"}
}