{
  "type": "Feature",
  "properties": {
    "iso:country":"US",
    "sg:address":"5901 Brook Hollow Dr",
    "sg:city":"El Paso",
    "sg:classifiers":[
        {
            "category":"Restaurant",
            "type":"Food & Drink"
        }
    ],
    "sg:phone":"+1 915 772 7057",
    "sg:postcode":"79925",
    "sg:province":"TX",
    "sg:tags":[
        "eating"
    ],
    "wof:name":"LA Malinche",
    "wof:placetype":"venue"
},
  "geometry": {"coordinates":[-106.413439,31.787713],"type":"Point"}
}