{
  "type": "Feature",
  "properties": {
    "iso:country":"US",
    "sg:address":"803 Dunson Glen Dr",
    "sg:city":"Houston",
    "sg:classifiers":[
        {
            "category":"Personal",
            "subcategory":"Beauty Salon",
            "type":"Services"
        }
    ],
    "sg:phone":"+1 281 880 8984",
    "sg:postcode":"77090",
    "sg:province":"TX",
    "sg:tags":[
        "shop"
    ],
    "wof:name":"Barber Beauty & Braids",
    "wof:placetype":"venue"
},
  "geometry": {"coordinates":[-95.432446,29.988057],"type":"Point"}
}