{
  "type": "Feature",
  "properties": {
    "iso:country":"US",
    "sg:address":"315 E Sagebrush St",
    "sg:city":"Rockport",
    "sg:classifiers":[
        {
            "category":"Personal",
            "subcategory":"Beauty Salon",
            "type":"Services"
        }
    ],
    "sg:phone":"+1 361 729 6127",
    "sg:postcode":"78382",
    "sg:province":"TX",
    "wof:name":"Shannon Coleman",
    "wof:placetype":"venue"
},
  "geometry": {"coordinates":[-97.09474400000001,28.063844],"type":"Point"}
}