{
  "type": "Feature",
  "properties": {
    "iso:country":"US",
    "sg:address":"306 E Main St",
    "sg:city":"Crosbyton",
    "sg:classifiers":[
        {
            "category":"Wholesale",
            "subcategory":"Farm Supplies",
            "type":"Manufacturing & Wholesale Goods"
        }
    ],
    "sg:phone":"+1 806 675 2308",
    "sg:postcode":"79322",
    "sg:province":"TX",
    "sg:tags":[
        "bulb",
        "seed"
    ],
    "sg:website":"www.crosbytonseed.com",
    "wof:name":"Crosbyton Seed Co",
    "wof:placetype":"venue"
},
  "geometry": {"coordinates":[-101.235452,33.659921],"type":"Point"}
}