{
  "type": "Feature",
  "properties": {
    "iso:country":"US",
    "sg:address":"2941 W Anderson Ln",
    "sg:city":"Austin",
    "sg:classifiers":[
        {
            "category":"Health Services",
            "subcategory":"Chiropractor",
            "type":"Services"
        }
    ],
    "sg:phone":"+1 512 419 1367",
    "sg:postcode":"78757",
    "sg:province":"TX",
    "wof:name":"Austin Hillside Family Chiropractic",
    "wof:placetype":"venue"
},
  "geometry": {"coordinates":[-97.738995,30.359869],"type":"Point"}
}