{
  "type": "Feature",
  "properties": {
    "iso:country":"US",
    "sg:address":"882 Martinez St",
    "sg:city":"Pecos",
    "sg:classifiers":[
        {
            "category":"Organizations",
            "subcategory":"Religious Organization",
            "type":"Services"
        }
    ],
    "sg:phone":"+1 432 445 5623",
    "sg:postcode":"79772",
    "sg:province":"TX",
    "wof:name":"Community Church of Christ",
    "wof:placetype":"venue"
},
  "geometry": {"coordinates":[-103.481255,31.423815],"type":"Point"}
}