{
  "type": "Feature",
  "properties": {
    "iso:country":"US",
    "sg:address":"5326 W 34th St",
    "sg:city":"Houston",
    "sg:classifiers":[
        {
            "category":"Restaurant",
            "type":"Food & Drink"
        }
    ],
    "sg:menulink":"http://www.allmenus.com/tx/houston/62785-subway/menu/",
    "sg:phone":"+1 713 956 6139",
    "sg:postcode":"77092",
    "sg:province":"TX",
    "sg:tags":[
        "american",
        "sandwich"
    ],
    "wof:name":"Subway",
    "wof:placetype":"venue"
},
  "geometry": {"coordinates":[-95.46719400000001,29.819567],"type":"Point"}
}