{
  "type": "Feature",
  "properties": {
    "iso:country":"US",
    "sg:address":"4520 Techniplex Drive",
    "sg:city":"Stafford",
    "sg:classifiers":[
        {
            "category":"Travel",
            "subcategory":"Hotels & Motels",
            "type":"Entertainment"
        }
    ],
    "sg:phone":"+1 281 265 2760",
    "sg:postcode":"77477",
    "sg:province":"TX",
    "sg:website":"http://www.houstonstafford.homewoodsuites.com",
    "wof:name":"Homewood Suites by Hilton - Stafford",
    "wof:placetype":"venue"
},
  "geometry": {"coordinates":[-95.580991,29.635899],"type":"Point"}
}