{
  "type": "Feature",
  "properties": {
    "iso:country":"US",
    "sg:address":"5615 Troup Hwy",
    "sg:city":"Tyler",
    "sg:classifiers":[
        {
            "category":"Arts & Performance",
            "subcategory":"Dance",
            "type":"Entertainment"
        }
    ],
    "sg:phone":"+1 903 509 3400",
    "sg:postcode":"75707",
    "sg:province":"TX",
    "sg:tags":[
        "instruction",
        "dancing"
    ],
    "wof:name":"Project Dance",
    "wof:placetype":"venue"
},
  "geometry": {"coordinates":[-95.257105,32.291586],"type":"Point"}
}