{
  "type": "Feature",
  "properties": {
    "iso:country":"US",
    "sg:address":"1107 California Ln",
    "sg:city":"Arlington",
    "sg:classifiers":[
        {
            "category":"Wholesale",
            "subcategory":"Machinery & Supplies",
            "type":"Manufacturing & Wholesale Goods"
        }
    ],
    "sg:phone":"+1 817 277 1823",
    "sg:postcode":"76015",
    "sg:province":"TX",
    "sg:tags":[
        "equipment",
        "industrial"
    ],
    "wof:name":"Cool Zone Compressors",
    "wof:placetype":"venue"
},
  "geometry": {"coordinates":[-97.127807,32.699454],"type":"Point"}
}