{
  "type": "Feature",
  "properties": {
    "iso:country":"US",
    "sg:address":"9301 Johnny Morris Rd",
    "sg:city":"Austin",
    "sg:classifiers":[
        {
            "category":"Government",
            "subcategory":"Police Station",
            "type":"Public Place"
        }
    ],
    "sg:phone":"+1 512 473 9285",
    "sg:postcode":"78724",
    "sg:province":"TX",
    "sg:tags":[
        "sheriff"
    ],
    "wof:name":"Sheriff's Office-Patrol Svc",
    "wof:placetype":"venue"
},
  "geometry": {"coordinates":[-97.623921,30.329168],"type":"Point"}
}