{
  "type": "Feature",
  "properties": {
    "iso:country":"US",
    "sg:address":"215 W Sunset Rd",
    "sg:city":"San Antonio",
    "sg:classifiers":[
        {
            "category":"Personal",
            "type":"Services"
        }
    ],
    "sg:phone":"+1 210 832 0892",
    "sg:postcode":"78209",
    "sg:province":"TX",
    "wof:name":"ART Massage Therapy",
    "wof:placetype":"venue"
},
  "geometry": {"coordinates":[-98.470799,29.507328],"type":"Point"}
}