{
  "type": "Feature",
  "properties": {
    "iso:country":"US",
    "sg:address":"1701 W 4th St",
    "sg:city":"Cameron",
    "sg:classifiers":[
        {
            "category":"Personal",
            "subcategory":"Beauty Salon",
            "type":"Services"
        }
    ],
    "sg:phone":"+1 254 697 8585",
    "sg:postcode":"76520",
    "sg:province":"TX",
    "sg:tags":[
        "shop"
    ],
    "wof:name":"Kleen Kutz",
    "wof:placetype":"venue"
},
  "geometry": {"coordinates":[-96.98780600000001,30.856309],"type":"Point"}
}