{
  "type": "Feature",
  "properties": {
    "iso:country":"US",
    "sg:address":"7500 Valley Laurel Ct",
    "sg:city":"Houston",
    "sg:classifiers":[
        {
            "category":"Shopping",
            "subcategory":"Jewelry",
            "type":"Retail Goods"
        }
    ],
    "sg:phone":"+1 713 777 8899",
    "sg:postcode":"77095",
    "sg:province":"TX",
    "sg:tags":[
        "wholesale"
    ],
    "wof:name":"Its About Time",
    "wof:placetype":"venue"
},
  "geometry": {"coordinates":[-95.65958000000001,29.887611],"type":"Point"}
}