{
  "type": "Feature",
  "properties": {
    "iso:country":"US",
    "sg:address":"203 S Lowell Ave",
    "sg:city":"Breckenridge",
    "sg:classifiers":[
        {
            "category":"Building & Trades",
            "subcategory":"Plumbing",
            "type":"Services"
        }
    ],
    "sg:phone":"+1 254 559 8186",
    "sg:postcode":"76424",
    "sg:province":"TX",
    "sg:tags":[
        "conditioning",
        "air",
        "system",
        "contractor"
    ],
    "wof:name":"A & M Air Cond & Refrig",
    "wof:placetype":"venue"
},
  "geometry": {"coordinates":[-98.88041200000001,32.753815],"type":"Point"}
}