{
  "type": "Feature",
  "properties": {
    "iso:country":"US",
    "sg:address":"859 Co Rd 1170",
    "sg:city":"Decatur",
    "sg:classifiers":[
        {
            "category":"Retail",
            "subcategory":"Auto Repair",
            "type":"Services"
        }
    ],
    "sg:phone":"+1 940 627 2431",
    "sg:postcode":"76234",
    "sg:province":"TX",
    "sg:tags":[
        "body"
    ],
    "wof:name":"Billy E James",
    "wof:placetype":"venue"
},
  "geometry": {"coordinates":[-97.62933200000001,33.276488],"type":"Point"}
}