{
  "type": "Feature",
  "properties": {
    "iso:country":"US",
    "sg:address":"7522 Campbell Rd",
    "sg:city":"Dallas",
    "sg:classifiers":[
        {
            "category":"Personal",
            "type":"Services"
        }
    ],
    "sg:phone":"+1 972 380 0018",
    "sg:postcode":"75248",
    "sg:province":"TX",
    "sg:tags":[
        "rental",
        "costume",
        "supply"
    ],
    "wof:name":"Costume Adventures",
    "wof:placetype":"venue"
},
  "geometry": {"coordinates":[-96.76857,32.978143],"type":"Point"}
}