{
  "type": "Feature",
  "properties": {
    "iso:country":"US",
    "sg:address":"1510 Calle del Norte",
    "sg:city":"Laredo",
    "sg:classifiers":[
        {
            "category":"Professional",
            "subcategory":"Lawyer & Legal Services",
            "type":"Services"
        }
    ],
    "sg:phone":"+1 956 726 0722",
    "sg:postcode":"78041",
    "sg:province":"TX",
    "sg:tags":[
        "attorney",
        "accident",
        "family",
        "personal",
        "divorce",
        "automobile",
        "injury",
        "law"
    ],
    "wof:name":"Lopez, Armando X. Attorney At Law",
    "wof:placetype":"venue"
},
  "geometry": {"coordinates":[-99.480565,27.556164],"type":"Point"}
}