{
  "type": "Feature",
  "properties": {
    "iso:country":"US",
    "sg:address":"21280 Kristen Dr",
    "sg:city":"Chandler",
    "sg:classifiers":[
        {
            "category":"Autos & Motor Vehicles",
            "subcategory":"Fuel & Gas Station",
            "type":"Retail Goods"
        }
    ],
    "sg:phone":"+1 903 849 4922",
    "sg:postcode":"75758",
    "sg:province":"TX",
    "wof:name":"Gulf State Development Company",
    "wof:placetype":"venue"
},
  "geometry": {"coordinates":[-95.499501,32.205743],"type":"Point"}
}