{
  "type": "Feature",
  "properties": {
    "iso:country":"US",
    "sg:address":"2210 E 29th St",
    "sg:city":"Bryan",
    "sg:classifiers":[
        {
            "category":"Professional",
            "subcategory":"Research",
            "type":"Services"
        },
        {
            "category":"Health Services",
            "subcategory":"Clinic",
            "type":"Services"
        }
    ],
    "sg:phone":"+1 979 779 3303",
    "sg:postcode":"77802",
    "sg:province":"TX",
    "sg:tags":[
        "medical"
    ],
    "wof:name":"Discover Research Inc",
    "wof:placetype":"venue"
},
  "geometry": {"coordinates":[-96.350854,30.658428],"type":"Point"}
}