{
  "type": "Feature",
  "properties": {
    "iso:country":"US",
    "sg:address":"4920 Robindale Rd",
    "sg:city":"Brownsville",
    "sg:classifiers":[
        {
            "category":"Organizations",
            "subcategory":"Religious Organization",
            "type":"Services"
        }
    ],
    "sg:phone":"+1 956 831 2008",
    "sg:postcode":"78526",
    "sg:province":"TX",
    "sg:tags":[
        "church"
    ],
    "wof:name":"Unity Church Of Brownsville",
    "wof:placetype":"venue"
},
  "geometry": {"coordinates":[-97.45357799999999,25.973027],"type":"Point"}
}