{
  "type": "Feature",
  "properties": {
    "iso:country":"US",
    "sg:address":"309 S Fulton Beach Rd",
    "sg:city":"Rockport",
    "sg:classifiers":[
        {
            "category":"Travel",
            "subcategory":"Hotels & Motels",
            "type":"Entertainment"
        }
    ],
    "sg:phone":"+1 361 729 6693",
    "sg:postcode":"78382",
    "sg:province":"TX",
    "sg:tags":[
        "resort"
    ],
    "wof:name":"Bayfront Cottages",
    "wof:placetype":"venue"
},
  "geometry": {"coordinates":[-97.034083,28.057481],"type":"Point"}
}