{
  "type": "Feature",
  "properties": {
    "iso:country":"US",
    "sg:address":"5531 Beechnut St",
    "sg:city":"Houston",
    "sg:classifiers":[
        {
            "category":"Organizations",
            "subcategory":"Religious Organization",
            "type":"Services"
        }
    ],
    "sg:phone":"+1 713 660 9793",
    "sg:postcode":"77096",
    "sg:province":"TX",
    "wof:name":"Corporation of President of Th",
    "wof:placetype":"venue"
},
  "geometry": {"coordinates":[-95.489406,29.688822],"type":"Point"}
}