{
  "type": "Feature",
  "properties": {
    "iso:country":"US",
    "sg:address":"11312 S Pipeline Rd",
    "sg:city":"Euless",
    "sg:classifiers":[
        {
            "category":"Professional",
            "subcategory":"Engineering",
            "type":"Services"
        }
    ],
    "sg:phone":"+1 817 858 0398",
    "sg:postcode":"76040",
    "sg:province":"TX",
    "wof:name":"Specialty Engineering",
    "wof:placetype":"venue"
},
  "geometry": {"coordinates":[-97.12514,32.814593],"type":"Point"}
}