{
  "type": "Feature",
  "properties": {
    "iso:country":"US",
    "sg:address":"5919 E Lancaster Ave",
    "sg:city":"Fort Worth",
    "sg:classifiers":[
        {
            "category":"Professional",
            "subcategory":"Management & Consulting",
            "type":"Services"
        }
    ],
    "sg:phone":"+1 817 784 8282",
    "sg:postcode":"76112",
    "sg:province":"TX",
    "sg:tags":[
        "marketing",
        "consultant"
    ],
    "wof:name":"Stonewall Marketing",
    "wof:placetype":"venue"
},
  "geometry": {"coordinates":[-97.228561,32.736178],"type":"Point"}
}