{
  "type": "Feature",
  "properties": {
    "iso:country":"US",
    "sg:address":"2700 W 45th Ave",
    "sg:city":"Amarillo",
    "sg:classifiers":[
        {
            "category":"Banks & Credit Unions",
            "subcategory":"Bank",
            "type":"Services"
        }
    ],
    "sg:phone":"+1 806 351 0299",
    "sg:postcode":"79110",
    "sg:province":"TX",
    "sg:tags":[
        "personal",
        "institution",
        "business"
    ],
    "wof:name":"Timberwolf Financial Services",
    "wof:placetype":"venue"
},
  "geometry": {"coordinates":[-101.869517,35.163809],"type":"Point"}
}