{
  "type": "Feature",
  "properties": {
    "iso:country":"US",
    "sg:address":"108 E Main St",
    "sg:city":"Alice",
    "sg:classifiers":[
        {
            "category":"Fast Food",
            "type":"Food & Drink"
        },
        {
            "category":"Restaurant",
            "type":"Food & Drink"
        }
    ],
    "sg:phone":"+1 361 661 1123",
    "sg:postcode":"78332",
    "sg:province":"TX",
    "sg:tags":[
        "house",
        "steak",
        "take"
    ],
    "wof:name":"Jeans Steakhouse & Restaurant",
    "wof:placetype":"venue"
},
  "geometry": {"coordinates":[-98.076539,27.750139],"type":"Point"}
}