{
  "type": "Feature",
  "properties": {
    "iso:country":"US",
    "sg:address":"7013 Robin Sound St",
    "sg:city":"Pearland",
    "sg:classifiers":[
        {
            "category":"Manufacturing",
            "subcategory":"Petroleum Products",
            "type":"Manufacturing & Wholesale Goods"
        }
    ],
    "sg:phone":"+1 281 485 8840",
    "sg:postcode":"77581",
    "sg:province":"TX",
    "sg:tags":[
        "contract"
    ],
    "wof:name":"Geraldines Gems",
    "wof:placetype":"venue"
},
  "geometry": {"coordinates":[-95.329626,29.576704],"type":"Point"}
}