{
  "type": "Feature",
  "properties": {
    "iso:country":"US",
    "sg:address":"1350 E Arapaho Rd",
    "sg:city":"Richardson",
    "sg:classifiers":[
        {
            "category":"Freight",
            "type":"Transportation"
        }
    ],
    "sg:phone":"+1 972 437 3327",
    "sg:postcode":"75081",
    "sg:province":"TX",
    "sg:tags":[
        "arrangement"
    ],
    "wof:name":"Remel",
    "wof:placetype":"venue"
},
  "geometry": {"coordinates":[-96.70156799999999,32.960504],"type":"Point"}
}