{
  "type": "Feature",
  "properties": {
    "iso:country":"US",
    "sg:address":"899 N Bonham St",
    "sg:city":"San Benito",
    "sg:classifiers":[
        {
            "category":"Insurance",
            "subcategory":"Insurance Agent",
            "type":"Services"
        }
    ],
    "sg:phone":"+1 956 361 0056",
    "sg:postcode":"78586",
    "sg:province":"TX",
    "wof:name":"Allstate Insurance",
    "wof:placetype":"venue"
},
  "geometry": {"coordinates":[-97.622506,26.13392],"type":"Point"}
}