{
  "type": "Feature",
  "properties": {
    "iso:country":"US",
    "sg:address":"501 US Hwy 287 Bus",
    "sg:city":"Ennis",
    "sg:classifiers":[
        {
            "category":"Recreation",
            "type":"Entertainment"
        }
    ],
    "sg:phone":"+1 972 875 1155",
    "sg:postcode":"75119",
    "sg:province":"TX",
    "sg:tags":[
        "club",
        "membership",
        "baseball"
    ],
    "wof:name":"Ennis Boys Little League",
    "wof:placetype":"venue"
},
  "geometry": {"coordinates":[-96.630871,32.325973],"type":"Point"}
}