{
  "type": "Feature",
  "properties": {
    "iso:country":"US",
    "sg:address":"807 Scottsdale Dr",
    "sg:city":"Richardson",
    "sg:classifiers":[
        {
            "category":"Professional",
            "subcategory":"Management & Consulting",
            "type":"Services"
        }
    ],
    "sg:phone":"+1 972 231 9104",
    "sg:postcode":"75080",
    "sg:province":"TX",
    "wof:name":"Michael J Murphy Consulting",
    "wof:placetype":"venue"
},
  "geometry": {"coordinates":[-96.75179199999999,32.948287],"type":"Point"}
}