{
  "type": "Feature",
  "properties": {
    "iso:country":"US",
    "sg:address":"1398 FM 2673",
    "sg:city":"Canyon Lake",
    "sg:classifiers":[
        {
            "category":"Shopping",
            "subcategory":"Florist",
            "type":"Retail Goods"
        }
    ],
    "sg:phone":"+1 830 660 3650",
    "sg:postcode":"78133",
    "sg:province":"TX",
    "sg:tags":[
        "plant"
    ],
    "wof:name":"Dragon Fly",
    "wof:placetype":"venue"
},
  "geometry": {"coordinates":[-98.172506,29.849611],"type":"Point"}
}