{
  "type": "Feature",
  "properties": {
    "iso:country":"US",
    "sg:address":"11515 Quail Creek Dr",
    "sg:city":"Houston",
    "sg:classifiers":[
        {
            "category":"Retail",
            "subcategory":"Portrait Studio",
            "type":"Services"
        }
    ],
    "sg:phone":"+1 281 513 0011",
    "sg:postcode":"77070",
    "sg:province":"TX",
    "sg:tags":[
        "photographer"
    ],
    "wof:name":"Allred Photography",
    "wof:placetype":"venue"
},
  "geometry": {"coordinates":[-95.590756,29.986264],"type":"Point"}
}