{
  "type": "Feature",
  "properties": {
    "iso:country":"US",
    "sg:address":"14335 Eagle Pass St",
    "sg:city":"Houston",
    "sg:classifiers":[
        {
            "category":"Building & Trades",
            "subcategory":"Construction",
            "type":"Services"
        }
    ],
    "sg:phone":"+1 832 309 6489",
    "sg:postcode":"77015",
    "sg:province":"TX",
    "sg:tags":[
        "contractor"
    ],
    "sg:website":"www.razysconstruction.com",
    "wof:name":"ABRAHAM CONSTRUCTION & REMODELING",
    "wof:placetype":"venue"
},
  "geometry": {"coordinates":[-95.169033,29.784582],"type":"Point"}
}