{
  "type": "Feature",
  "properties": {
    "iso:country":"US",
    "sg:address":"11927 la Vernia Rd",
    "sg:city":"Adkins",
    "sg:classifiers":[
        {
            "category":"Building & Trades",
            "subcategory":"Electrical",
            "type":"Services"
        },
        {
            "category":"Retail",
            "subcategory":"Auto Repair",
            "type":"Services"
        }
    ],
    "sg:phone":"+1 210 649 2919",
    "sg:postcode":"78101",
    "sg:province":"TX",
    "sg:tags":[
        "automobile",
        "electrician",
        "electric"
    ],
    "wof:name":"Miktech Power Systems",
    "wof:placetype":"venue"
},
  "geometry": {"coordinates":[-98.248789,29.398151],"type":"Point"}
}