{
  "type": "Feature",
  "properties": {
    "iso:country":"US",
    "sg:address":"1017 Co Rd 4314",
    "sg:city":"Tenaha",
    "sg:classifiers":[
        {
            "category":"Wholesale",
            "subcategory":"Meat",
            "type":"Manufacturing & Wholesale Goods"
        }
    ],
    "sg:phone":"+1 936 598 4781",
    "sg:postcode":"75974",
    "sg:province":"TX",
    "sg:tags":[
        "product"
    ],
    "wof:name":"Bradshaw's Deer Processing",
    "wof:placetype":"venue"
},
  "geometry": {"coordinates":[-94.249269,31.872148],"type":"Point"}
}