{
  "type": "Feature",
  "properties": {
    "iso:country":"US",
    "sg:address":"708 Liveoak Dr",
    "sg:city":"Johnson City",
    "sg:classifiers":[
        {
            "category":"Professional",
            "subcategory":"Computer Services",
            "type":"Services"
        }
    ],
    "sg:phone":"+1 830 868 7296",
    "sg:postcode":"78636",
    "sg:province":"TX",
    "sg:tags":[
        "repair"
    ],
    "wof:name":"K J Computers",
    "wof:placetype":"venue"
},
  "geometry": {"coordinates":[-98.407901,30.263737],"type":"Point"}
}