{
  "type": "Feature",
  "properties": {
    "iso:country":"US",
    "sg:address":"12900 Steeple-Chase Dr",
    "sg:city":"Austin",
    "sg:classifiers":[
        {
            "category":"Manufacturing",
            "subcategory":"Retail Goods",
            "type":"Manufacturing & Wholesale Goods"
        }
    ],
    "sg:phone":"+1 512 335 3675",
    "sg:postcode":"78729",
    "sg:province":"TX",
    "sg:tags":[
        "pencil"
    ],
    "wof:name":"Darrell R Mica Mfg",
    "wof:placetype":"venue"
},
  "geometry": {"coordinates":[-97.761582,30.447],"type":"Point"}
}