{
  "type": "Feature",
  "properties": {
    "iso:country":"US",
    "sg:address":"302 Linda St",
    "sg:city":"Deer Park",
    "sg:classifiers":[
        {
            "category":"Wholesale",
            "subcategory":"Farm Supplies",
            "type":"Manufacturing & Wholesale Goods"
        }
    ],
    "sg:phone":"+1 281 479 2418",
    "sg:postcode":"77536",
    "sg:province":"TX",
    "sg:tags":[
        "livestock"
    ],
    "wof:name":"Hoof & Horn Ranch",
    "wof:placetype":"venue"
},
  "geometry": {"coordinates":[-95.129848,29.709018],"type":"Point"}
}