{
  "type": "Feature",
  "properties": {
    "iso:country":"US",
    "sg:address":"707 North Fwy",
    "sg:city":"Fort Worth",
    "sg:classifiers":[
        {
            "category":"Freight",
            "type":"Transportation"
        },
        {
            "category":"Professional",
            "type":"Services"
        }
    ],
    "sg:phone":"+1 817 882 8055",
    "sg:postcode":"76102",
    "sg:province":"TX",
    "sg:tags":[
        "trucking"
    ],
    "wof:name":"Standard Automatic Fire Ents",
    "wof:placetype":"venue"
},
  "geometry": {"coordinates":[-97.319481,32.772526],"type":"Point"}
}