{
  "type": "Feature",
  "properties": {
    "iso:country":"US",
    "sg:address":"1972 Abshire Ln",
    "sg:city":"Dallas",
    "sg:classifiers":[
        {
            "category":"Organizations",
            "subcategory":"Religious Organization",
            "type":"Services"
        }
    ],
    "sg:phone":"+1 214 324 1031",
    "sg:postcode":"75228",
    "sg:province":"TX",
    "wof:name":"God In Full Force Gief",
    "wof:placetype":"venue"
},
  "geometry": {"coordinates":[-96.68329199999999,32.810329],"type":"Point"}
}