{
  "type": "Feature",
  "properties": {
    "iso:country":"US",
    "sg:address":"632 Post Oak Dr",
    "sg:city":"Plano",
    "sg:classifiers":[
        {
            "category":"Autos & Motor Vehicles",
            "subcategory":"Automobile Sales",
            "type":"Retail Goods"
        }
    ],
    "sg:phone":"+1 972 517 2205",
    "sg:postcode":"75025",
    "sg:province":"TX",
    "wof:name":"Lone Star BMW Riders Inc",
    "wof:placetype":"venue"
},
  "geometry": {"coordinates":[-96.69868200000001,33.078084],"type":"Point"}
}