{
  "type": "Feature",
  "properties": {
    "iso:country":"US",
    "sg:address":"610 Martin Luther King Rd",
    "sg:city":"Alice",
    "sg:classifiers":[
        {
            "category":"Organizations",
            "subcategory":"Religious Organization",
            "type":"Services"
        }
    ],
    "sg:phone":"+1 361 664 6661",
    "sg:postcode":"78332",
    "sg:province":"TX",
    "sg:tags":[
        "church"
    ],
    "wof:name":"True Light Baptist Church",
    "wof:placetype":"venue"
},
  "geometry": {"coordinates":[-98.077208,27.744816],"type":"Point"}
}