{
  "type": "Feature",
  "properties": {
    "iso:country":"US",
    "sg:address":"7556 Sand St",
    "sg:city":"Fort Worth",
    "sg:classifiers":[
        {
            "category":"Wholesale",
            "subcategory":"Electrical",
            "type":"Manufacturing & Wholesale Goods"
        }
    ],
    "sg:phone":"+1 817 284 2032",
    "sg:postcode":"76118",
    "sg:province":"TX",
    "sg:tags":[
        "game",
        "importer"
    ],
    "wof:name":"Fame (usa) Productsinc",
    "wof:placetype":"venue"
},
  "geometry": {"coordinates":[-97.21300599999999,32.795707],"type":"Point"}
}