{
  "type": "Feature",
  "properties": {
    "iso:country":"US",
    "sg:address":"2040 Sam Houston Pkwy",
    "sg:city":"Houston",
    "sg:classifiers":[
        {
            "category":"Real Estate",
            "subcategory":"Real Estate Agent",
            "type":"Services"
        }
    ],
    "sg:phone":"+1 713 935 1500",
    "sg:postcode":"77042",
    "sg:province":"TX",
    "sg:tags":[
        "property",
        "company",
        "management"
    ],
    "wof:name":"West Belt Industrial Bldg Corp",
    "wof:placetype":"venue"
},
  "geometry": {"coordinates":[-95.558339,29.743328],"type":"Point"}
}