{
  "type": "Feature",
  "properties": {
    "iso:country":"US",
    "sg:address":"4701 W Park Blvd Ste 106",
    "sg:city":"Plano",
    "sg:classifiers":[
        {
            "category":"Shopping",
            "subcategory":"Mobile Phones",
            "type":"Retail Goods"
        }
    ],
    "sg:phone":"+1 972 758 1415",
    "sg:postcode":"75093",
    "sg:province":"TX",
    "wof:name":"Just Get Wireless",
    "wof:placetype":"venue"
},
  "geometry": {"coordinates":[-96.788597,33.027],"type":"Point"}
}