{
  "type": "Feature",
  "properties": {
    "iso:country":"US",
    "sg:address":"1202 12th St",
    "sg:city":"Anson",
    "sg:classifiers":[
        {
            "category":"Building & Trades",
            "subcategory":"Construction",
            "type":"Services"
        }
    ],
    "sg:phone":"+1 325 823 3276",
    "sg:postcode":"79501",
    "sg:province":"TX",
    "sg:tags":[
        "system",
        "contractor",
        "air conditioning"
    ],
    "wof:name":"Anson Heating And Cooling",
    "wof:placetype":"venue"
},
  "geometry": {"coordinates":[-99.898088,32.756001],"type":"Point"}
}