{
  "type": "Feature",
  "properties": {
    "iso:country":"US",
    "sg:address":"729 S Mill St",
    "sg:city":"Lewisville",
    "sg:classifiers":[
        {
            "category":"Autos & Motor Vehicles",
            "subcategory":"Auto Supplies",
            "type":"Retail Goods"
        },
        {
            "category":"Retail",
            "subcategory":"Auto Repair",
            "type":"Services"
        }
    ],
    "sg:phone":"+1 214 222 3141",
    "sg:postcode":"75057",
    "sg:province":"TX",
    "sg:tags":[
        "body",
        "wheel",
        "automobile",
        "dent",
        "servicing-automotive",
        "truck",
        "axle",
        "alignment-frame",
        "removal",
        "painting",
        "repairing"
    ],
    "sg:website":"http://www.alexbodyshop.com",
    "wof:name":"Alex Paint & Body",
    "wof:placetype":"venue"
},
  "geometry": {"coordinates":[-96.99291599999999,33.039561],"type":"Point"}
}