{
  "type": "Feature",
  "properties": {
    "iso:country":"US",
    "sg:address":"3407 Wells Branch Pkwy",
    "sg:city":"Austin",
    "sg:classifiers":[
        {
            "category":"Restaurant",
            "type":"Food & Drink"
        }
    ],
    "sg:menulink":"http://www.allmenus.com/tx/austin/130696-subway/menu/",
    "sg:phone":"+1 512 218 4662",
    "sg:postcode":"78728",
    "sg:province":"TX",
    "sg:tags":[
        "american",
        "sandwich"
    ],
    "wof:name":"Subway",
    "wof:placetype":"venue"
},
  "geometry": {"coordinates":[-97.696113,30.439655],"type":"Point"}
}