{
  "type": "Feature",
  "properties": {
    "iso:country":"US",
    "sg:address":"699 S Friendswood Dr",
    "sg:city":"Friendswood",
    "sg:classifiers":[
        {
            "category":"Utilities",
            "subcategory":"Telephone",
            "type":"Services"
        }
    ],
    "sg:phone":"+1 281 652 4800",
    "sg:postcode":"77546",
    "sg:province":"TX",
    "sg:tags":[
        "communications"
    ],
    "wof:name":"Novolink Communications Inc",
    "wof:placetype":"venue"
},
  "geometry": {"coordinates":[-95.19847300000001,29.527307],"type":"Point"}
}