{
  "type": "Feature",
  "properties": {
    "iso:country":"US",
    "sg:address":"7257 Rendon New Hope Rd",
    "sg:city":"Fort Worth",
    "sg:classifiers":[
        {
            "category":"Manufacturing",
            "subcategory":"Buildings",
            "type":"Manufacturing & Wholesale Goods"
        }
    ],
    "sg:phone":"+1 817 483 5042",
    "sg:postcode":"76140",
    "sg:province":"TX",
    "sg:tags":[
        "prefabricated",
        "wood",
        "mfg"
    ],
    "wof:name":"Blackberry Meadows Inc",
    "wof:placetype":"venue"
},
  "geometry": {"coordinates":[-97.23287999999999,32.575293],"type":"Point"}
}