{
  "type": "Feature",
  "properties": {
    "iso:country":"US",
    "sg:address":"1575 Goliad Rd",
    "sg:city":"San Antonio",
    "sg:classifiers":[
        {
            "category":"Social Services",
            "subcategory":"Child Care",
            "type":"Services"
        }
    ],
    "sg:phone":"+1 210 533 8242",
    "sg:postcode":"78223",
    "sg:province":"TX",
    "wof:name":"Parent/Child Inc-Headstart",
    "wof:placetype":"venue"
},
  "geometry": {"coordinates":[-98.44535999999999,29.371224],"type":"Point"}
}