{
  "type": "Feature",
  "properties": {
    "iso:country":"US",
    "sg:address":"1412 W Main St",
    "sg:city":"Port Lavaca",
    "sg:classifiers":[
        {
            "category":"Personal",
            "subcategory":"Beauty Salon",
            "type":"Services"
        }
    ],
    "sg:phone":"+1 361 552 3090",
    "sg:postcode":"77979",
    "sg:province":"TX",
    "wof:name":"Hair Performance",
    "wof:placetype":"venue"
},
  "geometry": {"coordinates":[-96.63851099999999,28.609596],"type":"Point"}
}