{
  "type": "Feature",
  "properties": {
    "iso:country":"US",
    "sg:address":"8938 Broadway",
    "sg:city":"San Antonio",
    "sg:classifiers":[
        {
            "category":"Manufacturing",
            "subcategory":"Printing",
            "type":"Manufacturing & Wholesale Goods"
        }
    ],
    "sg:phone":"+1 210 822 1908",
    "sg:postcode":"78217",
    "sg:province":"TX",
    "sg:tags":[
        "offset"
    ],
    "wof:name":"Speedy Printing Service",
    "wof:placetype":"venue"
},
  "geometry": {"coordinates":[-98.459183,29.521959],"type":"Point"}
}