{
  "type": "Feature",
  "properties": {
    "iso:country":"US",
    "sg:address":"213 Carlsbad Dr",
    "sg:city":"Mansfield",
    "sg:classifiers":[
        {
            "category":"Professional",
            "subcategory":"Business Services",
            "type":"Services"
        }
    ],
    "sg:phone":"+1 817 453 4021",
    "sg:postcode":"76063",
    "sg:province":"TX",
    "wof:name":"Hot Screens",
    "wof:placetype":"venue"
},
  "geometry": {"coordinates":[-97.144465,32.577556],"type":"Point"}
}