{
  "type": "Feature",
  "properties": {
    "iso:country":"US",
    "sg:address":"2613 Country Valley Rd",
    "sg:city":"Garland",
    "sg:classifiers":[
        {
            "category":"Personal",
            "type":"Services"
        }
    ],
    "sg:phone":"+1 972 840 1935",
    "sg:postcode":"75043",
    "sg:province":"TX",
    "sg:tags":[
        "assistant"
    ],
    "wof:name":"State Recoveries",
    "wof:placetype":"venue"
},
  "geometry": {"coordinates":[-96.60956299999999,32.888252],"type":"Point"}
}