{
  "type": "Feature",
  "properties": {
    "iso:country":"US",
    "sg:address":"1821 Oates Dr Apt 412",
    "sg:city":"Mesquite",
    "sg:classifiers":[
        {
            "category":"Shopping",
            "subcategory":"Florist",
            "type":"Retail Goods"
        }
    ],
    "sg:phone":"+1 972 682 4101",
    "sg:postcode":"75150",
    "sg:province":"TX",
    "wof:name":"Mesquite Florist",
    "wof:placetype":"venue"
},
  "geometry": {"coordinates":[-96.62925300000001,32.838095],"type":"Point"}
}