{
  "type": "Feature",
  "properties": {
    "iso:country":"US",
    "sg:address":"203 Nash Ct",
    "sg:city":"Terrell",
    "sg:classifiers":[
        {
            "category":"Insurance",
            "subcategory":"Insurance Agent",
            "type":"Services"
        }
    ],
    "sg:phone":"+1 972 524 3001",
    "sg:postcode":"75160",
    "sg:province":"TX",
    "wof:name":"Morgan Miller Insurance",
    "wof:placetype":"venue"
},
  "geometry": {"coordinates":[-96.279331,32.737766],"type":"Point"}
}