{
  "type": "Feature",
  "properties": {
    "iso:country":"US",
    "sg:address":"4358 Woodhollow Dr",
    "sg:city":"Dallas",
    "sg:classifiers":[
        {
            "category":"Professional",
            "subcategory":"Management & Consulting",
            "type":"Services"
        }
    ],
    "sg:phone":"+1 214 330 1004",
    "sg:postcode":"75237",
    "sg:province":"TX",
    "sg:tags":[
        "consultant"
    ],
    "wof:name":"Legacy Consultants",
    "wof:placetype":"venue"
},
  "geometry": {"coordinates":[-96.863923,32.689381],"type":"Point"}
}