{
  "type": "Feature",
  "properties": {
    "iso:country":"US",
    "sg:address":"4299 San Felipe St",
    "sg:city":"Houston",
    "sg:classifiers":[
        {
            "category":"Health Services",
            "subcategory":"Clinic",
            "type":"Services"
        }
    ],
    "sg:phone":"+1 832 476 3900",
    "sg:postcode":"77027",
    "sg:province":"TX",
    "sg:tags":[
        "organization",
        "medical",
        "surgical"
    ],
    "sg:website":"www.inpatient-med.com",
    "wof:name":"IMS",
    "wof:placetype":"venue"
},
  "geometry": {"coordinates":[-95.451809,29.746624],"type":"Point"}
}