{
  "type": "Feature",
  "properties": {
    "iso:country":"US",
    "sg:address":"2835 US Hwy 80",
    "sg:city":"Odessa",
    "sg:classifiers":[
        {
            "category":"Retail",
            "subcategory":"Auto Repair",
            "type":"Services"
        }
    ],
    "sg:phone":"+1 432 332 5948",
    "sg:postcode":"79761",
    "sg:province":"TX",
    "sg:tags":[
        "automotive",
        "general"
    ],
    "wof:name":"Performance Plus",
    "wof:placetype":"venue"
},
  "geometry": {"coordinates":[-102.32623599999999,31.865871],"type":"Point"}
}