{
  "type": "Feature",
  "properties": {
    "iso:country":"US",
    "sg:address":"8930 Kenton Mist",
    "sg:city":"San Antonio",
    "sg:classifiers":[
        {
            "category":"Retail",
            "subcategory":"Portrait Studio",
            "type":"Services"
        }
    ],
    "sg:phone":"+1 210 641 2853",
    "sg:postcode":"78240",
    "sg:province":"TX",
    "sg:tags":[
        "photographer"
    ],
    "wof:name":"Chris Rutz",
    "wof:placetype":"venue"
},
  "geometry": {"coordinates":[-98.587356,29.523113],"type":"Point"}
}