{
  "type": "Feature",
  "properties": {
    "iso:country":"US",
    "sg:address":"4414 N Main St",
    "sg:city":"Liberty",
    "sg:classifiers":[
        {
            "category":"Mining & Drilling",
            "type":"Manufacturing & Wholesale Goods"
        }
    ],
    "sg:phone":"+1 936 336 9665",
    "sg:postcode":"77575",
    "sg:province":"TX",
    "sg:tags":[
        "development",
        "gas",
        "oil",
        "exploration"
    ],
    "wof:name":"Stuart Petroleum",
    "wof:placetype":"venue"
},
  "geometry": {"coordinates":[-94.759146,30.089925],"type":"Point"}
}