{
  "type": "Feature",
  "properties": {
    "iso:country":"US",
    "sg:address":"4303 McKinney Falls Pkwy",
    "sg:city":"Austin",
    "sg:classifiers":[
        {
            "category":"Building & Trades",
            "subcategory":"Construction",
            "type":"Services"
        }
    ],
    "sg:phone":"+1 512 386 6985",
    "sg:postcode":"78744",
    "sg:province":"TX",
    "sg:tags":[
        "house"
    ],
    "wof:name":"D L Bandy Construction",
    "wof:placetype":"venue"
},
  "geometry": {"coordinates":[-97.701273,30.189946],"type":"Point"}
}