{
  "type": "Feature",
  "properties": {
    "iso:country":"US",
    "sg:address":"1115 E Pioneer Pkwy",
    "sg:city":"Arlington",
    "sg:classifiers":[
        {
            "category":"Banks & Credit Unions",
            "subcategory":"Bank",
            "type":"Services"
        }
    ],
    "sg:phone":"+1 817 223 9239",
    "sg:postcode":"76010",
    "sg:province":"TX",
    "sg:tags":[
        "broker",
        "mortgage"
    ],
    "wof:name":"Lone Star Mortgage HM Ln & RE",
    "wof:placetype":"venue"
},
  "geometry": {"coordinates":[-97.089759,32.708056],"type":"Point"}
}