{
  "type": "Feature",
  "properties": {
    "iso:country":"US",
    "sg:address":"14105 Heartside Pl",
    "sg:city":"Farmers Branch",
    "sg:classifiers":[
        {
            "category":"Building & Trades",
            "subcategory":"Landscaping Services",
            "type":"Services"
        }
    ],
    "sg:phone":"+1 972 841 4816",
    "sg:postcode":"75234",
    "sg:province":"TX",
    "sg:tags":[
        "landscape",
        "contractor"
    ],
    "wof:name":"North Dallas Landscaping",
    "wof:placetype":"venue"
},
  "geometry": {"coordinates":[-96.880208,32.939711],"type":"Point"}
}