{
  "type": "Feature",
  "properties": {
    "iso:country":"US",
    "sg:address":"808 Russell Palmer Rd",
    "sg:city":"Humble",
    "sg:classifiers":[
        {
            "category":"Wholesale",
            "subcategory":"Medical Equipment & Supplies",
            "type":"Manufacturing & Wholesale Goods"
        }
    ],
    "sg:phone":"+1 281 358 1115",
    "sg:postcode":"77339",
    "sg:province":"TX",
    "wof:name":"SA Medical",
    "wof:placetype":"venue"
},
  "geometry": {"coordinates":[-95.22726900000001,30.064803],"type":"Point"}
}