{
  "type": "Feature",
  "properties": {
    "iso:country":"US",
    "sg:address":"1915 Junction Hwy",
    "sg:city":"Kerrville",
    "sg:classifiers":[
        {
            "category":"Retail",
            "subcategory":"Repair Shop",
            "type":"Services"
        }
    ],
    "sg:phone":"+1 830 895 5969",
    "sg:postcode":"78028",
    "sg:province":"TX",
    "sg:tags":[
        "appliance"
    ],
    "wof:name":"A To Z Appliance Ctr",
    "wof:placetype":"venue"
},
  "geometry": {"coordinates":[-99.19157800000001,30.072284],"type":"Point"}
}