{
  "type": "Feature",
  "properties": {
    "iso:country":"US",
    "sg:address":"1700 Circle Creek Dr",
    "sg:city":"Lewisville",
    "sg:classifiers":[
        {
            "category":"Professional",
            "subcategory":"Management & Consulting",
            "type":"Services"
        }
    ],
    "sg:phone":"+1 972 420 0532",
    "sg:postcode":"75067",
    "sg:province":"TX",
    "sg:tags":[
        "business"
    ],
    "wof:name":"F&O Consulting Co",
    "wof:placetype":"venue"
},
  "geometry": {"coordinates":[-97.03058900000001,33.02646],"type":"Point"}
}