{
  "type": "Feature",
  "properties": {
    "iso:country":"US",
    "sg:address":"1011 N Lamar Blvd",
    "sg:city":"Austin",
    "sg:classifiers":[
        {
            "category":"Professional",
            "type":"Services"
        }
    ],
    "sg:phone":"+1 512 472 6262",
    "sg:postcode":"78703",
    "sg:province":"TX",
    "sg:tags":[
        "establishment"
    ],
    "wof:name":"Silverton Foundation Inc",
    "wof:placetype":"venue"
},
  "geometry": {"coordinates":[-97.751796,30.275834],"type":"Point"}
}