{
  "type": "Feature",
  "properties": {
    "iso:country":"US",
    "sg:address":"2335 Binley Dr",
    "sg:city":"Houston",
    "sg:classifiers":[
        {
            "category":"Wholesale",
            "subcategory":"Stationery",
            "type":"Manufacturing & Wholesale Goods"
        }
    ],
    "sg:phone":"+1 281 759 9300",
    "sg:postcode":"77077",
    "sg:province":"TX",
    "sg:tags":[
        "cards",
        "greeting",
        "supply"
    ],
    "wof:name":"Jellybean Express LLC",
    "wof:placetype":"venue"
},
  "geometry": {"coordinates":[-95.619304,29.738956],"type":"Point"}
}