{
  "type": "Feature",
  "properties": {
    "iso:country":"US",
    "sg:address":"600 W Pioneer Dr",
    "sg:city":"Irving",
    "sg:classifiers":[
        {
            "category":"Government",
            "subcategory":"Office",
            "type":"Public Place"
        },
        {
            "category":"Social Services",
            "type":"Services"
        }
    ],
    "sg:phone":"+1 972 721 6521",
    "sg:postcode":"75061",
    "sg:province":"TX",
    "sg:tags":[
        "family",
        "village"
    ],
    "wof:name":"Irving Family Advocacy Center",
    "wof:placetype":"venue"
},
  "geometry": {"coordinates":[-96.95648,32.819769],"type":"Point"}
}