{
  "type": "Feature",
  "properties": {
    "iso:country":"US",
    "sg:address":"7410 Bairnsdale Ln",
    "sg:city":"Houston",
    "sg:classifiers":[
        {
            "category":"Banks & Credit Unions",
            "subcategory":"Financial Services",
            "type":"Services"
        }
    ],
    "sg:phone":"+1 281 970 1897",
    "sg:postcode":"77070",
    "sg:province":"TX",
    "sg:tags":[
        "investor"
    ],
    "wof:name":"RSR Investment Group",
    "wof:placetype":"venue"
},
  "geometry": {"coordinates":[-95.54713700000001,29.98037],"type":"Point"}
}