{
  "type": "Feature",
  "properties": {
    "iso:country":"US",
    "sg:address":"141 Valley Rd",
    "sg:city":"Italy",
    "sg:classifiers":[
        {
            "category":"Professional",
            "subcategory":"Business Services",
            "type":"Services"
        }
    ],
    "sg:phone":"+1 972 483 6005",
    "sg:postcode":"76670",
    "sg:province":"TX",
    "wof:name":"Latonia Smith",
    "wof:placetype":"venue"
},
  "geometry": {"coordinates":[-96.951565,32.179741],"type":"Point"}
}