{
  "type": "Feature",
  "properties": {
    "iso:country":"US",
    "sg:address":"304 S Cottonwood Dr Ste A",
    "sg:city":"Richardson",
    "sg:classifiers":[
        {
            "category":"Personal",
            "subcategory":"Adult",
            "type":"Services"
        }
    ],
    "sg:phone":"+1 214 366 3579",
    "sg:postcode":"75080",
    "sg:province":"TX",
    "sg:tags":[
        "midwife"
    ],
    "sg:website":"www.loverslanebirthcenter.com",
    "wof:name":"Lovers Lane Birth Center",
    "wof:placetype":"venue"
},
  "geometry": {"coordinates":[-96.766447,32.948437],"type":"Point"}
}