{
  "type": "Feature",
  "properties": {
    "iso:country":"US",
    "sg:address":"606 N Beal St",
    "sg:city":"Belton",
    "sg:classifiers":[
        {
            "category":"Shopping",
            "type":"Retail Goods"
        }
    ],
    "sg:phone":"+1 254 933 7765",
    "sg:postcode":"76513",
    "sg:province":"TX",
    "sg:tags":[
        "item",
        "boutique"
    ],
    "wof:name":"Abbirose Baby Boutique",
    "wof:placetype":"venue"
},
  "geometry": {"coordinates":[-97.45756,31.060753],"type":"Point"}
}