{
  "type": "Feature",
  "properties": {
    "iso:country":"US",
    "sg:address":"312 W 9th St",
    "sg:city":"Houston",
    "sg:classifiers":[
        {
            "category":"Personal",
            "subcategory":"Beauty Salon",
            "type":"Services"
        }
    ],
    "sg:phone":"+1 713 864 1778",
    "sg:postcode":"77007",
    "sg:province":"TX",
    "wof:name":"Marlene's Beauty Salon",
    "wof:placetype":"venue"
},
  "geometry": {"coordinates":[-95.400997,29.786883],"type":"Point"}
}