{
  "type": "Feature",
  "properties": {
    "iso:country":"US",
    "sg:address":"2900 Ashley Dr",
    "sg:city":"Pharr",
    "sg:classifiers":[
        {
            "category":"Professional",
            "subcategory":"Management & Consulting",
            "type":"Services"
        }
    ],
    "sg:phone":"+1 956 781 8922",
    "sg:postcode":"78577",
    "sg:province":"TX",
    "sg:tags":[
        "business"
    ],
    "wof:name":"Fineview Financial Services",
    "wof:placetype":"venue"
},
  "geometry": {"coordinates":[-98.18098500000001,26.158379],"type":"Point"}
}