{
  "type": "Feature",
  "properties": {
    "iso:country":"US",
    "sg:address":"1504 Westlake Dr",
    "sg:city":"Plano",
    "sg:classifiers":[
        {
            "category":"Professional",
            "type":"Services"
        }
    ],
    "sg:phone":"+1 972 423 4603",
    "sg:postcode":"75075",
    "sg:province":"TX",
    "wof:name":"Jemimah LLC",
    "wof:placetype":"venue"
},
  "geometry": {"coordinates":[-96.72605799999999,33.008568],"type":"Point"}
}