{
  "type": "Feature",
  "properties": {
    "iso:country":"US",
    "sg:address":"12013 Bellows Ct",
    "sg:city":"El Paso",
    "sg:classifiers":[
        {
            "category":"Shopping",
            "subcategory":"Computers & Home Electronics",
            "type":"Retail Goods"
        }
    ],
    "sg:phone":"+1 915 771 0033",
    "sg:postcode":"79936",
    "sg:province":"TX",
    "sg:tags":[
        "equipment",
        "dealer"
    ],
    "wof:name":"Computer Exposure",
    "wof:placetype":"venue"
},
  "geometry": {"coordinates":[-106.279416,31.742327],"type":"Point"}
}