{
  "type": "Feature",
  "properties": {
    "iso:country":"US",
    "sg:address":"2701 Saint Charles Dr",
    "sg:city":"Mansfield",
    "sg:classifiers":[
        {
            "category":"Building & Trades",
            "subcategory":"Construction",
            "type":"Services"
        }
    ],
    "sg:phone":"+1 817 477 1677",
    "sg:postcode":"76063",
    "sg:province":"TX",
    "sg:tags":[
        "house"
    ],
    "wof:name":"Pulte",
    "wof:placetype":"venue"
},
  "geometry": {"coordinates":[-97.12487900000001,32.602106],"type":"Point"}
}