{
  "type": "Feature",
  "properties": {
    "iso:country":"US",
    "sg:address":"1406 Cross Courts Dr",
    "sg:city":"Garland",
    "sg:classifiers":[
        {
            "category":"Professional",
            "subcategory":"Computer Services",
            "type":"Services"
        }
    ],
    "sg:phone":"+1 972 840 8431",
    "sg:postcode":"75040",
    "sg:province":"TX",
    "wof:name":"NM & P",
    "wof:placetype":"venue"
},
  "geometry": {"coordinates":[-96.60812199999999,32.902553],"type":"Point"}
}