{
  "type": "Feature",
  "properties": {
    "iso:country":"US",
    "sg:address":"11740 D-K Ranch Rd",
    "sg:city":"Austin",
    "sg:classifiers":[
        {
            "category":"Professional",
            "type":"Services"
        }
    ],
    "sg:phone":"+1 512 918 0600",
    "sg:postcode":"78759",
    "sg:province":"TX",
    "wof:name":"Tasha Devi",
    "wof:placetype":"venue"
},
  "geometry": {"coordinates":[-97.76615700000001,30.425621],"type":"Point"}
}