{
  "type": "Feature",
  "properties": {
    "iso:country":"US",
    "sg:address":"400 W Hopkins St",
    "sg:city":"San Marcos",
    "sg:classifiers":[
        {
            "category":"Insurance",
            "subcategory":"Insurance Agent",
            "type":"Services"
        }
    ],
    "sg:phone":"+1 512 396 8290",
    "sg:postcode":"78666",
    "sg:province":"TX",
    "wof:name":"Insurance Agency Of San Marcos",
    "wof:placetype":"venue"
},
  "geometry": {"coordinates":[-97.94551300000001,29.882531],"type":"Point"}
}