{
  "type": "Feature",
  "properties": {
    "iso:country":"US",
    "sg:address":"3035 S Shiloh Rd",
    "sg:city":"Garland",
    "sg:classifiers":[
        {
            "category":"Education",
            "subcategory":"Special Training",
            "type":"Public Place"
        },
        {
            "category":"Education",
            "subcategory":"Vocational School",
            "type":"Public Place"
        },
        {
            "category":"Education",
            "subcategory":"School",
            "type":"Public Place"
        }
    ],
    "sg:phone":"+1 888 209 8264",
    "sg:postcode":"75041",
    "sg:province":"TX",
    "sg:tags":[
        "technical",
        "industrial",
        "business",
        "language",
        "trade"
    ],
    "sg:website":"http://www.aticareertraining.edu/?Lead_Source=SuperPages&Lead_Type=Website",
    "wof:name":"ATI Career Training Center",
    "wof:placetype":"venue"
},
  "geometry": {"coordinates":[-96.665604,32.879431],"type":"Point"}
}