{
  "type": "Feature",
  "properties": {
    "iso:country":"US",
    "sg:address":"5908 73rd St",
    "sg:city":"Lubbock",
    "sg:classifiers":[
        {
            "category":"Professional",
            "subcategory":"Computer Services",
            "type":"Services"
        }
    ],
    "sg:phone":"+1 806 798 0881",
    "sg:postcode":"79424",
    "sg:province":"TX",
    "sg:tags":[
        "related"
    ],
    "wof:name":"Write Away Resume",
    "wof:placetype":"venue"
},
  "geometry": {"coordinates":[-101.941939,33.527475],"type":"Point"}
}