{
  "type": "Feature",
  "properties": {
    "iso:country":"US",
    "sg:address":"806 Main St",
    "sg:city":"Houston",
    "sg:classifiers":[
        {
            "category":"Shopping",
            "subcategory":"Jewelry",
            "type":"Retail Goods"
        }
    ],
    "sg:phone":"+1 713 227 7793",
    "sg:postcode":"77002",
    "sg:province":"TX",
    "sg:tags":[
        "watch"
    ],
    "wof:name":"Cooper & Co",
    "wof:placetype":"venue"
},
  "geometry": {"coordinates":[-95.364357,29.757767],"type":"Point"}
}