{
  "type": "Feature",
  "properties": {
    "iso:country":"US",
    "sg:address":"630 Boyd St",
    "sg:city":"Waco",
    "sg:classifiers":[
        {
            "category":"Building & Trades",
            "subcategory":"Construction",
            "type":"Services"
        }
    ],
    "sg:phone":"+1 254 753 5555",
    "sg:postcode":"76706",
    "sg:province":"TX",
    "sg:tags":[
        "house"
    ],
    "wof:name":"Shop At Home Roofing & Siding",
    "wof:placetype":"venue"
},
  "geometry": {"coordinates":[-97.09643199999999,31.527154],"type":"Point"}
}