{
  "type": "Feature",
  "properties": {
    "iso:country":"US",
    "sg:address":"3230 S Gessner Rd",
    "sg:city":"Houston",
    "sg:classifiers":[
        {
            "category":"Real Estate",
            "subcategory":"Real Estate Operator",
            "type":"Services"
        }
    ],
    "sg:phone":"+1 281 974 5639",
    "sg:postcode":"77063",
    "sg:province":"TX",
    "sg:tags":[
        "building",
        "apartment"
    ],
    "wof:name":"Tri Management Systems",
    "wof:placetype":"venue"
},
  "geometry": {"coordinates":[-95.53919500000001,29.729595],"type":"Point"}
}