{
  "type": "Feature",
  "properties": {
    "iso:country":"US",
    "sg:address":"12300 San Pedro Ave",
    "sg:city":"San Antonio",
    "sg:classifiers":[
        {
            "category":"Retail",
            "subcategory":"Auto Repair",
            "type":"Services"
        }
    ],
    "sg:phone":"+1 210 525 9800",
    "sg:postcode":"78216",
    "sg:province":"TX",
    "sg:tags":[
        "repairing",
        "automobile"
    ],
    "sg:website":"www.nsford.com",
    "wof:name":"Northside Ford",
    "wof:placetype":"venue"
},
  "geometry": {"coordinates":[-98.486357,29.55248],"type":"Point"}
}