{
  "type": "Feature",
  "properties": {
    "iso:country":"US",
    "sg:address":"1223 Industrial St",
    "sg:city":"New Braunfels",
    "sg:classifiers":[
        {
            "category":"Wholesale",
            "subcategory":"Hardware",
            "type":"Manufacturing & Wholesale Goods"
        }
    ],
    "sg:phone":"+1 830 625 7743",
    "sg:postcode":"78130",
    "sg:province":"TX",
    "sg:tags":[
        "air",
        "parts",
        "conditioning",
        "supply"
    ],
    "wof:name":"Insco Distributing Inc",
    "wof:placetype":"venue"
},
  "geometry": {"coordinates":[-98.097106,29.716294],"type":"Point"}
}