{
  "type": "Feature",
  "properties": {
    "iso:country":"US",
    "sg:address":"5120 Canal St",
    "sg:city":"Houston",
    "sg:classifiers":[
        {
            "category":"Organizations",
            "subcategory":"Religious Organization",
            "type":"Services"
        }
    ],
    "sg:phone":"+1 713 921 6072",
    "sg:postcode":"77011",
    "sg:province":"TX",
    "wof:name":"Iglesia Jesus Cristo El Salvador",
    "wof:placetype":"venue"
},
  "geometry": {"coordinates":[-95.322163,29.746528],"type":"Point"}
}