{
  "type": "Feature",
  "properties": {
    "iso:country":"US",
    "sg:address":"1309 Capital Ave",
    "sg:city":"Plano",
    "sg:classifiers":[
        {
            "category":"Real Estate",
            "subcategory":"Architect",
            "type":"Services"
        }
    ],
    "sg:phone":"+1 972 578 1681",
    "sg:postcode":"75074",
    "sg:province":"TX",
    "sg:tags":[
        "estimate",
        "construction"
    ],
    "wof:name":"Smith Steelite",
    "wof:placetype":"venue"
},
  "geometry": {"coordinates":[-96.69576600000001,33.011223],"type":"Point"}
}