{
  "type": "Feature",
  "properties": {
    "iso:country":"US",
    "sg:address":"10801 Moss Ridge Rd",
    "sg:city":"Houston",
    "sg:classifiers":[
        {
            "category":"Freight",
            "type":"Transportation"
        }
    ],
    "sg:phone":"+1 713 939 7609",
    "sg:postcode":"77043",
    "sg:province":"TX",
    "sg:tags":[
        "operator",
        "delivery",
        "local",
        "trucking"
    ],
    "wof:name":"Excel Direct",
    "wof:placetype":"venue"
},
  "geometry": {"coordinates":[-95.56711199999999,29.827479],"type":"Point"}
}