{
  "type": "Feature",
  "properties": {
    "iso:country":"US",
    "sg:address":"1804 Provine Ct",
    "sg:city":"Mc Kinney",
    "sg:classifiers":[
        {
            "category":"Professional",
            "type":"Services"
        }
    ],
    "sg:phone":"+1 214 544 3621",
    "sg:postcode":"75070",
    "sg:province":"TX",
    "wof:name":"Entrepreneurs Source",
    "wof:placetype":"venue"
},
  "geometry": {"coordinates":[-96.654138,33.18965],"type":"Point"}
}