{
  "type": "Feature",
  "properties": {
    "iso:country":"US",
    "sg:address":"15310 Ledgewood Park Dr",
    "sg:city":"Cypress",
    "sg:classifiers":[
        {
            "category":"Building & Trades",
            "subcategory":"Construction",
            "type":"Services"
        }
    ],
    "sg:phone":"+1 281 304 0008",
    "sg:postcode":"77429",
    "sg:province":"TX",
    "sg:tags":[
        "designer",
        "dealer",
        "pool",
        "swimming"
    ],
    "wof:name":"Aquatime Pools",
    "wof:placetype":"venue"
},
  "geometry": {"coordinates":[-95.65305600000001,29.967212],"type":"Point"}
}