{
  "type": "Feature",
  "properties": {
    "iso:country":"US",
    "sg:address":"3073 College Park Dr",
    "sg:city":"Conroe",
    "sg:classifiers":[
        {
            "category":"Restaurant",
            "type":"Food & Drink"
        }
    ],
    "sg:menulink":"http://www.allmenus.com/tx/southeast-montgomery/157476-whataburger/menu/",
    "sg:phone":"+1 936 273 7724",
    "sg:postcode":"77384",
    "sg:province":"TX",
    "sg:tags":[
        "burger",
        "american"
    ],
    "wof:name":"Whataburger",
    "wof:placetype":"venue"
},
  "geometry": {"coordinates":[-95.462064,30.206394],"type":"Point"}
}