{
  "type": "Feature",
  "properties": {
    "iso:country":"US",
    "sg:address":"4357 Whitfield Ave",
    "sg:city":"Fort Worth",
    "sg:classifiers":[
        {
            "category":"Professional",
            "type":"Services"
        }
    ],
    "sg:phone":"+1 817 924 1158",
    "sg:postcode":"76109",
    "sg:province":"TX",
    "wof:name":"Info World",
    "wof:placetype":"venue"
},
  "geometry": {"coordinates":[-97.38840500000001,32.679883],"type":"Point"}
}