{
  "type": "Feature",
  "properties": {
    "iso:country":"US",
    "sg:address":"8601 Redondo Dr",
    "sg:city":"Dallas",
    "sg:classifiers":[
        {
            "category":"Retail",
            "subcategory":"Repair Shop",
            "type":"Services"
        }
    ],
    "sg:phone":"+1 214 328 0328",
    "sg:postcode":"75218",
    "sg:province":"TX",
    "wof:name":"Robs PC Repair",
    "wof:placetype":"venue"
},
  "geometry": {"coordinates":[-96.70792899999999,32.823223],"type":"Point"}
}