{
  "type": "Feature",
  "properties": {
    "iso:country":"US",
    "sg:address":"2167 US Hwy 77",
    "sg:city":"Waxahachie",
    "sg:classifiers":[
        {
            "category":"Restaurant",
            "type":"Food & Drink"
        }
    ],
    "sg:phone":"+1 972 938 0047",
    "sg:postcode":"75165",
    "sg:province":"TX",
    "wof:name":"Campuzano's Fine Mexican Food",
    "wof:placetype":"venue"
},
  "geometry": {"coordinates":[-96.83917599999999,32.426307],"type":"Point"}
}