{
  "type": "Feature",
  "properties": {
    "iso:country":"US",
    "sg:address":"110 E Agostadero St",
    "sg:city":"Weslaco",
    "sg:classifiers":[
        {
            "category":"Health Services",
            "subcategory":"Clinic",
            "type":"Services"
        },
        {
            "category":"Personal",
            "type":"Services"
        },
        {
            "category":"Health Services",
            "subcategory":"Chiropractor",
            "type":"Services"
        }
    ],
    "sg:phone":"+1 956 969 8010",
    "sg:postcode":"78596",
    "sg:province":"TX",
    "sg:tags":[
        "chiropractic",
        "consultant",
        "program",
        "therapy",
        "fitness",
        "physical"
    ],
    "sg:website":"http://www.texasspinalsolutions.com",
    "wof:name":"Texas Spinal Care Centers",
    "wof:placetype":"venue"
},
  "geometry": {"coordinates":[-97.99069,26.165419],"type":"Point"}
}