{
  "type": "Feature",
  "properties": {
    "iso:country":"US",
    "sg:address":"2008 Oak Bluff Dr",
    "sg:city":"Arlington",
    "sg:classifiers":[
        {
            "category":"Professional",
            "subcategory":"Business Services",
            "type":"Services"
        }
    ],
    "sg:phone":"+1 817 469 7273",
    "sg:postcode":"76006",
    "sg:province":"TX",
    "sg:tags":[
        "commercial",
        "design"
    ],
    "wof:name":"Armstrong & Sons",
    "wof:placetype":"venue"
},
  "geometry": {"coordinates":[-97.074395,32.768431],"type":"Point"}
}