{
  "type": "Feature",
  "properties": {
    "iso:country":"US",
    "sg:address":"4707 Trinidad Dr",
    "sg:city":"Wichita Falls",
    "sg:classifiers":[
        {
            "category":"Professional",
            "subcategory":"Business Services",
            "type":"Services"
        }
    ],
    "sg:phone":"+1 940 696 1190",
    "sg:postcode":"76310",
    "sg:province":"TX",
    "wof:name":"R Boller LLC",
    "wof:placetype":"venue"
},
  "geometry": {"coordinates":[-98.57086700000001,33.858066],"type":"Point"}
}