{
  "type": "Feature",
  "properties": {
    "iso:country":"US",
    "sg:address":"12787 Somerset Rd",
    "sg:city":"Von Ormy",
    "sg:classifiers":[
        {
            "category":"Building & Trades",
            "subcategory":"Construction",
            "type":"Services"
        }
    ],
    "sg:phone":"+1 210 623 4458",
    "sg:postcode":"78073",
    "sg:province":"TX",
    "sg:tags":[
        "residential"
    ],
    "wof:name":"Ramiro O Flores",
    "wof:placetype":"venue"
},
  "geometry": {"coordinates":[-98.60263399999999,29.296796],"type":"Point"}
}