{
  "type": "Feature",
  "properties": {
    "iso:country":"US",
    "sg:address":"1710 W US Hwy 287 Byp",
    "sg:city":"Waxahachie",
    "sg:classifiers":[
        {
            "category":"Health Services",
            "subcategory":"Doctor",
            "type":"Services"
        }
    ],
    "sg:phone":"+1 972 937 1221",
    "sg:postcode":"75165",
    "sg:province":"TX",
    "sg:tags":[
        "medical"
    ],
    "wof:name":"M J Strength MD",
    "wof:placetype":"venue"
},
  "geometry": {"coordinates":[-96.855699,32.424552],"type":"Point"}
}