{
  "type": "Feature",
  "properties": {
    "iso:country":"US",
    "sg:address":"12952 Willow Chase Dr",
    "sg:city":"Houston",
    "sg:classifiers":[
        {
            "category":"Shopping",
            "subcategory":"Crafts & Fabrics",
            "type":"Retail Goods"
        }
    ],
    "sg:phone":"+1 281 469 6162",
    "sg:postcode":"77070",
    "sg:province":"TX",
    "sg:tags":[
        "sewing",
        "needlework"
    ],
    "wof:name":"Jo-Ann Fabrics & Crafts",
    "wof:placetype":"venue"
},
  "geometry": {"coordinates":[-95.552069,29.962115],"type":"Point"}
}