{
  "type": "Feature",
  "properties": {
    "iso:country":"US",
    "sg:address":"1134 W Main St",
    "sg:city":"Lewisville",
    "sg:classifiers":[
        {
            "category":"Shopping",
            "subcategory":"Hobbies, Toys, & Games",
            "type":"Retail Goods"
        }
    ],
    "sg:phone":"+1 972 221 1155",
    "sg:postcode":"75067",
    "sg:province":"TX",
    "wof:name":"Josies Gifts & Collectibles",
    "wof:placetype":"venue"
},
  "geometry": {"coordinates":[-97.023037,33.041956],"type":"Point"}
}