{
  "type": "Feature",
  "properties": {
    "iso:country":"US",
    "sg:address":"1414 Colorado St",
    "sg:city":"Austin",
    "sg:classifiers":[
        {
            "category":"Government",
            "subcategory":"City Hall",
            "type":"Public Place"
        }
    ],
    "sg:phone":"+1 512 427 1463",
    "sg:postcode":"78701",
    "sg:province":"TX",
    "sg:website":"www.texasbar.com",
    "wof:name":"State Bar of Texas",
    "wof:placetype":"venue"
},
  "geometry": {"coordinates":[-97.741067,30.276718],"type":"Point"}
}