{
  "type": "Feature",
  "properties": {
    "iso:country":"US",
    "sg:address":"515 Caroline St",
    "sg:city":"Houston",
    "sg:classifiers":[
        {
            "category":"Professional",
            "subcategory":"Lawyer & Legal Services",
            "type":"Services"
        }
    ],
    "sg:phone":"+1 713 224 2667",
    "sg:postcode":"77002",
    "sg:province":"TX",
    "wof:name":"Law Office of Troy Dun",
    "wof:placetype":"venue"
},
  "geometry": {"coordinates":[-95.359802,29.758475],"type":"Point"}
}