{
  "type": "Feature",
  "properties": {
    "iso:country":"US",
    "sg:address":"861 Landa St",
    "sg:city":"New Braunfels",
    "sg:classifiers":[
        {
            "category":"Health Services",
            "subcategory":"Health Practitioner",
            "type":"Services"
        }
    ],
    "sg:phone":"+1 830 609 3800",
    "sg:postcode":"78130",
    "sg:province":"TX",
    "wof:name":"Spinal Clinic South Texas",
    "wof:placetype":"venue"
},
  "geometry": {"coordinates":[-98.134293,29.705248],"type":"Point"}
}