{
  "type": "Feature",
  "properties": {
    "iso:country":"US",
    "sg:address":"2330 Texas Pkwy",
    "sg:city":"Missouri City",
    "sg:classifiers":[
        {
            "category":"Retail",
            "subcategory":"Auto Repair",
            "type":"Services"
        }
    ],
    "sg:phone":"+1 281 499 8926",
    "sg:postcode":"77489",
    "sg:province":"TX",
    "sg:tags":[
        "repairing",
        "automobile"
    ],
    "wof:name":"Prime Auto Care",
    "wof:placetype":"venue"
},
  "geometry": {"coordinates":[-95.52685200000001,29.594308],"type":"Point"}
}