{
  "type": "Feature",
  "properties": {
    "iso:country":"US",
    "sg:address":"115 N 9th St",
    "sg:city":"Mcallen",
    "sg:classifiers":[
        {
            "category":"Organizations",
            "subcategory":"Non-profit Organization",
            "type":"Services"
        }
    ],
    "sg:phone":"+1 956 687 7714",
    "sg:postcode":"78501",
    "sg:province":"TX",
    "sg:tags":[
        "info",
        "addiction",
        "abuse",
        "treatment",
        "drug"
    ],
    "wof:name":"Palmer Drug Abuse Program",
    "wof:placetype":"venue"
},
  "geometry": {"coordinates":[-98.22866500000001,26.205562],"type":"Point"}
}