{
  "type": "Feature",
  "properties": {
    "iso:country":"US",
    "sg:address":"10727 Memory Ln",
    "sg:city":"San Antonio",
    "sg:classifiers":[
        {
            "category":"Education",
            "subcategory":"School",
            "type":"Public Place"
        }
    ],
    "sg:phone":"+1 210 442 0625",
    "sg:postcode":"78216",
    "sg:province":"TX",
    "sg:tags":[
        "association"
    ],
    "wof:name":"Harmony Hills Elementary Schl",
    "wof:placetype":"venue"
},
  "geometry": {"coordinates":[-98.50020000000001,29.53836],"type":"Point"}
}