{
  "type": "Feature",
  "properties": {
    "iso:country":"US",
    "sg:address":"4315 S 1st St",
    "sg:city":"Austin",
    "sg:classifiers":[
        {
            "category":"Professional",
            "type":"Services"
        }
    ],
    "sg:phone":"+1 512 440 9340",
    "sg:postcode":"78745",
    "sg:province":"TX",
    "wof:name":"Texas Country Doctor",
    "wof:placetype":"venue"
},
  "geometry": {"coordinates":[-97.77273700000001,30.221144],"type":"Point"}
}