{
  "type": "Feature",
  "properties": {
    "iso:country":"US",
    "sg:address":"9518 Tallow Berry Dr",
    "sg:city":"Dallas",
    "sg:classifiers":[
        {
            "category":"Building & Trades",
            "subcategory":"Construction",
            "type":"Services"
        }
    ],
    "sg:phone":"+1 972 283 6671",
    "sg:postcode":"75249",
    "sg:province":"TX",
    "sg:tags":[
        "painter"
    ],
    "wof:name":"H&E Painting & Remodeling Co.",
    "wof:placetype":"venue"
},
  "geometry": {"coordinates":[-96.94547900000001,32.633942],"type":"Point"}
}