{
  "type": "Feature",
  "properties": {
    "iso:country":"US",
    "sg:address":"406 E Main Ave",
    "sg:city":"Round Rock",
    "sg:classifiers":[
        {
            "category":"Professional",
            "subcategory":"Management & Consulting",
            "type":"Services"
        }
    ],
    "sg:phone":"+1 512 238 8444",
    "sg:postcode":"78664",
    "sg:province":"TX",
    "wof:name":"Jwc Professionals",
    "wof:placetype":"venue"
},
  "geometry": {"coordinates":[-97.67465300000001,30.509826],"type":"Point"}
}