{
  "type": "Feature",
  "properties": {
    "iso:country":"US",
    "sg:address":"637 Westport Pkwy",
    "sg:city":"Grapevine",
    "sg:classifiers":[
        {
            "category":"Building & Trades",
            "subcategory":"Electrical",
            "type":"Services"
        }
    ],
    "sg:phone":"+1 817 410 1724",
    "sg:postcode":"76051",
    "sg:province":"TX",
    "sg:tags":[
        "control",
        "industrial",
        "electrician",
        "electric",
        "system",
        "controls",
        "regulator",
        "contractors-commercial"
    ],
    "sg:website":"http://www.panelmate.com",
    "wof:name":"Eaton Corporation",
    "wof:placetype":"venue"
},
  "geometry": {"coordinates":[-97.084236,32.903983],"type":"Point"}
}