{
  "type": "Feature",
  "properties": {
    "iso:country":"US",
    "sg:address":"1208 Zana Ln",
    "sg:city":"Rockdale",
    "sg:classifiers":[
        {
            "category":"Retail",
            "subcategory":"Laundry & Dry Cleaning",
            "type":"Services"
        }
    ],
    "sg:phone":"+1 512 446 9436",
    "sg:postcode":"76567",
    "sg:province":"TX",
    "wof:name":"Mary L Yates",
    "wof:placetype":"venue"
},
  "geometry": {"coordinates":[-97.016493,30.650013],"type":"Point"}
}