{
  "type": "Feature",
  "properties": {
    "iso:country":"US",
    "sg:address":"5201 E 42nd St",
    "sg:city":"Odessa",
    "sg:classifiers":[
        {
            "category":"Food & Beverages",
            "subcategory":"Groceries & Convenience Stores",
            "type":"Retail Goods"
        }
    ],
    "sg:phone":"+1 432 362 5161",
    "sg:postcode":"79762",
    "sg:province":"TX",
    "wof:name":"Town & Country Food Store 233",
    "wof:placetype":"venue"
},
  "geometry": {"coordinates":[-102.31093300000001,31.896976],"type":"Point"}
}