{
  "type": "Feature",
  "properties": {
    "iso:country":"US",
    "sg:address":"102 Axis Deer Trl",
    "sg:city":"Hutto",
    "sg:classifiers":[
        {
            "category":"Professional",
            "type":"Services"
        }
    ],
    "sg:phone":"+1 512 846 2389",
    "sg:postcode":"78634",
    "sg:province":"TX",
    "sg:tags":[
        "establishment"
    ],
    "wof:name":"American Commercial Flr Msters",
    "wof:placetype":"venue"
},
  "geometry": {"coordinates":[-97.58619299999999,30.535112],"type":"Point"}
}