{
  "type": "Feature",
  "properties": {
    "iso:country":"US",
    "sg:address":"1108 Wynncrest Ln",
    "sg:city":"Arlington",
    "sg:classifiers":[
        {
            "category":"Real Estate",
            "subcategory":"Real Estate Operator",
            "type":"Services"
        }
    ],
    "sg:phone":"+1 817 640 4006",
    "sg:postcode":"76006",
    "sg:province":"TX",
    "sg:tags":[
        "building",
        "apartment"
    ],
    "wof:name":"Oak Forest Apartments",
    "wof:placetype":"venue"
},
  "geometry": {"coordinates":[-97.06655600000001,32.76709],"type":"Point"}
}