{
  "type": "Feature",
  "properties": {
    "iso:country":"US",
    "sg:address":"7121 Windbrook Ln",
    "sg:city":"Corpus Christi",
    "sg:classifiers":[
        {
            "category":"Real Estate",
            "subcategory":"Real Estate Agent",
            "type":"Services"
        }
    ],
    "sg:phone":"+1 361 991 1988",
    "sg:postcode":"78414",
    "sg:province":"TX",
    "sg:tags":[
        "inspection"
    ],
    "wof:name":"ASI Andy Skloss Inspections",
    "wof:placetype":"venue"
},
  "geometry": {"coordinates":[-97.352127,27.679573],"type":"Point"}
}