{
  "type": "Feature",
  "properties": {
    "iso:country":"US",
    "sg:address":"1312 Linden Dr",
    "sg:city":"Plano",
    "sg:classifiers":[
        {
            "category":"Wholesale",
            "subcategory":"Electrical",
            "type":"Manufacturing & Wholesale Goods"
        }
    ],
    "sg:phone":"+1 972 424 7914",
    "sg:postcode":"75075",
    "sg:province":"TX",
    "sg:tags":[
        "equipment"
    ],
    "wof:name":"J G Lighting",
    "wof:placetype":"venue"
},
  "geometry": {"coordinates":[-96.72130900000001,33.013002],"type":"Point"}
}