{
  "type": "Feature",
  "properties": {
    "iso:country":"US",
    "sg:address":"3620 Strawberry Rd",
    "sg:city":"Pasadena",
    "sg:classifiers":[
        {
            "category":"Retail",
            "subcategory":"Repair Shop",
            "type":"Services"
        }
    ],
    "sg:phone":"+1 713 946 7900",
    "sg:postcode":"77504",
    "sg:province":"TX",
    "wof:name":"Front Line Technologies Inc",
    "wof:placetype":"venue"
},
  "geometry": {"coordinates":[-95.192314,29.658479],"type":"Point"}
}