{
  "type": "Feature",
  "properties": {
    "iso:country":"US",
    "sg:address":"2810 Buckeye Trl",
    "sg:city":"Cedar Park",
    "sg:classifiers":[
        {
            "category":"Professional",
            "type":"Services"
        }
    ],
    "sg:phone":"+1 512 257 7029",
    "sg:postcode":"78613",
    "sg:province":"TX",
    "wof:name":"Uniquely Yours",
    "wof:placetype":"venue"
},
  "geometry": {"coordinates":[-97.835455,30.466113],"type":"Point"}
}