{
  "type": "Feature",
  "properties": {
    "iso:country":"US",
    "sg:address":"5229 Spencer Hwy",
    "sg:city":"Pasadena",
    "sg:classifiers":[
        {
            "category":"Wholesale",
            "subcategory":"Farm Supplies",
            "type":"Manufacturing & Wholesale Goods"
        }
    ],
    "sg:phone":"+1 281 487 7267",
    "sg:postcode":"77505",
    "sg:province":"TX",
    "wof:name":"Feed Store",
    "wof:placetype":"venue"
},
  "geometry": {"coordinates":[-95.16136,29.665631],"type":"Point"}
}