{
  "type": "Feature",
  "properties": {
    "iso:country":"US",
    "sg:address":"20539 Umber Oak Ct",
    "sg:city":"Humble",
    "sg:classifiers":[
        {
            "category":"Personal",
            "subcategory":"Beauty Salon",
            "type":"Services"
        }
    ],
    "sg:phone":"+1 281 852 8294",
    "sg:postcode":"77346",
    "sg:province":"TX",
    "wof:name":"The Studio Salon",
    "wof:placetype":"venue"
},
  "geometry": {"coordinates":[-95.17371900000001,30.012545],"type":"Point"}
}