{
  "type": "Feature",
  "properties": {
    "iso:country":"US",
    "sg:address":"908 Flood St",
    "sg:city":"Wichita Falls",
    "sg:classifiers":[
        {
            "category":"Organizations",
            "subcategory":"Religious Organization",
            "type":"Services"
        }
    ],
    "sg:phone":"+1 940 716 9388",
    "sg:postcode":"76301",
    "sg:province":"TX",
    "wof:name":"Impact Word Of Faith",
    "wof:placetype":"venue"
},
  "geometry": {"coordinates":[-98.474085,33.915281],"type":"Point"}
}