{
  "type": "Feature",
  "properties": {
    "iso:country":"US",
    "sg:address":"1327 Gembler Rd",
    "sg:city":"San Antonio",
    "sg:classifiers":[
        {
            "category":"Professional",
            "subcategory":"Management & Consulting",
            "type":"Services"
        }
    ],
    "sg:phone":"+1 210 333 4134",
    "sg:postcode":"78219",
    "sg:province":"TX",
    "sg:tags":[
        "fuel"
    ],
    "wof:name":"R Schnieder Management Corp",
    "wof:placetype":"venue"
},
  "geometry": {"coordinates":[-98.408576,29.435711],"type":"Point"}
}