{
  "type": "Feature",
  "properties": {
    "iso:country":"US",
    "sg:address":"306 S 1st St",
    "sg:city":"Huntington",
    "sg:phone":"+1 936 824 5002",
    "sg:postcode":"75949",
    "sg:province":"TX",
    "sg:tags":[
        "product",
        "petroleum"
    ],
    "wof:name":"Spiveys Oil & Tire",
    "wof:placetype":"venue"
},
  "geometry": {"coordinates":[-94.58160700000001,31.276754],"type":"Point"}
}