{
  "type": "Feature",
  "properties": {
    "iso:country":"US",
    "sg:address":"6709 Beauford Dr",
    "sg:city":"Austin",
    "sg:classifiers":[
        {
            "category":"Professional",
            "subcategory":"Advertising",
            "type":"Services"
        }
    ],
    "sg:phone":"+1 512 345 3468",
    "sg:postcode":"78750",
    "sg:province":"TX",
    "sg:tags":[
        "representative"
    ],
    "wof:name":"Rood Productions",
    "wof:placetype":"venue"
},
  "geometry": {"coordinates":[-97.79412000000001,30.3755],"type":"Point"}
}