{
  "type": "Feature",
  "properties": {
    "iso:country":"US",
    "sg:address":"4505 Lone Tree Dr",
    "sg:city":"Plano",
    "sg:classifiers":[
        {
            "category":"Professional",
            "subcategory":"Business Services",
            "type":"Services"
        }
    ],
    "sg:phone":"+1 972 599 9096",
    "sg:postcode":"75093",
    "sg:province":"TX",
    "wof:name":"Nextek Solutions Inc",
    "wof:placetype":"venue"
},
  "geometry": {"coordinates":[-96.78304300000001,33.036456],"type":"Point"}
}