{
  "type": "Feature",
  "properties": {
    "iso:country":"US",
    "sg:address":"4241 Tanglewood Ln",
    "sg:city":"Odessa",
    "sg:classifiers":[
        {
            "category":"Professional",
            "subcategory":"Management & Consulting",
            "type":"Services"
        }
    ],
    "sg:phone":"+1 432 362 8600",
    "sg:postcode":"79762",
    "sg:province":"TX",
    "sg:tags":[
        "consultant",
        "business"
    ],
    "wof:name":"Permian Provider Management",
    "wof:placetype":"venue"
},
  "geometry": {"coordinates":[-102.34233500000001,31.89321],"type":"Point"}
}