{
  "type": "Feature",
  "properties": {
    "iso:country":"US",
    "sg:address":"1214 Dulles Ave",
    "sg:city":"Sugar Land",
    "sg:classifiers":[
        {
            "category":"Shopping",
            "subcategory":"Bicycles & Sporting Goods",
            "type":"Retail Goods"
        }
    ],
    "sg:phone":"+1 281 269 2527",
    "sg:postcode":"77478",
    "sg:province":"TX",
    "wof:name":"Riverband Golf Shop",
    "wof:placetype":"venue"
},
  "geometry": {"coordinates":[-95.582427,29.607663],"type":"Point"}
}