{
  "type": "Feature",
  "properties": {
    "iso:country":"US",
    "sg:address":"8028 Treeleaf",
    "sg:city":"Fort Worth",
    "sg:classifiers":[
        {
            "category":"Building & Trades",
            "subcategory":"Construction",
            "type":"Services"
        }
    ],
    "sg:phone":"+1 817 294 8784",
    "sg:postcode":"76123",
    "sg:province":"TX",
    "sg:tags":[
        "house",
        "real estate"
    ],
    "wof:name":"Steve Hawkins Custom Homes",
    "wof:placetype":"venue"
},
  "geometry": {"coordinates":[-97.38152100000001,32.625862],"type":"Point"}
}