{
  "type": "Feature",
  "properties": {
    "iso:country":"US",
    "sg:address":"1531 Commercial Ave",
    "sg:city":"Anson",
    "sg:classifiers":[
        {
            "category":"Organizations",
            "subcategory":"Religious Organization",
            "type":"Services"
        }
    ],
    "sg:phone":"+1 325 823 3682",
    "sg:postcode":"79501",
    "sg:province":"TX",
    "sg:tags":[
        "churches-baptist",
        "church"
    ],
    "wof:name":"First Baptist Church Of Anson",
    "wof:placetype":"venue"
},
  "geometry": {"coordinates":[-99.89685,32.752329],"type":"Point"}
}