{
  "type": "Feature",
  "properties": {
    "iso:country":"US",
    "sg:address":"7341 Wildvalley Dr",
    "sg:city":"Dallas",
    "sg:classifiers":[
        {
            "category":"Professional",
            "type":"Services"
        }
    ],
    "sg:phone":"+1 214 343 6188",
    "sg:postcode":"75231",
    "sg:province":"TX",
    "wof:name":"Amy Lootens",
    "wof:placetype":"venue"
},
  "geometry": {"coordinates":[-96.735365,32.859264],"type":"Point"}
}