{
  "type": "Feature",
  "properties": {
    "iso:country":"US",
    "sg:address":"6610 Harwin Dr",
    "sg:city":"Houston",
    "sg:classifiers":[
        {
            "category":"Health Services",
            "subcategory":"Clinic",
            "type":"Services"
        }
    ],
    "sg:phone":"+1 713 787 0949",
    "sg:postcode":"77036",
    "sg:province":"TX",
    "sg:tags":[
        "home",
        "care"
    ],
    "wof:name":"Maxwell Medical Service Inc",
    "wof:placetype":"venue"
},
  "geometry": {"coordinates":[-95.499326,29.719791],"type":"Point"}
}