{
  "type": "Feature",
  "properties": {
    "iso:country":"US",
    "sg:address":"3619 Drawbridge Dr",
    "sg:city":"Humble",
    "sg:classifiers":[
        {
            "category":"Professional",
            "subcategory":"Computer Services",
            "type":"Services"
        }
    ],
    "sg:phone":"+1 281 454 6304",
    "sg:postcode":"77396",
    "sg:province":"TX",
    "sg:tags":[
        "design",
        "system"
    ],
    "wof:name":"Gaila R Roberts",
    "wof:placetype":"venue"
},
  "geometry": {"coordinates":[-95.21836,29.973992],"type":"Point"}
}