{
  "type": "Feature",
  "properties": {
    "iso:country":"US",
    "sg:address":"3614 W Jefferson Blvd",
    "sg:city":"Dallas",
    "sg:classifiers":[
        {
            "category":"Autos & Motor Vehicles",
            "subcategory":"Automobile Sales",
            "type":"Retail Goods"
        }
    ],
    "sg:phone":"+1 214 467 8228",
    "sg:postcode":"75211",
    "sg:province":"TX",
    "sg:tags":[
        "dealers-used",
        "car",
        "used",
        "cars-wholesale"
    ],
    "wof:name":"B & J Auto Sales",
    "wof:placetype":"venue"
},
  "geometry": {"coordinates":[-96.879182,32.740276],"type":"Point"}
}