{
  "type": "Feature",
  "properties": {
    "iso:country":"US",
    "sg:address":"5010 Burma Rd",
    "sg:city":"Houston",
    "sg:classifiers":[
        {
            "category":"Manufacturing",
            "subcategory":"Glass & Minerals",
            "type":"Manufacturing & Wholesale Goods"
        }
    ],
    "sg:phone":"+1 713 738 3407",
    "sg:postcode":"77033",
    "sg:province":"TX",
    "sg:tags":[
        "tile",
        "mfg"
    ],
    "wof:name":"Manuela Quinones and Juan",
    "wof:placetype":"venue"
},
  "geometry": {"coordinates":[-95.344314,29.680385],"type":"Point"}
}