{
  "type": "Feature",
  "properties": {
    "iso:country":"US",
    "sg:address":"11010 Old Katy Rd",
    "sg:city":"Houston",
    "sg:classifiers":[
        {
            "category":"Retail",
            "subcategory":"Laundry & Dry Cleaning",
            "type":"Services"
        }
    ],
    "sg:phone":"+1 713 461 9276",
    "sg:postcode":"77043",
    "sg:province":"TX",
    "sg:tags":[
        "cleaners",
        "rug",
        "carpet"
    ],
    "wof:name":"Milenco LLC",
    "wof:placetype":"venue"
},
  "geometry": {"coordinates":[-95.574259,29.785099],"type":"Point"}
}