{
  "type": "Feature",
  "properties": {
    "iso:country":"US",
    "sg:address":"1310 E 1st St",
    "sg:city":"Del Rio",
    "sg:classifiers":[
        {
            "category":"Manufacturing",
            "subcategory":"Food",
            "type":"Manufacturing & Wholesale Goods"
        }
    ],
    "sg:phone":"+1 830 775 8561",
    "sg:postcode":"78840",
    "sg:province":"TX",
    "sg:tags":[
        "bottler"
    ],
    "wof:name":"Coca-Cola Bottling Co",
    "wof:placetype":"venue"
},
  "geometry": {"coordinates":[-100.888963,29.370001],"type":"Point"}
}