{
  "type": "Feature",
  "properties": {
    "iso:country":"US",
    "sg:address":"1800 Plymouth Dr W",
    "sg:city":"Irving",
    "sg:classifiers":[
        {
            "category":"Education",
            "subcategory":"School",
            "type":"Public Place"
        }
    ],
    "sg:phone":"+1 972 273 6700",
    "sg:postcode":"75061",
    "sg:province":"TX",
    "sg:website":"www.irvingisd.net",
    "wof:name":"IRVING INDEPENDENT SCHOOL DISTRICT ADMINISTRATIVE ANNEX",
    "wof:placetype":"venue"
},
  "geometry": {"coordinates":[-96.96826799999999,32.830882],"type":"Point"}
}