{
  "type": "Feature",
  "properties": {
    "iso:country":"US",
    "sg:address":"5002 52nd St",
    "sg:city":"Lubbock",
    "sg:classifiers":[
        {
            "category":"Building & Trades",
            "subcategory":"Construction",
            "type":"Services"
        }
    ],
    "sg:phone":"+1 806 792 5796",
    "sg:postcode":"79414",
    "sg:province":"TX",
    "sg:tags":[
        "nonresidential"
    ],
    "wof:name":"Premier Designs & Remodeling",
    "wof:placetype":"venue"
},
  "geometry": {"coordinates":[-101.922372,33.546916],"type":"Point"}
}