{
  "type": "Feature",
  "properties": {
    "iso:country":"US",
    "sg:address":"2003 Shadylane St",
    "sg:city":"Richmond",
    "sg:classifiers":[
        {
            "category":"Food & Beverages",
            "subcategory":"Groceries & Convenience Stores",
            "type":"Retail Goods"
        }
    ],
    "sg:phone":"+1 281 342 5987",
    "sg:postcode":"77469",
    "sg:province":"TX",
    "wof:name":"Plaid Leaf",
    "wof:placetype":"venue"
},
  "geometry": {"coordinates":[-95.756471,29.570013],"type":"Point"}
}