{
  "type": "Feature",
  "properties": {
    "iso:country":"US",
    "sg:address":"3415 Mall Dr",
    "sg:city":"Texarkana",
    "sg:classifiers":[
        {
            "category":"Restaurant",
            "type":"Food & Drink"
        }
    ],
    "sg:menulink":"http://www.allmenus.com/tx/texarkana/115009-chilis/menu/",
    "sg:phone":"+1 903 832 8763",
    "sg:postcode":"75503",
    "sg:province":"TX",
    "sg:tags":[
        "burger",
        "american",
        "sandwich",
        "tex-mex",
        "soup"
    ],
    "wof:name":"Chili's",
    "wof:placetype":"venue"
},
  "geometry": {"coordinates":[-94.08326099999999,33.45747],"type":"Point"}
}