{
  "type": "Feature",
  "properties": {
    "iso:country":"US",
    "sg:address":"10432 Coleridge St",
    "sg:city":"Dallas",
    "sg:classifiers":[
        {
            "category":"Banks & Credit Unions",
            "subcategory":"Bank",
            "type":"Services"
        }
    ],
    "sg:phone":"+1 214 321 5369",
    "sg:postcode":"75218",
    "sg:province":"TX",
    "sg:tags":[
        "depository",
        "banking"
    ],
    "wof:name":"Your Money Today",
    "wof:placetype":"venue"
},
  "geometry": {"coordinates":[-96.70077999999999,32.850714],"type":"Point"}
}