{
  "type": "Feature",
  "properties": {
    "iso:country":"US",
    "sg:address":"4117 Gulfway Dr",
    "sg:city":"Port Arthur",
    "sg:classifiers":[
        {
            "category":"Real Estate",
            "subcategory":"Real Estate Operator",
            "type":"Services"
        }
    ],
    "sg:phone":"+1 409 982 3260",
    "sg:postcode":"77642",
    "sg:province":"TX",
    "sg:tags":[
        "building",
        "apartment"
    ],
    "wof:name":"Tropicana Apartments",
    "wof:placetype":"venue"
},
  "geometry": {"coordinates":[-93.90991099999999,29.919221],"type":"Point"}
}