{
  "type": "Feature",
  "properties": {
    "iso:country":"US",
    "sg:address":"1802 Lamar Ave",
    "sg:city":"Paris",
    "sg:classifiers":[
        {
            "category":"Utilities",
            "subcategory":"Telephone",
            "type":"Services"
        }
    ],
    "sg:phone":"+1 903 785 8660",
    "sg:postcode":"75460",
    "sg:province":"TX",
    "sg:tags":[
        "communications",
        "r",
        "radiotelephone",
        "communication"
    ],
    "wof:name":"In Touch Phones",
    "wof:placetype":"venue"
},
  "geometry": {"coordinates":[-95.53799600000001,33.661184],"type":"Point"}
}