{
  "type": "Feature",
  "properties": {
    "iso:country":"US",
    "sg:address":"610 N Coit Rd",
    "sg:city":"Richardson",
    "sg:classifiers":[
        {
            "category":"Wholesale",
            "subcategory":"Computers",
            "type":"Manufacturing & Wholesale Goods"
        }
    ],
    "sg:phone":"+1 972 680 8452",
    "sg:postcode":"75080",
    "sg:province":"TX",
    "sg:tags":[
        "information",
        "technology",
        "sales"
    ],
    "wof:name":"Diversified Systems Inc",
    "wof:placetype":"venue"
},
  "geometry": {"coordinates":[-96.768902,32.957622],"type":"Point"}
}