{
  "type": "Feature",
  "properties": {
    "iso:country":"US",
    "sg:address":"116 Industrial Ct",
    "sg:city":"Conroe",
    "sg:classifiers":[
        {
            "category":"Manufacturing",
            "subcategory":"Rubber & Plastics",
            "type":"Manufacturing & Wholesale Goods"
        }
    ],
    "sg:phone":"+1 936 760 4100",
    "sg:postcode":"77301",
    "sg:province":"TX",
    "sg:tags":[
        "supply"
    ],
    "wof:name":"Applied Rubber Technology Inc",
    "wof:placetype":"venue"
},
  "geometry": {"coordinates":[-95.433886,30.316673],"type":"Point"}
}