{
  "type": "Feature",
  "properties": {
    "iso:country":"US",
    "sg:address":"2862 Nagle St",
    "sg:city":"Dallas",
    "sg:classifiers":[
        {
            "category":"Utilities",
            "subcategory":"Cable",
            "type":"Services"
        }
    ],
    "sg:phone":"+1 214 357 2099",
    "sg:postcode":"75220",
    "sg:province":"TX",
    "sg:tags":[
        "antenna",
        "community",
        "system"
    ],
    "sg:website":"www.brion-enterprises.com",
    "wof:name":"B & H Commercial Svc",
    "wof:placetype":"venue"
},
  "geometry": {"coordinates":[-96.87595,32.863644],"type":"Point"}
}