{
  "type": "Feature",
  "properties": {
    "iso:country":"US",
    "sg:address":"6414 Williamson Rd",
    "sg:city":"Creedmoor",
    "sg:classifiers":[
        {
            "category":"Professional",
            "subcategory":"Detective & Security Services",
            "type":"Services"
        }
    ],
    "sg:phone":"+1 512 826 5063",
    "sg:postcode":"78610",
    "sg:province":"TX",
    "sg:tags":[
        "information",
        "bureau"
    ],
    "wof:name":"Mobile Clubmaker Club Repair Service",
    "wof:placetype":"venue"
},
  "geometry": {"coordinates":[-97.728595,30.053895],"type":"Point"}
}