{
  "type": "Feature",
  "properties": {
    "iso:country":"US",
    "sg:address":"782 E I- 30",
    "sg:city":"Rockwall",
    "sg:classifiers":[
        {
            "category":"Professional",
            "subcategory":"Accounting & Tax Preparation",
            "type":"Services"
        }
    ],
    "sg:phone":"+1 972 772 6905",
    "sg:postcode":"75043",
    "sg:province":"TX",
    "sg:tags":[
        "return",
        "filing"
    ],
    "wof:name":"Jackson Hewitt Tax Svc",
    "wof:placetype":"venue"
},
  "geometry": {"coordinates":[-96.56616099999999,32.852017],"type":"Point"}
}