{
  "type": "Feature",
  "properties": {
    "iso:country":"US",
    "sg:address":"103 S Washburn St",
    "sg:city":"Decatur",
    "sg:classifiers":[
        {
            "category":"Personal",
            "subcategory":"Beauty Salon",
            "type":"Services"
        }
    ],
    "sg:phone":"+1 940 626 1516",
    "sg:postcode":"76234",
    "sg:province":"TX",
    "wof:name":"Freedom Lines",
    "wof:placetype":"venue"
},
  "geometry": {"coordinates":[-97.594353,33.23422],"type":"Point"}
}