{
  "type": "Feature",
  "properties": {
    "iso:country":"US",
    "sg:address":"6165 Hayes Ranch Rd",
    "sg:city":"Snyder",
    "sg:classifiers":[
        {
            "category":"Farming",
            "subcategory":"Livestock Farm",
            "type":"Manufacturing & Wholesale Goods"
        }
    ],
    "sg:phone":"+1 325 573 3505",
    "sg:postcode":"79549",
    "sg:province":"TX",
    "sg:tags":[
        "beef",
        "equine",
        "feedlot",
        "cattle"
    ],
    "wof:name":"Hays Ranch",
    "wof:placetype":"venue"
},
  "geometry": {"coordinates":[-100.999495,32.798894],"type":"Point"}
}