{
  "type": "Feature",
  "properties": {
    "iso:country":"US",
    "sg:address":"3028 Ash Ave",
    "sg:city":"Groves",
    "sg:classifiers":[
        {
            "category":"Shopping",
            "subcategory":"Hobbies, Toys, & Games",
            "type":"Retail Goods"
        },
        {
            "category":"Professional",
            "subcategory":"Business Services",
            "type":"Services"
        }
    ],
    "sg:phone":"+1 409 962 1293",
    "sg:postcode":"77619",
    "sg:province":"TX",
    "sg:tags":[
        "craft",
        "supply"
    ],
    "wof:name":"B T Express",
    "wof:placetype":"venue"
},
  "geometry": {"coordinates":[-93.903007,29.947069],"type":"Point"}
}