{
  "type": "Feature",
  "properties": {
    "iso:country":"US",
    "sg:address":"4510 S Broadway Ave",
    "sg:city":"Tyler",
    "sg:classifiers":[
        {
            "category":"Ice Cream",
            "type":"Food & Drink"
        }
    ],
    "sg:menulink":"http://www.allmenus.com/tx/tyler/162553-dairy-queen/menu/",
    "sg:phone":"+1 903 561 6111",
    "sg:postcode":"75703",
    "sg:province":"TX",
    "sg:tags":[
        "burger",
        "american"
    ],
    "wof:name":"Dairy Queen",
    "wof:placetype":"venue"
},
  "geometry": {"coordinates":[-95.300693,32.30096],"type":"Point"}
}