{
  "type": "Feature",
  "properties": {
    "iso:country":"US",
    "sg:address":"815 Frio City Rd",
    "sg:city":"San Antonio",
    "sg:classifiers":[
        {
            "category":"Retail",
            "subcategory":"Auto Repair",
            "type":"Services"
        }
    ],
    "sg:phone":"+1 210 271 1080",
    "sg:postcode":"78207",
    "sg:province":"TX",
    "sg:tags":[
        "repairing",
        "automobile"
    ],
    "wof:name":"Conchas Auto Mechanic",
    "wof:placetype":"venue"
},
  "geometry": {"coordinates":[-98.525043,29.401],"type":"Point"}
}