{
  "type": "Feature",
  "properties": {
    "iso:country":"US",
    "sg:address":"5550 Lyndon B. Johnson Freeway Suite 700",
    "sg:city":"Dallas",
    "sg:classifiers":[
        {
            "category":"Professional",
            "subcategory":"Computer Services",
            "type":"Services"
        }
    ],
    "sg:phone":"+1 214 296 2111",
    "sg:postcode":"75240",
    "sg:province":"TX",
    "sg:tags":[
        "geniusroom",
        "teleconferencing",
        "web-meeting",
        "collaboration",
        "communications",
        "web-2-0",
        "saas",
        "cloud-computing"
    ],
    "sg:website":"http://www.GeniusRoom.com/",
    "wof:name":"Virtual Telephone & Telegraph",
    "wof:placetype":"venue"
},
  "geometry": {"coordinates":[-96.811595,32.926341],"type":"Point"}
}