{
  "type": "Feature",
  "properties": {
    "iso:country":"US",
    "sg:address":"20343 Northbriar Dr",
    "sg:city":"Houston",
    "sg:classifiers":[
        {
            "category":"Building & Trades",
            "subcategory":"Construction",
            "type":"Services"
        }
    ],
    "sg:phone":"+1 281 821 0807",
    "sg:postcode":"77073",
    "sg:province":"TX",
    "sg:tags":[
        "hanging",
        "contractor"
    ],
    "wof:name":"Jeskims Fabric Wallcovering",
    "wof:placetype":"venue"
},
  "geometry": {"coordinates":[-95.401624,29.989043],"type":"Point"}
}