{
  "type": "Feature",
  "properties": {
    "iso:country":"US",
    "sg:address":"509 S Main St",
    "sg:city":"Paris",
    "sg:classifiers":[
        {
            "category":"Professional",
            "subcategory":"Computer Services",
            "type":"Services"
        }
    ],
    "sg:phone":"+1 903 783 1211",
    "sg:postcode":"75460",
    "sg:province":"TX",
    "sg:tags":[
        "design",
        "system"
    ],
    "wof:name":"Paris Tech Works",
    "wof:placetype":"venue"
},
  "geometry": {"coordinates":[-95.55622099999999,33.657132],"type":"Point"}
}