{
  "type": "Feature",
  "properties": {
    "iso:country":"US",
    "sg:address":"1818 E Overton Rd",
    "sg:city":"Dallas",
    "sg:classifiers":[
        {
            "category":"Social Services",
            "subcategory":"Child Care",
            "type":"Services"
        }
    ],
    "sg:phone":"+1 214 374 3007",
    "sg:postcode":"75216",
    "sg:province":"TX",
    "sg:tags":[
        "day"
    ],
    "wof:name":"A New Beginning Developement & Learning Cntr",
    "wof:placetype":"venue"
},
  "geometry": {"coordinates":[-96.799004,32.7047],"type":"Point"}
}