{
  "type": "Feature",
  "properties": {
    "iso:country":"US",
    "sg:address":"3222 Granite Lake Dr",
    "sg:city":"Missouri City",
    "sg:classifiers":[
        {
            "category":"Home & Garden",
            "subcategory":"Furniture",
            "type":"Retail Goods"
        }
    ],
    "sg:phone":"+1 281 499 0548",
    "sg:postcode":"77459",
    "sg:province":"TX",
    "sg:tags":[
        "rep",
        "mfg",
        "furnishing",
        "sales"
    ],
    "wof:name":"W H Casimir & Co",
    "wof:placetype":"venue"
},
  "geometry": {"coordinates":[-95.58017100000001,29.571135],"type":"Point"}
}