{
  "type": "Feature",
  "properties": {
    "iso:country":"US",
    "sg:address":"502 E Royall Blvd",
    "sg:city":"Malakoff",
    "sg:classifiers":[
        {
            "category":"Personal",
            "subcategory":"Beauty Salon",
            "type":"Services"
        }
    ],
    "sg:phone":"+1 903 489 3727",
    "sg:postcode":"75148",
    "sg:province":"TX",
    "sg:tags":[
        "shop"
    ],
    "wof:name":"Denises Hair Depot",
    "wof:placetype":"venue"
},
  "geometry": {"coordinates":[-95.99407600000001,32.17505],"type":"Point"}
}