{
  "type": "Feature",
  "properties": {
    "iso:country":"US",
    "sg:address":"221 E Expy 83",
    "sg:city":"Mission",
    "sg:classifiers":[
        {
            "category":"Shopping",
            "subcategory":"Jewelry",
            "type":"Retail Goods"
        }
    ],
    "sg:phone":"+1 956 519 3116",
    "sg:postcode":"78572",
    "sg:province":"TX",
    "wof:name":"Casa De Oro Romo",
    "wof:placetype":"venue"
},
  "geometry": {"coordinates":[-98.325031,26.201249],"type":"Point"}
}