{
  "type": "Feature",
  "properties": {
    "iso:country":"US",
    "sg:address":"338 E Cameron Ave",
    "sg:city":"Rockdale",
    "sg:classifiers":[
        {
            "category":"Retail",
            "subcategory":"Car Wash",
            "type":"Services"
        }
    ],
    "sg:phone":"+1 512 446 2077",
    "sg:postcode":"76567",
    "sg:province":"TX",
    "sg:tags":[
        "automobile",
        "detail",
        "clean"
    ],
    "wof:name":"Magic Wand Car Wash",
    "wof:placetype":"venue"
},
  "geometry": {"coordinates":[-96.99870900000001,30.65673],"type":"Point"}
}