{
  "type": "Feature",
  "properties": {
    "iso:country":"US",
    "sg:address":"106 W Blackstone Ln",
    "sg:city":"Alvin",
    "sg:classifiers":[
        {
            "category":"Utilities",
            "subcategory":"Refuse",
            "type":"Services"
        }
    ],
    "sg:phone":"+1 281 331 8400",
    "sg:postcode":"77511",
    "sg:province":"TX",
    "sg:tags":[
        "garbage",
        "collection"
    ],
    "wof:name":"Ameriwaste Inc",
    "wof:placetype":"venue"
},
  "geometry": {"coordinates":[-95.245357,29.413819],"type":"Point"}
}