{
  "type": "Feature",
  "properties": {
    "iso:country":"US",
    "sg:address":"2503 Frontier Dr",
    "sg:city":"Midland",
    "sg:classifiers":[
        {
            "category":"Building & Trades",
            "subcategory":"Construction",
            "type":"Services"
        }
    ],
    "sg:phone":"+1 432 570 7555",
    "sg:postcode":"79705",
    "sg:province":"TX",
    "sg:tags":[
        "painter"
    ],
    "wof:name":"Ronny Poole Painting",
    "wof:placetype":"venue"
},
  "geometry": {"coordinates":[-102.113157,32.017892],"type":"Point"}
}