{
  "type": "Feature",
  "properties": {
    "iso:country":"US",
    "sg:address":"136 W Slaughter Ln W",
    "sg:city":"Austin",
    "sg:classifiers":[
        {
            "category":"Professional",
            "type":"Services"
        },
        {
            "category":"Restaurant",
            "type":"Food & Drink"
        }
    ],
    "sg:phone":"+1 512 280 8364",
    "sg:postcode":"78745",
    "sg:province":"TX",
    "sg:tags":[
        "barbeque",
        "caterer"
    ],
    "sg:website":"www.billmillerbbq.com",
    "wof:name":"Bill Miller Bar-B-Q",
    "wof:placetype":"venue"
},
  "geometry": {"coordinates":[-97.788275,30.167199],"type":"Point"}
}