{
  "type": "Feature",
  "properties": {
    "iso:country":"US",
    "sg:address":"801 Princeton Dr",
    "sg:city":"Pflugerville",
    "sg:classifiers":[
        {
            "category":"Shopping",
            "type":"Retail Goods"
        }
    ],
    "sg:phone":"+1 512 990 8599",
    "sg:postcode":"78660",
    "sg:province":"TX",
    "sg:tags":[
        "merchandise"
    ],
    "wof:name":"Hubbard Designer Pins",
    "wof:placetype":"venue"
},
  "geometry": {"coordinates":[-97.630537,30.435212],"type":"Point"}
}