{
  "type": "Feature",
  "properties": {
    "iso:country":"US",
    "sg:address":"110 E Court St",
    "sg:city":"Seguin",
    "sg:classifiers":[
        {
            "category":"Restaurant",
            "type":"Food & Drink"
        }
    ],
    "sg:phone":"+1 830 379 4000",
    "sg:postcode":"78155",
    "sg:province":"TX",
    "sg:tags":[
        "eating"
    ],
    "wof:name":"P J's Restaurant",
    "wof:placetype":"venue"
},
  "geometry": {"coordinates":[-97.96386699999999,29.568993],"type":"Point"}
}