{
  "type": "Feature",
  "properties": {
    "iso:country":"US",
    "sg:address":"1614 Hannington Dr",
    "sg:city":"Katy",
    "sg:classifiers":[
        {
            "category":"Wholesale",
            "subcategory":"Chemicals & Plastics",
            "type":"Manufacturing & Wholesale Goods"
        }
    ],
    "sg:phone":"+1 281 492 2000",
    "sg:postcode":"77450",
    "sg:province":"TX",
    "wof:name":"AMJAY Chemicals",
    "wof:placetype":"venue"
},
  "geometry": {"coordinates":[-95.725526,29.761873],"type":"Point"}
}