{
  "type": "Feature",
  "properties": {
    "iso:country":"US",
    "sg:address":"17514 Brushy River Ct",
    "sg:city":"Houston",
    "sg:classifiers":[
        {
            "category":"Professional",
            "type":"Services"
        }
    ],
    "sg:phone":"+1 281 373 2114",
    "sg:postcode":"77095",
    "sg:province":"TX",
    "sg:tags":[
        "establishment"
    ],
    "wof:name":"Johnson Models",
    "wof:placetype":"venue"
},
  "geometry": {"coordinates":[-95.68227899999999,29.932788],"type":"Point"}
}