{
  "type": "Feature",
  "properties": {
    "iso:country":"US",
    "sg:address":"11856 Taylorcrest Rd",
    "sg:city":"Houston",
    "sg:classifiers":[
        {
            "category":"Health Services",
            "subcategory":"Dentist",
            "type":"Services"
        }
    ],
    "sg:phone":"+1 713 467 1037",
    "sg:postcode":"77024",
    "sg:province":"TX",
    "wof:name":"Renger Everett Dds",
    "wof:placetype":"venue"
},
  "geometry": {"coordinates":[-95.533489,29.773335],"type":"Point"}
}