{
  "type": "Feature",
  "properties": {
    "iso:country":"US",
    "sg:address":"24802 Aldine Westfield Rd",
    "sg:city":"Spring",
    "sg:classifiers":[
        {
            "category":"Health Services",
            "subcategory":"Clinic",
            "type":"Services"
        },
        {
            "category":"Health Services",
            "subcategory":"Nursing And Care Facility",
            "type":"Services"
        },
        {
            "category":"Community Center",
            "type":"Public Place"
        },
        {
            "category":"Health Services",
            "subcategory":"Hospital",
            "type":"Services"
        }
    ],
    "sg:phone":"+1 800 746 7287",
    "sg:postcode":"77373",
    "sg:province":"TX",
    "sg:tags":[
        "urgent",
        "medical",
        "nurse"
    ],
    "sg:website":"http://www.minuteclinic.com",
    "wof:name":"MinuteClinic",
    "wof:placetype":"venue"
},
  "geometry": {"coordinates":[-95.404197,30.064919],"type":"Point"}
}