{
  "type": "Feature",
  "properties": {
    "iso:country":"US",
    "sg:address":"401 Stone Ridge Dr",
    "sg:city":"Austin",
    "sg:classifiers":[
        {
            "category":"Professional",
            "subcategory":"Business Services",
            "type":"Services"
        }
    ],
    "sg:phone":"+1 512 266 1780",
    "sg:postcode":"78734",
    "sg:province":"TX",
    "sg:tags":[
        "appraiser"
    ],
    "wof:name":"Allison Business Machines",
    "wof:placetype":"venue"
},
  "geometry": {"coordinates":[-97.961324,30.373813],"type":"Point"}
}