{
  "type": "Feature",
  "properties": {
    "iso:country":"US",
    "sg:address":"2211 Fawn Glen St",
    "sg:city":"San Antonio",
    "sg:classifiers":[
        {
            "category":"Organizations",
            "subcategory":"Religious Organization",
            "type":"Services"
        }
    ],
    "sg:phone":"+1 210 494 1367",
    "sg:postcode":"78232",
    "sg:province":"TX",
    "wof:name":"Ministerio Derestauracion",
    "wof:placetype":"venue"
},
  "geometry": {"coordinates":[-98.455536,29.565735],"type":"Point"}
}