{
  "type": "Feature",
  "properties": {
    "iso:country":"US",
    "sg:address":"3185 Southmost Rd",
    "sg:city":"Brownsville",
    "sg:classifiers":[
        {
            "category":"Building & Trades",
            "subcategory":"Construction",
            "type":"Services"
        }
    ],
    "sg:phone":"+1 956 554 0009",
    "sg:postcode":"78521",
    "sg:province":"TX",
    "sg:tags":[
        "general",
        "contractor"
    ],
    "wof:name":"Lez Construction LLC",
    "wof:placetype":"venue"
},
  "geometry": {"coordinates":[-97.460312,25.905174],"type":"Point"}
}