{
  "type": "Feature",
  "properties": {
    "iso:country":"US",
    "sg:address":"38 Greentree Ln",
    "sg:city":"Conroe",
    "sg:classifiers":[
        {
            "category":"Shopping",
            "subcategory":"Gifts & Souvenirs",
            "type":"Retail Goods"
        }
    ],
    "sg:phone":"+1 936 856 5994",
    "sg:postcode":"77304",
    "sg:province":"TX",
    "wof:name":"Bingham Lyndith",
    "wof:placetype":"venue"
},
  "geometry": {"coordinates":[-95.497356,30.383993],"type":"Point"}
}