{
  "type": "Feature",
  "properties": {
    "iso:country":"US",
    "sg:address":"3719 Kings Row Dr",
    "sg:city":"Nacogdoches",
    "sg:classifiers":[
        {
            "category":"Professional",
            "subcategory":"Advertising",
            "type":"Services"
        }
    ],
    "sg:phone":"+1 936 564 7441",
    "sg:postcode":"75965",
    "sg:province":"TX",
    "sg:tags":[
        "agency"
    ],
    "wof:name":"Worldtourgroups",
    "wof:placetype":"venue"
},
  "geometry": {"coordinates":[-94.61827700000001,31.635959],"type":"Point"}
}