{
  "type": "Feature",
  "properties": {
    "iso:country":"US",
    "sg:address":"3710 E 29th St",
    "sg:city":"Bryan",
    "sg:classifiers":[
        {
            "category":"Banks & Credit Unions",
            "subcategory":"Bank",
            "type":"Services"
        }
    ],
    "sg:phone":"+1 979 260 3252",
    "sg:postcode":"77802",
    "sg:province":"TX",
    "sg:tags":[
        "state",
        "commercial"
    ],
    "wof:name":"Planters & Merchants State Bnk",
    "wof:placetype":"venue"
},
  "geometry": {"coordinates":[-96.33401000000001,30.647735],"type":"Point"}
}