{
  "type": "Feature",
  "properties": {
    "iso:country":"US",
    "sg:address":"10661 Haddington Dr Ste 160",
    "sg:city":"Houston",
    "sg:classifiers":[
        {
            "category":"Professional",
            "type":"Services"
        }
    ],
    "sg:phone":"+1 713 690 7823",
    "sg:postcode":"77043",
    "sg:province":"TX",
    "sg:website":"www.asisignage.com",
    "wof:name":"ASI Signage Innovations",
    "wof:placetype":"venue"
},
  "geometry": {"coordinates":[-95.560197,29.799977],"type":"Point"}
}