{
  "type": "Feature",
  "properties": {
    "iso:country":"US",
    "sg:address":"8222 Jamestown Dr",
    "sg:city":"Austin",
    "sg:classifiers":[
        {
            "category":"Wholesale",
            "subcategory":"Apparel",
            "type":"Manufacturing & Wholesale Goods"
        },
        {
            "category":"Manufacturing",
            "subcategory":"Apparel",
            "type":"Manufacturing & Wholesale Goods"
        }
    ],
    "sg:phone":"+1 512 833 8854",
    "sg:postcode":"78758",
    "sg:province":"TX",
    "sg:tags":[
        "leather",
        "clothing"
    ],
    "wof:name":"Hot Skins",
    "wof:placetype":"venue"
},
  "geometry": {"coordinates":[-97.712619,30.355311],"type":"Point"}
}