{
  "type": "Feature",
  "properties": {
    "iso:country":"US",
    "sg:address":"5012 Sable Oaks Dr",
    "sg:city":"Round Rock",
    "sg:classifiers":[
        {
            "category":"Banks & Credit Unions",
            "subcategory":"Financial Services",
            "type":"Services"
        }
    ],
    "sg:phone":"+1 512 238 1255",
    "sg:postcode":"78664",
    "sg:province":"TX",
    "sg:tags":[
        "investor"
    ],
    "wof:name":"New Paradigm Investments",
    "wof:placetype":"venue"
},
  "geometry": {"coordinates":[-97.605321,30.516893],"type":"Point"}
}