{
  "type": "Feature",
  "properties": {
    "iso:country":"US",
    "sg:address":"6037 W 34th Ave",
    "sg:city":"Amarillo",
    "sg:classifiers":[
        {
            "category":"Organizations",
            "subcategory":"Professional Association",
            "type":"Services"
        }
    ],
    "sg:phone":"+1 806 352 3108",
    "sg:postcode":"79109",
    "sg:province":"TX",
    "sg:tags":[
        "business"
    ],
    "wof:name":"Rotary Clubc",
    "wof:placetype":"venue"
},
  "geometry": {"coordinates":[-101.90408499999999,35.176391],"type":"Point"}
}