{
  "type": "Feature",
  "properties": {
    "iso:country":"US",
    "sg:address":"3023 Edgar Allen Poe Dr",
    "sg:city":"Laredo",
    "sg:classifiers":[
        {
            "category":"Professional",
            "subcategory":"Business Services",
            "type":"Services"
        }
    ],
    "sg:phone":"+1 956 717 2274",
    "sg:postcode":"78045",
    "sg:province":"TX",
    "wof:name":"Fire Star Express Inc",
    "wof:placetype":"venue"
},
  "geometry": {"coordinates":[-99.451843,27.581113],"type":"Point"}
}