{
  "type": "Feature",
  "properties": {
    "iso:country":"US",
    "sg:address":"1122 W Belt Line Rd",
    "sg:city":"Desoto",
    "sg:classifiers":[
        {
            "category":"Retail",
            "subcategory":"Car Wash",
            "type":"Services"
        }
    ],
    "sg:phone":"+1 972 223 3300",
    "sg:postcode":"75115",
    "sg:province":"TX",
    "wof:name":"Your Express Car Wash",
    "wof:placetype":"venue"
},
  "geometry": {"coordinates":[-96.886009,32.589522],"type":"Point"}
}