{
  "type": "Feature",
  "properties": {
    "iso:country":"US",
    "sg:address":"3401 NW 28th St",
    "sg:city":"Fort Worth",
    "sg:classifiers":[
        {
            "category":"Professional",
            "type":"Services"
        }
    ],
    "sg:phone":"+1 817 625 0181",
    "sg:postcode":"76106",
    "sg:province":"TX",
    "wof:name":"Louis Bonaldi",
    "wof:placetype":"venue"
},
  "geometry": {"coordinates":[-97.388306,32.809106],"type":"Point"}
}