{
  "type": "Feature",
  "properties": {
    "iso:country":"US",
    "sg:address":"1400 1st St E",
    "sg:city":"Humble",
    "sg:classifiers":[
        {
            "category":"Retail",
            "subcategory":"Veterinary Services",
            "type":"Services"
        }
    ],
    "sg:phone":"+1 281 446 7148",
    "sg:postcode":"77338",
    "sg:province":"TX",
    "sg:tags":[
        "clinic",
        "hospital",
        "veterinarian",
        "specialty"
    ],
    "sg:website":"http://vitalpet.com/index.php/offices/eastex_veterinary_clinic",
    "wof:name":"VitalPet-Eastex Veterinary Clinic",
    "wof:placetype":"venue"
},
  "geometry": {"coordinates":[-95.253113,29.999201],"type":"Point"}
}