{
  "type": "Feature",
  "properties": {
    "iso:country":"US",
    "sg:address":"1865 SE 4301",
    "sg:city":"Andrews",
    "sg:classifiers":[
        {
            "category":"Retail",
            "subcategory":"Laundry & Dry Cleaning",
            "type":"Services"
        },
        {
            "category":"Building & Trades",
            "subcategory":"Cleaning & Sanitation",
            "type":"Services"
        }
    ],
    "sg:phone":"+1 866 906 9546",
    "sg:postcode":"79714",
    "sg:province":"TX",
    "sg:tags":[
        "cleaner",
        "upholstery",
        "site-clean-up",
        "house",
        "rug",
        "damage",
        "water",
        "construction",
        "restoration",
        "carpet"
    ],
    "wof:name":"Dee's Cleaning Service",
    "wof:placetype":"venue"
},
  "geometry": {"coordinates":[-102.443499,32.310602],"type":"Point"}
}