{
  "type": "Feature",
  "properties": {
    "iso:country":"US",
    "sg:address":"16026 Miller Road 1",
    "sg:city":"Houston",
    "sg:classifiers":[
        {
            "category":"Professional",
            "type":"Services"
        }
    ],
    "sg:phone":"+1 281 457 6622",
    "sg:postcode":"77049",
    "sg:province":"TX",
    "sg:tags":[
        "establishment"
    ],
    "wof:name":"H & H Coupling",
    "wof:placetype":"venue"
},
  "geometry": {"coordinates":[-95.127697,29.835936],"type":"Point"}
}