{
  "type": "Feature",
  "properties": {
    "iso:country":"US",
    "sg:address":"3211 Ave E E",
    "sg:city":"Arlington",
    "sg:classifiers":[
        {
            "category":"Home & Garden",
            "subcategory":"Building Materials",
            "type":"Retail Goods"
        }
    ],
    "sg:phone":"+1 817 649 9577",
    "sg:postcode":"76011",
    "sg:province":"TX",
    "sg:tags":[
        "shower",
        "door",
        "enclosure"
    ],
    "wof:name":"Hartung Agalite",
    "wof:placetype":"venue"
},
  "geometry": {"coordinates":[-97.05029500000001,32.75652],"type":"Point"}
}