{
  "type": "Feature",
  "properties": {
    "iso:country":"US",
    "sg:address":"100 Crockett Rd",
    "sg:city":"Palestine",
    "sg:classifiers":[
        {
            "category":"Restaurant",
            "type":"Food & Drink"
        }
    ],
    "sg:phone":"+1 903 731 4507",
    "sg:postcode":"75801",
    "sg:province":"TX",
    "sg:tags":[
        "shop",
        "coffee"
    ],
    "wof:name":"Donut Palace",
    "wof:placetype":"venue"
},
  "geometry": {"coordinates":[-95.62723699999999,31.76173],"type":"Point"}
}