{
  "type": "Feature",
  "properties": {
    "iso:country":"US",
    "sg:address":"3026 Evergreen Glade Ct",
    "sg:city":"Humble",
    "sg:classifiers":[
        {
            "category":"Professional",
            "subcategory":"Secretarial Services",
            "type":"Services"
        }
    ],
    "sg:phone":"+1 281 359 4028",
    "sg:postcode":"77339",
    "sg:province":"TX",
    "sg:tags":[
        "reporting"
    ],
    "wof:name":"Adams Services",
    "wof:placetype":"venue"
},
  "geometry": {"coordinates":[-95.22605,30.055978],"type":"Point"}
}