{
  "type": "Feature",
  "properties": {
    "iso:country":"US",
    "sg:address":"5404 Almeda Rd",
    "sg:city":"Houston",
    "sg:classifiers":[
        {
            "category":"Restaurant",
            "type":"Food & Drink"
        }
    ],
    "sg:phone":"+1 713 533 1230",
    "sg:postcode":"77004",
    "sg:province":"TX",
    "sg:tags":[
        "barbeque"
    ],
    "wof:name":"Bar-B-Que Blues",
    "wof:placetype":"venue"
},
  "geometry": {"coordinates":[-95.37966,29.721658],"type":"Point"}
}