{
  "type": "Feature",
  "properties": {
    "iso:country":"US",
    "sg:address":"640 S Hwy 77",
    "sg:city":"Robstown",
    "sg:classifiers":[
        {
            "category":"Building & Trades",
            "subcategory":"Construction",
            "type":"Services"
        }
    ],
    "sg:phone":"+1 361 387 4364",
    "sg:postcode":"78380",
    "sg:province":"TX",
    "sg:tags":[
        "contractor"
    ],
    "wof:name":"Barron Builders & Management",
    "wof:placetype":"venue"
},
  "geometry": {"coordinates":[-97.661063,27.779833],"type":"Point"}
}