{
  "type": "Feature",
  "properties": {
    "iso:country":"US",
    "sg:address":"7702 Alameda Ave",
    "sg:city":"El Paso",
    "sg:classifiers":[
        {
            "category":"Retail",
            "subcategory":"Auto Repair",
            "type":"Services"
        }
    ],
    "sg:phone":"+1 915 778 2312",
    "sg:postcode":"79915",
    "sg:province":"TX",
    "sg:tags":[
        "general",
        "supply"
    ],
    "wof:name":"Beetle Shop",
    "wof:placetype":"venue"
},
  "geometry": {"coordinates":[-106.365002,31.731629],"type":"Point"}
}