{
  "type": "Feature",
  "properties": {
    "iso:country":"US",
    "sg:address":"1109 W University Dr",
    "sg:city":"Gainesville",
    "sg:classifiers":[
        {
            "category":"Mining & Drilling",
            "type":"Manufacturing & Wholesale Goods"
        }
    ],
    "sg:phone":"+1 940 668 9075",
    "sg:postcode":"76240",
    "sg:province":"TX",
    "sg:tags":[
        "field"
    ],
    "wof:name":"Walter J Haverkamp Inc",
    "wof:placetype":"venue"
},
  "geometry": {"coordinates":[-97.173569,33.616064],"type":"Point"}
}