{
  "type": "Feature",
  "properties": {
    "iso:country":"US",
    "sg:address":"813 Candle Meadow Blvd",
    "sg:city":"Desoto",
    "sg:classifiers":[
        {
            "category":"Banks & Credit Unions",
            "subcategory":"Investment Brokerage",
            "type":"Services"
        }
    ],
    "sg:phone":"+1 972 274 2394",
    "sg:postcode":"75115",
    "sg:province":"TX",
    "sg:tags":[
        "advisory"
    ],
    "wof:name":"Fresh Start Investment",
    "wof:placetype":"venue"
},
  "geometry": {"coordinates":[-96.89041899999999,32.576178],"type":"Point"}
}