{
  "type": "Feature",
  "properties": {
    "iso:country":"US",
    "sg:address":"515 N Capital of Texas Hwy",
    "sg:city":"Austin",
    "sg:classifiers":[
        {
            "category":"Professional",
            "subcategory":"Lawyer & Legal Services",
            "type":"Services"
        }
    ],
    "sg:phone":"+1 512 330 9005",
    "sg:postcode":"78746",
    "sg:province":"TX",
    "sg:tags":[
        "attorney"
    ],
    "wof:name":"Jeff Myerson Law Offices",
    "wof:placetype":"venue"
},
  "geometry": {"coordinates":[-97.826562,30.312394],"type":"Point"}
}