{
  "type": "Feature",
  "properties": {
    "iso:country":"US",
    "sg:address":"3522 Gus Thomasson Rd",
    "sg:city":"Mesquite",
    "sg:classifiers":[
        {
            "category":"Professional",
            "subcategory":"Detective & Security Services",
            "type":"Services"
        }
    ],
    "sg:phone":"+1 972 288 4300",
    "sg:postcode":"75150",
    "sg:province":"TX",
    "sg:tags":[
        "car",
        "investigator"
    ],
    "wof:name":"Triad Investigations Agency",
    "wof:placetype":"venue"
},
  "geometry": {"coordinates":[-96.633813,32.807907],"type":"Point"}
}