{
  "type": "Feature",
  "properties": {
    "iso:country":"US",
    "sg:address":"500 W Canton Rd",
    "sg:city":"Edinburg",
    "sg:classifiers":[
        {
            "category":"Professional",
            "subcategory":"Lawyer & Legal Services",
            "type":"Services"
        }
    ],
    "sg:phone":"+1 956 318 3700",
    "sg:postcode":"78539",
    "sg:province":"TX",
    "sg:tags":[
        "attorney"
    ],
    "wof:name":"Amado Robledo & Assoc",
    "wof:placetype":"venue"
},
  "geometry": {"coordinates":[-98.17100000000001,26.276321],"type":"Point"}
}