{
  "type": "Feature",
  "properties": {
    "iso:country":"US",
    "sg:address":"117 Warren Ct",
    "sg:city":"Denton",
    "sg:classifiers":[
        {
            "category":"Building & Trades",
            "subcategory":"Plumbing",
            "type":"Services"
        }
    ],
    "sg:phone":"+1 940 484 0556",
    "sg:postcode":"76201",
    "sg:province":"TX",
    "sg:tags":[
        "plumbing",
        "contractor"
    ],
    "wof:name":"Town & Country Plumbing",
    "wof:placetype":"venue"
},
  "geometry": {"coordinates":[-97.131486,33.2098],"type":"Point"}
}