{
  "type": "Feature",
  "properties": {
    "iso:country":"US",
    "sg:address":"531 Sheldon Rd",
    "sg:city":"Channelview",
    "sg:classifiers":[
        {
            "category":"Government",
            "subcategory":"Post Office",
            "type":"Public Place"
        }
    ],
    "sg:phone":"+1 281 457 5479",
    "sg:postcode":"77530",
    "sg:province":"TX",
    "wof:name":"US Government Post Offices",
    "wof:placetype":"venue"
},
  "geometry": {"coordinates":[-95.124802,29.7817],"type":"Point"}
}