{
  "type": "Feature",
  "properties": {
    "iso:country":"US",
    "sg:address":"3909 Spring Meadow Dr",
    "sg:city":"Pearland",
    "sg:classifiers":[
        {
            "category":"Manufacturing",
            "subcategory":"Printing",
            "type":"Manufacturing & Wholesale Goods"
        }
    ],
    "sg:phone":"+1 281 489 7545",
    "sg:postcode":"77584",
    "sg:province":"TX",
    "sg:tags":[
        "commercial"
    ],
    "wof:name":"Smartpictureadscom",
    "wof:placetype":"venue"
},
  "geometry": {"coordinates":[-95.30287199999999,29.537393],"type":"Point"}
}