{
  "type": "Feature",
  "properties": {
    "iso:country":"US",
    "sg:address":"2904 State Hwy 3",
    "sg:city":"La Marque",
    "sg:classifiers":[
        {
            "category":"Retail",
            "subcategory":"Repair Shop",
            "type":"Services"
        }
    ],
    "sg:phone":"+1 409 938 1632",
    "sg:postcode":"77568",
    "sg:province":"TX",
    "sg:tags":[
        "truck"
    ],
    "wof:name":"L & L Forklift Repairs",
    "wof:placetype":"venue"
},
  "geometry": {"coordinates":[-94.950497,29.359281],"type":"Point"}
}