{
  "type": "Feature",
  "properties": {
    "iso:country":"US",
    "sg:address":"13206 Summer Snow Cir",
    "sg:city":"Houston",
    "sg:classifiers":[
        {
            "category":"Restaurant",
            "type":"Food & Drink"
        }
    ],
    "sg:phone":"+1 713 849 5828",
    "sg:postcode":"77041",
    "sg:province":"TX",
    "sg:tags":[
        "eating"
    ],
    "wof:name":"In Chung",
    "wof:placetype":"venue"
},
  "geometry": {"coordinates":[-95.60908999999999,29.845541],"type":"Point"}
}