{
  "type": "Feature",
  "properties": {
    "iso:country":"US",
    "sg:address":"4532 Banyan Ln",
    "sg:city":"Dallas",
    "sg:classifiers":[
        {
            "category":"Health Services",
            "subcategory":"Doctor",
            "type":"Services"
        }
    ],
    "sg:phone":"+1 972 733 1488",
    "sg:postcode":"75287",
    "sg:province":"TX",
    "sg:tags":[
        "medicine",
        "physician",
        "practice",
        "surgeons",
        "family"
    ],
    "wof:name":"Bharat N. Vadher, M.D., P.A.",
    "wof:placetype":"venue"
},
  "geometry": {"coordinates":[-96.820666,32.997424],"type":"Point"}
}