{
  "type": "Feature",
  "properties": {
    "iso:country":"US",
    "sg:address":"595 Orleans St",
    "sg:city":"Beaumont",
    "sg:classifiers":[
        {
            "category":"Museum",
            "type":"Entertainment"
        }
    ],
    "sg:phone":"+1 409 835 3884",
    "sg:postcode":"77701",
    "sg:province":"TX",
    "sg:tags":[
        "organization",
        "arts",
        "information"
    ],
    "wof:name":"Young Audiences",
    "wof:placetype":"venue"
},
  "geometry": {"coordinates":[-94.098974,30.082645],"type":"Point"}
}