{
  "type": "Feature",
  "properties": {
    "iso:country":"US",
    "sg:address":"11505 Carla St",
    "sg:city":"Houston",
    "sg:classifiers":[
        {
            "category":"Retail",
            "subcategory":"Auto Repair",
            "type":"Services"
        }
    ],
    "sg:phone":"+1 713 696 9819",
    "sg:postcode":"77076",
    "sg:province":"TX",
    "sg:tags":[
        "truck",
        "general"
    ],
    "wof:name":"Albert's Shade Tree Garage",
    "wof:placetype":"venue"
},
  "geometry": {"coordinates":[-95.374104,29.870127],"type":"Point"}
}