{
  "type": "Feature",
  "properties": {
    "iso:country":"US",
    "sg:address":"708 San Antonio St.",
    "sg:city":"Austin",
    "sg:classifiers":[
        {
            "category":"Retail",
            "subcategory":"Event Space",
            "type":"Services"
        }
    ],
    "sg:phone":"+1 512 472 1336",
    "sg:postcode":"78701",
    "sg:province":"TX",
    "sg:tags":[
        "venue"
    ],
    "sg:website":"www.austinwc.org",
    "wof:name":"Austin Women's Club/ Chateau Bellevue",
    "wof:placetype":"venue"
},
  "geometry": {"coordinates":[-97.74732,30.271116],"type":"Point"}
}