{
  "type": "Feature",
  "properties": {
    "iso:country":"US",
    "sg:address":"10525 Palestine St",
    "sg:city":"Houston",
    "sg:classifiers":[
        {
            "category":"Building & Trades",
            "subcategory":"Construction",
            "type":"Services"
        }
    ],
    "sg:phone":"+1 713 675 5667",
    "sg:postcode":"77029",
    "sg:province":"TX",
    "sg:tags":[
        "sealcoating",
        "asphalt",
        "paving"
    ],
    "wof:name":"Portillos Asphalt",
    "wof:placetype":"venue"
},
  "geometry": {"coordinates":[-95.243235,29.766718],"type":"Point"}
}