{
  "type": "Feature",
  "properties": {
    "iso:country":"US",
    "sg:address":"1608 Red Leaf Dr",
    "sg:city":"San Antonio",
    "sg:classifiers":[
        {
            "category":"Personal",
            "type":"Services"
        }
    ],
    "sg:phone":"+1 210 402 0774",
    "sg:postcode":"78232",
    "sg:province":"TX",
    "sg:tags":[
        "therapist",
        "massage"
    ],
    "wof:name":"Joyce Medaris",
    "wof:placetype":"venue"
},
  "geometry": {"coordinates":[-98.468474,29.598157],"type":"Point"}
}