{
  "type": "Feature",
  "properties": {
    "iso:country":"US",
    "sg:address":"5512 Bellaire Dr S",
    "sg:city":"Benbrook",
    "sg:classifiers":[
        {
            "category":"Shopping",
            "subcategory":"Used Merchandise",
            "type":"Retail Goods"
        },
        {
            "category":"Shopping",
            "subcategory":"Clothing, Apparel, & Fashions",
            "type":"Retail Goods"
        }
    ],
    "sg:phone":"+1 817 377 9592",
    "sg:postcode":"76109",
    "sg:province":"TX",
    "sg:tags":[
        "uniform"
    ],
    "wof:name":"Medical Wear House",
    "wof:placetype":"venue"
},
  "geometry": {"coordinates":[-97.413072,32.694522],"type":"Point"}
}