{
  "type": "Feature",
  "properties": {
    "iso:country":"US",
    "sg:address":"2900 Boca Chica Blvd",
    "sg:city":"Brownsville",
    "sg:classifiers":[
        {
            "category":"Home & Garden",
            "subcategory":"Furniture",
            "type":"Retail Goods"
        }
    ],
    "sg:phone":"+1 956 982 0954",
    "sg:postcode":"78521",
    "sg:province":"TX",
    "wof:name":"Furniture Factory Warehouse",
    "wof:placetype":"venue"
},
  "geometry": {"coordinates":[-97.477847,25.921388],"type":"Point"}
}