{
  "type": "Feature",
  "properties": {
    "iso:country":"US",
    "sg:address":"2630 Culebra Rd",
    "sg:city":"San Antonio",
    "sg:classifiers":[
        {
            "category":"Autos & Motor Vehicles",
            "subcategory":"Auto Supplies",
            "type":"Retail Goods"
        }
    ],
    "sg:phone":"+1 210 438 1008",
    "sg:postcode":"78228",
    "sg:province":"TX",
    "wof:name":"Uniparts Inc",
    "wof:placetype":"venue"
},
  "geometry": {"coordinates":[-98.55117799999999,29.447614],"type":"Point"}
}