{
  "type": "Feature",
  "properties": {
    "iso:country":"US",
    "sg:address":"113 E Erwin St",
    "sg:city":"Tyler",
    "sg:classifiers":[
        {
            "category":"Professional",
            "subcategory":"Business Services",
            "type":"Services"
        }
    ],
    "sg:phone":"+1 903 526 0702",
    "sg:postcode":"75702",
    "sg:province":"TX",
    "wof:name":"Don Juans",
    "wof:placetype":"venue"
},
  "geometry": {"coordinates":[-95.299582,32.350757],"type":"Point"}
}