{
  "type": "Feature",
  "properties": {
    "iso:country":"US",
    "sg:address":"5405 E 11th St",
    "sg:city":"Brownsville",
    "sg:classifiers":[
        {
            "category":"Wholesale",
            "subcategory":"Scrap",
            "type":"Manufacturing & Wholesale Goods"
        }
    ],
    "sg:phone":"+1 956 831 0022",
    "sg:postcode":"78521",
    "sg:province":"TX",
    "sg:tags":[
        "recycling",
        "center"
    ],
    "wof:name":"Valley Cardboard Recycle",
    "wof:placetype":"venue"
},
  "geometry": {"coordinates":[-97.454142,25.930695],"type":"Point"}
}