{
  "type": "Feature",
  "properties": {
    "iso:country":"US",
    "sg:address":"917 E Lacy St",
    "sg:city":"Palestine",
    "sg:classifiers":[
        {
            "category":"Organizations",
            "subcategory":"Religious Organization",
            "type":"Services"
        }
    ],
    "sg:phone":"+1 903 729 1170",
    "sg:postcode":"75801",
    "sg:province":"TX",
    "wof:name":"Pastor Lee Jay",
    "wof:placetype":"venue"
},
  "geometry": {"coordinates":[-95.623768,31.765507],"type":"Point"}
}