{
  "type": "Feature",
  "properties": {
    "iso:country":"US",
    "sg:address":"550 Industrial Ave",
    "sg:city":"Odessa",
    "sg:classifiers":[
        {
            "category":"Wholesale",
            "subcategory":"Machinery & Supplies",
            "type":"Manufacturing & Wholesale Goods"
        }
    ],
    "sg:phone":"+1 432 580 0329",
    "sg:postcode":"79761",
    "sg:province":"TX",
    "sg:tags":[
        "equipment"
    ],
    "wof:name":"Weatherford Artfl Lift Systems",
    "wof:placetype":"venue"
},
  "geometry": {"coordinates":[-102.336488,31.840511],"type":"Point"}
}