{
  "type": "Feature",
  "properties": {
    "iso:country":"US",
    "sg:address":"4019 Mansfield Hwy",
    "sg:city":"Fort Worth",
    "sg:classifiers":[
        {
            "category":"Shopping",
            "type":"Retail Goods"
        }
    ],
    "sg:phone":"+1 817 536 1349",
    "sg:postcode":"76119",
    "sg:province":"TX",
    "sg:tags":[
        "farm",
        "merchandise",
        "supply"
    ],
    "wof:name":"Discount Feed & More",
    "wof:placetype":"venue"
},
  "geometry": {"coordinates":[-97.26725999999999,32.677551],"type":"Point"}
}