{
  "type": "Feature",
  "properties": {
    "iso:country":"US",
    "sg:address":"902 Hickory St",
    "sg:city":"Abilene",
    "sg:classifiers":[
        {
            "category":"Shopping",
            "subcategory":"Florist",
            "type":"Retail Goods"
        }
    ],
    "sg:phone":"+1 325 677 0042",
    "sg:postcode":"79601",
    "sg:province":"TX",
    "wof:name":"Wild Rice Flowers & More",
    "wof:placetype":"venue"
},
  "geometry": {"coordinates":[-99.735742,32.460725],"type":"Point"}
}