{
  "type": "Feature",
  "properties": {
    "iso:country":"US",
    "sg:address":"201 Dodge Rd",
    "sg:city":"El Paso",
    "sg:classifiers":[
        {
            "category":"Building & Trades",
            "subcategory":"Construction",
            "type":"Services"
        }
    ],
    "sg:phone":"+1 915 778 1881",
    "sg:postcode":"79915",
    "sg:province":"TX",
    "sg:tags":[
        "heavy"
    ],
    "wof:name":"In Terminal Services",
    "wof:placetype":"venue"
},
  "geometry": {"coordinates":[-106.379932,31.747795],"type":"Point"}
}