{
  "type": "Feature",
  "properties": {
    "iso:country":"US",
    "sg:address":"932 Carousel Dr",
    "sg:city":"Bedford",
    "sg:classifiers":[
        {
            "category":"Professional",
            "subcategory":"Management & Consulting",
            "type":"Services"
        }
    ],
    "sg:phone":"+1 817 281 9663",
    "sg:postcode":"76021",
    "sg:province":"TX",
    "sg:tags":[
        "business"
    ],
    "wof:name":"Sp Consolidated",
    "wof:placetype":"venue"
},
  "geometry": {"coordinates":[-97.15292599999999,32.858851],"type":"Point"}
}