{
  "type": "Feature",
  "properties": {
    "iso:country":"US",
    "sg:address":"13740 N Hwy 183 A-1",
    "sg:city":"Austin",
    "sg:classifiers":[
        {
            "category":"Banks & Credit Unions",
            "subcategory":"Investment Brokerage",
            "type":"Services"
        },
        {
            "category":"Insurance",
            "subcategory":"Hazard Insurance",
            "type":"Services"
        }
    ],
    "sg:phone":"+1 512 836 1231",
    "sg:postcode":"78750",
    "sg:province":"TX",
    "sg:tags":[
        "investing"
    ],
    "sg:website":"www.allstate.com/johnmurphy",
    "wof:name":"John Murphy - Allstate",
    "wof:placetype":"venue"
},
  "geometry": {"coordinates":[-97.794231,30.459217],"type":"Point"}
}