{
  "type": "Feature",
  "properties": {
    "iso:country":"US",
    "sg:address":"29334 McKinnon Rd",
    "sg:city":"Fulshear",
    "sg:classifiers":[
        {
            "category":"Retail",
            "subcategory":"Auto Repair",
            "type":"Services"
        }
    ],
    "sg:phone":"+1 281 346 0998",
    "sg:postcode":"77469",
    "sg:province":"TX",
    "sg:tags":[
        "automotive"
    ],
    "wof:name":"Kwf Electric LLC",
    "wof:placetype":"venue"
},
  "geometry": {"coordinates":[-95.882138,29.687538],"type":"Point"}
}