{
  "type": "Feature",
  "properties": {
    "iso:country":"US",
    "sg:address":"2416 Embry Pl",
    "sg:city":"Fort Worth",
    "sg:classifiers":[
        {
            "category":"Building & Trades",
            "subcategory":"Landscaping Services",
            "type":"Services"
        }
    ],
    "sg:phone":"+1 817 834 3118",
    "sg:postcode":"76111",
    "sg:province":"TX",
    "wof:name":"Contreras Genaro Jr",
    "wof:placetype":"venue"
},
  "geometry": {"coordinates":[-97.31028499999999,32.774914],"type":"Point"}
}