{
  "type": "Feature",
  "properties": {
    "iso:country":"US",
    "sg:address":"3824 E Loop 820 S",
    "sg:city":"Fort Worth",
    "sg:classifiers":[
        {
            "category":"Travel",
            "subcategory":"Hotels & Motels",
            "type":"Entertainment"
        }
    ],
    "sg:phone":"+1 817 451 7272",
    "sg:postcode":"76119",
    "sg:province":"TX",
    "wof:name":"Great Western Inn",
    "wof:placetype":"venue"
},
  "geometry": {"coordinates":[-97.232984,32.70643],"type":"Point"}
}