{
  "type": "Feature",
  "properties": {
    "iso:country":"US",
    "sg:address":"515 S. Congress #103",
    "sg:city":"Austin",
    "sg:classifiers":[
        {
            "category":"Real Estate",
            "subcategory":"Real Estate Services",
            "type":"Services"
        }
    ],
    "sg:phone":"+1 512 440 7776",
    "sg:postcode":"78704",
    "sg:province":"TX",
    "sg:website":"urban2realty.com",
    "wof:name":"Urban Squared Realty",
    "wof:placetype":"venue"
},
  "geometry": {"coordinates":[-97.746618,30.255921],"type":"Point"}
}