{
  "type": "Feature",
  "properties": {
    "iso:country":"US",
    "sg:address":"2162 Crockett Dr",
    "sg:city":"Denton",
    "sg:classifiers":[
        {
            "category":"Banks & Credit Unions",
            "subcategory":"Investment Brokerage",
            "type":"Services"
        }
    ],
    "sg:phone":"+1 940 321 5960",
    "sg:postcode":"76210",
    "sg:province":"TX",
    "sg:tags":[
        "advisory"
    ],
    "wof:name":"P & L Financial",
    "wof:placetype":"venue"
},
  "geometry": {"coordinates":[-97.07705300000001,33.136977],"type":"Point"}
}