{
  "type": "Feature",
  "properties": {
    "iso:country":"US",
    "sg:address":"1255 Coronado Cir",
    "sg:city":"Beaumont",
    "sg:classifiers":[
        {
            "category":"Professional",
            "type":"Services"
        }
    ],
    "sg:phone":"+1 409 866 1590",
    "sg:postcode":"77706",
    "sg:province":"TX",
    "wof:name":"Hollmont Ltd",
    "wof:placetype":"venue"
},
  "geometry": {"coordinates":[-94.175501,30.088711],"type":"Point"}
}