{
  "type": "Feature",
  "properties": {
    "iso:country":"US",
    "sg:address":"501 Texas Ave",
    "sg:city":"La Marque",
    "sg:classifiers":[
        {
            "category":"Food & Beverages",
            "subcategory":"Groceries & Convenience Stores",
            "type":"Retail Goods"
        }
    ],
    "sg:phone":"+1 409 938 8488",
    "sg:postcode":"77568",
    "sg:province":"TX",
    "wof:name":"Rocket Gas",
    "wof:placetype":"venue"
},
  "geometry": {"coordinates":[-94.95784399999999,29.379002],"type":"Point"}
}