{
  "type": "Feature",
  "properties": {
    "iso:country":"US",
    "sg:address":"1359 Lomaland Dr",
    "sg:city":"El Paso",
    "sg:classifiers":[
        {
            "category":"Social Services",
            "subcategory":"Job Training",
            "type":"Services"
        },
        {
            "category":"Professional",
            "subcategory":"Employment Agencies",
            "type":"Services"
        }
    ],
    "sg:phone":"+1 915 887 2400",
    "sg:postcode":"79935",
    "sg:province":"TX",
    "sg:tags":[
        "rehab",
        "opportunity",
        "government"
    ],
    "wof:name":"Texas Workforce Commission",
    "wof:placetype":"venue"
},
  "geometry": {"coordinates":[-106.327507,31.749692],"type":"Point"}
}