{
  "type": "Feature",
  "properties": {
    "iso:country":"US",
    "sg:address":"6490 FM 236",
    "sg:city":"Victoria",
    "sg:classifiers":[
        {
            "category":"Food & Beverages",
            "subcategory":"Groceries & Convenience Stores",
            "type":"Retail Goods"
        }
    ],
    "sg:phone":"+1 361 572 3397",
    "sg:postcode":"77905",
    "sg:province":"TX",
    "wof:name":"Windmill Store The",
    "wof:placetype":"venue"
},
  "geometry": {"coordinates":[-97.139973,28.848196],"type":"Point"}
}