{
  "type": "Feature",
  "properties": {
    "iso:country":"US",
    "sg:address":"122 W 2nd St",
    "sg:city":"Dalhart",
    "sg:classifiers":[
        {
            "category":"Wholesale",
            "subcategory":"Durable Goods & Equipment",
            "type":"Manufacturing & Wholesale Goods"
        }
    ],
    "sg:phone":"+1 806 268 0251",
    "sg:postcode":"79022",
    "sg:province":"TX",
    "wof:name":"Crossfire Extinguisher Sales",
    "wof:placetype":"venue"
},
  "geometry": {"coordinates":[-102.523899,36.064341],"type":"Point"}
}