{
  "type": "Feature",
  "properties": {
    "iso:country":"US",
    "sg:address":"607 S Friendswood Dr",
    "sg:city":"Friendswood",
    "sg:classifiers":[
        {
            "category":"Shopping",
            "type":"Retail Goods"
        }
    ],
    "sg:phone":"+1 281 992 7465",
    "sg:postcode":"77546",
    "sg:province":"TX",
    "sg:tags":[
        "item",
        "boutique"
    ],
    "wof:name":"The Girly Girl Boutique",
    "wof:placetype":"venue"
},
  "geometry": {"coordinates":[-95.197807,29.526819],"type":"Point"}
}