{
  "type": "Feature",
  "properties": {
    "iso:country":"US",
    "sg:address":"808 Ashburn Pl",
    "sg:city":"Plano",
    "sg:classifiers":[
        {
            "category":"Building & Trades",
            "subcategory":"Electrical",
            "type":"Services"
        }
    ],
    "sg:phone":"+1 469 241 0760",
    "sg:postcode":"75075",
    "sg:province":"TX",
    "sg:tags":[
        "telecommunication",
        "contractor"
    ],
    "wof:name":"Ericcsson Inc",
    "wof:placetype":"venue"
},
  "geometry": {"coordinates":[-96.711276,33.032777],"type":"Point"}
}