{
  "type": "Feature",
  "properties": {
    "iso:country":"US",
    "sg:address":"319 W Lakewood St",
    "sg:city":"Nacogdoches",
    "sg:classifiers":[
        {
            "category":"Shopping",
            "type":"Retail Goods"
        }
    ],
    "sg:phone":"+1 936 569 6776",
    "sg:postcode":"75965",
    "sg:province":"TX",
    "sg:tags":[
        "merchandise"
    ],
    "wof:name":"Alpha Tech International",
    "wof:placetype":"venue"
},
  "geometry": {"coordinates":[-94.654555,31.635211],"type":"Point"}
}