{
  "type": "Feature",
  "properties": {
    "iso:country":"US",
    "sg:address":"2400 Lakeview Dr",
    "sg:city":"Amarillo",
    "sg:classifiers":[
        {
            "category":"Education",
            "subcategory":"Dance Studio",
            "type":"Public Place"
        }
    ],
    "sg:phone":"+1 806 331 5867",
    "sg:postcode":"79109",
    "sg:province":"TX",
    "sg:tags":[
        "instruction",
        "dancing"
    ],
    "wof:name":"Cheer & Dance Co",
    "wof:placetype":"venue"
},
  "geometry": {"coordinates":[-101.874978,35.187262],"type":"Point"}
}