{
  "type": "Feature",
  "properties": {
    "iso:country":"US",
    "sg:address":"207 E Main St",
    "sg:city":"Post",
    "sg:classifiers":[
        {
            "category":"Shopping",
            "subcategory":"Gifts & Souvenirs",
            "type":"Retail Goods"
        }
    ],
    "sg:phone":"+1 806 495 0888",
    "sg:postcode":"79356",
    "sg:province":"TX",
    "sg:tags":[
        "shop"
    ],
    "wof:name":"Plum Crazy",
    "wof:placetype":"venue"
},
  "geometry": {"coordinates":[-101.37690499999999,33.190771],"type":"Point"}
}