{
  "type": "Feature",
  "properties": {
    "iso:country":"US",
    "sg:address":"2470 Woodbury Ct",
    "sg:city":"Pearland",
    "sg:classifiers":[
        {
            "category":"Shopping",
            "subcategory":"Hobbies, Toys, & Games",
            "type":"Retail Goods"
        }
    ],
    "sg:phone":"+1 281 997 8651",
    "sg:postcode":"77584",
    "sg:province":"TX",
    "wof:name":"Clarkes Hobby Shop Inc",
    "wof:placetype":"venue"
},
  "geometry": {"coordinates":[-95.362458,29.55054],"type":"Point"}
}