{
  "type": "Feature",
  "properties": {
    "iso:country":"US",
    "sg:address":"3824 Weyburn Dr",
    "sg:city":"Fort Worth",
    "sg:classifiers":[
        {
            "category":"Banks & Credit Unions",
            "subcategory":"Investment Brokerage",
            "type":"Services"
        }
    ],
    "sg:phone":"+1 817 927 4372",
    "sg:postcode":"76109",
    "sg:province":"TX",
    "wof:name":"Edward Jones Investments",
    "wof:placetype":"venue"
},
  "geometry": {"coordinates":[-97.376604,32.682564],"type":"Point"}
}