{
  "type": "Feature",
  "properties": {
    "iso:country":"US",
    "sg:address":"612 Jamie Ln",
    "sg:city":"Mansfield",
    "sg:classifiers":[
        {
            "category":"Professional",
            "subcategory":"Business Services",
            "type":"Services"
        }
    ],
    "sg:phone":"+1 682 518 1175",
    "sg:postcode":"76063",
    "sg:province":"TX",
    "wof:name":"Visual Perception Business Car",
    "wof:placetype":"venue"
},
  "geometry": {"coordinates":[-97.129851,32.603935],"type":"Point"}
}