{
  "type": "Feature",
  "properties": {
    "iso:country":"US",
    "sg:address":"1423 Marblecrest Dr",
    "sg:city":"Lewisville",
    "sg:classifiers":[
        {
            "category":"Autos & Motor Vehicles",
            "subcategory":"Automobile Sales",
            "type":"Retail Goods"
        }
    ],
    "sg:phone":"+1 214 222 0760",
    "sg:postcode":"75067",
    "sg:province":"TX",
    "sg:tags":[
        "used"
    ],
    "wof:name":"L Won Used Cars Inc",
    "wof:placetype":"venue"
},
  "geometry": {"coordinates":[-97.034989,33.037421],"type":"Point"}
}