{
  "type": "Feature",
  "properties": {
    "iso:country":"US",
    "sg:address":"1000 14th St",
    "sg:city":"Plano",
    "sg:classifiers":[
        {
            "category":"Building & Trades",
            "subcategory":"Construction",
            "type":"Services"
        }
    ],
    "sg:phone":"+1 972 422 0071",
    "sg:postcode":"75074",
    "sg:province":"TX",
    "sg:tags":[
        "contractor"
    ],
    "wof:name":"American Custom Roof",
    "wof:placetype":"venue"
},
  "geometry": {"coordinates":[-96.700654,33.018397],"type":"Point"}
}