{
  "type": "Feature",
  "properties": {
    "iso:country":"US",
    "sg:address":"9350 FM 1388",
    "sg:city":"Scurry",
    "sg:classifiers":[
        {
            "category":"Shopping",
            "subcategory":"Bicycles & Sporting Goods",
            "type":"Retail Goods"
        }
    ],
    "sg:phone":"+1 972 452 3488",
    "sg:postcode":"75142",
    "sg:province":"TX",
    "wof:name":"Dream Lake Ski Ranch",
    "wof:placetype":"venue"
},
  "geometry": {"coordinates":[-96.32959700000001,32.512777],"type":"Point"}
}