{
  "type": "Feature",
  "properties": {
    "iso:country":"US",
    "sg:address":"22910 Lodge Meadows Dr",
    "sg:city":"Katy",
    "sg:classifiers":[
        {
            "category":"Professional",
            "subcategory":"Management & Consulting",
            "type":"Services"
        }
    ],
    "sg:phone":"+1 281 395 1013",
    "sg:postcode":"77494",
    "sg:province":"TX",
    "sg:tags":[
        "business"
    ],
    "wof:name":"MCR Business Management",
    "wof:placetype":"venue"
},
  "geometry": {"coordinates":[-95.76951200000001,29.755739],"type":"Point"}
}