{
  "type": "Feature",
  "properties": {
    "iso:country":"US",
    "sg:address":"5400 Memorial Dr",
    "sg:city":"Houston",
    "sg:classifiers":[
        {
            "category":"Professional",
            "subcategory":"Business Services",
            "type":"Services"
        }
    ],
    "sg:phone":"+1 713 880 0312",
    "sg:postcode":"77007",
    "sg:province":"TX",
    "wof:name":"Dannette Interiors",
    "wof:placetype":"venue"
},
  "geometry": {"coordinates":[-95.417563,29.761377],"type":"Point"}
}