{
  "type": "Feature",
  "properties": {
    "iso:country":"US",
    "sg:address":"320 S Utah Ave",
    "sg:city":"Weslaco",
    "sg:classifiers":[
        {
            "category":"Manufacturing",
            "subcategory":"Food",
            "type":"Manufacturing & Wholesale Goods"
        }
    ],
    "sg:phone":"+1 956 969 8747",
    "sg:postcode":"78596",
    "sg:province":"TX",
    "sg:tags":[
        "mfg",
        "potato"
    ],
    "wof:name":"Mission Foods",
    "wof:placetype":"venue"
},
  "geometry": {"coordinates":[-97.978678,26.160238],"type":"Point"}
}