{
  "type": "Feature",
  "properties": {
    "iso:country":"US",
    "sg:address":"176 Alma Dr",
    "sg:city":"Ennis",
    "sg:classifiers":[
        {
            "category":"Building & Trades",
            "subcategory":"Equipment Rental",
            "type":"Services"
        }
    ],
    "sg:phone":"+1 972 878 7934",
    "sg:postcode":"75119",
    "sg:province":"TX",
    "wof:name":"B & B Fun",
    "wof:placetype":"venue"
},
  "geometry": {"coordinates":[-96.55659,32.268819],"type":"Point"}
}