{
  "type": "Feature",
  "properties": {
    "iso:country":"US",
    "sg:address":"401 E Davis St",
    "sg:city":"Luling",
    "sg:classifiers":[
        {
            "category":"Restaurant",
            "type":"Food & Drink"
        }
    ],
    "sg:phone":"+1 830 540 4943",
    "sg:postcode":"78648",
    "sg:province":"TX",
    "sg:tags":[
        "eating"
    ],
    "wof:name":"Montes",
    "wof:placetype":"venue"
},
  "geometry": {"coordinates":[-97.638017,29.679536],"type":"Point"}
}