{
  "type": "Feature",
  "properties": {
    "iso:country":"US",
    "sg:address":"506 S Jefferson St",
    "sg:city":"Amarillo",
    "sg:classifiers":[
        {
            "category":"Building & Trades",
            "subcategory":"Plumbing",
            "type":"Services"
        }
    ],
    "sg:phone":"+1 806 372 9414",
    "sg:postcode":"79101",
    "sg:province":"AR",
    "sg:tags":[
        "plumbing",
        "contractor"
    ],
    "wof:name":"Advanced Plumbing",
    "wof:placetype":"venue"
},
  "geometry": {"coordinates":[-101.84584,35.208851],"type":"Point"}
}