{
  "type": "Feature",
  "properties": {
    "iso:country":"US",
    "sg:address":"5824 Dick Price Rd",
    "sg:city":"Fort Worth",
    "sg:classifiers":[
        {
            "category":"Building & Trades",
            "subcategory":"Landscaping Services",
            "type":"Services"
        }
    ],
    "sg:phone":"+1 817 563 5900",
    "sg:postcode":"76140",
    "sg:province":"TX",
    "sg:tags":[
        "grass"
    ],
    "wof:name":"Skeeter's Portable Welding",
    "wof:placetype":"venue"
},
  "geometry": {"coordinates":[-97.234424,32.611504],"type":"Point"}
}