{
  "type": "Feature",
  "properties": {
    "iso:country":"US",
    "sg:address":"8530 Congress Ave S",
    "sg:city":"Austin",
    "sg:classifiers":[
        {
            "category":"Professional",
            "subcategory":"Business Services",
            "type":"Services"
        }
    ],
    "sg:phone":"+1 512 656 0141",
    "sg:postcode":"78745",
    "sg:province":"TX",
    "wof:name":"Perez Enterprises Inc",
    "wof:placetype":"venue"
},
  "geometry": {"coordinates":[-97.785985,30.171016],"type":"Point"}
}