{
  "type": "Feature",
  "properties": {
    "iso:country":"US",
    "sg:address":"20700 State Hwy 71",
    "sg:city":"Spicewood",
    "sg:classifiers":[
        {
            "category":"Restaurant",
            "type":"Food & Drink"
        }
    ],
    "sg:phone":"+1 512 264 9378",
    "sg:postcode":"78669",
    "sg:province":"TX",
    "wof:name":"Cedar Bar & Grill",
    "wof:placetype":"venue"
},
  "geometry": {"coordinates":[-98.061302,30.349492],"type":"Point"}
}