{
  "type": "Feature",
  "properties": {
    "iso:country":"US",
    "sg:address":"4331 Gus Thomasson Rd",
    "sg:city":"Mesquite",
    "sg:classifiers":[
        {
            "category":"Retail",
            "subcategory":"Laundry & Dry Cleaning",
            "type":"Services"
        }
    ],
    "sg:phone":"+1 972 279 2000",
    "sg:postcode":"75150",
    "sg:province":"TX",
    "sg:tags":[
        "cleaner"
    ],
    "wof:name":"Cleaning Shop the",
    "wof:placetype":"venue"
},
  "geometry": {"coordinates":[-96.642899,32.820499],"type":"Point"}
}