{
  "type": "Feature",
  "properties": {
    "iso:country":"US",
    "sg:address":"9415 W University Blvd",
    "sg:city":"Odessa",
    "sg:classifiers":[
        {
            "category":"Retail",
            "subcategory":"Laundry & Dry Cleaning",
            "type":"Services"
        }
    ],
    "sg:phone":"+1 432 381 7537",
    "sg:postcode":"79764",
    "sg:province":"TX",
    "sg:tags":[
        "cleaners"
    ],
    "wof:name":"Sunshine Laundry & Dry Clean",
    "wof:placetype":"venue"
},
  "geometry": {"coordinates":[-102.48857599999999,31.843737],"type":"Point"}
}