{
  "type": "Feature",
  "properties": {
    "iso:country":"US",
    "sg:address":"3434 W Little York Rd",
    "sg:city":"Houston",
    "sg:classifiers":[
        {
            "category":"Personal",
            "type":"Services"
        }
    ],
    "sg:phone":"+1 713 631 1710",
    "sg:postcode":"77091",
    "sg:province":"TX",
    "wof:name":"B & K Weddings",
    "wof:placetype":"venue"
},
  "geometry": {"coordinates":[-95.459317,29.863525],"type":"Point"}
}