{
  "type": "Feature",
  "properties": {
    "iso:country":"US",
    "sg:address":"1628 Aquarena Springs Dr",
    "sg:city":"San Marcos",
    "sg:classifiers":[
        {
            "category":"Real Estate",
            "subcategory":"Real Estate Agent",
            "type":"Services"
        },
        {
            "category":"Organizations",
            "subcategory":"Professional Association",
            "type":"Services"
        }
    ],
    "sg:phone":"+1 512 396 5478",
    "sg:postcode":"78666",
    "sg:province":"TX",
    "sg:tags":[
        "consultant",
        "consulting",
        "management",
        "business"
    ],
    "wof:name":"San Marcos Area Board Realtors",
    "wof:placetype":"venue"
},
  "geometry": {"coordinates":[-97.918138,29.892791],"type":"Point"}
}