{
  "type": "Feature",
  "properties": {
    "iso:country":"US",
    "sg:address":"7110 Tierra Bonita",
    "sg:city":"San Antonio",
    "sg:classifiers":[
        {
            "category":"Building & Trades",
            "subcategory":"Plumbing",
            "type":"Services"
        }
    ],
    "sg:phone":"+1 210 648 3700",
    "sg:postcode":"78263",
    "sg:province":"TX",
    "sg:tags":[
        "plumbing",
        "contractor"
    ],
    "wof:name":"River City Plumbing",
    "wof:placetype":"venue"
},
  "geometry": {"coordinates":[-98.347289,29.402289],"type":"Point"}
}