{
  "type": "Feature",
  "properties": {
    "iso:country":"US",
    "sg:address":"1490 S Church St",
    "sg:city":"Paris",
    "sg:classifiers":[
        {
            "category":"Retail",
            "subcategory":"Repair Shop",
            "type":"Services"
        }
    ],
    "sg:phone":"+1 903 785 0700",
    "sg:postcode":"75460",
    "sg:province":"TX",
    "sg:tags":[
        "door"
    ],
    "wof:name":"Overhead Door Co Of Paris",
    "wof:placetype":"venue"
},
  "geometry": {"coordinates":[-95.554785,33.64791],"type":"Point"}
}