{
  "type": "Feature",
  "properties": {
    "iso:country":"US",
    "sg:address":"5245 Joe Herrera Dr",
    "sg:city":"El Paso",
    "sg:classifiers":[
        {
            "category":"Social Services",
            "subcategory":"Child Care",
            "type":"Services"
        }
    ],
    "sg:phone":"+1 915 755 1720",
    "sg:postcode":"79924",
    "sg:province":"TX",
    "wof:name":"Erika H Tosh",
    "wof:placetype":"venue"
},
  "geometry": {"coordinates":[-106.417751,31.874148],"type":"Point"}
}