{
  "type": "Feature",
  "properties": {
    "iso:country":"US",
    "sg:address":"11200 Westheimer Rd",
    "sg:city":"Houston",
    "sg:classifiers":[
        {
            "category":"Manufacturing",
            "subcategory":"Printing",
            "type":"Manufacturing & Wholesale Goods"
        }
    ],
    "sg:phone":"+1 713 972 0003",
    "sg:postcode":"77042",
    "sg:province":"TX",
    "sg:tags":[
        "newspaper"
    ],
    "wof:name":"Al Haqiqa Newspaper",
    "wof:placetype":"venue"
},
  "geometry": {"coordinates":[-95.575107,29.736708],"type":"Point"}
}