{
  "type": "Feature",
  "properties": {
    "iso:country":"US",
    "sg:address":"6012 Sisk Rd",
    "sg:city":"Wichita Falls",
    "sg:classifiers":[
        {
            "category":"Retail",
            "subcategory":"Repair Shop",
            "type":"Services"
        }
    ],
    "sg:phone":"+1 940 691 5075",
    "sg:postcode":"76310",
    "sg:province":"TX",
    "sg:tags":[
        "taxidermist"
    ],
    "wof:name":"Lone Wolf Wildlife Studio",
    "wof:placetype":"venue"
},
  "geometry": {"coordinates":[-98.60357999999999,33.848122],"type":"Point"}
}