{
  "type": "Feature",
  "properties": {
    "iso:country":"US",
    "sg:address":"1727 N Prairie Ave",
    "sg:city":"Dallas",
    "sg:classifiers":[
        {
            "category":"Professional",
            "subcategory":"Computer Services",
            "type":"Services"
        }
    ],
    "sg:phone":"+1 214 887 3413",
    "sg:postcode":"75204",
    "sg:province":"TX",
    "sg:tags":[
        "datum"
    ],
    "wof:name":"Exl Media",
    "wof:placetype":"venue"
},
  "geometry": {"coordinates":[-96.778249,32.806323],"type":"Point"}
}