{
  "type": "Feature",
  "properties": {
    "iso:country":"US",
    "sg:address":"10566 N Dowling Rd",
    "sg:city":"College Station",
    "sg:classifiers":[
        {
            "category":"Building & Trades",
            "subcategory":"Plumbing",
            "type":"Services"
        }
    ],
    "sg:phone":"+1 979 693 7568",
    "sg:postcode":"77845",
    "sg:province":"TX",
    "sg:tags":[
        "contractor"
    ],
    "wof:name":"Sustaire Plumbing Co",
    "wof:placetype":"venue"
},
  "geometry": {"coordinates":[-96.34699500000001,30.572661],"type":"Point"}
}