{
  "type": "Feature",
  "properties": {
    "iso:country":"US",
    "sg:address":"2218 E Main St",
    "sg:city":"Gatesville",
    "sg:phone":"+1 254 865 5040",
    "sg:postcode":"76528",
    "sg:province":"TX",
    "sg:website":"http://www.cugino.com",
    "wof:name":"Andys Restaurant",
    "wof:placetype":"venue"
},
  "geometry": {"coordinates":[-97.724006,31.434721],"type":"Point"}
}