{
  "type": "Feature",
  "properties": {
    "iso:country":"US",
    "sg:address":"12119 E FM 917",
    "sg:city":"Alvarado",
    "sg:classifiers":[
        {
            "category":"Building & Trades",
            "subcategory":"Electrical",
            "type":"Services"
        }
    ],
    "sg:phone":"+1 682 518 8333",
    "sg:postcode":"76009",
    "sg:province":"TX",
    "sg:tags":[
        "electric",
        "contractor"
    ],
    "wof:name":"Kiker Electric",
    "wof:placetype":"venue"
},
  "geometry": {"coordinates":[-97.16370000000001,32.51443],"type":"Point"}
}