{
  "type": "Feature",
  "properties": {
    "iso:country":"US",
    "sg:address":"18121 Marsh Lane",
    "sg:city":"Dallas",
    "sg:classifiers":[
        {
            "category":"Health Services",
            "subcategory":"Optometrist",
            "type":"Services"
        }
    ],
    "sg:phone":"+1 972 862 2262",
    "sg:postcode":"75287",
    "sg:province":"TX",
    "sg:website":"www.merchanteyecare.com",
    "wof:name":"Mona Merchant O.D.",
    "wof:placetype":"venue"
},
  "geometry": {"coordinates":[-96.855619,32.995059],"type":"Point"}
}