{
  "type": "Feature",
  "properties": {
    "iso:country":"US",
    "sg:address":"107 S Kirkwell Cir",
    "sg:city":"Wichita Falls",
    "sg:classifiers":[
        {
            "category":"Retail",
            "subcategory":"Repair Shop",
            "type":"Services"
        }
    ],
    "sg:phone":"+1 940 337 4213",
    "sg:postcode":"76302",
    "sg:province":"TX",
    "sg:tags":[
        "equipment"
    ],
    "wof:name":"Falls Services",
    "wof:placetype":"venue"
},
  "geometry": {"coordinates":[-98.483097,33.85896],"type":"Point"}
}