{
  "type": "Feature",
  "properties": {
    "iso:country":"US",
    "sg:address":"1519 E 28th St",
    "sg:city":"Lubbock",
    "sg:classifiers":[
        {
            "category":"Professional",
            "type":"Services"
        }
    ],
    "sg:phone":"+1 806 747 1178",
    "sg:postcode":"79404",
    "sg:province":"TX",
    "sg:tags":[
        "establishment"
    ],
    "wof:name":"T Clark",
    "wof:placetype":"venue"
},
  "geometry": {"coordinates":[-101.81847500000001,33.568648],"type":"Point"}
}