{
  "type": "Feature",
  "properties": {
    "iso:country":"US",
    "sg:address":"11808 Asa Dr",
    "sg:city":"Mesquite",
    "sg:classifiers":[
        {
            "category":"Retail",
            "subcategory":"Animal Services",
            "type":"Services"
        }
    ],
    "sg:phone":"+1 972 557 5771",
    "sg:postcode":"75180",
    "sg:province":"TX",
    "wof:name":"American Kennel Club",
    "wof:placetype":"venue"
},
  "geometry": {"coordinates":[-96.622972,32.694792],"type":"Point"}
}