{
  "type": "Feature",
  "properties": {
    "iso:country":"US",
    "sg:address":"2801 Regal Rd",
    "sg:city":"Plano",
    "sg:classifiers":[
        {
            "category":"Professional",
            "subcategory":"Accounting & Tax Preparation",
            "type":"Services"
        }
    ],
    "sg:phone":"+1 972 596 1609",
    "sg:postcode":"75075",
    "sg:province":"TX",
    "sg:tags":[
        "accountant"
    ],
    "wof:name":"Tim Wright CPA",
    "wof:placetype":"venue"
},
  "geometry": {"coordinates":[-96.74779599999999,33.021656],"type":"Point"}
}