{
  "type": "Feature",
  "properties": {
    "iso:country":"US",
    "sg:address":"133 S Ector Dr",
    "sg:city":"Euless",
    "sg:classifiers":[
        {
            "category":"Food & Beverages",
            "subcategory":"Groceries & Convenience Stores",
            "type":"Retail Goods"
        }
    ],
    "sg:phone":"+1 817 354 8917",
    "sg:postcode":"76040",
    "sg:province":"TX",
    "wof:name":"Savanth Market",
    "wof:placetype":"venue"
},
  "geometry": {"coordinates":[-97.09057199999999,32.834545],"type":"Point"}
}