{
  "type": "Feature",
  "properties": {
    "iso:country":"US",
    "sg:address":"4404 52nd St",
    "sg:city":"Lubbock",
    "sg:classifiers":[
        {
            "category":"Professional",
            "type":"Services"
        }
    ],
    "sg:phone":"+1 806 792 8993",
    "sg:postcode":"79414",
    "sg:province":"TX",
    "sg:tags":[
        "establishment"
    ],
    "wof:name":"Calab Inc",
    "wof:placetype":"venue"
},
  "geometry": {"coordinates":[-101.90717100000001,33.546984],"type":"Point"}
}