{
  "type": "Feature",
  "properties": {
    "iso:country":"US",
    "sg:address":"5712 Robertson St",
    "sg:city":"Houston",
    "sg:classifiers":[
        {
            "category":"Manufacturing",
            "subcategory":"Metals",
            "type":"Manufacturing & Wholesale Goods"
        }
    ],
    "sg:phone":"+1 713 694 3170",
    "sg:postcode":"77009",
    "sg:province":"TX",
    "sg:tags":[
        "metalwork",
        "architectural",
        "mfg"
    ],
    "wof:name":"Wrought Iron By Rivera",
    "wof:placetype":"venue"
},
  "geometry": {"coordinates":[-95.357557,29.811822],"type":"Point"}
}