{
  "type": "Feature",
  "properties": {
    "iso:country":"US",
    "sg:address":"4309 Young St",
    "sg:city":"Pasadena",
    "sg:classifiers":[
        {
            "category":"Organizations",
            "subcategory":"Religious Organization",
            "type":"Services"
        }
    ],
    "sg:phone":"+1 281 998 8366",
    "sg:postcode":"77504",
    "sg:province":"TX",
    "wof:name":"Norwegian Seamans Church",
    "wof:placetype":"venue"
},
  "geometry": {"coordinates":[-95.194109,29.646699],"type":"Point"}
}