{
  "type": "Feature",
  "properties": {
    "iso:country":"US",
    "sg:address":"114 Clarksville St",
    "sg:city":"Paris",
    "sg:classifiers":[
        {
            "category":"Communications",
            "subcategory":"Radio Station",
            "type":"Services"
        }
    ],
    "sg:phone":"+1 903 739 9850",
    "sg:postcode":"75460",
    "sg:province":"TX",
    "sg:tags":[
        "company",
        "broadcasting"
    ],
    "wof:name":"KOOL Radio",
    "wof:placetype":"venue"
},
  "geometry": {"coordinates":[-95.555277,33.660613],"type":"Point"}
}