{
  "type": "Feature",
  "properties": {
    "iso:country":"US",
    "sg:address":"8013 N Macarthur Blvd",
    "sg:city":"Irving",
    "sg:classifiers":[
        {
            "category":"Travel",
            "subcategory":"Travel Agent",
            "type":"Entertainment"
        }
    ],
    "sg:phone":"+1 972 506 7559",
    "sg:postcode":"75063",
    "sg:province":"TX",
    "sg:tags":[
        "agency"
    ],
    "wof:name":"Twenty Four Seven Travel",
    "wof:placetype":"venue"
},
  "geometry": {"coordinates":[-96.957978,32.921937],"type":"Point"}
}