{
  "type": "Feature",
  "properties": {
    "iso:country":"US",
    "sg:address":"139 Champions Dr",
    "sg:city":"Rockdale",
    "sg:classifiers":[
        {
            "category":"Manufacturing",
            "subcategory":"Buildings",
            "type":"Manufacturing & Wholesale Goods"
        },
        {
            "category":"Building & Trades",
            "subcategory":"Construction",
            "type":"Services"
        }
    ],
    "sg:phone":"+1 512 446 0566",
    "sg:postcode":"76567",
    "sg:province":"TX",
    "sg:tags":[
        "home",
        "builder",
        "contractor"
    ],
    "wof:name":"Adcox Construction",
    "wof:placetype":"venue"
},
  "geometry": {"coordinates":[-97.030451,30.608369],"type":"Point"}
}