{
  "type": "Feature",
  "properties": {
    "iso:country":"US",
    "sg:address":"4810 Boyd Blvd",
    "sg:city":"Rowlett",
    "sg:classifiers":[
        {
            "category":"Manufacturing",
            "subcategory":"Glass & Minerals",
            "type":"Manufacturing & Wholesale Goods"
        }
    ],
    "sg:phone":"+1 972 475 1563",
    "sg:postcode":"75088",
    "sg:province":"TX",
    "sg:tags":[
        "ready"
    ],
    "wof:name":"Bodin Concrete Co Inc",
    "wof:placetype":"venue"
},
  "geometry": {"coordinates":[-96.57927599999999,32.903062],"type":"Point"}
}