{
  "type": "Feature",
  "properties": {
    "iso:country":"US",
    "sg:address":"605 6th St",
    "sg:city":"Kemah",
    "sg:classifiers":[
        {
            "category":"Professional",
            "subcategory":"Research",
            "type":"Services"
        }
    ],
    "sg:phone":"+1 281 535 7077",
    "sg:postcode":"77565",
    "sg:province":"TX",
    "sg:tags":[
        "nonphysical",
        "commercial"
    ],
    "wof:name":"Cyrospace Inc",
    "wof:placetype":"venue"
},
  "geometry": {"coordinates":[-95.01737799999999,29.543868],"type":"Point"}
}