{
  "type": "Feature",
  "properties": {
    "iso:country":"US",
    "sg:address":"17269 US Hwy 69",
    "sg:city":"Tyler",
    "sg:classifiers":[
        {
            "category":"Organizations",
            "subcategory":"Religious Organization",
            "type":"Services"
        }
    ],
    "sg:phone":"+1 903 839 7806",
    "sg:postcode":"75703",
    "sg:province":"TX",
    "wof:name":"Grace Chapel Assembly Of God",
    "wof:placetype":"venue"
},
  "geometry": {"coordinates":[-95.310714,32.234319],"type":"Point"}
}