{
  "type": "Feature",
  "properties": {
    "iso:country":"US",
    "sg:address":"7512 Main St",
    "sg:city":"The Colony",
    "sg:classifiers":[
        {
            "category":"Professional",
            "type":"Services"
        }
    ],
    "sg:phone":"+1 972 370 2300",
    "sg:postcode":"75056",
    "sg:province":"TX",
    "sg:tags":[
        "establishment"
    ],
    "wof:name":"John Andrews & Assoc",
    "wof:placetype":"venue"
},
  "geometry": {"coordinates":[-96.891544,33.105057],"type":"Point"}
}