{
  "type": "Feature",
  "properties": {
    "iso:country":"US",
    "sg:address":"15469 State Hwy 135",
    "sg:city":"Overton",
    "sg:classifiers":[
        {
            "category":"Retail",
            "subcategory":"Repair Shop",
            "type":"Services"
        }
    ],
    "sg:phone":"+1 903 834 3239",
    "sg:postcode":"75684",
    "sg:province":"TX",
    "sg:tags":[
        "contractor"
    ],
    "wof:name":"Tyiska Septic Services",
    "wof:placetype":"venue"
},
  "geometry": {"coordinates":[-95.015833,32.250487],"type":"Point"}
}