{
  "type": "Feature",
  "properties": {
    "iso:country":"US",
    "sg:address":"4220 W State Highway 31",
    "sg:city":"Corsicana",
    "sg:classifiers":[
        {
            "category":"Retail",
            "subcategory":"Storage",
            "type":"Services"
        }
    ],
    "sg:phone":"+1 903 872 9333",
    "sg:postcode":"75110",
    "sg:province":"TX",
    "sg:tags":[
        "household",
        "commercial"
    ],
    "wof:name":"Corsicana West 31 Mini Whse",
    "wof:placetype":"venue"
},
  "geometry": {"coordinates":[-96.514561,32.06403],"type":"Point"}
}