{
  "type": "Feature",
  "properties": {
    "iso:country":"US",
    "sg:address":"2325 NW Military Hwy",
    "sg:city":"San Antonio",
    "sg:classifiers":[
        {
            "category":"Personal",
            "subcategory":"Beauty Salon",
            "type":"Services"
        }
    ],
    "sg:phone":"+1 210 541 9644",
    "sg:postcode":"78231",
    "sg:province":"TX",
    "wof:name":"Supercuts",
    "wof:placetype":"venue"
},
  "geometry": {"coordinates":[-98.529139,29.544389],"type":"Point"}
}