{
  "type": "Feature",
  "properties": {
    "iso:country":"US",
    "sg:address":"930 E Adams St",
    "sg:city":"Brownsville",
    "sg:classifiers":[
        {
            "category":"Banks & Credit Unions",
            "subcategory":"Bank",
            "type":"Services"
        }
    ],
    "sg:phone":"+1 956 542 5152",
    "sg:postcode":"78520",
    "sg:province":"TX",
    "sg:tags":[
        "financing",
        "loan"
    ],
    "wof:name":"Economy Finance Co",
    "wof:placetype":"venue"
},
  "geometry": {"coordinates":[-97.498684,25.904099],"type":"Point"}
}