{
  "type": "Feature",
  "properties": {
    "iso:country":"US",
    "sg:address":"2512 Boardwalk Dr",
    "sg:city":"Mesquite",
    "sg:classifiers":[
        {
            "category":"Shopping",
            "subcategory":"Hobbies, Toys, & Games",
            "type":"Retail Goods"
        }
    ],
    "sg:phone":"+1 972 222 1215",
    "sg:postcode":"75181",
    "sg:province":"TX",
    "sg:tags":[
        "miscellaneous",
        "store"
    ],
    "wof:name":"Madelons Antq & Collectibles",
    "wof:placetype":"venue"
},
  "geometry": {"coordinates":[-96.553715,32.733296],"type":"Point"}
}