{
  "type": "Feature",
  "properties": {
    "iso:country":"US",
    "sg:address":"1133 N Zang Blvd",
    "sg:city":"Dallas",
    "sg:classifiers":[
        {
            "category":"Personal",
            "subcategory":"Beauty Salon",
            "type":"Services"
        }
    ],
    "sg:phone":"+1 214 943 4963",
    "sg:postcode":"75203",
    "sg:province":"TX",
    "sg:tags":[
        "shop"
    ],
    "wof:name":"Abigail's Beauty Salon",
    "wof:placetype":"venue"
},
  "geometry": {"coordinates":[-96.821772,32.757469],"type":"Point"}
}