{
  "type": "Feature",
  "properties": {
    "iso:country":"US",
    "sg:address":"708 S Gray Ave",
    "sg:city":"West Columbia",
    "sg:classifiers":[
        {
            "category":"Professional",
            "subcategory":"Management & Consulting",
            "type":"Services"
        }
    ],
    "sg:phone":"+1 979 345 3329",
    "sg:postcode":"77486",
    "sg:province":"TX",
    "sg:tags":[
        "business"
    ],
    "wof:name":"Lone Star Learning Resources",
    "wof:placetype":"venue"
},
  "geometry": {"coordinates":[-95.64583500000001,29.135157],"type":"Point"}
}