{
  "type": "Feature",
  "properties": {
    "iso:country":"US",
    "sg:address":"1606 Canadian Cir",
    "sg:city":"Grand Prairie",
    "sg:classifiers":[
        {
            "category":"Wholesale",
            "subcategory":"Toys & Hobbies",
            "type":"Manufacturing & Wholesale Goods"
        }
    ],
    "sg:phone":"+1 972 313 1753",
    "sg:postcode":"75050",
    "sg:province":"TX",
    "sg:tags":[
        "balloon"
    ],
    "sg:website":"www.lonestarballoon.com",
    "wof:name":"Lone Star Balloon",
    "wof:placetype":"venue"
},
  "geometry": {"coordinates":[-97.026584,32.762205],"type":"Point"}
}