{
  "type": "Feature",
  "properties": {
    "iso:country":"US",
    "sg:address":"405 Grace St",
    "sg:city":"San Angelo",
    "sg:classifiers":[
        {
            "category":"Real Estate",
            "subcategory":"Real Estate Operator",
            "type":"Services"
        }
    ],
    "sg:phone":"+1 325 655 7950",
    "sg:postcode":"76901",
    "sg:province":"TX",
    "sg:tags":[
        "sub",
        "lessor"
    ],
    "wof:name":"Price Home Solutions",
    "wof:placetype":"venue"
},
  "geometry": {"coordinates":[-100.45769799999999,31.450146],"type":"Point"}
}