{
  "type": "Feature",
  "properties": {
    "iso:country":"US",
    "sg:address":"1214 Alpine St",
    "sg:city":"Odessa",
    "sg:classifiers":[
        {
            "category":"Building & Trades",
            "subcategory":"Pest Control",
            "type":"Services"
        }
    ],
    "sg:phone":"+1 432 362 8018",
    "sg:postcode":"79762",
    "sg:province":"TX",
    "wof:name":"Lee Winters Exterminating",
    "wof:placetype":"venue"
},
  "geometry": {"coordinates":[-102.371606,31.886998],"type":"Point"}
}