{
  "type": "Feature",
  "properties": {
    "iso:country":"US",
    "sg:address":"17914 Asphodel Ln",
    "sg:city":"Spring",
    "sg:classifiers":[
        {
            "category":"Banks & Credit Unions",
            "subcategory":"Investment Brokerage",
            "type":"Services"
        }
    ],
    "sg:phone":"+1 281 370 1193",
    "sg:postcode":"77379",
    "sg:province":"TX",
    "sg:tags":[
        "security"
    ],
    "wof:name":"North American Beryllium",
    "wof:placetype":"venue"
},
  "geometry": {"coordinates":[-95.496191,30.026898],"type":"Point"}
}