{
  "type": "Feature",
  "properties": {
    "iso:country":"US",
    "sg:address":"5949 Sherry Ln",
    "sg:city":"Dallas",
    "sg:classifiers":[
        {
            "category":"Professional",
            "subcategory":"Advertising",
            "type":"Services"
        }
    ],
    "sg:phone":"+1 214 378 7970",
    "sg:postcode":"75225",
    "sg:province":"TX",
    "sg:tags":[
        "counselor"
    ],
    "sg:website":"www.thepointgroup.net",
    "wof:name":"Point Group Inc",
    "wof:placetype":"venue"
},
  "geometry": {"coordinates":[-96.810025,32.862362],"type":"Point"}
}