{
  "type": "Feature",
  "properties": {
    "iso:country":"US",
    "sg:address":"8625 Mesa Dr",
    "sg:city":"Houston",
    "sg:classifiers":[
        {
            "category":"Personal",
            "subcategory":"Beauty Salon",
            "type":"Services"
        }
    ],
    "sg:phone":"+1 713 631 4814",
    "sg:postcode":"77028",
    "sg:province":"TX",
    "sg:tags":[
        "shop"
    ],
    "wof:name":"Sanchez Beauty Salon",
    "wof:placetype":"venue"
},
  "geometry": {"coordinates":[-95.262325,29.840383],"type":"Point"}
}