{
  "type": "Feature",
  "properties": {
    "iso:country":"US",
    "sg:address":"1920 Westview Blvd",
    "sg:city":"Conroe",
    "sg:phone":"+1 800 508 4761",
    "sg:postcode":"77304",
    "sg:province":"TX",
    "sg:website":"http://www-sunbeltrentals-com.netsolads.com/?utm_source=yp.com&utm_medium=tilead&utm_term=localsearch&utm_campaign=&_nsag=39093",
    "wof:name":"Sunbelt Rentals At Lowe's",
    "wof:placetype":"venue"
},
  "geometry": {"coordinates":[-95.48159,30.326758],"type":"Point"}
}