{
  "type": "Feature",
  "properties": {
    "iso:country":"US",
    "sg:address":"850 S Lynchburg Rd",
    "sg:city":"Baytown",
    "sg:classifiers":[
        {
            "category":"Professional",
            "subcategory":"Business Services",
            "type":"Services"
        }
    ],
    "sg:phone":"+1 281 424 1740",
    "sg:postcode":"77520",
    "sg:province":"TX",
    "wof:name":"H M S Environmental Tech",
    "wof:placetype":"venue"
},
  "geometry": {"coordinates":[-95.068814,29.768902],"type":"Point"}
}