{
  "type": "Feature",
  "properties": {
    "iso:country":"US",
    "sg:address":"101 E North St",
    "sg:city":"Arlington",
    "sg:classifiers":[
        {
            "category":"Social Services",
            "type":"Services"
        }
    ],
    "sg:phone":"+1 817 275 0172",
    "sg:postcode":"76011",
    "sg:province":"TX",
    "sg:tags":[
        "hospital",
        "specialty"
    ],
    "wof:name":"Estes Josie MA Ms",
    "wof:placetype":"venue"
},
  "geometry": {"coordinates":[-97.10562400000001,32.740322],"type":"Point"}
}