{
  "type": "Feature",
  "properties": {
    "iso:country":"US",
    "sg:address":"2900 Raul Longoria Rd",
    "sg:city":"San Juan",
    "sg:classifiers":[
        {
            "category":"Health Services",
            "subcategory":"Doctor",
            "type":"Services"
        }
    ],
    "sg:phone":"+1 956 781 6077",
    "sg:postcode":"78589",
    "sg:province":"TX",
    "sg:tags":[
        "clinic"
    ],
    "wof:name":"Nuestra Clinica Del Valle",
    "wof:placetype":"venue"
},
  "geometry": {"coordinates":[-98.14945,26.224971],"type":"Point"}
}