{
  "type": "Feature",
  "properties": {
    "iso:country":"US",
    "sg:address":"7401 N Minnesota Rd",
    "sg:city":"Palmview",
    "sg:classifiers":[
        {
            "category":"Restaurant",
            "type":"Food & Drink"
        }
    ],
    "sg:phone":"+1 956 519 7377",
    "sg:postcode":"78574",
    "sg:province":"TX",
    "sg:tags":[
        "mexican"
    ],
    "wof:name":"Virginia Garcia",
    "wof:placetype":"venue"
},
  "geometry": {"coordinates":[-98.365723,26.309771],"type":"Point"}
}