{
  "type": "Feature",
  "properties": {
    "iso:country":"US",
    "sg:address":"2800 Routh St",
    "sg:city":"Dallas",
    "sg:classifiers":[
        {
            "category":"Shopping",
            "subcategory":"Jewelry",
            "type":"Retail Goods"
        }
    ],
    "sg:phone":"+1 214 855 1405",
    "sg:postcode":"75201",
    "sg:province":"TX",
    "sg:tags":[
        "glass",
        "handmade",
        "sculpture",
        "hand"
    ],
    "wof:name":"Invision",
    "wof:placetype":"venue"
},
  "geometry": {"coordinates":[-96.804575,32.798823],"type":"Point"}
}