{
  "type": "Feature",
  "properties": {
    "iso:country":"US",
    "sg:address":"1100 San Jacinto Blvd",
    "sg:city":"Austin",
    "sg:classifiers":[
        {
            "category":"Government",
            "subcategory":"Police Station",
            "type":"Public Place"
        }
    ],
    "sg:phone":"+1 512 463 1919",
    "sg:postcode":"78701",
    "sg:province":"TX",
    "sg:tags":[
        "state"
    ],
    "wof:name":"Criminal Justice Div",
    "wof:placetype":"venue"
},
  "geometry": {"coordinates":[-97.738232,30.273207],"type":"Point"}
}