{
  "type": "Feature",
  "properties": {
    "iso:country":"US",
    "sg:address":"309 W 7th St",
    "sg:city":"Fort Worth",
    "sg:classifiers":[
        {
            "category":"Travel",
            "subcategory":"Travel Agent",
            "type":"Entertainment"
        }
    ],
    "sg:phone":"+1 817 348 8588",
    "sg:postcode":"76102",
    "sg:province":"TX",
    "sg:tags":[
        "agency",
        "bureau"
    ],
    "wof:name":"Executive Class Travel",
    "wof:placetype":"venue"
},
  "geometry": {"coordinates":[-97.332177,32.751492],"type":"Point"}
}