{
  "type": "Feature",
  "properties": {
    "iso:country":"US",
    "sg:address":"4403 Nottingham Ln",
    "sg:city":"Bryan",
    "sg:classifiers":[
        {
            "category":"Building & Trades",
            "subcategory":"Construction",
            "type":"Services"
        }
    ],
    "sg:phone":"+1 979 774 0627",
    "sg:postcode":"77802",
    "sg:province":"TX",
    "sg:tags":[
        "home",
        "builder"
    ],
    "wof:name":"Ranier Homes",
    "wof:placetype":"venue"
},
  "geometry": {"coordinates":[-96.298844,30.671723],"type":"Point"}
}