{
  "type": "Feature",
  "properties": {
    "iso:country":"US",
    "sg:address":"5604 Oak Branch Dr",
    "sg:city":"Arlington",
    "sg:classifiers":[
        {
            "category":"Building & Trades",
            "subcategory":"Landscaping Services",
            "type":"Services"
        }
    ],
    "sg:phone":"+1 817 263 0880",
    "sg:postcode":"76016",
    "sg:province":"TX",
    "sg:tags":[
        "designer",
        "landscape"
    ],
    "wof:name":"Bushville Gardens",
    "wof:placetype":"venue"
},
  "geometry": {"coordinates":[-97.19157300000001,32.678355],"type":"Point"}
}