{
  "type": "Feature",
  "properties": {
    "iso:country":"US",
    "sg:address":"64 N Reynolds St",
    "sg:city":"Alice",
    "sg:classifiers":[
        {
            "category":"Insurance",
            "subcategory":"Insurance Agent",
            "type":"Services"
        }
    ],
    "sg:phone":"+1 361 668 4670",
    "sg:postcode":"78332",
    "sg:province":"TX",
    "wof:name":"Insurance Outlet",
    "wof:placetype":"venue"
},
  "geometry": {"coordinates":[-98.073246,27.750498],"type":"Point"}
}