{
  "type": "Feature",
  "properties": {
    "iso:country":"US",
    "sg:address":"506 Evonne St",
    "sg:city":"Houston",
    "sg:classifiers":[
        {
            "category":"Professional",
            "type":"Services"
        }
    ],
    "sg:phone":"+1 713 644 4883",
    "sg:postcode":"77017",
    "sg:province":"TX",
    "wof:name":"Golden Key Environmental",
    "wof:placetype":"venue"
},
  "geometry": {"coordinates":[-95.238911,29.69337],"type":"Point"}
}