{
  "type": "Feature",
  "properties": {
    "iso:country":"US",
    "sg:address":"14366 Memorial Dr",
    "sg:city":"Houston",
    "sg:classifiers":[
        {
            "category":"Shopping",
            "subcategory":"Discount & Variety Stores",
            "type":"Retail Goods"
        }
    ],
    "sg:phone":"+1 281 596 0588",
    "sg:postcode":"77079",
    "sg:province":"TX",
    "sg:tags":[
        "merchandise",
        "general"
    ],
    "wof:name":"Dollars Plus",
    "wof:placetype":"venue"
},
  "geometry": {"coordinates":[-95.59938,29.770278],"type":"Point"}
}