{
  "type": "Feature",
  "properties": {
    "iso:country":"US",
    "sg:address":"5320 Garfield Ave",
    "sg:city":"Groves",
    "sg:classifiers":[
        {
            "category":"Wholesale",
            "subcategory":"Non-durable Goods",
            "type":"Manufacturing & Wholesale Goods"
        }
    ],
    "sg:phone":"+1 409 962 5602",
    "sg:postcode":"77619",
    "sg:province":"TX",
    "wof:name":"Dos Imports",
    "wof:placetype":"venue"
},
  "geometry": {"coordinates":[-93.927273,29.956611],"type":"Point"}
}