{
  "type": "Feature",
  "properties": {
    "iso:country":"US",
    "sg:address":"9718 Astronaut Dr",
    "sg:city":"San Antonio",
    "sg:classifiers":[
        {
            "category":"Shopping",
            "subcategory":"Hobbies, Toys, & Games",
            "type":"Retail Goods"
        }
    ],
    "sg:phone":"+1 210 653 4708",
    "sg:postcode":"78217",
    "sg:province":"TX",
    "wof:name":"Woodcarving Cajun",
    "wof:placetype":"venue"
},
  "geometry": {"coordinates":[-98.43830800000001,29.529531],"type":"Point"}
}