{
  "type": "Feature",
  "properties": {
    "iso:country":"US",
    "sg:address":"665 W Lbj Freeway Ste 116",
    "sg:city":"Irving",
    "sg:classifiers":[
        {
            "category":"Personal",
            "subcategory":"Beauty Salon",
            "type":"Services"
        }
    ],
    "sg:phone":"+1 214 991 5501",
    "sg:postcode":"75063",
    "sg:province":"TX",
    "sg:tags":[
        "hair"
    ],
    "sg:website":"www.KarlasSalon.net",
    "wof:name":"Karla's Salon",
    "wof:placetype":"venue"
},
  "geometry": {"coordinates":[-96.954598,32.915386],"type":"Point"}
}