{
  "type": "Feature",
  "properties": {
    "iso:country":"US",
    "sg:address":"1111 Augusta Dr",
    "sg:city":"Houston",
    "sg:classifiers":[
        {
            "category":"Health Services",
            "subcategory":"Doctor",
            "type":"Services"
        }
    ],
    "sg:phone":"+1 713 442 2400",
    "sg:postcode":"77057",
    "sg:province":"TX",
    "sg:tags":[
        "medical"
    ],
    "wof:name":"West K S II Ob Gyn",
    "wof:placetype":"venue"
},
  "geometry": {"coordinates":[-95.48260999999999,29.753889],"type":"Point"}
}