{
  "type": "Feature",
  "properties": {
    "iso:country":"US",
    "sg:address":"1201 N Apache St",
    "sg:city":"Amarillo",
    "sg:classifiers":[
        {
            "category":"Organizations",
            "subcategory":"Religious Organization",
            "type":"Services"
        }
    ],
    "sg:phone":"+1 806 383 6767",
    "sg:postcode":"79107",
    "sg:province":"TX",
    "sg:tags":[
        "church"
    ],
    "wof:name":"Parkview Christian Church",
    "wof:placetype":"venue"
},
  "geometry": {"coordinates":[-101.79648,35.227622],"type":"Point"}
}