{
  "type": "Feature",
  "properties": {
    "iso:country":"US",
    "sg:address":"2233 Ackerman Rd",
    "sg:city":"San Antonio",
    "sg:classifiers":[
        {
            "category":"Building & Trades",
            "subcategory":"Construction",
            "type":"Services"
        }
    ],
    "sg:phone":"+1 210 666 4989",
    "sg:postcode":"78219",
    "sg:province":"TX",
    "sg:tags":[
        "concrete",
        "contractor"
    ],
    "wof:name":"Southwest Concrete Products",
    "wof:placetype":"venue"
},
  "geometry": {"coordinates":[-98.381265,29.442441],"type":"Point"}
}