{
  "type": "Feature",
  "properties": {
    "iso:country":"US",
    "sg:address":"1403 W Mount Houston Rd",
    "sg:city":"Houston",
    "sg:classifiers":[
        {
            "category":"Wholesale",
            "subcategory":"Machinery & Supplies",
            "type":"Manufacturing & Wholesale Goods"
        }
    ],
    "sg:phone":"+1 281 847 1830",
    "sg:postcode":"77038",
    "sg:province":"TX",
    "sg:tags":[
        "equipment",
        "establishment"
    ],
    "wof:name":"K Y Fashions",
    "wof:placetype":"venue"
},
  "geometry": {"coordinates":[-95.42935,29.897951],"type":"Point"}
}