{
  "type": "Feature",
  "properties": {
    "iso:country":"US",
    "sg:address":"3113 Gulf Ave",
    "sg:city":"Midland",
    "sg:classifiers":[
        {
            "category":"Professional",
            "subcategory":"Business Services",
            "type":"Services"
        }
    ],
    "sg:phone":"+1 432 520 4080",
    "sg:postcode":"79705",
    "sg:province":"TX",
    "sg:tags":[
        "interior",
        "consultant",
        "design",
        "decorator"
    ],
    "wof:name":"Edwards & Assoc",
    "wof:placetype":"venue"
},
  "geometry": {"coordinates":[-102.12000399999999,32.010163],"type":"Point"}
}