{
  "type": "Feature",
  "properties": {
    "iso:country":"US",
    "sg:address":"9780 Bissonnet St",
    "sg:city":"Houston",
    "sg:classifiers":[
        {
            "category":"Social Services",
            "type":"Services"
        }
    ],
    "sg:phone":"+1 713 981 0707",
    "sg:postcode":"77036",
    "sg:province":"TX",
    "wof:name":"Ultimate Adult Day Care",
    "wof:placetype":"venue"
},
  "geometry": {"coordinates":[-95.55006899999999,29.67543],"type":"Point"}
}