{
  "type": "Feature",
  "properties": {
    "iso:country":"US",
    "sg:address":"128 Bermuda Ln",
    "sg:city":"Palestine",
    "sg:classifiers":[
        {
            "category":"Professional",
            "subcategory":"Business Services",
            "type":"Services"
        }
    ],
    "sg:phone":"+1 903 723 5040",
    "sg:postcode":"75803",
    "sg:province":"TX",
    "wof:name":"J & J Enterprises",
    "wof:placetype":"venue"
},
  "geometry": {"coordinates":[-95.68677099999999,31.732869],"type":"Point"}
}