{
  "type": "Feature",
  "properties": {
    "iso:country":"US",
    "sg:address":"205 S Polk St",
    "sg:city":"Amarillo",
    "sg:classifiers":[
        {
            "category":"Place Of Worship",
            "subcategory":"Church",
            "type":"Public Place"
        },
        {
            "category":"Place Of Worship",
            "type":"Public Place"
        },
        {
            "category":"Organizations",
            "subcategory":"Religious Organization",
            "type":"Services"
        }
    ],
    "sg:phone":"+1 806 371 0089",
    "sg:postcode":"79101",
    "sg:province":"TX",
    "sg:tags":[
        "churches-non-denominational"
    ],
    "wof:name":"City Church Outreach Ministry",
    "wof:placetype":"venue"
},
  "geometry": {"coordinates":[-101.83622,35.211747],"type":"Point"}
}