{
  "type": "Feature",
  "properties": {
    "iso:country":"US",
    "sg:address":"1709 Forest Ridge Dr",
    "sg:city":"Bedford",
    "sg:classifiers":[
        {
            "category":"Personal",
            "subcategory":"Beauty Salon",
            "type":"Services"
        }
    ],
    "sg:phone":"+1 817 416 2075",
    "sg:postcode":"76022",
    "sg:province":"TX",
    "wof:name":"Mouton's",
    "wof:placetype":"venue"
},
  "geometry": {"coordinates":[-97.142073,32.834434],"type":"Point"}
}