{
  "type": "Feature",
  "properties": {
    "iso:country":"US",
    "sg:address":"711 W 38th St",
    "sg:city":"Austin",
    "sg:classifiers":[
        {
            "category":"Health Services",
            "subcategory":"Doctor",
            "type":"Services"
        }
    ],
    "sg:phone":"+1 512 454 3500",
    "sg:postcode":"78705",
    "sg:province":"TX",
    "wof:name":"Samaan Michael MD",
    "wof:placetype":"venue"
},
  "geometry": {"coordinates":[-97.739968,30.303593],"type":"Point"}
}