{
  "type": "Feature",
  "properties": {
    "iso:country":"US",
    "sg:address":"1244 Santa Barbara St",
    "sg:city":"San Antonio",
    "sg:classifiers":[
        {
            "category":"Autos & Motor Vehicles",
            "subcategory":"Automobile Sales",
            "type":"Retail Goods"
        }
    ],
    "sg:phone":"+1 210 734 3333",
    "sg:postcode":"78201",
    "sg:province":"TX",
    "sg:tags":[
        "car",
        "dealer"
    ],
    "wof:name":"Magic Time Motors",
    "wof:placetype":"venue"
},
  "geometry": {"coordinates":[-98.514878,29.470269],"type":"Point"}
}