{
  "type": "Feature",
  "properties": {
    "iso:country":"US",
    "sg:address":"2603 San Alejandro St",
    "sg:city":"Edinburg",
    "sg:classifiers":[
        {
            "category":"Shopping",
            "type":"Retail Goods"
        }
    ],
    "sg:phone":"+1 956 316 4071",
    "sg:postcode":"78539",
    "sg:province":"TX",
    "sg:tags":[
        "merchandise"
    ],
    "wof:name":"Rubber Process Company",
    "wof:placetype":"venue"
},
  "geometry": {"coordinates":[-98.19350300000001,26.288513],"type":"Point"}
}