{
  "type": "Feature",
  "properties": {
    "iso:country":"US",
    "sg:address":"3703 Broadway",
    "sg:city":"San Antonio",
    "sg:classifiers":[
        {
            "category":"Shopping",
            "subcategory":"Music",
            "type":"Retail Goods"
        }
    ],
    "sg:phone":"+1 210 828 5525",
    "sg:postcode":"78209",
    "sg:province":"TX",
    "sg:tags":[
        "compact",
        "record",
        "disc",
        "tape"
    ],
    "wof:name":"CD Exchange",
    "wof:placetype":"venue"
},
  "geometry": {"coordinates":[-98.466936,29.461032],"type":"Point"}
}