{
  "type": "Feature",
  "properties": {
    "iso:country":"US",
    "sg:address":"1601 Air Base Rd",
    "sg:city":"Waco",
    "sg:classifiers":[
        {
            "category":"Organizations",
            "subcategory":"Religious Organization",
            "type":"Services"
        }
    ],
    "sg:phone":"+1 254 799 5640",
    "sg:postcode":"76705",
    "sg:province":"TX",
    "sg:tags":[
        "church"
    ],
    "wof:name":"New Generation Church Inc",
    "wof:placetype":"venue"
},
  "geometry": {"coordinates":[-97.09355499999999,31.620219],"type":"Point"}
}