{
  "type": "Feature",
  "properties": {
    "iso:country":"US",
    "sg:address":"1402 Cates St",
    "sg:city":"Bridgeport",
    "sg:classifiers":[
        {
            "category":"Health Services",
            "subcategory":"Doctor",
            "type":"Services"
        }
    ],
    "sg:phone":"+1 940 683 1062",
    "sg:postcode":"76426",
    "sg:province":"TX",
    "sg:tags":[
        "medicine",
        "injury",
        "sport"
    ],
    "wof:name":"North Texas Sports Medicine",
    "wof:placetype":"venue"
},
  "geometry": {"coordinates":[-97.753557,33.209247],"type":"Point"}
}