{
  "type": "Feature",
  "properties": {
    "iso:country":"US",
    "sg:address":"216 Ten Oaks Dr",
    "sg:city":"Georgetown",
    "sg:classifiers":[
        {
            "category":"Professional",
            "subcategory":"Business Services",
            "type":"Services"
        }
    ],
    "sg:phone":"+1 512 868 8830",
    "sg:postcode":"78628",
    "sg:province":"TX",
    "wof:name":"Supplier Solutions LLC",
    "wof:placetype":"venue"
},
  "geometry": {"coordinates":[-97.70059500000001,30.739115],"type":"Point"}
}