{
  "type": "Feature",
  "properties": {
    "iso:country":"US",
    "sg:address":"2525 Ridgmar Blvd",
    "sg:city":"Fort Worth",
    "sg:classifiers":[
        {
            "category":"Banks & Credit Unions",
            "subcategory":"Financial Services",
            "type":"Services"
        }
    ],
    "sg:phone":"+1 866 809 4553",
    "sg:postcode":"76116",
    "sg:province":"TX",
    "sg:tags":[
        "royalty",
        "trust"
    ],
    "wof:name":"San Juan Basin Royalty Trust",
    "wof:placetype":"venue"
},
  "geometry": {"coordinates":[-97.424134,32.735544],"type":"Point"}
}