{
  "type": "Feature",
  "properties": {
    "iso:country":"US",
    "sg:address":"3613 Parry Ave # A",
    "sg:city":"Dallas",
    "sg:classifiers":[
        {
            "category":"Personal",
            "subcategory":"Barber",
            "type":"Services"
        }
    ],
    "sg:phone":"+1 214 824 7627",
    "sg:postcode":"75226",
    "sg:province":"TX",
    "wof:name":"Rob's Chop Shop",
    "wof:placetype":"venue"
},
  "geometry": {"coordinates":[-96.76660200000001,32.7817],"type":"Point"}
}