{
  "type": "Feature",
  "properties": {
    "iso:country":"US",
    "sg:address":"7318 Blanco Pines Dr",
    "sg:city":"Humble",
    "sg:classifiers":[
        {
            "category":"Professional",
            "subcategory":"Business Services",
            "type":"Services"
        }
    ],
    "sg:phone":"+1 281 812 1210",
    "sg:postcode":"77346",
    "sg:province":"TX",
    "wof:name":"Visions Interior Decorating",
    "wof:placetype":"venue"
},
  "geometry": {"coordinates":[-95.1651,29.987709],"type":"Point"}
}