{
  "type": "Feature",
  "properties": {
    "iso:country":"US",
    "sg:address":"5317 Blue Mound Rd",
    "sg:city":"Fort Worth",
    "sg:classifiers":[
        {
            "category":"Travel",
            "subcategory":"Hotels & Motels",
            "type":"Entertainment"
        }
    ],
    "sg:phone":"+1 817 625 6211",
    "sg:postcode":"76106",
    "sg:province":"TX",
    "sg:tags":[
        "operation"
    ],
    "wof:name":"Great Western Inn Saginaw",
    "wof:placetype":"venue"
},
  "geometry": {"coordinates":[-97.34274600000001,32.82492],"type":"Point"}
}