{
  "type": "Feature",
  "properties": {
    "iso:country":"US",
    "sg:address":"501 James St",
    "sg:city":"Houston",
    "sg:classifiers":[
        {
            "category":"Recreation",
            "type":"Entertainment"
        }
    ],
    "sg:phone":"+1 281 255 3787",
    "sg:postcode":"77009",
    "sg:province":"TX",
    "wof:name":"Tomball Community Center",
    "wof:placetype":"venue"
},
  "geometry": {"coordinates":[-95.36217499999999,29.777268],"type":"Point"}
}