{
  "type": "Feature",
  "properties": {
    "iso:country":"US",
    "sg:address":"5702 Garden Hills Dr",
    "sg:city":"Sugar Land",
    "sg:classifiers":[
        {
            "category":"Shopping",
            "subcategory":"Discount & Variety Stores",
            "type":"Retail Goods"
        },
        {
            "category":"Wholesale",
            "subcategory":"Computers",
            "type":"Manufacturing & Wholesale Goods"
        }
    ],
    "sg:phone":"+1 281 313 2440",
    "sg:postcode":"77479",
    "sg:province":"TX",
    "sg:tags":[
        "merchandise",
        "general"
    ],
    "wof:name":"Heavenly Treasures & Accents",
    "wof:placetype":"venue"
},
  "geometry": {"coordinates":[-95.630653,29.562512],"type":"Point"}
}