{
  "type": "Feature",
  "properties": {
    "iso:country":"US",
    "sg:address":"308 E Taylor St",
    "sg:city":"Gilmer",
    "sg:classifiers":[
        {
            "category":"Freight",
            "type":"Transportation"
        }
    ],
    "sg:phone":"+1 903 843 5065",
    "sg:postcode":"75644",
    "sg:province":"TX",
    "sg:tags":[
        "hauling",
        "trucking"
    ],
    "sg:website":"www.customcommodities.com",
    "wof:name":"Custom Commodities",
    "wof:placetype":"venue"
},
  "geometry": {"coordinates":[-94.942564,32.731845],"type":"Point"}
}