{
  "type": "Feature",
  "properties": {
    "iso:country":"US",
    "sg:address":"15333 John F Kennedy Blvd Ste 120",
    "sg:city":"Houston",
    "sg:classifiers":[
        {
            "category":"Deli",
            "type":"Food & Drink"
        }
    ],
    "sg:phone":"+1 281 227 9833",
    "sg:postcode":"77032",
    "sg:province":"TX",
    "wof:name":"Rose's Deli & Catering No 3",
    "wof:placetype":"venue"
},
  "geometry": {"coordinates":[-95.331703,29.9408],"type":"Point"}
}