{
  "type": "Feature",
  "properties": {
    "iso:country":"US",
    "sg:address":"5817 S Interregional Hwy",
    "sg:city":"Austin",
    "sg:classifiers":[
        {
            "category":"Retail",
            "subcategory":"Auto Repair",
            "type":"Services"
        }
    ],
    "sg:phone":"+1 512 467 1967",
    "sg:postcode":"78744",
    "sg:province":"TX",
    "sg:tags":[
        "brake"
    ],
    "wof:name":"Brake Check",
    "wof:placetype":"venue"
},
  "geometry": {"coordinates":[-97.764475,30.197215],"type":"Point"}
}