{
  "type": "Feature",
  "properties": {
    "iso:country":"US",
    "sg:address":"24 Grants Lake",
    "sg:city":"San Antonio",
    "sg:classifiers":[
        {
            "category":"Insurance",
            "subcategory":"Insurance Agent",
            "type":"Services"
        }
    ],
    "sg:phone":"+1 210 545 3343",
    "sg:postcode":"78248",
    "sg:province":"TX",
    "wof:name":"Sentry Select Insurance Co",
    "wof:placetype":"venue"
},
  "geometry": {"coordinates":[-98.537284,29.595222],"type":"Point"}
}