{
  "type": "Feature",
  "properties": {
    "iso:country":"US",
    "sg:address":"8725 Highview Dr",
    "sg:city":"Seagoville",
    "sg:classifiers":[
        {
            "category":"Shopping",
            "subcategory":"Computers & Home Electronics",
            "type":"Retail Goods"
        }
    ],
    "sg:phone":"+1 972 427 3997",
    "sg:postcode":"75114",
    "sg:province":"TX",
    "sg:tags":[
        "equipment",
        "dealer"
    ],
    "wof:name":"Elite Computer Systems",
    "wof:placetype":"venue"
},
  "geometry": {"coordinates":[-96.39085,32.648216],"type":"Point"}
}