{
  "type": "Feature",
  "properties": {
    "iso:country":"US",
    "sg:address":"10162 Beekman Place Dr",
    "sg:city":"Houston",
    "sg:classifiers":[
        {
            "category":"Professional",
            "subcategory":"Business Services",
            "type":"Services"
        }
    ],
    "sg:phone":"+1 713 550 9090",
    "sg:postcode":"77043",
    "sg:province":"TX",
    "sg:tags":[
        "fund",
        "promotion",
        "raising"
    ],
    "wof:name":"B & L Promotions",
    "wof:placetype":"venue"
},
  "geometry": {"coordinates":[-95.545205,29.792696],"type":"Point"}
}