{
  "type": "Feature",
  "properties": {
    "iso:country":"US",
    "sg:address":"3701 E Saunders St",
    "sg:city":"Laredo",
    "sg:classifiers":[
        {
            "category":"Autos & Motor Vehicles",
            "subcategory":"Automobile Sales",
            "type":"Retail Goods"
        },
        {
            "category":"Retail",
            "subcategory":"Auto Repair",
            "type":"Services"
        }
    ],
    "sg:phone":"+1 956 754 7400",
    "sg:postcode":"78041",
    "sg:province":"TX",
    "sg:tags":[
        "truck",
        "used",
        "leasing",
        "car",
        "new"
    ],
    "sg:website":"http://www.nissanoflaredo.com/",
    "wof:name":"Family Nissan Of Laredo",
    "wof:placetype":"venue"
},
  "geometry": {"coordinates":[-99.463105,27.529899],"type":"Point"}
}