{
  "type": "Feature",
  "properties": {
    "iso:country":"US",
    "sg:address":"643 Glen Lakes Dr",
    "sg:city":"Coppell",
    "sg:classifiers":[
        {
            "category":"Travel",
            "subcategory":"Hotels & Motels",
            "type":"Entertainment"
        }
    ],
    "sg:phone":"+1 972 462 1009",
    "sg:postcode":"75019",
    "sg:province":"TX",
    "sg:website":"www.ayellowrosehotels.com",
    "wof:name":"A Yellow Rose A Boutique Hotel",
    "wof:placetype":"venue"
},
  "geometry": {"coordinates":[-96.97484300000001,32.985568],"type":"Point"}
}