{
  "type": "Feature",
  "properties": {
    "iso:country":"US",
    "sg:address":"100 S Glasgow Dr",
    "sg:city":"Dallas",
    "sg:classifiers":[
        {
            "category":"Education",
            "subcategory":"School",
            "type":"Public Place"
        }
    ],
    "sg:phone":"+1 972 502 4400",
    "sg:postcode":"75214",
    "sg:province":"TX",
    "sg:website":"www.dallasisd.org",
    "wof:name":"Schools",
    "wof:placetype":"venue"
},
  "geometry": {"coordinates":[-96.75133700000001,32.805622],"type":"Point"}
}