{
  "type": "Feature",
  "properties": {
    "iso:country":"US",
    "sg:address":"11280 US Hwy 84",
    "sg:city":"Zephyr",
    "sg:classifiers":[
        {
            "category":"Organizations",
            "subcategory":"Religious Organization",
            "type":"Services"
        }
    ],
    "sg:phone":"+1 325 739 5981",
    "sg:postcode":"76890",
    "sg:province":"TX",
    "sg:tags":[
        "church"
    ],
    "wof:name":"Zephyr Baptist Ch",
    "wof:placetype":"venue"
},
  "geometry": {"coordinates":[-98.80059,31.681974],"type":"Point"}
}