{
  "type": "Feature",
  "properties": {
    "iso:country":"US",
    "sg:address":"3909 Martingale Dr",
    "sg:city":"Plano",
    "sg:classifiers":[
        {
            "category":"Retail",
            "subcategory":"Laundry & Dry Cleaning",
            "type":"Services"
        }
    ],
    "sg:phone":"+1 214 236 4699",
    "sg:postcode":"75023",
    "sg:province":"TX",
    "wof:name":"Resolve Carpet Cleaning",
    "wof:placetype":"venue"
},
  "geometry": {"coordinates":[-96.76433299999999,33.049643],"type":"Point"}
}