{
  "type": "Feature",
  "properties": {
    "iso:country":"US",
    "sg:address":"112 S Evans St",
    "sg:city":"Boyd",
    "sg:classifiers":[
        {
            "category":"Wholesale",
            "subcategory":"Non-durable Goods",
            "type":"Manufacturing & Wholesale Goods"
        }
    ],
    "sg:phone":"+1 940 433 3406",
    "sg:postcode":"76023",
    "sg:province":"TX",
    "wof:name":"Dahlhouse Distributors",
    "wof:placetype":"venue"
},
  "geometry": {"coordinates":[-97.566428,33.078409],"type":"Point"}
}