{
  "type": "Feature",
  "properties": {
    "iso:country":"US",
    "sg:address":"6003 S Cooper St",
    "sg:city":"Arlington",
    "sg:classifiers":[
        {
            "category":"Retail",
            "subcategory":"Laundry & Dry Cleaning",
            "type":"Services"
        }
    ],
    "sg:phone":"+1 817 417 5570",
    "sg:postcode":"76001",
    "sg:province":"TX",
    "sg:tags":[
        "cleaners"
    ],
    "wof:name":"Park Cleaners Inc",
    "wof:placetype":"venue"
},
  "geometry": {"coordinates":[-97.13350699999999,32.645845],"type":"Point"}
}