{
  "type": "Feature",
  "properties": {
    "iso:country":"US",
    "sg:address":"810 Champions Row",
    "sg:city":"Victoria",
    "sg:classifiers":[
        {
            "category":"Professional",
            "subcategory":"Business Services",
            "type":"Services"
        }
    ],
    "sg:phone":"+1 361 582 4704",
    "sg:postcode":"77904",
    "sg:province":"TX",
    "wof:name":"Boozalis Enterprises LLC",
    "wof:placetype":"venue"
},
  "geometry": {"coordinates":[-97.009781,28.854452],"type":"Point"}
}