{
  "type": "Feature",
  "properties": {
    "iso:country":"US",
    "sg:address":"2200 SW 3rd St",
    "sg:city":"Grand Prairie",
    "sg:classifiers":[
        {
            "category":"Organizations",
            "subcategory":"Religious Organization",
            "type":"Services"
        }
    ],
    "sg:phone":"+1 972 264 2511",
    "sg:postcode":"75051",
    "sg:province":"TX",
    "wof:name":"Faith Lutheran Church",
    "wof:placetype":"venue"
},
  "geometry": {"coordinates":[-97.007341,32.710146],"type":"Point"}
}