{
  "type": "Feature",
  "properties": {
    "iso:country":"US",
    "sg:address":"2300 E Main St",
    "sg:city":"Uvalde",
    "sg:classifiers":[
        {
            "category":"Wholesale",
            "subcategory":"Auto Parts",
            "type":"Manufacturing & Wholesale Goods"
        }
    ],
    "sg:phone":"+1 830 278 3355",
    "sg:postcode":"78801",
    "sg:province":"TX",
    "sg:tags":[
        "automobile",
        "rebuilt"
    ],
    "wof:name":"Main Auto Supply Inc",
    "wof:placetype":"venue"
},
  "geometry": {"coordinates":[-99.76345000000001,29.222115],"type":"Point"}
}