{
  "type": "Feature",
  "properties": {
    "iso:country":"US",
    "sg:address":"9842 State Hwy 171",
    "sg:city":"Itasca",
    "sg:classifiers":[
        {
            "category":"Personal",
            "subcategory":"Beauty Salon",
            "type":"Services"
        }
    ],
    "sg:phone":"+1 254 687 9848",
    "sg:postcode":"76050",
    "sg:province":"TX",
    "wof:name":"Haircuts Etc",
    "wof:placetype":"venue"
},
  "geometry": {"coordinates":[-97.273151,32.231932],"type":"Point"}
}