{
  "type": "Feature",
  "properties": {
    "iso:country":"US",
    "sg:address":"15950 Dallas Pkwy Ste 400",
    "sg:city":"Dallas",
    "sg:classifiers":[
        {
            "category":"Local Transit",
            "type":"Transportation"
        }
    ],
    "sg:phone":"+1 972 361 8050",
    "sg:postcode":"75248",
    "sg:province":"TX",
    "sg:tags":[
        "public"
    ],
    "wof:name":"Executive Auto Services Inc",
    "wof:placetype":"venue"
},
  "geometry": {"coordinates":[-96.82109800000001,32.9659],"type":"Point"}
}