{
  "type": "Feature",
  "properties": {
    "iso:country":"US",
    "sg:address":"210 W Spring St",
    "sg:city":"Fort Stockton",
    "sg:classifiers":[
        {
            "category":"Government",
            "subcategory":"Office",
            "type":"Public Place"
        }
    ],
    "sg:phone":"+1 432 336 8256",
    "sg:postcode":"79735",
    "sg:province":"TX",
    "wof:name":"Pecos County Historical Comm",
    "wof:placetype":"venue"
},
  "geometry": {"coordinates":[-102.881289,30.878399],"type":"Point"}
}