{
  "type": "Feature",
  "properties": {
    "iso:country":"US",
    "sg:address":"2023 Grand Willow Ln",
    "sg:city":"Richmond",
    "sg:classifiers":[
        {
            "category":"Wholesale",
            "subcategory":"Apparel",
            "type":"Manufacturing & Wholesale Goods"
        }
    ],
    "sg:phone":"+1 281 238 0646",
    "sg:postcode":"77469",
    "sg:province":"TX",
    "sg:tags":[
        "shoes-wholesale",
        "manufacturer"
    ],
    "wof:name":"Shoes Spice & Everything Nice",
    "wof:placetype":"venue"
},
  "geometry": {"coordinates":[-95.71650200000001,29.560913],"type":"Point"}
}