{
  "type": "Feature",
  "properties": {
    "iso:country":"US",
    "sg:address":"1500 E Hwy 90",
    "sg:city":"Liberty",
    "sg:classifiers":[
        {
            "category":"Banks & Credit Unions",
            "subcategory":"Bank",
            "type":"Services"
        }
    ],
    "sg:phone":"+1 936 336 2121",
    "sg:postcode":"77575",
    "sg:province":"TX",
    "sg:tags":[
        "money",
        "transfer"
    ],
    "wof:name":"Western Union",
    "wof:placetype":"venue"
},
  "geometry": {"coordinates":[-94.72754,30.051013],"type":"Point"}
}