{
  "type": "Feature",
  "properties": {
    "iso:country":"US",
    "sg:address":"3718 Decker Dr",
    "sg:city":"Baytown",
    "sg:classifiers":[
        {
            "category":"Retail",
            "subcategory":"Auto Rental",
            "type":"Services"
        }
    ],
    "sg:phone":"+1 281 424 3350",
    "sg:postcode":"77520",
    "sg:province":"TX",
    "sg:tags":[
        "car"
    ],
    "sg:website":"www.enterprise.com",
    "wof:name":"Enterprise Rent-A-Car",
    "wof:placetype":"venue"
},
  "geometry": {"coordinates":[-95.348395,29.765334],"type":"Point"}
}