{
  "type": "Feature",
  "properties": {
    "iso:country":"US",
    "sg:address":"2900 McKinney Ave",
    "sg:city":"Dallas",
    "sg:classifiers":[
        {
            "category":"Restaurant",
            "type":"Food & Drink"
        }
    ],
    "sg:phone":"+1 214 979 2400",
    "sg:postcode":"75204",
    "sg:province":"TX",
    "sg:tags":[
        "eating"
    ],
    "wof:name":"American Latin Cuisine",
    "wof:placetype":"venue"
},
  "geometry": {"coordinates":[-96.800828,32.799994],"type":"Point"}
}