{
  "type": "Feature",
  "properties": {
    "iso:country":"US",
    "sg:address":"111 N Summer Cloud Dr",
    "sg:city":"Spring",
    "sg:classifiers":[
        {
            "category":"Professional",
            "subcategory":"Art Services",
            "type":"Services"
        }
    ],
    "sg:phone":"+1 281 273 4219",
    "sg:postcode":"77381",
    "sg:province":"TX",
    "sg:tags":[
        "commercial",
        "design"
    ],
    "wof:name":"Inspired Graphic Design",
    "wof:placetype":"venue"
},
  "geometry": {"coordinates":[-95.520026,30.202826],"type":"Point"}
}