{
  "type": "Feature",
  "properties": {
    "iso:country":"US",
    "sg:address":"104 W 1st St",
    "sg:city":"Bishop",
    "sg:classifiers":[
        {
            "category":"Wholesale",
            "subcategory":"Auto Parts",
            "type":"Manufacturing & Wholesale Goods"
        }
    ],
    "sg:phone":"+1 361 584 5141",
    "sg:postcode":"78343",
    "sg:province":"TX",
    "sg:tags":[
        "tire"
    ],
    "wof:name":"Mario Alvarez & Sons",
    "wof:placetype":"venue"
},
  "geometry": {"coordinates":[-97.79972100000001,27.589773],"type":"Point"}
}