{
  "type": "Feature",
  "properties": {
    "iso:country":"US",
    "sg:address":"1500 N Cuernavaca Dr",
    "sg:city":"Austin",
    "sg:classifiers":[
        {
            "category":"Food & Beverages",
            "subcategory":"Groceries & Convenience Stores",
            "type":"Retail Goods"
        }
    ],
    "sg:phone":"+1 512 263 9809",
    "sg:postcode":"78733",
    "sg:province":"TX",
    "wof:name":"Lake Hills Grocery & Meat Market",
    "wof:placetype":"venue"
},
  "geometry": {"coordinates":[-97.864403,30.3384],"type":"Point"}
}