{
  "type": "Feature",
  "properties": {
    "iso:country":"US",
    "sg:address":"5403 S Rice Ave",
    "sg:city":"Houston",
    "sg:classifiers":[
        {
            "category":"Wholesale",
            "subcategory":"Medical Equipment & Supplies",
            "type":"Manufacturing & Wholesale Goods"
        }
    ],
    "sg:phone":"+1 713 218 0844",
    "sg:postcode":"77081",
    "sg:province":"TX",
    "sg:tags":[
        "physician",
        "surgeon"
    ],
    "wof:name":"Diamed",
    "wof:placetype":"venue"
},
  "geometry": {"coordinates":[-95.468087,29.724258],"type":"Point"}
}