{
  "type": "Feature",
  "properties": {
    "iso:country":"US",
    "sg:address":"817 Sidney Baker St",
    "sg:city":"Kerrville",
    "sg:classifiers":[
        {
            "category":"Health Services",
            "subcategory":"Doctor",
            "type":"Services"
        }
    ],
    "sg:phone":"+1 830 896 3804",
    "sg:postcode":"78028",
    "sg:province":"TX",
    "wof:name":"E Harold Bammel DDS",
    "wof:placetype":"venue"
},
  "geometry": {"coordinates":[-99.135581,30.051552],"type":"Point"}
}