{
  "type": "Feature",
  "properties": {
    "iso:country":"US",
    "sg:address":"2220 Avenue E",
    "sg:city":"Bay City",
    "sg:classifiers":[
        {
            "category":"Government",
            "subcategory":"Office",
            "type":"Public Place"
        }
    ],
    "sg:phone":"+1 979 245 1401",
    "sg:postcode":"77414",
    "sg:province":"TX",
    "sg:tags":[
        "county"
    ],
    "wof:name":"Matagorda County Teen Court",
    "wof:placetype":"venue"
},
  "geometry": {"coordinates":[-95.971228,28.981618],"type":"Point"}
}