{
  "type": "Feature",
  "properties": {
    "iso:country":"US",
    "sg:address":"721 W Martinez St",
    "sg:city":"Del Rio",
    "sg:classifiers":[
        {
            "category":"Restaurant",
            "type":"Food & Drink"
        }
    ],
    "sg:phone":"+1 956 565 9704",
    "sg:postcode":"78840",
    "sg:province":"TX",
    "wof:name":"Subway Sandwiches & Salads",
    "wof:placetype":"venue"
},
  "geometry": {"coordinates":[-100.876307,29.356693],"type":"Point"}
}