{
  "type": "Feature",
  "properties": {
    "iso:country":"US",
    "sg:address":"2001 Broadway St",
    "sg:city":"Marble Falls",
    "sg:classifiers":[
        {
            "category":"Education",
            "subcategory":"School",
            "type":"Public Place"
        }
    ],
    "sg:phone":"+1 830 693 4357",
    "sg:postcode":"78654",
    "sg:province":"TX",
    "sg:website":"www.mfisd.txed.net",
    "wof:name":"Marble Falls ISD",
    "wof:placetype":"venue"
},
  "geometry": {"coordinates":[-98.28768700000001,30.583109],"type":"Point"}
}