{
  "type": "Feature",
  "properties": {
    "iso:country":"US",
    "sg:address":"5865 San Felipe St",
    "sg:city":"Houston",
    "sg:classifiers":[
        {
            "category":"Shopping",
            "subcategory":"Bicycles & Sporting Goods",
            "type":"Retail Goods"
        }
    ],
    "sg:phone":"+1 713 783 5550",
    "sg:postcode":"77057",
    "sg:province":"TX",
    "wof:name":"Life Fitness James Risner",
    "wof:placetype":"venue"
},
  "geometry": {"coordinates":[-95.485372,29.749827],"type":"Point"}
}