{
  "type": "Feature",
  "properties": {
    "iso:country":"US",
    "sg:address":"1205 N Josey Lane #100",
    "sg:city":"Carrollton",
    "sg:classifiers":[
        {
            "category":"Personal",
            "subcategory":"Beauty Salon",
            "type":"Services"
        }
    ],
    "sg:phone":"+1 972 323 6836",
    "sg:postcode":"75006",
    "sg:province":"TX",
    "sg:tags":[
        "spa"
    ],
    "sg:website":"www.fitandbeautifulmedspa.com",
    "wof:name":"Fit & Beautiful Medical Spa",
    "wof:placetype":"venue"
},
  "geometry": {"coordinates":[-96.890528,32.956363],"type":"Point"}
}