{
  "type": "Feature",
  "properties": {
    "iso:country":"US",
    "sg:address":"620 E Ridge Rd",
    "sg:city":"Pharr",
    "sg:classifiers":[
        {
            "category":"Organizations",
            "subcategory":"Religious Organization",
            "type":"Services"
        }
    ],
    "sg:phone":"+1 956 787 1394",
    "sg:postcode":"78577",
    "sg:province":"TX",
    "sg:tags":[
        "church"
    ],
    "wof:name":"Centro De Alabanza Y Adoracion",
    "wof:placetype":"venue"
},
  "geometry": {"coordinates":[-98.18049600000001,26.17982],"type":"Point"}
}