{
  "type": "Feature",
  "properties": {
    "iso:country":"US",
    "sg:address":"735 Co Rd 6712",
    "sg:city":"Natalia",
    "sg:classifiers":[
        {
            "category":"Social Services",
            "subcategory":"Child Care",
            "type":"Services"
        }
    ],
    "sg:phone":"+1 830 772 3889",
    "sg:postcode":"78059",
    "sg:province":"TX",
    "sg:tags":[
        "day"
    ],
    "wof:name":"Denver Day",
    "wof:placetype":"venue"
},
  "geometry": {"coordinates":[-98.84586400000001,29.220882],"type":"Point"}
}