{
  "type": "Feature",
  "properties": {
    "iso:country":"US",
    "sg:address":"1201 Elm St",
    "sg:city":"Dallas",
    "sg:classifiers":[
        {
            "category":"Professional",
            "subcategory":"Lawyer & Legal Services",
            "type":"Services"
        }
    ],
    "sg:phone":"+1 214 760 8100",
    "sg:postcode":"75202",
    "sg:province":"TX",
    "sg:tags":[
        "attorney",
        "law"
    ],
    "wof:name":"Reyna Hinds & Crandall",
    "wof:placetype":"venue"
},
  "geometry": {"coordinates":[-96.801384,32.781047],"type":"Point"}
}