{
  "type": "Feature",
  "properties": {
    "iso:country":"US",
    "sg:address":"110 N 2nd St",
    "sg:city":"Texhoma",
    "sg:classifiers":[
        {
            "category":"Real Estate",
            "subcategory":"Real Estate Agent",
            "type":"Services"
        }
    ],
    "sg:phone":"+1 580 423 7616",
    "sg:postcode":"73949",
    "sg:province":"TX",
    "wof:name":"Winn Fred Real Estate",
    "wof:placetype":"venue"
},
  "geometry": {"coordinates":[-101.783186,36.505315],"type":"Point"}
}