{
  "type": "Feature",
  "properties": {
    "iso:country":"US",
    "sg:address":"643 Cortlandt St",
    "sg:city":"Houston",
    "sg:classifiers":[
        {
            "category":"Banks & Credit Unions",
            "subcategory":"Financial Services",
            "type":"Services"
        }
    ],
    "sg:phone":"+1 713 863 8676",
    "sg:postcode":"77007",
    "sg:province":"TX",
    "sg:tags":[
        "investor"
    ],
    "wof:name":"Smith Glover Investments LLC",
    "wof:placetype":"venue"
},
  "geometry": {"coordinates":[-95.395223,29.782549],"type":"Point"}
}