{
  "type": "Feature",
  "properties": {
    "iso:country":"US",
    "sg:address":"3905 Almeda-Genoa Rd",
    "sg:city":"Houston",
    "sg:classifiers":[
        {
            "category":"Real Estate",
            "subcategory":"Real Estate Operator",
            "type":"Services"
        }
    ],
    "sg:phone":"+1 713 733 8729",
    "sg:postcode":"77047",
    "sg:province":"TX",
    "sg:tags":[
        "mobile",
        "home",
        "community"
    ],
    "wof:name":"L & L Mobile Home Svc",
    "wof:placetype":"venue"
},
  "geometry": {"coordinates":[-95.359461,29.616714],"type":"Point"}
}