{
  "type": "Feature",
  "properties": {
    "iso:country":"US",
    "sg:address":"1212 S Shiloh Rd",
    "sg:city":"Garland",
    "sg:classifiers":[
        {
            "category":"Shopping",
            "subcategory":"Clothing, Apparel, & Fashions",
            "type":"Retail Goods"
        }
    ],
    "sg:phone":"+1 972 276 9075",
    "sg:postcode":"75042",
    "sg:province":"TX",
    "sg:tags":[
        "alteration"
    ],
    "wof:name":"J & T Sewing Inc",
    "wof:placetype":"venue"
},
  "geometry": {"coordinates":[-96.66553999999999,32.903669],"type":"Point"}
}