{
  "type": "Feature",
  "properties": {
    "iso:country":"US",
    "sg:address":"123 Kenway St",
    "sg:city":"Rockwall",
    "sg:classifiers":[
        {
            "category":"Manufacturing",
            "subcategory":"Retail Goods",
            "type":"Manufacturing & Wholesale Goods"
        }
    ],
    "sg:phone":"+1 972 771 0363",
    "sg:postcode":"75087",
    "sg:province":"TX",
    "sg:tags":[
        "product",
        "ware",
        "mfg"
    ],
    "wof:name":"L S J Gifts & Awards By",
    "wof:placetype":"venue"
},
  "geometry": {"coordinates":[-96.460705,32.926494],"type":"Point"}
}