{
  "type": "Feature",
  "properties": {
    "iso:country":"US",
    "sg:address":"2720 E Marshall Ave",
    "sg:city":"Longview",
    "sg:classifiers":[
        {
            "category":"Food & Beverages",
            "subcategory":"Groceries & Convenience Stores",
            "type":"Retail Goods"
        }
    ],
    "sg:phone":"+1 903 753 6678",
    "sg:postcode":"75601",
    "sg:province":"TX",
    "wof:name":"Sheik Enterprises",
    "wof:placetype":"venue"
},
  "geometry": {"coordinates":[-94.695122,32.503992],"type":"Point"}
}