{
  "type": "Feature",
  "properties": {
    "iso:country":"US",
    "sg:address":"3240 S Soncy Rd Suite 400",
    "sg:city":"Amarillo",
    "sg:classifiers":[
        {
            "category":"Insurance",
            "subcategory":"Insurance Agent",
            "type":"Services"
        },
        {
            "category":"Insurance",
            "subcategory":"Hazard Insurance",
            "type":"Services"
        }
    ],
    "sg:phone":"+1 806 359 7867",
    "sg:postcode":"79124",
    "sg:province":"TX",
    "sg:tags":[
        "auto",
        "recreational",
        "motorcycle",
        "vehicle",
        "marine",
        "boat"
    ],
    "wof:name":"The Insurance Stop",
    "wof:placetype":"venue"
},
  "geometry": {"coordinates":[-101.938608,35.240866],"type":"Point"}
}