{
  "type": "Feature",
  "properties": {
    "iso:country":"US",
    "sg:address":"2118 Cannon Farm Hills Ln",
    "sg:city":"Richmond",
    "sg:classifiers":[
        {
            "category":"Wholesale",
            "subcategory":"Electrical",
            "type":"Manufacturing & Wholesale Goods"
        }
    ],
    "sg:phone":"+1 713 304 7474",
    "sg:postcode":"77469",
    "sg:province":"TX",
    "sg:tags":[
        "equipment"
    ],
    "wof:name":"Advanced Protective Technology",
    "wof:placetype":"venue"
},
  "geometry": {"coordinates":[-95.73887000000001,29.63484],"type":"Point"}
}