{
  "type": "Feature",
  "properties": {
    "iso:country":"US",
    "sg:address":"4807 NW Industrial",
    "sg:city":"San Antonio",
    "sg:phone":"+1 210 521 9005",
    "sg:postcode":"78238",
    "sg:province":"TX",
    "sg:tags":[
        "scale"
    ],
    "wof:name":"South Texas Scale Svc Inc",
    "wof:placetype":"venue"
},
  "geometry": {"coordinates":[-98.59858800000001,29.479534],"type":"Point"}
}