{
  "type": "Feature",
  "properties": {
    "iso:country":"US",
    "sg:address":"5606 FM 1585",
    "sg:city":"Lubbock",
    "sg:classifiers":[
        {
            "category":"Home & Garden",
            "subcategory":"Garden Supply",
            "type":"Retail Goods"
        }
    ],
    "sg:phone":"+1 806 798 1228",
    "sg:postcode":"79424",
    "sg:province":"TX",
    "sg:tags":[
        "stone",
        "brick",
        "lawn"
    ],
    "wof:name":"Stewart Rock & Stone",
    "wof:placetype":"venue"
},
  "geometry": {"coordinates":[-101.933986,33.476131],"type":"Point"}
}