{
  "type": "Feature",
  "properties": {
    "iso:country":"US",
    "sg:address":"518 E Main St",
    "sg:city":"Teague",
    "sg:classifiers":[
        {
            "category":"Wholesale",
            "subcategory":"Machinery & Supplies",
            "type":"Manufacturing & Wholesale Goods"
        }
    ],
    "sg:phone":"+1 254 739 5001",
    "sg:postcode":"75860",
    "sg:province":"TX",
    "sg:tags":[
        "field",
        "oil",
        "equipment"
    ],
    "wof:name":"Premier Designs",
    "wof:placetype":"venue"
},
  "geometry": {"coordinates":[-96.28269299999999,31.626986],"type":"Point"}
}