{
  "type": "Feature",
  "properties": {
    "iso:country":"US",
    "sg:address":"3129 Handley Dr",
    "sg:city":"Fort Worth",
    "sg:classifiers":[
        {
            "category":"Professional",
            "subcategory":"Engineering",
            "type":"Services"
        }
    ],
    "sg:phone":"+1 817 451 6687",
    "sg:postcode":"76112",
    "sg:province":"TX",
    "sg:tags":[
        "firm",
        "consulting"
    ],
    "wof:name":"Scarborough Engineering Inc",
    "wof:placetype":"venue"
},
  "geometry": {"coordinates":[-97.21778399999999,32.734088],"type":"Point"}
}