{
  "type": "Feature",
  "properties": {
    "iso:country":"US",
    "sg:address":"3021 34th St",
    "sg:city":"Lubbock",
    "sg:classifiers":[
        {
            "category":"Social Services",
            "type":"Services"
        }
    ],
    "sg:phone":"+1 806 788 0500",
    "sg:postcode":"79410",
    "sg:province":"TX",
    "wof:name":"Outreach Committee",
    "wof:placetype":"venue"
},
  "geometry": {"coordinates":[-101.8809,33.563192],"type":"Point"}
}