{
  "type": "Feature",
  "properties": {
    "iso:country":"US",
    "sg:address":"156 N Courthouse Sq",
    "sg:city":"Goliad",
    "sg:classifiers":[
        {
            "category":"Personal",
            "type":"Services"
        },
        {
            "category":"Health Services",
            "subcategory":"Health Practitioner",
            "type":"Services"
        }
    ],
    "sg:phone":"+1 361 645 3300",
    "sg:postcode":"77963",
    "sg:province":"TX",
    "sg:tags":[
        "hypnotist"
    ],
    "wof:name":"Orsak Jo Ann Massage Therapy",
    "wof:placetype":"venue"
},
  "geometry": {"coordinates":[-97.39196200000001,28.666521],"type":"Point"}
}