{
  "type": "Feature",
  "properties": {
    "iso:country":"US",
    "sg:address":"4485 Trinity Mills Ste 200, Salon Ste 01",
    "sg:city":"Dallas",
    "sg:classifiers":[
        {
            "category":"Personal",
            "subcategory":"Beauty Salon",
            "type":"Services"
        }
    ],
    "sg:phone":"+1 469 951 1606",
    "sg:postcode":"75287",
    "sg:province":"TX",
    "sg:tags":[
        "hair"
    ],
    "sg:website":"www.saramcroberts.com",
    "wof:name":"Sara McRoberts Hair Design",
    "wof:placetype":"venue"
},
  "geometry": {"coordinates":[-96.832038,32.990468],"type":"Point"}
}