{
  "type": "Feature",
  "properties": {
    "iso:country":"US",
    "sg:address":"121 E 7th St",
    "sg:city":"Plainview",
    "sg:classifiers":[
        {
            "category":"Government",
            "subcategory":"Office",
            "type":"Public Place"
        },
        {
            "category":"Social Services",
            "type":"Services"
        }
    ],
    "sg:phone":"+1 806 293 4833",
    "sg:postcode":"79072",
    "sg:province":"TX",
    "wof:name":"Adults Protective Services",
    "wof:placetype":"venue"
},
  "geometry": {"coordinates":[-101.70198499999999,34.187081],"type":"Point"}
}