{
  "type": "Feature",
  "properties": {
    "iso:country":"US",
    "sg:address":"607 West St",
    "sg:city":"Rosenberg",
    "sg:classifiers":[
        {
            "category":"Organizations",
            "subcategory":"Religious Organization",
            "type":"Services"
        }
    ],
    "sg:phone":"+1 281 342 0527",
    "sg:postcode":"77471",
    "sg:province":"TX",
    "wof:name":"Shilo Baptist Church",
    "wof:placetype":"venue"
},
  "geometry": {"coordinates":[-95.81433199999999,29.561676],"type":"Point"}
}