{
  "type": "Feature",
  "properties": {
    "iso:country":"US",
    "sg:address":"925 Capitol Ct",
    "sg:city":"Austin",
    "sg:classifiers":[
        {
            "category":"Banks & Credit Unions",
            "subcategory":"Bank",
            "type":"Services"
        }
    ],
    "sg:phone":"+1 512 732 2882",
    "sg:postcode":"78756",
    "sg:province":"TX",
    "sg:tags":[
        "broker",
        "mortgage"
    ],
    "wof:name":"Key Mortgage",
    "wof:placetype":"venue"
},
  "geometry": {"coordinates":[-97.731133,30.318265],"type":"Point"}
}