{
  "type": "Feature",
  "properties": {
    "iso:country":"US",
    "sg:address":"5601 W Lovers Ln",
    "sg:city":"Dallas",
    "sg:classifiers":[
        {
            "category":"Health Services",
            "subcategory":"Doctor",
            "type":"Services"
        }
    ],
    "sg:phone":"+1 214 366 4600",
    "sg:postcode":"75209",
    "sg:province":"TX",
    "sg:tags":[
        "podiatrist"
    ],
    "wof:name":"Saginaw Michael DPM",
    "wof:placetype":"venue"
},
  "geometry": {"coordinates":[-96.817497,32.851299],"type":"Point"}
}