{
  "type": "Feature",
  "properties": {
    "iso:country":"US",
    "sg:address":"5599 San Felipe St Ste 1450",
    "sg:city":"Houston",
    "sg:classifiers":[
        {
            "category":"Professional",
            "subcategory":"Lawyer & Legal Services",
            "type":"Services"
        }
    ],
    "sg:phone":"+1 713 622 3459",
    "sg:postcode":"77056",
    "sg:province":"TX",
    "wof:name":"Parker Vaughan & Werlein",
    "wof:placetype":"venue"
},
  "geometry": {"coordinates":[-95.47444400000001,29.749902],"type":"Point"}
}