{
  "type": "Feature",
  "properties": {
    "iso:country":"US",
    "sg:address":"4719 Raylett Dr",
    "sg:city":"Wichita Falls",
    "sg:classifiers":[
        {
            "category":"Home & Garden",
            "subcategory":"Household Appliances",
            "type":"Retail Goods"
        }
    ],
    "sg:phone":"+1 940 851 6843",
    "sg:postcode":"76306",
    "sg:province":"TX",
    "wof:name":"Kussavage Enterprises",
    "wof:placetype":"venue"
},
  "geometry": {"coordinates":[-98.527264,33.973676],"type":"Point"}
}