{
  "type": "Feature",
  "properties": {
    "iso:country":"US",
    "sg:address":"15318 Appleridge Dr",
    "sg:city":"Missouri City",
    "sg:classifiers":[
        {
            "category":"Health Services",
            "subcategory":"Health Practitioner",
            "type":"Services"
        }
    ],
    "sg:phone":"+1 281 437 1724",
    "sg:postcode":"77489",
    "sg:province":"TX",
    "wof:name":"4 Stars Health Care Manag",
    "wof:placetype":"venue"
},
  "geometry": {"coordinates":[-95.499371,29.60354],"type":"Point"}
}