{
  "type": "Feature",
  "properties": {
    "iso:country":"US",
    "sg:address":"3307 W Airport Fwy",
    "sg:city":"Irving",
    "sg:classifiers":[
        {
            "category":"Shopping",
            "type":"Retail Goods"
        }
    ],
    "sg:phone":"+1 972 413 7360",
    "sg:postcode":"75062",
    "sg:province":"TX",
    "sg:tags":[
        "merchandise"
    ],
    "wof:name":"Verizon",
    "wof:placetype":"venue"
},
  "geometry": {"coordinates":[-96.99080499999999,32.838154],"type":"Point"}
}