{
  "type": "Feature",
  "properties": {
    "iso:country":"US",
    "sg:address":"206 N 28th St",
    "sg:city":"Gatesville",
    "sg:classifiers":[
        {
            "category":"Building & Trades",
            "subcategory":"Construction",
            "type":"Services"
        }
    ],
    "sg:phone":"+1 254 865 7407",
    "sg:postcode":"76528",
    "sg:province":"TX",
    "sg:tags":[
        "woodworker"
    ],
    "wof:name":"Sawdust & Splinters",
    "wof:placetype":"venue"
},
  "geometry": {"coordinates":[-97.71934899999999,31.439448],"type":"Point"}
}