{
  "type": "Feature",
  "properties": {
    "iso:country":"US",
    "sg:address":"7811 Wheel Rim Cir",
    "sg:city":"Austin",
    "sg:classifiers":[
        {
            "category":"Utilities",
            "subcategory":"Electric",
            "type":"Services"
        }
    ],
    "sg:phone":"+1 512 301 4166",
    "sg:postcode":"78749",
    "sg:province":"TX",
    "wof:name":"Clay Electric",
    "wof:placetype":"venue"
},
  "geometry": {"coordinates":[-97.86915399999999,30.219047],"type":"Point"}
}