{
  "type": "Feature",
  "properties": {
    "iso:country":"US",
    "sg:address":"731 State Hwy 97 E",
    "sg:city":"Nixon",
    "sg:classifiers":[
        {
            "category":"Retail",
            "subcategory":"Repair Shop",
            "type":"Services"
        }
    ],
    "sg:phone":"+1 830 582 2471",
    "sg:postcode":"78140",
    "sg:province":"TX",
    "sg:tags":[
        "welding"
    ],
    "wof:name":"Altwein Welding",
    "wof:placetype":"venue"
},
  "geometry": {"coordinates":[-97.744795,29.333151],"type":"Point"}
}