{
  "type": "Feature",
  "properties": {
    "iso:country":"US",
    "sg:address":"1920 E Belt Line Rd",
    "sg:city":"Carrollton",
    "sg:classifiers":[
        {
            "category":"Restaurant",
            "type":"Food & Drink"
        }
    ],
    "sg:phone":"+1 972 416 3201",
    "sg:postcode":"75006",
    "sg:province":"TX",
    "wof:name":"Subway",
    "wof:placetype":"venue"
},
  "geometry": {"coordinates":[-96.88800000000001,32.953499],"type":"Point"}
}