{
  "type": "Feature",
  "properties": {
    "iso:country":"US",
    "sg:address":"5126 Burnet Rd",
    "sg:city":"Austin",
    "sg:classifiers":[
        {
            "category":"Retail",
            "subcategory":"Auto Repair",
            "type":"Services"
        }
    ],
    "sg:phone":"+1 512 478 1531",
    "sg:postcode":"78756",
    "sg:province":"TX",
    "sg:tags":[
        "repairing",
        "automobile"
    ],
    "wof:name":"Doc's Motorworks",
    "wof:placetype":"venue"
},
  "geometry": {"coordinates":[-97.73948799999999,30.323086],"type":"Point"}
}