{
  "type": "Feature",
  "properties": {
    "iso:country":"US",
    "sg:address":"728 E Starr Ave Apt 101",
    "sg:city":"Nacogdoches",
    "sg:classifiers":[
        {
            "category":"Real Estate",
            "subcategory":"Real Estate Services",
            "type":"Services"
        },
        {
            "category":"Real Estate",
            "subcategory":"Real Estate Operator",
            "type":"Services"
        }
    ],
    "sg:phone":"+1 936 569 2477",
    "sg:postcode":"75961",
    "sg:province":"TX",
    "sg:tags":[
        "apartment",
        "vacancy",
        "listing",
        "rental",
        "finder"
    ],
    "wof:name":"Park Pecan Apartments",
    "wof:placetype":"venue"
},
  "geometry": {"coordinates":[-94.646255,31.615971],"type":"Point"}
}