{
  "type": "Feature",
  "properties": {
    "iso:country":"US",
    "sg:address":"1650 S Mason Rd",
    "sg:city":"Katy",
    "sg:classifiers":[
        {
            "category":"Restaurant",
            "type":"Food & Drink"
        }
    ],
    "sg:menulink":"http://www.allmenus.com/tx/houston/73339-doubledaves-pizza-works/menu/",
    "sg:phone":"+1 281 391 3283",
    "sg:postcode":"77450",
    "sg:province":"TX",
    "sg:tags":[
        "american",
        "pizza"
    ],
    "wof:name":"DoubleDave's Pizza Works",
    "wof:placetype":"venue"
},
  "geometry": {"coordinates":[-95.751609,29.756899],"type":"Point"}
}