{
  "type": "Feature",
  "properties": {
    "iso:country":"US",
    "sg:address":"9655 Richmond Ave",
    "sg:city":"Houston",
    "sg:classifiers":[
        {
            "category":"Professional",
            "subcategory":"Computer Services",
            "type":"Services"
        }
    ],
    "sg:phone":"+1 713 953 1556",
    "sg:postcode":"77063",
    "sg:province":"TX",
    "sg:tags":[
        "consultant",
        "designer"
    ],
    "sg:website":"www.appliedbc.com",
    "wof:name":"Applied Business Computers",
    "wof:placetype":"venue"
},
  "geometry": {"coordinates":[-95.537043,29.727959],"type":"Point"}
}