{
  "type": "Feature",
  "properties": {
    "iso:country":"US",
    "sg:address":"1240 Co Rd 226",
    "sg:city":"Llano",
    "sg:classifiers":[
        {
            "category":"Farming",
            "subcategory":"Livestock Farm",
            "type":"Manufacturing & Wholesale Goods"
        }
    ],
    "sg:phone":"+1 325 247 4169",
    "sg:postcode":"78666",
    "sg:province":"TX",
    "sg:tags":[
        "general"
    ],
    "wof:name":"Sawyer John",
    "wof:placetype":"venue"
},
  "geometry": {"coordinates":[-97.971326,29.912067],"type":"Point"}
}