{
  "type": "Feature",
  "properties": {
    "iso:country":"US",
    "sg:address":"3950 State Hwy 110",
    "sg:city":"Tyler",
    "sg:classifiers":[
        {
            "category":"Health Services",
            "subcategory":"Clinic",
            "type":"Services"
        }
    ],
    "sg:phone":"+1 903 592 4245",
    "sg:postcode":"75704",
    "sg:province":"TX",
    "wof:name":"Tyler Paramedical Services",
    "wof:placetype":"venue"
},
  "geometry": {"coordinates":[-95.36017699999999,32.378823],"type":"Point"}
}