{
  "type": "Feature",
  "properties": {
    "iso:country":"US",
    "sg:address":"1801 Dupont Dr",
    "sg:city":"Orange",
    "sg:classifiers":[
        {
            "category":"Food & Beverages",
            "subcategory":"Groceries & Convenience Stores",
            "type":"Retail Goods"
        },
        {
            "category":"Recreation",
            "type":"Entertainment"
        }
    ],
    "sg:phone":"+1 409 886 3810",
    "sg:postcode":"77630",
    "sg:province":"TX",
    "sg:tags":[
        "lottery",
        "agent"
    ],
    "wof:name":"Stop N Drive",
    "wof:placetype":"venue"
},
  "geometry": {"coordinates":[-93.742763,30.06769],"type":"Point"}
}