{
  "type": "Feature",
  "properties": {
    "iso:country":"US",
    "sg:address":"11020 Audelia Rd",
    "sg:city":"Dallas",
    "sg:classifiers":[
        {
            "category":"Professional",
            "subcategory":"Lawyer & Legal Services",
            "type":"Services"
        }
    ],
    "sg:phone":"+1 214 265 9700",
    "sg:postcode":"75243",
    "sg:province":"TX",
    "wof:name":"Lorenz Ted R Law Office",
    "wof:placetype":"venue"
},
  "geometry": {"coordinates":[-96.7174,32.9039],"type":"Point"}
}