{
  "type": "Feature",
  "properties": {
    "iso:country":"US",
    "sg:address":"7075 FM 1960 W",
    "sg:city":"Houston",
    "sg:classifiers":[
        {
            "category":"Shopping",
            "subcategory":"Department Store",
            "type":"Retail Goods"
        }
    ],
    "sg:phone":"+1 281 893 2207",
    "sg:postcode":"77069",
    "sg:province":"TX",
    "sg:tags":[
        "grocery"
    ],
    "wof:name":"Wal-Mart",
    "wof:placetype":"venue"
},
  "geometry": {"coordinates":[-95.53367299999999,29.968362],"type":"Point"}
}