{
  "type": "Feature",
  "properties": {
    "iso:country":"US",
    "sg:address":"4136 S. Carrier Pkwy Ste 340",
    "sg:city":"Grand Prairie",
    "sg:classifiers":[
        {
            "category":"Ice Cream",
            "type":"Food & Drink"
        }
    ],
    "sg:phone":"+1 972 642 7023",
    "sg:postcode":"75052",
    "sg:province":"TX",
    "sg:tags":[
        "frozen",
        "yogurt"
    ],
    "wof:name":"Baskin-Robbins",
    "wof:placetype":"venue"
},
  "geometry": {"coordinates":[-97.00583899999999,32.671475],"type":"Point"}
}