{
  "type": "Feature",
  "properties": {
    "iso:country":"US",
    "sg:address":"307 W Elm St",
    "sg:city":"Winnsboro",
    "sg:phone":"+1 903 342 5629",
    "sg:postcode":"75494",
    "sg:province":"TX",
    "wof:name":"Hubbell House Bed & Breakfast Thee",
    "wof:placetype":"venue"
},
  "geometry": {"coordinates":[-95.292264,32.958896],"type":"Point"}
}