{
  "type": "Feature",
  "properties": {
    "iso:country":"US",
    "sg:address":"3417 Prospect St",
    "sg:city":"Houston",
    "sg:classifiers":[
        {
            "category":"Freight",
            "type":"Transportation"
        }
    ],
    "sg:phone":"+1 713 523 0312",
    "sg:postcode":"77004",
    "sg:province":"TX",
    "sg:tags":[
        "broker",
        "trucking"
    ],
    "wof:name":"MSM Transportation Inc",
    "wof:placetype":"venue"
},
  "geometry": {"coordinates":[-95.361982,29.712579],"type":"Point"}
}