{
  "type": "Feature",
  "properties": {
    "iso:country":"US",
    "sg:address":"1500 Spyglass Dr",
    "sg:city":"Austin",
    "sg:classifiers":[
        {
            "category":"Food & Beverages",
            "subcategory":"Groceries & Convenience Stores",
            "type":"Retail Goods"
        }
    ],
    "sg:phone":"+1 512 327 5145",
    "sg:postcode":"78746",
    "sg:province":"TX",
    "wof:name":"Stop-N-Go Market",
    "wof:placetype":"venue"
},
  "geometry": {"coordinates":[-97.786545,30.258967],"type":"Point"}
}