{
  "type": "Feature",
  "properties": {
    "iso:country":"US",
    "sg:address":"10720A Kingspoint Rd",
    "sg:city":"Houston",
    "sg:classifiers":[
        {
            "category":"Personal",
            "subcategory":"Nail Salon",
            "type":"Services"
        }
    ],
    "sg:phone":"+1 713 947 3075",
    "sg:postcode":"77075",
    "sg:province":"TX",
    "wof:name":"Nail by Sandi",
    "wof:placetype":"venue"
},
  "geometry": {"coordinates":[-95.22982399999999,29.618933],"type":"Point"}
}