{
  "type": "Feature",
  "properties": {
    "iso:country":"US",
    "sg:address":"402 E Main St",
    "sg:city":"Grand Prairie",
    "sg:classifiers":[
        {
            "category":"Restaurant",
            "type":"Food & Drink"
        }
    ],
    "sg:phone":"+1 972 262 8188",
    "sg:postcode":"75050",
    "sg:province":"TX",
    "sg:tags":[
        "eating"
    ],
    "wof:name":"Joy Luck",
    "wof:placetype":"venue"
},
  "geometry": {"coordinates":[-96.99818,32.745807],"type":"Point"}
}