{
  "type": "Feature",
  "properties": {
    "iso:country":"US",
    "sg:address":"2132 Stevenson Ln",
    "sg:city":"Flower Mound",
    "sg:classifiers":[
        {
            "category":"Professional",
            "subcategory":"Management & Consulting",
            "type":"Services"
        }
    ],
    "sg:phone":"+1 972 355 2855",
    "sg:postcode":"75028",
    "sg:province":"TX",
    "sg:tags":[
        "business"
    ],
    "wof:name":"A&E Consulting",
    "wof:placetype":"venue"
},
  "geometry": {"coordinates":[-97.05987500000001,33.065035],"type":"Point"}
}