{
  "type": "Feature",
  "properties": {
    "iso:country":"US",
    "sg:address":"180 Crockett St",
    "sg:city":"Quemado",
    "sg:classifiers":[
        {
            "category":"Organizations",
            "subcategory":"Religious Organization",
            "type":"Services"
        }
    ],
    "sg:phone":"+1 830 757 1625",
    "sg:postcode":"78852",
    "sg:province":"TX",
    "sg:tags":[
        "church"
    ],
    "wof:name":"Rio Bravo Christian Ministries",
    "wof:placetype":"venue"
},
  "geometry": {"coordinates":[-100.496245,28.702909],"type":"Point"}
}