{
  "type": "Feature",
  "properties": {
    "iso:country":"US",
    "sg:address":"16850 Saturn Ln",
    "sg:city":"Houston",
    "sg:classifiers":[
        {
            "category":"Professional",
            "subcategory":"Management & Consulting",
            "type":"Services"
        }
    ],
    "sg:phone":"+1 281 480 8282",
    "sg:postcode":"77062",
    "sg:province":"TX",
    "sg:tags":[
        "consultant",
        "business"
    ],
    "wof:name":"He Space Operations",
    "wof:placetype":"venue"
},
  "geometry": {"coordinates":[-95.11412300000001,29.560316],"type":"Point"}
}