{
  "type": "Feature",
  "properties": {
    "iso:country":"US",
    "sg:address":"3501 Keller Rd",
    "sg:city":"Temple",
    "sg:classifiers":[
        {
            "category":"Shopping",
            "subcategory":"Stationery & Office Supplies",
            "type":"Retail Goods"
        }
    ],
    "sg:phone":"+1 254 791 0854",
    "sg:postcode":"76504",
    "sg:province":"TX",
    "wof:name":"Earl Brewer Specialties",
    "wof:placetype":"venue"
},
  "geometry": {"coordinates":[-97.38232000000001,31.098526],"type":"Point"}
}