{
  "type": "Feature",
  "properties": {
    "iso:country":"US",
    "sg:address":"1202 36th St",
    "sg:city":"Wichita Falls",
    "sg:classifiers":[
        {
            "category":"Organizations",
            "subcategory":"Religious Organization",
            "type":"Services"
        }
    ],
    "sg:phone":"+1 940 767 3265",
    "sg:postcode":"76302",
    "sg:province":"TX",
    "wof:name":"Faith Freewill Baptist Church",
    "wof:placetype":"venue"
},
  "geometry": {"coordinates":[-98.488502,33.878008],"type":"Point"}
}