{
  "type": "Feature",
  "properties": {
    "iso:country":"US",
    "sg:address":"10021 Cayuga Dr",
    "sg:city":"Dallas",
    "sg:classifiers":[
        {
            "category":"Building & Trades",
            "subcategory":"Construction",
            "type":"Services"
        }
    ],
    "sg:phone":"+1 214 321 9341",
    "sg:postcode":"75228",
    "sg:province":"TX",
    "sg:tags":[
        "roofing",
        "nonresidential",
        "contractor"
    ],
    "wof:name":"Bert Roofing Inc",
    "wof:placetype":"venue"
},
  "geometry": {"coordinates":[-96.689301,32.833],"type":"Point"}
}