{
  "type": "Feature",
  "properties": {
    "iso:country":"US",
    "sg:address":"10223 Broadway St",
    "sg:city":"Pearland",
    "sg:classifiers":[
        {
            "category":"Utilities",
            "subcategory":"Mobile Phone",
            "type":"Services"
        }
    ],
    "sg:phone":"+1 713 436 1037",
    "sg:postcode":"77584",
    "sg:province":"TX",
    "sg:tags":[
        "telephone",
        "cellular"
    ],
    "wof:name":"Verizon Wireless",
    "wof:placetype":"venue"
},
  "geometry": {"coordinates":[-95.37848200000001,29.556106],"type":"Point"}
}