{
  "type": "Feature",
  "properties": {
    "iso:country":"US",
    "sg:address":"4325 Stapper Rd",
    "sg:city":"St Hedwig",
    "sg:classifiers":[
        {
            "category":"Autos & Motor Vehicles",
            "subcategory":"Automobile Sales",
            "type":"Retail Goods"
        }
    ],
    "sg:phone":"+1 830 420 2230",
    "sg:postcode":"78152",
    "sg:province":"TX",
    "sg:tags":[
        "car",
        "dealer"
    ],
    "wof:name":"D & A Auto Sales & Auto",
    "wof:placetype":"venue"
},
  "geometry": {"coordinates":[-98.196254,29.466957],"type":"Point"}
}