{
  "type": "Feature",
  "properties": {
    "iso:country":"US",
    "sg:address":"1628 Comfort",
    "sg:city":"New Braunfels",
    "sg:classifiers":[
        {
            "category":"Building & Trades",
            "subcategory":"Construction",
            "type":"Services"
        }
    ],
    "sg:phone":"+1 830 899 7370",
    "sg:postcode":"78133",
    "sg:province":"TX",
    "wof:name":"Forest Construction",
    "wof:placetype":"venue"
},
  "geometry": {"coordinates":[-98.266282,29.880078],"type":"Point"}
}