{
  "type": "Feature",
  "properties": {
    "iso:country":"US",
    "sg:address":"14131 Midway Rd",
    "sg:city":"Addison",
    "sg:classifiers":[
        {
            "category":"Professional",
            "subcategory":"Lawyer & Legal Services",
            "type":"Services"
        }
    ],
    "sg:phone":"+1 972 701 9222",
    "sg:postcode":"75001",
    "sg:province":"TX",
    "wof:name":"Kohm David S Attorney At Law",
    "wof:placetype":"venue"
},
  "geometry": {"coordinates":[-96.839169,32.94247],"type":"Point"}
}