{
  "type": "Feature",
  "properties": {
    "iso:country":"US",
    "sg:address":"5916 W 34th St",
    "sg:city":"Houston",
    "sg:classifiers":[
        {
            "category":"Local Transit",
            "type":"Transportation"
        }
    ],
    "sg:phone":"+1 713 956 1822",
    "sg:postcode":"77092",
    "sg:province":"TX",
    "sg:tags":[
        "passenger"
    ],
    "wof:name":"All Care EMS",
    "wof:placetype":"venue"
},
  "geometry": {"coordinates":[-95.476039,29.819379],"type":"Point"}
}