{
  "type": "Feature",
  "properties": {
    "iso:country":"US",
    "sg:address":"1520 West Ave",
    "sg:city":"Waco",
    "sg:classifiers":[
        {
            "category":"Building & Trades",
            "subcategory":"Landscaping Services",
            "type":"Services"
        }
    ],
    "sg:phone":"+1 254 235 3259",
    "sg:postcode":"76707",
    "sg:province":"TX",
    "wof:name":"Ias Lawn Service",
    "wof:placetype":"venue"
},
  "geometry": {"coordinates":[-97.15056800000001,31.556788],"type":"Point"}
}