{
  "type": "Feature",
  "properties": {
    "iso:country":"US",
    "sg:address":"2902 Kirby Dr",
    "sg:city":"Houston",
    "sg:classifiers":[
        {
            "category":"Fast Food",
            "type":"Food & Drink"
        },
        {
            "category":"Restaurant",
            "type":"Food & Drink"
        }
    ],
    "sg:phone":"+1 713 524 7085",
    "sg:postcode":"77098",
    "sg:province":"TX",
    "sg:tags":[
        "burger",
        "american",
        "traditional"
    ],
    "sg:website":"www.becksprime.com/",
    "wof:name":"Becks Prime",
    "wof:placetype":"venue"
},
  "geometry": {"coordinates":[-95.41889999999999,29.74],"type":"Point"}
}