{
  "type": "Feature",
  "properties": {
    "iso:country":"US",
    "sg:address":"1350 W Poplar St",
    "sg:city":"San Antonio",
    "sg:classifiers":[
        {
            "category":"Wholesale",
            "subcategory":"Machinery & Supplies",
            "type":"Manufacturing & Wholesale Goods"
        }
    ],
    "sg:phone":"+1 210 736 4431",
    "sg:postcode":"78207",
    "sg:province":"TX",
    "sg:tags":[
        "concrete",
        "equipment"
    ],
    "sg:website":"www.rufusawalker.com",
    "wof:name":"Rufus A Walker & Co",
    "wof:placetype":"venue"
},
  "geometry": {"coordinates":[-98.508516,29.439061],"type":"Point"}
}