{
  "type": "Feature",
  "properties": {
    "iso:country":"US",
    "sg:address":"7201 Colony Loop Dr",
    "sg:city":"Austin",
    "sg:classifiers":[
        {
            "category":"Education",
            "subcategory":"School",
            "type":"Public Place"
        }
    ],
    "sg:phone":"+1 512 841 9300",
    "sg:postcode":"78724",
    "sg:province":"TX",
    "sg:tags":[
        "k-",
        "private"
    ],
    "wof:name":"Austin Independent School District",
    "wof:placetype":"venue"
},
  "geometry": {"coordinates":[-97.637822,30.302187],"type":"Point"}
}