{
  "type": "Feature",
  "properties": {
    "iso:country":"US",
    "sg:address":"13170 Pond Springs Rd",
    "sg:city":"Austin",
    "sg:classifiers":[
        {
            "category":"Professional",
            "subcategory":"Management & Consulting",
            "type":"Services"
        }
    ],
    "sg:phone":"+1 512 258 6728",
    "sg:postcode":"78729",
    "sg:province":"TX",
    "wof:name":"Prosperity Management Ser",
    "wof:placetype":"venue"
},
  "geometry": {"coordinates":[-97.77788700000001,30.444898],"type":"Point"}
}