{
  "type": "Feature",
  "properties": {
    "iso:country":"US",
    "sg:address":"6502 Ranch Park Dr",
    "sg:city":"Magnolia",
    "sg:classifiers":[
        {
            "category":"Building & Trades",
            "subcategory":"Electrical",
            "type":"Services"
        }
    ],
    "sg:phone":"+1 281 797 4403",
    "sg:postcode":"77354",
    "sg:province":"TX",
    "sg:tags":[
        "electrician"
    ],
    "wof:name":"Sellers Electric",
    "wof:placetype":"venue"
},
  "geometry": {"coordinates":[-95.565573,30.243993],"type":"Point"}
}