{
  "type": "Feature",
  "properties": {
    "iso:country":"US",
    "sg:address":"128 Texas Way",
    "sg:city":"Fort Worth",
    "sg:classifiers":[
        {
            "category":"Professional",
            "subcategory":"Lawyer & Legal Services",
            "type":"Services"
        }
    ],
    "sg:phone":"+1 817 877 1841",
    "sg:postcode":"76106",
    "sg:province":"TX",
    "sg:tags":[
        "attorney"
    ],
    "wof:name":"Jon Michael Franks",
    "wof:placetype":"venue"
},
  "geometry": {"coordinates":[-97.355727,32.825228],"type":"Point"}
}