{
  "type": "Feature",
  "properties": {
    "iso:country":"US",
    "sg:address":"4444 W Illinois Ave",
    "sg:city":"Dallas",
    "sg:classifiers":[
        {
            "category":"Personal",
            "subcategory":"Beauty Salon",
            "type":"Services"
        }
    ],
    "sg:phone":"+1 214 467 3352",
    "sg:postcode":"75211",
    "sg:province":"TX",
    "sg:tags":[
        "nail",
        "shop"
    ],
    "wof:name":"Today's Nails II",
    "wof:placetype":"venue"
},
  "geometry": {"coordinates":[-96.892799,32.720402],"type":"Point"}
}