{
  "type": "Feature",
  "properties": {
    "iso:country":"US",
    "sg:address":"909 University Blvd",
    "sg:city":"Galveston",
    "sg:classifiers":[
        {
            "category":"Personal",
            "subcategory":"Beauty Salon",
            "type":"Services"
        }
    ],
    "sg:phone":"+1 409 763 6855",
    "sg:postcode":"77550",
    "sg:province":"TX",
    "sg:tags":[
        "hair",
        "shop",
        "stylist"
    ],
    "wof:name":"Diana's Hair Salon",
    "wof:placetype":"venue"
},
  "geometry": {"coordinates":[-94.77297,29.306149],"type":"Point"}
}