{
  "type": "Feature",
  "properties": {
    "iso:country":"US",
    "sg:address":"7508 Fossil Garden Dr",
    "sg:city":"Arlington",
    "sg:classifiers":[
        {
            "category":"Building & Trades",
            "subcategory":"Construction",
            "type":"Services"
        }
    ],
    "sg:phone":"+1 817 417 4827",
    "sg:postcode":"76002",
    "sg:province":"TX",
    "sg:tags":[
        "home",
        "builder"
    ],
    "wof:name":"Plantation Homes",
    "wof:placetype":"venue"
},
  "geometry": {"coordinates":[-97.099795,32.622349],"type":"Point"}
}