{
  "type": "Feature",
  "properties": {
    "iso:country":"US",
    "sg:address":"5435 N Garland Ave",
    "sg:city":"Garland",
    "sg:classifiers":[
        {
            "category":"Real Estate",
            "subcategory":"Real Estate Services",
            "type":"Services"
        }
    ],
    "sg:phone":"+1 214 703 9607",
    "sg:postcode":"75040",
    "sg:province":"TX",
    "sg:tags":[
        "company",
        "title"
    ],
    "wof:name":"North American Title Co",
    "wof:placetype":"venue"
},
  "geometry": {"coordinates":[-96.64302499999999,32.965123],"type":"Point"}
}