{
  "type": "Feature",
  "properties": {
    "iso:country":"US",
    "sg:address":"12095 Converse Rd",
    "sg:city":"Universal City",
    "sg:classifiers":[
        {
            "category":"Organizations",
            "subcategory":"Community Association",
            "type":"Services"
        }
    ],
    "sg:phone":"+1 210 658 8074",
    "sg:postcode":"78148",
    "sg:province":"TX",
    "wof:name":"San Antonio Rose Society",
    "wof:placetype":"venue"
},
  "geometry": {"coordinates":[-98.319211,29.54766],"type":"Point"}
}