{
  "type": "Feature",
  "properties": {
    "iso:country":"US",
    "sg:address":"15104 Linda Ln",
    "sg:city":"Santa Fe",
    "sg:classifiers":[
        {
            "category":"Professional",
            "subcategory":"Business Services",
            "type":"Services"
        }
    ],
    "sg:phone":"+1 409 316 1040",
    "sg:postcode":"77517",
    "sg:province":"TX",
    "sg:tags":[
        "process",
        "server"
    ],
    "wof:name":"Professional Civil Process",
    "wof:placetype":"venue"
},
  "geometry": {"coordinates":[-95.13916999999999,29.363705],"type":"Point"}
}