{
  "type": "Feature",
  "properties": {
    "iso:country":"US",
    "sg:address":"1107 N Kilgore St",
    "sg:city":"Kilgore",
    "sg:classifiers":[
        {
            "category":"Restaurant",
            "type":"Food & Drink"
        }
    ],
    "sg:phone":"+1 903 987 5777",
    "sg:postcode":"75662",
    "sg:province":"TX",
    "wof:name":"Restorant La Laguna",
    "wof:placetype":"venue"
},
  "geometry": {"coordinates":[-94.867732,32.390691],"type":"Point"}
}