{
  "type": "Feature",
  "properties": {
    "iso:country":"US",
    "sg:address":"801 Calhoun St",
    "sg:city":"Rice",
    "sg:classifiers":[
        {
            "category":"Manufacturing",
            "subcategory":"Printing",
            "type":"Manufacturing & Wholesale Goods"
        }
    ],
    "sg:phone":"+1 903 326 4928",
    "sg:postcode":"75155",
    "sg:province":"TX",
    "sg:tags":[
        "newspaper"
    ],
    "wof:name":"Rice City Newsletter",
    "wof:placetype":"venue"
},
  "geometry": {"coordinates":[-96.49078900000001,32.246685],"type":"Point"}
}