{
  "type": "Feature",
  "properties": {
    "iso:country":"US",
    "sg:address":"4023 Green Crest Dr",
    "sg:city":"Houston",
    "sg:classifiers":[
        {
            "category":"Retail",
            "subcategory":"Repair Shop",
            "type":"Services"
        }
    ],
    "sg:phone":"+1 713 917 0906",
    "sg:postcode":"77082",
    "sg:province":"TX",
    "sg:tags":[
        "refrigeration"
    ],
    "wof:name":"Air 1",
    "wof:placetype":"venue"
},
  "geometry": {"coordinates":[-95.65924800000001,29.711765],"type":"Point"}
}