{
  "type": "Feature",
  "properties": {
    "iso:country":"US",
    "sg:address":"1591 Meadowview Dr",
    "sg:city":"Lake Dallas",
    "sg:classifiers":[
        {
            "category":"Manufacturing",
            "subcategory":"Signs",
            "type":"Manufacturing & Wholesale Goods"
        }
    ],
    "sg:phone":"+1 940 497 5505",
    "sg:postcode":"75080",
    "sg:province":"TX",
    "wof:name":"Advanced Lighting Systems Inc",
    "wof:placetype":"venue"
},
  "geometry": {"coordinates":[-96.751803,32.970873],"type":"Point"}
}