{
  "type": "Feature",
  "properties": {
    "iso:country":"US",
    "sg:address":"1629 Circle Dr",
    "sg:city":"Tyler",
    "sg:classifiers":[
        {
            "category":"Wholesale",
            "subcategory":"Vending Machines",
            "type":"Manufacturing & Wholesale Goods"
        }
    ],
    "sg:phone":"+1 903 561 1542",
    "sg:postcode":"75703",
    "sg:province":"TX",
    "sg:tags":[
        "operator"
    ],
    "wof:name":"Cr Vending & Sales",
    "wof:placetype":"venue"
},
  "geometry": {"coordinates":[-95.279461,32.274364],"type":"Point"}
}