{
  "type": "Feature",
  "properties": {
    "iso:country":"US",
    "sg:address":"3410 W Rochelle Rd",
    "sg:city":"Irving",
    "sg:classifiers":[
        {
            "category":"Restaurant",
            "type":"Food & Drink"
        }
    ],
    "sg:phone":"+1 800 225 5532",
    "sg:postcode":"75062",
    "sg:province":"TX",
    "sg:tags":[
        "eating"
    ],
    "sg:website":"http://www.kfc.com",
    "wof:name":"KFC",
    "wof:placetype":"venue"
},
  "geometry": {"coordinates":[-96.99391900000001,32.84763],"type":"Point"}
}