{
  "type": "Feature",
  "properties": {
    "iso:country":"US",
    "sg:address":"10053 Sawmill Rd",
    "sg:city":"Brenham",
    "sg:classifiers":[
        {
            "category":"Wholesale",
            "subcategory":"Farm Supplies",
            "type":"Manufacturing & Wholesale Goods"
        }
    ],
    "sg:phone":"+1 979 830 1550",
    "sg:postcode":"77833",
    "sg:province":"TX",
    "sg:tags":[
        "livestock"
    ],
    "wof:name":"Jacob Ullrich",
    "wof:placetype":"venue"
},
  "geometry": {"coordinates":[-96.532293,30.087926],"type":"Point"}
}