{
  "type": "Feature",
  "properties": {
    "iso:country":"US",
    "sg:address":"5521 Greenwich Dr",
    "sg:city":"Arlington",
    "sg:classifiers":[
        {
            "category":"Building & Trades",
            "subcategory":"Construction",
            "type":"Services"
        }
    ],
    "sg:phone":"+1 817 472 0514",
    "sg:postcode":"76018",
    "sg:province":"TX",
    "sg:tags":[
        "house"
    ],
    "wof:name":"Dads Fix It Service",
    "wof:placetype":"venue"
},
  "geometry": {"coordinates":[-97.097257,32.652035],"type":"Point"}
}