{
  "type": "Feature",
  "properties": {
    "iso:country":"US",
    "sg:address":"2905 Live Oak Dr",
    "sg:city":"Rowlett",
    "sg:classifiers":[
        {
            "category":"Autos & Motor Vehicles",
            "subcategory":"Auto Supplies",
            "type":"Retail Goods"
        }
    ],
    "sg:phone":"+1 972 412 0715",
    "sg:postcode":"75088",
    "sg:province":"TX",
    "sg:tags":[
        "tire"
    ],
    "sg:website":"http://www.efirestone.com",
    "wof:name":"Firestone",
    "wof:placetype":"venue"
},
  "geometry": {"coordinates":[-96.573673,32.887236],"type":"Point"}
}