{
  "type": "Feature",
  "properties": {
    "iso:country":"US",
    "sg:address":"720 Brook Ave",
    "sg:city":"Waco",
    "sg:classifiers":[
        {
            "category":"Education",
            "subcategory":"School",
            "type":"Public Place"
        }
    ],
    "sg:phone":"+1 254 750 3562",
    "sg:postcode":"76708",
    "sg:province":"TX",
    "sg:website":"www.wacoisd.org",
    "wof:name":"Brook Avenue Elementary School",
    "wof:placetype":"venue"
},
  "geometry": {"coordinates":[-97.151554,31.566878],"type":"Point"}
}