{
  "type": "Feature",
  "properties": {
    "iso:country":"US",
    "sg:address":"125 Saddle Club Cir",
    "sg:city":"Boerne",
    "sg:classifiers":[
        {
            "category":"Food & Beverages",
            "subcategory":"Bakery",
            "type":"Retail Goods"
        }
    ],
    "sg:phone":"+1 830 816 2407",
    "sg:postcode":"78006",
    "sg:province":"TX",
    "wof:name":"Baker S Best",
    "wof:placetype":"venue"
},
  "geometry": {"coordinates":[-98.727335,29.782101],"type":"Point"}
}