{
  "type": "Feature",
  "properties": {
    "iso:country":"US",
    "sg:address":"501 Wales Ct",
    "sg:city":"Coppell",
    "sg:classifiers":[
        {
            "category":"Real Estate",
            "subcategory":"Real Estate Operator",
            "type":"Services"
        }
    ],
    "sg:phone":"+1 972 745 7753",
    "sg:postcode":"75019",
    "sg:province":"TX",
    "sg:tags":[
        "apartment"
    ],
    "wof:name":"Creekwood Marketplace",
    "wof:placetype":"venue"
},
  "geometry": {"coordinates":[-96.995507,32.957581],"type":"Point"}
}