{
  "type": "Feature",
  "properties": {
    "iso:country":"US",
    "sg:address":"17655 Waterview Pkwy",
    "sg:city":"Dallas",
    "sg:classifiers":[
        {
            "category":"Professional",
            "subcategory":"Credit Reporting & Collection",
            "type":"Services"
        }
    ],
    "sg:phone":"+1 972 388 3000",
    "sg:postcode":"75252",
    "sg:province":"TX",
    "sg:tags":[
        "datum"
    ],
    "wof:name":"A D S",
    "wof:placetype":"venue"
},
  "geometry": {"coordinates":[-96.756528,32.988481],"type":"Point"}
}