{
  "type": "Feature",
  "properties": {
    "iso:country":"US",
    "sg:address":"3707 Gaston Ave",
    "sg:city":"Dallas",
    "sg:classifiers":[
        {
            "category":"Health Services",
            "subcategory":"Doctor",
            "type":"Services"
        }
    ],
    "sg:phone":"+1 214 824 2547",
    "sg:postcode":"75246",
    "sg:province":"TX",
    "sg:tags":[
        "obstetrician",
        "gynecologist"
    ],
    "wof:name":"Branning George MD PA",
    "wof:placetype":"venue"
},
  "geometry": {"coordinates":[-96.77919799999999,32.792],"type":"Point"}
}