{
  "type": "Feature",
  "properties": {
    "iso:country":"US",
    "sg:address":"5190 E I- 20",
    "sg:city":"Willow Park",
    "sg:classifiers":[
        {
            "category":"Manufacturing",
            "subcategory":"Printing",
            "type":"Manufacturing & Wholesale Goods"
        }
    ],
    "sg:phone":"+1 817 441 7661",
    "sg:postcode":"76008",
    "sg:province":"TX",
    "sg:tags":[
        "newspaper"
    ],
    "sg:website":"www.community-news.com",
    "wof:name":"Community News",
    "wof:placetype":"venue"
},
  "geometry": {"coordinates":[-97.60705400000001,32.729075],"type":"Point"}
}