{
  "type": "Feature",
  "properties": {
    "iso:country":"US",
    "sg:address":"500 Young Ranch Rd",
    "sg:city":"Jonesboro",
    "sg:classifiers":[
        {
            "category":"Farming",
            "subcategory":"Livestock Farm",
            "type":"Manufacturing & Wholesale Goods"
        }
    ],
    "sg:phone":"+1 254 463 4608",
    "sg:postcode":"76538",
    "sg:province":"TX",
    "sg:tags":[
        "animal",
        "general"
    ],
    "wof:name":"5y Land & Cattle Company",
    "wof:placetype":"venue"
},
  "geometry": {"coordinates":[-97.829886,31.566654],"type":"Point"}
}