{
  "type": "Feature",
  "properties": {
    "iso:country":"US",
    "sg:address":"6326 Havendale Dr",
    "sg:city":"Houston",
    "sg:classifiers":[
        {
            "category":"Professional",
            "subcategory":"Art Services",
            "type":"Services"
        }
    ],
    "sg:phone":"+1 281 498 3480",
    "sg:postcode":"77072",
    "sg:province":"TX",
    "sg:tags":[
        "photography",
        "commercial"
    ],
    "wof:name":"Lps",
    "wof:placetype":"venue"
},
  "geometry": {"coordinates":[-95.567475,29.711574],"type":"Point"}
}