{
  "type": "Feature",
  "properties": {
    "iso:country":"US",
    "sg:address":"12720 Cutten Rd",
    "sg:city":"Houston",
    "sg:classifiers":[
        {
            "category":"Autos & Motor Vehicles",
            "subcategory":"Auto Supplies",
            "type":"Retail Goods"
        }
    ],
    "sg:phone":"+1 713 668 9484",
    "sg:postcode":"77066",
    "sg:province":"TX",
    "sg:tags":[
        "automobile",
        "parts",
        "accessory",
        "part",
        "accessories-wholesale",
        "manufacturer"
    ],
    "wof:name":"Frank Supply Co",
    "wof:placetype":"venue"
},
  "geometry": {"coordinates":[-95.530418,29.964041],"type":"Point"}
}