{
  "type": "Feature",
  "properties": {
    "iso:country":"US",
    "sg:address":"117 Guinevere St",
    "sg:city":"Victoria",
    "sg:classifiers":[
        {
            "category":"Retail",
            "subcategory":"Repair Shop",
            "type":"Services"
        }
    ],
    "sg:phone":"+1 361 573 9195",
    "sg:postcode":"77904",
    "sg:province":"TX",
    "wof:name":"Lh Sports Repairs",
    "wof:placetype":"venue"
},
  "geometry": {"coordinates":[-96.99263000000001,28.852625],"type":"Point"}
}