{
  "type": "Feature",
  "properties": {
    "iso:country":"US",
    "sg:address":"4236 Cedar Ridge Dr",
    "sg:city":"Grand Prairie",
    "sg:classifiers":[
        {
            "category":"Building & Trades",
            "subcategory":"Construction",
            "type":"Services"
        }
    ],
    "sg:phone":"+1 972 263 1612",
    "sg:postcode":"75052",
    "sg:province":"TX",
    "sg:tags":[
        "home",
        "builder"
    ],
    "wof:name":"Legacy Homes Westchester",
    "wof:placetype":"venue"
},
  "geometry": {"coordinates":[-97.009281,32.671541],"type":"Point"}
}