{
  "type": "Feature",
  "properties": {
    "iso:country":"US",
    "sg:address":"1202 N Frazier St",
    "sg:city":"Conroe",
    "sg:classifiers":[
        {
            "category":"Restaurant",
            "type":"Food & Drink"
        }
    ],
    "sg:menulink":"http://www.allmenus.com/tx/southeast-montgomery/57413-dixies-bayou-victuals/menu/",
    "sg:phone":"+1 936 441 1177",
    "sg:postcode":"77301",
    "sg:province":"TX",
    "sg:tags":[
        "seafood",
        "american"
    ],
    "wof:name":"Dixie's Bayou Victuals",
    "wof:placetype":"venue"
},
  "geometry": {"coordinates":[-95.464303,30.319933],"type":"Point"}
}