{
  "type": "Feature",
  "properties": {
    "iso:country":"US",
    "sg:address":"743 S Blanco St",
    "sg:city":"Lockhart",
    "sg:classifiers":[
        {
            "category":"Restaurant",
            "type":"Food & Drink"
        }
    ],
    "sg:phone":"+1 512 398 3161",
    "sg:postcode":"78644",
    "sg:province":"TX",
    "wof:name":"Premier Video's & Pizza",
    "wof:placetype":"venue"
},
  "geometry": {"coordinates":[-97.672952,29.876815],"type":"Point"}
}