{
  "type": "Feature",
  "properties": {
    "iso:country":"US",
    "sg:address":"3725 Sandia Dr",
    "sg:city":"Plano",
    "sg:classifiers":[
        {
            "category":"Manufacturing",
            "subcategory":"Building Materials",
            "type":"Manufacturing & Wholesale Goods"
        }
    ],
    "sg:phone":"+1 972 964 0514",
    "sg:postcode":"75023",
    "sg:province":"TX",
    "sg:tags":[
        "mfg"
    ],
    "wof:name":"Sak Wood Creations",
    "wof:placetype":"venue"
},
  "geometry": {"coordinates":[-96.764827,33.045095],"type":"Point"}
}