{
  "type": "Feature",
  "properties": {
    "iso:country":"US",
    "sg:address":"2001 W Northwest Hwy",
    "sg:city":"Grapevine",
    "sg:classifiers":[
        {
            "category":"Real Estate",
            "subcategory":"Real Estate Agent",
            "type":"Services"
        },
        {
            "category":"Real Estate",
            "subcategory":"Real Estate Operator",
            "type":"Services"
        }
    ],
    "sg:phone":"+1 817 416 1907",
    "sg:postcode":"76051",
    "sg:province":"TX",
    "sg:tags":[
        "finding",
        "building",
        "apartment",
        "rental"
    ],
    "wof:name":"Ellis J Apartment Locators",
    "wof:placetype":"venue"
},
  "geometry": {"coordinates":[-97.097171,32.941056],"type":"Point"}
}