{
  "type": "Feature",
  "properties": {
    "iso:country":"US",
    "sg:address":"8908 Ambassador Row",
    "sg:city":"Dallas",
    "sg:classifiers":[
        {
            "category":"Building & Trades",
            "subcategory":"Construction",
            "type":"Services"
        }
    ],
    "sg:phone":"+1 214 415 7995",
    "sg:postcode":"75247",
    "sg:province":"TX",
    "sg:tags":[
        "contractor"
    ],
    "wof:name":"Tng Environmental LLC",
    "wof:placetype":"venue"
},
  "geometry": {"coordinates":[-96.886459,32.8244],"type":"Point"}
}