{
  "type": "Feature",
  "properties": {
    "iso:country":"US",
    "sg:address":"350 Co Rd 606",
    "sg:city":"Tuscola",
    "sg:classifiers":[
        {
            "category":"Farming",
            "subcategory":"Farm & Veterinary Services",
            "type":"Manufacturing & Wholesale Goods"
        }
    ],
    "sg:phone":"+1 325 572 3792",
    "sg:postcode":"79562",
    "sg:province":"TX",
    "sg:tags":[
        "control",
        "weed"
    ],
    "wof:name":"Vince's Tree & Shrub",
    "wof:placetype":"venue"
},
  "geometry": {"coordinates":[-99.98181599999999,32.259101],"type":"Point"}
}