{
  "type": "Feature",
  "properties": {
    "iso:country":"US",
    "sg:address":"3055 Fm 731",
    "sg:city":"Burleson",
    "sg:classifiers":[
        {
            "category":"Shopping",
            "type":"Retail Goods"
        }
    ],
    "sg:phone":"+1 817 295 3388",
    "sg:postcode":"76028",
    "sg:province":"TX",
    "sg:tags":[
        "merchandising"
    ],
    "wof:name":"Let's Go Scootering",
    "wof:placetype":"venue"
},
  "geometry": {"coordinates":[-97.339495,32.477495],"type":"Point"}
}