{
  "type": "Feature",
  "properties": {
    "iso:country":"US",
    "sg:address":"8810 Galena Dr",
    "sg:city":"El Paso",
    "sg:classifiers":[
        {
            "category":"Real Estate",
            "subcategory":"Real Estate Agent",
            "type":"Services"
        }
    ],
    "sg:phone":"+1 915 751 3714",
    "sg:postcode":"79904",
    "sg:province":"TX",
    "wof:name":"Bobbie Waltz Inc",
    "wof:placetype":"venue"
},
  "geometry": {"coordinates":[-106.456351,31.86368],"type":"Point"}
}