{
  "type": "Feature",
  "properties": {
    "iso:country":"US",
    "sg:address":"3755 S Capital of Texas Hwy",
    "sg:city":"Austin",
    "sg:classifiers":[
        {
            "category":"Professional",
            "subcategory":"Computer Services",
            "type":"Services"
        }
    ],
    "sg:phone":"+1 512 329 8027",
    "sg:postcode":"78704",
    "sg:province":"TX",
    "sg:tags":[
        "programing",
        "custom"
    ],
    "wof:name":"Business Management Systems",
    "wof:placetype":"venue"
},
  "geometry": {"coordinates":[-97.801141,30.242843],"type":"Point"}
}