{
  "type": "Feature",
  "properties": {
    "iso:country":"US",
    "sg:address":"1117 Tahoka Rd",
    "sg:city":"Brownfield",
    "sg:classifiers":[
        {
            "category":"Travel",
            "subcategory":"Travel Agent",
            "type":"Entertainment"
        }
    ],
    "sg:phone":"+1 806 637 4830",
    "sg:postcode":"79316",
    "sg:province":"TX",
    "sg:tags":[
        "agency"
    ],
    "wof:name":"Cruise Agency",
    "wof:placetype":"venue"
},
  "geometry": {"coordinates":[-102.263087,33.181139],"type":"Point"}
}