{
  "type": "Feature",
  "properties": {
    "iso:country":"US",
    "sg:address":"525 N Sam Houston Pkwy E Ste 595",
    "sg:city":"Houston",
    "sg:classifiers":[
        {
            "category":"Professional",
            "subcategory":"Employment Agencies",
            "type":"Services"
        }
    ],
    "sg:phone":"+1 713 965 4959",
    "sg:postcode":"77060",
    "sg:province":"TX",
    "wof:name":"Spec Personnel LLC",
    "wof:placetype":"venue"
},
  "geometry": {"coordinates":[-95.39048099999999,29.939117],"type":"Point"}
}