{
  "type": "Feature",
  "properties": {
    "iso:country":"US",
    "sg:address":"4350 Coffeeport Rd",
    "sg:city":"Brownsville",
    "sg:classifiers":[
        {
            "category":"Education",
            "subcategory":"School",
            "type":"Public Place"
        }
    ],
    "sg:phone":"+1 956 831 6030",
    "sg:postcode":"78521",
    "sg:province":"TX",
    "sg:tags":[
        "elementary"
    ],
    "wof:name":"Gonzalez Elementary School",
    "wof:placetype":"venue"
},
  "geometry": {"coordinates":[-97.45434899999999,25.940284],"type":"Point"}
}