{
  "type": "Feature",
  "properties": {
    "iso:country":"US",
    "sg:address":"400 S Henderson St",
    "sg:city":"Fort Worth",
    "sg:classifiers":[
        {
            "category":"Shopping",
            "type":"Retail Goods"
        }
    ],
    "sg:phone":"+1 817 335 2583",
    "sg:postcode":"76104",
    "sg:province":"TX",
    "sg:tags":[
        "aids",
        "hearing",
        "accessory"
    ],
    "wof:name":"Jones Adology Hearing Aid Ctrs",
    "wof:placetype":"venue"
},
  "geometry": {"coordinates":[-97.337772,32.739902],"type":"Point"}
}