{
  "type": "Feature",
  "properties": {
    "iso:country":"US",
    "sg:address":"2314 Bissonnet St",
    "sg:city":"Houston",
    "sg:classifiers":[
        {
            "category":"Professional",
            "subcategory":"Business Services",
            "type":"Services"
        }
    ],
    "sg:phone":"+1 713 529 5428",
    "sg:postcode":"77005",
    "sg:province":"TX",
    "sg:tags":[
        "interior",
        "consultant",
        "design",
        "decorator"
    ],
    "wof:name":"Babs Watkins Design",
    "wof:placetype":"venue"
},
  "geometry": {"coordinates":[-95.414754,29.725596],"type":"Point"}
}