{
  "type": "Feature",
  "properties": {
    "iso:country":"US",
    "sg:address":"6031 19th St",
    "sg:city":"Lubbock",
    "sg:classifiers":[
        {
            "category":"Restaurant",
            "type":"Food & Drink"
        }
    ],
    "sg:menulink":"http://www.allmenus.com/tx/lubbock/130870-subway/menu/",
    "sg:phone":"+1 806 687 5071",
    "sg:postcode":"79407",
    "sg:province":"TX",
    "sg:tags":[
        "american",
        "sandwich"
    ],
    "wof:name":"Subway",
    "wof:placetype":"venue"
},
  "geometry": {"coordinates":[-101.94793300000001,33.577781],"type":"Point"}
}