{
  "type": "Feature",
  "properties": {
    "iso:country":"US",
    "sg:address":"4500 Steiner Ranch Blvd",
    "sg:city":"Austin",
    "sg:classifiers":[
        {
            "category":"Building & Trades",
            "subcategory":"Construction",
            "type":"Services"
        }
    ],
    "sg:phone":"+1 512 266 2916",
    "sg:postcode":"78732",
    "sg:province":"TX",
    "sg:tags":[
        "roofing",
        "contractor"
    ],
    "wof:name":"C &M Construction",
    "wof:placetype":"venue"
},
  "geometry": {"coordinates":[-97.870733,30.390023],"type":"Point"}
}