{
  "type": "Feature",
  "properties": {
    "iso:country":"US",
    "sg:address":"8718 Jones Rd",
    "sg:city":"Houston",
    "sg:classifiers":[
        {
            "category":"Shopping",
            "subcategory":"Used Merchandise",
            "type":"Retail Goods"
        }
    ],
    "sg:phone":"+1 281 890 2615",
    "sg:postcode":"77065",
    "sg:province":"TX",
    "sg:tags":[
        "durable"
    ],
    "wof:name":"That Antique Place",
    "wof:placetype":"venue"
},
  "geometry": {"coordinates":[-95.58441999999999,29.898074],"type":"Point"}
}