{
  "type": "Feature",
  "properties": {
    "iso:country":"US",
    "sg:address":"2430 Country Grace",
    "sg:city":"New Braunfels",
    "sg:classifiers":[
        {
            "category":"Education",
            "subcategory":"School",
            "type":"Public Place"
        }
    ],
    "sg:phone":"+1 830 629 8043",
    "sg:postcode":"78130",
    "sg:province":"TX",
    "wof:name":"South Texas School Nurse Aide",
    "wof:placetype":"venue"
},
  "geometry": {"coordinates":[-98.096996,29.669593],"type":"Point"}
}