{
  "type": "Feature",
  "properties": {
    "iso:country":"US",
    "sg:address":"3111 Midwestern Pkwy",
    "sg:city":"Wichita Falls",
    "sg:classifiers":[
        {
            "category":"Shopping",
            "subcategory":"Shoes",
            "type":"Retail Goods"
        }
    ],
    "sg:phone":"+1 940 692 3566",
    "sg:postcode":"76308",
    "sg:province":"TX",
    "wof:name":"Finish Line",
    "wof:placetype":"venue"
},
  "geometry": {"coordinates":[-98.533765,33.870432],"type":"Point"}
}