{
  "type": "Feature",
  "properties": {
    "iso:country":"US",
    "sg:address":"2812 Cibola Dr",
    "sg:city":"Irving",
    "sg:classifiers":[
        {
            "category":"Farming",
            "subcategory":"Fish & Marine Products",
            "type":"Manufacturing & Wholesale Goods"
        },
        {
            "category":"Retail",
            "subcategory":"Storage",
            "type":"Services"
        }
    ],
    "sg:phone":"+1 469 955 7577",
    "sg:postcode":"75062",
    "sg:province":"TX",
    "sg:tags":[
        "box",
        "boxes-used"
    ],
    "wof:name":"Pennco Container",
    "wof:placetype":"venue"
},
  "geometry": {"coordinates":[-96.997956,32.845099],"type":"Point"}
}