{
  "type": "Feature",
  "properties": {
    "iso:country":"US",
    "sg:address":"12902 Waters Edge Pl",
    "sg:city":"Houston",
    "sg:classifiers":[
        {
            "category":"Building & Trades",
            "subcategory":"Construction",
            "type":"Services"
        }
    ],
    "sg:phone":"+1 713 937 7010",
    "sg:postcode":"77041",
    "sg:province":"TX",
    "sg:tags":[
        "contractor"
    ],
    "sg:website":"http://www.qrb.com",
    "wof:name":"Hacksoft",
    "wof:placetype":"venue"
},
  "geometry": {"coordinates":[-95.604202,29.84647],"type":"Point"}
}