{
  "type": "Feature",
  "properties": {
    "iso:country":"US",
    "sg:address":"8818 Tradeway St",
    "sg:city":"San Antonio",
    "sg:classifiers":[
        {
            "category":"Retail",
            "subcategory":"Portrait Studio",
            "type":"Services"
        }
    ],
    "sg:phone":"+1 210 829 1640",
    "sg:postcode":"78217",
    "sg:province":"TX",
    "sg:tags":[
        "photographer"
    ],
    "wof:name":"Neka Scarbrough Creations",
    "wof:placetype":"venue"
},
  "geometry": {"coordinates":[-98.457425,29.520521],"type":"Point"}
}