{
  "type": "Feature",
  "properties": {
    "iso:country":"US",
    "sg:address":"1501 W Ennis Ave",
    "sg:city":"Ennis",
    "sg:classifiers":[
        {
            "category":"Building & Trades",
            "subcategory":"Equipment Rental",
            "type":"Services"
        }
    ],
    "sg:phone":"+1 972 875 7040",
    "sg:postcode":"75119",
    "sg:province":"TX",
    "wof:name":"Rent-A-Center",
    "wof:placetype":"venue"
},
  "geometry": {"coordinates":[-96.64093099999999,32.320938],"type":"Point"}
}