{
  "type": "Feature",
  "properties": {
    "iso:country":"US",
    "sg:address":"2222 US Hwy 77X Bus",
    "sg:city":"Harlingen",
    "sg:classifiers":[
        {
            "category":"Restaurant",
            "type":"Food & Drink"
        }
    ],
    "sg:phone":"+1 956 428 3354",
    "sg:postcode":"78550",
    "sg:province":"TX",
    "sg:tags":[
        "eating"
    ],
    "wof:name":"Jasons Deli",
    "wof:placetype":"venue"
},
  "geometry": {"coordinates":[-97.71015800000001,26.215004],"type":"Point"}
}