{
  "type": "Feature",
  "properties": {
    "iso:country":"US",
    "sg:address":"505 5th St",
    "sg:city":"Graham",
    "sg:classifiers":[
        {
            "category":"Autos & Motor Vehicles",
            "subcategory":"Fuel & Gas Station",
            "type":"Retail Goods"
        }
    ],
    "sg:phone":"+1 940 549 0780",
    "sg:postcode":"76450",
    "sg:province":"TX",
    "wof:name":"Sonic Oil & Gas LP",
    "wof:placetype":"venue"
},
  "geometry": {"coordinates":[-98.59119200000001,33.109509],"type":"Point"}
}