{
  "type": "Feature",
  "properties": {
    "iso:country":"US",
    "sg:address":"7861 San Jose Rd",
    "sg:city":"El Paso",
    "sg:classifiers":[
        {
            "category":"Recreation",
            "subcategory":"Arcade",
            "type":"Entertainment"
        }
    ],
    "sg:phone":"+1 915 594 9288",
    "sg:postcode":"79915",
    "sg:province":"TX",
    "sg:tags":[
        "casino"
    ],
    "wof:name":"BJP & C Casino Dealer Shcool",
    "wof:placetype":"venue"
},
  "geometry": {"coordinates":[-106.356672,31.732175],"type":"Point"}
}