{
  "type": "Feature",
  "properties": {
    "iso:country":"US",
    "sg:address":"2734 Cody Ave",
    "sg:city":"Leander",
    "sg:classifiers":[
        {
            "category":"Professional",
            "subcategory":"Accounting & Tax Preparation",
            "type":"Services"
        }
    ],
    "sg:phone":"+1 512 267 0067",
    "sg:postcode":"78645",
    "sg:province":"TX",
    "wof:name":"Business Svcs Unlimited",
    "wof:placetype":"venue"
},
  "geometry": {"coordinates":[-98.00408400000001,30.419615],"type":"Point"}
}