{
  "type": "Feature",
  "properties": {
    "iso:country":"US",
    "sg:address":"3716 San Juan Cir",
    "sg:city":"Plano",
    "sg:classifiers":[
        {
            "category":"Wholesale",
            "subcategory":"Groceries",
            "type":"Manufacturing & Wholesale Goods"
        }
    ],
    "sg:phone":"+1 972 596 4248",
    "sg:postcode":"75023",
    "sg:province":"TX",
    "sg:tags":[
        "general"
    ],
    "wof:name":"Mesa Marketing",
    "wof:placetype":"venue"
},
  "geometry": {"coordinates":[-96.76594900000001,33.042478],"type":"Point"}
}