{
  "type": "Feature",
  "properties": {
    "iso:country":"US",
    "sg:address":"538 Longview Dr",
    "sg:city":"Sugar Land",
    "sg:classifiers":[
        {
            "category":"Manufacturing",
            "subcategory":"Printing",
            "type":"Manufacturing & Wholesale Goods"
        }
    ],
    "sg:phone":"+1 281 491 1438",
    "sg:postcode":"77478",
    "sg:province":"TX",
    "sg:tags":[
        "book"
    ],
    "wof:name":"Cohen Communications",
    "wof:placetype":"venue"
},
  "geometry": {"coordinates":[-95.588035,29.619674],"type":"Point"}
}