{
  "type": "Feature",
  "properties": {
    "iso:country":"US",
    "sg:address":"12811 Country Sound",
    "sg:city":"San Antonio",
    "sg:classifiers":[
        {
            "category":"Building & Trades",
            "subcategory":"Plumbing",
            "type":"Services"
        }
    ],
    "sg:phone":"+1 210 344 4522",
    "sg:postcode":"78216",
    "sg:province":"TX",
    "sg:tags":[
        "contractor"
    ],
    "wof:name":"Wedige Plumbing Co",
    "wof:placetype":"venue"
},
  "geometry": {"coordinates":[-98.47589000000001,29.558567],"type":"Point"}
}