{
  "type": "Feature",
  "properties": {
    "iso:country":"US",
    "sg:address":"3407 Wells Branch Pkwy",
    "sg:city":"Austin",
    "sg:classifiers":[
        {
            "category":"Health Services",
            "subcategory":"Doctor",
            "type":"Services"
        }
    ],
    "sg:phone":"+1 512 244 6452",
    "sg:postcode":"78728",
    "sg:province":"TX",
    "sg:tags":[
        "medicine",
        "physician",
        "surgeon",
        "internal"
    ],
    "wof:name":"Medical Clinic",
    "wof:placetype":"venue"
},
  "geometry": {"coordinates":[-97.69589999999999,30.440001],"type":"Point"}
}