{
  "type": "Feature",
  "properties": {
    "iso:country":"US",
    "sg:address":"14902 Preston Rd",
    "sg:city":"Dallas",
    "sg:classifiers":[
        {
            "category":"Shopping",
            "subcategory":"Music",
            "type":"Retail Goods"
        }
    ],
    "sg:phone":"+1 972 404 0276",
    "sg:postcode":"75254",
    "sg:province":"TX",
    "sg:tags":[
        "compact",
        "record",
        "disc",
        "tape"
    ],
    "wof:name":"Wherehouse Music",
    "wof:placetype":"venue"
},
  "geometry": {"coordinates":[-96.80362100000001,32.94985],"type":"Point"}
}