{
  "type": "Feature",
  "properties": {
    "iso:country":"US",
    "sg:address":"500 E 15th St",
    "sg:city":"Hereford",
    "sg:classifiers":[
        {
            "category":"Social Services",
            "type":"Services"
        }
    ],
    "sg:phone":"+1 806 364 6990",
    "sg:postcode":"79045",
    "sg:province":"TX",
    "sg:tags":[
        "organization",
        "welfare"
    ],
    "wof:name":"YMCA-Hereford Inc",
    "wof:placetype":"venue"
},
  "geometry": {"coordinates":[-102.397508,34.83654],"type":"Point"}
}