{
  "type": "Feature",
  "properties": {
    "iso:country":"US",
    "sg:address":"2405 N Preston St",
    "sg:city":"Ennis",
    "sg:classifiers":[
        {
            "category":"Wholesale",
            "subcategory":"Jewelry",
            "type":"Manufacturing & Wholesale Goods"
        }
    ],
    "sg:phone":"+1 972 875 8681",
    "sg:postcode":"75119",
    "sg:province":"TX",
    "sg:tags":[
        "ribbon"
    ],
    "sg:website":"www.finelineribbon.com",
    "wof:name":"Fine Line Ribbon Co",
    "wof:placetype":"venue"
},
  "geometry": {"coordinates":[-96.645471,32.347113],"type":"Point"}
}