{
  "type": "Feature",
  "properties": {
    "iso:country":"US",
    "sg:address":"24400 Canyon Golf Rd",
    "sg:city":"San Antonio",
    "sg:classifiers":[
        {
            "category":"Retail",
            "subcategory":"Event Space",
            "type":"Services"
        },
        {
            "category":"Sports & Exercise",
            "subcategory":"Golf",
            "type":"Entertainment"
        }
    ],
    "sg:phone":"+1 210 497 1770",
    "sg:postcode":"78258",
    "sg:province":"TX",
    "sg:tags":[
        "venue"
    ],
    "sg:website":"www.canyonspringsgc.com",
    "wof:name":"Canyon Springs Golf Club",
    "wof:placetype":"venue"
},
  "geometry": {"coordinates":[-98.479405,29.660025],"type":"Point"}
}