{
  "type": "Feature",
  "properties": {
    "iso:country":"US",
    "sg:address":"2217 Arbor Chase Cir",
    "sg:city":"Arlington",
    "sg:classifiers":[
        {
            "category":"Professional",
            "subcategory":"Management & Consulting",
            "type":"Services"
        }
    ],
    "sg:phone":"+1 817 860 2539",
    "sg:postcode":"76011",
    "sg:province":"TX",
    "sg:tags":[
        "business"
    ],
    "wof:name":"Gerzon Way Consulting LLC",
    "wof:placetype":"venue"
},
  "geometry": {"coordinates":[-97.085818,32.771023],"type":"Point"}
}