{
  "type": "Feature",
  "properties": {
    "iso:country":"US",
    "sg:address":"2704 Spruce St",
    "sg:city":"Kilgore",
    "sg:classifiers":[
        {
            "category":"Real Estate",
            "subcategory":"Surveying",
            "type":"Services"
        }
    ],
    "sg:phone":"+1 903 983 3425",
    "sg:postcode":"75662",
    "sg:province":"TX",
    "sg:tags":[
        "surveyor"
    ],
    "wof:name":"Hedrick Land Surveying Co",
    "wof:placetype":"venue"
},
  "geometry": {"coordinates":[-94.864771,32.362591],"type":"Point"}
}