{
  "type": "Feature",
  "properties": {
    "iso:country":"US",
    "sg:address":"3821 Falcon Dr",
    "sg:city":"Fort Worth",
    "sg:classifiers":[
        {
            "category":"Home & Garden",
            "subcategory":"Hardware",
            "type":"Retail Goods"
        }
    ],
    "sg:phone":"+1 817 534 8365",
    "sg:postcode":"76119",
    "sg:province":"TX",
    "wof:name":"Forest Hill Hardware Inc",
    "wof:placetype":"venue"
},
  "geometry": {"coordinates":[-97.26506000000001,32.668951],"type":"Point"}
}