{
  "type": "Feature",
  "properties": {
    "iso:country":"US",
    "sg:address":"1776 Teasley Ln",
    "sg:city":"Denton",
    "sg:classifiers":[
        {
            "category":"Restaurant",
            "type":"Food & Drink"
        },
        {
            "category":"Donuts",
            "subcategory":"None",
            "type":"Food & Drink"
        }
    ],
    "sg:phone":"+1 940 565 6790",
    "sg:postcode":"76205",
    "sg:province":"TX",
    "sg:tags":[
        "shop"
    ],
    "wof:name":"Teasley Donut",
    "wof:placetype":"venue"
},
  "geometry": {"coordinates":[-97.124469,33.191492],"type":"Point"}
}