{
  "type": "Feature",
  "properties": {
    "iso:country":"US",
    "sg:address":"409 W Bridge St",
    "sg:city":"Weatherford",
    "sg:classifiers":[
        {
            "category":"Personal",
            "type":"Services"
        }
    ],
    "sg:phone":"+1 817 341 0792",
    "sg:postcode":"76086",
    "sg:province":"TX",
    "wof:name":"McNutt Group",
    "wof:placetype":"venue"
},
  "geometry": {"coordinates":[-97.803766,32.761474],"type":"Point"}
}