{
  "type": "Feature",
  "properties": {
    "iso:country":"US",
    "sg:address":"3228 Regal Oaks Ln",
    "sg:city":"Pearland",
    "sg:classifiers":[
        {
            "category":"Home & Garden",
            "subcategory":"Home Furnishings",
            "type":"Retail Goods"
        }
    ],
    "sg:phone":"+1 281 485 6996",
    "sg:postcode":"77581",
    "sg:province":"TX",
    "wof:name":"Lite Up Your Life Lamps",
    "wof:placetype":"venue"
},
  "geometry": {"coordinates":[-95.24888900000001,29.553393],"type":"Point"}
}