{
  "type": "Feature",
  "properties": {
    "iso:country":"US",
    "sg:address":"328 Oakhurst Scenic Dr",
    "sg:city":"Fort Worth",
    "sg:classifiers":[
        {
            "category":"Wholesale",
            "subcategory":"Machinery & Supplies",
            "type":"Manufacturing & Wholesale Goods"
        }
    ],
    "sg:phone":"+1 817 831 1240",
    "sg:postcode":"76111",
    "sg:province":"TX",
    "sg:tags":[
        "tank"
    ],
    "wof:name":"Nortex Inc",
    "wof:placetype":"venue"
},
  "geometry": {"coordinates":[-97.311053,32.769875],"type":"Point"}
}