{
  "type": "Feature",
  "properties": {
    "iso:country":"US",
    "sg:address":"703 Beckley Dr",
    "sg:city":"Midland",
    "sg:classifiers":[
        {
            "category":"Retail",
            "subcategory":"Car Wash",
            "type":"Services"
        }
    ],
    "sg:phone":"+1 432 689 0121",
    "sg:postcode":"79703",
    "sg:province":"TX",
    "sg:tags":[
        "polishing",
        "carwash",
        "washing"
    ],
    "wof:name":"Martha's Car Wash",
    "wof:placetype":"venue"
},
  "geometry": {"coordinates":[-102.12568400000001,31.978604],"type":"Point"}
}