{
  "type": "Feature",
  "properties": {
    "iso:country":"US",
    "sg:address":"7411 Barlite Blvd",
    "sg:city":"San Antonio",
    "sg:classifiers":[
        {
            "category":"Government",
            "subcategory":"Post Office",
            "type":"Public Place"
        }
    ],
    "sg:phone":"+1 210 000 1111",
    "sg:postcode":"78224",
    "sg:province":"TX",
    "wof:name":"US Post Office",
    "wof:placetype":"venue"
},
  "geometry": {"coordinates":[-98.546638,29.352544],"type":"Point"}
}