{
  "type": "Feature",
  "properties": {
    "iso:country":"US",
    "sg:address":"5003 John Stockbauer Dr",
    "sg:city":"Victoria",
    "sg:classifiers":[
        {
            "category":"Food & Beverages",
            "subcategory":"Bakery",
            "type":"Retail Goods"
        }
    ],
    "sg:phone":"+1 361 576 5930",
    "sg:postcode":"77904",
    "sg:province":"TX",
    "sg:tags":[
        "baker"
    ],
    "wof:name":"Betti's Pastries",
    "wof:placetype":"venue"
},
  "geometry": {"coordinates":[-96.949663,28.821667],"type":"Point"}
}