{
  "type": "Feature",
  "properties": {
    "iso:country":"US",
    "sg:address":"1927 S Manhattan St",
    "sg:city":"Amarillo",
    "sg:classifiers":[
        {
            "category":"Wholesale",
            "subcategory":"Hardware",
            "type":"Manufacturing & Wholesale Goods"
        }
    ],
    "sg:phone":"+1 806 342 0034",
    "sg:postcode":"79103",
    "sg:province":"TX",
    "sg:tags":[
        "refrigeration"
    ],
    "wof:name":"Lightning Services",
    "wof:placetype":"venue"
},
  "geometry": {"coordinates":[-101.804106,35.188549],"type":"Point"}
}