{
  "type": "Feature",
  "properties": {
    "iso:country":"US",
    "sg:address":"2005 Commerce St",
    "sg:city":"Belton",
    "sg:classifiers":[
        {
            "category":"Animal Shelter",
            "type":"Public Place"
        },
        {
            "category":"Building & Trades",
            "subcategory":"Pest Control",
            "type":"Services"
        }
    ],
    "sg:phone":"+1 254 773 7977",
    "sg:postcode":"76513",
    "sg:province":"TX",
    "sg:tags":[
        "removal",
        "industrial",
        "services-commercial",
        "termite",
        "bee"
    ],
    "sg:website":"http://www.thebugmaster.com",
    "wof:name":"Bug Master",
    "wof:placetype":"venue"
},
  "geometry": {"coordinates":[-97.465649,31.076837],"type":"Point"}
}