{
  "type": "Feature",
  "properties": {
    "iso:country":"US",
    "sg:address":"14643 Dallas Pkwy Ste 636",
    "sg:city":"Dallas",
    "sg:classifiers":[
        {
            "category":"Real Estate",
            "subcategory":"Architect",
            "type":"Services"
        }
    ],
    "sg:phone":"+1 972 980 8980",
    "sg:postcode":"75254",
    "sg:province":"TX",
    "wof:name":"Meinhardt & Associates",
    "wof:placetype":"venue"
},
  "geometry": {"coordinates":[-96.823808,32.94459],"type":"Point"}
}