{
  "type": "Feature",
  "properties": {
    "iso:country":"US",
    "sg:address":"957 Equestrian Dr",
    "sg:city":"Rockwall",
    "sg:classifiers":[
        {
            "category":"Building & Trades",
            "subcategory":"Construction",
            "type":"Services"
        }
    ],
    "sg:phone":"+1 972 771 9868",
    "sg:postcode":"75032",
    "sg:province":"TX",
    "sg:tags":[
        "hanging",
        "contractor"
    ],
    "wof:name":"Matt Burton",
    "wof:placetype":"venue"
},
  "geometry": {"coordinates":[-96.382998,32.886206],"type":"Point"}
}