{
  "type": "Feature",
  "properties": {
    "iso:country":"US",
    "sg:address":"1147 Kress St",
    "sg:city":"Houston",
    "sg:classifiers":[
        {
            "category":"Education",
            "subcategory":"School",
            "type":"Public Place"
        }
    ],
    "sg:phone":"+1 713 671 3820",
    "sg:postcode":"77020",
    "sg:province":"TX",
    "sg:tags":[
        "high",
        "middle",
        "elementary"
    ],
    "wof:name":"Schools",
    "wof:placetype":"venue"
},
  "geometry": {"coordinates":[-95.307236,29.768341],"type":"Point"}
}