{
  "type": "Feature",
  "properties": {
    "iso:country":"US",
    "sg:address":"20607 Nannette Ln",
    "sg:city":"Spring",
    "sg:classifiers":[
        {
            "category":"Freight",
            "type":"Transportation"
        }
    ],
    "sg:phone":"+1 281 353 1440",
    "sg:postcode":"77388",
    "sg:province":"TX",
    "sg:tags":[
        "operator",
        "local",
        "trucking"
    ],
    "wof:name":"Class Act Trucking Inc",
    "wof:placetype":"venue"
},
  "geometry": {"coordinates":[-95.438295,30.066802],"type":"Point"}
}