{
  "type": "Feature",
  "properties": {
    "iso:country":"US",
    "sg:address":"2019 W Oak St",
    "sg:city":"Palestine",
    "sg:classifiers":[
        {
            "category":"Wholesale",
            "subcategory":"Beer",
            "type":"Manufacturing & Wholesale Goods"
        }
    ],
    "sg:phone":"+1 903 729 1770",
    "sg:postcode":"75801",
    "sg:province":"TX",
    "sg:tags":[
        "ale"
    ],
    "sg:website":"www.benekeith.com",
    "wof:name":"Ben E Keith Co",
    "wof:placetype":"venue"
},
  "geometry": {"coordinates":[-95.653492,31.746643],"type":"Point"}
}