{
  "type": "Feature",
  "properties": {
    "iso:country":"US",
    "sg:address":"612 E Sandy Lake Rd",
    "sg:city":"Coppell",
    "sg:classifiers":[
        {
            "category":"Restaurant",
            "type":"Food & Drink"
        }
    ],
    "sg:phone":"+1 972 393 7272",
    "sg:postcode":"75019",
    "sg:province":"TX",
    "sg:tags":[
        "pizza"
    ],
    "sg:website":"www.papamurphys.com",
    "wof:name":"Papa Murphy's",
    "wof:placetype":"venue"
},
  "geometry": {"coordinates":[-96.976663,32.969558],"type":"Point"}
}