{
  "type": "Feature",
  "properties": {
    "iso:country":"US",
    "sg:address":"121 S 7th St",
    "sg:city":"Mathis",
    "sg:classifiers":[
        {
            "category":"Education",
            "subcategory":"Special Training",
            "type":"Public Place"
        }
    ],
    "sg:phone":"+1 361 547 0783",
    "sg:postcode":"78368",
    "sg:province":"TX",
    "sg:tags":[
        "kindergarten",
        "center",
        "preschool"
    ],
    "wof:name":"CDI Head Start New Horizons",
    "wof:placetype":"venue"
},
  "geometry": {"coordinates":[-97.83448799999999,28.098603],"type":"Point"}
}