{
  "type": "Feature",
  "properties": {
    "iso:country":"US",
    "sg:address":"1601 S Mo Pac Expy",
    "sg:city":"Austin",
    "sg:classifiers":[
        {
            "category":"Banks & Credit Unions",
            "subcategory":"Financial Services",
            "type":"Services"
        }
    ],
    "sg:phone":"+1 512 306 9312",
    "sg:postcode":"78746",
    "sg:province":"TX",
    "sg:tags":[
        "card-merchant"
    ],
    "sg:website":"http://www.americanexpress.com",
    "wof:name":"American Express",
    "wof:placetype":"venue"
},
  "geometry": {"coordinates":[-97.790886,30.261389],"type":"Point"}
}