{
  "type": "Feature",
  "properties": {
    "iso:country":"US",
    "sg:address":"3608 N Navarro St",
    "sg:city":"Victoria",
    "sg:classifiers":[
        {
            "category":"Building & Trades",
            "subcategory":"Construction",
            "type":"Services"
        }
    ],
    "sg:phone":"+1 361 575 0224",
    "sg:postcode":"77901",
    "sg:province":"TX",
    "sg:tags":[
        "contractor"
    ],
    "wof:name":"Puckett Lumber & Construction",
    "wof:placetype":"venue"
},
  "geometry": {"coordinates":[-97.001047,28.829766],"type":"Point"}
}