{
  "type": "Feature",
  "properties": {
    "iso:country":"US",
    "sg:address":"6015 Berkshire Ln",
    "sg:city":"Dallas",
    "sg:classifiers":[
        {
            "category":"Health Services",
            "subcategory":"Chiropractor",
            "type":"Services"
        }
    ],
    "sg:phone":"+1 214 696 3500",
    "sg:postcode":"75225",
    "sg:province":"TX",
    "wof:name":"Ahee S Luke Dr",
    "wof:placetype":"venue"
},
  "geometry": {"coordinates":[-96.807726,32.86502],"type":"Point"}
}