{
  "type": "Feature",
  "properties": {
    "iso:country":"US",
    "sg:address":"19126 Enchanted Oaks Dr",
    "sg:city":"Spring",
    "sg:classifiers":[
        {
            "category":"Shopping",
            "subcategory":"Florist",
            "type":"Retail Goods"
        }
    ],
    "sg:phone":"+1 281 355 9797",
    "sg:postcode":"77388",
    "sg:province":"TX",
    "wof:name":"Belladonna",
    "wof:placetype":"venue"
},
  "geometry": {"coordinates":[-95.433286,30.043898],"type":"Point"}
}