{
  "type": "Feature",
  "properties": {
    "iso:country":"US",
    "sg:address":"3201 Berry Holw",
    "sg:city":"Melissa",
    "sg:classifiers":[
        {
            "category":"Manufacturing",
            "subcategory":"Food",
            "type":"Manufacturing & Wholesale Goods"
        }
    ],
    "sg:phone":"+1 972 837 4305",
    "sg:postcode":"75454",
    "sg:province":"TX",
    "sg:tags":[
        "product"
    ],
    "wof:name":"Java Flakes, Inc",
    "wof:placetype":"venue"
},
  "geometry": {"coordinates":[-96.554699,33.276466],"type":"Point"}
}