{
  "type": "Feature",
  "properties": {
    "iso:country":"US",
    "sg:address":"1920 Treble Dr",
    "sg:city":"Humble",
    "sg:classifiers":[
        {
            "category":"Retail",
            "subcategory":"Laundry & Dry Cleaning",
            "type":"Services"
        }
    ],
    "sg:phone":"+1 281 540 8180",
    "sg:postcode":"77338",
    "sg:province":"TX",
    "sg:tags":[
        "water",
        "restoration",
        "damage"
    ],
    "wof:name":"SERVPRO of The Woodland/Conroe",
    "wof:placetype":"venue"
},
  "geometry": {"coordinates":[-95.24521300000001,29.994339],"type":"Point"}
}