{
  "type": "Feature",
  "properties": {
    "iso:country":"US",
    "sg:address":"5003 John Stockbauer Dr",
    "sg:city":"Victoria",
    "sg:classifiers":[
        {
            "category":"Personal",
            "subcategory":"Beauty Salon",
            "type":"Services"
        }
    ],
    "sg:phone":"+1 361 573 3300",
    "sg:postcode":"77904",
    "sg:province":"TX",
    "sg:tags":[
        "shop"
    ],
    "wof:name":"Electric Tans Salon",
    "wof:placetype":"venue"
},
  "geometry": {"coordinates":[-96.949663,28.821667],"type":"Point"}
}