{
  "type": "Feature",
  "properties": {
    "iso:country":"US",
    "sg:address":"2737 S Broadway Ave",
    "sg:city":"Tyler",
    "sg:classifiers":[
        {
            "category":"Health Services",
            "subcategory":"Medical Lab",
            "type":"Services"
        }
    ],
    "sg:phone":"+1 903 533 8456",
    "sg:postcode":"75701",
    "sg:province":"TX",
    "sg:tags":[
        "laboratory"
    ],
    "wof:name":"Mes",
    "wof:placetype":"venue"
},
  "geometry": {"coordinates":[-95.300707,32.316283],"type":"Point"}
}