{
  "type": "Feature",
  "properties": {
    "iso:country":"US",
    "sg:address":"3920 Charlton Ave",
    "sg:city":"Waco",
    "sg:classifiers":[
        {
            "category":"Building & Trades",
            "subcategory":"Pest Control",
            "type":"Services"
        }
    ],
    "sg:phone":"+1 254 715 8423",
    "sg:postcode":"76711",
    "sg:province":"TX",
    "wof:name":"Brown Termite & Pest Control",
    "wof:placetype":"venue"
},
  "geometry": {"coordinates":[-97.151456,31.517827],"type":"Point"}
}