{
  "type": "Feature",
  "properties": {
    "iso:country":"US",
    "sg:address":"421 Sugar Mill",
    "sg:city":"Cedar Hill",
    "sg:classifiers":[
        {
            "category":"Shopping",
            "type":"Retail Goods"
        }
    ],
    "sg:phone":"+1 972 299 0063",
    "sg:postcode":"75104",
    "sg:province":"TX",
    "sg:tags":[
        "merchandise"
    ],
    "wof:name":"Tara Y Peters",
    "wof:placetype":"venue"
},
  "geometry": {"coordinates":[-96.950102,32.610772],"type":"Point"}
}