{
  "type": "Feature",
  "properties": {
    "iso:country":"US",
    "sg:address":"1312 Travis St",
    "sg:city":"Orange",
    "sg:classifiers":[
        {
            "category":"Building & Trades",
            "subcategory":"Plumbing",
            "type":"Services"
        }
    ],
    "sg:phone":"+1 409 883 8358",
    "sg:postcode":"77630",
    "sg:province":"TX",
    "sg:tags":[
        "contractor"
    ],
    "wof:name":"Long Air Cond Serv Orange",
    "wof:placetype":"venue"
},
  "geometry": {"coordinates":[-93.743627,30.077462],"type":"Point"}
}