{
  "type": "Feature",
  "properties": {
    "iso:country":"US",
    "sg:address":"3114 Plantation Rd",
    "sg:city":"Austin",
    "sg:classifiers":[
        {
            "category":"Travel",
            "subcategory":"Travel Agent",
            "type":"Entertainment"
        }
    ],
    "sg:phone":"+1 512 282 2054",
    "sg:postcode":"78745",
    "sg:province":"TX",
    "sg:tags":[
        "operator",
        "tour",
        "tours",
        "promoter"
    ],
    "wof:name":"Blue Sky Wellness & Adventure",
    "wof:placetype":"venue"
},
  "geometry": {"coordinates":[-97.83121300000001,30.198767],"type":"Point"}
}