{
  "type": "Feature",
  "properties": {
    "iso:country":"US",
    "sg:address":"3178 Co Rd 343",
    "sg:city":"Forestburg",
    "sg:classifiers":[
        {
            "category":"Recreation",
            "type":"Entertainment"
        }
    ],
    "sg:phone":"+1 940 964 2301",
    "sg:postcode":"76239",
    "sg:province":"TX",
    "sg:tags":[
        "concessionaire"
    ],
    "wof:name":"Fillin Station",
    "wof:placetype":"venue"
},
  "geometry": {"coordinates":[-97.468403,33.550637],"type":"Point"}
}