{
  "type": "Feature",
  "properties": {
    "iso:country":"US",
    "sg:address":"1701 N Greenville Ave Ste 1105",
    "sg:city":"Richardson",
    "sg:classifiers":[
        {
            "category":"Professional",
            "subcategory":"Accounting & Tax Preparation",
            "type":"Services"
        }
    ],
    "sg:phone":"+1 972 231 2538",
    "sg:postcode":"75081",
    "sg:province":"TX",
    "sg:tags":[
        "accountant"
    ],
    "wof:name":"Westerfield Brenda K CPA",
    "wof:placetype":"venue"
},
  "geometry": {"coordinates":[-96.716202,32.9715],"type":"Point"}
}