{
  "type": "Feature",
  "properties": {
    "iso:country":"US",
    "sg:address":"8205 Broussard Rd",
    "sg:city":"Beaumont",
    "sg:classifiers":[
        {
            "category":"Organizations",
            "subcategory":"Religious Organization",
            "type":"Services"
        }
    ],
    "sg:phone":"+1 409 892 4140",
    "sg:postcode":"77713",
    "sg:province":"TX",
    "sg:tags":[
        "church"
    ],
    "wof:name":"Voth First Baptist Church",
    "wof:placetype":"venue"
},
  "geometry": {"coordinates":[-94.204419,30.175007],"type":"Point"}
}