{
  "type": "Feature",
  "properties": {
    "iso:country":"US",
    "sg:address":"3019 San Bernardo Ave",
    "sg:city":"Laredo",
    "sg:classifiers":[
        {
            "category":"Professional",
            "type":"Services"
        }
    ],
    "sg:phone":"+1 956 725 7164",
    "sg:postcode":"78040",
    "sg:province":"TX",
    "wof:name":"Creations Forever",
    "wof:placetype":"venue"
},
  "geometry": {"coordinates":[-99.504345,27.527064],"type":"Point"}
}