{
  "type": "Feature",
  "properties": {
    "iso:country":"US",
    "sg:address":"11539 Lakewood Pl",
    "sg:city":"Houston",
    "sg:classifiers":[
        {
            "category":"Shopping",
            "subcategory":"Hobbies, Toys, & Games",
            "type":"Retail Goods"
        }
    ],
    "sg:phone":"+1 281 370 3091",
    "sg:postcode":"77070",
    "sg:province":"TX",
    "sg:tags":[
        "model",
        "supply"
    ],
    "wof:name":"House Of Squire",
    "wof:placetype":"venue"
},
  "geometry": {"coordinates":[-95.591695,29.982753],"type":"Point"}
}