{
  "type": "Feature",
  "properties": {
    "iso:country":"US",
    "sg:address":"8641 Moers Rd",
    "sg:city":"Houston",
    "sg:classifiers":[
        {
            "category":"Manufacturing",
            "subcategory":"Tools & Machinery",
            "type":"Manufacturing & Wholesale Goods"
        }
    ],
    "sg:phone":"+1 713 941 6639",
    "sg:postcode":"77075",
    "sg:province":"TX",
    "sg:tags":[
        "field",
        "fitting",
        "mfg"
    ],
    "wof:name":"Hydril Company",
    "wof:placetype":"venue"
},
  "geometry": {"coordinates":[-95.262434,29.641502],"type":"Point"}
}