{
  "type": "Feature",
  "properties": {
    "iso:country":"US",
    "sg:address":"134 Hillview Dr",
    "sg:city":"San Antonio",
    "sg:classifiers":[
        {
            "category":"Organizations",
            "subcategory":"Religious Organization",
            "type":"Services"
        }
    ],
    "sg:phone":"+1 210 822 2032",
    "sg:postcode":"78209",
    "sg:province":"TX",
    "wof:name":"Temple Hill Holdings LLC",
    "wof:placetype":"venue"
},
  "geometry": {"coordinates":[-98.457116,29.509374],"type":"Point"}
}