{
  "type": "Feature",
  "properties": {
    "iso:country":"US",
    "sg:address":"1739 Citadel Plz",
    "sg:city":"San Antonio",
    "sg:classifiers":[
        {
            "category":"Insurance",
            "subcategory":"Insurance Agent",
            "type":"Services"
        }
    ],
    "sg:phone":"+1 210 821 5080",
    "sg:postcode":"78209",
    "sg:province":"TX",
    "wof:name":"Abbott Insurance",
    "wof:placetype":"venue"
},
  "geometry": {"coordinates":[-98.467067,29.514526],"type":"Point"}
}