{
  "type": "Feature",
  "properties": {
    "iso:country":"US",
    "sg:address":"2305 Gulf Fwy S",
    "sg:city":"League City",
    "sg:classifiers":[
        {
            "category":"Wholesale",
            "subcategory":"Electrical",
            "type":"Manufacturing & Wholesale Goods"
        }
    ],
    "sg:phone":"+1 281 338 9180",
    "sg:postcode":"77573",
    "sg:province":"TX",
    "sg:tags":[
        "equipment"
    ],
    "wof:name":"Summers Group Inc",
    "wof:placetype":"venue"
},
  "geometry": {"coordinates":[-95.100593,29.479295],"type":"Point"}
}