{
  "type": "Feature",
  "properties": {
    "iso:country":"US",
    "sg:address":"520 Gulf Bank Rd",
    "sg:city":"Houston",
    "sg:classifiers":[
        {
            "category":"Real Estate",
            "subcategory":"Real Estate Operator",
            "type":"Services"
        }
    ],
    "sg:phone":"+1 281 448 1118",
    "sg:postcode":"77037",
    "sg:province":"TX",
    "sg:tags":[
        "mobile",
        "home",
        "site"
    ],
    "wof:name":"Westfield Mfg MBL HM Pk",
    "wof:placetype":"venue"
},
  "geometry": {"coordinates":[-95.38773399999999,29.88939],"type":"Point"}
}