{
  "type": "Feature",
  "properties": {
    "iso:country":"US",
    "sg:address":"10115 Sable Trail Ct",
    "sg:city":"Houston",
    "sg:classifiers":[
        {
            "category":"Professional",
            "type":"Services"
        }
    ],
    "sg:phone":"+1 281 970 2079",
    "sg:postcode":"77064",
    "sg:province":"TX",
    "wof:name":"Noway2lose Co",
    "wof:placetype":"venue"
},
  "geometry": {"coordinates":[-95.563489,29.921225],"type":"Point"}
}