{
  "type": "Feature",
  "properties": {
    "iso:country":"US",
    "sg:address":"10461 Commerce Row",
    "sg:city":"Montgomery",
    "sg:classifiers":[
        {
            "category":"Building & Trades",
            "subcategory":"Plumbing",
            "type":"Services"
        }
    ],
    "sg:phone":"+1 936 597 4445",
    "sg:postcode":"77356",
    "sg:province":"TX",
    "sg:tags":[
        "heating",
        "contractor"
    ],
    "wof:name":"Downs Keith AC & Htg",
    "wof:placetype":"venue"
},
  "geometry": {"coordinates":[-95.663037,30.387818],"type":"Point"}
}