{
  "type": "Feature",
  "properties": {
    "iso:country":"US",
    "sg:address":"2442 Westmoreland St",
    "sg:city":"Abilene",
    "sg:classifiers":[
        {
            "category":"Building & Trades",
            "subcategory":"Construction",
            "type":"Services"
        }
    ],
    "sg:phone":"+1 325 672 1440",
    "sg:postcode":"79603",
    "sg:province":"TX",
    "sg:tags":[
        "concrete",
        "contractor"
    ],
    "wof:name":"Johnnys Concrete Construction",
    "wof:placetype":"venue"
},
  "geometry": {"coordinates":[-99.75236599999999,32.476823],"type":"Point"}
}