{
  "type": "Feature",
  "properties": {
    "iso:country":"US",
    "sg:address":"1005 S Highway 183",
    "sg:city":"Leander",
    "sg:classifiers":[
        {
            "category":"Restaurant",
            "type":"Food & Drink"
        }
    ],
    "sg:phone":"+1 512 259 4700",
    "sg:postcode":"78641",
    "sg:province":"TX",
    "wof:name":"New Burger Central The",
    "wof:placetype":"venue"
},
  "geometry": {"coordinates":[-97.869974,30.640066],"type":"Point"}
}