{
  "type": "Feature",
  "properties": {
    "iso:country":"US",
    "sg:address":"2220 Morriss Ct",
    "sg:city":"Flower Mound",
    "sg:classifiers":[
        {
            "category":"Retail",
            "subcategory":"Laundry & Dry Cleaning",
            "type":"Services"
        }
    ],
    "sg:phone":"+1 972 355 1266",
    "sg:postcode":"75028",
    "sg:province":"TX",
    "wof:name":"Dfw Mighty Clean",
    "wof:placetype":"venue"
},
  "geometry": {"coordinates":[-97.06380799999999,33.051248],"type":"Point"}
}