{
  "type": "Feature",
  "properties": {
    "iso:country":"US",
    "sg:address":"35826 Post Oak Cir",
    "sg:city":"Magnolia",
    "sg:classifiers":[
        {
            "category":"Building & Trades",
            "subcategory":"Construction",
            "type":"Services"
        }
    ],
    "sg:phone":"+1 281 259 8409",
    "sg:postcode":"77355",
    "sg:province":"TX",
    "sg:tags":[
        "house"
    ],
    "wof:name":"Hawthorne Barns Buildings LLC",
    "wof:placetype":"venue"
},
  "geometry": {"coordinates":[-95.70178199999999,30.167323],"type":"Point"}
}