{
  "type": "Feature",
  "properties": {
    "iso:country":"US",
    "sg:address":"6803 S Flores St",
    "sg:city":"San Antonio",
    "sg:classifiers":[
        {
            "category":"Autos & Motor Vehicles",
            "subcategory":"Automobile Sales",
            "type":"Retail Goods"
        }
    ],
    "sg:phone":"+1 210 927 7697",
    "sg:postcode":"78221",
    "sg:province":"TX",
    "sg:tags":[
        "used"
    ],
    "wof:name":"L&N Motors",
    "wof:placetype":"venue"
},
  "geometry": {"coordinates":[-98.48914499999999,29.352223],"type":"Point"}
}