{
  "type": "Feature",
  "properties": {
    "iso:country":"US",
    "sg:address":"4415 Hudson Bend Rd",
    "sg:city":"Austin",
    "sg:classifiers":[
        {
            "category":"Arena",
            "subcategory":"Sports Club",
            "type":"Entertainment"
        }
    ],
    "sg:phone":"+1 512 266 0033",
    "sg:postcode":"78734",
    "sg:province":"TX",
    "wof:name":"J 24 Class Association",
    "wof:placetype":"venue"
},
  "geometry": {"coordinates":[-97.92638599999999,30.407854],"type":"Point"}
}