{
  "type": "Feature",
  "properties": {
    "iso:country":"US",
    "sg:address":"542 Haggard St",
    "sg:city":"Plano",
    "sg:classifiers":[
        {
            "category":"Professional",
            "subcategory":"Management & Consulting",
            "type":"Services"
        }
    ],
    "sg:phone":"+1 972 281 0070",
    "sg:postcode":"75074",
    "sg:province":"TX",
    "sg:tags":[
        "break",
        "coffee",
        "supply"
    ],
    "wof:name":"True Brew Coffee & Espresso",
    "wof:placetype":"venue"
},
  "geometry": {"coordinates":[-96.707066,33.026275],"type":"Point"}
}