{
  "type": "Feature",
  "properties": {
    "iso:country":"US",
    "sg:address":"533 S Jackson St",
    "sg:city":"Jacksonville",
    "sg:classifiers":[
        {
            "category":"Autos & Motor Vehicles",
            "subcategory":"Automobile Sales",
            "type":"Retail Goods"
        }
    ],
    "sg:phone":"+1 903 586 4412",
    "sg:postcode":"75766",
    "sg:province":"TX",
    "sg:tags":[
        "new",
        "used",
        "sales"
    ],
    "wof:name":"Pelpier Chevrolet Pontiac",
    "wof:placetype":"venue"
},
  "geometry": {"coordinates":[-95.269355,31.961185],"type":"Point"}
}