{
  "type": "Feature",
  "properties": {
    "iso:country":"US",
    "sg:address":"3404 Halifax St",
    "sg:city":"Dallas",
    "sg:classifiers":[
        {
            "category":"Ice Cream",
            "type":"Food & Drink"
        }
    ],
    "sg:menulink":"http://www.allmenus.com/tx/northeast/242731-baskin-robbins/menu/",
    "sg:phone":"+1 214 905 5003",
    "sg:postcode":"75247",
    "sg:province":"TX",
    "sg:tags":[
        "american"
    ],
    "wof:name":"Baskin-Robbins",
    "wof:placetype":"venue"
},
  "geometry": {"coordinates":[-96.876617,32.811476],"type":"Point"}
}