{
  "type": "Feature",
  "properties": {
    "iso:country":"US",
    "sg:address":"618 N Britain Rd",
    "sg:city":"Irving",
    "sg:classifiers":[
        {
            "category":"Professional",
            "subcategory":"Lawyer & Legal Services",
            "type":"Services"
        }
    ],
    "sg:phone":"+1 972 445 1212",
    "sg:postcode":"75061",
    "sg:province":"TX",
    "sg:tags":[
        "naturalization",
        "immigration"
    ],
    "sg:website":"www.ecsagroup.com",
    "wof:name":"El Centro Hispano",
    "wof:placetype":"venue"
},
  "geometry": {"coordinates":[-96.942356,32.818848],"type":"Point"}
}