{
  "type": "Feature",
  "properties": {
    "iso:country":"US",
    "sg:address":"4105 Pinehurst Dr",
    "sg:city":"Taylor",
    "sg:classifiers":[
        {
            "category":"Professional",
            "type":"Services"
        }
    ],
    "sg:phone":"+1 512 365 1756",
    "sg:postcode":"76574",
    "sg:province":"TX",
    "wof:name":"Sandy Hirt",
    "wof:placetype":"venue"
},
  "geometry": {"coordinates":[-97.430567,30.593498],"type":"Point"}
}