{
  "type": "Feature",
  "properties": {
    "iso:country":"US",
    "sg:address":"5555 Morningside Dr",
    "sg:city":"Houston",
    "sg:classifiers":[
        {
            "category":"Wholesale",
            "subcategory":"Apparel",
            "type":"Manufacturing & Wholesale Goods"
        },
        {
            "category":"Manufacturing",
            "subcategory":"Apparel",
            "type":"Manufacturing & Wholesale Goods"
        }
    ],
    "sg:phone":"+1 713 523 2485",
    "sg:postcode":"77005",
    "sg:province":"TX",
    "sg:tags":[
        "clothing",
        "mfg"
    ],
    "wof:name":"Bingham Bill Do It Now Co",
    "wof:placetype":"venue"
},
  "geometry": {"coordinates":[-95.414835,29.715471],"type":"Point"}
}