{
  "type": "Feature",
  "properties": {
    "iso:country":"US",
    "sg:address":"160 Ebony St",
    "sg:city":"San Benito",
    "sg:classifiers":[
        {
            "category":"Insurance",
            "subcategory":"Insurance Agent",
            "type":"Services"
        }
    ],
    "sg:phone":"+1 956 361 7272",
    "sg:postcode":"78586",
    "sg:province":"TX",
    "sg:tags":[
        "adjuster"
    ],
    "wof:name":"Brush Country Claims Svc",
    "wof:placetype":"venue"
},
  "geometry": {"coordinates":[-97.656491,26.143581],"type":"Point"}
}