{
  "type": "Feature",
  "properties": {
    "iso:country":"US",
    "sg:address":"17111 Meadow Heights Dr",
    "sg:city":"Houston",
    "sg:classifiers":[
        {
            "category":"Manufacturing",
            "subcategory":"Rubber & Plastics",
            "type":"Manufacturing & Wholesale Goods"
        }
    ],
    "sg:phone":"+1 281 859 7080",
    "sg:postcode":"77095",
    "sg:province":"TX",
    "sg:tags":[
        "belting",
        "supply"
    ],
    "wof:name":"Gates Rubber Co",
    "wof:placetype":"venue"
},
  "geometry": {"coordinates":[-95.66922700000001,29.890611],"type":"Point"}
}