{
  "type": "Feature",
  "properties": {
    "iso:country":"US",
    "sg:address":"12319 Adams Run Dr",
    "sg:city":"Cypress",
    "sg:classifiers":[
        {
            "category":"Building & Trades",
            "subcategory":"Construction",
            "type":"Services"
        }
    ],
    "sg:phone":"+1 713 461 5161",
    "sg:postcode":"77429",
    "sg:province":"TX",
    "sg:tags":[
        "contractor"
    ],
    "wof:name":"A Certfied Hot Roof Specialist",
    "wof:placetype":"venue"
},
  "geometry": {"coordinates":[-95.640281,29.948196],"type":"Point"}
}