{
  "type": "Feature",
  "properties": {
    "iso:country":"US",
    "sg:address":"401 Coke Ave",
    "sg:city":"Hillsboro",
    "sg:classifiers":[
        {
            "category":"Shopping",
            "subcategory":"Department Store",
            "type":"Retail Goods"
        }
    ],
    "sg:phone":"+1 254 582 2523",
    "sg:postcode":"76645",
    "sg:province":"TX",
    "sg:tags":[
        "grocery"
    ],
    "wof:name":"Wal-Mart",
    "wof:placetype":"venue"
},
  "geometry": {"coordinates":[-97.09872,32.007652],"type":"Point"}
}