{
  "type": "Feature",
  "properties": {
    "iso:country":"US",
    "sg:address":"403 W Wallace St",
    "sg:city":"San Saba",
    "sg:classifiers":[
        {
            "category":"Health Services",
            "subcategory":"Doctor",
            "type":"Services"
        }
    ],
    "sg:phone":"+1 325 372 5701",
    "sg:postcode":"76877",
    "sg:province":"TX",
    "sg:tags":[
        "physician",
        "surgeon"
    ],
    "wof:name":"One Source Health Ctr-San Saba",
    "wof:placetype":"venue"
},
  "geometry": {"coordinates":[-98.722945,31.195689],"type":"Point"}
}