{
  "type": "Feature",
  "properties": {
    "iso:country":"US",
    "sg:address":"6330 E Mockingbird Ln",
    "sg:city":"Dallas",
    "sg:classifiers":[
        {
            "category":"Shopping",
            "subcategory":"Crafts & Fabrics",
            "type":"Retail Goods"
        }
    ],
    "sg:phone":"+1 214 821 4520",
    "sg:postcode":"75214",
    "sg:province":"TX",
    "sg:tags":[
        "store"
    ],
    "wof:name":"Jo-Ann Fabrics & Crafts",
    "wof:placetype":"venue"
},
  "geometry": {"coordinates":[-96.754898,32.8363],"type":"Point"}
}