{
  "type": "Feature",
  "properties": {
    "iso:country":"US",
    "sg:address":"4600 Olsen Blvd",
    "sg:city":"Amarillo",
    "sg:classifiers":[
        {
            "category":"Real Estate",
            "subcategory":"Real Estate Agent",
            "type":"Services"
        },
        {
            "category":"Professional",
            "subcategory":"Business Services",
            "type":"Services"
        }
    ],
    "sg:phone":"+1 806 352 7241",
    "sg:postcode":"79106",
    "sg:province":"TX",
    "sg:tags":[
        "inspection"
    ],
    "wof:name":"T E X Inspect Jim Man",
    "wof:placetype":"venue"
},
  "geometry": {"coordinates":[-101.891893,35.187311],"type":"Point"}
}