{
  "type": "Feature",
  "properties": {
    "iso:country":"US",
    "sg:address":"1500 Coryell Ct",
    "sg:city":"Southlake",
    "sg:classifiers":[
        {
            "category":"Professional",
            "type":"Services"
        }
    ],
    "sg:phone":"+1 817 416 1094",
    "sg:postcode":"76092",
    "sg:province":"TX",
    "wof:name":"James Galloway Inc",
    "wof:placetype":"venue"
},
  "geometry": {"coordinates":[-97.17214199999999,32.9484],"type":"Point"}
}