{
  "type": "Feature",
  "properties": {
    "iso:country":"US",
    "sg:address":"1515 W 6th St",
    "sg:city":"Austin",
    "sg:classifiers":[
        {
            "category":"Real Estate",
            "subcategory":"Architect",
            "type":"Services"
        }
    ],
    "sg:phone":"+1 512 472 0888",
    "sg:postcode":"78703",
    "sg:province":"TX",
    "sg:tags":[
        "architects'",
        "builders'"
    ],
    "wof:name":"Texas Four",
    "wof:placetype":"venue"
},
  "geometry": {"coordinates":[-97.76203599999999,30.274583],"type":"Point"}
}