{
  "type": "Feature",
  "properties": {
    "iso:country":"US",
    "sg:address":"4800 Texoma Pkwy",
    "sg:city":"Sherman",
    "sg:classifiers":[
        {
            "category":"Shopping",
            "subcategory":"Clothing, Apparel, & Fashions",
            "type":"Retail Goods"
        }
    ],
    "sg:phone":"+1 903 870 0543",
    "sg:postcode":"75090",
    "sg:province":"TX",
    "wof:name":"Old Navy",
    "wof:placetype":"venue"
},
  "geometry": {"coordinates":[-96.58098,33.687988],"type":"Point"}
}