{
  "type": "Feature",
  "properties": {
    "iso:country":"US",
    "sg:address":"7104 Majorca Ct",
    "sg:city":"El Paso",
    "sg:classifiers":[
        {
            "category":"Shopping",
            "subcategory":"Catalog Store",
            "type":"Retail Goods"
        }
    ],
    "sg:phone":"+1 915 581 4188",
    "sg:postcode":"79912",
    "sg:province":"TX",
    "sg:tags":[
        "automobile",
        "customizing"
    ],
    "wof:name":"Dealer Specialties of El Paso",
    "wof:placetype":"venue"
},
  "geometry": {"coordinates":[-106.552482,31.843027],"type":"Point"}
}