{
  "type": "Feature",
  "properties": {
    "iso:country":"US",
    "sg:address":"4600 Bosque Blvd",
    "sg:city":"Waco",
    "sg:classifiers":[
        {
            "category":"Professional",
            "subcategory":"Lawyer & Legal Services",
            "type":"Services"
        }
    ],
    "sg:phone":"+1 254 772 6853",
    "sg:postcode":"76710",
    "sg:province":"TX",
    "wof:name":"Derrel J Luce Inc",
    "wof:placetype":"venue"
},
  "geometry": {"coordinates":[-97.18685499999999,31.536207],"type":"Point"}
}