{
  "type": "Feature",
  "properties": {
    "iso:country":"US",
    "sg:address":"1520 Reynoldston Ln",
    "sg:city":"Dallas",
    "sg:classifiers":[
        {
            "category":"Professional",
            "type":"Services"
        }
    ],
    "sg:phone":"+1 214 376 3955",
    "sg:postcode":"75232",
    "sg:province":"TX",
    "wof:name":"JEM Iv Svc",
    "wof:placetype":"venue"
},
  "geometry": {"coordinates":[-96.848305,32.676581],"type":"Point"}
}