{
  "type": "Feature",
  "properties": {
    "iso:country":"US",
    "sg:address":"2723 Austin St",
    "sg:city":"Texarkana",
    "sg:classifiers":[
        {
            "category":"Building & Trades",
            "subcategory":"Construction",
            "type":"Services"
        }
    ],
    "sg:phone":"+1 903 793 1927",
    "sg:postcode":"75501",
    "sg:province":"TX",
    "sg:tags":[
        "residential"
    ],
    "wof:name":"Poteet Construction",
    "wof:placetype":"venue"
},
  "geometry": {"coordinates":[-94.07693500000001,33.415386],"type":"Point"}
}