{
  "type": "Feature",
  "properties": {
    "iso:country":"US",
    "sg:address":"1300 S Pleasant Valley Rd",
    "sg:city":"Austin",
    "sg:classifiers":[
        {
            "category":"Food & Beverages",
            "subcategory":"Chocolate",
            "type":"Retail Goods"
        }
    ],
    "sg:phone":"+1 512 707 1163",
    "sg:postcode":"78741",
    "sg:province":"TX",
    "sg:tags":[
        "cocoa"
    ],
    "wof:name":"Texas Association Of Fine Chocolate",
    "wof:placetype":"venue"
},
  "geometry": {"coordinates":[-97.718936,30.239718],"type":"Point"}
}