{
  "type": "Feature",
  "properties": {
    "iso:country":"US",
    "sg:address":"8213 N Tahoe Dr",
    "sg:city":"Houston",
    "sg:classifiers":[
        {
            "category":"Professional",
            "subcategory":"Business Services",
            "type":"Services"
        }
    ],
    "sg:phone":"+1 713 937 6300",
    "sg:postcode":"77040",
    "sg:province":"TX",
    "wof:name":"Octoplant Inc",
    "wof:placetype":"venue"
},
  "geometry": {"coordinates":[-95.55903499999999,29.891196],"type":"Point"}
}