{
  "type": "Feature",
  "properties": {
    "iso:country":"US",
    "sg:address":"1724 17th St",
    "sg:city":"Corpus Christi",
    "sg:classifiers":[
        {
            "category":"Building & Trades",
            "subcategory":"Pest Control",
            "type":"Services"
        }
    ],
    "sg:phone":"+1 361 884 8353",
    "sg:postcode":"78404",
    "sg:province":"TX",
    "sg:tags":[
        "disinfecting"
    ],
    "wof:name":"Texas Pest Control",
    "wof:placetype":"venue"
},
  "geometry": {"coordinates":[-97.404781,27.768551],"type":"Point"}
}