{
  "type": "Feature",
  "properties": {
    "iso:country":"US",
    "sg:address":"210 Richmond Ct",
    "sg:city":"Coppell",
    "sg:classifiers":[
        {
            "category":"Retail",
            "subcategory":"Repair Shop",
            "type":"Services"
        }
    ],
    "sg:phone":"+1 972 393 0126",
    "sg:postcode":"75019",
    "sg:province":"TX",
    "wof:name":"Kents Equipment N Truck",
    "wof:placetype":"venue"
},
  "geometry": {"coordinates":[-97.002645,32.965205],"type":"Point"}
}