{
  "type": "Feature",
  "properties": {
    "iso:country":"US",
    "sg:address":"2900 N 16th St",
    "sg:city":"Orange",
    "sg:classifiers":[
        {
            "category":"Restaurant",
            "type":"Food & Drink"
        }
    ],
    "sg:menulink":"http://www.allmenus.com/tx/orange/177671-jack-in-the-box/menu/",
    "sg:phone":"+1 409 883 2661",
    "sg:postcode":"77630",
    "sg:province":"TX",
    "sg:tags":[
        "burger",
        "american"
    ],
    "wof:name":"Jack in the Box",
    "wof:placetype":"venue"
},
  "geometry": {"coordinates":[-93.747468,30.116287],"type":"Point"}
}