{
  "type": "Feature",
  "properties": {
    "iso:country":"US",
    "sg:address":"2397 66th St",
    "sg:city":"Port Arthur",
    "sg:classifiers":[
        {
            "category":"Professional",
            "subcategory":"Business Services",
            "type":"Services"
        }
    ],
    "sg:phone":"+1 409 736 2127",
    "sg:postcode":"77640",
    "sg:province":"TX",
    "wof:name":"Summer Business Inc",
    "wof:placetype":"venue"
},
  "geometry": {"coordinates":[-94.019993,29.913156],"type":"Point"}
}