{
  "type": "Feature",
  "properties": {
    "iso:country":"US",
    "sg:address":"301 S Chestnut St",
    "sg:city":"Lufkin",
    "sg:classifiers":[
        {
            "category":"Food & Beverages",
            "subcategory":"Specialty",
            "type":"Retail Goods"
        },
        {
            "category":"Shopping",
            "subcategory":"Pharmacy",
            "type":"Retail Goods"
        },
        {
            "category":"Food & Beverages",
            "subcategory":"Groceries & Convenience Stores",
            "type":"Retail Goods"
        }
    ],
    "sg:phone":"+1 936 637 7086",
    "sg:postcode":"75901",
    "sg:province":"TX",
    "sg:tags":[
        "supplement",
        "vitamin"
    ],
    "sg:website":"http://www.brookshirebrothers.com",
    "wof:name":"Brookshire Pharmacy",
    "wof:placetype":"venue"
},
  "geometry": {"coordinates":[-94.718628,31.33427],"type":"Point"}
}