{
  "type": "Feature",
  "properties": {
    "iso:country":"US",
    "sg:address":"3014 Glen Springs Dr",
    "sg:city":"Humble",
    "sg:classifiers":[
        {
            "category":"Retail",
            "subcategory":"Repair Shop",
            "type":"Services"
        }
    ],
    "sg:phone":"+1 281 360 4510",
    "sg:postcode":"77339",
    "sg:province":"TX",
    "sg:tags":[
        "welding"
    ],
    "wof:name":"R&D Welding Services",
    "wof:placetype":"venue"
},
  "geometry": {"coordinates":[-95.195526,30.073334],"type":"Point"}
}