{
  "type": "Feature",
  "properties": {
    "iso:country":"US",
    "sg:address":"7399 US Hwy 69",
    "sg:city":"Pollok",
    "sg:classifiers":[
        {
            "category":"Retail",
            "subcategory":"Repair Shop",
            "type":"Services"
        },
        {
            "category":"Retail",
            "subcategory":"Auto Repair",
            "type":"Services"
        }
    ],
    "sg:phone":"+1 936 853 3739",
    "sg:postcode":"75969",
    "sg:province":"TX",
    "sg:tags":[
        "repairing",
        "automobile"
    ],
    "wof:name":"Virgil's Auto Repair",
    "wof:placetype":"venue"
},
  "geometry": {"coordinates":[-94.805615,31.422509],"type":"Point"}
}