{
  "type": "Feature",
  "properties": {
    "iso:country":"US",
    "sg:address":"2310 Manor Rd",
    "sg:city":"Austin",
    "sg:classifiers":[
        {
            "category":"Autos & Motor Vehicles",
            "subcategory":"Auto Supplies",
            "type":"Retail Goods"
        }
    ],
    "sg:phone":"+1 512 476 4315",
    "sg:postcode":"78722",
    "sg:province":"TX",
    "sg:tags":[
        "automotive",
        "parts",
        "accessory"
    ],
    "wof:name":"NAPA Auto Parts",
    "wof:placetype":"venue"
},
  "geometry": {"coordinates":[-97.717201,30.284671],"type":"Point"}
}