{
  "type": "Feature",
  "properties": {
    "iso:country":"US",
    "sg:address":"200 Carroll St",
    "sg:city":"Fort Worth",
    "sg:classifiers":[
        {
            "category":"Autos & Motor Vehicles",
            "subcategory":"Auto Supplies",
            "type":"Retail Goods"
        }
    ],
    "sg:phone":"+1 817 877 5455",
    "sg:postcode":"76107",
    "sg:province":"TX",
    "sg:tags":[
        "automobile",
        "stereo",
        "radio"
    ],
    "wof:name":"Mathis Radio & Speedometer Inc",
    "wof:placetype":"venue"
},
  "geometry": {"coordinates":[-97.354601,32.757174],"type":"Point"}
}