{
  "type": "Feature",
  "properties": {
    "iso:country":"US",
    "sg:address":"3824 Watersridge Cir",
    "sg:city":"Cleburne",
    "sg:classifiers":[
        {
            "category":"Building & Trades",
            "subcategory":"Construction",
            "type":"Services"
        },
        {
            "category":"Military Area",
            "subcategory":"Armory",
            "type":"Public Place"
        }
    ],
    "sg:phone":"+1 817 558 6326",
    "sg:postcode":"76031",
    "sg:province":"TX",
    "sg:tags":[
        "repair",
        "fence-sales",
        "fence",
        "contractor"
    ],
    "wof:name":"Malibu Fence & Deck",
    "wof:placetype":"venue"
},
  "geometry": {"coordinates":[-97.345108,32.296237],"type":"Point"}
}