{
  "type": "Feature",
  "properties": {
    "iso:country":"US",
    "sg:address":"3185 Merriman St",
    "sg:city":"Port Neches",
    "sg:classifiers":[
        {
            "category":"Health Services",
            "subcategory":"Doctor",
            "type":"Services"
        }
    ],
    "sg:phone":"+1 409 727 2164",
    "sg:postcode":"77651",
    "sg:province":"TX",
    "sg:tags":[
        "dentist"
    ],
    "wof:name":"Family Dentistry",
    "wof:placetype":"venue"
},
  "geometry": {"coordinates":[-93.968829,29.96195],"type":"Point"}
}