{
  "type": "Feature",
  "properties": {
    "iso:country":"US",
    "sg:address":"309 N Union St",
    "sg:city":"Whitesboro",
    "sg:classifiers":[
        {
            "category":"Shopping",
            "subcategory":"Bicycles & Sporting Goods",
            "type":"Retail Goods"
        }
    ],
    "sg:phone":"+1 903 564 7953",
    "sg:postcode":"76273",
    "sg:province":"TX",
    "sg:tags":[
        "gun",
        "gunsmith"
    ],
    "wof:name":"Kenneth M Lowry Sporting Goods",
    "wof:placetype":"venue"
},
  "geometry": {"coordinates":[-96.906796,33.658921],"type":"Point"}
}