{
  "type": "Feature",
  "properties": {
    "iso:country":"US",
    "sg:address":"4901 Tanglewood Dr",
    "sg:city":"Burleson",
    "sg:classifiers":[
        {
            "category":"Building & Trades",
            "subcategory":"Pest Control",
            "type":"Services"
        }
    ],
    "sg:phone":"+1 817 925 0248",
    "sg:postcode":"76028",
    "sg:province":"TX",
    "wof:name":"Sifford Home Inspections & Pest Control",
    "wof:placetype":"venue"
},
  "geometry": {"coordinates":[-97.240104,32.492202],"type":"Point"}
}