{
  "type": "Feature",
  "properties": {
    "iso:country":"US",
    "sg:address":"2508 E Riverside Dr",
    "sg:city":"Austin",
    "sg:classifiers":[
        {
            "category":"Utilities",
            "subcategory":"Mobile Phone",
            "type":"Services"
        }
    ],
    "sg:phone":"+1 512 912 0134",
    "sg:postcode":"78741",
    "sg:province":"TX",
    "sg:tags":[
        "telephone",
        "cellular"
    ],
    "wof:name":"T Mobile East Riverside Dr",
    "wof:placetype":"venue"
},
  "geometry": {"coordinates":[-97.725934,30.238883],"type":"Point"}
}