{
  "type": "Feature",
  "properties": {
    "iso:country":"US",
    "sg:address":"231 E Main Ave",
    "sg:city":"Round Rock",
    "sg:classifiers":[
        {
            "category":"Professional",
            "subcategory":"Computer Services",
            "type":"Services"
        }
    ],
    "sg:phone":"+1 512 733 0110",
    "sg:postcode":"78664",
    "sg:province":"TX",
    "sg:tags":[
        "related"
    ],
    "sg:website":"www.edge-tec.com",
    "wof:name":"Edge Technologies Inc",
    "wof:placetype":"venue"
},
  "geometry": {"coordinates":[-97.676957,30.509007],"type":"Point"}
}