{
  "type": "Feature",
  "properties": {
    "iso:country":"US",
    "sg:address":"6001 Hillcroft St",
    "sg:city":"Houston",
    "sg:classifiers":[
        {
            "category":"Professional",
            "subcategory":"Business Services",
            "type":"Services"
        }
    ],
    "sg:phone":"+1 713 777 4786",
    "sg:postcode":"77081",
    "sg:province":"TX",
    "sg:tags":[
        "packaging"
    ],
    "wof:name":"Bombino Express",
    "wof:placetype":"venue"
},
  "geometry": {"coordinates":[-95.498385,29.716037],"type":"Point"}
}