{
  "type": "Feature",
  "properties": {
    "iso:country":"US",
    "sg:address":"10440 Deerwood Rd",
    "sg:city":"Houston",
    "sg:classifiers":[
        {
            "category":"Education",
            "subcategory":"Special Training",
            "type":"Public Place"
        }
    ],
    "sg:phone":"+1 713 782 3158",
    "sg:postcode":"77042",
    "sg:province":"TX",
    "wof:name":"Plus Ultra International",
    "wof:placetype":"venue"
},
  "geometry": {"coordinates":[-95.56026799999999,29.758425],"type":"Point"}
}