{
  "type": "Feature",
  "properties": {
    "iso:country":"US",
    "sg:address":"140 Meadows Dr",
    "sg:city":"Mc Kinney",
    "sg:classifiers":[
        {
            "category":"Shopping",
            "subcategory":"Catalog Store",
            "type":"Retail Goods"
        }
    ],
    "sg:phone":"+1 972 562 8128",
    "sg:postcode":"75071",
    "sg:province":"TX",
    "sg:tags":[
        "mail",
        "house"
    ],
    "wof:name":"Hummingbird Hill Gift Baskets",
    "wof:placetype":"venue"
},
  "geometry": {"coordinates":[-96.555532,33.219664],"type":"Point"}
}