{
  "type": "Feature",
  "properties": {
    "iso:country":"US",
    "sg:address":"1115 Probandt St",
    "sg:city":"San Antonio",
    "sg:classifiers":[
        {
            "category":"Food & Beverages",
            "subcategory":"Groceries & Convenience Stores",
            "type":"Retail Goods"
        }
    ],
    "sg:phone":"+1 210 532 3134",
    "sg:postcode":"78204",
    "sg:province":"TX",
    "wof:name":"Handi Plus",
    "wof:placetype":"venue"
},
  "geometry": {"coordinates":[-98.49834300000001,29.39545],"type":"Point"}
}