{
  "type": "Feature",
  "properties": {
    "iso:country":"US",
    "sg:address":"312 Lawn Dr",
    "sg:city":"Sinton",
    "sg:classifiers":[
        {
            "category":"Professional",
            "subcategory":"Computer Services",
            "type":"Services"
        }
    ],
    "sg:phone":"+1 361 739 8721",
    "sg:postcode":"78387",
    "sg:province":"TX",
    "sg:tags":[
        "related"
    ],
    "wof:name":"Gigabyte Computer Concepts",
    "wof:placetype":"venue"
},
  "geometry": {"coordinates":[-97.521495,28.035092],"type":"Point"}
}