{
  "type": "Feature",
  "properties": {
    "iso:country":"US",
    "sg:address":"3200 N Main St",
    "sg:city":"Vidor",
    "sg:classifiers":[
        {
            "category":"Building & Trades",
            "subcategory":"Pest Control",
            "type":"Services"
        }
    ],
    "sg:phone":"+1 409 769 8842",
    "sg:postcode":"77662",
    "sg:province":"TX",
    "wof:name":"Giant Pest Control",
    "wof:placetype":"venue"
},
  "geometry": {"coordinates":[-94.022778,30.170264],"type":"Point"}
}