{
  "type": "Feature",
  "properties": {
    "iso:country":"US",
    "sg:address":"5301 Blackhawk Dr",
    "sg:city":"Plano",
    "sg:classifiers":[
        {
            "category":"Banks & Credit Unions",
            "subcategory":"Financial Services",
            "type":"Services"
        }
    ],
    "sg:phone":"+1 972 931 6380",
    "sg:postcode":"75093",
    "sg:province":"TX",
    "sg:tags":[
        "investor"
    ],
    "wof:name":"Sws Investments Corp",
    "wof:placetype":"venue"
},
  "geometry": {"coordinates":[-96.805988,33.022484],"type":"Point"}
}