{
  "type": "Feature",
  "properties": {
    "iso:country":"US",
    "sg:address":"5816 Greenwyck Dr",
    "sg:city":"Plano",
    "sg:classifiers":[
        {
            "category":"Real Estate",
            "subcategory":"Real Estate Agent",
            "type":"Services"
        }
    ],
    "sg:phone":"+1 972 378 1540",
    "sg:postcode":"75093",
    "sg:province":"TX",
    "wof:name":"Kay Cheek Realtor",
    "wof:placetype":"venue"
},
  "geometry": {"coordinates":[-96.814365,33.051214],"type":"Point"}
}