{
  "type": "Feature",
  "properties": {
    "iso:country":"US",
    "sg:address":"202 Southtown Dr",
    "sg:city":"Muenster",
    "sg:classifiers":[
        {
            "category":"Mining & Drilling",
            "type":"Manufacturing & Wholesale Goods"
        }
    ],
    "sg:phone":"+1 940 736 4093",
    "sg:postcode":"76252",
    "sg:province":"TX",
    "sg:tags":[
        "field"
    ],
    "wof:name":"Lloyd J Walterscheid",
    "wof:placetype":"venue"
},
  "geometry": {"coordinates":[-97.383825,33.646469],"type":"Point"}
}