{
  "type": "Feature",
  "properties": {
    "iso:country":"US",
    "sg:address":"3540 US Highway 69 N",
    "sg:city":"Lufkin",
    "sg:classifiers":[
        {
            "category":"Mining & Drilling",
            "type":"Manufacturing & Wholesale Goods"
        }
    ],
    "sg:phone":"+1 936 639 9400",
    "sg:postcode":"75904",
    "sg:province":"TX",
    "sg:tags":[
        "boring",
        "contractor"
    ],
    "wof:name":"Tiger Greek Enterprises",
    "wof:placetype":"venue"
},
  "geometry": {"coordinates":[-94.770698,31.382122],"type":"Point"}
}