{
  "type": "Feature",
  "properties": {
    "iso:country":"US",
    "sg:address":"10880 Bekay St",
    "sg:city":"Dallas",
    "sg:classifiers":[
        {
            "category":"Manufacturing",
            "subcategory":"Metals",
            "type":"Manufacturing & Wholesale Goods"
        }
    ],
    "sg:phone":"+1 214 221 5020",
    "sg:postcode":"75238",
    "sg:province":"TX",
    "wof:name":"Teco Metal Products",
    "wof:placetype":"venue"
},
  "geometry": {"coordinates":[-96.69515699999999,32.901656],"type":"Point"}
}