{
  "type": "Feature",
  "properties": {
    "iso:country":"US",
    "sg:address":"18802 Turtle Creek Way",
    "sg:city":"Magnolia",
    "sg:classifiers":[
        {
            "category":"Retail",
            "subcategory":"Auto Repair",
            "type":"Services"
        }
    ],
    "sg:phone":"+1 281 356 7828",
    "sg:postcode":"77355",
    "sg:province":"TX",
    "sg:tags":[
        "automotive"
    ],
    "wof:name":"Dowies Automotive",
    "wof:placetype":"venue"
},
  "geometry": {"coordinates":[-95.73008,30.121865],"type":"Point"}
}