{
  "type": "Feature",
  "properties": {
    "iso:country":"US",
    "sg:address":"7619 Montana Ave",
    "sg:city":"El Paso",
    "sg:classifiers":[
        {
            "category":"Education",
            "subcategory":"Vocational School",
            "type":"Public Place"
        }
    ],
    "sg:phone":"+1 915 779 0096",
    "sg:postcode":"79925",
    "sg:province":"TX",
    "sg:tags":[
        "real estate"
    ],
    "sg:website":"www.academyofrealestate.com",
    "wof:name":"Academy Of Real Estate",
    "wof:placetype":"venue"
},
  "geometry": {"coordinates":[-106.38573700000001,31.79122],"type":"Point"}
}