{
  "type": "Feature",
  "properties": {
    "iso:country":"US",
    "sg:address":"11511 Katy Fwy",
    "sg:city":"Houston",
    "sg:classifiers":[
        {
            "category":"Building & Trades",
            "subcategory":"Landscaping Services",
            "type":"Services"
        }
    ],
    "sg:phone":"+1 281 895 7661",
    "sg:postcode":"77079",
    "sg:province":"TX",
    "sg:tags":[
        "landscape",
        "contractor"
    ],
    "wof:name":"J H Plantscapes",
    "wof:placetype":"venue"
},
  "geometry": {"coordinates":[-95.58647499999999,29.78415],"type":"Point"}
}