{
  "type": "Feature",
  "properties": {
    "iso:country":"US",
    "sg:address":"7810 Baneway Dr",
    "sg:city":"Houston",
    "sg:classifiers":[
        {
            "category":"Building & Trades",
            "subcategory":"Construction",
            "type":"Services"
        }
    ],
    "sg:phone":"+1 281 561 8600",
    "sg:postcode":"77072",
    "sg:province":"TX",
    "sg:tags":[
        "concrete",
        "contractor"
    ],
    "wof:name":"2gs Concrete",
    "wof:placetype":"venue"
},
  "geometry": {"coordinates":[-95.581356,29.693294],"type":"Point"}
}