{
  "type": "Feature",
  "properties": {
    "iso:country":"US",
    "sg:address":"4717 Eagle Feather Dr",
    "sg:city":"Austin",
    "sg:classifiers":[
        {
            "category":"Arts & Performance",
            "subcategory":"Theater",
            "type":"Entertainment"
        }
    ],
    "sg:phone":"+1 512 892 8883",
    "sg:postcode":"78735",
    "sg:province":"TX",
    "sg:tags":[
        "theatrical",
        "stage",
        "lighting",
        "equipment"
    ],
    "wof:name":"Illumitex",
    "wof:placetype":"venue"
},
  "geometry": {"coordinates":[-97.83086900000001,30.242937],"type":"Point"}
}