{
  "type": "Feature",
  "properties": {
    "iso:country":"US",
    "sg:address":"49 San Jacinto St",
    "sg:city":"Houston",
    "sg:classifiers":[
        {
            "category":"Government",
            "subcategory":"Jail",
            "type":"Public Place"
        }
    ],
    "sg:phone":"+1 713 755 2507",
    "sg:postcode":"77002",
    "sg:province":"TX",
    "sg:tags":[
        "correctional",
        "institution"
    ],
    "wof:name":"Community Sprvsion Corrections",
    "wof:placetype":"venue"
},
  "geometry": {"coordinates":[-95.357648,29.762778],"type":"Point"}
}