{
  "type": "Feature",
  "properties": {
    "iso:country":"US",
    "sg:address":"15995 N Barkers Landing Rd",
    "sg:city":"Houston",
    "sg:classifiers":[
        {
            "category":"Building & Trades",
            "subcategory":"Construction",
            "type":"Services"
        }
    ],
    "sg:phone":"+1 281 920 4100",
    "sg:postcode":"77079",
    "sg:province":"TX",
    "sg:tags":[
        "house"
    ],
    "wof:name":"Kubosh Construction LLC",
    "wof:placetype":"venue"
},
  "geometry": {"coordinates":[-95.64128599999999,29.780869],"type":"Point"}
}