{
  "type": "Feature",
  "properties": {
    "iso:country":"US",
    "sg:address":"8711 Honora Ave",
    "sg:city":"San Antonio",
    "sg:classifiers":[
        {
            "category":"Retail",
            "subcategory":"Auto Repair",
            "type":"Services"
        }
    ],
    "sg:phone":"+1 210 922 7021",
    "sg:postcode":"78221",
    "sg:province":"TX",
    "sg:tags":[
        "general"
    ],
    "wof:name":"JV Garage",
    "wof:placetype":"venue"
},
  "geometry": {"coordinates":[-98.51515999999999,29.338983],"type":"Point"}
}