{
  "type": "Feature",
  "properties": {
    "iso:country":"US",
    "sg:address":"13712 Walters Rd",
    "sg:city":"Houston",
    "sg:classifiers":[
        {
            "category":"Retail",
            "subcategory":"Laundry & Dry Cleaning",
            "type":"Services"
        }
    ],
    "sg:phone":"+1 281 444 8189",
    "sg:postcode":"77014",
    "sg:province":"TX",
    "sg:tags":[
        "cleaners"
    ],
    "wof:name":"Joy Cleaners & Alterations",
    "wof:placetype":"venue"
},
  "geometry": {"coordinates":[-95.477099,29.981585],"type":"Point"}
}