{
  "type": "Feature",
  "properties": {
    "iso:country":"US",
    "sg:address":"112 E Houston St",
    "sg:city":"Tyler",
    "sg:classifiers":[
        {
            "category":"Organizations",
            "subcategory":"Religious Organization",
            "type":"Services"
        }
    ],
    "sg:phone":"+1 903 526 4775",
    "sg:postcode":"75702",
    "sg:province":"TX",
    "sg:tags":[
        "church"
    ],
    "wof:name":"Friends Community Church",
    "wof:placetype":"venue"
},
  "geometry": {"coordinates":[-95.299654,32.343816],"type":"Point"}
}