{
  "type": "Feature",
  "properties": {
    "iso:country":"US",
    "sg:address":"311 Saint Lawrence St",
    "sg:city":"Gonzales",
    "sg:classifiers":[
        {
            "category":"Fast Food",
            "type":"Food & Drink"
        },
        {
            "category":"Restaurant",
            "type":"Food & Drink"
        }
    ],
    "sg:phone":"+1 830 672 3156",
    "sg:postcode":"78629",
    "sg:province":"TX",
    "sg:tags":[
        "barbecue"
    ],
    "wof:name":"Gonzales Food Market",
    "wof:placetype":"venue"
},
  "geometry": {"coordinates":[-97.453771,29.501049],"type":"Point"}
}