{
  "type": "Feature",
  "properties": {
    "iso:country":"US",
    "sg:address":"1106 Town East Mall",
    "sg:city":"Mesquite",
    "sg:classifiers":[
        {
            "category":"Restaurant",
            "type":"Food & Drink"
        }
    ],
    "sg:phone":"+1 972 682 5800",
    "sg:postcode":"75150",
    "sg:province":"TX",
    "sg:tags":[
        "pizza"
    ],
    "wof:name":"BJ's Restaurant & Brewhouse",
    "wof:placetype":"venue"
},
  "geometry": {"coordinates":[-96.626367,32.80866],"type":"Point"}
}