{
  "type": "Feature",
  "properties": {
    "iso:country":"US",
    "sg:address":"7101 Lawndale St",
    "sg:city":"Houston",
    "sg:classifiers":[
        {
            "category":"Shopping",
            "subcategory":"Pharmacy",
            "type":"Retail Goods"
        }
    ],
    "sg:phone":"+1 713 921 7500",
    "sg:postcode":"77023",
    "sg:province":"TX",
    "sg:tags":[
        "drugstore"
    ],
    "wof:name":"Cunningham Pharmacy",
    "wof:placetype":"venue"
},
  "geometry": {"coordinates":[-95.29489,29.717467],"type":"Point"}
}