{
  "type": "Feature",
  "properties": {
    "iso:country":"US",
    "sg:address":"306 Blalock Rd",
    "sg:city":"Houston",
    "sg:classifiers":[
        {
            "category":"Health Services",
            "subcategory":"Doctor",
            "type":"Services"
        }
    ],
    "sg:phone":"+1 713 784 5750",
    "sg:postcode":"77024",
    "sg:province":"TX",
    "sg:tags":[
        "medical"
    ],
    "wof:name":"Cartwrig Rosalie & Joiner",
    "wof:placetype":"venue"
},
  "geometry": {"coordinates":[-95.522531,29.757728],"type":"Point"}
}