{
  "type": "Feature",
  "properties": {
    "iso:country":"US",
    "sg:address":"101 Glover Dr",
    "sg:city":"Longview",
    "sg:classifiers":[
        {
            "category":"Education",
            "subcategory":"College",
            "type":"Public Place"
        }
    ],
    "sg:phone":"+1 903 236 3797",
    "sg:postcode":"75601",
    "sg:province":"TX",
    "sg:tags":[
        "school",
        "theological"
    ],
    "wof:name":"Brazzle School Of Theology",
    "wof:placetype":"venue"
},
  "geometry": {"coordinates":[-94.721385,32.505846],"type":"Point"}
}