{
  "type": "Feature",
  "properties": {
    "iso:country":"US",
    "sg:address":"12910 Belgrave Dr",
    "sg:city":"Cypress",
    "sg:classifiers":[
        {
            "category":"Professional",
            "subcategory":"Management & Consulting",
            "type":"Services"
        }
    ],
    "sg:phone":"+1 281 370 8733",
    "sg:postcode":"77429",
    "sg:province":"TX",
    "sg:tags":[
        "consultant"
    ],
    "wof:name":"Joe S Rowland Inc",
    "wof:placetype":"venue"
},
  "geometry": {"coordinates":[-95.610474,29.996289],"type":"Point"}
}