{
  "type": "Feature",
  "properties": {
    "iso:country":"US",
    "sg:address":"816 Mattie St",
    "sg:city":"Wharton",
    "sg:classifiers":[
        {
            "category":"Organizations",
            "subcategory":"Religious Organization",
            "type":"Services"
        }
    ],
    "sg:phone":"+1 979 532 3764",
    "sg:postcode":"77488",
    "sg:province":"TX",
    "sg:tags":[
        "church"
    ],
    "wof:name":"St James Baptist Church",
    "wof:placetype":"venue"
},
  "geometry": {"coordinates":[-96.116654,29.320761],"type":"Point"}
}