{
  "type": "Feature",
  "properties": {
    "iso:country":"US",
    "sg:address":"2005 Deer Trl",
    "sg:city":"Floresville",
    "sg:classifiers":[
        {
            "category":"Building & Trades",
            "subcategory":"Plumbing",
            "type":"Services"
        }
    ],
    "sg:phone":"+1 830 393 6845",
    "sg:postcode":"78114",
    "sg:province":"TX",
    "sg:tags":[
        "plumber",
        "industrial",
        "contractors-commercial"
    ],
    "wof:name":"Hansen's Plumbing",
    "wof:placetype":"venue"
},
  "geometry": {"coordinates":[-98.171612,29.204971],"type":"Point"}
}