{
  "type": "Feature",
  "properties": {
    "iso:country":"US",
    "sg:address":"4000 Essex Ln",
    "sg:city":"Houston",
    "sg:classifiers":[
        {
            "category":"Personal",
            "subcategory":"Massage",
            "type":"Services"
        },
        {
            "category":"Personal",
            "subcategory":"Day Spa",
            "type":"Services"
        }
    ],
    "sg:phone":"+1 832 292 9146",
    "sg:postcode":"77027",
    "sg:province":"TX",
    "sg:website":"www.spaalexis.com",
    "wof:name":"Spa Alexis",
    "wof:placetype":"venue"
},
  "geometry": {"coordinates":[-95.446622,29.739433],"type":"Point"}
}