{
  "type": "Feature",
  "properties": {
    "iso:country":"US",
    "sg:address":"224 Sunway Dr",
    "sg:city":"San Antonio",
    "sg:classifiers":[
        {
            "category":"Manufacturing",
            "subcategory":"Jewelry",
            "type":"Manufacturing & Wholesale Goods"
        }
    ],
    "sg:phone":"+1 210 494 3786",
    "sg:postcode":"78232",
    "sg:province":"TX",
    "sg:tags":[
        "plumbing",
        "vitreous",
        "precious",
        "metal",
        "mfg"
    ],
    "wof:name":"Bmarie",
    "wof:placetype":"venue"
},
  "geometry": {"coordinates":[-98.483063,29.593456],"type":"Point"}
}