{
  "type": "Feature",
  "properties": {
    "iso:country":"US",
    "sg:address":"1112 E University Dr",
    "sg:city":"Denton",
    "sg:classifiers":[
        {
            "category":"Travel",
            "subcategory":"Hotels & Motels",
            "type":"Entertainment"
        }
    ],
    "sg:phone":"+1 940 382 9688",
    "sg:postcode":"76209",
    "sg:province":"TX",
    "sg:tags":[
        "lodging"
    ],
    "wof:name":"Holiday Lodge",
    "wof:placetype":"venue"
},
  "geometry": {"coordinates":[-97.118853,33.232259],"type":"Point"}
}