{
  "type": "Feature",
  "properties": {
    "iso:country":"US",
    "sg:address":"3003 S Loop Fwy",
    "sg:city":"Houston",
    "sg:classifiers":[
        {
            "category":"Education",
            "subcategory":"School",
            "type":"Public Place"
        }
    ],
    "sg:phone":"+1 713 394 3500",
    "sg:postcode":"77054",
    "sg:province":"TX",
    "sg:tags":[
        "specialty"
    ],
    "wof:name":"Community Education Partners",
    "wof:placetype":"venue"
},
  "geometry": {"coordinates":[-95.424763,29.677008],"type":"Point"}
}