{
  "type": "Feature",
  "properties": {
    "iso:country":"US",
    "sg:address":"20607 Pecan Bend Rd",
    "sg:city":"Damon",
    "sg:classifiers":[
        {
            "category":"Professional",
            "type":"Services"
        }
    ],
    "sg:phone":"+1 281 343 1604",
    "sg:postcode":"77430",
    "sg:province":"TX",
    "sg:tags":[
        "establishment"
    ],
    "wof:name":"Gulf Coast Technology",
    "wof:placetype":"venue"
},
  "geometry": {"coordinates":[-95.605036,29.355873],"type":"Point"}
}