{
  "type": "Feature",
  "properties": {
    "iso:country":"US",
    "sg:address":"2001 Hawthorne Ln",
    "sg:city":"Plano",
    "sg:classifiers":[
        {
            "category":"Professional",
            "type":"Services"
        }
    ],
    "sg:phone":"+1 972 422 7717",
    "sg:postcode":"75074",
    "sg:province":"TX",
    "wof:name":"Go For Concierge",
    "wof:placetype":"venue"
},
  "geometry": {"coordinates":[-96.68697299999999,33.033092],"type":"Point"}
}