{
  "type": "Feature",
  "properties": {
    "iso:country":"US",
    "sg:address":"1651 Choteau Cir",
    "sg:city":"Grapevine",
    "sg:classifiers":[
        {
            "category":"Professional",
            "type":"Services"
        }
    ],
    "sg:phone":"+1 817 421 7338",
    "sg:postcode":"76051",
    "sg:province":"TX",
    "wof:name":"Visions By Bc",
    "wof:placetype":"venue"
},
  "geometry": {"coordinates":[-97.09393,32.955813],"type":"Point"}
}