{
  "type": "Feature",
  "properties": {
    "iso:country":"US",
    "sg:address":"503 N Center St",
    "sg:city":"Weimar",
    "sg:classifiers":[
        {
            "category":"Wholesale",
            "subcategory":"Machinery & Supplies",
            "type":"Manufacturing & Wholesale Goods"
        }
    ],
    "sg:phone":"+1 979 725 6253",
    "sg:postcode":"78962",
    "sg:province":"TX",
    "wof:name":"Davila Irrigation Systems",
    "wof:placetype":"venue"
},
  "geometry": {"coordinates":[-96.78019,29.709134],"type":"Point"}
}