{
  "type": "Feature",
  "properties": {
    "iso:country":"US",
    "sg:address":"8501 W Montgomery Rd",
    "sg:city":"Houston",
    "sg:classifiers":[
        {
            "category":"Education",
            "subcategory":"Library",
            "type":"Public Place"
        }
    ],
    "sg:phone":"+1 832 393 1700",
    "sg:postcode":"77088",
    "sg:province":"TX",
    "sg:website":"http://www.houstonconventionctr.com",
    "wof:name":"Public Libraries",
    "wof:placetype":"venue"
},
  "geometry": {"coordinates":[-95.43673699999999,29.87079],"type":"Point"}
}