{
  "type": "Feature",
  "properties": {
    "iso:country":"US",
    "sg:address":"1765 US Hwy 79 N",
    "sg:city":"Henderson",
    "sg:classifiers":[
        {
            "category":"Shopping",
            "subcategory":"Tobacco",
            "type":"Retail Goods"
        }
    ],
    "sg:phone":"+1 903 657 9959",
    "sg:postcode":"75652",
    "sg:province":"TX",
    "sg:tags":[
        "cigarette",
        "cigar",
        "dealer"
    ],
    "wof:name":"D & B Tobacco Wholesale",
    "wof:placetype":"venue"
},
  "geometry": {"coordinates":[-94.784184,32.1586],"type":"Point"}
}