{
  "type": "Feature",
  "properties": {
    "iso:country":"US",
    "sg:address":"5202 Bissonnet St",
    "sg:city":"Bellaire",
    "sg:classifiers":[
        {
            "category":"Food & Beverages",
            "subcategory":"Bakery",
            "type":"Retail Goods"
        }
    ],
    "sg:phone":"+1 713 666 0505",
    "sg:postcode":"77401",
    "sg:province":"TX",
    "sg:tags":[
        "baker"
    ],
    "wof:name":"Cake Affairs",
    "wof:placetype":"venue"
},
  "geometry": {"coordinates":[-95.471413,29.705954],"type":"Point"}
}