{
  "type": "Feature",
  "properties": {
    "iso:country":"US",
    "sg:address":"9115 Poco Rd",
    "sg:city":"Houston",
    "sg:classifiers":[
        {
            "category":"Professional",
            "type":"Services"
        }
    ],
    "sg:phone":"+1 713 869 5861",
    "sg:postcode":"77080",
    "sg:province":"TX",
    "wof:name":"Skyline Art Co Management Inc",
    "wof:placetype":"venue"
},
  "geometry": {"coordinates":[-95.515248,29.809337],"type":"Point"}
}