{
  "type": "Feature",
  "properties": {
    "iso:country":"US",
    "sg:address":"743 Ted Pickett",
    "sg:city":"League City",
    "sg:classifiers":[
        {
            "category":"Shopping",
            "subcategory":"Bicycles & Sporting Goods",
            "type":"Retail Goods"
        }
    ],
    "sg:phone":"+1 281 338 2232",
    "sg:postcode":"77573",
    "sg:province":"TX",
    "wof:name":"A & R Marine",
    "wof:placetype":"venue"
},
  "geometry": {"coordinates":[-95.0835,29.507338],"type":"Point"}
}