{
  "type": "Feature",
  "properties": {
    "iso:country":"US",
    "sg:address":"304 Caney St",
    "sg:city":"Dodd City",
    "sg:classifiers":[
        {
            "category":"Government",
            "subcategory":"Office",
            "type":"Public Place"
        }
    ],
    "sg:phone":"+1 903 583 7710",
    "sg:postcode":"75438",
    "sg:province":"TX",
    "sg:tags":[
        "city"
    ],
    "wof:name":"City Hall",
    "wof:placetype":"venue"
},
  "geometry": {"coordinates":[-96.07787500000001,33.574523],"type":"Point"}
}