{
  "type": "Feature",
  "properties": {
    "iso:country":"US",
    "sg:address":"214 Heatherwood Dr",
    "sg:city":"Spring",
    "sg:classifiers":[
        {
            "category":"Building & Trades",
            "subcategory":"Electrical",
            "type":"Services"
        },
        {
            "category":"Utilities",
            "subcategory":"Electric",
            "type":"Services"
        }
    ],
    "sg:phone":"+1 281 362 7523",
    "sg:postcode":"77386",
    "sg:province":"TX",
    "sg:tags":[
        "electrical",
        "contractor"
    ],
    "wof:name":"John Estes Electrical Co",
    "wof:placetype":"venue"
},
  "geometry": {"coordinates":[-95.444979,30.139383],"type":"Point"}
}