{
  "type": "Feature",
  "properties": {
    "iso:country":"US",
    "sg:address":"10943 Cayman Mist Dr",
    "sg:city":"Houston",
    "sg:classifiers":[
        {
            "category":"Retail",
            "subcategory":"Repair Shop",
            "type":"Services"
        }
    ],
    "sg:phone":"+1 713 991 2320",
    "sg:postcode":"77075",
    "sg:province":"TX",
    "wof:name":"Turner Co",
    "wof:placetype":"venue"
},
  "geometry": {"coordinates":[-95.252521,29.606091],"type":"Point"}
}