{
  "type": "Feature",
  "properties": {
    "iso:country":"US",
    "sg:address":"5502 Petty St",
    "sg:city":"Houston",
    "sg:classifiers":[
        {
            "category":"Organizations",
            "subcategory":"Religious Organization",
            "type":"Services"
        }
    ],
    "sg:phone":"+1 713 863 7820",
    "sg:postcode":"77007",
    "sg:province":"TX",
    "wof:name":"Mission Jehovah Jireh",
    "wof:placetype":"venue"
},
  "geometry": {"coordinates":[-95.420303,29.7806],"type":"Point"}
}