{
  "type": "Feature",
  "properties": {
    "iso:country":"US",
    "sg:address":"610 N 60th St",
    "sg:city":"Waco",
    "sg:classifiers":[
        {
            "category":"Travel",
            "subcategory":"Campground",
            "type":"Entertainment"
        }
    ],
    "sg:phone":"+1 254 772 1153",
    "sg:postcode":"76710",
    "sg:province":"TX",
    "sg:tags":[
        "camp"
    ],
    "wof:name":"Camp Easterling Inc",
    "wof:placetype":"venue"
},
  "geometry": {"coordinates":[-97.191971,31.522185],"type":"Point"}
}