{
  "type": "Feature",
  "properties": {
    "iso:country":"US",
    "sg:address":"418 US Hwy 90 Alt",
    "sg:city":"Sealy",
    "sg:classifiers":[
        {
            "category":"Banks & Credit Unions",
            "subcategory":"Bank",
            "type":"Services"
        }
    ],
    "sg:phone":"+1 979 885 7987",
    "sg:postcode":"77434",
    "sg:province":"TX",
    "sg:tags":[
        "personal",
        "institution"
    ],
    "wof:name":"Security Finance",
    "wof:placetype":"venue"
},
  "geometry": {"coordinates":[-96.33706100000001,29.586612],"type":"Point"}
}