{
  "type": "Feature",
  "properties": {
    "iso:country":"US",
    "sg:address":"2707 E Southlake Blvd",
    "sg:city":"Southlake",
    "sg:classifiers":[
        {
            "category":"Personal",
            "subcategory":"Beauty Salon",
            "type":"Services"
        }
    ],
    "sg:phone":"+1 817 442 1088",
    "sg:postcode":"76092",
    "sg:province":"TX",
    "sg:tags":[
        "nail",
        "shop"
    ],
    "wof:name":"Nail Spa",
    "wof:placetype":"venue"
},
  "geometry": {"coordinates":[-97.109577,32.938865],"type":"Point"}
}