{
  "type": "Feature",
  "properties": {
    "iso:country":"US",
    "sg:address":"5952 Pine Forest Rd",
    "sg:city":"Houston",
    "sg:classifiers":[
        {
            "category":"Building & Trades",
            "subcategory":"Construction",
            "type":"Services"
        }
    ],
    "sg:phone":"+1 713 973 1221",
    "sg:postcode":"77057",
    "sg:province":"TX",
    "sg:tags":[
        "contractor"
    ],
    "wof:name":"Memorial Builders",
    "wof:placetype":"venue"
},
  "geometry": {"coordinates":[-95.485274,29.764267],"type":"Point"}
}