{
  "type": "Feature",
  "properties": {
    "iso:country":"US",
    "sg:address":"1910 W 5th St",
    "sg:city":"Irving",
    "sg:classifiers":[
        {
            "category":"Building & Trades",
            "subcategory":"Landscaping Services",
            "type":"Services"
        }
    ],
    "sg:phone":"+1 972 254 4638",
    "sg:postcode":"75060",
    "sg:province":"TX",
    "sg:tags":[
        "mover",
        "mowing"
    ],
    "wof:name":"Quality Tractor Mowing",
    "wof:placetype":"venue"
},
  "geometry": {"coordinates":[-96.971802,32.8097],"type":"Point"}
}