{
  "type": "Feature",
  "properties": {
    "iso:country":"US",
    "sg:address":"206 W Highland Dr",
    "sg:city":"Boerne",
    "sg:classifiers":[
        {
            "category":"Communications",
            "subcategory":"Film & Video Production",
            "type":"Services"
        }
    ],
    "sg:phone":"+1 210 602 5004",
    "sg:postcode":"78006",
    "sg:province":"TX",
    "sg:tags":[
        "motion"
    ],
    "wof:name":"Birdland Productions Inc",
    "wof:placetype":"venue"
},
  "geometry": {"coordinates":[-98.731841,29.784433],"type":"Point"}
}