{
  "type": "Feature",
  "properties": {
    "iso:country":"US",
    "sg:address":"750 Everhart Rd",
    "sg:city":"Corpus Christi",
    "sg:classifiers":[
        {
            "category":"Social Services",
            "subcategory":"Child Care",
            "type":"Services"
        }
    ],
    "sg:phone":"+1 361 855 6239",
    "sg:postcode":"78411",
    "sg:province":"TX",
    "sg:tags":[
        "kindergarten",
        "academic",
        "school"
    ],
    "wof:name":"Jewish Community Council",
    "wof:placetype":"venue"
},
  "geometry": {"coordinates":[-97.376897,27.726711],"type":"Point"}
}