{
  "type": "Feature",
  "properties": {
    "iso:country":"US",
    "sg:address":"1213 E Alton Gloor Blvd",
    "sg:city":"Brownsville",
    "sg:classifiers":[
        {
            "category":"Health Services",
            "subcategory":"Chiropractor",
            "type":"Services"
        }
    ],
    "sg:phone":"+1 956 554 0533",
    "sg:postcode":"78526",
    "sg:province":"TX",
    "sg:tags":[
        "chiropractic"
    ],
    "wof:name":"Gracia Chiropractic Wellness Clinic",
    "wof:placetype":"venue"
},
  "geometry": {"coordinates":[-97.496026,25.980124],"type":"Point"}
}