{
  "type": "Feature",
  "properties": {
    "iso:country":"US",
    "sg:address":"4311 Lindbergh Dr",
    "sg:city":"Addison",
    "sg:classifiers":[
        {
            "category":"Manufacturing",
            "subcategory":"Printing",
            "type":"Manufacturing & Wholesale Goods"
        }
    ],
    "sg:phone":"+1 972 233 8404",
    "sg:postcode":"75001",
    "sg:province":"TX",
    "sg:tags":[
        "newspaper",
        "publishing"
    ],
    "sg:website":"www.midwaypress.com",
    "wof:name":"Midway Press LTD",
    "wof:placetype":"venue"
},
  "geometry": {"coordinates":[-96.836889,32.957992],"type":"Point"}
}