{
  "type": "Feature",
  "properties": {
    "iso:country":"US",
    "sg:address":"1401 Provincetown Ln",
    "sg:city":"Richardson",
    "sg:classifiers":[
        {
            "category":"Building & Trades",
            "subcategory":"Construction",
            "type":"Services"
        }
    ],
    "sg:phone":"+1 972 231 6569",
    "sg:postcode":"75080",
    "sg:province":"TX",
    "sg:tags":[
        "hanging",
        "contractor"
    ],
    "wof:name":"Horvath Tibor Painting",
    "wof:placetype":"venue"
},
  "geometry": {"coordinates":[-96.739746,32.968279],"type":"Point"}
}