{
  "type": "Feature",
  "properties": {
    "iso:country":"US",
    "sg:address":"408 Knightsbridge Rd",
    "sg:city":"Arlington",
    "sg:classifiers":[
        {
            "category":"Freight",
            "type":"Transportation"
        }
    ],
    "sg:phone":"+1 817 417 6834",
    "sg:postcode":"76014",
    "sg:province":"TX",
    "sg:tags":[
        "operator",
        "local",
        "trucking"
    ],
    "wof:name":"Saavedra Trucking",
    "wof:placetype":"venue"
},
  "geometry": {"coordinates":[-97.107608,32.693351],"type":"Point"}
}