{
  "type": "Feature",
  "properties": {
    "iso:country":"US",
    "sg:address":"2128 Cedar Dr",
    "sg:city":"Texas City",
    "sg:classifiers":[
        {
            "category":"Professional",
            "subcategory":"Business Services",
            "type":"Services"
        }
    ],
    "sg:phone":"+1 409 908 9033",
    "sg:postcode":"77568",
    "sg:province":"TX",
    "sg:tags":[
        "recording",
        "studio"
    ],
    "wof:name":"Studio B",
    "wof:placetype":"venue"
},
  "geometry": {"coordinates":[-94.975933,29.36854],"type":"Point"}
}