{
  "type": "Feature",
  "properties": {
    "iso:country":"US",
    "sg:address":"2691 Wilcrest Dr",
    "sg:city":"Houston",
    "sg:classifiers":[
        {
            "category":"Professional",
            "subcategory":"Business Services",
            "type":"Services"
        }
    ],
    "sg:phone":"+1 713 278 7278",
    "sg:postcode":"77042",
    "sg:province":"TX",
    "sg:tags":[
        "embroidery"
    ],
    "wof:name":"Embroidme",
    "wof:placetype":"venue"
},
  "geometry": {"coordinates":[-95.57168299999999,29.735543],"type":"Point"}
}