{
  "type": "Feature",
  "properties": {
    "iso:country":"US",
    "sg:address":"2416 Lillian Miller Pkwy",
    "sg:city":"Denton",
    "sg:classifiers":[
        {
            "category":"Banks & Credit Unions",
            "subcategory":"Bank",
            "type":"Services"
        }
    ],
    "sg:phone":"+1 940 383 3002",
    "sg:postcode":"76205",
    "sg:province":"TX",
    "sg:tags":[
        "loan"
    ],
    "wof:name":"Cash Now",
    "wof:placetype":"venue"
},
  "geometry": {"coordinates":[-97.10865200000001,33.186038],"type":"Point"}
}