{
  "type": "Feature",
  "properties": {
    "iso:country":"US",
    "sg:address":"3215 Sesbania Dr",
    "sg:city":"Austin",
    "sg:classifiers":[
        {
            "category":"Building & Trades",
            "subcategory":"Construction",
            "type":"Services"
        }
    ],
    "sg:phone":"+1 512 292 3823",
    "sg:postcode":"78748",
    "sg:province":"TX",
    "sg:tags":[
        "contractor"
    ],
    "wof:name":"Hawk Eye Tile Inc",
    "wof:placetype":"venue"
},
  "geometry": {"coordinates":[-97.85795400000001,30.163794],"type":"Point"}
}