{
  "type": "Feature",
  "properties": {
    "iso:country":"US",
    "sg:address":"8226 Marbach Rd",
    "sg:city":"San Antonio",
    "sg:classifiers":[
        {
            "category":"Health Services",
            "subcategory":"Doctor",
            "type":"Services"
        }
    ],
    "sg:phone":"+1 210 674 5370",
    "sg:postcode":"78227",
    "sg:province":"TX",
    "sg:tags":[
        "dentist"
    ],
    "wof:name":"Britt Shanna",
    "wof:placetype":"venue"
},
  "geometry": {"coordinates":[-98.652388,29.417759],"type":"Point"}
}