{
  "type": "Feature",
  "properties": {
    "iso:country":"US",
    "sg:address":"1621 Morrison Dr",
    "sg:city":"Fort Worth",
    "sg:classifiers":[
        {
            "category":"Professional",
            "subcategory":"Computer Services",
            "type":"Services"
        }
    ],
    "sg:phone":"+1 817 654 1475",
    "sg:postcode":"76112",
    "sg:province":"TX",
    "sg:tags":[
        "home",
        "consulting",
        "page",
        "dev",
        "internet"
    ],
    "wof:name":"Cyber Moon",
    "wof:placetype":"venue"
},
  "geometry": {"coordinates":[-97.19086900000001,32.756714],"type":"Point"}
}