{
  "type": "Feature",
  "properties": {
    "iso:country":"US",
    "sg:address":"7008 South Rice Ave.",
    "sg:city":"Bellaire",
    "sg:classifiers":[
        {
            "category":"Sports & Exercise",
            "subcategory":"Swimming Pool",
            "type":"Entertainment"
        }
    ],
    "sg:phone":"+1 713 662 8249",
    "sg:postcode":"77401",
    "sg:province":"TX",
    "sg:website":"www.ci.bellaire.tx.us/index.aspx...",
    "wof:name":"Bellaire Town Square Family Aquatic Center",
    "wof:placetype":"venue"
},
  "geometry": {"coordinates":[-95.46789699999999,29.70336],"type":"Point"}
}