{
  "type": "Feature",
  "properties": {
    "iso:country":"US",
    "sg:address":"4408 Burnet Rd",
    "sg:city":"Austin",
    "sg:classifiers":[
        {
            "category":"Professional",
            "subcategory":"Management & Consulting",
            "type":"Services"
        }
    ],
    "sg:phone":"+1 512 454 7234",
    "sg:postcode":"78756",
    "sg:province":"TX",
    "sg:tags":[
        "marketing",
        "agency"
    ],
    "wof:name":"MCS",
    "wof:placetype":"venue"
},
  "geometry": {"coordinates":[-97.742239,30.314382],"type":"Point"}
}