{
  "type": "Feature",
  "properties": {
    "iso:country":"US",
    "sg:address":"411 S Friendswood Dr",
    "sg:city":"Friendswood",
    "sg:classifiers":[
        {
            "category":"Shopping",
            "subcategory":"Crafts & Fabrics",
            "type":"Retail Goods"
        }
    ],
    "sg:phone":"+1 281 482 8546",
    "sg:postcode":"77546",
    "sg:province":"TX",
    "sg:tags":[
        "material",
        "needlework",
        "sewing"
    ],
    "wof:name":"Marie's Yarn Shop",
    "wof:placetype":"venue"
},
  "geometry": {"coordinates":[-95.200987,29.529472],"type":"Point"}
}