{
  "type": "Feature",
  "properties": {
    "iso:country":"US",
    "sg:address":"1111 Milford Way",
    "sg:city":"Austin",
    "sg:classifiers":[
        {
            "category":"Cinema",
            "subcategory":"Movie Rental",
            "type":"Entertainment"
        }
    ],
    "sg:phone":"+1 512 619 4371",
    "sg:postcode":"78745",
    "sg:province":"TX",
    "sg:tags":[
        "picture",
        "exchange",
        "motion",
        "distributor",
        "film"
    ],
    "wof:name":"Jcp Productions Unlmtd",
    "wof:placetype":"venue"
},
  "geometry": {"coordinates":[-97.792484,30.202615],"type":"Point"}
}