{
  "type": "Feature",
  "properties": {
    "iso:country":"US",
    "sg:address":"503 State Hwy 243",
    "sg:city":"Canton",
    "sg:classifiers":[
        {
            "category":"Health Services",
            "subcategory":"Nursing And Care Facility",
            "type":"Services"
        }
    ],
    "sg:phone":"+1 903 567 2762",
    "sg:postcode":"75103",
    "sg:province":"TX",
    "sg:tags":[
        "intermediate"
    ],
    "wof:name":"Gold Star Assisted Living",
    "wof:placetype":"venue"
},
  "geometry": {"coordinates":[-95.87264,32.543344],"type":"Point"}
}