{
  "type": "Feature",
  "properties": {
    "iso:country":"US",
    "sg:address":"14208 Tea Room Cove",
    "sg:city":"Pflugerville",
    "sg:classifiers":[
        {
            "category":"Building & Trades",
            "subcategory":"Construction",
            "type":"Services"
        }
    ],
    "sg:phone":"+1 512 252 3190",
    "sg:postcode":"78660",
    "sg:province":"TX",
    "sg:tags":[
        "home",
        "builder"
    ],
    "wof:name":"D R Horton Inc",
    "wof:placetype":"venue"
},
  "geometry": {"coordinates":[-97.635696,30.415456],"type":"Point"}
}