{
  "type": "Feature",
  "properties": {
    "iso:country":"US",
    "sg:address":"1755 W US Highway 69",
    "sg:city":"Emory",
    "sg:classifiers":[
        {
            "category":"Education",
            "subcategory":"School",
            "type":"Public Place"
        }
    ],
    "sg:phone":"+1 903 473 2222",
    "sg:postcode":"75440",
    "sg:province":"TX",
    "sg:website":"http://www.rains.isd-tx.net",
    "wof:name":"Rains Intermediate School",
    "wof:placetype":"venue"
},
  "geometry": {"coordinates":[-95.790132,32.891373],"type":"Point"}
}