{
  "type": "Feature",
  "properties": {
    "iso:country":"US",
    "sg:address":"3919 San Bernardo Ave",
    "sg:city":"Laredo",
    "sg:classifiers":[
        {
            "category":"Professional",
            "subcategory":"Business Services",
            "type":"Services"
        }
    ],
    "sg:phone":"+1 956 727 2014",
    "sg:postcode":"78041",
    "sg:province":"TX",
    "wof:name":"Check Rite Of Corpus Christi",
    "wof:placetype":"venue"
},
  "geometry": {"coordinates":[-99.50428700000001,27.535333],"type":"Point"}
}