{
  "type": "Feature",
  "properties": {
    "iso:country":"US",
    "sg:address":"302 W 6th St",
    "sg:city":"Cameron",
    "sg:classifiers":[
        {
            "category":"Health Services",
            "subcategory":"Clinic",
            "type":"Services"
        }
    ],
    "sg:phone":"+1 254 697 4422",
    "sg:postcode":"76520",
    "sg:province":"TX",
    "sg:tags":[
        "home",
        "care"
    ],
    "wof:name":"Family Care Home Health",
    "wof:placetype":"venue"
},
  "geometry": {"coordinates":[-96.977474,30.855006],"type":"Point"}
}