{
  "type": "Feature",
  "properties": {
    "iso:country":"US",
    "sg:address":"11200 Harry Hines Blvd",
    "sg:city":"Dallas",
    "sg:classifiers":[
        {
            "category":"Wholesale",
            "subcategory":"Computers",
            "type":"Manufacturing & Wholesale Goods"
        }
    ],
    "sg:phone":"+1 972 243 7571",
    "sg:postcode":"75229",
    "sg:province":"TX",
    "wof:name":"A Plus Computers",
    "wof:placetype":"venue"
},
  "geometry": {"coordinates":[-96.88864,32.889256],"type":"Point"}
}