{
  "type": "Feature",
  "properties": {
    "iso:country":"US",
    "sg:address":"6143 Sunset Haven St",
    "sg:city":"San Antonio",
    "sg:classifiers":[
        {
            "category":"Professional",
            "subcategory":"Business Services",
            "type":"Services"
        }
    ],
    "sg:phone":"+1 210 558 1578",
    "sg:postcode":"78249",
    "sg:province":"TX",
    "wof:name":"Crystal Scents Etc",
    "wof:placetype":"venue"
},
  "geometry": {"coordinates":[-98.609692,29.556858],"type":"Point"}
}