{
  "type": "Feature",
  "properties": {
    "iso:country":"US",
    "sg:address":"3975 High Summit Dr",
    "sg:city":"Dallas",
    "sg:classifiers":[
        {
            "category":"Professional",
            "subcategory":"Lawyer & Legal Services",
            "type":"Services"
        }
    ],
    "sg:phone":"+1 972 241 1366",
    "sg:postcode":"75244",
    "sg:province":"TX",
    "wof:name":"Smith Frank Tupper Jr Atty",
    "wof:placetype":"venue"
},
  "geometry": {"coordinates":[-96.847504,32.9188],"type":"Point"}
}