{
  "type": "Feature",
  "properties": {
    "iso:country":"US",
    "sg:address":"3708 Amelia Dr",
    "sg:city":"Midland",
    "sg:classifiers":[
        {
            "category":"Building & Trades",
            "subcategory":"Construction",
            "type":"Services"
        }
    ],
    "sg:phone":"+1 432 694 8412",
    "sg:postcode":"79703",
    "sg:province":"TX",
    "sg:tags":[
        "house",
        "contractor"
    ],
    "wof:name":"Jerry Hayes Builders",
    "wof:placetype":"venue"
},
  "geometry": {"coordinates":[-102.119105,31.977704],"type":"Point"}
}