{
  "type": "Feature",
  "properties": {
    "iso:country":"US",
    "sg:address":"1710 Federal Rd",
    "sg:city":"Houston",
    "sg:classifiers":[
        {
            "category":"Professional",
            "type":"Services"
        }
    ],
    "sg:phone":"+1 713 455 8918",
    "sg:postcode":"77015",
    "sg:province":"TX",
    "wof:name":"Angela Ortiz",
    "wof:placetype":"venue"
},
  "geometry": {"coordinates":[-95.213128,29.759495],"type":"Point"}
}