{
  "type": "Feature",
  "properties": {
    "iso:country":"US",
    "sg:address":"431 Broadway St",
    "sg:city":"Plainview",
    "sg:classifiers":[
        {
            "category":"Shopping",
            "subcategory":"Used Merchandise",
            "type":"Retail Goods"
        }
    ],
    "sg:phone":"+1 806 293 3118",
    "sg:postcode":"79072",
    "sg:province":"TX",
    "sg:tags":[
        "antique",
        "shop",
        "gift"
    ],
    "wof:name":"Passport Gift Collection",
    "wof:placetype":"venue"
},
  "geometry": {"coordinates":[-101.703065,34.184165],"type":"Point"}
}