{
  "type": "Feature",
  "properties": {
    "iso:country":"US",
    "sg:address":"1413 Butlercrest St",
    "sg:city":"Houston",
    "sg:classifiers":[
        {
            "category":"Arena",
            "subcategory":"Sports Club",
            "type":"Entertainment"
        }
    ],
    "sg:phone":"+1 713 468 4879",
    "sg:postcode":"77080",
    "sg:province":"TX",
    "sg:tags":[
        "martial art"
    ],
    "wof:name":"Geis Karl Judo School Inc",
    "wof:placetype":"venue"
},
  "geometry": {"coordinates":[-95.53589599999999,29.7945],"type":"Point"}
}