{
  "type": "Feature",
  "properties": {
    "iso:country":"US",
    "sg:address":"1717 Nederland Ave",
    "sg:city":"Nederland",
    "sg:classifiers":[
        {
            "category":"Autos & Motor Vehicles",
            "subcategory":"Fuel & Gas Station",
            "type":"Retail Goods"
        }
    ],
    "sg:phone":"+1 409 727 5076",
    "sg:postcode":"77627",
    "sg:province":"TX",
    "sg:tags":[
        "convenience",
        "station"
    ],
    "wof:name":"Chevron",
    "wof:placetype":"venue"
},
  "geometry": {"coordinates":[-93.99301199999999,29.970549],"type":"Point"}
}