{
  "type": "Feature",
  "properties": {
    "iso:country":"US",
    "sg:address":"6500 Cypress Point Dr",
    "sg:city":"Plano",
    "sg:classifiers":[
        {
            "category":"Shopping",
            "type":"Retail Goods"
        }
    ],
    "sg:phone":"+1 469 443 0702",
    "sg:postcode":"75093",
    "sg:province":"TX",
    "sg:tags":[
        "merchandise"
    ],
    "wof:name":"H Parker Deidrea",
    "wof:placetype":"venue"
},
  "geometry": {"coordinates":[-96.84099999999999,33.041719],"type":"Point"}
}