{
  "type": "Feature",
  "properties": {
    "iso:country":"US",
    "sg:address":"1153 Beagle Rd",
    "sg:city":"Orange",
    "sg:classifiers":[
        {
            "category":"Building & Trades",
            "subcategory":"Landscaping Services",
            "type":"Services"
        }
    ],
    "sg:phone":"+1 409 883 8818",
    "sg:postcode":"77632",
    "sg:province":"TX",
    "sg:tags":[
        "tree"
    ],
    "wof:name":"Owen Tree Service",
    "wof:placetype":"venue"
},
  "geometry": {"coordinates":[-93.76460299999999,30.154377],"type":"Point"}
}