{
  "type": "Feature",
  "properties": {
    "iso:country":"US",
    "sg:address":"2615 Bluerock St",
    "sg:city":"Houston",
    "sg:classifiers":[
        {
            "category":"Shopping",
            "subcategory":"Gifts & Souvenirs",
            "type":"Retail Goods"
        }
    ],
    "sg:phone":"+1 281 442 0965",
    "sg:postcode":"77039",
    "sg:province":"TX",
    "wof:name":"Flowers Unlimited & Gifts",
    "wof:placetype":"venue"
},
  "geometry": {"coordinates":[-95.34725299999999,29.910458],"type":"Point"}
}