{
  "type": "Feature",
  "properties": {
    "iso:country":"US",
    "sg:address":"2501 E 8th St",
    "sg:city":"Odessa",
    "sg:classifiers":[
        {
            "category":"Autos & Motor Vehicles",
            "subcategory":"Automobile Sales",
            "type":"Retail Goods"
        }
    ],
    "sg:phone":"+1 432 580 6800",
    "sg:postcode":"79761",
    "sg:province":"TX",
    "sg:tags":[
        "used"
    ],
    "wof:name":"Liberty Motors",
    "wof:placetype":"venue"
},
  "geometry": {"coordinates":[-102.332427,31.863996],"type":"Point"}
}