{
  "type": "Feature",
  "properties": {
    "iso:country":"US",
    "sg:address":"3829 Flory Ave",
    "sg:city":"El Paso",
    "sg:classifiers":[
        {
            "category":"Manufacturing",
            "subcategory":"Retail Goods",
            "type":"Manufacturing & Wholesale Goods"
        }
    ],
    "sg:phone":"+1 915 564 3136",
    "sg:postcode":"79904",
    "sg:province":"TX",
    "sg:tags":[
        "product",
        "mfg"
    ],
    "wof:name":"Simply Buttons",
    "wof:placetype":"venue"
},
  "geometry": {"coordinates":[-106.447048,31.832203],"type":"Point"}
}