{
  "type": "Feature",
  "properties": {
    "iso:country":"US",
    "sg:address":"12345 Alameda Trace Cir",
    "sg:city":"Austin",
    "sg:classifiers":[
        {
            "category":"Professional",
            "subcategory":"Advertising",
            "type":"Services"
        }
    ],
    "sg:phone":"+1 512 506 9912",
    "sg:postcode":"78727",
    "sg:province":"TX",
    "sg:tags":[
        "agency"
    ],
    "wof:name":"Blue Sky Advertising LLC",
    "wof:placetype":"venue"
},
  "geometry": {"coordinates":[-97.74773,30.429913],"type":"Point"}
}