{
  "type": "Feature",
  "properties": {
    "iso:country":"US",
    "sg:address":"200 N Main St",
    "sg:city":"Andrews",
    "sg:classifiers":[
        {
            "category":"Shopping",
            "subcategory":"Pharmacy",
            "type":"Retail Goods"
        }
    ],
    "sg:phone":"+1 432 523 2430",
    "sg:postcode":"79714",
    "sg:province":"TX",
    "wof:name":"Corner Drug",
    "wof:placetype":"venue"
},
  "geometry": {"coordinates":[-102.54703499999999,32.320273],"type":"Point"}
}