{
  "type": "Feature",
  "properties": {
    "iso:country":"US",
    "sg:address":"319 Mcarthur St",
    "sg:city":"Athens",
    "sg:classifiers":[
        {
            "category":"Building & Trades",
            "subcategory":"Landscaping Services",
            "type":"Services"
        }
    ],
    "sg:phone":"+1 903 292 1463",
    "sg:postcode":"75751",
    "sg:province":"TX",
    "sg:tags":[
        "tree"
    ],
    "wof:name":"Cs Tree Service Inc",
    "wof:placetype":"venue"
},
  "geometry": {"coordinates":[-95.87808200000001,32.20517],"type":"Point"}
}