{
  "type": "Feature",
  "properties": {
    "iso:country":"US",
    "sg:address":"251 S Guenther Ave",
    "sg:city":"New Braunfels",
    "sg:classifiers":[
        {
            "category":"Organizations",
            "subcategory":"Religious Organization",
            "type":"Services"
        }
    ],
    "sg:phone":"+1 830 624 2762",
    "sg:postcode":"78130",
    "sg:province":"TX",
    "wof:name":"Revival Ministries Intl",
    "wof:placetype":"venue"
},
  "geometry": {"coordinates":[-98.12778299999999,29.696613],"type":"Point"}
}