{
  "type": "Feature",
  "properties": {
    "iso:country":"US",
    "sg:address":"2800 Yeager St",
    "sg:city":"Fort Worth",
    "sg:classifiers":[
        {
            "category":"Social Services",
            "subcategory":"Child Care",
            "type":"Services"
        }
    ],
    "sg:phone":"+1 817 446 0053",
    "sg:postcode":"76112",
    "sg:province":"TX",
    "sg:tags":[
        "day"
    ],
    "wof:name":"Kidcare",
    "wof:placetype":"venue"
},
  "geometry": {"coordinates":[-97.23339,32.737783],"type":"Point"}
}