{
  "type": "Feature",
  "properties": {
    "iso:country":"US",
    "sg:address":"520 W 12th St",
    "sg:city":"Texarkana",
    "sg:classifiers":[
        {
            "category":"Health Services",
            "subcategory":"Doctor",
            "type":"Services"
        }
    ],
    "sg:phone":"+1 903 792 1216",
    "sg:postcode":"75501",
    "sg:province":"TX",
    "sg:tags":[
        "physician",
        "surgeon"
    ],
    "wof:name":"Medselect",
    "wof:placetype":"venue"
},
  "geometry": {"coordinates":[-94.048202,33.430753],"type":"Point"}
}