{
  "type": "Feature",
  "properties": {
    "iso:country":"US",
    "sg:address":"12316 Fondren Rd",
    "sg:city":"Houston",
    "sg:classifiers":[
        {
            "category":"Personal",
            "subcategory":"Beauty Salon",
            "type":"Services"
        }
    ],
    "sg:phone":"+1 713 721 3481",
    "sg:postcode":"77035",
    "sg:province":"TX",
    "sg:tags":[
        "shop"
    ],
    "wof:name":"Nails By Yen",
    "wof:placetype":"venue"
},
  "geometry": {"coordinates":[-95.50837300000001,29.644009],"type":"Point"}
}