{
  "type": "Feature",
  "properties": {
    "iso:country":"US",
    "sg:address":"408 Silverton Dr",
    "sg:city":"Irving",
    "sg:classifiers":[
        {
            "category":"Food & Beverages",
            "subcategory":"Meat & Fish",
            "type":"Retail Goods"
        }
    ],
    "sg:phone":"+1 972 432 8638",
    "sg:postcode":"75063",
    "sg:province":"TX",
    "wof:name":"Action Meat Dfw",
    "wof:placetype":"venue"
},
  "geometry": {"coordinates":[-96.9504,32.930177],"type":"Point"}
}