{
  "type": "Feature",
  "properties": {
    "iso:country":"US",
    "sg:address":"730 Briggs St",
    "sg:city":"Cedar Hill",
    "sg:classifiers":[
        {
            "category":"Professional",
            "subcategory":"Business Services",
            "type":"Services"
        }
    ],
    "sg:phone":"+1 972 291 2830",
    "sg:postcode":"75104",
    "sg:province":"TX",
    "wof:name":"Pbp Enterprises",
    "wof:placetype":"venue"
},
  "geometry": {"coordinates":[-96.95779400000001,32.598162],"type":"Point"}
}