{
  "type": "Feature",
  "properties": {
    "iso:country":"US",
    "sg:address":"100 N 5th St",
    "sg:city":"Driscoll",
    "sg:classifiers":[
        {
            "category":"Wholesale",
            "subcategory":"Farm Supplies",
            "type":"Manufacturing & Wholesale Goods"
        }
    ],
    "sg:phone":"+1 361 387 6242",
    "sg:postcode":"78358",
    "sg:province":"TX",
    "sg:tags":[
        "grain"
    ],
    "wof:name":"Driscoll Grain Co-Op",
    "wof:placetype":"venue"
},
  "geometry": {"coordinates":[-97.038342,28.062855],"type":"Point"}
}