{
  "type": "Feature",
  "properties": {
    "iso:country":"US",
    "sg:address":"4222 Trinity Mills Rd",
    "sg:city":"Dallas",
    "sg:classifiers":[
        {
            "category":"Health Services",
            "subcategory":"Doctor",
            "type":"Services"
        }
    ],
    "sg:phone":"+1 972 250 4016",
    "sg:postcode":"75287",
    "sg:province":"TX",
    "sg:tags":[
        "medical"
    ],
    "wof:name":"Dutta P C MD PA",
    "wof:placetype":"venue"
},
  "geometry": {"coordinates":[-96.838262,32.987609],"type":"Point"}
}