{
  "type": "Feature",
  "properties": {
    "iso:country":"US",
    "sg:address":"1412 San Saba Dr",
    "sg:city":"Dallas",
    "sg:classifiers":[
        {
            "category":"Building & Trades",
            "subcategory":"Landscaping Services",
            "type":"Services"
        }
    ],
    "sg:phone":"+1 214 320 3764",
    "sg:postcode":"75218",
    "sg:province":"TX",
    "sg:tags":[
        "landscape"
    ],
    "wof:name":"Office of Christopher Miller",
    "wof:placetype":"venue"
},
  "geometry": {"coordinates":[-96.70313899999999,32.826039],"type":"Point"}
}