{
  "type": "Feature",
  "properties": {
    "iso:country":"US",
    "sg:address":"9 Medical Pkwy N",
    "sg:city":"Dallas",
    "sg:classifiers":[
        {
            "category":"Health Services",
            "subcategory":"Doctor",
            "type":"Services"
        }
    ],
    "sg:phone":"+1 972 484 7880",
    "sg:postcode":"75234",
    "sg:province":"TX",
    "sg:tags":[
        "physician",
        "surgeon"
    ],
    "wof:name":"Julio E Len Pediatrics",
    "wof:placetype":"venue"
},
  "geometry": {"coordinates":[-96.87167100000001,32.915507],"type":"Point"}
}