{
  "type": "Feature",
  "properties": {
    "iso:country":"US",
    "sg:address":"1500 S Dairy Ashford St",
    "sg:city":"Houston",
    "sg:classifiers":[
        {
            "category":"Building & Trades",
            "subcategory":"Construction",
            "type":"Services"
        }
    ],
    "sg:phone":"+1 281 589 2525",
    "sg:postcode":"77077",
    "sg:province":"TX",
    "sg:tags":[
        "general",
        "contractor"
    ],
    "wof:name":"EIU",
    "wof:placetype":"venue"
},
  "geometry": {"coordinates":[-95.606078,29.752409],"type":"Point"}
}