{
  "type": "Feature",
  "properties": {
    "iso:country":"US",
    "sg:address":"1111 W Ledbetter Dr",
    "sg:city":"Dallas",
    "sg:classifiers":[
        {
            "category":"Banks & Credit Unions",
            "subcategory":"Bank",
            "type":"Services"
        }
    ],
    "sg:phone":"+1 214 374 8899",
    "sg:postcode":"75224",
    "sg:province":"TX",
    "sg:tags":[
        "loan",
        "broker",
        "mortgage"
    ],
    "wof:name":"Allied Home Mrtg Capitl Corp",
    "wof:placetype":"venue"
},
  "geometry": {"coordinates":[-96.84004899999999,32.691288],"type":"Point"}
}