{
  "type": "Feature",
  "properties": {
    "iso:country":"US",
    "sg:address":"430 McMullen St",
    "sg:city":"San Antonio",
    "sg:classifiers":[
        {
            "category":"Manufacturing",
            "subcategory":"Rubber & Plastics",
            "type":"Manufacturing & Wholesale Goods"
        }
    ],
    "sg:phone":"+1 210 884 3539",
    "sg:postcode":"78210",
    "sg:province":"TX",
    "sg:tags":[
        "product",
        "fabricated",
        "mfg"
    ],
    "wof:name":"IMG Medical",
    "wof:placetype":"venue"
},
  "geometry": {"coordinates":[-98.48493999999999,29.38574],"type":"Point"}
}