{
  "type": "Feature",
  "properties": {
    "iso:country":"US",
    "sg:address":"16020 Chalfont Cir",
    "sg:city":"Dallas",
    "sg:classifiers":[
        {
            "category":"Organizations",
            "subcategory":"Membership Organization",
            "type":"Services"
        }
    ],
    "sg:phone":"+1 972 991 9803",
    "sg:postcode":"75248",
    "sg:province":"TX",
    "wof:name":"Laction Automobile",
    "wof:placetype":"venue"
},
  "geometry": {"coordinates":[-96.80504000000001,32.967489],"type":"Point"}
}