{
  "type": "Feature",
  "properties": {
    "iso:country":"US",
    "sg:address":"5950 FM 1082",
    "sg:city":"Hawley",
    "sg:classifiers":[
        {
            "category":"Shopping",
            "type":"Retail Goods"
        }
    ],
    "sg:phone":"+1 325 537 2485",
    "sg:postcode":"79525",
    "sg:province":"TX",
    "sg:tags":[
        "merchandise"
    ],
    "wof:name":"James Burleson",
    "wof:placetype":"venue"
},
  "geometry": {"coordinates":[-99.75541699999999,32.595696],"type":"Point"}
}