{
  "type": "Feature",
  "properties": {
    "iso:country":"US",
    "sg:address":"5456 Frontier Dr",
    "sg:city":"Sanger",
    "sg:classifiers":[
        {
            "category":"Wholesale",
            "subcategory":"Apparel",
            "type":"Manufacturing & Wholesale Goods"
        },
        {
            "category":"Shopping",
            "subcategory":"Shoes",
            "type":"Retail Goods"
        }
    ],
    "sg:phone":"+1 940 458 7646",
    "sg:postcode":"76266",
    "sg:province":"TX",
    "sg:tags":[
        "shoes-wholesale",
        "boots-retail",
        "manufacturer"
    ],
    "wof:name":"C Bar T Inc",
    "wof:placetype":"venue"
},
  "geometry": {"coordinates":[-97.221962,33.401943],"type":"Point"}
}