{
  "type": "Feature",
  "properties": {
    "iso:country":"US",
    "sg:address":"2408 Texas Ave",
    "sg:city":"El Paso",
    "sg:classifiers":[
        {
            "category":"Home & Garden",
            "subcategory":"Household Appliances",
            "type":"Retail Goods"
        }
    ],
    "sg:phone":"+1 915 564 8247",
    "sg:postcode":"79901",
    "sg:province":"TX",
    "sg:tags":[
        "machine",
        "sewing"
    ],
    "wof:name":"La Internacional",
    "wof:placetype":"venue"
},
  "geometry": {"coordinates":[-106.462244,31.774695],"type":"Point"}
}