{
  "type": "Feature",
  "properties": {
    "iso:country":"US",
    "sg:address":"4901 Eldorado Pkwy",
    "sg:city":"Mc Kinney",
    "sg:classifiers":[
        {
            "category":"Autos & Motor Vehicles",
            "subcategory":"Auto Supplies",
            "type":"Retail Goods"
        }
    ],
    "sg:phone":"+1 214 592 0005",
    "sg:postcode":"75070",
    "sg:province":"TX",
    "sg:tags":[
        "tire"
    ],
    "sg:website":"www.greatamerican.com",
    "wof:name":"Great American Tire & Auto Svc",
    "wof:placetype":"venue"
},
  "geometry": {"coordinates":[-96.681214,33.173473],"type":"Point"}
}