{
  "type": "Feature",
  "properties": {
    "iso:country":"US",
    "sg:address":"12125 Abrams Rd",
    "sg:city":"Dallas",
    "sg:classifiers":[
        {
            "category":"Cinema",
            "subcategory":"Movie Rental",
            "type":"Entertainment"
        }
    ],
    "sg:phone":"+1 972 680 9940",
    "sg:postcode":"75243",
    "sg:province":"TX",
    "sg:tags":[
        "leasing",
        "motion",
        "disc",
        "tape",
        "video",
        "distribution"
    ],
    "wof:name":"I Love Video",
    "wof:placetype":"venue"
},
  "geometry": {"coordinates":[-96.735608,32.912192],"type":"Point"}
}