{
  "type": "Feature",
  "properties": {
    "iso:country":"US",
    "sg:address":"7204 Rusty Fig Dr",
    "sg:city":"Austin",
    "sg:classifiers":[
        {
            "category":"Professional",
            "subcategory":"Computer Services",
            "type":"Services"
        }
    ],
    "sg:phone":"+1 512 418 9348",
    "sg:postcode":"78750",
    "sg:province":"TX",
    "sg:tags":[
        "development",
        "software"
    ],
    "wof:name":"Potomac Fusion Inc",
    "wof:placetype":"venue"
},
  "geometry": {"coordinates":[-97.794714,30.376417],"type":"Point"}
}