{
  "type": "Feature",
  "properties": {
    "iso:country":"US",
    "sg:address":"1312 Southmoor Dr",
    "sg:city":"Arlington",
    "sg:classifiers":[
        {
            "category":"Organizations",
            "subcategory":"Religious Organization",
            "type":"Services"
        }
    ],
    "sg:phone":"+1 817 801 0574",
    "sg:postcode":"76010",
    "sg:province":"TX",
    "wof:name":"Broken Women Ministry",
    "wof:placetype":"venue"
},
  "geometry": {"coordinates":[-97.0924,32.709555],"type":"Point"}
}