{
  "type": "Feature",
  "properties": {
    "iso:country":"US",
    "sg:address":"4505 State Hwy 146",
    "sg:city":"Bacliff",
    "sg:classifiers":[
        {
            "category":"Restaurant",
            "type":"Food & Drink"
        }
    ],
    "sg:phone":"+1 281 339 5949",
    "sg:postcode":"77518",
    "sg:province":"TX",
    "wof:name":"Mc Donald's",
    "wof:placetype":"venue"
},
  "geometry": {"coordinates":[-94.995408,29.499368],"type":"Point"}
}