{
  "type": "Feature",
  "properties": {
    "iso:country":"US",
    "sg:address":"2909 Bolero Ct",
    "sg:city":"College Station",
    "sg:classifiers":[
        {
            "category":"Professional",
            "subcategory":"Business Services",
            "type":"Services"
        }
    ],
    "sg:phone":"+1 979 693 4313",
    "sg:postcode":"77845",
    "sg:province":"TX",
    "wof:name":"Tody Squarters Bed & Breakfast",
    "wof:placetype":"venue"
},
  "geometry": {"coordinates":[-96.313519,30.581068],"type":"Point"}
}