{
  "type": "Feature",
  "properties": {
    "iso:country":"US",
    "sg:address":"300 Centre St",
    "sg:city":"Dallas",
    "sg:classifiers":[
        {
            "category":"Real Estate",
            "subcategory":"Real Estate Services",
            "type":"Services"
        }
    ],
    "sg:phone":"+1 214 941 5253",
    "sg:postcode":"75208",
    "sg:province":"TX",
    "sg:tags":[
        "company",
        "title"
    ],
    "wof:name":"Fidelity National Title",
    "wof:placetype":"venue"
},
  "geometry": {"coordinates":[-96.8283,32.742283],"type":"Point"}
}