{
  "type": "Feature",
  "properties": {
    "iso:country":"US",
    "sg:address":"108 N Texana St",
    "sg:city":"Hallettsville",
    "sg:classifiers":[
        {
            "category":"Insurance",
            "subcategory":"Insurance Agent",
            "type":"Services"
        }
    ],
    "sg:phone":"+1 361 798 4245",
    "sg:postcode":"77964",
    "sg:province":"TX",
    "wof:name":"Barnes Insurance",
    "wof:placetype":"venue"
},
  "geometry": {"coordinates":[-96.941562,29.445549],"type":"Point"}
}