{
  "type": "Feature",
  "properties": {
    "iso:country":"US",
    "sg:address":"2719 Mier St",
    "sg:city":"Laredo",
    "sg:classifiers":[
        {
            "category":"Recreation",
            "type":"Entertainment"
        },
        {
            "category":"Restaurant",
            "type":"Food & Drink"
        }
    ],
    "sg:phone":"+1 956 722 9410",
    "sg:postcode":"78043",
    "sg:province":"TX",
    "sg:tags":[
        "eating",
        "amusement"
    ],
    "wof:name":"Raspas Iglu",
    "wof:placetype":"venue"
},
  "geometry": {"coordinates":[-99.46818,27.510147],"type":"Point"}
}