{
  "type": "Feature",
  "properties": {
    "iso:country":"US",
    "sg:address":"7208 Nordling Rd",
    "sg:city":"Houston",
    "sg:classifiers":[
        {
            "category":"Personal",
            "type":"Services"
        }
    ],
    "sg:phone":"+1 713 694 3684",
    "sg:postcode":"77076",
    "sg:province":"TX",
    "wof:name":"LA-Fontana Hall",
    "wof:placetype":"venue"
},
  "geometry": {"coordinates":[-95.391097,29.866451],"type":"Point"}
}