{
  "type": "Feature",
  "properties": {
    "iso:country":"US",
    "sg:address":"5312 Taylor Rd",
    "sg:city":"Fort Worth",
    "sg:classifiers":[
        {
            "category":"Shopping",
            "type":"Retail Goods"
        }
    ],
    "sg:phone":"+1 817 738 1825",
    "sg:postcode":"76114",
    "sg:province":"TX",
    "sg:tags":[
        "merchandise"
    ],
    "wof:name":"Michael D Deatherage",
    "wof:placetype":"venue"
},
  "geometry": {"coordinates":[-97.401614,32.766474],"type":"Point"}
}