{
  "type": "Feature",
  "properties": {
    "iso:country":"US",
    "sg:address":"7400 Harwin Dr",
    "sg:city":"Houston",
    "sg:classifiers":[
        {
            "category":"Health Services",
            "subcategory":"Dentist",
            "type":"Services"
        }
    ],
    "sg:phone":"+1 713 914 0500",
    "sg:postcode":"77036",
    "sg:province":"TX",
    "wof:name":"Grand Products Company Inc",
    "wof:placetype":"venue"
},
  "geometry": {"coordinates":[-95.512624,29.717967],"type":"Point"}
}