{
  "type": "Feature",
  "properties": {
    "iso:country":"US",
    "sg:address":"3122 Kellway Dr",
    "sg:city":"Carrollton",
    "sg:classifiers":[
        {
            "category":"Retail",
            "subcategory":"Auto Rental",
            "type":"Services"
        }
    ],
    "sg:phone":"+1 972 407 9560",
    "sg:postcode":"75006",
    "sg:province":"TX",
    "sg:tags":[
        "renting",
        "automobile"
    ],
    "wof:name":"Premier Car Rental",
    "wof:placetype":"venue"
},
  "geometry": {"coordinates":[-96.84671299999999,32.972303],"type":"Point"}
}