{
  "type": "Feature",
  "properties": {
    "iso:country":"US",
    "sg:address":"104 W Oak Ave",
    "sg:city":"Mertzon",
    "sg:classifiers":[
        {
            "category":"Building & Trades",
            "subcategory":"Electrical",
            "type":"Services"
        }
    ],
    "sg:phone":"+1 325 835 9939",
    "sg:postcode":"76941",
    "sg:province":"TX",
    "sg:tags":[
        "electrical",
        "contractor"
    ],
    "wof:name":"Oak Electric Company",
    "wof:placetype":"venue"
},
  "geometry": {"coordinates":[-100.82042800000001,31.265619],"type":"Point"}
}