{
  "type": "Feature",
  "properties": {
    "iso:country":"US",
    "sg:address":"317 Peoples St",
    "sg:city":"Corpus Christi",
    "sg:classifiers":[
        {
            "category":"Professional",
            "type":"Services"
        }
    ],
    "sg:phone":"+1 361 561 0567",
    "sg:postcode":"78401",
    "sg:province":"TX",
    "sg:tags":[
        "establishment"
    ],
    "wof:name":"Fischer Operating Corp",
    "wof:placetype":"venue"
},
  "geometry": {"coordinates":[-97.39366800000001,27.796732],"type":"Point"}
}