{
  "type": "Feature",
  "properties": {
    "iso:country":"US",
    "sg:address":"702 S Stemmons Fwy",
    "sg:city":"Lewisville",
    "sg:classifiers":[
        {
            "category":"Building & Trades",
            "subcategory":"Construction",
            "type":"Services"
        }
    ],
    "sg:phone":"+1 972 221 0095",
    "sg:postcode":"75067",
    "sg:province":"TX",
    "sg:tags":[
        "general",
        "contractor"
    ],
    "sg:website":"www.neconstructioninc.com",
    "wof:name":"N E Construction LTD",
    "wof:placetype":"venue"
},
  "geometry": {"coordinates":[-97.003102,33.039859],"type":"Point"}
}