{
  "type": "Feature",
  "properties": {
    "iso:country":"US",
    "sg:address":"600 E Taylor St",
    "sg:city":"Sherman",
    "sg:classifiers":[
        {
            "category":"Real Estate",
            "subcategory":"Real Estate Agent",
            "type":"Services"
        }
    ],
    "sg:phone":"+1 903 870 0979",
    "sg:postcode":"75090",
    "sg:province":"TX",
    "wof:name":"Cantex Management Corp",
    "wof:placetype":"venue"
},
  "geometry": {"coordinates":[-96.60672599999999,33.656875],"type":"Point"}
}