{
  "type": "Feature",
  "properties": {
    "iso:country":"US",
    "sg:address":"3500 Wheatley Pl",
    "sg:city":"Dallas",
    "sg:classifiers":[
        {
            "category":"Health Services",
            "subcategory":"Hospital",
            "type":"Services"
        }
    ],
    "sg:phone":"+1 214 947 0813",
    "sg:postcode":"75204",
    "sg:province":"TX",
    "sg:tags":[
        "general"
    ],
    "wof:name":"Methodist Hospitals of Dallas",
    "wof:placetype":"venue"
},
  "geometry": {"coordinates":[-96.789963,32.798372],"type":"Point"}
}