{
  "type": "Feature",
  "properties": {
    "iso:country":"US",
    "sg:address":"916 Main St",
    "sg:city":"Lubbock",
    "sg:classifiers":[
        {
            "category":"Government",
            "subcategory":"Court House",
            "type":"Public Place"
        }
    ],
    "sg:phone":"+1 806 765 0094",
    "sg:postcode":"79401",
    "sg:province":"TX",
    "sg:tags":[
        "enforcement",
        "support",
        "child"
    ],
    "wof:name":"Child Support Enforcement",
    "wof:placetype":"venue"
},
  "geometry": {"coordinates":[-101.845474,33.585582],"type":"Point"}
}