{
  "type": "Feature",
  "properties": {
    "iso:country":"US",
    "sg:address":"12955 W Airport Blvd",
    "sg:city":"Sugar Land",
    "sg:phone":"+1 281 340 8400",
    "sg:postcode":"77478",
    "sg:province":"TX",
    "sg:tags":[
        "agricultural",
        "tool",
        "cookware",
        "cutlery",
        "hand"
    ],
    "wof:name":"Tramontina USA Inc",
    "wof:placetype":"venue"
},
  "geometry": {"coordinates":[-95.609103,29.645562],"type":"Point"}
}