{
  "type": "Feature",
  "properties": {
    "iso:country":"US",
    "sg:address":"301 Colonial Dr",
    "sg:city":"Friendswood",
    "sg:classifiers":[
        {
            "category":"Manufacturing",
            "subcategory":"Printing",
            "type":"Manufacturing & Wholesale Goods"
        }
    ],
    "sg:phone":"+1 281 482 4890",
    "sg:postcode":"77546",
    "sg:province":"TX",
    "sg:tags":[
        "publishing"
    ],
    "wof:name":"Full House Publishing",
    "wof:placetype":"venue"
},
  "geometry": {"coordinates":[-95.19541700000001,29.534596],"type":"Point"}
}