{
  "type": "Feature",
  "properties": {
    "iso:country":"US",
    "sg:address":"7629 Tezel Rd",
    "sg:city":"San Antonio",
    "sg:classifiers":[
        {
            "category":"Health Services",
            "subcategory":"Doctor",
            "type":"Services"
        }
    ],
    "sg:phone":"+1 210 509 2487",
    "sg:postcode":"78250",
    "sg:province":"TX",
    "wof:name":"Brad D Bruchmiller",
    "wof:placetype":"venue"
},
  "geometry": {"coordinates":[-98.662404,29.510734],"type":"Point"}
}