{
  "type": "Feature",
  "properties": {
    "iso:country":"US",
    "sg:address":"5 Eureka Cir",
    "sg:city":"Wichita Falls",
    "sg:classifiers":[
        {
            "category":"Health Services",
            "subcategory":"Doctor",
            "type":"Services"
        }
    ],
    "sg:phone":"+1 940 696 0326",
    "sg:postcode":"76308",
    "sg:province":"TX",
    "wof:name":"Frank L Jones DDS Ms",
    "wof:placetype":"venue"
},
  "geometry": {"coordinates":[-98.526338,33.869527],"type":"Point"}
}