{
  "type": "Feature",
  "properties": {
    "iso:country":"US",
    "sg:address":"125 E 6th St",
    "sg:city":"Rusk",
    "sg:classifiers":[
        {
            "category":"Real Estate",
            "subcategory":"Real Estate Agent",
            "type":"Services"
        }
    ],
    "sg:phone":"+1 903 683 2614",
    "sg:postcode":"75785",
    "sg:province":"TX",
    "wof:name":"Arrow Head Creek Realty Inc",
    "wof:placetype":"venue"
},
  "geometry": {"coordinates":[-95.149478,31.796011],"type":"Point"}
}