{
  "type": "Feature",
  "properties": {
    "iso:country":"US",
    "sg:address":"821 W Russell Pl",
    "sg:city":"San Antonio",
    "sg:classifiers":[
        {
            "category":"Wholesale",
            "subcategory":"Dairy",
            "type":"Manufacturing & Wholesale Goods"
        }
    ],
    "sg:phone":"+1 210 733 8655",
    "sg:postcode":"78212",
    "sg:province":"TX",
    "sg:tags":[
        "product"
    ],
    "wof:name":"Fernando L Gutierrez Distrg Co",
    "wof:placetype":"venue"
},
  "geometry": {"coordinates":[-98.504159,29.451097],"type":"Point"}
}