{
  "type": "Feature",
  "properties": {
    "iso:country":"US",
    "sg:address":"2420 Herring Ave",
    "sg:city":"Waco",
    "sg:classifiers":[
        {
            "category":"Personal",
            "subcategory":"Beauty Salon",
            "type":"Services"
        }
    ],
    "sg:phone":"+1 254 753 3561",
    "sg:postcode":"76708",
    "sg:province":"TX",
    "wof:name":"Dot's Coiffures & Wig Fashions",
    "wof:placetype":"venue"
},
  "geometry": {"coordinates":[-97.168724,31.563196],"type":"Point"}
}