{
  "type": "Feature",
  "properties": {
    "iso:country":"US",
    "sg:address":"3401 San Mateo Dr",
    "sg:city":"Austin",
    "sg:classifiers":[
        {
            "category":"Professional",
            "type":"Services"
        }
    ],
    "sg:phone":"+1 512 263 0206",
    "sg:postcode":"78738",
    "sg:province":"TX",
    "wof:name":"Gramercy L L C",
    "wof:placetype":"venue"
},
  "geometry": {"coordinates":[-97.93200299999999,30.311733],"type":"Point"}
}