{
  "type": "Feature",
  "properties": {
    "iso:country":"US",
    "sg:address":"1302 35th St",
    "sg:city":"Lubbock",
    "sg:classifiers":[
        {
            "category":"Retail",
            "subcategory":"Laundry & Dry Cleaning",
            "type":"Services"
        }
    ],
    "sg:phone":"+1 806 747 3939",
    "sg:postcode":"79412",
    "sg:province":"TX",
    "sg:tags":[
        "cleaner",
        "rug",
        "carpet"
    ],
    "sg:website":"http://www.chemdry.com",
    "wof:name":"Chem-Dry",
    "wof:placetype":"venue"
},
  "geometry": {"coordinates":[-101.84944900000001,33.562431],"type":"Point"}
}