{
  "type": "Feature",
  "properties": {
    "iso:country":"US",
    "sg:address":"7203 Cercis Cove",
    "sg:city":"Austin",
    "sg:classifiers":[
        {
            "category":"Shopping",
            "subcategory":"Computers & Home Electronics",
            "type":"Retail Goods"
        },
        {
            "category":"Professional",
            "subcategory":"Computer Services",
            "type":"Services"
        }
    ],
    "sg:phone":"+1 512 335 6318",
    "sg:postcode":"78759",
    "sg:province":"TX",
    "sg:tags":[
        "custom",
        "programing",
        "software"
    ],
    "wof:name":"W A Rogers Software Engineers",
    "wof:placetype":"venue"
},
  "geometry": {"coordinates":[-97.77497700000001,30.414038],"type":"Point"}
}