{
  "type": "Feature",
  "properties": {
    "iso:country":"US",
    "sg:address":"607 N Craig St",
    "sg:city":"Victoria",
    "sg:classifiers":[
        {
            "category":"Farming",
            "subcategory":"Livestock Farm",
            "type":"Manufacturing & Wholesale Goods"
        }
    ],
    "sg:phone":"+1 361 575 0938",
    "sg:postcode":"77901",
    "sg:province":"TX",
    "sg:tags":[
        "beef",
        "feedlot",
        "cattle"
    ],
    "wof:name":"Double L Cattle Ranch",
    "wof:placetype":"venue"
},
  "geometry": {"coordinates":[-97.00975099999999,28.806184],"type":"Point"}
}