{
  "type": "Feature",
  "properties": {
    "iso:country":"US",
    "sg:address":"591 W Campbell Rd",
    "sg:city":"Richardson",
    "sg:classifiers":[
        {
            "category":"Autos & Motor Vehicles",
            "subcategory":"Fuel & Gas Station",
            "type":"Retail Goods"
        },
        {
            "category":"Autos & Motor Vehicles",
            "subcategory":"Auto Supplies",
            "type":"Retail Goods"
        },
        {
            "category":"Retail",
            "subcategory":"Auto Repair",
            "type":"Services"
        }
    ],
    "sg:phone":"+1 972 231 8339",
    "sg:postcode":"75080",
    "sg:province":"TX",
    "sg:tags":[
        "oil",
        "transmission",
        "automotive",
        "lube",
        "automobile",
        "inspection",
        "tune"
    ],
    "sg:website":"http://www.campbellroadcarcare.com",
    "wof:name":"Campbell Road Car Care",
    "wof:placetype":"venue"
},
  "geometry": {"coordinates":[-96.739968,32.978051],"type":"Point"}
}