{
  "type": "Feature",
  "properties": {
    "iso:country":"US",
    "sg:address":"4541 Canyon Dr",
    "sg:city":"Amarillo",
    "sg:classifiers":[
        {
            "category":"Professional",
            "subcategory":"Business Services",
            "type":"Services"
        }
    ],
    "sg:phone":"+1 806 352 4076",
    "sg:postcode":"79110",
    "sg:province":"TX",
    "wof:name":"Shree Aum Enterprise Inc",
    "wof:placetype":"venue"
},
  "geometry": {"coordinates":[-101.873464,35.161334],"type":"Point"}
}