{
  "type": "Feature",
  "properties": {
    "iso:country":"US",
    "sg:address":"2558 Shanks Rd",
    "sg:city":"Angleton",
    "sg:classifiers":[
        {
            "category":"Building & Trades",
            "subcategory":"Construction",
            "type":"Services"
        }
    ],
    "sg:phone":"+1 979 849 5295",
    "sg:postcode":"77515",
    "sg:province":"TX",
    "sg:tags":[
        "house"
    ],
    "wof:name":"Lone Star Remodeling & Cnstr",
    "wof:placetype":"venue"
},
  "geometry": {"coordinates":[-95.424035,29.129474],"type":"Point"}
}