{
  "type": "Feature",
  "properties": {
    "iso:country":"US",
    "sg:address":"3104 Edith Ln",
    "sg:city":"Fort Worth",
    "sg:classifiers":[
        {
            "category":"Manufacturing",
            "subcategory":"Tools & Machinery",
            "type":"Manufacturing & Wholesale Goods"
        }
    ],
    "sg:phone":"+1 817 838 2685",
    "sg:postcode":"76117",
    "sg:province":"TX",
    "sg:tags":[
        "machine",
        "mfg"
    ],
    "wof:name":"Barlag Tool",
    "wof:placetype":"venue"
},
  "geometry": {"coordinates":[-97.28651600000001,32.799772],"type":"Point"}
}