{
  "type": "Feature",
  "properties": {
    "iso:country":"US",
    "sg:address":"515 Sterley St",
    "sg:city":"Spur",
    "sg:classifiers":[
        {
            "category":"Health Services",
            "subcategory":"Clinic",
            "type":"Services"
        }
    ],
    "sg:phone":"+1 806 271 4696",
    "sg:postcode":"79370",
    "sg:province":"TX",
    "sg:tags":[
        "home",
        "care"
    ],
    "wof:name":"Covenant Home Health Care",
    "wof:placetype":"venue"
},
  "geometry": {"coordinates":[-100.849417,33.476825],"type":"Point"}
}