{
  "type": "Feature",
  "properties": {
    "iso:country":"US",
    "sg:address":"6400 W Little York Rd",
    "sg:city":"Houston",
    "sg:classifiers":[
        {
            "category":"Professional",
            "subcategory":"Business Services",
            "type":"Services"
        }
    ],
    "sg:phone":"+1 713 466 5246",
    "sg:postcode":"77091",
    "sg:province":"TX",
    "sg:tags":[
        "forwarder",
        "freight",
        "purchasing",
        "offer"
    ],
    "wof:name":"Logistical Purchasing & Frt",
    "wof:placetype":"venue"
},
  "geometry": {"coordinates":[-95.486772,29.865751],"type":"Point"}
}