{
  "type": "Feature",
  "properties": {
    "iso:country":"US",
    "sg:address":"13550 State Hwy 29",
    "sg:city":"Liberty Hill",
    "sg:classifiers":[
        {
            "category":"Wholesale",
            "subcategory":"Durable Goods & Equipment",
            "type":"Manufacturing & Wholesale Goods"
        }
    ],
    "sg:phone":"+1 512 515 6643",
    "sg:postcode":"78642",
    "sg:province":"TX",
    "sg:tags":[
        "geophysical",
        "apparatus"
    ],
    "wof:name":"Carson Gravity Meter & Instrmt",
    "wof:placetype":"venue"
},
  "geometry": {"coordinates":[-97.906851,30.665721],"type":"Point"}
}