{
  "type": "Feature",
  "properties": {
    "iso:country":"US",
    "sg:address":"115 Pan American Dr # 400",
    "sg:city":"Livingston",
    "sg:classifiers":[
        {
            "category":"Personal",
            "subcategory":"Beauty Salon",
            "type":"Services"
        }
    ],
    "sg:phone":"+1 936 327 4833",
    "sg:postcode":"77351",
    "sg:province":"TX",
    "wof:name":"Steel Magnolia",
    "wof:placetype":"venue"
},
  "geometry": {"coordinates":[-94.93262,30.701602],"type":"Point"}
}