{
  "type": "Feature",
  "properties": {
    "iso:country":"US",
    "sg:address":"101 N Swenson St",
    "sg:city":"Stamford",
    "sg:classifiers":[
        {
            "category":"Shopping",
            "subcategory":"Gifts & Souvenirs",
            "type":"Retail Goods"
        }
    ],
    "sg:phone":"+1 325 773 2661",
    "sg:postcode":"79553",
    "sg:province":"TX",
    "sg:tags":[
        "variety",
        "st"
    ],
    "wof:name":"Country Friends & Frames",
    "wof:placetype":"venue"
},
  "geometry": {"coordinates":[-99.803028,32.946424],"type":"Point"}
}