{
  "type": "Feature",
  "properties": {
    "iso:country":"US",
    "sg:address":"1402 Mockingbird Ln",
    "sg:city":"Sulphur Springs",
    "sg:classifiers":[
        {
            "category":"Shopping",
            "subcategory":"Jewelry",
            "type":"Retail Goods"
        }
    ],
    "sg:phone":"+1 903 885 1118",
    "sg:postcode":"75482",
    "sg:province":"TX",
    "sg:tags":[
        "jeweler"
    ],
    "sg:website":"www.diamonds-n-designs.com",
    "wof:name":"Diamonds N Designs",
    "wof:placetype":"venue"
},
  "geometry": {"coordinates":[-95.59285300000001,33.115572],"type":"Point"}
}