{
  "type": "Feature",
  "properties": {
    "iso:country":"US",
    "sg:address":"471 N Harbin Dr",
    "sg:city":"Stephenville",
    "sg:classifiers":[
        {
            "category":"Professional",
            "type":"Services"
        }
    ],
    "sg:phone":"+1 254 968 5060",
    "sg:postcode":"76401",
    "sg:province":"TX",
    "sg:tags":[
        "establishment"
    ],
    "wof:name":"Stephenville Sports Shack",
    "wof:placetype":"venue"
},
  "geometry": {"coordinates":[-98.223809,32.212759],"type":"Point"}
}