{
  "type": "Feature",
  "properties": {
    "iso:country":"US",
    "sg:address":"308 Jim Wright Fwy N",
    "sg:city":"White Settlement",
    "sg:classifiers":[
        {
            "category":"Insurance",
            "subcategory":"Insurance Agent",
            "type":"Services"
        }
    ],
    "sg:phone":"+1 817 246 5549",
    "sg:postcode":"76108",
    "sg:province":"TX",
    "wof:name":"Allstate Insurance",
    "wof:placetype":"venue"
},
  "geometry": {"coordinates":[-97.47615,32.764242],"type":"Point"}
}