{
  "type": "Feature",
  "properties": {
    "iso:country":"US",
    "sg:address":"10000 Emmett F Lowry Expy",
    "sg:city":"Texas City",
    "sg:classifiers":[
        {
            "category":"Health Services",
            "subcategory":"Optometrist",
            "type":"Services"
        }
    ],
    "sg:phone":"+1 409 986 2155",
    "sg:postcode":"77591",
    "sg:province":"TX",
    "wof:name":"Kevin Hoang OD",
    "wof:placetype":"venue"
},
  "geometry": {"coordinates":[-95.02682799999999,29.403789],"type":"Point"}
}