{
  "type": "Feature",
  "properties": {
    "iso:country":"US",
    "sg:address":"247 N Bliss Ave",
    "sg:city":"Dumas",
    "sg:classifiers":[
        {
            "category":"Professional",
            "subcategory":"Accounting & Tax Preparation",
            "type":"Services"
        }
    ],
    "sg:phone":"+1 806 934 9188",
    "sg:postcode":"79029",
    "sg:province":"TX",
    "wof:name":"Southwest Billing Service",
    "wof:placetype":"venue"
},
  "geometry": {"coordinates":[-101.97187099999999,35.867141],"type":"Point"}
}