{
  "type": "Feature",
  "properties": {
    "iso:country":"US",
    "sg:address":"108 Topeka Dr",
    "sg:city":"Waco",
    "sg:classifiers":[
        {
            "category":"Professional",
            "subcategory":"Accounting & Tax Preparation",
            "type":"Services"
        }
    ],
    "sg:phone":"+1 254 776 8300",
    "sg:postcode":"76712",
    "sg:province":"TX",
    "sg:tags":[
        "accountant"
    ],
    "wof:name":"Robert J Bestor CPA",
    "wof:placetype":"venue"
},
  "geometry": {"coordinates":[-97.203283,31.506818],"type":"Point"}
}