{
  "type": "Feature",
  "properties": {
    "iso:country":"US",
    "sg:address":"3460 Elgin St",
    "sg:city":"Houston",
    "sg:classifiers":[
        {
            "category":"Food & Beverages",
            "subcategory":"Liquor & Beverages",
            "type":"Retail Goods"
        }
    ],
    "sg:phone":"+1 713 655 7947",
    "sg:postcode":"77004",
    "sg:province":"TX",
    "sg:tags":[
        "alcoholic"
    ],
    "wof:name":"Super Liquor",
    "wof:placetype":"venue"
},
  "geometry": {"coordinates":[-95.351607,29.728332],"type":"Point"}
}