{
  "type": "Feature",
  "properties": {
    "iso:country":"US",
    "sg:address":"6321 New Copeland Rd",
    "sg:city":"Tyler",
    "sg:classifiers":[
        {
            "category":"Social Services",
            "subcategory":"Child Care",
            "type":"Services"
        }
    ],
    "sg:phone":"+1 903 581 4075",
    "sg:postcode":"75703",
    "sg:province":"TX",
    "sg:tags":[
        "preschool"
    ],
    "wof:name":"Oak Tree Academy LLC",
    "wof:placetype":"venue"
},
  "geometry": {"coordinates":[-95.282966,32.278019],"type":"Point"}
}