{
  "type": "Feature",
  "properties": {
    "iso:country":"US",
    "sg:address":"2826 Merrell Rd",
    "sg:city":"Dallas",
    "sg:classifiers":[
        {
            "category":"Freight",
            "type":"Transportation"
        }
    ],
    "sg:phone":"+1 972 484 2112",
    "sg:postcode":"75229",
    "sg:province":"TX",
    "sg:tags":[
        "operator",
        "local",
        "trucking"
    ],
    "wof:name":"IMS Relocation",
    "wof:placetype":"venue"
},
  "geometry": {"coordinates":[-96.88314,32.886474],"type":"Point"}
}