{
  "type": "Feature",
  "properties": {
    "iso:country":"US",
    "sg:address":"3409 Worth St",
    "sg:city":"Dallas",
    "sg:classifiers":[
        {
            "category":"Professional",
            "type":"Services"
        }
    ],
    "sg:phone":"+1 214 820 1583",
    "sg:postcode":"75246",
    "sg:province":"TX",
    "wof:name":"Perfusion Reliance Network LLC",
    "wof:placetype":"venue"
},
  "geometry": {"coordinates":[-96.77919,32.7885],"type":"Point"}
}