{
  "type": "Feature",
  "properties": {
    "iso:country":"US",
    "sg:address":"10039 Dyer St",
    "sg:city":"El Paso",
    "sg:classifiers":[
        {
            "category":"Home & Garden",
            "subcategory":"Furniture",
            "type":"Retail Goods"
        }
    ],
    "sg:phone":"+1 915 755 8830",
    "sg:postcode":"79924",
    "sg:province":"TX",
    "wof:name":"Los Guapos",
    "wof:placetype":"venue"
},
  "geometry": {"coordinates":[-106.40719199999999,31.901837],"type":"Point"}
}