{
  "type": "Feature",
  "properties": {
    "iso:country":"US",
    "sg:address":"3233 State Hwy 350",
    "sg:city":"Snyder",
    "sg:classifiers":[
        {
            "category":"Building & Trades",
            "subcategory":"Construction",
            "type":"Services"
        }
    ],
    "sg:phone":"+1 325 573 5540",
    "sg:postcode":"79549",
    "sg:province":"TX",
    "sg:tags":[
        "water",
        "well",
        "drilling"
    ],
    "wof:name":"J W Womack Drilling Svc",
    "wof:placetype":"venue"
},
  "geometry": {"coordinates":[-100.919012,32.709892],"type":"Point"}
}