{
  "type": "Feature",
  "properties": {
    "iso:country":"US",
    "sg:address":"5700 W Plano Pkwy Ste 2200",
    "sg:city":"Plano",
    "sg:classifiers":[
        {
            "category":"Professional",
            "subcategory":"Lawyer & Legal Services",
            "type":"Services"
        }
    ],
    "sg:phone":"+1 972 769 2727",
    "sg:postcode":"75093",
    "sg:province":"TX",
    "sg:tags":[
        "divorce",
        "law",
        "family"
    ],
    "wof:name":"Robertson Richard L",
    "wof:placetype":"venue"
},
  "geometry": {"coordinates":[-96.81559799999999,33.016399],"type":"Point"}
}