{
  "type": "Feature",
  "properties": {
    "iso:country":"US",
    "sg:address":"8802 Woodrow Rd",
    "sg:city":"Wolfforth",
    "sg:classifiers":[
        {
            "category":"Building & Trades",
            "subcategory":"Construction",
            "type":"Services"
        }
    ],
    "sg:phone":"+1 806 863 3269",
    "sg:postcode":"79382",
    "sg:province":"TX",
    "sg:tags":[
        "residential",
        "nonresidential"
    ],
    "wof:name":"Dl Johnson Construction Inc",
    "wof:placetype":"venue"
},
  "geometry": {"coordinates":[-102.017565,33.447166],"type":"Point"}
}