{
  "type": "Feature",
  "properties": {
    "iso:country":"US",
    "sg:address":"7728 Mid Cities Blvd",
    "sg:city":"Fort Worth",
    "sg:classifiers":[
        {
            "category":"Shopping",
            "subcategory":"Optical Goods",
            "type":"Retail Goods"
        },
        {
            "category":"Health Services",
            "subcategory":"Optometrist",
            "type":"Services"
        }
    ],
    "sg:phone":"+1 817 281 3386",
    "sg:postcode":"76180",
    "sg:province":"TX",
    "wof:name":"Southwest Vision Center",
    "wof:placetype":"venue"
},
  "geometry": {"coordinates":[-97.212459,32.861513],"type":"Point"}
}