{
  "type": "Feature",
  "properties": {
    "iso:country":"US",
    "sg:address":"5879 Babcock Rd",
    "sg:city":"San Antonio",
    "sg:classifiers":[
        {
            "category":"Food & Beverages",
            "subcategory":"Candy",
            "type":"Retail Goods"
        }
    ],
    "sg:phone":"+1 210 561 1442",
    "sg:postcode":"78240",
    "sg:province":"TX",
    "sg:tags":[
        "confectionery"
    ],
    "wof:name":"VIP Chocolate Fountains",
    "wof:placetype":"venue"
},
  "geometry": {"coordinates":[-98.60141,29.526806],"type":"Point"}
}