{
  "type": "Feature",
  "properties": {
    "iso:country":"US",
    "sg:address":"2709 Ripplewood Dr",
    "sg:city":"Dallas",
    "sg:classifiers":[
        {
            "category":"Farming",
            "subcategory":"Orchard",
            "type":"Manufacturing & Wholesale Goods"
        }
    ],
    "sg:phone":"+1 214 321 9629",
    "sg:postcode":"75228",
    "sg:province":"TX",
    "sg:tags":[
        "fruit",
        "tree"
    ],
    "wof:name":"Ellis Mountain Orchards",
    "wof:placetype":"venue"
},
  "geometry": {"coordinates":[-96.69232599999999,32.812862],"type":"Point"}
}