{
  "type": "Feature",
  "properties": {
    "iso:country":"US",
    "sg:address":"1840 W Airfield Dr 300",
    "sg:city":"Dallas",
    "sg:classifiers":[
        {
            "category":"Airport",
            "type":"Transportation"
        }
    ],
    "sg:phone":"+1 972 615 2410",
    "sg:postcode":"75261",
    "sg:province":"TX",
    "sg:website":"http://www.execucar.com",
    "wof:name":"Super Shuttle Dfw",
    "wof:placetype":"venue"
},
  "geometry": {"coordinates":[-97.06761299999999,32.91247],"type":"Point"}
}