{
  "type": "Feature",
  "properties": {
    "iso:country":"US",
    "sg:address":"5921 East Fwy",
    "sg:city":"Baytown",
    "sg:classifiers":[
        {
            "category":"Shopping",
            "subcategory":"Bicycles & Sporting Goods",
            "type":"Retail Goods"
        }
    ],
    "sg:phone":"+1 281 421 7674",
    "sg:postcode":"77521",
    "sg:province":"TX",
    "sg:tags":[
        "equipment",
        "golf",
        "supply"
    ],
    "wof:name":"Baytown Golf Ctr",
    "wof:placetype":"venue"
},
  "geometry": {"coordinates":[-94.968129,29.806977],"type":"Point"}
}