{
  "type": "Feature",
  "properties": {
    "iso:country":"US",
    "sg:address":"9901 Sharpcrest St",
    "sg:city":"Houston",
    "sg:classifiers":[
        {
            "category":"Shopping",
            "subcategory":"Jewelry",
            "type":"Retail Goods"
        }
    ],
    "sg:phone":"+1 713 272 7400",
    "sg:postcode":"77036",
    "sg:province":"TX",
    "wof:name":"Lippman Louis",
    "wof:placetype":"venue"
},
  "geometry": {"coordinates":[-95.555244,29.696309],"type":"Point"}
}