{
  "type": "Feature",
  "properties": {
    "iso:country":"US",
    "sg:address":"1213 Huck St",
    "sg:city":"Cuero",
    "sg:classifiers":[
        {
            "category":"Farming",
            "subcategory":"Livestock Farm",
            "type":"Manufacturing & Wholesale Goods"
        }
    ],
    "sg:phone":"+1 361 275 5100",
    "sg:postcode":"77954",
    "sg:province":"TX",
    "sg:tags":[
        "beef",
        "feedlot",
        "cattle"
    ],
    "wof:name":"MBC Cattle Co",
    "wof:placetype":"venue"
},
  "geometry": {"coordinates":[-97.278235,29.083492],"type":"Point"}
}