{
  "type": "Feature",
  "properties": {
    "iso:country":"US",
    "sg:address":"338 W Main St",
    "sg:city":"Fredericksburg",
    "sg:classifiers":[
        {
            "category":"Food & Beverages",
            "subcategory":"Specialty",
            "type":"Retail Goods"
        },
        {
            "category":"Restaurant",
            "type":"Food & Drink"
        }
    ],
    "sg:phone":"+1 830 997 8327",
    "sg:postcode":"78624",
    "sg:province":"TX",
    "sg:tags":[
        "tea",
        "coffee",
        "eating"
    ],
    "wof:name":"Fredericksburg Coffee & Tea",
    "wof:placetype":"venue"
},
  "geometry": {"coordinates":[-98.876749,30.278402],"type":"Point"}
}