{
  "type": "Feature",
  "properties": {
    "iso:country":"US",
    "sg:address":"18 Uvalde Rd",
    "sg:city":"Houston",
    "sg:classifiers":[
        {
            "category":"Food & Beverages",
            "subcategory":"Bakery",
            "type":"Retail Goods"
        }
    ],
    "sg:phone":"+1 713 637 6322",
    "sg:postcode":"77015",
    "sg:province":"TX",
    "sg:tags":[
        "doughnut"
    ],
    "wof:name":"Double T's Donuts",
    "wof:placetype":"venue"
},
  "geometry": {"coordinates":[-95.182255,29.806151],"type":"Point"}
}