{
  "type": "Feature",
  "properties": {
    "iso:country":"US",
    "sg:address":"1111 W Gray St",
    "sg:city":"Houston",
    "sg:classifiers":[
        {
            "category":"Wholesale",
            "subcategory":"Machinery & Supplies",
            "type":"Manufacturing & Wholesale Goods"
        }
    ],
    "sg:phone":"+1 713 528 0134",
    "sg:postcode":"77019",
    "sg:province":"TX",
    "sg:tags":[
        "equipment",
        "establishment"
    ],
    "wof:name":"Burwell Charles W III",
    "wof:placetype":"venue"
},
  "geometry": {"coordinates":[-95.39277199999999,29.753247],"type":"Point"}
}