{
  "type": "Feature",
  "properties": {
    "iso:country":"US",
    "sg:address":"1528 S Clark Rd",
    "sg:city":"Duncanville",
    "sg:classifiers":[
        {
            "category":"Shopping",
            "subcategory":"Beauty & Cosmetics",
            "type":"Retail Goods"
        }
    ],
    "sg:phone":"+1 972 780 7465",
    "sg:postcode":"75137",
    "sg:province":"TX",
    "sg:tags":[
        "merchandise"
    ],
    "wof:name":"Amy Beauty Supply",
    "wof:placetype":"venue"
},
  "geometry": {"coordinates":[-96.943228,32.631819],"type":"Point"}
}