{
  "type": "Feature",
  "properties": {
    "iso:country":"US",
    "sg:address":"3209 Toler Rd",
    "sg:city":"Rowlett",
    "sg:classifiers":[
        {
            "category":"Wholesale",
            "subcategory":"Machinery & Supplies",
            "type":"Manufacturing & Wholesale Goods"
        }
    ],
    "sg:phone":"+1 972 463 1300",
    "sg:postcode":"75089",
    "sg:province":"TX",
    "sg:tags":[
        "hardware",
        "industrial"
    ],
    "wof:name":"Pan American Tool Corp",
    "wof:placetype":"venue"
},
  "geometry": {"coordinates":[-96.570205,32.926109],"type":"Point"}
}