{
  "type": "Feature",
  "properties": {
    "iso:country":"US",
    "sg:address":"215 N San Saba St",
    "sg:city":"San Antonio",
    "sg:classifiers":[
        {
            "category":"Health Services",
            "subcategory":"Doctor",
            "type":"Services"
        }
    ],
    "sg:phone":"+1 210 527 9111",
    "sg:postcode":"78207",
    "sg:province":"TX",
    "sg:tags":[
        "physician",
        "surgeon"
    ],
    "wof:name":"Ernesto Martinez MD",
    "wof:placetype":"venue"
},
  "geometry": {"coordinates":[-98.49979999999999,29.429553],"type":"Point"}
}