{
  "type": "Feature",
  "properties": {
    "iso:country":"US",
    "sg:address":"110 N Ave B",
    "sg:city":"Freeport",
    "sg:classifiers":[
        {
            "category":"Building & Trades",
            "subcategory":"Construction",
            "type":"Services"
        }
    ],
    "sg:phone":"+1 979 373 0680",
    "sg:postcode":"77541",
    "sg:province":"TX",
    "sg:tags":[
        "contractor"
    ],
    "wof:name":"Vegas Roofing",
    "wof:placetype":"venue"
},
  "geometry": {"coordinates":[-95.36233,28.960936],"type":"Point"}
}