{
  "type": "Feature",
  "properties": {
    "iso:country":"US",
    "sg:address":"1905 Padre Blvd",
    "sg:city":"South Padre Island",
    "sg:classifiers":[
        {
            "category":"Restaurant",
            "type":"Food & Drink"
        }
    ],
    "sg:menulink":"http://www.allmenus.com/tx/east-cameron/70666-pizza-hut/menu/",
    "sg:phone":"+1 956 761 1361",
    "sg:postcode":"78597",
    "sg:province":"TX",
    "sg:tags":[
        "american",
        "pizza"
    ],
    "wof:name":"PIZZA HUT",
    "wof:placetype":"venue"
},
  "geometry": {"coordinates":[-97.16483700000001,26.090501],"type":"Point"}
}