{
  "type": "Feature",
  "properties": {
    "iso:country":"US",
    "sg:address":"9896 Bellaire Blvd Ste M",
    "sg:city":"Houston",
    "sg:classifiers":[
        {
            "category":"Restaurant",
            "type":"Food & Drink"
        }
    ],
    "sg:phone":"+1 713 270 6000",
    "sg:postcode":"77036",
    "sg:province":"TX",
    "sg:tags":[
        "barbeque"
    ],
    "wof:name":"Willie's Barbecue",
    "wof:placetype":"venue"
},
  "geometry": {"coordinates":[-95.555093,29.704855],"type":"Point"}
}