{
  "type": "Feature",
  "properties": {
    "iso:country":"US",
    "sg:address":"12130 Highway 3",
    "sg:city":"Webster",
    "sg:classifiers":[
        {
            "category":"Home & Garden",
            "subcategory":"Furniture",
            "type":"Retail Goods"
        }
    ],
    "sg:phone":"+1 281 464 3844",
    "sg:postcode":"77598",
    "sg:province":"TX",
    "sg:tags":[
        "store"
    ],
    "wof:name":"Sussan Fine Furniture",
    "wof:placetype":"venue"
},
  "geometry": {"coordinates":[-95.173951,29.597389],"type":"Point"}
}