{
  "type": "Feature",
  "properties": {
    "iso:country":"US",
    "sg:address":"7900 Fannin St Ste 2300",
    "sg:city":"Houston",
    "sg:classifiers":[
        {
            "category":"Health Services",
            "subcategory":"Doctor",
            "type":"Services"
        }
    ],
    "sg:phone":"+1 713 790 1349",
    "sg:postcode":"77054",
    "sg:province":"TX",
    "sg:website":"www.fshivf.com",
    "wof:name":"Anesthesia Specialists of Houston",
    "wof:placetype":"venue"
},
  "geometry": {"coordinates":[-95.402708,29.693384],"type":"Point"}
}