{
  "type": "Feature",
  "properties": {
    "iso:country":"US",
    "sg:address":"3026 S Staples St",
    "sg:city":"Corpus Christi",
    "sg:classifiers":[
        {
            "category":"Organizations",
            "subcategory":"Non-profit Organization",
            "type":"Services"
        }
    ],
    "sg:phone":"+1 361 814 6565",
    "sg:postcode":"78404",
    "sg:province":"TX",
    "wof:name":"South Texas Interfaith Council",
    "wof:placetype":"venue"
},
  "geometry": {"coordinates":[-97.398758,27.755715],"type":"Point"}
}