{
  "type": "Feature",
  "properties": {
    "iso:country":"US",
    "sg:address":"205 Superior Dr",
    "sg:city":"Laredo",
    "sg:classifiers":[
        {
            "category":"Shopping",
            "subcategory":"Used Merchandise",
            "type":"Retail Goods"
        }
    ],
    "sg:phone":"+1 956 791 0628",
    "sg:postcode":"78045",
    "sg:province":"TX",
    "wof:name":"Jose L Garza",
    "wof:placetype":"venue"
},
  "geometry": {"coordinates":[-99.496188,27.575655],"type":"Point"}
}