{
  "type": "Feature",
  "properties": {
    "iso:country":"US",
    "sg:address":"188 N Valley Pkwy",
    "sg:city":"Lewisville",
    "sg:classifiers":[
        {
            "category":"Government",
            "subcategory":"Fire Station",
            "type":"Public Place"
        }
    ],
    "sg:phone":"+1 972 219 3580",
    "sg:postcode":"75067",
    "sg:province":"TX",
    "sg:tags":[
        "department"
    ],
    "wof:name":"Lewisville Fire Dept",
    "wof:placetype":"venue"
},
  "geometry": {"coordinates":[-97.020749,33.044862],"type":"Point"}
}