{
  "type": "Feature",
  "properties": {
    "iso:country":"US",
    "sg:address":"1920 Pecos St",
    "sg:city":"San Angelo",
    "sg:classifiers":[
        {
            "category":"Real Estate",
            "subcategory":"Real Estate Agent",
            "type":"Services"
        }
    ],
    "sg:phone":"+1 325 949 1099",
    "sg:postcode":"76901",
    "sg:province":"TX",
    "wof:name":"Cross L Properties",
    "wof:placetype":"venue"
},
  "geometry": {"coordinates":[-100.462386,31.4548],"type":"Point"}
}