{
  "type": "Feature",
  "properties": {
    "iso:country":"US",
    "sg:address":"14121 Northwest Fwy",
    "sg:city":"Houston",
    "sg:classifiers":[
        {
            "category":"Shopping",
            "subcategory":"Bicycles & Sporting Goods",
            "type":"Retail Goods"
        }
    ],
    "sg:phone":"+1 713 462 2225",
    "sg:postcode":"77040",
    "sg:province":"TX",
    "sg:tags":[
        "equipment",
        "golf",
        "supply"
    ],
    "wof:name":"Custom Fit Golf Equipment",
    "wof:placetype":"venue"
},
  "geometry": {"coordinates":[-95.52496499999999,29.859496],"type":"Point"}
}