{
  "type": "Feature",
  "properties": {
    "iso:country":"US",
    "sg:address":"3023 S University Dr",
    "sg:city":"Fort Worth",
    "sg:classifiers":[
        {
            "category":"Building & Trades",
            "subcategory":"Plumbing",
            "type":"Services"
        }
    ],
    "sg:phone":"+1 817 926 4268",
    "sg:postcode":"76109",
    "sg:province":"TX",
    "sg:tags":[
        "mechanical",
        "contractor"
    ],
    "wof:name":"Gant Mechanical Svc",
    "wof:placetype":"venue"
},
  "geometry": {"coordinates":[-97.360388,32.707393],"type":"Point"}
}