{
  "type": "Feature",
  "properties": {
    "iso:country":"US",
    "sg:address":"1500 Grant St",
    "sg:city":"Wichita Falls",
    "sg:classifiers":[
        {
            "category":"Retail",
            "subcategory":"Laundry & Dry Cleaning",
            "type":"Services"
        },
        {
            "category":"Shopping",
            "subcategory":"Clothing, Apparel, & Fashions",
            "type":"Retail Goods"
        }
    ],
    "sg:phone":"+1 940 723 7394",
    "sg:postcode":"76309",
    "sg:province":"TX",
    "sg:tags":[
        "alteration"
    ],
    "wof:name":"Karen's Alterations",
    "wof:placetype":"venue"
},
  "geometry": {"coordinates":[-98.52468399999999,33.899277],"type":"Point"}
}