{
  "type": "Feature",
  "properties": {
    "iso:country":"US",
    "sg:address":"6617 Forest Hill Dr",
    "sg:city":"Fort Worth",
    "sg:classifiers":[
        {
            "category":"Shopping",
            "subcategory":"Discount & Variety Stores",
            "type":"Retail Goods"
        }
    ],
    "sg:phone":"+1 817 478 3900",
    "sg:postcode":"76140",
    "sg:province":"TX",
    "wof:name":"Dollar General",
    "wof:placetype":"venue"
},
  "geometry": {"coordinates":[-97.269823,32.658107],"type":"Point"}
}