{
  "type": "Feature",
  "properties": {
    "iso:country":"US",
    "sg:address":"213 Brooks Ave",
    "sg:city":"Canutillo",
    "sg:classifiers":[
        {
            "category":"Building & Trades",
            "subcategory":"Equipment Rental",
            "type":"Services"
        }
    ],
    "sg:phone":"+1 915 731 2975",
    "sg:postcode":"79835",
    "sg:province":"TX",
    "wof:name":"Millennium Party Rental",
    "wof:placetype":"venue"
},
  "geometry": {"coordinates":[-106.598643,31.93823],"type":"Point"}
}