{
  "type": "Feature",
  "properties": {
    "iso:country":"US",
    "sg:address":"1480 Sawdust Rd",
    "sg:city":"Spring",
    "sg:classifiers":[
        {
            "category":"Autos & Motor Vehicles",
            "subcategory":"Fuel & Gas Station",
            "type":"Retail Goods"
        }
    ],
    "sg:phone":"+1 281 367 1331",
    "sg:postcode":"77380",
    "sg:province":"TX",
    "sg:tags":[
        "oil"
    ],
    "wof:name":"Diamond Shamrock",
    "wof:placetype":"venue"
},
  "geometry": {"coordinates":[-95.468147,30.126332],"type":"Point"}
}