{
  "type": "Feature",
  "properties": {
    "iso:country":"US",
    "sg:address":"2127 Jester Farms Rd",
    "sg:city":"Round Rock",
    "sg:classifiers":[
        {
            "category":"Professional",
            "subcategory":"Business Services",
            "type":"Services"
        }
    ],
    "sg:phone":"+1 512 716 1489",
    "sg:postcode":"78664",
    "sg:province":"TX",
    "wof:name":"Advanced Business Concepts",
    "wof:placetype":"venue"
},
  "geometry": {"coordinates":[-97.666254,30.532434],"type":"Point"}
}