{
  "type": "Feature",
  "properties": {
    "iso:country":"US",
    "sg:address":"9908 Hundred Oaks Cir",
    "sg:city":"Austin",
    "sg:classifiers":[
        {
            "category":"Professional",
            "subcategory":"Business Services",
            "type":"Services"
        }
    ],
    "sg:phone":"+1 512 219 0045",
    "sg:postcode":"78750",
    "sg:province":"TX",
    "wof:name":"Hot Wings Express",
    "wof:placetype":"venue"
},
  "geometry": {"coordinates":[-97.80044100000001,30.420342],"type":"Point"}
}