{
  "type": "Feature",
  "properties": {
    "iso:country":"US",
    "sg:address":"811 Heights Blvd",
    "sg:city":"Houston",
    "sg:classifiers":[
        {
            "category":"Professional",
            "subcategory":"Advertising",
            "type":"Services"
        }
    ],
    "sg:phone":"+1 713 960 0391",
    "sg:postcode":"77007",
    "sg:province":"TX",
    "sg:tags":[
        "agency"
    ],
    "wof:name":"J Steve Brownhill PC",
    "wof:placetype":"venue"
},
  "geometry": {"coordinates":[-95.39769,29.786818],"type":"Point"}
}