{
  "type": "Feature",
  "properties": {
    "iso:country":"US",
    "sg:address":"1929 Central Ave",
    "sg:city":"Port Lavaca",
    "sg:classifiers":[
        {
            "category":"Personal",
            "subcategory":"Beauty Salon",
            "type":"Services"
        }
    ],
    "sg:phone":"+1 361 552 9380",
    "sg:postcode":"77979",
    "sg:province":"TX",
    "sg:tags":[
        "shop"
    ],
    "wof:name":"Jabo Hair Studio",
    "wof:placetype":"venue"
},
  "geometry": {"coordinates":[-96.642284,28.611621],"type":"Point"}
}