{
  "type": "Feature",
  "properties": {
    "iso:country":"US",
    "sg:address":"400 S Fredonia St",
    "sg:city":"Longview",
    "sg:classifiers":[
        {
            "category":"Real Estate",
            "subcategory":"Real Estate Agent",
            "type":"Services"
        }
    ],
    "sg:phone":"+1 903 753 4444",
    "sg:postcode":"75601",
    "sg:province":"TX",
    "wof:name":"Ruff Realtors Inc",
    "wof:placetype":"venue"
},
  "geometry": {"coordinates":[-94.74039500000001,32.487282],"type":"Point"}
}