{
  "type": "Feature",
  "properties": {
    "iso:country":"US",
    "sg:address":"3550 Mark Jason Dr",
    "sg:city":"El Paso",
    "sg:classifiers":[
        {
            "category":"Education",
            "subcategory":"School",
            "type":"Public Place"
        }
    ],
    "sg:phone":"+1 915 857 1185",
    "sg:postcode":"79938",
    "sg:province":"TX",
    "wof:name":"Montana Vista Elementary Schl",
    "wof:placetype":"venue"
},
  "geometry": {"coordinates":[-106.16573200000001,31.802507],"type":"Point"}
}