{
  "type": "Feature",
  "properties": {
    "iso:country":"US",
    "sg:address":"7086 Gentle Breeze Dr",
    "sg:city":"Willis",
    "sg:classifiers":[
        {
            "category":"Professional",
            "type":"Services"
        }
    ],
    "sg:phone":"+1 936 856 2923",
    "sg:postcode":"77318",
    "sg:province":"TX",
    "wof:name":"Amundsen Home Services",
    "wof:placetype":"venue"
},
  "geometry": {"coordinates":[-95.566146,30.408659],"type":"Point"}
}