{
  "type": "Feature",
  "properties": {
    "iso:country":"US",
    "sg:address":"507 Houston St",
    "sg:city":"Kilgore",
    "sg:classifiers":[
        {
            "category":"Professional",
            "type":"Services"
        }
    ],
    "sg:phone":"+1 903 983 1190",
    "sg:postcode":"75662",
    "sg:province":"TX",
    "wof:name":"Grw Division of A&E Enter",
    "wof:placetype":"venue"
},
  "geometry": {"coordinates":[-94.875337,32.379687],"type":"Point"}
}