{
  "type": "Feature",
  "properties": {
    "iso:country":"US",
    "sg:address":"2944 Motley Dr",
    "sg:city":"Mesquite",
    "sg:classifiers":[
        {
            "category":"Restaurant",
            "type":"Food & Drink"
        }
    ],
    "sg:phone":"+1 972 698 9777",
    "sg:postcode":"75150",
    "sg:province":"TX",
    "wof:name":"Warren Lynch",
    "wof:placetype":"venue"
},
  "geometry": {"coordinates":[-96.648938,32.804827],"type":"Point"}
}