{
  "type": "Feature",
  "properties": {
    "iso:country":"US",
    "sg:address":"2290 John Charles Rd",
    "sg:city":"Bulverde",
    "sg:classifiers":[
        {
            "category":"Personal",
            "type":"Services"
        }
    ],
    "sg:phone":"+1 830 980 9512",
    "sg:postcode":"78163",
    "sg:province":"TX",
    "wof:name":"Cynthia L Fuller Fitness",
    "wof:placetype":"venue"
},
  "geometry": {"coordinates":[-98.453914,29.776875],"type":"Point"}
}