{
  "type": "Feature",
  "properties": {
    "iso:country":"US",
    "sg:address":"309 NE Ave E",
    "sg:city":"Andrews",
    "sg:classifiers":[
        {
            "category":"Building & Trades",
            "subcategory":"Cleaning & Sanitation",
            "type":"Services"
        }
    ],
    "sg:phone":"+1 432 524 9678",
    "sg:postcode":"79714",
    "sg:province":"TX",
    "sg:tags":[
        "maintenance"
    ],
    "wof:name":"Maria G Banda",
    "wof:placetype":"venue"
},
  "geometry": {"coordinates":[-102.54496899999999,32.324553],"type":"Point"}
}