{
  "type": "Feature",
  "properties": {
    "iso:country":"US",
    "sg:address":"1105 W Pipeline Rd",
    "sg:city":"Hurst",
    "sg:classifiers":[
        {
            "category":"Shopping",
            "subcategory":"Clothing, Apparel, & Fashions",
            "type":"Retail Goods"
        }
    ],
    "sg:phone":"+1 817 595 2668",
    "sg:postcode":"76053",
    "sg:province":"TX",
    "sg:tags":[
        "western"
    ],
    "sg:website":"www.boottown.com",
    "wof:name":"Boot Town Western World",
    "wof:placetype":"venue"
},
  "geometry": {"coordinates":[-97.198849,32.823681],"type":"Point"}
}