{
  "type": "Feature",
  "properties": {
    "iso:country":"US",
    "sg:address":"3220 Bryan Ave",
    "sg:city":"Fort Worth",
    "sg:classifiers":[
        {
            "category":"Professional",
            "type":"Services"
        }
    ],
    "sg:phone":"+1 817 926 1517",
    "sg:postcode":"76110",
    "sg:province":"TX",
    "wof:name":"Protest Motorsports",
    "wof:placetype":"venue"
},
  "geometry": {"coordinates":[-97.325427,32.702636],"type":"Point"}
}