{
  "type": "Feature",
  "properties": {
    "iso:country":"US",
    "sg:address":"1002 N Mallard St",
    "sg:city":"Palestine",
    "sg:classifiers":[
        {
            "category":"Health Services",
            "subcategory":"Nursing And Care Facility",
            "type":"Services"
        },
        {
            "category":"Health Services",
            "subcategory":"Health Practitioner",
            "type":"Services"
        },
        {
            "category":"Health Services",
            "subcategory":"Chiropractor",
            "type":"Services"
        }
    ],
    "sg:phone":"+1 903 723 1500",
    "sg:postcode":"75801",
    "sg:province":"TX",
    "sg:tags":[
        "control",
        "management",
        "pain",
        "weight",
        "chiropractic",
        "therapist",
        "reducing",
        "physical"
    ],
    "sg:website":"http://www.palestinechiropractic.com",
    "wof:name":"Chiropractic Center Of Palestine",
    "wof:placetype":"venue"
},
  "geometry": {"coordinates":[-95.627571,31.769039],"type":"Point"}
}