{
  "type": "Feature",
  "properties": {
    "iso:country":"US",
    "sg:address":"11615 Forest Central Dr Ste 214",
    "sg:city":"Dallas",
    "sg:classifiers":[
        {
            "category":"Communications",
            "type":"Services"
        }
    ],
    "sg:phone":"+1 214 349 5067",
    "sg:postcode":"75243",
    "sg:province":"TX",
    "sg:tags":[
        "web",
        "design"
    ],
    "sg:website":"www.Masterlink.com",
    "wof:name":"Masterlink Group the",
    "wof:placetype":"venue"
},
  "geometry": {"coordinates":[-96.727898,32.909302],"type":"Point"}
}