{
  "type": "Feature",
  "properties": {
    "iso:country":"US",
    "sg:address":"3824 S Clack St",
    "sg:city":"Abilene",
    "sg:classifiers":[
        {
            "category":"Restaurant",
            "type":"Food & Drink"
        }
    ],
    "sg:menulink":"http://www.allmenus.com/tx/abilene/166354-arbys/menu/",
    "sg:phone":"+1 325 695 4491",
    "sg:postcode":"79606",
    "sg:province":"TX",
    "sg:tags":[
        "burger",
        "american"
    ],
    "wof:name":"Arby's",
    "wof:placetype":"venue"
},
  "geometry": {"coordinates":[-99.769445,32.408004],"type":"Point"}
}