{
  "type": "Feature",
  "properties": {
    "iso:country":"US",
    "sg:address":"2192 Texas Pkwy",
    "sg:city":"Missouri City",
    "sg:classifiers":[
        {
            "category":"Food & Beverages",
            "subcategory":"Groceries & Convenience Stores",
            "type":"Retail Goods"
        }
    ],
    "sg:phone":"+1 281 499 1700",
    "sg:postcode":"77489",
    "sg:province":"TX",
    "wof:name":"Kroger Food Stores",
    "wof:placetype":"venue"
},
  "geometry": {"coordinates":[-95.526901,29.5956],"type":"Point"}
}