{
  "type": "Feature",
  "properties": {
    "iso:country":"US",
    "sg:address":"1332 S Plano Rd",
    "sg:city":"Richardson",
    "sg:classifiers":[
        {
            "category":"Shopping",
            "subcategory":"Department Store",
            "type":"Retail Goods"
        }
    ],
    "sg:phone":"+1 972 480 0921",
    "sg:postcode":"75081",
    "sg:province":"TX",
    "sg:tags":[
        "shop"
    ],
    "wof:name":"Big Lots",
    "wof:placetype":"venue"
},
  "geometry": {"coordinates":[-96.700209,32.932661],"type":"Point"}
}