{
  "type": "Feature",
  "properties": {
    "iso:country":"US",
    "sg:address":"7801 Broadway",
    "sg:city":"San Antonio",
    "sg:classifiers":[
        {
            "category":"Professional",
            "subcategory":"Lawyer & Legal Services",
            "type":"Services"
        }
    ],
    "sg:phone":"+1 210 821 3377",
    "sg:postcode":"78209",
    "sg:province":"TX",
    "wof:name":"Perry & Kellogg LLP",
    "wof:placetype":"venue"
},
  "geometry": {"coordinates":[-98.466454,29.503394],"type":"Point"}
}