{
  "type": "Feature",
  "properties": {
    "iso:country":"US",
    "sg:address":"7832 Chapin Rd",
    "sg:city":"Fort Worth",
    "sg:classifiers":[
        {
            "category":"Social Services",
            "subcategory":"Adult Care",
            "type":"Services"
        }
    ],
    "sg:phone":"+1 817 244 0142",
    "sg:postcode":"76116",
    "sg:province":"TX",
    "sg:tags":[
        "residential"
    ],
    "wof:name":"Fairview Retirement Community",
    "wof:placetype":"venue"
},
  "geometry": {"coordinates":[-97.44929399999999,32.716354],"type":"Point"}
}