{
  "type": "Feature",
  "properties": {
    "iso:country":"US",
    "sg:address":"447 Mimosa Dr",
    "sg:city":"San Angelo",
    "sg:classifiers":[
        {
            "category":"Food & Beverages",
            "subcategory":"Groceries & Convenience Stores",
            "type":"Retail Goods"
        }
    ],
    "sg:phone":"+1 325 486 9430",
    "sg:postcode":"76903",
    "sg:province":"TX",
    "wof:name":"Grocery Corral",
    "wof:placetype":"venue"
},
  "geometry": {"coordinates":[-100.451829,31.512682],"type":"Point"}
}