{
  "type": "Feature",
  "properties": {
    "iso:country":"US",
    "sg:address":"3505 Olsen Blvd",
    "sg:city":"Amarillo",
    "sg:classifiers":[
        {
            "category":"Organizations",
            "subcategory":"Professional Association",
            "type":"Services"
        }
    ],
    "sg:phone":"+1 806 359 3141",
    "sg:postcode":"79109",
    "sg:province":"TX",
    "wof:name":"Muscular Dystrophy Assn",
    "wof:placetype":"venue"
},
  "geometry": {"coordinates":[-101.878638,35.184748],"type":"Point"}
}