{
  "type": "Feature",
  "properties": {
    "iso:country":"US",
    "sg:address":"7116 Starnes Rd",
    "sg:city":"Fort Worth",
    "sg:classifiers":[
        {
            "category":"Professional",
            "type":"Services"
        }
    ],
    "sg:phone":"+1 817 788 2479",
    "sg:postcode":"76180",
    "sg:province":"TX",
    "wof:name":"Mom Dad Williams",
    "wof:placetype":"venue"
},
  "geometry": {"coordinates":[-97.22663300000001,32.8821],"type":"Point"}
}