{
  "type": "Feature",
  "properties": {
    "iso:country":"US",
    "sg:address":"3355 Long Prairie Rd",
    "sg:city":"Flower Mound",
    "sg:classifiers":[
        {
            "category":"Health Services",
            "subcategory":"Chiropractor",
            "type":"Services"
        }
    ],
    "sg:phone":"+1 972 539 4600",
    "sg:postcode":"75022",
    "sg:province":"TX",
    "wof:name":"Chiropractic Health Center",
    "wof:placetype":"venue"
},
  "geometry": {"coordinates":[-97.070891,33.03068],"type":"Point"}
}