{
  "type": "Feature",
  "properties": {
    "iso:country":"US",
    "sg:address":"6721 Ave K",
    "sg:city":"Houston",
    "sg:classifiers":[
        {
            "category":"Building & Trades",
            "subcategory":"Landscaping Services",
            "type":"Services"
        }
    ],
    "sg:phone":"+1 713 330 8717",
    "sg:postcode":"77011",
    "sg:province":"TX",
    "wof:name":"Eden Lawn Service",
    "wof:placetype":"venue"
},
  "geometry": {"coordinates":[-95.303798,29.743903],"type":"Point"}
}