{
  "type": "Feature",
  "properties": {
    "iso:country":"US",
    "sg:address":"602 W Wheatland Rd",
    "sg:city":"Duncanville",
    "sg:classifiers":[
        {
            "category":"Organizations",
            "subcategory":"Religious Organization",
            "type":"Services"
        }
    ],
    "sg:phone":"+1 972 780 0150",
    "sg:postcode":"75116",
    "sg:province":"TX",
    "wof:name":"Loving Fellowship Christian Church",
    "wof:placetype":"venue"
},
  "geometry": {"coordinates":[-96.9207,32.647499],"type":"Point"}
}