{
  "type": "Feature",
  "properties": {
    "iso:country":"US",
    "sg:address":"5342 Cervantes Dr",
    "sg:city":"San Antonio",
    "sg:classifiers":[
        {
            "category":"Professional",
            "type":"Services"
        }
    ],
    "sg:phone":"+1 210 438 5233",
    "sg:postcode":"78228",
    "sg:province":"TX",
    "wof:name":"Bouquets Of Memories",
    "wof:placetype":"venue"
},
  "geometry": {"coordinates":[-98.59234600000001,29.451604],"type":"Point"}
}