{
  "type": "Feature",
  "properties": {
    "iso:country":"US",
    "sg:address":"4709 Safe Harbour Dr",
    "sg:city":"Arlington",
    "sg:classifiers":[
        {
            "category":"Manufacturing",
            "subcategory":"Textiles",
            "type":"Manufacturing & Wholesale Goods"
        }
    ],
    "sg:phone":"+1 817 483 8920",
    "sg:postcode":"76016",
    "sg:province":"TX",
    "sg:tags":[
        "plant",
        "silk",
        "finishing",
        "fiber"
    ],
    "wof:name":"Silken Memories",
    "wof:placetype":"venue"
},
  "geometry": {"coordinates":[-97.22913,32.671268],"type":"Point"}
}