{
  "type": "Feature",
  "properties": {
    "iso:country":"US",
    "sg:address":"813 W FM 917",
    "sg:city":"Joshua",
    "sg:classifiers":[
        {
            "category":"Professional",
            "subcategory":"Business Services",
            "type":"Services"
        }
    ],
    "sg:phone":"+1 817 558 9229",
    "sg:postcode":"76058",
    "sg:province":"TX",
    "wof:name":"Advance Sign Co",
    "wof:placetype":"venue"
},
  "geometry": {"coordinates":[-97.395126,32.460336],"type":"Point"}
}