{
  "type": "Feature",
  "properties": {
    "iso:country":"US",
    "sg:address":"4669 Birchbend Ln",
    "sg:city":"Fort Worth",
    "sg:classifiers":[
        {
            "category":"Building & Trades",
            "subcategory":"Construction",
            "type":"Services"
        }
    ],
    "sg:phone":"+1 817 581 7379",
    "sg:postcode":"76137",
    "sg:province":"TX",
    "sg:tags":[
        "contractor"
    ],
    "wof:name":"A & T Glass Tinters",
    "wof:placetype":"venue"
},
  "geometry": {"coordinates":[-97.285623,32.874308],"type":"Point"}
}