{
  "type": "Feature",
  "properties": {
    "iso:country":"US",
    "sg:address":"1031 Purple Sage",
    "sg:city":"Canyon Lake",
    "sg:classifiers":[
        {
            "category":"Travel",
            "subcategory":"Hotels & Motels",
            "type":"Entertainment"
        }
    ],
    "sg:phone":"+1 830 935 4123",
    "sg:postcode":"78133",
    "sg:province":"TX",
    "sg:tags":[
        "breakfast",
        "accommodation",
        "bed"
    ],
    "wof:name":"Rustic Ridge",
    "wof:placetype":"venue"
},
  "geometry": {"coordinates":[-98.25552999999999,29.926455],"type":"Point"}
}