{
  "type": "Feature",
  "properties": {
    "iso:country":"US",
    "sg:address":"5919 Bellaire Blvd",
    "sg:city":"Houston",
    "sg:classifiers":[
        {
            "category":"Building & Trades",
            "subcategory":"Plumbing",
            "type":"Services"
        }
    ],
    "sg:phone":"+1 713 666 5890",
    "sg:postcode":"77081",
    "sg:province":"TX",
    "sg:tags":[
        "contractor"
    ],
    "wof:name":"Cardinal Plumbing Company",
    "wof:placetype":"venue"
},
  "geometry": {"coordinates":[-95.485648,29.705136],"type":"Point"}
}