{
  "type": "Feature",
  "properties": {
    "iso:country":"US",
    "sg:address":"3106 S Birmingham St",
    "sg:city":"Amarillo",
    "sg:classifiers":[
        {
            "category":"Shopping",
            "subcategory":"Hobbies, Toys, & Games",
            "type":"Retail Goods"
        }
    ],
    "sg:phone":"+1 806 342 4207",
    "sg:postcode":"79103",
    "sg:province":"TX",
    "wof:name":"TNT Crafts",
    "wof:placetype":"venue"
},
  "geometry": {"coordinates":[-101.810551,35.179667],"type":"Point"}
}