{
  "type": "Feature",
  "properties": {
    "iso:country":"US",
    "sg:address":"26402 Cottage Cypress Ln",
    "sg:city":"Cypress",
    "sg:classifiers":[
        {
            "category":"Professional",
            "subcategory":"Business Services",
            "type":"Services"
        }
    ],
    "sg:phone":"+1 281 213 8289",
    "sg:postcode":"77433",
    "sg:province":"TX",
    "sg:tags":[
        "consultant",
        "coach"
    ],
    "wof:name":"Nomarian Consulting",
    "wof:placetype":"venue"
},
  "geometry": {"coordinates":[-95.70540200000001,29.949396],"type":"Point"}
}