{
  "type": "Feature",
  "properties": {
    "iso:country":"US",
    "sg:address":"4133 Lavell Ave",
    "sg:city":"Wichita Falls",
    "sg:classifiers":[
        {
            "category":"Building & Trades",
            "subcategory":"Construction",
            "type":"Services"
        }
    ],
    "sg:phone":"+1 940 691 5335",
    "sg:postcode":"76308",
    "sg:province":"TX",
    "sg:tags":[
        "hanging",
        "contractor"
    ],
    "wof:name":"Halls Painting",
    "wof:placetype":"venue"
},
  "geometry": {"coordinates":[-98.550737,33.860767],"type":"Point"}
}