{
  "type": "Feature",
  "properties": {
    "iso:country":"US",
    "sg:address":"4800 Lansdale Dr",
    "sg:city":"Flower Mound",
    "sg:classifiers":[
        {
            "category":"Manufacturing",
            "subcategory":"Jewelry",
            "type":"Manufacturing & Wholesale Goods"
        }
    ],
    "sg:phone":"+1 972 539 7402",
    "sg:postcode":"75028",
    "sg:province":"TX",
    "sg:tags":[
        "precious",
        "metal",
        "mfg"
    ],
    "wof:name":"Joy Absolute",
    "wof:placetype":"venue"
},
  "geometry": {"coordinates":[-97.053381,33.051038],"type":"Point"}
}