{
  "type": "Feature",
  "properties": {
    "iso:country":"US",
    "sg:address":"7916 Fredericksburg Rd",
    "sg:city":"San Antonio",
    "sg:classifiers":[
        {
            "category":"Health Services",
            "subcategory":"Doctor",
            "type":"Services"
        }
    ],
    "sg:phone":"+1 210 492 7777",
    "sg:postcode":"78229",
    "sg:province":"TX",
    "sg:tags":[
        "dentist"
    ],
    "wof:name":"Rapanotti & Rapanotti",
    "wof:placetype":"venue"
},
  "geometry": {"coordinates":[-98.567166,29.510873],"type":"Point"}
}