{
  "type": "Feature",
  "properties": {
    "iso:country":"US",
    "sg:address":"805 W Centerville Rd",
    "sg:city":"Garland",
    "sg:classifiers":[
        {
            "category":"Restaurant",
            "type":"Food & Drink"
        }
    ],
    "sg:phone":"+1 972 682 5411",
    "sg:postcode":"75041",
    "sg:province":"TX",
    "sg:tags":[
        "seafood"
    ],
    "wof:name":"Crazy Catfish Restaurant",
    "wof:placetype":"venue"
},
  "geometry": {"coordinates":[-96.642799,32.860901],"type":"Point"}
}