{
  "type": "Feature",
  "properties": {
    "iso:country":"US",
    "sg:address":"3404 Rankin St",
    "sg:city":"Dallas",
    "sg:classifiers":[
        {
            "category":"Personal",
            "subcategory":"Beauty Salon",
            "type":"Services"
        }
    ],
    "sg:phone":"+1 214 692 6338",
    "sg:postcode":"75205",
    "sg:province":"TX",
    "sg:tags":[
        "spa",
        "skin",
        "treatment",
        "day"
    ],
    "wof:name":"Time Well Spent Day Spa",
    "wof:placetype":"venue"
},
  "geometry": {"coordinates":[-96.78689199999999,32.849345],"type":"Point"}
}