{
  "type": "Feature",
  "properties": {
    "iso:country":"US",
    "sg:address":"122 W 2nd St",
    "sg:city":"Shamrock",
    "sg:classifiers":[
        {
            "category":"Government",
            "subcategory":"Office",
            "type":"Public Place"
        }
    ],
    "sg:phone":"+1 806 256 2552",
    "sg:postcode":"79079",
    "sg:province":"TX",
    "wof:name":"Wheeler County Justice-Peace",
    "wof:placetype":"venue"
},
  "geometry": {"coordinates":[-100.250213,35.215402],"type":"Point"}
}