{
  "type": "Feature",
  "properties": {
    "iso:country":"US",
    "sg:address":"9 Uvalde Rd",
    "sg:city":"Houston",
    "sg:classifiers":[
        {
            "category":"Food & Beverages",
            "subcategory":"Liquor & Beverages",
            "type":"Retail Goods"
        }
    ],
    "sg:phone":"+1 713 453 0535",
    "sg:postcode":"77015",
    "sg:province":"TX",
    "sg:tags":[
        "beer",
        "wine",
        "spirit",
        "alcoholic"
    ],
    "wof:name":"Rose Liquor",
    "wof:placetype":"venue"
},
  "geometry": {"coordinates":[-95.182198,29.805901],"type":"Point"}
}