{
  "type": "Feature",
  "properties": {
    "iso:country":"US",
    "sg:address":"4347 S Hampton Rd",
    "sg:city":"Dallas",
    "sg:classifiers":[
        {
            "category":"Professional",
            "subcategory":"Employment Agencies",
            "type":"Services"
        }
    ],
    "sg:phone":"+1 214 331 0790",
    "sg:postcode":"75232",
    "sg:province":"TX",
    "sg:tags":[
        "secretarial",
        "resume"
    ],
    "wof:name":"Safety & Office",
    "wof:placetype":"venue"
},
  "geometry": {"coordinates":[-96.85714,32.690446],"type":"Point"}
}