{
  "type": "Feature",
  "properties": {
    "iso:country":"US",
    "sg:address":"1700 Rivercrest Dr",
    "sg:city":"Sugar Land",
    "sg:classifiers":[
        {
            "category":"Professional",
            "type":"Services"
        }
    ],
    "sg:phone":"+1 281 265 7127",
    "sg:postcode":"77478",
    "sg:province":"TX",
    "sg:tags":[
        "establishment"
    ],
    "wof:name":"Graphically Speaking",
    "wof:placetype":"venue"
},
  "geometry": {"coordinates":[-95.61588999999999,29.599527],"type":"Point"}
}