{
  "type": "Feature",
  "properties": {
    "iso:country":"US",
    "sg:address":"4521 Garden Ln",
    "sg:city":"Odessa",
    "sg:classifiers":[
        {
            "category":"Manufacturing",
            "subcategory":"Metals",
            "type":"Manufacturing & Wholesale Goods"
        }
    ],
    "sg:phone":"+1 432 367 2909",
    "sg:postcode":"79761",
    "sg:province":"TX",
    "sg:tags":[
        "coating"
    ],
    "wof:name":"Carboline Co",
    "wof:placetype":"venue"
},
  "geometry": {"coordinates":[-102.32507099999999,31.870514],"type":"Point"}
}