{
  "type": "Feature",
  "properties": {
    "iso:country":"US",
    "sg:address":"1120 SW 15th Ave",
    "sg:city":"Amarillo",
    "sg:classifiers":[
        {
            "category":"Shopping",
            "subcategory":"Department Store",
            "type":"Retail Goods"
        },
        {
            "category":"Shopping",
            "subcategory":"Discount & Variety Stores",
            "type":"Retail Goods"
        },
        {
            "category":"Food & Beverages",
            "subcategory":"Groceries & Convenience Stores",
            "type":"Retail Goods"
        }
    ],
    "sg:phone":"+1 806 372 7008",
    "sg:postcode":"79102",
    "sg:province":"TX",
    "wof:name":"Family Discount",
    "wof:placetype":"venue"
},
  "geometry": {"coordinates":[-101.85003399999999,35.199684],"type":"Point"}
}