{
  "type": "Feature",
  "properties": {
    "iso:country":"US",
    "sg:address":"1008 Hebron Pkwy W",
    "sg:city":"Carrollton",
    "sg:classifiers":[
        {
            "category":"Personal",
            "type":"Services"
        },
        {
            "category":"Health Services",
            "subcategory":"Clinic",
            "type":"Services"
        }
    ],
    "sg:phone":"+1 972 731 1220",
    "sg:postcode":"75010",
    "sg:province":"TX",
    "sg:tags":[
        "consultant",
        "program",
        "fitness"
    ],
    "wof:name":"Smoothie Factory The",
    "wof:placetype":"venue"
},
  "geometry": {"coordinates":[-96.91608600000001,33.020848],"type":"Point"}
}