{
  "type": "Feature",
  "properties": {
    "iso:country":"US",
    "sg:address":"2324 W Reagan St",
    "sg:city":"Palestine",
    "sg:classifiers":[
        {
            "category":"Manufacturing",
            "subcategory":"Building Materials",
            "type":"Manufacturing & Wholesale Goods"
        }
    ],
    "sg:phone":"+1 903 729 6804",
    "sg:postcode":"75801",
    "sg:province":"TX",
    "sg:tags":[
        "cabinet"
    ],
    "sg:website":"www.terrymfgco.com",
    "wof:name":"Terry Manufacturing Co",
    "wof:placetype":"venue"
},
  "geometry": {"coordinates":[-95.653092,31.74145],"type":"Point"}
}