{
  "type": "Feature",
  "properties": {
    "iso:country":"US",
    "sg:address":"7946 Wolf Dr",
    "sg:city":"Corpus Christi",
    "sg:classifiers":[
        {
            "category":"Food & Beverages",
            "subcategory":"Candy",
            "type":"Retail Goods"
        }
    ],
    "sg:phone":"+1 361 980 1047",
    "sg:postcode":"78414",
    "sg:province":"TX",
    "wof:name":"Choco Latte",
    "wof:placetype":"venue"
},
  "geometry": {"coordinates":[-97.385752,27.650178],"type":"Point"}
}