{
  "type": "Feature",
  "properties": {
    "iso:country":"US",
    "sg:address":"704 Noyes Ave",
    "sg:city":"Melvin",
    "sg:phone":"+1 325 286 4296",
    "sg:postcode":"76858",
    "sg:province":"TX",
    "sg:tags":[
        "farm",
        "wheat",
        "crop",
        "harvesting"
    ],
    "wof:name":"Needle Creek Farms",
    "wof:placetype":"venue"
},
  "geometry": {"coordinates":[-99.58253000000001,31.190862],"type":"Point"}
}