{
  "type": "Feature",
  "properties": {
    "iso:country":"US",
    "sg:address":"730 Sodville St",
    "sg:city":"Sinton",
    "sg:classifiers":[
        {
            "category":"Personal",
            "subcategory":"Beauty Salon",
            "type":"Services"
        }
    ],
    "sg:phone":"+1 361 364 5974",
    "sg:postcode":"78387",
    "sg:province":"TX",
    "wof:name":"Olgas Beauty Salon",
    "wof:placetype":"venue"
},
  "geometry": {"coordinates":[-97.504946,28.030082],"type":"Point"}
}