{
  "type": "Feature",
  "properties": {
    "iso:country":"US",
    "sg:address":"2124 Myrtle Ave",
    "sg:city":"El Paso",
    "sg:classifiers":[
        {
            "category":"Retail",
            "subcategory":"Auto Repair",
            "type":"Services"
        }
    ],
    "sg:phone":"+1 915 544 0010",
    "sg:postcode":"79901",
    "sg:province":"TX",
    "sg:tags":[
        "body",
        "automobile",
        "painting"
    ],
    "wof:name":"Quiroga's Body Shop",
    "wof:placetype":"venue"
},
  "geometry": {"coordinates":[-106.46544900000001,31.771554],"type":"Point"}
}