{
  "type": "Feature",
  "properties": {
    "iso:country":"US",
    "sg:address":"1 Park Ten Pl",
    "sg:city":"Houston",
    "sg:classifiers":[
        {
            "category":"Wholesale",
            "subcategory":"Machinery & Supplies",
            "type":"Manufacturing & Wholesale Goods"
        },
        {
            "category":"Wholesale",
            "subcategory":"Durable Goods & Equipment",
            "type":"Manufacturing & Wholesale Goods"
        }
    ],
    "sg:phone":"+1 281 647 9150",
    "sg:postcode":"77084",
    "sg:province":"TX",
    "sg:tags":[
        "industrial",
        "export",
        "exporter"
    ],
    "wof:name":"Cana International Co",
    "wof:placetype":"venue"
},
  "geometry": {"coordinates":[-95.668289,29.786814],"type":"Point"}
}