{
  "type": "Feature",
  "properties": {
    "iso:country":"US",
    "sg:address":"14412 Highway 105 E",
    "sg:city":"Conroe",
    "sg:classifiers":[
        {
            "category":"Government",
            "subcategory":"Fire Station",
            "type":"Public Place"
        }
    ],
    "sg:phone":"+1 936 264 1313",
    "sg:postcode":"77306",
    "sg:province":"TX",
    "sg:tags":[
        "department"
    ],
    "wof:name":"Cut-N-Shoot Volunteer Fire Department Inc",
    "wof:placetype":"venue"
},
  "geometry": {"coordinates":[-95.349226,30.333049],"type":"Point"}
}