{
  "type": "Feature",
  "properties": {
    "iso:country":"US",
    "sg:address":"1900 Abrams Pkwy",
    "sg:city":"Dallas",
    "sg:classifiers":[
        {
            "category":"Shopping",
            "subcategory":"Gifts & Souvenirs",
            "type":"Retail Goods"
        }
    ],
    "sg:phone":"+1 214 824 2777",
    "sg:postcode":"75214",
    "sg:province":"TX",
    "wof:name":"Splendor In Grass LLC",
    "wof:placetype":"venue"
},
  "geometry": {"coordinates":[-96.75290099999999,32.812686],"type":"Point"}
}