{
  "type": "Feature",
  "properties": {
    "iso:country":"US",
    "sg:address":"1327 Fair Ave",
    "sg:city":"San Antonio",
    "sg:classifiers":[
        {
            "category":"Shopping",
            "type":"Retail Goods"
        }
    ],
    "sg:phone":"+1 210 534 7218",
    "sg:postcode":"78223",
    "sg:province":"TX",
    "sg:tags":[
        "merchandise",
        "animal"
    ],
    "wof:name":"Cathy-Ann Pet Center",
    "wof:placetype":"venue"
},
  "geometry": {"coordinates":[-98.457239,29.384189],"type":"Point"}
}