{
  "type": "Feature",
  "properties": {
    "iso:country":"US",
    "sg:address":"711 Main St",
    "sg:city":"Dallas",
    "sg:classifiers":[
        {
            "category":"Professional",
            "subcategory":"Lawyer & Legal Services",
            "type":"Services"
        }
    ],
    "sg:phone":"+1 972 998 2079",
    "sg:postcode":"75201",
    "sg:province":"TX",
    "sg:tags":[
        "litigation"
    ],
    "wof:name":"John T McCully",
    "wof:placetype":"venue"
},
  "geometry": {"coordinates":[-96.805206,32.779386],"type":"Point"}
}