{
  "type": "Feature",
  "properties": {
    "iso:country":"US",
    "sg:address":"7 Nelson Ct",
    "sg:city":"Freeport",
    "sg:classifiers":[
        {
            "category":"Building & Trades",
            "subcategory":"Electrical",
            "type":"Services"
        }
    ],
    "sg:phone":"+1 979 233 5020",
    "sg:postcode":"77541",
    "sg:province":"TX",
    "sg:tags":[
        "electric",
        "contractor"
    ],
    "wof:name":"DWD Electric",
    "wof:placetype":"venue"
},
  "geometry": {"coordinates":[-95.492683,28.978783],"type":"Point"}
}