{
  "type": "Feature",
  "properties": {
    "iso:country":"US",
    "sg:address":"8102 Cross Creek Dr",
    "sg:city":"San Antonio",
    "sg:classifiers":[
        {
            "category":"Professional",
            "type":"Services"
        }
    ],
    "sg:phone":"+1 210 637 5673",
    "sg:postcode":"78218",
    "sg:province":"TX",
    "wof:name":"Dreammasters",
    "wof:placetype":"venue"
},
  "geometry": {"coordinates":[-98.402832,29.511938],"type":"Point"}
}