{
  "type": "Feature",
  "properties": {
    "iso:country":"US",
    "sg:address":"12 Elm St",
    "sg:city":"Blanco",
    "sg:classifiers":[
        {
            "category":"Recreation",
            "type":"Entertainment"
        }
    ],
    "sg:phone":"+1 830 833 0318",
    "sg:postcode":"78606",
    "sg:province":"TX",
    "wof:name":"Casa De Yoga",
    "wof:placetype":"venue"
},
  "geometry": {"coordinates":[-98.425603,30.091926],"type":"Point"}
}