{
  "type": "Feature",
  "properties": {
    "iso:country":"US",
    "sg:address":"17007 Barcelona Dr",
    "sg:city":"Friendswood",
    "sg:classifiers":[
        {
            "category":"Professional",
            "type":"Services"
        }
    ],
    "sg:phone":"+1 281 482 3819",
    "sg:postcode":"77546",
    "sg:province":"TX",
    "wof:name":"Flinnart",
    "wof:placetype":"venue"
},
  "geometry": {"coordinates":[-95.17393,29.526827],"type":"Point"}
}