{
  "type": "Feature",
  "properties": {
    "iso:country":"US",
    "sg:address":"503 Clear Creek Ln",
    "sg:city":"Dripping Springs",
    "sg:classifiers":[
        {
            "category":"Professional",
            "subcategory":"Management & Consulting",
            "type":"Services"
        }
    ],
    "sg:phone":"+1 512 858 0941",
    "sg:postcode":"78620",
    "sg:province":"TX",
    "sg:tags":[
        "information",
        "technology"
    ],
    "wof:name":"Catalan Group  The",
    "wof:placetype":"venue"
},
  "geometry": {"coordinates":[-98.04821699999999,30.214023],"type":"Point"}
}