{
  "type": "Feature",
  "properties": {
    "iso:country":"US",
    "sg:address":"12872 State Hwy 155",
    "sg:city":"Tyler",
    "sg:classifiers":[
        {
            "category":"Social Services",
            "type":"Services"
        }
    ],
    "sg:phone":"+1 903 939 0899",
    "sg:postcode":"75703",
    "sg:province":"TX",
    "sg:tags":[
        "counseling"
    ],
    "wof:name":"Counseling Services",
    "wof:placetype":"venue"
},
  "geometry": {"coordinates":[-95.35002799999999,32.292425],"type":"Point"}
}