{
  "type": "Feature",
  "properties": {
    "iso:country":"US",
    "sg:address":"200 E Milam St",
    "sg:city":"Wharton",
    "sg:classifiers":[
        {
            "category":"Building & Trades",
            "subcategory":"Plumbing",
            "type":"Services"
        }
    ],
    "sg:phone":"+1 979 532 5101",
    "sg:postcode":"77488",
    "sg:province":"TX",
    "sg:tags":[
        "conditioning",
        "air",
        "system",
        "contractor"
    ],
    "wof:name":"Roberson Air Conditioning",
    "wof:placetype":"venue"
},
  "geometry": {"coordinates":[-96.099019,29.310513],"type":"Point"}
}