{
  "type": "Feature",
  "properties": {
    "iso:country":"US",
    "sg:address":"2924 Co Rd 520",
    "sg:city":"Brazoria",
    "sg:classifiers":[
        {
            "category":"Organizations",
            "subcategory":"Religious Organization",
            "type":"Services"
        }
    ],
    "sg:phone":"+1 979 798 8362",
    "sg:postcode":"77422",
    "sg:province":"TX",
    "wof:name":"Greater Mt Zion Baptist Church",
    "wof:placetype":"venue"
},
  "geometry": {"coordinates":[-95.582554,29.011203],"type":"Point"}
}