{
  "type": "Feature",
  "properties": {
    "iso:country":"US",
    "sg:address":"417 W Van Buren Ave",
    "sg:city":"Harlingen",
    "sg:classifiers":[
        {
            "category":"Restaurant",
            "type":"Food & Drink"
        }
    ],
    "sg:phone":"+1 956 440 0080",
    "sg:postcode":"78550",
    "sg:province":"TX",
    "sg:tags":[
        "eating"
    ],
    "wof:name":"Dona Ana Cocina",
    "wof:placetype":"venue"
},
  "geometry": {"coordinates":[-97.69983499999999,26.191628],"type":"Point"}
}