{
  "type": "Feature",
  "properties": {
    "iso:country":"US",
    "sg:address":"15407 Waldwick Dr",
    "sg:city":"Tomball",
    "sg:classifiers":[
        {
            "category":"Professional",
            "type":"Services"
        }
    ],
    "sg:phone":"+1 281 320 2152",
    "sg:postcode":"77377",
    "sg:province":"TX",
    "wof:name":"Premium Workforce Inc",
    "wof:placetype":"venue"
},
  "geometry": {"coordinates":[-95.59553,29.996741],"type":"Point"}
}