{
  "type": "Feature",
  "properties": {
    "iso:country":"US",
    "sg:address":"11110 W Airport Blvd",
    "sg:city":"Stafford",
    "sg:classifiers":[
        {
            "category":"Bars & Pubs",
            "type":"Food & Drink"
        }
    ],
    "sg:phone":"+1 281 498 4757",
    "sg:postcode":"77477",
    "sg:province":"TX",
    "sg:tags":[
        "sport",
        "bar"
    ],
    "wof:name":"Sports Resort III Bar & Grill",
    "wof:placetype":"venue"
},
  "geometry": {"coordinates":[-95.568243,29.641216],"type":"Point"}
}