{
  "type": "Feature",
  "properties": {
    "iso:country":"US",
    "sg:address":"19415 Indigo Lake Dr",
    "sg:city":"Magnolia",
    "sg:classifiers":[
        {
            "category":"Organizations",
            "subcategory":"Membership Organization",
            "type":"Services"
        }
    ],
    "sg:phone":"+1 281 356 1690",
    "sg:postcode":"77355",
    "sg:province":"TX",
    "wof:name":"Texas Slammers Volleyball Club",
    "wof:placetype":"venue"
},
  "geometry": {"coordinates":[-95.772952,30.158666],"type":"Point"}
}