{
  "type": "Feature",
  "properties": {
    "iso:country":"US",
    "sg:address":"908 W Tennessee St",
    "sg:city":"Floydada",
    "sg:classifiers":[
        {
            "category":"Freight",
            "type":"Transportation"
        }
    ],
    "sg:phone":"+1 806 983 2641",
    "sg:postcode":"79235",
    "sg:province":"TX",
    "sg:tags":[
        "trucking"
    ],
    "wof:name":"Sanders & Sanders Harvesting",
    "wof:placetype":"venue"
},
  "geometry": {"coordinates":[-101.34972500000001,33.981032],"type":"Point"}
}