{
  "type": "Feature",
  "properties": {
    "iso:country":"US",
    "sg:address":"5140 Rufe Snow Dr",
    "sg:city":"Fort Worth",
    "sg:classifiers":[
        {
            "category":"Restaurant",
            "type":"Food & Drink"
        }
    ],
    "sg:phone":"+1 817 281 8888",
    "sg:postcode":"76180",
    "sg:province":"TX",
    "wof:name":"Mc Donald's",
    "wof:placetype":"venue"
},
  "geometry": {"coordinates":[-97.23866099999999,32.839018],"type":"Point"}
}