{
  "type": "Feature",
  "properties": {
    "iso:country":"US",
    "sg:address":"1209 Elm St",
    "sg:city":"Sweetwater",
    "sg:classifiers":[
        {
            "category":"Restaurant",
            "type":"Food & Drink"
        }
    ],
    "sg:phone":"+1 325 235 1448",
    "sg:postcode":"79556",
    "sg:province":"TX",
    "sg:tags":[
        "eating"
    ],
    "wof:name":"Williams Barbeque",
    "wof:placetype":"venue"
},
  "geometry": {"coordinates":[-100.410196,32.479345],"type":"Point"}
}