{
  "type": "Feature",
  "properties": {
    "iso:country":"US",
    "sg:address":"101 W Jackson Ave",
    "sg:city":"Harlingen",
    "sg:classifiers":[
        {
            "category":"Professional",
            "subcategory":"Accounting & Tax Preparation",
            "type":"Services"
        }
    ],
    "sg:phone":"+1 956 412 7230",
    "sg:postcode":"78550",
    "sg:province":"TX",
    "sg:tags":[
        "bookkeeping",
        "general"
    ],
    "wof:name":"Business Management Svc",
    "wof:placetype":"venue"
},
  "geometry": {"coordinates":[-97.696703,26.192756],"type":"Point"}
}