{
  "type": "Feature",
  "properties": {
    "iso:country":"US",
    "sg:address":"413 Campbell Rd",
    "sg:city":"Longview",
    "sg:classifiers":[
        {
            "category":"Shopping",
            "subcategory":"Jewelry",
            "type":"Retail Goods"
        },
        {
            "category":"Manufacturing",
            "subcategory":"Jewelry",
            "type":"Manufacturing & Wholesale Goods"
        }
    ],
    "sg:phone":"+1 903 663 2913",
    "sg:postcode":"75605",
    "sg:province":"TX",
    "sg:tags":[
        "designer",
        "jeweler"
    ],
    "wof:name":"Widows Ring Enterprises Inc",
    "wof:placetype":"venue"
},
  "geometry": {"coordinates":[-94.788217,32.626118],"type":"Point"}
}