{
  "type": "Feature",
  "properties": {
    "iso:country":"US",
    "sg:address":"1301 N Ave E",
    "sg:city":"Beeville",
    "sg:classifiers":[
        {
            "category":"Restaurant",
            "type":"Food & Drink"
        }
    ],
    "sg:phone":"+1 361 358 9922",
    "sg:postcode":"78102",
    "sg:province":"TX",
    "sg:tags":[
        "eating"
    ],
    "wof:name":"Goodies",
    "wof:placetype":"venue"
},
  "geometry": {"coordinates":[-97.75718500000001,28.411555],"type":"Point"}
}