{
  "type": "Feature",
  "properties": {
    "iso:country":"US",
    "sg:address":"6101 N 27th St",
    "sg:city":"Mcallen",
    "sg:classifiers":[
        {
            "category":"Professional",
            "subcategory":"Business Services",
            "type":"Services"
        }
    ],
    "sg:phone":"+1 956 928 1749",
    "sg:postcode":"78504",
    "sg:province":"TX",
    "wof:name":"Andrews Enterprises",
    "wof:placetype":"venue"
},
  "geometry": {"coordinates":[-98.24193200000001,26.260247],"type":"Point"}
}