{
  "type": "Feature",
  "properties": {
    "iso:country":"US",
    "sg:address":"12602 Mews Cir",
    "sg:city":"Houston",
    "sg:classifiers":[
        {
            "category":"Freight",
            "type":"Transportation"
        }
    ],
    "sg:phone":"+1 281 431 9191",
    "sg:postcode":"77082",
    "sg:province":"TX",
    "wof:name":"Nat Jackson Transportation Svc",
    "wof:placetype":"venue"
},
  "geometry": {"coordinates":[-95.606908,29.734407],"type":"Point"}
}