{
  "type": "Feature",
  "properties": {
    "iso:country":"US",
    "sg:address":"1407 W Loop 281",
    "sg:city":"Longview",
    "sg:classifiers":[
        {
            "category":"Shopping",
            "type":"Retail Goods"
        }
    ],
    "sg:phone":"+1 903 759 2707",
    "sg:postcode":"75604",
    "sg:province":"TX",
    "sg:tags":[
        "lumber",
        "merchandise"
    ],
    "wof:name":"C & H Art and Framing",
    "wof:placetype":"venue"
},
  "geometry": {"coordinates":[-94.776881,32.529051],"type":"Point"}
}