{
  "type": "Feature",
  "properties": {
    "iso:country":"US",
    "sg:address":"2015 W Northwest Hwy",
    "sg:city":"Dallas",
    "sg:classifiers":[
        {
            "category":"Banks & Credit Unions",
            "subcategory":"Bank",
            "type":"Services"
        }
    ],
    "sg:phone":"+1 972 364 6795",
    "sg:postcode":"75220",
    "sg:province":"TX",
    "sg:website":"www.capitalonebank.com",
    "wof:name":"CapitalOne",
    "wof:placetype":"venue"
},
  "geometry": {"coordinates":[-96.90901700000001,32.867697],"type":"Point"}
}