{
  "type": "Feature",
  "properties": {
    "iso:country":"US",
    "sg:address":"6000 Industrial Dr",
    "sg:city":"Waco",
    "sg:classifiers":[
        {
            "category":"Government",
            "subcategory":"Office",
            "type":"Public Place"
        }
    ],
    "sg:phone":"+1 254 753 3052",
    "sg:postcode":"76710",
    "sg:province":"TX",
    "wof:name":"Mc Lennan County Restitution",
    "wof:placetype":"venue"
},
  "geometry": {"coordinates":[-97.174578,31.520052],"type":"Point"}
}