{
  "type": "Feature",
  "properties": {
    "iso:country":"US",
    "sg:address":"8311 Knight Rd",
    "sg:city":"Houston",
    "sg:classifiers":[
        {
            "category":"Manufacturing",
            "subcategory":"Tools & Machinery",
            "type":"Manufacturing & Wholesale Goods"
        }
    ],
    "sg:phone":"+1 713 383 0002",
    "sg:postcode":"77054",
    "sg:province":"TX",
    "sg:tags":[
        "machine",
        "equipment",
        "automatic",
        "teller",
        "mfg"
    ],
    "wof:name":"Resource Teledata Inc",
    "wof:placetype":"venue"
},
  "geometry": {"coordinates":[-95.39980300000001,29.683701],"type":"Point"}
}