{
  "type": "Feature",
  "properties": {
    "iso:country":"US",
    "sg:address":"2650 Fountain View Ste 103",
    "sg:city":"Houston",
    "sg:classifiers":[
        {
            "category":"Personal",
            "subcategory":"Beauty Salon",
            "type":"Services"
        }
    ],
    "sg:phone":"+1 832 454 6555",
    "sg:postcode":"77057",
    "sg:province":"TX",
    "sg:tags":[
        "hair"
    ],
    "sg:website":"hollywood2houston.com",
    "wof:name":"Hollywood 2 Houston Salon",
    "wof:placetype":"venue"
},
  "geometry": {"coordinates":[-95.485592,29.739223],"type":"Point"}
}