{
  "type": "Feature",
  "properties": {
    "iso:country":"US",
    "sg:address":"12046 la Salle Br",
    "sg:city":"Conroe",
    "sg:classifiers":[
        {
            "category":"Food & Beverages",
            "subcategory":"Groceries & Convenience Stores",
            "type":"Retail Goods"
        }
    ],
    "sg:phone":"+1 936 441 2168",
    "sg:postcode":"77304",
    "sg:province":"TX",
    "wof:name":"Lytrinh Super K Inc",
    "wof:placetype":"venue"
},
  "geometry": {"coordinates":[-95.543896,30.351402],"type":"Point"}
}