{
  "type": "Feature",
  "properties": {
    "iso:country":"US",
    "sg:address":"490 Arbors Cir",
    "sg:city":"Elgin",
    "sg:classifiers":[
        {
            "category":"Retail",
            "subcategory":"Veterinary Services",
            "type":"Services"
        }
    ],
    "sg:phone":"+1 512 281 3800",
    "sg:postcode":"78621",
    "sg:province":"TX",
    "sg:tags":[
        "veterinarian",
        "specialty"
    ],
    "wof:name":"W H Cardwell",
    "wof:placetype":"venue"
},
  "geometry": {"coordinates":[-97.336822,30.299727],"type":"Point"}
}