{
  "type": "Feature",
  "properties": {
    "iso:country":"US",
    "sg:address":"6302 Innsbrooke Dr",
    "sg:city":"Arlington",
    "sg:classifiers":[
        {
            "category":"Professional",
            "subcategory":"Business Services",
            "type":"Services"
        }
    ],
    "sg:phone":"+1 817 483 2418",
    "sg:postcode":"76016",
    "sg:province":"TX",
    "wof:name":"DMV Enterprises",
    "wof:placetype":"venue"
},
  "geometry": {"coordinates":[-97.20774900000001,32.674952],"type":"Point"}
}