{
  "type": "Feature",
  "properties": {
    "iso:country":"US",
    "sg:address":"4779 N Galloway Ave",
    "sg:city":"Mesquite",
    "sg:classifiers":[
        {
            "category":"Communications",
            "subcategory":"Film & Video Production",
            "type":"Services"
        }
    ],
    "sg:phone":"+1 214 577 8357",
    "sg:postcode":"75150",
    "sg:province":"TX",
    "sg:tags":[
        "motion"
    ],
    "wof:name":"Action Productions",
    "wof:placetype":"venue"
},
  "geometry": {"coordinates":[-96.626706,32.827463],"type":"Point"}
}