{
  "type": "Feature",
  "properties": {
    "iso:country":"US",
    "sg:address":"15328 Ladera Dr",
    "sg:city":"Dallas",
    "sg:classifiers":[
        {
            "category":"Professional",
            "type":"Services"
        }
    ],
    "sg:phone":"+1 214 703 0250",
    "sg:postcode":"75248",
    "sg:province":"TX",
    "sg:tags":[
        "establishment"
    ],
    "wof:name":"Watson Capital",
    "wof:placetype":"venue"
},
  "geometry": {"coordinates":[-96.808937,32.956937],"type":"Point"}
}