{
  "type": "Feature",
  "properties": {
    "iso:country":"US",
    "sg:address":"1219 Missouri St",
    "sg:city":"Houston",
    "sg:classifiers":[
        {
            "category":"Organizations",
            "subcategory":"Community Association",
            "type":"Services"
        }
    ],
    "sg:phone":"+1 713 527 9880",
    "sg:postcode":"77006",
    "sg:province":"TX",
    "wof:name":"Tower Lofts Maintenance Assoc",
    "wof:placetype":"venue"
},
  "geometry": {"coordinates":[-95.39339099999999,29.746194],"type":"Point"}
}