{
  "type": "Feature",
  "properties": {
    "iso:country":"US",
    "sg:address":"6501 Legacy Dr",
    "sg:city":"Plano",
    "sg:classifiers":[
        {
            "category":"Shopping",
            "subcategory":"Department Store",
            "type":"Retail Goods"
        }
    ],
    "sg:phone":"+1 972 431 1000",
    "sg:postcode":"75024",
    "sg:province":"TX",
    "sg:website":"www.jcpenney.com",
    "wof:name":"J C Penney China Inc",
    "wof:placetype":"venue"
},
  "geometry": {"coordinates":[-96.83387399999999,33.07872],"type":"Point"}
}