{
  "type": "Feature",
  "properties": {
    "iso:country":"US",
    "sg:address":"110 W Martindale Rd",
    "sg:city":"Seguin",
    "sg:classifiers":[
        {
            "category":"Professional",
            "type":"Services"
        }
    ],
    "sg:phone":"+1 830 303 9266",
    "sg:postcode":"78155",
    "sg:province":"TX",
    "wof:name":"Mawauzo Fikira",
    "wof:placetype":"venue"
},
  "geometry": {"coordinates":[-97.965085,29.593465],"type":"Point"}
}