{
  "type": "Feature",
  "properties": {
    "iso:country":"US",
    "sg:address":"411 E 66th St",
    "sg:city":"Lubbock",
    "sg:classifiers":[
        {
            "category":"Freight",
            "type":"Transportation"
        }
    ],
    "sg:phone":"+1 806 745 4502",
    "sg:postcode":"79404",
    "sg:province":"TX",
    "sg:tags":[
        "carrier",
        "common",
        "trucking"
    ],
    "wof:name":"Watkins Motor Lines Inc",
    "wof:placetype":"venue"
},
  "geometry": {"coordinates":[-101.83341799999999,33.534123],"type":"Point"}
}