{
  "type": "Feature",
  "properties": {
    "iso:country":"US",
    "sg:address":"1815 Penina Dr",
    "sg:city":"Crosby",
    "sg:classifiers":[
        {
            "category":"Professional",
            "subcategory":"Business Services",
            "type":"Services"
        }
    ],
    "sg:phone":"+1 281 328 7920",
    "sg:postcode":"77532",
    "sg:province":"TX",
    "wof:name":"Libbra Designs",
    "wof:placetype":"venue"
},
  "geometry": {"coordinates":[-95.100623,29.911941],"type":"Point"}
}