{
  "type": "Feature",
  "properties": {
    "iso:country":"US",
    "sg:address":"1503 Main St",
    "sg:city":"Texarkana",
    "sg:classifiers":[
        {
            "category":"Autos & Motor Vehicles",
            "subcategory":"Automobile Sales",
            "type":"Retail Goods"
        }
    ],
    "sg:phone":"+1 903 792 5808",
    "sg:postcode":"75501",
    "sg:province":"TX",
    "sg:tags":[
        "used"
    ],
    "wof:name":"Integrity Auto Sales",
    "wof:placetype":"venue"
},
  "geometry": {"coordinates":[-94.05172899999999,33.433565],"type":"Point"}
}