{
  "type": "Feature",
  "properties": {
    "iso:country":"US",
    "sg:address":"6006 82nd St",
    "sg:city":"Lubbock",
    "sg:classifiers":[
        {
            "category":"Retail",
            "subcategory":"Laundry & Dry Cleaning",
            "type":"Services"
        }
    ],
    "sg:phone":"+1 806 722 1940",
    "sg:postcode":"79424",
    "sg:province":"TX",
    "sg:tags":[
        "cleaners"
    ],
    "wof:name":"Master Cleaners",
    "wof:placetype":"venue"
},
  "geometry": {"coordinates":[-101.948258,33.519775],"type":"Point"}
}