{
  "type": "Feature",
  "properties": {
    "iso:country":"US",
    "sg:address":"6354 Edgemere Blvd",
    "sg:city":"El Paso",
    "sg:classifiers":[
        {
            "category":"Professional",
            "subcategory":"Testing Lab",
            "type":"Services"
        },
        {
            "category":"Retail",
            "subcategory":"Repair Shop",
            "type":"Services"
        }
    ],
    "sg:phone":"+1 915 774 9987",
    "sg:postcode":"79925",
    "sg:province":"TX",
    "sg:tags":[
        "repairing",
        "aids",
        "hearing",
        "audiologist"
    ],
    "wof:name":"Sandia Hearing Aids Center",
    "wof:placetype":"venue"
},
  "geometry": {"coordinates":[-106.404928,31.783623],"type":"Point"}
}