{
  "type": "Feature",
  "properties": {
    "iso:country":"US",
    "sg:address":"2522 Rosebud Ct",
    "sg:city":"Carrollton",
    "sg:classifiers":[
        {
            "category":"Banks & Credit Unions",
            "subcategory":"Financial Services",
            "type":"Services"
        }
    ],
    "sg:phone":"+1 972 416 2807",
    "sg:postcode":"75006",
    "sg:province":"TX",
    "sg:tags":[
        "investor"
    ],
    "wof:name":"Mayfield Investments",
    "wof:placetype":"venue"
},
  "geometry": {"coordinates":[-96.868424,32.972522],"type":"Point"}
}