{
  "type": "Feature",
  "properties": {
    "iso:country":"US",
    "sg:address":"655 N Park Blvd",
    "sg:city":"Grapevine",
    "sg:classifiers":[
        {
            "category":"Real Estate",
            "subcategory":"Real Estate Operator",
            "type":"Services"
        }
    ],
    "sg:phone":"+1 817 481 4308",
    "sg:postcode":"76051",
    "sg:province":"TX",
    "sg:tags":[
        "building",
        "apartment"
    ],
    "wof:name":"Woodlake Apartments LTD",
    "wof:placetype":"venue"
},
  "geometry": {"coordinates":[-97.099446,32.946901],"type":"Point"}
}