{
  "type": "Feature",
  "properties": {
    "iso:country":"US",
    "sg:address":"115 S Wild Basin Rd",
    "sg:city":"Austin",
    "sg:classifiers":[
        {
            "category":"Communications",
            "type":"Services"
        }
    ],
    "sg:phone":"+1 512 402 5287",
    "sg:postcode":"78746",
    "sg:province":"TX",
    "sg:tags":[
        "web",
        "design"
    ],
    "sg:website":"www.iflexion.com/",
    "wof:name":"Iflexion",
    "wof:placetype":"venue"
},
  "geometry": {"coordinates":[-97.827614,30.304505],"type":"Point"}
}