{
  "type": "Feature",
  "properties": {
    "iso:country":"US",
    "sg:address":"4706 Ave H",
    "sg:city":"Rosenberg",
    "sg:classifiers":[
        {
            "category":"Restaurant",
            "type":"Food & Drink"
        }
    ],
    "sg:phone":"+1 832 595 8548",
    "sg:postcode":"77471",
    "sg:province":"TX",
    "wof:name":"Taqueria Azteca",
    "wof:placetype":"venue"
},
  "geometry": {"coordinates":[-95.78044300000001,29.566948],"type":"Point"}
}