{
  "type": "Feature",
  "properties": {
    "iso:country":"US",
    "sg:address":"4100 Greenbriar St",
    "sg:city":"Houston",
    "sg:classifiers":[
        {
            "category":"Building & Trades",
            "subcategory":"Construction",
            "type":"Services"
        }
    ],
    "sg:phone":"+1 713 825 0552",
    "sg:postcode":"77098",
    "sg:province":"TX",
    "sg:tags":[
        "commercial"
    ],
    "wof:name":"All American Brothers Co LLC",
    "wof:placetype":"venue"
},
  "geometry": {"coordinates":[-95.41290499999999,29.72981],"type":"Point"}
}