{
  "type": "Feature",
  "properties": {
    "iso:country":"US",
    "sg:address":"3511 S Home Pl",
    "sg:city":"Sugar Land",
    "sg:classifiers":[
        {
            "category":"Professional",
            "type":"Services"
        }
    ],
    "sg:phone":"+1 713 410 8895",
    "sg:postcode":"77479",
    "sg:province":"TX",
    "wof:name":"Cleveland White",
    "wof:placetype":"venue"
},
  "geometry": {"coordinates":[-95.592223,29.579756],"type":"Point"}
}