{
  "type": "Feature",
  "properties": {
    "iso:country":"US",
    "sg:address":"1910 Kensington Dr",
    "sg:city":"Carrollton",
    "sg:classifiers":[
        {
            "category":"Professional",
            "subcategory":"Management & Consulting",
            "type":"Services"
        }
    ],
    "sg:phone":"+1 972 492 1753",
    "sg:postcode":"75007",
    "sg:province":"TX",
    "sg:tags":[
        "consultant",
        "radio"
    ],
    "wof:name":"Casey Cal Radio Program Conslt",
    "wof:placetype":"venue"
},
  "geometry": {"coordinates":[-96.88695,33.014718],"type":"Point"}
}