{
  "type": "Feature",
  "properties": {
    "iso:country":"US",
    "sg:address":"923 W 42nd St",
    "sg:city":"Houston",
    "sg:classifiers":[
        {
            "category":"Communications",
            "subcategory":"Film & Video Production",
            "type":"Services"
        }
    ],
    "sg:phone":"+1 713 686 5743",
    "sg:postcode":"77018",
    "sg:province":"TX",
    "sg:tags":[
        "motion"
    ],
    "wof:name":"Innovision Productions",
    "wof:placetype":"venue"
},
  "geometry": {"coordinates":[-95.423672,29.825969],"type":"Point"}
}