{
  "type": "Feature",
  "properties": {
    "iso:country":"US",
    "sg:address":"3713 Pabst Rd",
    "sg:city":"Dickinson",
    "sg:classifiers":[
        {
            "category":"Building & Trades",
            "subcategory":"Pest Control",
            "type":"Services"
        }
    ],
    "sg:phone":"+1 281 337 0813",
    "sg:postcode":"77539",
    "sg:province":"TX",
    "wof:name":"D & B Pest Control Inc",
    "wof:placetype":"venue"
},
  "geometry": {"coordinates":[-95.082607,29.445531],"type":"Point"}
}