{
  "type": "Feature",
  "properties": {
    "iso:country":"US",
    "sg:address":"3902 Anton Dr",
    "sg:city":"San Antonio",
    "sg:classifiers":[
        {
            "category":"Building & Trades",
            "subcategory":"Pest Control",
            "type":"Services"
        }
    ],
    "sg:phone":"+1 210 359 6978",
    "sg:postcode":"78223",
    "sg:province":"TX",
    "wof:name":"Santone Pest Control",
    "wof:placetype":"venue"
},
  "geometry": {"coordinates":[-98.42031299999999,29.363802],"type":"Point"}
}