{
  "type": "Feature",
  "properties": {
    "iso:country":"US",
    "sg:address":"270 Deer Creek Dr",
    "sg:city":"Boerne",
    "sg:classifiers":[
        {
            "category":"Building & Trades",
            "subcategory":"Construction",
            "type":"Services"
        }
    ],
    "sg:phone":"+1 830 249 2989",
    "sg:postcode":"78006",
    "sg:province":"TX",
    "sg:tags":[
        "system",
        "contractor",
        "air conditioning"
    ],
    "wof:name":"Mike Finch Air Conditioning An",
    "wof:placetype":"venue"
},
  "geometry": {"coordinates":[-98.707943,29.800947],"type":"Point"}
}