{
  "type": "Feature",
  "properties": {
    "iso:country":"US",
    "sg:address":"10940 FM 1484",
    "sg:city":"Conroe",
    "sg:classifiers":[
        {
            "category":"Freight",
            "type":"Transportation"
        }
    ],
    "sg:phone":"+1 936 264 2225",
    "sg:postcode":"77303",
    "sg:province":"TX",
    "sg:tags":[
        "special"
    ],
    "wof:name":"Airport Road Mini Storage",
    "wof:placetype":"venue"
},
  "geometry": {"coordinates":[-95.404652,30.390018],"type":"Point"}
}