{
  "type": "Feature",
  "properties": {
    "iso:country":"US",
    "sg:address":"600 Pippin Ln",
    "sg:city":"Kingsville",
    "sg:classifiers":[
        {
            "category":"Farming",
            "subcategory":"Livestock Farm",
            "type":"Manufacturing & Wholesale Goods"
        }
    ],
    "sg:phone":"+1 361 592 6850",
    "sg:postcode":"78363",
    "sg:province":"TX",
    "sg:tags":[
        "beef",
        "feedlot",
        "cattle"
    ],
    "wof:name":"W Coleman",
    "wof:placetype":"venue"
},
  "geometry": {"coordinates":[-97.86062200000001,27.482749],"type":"Point"}
}