{
  "type": "Feature",
  "properties": {
    "iso:country":"US",
    "sg:address":"119 Worth St",
    "sg:city":"Henderson",
    "sg:classifiers":[
        {
            "category":"Personal",
            "subcategory":"Beauty Salon",
            "type":"Services"
        }
    ],
    "sg:phone":"+1 409 787 1999",
    "sg:postcode":"75654",
    "sg:province":"TX",
    "wof:name":"Tips & Tans Salon",
    "wof:placetype":"venue"
},
  "geometry": {"coordinates":[-94.803453,32.13625],"type":"Point"}
}