{
  "type": "Feature",
  "properties": {
    "iso:country":"US",
    "sg:address":"1601 Osprey Dr",
    "sg:city":"De Soto",
    "sg:classifiers":[
        {
            "category":"Local Transit",
            "type":"Transportation"
        }
    ],
    "sg:phone":"+1 972 224 2693",
    "sg:postcode":"75115",
    "sg:province":"TX",
    "sg:tags":[
        "passenger"
    ],
    "wof:name":"Boyd Group",
    "wof:placetype":"venue"
},
  "geometry": {"coordinates":[-96.84966,32.622633],"type":"Point"}
}