{
  "type": "Feature",
  "properties": {
    "iso:country":"US",
    "sg:address":"1200 Blalock #213",
    "sg:city":"Houston",
    "sg:classifiers":[
        {
            "category":"Building & Trades",
            "subcategory":"Construction",
            "type":"Services"
        }
    ],
    "sg:phone":"+1 713 722 0511",
    "sg:postcode":"77055",
    "sg:province":"TX",
    "sg:tags":[
        "interior",
        "design"
    ],
    "sg:website":"www.contourinteriordesign.com",
    "wof:name":"Contour Interior Design",
    "wof:placetype":"venue"
},
  "geometry": {"coordinates":[-95.521013,29.789452],"type":"Point"}
}