{
  "type": "Feature",
  "properties": {
    "iso:country":"US",
    "sg:address":"1010 S Calaveras St",
    "sg:city":"San Antonio",
    "sg:classifiers":[
        {
            "category":"Building & Trades",
            "subcategory":"Landscaping Services",
            "type":"Services"
        }
    ],
    "sg:phone":"+1 210 367 2644",
    "sg:postcode":"78207",
    "sg:province":"TX",
    "sg:tags":[
        "tree"
    ],
    "wof:name":"E Z Tree & Lawn Svc",
    "wof:placetype":"venue"
},
  "geometry": {"coordinates":[-98.52584,29.41823],"type":"Point"}
}