{
  "type": "Feature",
  "properties": {
    "iso:country":"US",
    "sg:address":"253 Candlelight Cove",
    "sg:city":"Coppell",
    "sg:classifiers":[
        {
            "category":"Restaurant",
            "type":"Food & Drink"
        }
    ],
    "sg:phone":"+1 972 304 8613",
    "sg:postcode":"75019",
    "sg:province":"TX",
    "sg:tags":[
        "eating"
    ],
    "wof:name":"Dairy Queen",
    "wof:placetype":"venue"
},
  "geometry": {"coordinates":[-96.98772700000001,32.973063],"type":"Point"}
}