{
  "type": "Feature",
  "properties": {
    "iso:country":"US",
    "sg:address":"6805 N Capital of Texas Hwy",
    "sg:city":"Austin",
    "sg:classifiers":[
        {
            "category":"Restaurant",
            "type":"Food & Drink"
        }
    ],
    "sg:phone":"+1 512 338 8901",
    "sg:postcode":"78731",
    "sg:province":"TX",
    "sg:tags":[
        "delicatessen"
    ],
    "wof:name":"Deli 360",
    "wof:placetype":"venue"
},
  "geometry": {"coordinates":[-97.789958,30.363916],"type":"Point"}
}