{
  "type": "Feature",
  "properties": {
    "iso:country":"US",
    "sg:address":"2006 Evergreen Dr",
    "sg:city":"Houston",
    "sg:classifiers":[
        {
            "category":"Personal",
            "subcategory":"Barber",
            "type":"Services"
        }
    ],
    "sg:phone":"+1 713 924 4914",
    "sg:postcode":"77087",
    "sg:province":"TX",
    "wof:name":"Alita's Guerrero",
    "wof:placetype":"venue"
},
  "geometry": {"coordinates":[-95.290257,29.708563],"type":"Point"}
}