{
  "type": "Feature",
  "properties": {
    "iso:country":"US",
    "sg:address":"404 W Liberty Ave",
    "sg:city":"Round Rock",
    "sg:classifiers":[
        {
            "category":"Restaurant",
            "type":"Food & Drink"
        }
    ],
    "sg:phone":"+1 512 246 1500",
    "sg:postcode":"78664",
    "sg:province":"TX",
    "sg:tags":[
        "fast"
    ],
    "wof:name":"G G W Inc",
    "wof:placetype":"venue"
},
  "geometry": {"coordinates":[-97.682789,30.508542],"type":"Point"}
}