{
  "type": "Feature",
  "properties": {
    "iso:country":"US",
    "sg:address":"1112 N Fielder Rd",
    "sg:city":"Arlington",
    "sg:classifiers":[
        {
            "category":"Cinema",
            "subcategory":"Movie Rental",
            "type":"Entertainment"
        }
    ],
    "sg:phone":"+1 817 548 0321",
    "sg:postcode":"76012",
    "sg:province":"TX",
    "sg:tags":[
        "leasing",
        "video",
        "disc",
        "tape"
    ],
    "sg:website":"www.blockbuster.com",
    "wof:name":"Blockbuster Video",
    "wof:placetype":"venue"
},
  "geometry": {"coordinates":[-97.131761,32.753209],"type":"Point"}
}