{
  "type": "Feature",
  "properties": {
    "iso:country":"US",
    "sg:address":"209 Pine Hill Dr",
    "sg:city":"Conroe",
    "sg:classifiers":[
        {
            "category":"Banks & Credit Unions",
            "subcategory":"Investment Brokerage",
            "type":"Services"
        }
    ],
    "sg:phone":"+1 936 597 8766",
    "sg:postcode":"77301",
    "sg:province":"TX",
    "sg:tags":[
        "security"
    ],
    "wof:name":"Edward Jones 27264",
    "wof:placetype":"venue"
},
  "geometry": {"coordinates":[-95.43222,30.311116],"type":"Point"}
}