{
  "type": "Feature",
  "properties": {
    "iso:country":"US",
    "sg:address":"22 SE 6th Ave",
    "sg:city":"Perryton",
    "sg:classifiers":[
        {
            "category":"Professional",
            "type":"Services"
        }
    ],
    "sg:phone":"+1 806 435 5154",
    "sg:postcode":"79070",
    "sg:province":"TX",
    "wof:name":"Panhandle Community Svc",
    "wof:placetype":"venue"
},
  "geometry": {"coordinates":[-100.80244,36.394271],"type":"Point"}
}