{
  "type": "Feature",
  "properties": {
    "iso:country":"US",
    "sg:address":"1325 Belvidere St",
    "sg:city":"El Paso",
    "sg:classifiers":[
        {
            "category":"Manufacturing",
            "subcategory":"Pottery",
            "type":"Manufacturing & Wholesale Goods"
        }
    ],
    "sg:phone":"+1 915 587 0924",
    "sg:postcode":"79912",
    "sg:province":"TX",
    "sg:tags":[
        "product",
        "mfg"
    ],
    "wof:name":"El Torreon Corporation",
    "wof:placetype":"venue"
},
  "geometry": {"coordinates":[-106.53224299999999,31.854228],"type":"Point"}
}