{
  "type": "Feature",
  "properties": {
    "iso:country":"US",
    "sg:address":"4845 Keller Springs Rd",
    "sg:city":"Addison",
    "sg:classifiers":[
        {
            "category":"Wholesale",
            "subcategory":"Machinery & Supplies",
            "type":"Manufacturing & Wholesale Goods"
        }
    ],
    "sg:phone":"+1 972 732 0057",
    "sg:postcode":"75001",
    "sg:province":"TX",
    "sg:tags":[
        "food",
        "equipment",
        "processing"
    ],
    "sg:website":"http://www.munn-mktg.com",
    "wof:name":"Munn Marketing Group",
    "wof:placetype":"venue"
},
  "geometry": {"coordinates":[-96.829044,32.968658],"type":"Point"}
}