{
  "type": "Feature",
  "properties": {
    "iso:country":"US",
    "sg:address":"11011 Indian Trl",
    "sg:city":"Dallas",
    "sg:classifiers":[
        {
            "category":"Freight",
            "type":"Transportation"
        }
    ],
    "sg:phone":"+1 972 243 3621",
    "sg:postcode":"75229",
    "sg:province":"TX",
    "sg:tags":[
        "commercial",
        "storage",
        "special"
    ],
    "wof:name":"Any Fill Self Storage",
    "wof:placetype":"venue"
},
  "geometry": {"coordinates":[-96.88370500000001,32.896529],"type":"Point"}
}