{
  "type": "Feature",
  "properties": {
    "iso:country":"US",
    "sg:address":"401 Hoover Dr",
    "sg:city":"Lewisville",
    "sg:classifiers":[
        {
            "category":"Professional",
            "subcategory":"Computer Services",
            "type":"Services"
        }
    ],
    "sg:phone":"+1 972 221 0317",
    "sg:postcode":"75067",
    "sg:province":"TX",
    "sg:tags":[
        "programing",
        "custom"
    ],
    "wof:name":"Alphanet Computer",
    "wof:placetype":"venue"
},
  "geometry": {"coordinates":[-96.99941,33.022293],"type":"Point"}
}