{
  "type": "Feature",
  "properties": {
    "iso:country":"US",
    "sg:address":"1508 W Mayfield Rd",
    "sg:city":"Arlington",
    "sg:classifiers":[
        {
            "category":"Food & Beverages",
            "subcategory":"Groceries & Convenience Stores",
            "type":"Retail Goods"
        }
    ],
    "sg:phone":"+1 817 465 1438",
    "sg:postcode":"76015",
    "sg:province":"TX",
    "sg:tags":[
        "station",
        "gas"
    ],
    "wof:name":"E-Z Mart Stores Inc",
    "wof:placetype":"venue"
},
  "geometry": {"coordinates":[-97.131315,32.692021],"type":"Point"}
}