{
  "type": "Feature",
  "properties": {
    "iso:country":"US",
    "sg:address":"17750 FM 529",
    "sg:city":"Houston",
    "sg:classifiers":[
        {
            "category":"Retail",
            "subcategory":"Auto Repair",
            "type":"Services"
        }
    ],
    "sg:phone":"+1 281 856 7864",
    "sg:postcode":"77095",
    "sg:province":"TX",
    "sg:tags":[
        "general"
    ],
    "wof:name":"Goodyear Automotive",
    "wof:placetype":"venue"
},
  "geometry": {"coordinates":[-95.67861000000001,29.879041],"type":"Point"}
}