{
  "type": "Feature",
  "properties": {
    "iso:country":"US",
    "sg:address":"1431 Commerce Dr",
    "sg:city":"Denison",
    "sg:classifiers":[
        {
            "category":"Home & Garden",
            "subcategory":"Household Appliances",
            "type":"Retail Goods"
        }
    ],
    "sg:phone":"+1 903 463 3261",
    "sg:postcode":"75020",
    "sg:province":"TX",
    "sg:tags":[
        "cleaners",
        "vacuum"
    ],
    "wof:name":"Vacuum Center",
    "wof:placetype":"venue"
},
  "geometry": {"coordinates":[-96.55761699999999,33.782059],"type":"Point"}
}