{
  "type": "Feature",
  "properties": {
    "iso:country":"US",
    "sg:address":"4801 S Austin St",
    "sg:city":"Amarillo",
    "sg:classifiers":[
        {
            "category":"Organizations",
            "subcategory":"Religious Organization",
            "type":"Services"
        }
    ],
    "sg:phone":"+1 806 358 7095",
    "sg:postcode":"79110",
    "sg:province":"TX",
    "sg:tags":[
        "methodist",
        "church"
    ],
    "wof:name":"Kingswood Untd Methdst Church",
    "wof:placetype":"venue"
},
  "geometry": {"coordinates":[-101.86376199999999,35.154613],"type":"Point"}
}