{
  "type": "Feature",
  "properties": {
    "iso:country":"US",
    "sg:address":"314 Helen Dr",
    "sg:city":"Deer Park",
    "sg:classifiers":[
        {
            "category":"Professional",
            "subcategory":"Computer Services",
            "type":"Services"
        }
    ],
    "sg:phone":"+1 281 479 2807",
    "sg:postcode":"77536",
    "sg:province":"TX",
    "wof:name":"Elizabeth's Computer Svc",
    "wof:placetype":"venue"
},
  "geometry": {"coordinates":[-95.119084,29.699359],"type":"Point"}
}