{
  "type": "Feature",
  "properties": {
    "iso:country":"US",
    "sg:address":"18671 State Highway 95",
    "sg:city":"Holland",
    "sg:classifiers":[
        {
            "category":"Building & Trades",
            "subcategory":"Landscaping Services",
            "type":"Services"
        }
    ],
    "sg:phone":"+1 254 982 4472",
    "sg:postcode":"76534",
    "sg:province":"TX",
    "sg:tags":[
        "landscape",
        "contractor"
    ],
    "wof:name":"Edwin Massar",
    "wof:placetype":"venue"
},
  "geometry": {"coordinates":[-97.365773,30.913833],"type":"Point"}
}