{
  "type": "Feature",
  "properties": {
    "iso:country":"US",
    "sg:address":"930 W Jefferson Blvd",
    "sg:city":"Dallas",
    "sg:classifiers":[
        {
            "category":"Shopping",
            "subcategory":"Books",
            "type":"Retail Goods"
        }
    ],
    "sg:phone":"+1 214 942 3474",
    "sg:postcode":"75208",
    "sg:province":"TX",
    "sg:tags":[
        "bookstore"
    ],
    "wof:name":"Libreria Parroquial",
    "wof:placetype":"venue"
},
  "geometry": {"coordinates":[-96.83910400000001,32.743198],"type":"Point"}
}