{
  "type": "Feature",
  "properties": {
    "iso:country":"US",
    "sg:address":"4021 Wood River Dr",
    "sg:city":"Corpus Christi",
    "sg:classifiers":[
        {
            "category":"Retail",
            "subcategory":"Repair Shop",
            "type":"Services"
        }
    ],
    "sg:phone":"+1 361 241 2973",
    "sg:postcode":"78410",
    "sg:province":"TX",
    "sg:tags":[
        "refrigeration"
    ],
    "wof:name":"Arktik Air",
    "wof:placetype":"venue"
},
  "geometry": {"coordinates":[-97.65979799999999,27.858748],"type":"Point"}
}