{
  "type": "Feature",
  "properties": {
    "iso:country":"US",
    "sg:address":"4424 Titanic Ave",
    "sg:city":"El Paso",
    "sg:classifiers":[
        {
            "category":"Retail",
            "subcategory":"Veterinary Services",
            "type":"Services"
        }
    ],
    "sg:phone":"+1 915 755 7647",
    "sg:postcode":"79904",
    "sg:province":"TX",
    "sg:tags":[
        "veterinarian"
    ],
    "wof:name":"Skyline Veterinary Hospital",
    "wof:placetype":"venue"
},
  "geometry": {"coordinates":[-106.43373,31.853361],"type":"Point"}
}