{
  "type": "Feature",
  "properties": {
    "iso:country":"US",
    "sg:address":"1213 Chatsworth Dr",
    "sg:city":"Colleyville",
    "sg:classifiers":[
        {
            "category":"Professional",
            "subcategory":"Management & Consulting",
            "type":"Services"
        }
    ],
    "sg:phone":"+1 817 577 2315",
    "sg:postcode":"76034",
    "sg:province":"TX",
    "sg:tags":[
        "organization",
        "membership"
    ],
    "wof:name":"Whatever It Takes",
    "wof:placetype":"venue"
},
  "geometry": {"coordinates":[-97.148331,32.877996],"type":"Point"}
}