{
  "type": "Feature",
  "properties": {
    "iso:country":"US",
    "sg:address":"705 8th St",
    "sg:city":"Wichita Falls",
    "sg:classifiers":[
        {
            "category":"Shopping",
            "subcategory":"Computers & Home Electronics",
            "type":"Retail Goods"
        },
        {
            "category":"Professional",
            "subcategory":"Computer Services",
            "type":"Services"
        }
    ],
    "sg:phone":"+1 940 767 6387",
    "sg:postcode":"76301",
    "sg:province":"TX",
    "sg:tags":[
        "equipment",
        "networking",
        "dealer"
    ],
    "sg:website":"www.netess.net",
    "wof:name":"Netessentials Inc",
    "wof:placetype":"venue"
},
  "geometry": {"coordinates":[-98.492001,33.911873],"type":"Point"}
}