{
  "type": "Feature",
  "properties": {
    "iso:country":"US",
    "sg:address":"11763 Timbercrest Dr",
    "sg:city":"Tomball",
    "sg:classifiers":[
        {
            "category":"Building & Trades",
            "subcategory":"Construction",
            "type":"Services"
        }
    ],
    "sg:phone":"+1 281 635 7495",
    "sg:postcode":"77375",
    "sg:province":"TX",
    "sg:tags":[
        "contractor",
        "mechanical"
    ],
    "wof:name":"Lightning Mechanical",
    "wof:placetype":"venue"
},
  "geometry": {"coordinates":[-95.59782300000001,30.131924],"type":"Point"}
}