{
  "type": "Feature",
  "properties": {
    "iso:country":"US",
    "sg:address":"3100 Broadway St",
    "sg:city":"Houston",
    "sg:classifiers":[
        {
            "category":"Health Services",
            "subcategory":"Doctor",
            "type":"Services"
        }
    ],
    "sg:phone":"+1 713 634 0333",
    "sg:postcode":"77017",
    "sg:province":"TX",
    "sg:tags":[
        "clinic"
    ],
    "wof:name":"Clinica Familiar",
    "wof:placetype":"venue"
},
  "geometry": {"coordinates":[-95.277715,29.694637],"type":"Point"}
}