{
  "type": "Feature",
  "properties": {
    "iso:country":"US",
    "sg:address":"1524 S Interstate 35 Ste 209",
    "sg:city":"Austin",
    "sg:classifiers":[
        {
            "category":"Professional",
            "subcategory":"Lawyer & Legal Services",
            "type":"Services"
        }
    ],
    "sg:phone":"+1 512 637 0800",
    "sg:postcode":"78704",
    "sg:province":"TX",
    "wof:name":"Scheinberg & Griner LLP",
    "wof:placetype":"venue"
},
  "geometry": {"coordinates":[-97.73661300000001,30.242429],"type":"Point"}
}