{
  "type": "Feature",
  "properties": {
    "iso:country":"US",
    "sg:address":"12717 N Lamar Blvd",
    "sg:city":"Austin",
    "sg:classifiers":[
        {
            "category":"Professional",
            "subcategory":"Business Services",
            "type":"Services"
        }
    ],
    "sg:phone":"+1 512 339 2949",
    "sg:postcode":"78753",
    "sg:province":"TX",
    "sg:tags":[
        "conference",
        "center"
    ],
    "wof:name":"Five Oaks",
    "wof:placetype":"venue"
},
  "geometry": {"coordinates":[-97.674251,30.420052],"type":"Point"}
}