{
  "type": "Feature",
  "properties": {
    "iso:country":"US",
    "sg:address":"2618 Sara Ridge Ln",
    "sg:city":"Katy",
    "sg:classifiers":[
        {
            "category":"Government",
            "subcategory":"Office",
            "type":"Public Place"
        }
    ],
    "sg:phone":"+1 281 398 1616",
    "sg:postcode":"77450",
    "sg:province":"TX",
    "sg:tags":[
        "parish",
        "government-county"
    ],
    "wof:name":"The Ashlyn Horry Foundation Incorporated",
    "wof:placetype":"venue"
},
  "geometry": {"coordinates":[-95.728432,29.74353],"type":"Point"}
}