{
  "type": "Feature",
  "properties": {
    "iso:country":"US",
    "sg:address":"1532 Edison St",
    "sg:city":"Dallas",
    "sg:classifiers":[
        {
            "category":"Professional",
            "type":"Services"
        }
    ],
    "sg:phone":"+1 214 752 0282",
    "sg:postcode":"75207",
    "sg:province":"TX",
    "sg:tags":[
        "establishment"
    ],
    "wof:name":"Sullivanbarnes Associates Inc",
    "wof:placetype":"venue"
},
  "geometry": {"coordinates":[-96.816703,32.793809],"type":"Point"}
}