{
  "type": "Feature",
  "properties": {
    "iso:country":"US",
    "sg:address":"7925 Luling Ln",
    "sg:city":"Austin",
    "sg:classifiers":[
        {
            "category":"Professional",
            "subcategory":"Business Services",
            "type":"Services"
        }
    ],
    "sg:phone":"+1 512 249 9817",
    "sg:postcode":"78729",
    "sg:province":"TX",
    "wof:name":"Family Advocare Business",
    "wof:placetype":"venue"
},
  "geometry": {"coordinates":[-97.75870399999999,30.455237],"type":"Point"}
}