{
  "type": "Feature",
  "properties": {
    "iso:country":"US",
    "sg:address":"7710 S Westmoreland Rd",
    "sg:city":"Dallas",
    "sg:classifiers":[
        {
            "category":"Organizations",
            "subcategory":"Religious Organization",
            "type":"Services"
        }
    ],
    "sg:phone":"+1 972 298 6565",
    "sg:postcode":"75237",
    "sg:province":"TX",
    "wof:name":"Rickie G Rush Inspirationals",
    "wof:placetype":"venue"
},
  "geometry": {"coordinates":[-96.88722,32.650638],"type":"Point"}
}