{
  "type": "Feature",
  "properties": {
    "iso:country":"US",
    "sg:address":"8601 Dulcet Dr",
    "sg:city":"Austin",
    "sg:phone":"+1 713 515 0136",
    "sg:postcode":"78745",
    "sg:province":"TX",
    "wof:name":"zoo's aquarium services",
    "wof:placetype":"venue"
},
  "geometry": {"coordinates":[-97.81659999999999,30.18749],"type":"Point"}
}