{
  "type": "Feature",
  "properties": {
    "iso:country":"US",
    "sg:address":"5801 Preston Oaks Rd",
    "sg:city":"Dallas",
    "sg:classifiers":[
        {
            "category":"Freight",
            "type":"Transportation"
        }
    ],
    "sg:phone":"+1 972 774 0854",
    "sg:postcode":"75254",
    "sg:province":"TX",
    "sg:tags":[
        "delivery"
    ],
    "wof:name":"Store To Door",
    "wof:placetype":"venue"
},
  "geometry": {"coordinates":[-96.805998,32.942116],"type":"Point"}
}