{
  "type": "Feature",
  "properties": {
    "iso:country":"US",
    "sg:address":"2304 Hamilton Dr",
    "sg:city":"Argyle",
    "sg:classifiers":[
        {
            "category":"Freight",
            "type":"Transportation"
        }
    ],
    "sg:phone":"+1 940 382 4128",
    "sg:postcode":"76226",
    "sg:province":"TX",
    "sg:tags":[
        "hardware"
    ],
    "wof:name":"Baker Enterprises",
    "wof:placetype":"venue"
},
  "geometry": {"coordinates":[-97.16237,33.15213],"type":"Point"}
}