{
  "type": "Feature",
  "properties": {
    "iso:country":"US",
    "sg:address":"3939 Belt Line Rd",
    "sg:city":"Addison",
    "sg:classifiers":[
        {
            "category":"Banks & Credit Unions",
            "subcategory":"Investment Brokerage",
            "type":"Services"
        }
    ],
    "sg:phone":"+1 972 277 8555",
    "sg:postcode":"75001",
    "sg:province":"TX",
    "sg:tags":[
        "advisory",
        "financial"
    ],
    "wof:name":"Shelman Securities",
    "wof:placetype":"venue"
},
  "geometry": {"coordinates":[-96.849071,32.953227],"type":"Point"}
}