{
  "type": "Feature",
  "properties": {
    "iso:country":"US",
    "sg:address":"121 Westmeadow Dr",
    "sg:city":"Cleburne",
    "sg:classifiers":[
        {
            "category":"Restaurant",
            "type":"Food & Drink"
        }
    ],
    "sg:phone":"+1 817 645 4141",
    "sg:postcode":"76033",
    "sg:province":"TX",
    "sg:tags":[
        "shop",
        "coffee"
    ],
    "wof:name":"Java Lounge",
    "wof:placetype":"venue"
},
  "geometry": {"coordinates":[-97.418398,32.338144],"type":"Point"}
}