{
  "type": "Feature",
  "properties": {
    "iso:country":"US",
    "sg:address":"2705 Cedar Springs Ct",
    "sg:city":"Bedford",
    "sg:classifiers":[
        {
            "category":"Retail",
            "subcategory":"Repair Shop",
            "type":"Services"
        },
        {
            "category":"Home & Garden",
            "subcategory":"Furniture",
            "type":"Retail Goods"
        }
    ],
    "sg:phone":"+1 817 354 2286",
    "sg:postcode":"76021",
    "sg:province":"TX",
    "sg:tags":[
        "refinishing"
    ],
    "wof:name":"Furniture Medic Inc",
    "wof:placetype":"venue"
},
  "geometry": {"coordinates":[-97.12097199999999,32.851536],"type":"Point"}
}