{
  "type": "Feature",
  "properties": {
    "iso:country":"US",
    "sg:address":"5930 Southmund St",
    "sg:city":"Houston",
    "sg:classifiers":[
        {
            "category":"Professional",
            "subcategory":"Management & Consulting",
            "type":"Services"
        }
    ],
    "sg:phone":"+1 713 847 8671",
    "sg:postcode":"77033",
    "sg:province":"TX",
    "wof:name":"Newton Management & Cnstr",
    "wof:placetype":"venue"
},
  "geometry": {"coordinates":[-95.32974900000001,29.683176],"type":"Point"}
}