{
  "type": "Feature",
  "properties": {
    "iso:country":"US",
    "sg:address":"406 N Washington Ave",
    "sg:city":"Cleveland",
    "sg:classifiers":[
        {
            "category":"Professional",
            "subcategory":"Business Services",
            "type":"Services"
        }
    ],
    "sg:phone":"+1 281 593 3555",
    "sg:postcode":"77327",
    "sg:province":"TX",
    "wof:name":"Tri County M H M R",
    "wof:placetype":"venue"
},
  "geometry": {"coordinates":[-95.08778599999999,30.346432],"type":"Point"}
}