{
  "type": "Feature",
  "properties": {
    "iso:country":"US",
    "sg:address":"4518 State Hwy 6",
    "sg:city":"Sugar Land",
    "sg:classifiers":[
        {
            "category":"Real Estate",
            "subcategory":"Real Estate Agent",
            "type":"Services"
        }
    ],
    "sg:phone":"+1 281 242 6655",
    "sg:postcode":"77478",
    "sg:province":"TX",
    "wof:name":"Dreams Come True Realty",
    "wof:placetype":"venue"
},
  "geometry": {"coordinates":[-95.58554100000001,29.582341],"type":"Point"}
}