{
  "type": "Feature",
  "properties": {
    "iso:country":"US",
    "sg:address":"410 Jackson St",
    "sg:city":"Richmond",
    "sg:classifiers":[
        {
            "category":"Organizations",
            "subcategory":"Membership Organization",
            "type":"Services"
        }
    ],
    "sg:phone":"+1 281 239 9235",
    "sg:postcode":"77469",
    "sg:province":"TX",
    "wof:name":"Texas Independence Trail Reg",
    "wof:placetype":"venue"
},
  "geometry": {"coordinates":[-95.76152500000001,29.582162],"type":"Point"}
}