{
  "type": "Feature",
  "properties": {
    "iso:country":"US",
    "sg:address":"3783 Jardin St",
    "sg:city":"Houston",
    "sg:classifiers":[
        {
            "category":"Health Services",
            "subcategory":"Doctor",
            "type":"Services"
        }
    ],
    "sg:phone":"+1 713 665 7635",
    "sg:postcode":"77005",
    "sg:province":"TX",
    "wof:name":"Mihalo Robert M MD",
    "wof:placetype":"venue"
},
  "geometry": {"coordinates":[-95.43710299999999,29.7138],"type":"Point"}
}