{
  "type": "Feature",
  "properties": {
    "iso:country":"US",
    "sg:address":"101 W Main St",
    "sg:city":"Fredericksburg",
    "sg:classifiers":[
        {
            "category":"Government",
            "subcategory":"Office",
            "type":"Public Place"
        }
    ],
    "sg:phone":"+1 830 997 6521",
    "sg:postcode":"78624",
    "sg:province":"TX",
    "sg:tags":[
        "county",
        "taxation"
    ],
    "wof:name":"Gillespie County Treasurer Ofc",
    "wof:placetype":"venue"
},
  "geometry": {"coordinates":[-98.873127,30.275727],"type":"Point"}
}