{
  "type": "Feature",
  "properties": {
    "iso:country":"US",
    "sg:address":"9701 Manchester St",
    "sg:city":"Houston",
    "sg:classifiers":[
        {
            "category":"Building & Trades",
            "subcategory":"Construction",
            "type":"Services"
        }
    ],
    "sg:phone":"+1 713 926 9902",
    "sg:postcode":"77012",
    "sg:province":"TX",
    "sg:tags":[
        "contractor"
    ],
    "wof:name":"Triple S Industrial Corporation",
    "wof:placetype":"venue"
},
  "geometry": {"coordinates":[-95.25369999999999,29.7187],"type":"Point"}
}