{
  "type": "Feature",
  "properties": {
    "iso:country":"US",
    "sg:address":"1407 Ave H",
    "sg:city":"Bay City",
    "sg:classifiers":[
        {
            "category":"Professional",
            "type":"Services"
        }
    ],
    "sg:phone":"+1 979 244 9473",
    "sg:postcode":"77414",
    "sg:province":"TX",
    "sg:tags":[
        "establishment"
    ],
    "wof:name":"NHLI",
    "wof:placetype":"venue"
},
  "geometry": {"coordinates":[-95.96776,28.990294],"type":"Point"}
}