{
  "type": "Feature",
  "properties": {
    "iso:country":"US",
    "sg:address":"15608 Spring Hill Ln",
    "sg:city":"Pflugerville",
    "sg:classifiers":[
        {
            "category":"Utilities",
            "subcategory":"Electric",
            "type":"Services"
        }
    ],
    "sg:phone":"+1 512 251 4881",
    "sg:postcode":"78660",
    "sg:province":"TX",
    "sg:tags":[
        "company"
    ],
    "wof:name":"Angel Electric",
    "wof:placetype":"venue"
},
  "geometry": {"coordinates":[-97.65168199999999,30.444589],"type":"Point"}
}