{
  "type": "Feature",
  "properties": {
    "iso:country":"US",
    "sg:address":"609 Country Club Cir",
    "sg:city":"Athens",
    "sg:classifiers":[
        {
            "category":"Professional",
            "subcategory":"Business Services",
            "type":"Services"
        }
    ],
    "sg:phone":"+1 903 677 2777",
    "sg:postcode":"75751",
    "sg:province":"TX",
    "sg:tags":[
        "consultant",
        "coach"
    ],
    "wof:name":"Texas Power Consultants",
    "wof:placetype":"venue"
},
  "geometry": {"coordinates":[-95.86815,32.189568],"type":"Point"}
}