{
  "type": "Feature",
  "properties": {
    "iso:country":"US",
    "sg:address":"201 Foster Dr",
    "sg:city":"El Paso",
    "sg:classifiers":[
        {
            "category":"Shopping",
            "subcategory":"Florist",
            "type":"Retail Goods"
        }
    ],
    "sg:phone":"+1 915 859 4670",
    "sg:postcode":"79907",
    "sg:province":"TX",
    "wof:name":"Daisy Flowers",
    "wof:placetype":"venue"
},
  "geometry": {"coordinates":[-106.34502500000001,31.71538],"type":"Point"}
}