{
  "type": "Feature",
  "properties": {
    "iso:country":"US",
    "sg:address":"134 Devine St",
    "sg:city":"San Antonio",
    "sg:classifiers":[
        {
            "category":"Organizations",
            "subcategory":"Religious Organization",
            "type":"Services"
        }
    ],
    "sg:phone":"+1 210 226 4603",
    "sg:postcode":"78210",
    "sg:province":"TX",
    "wof:name":"Jehovahs Witnesses",
    "wof:placetype":"venue"
},
  "geometry": {"coordinates":[-98.486704,29.411744],"type":"Point"}
}