{
  "type": "Feature",
  "properties": {
    "iso:country":"US",
    "sg:address":"9409 Bradner Dr",
    "sg:city":"Austin",
    "sg:classifiers":[
        {
            "category":"Retail",
            "subcategory":"Animal Services",
            "type":"Services"
        }
    ],
    "sg:phone":"+1 512 282 7477",
    "sg:postcode":"78748",
    "sg:province":"TX",
    "wof:name":"A Dogs Eye View",
    "wof:placetype":"venue"
},
  "geometry": {"coordinates":[-97.838204,30.186631],"type":"Point"}
}