{
  "type": "Feature",
  "properties": {
    "iso:country":"US",
    "sg:address":"742 Hummingbird Cir",
    "sg:city":"Lewisville",
    "sg:classifiers":[
        {
            "category":"Building & Trades",
            "subcategory":"Cleaning & Sanitation",
            "type":"Services"
        }
    ],
    "sg:phone":"+1 469 948 0248",
    "sg:postcode":"75067",
    "sg:province":"TX",
    "sg:tags":[
        "maintenance"
    ],
    "wof:name":"Immaculate Window Cleaning",
    "wof:placetype":"venue"
},
  "geometry": {"coordinates":[-97.0064,33.026073],"type":"Point"}
}