{
  "type": "Feature",
  "properties": {
    "iso:country":"US",
    "sg:address":"1855 Cullen Blvd",
    "sg:city":"Pearland",
    "sg:classifiers":[
        {
            "category":"Building & Trades",
            "subcategory":"Construction",
            "type":"Services"
        }
    ],
    "sg:phone":"+1 832 736 9739",
    "sg:postcode":"77581",
    "sg:province":"TX",
    "sg:tags":[
        "insulation",
        "heat",
        "contractor"
    ],
    "wof:name":"Quality Insulation",
    "wof:placetype":"venue"
},
  "geometry": {"coordinates":[-95.35039500000001,29.561855],"type":"Point"}
}