{
  "type": "Feature",
  "properties": {
    "iso:country":"US",
    "sg:address":"2616 Louisiana St",
    "sg:city":"Houston",
    "sg:classifiers":[
        {
            "category":"Organizations",
            "subcategory":"Community Association",
            "type":"Services"
        }
    ],
    "sg:phone":"+1 713 528 1625",
    "sg:postcode":"77006",
    "sg:province":"TX",
    "sg:tags":[
        "fraternal"
    ],
    "sg:website":"www.kc803.org",
    "wof:name":"Knights Of Columbus",
    "wof:placetype":"venue"
},
  "geometry": {"coordinates":[-95.37720299999999,29.7464],"type":"Point"}
}