{
  "type": "Feature",
  "properties": {
    "iso:country":"US",
    "sg:address":"908 Curtiss Ave",
    "sg:city":"Schertz",
    "sg:classifiers":[
        {
            "category":"Utilities",
            "subcategory":"Electric",
            "type":"Services"
        }
    ],
    "sg:phone":"+1 210 658 7033",
    "sg:postcode":"78154",
    "sg:province":"TX",
    "sg:tags":[
        "company",
        "construction"
    ],
    "sg:website":"www.gvec.org",
    "wof:name":"Guadalupe Valley Electric Coop",
    "wof:placetype":"venue"
},
  "geometry": {"coordinates":[-98.263341,29.558567],"type":"Point"}
}