{
  "type": "Feature",
  "properties": {
    "iso:country":"US",
    "sg:address":"15907 Market St",
    "sg:city":"Channelview",
    "sg:classifiers":[
        {
            "category":"Food & Beverages",
            "subcategory":"Groceries & Convenience Stores",
            "type":"Retail Goods"
        }
    ],
    "sg:phone":"+1 281 452 3500",
    "sg:postcode":"77530",
    "sg:province":"TX",
    "wof:name":"Salzas Market",
    "wof:placetype":"venue"
},
  "geometry": {"coordinates":[-95.121774,29.77271],"type":"Point"}
}