{
  "type": "Feature",
  "properties": {
    "iso:country":"US",
    "sg:address":"26006 Oakridge Dr",
    "sg:city":"Spring",
    "sg:classifiers":[
        {
            "category":"Freight",
            "type":"Transportation"
        }
    ],
    "sg:phone":"+1 281 363 1114",
    "sg:postcode":"77380",
    "sg:province":"TX",
    "wof:name":"3e Transportation Inc",
    "wof:placetype":"venue"
},
  "geometry": {"coordinates":[-95.447784,30.138135],"type":"Point"}
}