{
  "type": "Feature",
  "properties": {
    "iso:country":"US",
    "sg:address":"5513 Community Center Dr",
    "sg:city":"Del Valle",
    "sg:classifiers":[
        {
            "category":"Real Estate",
            "subcategory":"Real Estate Agent",
            "type":"Services"
        }
    ],
    "sg:phone":"+1 512 247 2307",
    "sg:postcode":"78617",
    "sg:province":"TX",
    "sg:tags":[
        "appraiser"
    ],
    "wof:name":"Guardian Real Estate Svc",
    "wof:placetype":"venue"
},
  "geometry": {"coordinates":[-97.62925199999999,30.173655],"type":"Point"}
}