{
  "type": "Feature",
  "properties": {
    "iso:country":"US",
    "sg:address":"417 Tamara Dr",
    "sg:city":"Georgetown",
    "sg:classifiers":[
        {
            "category":"Professional",
            "type":"Services"
        }
    ],
    "sg:phone":"+1 512 869 7797",
    "sg:postcode":"78628",
    "sg:province":"TX",
    "wof:name":"Kinseys Home Accents",
    "wof:placetype":"venue"
},
  "geometry": {"coordinates":[-97.697022,30.610709],"type":"Point"}
}