{
  "type": "Feature",
  "properties": {
    "iso:country":"US",
    "sg:address":"612 W Adams Ave",
    "sg:city":"Temple",
    "sg:classifiers":[
        {
            "category":"Professional",
            "subcategory":"Employment Agencies",
            "type":"Services"
        }
    ],
    "sg:phone":"+1 254 771 2188",
    "sg:postcode":"76501",
    "sg:province":"TX",
    "sg:tags":[
        "opportunity",
        "temporary",
        "contractor"
    ],
    "sg:website":"http://www.laborfinders.com",
    "wof:name":"Labor Finders",
    "wof:placetype":"venue"
},
  "geometry": {"coordinates":[-97.346869,31.099325],"type":"Point"}
}