{
  "type": "Feature",
  "properties": {
    "iso:country":"US",
    "sg:address":"602 Houston St",
    "sg:city":"Sanger",
    "sg:classifiers":[
        {
            "category":"Building & Trades",
            "subcategory":"Construction",
            "type":"Services"
        }
    ],
    "sg:phone":"+1 940 458 5818",
    "sg:postcode":"76266",
    "sg:province":"TX",
    "sg:tags":[
        "contractor"
    ],
    "wof:name":"Lewis Drywall",
    "wof:placetype":"venue"
},
  "geometry": {"coordinates":[-97.175022,33.355811],"type":"Point"}
}