{
  "type": "Feature",
  "properties": {
    "iso:country":"US",
    "sg:address":"10202 E Miller Rd",
    "sg:city":"Dallas",
    "sg:phone":"+1 214 221 6840",
    "sg:postcode":"75238",
    "sg:province":"TX",
    "sg:tags":[
        "material",
        "fixture",
        "display"
    ],
    "sg:website":"www.tscexhibits.com",
    "wof:name":"TSC Exhibits",
    "wof:placetype":"venue"
},
  "geometry": {"coordinates":[-96.709165,32.894476],"type":"Point"}
}