{
  "type": "Feature",
  "properties": {
    "iso:country":"US",
    "sg:address":"8550 Fair Oaks Xing",
    "sg:city":"Dallas",
    "sg:classifiers":[
        {
            "category":"Restaurant",
            "type":"Food & Drink"
        }
    ],
    "sg:phone":"+1 214 349 3502",
    "sg:postcode":"75243",
    "sg:province":"TX",
    "sg:tags":[
        "eating"
    ],
    "wof:name":"Two Guys and A Lipstick",
    "wof:placetype":"venue"
},
  "geometry": {"coordinates":[-96.728268,32.895573],"type":"Point"}
}