{
  "type": "Feature",
  "properties": {
    "iso:country":"US",
    "sg:address":"16434 Havenpark Dr",
    "sg:city":"Houston",
    "sg:classifiers":[
        {
            "category":"Professional",
            "subcategory":"Computer Services",
            "type":"Services"
        }
    ],
    "sg:phone":"+1 281 488 6303",
    "sg:postcode":"77059",
    "sg:province":"TX",
    "sg:tags":[
        "programing",
        "custom"
    ],
    "wof:name":"Arj Software Services",
    "wof:placetype":"venue"
},
  "geometry": {"coordinates":[-95.105594,29.593287],"type":"Point"}
}