{
  "type": "Feature",
  "properties": {
    "iso:country":"US",
    "sg:address":"1209 Goodwin Dr",
    "sg:city":"Plano",
    "sg:classifiers":[
        {
            "category":"Food & Beverages",
            "subcategory":"Groceries & Convenience Stores",
            "type":"Retail Goods"
        }
    ],
    "sg:phone":"+1 972 881 4201",
    "sg:postcode":"75023",
    "sg:province":"TX",
    "sg:tags":[
        "wholesale",
        "sales"
    ],
    "wof:name":"Food Service Sales Management",
    "wof:placetype":"venue"
},
  "geometry": {"coordinates":[-96.715024,33.053809],"type":"Point"}
}