{
  "type": "Feature",
  "properties": {
    "iso:country":"US",
    "sg:address":"3448 Rankin St",
    "sg:city":"Dallas",
    "sg:classifiers":[
        {
            "category":"Professional",
            "subcategory":"Business Services",
            "type":"Services"
        }
    ],
    "sg:phone":"+1 214 360 0535",
    "sg:postcode":"75205",
    "sg:province":"TX",
    "wof:name":"Reid-Kugle Interiors",
    "wof:placetype":"venue"
},
  "geometry": {"coordinates":[-96.78963899999999,32.849439],"type":"Point"}
}