{
  "type": "Feature",
  "properties": {
    "iso:country":"US",
    "sg:address":"102 N Macarthur Blvd",
    "sg:city":"Irving",
    "sg:classifiers":[
        {
            "category":"Shopping",
            "type":"Retail Goods"
        }
    ],
    "sg:phone":"+1 972 254 3018",
    "sg:postcode":"75061",
    "sg:province":"TX",
    "sg:tags":[
        "merchandise"
    ],
    "wof:name":"Covenant Trophies",
    "wof:placetype":"venue"
},
  "geometry": {"coordinates":[-96.95972,32.815165],"type":"Point"}
}