{
  "type": "Feature",
  "properties": {
    "iso:country":"US",
    "sg:address":"301 N Ballard St",
    "sg:city":"Pampa",
    "sg:classifiers":[
        {
            "category":"Building & Trades",
            "subcategory":"Construction",
            "type":"Services"
        }
    ],
    "sg:phone":"+1 806 665 4243",
    "sg:postcode":"79065",
    "sg:province":"TX",
    "sg:tags":[
        "contractor"
    ],
    "wof:name":"A1 Roofing & Construction",
    "wof:placetype":"venue"
},
  "geometry": {"coordinates":[-100.962217,35.539164],"type":"Point"}
}