{
  "type": "Feature",
  "properties": {
    "iso:country":"US",
    "sg:address":"471 Upper Elgin River Rd",
    "sg:city":"Elgin",
    "sg:classifiers":[
        {
            "category":"Home & Garden",
            "subcategory":"Garden Supply",
            "type":"Retail Goods"
        }
    ],
    "sg:phone":"+1 512 281 0021",
    "sg:postcode":"78621",
    "sg:province":"TX",
    "sg:tags":[
        "landscaping",
        "equipment"
    ],
    "wof:name":"Mother Earth Cure-Water-Lok",
    "wof:placetype":"venue"
},
  "geometry": {"coordinates":[-97.399314,30.321964],"type":"Point"}
}