{
  "type": "Feature",
  "properties": {
    "iso:country":"US",
    "sg:address":"4545 Cambridge Rd",
    "sg:city":"Fort Worth",
    "sg:classifiers":[
        {
            "category":"Banks & Credit Unions",
            "subcategory":"Bank",
            "type":"Services"
        }
    ],
    "sg:phone":"+1 817 288 0106",
    "sg:postcode":"76155",
    "sg:province":"TX",
    "sg:tags":[
        "financing"
    ],
    "wof:name":"Patient Finance Plan",
    "wof:placetype":"venue"
},
  "geometry": {"coordinates":[-97.044121,32.830962],"type":"Point"}
}