{
  "type": "Feature",
  "properties": {
    "iso:country":"US",
    "sg:address":"5810 Hardy St",
    "sg:city":"Houston",
    "sg:classifiers":[
        {
            "category":"Building & Trades",
            "subcategory":"Construction",
            "type":"Services"
        }
    ],
    "sg:phone":"+1 713 692 0147",
    "sg:postcode":"77009",
    "sg:province":"TX",
    "sg:tags":[
        "hanging",
        "contractor"
    ],
    "wof:name":"Pro Marks Painting",
    "wof:placetype":"venue"
},
  "geometry": {"coordinates":[-95.35249399999999,29.812766],"type":"Point"}
}