{
  "type": "Feature",
  "properties": {
    "iso:country":"US",
    "sg:address":"2204 Gulf Ave",
    "sg:city":"Midland",
    "sg:classifiers":[
        {
            "category":"Shopping",
            "subcategory":"Gifts & Souvenirs",
            "type":"Retail Goods"
        }
    ],
    "sg:phone":"+1 432 686 7538",
    "sg:postcode":"79705",
    "sg:province":"TX",
    "sg:tags":[
        "shop"
    ],
    "wof:name":"Gifts To Go",
    "wof:placetype":"venue"
},
  "geometry": {"coordinates":[-102.105171,32.014009],"type":"Point"}
}