{
  "type": "Feature",
  "properties": {
    "iso:country":"US",
    "sg:address":"2518 Old Goliad Rd",
    "sg:city":"Goliad",
    "sg:classifiers":[
        {
            "category":"Retail",
            "subcategory":"Repair Shop",
            "type":"Services"
        }
    ],
    "sg:phone":"+1 361 645 3350",
    "sg:postcode":"77963",
    "sg:province":"TX",
    "sg:tags":[
        "compressor"
    ],
    "wof:name":"Sam Johnson Svc Co",
    "wof:placetype":"venue"
},
  "geometry": {"coordinates":[-97.400324,28.716074],"type":"Point"}
}