{
  "type": "Feature",
  "properties": {
    "iso:country":"US",
    "sg:address":"6727 Theall Rd",
    "sg:city":"Houston",
    "sg:classifiers":[
        {
            "category":"Wholesale",
            "subcategory":"Machinery & Supplies",
            "type":"Manufacturing & Wholesale Goods"
        },
        {
            "category":"Wholesale",
            "subcategory":"Electrical",
            "type":"Manufacturing & Wholesale Goods"
        }
    ],
    "sg:phone":"+1 281 895 8189",
    "sg:postcode":"77066",
    "sg:province":"TX",
    "sg:tags":[
        "sales",
        "meter",
        "representative"
    ],
    "wof:name":"Betsco",
    "wof:placetype":"venue"
},
  "geometry": {"coordinates":[-95.524727,29.964976],"type":"Point"}
}