{
  "type": "Feature",
  "properties": {
    "iso:country":"US",
    "sg:address":"1500 Coggin Ave",
    "sg:city":"Brownwood",
    "sg:classifiers":[
        {
            "category":"Professional",
            "subcategory":"Accounting & Tax Preparation",
            "type":"Services"
        }
    ],
    "sg:phone":"+1 325 646 4491",
    "sg:postcode":"76801",
    "sg:province":"TX",
    "sg:tags":[
        "bookkeeping",
        "general"
    ],
    "wof:name":"Vences Bookkeeping & Svc",
    "wof:placetype":"venue"
},
  "geometry": {"coordinates":[-98.981512,31.706255],"type":"Point"}
}