{
  "type": "Feature",
  "properties": {
    "iso:country":"US",
    "sg:address":"5615 Richmond Ave",
    "sg:city":"Houston",
    "sg:classifiers":[
        {
            "category":"Shopping",
            "subcategory":"Pharmacy",
            "type":"Retail Goods"
        }
    ],
    "sg:phone":"+1 713 780 7600",
    "sg:postcode":"77057",
    "sg:province":"TX",
    "sg:tags":[
        "drugstore"
    ],
    "wof:name":"Peccio Pharmacy Plus",
    "wof:placetype":"venue"
},
  "geometry": {"coordinates":[-95.477493,29.731302],"type":"Point"}
}