{
  "type": "Feature",
  "properties": {
    "iso:country":"US",
    "sg:address":"501 E Bedford St",
    "sg:city":"Dimmitt",
    "sg:classifiers":[
        {
            "category":"Food & Beverages",
            "subcategory":"Groceries & Convenience Stores",
            "type":"Retail Goods"
        }
    ],
    "sg:phone":"+1 806 647 5289",
    "sg:postcode":"79027",
    "sg:province":"TX",
    "sg:tags":[
        "station",
        "gasoline"
    ],
    "wof:name":"Allsups 24",
    "wof:placetype":"venue"
},
  "geometry": {"coordinates":[-102.30704,34.550857],"type":"Point"}
}