{
  "type": "Feature",
  "properties": {
    "iso:country":"US",
    "sg:address":"3548 Piedmont Pl",
    "sg:city":"Schertz",
    "sg:classifiers":[
        {
            "category":"Banks & Credit Unions",
            "subcategory":"Investment Brokerage",
            "type":"Services"
        }
    ],
    "sg:phone":"+1 210 659 2787",
    "sg:postcode":"78154",
    "sg:province":"TX",
    "wof:name":"Edward Jones Investments",
    "wof:placetype":"venue"
},
  "geometry": {"coordinates":[-98.278479,29.581551],"type":"Point"}
}