{
  "type": "Feature",
  "properties": {
    "iso:country":"US",
    "sg:address":"5704 41st St",
    "sg:city":"Lubbock",
    "sg:classifiers":[
        {
            "category":"Manufacturing",
            "subcategory":"Buildings",
            "type":"Manufacturing & Wholesale Goods"
        },
        {
            "category":"Real Estate",
            "subcategory":"Real Estate Services",
            "type":"Services"
        },
        {
            "category":"Real Estate",
            "subcategory":"Real Estate Agent",
            "type":"Services"
        },
        {
            "category":"Building & Trades",
            "subcategory":"Construction",
            "type":"Services"
        }
    ],
    "sg:phone":"+1 806 792 9068",
    "sg:postcode":"79407",
    "sg:province":"TX",
    "sg:tags":[
        "home",
        "builder",
        "management",
        "contractor"
    ],
    "wof:name":"Pearson Properties",
    "wof:placetype":"venue"
},
  "geometry": {"coordinates":[-101.93668099999999,33.557463],"type":"Point"}
}