{
  "type": "Feature",
  "properties": {
    "iso:country":"US",
    "sg:address":"401 W 14th St",
    "sg:city":"Dumas",
    "sg:classifiers":[
        {
            "category":"Education",
            "subcategory":"School",
            "type":"Public Place"
        }
    ],
    "sg:phone":"+1 806 935 2127",
    "sg:postcode":"79029",
    "sg:province":"TX",
    "wof:name":"Sunset Elementary School",
    "wof:placetype":"venue"
},
  "geometry": {"coordinates":[-101.978179,35.851015],"type":"Point"}
}