{
  "type": "Feature",
  "properties": {
    "iso:country":"US",
    "sg:address":"38 Holly Ct",
    "sg:city":"Conroe",
    "sg:classifiers":[
        {
            "category":"Organizations",
            "subcategory":"Religious Organization",
            "type":"Services"
        }
    ],
    "sg:phone":"+1 936 856 2774",
    "sg:postcode":"77304",
    "sg:province":"TX",
    "wof:name":"St Pauls Traditional Epi",
    "wof:placetype":"venue"
},
  "geometry": {"coordinates":[-95.49212799999999,30.371491],"type":"Point"}
}