{
  "type": "Feature",
  "properties": {
    "iso:country":"US",
    "sg:address":"100 Enterprise Ave",
    "sg:city":"League City",
    "sg:classifiers":[
        {
            "category":"Health Services",
            "subcategory":"Doctor",
            "type":"Services"
        }
    ],
    "sg:phone":"+1 281 538 8682",
    "sg:postcode":"77573",
    "sg:province":"TX",
    "sg:tags":[
        "physician",
        "surgeon"
    ],
    "wof:name":"Mainland Obstetrics & Gynclgy",
    "wof:placetype":"venue"
},
  "geometry": {"coordinates":[-95.05967,29.543568],"type":"Point"}
}