{
  "type": "Feature",
  "properties": {
    "iso:country":"US",
    "sg:address":"4305 Bryant Irvin Rd",
    "sg:city":"Fort Worth",
    "sg:classifiers":[
        {
            "category":"Home & Garden",
            "subcategory":"Building Materials",
            "type":"Retail Goods"
        }
    ],
    "sg:phone":"+1 817 738 7599",
    "sg:postcode":"76132",
    "sg:province":"TX",
    "sg:tags":[
        "center"
    ],
    "wof:name":"Lowe's",
    "wof:placetype":"venue"
},
  "geometry": {"coordinates":[-97.41346900000001,32.717955],"type":"Point"}
}