{
  "type": "Feature",
  "properties": {
    "iso:country":"US",
    "sg:address":"7206 Pella Dr",
    "sg:city":"Houston",
    "sg:classifiers":[
        {
            "category":"Shopping",
            "subcategory":"Department Store",
            "type":"Retail Goods"
        }
    ],
    "sg:phone":"+1 713 272 7602",
    "sg:postcode":"77036",
    "sg:province":"TX",
    "wof:name":"Su-Pu Fu",
    "wof:placetype":"venue"
},
  "geometry": {"coordinates":[-95.543498,29.700592],"type":"Point"}
}