{
  "type": "Feature",
  "properties": {
    "iso:country":"US",
    "sg:address":"1636 Gessner Dr",
    "sg:city":"Houston",
    "sg:classifiers":[
        {
            "category":"Retail",
            "subcategory":"Laundry & Dry Cleaning",
            "type":"Services"
        }
    ],
    "sg:phone":"+1 713 467 4282",
    "sg:postcode":"77080",
    "sg:province":"TX",
    "sg:tags":[
        "cleaner",
        "plant",
        "power",
        "drycleaning"
    ],
    "wof:name":"Jerry's Cleaners",
    "wof:placetype":"venue"
},
  "geometry": {"coordinates":[-95.544601,29.8015],"type":"Point"}
}