{
  "type": "Feature",
  "properties": {
    "iso:country":"US",
    "sg:address":"15219 Co Rd 285",
    "sg:city":"Tyler",
    "sg:classifiers":[
        {
            "category":"Retail",
            "subcategory":"Auto Repair",
            "type":"Services"
        }
    ],
    "sg:phone":"+1 903 566 4424",
    "sg:postcode":"75707",
    "sg:province":"TX",
    "sg:tags":[
        "transmission"
    ],
    "wof:name":"Addington Automotive",
    "wof:placetype":"venue"
},
  "geometry": {"coordinates":[-95.155784,32.259308],"type":"Point"}
}