{
  "type": "Feature",
  "properties": {
    "iso:country":"US",
    "sg:address":"3304 Towerwood Dr",
    "sg:city":"Dallas",
    "sg:classifiers":[
        {
            "category":"Wholesale",
            "subcategory":"Computers",
            "type":"Manufacturing & Wholesale Goods"
        }
    ],
    "sg:phone":"+1 972 488 9888",
    "sg:postcode":"75234",
    "sg:province":"TX",
    "sg:tags":[
        "integrator",
        "system"
    ],
    "wof:name":"Aopen Center Dallas",
    "wof:placetype":"venue"
},
  "geometry": {"coordinates":[-96.867671,32.951472],"type":"Point"}
}