{
  "type": "Feature",
  "properties": {
    "iso:country":"US",
    "sg:address":"205 W Owens St",
    "sg:city":"Weatherford",
    "sg:classifiers":[
        {
            "category":"Social Services",
            "type":"Services"
        }
    ],
    "sg:phone":"+1 817 613 0649",
    "sg:postcode":"76086",
    "sg:province":"TX",
    "sg:tags":[
        "counselor",
        "marriage",
        "family"
    ],
    "wof:name":"New Beginnings Counseling Cntr",
    "wof:placetype":"venue"
},
  "geometry": {"coordinates":[-97.79940000000001,32.740924],"type":"Point"}
}