{
  "type": "Feature",
  "properties": {
    "iso:country":"US",
    "sg:address":"852 Secretary Dr",
    "sg:city":"Arlington",
    "sg:classifiers":[
        {
            "category":"Banks & Credit Unions",
            "subcategory":"Bank",
            "type":"Services"
        }
    ],
    "sg:phone":"+1 817 276 1100",
    "sg:postcode":"76015",
    "sg:province":"TX",
    "sg:tags":[
        "personal",
        "institution"
    ],
    "wof:name":"Continental Credit Corp",
    "wof:placetype":"venue"
},
  "geometry": {"coordinates":[-97.118684,32.702929],"type":"Point"}
}