{
  "type": "Feature",
  "properties": {
    "iso:country":"US",
    "sg:address":"3414 Hondo Pass Ave",
    "sg:city":"El Paso",
    "sg:classifiers":[
        {
            "category":"Real Estate",
            "subcategory":"Real Estate Agent",
            "type":"Services"
        }
    ],
    "sg:phone":"+1 915 751 7000",
    "sg:postcode":"79904",
    "sg:province":"TX",
    "wof:name":"Assist 2 Sell",
    "wof:placetype":"venue"
},
  "geometry": {"coordinates":[-106.45176499999999,31.869373],"type":"Point"}
}