{
  "type": "Feature",
  "properties": {
    "iso:country":"US",
    "sg:address":"312 Melrose Pl",
    "sg:city":"San Antonio",
    "sg:classifiers":[
        {
            "category":"Banks & Credit Unions",
            "subcategory":"Financial Services",
            "type":"Services"
        }
    ],
    "sg:phone":"+1 210 828 1347",
    "sg:postcode":"78212",
    "sg:province":"TX",
    "sg:tags":[
        "investor"
    ],
    "wof:name":"Gpr Investments LLC",
    "wof:placetype":"venue"
},
  "geometry": {"coordinates":[-98.49720000000001,29.469318],"type":"Point"}
}