{
  "type": "Feature",
  "properties": {
    "iso:country":"US",
    "sg:address":"6666 Sam Houston Pkwy",
    "sg:city":"Houston",
    "sg:classifiers":[
        {
            "category":"Food & Beverages",
            "subcategory":"Groceries & Convenience Stores",
            "type":"Retail Goods"
        }
    ],
    "sg:phone":"+1 713 849 4820",
    "sg:postcode":"77085",
    "sg:province":"TX",
    "wof:name":"Diamond Shamrock",
    "wof:placetype":"venue"
},
  "geometry": {"coordinates":[-95.484987,29.609587],"type":"Point"}
}