{
  "type": "Feature",
  "properties": {
    "iso:country":"US",
    "sg:address":"4441 de Zavala Rd",
    "sg:city":"San Antonio",
    "sg:classifiers":[
        {
            "category":"Retail",
            "subcategory":"Animal Services",
            "type":"Services"
        }
    ],
    "sg:phone":"+1 210 764 8300",
    "sg:postcode":"78249",
    "sg:province":"TX",
    "sg:tags":[
        "pet",
        "grooming",
        "washing"
    ],
    "wof:name":"Cute Cuts Pet Grooming",
    "wof:placetype":"venue"
},
  "geometry": {"coordinates":[-98.572379,29.571977],"type":"Point"}
}