{
  "type": "Feature",
  "properties": {
    "iso:country":"US",
    "sg:address":"2505 Oaks Dr",
    "sg:city":"Pasadena",
    "sg:classifiers":[
        {
            "category":"Professional",
            "type":"Services"
        }
    ],
    "sg:phone":"+1 713 910 3894",
    "sg:postcode":"77502",
    "sg:province":"TX",
    "wof:name":"Cybertex Electronics",
    "wof:placetype":"venue"
},
  "geometry": {"coordinates":[-95.21508,29.673432],"type":"Point"}
}