{
  "type": "Feature",
  "properties": {
    "iso:country":"US",
    "sg:address":"313 W 15th Ave",
    "sg:city":"Amarillo",
    "sg:classifiers":[
        {
            "category":"Professional",
            "subcategory":"Lawyer & Legal Services",
            "type":"Services"
        }
    ],
    "sg:phone":"+1 806 371 8888",
    "sg:postcode":"79101",
    "sg:province":"AR",
    "sg:tags":[
        "attorney"
    ],
    "wof:name":"Ronald D Nickum",
    "wof:placetype":"venue"
},
  "geometry": {"coordinates":[-101.841846,35.198614],"type":"Point"}
}