{
  "type": "Feature",
  "properties": {
    "iso:country":"US",
    "sg:address":"2304 Thunderbird Ave",
    "sg:city":"Mcallen",
    "sg:classifiers":[
        {
            "category":"Professional",
            "subcategory":"Management & Consulting",
            "type":"Services"
        }
    ],
    "sg:phone":"+1 956 682 4820",
    "sg:postcode":"78504",
    "sg:province":"TX",
    "sg:tags":[
        "consultant",
        "educational"
    ],
    "wof:name":"Institute-Interdisciplinary",
    "wof:placetype":"venue"
},
  "geometry": {"coordinates":[-98.234651,26.269195],"type":"Point"}
}