{
  "type": "Feature",
  "properties": {
    "iso:country":"US",
    "sg:address":"1834 Eastfield Dr",
    "sg:city":"Missouri City",
    "sg:classifiers":[
        {
            "category":"Real Estate",
            "subcategory":"Real Estate Agent",
            "type":"Services"
        }
    ],
    "sg:phone":"+1 281 437 7057",
    "sg:postcode":"77459",
    "sg:province":"TX",
    "wof:name":"Ratliff & Gardner Investments",
    "wof:placetype":"venue"
},
  "geometry": {"coordinates":[-95.52730699999999,29.572252],"type":"Point"}
}