{
  "type": "Feature",
  "properties": {
    "iso:country":"US",
    "sg:address":"1431 N Shepherd Dr",
    "sg:city":"Houston",
    "sg:classifiers":[
        {
            "category":"Retail",
            "subcategory":"Veterinary Services",
            "type":"Services"
        }
    ],
    "sg:phone":"+1 713 869 6644",
    "sg:postcode":"77008",
    "sg:province":"TX",
    "sg:tags":[
        "veterinarian"
    ],
    "sg:website":"www.heightsvet.com",
    "wof:name":"Kenneth H Williams DVM",
    "wof:placetype":"venue"
},
  "geometry": {"coordinates":[-95.41042899999999,29.797061],"type":"Point"}
}