{
  "type": "Feature",
  "properties": {
    "iso:country":"US",
    "sg:address":"704 Colony Dr",
    "sg:city":"Schertz",
    "sg:classifiers":[
        {
            "category":"Building & Trades",
            "subcategory":"Plumbing",
            "type":"Services"
        }
    ],
    "sg:phone":"+1 210 566 8018",
    "sg:postcode":"78154",
    "sg:province":"TX",
    "sg:tags":[
        "air",
        "conditioning",
        "contractor"
    ],
    "wof:name":"Absolute Quality AC",
    "wof:placetype":"venue"
},
  "geometry": {"coordinates":[-98.26835800000001,29.56043],"type":"Point"}
}