{
  "type": "Feature",
  "properties": {
    "iso:country":"US",
    "sg:address":"2040 Valley View Mall",
    "sg:city":"Dallas",
    "sg:classifiers":[
        {
            "category":"Restaurant",
            "type":"Food & Drink"
        }
    ],
    "sg:phone":"+1 972 233 3938",
    "sg:postcode":"75240",
    "sg:province":"TX",
    "sg:tags":[
        "eating"
    ],
    "wof:name":"Paradise Island Snack Bar",
    "wof:placetype":"venue"
},
  "geometry": {"coordinates":[-96.80605199999999,32.93147],"type":"Point"}
}