{
  "type": "Feature",
  "properties": {
    "iso:country":"US",
    "sg:address":"516 Sherwood Loop",
    "sg:city":"Mertzon",
    "sg:classifiers":[
        {
            "category":"Professional",
            "type":"Services"
        }
    ],
    "sg:phone":"+1 325 835 5008",
    "sg:postcode":"76941",
    "sg:province":"TX",
    "wof:name":"Marc Amonett",
    "wof:placetype":"venue"
},
  "geometry": {"coordinates":[-100.80408,31.274807],"type":"Point"}
}