{
  "type": "Feature",
  "properties": {
    "iso:country":"US",
    "sg:address":"12521 Fondren Rd",
    "sg:city":"Houston",
    "sg:classifiers":[
        {
            "category":"Local Transit",
            "type":"Transportation"
        }
    ],
    "sg:phone":"+1 713 283 8577",
    "sg:postcode":"77035",
    "sg:province":"TX",
    "sg:tags":[
        "ambulance"
    ],
    "wof:name":"Champion Ems",
    "wof:placetype":"venue"
},
  "geometry": {"coordinates":[-95.50820299999999,29.641533],"type":"Point"}
}