{
  "type": "Feature",
  "properties": {
    "iso:country":"US",
    "sg:address":"9752 Harry Hines Blvd",
    "sg:city":"Dallas",
    "sg:classifiers":[
        {
            "category":"Autos & Motor Vehicles",
            "subcategory":"Automobile Sales",
            "type":"Retail Goods"
        }
    ],
    "sg:phone":"+1 214 358 1949",
    "sg:postcode":"75220",
    "sg:province":"TX",
    "sg:tags":[
        "car",
        "dealer"
    ],
    "wof:name":"Fuentes Motors",
    "wof:placetype":"venue"
},
  "geometry": {"coordinates":[-96.879254,32.854956],"type":"Point"}
}