{
  "type": "Feature",
  "properties": {
    "iso:country":"US",
    "sg:address":"2162 Little Cedar Dr",
    "sg:city":"Humble",
    "sg:classifiers":[
        {
            "category":"Mining & Drilling",
            "type":"Manufacturing & Wholesale Goods"
        }
    ],
    "sg:phone":"+1 281 358 5414",
    "sg:postcode":"77339",
    "sg:province":"TX",
    "sg:tags":[
        "field"
    ],
    "wof:name":"Fabrication Services Inc",
    "wof:placetype":"venue"
},
  "geometry": {"coordinates":[-95.21606300000001,30.059578],"type":"Point"}
}