{
  "type": "Feature",
  "properties": {
    "iso:country":"US",
    "sg:address":"234 Main St",
    "sg:city":"Quitaque",
    "sg:classifiers":[
        {
            "category":"Autos & Motor Vehicles",
            "subcategory":"Automobile Sales",
            "type":"Retail Goods"
        }
    ],
    "sg:phone":"+1 806 455 1226",
    "sg:postcode":"79255",
    "sg:province":"TX",
    "sg:tags":[
        "car",
        "dealer"
    ],
    "wof:name":"Quitaque Motors",
    "wof:placetype":"venue"
},
  "geometry": {"coordinates":[-101.055376,34.366077],"type":"Point"}
}