{
  "type": "Feature",
  "properties": {
    "iso:country":"US",
    "sg:address":"616 Circle Dr",
    "sg:city":"Bullard",
    "sg:classifiers":[
        {
            "category":"Professional",
            "subcategory":"Art Services",
            "type":"Services"
        }
    ],
    "sg:phone":"+1 903 894 9397",
    "sg:postcode":"75757",
    "sg:province":"TX",
    "sg:tags":[
        "designer",
        "display",
        "producer"
    ],
    "wof:name":"Extreme Designs",
    "wof:placetype":"venue"
},
  "geometry": {"coordinates":[-95.323982,32.135882],"type":"Point"}
}