{
  "type": "Feature",
  "properties": {
    "iso:country":"US",
    "sg:address":"12008 Warfield St",
    "sg:city":"San Antonio",
    "sg:classifiers":[
        {
            "category":"Shopping",
            "type":"Retail Goods"
        },
        {
            "category":"Retail",
            "subcategory":"Repair Shop",
            "type":"Services"
        }
    ],
    "sg:phone":"+1 210 341 1188",
    "sg:postcode":"78216",
    "sg:province":"TX",
    "sg:tags":[
        "equipment",
        "electrical",
        "telephone",
        "merchandise",
        "supply"
    ],
    "wof:name":"Design Telephone Systems",
    "wof:placetype":"venue"
},
  "geometry": {"coordinates":[-98.49175099999999,29.552538],"type":"Point"}
}