{
  "type": "Feature",
  "properties": {
    "iso:country":"US",
    "sg:address":"2005 Birdcreek Dr",
    "sg:city":"Temple",
    "sg:classifiers":[
        {
            "category":"Professional",
            "subcategory":"Lawyer & Legal Services",
            "type":"Services"
        }
    ],
    "sg:phone":"+1 254 773 9081",
    "sg:postcode":"76502",
    "sg:province":"TX",
    "sg:tags":[
        "attorney"
    ],
    "wof:name":"Patrick J Ridley",
    "wof:placetype":"venue"
},
  "geometry": {"coordinates":[-97.38712099999999,31.087478],"type":"Point"}
}