{
  "type": "Feature",
  "properties": {
    "iso:country":"US",
    "sg:address":"2659 Gravel Dr",
    "sg:city":"Fort Worth",
    "sg:classifiers":[
        {
            "category":"Wholesale",
            "subcategory":"Electrical",
            "type":"Manufacturing & Wholesale Goods"
        }
    ],
    "sg:phone":"+1 817 284 2803",
    "sg:postcode":"76118",
    "sg:province":"TX",
    "sg:tags":[
        "fire",
        "equipment",
        "protection"
    ],
    "wof:name":"Grinnell Fire Protection",
    "wof:placetype":"venue"
},
  "geometry": {"coordinates":[-97.217033,32.796642],"type":"Point"}
}