{
  "type": "Feature",
  "properties": {
    "iso:country":"US",
    "sg:address":"2924 Lagerway Cove",
    "sg:city":"Austin",
    "sg:classifiers":[
        {
            "category":"Social Services",
            "type":"Services"
        }
    ],
    "sg:phone":"+1 512 990 8361",
    "sg:postcode":"78748",
    "sg:province":"TX",
    "sg:tags":[
        "case",
        "worker"
    ],
    "wof:name":"Kris O Wagar",
    "wof:placetype":"venue"
},
  "geometry": {"coordinates":[-97.836782,30.182438],"type":"Point"}
}