{
  "type": "Feature",
  "properties": {
    "iso:country":"US",
    "sg:address":"13601 Preston Rd",
    "sg:city":"Dallas",
    "sg:classifiers":[
        {
            "category":"Personal",
            "type":"Services"
        }
    ],
    "sg:phone":"+1 972 980 2333",
    "sg:postcode":"75240",
    "sg:province":"TX",
    "sg:tags":[
        "credit",
        "debt",
        "counseling"
    ],
    "wof:name":"V Management",
    "wof:placetype":"venue"
},
  "geometry": {"coordinates":[-96.803799,32.934306],"type":"Point"}
}