{
  "type": "Feature",
  "properties": {
    "iso:country":"US",
    "sg:address":"14680 Perthshire Rd",
    "sg:city":"Houston",
    "sg:classifiers":[
        {
            "category":"Manufacturing",
            "subcategory":"Toys & Sporting Goods",
            "type":"Manufacturing & Wholesale Goods"
        }
    ],
    "sg:phone":"+1 832 593 0719",
    "sg:postcode":"77079",
    "sg:province":"TX",
    "sg:tags":[
        "stuffed",
        "doll"
    ],
    "wof:name":"Back In Time",
    "wof:placetype":"venue"
},
  "geometry": {"coordinates":[-95.607456,29.773852],"type":"Point"}
}