{
  "type": "Feature",
  "properties": {
    "iso:country":"US",
    "sg:address":"11917 Hardwood Trl",
    "sg:city":"Austin",
    "sg:classifiers":[
        {
            "category":"Retail",
            "subcategory":"Repair Shop",
            "type":"Services"
        }
    ],
    "sg:phone":"+1 512 335 6579",
    "sg:postcode":"78750",
    "sg:province":"TX",
    "sg:tags":[
        "refrigeration",
        "air conditioning"
    ],
    "sg:website":"http://www.americanstandardair.com",
    "wof:name":"Davis Service Company",
    "wof:placetype":"venue"
},
  "geometry": {"coordinates":[-97.816093,30.456711],"type":"Point"}
}