{
  "type": "Feature",
  "properties": {
    "iso:country":"US",
    "sg:address":"1310 Ranch Rd 620 S",
    "sg:city":"Austin",
    "sg:classifiers":[
        {
            "category":"Insurance",
            "subcategory":"Hazard Insurance",
            "type":"Services"
        },
        {
            "category":"Insurance",
            "subcategory":"Insurance Agent",
            "type":"Services"
        }
    ],
    "sg:phone":"+1 512 263 3293",
    "sg:postcode":"78734",
    "sg:province":"TX",
    "sg:tags":[
        "underwriter",
        "auto"
    ],
    "wof:name":"BISYS Specialty Programs",
    "wof:placetype":"venue"
},
  "geometry": {"coordinates":[-97.96316899999999,30.351303],"type":"Point"}
}