{
  "type": "Feature",
  "properties": {
    "iso:country":"US",
    "sg:address":"203 E Ave A",
    "sg:city":"Hooks",
    "sg:classifiers":[
        {
            "category":"Cinema",
            "subcategory":"Movie Rental",
            "type":"Entertainment"
        }
    ],
    "sg:phone":"+1 903 547 1744",
    "sg:postcode":"75561",
    "sg:province":"TX",
    "sg:tags":[
        "video",
        "tape"
    ],
    "wof:name":"Hooks Video",
    "wof:placetype":"venue"
},
  "geometry": {"coordinates":[-94.285006,33.466533],"type":"Point"}
}