{
  "type": "Feature",
  "properties": {
    "iso:country":"US",
    "sg:address":"407 E Royall Blvd",
    "sg:city":"Malakoff",
    "sg:classifiers":[
        {
            "category":"Shopping",
            "subcategory":"Discount & Variety Stores",
            "type":"Retail Goods"
        }
    ],
    "sg:phone":"+1 903 489 3424",
    "sg:postcode":"75148",
    "sg:province":"TX",
    "sg:tags":[
        "merchandise",
        "general"
    ],
    "wof:name":"Dollar General 0515",
    "wof:placetype":"venue"
},
  "geometry": {"coordinates":[-95.99401899999999,32.175068],"type":"Point"}
}