{
  "type": "Feature",
  "properties": {
    "iso:country":"US",
    "sg:address":"603 E Houston St",
    "sg:city":"Cleveland",
    "sg:classifiers":[
        {
            "category":"Shopping",
            "subcategory":"Pharmacy",
            "type":"Retail Goods"
        }
    ],
    "sg:phone":"+1 281 592 5257",
    "sg:postcode":"77327",
    "sg:province":"TX",
    "wof:name":"Pharmacy The",
    "wof:placetype":"venue"
},
  "geometry": {"coordinates":[-95.081763,30.341149],"type":"Point"}
}