{
  "type": "Feature",
  "properties": {
    "iso:country":"US",
    "sg:address":"425 N Fredonia St",
    "sg:city":"Longview",
    "sg:classifiers":[
        {
            "category":"Health Services",
            "subcategory":"Doctor",
            "type":"Services"
        }
    ],
    "sg:phone":"+1 903 238 8972",
    "sg:postcode":"75601",
    "sg:province":"TX",
    "sg:tags":[
        "clinic"
    ],
    "wof:name":"Da Vita Region Five Office",
    "wof:placetype":"venue"
},
  "geometry": {"coordinates":[-94.737138,32.500528],"type":"Point"}
}