{
  "type": "Feature",
  "properties": {
    "iso:country":"US",
    "sg:address":"1934 E Abram St",
    "sg:city":"Arlington",
    "sg:classifiers":[
        {
            "category":"Personal",
            "subcategory":"Beauty Salon",
            "type":"Services"
        }
    ],
    "sg:phone":"+1 817 275 1611",
    "sg:postcode":"76010",
    "sg:province":"TX",
    "sg:tags":[
        "shop"
    ],
    "wof:name":"Circle Beauty Salon",
    "wof:placetype":"venue"
},
  "geometry": {"coordinates":[-97.078265,32.735174],"type":"Point"}
}