{
  "type": "Feature",
  "properties": {
    "iso:country":"US",
    "sg:address":"1900 Airline Dr",
    "sg:city":"Houston",
    "sg:classifiers":[
        {
            "category":"Wholesale",
            "subcategory":"Fruits & Vegetables",
            "type":"Manufacturing & Wholesale Goods"
        }
    ],
    "sg:phone":"+1 713 880 0404",
    "sg:postcode":"77009",
    "sg:province":"TX",
    "sg:tags":[
        "veggie"
    ],
    "wof:name":"Green & Fresh Produce Co",
    "wof:placetype":"venue"
},
  "geometry": {"coordinates":[-95.381798,29.804899],"type":"Point"}
}