{
  "type": "Feature",
  "properties": {
    "iso:country":"US",
    "sg:address":"5802 Onion Creek Dr",
    "sg:city":"Garland",
    "sg:classifiers":[
        {
            "category":"Communications",
            "type":"Services"
        }
    ],
    "sg:phone":"+1 972 495 8245",
    "sg:postcode":"75044",
    "sg:province":"TX",
    "sg:tags":[
        "communication"
    ],
    "wof:name":"Power Of Communications",
    "wof:placetype":"venue"
},
  "geometry": {"coordinates":[-96.636967,32.968068],"type":"Point"}
}