{
  "type": "Feature",
  "properties": {
    "iso:country":"US",
    "sg:address":"3302 61st St",
    "sg:city":"Lubbock",
    "sg:classifiers":[
        {
            "category":"Manufacturing",
            "subcategory":"Tools & Machinery",
            "type":"Manufacturing & Wholesale Goods"
        },
        {
            "category":"Manufacturing",
            "subcategory":"Motor Vehicles & Parts",
            "type":"Manufacturing & Wholesale Goods"
        }
    ],
    "sg:phone":"+1 806 785 8036",
    "sg:postcode":"79413",
    "sg:province":"TX",
    "sg:tags":[
        "engine",
        "mfg"
    ],
    "wof:name":"Garrett Malcolm Racing Engines",
    "wof:placetype":"venue"
},
  "geometry": {"coordinates":[-101.887703,33.538917],"type":"Point"}
}