{
  "type": "Feature",
  "properties": {
    "iso:country":"US",
    "sg:address":"2603 Joel Wheaton Rd",
    "sg:city":"Houston",
    "sg:classifiers":[
        {
            "category":"Wholesale",
            "subcategory":"Vending Machines",
            "type":"Manufacturing & Wholesale Goods"
        }
    ],
    "sg:phone":"+1 281 493 4804",
    "sg:postcode":"77082",
    "sg:province":"TX",
    "sg:tags":[
        "operator"
    ],
    "wof:name":"Alltexas Vending",
    "wof:placetype":"venue"
},
  "geometry": {"coordinates":[-95.633844,29.734605],"type":"Point"}
}