{
  "type": "Feature",
  "properties": {
    "iso:country":"US",
    "sg:address":"577 Watson Ln W",
    "sg:city":"New Braunfels",
    "sg:classifiers":[
        {
            "category":"Building & Trades",
            "subcategory":"Landscaping Services",
            "type":"Services"
        }
    ],
    "sg:phone":"+1 830 620 5002",
    "sg:postcode":"78130",
    "sg:province":"TX",
    "sg:tags":[
        "landscape"
    ],
    "wof:name":"El Eden",
    "wof:placetype":"venue"
},
  "geometry": {"coordinates":[-98.041318,29.7864],"type":"Point"}
}