{
  "type": "Feature",
  "properties": {
    "iso:country":"US",
    "sg:address":"1119 Farragut St",
    "sg:city":"Laredo",
    "sg:classifiers":[
        {
            "category":"Shopping",
            "subcategory":"Shoes",
            "type":"Retail Goods"
        }
    ],
    "sg:phone":"+1 956 726 4941",
    "sg:postcode":"78040",
    "sg:province":"TX",
    "wof:name":"Payless Shoe Source",
    "wof:placetype":"venue"
},
  "geometry": {"coordinates":[-99.507346,27.505586],"type":"Point"}
}