{
  "type": "Feature",
  "properties": {
    "iso:country":"US",
    "sg:address":"1214 E Marshall Ave",
    "sg:city":"Longview",
    "sg:classifiers":[
        {
            "category":"Recreation",
            "type":"Entertainment"
        }
    ],
    "sg:phone":"+1 903 236 8500",
    "sg:postcode":"75601",
    "sg:province":"TX",
    "sg:tags":[
        "psychic",
        "medium"
    ],
    "wof:name":"Patsy's Psychic Readings",
    "wof:placetype":"venue"
},
  "geometry": {"coordinates":[-94.722274,32.503454],"type":"Point"}
}