{
  "type": "Feature",
  "properties": {
    "iso:country":"US",
    "sg:address":"1205 Placid Ave",
    "sg:city":"Plano",
    "sg:classifiers":[
        {
            "category":"Building & Trades",
            "subcategory":"Landscaping Services",
            "type":"Services"
        }
    ],
    "sg:phone":"+1 972 516 1122",
    "sg:postcode":"75074",
    "sg:province":"TX",
    "sg:tags":[
        "landscape",
        "contractor"
    ],
    "wof:name":"Bruce Landscaping/Maintenance",
    "wof:placetype":"venue"
},
  "geometry": {"coordinates":[-96.68988400000001,33.012683],"type":"Point"}
}