{
  "type": "Feature",
  "properties": {
    "iso:country":"US",
    "sg:address":"306 W 61st St",
    "sg:city":"Odessa",
    "sg:classifiers":[
        {
            "category":"Autos & Motor Vehicles",
            "subcategory":"Motorcycle Sales",
            "type":"Retail Goods"
        }
    ],
    "sg:phone":"+1 432 367 8018",
    "sg:postcode":"79764",
    "sg:province":"TX",
    "sg:tags":[
        "scooter"
    ],
    "wof:name":"W T Ustoms Inc",
    "wof:placetype":"venue"
},
  "geometry": {"coordinates":[-102.396208,31.900103],"type":"Point"}
}