{
  "type": "Feature",
  "properties": {
    "iso:country":"US",
    "sg:address":"4131 Spicewood Springs Rd Q2",
    "sg:city":"Austin",
    "sg:classifiers":[
        {
            "category":"Social Services",
            "type":"Services"
        },
        {
            "category":"Personal",
            "type":"Services"
        },
        {
            "category":"Health Services",
            "subcategory":"Health Practitioner",
            "type":"Services"
        }
    ],
    "sg:phone":"+1 512 918 1391",
    "sg:postcode":"78759",
    "sg:province":"TX",
    "sg:tags":[
        "family",
        "psychotherapist",
        "counselors-licensed",
        "individual",
        "marriage",
        "child",
        "professional",
        "counselor"
    ],
    "sg:website":"http://www.mpsaustin.com",
    "wof:name":"Mariposa Psychotherapy Assoc",
    "wof:placetype":"venue"
},
  "geometry": {"coordinates":[-97.754965,30.36958],"type":"Point"}
}