{
  "type": "Feature",
  "properties": {
    "iso:country":"US",
    "sg:address":"521 Sunnyside Dr",
    "sg:city":"Chandler",
    "sg:classifiers":[
        {
            "category":"Freight",
            "type":"Transportation"
        }
    ],
    "sg:phone":"+1 903 849 1930",
    "sg:postcode":"75758",
    "sg:province":"TX",
    "sg:tags":[
        "operator",
        "local",
        "trucking"
    ],
    "wof:name":"R&L Trucking Co",
    "wof:placetype":"venue"
},
  "geometry": {"coordinates":[-95.472841,32.312242],"type":"Point"}
}