{
  "type": "Feature",
  "properties": {
    "iso:country":"US",
    "sg:address":"104 I- 45 N",
    "sg:city":"Conroe",
    "sg:classifiers":[
        {
            "category":"Education",
            "subcategory":"Library",
            "type":"Public Place"
        }
    ],
    "sg:phone":"+1 936 756 0571",
    "sg:postcode":"77301",
    "sg:province":"TX",
    "wof:name":"Central Library",
    "wof:placetype":"venue"
},
  "geometry": {"coordinates":[-95.469228,30.31077],"type":"Point"}
}