{
  "type": "Feature",
  "properties": {
    "iso:country":"US",
    "sg:address":"9300 Needlepoint Rd",
    "sg:city":"Baytown",
    "sg:classifiers":[
        {
            "category":"Manufacturing",
            "subcategory":"Chemicals & Compounds",
            "type":"Manufacturing & Wholesale Goods"
        }
    ],
    "sg:phone":"+1 281 421 2500",
    "sg:postcode":"77521",
    "sg:province":"TX",
    "sg:tags":[
        "carbon",
        "black",
        "mfg"
    ],
    "wof:name":"Engineered Carbons Inc",
    "wof:placetype":"venue"
},
  "geometry": {"coordinates":[-94.930319,29.811488],"type":"Point"}
}