{
  "type": "Feature",
  "properties": {
    "iso:country":"US",
    "sg:address":"1808 Weanne Dr",
    "sg:city":"Richardson",
    "sg:classifiers":[
        {
            "category":"Professional",
            "subcategory":"Computer Services",
            "type":"Services"
        }
    ],
    "sg:phone":"+1 214 924 8126",
    "sg:postcode":"75082",
    "sg:province":"TX",
    "sg:tags":[
        "datum"
    ],
    "wof:name":"Netcom Solutions",
    "wof:placetype":"venue"
},
  "geometry": {"coordinates":[-96.688261,32.990783],"type":"Point"}
}