{
  "type": "Feature",
  "properties": {
    "iso:country":"US",
    "sg:address":"184 Tank Destroyer Blvd",
    "sg:city":"Fort Hood",
    "sg:classifiers":[
        {
            "category":"Real Estate",
            "subcategory":"Real Estate Agent",
            "type":"Services"
        }
    ],
    "sg:phone":"+1 254 554 2482",
    "sg:postcode":"76544",
    "sg:province":"TX",
    "sg:tags":[
        "authorities",
        "housing"
    ],
    "wof:name":"Fort Hood Family Housing",
    "wof:placetype":"venue"
},
  "geometry": {"coordinates":[-97.75788900000001,31.134231],"type":"Point"}
}