{
  "type": "Feature",
  "properties": {
    "iso:country":"US",
    "sg:address":"3051 Ira E Woods Ave",
    "sg:city":"Grapevine",
    "sg:classifiers":[
        {
            "category":"Education",
            "subcategory":"School",
            "type":"Public Place"
        }
    ],
    "sg:phone":"+1 817 251 5466",
    "sg:postcode":"76051",
    "sg:province":"TX",
    "wof:name":"Vista Alternative Campus",
    "wof:placetype":"venue"
},
  "geometry": {"coordinates":[-97.11763500000001,32.919924],"type":"Point"}
}