{
  "type": "Feature",
  "properties": {
    "iso:country":"US",
    "sg:address":"6607 Country Ln",
    "sg:city":"Richmond",
    "sg:classifiers":[
        {
            "category":"Professional",
            "type":"Services"
        }
    ],
    "sg:phone":"+1 281 232 5951",
    "sg:postcode":"77469",
    "sg:province":"TX",
    "wof:name":"Herman N Trevino",
    "wof:placetype":"venue"
},
  "geometry": {"coordinates":[-95.741713,29.446963],"type":"Point"}
}