{
  "type": "Feature",
  "properties": {
    "iso:country":"US",
    "sg:address":"1441 Forest Ln",
    "sg:city":"Garland",
    "sg:classifiers":[
        {
            "category":"Health Services",
            "subcategory":"Chiropractor",
            "type":"Services"
        }
    ],
    "sg:phone":"+1 972 276 7800",
    "sg:postcode":"75042",
    "sg:province":"TX",
    "wof:name":"Klesmit Chiropractic Offices PA",
    "wof:placetype":"venue"
},
  "geometry": {"coordinates":[-96.650299,32.9095],"type":"Point"}
}