{
  "type": "Feature",
  "properties": {
    "iso:country":"US",
    "sg:address":"1301 W Dickinson Blvd",
    "sg:city":"Fort Stockton",
    "sg:classifiers":[
        {
            "category":"Wholesale",
            "subcategory":"Medical Equipment & Supplies",
            "type":"Manufacturing & Wholesale Goods"
        }
    ],
    "sg:phone":"+1 432 336 5855",
    "sg:postcode":"79735",
    "sg:province":"TX",
    "wof:name":"Wheel Chairs Etc",
    "wof:placetype":"venue"
},
  "geometry": {"coordinates":[-102.893309,30.893929],"type":"Point"}
}