{
  "type": "Feature",
  "properties": {
    "iso:country":"US",
    "sg:address":"1525 Viceroy Dr",
    "sg:city":"Dallas",
    "sg:classifiers":[
        {
            "category":"Professional",
            "subcategory":"Engineering",
            "type":"Services"
        }
    ],
    "sg:phone":"+1 214 634 3300",
    "sg:postcode":"75235",
    "sg:province":"TX",
    "sg:tags":[
        "civil",
        "consulting",
        "engineer"
    ],
    "sg:website":"http://www.usaengineers.com",
    "wof:name":"USA Professional Svcs Group Inc",
    "wof:placetype":"venue"
},
  "geometry": {"coordinates":[-96.87139500000001,32.833166],"type":"Point"}
}