{
  "type": "Feature",
  "properties": {
    "iso:country":"US",
    "sg:address":"28 W Plaza St",
    "sg:city":"Paris",
    "sg:classifiers":[
        {
            "category":"Shopping",
            "subcategory":"Musical Instruments",
            "type":"Retail Goods"
        }
    ],
    "sg:phone":"+1 903 784 5292",
    "sg:postcode":"75449",
    "sg:province":"TX",
    "wof:name":"Mc Kay Music Co",
    "wof:placetype":"venue"
},
  "geometry": {"coordinates":[-95.94738599999999,33.425944],"type":"Point"}
}