{
  "type": "Feature",
  "properties": {
    "iso:country":"US",
    "sg:address":"18010 Blinka Rd",
    "sg:city":"Waller",
    "sg:classifiers":[
        {
            "category":"Shopping",
            "subcategory":"Hobbies, Toys, & Games",
            "type":"Retail Goods"
        }
    ],
    "sg:phone":"+1 936 931 2919",
    "sg:postcode":"77484",
    "sg:province":"TX",
    "wof:name":"Sandys Country Crafts",
    "wof:placetype":"venue"
},
  "geometry": {"coordinates":[-95.966471,30.036728],"type":"Point"}
}