{
  "type": "Feature",
  "properties": {
    "iso:country":"US",
    "sg:address":"260 W Ridgewood Rd",
    "sg:city":"Georgetown",
    "sg:classifiers":[
        {
            "category":"Professional",
            "subcategory":"Management & Consulting",
            "type":"Services"
        }
    ],
    "sg:phone":"+1 512 763 1090",
    "sg:postcode":"78628",
    "sg:province":"TX",
    "sg:tags":[
        "business"
    ],
    "wof:name":"Bullard Environmental Consulti",
    "wof:placetype":"venue"
},
  "geometry": {"coordinates":[-97.772476,30.714473],"type":"Point"}
}