{
  "type": "Feature",
  "properties": {
    "iso:country":"US",
    "sg:address":"4704 Tumbleweed Ave",
    "sg:city":"El Paso",
    "sg:classifiers":[
        {
            "category":"Home & Garden",
            "subcategory":"Home Furnishings",
            "type":"Retail Goods"
        }
    ],
    "sg:phone":"+1 915 755 4477",
    "sg:postcode":"79924",
    "sg:province":"TX",
    "wof:name":"P & J Knives",
    "wof:placetype":"venue"
},
  "geometry": {"coordinates":[-106.437933,31.906059],"type":"Point"}
}