{
  "type": "Feature",
  "properties": {
    "iso:country":"US",
    "sg:address":"2727 Weslayan St",
    "sg:city":"Houston",
    "sg:classifiers":[
        {
            "category":"Banks & Credit Unions",
            "subcategory":"Financial Services",
            "type":"Services"
        }
    ],
    "sg:phone":"+1 713 623 0600",
    "sg:postcode":"77027",
    "sg:province":"TX",
    "sg:tags":[
        "company",
        "holding"
    ],
    "wof:name":"Timothy K & Duck GI Seo Family",
    "wof:placetype":"venue"
},
  "geometry": {"coordinates":[-95.441531,29.7383],"type":"Point"}
}