{
  "type": "Feature",
  "properties": {
    "iso:country":"US",
    "sg:address":"3901 Flamingo Dr",
    "sg:city":"El Paso",
    "sg:classifiers":[
        {
            "category":"Building & Trades",
            "subcategory":"Cleaning & Sanitation",
            "type":"Services"
        }
    ],
    "sg:phone":"+1 915 532 5485",
    "sg:postcode":"79902",
    "sg:province":"TX",
    "sg:tags":[
        "janitor"
    ],
    "wof:name":"Sparkle Inc",
    "wof:placetype":"venue"
},
  "geometry": {"coordinates":[-106.50091500000001,31.792951],"type":"Point"}
}