{
  "type": "Feature",
  "properties": {
    "iso:country":"US",
    "sg:address":"4620 E Hwy 377",
    "sg:city":"Granbury",
    "sg:classifiers":[
        {
            "category":"Personal",
            "subcategory":"Beauty Salon",
            "type":"Services"
        }
    ],
    "sg:phone":"+1 817 573 6444",
    "sg:postcode":"76049",
    "sg:province":"TX",
    "sg:tags":[
        "shop"
    ],
    "wof:name":"Beauty On Brazos",
    "wof:placetype":"venue"
},
  "geometry": {"coordinates":[-97.716278,32.462757],"type":"Point"}
}