{
  "type": "Feature",
  "properties": {
    "iso:country":"US",
    "sg:address":"3018 W Walker St",
    "sg:city":"Breckenridge",
    "sg:classifiers":[
        {
            "category":"Shopping",
            "subcategory":"Computers & Home Electronics",
            "type":"Retail Goods"
        }
    ],
    "sg:phone":"+1 254 559 1630",
    "sg:postcode":"76424",
    "sg:province":"TX",
    "sg:tags":[
        "equipment",
        "dealer"
    ],
    "wof:name":"Steve's Computer Shop",
    "wof:placetype":"venue"
},
  "geometry": {"coordinates":[-98.94566,32.759371],"type":"Point"}
}