{
  "type": "Feature",
  "properties": {
    "iso:country":"US",
    "sg:address":"506 E Ramsey Rd",
    "sg:city":"San Antonio",
    "sg:classifiers":[
        {
            "category":"Manufacturing",
            "subcategory":"Printing",
            "type":"Manufacturing & Wholesale Goods"
        }
    ],
    "sg:phone":"+1 210 572 4346",
    "sg:postcode":"78216",
    "sg:province":"TX",
    "sg:tags":[
        "commercial"
    ],
    "wof:name":"Ceasars Creation Screen Print",
    "wof:placetype":"venue"
},
  "geometry": {"coordinates":[-98.48427100000001,29.526847],"type":"Point"}
}