{
  "type": "Feature",
  "properties": {
    "iso:country":"US",
    "sg:address":"2200 Brazosport Blvd N",
    "sg:city":"Richwood",
    "sg:classifiers":[
        {
            "category":"Wholesale",
            "subcategory":"Machinery & Supplies",
            "type":"Manufacturing & Wholesale Goods"
        }
    ],
    "sg:phone":"+1 979 265 8303",
    "sg:postcode":"77531",
    "sg:province":"TX",
    "sg:tags":[
        "valve"
    ],
    "wof:name":"Mmi",
    "wof:placetype":"venue"
},
  "geometry": {"coordinates":[-95.408858,29.070044],"type":"Point"}
}