{
  "type": "Feature",
  "properties": {
    "iso:country":"US",
    "sg:address":"902 US Hwy 90 Alt",
    "sg:city":"Richmond",
    "sg:classifiers":[
        {
            "category":"Building & Trades",
            "subcategory":"Construction",
            "type":"Services"
        }
    ],
    "sg:phone":"+1 281 239 8667",
    "sg:postcode":"77469",
    "sg:province":"TX",
    "sg:tags":[
        "concrete",
        "contractor"
    ],
    "wof:name":"Tex Star Concrete Co",
    "wof:placetype":"venue"
},
  "geometry": {"coordinates":[-95.765502,29.580627],"type":"Point"}
}