{
  "type": "Feature",
  "properties": {
    "iso:country":"US",
    "sg:address":"155 River North Blvd",
    "sg:city":"Stephenville",
    "sg:classifiers":[
        {
            "category":"Place Of Worship",
            "subcategory":"Church",
            "type":"Public Place"
        },
        {
            "category":"Place Of Worship",
            "type":"Public Place"
        }
    ],
    "sg:phone":"+1 254 968 8580",
    "sg:postcode":"76401",
    "sg:province":"TX",
    "sg:tags":[
        "churches-baptist-general",
        "churches-baptist"
    ],
    "sg:website":"http://www.calvarybaptistchurch.com",
    "wof:name":"Calvary Baptist Church",
    "wof:placetype":"venue"
},
  "geometry": {"coordinates":[-98.232274,32.226248],"type":"Point"}
}