{
  "type": "Feature",
  "properties": {
    "iso:country":"US",
    "sg:address":"19 E Briar Hollow Ln",
    "sg:city":"Houston",
    "sg:phone":"+1 713 255 0035",
    "sg:postcode":"77027",
    "sg:province":"TX",
    "sg:website":"http://centerforaud.com",
    "wof:name":"Center For Audiology",
    "wof:placetype":"venue"
},
  "geometry": {"coordinates":[-95.44868,29.751473],"type":"Point"}
}