{
  "type": "Feature",
  "properties": {
    "iso:country":"US",
    "sg:address":"1721 Pleasant Pl",
    "sg:city":"Arlington",
    "sg:classifiers":[
        {
            "category":"Banks & Credit Unions",
            "subcategory":"Financial Services",
            "type":"Services"
        }
    ],
    "sg:phone":"+1 817 419 7269",
    "sg:postcode":"76015",
    "sg:province":"TX",
    "sg:tags":[
        "investor"
    ],
    "wof:name":"N2 Investments",
    "wof:placetype":"venue"
},
  "geometry": {"coordinates":[-97.135626,32.67797],"type":"Point"}
}