{
  "type": "Feature",
  "properties": {
    "iso:country":"US",
    "sg:address":"8584 Katy Fwy",
    "sg:city":"Houston",
    "sg:classifiers":[
        {
            "category":"Professional",
            "subcategory":"Lawyer & Legal Services",
            "type":"Services"
        }
    ],
    "sg:phone":"+1 713 973 8888",
    "sg:postcode":"77024",
    "sg:province":"TX",
    "sg:tags":[
        "personal",
        "injury"
    ],
    "wof:name":"Wadler Michael R Atty",
    "wof:placetype":"venue"
},
  "geometry": {"coordinates":[-95.49569700000001,29.7836],"type":"Point"}
}