{
  "type": "Feature",
  "properties": {
    "iso:country":"US",
    "sg:address":"9519 Rannock Way",
    "sg:city":"Spring",
    "sg:classifiers":[
        {
            "category":"Food & Beverages",
            "subcategory":"Groceries & Convenience Stores",
            "type":"Retail Goods"
        }
    ],
    "sg:phone":"+1 281 376 1852",
    "sg:postcode":"77379",
    "sg:province":"TX",
    "wof:name":"Artist Market Showroom",
    "wof:placetype":"venue"
},
  "geometry": {"coordinates":[-95.56179899999999,30.017501],"type":"Point"}
}