{
  "type": "Feature",
  "properties": {
    "iso:country":"US",
    "sg:address":"9179 Shadow Creek Ln",
    "sg:city":"Converse",
    "sg:classifiers":[
        {
            "category":"Building & Trades",
            "subcategory":"Landscaping Services",
            "type":"Services"
        }
    ],
    "sg:phone":"+1 210 659 0080",
    "sg:postcode":"78109",
    "sg:province":"TX",
    "sg:tags":[
        "landscape",
        "contractor"
    ],
    "wof:name":"Walker Landscape Management",
    "wof:placetype":"venue"
},
  "geometry": {"coordinates":[-98.304428,29.516564],"type":"Point"}
}