{
  "type": "Feature",
  "properties": {
    "iso:country":"US",
    "sg:address":"610 Willow Oak St",
    "sg:city":"Nacogdoches",
    "sg:classifiers":[
        {
            "category":"Professional",
            "subcategory":"Business Services",
            "type":"Services"
        }
    ],
    "sg:phone":"+1 936 559 9948",
    "sg:postcode":"75964",
    "sg:province":"TX",
    "wof:name":"G&P Enterprises",
    "wof:placetype":"venue"
},
  "geometry": {"coordinates":[-94.681353,31.572251],"type":"Point"}
}