{
  "type": "Feature",
  "properties": {
    "iso:country":"US",
    "sg:address":"3506 Liberty Rd",
    "sg:city":"Houston",
    "sg:classifiers":[
        {
            "category":"Restaurant",
            "type":"Food & Drink"
        }
    ],
    "sg:phone":"+1 713 236 0976",
    "sg:postcode":"77026",
    "sg:province":"TX",
    "wof:name":"Donna Burgers & More",
    "wof:placetype":"venue"
},
  "geometry": {"coordinates":[-95.334295,29.784783],"type":"Point"}
}