{
  "type": "Feature",
  "properties": {
    "iso:country":"US",
    "sg:address":"9207 N Lamar Blvd",
    "sg:city":"Austin",
    "sg:classifiers":[
        {
            "category":"Restaurant",
            "type":"Food & Drink"
        }
    ],
    "sg:phone":"+1 512 845 3926",
    "sg:postcode":"78753",
    "sg:province":"TX",
    "sg:tags":[
        "eating"
    ],
    "wof:name":"Rostell Inc",
    "wof:placetype":"venue"
},
  "geometry": {"coordinates":[-97.696939,30.363011],"type":"Point"}
}