{
  "type": "Feature",
  "properties": {
    "iso:country":"US",
    "sg:address":"2210 Allen Genoa Rd",
    "sg:city":"Houston",
    "sg:classifiers":[
        {
            "category":"Personal",
            "subcategory":"Barber",
            "type":"Services"
        }
    ],
    "sg:phone":"+1 713 910 3332",
    "sg:postcode":"77017",
    "sg:province":"TX",
    "wof:name":"Aly's Beauty Salon",
    "wof:placetype":"venue"
},
  "geometry": {"coordinates":[-95.22663,29.678935],"type":"Point"}
}