{
  "type": "Feature",
  "properties": {
    "iso:country":"US",
    "sg:address":"709 E Main St",
    "sg:city":"Clute",
    "sg:classifiers":[
        {
            "category":"Bars & Pubs",
            "type":"Food & Drink"
        }
    ],
    "sg:phone":"+1 979 265 9856",
    "sg:postcode":"77531",
    "sg:province":"TX",
    "sg:tags":[
        "lounge",
        "drinking",
        "cocktail"
    ],
    "wof:name":"New Gold Star T L P Lounge",
    "wof:placetype":"venue"
},
  "geometry": {"coordinates":[-95.398302,29.0251],"type":"Point"}
}