{
  "type": "Feature",
  "properties": {
    "iso:country":"US",
    "sg:address":"10761 US Hwy 80",
    "sg:city":"Hallsville",
    "sg:classifiers":[
        {
            "category":"Retail",
            "subcategory":"Repair Shop",
            "type":"Services"
        }
    ],
    "sg:phone":"+1 903 660 3421",
    "sg:postcode":"75650",
    "sg:province":"TX",
    "wof:name":"Willams Small Engine Repairs",
    "wof:placetype":"venue"
},
  "geometry": {"coordinates":[-94.51761399999999,32.513595],"type":"Point"}
}