{
  "type": "Feature",
  "properties": {
    "iso:country":"US",
    "sg:address":"11663 Jones Rd Ste D",
    "sg:city":"Houston",
    "sg:classifiers":[
        {
            "category":"Manufacturing",
            "subcategory":"Metals",
            "type":"Manufacturing & Wholesale Goods"
        },
        {
            "category":"Shopping",
            "subcategory":"Hobbies, Toys, & Games",
            "type":"Retail Goods"
        },
        {
            "category":"Shopping",
            "subcategory":"Jewelry",
            "type":"Retail Goods"
        },
        {
            "category":"Manufacturing",
            "subcategory":"Jewelry",
            "type":"Manufacturing & Wholesale Goods"
        }
    ],
    "sg:phone":"+1 713 557 4849",
    "sg:postcode":"77070",
    "sg:province":"TX",
    "sg:tags":[
        "platinum",
        "gold",
        "supply",
        "metals-precious",
        "buyer",
        "coin",
        "silver"
    ],
    "sg:website":"http://www.texasbullionexchange.com",
    "wof:name":"Texas Bullion Exchange",
    "wof:placetype":"venue"
},
  "geometry": {"coordinates":[-95.584934,29.943548],"type":"Point"}
}