{
  "type": "Feature",
  "properties": {
    "iso:country":"US",
    "sg:address":"1235 Coronado Ln",
    "sg:city":"Duncanville",
    "sg:classifiers":[
        {
            "category":"Professional",
            "subcategory":"Business Services",
            "type":"Services"
        }
    ],
    "sg:phone":"+1 972 572 6486",
    "sg:postcode":"75137",
    "sg:province":"TX",
    "wof:name":"Simpson & McCormick Enterprise",
    "wof:placetype":"venue"
},
  "geometry": {"coordinates":[-96.919175,32.639576],"type":"Point"}
}