{
  "type": "Feature",
  "properties": {
    "iso:country":"US",
    "sg:address":"2020 Eastbrook Cir",
    "sg:city":"Mesquite",
    "sg:classifiers":[
        {
            "category":"Real Estate",
            "subcategory":"Developer",
            "type":"Services"
        }
    ],
    "sg:phone":"+1 972 613 5201",
    "sg:postcode":"75150",
    "sg:province":"TX",
    "sg:tags":[
        "cemetery"
    ],
    "wof:name":"Rock Hill Cemetery Assoc",
    "wof:placetype":"venue"
},
  "geometry": {"coordinates":[-96.646869,32.794813],"type":"Point"}
}