{
  "type": "Feature",
  "properties": {
    "iso:country":"US",
    "sg:address":"9221 Westview Dr",
    "sg:city":"Houston",
    "sg:classifiers":[
        {
            "category":"Professional",
            "type":"Services"
        }
    ],
    "sg:phone":"+1 713 722 0142",
    "sg:postcode":"77055",
    "sg:province":"TX",
    "wof:name":"Brian S Henry",
    "wof:placetype":"venue"
},
  "geometry": {"coordinates":[-95.519774,29.793719],"type":"Point"}
}