{
  "type": "Feature",
  "properties": {
    "iso:country":"US",
    "sg:address":"722 S Denton Tap Rd",
    "sg:city":"Coppell",
    "sg:classifiers":[
        {
            "category":"Manufacturing",
            "subcategory":"Printing",
            "type":"Manufacturing & Wholesale Goods"
        }
    ],
    "sg:phone":"+1 972 745 0770",
    "sg:postcode":"75019",
    "sg:province":"TX",
    "sg:tags":[
        "publisher",
        "periodical"
    ],
    "wof:name":"Youth Sports Today",
    "wof:placetype":"venue"
},
  "geometry": {"coordinates":[-96.99351299999999,32.955122],"type":"Point"}
}