{
  "type": "Feature",
  "properties": {
    "iso:country":"US",
    "sg:address":"3527 Oak Lawn Ave",
    "sg:city":"Dallas",
    "sg:classifiers":[
        {
            "category":"Personal",
            "subcategory":"Adult",
            "type":"Services"
        }
    ],
    "sg:phone":"+1 214 720 0008",
    "sg:postcode":"75219",
    "sg:province":"TX",
    "sg:tags":[
        "escort"
    ],
    "wof:name":"Fabulous Forty",
    "wof:placetype":"venue"
},
  "geometry": {"coordinates":[-96.804878,32.81252],"type":"Point"}
}