{
  "type": "Feature",
  "properties": {
    "iso:country":"US",
    "sg:address":"6920 Fall Creek Hwy",
    "sg:city":"Granbury",
    "sg:classifiers":[
        {
            "category":"Building & Trades",
            "subcategory":"Plumbing",
            "type":"Services"
        }
    ],
    "sg:phone":"+1 817 910 9232",
    "sg:postcode":"76049",
    "sg:province":"TX",
    "wof:name":"Crisp Firespinklers",
    "wof:placetype":"venue"
},
  "geometry": {"coordinates":[-97.666308,32.402457],"type":"Point"}
}