{
  "type": "Feature",
  "properties": {
    "iso:country":"US",
    "sg:address":"123 Wallace Blvd",
    "sg:city":"Cameron",
    "sg:classifiers":[
        {
            "category":"Wholesale",
            "subcategory":"Durable Goods & Equipment",
            "type":"Manufacturing & Wholesale Goods"
        }
    ],
    "sg:phone":"+1 254 697 4382",
    "sg:postcode":"76520",
    "sg:province":"TX",
    "wof:name":"Texas Classic",
    "wof:placetype":"venue"
},
  "geometry": {"coordinates":[-96.95983699999999,30.856509],"type":"Point"}
}