{
  "type": "Feature",
  "properties": {
    "iso:country":"US",
    "sg:address":"3676 Jensen Dr",
    "sg:city":"Houston",
    "sg:classifiers":[
        {
            "category":"Wholesale",
            "subcategory":"Scrap",
            "type":"Manufacturing & Wholesale Goods"
        }
    ],
    "sg:phone":"+1 713 227 1387",
    "sg:postcode":"77026",
    "sg:province":"TX",
    "sg:tags":[
        "metal",
        "iron"
    ],
    "wof:name":"Armando's Scrap Metal",
    "wof:placetype":"venue"
},
  "geometry": {"coordinates":[-95.34218799999999,29.800276],"type":"Point"}
}