{
  "type": "Feature",
  "properties": {
    "iso:country":"US",
    "sg:address":"3321 Towerwood Dr",
    "sg:city":"Farmers Branch",
    "sg:classifiers":[
        {
            "category":"Wholesale",
            "subcategory":"Machinery & Supplies",
            "type":"Manufacturing & Wholesale Goods"
        }
    ],
    "sg:phone":"+1 972 484 1861",
    "sg:postcode":"75234",
    "sg:province":"TX",
    "sg:tags":[
        "machine",
        "tool"
    ],
    "wof:name":"Knight's Machine Tools & Gages",
    "wof:placetype":"venue"
},
  "geometry": {"coordinates":[-96.868014,32.951626],"type":"Point"}
}