{
  "type": "Feature",
  "properties": {
    "iso:country":"US",
    "sg:address":"5655 Beechnut St",
    "sg:city":"Houston",
    "sg:classifiers":[
        {
            "category":"Shopping",
            "subcategory":"Computers & Home Electronics",
            "type":"Retail Goods"
        }
    ],
    "sg:phone":"+1 713 779 1327",
    "sg:postcode":"77096",
    "sg:province":"TX",
    "wof:name":"Radio Shack",
    "wof:placetype":"venue"
},
  "geometry": {"coordinates":[-95.491013,29.688351],"type":"Point"}
}