{
  "type": "Feature",
  "properties": {
    "iso:country":"US",
    "sg:address":"3950 Grimes Rd",
    "sg:city":"Irving",
    "sg:classifiers":[
        {
            "category":"Organizations",
            "subcategory":"Religious Organization",
            "type":"Services"
        }
    ],
    "sg:phone":"+1 972 790 6700",
    "sg:postcode":"75061",
    "sg:province":"TX",
    "sg:tags":[
        "church"
    ],
    "wof:name":"New Home Baptist Church",
    "wof:placetype":"venue"
},
  "geometry": {"coordinates":[-97.002178,32.825107],"type":"Point"}
}