{
  "type": "Feature",
  "properties": {
    "iso:country":"US",
    "sg:address":"2800 Polk St",
    "sg:city":"Houston",
    "sg:classifiers":[
        {
            "category":"Local Transit",
            "type":"Transportation"
        }
    ],
    "sg:phone":"+1 713 224 0850",
    "sg:postcode":"77003",
    "sg:province":"TX",
    "sg:tags":[
        "line"
    ],
    "wof:name":"First Transit Inc",
    "wof:placetype":"venue"
},
  "geometry": {"coordinates":[-95.350414,29.744902],"type":"Point"}
}