{
  "type": "Feature",
  "properties": {
    "iso:country":"US",
    "sg:address":"7846 Gholson Rd",
    "sg:city":"Waco",
    "sg:classifiers":[
        {
            "category":"Professional",
            "subcategory":"Advertising",
            "type":"Services"
        }
    ],
    "sg:phone":"+1 254 829 0373",
    "sg:postcode":"76705",
    "sg:province":"TX",
    "wof:name":"Stamp Works",
    "wof:placetype":"venue"
},
  "geometry": {"coordinates":[-97.144778,31.662179],"type":"Point"}
}