{
  "type": "Feature",
  "properties": {
    "iso:country":"US",
    "sg:address":"700 N 9th St",
    "sg:city":"Ballinger",
    "sg:classifiers":[
        {
            "category":"Home & Garden",
            "subcategory":"Home Furnishings",
            "type":"Retail Goods"
        }
    ],
    "sg:phone":"+1 325 365 3567",
    "sg:postcode":"76821",
    "sg:province":"TX",
    "sg:tags":[
        "lighting",
        "fixture"
    ],
    "wof:name":"Ideal Lighting",
    "wof:placetype":"venue"
},
  "geometry": {"coordinates":[-99.95533500000001,31.742345],"type":"Point"}
}