{
  "type": "Feature",
  "properties": {
    "iso:country":"US",
    "sg:address":"4216 Hildring Dr W",
    "sg:city":"Fort Worth",
    "sg:classifiers":[
        {
            "category":"Education",
            "subcategory":"Special Training",
            "type":"Public Place"
        }
    ],
    "sg:phone":"+1 817 923 6747",
    "sg:postcode":"76109",
    "sg:province":"TX",
    "sg:tags":[
        "educational"
    ],
    "wof:name":"Proctor Ed Dgn Ofc",
    "wof:placetype":"venue"
},
  "geometry": {"coordinates":[-97.38477,32.685395],"type":"Point"}
}