{
  "type": "Feature",
  "properties": {
    "iso:country":"US",
    "sg:address":"2906 Algie St",
    "sg:city":"Victoria",
    "sg:classifiers":[
        {
            "category":"Professional",
            "subcategory":"Business Services",
            "type":"Services"
        }
    ],
    "sg:phone":"+1 361 573 2762",
    "sg:postcode":"77901",
    "sg:province":"TX",
    "wof:name":"Reds Decor",
    "wof:placetype":"venue"
},
  "geometry": {"coordinates":[-96.975898,28.782086],"type":"Point"}
}