{
  "type": "Feature",
  "properties": {
    "iso:country":"US",
    "sg:address":"1201 W Sherer St",
    "sg:city":"Fort Stockton",
    "sg:classifiers":[
        {
            "category":"Government",
            "subcategory":"Office",
            "type":"Public Place"
        }
    ],
    "sg:phone":"+1 432 336 4617",
    "sg:postcode":"79735",
    "sg:province":"TX",
    "sg:tags":[
        "village"
    ],
    "wof:name":"Fort Stockton City Office",
    "wof:placetype":"venue"
},
  "geometry": {"coordinates":[-102.89130299999999,30.880568],"type":"Point"}
}