{
  "type": "Feature",
  "properties": {
    "iso:country":"US",
    "sg:address":"818 Richcrest Dr",
    "sg:city":"Houston",
    "sg:classifiers":[
        {
            "category":"Real Estate",
            "subcategory":"Real Estate Operator",
            "type":"Services"
        }
    ],
    "sg:phone":"+1 281 876 3666",
    "sg:postcode":"77060",
    "sg:province":"TX",
    "sg:tags":[
        "building",
        "apartment"
    ],
    "wof:name":"C N C Investments",
    "wof:placetype":"venue"
},
  "geometry": {"coordinates":[-95.393473,29.955074],"type":"Point"}
}