{
  "type": "Feature",
  "properties": {
    "iso:country":"US",
    "sg:address":"1603 E Fordyce Ave",
    "sg:city":"Kingsville",
    "sg:classifiers":[
        {
            "category":"Professional",
            "type":"Services"
        }
    ],
    "sg:phone":"+1 361 592 1700",
    "sg:postcode":"78363",
    "sg:province":"TX",
    "sg:tags":[
        "establishment"
    ],
    "wof:name":"Corner Depot",
    "wof:placetype":"venue"
},
  "geometry": {"coordinates":[-97.84587999999999,27.512397],"type":"Point"}
}