{
  "type": "Feature",
  "properties": {
    "iso:country":"US",
    "sg:address":"111 Nelson St",
    "sg:city":"Yoakum",
    "sg:classifiers":[
        {
            "category":"Utilities",
            "subcategory":"Natural Gas",
            "type":"Services"
        }
    ],
    "sg:phone":"+1 361 293 3331",
    "sg:postcode":"77995",
    "sg:province":"TX",
    "sg:tags":[
        "company"
    ],
    "sg:website":"www.sug.com",
    "wof:name":"Texas Gas Svc",
    "wof:placetype":"venue"
},
  "geometry": {"coordinates":[-97.149852,29.291447],"type":"Point"}
}