{
  "type": "Feature",
  "properties": {
    "iso:country":"US",
    "sg:address":"14175 Proton Rd",
    "sg:city":"Dallas",
    "sg:classifiers":[
        {
            "category":"Real Estate",
            "subcategory":"Real Estate Agent",
            "type":"Services"
        }
    ],
    "sg:phone":"+1 972 233 5700",
    "sg:postcode":"75244",
    "sg:province":"TX",
    "wof:name":"Inventek",
    "wof:placetype":"venue"
},
  "geometry": {"coordinates":[-96.838382,32.945837],"type":"Point"}
}