{
  "type": "Feature",
  "properties": {
    "iso:country":"US",
    "sg:address":"5320 W Parkway St",
    "sg:city":"Groves",
    "sg:classifiers":[
        {
            "category":"Building & Trades",
            "subcategory":"Construction",
            "type":"Services"
        }
    ],
    "sg:phone":"+1 409 548 0788",
    "sg:postcode":"77619",
    "sg:province":"TX",
    "sg:tags":[
        "wallcoverings-installation",
        "wallpaper",
        "painting",
        "contractor"
    ],
    "wof:name":"Gonzo's Custom Paint & Body",
    "wof:placetype":"venue"
},
  "geometry": {"coordinates":[-93.92721,29.938987],"type":"Point"}
}