{
  "type": "Feature",
  "properties": {
    "iso:country":"US",
    "sg:address":"202 W Beauregard Ave",
    "sg:city":"San Angelo",
    "sg:classifiers":[
        {
            "category":"Professional",
            "subcategory":"Lawyer & Legal Services",
            "type":"Services"
        }
    ],
    "sg:phone":"+1 325 659 6628",
    "sg:postcode":"76903",
    "sg:province":"TX",
    "wof:name":"Motl Terri H Attorney At Law",
    "wof:placetype":"venue"
},
  "geometry": {"coordinates":[-100.442148,31.460947],"type":"Point"}
}