{
  "type": "Feature",
  "properties": {
    "iso:country":"US",
    "sg:address":"7800 Mockingbird Ln",
    "sg:city":"N Richland Hills",
    "sg:classifiers":[
        {
            "category":"Organizations",
            "subcategory":"Community Association",
            "type":"Services"
        }
    ],
    "sg:phone":"+1 817 503 7272",
    "sg:postcode":"76180",
    "sg:province":"TX",
    "sg:tags":[
        "fraternal"
    ],
    "wof:name":"Grand Lodge Knights Of Pythias",
    "wof:placetype":"venue"
},
  "geometry": {"coordinates":[-97.211614,32.85168],"type":"Point"}
}