{
  "type": "Feature",
  "properties": {
    "iso:country":"US",
    "sg:address":"502 W Calton Rd",
    "sg:city":"Laredo",
    "sg:classifiers":[
        {
            "category":"Banks & Credit Unions",
            "subcategory":"Bank",
            "type":"Services"
        }
    ],
    "sg:phone":"+1 956 712 0882",
    "sg:postcode":"78041",
    "sg:province":"TX",
    "sg:tags":[
        "federal",
        "agency"
    ],
    "wof:name":"Beneficial",
    "wof:placetype":"venue"
},
  "geometry": {"coordinates":[-99.498909,27.543631],"type":"Point"}
}