{
  "type": "Feature",
  "properties": {
    "iso:country":"US",
    "sg:address":"5921 E Sam Houston Pkwy N",
    "sg:city":"Houston",
    "sg:classifiers":[
        {
            "category":"Restaurant",
            "type":"Food & Drink"
        }
    ],
    "sg:menulink":"http://www.allmenus.com/tx/houston/49036-johnny-carinos-country-italian/menu/",
    "sg:phone":"+1 281 458 4424",
    "sg:postcode":"77049",
    "sg:province":"TX",
    "sg:tags":[
        "italian"
    ],
    "wof:name":"Johnny Carino's Country Italian",
    "wof:placetype":"venue"
},
  "geometry": {"coordinates":[-95.16394099999999,29.810177],"type":"Point"}
}