{
  "type": "Feature",
  "properties": {
    "iso:country":"US",
    "sg:address":"3755 Walnut Hill Ln",
    "sg:city":"Dallas",
    "sg:classifiers":[
        {
            "category":"Organizations",
            "subcategory":"Religious Organization",
            "type":"Services"
        }
    ],
    "sg:phone":"+1 214 350 2104",
    "sg:postcode":"75229",
    "sg:province":"TX",
    "wof:name":"Saints Cnstntine Hlen Antchian",
    "wof:placetype":"venue"
},
  "geometry": {"coordinates":[-96.85613600000001,32.880381],"type":"Point"}
}