{
  "type": "Feature",
  "properties": {
    "iso:country":"US",
    "sg:address":"3825 Woodvalley Dr",
    "sg:city":"Houston",
    "sg:classifiers":[
        {
            "category":"Food & Beverages",
            "subcategory":"Meat & Fish",
            "type":"Retail Goods"
        }
    ],
    "sg:phone":"+1 713 661 6102",
    "sg:postcode":"77025",
    "sg:province":"TX",
    "sg:tags":[
        "seafood",
        "market"
    ],
    "wof:name":"J & J Fish Market",
    "wof:placetype":"venue"
},
  "geometry": {"coordinates":[-95.439201,29.680201],"type":"Point"}
}