{
  "type": "Feature",
  "properties": {
    "iso:country":"US",
    "sg:address":"8001 Beardsley Cove",
    "sg:city":"Austin",
    "sg:classifiers":[
        {
            "category":"Professional",
            "subcategory":"Art Services",
            "type":"Services"
        }
    ],
    "sg:phone":"+1 512 306 1455",
    "sg:postcode":"78746",
    "sg:province":"TX",
    "sg:tags":[
        "commercial",
        "design",
        "business"
    ],
    "wof:name":"Grid Design",
    "wof:placetype":"venue"
},
  "geometry": {"coordinates":[-97.851777,30.309033],"type":"Point"}
}