{
  "type": "Feature",
  "properties": {
    "iso:country":"US",
    "sg:address":"615 W Mansfield Hwy",
    "sg:city":"Kennedale",
    "sg:classifiers":[
        {
            "category":"Building & Trades",
            "subcategory":"Construction",
            "type":"Services"
        }
    ],
    "sg:phone":"+1 817 516 8190",
    "sg:postcode":"76060",
    "sg:province":"TX",
    "sg:tags":[
        "pipe",
        "line",
        "contractor"
    ],
    "sg:website":"www.driverpipeline.com",
    "wof:name":"Driver Pipeline",
    "wof:placetype":"venue"
},
  "geometry": {"coordinates":[-97.23044299999999,32.655217],"type":"Point"}
}