{
  "type": "Feature",
  "properties": {
    "iso:country":"US",
    "sg:address":"11915 Medicine Bow Cir",
    "sg:city":"Houston",
    "sg:classifiers":[
        {
            "category":"Retail",
            "subcategory":"Repair Shop",
            "type":"Services"
        }
    ],
    "sg:phone":"+1 281 583 7707",
    "sg:postcode":"77067",
    "sg:province":"TX",
    "sg:tags":[
        "machine",
        "tool",
        "boards",
        "circuit"
    ],
    "wof:name":"B & B Electronics",
    "wof:placetype":"venue"
},
  "geometry": {"coordinates":[-95.46805000000001,29.96152],"type":"Point"}
}