{
  "type": "Feature",
  "properties": {
    "iso:country":"US",
    "sg:address":"8383 Commerce Park Dr Ste 604",
    "sg:city":"Houston",
    "sg:classifiers":[
        {
            "category":"Communications",
            "type":"Services"
        }
    ],
    "sg:phone":"+1 713 777 9975",
    "sg:postcode":"77036",
    "sg:province":"TX",
    "sg:tags":[
        "recording",
        "rehearsal",
        "studio"
    ],
    "wof:name":"Creative Sound Productions Inc",
    "wof:placetype":"venue"
},
  "geometry": {"coordinates":[-95.53630099999999,29.6884],"type":"Point"}
}