{
  "type": "Feature",
  "properties": {
    "iso:country":"US",
    "sg:address":"519 Co Rd 138",
    "sg:city":"Gainesville",
    "sg:classifiers":[
        {
            "category":"Retail",
            "subcategory":"Portrait Studio",
            "type":"Services"
        }
    ],
    "sg:phone":"+1 940 668 1422",
    "sg:postcode":"76240",
    "sg:province":"TX",
    "sg:tags":[
        "photographer"
    ],
    "sg:website":"www.garnerstudio.net",
    "wof:name":"Garner Studio",
    "wof:placetype":"venue"
},
  "geometry": {"coordinates":[-97.074726,33.658469],"type":"Point"}
}