{
  "type": "Feature",
  "properties": {
    "iso:country":"US",
    "sg:address":"2416 N Preston St",
    "sg:city":"Ennis",
    "sg:classifiers":[
        {
            "category":"Wholesale",
            "subcategory":"Hardware",
            "type":"Manufacturing & Wholesale Goods"
        }
    ],
    "sg:phone":"+1 972 878 0040",
    "sg:postcode":"75119",
    "sg:province":"TX",
    "sg:tags":[
        "refrigerating"
    ],
    "wof:name":"WEI Cool",
    "wof:placetype":"venue"
},
  "geometry": {"coordinates":[-96.645415,32.347316],"type":"Point"}
}