{
  "type": "Feature",
  "properties": {
    "iso:country":"US",
    "sg:address":"12804 East Fwy",
    "sg:city":"Houston",
    "sg:classifiers":[
        {
            "category":"Personal",
            "subcategory":"Beauty Salon",
            "type":"Services"
        }
    ],
    "sg:phone":"+1 713 451 1590",
    "sg:postcode":"77015",
    "sg:province":"TX",
    "sg:tags":[
        "hair"
    ],
    "wof:name":"De Cache Beauty Salon",
    "wof:placetype":"venue"
},
  "geometry": {"coordinates":[-95.205806,29.770792],"type":"Point"}
}