{
  "type": "Feature",
  "properties": {
    "iso:country":"US",
    "sg:address":"8631 East Fwy",
    "sg:city":"Houston",
    "sg:classifiers":[
        {
            "category":"Building & Trades",
            "subcategory":"Equipment Rental",
            "type":"Services"
        }
    ],
    "sg:phone":"+1 713 671 6100",
    "sg:postcode":"77029",
    "sg:province":"TX",
    "wof:name":"Power Rental Division Stewart",
    "wof:placetype":"venue"
},
  "geometry": {"coordinates":[-95.272355,29.777461],"type":"Point"}
}