{
  "type": "Feature",
  "properties": {
    "iso:country":"US",
    "sg:address":"1300 S Congress Ave",
    "sg:city":"Austin",
    "sg:classifiers":[
        {
            "category":"Coffee & Tea",
            "type":"Food & Drink"
        },
        {
            "category":"Food & Beverages",
            "subcategory":"Bakery",
            "type":"Retail Goods"
        }
    ],
    "sg:phone":"+1 512 444 3800",
    "sg:postcode":"78704",
    "sg:province":"TX",
    "sg:tags":[
        "sandwich"
    ],
    "sg:website":"www.joscoffee.com/",
    "wof:name":"Jo's",
    "wof:placetype":"venue"
},
  "geometry": {"coordinates":[-97.749397,30.2509],"type":"Point"}
}