{
  "type": "Feature",
  "properties": {
    "iso:country":"US",
    "sg:address":"216 Dellwood Dr",
    "sg:city":"San Angelo",
    "sg:classifiers":[
        {
            "category":"Professional",
            "subcategory":"Computer Services",
            "type":"Services"
        }
    ],
    "sg:phone":"+1 325 658 7484",
    "sg:postcode":"76903",
    "sg:province":"TX",
    "sg:website":"www.communications-etc.com",
    "wof:name":"Communications Etc",
    "wof:placetype":"venue"
},
  "geometry": {"coordinates":[-100.41779099999999,31.427464],"type":"Point"}
}