{
  "type": "Feature",
  "properties": {
    "iso:country":"US",
    "sg:address":"4102 Woodlawn Ave Ste 220",
    "sg:city":"Pasadena",
    "sg:classifiers":[
        {
            "category":"Health Services",
            "subcategory":"Doctor",
            "type":"Services"
        }
    ],
    "sg:phone":"+1 713 475 5940",
    "sg:postcode":"77504",
    "sg:province":"TX",
    "wof:name":"Jeroudi Mohamed MD",
    "wof:placetype":"venue"
},
  "geometry": {"coordinates":[-95.18229700000001,29.6602],"type":"Point"}
}