{
  "type": "Feature",
  "properties": {
    "iso:country":"US",
    "sg:address":"949 Frankie St",
    "sg:city":"Houston",
    "sg:classifiers":[
        {
            "category":"Building & Trades",
            "subcategory":"Construction",
            "type":"Services"
        }
    ],
    "sg:phone":"+1 713 455 7820",
    "sg:postcode":"77015",
    "sg:province":"TX",
    "sg:tags":[
        "house"
    ],
    "wof:name":"Easy Remodeling & Construction",
    "wof:placetype":"venue"
},
  "geometry": {"coordinates":[-95.175847,29.777787],"type":"Point"}
}