{
  "type": "Feature",
  "properties": {
    "iso:country":"US",
    "sg:address":"2741 N Stemmons Fwy",
    "sg:city":"Dallas",
    "sg:classifiers":[
        {
            "category":"Restaurant",
            "type":"Food & Drink"
        }
    ],
    "sg:menulink":"http://www.allmenus.com/tx/northeast/157090-whataburger/menu/",
    "sg:phone":"+1 214 630 1210",
    "sg:postcode":"75207",
    "sg:province":"TX",
    "sg:tags":[
        "burger",
        "american"
    ],
    "wof:name":"Whataburger",
    "wof:placetype":"venue"
},
  "geometry": {"coordinates":[-96.845682,32.808807],"type":"Point"}
}