{
  "type": "Feature",
  "properties": {
    "iso:country":"US",
    "sg:address":"1007 Mo-Pac Cir",
    "sg:city":"Austin",
    "sg:classifiers":[
        {
            "category":"Health Services",
            "subcategory":"Health Practitioner",
            "type":"Services"
        }
    ],
    "sg:phone":"+1 512 327 7500",
    "sg:postcode":"78746",
    "sg:province":"TX",
    "wof:name":"Travis Sebera",
    "wof:placetype":"venue"
},
  "geometry": {"coordinates":[-97.78465,30.265562],"type":"Point"}
}