{
  "type": "Feature",
  "properties": {
    "iso:country":"US",
    "sg:address":"6615 Snider Plz",
    "sg:city":"Dallas",
    "sg:classifiers":[
        {
            "category":"Professional",
            "subcategory":"Research",
            "type":"Services"
        }
    ],
    "sg:phone":"+1 214 987 4662",
    "sg:postcode":"75205",
    "sg:province":"TX",
    "sg:tags":[
        "profit",
        "found",
        "raising",
        "cancer",
        "for"
    ],
    "wof:name":"Wipe Out Kids Cancer Inc",
    "wof:placetype":"venue"
},
  "geometry": {"coordinates":[-96.78784,32.84746],"type":"Point"}
}