{
  "type": "Feature",
  "properties": {
    "iso:country":"US",
    "sg:address":"3101 Woodlawn Blvd",
    "sg:city":"Denison",
    "sg:classifiers":[
        {
            "category":"Insurance",
            "subcategory":"Health Insurance",
            "type":"Services"
        }
    ],
    "sg:phone":"+1 903 463 0715",
    "sg:postcode":"75020",
    "sg:province":"TX",
    "sg:tags":[
        "plan"
    ],
    "wof:name":"Trail Blazer Health Entps",
    "wof:placetype":"venue"
},
  "geometry": {"coordinates":[-96.556122,33.724965],"type":"Point"}
}