{
  "type": "Feature",
  "properties": {
    "iso:country":"US",
    "sg:address":"11544 Sandy Loam Trl",
    "sg:city":"Austin",
    "sg:classifiers":[
        {
            "category":"Shopping",
            "subcategory":"Bicycles & Sporting Goods",
            "type":"Retail Goods"
        }
    ],
    "sg:phone":"+1 512 923 6692",
    "sg:postcode":"78750",
    "sg:province":"TX",
    "wof:name":"Discount Fitness Equipmen",
    "wof:placetype":"venue"
},
  "geometry": {"coordinates":[-97.812324,30.44899],"type":"Point"}
}