{
  "type": "Feature",
  "properties": {
    "iso:country":"US",
    "sg:address":"317 Buffalo St",
    "sg:city":"Gilmer",
    "sg:classifiers":[
        {
            "category":"Wholesale",
            "subcategory":"Farm Supplies",
            "type":"Manufacturing & Wholesale Goods"
        },
        {
            "category":"Shopping",
            "subcategory":"Pets & Pet Supplies",
            "type":"Retail Goods"
        }
    ],
    "sg:phone":"+1 903 843 5621",
    "sg:postcode":"75644",
    "sg:province":"TX",
    "sg:tags":[
        "feed",
        "feed-wholesale",
        "supplement",
        "concentrate",
        "manufacturer"
    ],
    "wof:name":"R B Cook & Company",
    "wof:placetype":"venue"
},
  "geometry": {"coordinates":[-94.94653599999999,32.729764],"type":"Point"}
}