{
  "type": "Feature",
  "properties": {
    "iso:country":"US",
    "sg:address":"27221 US Hwy 90",
    "sg:city":"Katy",
    "sg:classifiers":[
        {
            "category":"Professional",
            "subcategory":"Business Services",
            "type":"Services"
        }
    ],
    "sg:phone":"+1 979 885 0761",
    "sg:postcode":"77494",
    "sg:province":"TX",
    "sg:tags":[
        "auctioneer"
    ],
    "wof:name":"Matt Thomas Auctions",
    "wof:placetype":"venue"
},
  "geometry": {"coordinates":[-95.846729,29.785813],"type":"Point"}
}