{
  "type": "Feature",
  "properties": {
    "iso:country":"US",
    "sg:address":"1916 E Abram St",
    "sg:city":"Arlington",
    "sg:classifiers":[
        {
            "category":"Professional",
            "type":"Services"
        }
    ],
    "sg:phone":"+1 817 275 2266",
    "sg:postcode":"76010",
    "sg:province":"TX",
    "wof:name":"NS Lucky Inc",
    "wof:placetype":"venue"
},
  "geometry": {"coordinates":[-97.07783999999999,32.735173],"type":"Point"}
}