{
  "type": "Feature",
  "properties": {
    "iso:country":"US",
    "sg:address":"409 Nolana St",
    "sg:city":"Mcallen",
    "sg:classifiers":[
        {
            "category":"Personal",
            "subcategory":"Beauty Salon",
            "type":"Services"
        }
    ],
    "sg:phone":"+1 956 971 9997",
    "sg:postcode":"78504",
    "sg:province":"TX",
    "sg:tags":[
        "shop"
    ],
    "wof:name":"Le Elegante",
    "wof:placetype":"venue"
},
  "geometry": {"coordinates":[-98.219441,26.238632],"type":"Point"}
}