{
  "type": "Feature",
  "properties": {
    "iso:country":"US",
    "sg:address":"910 S Bell Blvd",
    "sg:city":"Cedar Park",
    "sg:classifiers":[
        {
            "category":"Autos & Motor Vehicles",
            "subcategory":"Automobile Sales",
            "type":"Retail Goods"
        }
    ],
    "sg:phone":"+1 512 335 0000",
    "sg:postcode":"78613",
    "sg:province":"TX",
    "sg:tags":[
        "car",
        "used",
        "dealer"
    ],
    "wof:name":"Austintatious Autos Inc",
    "wof:placetype":"venue"
},
  "geometry": {"coordinates":[-97.81634099999999,30.500668],"type":"Point"}
}