{
  "type": "Feature",
  "properties": {
    "iso:country":"US",
    "sg:address":"427 W 20th St Ste 602",
    "sg:city":"Houston",
    "sg:classifiers":[
        {
            "category":"Health Services",
            "subcategory":"Doctor",
            "type":"Services"
        }
    ],
    "sg:phone":"+1 713 802 1177",
    "sg:postcode":"77008",
    "sg:province":"TX",
    "wof:name":"Pharo Arlette DO",
    "wof:placetype":"venue"
},
  "geometry": {"coordinates":[-95.40419799999999,29.8039],"type":"Point"}
}