{
  "type": "Feature",
  "properties": {
    "iso:country":"US",
    "sg:address":"409 E Corsicana St",
    "sg:city":"Athens",
    "sg:classifiers":[
        {
            "category":"Professional",
            "type":"Services"
        }
    ],
    "sg:phone":"+1 903 677 0705",
    "sg:postcode":"75751",
    "sg:province":"TX",
    "wof:name":"Ricks Gym",
    "wof:placetype":"venue"
},
  "geometry": {"coordinates":[-95.850875,32.204362],"type":"Point"}
}