{
  "type": "Feature",
  "properties": {
    "iso:country":"US",
    "sg:address":"3510 Columbia Blvd",
    "sg:city":"Garland",
    "sg:classifiers":[
        {
            "category":"Wholesale",
            "subcategory":"Machinery & Supplies",
            "type":"Manufacturing & Wholesale Goods"
        }
    ],
    "sg:phone":"+1 972 864 2324",
    "sg:postcode":"75043",
    "sg:province":"TX",
    "sg:tags":[
        "equipment",
        "establishment"
    ],
    "wof:name":"A A A Janitorial Sups & Eqp",
    "wof:placetype":"venue"
},
  "geometry": {"coordinates":[-96.624258,32.8731],"type":"Point"}
}