{
  "type": "Feature",
  "properties": {
    "iso:country":"US",
    "sg:address":"2418 S Main St",
    "sg:city":"Pearland",
    "sg:classifiers":[
        {
            "category":"Real Estate",
            "subcategory":"Real Estate Services",
            "type":"Services"
        },
        {
            "category":"Banks & Credit Unions",
            "subcategory":"Financial Services",
            "type":"Services"
        }
    ],
    "sg:phone":"+1 281 485 6353",
    "sg:postcode":"77581",
    "sg:province":"TX",
    "sg:tags":[
        "loan",
        "processing"
    ],
    "wof:name":"Absolute Mortgage Co",
    "wof:placetype":"venue"
},
  "geometry": {"coordinates":[-95.28609400000001,29.563351],"type":"Point"}
}