{
  "type": "Feature",
  "properties": {
    "iso:country":"US",
    "sg:address":"10710 Research Blvd Ste 126",
    "sg:city":"Austin",
    "sg:classifiers":[
        {
            "category":"Restaurant",
            "type":"Food & Drink"
        }
    ],
    "sg:phone":"+1 512 342 2252",
    "sg:postcode":"78759",
    "sg:province":"TX",
    "sg:tags":[
        "pakistani",
        "indian",
        "buffet"
    ],
    "sg:website":"www.bombay-bistro.com/",
    "wof:name":"Bombay Bistro",
    "wof:placetype":"venue"
},
  "geometry": {"coordinates":[-97.748034,30.398914],"type":"Point"}
}