{
  "type": "Feature",
  "properties": {
    "iso:country":"US",
    "sg:address":"502 E Gaston Dr",
    "sg:city":"Wylie",
    "sg:classifiers":[
        {
            "category":"Personal",
            "type":"Services"
        }
    ],
    "sg:phone":"+1 972 814 2768",
    "sg:postcode":"75098",
    "sg:province":"TX",
    "sg:tags":[
        "butlers'",
        "maids'"
    ],
    "wof:name":"Trinity Maids",
    "wof:placetype":"venue"
},
  "geometry": {"coordinates":[-96.54476200000001,33.02478],"type":"Point"}
}