{
  "type": "Feature",
  "properties": {
    "iso:country":"US",
    "sg:address":"222 Matthew Ln",
    "sg:city":"Georgetown",
    "sg:classifiers":[
        {
            "category":"Building & Trades",
            "subcategory":"Landscaping Services",
            "type":"Services"
        }
    ],
    "sg:phone":"+1 512 868 0350",
    "sg:postcode":"78626",
    "sg:province":"TX",
    "wof:name":"Gonzalez Landscaping",
    "wof:placetype":"venue"
},
  "geometry": {"coordinates":[-97.61911000000001,30.601733],"type":"Point"}
}