{
  "type": "Feature",
  "properties": {
    "iso:country":"US",
    "sg:address":"1518 Brittmoore Rd",
    "sg:city":"Houston",
    "sg:classifiers":[
        {
            "category":"Food & Beverages",
            "subcategory":"Groceries & Convenience Stores",
            "type":"Retail Goods"
        }
    ],
    "sg:phone":"+1 713 464 9002",
    "sg:postcode":"77043",
    "sg:province":"TX",
    "sg:tags":[
        "station",
        "gasoline"
    ],
    "wof:name":"Quality Food",
    "wof:placetype":"venue"
},
  "geometry": {"coordinates":[-95.569793,29.801869],"type":"Point"}
}