{
  "type": "Feature",
  "properties": {
    "iso:country":"US",
    "sg:address":"9215 Esplanade Dr",
    "sg:city":"Dallas",
    "sg:classifiers":[
        {
            "category":"Shopping",
            "subcategory":"Used Merchandise",
            "type":"Retail Goods"
        }
    ],
    "sg:phone":"+1 214 956 7070",
    "sg:postcode":"75220",
    "sg:province":"TX",
    "wof:name":"Lareine Abeille Antiques & App",
    "wof:placetype":"venue"
},
  "geometry": {"coordinates":[-96.841229,32.864094],"type":"Point"}
}