{
  "type": "Feature",
  "properties": {
    "iso:country":"US",
    "sg:address":"811 Barton Springs Rd",
    "sg:city":"Austin",
    "sg:classifiers":[
        {
            "category":"Professional",
            "subcategory":"Employment Agencies",
            "type":"Services"
        }
    ],
    "sg:phone":"+1 512 474 1545",
    "sg:postcode":"78704",
    "sg:province":"TX",
    "sg:tags":[
        "temporary",
        "help"
    ],
    "wof:name":"Kelly Services",
    "wof:placetype":"venue"
},
  "geometry": {"coordinates":[-97.751431,30.258667],"type":"Point"}
}