{
  "type": "Feature",
  "properties": {
    "iso:country":"US",
    "sg:address":"3917 Felisa Pl",
    "sg:city":"Fort Worth",
    "sg:classifiers":[
        {
            "category":"Professional",
            "subcategory":"Computer Services",
            "type":"Services"
        }
    ],
    "sg:phone":"+1 817 346 3301",
    "sg:postcode":"76133",
    "sg:province":"TX",
    "sg:tags":[
        "development",
        "educational",
        "software"
    ],
    "wof:name":"4 Monkeys LLC",
    "wof:placetype":"venue"
},
  "geometry": {"coordinates":[-97.37850400000001,32.644927],"type":"Point"}
}