{
  "type": "Feature",
  "properties": {
    "iso:country":"US",
    "sg:address":"12615 Fern Creek Trl",
    "sg:city":"Humble",
    "sg:classifiers":[
        {
            "category":"Professional",
            "type":"Services"
        }
    ],
    "sg:phone":"+1 281 812 9949",
    "sg:postcode":"77346",
    "sg:province":"TX",
    "wof:name":"Get Organized",
    "wof:placetype":"venue"
},
  "geometry": {"coordinates":[-95.183223,29.986078],"type":"Point"}
}