{
  "type": "Feature",
  "properties": {
    "iso:country":"US",
    "sg:address":"1060 Doniphan Park Cir",
    "sg:city":"El Paso",
    "sg:classifiers":[
        {
            "category":"Sports & Exercise",
            "subcategory":"Gym",
            "type":"Entertainment"
        }
    ],
    "sg:phone":"+1 915 581 5518",
    "sg:postcode":"79922",
    "sg:province":"TX",
    "sg:tags":[
        "club",
        "health",
        "studio",
        "gymnasium"
    ],
    "wof:name":"Certified Personal Fitness",
    "wof:placetype":"venue"
},
  "geometry": {"coordinates":[-106.557506,31.814463],"type":"Point"}
}