{
  "type": "Feature",
  "properties": {
    "iso:country":"US",
    "sg:address":"40 Pinehurst",
    "sg:city":"Abilene",
    "sg:classifiers":[
        {
            "category":"Shopping",
            "subcategory":"Clothing, Apparel, & Fashions",
            "type":"Retail Goods"
        }
    ],
    "sg:phone":"+1 325 698 0848",
    "sg:postcode":"79606",
    "sg:province":"TX",
    "sg:tags":[
        "accessory"
    ],
    "wof:name":"Diane Jones LTD",
    "wof:placetype":"venue"
},
  "geometry": {"coordinates":[-99.75604300000001,32.373147],"type":"Point"}
}