{
  "type": "Feature",
  "properties": {
    "iso:country":"US",
    "sg:address":"4350 Koppe Bridge Rd",
    "sg:city":"College Station",
    "sg:classifiers":[
        {
            "category":"Building & Trades",
            "subcategory":"Construction",
            "type":"Services"
        }
    ],
    "sg:phone":"+1 979 690 7136",
    "sg:postcode":"77845",
    "sg:province":"TX",
    "sg:tags":[
        "residential",
        "contractor"
    ],
    "wof:name":"Northcutt Construction",
    "wof:placetype":"venue"
},
  "geometry": {"coordinates":[-96.301939,30.53185],"type":"Point"}
}