{
  "type": "Feature",
  "properties": {
    "iso:country":"US",
    "sg:address":"3401 N Ben Jordan St",
    "sg:city":"Victoria",
    "sg:classifiers":[
        {
            "category":"Organizations",
            "subcategory":"Religious Organization",
            "type":"Services"
        }
    ],
    "sg:phone":"+1 361 575 8235",
    "sg:postcode":"77901",
    "sg:province":"TX",
    "sg:tags":[
        "church"
    ],
    "sg:website":"www.fbcvic.org",
    "wof:name":"Fellowship Bible Church",
    "wof:placetype":"venue"
},
  "geometry": {"coordinates":[-96.98389299999999,28.824147],"type":"Point"}
}