{
  "type": "Feature",
  "properties": {
    "iso:country":"US",
    "sg:address":"3919 Kendall Ln",
    "sg:city":"Waco",
    "sg:classifiers":[
        {
            "category":"Personal",
            "subcategory":"Beauty Salon",
            "type":"Services"
        }
    ],
    "sg:phone":"+1 254 799 3431",
    "sg:postcode":"76705",
    "sg:province":"TX",
    "sg:tags":[
        "shop"
    ],
    "wof:name":"Looking Good",
    "wof:placetype":"venue"
},
  "geometry": {"coordinates":[-97.07883699999999,31.571443],"type":"Point"}
}