{
  "type": "Feature",
  "properties": {
    "iso:country":"US",
    "sg:address":"210 W 6th St",
    "sg:city":"Fort Worth",
    "sg:classifiers":[
        {
            "category":"Professional",
            "subcategory":"Lawyer & Legal Services",
            "type":"Services"
        }
    ],
    "sg:phone":"+1 817 335 2208",
    "sg:postcode":"76102",
    "sg:province":"TX",
    "sg:tags":[
        "attorney"
    ],
    "sg:website":"www.lawbms.com",
    "wof:name":"Bakutis McCully & Sawyer PC",
    "wof:placetype":"venue"
},
  "geometry": {"coordinates":[-97.33179800000001,32.752566],"type":"Point"}
}