{
  "type": "Feature",
  "properties": {
    "iso:country":"US",
    "sg:address":"46 N Longspur Dr",
    "sg:city":"Spring",
    "sg:classifiers":[
        {
            "category":"Retail",
            "subcategory":"Auto Repair",
            "type":"Services"
        }
    ],
    "sg:phone":"+1 281 298 6270",
    "sg:postcode":"77380",
    "sg:province":"TX",
    "sg:tags":[
        "general"
    ],
    "wof:name":"Holcombe Auto Service LLC",
    "wof:placetype":"venue"
},
  "geometry": {"coordinates":[-95.480968,30.125927],"type":"Point"}
}