{
  "type": "Feature",
  "properties": {
    "iso:country":"US",
    "sg:address":"434 E Hwy 199",
    "sg:city":"Springtown",
    "sg:classifiers":[
        {
            "category":"Health Services",
            "subcategory":"Doctor",
            "type":"Services"
        }
    ],
    "sg:phone":"+1 817 523 5963",
    "sg:postcode":"76082",
    "sg:province":"TX",
    "sg:tags":[
        "dentist"
    ],
    "wof:name":"Springtown Family Dental",
    "wof:placetype":"venue"
},
  "geometry": {"coordinates":[-97.676271,32.961296],"type":"Point"}
}