{
  "type": "Feature",
  "properties": {
    "iso:country":"US",
    "sg:address":"2204 US Hwy 90",
    "sg:city":"Del Rio",
    "sg:classifiers":[
        {
            "category":"Restaurant",
            "type":"Food & Drink"
        }
    ],
    "sg:phone":"+1 830 775 0833",
    "sg:postcode":"78840",
    "sg:province":"TX",
    "sg:tags":[
        "eating"
    ],
    "wof:name":"Burger King",
    "wof:placetype":"venue"
},
  "geometry": {"coordinates":[-100.905424,29.388616],"type":"Point"}
}