{
  "type": "Feature",
  "properties": {
    "iso:country":"US",
    "sg:address":"1102 Fm 1585",
    "sg:city":"Lubbock",
    "sg:classifiers":[
        {
            "category":"Fast Food",
            "type":"Food & Drink"
        },
        {
            "category":"Restaurant",
            "type":"Food & Drink"
        }
    ],
    "sg:phone":"+1 806 745 3515",
    "sg:postcode":"79423",
    "sg:province":"TX",
    "sg:tags":[
        "take"
    ],
    "wof:name":"Cooper's Drivee-In",
    "wof:placetype":"venue"
},
  "geometry": {"coordinates":[-101.84717000000001,33.476276],"type":"Point"}
}