{
  "type": "Feature",
  "properties": {
    "iso:country":"US",
    "sg:address":"1145 Clear Lake City Blvd",
    "sg:city":"Houston",
    "sg:classifiers":[
        {
            "category":"Personal",
            "subcategory":"Beauty Salon",
            "type":"Services"
        }
    ],
    "sg:phone":"+1 281 286 1080",
    "sg:postcode":"77062",
    "sg:province":"TX",
    "sg:tags":[
        "manicuring"
    ],
    "wof:name":"L C Nails",
    "wof:placetype":"venue"
},
  "geometry": {"coordinates":[-95.156845,29.580817],"type":"Point"}
}