{
  "type": "Feature",
  "properties": {
    "iso:country":"US",
    "sg:address":"16 Jamison St",
    "sg:city":"Dayton",
    "sg:classifiers":[
        {
            "category":"Farming",
            "subcategory":"Farm",
            "type":"Manufacturing & Wholesale Goods"
        }
    ],
    "sg:phone":"+1 936 258 2389",
    "sg:postcode":"77535",
    "sg:province":"TX",
    "sg:tags":[
        "crop",
        "general"
    ],
    "wof:name":"Reidland & Guthrie Inc",
    "wof:placetype":"venue"
},
  "geometry": {"coordinates":[-94.898787,30.066351],"type":"Point"}
}