{
  "type": "Feature",
  "properties": {
    "iso:country":"US",
    "sg:address":"239 Overbluff St",
    "sg:city":"Channelview",
    "sg:classifiers":[
        {
            "category":"Building & Trades",
            "subcategory":"Plumbing",
            "type":"Services"
        }
    ],
    "sg:phone":"+1 281 452 2372",
    "sg:postcode":"77530",
    "sg:province":"TX",
    "sg:tags":[
        "conditioning",
        "air",
        "system",
        "contractor"
    ],
    "wof:name":"Lyons Air Conditioning",
    "wof:placetype":"venue"
},
  "geometry": {"coordinates":[-95.15526800000001,29.775848],"type":"Point"}
}