{
  "type": "Feature",
  "properties": {
    "iso:country":"US",
    "sg:address":"409 Skyforest Dr",
    "sg:city":"San Antonio",
    "sg:classifiers":[
        {
            "category":"Building & Trades",
            "subcategory":"Construction",
            "type":"Services"
        }
    ],
    "sg:phone":"+1 210 494 3050",
    "sg:postcode":"78232",
    "sg:province":"TX",
    "sg:tags":[
        "house"
    ],
    "wof:name":"Design Builders",
    "wof:placetype":"venue"
},
  "geometry": {"coordinates":[-98.494873,29.598565],"type":"Point"}
}