{
  "type": "Feature",
  "properties": {
    "iso:country":"US",
    "sg:address":"2500 N 1st St",
    "sg:city":"Abilene",
    "sg:classifiers":[
        {
            "category":"Banks & Credit Unions",
            "subcategory":"Bank",
            "type":"Services"
        }
    ],
    "sg:phone":"+1 325 674 9993",
    "sg:postcode":"79603",
    "sg:province":"TX",
    "sg:tags":[
        "loan"
    ],
    "wof:name":"Jaestar Auto",
    "wof:placetype":"venue"
},
  "geometry": {"coordinates":[-99.75382999999999,32.450655],"type":"Point"}
}