{
  "type": "Feature",
  "properties": {
    "iso:country":"US",
    "sg:address":"611 Brook Hollow Dr",
    "sg:city":"Conroe",
    "sg:classifiers":[
        {
            "category":"Professional",
            "subcategory":"Computer Services",
            "type":"Services"
        }
    ],
    "sg:phone":"+1 936 271 4508",
    "sg:postcode":"77385",
    "sg:province":"TX",
    "sg:tags":[
        "design",
        "system"
    ],
    "wof:name":"Lansdowne Web Design",
    "wof:placetype":"venue"
},
  "geometry": {"coordinates":[-95.445185,30.230416],"type":"Point"}
}