{
  "type": "Feature",
  "properties": {
    "iso:country":"US",
    "sg:address":"170 de Chantle Rd",
    "sg:city":"San Antonio",
    "sg:classifiers":[
        {
            "category":"Real Estate",
            "subcategory":"Real Estate Agent",
            "type":"Services"
        }
    ],
    "sg:phone":"+1 210 732 8021",
    "sg:postcode":"78201",
    "sg:province":"TX",
    "wof:name":"Villa Bordeaux Condominiums",
    "wof:placetype":"venue"
},
  "geometry": {"coordinates":[-98.542497,29.479332],"type":"Point"}
}