{
  "type": "Feature",
  "properties": {
    "iso:country":"US",
    "sg:address":"426 S 8th St",
    "sg:city":"Donna",
    "sg:classifiers":[
        {
            "category":"Building & Trades",
            "subcategory":"Landscaping Services",
            "type":"Services"
        }
    ],
    "sg:phone":"+1 956 464 7794",
    "sg:postcode":"78537",
    "sg:province":"TX",
    "sg:tags":[
        "landscape"
    ],
    "wof:name":"Superior Lawn Care",
    "wof:placetype":"venue"
},
  "geometry": {"coordinates":[-98.056168,26.166094],"type":"Point"}
}