{
  "type": "Feature",
  "properties": {
    "iso:country":"US",
    "sg:address":"2980 Ashfield",
    "sg:city":"San Antonio",
    "sg:classifiers":[
        {
            "category":"Professional",
            "subcategory":"Management & Consulting",
            "type":"Services"
        }
    ],
    "sg:phone":"+1 210 674 1107",
    "sg:postcode":"78245",
    "sg:province":"TX",
    "sg:tags":[
        "consultant",
        "business"
    ],
    "wof:name":"Dan Pareso Co",
    "wof:placetype":"venue"
},
  "geometry": {"coordinates":[-98.696119,29.400862],"type":"Point"}
}