{
  "type": "Feature",
  "properties": {
    "iso:country":"US",
    "sg:address":"1000 McCoy Dr",
    "sg:city":"Irving",
    "sg:classifiers":[
        {
            "category":"Shopping",
            "subcategory":"Jewelry",
            "type":"Retail Goods"
        }
    ],
    "sg:phone":"+1 972 594 6139",
    "sg:postcode":"75062",
    "sg:province":"TX",
    "wof:name":"Js Jewelry Etc",
    "wof:placetype":"venue"
},
  "geometry": {"coordinates":[-96.958349,32.849046],"type":"Point"}
}