{
  "type": "Feature",
  "properties": {
    "iso:country":"US",
    "sg:address":"703 E Houston Ave",
    "sg:city":"Crockett",
    "sg:classifiers":[
        {
            "category":"Retail",
            "subcategory":"Laundry & Dry Cleaning",
            "type":"Services"
        }
    ],
    "sg:phone":"+1 936 544 8716",
    "sg:postcode":"75835",
    "sg:province":"TX",
    "sg:tags":[
        "cleaners",
        "plant",
        "drycleaning"
    ],
    "wof:name":"Robinson's Cleaners",
    "wof:placetype":"venue"
},
  "geometry": {"coordinates":[-95.4524,31.318424],"type":"Point"}
}