{
  "type": "Feature",
  "properties": {
    "iso:country":"US",
    "sg:address":"122 Lemley Dr",
    "sg:city":"Rockwall",
    "sg:classifiers":[
        {
            "category":"Building & Trades",
            "subcategory":"Construction",
            "type":"Services"
        }
    ],
    "sg:phone":"+1 214 682 1128",
    "sg:postcode":"75032",
    "sg:province":"TX",
    "sg:tags":[
        "hanging",
        "contractor"
    ],
    "wof:name":"Tony Martinez Painting",
    "wof:placetype":"venue"
},
  "geometry": {"coordinates":[-96.506263,32.837857],"type":"Point"}
}