{
  "type": "Feature",
  "properties": {
    "iso:country":"US",
    "sg:address":"519 E Irving Blvd",
    "sg:city":"Irving",
    "sg:classifiers":[
        {
            "category":"Home & Garden",
            "subcategory":"Household Appliances",
            "type":"Retail Goods"
        }
    ],
    "sg:phone":"+1 972 721 7141",
    "sg:postcode":"75060",
    "sg:province":"TX",
    "wof:name":"Grupo Mexicano",
    "wof:placetype":"venue"
},
  "geometry": {"coordinates":[-96.94135799999999,32.813899],"type":"Point"}
}