{
  "type": "Feature",
  "properties": {
    "iso:country":"US",
    "sg:address":"2312 W Crawford St",
    "sg:city":"Denison",
    "sg:classifiers":[
        {
            "category":"Professional",
            "subcategory":"Computer Services",
            "type":"Services"
        }
    ],
    "sg:phone":"+1 903 327 0017",
    "sg:postcode":"75020",
    "sg:province":"TX",
    "sg:tags":[
        "repair"
    ],
    "wof:name":"G & R Creations",
    "wof:placetype":"venue"
},
  "geometry": {"coordinates":[-96.56670800000001,33.75293],"type":"Point"}
}