{
  "type": "Feature",
  "properties": {
    "iso:country":"US",
    "sg:address":"6926 Harry Hines Blvd",
    "sg:city":"Dallas",
    "sg:classifiers":[
        {
            "category":"Food & Beverages",
            "subcategory":"Liquor & Beverages",
            "type":"Retail Goods"
        }
    ],
    "sg:phone":"+1 214 357 0481",
    "sg:postcode":"75235",
    "sg:province":"TX",
    "sg:tags":[
        "beer",
        "spirit",
        "wine"
    ],
    "wof:name":"Empire Central Beverage",
    "wof:placetype":"venue"
},
  "geometry": {"coordinates":[-96.854202,32.825802],"type":"Point"}
}