{
  "type": "Feature",
  "properties": {
    "iso:country":"US",
    "sg:address":"7610 Dahlia St",
    "sg:city":"Houston",
    "sg:classifiers":[
        {
            "category":"Education",
            "subcategory":"School",
            "type":"Public Place"
        }
    ],
    "sg:phone":"+1 713 924 1851",
    "sg:postcode":"77012",
    "sg:province":"TX",
    "sg:tags":[
        "high",
        "middle",
        "elementary"
    ],
    "wof:name":"Schools",
    "wof:placetype":"venue"
},
  "geometry": {"coordinates":[-95.28409000000001,29.714444],"type":"Point"}
}