{
  "type": "Feature",
  "properties": {
    "iso:country":"US",
    "sg:address":"609 Congress Ave",
    "sg:city":"Austin",
    "sg:classifiers":[
        {
            "category":"Restaurant",
            "type":"Food & Drink"
        }
    ],
    "sg:phone":"+1 512 472 9454",
    "sg:postcode":"78701",
    "sg:province":"TX",
    "sg:tags":[
        "bar",
        "sushi",
        "japanese",
        "asian",
        "pan"
    ],
    "wof:name":"Wiki Wiki Teriyaki",
    "wof:placetype":"venue"
},
  "geometry": {"coordinates":[-97.74279900000001,30.268127],"type":"Point"}
}