{
  "type": "Feature",
  "properties": {
    "iso:country":"US",
    "sg:address":"229 Dowlen Rd",
    "sg:city":"Beaumont",
    "sg:classifiers":[
        {
            "category":"Personal",
            "subcategory":"Beauty Salon",
            "type":"Services"
        }
    ],
    "sg:phone":"+1 409 860 5578",
    "sg:postcode":"77706",
    "sg:province":"TX",
    "sg:tags":[
        "nail",
        "shop",
        "manicuring"
    ],
    "sg:website":"http://www.starnail.com",
    "wof:name":"Star Nails",
    "wof:placetype":"venue"
},
  "geometry": {"coordinates":[-94.17227800000001,30.075023],"type":"Point"}
}