{
  "type": "Feature",
  "properties": {
    "iso:country":"US",
    "sg:address":"314 N Post Oak Ln",
    "sg:city":"Houston",
    "sg:classifiers":[
        {
            "category":"Freight",
            "type":"Transportation"
        }
    ],
    "sg:phone":"+1 713 682 4785",
    "sg:postcode":"77024",
    "sg:province":"TX",
    "sg:tags":[
        "hauling",
        "trucking"
    ],
    "sg:website":"www.ascous.com",
    "wof:name":"Asco Us",
    "wof:placetype":"venue"
},
  "geometry": {"coordinates":[-95.45745100000001,29.769001],"type":"Point"}
}