{
  "type": "Feature",
  "properties": {
    "iso:country":"US",
    "sg:address":"616 Remington Park",
    "sg:city":"Robinson",
    "sg:classifiers":[
        {
            "category":"Home & Garden",
            "subcategory":"Building Materials",
            "type":"Retail Goods"
        },
        {
            "category":"Building & Trades",
            "subcategory":"Construction",
            "type":"Services"
        }
    ],
    "sg:phone":"+1 254 662 5411",
    "sg:postcode":"76706",
    "sg:province":"TX",
    "sg:tags":[
        "concrete",
        "staining",
        "contractor"
    ],
    "wof:name":"Concrete Decor Of Texas",
    "wof:placetype":"venue"
},
  "geometry": {"coordinates":[-97.130376,31.455502],"type":"Point"}
}