{
  "type": "Feature",
  "properties": {
    "iso:country":"US",
    "sg:address":"23699 Sharp Rd",
    "sg:city":"Montgomery",
    "sg:classifiers":[
        {
            "category":"Shopping",
            "subcategory":"Department Store",
            "type":"Retail Goods"
        }
    ],
    "sg:phone":"+1 936 597 6342",
    "sg:postcode":"77356",
    "sg:province":"TX",
    "wof:name":"H&H Collectables",
    "wof:placetype":"venue"
},
  "geometry": {"coordinates":[-95.695594,30.42578],"type":"Point"}
}