{
  "type": "Feature",
  "properties": {
    "iso:country":"US",
    "sg:address":"7622 Louis Pasteur Dr",
    "sg:city":"San Antonio",
    "sg:classifiers":[
        {
            "category":"Health Services",
            "subcategory":"Doctor",
            "type":"Services"
        }
    ],
    "sg:phone":"+1 210 614 7840",
    "sg:postcode":"78229",
    "sg:province":"TX",
    "sg:tags":[
        "physician",
        "surgeon"
    ],
    "wof:name":"Wellmed At Physicians Plaza",
    "wof:placetype":"venue"
},
  "geometry": {"coordinates":[-98.57084399999999,29.507065],"type":"Point"}
}