{
  "type": "Feature",
  "properties": {
    "iso:country":"US",
    "sg:address":"932 N Cooper St",
    "sg:city":"Arlington",
    "sg:classifiers":[
        {
            "category":"Professional",
            "subcategory":"Printing & Photocopies",
            "type":"Services"
        }
    ],
    "sg:phone":"+1 817 303 9426",
    "sg:postcode":"76011",
    "sg:province":"TX",
    "sg:tags":[
        "equipment-repairing"
    ],
    "wof:name":"Cartridge World Arlington",
    "wof:placetype":"venue"
},
  "geometry": {"coordinates":[-97.11413400000001,32.74846],"type":"Point"}
}