{
  "type": "Feature",
  "properties": {
    "iso:country":"US",
    "sg:address":"727 Airport Blvd",
    "sg:city":"Austin",
    "sg:classifiers":[
        {
            "category":"Professional",
            "subcategory":"Management & Consulting",
            "type":"Services"
        }
    ],
    "sg:phone":"+1 512 385 5466",
    "sg:postcode":"78702",
    "sg:province":"TX",
    "sg:tags":[
        "personnel",
        "agency",
        "employment",
        "consultant"
    ],
    "wof:name":"Ironlion",
    "wof:placetype":"venue"
},
  "geometry": {"coordinates":[-97.69245100000001,30.25359],"type":"Point"}
}