{
  "type": "Feature",
  "properties": {
    "iso:country":"US",
    "sg:address":"5415 Luhning Rd",
    "sg:city":"Dickinson",
    "sg:classifiers":[
        {
            "category":"Manufacturing",
            "subcategory":"Jewelry",
            "type":"Manufacturing & Wholesale Goods"
        }
    ],
    "sg:phone":"+1 281 534 1115",
    "sg:postcode":"77539",
    "sg:province":"TX",
    "sg:tags":[
        "precious",
        "metal",
        "mfg"
    ],
    "wof:name":"Dakota Territories Moder",
    "wof:placetype":"venue"
},
  "geometry": {"coordinates":[-95.021416,29.452599],"type":"Point"}
}