{
  "type": "Feature",
  "properties": {
    "iso:country":"US",
    "sg:address":"13602 Branson Ln",
    "sg:city":"Cypress",
    "sg:classifiers":[
        {
            "category":"Manufacturing",
            "subcategory":"Electronics",
            "type":"Manufacturing & Wholesale Goods"
        }
    ],
    "sg:phone":"+1 281 374 0211",
    "sg:postcode":"77429",
    "sg:province":"TX",
    "sg:tags":[
        "semiconductor",
        "devices"
    ],
    "wof:name":"Cypress Semiconductor",
    "wof:placetype":"venue"
},
  "geometry": {"coordinates":[-95.632267,30.000025],"type":"Point"}
}