{
  "type": "Feature",
  "properties": {
    "iso:country":"US",
    "sg:address":"4426 Point Blvd",
    "sg:city":"Garland",
    "sg:classifiers":[
        {
            "category":"Retail",
            "subcategory":"Laundry & Dry Cleaning",
            "type":"Services"
        }
    ],
    "sg:phone":"+1 972 226 9903",
    "sg:postcode":"75043",
    "sg:province":"TX",
    "sg:tags":[
        "cleaners",
        "rug",
        "carpet"
    ],
    "wof:name":"Aladdin Plus Carpet Care",
    "wof:placetype":"venue"
},
  "geometry": {"coordinates":[-96.544595,32.862026],"type":"Point"}
}