{
  "type": "Feature",
  "properties": {
    "iso:country":"US",
    "sg:address":"1014 Ash St",
    "sg:city":"Victoria",
    "sg:classifiers":[
        {
            "category":"Building & Trades",
            "subcategory":"Landscaping Services",
            "type":"Services"
        }
    ],
    "sg:phone":"+1 361 573 7307",
    "sg:postcode":"77901",
    "sg:province":"TX",
    "wof:name":"Rangels Lawn Care",
    "wof:placetype":"venue"
},
  "geometry": {"coordinates":[-96.993015,28.804471],"type":"Point"}
}