{
  "type": "Feature",
  "properties": {
    "iso:country":"US",
    "sg:address":"4908 Brazos Ave",
    "sg:city":"Midland",
    "sg:classifiers":[
        {
            "category":"Building & Trades",
            "subcategory":"Construction",
            "type":"Services"
        }
    ],
    "sg:phone":"+1 432 694 5742",
    "sg:postcode":"79707",
    "sg:province":"TX",
    "sg:tags":[
        "industrial"
    ],
    "wof:name":"Rhonda L Dawson Construction",
    "wof:placetype":"venue"
},
  "geometry": {"coordinates":[-102.153706,32.025483],"type":"Point"}
}