{
  "type": "Feature",
  "properties": {
    "iso:country":"US",
    "sg:address":"19032 Gulf Fwy",
    "sg:city":"Friendswood",
    "sg:classifiers":[
        {
            "category":"Shopping",
            "subcategory":"Musical Instruments",
            "type":"Retail Goods"
        }
    ],
    "sg:phone":"+1 281 486 0082",
    "sg:postcode":"77546",
    "sg:province":"TX",
    "wof:name":"H & H Music 23",
    "wof:placetype":"venue"
},
  "geometry": {"coordinates":[-95.146655,29.545049],"type":"Point"}
}