{
  "type": "Feature",
  "properties": {
    "iso:country":"US",
    "sg:address":"1100 E Pleasant Run Rd",
    "sg:city":"De Soto",
    "sg:classifiers":[
        {
            "category":"Manufacturing",
            "subcategory":"Food",
            "type":"Manufacturing & Wholesale Goods"
        }
    ],
    "sg:phone":"+1 972 230 6445",
    "sg:postcode":"75115",
    "sg:province":"TX",
    "sg:tags":[
        "product",
        "retail",
        "bakery",
        "mfg"
    ],
    "wof:name":"Donut Palace",
    "wof:placetype":"venue"
},
  "geometry": {"coordinates":[-96.82944000000001,32.604324],"type":"Point"}
}