{
  "type": "Feature",
  "properties": {
    "iso:country":"US",
    "sg:address":"210 Lowrance St",
    "sg:city":"Yoakum",
    "sg:classifiers":[
        {
            "category":"Government",
            "subcategory":"Office",
            "type":"Public Place"
        }
    ],
    "sg:phone":"+1 361 293 2772",
    "sg:postcode":"77995",
    "sg:province":"TX",
    "wof:name":"Dewitt County Barn Precinct 2",
    "wof:placetype":"venue"
},
  "geometry": {"coordinates":[-97.15267900000001,29.284359],"type":"Point"}
}