{
  "type": "Feature",
  "properties": {
    "iso:country":"US",
    "sg:address":"3410 Midcourt Rd",
    "sg:city":"Carrollton",
    "sg:classifiers":[
        {
            "category":"Professional",
            "type":"Services"
        }
    ],
    "sg:phone":"+1 972 394 2919",
    "sg:postcode":"75006",
    "sg:province":"TX",
    "wof:name":"Residence",
    "wof:placetype":"venue"
},
  "geometry": {"coordinates":[-96.841624,32.963637],"type":"Point"}
}