{
  "type": "Feature",
  "properties": {
    "iso:country":"US",
    "sg:address":"2115 Rustic Ridge Dr",
    "sg:city":"Keller",
    "sg:classifiers":[
        {
            "category":"Professional",
            "subcategory":"Computer Services",
            "type":"Services"
        }
    ],
    "sg:phone":"+1 817 581 8374",
    "sg:postcode":"76248",
    "sg:province":"TX",
    "wof:name":"Thom Technology Inc",
    "wof:placetype":"venue"
},
  "geometry": {"coordinates":[-97.244739,32.895658],"type":"Point"}
}