{
  "type": "Feature",
  "properties": {
    "iso:country":"US",
    "sg:address":"1301 Brazos River Rd",
    "sg:city":"Freeport",
    "sg:classifiers":[
        {
            "category":"Government",
            "subcategory":"Office",
            "type":"Public Place"
        }
    ],
    "sg:phone":"+1 979 233 5063",
    "sg:postcode":"77541",
    "sg:province":"TX",
    "sg:tags":[
        "township",
        "government-city",
        "village"
    ],
    "wof:name":"Pony Party Planners Of Pea",
    "wof:placetype":"venue"
},
  "geometry": {"coordinates":[-95.43174,28.975861],"type":"Point"}
}