{
  "type": "Feature",
  "properties": {
    "iso:country":"US",
    "sg:address":"809 Main St",
    "sg:city":"Kerrville",
    "sg:classifiers":[
        {
            "category":"Mining & Drilling",
            "type":"Manufacturing & Wholesale Goods"
        }
    ],
    "sg:phone":"+1 830 792 3302",
    "sg:postcode":"78028",
    "sg:province":"TX",
    "sg:tags":[
        "development",
        "exploration",
        "oil",
        "gas"
    ],
    "wof:name":"Culebra Oil & Gas",
    "wof:placetype":"venue"
},
  "geometry": {"coordinates":[-99.139433,30.046515],"type":"Point"}
}