{
  "type": "Feature",
  "properties": {
    "iso:country":"US",
    "sg:address":"737 Knickerbocker Rd",
    "sg:city":"San Angelo",
    "sg:classifiers":[
        {
            "category":"Building & Trades",
            "subcategory":"Equipment Rental",
            "type":"Services"
        }
    ],
    "sg:phone":"+1 325 653 1077",
    "sg:postcode":"76903",
    "sg:province":"TX",
    "sg:tags":[
        "hospital",
        "supply"
    ],
    "sg:website":"www.professionalmedical.com",
    "wof:name":"Professional Medical",
    "wof:placetype":"venue"
},
  "geometry": {"coordinates":[-100.444372,31.439221],"type":"Point"}
}