{
  "type": "Feature",
  "properties": {
    "iso:country":"US",
    "sg:address":"140 Polo Inn Rd",
    "sg:city":"El Paso",
    "sg:classifiers":[
        {
            "category":"Shopping",
            "subcategory":"Bicycles & Sporting Goods",
            "type":"Retail Goods"
        }
    ],
    "sg:phone":"+1 915 778 4763",
    "sg:postcode":"79915",
    "sg:province":"TX",
    "wof:name":"Hugos Leather Goods",
    "wof:placetype":"venue"
},
  "geometry": {"coordinates":[-106.38951,31.745893],"type":"Point"}
}