{
  "type": "Feature",
  "properties": {
    "iso:country":"US",
    "sg:address":"2108 Dallas Pkwy #216A",
    "sg:city":"Plano",
    "sg:classifiers":[
        {
            "category":"Professional",
            "subcategory":"Art Services",
            "type":"Services"
        }
    ],
    "sg:phone":"+1 972 473 6535",
    "sg:postcode":"75093",
    "sg:province":"TX",
    "sg:tags":[
        "photographer"
    ],
    "sg:website":"www.portraitinnovations.com",
    "wof:name":"Portrait Innovations",
    "wof:placetype":"venue"
},
  "geometry": {"coordinates":[-96.827387,33.028736],"type":"Point"}
}