{
  "type": "Feature",
  "properties": {
    "iso:country":"US",
    "sg:address":"23 Daly Pl # 2Ndell",
    "sg:city":"Houston",
    "sg:classifiers":[
        {
            "category":"Shopping",
            "subcategory":"Tobacco",
            "type":"Retail Goods"
        }
    ],
    "sg:phone":"+1 713 453 2631",
    "sg:postcode":"77009",
    "sg:province":"TX",
    "sg:tags":[
        "shop"
    ],
    "wof:name":"Pepper Joe's Fun Shop",
    "wof:placetype":"venue"
},
  "geometry": {"coordinates":[-95.361198,29.7717],"type":"Point"}
}