{
  "type": "Feature",
  "properties": {
    "iso:country":"US",
    "sg:address":"3340 E Walnut St",
    "sg:city":"Pearland",
    "sg:classifiers":[
        {
            "category":"Real Estate",
            "subcategory":"Real Estate Operator",
            "type":"Services"
        }
    ],
    "sg:phone":"+1 281 485 4738",
    "sg:postcode":"77581",
    "sg:province":"TX",
    "sg:tags":[
        "building",
        "apartment"
    ],
    "wof:name":"Park Place Apartments",
    "wof:placetype":"venue"
},
  "geometry": {"coordinates":[-95.27516,29.560061],"type":"Point"}
}