{
  "type": "Feature",
  "properties": {
    "iso:country":"US",
    "sg:address":"151 W Spring Creek Pkwy #511",
    "sg:city":"Plano",
    "sg:classifiers":[
        {
            "category":"Food & Beverages",
            "subcategory":"Candy",
            "type":"Retail Goods"
        },
        {
            "category":"Shopping",
            "subcategory":"Party Supplies",
            "type":"Retail Goods"
        },
        {
            "category":"Bakery",
            "type":"Food & Drink"
        }
    ],
    "sg:phone":"+1 972 517 0009",
    "sg:postcode":"75023",
    "sg:province":"TX",
    "sg:tags":[
        "cake",
        "confectionery",
        "pastry",
        "wedding"
    ],
    "sg:website":"http://www.cakesamore.com",
    "wof:name":"Cakes Amore",
    "wof:placetype":"venue"
},
  "geometry": {"coordinates":[-96.695243,33.057448],"type":"Point"}
}