{
  "type": "Feature",
  "properties": {
    "iso:country":"US",
    "sg:address":"605 N Kaufman St",
    "sg:city":"Seagoville",
    "sg:classifiers":[
        {
            "category":"Building & Trades",
            "subcategory":"Landscaping Services",
            "type":"Services"
        }
    ],
    "sg:phone":"+1 972 287 7400",
    "sg:postcode":"75159",
    "sg:province":"TX",
    "sg:tags":[
        "lawn",
        "maintenance",
        "grounds"
    ],
    "wof:name":"Lawnlab",
    "wof:placetype":"venue"
},
  "geometry": {"coordinates":[-96.54553900000001,32.644911],"type":"Point"}
}