{
  "type": "Feature",
  "properties": {
    "iso:country":"US",
    "sg:address":"2105 W Davis St",
    "sg:city":"Conroe",
    "sg:classifiers":[
        {
            "category":"Food & Beverages",
            "subcategory":"Bakery",
            "type":"Retail Goods"
        }
    ],
    "sg:phone":"+1 936 756 3200",
    "sg:postcode":"77304",
    "sg:province":"TX",
    "sg:tags":[
        "doughnut"
    ],
    "wof:name":"Southern Maid Donut Shop",
    "wof:placetype":"venue"
},
  "geometry": {"coordinates":[-95.482978,30.319833],"type":"Point"}
}