{
  "type": "Feature",
  "properties": {
    "iso:country":"US",
    "sg:address":"351 FM 646 W",
    "sg:city":"Dickinson",
    "sg:classifiers":[
        {
            "category":"Food & Beverages",
            "subcategory":"Groceries & Convenience Stores",
            "type":"Retail Goods"
        }
    ],
    "sg:phone":"+1 281 309 0900",
    "sg:postcode":"77539",
    "sg:province":"TX",
    "wof:name":"Super Star Food",
    "wof:placetype":"venue"
},
  "geometry": {"coordinates":[-95.07352899999999,29.477966],"type":"Point"}
}