{
  "type": "Feature",
  "properties": {
    "iso:country":"US",
    "sg:address":"3416 S Southwest Loop 323",
    "sg:city":"Tyler",
    "sg:classifiers":[
        {
            "category":"Building & Trades",
            "subcategory":"Pest Control",
            "type":"Services"
        }
    ],
    "sg:phone":"+1 903 939 3700",
    "sg:postcode":"75701",
    "sg:province":"TX",
    "sg:website":"http://www.pestpunishers.com",
    "wof:name":"Pest Punishers",
    "wof:placetype":"venue"
},
  "geometry": {"coordinates":[-95.33999900000001,32.309671],"type":"Point"}
}