{
  "type": "Feature",
  "properties": {
    "iso:country":"US",
    "sg:address":"10180 Co Rd 391",
    "sg:city":"Tyler",
    "sg:classifiers":[
        {
            "category":"Building & Trades",
            "subcategory":"Construction",
            "type":"Services"
        }
    ],
    "sg:phone":"+1 903 597 8307",
    "sg:postcode":"75708",
    "sg:province":"TX",
    "sg:tags":[
        "house"
    ],
    "wof:name":"Maddox Construction",
    "wof:placetype":"venue"
},
  "geometry": {"coordinates":[-95.193749,32.4058],"type":"Point"}
}