{
  "type": "Feature",
  "properties": {
    "iso:country":"US",
    "sg:address":"1815 Mimosa Ln",
    "sg:city":"Plano",
    "sg:classifiers":[
        {
            "category":"Community Center",
            "subcategory":"Senior",
            "type":"Public Place"
        },
        {
            "category":"Social Services",
            "subcategory":"Adult Care",
            "type":"Services"
        }
    ],
    "sg:phone":"+1 972 424 9889",
    "sg:postcode":"75074",
    "sg:province":"TX",
    "sg:tags":[
        "counseling",
        "citizen"
    ],
    "wof:name":"Praise Land Retirement Village",
    "wof:placetype":"venue"
},
  "geometry": {"coordinates":[-96.68841999999999,33.025863],"type":"Point"}
}