{
  "type": "Feature",
  "properties": {
    "iso:country":"US",
    "sg:address":"816 Maxey Rd",
    "sg:city":"Houston",
    "sg:classifiers":[
        {
            "category":"Restaurant",
            "type":"Food & Drink"
        }
    ],
    "sg:phone":"+1 713 451 2254",
    "sg:postcode":"77013",
    "sg:province":"TX",
    "wof:name":"Peking Chef",
    "wof:placetype":"venue"
},
  "geometry": {"coordinates":[-95.218597,29.7764],"type":"Point"}
}