{
  "type": "Feature",
  "properties": {
    "iso:country":"US",
    "sg:address":"4015 31st St",
    "sg:city":"Lubbock",
    "sg:classifiers":[
        {
            "category":"Building & Trades",
            "subcategory":"Landscaping Services",
            "type":"Services"
        }
    ],
    "sg:phone":"+1 806 793 5655",
    "sg:postcode":"79410",
    "sg:province":"TX",
    "wof:name":"Milwaukee St Shop",
    "wof:placetype":"venue"
},
  "geometry": {"coordinates":[-101.900492,33.565914],"type":"Point"}
}