{
  "type": "Feature",
  "properties": {
    "iso:country":"US",
    "sg:address":"604 Merritt St",
    "sg:city":"River Oaks",
    "sg:classifiers":[
        {
            "category":"Professional",
            "subcategory":"Accounting & Tax Preparation",
            "type":"Services"
        }
    ],
    "sg:phone":"+1 817 737 8186",
    "sg:postcode":"76114",
    "sg:province":"TX",
    "sg:tags":[
        "accountant"
    ],
    "wof:name":"J Wayne Land CPA",
    "wof:placetype":"venue"
},
  "geometry": {"coordinates":[-97.396879,32.766721],"type":"Point"}
}