{
  "type": "Feature",
  "properties": {
    "iso:country":"US",
    "sg:address":"12203 Lennox Gardens Dr",
    "sg:city":"Houston",
    "sg:classifiers":[
        {
            "category":"Building & Trades",
            "subcategory":"Landscaping Services",
            "type":"Services"
        }
    ],
    "sg:phone":"+1 281 537 1906",
    "sg:postcode":"77066",
    "sg:province":"TX",
    "wof:name":"Canas Landscaping & Lawn Svc",
    "wof:placetype":"venue"
},
  "geometry": {"coordinates":[-95.48307,29.963276],"type":"Point"}
}