{
  "type": "Feature",
  "properties": {
    "iso:country":"US",
    "sg:address":"5000 Plaza on the Lake Ste. #250",
    "sg:city":"Austin",
    "sg:classifiers":[
        {
            "category":"Real Estate",
            "subcategory":"Real Estate Services",
            "type":"Services"
        },
        {
            "category":"Banks & Credit Unions",
            "subcategory":"Financial Services",
            "type":"Services"
        }
    ],
    "sg:phone":"+1 512 415 6142",
    "sg:postcode":"78746",
    "sg:province":"TX",
    "sg:tags":[
        "alternative",
        "loan",
        "broker",
        "mortgage"
    ],
    "sg:website":"http://www.austinhomeloans.org",
    "wof:name":"Austin Home Loans",
    "wof:placetype":"venue"
},
  "geometry": {"coordinates":[-97.800905,30.349602],"type":"Point"}
}