{
  "type": "Feature",
  "properties": {
    "iso:country":"US",
    "sg:address":"207 Anaqua Ave",
    "sg:city":"Victoria",
    "sg:classifiers":[
        {
            "category":"Retail",
            "subcategory":"Repair Shop",
            "type":"Services"
        }
    ],
    "sg:phone":"+1 361 576 0664",
    "sg:postcode":"77901",
    "sg:province":"TX",
    "sg:tags":[
        "chemical",
        "product"
    ],
    "wof:name":"Toms Video Service",
    "wof:placetype":"venue"
},
  "geometry": {"coordinates":[-97.001516,28.826785],"type":"Point"}
}