{
  "type": "Feature",
  "properties": {
    "iso:country":"US",
    "sg:address":"9714 Seeker St",
    "sg:city":"Houston",
    "sg:classifiers":[
        {
            "category":"Building & Trades",
            "subcategory":"Plumbing",
            "type":"Services"
        }
    ],
    "sg:phone":"+1 713 633 2590",
    "sg:postcode":"77078",
    "sg:province":"TX",
    "sg:tags":[
        "contractor"
    ],
    "wof:name":"Goodwin Plumbing Co",
    "wof:placetype":"venue"
},
  "geometry": {"coordinates":[-95.27288299999999,29.852834],"type":"Point"}
}