{
  "type": "Feature",
  "properties": {
    "iso:country":"US",
    "sg:address":"4000 S Zapata Hwy",
    "sg:city":"Laredo",
    "sg:classifiers":[
        {
            "category":"Building & Trades",
            "subcategory":"Construction",
            "type":"Services"
        }
    ],
    "sg:phone":"+1 956 712 3964",
    "sg:postcode":"78046",
    "sg:province":"TX",
    "sg:tags":[
        "general",
        "contractor"
    ],
    "wof:name":"Closner Construction Co",
    "wof:placetype":"venue"
},
  "geometry": {"coordinates":[-99.477315,27.458335],"type":"Point"}
}