{
  "type": "Feature",
  "properties": {
    "iso:country":"US",
    "sg:address":"12050 Old Kluge Rd",
    "sg:city":"Cypress",
    "sg:classifiers":[
        {
            "category":"Education",
            "subcategory":"School",
            "type":"Public Place"
        }
    ],
    "sg:phone":"+1 281 370 0990",
    "sg:postcode":"77429",
    "sg:province":"TX",
    "sg:tags":[
        "elementary"
    ],
    "wof:name":"Hamilton Elementary School",
    "wof:placetype":"venue"
},
  "geometry": {"coordinates":[-95.615724,29.984994],"type":"Point"}
}