{
  "type": "Feature",
  "properties": {
    "iso:country":"US",
    "sg:address":"1505 State Hwy 6",
    "sg:city":"Houston",
    "sg:classifiers":[
        {
            "category":"Insurance",
            "subcategory":"Insurance Agent",
            "type":"Services"
        }
    ],
    "sg:phone":"+1 281 497 5497",
    "sg:postcode":"77077",
    "sg:province":"TX",
    "wof:name":"Allstate",
    "wof:placetype":"venue"
},
  "geometry": {"coordinates":[-95.644491,29.758846],"type":"Point"}
}