{
  "type": "Feature",
  "properties": {
    "iso:country":"US",
    "sg:address":"2663 Freewood Dr",
    "sg:city":"Dallas",
    "sg:classifiers":[
        {
            "category":"Retail",
            "subcategory":"Laundry & Dry Cleaning",
            "type":"Services"
        }
    ],
    "sg:phone":"+1 214 350 1234",
    "sg:postcode":"75220",
    "sg:province":"TX",
    "sg:tags":[
        "laundries-self",
        "operated",
        "washer",
        "dryer",
        "coin"
    ],
    "wof:name":"Wash N Dry",
    "wof:placetype":"venue"
},
  "geometry": {"coordinates":[-96.884021,32.870458],"type":"Point"}
}