{
  "type": "Feature",
  "properties": {
    "iso:country":"US",
    "sg:address":"907 Sequoyah Ln",
    "sg:city":"Longview",
    "sg:classifiers":[
        {
            "category":"Professional",
            "type":"Services"
        }
    ],
    "sg:phone":"+1 903 291 0930",
    "sg:postcode":"75605",
    "sg:province":"TX",
    "sg:tags":[
        "establishment"
    ],
    "wof:name":"Willand Inc",
    "wof:placetype":"venue"
},
  "geometry": {"coordinates":[-94.72755600000001,32.528544],"type":"Point"}
}