{
  "type": "Feature",
  "properties": {
    "iso:country":"US",
    "sg:address":"1800 NW 28th St",
    "sg:city":"Fort Worth",
    "sg:classifiers":[
        {
            "category":"Retail",
            "subcategory":"Auto Repair",
            "type":"Services"
        }
    ],
    "sg:phone":"+1 817 624 4342",
    "sg:postcode":"76164",
    "sg:province":"TX",
    "sg:tags":[
        "transmission"
    ],
    "wof:name":"A-1 AAAA Transmissions Inc",
    "wof:placetype":"venue"
},
  "geometry": {"coordinates":[-97.37069700000001,32.795412],"type":"Point"}
}