{
  "type": "Feature",
  "properties": {
    "iso:country":"US",
    "sg:address":"11337 Co Rd 1302",
    "sg:city":"Whitehouse",
    "sg:classifiers":[
        {
            "category":"Real Estate",
            "subcategory":"Real Estate Agent",
            "type":"Services"
        }
    ],
    "sg:phone":"+1 903 839 4365",
    "sg:postcode":"75791",
    "sg:province":"TX",
    "wof:name":"Key Realty",
    "wof:placetype":"venue"
},
  "geometry": {"coordinates":[-95.223423,32.195424],"type":"Point"}
}