{
  "type": "Feature",
  "properties": {
    "iso:country":"US",
    "sg:address":"1611 Stonehaven Village Cir",
    "sg:city":"Spring",
    "sg:classifiers":[
        {
            "category":"Shopping",
            "subcategory":"Used Merchandise",
            "type":"Retail Goods"
        }
    ],
    "sg:phone":"+1 281 364 9587",
    "sg:postcode":"77386",
    "sg:province":"TX",
    "wof:name":"Charles Rew",
    "wof:placetype":"venue"
},
  "geometry": {"coordinates":[-95.418485,30.141678],"type":"Point"}
}