{
  "type": "Feature",
  "properties": {
    "iso:country":"US",
    "sg:address":"4801 Legendary Dr",
    "sg:city":"Frisco",
    "sg:classifiers":[
        {
            "category":"Place Of Worship",
            "subcategory":"Church",
            "type":"Public Place"
        },
        {
            "category":"Place Of Worship",
            "type":"Public Place"
        }
    ],
    "sg:phone":"+1 469 252 5200",
    "sg:postcode":"75034",
    "sg:province":"TX",
    "sg:tags":[
        "churches-independent",
        "churches-christian",
        "churches-bible",
        "churches-non-denominational"
    ],
    "sg:website":"http://www.stonebriar.org",
    "wof:name":"Stonebriar Community Church",
    "wof:placetype":"venue"
},
  "geometry": {"coordinates":[-96.80976,33.120102],"type":"Point"}
}