{
  "type": "Feature",
  "properties": {
    "iso:country":"US",
    "sg:address":"152 Grand Ave",
    "sg:city":"Victoria",
    "sg:classifiers":[
        {
            "category":"Building & Trades",
            "subcategory":"Landscaping Services",
            "type":"Services"
        }
    ],
    "sg:phone":"+1 361 575 7174",
    "sg:postcode":"77905",
    "sg:province":"TX",
    "wof:name":"Jordan Lawn Service",
    "wof:placetype":"venue"
},
  "geometry": {"coordinates":[-96.87374800000001,28.722123],"type":"Point"}
}