{
  "type": "Feature",
  "properties": {
    "iso:country":"US",
    "sg:address":"13707 Corinth",
    "sg:city":"Universal City",
    "sg:classifiers":[
        {
            "category":"Real Estate",
            "subcategory":"Developer",
            "type":"Services"
        }
    ],
    "sg:phone":"+1 210 653 5456",
    "sg:postcode":"78148",
    "sg:province":"TX",
    "wof:name":"Shadow Mountain Ranches Inc",
    "wof:placetype":"venue"
},
  "geometry": {"coordinates":[-98.313053,29.574138],"type":"Point"}
}