{
  "type": "Feature",
  "properties": {
    "iso:country":"US",
    "sg:address":"8351 Park Place Blvd Apt 35",
    "sg:city":"Houston",
    "sg:classifiers":[
        {
            "category":"Real Estate",
            "subcategory":"Real Estate Operator",
            "type":"Services"
        }
    ],
    "sg:phone":"+1 713 643 5839",
    "sg:postcode":"77017",
    "sg:province":"TX",
    "sg:tags":[
        "apartment"
    ],
    "wof:name":"Colonial Park Apts",
    "wof:placetype":"venue"
},
  "geometry": {"coordinates":[-95.2681,29.692747],"type":"Point"}
}