{
  "type": "Feature",
  "properties": {
    "iso:country":"US",
    "sg:address":"608 Dominion Dr",
    "sg:city":"Southlake",
    "sg:classifiers":[
        {
            "category":"Professional",
            "subcategory":"Lawyer & Legal Services",
            "type":"Services"
        }
    ],
    "sg:phone":"+1 817 251 9323",
    "sg:postcode":"76092",
    "sg:province":"TX",
    "wof:name":"Law Noel C Etux Rita M",
    "wof:placetype":"venue"
},
  "geometry": {"coordinates":[-97.147778,32.933321],"type":"Point"}
}