{
  "type": "Feature",
  "properties": {
    "iso:country":"US",
    "sg:address":"9 Suncrest Ln",
    "sg:city":"Jasper",
    "sg:classifiers":[
        {
            "category":"Shopping",
            "subcategory":"Bicycles & Sporting Goods",
            "type":"Retail Goods"
        }
    ],
    "sg:phone":"+1 409 384 6335",
    "sg:postcode":"75951",
    "sg:province":"TX",
    "wof:name":"Gunslinger",
    "wof:placetype":"venue"
},
  "geometry": {"coordinates":[-93.975228,30.906525],"type":"Point"}
}