{
  "type": "Feature",
  "properties": {
    "iso:country":"US",
    "sg:address":"200 W Washington St",
    "sg:city":"Stephenville",
    "sg:classifiers":[
        {
            "category":"Professional",
            "type":"Services"
        }
    ],
    "sg:phone":"+1 254 968 5882",
    "sg:postcode":"76401",
    "sg:province":"TX",
    "wof:name":"Not Too Shabby",
    "wof:placetype":"venue"
},
  "geometry": {"coordinates":[-98.202862,32.220295],"type":"Point"}
}