{
  "type": "Feature",
  "properties": {
    "iso:country":"US",
    "sg:address":"7707 Bissonnet St",
    "sg:city":"Houston",
    "sg:classifiers":[
        {
            "category":"Organizations",
            "subcategory":"Religious Organization",
            "type":"Services"
        }
    ],
    "sg:phone":"+1 713 777 5673",
    "sg:postcode":"77074",
    "sg:province":"TX",
    "wof:name":"Love Center Church",
    "wof:placetype":"venue"
},
  "geometry": {"coordinates":[-95.514199,29.684012],"type":"Point"}
}