{
  "type": "Feature",
  "properties": {
    "iso:country":"US",
    "sg:address":"403 Woodridge",
    "sg:city":"Hallsville",
    "sg:classifiers":[
        {
            "category":"Professional",
            "subcategory":"Computer Services",
            "type":"Services"
        }
    ],
    "sg:phone":"+1 903 759 2812",
    "sg:postcode":"75650",
    "sg:province":"TX",
    "sg:tags":[
        "related"
    ],
    "wof:name":"Antigraphix",
    "wof:placetype":"venue"
},
  "geometry": {"coordinates":[-94.56987100000001,32.508719],"type":"Point"}
}