{
  "type": "Feature",
  "properties": {
    "iso:country":"US",
    "sg:address":"22604 Co Rd 3107",
    "sg:city":"Gladewater",
    "sg:classifiers":[
        {
            "category":"Organizations",
            "subcategory":"Religious Organization",
            "type":"Services"
        }
    ],
    "sg:phone":"+1 903 845 4603",
    "sg:postcode":"75647",
    "sg:province":"TX",
    "wof:name":"Friendship Baptist Church",
    "wof:placetype":"venue"
},
  "geometry": {"coordinates":[-95.024332,32.489908],"type":"Point"}
}