{
  "type": "Feature",
  "properties": {
    "iso:country":"US",
    "sg:address":"2220 Newbury Dr",
    "sg:city":"Arlington",
    "sg:classifiers":[
        {
            "category":"Shopping",
            "subcategory":"Computers & Home Electronics",
            "type":"Retail Goods"
        }
    ],
    "sg:phone":"+1 817 312 3006",
    "sg:postcode":"76014",
    "sg:province":"TX",
    "sg:tags":[
        "equipment",
        "dealer"
    ],
    "wof:name":"A C's Computers",
    "wof:placetype":"venue"
},
  "geometry": {"coordinates":[-97.067669,32.686456],"type":"Point"}
}