{
  "type": "Feature",
  "properties": {
    "iso:country":"US",
    "sg:address":"8621 Funtier Ct",
    "sg:city":"Fort Worth",
    "sg:classifiers":[
        {
            "category":"Building & Trades",
            "subcategory":"Construction",
            "type":"Services"
        }
    ],
    "sg:phone":"+1 817 236 6758",
    "sg:postcode":"76179",
    "sg:province":"TX",
    "sg:tags":[
        "heavy"
    ],
    "wof:name":"Forbes Contracting Inc",
    "wof:placetype":"venue"
},
  "geometry": {"coordinates":[-97.439804,32.881975],"type":"Point"}
}