{
  "type": "Feature",
  "properties": {
    "iso:country":"US",
    "sg:address":"1701 Evergreen Ave",
    "sg:city":"Austin",
    "sg:classifiers":[
        {
            "category":"Social Services",
            "subcategory":"Adult Care",
            "type":"Services"
        }
    ],
    "sg:phone":"+1 512 444 6081",
    "sg:postcode":"78704",
    "sg:province":"TX",
    "sg:tags":[
        "independent",
        "disabled",
        "living"
    ],
    "sg:website":"http://www.vaughnhouse.org",
    "wof:name":"Architerra Inc",
    "wof:placetype":"venue"
},
  "geometry": {"coordinates":[-97.764798,30.250937],"type":"Point"}
}