{
  "type": "Feature",
  "properties": {
    "iso:country":"US",
    "sg:address":"731 N Collins St",
    "sg:city":"Arlington",
    "sg:classifiers":[
        {
            "category":"Professional",
            "subcategory":"Accounting & Tax Preparation",
            "type":"Services"
        }
    ],
    "sg:phone":"+1 817 274 5699",
    "sg:postcode":"76011",
    "sg:province":"TX",
    "sg:tags":[
        "return",
        "filing"
    ],
    "wof:name":"Fidelity Tax Svc",
    "wof:placetype":"venue"
},
  "geometry": {"coordinates":[-97.097306,32.745803],"type":"Point"}
}