{
  "type": "Feature",
  "properties": {
    "iso:country":"US",
    "sg:address":"11029 Shady Trl",
    "sg:city":"Dallas",
    "sg:classifiers":[
        {
            "category":"Professional",
            "subcategory":"Employment Agencies",
            "type":"Services"
        }
    ],
    "sg:phone":"+1 214 350 2233",
    "sg:postcode":"75229",
    "sg:province":"TX",
    "sg:tags":[
        "truck",
        "driver"
    ],
    "wof:name":"American Driver Leasing",
    "wof:placetype":"venue"
},
  "geometry": {"coordinates":[-96.890517,32.882913],"type":"Point"}
}