{
  "type": "Feature",
  "properties": {
    "iso:country":"US",
    "sg:address":"921 US Hwy 90 Alt",
    "sg:city":"Richmond",
    "sg:classifiers":[
        {
            "category":"Retail",
            "subcategory":"Auto Repair",
            "type":"Services"
        }
    ],
    "sg:phone":"+1 281 633 8473",
    "sg:postcode":"77469",
    "sg:province":"TX",
    "sg:tags":[
        "repairing",
        "automobile"
    ],
    "wof:name":"Integrity",
    "wof:placetype":"venue"
},
  "geometry": {"coordinates":[-95.765573,29.580434],"type":"Point"}
}