{
  "type": "Feature",
  "properties": {
    "iso:country":"US",
    "sg:address":"2351 Performance Dr",
    "sg:city":"Richardson",
    "sg:classifiers":[
        {
            "category":"Arts & Performance",
            "subcategory":"Theater",
            "type":"Entertainment"
        }
    ],
    "sg:phone":"+1 972 744 4650",
    "sg:postcode":"75082",
    "sg:province":"TX",
    "sg:tags":[
        "theatrical"
    ],
    "wof:name":"Charles W Eisemann Center",
    "wof:placetype":"venue"
},
  "geometry": {"coordinates":[-96.708467,32.984167],"type":"Point"}
}