{
  "type": "Feature",
  "properties": {
    "iso:country":"US",
    "sg:address":"2732 Weisenberger St",
    "sg:city":"Fort Worth",
    "sg:classifiers":[
        {
            "category":"Manufacturing",
            "subcategory":"Tools & Machinery",
            "type":"Manufacturing & Wholesale Goods"
        }
    ],
    "sg:phone":"+1 817 336 5449",
    "sg:postcode":"76107",
    "sg:province":"TX",
    "sg:tags":[
        "electrical",
        "mfg"
    ],
    "wof:name":"Hde",
    "wof:placetype":"venue"
},
  "geometry": {"coordinates":[-97.35592,32.757249],"type":"Point"}
}