{
  "type": "Feature",
  "properties": {
    "iso:country":"US",
    "sg:address":"7777 Forest Ln Ste D-570",
    "sg:city":"Dallas",
    "sg:classifiers":[
        {
            "category":"Health Services",
            "subcategory":"Clinic",
            "type":"Services"
        }
    ],
    "sg:phone":"+1 214 728 7743",
    "sg:postcode":"75251",
    "sg:province":"TX",
    "sg:tags":[
        "spa",
        "medical"
    ],
    "sg:website":"www.SpaInTheCity570.com",
    "wof:name":"Spa in the City",
    "wof:placetype":"venue"
},
  "geometry": {"coordinates":[-96.774466,32.911081],"type":"Point"}
}