{
  "type": "Feature",
  "properties": {
    "iso:country":"US",
    "sg:address":"1507 Marlee Ln",
    "sg:city":"Arlington",
    "sg:classifiers":[
        {
            "category":"Professional",
            "type":"Services"
        }
    ],
    "sg:phone":"+1 817 265 4138",
    "sg:postcode":"76014",
    "sg:province":"TX",
    "wof:name":"Steel Detailing Svc",
    "wof:placetype":"venue"
},
  "geometry": {"coordinates":[-97.08807400000001,32.705041],"type":"Point"}
}