{
  "type": "Feature",
  "properties": {
    "iso:country":"US",
    "sg:address":"4601 Southwest Parkway",
    "sg:city":"Austin",
    "sg:classifiers":[
        {
            "category":"Personal",
            "subcategory":"Nail Salon",
            "type":"Services"
        }
    ],
    "sg:phone":"+1 512 891 6900",
    "sg:postcode":"78735",
    "sg:province":"TX",
    "wof:name":"Serenity Nails & Spa",
    "wof:placetype":"venue"
},
  "geometry": {"coordinates":[-97.830338,30.239889],"type":"Point"}
}