{
  "type": "Feature",
  "properties": {
    "iso:country":"US",
    "sg:address":"3109 Dublin Rd",
    "sg:city":"Allen",
    "sg:classifiers":[
        {
            "category":"Retail",
            "subcategory":"Veterinary Services",
            "type":"Services"
        }
    ],
    "sg:phone":"+1 972 424 7670",
    "sg:postcode":"75002",
    "sg:province":"TX",
    "wof:name":"Anne Fraser Matthews DMV",
    "wof:placetype":"venue"
},
  "geometry": {"coordinates":[-96.635772,33.035852],"type":"Point"}
}