{
  "type": "Feature",
  "properties": {
    "iso:country":"US",
    "sg:address":"615 Main St",
    "sg:city":"Garland",
    "sg:classifiers":[
        {
            "category":"Insurance",
            "subcategory":"Hazard Insurance",
            "type":"Services"
        },
        {
            "category":"Insurance",
            "subcategory":"Insurance Agent",
            "type":"Services"
        },
        {
            "category":"Insurance",
            "subcategory":"Life Insurance",
            "type":"Services"
        },
        {
            "category":"Insurance",
            "subcategory":"Title Insurance",
            "type":"Services"
        }
    ],
    "sg:phone":"+1 972 494 2200",
    "sg:postcode":"75040",
    "sg:province":"TX",
    "sg:tags":[
        "auto",
        "commercial",
        "business",
        "homeowner"
    ],
    "sg:website":"http://www.farmersagent.com/gpool/",
    "wof:name":"Gene Pool - Farmers Insurance",
    "wof:placetype":"venue"
},
  "geometry": {"coordinates":[-96.637953,32.912682],"type":"Point"}
}