{
  "type": "Feature",
  "properties": {
    "iso:country":"US",
    "sg:address":"327 N 16th St",
    "sg:city":"Junction",
    "sg:classifiers":[
        {
            "category":"Shopping",
            "subcategory":"Florist",
            "type":"Retail Goods"
        }
    ],
    "sg:phone":"+1 325 446 2525",
    "sg:postcode":"76849",
    "sg:province":"TX",
    "wof:name":"Country Florist & Nursery",
    "wof:placetype":"venue"
},
  "geometry": {"coordinates":[-99.776613,30.494128],"type":"Point"}
}