{
  "type": "Feature",
  "properties": {
    "iso:country":"US",
    "sg:address":"1821 E Yukon Rd",
    "sg:city":"Odessa",
    "sg:classifiers":[
        {
            "category":"Organizations",
            "subcategory":"Religious Organization",
            "type":"Services"
        }
    ],
    "sg:phone":"+1 432 552 0241",
    "sg:postcode":"79762",
    "sg:province":"TX",
    "sg:tags":[
        "church"
    ],
    "wof:name":"Cornerstone Worship Ctr Chr",
    "wof:placetype":"venue"
},
  "geometry": {"coordinates":[-102.376096,31.91441],"type":"Point"}
}