{
  "type": "Feature",
  "properties": {
    "iso:country":"US",
    "sg:address":"2200 Melissa St",
    "sg:city":"Arlington",
    "sg:classifiers":[
        {
            "category":"Building & Trades",
            "subcategory":"Landscaping Services",
            "type":"Services"
        }
    ],
    "sg:phone":"+1 817 274 4205",
    "sg:postcode":"76010",
    "sg:province":"TX",
    "sg:tags":[
        "lawn",
        "maintenance",
        "grounds"
    ],
    "sg:website":"www.weekenders.com",
    "wof:name":"Weekenders Complete Lawn Svc",
    "wof:placetype":"venue"
},
  "geometry": {"coordinates":[-97.070526,32.732084],"type":"Point"}
}