{
  "type": "Feature",
  "properties": {
    "iso:country":"US",
    "sg:address":"13505 Campesina Dr",
    "sg:city":"Austin",
    "sg:classifiers":[
        {
            "category":"Building & Trades",
            "subcategory":"Construction",
            "type":"Services"
        }
    ],
    "sg:phone":"+1 512 762 7001",
    "sg:postcode":"78727",
    "sg:province":"TX",
    "sg:tags":[
        "concrete",
        "contractor"
    ],
    "wof:name":"A & B Development Inc",
    "wof:placetype":"venue"
},
  "geometry": {"coordinates":[-97.687585,30.42832],"type":"Point"}
}