{
  "type": "Feature",
  "properties": {
    "iso:country":"US",
    "sg:address":"17105 State Hwy 123",
    "sg:city":"Seguin",
    "sg:classifiers":[
        {
            "category":"Building & Trades",
            "subcategory":"Plumbing",
            "type":"Services"
        }
    ],
    "sg:phone":"+1 830 379 3611",
    "sg:postcode":"78155",
    "sg:province":"TX",
    "sg:tags":[
        "conditioning",
        "contractor",
        "system",
        "air"
    ],
    "wof:name":"Absolute AC & Heating",
    "wof:placetype":"venue"
},
  "geometry": {"coordinates":[-97.952265,29.414412],"type":"Point"}
}