{
  "type": "Feature",
  "properties": {
    "iso:country":"US",
    "sg:address":"3660 Glenn Lakes Ln",
    "sg:city":"Missouri City",
    "sg:classifiers":[
        {
            "category":"Education",
            "subcategory":"School",
            "type":"Public Place"
        }
    ],
    "sg:phone":"+1 281 499 3141",
    "sg:postcode":"77459",
    "sg:province":"TX",
    "sg:tags":[
        "academic",
        "special"
    ],
    "sg:website":"www.texanamhmr.com",
    "wof:name":"Texana Mh & Mr Ctr",
    "wof:placetype":"venue"
},
  "geometry": {"coordinates":[-95.561474,29.563852],"type":"Point"}
}