{
  "type": "Feature",
  "properties": {
    "iso:country":"US",
    "sg:address":"707 Pleasant View Ave",
    "sg:city":"Brenham",
    "sg:classifiers":[
        {
            "category":"Real Estate",
            "subcategory":"Real Estate Agent",
            "type":"Services"
        },
        {
            "category":"Real Estate",
            "subcategory":"Real Estate Operator",
            "type":"Services"
        }
    ],
    "sg:phone":"+1 979 836 9204",
    "sg:postcode":"77833",
    "sg:province":"TX",
    "sg:tags":[
        "apartment"
    ],
    "wof:name":"Brenham Village Apartments",
    "wof:placetype":"venue"
},
  "geometry": {"coordinates":[-96.408557,30.170101],"type":"Point"}
}