{
  "type": "Feature",
  "properties": {
    "iso:country":"US",
    "sg:address":"2128 N Collins St",
    "sg:city":"Arlington",
    "sg:classifiers":[
        {
            "category":"Organizations",
            "subcategory":"Religious Organization",
            "type":"Services"
        }
    ],
    "sg:phone":"+1 817 860 1357",
    "sg:postcode":"76011",
    "sg:province":"TX",
    "sg:tags":[
        "church"
    ],
    "wof:name":"Abundant Life Worship Center",
    "wof:placetype":"venue"
},
  "geometry": {"coordinates":[-97.097098,32.768576],"type":"Point"}
}