{
  "type": "Feature",
  "properties": {
    "iso:country":"US",
    "sg:address":"1800 N Belt Line Rd",
    "sg:city":"Irving",
    "sg:classifiers":[
        {
            "category":"Shopping",
            "subcategory":"Florist",
            "type":"Retail Goods"
        }
    ],
    "sg:phone":"+1 972 313 3437",
    "sg:postcode":"75061",
    "sg:province":"TX",
    "wof:name":"Alotta Blossoms Florist",
    "wof:placetype":"venue"
},
  "geometry": {"coordinates":[-96.993647,32.835206],"type":"Point"}
}