{
  "type": "Feature",
  "properties": {
    "iso:country":"US",
    "sg:address":"6494 Brazos Dr",
    "sg:city":"College Station",
    "sg:classifiers":[
        {
            "category":"Professional",
            "type":"Services"
        }
    ],
    "sg:phone":"+1 979 690 9229",
    "sg:postcode":"77845",
    "sg:province":"TX",
    "wof:name":"Thomas B Lyne III",
    "wof:placetype":"venue"
},
  "geometry": {"coordinates":[-96.353066,30.530773],"type":"Point"}
}