{
  "type": "Feature",
  "properties": {
    "iso:country":"US",
    "sg:address":"6300 Ridglea Pl",
    "sg:city":"Fort Worth",
    "sg:classifiers":[
        {
            "category":"Professional",
            "subcategory":"Computer Services",
            "type":"Services"
        }
    ],
    "sg:phone":"+1 817 569 8920",
    "sg:postcode":"76116",
    "sg:province":"TX",
    "sg:tags":[
        "credit",
        "card"
    ],
    "sg:website":"www.chexcardonline.com",
    "wof:name":"MBSC",
    "wof:placetype":"venue"
},
  "geometry": {"coordinates":[-97.41809499999999,32.724086],"type":"Point"}
}