{
  "type": "Feature",
  "properties": {
    "iso:country":"US",
    "sg:address":"201 E 9th St # 3",
    "sg:city":"Dallas",
    "sg:classifiers":[
        {
            "category":"Education",
            "subcategory":"School",
            "type":"Public Place"
        }
    ],
    "sg:phone":"+1 972 749 1400",
    "sg:postcode":"75203",
    "sg:province":"TX",
    "wof:name":"Schools",
    "wof:placetype":"venue"
},
  "geometry": {"coordinates":[-96.822075,32.746951],"type":"Point"}
}