{
  "type": "Feature",
  "properties": {
    "iso:country":"US",
    "sg:address":"1100 Como St S",
    "sg:city":"Sulphur Springs",
    "sg:classifiers":[
        {
            "category":"Freight",
            "type":"Transportation"
        }
    ],
    "sg:phone":"+1 903 885 0031",
    "sg:postcode":"75482",
    "sg:province":"TX",
    "sg:tags":[
        "trucking"
    ],
    "wof:name":"ABF Freight System Inc",
    "wof:placetype":"venue"
},
  "geometry": {"coordinates":[-95.586018,33.124762],"type":"Point"}
}