{
  "type": "Feature",
  "properties": {
    "iso:country":"US",
    "sg:address":"102 N Peach St",
    "sg:city":"Laredo",
    "sg:classifiers":[
        {
            "category":"Wholesale",
            "subcategory":"Machinery & Supplies",
            "type":"Manufacturing & Wholesale Goods"
        }
    ],
    "sg:phone":"+1 956 723 5057",
    "sg:postcode":"78061",
    "sg:province":"TX",
    "sg:tags":[
        "fitting",
        "hose",
        "coupling"
    ],
    "wof:name":"Mc Carty Equipment Co",
    "wof:placetype":"venue"
},
  "geometry": {"coordinates":[-99.098209,28.894107],"type":"Point"}
}