{
  "type": "Feature",
  "properties": {
    "iso:country":"US",
    "sg:address":"11079 FM 1388",
    "sg:city":"Scurry",
    "sg:classifiers":[
        {
            "category":"Shopping",
            "subcategory":"Discount & Variety Stores",
            "type":"Retail Goods"
        }
    ],
    "sg:phone":"+1 972 452 8026",
    "sg:postcode":"75158",
    "sg:province":"TX",
    "sg:tags":[
        "merchandise",
        "general"
    ],
    "wof:name":"Preferred Sales",
    "wof:placetype":"venue"
},
  "geometry": {"coordinates":[-96.33585600000001,32.504117],"type":"Point"}
}