{
  "type": "Feature",
  "properties": {
    "iso:country":"US",
    "sg:address":"2508 10th Ave",
    "sg:city":"Canyon",
    "sg:classifiers":[
        {
            "category":"Building & Trades",
            "subcategory":"Construction",
            "type":"Services"
        }
    ],
    "sg:phone":"+1 806 656 0180",
    "sg:postcode":"79015",
    "sg:province":"TX",
    "sg:tags":[
        "general",
        "contractor"
    ],
    "wof:name":"Joe Burnett Construction",
    "wof:placetype":"venue"
},
  "geometry": {"coordinates":[-101.915792,34.973518],"type":"Point"}
}