{
  "type": "Feature",
  "properties": {
    "iso:country":"US",
    "sg:address":"3215 Ivory Point Dr",
    "sg:city":"League City",
    "sg:classifiers":[
        {
            "category":"Health Services",
            "subcategory":"Optometrist",
            "type":"Services"
        }
    ],
    "sg:phone":"+1 281 334 7697",
    "sg:postcode":"77573",
    "sg:province":"TX",
    "wof:name":"Zeinep O Echetebu Od PHD P",
    "wof:placetype":"venue"
},
  "geometry": {"coordinates":[-95.03877900000001,29.520395],"type":"Point"}
}