{
  "type": "Feature",
  "properties": {
    "iso:country":"US",
    "sg:address":"512 Vonda Dr",
    "sg:city":"Sulphur Springs",
    "sg:classifiers":[
        {
            "category":"Education",
            "subcategory":"Special Training",
            "type":"Public Place"
        },
        {
            "category":"Mining & Drilling",
            "type":"Manufacturing & Wholesale Goods"
        }
    ],
    "sg:phone":"+1 903 438 2707",
    "sg:postcode":"75482",
    "sg:province":"TX",
    "sg:tags":[
        "field",
        "school",
        "instruction",
        "art"
    ],
    "wof:name":"Carolyn's Oil Painting",
    "wof:placetype":"venue"
},
  "geometry": {"coordinates":[-95.586258,33.108798],"type":"Point"}
}