{
  "type": "Feature",
  "properties": {
    "iso:country":"US",
    "sg:address":"600 Commerce St",
    "sg:city":"Dallas",
    "sg:classifiers":[
        {
            "category":"Government",
            "subcategory":"Office",
            "type":"Public Place"
        }
    ],
    "sg:phone":"+1 214 653 7121",
    "sg:postcode":"75202",
    "sg:province":"TX",
    "wof:name":"County Constable",
    "wof:placetype":"venue"
},
  "geometry": {"coordinates":[-96.80586,32.778433],"type":"Point"}
}