{
  "type": "Feature",
  "properties": {
    "iso:country":"US",
    "sg:address":"18300 Doe Run Creek Ln",
    "sg:city":"Washington",
    "sg:classifiers":[
        {
            "category":"Organizations",
            "subcategory":"Political Organization",
            "type":"Services"
        }
    ],
    "sg:phone":"+1 936 878 2737",
    "sg:postcode":"77880",
    "sg:province":"TX",
    "wof:name":"Acafo",
    "wof:placetype":"venue"
},
  "geometry": {"coordinates":[-96.156702,30.267087],"type":"Point"}
}