{
  "type": "Feature",
  "properties": {
    "iso:country":"US",
    "sg:address":"1227 S Murphy St",
    "sg:city":"Odessa",
    "sg:classifiers":[
        {
            "category":"Building & Trades",
            "subcategory":"Construction",
            "type":"Services"
        }
    ],
    "sg:phone":"+1 432 335 9811",
    "sg:postcode":"79766",
    "sg:province":"TX",
    "sg:tags":[
        "painter"
    ],
    "wof:name":"Arrow Construction Co",
    "wof:placetype":"venue"
},
  "geometry": {"coordinates":[-102.322222,31.848554],"type":"Point"}
}