{
  "type": "Feature",
  "properties": {
    "iso:country":"US",
    "sg:address":"7301 Whitehall St",
    "sg:city":"Richland Hills",
    "sg:classifiers":[
        {
            "category":"Wholesale",
            "subcategory":"Machinery & Supplies",
            "type":"Manufacturing & Wholesale Goods"
        }
    ],
    "sg:phone":"+1 817 595 2244",
    "sg:postcode":"76118",
    "sg:province":"TX",
    "sg:tags":[
        "tubing",
        "hose",
        "plastic"
    ],
    "sg:website":"www.wilson-co.com",
    "wof:name":"Wilson Co",
    "wof:placetype":"venue"
},
  "geometry": {"coordinates":[-97.21699599999999,32.807111],"type":"Point"}
}