{
  "type": "Feature",
  "properties": {
    "iso:country":"US",
    "sg:address":"1506 W Pioneer Pkwy",
    "sg:city":"Arlington",
    "sg:classifiers":[
        {
            "category":"Banks & Credit Unions",
            "subcategory":"Investment Brokerage",
            "type":"Services"
        }
    ],
    "sg:phone":"+1 817 274 2224",
    "sg:postcode":"76013",
    "sg:province":"TX",
    "sg:tags":[
        "tax"
    ],
    "wof:name":"McGill Financial Group",
    "wof:placetype":"venue"
},
  "geometry": {"coordinates":[-97.13046300000001,32.708932],"type":"Point"}
}