{
  "type": "Feature",
  "properties": {
    "iso:country":"US",
    "sg:address":"2505 Wheelwright Pl",
    "sg:city":"Garland",
    "sg:classifiers":[
        {
            "category":"Professional",
            "subcategory":"Management & Consulting",
            "type":"Services"
        }
    ],
    "sg:phone":"+1 972 495 7705",
    "sg:postcode":"75044",
    "sg:province":"TX",
    "sg:tags":[
        "business"
    ],
    "wof:name":"Sharon Consulting Enterprises",
    "wof:placetype":"venue"
},
  "geometry": {"coordinates":[-96.667188,32.955958],"type":"Point"}
}