{
  "type": "Feature",
  "properties": {
    "iso:country":"US",
    "sg:address":"2911 Medical Arts St Ste 6",
    "sg:city":"Austin",
    "sg:classifiers":[
        {
            "category":"Health Services",
            "subcategory":"Doctor",
            "type":"Services"
        }
    ],
    "sg:phone":"+1 512 476 6691",
    "sg:postcode":"78705",
    "sg:province":"TX",
    "sg:tags":[
        "gynecology",
        "physician",
        "surgeon",
        "surgeons",
        "obstetrics"
    ],
    "wof:name":"Price Bradley B MD",
    "wof:placetype":"venue"
},
  "geometry": {"coordinates":[-97.727591,30.288889],"type":"Point"}
}