{
  "type": "Feature",
  "properties": {
    "iso:country":"US",
    "sg:address":"2714 Hillcrest Dr",
    "sg:city":"San Antonio",
    "sg:classifiers":[
        {
            "category":"Personal",
            "subcategory":"Beauty Salon",
            "type":"Services"
        }
    ],
    "sg:phone":"+1 210 735 1019",
    "sg:postcode":"78228",
    "sg:province":"TX",
    "sg:tags":[
        "shop"
    ],
    "wof:name":"Margaret V Ruiz",
    "wof:placetype":"venue"
},
  "geometry": {"coordinates":[-98.559546,29.483891],"type":"Point"}
}