{
  "type": "Feature",
  "properties": {
    "iso:country":"US",
    "sg:address":"17907 Autumn Hills Dr",
    "sg:city":"Houston",
    "sg:classifiers":[
        {
            "category":"Professional",
            "subcategory":"Computer Services",
            "type":"Services"
        }
    ],
    "sg:phone":"+1 281 463 6795",
    "sg:postcode":"77084",
    "sg:province":"TX",
    "sg:tags":[
        "system",
        "integration"
    ],
    "wof:name":"Complete Computing Inc",
    "wof:placetype":"venue"
},
  "geometry": {"coordinates":[-95.68073200000001,29.875728],"type":"Point"}
}