{
  "type": "Feature",
  "properties": {
    "iso:country":"US",
    "sg:address":"404 N 4th St",
    "sg:city":"Crockett",
    "sg:classifiers":[
        {
            "category":"Restaurant",
            "type":"Food & Drink"
        }
    ],
    "sg:phone":"+1 936 545 9974",
    "sg:postcode":"75835",
    "sg:province":"TX",
    "wof:name":"Las Comadres",
    "wof:placetype":"venue"
},
  "geometry": {"coordinates":[-95.457893,31.320563],"type":"Point"}
}