{
  "type": "Feature",
  "properties": {
    "iso:country":"US",
    "sg:address":"1008 Wilson Rd",
    "sg:city":"Lancaster",
    "sg:classifiers":[
        {
            "category":"Professional",
            "subcategory":"Management & Consulting",
            "type":"Services"
        }
    ],
    "sg:phone":"+1 972 227 7662",
    "sg:postcode":"75146",
    "sg:province":"TX",
    "wof:name":"Construction Consultants Assoc",
    "wof:placetype":"venue"
},
  "geometry": {"coordinates":[-96.73341499999999,32.567429],"type":"Point"}
}