{
  "type": "Feature",
  "properties": {
    "iso:country":"US",
    "sg:address":"27 State Hwy 75",
    "sg:city":"Huntsville",
    "sg:classifiers":[
        {
            "category":"Wholesale",
            "subcategory":"Chemicals & Plastics",
            "type":"Manufacturing & Wholesale Goods"
        }
    ],
    "sg:phone":"+1 936 295 0036",
    "sg:postcode":"77320",
    "sg:province":"TX",
    "wof:name":"Timberland Chemical",
    "wof:placetype":"venue"
},
  "geometry": {"coordinates":[-95.560282,30.72403],"type":"Point"}
}