{
  "type": "Feature",
  "properties": {
    "iso:country":"US",
    "sg:address":"112 W Pipeline Rd",
    "sg:city":"Hurst",
    "sg:classifiers":[
        {
            "category":"Professional",
            "subcategory":"Accounting & Tax Preparation",
            "type":"Services"
        }
    ],
    "sg:phone":"+1 817 391 0130",
    "sg:postcode":"76053",
    "sg:province":"TX",
    "sg:tags":[
        "billing"
    ],
    "wof:name":"Mtr. Mgmt. Services Inc.",
    "wof:placetype":"venue"
},
  "geometry": {"coordinates":[-97.167823,32.823585],"type":"Point"}
}