{
  "type": "Feature",
  "properties": {
    "iso:country":"US",
    "sg:address":"12323 Normont Dr",
    "sg:city":"Houston",
    "sg:classifiers":[
        {
            "category":"Professional",
            "subcategory":"Management & Consulting",
            "type":"Services"
        }
    ],
    "sg:phone":"+1 713 851 1277",
    "sg:postcode":"77070",
    "sg:province":"TX",
    "sg:tags":[
        "datum",
        "business"
    ],
    "wof:name":"Acd Ebusiness Solutions LLC",
    "wof:placetype":"venue"
},
  "geometry": {"coordinates":[-95.610798,29.98588],"type":"Point"}
}