{
  "type": "Feature",
  "properties": {
    "iso:country":"US",
    "sg:address":"317 Mill Creek Dr",
    "sg:city":"Salado",
    "sg:classifiers":[
        {
            "category":"Real Estate",
            "subcategory":"Real Estate Agent",
            "type":"Services"
        }
    ],
    "sg:phone":"+1 254 947 4409",
    "sg:postcode":"76571",
    "sg:province":"TX",
    "wof:name":"Charles Schreiner IV",
    "wof:placetype":"venue"
},
  "geometry": {"coordinates":[-97.53325700000001,30.956491],"type":"Point"}
}