{
  "type": "Feature",
  "properties": {
    "iso:country":"US",
    "sg:address":"1629 S Palo Duro St",
    "sg:city":"Amarillo",
    "sg:classifiers":[
        {
            "category":"Professional",
            "subcategory":"Business Services",
            "type":"Services"
        }
    ],
    "sg:phone":"+1 806 355 2796",
    "sg:postcode":"79106",
    "sg:province":"TX",
    "wof:name":"Ptm Enterprises",
    "wof:placetype":"venue"
},
  "geometry": {"coordinates":[-101.884995,35.197431],"type":"Point"}
}