{
  "type": "Feature",
  "properties": {
    "iso:country":"US",
    "sg:address":"13572 Tomball Parkway",
    "sg:city":"Houston",
    "sg:classifiers":[
        {
            "category":"Retail",
            "subcategory":"Auto Repair",
            "type":"Services"
        }
    ],
    "sg:phone":"+1 281 804 0933",
    "sg:postcode":"77086",
    "sg:province":"TX",
    "sg:tags":[
        "windshield",
        "installation"
    ],
    "sg:website":"www.patscowindshieldrepair.com/",
    "wof:name":"Patsco Windshield Repair : Bammel - North ?Houston",
    "wof:placetype":"venue"
},
  "geometry": {"coordinates":[-95.490503,29.918136],"type":"Point"}
}