{
  "type": "Feature",
  "properties": {
    "iso:country":"US",
    "sg:address":"7709 Inwood Rd",
    "sg:city":"Dallas",
    "sg:phone":"+1 214 358 1100",
    "sg:postcode":"75209",
    "sg:province":"TX",
    "wof:name":"Urban Bistro",
    "wof:placetype":"venue"
},
  "geometry": {"coordinates":[-96.82135,32.849413],"type":"Point"}
}