{
  "type": "Feature",
  "properties": {
    "iso:country":"US",
    "sg:address":"601 North Ave E",
    "sg:city":"Bryan",
    "sg:classifiers":[
        {
            "category":"Shopping",
            "subcategory":"Jewelry",
            "type":"Retail Goods"
        }
    ],
    "sg:phone":"+1 979 260 3989",
    "sg:postcode":"77801",
    "sg:province":"TX",
    "wof:name":"All That Glitters",
    "wof:placetype":"venue"
},
  "geometry": {"coordinates":[-96.34634800000001,30.637525],"type":"Point"}
}