{
  "type": "Feature",
  "properties": {
    "iso:country":"US",
    "sg:address":"725 Potosi Rd",
    "sg:city":"Abilene",
    "sg:classifiers":[
        {
            "category":"Farming",
            "subcategory":"Livestock Farm",
            "type":"Manufacturing & Wholesale Goods"
        }
    ],
    "sg:phone":"+1 325 698 6979",
    "sg:postcode":"79602",
    "sg:province":"TX",
    "sg:tags":[
        "beef",
        "feedlot",
        "cattle"
    ],
    "wof:name":"Floyd G McComas Co",
    "wof:placetype":"venue"
},
  "geometry": {"coordinates":[-99.65642200000001,32.403988],"type":"Point"}
}