{
  "type": "Feature",
  "properties": {
    "iso:country":"US",
    "sg:address":"6730 Doniphan Dr",
    "sg:city":"Canutillo",
    "sg:classifiers":[
        {
            "category":"Professional",
            "type":"Services"
        },
        {
            "category":"Restaurant",
            "type":"Food & Drink"
        }
    ],
    "sg:phone":"+1 915 877 1022",
    "sg:postcode":"79835",
    "sg:province":"TX",
    "wof:name":"Flautas Vaqueras",
    "wof:placetype":"venue"
},
  "geometry": {"coordinates":[-106.59926400000001,31.901072],"type":"Point"}
}