{
  "type": "Feature",
  "properties": {
    "iso:country":"US",
    "sg:address":"511 E Broadway St",
    "sg:city":"Cuero",
    "sg:classifiers":[
        {
            "category":"Autos & Motor Vehicles",
            "subcategory":"Automobile Sales",
            "type":"Retail Goods"
        }
    ],
    "sg:phone":"+1 361 275 6161",
    "sg:postcode":"77954",
    "sg:province":"TX",
    "sg:tags":[
        "car",
        "dealer"
    ],
    "wof:name":"Duckett Motor Co",
    "wof:placetype":"venue"
},
  "geometry": {"coordinates":[-97.285633,29.092054],"type":"Point"}
}