{
  "type": "Feature",
  "properties": {
    "iso:country":"US",
    "sg:address":"1904 Goodrich Ave Ste 8",
    "sg:city":"Austin",
    "sg:classifiers":[
        {
            "category":"Building & Trades",
            "subcategory":"Construction",
            "type":"Services"
        }
    ],
    "sg:phone":"+1 512 560 1004",
    "sg:postcode":"78704",
    "sg:province":"TX",
    "sg:tags":[
        "deck",
        "altering",
        "consultant",
        "builder",
        "carpenter",
        "contractor",
        "remodeling",
        "fence-sales"
    ],
    "wof:name":"2-J Enterprises",
    "wof:placetype":"venue"
},
  "geometry": {"coordinates":[-97.770993,30.252368],"type":"Point"}
}