{
  "type": "Feature",
  "properties": {
    "iso:country":"US",
    "sg:address":"208 E Wheeler Ave",
    "sg:city":"Aransas Pass",
    "sg:classifiers":[
        {
            "category":"Bars & Pubs",
            "type":"Food & Drink"
        }
    ],
    "sg:phone":"+1 361 758 6487",
    "sg:postcode":"78336",
    "sg:province":"TX",
    "sg:tags":[
        "drinking"
    ],
    "wof:name":"Bonnies Bar",
    "wof:placetype":"venue"
},
  "geometry": {"coordinates":[-97.142568,27.905429],"type":"Point"}
}