{
  "type": "Feature",
  "properties": {
    "iso:country":"US",
    "sg:address":"3210 Belt Line Rd",
    "sg:city":"Farmers Branch",
    "sg:classifiers":[
        {
            "category":"Professional",
            "type":"Services"
        }
    ],
    "sg:phone":"+1 972 788 2072",
    "sg:postcode":"75234",
    "sg:province":"TX",
    "sg:tags":[
        "establishment"
    ],
    "wof:name":"Exeter Partners",
    "wof:placetype":"venue"
},
  "geometry": {"coordinates":[-96.869168,32.953247],"type":"Point"}
}