{
  "type": "Feature",
  "properties": {
    "iso:country":"US",
    "sg:address":"4020 Navigation Blvd",
    "sg:city":"Houston",
    "sg:classifiers":[
        {
            "category":"Professional",
            "type":"Services"
        }
    ],
    "sg:phone":"+1 713 222 0046",
    "sg:postcode":"77003",
    "sg:province":"TX",
    "sg:tags":[
        "establishment"
    ],
    "wof:name":"Mi Suerte",
    "wof:placetype":"venue"
},
  "geometry": {"coordinates":[-95.33168000000001,29.753896],"type":"Point"}
}