{
  "type": "Feature",
  "properties": {
    "iso:country":"US",
    "sg:address":"3730 N Piedras St",
    "sg:city":"El Paso",
    "sg:classifiers":[
        {
            "category":"Real Estate",
            "subcategory":"Real Estate Operator",
            "type":"Services"
        }
    ],
    "sg:phone":"+1 915 566 6644",
    "sg:postcode":"79930",
    "sg:province":"TX",
    "sg:tags":[
        "building",
        "apartment"
    ],
    "wof:name":"Grandview Apts",
    "wof:placetype":"venue"
},
  "geometry": {"coordinates":[-106.46126599999999,31.810195],"type":"Point"}
}