{
  "type": "Feature",
  "properties": {
    "iso:country":"US",
    "sg:address":"9430 Concourse Dr",
    "sg:city":"Houston",
    "sg:classifiers":[
        {
            "category":"Social Services",
            "subcategory":"Child Care",
            "type":"Services"
        }
    ],
    "sg:phone":"+1 713 353 1050",
    "sg:postcode":"77036",
    "sg:province":"TX",
    "wof:name":"Babies R Us Daycare",
    "wof:placetype":"venue"
},
  "geometry": {"coordinates":[-95.555976,29.679487],"type":"Point"}
}