{
  "type": "Feature",
  "properties": {
    "iso:country":"US",
    "sg:address":"304 Coit Rd",
    "sg:city":"Plano",
    "sg:classifiers":[
        {
            "category":"Shopping",
            "subcategory":"Clothing, Apparel, & Fashions",
            "type":"Retail Goods"
        }
    ],
    "sg:phone":"+1 972 673 0929",
    "sg:postcode":"75075",
    "sg:province":"TX",
    "wof:name":"Pappagallo",
    "wof:placetype":"venue"
},
  "geometry": {"coordinates":[-96.76793499999999,33.001992],"type":"Point"}
}