{
  "type": "Feature",
  "properties": {
    "iso:country":"US",
    "sg:address":"9514 Telephone Rd",
    "sg:city":"Houston",
    "sg:classifiers":[
        {
            "category":"Autos & Motor Vehicles",
            "subcategory":"Auto Supplies",
            "type":"Retail Goods"
        }
    ],
    "sg:phone":"+1 713 991 5015",
    "sg:postcode":"77075",
    "sg:province":"TX",
    "sg:tags":[
        "tire"
    ],
    "wof:name":"All Pro Tire",
    "wof:placetype":"venue"
},
  "geometry": {"coordinates":[-95.285599,29.627501],"type":"Point"}
}