{
  "type": "Feature",
  "properties": {
    "iso:country":"US",
    "sg:address":"10916 Bywood Dr",
    "sg:city":"El Paso",
    "sg:classifiers":[
        {
            "category":"Building & Trades",
            "subcategory":"Electrical",
            "type":"Services"
        }
    ],
    "sg:phone":"+1 915 592 3453",
    "sg:postcode":"79936",
    "sg:province":"TX",
    "sg:tags":[
        "electrical",
        "contractor"
    ],
    "wof:name":"Advance Home Networks",
    "wof:placetype":"venue"
},
  "geometry": {"coordinates":[-106.321172,31.779943],"type":"Point"}
}