{
  "type": "Feature",
  "properties": {
    "iso:country":"US",
    "sg:address":"7101 Whitley Rd",
    "sg:city":"Watauga",
    "sg:classifiers":[
        {
            "category":"Government",
            "subcategory":"Police Station",
            "type":"Public Place"
        }
    ],
    "sg:phone":"+1 817 281 3307",
    "sg:postcode":"76148",
    "sg:province":"TX",
    "sg:tags":[
        "department"
    ],
    "wof:name":"Watauga Police Dept",
    "wof:placetype":"venue"
},
  "geometry": {"coordinates":[-97.255077,32.87387],"type":"Point"}
}