{
  "type": "Feature",
  "properties": {
    "iso:country":"US",
    "sg:address":"12825 Sunset Dune Dr",
    "sg:city":"Houston",
    "sg:classifiers":[
        {
            "category":"Shopping",
            "subcategory":"Computers & Home Electronics",
            "type":"Retail Goods"
        }
    ],
    "sg:phone":"+1 713 816 9050",
    "sg:postcode":"77082",
    "sg:province":"TX",
    "sg:tags":[
        "support",
        "tech"
    ],
    "wof:name":"Computers Etc",
    "wof:placetype":"venue"
},
  "geometry": {"coordinates":[-95.611425,29.722548],"type":"Point"}
}