{
  "type": "Feature",
  "properties": {
    "iso:country":"US",
    "sg:address":"6105 Shadow Mountain Dr",
    "sg:city":"Austin",
    "sg:classifiers":[
        {
            "category":"Professional",
            "subcategory":"Computer Services",
            "type":"Services"
        }
    ],
    "sg:phone":"+1 512 345 8988",
    "sg:postcode":"78731",
    "sg:province":"TX",
    "sg:tags":[
        "related"
    ],
    "wof:name":"River City Assoc Inc",
    "wof:placetype":"venue"
},
  "geometry": {"coordinates":[-97.761076,30.348572],"type":"Point"}
}