{
  "type": "Feature",
  "properties": {
    "iso:country":"US",
    "sg:address":"2817 Bennington St",
    "sg:city":"Houston",
    "sg:classifiers":[
        {
            "category":"Restaurant",
            "type":"Food & Drink"
        }
    ],
    "sg:phone":"+1 713 691 9988",
    "sg:postcode":"77093",
    "sg:province":"TX",
    "wof:name":"Joseph's House Drive-In Restaurant",
    "wof:placetype":"venue"
},
  "geometry": {"coordinates":[-95.34229999999999,29.822001],"type":"Point"}
}