{
  "type": "Feature",
  "properties": {
    "iso:country":"US",
    "sg:address":"808 S Halbryan St",
    "sg:city":"Eastland",
    "sg:classifiers":[
        {
            "category":"Professional",
            "type":"Services"
        }
    ],
    "sg:phone":"+1 254 629 2856",
    "sg:postcode":"76448",
    "sg:province":"TX",
    "wof:name":"J T Horn Oil Co Inc A Corpor",
    "wof:placetype":"venue"
},
  "geometry": {"coordinates":[-98.814639,32.394439],"type":"Point"}
}