{
  "type": "Feature",
  "properties": {
    "iso:country":"US",
    "sg:address":"711 Texas Ave",
    "sg:city":"La Marque",
    "sg:classifiers":[
        {
            "category":"Professional",
            "subcategory":"Business Services",
            "type":"Services"
        }
    ],
    "sg:phone":"+1 409 935 1572",
    "sg:postcode":"77568",
    "sg:province":"TX",
    "wof:name":"Gulf Coast Entertainment",
    "wof:placetype":"venue"
},
  "geometry": {"coordinates":[-94.96418799999999,29.378925],"type":"Point"}
}