{
  "type": "Feature",
  "properties": {
    "iso:country":"US",
    "sg:address":"881 Pine St",
    "sg:city":"Abilene",
    "sg:classifiers":[
        {
            "category":"Retail",
            "subcategory":"Auto Repair",
            "type":"Services"
        }
    ],
    "sg:phone":"+1 325 672 7094",
    "sg:postcode":"79601",
    "sg:province":"TX",
    "sg:tags":[
        "repairing",
        "automobile",
        "general"
    ],
    "wof:name":"Dempsey's Auto Repair",
    "wof:placetype":"venue"
},
  "geometry": {"coordinates":[-99.73202999999999,32.458784],"type":"Point"}
}