{
  "type": "Feature",
  "properties": {
    "iso:country":"US",
    "sg:address":"5518 Dyer St",
    "sg:city":"Dallas",
    "sg:classifiers":[
        {
            "category":"Personal",
            "subcategory":"Beauty Salon",
            "type":"Services"
        }
    ],
    "sg:phone":"+1 469 569 0132",
    "sg:postcode":"75206",
    "sg:province":"TX",
    "sg:tags":[
        "makeup",
        "artist"
    ],
    "sg:website":"www.kcolaneri.com/",
    "wof:name":"Kristin Colaneri Make Up and Hair Design",
    "wof:placetype":"venue"
},
  "geometry": {"coordinates":[-96.77392,32.842894],"type":"Point"}
}