{
  "type": "Feature",
  "properties": {
    "iso:country":"US",
    "sg:address":"3041 Fondren Rd",
    "sg:city":"Houston",
    "sg:classifiers":[
        {
            "category":"Home & Garden",
            "subcategory":"Furniture",
            "type":"Retail Goods"
        }
    ],
    "sg:phone":"+1 713 339 2877",
    "sg:postcode":"77063",
    "sg:province":"TX",
    "sg:website":"www.nextfurniture.net",
    "wof:name":"Next Furniture Inc",
    "wof:placetype":"venue"
},
  "geometry": {"coordinates":[-95.52045699999999,29.732787],"type":"Point"}
}