{
  "type": "Feature",
  "properties": {
    "iso:country":"US",
    "sg:address":"4925 Lake Nocona Dr",
    "sg:city":"Corpus Christi",
    "sg:classifiers":[
        {
            "category":"Building & Trades",
            "subcategory":"Equipment Rental",
            "type":"Services"
        }
    ],
    "sg:phone":"+1 361 993 2709",
    "sg:postcode":"78413",
    "sg:province":"TX",
    "wof:name":"Moya Moonwalk Rentals",
    "wof:placetype":"venue"
},
  "geometry": {"coordinates":[-97.406004,27.674369],"type":"Point"}
}