{
  "type": "Feature",
  "properties": {
    "iso:country":"US",
    "sg:address":"5721 E Rosedale St",
    "sg:city":"Fort Worth",
    "sg:classifiers":[
        {
            "category":"Manufacturing",
            "subcategory":"Tools & Machinery",
            "type":"Manufacturing & Wholesale Goods"
        }
    ],
    "sg:phone":"+1 817 429 0349",
    "sg:postcode":"76112",
    "sg:province":"TX",
    "sg:tags":[
        "machine",
        "shop"
    ],
    "wof:name":"Sunrise Tool & Manufacturing",
    "wof:placetype":"venue"
},
  "geometry": {"coordinates":[-97.233289,32.729771],"type":"Point"}
}