{
  "type": "Feature",
  "properties": {
    "iso:country":"US",
    "sg:address":"2603 Texas Blvd",
    "sg:city":"Texarkana",
    "sg:classifiers":[
        {
            "category":"Social Services",
            "type":"Services"
        }
    ],
    "sg:phone":"+1 903 794 1398",
    "sg:postcode":"75503",
    "sg:province":"TX",
    "sg:tags":[
        "organization",
        "welfare"
    ],
    "wof:name":"Harvest Texarkana",
    "wof:placetype":"venue"
},
  "geometry": {"coordinates":[-94.05317599999999,33.442293],"type":"Point"}
}