{
  "type": "Feature",
  "properties": {
    "iso:country":"US",
    "sg:address":"12924 US Hwy 259",
    "sg:city":"Nacogdoches",
    "sg:classifiers":[
        {
            "category":"Retail",
            "subcategory":"Repair Shop",
            "type":"Services"
        }
    ],
    "sg:phone":"+1 936 564 6232",
    "sg:postcode":"75965",
    "sg:province":"TX",
    "sg:tags":[
        "welding"
    ],
    "wof:name":"Nacogdoches Ornamental Iron",
    "wof:placetype":"venue"
},
  "geometry": {"coordinates":[-94.67661699999999,31.734583],"type":"Point"}
}