{
  "type": "Feature",
  "properties": {
    "iso:country":"US",
    "sg:address":"203 N Sandra St",
    "sg:city":"Conroe",
    "sg:classifiers":[
        {
            "category":"Retail",
            "subcategory":"Auto Repair",
            "type":"Services"
        }
    ],
    "sg:phone":"+1 936 756 0022",
    "sg:postcode":"77301",
    "sg:province":"TX",
    "sg:tags":[
        "body",
        "automotive",
        "painting",
        "shop",
        "automobile"
    ],
    "wof:name":"Tommy's Paint & Body",
    "wof:placetype":"venue"
},
  "geometry": {"coordinates":[-95.464034,30.309298],"type":"Point"}
}