{
  "type": "Feature",
  "properties": {
    "iso:country":"US",
    "sg:address":"1807 W Slaughter Ln",
    "sg:city":"Austin",
    "sg:classifiers":[
        {
            "category":"Sports & Exercise",
            "subcategory":"Gym",
            "type":"Entertainment"
        },
        {
            "category":"Arena",
            "subcategory":"Sports Club",
            "type":"Entertainment"
        }
    ],
    "sg:phone":"+1 512 501 1342",
    "sg:postcode":"78748",
    "sg:province":"TX",
    "sg:tags":[
        "program",
        "health",
        "physical",
        "fitness"
    ],
    "sg:website":"http://planetfitness1.reachlocal.com/?scid=1657110",
    "wof:name":"Affordable Health Club",
    "wof:placetype":"venue"
},
  "geometry": {"coordinates":[-97.822609,30.173665],"type":"Point"}
}