{
  "type": "Feature",
  "properties": {
    "iso:country":"US",
    "sg:address":"2917 Fairmount St",
    "sg:city":"Dallas",
    "sg:classifiers":[
        {
            "category":"Bars & Pubs",
            "type":"Food & Drink"
        },
        {
            "category":"Restaurant",
            "type":"Food & Drink"
        },
        {
            "category":"Fast Food",
            "type":"Food & Drink"
        }
    ],
    "sg:phone":"+1 214 880 7414",
    "sg:postcode":"75201",
    "sg:province":"TX",
    "sg:tags":[
        "burger",
        "american",
        "new"
    ],
    "sg:website":"www.thecommontable.com/",
    "wof:name":"The Common Table",
    "wof:placetype":"venue"
},
  "geometry": {"coordinates":[-96.80624400000001,32.798165],"type":"Point"}
}