{
  "type": "Feature",
  "properties": {
    "iso:country":"US",
    "sg:address":"302 Illinois St",
    "sg:city":"Texhoma",
    "sg:classifiers":[
        {
            "category":"Personal",
            "subcategory":"Beauty Salon",
            "type":"Services"
        }
    ],
    "sg:phone":"+1 580 423 7787",
    "sg:postcode":"73949",
    "sg:province":"TX",
    "wof:name":"Luci's Hair Review",
    "wof:placetype":"venue"
},
  "geometry": {"coordinates":[-101.785588,36.510211],"type":"Point"}
}