{
  "type": "Feature",
  "properties": {
    "iso:country":"US",
    "sg:address":"3700 Reagan Dr",
    "sg:city":"Fort Worth",
    "sg:classifiers":[
        {
            "category":"Building & Trades",
            "subcategory":"Construction",
            "type":"Services"
        }
    ],
    "sg:phone":"+1 817 246 7779",
    "sg:postcode":"76116",
    "sg:province":"TX",
    "sg:tags":[
        "insulation",
        "heat",
        "contractor"
    ],
    "sg:website":"www.a-betterinsulation.com",
    "wof:name":"A-Better Insulation",
    "wof:placetype":"venue"
},
  "geometry": {"coordinates":[-97.447712,32.71627],"type":"Point"}
}