{
  "type": "Feature",
  "properties": {
    "iso:country":"US",
    "sg:address":"4451 Lovers Ln",
    "sg:city":"Dallas",
    "sg:classifiers":[
        {
            "category":"Home & Garden",
            "subcategory":"Household Appliances",
            "type":"Retail Goods"
        }
    ],
    "sg:phone":"+1 214 521 2558",
    "sg:postcode":"75225",
    "sg:province":"TX",
    "sg:tags":[
        "cleaner",
        "repair",
        "vacuum"
    ],
    "wof:name":"All Vac Inc",
    "wof:placetype":"venue"
},
  "geometry": {"coordinates":[-96.811798,32.851002],"type":"Point"}
}