{
  "type": "Feature",
  "properties": {
    "iso:country":"US",
    "sg:address":"702 N 8th St",
    "sg:city":"Temple",
    "sg:classifiers":[
        {
            "category":"Professional",
            "subcategory":"Computer Services",
            "type":"Services"
        }
    ],
    "sg:phone":"+1 254 774 7723",
    "sg:postcode":"76501",
    "sg:province":"TX",
    "wof:name":"Uce Enterprises",
    "wof:placetype":"venue"
},
  "geometry": {"coordinates":[-97.334728,31.10272],"type":"Point"}
}