{
  "type": "Feature",
  "properties": {
    "iso:country":"US",
    "sg:address":"1613 W 7th St",
    "sg:city":"Texarkana",
    "sg:classifiers":[
        {
            "category":"Retail",
            "subcategory":"Laundry & Dry Cleaning",
            "type":"Services"
        }
    ],
    "sg:phone":"+1 903 792 1025",
    "sg:postcode":"75501",
    "sg:province":"TX",
    "sg:tags":[
        "cleaner",
        "operated",
        "dryer",
        "laundries-self",
        "washer",
        "coin"
    ],
    "wof:name":"New York Coin Laundry",
    "wof:placetype":"venue"
},
  "geometry": {"coordinates":[-94.05929999999999,33.423218],"type":"Point"}
}