{
  "type": "Feature",
  "properties": {
    "iso:country":"US",
    "sg:address":"19 Macarthur Dr",
    "sg:city":"Denison",
    "sg:classifiers":[
        {
            "category":"Shopping",
            "subcategory":"Gifts & Souvenirs",
            "type":"Retail Goods"
        }
    ],
    "sg:phone":"+1 903 786 6192",
    "sg:postcode":"75020",
    "sg:province":"TX",
    "wof:name":"Enchanted Fantasies Unlimited",
    "wof:placetype":"venue"
},
  "geometry": {"coordinates":[-96.656694,33.712412],"type":"Point"}
}