{
  "type": "Feature",
  "properties": {
    "iso:country":"US",
    "sg:address":"313 Parkview Pl",
    "sg:city":"Coppell",
    "sg:classifiers":[
        {
            "category":"Professional",
            "type":"Services"
        }
    ],
    "sg:phone":"+1 972 471 2177",
    "sg:postcode":"75019",
    "sg:province":"TX",
    "wof:name":"Ltd Society",
    "wof:placetype":"venue"
},
  "geometry": {"coordinates":[-96.983845,32.97874],"type":"Point"}
}