{
  "type": "Feature",
  "properties": {
    "iso:country":"US",
    "sg:address":"15115 Mesa Dr",
    "sg:city":"Humble",
    "sg:classifiers":[
        {
            "category":"Organizations",
            "subcategory":"Professional Association",
            "type":"Services"
        }
    ],
    "sg:phone":"+1 281 441 2620",
    "sg:postcode":"77396",
    "sg:province":"TX",
    "wof:name":"Audubon Park Condominium Assn",
    "wof:placetype":"venue"
},
  "geometry": {"coordinates":[-95.26848200000001,29.940457],"type":"Point"}
}