{
  "type": "Feature",
  "properties": {
    "iso:country":"US",
    "sg:address":"945 Old Black Colony Rd",
    "sg:city":"Buda",
    "sg:classifiers":[
        {
            "category":"Autos & Motor Vehicles",
            "subcategory":"Automobile Sales",
            "type":"Retail Goods"
        }
    ],
    "sg:phone":"+1 512 295 8209",
    "sg:postcode":"78610",
    "sg:province":"TX",
    "sg:tags":[
        "used"
    ],
    "wof:name":"Honest Engine Auto Sales",
    "wof:placetype":"venue"
},
  "geometry": {"coordinates":[-97.874624,30.085401],"type":"Point"}
}