{
  "type": "Feature",
  "properties": {
    "iso:country":"US",
    "sg:address":"9556 Indigo Brush Dr",
    "sg:city":"Austin",
    "sg:classifiers":[
        {
            "category":"Professional",
            "subcategory":"Management & Consulting",
            "type":"Services"
        }
    ],
    "sg:phone":"+1 512 335 6958",
    "sg:postcode":"78726",
    "sg:province":"TX",
    "wof:name":"Unite Family Management LLC",
    "wof:placetype":"venue"
},
  "geometry": {"coordinates":[-97.828855,30.43122],"type":"Point"}
}