{
  "type": "Feature",
  "properties": {
    "iso:country":"US",
    "sg:address":"72 Hassell St",
    "sg:city":"San Angelo",
    "sg:classifiers":[
        {
            "category":"Personal",
            "subcategory":"Beauty Salon",
            "type":"Services"
        }
    ],
    "sg:phone":"+1 325 942 1269",
    "sg:postcode":"76901",
    "sg:province":"TX",
    "wof:name":"Extensions",
    "wof:placetype":"venue"
},
  "geometry": {"coordinates":[-100.474718,31.447697],"type":"Point"}
}