{
  "type": "Feature",
  "properties": {
    "iso:country":"US",
    "sg:address":"1919 Walnut Plz",
    "sg:city":"Carrollton",
    "sg:classifiers":[
        {
            "category":"Real Estate",
            "subcategory":"Real Estate Operator",
            "type":"Services"
        }
    ],
    "sg:phone":"+1 972 418 8305",
    "sg:postcode":"75006",
    "sg:province":"TX",
    "sg:tags":[
        "apartment"
    ],
    "wof:name":"Estrada Apartments",
    "wof:placetype":"venue"
},
  "geometry": {"coordinates":[-96.889397,32.9561],"type":"Point"}
}