{
  "type": "Feature",
  "properties": {
    "iso:country":"US",
    "sg:address":"2690 County Rd",
    "sg:city":"Lexington",
    "sg:classifiers":[
        {
            "category":"Professional",
            "subcategory":"Management & Consulting",
            "type":"Services"
        }
    ],
    "sg:phone":"+1 512 856 1136",
    "sg:postcode":"78962",
    "sg:province":"TX",
    "sg:tags":[
        "business"
    ],
    "wof:name":"Doris Eldridge Consulting",
    "wof:placetype":"venue"
},
  "geometry": {"coordinates":[-96.773432,29.693515],"type":"Point"}
}