{
  "type": "Feature",
  "properties": {
    "iso:country":"US",
    "sg:address":"8600 Skyline Dr",
    "sg:city":"Dallas",
    "sg:classifiers":[
        {
            "category":"Professional",
            "type":"Services"
        }
    ],
    "sg:phone":"+1 214 345 9451",
    "sg:postcode":"75243",
    "sg:province":"TX",
    "sg:tags":[
        "establishment"
    ],
    "wof:name":"Callaway Belle",
    "wof:placetype":"venue"
},
  "geometry": {"coordinates":[-96.754869,32.907725],"type":"Point"}
}