{
  "type": "Feature",
  "properties": {
    "iso:country":"US",
    "sg:address":"10325 Cypresswood Dr",
    "sg:city":"Houston",
    "sg:classifiers":[
        {
            "category":"Organizations",
            "subcategory":"Professional Association",
            "type":"Services"
        }
    ],
    "sg:phone":"+1 281 477 6080",
    "sg:postcode":"77070",
    "sg:province":"TX",
    "sg:tags":[
        "business"
    ],
    "wof:name":"Pebble Investments",
    "wof:placetype":"venue"
},
  "geometry": {"coordinates":[-95.572596,29.977817],"type":"Point"}
}