{
  "type": "Feature",
  "properties": {
    "iso:country":"US",
    "sg:address":"4040 N Central Expy",
    "sg:city":"Dallas",
    "sg:classifiers":[
        {
            "category":"Real Estate",
            "subcategory":"Architect",
            "type":"Services"
        },
        {
            "category":"Professional",
            "subcategory":"Business Services",
            "type":"Services"
        }
    ],
    "sg:phone":"+1 214 823 5800",
    "sg:postcode":"75204",
    "sg:province":"TX",
    "sg:tags":[
        "design",
        "architecture"
    ],
    "wof:name":"Booth Architecture LLC",
    "wof:placetype":"venue"
},
  "geometry": {"coordinates":[-96.789068,32.815438],"type":"Point"}
}