{
  "type": "Feature",
  "properties": {
    "iso:country":"US",
    "sg:address":"2211 Texas Ave",
    "sg:city":"El Paso",
    "sg:classifiers":[
        {
            "category":"Restaurant",
            "type":"Food & Drink"
        }
    ],
    "sg:phone":"+1 915 351 8577",
    "sg:postcode":"79901",
    "sg:province":"TX",
    "sg:tags":[
        "parlor",
        "ice",
        "cream"
    ],
    "wof:name":"Fruitiki",
    "wof:placetype":"venue"
},
  "geometry": {"coordinates":[-106.46481900000001,31.773286],"type":"Point"}
}