{
  "type": "Feature",
  "properties": {
    "iso:country":"US",
    "sg:address":"126 Grandchase Dr",
    "sg:city":"Nederland",
    "sg:classifiers":[
        {
            "category":"Building & Trades",
            "subcategory":"Construction",
            "type":"Services"
        }
    ],
    "sg:phone":"+1 409 727 5780",
    "sg:postcode":"77627",
    "sg:province":"TX",
    "sg:tags":[
        "house"
    ],
    "wof:name":"Whaley Custom Homes Inc",
    "wof:placetype":"venue"
},
  "geometry": {"coordinates":[-94.011095,29.982856],"type":"Point"}
}