{
  "type": "Feature",
  "properties": {
    "iso:country":"US",
    "sg:address":"2303 Atkinson Ave",
    "sg:city":"Killeen",
    "sg:classifiers":[
        {
            "category":"Professional",
            "subcategory":"Management & Consulting",
            "type":"Services"
        },
        {
            "category":"Organizations",
            "subcategory":"Community Association",
            "type":"Services"
        }
    ],
    "sg:phone":"+1 254 526 7231",
    "sg:postcode":"76543",
    "sg:province":"TX",
    "sg:tags":[
        "consultant",
        "educational"
    ],
    "wof:name":"Alternative Teacher Cert Esc",
    "wof:placetype":"venue"
},
  "geometry": {"coordinates":[-97.707723,31.114975],"type":"Point"}
}