{
  "type": "Feature",
  "properties": {
    "iso:country":"US",
    "sg:address":"6933 Aspen Creek Ln",
    "sg:city":"Dallas",
    "sg:classifiers":[
        {
            "category":"Manufacturing",
            "subcategory":"Printing",
            "type":"Manufacturing & Wholesale Goods"
        }
    ],
    "sg:phone":"+1 972 769 8900",
    "sg:postcode":"75252",
    "sg:province":"TX",
    "sg:tags":[
        "printer"
    ],
    "wof:name":"Presslink Printing",
    "wof:placetype":"venue"
},
  "geometry": {"coordinates":[-96.782483,32.999673],"type":"Point"}
}