{
  "type": "Feature",
  "properties": {
    "iso:country":"US",
    "sg:address":"2741 E Belt Line Rd",
    "sg:city":"Carrollton",
    "sg:classifiers":[
        {
            "category":"Utilities",
            "subcategory":"Mobile Phone",
            "type":"Services"
        }
    ],
    "sg:phone":"+1 972 478 2351",
    "sg:postcode":"75006",
    "sg:province":"TX",
    "sg:tags":[
        "communication",
        "radiotelephone"
    ],
    "wof:name":"UNI Wireless Communication",
    "wof:placetype":"venue"
},
  "geometry": {"coordinates":[-96.86495600000001,32.953355],"type":"Point"}
}