{
  "type": "Feature",
  "properties": {
    "iso:country":"US",
    "sg:address":"201 College Ave",
    "sg:city":"Levelland",
    "sg:classifiers":[
        {
            "category":"Restaurant",
            "type":"Food & Drink"
        }
    ],
    "sg:phone":"+1 806 894 5902",
    "sg:postcode":"79336",
    "sg:province":"TX",
    "sg:tags":[
        "eating"
    ],
    "wof:name":"C & C Restaurants",
    "wof:placetype":"venue"
},
  "geometry": {"coordinates":[-102.367526,33.592082],"type":"Point"}
}