{
  "type": "Feature",
  "properties": {
    "iso:country":"US",
    "sg:address":"4820 Peach Tree Ln",
    "sg:city":"Garland",
    "sg:classifiers":[
        {
            "category":"Retail",
            "subcategory":"Portrait Studio",
            "type":"Services"
        }
    ],
    "sg:phone":"+1 972 530 4268",
    "sg:postcode":"75048",
    "sg:province":"TX",
    "sg:tags":[
        "photo"
    ],
    "wof:name":"Paul Dusza Photography",
    "wof:placetype":"venue"
},
  "geometry": {"coordinates":[-96.59054399999999,32.96737],"type":"Point"}
}