{
  "type": "Feature",
  "properties": {
    "iso:country":"US",
    "sg:address":"100 E Cano St",
    "sg:city":"Edinburg",
    "sg:classifiers":[
        {
            "category":"Government",
            "subcategory":"Office",
            "type":"Public Place"
        }
    ],
    "sg:phone":"+1 956 318 2299",
    "sg:postcode":"78539",
    "sg:province":"TX",
    "sg:tags":[
        "county",
        "safety",
        "order"
    ],
    "wof:name":"Hidalgo County Emergency Mgmt",
    "wof:placetype":"venue"
},
  "geometry": {"coordinates":[-98.16252799999999,26.300385],"type":"Point"}
}