{
  "type": "Feature",
  "properties": {
    "iso:country":"US",
    "sg:address":"5834 Windmier Ln",
    "sg:city":"Dallas",
    "sg:classifiers":[
        {
            "category":"Real Estate",
            "subcategory":"Architect",
            "type":"Services"
        }
    ],
    "sg:phone":"+1 972 250 1542",
    "sg:postcode":"75252",
    "sg:province":"TX",
    "sg:tags":[
        "architectural"
    ],
    "wof:name":"Robert T Chang Architect",
    "wof:placetype":"venue"
},
  "geometry": {"coordinates":[-96.806342,32.998665],"type":"Point"}
}