{
  "type": "Feature",
  "properties": {
    "iso:country":"US",
    "sg:address":"12557 Airport Dr",
    "sg:city":"Vernon",
    "sg:classifiers":[
        {
            "category":"Airport",
            "type":"Transportation"
        }
    ],
    "sg:phone":"+1 940 552 2182",
    "sg:postcode":"76384",
    "sg:province":"TX",
    "sg:tags":[
        "executive"
    ],
    "wof:name":"Wilbarger County",
    "wof:placetype":"venue"
},
  "geometry": {"coordinates":[-99.277052,34.220416],"type":"Point"}
}