{
  "type": "Feature",
  "properties": {
    "iso:country":"US",
    "sg:address":"9906 Stepney Green Dr",
    "sg:city":"Houston",
    "sg:classifiers":[
        {
            "category":"Building & Trades",
            "subcategory":"Landscaping Services",
            "type":"Services"
        }
    ],
    "sg:phone":"+1 281 370 3361",
    "sg:postcode":"77070",
    "sg:province":"TX",
    "wof:name":"Trees & Palms of Texas",
    "wof:placetype":"venue"
},
  "geometry": {"coordinates":[-95.568425,30.014953],"type":"Point"}
}