{
  "type": "Feature",
  "properties": {
    "iso:country":"US",
    "sg:address":"11203 Sageblossom Dr",
    "sg:city":"Houston",
    "sg:classifiers":[
        {
            "category":"Professional",
            "subcategory":"Computer Services",
            "type":"Services"
        }
    ],
    "sg:phone":"+1 713 410 9285",
    "sg:postcode":"77089",
    "sg:province":"TX",
    "sg:tags":[
        "consulting",
        "support"
    ],
    "wof:name":"Tccg",
    "wof:placetype":"venue"
},
  "geometry": {"coordinates":[-95.23730999999999,29.583206],"type":"Point"}
}