{
  "type": "Feature",
  "properties": {
    "iso:country":"US",
    "sg:address":"2057 Castle Dr Apt B",
    "sg:city":"Garland",
    "sg:classifiers":[
        {
            "category":"Real Estate",
            "subcategory":"Real Estate Services",
            "type":"Services"
        },
        {
            "category":"Real Estate",
            "subcategory":"Real Estate Operator",
            "type":"Services"
        }
    ],
    "sg:phone":"+1 972 276 9928",
    "sg:postcode":"75040",
    "sg:province":"TX",
    "sg:tags":[
        "vacancy",
        "apartment",
        "rental",
        "listing"
    ],
    "wof:name":"Castle Cove Apartments",
    "wof:placetype":"venue"
},
  "geometry": {"coordinates":[-96.603683,32.919369],"type":"Point"}
}