{
  "type": "Feature",
  "properties": {
    "iso:country":"US",
    "sg:address":"602 Territory Cove",
    "sg:city":"Cedar Park",
    "sg:classifiers":[
        {
            "category":"Professional",
            "subcategory":"Art Services",
            "type":"Services"
        }
    ],
    "sg:phone":"+1 512 731 8625",
    "sg:postcode":"78613",
    "sg:province":"TX",
    "sg:tags":[
        "web",
        "graphic",
        "design"
    ],
    "wof:name":"Casterline  Leesa",
    "wof:placetype":"venue"
},
  "geometry": {"coordinates":[-97.822996,30.517224],"type":"Point"}
}