{
  "type": "Feature",
  "properties": {
    "iso:country":"US",
    "sg:address":"1385 FM 359",
    "sg:city":"Richmond",
    "sg:classifiers":[
        {
            "category":"Retail",
            "subcategory":"Laundry & Dry Cleaning",
            "type":"Services"
        }
    ],
    "sg:phone":"+1 281 344 8299",
    "sg:postcode":"77469",
    "sg:province":"TX",
    "sg:tags":[
        "cleaners"
    ],
    "wof:name":"Country Cleaners",
    "wof:placetype":"venue"
},
  "geometry": {"coordinates":[-95.743487,29.617381],"type":"Point"}
}