{
  "type": "Feature",
  "properties": {
    "iso:country":"US",
    "sg:address":"1729 1st St",
    "sg:city":"Palacios",
    "sg:classifiers":[
        {
            "category":"Manufacturing",
            "subcategory":"Watercraft",
            "type":"Manufacturing & Wholesale Goods"
        }
    ],
    "sg:phone":"+1 361 972 6629",
    "sg:postcode":"77465",
    "sg:province":"TX",
    "sg:tags":[
        "boat"
    ],
    "wof:name":"Tran's Fiberglass Boat",
    "wof:placetype":"venue"
},
  "geometry": {"coordinates":[-96.210325,28.719771],"type":"Point"}
}