{
  "type": "Feature",
  "properties": {
    "iso:country":"US",
    "sg:address":"5704 Fondren Rd",
    "sg:city":"Houston",
    "sg:classifiers":[
        {
            "category":"Restaurant",
            "type":"Food & Drink"
        }
    ],
    "sg:phone":"+1 713 278 2227",
    "sg:postcode":"77036",
    "sg:province":"TX",
    "sg:tags":[
        "eating"
    ],
    "wof:name":"Pupuseria Carmelita 2 Inc",
    "wof:placetype":"venue"
},
  "geometry": {"coordinates":[-95.520066,29.717827],"type":"Point"}
}