{
  "type": "Feature",
  "properties": {
    "iso:country":"US",
    "sg:address":"266 Co Rd 911",
    "sg:city":"Royse City",
    "sg:classifiers":[
        {
            "category":"Manufacturing",
            "subcategory":"Tools & Machinery",
            "type":"Manufacturing & Wholesale Goods"
        }
    ],
    "sg:phone":"+1 214 808 0392",
    "sg:postcode":"75189",
    "sg:province":"TX",
    "sg:tags":[
        "mfg",
        "apparatus",
        "welding"
    ],
    "wof:name":"Randy Williams Co",
    "wof:placetype":"venue"
},
  "geometry": {"coordinates":[-96.366727,32.993727],"type":"Point"}
}