{
  "type": "Feature",
  "properties": {
    "iso:country":"US",
    "sg:address":"828 S Frazier St",
    "sg:city":"Conroe",
    "sg:classifiers":[
        {
            "category":"Autos & Motor Vehicles",
            "subcategory":"Auto Supplies",
            "type":"Retail Goods"
        }
    ],
    "sg:phone":"+1 936 756 5015",
    "sg:postcode":"77301",
    "sg:province":"TX",
    "sg:tags":[
        "automobile",
        "parts"
    ],
    "wof:name":"O'Reilly Auto Parts",
    "wof:placetype":"venue"
},
  "geometry": {"coordinates":[-95.45746,30.298886],"type":"Point"}
}