{
  "type": "Feature",
  "properties": {
    "iso:country":"US",
    "sg:address":"8171 Military Pkwy",
    "sg:city":"Dallas",
    "sg:classifiers":[
        {
            "category":"Social Services",
            "subcategory":"Child Care",
            "type":"Services"
        }
    ],
    "sg:phone":"+1 214 388 8464",
    "sg:postcode":"75227",
    "sg:province":"TX",
    "sg:tags":[
        "day"
    ],
    "wof:name":"Christian St Philip Lrng Ctr",
    "wof:placetype":"venue"
},
  "geometry": {"coordinates":[-96.677183,32.768623],"type":"Point"}
}