{
  "type": "Feature",
  "properties": {
    "iso:country":"US",
    "sg:address":"9839 Dyer St",
    "sg:city":"El Paso",
    "sg:classifiers":[
        {
            "category":"Banks & Credit Unions",
            "subcategory":"Bank",
            "type":"Services"
        }
    ],
    "sg:phone":"+1 915 751 3355",
    "sg:postcode":"79924",
    "sg:province":"TX",
    "sg:tags":[
        "loan"
    ],
    "wof:name":"Continental Credit Corp",
    "wof:placetype":"venue"
},
  "geometry": {"coordinates":[-106.41105899999999,31.89601],"type":"Point"}
}