{
  "type": "Feature",
  "properties": {
    "iso:country":"US",
    "sg:address":"512 W Woodard St",
    "sg:city":"Denison",
    "sg:classifiers":[
        {
            "category":"Retail",
            "subcategory":"Portrait Studio",
            "type":"Services"
        }
    ],
    "sg:phone":"+1 903 464 0976",
    "sg:postcode":"75020",
    "sg:province":"TX",
    "sg:tags":[
        "photo"
    ],
    "wof:name":"Special Moments Photography",
    "wof:placetype":"venue"
},
  "geometry": {"coordinates":[-96.542856,33.756449],"type":"Point"}
}