{
  "type": "Feature",
  "properties": {
    "iso:country":"US",
    "sg:address":"712 Elm St",
    "sg:city":"Teague",
    "sg:classifiers":[
        {
            "category":"Personal",
            "subcategory":"Beauty Salon",
            "type":"Services"
        }
    ],
    "sg:phone":"+1 254 739 2081",
    "sg:postcode":"75860",
    "sg:province":"TX",
    "wof:name":"Zeldas Beauty Shop",
    "wof:placetype":"venue"
},
  "geometry": {"coordinates":[-96.280474,31.625809],"type":"Point"}
}