{
  "type": "Feature",
  "properties": {
    "iso:country":"US",
    "sg:address":"1505 Shorecrest Dr",
    "sg:city":"Garland",
    "sg:classifiers":[
        {
            "category":"Wholesale",
            "subcategory":"Home Furnishings",
            "type":"Manufacturing & Wholesale Goods"
        }
    ],
    "sg:phone":"+1 972 485 0485",
    "sg:postcode":"75040",
    "sg:province":"TX",
    "sg:tags":[
        "venetian",
        "blind"
    ],
    "wof:name":"Wholesale Blinds",
    "wof:placetype":"venue"
},
  "geometry": {"coordinates":[-96.61157300000001,32.91585],"type":"Point"}
}