{
  "type": "Feature",
  "properties": {
    "iso:country":"US",
    "sg:address":"12360 Grant Rd",
    "sg:city":"Cypress",
    "sg:classifiers":[
        {
            "category":"Autos & Motor Vehicles",
            "subcategory":"Fuel & Gas Station",
            "type":"Retail Goods"
        }
    ],
    "sg:phone":"+1 281 374 9847",
    "sg:postcode":"77429",
    "sg:province":"TX",
    "sg:tags":[
        "oil"
    ],
    "wof:name":"Exxon Mobil Corp",
    "wof:placetype":"venue"
},
  "geometry": {"coordinates":[-95.611056,29.984178],"type":"Point"}
}