{
  "type": "Feature",
  "properties": {
    "iso:country":"US",
    "sg:address":"1100 Bonham Aly",
    "sg:city":"Commerce",
    "sg:classifiers":[
        {
            "category":"Wholesale",
            "subcategory":"Farm Supplies",
            "type":"Manufacturing & Wholesale Goods"
        }
    ],
    "sg:phone":"+1 903 886 3368",
    "sg:postcode":"75428",
    "sg:province":"TX",
    "wof:name":"U-Haul",
    "wof:placetype":"venue"
},
  "geometry": {"coordinates":[-95.898197,33.251148],"type":"Point"}
}