{
  "type": "Feature",
  "properties": {
    "iso:country":"US",
    "sg:address":"918 Spring Brook Dr",
    "sg:city":"Allen",
    "sg:classifiers":[
        {
            "category":"Health Services",
            "subcategory":"Health Practitioner",
            "type":"Services"
        }
    ],
    "sg:phone":"+1 214 547 8230",
    "sg:postcode":"75002",
    "sg:province":"TX",
    "wof:name":"James T Rockwood Th M PH D P C",
    "wof:placetype":"venue"
},
  "geometry": {"coordinates":[-96.64872099999999,33.103609],"type":"Point"}
}