{
  "type": "Feature",
  "properties": {
    "iso:country":"US",
    "sg:address":"625 Taft Blvd",
    "sg:city":"San Antonio",
    "sg:classifiers":[
        {
            "category":"Real Estate",
            "subcategory":"Real Estate Agent",
            "type":"Services"
        }
    ],
    "sg:phone":"+1 210 277 1288",
    "sg:postcode":"78225",
    "sg:province":"TX",
    "wof:name":"H 2 Property Investments",
    "wof:placetype":"venue"
},
  "geometry": {"coordinates":[-98.53054899999999,29.396256],"type":"Point"}
}