{
  "type": "Feature",
  "properties": {
    "iso:country":"US",
    "sg:address":"230 Pine Bluff St",
    "sg:city":"Paris",
    "sg:classifiers":[
        {
            "category":"Restaurant",
            "type":"Food & Drink"
        }
    ],
    "sg:phone":"+1 903 784 3088",
    "sg:postcode":"75460",
    "sg:province":"TX",
    "wof:name":"Texas Allstar Burgers",
    "wof:placetype":"venue"
},
  "geometry": {"coordinates":[-95.55431799999999,33.663967],"type":"Point"}
}