{
  "type": "Feature",
  "properties": {
    "iso:country":"US",
    "sg:address":"100 N Central Expy Ste 1201",
    "sg:city":"Richardson",
    "sg:classifiers":[
        {
            "category":"Banks & Credit Unions",
            "subcategory":"Financial Services",
            "type":"Services"
        }
    ],
    "sg:phone":"+1 972 997 8293",
    "sg:postcode":"75080",
    "sg:province":"TX",
    "sg:tags":[
        "broker",
        "mortgage"
    ],
    "wof:name":"Praxis Mortgage & Financial",
    "wof:placetype":"venue"
},
  "geometry": {"coordinates":[-96.73384,32.950838],"type":"Point"}
}