{
  "type": "Feature",
  "properties": {
    "iso:country":"US",
    "sg:address":"20131 Highway 59 N Ste 4000",
    "sg:city":"Humble",
    "sg:classifiers":[
        {
            "category":"Shopping",
            "subcategory":"Department Store",
            "type":"Retail Goods"
        }
    ],
    "sg:phone":"+1 281 540 9113",
    "sg:postcode":"77338",
    "sg:province":"TX",
    "wof:name":"Foley's",
    "wof:placetype":"venue"
},
  "geometry": {"coordinates":[-95.267382,30.007505],"type":"Point"}
}