{
  "type": "Feature",
  "properties": {
    "iso:country":"US",
    "sg:address":"3312 Forest Ln",
    "sg:city":"Dallas",
    "sg:classifiers":[
        {
            "category":"Restaurant",
            "type":"Food & Drink"
        }
    ],
    "sg:phone":"+1 972 241 9848",
    "sg:postcode":"75234",
    "sg:province":"TX",
    "sg:tags":[
        "eating"
    ],
    "wof:name":"Golden Corral",
    "wof:placetype":"venue"
},
  "geometry": {"coordinates":[-96.86599699999999,32.9095],"type":"Point"}
}