{
  "type": "Feature",
  "properties": {
    "iso:country":"US",
    "sg:address":"4931 State Hwy 114",
    "sg:city":"Levelland",
    "sg:classifiers":[
        {
            "category":"Retail",
            "subcategory":"Veterinary Services",
            "type":"Services"
        }
    ],
    "sg:phone":"+1 806 894 6533",
    "sg:postcode":"79336",
    "sg:province":"TX",
    "wof:name":"West Plains Veterinary",
    "wof:placetype":"venue"
},
  "geometry": {"coordinates":[-102.275325,33.593256],"type":"Point"}
}