{
  "type": "Feature",
  "properties": {
    "iso:country":"US",
    "sg:address":"7293 Co Rd 482",
    "sg:city":"Anson",
    "sg:classifiers":[
        {
            "category":"Farming",
            "subcategory":"Livestock Farm",
            "type":"Manufacturing & Wholesale Goods"
        }
    ],
    "sg:phone":"+1 325 823 2481",
    "sg:postcode":"79501",
    "sg:province":"TX",
    "sg:tags":[
        "animal",
        "general"
    ],
    "wof:name":"4b Ranch Inc",
    "wof:placetype":"venue"
},
  "geometry": {"coordinates":[-99.980324,32.672039],"type":"Point"}
}