{
  "type": "Feature",
  "properties": {
    "iso:country":"US",
    "sg:address":"2300 Sahara Dr",
    "sg:city":"Arlington",
    "sg:classifiers":[
        {
            "category":"Building & Trades",
            "subcategory":"Cleaning & Sanitation",
            "type":"Services"
        }
    ],
    "sg:phone":"+1 817 265 4989",
    "sg:postcode":"76012",
    "sg:province":"TX",
    "sg:tags":[
        "maintenance"
    ],
    "wof:name":"Bills Cleaning Service",
    "wof:placetype":"venue"
},
  "geometry": {"coordinates":[-97.12927999999999,32.772396],"type":"Point"}
}