{
  "type": "Feature",
  "properties": {
    "iso:country":"US",
    "sg:address":"965 N Cooper St",
    "sg:city":"Arlington",
    "sg:classifiers":[
        {
            "category":"Insurance",
            "subcategory":"Insurance Agent",
            "type":"Services"
        }
    ],
    "sg:phone":"+1 817 275 8836",
    "sg:postcode":"76011",
    "sg:province":"TX",
    "wof:name":"Avalon Insurance Agency",
    "wof:placetype":"venue"
},
  "geometry": {"coordinates":[-97.113805,32.749487],"type":"Point"}
}