{
  "type": "Feature",
  "properties": {
    "iso:country":"US",
    "sg:address":"1601 S Main St",
    "sg:city":"Lindale",
    "sg:classifiers":[
        {
            "category":"Shopping",
            "subcategory":"Department Store",
            "type":"Retail Goods"
        },
        {
            "category":"Shopping",
            "subcategory":"Discount & Variety Stores",
            "type":"Retail Goods"
        }
    ],
    "sg:phone":"+1 903 882 7686",
    "sg:postcode":"75771",
    "sg:province":"TX",
    "sg:website":"http://www.fredsdiscount.com",
    "wof:name":"Fred's Store 2218",
    "wof:placetype":"venue"
},
  "geometry": {"coordinates":[-95.404152,32.49789],"type":"Point"}
}