{
  "type": "Feature",
  "properties": {
    "iso:country":"US",
    "sg:address":"113 W Park Ave",
    "sg:city":"Iowa Park",
    "sg:classifiers":[
        {
            "category":"Shopping",
            "subcategory":"Clothing, Apparel, & Fashions",
            "type":"Retail Goods"
        }
    ],
    "sg:phone":"+1 940 592 8637",
    "sg:postcode":"76367",
    "sg:province":"TX",
    "sg:tags":[
        "infant",
        "wear"
    ],
    "wof:name":"Baby Toes Childrens Clothing U",
    "wof:placetype":"venue"
},
  "geometry": {"coordinates":[-98.66898500000001,33.952216],"type":"Point"}
}