{
  "type": "Feature",
  "properties": {
    "iso:country":"US",
    "sg:address":"2606 Quaker Dr",
    "sg:city":"Texas City",
    "sg:classifiers":[
        {
            "category":"Building & Trades",
            "subcategory":"Construction",
            "type":"Services"
        }
    ],
    "sg:phone":"+1 409 948 1307",
    "sg:postcode":"77590",
    "sg:province":"TX",
    "sg:tags":[
        "house"
    ],
    "wof:name":"Precision Constructors",
    "wof:placetype":"venue"
},
  "geometry": {"coordinates":[-94.92816000000001,29.421126],"type":"Point"}
}