{
  "type": "Feature",
  "properties": {
    "iso:country":"US",
    "sg:address":"14752 Ranch Rd",
    "sg:city":"Forney",
    "sg:classifiers":[
        {
            "category":"Building & Trades",
            "subcategory":"Landscaping Services",
            "type":"Services"
        }
    ],
    "sg:phone":"+1 972 552 3626",
    "sg:postcode":"75126",
    "sg:province":"TX",
    "sg:tags":[
        "landscape"
    ],
    "wof:name":"Norris Landscape",
    "wof:placetype":"venue"
},
  "geometry": {"coordinates":[-96.447926,32.772082],"type":"Point"}
}