{
  "type": "Feature",
  "properties": {
    "iso:country":"US",
    "sg:address":"2596 Mesquite Pass",
    "sg:city":"Seguin",
    "sg:classifiers":[
        {
            "category":"Professional",
            "subcategory":"Management & Consulting",
            "type":"Services"
        }
    ],
    "sg:phone":"+1 830 372 5039",
    "sg:postcode":"78155",
    "sg:province":"TX",
    "wof:name":"Bones Management LLC",
    "wof:placetype":"venue"
},
  "geometry": {"coordinates":[-97.993351,29.481178],"type":"Point"}
}