{
  "type": "Feature",
  "properties": {
    "iso:country":"US",
    "sg:address":"7905 Oak Forest St",
    "sg:city":"San Antonio",
    "sg:classifiers":[
        {
            "category":"Professional",
            "subcategory":"Lawyer & Legal Services",
            "type":"Services"
        }
    ],
    "sg:phone":"+1 210 656 4708",
    "sg:postcode":"78233",
    "sg:province":"TX",
    "wof:name":"Bizzy Bee Crafts",
    "wof:placetype":"venue"
},
  "geometry": {"coordinates":[-98.334137,29.546388],"type":"Point"}
}