{
  "type": "Feature",
  "properties": {
    "iso:country":"US",
    "sg:address":"1208 Harmony Hill Dr",
    "sg:city":"Lufkin",
    "sg:classifiers":[
        {
            "category":"Professional",
            "type":"Services"
        }
    ],
    "sg:phone":"+1 936 639 3898",
    "sg:postcode":"75901",
    "sg:province":"TX",
    "wof:name":"Adornments Plus",
    "wof:placetype":"venue"
},
  "geometry": {"coordinates":[-94.710824,31.310421],"type":"Point"}
}