{
  "type": "Feature",
  "properties": {
    "iso:country":"US",
    "sg:address":"5710 Hondo Pass Ave",
    "sg:city":"El Paso",
    "sg:classifiers":[
        {
            "category":"Food & Beverages",
            "subcategory":"Groceries & Convenience Stores",
            "type":"Retail Goods"
        }
    ],
    "sg:phone":"+1 915 755 2013",
    "sg:postcode":"79924",
    "sg:province":"TX",
    "wof:name":"7-Eleven",
    "wof:placetype":"venue"
},
  "geometry": {"coordinates":[-106.407611,31.870213],"type":"Point"}
}