{
  "type": "Feature",
  "properties": {
    "iso:country":"US",
    "sg:address":"15303 S Flamingo Dr",
    "sg:city":"Austin",
    "sg:classifiers":[
        {
            "category":"Real Estate",
            "subcategory":"Real Estate Agent",
            "type":"Services"
        }
    ],
    "sg:phone":"+1 512 263 1300",
    "sg:postcode":"78734",
    "sg:province":"TX",
    "wof:name":"Lake Travis Locating",
    "wof:placetype":"venue"
},
  "geometry": {"coordinates":[-97.95308,30.361439],"type":"Point"}
}