{
  "type": "Feature",
  "properties": {
    "iso:country":"US",
    "sg:address":"2205 Strawberry Rd",
    "sg:city":"Pasadena",
    "sg:classifiers":[
        {
            "category":"Professional",
            "subcategory":"Accounting & Tax Preparation",
            "type":"Services"
        }
    ],
    "sg:phone":"+1 713 473 5677",
    "sg:postcode":"77502",
    "sg:province":"TX",
    "sg:tags":[
        "accountant"
    ],
    "wof:name":"Wingo Judy S CPA",
    "wof:placetype":"venue"
},
  "geometry": {"coordinates":[-95.192902,29.6791],"type":"Point"}
}