{
  "type": "Feature",
  "properties": {
    "iso:country":"US",
    "sg:address":"704 US Hwy 281",
    "sg:city":"Brownsville",
    "sg:classifiers":[
        {
            "category":"Autos & Motor Vehicles",
            "subcategory":"Auto Supplies",
            "type":"Retail Goods"
        }
    ],
    "sg:phone":"+1 956 574 0206",
    "sg:postcode":"78520",
    "sg:province":"TX",
    "sg:tags":[
        "tire"
    ],
    "wof:name":"Ortega's Tire Shop",
    "wof:placetype":"venue"
},
  "geometry": {"coordinates":[-97.511371,25.925779],"type":"Point"}
}