{
  "type": "Feature",
  "properties": {
    "iso:country":"US",
    "sg:address":"806 Water St",
    "sg:city":"Bastrop",
    "sg:classifiers":[
        {
            "category":"Government",
            "subcategory":"Office",
            "type":"Public Place"
        }
    ],
    "sg:phone":"+1 512 332 7276",
    "sg:postcode":"78602",
    "sg:province":"TX",
    "sg:tags":[
        "county",
        "program"
    ],
    "wof:name":"Bastrop Cnty Health-Sanitation",
    "wof:placetype":"venue"
},
  "geometry": {"coordinates":[-97.3188,30.109394],"type":"Point"}
}