{
  "type": "Feature",
  "properties": {
    "iso:country":"US",
    "sg:address":"205 Short St",
    "sg:city":"Canton",
    "sg:classifiers":[
        {
            "category":"Health Services",
            "subcategory":"Nursing And Care Facility",
            "type":"Services"
        }
    ],
    "sg:phone":"+1 214 567 4541",
    "sg:postcode":"75103",
    "sg:province":"TX",
    "sg:tags":[
        "home",
        "group"
    ],
    "wof:name":"Andrews Ctr Shrt St Group HM",
    "wof:placetype":"venue"
},
  "geometry": {"coordinates":[-95.875984,32.540783],"type":"Point"}
}