{
  "type": "Feature",
  "properties": {
    "iso:country":"US",
    "sg:address":"2840 Laramie St",
    "sg:city":"Irving",
    "sg:classifiers":[
        {
            "category":"Health Services",
            "subcategory":"Clinic",
            "type":"Services"
        }
    ],
    "sg:phone":"+1 214 726 9506",
    "sg:postcode":"75062",
    "sg:province":"TX",
    "wof:name":"Wellness Workshop",
    "wof:placetype":"venue"
},
  "geometry": {"coordinates":[-97.008011,32.846448],"type":"Point"}
}