{
  "type": "Feature",
  "properties": {
    "iso:country":"US",
    "sg:address":"15402 Midway Rd",
    "sg:city":"Addison",
    "sg:classifiers":[
        {
            "category":"Wholesale",
            "subcategory":"Furniture",
            "type":"Manufacturing & Wholesale Goods"
        }
    ],
    "sg:phone":"+1 214 866 0085",
    "sg:postcode":"75001",
    "sg:province":"TX",
    "wof:name":"Aztec Shiva USA",
    "wof:placetype":"venue"
},
  "geometry": {"coordinates":[-96.83836100000001,32.95936],"type":"Point"}
}