{
  "type": "Feature",
  "properties": {
    "iso:country":"US",
    "sg:address":"1008 W 4th St",
    "sg:city":"Tyler",
    "sg:classifiers":[
        {
            "category":"Autos & Motor Vehicles",
            "subcategory":"Automobile Sales",
            "type":"Retail Goods"
        },
        {
            "category":"Retail",
            "subcategory":"Auto Repair",
            "type":"Services"
        }
    ],
    "sg:phone":"+1 903 593 2552",
    "sg:postcode":"75701",
    "sg:province":"TX",
    "sg:tags":[
        "dealers-used",
        "car",
        "used",
        "cars-wholesale"
    ],
    "wof:name":"Firestation Auto Center",
    "wof:placetype":"venue"
},
  "geometry": {"coordinates":[-95.31175500000001,32.332235],"type":"Point"}
}