{
  "type": "Feature",
  "properties": {
    "iso:country":"US",
    "sg:address":"1811 US Hwy 259",
    "sg:city":"Kilgore",
    "sg:classifiers":[
        {
            "category":"Utilities",
            "subcategory":"Telephone",
            "type":"Services"
        }
    ],
    "sg:phone":"+1 903 986 3799",
    "sg:postcode":"75662",
    "sg:province":"TX",
    "sg:tags":[
        "communications",
        "merchandise"
    ],
    "wof:name":"Alltel",
    "wof:placetype":"venue"
},
  "geometry": {"coordinates":[-94.854519,32.396687],"type":"Point"}
}