{
  "type": "Feature",
  "properties": {
    "iso:country":"US",
    "sg:address":"3202 E Main St",
    "sg:city":"Grand Prairie",
    "sg:classifiers":[
        {
            "category":"Autos & Motor Vehicles",
            "subcategory":"Automobile Sales",
            "type":"Retail Goods"
        }
    ],
    "sg:phone":"+1 972 263 3773",
    "sg:postcode":"75050",
    "sg:province":"TX",
    "sg:tags":[
        "car",
        "used",
        "dealer"
    ],
    "wof:name":"Rio's Auto Sales",
    "wof:placetype":"venue"
},
  "geometry": {"coordinates":[-96.95757500000001,32.749459],"type":"Point"}
}