{
  "type": "Feature",
  "properties": {
    "iso:country":"US",
    "sg:address":"8814 Alcott Dr",
    "sg:city":"Houston",
    "sg:classifiers":[
        {
            "category":"Home & Garden",
            "subcategory":"Carpets & Floor Coverings",
            "type":"Retail Goods"
        }
    ],
    "sg:phone":"+1 713 467 4187",
    "sg:postcode":"77080",
    "sg:province":"TX",
    "sg:tags":[
        "carpeting"
    ],
    "wof:name":"Dees Rug Service",
    "wof:placetype":"venue"
},
  "geometry": {"coordinates":[-95.511002,29.8172],"type":"Point"}
}