{
  "type": "Feature",
  "properties": {
    "iso:country":"US",
    "sg:address":"215 Cotton Dr",
    "sg:city":"Waco",
    "sg:classifiers":[
        {
            "category":"Wholesale",
            "subcategory":"Hardware",
            "type":"Manufacturing & Wholesale Goods"
        }
    ],
    "sg:phone":"+1 254 741 1948",
    "sg:postcode":"76712",
    "sg:province":"TX",
    "sg:tags":[
        "air",
        "parts",
        "conditioning",
        "supply"
    ],
    "wof:name":"American Distributors",
    "wof:placetype":"venue"
},
  "geometry": {"coordinates":[-97.18856599999999,31.507907],"type":"Point"}
}