{
  "type": "Feature",
  "properties": {
    "iso:country":"US",
    "sg:address":"2240 Royal Ln",
    "sg:city":"Dallas",
    "sg:classifiers":[
        {
            "category":"Professional",
            "subcategory":"Business Services",
            "type":"Services"
        }
    ],
    "sg:phone":"+1 972 247 5550",
    "sg:postcode":"75229",
    "sg:province":"TX",
    "sg:tags":[
        "recording",
        "studio"
    ],
    "wof:name":"Studio 3 Kang",
    "wof:placetype":"venue"
},
  "geometry": {"coordinates":[-96.901337,32.895635],"type":"Point"}
}