{
  "type": "Feature",
  "properties": {
    "iso:country":"US",
    "sg:address":"2525 Honeysuckle Ave",
    "sg:city":"Fort Worth",
    "sg:classifiers":[
        {
            "category":"Organizations",
            "subcategory":"Religious Organization",
            "type":"Services"
        }
    ],
    "sg:phone":"+1 817 222 9168",
    "sg:postcode":"76111",
    "sg:province":"TX",
    "wof:name":"Jesus Olivarez Etux Auror",
    "wof:placetype":"venue"
},
  "geometry": {"coordinates":[-97.309062,32.784232],"type":"Point"}
}