{
  "type": "Feature",
  "properties": {
    "iso:country":"US",
    "sg:address":"2001 Bay Ave",
    "sg:city":"Rockport",
    "sg:classifiers":[
        {
            "category":"Real Estate",
            "subcategory":"Real Estate Services",
            "type":"Services"
        },
        {
            "category":"Real Estate",
            "subcategory":"Real Estate Agent",
            "type":"Services"
        }
    ],
    "sg:phone":"+1 361 729 7307",
    "sg:postcode":"78382",
    "sg:province":"TX",
    "sg:tags":[
        "buyer",
        "management",
        "rental",
        "broker"
    ],
    "wof:name":"Rockport Fulton Real Estate",
    "wof:placetype":"venue"
},
  "geometry": {"coordinates":[-97.040558,28.04336],"type":"Point"}
}