{
  "type": "Feature",
  "properties": {
    "iso:country":"US",
    "sg:address":"2600 Longhorn Blvd",
    "sg:city":"Austin",
    "sg:classifiers":[
        {
            "category":"Professional",
            "type":"Services"
        }
    ],
    "sg:phone":"+1 512 258 7019",
    "sg:postcode":"78758",
    "sg:province":"TX",
    "sg:tags":[
        "establishment"
    ],
    "wof:name":"Allen Technologies",
    "wof:placetype":"venue"
},
  "geometry": {"coordinates":[-97.726472,30.380788],"type":"Point"}
}