{
  "type": "Feature",
  "properties": {
    "iso:country":"US",
    "sg:address":"2707 Bayshore Dr",
    "sg:city":"Bacliff",
    "sg:classifiers":[
        {
            "category":"Professional",
            "subcategory":"Computer Services",
            "type":"Services"
        }
    ],
    "sg:phone":"+1 281 559 3760",
    "sg:postcode":"77518",
    "sg:province":"TX",
    "sg:tags":[
        "related"
    ],
    "wof:name":"Segue Systems LLC",
    "wof:placetype":"venue"
},
  "geometry": {"coordinates":[-95.000283,29.523484],"type":"Point"}
}