{
  "type": "Feature",
  "properties": {
    "iso:country":"US",
    "sg:address":"3541 Up River Rd",
    "sg:city":"Corpus Christi",
    "sg:classifiers":[
        {
            "category":"Local Transit",
            "type":"Transportation"
        }
    ],
    "sg:phone":"+1 361 884 3211",
    "sg:postcode":"78408",
    "sg:province":"TX",
    "sg:tags":[
        "airport"
    ],
    "wof:name":"United Yellow Checker Cab",
    "wof:placetype":"venue"
},
  "geometry": {"coordinates":[-97.42993800000001,27.795534],"type":"Point"}
}