{
  "type": "Feature",
  "properties": {
    "iso:country":"US",
    "sg:address":"1280 Cheers St",
    "sg:city":"Brownsville",
    "sg:classifiers":[
        {
            "category":"Freight",
            "type":"Transportation"
        }
    ],
    "sg:phone":"+1 956 831 3063",
    "sg:postcode":"78521",
    "sg:province":"TX",
    "sg:tags":[
        "consultant"
    ],
    "wof:name":"Jorge Ancer Transportes",
    "wof:placetype":"venue"
},
  "geometry": {"coordinates":[-97.452551,25.929037],"type":"Point"}
}