{
  "type": "Feature",
  "properties": {
    "iso:country":"US",
    "sg:address":"121 N Chilton Ave",
    "sg:city":"Goliad",
    "sg:classifiers":[
        {
            "category":"Retail",
            "subcategory":"Car Wash",
            "type":"Services"
        }
    ],
    "sg:phone":"+1 361 645 8288",
    "sg:postcode":"77963",
    "sg:province":"TX",
    "sg:tags":[
        "carwash"
    ],
    "wof:name":"Kwik Kar Wash",
    "wof:placetype":"venue"
},
  "geometry": {"coordinates":[-97.393807,28.669164],"type":"Point"}
}