{
  "type": "Feature",
  "properties": {
    "iso:country":"US",
    "sg:address":"1900 Coulter St",
    "sg:city":"Amarillo",
    "sg:classifiers":[
        {
            "category":"Shopping",
            "type":"Retail Goods"
        }
    ],
    "sg:phone":"+1 806 351 1775",
    "sg:postcode":"79106",
    "sg:province":"TX",
    "sg:tags":[
        "limb",
        "artificial"
    ],
    "wof:name":"Advanced Limb & Brace",
    "wof:placetype":"venue"
},
  "geometry": {"coordinates":[-101.920355,35.188663],"type":"Point"}
}