{
  "type": "Feature",
  "properties": {
    "iso:country":"US",
    "sg:address":"916 Cypress Cove Rd",
    "sg:city":"Spring Branch",
    "sg:classifiers":[
        {
            "category":"Retail",
            "subcategory":"Repair Shop",
            "type":"Services"
        }
    ],
    "sg:phone":"+1 830 885 4713",
    "sg:postcode":"78070",
    "sg:province":"TX",
    "wof:name":"Rusty Hinge Repairs",
    "wof:placetype":"venue"
},
  "geometry": {"coordinates":[-98.35971499999999,29.920905],"type":"Point"}
}