{
  "type": "Feature",
  "properties": {
    "iso:country":"US",
    "sg:address":"11367 Harry Hines Blvd",
    "sg:city":"Dallas",
    "sg:classifiers":[
        {
            "category":"Shopping",
            "subcategory":"Mobile Phones",
            "type":"Retail Goods"
        }
    ],
    "sg:phone":"+1 972 488 6968",
    "sg:postcode":"75229",
    "sg:province":"TX",
    "wof:name":"National Wireless",
    "wof:placetype":"venue"
},
  "geometry": {"coordinates":[-96.89107,32.894434],"type":"Point"}
}