{
  "type": "Feature",
  "properties": {
    "iso:country":"US",
    "sg:address":"140 Fallbrook Dr",
    "sg:city":"Houston",
    "sg:classifiers":[
        {
            "category":"Wholesale",
            "subcategory":"Hardware",
            "type":"Manufacturing & Wholesale Goods"
        }
    ],
    "sg:phone":"+1 281 820 9467",
    "sg:postcode":"77038",
    "sg:province":"TX",
    "wof:name":"DE-Ro Products",
    "wof:placetype":"venue"
},
  "geometry": {"coordinates":[-95.41434099999999,29.931701],"type":"Point"}
}