{
  "type": "Feature",
  "properties": {
    "iso:country":"US",
    "sg:address":"3426 Valerie Ln",
    "sg:city":"Spring",
    "sg:classifiers":[
        {
            "category":"Manufacturing",
            "subcategory":"Chemicals & Compounds",
            "type":"Manufacturing & Wholesale Goods"
        }
    ],
    "sg:phone":"+1 281 363 2962",
    "sg:postcode":"77380",
    "sg:province":"TX",
    "sg:tags":[
        "product",
        "mfg"
    ],
    "wof:name":"Colors Paint",
    "wof:placetype":"venue"
},
  "geometry": {"coordinates":[-95.494362,30.146864],"type":"Point"}
}