{
  "type": "Feature",
  "properties": {
    "iso:country":"US",
    "sg:address":"11218 Henge Dr",
    "sg:city":"Austin",
    "sg:classifiers":[
        {
            "category":"Professional",
            "type":"Services"
        }
    ],
    "sg:phone":"+1 512 331 7970",
    "sg:postcode":"78759",
    "sg:province":"TX",
    "wof:name":"Intellectual Research & Develo",
    "wof:placetype":"venue"
},
  "geometry": {"coordinates":[-97.776409,30.425303],"type":"Point"}
}