{
  "type": "Feature",
  "properties": {
    "iso:country":"US",
    "sg:address":"1829 Gravley Dr",
    "sg:city":"Carrollton",
    "sg:classifiers":[
        {
            "category":"Manufacturing",
            "subcategory":"Printing",
            "type":"Manufacturing & Wholesale Goods"
        }
    ],
    "sg:phone":"+1 972 242 9202",
    "sg:postcode":"75006",
    "sg:province":"TX",
    "sg:tags":[
        "engraver",
        "wood"
    ],
    "wof:name":"WATCO Engravers",
    "wof:placetype":"venue"
},
  "geometry": {"coordinates":[-96.890382,32.960805],"type":"Point"}
}