{
  "type": "Feature",
  "properties": {
    "iso:country":"US",
    "sg:address":"4600 Market St",
    "sg:city":"Mineral Wells",
    "sg:classifiers":[
        {
            "category":"Recreation",
            "type":"Entertainment"
        }
    ],
    "sg:phone":"+1 940 327 0979",
    "sg:postcode":"76067",
    "sg:province":"TX",
    "wof:name":"Treasure Island Game Room",
    "wof:placetype":"venue"
},
  "geometry": {"coordinates":[-98.06240699999999,32.80809],"type":"Point"}
}