{
  "type": "Feature",
  "properties": {
    "iso:country":"US",
    "sg:address":"100 W 1st St",
    "sg:city":"Mt Pleasant",
    "sg:classifiers":[
        {
            "category":"Government",
            "subcategory":"Office",
            "type":"Public Place"
        }
    ],
    "sg:phone":"+1 903 577 6762",
    "sg:postcode":"75455",
    "sg:province":"TX",
    "wof:name":"Titus County Constables",
    "wof:placetype":"venue"
},
  "geometry": {"coordinates":[-94.96949600000001,33.156703],"type":"Point"}
}