{
  "type": "Feature",
  "properties": {
    "iso:country":"US",
    "sg:address":"6402 Grand Canyon Dr",
    "sg:city":"Katy",
    "sg:classifiers":[
        {
            "category":"Wholesale",
            "subcategory":"Drugs",
            "type":"Manufacturing & Wholesale Goods"
        }
    ],
    "sg:phone":"+1 281 646 7746",
    "sg:postcode":"77450",
    "sg:province":"TX",
    "sg:tags":[
        "skin",
        "care"
    ],
    "wof:name":"Body Beautiful Products",
    "wof:placetype":"venue"
},
  "geometry": {"coordinates":[-95.738041,29.70987],"type":"Point"}
}