{
  "type": "Feature",
  "properties": {
    "iso:country":"US",
    "sg:address":"5207 Huisache St",
    "sg:city":"Bellaire",
    "sg:classifiers":[
        {
            "category":"Banks & Credit Unions",
            "subcategory":"Financial Services",
            "type":"Services"
        }
    ],
    "sg:phone":"+1 713 669 0038",
    "sg:postcode":"77401",
    "sg:province":"TX",
    "sg:tags":[
        "investment",
        "closed"
    ],
    "wof:name":"Mj Investment Properties LLC",
    "wof:placetype":"venue"
},
  "geometry": {"coordinates":[-95.471924,29.700147],"type":"Point"}
}