{
  "type": "Feature",
  "properties": {
    "iso:country":"US",
    "sg:address":"5417 Taos Dr",
    "sg:city":"Abilene",
    "sg:classifiers":[
        {
            "category":"Building & Trades",
            "subcategory":"Cleaning & Sanitation",
            "type":"Services"
        }
    ],
    "sg:phone":"+1 325 692 6688",
    "sg:postcode":"79605",
    "sg:province":"TX",
    "sg:tags":[
        "janitor"
    ],
    "wof:name":"Sherry Janitorial Svc",
    "wof:placetype":"venue"
},
  "geometry": {"coordinates":[-99.796581,32.445832],"type":"Point"}
}