{
  "type": "Feature",
  "properties": {
    "iso:country":"US",
    "sg:address":"6120 Lake Worth Blvd",
    "sg:city":"Fort Worth",
    "sg:classifiers":[
        {
            "category":"Restaurant",
            "type":"Food & Drink"
        }
    ],
    "sg:menulink":"http://www.allmenus.com/tx/fort-worth/157284-whataburger/menu/",
    "sg:phone":"+1 817 237 8271",
    "sg:postcode":"76135",
    "sg:province":"TX",
    "sg:tags":[
        "burger",
        "american"
    ],
    "wof:name":"Whataburger",
    "wof:placetype":"venue"
},
  "geometry": {"coordinates":[-97.41636099999999,32.808006],"type":"Point"}
}