{
  "type": "Feature",
  "properties": {
    "iso:country":"US",
    "sg:address":"7804 Myrtle Springs Dr",
    "sg:city":"Plano",
    "sg:classifiers":[
        {
            "category":"Retail",
            "subcategory":"Auto Repair",
            "type":"Services"
        }
    ],
    "sg:phone":"+1 972 596 4386",
    "sg:postcode":"75025",
    "sg:province":"TX",
    "sg:tags":[
        "general"
    ],
    "wof:name":"John Edwards C Jaguar Service",
    "wof:placetype":"venue"
},
  "geometry": {"coordinates":[-96.76380399999999,33.083269],"type":"Point"}
}