{
  "type": "Feature",
  "properties": {
    "iso:country":"US",
    "sg:address":"14911 Village Elm St",
    "sg:city":"Houston",
    "sg:classifiers":[
        {
            "category":"Real Estate",
            "subcategory":"Architect",
            "type":"Services"
        }
    ],
    "sg:phone":"+1 281 480 3574",
    "sg:postcode":"77062",
    "sg:province":"TX",
    "sg:tags":[
        "architectural"
    ],
    "wof:name":"Eng Architect Inc",
    "wof:placetype":"venue"
},
  "geometry": {"coordinates":[-95.12665800000001,29.587055],"type":"Point"}
}