{
  "type": "Feature",
  "properties": {
    "iso:country":"US",
    "sg:address":"5730 Andrews Hwy",
    "sg:city":"Odessa",
    "sg:classifiers":[
        {
            "category":"Home & Garden",
            "subcategory":"Mobile Homes",
            "type":"Retail Goods"
        }
    ],
    "sg:phone":"+1 432 550 0018",
    "sg:postcode":"79762",
    "sg:province":"TX",
    "wof:name":"CMH",
    "wof:placetype":"venue"
},
  "geometry": {"coordinates":[-102.390807,31.900883],"type":"Point"}
}