{
  "type": "Feature",
  "properties": {
    "iso:country":"US",
    "sg:address":"5610 E. Mockingbird Lane",
    "sg:city":"Dallas",
    "sg:classifiers":[
        {
            "category":"Restaurant",
            "type":"Food & Drink"
        }
    ],
    "sg:phone":"+1 214 827 0355",
    "sg:postcode":"75206",
    "sg:province":"TX",
    "sg:tags":[
        "italian"
    ],
    "sg:website":"www.campisis.us/",
    "wof:name":"Campisi's Egyptian Lounge",
    "wof:placetype":"venue"
},
  "geometry": {"coordinates":[-96.77179700000001,32.836399],"type":"Point"}
}