{
  "type": "Feature",
  "properties": {
    "iso:country":"US",
    "sg:address":"421 W I- 30",
    "sg:city":"Garland",
    "sg:classifiers":[
        {
            "category":"Wholesale",
            "subcategory":"Machinery & Supplies",
            "type":"Manufacturing & Wholesale Goods"
        },
        {
            "category":"Wholesale",
            "subcategory":"Hardware",
            "type":"Manufacturing & Wholesale Goods"
        }
    ],
    "sg:phone":"+1 972 303 9555",
    "sg:postcode":"75043",
    "sg:province":"TX",
    "sg:tags":[
        "stapler",
        "industrial",
        "tacker",
        "staple"
    ],
    "wof:name":"Southern Fastening Systems",
    "wof:placetype":"venue"
},
  "geometry": {"coordinates":[-96.591426,32.842282],"type":"Point"}
}