{
  "type": "Feature",
  "properties": {
    "iso:country":"US",
    "sg:address":"5925 Phelan Blvd",
    "sg:city":"Beaumont",
    "sg:classifiers":[
        {
            "category":"Professional",
            "subcategory":"Advertising",
            "type":"Services"
        }
    ],
    "sg:phone":"+1 409 866 5208",
    "sg:postcode":"77706",
    "sg:province":"TX",
    "sg:tags":[
        "medium",
        "interactive"
    ],
    "wof:name":"Dynamic Memories",
    "wof:placetype":"venue"
},
  "geometry": {"coordinates":[-94.16379000000001,30.080005],"type":"Point"}
}