{
  "type": "Feature",
  "properties": {
    "iso:country":"US",
    "sg:address":"313 Chestnut Ave",
    "sg:city":"Edinburg",
    "sg:classifiers":[
        {
            "category":"Arts & Performance",
            "subcategory":"Theater",
            "type":"Entertainment"
        }
    ],
    "sg:phone":"+1 956 358 6911",
    "sg:postcode":"78541",
    "sg:province":"TX",
    "sg:tags":[
        "live",
        "music"
    ],
    "wof:name":"Party Doctors",
    "wof:placetype":"venue"
},
  "geometry": {"coordinates":[-98.188992,26.308606],"type":"Point"}
}