{
  "type": "Feature",
  "properties": {
    "iso:country":"US",
    "sg:address":"2120 Deerfield Dr",
    "sg:city":"Plano",
    "sg:classifiers":[
        {
            "category":"Landmark",
            "subcategory":"Tourist Information",
            "type":"Public Place"
        }
    ],
    "sg:phone":"+1 972 535 6824",
    "sg:postcode":"75023",
    "sg:province":"TX",
    "sg:tags":[
        "tour"
    ],
    "wof:name":"International Vacations Inc",
    "wof:placetype":"venue"
},
  "geometry": {"coordinates":[-96.734713,33.295334],"type":"Point"}
}