{
  "type": "Feature",
  "properties": {
    "iso:country":"US",
    "sg:address":"3808 Harlanwood Dr",
    "sg:city":"Fort Worth",
    "sg:classifiers":[
        {
            "category":"Professional",
            "type":"Services"
        }
    ],
    "sg:phone":"+1 817 926 3444",
    "sg:postcode":"76109",
    "sg:province":"TX",
    "wof:name":"Hlp Corp",
    "wof:placetype":"venue"
},
  "geometry": {"coordinates":[-97.37652,32.70664],"type":"Point"}
}