{
  "type": "Feature",
  "properties": {
    "iso:country":"US",
    "sg:address":"2900 Tee Anchor Blvd",
    "sg:city":"Amarillo",
    "sg:classifiers":[
        {
            "category":"Government",
            "subcategory":"Office",
            "type":"Public Place"
        }
    ],
    "sg:phone":"+1 806 372 4812",
    "sg:postcode":"79104",
    "sg:province":"TX",
    "wof:name":"Alpha Co",
    "wof:placetype":"venue"
},
  "geometry": {"coordinates":[-101.804585,35.197047],"type":"Point"}
}