{
  "type": "Feature",
  "properties": {
    "iso:country":"US",
    "sg:address":"1502 Levee St",
    "sg:city":"Dallas",
    "sg:classifiers":[
        {
            "category":"Building & Trades",
            "subcategory":"Construction",
            "type":"Services"
        }
    ],
    "sg:phone":"+1 972 524 9944",
    "sg:postcode":"75207",
    "sg:province":"TX",
    "sg:tags":[
        "contractor"
    ],
    "sg:website":"claysroofing.com/",
    "wof:name":"Clay's Roofing",
    "wof:placetype":"venue"
},
  "geometry": {"coordinates":[-96.82466700000001,32.789384],"type":"Point"}
}