{
  "type": "Feature",
  "properties": {
    "iso:country":"US",
    "sg:address":"546 Harrold St",
    "sg:city":"Fort Worth",
    "sg:classifiers":[
        {
            "category":"Health Services",
            "subcategory":"Chiropractor",
            "type":"Services"
        }
    ],
    "sg:phone":"+1 817 427 2720",
    "sg:postcode":"76107",
    "sg:province":"TX",
    "wof:name":"John C Runnells",
    "wof:placetype":"venue"
},
  "geometry": {"coordinates":[-97.34901000000001,32.753411],"type":"Point"}
}