{
  "type": "Feature",
  "properties": {
    "iso:country":"US",
    "sg:address":"11130 Old Katy Rd",
    "sg:city":"Houston",
    "sg:classifiers":[
        {
            "category":"Shopping",
            "type":"Retail Goods"
        }
    ],
    "sg:phone":"+1 713 467 3400",
    "sg:postcode":"77043",
    "sg:province":"TX",
    "sg:tags":[
        "clean",
        "supply",
        "provides",
        "mai",
        "pool",
        "swimming"
    ],
    "wof:name":"Watts Pool Service Inc",
    "wof:placetype":"venue"
},
  "geometry": {"coordinates":[-95.577787,29.785205],"type":"Point"}
}