{
  "type": "Feature",
  "properties": {
    "iso:country":"US",
    "sg:address":"5108 Mack Rd",
    "sg:city":"Fort Worth",
    "sg:classifiers":[
        {
            "category":"Manufacturing",
            "subcategory":"Furniture",
            "type":"Manufacturing & Wholesale Goods"
        }
    ],
    "sg:phone":"+1 817 605 9536",
    "sg:postcode":"76117",
    "sg:province":"TX",
    "sg:tags":[
        "mfg"
    ],
    "wof:name":"A+ Woodcrafters",
    "wof:placetype":"venue"
},
  "geometry": {"coordinates":[-97.27265,32.827008],"type":"Point"}
}