{
  "type": "Feature",
  "properties": {
    "iso:country":"US",
    "sg:address":"2383 Green Dewitt Rd",
    "sg:city":"Cuero",
    "sg:classifiers":[
        {
            "category":"Farming",
            "subcategory":"Farm",
            "type":"Manufacturing & Wholesale Goods"
        }
    ],
    "sg:phone":"+1 361 275 8949",
    "sg:postcode":"77954",
    "sg:province":"TX",
    "wof:name":"Christopher Rath",
    "wof:placetype":"venue"
},
  "geometry": {"coordinates":[-97.229668,29.006163],"type":"Point"}
}