{
  "type": "Feature",
  "properties": {
    "iso:country":"US",
    "sg:address":"12224 Almeda Rd",
    "sg:city":"Houston",
    "sg:classifiers":[
        {
            "category":"Personal",
            "subcategory":"Barber",
            "type":"Services"
        }
    ],
    "sg:phone":"+1 713 434 9971",
    "sg:postcode":"77045",
    "sg:province":"TX",
    "wof:name":"Malveaux's Barber Shop",
    "wof:placetype":"venue"
},
  "geometry": {"coordinates":[-95.412201,29.6325],"type":"Point"}
}