{
  "type": "Feature",
  "properties": {
    "iso:country":"US",
    "sg:address":"3210 W 10th Ave",
    "sg:city":"Amarillo",
    "sg:classifiers":[
        {
            "category":"Building & Trades",
            "subcategory":"Pest Control",
            "type":"Services"
        }
    ],
    "sg:phone":"+1 806 351 0250",
    "sg:postcode":"79106",
    "sg:province":"TX",
    "wof:name":"Pond Pest Control",
    "wof:placetype":"venue"
},
  "geometry": {"coordinates":[-101.873279,35.205013],"type":"Point"}
}