{
  "type": "Feature",
  "properties": {
    "iso:country":"US",
    "sg:address":"320 W 1st St",
    "sg:city":"Odessa",
    "sg:classifiers":[
        {
            "category":"Home & Garden",
            "subcategory":"Household Appliances",
            "type":"Retail Goods"
        }
    ],
    "sg:phone":"+1 432 337 0861",
    "sg:postcode":"79761",
    "sg:province":"TX",
    "sg:tags":[
        "pump"
    ],
    "wof:name":"Bolland Pump Co",
    "wof:placetype":"venue"
},
  "geometry": {"coordinates":[-102.370059,31.843341],"type":"Point"}
}