{
  "type": "Feature",
  "properties": {
    "iso:country":"US",
    "sg:address":"514 el Paso St",
    "sg:city":"San Antonio",
    "sg:classifiers":[
        {
            "category":"Professional",
            "type":"Services"
        }
    ],
    "sg:phone":"+1 210 223 1178",
    "sg:postcode":"78207",
    "sg:province":"TX",
    "wof:name":"Zelzer Corp",
    "wof:placetype":"venue"
},
  "geometry": {"coordinates":[-98.506079,29.418557],"type":"Point"}
}