{
  "type": "Feature",
  "properties": {
    "iso:country":"US",
    "sg:address":"6060 Fairmont Pkwy",
    "sg:city":"Pasadena",
    "sg:classifiers":[
        {
            "category":"Real Estate",
            "subcategory":"Real Estate Operator",
            "type":"Services"
        }
    ],
    "sg:phone":"+1 281 991 9511",
    "sg:postcode":"77505",
    "sg:province":"TX",
    "sg:tags":[
        "building",
        "apartment"
    ],
    "wof:name":"Park At Fairmont",
    "wof:placetype":"venue"
},
  "geometry": {"coordinates":[-95.147621,29.649587],"type":"Point"}
}