{
  "type": "Feature",
  "properties": {
    "iso:country":"US",
    "sg:address":"3620 Miramar Dr",
    "sg:city":"La Porte",
    "sg:classifiers":[
        {
            "category":"Organizations",
            "subcategory":"Community Association",
            "type":"Services"
        }
    ],
    "sg:phone":"+1 281 471 1255",
    "sg:postcode":"77571",
    "sg:province":"TX",
    "sg:tags":[
        "club"
    ],
    "sg:website":"www.houstonyachtclub.com",
    "wof:name":"Houston Yacht Club",
    "wof:placetype":"venue"
},
  "geometry": {"coordinates":[-95.002797,29.618613],"type":"Point"}
}