{
  "type": "Feature",
  "properties": {
    "iso:country":"US",
    "sg:address":"1410 N Main St",
    "sg:city":"Fort Worth",
    "sg:classifiers":[
        {
            "category":"Shopping",
            "subcategory":"Florist",
            "type":"Retail Goods"
        }
    ],
    "sg:phone":"+1 817 626 5681",
    "sg:postcode":"76164",
    "sg:province":"TX",
    "sg:tags":[
        "merchandise"
    ],
    "wof:name":"B & L Flowers",
    "wof:placetype":"venue"
},
  "geometry": {"coordinates":[-97.347714,32.779477],"type":"Point"}
}