{
  "type": "Feature",
  "properties": {
    "iso:country":"US",
    "sg:address":"230 N Armstrong Rd",
    "sg:city":"Venus",
    "sg:classifiers":[
        {
            "category":"Building & Trades",
            "subcategory":"Electrical",
            "type":"Services"
        }
    ],
    "sg:phone":"+1 972 723 7984",
    "sg:postcode":"76084",
    "sg:province":"TX",
    "sg:tags":[
        "electrician"
    ],
    "wof:name":"Silverstone Electric",
    "wof:placetype":"venue"
},
  "geometry": {"coordinates":[-97.04760899999999,32.357447],"type":"Point"}
}