{
  "type": "Feature",
  "properties": {
    "iso:country":"US",
    "sg:address":"8752 Winding Ln",
    "sg:city":"Fort Worth",
    "sg:classifiers":[
        {
            "category":"Professional",
            "subcategory":"Business Services",
            "type":"Services"
        }
    ],
    "sg:phone":"+1 817 469 7512",
    "sg:postcode":"76120",
    "sg:province":"TX",
    "wof:name":"Carl Green Enterprises",
    "wof:placetype":"venue"
},
  "geometry": {"coordinates":[-97.16080599999999,32.766166],"type":"Point"}
}