{
  "type": "Feature",
  "properties": {
    "iso:country":"US",
    "sg:address":"13114 Ralph Culver Rd",
    "sg:city":"Houston",
    "sg:classifiers":[
        {
            "category":"Building & Trades",
            "subcategory":"Plumbing",
            "type":"Services"
        }
    ],
    "sg:phone":"+1 281 260 0293",
    "sg:postcode":"77086",
    "sg:province":"TX",
    "sg:tags":[
        "contractor"
    ],
    "wof:name":"Do It All Plumbing",
    "wof:placetype":"venue"
},
  "geometry": {"coordinates":[-95.47441999999999,29.924494],"type":"Point"}
}