{
  "type": "Feature",
  "properties": {
    "iso:country":"US",
    "sg:address":"9425 Sam Houston Pkwy",
    "sg:city":"Houston",
    "sg:classifiers":[
        {
            "category":"Organizations",
            "subcategory":"Religious Organization",
            "type":"Services"
        }
    ],
    "sg:phone":"+1 281 890 1002",
    "sg:postcode":"77064",
    "sg:province":"TX",
    "wof:name":"Houston Ctrl Seven Day Advnts",
    "wof:placetype":"venue"
},
  "geometry": {"coordinates":[-95.553978,29.904028],"type":"Point"}
}