{
  "type": "Feature",
  "properties": {
    "iso:country":"US",
    "sg:address":"601 Van Cleve Dr",
    "sg:city":"Corpus Christi",
    "sg:classifiers":[
        {
            "category":"Professional",
            "type":"Services"
        }
    ],
    "sg:phone":"+1 361 883 5447",
    "sg:postcode":"78408",
    "sg:province":"TX",
    "wof:name":"Buccaneer Games",
    "wof:placetype":"venue"
},
  "geometry": {"coordinates":[-97.44105399999999,27.797072],"type":"Point"}
}