{
  "type": "Feature",
  "properties": {
    "iso:country":"US",
    "sg:address":"6906 Atwell Dr",
    "sg:city":"Houston",
    "sg:classifiers":[
        {
            "category":"Professional",
            "subcategory":"Lawyer & Legal Services",
            "type":"Services"
        }
    ],
    "sg:phone":"+1 832 778 8561",
    "sg:postcode":"77081",
    "sg:province":"TX",
    "wof:name":"Garcia Israel B Jr Atty",
    "wof:placetype":"venue"
},
  "geometry": {"coordinates":[-95.482697,29.7043],"type":"Point"}
}