{
  "type": "Feature",
  "properties": {
    "iso:country":"US",
    "sg:address":"6502 Caprock Dr",
    "sg:city":"Lubbock",
    "sg:classifiers":[
        {
            "category":"Banks & Credit Unions",
            "subcategory":"Bank",
            "type":"Services"
        }
    ],
    "sg:phone":"+1 806 745 4575",
    "sg:postcode":"79412",
    "sg:province":"TX",
    "sg:tags":[
        "loan"
    ],
    "wof:name":"Ag Texas Farm Credit Svc",
    "wof:placetype":"venue"
},
  "geometry": {"coordinates":[-101.845715,33.535554],"type":"Point"}
}