{
  "type": "Feature",
  "properties": {
    "iso:country":"US",
    "sg:address":"925 N Carrier Pkwy",
    "sg:city":"Grand Prairie",
    "sg:classifiers":[
        {
            "category":"Wholesale",
            "subcategory":"Durable Goods & Equipment",
            "type":"Manufacturing & Wholesale Goods"
        }
    ],
    "sg:phone":"+1 972 641 0386",
    "sg:postcode":"75050",
    "sg:province":"TX",
    "sg:tags":[
        "importer"
    ],
    "wof:name":"Wainwright Industries",
    "wof:placetype":"venue"
},
  "geometry": {"coordinates":[-97.017399,32.753453],"type":"Point"}
}