{
  "type": "Feature",
  "properties": {
    "iso:country":"US",
    "sg:address":"4620 Royal Ln",
    "sg:city":"Dallas",
    "sg:phone":"+1 214 373 0093",
    "sg:postcode":"75229",
    "sg:province":"TX",
    "sg:tags":[
        "equipment",
        "commercial"
    ],
    "wof:name":"BJ Finicial Corp",
    "wof:placetype":"venue"
},
  "geometry": {"coordinates":[-96.82876,32.894918],"type":"Point"}
}