{
  "type": "Feature",
  "properties": {
    "iso:country":"US",
    "sg:address":"1322 Space Park Dr Ste A2",
    "sg:city":"Houston",
    "sg:classifiers":[
        {
            "category":"Building & Trades",
            "subcategory":"Construction",
            "type":"Services"
        }
    ],
    "sg:phone":"+1 281 335 5544",
    "sg:postcode":"77058",
    "sg:province":"TX",
    "sg:tags":[
        "management"
    ],
    "wof:name":"Watco Management Inc",
    "wof:placetype":"venue"
},
  "geometry": {"coordinates":[-95.100351,29.546325],"type":"Point"}
}