{
  "type": "Feature",
  "properties": {
    "iso:country":"US",
    "sg:address":"15101 S Padre Island Dr",
    "sg:city":"Corpus Christi",
    "sg:classifiers":[
        {
            "category":"Personal",
            "subcategory":"Beauty Salon",
            "type":"Services"
        }
    ],
    "sg:phone":"+1 361 949 6777",
    "sg:postcode":"78418",
    "sg:province":"TX",
    "wof:name":"Papillion Day & Spa",
    "wof:placetype":"venue"
},
  "geometry": {"coordinates":[-97.222161,27.607525],"type":"Point"}
}