{
  "type": "Feature",
  "properties": {
    "iso:country":"US",
    "sg:address":"9795 Shepherd St",
    "sg:city":"Beaumont",
    "sg:classifiers":[
        {
            "category":"Wholesale",
            "subcategory":"Painting Supplies",
            "type":"Manufacturing & Wholesale Goods"
        }
    ],
    "sg:phone":"+1 409 860 4372",
    "sg:postcode":"77707",
    "sg:province":"TX",
    "wof:name":"Works Of Fine Art",
    "wof:placetype":"venue"
},
  "geometry": {"coordinates":[-94.20692099999999,30.072933],"type":"Point"}
}