{
  "type": "Feature",
  "properties": {
    "iso:country":"US",
    "sg:address":"4910 Timber Hts",
    "sg:city":"San Antonio",
    "sg:classifiers":[
        {
            "category":"Wholesale",
            "subcategory":"Non-durable Goods",
            "type":"Manufacturing & Wholesale Goods"
        }
    ],
    "sg:phone":"+1 210 681 0356",
    "sg:postcode":"78250",
    "sg:province":"TX",
    "wof:name":"Sewing Supplies Imports",
    "wof:placetype":"venue"
},
  "geometry": {"coordinates":[-98.64827200000001,29.484821],"type":"Point"}
}