{
  "type": "Feature",
  "properties": {
    "iso:country":"US",
    "sg:address":"116 Walton Dr",
    "sg:city":"College Station",
    "sg:classifiers":[
        {
            "category":"Home & Garden",
            "subcategory":"Building Materials",
            "type":"Retail Goods"
        }
    ],
    "sg:phone":"+1 979 764 8240",
    "sg:postcode":"77840",
    "sg:province":"TX",
    "sg:tags":[
        "glass",
        "window",
        "plate"
    ],
    "wof:name":"Aggieland Glass & Mirror",
    "wof:placetype":"venue"
},
  "geometry": {"coordinates":[-96.328524,30.624223],"type":"Point"}
}