{
  "type": "Feature",
  "properties": {
    "iso:country":"US",
    "sg:address":"9926 Glenkirk Dr",
    "sg:city":"Houston",
    "sg:classifiers":[
        {
            "category":"Professional",
            "type":"Services"
        }
    ],
    "sg:phone":"+1 281 481 4323",
    "sg:postcode":"77089",
    "sg:province":"TX",
    "wof:name":"Hurd M Jones Jr Scholarsh",
    "wof:placetype":"venue"
},
  "geometry": {"coordinates":[-95.24575400000001,29.598877],"type":"Point"}
}