{
  "type": "Feature",
  "properties": {
    "iso:country":"US",
    "sg:address":"5807 Nutcracker Dr",
    "sg:city":"Granbury",
    "sg:classifiers":[
        {
            "category":"Professional",
            "subcategory":"Secretarial Services",
            "type":"Services"
        }
    ],
    "sg:phone":"+1 817 573 9102",
    "sg:postcode":"76049",
    "sg:province":"TX",
    "sg:tags":[
        "reporting"
    ],
    "wof:name":"Walters & Associates",
    "wof:placetype":"venue"
},
  "geometry": {"coordinates":[-97.670119,32.362027],"type":"Point"}
}