{
  "type": "Feature",
  "properties": {
    "iso:country":"US",
    "sg:address":"1518 W Koenig Ln",
    "sg:city":"Austin",
    "sg:classifiers":[
        {
            "category":"Professional",
            "subcategory":"Management & Consulting",
            "type":"Services"
        }
    ],
    "sg:phone":"+1 512 465 9000",
    "sg:postcode":"78756",
    "sg:province":"TX",
    "sg:tags":[
        "consultant",
        "search",
        "executive"
    ],
    "wof:name":"Acadia Hr",
    "wof:placetype":"venue"
},
  "geometry": {"coordinates":[-97.733197,30.331643],"type":"Point"}
}