{
  "type": "Feature",
  "properties": {
    "iso:country":"US",
    "sg:address":"2500 E Central Texas Expy",
    "sg:city":"Killeen",
    "sg:classifiers":[
        {
            "category":"Shopping",
            "subcategory":"Hobbies, Toys, & Games",
            "type":"Retail Goods"
        }
    ],
    "sg:phone":"+1 254 634 8697",
    "sg:postcode":"76543",
    "sg:province":"TX",
    "wof:name":"Toys R Us",
    "wof:placetype":"venue"
},
  "geometry": {"coordinates":[-97.718929,31.089663],"type":"Point"}
}