{
  "type": "Feature",
  "properties": {
    "iso:country":"US",
    "sg:address":"7515 Carriage Dr",
    "sg:city":"Austin",
    "sg:classifiers":[
        {
            "category":"Retail",
            "subcategory":"Laundry & Dry Cleaning",
            "type":"Services"
        }
    ],
    "sg:phone":"+1 512 459 5613",
    "sg:postcode":"78752",
    "sg:province":"TX",
    "sg:tags":[
        "cleaners",
        "rug",
        "carpet"
    ],
    "wof:name":"Above-N-Beyond Restoration",
    "wof:placetype":"venue"
},
  "geometry": {"coordinates":[-97.707498,30.340385],"type":"Point"}
}