{
  "type": "Feature",
  "properties": {
    "iso:country":"US",
    "sg:address":"2715 E Parker Rd",
    "sg:city":"Plano",
    "sg:classifiers":[
        {
            "category":"Farming",
            "subcategory":"Farm",
            "type":"Manufacturing & Wholesale Goods"
        }
    ],
    "sg:phone":"+1 972 422 1126",
    "sg:postcode":"75074",
    "sg:province":"TX",
    "sg:tags":[
        "crop",
        "general"
    ],
    "wof:name":"Buckley Farms",
    "wof:placetype":"venue"
},
  "geometry": {"coordinates":[-96.67769199999999,33.044492],"type":"Point"}
}