{
  "type": "Feature",
  "properties": {
    "iso:country":"US",
    "sg:address":"1417 N Big Spring St",
    "sg:city":"Midland",
    "sg:classifiers":[
        {
            "category":"Shopping",
            "subcategory":"Clothing, Apparel, & Fashions",
            "type":"Retail Goods"
        }
    ],
    "sg:phone":"+1 432 687 2411",
    "sg:postcode":"79701",
    "sg:province":"TX",
    "sg:tags":[
        "shop",
        "bridal"
    ],
    "wof:name":"An Elegant Touch",
    "wof:placetype":"venue"
},
  "geometry": {"coordinates":[-102.078642,32.011819],"type":"Point"}
}