{
  "type": "Feature",
  "properties": {
    "iso:country":"US",
    "sg:address":"5811 Gomer Pyle Dr",
    "sg:city":"San Antonio",
    "sg:classifiers":[
        {
            "category":"Building & Trades",
            "subcategory":"Construction",
            "type":"Services"
        }
    ],
    "sg:phone":"+1 210 509 3390",
    "sg:postcode":"78240",
    "sg:province":"TX",
    "sg:tags":[
        "contractor"
    ],
    "wof:name":"Ash Masonry",
    "wof:placetype":"venue"
},
  "geometry": {"coordinates":[-98.60088,29.505118],"type":"Point"}
}