{
  "type": "Feature",
  "properties": {
    "iso:country":"US",
    "sg:address":"701 E Rendon Crowley Rd",
    "sg:city":"Burleson",
    "sg:classifiers":[
        {
            "category":"Health Services",
            "subcategory":"Doctor",
            "type":"Services"
        }
    ],
    "sg:phone":"+1 817 293 9292",
    "sg:postcode":"76028",
    "sg:province":"TX",
    "wof:name":"Anees Mukhtar MD",
    "wof:placetype":"venue"
},
  "geometry": {"coordinates":[-97.311745,32.580306],"type":"Point"}
}