{
  "type": "Feature",
  "properties": {
    "iso:country":"US",
    "sg:address":"710 E Center St",
    "sg:city":"Longview",
    "sg:classifiers":[
        {
            "category":"Organizations",
            "subcategory":"Religious Organization",
            "type":"Services"
        }
    ],
    "sg:phone":"+1 903 295 9101",
    "sg:postcode":"75693",
    "sg:province":"TX",
    "sg:tags":[
        "church"
    ],
    "wof:name":"Center Street Church Of Christ",
    "wof:placetype":"venue"
},
  "geometry": {"coordinates":[-94.850385,32.532984],"type":"Point"}
}