{
  "type": "Feature",
  "properties": {
    "iso:country":"US",
    "sg:address":"418 Villita St",
    "sg:city":"San Antonio",
    "sg:classifiers":[
        {
            "category":"Shopping",
            "subcategory":"Hobbies, Toys, & Games",
            "type":"Retail Goods"
        },
        {
            "category":"Shopping",
            "type":"Retail Goods"
        }
    ],
    "sg:phone":"+1 210 226 7625",
    "sg:postcode":"78205",
    "sg:province":"TX",
    "sg:tags":[
        "shop",
        "merchandise",
        "rock"
    ],
    "wof:name":"Originals Jewelry & Gifts",
    "wof:placetype":"venue"
},
  "geometry": {"coordinates":[-98.48899900000001,29.421765],"type":"Point"}
}