{
  "type": "Feature",
  "properties": {
    "iso:country":"US",
    "sg:address":"107 Sunflower St",
    "sg:city":"Georgetown",
    "sg:classifiers":[
        {
            "category":"Professional",
            "type":"Services"
        }
    ],
    "sg:phone":"+1 512 864 0370",
    "sg:postcode":"78633",
    "sg:province":"TX",
    "wof:name":"Lemleys Arts",
    "wof:placetype":"venue"
},
  "geometry": {"coordinates":[-97.713129,30.711239],"type":"Point"}
}