{
  "type": "Feature",
  "properties": {
    "iso:country":"US",
    "sg:address":"5803 de Lange Ln",
    "sg:city":"Houston",
    "sg:classifiers":[
        {
            "category":"Building & Trades",
            "subcategory":"Construction",
            "type":"Services"
        }
    ],
    "sg:phone":"+1 713 681 0800",
    "sg:postcode":"77092",
    "sg:province":"TX",
    "sg:tags":[
        "contractor"
    ],
    "wof:name":"J G Thompson Construction MGT",
    "wof:placetype":"venue"
},
  "geometry": {"coordinates":[-95.476827,29.835977],"type":"Point"}
}