{
  "type": "Feature",
  "properties": {
    "iso:country":"US",
    "sg:address":"3518 FM 973 S",
    "sg:city":"Del Valle",
    "sg:classifiers":[
        {
            "category":"Recreation",
            "type":"Entertainment"
        }
    ],
    "sg:phone":"+1 512 247 4407",
    "sg:postcode":"78617",
    "sg:province":"TX",
    "sg:tags":[
        "hall",
        "auditorium"
    ],
    "wof:name":"Del Valle-South Rural Comm",
    "wof:placetype":"venue"
},
  "geometry": {"coordinates":[-97.64375200000001,30.197025],"type":"Point"}
}