{
  "type": "Feature",
  "properties": {
    "iso:country":"US",
    "sg:address":"11401 Elam Rd",
    "sg:city":"Balch Springs",
    "sg:classifiers":[
        {
            "category":"Organizations",
            "subcategory":"Non-profit Organization",
            "type":"Services"
        }
    ],
    "sg:phone":"+1 972 286 9230",
    "sg:postcode":"75180",
    "sg:province":"TX",
    "sg:tags":[
        "information",
        "alcoholism",
        "treatment"
    ],
    "wof:name":"Alcoholics Anonymous",
    "wof:placetype":"venue"
},
  "geometry": {"coordinates":[-96.62679799999999,32.719577],"type":"Point"}
}