{
  "type": "Feature",
  "properties": {
    "iso:country":"US",
    "sg:address":"14414 Dewberry Dr",
    "sg:city":"Pflugerville",
    "sg:classifiers":[
        {
            "category":"Restaurant",
            "type":"Food & Drink"
        }
    ],
    "sg:phone":"+1 512 252 3140",
    "sg:postcode":"78660",
    "sg:province":"TX",
    "sg:tags":[
        "eating"
    ],
    "wof:name":"Smoke In Your Eyes Bbq",
    "wof:placetype":"venue"
},
  "geometry": {"coordinates":[-97.631502,30.41471],"type":"Point"}
}