{
  "type": "Feature",
  "properties": {
    "iso:country":"US",
    "sg:address":"5627 Smu Blvd",
    "sg:city":"Dallas",
    "sg:classifiers":[
        {
            "category":"Bars & Pubs",
            "subcategory":"Nightclub",
            "type":"Food & Drink"
        }
    ],
    "sg:phone":"+1 214 691 5296",
    "sg:postcode":"75206",
    "sg:province":"TX",
    "sg:tags":[
        "nightlife"
    ],
    "wof:name":"Across The Street Bar",
    "wof:placetype":"venue"
},
  "geometry": {"coordinates":[-96.77187499999999,32.84214],"type":"Point"}
}