{
  "type": "Feature",
  "properties": {
    "iso:country":"US",
    "sg:address":"4050 Rio Bravo St",
    "sg:city":"El Paso",
    "sg:classifiers":[
        {
            "category":"Autos & Motor Vehicles",
            "subcategory":"Automobile Sales",
            "type":"Retail Goods"
        }
    ],
    "sg:phone":"+1 915 351 8855",
    "sg:postcode":"79902",
    "sg:province":"TX",
    "sg:tags":[
        "car",
        "dealer"
    ],
    "wof:name":"United Auto Credit Corp",
    "wof:placetype":"venue"
},
  "geometry": {"coordinates":[-106.515807,31.79398],"type":"Point"}
}