{
  "type": "Feature",
  "properties": {
    "iso:country":"US",
    "sg:address":"2521 Rutland Dr",
    "sg:city":"Austin",
    "sg:classifiers":[
        {
            "category":"Personal",
            "type":"Services"
        }
    ],
    "sg:phone":"+1 512 491 6966",
    "sg:postcode":"78758",
    "sg:province":"TX",
    "sg:tags":[
        "clinic",
        "therapy",
        "physical"
    ],
    "wof:name":"Massage and Body Care",
    "wof:placetype":"venue"
},
  "geometry": {"coordinates":[-97.722881,30.383049],"type":"Point"}
}