{
  "type": "Feature",
  "properties": {
    "iso:country":"US",
    "sg:address":"1704 US Hwy 83",
    "sg:city":"Zapata",
    "sg:classifiers":[
        {
            "category":"Personal",
            "subcategory":"Barber",
            "type":"Services"
        }
    ],
    "sg:phone":"+1 956 765 6461",
    "sg:postcode":"78076",
    "sg:province":"TX",
    "sg:tags":[
        "shop"
    ],
    "wof:name":"Gonzalez Barber Shop",
    "wof:placetype":"venue"
},
  "geometry": {"coordinates":[-99.275345,26.912023],"type":"Point"}
}