{
  "type": "Feature",
  "properties": {
    "iso:country":"US",
    "sg:address":"2126 Virginia St",
    "sg:city":"Grand Prairie",
    "sg:classifiers":[
        {
            "category":"Health Services",
            "subcategory":"Doctor",
            "type":"Services"
        }
    ],
    "sg:phone":"+1 972 264 5795",
    "sg:postcode":"75051",
    "sg:province":"TX",
    "sg:tags":[
        "dental",
        "clinic",
        "dentist"
    ],
    "wof:name":"Novak George & Maxey",
    "wof:placetype":"venue"
},
  "geometry": {"coordinates":[-97.013161,32.718357],"type":"Point"}
}