{
  "type": "Feature",
  "properties": {
    "iso:country":"US",
    "sg:address":"925 Moller Rd",
    "sg:city":"Alvin",
    "sg:classifiers":[
        {
            "category":"Manufacturing",
            "subcategory":"Metals",
            "type":"Manufacturing & Wholesale Goods"
        },
        {
            "category":"Wholesale",
            "subcategory":"Metals & Minerals",
            "type":"Manufacturing & Wholesale Goods"
        }
    ],
    "sg:phone":"+1 281 331 5789",
    "sg:postcode":"77511",
    "sg:province":"TX",
    "sg:tags":[
        "wire",
        "cable",
        "mfg"
    ],
    "wof:name":"Cablepro Inc",
    "wof:placetype":"venue"
},
  "geometry": {"coordinates":[-95.256074,29.413563],"type":"Point"}
}