{
  "type": "Feature",
  "properties": {
    "iso:country":"US",
    "sg:address":"2420 N Haskell Ave",
    "sg:city":"Dallas",
    "sg:classifiers":[
        {
            "category":"Retail",
            "subcategory":"Laundry & Dry Cleaning",
            "type":"Services"
        }
    ],
    "sg:phone":"+1 214 821 3685",
    "sg:postcode":"75204",
    "sg:province":"TX",
    "wof:name":"Wash Works Coin Laundry",
    "wof:placetype":"venue"
},
  "geometry": {"coordinates":[-96.789565,32.80492],"type":"Point"}
}