{
  "type": "Feature",
  "properties": {
    "iso:country":"US",
    "sg:address":"1788 Hwy 157 N",
    "sg:city":"Mansfield",
    "sg:classifiers":[
        {
            "category":"Health Services",
            "subcategory":"Doctor",
            "type":"Services"
        }
    ],
    "sg:phone":"+1 817 453 9166",
    "sg:postcode":"76063",
    "sg:province":"TX",
    "sg:tags":[
        "physician",
        "surgeon"
    ],
    "wof:name":"Marvin Lynn Faulkner DO",
    "wof:placetype":"venue"
},
  "geometry": {"coordinates":[-97.148135,32.596351],"type":"Point"}
}