{
  "type": "Feature",
  "properties": {
    "iso:country":"US",
    "sg:address":"2100 N Stemmons Fwy",
    "sg:city":"Dallas",
    "sg:classifiers":[
        {
            "category":"Manufacturing",
            "subcategory":"Leather Goods",
            "type":"Manufacturing & Wholesale Goods"
        }
    ],
    "sg:phone":"+1 214 760 8626",
    "sg:postcode":"75207",
    "sg:province":"TX",
    "wof:name":"Scully Leather Wear",
    "wof:placetype":"venue"
},
  "geometry": {"coordinates":[-96.82570800000001,32.802005],"type":"Point"}
}