{
  "type": "Feature",
  "properties": {
    "iso:country":"US",
    "sg:address":"919 Main St",
    "sg:city":"Bastrop",
    "sg:phone":"+1 512 371 8832",
    "sg:postcode":"78602",
    "sg:province":"TX",
    "sg:website":"http://austin.citysearch.com/profile/external/603449632/bastrop_tx/roto_rooter_plumbing_drain_service.html?publisher=yellowpages&reference_id=1&placement=ypwebsitemip",
    "wof:name":"Roto-Rooter Plumbing & Drain Service",
    "wof:placetype":"venue"
},
  "geometry": {"coordinates":[-97.319975,30.109632],"type":"Point"}
}