{
  "type": "Feature",
  "properties": {
    "iso:country":"US",
    "sg:address":"907 Halsell Ave",
    "sg:city":"Bridgeport",
    "sg:classifiers":[
        {
            "category":"Home & Garden",
            "subcategory":"Carpets & Floor Coverings",
            "type":"Retail Goods"
        }
    ],
    "sg:phone":"+1 940 683 6674",
    "sg:postcode":"76426",
    "sg:province":"TX",
    "wof:name":"Giselles Little Shop",
    "wof:placetype":"venue"
},
  "geometry": {"coordinates":[-97.765975,33.210516],"type":"Point"}
}