{
  "type": "Feature",
  "properties": {
    "iso:country":"US",
    "sg:address":"3020 E Hwy 377",
    "sg:city":"Granbury",
    "sg:classifiers":[
        {
            "category":"Professional",
            "subcategory":"Accounting & Tax Preparation",
            "type":"Services"
        }
    ],
    "sg:phone":"+1 817 573 5838",
    "sg:postcode":"76049",
    "sg:province":"TX",
    "wof:name":"Barker & Fleming PC",
    "wof:placetype":"venue"
},
  "geometry": {"coordinates":[-97.74007,32.449452],"type":"Point"}
}