{
  "type": "Feature",
  "properties": {
    "iso:country":"US",
    "sg:address":"6023 Foxcroft Rd",
    "sg:city":"Tyler",
    "sg:classifiers":[
        {
            "category":"Shopping",
            "type":"Retail Goods"
        }
    ],
    "sg:phone":"+1 903 509 4453",
    "sg:postcode":"75703",
    "sg:province":"TX",
    "sg:tags":[
        "merchandise"
    ],
    "wof:name":"McIntire Galleries",
    "wof:placetype":"venue"
},
  "geometry": {"coordinates":[-95.292647,32.282167],"type":"Point"}
}