{
  "type": "Feature",
  "properties": {
    "iso:country":"US",
    "sg:address":"101 N de Leon St",
    "sg:city":"Victoria",
    "sg:classifiers":[
        {
            "category":"Professional",
            "subcategory":"Advertising",
            "type":"Services"
        }
    ],
    "sg:phone":"+1 361 570 2933",
    "sg:postcode":"77901",
    "sg:province":"TX",
    "sg:tags":[
        "agency"
    ],
    "wof:name":"Captive Eye Publishing",
    "wof:placetype":"venue"
},
  "geometry": {"coordinates":[-97.002753,28.799054],"type":"Point"}
}