{
  "type": "Feature",
  "properties": {
    "iso:country":"US",
    "sg:address":"2110 Cupples Rd",
    "sg:city":"San Antonio",
    "sg:classifiers":[
        {
            "category":"Restaurant",
            "type":"Food & Drink"
        }
    ],
    "sg:phone":"+1 210 435 1937",
    "sg:postcode":"78226",
    "sg:province":"TX",
    "wof:name":"Kelly Island Bar and Cafe",
    "wof:placetype":"venue"
},
  "geometry": {"coordinates":[-98.550471,29.386918],"type":"Point"}
}