{
  "type": "Feature",
  "properties": {
    "iso:country":"US",
    "sg:address":"4622 Long Climb Cyn",
    "sg:city":"Humble",
    "sg:classifiers":[
        {
            "category":"Sports & Exercise",
            "subcategory":"Gym",
            "type":"Entertainment"
        }
    ],
    "sg:phone":"+1 281 441 1982",
    "sg:postcode":"77396",
    "sg:province":"TX",
    "sg:tags":[
        "gymnasium"
    ],
    "wof:name":"Elitefit Physical Training",
    "wof:placetype":"venue"
},
  "geometry": {"coordinates":[-95.23964700000001,29.941677],"type":"Point"}
}