{
  "type": "Feature",
  "properties": {
    "iso:country":"US",
    "sg:address":"104 Dianne Ln",
    "sg:city":"Mount Pleasant",
    "sg:classifiers":[
        {
            "category":"Shopping",
            "subcategory":"Discount & Variety Stores",
            "type":"Retail Goods"
        }
    ],
    "sg:phone":"+1 903 577 8855",
    "sg:postcode":"75455",
    "sg:province":"TX",
    "sg:tags":[
        "mill",
        "oil",
        "merchandise",
        "soybean",
        "general"
    ],
    "wof:name":"Bowman Enterprises",
    "wof:placetype":"venue"
},
  "geometry": {"coordinates":[-94.965964,33.186524],"type":"Point"}
}