{
  "type": "Feature",
  "properties": {
    "iso:country":"US",
    "sg:address":"5415 Maple Ave",
    "sg:city":"Dallas",
    "sg:classifiers":[
        {
            "category":"Organizations",
            "subcategory":"Non-profit Organization",
            "type":"Services"
        }
    ],
    "sg:phone":"+1 214 905 0770",
    "sg:postcode":"75235",
    "sg:province":"TX",
    "sg:tags":[
        "social"
    ],
    "wof:name":"Aa",
    "wof:placetype":"venue"
},
  "geometry": {"coordinates":[-96.83327800000001,32.818568],"type":"Point"}
}