{
  "type": "Feature",
  "properties": {
    "iso:country":"US",
    "sg:address":"2502 Marlin Dr",
    "sg:city":"Killeen",
    "sg:classifiers":[
        {
            "category":"Professional",
            "subcategory":"Business Services",
            "type":"Services"
        }
    ],
    "sg:phone":"+1 254 690 3479",
    "sg:postcode":"76543",
    "sg:province":"TX",
    "wof:name":"Central Texas Refinishers",
    "wof:placetype":"venue"
},
  "geometry": {"coordinates":[-97.685829,31.127934],"type":"Point"}
}