{
  "type": "Feature",
  "properties": {
    "iso:country":"US",
    "sg:address":"9900 Mountain Quail",
    "sg:city":"Austin",
    "sg:classifiers":[
        {
            "category":"Building & Trades",
            "subcategory":"Cleaning & Sanitation",
            "type":"Services"
        }
    ],
    "sg:phone":"+1 512 529 9090",
    "sg:postcode":"78758",
    "sg:province":"TX",
    "sg:tags":[
        "home"
    ],
    "sg:website":"www.heavenlymaid.com",
    "wof:name":"Heavenly Maid & Cleaning Service",
    "wof:placetype":"venue"
},
  "geometry": {"coordinates":[-97.70699500000001,30.375352],"type":"Point"}
}