{
  "type": "Feature",
  "properties": {
    "iso:country":"US",
    "sg:address":"801 Eastern Valley Ln",
    "sg:city":"Whitesboro",
    "sg:classifiers":[
        {
            "category":"Freight",
            "type":"Transportation"
        }
    ],
    "sg:phone":"+1 940 668 0628",
    "sg:postcode":"76273",
    "sg:province":"TX",
    "sg:tags":[
        "operator",
        "local",
        "trucking"
    ],
    "wof:name":"TLC Equine Transportation",
    "wof:placetype":"venue"
},
  "geometry": {"coordinates":[-96.972256,33.66481],"type":"Point"}
}