{
  "type": "Feature",
  "properties": {
    "iso:country":"US",
    "sg:address":"1705 Shire St",
    "sg:city":"Pflugerville",
    "sg:classifiers":[
        {
            "category":"Professional",
            "type":"Services"
        }
    ],
    "sg:phone":"+1 512 990 0282",
    "sg:postcode":"78660",
    "sg:province":"TX",
    "wof:name":"Kosich LLC",
    "wof:placetype":"venue"
},
  "geometry": {"coordinates":[-97.574974,30.493634],"type":"Point"}
}