{
  "type": "Feature",
  "properties": {
    "iso:country":"US",
    "sg:address":"1003 Antelope Ridge",
    "sg:city":"Cedar Park",
    "sg:classifiers":[
        {
            "category":"Professional",
            "subcategory":"Management & Consulting",
            "type":"Services"
        }
    ],
    "sg:phone":"+1 512 528 8069",
    "sg:postcode":"78613",
    "sg:province":"TX",
    "wof:name":"JMB Consulting J",
    "wof:placetype":"venue"
},
  "geometry": {"coordinates":[-97.80558499999999,30.504995],"type":"Point"}
}