{
  "type": "Feature",
  "properties": {
    "iso:country":"US",
    "sg:address":"3000 Kellway Dr Ste 108",
    "sg:city":"Carrollton",
    "sg:classifiers":[
        {
            "category":"Shopping",
            "subcategory":"Stationery & Office Supplies",
            "type":"Retail Goods"
        }
    ],
    "sg:phone":"+1 972 418 9594",
    "sg:postcode":"75006",
    "sg:province":"TX",
    "sg:tags":[
        "equipment"
    ],
    "sg:website":"www.konica.com",
    "wof:name":"Konica Minolta Business Solutions",
    "wof:placetype":"venue"
},
  "geometry": {"coordinates":[-96.851392,32.973742],"type":"Point"}
}