{
  "type": "Feature",
  "properties": {
    "iso:country":"US",
    "sg:address":"14110 River Forest Dr",
    "sg:city":"Houston",
    "sg:classifiers":[
        {
            "category":"Retail",
            "subcategory":"Portrait Studio",
            "type":"Services"
        }
    ],
    "sg:phone":"+1 281 759 9908",
    "sg:postcode":"77079",
    "sg:province":"TX",
    "sg:tags":[
        "photo"
    ],
    "wof:name":"James Hoffman Photographer",
    "wof:placetype":"venue"
},
  "geometry": {"coordinates":[-95.591464,29.762296],"type":"Point"}
}