{
  "type": "Feature",
  "properties": {
    "iso:country":"US",
    "sg:address":"1111 Northpoint Dr",
    "sg:city":"Coppell",
    "sg:classifiers":[
        {
            "category":"Professional",
            "subcategory":"Credit Reporting & Collection",
            "type":"Services"
        }
    ],
    "sg:phone":"+1 972 657 1286",
    "sg:postcode":"75019",
    "sg:province":"TX",
    "sg:tags":[
        "loan",
        "broker"
    ],
    "wof:name":"Citifinancial Mortgage Company",
    "wof:placetype":"venue"
},
  "geometry": {"coordinates":[-97.02598399999999,32.96773],"type":"Point"}
}