{
  "type": "Feature",
  "properties": {
    "iso:country":"US",
    "sg:address":"3605 Steck Ave",
    "sg:city":"Austin",
    "sg:classifiers":[
        {
            "category":"Building & Trades",
            "subcategory":"Landscaping Services",
            "type":"Services"
        }
    ],
    "sg:phone":"+1 512 349 9843",
    "sg:postcode":"78759",
    "sg:province":"TX",
    "sg:tags":[
        "landscape"
    ],
    "wof:name":"JC Landscaping",
    "wof:placetype":"venue"
},
  "geometry": {"coordinates":[-97.74573700000001,30.36964],"type":"Point"}
}