{
  "type": "Feature",
  "properties": {
    "iso:country":"US",
    "sg:address":"5325 Glenmont Dr",
    "sg:city":"Houston",
    "sg:classifiers":[
        {
            "category":"Shopping",
            "subcategory":"Clothing, Apparel, & Fashions",
            "type":"Retail Goods"
        }
    ],
    "sg:phone":"+1 713 661 7272",
    "sg:postcode":"77081",
    "sg:province":"TX",
    "sg:tags":[
        "datum"
    ],
    "wof:name":"Tom Girl",
    "wof:placetype":"venue"
},
  "geometry": {"coordinates":[-95.472605,29.720106],"type":"Point"}
}