{
  "type": "Feature",
  "properties": {
    "iso:country":"US",
    "sg:address":"802 Commerce St",
    "sg:city":"Dallas",
    "sg:classifiers":[
        {
            "category":"Local Transit",
            "type":"Transportation"
        }
    ],
    "sg:phone":"+1 214 849 8604",
    "sg:postcode":"75202",
    "sg:province":"TX",
    "sg:tags":[
        "bus"
    ],
    "wof:name":"Greyhound Packaging Express",
    "wof:placetype":"venue"
},
  "geometry": {"coordinates":[-96.804057,32.778757],"type":"Point"}
}