{
  "type": "Feature",
  "properties": {
    "iso:country":"US",
    "sg:address":"11792 Wilcrest Dr",
    "sg:city":"Houston",
    "sg:classifiers":[
        {
            "category":"Restaurant",
            "type":"Food & Drink"
        }
    ],
    "sg:phone":"+1 281 495 0137",
    "sg:postcode":"77099",
    "sg:province":"TX",
    "wof:name":"China Chef",
    "wof:placetype":"venue"
},
  "geometry": {"coordinates":[-95.569638,29.652459],"type":"Point"}
}