{
  "type": "Feature",
  "properties": {
    "iso:country":"US",
    "sg:address":"9425 Gardner St",
    "sg:city":"Beaumont",
    "sg:classifiers":[
        {
            "category":"Shopping",
            "subcategory":"Gifts & Souvenirs",
            "type":"Retail Goods"
        }
    ],
    "sg:phone":"+1 409 866 3022",
    "sg:postcode":"77707",
    "sg:province":"TX",
    "wof:name":"Prairie Rose",
    "wof:placetype":"venue"
},
  "geometry": {"coordinates":[-94.204674,30.07197],"type":"Point"}
}