{
  "type": "Feature",
  "properties": {
    "iso:country":"US",
    "sg:address":"14657 Pebble Bend Dr",
    "sg:city":"Houston",
    "sg:classifiers":[
        {
            "category":"Professional",
            "subcategory":"Computer Services",
            "type":"Services"
        }
    ],
    "sg:phone":"+1 713 939 1000",
    "sg:postcode":"77068",
    "sg:province":"TX",
    "sg:tags":[
        "processing",
        "datum"
    ],
    "sg:website":"www.ebs-next.com",
    "wof:name":"Ebs Mechdata Corp",
    "wof:placetype":"venue"
},
  "geometry": {"coordinates":[-95.48689400000001,29.994873],"type":"Point"}
}