{
  "type": "Feature",
  "properties": {
    "iso:country":"US",
    "sg:address":"103 Union St",
    "sg:city":"Borger",
    "sg:classifiers":[
        {
            "category":"Organizations",
            "subcategory":"Religious Organization",
            "type":"Services"
        }
    ],
    "sg:phone":"+1 806 274 6109",
    "sg:postcode":"79007",
    "sg:province":"TX",
    "sg:tags":[
        "church"
    ],
    "wof:name":"Kingdom Hall-Jehovah's",
    "wof:placetype":"venue"
},
  "geometry": {"coordinates":[-101.380251,35.655283],"type":"Point"}
}