{
  "type": "Feature",
  "properties": {
    "iso:country":"US",
    "sg:address":"11 Camden Pl",
    "sg:city":"Corpus Christi",
    "sg:classifiers":[
        {
            "category":"Freight",
            "type":"Transportation"
        }
    ],
    "sg:phone":"+1 361 991 8978",
    "sg:postcode":"78412",
    "sg:province":"TX",
    "sg:tags":[
        "arrangement"
    ],
    "wof:name":"Lin Jin LLC",
    "wof:placetype":"venue"
},
  "geometry": {"coordinates":[-97.360614,27.729086],"type":"Point"}
}