{
  "type": "Feature",
  "properties": {
    "iso:country":"US",
    "sg:address":"800 N Main St",
    "sg:city":"Vidor",
    "sg:classifiers":[
        {
            "category":"Food & Beverages",
            "subcategory":"Groceries & Convenience Stores",
            "type":"Retail Goods"
        }
    ],
    "sg:phone":"+1 409 769 6416",
    "sg:postcode":"77662",
    "sg:province":"TX",
    "wof:name":"M & E Food Mart",
    "wof:placetype":"venue"
},
  "geometry": {"coordinates":[-94.016103,30.134326],"type":"Point"}
}