{
  "type": "Feature",
  "properties": {
    "iso:country":"US",
    "sg:address":"11815 Lafferty Oaks St",
    "sg:city":"Houston",
    "sg:classifiers":[
        {
            "category":"Professional",
            "type":"Services"
        }
    ],
    "sg:phone":"+1 713 455 9133",
    "sg:postcode":"77013",
    "sg:province":"TX",
    "wof:name":"Gugogs",
    "wof:placetype":"venue"
},
  "geometry": {"coordinates":[-95.22636,29.778326],"type":"Point"}
}