{
  "type": "Feature",
  "properties": {
    "iso:country":"US",
    "sg:address":"16902 Soaring Forest Dr",
    "sg:city":"Houston",
    "sg:classifiers":[
        {
            "category":"Professional",
            "type":"Services"
        }
    ],
    "sg:phone":"+1 281 480 5434",
    "sg:postcode":"77059",
    "sg:province":"TX",
    "wof:name":"Sagar N Vidyasagaran",
    "wof:placetype":"venue"
},
  "geometry": {"coordinates":[-95.105332,29.602648],"type":"Point"}
}