{
  "type": "Feature",
  "properties": {
    "iso:country":"US",
    "sg:address":"1410 Preston Ave",
    "sg:city":"Pasadena",
    "sg:classifiers":[
        {
            "category":"Farming",
            "subcategory":"Livestock Farm",
            "type":"Manufacturing & Wholesale Goods"
        }
    ],
    "sg:phone":"+1 713 534 1276",
    "sg:postcode":"77503",
    "sg:province":"TX",
    "sg:tags":[
        "feeding"
    ],
    "wof:name":"Circle A",
    "wof:placetype":"venue"
},
  "geometry": {"coordinates":[-95.172715,29.690096],"type":"Point"}
}