{
  "type": "Feature",
  "properties": {
    "iso:country":"US",
    "sg:address":"516 N Main St",
    "sg:city":"Taylor",
    "sg:classifiers":[
        {
            "category":"Professional",
            "subcategory":"Employment Agencies",
            "type":"Services"
        }
    ],
    "sg:phone":"+1 512 365 8750",
    "sg:postcode":"76574",
    "sg:province":"TX",
    "sg:tags":[
        "consultant"
    ],
    "wof:name":"Texas Work Force Ctr",
    "wof:placetype":"venue"
},
  "geometry": {"coordinates":[-97.40980500000001,30.572404],"type":"Point"}
}