{
  "type": "Feature",
  "properties": {
    "iso:country":"US",
    "sg:address":"3860 Concord Rd",
    "sg:city":"Beaumont",
    "sg:classifiers":[
        {
            "category":"Wholesale",
            "subcategory":"Non-durable Goods",
            "type":"Manufacturing & Wholesale Goods"
        }
    ],
    "sg:phone":"+1 409 892 0475",
    "sg:postcode":"77703",
    "sg:province":"TX",
    "sg:tags":[
        "supply"
    ],
    "wof:name":"Cycads & Palms",
    "wof:placetype":"venue"
},
  "geometry": {"coordinates":[-94.13137399999999,30.113238],"type":"Point"}
}