{
  "type": "Feature",
  "properties": {
    "iso:country":"US",
    "sg:address":"1923 E Auburn St",
    "sg:city":"Lubbock",
    "sg:classifiers":[
        {
            "category":"Wholesale",
            "subcategory":"Machinery & Supplies",
            "type":"Manufacturing & Wholesale Goods"
        }
    ],
    "sg:phone":"+1 806 744 4847",
    "sg:postcode":"79403",
    "sg:province":"TX",
    "sg:tags":[
        "equipment",
        "establishment"
    ],
    "wof:name":"Sharons Beauty Supplies",
    "wof:placetype":"venue"
},
  "geometry": {"coordinates":[-101.809828,33.599787],"type":"Point"}
}