{
  "type": "Feature",
  "properties": {
    "iso:country":"US",
    "sg:address":"736 County Road 33450",
    "sg:city":"Sumner",
    "sg:classifiers":[
        {
            "category":"Government",
            "subcategory":"Office",
            "type":"Public Place"
        }
    ],
    "sg:phone":"+1 903 784 6085",
    "sg:postcode":"75486",
    "sg:province":"TX",
    "sg:tags":[
        "parish",
        "government-county"
    ],
    "wof:name":"Lamar County",
    "wof:placetype":"venue"
},
  "geometry": {"coordinates":[-95.67577799999999,33.73934],"type":"Point"}
}