{
  "type": "Feature",
  "properties": {
    "iso:country":"US",
    "sg:address":"2229 34th St",
    "sg:city":"Lubbock",
    "sg:classifiers":[
        {
            "category":"Shopping",
            "subcategory":"Jewelry",
            "type":"Retail Goods"
        }
    ],
    "sg:phone":"+1 806 744 7737",
    "sg:postcode":"79411",
    "sg:province":"TX",
    "sg:tags":[
        "jeweler"
    ],
    "wof:name":"Herff Jones Inc",
    "wof:placetype":"venue"
},
  "geometry": {"coordinates":[-101.865988,33.563204],"type":"Point"}
}