{
  "type": "Feature",
  "properties": {
    "iso:country":"US",
    "sg:address":"2000 S 10th St",
    "sg:city":"Mcallen",
    "sg:classifiers":[
        {
            "category":"Travel",
            "subcategory":"Hotels & Motels",
            "type":"Entertainment"
        }
    ],
    "sg:phone":"+1 956 686 1741",
    "sg:postcode":"78503",
    "sg:province":"TX",
    "sg:tags":[
        "operation"
    ],
    "sg:website":"http://www.holidayinn.com",
    "wof:name":"Holiday Inn",
    "wof:placetype":"venue"
},
  "geometry": {"coordinates":[-98.233087,26.185651],"type":"Point"}
}