{
  "type": "Feature",
  "properties": {
    "iso:country":"US",
    "sg:address":"105 W Gibbs St",
    "sg:city":"Del Rio",
    "sg:classifiers":[
        {
            "category":"Government",
            "subcategory":"Office",
            "type":"Public Place"
        }
    ],
    "sg:phone":"+1 830 774 8774",
    "sg:postcode":"78840",
    "sg:province":"TX",
    "sg:tags":[
        "village"
    ],
    "wof:name":"Del Rio Fleet Svc Maintenance",
    "wof:placetype":"venue"
},
  "geometry": {"coordinates":[-100.902232,29.364398],"type":"Point"}
}