{
  "type": "Feature",
  "properties": {
    "iso:country":"US",
    "sg:address":"1511 Misty Bend Dr",
    "sg:city":"Katy",
    "sg:classifiers":[
        {
            "category":"Professional",
            "subcategory":"Computer Services",
            "type":"Services"
        }
    ],
    "sg:phone":"+1 281 392 6099",
    "sg:postcode":"77494",
    "sg:province":"TX",
    "sg:tags":[
        "related"
    ],
    "wof:name":"Priddy Investments",
    "wof:placetype":"venue"
},
  "geometry": {"coordinates":[-95.81215899999999,29.767701],"type":"Point"}
}