{
  "type": "Feature",
  "properties": {
    "iso:country":"US",
    "sg:address":"1811 Judson Rd",
    "sg:city":"Longview",
    "sg:classifiers":[
        {
            "category":"Food & Beverages",
            "subcategory":"Groceries & Convenience Stores",
            "type":"Retail Goods"
        }
    ],
    "sg:phone":"+1 903 753 9002",
    "sg:postcode":"75605",
    "sg:province":"TX",
    "wof:name":"Tree Frog Deli & Catering",
    "wof:placetype":"venue"
},
  "geometry": {"coordinates":[-94.742672,32.527675],"type":"Point"}
}