{
  "type": "Feature",
  "properties": {
    "iso:country":"US",
    "sg:address":"7234 Boone Rd",
    "sg:city":"Houston",
    "sg:classifiers":[
        {
            "category":"Wholesale",
            "subcategory":"Machinery & Supplies",
            "type":"Manufacturing & Wholesale Goods"
        }
    ],
    "sg:phone":"+1 281 561 9977",
    "sg:postcode":"77072",
    "sg:province":"TX",
    "sg:tags":[
        "equipment",
        "establishment"
    ],
    "wof:name":"ATt Houston Barbr & Buty Sup",
    "wof:placetype":"venue"
},
  "geometry": {"coordinates":[-95.57539300000001,29.699525],"type":"Point"}
}