{
  "type": "Feature",
  "properties": {
    "iso:country":"US",
    "sg:address":"600 N Shelby St",
    "sg:city":"Carthage",
    "sg:classifiers":[
        {
            "category":"Autos & Motor Vehicles",
            "subcategory":"Fuel & Gas Station",
            "type":"Retail Goods"
        }
    ],
    "sg:phone":"+1 903 693 6322",
    "sg:postcode":"75633",
    "sg:province":"TX",
    "sg:tags":[
        "station",
        "gasoline"
    ],
    "wof:name":"Citgo",
    "wof:placetype":"venue"
},
  "geometry": {"coordinates":[-94.33879399999999,32.164854],"type":"Point"}
}