{
  "type": "Feature",
  "properties": {
    "iso:country":"US",
    "sg:address":"512 W Arapaho Rd",
    "sg:city":"Richardson",
    "sg:classifiers":[
        {
            "category":"Personal",
            "subcategory":"Nail Salon",
            "type":"Services"
        }
    ],
    "sg:phone":"+1 972 680 2000",
    "sg:postcode":"75080",
    "sg:province":"TX",
    "wof:name":"Orchid Nails",
    "wof:placetype":"venue"
},
  "geometry": {"coordinates":[-96.735606,32.961686],"type":"Point"}
}