{
  "type": "Feature",
  "properties": {
    "iso:country":"US",
    "sg:address":"1404 S Louisiana St",
    "sg:city":"Grandview",
    "sg:classifiers":[
        {
            "category":"Building & Trades",
            "subcategory":"Construction",
            "type":"Services"
        }
    ],
    "sg:phone":"+1 817 866 4313",
    "sg:postcode":"76050",
    "sg:province":"TX",
    "sg:tags":[
        "roofing"
    ],
    "wof:name":"Jgj Roofing",
    "wof:placetype":"venue"
},
  "geometry": {"coordinates":[-97.18183399999999,32.269414],"type":"Point"}
}