{
  "type": "Feature",
  "properties": {
    "iso:country":"US",
    "sg:address":"7056 Comanche Trl",
    "sg:city":"Austin",
    "sg:classifiers":[
        {
            "category":"Professional",
            "subcategory":"Management & Consulting",
            "type":"Services"
        }
    ],
    "sg:phone":"+1 512 266 7556",
    "sg:postcode":"78732",
    "sg:province":"TX",
    "sg:tags":[
        "consultant",
        "business"
    ],
    "wof:name":"Fullagar-Ellis Enterprises",
    "wof:placetype":"venue"
},
  "geometry": {"coordinates":[-97.896998,30.415885],"type":"Point"}
}