{
  "type": "Feature",
  "properties": {
    "iso:country":"US",
    "sg:address":"1085 River Rock",
    "sg:city":"New Braunfels",
    "sg:classifiers":[
        {
            "category":"Retail",
            "subcategory":"Repair Shop",
            "type":"Services"
        }
    ],
    "sg:phone":"+1 830 624 8071",
    "sg:postcode":"78130",
    "sg:province":"TX",
    "wof:name":"Solid Rock Home Technologies",
    "wof:placetype":"venue"
},
  "geometry": {"coordinates":[-98.087943,29.691921],"type":"Point"}
}