{
  "type": "Feature",
  "properties": {
    "iso:country":"US",
    "sg:address":"1319 Zion Hill Rd",
    "sg:city":"Seguin",
    "sg:classifiers":[
        {
            "category":"Building & Trades",
            "subcategory":"Construction",
            "type":"Services"
        },
        {
            "category":"Military Area",
            "subcategory":"Armory",
            "type":"Public Place"
        }
    ],
    "sg:phone":"+1 830 491 4231",
    "sg:postcode":"78155",
    "sg:province":"TX",
    "sg:tags":[
        "repair",
        "fence-sales",
        "fence",
        "contractor"
    ],
    "sg:website":"http://www.edhhernandezconstruction.com",
    "wof:name":"EDH Hernandez Construction",
    "wof:placetype":"venue"
},
  "geometry": {"coordinates":[-97.930953,29.479155],"type":"Point"}
}