{
  "type": "Feature",
  "properties": {
    "iso:country":"US",
    "sg:address":"1600 State Hwy 6",
    "sg:city":"Sugar Land",
    "sg:classifiers":[
        {
            "category":"Professional",
            "subcategory":"Accounting & Tax Preparation",
            "type":"Services"
        }
    ],
    "sg:phone":"+1 281 240 0141",
    "sg:postcode":"77478",
    "sg:province":"TX",
    "wof:name":"Brantley & Brantley",
    "wof:placetype":"venue"
},
  "geometry": {"coordinates":[-95.62841899999999,29.600362],"type":"Point"}
}