{
  "type": "Feature",
  "properties": {
    "iso:country":"US",
    "sg:address":"701 Solar Dr",
    "sg:city":"Victoria",
    "sg:classifiers":[
        {
            "category":"Real Estate",
            "subcategory":"Real Estate Services",
            "type":"Services"
        },
        {
            "category":"Real Estate",
            "subcategory":"Real Estate Agent",
            "type":"Services"
        }
    ],
    "sg:phone":"+1 361 575 7978",
    "sg:postcode":"77904",
    "sg:province":"TX",
    "sg:tags":[
        "management"
    ],
    "wof:name":"Leal Properties",
    "wof:placetype":"venue"
},
  "geometry": {"coordinates":[-97.01450800000001,28.892285],"type":"Point"}
}