{
  "type": "Feature",
  "properties": {
    "iso:country":"US",
    "sg:address":"316 Fm 927",
    "sg:city":"Morgan",
    "sg:classifiers":[
        {
            "category":"Personal",
            "subcategory":"Beauty Salon",
            "type":"Services"
        }
    ],
    "sg:phone":"+1 254 775 4231",
    "sg:postcode":"76671",
    "sg:province":"TX",
    "wof:name":"Village Hairport",
    "wof:placetype":"venue"
},
  "geometry": {"coordinates":[-97.599137,32.01694],"type":"Point"}
}