{
  "type": "Feature",
  "properties": {
    "iso:country":"US",
    "sg:address":"3127 Lawrence Rd",
    "sg:city":"Wichita Falls",
    "sg:classifiers":[
        {
            "category":"Retail",
            "subcategory":"Auto Repair",
            "type":"Services"
        }
    ],
    "sg:phone":"+1 940 691 8407",
    "sg:postcode":"76308",
    "sg:province":"TX",
    "sg:tags":[
        "repairing",
        "automobile"
    ],
    "wof:name":"Ferguson Pump & Supply Co",
    "wof:placetype":"venue"
},
  "geometry": {"coordinates":[-98.539919,33.875769],"type":"Point"}
}