{
  "type": "Feature",
  "properties": {
    "iso:country":"US",
    "sg:address":"6100 Southwest Fwy",
    "sg:city":"Houston",
    "sg:classifiers":[
        {
            "category":"Autos & Motor Vehicles",
            "subcategory":"Automobile Sales",
            "type":"Retail Goods"
        },
        {
            "category":"Retail",
            "subcategory":"Auto Repair",
            "type":"Services"
        }
    ],
    "sg:phone":"+1 713 772 3868",
    "sg:postcode":"77057",
    "sg:province":"TX",
    "sg:tags":[
        "body",
        "shop",
        "used",
        "new",
        "car"
    ],
    "sg:website":"www.ferrariofhouston.com/",
    "wof:name":"Ferrari of Houston",
    "wof:placetype":"venue"
},
  "geometry": {"coordinates":[-95.487297,29.7262],"type":"Point"}
}