{
  "type": "Feature",
  "properties": {
    "iso:country":"US",
    "sg:address":"6726 Loma Vista St",
    "sg:city":"Houston",
    "sg:classifiers":[
        {
            "category":"Retail",
            "subcategory":"Auto Repair",
            "type":"Services"
        }
    ],
    "sg:phone":"+1 713 551 9669",
    "sg:postcode":"77085",
    "sg:province":"TX",
    "sg:tags":[
        "automotive"
    ],
    "wof:name":"Tfw Auto",
    "wof:placetype":"venue"
},
  "geometry": {"coordinates":[-95.485191,29.61281],"type":"Point"}
}