{
  "type": "Feature",
  "properties": {
    "iso:country":"US",
    "sg:address":"9706 Aldine Westfield Rd",
    "sg:city":"Houston",
    "sg:classifiers":[
        {
            "category":"Building & Trades",
            "subcategory":"Plumbing",
            "type":"Services"
        }
    ],
    "sg:phone":"+1 713 695 7842",
    "sg:postcode":"77093",
    "sg:province":"TX",
    "sg:tags":[
        "contractor"
    ],
    "wof:name":"Havens AC & Rfrgn Svc",
    "wof:placetype":"venue"
},
  "geometry": {"coordinates":[-95.349778,29.853454],"type":"Point"}
}