{
  "type": "Feature",
  "properties": {
    "iso:country":"US",
    "sg:address":"919 Northwood St",
    "sg:city":"Baytown",
    "sg:classifiers":[
        {
            "category":"Professional",
            "subcategory":"Advertising",
            "type":"Services"
        }
    ],
    "sg:phone":"+1 281 837 6660",
    "sg:postcode":"77521",
    "sg:province":"TX",
    "sg:tags":[
        "agency"
    ],
    "wof:name":"Reeves Melina",
    "wof:placetype":"venue"
},
  "geometry": {"coordinates":[-94.984117,29.756028],"type":"Point"}
}