{
  "type": "Feature",
  "properties": {
    "iso:country":"US",
    "sg:address":"405 Gilmer Rd",
    "sg:city":"Longview",
    "sg:classifiers":[
        {
            "category":"Utilities",
            "subcategory":"Cable",
            "type":"Services"
        }
    ],
    "sg:phone":"+1 903 236 9929",
    "sg:postcode":"75604",
    "sg:province":"TX",
    "sg:tags":[
        "television"
    ],
    "wof:name":"Direct Cable Inc",
    "wof:placetype":"venue"
},
  "geometry": {"coordinates":[-94.768799,32.510204],"type":"Point"}
}