{
  "type": "Feature",
  "properties": {
    "iso:country":"US",
    "sg:address":"117 E Railroad Ave",
    "sg:city":"Shamrock",
    "sg:classifiers":[
        {
            "category":"Wholesale",
            "subcategory":"Medical Equipment & Supplies",
            "type":"Manufacturing & Wholesale Goods"
        }
    ],
    "sg:phone":"+1 806 256 1004",
    "sg:postcode":"79079",
    "sg:province":"TX",
    "wof:name":"Home Med Str & Shamrock Oxgn",
    "wof:placetype":"venue"
},
  "geometry": {"coordinates":[-100.24895600000001,35.214182],"type":"Point"}
}