{
  "type": "Feature",
  "properties": {
    "iso:country":"US",
    "sg:address":"15909 Milo Rd",
    "sg:city":"Austin",
    "sg:classifiers":[
        {
            "category":"Wholesale",
            "subcategory":"Computers",
            "type":"Manufacturing & Wholesale Goods"
        }
    ],
    "sg:phone":"+1 512 659 8127",
    "sg:postcode":"78725",
    "sg:province":"TX",
    "sg:tags":[
        "computer-wholesale",
        "manufacturer"
    ],
    "wof:name":"Patricia Olvera Ibm",
    "wof:placetype":"venue"
},
  "geometry": {"coordinates":[-97.566852,30.227825],"type":"Point"}
}