{
  "type": "Feature",
  "properties": {
    "iso:country":"US",
    "sg:address":"1562 Norman St",
    "sg:city":"Wichita Falls",
    "sg:classifiers":[
        {
            "category":"Education",
            "subcategory":"School",
            "type":"Public Place"
        }
    ],
    "sg:phone":"+1 940 720 3157",
    "sg:postcode":"76302",
    "sg:province":"TX",
    "wof:name":"Fain Elementary School",
    "wof:placetype":"venue"
},
  "geometry": {"coordinates":[-98.50088,33.862607],"type":"Point"}
}