{
  "type": "Feature",
  "properties": {
    "iso:country":"US",
    "sg:address":"2011 W Spring Creek Pkwy",
    "sg:city":"Plano",
    "sg:classifiers":[
        {
            "category":"Food & Beverages",
            "subcategory":"Liquor & Beverages",
            "type":"Retail Goods"
        }
    ],
    "sg:phone":"+1 972 517 1812",
    "sg:postcode":"75023",
    "sg:province":"TX",
    "sg:tags":[
        "store"
    ],
    "wof:name":"Five Star Beer and Wine",
    "wof:placetype":"venue"
},
  "geometry": {"coordinates":[-96.73141099999999,33.058912],"type":"Point"}
}