{
  "type": "Feature",
  "properties": {
    "iso:country":"US",
    "sg:address":"5309 Spanky Ln",
    "sg:city":"Amarillo",
    "sg:classifiers":[
        {
            "category":"Building & Trades",
            "subcategory":"Cleaning & Sanitation",
            "type":"Services"
        }
    ],
    "sg:phone":"+1 806 457 9975",
    "sg:postcode":"79110",
    "sg:province":"TX",
    "sg:tags":[
        "maintenance"
    ],
    "wof:name":"Angel Janitorial Service",
    "wof:placetype":"venue"
},
  "geometry": {"coordinates":[-101.850403,35.151375],"type":"Point"}
}