{
  "type": "Feature",
  "properties": {
    "iso:country":"US",
    "sg:address":"22023 Brierwood Dr",
    "sg:city":"Frankston",
    "sg:classifiers":[
        {
            "category":"Transit Center",
            "subcategory":"Freight",
            "type":"Transportation"
        },
        {
            "category":"Freight",
            "type":"Transportation"
        }
    ],
    "sg:phone":"+1 903 876 3330",
    "sg:postcode":"75763",
    "sg:province":"TX",
    "sg:tags":[
        "trucking-motor",
        "trucking"
    ],
    "wof:name":"Landstar",
    "wof:placetype":"venue"
},
  "geometry": {"coordinates":[-95.489176,32.145784],"type":"Point"}
}