{
  "type": "Feature",
  "properties": {
    "iso:country":"US",
    "sg:address":"406 Shirley St",
    "sg:city":"Marshall",
    "sg:classifiers":[
        {
            "category":"Organizations",
            "subcategory":"Religious Organization",
            "type":"Services"
        }
    ],
    "sg:phone":"+1 903 938 9344",
    "sg:postcode":"75670",
    "sg:province":"TX",
    "sg:tags":[
        "church"
    ],
    "wof:name":"Church Of Marshall",
    "wof:placetype":"venue"
},
  "geometry": {"coordinates":[-94.364384,32.535835],"type":"Point"}
}