{
  "type": "Feature",
  "properties": {
    "iso:country":"US",
    "sg:address":"7029 Michael Dr",
    "sg:city":"N Richland Hills",
    "sg:classifiers":[
        {
            "category":"Banks & Credit Unions",
            "subcategory":"Investment Brokerage",
            "type":"Services"
        }
    ],
    "sg:phone":"+1 817 399 8889",
    "sg:postcode":"76180",
    "sg:province":"TX",
    "sg:tags":[
        "security"
    ],
    "wof:name":"Edward Jones Co",
    "wof:placetype":"venue"
},
  "geometry": {"coordinates":[-97.19806800000001,32.874964],"type":"Point"}
}