{
  "type": "Feature",
  "properties": {
    "iso:country":"US",
    "sg:address":"1840 Junction Hwy",
    "sg:city":"Kerrville",
    "sg:classifiers":[
        {
            "category":"Social Services",
            "subcategory":"Job Training",
            "type":"Services"
        }
    ],
    "sg:phone":"+1 830 895 3660",
    "sg:postcode":"78028",
    "sg:province":"TX",
    "sg:tags":[
        "career",
        "counseling",
        "vocational"
    ],
    "wof:name":"Christian Womens Job Corps",
    "wof:placetype":"venue"
},
  "geometry": {"coordinates":[-99.181861,30.067701],"type":"Point"}
}