{
  "type": "Feature",
  "properties": {
    "iso:country":"US",
    "sg:address":"7202 Spiller St",
    "sg:city":"Hitchcock",
    "sg:classifiers":[
        {
            "category":"Professional",
            "type":"Services"
        }
    ],
    "sg:phone":"+1 409 986 6097",
    "sg:postcode":"77563",
    "sg:province":"TX",
    "wof:name":"Peetenbrink Velva",
    "wof:placetype":"venue"
},
  "geometry": {"coordinates":[-95.00856400000001,29.343553],"type":"Point"}
}