{
  "type": "Feature",
  "properties": {
    "iso:country":"US",
    "sg:address":"6333 Airport Fwy",
    "sg:city":"Fort Worth",
    "sg:classifiers":[
        {
            "category":"Building & Trades",
            "subcategory":"Construction",
            "type":"Services"
        }
    ],
    "sg:phone":"+1 817 834 7777",
    "sg:postcode":"76117",
    "sg:province":"TX",
    "sg:tags":[
        "roofing",
        "contractor"
    ],
    "wof:name":"Ridge Roofing",
    "wof:placetype":"venue"
},
  "geometry": {"coordinates":[-97.247984,32.791598],"type":"Point"}
}