{
  "type": "Feature",
  "properties": {
    "iso:country":"US",
    "sg:address":"4020 Juneberry St",
    "sg:city":"Fort Worth",
    "sg:classifiers":[
        {
            "category":"Retail",
            "subcategory":"Portrait Studio",
            "type":"Services"
        }
    ],
    "sg:phone":"+1 817 368 8163",
    "sg:postcode":"76137",
    "sg:province":"TX",
    "sg:tags":[
        "photographer",
        "imaging"
    ],
    "wof:name":"Helen Bruns Photography",
    "wof:placetype":"venue"
},
  "geometry": {"coordinates":[-97.29364200000001,32.871107],"type":"Point"}
}