{
  "type": "Feature",
  "properties": {
    "iso:country":"US",
    "sg:address":"7010 N Dessert Rd",
    "sg:city":"El Paso",
    "sg:classifiers":[
        {
            "category":"Shopping Center",
            "type":"Public Place"
        }
    ],
    "sg:phone":"+1 915 877 3208",
    "sg:postcode":"79912",
    "sg:province":"TX",
    "sg:website":"www.theoutletshoppesatelpaso.com",
    "wof:name":"Outlet Shoppes at El Paso",
    "wof:placetype":"venue"
},
  "geometry": {"coordinates":[-106.582171,31.908789],"type":"Point"}
}