{
  "type": "Feature",
  "properties": {
    "iso:country":"US",
    "sg:address":"1114 Jefferson Ave",
    "sg:city":"Lufkin",
    "sg:classifiers":[
        {
            "category":"Building & Trades",
            "subcategory":"Equipment Rental",
            "type":"Services"
        }
    ],
    "sg:phone":"+1 936 674 5455",
    "sg:postcode":"75904",
    "sg:province":"TX",
    "wof:name":"Audio Works",
    "wof:placetype":"venue"
},
  "geometry": {"coordinates":[-94.748429,31.331813],"type":"Point"}
}