{
  "type": "Feature",
  "properties": {
    "iso:country":"US",
    "sg:address":"16014 Green Mountain Dr",
    "sg:city":"Houston",
    "sg:classifiers":[
        {
            "category":"Retail",
            "subcategory":"Repair Shop",
            "type":"Services"
        }
    ],
    "sg:phone":"+1 281 209 2686",
    "sg:postcode":"77032",
    "sg:province":"TX",
    "sg:tags":[
        "compressor",
        "sales",
        "air"
    ],
    "wof:name":"MANN ART",
    "wof:placetype":"venue"
},
  "geometry": {"coordinates":[-95.354816,29.9526],"type":"Point"}
}