{
  "type": "Feature",
  "properties": {
    "iso:country":"US",
    "sg:address":"900 Preston Rd",
    "sg:city":"Buchanan Dam",
    "sg:classifiers":[
        {
            "category":"Communications",
            "subcategory":"Film & Video Production",
            "type":"Services"
        }
    ],
    "sg:phone":"+1 512 793 5464",
    "sg:postcode":"78609",
    "sg:province":"TX",
    "sg:tags":[
        "motion"
    ],
    "wof:name":"Jkc Productions",
    "wof:placetype":"venue"
},
  "geometry": {"coordinates":[-98.46306199999999,30.745141],"type":"Point"}
}