{
  "type": "Feature",
  "properties": {
    "iso:country":"US",
    "sg:address":"1108 Walnut St",
    "sg:city":"Bastrop",
    "sg:classifiers":[
        {
            "category":"Organizations",
            "subcategory":"Religious Organization",
            "type":"Services"
        }
    ],
    "sg:phone":"+1 512 303 9033",
    "sg:postcode":"78602",
    "sg:province":"TX",
    "sg:tags":[
        "church"
    ],
    "wof:name":"Paul Quinn AME Church",
    "wof:placetype":"venue"
},
  "geometry": {"coordinates":[-97.314913,30.108537],"type":"Point"}
}