{
  "type": "Feature",
  "properties": {
    "iso:country":"US",
    "sg:address":"2910 Beverly Rd",
    "sg:city":"Pasadena",
    "sg:classifiers":[
        {
            "category":"Building & Trades",
            "subcategory":"Construction",
            "type":"Services"
        }
    ],
    "sg:phone":"+1 281 998 1828",
    "sg:postcode":"77503",
    "sg:province":"TX",
    "sg:tags":[
        "hanging",
        "contractor"
    ],
    "wof:name":"Lopez Paint Contractor",
    "wof:placetype":"venue"
},
  "geometry": {"coordinates":[-95.147702,29.669833],"type":"Point"}
}