{
  "type": "Feature",
  "properties": {
    "iso:country":"US",
    "sg:address":"922 Tassell St",
    "sg:city":"Houston",
    "sg:classifiers":[
        {
            "category":"Manufacturing",
            "subcategory":"Tools & Machinery",
            "type":"Manufacturing & Wholesale Goods"
        }
    ],
    "sg:phone":"+1 713 695 1812",
    "sg:postcode":"77076",
    "sg:province":"TX",
    "sg:tags":[
        "machine",
        "shop"
    ],
    "wof:name":"C & G Machine Works Inc",
    "wof:placetype":"venue"
},
  "geometry": {"coordinates":[-95.386019,29.846257],"type":"Point"}
}