{
  "type": "Feature",
  "properties": {
    "iso:country":"US",
    "sg:address":"811 Main St",
    "sg:city":"Alamo",
    "sg:classifiers":[
        {
            "category":"Cinema",
            "subcategory":"Movie Rental",
            "type":"Entertainment"
        }
    ],
    "sg:phone":"+1 956 783 1601",
    "sg:postcode":"78516",
    "sg:province":"TX",
    "sg:tags":[
        "leasing",
        "video",
        "disc",
        "tape"
    ],
    "wof:name":"Super Video",
    "wof:placetype":"venue"
},
  "geometry": {"coordinates":[-98.11919899999999,26.18246],"type":"Point"}
}