{
  "type": "Feature",
  "properties": {
    "iso:country":"US",
    "sg:address":"1305 Monterrey Blvd",
    "sg:city":"Euless",
    "sg:classifiers":[
        {
            "category":"Social Services",
            "subcategory":"Child Care",
            "type":"Services"
        }
    ],
    "sg:phone":"+1 817 283 4631",
    "sg:postcode":"76040",
    "sg:province":"TX",
    "wof:name":"Delores Churuba",
    "wof:placetype":"venue"
},
  "geometry": {"coordinates":[-97.141384,32.821105],"type":"Point"}
}