{
  "type": "Feature",
  "properties": {
    "iso:country":"US",
    "sg:address":"813 Moonlight Bay Dr",
    "sg:city":"Spicewood",
    "sg:classifiers":[
        {
            "category":"Professional",
            "subcategory":"Business Services",
            "type":"Services"
        }
    ],
    "sg:phone":"+1 512 264 2096",
    "sg:postcode":"78669",
    "sg:province":"TX",
    "wof:name":"William F Fox",
    "wof:placetype":"venue"
},
  "geometry": {"coordinates":[-98.00813599999999,30.401682],"type":"Point"}
}