{
  "type": "Feature",
  "properties": {
    "iso:country":"US",
    "sg:address":"1368 Lakeview Dr",
    "sg:city":"Southlake",
    "sg:classifiers":[
        {
            "category":"Building & Trades",
            "subcategory":"Construction",
            "type":"Services"
        }
    ],
    "sg:phone":"+1 817 577 1383",
    "sg:postcode":"76092",
    "sg:province":"TX",
    "sg:tags":[
        "general",
        "contractor"
    ],
    "wof:name":"Steve Sherrill Inc",
    "wof:placetype":"venue"
},
  "geometry": {"coordinates":[-97.180808,32.954018],"type":"Point"}
}