{
  "type": "Feature",
  "properties": {
    "iso:country":"US",
    "sg:address":"11242 Bluebird Ln",
    "sg:city":"Bellville",
    "sg:classifiers":[
        {
            "category":"Manufacturing",
            "subcategory":"Aerospace",
            "type":"Manufacturing & Wholesale Goods"
        }
    ],
    "sg:phone":"+1 979 865 2036",
    "sg:postcode":"77418",
    "sg:province":"TX",
    "sg:tags":[
        "aircraft",
        "mfg"
    ],
    "wof:name":"Pnk Aircraft Contr",
    "wof:placetype":"venue"
},
  "geometry": {"coordinates":[-96.16052999999999,30.035349],"type":"Point"}
}