{
  "type": "Feature",
  "properties": {
    "iso:country":"US",
    "sg:address":"309 W Cedar St",
    "sg:city":"Seguin",
    "sg:classifiers":[
        {
            "category":"Manufacturing",
            "subcategory":"Printing",
            "type":"Manufacturing & Wholesale Goods"
        }
    ],
    "sg:phone":"+1 830 372 9895",
    "sg:postcode":"78155",
    "sg:province":"TX",
    "sg:tags":[
        "newspaper"
    ],
    "wof:name":"San Antonio Express News",
    "wof:placetype":"venue"
},
  "geometry": {"coordinates":[-97.966176,29.578595],"type":"Point"}
}