{
  "type": "Feature",
  "properties": {
    "iso:country":"US",
    "sg:address":"5800 N Mo Pac Expy",
    "sg:city":"Austin",
    "sg:classifiers":[
        {
            "category":"Insurance",
            "subcategory":"Insurance Agent",
            "type":"Services"
        }
    ],
    "sg:phone":"+1 512 421 5705",
    "sg:postcode":"78731",
    "sg:province":"TX",
    "wof:name":"Compass Insurance Inc",
    "wof:placetype":"venue"
},
  "geometry": {"coordinates":[-97.756013,30.336812],"type":"Point"}
}