{
  "type": "Feature",
  "properties": {
    "iso:country":"US",
    "sg:address":"4501 Spicewood Springs Rd",
    "sg:city":"Austin",
    "sg:classifiers":[
        {
            "category":"Health Services",
            "subcategory":"Clinic",
            "type":"Services"
        },
        {
            "category":"Health Services",
            "subcategory":"Doctor",
            "type":"Services"
        }
    ],
    "sg:phone":"+1 512 477 0500",
    "sg:postcode":"78759",
    "sg:province":"TX",
    "sg:tags":[
        "physician",
        "surgeon"
    ],
    "wof:name":"Lonestar Sleep Diagnostics",
    "wof:placetype":"venue"
},
  "geometry": {"coordinates":[-97.758752,30.373265],"type":"Point"}
}