{
  "type": "Feature",
  "properties": {
    "iso:country":"US",
    "sg:address":"422 W Nasa Rd 1",
    "sg:city":"Webster",
    "sg:classifiers":[
        {
            "category":"Wholesale",
            "subcategory":"Non-durable Goods",
            "type":"Manufacturing & Wholesale Goods"
        }
    ],
    "sg:phone":"+1 281 338 1327",
    "sg:postcode":"77598",
    "sg:province":"TX",
    "wof:name":"F&M Import Inc",
    "wof:placetype":"venue"
},
  "geometry": {"coordinates":[-95.121915,29.535009],"type":"Point"}
}