{
  "type": "Feature",
  "properties": {
    "iso:country":"US",
    "sg:address":"4424 Walzem Rd",
    "sg:city":"San Antonio",
    "sg:classifiers":[
        {
            "category":"Retail",
            "subcategory":"Auto Repair",
            "type":"Services"
        }
    ],
    "sg:phone":"+1 210 657 4466",
    "sg:postcode":"78218",
    "sg:province":"TX",
    "sg:tags":[
        "automotive",
        "merchandise"
    ],
    "wof:name":"Double Team",
    "wof:placetype":"venue"
},
  "geometry": {"coordinates":[-98.404642,29.510236],"type":"Point"}
}