{
  "type": "Feature",
  "properties": {
    "iso:country":"US",
    "sg:address":"832 Yellowstone Dr",
    "sg:city":"Grapevine",
    "sg:classifiers":[
        {
            "category":"Retail",
            "subcategory":"Portrait Studio",
            "type":"Services"
        }
    ],
    "sg:phone":"+1 817 421 6244",
    "sg:postcode":"76051",
    "sg:province":"TX",
    "sg:tags":[
        "photo"
    ],
    "wof:name":"Robin Cunningham Photography",
    "wof:placetype":"venue"
},
  "geometry": {"coordinates":[-97.09636399999999,32.948234],"type":"Point"}
}