{
  "type": "Feature",
  "properties": {
    "iso:country":"US",
    "sg:address":"4030 Wesley St",
    "sg:city":"Greenville",
    "sg:classifiers":[
        {
            "category":"Real Estate",
            "subcategory":"Surveying",
            "type":"Services"
        }
    ],
    "sg:phone":"+1 903 450 9837",
    "sg:postcode":"75401",
    "sg:province":"TX",
    "sg:tags":[
        "surveyor"
    ],
    "wof:name":"Owens Land Survey",
    "wof:placetype":"venue"
},
  "geometry": {"coordinates":[-96.10921399999999,33.128911],"type":"Point"}
}