{
  "type": "Feature",
  "properties": {
    "iso:country":"US",
    "sg:address":"1903 Joe Stephens Ave",
    "sg:city":"Weslaco",
    "sg:classifiers":[
        {
            "category":"Building & Trades",
            "subcategory":"Pest Control",
            "type":"Services"
        }
    ],
    "sg:phone":"+1 956 423 2573",
    "sg:postcode":"78596",
    "sg:province":"TX",
    "sg:tags":[
        "industrial",
        "services-commercial"
    ],
    "sg:website":"http://www.terminix.com",
    "wof:name":"Terminix",
    "wof:placetype":"venue"
},
  "geometry": {"coordinates":[-97.9683,26.176045],"type":"Point"}
}