{
  "type": "Feature",
  "properties": {
    "iso:country":"US",
    "sg:address":"6301 Manchaca Rd Suite E",
    "sg:city":"Austin",
    "sg:classifiers":[
        {
            "category":"Education",
            "subcategory":"Music School",
            "type":"Public Place"
        },
        {
            "category":"Personal",
            "type":"Services"
        }
    ],
    "sg:phone":"+1 512 228 4074",
    "sg:postcode":"78745",
    "sg:province":"TX",
    "sg:tags":[
        "instrument",
        "local",
        "musical",
        "teacher"
    ],
    "sg:website":"guitaraustin.tripod.com/",
    "wof:name":"Austin Instrument Repair",
    "wof:placetype":"venue"
},
  "geometry": {"coordinates":[-97.804035,30.209055],"type":"Point"}
}