{
  "type": "Feature",
  "properties": {
    "iso:country":"US",
    "sg:address":"602 Sawyer St",
    "sg:city":"Houston",
    "sg:classifiers":[
        {
            "category":"Professional",
            "subcategory":"Lawyer & Legal Services",
            "type":"Services"
        }
    ],
    "sg:phone":"+1 713 868 5995",
    "sg:postcode":"77007",
    "sg:province":"TX",
    "wof:name":"Gene Jones",
    "wof:placetype":"venue"
},
  "geometry": {"coordinates":[-95.381275,29.765522],"type":"Point"}
}