{
  "type": "Feature",
  "properties": {
    "iso:country":"US",
    "sg:address":"200 Stonegate Ln",
    "sg:city":"Sunnyvale",
    "sg:classifiers":[
        {
            "category":"Arts & Performance",
            "subcategory":"Art Gallery",
            "type":"Entertainment"
        }
    ],
    "sg:phone":"+1 972 226 7200",
    "sg:postcode":"75182",
    "sg:province":"TX",
    "sg:tags":[
        "craft"
    ],
    "wof:name":"Gracy's Treasures",
    "wof:placetype":"venue"
},
  "geometry": {"coordinates":[-96.587227,32.806961],"type":"Point"}
}