{
  "type": "Feature",
  "properties": {
    "iso:country":"US",
    "sg:address":"614 E Ferguson Ave",
    "sg:city":"Pharr",
    "sg:classifiers":[
        {
            "category":"Wholesale",
            "subcategory":"Toys & Hobbies",
            "type":"Manufacturing & Wholesale Goods"
        }
    ],
    "sg:phone":"+1 956 702 2960",
    "sg:postcode":"78577",
    "sg:province":"TX",
    "sg:tags":[
        "wholesaler"
    ],
    "wof:name":"B & B Wholesalers",
    "wof:placetype":"venue"
},
  "geometry": {"coordinates":[-98.173458,26.210564],"type":"Point"}
}