{
  "type": "Feature",
  "properties": {
    "iso:country":"US",
    "sg:address":"110 Cambridge Dr",
    "sg:city":"Cedar Hill",
    "sg:classifiers":[
        {
            "category":"Retail",
            "subcategory":"Animal Services",
            "type":"Services"
        }
    ],
    "sg:phone":"+1 972 293 3223",
    "sg:postcode":"75104",
    "sg:province":"TX",
    "wof:name":"D & B Reptiles Inc",
    "wof:placetype":"venue"
},
  "geometry": {"coordinates":[-96.946564,32.583167],"type":"Point"}
}