{
  "type": "Feature",
  "properties": {
    "iso:country":"US",
    "sg:address":"53 Lake Rd",
    "sg:city":"Lake Jackson",
    "sg:classifiers":[
        {
            "category":"Education",
            "subcategory":"Special Training",
            "type":"Public Place"
        }
    ],
    "sg:phone":"+1 979 297 6379",
    "sg:postcode":"77566",
    "sg:province":"TX",
    "wof:name":"The French",
    "wof:placetype":"venue"
},
  "geometry": {"coordinates":[-95.465329,29.053234],"type":"Point"}
}