{
  "type": "Feature",
  "properties": {
    "iso:country":"US",
    "sg:address":"13621 Inwood Rd Ste 420",
    "sg:city":"Dallas",
    "sg:classifiers":[
        {
            "category":"Shopping",
            "subcategory":"Pharmacy",
            "type":"Retail Goods"
        }
    ],
    "sg:phone":"+1 214 866 2700",
    "sg:postcode":"75244",
    "sg:province":"TX",
    "sg:tags":[
        "drugstore"
    ],
    "wof:name":"Park Infusion Services",
    "wof:placetype":"venue"
},
  "geometry": {"coordinates":[-96.823196,32.9333],"type":"Point"}
}