{
  "type": "Feature",
  "properties": {
    "iso:country":"US",
    "sg:address":"255 Rio West Dr",
    "sg:city":"El Paso",
    "sg:classifiers":[
        {
            "category":"Building & Trades",
            "subcategory":"Construction",
            "type":"Services"
        }
    ],
    "sg:phone":"+1 915 833 7699",
    "sg:postcode":"79932",
    "sg:province":"TX",
    "sg:tags":[
        "roofing",
        "asphalt",
        "contractor"
    ],
    "wof:name":"Asphalt & Roofing Consultants",
    "wof:placetype":"venue"
},
  "geometry": {"coordinates":[-106.597334,31.880296],"type":"Point"}
}