{
  "type": "Feature",
  "properties": {
    "iso:country":"US",
    "sg:address":"9850 N Central Expy",
    "sg:city":"Dallas",
    "sg:classifiers":[
        {
            "category":"Professional",
            "type":"Services"
        }
    ],
    "sg:phone":"+1 214 361 9474",
    "sg:postcode":"75231",
    "sg:province":"TX",
    "wof:name":"Marbur Development",
    "wof:placetype":"venue"
},
  "geometry": {"coordinates":[-96.769617,32.883273],"type":"Point"}
}