{
  "type": "Feature",
  "properties": {
    "iso:country":"US",
    "sg:address":"1211 W 6th Street",
    "sg:city":"Austin",
    "sg:classifiers":[
        {
            "category":"Autos & Motor Vehicles",
            "subcategory":"Motorcycle Sales",
            "type":"Retail Goods"
        }
    ],
    "sg:phone":"+1 512 236 1113",
    "sg:postcode":"78703",
    "sg:province":"TX",
    "wof:name":"Texas E Rider Lp",
    "wof:placetype":"venue"
},
  "geometry": {"coordinates":[-97.75857000000001,30.273273],"type":"Point"}
}