{
  "type": "Feature",
  "properties": {
    "iso:country":"US",
    "sg:address":"99 One Sugar Creek Pl",
    "sg:city":"Sugar Land",
    "sg:classifiers":[
        {
            "category":"Restaurant",
            "type":"Food & Drink"
        }
    ],
    "sg:menulink":"http://www.allmenus.com/tx/sugar-land/43048-perrys-steakhouse--grille/menu/",
    "sg:phone":"+1 281 565 2727",
    "sg:postcode":"77478",
    "sg:province":"TX",
    "sg:tags":[
        "american",
        "steakhouse"
    ],
    "wof:name":"Perry's Steakhouse & Grille",
    "wof:placetype":"venue"
},
  "geometry": {"coordinates":[-95.60504400000001,29.614554],"type":"Point"}
}