{
  "type": "Feature",
  "properties": {
    "iso:country":"US",
    "sg:address":"2512 Mesa Rd",
    "sg:city":"Lubbock",
    "sg:phone":"+1 806 763 7245",
    "sg:postcode":"79403",
    "sg:province":"TX",
    "sg:tags":[
        "farm",
        "cotton"
    ],
    "wof:name":"Kristinek Inc",
    "wof:placetype":"venue"
},
  "geometry": {"coordinates":[-101.84243600000001,33.628112],"type":"Point"}
}