{
  "type": "Feature",
  "properties": {
    "iso:country":"US",
    "sg:address":"18035 W Little York Rd",
    "sg:city":"Katy",
    "sg:classifiers":[
        {
            "category":"Manufacturing",
            "subcategory":"Pet Food",
            "type":"Manufacturing & Wholesale Goods"
        }
    ],
    "sg:phone":"+1 281 463 1011",
    "sg:postcode":"77449",
    "sg:province":"TX",
    "sg:tags":[
        "feed",
        "mfg",
        "prepared"
    ],
    "wof:name":"P & V Distributors",
    "wof:placetype":"venue"
},
  "geometry": {"coordinates":[-95.68376600000001,29.865282],"type":"Point"}
}