{
  "type": "Feature",
  "properties": {
    "iso:country":"US",
    "sg:address":"7021 Creek Bend Rd",
    "sg:city":"Dallas",
    "sg:classifiers":[
        {
            "category":"Cinema",
            "subcategory":"Movie Rental",
            "type":"Entertainment"
        }
    ],
    "sg:phone":"+1 972 380 0220",
    "sg:postcode":"75252",
    "sg:province":"TX",
    "sg:tags":[
        "video",
        "tape"
    ],
    "wof:name":"Jean Marie Video",
    "wof:placetype":"venue"
},
  "geometry": {"coordinates":[-96.79126100000001,32.997757],"type":"Point"}
}