{
  "type": "Feature",
  "properties": {
    "iso:country":"US",
    "sg:address":"16915 Cobbler Crossing Dr",
    "sg:city":"Sugar Land",
    "sg:classifiers":[
        {
            "category":"Insurance",
            "subcategory":"Life Insurance",
            "type":"Services"
        }
    ],
    "sg:phone":"+1 281 879 5824",
    "sg:postcode":"77478",
    "sg:province":"TX",
    "sg:tags":[
        "carrier"
    ],
    "wof:name":"Spees & Associates",
    "wof:placetype":"venue"
},
  "geometry": {"coordinates":[-95.66132,29.648622],"type":"Point"}
}