{
  "type": "Feature",
  "properties": {
    "iso:country":"US",
    "sg:address":"2831 NE Stallings Dr C",
    "sg:city":"Nacogdoches",
    "sg:classifiers":[
        {
            "category":"Autos & Motor Vehicles",
            "subcategory":"Automobile Sales",
            "type":"Retail Goods"
        }
    ],
    "sg:phone":"+1 936 569 0398",
    "sg:postcode":"75965",
    "sg:province":"TX",
    "sg:tags":[
        "distributor",
        "manufacturer"
    ],
    "wof:name":"East Texas Race Car Co",
    "wof:placetype":"venue"
},
  "geometry": {"coordinates":[-94.614665,31.635375],"type":"Point"}
}