{
  "type": "Feature",
  "properties": {
    "iso:country":"US",
    "sg:address":"1801 S 2nd St",
    "sg:city":"Mcallen",
    "sg:classifiers":[
        {
            "category":"Professional",
            "subcategory":"Accounting & Tax Preparation",
            "type":"Services"
        }
    ],
    "sg:phone":"+1 956 630 5888",
    "sg:postcode":"78503",
    "sg:province":"TX",
    "sg:tags":[
        "bookkeeping",
        "billing"
    ],
    "wof:name":"Affordable Billing Consultants",
    "wof:placetype":"venue"
},
  "geometry": {"coordinates":[-98.224256,26.185139],"type":"Point"}
}