{
  "type": "Feature",
  "properties": {
    "iso:country":"US",
    "sg:address":"11824 Jollyville Rd",
    "sg:city":"Austin",
    "sg:classifiers":[
        {
            "category":"Professional",
            "subcategory":"Computer Services",
            "type":"Services"
        },
        {
            "category":"Shopping",
            "subcategory":"Computers & Home Electronics",
            "type":"Retail Goods"
        }
    ],
    "sg:phone":"+1 512 444 2800",
    "sg:postcode":"78759",
    "sg:province":"TX",
    "sg:tags":[
        "prepackaged",
        "software"
    ],
    "wof:name":"13 Colonies Software",
    "wof:placetype":"venue"
},
  "geometry": {"coordinates":[-97.756877,30.424056],"type":"Point"}
}