{
  "type": "Feature",
  "properties": {
    "iso:country":"US",
    "sg:address":"6000 S Staples St",
    "sg:city":"Corpus Christi",
    "sg:classifiers":[
        {
            "category":"Professional",
            "subcategory":"Business Services",
            "type":"Services"
        }
    ],
    "sg:phone":"+1 361 991 1170",
    "sg:postcode":"78413",
    "sg:province":"TX",
    "sg:tags":[
        "communications",
        "consulting"
    ],
    "wof:name":"Omni Digital Systems Inc",
    "wof:placetype":"venue"
},
  "geometry": {"coordinates":[-97.377988,27.694922],"type":"Point"}
}