{
  "type": "Feature",
  "properties": {
    "iso:country":"US",
    "sg:address":"202 Lena Dr",
    "sg:city":"Houston",
    "sg:classifiers":[
        {
            "category":"Building & Trades",
            "subcategory":"Plumbing",
            "type":"Services"
        }
    ],
    "sg:phone":"+1 713 694 5956",
    "sg:postcode":"77022",
    "sg:province":"TX",
    "sg:tags":[
        "sheet",
        "work",
        "metal",
        "contractor"
    ],
    "wof:name":"Marches Enterprises",
    "wof:placetype":"venue"
},
  "geometry": {"coordinates":[-95.39803499999999,29.834476],"type":"Point"}
}