{
  "type": "Feature",
  "properties": {
    "iso:country":"US",
    "sg:address":"2859 60th St",
    "sg:city":"Port Arthur",
    "sg:classifiers":[
        {
            "category":"Freight",
            "type":"Transportation"
        }
    ],
    "sg:phone":"+1 409 736 1408",
    "sg:postcode":"77640",
    "sg:province":"TX",
    "sg:tags":[
        "operator",
        "local",
        "trucking"
    ],
    "wof:name":"Johnson Truck Service",
    "wof:placetype":"venue"
},
  "geometry": {"coordinates":[-94.032617,29.896435],"type":"Point"}
}