{
  "type": "Feature",
  "properties": {
    "iso:country":"US",
    "sg:address":"14785 Preston Rd",
    "sg:city":"Dallas",
    "sg:classifiers":[
        {
            "category":"Real Estate",
            "subcategory":"Real Estate Agent",
            "type":"Services"
        }
    ],
    "sg:phone":"+1 972 789 5100",
    "sg:postcode":"75254",
    "sg:province":"TX",
    "sg:tags":[
        "desk",
        "space"
    ],
    "wof:name":"Ceo",
    "wof:placetype":"venue"
},
  "geometry": {"coordinates":[-96.803715,32.948325],"type":"Point"}
}