{
  "type": "Feature",
  "properties": {
    "iso:country":"US",
    "sg:address":"5615 Richmond Ave Suite 163",
    "sg:city":"Houston",
    "sg:classifiers":[
        {
            "category":"Personal",
            "type":"Services"
        }
    ],
    "sg:phone":"+1 713 787 9303",
    "sg:postcode":"77057",
    "sg:province":"TX",
    "sg:tags":[
        "sewing",
        "alteration"
    ],
    "wof:name":"R &G Alterations",
    "wof:placetype":"venue"
},
  "geometry": {"coordinates":[-95.47734,29.730843],"type":"Point"}
}