{
  "type": "Feature",
  "properties": {
    "iso:country":"US",
    "sg:address":"589 W Donovan St",
    "sg:city":"Houston",
    "sg:classifiers":[
        {
            "category":"Professional",
            "subcategory":"Business Services",
            "type":"Services"
        }
    ],
    "sg:phone":"+1 713 691 6699",
    "sg:postcode":"77091",
    "sg:province":"TX",
    "wof:name":"Kairos Life Technologies",
    "wof:placetype":"venue"
},
  "geometry": {"coordinates":[-95.410629,29.844064],"type":"Point"}
}