{
  "type": "Feature",
  "properties": {
    "iso:country":"US",
    "sg:address":"543 N Americas Ave",
    "sg:city":"El Paso",
    "sg:classifiers":[
        {
            "category":"Wholesale",
            "subcategory":"Durable Goods & Equipment",
            "type":"Manufacturing & Wholesale Goods"
        }
    ],
    "sg:phone":"+1 915 859 6198",
    "sg:postcode":"79907",
    "sg:province":"TX",
    "sg:tags":[
        "representative",
        "manufacturer"
    ],
    "wof:name":"Springs Industry Inc",
    "wof:placetype":"venue"
},
  "geometry": {"coordinates":[-106.303207,31.684972],"type":"Point"}
}