{
  "type": "Feature",
  "properties": {
    "iso:country":"US",
    "sg:address":"221 W Rhapsody Dr",
    "sg:city":"San Antonio",
    "sg:classifiers":[
        {
            "category":"Professional",
            "subcategory":"Business Services",
            "type":"Services"
        }
    ],
    "sg:phone":"+1 210 308 0675",
    "sg:postcode":"78216",
    "sg:province":"TX",
    "wof:name":"Food Safety Net Service Ltd",
    "wof:placetype":"venue"
},
  "geometry": {"coordinates":[-98.4965,29.545091],"type":"Point"}
}