{
  "type": "Feature",
  "properties": {
    "iso:country":"US",
    "sg:address":"2123 el Dorado Blvd",
    "sg:city":"Friendswood",
    "sg:classifiers":[
        {
            "category":"Shopping",
            "subcategory":"Clothing, Apparel, & Fashions",
            "type":"Retail Goods"
        }
    ],
    "sg:phone":"+1 281 992 3100",
    "sg:postcode":"77546",
    "sg:province":"TX",
    "wof:name":"Sam's Clothiers",
    "wof:placetype":"venue"
},
  "geometry": {"coordinates":[-95.165668,29.541366],"type":"Point"}
}