{
  "type": "Feature",
  "properties": {
    "iso:country":"US",
    "sg:address":"100 W Southlake Blvd",
    "sg:city":"Southlake",
    "sg:classifiers":[
        {
            "category":"Personal",
            "subcategory":"Tanning Parlor",
            "type":"Services"
        },
        {
            "category":"Personal",
            "type":"Services"
        }
    ],
    "sg:phone":"+1 817 329 4430",
    "sg:postcode":"76092",
    "sg:province":"TX",
    "sg:tags":[
        "salon"
    ],
    "wof:name":"Platinum Tan LLC",
    "wof:placetype":"venue"
},
  "geometry": {"coordinates":[-97.15101799999999,32.94153],"type":"Point"}
}