{
  "type": "Feature",
  "properties": {
    "iso:country":"US",
    "sg:address":"2995 Lyndon B Johnson Fwy",
    "sg:city":"Farmers Branch",
    "sg:classifiers":[
        {
            "category":"Banks & Credit Unions",
            "subcategory":"Investment Brokerage",
            "type":"Services"
        }
    ],
    "sg:phone":"+1 972 484 3352",
    "sg:postcode":"75234",
    "sg:province":"TX",
    "wof:name":"Paradigm Suites",
    "wof:placetype":"venue"
},
  "geometry": {"coordinates":[-96.881187,32.911309],"type":"Point"}
}