{
  "type": "Feature",
  "properties": {
    "iso:country":"US",
    "sg:address":"1710 Esperanza Ave",
    "sg:city":"Hidalgo",
    "sg:classifiers":[
        {
            "category":"Building & Trades",
            "subcategory":"Plumbing",
            "type":"Services"
        },
        {
            "category":"Building & Trades",
            "subcategory":"Cleaning & Sanitation",
            "type":"Services"
        },
        {
            "category":"Building & Trades",
            "subcategory":"Construction",
            "type":"Services"
        }
    ],
    "sg:phone":"+1 956 451 1954",
    "sg:postcode":"78557",
    "sg:province":"TX",
    "sg:tags":[
        "cleaner",
        "plumbing-drain",
        "tank",
        "radiators-heating",
        "septic",
        "supply",
        "repairer",
        "sales",
        "system",
        "sewer",
        "tanks-treatment"
    ],
    "wof:name":"American Rooter",
    "wof:placetype":"venue"
},
  "geometry": {"coordinates":[-98.243714,26.097186],"type":"Point"}
}