{
  "type": "Feature",
  "properties": {
    "iso:country":"US",
    "sg:address":"14 Crescent View Ct",
    "sg:city":"Spring",
    "sg:classifiers":[
        {
            "category":"Professional",
            "subcategory":"Business Services",
            "type":"Services"
        }
    ],
    "sg:phone":"+1 281 363 0490",
    "sg:postcode":"77381",
    "sg:province":"TX",
    "wof:name":"Lattice Communications In",
    "wof:placetype":"venue"
},
  "geometry": {"coordinates":[-95.492493,30.174728],"type":"Point"}
}