{
  "type": "Feature",
  "properties": {
    "iso:country":"US",
    "sg:address":"14433 Eichelberger Ave",
    "sg:city":"El Paso",
    "sg:classifiers":[
        {
            "category":"Building & Trades",
            "subcategory":"Construction",
            "type":"Services"
        }
    ],
    "sg:phone":"+1 915 383 0188",
    "sg:postcode":"79938",
    "sg:province":"TX",
    "sg:tags":[
        "house"
    ],
    "wof:name":"El Pueblito Estates Inc",
    "wof:placetype":"venue"
},
  "geometry": {"coordinates":[-106.179428,31.848017],"type":"Point"}
}