{
  "type": "Feature",
  "properties": {
    "iso:country":"US",
    "sg:address":"333 S Hackberry St",
    "sg:city":"San Antonio",
    "sg:classifiers":[
        {
            "category":"Manufacturing",
            "subcategory":"Printing",
            "type":"Manufacturing & Wholesale Goods"
        }
    ],
    "sg:phone":"+1 210 227 8300",
    "sg:postcode":"78203",
    "sg:province":"TX",
    "sg:tags":[
        "newspaper"
    ],
    "wof:name":"Informer Publishing",
    "wof:placetype":"venue"
},
  "geometry": {"coordinates":[-98.47333500000001,29.417255],"type":"Point"}
}