{
  "type": "Feature",
  "properties": {
    "iso:country":"US",
    "sg:address":"1369 Skyview Cir",
    "sg:city":"Hideaway",
    "sg:classifiers":[
        {
            "category":"Animal Shelter",
            "type":"Public Place"
        },
        {
            "category":"Retail",
            "subcategory":"Pet Boarding",
            "type":"Services"
        }
    ],
    "sg:phone":"+1 903 881 8848",
    "sg:postcode":"75771",
    "sg:province":"TX",
    "sg:tags":[
        "kennel"
    ],
    "wof:name":"Four Paws Kennel",
    "wof:placetype":"venue"
},
  "geometry": {"coordinates":[-95.466055,32.49178],"type":"Point"}
}