{
  "type": "Feature",
  "properties": {
    "iso:country":"US",
    "sg:address":"5114 Balcones Woods Dr. #307-336",
    "sg:city":"Austin",
    "sg:classifiers":[
        {
            "category":"Home & Garden",
            "subcategory":"Carpets & Floor Coverings",
            "type":"Retail Goods"
        }
    ],
    "sg:phone":"+1 512 335 8310",
    "sg:postcode":"78759",
    "sg:province":"TX",
    "sg:tags":[
        "flooring"
    ],
    "wof:name":"Floor Coverings International",
    "wof:placetype":"venue"
},
  "geometry": {"coordinates":[-97.74661399999999,30.407911],"type":"Point"}
}