{
  "type": "Feature",
  "properties": {
    "iso:country":"US",
    "sg:address":"300 Lake Brazos Pkwy",
    "sg:city":"Waco",
    "sg:classifiers":[
        {
            "category":"Recreation",
            "type":"Entertainment"
        }
    ],
    "sg:phone":"+1 254 750 5994",
    "sg:postcode":"76704",
    "sg:province":"TX",
    "sg:tags":[
        "center"
    ],
    "wof:name":"Bledsoe Miller Recreation Ctr",
    "wof:placetype":"venue"
},
  "geometry": {"coordinates":[-97.12226,31.561083],"type":"Point"}
}