{
  "type": "Feature",
  "properties": {
    "iso:country":"US",
    "sg:address":"220 W 8th St",
    "sg:city":"Georgetown",
    "sg:classifiers":[
        {
            "category":"Autos & Motor Vehicles",
            "subcategory":"Auto Supplies",
            "type":"Retail Goods"
        }
    ],
    "sg:phone":"+1 512 863 3200",
    "sg:postcode":"78626",
    "sg:province":"TX",
    "sg:tags":[
        "battery"
    ],
    "wof:name":"Hoyt's Auto Parts",
    "wof:placetype":"venue"
},
  "geometry": {"coordinates":[-97.678854,30.636491],"type":"Point"}
}