{
  "type": "Feature",
  "properties": {
    "iso:country":"US",
    "sg:address":"8212 S Presa St",
    "sg:city":"San Antonio",
    "sg:classifiers":[
        {
            "category":"Home & Garden",
            "subcategory":"Building Materials",
            "type":"Retail Goods"
        }
    ],
    "sg:phone":"+1 210 532 5556",
    "sg:postcode":"78223",
    "sg:province":"TX",
    "wof:name":"Mc Coys Building Supply Center",
    "wof:placetype":"venue"
},
  "geometry": {"coordinates":[-98.45542399999999,29.34032],"type":"Point"}
}