{
  "type": "Feature",
  "properties": {
    "iso:country":"US",
    "sg:address":"1010 Ave F",
    "sg:city":"Del Rio",
    "sg:classifiers":[
        {
            "category":"Personal",
            "subcategory":"Beauty Salon",
            "type":"Services"
        }
    ],
    "sg:phone":"+1 830 775 7448",
    "sg:postcode":"78840",
    "sg:province":"TX",
    "sg:tags":[
        "shop"
    ],
    "wof:name":"The Cutting Edge",
    "wof:placetype":"venue"
},
  "geometry": {"coordinates":[-100.90170999999999,29.373953],"type":"Point"}
}