{
  "type": "Feature",
  "properties": {
    "iso:country":"US",
    "sg:address":"2818 Hummingbird Ln",
    "sg:city":"Humble",
    "sg:classifiers":[
        {
            "category":"Professional",
            "subcategory":"Computer Services",
            "type":"Services"
        }
    ],
    "sg:phone":"+1 281 441 9200",
    "sg:postcode":"77396",
    "sg:province":"TX",
    "sg:tags":[
        "related"
    ],
    "wof:name":"DMaas Computer Consulting",
    "wof:placetype":"venue"
},
  "geometry": {"coordinates":[-95.275381,29.962006],"type":"Point"}
}