{
  "type": "Feature",
  "properties": {
    "iso:country":"US",
    "sg:address":"14770 Memorial Dr Ste 200",
    "sg:city":"Houston",
    "sg:classifiers":[
        {
            "category":"Professional",
            "subcategory":"Accounting & Tax Preparation",
            "type":"Services"
        }
    ],
    "sg:phone":"+1 281 493 5535",
    "sg:postcode":"77079",
    "sg:province":"TX",
    "sg:tags":[
        "bookkeeping",
        "billing"
    ],
    "sg:website":"http://www.medbillmanagement.com",
    "wof:name":"Summit Management",
    "wof:placetype":"venue"
},
  "geometry": {"coordinates":[-95.611581,29.771124],"type":"Point"}
}