{
  "type": "Feature",
  "properties": {
    "iso:country":"US",
    "sg:address":"3301 Crescent Ct",
    "sg:city":"Plano",
    "sg:classifiers":[
        {
            "category":"Retail",
            "subcategory":"Laundry & Dry Cleaning",
            "type":"Services"
        }
    ],
    "sg:phone":"+1 972 608 8842",
    "sg:postcode":"75093",
    "sg:province":"TX",
    "wof:name":"Color Your Carpet",
    "wof:placetype":"venue"
},
  "geometry": {"coordinates":[-96.83377400000001,33.045887],"type":"Point"}
}