{
  "type": "Feature",
  "properties": {
    "iso:country":"US",
    "sg:address":"4108 Aldama Dr",
    "sg:city":"Austin",
    "sg:classifiers":[
        {
            "category":"Professional",
            "subcategory":"Accounting & Tax Preparation",
            "type":"Services"
        }
    ],
    "sg:phone":"+1 512 282 5305",
    "sg:postcode":"78739",
    "sg:province":"TX",
    "wof:name":"April C Lund Dgn CPA",
    "wof:placetype":"venue"
},
  "geometry": {"coordinates":[-97.86830999999999,30.171037],"type":"Point"}
}