{
  "type": "Feature",
  "properties": {
    "iso:country":"US",
    "sg:address":"547 Fm 876",
    "sg:city":"Waxahachie",
    "sg:classifiers":[
        {
            "category":"Building & Trades",
            "subcategory":"Construction",
            "type":"Services"
        }
    ],
    "sg:phone":"+1 972 937 2220",
    "sg:postcode":"75167",
    "sg:province":"TX",
    "sg:tags":[
        "welder"
    ],
    "wof:name":"Randy Johnston Sales & Service",
    "wof:placetype":"venue"
},
  "geometry": {"coordinates":[-96.87089400000001,32.35085],"type":"Point"}
}