{
  "type": "Feature",
  "properties": {
    "iso:country":"US",
    "sg:address":"906 E Main St",
    "sg:city":"League City",
    "sg:classifiers":[
        {
            "category":"Shopping",
            "type":"Retail Goods"
        }
    ],
    "sg:phone":"+1 281 554 5955",
    "sg:postcode":"77573",
    "sg:province":"TX",
    "sg:tags":[
        "wedding",
        "supply"
    ],
    "wof:name":"Under The Oaks Wedding Info",
    "wof:placetype":"venue"
},
  "geometry": {"coordinates":[-95.08741000000001,29.513498],"type":"Point"}
}