{
  "type": "Feature",
  "properties": {
    "iso:country":"US",
    "sg:address":"551 Block Rd",
    "sg:city":"Gunter",
    "sg:classifiers":[
        {
            "category":"Retail",
            "subcategory":"Auto Repair",
            "type":"Services"
        }
    ],
    "sg:phone":"+1 903 433 1469",
    "sg:postcode":"75058",
    "sg:province":"TX",
    "sg:tags":[
        "truck"
    ],
    "wof:name":"JDM Svc",
    "wof:placetype":"venue"
},
  "geometry": {"coordinates":[-96.731847,33.426114],"type":"Point"}
}