{
  "type": "Feature",
  "properties": {
    "iso:country":"US",
    "sg:address":"1402 N Market Loop",
    "sg:city":"Baytown",
    "sg:classifiers":[
        {
            "category":"Professional",
            "type":"Services"
        },
        {
            "category":"Restaurant",
            "type":"Food & Drink"
        },
        {
            "category":"Food & Beverages",
            "subcategory":"Meat & Fish",
            "type":"Retail Goods"
        }
    ],
    "sg:phone":"+1 281 424 8612",
    "sg:postcode":"77521",
    "sg:province":"TX",
    "sg:tags":[
        "shop",
        "barbeque",
        "caterer"
    ],
    "wof:name":"Daniel's Meat Market",
    "wof:placetype":"venue"
},
  "geometry": {"coordinates":[-95.03600299999999,29.7869],"type":"Point"}
}