{
  "type": "Feature",
  "properties": {
    "iso:country":"US",
    "sg:address":"6998 Trowbridge Dr",
    "sg:city":"El Paso",
    "sg:classifiers":[
        {
            "category":"Freight",
            "type":"Transportation"
        }
    ],
    "sg:phone":"+1 915 920 7857",
    "sg:postcode":"79905",
    "sg:province":"TX",
    "sg:tags":[
        "general"
    ],
    "wof:name":"Trow-Delta",
    "wof:placetype":"venue"
},
  "geometry": {"coordinates":[-106.398422,31.767111],"type":"Point"}
}