{
  "type": "Feature",
  "properties": {
    "iso:country":"US",
    "sg:address":"2212 Sinclair Ave",
    "sg:city":"Midland",
    "sg:classifiers":[
        {
            "category":"Professional",
            "subcategory":"Business Services",
            "type":"Services"
        }
    ],
    "sg:phone":"+1 432 570 6780",
    "sg:postcode":"79705",
    "sg:province":"TX",
    "wof:name":"Newcomers Unlimited",
    "wof:placetype":"venue"
},
  "geometry": {"coordinates":[-102.104178,32.011432],"type":"Point"}
}