{
  "type": "Feature",
  "properties": {
    "iso:country":"US",
    "sg:address":"4447 N Central Expy 294",
    "sg:city":"Dallas",
    "sg:classifiers":[
        {
            "category":"Real Estate",
            "subcategory":"Real Estate Services",
            "type":"Services"
        },
        {
            "category":"Professional",
            "subcategory":"Lawyer & Legal Services",
            "type":"Services"
        }
    ],
    "sg:phone":"+1 214 714 0717",
    "sg:postcode":"75205",
    "sg:province":"TX",
    "wof:name":"J.R. Slider & Associates",
    "wof:placetype":"venue"
},
  "geometry": {"coordinates":[-96.787558,32.820386],"type":"Point"}
}