{
  "type": "Feature",
  "properties": {
    "iso:country":"US",
    "sg:address":"104 Plaza Dr",
    "sg:city":"Kerrville",
    "sg:classifiers":[
        {
            "category":"Food & Beverages",
            "subcategory":"Specialty",
            "type":"Retail Goods"
        }
    ],
    "sg:phone":"+1 830 895 3077",
    "sg:postcode":"78028",
    "sg:province":"TX",
    "sg:tags":[
        "herb"
    ],
    "wof:name":"Creative Health & Nutrition",
    "wof:placetype":"venue"
},
  "geometry": {"coordinates":[-99.16233699999999,30.057823],"type":"Point"}
}