{
  "type": "Feature",
  "properties": {
    "iso:country":"US",
    "sg:address":"11980 Westheimer Rd",
    "sg:city":"Houston",
    "sg:classifiers":[
        {
            "category":"Restaurant",
            "type":"Food & Drink"
        }
    ],
    "sg:menulink":"http://www.allmenus.com/tx/houston/43294-the-bull--bear-tavern--eatery/menu/",
    "sg:phone":"+1 281 496 6655",
    "sg:postcode":"77077",
    "sg:province":"TX",
    "sg:tags":[
        "american"
    ],
    "wof:name":"The Bull & Bear Tavern & Eatery",
    "wof:placetype":"venue"
},
  "geometry": {"coordinates":[-95.592472,29.750308],"type":"Point"}
}