{
  "type": "Feature",
  "properties": {
    "iso:country":"US",
    "sg:address":"315 S Main St",
    "sg:city":"Morton",
    "sg:classifiers":[
        {
            "category":"Autos & Motor Vehicles",
            "subcategory":"Fuel & Gas Station",
            "type":"Retail Goods"
        }
    ],
    "sg:phone":"+1 806 266 8687",
    "sg:postcode":"79346",
    "sg:province":"TX",
    "sg:tags":[
        "oil"
    ],
    "wof:name":"Greer's Exxon Serv St",
    "wof:placetype":"venue"
},
  "geometry": {"coordinates":[-102.75915000000001,33.723154],"type":"Point"}
}