{
  "type": "Feature",
  "properties": {
    "iso:country":"US",
    "sg:address":"1608 S I- 35",
    "sg:city":"San Marcos",
    "sg:classifiers":[
        {
            "category":"Retail",
            "subcategory":"Auto Repair",
            "type":"Services"
        }
    ],
    "sg:phone":"+1 512 396 8972",
    "sg:postcode":"78666",
    "sg:province":"TX",
    "sg:tags":[
        "body",
        "automobile",
        "painting"
    ],
    "sg:website":"www.ernies.us",
    "wof:name":"Ernies Paint and Body Shop",
    "wof:placetype":"venue"
},
  "geometry": {"coordinates":[-97.946383,29.863369],"type":"Point"}
}