{
  "type": "Feature",
  "properties": {
    "iso:country":"US",
    "sg:address":"300 E Harris Ave",
    "sg:city":"Kilgore",
    "sg:classifiers":[
        {
            "category":"Manufacturing",
            "subcategory":"Retail Goods",
            "type":"Manufacturing & Wholesale Goods"
        }
    ],
    "sg:phone":"+1 903 986 1226",
    "sg:postcode":"75662",
    "sg:province":"TX",
    "sg:tags":[
        "assembly",
        "fabricating"
    ],
    "wof:name":"Fabrication Technologies",
    "wof:placetype":"venue"
},
  "geometry": {"coordinates":[-94.879076,32.373423],"type":"Point"}
}