{
  "type": "Feature",
  "properties": {
    "iso:country":"US",
    "sg:address":"2215 State Loop 288",
    "sg:city":"Denton",
    "sg:classifiers":[
        {
            "category":"Manufacturing",
            "subcategory":"Paper Products",
            "type":"Manufacturing & Wholesale Goods"
        }
    ],
    "sg:phone":"+1 940 591 6565",
    "sg:postcode":"76205",
    "sg:province":"TX",
    "sg:tags":[
        "printing",
        "supply"
    ],
    "wof:name":"Cartridge World",
    "wof:placetype":"venue"
},
  "geometry": {"coordinates":[-97.10423,33.189169],"type":"Point"}
}