{
  "type": "Feature",
  "properties": {
    "iso:country":"US",
    "sg:address":"1011 W Main St",
    "sg:city":"Brenham",
    "sg:classifiers":[
        {
            "category":"Food & Beverages",
            "subcategory":"Specialty",
            "type":"Retail Goods"
        }
    ],
    "sg:phone":"+1 979 836 1243",
    "sg:postcode":"77833",
    "sg:province":"TX",
    "sg:tags":[
        "product",
        "health",
        "diet"
    ],
    "sg:website":"http://www.brenhamhealthfood.com",
    "wof:name":"Brenham Health Food",
    "wof:placetype":"venue"
},
  "geometry": {"coordinates":[-96.40923100000001,30.165048],"type":"Point"}
}