{
  "type": "Feature",
  "properties": {
    "iso:country":"US",
    "sg:address":"4405 Princeton Dr",
    "sg:city":"Garland",
    "sg:classifiers":[
        {
            "category":"Professional",
            "type":"Services"
        }
    ],
    "sg:phone":"+1 972 494 6526",
    "sg:postcode":"75042",
    "sg:province":"TX",
    "wof:name":"To Z A Custom",
    "wof:placetype":"venue"
},
  "geometry": {"coordinates":[-96.69737000000001,32.918665],"type":"Point"}
}