{
  "type": "Feature",
  "properties": {
    "iso:country":"US",
    "sg:address":"227 Sequoia",
    "sg:city":"San Antonio",
    "sg:classifiers":[
        {
            "category":"Professional",
            "type":"Services"
        }
    ],
    "sg:phone":"+1 210 545 2772",
    "sg:postcode":"78232",
    "sg:province":"TX",
    "wof:name":"Stefani Job Spears",
    "wof:placetype":"venue"
},
  "geometry": {"coordinates":[-98.487816,29.595834],"type":"Point"}
}