{
  "type": "Feature",
  "properties": {
    "iso:country":"US",
    "sg:address":"1109 S Treadaway Blvd",
    "sg:city":"Abilene",
    "sg:classifiers":[
        {
            "category":"Food & Beverages",
            "subcategory":"Groceries & Convenience Stores",
            "type":"Retail Goods"
        }
    ],
    "sg:phone":"+1 325 437 0440",
    "sg:postcode":"79602",
    "sg:province":"TX",
    "wof:name":"Chillerz 2",
    "wof:placetype":"venue"
},
  "geometry": {"coordinates":[-99.72856299999999,32.435811],"type":"Point"}
}