{
  "type": "Feature",
  "properties": {
    "iso:country":"US",
    "sg:address":"904 Pilar Spr",
    "sg:city":"Killeen",
    "sg:classifiers":[
        {
            "category":"Shopping",
            "subcategory":"Hobbies, Toys, & Games",
            "type":"Retail Goods"
        }
    ],
    "sg:phone":"+1 254 526 6025",
    "sg:postcode":"76541",
    "sg:province":"TX",
    "sg:tags":[
        "craft"
    ],
    "wof:name":"Rainbows End",
    "wof:placetype":"venue"
},
  "geometry": {"coordinates":[-97.74266900000001,31.111904],"type":"Point"}
}