{
  "type": "Feature",
  "properties": {
    "iso:country":"US",
    "sg:address":"13636 Neutron Rd",
    "sg:city":"Dallas",
    "sg:classifiers":[
        {
            "category":"Health Services",
            "subcategory":"Optometrist",
            "type":"Services"
        }
    ],
    "sg:phone":"+1 972 387 3937",
    "sg:postcode":"75244",
    "sg:province":"TX",
    "wof:name":"Shropshire D B & Associates",
    "wof:placetype":"venue"
},
  "geometry": {"coordinates":[-96.834799,32.934341],"type":"Point"}
}