{
  "type": "Feature",
  "properties": {
    "iso:country":"US",
    "sg:address":"115 S 17th St",
    "sg:city":"Mcallen",
    "sg:classifiers":[
        {
            "category":"Wholesale",
            "subcategory":"Farm Supplies",
            "type":"Manufacturing & Wholesale Goods"
        }
    ],
    "sg:phone":"+1 956 686 6401",
    "sg:postcode":"78501",
    "sg:province":"TX",
    "wof:name":"Kalifa Feed & Seed",
    "wof:placetype":"venue"
},
  "geometry": {"coordinates":[-98.23794700000001,26.202978],"type":"Point"}
}