{
  "type": "Feature",
  "properties": {
    "iso:country":"US",
    "sg:address":"2918 Brinwood Ave",
    "sg:city":"Austin",
    "sg:classifiers":[
        {
            "category":"Wholesale",
            "subcategory":"Machinery & Supplies",
            "type":"Manufacturing & Wholesale Goods"
        }
    ],
    "sg:phone":"+1 512 336 9633",
    "sg:postcode":"78704",
    "sg:province":"TX",
    "sg:tags":[
        "equipment",
        "industrial"
    ],
    "wof:name":"Kalix USA Inc",
    "wof:placetype":"venue"
},
  "geometry": {"coordinates":[-97.76026299999999,30.233482],"type":"Point"}
}