{
  "type": "Feature",
  "properties": {
    "iso:country":"US",
    "sg:address":"1412 N Main St",
    "sg:city":"Highlands",
    "sg:classifiers":[
        {
            "category":"Manufacturing",
            "subcategory":"Building Materials",
            "type":"Manufacturing & Wholesale Goods"
        }
    ],
    "sg:phone":"+1 281 843 2991",
    "sg:postcode":"77562",
    "sg:province":"TX",
    "sg:tags":[
        "mfg",
        "wood",
        "kitchen",
        "cabinet"
    ],
    "wof:name":"Krooked Kabinets",
    "wof:placetype":"venue"
},
  "geometry": {"coordinates":[-95.057941,29.834566],"type":"Point"}
}