{
  "type": "Feature",
  "properties": {
    "iso:country":"US",
    "sg:address":"4608 Livingston Ave",
    "sg:city":"Dallas",
    "sg:classifiers":[
        {
            "category":"Professional",
            "subcategory":"Business Services",
            "type":"Services"
        }
    ],
    "sg:phone":"+1 214 353 9300",
    "sg:postcode":"75209",
    "sg:province":"TX",
    "wof:name":"Marion Nichols Interiors",
    "wof:placetype":"venue"
},
  "geometry": {"coordinates":[-96.818944,32.834957],"type":"Point"}
}