{
  "type": "Feature",
  "properties": {
    "iso:country":"US",
    "sg:address":"313 Southwind Rd",
    "sg:city":"Leander",
    "sg:classifiers":[
        {
            "category":"Real Estate",
            "subcategory":"Developer",
            "type":"Services"
        }
    ],
    "sg:phone":"+1 512 267 6729",
    "sg:postcode":"78645",
    "sg:province":"TX",
    "sg:tags":[
        "merchandise",
        "general"
    ],
    "wof:name":"Shawn E Higley",
    "wof:placetype":"venue"
},
  "geometry": {"coordinates":[-97.990465,30.388546],"type":"Point"}
}