{
  "type": "Feature",
  "properties": {
    "iso:country":"US",
    "sg:address":"18909 Lloyd Cir",
    "sg:city":"Dallas",
    "sg:classifiers":[
        {
            "category":"Banks & Credit Unions",
            "subcategory":"Bank",
            "type":"Services"
        }
    ],
    "sg:phone":"+1 972 250 9210",
    "sg:postcode":"75252",
    "sg:province":"TX",
    "sg:tags":[
        "broker",
        "mortgage"
    ],
    "wof:name":"Expedia Mortgage LLC",
    "wof:placetype":"venue"
},
  "geometry": {"coordinates":[-96.795519,33.010204],"type":"Point"}
}