{
  "type": "Feature",
  "properties": {
    "iso:country":"US",
    "sg:address":"2225 E Randol Mill Rd",
    "sg:city":"Arlington",
    "sg:classifiers":[
        {
            "category":"Manufacturing",
            "subcategory":"Electronics",
            "type":"Manufacturing & Wholesale Goods"
        }
    ],
    "sg:phone":"+1 817 640 5300",
    "sg:postcode":"76011",
    "sg:province":"TX",
    "sg:tags":[
        "equipment",
        "electronic",
        "supply"
    ],
    "wof:name":"Remec Wacom",
    "wof:placetype":"venue"
},
  "geometry": {"coordinates":[-97.069694,32.748036],"type":"Point"}
}