{
  "type": "Feature",
  "properties": {
    "iso:country":"US",
    "sg:address":"1433 College Dr",
    "sg:city":"Texarkana",
    "sg:classifiers":[
        {
            "category":"Shopping",
            "subcategory":"Bicycles & Sporting Goods",
            "type":"Retail Goods"
        }
    ],
    "sg:phone":"+1 903 792 3391",
    "sg:postcode":"75503",
    "sg:province":"TX",
    "wof:name":"Scoreboard The",
    "wof:placetype":"venue"
},
  "geometry": {"coordinates":[-94.06202,33.448763],"type":"Point"}
}