{
  "type": "Feature",
  "properties": {
    "iso:country":"US",
    "sg:address":"14256 Timberridge Ln",
    "sg:city":"Winona",
    "sg:classifiers":[
        {
            "category":"Food & Beverages",
            "subcategory":"Groceries & Convenience Stores",
            "type":"Retail Goods"
        }
    ],
    "sg:phone":"+1 903 643 2038",
    "sg:postcode":"75792",
    "sg:province":"TX",
    "sg:tags":[
        "station",
        "gasoline"
    ],
    "wof:name":"Handy Pantry",
    "wof:placetype":"venue"
},
  "geometry": {"coordinates":[-95.059431,32.471437],"type":"Point"}
}