{
  "type": "Feature",
  "properties": {
    "iso:country":"US",
    "sg:address":"12801 Midway Rd",
    "sg:city":"Dallas",
    "sg:classifiers":[
        {
            "category":"Home & Garden",
            "subcategory":"Carpets & Floor Coverings",
            "type":"Retail Goods"
        }
    ],
    "sg:phone":"+1 972 241 9036",
    "sg:postcode":"75229",
    "sg:province":"TX",
    "sg:tags":[
        "dealer",
        "rug"
    ],
    "wof:name":"Carpet Tree",
    "wof:placetype":"venue"
},
  "geometry": {"coordinates":[-96.838453,32.924585],"type":"Point"}
}