{
  "type": "Feature",
  "properties": {
    "iso:country":"US",
    "sg:address":"6 Maple Ln",
    "sg:city":"Galveston",
    "sg:classifiers":[
        {
            "category":"Building & Trades",
            "subcategory":"Equipment Rental",
            "type":"Services"
        }
    ],
    "sg:phone":"+1 409 744 7397",
    "sg:postcode":"77551",
    "sg:province":"TX",
    "wof:name":"Habana West Beach Service",
    "wof:placetype":"venue"
},
  "geometry": {"coordinates":[-94.840574,29.27852],"type":"Point"}
}