{
  "type": "Feature",
  "properties": {
    "iso:country":"US",
    "sg:address":"9401 Anderson Mill Rd",
    "sg:city":"Austin",
    "sg:classifiers":[
        {
            "category":"Professional",
            "subcategory":"Employment Agencies",
            "type":"Services"
        }
    ],
    "sg:phone":"+1 512 331 2900",
    "sg:postcode":"78729",
    "sg:province":"TX",
    "sg:tags":[
        "consultant",
        "search",
        "executive"
    ],
    "wof:name":"Xecute Technology",
    "wof:placetype":"venue"
},
  "geometry": {"coordinates":[-97.786477,30.449982],"type":"Point"}
}