{
  "type": "Feature",
  "properties": {
    "iso:country":"US",
    "sg:address":"6001 Airport Blvd",
    "sg:city":"Austin",
    "sg:classifiers":[
        {
            "category":"Shopping",
            "subcategory":"Discount & Variety Stores",
            "type":"Retail Goods"
        }
    ],
    "sg:phone":"+1 512 371 3802",
    "sg:postcode":"78752",
    "sg:province":"TX",
    "wof:name":"Brookstone Inc",
    "wof:placetype":"venue"
},
  "geometry": {"coordinates":[-97.715479,30.323839],"type":"Point"}
}