{
  "type": "Feature",
  "properties": {
    "iso:country":"US",
    "sg:address":"4005 Scott Dr",
    "sg:city":"Rowlett",
    "sg:classifiers":[
        {
            "category":"Wholesale",
            "subcategory":"Furniture",
            "type":"Manufacturing & Wholesale Goods"
        }
    ],
    "sg:phone":"+1 214 562 4453",
    "sg:postcode":"75088",
    "sg:province":"TX",
    "wof:name":"Million Dollar Rustic",
    "wof:placetype":"venue"
},
  "geometry": {"coordinates":[-96.56422499999999,32.88691],"type":"Point"}
}