{
  "type": "Feature",
  "properties": {
    "iso:country":"US",
    "sg:address":"1104 W Jefferson Blvd",
    "sg:city":"Dallas",
    "sg:classifiers":[
        {
            "category":"Health Services",
            "subcategory":"Chiropractor",
            "type":"Services"
        }
    ],
    "sg:phone":"+1 214 696 9969",
    "sg:postcode":"75208",
    "sg:province":"TX",
    "wof:name":"Dallas Chiropractic & Carpal",
    "wof:placetype":"venue"
},
  "geometry": {"coordinates":[-96.841672,32.743436],"type":"Point"}
}