{
  "type": "Feature",
  "properties": {
    "iso:country":"US",
    "sg:address":"9451 Winkler Dr",
    "sg:city":"Houston",
    "sg:classifiers":[
        {
            "category":"Wholesale",
            "subcategory":"Hardware",
            "type":"Manufacturing & Wholesale Goods"
        }
    ],
    "sg:phone":"+1 713 944 2962",
    "sg:postcode":"77017",
    "sg:province":"TX",
    "wof:name":"Solar Supply of Houston SE",
    "wof:placetype":"venue"
},
  "geometry": {"coordinates":[-95.247747,29.670184],"type":"Point"}
}