{
  "type": "Feature",
  "properties": {
    "iso:country":"US",
    "sg:address":"3002 Skyway Cir S",
    "sg:city":"Irving",
    "sg:classifiers":[
        {
            "category":"Real Estate",
            "subcategory":"Real Estate Agent",
            "type":"Services"
        }
    ],
    "sg:phone":"+1 972 252 9468",
    "sg:postcode":"75038",
    "sg:province":"TX",
    "wof:name":"Reibold Group",
    "wof:placetype":"venue"
},
  "geometry": {"coordinates":[-96.984274,32.869573],"type":"Point"}
}