{
  "type": "Feature",
  "properties": {
    "iso:country":"US",
    "sg:address":"5551 Randolph Blvd",
    "sg:city":"San Antonio",
    "sg:classifiers":[
        {
            "category":"Wholesale",
            "subcategory":"Construction Materials",
            "type":"Manufacturing & Wholesale Goods"
        }
    ],
    "sg:phone":"+1 210 653 8846",
    "sg:postcode":"78233",
    "sg:province":"TX",
    "sg:tags":[
        "glass",
        "glazing"
    ],
    "wof:name":"National Glass & Mirror Prod",
    "wof:placetype":"venue"
},
  "geometry": {"coordinates":[-98.379909,29.532443],"type":"Point"}
}