{
  "type": "Feature",
  "properties": {
    "iso:country":"US",
    "sg:address":"6120 Huddleston St",
    "sg:city":"Haltom City",
    "sg:classifiers":[
        {
            "category":"Recreation",
            "type":"Entertainment"
        }
    ],
    "sg:phone":"+1 817 498 8700",
    "sg:postcode":"76137",
    "sg:province":"TX",
    "sg:tags":[
        "instruction",
        "gymnastic"
    ],
    "wof:name":"Texas Tumblers Gymnastics",
    "wof:placetype":"venue"
},
  "geometry": {"coordinates":[-97.26629200000001,32.859407],"type":"Point"}
}