{
  "type": "Feature",
  "properties": {
    "iso:country":"US",
    "sg:address":"17611 Loring Ln",
    "sg:city":"Spring",
    "sg:classifiers":[
        {
            "category":"Professional",
            "subcategory":"Computer Services",
            "type":"Services"
        }
    ],
    "sg:phone":"+1 281 651 7106",
    "sg:postcode":"77388",
    "sg:province":"TX",
    "sg:tags":[
        "related"
    ],
    "wof:name":"Abacus Technologies",
    "wof:placetype":"venue"
},
  "geometry": {"coordinates":[-95.47670599999999,30.031531],"type":"Point"}
}