{
  "type": "Feature",
  "properties": {
    "iso:country":"US",
    "sg:address":"1818 Hemphill St",
    "sg:city":"Fort Worth",
    "sg:classifiers":[
        {
            "category":"Professional",
            "type":"Services"
        }
    ],
    "sg:phone":"+1 817 207 9407",
    "sg:postcode":"76110",
    "sg:province":"TX",
    "wof:name":"Antojitos Monterry",
    "wof:placetype":"venue"
},
  "geometry": {"coordinates":[-97.33164499999999,32.72383],"type":"Point"}
}