{
  "type": "Feature",
  "properties": {
    "iso:country":"US",
    "sg:address":"825 Piedmont Dr",
    "sg:city":"Garland",
    "sg:classifiers":[
        {
            "category":"Professional",
            "type":"Services"
        }
    ],
    "sg:phone":"+1 972 864 0604",
    "sg:postcode":"75040",
    "sg:province":"TX",
    "wof:name":"Magdas Etc",
    "wof:placetype":"venue"
},
  "geometry": {"coordinates":[-96.61847,32.900534],"type":"Point"}
}