{
  "type": "Feature",
  "properties": {
    "iso:country":"US",
    "sg:address":"955 Dairy Ashford St",
    "sg:city":"Houston",
    "sg:classifiers":[
        {
            "category":"Health Services",
            "subcategory":"Health Practitioner",
            "type":"Services"
        }
    ],
    "sg:phone":"+1 281 679 0001",
    "sg:postcode":"77079",
    "sg:province":"TX",
    "wof:name":"Robert F Sarmiento PHD",
    "wof:placetype":"venue"
},
  "geometry": {"coordinates":[-95.606343,29.777392],"type":"Point"}
}