{
  "type": "Feature",
  "properties": {
    "iso:country":"US",
    "sg:address":"234 Katy St",
    "sg:city":"Garland",
    "sg:classifiers":[
        {
            "category":"Building & Trades",
            "subcategory":"Construction",
            "type":"Services"
        }
    ],
    "sg:phone":"+1 972 276 3904",
    "sg:postcode":"75040",
    "sg:province":"TX",
    "sg:tags":[
        "commercial",
        "contractor"
    ],
    "wof:name":"Binder Jay C Construction Co",
    "wof:placetype":"venue"
},
  "geometry": {"coordinates":[-96.63159899999999,32.916302],"type":"Point"}
}