{
  "type": "Feature",
  "properties": {
    "iso:country":"US",
    "sg:address":"12850 Ashford Creek Dr",
    "sg:city":"Houston",
    "sg:classifiers":[
        {
            "category":"Professional",
            "subcategory":"Management & Consulting",
            "type":"Services"
        }
    ],
    "sg:phone":"+1 281 870 1442",
    "sg:postcode":"77082",
    "sg:province":"TX",
    "sg:tags":[
        "business"
    ],
    "wof:name":"Terrys Part Tchncal Consulting",
    "wof:placetype":"venue"
},
  "geometry": {"coordinates":[-95.612443,29.734286],"type":"Point"}
}