{
  "type": "Feature",
  "properties": {
    "iso:country":"US",
    "sg:address":"107 W Main St",
    "sg:city":"Allen",
    "sg:classifiers":[
        {
            "category":"Professional",
            "subcategory":"Art Services",
            "type":"Services"
        }
    ],
    "sg:phone":"+1 972 727 1981",
    "sg:postcode":"75013",
    "sg:province":"TX",
    "sg:tags":[
        "commercial",
        "printing",
        "design"
    ],
    "wof:name":"Squeegees Emporium",
    "wof:placetype":"venue"
},
  "geometry": {"coordinates":[-96.670856,33.103072],"type":"Point"}
}