{
  "type": "Feature",
  "properties": {
    "iso:country":"US",
    "sg:address":"305 N 13th St",
    "sg:city":"Donna",
    "sg:classifiers":[
        {
            "category":"Shopping",
            "type":"Retail Goods"
        }
    ],
    "sg:phone":"+1 956 464 2695",
    "sg:postcode":"78537",
    "sg:province":"TX",
    "sg:tags":[
        "merchandise"
    ],
    "wof:name":"D Wood Shop",
    "wof:placetype":"venue"
},
  "geometry": {"coordinates":[-98.048811,26.175437],"type":"Point"}
}