{
  "type": "Feature",
  "properties": {
    "iso:country":"US",
    "sg:address":"13759 Dairyland Dr",
    "sg:city":"Willis",
    "sg:classifiers":[
        {
            "category":"Shopping",
            "subcategory":"Beauty & Cosmetics",
            "type":"Retail Goods"
        }
    ],
    "sg:phone":"+1 936 856 8290",
    "sg:postcode":"77318",
    "sg:province":"TX",
    "sg:tags":[
        "merchandise"
    ],
    "wof:name":"Bernice Hines",
    "wof:placetype":"venue"
},
  "geometry": {"coordinates":[-95.57016900000001,30.443523],"type":"Point"}
}