{
  "type": "Feature",
  "properties": {
    "iso:country":"US",
    "sg:address":"4600 S Medford Dr",
    "sg:city":"Lufkin",
    "sg:classifiers":[
        {
            "category":"Professional",
            "subcategory":"Business Services",
            "type":"Services"
        }
    ],
    "sg:phone":"+1 936 637 1210",
    "sg:postcode":"75901",
    "sg:province":"TX",
    "wof:name":"Aeropostale",
    "wof:placetype":"venue"
},
  "geometry": {"coordinates":[-94.725319,31.310554],"type":"Point"}
}