{
  "type": "Feature",
  "properties": {
    "iso:country":"US",
    "sg:address":"305 N Baird St",
    "sg:city":"Midland",
    "sg:classifiers":[
        {
            "category":"Organizations",
            "subcategory":"Religious Organization",
            "type":"Services"
        }
    ],
    "sg:phone":"+1 432 682 3701",
    "sg:postcode":"79701",
    "sg:province":"TX",
    "sg:tags":[
        "church"
    ],
    "sg:website":"www.fumcmidland.org",
    "wof:name":"First United Methodist Church",
    "wof:placetype":"venue"
},
  "geometry": {"coordinates":[-102.073308,32.000634],"type":"Point"}
}