{
  "type": "Feature",
  "properties": {
    "iso:country":"US",
    "sg:address":"4415 Sue Belle Lake Rd",
    "sg:city":"Marshall",
    "sg:classifiers":[
        {
            "category":"Real Estate",
            "subcategory":"Real Estate Agent",
            "type":"Services"
        }
    ],
    "sg:phone":"+1 903 935 6882",
    "sg:postcode":"75670",
    "sg:province":"TX",
    "wof:name":"Emit Co",
    "wof:placetype":"venue"
},
  "geometry": {"coordinates":[-94.369868,32.59181],"type":"Point"}
}