{
  "type": "Feature",
  "properties": {
    "iso:country":"US",
    "sg:address":"13003 Southwest Fwy # 145",
    "sg:city":"Stafford",
    "sg:classifiers":[
        {
            "category":"Home & Garden",
            "subcategory":"Household Appliances",
            "type":"Retail Goods"
        },
        {
            "category":"Wholesale",
            "subcategory":"Electrical",
            "type":"Manufacturing & Wholesale Goods"
        },
        {
            "category":"Building & Trades",
            "subcategory":"Construction",
            "type":"Services"
        },
        {
            "category":"Professional",
            "subcategory":"Engineering",
            "type":"Services"
        }
    ],
    "sg:phone":"+1 281 240 5858",
    "sg:postcode":"77477",
    "sg:province":"TX",
    "sg:tags":[
        "systems-wholesale",
        "major",
        "dishwashing",
        "radiators-heating",
        "supply",
        "sales",
        "system",
        "machine",
        "equipment",
        "air conditioning",
        "manufacturer"
    ],
    "wof:name":"Texas Reps",
    "wof:placetype":"venue"
},
  "geometry": {"coordinates":[-95.590363,29.630289],"type":"Point"}
}