{
  "type": "Feature",
  "properties": {
    "iso:country":"US",
    "sg:address":"1711 Glade St",
    "sg:city":"College Station",
    "sg:classifiers":[
        {
            "category":"Health Services",
            "subcategory":"Health Practitioner",
            "type":"Services"
        }
    ],
    "sg:phone":"+1 979 693 6759",
    "sg:postcode":"77840",
    "sg:province":"TX",
    "wof:name":"Barbara D Clark PHD",
    "wof:placetype":"venue"
},
  "geometry": {"coordinates":[-96.317224,30.603878],"type":"Point"}
}