{
  "type": "Feature",
  "properties": {
    "iso:country":"US",
    "sg:address":"12804 Scofield Farms Dr",
    "sg:city":"Austin",
    "sg:classifiers":[
        {
            "category":"Professional",
            "subcategory":"Business Services",
            "type":"Services"
        }
    ],
    "sg:phone":"+1 512 873 0199",
    "sg:postcode":"78727",
    "sg:province":"TX",
    "sg:tags":[
        "assistance",
        "group",
        "event",
        "lodging"
    ],
    "wof:name":"David Green Organization",
    "wof:placetype":"venue"
},
  "geometry": {"coordinates":[-97.68257199999999,30.415491],"type":"Point"}
}