{
  "type": "Feature",
  "properties": {
    "iso:country":"US",
    "sg:address":"6315 Winkleman Rd",
    "sg:city":"Houston",
    "sg:classifiers":[
        {
            "category":"Education",
            "subcategory":"School",
            "type":"Public Place"
        }
    ],
    "sg:phone":"+1 281 983 8411",
    "sg:postcode":"77083",
    "sg:province":"TX",
    "sg:tags":[
        "middle"
    ],
    "wof:name":"Albright Middle School",
    "wof:placetype":"venue"
},
  "geometry": {"coordinates":[-95.65482299999999,29.707979],"type":"Point"}
}