{
  "type": "Feature",
  "properties": {
    "iso:country":"US",
    "sg:address":"2154 Motley Dr",
    "sg:city":"Mesquite",
    "sg:classifiers":[
        {
            "category":"Organizations",
            "subcategory":"Religious Organization",
            "type":"Services"
        }
    ],
    "sg:phone":"+1 972 270 1087",
    "sg:postcode":"75150",
    "sg:province":"TX",
    "sg:tags":[
        "church"
    ],
    "wof:name":"Eastridge Park Congregational",
    "wof:placetype":"venue"
},
  "geometry": {"coordinates":[-96.635119,32.795518],"type":"Point"}
}