{
  "type": "Feature",
  "properties": {
    "iso:country":"US",
    "sg:address":"311 Ranch Rd 620 S",
    "sg:city":"Lakeway",
    "sg:classifiers":[
        {
            "category":"Building & Trades",
            "subcategory":"Construction",
            "type":"Services"
        }
    ],
    "sg:phone":"+1 512 263 3532",
    "sg:postcode":"78734",
    "sg:province":"TX",
    "sg:tags":[
        "coping",
        "plastering",
        "tiling",
        "pool",
        "swimming"
    ],
    "wof:name":"Lakeway Pool Maintenance",
    "wof:placetype":"venue"
},
  "geometry": {"coordinates":[-97.95257700000001,30.362846],"type":"Point"}
}