{
  "type": "Feature",
  "properties": {
    "iso:country":"US",
    "sg:address":"810 E Yandell Dr",
    "sg:city":"El Paso",
    "sg:classifiers":[
        {
            "category":"Professional",
            "subcategory":"Engineering",
            "type":"Services"
        }
    ],
    "sg:phone":"+1 915 533 6811",
    "sg:postcode":"79902",
    "sg:province":"TX",
    "sg:tags":[
        "engineer"
    ],
    "sg:website":"www.team-psc.com",
    "wof:name":"Parkhill Smith & Cooper Inc",
    "wof:placetype":"venue"
},
  "geometry": {"coordinates":[-106.485088,31.766888],"type":"Point"}
}