{
  "type": "Feature",
  "properties": {
    "iso:country":"US",
    "sg:address":"22124 Briarcliff Dr",
    "sg:city":"Spicewood",
    "sg:classifiers":[
        {
            "category":"Wholesale",
            "subcategory":"Groceries",
            "type":"Manufacturing & Wholesale Goods"
        }
    ],
    "sg:phone":"+1 512 266 7157",
    "sg:postcode":"78669",
    "sg:province":"TX",
    "sg:tags":[
        "food",
        "product"
    ],
    "sg:website":"www.classydelites.com",
    "wof:name":"Classy Delites",
    "wof:placetype":"venue"
},
  "geometry": {"coordinates":[-98.04636000000001,30.412328],"type":"Point"}
}