{
  "type": "Feature",
  "properties": {
    "iso:country":"US",
    "sg:address":"3605 Montecito Dr",
    "sg:city":"Denton",
    "sg:classifiers":[
        {
            "category":"Professional",
            "type":"Services"
        }
    ],
    "sg:phone":"+1 940 380 1291",
    "sg:postcode":"76205",
    "sg:province":"TX",
    "wof:name":"Bbf Inc",
    "wof:placetype":"venue"
},
  "geometry": {"coordinates":[-97.124028,33.166148],"type":"Point"}
}