{
  "type": "Feature",
  "properties": {
    "iso:country":"US",
    "sg:address":"2301 Fairway Dr",
    "sg:city":"Alvin",
    "sg:classifiers":[
        {
            "category":"Shopping",
            "subcategory":"Hobbies, Toys, & Games",
            "type":"Retail Goods"
        }
    ],
    "sg:phone":"+1 281 331 5376",
    "sg:postcode":"77511",
    "sg:province":"TX",
    "wof:name":"Pjs Country Crafts",
    "wof:placetype":"venue"
},
  "geometry": {"coordinates":[-95.233429,29.406409],"type":"Point"}
}