{
  "type": "Feature",
  "properties": {
    "iso:country":"US",
    "sg:address":"5331 Beverlyhill St",
    "sg:city":"Houston",
    "sg:classifiers":[
        {
            "category":"Personal",
            "type":"Services"
        }
    ],
    "sg:phone":"+1 713 203 7413",
    "sg:postcode":"77056",
    "sg:province":"TX",
    "sg:tags":[
        "therapist",
        "massage"
    ],
    "wof:name":"Massage & Astrology By Dave's",
    "wof:placetype":"venue"
},
  "geometry": {"coordinates":[-95.470252,29.730062],"type":"Point"}
}