{
  "type": "Feature",
  "properties": {
    "iso:country":"US",
    "sg:address":"11819 Blanco Rd",
    "sg:city":"San Antonio",
    "sg:classifiers":[
        {
            "category":"Health Services",
            "subcategory":"Doctor",
            "type":"Services"
        }
    ],
    "sg:phone":"+1 210 344 0101",
    "sg:postcode":"78216",
    "sg:province":"TX",
    "sg:tags":[
        "dentist"
    ],
    "wof:name":"Churchill Dental Assoc",
    "wof:placetype":"venue"
},
  "geometry": {"coordinates":[-98.512533,29.551359],"type":"Point"}
}