{
  "type": "Feature",
  "properties": {
    "iso:country":"US",
    "sg:address":"2710 Oak Lawn Ave",
    "sg:city":"Dallas",
    "sg:classifiers":[
        {
            "category":"Banks & Credit Unions",
            "subcategory":"Investment Brokerage",
            "type":"Services"
        }
    ],
    "sg:phone":"+1 214 522 8620",
    "sg:postcode":"75219",
    "sg:province":"TX",
    "sg:tags":[
        "security"
    ],
    "wof:name":"Tollwood USA Investment Co",
    "wof:placetype":"venue"
},
  "geometry": {"coordinates":[-96.81101700000001,32.806802],"type":"Point"}
}