{
  "type": "Feature",
  "properties": {
    "iso:country":"US",
    "sg:address":"12425 E Northwest Hwy",
    "sg:city":"Dallas",
    "sg:classifiers":[
        {
            "category":"Travel",
            "subcategory":"Hotels & Motels",
            "type":"Entertainment"
        }
    ],
    "sg:phone":"+1 214 327 3278",
    "sg:postcode":"75228",
    "sg:province":"TX",
    "wof:name":"Budget Inn Llc",
    "wof:placetype":"venue"
},
  "geometry": {"coordinates":[-96.66680100000001,32.8643],"type":"Point"}
}