{
  "type": "Feature",
  "properties": {
    "iso:country":"US",
    "sg:address":"1511 Haskin Dr",
    "sg:city":"San Antonio",
    "sg:classifiers":[
        {
            "category":"Insurance",
            "subcategory":"Insurance Agent",
            "type":"Services"
        }
    ],
    "sg:phone":"+1 210 824 1955",
    "sg:postcode":"78209",
    "sg:province":"TX",
    "wof:name":"Alamo Area Insurance",
    "wof:placetype":"venue"
},
  "geometry": {"coordinates":[-98.44662599999999,29.513584],"type":"Point"}
}