{
  "type": "Feature",
  "properties": {
    "iso:country":"US",
    "sg:address":"604 N Riverside Dr",
    "sg:city":"Fort Worth",
    "sg:classifiers":[
        {
            "category":"Food & Beverages",
            "subcategory":"Groceries & Convenience Stores",
            "type":"Retail Goods"
        }
    ],
    "sg:phone":"+1 817 222 9922",
    "sg:postcode":"76111",
    "sg:province":"TX",
    "wof:name":"Discount Food Store",
    "wof:placetype":"venue"
},
  "geometry": {"coordinates":[-97.301604,32.772327],"type":"Point"}
}