{
  "type": "Feature",
  "properties": {
    "iso:country":"US",
    "sg:address":"910 Taulbee Ln",
    "sg:city":"Austin",
    "sg:classifiers":[
        {
            "category":"Professional",
            "type":"Services"
        }
    ],
    "sg:phone":"+1 512 419 9596",
    "sg:postcode":"78757",
    "sg:province":"TX",
    "wof:name":"Anh Diep",
    "wof:placetype":"venue"
},
  "geometry": {"coordinates":[-97.716708,30.346225],"type":"Point"}
}