{
  "type": "Feature",
  "properties": {
    "iso:country":"US",
    "sg:address":"4505 W Trimmier Rd",
    "sg:city":"Killeen",
    "sg:classifiers":[
        {
            "category":"Wholesale",
            "subcategory":"Electrical",
            "type":"Manufacturing & Wholesale Goods"
        }
    ],
    "sg:phone":"+1 254 200 1020",
    "sg:postcode":"76542",
    "sg:province":"TX",
    "sg:tags":[
        "alarm",
        "burglar",
        "system"
    ],
    "sg:website":"www.ur-security.com",
    "wof:name":"U R Security",
    "wof:placetype":"venue"
},
  "geometry": {"coordinates":[-97.739774,31.074886],"type":"Point"}
}