{
  "type": "Feature",
  "properties": {
    "iso:country":"US",
    "sg:address":"1380 Fish Hatchery Rd",
    "sg:city":"Huntsville",
    "sg:classifiers":[
        {
            "category":"Organizations",
            "subcategory":"Religious Organization",
            "type":"Services"
        }
    ],
    "sg:phone":"+1 936 438 8202",
    "sg:postcode":"77320",
    "sg:province":"TX",
    "sg:tags":[
        "church"
    ],
    "wof:name":"Church Christ",
    "wof:placetype":"venue"
},
  "geometry": {"coordinates":[-95.50922,30.745828],"type":"Point"}
}