{
  "type": "Feature",
  "properties": {
    "iso:country":"US",
    "sg:address":"1863 Briarcrest Dr",
    "sg:city":"Bryan",
    "sg:classifiers":[
        {
            "category":"Professional",
            "subcategory":"Employment Agencies",
            "type":"Services"
        }
    ],
    "sg:phone":"+1 979 776 4455",
    "sg:postcode":"77802",
    "sg:province":"TX",
    "sg:tags":[
        "opportunity"
    ],
    "sg:website":"www.expresspersonnel.com",
    "wof:name":"Express Personnel Svc",
    "wof:placetype":"venue"
},
  "geometry": {"coordinates":[-96.336139,30.655527],"type":"Point"}
}