{
  "type": "Feature",
  "properties": {
    "iso:country":"US",
    "sg:address":"5432 E Lancaster Ave",
    "sg:city":"Fort Worth",
    "sg:classifiers":[
        {
            "category":"Building & Trades",
            "subcategory":"Plumbing",
            "type":"Services"
        }
    ],
    "sg:phone":"+1 817 480 4343",
    "sg:postcode":"76112",
    "sg:province":"TX",
    "sg:tags":[
        "conditioning",
        "air",
        "system",
        "contractor"
    ],
    "wof:name":"Save Way Svc",
    "wof:placetype":"venue"
},
  "geometry": {"coordinates":[-97.23724300000001,32.739126],"type":"Point"}
}