{
  "type": "Feature",
  "properties": {
    "iso:country":"US",
    "sg:address":"811 Meadow Dr",
    "sg:city":"Wylie",
    "sg:classifiers":[
        {
            "category":"Professional",
            "type":"Services"
        }
    ],
    "sg:phone":"+1 972 442 7404",
    "sg:postcode":"75098",
    "sg:province":"TX",
    "wof:name":"Aaron Buford Co",
    "wof:placetype":"venue"
},
  "geometry": {"coordinates":[-96.52772299999999,32.981557],"type":"Point"}
}