{
  "type": "Feature",
  "properties": {
    "iso:country":"US",
    "sg:address":"10205 Natalie Dr",
    "sg:city":"Frisco",
    "sg:classifiers":[
        {
            "category":"Building & Trades",
            "subcategory":"Landscaping Services",
            "type":"Services"
        }
    ],
    "sg:phone":"+1 972 335 2162",
    "sg:postcode":"75035",
    "sg:province":"TX",
    "sg:tags":[
        "landscape"
    ],
    "wof:name":"Viktorin & Assoc",
    "wof:placetype":"venue"
},
  "geometry": {"coordinates":[-96.789978,33.112613],"type":"Point"}
}