{
  "type": "Feature",
  "properties": {
    "iso:country":"US",
    "sg:address":"7302 Alabonson Rd",
    "sg:city":"Houston",
    "sg:classifiers":[
        {
            "category":"Professional",
            "subcategory":"Lawyer & Legal Services",
            "type":"Services"
        }
    ],
    "sg:phone":"+1 281 447 8449",
    "sg:postcode":"77088",
    "sg:province":"TX",
    "wof:name":"Daniel Ted C Atty",
    "wof:placetype":"venue"
},
  "geometry": {"coordinates":[-95.48138,29.875453],"type":"Point"}
}