{
  "type": "Feature",
  "properties": {
    "iso:country":"US",
    "sg:address":"310 W Alameda St",
    "sg:city":"Iowa Park",
    "sg:classifiers":[
        {
            "category":"Health Services",
            "subcategory":"Doctor",
            "type":"Services"
        }
    ],
    "sg:phone":"+1 940 592 4141",
    "sg:postcode":"76367",
    "sg:province":"TX",
    "sg:tags":[
        "physician",
        "surgeon"
    ],
    "wof:name":"Park Clinic",
    "wof:placetype":"venue"
},
  "geometry": {"coordinates":[-98.671561,33.955466],"type":"Point"}
}