{
  "type": "Feature",
  "properties": {
    "iso:country":"US",
    "sg:address":"509 Avenue H",
    "sg:city":"Poteet",
    "sg:classifiers":[
        {
            "category":"Wholesale",
            "subcategory":"Hardware",
            "type":"Manufacturing & Wholesale Goods"
        },
        {
            "category":"Home & Garden",
            "subcategory":"Garden Supply",
            "type":"Retail Goods"
        },
        {
            "category":"Retail",
            "subcategory":"Repair Shop",
            "type":"Services"
        }
    ],
    "sg:phone":"+1 800 880 8722",
    "sg:postcode":"78065",
    "sg:province":"TX",
    "sg:tags":[
        "renting",
        "lawn",
        "outdoor",
        "power",
        "landscaping",
        "equipment-sales",
        "equipment",
        "saw"
    ],
    "sg:website":"http://www.stihldealer.net/default-dealer-041328.aspx",
    "wof:name":"Tuttle Motor & Hardware Company",
    "wof:placetype":"venue"
},
  "geometry": {"coordinates":[-98.574465,29.037364],"type":"Point"}
}