{
  "type": "Feature",
  "properties": {
    "iso:country":"US",
    "sg:address":"2605 Chapman St",
    "sg:city":"Houston",
    "sg:classifiers":[
        {
            "category":"Wholesale",
            "subcategory":"Hardware",
            "type":"Manufacturing & Wholesale Goods"
        }
    ],
    "sg:phone":"+1 713 223 8495",
    "sg:postcode":"77009",
    "sg:province":"TX",
    "sg:tags":[
        "pipe",
        "product"
    ],
    "wof:name":"R Smith & Son Inc",
    "wof:placetype":"venue"
},
  "geometry": {"coordinates":[-95.354034,29.786327],"type":"Point"}
}