{
  "type": "Feature",
  "properties": {
    "iso:country":"US",
    "sg:address":"9490 Vernon Ln",
    "sg:city":"Belton",
    "sg:classifiers":[
        {
            "category":"Manufacturing",
            "subcategory":"Apparel",
            "type":"Manufacturing & Wholesale Goods"
        }
    ],
    "sg:phone":"+1 254 933 8160",
    "sg:postcode":"76513",
    "sg:province":"TX",
    "sg:tags":[
        "mfg"
    ],
    "wof:name":"Capes & More By Ladi Red",
    "wof:placetype":"venue"
},
  "geometry": {"coordinates":[-97.56036400000001,31.084324],"type":"Point"}
}