{
  "type": "Feature",
  "properties": {
    "iso:country":"US",
    "sg:address":"4564 Doniphan Dr",
    "sg:city":"El Paso",
    "sg:classifiers":[
        {
            "category":"Wholesale",
            "subcategory":"Home Furnishings",
            "type":"Manufacturing & Wholesale Goods"
        }
    ],
    "sg:phone":"+1 915 585 1174",
    "sg:postcode":"79922",
    "sg:province":"TX",
    "sg:tags":[
        "leather",
        "blanket",
        "rug"
    ],
    "wof:name":"El Paso Trading Post",
    "wof:placetype":"venue"
},
  "geometry": {"coordinates":[-106.574139,31.832655],"type":"Point"}
}