{
  "type": "Feature",
  "properties": {
    "iso:country":"US",
    "sg:address":"102 N Main St",
    "sg:city":"Duncanville",
    "sg:classifiers":[
        {
            "category":"Organizations",
            "subcategory":"Religious Organization",
            "type":"Services"
        }
    ],
    "sg:phone":"+1 972 709 7951",
    "sg:postcode":"75116",
    "sg:province":"TX",
    "sg:tags":[
        "church"
    ],
    "wof:name":"Saint Luke Christian Ctr",
    "wof:placetype":"venue"
},
  "geometry": {"coordinates":[-96.908394,32.652596],"type":"Point"}
}