{
  "type": "Feature",
  "properties": {
    "iso:country":"US",
    "sg:address":"120 E Constitution St",
    "sg:city":"Victoria",
    "sg:classifiers":[
        {
            "category":"Real Estate",
            "subcategory":"Real Estate Operator",
            "type":"Services"
        }
    ],
    "sg:phone":"+1 361 580 3488",
    "sg:postcode":"77901",
    "sg:province":"TX",
    "sg:tags":[
        "mobile",
        "home",
        "community"
    ],
    "wof:name":"Crescent Valley Meadows",
    "wof:placetype":"venue"
},
  "geometry": {"coordinates":[-97.005195,28.798975],"type":"Point"}
}