{
  "type": "Feature",
  "properties": {
    "iso:country":"US",
    "sg:address":"5310 Belt Line Rd",
    "sg:city":"Dallas",
    "sg:classifiers":[
        {
            "category":"Shopping",
            "subcategory":"Florist",
            "type":"Retail Goods"
        }
    ],
    "sg:phone":"+1 972 386 5010",
    "sg:postcode":"75254",
    "sg:province":"TX",
    "sg:website":"www.atouchofclassflorist.com",
    "wof:name":"A Touch of Class Florist",
    "wof:placetype":"venue"
},
  "geometry": {"coordinates":[-96.814003,32.9538],"type":"Point"}
}