{
  "type": "Feature",
  "properties": {
    "iso:country":"US",
    "sg:address":"2817 Fillmore Ave",
    "sg:city":"El Paso",
    "sg:classifiers":[
        {
            "category":"Building & Trades",
            "subcategory":"Electrical",
            "type":"Services"
        }
    ],
    "sg:phone":"+1 915 566 0624",
    "sg:postcode":"79930",
    "sg:province":"TX",
    "sg:tags":[
        "electrical",
        "contractor"
    ],
    "wof:name":"Mp 2 Electric",
    "wof:placetype":"venue"
},
  "geometry": {"coordinates":[-106.46160399999999,31.817506],"type":"Point"}
}