{
  "type": "Feature",
  "properties": {
    "iso:country":"US",
    "sg:address":"517 Shiloh Dr",
    "sg:city":"Laredo",
    "sg:classifiers":[
        {
            "category":"Recreation",
            "subcategory":"Amusement Park",
            "type":"Entertainment"
        },
        {
            "category":"Recreation",
            "subcategory":"Picnic Area",
            "type":"Entertainment"
        }
    ],
    "sg:phone":"+1 956 724 9200",
    "sg:postcode":"78045",
    "sg:province":"TX",
    "sg:tags":[
        "equipment",
        "ride",
        "place",
        "arcade"
    ],
    "wof:name":"Lucky Venus",
    "wof:placetype":"venue"
},
  "geometry": {"coordinates":[-99.495098,27.586376],"type":"Point"}
}