{
  "type": "Feature",
  "properties": {
    "iso:country":"US",
    "sg:address":"2615 Lake Ledge",
    "sg:city":"San Antonio",
    "sg:classifiers":[
        {
            "category":"Professional",
            "subcategory":"Lawyer & Legal Services",
            "type":"Services"
        },
        {
            "category":"Professional",
            "subcategory":"Computer Services",
            "type":"Services"
        }
    ],
    "sg:phone":"+1 210 648 5119",
    "sg:postcode":"78222",
    "sg:province":"TX",
    "sg:tags":[
        "prepackaged",
        "plan",
        "software"
    ],
    "wof:name":"B J Distributors",
    "wof:placetype":"venue"
},
  "geometry": {"coordinates":[-98.37735000000001,29.39274],"type":"Point"}
}