{
  "type": "Feature",
  "properties": {
    "iso:country":"US",
    "sg:address":"3901 N Glasscock Rd",
    "sg:city":"Mission",
    "sg:classifiers":[
        {
            "category":"Manufacturing",
            "subcategory":"Buildings",
            "type":"Manufacturing & Wholesale Goods"
        },
        {
            "category":"Building & Trades",
            "subcategory":"Construction",
            "type":"Services"
        }
    ],
    "sg:phone":"+1 956 581 4672",
    "sg:postcode":"78573",
    "sg:province":"TX",
    "sg:tags":[
        "home",
        "builder",
        "contractor"
    ],
    "wof:name":"Breman Construction",
    "wof:placetype":"venue"
},
  "geometry": {"coordinates":[-98.287256,26.250657],"type":"Point"}
}