{
  "type": "Feature",
  "properties": {
    "iso:country":"US",
    "sg:address":"1419 E Adams St",
    "sg:city":"Brownsville",
    "sg:classifiers":[
        {
            "category":"Restaurant",
            "type":"Food & Drink"
        }
    ],
    "sg:phone":"+1 956 542 0469",
    "sg:postcode":"78520",
    "sg:province":"TX",
    "wof:name":"El Expreso",
    "wof:placetype":"venue"
},
  "geometry": {"coordinates":[-97.49460999999999,25.900424],"type":"Point"}
}