{
  "type": "Feature",
  "properties": {
    "iso:country":"US",
    "sg:address":"8414 Mosshang Ct",
    "sg:city":"Houston",
    "sg:classifiers":[
        {
            "category":"Professional",
            "subcategory":"Credit Reporting & Collection",
            "type":"Services"
        }
    ],
    "sg:phone":"+1 713 466 6688",
    "sg:postcode":"77040",
    "sg:province":"TX",
    "wof:name":"Credit Mgt Consulting Co",
    "wof:placetype":"venue"
},
  "geometry": {"coordinates":[-95.528132,29.896147],"type":"Point"}
}