{
  "type": "Feature",
  "properties": {
    "iso:country":"US",
    "sg:address":"502 W Front St",
    "sg:city":"Alice",
    "sg:classifiers":[
        {
            "category":"Shopping",
            "subcategory":"Music",
            "type":"Retail Goods"
        }
    ],
    "sg:phone":"+1 361 668 1535",
    "sg:postcode":"78332",
    "sg:province":"TX",
    "wof:name":"Tejano Party Music Store",
    "wof:placetype":"venue"
},
  "geometry": {"coordinates":[-98.081149,27.747336],"type":"Point"}
}