{
  "type": "Feature",
  "properties": {
    "iso:country":"US",
    "sg:address":"1834 Arrowhead Ct",
    "sg:city":"Missouri City",
    "sg:classifiers":[
        {
            "category":"Professional",
            "type":"Services"
        }
    ],
    "sg:phone":"+1 281 298 3154",
    "sg:postcode":"77459",
    "sg:province":"TX",
    "wof:name":"Allnighters",
    "wof:placetype":"venue"
},
  "geometry": {"coordinates":[-95.530512,29.568861],"type":"Point"}
}