{
  "type": "Feature",
  "properties": {
    "iso:country":"US",
    "sg:address":"13506 Royal Fifth Ct",
    "sg:city":"Corpus Christi",
    "sg:classifiers":[
        {
            "category":"Restaurant",
            "type":"Food & Drink"
        }
    ],
    "sg:phone":"+1 361 949 8240",
    "sg:postcode":"78418",
    "sg:province":"TX",
    "sg:tags":[
        "eating"
    ],
    "wof:name":"Alpers Island Subs Inc",
    "wof:placetype":"venue"
},
  "geometry": {"coordinates":[-97.244376,27.604219],"type":"Point"}
}