{
  "type": "Feature",
  "properties": {
    "iso:country":"US",
    "sg:address":"813 S W S Young Dr",
    "sg:city":"Killeen",
    "sg:classifiers":[
        {
            "category":"Organizations",
            "subcategory":"Religious Organization",
            "type":"Services"
        }
    ],
    "sg:phone":"+1 254 690 6500",
    "sg:postcode":"76543",
    "sg:province":"TX",
    "sg:tags":[
        "church"
    ],
    "wof:name":"Philadelphia Mission Ctr",
    "wof:placetype":"venue"
},
  "geometry": {"coordinates":[-97.716645,31.106818],"type":"Point"}
}