{
  "type": "Feature",
  "properties": {
    "iso:country":"US",
    "sg:address":"15931 Spinnaker Dr",
    "sg:city":"Crosby",
    "sg:classifiers":[
        {
            "category":"Real Estate",
            "subcategory":"Real Estate Operator",
            "type":"Services"
        }
    ],
    "sg:phone":"+1 281 328 1073",
    "sg:postcode":"77532",
    "sg:province":"TX",
    "sg:tags":[
        "building",
        "nonresidential"
    ],
    "wof:name":"Johnson Properties Independent",
    "wof:placetype":"venue"
},
  "geometry": {"coordinates":[-95.084558,29.912146],"type":"Point"}
}