{
  "type": "Feature",
  "properties": {
    "iso:country":"US",
    "sg:address":"9220 Skillman St",
    "sg:city":"Dallas",
    "sg:classifiers":[
        {
            "category":"Restaurant",
            "type":"Food & Drink"
        }
    ],
    "sg:menulink":"http://www.allmenus.com/tx/northeast/139412-quiznos-sub/menu/",
    "sg:phone":"+1 214 348 1540",
    "sg:postcode":"75243",
    "sg:province":"TX",
    "sg:tags":[
        "wrap",
        "american",
        "sandwich"
    ],
    "wof:name":"Quiznos Sub",
    "wof:placetype":"venue"
},
  "geometry": {"coordinates":[-96.714281,32.902513],"type":"Point"}
}