{
  "type": "Feature",
  "properties": {
    "iso:country":"US",
    "sg:address":"6501 W William Cannon Dr",
    "sg:city":"Austin",
    "sg:classifiers":[
        {
            "category":"Banks & Credit Unions",
            "subcategory":"Bank",
            "type":"Services"
        }
    ],
    "sg:phone":"+1 512 996 4000",
    "sg:postcode":"78735",
    "sg:province":"TX",
    "sg:tags":[
        "loan"
    ],
    "wof:name":"Tru West Credit Union",
    "wof:placetype":"venue"
},
  "geometry": {"coordinates":[-97.865532,30.235961],"type":"Point"}
}