{
  "type": "Feature",
  "properties": {
    "iso:country":"US",
    "sg:address":"804 N 10th St",
    "sg:city":"Killeen",
    "sg:classifiers":[
        {
            "category":"Personal",
            "subcategory":"Barber",
            "type":"Services"
        }
    ],
    "sg:phone":"+1 254 634 9779",
    "sg:postcode":"76541",
    "sg:province":"TX",
    "sg:tags":[
        "shop"
    ],
    "wof:name":"Chong Barber Shop",
    "wof:placetype":"venue"
},
  "geometry": {"coordinates":[-97.723923,31.123875],"type":"Point"}
}