{
  "type": "Feature",
  "properties": {
    "iso:country":"US",
    "sg:address":"1300 N 10th St",
    "sg:city":"Mcallen",
    "sg:classifiers":[
        {
            "category":"Health Services",
            "subcategory":"Clinic",
            "type":"Services"
        }
    ],
    "sg:phone":"+1 956 664 8160",
    "sg:postcode":"78501",
    "sg:province":"TX",
    "sg:tags":[
        "home"
    ],
    "wof:name":"IPH-Community Based Asstnc",
    "wof:placetype":"venue"
},
  "geometry": {"coordinates":[-98.228075,26.214349],"type":"Point"}
}