{
  "type": "Feature",
  "properties": {
    "iso:country":"US",
    "sg:address":"2609 Thornton Ln",
    "sg:city":"Temple",
    "sg:classifiers":[
        {
            "category":"Restaurant",
            "type":"Food & Drink"
        }
    ],
    "sg:phone":"+1 254 773 3059",
    "sg:postcode":"76502",
    "sg:province":"TX",
    "sg:tags":[
        "eating"
    ],
    "wof:name":"Ry's Burgers",
    "wof:placetype":"venue"
},
  "geometry": {"coordinates":[-97.380984,31.076366],"type":"Point"}
}