{
  "type": "Feature",
  "properties": {
    "iso:country":"US",
    "sg:address":"200 Concord Plaza Dr",
    "sg:city":"San Antonio",
    "sg:classifiers":[
        {
            "category":"Professional",
            "subcategory":"Management & Consulting",
            "type":"Services"
        }
    ],
    "sg:phone":"+1 210 930 4545",
    "sg:postcode":"78216",
    "sg:province":"TX",
    "sg:tags":[
        "consultant",
        "business"
    ],
    "wof:name":"Gonzaba Management Group",
    "wof:placetype":"venue"
},
  "geometry": {"coordinates":[-98.480386,29.505682],"type":"Point"}
}