{
  "type": "Feature",
  "properties": {
    "iso:country":"US",
    "sg:address":"2011 N Collins Blvd",
    "sg:city":"Richardson",
    "sg:classifiers":[
        {
            "category":"Health Services",
            "subcategory":"Doctor",
            "type":"Services"
        }
    ],
    "sg:phone":"+1 972 437 5320",
    "sg:postcode":"75080",
    "sg:province":"TX",
    "sg:tags":[
        "clinic"
    ],
    "wof:name":"Texas Medical Diagnostics",
    "wof:placetype":"venue"
},
  "geometry": {"coordinates":[-96.72290599999999,32.976865],"type":"Point"}
}