{
  "type": "Feature",
  "properties": {
    "iso:country":"US",
    "sg:address":"2701 N Stemmons Fwy",
    "sg:city":"Dallas",
    "sg:classifiers":[
        {
            "category":"Restaurant",
            "type":"Food & Drink"
        }
    ],
    "sg:phone":"+1 214 920 9240",
    "sg:postcode":"75207",
    "sg:province":"TX",
    "sg:tags":[
        "mexican"
    ],
    "sg:website":"www.jpepes.com",
    "wof:name":"J Pepes",
    "wof:placetype":"venue"
},
  "geometry": {"coordinates":[-96.84247000000001,32.807],"type":"Point"}
}