{
  "type": "Feature",
  "properties": {
    "iso:country":"US",
    "sg:address":"12255 Huebner Rd",
    "sg:city":"San Antonio",
    "sg:classifiers":[
        {
            "category":"Home & Garden",
            "subcategory":"Furniture",
            "type":"Retail Goods"
        }
    ],
    "sg:phone":"+1 210 495 3227",
    "sg:postcode":"78230",
    "sg:province":"TX",
    "wof:name":"Wholesale Art & Furniture Gall",
    "wof:placetype":"venue"
},
  "geometry": {"coordinates":[-98.567142,29.555681],"type":"Point"}
}