{
  "type": "Feature",
  "properties": {
    "iso:country":"US",
    "sg:address":"1106 Edwards Ct S",
    "sg:city":"Irving",
    "sg:classifiers":[
        {
            "category":"Professional",
            "subcategory":"Lawyer & Legal Services",
            "type":"Services"
        }
    ],
    "sg:phone":"+1 972 659 0102",
    "sg:postcode":"75062",
    "sg:province":"TX",
    "wof:name":"Bradford Douglas E Attorney At Law",
    "wof:placetype":"venue"
},
  "geometry": {"coordinates":[-96.959204,32.854975],"type":"Point"}
}