{
  "type": "Feature",
  "properties": {
    "iso:country":"US",
    "sg:address":"530 N Gulf Blvd",
    "sg:city":"Freeport",
    "sg:classifiers":[
        {
            "category":"Shopping",
            "subcategory":"Clothing, Apparel, & Fashions",
            "type":"Retail Goods"
        }
    ],
    "sg:phone":"+1 979 233 1448",
    "sg:postcode":"77541",
    "sg:province":"TX",
    "sg:tags":[
        "alteration"
    ],
    "wof:name":"Creations By Rosa",
    "wof:placetype":"venue"
},
  "geometry": {"coordinates":[-95.364642,28.965881],"type":"Point"}
}