{
  "type": "Feature",
  "properties": {
    "iso:country":"US",
    "sg:address":"5803 Sovereign Dr",
    "sg:city":"Houston",
    "sg:classifiers":[
        {
            "category":"Shopping",
            "subcategory":"Computers & Home Electronics",
            "type":"Retail Goods"
        }
    ],
    "sg:phone":"+1 713 776 8866",
    "sg:postcode":"77036",
    "sg:province":"TX",
    "wof:name":"P C Wave",
    "wof:placetype":"venue"
},
  "geometry": {"coordinates":[-95.55382,29.716625],"type":"Point"}
}