{
  "type": "Feature",
  "properties": {
    "iso:country":"US",
    "sg:address":"3207 Daisy St",
    "sg:city":"Pasadena",
    "sg:classifiers":[
        {
            "category":"Personal",
            "type":"Services"
        }
    ],
    "sg:phone":"+1 281 487 7887",
    "sg:postcode":"77505",
    "sg:province":"TX",
    "sg:tags":[
        "towing"
    ],
    "wof:name":"Eady's Salvage & Wrecker Service",
    "wof:placetype":"venue"
},
  "geometry": {"coordinates":[-95.16480300000001,29.663799],"type":"Point"}
}