{
  "type": "Feature",
  "properties": {
    "iso:country":"US",
    "sg:address":"1923 Hoskins Dr",
    "sg:city":"Houston",
    "sg:classifiers":[
        {
            "category":"Wholesale",
            "subcategory":"Hardware",
            "type":"Manufacturing & Wholesale Goods"
        }
    ],
    "sg:phone":"+1 713 975 9222",
    "sg:postcode":"77080",
    "sg:province":"TX",
    "sg:tags":[
        "condensing",
        "refrigeration",
        "unit"
    ],
    "wof:name":"Thermo Parts Supply Inc",
    "wof:placetype":"venue"
},
  "geometry": {"coordinates":[-95.522859,29.808109],"type":"Point"}
}