{
  "type": "Feature",
  "properties": {
    "iso:country":"US",
    "sg:address":"1009 S 13th St",
    "sg:city":"Longview",
    "sg:classifiers":[
        {
            "category":"Education",
            "subcategory":"Special Training",
            "type":"Public Place"
        }
    ],
    "sg:phone":"+1 903 874 4023",
    "sg:postcode":"75602",
    "sg:province":"TX",
    "sg:tags":[
        "center"
    ],
    "wof:name":"Navarro Alternative Edu Prgm",
    "wof:placetype":"venue"
},
  "geometry": {"coordinates":[-94.72122,32.480616],"type":"Point"}
}