{
  "type": "Feature",
  "properties": {
    "iso:country":"US",
    "sg:address":"10344 Ferguson Rd",
    "sg:city":"Dallas",
    "sg:classifiers":[
        {
            "category":"Professional",
            "subcategory":"Accounting & Tax Preparation",
            "type":"Services"
        }
    ],
    "sg:phone":"+1 214 321 7903",
    "sg:postcode":"75228",
    "sg:province":"TX",
    "sg:tags":[
        "return"
    ],
    "wof:name":"K-Tax",
    "wof:placetype":"venue"
},
  "geometry": {"coordinates":[-96.67215299999999,32.835898],"type":"Point"}
}