{
  "type": "Feature",
  "properties": {
    "iso:country":"US",
    "sg:address":"8801 Whiteworth Loop",
    "sg:city":"Austin",
    "sg:classifiers":[
        {
            "category":"Professional",
            "subcategory":"Art Services",
            "type":"Services"
        }
    ],
    "sg:phone":"+1 512 292 7988",
    "sg:postcode":"78749",
    "sg:province":"TX",
    "sg:tags":[
        "design",
        "graphic",
        "commercial",
        "designer"
    ],
    "wof:name":"Magda Dot Webdesign",
    "wof:placetype":"venue"
},
  "geometry": {"coordinates":[-97.85813899999999,30.19976],"type":"Point"}
}