{
  "type": "Feature",
  "properties": {
    "iso:country":"US",
    "sg:address":"7038 Alameda Ave",
    "sg:city":"El Paso",
    "sg:classifiers":[
        {
            "category":"Shopping",
            "type":"Retail Goods"
        }
    ],
    "sg:phone":"+1 915 781 0188",
    "sg:postcode":"79915",
    "sg:province":"TX",
    "sg:tags":[
        "candle"
    ],
    "wof:name":"Botanica Ogunochun",
    "wof:placetype":"venue"
},
  "geometry": {"coordinates":[-106.395422,31.756162],"type":"Point"}
}