{
  "type": "Feature",
  "properties": {
    "iso:country":"US",
    "sg:address":"525 Co Rd 275",
    "sg:city":"Round Rock",
    "sg:classifiers":[
        {
            "category":"Professional",
            "subcategory":"Engineering",
            "type":"Services"
        }
    ],
    "sg:phone":"+1 512 828 3661",
    "sg:postcode":"78641",
    "sg:province":"TX",
    "sg:tags":[
        "electrical",
        "electronic",
        "or"
    ],
    "wof:name":"D2m Technologies",
    "wof:placetype":"venue"
},
  "geometry": {"coordinates":[-97.849976,30.556164],"type":"Point"}
}