{
  "type": "Feature",
  "properties": {
    "iso:country":"US",
    "sg:address":"3545 W Walnut St",
    "sg:city":"Garland",
    "sg:classifiers":[
        {
            "category":"Restaurant",
            "type":"Food & Drink"
        }
    ],
    "sg:phone":"+1 972 494 4913",
    "sg:postcode":"75042",
    "sg:province":"TX",
    "wof:name":"La Paloma Taqueria",
    "wof:placetype":"venue"
},
  "geometry": {"coordinates":[-96.684196,32.917099],"type":"Point"}
}