{
  "type": "Feature",
  "properties": {
    "iso:country":"US",
    "sg:address":"18601 Lyndon B Johnson Fwy",
    "sg:city":"Mesquite",
    "sg:classifiers":[
        {
            "category":"Insurance",
            "subcategory":"Insurance Agent",
            "type":"Services"
        },
        {
            "category":"Insurance",
            "subcategory":"Hazard Insurance",
            "type":"Services"
        },
        {
            "category":"Insurance",
            "subcategory":"Title Insurance",
            "type":"Services"
        },
        {
            "category":"Insurance",
            "subcategory":"Life Insurance",
            "type":"Services"
        }
    ],
    "sg:phone":"+1 469 619 4609",
    "sg:postcode":"75150",
    "sg:province":"TX",
    "sg:tags":[
        "business",
        "auto",
        "commercial",
        "homeowner",
        "motorcycle",
        "renter"
    ],
    "wof:name":"Allstate Insurance Company - Randy Lamm",
    "wof:placetype":"venue"
},
  "geometry": {"coordinates":[-96.627296,32.803347],"type":"Point"}
}