{
  "type": "Feature",
  "properties": {
    "iso:country":"US",
    "sg:address":"544 Ridgemont Dr",
    "sg:city":"El Paso",
    "sg:classifiers":[
        {
            "category":"Professional",
            "subcategory":"Detective & Security Services",
            "type":"Services"
        }
    ],
    "sg:phone":"+1 915 842 9415",
    "sg:postcode":"79912",
    "sg:province":"TX",
    "sg:tags":[
        "investigator"
    ],
    "wof:name":"Carl Hanly Accident & Insuranc",
    "wof:placetype":"venue"
},
  "geometry": {"coordinates":[-106.53566600000001,31.819137],"type":"Point"}
}