{
  "type": "Feature",
  "properties": {
    "iso:country":"US",
    "sg:address":"12777 Jones Rd",
    "sg:city":"Houston",
    "sg:classifiers":[
        {
            "category":"Wholesale",
            "subcategory":"Machinery & Supplies",
            "type":"Manufacturing & Wholesale Goods"
        }
    ],
    "sg:phone":"+1 281 807 0890",
    "sg:postcode":"77070",
    "sg:province":"TX",
    "sg:tags":[
        "dam",
        "inflatable",
        "container",
        "liner"
    ],
    "wof:name":"Hydrological Solutions",
    "wof:placetype":"venue"
},
  "geometry": {"coordinates":[-95.585098,29.958758],"type":"Point"}
}