{
  "type": "Feature",
  "properties": {
    "iso:country":"US",
    "sg:address":"4223 Apollo St",
    "sg:city":"Houston",
    "sg:classifiers":[
        {
            "category":"Health Services",
            "subcategory":"Health Practitioner",
            "type":"Services"
        }
    ],
    "sg:phone":"+1 713 812 7665",
    "sg:postcode":"77018",
    "sg:province":"TX",
    "wof:name":"Communication Frontiers PC",
    "wof:placetype":"venue"
},
  "geometry": {"coordinates":[-95.428487,29.82717],"type":"Point"}
}