{
  "type": "Feature",
  "properties": {
    "iso:country":"US",
    "sg:address":"1302 Merlene Dr",
    "sg:city":"Austin",
    "sg:classifiers":[
        {
            "category":"Building & Trades",
            "subcategory":"Plumbing",
            "type":"Services"
        }
    ],
    "sg:phone":"+1 512 258 8414",
    "sg:postcode":"78732",
    "sg:province":"TX",
    "sg:tags":[
        "plumbing",
        "contractor"
    ],
    "wof:name":"Capitol Plumbing",
    "wof:placetype":"venue"
},
  "geometry": {"coordinates":[-97.923963,30.331671],"type":"Point"}
}