{
  "type": "Feature",
  "properties": {
    "iso:country":"US",
    "sg:address":"313 W Main St",
    "sg:city":"Archer City",
    "sg:classifiers":[
        {
            "category":"Government",
            "subcategory":"Office",
            "type":"Public Place"
        }
    ],
    "sg:phone":"+1 817 574 4612",
    "sg:postcode":"76351",
    "sg:province":"TX",
    "sg:tags":[
        "farm",
        "agency"
    ],
    "wof:name":"Farm Service Agency",
    "wof:placetype":"venue"
},
  "geometry": {"coordinates":[-98.629879,33.596381],"type":"Point"}
}