{
  "type": "Feature",
  "properties": {
    "iso:country":"US",
    "sg:address":"2010 Alameda Drive",
    "sg:city":"Austin",
    "sg:classifiers":[
        {
            "category":"Education",
            "subcategory":"School",
            "type":"Public Place"
        }
    ],
    "sg:phone":"+1 512 414 4495",
    "sg:postcode":"78704",
    "sg:province":"TX",
    "wof:name":"Austin Independent School District",
    "wof:placetype":"venue"
},
  "geometry": {"coordinates":[-97.745476,30.241445],"type":"Point"}
}