{
  "type": "Feature",
  "properties": {
    "iso:country":"US",
    "sg:address":"7025 Cattle Dr",
    "sg:city":"Fort Worth",
    "sg:classifiers":[
        {
            "category":"Professional",
            "type":"Services"
        }
    ],
    "sg:phone":"+1 817 236 5194",
    "sg:postcode":"76179",
    "sg:province":"TX",
    "sg:tags":[
        "establishment"
    ],
    "wof:name":"Marketing Services",
    "wof:placetype":"venue"
},
  "geometry": {"coordinates":[-97.43271300000001,32.866158],"type":"Point"}
}