{
  "type": "Feature",
  "properties": {
    "iso:country":"US",
    "sg:address":"1970 Rebecca Creek Rd",
    "sg:city":"Canyon Lake",
    "sg:classifiers":[
        {
            "category":"Wholesale",
            "subcategory":"Construction Materials",
            "type":"Manufacturing & Wholesale Goods"
        }
    ],
    "sg:phone":"+1 830 228 5985",
    "sg:postcode":"78133",
    "sg:province":"TX",
    "sg:tags":[
        "granite"
    ],
    "wof:name":"A2Z Granite & Tile Inc",
    "wof:placetype":"venue"
},
  "geometry": {"coordinates":[-98.33892,29.833482],"type":"Point"}
}