{
  "type": "Feature",
  "properties": {
    "iso:country":"US",
    "sg:address":"19133 Big Oak Dr",
    "sg:city":"Conroe",
    "sg:classifiers":[
        {
            "category":"Freight",
            "type":"Transportation"
        }
    ],
    "sg:phone":"+1 281 572 1987",
    "sg:postcode":"77302",
    "sg:province":"TX",
    "wof:name":"Joes Mobile Home Puller",
    "wof:placetype":"venue"
},
  "geometry": {"coordinates":[-95.27531500000001,30.197297],"type":"Point"}
}