{
  "type": "Feature",
  "properties": {
    "iso:country":"US",
    "sg:address":"2830 Lotus St",
    "sg:city":"Harlingen",
    "sg:classifiers":[
        {
            "category":"Building & Trades",
            "subcategory":"Electrical",
            "type":"Services"
        }
    ],
    "sg:phone":"+1 956 423 2673",
    "sg:postcode":"78550",
    "sg:province":"TX",
    "sg:tags":[
        "industrial",
        "electrician",
        "contractors-commercial",
        "electric"
    ],
    "wof:name":"Ruben's Electric",
    "wof:placetype":"venue"
},
  "geometry": {"coordinates":[-97.661126,26.180787],"type":"Point"}
}