{
  "type": "Feature",
  "properties": {
    "iso:country":"US",
    "sg:address":"3115 S 1st St",
    "sg:city":"Austin",
    "sg:classifiers":[
        {
            "category":"Food & Beverages",
            "subcategory":"Specialty",
            "type":"Retail Goods"
        }
    ],
    "sg:phone":"+1 512 383 9799",
    "sg:postcode":"78704",
    "sg:province":"TX",
    "wof:name":"Coffee Bar",
    "wof:placetype":"venue"
},
  "geometry": {"coordinates":[-97.764917,30.233585],"type":"Point"}
}