{
  "type": "Feature",
  "properties": {
    "iso:country":"US",
    "sg:address":"40 W Twohig Ave",
    "sg:city":"San Angelo",
    "sg:classifiers":[
        {
            "category":"Banks & Credit Unions",
            "subcategory":"Bank",
            "type":"Services"
        }
    ],
    "sg:phone":"+1 325 658 5065",
    "sg:postcode":"76903",
    "sg:province":"TX",
    "sg:tags":[
        "loan"
    ],
    "wof:name":"Bridge Loan Funding",
    "wof:placetype":"venue"
},
  "geometry": {"coordinates":[-100.437344,31.460993],"type":"Point"}
}