{
  "type": "Feature",
  "properties": {
    "iso:country":"US",
    "sg:address":"5809 Highland Hills Dr",
    "sg:city":"Austin",
    "sg:classifiers":[
        {
            "category":"Professional",
            "type":"Services"
        }
    ],
    "sg:phone":"+1 512 458 1400",
    "sg:postcode":"78731",
    "sg:province":"TX",
    "wof:name":"Nfnt Inc",
    "wof:placetype":"venue"
},
  "geometry": {"coordinates":[-97.75947499999999,30.343232],"type":"Point"}
}