{
  "type": "Feature",
  "properties": {
    "iso:country":"US",
    "sg:address":"303 W Veterans Memorial Blvd",
    "sg:city":"Killeen",
    "sg:classifiers":[
        {
            "category":"Autos & Motor Vehicles",
            "subcategory":"Auto Supplies",
            "type":"Retail Goods"
        }
    ],
    "sg:phone":"+1 254 616 5955",
    "sg:postcode":"76541",
    "sg:province":"TX",
    "sg:tags":[
        "tire"
    ],
    "wof:name":"A Better Buy Tire & Glass",
    "wof:placetype":"venue"
},
  "geometry": {"coordinates":[-97.734182,31.118596],"type":"Point"}
}