{
  "type": "Feature",
  "properties": {
    "iso:country":"US",
    "sg:address":"4316 S Fannin St",
    "sg:city":"Amarillo",
    "sg:classifiers":[
        {
            "category":"Shopping",
            "subcategory":"Gifts & Souvenirs",
            "type":"Retail Goods"
        }
    ],
    "sg:phone":"+1 806 353 0255",
    "sg:postcode":"79110",
    "sg:province":"TX",
    "sg:tags":[
        "collectible"
    ],
    "wof:name":"Longhorn Valley Trading Co",
    "wof:placetype":"venue"
},
  "geometry": {"coordinates":[-101.860716,35.165908],"type":"Point"}
}