{
  "type": "Feature",
  "properties": {
    "iso:country":"US",
    "sg:address":"1653 Lomaland Dr",
    "sg:city":"El Paso",
    "sg:classifiers":[
        {
            "category":"Shopping",
            "type":"Retail Goods"
        }
    ],
    "sg:phone":"+1 915 592 7908",
    "sg:postcode":"79935",
    "sg:province":"TX",
    "sg:tags":[
        "equipment",
        "telephone",
        "supply"
    ],
    "wof:name":"Datatel Communications",
    "wof:placetype":"venue"
},
  "geometry": {"coordinates":[-106.32999,31.75933],"type":"Point"}
}