{
  "type": "Feature",
  "properties": {
    "iso:country":"US",
    "sg:address":"14022 Sycamore Rd",
    "sg:city":"Cat Spring",
    "sg:classifiers":[
        {
            "category":"Travel",
            "subcategory":"Hotels & Motels",
            "type":"Entertainment"
        }
    ],
    "sg:phone":"+1 979 992 3270",
    "sg:postcode":"78933",
    "sg:province":"TX",
    "sg:tags":[
        "breakfast",
        "accommodation",
        "bed"
    ],
    "wof:name":"Cat Spring's Southwind B & B",
    "wof:placetype":"venue"
},
  "geometry": {"coordinates":[-96.32284199999999,29.874508],"type":"Point"}
}