{
  "type": "Feature",
  "properties": {
    "iso:country":"US",
    "sg:address":"6717 Canal St",
    "sg:city":"Houston",
    "sg:classifiers":[
        {
            "category":"Personal",
            "subcategory":"Beauty Salon",
            "type":"Services"
        }
    ],
    "sg:phone":"+1 713 923 4407",
    "sg:postcode":"77011",
    "sg:province":"TX",
    "wof:name":"El Tapatio",
    "wof:placetype":"venue"
},
  "geometry": {"coordinates":[-95.30482000000001,29.741206],"type":"Point"}
}