{
  "type": "Feature",
  "properties": {
    "iso:country":"US",
    "sg:address":"8527 Enchanted Forest Dr",
    "sg:city":"Houston",
    "sg:classifiers":[
        {
            "category":"Recreation",
            "type":"Entertainment"
        }
    ],
    "sg:phone":"+1 281 447 3933",
    "sg:postcode":"77088",
    "sg:province":"TX",
    "sg:tags":[
        "pool",
        "swimming"
    ],
    "wof:name":"Inwood North HOA Pool II",
    "wof:placetype":"venue"
},
  "geometry": {"coordinates":[-95.474799,29.889705],"type":"Point"}
}