{
  "type": "Feature",
  "properties": {
    "iso:country":"US",
    "sg:address":"2401 Manana St",
    "sg:city":"Austin",
    "sg:classifiers":[
        {
            "category":"Retail",
            "subcategory":"Repair Shop",
            "type":"Services"
        }
    ],
    "sg:phone":"+1 512 346 4390",
    "sg:postcode":"78730",
    "sg:province":"TX",
    "wof:name":"Leota Kay Biggs Custom Im",
    "wof:placetype":"venue"
},
  "geometry": {"coordinates":[-97.8301,30.327407],"type":"Point"}
}