{
  "type": "Feature",
  "properties": {
    "iso:country":"US",
    "sg:address":"5454 FM 1960 W",
    "sg:city":"Houston",
    "sg:classifiers":[
        {
            "category":"Personal",
            "subcategory":"Beauty Salon",
            "type":"Services"
        }
    ],
    "sg:phone":"+1 281 537 0771",
    "sg:postcode":"77069",
    "sg:province":"TX",
    "sg:tags":[
        "shop"
    ],
    "sg:website":"www.alanmurphysalon.com",
    "wof:name":"Alan Murphy Beauty Salon",
    "wof:placetype":"venue"
},
  "geometry": {"coordinates":[-95.50828799999999,29.982267],"type":"Point"}
}