{
  "type": "Feature",
  "properties": {
    "iso:country":"US",
    "sg:address":"4419 Frontier Trl Ste 101",
    "sg:city":"Austin",
    "sg:classifiers":[
        {
            "category":"Professional",
            "subcategory":"Detective & Security Services",
            "type":"Services"
        }
    ],
    "sg:phone":"+1 512 719 4310",
    "sg:postcode":"78745",
    "sg:province":"TX",
    "sg:tags":[
        "guard",
        "patrol"
    ],
    "wof:name":"Chapparal Business Security",
    "wof:placetype":"venue"
},
  "geometry": {"coordinates":[-97.79477300000001,30.232003],"type":"Point"}
}