{
  "type": "Feature",
  "properties": {
    "iso:country":"US",
    "sg:address":"4101 Mockingbird Ln",
    "sg:city":"Amarillo",
    "sg:classifiers":[
        {
            "category":"Wholesale",
            "subcategory":"Medical Equipment & Supplies",
            "type":"Manufacturing & Wholesale Goods"
        },
        {
            "category":"Shopping",
            "subcategory":"Pharmacy",
            "type":"Retail Goods"
        }
    ],
    "sg:phone":"+1 806 353 1253",
    "sg:postcode":"79109",
    "sg:province":"TX",
    "sg:tags":[
        "home",
        "health",
        "care"
    ],
    "wof:name":"Vitalert",
    "wof:placetype":"venue"
},
  "geometry": {"coordinates":[-101.882291,35.183239],"type":"Point"}
}