{
  "type": "Feature",
  "properties": {
    "iso:country":"US",
    "sg:address":"2726 N Peach Hollow Cir",
    "sg:city":"Pearland",
    "sg:classifiers":[
        {
            "category":"Wholesale",
            "subcategory":"Electrical",
            "type":"Manufacturing & Wholesale Goods"
        }
    ],
    "sg:phone":"+1 713 436 3945",
    "sg:postcode":"77584",
    "sg:province":"TX",
    "sg:tags":[
        "control"
    ],
    "wof:name":"Krohne Inc",
    "wof:placetype":"venue"
},
  "geometry": {"coordinates":[-95.379408,29.579514],"type":"Point"}
}