{
  "type": "Feature",
  "properties": {
    "iso:country":"US",
    "sg:address":"16717 Katy Fwy",
    "sg:city":"Houston",
    "sg:classifiers":[
        {
            "category":"Freight",
            "type":"Transportation"
        }
    ],
    "sg:phone":"+1 281 579 1472",
    "sg:postcode":"77094",
    "sg:province":"TX",
    "sg:tags":[
        "trucking"
    ],
    "wof:name":"CJM Trucking & Soils Co",
    "wof:placetype":"venue"
},
  "geometry": {"coordinates":[-95.672388,29.784456],"type":"Point"}
}