{
  "type": "Feature",
  "properties": {
    "iso:country":"US",
    "sg:address":"10655 Six Pines Rd",
    "sg:city":"Spring",
    "sg:classifiers":[
        {
            "category":"Professional",
            "subcategory":"Management & Consulting",
            "type":"Services"
        }
    ],
    "sg:phone":"+1 281 367 5190",
    "sg:postcode":"77380",
    "sg:province":"TX",
    "sg:tags":[
        "business"
    ],
    "wof:name":"Carnrite Consulting Group",
    "wof:placetype":"venue"
},
  "geometry": {"coordinates":[-95.46128400000001,30.15321],"type":"Point"}
}