{
  "type": "Feature",
  "properties": {
    "iso:country":"US",
    "sg:address":"4965 Preston Park Blvd. Suite 260",
    "sg:city":"Plano",
    "sg:classifiers":[
        {
            "category":"Professional",
            "subcategory":"Management & Consulting",
            "type":"Services"
        }
    ],
    "sg:phone":"+1 972 509 0110",
    "sg:postcode":"75093",
    "sg:province":"TX",
    "sg:website":"http://www.horizondcs.com/",
    "wof:name":"Horizon Data Center Solutions",
    "wof:placetype":"venue"
},
  "geometry": {"coordinates":[-96.78855299999999,33.026916],"type":"Point"}
}