{
  "type": "Feature",
  "properties": {
    "iso:country":"US",
    "sg:address":"11704 Imperial Gem Ave",
    "sg:city":"El Paso",
    "sg:classifiers":[
        {
            "category":"Social Services",
            "subcategory":"Child Care",
            "type":"Services"
        }
    ],
    "sg:phone":"+1 915 857 6665",
    "sg:postcode":"79936",
    "sg:province":"TX",
    "sg:tags":[
        "day"
    ],
    "wof:name":"Little Stars Day Care",
    "wof:placetype":"venue"
},
  "geometry": {"coordinates":[-106.282616,31.79309],"type":"Point"}
}