{
  "type": "Feature",
  "properties": {
    "iso:country":"US",
    "sg:address":"4020 Olive St",
    "sg:city":"Texarkana",
    "sg:classifiers":[
        {
            "category":"Freight",
            "type":"Transportation"
        }
    ],
    "sg:phone":"+1 903 791 1684",
    "sg:postcode":"75503",
    "sg:province":"TX",
    "sg:tags":[
        "hauling",
        "trucking"
    ],
    "wof:name":"Purcell Enterprises",
    "wof:placetype":"venue"
},
  "geometry": {"coordinates":[-94.04849900000001,33.455108],"type":"Point"}
}