{
  "type": "Feature",
  "properties": {
    "iso:country":"US",
    "sg:address":"5495 Belt Line Rd Ste 290",
    "sg:city":"Dallas",
    "sg:classifiers":[
        {
            "category":"Home & Garden",
            "subcategory":"Carpets & Floor Coverings",
            "type":"Retail Goods"
        }
    ],
    "sg:phone":"+1 972 991 4919",
    "sg:postcode":"75254",
    "sg:province":"TX",
    "sg:tags":[
        "carpeting"
    ],
    "wof:name":"Scott Group",
    "wof:placetype":"venue"
},
  "geometry": {"coordinates":[-96.8134,32.953999],"type":"Point"}
}