{
  "type": "Feature",
  "properties": {
    "iso:country":"US",
    "sg:address":"210 S Echols St",
    "sg:city":"Caldwell",
    "sg:classifiers":[
        {
            "category":"Personal",
            "subcategory":"Beauty Salon",
            "type":"Services"
        },
        {
            "category":"Personal",
            "subcategory":"Barber",
            "type":"Services"
        }
    ],
    "sg:phone":"+1 979 567 3373",
    "sg:postcode":"77836",
    "sg:province":"TX",
    "sg:tags":[
        "hair",
        "stylist"
    ],
    "wof:name":"Parlor Hair & Spa",
    "wof:placetype":"venue"
},
  "geometry": {"coordinates":[-96.693144,30.531344],"type":"Point"}
}