{
  "type": "Feature",
  "properties": {
    "iso:country":"US",
    "sg:address":"857 W Mayfield Blvd",
    "sg:city":"San Antonio",
    "sg:classifiers":[
        {
            "category":"Building & Trades",
            "subcategory":"Construction",
            "type":"Services"
        }
    ],
    "sg:phone":"+1 210 648 2320",
    "sg:postcode":"78211",
    "sg:province":"TX",
    "sg:tags":[
        "house"
    ],
    "wof:name":"Adobe General Contracting Inc",
    "wof:placetype":"venue"
},
  "geometry": {"coordinates":[-98.54546999999999,29.361628],"type":"Point"}
}