{
  "type": "Feature",
  "properties": {
    "iso:country":"US",
    "sg:address":"825 Tartan Trl",
    "sg:city":"Lewisville",
    "sg:classifiers":[
        {
            "category":"Freight",
            "type":"Transportation"
        }
    ],
    "sg:phone":"+1 972 917 6825",
    "sg:postcode":"75077",
    "sg:province":"TX",
    "sg:tags":[
        "waste"
    ],
    "wof:name":"CIMA Transporting",
    "wof:placetype":"venue"
},
  "geometry": {"coordinates":[-97.071347,33.079645],"type":"Point"}
}