{
  "type": "Feature",
  "properties": {
    "iso:country":"US",
    "sg:address":"700 N Austin Ave",
    "sg:city":"Georgetown",
    "sg:classifiers":[
        {
            "category":"Autos & Motor Vehicles",
            "subcategory":"Fuel & Gas Station",
            "type":"Retail Goods"
        },
        {
            "category":"Food & Beverages",
            "subcategory":"Groceries & Convenience Stores",
            "type":"Retail Goods"
        }
    ],
    "sg:phone":"+1 512 863 3799",
    "sg:postcode":"78626",
    "sg:province":"TX",
    "sg:website":"http://www.valero.com",
    "wof:name":"Diamond Shamrock",
    "wof:placetype":"venue"
},
  "geometry": {"coordinates":[-97.67823,30.647329],"type":"Point"}
}