{
  "type": "Feature",
  "properties": {
    "iso:country":"US",
    "sg:address":"144 S Chestnut St",
    "sg:city":"Tomball",
    "sg:classifiers":[
        {
            "category":"Professional",
            "type":"Services"
        }
    ],
    "sg:phone":"+1 281 516 1355",
    "sg:postcode":"77375",
    "sg:province":"TX",
    "wof:name":"Sotex Street Machines",
    "wof:placetype":"venue"
},
  "geometry": {"coordinates":[-95.60944000000001,30.099121],"type":"Point"}
}