{
  "type": "Feature",
  "properties": {
    "iso:country":"US",
    "sg:address":"1811 Hwy 287 N",
    "sg:city":"Mansfield",
    "sg:classifiers":[
        {
            "category":"Restaurant",
            "type":"Food & Drink"
        }
    ],
    "sg:phone":"+1 682 518 7800",
    "sg:postcode":"76063",
    "sg:province":"TX",
    "wof:name":"Subway Sandwiches & Salads",
    "wof:placetype":"venue"
},
  "geometry": {"coordinates":[-97.148146,32.59644],"type":"Point"}
}