{
  "type": "Feature",
  "properties": {
    "iso:country":"US",
    "sg:address":"9944 Walnut St",
    "sg:city":"Dallas",
    "sg:classifiers":[
        {
            "category":"Freight",
            "type":"Transportation"
        }
    ],
    "sg:phone":"+1 972 664 9667",
    "sg:postcode":"75243",
    "sg:province":"TX",
    "sg:tags":[
        "operator",
        "local",
        "trucking"
    ],
    "wof:name":"Family Tradition Trucking",
    "wof:placetype":"venue"
},
  "geometry": {"coordinates":[-96.71148599999999,32.919326],"type":"Point"}
}