{
  "type": "Feature",
  "properties": {
    "iso:country":"US",
    "sg:address":"23461 US Hwy 59",
    "sg:city":"Porter",
    "sg:classifiers":[
        {
            "category":"Real Estate",
            "subcategory":"Real Estate Operator",
            "type":"Services"
        }
    ],
    "sg:phone":"+1 281 354 0066",
    "sg:postcode":"77365",
    "sg:province":"TX",
    "sg:tags":[
        "apartment"
    ],
    "wof:name":"Green Parkway Partners LP",
    "wof:placetype":"venue"
},
  "geometry": {"coordinates":[-95.23525600000001,30.106803],"type":"Point"}
}