{
  "type": "Feature",
  "properties": {
    "iso:country":"US",
    "sg:address":"15400 Knoll Trail Dr.  Suite 220",
    "sg:city":"Dallas",
    "sg:classifiers":[
        {
            "category":"Professional",
            "subcategory":"Computer Services",
            "type":"Services"
        }
    ],
    "sg:phone":"+1 214 988 5429",
    "sg:postcode":"75248",
    "sg:province":"TX",
    "sg:tags":[
        "credentialing",
        "screening",
        "background-check",
        "insurance",
        "vendor",
        "contractor"
    ],
    "sg:website":"http://www.assurancescreening.com",
    "wof:name":"Assurance Screening",
    "wof:placetype":"venue"
},
  "geometry": {"coordinates":[-96.818856,32.962942],"type":"Point"}
}