{
  "type": "Feature",
  "properties": {
    "iso:country":"US",
    "sg:address":"20602 FM 1431",
    "sg:city":"Leander",
    "sg:classifiers":[
        {
            "category":"Travel",
            "subcategory":"Travel Agent",
            "type":"Entertainment"
        }
    ],
    "sg:phone":"+1 512 267 7748",
    "sg:postcode":"78645",
    "sg:province":"TX",
    "sg:tags":[
        "passenger",
        "agency",
        "transportation",
        "arrangement"
    ],
    "wof:name":"Christopher Travels",
    "wof:placetype":"venue"
},
  "geometry": {"coordinates":[-97.974622,30.475525],"type":"Point"}
}