{
  "type": "Feature",
  "properties": {
    "iso:country":"US",
    "sg:address":"10561 Goodnight Ln",
    "sg:city":"Dallas",
    "sg:classifiers":[
        {
            "category":"Building & Trades",
            "subcategory":"Construction",
            "type":"Services"
        }
    ],
    "sg:phone":"+1 972 444 0303",
    "sg:postcode":"75220",
    "sg:province":"TX",
    "sg:tags":[
        "foundation"
    ],
    "wof:name":"MBR Guaranteed Foundation",
    "wof:placetype":"venue"
},
  "geometry": {"coordinates":[-96.902434,32.869992],"type":"Point"}
}