{
  "type": "Feature",
  "properties": {
    "iso:country":"US",
    "sg:address":"3608 Encanto Cir",
    "sg:city":"Irving",
    "sg:classifiers":[
        {
            "category":"Building & Trades",
            "subcategory":"Construction",
            "type":"Services"
        }
    ],
    "sg:phone":"+1 972 255 4766",
    "sg:postcode":"75062",
    "sg:province":"TX",
    "sg:tags":[
        "carpentry",
        "contractor"
    ],
    "wof:name":"Glass Bricks By Tc",
    "wof:placetype":"venue"
},
  "geometry": {"coordinates":[-96.999201,32.846534],"type":"Point"}
}