{
  "type": "Feature",
  "properties": {
    "iso:country":"US",
    "sg:address":"1905 S Walnut St",
    "sg:city":"Brady",
    "sg:phone":"+1 325 597 2221",
    "sg:postcode":"76825",
    "sg:province":"TX",
    "sg:tags":[
        "product",
        "petroleum"
    ],
    "wof:name":"Little River Operating Co",
    "wof:placetype":"venue"
},
  "geometry": {"coordinates":[-99.340352,31.118107],"type":"Point"}
}