{
  "type": "Feature",
  "properties": {
    "iso:country":"US",
    "sg:address":"119 el Mio Dr",
    "sg:city":"San Antonio",
    "sg:classifiers":[
        {
            "category":"Bars & Pubs",
            "type":"Food & Drink"
        }
    ],
    "sg:phone":"+1 210 342 2276",
    "sg:postcode":"78216",
    "sg:province":"TX",
    "sg:tags":[
        "drinking"
    ],
    "wof:name":"Two Bone Heads",
    "wof:placetype":"venue"
},
  "geometry": {"coordinates":[-98.50131500000001,29.494665],"type":"Point"}
}