{
  "type": "Feature",
  "properties": {
    "iso:country":"US",
    "sg:address":"3534 E T C Jester Blvd",
    "sg:city":"Houston",
    "sg:classifiers":[
        {
            "category":"Wholesale",
            "subcategory":"Machinery & Supplies",
            "type":"Manufacturing & Wholesale Goods"
        },
        {
            "category":"Manufacturing",
            "subcategory":"Metals",
            "type":"Manufacturing & Wholesale Goods"
        }
    ],
    "sg:phone":"+1 713 682 4515",
    "sg:postcode":"77018",
    "sg:province":"TX",
    "sg:tags":[
        "industrial",
        "valve",
        "mfg"
    ],
    "wof:name":"B S & B Safety Systems Inc",
    "wof:placetype":"venue"
},
  "geometry": {"coordinates":[-95.444411,29.82033],"type":"Point"}
}