{
  "type": "Feature",
  "properties": {
    "iso:country":"US",
    "sg:address":"1304 Hilltop Dr",
    "sg:city":"Irving",
    "sg:classifiers":[
        {
            "category":"Building & Trades",
            "subcategory":"Construction",
            "type":"Services"
        }
    ],
    "sg:phone":"+1 972 253 8265",
    "sg:postcode":"75060",
    "sg:province":"TX",
    "sg:tags":[
        "painter"
    ],
    "wof:name":"Tank Maintenance",
    "wof:placetype":"venue"
},
  "geometry": {"coordinates":[-96.953323,32.799228],"type":"Point"}
}