{
  "type": "Feature",
  "properties": {
    "iso:country":"US",
    "sg:address":"7323 Emerald Glen Dr",
    "sg:city":"Sugar Land",
    "sg:classifiers":[
        {
            "category":"Wholesale",
            "subcategory":"Sporting Goods",
            "type":"Manufacturing & Wholesale Goods"
        }
    ],
    "sg:phone":"+1 281 343 7122",
    "sg:postcode":"77479",
    "sg:province":"TX",
    "wof:name":"Tier 1 Gear",
    "wof:placetype":"venue"
},
  "geometry": {"coordinates":[-95.68271799999999,29.548456],"type":"Point"}
}