{
  "type": "Feature",
  "properties": {
    "iso:country":"US",
    "sg:address":"778 Barbarosa Rd",
    "sg:city":"New Braunfels",
    "sg:classifiers":[
        {
            "category":"Wholesale",
            "subcategory":"Furniture",
            "type":"Manufacturing & Wholesale Goods"
        }
    ],
    "sg:phone":"+1 830 625 0764",
    "sg:postcode":"78130",
    "sg:province":"TX",
    "sg:website":"www.financialbusinessmachines.com",
    "wof:name":"Financial Business Machines",
    "wof:placetype":"venue"
},
  "geometry": {"coordinates":[-98.06317,29.712034],"type":"Point"}
}