{
  "type": "Feature",
  "properties": {
    "iso:country":"US",
    "sg:address":"2919 Rockyridge Dr",
    "sg:city":"Houston",
    "sg:classifiers":[
        {
            "category":"Professional",
            "type":"Services"
        }
    ],
    "sg:phone":"+1 713 780 4393",
    "sg:postcode":"77063",
    "sg:province":"TX",
    "sg:tags":[
        "consultant",
        "geological"
    ],
    "wof:name":"Inverness Resources",
    "wof:placetype":"venue"
},
  "geometry": {"coordinates":[-95.532454,29.733404],"type":"Point"}
}