{
  "type": "Feature",
  "properties": {
    "iso:country":"US",
    "sg:address":"11390 State Hwy 1604",
    "sg:city":"San Antonio",
    "sg:classifiers":[
        {
            "category":"Building & Trades",
            "subcategory":"Construction",
            "type":"Services"
        }
    ],
    "sg:phone":"+1 210 508 9594",
    "sg:postcode":"78263",
    "sg:province":"TX",
    "sg:tags":[
        "masonry",
        "contractor"
    ],
    "wof:name":"SD Homes Inc",
    "wof:placetype":"venue"
},
  "geometry": {"coordinates":[-98.259765,29.306859],"type":"Point"}
}