{
  "type": "Feature",
  "properties": {
    "iso:country":"US",
    "sg:address":"403 East 23rd Street Suite 5.700",
    "sg:city":"Austin",
    "sg:classifiers":[
        {
            "category":"Education",
            "subcategory":"School",
            "type":"Public Place"
        }
    ],
    "sg:phone":"+1 512 471 4890",
    "sg:postcode":"78712",
    "sg:province":"TX",
    "sg:website":"www.starkcenter.org",
    "wof:name":"H.J. Lutcher Stark Center for Physical Culture and Sports",
    "wof:placetype":"venue"
},
  "geometry": {"coordinates":[-97.733722,30.285208],"type":"Point"}
}