{
  "type": "Feature",
  "properties": {
    "iso:country":"US",
    "sg:address":"11974 Foutch Rd",
    "sg:city":"Pilot Point",
    "sg:classifiers":[
        {
            "category":"Professional",
            "type":"Services"
        }
    ],
    "sg:phone":"+1 940 686 5568",
    "sg:postcode":"76258",
    "sg:province":"TX",
    "sg:tags":[
        "establishment"
    ],
    "wof:name":"Jack Olsta Co",
    "wof:placetype":"venue"
},
  "geometry": {"coordinates":[-96.93103000000001,33.370155],"type":"Point"}
}