{
  "type": "Feature",
  "properties": {
    "iso:country":"US",
    "sg:address":"15020 Starboard Dr",
    "sg:city":"Willis",
    "sg:classifiers":[
        {
            "category":"Organizations",
            "subcategory":"Religious Organization",
            "type":"Services"
        }
    ],
    "sg:phone":"+1 936 856 1734",
    "sg:postcode":"77318",
    "sg:province":"TX",
    "wof:name":"Thirty Seventh Time",
    "wof:placetype":"venue"
},
  "geometry": {"coordinates":[-95.553607,30.45984],"type":"Point"}
}