{
  "type": "Feature",
  "properties": {
    "iso:country":"US",
    "sg:address":"910 E Redd Rd",
    "sg:city":"El Paso",
    "sg:classifiers":[
        {
            "category":"Professional",
            "subcategory":"Computer Services",
            "type":"Services"
        }
    ],
    "sg:phone":"+1 915 231 9530",
    "sg:postcode":"79912",
    "sg:province":"TX",
    "sg:tags":[
        "internet"
    ],
    "wof:name":"Chronic's Cyber Gaming Cafe",
    "wof:placetype":"venue"
},
  "geometry": {"coordinates":[-106.548391,31.863404],"type":"Point"}
}