{
  "type": "Feature",
  "properties": {
    "iso:country":"US",
    "sg:address":"2517 Highland Blvd",
    "sg:city":"Nederland",
    "sg:classifiers":[
        {
            "category":"Retail",
            "subcategory":"Auto Repair",
            "type":"Services"
        }
    ],
    "sg:phone":"+1 409 722 7992",
    "sg:postcode":"77627",
    "sg:province":"TX",
    "sg:tags":[
        "automotive"
    ],
    "wof:name":"Ross Alignment Services",
    "wof:placetype":"venue"
},
  "geometry": {"coordinates":[-94.017196,29.986393],"type":"Point"}
}