{
  "type": "Feature",
  "properties": {
    "iso:country":"US",
    "sg:address":"13223 Fall Manor Dr",
    "sg:city":"Dallas",
    "sg:classifiers":[
        {
            "category":"Building & Trades",
            "subcategory":"Construction",
            "type":"Services"
        }
    ],
    "sg:phone":"+1 214 215 2532",
    "sg:postcode":"75243",
    "sg:province":"TX",
    "sg:tags":[
        "builder",
        "patio",
        "deck"
    ],
    "wof:name":"Deck One",
    "wof:placetype":"venue"
},
  "geometry": {"coordinates":[-96.71375399999999,32.930904],"type":"Point"}
}