{
  "type": "Feature",
  "properties": {
    "iso:country":"US",
    "sg:address":"767 Village Green Dr",
    "sg:city":"De Soto",
    "sg:classifiers":[
        {
            "category":"Professional",
            "subcategory":"Business Services",
            "type":"Services"
        }
    ],
    "sg:phone":"+1 972 572 3839",
    "sg:postcode":"75115",
    "sg:province":"TX",
    "wof:name":"Jonel Silk Interiors",
    "wof:placetype":"venue"
},
  "geometry": {"coordinates":[-96.873259,32.620146],"type":"Point"}
}