{
  "type": "Feature",
  "properties": {
    "iso:country":"US",
    "sg:address":"401 W Hickory St Ste 309",
    "sg:city":"Denton",
    "sg:classifiers":[
        {
            "category":"Government",
            "subcategory":"Office",
            "type":"Public Place"
        }
    ],
    "sg:phone":"+1 940 320 1028",
    "sg:postcode":"76201",
    "sg:province":"TX",
    "sg:tags":[
        "township",
        "government-city",
        "village"
    ],
    "sg:website":"http://www.dentoncounty.com",
    "wof:name":"Treasures Office",
    "wof:placetype":"venue"
},
  "geometry": {"coordinates":[-97.136543,33.214561],"type":"Point"}
}