{
  "type": "Feature",
  "properties": {
    "iso:country":"US",
    "sg:address":"1111 W Illinois Ave",
    "sg:city":"Midland",
    "sg:classifiers":[
        {
            "category":"Insurance",
            "subcategory":"Insurance Agent",
            "type":"Services"
        }
    ],
    "sg:phone":"+1 432 694 0508",
    "sg:postcode":"79701",
    "sg:province":"TX",
    "wof:name":"Bob Moore Insurance Agency",
    "wof:placetype":"venue"
},
  "geometry": {"coordinates":[-102.087338,31.998257],"type":"Point"}
}