{
  "type": "Feature",
  "properties": {
    "iso:country":"US",
    "sg:address":"2318 Ragland Dr",
    "sg:city":"Houston",
    "sg:classifiers":[
        {
            "category":"Professional",
            "subcategory":"Business Services",
            "type":"Services"
        }
    ],
    "sg:phone":"+1 281 445 8188",
    "sg:postcode":"77067",
    "sg:province":"TX",
    "wof:name":"Ltb Sales",
    "wof:placetype":"venue"
},
  "geometry": {"coordinates":[-95.45712399999999,29.939754],"type":"Point"}
}