{
  "type": "Feature",
  "properties": {
    "iso:country":"US",
    "sg:address":"2650 N State Highway 360",
    "sg:city":"Grand Prairie",
    "sg:classifiers":[
        {
            "category":"Restaurant",
            "type":"Food & Drink"
        }
    ],
    "sg:menulink":"http://www.allmenus.com/tx/arlington/204017-sonic/menu/",
    "sg:phone":"+1 972 641 5877",
    "sg:postcode":"75050",
    "sg:province":"TX",
    "sg:tags":[
        "burger",
        "american"
    ],
    "wof:name":"Sonic",
    "wof:placetype":"venue"
},
  "geometry": {"coordinates":[-97.055634,32.794854],"type":"Point"}
}