{
  "type": "Feature",
  "properties": {
    "iso:country":"US",
    "sg:address":"1205 Round Rock Ave",
    "sg:city":"Round Rock",
    "sg:classifiers":[
        {
            "category":"Organizations",
            "subcategory":"Religious Organization",
            "type":"Services"
        }
    ],
    "sg:phone":"+1 512 218 4673",
    "sg:postcode":"78681",
    "sg:province":"TX",
    "sg:tags":[
        "evangelical",
        "church"
    ],
    "sg:website":"www.hopebiblefellowship.org",
    "wof:name":"Hope Bible Fellowship",
    "wof:placetype":"venue"
},
  "geometry": {"coordinates":[-97.69465099999999,30.511652],"type":"Point"}
}