{
  "type": "Feature",
  "properties": {
    "iso:country":"US",
    "sg:address":"118 N San Jacinto St",
    "sg:city":"Conroe",
    "sg:classifiers":[
        {
            "category":"Professional",
            "subcategory":"Accounting & Tax Preparation",
            "type":"Services"
        }
    ],
    "sg:phone":"+1 936 539 5995",
    "sg:postcode":"77301",
    "sg:province":"TX",
    "sg:tags":[
        "accountant"
    ],
    "wof:name":"Taxpert",
    "wof:placetype":"venue"
},
  "geometry": {"coordinates":[-95.45913899999999,30.310027],"type":"Point"}
}