{
  "type": "Feature",
  "properties": {
    "iso:country":"US",
    "sg:address":"207 N Fannin Ave",
    "sg:city":"Denison",
    "sg:classifiers":[
        {
            "category":"Insurance",
            "subcategory":"Insurance Agent",
            "type":"Services"
        }
    ],
    "sg:phone":"+1 903 465 7242",
    "sg:postcode":"75020",
    "sg:province":"TX",
    "wof:name":"Hartfield & Son Insurance",
    "wof:placetype":"venue"
},
  "geometry": {"coordinates":[-96.54150199999999,33.757465],"type":"Point"}
}