{
  "type": "Feature",
  "properties": {
    "iso:country":"US",
    "sg:address":"5120 82nd St",
    "sg:city":"Lubbock",
    "sg:classifiers":[
        {
            "category":"Banks & Credit Unions",
            "subcategory":"Bank",
            "type":"Services"
        }
    ],
    "sg:phone":"+1 806 767 8200",
    "sg:postcode":"79424",
    "sg:province":"TX",
    "sg:website":"www.asbonline.com",
    "wof:name":"American State Bank",
    "wof:placetype":"venue"
},
  "geometry": {"coordinates":[-101.918693,33.519798],"type":"Point"}
}