{
  "type": "Feature",
  "properties": {
    "iso:country":"US",
    "sg:address":"3501 N Macarthur Blvd",
    "sg:city":"Irving",
    "sg:classifiers":[
        {
            "category":"Health Services",
            "subcategory":"Clinic",
            "type":"Services"
        },
        {
            "category":"Health Services",
            "subcategory":"Doctor",
            "type":"Services"
        }
    ],
    "sg:phone":"+1 972 594 0100",
    "sg:postcode":"75062",
    "sg:province":"TX",
    "wof:name":"Valdez Clinic",
    "wof:placetype":"venue"
},
  "geometry": {"coordinates":[-96.959118,32.852343],"type":"Point"}
}