{
  "type": "Feature",
  "properties": {
    "iso:country":"US",
    "sg:address":"7022 Cove Rd",
    "sg:city":"Pearland",
    "sg:classifiers":[
        {
            "category":"Retail",
            "subcategory":"Auto Repair",
            "type":"Services"
        }
    ],
    "sg:phone":"+1 281 997 2676",
    "sg:postcode":"77520",
    "sg:province":"TX",
    "sg:tags":[
        "body"
    ],
    "wof:name":"Motorplan Auto",
    "wof:placetype":"venue"
},
  "geometry": {"coordinates":[-94.843345,29.867834],"type":"Point"}
}