{
  "type": "Feature",
  "properties": {
    "iso:country":"US",
    "sg:address":"5758 Lark Ct",
    "sg:city":"Abilene",
    "sg:classifiers":[
        {
            "category":"Manufacturing",
            "subcategory":"Petroleum Products",
            "type":"Manufacturing & Wholesale Goods"
        },
        {
            "category":"Building & Trades",
            "subcategory":"Construction",
            "type":"Services"
        }
    ],
    "sg:phone":"+1 325 691 5363",
    "sg:postcode":"79605",
    "sg:province":"TX",
    "sg:tags":[
        "finishing",
        "wood",
        "contract"
    ],
    "wof:name":"Clean Spirit Carpet & Floor Finish Svc",
    "wof:placetype":"venue"
},
  "geometry": {"coordinates":[-99.80037,32.442376],"type":"Point"}
}