{
  "type": "Feature",
  "properties": {
    "iso:country":"US",
    "sg:address":"12111 Garland Rd",
    "sg:city":"Dallas",
    "sg:classifiers":[
        {
            "category":"Retail",
            "subcategory":"Auto Repair",
            "type":"Services"
        }
    ],
    "sg:phone":"+1 214 327 6675",
    "sg:postcode":"75218",
    "sg:province":"TX",
    "sg:tags":[
        "body",
        "shop"
    ],
    "wof:name":"Sterling Auto Body",
    "wof:placetype":"venue"
},
  "geometry": {"coordinates":[-96.670097,32.865101],"type":"Point"}
}