{
  "type": "Feature",
  "properties": {
    "iso:country":"US",
    "sg:address":"1809 Center St",
    "sg:city":"Deer Park",
    "sg:classifiers":[
        {
            "category":"Professional",
            "subcategory":"Employment Agencies",
            "type":"Services"
        }
    ],
    "sg:phone":"+1 281 478 4035",
    "sg:postcode":"77536",
    "sg:province":"TX",
    "sg:tags":[
        "opportunity"
    ],
    "wof:name":"Daniel Craft Fluor Employment",
    "wof:placetype":"venue"
},
  "geometry": {"coordinates":[-95.123608,29.695956],"type":"Point"}
}