{
  "type": "Feature",
  "properties": {
    "iso:country":"US",
    "sg:address":"224 S Fredericksburg St",
    "sg:city":"San Marcos",
    "sg:classifiers":[
        {
            "category":"Organizations",
            "subcategory":"Religious Organization",
            "type":"Services"
        }
    ],
    "sg:phone":"+1 512 392 8034",
    "sg:postcode":"78666",
    "sg:province":"TX",
    "sg:tags":[
        "church"
    ],
    "wof:name":"Wesley Chapel AME Church",
    "wof:placetype":"venue"
},
  "geometry": {"coordinates":[-97.942189,29.879388],"type":"Point"}
}