{
  "type": "Feature",
  "properties": {
    "iso:country":"US",
    "sg:address":"101 Roma Dr",
    "sg:city":"Garland",
    "sg:classifiers":[
        {
            "category":"Building & Trades",
            "subcategory":"Cleaning & Sanitation",
            "type":"Services"
        }
    ],
    "sg:phone":"+1 972 271 3017",
    "sg:postcode":"75041",
    "sg:province":"TX",
    "sg:tags":[
        "maintenance"
    ],
    "wof:name":"B&S Associate",
    "wof:placetype":"venue"
},
  "geometry": {"coordinates":[-96.63243300000001,32.884085],"type":"Point"}
}