{
  "type": "Feature",
  "properties": {
    "iso:country":"US",
    "sg:address":"902 Rio Grande St",
    "sg:city":"Austin",
    "sg:classifiers":[
        {
            "category":"Professional",
            "subcategory":"Lawyer & Legal Services",
            "type":"Services"
        }
    ],
    "sg:phone":"+1 512 476 7500",
    "sg:postcode":"78701",
    "sg:province":"TX",
    "sg:tags":[
        "divorce",
        "law",
        "family"
    ],
    "sg:website":"www.boozerlaw.com",
    "wof:name":"BOOZER MARTIN H",
    "wof:placetype":"venue"
},
  "geometry": {"coordinates":[-97.748594,30.272802],"type":"Point"}
}