{
  "type": "Feature",
  "properties": {
    "iso:country":"US",
    "sg:address":"601 Jefferson St",
    "sg:city":"Arlington",
    "sg:classifiers":[
        {
            "category":"Retail",
            "subcategory":"Photofinishing",
            "type":"Services"
        }
    ],
    "sg:phone":"+1 817 571 3039",
    "sg:postcode":"76012",
    "sg:province":"TX",
    "sg:tags":[
        "laboratory"
    ],
    "wof:name":"Datoo 2 Inc",
    "wof:placetype":"venue"
},
  "geometry": {"coordinates":[-97.115878,32.742858],"type":"Point"}
}