{
  "type": "Feature",
  "properties": {
    "iso:country":"US",
    "sg:address":"1217 N Slope",
    "sg:city":"Carrollton",
    "sg:classifiers":[
        {
            "category":"Professional",
            "type":"Services"
        }
    ],
    "sg:phone":"+1 972 394 8827",
    "sg:postcode":"75007",
    "sg:province":"TX",
    "wof:name":"Drive Defensively In Texas",
    "wof:placetype":"venue"
},
  "geometry": {"coordinates":[-96.91404900000001,33.000911],"type":"Point"}
}