{
  "type": "Feature",
  "properties": {
    "iso:country":"US",
    "sg:address":"4760 Beechnut Street",
    "sg:city":"Houston",
    "sg:classifiers":[
        {
            "category":"Health Services",
            "subcategory":"Optometrist",
            "type":"Services"
        }
    ],
    "sg:phone":"+1 713 668 6604",
    "sg:postcode":"77096",
    "sg:province":"TX",
    "wof:name":"Allan Panzer, OD",
    "wof:placetype":"venue"
},
  "geometry": {"coordinates":[-95.460841,29.689314],"type":"Point"}
}