{
  "type": "Feature",
  "properties": {
    "iso:country":"US",
    "sg:address":"307 Lindsey St",
    "sg:city":"Bowie",
    "sg:classifiers":[
        {
            "category":"Place Of Worship",
            "subcategory":"Church",
            "type":"Public Place"
        },
        {
            "category":"Place Of Worship",
            "type":"Public Place"
        }
    ],
    "sg:phone":"+1 940 872 1193",
    "sg:postcode":"76230",
    "sg:province":"TX",
    "sg:tags":[
        "churches-baptist-general",
        "churches-baptist"
    ],
    "sg:website":"http://www.fbcbowie.org",
    "wof:name":"First Baptist Church",
    "wof:placetype":"venue"
},
  "geometry": {"coordinates":[-97.846858,33.559479],"type":"Point"}
}