{
  "type": "Feature",
  "properties": {
    "iso:country":"US",
    "sg:address":"746 W Jefferson Blvd",
    "sg:city":"Dallas",
    "sg:classifiers":[
        {
            "category":"Insurance",
            "subcategory":"Insurance Agent",
            "type":"Services"
        }
    ],
    "sg:phone":"+1 214 943 7383",
    "sg:postcode":"75208",
    "sg:province":"TX",
    "wof:name":"I M A Auto Insurance",
    "wof:placetype":"venue"
},
  "geometry": {"coordinates":[-96.83505100000001,32.743075],"type":"Point"}
}