{
  "type": "Feature",
  "properties": {
    "iso:country":"US",
    "sg:address":"938 Main St",
    "sg:city":"Sulphur Springs",
    "sg:classifiers":[
        {
            "category":"Health Services",
            "subcategory":"Clinic",
            "type":"Services"
        }
    ],
    "sg:phone":"+1 903 885 5606",
    "sg:postcode":"75482",
    "sg:province":"TX",
    "sg:tags":[
        "home",
        "care"
    ],
    "wof:name":"At Home Health Care",
    "wof:placetype":"venue"
},
  "geometry": {"coordinates":[-95.61345799999999,33.134024],"type":"Point"}
}