{
  "type": "Feature",
  "properties": {
    "iso:country":"US",
    "sg:address":"704 W Pleasantview Dr",
    "sg:city":"Hurst",
    "sg:classifiers":[
        {
            "category":"Wholesale",
            "subcategory":"Hardware",
            "type":"Manufacturing & Wholesale Goods"
        }
    ],
    "sg:phone":"+1 817 285 9703",
    "sg:postcode":"76054",
    "sg:province":"TX",
    "sg:tags":[
        "plumbing"
    ],
    "wof:name":"Tri State Fininshing Equipment",
    "wof:placetype":"venue"
},
  "geometry": {"coordinates":[-97.18358499999999,32.842681],"type":"Point"}
}