{
  "type": "Feature",
  "properties": {
    "iso:country":"US",
    "sg:address":"2319 Old Dixie Dr",
    "sg:city":"Richmond",
    "sg:classifiers":[
        {
            "category":"Building & Trades",
            "subcategory":"Landscaping Services",
            "type":"Services"
        }
    ],
    "sg:phone":"+1 281 238 8078",
    "sg:postcode":"77469",
    "sg:province":"TX",
    "sg:tags":[
        "designer",
        "landscape"
    ],
    "wof:name":"Falling Waters Landscape Inc",
    "wof:placetype":"venue"
},
  "geometry": {"coordinates":[-95.741646,29.640616],"type":"Point"}
}