{
  "type": "Feature",
  "properties": {
    "iso:country":"US",
    "sg:address":"2525 W Interstate 20",
    "sg:city":"Grand Prairie",
    "sg:classifiers":[
        {
            "category":"Food & Beverages",
            "subcategory":"Groceries & Convenience Stores",
            "type":"Retail Goods"
        }
    ],
    "sg:phone":"+1 972 988 1366",
    "sg:postcode":"75052",
    "sg:province":"TX",
    "wof:name":"Kroger Texas Lp",
    "wof:placetype":"venue"
},
  "geometry": {"coordinates":[-97.04239699999999,32.675098],"type":"Point"}
}