{
  "type": "Feature",
  "properties": {
    "iso:country":"US",
    "sg:address":"10613 Bellaire Blvd Suite A-120",
    "sg:city":"Houston",
    "sg:classifiers":[
        {
            "category":"Personal",
            "subcategory":"Beauty Salon",
            "type":"Services"
        }
    ],
    "sg:phone":"+1 832 528 7562",
    "sg:postcode":"77072",
    "sg:province":"TX",
    "sg:website":"http://www.blushandco.com",
    "wof:name":"Blush and Company",
    "wof:placetype":"venue"
},
  "geometry": {"coordinates":[-95.56741100000001,29.703894],"type":"Point"}
}