{
  "type": "Feature",
  "properties": {
    "iso:country":"US",
    "sg:address":"300 Clay St",
    "sg:city":"Houston",
    "sg:classifiers":[
        {
            "category":"Professional",
            "subcategory":"Printing & Photocopies",
            "type":"Services"
        }
    ],
    "sg:phone":"+1 713 759 0118",
    "sg:postcode":"77002",
    "sg:province":"TX",
    "sg:tags":[
        "duplicating",
        "copying"
    ],
    "wof:name":"Central Graphics",
    "wof:placetype":"venue"
},
  "geometry": {"coordinates":[-95.37279599999999,29.758471],"type":"Point"}
}