{
  "type": "Feature",
  "properties": {
    "iso:country":"US",
    "sg:address":"6759 E Lancaster Ave",
    "sg:city":"Fort Worth",
    "sg:classifiers":[
        {
            "category":"Shopping",
            "subcategory":"Used Merchandise",
            "type":"Retail Goods"
        }
    ],
    "sg:phone":"+1 817 457 8091",
    "sg:postcode":"76112",
    "sg:province":"TX",
    "sg:tags":[
        "pawnbroker",
        "pawnshop"
    ],
    "wof:name":"First Cash Pawn 65",
    "wof:placetype":"venue"
},
  "geometry": {"coordinates":[-97.21549400000001,32.731917],"type":"Point"}
}