{
  "type": "Feature",
  "properties": {
    "iso:country":"US",
    "sg:address":"2701 S General Bruce Dr",
    "sg:city":"Temple",
    "sg:classifiers":[
        {
            "category":"Food & Beverages",
            "subcategory":"Groceries & Convenience Stores",
            "type":"Retail Goods"
        }
    ],
    "sg:phone":"+1 254 773 6082",
    "sg:postcode":"76504",
    "sg:province":"TX",
    "sg:tags":[
        "station",
        "gasoline"
    ],
    "wof:name":"Triangle Drive In",
    "wof:placetype":"venue"
},
  "geometry": {"coordinates":[-97.37615099999999,31.093643],"type":"Point"}
}