{
  "type": "Feature",
  "properties": {
    "iso:country":"US",
    "sg:address":"3801 Gaston Ave Ste 300",
    "sg:city":"Dallas",
    "sg:classifiers":[
        {
            "category":"Health Services",
            "subcategory":"Doctor",
            "type":"Services"
        }
    ],
    "sg:phone":"+1 214 887 6682",
    "sg:postcode":"75246",
    "sg:province":"TX",
    "wof:name":"Ab Therapeutics",
    "wof:placetype":"venue"
},
  "geometry": {"coordinates":[-96.778999,32.792198],"type":"Point"}
}