{
  "type": "Feature",
  "properties": {
    "iso:country":"US",
    "sg:address":"7509 Penney Ln",
    "sg:city":"Abilene",
    "sg:classifiers":[
        {
            "category":"Shopping",
            "type":"Retail Goods"
        }
    ],
    "sg:phone":"+1 325 692 0323",
    "sg:postcode":"79606",
    "sg:province":"TX",
    "sg:tags":[
        "merchandise"
    ],
    "wof:name":"Big D Metal Works",
    "wof:placetype":"venue"
},
  "geometry": {"coordinates":[-99.786129,32.356916],"type":"Point"}
}