{
  "type": "Feature",
  "properties": {
    "iso:country":"US",
    "sg:address":"12224 Jourdan Crossing Blvd",
    "sg:city":"Austin",
    "sg:classifiers":[
        {
            "category":"Social Services",
            "subcategory":"Child Care",
            "type":"Services"
        }
    ],
    "sg:phone":"+1 512 836 9550",
    "sg:postcode":"78753",
    "sg:province":"TX",
    "wof:name":"Noah's Ark Learning Ctr",
    "wof:placetype":"venue"
},
  "geometry": {"coordinates":[-97.65244199999999,30.38729],"type":"Point"}
}