{
  "type": "Feature",
  "properties": {
    "iso:country":"US",
    "sg:address":"13815 Northern Oak",
    "sg:city":"San Antonio",
    "sg:classifiers":[
        {
            "category":"Home & Garden",
            "subcategory":"Building Materials",
            "type":"Retail Goods"
        },
        {
            "category":"Home & Garden",
            "subcategory":"Home Furnishings",
            "type":"Retail Goods"
        }
    ],
    "sg:phone":"+1 210 655 6143",
    "sg:postcode":"78217",
    "sg:province":"TX",
    "sg:tags":[
        "shutter"
    ],
    "wof:name":"Central Texas Wood Designs Inc",
    "wof:placetype":"venue"
},
  "geometry": {"coordinates":[-98.410265,29.569429],"type":"Point"}
}