{
  "type": "Feature",
  "properties": {
    "iso:country":"US",
    "sg:address":"970 Spiral Ave",
    "sg:city":"San Antonio",
    "sg:classifiers":[
        {
            "category":"Restaurant",
            "type":"Food & Drink"
        }
    ],
    "sg:phone":"+1 210 673 9966",
    "sg:postcode":"78227",
    "sg:province":"TX",
    "sg:tags":[
        "barbecue",
        "eating"
    ],
    "wof:name":"Gilbert's Barbeque",
    "wof:placetype":"venue"
},
  "geometry": {"coordinates":[-98.647655,29.398539],"type":"Point"}
}