{
  "type": "Feature",
  "properties": {
    "iso:country":"US",
    "sg:address":"6355 Westheimer Rd",
    "sg:city":"Houston",
    "sg:classifiers":[
        {
            "category":"Professional",
            "subcategory":"Business Services",
            "type":"Services"
        }
    ],
    "sg:phone":"+1 713 278 2274",
    "sg:postcode":"77057",
    "sg:province":"TX",
    "sg:tags":[
        "auctioneer"
    ],
    "wof:name":"E Auction",
    "wof:placetype":"venue"
},
  "geometry": {"coordinates":[-95.49827399999999,29.737465],"type":"Point"}
}