{
  "type": "Feature",
  "properties": {
    "iso:country":"US",
    "sg:address":"810 E Highway St",
    "sg:city":"Iowa Park",
    "sg:classifiers":[
        {
            "category":"Retail",
            "subcategory":"Auto Repair",
            "type":"Services"
        }
    ],
    "sg:phone":"+1 940 592 4599",
    "sg:postcode":"76367",
    "sg:province":"TX",
    "sg:tags":[
        "repairing",
        "automobile"
    ],
    "wof:name":"Iowa Park Auto Repair",
    "wof:placetype":"venue"
},
  "geometry": {"coordinates":[-98.65897699999999,33.949728],"type":"Point"}
}