{
  "type": "Feature",
  "properties": {
    "iso:country":"US",
    "sg:address":"204 N Main St Ste 112",
    "sg:city":"Duncanville",
    "sg:classifiers":[
        {
            "category":"Banks & Credit Unions",
            "subcategory":"Financial Services",
            "type":"Services"
        }
    ],
    "sg:phone":"+1 972 572 0178",
    "sg:postcode":"75116",
    "sg:province":"TX",
    "sg:tags":[
        "loan",
        "financing"
    ],
    "wof:name":"D N B Auto Loans Inc",
    "wof:placetype":"venue"
},
  "geometry": {"coordinates":[-96.908477,32.652636],"type":"Point"}
}