{
  "type": "Feature",
  "properties": {
    "iso:country":"US",
    "sg:address":"8402 Homestead Rd",
    "sg:city":"Houston",
    "sg:classifiers":[
        {
            "category":"Organizations",
            "subcategory":"Community Association",
            "type":"Services"
        }
    ],
    "sg:phone":"+1 713 633 2367",
    "sg:postcode":"77028",
    "sg:province":"TX",
    "sg:tags":[
        "club"
    ],
    "wof:name":"Chit Chat Club",
    "wof:placetype":"venue"
},
  "geometry": {"coordinates":[-95.301974,29.839008],"type":"Point"}
}