{
  "type": "Feature",
  "properties": {
    "iso:country":"US",
    "sg:address":"5223 28th St",
    "sg:city":"Lubbock",
    "sg:classifiers":[
        {
            "category":"Professional",
            "subcategory":"Management & Consulting",
            "type":"Services"
        }
    ],
    "sg:phone":"+1 806 797 5529",
    "sg:postcode":"79407",
    "sg:province":"TX",
    "sg:tags":[
        "business"
    ],
    "wof:name":"Well Corp Consulting",
    "wof:placetype":"venue"
},
  "geometry": {"coordinates":[-101.92661,33.568635],"type":"Point"}
}