{
  "type": "Feature",
  "properties": {
    "iso:country":"US",
    "sg:address":"1511 Elm St",
    "sg:city":"Dallas",
    "sg:classifiers":[
        {
            "category":"Parking",
            "type":"Transportation"
        }
    ],
    "sg:phone":"+1 214 965 0870",
    "sg:postcode":"75201",
    "sg:province":"TX",
    "sg:website":"www.centralparkingsystem.com",
    "wof:name":"Central Parking System",
    "wof:placetype":"venue"
},
  "geometry": {"coordinates":[-96.79963600000001,32.781498],"type":"Point"}
}