{
  "type": "Feature",
  "properties": {
    "iso:country":"US",
    "sg:address":"1208 W Pike Blvd",
    "sg:city":"Weslaco",
    "sg:classifiers":[
        {
            "category":"Social Services",
            "subcategory":"Job Training",
            "type":"Services"
        }
    ],
    "sg:phone":"+1 956 969 0969",
    "sg:postcode":"78596",
    "sg:province":"TX",
    "sg:tags":[
        "rehabilitation"
    ],
    "wof:name":"Texas Rehabilitation Commissn",
    "wof:placetype":"venue"
},
  "geometry": {"coordinates":[-98.003945,26.169645],"type":"Point"}
}