{
  "type": "Feature",
  "properties": {
    "iso:country":"US",
    "sg:address":"1414 Graham Dr",
    "sg:city":"Tomball",
    "sg:classifiers":[
        {
            "category":"Fast Food",
            "type":"Food & Drink"
        }
    ],
    "sg:phone":"+1 281 351 8037",
    "sg:postcode":"77375",
    "sg:province":"TX",
    "sg:tags":[
        "restaurant"
    ],
    "sg:website":"http://www.popeyes.com",
    "wof:name":"Popeyes Chicken & Biscuits",
    "wof:placetype":"venue"
},
  "geometry": {"coordinates":[-95.631416,30.087771],"type":"Point"}
}