{
  "type": "Feature",
  "properties": {
    "iso:country":"US",
    "sg:address":"6033 Kelsing Cv",
    "sg:city":"Austin",
    "sg:classifiers":[
        {
            "category":"Professional",
            "subcategory":"Business Services",
            "type":"Services"
        }
    ],
    "sg:phone":"+1 512 268 2436",
    "sg:postcode":"78735",
    "sg:province":"TX",
    "sg:tags":[
        "consultant",
        "coach"
    ],
    "wof:name":"Lau Research Consultants, Inc",
    "wof:placetype":"venue"
},
  "geometry": {"coordinates":[-97.876458,30.248172],"type":"Point"}
}