{
  "type": "Feature",
  "properties": {
    "iso:country":"US",
    "sg:address":"111 Rayburn Dr",
    "sg:city":"San Antonio",
    "sg:classifiers":[
        {
            "category":"Banks & Credit Unions",
            "subcategory":"Bank",
            "type":"Services"
        }
    ],
    "sg:phone":"+1 210 921 8409",
    "sg:postcode":"78221",
    "sg:province":"TX",
    "sg:tags":[
        "national",
        "commercial"
    ],
    "wof:name":"Bank Of America",
    "wof:placetype":"venue"
},
  "geometry": {"coordinates":[-98.50512999999999,29.357862],"type":"Point"}
}