{
  "type": "Feature",
  "properties": {
    "iso:country":"US",
    "sg:address":"1231 Alma St",
    "sg:city":"Tomball",
    "sg:classifiers":[
        {
            "category":"Retail",
            "subcategory":"Repair Shop",
            "type":"Services"
        }
    ],
    "sg:phone":"+1 281 351 4152",
    "sg:postcode":"77375",
    "sg:province":"TX",
    "sg:tags":[
        "lock",
        "locksmith"
    ],
    "wof:name":"Hill's Lock Shop",
    "wof:placetype":"venue"
},
  "geometry": {"coordinates":[-95.62808800000001,30.090291],"type":"Point"}
}