{
  "type": "Feature",
  "properties": {
    "iso:country":"US",
    "sg:address":"2803 Rogge Ln",
    "sg:city":"Austin",
    "sg:classifiers":[
        {
            "category":"Personal",
            "subcategory":"Beauty Salon",
            "type":"Services"
        }
    ],
    "sg:phone":"+1 512 929 0012",
    "sg:postcode":"78723",
    "sg:province":"TX",
    "sg:tags":[
        "shop"
    ],
    "wof:name":"Imagen Latina Beauty Salon",
    "wof:placetype":"venue"
},
  "geometry": {"coordinates":[-97.681793,30.304742],"type":"Point"}
}