{
  "type": "Feature",
  "properties": {
    "iso:country":"US",
    "sg:address":"1604 Reever St",
    "sg:city":"Arlington",
    "sg:classifiers":[
        {
            "category":"Manufacturing",
            "subcategory":"Apparel",
            "type":"Manufacturing & Wholesale Goods"
        }
    ],
    "sg:phone":"+1 817 274 5365",
    "sg:postcode":"76010",
    "sg:province":"TX",
    "sg:tags":[
        "product",
        "mfg"
    ],
    "wof:name":"EZ Go Canvas Products",
    "wof:placetype":"venue"
},
  "geometry": {"coordinates":[-97.084363,32.7233],"type":"Point"}
}