{
  "type": "Feature",
  "properties": {
    "iso:country":"US",
    "sg:address":"739 Woodlawn Ave",
    "sg:city":"Dallas",
    "sg:classifiers":[
        {
            "category":"Retail",
            "subcategory":"Repair Shop",
            "type":"Services"
        }
    ],
    "sg:phone":"+1 214 941 6556",
    "sg:postcode":"75208",
    "sg:province":"TX",
    "sg:tags":[
        "clocks",
        "parts"
    ],
    "wof:name":"American & European Clock Rpr",
    "wof:placetype":"venue"
},
  "geometry": {"coordinates":[-96.83038999999999,32.751628],"type":"Point"}
}