{
  "type": "Feature",
  "properties": {
    "iso:country":"US",
    "sg:address":"1734 Northaven Ct",
    "sg:city":"Arlington",
    "sg:classifiers":[
        {
            "category":"Personal",
            "type":"Services"
        },
        {
            "category":"Professional",
            "subcategory":"Art Services",
            "type":"Services"
        }
    ],
    "sg:phone":"+1 817 861 4023",
    "sg:postcode":"76012",
    "sg:province":"TX",
    "sg:tags":[
        "photography",
        "videography",
        "wedding"
    ],
    "wof:name":"Steve Edmonds Photography",
    "wof:placetype":"venue"
},
  "geometry": {"coordinates":[-97.134219,32.758877],"type":"Point"}
}