{
  "type": "Feature",
  "properties": {
    "iso:country":"US",
    "sg:address":"4809 Brentwood Stair Rd",
    "sg:city":"Fort Worth",
    "sg:classifiers":[
        {
            "category":"Professional",
            "subcategory":"Lawyer & Legal Services",
            "type":"Services"
        }
    ],
    "sg:phone":"+1 817 446 3360",
    "sg:postcode":"76103",
    "sg:province":"TX",
    "wof:name":"Raymond Daniel",
    "wof:placetype":"venue"
},
  "geometry": {"coordinates":[-97.25147699999999,32.75835],"type":"Point"}
}