{
  "type": "Feature",
  "properties": {
    "iso:country":"US",
    "sg:address":"25536 Aldine Westfield Rd",
    "sg:city":"Spring",
    "sg:classifiers":[
        {
            "category":"Food & Beverages",
            "subcategory":"Bakery",
            "type":"Retail Goods"
        }
    ],
    "sg:phone":"+1 281 288 5949",
    "sg:postcode":"77373",
    "sg:province":"TX",
    "sg:tags":[
        "doughnut"
    ],
    "wof:name":"Max Donuts",
    "wof:placetype":"venue"
},
  "geometry": {"coordinates":[-95.40871799999999,30.070875],"type":"Point"}
}