{
  "type": "Feature",
  "properties": {
    "iso:country":"US",
    "sg:address":"100 W Bivar Ave",
    "sg:city":"De Leon",
    "sg:classifiers":[
        {
            "category":"Wholesale",
            "subcategory":"Hardware",
            "type":"Manufacturing & Wholesale Goods"
        }
    ],
    "sg:phone":"+1 573 332 0303",
    "sg:postcode":"76444",
    "sg:province":"TX",
    "sg:tags":[
        "plumbing"
    ],
    "wof:name":"Kitchen & Bath Showplace",
    "wof:placetype":"venue"
},
  "geometry": {"coordinates":[-98.537486,32.112533],"type":"Point"}
}