{
  "type": "Feature",
  "properties": {
    "iso:country":"US",
    "sg:address":"24549 State Loop 494",
    "sg:city":"Humble",
    "sg:classifiers":[
        {
            "category":"Autos & Motor Vehicles",
            "subcategory":"Fuel & Gas Station",
            "type":"Retail Goods"
        }
    ],
    "sg:phone":"+1 281 358 6590",
    "sg:postcode":"77339",
    "sg:province":"TX",
    "sg:tags":[
        "station",
        "gasoline"
    ],
    "wof:name":"Texaco",
    "wof:placetype":"venue"
},
  "geometry": {"coordinates":[-95.245949,30.055819],"type":"Point"}
}