{
  "type": "Feature",
  "properties": {
    "iso:country":"US",
    "sg:address":"109 S Ranch House Rd",
    "sg:city":"Aledo",
    "sg:classifiers":[
        {
            "category":"Retail",
            "subcategory":"Laundry & Dry Cleaning",
            "type":"Services"
        }
    ],
    "sg:phone":"+1 817 441 1930",
    "sg:postcode":"76008",
    "sg:province":"TX",
    "sg:tags":[
        "drycleaning",
        "plant"
    ],
    "wof:name":"Willow Park Cleaners",
    "wof:placetype":"venue"
},
  "geometry": {"coordinates":[-97.63401399999999,32.732031],"type":"Point"}
}