{
  "type": "Feature",
  "properties": {
    "iso:country":"US",
    "sg:address":"19245 David Memorial Dr",
    "sg:city":"Conroe",
    "sg:classifiers":[
        {
            "category":"Food & Beverages",
            "subcategory":"Groceries & Convenience Stores",
            "type":"Retail Goods"
        }
    ],
    "sg:phone":"+1 713 507 6001",
    "sg:postcode":"77385",
    "sg:province":"TX",
    "sg:tags":[
        "grocer"
    ],
    "sg:website":"www.kroger.com",
    "wof:name":"Kroger",
    "wof:placetype":"venue"
},
  "geometry": {"coordinates":[-95.44931200000001,30.18027],"type":"Point"}
}