{
  "type": "Feature",
  "properties": {
    "iso:country":"US",
    "sg:address":"6400 Las Colinas Blvd",
    "sg:city":"Irving",
    "sg:classifiers":[
        {
            "category":"Banks & Credit Unions",
            "subcategory":"Bank",
            "type":"Services"
        }
    ],
    "sg:phone":"+1 972 652 4000",
    "sg:postcode":"75039",
    "sg:province":"TX",
    "sg:tags":[
        "term",
        "short",
        "business"
    ],
    "wof:name":"Citicorp",
    "wof:placetype":"venue"
},
  "geometry": {"coordinates":[-96.95134400000001,32.896268],"type":"Point"}
}