{
  "type": "Feature",
  "properties": {
    "iso:country":"US",
    "sg:address":"1602 Phil Gibbs Dr",
    "sg:city":"El Paso",
    "sg:classifiers":[
        {
            "category":"Shopping",
            "type":"Retail Goods"
        }
    ],
    "sg:phone":"+1 915 855 6768",
    "sg:postcode":"79936",
    "sg:province":"TX",
    "sg:tags":[
        "merchandise"
    ],
    "wof:name":"AB Machine Shop",
    "wof:placetype":"venue"
},
  "geometry": {"coordinates":[-106.292036,31.752533],"type":"Point"}
}