{
  "type": "Feature",
  "properties": {
    "iso:country":"US",
    "sg:address":"1939 FM 1731",
    "sg:city":"Bovina",
    "sg:phone":"+1 806 225 4004",
    "sg:postcode":"79009",
    "sg:province":"TX",
    "sg:tags":[
        "farm",
        "wheat"
    ],
    "wof:name":"D and L Farms",
    "wof:placetype":"venue"
},
  "geometry": {"coordinates":[-102.88622100000001,34.570843],"type":"Point"}
}