{
  "type": "Feature",
  "properties": {
    "iso:country":"US",
    "sg:address":"9212 Eddy Cove",
    "sg:city":"Austin",
    "sg:classifiers":[
        {
            "category":"Professional",
            "type":"Services"
        }
    ],
    "sg:phone":"+1 512 261 1647",
    "sg:postcode":"78735",
    "sg:province":"TX",
    "wof:name":"Lacigogne Co",
    "wof:placetype":"venue"
},
  "geometry": {"coordinates":[-97.87490099999999,30.295483],"type":"Point"}
}