{
  "type": "Feature",
  "properties": {
    "iso:country":"US",
    "sg:address":"14348 Proton Rd",
    "sg:city":"Farmers Branch",
    "sg:classifiers":[
        {
            "category":"Travel",
            "subcategory":"Hotels & Motels",
            "type":"Entertainment"
        }
    ],
    "sg:phone":"+1 214 574 4800",
    "sg:postcode":"75244",
    "sg:province":"TX",
    "wof:name":"Marriott ExecuStay",
    "wof:placetype":"venue"
},
  "geometry": {"coordinates":[-96.836561,32.945214],"type":"Point"}
}