{
  "type": "Feature",
  "properties": {
    "iso:country":"US",
    "sg:address":"2990 Highway 290 W",
    "sg:city":"Brenham",
    "sg:classifiers":[
        {
            "category":"Restaurant",
            "type":"Food & Drink"
        }
    ],
    "sg:phone":"+1 979 830 0392",
    "sg:postcode":"77833",
    "sg:province":"TX",
    "sg:tags":[
        "house",
        "steak",
        "barbecue"
    ],
    "wof:name":"Js Bar Bq",
    "wof:placetype":"venue"
},
  "geometry": {"coordinates":[-96.421789,30.159391],"type":"Point"}
}