{
  "type": "Feature",
  "properties": {
    "iso:country":"US",
    "sg:address":"1437 Rollins Dr",
    "sg:city":"Allen",
    "sg:classifiers":[
        {
            "category":"Health Services",
            "subcategory":"Health Practitioner",
            "type":"Services"
        }
    ],
    "sg:phone":"+1 214 505 1908",
    "sg:postcode":"75013",
    "sg:province":"TX",
    "sg:tags":[
        "hypnotist"
    ],
    "wof:name":"Mind Over Matter Counseling",
    "wof:placetype":"venue"
},
  "geometry": {"coordinates":[-96.71597199999999,33.087619],"type":"Point"}
}