{
  "type": "Feature",
  "properties": {
    "iso:country":"US",
    "sg:address":"3407 Mountain Top Cir",
    "sg:city":"Austin",
    "sg:classifiers":[
        {
            "category":"Real Estate",
            "subcategory":"Real Estate Agent",
            "type":"Services"
        }
    ],
    "sg:phone":"+1 512 452 3248",
    "sg:postcode":"78731",
    "sg:province":"TX",
    "wof:name":"Bergstrom - Jackson",
    "wof:placetype":"venue"
},
  "geometry": {"coordinates":[-97.77248299999999,30.325454],"type":"Point"}
}