{
  "type": "Feature",
  "properties": {
    "iso:country":"US",
    "sg:address":"4302 Ironton Ave",
    "sg:city":"Lubbock",
    "sg:classifiers":[
        {
            "category":"Professional",
            "subcategory":"Art Services",
            "type":"Services"
        }
    ],
    "sg:phone":"+1 806 791 2877",
    "sg:postcode":"79407",
    "sg:province":"TX",
    "sg:tags":[
        "silk",
        "screen",
        "printing"
    ],
    "wof:name":"Stephen Joseph Inc",
    "wof:placetype":"venue"
},
  "geometry": {"coordinates":[-101.94985200000001,33.553605],"type":"Point"}
}