{
  "type": "Feature",
  "properties": {
    "iso:country":"US",
    "sg:address":"1117 E Court St",
    "sg:city":"Seguin",
    "sg:classifiers":[
        {
            "category":"Real Estate",
            "subcategory":"Real Estate Agent",
            "type":"Services"
        }
    ],
    "sg:phone":"+1 830 379 5251",
    "sg:postcode":"78155",
    "sg:province":"TX",
    "wof:name":"King Properties",
    "wof:placetype":"venue"
},
  "geometry": {"coordinates":[-97.951853,29.568971],"type":"Point"}
}