{
  "type": "Feature",
  "properties": {
    "iso:country":"US",
    "sg:address":"600 Sheffield Dr",
    "sg:city":"Richardson",
    "sg:classifiers":[
        {
            "category":"Wholesale",
            "subcategory":"Vending Machines",
            "type":"Manufacturing & Wholesale Goods"
        }
    ],
    "sg:phone":"+1 972 235 6257",
    "sg:postcode":"75081",
    "sg:province":"TX",
    "sg:tags":[
        "operator"
    ],
    "wof:name":"G&M Vending Service",
    "wof:placetype":"venue"
},
  "geometry": {"coordinates":[-96.72121199999999,32.930206],"type":"Point"}
}