{
  "type": "Feature",
  "properties": {
    "iso:country":"US",
    "sg:address":"1220 Broadway",
    "sg:city":"Lubbock",
    "sg:classifiers":[
        {
            "category":"Professional",
            "type":"Services"
        }
    ],
    "sg:phone":"+1 806 744 2294",
    "sg:postcode":"79401",
    "sg:province":"TX",
    "sg:tags":[
        "publication",
        "editorial"
    ],
    "wof:name":"Heavenly Editing & Publications",
    "wof:placetype":"venue"
},
  "geometry": {"coordinates":[-101.848163,33.5845],"type":"Point"}
}