{
  "type": "Feature",
  "properties": {
    "iso:country":"US",
    "sg:address":"1215 Davis St N",
    "sg:city":"Sulphur Springs",
    "sg:classifiers":[
        {
            "category":"Social Services",
            "subcategory":"Child Care",
            "type":"Services"
        }
    ],
    "sg:phone":"+1 903 885 3011",
    "sg:postcode":"75482",
    "sg:province":"TX",
    "wof:name":"Little Texans' Learning Ctr",
    "wof:placetype":"venue"
},
  "geometry": {"coordinates":[-95.60079399999999,33.154564],"type":"Point"}
}