{
  "type": "Feature",
  "properties": {
    "iso:country":"US",
    "sg:address":"9537 Dyer St",
    "sg:city":"El Paso",
    "sg:classifiers":[
        {
            "category":"Shopping",
            "subcategory":"Hobbies, Toys, & Games",
            "type":"Retail Goods"
        }
    ],
    "sg:phone":"+1 915 751 2030",
    "sg:postcode":"79924",
    "sg:province":"TX",
    "sg:tags":[
        "equipment",
        "ceramic",
        "supply"
    ],
    "wof:name":"Martin Ceramics & Crafts",
    "wof:placetype":"venue"
},
  "geometry": {"coordinates":[-106.42043099999999,31.881691],"type":"Point"}
}