{
  "type": "Feature",
  "properties": {
    "iso:country":"US",
    "sg:address":"620 E Euless Blvd",
    "sg:city":"Euless",
    "sg:classifiers":[
        {
            "category":"Travel",
            "subcategory":"Hotels & Motels",
            "type":"Entertainment"
        }
    ],
    "sg:phone":"+1 817 545 2222",
    "sg:postcode":"76040",
    "sg:province":"TX",
    "sg:tags":[
        "operation"
    ],
    "wof:name":"Great Western Inn",
    "wof:placetype":"venue"
},
  "geometry": {"coordinates":[-97.071145,32.836927],"type":"Point"}
}