{
  "type": "Feature",
  "properties": {
    "iso:country":"US",
    "sg:address":"506 N 38th St",
    "sg:city":"Killeen",
    "sg:classifiers":[
        {
            "category":"Retail",
            "subcategory":"Funeral Services",
            "type":"Services"
        }
    ],
    "sg:phone":"+1 254 699 8200",
    "sg:postcode":"76543",
    "sg:province":"TX",
    "sg:tags":[
        "director"
    ],
    "wof:name":"Harper-Talasek Funeral Home",
    "wof:placetype":"venue"
},
  "geometry": {"coordinates":[-97.698775,31.11654],"type":"Point"}
}