{
  "type": "Feature",
  "properties": {
    "iso:country":"US",
    "sg:address":"829 Main St",
    "sg:city":"Kerrville",
    "sg:classifiers":[
        {
            "category":"Real Estate",
            "subcategory":"Real Estate Agent",
            "type":"Services"
        }
    ],
    "sg:phone":"+1 830 896 2800",
    "sg:postcode":"78028",
    "sg:province":"TX",
    "wof:name":"Landmark Realty",
    "wof:placetype":"venue"
},
  "geometry": {"coordinates":[-99.139258,30.046199],"type":"Point"}
}