{
  "type": "Feature",
  "properties": {
    "iso:country":"US",
    "sg:address":"2004 Bobby Ln",
    "sg:city":"Granbury",
    "sg:classifiers":[
        {
            "category":"Food & Beverages",
            "subcategory":"Bakery",
            "type":"Retail Goods"
        }
    ],
    "sg:phone":"+1 817 279 7676",
    "sg:postcode":"76048",
    "sg:province":"TX",
    "wof:name":"Flowers Baking Co Tyler Llc",
    "wof:placetype":"venue"
},
  "geometry": {"coordinates":[-97.810722,32.437237],"type":"Point"}
}