{
  "type": "Feature",
  "properties": {
    "iso:country":"US",
    "sg:address":"12009 Coit Rd 5413",
    "sg:city":"Dallas",
    "sg:classifiers":[
        {
            "category":"Health Services",
            "subcategory":"Clinic",
            "type":"Services"
        },
        {
            "category":"Sports & Exercise",
            "subcategory":"Gym",
            "type":"Entertainment"
        }
    ],
    "sg:phone":"+1 469 248 5348",
    "sg:postcode":"75251",
    "sg:province":"TX",
    "sg:tags":[
        "trainer",
        "loss",
        "weight"
    ],
    "sg:website":"allstarfitnessgroup.com",
    "wof:name":"All-Star Fitness",
    "wof:placetype":"venue"
},
  "geometry": {"coordinates":[-96.76938699999999,32.911283],"type":"Point"}
}