{
  "type": "Feature",
  "properties": {
    "iso:country":"US",
    "sg:address":"11825 River View Way",
    "sg:city":"Aledo",
    "sg:classifiers":[
        {
            "category":"Professional",
            "subcategory":"Printing & Photocopies",
            "type":"Services"
        }
    ],
    "sg:phone":"+1 817 244 5929",
    "sg:postcode":"76008",
    "sg:province":"TX",
    "sg:tags":[
        "lithographer"
    ],
    "wof:name":"Dh Printing",
    "wof:placetype":"venue"
},
  "geometry": {"coordinates":[-97.52650800000001,32.710417],"type":"Point"}
}