{
  "type": "Feature",
  "properties": {
    "iso:country":"US",
    "sg:address":"5806 4th St",
    "sg:city":"Katy",
    "sg:classifiers":[
        {
            "category":"Restaurant",
            "type":"Food & Drink"
        }
    ],
    "sg:phone":"+1 281 391 8117",
    "sg:postcode":"77493",
    "sg:province":"TX",
    "sg:tags":[
        "eating"
    ],
    "wof:name":"Georgia Gates Tea Room",
    "wof:placetype":"venue"
},
  "geometry": {"coordinates":[-95.824341,29.789134],"type":"Point"}
}