{
  "type": "Feature",
  "properties": {
    "iso:country":"US",
    "sg:address":"19120 W Lake Houston Pkwy",
    "sg:city":"Humble",
    "sg:classifiers":[
        {
            "category":"Social Services",
            "subcategory":"Child Care",
            "type":"Services"
        }
    ],
    "sg:phone":"+1 281 852 7738",
    "sg:postcode":"77346",
    "sg:province":"TX",
    "sg:tags":[
        "nursery",
        "day"
    ],
    "wof:name":"Montessori Unlimited",
    "wof:placetype":"venue"
},
  "geometry": {"coordinates":[-95.161652,29.99601],"type":"Point"}
}