{
  "type": "Feature",
  "properties": {
    "iso:country":"US",
    "sg:address":"13515 Somersworth Dr",
    "sg:city":"Houston",
    "sg:classifiers":[
        {
            "category":"Retail",
            "subcategory":"Repair Shop",
            "type":"Services"
        }
    ],
    "sg:phone":"+1 713 849 0449",
    "sg:postcode":"77041",
    "sg:province":"TX",
    "sg:tags":[
        "electrical"
    ],
    "wof:name":"Houston West Office Machines",
    "wof:placetype":"venue"
},
  "geometry": {"coordinates":[-95.613849,29.86243],"type":"Point"}
}