{
  "type": "Feature",
  "properties": {
    "iso:country":"US",
    "sg:address":"5401 N Central Expy",
    "sg:city":"Dallas",
    "sg:classifiers":[
        {
            "category":"Banks & Credit Unions",
            "subcategory":"Atm",
            "type":"Services"
        }
    ],
    "sg:phone":"+1 214 320 0079",
    "sg:postcode":"75205",
    "sg:province":"TX",
    "sg:tags":[
        "bankruptcy"
    ],
    "sg:website":"www.dallasbankruptcylawyer.com",
    "wof:name":"Dallas Bankruptcy Lawyer",
    "wof:placetype":"venue"
},
  "geometry": {"coordinates":[-96.78142699999999,32.831308],"type":"Point"}
}