{
  "type": "Feature",
  "properties": {
    "iso:country":"US",
    "sg:address":"3000 Blackburn St",
    "sg:city":"Amarillo",
    "sg:classifiers":[
        {
            "category":"Sports & Exercise",
            "subcategory":"Gym",
            "type":"Entertainment"
        }
    ],
    "sg:phone":"+1 806 359 5438",
    "sg:postcode":"79109",
    "sg:province":"TX",
    "sg:tags":[
        "club",
        "health",
        "studio",
        "gymnasium"
    ],
    "sg:website":"www.goldsgymamarillo.com",
    "wof:name":"Gold's Gym",
    "wof:placetype":"venue"
},
  "geometry": {"coordinates":[-101.87084299999999,35.189095],"type":"Point"}
}