{
  "type": "Feature",
  "properties": {
    "iso:country":"US",
    "sg:address":"1110 Willard St",
    "sg:city":"Houston",
    "sg:classifiers":[
        {
            "category":"Professional",
            "subcategory":"Art Services",
            "type":"Services"
        }
    ],
    "sg:phone":"+1 713 522 8201",
    "sg:postcode":"77006",
    "sg:province":"TX",
    "sg:tags":[
        "commercial",
        "design"
    ],
    "wof:name":"Lead M",
    "wof:placetype":"venue"
},
  "geometry": {"coordinates":[-95.39352700000001,29.75115],"type":"Point"}
}