{
  "type": "Feature",
  "properties": {
    "iso:country":"US",
    "sg:address":"17015 Simsbrook Dr",
    "sg:city":"Pflugerville",
    "sg:classifiers":[
        {
            "category":"Organizations",
            "subcategory":"Religious Organization",
            "type":"Services"
        }
    ],
    "sg:phone":"+1 512 990 2111",
    "sg:postcode":"78660",
    "sg:province":"TX",
    "sg:tags":[
        "church"
    ],
    "wof:name":"Christian Hope Outreach",
    "wof:placetype":"venue"
},
  "geometry": {"coordinates":[-97.63574699999999,30.458331],"type":"Point"}
}