{
  "type": "Feature",
  "properties": {
    "iso:country":"US",
    "sg:address":"4520 Beechnut St",
    "sg:city":"Houston",
    "sg:classifiers":[
        {
            "category":"Food & Beverages",
            "subcategory":"Groceries & Convenience Stores",
            "type":"Retail Goods"
        }
    ],
    "sg:phone":"+1 713 661 8242",
    "sg:postcode":"77096",
    "sg:province":"TX",
    "wof:name":"Beechnut Corner Food Store",
    "wof:placetype":"venue"
},
  "geometry": {"coordinates":[-95.455591,29.689225],"type":"Point"}
}