{
  "type": "Feature",
  "properties": {
    "iso:country":"US",
    "sg:address":"5600 Wichita St",
    "sg:city":"Fort Worth",
    "sg:classifiers":[
        {
            "category":"Personal",
            "subcategory":"Beauty Salon",
            "type":"Services"
        }
    ],
    "sg:phone":"+1 817 535 9623",
    "sg:postcode":"76119",
    "sg:province":"TX",
    "sg:tags":[
        "shop"
    ],
    "wof:name":"Worth It Beauty Salon",
    "wof:placetype":"venue"
},
  "geometry": {"coordinates":[-97.280193,32.676045],"type":"Point"}
}