{
  "type": "Feature",
  "properties": {
    "iso:country":"US",
    "sg:address":"5238 De Zavala Rd",
    "sg:city":"San Antonio",
    "sg:classifiers":[
        {
            "category":"Ice Cream",
            "type":"Food & Drink"
        }
    ],
    "sg:menulink":"http://www.allmenus.com/tx/san-antonio/242741-baskin-robbins/menu/",
    "sg:phone":"+1 210 699 3911",
    "sg:postcode":"78249",
    "sg:province":"TX",
    "sg:tags":[
        "american"
    ],
    "wof:name":"Baskin-Robbins",
    "wof:placetype":"venue"
},
  "geometry": {"coordinates":[-98.588442,29.563457],"type":"Point"}
}