{
  "type": "Feature",
  "properties": {
    "iso:country":"US",
    "sg:address":"2294 Nantucket Village Cir",
    "sg:city":"Dallas",
    "sg:classifiers":[
        {
            "category":"Restaurant",
            "type":"Food & Drink"
        }
    ],
    "sg:phone":"+1 972 288 5811",
    "sg:postcode":"75227",
    "sg:province":"TX",
    "sg:tags":[
        "eating"
    ],
    "wof:name":"Down South Catering",
    "wof:placetype":"venue"
},
  "geometry": {"coordinates":[-96.644373,32.749839],"type":"Point"}
}