{
  "type": "Feature",
  "properties": {
    "iso:country":"US",
    "sg:address":"3310 N Houston Ave",
    "sg:city":"Humble",
    "sg:classifiers":[
        {
            "category":"Building & Trades",
            "subcategory":"Construction",
            "type":"Services"
        }
    ],
    "sg:phone":"+1 281 540 2792",
    "sg:postcode":"77338",
    "sg:province":"TX",
    "sg:tags":[
        "contractor"
    ],
    "wof:name":"Rhino Construction",
    "wof:placetype":"venue"
},
  "geometry": {"coordinates":[-95.248924,30.024504],"type":"Point"}
}