{
  "type": "Feature",
  "properties": {
    "iso:country":"US",
    "sg:address":"12141 Katy Fwy",
    "sg:city":"Houston",
    "sg:classifiers":[
        {
            "category":"Shopping",
            "subcategory":"Clothing, Apparel, & Fashions",
            "type":"Retail Goods"
        }
    ],
    "sg:phone":"+1 281 597 1110",
    "sg:postcode":"77079",
    "sg:province":"TX",
    "sg:tags":[
        "western"
    ],
    "sg:website":"www.cavenders.com",
    "wof:name":"Cavender's Boot City Inc",
    "wof:placetype":"venue"
},
  "geometry": {"coordinates":[-95.599406,29.784163],"type":"Point"}
}