{
  "type": "Feature",
  "properties": {
    "iso:country":"US",
    "sg:address":"101 W 10th St",
    "sg:city":"Borger",
    "sg:classifiers":[
        {
            "category":"Food & Beverages",
            "subcategory":"Groceries & Convenience Stores",
            "type":"Retail Goods"
        }
    ],
    "sg:phone":"+1 806 273 5649",
    "sg:postcode":"79007",
    "sg:province":"TX",
    "sg:tags":[
        "grocer"
    ],
    "wof:name":"B & R Thriftway 54",
    "wof:placetype":"venue"
},
  "geometry": {"coordinates":[-101.390987,35.676821],"type":"Point"}
}