{
  "type": "Feature",
  "properties": {
    "iso:country":"US",
    "sg:address":"6300 W Parker Rd Ste 100",
    "sg:city":"Plano",
    "sg:classifiers":[
        {
            "category":"Science Facility",
            "type":"Public Place"
        }
    ],
    "sg:phone":"+1 972 608 5160",
    "sg:postcode":"75093",
    "sg:province":"TX",
    "sg:tags":[
        "development",
        "laboratories-research"
    ],
    "wof:name":"Institute For Spine & Biomedical Researc",
    "wof:placetype":"venue"
},
  "geometry": {"coordinates":[-96.837068,33.045139],"type":"Point"}
}