{
  "type": "Feature",
  "properties": {
    "iso:country":"US",
    "sg:address":"1801 Lockwood Dr",
    "sg:city":"Houston",
    "sg:classifiers":[
        {
            "category":"Organizations",
            "subcategory":"Religious Organization",
            "type":"Services"
        }
    ],
    "sg:phone":"+1 713 675 5742",
    "sg:postcode":"77020",
    "sg:province":"TX",
    "sg:tags":[
        "church"
    ],
    "wof:name":"Christian Love",
    "wof:placetype":"venue"
},
  "geometry": {"coordinates":[-95.315979,29.777729],"type":"Point"}
}