{
  "type": "Feature",
  "properties": {
    "iso:country":"US",
    "sg:address":"14576 China Spring Rd",
    "sg:city":"China Spring",
    "sg:classifiers":[
        {
            "category":"Shopping",
            "subcategory":"Computers & Home Electronics",
            "type":"Retail Goods"
        }
    ],
    "sg:phone":"+1 254 836 4971",
    "sg:postcode":"76633",
    "sg:province":"TX",
    "wof:name":"JC Computers",
    "wof:placetype":"venue"
},
  "geometry": {"coordinates":[-97.32439100000001,31.65432],"type":"Point"}
}