{
  "type": "Feature",
  "properties": {
    "iso:country":"US",
    "sg:address":"585 Byrd St",
    "sg:city":"Vidor",
    "sg:classifiers":[
        {
            "category":"Professional",
            "subcategory":"Accounting & Tax Preparation",
            "type":"Services"
        }
    ],
    "sg:phone":"+1 409 769 3846",
    "sg:postcode":"77662",
    "sg:province":"TX",
    "sg:tags":[
        "auditing",
        "bookkeeping",
        "return",
        "filing"
    ],
    "wof:name":"Edna Thompson Tax Service",
    "wof:placetype":"venue"
},
  "geometry": {"coordinates":[-94.020399,30.113795],"type":"Point"}
}