{
  "type": "Feature",
  "properties": {
    "iso:country":"US",
    "sg:address":"3838 Oak Lawn Ave Ste 910",
    "sg:city":"Dallas",
    "sg:classifiers":[
        {
            "category":"Professional",
            "subcategory":"Accounting & Tax Preparation",
            "type":"Services"
        }
    ],
    "sg:phone":"+1 214 526 6644",
    "sg:postcode":"75219",
    "sg:province":"TX",
    "sg:tags":[
        "accountant"
    ],
    "wof:name":"Danny Looney Inc",
    "wof:placetype":"venue"
},
  "geometry": {"coordinates":[-96.802299,32.815201],"type":"Point"}
}