{
  "type": "Feature",
  "properties": {
    "iso:country":"US",
    "sg:address":"312 E Mable St",
    "sg:city":"Odessa",
    "sg:classifiers":[
        {
            "category":"Retail",
            "subcategory":"Auto Repair",
            "type":"Services"
        }
    ],
    "sg:phone":"+1 432 334 6936",
    "sg:postcode":"79761",
    "sg:province":"TX",
    "wof:name":"Garcia Mechanic Shop",
    "wof:placetype":"venue"
},
  "geometry": {"coordinates":[-102.360151,31.841302],"type":"Point"}
}