{
  "type": "Feature",
  "properties": {
    "iso:country":"US",
    "sg:address":"12820 W Highway 71",
    "sg:city":"Austin",
    "sg:classifiers":[
        {
            "category":"Coffee & Tea",
            "type":"Food & Drink"
        }
    ],
    "sg:phone":"+1 512 263 1855",
    "sg:postcode":"78738",
    "sg:province":"TX",
    "sg:tags":[
        "espresso",
        "restaurant"
    ],
    "wof:name":"Texenza Coffee",
    "wof:placetype":"venue"
},
  "geometry": {"coordinates":[-97.94059799999999,30.306932],"type":"Point"}
}