{
  "type": "Feature",
  "properties": {
    "iso:country":"US",
    "sg:address":"4503 34th St",
    "sg:city":"Lubbock",
    "sg:classifiers":[
        {
            "category":"Local Transit",
            "type":"Transportation"
        }
    ],
    "sg:phone":"+1 806 794 7573",
    "sg:postcode":"79410",
    "sg:province":"TX",
    "wof:name":"Wheelcare Transportation",
    "wof:placetype":"venue"
},
  "geometry": {"coordinates":[-101.908509,33.563183],"type":"Point"}
}