{
  "type": "Feature",
  "properties": {
    "iso:country":"US",
    "sg:address":"2816 Atrium Dr",
    "sg:city":"Grand Prairie",
    "sg:classifiers":[
        {
            "category":"Professional",
            "type":"Services"
        }
    ],
    "sg:phone":"+1 972 641 7310",
    "sg:postcode":"75052",
    "sg:province":"TX",
    "wof:name":"In House PC Doctor",
    "wof:placetype":"venue"
},
  "geometry": {"coordinates":[-97.053117,32.688996],"type":"Point"}
}