{
  "type": "Feature",
  "properties": {
    "iso:country":"US",
    "sg:address":"1111 W North Loop Blvd",
    "sg:city":"Austin",
    "sg:classifiers":[
        {
            "category":"Government",
            "subcategory":"Office",
            "type":"Public Place"
        }
    ],
    "sg:phone":"+1 512 377 0344",
    "sg:postcode":"78756",
    "sg:province":"TX",
    "wof:name":"Commission-Blind Warehouse",
    "wof:placetype":"venue"
},
  "geometry": {"coordinates":[-97.733943,30.323197],"type":"Point"}
}