{
  "type": "Feature",
  "properties": {
    "iso:country":"US",
    "sg:address":"301 Horseshoe Bend Trl",
    "sg:city":"Mertzon",
    "sg:classifiers":[
        {
            "category":"Building & Trades",
            "subcategory":"Construction",
            "type":"Services"
        },
        {
            "category":"Military Area",
            "subcategory":"Armory",
            "type":"Public Place"
        }
    ],
    "sg:phone":"+1 325 835 4583",
    "sg:postcode":"76941",
    "sg:province":"TX",
    "sg:tags":[
        "repair",
        "fence-sales",
        "fence",
        "contractor"
    ],
    "wof:name":"Robert E Steger",
    "wof:placetype":"venue"
},
  "geometry": {"coordinates":[-100.775096,31.310979],"type":"Point"}
}