{
  "type": "Feature",
  "properties": {
    "iso:country":"US",
    "sg:address":"3408 Foxfield Trl",
    "sg:city":"Mckinney",
    "sg:classifiers":[
        {
            "category":"Building & Trades",
            "subcategory":"Equipment Rental",
            "type":"Services"
        }
    ],
    "sg:phone":"+1 972 540 6886",
    "sg:postcode":"75071",
    "sg:province":"TX",
    "sg:tags":[
        "yard",
        "store"
    ],
    "wof:name":"Lease With Stephanie At Onsite",
    "wof:placetype":"venue"
},
  "geometry": {"coordinates":[-96.648585,33.235451],"type":"Point"}
}