{
  "type": "Feature",
  "properties": {
    "iso:country":"US",
    "sg:address":"20301 Rhodes Rd",
    "sg:city":"Spring",
    "sg:classifiers":[
        {
            "category":"Sports & Exercise",
            "subcategory":"Gym",
            "type":"Entertainment"
        }
    ],
    "sg:phone":"+1 281 350 0197",
    "sg:postcode":"77388",
    "sg:province":"TX",
    "sg:tags":[
        "equipment",
        "fitness"
    ],
    "wof:name":"Giesecke Co",
    "wof:placetype":"venue"
},
  "geometry": {"coordinates":[-95.49678900000001,30.064563],"type":"Point"}
}