{
  "type": "Feature",
  "properties": {
    "iso:country":"US",
    "sg:address":"4418 Valleyfield Dr",
    "sg:city":"San Antonio",
    "sg:classifiers":[
        {
            "category":"Banks & Credit Unions",
            "subcategory":"Bank",
            "type":"Services"
        }
    ],
    "sg:phone":"+1 210 337 9228",
    "sg:postcode":"78222",
    "sg:province":"TX",
    "sg:tags":[
        "mortgage"
    ],
    "wof:name":"Contreras Mortgage",
    "wof:placetype":"venue"
},
  "geometry": {"coordinates":[-98.40577,29.376065],"type":"Point"}
}