{
  "type": "Feature",
  "properties": {
    "iso:country":"US",
    "sg:address":"3004 George Richey Rd",
    "sg:city":"Gladewater",
    "sg:classifiers":[
        {
            "category":"Government",
            "subcategory":"Office",
            "type":"Public Place"
        }
    ],
    "sg:phone":"+1 903 845 3917",
    "sg:postcode":"75647",
    "sg:province":"TX",
    "sg:tags":[
        "city"
    ],
    "wof:name":"Warren City City Hall",
    "wof:placetype":"venue"
},
  "geometry": {"coordinates":[-94.9011,32.547548],"type":"Point"}
}