{
  "type": "Feature",
  "properties": {
    "iso:country":"US",
    "sg:address":"304 E Trunk St",
    "sg:city":"Crandall",
    "sg:classifiers":[
        {
            "category":"Restaurant",
            "type":"Food & Drink"
        }
    ],
    "sg:phone":"+1 972 427 3663",
    "sg:postcode":"75114",
    "sg:province":"TX",
    "sg:tags":[
        "pizza"
    ],
    "wof:name":"J Bs Pizza",
    "wof:placetype":"venue"
},
  "geometry": {"coordinates":[-96.45372,32.629228],"type":"Point"}
}