{
  "type": "Feature",
  "properties": {
    "iso:country":"US",
    "sg:address":"1204 Wyndham Hill Ln",
    "sg:city":"Southlake",
    "sg:classifiers":[
        {
            "category":"Building & Trades",
            "subcategory":"Equipment Rental",
            "type":"Services"
        }
    ],
    "sg:phone":"+1 817 421 3576",
    "sg:postcode":"76092",
    "sg:province":"TX",
    "wof:name":"Intergrated Electronic Media",
    "wof:placetype":"venue"
},
  "geometry": {"coordinates":[-97.166774,32.925557],"type":"Point"}
}