{
  "type": "Feature",
  "properties": {
    "iso:country":"US",
    "sg:address":"660 Parker Sq",
    "sg:city":"Flower Mound",
    "sg:classifiers":[
        {
            "category":"Manufacturing",
            "subcategory":"Chemicals & Compounds",
            "type":"Manufacturing & Wholesale Goods"
        }
    ],
    "sg:phone":"+1 972 899 5990",
    "sg:postcode":"75028",
    "sg:province":"TX",
    "sg:tags":[
        "preparation",
        "pharmaceutical",
        "mfg"
    ],
    "wof:name":"Ultimate Sports Nutrition",
    "wof:placetype":"venue"
},
  "geometry": {"coordinates":[-97.051073,33.039223],"type":"Point"}
}