{
  "type": "Feature",
  "properties": {
    "iso:country":"US",
    "sg:address":"109 Avenue F",
    "sg:city":"Stafford",
    "sg:classifiers":[
        {
            "category":"Restaurant",
            "type":"Food & Drink"
        }
    ],
    "sg:phone":"+1 281 261 8282",
    "sg:postcode":"77477",
    "sg:province":"TX",
    "sg:tags":[
        "mexican"
    ],
    "wof:name":"Huarache Azteca Express",
    "wof:placetype":"venue"
},
  "geometry": {"coordinates":[-95.55871500000001,29.616101],"type":"Point"}
}