{
  "type": "Feature",
  "properties": {
    "iso:country":"US",
    "sg:address":"13450 N US Hwy 183",
    "sg:city":"Austin",
    "sg:classifiers":[
        {
            "category":"Restaurant",
            "type":"Food & Drink"
        }
    ],
    "sg:phone":"+1 512 336 5999",
    "sg:postcode":"78750",
    "sg:province":"TX",
    "sg:tags":[
        "eating"
    ],
    "wof:name":"Tino's Greek Cafe",
    "wof:placetype":"venue"
},
  "geometry": {"coordinates":[-97.787645,30.444529],"type":"Point"}
}