{
  "type": "Feature",
  "properties": {
    "iso:country":"US",
    "sg:address":"1211 Burrows Chapel Rd",
    "sg:city":"Whitesboro",
    "sg:classifiers":[
        {
            "category":"Retail",
            "subcategory":"Repair Shop",
            "type":"Services"
        }
    ],
    "sg:phone":"+1 940 668 2256",
    "sg:postcode":"76273",
    "sg:province":"TX",
    "sg:tags":[
        "water",
        "heater"
    ],
    "wof:name":"Starnes Plumbing",
    "wof:placetype":"venue"
},
  "geometry": {"coordinates":[-96.922962,33.844045],"type":"Point"}
}