{
  "type": "Feature",
  "properties": {
    "iso:country":"US",
    "sg:address":"4120 Rio Bravo St",
    "sg:city":"El Paso",
    "sg:classifiers":[
        {
            "category":"Wholesale",
            "subcategory":"Electrical",
            "type":"Manufacturing & Wholesale Goods"
        }
    ],
    "sg:phone":"+1 915 533 1566",
    "sg:postcode":"79902",
    "sg:province":"TX",
    "sg:tags":[
        "instrument",
        "electronic"
    ],
    "wof:name":"Wilson-Mohr Inc",
    "wof:placetype":"venue"
},
  "geometry": {"coordinates":[-106.512862,31.795093],"type":"Point"}
}