{
  "type": "Feature",
  "properties": {
    "iso:country":"US",
    "sg:address":"12521 Market Street Rd",
    "sg:city":"Houston",
    "sg:classifiers":[
        {
            "category":"Autos & Motor Vehicles",
            "subcategory":"Automobile Sales",
            "type":"Retail Goods"
        }
    ],
    "sg:phone":"+1 713 330 7278",
    "sg:postcode":"77015",
    "sg:province":"TX",
    "sg:tags":[
        "dealers-used",
        "car",
        "used",
        "cars-wholesale",
        "new"
    ],
    "wof:name":"Jaramillo Auto Sales",
    "wof:placetype":"venue"
},
  "geometry": {"coordinates":[-95.21494300000001,29.767269],"type":"Point"}
}