{
  "type": "Feature",
  "properties": {
    "iso:country":"US",
    "sg:address":"402 N Nursery Rd Ste 100",
    "sg:city":"Irving",
    "sg:classifiers":[
        {
            "category":"Retail",
            "subcategory":"Auto Repair",
            "type":"Services"
        }
    ],
    "sg:phone":"+1 972 721 1588",
    "sg:postcode":"75061",
    "sg:province":"TX",
    "wof:name":"Lima Auto Repair",
    "wof:placetype":"venue"
},
  "geometry": {"coordinates":[-96.934303,32.815102],"type":"Point"}
}