{
  "type": "Feature",
  "properties": {
    "iso:country":"US",
    "sg:address":"110 W 4th St",
    "sg:city":"Sinton",
    "sg:classifiers":[
        {
            "category":"Place Of Worship",
            "subcategory":"Church",
            "type":"Public Place"
        },
        {
            "category":"Place Of Worship",
            "type":"Public Place"
        }
    ],
    "sg:phone":"+1 361 364 2036",
    "sg:postcode":"78387",
    "sg:province":"TX",
    "sg:tags":[
        "churches-baptist-general",
        "churches-baptist"
    ],
    "wof:name":"Primera Iglesia Bautista",
    "wof:placetype":"venue"
},
  "geometry": {"coordinates":[-97.51067,28.03056],"type":"Point"}
}