{
  "type": "Feature",
  "properties": {
    "iso:country":"US",
    "sg:address":"1019 San Bernardo Ave",
    "sg:city":"Laredo",
    "sg:classifiers":[
        {
            "category":"Banks & Credit Unions",
            "subcategory":"Bank",
            "type":"Services"
        }
    ],
    "sg:phone":"+1 956 726 9781",
    "sg:postcode":"78040",
    "sg:province":"TX",
    "sg:tags":[
        "loan"
    ],
    "wof:name":"Reliable Finance Co",
    "wof:placetype":"venue"
},
  "geometry": {"coordinates":[-99.504519,27.50861],"type":"Point"}
}