{
  "type": "Feature",
  "properties": {
    "iso:country":"US",
    "sg:address":"10670 N Central Expy",
    "sg:city":"Dallas",
    "sg:classifiers":[
        {
            "category":"Professional",
            "subcategory":"Employment Agencies",
            "type":"Services"
        }
    ],
    "sg:phone":"+1 214 739 5007",
    "sg:postcode":"75231",
    "sg:province":"TX",
    "sg:tags":[
        "leasing",
        "help",
        "supply"
    ],
    "wof:name":"Staffnet",
    "wof:placetype":"venue"
},
  "geometry": {"coordinates":[-96.76873399999999,32.892243],"type":"Point"}
}