{
  "type": "Feature",
  "properties": {
    "iso:country":"US",
    "sg:address":"8818 W Hwy 80",
    "sg:city":"Midland",
    "sg:classifiers":[
        {
            "category":"Organizations",
            "subcategory":"Community Association",
            "type":"Services"
        }
    ],
    "sg:phone":"+1 432 561 9905",
    "sg:postcode":"79706",
    "sg:province":"TX",
    "sg:tags":[
        "educational"
    ],
    "wof:name":"Permian Basin Tech Prep Odessa",
    "wof:placetype":"venue"
},
  "geometry": {"coordinates":[-102.20667,31.928513],"type":"Point"}
}