{
  "type": "Feature",
  "properties": {
    "iso:country":"US",
    "sg:address":"11501 Chimney Rock Rd",
    "sg:city":"Houston",
    "sg:classifiers":[
        {
            "category":"Insurance",
            "subcategory":"Insurance Agent",
            "type":"Services"
        }
    ],
    "sg:phone":"+1 713 721 5600",
    "sg:postcode":"77035",
    "sg:province":"TX",
    "wof:name":"Eagle Benefits Group Health",
    "wof:placetype":"venue"
},
  "geometry": {"coordinates":[-95.47681799999999,29.657839],"type":"Point"}
}