{
  "type": "Feature",
  "properties": {
    "iso:country":"US",
    "sg:address":"1701 N 8th St",
    "sg:city":"Mcallen",
    "sg:classifiers":[
        {
            "category":"Professional",
            "subcategory":"Accounting & Tax Preparation",
            "type":"Services"
        },
        {
            "category":"Professional",
            "subcategory":"Management & Consulting",
            "type":"Services"
        },
        {
            "category":"Banks & Credit Unions",
            "subcategory":"Financial Services",
            "type":"Services"
        }
    ],
    "sg:phone":"+1 956 686 1796",
    "sg:postcode":"78501",
    "sg:province":"TX",
    "sg:tags":[
        "consultant",
        "financing",
        "planning",
        "public",
        "accountants-certified"
    ],
    "wof:name":"Zamora R Financial Services",
    "wof:placetype":"venue"
},
  "geometry": {"coordinates":[-98.225212,26.21863],"type":"Point"}
}