{
  "type": "Feature",
  "properties": {
    "iso:country":"US",
    "sg:address":"1100 California St",
    "sg:city":"Bryan",
    "sg:classifiers":[
        {
            "category":"Building & Trades",
            "subcategory":"Plumbing",
            "type":"Services"
        }
    ],
    "sg:phone":"+1 979 775 1907",
    "sg:postcode":"77803",
    "sg:province":"TX",
    "sg:tags":[
        "conditioner",
        "air",
        "heater"
    ],
    "wof:name":"Affordable Handyman Service",
    "wof:placetype":"venue"
},
  "geometry": {"coordinates":[-96.38416599999999,30.691152],"type":"Point"}
}