{
  "type": "Feature",
  "properties": {
    "iso:country":"US",
    "sg:address":"100 S 1st St",
    "sg:city":"Conroe",
    "sg:classifiers":[
        {
            "category":"Wholesale",
            "subcategory":"Auto Parts",
            "type":"Manufacturing & Wholesale Goods"
        }
    ],
    "sg:phone":"+1 936 441 0255",
    "sg:postcode":"77301",
    "sg:province":"TX",
    "sg:tags":[
        "automobile",
        "supply"
    ],
    "wof:name":"X L Parts",
    "wof:placetype":"venue"
},
  "geometry": {"coordinates":[-95.453908,30.310277],"type":"Point"}
}