{
  "type": "Feature",
  "properties": {
    "iso:country":"US",
    "sg:address":"606 N Loop 336 E",
    "sg:city":"Conroe",
    "sg:classifiers":[
        {
            "category":"Food & Beverages",
            "subcategory":"Groceries & Convenience Stores",
            "type":"Retail Goods"
        }
    ],
    "sg:phone":"+1 936 539 5011",
    "sg:postcode":"77301",
    "sg:province":"TX",
    "sg:tags":[
        "grocer"
    ],
    "wof:name":"St Joseph Food Mart Inc",
    "wof:placetype":"venue"
},
  "geometry": {"coordinates":[-95.443924,30.34002],"type":"Point"}
}