{
  "type": "Feature",
  "properties": {
    "iso:country":"US",
    "sg:address":"1212 Capitol Ave",
    "sg:city":"San Antonio",
    "sg:classifiers":[
        {
            "category":"Retail",
            "subcategory":"Repair Shop",
            "type":"Services"
        }
    ],
    "sg:phone":"+1 210 731 8392",
    "sg:postcode":"78201",
    "sg:province":"TX",
    "sg:tags":[
        "welding"
    ],
    "wof:name":"Dr Welding & Fabrication",
    "wof:placetype":"venue"
},
  "geometry": {"coordinates":[-98.513898,29.464725],"type":"Point"}
}