{
  "type": "Feature",
  "properties": {
    "iso:country":"US",
    "sg:address":"1601 Burleson Retta Rd",
    "sg:city":"Burleson",
    "sg:classifiers":[
        {
            "category":"Utilities",
            "subcategory":"Telephone",
            "type":"Services"
        }
    ],
    "sg:phone":"+1 817 426 2202",
    "sg:postcode":"76028",
    "sg:province":"TX",
    "sg:tags":[
        "telecommunication"
    ],
    "wof:name":"Tektron Electrical Systems Inc",
    "wof:placetype":"venue"
},
  "geometry": {"coordinates":[-97.292671,32.560605],"type":"Point"}
}