{
  "type": "Feature",
  "properties": {
    "iso:country":"US",
    "sg:address":"704 Tanglewood Ln",
    "sg:city":"Arlington",
    "sg:classifiers":[
        {
            "category":"Shopping",
            "subcategory":"Photographic Equipment",
            "type":"Retail Goods"
        }
    ],
    "sg:phone":"+1 817 265 9262",
    "sg:postcode":"76012",
    "sg:province":"TX",
    "sg:tags":[
        "supply"
    ],
    "wof:name":"Ernest D Swersky",
    "wof:placetype":"venue"
},
  "geometry": {"coordinates":[-97.144356,32.744543],"type":"Point"}
}