{
  "type": "Feature",
  "properties": {
    "iso:country":"US",
    "sg:address":"1300 26th St",
    "sg:city":"Snyder",
    "sg:classifiers":[
        {
            "category":"Government",
            "subcategory":"Police Station",
            "type":"Public Place"
        },
        {
            "category":"Government",
            "subcategory":"Office",
            "type":"Public Place"
        }
    ],
    "sg:phone":"+1 325 573 5631",
    "sg:postcode":"79549",
    "sg:province":"TX",
    "sg:tags":[
        "government-state",
        "department"
    ],
    "wof:name":"Texas-State Public Safety Department",
    "wof:placetype":"venue"
},
  "geometry": {"coordinates":[-100.91127,32.716019],"type":"Point"}
}