{
  "type": "Feature",
  "properties": {
    "iso:country":"US",
    "sg:address":"7300 Blanco Rd",
    "sg:city":"San Antonio",
    "sg:classifiers":[
        {
            "category":"Health Services",
            "subcategory":"Doctor",
            "type":"Services"
        }
    ],
    "sg:phone":"+1 210 733 0990",
    "sg:postcode":"78216",
    "sg:province":"TX",
    "sg:tags":[
        "clinic"
    ],
    "wof:name":"Center For Complimentary Med",
    "wof:placetype":"venue"
},
  "geometry": {"coordinates":[-98.504783,29.523568],"type":"Point"}
}