{
  "type": "Feature",
  "properties": {
    "iso:country":"US",
    "sg:address":"460 Morningwood Dr",
    "sg:city":"San Marcos",
    "sg:classifiers":[
        {
            "category":"Wholesale",
            "subcategory":"Groceries",
            "type":"Manufacturing & Wholesale Goods"
        }
    ],
    "sg:phone":"+1 512 353 0025",
    "sg:postcode":"78666",
    "sg:province":"TX",
    "sg:tags":[
        "confectionery"
    ],
    "wof:name":"Rammar Distributing",
    "wof:placetype":"venue"
},
  "geometry": {"coordinates":[-97.979305,29.961683],"type":"Point"}
}