{
  "type": "Feature",
  "properties": {
    "iso:country":"US",
    "sg:address":"7 W Main St",
    "sg:city":"Humble",
    "sg:classifiers":[
        {
            "category":"Bars & Pubs",
            "type":"Food & Drink"
        }
    ],
    "sg:phone":"+1 281 540 2582",
    "sg:postcode":"77338",
    "sg:province":"TX",
    "wof:name":"Club Episode 2008",
    "wof:placetype":"venue"
},
  "geometry": {"coordinates":[-95.265852,29.99832],"type":"Point"}
}