{
  "type": "Feature",
  "properties": {
    "iso:country":"US",
    "sg:address":"170 Texas Kiln Pl",
    "sg:city":"Smithville",
    "sg:classifiers":[
        {
            "category":"Home & Garden",
            "subcategory":"Building Materials",
            "type":"Retail Goods"
        },
        {
            "category":"Manufacturing",
            "subcategory":"Lumber",
            "type":"Manufacturing & Wholesale Goods"
        }
    ],
    "sg:phone":"+1 512 360 2803",
    "sg:postcode":"78957",
    "sg:province":"TX",
    "sg:tags":[
        "hardwood",
        "mill"
    ],
    "sg:website":"www.texaskilnproducts.com",
    "wof:name":"Texas Kiln Products Inc",
    "wof:placetype":"venue"
},
  "geometry": {"coordinates":[-97.230527,30.080647],"type":"Point"}
}