{
  "type": "Feature",
  "properties": {
    "iso:country":"US",
    "sg:address":"4843 Bucknell St",
    "sg:city":"San Antonio",
    "sg:classifiers":[
        {
            "category":"Building & Trades",
            "subcategory":"Plumbing",
            "type":"Services"
        }
    ],
    "sg:phone":"+1 210 696 0806",
    "sg:postcode":"78249",
    "sg:province":"TX",
    "sg:tags":[
        "plumbing",
        "contractor"
    ],
    "wof:name":"Mike's Plumbing",
    "wof:placetype":"venue"
},
  "geometry": {"coordinates":[-98.582384,29.571168],"type":"Point"}
}