{
  "type": "Feature",
  "properties": {
    "iso:country":"US",
    "sg:address":"1011 S 6th St",
    "sg:city":"Richmond",
    "sg:classifiers":[
        {
            "category":"Building & Trades",
            "subcategory":"Construction",
            "type":"Services"
        }
    ],
    "sg:phone":"+1 281 239 7030",
    "sg:postcode":"77469",
    "sg:province":"TX",
    "sg:tags":[
        "general",
        "contractor"
    ],
    "wof:name":"MMM Construction Products",
    "wof:placetype":"venue"
},
  "geometry": {"coordinates":[-95.760254,29.575963],"type":"Point"}
}