{
  "type": "Feature",
  "properties": {
    "iso:country":"US",
    "sg:address":"1017 Ellis Ave",
    "sg:city":"Lufkin",
    "sg:classifiers":[
        {
            "category":"Health Services",
            "subcategory":"Clinic",
            "type":"Services"
        }
    ],
    "sg:phone":"+1 936 526 3397",
    "sg:postcode":"75904",
    "sg:province":"TX",
    "sg:tags":[
        "home",
        "care"
    ],
    "wof:name":"Alieve Health Care Supplies In",
    "wof:placetype":"venue"
},
  "geometry": {"coordinates":[-94.73908900000001,31.33632],"type":"Point"}
}