{
  "type": "Feature",
  "properties": {
    "iso:country":"US",
    "sg:address":"2918 County Ave",
    "sg:city":"Texarkana",
    "sg:classifiers":[
        {
            "category":"Insurance",
            "subcategory":"Insurance Agent",
            "type":"Services"
        }
    ],
    "sg:phone":"+1 870 772 0313",
    "sg:postcode":"71854",
    "sg:province":"TX",
    "wof:name":"Shelter Insurance",
    "wof:placetype":"venue"
},
  "geometry": {"coordinates":[-94.03799600000001,33.450476],"type":"Point"}
}