{
  "type": "Feature",
  "properties": {
    "iso:country":"US",
    "sg:address":"3338 Stalcup Rd",
    "sg:city":"Fort Worth",
    "sg:classifiers":[
        {
            "category":"Organizations",
            "subcategory":"Religious Organization",
            "type":"Services"
        }
    ],
    "sg:phone":"+1 817 451 2422",
    "sg:postcode":"76119",
    "sg:province":"TX",
    "wof:name":"Heavenly Gospel Outreach Ctr",
    "wof:placetype":"venue"
},
  "geometry": {"coordinates":[-97.23797399999999,32.713481],"type":"Point"}
}