{
  "type": "Feature",
  "properties": {
    "iso:country":"US",
    "sg:address":"1100 Summit Ave",
    "sg:city":"Plano",
    "sg:classifiers":[
        {
            "category":"Mining & Drilling",
            "type":"Manufacturing & Wholesale Goods"
        }
    ],
    "sg:phone":"+1 972 424 5324",
    "sg:postcode":"75074",
    "sg:province":"TX",
    "sg:tags":[
        "development",
        "gas",
        "oil",
        "exploration"
    ],
    "wof:name":"Euro American Capital Corp",
    "wof:placetype":"venue"
},
  "geometry": {"coordinates":[-96.69390799999999,33.009445],"type":"Point"}
}