{
  "type": "Feature",
  "properties": {
    "iso:country":"US",
    "sg:address":"208 S Houston St",
    "sg:city":"Kaufman",
    "sg:classifiers":[
        {
            "category":"Organizations",
            "subcategory":"Religious Organization",
            "type":"Services"
        }
    ],
    "sg:phone":"+1 972 932 2838",
    "sg:postcode":"75142",
    "sg:province":"TX",
    "sg:tags":[
        "church"
    ],
    "wof:name":"Methodist Church First United",
    "wof:placetype":"venue"
},
  "geometry": {"coordinates":[-96.31252600000001,32.588309],"type":"Point"}
}