{
  "type": "Feature",
  "properties": {
    "iso:country":"US",
    "sg:address":"5151 Flynn Pkwy",
    "sg:city":"Corpus Christi",
    "sg:classifiers":[
        {
            "category":"Education",
            "subcategory":"Vocational School",
            "type":"Public Place"
        }
    ],
    "sg:phone":"+1 361 852 2000",
    "sg:postcode":"78411",
    "sg:province":"TX",
    "sg:tags":[
        "real estate"
    ],
    "sg:website":"www.reicc.com",
    "wof:name":"Real Estate Institute",
    "wof:placetype":"venue"
},
  "geometry": {"coordinates":[-97.39233,27.716855],"type":"Point"}
}