{
  "type": "Feature",
  "properties": {
    "iso:country":"US",
    "sg:address":"4480 State Hwy 276",
    "sg:city":"Rockwall",
    "sg:classifiers":[
        {
            "category":"Building & Trades",
            "subcategory":"Plumbing",
            "type":"Services"
        }
    ],
    "sg:phone":"+1 972 771 3697",
    "sg:postcode":"75032",
    "sg:province":"TX",
    "sg:tags":[
        "plumbing",
        "contractor"
    ],
    "wof:name":"Gentry Plumbing",
    "wof:placetype":"venue"
},
  "geometry": {"coordinates":[-96.38023699999999,32.904579],"type":"Point"}
}