{
  "type": "Feature",
  "properties": {
    "iso:country":"US",
    "sg:address":"301 W Park Place Dr",
    "sg:city":"Lancaster",
    "sg:classifiers":[
        {
            "category":"Organizations",
            "subcategory":"Religious Organization",
            "type":"Services"
        }
    ],
    "sg:phone":"+1 469 547 0550",
    "sg:postcode":"75134",
    "sg:province":"TX",
    "wof:name":"Menders House Church",
    "wof:placetype":"venue"
},
  "geometry": {"coordinates":[-96.76125399999999,32.605027],"type":"Point"}
}