{
  "type": "Feature",
  "properties": {
    "iso:country":"US",
    "sg:address":"1000 Austin St",
    "sg:city":"Richmond",
    "sg:classifiers":[
        {
            "category":"Social Services",
            "type":"Services"
        }
    ],
    "sg:phone":"+1 281 232 2394",
    "sg:postcode":"77469",
    "sg:province":"TX",
    "sg:tags":[
        "crisis",
        "intervention"
    ],
    "wof:name":"Family To Family Pregnacy",
    "wof:placetype":"venue"
},
  "geometry": {"coordinates":[-95.76451299999999,29.576622],"type":"Point"}
}