{
  "type": "Feature",
  "properties": {
    "iso:country":"US",
    "sg:address":"1823 Fort View Rd",
    "sg:city":"Austin",
    "sg:classifiers":[
        {
            "category":"Health Services",
            "subcategory":"Health Practitioner",
            "type":"Services"
        }
    ],
    "sg:phone":"+1 512 326 9151",
    "sg:postcode":"78704",
    "sg:province":"TX",
    "sg:tags":[
        "psychotherapist"
    ],
    "wof:name":"Scott A Harpst",
    "wof:placetype":"venue"
},
  "geometry": {"coordinates":[-97.787502,30.230855],"type":"Point"}
}