{
  "type": "Feature",
  "properties": {
    "iso:country":"US",
    "sg:address":"15051 Barfield Ln",
    "sg:city":"Kaufman",
    "sg:classifiers":[
        {
            "category":"Wholesale",
            "subcategory":"Non-durable Goods",
            "type":"Manufacturing & Wholesale Goods"
        }
    ],
    "sg:phone":"+1 972 932 2213",
    "sg:postcode":"75142",
    "sg:province":"TX",
    "wof:name":"Pearl Birds",
    "wof:placetype":"venue"
},
  "geometry": {"coordinates":[-96.088757,32.571993],"type":"Point"}
}