{
  "type": "Feature",
  "properties": {
    "iso:country":"US",
    "sg:address":"4818 N FM 565",
    "sg:city":"Mont Belvieu",
    "sg:classifiers":[
        {
            "category":"Government",
            "subcategory":"Fire Station",
            "type":"Public Place"
        }
    ],
    "sg:phone":"+1 281 576 2655",
    "sg:postcode":"77520",
    "sg:province":"TX",
    "sg:tags":[
        "department"
    ],
    "wof:name":"Old River Winfree Fire Dept",
    "wof:placetype":"venue"
},
  "geometry": {"coordinates":[-94.85466099999999,29.861729],"type":"Point"}
}