{
  "type": "Feature",
  "properties": {
    "iso:country":"US",
    "sg:address":"3000 Weslayan Ave Suite 225",
    "sg:city":"Houston",
    "sg:classifiers":[
        {
            "category":"Health Services",
            "subcategory":"Health Practitioner",
            "type":"Services"
        }
    ],
    "sg:phone":"+1 713 960 1994",
    "sg:postcode":"77027",
    "sg:province":"TX",
    "sg:tags":[
        "acupuncture"
    ],
    "sg:website":"www.jieboacupuncture.com",
    "wof:name":"Jie Bo Acupuncture",
    "wof:placetype":"venue"
},
  "geometry": {"coordinates":[-95.44219,29.737708],"type":"Point"}
}