{
  "type": "Feature",
  "properties": {
    "iso:country":"US",
    "sg:address":"3800 Buffalo Speedway",
    "sg:city":"Houston",
    "sg:classifiers":[
        {
            "category":"Professional",
            "subcategory":"Accounting & Tax Preparation",
            "type":"Services"
        }
    ],
    "sg:phone":"+1 713 986 5000",
    "sg:postcode":"77005",
    "sg:province":"TX",
    "sg:tags":[
        "consultant"
    ],
    "wof:name":"Burr Wolff",
    "wof:placetype":"venue"
},
  "geometry": {"coordinates":[-95.42843000000001,29.730922],"type":"Point"}
}