{
  "type": "Feature",
  "properties": {
    "iso:country":"US",
    "sg:address":"5409 Hidalgo St",
    "sg:city":"Houston",
    "sg:classifiers":[
        {
            "category":"Building & Trades",
            "subcategory":"Construction",
            "type":"Services"
        }
    ],
    "sg:phone":"+1 713 552 1190",
    "sg:postcode":"77056",
    "sg:province":"TX",
    "sg:tags":[
        "contractor"
    ],
    "wof:name":"Rohe & Wright Builders",
    "wof:placetype":"venue"
},
  "geometry": {"coordinates":[-95.471846,29.734965],"type":"Point"}
}