{
  "type": "Feature",
  "properties": {
    "iso:country":"US",
    "sg:address":"1717 Main St Ste 4300",
    "sg:city":"Dallas",
    "sg:classifiers":[
        {
            "category":"Professional",
            "subcategory":"Lawyer & Legal Services",
            "type":"Services"
        }
    ],
    "sg:phone":"+1 214 761 4358",
    "sg:postcode":"75201",
    "sg:province":"TX",
    "wof:name":"Whitten David E Atty",
    "wof:placetype":"venue"
},
  "geometry": {"coordinates":[-96.796997,32.781101],"type":"Point"}
}