{
  "type": "Feature",
  "properties": {
    "iso:country":"US",
    "sg:address":"2226 Orchard Trl",
    "sg:city":"Garland",
    "sg:classifiers":[
        {
            "category":"Restaurant",
            "type":"Food & Drink"
        }
    ],
    "sg:phone":"+1 972 530 1235",
    "sg:postcode":"75040",
    "sg:province":"TX",
    "sg:tags":[
        "eating"
    ],
    "wof:name":"Casual Catering",
    "wof:placetype":"venue"
},
  "geometry": {"coordinates":[-96.60329900000001,32.93539],"type":"Point"}
}