{
  "type": "Feature",
  "properties": {
    "iso:country":"US",
    "sg:address":"1521 N Hoard Ave",
    "sg:city":"Sherman",
    "sg:classifiers":[
        {
            "category":"Building & Trades",
            "subcategory":"Pest Control",
            "type":"Services"
        }
    ],
    "sg:phone":"+1 903 892 3238",
    "sg:postcode":"75090",
    "sg:province":"TX",
    "wof:name":"Results Environmental Pest",
    "wof:placetype":"venue"
},
  "geometry": {"coordinates":[-96.590389,33.655675],"type":"Point"}
}