{
  "type": "Feature",
  "properties": {
    "iso:country":"US",
    "sg:address":"15241 Tradesman",
    "sg:city":"San Antonio",
    "sg:classifiers":[
        {
            "category":"Building & Trades",
            "subcategory":"Cleaning & Sanitation",
            "type":"Services"
        }
    ],
    "sg:phone":"+1 210 479 0821",
    "sg:postcode":"78249",
    "sg:province":"TX",
    "sg:tags":[
        "lighting",
        "maintenance"
    ],
    "wof:name":"Amtech Lighting Services Co",
    "wof:placetype":"venue"
},
  "geometry": {"coordinates":[-98.58443800000001,29.587782],"type":"Point"}
}