{
  "type": "Feature",
  "properties": {
    "iso:country":"US",
    "sg:address":"618 Broadway St",
    "sg:city":"Plainview",
    "sg:classifiers":[
        {
            "category":"Home & Garden",
            "subcategory":"Furniture",
            "type":"Retail Goods"
        }
    ],
    "sg:phone":"+1 806 296 0180",
    "sg:postcode":"79072",
    "sg:province":"TX",
    "wof:name":"Best Sales and Rentals",
    "wof:placetype":"venue"
},
  "geometry": {"coordinates":[-101.70296,34.186752],"type":"Point"}
}