{
  "type": "Feature",
  "properties": {
    "iso:country":"US",
    "sg:address":"5085 Westheimer Rd",
    "sg:city":"Houston",
    "sg:classifiers":[
        {
            "category":"Shopping",
            "subcategory":"Clothing, Apparel, & Fashions",
            "type":"Retail Goods"
        }
    ],
    "sg:phone":"+1 713 627 2057",
    "sg:postcode":"77056",
    "sg:province":"TX",
    "sg:website":"www.brooksbrothers.com",
    "wof:name":"Brooks Brothers",
    "wof:placetype":"venue"
},
  "geometry": {"coordinates":[-95.46277000000001,29.740636],"type":"Point"}
}