{
  "type": "Feature",
  "properties": {
    "iso:country":"US",
    "sg:address":"2810 E Trinity Mills Rd",
    "sg:city":"Carrollton",
    "sg:classifiers":[
        {
            "category":"Professional",
            "subcategory":"Lawyer & Legal Services",
            "type":"Services"
        }
    ],
    "sg:phone":"+1 972 418 6376",
    "sg:postcode":"75006",
    "sg:province":"TX",
    "sg:tags":[
        "notary"
    ],
    "wof:name":"Ups Store the",
    "wof:placetype":"venue"
},
  "geometry": {"coordinates":[-96.854401,32.987],"type":"Point"}
}