{
  "type": "Feature",
  "properties": {
    "iso:country":"US",
    "sg:address":"7817 Rockwood Ln",
    "sg:city":"Austin",
    "sg:classifiers":[
        {
            "category":"Personal",
            "subcategory":"Beauty Salon",
            "type":"Services"
        }
    ],
    "sg:phone":"+1 512 791 6008",
    "sg:postcode":"78757",
    "sg:province":"TX",
    "sg:tags":[
        "hair"
    ],
    "wof:name":"Todd Steward Haircolour",
    "wof:placetype":"venue"
},
  "geometry": {"coordinates":[-97.738148,30.358762],"type":"Point"}
}