{
  "type": "Feature",
  "properties": {
    "iso:country":"US",
    "sg:address":"615 Ciruela St",
    "sg:city":"San Antonio",
    "sg:classifiers":[
        {
            "category":"Shopping",
            "subcategory":"Clothing, Apparel, & Fashions",
            "type":"Retail Goods"
        }
    ],
    "sg:phone":"+1 210 824 3505",
    "sg:postcode":"78209",
    "sg:province":"TX",
    "sg:tags":[
        "family"
    ],
    "wof:name":"Worth It",
    "wof:placetype":"venue"
},
  "geometry": {"coordinates":[-98.477467,29.488463],"type":"Point"}
}