{
  "type": "Feature",
  "properties": {
    "iso:country":"US",
    "sg:address":"20503 Dawn Dr",
    "sg:city":"Lago Vista",
    "sg:classifiers":[
        {
            "category":"Real Estate",
            "subcategory":"Real Estate Services",
            "type":"Services"
        }
    ],
    "sg:phone":"+1 512 267 3233",
    "sg:postcode":"78645",
    "sg:province":"TX",
    "sg:tags":[
        "company",
        "title"
    ],
    "wof:name":"First American Title Co",
    "wof:placetype":"venue"
},
  "geometry": {"coordinates":[-97.985652,30.453234],"type":"Point"}
}