{
  "type": "Feature",
  "properties": {
    "iso:country":"US",
    "sg:address":"11210 Craighead Dr",
    "sg:city":"Houston",
    "sg:classifiers":[
        {
            "category":"Education",
            "subcategory":"Music School",
            "type":"Public Place"
        }
    ],
    "sg:phone":"+1 713 667 7029",
    "sg:postcode":"77025",
    "sg:province":"TX",
    "sg:tags":[
        "instrument",
        "teacher",
        "musical"
    ],
    "wof:name":"Allen Banjo Company",
    "wof:placetype":"venue"
},
  "geometry": {"coordinates":[-95.445801,29.662201],"type":"Point"}
}