{
  "type": "Feature",
  "properties": {
    "iso:country":"US",
    "sg:address":"6908 Ridgewood Dr",
    "sg:city":"Fort Worth",
    "sg:classifiers":[
        {
            "category":"Real Estate",
            "subcategory":"Developer",
            "type":"Services"
        }
    ],
    "sg:phone":"+1 817 294 2936",
    "sg:postcode":"76132",
    "sg:province":"TX",
    "wof:name":"Pride Properties Develpmn",
    "wof:placetype":"venue"
},
  "geometry": {"coordinates":[-97.437496,32.65173],"type":"Point"}
}