{
  "type": "Feature",
  "properties": {
    "iso:country":"US",
    "sg:address":"1410 W Victorson Ave",
    "sg:city":"Houston",
    "sg:classifiers":[
        {
            "category":"Wholesale",
            "subcategory":"Furniture",
            "type":"Manufacturing & Wholesale Goods"
        }
    ],
    "sg:phone":"+1 713 453 7249",
    "sg:postcode":"77015",
    "sg:province":"TX",
    "wof:name":"C JS Superior Products",
    "wof:placetype":"venue"
},
  "geometry": {"coordinates":[-95.174823,29.769079],"type":"Point"}
}