{
  "type": "Feature",
  "properties": {
    "iso:country":"US",
    "sg:address":"1100 W Sandlewood Dr",
    "sg:city":"Pampa",
    "sg:classifiers":[
        {
            "category":"Manufacturing",
            "subcategory":"Printing",
            "type":"Manufacturing & Wholesale Goods"
        }
    ],
    "sg:phone":"+1 806 665 1006",
    "sg:postcode":"79065",
    "sg:province":"TX",
    "sg:tags":[
        "publisher"
    ],
    "wof:name":"Focus Magazine",
    "wof:placetype":"venue"
},
  "geometry": {"coordinates":[-100.980304,35.56836],"type":"Point"}
}