{
  "type": "Feature",
  "properties": {
    "iso:country":"US",
    "sg:address":"1800 Texas Ave S",
    "sg:city":"College Station",
    "sg:classifiers":[
        {
            "category":"Personal",
            "subcategory":"Tanning Parlor",
            "type":"Services"
        },
        {
            "category":"Personal",
            "type":"Services"
        }
    ],
    "sg:phone":"+1 979 694 1103",
    "sg:postcode":"77840",
    "sg:province":"TX",
    "sg:tags":[
        "salon"
    ],
    "sg:website":"www.planetbeach.com",
    "wof:name":"Planet Beach Tanning Salon",
    "wof:placetype":"venue"
},
  "geometry": {"coordinates":[-96.3175,30.613923],"type":"Point"}
}