{
  "type": "Feature",
  "properties": {
    "iso:country":"US",
    "sg:address":"10530 Windsor Ln",
    "sg:city":"Houston",
    "sg:classifiers":[
        {
            "category":"Autos & Motor Vehicles",
            "subcategory":"Automobile Sales",
            "type":"Retail Goods"
        }
    ],
    "sg:phone":"+1 281 879 9860",
    "sg:postcode":"77031",
    "sg:province":"TX",
    "sg:tags":[
        "car",
        "dealer"
    ],
    "wof:name":"A & M Car Co",
    "wof:placetype":"venue"
},
  "geometry": {"coordinates":[-95.563417,29.643398],"type":"Point"}
}