{
  "type": "Feature",
  "properties": {
    "iso:country":"US",
    "sg:address":"17400 Judson Rd",
    "sg:city":"San Antonio",
    "sg:classifiers":[
        {
            "category":"Manufacturing",
            "subcategory":"Printing",
            "type":"Manufacturing & Wholesale Goods"
        }
    ],
    "sg:phone":"+1 830 980 3336",
    "sg:postcode":"78247",
    "sg:province":"TX",
    "sg:tags":[
        "newspaper"
    ],
    "wof:name":"Bulverde Community News",
    "wof:placetype":"venue"
},
  "geometry": {"coordinates":[-98.38542099999999,29.59911],"type":"Point"}
}