{
  "type": "Feature",
  "properties": {
    "iso:country":"US",
    "sg:address":"2023 W McDermott Dr",
    "sg:city":"Allen",
    "sg:classifiers":[
        {
            "category":"Health Services",
            "subcategory":"Doctor",
            "type":"Services"
        }
    ],
    "sg:phone":"+1 972 727 5700",
    "sg:postcode":"75013",
    "sg:province":"TX",
    "wof:name":"Hubbard Dental",
    "wof:placetype":"venue"
},
  "geometry": {"coordinates":[-96.732713,33.100738],"type":"Point"}
}