{
  "type": "Feature",
  "properties": {
    "iso:country":"US",
    "sg:address":"18333 Egret Bay Blvd",
    "sg:city":"Houston",
    "sg:classifiers":[
        {
            "category":"Banks & Credit Unions",
            "subcategory":"Investment Brokerage",
            "type":"Services"
        },
        {
            "category":"Insurance",
            "subcategory":"Insurance Agent",
            "type":"Services"
        }
    ],
    "sg:phone":"+1 281 335 3999",
    "sg:postcode":"77058",
    "sg:province":"TX",
    "sg:tags":[
        "planning",
        "consultant",
        "consulting",
        "management",
        "financial"
    ],
    "wof:name":"Michael Landry Insurance Co",
    "wof:placetype":"venue"
},
  "geometry": {"coordinates":[-95.10101299999999,29.541478],"type":"Point"}
}