{
  "type": "Feature",
  "properties": {
    "iso:country":"US",
    "sg:address":"1302 Hawk Trl",
    "sg:city":"Copperas Cove",
    "sg:classifiers":[
        {
            "category":"Professional",
            "type":"Services"
        }
    ],
    "sg:phone":"+1 254 542 6448",
    "sg:postcode":"76522",
    "sg:province":"TX",
    "sg:tags":[
        "establishment"
    ],
    "wof:name":"JFH Enterprises",
    "wof:placetype":"venue"
},
  "geometry": {"coordinates":[-97.88652999999999,31.126305],"type":"Point"}
}