{
  "type": "Feature",
  "properties": {
    "iso:country":"US",
    "sg:address":"204 N 5th St",
    "sg:city":"Carrizo Springs",
    "sg:classifiers":[
        {
            "category":"Real Estate",
            "subcategory":"Real Estate Services",
            "type":"Services"
        }
    ],
    "sg:phone":"+1 830 876 2926",
    "sg:postcode":"78834",
    "sg:province":"TX",
    "wof:name":"Border Title Group",
    "wof:placetype":"venue"
},
  "geometry": {"coordinates":[-99.86000300000001,28.523252],"type":"Point"}
}