{
  "type": "Feature",
  "properties": {
    "iso:country":"US",
    "sg:address":"2407 Lily Ln",
    "sg:city":"Highlands",
    "sg:classifiers":[
        {
            "category":"Professional",
            "subcategory":"Art Services",
            "type":"Services"
        }
    ],
    "sg:phone":"+1 281 426 4661",
    "sg:postcode":"77562",
    "sg:province":"TX",
    "sg:tags":[
        "commercial",
        "design"
    ],
    "wof:name":"Tiflo Graphics",
    "wof:placetype":"venue"
},
  "geometry": {"coordinates":[-95.021483,29.814152],"type":"Point"}
}