{
  "type": "Feature",
  "properties": {
    "iso:country":"US",
    "sg:address":"5604 Travis Cook Rd",
    "sg:city":"Austin",
    "sg:classifiers":[
        {
            "category":"Personal",
            "subcategory":"Beauty Salon",
            "type":"Services"
        }
    ],
    "sg:phone":"+1 512 301 7521",
    "sg:postcode":"78735",
    "sg:province":"TX",
    "sg:tags":[
        "shop"
    ],
    "wof:name":"2u Salon",
    "wof:placetype":"venue"
},
  "geometry": {"coordinates":[-97.888909,30.26134],"type":"Point"}
}