{
  "type": "Feature",
  "properties": {
    "iso:country":"US",
    "sg:address":"15911 la Madera Rio",
    "sg:city":"Helotes",
    "sg:classifiers":[
        {
            "category":"Building & Trades",
            "subcategory":"Electrical",
            "type":"Services"
        }
    ],
    "sg:phone":"+1 210 834 7363",
    "sg:postcode":"78023",
    "sg:province":"TX",
    "sg:tags":[
        "electrician"
    ],
    "wof:name":"Brothers Electric",
    "wof:placetype":"venue"
},
  "geometry": {"coordinates":[-98.65644500000001,29.592476],"type":"Point"}
}