{
  "type": "Feature",
  "properties": {
    "iso:country":"US",
    "sg:address":"12709 Toepperwein Rd",
    "sg:city":"Live Oak",
    "sg:classifiers":[
        {
            "category":"Health Services",
            "subcategory":"Doctor",
            "type":"Services"
        }
    ],
    "sg:phone":"+1 210 599 8882",
    "sg:postcode":"78233",
    "sg:province":"TX",
    "sg:tags":[
        "physician",
        "surgeon"
    ],
    "wof:name":"Alamo City Eye Physicians",
    "wof:placetype":"venue"
},
  "geometry": {"coordinates":[-98.347567,29.553959],"type":"Point"}
}