{
  "type": "Feature",
  "properties": {
    "iso:country":"US",
    "sg:address":"382 County Road 650",
    "sg:city":"Dayton",
    "sg:classifiers":[
        {
            "category":"Farming",
            "subcategory":"Farm",
            "type":"Manufacturing & Wholesale Goods"
        }
    ],
    "sg:phone":"+1 936 258 7922",
    "sg:postcode":"77535",
    "sg:province":"TX",
    "wof:name":"Kendrick Persell",
    "wof:placetype":"venue"
},
  "geometry": {"coordinates":[-94.880253,30.134701],"type":"Point"}
}