{
  "type": "Feature",
  "properties": {
    "iso:country":"US",
    "sg:address":"13355 Noel Rd",
    "sg:city":"Dallas",
    "sg:classifiers":[
        {
            "category":"Real Estate",
            "subcategory":"Real Estate Agent",
            "type":"Services"
        }
    ],
    "sg:phone":"+1 972 960 4877",
    "sg:postcode":"75240",
    "sg:province":"TX",
    "wof:name":"Norwood Properties",
    "wof:placetype":"venue"
},
  "geometry": {"coordinates":[-96.81811999999999,32.929623],"type":"Point"}
}