{
  "type": "Feature",
  "properties": {
    "iso:country":"US",
    "sg:address":"3325 N 10th St",
    "sg:city":"Mcallen",
    "sg:classifiers":[
        {
            "category":"Shopping",
            "subcategory":"Computers & Home Electronics",
            "type":"Retail Goods"
        },
        {
            "category":"Shopping",
            "subcategory":"Musical Instruments",
            "type":"Retail Goods"
        }
    ],
    "sg:phone":"+1 956 682 6147",
    "sg:postcode":"78501",
    "sg:province":"TX",
    "sg:tags":[
        "repair",
        "used"
    ],
    "sg:website":"www.melhart.com",
    "wof:name":"Melhart Music Center",
    "wof:placetype":"venue"
},
  "geometry": {"coordinates":[-98.225026,26.232829],"type":"Point"}
}