{
  "type": "Feature",
  "properties": {
    "iso:country":"US",
    "sg:address":"1605 Lake Bluff Dr",
    "sg:city":"Garland",
    "sg:classifiers":[
        {
            "category":"Health Services",
            "subcategory":"Doctor",
            "type":"Services"
        }
    ],
    "sg:phone":"+1 214 828 8455",
    "sg:postcode":"75043",
    "sg:province":"TX",
    "sg:tags":[
        "dental",
        "consulting"
    ],
    "wof:name":"Dr Roger Alexander",
    "wof:placetype":"venue"
},
  "geometry": {"coordinates":[-96.582756,32.865163],"type":"Point"}
}