{
  "type": "Feature",
  "properties": {
    "iso:country":"US",
    "sg:address":"6750 Corpus Christi Drive",
    "sg:city":"Austin",
    "sg:classifiers":[
        {
            "category":"Autos & Motor Vehicles",
            "subcategory":"Auto Supplies",
            "type":"Retail Goods"
        },
        {
            "category":"Retail",
            "subcategory":"Auto Repair",
            "type":"Services"
        }
    ],
    "sg:phone":"+1 512 335 4343",
    "sg:postcode":"78729",
    "sg:province":"TX",
    "sg:tags":[
        "automobile",
        "part",
        "truck"
    ],
    "sg:website":"www.foundationautorepair.com",
    "wof:name":"Foundation Auto Repair",
    "wof:placetype":"venue"
},
  "geometry": {"coordinates":[-97.750472,30.44261],"type":"Point"}
}