{
  "type": "Feature",
  "properties": {
    "iso:country":"US",
    "sg:address":"217 Pennsylvania St",
    "sg:city":"Webster",
    "sg:classifiers":[
        {
            "category":"Government",
            "subcategory":"Fire Station",
            "type":"Public Place"
        }
    ],
    "sg:phone":"+1 281 332 2426",
    "sg:postcode":"77598",
    "sg:province":"TX",
    "sg:tags":[
        "department",
        "protection",
        "police"
    ],
    "sg:website":"http://www.cityofwebster.com",
    "wof:name":"Webster Police Department",
    "wof:placetype":"venue"
},
  "geometry": {"coordinates":[-95.117028,29.534873],"type":"Point"}
}