{
  "type": "Feature",
  "properties": {
    "iso:country":"US",
    "sg:address":"322 W Texas Ave",
    "sg:city":"Baytown",
    "sg:classifiers":[
        {
            "category":"Home & Garden",
            "subcategory":"Carpets & Floor Coverings",
            "type":"Retail Goods"
        }
    ],
    "sg:phone":"+1 281 422 5600",
    "sg:postcode":"77520",
    "sg:province":"TX",
    "sg:tags":[
        "store",
        "flooring"
    ],
    "wof:name":"Texas Carpet & Flooring",
    "wof:placetype":"venue"
},
  "geometry": {"coordinates":[-94.970843,29.733189],"type":"Point"}
}