{
  "type": "Feature",
  "properties": {
    "iso:country":"US",
    "sg:address":"1300 Post Oak Blvd",
    "sg:city":"Houston",
    "sg:classifiers":[
        {
            "category":"Utilities",
            "subcategory":"Water",
            "type":"Services"
        }
    ],
    "sg:phone":"+1 281 356 7542",
    "sg:postcode":"77056",
    "sg:province":"TX",
    "sg:tags":[
        "sewer",
        "district"
    ],
    "wof:name":"NW Harris County Municipal Uti",
    "wof:placetype":"venue"
},
  "geometry": {"coordinates":[-95.458884,29.753128],"type":"Point"}
}