{
  "type": "Feature",
  "properties": {
    "iso:country":"US",
    "sg:address":"14054 Memorial Dr",
    "sg:city":"Houston",
    "sg:classifiers":[
        {
            "category":"Restaurant",
            "type":"Food & Drink"
        },
        {
            "category":"Food & Beverages",
            "subcategory":"Meat & Fish",
            "type":"Retail Goods"
        }
    ],
    "sg:menulink":"http://www.allmenus.com/tx/houston/152508-honeybaked-ham/menu/",
    "sg:phone":"+1 281 496 0001",
    "sg:postcode":"77079",
    "sg:province":"TX",
    "sg:tags":[
        "american"
    ],
    "wof:name":"The HoneyBaked Ham Company",
    "wof:placetype":"venue"
},
  "geometry": {"coordinates":[-95.590808,29.770622],"type":"Point"}
}