{
  "type": "Feature",
  "properties": {
    "iso:country":"US",
    "sg:address":"6407 Lake Bluff Dr",
    "sg:city":"Dallas",
    "sg:classifiers":[
        {
            "category":"Retail",
            "subcategory":"Laundry & Dry Cleaning",
            "type":"Services"
        }
    ],
    "sg:phone":"+1 972 298 6442",
    "sg:postcode":"75249",
    "sg:province":"TX",
    "sg:tags":[
        "garment",
        "agent"
    ],
    "wof:name":"Dyer Systems Inc",
    "wof:placetype":"venue"
},
  "geometry": {"coordinates":[-96.968385,32.646257],"type":"Point"}
}