{
  "type": "Feature",
  "properties": {
    "iso:country":"US",
    "sg:address":"5809 Delaney Rd",
    "sg:city":"Hitchcock",
    "sg:classifiers":[
        {
            "category":"Real Estate",
            "subcategory":"Real Estate Operator",
            "type":"Services"
        }
    ],
    "sg:phone":"+1 409 986 5508",
    "sg:postcode":"77563",
    "sg:province":"TX",
    "sg:tags":[
        "building",
        "apartment"
    ],
    "wof:name":"Mesquite Woods Apartments",
    "wof:placetype":"venue"
},
  "geometry": {"coordinates":[-95.020405,29.361845],"type":"Point"}
}