{
  "type": "Feature",
  "properties": {
    "iso:country":"US",
    "sg:address":"106 E Pine St",
    "sg:city":"Ector",
    "sg:classifiers":[
        {
            "category":"Retail",
            "subcategory":"Auto Repair",
            "type":"Services"
        }
    ],
    "sg:phone":"+1 903 961 3955",
    "sg:postcode":"75439",
    "sg:province":"TX",
    "sg:tags":[
        "repairing",
        "automobile"
    ],
    "wof:name":"Payne's Garage",
    "wof:placetype":"venue"
},
  "geometry": {"coordinates":[-96.273276,33.579229],"type":"Point"}
}