{
  "type": "Feature",
  "properties": {
    "iso:country":"US",
    "sg:address":"1611 N I- 35E",
    "sg:city":"Carrollton",
    "sg:phone":"+1 972 245 6366",
    "sg:postcode":"75006",
    "sg:province":"TX",
    "sg:tags":[
        "equipment",
        "commercial"
    ],
    "wof:name":"No Guns Neon Sign",
    "wof:placetype":"venue"
},
  "geometry": {"coordinates":[-96.916095,32.961382],"type":"Point"}
}