{
  "type": "Feature",
  "properties": {
    "iso:country":"US",
    "sg:address":"2220 Handley Dr",
    "sg:city":"Fort Worth",
    "sg:classifiers":[
        {
            "category":"Restaurant",
            "type":"Food & Drink"
        }
    ],
    "sg:phone":"+1 817 496 3361",
    "sg:postcode":"76112",
    "sg:province":"TX",
    "wof:name":"Charlie's Pizza & Italian",
    "wof:placetype":"venue"
},
  "geometry": {"coordinates":[-97.216364,32.747685],"type":"Point"}
}