{
  "type": "Feature",
  "properties": {
    "iso:country":"US",
    "sg:address":"2001 Cross Timbers Rd",
    "sg:city":"Flower Mound",
    "sg:classifiers":[
        {
            "category":"Deli",
            "type":"Food & Drink"
        },
        {
            "category":"Cafe",
            "type":"Food & Drink"
        }
    ],
    "sg:menulink":"http://www.allmenus.com/tx/lewisville/251168-cafe-green-bean-/menu/",
    "sg:phone":"+1 972 355 4492",
    "sg:postcode":"75028",
    "sg:province":"TX",
    "sg:tags":[
        "american"
    ],
    "wof:name":"Cafe Green Bean ",
    "wof:placetype":"venue"
},
  "geometry": {"coordinates":[-97.05921600000001,33.034262],"type":"Point"}
}