{
  "type": "Feature",
  "properties": {
    "iso:country":"US",
    "sg:address":"4412 Caroline St",
    "sg:city":"Houston",
    "sg:classifiers":[
        {
            "category":"Professional",
            "subcategory":"Lawyer & Legal Services",
            "type":"Services"
        }
    ],
    "sg:phone":"+1 713 821 0102",
    "sg:postcode":"77004",
    "sg:province":"TX",
    "wof:name":"Lance Nguyen Atty",
    "wof:placetype":"venue"
},
  "geometry": {"coordinates":[-95.380798,29.7323],"type":"Point"}
}