{
  "type": "Feature",
  "properties": {
    "iso:country":"US",
    "sg:address":"6302 Mountainclimb Dr",
    "sg:city":"Austin",
    "sg:classifiers":[
        {
            "category":"Organizations",
            "subcategory":"Membership Organization",
            "type":"Services"
        }
    ],
    "sg:phone":"+1 512 345 0004",
    "sg:postcode":"78731",
    "sg:province":"TX",
    "wof:name":"Hilburn John & Association",
    "wof:placetype":"venue"
},
  "geometry": {"coordinates":[-97.763751,30.350422],"type":"Point"}
}