{
  "type": "Feature",
  "properties": {
    "iso:country":"US",
    "sg:address":"217 Ave C",
    "sg:city":"Duncanville",
    "sg:classifiers":[
        {
            "category":"Personal",
            "subcategory":"Beauty Salon",
            "type":"Services"
        }
    ],
    "sg:phone":"+1 972 709 4460",
    "sg:postcode":"75116",
    "sg:province":"TX",
    "sg:tags":[
        "shop"
    ],
    "wof:name":"Ursulas Hair Salon",
    "wof:placetype":"venue"
},
  "geometry": {"coordinates":[-96.909768,32.64988],"type":"Point"}
}