{
  "type": "Feature",
  "properties": {
    "iso:country":"US",
    "sg:address":"2216 River Hills Rd",
    "sg:city":"Austin",
    "sg:classifiers":[
        {
            "category":"Health Services",
            "subcategory":"Clinic",
            "type":"Services"
        }
    ],
    "sg:phone":"+1 512 751 3653",
    "sg:postcode":"78733",
    "sg:province":"TX",
    "sg:tags":[
        "home",
        "care"
    ],
    "wof:name":"Hill Country Providers",
    "wof:placetype":"venue"
},
  "geometry": {"coordinates":[-97.84995600000001,30.341351],"type":"Point"}
}