{
  "type": "Feature",
  "properties": {
    "iso:country":"US",
    "sg:address":"9727 Cymbal Dr",
    "sg:city":"Stafford",
    "sg:classifiers":[
        {
            "category":"Building & Trades",
            "subcategory":"Construction",
            "type":"Services"
        }
    ],
    "sg:phone":"+1 281 568 7985",
    "sg:postcode":"77477",
    "sg:province":"TX",
    "sg:tags":[
        "house"
    ],
    "wof:name":"R & R Home Repairs & Rmdlg",
    "wof:placetype":"venue"
},
  "geometry": {"coordinates":[-95.547646,29.640259],"type":"Point"}
}