{
  "type": "Feature",
  "properties": {
    "iso:country":"US",
    "sg:address":"115 W 3rd St",
    "sg:city":"Arlington",
    "sg:classifiers":[
        {
            "category":"Real Estate",
            "subcategory":"Real Estate Operator",
            "type":"Services"
        }
    ],
    "sg:phone":"+1 817 275 2414",
    "sg:postcode":"76010",
    "sg:province":"TX",
    "sg:tags":[
        "building",
        "apartment"
    ],
    "wof:name":"Alpha Delta Apartments",
    "wof:placetype":"venue"
},
  "geometry": {"coordinates":[-97.108563,32.73021],"type":"Point"}
}