{
  "type": "Feature",
  "properties": {
    "iso:country":"US",
    "sg:address":"1267 Georgetown Rd",
    "sg:city":"Pottsboro",
    "sg:classifiers":[
        {
            "category":"Restaurant",
            "type":"Food & Drink"
        }
    ],
    "sg:phone":"+1 903 786 9413",
    "sg:postcode":"75076",
    "sg:province":"TX",
    "sg:tags":[
        "american"
    ],
    "wof:name":"Patsy's",
    "wof:placetype":"venue"
},
  "geometry": {"coordinates":[-96.696231,33.805374],"type":"Point"}
}