{
  "type": "Feature",
  "properties": {
    "iso:country":"US",
    "sg:address":"13677 State Hwy 29",
    "sg:city":"Liberty Hill",
    "sg:classifiers":[
        {
            "category":"Food & Beverages",
            "subcategory":"Groceries & Convenience Stores",
            "type":"Retail Goods"
        }
    ],
    "sg:phone":"+1 512 515 6951",
    "sg:postcode":"78642",
    "sg:province":"TX",
    "wof:name":"Skips",
    "wof:placetype":"venue"
},
  "geometry": {"coordinates":[-97.909595,30.666946],"type":"Point"}
}