{
  "type": "Feature",
  "properties": {
    "iso:country":"US",
    "sg:address":"1701 Oakhurst Scenic Dr",
    "sg:city":"Fort Worth",
    "sg:classifiers":[
        {
            "category":"Organizations",
            "subcategory":"Religious Organization",
            "type":"Services"
        }
    ],
    "sg:phone":"+1 817 834 7355",
    "sg:postcode":"76111",
    "sg:province":"TX",
    "sg:tags":[
        "church"
    ],
    "wof:name":"Midtown Church Of Christ",
    "wof:placetype":"venue"
},
  "geometry": {"coordinates":[-97.318546,32.784856],"type":"Point"}
}