{
  "type": "Feature",
  "properties": {
    "iso:country":"US",
    "sg:address":"2727 Lyndon B Johnson Fwy",
    "sg:city":"Dallas",
    "sg:classifiers":[
        {
            "category":"Professional",
            "subcategory":"Lawyer & Legal Services",
            "type":"Services"
        }
    ],
    "sg:phone":"+1 214 742 1100",
    "sg:postcode":"75234",
    "sg:province":"TX",
    "sg:website":"www.senderatitle.com",
    "wof:name":"Sendera Title",
    "wof:placetype":"venue"
},
  "geometry": {"coordinates":[-96.88718299999999,32.910359],"type":"Point"}
}