{
  "type": "Feature",
  "properties": {
    "iso:country":"US",
    "sg:address":"2930 Camelot Ln",
    "sg:city":"Missouri City",
    "sg:classifiers":[
        {
            "category":"Restaurant",
            "type":"Food & Drink"
        }
    ],
    "sg:phone":"+1 281 403 3087",
    "sg:postcode":"77459",
    "sg:province":"TX",
    "sg:tags":[
        "eating"
    ],
    "wof:name":"Palladium Sportsbar & Pizzeria",
    "wof:placetype":"venue"
},
  "geometry": {"coordinates":[-95.548849,29.582565],"type":"Point"}
}