{
  "type": "Feature",
  "properties": {
    "iso:country":"US",
    "sg:address":"5910 Star Ln",
    "sg:city":"Houston",
    "sg:classifiers":[
        {
            "category":"Autos & Motor Vehicles",
            "subcategory":"Boat Sales",
            "type":"Retail Goods"
        }
    ],
    "sg:phone":"+1 713 977 1469",
    "sg:postcode":"77057",
    "sg:province":"TX",
    "wof:name":"Marine Performance Specialties",
    "wof:placetype":"venue"
},
  "geometry": {"coordinates":[-95.482305,29.727586],"type":"Point"}
}