{
  "type": "Feature",
  "properties": {
    "iso:country":"US",
    "sg:address":"881 Junction Hwy",
    "sg:city":"Kerrville",
    "sg:classifiers":[
        {
            "category":"Restaurant",
            "type":"Food & Drink"
        }
    ],
    "sg:phone":"+1 830 895 2055",
    "sg:postcode":"78028",
    "sg:province":"TX",
    "wof:name":"China Inn",
    "wof:placetype":"venue"
},
  "geometry": {"coordinates":[-99.161185,30.057236],"type":"Point"}
}