{
  "type": "Feature",
  "properties": {
    "iso:country":"US",
    "sg:address":"16524 de Zavalla Rd",
    "sg:city":"Channelview",
    "sg:phone":"+1 281 457 5890",
    "sg:postcode":"77530",
    "sg:province":"TX",
    "sg:tags":[
        "oil"
    ],
    "wof:name":"Martin Midstream",
    "wof:placetype":"venue"
},
  "geometry": {"coordinates":[-95.10537600000001,29.767631],"type":"Point"}
}