{
  "type": "Feature",
  "properties": {
    "iso:country":"US",
    "sg:address":"3407 Esterbrook Dr",
    "sg:city":"Houston",
    "sg:classifiers":[
        {
            "category":"Professional",
            "subcategory":"Engineering",
            "type":"Services"
        }
    ],
    "sg:phone":"+1 281 870 0127",
    "sg:postcode":"77082",
    "sg:province":"TX",
    "wof:name":"Ecns Etc",
    "wof:placetype":"venue"
},
  "geometry": {"coordinates":[-95.664914,29.721648],"type":"Point"}
}