{
  "type": "Feature",
  "properties": {
    "iso:country":"US",
    "sg:address":"4206 Dexired Dr",
    "sg:city":"San Antonio",
    "sg:classifiers":[
        {
            "category":"Building & Trades",
            "subcategory":"Construction",
            "type":"Services"
        }
    ],
    "sg:phone":"+1 210 337 1588",
    "sg:postcode":"78222",
    "sg:province":"TX",
    "sg:tags":[
        "residential"
    ],
    "wof:name":"John Barrys Design Cnstr",
    "wof:placetype":"venue"
},
  "geometry": {"coordinates":[-98.41048499999999,29.369256],"type":"Point"}
}