{
  "type": "Feature",
  "properties": {
    "iso:country":"US",
    "sg:address":"12535 Rio Paloma",
    "sg:city":"San Antonio",
    "sg:classifiers":[
        {
            "category":"Shopping",
            "subcategory":"Gifts & Souvenirs",
            "type":"Retail Goods"
        }
    ],
    "sg:phone":"+1 210 520 5456",
    "sg:postcode":"78249",
    "sg:province":"TX",
    "wof:name":"Michael and Patricia Works",
    "wof:placetype":"venue"
},
  "geometry": {"coordinates":[-98.652507,29.559733],"type":"Point"}
}