{
  "type": "Feature",
  "properties": {
    "iso:country":"US",
    "sg:address":"9200 S Blessen Rd",
    "sg:city":"Amarillo",
    "sg:classifiers":[
        {
            "category":"Professional",
            "type":"Services"
        }
    ],
    "sg:phone":"+1 806 353 4089",
    "sg:postcode":"79119",
    "sg:province":"TX",
    "wof:name":"Kingdom Crowns Inc",
    "wof:placetype":"venue"
},
  "geometry": {"coordinates":[-102.04653399999999,35.112234],"type":"Point"}
}