{
  "type": "Feature",
  "properties": {
    "iso:country":"US",
    "sg:address":"7207 Regency Square Blvd",
    "sg:city":"Houston",
    "sg:classifiers":[
        {
            "category":"Professional",
            "subcategory":"Engineering",
            "type":"Services"
        }
    ],
    "sg:phone":"+1 713 782 7296",
    "sg:postcode":"77036",
    "sg:province":"TX",
    "sg:tags":[
        "engineer"
    ],
    "wof:name":"Interstate Engineers Inc",
    "wof:placetype":"venue"
},
  "geometry": {"coordinates":[-95.50963900000001,29.715612],"type":"Point"}
}