{
  "type": "Feature",
  "properties": {
    "iso:country":"US",
    "sg:address":"4620 College St",
    "sg:city":"Beaumont",
    "sg:classifiers":[
        {
            "category":"Building & Trades",
            "subcategory":"Equipment Rental",
            "type":"Services"
        }
    ],
    "sg:phone":"+1 409 833 1276",
    "sg:postcode":"77707",
    "sg:province":"TX",
    "sg:tags":[
        "moving",
        "supply"
    ],
    "wof:name":"Penske Truck Leasing",
    "wof:placetype":"venue"
},
  "geometry": {"coordinates":[-94.14600799999999,30.068076],"type":"Point"}
}