{
  "type": "Feature",
  "properties": {
    "iso:country":"US",
    "sg:address":"2605 Port Lavaca Dr",
    "sg:city":"Victoria",
    "sg:classifiers":[
        {
            "category":"Autos & Motor Vehicles",
            "subcategory":"Automobile Sales",
            "type":"Retail Goods"
        }
    ],
    "sg:phone":"+1 361 575 1481",
    "sg:postcode":"77901",
    "sg:province":"TX",
    "sg:tags":[
        "truck"
    ],
    "wof:name":"Gulf International Truck",
    "wof:placetype":"venue"
},
  "geometry": {"coordinates":[-96.980462,28.787825],"type":"Point"}
}