{
  "type": "Feature",
  "properties": {
    "iso:country":"US",
    "sg:address":"4603 Pleasant Dr",
    "sg:city":"Midland",
    "sg:classifiers":[
        {
            "category":"Wholesale",
            "subcategory":"Hardware",
            "type":"Manufacturing & Wholesale Goods"
        }
    ],
    "sg:phone":"+1 432 697 2881",
    "sg:postcode":"79703",
    "sg:province":"TX",
    "sg:tags":[
        "plumbing",
        "heating",
        "supply"
    ],
    "wof:name":"Economy Supply Company Odessa",
    "wof:placetype":"venue"
},
  "geometry": {"coordinates":[-102.135616,31.974153],"type":"Point"}
}