{
  "type": "Feature",
  "properties": {
    "iso:country":"US",
    "sg:address":"9465 Kempwood Dr",
    "sg:city":"Houston",
    "sg:classifiers":[
        {
            "category":"Personal",
            "subcategory":"Beauty Salon",
            "type":"Services"
        }
    ],
    "sg:phone":"+1 713 939 9496",
    "sg:postcode":"77080",
    "sg:province":"TX",
    "sg:tags":[
        "shop"
    ],
    "wof:name":"Caleb Beauty & Barber Shop",
    "wof:placetype":"venue"
},
  "geometry": {"coordinates":[-95.526101,29.821869],"type":"Point"}
}