{
  "type": "Feature",
  "properties": {
    "iso:country":"US",
    "sg:address":"4057 Bellaire Blvd",
    "sg:city":"Houston",
    "sg:classifiers":[
        {
            "category":"Restaurant",
            "type":"Food & Drink"
        }
    ],
    "sg:phone":"+1 713 661 0025",
    "sg:postcode":"77025",
    "sg:province":"TX",
    "sg:tags":[
        "new",
        "american"
    ],
    "wof:name":"The Union Kitchen",
    "wof:placetype":"venue"
},
  "geometry": {"coordinates":[-95.44229199999999,29.705359],"type":"Point"}
}