{
  "type": "Feature",
  "properties": {
    "iso:country":"US",
    "sg:address":"601 N Jackson Ave",
    "sg:city":"Livingston",
    "sg:classifiers":[
        {
            "category":"Education",
            "subcategory":"School",
            "type":"Public Place"
        }
    ],
    "sg:phone":"+1 936 328 2320",
    "sg:postcode":"77351",
    "sg:province":"TX",
    "wof:name":"Livingston Special Education",
    "wof:placetype":"venue"
},
  "geometry": {"coordinates":[-94.93396799999999,30.713392],"type":"Point"}
}