{
  "type": "Feature",
  "properties": {
    "iso:country":"US",
    "sg:address":"520 Washington St",
    "sg:city":"Columbus",
    "sg:classifiers":[
        {
            "category":"Government",
            "subcategory":"Office",
            "type":"Public Place"
        }
    ],
    "sg:phone":"+1 979 732 6635",
    "sg:postcode":"78934",
    "sg:province":"TX",
    "wof:name":"Women/Children Project",
    "wof:placetype":"venue"
},
  "geometry": {"coordinates":[-96.540717,29.704404],"type":"Point"}
}