{
  "type": "Feature",
  "properties": {
    "iso:country":"US",
    "sg:address":"1619 Quitman St",
    "sg:city":"Houston",
    "sg:classifiers":[
        {
            "category":"Retail",
            "subcategory":"Auto Repair",
            "type":"Services"
        }
    ],
    "sg:phone":"+1 713 227 1951",
    "sg:postcode":"77009",
    "sg:province":"TX",
    "wof:name":"Arturo's Automotive",
    "wof:placetype":"venue"
},
  "geometry": {"coordinates":[-95.352075,29.78349],"type":"Point"}
}