{
  "type": "Feature",
  "properties": {
    "iso:country":"US",
    "sg:address":"1341 W Mockingbird Ln",
    "sg:city":"Dallas",
    "sg:classifiers":[
        {
            "category":"Organizations",
            "subcategory":"Labor Organization",
            "type":"Services"
        }
    ],
    "sg:phone":"+1 972 263 4811",
    "sg:postcode":"75247",
    "sg:province":"TX",
    "wof:name":"Uaw",
    "wof:placetype":"venue"
},
  "geometry": {"coordinates":[-96.86535000000001,32.821632],"type":"Point"}
}