{
  "type": "Feature",
  "properties": {
    "iso:country":"US",
    "sg:address":"415 Decatur St",
    "sg:city":"Bowie",
    "sg:classifiers":[
        {
            "category":"Building & Trades",
            "subcategory":"Construction",
            "type":"Services"
        }
    ],
    "sg:phone":"+1 940 872 3930",
    "sg:postcode":"76230",
    "sg:province":"TX",
    "sg:tags":[
        "carpentry",
        "contractor"
    ],
    "wof:name":"Butler Did It",
    "wof:placetype":"venue"
},
  "geometry": {"coordinates":[-97.84374200000001,33.553746],"type":"Point"}
}