{
  "type": "Feature",
  "properties": {
    "iso:country":"US",
    "sg:address":"205 E Oak St",
    "sg:city":"Aledo",
    "sg:classifiers":[
        {
            "category":"Shopping",
            "subcategory":"Gifts & Souvenirs",
            "type":"Retail Goods"
        }
    ],
    "sg:phone":"+1 817 441 2217",
    "sg:postcode":"76008",
    "sg:province":"TX",
    "wof:name":"Falderal",
    "wof:placetype":"venue"
},
  "geometry": {"coordinates":[-97.600813,32.696596],"type":"Point"}
}