{
  "type": "Feature",
  "properties": {
    "iso:country":"US",
    "sg:address":"202 W Pleasant Run Rd",
    "sg:city":"Lancaster",
    "sg:classifiers":[
        {
            "category":"Ice Cream",
            "type":"Food & Drink"
        }
    ],
    "sg:menulink":"http://www.allmenus.com/tx/southwest/218995-braums-ice-cream--dairy-stores/menu/",
    "sg:phone":"+1 972 227 6921",
    "sg:postcode":"75146",
    "sg:province":"TX",
    "sg:tags":[
        "american"
    ],
    "wof:name":"Braum's Ice Cream & Dairy Stores",
    "wof:placetype":"venue"
},
  "geometry": {"coordinates":[-96.759657,32.60368],"type":"Point"}
}