{
  "type": "Feature",
  "properties": {
    "iso:country":"US",
    "sg:address":"701 N 1st St",
    "sg:city":"Lufkin",
    "sg:classifiers":[
        {
            "category":"Government",
            "subcategory":"Office",
            "type":"Public Place"
        }
    ],
    "sg:phone":"+1 936 639 8600",
    "sg:postcode":"75901",
    "sg:province":"TX",
    "sg:tags":[
        "federal",
        "security",
        "human",
        "social"
    ],
    "wof:name":"Social Security Administration",
    "wof:placetype":"venue"
},
  "geometry": {"coordinates":[-94.726095,31.345727],"type":"Point"}
}