{
  "type": "Feature",
  "properties": {
    "iso:country":"US",
    "sg:address":"1518 W Cameron Ave",
    "sg:city":"Rockdale",
    "sg:classifiers":[
        {
            "category":"Professional",
            "subcategory":"Management & Consulting",
            "type":"Services"
        }
    ],
    "sg:phone":"+1 979 364 3615",
    "sg:postcode":"76567",
    "sg:province":"TX",
    "wof:name":"Starfleet Services Inc",
    "wof:placetype":"venue"
},
  "geometry": {"coordinates":[-97.02058,30.646833],"type":"Point"}
}