{
  "type": "Feature",
  "properties": {
    "iso:country":"US",
    "sg:address":"804 W Holland Ave",
    "sg:city":"Alpine",
    "sg:classifiers":[
        {
            "category":"Home & Garden",
            "subcategory":"Garden Supply",
            "type":"Retail Goods"
        }
    ],
    "sg:phone":"+1 432 837 3960",
    "sg:postcode":"79830",
    "sg:province":"TX",
    "sg:tags":[
        "sprinkler"
    ],
    "wof:name":"Desert Rain",
    "wof:placetype":"venue"
},
  "geometry": {"coordinates":[-103.66835,30.355487],"type":"Point"}
}