{
  "type": "Feature",
  "properties": {
    "iso:country":"US",
    "sg:address":"7010 Greenspan Ave",
    "sg:city":"Dallas",
    "sg:classifiers":[
        {
            "category":"Social Services",
            "subcategory":"Child Care",
            "type":"Services"
        }
    ],
    "sg:phone":"+1 214 484 9055",
    "sg:postcode":"75232",
    "sg:province":"TX",
    "sg:tags":[
        "day"
    ],
    "wof:name":"Kiddazzle Child Care Center",
    "wof:placetype":"venue"
},
  "geometry": {"coordinates":[-96.83068900000001,32.663077],"type":"Point"}
}