{
  "type": "Feature",
  "properties": {
    "iso:country":"US",
    "sg:address":"4910 Aldine Mail Rd",
    "sg:city":"Houston",
    "sg:classifiers":[
        {
            "category":"Food & Beverages",
            "subcategory":"Groceries & Convenience Stores",
            "type":"Retail Goods"
        }
    ],
    "sg:phone":"+1 281 987 2047",
    "sg:postcode":"77039",
    "sg:province":"TX",
    "wof:name":"Supermercado La Mexicana # 2",
    "wof:placetype":"venue"
},
  "geometry": {"coordinates":[-95.31849699999999,29.9027],"type":"Point"}
}