{
  "type": "Feature",
  "properties": {
    "iso:country":"US",
    "sg:address":"512 Park Ln",
    "sg:city":"Richardson",
    "sg:classifiers":[
        {
            "category":"Professional",
            "type":"Services"
        }
    ],
    "sg:phone":"+1 972 235 1059",
    "sg:postcode":"75081",
    "sg:province":"TX",
    "wof:name":"Stans Specialties",
    "wof:placetype":"venue"
},
  "geometry": {"coordinates":[-96.722427,32.94078],"type":"Point"}
}