{
  "type": "Feature",
  "properties": {
    "iso:country":"US",
    "sg:address":"801 Fort Worth St",
    "sg:city":"Wellington",
    "sg:classifiers":[
        {
            "category":"Government",
            "subcategory":"Office",
            "type":"Public Place"
        }
    ],
    "sg:phone":"+1 806 447 5341",
    "sg:postcode":"79095",
    "sg:province":"TX",
    "sg:tags":[
        "federal"
    ],
    "wof:name":"Natural Resources Conservation",
    "wof:placetype":"venue"
},
  "geometry": {"coordinates":[-100.206785,34.856173],"type":"Point"}
}