{
  "type": "Feature",
  "properties": {
    "iso:country":"US",
    "sg:address":"204 Industrial Park Dr",
    "sg:city":"Victoria",
    "sg:classifiers":[
        {
            "category":"Mining & Drilling",
            "type":"Manufacturing & Wholesale Goods"
        }
    ],
    "sg:phone":"+1 361 576 5297",
    "sg:postcode":"77905",
    "sg:province":"TX",
    "sg:tags":[
        "gas",
        "oil",
        "well",
        "fluid"
    ],
    "wof:name":"Ambar Fluids Lp Lllp",
    "wof:placetype":"venue"
},
  "geometry": {"coordinates":[-97.09214299999999,28.768511],"type":"Point"}
}