{
  "type": "Feature",
  "properties": {
    "iso:country":"US",
    "sg:address":"1000 W Freeway St",
    "sg:city":"Grand Prairie",
    "sg:classifiers":[
        {
            "category":"Food & Beverages",
            "subcategory":"Groceries & Convenience Stores",
            "type":"Retail Goods"
        }
    ],
    "sg:phone":"+1 972 264 4831",
    "sg:postcode":"75051",
    "sg:province":"TX",
    "sg:tags":[
        "grocer"
    ],
    "wof:name":"Texas T Discount Grocery",
    "wof:placetype":"venue"
},
  "geometry": {"coordinates":[-97.01966299999999,32.729066],"type":"Point"}
}