{
  "type": "Feature",
  "properties": {
    "iso:country":"US",
    "sg:address":"828 Parkwood Ct",
    "sg:city":"Mckinney",
    "sg:classifiers":[
        {
            "category":"Professional",
            "subcategory":"Business Services",
            "type":"Services"
        }
    ],
    "sg:phone":"+1 972 529 6116",
    "sg:postcode":"75070",
    "sg:province":"TX",
    "sg:tags":[
        "apartment"
    ],
    "wof:name":"Windale Partners",
    "wof:placetype":"venue"
},
  "geometry": {"coordinates":[-96.687056,33.190058],"type":"Point"}
}