{
  "type": "Feature",
  "properties": {
    "iso:country":"US",
    "sg:address":"4000 McEwen Rd",
    "sg:city":"Dallas",
    "sg:classifiers":[
        {
            "category":"Shopping",
            "subcategory":"Computers & Home Electronics",
            "type":"Retail Goods"
        }
    ],
    "sg:phone":"+1 972 960 7053",
    "sg:postcode":"75244",
    "sg:province":"TX",
    "sg:tags":[
        "software"
    ],
    "wof:name":"Metamor Technology Information",
    "wof:placetype":"venue"
},
  "geometry": {"coordinates":[-96.83909199999999,32.928849],"type":"Point"}
}