{
  "type": "Feature",
  "properties": {
    "iso:country":"US",
    "sg:address":"2661 Midway Rd",
    "sg:city":"Carrollton",
    "sg:classifiers":[
        {
            "category":"Health Services",
            "subcategory":"Clinic",
            "type":"Services"
        }
    ],
    "sg:phone":"+1 972 931 4882",
    "sg:postcode":"75006",
    "sg:province":"TX",
    "sg:tags":[
        "holistic",
        "practitioner"
    ],
    "wof:name":"Holistic Herbal Health",
    "wof:placetype":"venue"
},
  "geometry": {"coordinates":[-96.84227199999999,32.986274],"type":"Point"}
}