{
  "type": "Feature",
  "properties": {
    "iso:country":"US",
    "sg:address":"5303 Sanger Ave",
    "sg:city":"Waco",
    "sg:classifiers":[
        {
            "category":"Retail",
            "subcategory":"Laundry & Dry Cleaning",
            "type":"Services"
        }
    ],
    "sg:phone":"+1 254 776 9124",
    "sg:postcode":"76710",
    "sg:province":"TX",
    "sg:tags":[
        "drycleaning",
        "plant"
    ],
    "wof:name":"Crystal Clear Cleaners",
    "wof:placetype":"venue"
},
  "geometry": {"coordinates":[-97.187698,31.525501],"type":"Point"}
}