{
  "type": "Feature",
  "properties": {
    "iso:country":"US",
    "sg:address":"19010 White Candle Dr",
    "sg:city":"Spring",
    "sg:classifiers":[
        {
            "category":"Professional",
            "subcategory":"Management & Consulting",
            "type":"Services"
        }
    ],
    "sg:phone":"+1 281 288 8644",
    "sg:postcode":"77388",
    "sg:province":"TX",
    "sg:tags":[
        "business"
    ],
    "wof:name":"Koch Consulting",
    "wof:placetype":"venue"
},
  "geometry": {"coordinates":[-95.456785,30.046045],"type":"Point"}
}