{
  "type": "Feature",
  "properties": {
    "iso:country":"US",
    "sg:address":"1721 Nogalitos St",
    "sg:city":"San Antonio",
    "sg:classifiers":[
        {
            "category":"Autos & Motor Vehicles",
            "subcategory":"Auto Supplies",
            "type":"Retail Goods"
        }
    ],
    "sg:phone":"+1 210 226 5956",
    "sg:postcode":"78204",
    "sg:province":"TX",
    "wof:name":"Nogalitos Auto Parts",
    "wof:placetype":"venue"
},
  "geometry": {"coordinates":[-98.515074,29.396745],"type":"Point"}
}