{
  "type": "Feature",
  "properties": {
    "iso:country":"US",
    "sg:address":"7502 Greenville Ave",
    "sg:city":"Dallas",
    "sg:classifiers":[
        {
            "category":"Professional",
            "subcategory":"Lawyer & Legal Services",
            "type":"Services"
        }
    ],
    "sg:phone":"+1 214 890 9225",
    "sg:postcode":"75231",
    "sg:province":"TX",
    "wof:name":"Thomas E Kirkland Attrny At Lw",
    "wof:placetype":"venue"
},
  "geometry": {"coordinates":[-96.758375,32.885596],"type":"Point"}
}