{
  "type": "Feature",
  "properties": {
    "iso:country":"US",
    "sg:address":"6 Meadow Brook Pl",
    "sg:city":"Conroe",
    "sg:classifiers":[
        {
            "category":"Utilities",
            "type":"Services"
        }
    ],
    "sg:phone":"+1 936 321 4000",
    "sg:postcode":"77382",
    "sg:province":"TX",
    "sg:tags":[
        "other",
        "gas",
        "combined"
    ],
    "wof:name":"W E R Holdings Inc",
    "wof:placetype":"venue"
},
  "geometry": {"coordinates":[-95.50887899999999,30.212743],"type":"Point"}
}