{
  "type": "Feature",
  "properties": {
    "iso:country":"US",
    "sg:address":"11 Cheshire Glen Ct",
    "sg:city":"Spring",
    "sg:classifiers":[
        {
            "category":"Professional",
            "subcategory":"Secretarial Services",
            "type":"Services"
        }
    ],
    "sg:phone":"+1 281 367 3199",
    "sg:postcode":"77382",
    "sg:province":"TX",
    "sg:tags":[
        "reporting"
    ],
    "wof:name":"Bradley Word Tech",
    "wof:placetype":"venue"
},
  "geometry": {"coordinates":[-95.531178,30.211338],"type":"Point"}
}