{
  "type": "Feature",
  "properties": {
    "iso:country":"US",
    "sg:address":"7922 Lichen Ln",
    "sg:city":"Spring",
    "sg:classifiers":[
        {
            "category":"Professional",
            "subcategory":"Business Services",
            "type":"Services"
        }
    ],
    "sg:phone":"+1 281 376 8296",
    "sg:postcode":"77379",
    "sg:province":"TX",
    "wof:name":"Orange Pool Service Inc",
    "wof:placetype":"venue"
},
  "geometry": {"coordinates":[-95.533664,30.017278],"type":"Point"}
}