{
  "type": "Feature",
  "properties": {
    "iso:country":"US",
    "sg:address":"5936 Military Pkwy",
    "sg:city":"Dallas",
    "sg:classifiers":[
        {
            "category":"Food & Beverages",
            "subcategory":"Groceries & Convenience Stores",
            "type":"Retail Goods"
        }
    ],
    "sg:phone":"+1 214 381 8034",
    "sg:postcode":"75227",
    "sg:province":"TX",
    "wof:name":"Military Quick Stop",
    "wof:placetype":"venue"
},
  "geometry": {"coordinates":[-96.715698,32.776402],"type":"Point"}
}