{
  "type": "Feature",
  "properties": {
    "iso:country":"US",
    "sg:address":"200 NE 10th St",
    "sg:city":"Cooper",
    "sg:classifiers":[
        {
            "category":"Professional",
            "type":"Services"
        }
    ],
    "sg:phone":"+1 903 395 4136",
    "sg:postcode":"75432",
    "sg:province":"TX",
    "wof:name":"Robert Huie",
    "wof:placetype":"venue"
},
  "geometry": {"coordinates":[-95.67980300000001,33.375128],"type":"Point"}
}