{
  "type": "Feature",
  "properties": {
    "iso:country":"US",
    "sg:address":"1101 Courtney Ln",
    "sg:city":"Lewisville",
    "sg:classifiers":[
        {
            "category":"Professional",
            "subcategory":"Business Services",
            "type":"Services"
        }
    ],
    "sg:phone":"+1 972 219 7290",
    "sg:postcode":"75077",
    "sg:province":"TX",
    "wof:name":"Ann Designs",
    "wof:placetype":"venue"
},
  "geometry": {"coordinates":[-97.019245,33.05804],"type":"Point"}
}