{
  "type": "Feature",
  "properties": {
    "iso:country":"US",
    "sg:address":"215 Oak Dr S",
    "sg:city":"Lake Jackson",
    "sg:classifiers":[
        {
            "category":"Health Services",
            "subcategory":"Doctor",
            "type":"Services"
        }
    ],
    "sg:phone":"+1 979 297 6458",
    "sg:postcode":"77566",
    "sg:province":"TX",
    "sg:tags":[
        "physician",
        "surgeon"
    ],
    "wof:name":"Brazosport Dermatology Clinic",
    "wof:placetype":"venue"
},
  "geometry": {"coordinates":[-95.457211,29.030735],"type":"Point"}
}