{
  "type": "Feature",
  "properties": {
    "iso:country":"US",
    "sg:address":"800 N Shoreline Blvd",
    "sg:city":"Corpus Christi",
    "sg:classifiers":[
        {
            "category":"Utilities",
            "subcategory":"Mobile Phone",
            "type":"Services"
        }
    ],
    "sg:phone":"+1 361 879 0260",
    "sg:postcode":"78401",
    "sg:province":"TX",
    "sg:tags":[
        "telephone",
        "cellular"
    ],
    "wof:name":"T-Mobile",
    "wof:placetype":"venue"
},
  "geometry": {"coordinates":[-97.39156800000001,27.799605],"type":"Point"}
}