{
  "type": "Feature",
  "properties": {
    "iso:country":"US",
    "sg:address":"1616 Thistledown Dr",
    "sg:city":"Plano",
    "sg:classifiers":[
        {
            "category":"Communications",
            "subcategory":"Radio Station",
            "type":"Services"
        }
    ],
    "sg:phone":"+1 972 447 0507",
    "sg:postcode":"75093",
    "sg:province":"TX",
    "sg:tags":[
        "broadcast"
    ],
    "wof:name":"Kgvl Radio",
    "wof:placetype":"venue"
},
  "geometry": {"coordinates":[-96.803748,33.021433],"type":"Point"}
}