{
  "type": "Feature",
  "properties": {
    "iso:country":"US",
    "sg:address":"1299 Commerce Dr",
    "sg:city":"Richardson",
    "sg:classifiers":[
        {
            "category":"Communications",
            "subcategory":"Film & Video Production",
            "type":"Services"
        }
    ],
    "sg:phone":"+1 214 575 9300",
    "sg:postcode":"75081",
    "sg:province":"TX",
    "sg:tags":[
        "motion",
        "picture",
        "studio",
        "producer"
    ],
    "wof:name":"TXP",
    "wof:placetype":"venue"
},
  "geometry": {"coordinates":[-96.705226,32.965949],"type":"Point"}
}