{
  "type": "Feature",
  "properties": {
    "iso:country":"US",
    "sg:address":"6351 Basswood Dr",
    "sg:city":"Fort Worth",
    "sg:classifiers":[
        {
            "category":"Mining & Drilling",
            "type":"Manufacturing & Wholesale Goods"
        }
    ],
    "sg:phone":"+1 817 237 7119",
    "sg:postcode":"76135",
    "sg:province":"TX",
    "sg:tags":[
        "oil",
        "gas",
        "producer"
    ],
    "wof:name":"Meeker & Co Inc",
    "wof:placetype":"venue"
},
  "geometry": {"coordinates":[-97.424935,32.827205],"type":"Point"}
}