{
  "type": "Feature",
  "properties": {
    "iso:country":"US",
    "sg:address":"410 Paloma St",
    "sg:city":"Corpus Christi",
    "sg:classifiers":[
        {
            "category":"Recreation",
            "type":"Entertainment"
        }
    ],
    "sg:phone":"+1 361 994 9620",
    "sg:postcode":"78412",
    "sg:province":"TX",
    "wof:name":"Air Bounce",
    "wof:placetype":"venue"
},
  "geometry": {"coordinates":[-97.358966,27.725428],"type":"Point"}
}