{
  "type": "Feature",
  "properties": {
    "iso:country":"US",
    "sg:address":"1105 Wooding St",
    "sg:city":"Houston",
    "sg:classifiers":[
        {
            "category":"Autos & Motor Vehicles",
            "subcategory":"Automobile Sales",
            "type":"Retail Goods"
        }
    ],
    "sg:phone":"+1 713 676 2660",
    "sg:postcode":"77011",
    "sg:province":"TX",
    "sg:tags":[
        "car",
        "dealer"
    ],
    "wof:name":"Mr G's Auto Sales",
    "wof:placetype":"venue"
},
  "geometry": {"coordinates":[-95.298314,29.74354],"type":"Point"}
}