{
  "type": "Feature",
  "properties": {
    "iso:country":"US",
    "sg:address":"1531 Jasmine Dr",
    "sg:city":"Schertz",
    "sg:classifiers":[
        {
            "category":"Organizations",
            "subcategory":"Religious Organization",
            "type":"Services"
        }
    ],
    "sg:phone":"+1 210 566 2237",
    "sg:postcode":"78154",
    "sg:province":"TX",
    "sg:tags":[
        "church"
    ],
    "wof:name":"Word Of Life Fellowship",
    "wof:placetype":"venue"
},
  "geometry": {"coordinates":[-98.255228,29.584945],"type":"Point"}
}