{
  "type": "Feature",
  "properties": {
    "iso:country":"US",
    "sg:address":"3208 E Perryton Dr",
    "sg:city":"Dallas",
    "sg:classifiers":[
        {
            "category":"Building & Trades",
            "subcategory":"Equipment Rental",
            "type":"Services"
        }
    ],
    "sg:phone":"+1 214 339 5379",
    "sg:postcode":"75224",
    "sg:province":"TX",
    "wof:name":"D&G Party Rentals",
    "wof:placetype":"venue"
},
  "geometry": {"coordinates":[-96.845085,32.70917],"type":"Point"}
}