{
  "type": "Feature",
  "properties": {
    "iso:country":"US",
    "sg:address":"2852 Gus Thomasson Rd",
    "sg:city":"Mesquite",
    "sg:classifiers":[
        {
            "category":"Manufacturing",
            "subcategory":"Chemicals & Compounds",
            "type":"Manufacturing & Wholesale Goods"
        }
    ],
    "sg:phone":"+1 972 524 4048",
    "sg:postcode":"75150",
    "sg:province":"TX",
    "sg:tags":[
        "industrial",
        "gas",
        "mfg"
    ],
    "wof:name":"Air Products",
    "wof:placetype":"venue"
},
  "geometry": {"coordinates":[-96.633577,32.801233],"type":"Point"}
}