{
  "type": "Feature",
  "properties": {
    "iso:country":"US",
    "sg:address":"7407 Navajo Pass",
    "sg:city":"Leander",
    "sg:classifiers":[
        {
            "category":"Recreation",
            "type":"Entertainment"
        }
    ],
    "sg:phone":"+1 512 258 8400",
    "sg:postcode":"78641",
    "sg:province":"TX",
    "sg:tags":[
        "water",
        "passenger",
        "transport"
    ],
    "wof:name":"Beach Front Boat Rentals LC",
    "wof:placetype":"venue"
},
  "geometry": {"coordinates":[-97.897678,30.429495],"type":"Point"}
}