{
  "type": "Feature",
  "properties": {
    "iso:country":"US",
    "sg:address":"14831 Horse Creek Ln",
    "sg:city":"Sugar Land",
    "sg:classifiers":[
        {
            "category":"Banks & Credit Unions",
            "subcategory":"Bank",
            "type":"Services"
        }
    ],
    "sg:phone":"+1 713 530 1106",
    "sg:postcode":"77478",
    "sg:province":"TX",
    "sg:tags":[
        "broker",
        "mortgage"
    ],
    "wof:name":"One Source Financing",
    "wof:placetype":"venue"
},
  "geometry": {"coordinates":[-95.640968,29.645544],"type":"Point"}
}