{
  "type": "Feature",
  "properties": {
    "iso:country":"US",
    "sg:address":"200 W Main St",
    "sg:city":"Waxahachie",
    "sg:classifiers":[
        {
            "category":"Banks & Credit Unions",
            "subcategory":"Bank",
            "type":"Services"
        }
    ],
    "sg:phone":"+1 972 937 2252",
    "sg:postcode":"75165",
    "sg:province":"TX",
    "wof:name":"Heritage Bank",
    "wof:placetype":"venue"
},
  "geometry": {"coordinates":[-96.84881799999999,32.386291],"type":"Point"}
}