{
  "type": "Feature",
  "properties": {
    "iso:country":"US",
    "sg:address":"12042 Blanco Rd",
    "sg:city":"San Antonio",
    "sg:classifiers":[
        {
            "category":"Professional",
            "type":"Services"
        }
    ],
    "sg:phone":"+1 210 341 0888",
    "sg:postcode":"78216",
    "sg:province":"TX",
    "sg:tags":[
        "establishment"
    ],
    "wof:name":"River Sub Corporate Office",
    "wof:placetype":"venue"
},
  "geometry": {"coordinates":[-98.510735,29.549153],"type":"Point"}
}