{
  "type": "Feature",
  "properties": {
    "iso:country":"US",
    "sg:address":"3646 State Hwy 34",
    "sg:city":"Ennis",
    "sg:classifiers":[
        {
            "category":"Retail",
            "subcategory":"Auto Repair",
            "type":"Services"
        }
    ],
    "sg:phone":"+1 972 875 9385",
    "sg:postcode":"75119",
    "sg:province":"TX",
    "sg:tags":[
        "general"
    ],
    "wof:name":"Carl W Novak",
    "wof:placetype":"venue"
},
  "geometry": {"coordinates":[-96.642239,32.298738],"type":"Point"}
}