{
  "type": "Feature",
  "properties": {
    "iso:country":"US",
    "sg:address":"700 N Town East Blvd Apt 328",
    "sg:city":"Mesquite",
    "sg:classifiers":[
        {
            "category":"Social Services",
            "subcategory":"Retirement Home",
            "type":"Services"
        }
    ],
    "sg:phone":"+1 972 270 6958",
    "sg:postcode":"75150",
    "sg:province":"TX",
    "wof:name":"Waterford At Mesquite the",
    "wof:placetype":"venue"
},
  "geometry": {"coordinates":[-96.60639999999999,32.813599],"type":"Point"}
}