{
  "type": "Feature",
  "properties": {
    "iso:country":"US",
    "sg:address":"306 Crosstimbers St",
    "sg:city":"Houston",
    "sg:classifiers":[
        {
            "category":"Education",
            "subcategory":"School",
            "type":"Public Place"
        }
    ],
    "sg:phone":"+1 713 697 0646",
    "sg:postcode":"77022",
    "sg:province":"TX",
    "wof:name":"Communities In Schools Houston Inc",
    "wof:placetype":"venue"
},
  "geometry": {"coordinates":[-95.397301,29.828199],"type":"Point"}
}