{
  "type": "Feature",
  "properties": {
    "iso:country":"US",
    "sg:address":"527 W Cevallos St",
    "sg:city":"San Antonio",
    "sg:classifiers":[
        {
            "category":"Autos & Motor Vehicles",
            "subcategory":"Fuel & Gas Station",
            "type":"Retail Goods"
        }
    ],
    "sg:phone":"+1 210 224 5419",
    "sg:postcode":"78204",
    "sg:province":"TX",
    "sg:tags":[
        "grocery",
        "gasoline"
    ],
    "wof:name":"Texaco",
    "wof:placetype":"venue"
},
  "geometry": {"coordinates":[-98.506677,29.411262],"type":"Point"}
}