{
  "type": "Feature",
  "properties": {
    "iso:country":"US",
    "sg:address":"301 N 8th St",
    "sg:city":"Midlothian",
    "sg:classifiers":[
        {
            "category":"Manufacturing",
            "subcategory":"Motor Vehicles & Parts",
            "type":"Manufacturing & Wholesale Goods"
        }
    ],
    "sg:phone":"+1 972 775 6515",
    "sg:postcode":"76065",
    "sg:province":"TX",
    "sg:tags":[
        "mfg"
    ],
    "wof:name":"NAPA Auto Parts",
    "wof:placetype":"venue"
},
  "geometry": {"coordinates":[-96.994518,32.484287],"type":"Point"}
}