{
  "type": "Feature",
  "properties": {
    "iso:country":"US",
    "sg:address":"12336 FM 2854",
    "sg:city":"Conroe",
    "sg:classifiers":[
        {
            "category":"Retail",
            "subcategory":"Auto Repair",
            "type":"Services"
        }
    ],
    "sg:phone":"+1 936 539 9808",
    "sg:postcode":"77304",
    "sg:province":"TX",
    "sg:tags":[
        "general"
    ],
    "wof:name":"Christopher Auto Repair",
    "wof:placetype":"venue"
},
  "geometry": {"coordinates":[-95.546036,30.317304],"type":"Point"}
}