{
  "type": "Feature",
  "properties": {
    "iso:country":"US",
    "sg:address":"915 N Garfield St",
    "sg:city":"San Angelo",
    "sg:classifiers":[
        {
            "category":"Building & Trades",
            "subcategory":"Plumbing",
            "type":"Services"
        }
    ],
    "sg:phone":"+1 325 949 4821",
    "sg:postcode":"76901",
    "sg:province":"TX",
    "sg:tags":[
        "plumbing",
        "contractor"
    ],
    "wof:name":"Mc Carley Plumbing Co Inc",
    "wof:placetype":"venue"
},
  "geometry": {"coordinates":[-100.47880600000001,31.456116],"type":"Point"}
}