{
  "type": "Feature",
  "properties": {
    "iso:country":"US",
    "sg:address":"4242 N Capistrano Dr",
    "sg:city":"Dallas",
    "sg:classifiers":[
        {
            "category":"Professional",
            "type":"Services"
        }
    ],
    "sg:phone":"+1 972 818 2276",
    "sg:postcode":"75287",
    "sg:province":"TX",
    "sg:tags":[
        "establishment"
    ],
    "wof:name":"Burkhartryan",
    "wof:placetype":"venue"
},
  "geometry": {"coordinates":[-96.836591,33.005916],"type":"Point"}
}