{
  "type": "Feature",
  "properties": {
    "iso:country":"US",
    "sg:address":"100 S Lacy Dr",
    "sg:city":"Waco",
    "sg:classifiers":[
        {
            "category":"Autos & Motor Vehicles",
            "subcategory":"Auto Supplies",
            "type":"Retail Goods"
        }
    ],
    "sg:phone":"+1 254 412 1230",
    "sg:postcode":"76705",
    "sg:province":"TX",
    "sg:tags":[
        "tire"
    ],
    "wof:name":"Quality Tire",
    "wof:placetype":"venue"
},
  "geometry": {"coordinates":[-97.10747499999999,31.621394],"type":"Point"}
}