{
  "type": "Feature",
  "properties": {
    "iso:country":"US",
    "sg:address":"12351 FM 830",
    "sg:city":"Willis",
    "sg:classifiers":[
        {
            "category":"Manufacturing",
            "subcategory":"Apparel",
            "type":"Manufacturing & Wholesale Goods"
        }
    ],
    "sg:phone":"+1 936 597 5804",
    "sg:postcode":"77318",
    "sg:province":"TX",
    "wof:name":"Beths Embroidery",
    "wof:placetype":"venue"
},
  "geometry": {"coordinates":[-95.54296600000001,30.406563],"type":"Point"}
}