{
  "type": "Feature",
  "properties": {
    "iso:country":"US",
    "sg:address":"14 Auburn Ct",
    "sg:city":"Midland",
    "sg:classifiers":[
        {
            "category":"Professional",
            "subcategory":"Accounting & Tax Preparation",
            "type":"Services"
        }
    ],
    "sg:phone":"+1 432 687 1175",
    "sg:postcode":"79705",
    "sg:province":"TX",
    "sg:tags":[
        "consultant"
    ],
    "wof:name":"Alpha Systems",
    "wof:placetype":"venue"
},
  "geometry": {"coordinates":[-102.116691,32.027228],"type":"Point"}
}