{
  "type": "Feature",
  "properties": {
    "iso:country":"US",
    "sg:address":"815 Walker St",
    "sg:city":"Houston",
    "sg:classifiers":[
        {
            "category":"Restaurant",
            "type":"Food & Drink"
        }
    ],
    "sg:phone":"+1 713 229 8480",
    "sg:postcode":"77002",
    "sg:province":"TX",
    "sg:tags":[
        "eating",
        "chinese"
    ],
    "wof:name":"Cajun Grill & Lotus Express",
    "wof:placetype":"venue"
},
  "geometry": {"coordinates":[-95.365936,29.758668],"type":"Point"}
}