{
  "type": "Feature",
  "properties": {
    "iso:country":"US",
    "sg:address":"111 Hwy 288B",
    "sg:city":"Clute",
    "sg:classifiers":[
        {
            "category":"Retail",
            "subcategory":"Auto Repair",
            "type":"Services"
        }
    ],
    "sg:phone":"+1 979 265 7476",
    "sg:postcode":"77531",
    "sg:province":"TX",
    "sg:tags":[
        "wheel",
        "axle",
        "alignment"
    ],
    "wof:name":"Midas Auto Svc Experts",
    "wof:placetype":"venue"
},
  "geometry": {"coordinates":[-95.39657099999999,29.026699],"type":"Point"}
}