{
  "type": "Feature",
  "properties": {
    "iso:country":"US",
    "sg:address":"1610 Big Horn Dr",
    "sg:city":"Houston",
    "sg:classifiers":[
        {
            "category":"Professional",
            "type":"Services"
        }
    ],
    "sg:phone":"+1 281 893 9157",
    "sg:postcode":"77090",
    "sg:province":"TX",
    "wof:name":"Sey & Kef Inc",
    "wof:placetype":"venue"
},
  "geometry": {"coordinates":[-95.46080600000001,30.022907],"type":"Point"}
}