{
  "type": "Feature",
  "properties": {
    "iso:country":"US",
    "sg:address":"3510 Frutas Ave",
    "sg:city":"El Paso",
    "sg:classifiers":[
        {
            "category":"Retail",
            "subcategory":"Auto Repair",
            "type":"Services"
        }
    ],
    "sg:phone":"+1 915 313 0499",
    "sg:postcode":"79905",
    "sg:province":"TX",
    "sg:tags":[
        "body"
    ],
    "wof:name":"Custom Elegance",
    "wof:placetype":"venue"
},
  "geometry": {"coordinates":[-106.451048,31.774381],"type":"Point"}
}