{
  "type": "Feature",
  "properties": {
    "iso:country":"US",
    "sg:address":"107 Tellus St",
    "sg:city":"Lakeway",
    "sg:classifiers":[
        {
            "category":"Building & Trades",
            "subcategory":"Cleaning & Sanitation",
            "type":"Services"
        }
    ],
    "sg:phone":"+1 512 261 9662",
    "sg:postcode":"78734",
    "sg:province":"TX",
    "sg:tags":[
        "janitor"
    ],
    "wof:name":"Office Keepers",
    "wof:placetype":"venue"
},
  "geometry": {"coordinates":[-97.97282300000001,30.376114],"type":"Point"}
}