{
  "type": "Feature",
  "properties": {
    "iso:country":"US",
    "sg:address":"510 Ellington Field",
    "sg:city":"Houston",
    "sg:classifiers":[
        {
            "category":"Government",
            "subcategory":"Office",
            "type":"Public Place"
        }
    ],
    "sg:phone":"+1 281 481 2828",
    "sg:postcode":"77034",
    "sg:province":"TX",
    "sg:tags":[
        "city",
        "program"
    ],
    "wof:name":"Houston Aviation Dept",
    "wof:placetype":"venue"
},
  "geometry": {"coordinates":[-95.180926,29.618558],"type":"Point"}
}