{
  "type": "Feature",
  "properties": {
    "iso:country":"US",
    "sg:address":"805 N Capital of Texas Hwy",
    "sg:city":"Austin",
    "sg:classifiers":[
        {
            "category":"Banks & Credit Unions",
            "subcategory":"Investment Brokerage",
            "type":"Services"
        }
    ],
    "sg:phone":"+1 512 347 1213",
    "sg:postcode":"78746",
    "sg:province":"TX",
    "sg:tags":[
        "consultant",
        "planning",
        "financial"
    ],
    "wof:name":"Jerome Collins Financial Plnnr",
    "wof:placetype":"venue"
},
  "geometry": {"coordinates":[-97.825816,30.309311],"type":"Point"}
}