{
  "type": "Feature",
  "properties": {
    "iso:country":"US",
    "sg:address":"912 Main St",
    "sg:city":"Bastrop",
    "sg:classifiers":[
        {
            "category":"Restaurant",
            "type":"Food & Drink"
        }
    ],
    "sg:phone":"+1 512 308 9600",
    "sg:postcode":"78602",
    "sg:province":"TX",
    "sg:tags":[
        "eating"
    ],
    "wof:name":"Bahia Abrigaba",
    "wof:placetype":"venue"
},
  "geometry": {"coordinates":[-97.320047,30.109323],"type":"Point"}
}