{
  "type": "Feature",
  "properties": {
    "iso:country":"US",
    "sg:address":"110 Dove Hill Dr",
    "sg:city":"Kyle",
    "sg:classifiers":[
        {
            "category":"Wholesale",
            "subcategory":"Chemicals & Plastics",
            "type":"Manufacturing & Wholesale Goods"
        }
    ],
    "sg:phone":"+1 512 376 6225",
    "sg:postcode":"78640",
    "sg:province":"TX",
    "sg:tags":[
        "textile",
        "dyer"
    ],
    "wof:name":"Plum Creek Textiles",
    "wof:placetype":"venue"
},
  "geometry": {"coordinates":[-97.71177900000001,29.992585],"type":"Point"}
}