{
  "type": "Feature",
  "properties": {
    "iso:country":"US",
    "sg:address":"2425 Underwood St",
    "sg:city":"Houston",
    "sg:classifiers":[
        {
            "category":"Freight",
            "type":"Transportation"
        }
    ],
    "sg:phone":"+1 713 668 1695",
    "sg:postcode":"77030",
    "sg:province":"TX",
    "sg:tags":[
        "trucking"
    ],
    "wof:name":"J A Trucking Inc",
    "wof:placetype":"venue"
},
  "geometry": {"coordinates":[-95.417295,29.699668],"type":"Point"}
}