{
  "type": "Feature",
  "properties": {
    "iso:country":"US",
    "sg:address":"5908 Trabadora Cove",
    "sg:city":"Austin",
    "sg:classifiers":[
        {
            "category":"Personal",
            "subcategory":"Beauty Salon",
            "type":"Services"
        }
    ],
    "sg:phone":"+1 512 249 5331",
    "sg:postcode":"78759",
    "sg:province":"TX",
    "sg:tags":[
        "shop"
    ],
    "wof:name":"Pamela's Beauty Secrets",
    "wof:placetype":"venue"
},
  "geometry": {"coordinates":[-97.75888999999999,30.413814],"type":"Point"}
}