{
  "type": "Feature",
  "properties": {
    "iso:country":"US",
    "sg:address":"632 Northew St",
    "sg:city":"Houston",
    "sg:classifiers":[
        {
            "category":"Manufacturing",
            "subcategory":"Chemicals & Compounds",
            "type":"Manufacturing & Wholesale Goods"
        }
    ],
    "sg:phone":"+1 713 694 2100",
    "sg:postcode":"77091",
    "sg:province":"TX",
    "sg:tags":[
        "mfg",
        "plastic"
    ],
    "wof:name":"TMJ Plastics",
    "wof:placetype":"venue"
},
  "geometry": {"coordinates":[-95.411176,29.851076],"type":"Point"}
}