{
  "type": "Feature",
  "properties": {
    "iso:country":"US",
    "sg:address":"2005 Pearl Ln",
    "sg:city":"Irving",
    "sg:classifiers":[
        {
            "category":"Shopping",
            "type":"Retail Goods"
        }
    ],
    "sg:phone":"+1 972 399 6408",
    "sg:postcode":"75060",
    "sg:province":"TX",
    "sg:tags":[
        "merchandise"
    ],
    "wof:name":"Service Fire & Safety",
    "wof:placetype":"venue"
},
  "geometry": {"coordinates":[-96.968191,32.787278],"type":"Point"}
}