{
  "type": "Feature",
  "properties": {
    "iso:country":"US",
    "sg:address":"1306 Fern Shadow Cove",
    "sg:city":"San Antonio",
    "sg:classifiers":[
        {
            "category":"Professional",
            "subcategory":"Business Services",
            "type":"Services"
        }
    ],
    "sg:phone":"+1 210 479 0649",
    "sg:postcode":"78258",
    "sg:province":"TX",
    "wof:name":"J Moore Interiors For You",
    "wof:placetype":"venue"
},
  "geometry": {"coordinates":[-98.51763699999999,29.619975],"type":"Point"}
}