{
  "type": "Feature",
  "properties": {
    "iso:country":"US",
    "sg:address":"6371 Richmond Ave Ste 200",
    "sg:city":"Houston",
    "sg:classifiers":[
        {
            "category":"Professional",
            "subcategory":"Lawyer & Legal Services",
            "type":"Services"
        }
    ],
    "sg:phone":"+1 713 266 4666",
    "sg:postcode":"77057",
    "sg:province":"TX",
    "wof:name":"Schmidt Roger N Atty",
    "wof:placetype":"venue"
},
  "geometry": {"coordinates":[-95.4953,29.7316],"type":"Point"}
}