{
  "type": "Feature",
  "properties": {
    "iso:country":"US",
    "sg:address":"10325 Landsbury Dr",
    "sg:city":"Houston",
    "sg:classifiers":[
        {
            "category":"Wholesale",
            "subcategory":"Machinery & Supplies",
            "type":"Manufacturing & Wholesale Goods"
        }
    ],
    "sg:phone":"+1 281 498 6600",
    "sg:postcode":"77099",
    "sg:province":"TX",
    "sg:tags":[
        "valve"
    ],
    "sg:website":"www.equipmentvalve.com",
    "wof:name":"Equipment Valve & Supply Inc",
    "wof:placetype":"venue"
},
  "geometry": {"coordinates":[-95.57316299999999,29.664517],"type":"Point"}
}