{
  "type": "Feature",
  "properties": {
    "iso:country":"US",
    "sg:address":"410 Browning St",
    "sg:city":"Amarillo",
    "sg:classifiers":[
        {
            "category":"Building & Trades",
            "subcategory":"Cleaning & Sanitation",
            "type":"Services"
        }
    ],
    "sg:phone":"+1 806 373 4324",
    "sg:postcode":"79104",
    "sg:province":"TX",
    "sg:tags":[
        "commercial",
        "janitorial"
    ],
    "wof:name":"Martinez Janitorial Service",
    "wof:placetype":"venue"
},
  "geometry": {"coordinates":[-101.807243,35.205534],"type":"Point"}
}