{
  "type": "Feature",
  "properties": {
    "iso:country":"US",
    "sg:address":"400 Kaye St",
    "sg:city":"Borger",
    "sg:classifiers":[
        {
            "category":"Education",
            "subcategory":"School",
            "type":"Public Place"
        }
    ],
    "sg:phone":"+1 806 273 1088",
    "sg:postcode":"79007",
    "sg:province":"TX",
    "wof:name":"Borger Headstart",
    "wof:placetype":"venue"
},
  "geometry": {"coordinates":[-101.39086399999999,35.653106],"type":"Point"}
}