{
  "type": "Feature",
  "properties": {
    "iso:country":"US",
    "sg:address":"4911 Fall Creek Hwy",
    "sg:city":"Granbury",
    "sg:classifiers":[
        {
            "category":"Professional",
            "subcategory":"Accounting & Tax Preparation",
            "type":"Services"
        }
    ],
    "sg:phone":"+1 817 326 2299",
    "sg:postcode":"76049",
    "sg:province":"TX",
    "wof:name":"Pugh Edward H Associates CPA",
    "wof:placetype":"venue"
},
  "geometry": {"coordinates":[-97.67555299999999,32.428899],"type":"Point"}
}