{
  "type": "Feature",
  "properties": {
    "iso:country":"US",
    "sg:address":"114 Premier Rd",
    "sg:city":"Longview",
    "sg:classifiers":[
        {
            "category":"Building & Trades",
            "subcategory":"Landscaping Services",
            "type":"Services"
        }
    ],
    "sg:phone":"+1 903 295 1441",
    "sg:postcode":"75604",
    "sg:province":"TX",
    "sg:tags":[
        "landscape",
        "contractor"
    ],
    "wof:name":"Quality Lawn Care",
    "wof:placetype":"venue"
},
  "geometry": {"coordinates":[-94.806094,32.503451],"type":"Point"}
}