{
  "type": "Feature",
  "properties": {
    "iso:country":"US",
    "sg:address":"1705 S Capital of Texas Hwy",
    "sg:city":"Austin",
    "sg:classifiers":[
        {
            "category":"Banks & Credit Unions",
            "subcategory":"Bank",
            "type":"Services"
        }
    ],
    "sg:phone":"+1 512 329 9040",
    "sg:postcode":"78746",
    "sg:province":"TX",
    "sg:tags":[
        "mortgage",
        "loan",
        "broker",
        "real estate"
    ],
    "sg:website":"www.wrstarkeymortgage.com",
    "wof:name":"W R Starkey Mortgage",
    "wof:placetype":"venue"
},
  "geometry": {"coordinates":[-97.81759599999999,30.2717],"type":"Point"}
}