{
  "type": "Feature",
  "properties": {
    "iso:country":"US",
    "sg:address":"6434 Kenwood Ave",
    "sg:city":"Dallas",
    "sg:classifiers":[
        {
            "category":"Shopping",
            "subcategory":"Clothing, Apparel, & Fashions",
            "type":"Retail Goods"
        }
    ],
    "sg:phone":"+1 214 823 5069",
    "sg:postcode":"75214",
    "sg:province":"TX",
    "wof:name":"Liza Bayze",
    "wof:placetype":"venue"
},
  "geometry": {"coordinates":[-96.751077,32.83261],"type":"Point"}
}