{
  "type": "Feature",
  "properties": {
    "iso:country":"US",
    "sg:address":"43 S Altwood Cir",
    "sg:city":"Spring",
    "sg:classifiers":[
        {
            "category":"Professional",
            "subcategory":"Business Services",
            "type":"Services"
        }
    ],
    "sg:phone":"+1 281 367 4792",
    "sg:postcode":"77382",
    "sg:province":"TX",
    "wof:name":"Right Next Door",
    "wof:placetype":"venue"
},
  "geometry": {"coordinates":[-95.55286700000001,30.179719],"type":"Point"}
}