{
  "type": "Feature",
  "properties": {
    "iso:country":"US",
    "sg:address":"1358 Salford Dr",
    "sg:city":"Houston",
    "sg:classifiers":[
        {
            "category":"Wholesale",
            "subcategory":"Groceries",
            "type":"Manufacturing & Wholesale Goods"
        }
    ],
    "sg:phone":"+1 713 838 7722",
    "sg:postcode":"77008",
    "sg:province":"TX",
    "sg:tags":[
        "food",
        "item",
        "specialty"
    ],
    "wof:name":"Selected Food & Beverage Inc",
    "wof:placetype":"venue"
},
  "geometry": {"coordinates":[-95.444647,29.793612],"type":"Point"}
}