{
  "type": "Feature",
  "properties": {
    "iso:country":"US",
    "sg:address":"1047 Flagstone Dr",
    "sg:city":"San Antonio",
    "sg:classifiers":[
        {
            "category":"Professional",
            "subcategory":"Computer Services",
            "type":"Services"
        }
    ],
    "sg:phone":"+1 210 495 4060",
    "sg:postcode":"78260",
    "sg:province":"TX",
    "sg:tags":[
        "related"
    ],
    "wof:name":"Twe International Inc",
    "wof:placetype":"venue"
},
  "geometry": {"coordinates":[-98.51016300000001,29.670798],"type":"Point"}
}