{
  "type": "Feature",
  "properties": {
    "iso:country":"US",
    "sg:address":"505 Boatler Rd",
    "sg:city":"Big Spring",
    "sg:classifiers":[
        {
            "category":"Professional",
            "type":"Services"
        }
    ],
    "sg:phone":"+1 432 264 1105",
    "sg:postcode":"79720",
    "sg:province":"TX",
    "wof:name":"Bayridge Texas Corp",
    "wof:placetype":"venue"
},
  "geometry": {"coordinates":[-101.469341,32.200275],"type":"Point"}
}