{
  "type": "Feature",
  "properties": {
    "iso:country":"US",
    "sg:address":"1000 S Columbia St",
    "sg:city":"Plainview",
    "sg:classifiers":[
        {
            "category":"Professional",
            "subcategory":"Engineering",
            "type":"Services"
        },
        {
            "category":"Retail",
            "subcategory":"Repair Shop",
            "type":"Services"
        },
        {
            "category":"Autos & Motor Vehicles",
            "subcategory":"Recreational Vehicle Sales",
            "type":"Retail Goods"
        }
    ],
    "sg:phone":"+1 806 293 1307",
    "sg:postcode":"79072",
    "sg:province":"TX",
    "sg:tags":[
        "rebuilding",
        "aircraft",
        "maintenance"
    ],
    "wof:name":"Hutcherson Air Service Inc",
    "wof:placetype":"venue"
},
  "geometry": {"coordinates":[-101.707362,34.169765],"type":"Point"}
}