{
  "type": "Feature",
  "properties": {
    "iso:country":"US",
    "sg:address":"4917 S Peachtree Rd",
    "sg:city":"Mesquite",
    "sg:classifiers":[
        {
            "category":"Real Estate",
            "subcategory":"Real Estate Agent",
            "type":"Services"
        }
    ],
    "sg:phone":"+1 972 557 3886",
    "sg:postcode":"75180",
    "sg:province":"TX",
    "wof:name":"North Mesquite Enterprise",
    "wof:placetype":"venue"
},
  "geometry": {"coordinates":[-96.631298,32.704893],"type":"Point"}
}