{
  "type": "Feature",
  "properties": {
    "iso:country":"US",
    "sg:address":"907 N Bergfield Ave",
    "sg:city":"Tyler",
    "sg:classifiers":[
        {
            "category":"Shopping",
            "subcategory":"Clothing, Apparel, & Fashions",
            "type":"Retail Goods"
        },
        {
            "category":"Retail",
            "subcategory":"Laundry & Dry Cleaning",
            "type":"Services"
        }
    ],
    "sg:phone":"+1 318 752 0460",
    "sg:postcode":"75702",
    "sg:province":"TX",
    "sg:tags":[
        "supply",
        "uniforms-accessories",
        "uniform"
    ],
    "sg:website":"http://profiles.cintas.com/USA/TX/Uniform-Rentals-Texarkana-TX.html",
    "wof:name":"Cintas Uniform Rental & Work Apparel",
    "wof:placetype":"venue"
},
  "geometry": {"coordinates":[-95.292787,32.35938],"type":"Point"}
}