{
  "type": "Feature",
  "properties": {
    "iso:country":"US",
    "sg:address":"704 E Walnut St",
    "sg:city":"Garland",
    "sg:classifiers":[
        {
            "category":"Retail",
            "subcategory":"Repair Shop",
            "type":"Services"
        },
        {
            "category":"Building & Trades",
            "subcategory":"Construction",
            "type":"Services"
        }
    ],
    "sg:phone":"+1 972 276 8535",
    "sg:postcode":"75040",
    "sg:province":"TX",
    "sg:tags":[
        "welding",
        "contractor"
    ],
    "wof:name":"Armstrong Fabrication Services",
    "wof:placetype":"venue"
},
  "geometry": {"coordinates":[-96.622489,32.91438],"type":"Point"}
}