{
  "type": "Feature",
  "properties": {
    "iso:country":"US",
    "sg:address":"739 White Ranch Rd",
    "sg:city":"Fredericksburg",
    "sg:classifiers":[
        {
            "category":"Education",
            "subcategory":"Dance Studio",
            "type":"Public Place"
        }
    ],
    "sg:phone":"+1 830 990 2666",
    "sg:postcode":"78606",
    "sg:province":"TX",
    "sg:tags":[
        "instruction",
        "dancing"
    ],
    "wof:name":"Beaux Hickey's Dance Hall",
    "wof:placetype":"venue"
},
  "geometry": {"coordinates":[-98.30344599999999,30.146987],"type":"Point"}
}