{
  "type": "Feature",
  "properties": {
    "iso:country":"US",
    "sg:address":"722 S Bois D Arc Ave",
    "sg:city":"Tyler",
    "sg:classifiers":[
        {
            "category":"Wholesale",
            "subcategory":"Drugs",
            "type":"Manufacturing & Wholesale Goods"
        }
    ],
    "sg:phone":"+1 903 592 8230",
    "sg:postcode":"75701",
    "sg:province":"TX",
    "sg:tags":[
        "pharmaceutical",
        "product"
    ],
    "wof:name":"Advanced Pharmaceutical Supply",
    "wof:placetype":"venue"
},
  "geometry": {"coordinates":[-95.303229,32.340998],"type":"Point"}
}