{
  "type": "Feature",
  "properties": {
    "iso:country":"US",
    "sg:address":"1047 Gardenia Dr",
    "sg:city":"Houston",
    "sg:classifiers":[
        {
            "category":"Shopping",
            "type":"Retail Goods"
        }
    ],
    "sg:phone":"+1 713 688 6363",
    "sg:postcode":"77018",
    "sg:province":"TX",
    "sg:tags":[
        "pet",
        "shop"
    ],
    "wof:name":"Bone Voyage Pet Sitting Svc",
    "wof:placetype":"venue"
},
  "geometry": {"coordinates":[-95.42642499999999,29.826878],"type":"Point"}
}