{
  "type": "Feature",
  "properties": {
    "iso:country":"US",
    "sg:address":"6101 Richmond Ave",
    "sg:city":"Houston",
    "sg:classifiers":[
        {
            "category":"Recreation",
            "subcategory":"Dance Hall",
            "type":"Entertainment"
        }
    ],
    "sg:phone":"+1 713 266 3455",
    "sg:postcode":"77057",
    "sg:province":"TX",
    "sg:tags":[
        "club"
    ],
    "sg:website":"www.wildwesthouston.com",
    "wof:name":"Wild West",
    "wof:placetype":"venue"
},
  "geometry": {"coordinates":[-95.4879,29.7316],"type":"Point"}
}