{
  "type": "Feature",
  "properties": {
    "iso:country":"US",
    "sg:address":"4511 Motley Dr",
    "sg:city":"Mesquite",
    "sg:classifiers":[
        {
            "category":"Organizations",
            "subcategory":"Religious Organization",
            "type":"Services"
        }
    ],
    "sg:phone":"+1 972 270 0677",
    "sg:postcode":"75150",
    "sg:province":"TX",
    "wof:name":"Wise Ministries",
    "wof:placetype":"venue"
},
  "geometry": {"coordinates":[-96.657731,32.826047],"type":"Point"}
}