{
  "type": "Feature",
  "properties": {
    "iso:country":"US",
    "sg:address":"5807 Dietrich Rd",
    "sg:city":"San Antonio",
    "sg:classifiers":[
        {
            "category":"Wholesale",
            "subcategory":"Hardware",
            "type":"Manufacturing & Wholesale Goods"
        }
    ],
    "sg:phone":"+1 210 661 4611",
    "sg:postcode":"78219",
    "sg:province":"TX",
    "sg:tags":[
        "repair",
        "truck",
        "unit",
        "refrigeration"
    ],
    "wof:name":"San Antonio Thermo King Inc",
    "wof:placetype":"venue"
},
  "geometry": {"coordinates":[-98.378288,29.441495],"type":"Point"}
}