{
  "type": "Feature",
  "properties": {
    "iso:country":"US",
    "sg:address":"3900 Junius St Ste 705",
    "sg:city":"Dallas",
    "sg:classifiers":[
        {
            "category":"Health Services",
            "subcategory":"Doctor",
            "type":"Services"
        }
    ],
    "sg:phone":"+1 214 370 3535",
    "sg:postcode":"75246",
    "sg:province":"TX",
    "wof:name":"PARK ANDREW E MD",
    "wof:placetype":"venue"
},
  "geometry": {"coordinates":[-96.778085,32.790914],"type":"Point"}
}