{
  "type": "Feature",
  "properties": {
    "iso:country":"US",
    "sg:address":"132 S Texas St",
    "sg:city":"De Leon",
    "sg:classifiers":[
        {
            "category":"Professional",
            "type":"Services"
        }
    ],
    "sg:phone":"+1 254 893 3678",
    "sg:postcode":"76444",
    "sg:province":"TX",
    "sg:tags":[
        "establishment"
    ],
    "wof:name":"Comanche County Water",
    "wof:placetype":"venue"
},
  "geometry": {"coordinates":[-98.53715800000001,32.108717],"type":"Point"}
}