{
  "type": "Feature",
  "properties": {
    "iso:country":"US",
    "sg:address":"1116 Midway Dr",
    "sg:city":"Richardson",
    "sg:classifiers":[
        {
            "category":"Professional",
            "subcategory":"Research",
            "type":"Services"
        }
    ],
    "sg:phone":"+1 972 671 0367",
    "sg:postcode":"75081",
    "sg:province":"TX",
    "sg:tags":[
        "nonphysical",
        "commercial"
    ],
    "wof:name":"Cousins Valentine & Pleasants",
    "wof:placetype":"venue"
},
  "geometry": {"coordinates":[-96.705511,32.95275],"type":"Point"}
}