{
  "type": "Feature",
  "properties": {
    "iso:country":"US",
    "sg:address":"2708 Flower Mound Rd",
    "sg:city":"Flower Mound",
    "sg:classifiers":[
        {
            "category":"Restaurant",
            "type":"Food & Drink"
        }
    ],
    "sg:menulink":"http://www.allmenus.com/tx/lewisville/193390-taco-bell/menu/",
    "sg:postcode":"75022",
    "sg:province":"TX",
    "sg:tags":[
        "mexican"
    ],
    "wof:name":"Taco Bell",
    "wof:placetype":"venue"
},
  "geometry": {"coordinates":[-97.07273499999999,33.014549],"type":"Point"}
}