{
  "type": "Feature",
  "properties": {
    "iso:country":"US",
    "sg:address":"1111 Center St",
    "sg:city":"San Antonio",
    "sg:classifiers":[
        {
            "category":"Manufacturing",
            "subcategory":"Paper Products",
            "type":"Manufacturing & Wholesale Goods"
        }
    ],
    "sg:phone":"+1 210 225 2901",
    "sg:postcode":"78202",
    "sg:province":"TX",
    "sg:tags":[
        "corrugated",
        "solid",
        "fiber",
        "box"
    ],
    "sg:website":"www.myinland.com",
    "wof:name":"Inland Paperboard & Packaging",
    "wof:placetype":"venue"
},
  "geometry": {"coordinates":[-98.46267899999999,29.42217],"type":"Point"}
}