{
  "type": "Feature",
  "properties": {
    "iso:country":"US",
    "sg:address":"707 S Tabor Ave",
    "sg:city":"Bryan",
    "sg:classifiers":[
        {
            "category":"Freight",
            "type":"Transportation"
        }
    ],
    "sg:phone":"+1 979 775 6683",
    "sg:postcode":"77803",
    "sg:province":"TX",
    "sg:tags":[
        "moving",
        "household",
        "used",
        "storage",
        "good"
    ],
    "wof:name":"Compass Moving & Storage",
    "wof:placetype":"venue"
},
  "geometry": {"coordinates":[-96.373002,30.667673],"type":"Point"}
}