{
  "type": "Feature",
  "properties": {
    "iso:country":"US",
    "sg:address":"1223 Temple Sq",
    "sg:city":"San Antonio",
    "sg:classifiers":[
        {
            "category":"Manufacturing",
            "subcategory":"Furniture",
            "type":"Manufacturing & Wholesale Goods"
        }
    ],
    "sg:phone":"+1 210 674 4234",
    "sg:postcode":"78245",
    "sg:province":"TX",
    "sg:tags":[
        "household",
        "metal",
        "mfg"
    ],
    "wof:name":"WD & Iron Dsgns of SA",
    "wof:placetype":"venue"
},
  "geometry": {"coordinates":[-98.680229,29.422291],"type":"Point"}
}