{
  "type": "Feature",
  "properties": {
    "iso:country":"US",
    "sg:address":"1619 Lubbock St",
    "sg:city":"Houston",
    "sg:classifiers":[
        {
            "category":"Professional",
            "subcategory":"Lawyer & Legal Services",
            "type":"Services"
        }
    ],
    "sg:phone":"+1 832 387 4394",
    "sg:postcode":"77007",
    "sg:province":"TX",
    "sg:website":"www.colebrookslaw.com/criminalde...",
    "wof:name":"J. Cole Brooks, Houston DWI & Criminal Defense Attorney",
    "wof:placetype":"venue"
},
  "geometry": {"coordinates":[-95.374544,29.765178],"type":"Point"}
}