{
  "type": "Feature",
  "properties": {
    "iso:country":"US",
    "sg:address":"811 Luke St",
    "sg:city":"Irving",
    "sg:classifiers":[
        {
            "category":"Wholesale",
            "subcategory":"Electrical",
            "type":"Manufacturing & Wholesale Goods"
        },
        {
            "category":"Military Area",
            "subcategory":"Restricted Area",
            "type":"Public Place"
        }
    ],
    "sg:phone":"+1 972 986 5823",
    "sg:postcode":"75061",
    "sg:province":"TX",
    "sg:tags":[
        "equipment",
        "breaker",
        "electric",
        "circuit",
        "supply"
    ],
    "sg:website":"http://www.occb.net",
    "wof:name":"Texas Breakers",
    "wof:placetype":"venue"
},
  "geometry": {"coordinates":[-96.991692,32.821858],"type":"Point"}
}