{
  "type": "Feature",
  "properties": {
    "iso:country":"US",
    "sg:address":"1501 Highway 290 E",
    "sg:city":"Brenham",
    "sg:classifiers":[
        {
            "category":"Travel",
            "subcategory":"Hotels & Motels",
            "type":"Entertainment"
        }
    ],
    "sg:phone":"+1 979 251 7791",
    "sg:postcode":"77833",
    "sg:province":"TX",
    "sg:website":"http://www.bestwestern.com",
    "wof:name":"Best Western Inn Of Brenham",
    "wof:placetype":"venue"
},
  "geometry": {"coordinates":[-96.375773,30.142803],"type":"Point"}
}