{
  "type": "Feature",
  "properties": {
    "iso:country":"US",
    "sg:address":"3429 Olton Rd",
    "sg:city":"Plainview",
    "sg:classifiers":[
        {
            "category":"Shopping",
            "subcategory":"Shoes",
            "type":"Retail Goods"
        }
    ],
    "sg:phone":"+1 806 293 1298",
    "sg:postcode":"79072",
    "sg:province":"TX",
    "wof:name":"Payless Shoe Source",
    "wof:placetype":"venue"
},
  "geometry": {"coordinates":[-101.74901699999999,34.187288],"type":"Point"}
}