{
  "type": "Feature",
  "properties": {
    "iso:country":"US",
    "sg:address":"1392 W Main St",
    "sg:city":"Lewisville",
    "sg:classifiers":[
        {
            "category":"Retail",
            "subcategory":"Veterinary Services",
            "type":"Services"
        }
    ],
    "sg:phone":"+1 972 221 3568",
    "sg:postcode":"75067",
    "sg:province":"TX",
    "wof:name":"Kirby J Gus Dvm",
    "wof:placetype":"venue"
},
  "geometry": {"coordinates":[-97.030052,33.042073],"type":"Point"}
}