{
  "type": "Feature",
  "properties": {
    "iso:country":"US",
    "sg:address":"15 Glenheather Ct",
    "sg:city":"Dallas",
    "sg:classifiers":[
        {
            "category":"Organizations",
            "subcategory":"Religious Organization",
            "type":"Services"
        }
    ],
    "sg:phone":"+1 214 987 6246",
    "sg:postcode":"75225",
    "sg:province":"TX",
    "wof:name":"Stark Temple C",
    "wof:placetype":"venue"
},
  "geometry": {"coordinates":[-96.775687,32.873922],"type":"Point"}
}