{
  "type": "Feature",
  "properties": {
    "iso:country":"US",
    "sg:address":"713 Russet Valley Dr",
    "sg:city":"Cedar Park",
    "sg:classifiers":[
        {
            "category":"Professional",
            "type":"Services"
        }
    ],
    "sg:phone":"+1 512 331 6011",
    "sg:postcode":"78613",
    "sg:province":"TX",
    "sg:tags":[
        "establishment"
    ],
    "wof:name":"Candlesource",
    "wof:placetype":"venue"
},
  "geometry": {"coordinates":[-97.82302799999999,30.499274],"type":"Point"}
}