{
  "type": "Feature",
  "properties": {
    "iso:country":"US",
    "sg:address":"114 W Laureland Rd",
    "sg:city":"Dallas",
    "sg:classifiers":[
        {
            "category":"Organizations",
            "subcategory":"Religious Organization",
            "type":"Services"
        }
    ],
    "sg:phone":"+1 214 374 0108",
    "sg:postcode":"75232",
    "sg:province":"TX",
    "sg:tags":[
        "church"
    ],
    "wof:name":"Empowerment Temple Of Praise",
    "wof:placetype":"venue"
},
  "geometry": {"coordinates":[-96.822931,32.674728],"type":"Point"}
}