{
  "type": "Feature",
  "properties": {
    "iso:country":"US",
    "sg:address":"7148 Tokalon Dr",
    "sg:city":"Dallas",
    "sg:classifiers":[
        {
            "category":"Professional",
            "subcategory":"Management & Consulting",
            "type":"Services"
        }
    ],
    "sg:phone":"+1 214 324 3807",
    "sg:postcode":"75214",
    "sg:province":"TX",
    "wof:name":"Martinez Management Inc",
    "wof:placetype":"venue"
},
  "geometry": {"coordinates":[-96.734764,32.820613],"type":"Point"}
}