{
  "type": "Feature",
  "properties": {
    "iso:country":"US",
    "sg:address":"1100 Louisiana St",
    "sg:city":"South Houston",
    "sg:classifiers":[
        {
            "category":"Retail",
            "subcategory":"Repair Shop",
            "type":"Services"
        }
    ],
    "sg:phone":"+1 713 947 1616",
    "sg:postcode":"77587",
    "sg:province":"TX",
    "wof:name":"Norwalk Compressor Repair Cent",
    "wof:placetype":"venue"
},
  "geometry": {"coordinates":[-95.249377,29.664787],"type":"Point"}
}