{
  "type": "Feature",
  "properties": {
    "iso:country":"US",
    "sg:address":"706 Shenandoah Dr",
    "sg:city":"Spring",
    "sg:classifiers":[
        {
            "category":"Freight",
            "type":"Transportation"
        }
    ],
    "sg:phone":"+1 281 367 8213",
    "sg:postcode":"77381",
    "sg:province":"TX",
    "sg:tags":[
        "operator",
        "local",
        "trucking"
    ],
    "wof:name":"Jcf Trucking",
    "wof:placetype":"venue"
},
  "geometry": {"coordinates":[-95.464507,30.181077],"type":"Point"}
}