{
  "type": "Feature",
  "properties": {
    "iso:country":"US",
    "sg:address":"303 Memorial City Way",
    "sg:city":"Houston",
    "sg:classifiers":[
        {
            "category":"Shopping",
            "subcategory":"Mobile Phones",
            "type":"Retail Goods"
        }
    ],
    "sg:phone":"+1 713 647 8842",
    "sg:postcode":"77024",
    "sg:province":"TX",
    "sg:website":"www.t-mobile.com",
    "wof:name":"T-Mobile",
    "wof:placetype":"venue"
},
  "geometry": {"coordinates":[-95.53575499999999,29.779658],"type":"Point"}
}