{
  "type": "Feature",
  "properties": {
    "iso:country":"US",
    "sg:address":"1913 State Hwy 6",
    "sg:city":"Houston",
    "sg:classifiers":[
        {
            "category":"Wholesale",
            "subcategory":"Durable Goods & Equipment",
            "type":"Manufacturing & Wholesale Goods"
        }
    ],
    "sg:phone":"+1 281 496 0767",
    "sg:postcode":"77077",
    "sg:province":"TX",
    "wof:name":"Highway 6 Firewood",
    "wof:placetype":"venue"
},
  "geometry": {"coordinates":[-95.644509,29.750408],"type":"Point"}
}