{
  "type": "Feature",
  "properties": {
    "iso:country":"US",
    "sg:address":"6632 Pinehurst Dr",
    "sg:city":"San Angelo",
    "sg:classifiers":[
        {
            "category":"Health Services",
            "subcategory":"Doctor",
            "type":"Services"
        }
    ],
    "sg:phone":"+1 325 651 7184",
    "sg:postcode":"76904",
    "sg:province":"TX",
    "wof:name":"Robert C Mankin DDS",
    "wof:placetype":"venue"
},
  "geometry": {"coordinates":[-100.4528,31.383066],"type":"Point"}
}