{
  "type": "Feature",
  "properties": {
    "iso:country":"US",
    "sg:address":"956 Commercial Ave",
    "sg:city":"Anson",
    "sg:classifiers":[
        {
            "category":"Autos & Motor Vehicles",
            "subcategory":"Auto Supplies",
            "type":"Retail Goods"
        },
        {
            "category":"Wholesale",
            "subcategory":"Auto Parts",
            "type":"Manufacturing & Wholesale Goods"
        }
    ],
    "sg:phone":"+1 325 823 3278",
    "sg:postcode":"79501",
    "sg:province":"TX",
    "sg:tags":[
        "automobile"
    ],
    "wof:name":"Anson Auto Parts Inc",
    "wof:placetype":"venue"
},
  "geometry": {"coordinates":[-99.896846,32.758502],"type":"Point"}
}