{
  "type": "Feature",
  "properties": {
    "iso:country":"US",
    "sg:address":"133 E Main St",
    "sg:city":"Yorktown",
    "sg:classifiers":[
        {
            "category":"Manufacturing",
            "subcategory":"Printing",
            "type":"Manufacturing & Wholesale Goods"
        }
    ],
    "sg:phone":"+1 361 564 2242",
    "sg:postcode":"78164",
    "sg:province":"TX",
    "sg:tags":[
        "newspaper"
    ],
    "wof:name":"Yorktown News View",
    "wof:placetype":"venue"
},
  "geometry": {"coordinates":[-97.501215,28.981314],"type":"Point"}
}