{
  "type": "Feature",
  "properties": {
    "iso:country":"US",
    "sg:address":"819 S 25 Mile Ave",
    "sg:city":"Hereford",
    "sg:classifiers":[
        {
            "category":"Cinema",
            "subcategory":"Movie Rental",
            "type":"Entertainment"
        }
    ],
    "sg:phone":"+1 806 363 1888",
    "sg:postcode":"79045",
    "sg:province":"TX",
    "sg:tags":[
        "video",
        "tape"
    ],
    "wof:name":"Movie Gallery",
    "wof:placetype":"venue"
},
  "geometry": {"coordinates":[-102.405745,34.820607],"type":"Point"}
}