{
  "type": "Feature",
  "properties": {
    "iso:country":"US",
    "sg:address":"6713 Matson Dr",
    "sg:city":"Lewisville",
    "sg:classifiers":[
        {
            "category":"Professional",
            "type":"Services"
        }
    ],
    "sg:phone":"+1 972 370 2429",
    "sg:postcode":"75056",
    "sg:province":"TX",
    "wof:name":"Chuting Stars Agility",
    "wof:placetype":"venue"
},
  "geometry": {"coordinates":[-96.873136,33.09225],"type":"Point"}
}