{
  "type": "Feature",
  "properties": {
    "iso:country":"US",
    "sg:address":"1634 Eastside Dr",
    "sg:city":"Wichita Falls",
    "sg:classifiers":[
        {
            "category":"Utilities",
            "subcategory":"Refuse",
            "type":"Services"
        }
    ],
    "sg:phone":"+1 940 767 1997",
    "sg:postcode":"76301",
    "sg:province":"TX",
    "sg:tags":[
        "garbage",
        "collection"
    ],
    "wof:name":"Wichita Waste Management",
    "wof:placetype":"venue"
},
  "geometry": {"coordinates":[-98.46115500000001,33.905725],"type":"Point"}
}