{
  "type": "Feature",
  "properties": {
    "iso:country":"US",
    "sg:address":"12949 Shannon Hills Dr",
    "sg:city":"Houston",
    "sg:classifiers":[
        {
            "category":"Building & Trades",
            "subcategory":"Plumbing",
            "type":"Services"
        }
    ],
    "sg:phone":"+1 281 498 6034",
    "sg:postcode":"77099",
    "sg:province":"TX",
    "sg:tags":[
        "contractor"
    ],
    "wof:name":"Lamb Plumbing",
    "wof:placetype":"venue"
},
  "geometry": {"coordinates":[-95.610551,29.6813],"type":"Point"}
}