{
  "type": "Feature",
  "properties": {
    "iso:country":"US",
    "sg:address":"1424 Linden Dr",
    "sg:city":"Denton",
    "sg:classifiers":[
        {
            "category":"Organizations",
            "subcategory":"Religious Organization",
            "type":"Services"
        }
    ],
    "sg:phone":"+1 940 243 3449",
    "sg:postcode":"76201",
    "sg:province":"TX",
    "sg:tags":[
        "church"
    ],
    "wof:name":"North Texas Chinese Church",
    "wof:placetype":"venue"
},
  "geometry": {"coordinates":[-97.149584,33.223605],"type":"Point"}
}