{
  "type": "Feature",
  "properties": {
    "iso:country":"US",
    "sg:address":"3828 Whitaker",
    "sg:city":"Schertz",
    "sg:classifiers":[
        {
            "category":"Professional",
            "subcategory":"Detective & Security Services",
            "type":"Services"
        }
    ],
    "sg:phone":"+1 210 415 9354",
    "sg:postcode":"78154",
    "sg:province":"TX",
    "sg:tags":[
        "civil",
        "process"
    ],
    "wof:name":"Bill Tuch Legal Services",
    "wof:placetype":"venue"
},
  "geometry": {"coordinates":[-98.275638,29.584038],"type":"Point"}
}