{
  "type": "Feature",
  "properties": {
    "iso:country":"US",
    "sg:address":"2205 Richmond Ave",
    "sg:city":"Houston",
    "sg:classifiers":[
        {
            "category":"Organizations",
            "subcategory":"Community Association",
            "type":"Services"
        }
    ],
    "sg:phone":"+1 713 523 3837",
    "sg:postcode":"77098",
    "sg:province":"TX",
    "sg:tags":[
        "club"
    ],
    "wof:name":"M P Tax Solutions",
    "wof:placetype":"venue"
},
  "geometry": {"coordinates":[-95.415015,29.73411],"type":"Point"}
}