{
  "type": "Feature",
  "properties": {
    "iso:country":"US",
    "sg:address":"2524 FM 1092",
    "sg:city":"Missouri City",
    "sg:classifiers":[
        {
            "category":"Organizations",
            "subcategory":"Non-profit Organization",
            "type":"Services"
        }
    ],
    "sg:phone":"+1 281 499 5496",
    "sg:postcode":"77459",
    "sg:province":"TX",
    "sg:tags":[
        "information",
        "alcoholism",
        "treatment"
    ],
    "wof:name":"Lamp Lighters Club",
    "wof:placetype":"venue"
},
  "geometry": {"coordinates":[-95.56413000000001,29.582209],"type":"Point"}
}