{
  "type": "Feature",
  "properties": {
    "iso:country":"US",
    "sg:address":"1104 Morgan Blvd",
    "sg:city":"Harlingen",
    "sg:classifiers":[
        {
            "category":"Shopping",
            "subcategory":"Jewelry",
            "type":"Retail Goods"
        }
    ],
    "sg:phone":"+1 956 365 4323",
    "sg:postcode":"78550",
    "sg:province":"TX",
    "sg:tags":[
        "jeweler"
    ],
    "wof:name":"Art's Jewelry Repair Shop",
    "wof:placetype":"venue"
},
  "geometry": {"coordinates":[-97.67533299999999,26.204462],"type":"Point"}
}