{
  "type": "Feature",
  "properties": {
    "iso:country":"US",
    "sg:address":"3019 N Yarbrough Dr",
    "sg:city":"El Paso",
    "sg:classifiers":[
        {
            "category":"Retail",
            "subcategory":"Repair Shop",
            "type":"Services"
        }
    ],
    "sg:phone":"+1 915 598 4803",
    "sg:postcode":"79925",
    "sg:province":"TX",
    "sg:tags":[
        "television"
    ],
    "wof:name":"Henrys Vcr & TV Service",
    "wof:placetype":"venue"
},
  "geometry": {"coordinates":[-106.336913,31.784499],"type":"Point"}
}