{
  "type": "Feature",
  "properties": {
    "iso:country":"US",
    "sg:address":"1725 E State Highway 356",
    "sg:city":"Irving",
    "sg:classifiers":[
        {
            "category":"Autos & Motor Vehicles",
            "subcategory":"Fuel & Gas Station",
            "type":"Retail Goods"
        },
        {
            "category":"Food & Beverages",
            "subcategory":"Groceries & Convenience Stores",
            "type":"Retail Goods"
        }
    ],
    "sg:phone":"+1 972 579 1088",
    "sg:postcode":"75060",
    "sg:province":"TX",
    "wof:name":"Raceway",
    "wof:placetype":"venue"
},
  "geometry": {"coordinates":[-96.923306,32.809817],"type":"Point"}
}