{
  "type": "Feature",
  "properties": {
    "iso:country":"US",
    "sg:address":"10010 Forest Ln",
    "sg:city":"Dallas",
    "sg:classifiers":[
        {
            "category":"Building & Trades",
            "subcategory":"Construction",
            "type":"Services"
        }
    ],
    "sg:phone":"+1 214 342 8313",
    "sg:postcode":"75243",
    "sg:province":"TX",
    "sg:tags":[
        "company"
    ],
    "wof:name":"Jones Construction",
    "wof:placetype":"venue"
},
  "geometry": {"coordinates":[-96.71646800000001,32.909469],"type":"Point"}
}