{
  "type": "Feature",
  "properties": {
    "iso:country":"US",
    "sg:address":"150 Flora St",
    "sg:city":"New Braunfels",
    "sg:classifiers":[
        {
            "category":"Building & Trades",
            "subcategory":"Equipment Rental",
            "type":"Services"
        }
    ],
    "sg:phone":"+1 830 625 4663",
    "sg:postcode":"78130",
    "sg:province":"TX",
    "wof:name":"Sams Rentals",
    "wof:placetype":"venue"
},
  "geometry": {"coordinates":[-98.05383500000001,29.65181],"type":"Point"}
}