{
  "type": "Feature",
  "properties": {
    "iso:country":"US",
    "sg:address":"5048 Blue Glen Dr",
    "sg:city":"The Colony",
    "sg:classifiers":[
        {
            "category":"Retail",
            "subcategory":"Portrait Studio",
            "type":"Services"
        }
    ],
    "sg:phone":"+1 972 624 1605",
    "sg:postcode":"75056",
    "sg:province":"TX",
    "sg:tags":[
        "photographer"
    ],
    "wof:name":"Casey Kidwell",
    "wof:placetype":"venue"
},
  "geometry": {"coordinates":[-96.88275,33.077925],"type":"Point"}
}