{
  "type": "Feature",
  "properties": {
    "iso:country":"US",
    "sg:address":"1200 Seley Ave",
    "sg:city":"Waco",
    "sg:classifiers":[
        {
            "category":"Food & Beverages",
            "subcategory":"Groceries & Convenience Stores",
            "type":"Retail Goods"
        }
    ],
    "sg:phone":"+1 254 752 1842",
    "sg:postcode":"76704",
    "sg:province":"TX",
    "wof:name":"Number 1 Food Mart",
    "wof:placetype":"venue"
},
  "geometry": {"coordinates":[-97.125174,31.582002],"type":"Point"}
}