{
  "type": "Feature",
  "properties": {
    "iso:country":"US",
    "sg:address":"2748 Mira Vista Ln",
    "sg:city":"Rockwall",
    "sg:classifiers":[
        {
            "category":"Travel",
            "subcategory":"Travel Agent",
            "type":"Entertainment"
        }
    ],
    "sg:phone":"+1 972 771 0227",
    "sg:postcode":"75032",
    "sg:province":"TX",
    "sg:tags":[
        "agency"
    ],
    "wof:name":"Cruise Away",
    "wof:placetype":"venue"
},
  "geometry": {"coordinates":[-96.47913699999999,32.889704],"type":"Point"}
}