{
  "type": "Feature",
  "properties": {
    "iso:country":"US",
    "sg:address":"3868 Pecan Cir",
    "sg:city":"La Porte",
    "sg:classifiers":[
        {
            "category":"Travel",
            "subcategory":"Travel Agent",
            "type":"Entertainment"
        }
    ],
    "sg:phone":"+1 281 471 2756",
    "sg:postcode":"77571",
    "sg:province":"TX",
    "sg:tags":[
        "agency"
    ],
    "wof:name":"World Class Travel S",
    "wof:placetype":"venue"
},
  "geometry": {"coordinates":[-95.068744,29.653485],"type":"Point"}
}