{
  "type": "Feature",
  "properties": {
    "iso:country":"US",
    "sg:address":"92 Tarpon Ln",
    "sg:city":"Hitchcock",
    "sg:classifiers":[
        {
            "category":"Education",
            "subcategory":"Vocational School",
            "type":"Public Place"
        }
    ],
    "sg:phone":"+1 409 935 3037",
    "sg:postcode":"77541",
    "sg:province":"TX",
    "wof:name":"P Factor Aviation Inc",
    "wof:placetype":"venue"
},
  "geometry": {"coordinates":[-95.29483,28.959087],"type":"Point"}
}