{
  "type": "Feature",
  "properties": {
    "iso:country":"US",
    "sg:address":"9414 Westpark Dr",
    "sg:city":"Houston",
    "sg:classifiers":[
        {
            "category":"Autos & Motor Vehicles",
            "subcategory":"Fuel & Gas Station",
            "type":"Retail Goods"
        },
        {
            "category":"Autos & Motor Vehicles",
            "subcategory":"Auto Supplies",
            "type":"Retail Goods"
        },
        {
            "category":"Retail",
            "subcategory":"Auto Repair",
            "type":"Services"
        }
    ],
    "sg:phone":"+1 888 273 5792",
    "sg:postcode":"77063",
    "sg:province":"TX",
    "sg:tags":[
        "engines-rebuild",
        "oil",
        "radiator",
        "rebuilding",
        "transmission",
        "automobile",
        "exchange",
        "body",
        "sale",
        "engine",
        "lube",
        "brake",
        "automotive",
        "painting",
        "repairing",
        "tune",
        "clutch"
    ],
    "sg:website":"http://houston.citysearch.com/profile/external/43093170/houston_tx/transmission_plus_quality_auto_repair_body_shop.html?publisher=yellowpages&reference_id=1&placement=ypwebsitemip",
    "wof:name":"Transmission Plus Quality Auto Repair & Body Shop",
    "wof:placetype":"venue"
},
  "geometry": {"coordinates":[-95.52765100000001,29.720831],"type":"Point"}
}