{
  "type": "Feature",
  "properties": {
    "iso:country":"US",
    "sg:address":"429 E 50th St",
    "sg:city":"Odessa",
    "sg:classifiers":[
        {
            "category":"Professional",
            "subcategory":"Business Services",
            "type":"Services"
        }
    ],
    "sg:phone":"+1 432 363 9717",
    "sg:postcode":"79762",
    "sg:province":"TX",
    "wof:name":"Lavern Jones Scales",
    "wof:placetype":"venue"
},
  "geometry": {"coordinates":[-102.378258,31.893259],"type":"Point"}
}