{
  "type": "Feature",
  "properties": {
    "iso:country":"US",
    "sg:address":"4534 W Gate Boulevard",
    "sg:city":"Austin",
    "sg:classifiers":[
        {
            "category":"Health Services",
            "subcategory":"Dentist",
            "type":"Services"
        }
    ],
    "sg:phone":"+1 512 892 5988",
    "sg:postcode":"78745",
    "sg:province":"TX",
    "sg:tags":[
        "orthodontist"
    ],
    "wof:name":"Castle Dental Centers",
    "wof:placetype":"venue"
},
  "geometry": {"coordinates":[-97.80079600000001,30.230718],"type":"Point"}
}