{
  "type": "Feature",
  "properties": {
    "iso:country":"US",
    "sg:address":"418 Weeping Willow Way",
    "sg:city":"Magnolia",
    "sg:classifiers":[
        {
            "category":"Bakery",
            "type":"Food & Drink"
        }
    ],
    "sg:phone":"+1 936 321 7051",
    "sg:postcode":"77354",
    "sg:province":"TX",
    "sg:tags":[
        "cake",
        "pastry",
        "wedding"
    ],
    "wof:name":"Dream Cakes, Inc.",
    "wof:placetype":"venue"
},
  "geometry": {"coordinates":[-95.565223,30.22581],"type":"Point"}
}