{
  "type": "Feature",
  "properties": {
    "iso:country":"US",
    "sg:address":"2075 State Hwy 97",
    "sg:city":"Nixon",
    "sg:classifiers":[
        {
            "category":"Retail",
            "subcategory":"Animal Services",
            "type":"Services"
        }
    ],
    "sg:phone":"+1 830 582 2117",
    "sg:postcode":"78140",
    "sg:province":"TX",
    "sg:tags":[
        "training",
        "dog"
    ],
    "sg:website":"www.blacksunrb.com",
    "wof:name":"Roni Braendle's Dog Obedience",
    "wof:placetype":"venue"
},
  "geometry": {"coordinates":[-97.724968,29.346568],"type":"Point"}
}