{
  "type": "Feature",
  "properties": {
    "iso:country":"US",
    "sg:address":"140 Old Chisholm Trl",
    "sg:city":"Georgetown",
    "sg:classifiers":[
        {
            "category":"Professional",
            "subcategory":"Lawyer & Legal Services",
            "type":"Services"
        }
    ],
    "sg:phone":"+1 512 864 2442",
    "sg:postcode":"78633",
    "sg:province":"TX",
    "wof:name":"Harold Resteiner",
    "wof:placetype":"venue"
},
  "geometry": {"coordinates":[-97.71507699999999,30.716624],"type":"Point"}
}