{
  "type": "Feature",
  "properties": {
    "iso:country":"US",
    "sg:address":"500 N Lamar Blvd",
    "sg:city":"Austin",
    "sg:classifiers":[
        {
            "category":"Personal",
            "subcategory":"Beauty Salon",
            "type":"Services"
        }
    ],
    "sg:phone":"+1 512 478 7744",
    "sg:postcode":"78703",
    "sg:province":"TX",
    "sg:tags":[
        "shop"
    ],
    "sg:website":"www.jacksonruiz.com",
    "wof:name":"Jackson Ruiz Salon Inc",
    "wof:placetype":"venue"
},
  "geometry": {"coordinates":[-97.753964,30.271538],"type":"Point"}
}