{
  "type": "Feature",
  "properties": {
    "iso:country":"US",
    "sg:address":"10497 Town and Country Way",
    "sg:city":"Houston",
    "sg:classifiers":[
        {
            "category":"Health Services",
            "subcategory":"Doctor",
            "type":"Services"
        }
    ],
    "sg:phone":"+1 713 342 2100",
    "sg:postcode":"77024",
    "sg:province":"TX",
    "wof:name":"Town & Country Family Physicians",
    "wof:placetype":"venue"
},
  "geometry": {"coordinates":[-95.5557,29.781373],"type":"Point"}
}