{
  "type": "Feature",
  "properties": {
    "iso:country":"US",
    "sg:address":"402 Village Ln",
    "sg:city":"Texarkana",
    "sg:classifiers":[
        {
            "category":"Manufacturing",
            "subcategory":"Toys & Sporting Goods",
            "type":"Manufacturing & Wholesale Goods"
        }
    ],
    "sg:phone":"+1 903 832 5598",
    "sg:postcode":"75501",
    "sg:province":"TX",
    "sg:tags":[
        "mfg"
    ],
    "wof:name":"Hamps Sports Ltd",
    "wof:placetype":"venue"
},
  "geometry": {"coordinates":[-94.121567,33.427832],"type":"Point"}
}