{
  "type": "Feature",
  "properties": {
    "iso:country":"US",
    "sg:address":"205 N Lacy Dr",
    "sg:city":"Waco",
    "sg:classifiers":[
        {
            "category":"Organizations",
            "subcategory":"Religious Organization",
            "type":"Services"
        }
    ],
    "sg:phone":"+1 254 799 3864",
    "sg:postcode":"76705",
    "sg:province":"TX",
    "wof:name":"1st Apostolic Church",
    "wof:placetype":"venue"
},
  "geometry": {"coordinates":[-97.10719899999999,31.621924],"type":"Point"}
}