{
  "type": "Feature",
  "properties": {
    "iso:country":"US",
    "sg:address":"1506 San Felipe Dr",
    "sg:city":"Mission",
    "sg:classifiers":[
        {
            "category":"Real Estate",
            "subcategory":"Developer",
            "type":"Services"
        }
    ],
    "sg:phone":"+1 956 581 7957",
    "sg:postcode":"78572",
    "sg:province":"TX",
    "wof:name":"J Goodwin Lot Sales Inc",
    "wof:placetype":"venue"
},
  "geometry": {"coordinates":[-98.30465700000001,26.219767],"type":"Point"}
}