{
  "type": "Feature",
  "properties": {
    "iso:country":"US",
    "sg:address":"2211 Norfolk St Ste 980",
    "sg:city":"Houston",
    "sg:classifiers":[
        {
            "category":"Professional",
            "subcategory":"Management & Consulting",
            "type":"Services"
        }
    ],
    "sg:phone":"+1 713 529 2241",
    "sg:postcode":"77098",
    "sg:province":"TX",
    "sg:tags":[
        "consultant",
        "educational"
    ],
    "wof:name":"Wonder Space Computer & Technology Camp",
    "wof:placetype":"venue"
},
  "geometry": {"coordinates":[-95.413021,29.732469],"type":"Point"}
}