{
  "type": "Feature",
  "properties": {
    "iso:country":"US",
    "sg:address":"277 N 18th St",
    "sg:city":"Beaumont",
    "sg:classifiers":[
        {
            "category":"Professional",
            "subcategory":"Business Services",
            "type":"Services"
        }
    ],
    "sg:phone":"+1 409 833 9146",
    "sg:postcode":"77707",
    "sg:province":"TX",
    "sg:tags":[
        "appraisers-business",
        "industrial",
        "commercial",
        "appraiser"
    ],
    "wof:name":"Appraisal Services of Southeast Texas",
    "wof:placetype":"venue"
},
  "geometry": {"coordinates":[-94.13773500000001,30.083342],"type":"Point"}
}