{
  "type": "Feature",
  "properties": {
    "iso:country":"US",
    "sg:address":"6209 Comfort Dr",
    "sg:city":"Fort Worth",
    "sg:classifiers":[
        {
            "category":"Insurance",
            "subcategory":"Insurance Agent",
            "type":"Services"
        }
    ],
    "sg:phone":"+1 817 361 9272",
    "sg:postcode":"76132",
    "sg:province":"TX",
    "wof:name":"Kelly Strange Health Insurance",
    "wof:placetype":"venue"
},
  "geometry": {"coordinates":[-97.410915,32.659402],"type":"Point"}
}