{
  "type": "Feature",
  "properties": {
    "iso:country":"US",
    "sg:address":"4951 Airport Pkwy",
    "sg:city":"Addison",
    "sg:classifiers":[
        {
            "category":"Manufacturing",
            "subcategory":"Electronics",
            "type":"Manufacturing & Wholesale Goods"
        }
    ],
    "sg:phone":"+1 972 392 1148",
    "sg:postcode":"75001",
    "sg:province":"TX",
    "sg:tags":[
        "semiconductor",
        "devices"
    ],
    "wof:name":"Kokusai Semiconductor Equip",
    "wof:placetype":"venue"
},
  "geometry": {"coordinates":[-96.82815100000001,32.966107],"type":"Point"}
}