{
  "type": "Feature",
  "properties": {
    "iso:country":"US",
    "sg:address":"901 S Philadelphia St",
    "sg:city":"Amarillo",
    "sg:classifiers":[
        {
            "category":"Organizations",
            "subcategory":"Religious Organization",
            "type":"Services"
        }
    ],
    "sg:phone":"+1 806 342 9542",
    "sg:postcode":"79104",
    "sg:province":"TX",
    "wof:name":"Amarillo Spanish Svnth Day Adv",
    "wof:placetype":"venue"
},
  "geometry": {"coordinates":[-101.810727,35.200229],"type":"Point"}
}