{
  "type": "Feature",
  "properties": {
    "iso:country":"US",
    "sg:address":"5313 Cory Dr",
    "sg:city":"El Paso",
    "sg:classifiers":[
        {
            "category":"Building & Trades",
            "subcategory":"Construction",
            "type":"Services"
        }
    ],
    "sg:phone":"+1 915 585 7004",
    "sg:postcode":"79932",
    "sg:province":"TX",
    "sg:tags":[
        "industrial"
    ],
    "wof:name":"Ramon H Garcia",
    "wof:placetype":"venue"
},
  "geometry": {"coordinates":[-106.616006,31.853382],"type":"Point"}
}