{
  "type": "Feature",
  "properties": {
    "iso:country":"US",
    "sg:address":"5216 Ashbrook Rd",
    "sg:city":"Dallas",
    "sg:classifiers":[
        {
            "category":"Social Services",
            "subcategory":"Job Training",
            "type":"Services"
        }
    ],
    "sg:phone":"+1 214 275 0625",
    "sg:postcode":"75227",
    "sg:province":"TX",
    "sg:tags":[
        "seminar"
    ],
    "wof:name":"Wallace",
    "wof:placetype":"venue"
},
  "geometry": {"coordinates":[-96.70569500000001,32.788145],"type":"Point"}
}