{
  "type": "Feature",
  "properties": {
    "iso:country":"US",
    "sg:address":"109 SE 9th Ave",
    "sg:city":"Mineral Wells",
    "sg:classifiers":[
        {
            "category":"Health Services",
            "subcategory":"Clinic",
            "type":"Services"
        }
    ],
    "sg:phone":"+1 940 325 5255",
    "sg:postcode":"76067",
    "sg:province":"TX",
    "sg:tags":[
        "home"
    ],
    "wof:name":"Integracare Home Health",
    "wof:placetype":"venue"
},
  "geometry": {"coordinates":[-98.105025,32.809107],"type":"Point"}
}