{
  "type": "Feature",
  "properties": {
    "iso:country":"US",
    "sg:address":"2015 Milam St",
    "sg:city":"Houston",
    "sg:classifiers":[
        {
            "category":"Retail",
            "subcategory":"Auto Rental",
            "type":"Services"
        }
    ],
    "sg:phone":"+1 713 659 2335",
    "sg:postcode":"77002",
    "sg:province":"TX",
    "sg:tags":[
        "car"
    ],
    "wof:name":"Pv Rentals",
    "wof:placetype":"venue"
},
  "geometry": {"coordinates":[-95.372803,29.7505],"type":"Point"}
}