{
  "type": "Feature",
  "properties": {
    "iso:country":"US",
    "sg:address":"1114 Choate Cir",
    "sg:city":"Houston",
    "sg:classifiers":[
        {
            "category":"Freight",
            "type":"Transportation"
        }
    ],
    "sg:phone":"+1 713 641 2123",
    "sg:postcode":"77017",
    "sg:province":"TX",
    "sg:tags":[
        "operator",
        "trucking"
    ],
    "wof:name":"Celestial Strobe Inc",
    "wof:placetype":"venue"
},
  "geometry": {"coordinates":[-95.244283,29.690642],"type":"Point"}
}