{
  "type": "Feature",
  "properties": {
    "iso:country":"US",
    "sg:address":"603 S 4th St",
    "sg:city":"Silsbee",
    "sg:classifiers":[
        {
            "category":"Health Services",
            "subcategory":"Doctor",
            "type":"Services"
        }
    ],
    "sg:phone":"+1 409 385 7352",
    "sg:postcode":"77656",
    "sg:province":"TX",
    "sg:tags":[
        "physician",
        "surgeon"
    ],
    "wof:name":"Harrypersad Singh MD",
    "wof:placetype":"venue"
},
  "geometry": {"coordinates":[-94.17967400000001,30.343815],"type":"Point"}
}