{
  "type": "Feature",
  "properties": {
    "iso:country":"US",
    "sg:address":"1100 W 29th St",
    "sg:city":"Austin",
    "sg:classifiers":[
        {
            "category":"Manufacturing",
            "subcategory":"Printing",
            "type":"Manufacturing & Wholesale Goods"
        }
    ],
    "sg:phone":"+1 512 476 9767",
    "sg:postcode":"78703",
    "sg:province":"TX",
    "sg:tags":[
        "newspaper"
    ],
    "wof:name":"Journal Pragmatics",
    "wof:placetype":"venue"
},
  "geometry": {"coordinates":[-97.750407,30.299671],"type":"Point"}
}