{
  "type": "Feature",
  "properties": {
    "iso:country":"US",
    "sg:address":"2908 Parkhaven Dr",
    "sg:city":"Flower Mound",
    "sg:classifiers":[
        {
            "category":"Professional",
            "type":"Services"
        }
    ],
    "sg:phone":"+1 972 355 5840",
    "sg:postcode":"75022",
    "sg:province":"TX",
    "wof:name":"Storytime Artist",
    "wof:placetype":"venue"
},
  "geometry": {"coordinates":[-97.080321,33.025203],"type":"Point"}
}