{
  "type": "Feature",
  "properties": {
    "iso:country":"US",
    "sg:address":"9416 Neils Thompson Dr",
    "sg:city":"Austin",
    "sg:classifiers":[
        {
            "category":"Shopping",
            "subcategory":"Computers & Home Electronics",
            "type":"Retail Goods"
        }
    ],
    "sg:phone":"+1 512 836 8201",
    "sg:postcode":"78758",
    "sg:province":"TX",
    "sg:tags":[
        "equipment",
        "audio",
        "video"
    ],
    "wof:name":"A&B TV",
    "wof:placetype":"venue"
},
  "geometry": {"coordinates":[-97.732935,30.38284],"type":"Point"}
}