{
  "type": "Feature",
  "properties": {
    "iso:country":"US",
    "sg:address":"226 Robin St",
    "sg:city":"Deer Park",
    "sg:classifiers":[
        {
            "category":"Professional",
            "type":"Services"
        }
    ],
    "sg:phone":"+1 281 478 0384",
    "sg:postcode":"77536",
    "sg:province":"TX",
    "wof:name":"Spectratek",
    "wof:placetype":"venue"
},
  "geometry": {"coordinates":[-95.12903300000001,29.709345],"type":"Point"}
}