{
  "type": "Feature",
  "properties": {
    "iso:country":"US",
    "sg:address":"980 FM 1092",
    "sg:city":"Missouri City",
    "sg:classifiers":[
        {
            "category":"Education",
            "subcategory":"Special Training",
            "type":"Public Place"
        }
    ],
    "sg:phone":"+1 281 208 1551",
    "sg:postcode":"77459",
    "sg:province":"TX",
    "wof:name":"Ambassabor Montesseri School",
    "wof:placetype":"venue"
},
  "geometry": {"coordinates":[-95.564448,29.604488],"type":"Point"}
}