{
  "type": "Feature",
  "properties": {
    "iso:country":"US",
    "sg:address":"7601 Wilcox Dr",
    "sg:city":"El Paso",
    "sg:classifiers":[
        {
            "category":"Organizations",
            "subcategory":"Religious Organization",
            "type":"Services"
        }
    ],
    "sg:phone":"+1 915 598 6035",
    "sg:postcode":"79915",
    "sg:province":"TX",
    "sg:tags":[
        "church"
    ],
    "wof:name":"Grace Chapel",
    "wof:placetype":"venue"
},
  "geometry": {"coordinates":[-106.36022699999999,31.759843],"type":"Point"}
}