{
  "type": "Feature",
  "properties": {
    "iso:country":"US",
    "sg:address":"16603 Rose Trl",
    "sg:city":"Cypress",
    "sg:classifiers":[
        {
            "category":"Professional",
            "subcategory":"Management & Consulting",
            "type":"Services"
        }
    ],
    "sg:phone":"+1 281 368 1670",
    "sg:postcode":"77429",
    "sg:province":"TX",
    "sg:tags":[
        "business"
    ],
    "wof:name":"Ws Rawles Consultant",
    "wof:placetype":"venue"
},
  "geometry": {"coordinates":[-95.685455,30.009494],"type":"Point"}
}