{
  "type": "Feature",
  "properties": {
    "iso:country":"US",
    "sg:address":"371 Buffalo Spring Rd",
    "sg:city":"New Braunfels",
    "sg:classifiers":[
        {
            "category":"Building & Trades",
            "subcategory":"Construction",
            "type":"Services"
        }
    ],
    "sg:phone":"+1 830 905 3741",
    "sg:postcode":"78132",
    "sg:province":"TX",
    "sg:tags":[
        "excavation",
        "contractor",
        "general"
    ],
    "wof:name":"Quality Dirt Works",
    "wof:placetype":"venue"
},
  "geometry": {"coordinates":[-98.209103,29.779976],"type":"Point"}
}