{
  "type": "Feature",
  "properties": {
    "iso:country":"US",
    "sg:address":"106 Windmill Cove",
    "sg:city":"Georgetown",
    "sg:classifiers":[
        {
            "category":"Health Services",
            "subcategory":"Health Practitioner",
            "type":"Services"
        }
    ],
    "sg:phone":"+1 512 930 3729",
    "sg:postcode":"78628",
    "sg:province":"TX",
    "sg:tags":[
        "nurse",
        "registry"
    ],
    "wof:name":"Marsha L Welch",
    "wof:placetype":"venue"
},
  "geometry": {"coordinates":[-97.68592099999999,30.671773],"type":"Point"}
}