{
  "type": "Feature",
  "properties": {
    "iso:country":"US",
    "sg:address":"7924 Hull Ave",
    "sg:city":"Dallas",
    "sg:classifiers":[
        {
            "category":"Professional",
            "type":"Services"
        }
    ],
    "sg:phone":"+1 214 371 3812",
    "sg:postcode":"75216",
    "sg:province":"TX",
    "wof:name":"Ladells Arts Unlimited",
    "wof:placetype":"venue"
},
  "geometry": {"coordinates":[-96.746786,32.713567],"type":"Point"}
}