{
  "type": "Feature",
  "properties": {
    "iso:country":"US",
    "sg:address":"3911 Loop 20",
    "sg:city":"Laredo",
    "sg:classifiers":[
        {
            "category":"Restaurant",
            "type":"Food & Drink"
        }
    ],
    "sg:phone":"+1 956 796 0021",
    "sg:postcode":"78043",
    "sg:province":"TX",
    "wof:name":"Domino's Pizza",
    "wof:placetype":"venue"
},
  "geometry": {"coordinates":[-99.456963,27.491872],"type":"Point"}
}