{
  "type": "Feature",
  "properties": {
    "iso:country":"US",
    "sg:address":"2904 Flower Hill Dr",
    "sg:city":"Round Rock",
    "sg:classifiers":[
        {
            "category":"Building & Trades",
            "subcategory":"Cleaning & Sanitation",
            "type":"Services"
        }
    ],
    "sg:phone":"+1 512 244 7557",
    "sg:postcode":"78664",
    "sg:province":"TX",
    "sg:tags":[
        "window",
        "maintenance"
    ],
    "wof:name":"Sunshine Window Cleaning",
    "wof:placetype":"venue"
},
  "geometry": {"coordinates":[-97.62049399999999,30.490161],"type":"Point"}
}