{
  "type": "Feature",
  "properties": {
    "iso:country":"US",
    "sg:address":"7290 Linne Rd",
    "sg:city":"Seguin",
    "sg:classifiers":[
        {
            "category":"Wholesale",
            "subcategory":"Auto Parts",
            "type":"Manufacturing & Wholesale Goods"
        }
    ],
    "sg:phone":"+1 830 914 4552",
    "sg:postcode":"78155",
    "sg:province":"TX",
    "sg:tags":[
        "equipment",
        "station",
        "automotive"
    ],
    "wof:name":"Cameron Automotive Distr Inc",
    "wof:placetype":"venue"
},
  "geometry": {"coordinates":[-98.103694,29.4825],"type":"Point"}
}