{
  "type": "Feature",
  "properties": {
    "iso:country":"US",
    "sg:address":"408 W Santa Rosa Ave",
    "sg:city":"Edcouch",
    "sg:classifiers":[
        {
            "category":"Fast Food",
            "type":"Food & Drink"
        },
        {
            "category":"Restaurant",
            "type":"Food & Drink"
        }
    ],
    "sg:phone":"+1 956 262 9444",
    "sg:postcode":"78538",
    "sg:province":"TX",
    "sg:tags":[
        "mexican",
        "hot",
        "dog",
        "american",
        "hamburger",
        "chicken"
    ],
    "wof:name":"Leroy's Chicken & Burgers",
    "wof:placetype":"venue"
},
  "geometry": {"coordinates":[-97.96402,26.293859],"type":"Point"}
}