{
  "type": "Feature",
  "properties": {
    "iso:country":"US",
    "sg:address":"4884 Bell Springs Rd",
    "sg:city":"Dripping Springs",
    "sg:classifiers":[
        {
            "category":"Professional",
            "type":"Services"
        }
    ],
    "sg:phone":"+1 512 288 5786",
    "sg:postcode":"78620",
    "sg:province":"TX",
    "wof:name":"Objective Innov Inc",
    "wof:placetype":"venue"
},
  "geometry": {"coordinates":[-98.11886800000001,30.215831],"type":"Point"}
}