{
  "type": "Feature",
  "properties": {
    "iso:country":"US",
    "sg:address":"2620 Buell Ave",
    "sg:city":"Austin",
    "sg:classifiers":[
        {
            "category":"Shopping",
            "subcategory":"Computers & Home Electronics",
            "type":"Retail Goods"
        }
    ],
    "sg:phone":"+1 512 459 4432",
    "sg:postcode":"78757",
    "sg:province":"TX",
    "sg:tags":[
        "high",
        "fidelity",
        "stereophonic"
    ],
    "sg:website":"www.cstaustin.com",
    "wof:name":"CST Inc",
    "wof:placetype":"venue"
},
  "geometry": {"coordinates":[-97.730391,30.363748],"type":"Point"}
}