{
  "type": "Feature",
  "properties": {
    "iso:country":"US",
    "sg:address":"1830 Garden Springs Dr",
    "sg:city":"Dallas",
    "sg:classifiers":[
        {
            "category":"Building & Trades",
            "subcategory":"Construction",
            "type":"Services"
        }
    ],
    "sg:phone":"+1 972 286 1718",
    "sg:postcode":"75253",
    "sg:province":"TX",
    "sg:tags":[
        "contractor"
    ],
    "wof:name":"B & B Concrete Sawing",
    "wof:placetype":"venue"
},
  "geometry": {"coordinates":[-96.62359600000001,32.6875],"type":"Point"}
}