{
  "type": "Feature",
  "properties": {
    "iso:country":"US",
    "sg:address":"314 E Highland Mall Blvd Ste 400",
    "sg:city":"Austin",
    "sg:classifiers":[
        {
            "category":"Insurance",
            "subcategory":"Hazard Insurance",
            "type":"Services"
        }
    ],
    "sg:phone":"+1 512 246 0007",
    "sg:postcode":"78752",
    "sg:province":"TX",
    "sg:tags":[
        "commercial",
        "business"
    ],
    "wof:name":"E-Choiceinsurance.com",
    "wof:placetype":"venue"
},
  "geometry": {"coordinates":[-97.712405,30.328529],"type":"Point"}
}