{
  "type": "Feature",
  "properties": {
    "iso:country":"US",
    "sg:address":"3509 S Martin Ave",
    "sg:city":"Laredo",
    "sg:classifiers":[
        {
            "category":"Professional",
            "subcategory":"Business Services",
            "type":"Services"
        }
    ],
    "sg:phone":"+1 956 725 0232",
    "sg:postcode":"78046",
    "sg:province":"TX",
    "wof:name":"Rado Agency",
    "wof:placetype":"venue"
},
  "geometry": {"coordinates":[-99.471373,27.464461],"type":"Point"}
}