{
  "type": "Feature",
  "properties": {
    "iso:country":"US",
    "sg:address":"1706 Ave M",
    "sg:city":"Hondo",
    "sg:classifiers":[
        {
            "category":"Health Services",
            "subcategory":"Optometrist",
            "type":"Services"
        }
    ],
    "sg:phone":"+1 830 426 2027",
    "sg:postcode":"78861",
    "sg:province":"TX",
    "wof:name":"Vision Source Optical",
    "wof:placetype":"venue"
},
  "geometry": {"coordinates":[-99.14187699999999,29.349179],"type":"Point"}
}