{
  "type": "Feature",
  "properties": {
    "iso:country":"US",
    "sg:address":"2510 Paramount Blvd",
    "sg:city":"Amarillo",
    "sg:classifiers":[
        {
            "category":"Home & Garden",
            "subcategory":"Furniture",
            "type":"Retail Goods"
        }
    ],
    "sg:phone":"+1 806 351 1752",
    "sg:postcode":"79109",
    "sg:province":"TX",
    "wof:name":"Mattress Express",
    "wof:placetype":"venue"
},
  "geometry": {"coordinates":[-101.87329699999999,35.186866],"type":"Point"}
}