{
  "type": "Feature",
  "properties": {
    "iso:country":"US",
    "sg:address":"4600 Fairmont Pkwy Ste 204",
    "sg:city":"Pasadena",
    "sg:classifiers":[
        {
            "category":"Communications",
            "type":"Services"
        }
    ],
    "sg:phone":"+1 281 991 1361",
    "sg:postcode":"77504",
    "sg:province":"TX",
    "sg:tags":[
        "web",
        "design"
    ],
    "wof:name":"Ellis Eric J",
    "wof:placetype":"venue"
},
  "geometry": {"coordinates":[-95.173519,29.649398],"type":"Point"}
}