{
  "type": "Feature",
  "properties": {
    "iso:country":"US",
    "sg:address":"14207 State Hwy 249",
    "sg:city":"Houston",
    "sg:classifiers":[
        {
            "category":"Organizations",
            "subcategory":"Religious Organization",
            "type":"Services"
        }
    ],
    "sg:phone":"+1 281 880 8300",
    "sg:postcode":"77086",
    "sg:province":"TX",
    "sg:tags":[
        "church"
    ],
    "wof:name":"New Frontier Fellowship Church",
    "wof:placetype":"venue"
},
  "geometry": {"coordinates":[-95.498116,29.922993],"type":"Point"}
}