{
  "type": "Feature",
  "properties": {
    "iso:country":"US",
    "sg:address":"7419 FM 1488",
    "sg:city":"Magnolia",
    "sg:classifiers":[
        {
            "category":"Building & Trades",
            "subcategory":"Construction",
            "type":"Services"
        }
    ],
    "sg:phone":"+1 281 356 3020",
    "sg:postcode":"77354",
    "sg:province":"TX",
    "sg:tags":[
        "contractor"
    ],
    "wof:name":"Rembrandt Pools",
    "wof:placetype":"venue"
},
  "geometry": {"coordinates":[-95.506697,30.230254],"type":"Point"}
}