{
  "type": "Feature",
  "properties": {
    "iso:country":"US",
    "sg:address":"14425 Fm 1826",
    "sg:city":"Austin",
    "sg:classifiers":[
        {
            "category":"Shopping",
            "subcategory":"Pets & Pet Supplies",
            "type":"Retail Goods"
        },
        {
            "category":"Retail",
            "subcategory":"Pet Boarding",
            "type":"Services"
        },
        {
            "category":"Retail",
            "subcategory":"Animal Services",
            "type":"Services"
        }
    ],
    "sg:phone":"+1 512 301 2279",
    "sg:postcode":"78737",
    "sg:province":"TX",
    "sg:tags":[
        "sitting",
        "dog",
        "cat",
        "furnishing",
        "exercising",
        "store",
        "kennel"
    ],
    "wof:name":"Austin Pet Ranch",
    "wof:placetype":"venue"
},
  "geometry": {"coordinates":[-97.952423,30.162076],"type":"Point"}
}