{
  "type": "Feature",
  "properties": {
    "iso:country":"US",
    "sg:address":"409 W Harwood Rd",
    "sg:city":"Hurst",
    "sg:classifiers":[
        {
            "category":"Real Estate",
            "subcategory":"Real Estate Services",
            "type":"Services"
        }
    ],
    "sg:phone":"+1 817 577 9300",
    "sg:postcode":"76054",
    "sg:province":"TX",
    "sg:tags":[
        "abstract",
        "title"
    ],
    "wof:name":"Title Chase Hurst Pllc",
    "wof:placetype":"venue"
},
  "geometry": {"coordinates":[-97.177643,32.847544],"type":"Point"}
}