{
  "type": "Feature",
  "properties": {
    "iso:country":"US",
    "sg:address":"4615 Belle Park Dr",
    "sg:city":"Houston",
    "sg:phone":"+1 281 933 8118",
    "sg:postcode":"77072",
    "sg:province":"TX",
    "wof:name":"Vietnamese Culture & Science Association",
    "wof:placetype":"venue"
},
  "geometry": {"coordinates":[-95.583167,29.706182],"type":"Point"}
}