{
  "type": "Feature",
  "properties": {
    "iso:country":"US",
    "sg:address":"400 S Buffalo St",
    "sg:city":"Canton",
    "sg:classifiers":[
        {
            "category":"Professional",
            "type":"Services"
        }
    ],
    "sg:phone":"+1 903 567 1500",
    "sg:postcode":"75103",
    "sg:province":"TX",
    "sg:tags":[
        "government"
    ],
    "wof:name":"City of Canton Municipal Judge",
    "wof:placetype":"venue"
},
  "geometry": {"coordinates":[-95.863838,32.55479],"type":"Point"}
}