{
  "type": "Feature",
  "properties": {
    "iso:country":"US",
    "sg:address":"5415 8th St",
    "sg:city":"Lubbock",
    "sg:classifiers":[
        {
            "category":"Building & Trades",
            "subcategory":"Plumbing",
            "type":"Services"
        }
    ],
    "sg:phone":"+1 806 795 1524",
    "sg:postcode":"79416",
    "sg:province":"TX",
    "sg:tags":[
        "plumbing",
        "contractor"
    ],
    "wof:name":"Kevin Batten Plumbing",
    "wof:placetype":"venue"
},
  "geometry": {"coordinates":[-101.929275,33.589132],"type":"Point"}
}