{
  "type": "Feature",
  "properties": {
    "iso:country":"US",
    "sg:address":"145 W Bethesda Rd",
    "sg:city":"Burleson",
    "sg:classifiers":[
        {
            "category":"Communications",
            "type":"Services"
        }
    ],
    "sg:phone":"+1 817 426 6513",
    "sg:postcode":"76028",
    "sg:province":"TX",
    "wof:name":"Spectrasite Communications",
    "wof:placetype":"venue"
},
  "geometry": {"coordinates":[-97.28171500000001,32.485004],"type":"Point"}
}