{
  "type": "Feature",
  "properties": {
    "iso:country":"US",
    "sg:address":"3512 E Walnut St",
    "sg:city":"Pearland",
    "sg:classifiers":[
        {
            "category":"Wholesale",
            "subcategory":"Electrical",
            "type":"Manufacturing & Wholesale Goods"
        }
    ],
    "sg:phone":"+1 281 997 8095",
    "sg:postcode":"77581",
    "sg:province":"TX",
    "sg:tags":[
        "supply"
    ],
    "wof:name":"Consolidated Electrical Distrs",
    "wof:placetype":"venue"
},
  "geometry": {"coordinates":[-95.279482,29.559973],"type":"Point"}
}