{
  "type": "Feature",
  "properties": {
    "iso:country":"US",
    "sg:address":"4031 Towne Crossing Blvd",
    "sg:city":"Mesquite",
    "sg:classifiers":[
        {
            "category":"Shopping",
            "subcategory":"Bicycles & Sporting Goods",
            "type":"Retail Goods"
        }
    ],
    "sg:phone":"+1 972 517 6684",
    "sg:postcode":"75150",
    "sg:province":"TX",
    "wof:name":"Stylex Scuba Inc",
    "wof:placetype":"venue"
},
  "geometry": {"coordinates":[-96.632075,32.818815],"type":"Point"}
}