{
  "type": "Feature",
  "properties": {
    "iso:country":"US",
    "sg:address":"15 S Hornbeam Pl",
    "sg:city":"Spring",
    "sg:classifiers":[
        {
            "category":"Professional",
            "subcategory":"Business Services",
            "type":"Services"
        }
    ],
    "sg:phone":"+1 281 364 1162",
    "sg:postcode":"77380",
    "sg:province":"TX",
    "wof:name":"USA General Technologies LLC",
    "wof:placetype":"venue"
},
  "geometry": {"coordinates":[-95.459453,30.135853],"type":"Point"}
}