{
  "type": "Feature",
  "properties": {
    "iso:country":"US",
    "sg:address":"112 Crumpton Dr",
    "sg:city":"Texarkana",
    "sg:classifiers":[
        {
            "category":"Retail",
            "subcategory":"Portrait Studio",
            "type":"Services"
        },
        {
            "category":"Professional",
            "subcategory":"Art Services",
            "type":"Services"
        }
    ],
    "sg:phone":"+1 903 831 5676",
    "sg:postcode":"75503",
    "sg:province":"TX",
    "sg:tags":[
        "rental",
        "photographers-portrait",
        "photographic",
        "darkroom"
    ],
    "wof:name":"Bob Joyner Photography",
    "wof:placetype":"venue"
},
  "geometry": {"coordinates":[-94.126356,33.46488],"type":"Point"}
}