{
  "type": "Feature",
  "properties": {
    "iso:country":"US",
    "sg:address":"3722 NE 28th St",
    "sg:city":"Fort Worth",
    "sg:classifiers":[
        {
            "category":"Building & Trades",
            "subcategory":"Construction",
            "type":"Services"
        }
    ],
    "sg:phone":"+1 817 834 4770",
    "sg:postcode":"76111",
    "sg:province":"TX",
    "sg:tags":[
        "roofing",
        "contractor"
    ],
    "wof:name":"Jose Franco Roofing",
    "wof:placetype":"venue"
},
  "geometry": {"coordinates":[-97.297225,32.795045],"type":"Point"}
}