{
  "type": "Feature",
  "properties": {
    "iso:country":"US",
    "sg:address":"201 Melicent St",
    "sg:city":"El Paso",
    "sg:classifiers":[
        {
            "category":"Professional",
            "type":"Services"
        }
    ],
    "sg:phone":"+1 915 842 8806",
    "sg:postcode":"79912",
    "sg:province":"TX",
    "sg:tags":[
        "establishment"
    ],
    "wof:name":"Sophisticated Or Simple",
    "wof:placetype":"venue"
},
  "geometry": {"coordinates":[-106.550054,31.839824],"type":"Point"}
}