{
  "type": "Feature",
  "properties": {
    "iso:country":"US",
    "sg:address":"225 Rhine Rd",
    "sg:city":"New Braunfels",
    "sg:classifiers":[
        {
            "category":"Building & Trades",
            "subcategory":"Plumbing",
            "type":"Services"
        }
    ],
    "sg:phone":"+1 830 629 3990",
    "sg:postcode":"78130",
    "sg:province":"TX",
    "sg:tags":[
        "contractor"
    ],
    "wof:name":"Fugetts Red Plumbing Co",
    "wof:placetype":"venue"
},
  "geometry": {"coordinates":[-98.097369,29.710998],"type":"Point"}
}