{
  "type": "Feature",
  "properties": {
    "iso:country":"US",
    "sg:address":"9726 Goldenglade Dr",
    "sg:city":"Houston",
    "sg:classifiers":[
        {
            "category":"Personal",
            "type":"Services"
        }
    ],
    "sg:phone":"+1 281 894 5310",
    "sg:postcode":"77064",
    "sg:province":"TX",
    "sg:tags":[
        "car",
        "loading",
        "unloading"
    ],
    "wof:name":"Accurate Transport Inc",
    "wof:placetype":"venue"
},
  "geometry": {"coordinates":[-95.55868599999999,29.911309],"type":"Point"}
}