{
  "type": "Feature",
  "properties": {
    "iso:country":"US",
    "sg:address":"200 S 25 Mile Ave",
    "sg:city":"Hereford",
    "sg:classifiers":[
        {
            "category":"Wholesale",
            "subcategory":"Farm Supplies",
            "type":"Manufacturing & Wholesale Goods"
        }
    ],
    "sg:phone":"+1 806 363 1343",
    "sg:postcode":"79045",
    "sg:province":"TX",
    "sg:tags":[
        "auction",
        "livestock",
        "market"
    ],
    "wof:name":"Horsequest Satellite Auction",
    "wof:placetype":"venue"
},
  "geometry": {"coordinates":[-102.405759,34.812535],"type":"Point"}
}