{
  "type": "Feature",
  "properties": {
    "iso:country":"US",
    "sg:address":"15 Cruz Trevino",
    "sg:city":"Roma",
    "sg:classifiers":[
        {
            "category":"Professional",
            "subcategory":"Detective & Security Services",
            "type":"Services"
        }
    ],
    "sg:phone":"+1 956 849 2180",
    "sg:postcode":"78584",
    "sg:province":"TX",
    "sg:tags":[
        "system"
    ],
    "wof:name":"Herby Systron",
    "wof:placetype":"venue"
},
  "geometry": {"coordinates":[-98.995892,26.402062],"type":"Point"}
}