{
  "type": "Feature",
  "properties": {
    "iso:country":"US",
    "sg:address":"9397 Richmond Ave",
    "sg:city":"Houston",
    "sg:classifiers":[
        {
            "category":"Professional",
            "subcategory":"Employment Agencies",
            "type":"Services"
        }
    ],
    "sg:phone":"+1 713 785 6111",
    "sg:postcode":"77063",
    "sg:province":"TX",
    "sg:website":"www.laborready.com",
    "wof:name":"Labor Ready",
    "wof:placetype":"venue"
},
  "geometry": {"coordinates":[-95.53130299999999,29.7288],"type":"Point"}
}