{
  "type": "Feature",
  "properties": {
    "iso:country":"US",
    "sg:address":"1636 Osage Ave",
    "sg:city":"Wichita Falls",
    "sg:classifiers":[
        {
            "category":"Professional",
            "subcategory":"Employment Agencies",
            "type":"Services"
        }
    ],
    "sg:phone":"+1 940 761 4352",
    "sg:postcode":"76301",
    "sg:province":"TX",
    "sg:tags":[
        "help",
        "supply"
    ],
    "wof:name":"Mark Washington",
    "wof:placetype":"venue"
},
  "geometry": {"coordinates":[-98.461713,33.896007],"type":"Point"}
}