{
  "type": "Feature",
  "properties": {
    "iso:country":"US",
    "sg:address":"2001 Holcombe Blvd Ofc",
    "sg:city":"Houston",
    "sg:classifiers":[
        {
            "category":"Retail",
            "subcategory":"Laundry & Dry Cleaning",
            "type":"Services"
        }
    ],
    "sg:phone":"+1 713 797 0454",
    "sg:postcode":"77030",
    "sg:province":"TX",
    "wof:name":"Highrise Cleaners",
    "wof:placetype":"venue"
},
  "geometry": {"coordinates":[-95.391701,29.7059],"type":"Point"}
}