{
  "type": "Feature",
  "properties": {
    "iso:country":"US",
    "sg:address":"1307 19th St",
    "sg:city":"Hondo",
    "sg:classifiers":[
        {
            "category":"Food & Beverages",
            "subcategory":"Liquor & Beverages",
            "type":"Retail Goods"
        }
    ],
    "sg:phone":"+1 830 426 3942",
    "sg:postcode":"78861",
    "sg:province":"TX",
    "wof:name":"Moreno's Liquor",
    "wof:placetype":"venue"
},
  "geometry": {"coordinates":[-99.142867,29.347411],"type":"Point"}
}