{
  "type": "Feature",
  "properties": {
    "iso:country":"US",
    "sg:address":"4502 Valerie St",
    "sg:city":"Bellaire",
    "sg:classifiers":[
        {
            "category":"Farming",
            "subcategory":"Farm",
            "type":"Manufacturing & Wholesale Goods"
        }
    ],
    "sg:phone":"+1 713 664 0626",
    "sg:postcode":"77401",
    "sg:province":"TX",
    "sg:tags":[
        "crop",
        "general"
    ],
    "wof:name":"Buerkle Four Farms LLC",
    "wof:placetype":"venue"
},
  "geometry": {"coordinates":[-95.453114,29.694127],"type":"Point"}
}