{
  "type": "Feature",
  "properties": {
    "iso:country":"US",
    "sg:address":"17209 Ravenwood Dr",
    "sg:city":"Flint",
    "sg:classifiers":[
        {
            "category":"Travel",
            "subcategory":"Hotels & Motels",
            "type":"Entertainment"
        }
    ],
    "sg:phone":"+1 903 825 3612",
    "sg:postcode":"75762",
    "sg:province":"TX",
    "sg:tags":[
        "operation"
    ],
    "wof:name":"Resort Water Service",
    "wof:placetype":"venue"
},
  "geometry": {"coordinates":[-95.458945,32.154748],"type":"Point"}
}