{
  "type": "Feature",
  "properties": {
    "iso:country":"US",
    "sg:address":"2911 Turtle Creek Blvd",
    "sg:city":"Dallas",
    "sg:classifiers":[
        {
            "category":"Professional",
            "type":"Services"
        }
    ],
    "sg:phone":"+1 214 528 8585",
    "sg:postcode":"75219",
    "sg:province":"TX",
    "wof:name":"Merx Inc",
    "wof:placetype":"venue"
},
  "geometry": {"coordinates":[-96.805598,32.803778],"type":"Point"}
}