{
  "type": "Feature",
  "properties": {
    "iso:country":"US",
    "sg:address":"713 Woodland Hills Dr",
    "sg:city":"Tyler",
    "sg:classifiers":[
        {
            "category":"Professional",
            "type":"Services"
        }
    ],
    "sg:phone":"+1 903 581 7225",
    "sg:postcode":"75701",
    "sg:province":"TX",
    "wof:name":"Crim Family LP",
    "wof:placetype":"venue"
},
  "geometry": {"coordinates":[-95.31020100000001,32.308043],"type":"Point"}
}