{
  "type": "Feature",
  "properties": {
    "iso:country":"US",
    "sg:address":"200 N 12th St",
    "sg:city":"Corsicana",
    "sg:classifiers":[
        {
            "category":"Government",
            "subcategory":"Office",
            "type":"Public Place"
        }
    ],
    "sg:phone":"+1 903 654 4889",
    "sg:postcode":"75110",
    "sg:province":"TX",
    "sg:tags":[
        "city",
        "program"
    ],
    "wof:name":"Corsicana Environmental Svc",
    "wof:placetype":"venue"
},
  "geometry": {"coordinates":[-96.467112,32.094285],"type":"Point"}
}