{
  "type": "Feature",
  "properties": {
    "iso:country":"US",
    "sg:address":"66 Pascal Ln",
    "sg:city":"Austin",
    "sg:classifiers":[
        {
            "category":"Professional",
            "subcategory":"Management & Consulting",
            "type":"Services"
        }
    ],
    "sg:phone":"+1 512 328 9647",
    "sg:postcode":"78746",
    "sg:province":"TX",
    "sg:tags":[
        "consultant",
        "lighting"
    ],
    "wof:name":"Hunter Ring DESIGN-Hrd",
    "wof:placetype":"venue"
},
  "geometry": {"coordinates":[-97.82561099999999,30.32566],"type":"Point"}
}