{
  "type": "Feature",
  "properties": {
    "iso:country":"US",
    "sg:address":"8924 Lake June Rd",
    "sg:city":"Dallas",
    "sg:classifiers":[
        {
            "category":"Shopping",
            "subcategory":"Clothing, Apparel, & Fashions",
            "type":"Retail Goods"
        }
    ],
    "sg:phone":"+1 214 309 1130",
    "sg:postcode":"75217",
    "sg:province":"TX",
    "wof:name":"Let There Be Light",
    "wof:placetype":"venue"
},
  "geometry": {"coordinates":[-96.666855,32.733977],"type":"Point"}
}