{
  "type": "Feature",
  "properties": {
    "iso:country":"US",
    "sg:address":"8102 Nottaway Cv",
    "sg:city":"Austin",
    "sg:classifiers":[
        {
            "category":"Health Services",
            "subcategory":"Medical Lab",
            "type":"Services"
        }
    ],
    "sg:phone":"+1 512 444 9346",
    "sg:postcode":"78745",
    "sg:province":"TX",
    "sg:tags":[
        "examination",
        "insurance"
    ],
    "wof:name":"Exam One",
    "wof:placetype":"venue"
},
  "geometry": {"coordinates":[-97.831292,30.199062],"type":"Point"}
}