{
  "type": "Feature",
  "properties": {
    "iso:country":"US",
    "sg:address":"121 Shavano Dr",
    "sg:city":"Shavano Park",
    "sg:classifiers":[
        {
            "category":"Shopping",
            "type":"Retail Goods"
        }
    ],
    "sg:phone":"+1 210 408 0989",
    "sg:postcode":"78231",
    "sg:province":"TX",
    "sg:tags":[
        "cosmetic",
        "merchandise",
        "perfume"
    ],
    "wof:name":"Kathleen Peyton",
    "wof:placetype":"venue"
},
  "geometry": {"coordinates":[-98.553605,29.593974],"type":"Point"}
}