{
  "type": "Feature",
  "properties": {
    "iso:country":"US",
    "sg:address":"2648 Fm 407 E # 105",
    "sg:city":"Argyle",
    "sg:classifiers":[
        {
            "category":"Personal",
            "subcategory":"Beauty Salon",
            "type":"Services"
        }
    ],
    "sg:phone":"+1 940 241 2345",
    "sg:postcode":"76226",
    "sg:province":"TX",
    "wof:name":"Shanna Ashley's Salon",
    "wof:placetype":"venue"
},
  "geometry": {"coordinates":[-97.131191,33.091759],"type":"Point"}
}