{
  "type": "Feature",
  "properties": {
    "iso:country":"US",
    "sg:address":"101 E Wallace St",
    "sg:city":"San Saba",
    "sg:classifiers":[
        {
            "category":"Real Estate",
            "subcategory":"Real Estate Agent",
            "type":"Services"
        }
    ],
    "sg:phone":"+1 325 372 6344",
    "sg:postcode":"76877",
    "sg:province":"TX",
    "wof:name":"Ashley Connell",
    "wof:placetype":"venue"
},
  "geometry": {"coordinates":[-98.720084,31.195781],"type":"Point"}
}