{
  "type": "Feature",
  "properties": {
    "iso:country":"US",
    "sg:address":"4601 Old Shepard Pl, Ste 106",
    "sg:city":"Plano",
    "sg:classifiers":[
        {
            "category":"Banks & Credit Unions",
            "subcategory":"Investment Brokerage",
            "type":"Services"
        },
        {
            "category":"Banks & Credit Unions",
            "subcategory":"Financial Services",
            "type":"Services"
        }
    ],
    "sg:phone":"+1 469 361 4017",
    "sg:postcode":"75093",
    "sg:province":"TX",
    "sg:tags":[
        "investing",
        "advising"
    ],
    "sg:website":"www.ameripriseadvisors.com/sean....",
    "wof:name":"Sean Brown - Ameriprise Financial Advisor",
    "wof:placetype":"venue"
},
  "geometry": {"coordinates":[-96.788138,33.022208],"type":"Point"}
}