{
  "type": "Feature",
  "properties": {
    "iso:country":"US",
    "sg:address":"522 Lindale St",
    "sg:city":"Houston",
    "sg:classifiers":[
        {
            "category":"Place Of Worship",
            "subcategory":"Church",
            "type":"Public Place"
        },
        {
            "category":"Place Of Worship",
            "type":"Public Place"
        },
        {
            "category":"Education",
            "subcategory":"School",
            "type":"Public Place"
        }
    ],
    "sg:phone":"+1 713 695 2933",
    "sg:postcode":"77022",
    "sg:province":"TX",
    "sg:tags":[
        "lutheran",
        "churches-lutheran-evangelical",
        "private",
        "k-",
        "interest",
        "america",
        "religious",
        "churches-lutheran"
    ],
    "wof:name":"Bethany Lutheran Church",
    "wof:placetype":"venue"
},
  "geometry": {"coordinates":[-95.36415700000001,29.818009],"type":"Point"}
}