{
  "type": "Feature",
  "properties": {
    "iso:country":"US",
    "sg:address":"609 S Grove St",
    "sg:city":"Marshall",
    "sg:classifiers":[
        {
            "category":"Social Services",
            "type":"Services"
        }
    ],
    "sg:phone":"+1 903 935 3602",
    "sg:postcode":"75670",
    "sg:province":"TX",
    "sg:tags":[
        "organization",
        "welfare"
    ],
    "wof:name":"Red Cross Office",
    "wof:placetype":"venue"
},
  "geometry": {"coordinates":[-94.371809,32.540198],"type":"Point"}
}