{
  "type": "Feature",
  "properties": {
    "iso:country":"US",
    "sg:address":"22995 Maple St",
    "sg:city":"Porter",
    "sg:classifiers":[
        {
            "category":"Building & Trades",
            "subcategory":"Construction",
            "type":"Services"
        }
    ],
    "sg:phone":"+1 281 354 3969",
    "sg:postcode":"77365",
    "sg:province":"TX",
    "sg:tags":[
        "residential"
    ],
    "wof:name":"Jadeco Enterprises",
    "wof:placetype":"venue"
},
  "geometry": {"coordinates":[-95.218979,30.084079],"type":"Point"}
}