{
  "type": "Feature",
  "properties": {
    "iso:country":"US",
    "sg:address":"3000 S Padre Island Dr",
    "sg:city":"Corpus Christi",
    "sg:classifiers":[
        {
            "category":"Autos & Motor Vehicles",
            "subcategory":"Automobile Sales",
            "type":"Retail Goods"
        }
    ],
    "sg:phone":"+1 361 654 1955",
    "sg:postcode":"78415",
    "sg:province":"TX",
    "sg:tags":[
        "car",
        "dealer"
    ],
    "wof:name":"Ed Hicks Nissan",
    "wof:placetype":"venue"
},
  "geometry": {"coordinates":[-97.42016599999999,27.732405],"type":"Point"}
}