{
  "type": "Feature",
  "properties": {
    "iso:country":"US",
    "sg:address":"2114 FM 1960 E",
    "sg:city":"Houston",
    "sg:classifiers":[
        {
            "category":"Professional",
            "subcategory":"Advertising",
            "type":"Services"
        }
    ],
    "sg:phone":"+1 281 443 8458",
    "sg:postcode":"77073",
    "sg:province":"TX",
    "wof:name":"BIDMYFLOOR.COM",
    "wof:placetype":"venue"
},
  "geometry": {"coordinates":[-95.395273,30.02538],"type":"Point"}
}