{
  "type": "Feature",
  "properties": {
    "iso:country":"US",
    "sg:address":"1200 Wade Dr",
    "sg:city":"Bedford",
    "sg:classifiers":[
        {
            "category":"Building & Trades",
            "subcategory":"Construction",
            "type":"Services"
        }
    ],
    "sg:phone":"+1 817 268 0190",
    "sg:postcode":"76022",
    "sg:province":"TX",
    "sg:tags":[
        "house"
    ],
    "wof:name":"Outdoor Specialties",
    "wof:placetype":"venue"
},
  "geometry": {"coordinates":[-97.154449,32.83117],"type":"Point"}
}