{
  "type": "Feature",
  "properties": {
    "iso:country":"US",
    "sg:address":"10935 Doud St",
    "sg:city":"Houston",
    "sg:classifiers":[
        {
            "category":"Shopping",
            "subcategory":"Gifts & Souvenirs",
            "type":"Retail Goods"
        }
    ],
    "sg:phone":"+1 713 723 5062",
    "sg:postcode":"77035",
    "sg:province":"TX",
    "wof:name":"Texas Gifts Unlimited",
    "wof:placetype":"venue"
},
  "geometry": {"coordinates":[-95.46570199999999,29.662142],"type":"Point"}
}