{
  "type": "Feature",
  "properties": {
    "iso:country":"US",
    "sg:address":"719 Ryan Plaza Dr",
    "sg:city":"Arlington",
    "sg:classifiers":[
        {
            "category":"Social Services",
            "type":"Services"
        }
    ],
    "sg:phone":"+1 817 459 8488",
    "sg:postcode":"76011",
    "sg:province":"TX",
    "sg:tags":[
        "counseling"
    ],
    "wof:name":"Shepherd's Call",
    "wof:placetype":"venue"
},
  "geometry": {"coordinates":[-97.09799,32.765574],"type":"Point"}
}