{
  "type": "Feature",
  "properties": {
    "iso:country":"US",
    "sg:address":"6911 Ten Oaks Cir",
    "sg:city":"Austin",
    "sg:classifiers":[
        {
            "category":"Food & Beverages",
            "subcategory":"Groceries & Convenience Stores",
            "type":"Retail Goods"
        }
    ],
    "sg:phone":"+1 512 445 4686",
    "sg:postcode":"78744",
    "sg:province":"TX",
    "sg:tags":[
        "notion"
    ],
    "wof:name":"Silver Thread",
    "wof:placetype":"venue"
},
  "geometry": {"coordinates":[-97.75258599999999,30.177005],"type":"Point"}
}