{
  "type": "Feature",
  "properties": {
    "iso:country":"US",
    "sg:address":"15812 Champion Forest Dr",
    "sg:city":"Spring",
    "sg:classifiers":[
        {
            "category":"Retail",
            "subcategory":"Veterinary Services",
            "type":"Services"
        }
    ],
    "sg:phone":"+1 281 376 2273",
    "sg:postcode":"77379",
    "sg:province":"TX",
    "sg:tags":[
        "hospital",
        "animal"
    ],
    "wof:name":"Champion Wood Animal Hospital",
    "wof:placetype":"venue"
},
  "geometry": {"coordinates":[-95.533067,30.002],"type":"Point"}
}