{
  "type": "Feature",
  "properties": {
    "iso:country":"US",
    "sg:address":"9218 Converse Business Ln",
    "sg:city":"Converse",
    "sg:classifiers":[
        {
            "category":"Manufacturing",
            "subcategory":"Buildings",
            "type":"Manufacturing & Wholesale Goods"
        },
        {
            "category":"Building & Trades",
            "subcategory":"Construction",
            "type":"Services"
        }
    ],
    "sg:phone":"+1 210 566 5668",
    "sg:postcode":"78109",
    "sg:province":"TX",
    "sg:tags":[
        "house",
        "mover",
        "demolition",
        "raising",
        "contractor"
    ],
    "wof:name":"1st Choice House Leveling",
    "wof:placetype":"venue"
},
  "geometry": {"coordinates":[-98.307957,29.511552],"type":"Point"}
}