{
  "type": "Feature",
  "properties": {
    "iso:country":"US",
    "sg:address":"11200 Lakeline Mall Dr",
    "sg:city":"Cedar Park",
    "sg:classifiers":[
        {
            "category":"Ice Cream",
            "type":"Food & Drink"
        }
    ],
    "sg:menulink":"http://www.allmenus.com/tx/liberty-hill-cedar-park/226807-dippin-dots/menu/",
    "sg:phone":"+1 512 401 0087",
    "sg:postcode":"78613",
    "sg:province":"TX",
    "sg:tags":[
        "american"
    ],
    "wof:name":"Dippin' Dots",
    "wof:placetype":"venue"
},
  "geometry": {"coordinates":[-97.806318,30.470546],"type":"Point"}
}