{
  "type": "Feature",
  "properties": {
    "iso:country":"US",
    "sg:address":"10610 Sagepark Ln",
    "sg:city":"Houston",
    "sg:classifiers":[
        {
            "category":"Professional",
            "subcategory":"Business Services",
            "type":"Services"
        }
    ],
    "sg:phone":"+1 281 481 8649",
    "sg:postcode":"77089",
    "sg:province":"TX",
    "wof:name":"Qualitel",
    "wof:placetype":"venue"
},
  "geometry": {"coordinates":[-95.23178299999999,29.597624],"type":"Point"}
}