{
  "type": "Feature",
  "properties": {
    "iso:country":"US",
    "sg:address":"109 S Oklahoma St",
    "sg:city":"Celina",
    "sg:classifiers":[
        {
            "category":"Retail",
            "subcategory":"Funeral Services",
            "type":"Services"
        }
    ],
    "sg:phone":"+1 972 382 2311",
    "sg:postcode":"75009",
    "sg:province":"TX",
    "sg:tags":[
        "cemetery"
    ],
    "sg:website":"www.tjmfuneral.com",
    "wof:name":"Turrentine-Jackson-Morrow",
    "wof:placetype":"venue"
},
  "geometry": {"coordinates":[-96.783096,33.323399],"type":"Point"}
}