{
  "type": "Feature",
  "properties": {
    "iso:country":"US",
    "sg:address":"405 Osage St",
    "sg:city":"Refugio",
    "sg:classifiers":[
        {
            "category":"Real Estate",
            "subcategory":"Real Estate Operator",
            "type":"Services"
        }
    ],
    "sg:phone":"+1 361 526 5933",
    "sg:postcode":"78377",
    "sg:province":"TX",
    "sg:tags":[
        "building",
        "apartment"
    ],
    "wof:name":"Refugio Apartments",
    "wof:placetype":"venue"
},
  "geometry": {"coordinates":[-97.27325399999999,28.301247],"type":"Point"}
}