{
  "type": "Feature",
  "properties": {
    "iso:country":"US",
    "sg:address":"5645 Tiger Trl",
    "sg:city":"Fort Worth",
    "sg:classifiers":[
        {
            "category":"Communications",
            "subcategory":"Film & Video Production",
            "type":"Services"
        }
    ],
    "sg:phone":"+1 817 249 1484",
    "sg:postcode":"76126",
    "sg:province":"TX",
    "sg:tags":[
        "motion"
    ],
    "wof:name":"Merry Heart Productions",
    "wof:placetype":"venue"
},
  "geometry": {"coordinates":[-97.49243,32.632076],"type":"Point"}
}