{
  "type": "Feature",
  "properties": {
    "iso:country":"US",
    "sg:address":"108 Commercial Ave",
    "sg:city":"San Antonio",
    "sg:classifiers":[
        {
            "category":"Wholesale",
            "subcategory":"Office Equipment",
            "type":"Manufacturing & Wholesale Goods"
        }
    ],
    "sg:phone":"+1 972 721 1959",
    "sg:postcode":"78211",
    "sg:province":"TX",
    "sg:tags":[
        "machine",
        "business"
    ],
    "wof:name":"B & B Technical Services Co",
    "wof:placetype":"venue"
},
  "geometry": {"coordinates":[-98.516837,29.380381],"type":"Point"}
}