{
  "type": "Feature",
  "properties": {
    "iso:country":"US",
    "sg:address":"4351 Booth Calloway Rd",
    "sg:city":"Fort Worth",
    "sg:classifiers":[
        {
            "category":"Health Services",
            "subcategory":"Doctor",
            "type":"Services"
        }
    ],
    "sg:phone":"+1 817 284 4994",
    "sg:postcode":"76118",
    "sg:province":"TX",
    "sg:tags":[
        "medical"
    ],
    "wof:name":"Mid Cities Oncology",
    "wof:placetype":"venue"
},
  "geometry": {"coordinates":[-97.212203,32.829889],"type":"Point"}
}