{
  "type": "Feature",
  "properties": {
    "iso:country":"US",
    "sg:address":"1609 US Hwy 380",
    "sg:city":"Graham",
    "sg:classifiers":[
        {
            "category":"Autos & Motor Vehicles",
            "subcategory":"Automobile Sales",
            "type":"Retail Goods"
        }
    ],
    "sg:phone":"+1 940 549 2020",
    "sg:postcode":"76450",
    "sg:province":"TX",
    "sg:tags":[
        "car",
        "dealer"
    ],
    "wof:name":"Don Helm Chevrolet Chrysler",
    "wof:placetype":"venue"
},
  "geometry": {"coordinates":[-98.56558800000001,33.11744],"type":"Point"}
}