{
  "type": "Feature",
  "properties": {
    "iso:country":"US",
    "sg:address":"118 E Brazos St",
    "sg:city":"Palestine",
    "sg:classifiers":[
        {
            "category":"Health Services",
            "subcategory":"Doctor",
            "type":"Services"
        }
    ],
    "sg:phone":"+1 903 729 5191",
    "sg:postcode":"75801",
    "sg:province":"TX",
    "sg:tags":[
        "physician",
        "surgeon"
    ],
    "wof:name":"Robert J Pate MD",
    "wof:placetype":"venue"
},
  "geometry": {"coordinates":[-95.62835800000001,31.753458],"type":"Point"}
}