{
  "type": "Feature",
  "properties": {
    "iso:country":"US",
    "sg:address":"809 Pasadena Fwy",
    "sg:city":"Pasadena",
    "sg:classifiers":[
        {
            "category":"Retail",
            "subcategory":"Repair Shop",
            "type":"Services"
        }
    ],
    "sg:phone":"+1 713 472 0606",
    "sg:postcode":"77506",
    "sg:province":"TX",
    "sg:tags":[
        "welding"
    ],
    "sg:website":"www.3jryan.com",
    "wof:name":"3-J Ryan Inc",
    "wof:placetype":"venue"
},
  "geometry": {"coordinates":[-95.219522,29.710272],"type":"Point"}
}