{
  "type": "Feature",
  "properties": {
    "iso:country":"US",
    "sg:address":"4201 S Congress Ave #106",
    "sg:city":"Austin",
    "sg:classifiers":[
        {
            "category":"Restaurant",
            "type":"Food & Drink"
        }
    ],
    "sg:phone":"+1 512 326 9788",
    "sg:postcode":"78745",
    "sg:province":"TX",
    "sg:tags":[
        "mexican"
    ],
    "wof:name":"Garibaldi's Mexican Food",
    "wof:placetype":"venue"
},
  "geometry": {"coordinates":[-97.76493499999999,30.221317],"type":"Point"}
}