{
  "type": "Feature",
  "properties": {
    "iso:country":"US",
    "sg:address":"1886 W Jeter Rd",
    "sg:city":"Argyle",
    "sg:classifiers":[
        {
            "category":"Wholesale",
            "subcategory":"Furniture",
            "type":"Manufacturing & Wholesale Goods"
        }
    ],
    "sg:phone":"+1 940 464 3488",
    "sg:postcode":"76226",
    "sg:province":"TX",
    "wof:name":"Scottie Nelson Sales",
    "wof:placetype":"venue"
},
  "geometry": {"coordinates":[-97.17670099999999,33.091743],"type":"Point"}
}