{
  "type": "Feature",
  "properties": {
    "iso:country":"US",
    "sg:address":"4015 Lady Atwell Ct",
    "sg:city":"Missouri City",
    "sg:classifiers":[
        {
            "category":"Building & Trades",
            "subcategory":"Construction",
            "type":"Services"
        }
    ],
    "sg:phone":"+1 281 778 7340",
    "sg:postcode":"77459",
    "sg:province":"TX",
    "sg:tags":[
        "house"
    ],
    "wof:name":"Lifestyles Austin & Homes",
    "wof:placetype":"venue"
},
  "geometry": {"coordinates":[-95.516453,29.504286],"type":"Point"}
}