{
  "type": "Feature",
  "properties": {
    "iso:country":"US",
    "sg:address":"7887 Katy Fwy",
    "sg:city":"Houston",
    "sg:classifiers":[
        {
            "category":"Shopping",
            "subcategory":"Clothing, Apparel, & Fashions",
            "type":"Retail Goods"
        }
    ],
    "sg:phone":"+1 713 290 8255",
    "sg:postcode":"77024",
    "sg:province":"TX",
    "sg:tags":[
        "wear"
    ],
    "wof:name":"Zindlers Post Oak Inc",
    "wof:placetype":"venue"
},
  "geometry": {"coordinates":[-95.47554700000001,29.783368],"type":"Point"}
}