{
  "type": "Feature",
  "properties": {
    "iso:country":"US",
    "sg:address":"8668 Skyline Dr",
    "sg:city":"Dallas",
    "sg:classifiers":[
        {
            "category":"Professional",
            "type":"Services"
        }
    ],
    "sg:phone":"+1 214 345 9468",
    "sg:postcode":"75243",
    "sg:province":"TX",
    "sg:tags":[
        "establishment"
    ],
    "wof:name":"Moody Minnie",
    "wof:placetype":"venue"
},
  "geometry": {"coordinates":[-96.751063,32.907626],"type":"Point"}
}