{
  "type": "Feature",
  "properties": {
    "iso:country":"US",
    "sg:address":"223 Etta Ave",
    "sg:city":"Waxahachie",
    "sg:classifiers":[
        {
            "category":"Professional",
            "subcategory":"Computer Services",
            "type":"Services"
        }
    ],
    "sg:phone":"+1 972 938 0064",
    "sg:postcode":"75165",
    "sg:province":"TX",
    "sg:tags":[
        "datum"
    ],
    "wof:name":"Picturethis Multimedia",
    "wof:placetype":"venue"
},
  "geometry": {"coordinates":[-96.836055,32.404426],"type":"Point"}
}