{
  "type": "Feature",
  "properties": {
    "iso:country":"US",
    "sg:address":"700 S Columbia Dr",
    "sg:city":"West Columbia",
    "sg:classifiers":[
        {
            "category":"Autos & Motor Vehicles",
            "subcategory":"Fuel & Gas Station",
            "type":"Retail Goods"
        }
    ],
    "sg:phone":"+1 903 757 7077",
    "sg:postcode":"77486",
    "sg:province":"TX",
    "sg:tags":[
        "station"
    ],
    "wof:name":"Your Pump of Texas Inc",
    "wof:placetype":"venue"
},
  "geometry": {"coordinates":[-95.653576,29.138857],"type":"Point"}
}