{
  "type": "Feature",
  "properties": {
    "iso:country":"US",
    "sg:address":"3636 Executive Center Dr",
    "sg:city":"Austin",
    "sg:classifiers":[
        {
            "category":"Banks & Credit Unions",
            "subcategory":"Bank",
            "type":"Services"
        }
    ],
    "sg:phone":"+1 512 231 1111",
    "sg:postcode":"78731",
    "sg:province":"TX",
    "sg:tags":[
        "loan",
        "real estate"
    ],
    "wof:name":"Mortgage Processing Cnnctns",
    "wof:placetype":"venue"
},
  "geometry": {"coordinates":[-97.75012,30.363097],"type":"Point"}
}