{
  "type": "Feature",
  "properties": {
    "iso:country":"US",
    "sg:address":"9228 Teagarden Rd",
    "sg:city":"Dallas",
    "sg:classifiers":[
        {
            "category":"Wholesale",
            "subcategory":"Office Equipment",
            "type":"Manufacturing & Wholesale Goods"
        }
    ],
    "sg:phone":"+1 972 286 4002",
    "sg:postcode":"75217",
    "sg:province":"TX",
    "sg:tags":[
        "machine",
        "duplicating",
        "copying"
    ],
    "wof:name":"Branbritt Copier Svc",
    "wof:placetype":"venue"
},
  "geometry": {"coordinates":[-96.67116,32.668389],"type":"Point"}
}