{
  "type": "Feature",
  "properties": {
    "iso:country":"US",
    "sg:address":"5700 Rowlett Rd Ste 160",
    "sg:city":"Rowlett",
    "sg:classifiers":[
        {
            "category":"Health Services",
            "subcategory":"Hospital",
            "type":"Services"
        }
    ],
    "sg:phone":"+1 972 475 5994",
    "sg:postcode":"75089",
    "sg:province":"TX",
    "sg:tags":[
        "equipment",
        "supply"
    ],
    "wof:name":"M B K R Medical Management",
    "wof:placetype":"venue"
},
  "geometry": {"coordinates":[-96.569455,32.911542],"type":"Point"}
}