{
  "type": "Feature",
  "properties": {
    "iso:country":"US",
    "sg:address":"1101 FM 517 W",
    "sg:city":"Dickinson",
    "sg:classifiers":[
        {
            "category":"Restaurant",
            "type":"Food & Drink"
        }
    ],
    "sg:phone":"+1 281 534 2126",
    "sg:postcode":"77539",
    "sg:province":"TX",
    "sg:tags":[
        "eating"
    ],
    "wof:name":"Sesame House",
    "wof:placetype":"venue"
},
  "geometry": {"coordinates":[-95.09822,29.43965],"type":"Point"}
}