{
  "type": "Feature",
  "properties": {
    "iso:country":"US",
    "sg:address":"1107 Ave K",
    "sg:city":"Lubbock",
    "sg:classifiers":[
        {
            "category":"Professional",
            "subcategory":"Accounting & Tax Preparation",
            "type":"Services"
        }
    ],
    "sg:phone":"+1 806 762 2720",
    "sg:postcode":"79401",
    "sg:province":"TX",
    "wof:name":"Robison Vanessa C CPA",
    "wof:placetype":"venue"
},
  "geometry": {"coordinates":[-101.84786,33.584544],"type":"Point"}
}