{
  "type": "Feature",
  "properties": {
    "iso:country":"US",
    "sg:address":"1259 Eldridge Rd",
    "sg:city":"Sugar Land",
    "sg:classifiers":[
        {
            "category":"Retail",
            "subcategory":"Veterinary Services",
            "type":"Services"
        }
    ],
    "sg:phone":"+1 281 491 5533",
    "sg:postcode":"77478",
    "sg:province":"TX",
    "wof:name":"Doug R Hendrix Dvm",
    "wof:placetype":"venue"
},
  "geometry": {"coordinates":[-95.61889499999999,29.637441],"type":"Point"}
}