{
  "type": "Feature",
  "properties": {
    "iso:country":"US",
    "sg:address":"519 S Main St",
    "sg:city":"Mcallen",
    "sg:classifiers":[
        {
            "category":"Manufacturing",
            "subcategory":"Tools & Machinery",
            "type":"Manufacturing & Wholesale Goods"
        }
    ],
    "sg:phone":"+1 956 682 7231",
    "sg:postcode":"78501",
    "sg:province":"TX",
    "sg:tags":[
        "engine"
    ],
    "wof:name":"De Leon Auto Accessories",
    "wof:placetype":"venue"
},
  "geometry": {"coordinates":[-98.23527199999999,26.198739],"type":"Point"}
}