{
  "type": "Feature",
  "properties": {
    "iso:country":"US",
    "sg:address":"8223 S Presa St",
    "sg:city":"San Antonio",
    "sg:classifiers":[
        {
            "category":"Retail",
            "subcategory":"Auto Repair",
            "type":"Services"
        }
    ],
    "sg:phone":"+1 210 533 1299",
    "sg:postcode":"78223",
    "sg:province":"TX",
    "sg:tags":[
        "transmission"
    ],
    "wof:name":"Top Gear Transmission",
    "wof:placetype":"venue"
},
  "geometry": {"coordinates":[-98.453382,29.335544],"type":"Point"}
}