{
  "type": "Feature",
  "properties": {
    "iso:country":"US",
    "sg:address":"402 NW 10th St",
    "sg:city":"Andrews",
    "sg:classifiers":[
        {
            "category":"Arena",
            "subcategory":"Sports Club",
            "type":"Entertainment"
        }
    ],
    "sg:phone":"+1 432 523 9460",
    "sg:postcode":"79714",
    "sg:province":"TX",
    "sg:tags":[
        "football"
    ],
    "wof:name":"Andrews Youth Sports Assn",
    "wof:placetype":"venue"
},
  "geometry": {"coordinates":[-102.55966100000001,32.320081],"type":"Point"}
}