{
  "type": "Feature",
  "properties": {
    "iso:country":"US",
    "sg:address":"1620 Seley Ave",
    "sg:city":"Waco",
    "sg:classifiers":[
        {
            "category":"Building & Trades",
            "subcategory":"Construction",
            "type":"Services"
        }
    ],
    "sg:phone":"+1 254 757 3511",
    "sg:postcode":"76704",
    "sg:province":"TX",
    "sg:tags":[
        "masonry",
        "contractor"
    ],
    "wof:name":"Adolf Salinas Masonry",
    "wof:placetype":"venue"
},
  "geometry": {"coordinates":[-97.118937,31.584808],"type":"Point"}
}