{
  "type": "Feature",
  "properties": {
    "iso:country":"US",
    "sg:address":"2310 Lyndon B Johnson Fwy",
    "sg:city":"Farmers Branch",
    "sg:classifiers":[
        {
            "category":"Professional",
            "subcategory":"Management & Consulting",
            "type":"Services"
        }
    ],
    "sg:phone":"+1 972 884 9292",
    "sg:postcode":"75234",
    "sg:province":"TX",
    "sg:tags":[
        "development",
        "industrial"
    ],
    "sg:website":"www.prologis.com",
    "wof:name":"Pro Logis",
    "wof:placetype":"venue"
},
  "geometry": {"coordinates":[-96.899795,32.90644],"type":"Point"}
}