{
  "type": "Feature",
  "properties": {
    "iso:country":"US",
    "sg:address":"601 Ave E NE",
    "sg:city":"Childress",
    "sg:classifiers":[
        {
            "category":"Retail",
            "subcategory":"Auto Repair",
            "type":"Services"
        }
    ],
    "sg:phone":"+1 940 937 3791",
    "sg:postcode":"79201",
    "sg:province":"TX",
    "sg:tags":[
        "automotive",
        "general"
    ],
    "wof:name":"Wilsons Garage",
    "wof:placetype":"venue"
},
  "geometry": {"coordinates":[-100.199809,34.423566],"type":"Point"}
}