{
  "type": "Feature",
  "properties": {
    "iso:country":"US",
    "sg:address":"172 Osburn Rd",
    "sg:city":"Aubrey",
    "sg:classifiers":[
        {
            "category":"Farming",
            "subcategory":"Livestock Farm",
            "type":"Manufacturing & Wholesale Goods"
        }
    ],
    "sg:phone":"+1 940 365 9121",
    "sg:postcode":"76258",
    "sg:province":"TX",
    "sg:tags":[
        "horse",
        "other",
        "equine"
    ],
    "wof:name":"Turner Ranch Retail",
    "wof:placetype":"venue"
},
  "geometry": {"coordinates":[-96.94826,33.341064],"type":"Point"}
}