{
  "type": "Feature",
  "properties": {
    "iso:country":"US",
    "sg:address":"4415 71st St",
    "sg:city":"Lubbock",
    "sg:classifiers":[
        {
            "category":"Banks & Credit Unions",
            "subcategory":"Investment Brokerage",
            "type":"Services"
        }
    ],
    "sg:phone":"+1 806 788 1267",
    "sg:postcode":"79424",
    "sg:province":"TX",
    "sg:tags":[
        "consultant",
        "security",
        "planning",
        "financial"
    ],
    "sg:website":"www.waddell.com",
    "wof:name":"Waddell & Reed Inc",
    "wof:placetype":"venue"
},
  "geometry": {"coordinates":[-101.90698500000001,33.528804],"type":"Point"}
}