{
  "type": "Feature",
  "properties": {
    "iso:country":"US",
    "sg:address":"95 Frederick Rd",
    "sg:city":"Fredericksburg",
    "sg:classifiers":[
        {
            "category":"Government",
            "subcategory":"Office",
            "type":"Public Place"
        }
    ],
    "sg:phone":"+1 830 997 7047",
    "sg:postcode":"78624",
    "sg:province":"TX",
    "wof:name":"Gillespie County Extension",
    "wof:placetype":"venue"
},
  "geometry": {"coordinates":[-98.850776,30.286772],"type":"Point"}
}