{
  "type": "Feature",
  "properties": {
    "iso:country":"US",
    "sg:address":"8602 Snowden Cv",
    "sg:city":"Austin",
    "sg:classifiers":[
        {
            "category":"Building & Trades",
            "subcategory":"Landscaping Services",
            "type":"Services"
        },
        {
            "category":"Home & Garden",
            "subcategory":"Garden Supply",
            "type":"Retail Goods"
        }
    ],
    "sg:phone":"+1 512 850 2005",
    "sg:postcode":"78729",
    "sg:province":"TX",
    "sg:tags":[
        "lawn",
        "installation",
        "sprinkler",
        "sprinklers-garden",
        "system",
        "supervisory"
    ],
    "wof:name":"Panchita Sprinkler Services",
    "wof:placetype":"venue"
},
  "geometry": {"coordinates":[-97.76908299999999,30.456088],"type":"Point"}
}