{
  "type": "Feature",
  "properties": {
    "iso:country":"US",
    "sg:address":"1900 Elm St",
    "sg:city":"Dallas",
    "sg:classifiers":[
        {
            "category":"Professional",
            "subcategory":"Management & Consulting",
            "type":"Services"
        }
    ],
    "sg:phone":"+1 214 571 9788",
    "sg:postcode":"75201",
    "sg:province":"TX",
    "sg:tags":[
        "personnel",
        "consultant"
    ],
    "wof:name":"Clear Creek Personnel LP",
    "wof:placetype":"venue"
},
  "geometry": {"coordinates":[-96.79433899999999,32.78246],"type":"Point"}
}