{
  "type": "Feature",
  "properties": {
    "iso:country":"US",
    "sg:address":"1519 Branard St",
    "sg:city":"Houston",
    "sg:classifiers":[
        {
            "category":"Organizations",
            "subcategory":"Non-profit Organization",
            "type":"Services"
        }
    ],
    "sg:phone":"+1 713 525 9480",
    "sg:postcode":"77006",
    "sg:province":"TX",
    "wof:name":"Menil Foundation Business",
    "wof:placetype":"venue"
},
  "geometry": {"coordinates":[-95.398625,29.736868],"type":"Point"}
}