{
  "type": "Feature",
  "properties": {
    "iso:country":"US",
    "sg:address":"700 N Pearl St",
    "sg:city":"Dallas",
    "sg:classifiers":[
        {
            "category":"Shopping",
            "subcategory":"Bicycles & Sporting Goods",
            "type":"Retail Goods"
        }
    ],
    "sg:phone":"+1 214 871 8246",
    "sg:postcode":"75201",
    "sg:province":"TX",
    "wof:name":"Skaters Edge TX Amer Ice Grdn",
    "wof:placetype":"venue"
},
  "geometry": {"coordinates":[-96.796841,32.787296],"type":"Point"}
}