{
  "type": "Feature",
  "properties": {
    "iso:country":"US",
    "sg:address":"829 State Hwy 21",
    "sg:city":"Cedar Creek",
    "sg:classifiers":[
        {
            "category":"Wholesale",
            "subcategory":"Books, Periodicals, & Newspapers",
            "type":"Manufacturing & Wholesale Goods"
        }
    ],
    "sg:phone":"+1 512 321 2368",
    "sg:postcode":"78612",
    "sg:province":"TX",
    "sg:tags":[
        "bible",
        "inspirational"
    ],
    "wof:name":"Cbnva Texas District",
    "wof:placetype":"venue"
},
  "geometry": {"coordinates":[-97.468655,30.093917],"type":"Point"}
}