{
  "type": "Feature",
  "properties": {
    "iso:country":"US",
    "sg:address":"301 Edwards St",
    "sg:city":"Merkel",
    "sg:classifiers":[
        {
            "category":"Banks & Credit Unions",
            "subcategory":"Bank",
            "type":"Services"
        }
    ],
    "sg:phone":"+1 325 928 4702",
    "sg:postcode":"79536",
    "sg:province":"TX",
    "sg:tags":[
        "state",
        "savings"
    ],
    "wof:name":"First American Bank Ssb",
    "wof:placetype":"venue"
},
  "geometry": {"coordinates":[-100.010902,32.473549],"type":"Point"}
}