{
  "type": "Feature",
  "properties": {
    "iso:country":"US",
    "sg:address":"311 Guy St",
    "sg:city":"Mineola",
    "sg:classifiers":[
        {
            "category":"Airport",
            "type":"Transportation"
        }
    ],
    "sg:phone":"+1 903 768 2611",
    "sg:postcode":"75773",
    "sg:province":"TX",
    "wof:name":"Wood County Airport",
    "wof:placetype":"venue"
},
  "geometry": {"coordinates":[-95.495695,32.661469],"type":"Point"}
}