{
  "type": "Feature",
  "properties": {
    "iso:country":"US",
    "sg:address":"2505 W Northgate Dr",
    "sg:city":"Irving",
    "sg:classifiers":[
        {
            "category":"Organizations",
            "subcategory":"Religious Organization",
            "type":"Services"
        }
    ],
    "sg:phone":"+1 972 255 0595",
    "sg:postcode":"75062",
    "sg:province":"TX",
    "wof:name":"Our Redeemer Lutheran Church",
    "wof:placetype":"venue"
},
  "geometry": {"coordinates":[-96.98007200000001,32.855227],"type":"Point"}
}