{
  "type": "Feature",
  "properties": {
    "iso:country":"US",
    "sg:address":"9514 Montana Ave",
    "sg:city":"El Paso",
    "sg:classifiers":[
        {
            "category":"Professional",
            "subcategory":"Management & Consulting",
            "type":"Services"
        }
    ],
    "sg:phone":"+1 915 590 0462",
    "sg:postcode":"79925",
    "sg:province":"TX",
    "sg:tags":[
        "consultant",
        "business"
    ],
    "wof:name":"Genpart Inc",
    "wof:placetype":"venue"
},
  "geometry": {"coordinates":[-106.35784200000001,31.794416],"type":"Point"}
}