{
  "type": "Feature",
  "properties": {
    "iso:country":"US",
    "sg:address":"1407 Richmond Ave",
    "sg:city":"Houston",
    "sg:classifiers":[
        {
            "category":"Cinema",
            "subcategory":"Movie Rental",
            "type":"Entertainment"
        },
        {
            "category":"Shopping",
            "subcategory":"Music",
            "type":"Retail Goods"
        }
    ],
    "sg:phone":"+1 713 527 9997",
    "sg:postcode":"77006",
    "sg:province":"TX",
    "sg:tags":[
        "game",
        "video",
        "dvd's"
    ],
    "sg:website":"moviesthestore.com",
    "wof:name":"MOVIES! The Store",
    "wof:placetype":"venue"
},
  "geometry": {"coordinates":[-95.397059,29.734354],"type":"Point"}
}