{
  "type": "Feature",
  "properties": {
    "iso:country":"US",
    "sg:address":"404 N Alabama Rd",
    "sg:city":"Wharton",
    "sg:classifiers":[
        {
            "category":"Government",
            "subcategory":"Office",
            "type":"Public Place"
        }
    ],
    "sg:phone":"+1 979 532 5910",
    "sg:postcode":"77488",
    "sg:province":"TX",
    "sg:tags":[
        "state",
        "resource"
    ],
    "wof:name":"Food Stamp Program",
    "wof:placetype":"venue"
},
  "geometry": {"coordinates":[-96.088511,29.31158],"type":"Point"}
}