{
  "type": "Feature",
  "properties": {
    "iso:country":"US",
    "sg:address":"4918 S Padre Island Dr",
    "sg:city":"Corpus Christi",
    "sg:classifiers":[
        {
            "category":"Restaurant",
            "type":"Food & Drink"
        }
    ],
    "sg:menulink":"http://www.allmenus.com/tx/corpus-christi/9573-dennys/menu/",
    "sg:phone":"+1 361 992 4332",
    "sg:postcode":"78411",
    "sg:province":"TX",
    "sg:tags":[
        "american",
        "diner"
    ],
    "wof:name":"Denny's",
    "wof:placetype":"venue"
},
  "geometry": {"coordinates":[-97.383044,27.714381],"type":"Point"}
}