{
  "type": "Feature",
  "properties": {
    "iso:country":"US",
    "sg:address":"1520 S Malinche Ave",
    "sg:city":"Laredo",
    "sg:classifiers":[
        {
            "category":"Retail",
            "subcategory":"Auto Repair",
            "type":"Services"
        }
    ],
    "sg:phone":"+1 956 728 9890",
    "sg:postcode":"78046",
    "sg:province":"TX",
    "sg:tags":[
        "body",
        "automobile",
        "painting"
    ],
    "wof:name":"Sammmy's Auto Frame Shop",
    "wof:placetype":"venue"
},
  "geometry": {"coordinates":[-99.47474200000001,27.483272],"type":"Point"}
}