{
  "type": "Feature",
  "properties": {
    "iso:country":"US",
    "sg:address":"3535 W Camp Wisdom Rd",
    "sg:city":"Dallas",
    "sg:classifiers":[
        {
            "category":"Banks & Credit Unions",
            "subcategory":"Bank",
            "type":"Services"
        }
    ],
    "sg:phone":"+1 972 298 6193",
    "sg:postcode":"75237",
    "sg:province":"TX",
    "sg:website":"www.chase.com",
    "wof:name":"Chase",
    "wof:placetype":"venue"
},
  "geometry": {"coordinates":[-96.87771100000001,32.662588],"type":"Point"}
}