{
  "type": "Feature",
  "properties": {
    "iso:country":"US",
    "sg:address":"13763 State Highway 249",
    "sg:city":"Houston",
    "sg:classifiers":[
        {
            "category":"Shopping",
            "subcategory":"Beauty & Cosmetics",
            "type":"Retail Goods"
        }
    ],
    "sg:phone":"+1 281 591 1400",
    "sg:postcode":"77086",
    "sg:province":"TX",
    "sg:tags":[
        "supply"
    ],
    "wof:name":"His Kingdom Barber And Beauty Salon",
    "wof:placetype":"venue"
},
  "geometry": {"coordinates":[-95.49472400000001,29.920356],"type":"Point"}
}