{
  "type": "Feature",
  "properties": {
    "iso:country":"US",
    "sg:address":"418 Old Pecan St",
    "sg:city":"Austin",
    "sg:classifiers":[
        {
            "category":"Professional",
            "type":"Services"
        }
    ],
    "sg:phone":"+1 512 476 0000",
    "sg:postcode":"78701",
    "sg:province":"TX",
    "sg:tags":[
        "establishment"
    ],
    "wof:name":"Rock Stars Bar",
    "wof:placetype":"venue"
},
  "geometry": {"coordinates":[-97.738398,30.266906],"type":"Point"}
}