{
  "type": "Feature",
  "properties": {
    "iso:country":"US",
    "sg:address":"5411 Saturn Dr",
    "sg:city":"Dallas",
    "sg:classifiers":[
        {
            "category":"Professional",
            "subcategory":"Lawyer & Legal Services",
            "type":"Services"
        }
    ],
    "sg:phone":"+1 214 333 3040",
    "sg:postcode":"75237",
    "sg:province":"TX",
    "wof:name":"Lenox Roger S Atty At Law",
    "wof:placetype":"venue"
},
  "geometry": {"coordinates":[-96.86309799999999,32.6814],"type":"Point"}
}