{
  "type": "Feature",
  "properties": {
    "iso:country":"US",
    "sg:address":"830 Taylor St",
    "sg:city":"Fort Worth",
    "sg:classifiers":[
        {
            "category":"Professional",
            "type":"Services"
        }
    ],
    "sg:phone":"+1 817 885 8967",
    "sg:postcode":"76102",
    "sg:province":"TX",
    "wof:name":"Bridges",
    "wof:placetype":"venue"
},
  "geometry": {"coordinates":[-97.332106,32.75048],"type":"Point"}
}