{
  "type": "Feature",
  "properties": {
    "iso:country":"US",
    "sg:address":"1830 N Western St",
    "sg:city":"Amarillo",
    "sg:classifiers":[
        {
            "category":"Building & Trades",
            "subcategory":"Plumbing",
            "type":"Services"
        }
    ],
    "sg:phone":"+1 806 374 2650",
    "sg:postcode":"79124",
    "sg:province":"TX",
    "sg:tags":[
        "product",
        "management",
        "energy",
        "system"
    ],
    "wof:name":"Tedco Energy Svc",
    "wof:placetype":"venue"
},
  "geometry": {"coordinates":[-101.884049,35.233764],"type":"Point"}
}