{
  "type": "Feature",
  "properties": {
    "iso:country":"US",
    "sg:address":"310 Comal Street",
    "sg:city":"Austin",
    "sg:classifiers":[
        {
            "category":"Home & Garden",
            "subcategory":"Hardware",
            "type":"Retail Goods"
        }
    ],
    "sg:phone":"+1 512 478 2165",
    "sg:postcode":"78702",
    "sg:province":"TX",
    "sg:tags":[
        "store"
    ],
    "wof:name":"Habitat For Humanity Re-Store",
    "wof:placetype":"venue"
},
  "geometry": {"coordinates":[-97.72759000000001,30.260507],"type":"Point"}
}