{
  "type": "Feature",
  "properties": {
    "iso:country":"US",
    "sg:address":"5451 Oleary Dr",
    "sg:city":"El Paso",
    "sg:classifiers":[
        {
            "category":"Shopping",
            "subcategory":"Used Merchandise",
            "type":"Retail Goods"
        }
    ],
    "sg:phone":"+1 915 855 8776",
    "sg:postcode":"79938",
    "sg:province":"TX",
    "wof:name":"Frantlin",
    "wof:placetype":"venue"
},
  "geometry": {"coordinates":[-106.141355,31.866693],"type":"Point"}
}