{
  "type": "Feature",
  "properties": {
    "iso:country":"US",
    "sg:address":"5433 Smith Rd",
    "sg:city":"Von Ormy",
    "sg:classifiers":[
        {
            "category":"Professional",
            "type":"Services"
        }
    ],
    "sg:phone":"+1 210 624 3406",
    "sg:postcode":"78073",
    "sg:province":"TX",
    "wof:name":"Peak Performance",
    "wof:placetype":"venue"
},
  "geometry": {"coordinates":[-98.60965,29.203194],"type":"Point"}
}