{
  "type": "Feature",
  "properties": {
    "iso:country":"US",
    "sg:address":"1010 Island View St",
    "sg:city":"Kemah",
    "sg:classifiers":[
        {
            "category":"Education",
            "subcategory":"Special Training",
            "type":"Public Place"
        }
    ],
    "sg:phone":"+1 281 334 5895",
    "sg:postcode":"77565",
    "sg:province":"TX",
    "wof:name":"Career Skills Corp",
    "wof:placetype":"venue"
},
  "geometry": {"coordinates":[-95.056122,29.553632],"type":"Point"}
}