{
  "type": "Feature",
  "properties": {
    "iso:country":"US",
    "sg:address":"974 E Harrison St",
    "sg:city":"Brownsville",
    "sg:classifiers":[
        {
            "category":"Government",
            "subcategory":"Court House",
            "type":"Public Place"
        }
    ],
    "sg:phone":"+1 956 544 0838",
    "sg:postcode":"78520",
    "sg:province":"TX",
    "sg:tags":[
        "judicial",
        "part",
        "system"
    ],
    "wof:name":"Cameron County Civil Dst Crt",
    "wof:placetype":"venue"
},
  "geometry": {"coordinates":[-97.494497,25.907772],"type":"Point"}
}