{
  "type": "Feature",
  "properties": {
    "iso:country":"US",
    "sg:address":"211 N Mesa St",
    "sg:city":"El Paso",
    "sg:classifiers":[
        {
            "category":"Shopping",
            "subcategory":"Music",
            "type":"Retail Goods"
        }
    ],
    "sg:phone":"+1 915 764 3066",
    "sg:postcode":"79901",
    "sg:province":"TX",
    "wof:name":"All That Music",
    "wof:placetype":"venue"
},
  "geometry": {"coordinates":[-106.48783,31.759448],"type":"Point"}
}