{
  "type": "Feature",
  "properties": {
    "iso:country":"US",
    "sg:address":"3907 Belton Dr",
    "sg:city":"Dallas",
    "sg:classifiers":[
        {
            "category":"Building & Trades",
            "subcategory":"Construction",
            "type":"Services"
        }
    ],
    "sg:phone":"+1 972 862 3161",
    "sg:postcode":"75287",
    "sg:province":"TX",
    "sg:tags":[
        "industrial"
    ],
    "wof:name":"Stilley Solutions",
    "wof:placetype":"venue"
},
  "geometry": {"coordinates":[-96.845304,33.001918],"type":"Point"}
}