{
  "type": "Feature",
  "properties": {
    "iso:country":"US",
    "sg:address":"3102 Hillcrest Dr",
    "sg:city":"San Antonio",
    "sg:classifiers":[
        {
            "category":"Real Estate",
            "subcategory":"Real Estate Operator",
            "type":"Services"
        }
    ],
    "sg:phone":"+1 210 733 7101",
    "sg:postcode":"78201",
    "sg:province":"TX",
    "sg:tags":[
        "building",
        "apartment"
    ],
    "wof:name":"Continental Apartments",
    "wof:placetype":"venue"
},
  "geometry": {"coordinates":[-98.555516,29.489662],"type":"Point"}
}