{
  "type": "Feature",
  "properties": {
    "iso:country":"US",
    "sg:address":"5112 Graystone Ln",
    "sg:city":"Houston",
    "sg:classifiers":[
        {
            "category":"Professional",
            "subcategory":"Research",
            "type":"Services"
        }
    ],
    "sg:phone":"+1 281 397 6886",
    "sg:postcode":"77069",
    "sg:province":"TX",
    "sg:tags":[
        "nonphysical",
        "commercial"
    ],
    "wof:name":"Aquisitions Mergers Ltd",
    "wof:placetype":"venue"
},
  "geometry": {"coordinates":[-95.509654,29.986964],"type":"Point"}
}