{
  "type": "Feature",
  "properties": {
    "iso:country":"US",
    "sg:address":"5365 Southcross Ranch Rd",
    "sg:city":"San Antonio",
    "sg:classifiers":[
        {
            "category":"Real Estate",
            "subcategory":"Real Estate Operator",
            "type":"Services"
        }
    ],
    "sg:phone":"+1 210 648 2262",
    "sg:postcode":"78222",
    "sg:province":"TX",
    "sg:tags":[
        "mobile",
        "home",
        "community"
    ],
    "wof:name":"Crescent Place",
    "wof:placetype":"venue"
},
  "geometry": {"coordinates":[-98.38629400000001,29.371164],"type":"Point"}
}