{
  "type": "Feature",
  "properties": {
    "iso:country":"US",
    "sg:address":"11031 Northwest Fwy",
    "sg:city":"Houston",
    "sg:classifiers":[
        {
            "category":"Restaurant",
            "type":"Food & Drink"
        }
    ],
    "sg:phone":"+1 713 682 2404",
    "sg:postcode":"77092",
    "sg:province":"TX",
    "sg:tags":[
        "mexican",
        "eating"
    ],
    "wof:name":"Chapala Mexican Restaurant",
    "wof:placetype":"venue"
},
  "geometry": {"coordinates":[-95.467598,29.817699],"type":"Point"}
}