{
  "type": "Feature",
  "properties": {
    "iso:country":"US",
    "sg:address":"6711 Feather Creek Dr",
    "sg:city":"Houston",
    "sg:classifiers":[
        {
            "category":"Professional",
            "subcategory":"Business Services",
            "type":"Services"
        }
    ],
    "sg:phone":"+1 281 820 3095",
    "sg:postcode":"77086",
    "sg:province":"TX",
    "wof:name":"Kdd Enterprises",
    "wof:placetype":"venue"
},
  "geometry": {"coordinates":[-95.485888,29.930647],"type":"Point"}
}