{
  "type": "Feature",
  "properties": {
    "iso:country":"US",
    "sg:address":"16537 Shady Ln",
    "sg:city":"Channelview",
    "sg:classifiers":[
        {
            "category":"Wholesale",
            "subcategory":"Construction Materials",
            "type":"Manufacturing & Wholesale Goods"
        },
        {
            "category":"Professional",
            "subcategory":"Art Services",
            "type":"Services"
        }
    ],
    "sg:phone":"+1 281 452 6877",
    "sg:postcode":"77530",
    "sg:province":"TX",
    "sg:tags":[
        "coatings-protective",
        "painting-production"
    ],
    "wof:name":"Dampney/Thurmalox",
    "wof:placetype":"venue"
},
  "geometry": {"coordinates":[-95.10607400000001,29.809351],"type":"Point"}
}