{
  "type": "Feature",
  "properties": {
    "iso:country":"US",
    "sg:address":"415 State Highway 27",
    "sg:city":"Comfort",
    "sg:classifiers":[
        {
            "category":"Personal",
            "subcategory":"Barber",
            "type":"Services"
        }
    ],
    "sg:phone":"+1 830 995 4744",
    "sg:postcode":"78013",
    "sg:province":"TX",
    "wof:name":"Comfort Barber",
    "wof:placetype":"venue"
},
  "geometry": {"coordinates":[-98.913234,29.967976],"type":"Point"}
}