{
  "type": "Feature",
  "properties": {
    "iso:country":"US",
    "sg:address":"410 W 5th St",
    "sg:city":"Plainview",
    "sg:classifiers":[
        {
            "category":"Autos & Motor Vehicles",
            "subcategory":"Automobile Sales",
            "type":"Retail Goods"
        }
    ],
    "sg:phone":"+1 806 296 6363",
    "sg:postcode":"79072",
    "sg:province":"TX",
    "sg:tags":[
        "dealers-used",
        "car",
        "used",
        "cars-wholesale",
        "new"
    ],
    "wof:name":"Johnston Motors Inc",
    "wof:placetype":"venue"
},
  "geometry": {"coordinates":[-101.706897,34.184489],"type":"Point"}
}