{
  "type": "Feature",
  "properties": {
    "iso:country":"US",
    "sg:address":"6602 Indian Lake Dr",
    "sg:city":"Missouri City",
    "sg:classifiers":[
        {
            "category":"Autos & Motor Vehicles",
            "subcategory":"Fuel & Gas Station",
            "type":"Retail Goods"
        }
    ],
    "sg:phone":"+1 281 437 2341",
    "sg:postcode":"77489",
    "sg:province":"TX",
    "sg:tags":[
        "station",
        "gasoline"
    ],
    "wof:name":"Shaws Chevron",
    "wof:placetype":"venue"
},
  "geometry": {"coordinates":[-95.485528,29.603441],"type":"Point"}
}