{
  "type": "Feature",
  "properties": {
    "iso:country":"US",
    "sg:address":"2800 Edgewood Ln",
    "sg:city":"Colleyville",
    "sg:classifiers":[
        {
            "category":"Real Estate",
            "subcategory":"Real Estate Agent",
            "type":"Services"
        }
    ],
    "sg:phone":"+1 817 267 6641",
    "sg:postcode":"76034",
    "sg:province":"TX",
    "wof:name":"Optima Central Inc",
    "wof:placetype":"venue"
},
  "geometry": {"coordinates":[-97.12382599999999,32.884966],"type":"Point"}
}