{
  "type": "Feature",
  "properties": {
    "iso:country":"US",
    "sg:address":"695 Orleans St",
    "sg:city":"Beaumont",
    "sg:classifiers":[
        {
            "category":"Bars & Pubs",
            "type":"Food & Drink"
        }
    ],
    "sg:phone":"+1 409 835 8900",
    "sg:postcode":"77701",
    "sg:province":"TX",
    "sg:tags":[
        "club",
        "drinking",
        "night"
    ],
    "sg:website":"www.platinumclub1.com",
    "wof:name":"Platinum Club Inc",
    "wof:placetype":"venue"
},
  "geometry": {"coordinates":[-94.098214,30.081907],"type":"Point"}
}