{
  "type": "Feature",
  "properties": {
    "iso:country":"US",
    "sg:address":"3324 Fondren Rd",
    "sg:city":"Houston",
    "sg:classifiers":[
        {
            "category":"Utilities",
            "subcategory":"Mobile Phone",
            "type":"Services"
        }
    ],
    "sg:phone":"+1 832 251 3200",
    "sg:postcode":"77063",
    "sg:province":"TX",
    "sg:tags":[
        "communication",
        "radiotelephone"
    ],
    "wof:name":"Unlimited Paging Inc",
    "wof:placetype":"venue"
},
  "geometry": {"coordinates":[-95.520663,29.728632],"type":"Point"}
}