{
  "type": "Feature",
  "properties": {
    "iso:country":"US",
    "sg:address":"177 Tranquil Pl",
    "sg:city":"Waxahachie",
    "sg:classifiers":[
        {
            "category":"Retail",
            "subcategory":"Portrait Studio",
            "type":"Services"
        }
    ],
    "sg:phone":"+1 972 617 8161",
    "sg:postcode":"75167",
    "sg:province":"TX",
    "sg:tags":[
        "photo"
    ],
    "wof:name":"David Truly - Photograhic",
    "wof:placetype":"venue"
},
  "geometry": {"coordinates":[-96.841579,32.497893],"type":"Point"}
}