{
  "type": "Feature",
  "properties": {
    "iso:country":"US",
    "sg:address":"535 W I- 30",
    "sg:city":"Garland",
    "sg:classifiers":[
        {
            "category":"Restaurant",
            "type":"Food & Drink"
        }
    ],
    "sg:phone":"+1 972 303 5575",
    "sg:postcode":"75043",
    "sg:province":"TX",
    "wof:name":"Chili's Grill & Bar",
    "wof:placetype":"venue"
},
  "geometry": {"coordinates":[-96.59713499999999,32.839995],"type":"Point"}
}