{
  "type": "Feature",
  "properties": {
    "iso:country":"US",
    "sg:address":"2406 Eagle Pt",
    "sg:city":"Austin",
    "sg:classifiers":[
        {
            "category":"Health Services",
            "subcategory":"Health Practitioner",
            "type":"Services"
        }
    ],
    "sg:phone":"+1 512 266 2851",
    "sg:postcode":"78734",
    "sg:province":"TX",
    "wof:name":"Modified Independence",
    "wof:placetype":"venue"
},
  "geometry": {"coordinates":[-97.92288600000001,30.378266],"type":"Point"}
}