{
  "type": "Feature",
  "properties": {
    "iso:country":"US",
    "sg:address":"3600 W Pioneer Pkwy",
    "sg:city":"Pantego",
    "sg:classifiers":[
        {
            "category":"Building & Trades",
            "subcategory":"Construction",
            "type":"Services"
        }
    ],
    "sg:phone":"+1 817 261 3037",
    "sg:postcode":"76013",
    "sg:province":"TX",
    "sg:tags":[
        "roofing",
        "contractor"
    ],
    "wof:name":"Isaac Construction & Roof",
    "wof:placetype":"venue"
},
  "geometry": {"coordinates":[-97.16547799999999,32.713957],"type":"Point"}
}