{
  "type": "Feature",
  "properties": {
    "iso:country":"US",
    "sg:address":"14341 East Fwy",
    "sg:city":"Houston",
    "sg:classifiers":[
        {
            "category":"Professional",
            "subcategory":"Accounting & Tax Preparation",
            "type":"Services"
        }
    ],
    "sg:phone":"+1 713 453 6513",
    "sg:postcode":"77015",
    "sg:province":"TX",
    "wof:name":"Johnny J Williams Inc",
    "wof:placetype":"venue"
},
  "geometry": {"coordinates":[-95.16828599999999,29.771188],"type":"Point"}
}