{
  "type": "Feature",
  "properties": {
    "iso:country":"US",
    "sg:address":"507 Richey St",
    "sg:city":"Pasadena",
    "sg:classifiers":[
        {
            "category":"Building & Trades",
            "subcategory":"Construction",
            "type":"Services"
        }
    ],
    "sg:phone":"+1 713 534 6291",
    "sg:postcode":"77506",
    "sg:province":"TX",
    "sg:tags":[
        "contractor"
    ],
    "wof:name":"Riveras Drywall",
    "wof:placetype":"venue"
},
  "geometry": {"coordinates":[-95.219791,29.704473],"type":"Point"}
}