{
  "type": "Feature",
  "properties": {
    "iso:country":"US",
    "sg:address":"3726 W Walker St",
    "sg:city":"Breckenridge",
    "sg:classifiers":[
        {
            "category":"Restaurant",
            "type":"Food & Drink"
        }
    ],
    "sg:menulink":"http://www.allmenus.com/tx/breckenridge-north/202489-mcdonalds/menu/",
    "sg:postcode":"76424",
    "sg:province":"TX",
    "sg:tags":[
        "burger",
        "american"
    ],
    "wof:name":"McDonald's",
    "wof:placetype":"venue"
},
  "geometry": {"coordinates":[-98.946815,32.759571],"type":"Point"}
}