{
  "type": "Feature",
  "properties": {
    "iso:country":"US",
    "sg:address":"603 N 23rd St",
    "sg:city":"Lamesa",
    "sg:classifiers":[
        {
            "category":"Shopping",
            "subcategory":"Gifts & Souvenirs",
            "type":"Retail Goods"
        }
    ],
    "sg:phone":"+1 806 872 7017",
    "sg:postcode":"79331",
    "sg:province":"TX",
    "wof:name":"Christmas In Action Lamesa",
    "wof:placetype":"venue"
},
  "geometry": {"coordinates":[-101.96057500000001,32.753765],"type":"Point"}
}