{
  "type": "Feature",
  "properties": {
    "iso:country":"US",
    "sg:address":"7849 Alto Caro Dr",
    "sg:city":"Dallas",
    "sg:classifiers":[
        {
            "category":"Professional",
            "subcategory":"Lawyer & Legal Services",
            "type":"Services"
        }
    ],
    "sg:phone":"+1 972 788 5016",
    "sg:postcode":"75248",
    "sg:province":"TX",
    "sg:tags":[
        "attorney"
    ],
    "wof:name":"Jeffrey P Buchwald",
    "wof:placetype":"venue"
},
  "geometry": {"coordinates":[-96.77044600000001,32.966176],"type":"Point"}
}