{
  "type": "Feature",
  "properties": {
    "iso:country":"US",
    "sg:address":"1510 Morning Park Dr",
    "sg:city":"Katy",
    "sg:classifiers":[
        {
            "category":"Home & Garden",
            "subcategory":"Home Furnishings",
            "type":"Retail Goods"
        }
    ],
    "sg:phone":"+1 281 392 8399",
    "sg:postcode":"77494",
    "sg:province":"TX",
    "sg:tags":[
        "bedding"
    ],
    "wof:name":"2 M Designs",
    "wof:placetype":"venue"
},
  "geometry": {"coordinates":[-95.767619,29.757131],"type":"Point"}
}