{
  "type": "Feature",
  "properties": {
    "iso:country":"US",
    "sg:address":"945 Airport Rd",
    "sg:city":"Roanoke",
    "sg:classifiers":[
        {
            "category":"Shopping",
            "subcategory":"Hobbies, Toys, & Games",
            "type":"Retail Goods"
        }
    ],
    "sg:phone":"+1 817 491 9500",
    "sg:postcode":"76262",
    "sg:province":"TX",
    "wof:name":"Texas Aero Hobbys",
    "wof:placetype":"venue"
},
  "geometry": {"coordinates":[-97.22810800000001,33.054666],"type":"Point"}
}