{
  "type": "Feature",
  "properties": {
    "iso:country":"US",
    "sg:address":"107 Westoak Rd",
    "sg:city":"San Antonio",
    "sg:classifiers":[
        {
            "category":"Retail",
            "subcategory":"Auto Repair",
            "type":"Services"
        }
    ],
    "sg:phone":"+1 210 674 9333",
    "sg:postcode":"78227",
    "sg:province":"TX",
    "sg:tags":[
        "automotive",
        "general"
    ],
    "wof:name":"Armstrong Automotive",
    "wof:placetype":"venue"
},
  "geometry": {"coordinates":[-98.635131,29.403567],"type":"Point"}
}