{
  "type": "Feature",
  "properties": {
    "iso:country":"US",
    "sg:address":"7520 Park North Dr",
    "sg:city":"Beaumont",
    "sg:classifiers":[
        {
            "category":"Wholesale",
            "subcategory":"Hardware",
            "type":"Manufacturing & Wholesale Goods"
        }
    ],
    "sg:phone":"+1 409 892 1207",
    "sg:postcode":"77708",
    "sg:province":"TX",
    "sg:tags":[
        "tool"
    ],
    "wof:name":"Southeast Texas Tools",
    "wof:placetype":"venue"
},
  "geometry": {"coordinates":[-94.172597,30.147593],"type":"Point"}
}