{
  "type": "Feature",
  "properties": {
    "iso:country":"US",
    "sg:address":"7937 US Hwy 80",
    "sg:city":"Fort Worth",
    "sg:classifiers":[
        {
            "category":"Retail",
            "subcategory":"Laundry & Dry Cleaning",
            "type":"Services"
        }
    ],
    "sg:phone":"+1 817 244 1140",
    "sg:postcode":"76116",
    "sg:province":"TX",
    "sg:tags":[
        "drycleaning",
        "plant"
    ],
    "wof:name":"Brothers Two Cleaners",
    "wof:placetype":"venue"
},
  "geometry": {"coordinates":[-97.45215899999999,32.723031],"type":"Point"}
}