{
  "type": "Feature",
  "properties": {
    "iso:country":"US",
    "sg:address":"2201 W Shady Grove Rd",
    "sg:city":"Irving",
    "sg:classifiers":[
        {
            "category":"Organizations",
            "subcategory":"Religious Organization",
            "type":"Services"
        }
    ],
    "sg:phone":"+1 972 313 7742",
    "sg:postcode":"75060",
    "sg:province":"TX",
    "wof:name":"Irving Baptist Fellowship",
    "wof:placetype":"venue"
},
  "geometry": {"coordinates":[-96.9739,32.800499],"type":"Point"}
}