{
  "type": "Feature",
  "properties": {
    "iso:country":"US",
    "sg:address":"18855 Lyndon B Johnson Fwy #6537",
    "sg:city":"Mesquite",
    "sg:classifiers":[
        {
            "category":"Home & Garden",
            "subcategory":"Household Appliances",
            "type":"Retail Goods"
        },
        {
            "category":"Home & Garden",
            "subcategory":"Home Furnishings",
            "type":"Retail Goods"
        },
        {
            "category":"Home & Garden",
            "subcategory":"Hardware",
            "type":"Retail Goods"
        }
    ],
    "sg:phone":"+1 972 682 6294",
    "sg:postcode":"75150",
    "sg:province":"TX",
    "sg:tags":[
        "kitchen",
        "store",
        "bath"
    ],
    "sg:website":"www.homedepot.com",
    "wof:name":"The Home Depot",
    "wof:placetype":"venue"
},
  "geometry": {"coordinates":[-96.62636999999999,32.801377],"type":"Point"}
}