{
  "type": "Feature",
  "properties": {
    "iso:country":"US",
    "sg:address":"8306 Jimmy Foxx St",
    "sg:city":"San Antonio",
    "sg:classifiers":[
        {
            "category":"Building & Trades",
            "subcategory":"Plumbing",
            "type":"Services"
        }
    ],
    "sg:phone":"+1 210 523 9842",
    "sg:postcode":"78240",
    "sg:province":"TX",
    "sg:tags":[
        "conditioning",
        "contractor",
        "system",
        "air"
    ],
    "wof:name":"Summit Air Conditioning & Heat",
    "wof:placetype":"venue"
},
  "geometry": {"coordinates":[-98.621269,29.518445],"type":"Point"}
}