{
  "type": "Feature",
  "properties": {
    "iso:country":"US",
    "sg:address":"608 Flightline Dr",
    "sg:city":"Laredo",
    "sg:classifiers":[
        {
            "category":"Airline",
            "type":"Transportation"
        }
    ],
    "sg:phone":"+1 956 725 8414",
    "sg:postcode":"78070",
    "sg:province":"TX",
    "sg:tags":[
        "passenger"
    ],
    "wof:name":"Aesa",
    "wof:placetype":"venue"
},
  "geometry": {"coordinates":[-98.425785,29.810116],"type":"Point"}
}