{
  "type": "Feature",
  "properties": {
    "iso:country":"US",
    "sg:address":"3401 Capella Ave",
    "sg:city":"El Paso",
    "sg:classifiers":[
        {
            "category":"Personal",
            "type":"Services"
        }
    ],
    "sg:phone":"+1 915 751 6090",
    "sg:postcode":"79904",
    "sg:province":"TX",
    "wof:name":"Bride Ideas",
    "wof:placetype":"venue"
},
  "geometry": {"coordinates":[-106.451351,31.856873],"type":"Point"}
}