{
  "type": "Feature",
  "properties": {
    "iso:country":"US",
    "sg:address":"7891 Culebra Rd",
    "sg:city":"San Antonio",
    "sg:classifiers":[
        {
            "category":"Restaurant",
            "type":"Food & Drink"
        }
    ],
    "sg:phone":"+1 210 681 9562",
    "sg:postcode":"78251",
    "sg:province":"TX",
    "sg:tags":[
        "eating"
    ],
    "wof:name":"Popeyes Chicken & Biscuits",
    "wof:placetype":"venue"
},
  "geometry": {"coordinates":[-98.643236,29.463623],"type":"Point"}
}