{
  "type": "Feature",
  "properties": {
    "iso:country":"US",
    "sg:address":"303 N Great Southwest Pkwy",
    "sg:city":"Arlington",
    "sg:classifiers":[
        {
            "category":"Restaurant",
            "type":"Food & Drink"
        }
    ],
    "sg:phone":"+1 817 695 2991",
    "sg:postcode":"76011",
    "sg:province":"TX",
    "wof:name":"Tj's Sports Bar",
    "wof:placetype":"venue"
},
  "geometry": {"coordinates":[-97.045991,32.741472],"type":"Point"}
}