{
  "type": "Feature",
  "properties": {
    "iso:country":"US",
    "sg:address":"24502 Chipwood Dr",
    "sg:city":"Magnolia",
    "sg:classifiers":[
        {
            "category":"Building & Trades",
            "subcategory":"Construction",
            "type":"Services"
        }
    ],
    "sg:phone":"+1 281 259 8732",
    "sg:postcode":"77355",
    "sg:province":"TX",
    "sg:tags":[
        "excavating",
        "contractor"
    ],
    "wof:name":"J & B & Sons Construction",
    "wof:placetype":"venue"
},
  "geometry": {"coordinates":[-95.76012799999999,30.127957],"type":"Point"}
}