{
  "type": "Feature",
  "properties": {
    "iso:country":"US",
    "sg:address":"3430 Dalworth St",
    "sg:city":"Arlington",
    "sg:classifiers":[
        {
            "category":"Home & Garden",
            "subcategory":"Building Materials",
            "type":"Retail Goods"
        }
    ],
    "sg:phone":"+1 817 640 7840",
    "sg:postcode":"76011",
    "sg:province":"TX",
    "sg:tags":[
        "door",
        "gate",
        "operating",
        "devices"
    ],
    "wof:name":"Bob's Distributing",
    "wof:placetype":"venue"
},
  "geometry": {"coordinates":[-97.050164,32.744754],"type":"Point"}
}