{
  "type": "Feature",
  "properties": {
    "iso:country":"US",
    "sg:address":"5020 FM 1960 W",
    "sg:city":"Houston",
    "sg:classifiers":[
        {
            "category":"Food & Beverages",
            "subcategory":"Candy",
            "type":"Retail Goods"
        }
    ],
    "sg:phone":"+1 281 583 1120",
    "sg:postcode":"77069",
    "sg:province":"TX",
    "sg:tags":[
        "confectionery"
    ],
    "wof:name":"Ferrell's Candy & Gift",
    "wof:placetype":"venue"
},
  "geometry": {"coordinates":[-95.505263,29.983949],"type":"Point"}
}