{
  "type": "Feature",
  "properties": {
    "iso:country":"US",
    "sg:address":"3414 Olsen Blvd",
    "sg:city":"Amarillo",
    "sg:classifiers":[
        {
            "category":"Government",
            "subcategory":"Office",
            "type":"Public Place"
        }
    ],
    "sg:phone":"+1 806 354 9779",
    "sg:postcode":"79109",
    "sg:province":"TX",
    "sg:tags":[
        "affairs",
        "administrative"
    ],
    "wof:name":"Amarillo Vet Center",
    "wof:placetype":"venue"
},
  "geometry": {"coordinates":[-101.87912900000001,35.184989],"type":"Point"}
}