{
  "type": "Feature",
  "properties": {
    "iso:country":"US",
    "sg:address":"3815 W Fuqua St",
    "sg:city":"Houston",
    "sg:classifiers":[
        {
            "category":"Building & Trades",
            "subcategory":"Construction",
            "type":"Services"
        }
    ],
    "sg:phone":"+1 713 413 2511",
    "sg:postcode":"77045",
    "sg:province":"TX",
    "sg:tags":[
        "contractor"
    ],
    "wof:name":"Weis Builders",
    "wof:placetype":"venue"
},
  "geometry": {"coordinates":[-95.43433899999999,29.613214],"type":"Point"}
}