{
  "type": "Feature",
  "properties": {
    "iso:country":"US",
    "sg:address":"13323 Veterans Memorial Dr",
    "sg:city":"Houston",
    "sg:classifiers":[
        {
            "category":"Professional",
            "subcategory":"Research",
            "type":"Services"
        }
    ],
    "sg:phone":"+1 832 484 9911",
    "sg:postcode":"77014",
    "sg:province":"TX",
    "sg:tags":[
        "environmental",
        "ecological"
    ],
    "wof:name":"G & S Environmental Svc",
    "wof:placetype":"venue"
},
  "geometry": {"coordinates":[-95.492564,29.980169],"type":"Point"}
}