{
  "type": "Feature",
  "properties": {
    "iso:country":"US",
    "sg:address":"5547 Castle Knight Dr",
    "sg:city":"San Antonio",
    "sg:classifiers":[
        {
            "category":"Shopping",
            "subcategory":"Musical Instruments",
            "type":"Retail Goods"
        }
    ],
    "sg:phone":"+1 210 590 1742",
    "sg:postcode":"78218",
    "sg:province":"TX",
    "wof:name":"Larry K Mueller",
    "wof:placetype":"venue"
},
  "geometry": {"coordinates":[-98.38351,29.504558],"type":"Point"}
}