{
  "type": "Feature",
  "properties": {
    "iso:country":"US",
    "sg:address":"10304 Winston Ave",
    "sg:city":"Lubbock",
    "sg:classifiers":[
        {
            "category":"Professional",
            "type":"Services"
        }
    ],
    "sg:phone":"+1 806 798 8582",
    "sg:postcode":"79424",
    "sg:province":"TX",
    "wof:name":"Aj Global Inc",
    "wof:placetype":"venue"
},
  "geometry": {"coordinates":[-101.91959799999999,33.499761],"type":"Point"}
}