{
  "type": "Feature",
  "properties": {
    "iso:country":"US",
    "sg:address":"420 Jefferson St",
    "sg:city":"Kerrville",
    "sg:classifiers":[
        {
            "category":"Freight",
            "type":"Transportation"
        },
        {
            "category":"Home & Garden",
            "subcategory":"Furniture",
            "type":"Retail Goods"
        }
    ],
    "sg:phone":"+1 830 257 7522",
    "sg:postcode":"78028",
    "sg:province":"TX",
    "sg:tags":[
        "mover"
    ],
    "wof:name":"Pioneer Moving Co",
    "wof:placetype":"venue"
},
  "geometry": {"coordinates":[-99.14243999999999,30.051082],"type":"Point"}
}