{
  "type": "Feature",
  "properties": {
    "iso:country":"US",
    "sg:address":"231 Madero St",
    "sg:city":"San Antonio",
    "sg:classifiers":[
        {
            "category":"Health Services",
            "subcategory":"Nursing And Care Facility",
            "type":"Services"
        }
    ],
    "sg:phone":"+1 210 224 7067",
    "sg:postcode":"78207",
    "sg:province":"TX",
    "sg:tags":[
        "skilled"
    ],
    "wof:name":"Mariner Health Care Inc",
    "wof:placetype":"venue"
},
  "geometry": {"coordinates":[-98.525263,29.402806],"type":"Point"}
}