{
  "type": "Feature",
  "properties": {
    "iso:country":"US",
    "sg:address":"5 Willow Run Dr",
    "sg:city":"Belton",
    "sg:classifiers":[
        {
            "category":"Professional",
            "subcategory":"Engineering",
            "type":"Services"
        }
    ],
    "sg:phone":"+1 254 780 9964",
    "sg:postcode":"76513",
    "sg:province":"TX",
    "wof:name":"Settle Civil Strl Engineers",
    "wof:placetype":"venue"
},
  "geometry": {"coordinates":[-97.437427,31.159838],"type":"Point"}
}