{
  "type": "Feature",
  "properties": {
    "iso:country":"US",
    "sg:address":"7766 Hammerly Blvd",
    "sg:city":"Houston",
    "sg:classifiers":[
        {
            "category":"Shopping",
            "subcategory":"Clothing, Apparel, & Fashions",
            "type":"Retail Goods"
        }
    ],
    "sg:phone":"+1 713 697 3774",
    "sg:postcode":"77055",
    "sg:province":"TX",
    "wof:name":"Greek Illustrated",
    "wof:placetype":"venue"
},
  "geometry": {"coordinates":[-95.48422100000001,29.810653],"type":"Point"}
}