{
  "type": "Feature",
  "properties": {
    "iso:country":"US",
    "sg:address":"809 E Polk Ave",
    "sg:city":"Harlingen",
    "sg:classifiers":[
        {
            "category":"Professional",
            "subcategory":"Business Services",
            "type":"Services"
        }
    ],
    "sg:phone":"+1 956 428 8190",
    "sg:postcode":"78550",
    "sg:province":"TX",
    "wof:name":"Bawm Technologies",
    "wof:placetype":"venue"
},
  "geometry": {"coordinates":[-97.686959,26.18867],"type":"Point"}
}