{
  "type": "Feature",
  "properties": {
    "iso:country":"US",
    "sg:address":"323 W Missouri Ave",
    "sg:city":"Dallas",
    "sg:classifiers":[
        {
            "category":"Building & Trades",
            "subcategory":"Landscaping Services",
            "type":"Services"
        }
    ],
    "sg:phone":"+1 214 941 9111",
    "sg:postcode":"75224",
    "sg:province":"TX",
    "sg:tags":[
        "landscape",
        "contractor"
    ],
    "wof:name":"Johnson Mowing",
    "wof:placetype":"venue"
},
  "geometry": {"coordinates":[-96.827578,32.717672],"type":"Point"}
}