{
  "type": "Feature",
  "properties": {
    "iso:country":"US",
    "sg:address":"9319 Stella Link Rd",
    "sg:city":"Houston",
    "sg:classifiers":[
        {
            "category":"Shopping",
            "subcategory":"Discount & Variety Stores",
            "type":"Retail Goods"
        }
    ],
    "sg:phone":"+1 713 661 2600",
    "sg:postcode":"77025",
    "sg:province":"TX",
    "sg:tags":[
        "merchandise",
        "general"
    ],
    "wof:name":"Dollar Emporium",
    "wof:placetype":"venue"
},
  "geometry": {"coordinates":[-95.43989000000001,29.681975],"type":"Point"}
}