{
  "type": "Feature",
  "properties": {
    "iso:country":"US",
    "sg:address":"4521 Waits Ave",
    "sg:city":"Fort Worth",
    "sg:classifiers":[
        {
            "category":"Building & Trades",
            "subcategory":"Construction",
            "type":"Services"
        }
    ],
    "sg:phone":"+1 817 921 0869",
    "sg:postcode":"76133",
    "sg:province":"TX",
    "sg:tags":[
        "hanging",
        "contractor"
    ],
    "wof:name":"Hernandez Custom Paint",
    "wof:placetype":"venue"
},
  "geometry": {"coordinates":[-97.35805499999999,32.681243],"type":"Point"}
}