{
  "type": "Feature",
  "properties": {
    "iso:country":"US",
    "sg:address":"28313 Wintergreen St",
    "sg:city":"Waller",
    "sg:classifiers":[
        {
            "category":"Building & Trades",
            "subcategory":"Plumbing",
            "type":"Services"
        }
    ],
    "sg:phone":"+1 936 931 1890",
    "sg:postcode":"77484",
    "sg:province":"TX",
    "sg:tags":[
        "contractor"
    ],
    "wof:name":"Texans Air Conditioning and H",
    "wof:placetype":"venue"
},
  "geometry": {"coordinates":[-95.86816399999999,30.068288],"type":"Point"}
}