{
  "type": "Feature",
  "properties": {
    "iso:country":"US",
    "sg:address":"11612 Spotted Horse Dr",
    "sg:city":"Austin",
    "sg:classifiers":[
        {
            "category":"Building & Trades",
            "subcategory":"Pest Control",
            "type":"Services"
        }
    ],
    "sg:phone":"+1 512 343 0858",
    "sg:postcode":"78759",
    "sg:province":"TX",
    "wof:name":"Hunter Bug Pest Control",
    "wof:placetype":"venue"
},
  "geometry": {"coordinates":[-97.73474299999999,30.410179],"type":"Point"}
}