{
  "type": "Feature",
  "properties": {
    "iso:country":"US",
    "sg:address":"3724 Boulder Ave",
    "sg:city":"Port Arthur",
    "sg:classifiers":[
        {
            "category":"Professional",
            "subcategory":"Business Services",
            "type":"Services"
        }
    ],
    "sg:phone":"+1 409 982 0628",
    "sg:postcode":"77640",
    "sg:province":"TX",
    "wof:name":"Bjs Boutique & Interiors",
    "wof:placetype":"venue"
},
  "geometry": {"coordinates":[-93.947537,29.910898],"type":"Point"}
}