{
  "type": "Feature",
  "properties": {
    "iso:country":"US",
    "sg:address":"514 Thames Dr",
    "sg:city":"San Antonio",
    "sg:classifiers":[
        {
            "category":"Shopping",
            "subcategory":"News",
            "type":"Retail Goods"
        }
    ],
    "sg:phone":"+1 210 525 0811",
    "sg:postcode":"78216",
    "sg:province":"TX",
    "sg:tags":[
        "dealer"
    ],
    "wof:name":"San Antonio Good News",
    "wof:placetype":"venue"
},
  "geometry": {"coordinates":[-98.50629499999999,29.515278],"type":"Point"}
}