{
  "type": "Feature",
  "properties": {
    "iso:country":"US",
    "sg:address":"431 Plantation Dr",
    "sg:city":"Pharr",
    "sg:classifiers":[
        {
            "category":"Banks & Credit Unions",
            "subcategory":"Investment Brokerage",
            "type":"Services"
        }
    ],
    "sg:phone":"+1 956 782 5001",
    "sg:postcode":"78577",
    "sg:province":"TX",
    "sg:tags":[
        "advisory"
    ],
    "wof:name":"Zip Investments",
    "wof:placetype":"venue"
},
  "geometry": {"coordinates":[-98.188023,26.161525],"type":"Point"}
}