{
  "type": "Feature",
  "properties": {
    "iso:country":"US",
    "sg:address":"1810 Novel Dr",
    "sg:city":"Garland",
    "sg:classifiers":[
        {
            "category":"Professional",
            "type":"Services"
        }
    ],
    "sg:phone":"+1 972 271 6397",
    "sg:postcode":"75040",
    "sg:province":"TX",
    "wof:name":"Patricia Lara",
    "wof:placetype":"venue"
},
  "geometry": {"coordinates":[-96.606185,32.894782],"type":"Point"}
}