{
  "type": "Feature",
  "properties": {
    "iso:country":"US",
    "sg:address":"1815 10th St",
    "sg:city":"Floresville",
    "sg:classifiers":[
        {
            "category":"Government",
            "subcategory":"Office",
            "type":"Public Place"
        }
    ],
    "sg:phone":"+1 830 393 3141",
    "sg:postcode":"78114",
    "sg:province":"TX",
    "sg:tags":[
        "state",
        "resource"
    ],
    "wof:name":"Human Resources Dept",
    "wof:placetype":"venue"
},
  "geometry": {"coordinates":[-98.14681,29.13497],"type":"Point"}
}