{
  "type": "Feature",
  "properties": {
    "iso:country":"US",
    "sg:address":"111 Sunset Heights Ave",
    "sg:city":"Dayton",
    "sg:classifiers":[
        {
            "category":"Real Estate",
            "subcategory":"Real Estate Services",
            "type":"Services"
        },
        {
            "category":"Building & Trades",
            "subcategory":"Cleaning & Sanitation",
            "type":"Services"
        }
    ],
    "sg:phone":"+1 936 334 5966",
    "sg:postcode":"77535",
    "sg:province":"TX",
    "sg:tags":[
        "maintenance",
        "cleaners-interior"
    ],
    "wof:name":"Ray S Home Maint Repai",
    "wof:placetype":"venue"
},
  "geometry": {"coordinates":[-94.903115,30.033676],"type":"Point"}
}