{
  "type": "Feature",
  "properties": {
    "iso:country":"US",
    "sg:address":"912 Summer Hill Rd",
    "sg:city":"Red Oak",
    "sg:classifiers":[
        {
            "category":"Personal",
            "subcategory":"Beauty Salon",
            "type":"Services"
        }
    ],
    "sg:phone":"+1 972 298 3470",
    "sg:postcode":"75154",
    "sg:province":"TX",
    "wof:name":"Main Street Stylist",
    "wof:placetype":"venue"
},
  "geometry": {"coordinates":[-96.83442700000001,32.523526],"type":"Point"}
}