{
  "type": "Feature",
  "properties": {
    "iso:country":"US",
    "sg:address":"6419 Orange Blossom Way",
    "sg:city":"Austin",
    "sg:classifiers":[
        {
            "category":"Professional",
            "subcategory":"Testing Lab",
            "type":"Services"
        }
    ],
    "sg:phone":"+1 512 280 1847",
    "sg:postcode":"78744",
    "sg:province":"TX",
    "sg:tags":[
        "laboratory"
    ],
    "wof:name":"Wilson Enterprises",
    "wof:placetype":"venue"
},
  "geometry": {"coordinates":[-97.740133,30.166639],"type":"Point"}
}