{
  "type": "Feature",
  "properties": {
    "iso:country":"US",
    "sg:address":"7501 Chesterfield Dr",
    "sg:city":"Dallas",
    "sg:classifiers":[
        {
            "category":"Restaurant",
            "type":"Food & Drink"
        }
    ],
    "sg:phone":"+1 972 296 4960",
    "sg:postcode":"75237",
    "sg:province":"TX",
    "sg:tags":[
        "caterer"
    ],
    "wof:name":"G& R Catering",
    "wof:placetype":"venue"
},
  "geometry": {"coordinates":[-96.869889,32.658377],"type":"Point"}
}