{
  "type": "Feature",
  "properties": {
    "iso:country":"US",
    "sg:address":"16715 Bentfield Way",
    "sg:city":"Houston",
    "sg:classifiers":[
        {
            "category":"Manufacturing",
            "subcategory":"Toys & Sporting Goods",
            "type":"Manufacturing & Wholesale Goods"
        }
    ],
    "sg:phone":"+1 281 480 6053",
    "sg:postcode":"77058",
    "sg:province":"TX",
    "sg:tags":[
        "manufacturer",
        "fishing",
        "tackle-wholesale",
        "mfg"
    ],
    "wof:name":"Scotts Custom Rods",
    "wof:placetype":"venue"
},
  "geometry": {"coordinates":[-95.105548,29.567647],"type":"Point"}
}