{
  "type": "Feature",
  "properties": {
    "iso:country":"US",
    "sg:address":"2750 E Southlake Blvd Ste 160",
    "sg:city":"Southlake",
    "sg:classifiers":[
        {
            "category":"Personal",
            "subcategory":"Nail Salon",
            "type":"Services"
        }
    ],
    "sg:phone":"+1 817 749 2022",
    "sg:postcode":"76092",
    "sg:province":"TX",
    "wof:name":"Excellent Nails & Spa",
    "wof:placetype":"venue"
},
  "geometry": {"coordinates":[-97.10771200000001,32.938332],"type":"Point"}
}