{
  "type": "Feature",
  "properties": {
    "iso:country":"US",
    "sg:address":"1224 N Hwy 377",
    "sg:city":"Roanoke",
    "sg:classifiers":[
        {
            "category":"Personal",
            "subcategory":"Tanning Parlor",
            "type":"Services"
        }
    ],
    "sg:phone":"+1 817 491 1881",
    "sg:postcode":"76258",
    "sg:province":"TX",
    "sg:tags":[
        "salon"
    ],
    "wof:name":"Glow Tanning Salon",
    "wof:placetype":"venue"
},
  "geometry": {"coordinates":[-96.92801,33.437899],"type":"Point"}
}