{
  "type": "Feature",
  "properties": {
    "iso:country":"US",
    "sg:address":"7913 Ave B",
    "sg:city":"Houston",
    "sg:classifiers":[
        {
            "category":"Building & Trades",
            "subcategory":"Construction",
            "type":"Services"
        }
    ],
    "sg:phone":"+1 713 926 3989",
    "sg:postcode":"77012",
    "sg:province":"TX",
    "sg:tags":[
        "hanging",
        "contractor"
    ],
    "wof:name":"Adonais Painting Company",
    "wof:placetype":"venue"
},
  "geometry": {"coordinates":[-95.28205199999999,29.730571],"type":"Point"}
}