{
  "type": "Feature",
  "properties": {
    "iso:country":"US",
    "sg:address":"1737 Wright Dr",
    "sg:city":"Kingsville",
    "sg:classifiers":[
        {
            "category":"Building & Trades",
            "subcategory":"Construction",
            "type":"Services"
        }
    ],
    "sg:phone":"+1 361 595 5819",
    "sg:postcode":"78363",
    "sg:province":"TX",
    "sg:tags":[
        "general",
        "contractor"
    ],
    "wof:name":"Terry W Yaklin Construction",
    "wof:placetype":"venue"
},
  "geometry": {"coordinates":[-97.84791199999999,27.499377],"type":"Point"}
}