{
  "type": "Feature",
  "properties": {
    "iso:country":"US",
    "sg:address":"209 E Park Ave",
    "sg:city":"Hereford",
    "sg:classifiers":[
        {
            "category":"Home & Garden",
            "subcategory":"Furniture",
            "type":"Retail Goods"
        },
        {
            "category":"Home & Garden",
            "subcategory":"Carpets & Floor Coverings",
            "type":"Retail Goods"
        }
    ],
    "sg:phone":"+1 806 364 4073",
    "sg:postcode":"79045",
    "sg:province":"TX",
    "sg:tags":[
        "material",
        "rug",
        "store"
    ],
    "sg:website":"http://www.dettens.com/",
    "wof:name":"Detten's Carpet Care",
    "wof:placetype":"venue"
},
  "geometry": {"coordinates":[-102.408089,34.82213],"type":"Point"}
}