{
  "type": "Feature",
  "properties": {
    "iso:country":"US",
    "sg:address":"1557 Blalock Rd",
    "sg:city":"Houston",
    "sg:classifiers":[
        {
            "category":"Manufacturing",
            "subcategory":"Printing",
            "type":"Manufacturing & Wholesale Goods"
        }
    ],
    "sg:phone":"+1 713 465 1396",
    "sg:postcode":"77080",
    "sg:province":"TX",
    "sg:tags":[
        "commercial"
    ],
    "wof:name":"Charlies Decals",
    "wof:placetype":"venue"
},
  "geometry": {"coordinates":[-95.524051,29.79843],"type":"Point"}
}