{
  "type": "Feature",
  "properties": {
    "iso:country":"US",
    "sg:address":"208 S Tower St",
    "sg:city":"Weatherford",
    "sg:classifiers":[
        {
            "category":"Shopping",
            "type":"Retail Goods"
        }
    ],
    "sg:phone":"+1 214 948 1274",
    "sg:postcode":"76086",
    "sg:province":"TX",
    "sg:tags":[
        "trophy",
        "medal",
        "award"
    ],
    "wof:name":"Evans Engraving & Stamping Inc",
    "wof:placetype":"venue"
},
  "geometry": {"coordinates":[-97.780171,32.757091],"type":"Point"}
}