{
  "type": "Feature",
  "properties": {
    "iso:country":"US",
    "sg:address":"3511 Palmer Hwy",
    "sg:city":"Texas City",
    "sg:classifiers":[
        {
            "category":"Wholesale",
            "subcategory":"Non-durable Goods",
            "type":"Manufacturing & Wholesale Goods"
        }
    ],
    "sg:phone":"+1 409 945 7798",
    "sg:postcode":"77590",
    "sg:province":"TX",
    "wof:name":"Quarter-To-Ten Store",
    "wof:placetype":"venue"
},
  "geometry": {"coordinates":[-94.94961499999999,29.395253],"type":"Point"}
}