{
  "type": "Feature",
  "properties": {
    "iso:country":"US",
    "sg:address":"5210 39th St",
    "sg:city":"Groves",
    "sg:classifiers":[
        {
            "category":"Retail",
            "subcategory":"Car Wash",
            "type":"Services"
        }
    ],
    "sg:phone":"+1 409 963 0024",
    "sg:postcode":"77619",
    "sg:province":"TX",
    "sg:tags":[
        "polishing",
        "washing"
    ],
    "wof:name":"Magic Car Wash & Lube",
    "wof:placetype":"venue"
},
  "geometry": {"coordinates":[-93.928483,29.936204],"type":"Point"}
}