{
  "type": "Feature",
  "properties": {
    "iso:country":"US",
    "sg:address":"200 W Pioneer Pkwy",
    "sg:city":"Grand Prairie",
    "sg:classifiers":[
        {
            "category":"Freight",
            "type":"Transportation"
        }
    ],
    "sg:phone":"+1 972 263 7888",
    "sg:postcode":"75051",
    "sg:province":"TX",
    "sg:tags":[
        "commercial",
        "storage"
    ],
    "wof:name":"Big John's Self Storage",
    "wof:placetype":"venue"
},
  "geometry": {"coordinates":[-97.00512500000001,32.709575],"type":"Point"}
}