{
  "type": "Feature",
  "properties": {
    "iso:country":"US",
    "sg:address":"4700 N Mesa St",
    "sg:city":"El Paso",
    "sg:classifiers":[
        {
            "category":"Health Services",
            "subcategory":"Health Practitioner",
            "type":"Services"
        }
    ],
    "sg:phone":"+1 915 544 5434",
    "sg:postcode":"79912",
    "sg:province":"TX",
    "wof:name":"Desert Spirit Therapeutic Mass",
    "wof:placetype":"venue"
},
  "geometry": {"coordinates":[-106.50908,31.805166],"type":"Point"}
}