{
  "type": "Feature",
  "properties": {
    "iso:country":"US",
    "sg:address":"3901 Airport Fwy",
    "sg:city":"Bedford",
    "sg:classifiers":[
        {
            "category":"Real Estate",
            "subcategory":"Real Estate Operator",
            "type":"Services"
        }
    ],
    "sg:phone":"+1 817 640 9555",
    "sg:postcode":"76021",
    "sg:province":"TX",
    "sg:tags":[
        "condominium"
    ],
    "wof:name":"Monarch Condos",
    "wof:placetype":"venue"
},
  "geometry": {"coordinates":[-97.100928,32.838052],"type":"Point"}
}