{
  "type": "Feature",
  "properties": {
    "iso:country":"US",
    "sg:address":"155 Hunters Glen Dr",
    "sg:city":"Waxahachie",
    "sg:classifiers":[
        {
            "category":"Social Services",
            "type":"Services"
        },
        {
            "category":"Health Services",
            "subcategory":"Clinic",
            "type":"Services"
        }
    ],
    "sg:phone":"+1 972 576 5106",
    "sg:postcode":"75167",
    "sg:province":"TX",
    "sg:tags":[
        "welfare"
    ],
    "wof:name":"Hosa Texas Advisor",
    "wof:placetype":"venue"
},
  "geometry": {"coordinates":[-96.84284700000001,32.498719],"type":"Point"}
}