{
  "type": "Feature",
  "properties": {
    "iso:country":"US",
    "sg:address":"12119 E FM 917",
    "sg:city":"Alvarado",
    "sg:classifiers":[
        {
            "category":"Wholesale",
            "subcategory":"Durable Goods & Equipment",
            "type":"Manufacturing & Wholesale Goods"
        }
    ],
    "sg:phone":"+1 817 473 3910",
    "sg:postcode":"76009",
    "sg:province":"TX",
    "wof:name":"Acase Distributors",
    "wof:placetype":"venue"
},
  "geometry": {"coordinates":[-97.16370000000001,32.51443],"type":"Point"}
}