{
  "type": "Feature",
  "properties": {
    "iso:country":"US",
    "sg:address":"1101 W Oak St",
    "sg:city":"Palestine",
    "sg:classifiers":[
        {
            "category":"Home & Garden",
            "subcategory":"Garden Supply",
            "type":"Retail Goods"
        }
    ],
    "sg:phone":"+1 903 723 9143",
    "sg:postcode":"75801",
    "sg:province":"TX",
    "sg:tags":[
        "engine"
    ],
    "wof:name":"Palestine Saw & Lawn Equipment",
    "wof:placetype":"venue"
},
  "geometry": {"coordinates":[-95.642951,31.759929],"type":"Point"}
}