{
  "type": "Feature",
  "properties": {
    "iso:country":"US",
    "sg:address":"109 S 7th St",
    "sg:city":"Gatesville",
    "sg:classifiers":[
        {
            "category":"Real Estate",
            "subcategory":"Real Estate Services",
            "type":"Services"
        }
    ],
    "sg:phone":"+1 254 865 2114",
    "sg:postcode":"76528",
    "sg:province":"TX",
    "sg:tags":[
        "abstract",
        "title"
    ],
    "wof:name":"Brown Abstract Co",
    "wof:placetype":"venue"
},
  "geometry": {"coordinates":[-97.74954200000001,31.434859],"type":"Point"}
}