{
  "type": "Feature",
  "properties": {
    "iso:country":"US",
    "sg:address":"11000 Beaumont Hwy",
    "sg:city":"Houston",
    "sg:classifiers":[
        {
            "category":"Freight",
            "type":"Transportation"
        }
    ],
    "sg:phone":"+1 281 559 3171",
    "sg:postcode":"77078",
    "sg:province":"TX",
    "sg:tags":[
        "commercial",
        "storage"
    ],
    "wof:name":"Coastal Container Co",
    "wof:placetype":"venue"
},
  "geometry": {"coordinates":[-95.23629699999999,29.82134],"type":"Point"}
}