{
  "type": "Feature",
  "properties": {
    "iso:country":"US",
    "sg:address":"7911 Gulf Isle Ct",
    "sg:city":"Houston",
    "sg:classifiers":[
        {
            "category":"Professional",
            "subcategory":"Business Services",
            "type":"Services"
        }
    ],
    "sg:phone":"+1 281 463 6777",
    "sg:postcode":"77095",
    "sg:province":"TX",
    "wof:name":"Expertise Building Inspec",
    "wof:placetype":"venue"
},
  "geometry": {"coordinates":[-95.67576200000001,29.894219],"type":"Point"}
}