{
  "type": "Feature",
  "properties": {
    "iso:country":"US",
    "sg:address":"2348 US Hwy 69",
    "sg:city":"Denison",
    "sg:classifiers":[
        {
            "category":"Retail",
            "subcategory":"Auto Repair",
            "type":"Services"
        }
    ],
    "sg:phone":"+1 903 463 4833",
    "sg:postcode":"75021",
    "sg:province":"TX",
    "sg:tags":[
        "body",
        "painting"
    ],
    "wof:name":"C & P Paint & Body",
    "wof:placetype":"venue"
},
  "geometry": {"coordinates":[-96.49737,33.711762],"type":"Point"}
}