{
  "type": "Feature",
  "properties": {
    "iso:country":"US",
    "sg:address":"1400 Post Oak Blvd",
    "sg:city":"Houston",
    "sg:classifiers":[
        {
            "category":"Banks & Credit Unions",
            "subcategory":"Bank",
            "type":"Services"
        }
    ],
    "sg:phone":"+1 713 355 6908",
    "sg:postcode":"77056",
    "sg:province":"TX",
    "sg:tags":[
        "mortgage"
    ],
    "wof:name":"Willow Bend Mortgage",
    "wof:placetype":"venue"
},
  "geometry": {"coordinates":[-95.45925800000001,29.752926],"type":"Point"}
}