{
  "type": "Feature",
  "properties": {
    "iso:country":"US",
    "sg:address":"3401 Chaney Ln",
    "sg:city":"Plano",
    "sg:classifiers":[
        {
            "category":"Communications",
            "type":"Services"
        },
        {
            "category":"Professional",
            "subcategory":"Management & Consulting",
            "type":"Services"
        }
    ],
    "sg:phone":"+1 972 985 0647",
    "sg:postcode":"75093",
    "sg:province":"TX",
    "sg:tags":[
        "public",
        "relations"
    ],
    "wof:name":"Meyne Communications LLC",
    "wof:placetype":"venue"
},
  "geometry": {"coordinates":[-96.78419599999999,33.042851],"type":"Point"}
}