{
  "type": "Feature",
  "properties": {
    "iso:country":"US",
    "sg:address":"403 N 4th St",
    "sg:city":"Jacksboro",
    "sg:classifiers":[
        {
            "category":"Professional",
            "subcategory":"Employment Agencies",
            "type":"Services"
        }
    ],
    "sg:phone":"+1 940 567 5962",
    "sg:postcode":"76458",
    "sg:province":"TX",
    "sg:tags":[
        "help",
        "supply"
    ],
    "wof:name":"SL Russell Transcription Servi",
    "wof:placetype":"venue"
},
  "geometry": {"coordinates":[-98.168992,33.223125],"type":"Point"}
}