{
  "type": "Feature",
  "properties": {
    "iso:country":"US",
    "sg:address":"2306 Sparrow Branch Ct",
    "sg:city":"Sugar Land",
    "sg:classifiers":[
        {
            "category":"Freight",
            "type":"Transportation"
        }
    ],
    "sg:phone":"+1 281 239 7616",
    "sg:postcode":"77479",
    "sg:province":"TX",
    "wof:name":"Kentran Freight Corp",
    "wof:placetype":"venue"
},
  "geometry": {"coordinates":[-95.68544199999999,29.575609],"type":"Point"}
}