{
  "type": "Feature",
  "properties": {
    "iso:country":"US",
    "sg:address":"11711 Primwood Dr",
    "sg:city":"Houston",
    "sg:classifiers":[
        {
            "category":"Shopping",
            "subcategory":"Gifts & Souvenirs",
            "type":"Retail Goods"
        }
    ],
    "sg:phone":"+1 281 251 2028",
    "sg:postcode":"77070",
    "sg:province":"TX",
    "wof:name":"Crafts Glor",
    "wof:placetype":"venue"
},
  "geometry": {"coordinates":[-95.59674699999999,29.987245],"type":"Point"}
}