{
  "type": "Feature",
  "properties": {
    "iso:country":"US",
    "sg:address":"132 Carol Dr",
    "sg:city":"Quinlan",
    "sg:classifiers":[
        {
            "category":"Wholesale",
            "subcategory":"Stationery",
            "type":"Manufacturing & Wholesale Goods"
        }
    ],
    "sg:phone":"+1 903 356 3602",
    "sg:postcode":"75474",
    "sg:province":"TX",
    "sg:tags":[
        "supply"
    ],
    "wof:name":"Memories & More",
    "wof:placetype":"venue"
},
  "geometry": {"coordinates":[-96.14676,32.907156],"type":"Point"}
}