{
  "type": "Feature",
  "properties": {
    "iso:country":"US",
    "sg:address":"215 W Camp Wisdom Rd",
    "sg:city":"Duncanville",
    "sg:classifiers":[
        {
            "category":"Retail",
            "subcategory":"Laundry & Dry Cleaning",
            "type":"Services"
        }
    ],
    "sg:phone":"+1 972 296 4851",
    "sg:postcode":"75116",
    "sg:province":"TX",
    "wof:name":"Comet One Hour Cleaners",
    "wof:placetype":"venue"
},
  "geometry": {"coordinates":[-96.908897,32.6619],"type":"Point"}
}