{
  "type": "Feature",
  "properties": {
    "iso:country":"US",
    "sg:address":"12561 FM 3226",
    "sg:city":"Tyler",
    "sg:classifiers":[
        {
            "category":"Professional",
            "type":"Services"
        }
    ],
    "sg:phone":"+1 903 566 8701",
    "sg:postcode":"75707",
    "sg:province":"TX",
    "sg:tags":[
        "establishment"
    ],
    "wof:name":"Cyber Station Texas",
    "wof:placetype":"venue"
},
  "geometry": {"coordinates":[-95.137935,32.29662],"type":"Point"}
}