{
  "type": "Feature",
  "properties": {
    "iso:country":"US",
    "sg:address":"12064 Veterans Memorial Dr",
    "sg:city":"Houston",
    "sg:classifiers":[
        {
            "category":"Retail",
            "subcategory":"Self-service Laundry",
            "type":"Services"
        }
    ],
    "sg:phone":"+1 281 893 6787",
    "sg:postcode":"77067",
    "sg:province":"TX",
    "sg:tags":[
        "coin"
    ],
    "wof:name":"Wash-O-Mat Washateria",
    "wof:placetype":"venue"
},
  "geometry": {"coordinates":[-95.477812,29.960905],"type":"Point"}
}