{
  "type": "Feature",
  "properties": {
    "iso:country":"US",
    "sg:address":"10890 Ferguson Rd",
    "sg:city":"Dallas",
    "sg:classifiers":[
        {
            "category":"Retail",
            "subcategory":"Repair Shop",
            "type":"Services"
        },
        {
            "category":"Shopping",
            "subcategory":"Computers & Home Electronics",
            "type":"Retail Goods"
        }
    ],
    "sg:phone":"+1 214 321 0010",
    "sg:postcode":"75228",
    "sg:province":"TX",
    "sg:tags":[
        "television",
        "stereo",
        "video",
        "radio-service",
        "equipment-dealers",
        "radio",
        "audio",
        "consumer",
        "store"
    ],
    "sg:website":"http://www.texastvandvideo.com",
    "wof:name":"Texas TV & Video",
    "wof:placetype":"venue"
},
  "geometry": {"coordinates":[-96.662582,32.844151],"type":"Point"}
}