{
  "type": "Feature",
  "properties": {
    "iso:country":"US",
    "sg:address":"104 W Polk St",
    "sg:city":"Burnet",
    "sg:classifiers":[
        {
            "category":"Shopping",
            "subcategory":"Used Merchandise",
            "type":"Retail Goods"
        }
    ],
    "sg:phone":"+1 512 756 8840",
    "sg:postcode":"78611",
    "sg:province":"TX",
    "wof:name":"Another Time Etc",
    "wof:placetype":"venue"
},
  "geometry": {"coordinates":[-98.228752,30.758105],"type":"Point"}
}