{
  "type": "Feature",
  "properties": {
    "iso:country":"US",
    "sg:address":"10651 King William Dr",
    "sg:city":"Dallas",
    "sg:classifiers":[
        {
            "category":"Wholesale",
            "subcategory":"Stationery",
            "type":"Manufacturing & Wholesale Goods"
        }
    ],
    "sg:phone":"+1 214 357 2088",
    "sg:postcode":"75220",
    "sg:province":"TX",
    "sg:tags":[
        "corrugated",
        "box",
        "fiber"
    ],
    "wof:name":"A-Box Connection",
    "wof:placetype":"venue"
},
  "geometry": {"coordinates":[-96.900251,32.870048],"type":"Point"}
}