{
  "type": "Feature",
  "properties": {
    "iso:country":"US",
    "sg:address":"6006 Club Oaks Dr",
    "sg:city":"Dallas",
    "sg:classifiers":[
        {
            "category":"Professional",
            "type":"Services"
        }
    ],
    "sg:phone":"+1 214 691 2210",
    "sg:postcode":"75248",
    "sg:province":"TX",
    "wof:name":"Katherine Eberhardt",
    "wof:placetype":"venue"
},
  "geometry": {"coordinates":[-96.815727,32.982674],"type":"Point"}
}