{
  "type": "Feature",
  "properties": {
    "iso:country":"US",
    "sg:address":"4210 South Dr",
    "sg:city":"Houston",
    "sg:classifiers":[
        {
            "category":"Shopping",
            "subcategory":"Computers & Home Electronics",
            "type":"Retail Goods"
        }
    ],
    "sg:phone":"+1 713 667 9424",
    "sg:postcode":"77053",
    "sg:province":"TX",
    "wof:name":"Halco Life Safety Systems",
    "wof:placetype":"venue"
},
  "geometry": {"coordinates":[-95.441676,29.586317],"type":"Point"}
}