{
  "type": "Feature",
  "properties": {
    "iso:country":"US",
    "sg:address":"4341 Lindbergh Dr",
    "sg:city":"Dallas",
    "sg:classifiers":[
        {
            "category":"Building & Trades",
            "subcategory":"Construction",
            "type":"Services"
        }
    ],
    "sg:phone":"+1 972 233 8073",
    "sg:postcode":"75001",
    "sg:province":"TX",
    "sg:tags":[
        "general",
        "contractor"
    ],
    "wof:name":"A B Construction",
    "wof:placetype":"venue"
},
  "geometry": {"coordinates":[-96.836491,32.957992],"type":"Point"}
}