{
  "type": "Feature",
  "properties": {
    "iso:country":"US",
    "sg:address":"207 Ember Glen Dr",
    "sg:city":"Arlington",
    "sg:classifiers":[
        {
            "category":"Manufacturing",
            "subcategory":"Apparel",
            "type":"Manufacturing & Wholesale Goods"
        }
    ],
    "sg:phone":"+1 817 472 7023",
    "sg:postcode":"76018",
    "sg:province":"TX",
    "wof:name":"Stitch Center",
    "wof:placetype":"venue"
},
  "geometry": {"coordinates":[-97.111501,32.668549],"type":"Point"}
}