{
  "type": "Feature",
  "properties": {
    "iso:country":"US",
    "sg:address":"5918 Silent Oaks Dr",
    "sg:city":"Humble",
    "sg:classifiers":[
        {
            "category":"Wholesale",
            "subcategory":"Scrap",
            "type":"Manufacturing & Wholesale Goods"
        }
    ],
    "sg:phone":"+1 281 852 2054",
    "sg:postcode":"77346",
    "sg:province":"TX",
    "sg:tags":[
        "material"
    ],
    "wof:name":"Susans Scrap Attack",
    "wof:placetype":"venue"
},
  "geometry": {"coordinates":[-95.183221,30.006656],"type":"Point"}
}