{
  "type": "Feature",
  "properties": {
    "iso:country":"US",
    "sg:address":"3613 W Pioneer Pkwy",
    "sg:city":"Arlington",
    "sg:classifiers":[
        {
            "category":"Mining & Drilling",
            "type":"Manufacturing & Wholesale Goods"
        }
    ],
    "sg:phone":"+1 817 461 0067",
    "sg:postcode":"76013",
    "sg:province":"TX",
    "sg:tags":[
        "exploration"
    ],
    "wof:name":"Titan Oil and Gas",
    "wof:placetype":"venue"
},
  "geometry": {"coordinates":[-97.164896,32.713667],"type":"Point"}
}