{
  "type": "Feature",
  "properties": {
    "iso:country":"US",
    "sg:address":"4151 Belt Line Rd",
    "sg:city":"Addison",
    "sg:classifiers":[
        {
            "category":"Retail",
            "subcategory":"Portrait Studio",
            "type":"Services"
        }
    ],
    "sg:phone":"+1 972 960 7057",
    "sg:postcode":"75001",
    "sg:province":"TX",
    "sg:tags":[
        "photo"
    ],
    "wof:name":"Hour Photos",
    "wof:placetype":"venue"
},
  "geometry": {"coordinates":[-96.838967,32.954265],"type":"Point"}
}