{
  "type": "Feature",
  "properties": {
    "iso:country":"US",
    "sg:address":"350 N Texas Ave",
    "sg:city":"Webster",
    "sg:classifiers":[
        {
            "category":"Health Services",
            "subcategory":"Podiatrist",
            "type":"Services"
        }
    ],
    "sg:phone":"+1 281 338 1166",
    "sg:postcode":"77598",
    "sg:province":"TX",
    "wof:name":"Bay Area Foot & Ankle Spec",
    "wof:placetype":"venue"
},
  "geometry": {"coordinates":[-95.126643,29.535891],"type":"Point"}
}