{
  "type": "Feature",
  "properties": {
    "iso:country":"US",
    "sg:address":"6635 Santa Anita Dr",
    "sg:city":"Brownsville",
    "sg:classifiers":[
        {
            "category":"Home & Garden",
            "subcategory":"Carpets & Floor Coverings",
            "type":"Retail Goods"
        }
    ],
    "sg:phone":"+1 956 504 5337",
    "sg:postcode":"78521",
    "sg:province":"TX",
    "wof:name":"Castillo Floor Care",
    "wof:placetype":"venue"
},
  "geometry": {"coordinates":[-97.423987,25.894183],"type":"Point"}
}