{
  "type": "Feature",
  "properties": {
    "iso:country":"US",
    "sg:address":"714 Cottonwood Dr",
    "sg:city":"Desoto",
    "sg:classifiers":[
        {
            "category":"Insurance",
            "subcategory":"Insurance Agent",
            "type":"Services"
        }
    ],
    "sg:phone":"+1 972 228 9902",
    "sg:postcode":"75115",
    "sg:province":"TX",
    "wof:name":"Frank L Pope & Assoc",
    "wof:placetype":"venue"
},
  "geometry": {"coordinates":[-96.838669,32.610829],"type":"Point"}
}