{
  "type": "Feature",
  "properties": {
    "iso:country":"US",
    "sg:address":"10200 Grogans Mill Rd",
    "sg:city":"Spring",
    "sg:classifiers":[
        {
            "category":"Building & Trades",
            "subcategory":"Construction",
            "type":"Services"
        }
    ],
    "sg:phone":"+1 281 419 7111",
    "sg:postcode":"77380",
    "sg:province":"TX",
    "sg:tags":[
        "contractor"
    ],
    "wof:name":"Vantage Builders Of Texas",
    "wof:placetype":"venue"
},
  "geometry": {"coordinates":[-95.47203399999999,30.157007],"type":"Point"}
}