{
  "type": "Feature",
  "properties": {
    "iso:country":"US",
    "sg:address":"202 Colorado St",
    "sg:city":"Austin",
    "sg:classifiers":[
        {
            "category":"Shopping",
            "subcategory":"Clothing, Apparel, & Fashions",
            "type":"Retail Goods"
        },
        {
            "category":"Shopping",
            "subcategory":"Shoes",
            "type":"Retail Goods"
        }
    ],
    "sg:phone":"+1 512 477 1559",
    "sg:postcode":"78701",
    "sg:province":"TX",
    "sg:tags":[
        "men's",
        "clothing",
        "store",
        "women's"
    ],
    "wof:name":"Legs Diamond",
    "wof:placetype":"venue"
},
  "geometry": {"coordinates":[-97.74543799999999,30.264814],"type":"Point"}
}