{
  "type": "Feature",
  "properties": {
    "iso:country":"US",
    "sg:address":"311 N Main Ave",
    "sg:city":"Denver City",
    "sg:classifiers":[
        {
            "category":"Personal",
            "subcategory":"Beauty Salon",
            "type":"Services"
        }
    ],
    "sg:phone":"+1 806 592 5192",
    "sg:postcode":"79323",
    "sg:province":"TX",
    "sg:tags":[
        "shop"
    ],
    "wof:name":"Emma's Hairshop",
    "wof:placetype":"venue"
},
  "geometry": {"coordinates":[-102.829307,32.967792],"type":"Point"}
}