{
  "type": "Feature",
  "properties": {
    "iso:country":"US",
    "sg:address":"2515 Stanford St",
    "sg:city":"Greenville",
    "sg:classifiers":[
        {
            "category":"Home & Garden",
            "subcategory":"Carpets & Floor Coverings",
            "type":"Retail Goods"
        }
    ],
    "sg:phone":"+1 903 454 2878",
    "sg:postcode":"75401",
    "sg:province":"TX",
    "wof:name":"Floors By Reeves Brothers",
    "wof:placetype":"venue"
},
  "geometry": {"coordinates":[-96.106683,33.125057],"type":"Point"}
}