{
  "type": "Feature",
  "properties": {
    "iso:country":"US",
    "sg:address":"8419 Stella Link Rd",
    "sg:city":"Houston",
    "sg:classifiers":[
        {
            "category":"Retail",
            "subcategory":"Laundry & Dry Cleaning",
            "type":"Services"
        }
    ],
    "sg:phone":"+1 713 349 8990",
    "sg:postcode":"77025",
    "sg:province":"TX",
    "sg:tags":[
        "drycleaning",
        "plant"
    ],
    "wof:name":"V T Cleaners",
    "wof:placetype":"venue"
},
  "geometry": {"coordinates":[-95.439903,29.692101],"type":"Point"}
}