{
  "type": "Feature",
  "properties": {
    "iso:country":"US",
    "sg:address":"1811 W Kuhn St",
    "sg:city":"Edinburg",
    "sg:classifiers":[
        {
            "category":"Real Estate",
            "subcategory":"Real Estate Services",
            "type":"Services"
        },
        {
            "category":"Real Estate",
            "subcategory":"Real Estate Operator",
            "type":"Services"
        }
    ],
    "sg:phone":"+1 956 380 0046",
    "sg:postcode":"78541",
    "sg:province":"TX",
    "sg:tags":[
        "vacancy",
        "apartment",
        "rental",
        "listing"
    ],
    "wof:name":"Oak Tree Apartments",
    "wof:placetype":"venue"
},
  "geometry": {"coordinates":[-98.180179,26.306071],"type":"Point"}
}