{
  "type": "Feature",
  "properties": {
    "iso:country":"US",
    "sg:address":"6751 Rufe Snow Dr",
    "sg:city":"Fort Worth",
    "sg:classifiers":[
        {
            "category":"Education",
            "subcategory":"Dance Studio",
            "type":"Public Place"
        }
    ],
    "sg:phone":"+1 817 485 3284",
    "sg:postcode":"76148",
    "sg:province":"TX",
    "sg:tags":[
        "instruction",
        "dancing"
    ],
    "wof:name":"Act One Dance Studio",
    "wof:placetype":"venue"
},
  "geometry": {"coordinates":[-97.23792299999999,32.872245],"type":"Point"}
}