{
  "type": "Feature",
  "properties": {
    "iso:country":"US",
    "sg:address":"1411 Campbell Rd",
    "sg:city":"Houston",
    "sg:classifiers":[
        {
            "category":"Wholesale",
            "subcategory":"Durable Goods & Equipment",
            "type":"Manufacturing & Wholesale Goods"
        }
    ],
    "sg:phone":"+1 281 575 1759",
    "sg:postcode":"77055",
    "sg:province":"TX",
    "sg:tags":[
        "representative",
        "manufacturer"
    ],
    "sg:website":"www.airmail.net",
    "wof:name":"Jim D Gray & Assoc Inc",
    "wof:placetype":"venue"
},
  "geometry": {"coordinates":[-95.513991,29.794587],"type":"Point"}
}