{
  "type": "Feature",
  "properties": {
    "iso:country":"US",
    "sg:address":"5098 Stitzle Rd",
    "sg:city":"Crandall",
    "sg:classifiers":[
        {
            "category":"Shopping",
            "subcategory":"Used Merchandise",
            "type":"Retail Goods"
        }
    ],
    "sg:phone":"+1 972 427 3801",
    "sg:postcode":"75114",
    "sg:province":"TX",
    "wof:name":"One Time Cad Service",
    "wof:placetype":"venue"
},
  "geometry": {"coordinates":[-96.38900599999999,32.638795],"type":"Point"}
}