{
  "type": "Feature",
  "properties": {
    "iso:country":"US",
    "sg:address":"3441 Spencer Hwy",
    "sg:city":"Pasadena",
    "sg:classifiers":[
        {
            "category":"Personal",
            "subcategory":"Beauty Salon",
            "type":"Services"
        }
    ],
    "sg:phone":"+1 713 943 0216",
    "sg:postcode":"77504",
    "sg:province":"TX",
    "sg:tags":[
        "notary"
    ],
    "wof:name":"Kosmos Hair Styling",
    "wof:placetype":"venue"
},
  "geometry": {"coordinates":[-95.190783,29.665105],"type":"Point"}
}