{
  "type": "Feature",
  "properties": {
    "iso:country":"US",
    "sg:address":"607 S Wisteria St",
    "sg:city":"Mansfield",
    "sg:classifiers":[
        {
            "category":"Manufacturing",
            "subcategory":"Paper Products",
            "type":"Manufacturing & Wholesale Goods"
        }
    ],
    "sg:phone":"+1 817 473 2992",
    "sg:postcode":"76063",
    "sg:province":"TX",
    "sg:tags":[
        "box",
        "folding",
        "pa",
        "paperboard",
        "mfg"
    ],
    "wof:name":"American Carton Company Inc",
    "wof:placetype":"venue"
},
  "geometry": {"coordinates":[-97.120935,32.553722],"type":"Point"}
}