{
  "type": "Feature",
  "properties": {
    "iso:country":"US",
    "sg:address":"326 Co Rd 318",
    "sg:city":"Abilene",
    "sg:classifiers":[
        {
            "category":"Utilities",
            "subcategory":"Cable",
            "type":"Services"
        }
    ],
    "sg:phone":"+1 325 695 9388",
    "sg:postcode":"79606",
    "sg:province":"TX",
    "sg:tags":[
        "satellite",
        "carrier"
    ],
    "wof:name":"Westexas Satellite Svc",
    "wof:placetype":"venue"
},
  "geometry": {"coordinates":[-99.844644,32.37634],"type":"Point"}
}