{
  "type": "Feature",
  "properties": {
    "iso:country":"US",
    "sg:address":"5680 State Hwy 6",
    "sg:city":"Missouri City",
    "sg:classifiers":[
        {
            "category":"Shopping",
            "type":"Retail Goods"
        }
    ],
    "sg:phone":"+1 832 277 0441",
    "sg:postcode":"77459",
    "sg:province":"TX",
    "sg:tags":[
        "communication"
    ],
    "wof:name":"Freedom Communication Services",
    "wof:placetype":"venue"
},
  "geometry": {"coordinates":[-95.57079400000001,29.572057],"type":"Point"}
}