{
  "type": "Feature",
  "properties": {
    "iso:country":"US",
    "sg:address":"527 W Erwin St",
    "sg:city":"Tyler",
    "sg:classifiers":[
        {
            "category":"Autos & Motor Vehicles",
            "subcategory":"Automobile Sales",
            "type":"Retail Goods"
        }
    ],
    "sg:phone":"+1 903 595 4531",
    "sg:postcode":"75702",
    "sg:province":"TX",
    "sg:tags":[
        "car",
        "dealer"
    ],
    "sg:website":"www.kingchevrolet.com",
    "wof:name":"King Chevrolet",
    "wof:placetype":"venue"
},
  "geometry": {"coordinates":[-95.307023,32.350799],"type":"Point"}
}