{
  "type": "Feature",
  "properties": {
    "iso:country":"US",
    "sg:address":"423 E Ledbetter Dr",
    "sg:city":"Dallas",
    "sg:classifiers":[
        {
            "category":"Wholesale",
            "subcategory":"Machinery & Supplies",
            "type":"Manufacturing & Wholesale Goods"
        }
    ],
    "sg:phone":"+1 214 341 3644",
    "sg:postcode":"75216",
    "sg:province":"TX",
    "sg:tags":[
        "equipment",
        "establishment"
    ],
    "wof:name":"All U Need One Stop Beauty Sup",
    "wof:placetype":"venue"
},
  "geometry": {"coordinates":[-96.817684,32.684332],"type":"Point"}
}