{
  "type": "Feature",
  "properties": {
    "iso:country":"US",
    "sg:address":"4722 Rittiman Rd",
    "sg:city":"San Antonio",
    "sg:classifiers":[
        {
            "category":"Bars & Pubs",
            "type":"Food & Drink"
        }
    ],
    "sg:phone":"+1 210 661 8885",
    "sg:postcode":"78218",
    "sg:province":"TX",
    "sg:tags":[
        "club",
        "night"
    ],
    "wof:name":"Club Royal",
    "wof:placetype":"venue"
},
  "geometry": {"coordinates":[-98.39345400000001,29.484144],"type":"Point"}
}