{
  "type": "Feature",
  "properties": {
    "iso:country":"US",
    "sg:address":"3827 Phelan Blvd",
    "sg:city":"Beaumont",
    "sg:classifiers":[
        {
            "category":"Freight",
            "type":"Transportation"
        }
    ],
    "sg:phone":"+1 409 839 8390",
    "sg:postcode":"77707",
    "sg:province":"TX",
    "sg:tags":[
        "delivery",
        "operator",
        "local",
        "business",
        "trucking"
    ],
    "wof:name":"Hot Shot Paperworks & Parcels",
    "wof:placetype":"venue"
},
  "geometry": {"coordinates":[-94.141204,30.084584],"type":"Point"}
}