{
  "type": "Feature",
  "properties": {
    "iso:country":"US",
    "sg:address":"11227 Goodnight Ln",
    "sg:city":"Dallas",
    "sg:classifiers":[
        {
            "category":"Manufacturing",
            "subcategory":"Textiles",
            "type":"Manufacturing & Wholesale Goods"
        },
        {
            "category":"Manufacturing",
            "subcategory":"Printing",
            "type":"Manufacturing & Wholesale Goods"
        }
    ],
    "sg:phone":"+1 972 620 9440",
    "sg:postcode":"75229",
    "sg:province":"TX",
    "sg:tags":[
        "plant",
        "fiber",
        "screen",
        "commercial",
        "finishing",
        "silk"
    ],
    "wof:name":"Quality Screen Printing",
    "wof:placetype":"venue"
},
  "geometry": {"coordinates":[-96.901949,32.890051],"type":"Point"}
}