{
  "type": "Feature",
  "properties": {
    "iso:country":"US",
    "sg:address":"12217 Lake Stone Dr",
    "sg:city":"Austin",
    "sg:classifiers":[
        {
            "category":"Professional",
            "subcategory":"Management & Consulting",
            "type":"Services"
        }
    ],
    "sg:phone":"+1 512 263 8007",
    "sg:postcode":"78738",
    "sg:province":"TX",
    "sg:tags":[
        "business"
    ],
    "wof:name":"Ntelegence Inc",
    "wof:placetype":"venue"
},
  "geometry": {"coordinates":[-97.92055000000001,30.31563],"type":"Point"}
}