{
  "type": "Feature",
  "properties": {
    "iso:country":"US",
    "sg:address":"2711 N Haskell Ave Ste 100",
    "sg:city":"Dallas",
    "sg:classifiers":[
        {
            "category":"Shopping",
            "subcategory":"Computers & Home Electronics",
            "type":"Retail Goods"
        }
    ],
    "sg:phone":"+1 214 828 7050",
    "sg:postcode":"75204",
    "sg:province":"TX",
    "wof:name":"Cityplace Conference Ctr",
    "wof:placetype":"venue"
},
  "geometry": {"coordinates":[-96.791702,32.806301],"type":"Point"}
}