{
  "type": "Feature",
  "properties": {
    "iso:country":"US",
    "sg:address":"3525 Burnet Dr",
    "sg:city":"Plano",
    "sg:classifiers":[
        {
            "category":"Utilities",
            "subcategory":"Telephone",
            "type":"Services"
        }
    ],
    "sg:phone":"+1 972 712 6479",
    "sg:postcode":"75025",
    "sg:province":"TX",
    "sg:tags":[
        "telecommunication"
    ],
    "wof:name":"Genesys Telecommunications",
    "wof:placetype":"venue"
},
  "geometry": {"coordinates":[-96.76070300000001,33.106213],"type":"Point"}
}