{
  "type": "Feature",
  "properties": {
    "iso:country":"US",
    "sg:address":"1430 Bradley Ln",
    "sg:city":"Carrollton",
    "sg:classifiers":[
        {
            "category":"Freight",
            "type":"Transportation"
        }
    ],
    "sg:phone":"+1 972 242 8864",
    "sg:postcode":"75007",
    "sg:province":"TX",
    "sg:tags":[
        "warehouse",
        "storage"
    ],
    "wof:name":"Servicecraft Dallas",
    "wof:placetype":"venue"
},
  "geometry": {"coordinates":[-96.92173699999999,32.9912],"type":"Point"}
}