{
  "type": "Feature",
  "properties": {
    "iso:country":"US",
    "sg:address":"16016 Arbor Trl",
    "sg:city":"Buda",
    "sg:classifiers":[
        {
            "category":"Building & Trades",
            "subcategory":"Construction",
            "type":"Services"
        }
    ],
    "sg:phone":"+1 512 295 4054",
    "sg:postcode":"78610",
    "sg:province":"TX",
    "sg:tags":[
        "painter"
    ],
    "wof:name":"Bates Painting Inc",
    "wof:placetype":"venue"
},
  "geometry": {"coordinates":[-97.91280399999999,30.1159],"type":"Point"}
}