{
  "type": "Feature",
  "properties": {
    "iso:country":"US",
    "sg:address":"1111 Vis Valet",
    "sg:city":"San Antonio",
    "sg:classifiers":[
        {
            "category":"Health Services",
            "subcategory":"Chiropractor",
            "type":"Services"
        }
    ],
    "sg:phone":"+1 210 764 1573",
    "sg:postcode":"78216",
    "sg:province":"TX",
    "wof:name":"Spiro Ioannidis D C P C",
    "wof:placetype":"venue"
},
  "geometry": {"coordinates":[-98.512252,29.558831],"type":"Point"}
}