{
  "type": "Feature",
  "properties": {
    "iso:country":"US",
    "sg:address":"2348 Texas St",
    "sg:city":"Pecos",
    "sg:classifiers":[
        {
            "category":"Health Services",
            "subcategory":"Doctor",
            "type":"Services"
        }
    ],
    "sg:phone":"+1 432 447 4155",
    "sg:postcode":"79772",
    "sg:province":"TX",
    "sg:tags":[
        "medical"
    ],
    "wof:name":"Jseph K Darpolor Fmly Practice",
    "wof:placetype":"venue"
},
  "geometry": {"coordinates":[-103.51288700000001,31.400904],"type":"Point"}
}