{
  "type": "Feature",
  "properties": {
    "iso:country":"US",
    "sg:address":"401 W 5th St",
    "sg:city":"Lampasas",
    "sg:classifiers":[
        {
            "category":"Building & Trades",
            "subcategory":"Plumbing",
            "type":"Services"
        }
    ],
    "sg:phone":"+1 512 556 8183",
    "sg:postcode":"76550",
    "sg:province":"TX",
    "sg:tags":[
        "plumber"
    ],
    "wof:name":"Badgers Den",
    "wof:placetype":"venue"
},
  "geometry": {"coordinates":[-98.18483000000001,31.06193],"type":"Point"}
}