{
  "type": "Feature",
  "properties": {
    "iso:country":"US",
    "sg:address":"19122 US Hwy 69",
    "sg:city":"Lindale",
    "sg:classifiers":[
        {
            "category":"Home & Garden",
            "subcategory":"Garden Supply",
            "type":"Retail Goods"
        }
    ],
    "sg:phone":"+1 903 881 0600",
    "sg:postcode":"75771",
    "sg:province":"TX",
    "sg:tags":[
        "nurseryman"
    ],
    "wof:name":"R & T Quality Nursery",
    "wof:placetype":"venue"
},
  "geometry": {"coordinates":[-95.421308,32.548236],"type":"Point"}
}