{
  "type": "Feature",
  "properties": {
    "iso:country":"US",
    "sg:address":"7000 Cook Rd",
    "sg:city":"Houston",
    "sg:classifiers":[
        {
            "category":"Freight",
            "type":"Transportation"
        }
    ],
    "sg:phone":"+1 281 564 3676",
    "sg:postcode":"77072",
    "sg:province":"TX",
    "sg:tags":[
        "operator",
        "local",
        "trucking"
    ],
    "wof:name":"Stewart Enterprise Trucking Di",
    "wof:placetype":"venue"
},
  "geometry": {"coordinates":[-95.59618500000001,29.700627],"type":"Point"}
}