{
  "type": "Feature",
  "properties": {
    "iso:country":"US",
    "sg:address":"3120 N Eastman Rd",
    "sg:city":"Longview",
    "sg:classifiers":[
        {
            "category":"Professional",
            "subcategory":"Business Services",
            "type":"Services"
        }
    ],
    "sg:phone":"+1 903 753 7296",
    "sg:postcode":"75605",
    "sg:province":"TX",
    "wof:name":"Auto Damage Appraisers E Texas",
    "wof:placetype":"venue"
},
  "geometry": {"coordinates":[-94.723355,32.535786],"type":"Point"}
}