{
  "type": "Feature",
  "properties": {
    "iso:country":"US",
    "sg:address":"1407 N Travis Ave",
    "sg:city":"Cameron",
    "sg:classifiers":[
        {
            "category":"Autos & Motor Vehicles",
            "subcategory":"Auto Supplies",
            "type":"Retail Goods"
        }
    ],
    "sg:phone":"+1 254 697 2971",
    "sg:postcode":"76520",
    "sg:province":"TX",
    "wof:name":"Cameron Tire Store",
    "wof:placetype":"venue"
},
  "geometry": {"coordinates":[-96.97430300000001,30.860972],"type":"Point"}
}