{
  "type": "Feature",
  "properties": {
    "iso:country":"US",
    "sg:address":"104 Main St",
    "sg:city":"La Marque",
    "sg:classifiers":[
        {
            "category":"Bars & Pubs",
            "type":"Food & Drink"
        }
    ],
    "sg:phone":"+1 409 935 9939",
    "sg:postcode":"77568",
    "sg:province":"TX",
    "sg:tags":[
        "drinking"
    ],
    "wof:name":"Murphy's On Main",
    "wof:placetype":"venue"
},
  "geometry": {"coordinates":[-94.95038599999999,29.358331],"type":"Point"}
}