{
  "type": "Feature",
  "properties": {
    "iso:country":"US",
    "sg:address":"9402 State Hwy 6",
    "sg:city":"Houston",
    "sg:classifiers":[
        {
            "category":"Shopping",
            "subcategory":"Pharmacy",
            "type":"Retail Goods"
        }
    ],
    "sg:phone":"+1 281 495 3062",
    "sg:postcode":"77083",
    "sg:province":"TX",
    "wof:name":"Kroger",
    "wof:placetype":"venue"
},
  "geometry": {"coordinates":[-95.64347600000001,29.677147],"type":"Point"}
}