{
  "type": "Feature",
  "properties": {
    "iso:country":"US",
    "sg:address":"1025 W Airport Fwy",
    "sg:city":"Irving",
    "sg:classifiers":[
        {
            "category":"Autos & Motor Vehicles",
            "subcategory":"Fuel & Gas Station",
            "type":"Retail Goods"
        }
    ],
    "sg:phone":"+1 210 821 5900",
    "sg:postcode":"75062",
    "sg:province":"TX",
    "sg:tags":[
        "station",
        "gasoline"
    ],
    "wof:name":"Tetco Stores Inc",
    "wof:placetype":"venue"
},
  "geometry": {"coordinates":[-96.95718100000001,32.837375],"type":"Point"}
}