{
  "type": "Feature",
  "properties": {
    "iso:country":"US",
    "sg:address":"3450 Boca Chica Blvd. Ste. 2",
    "sg:city":"Brownsville",
    "sg:phone":"+1 956 554 0805",
    "sg:postcode":"78521",
    "sg:province":"TX",
    "sg:website":"http://www.casadenoviasmiranda.com",
    "wof:name":"Casa De Novias Miranda",
    "wof:placetype":"venue"
},
  "geometry": {"coordinates":[-97.46495299999999,25.920076],"type":"Point"}
}