{
  "type": "Feature",
  "properties": {
    "iso:country":"US",
    "sg:address":"21146 State Hwy 155",
    "sg:city":"Flint",
    "sg:classifiers":[
        {
            "category":"Shopping",
            "subcategory":"Gifts & Souvenirs",
            "type":"Retail Goods"
        }
    ],
    "sg:phone":"+1 903 825 2259",
    "sg:postcode":"75762",
    "sg:province":"TX",
    "sg:tags":[
        "used",
        "merchandise",
        "furniture"
    ],
    "wof:name":"Chantillys Gifts and Home Furn",
    "wof:placetype":"venue"
},
  "geometry": {"coordinates":[-95.4516,32.174023],"type":"Point"}
}