{
  "type": "Feature",
  "properties": {
    "iso:country":"US",
    "sg:address":"302 Kurth Dr",
    "sg:city":"Lufkin",
    "sg:classifiers":[
        {
            "category":"Restaurant",
            "type":"Food & Drink"
        }
    ],
    "sg:phone":"+1 936 634 9959",
    "sg:postcode":"75904",
    "sg:province":"TX",
    "wof:name":"Lufkin's Finest Soul Food",
    "wof:placetype":"venue"
},
  "geometry": {"coordinates":[-94.723972,31.355216],"type":"Point"}
}