{
  "type": "Feature",
  "properties": {
    "iso:country":"US",
    "sg:address":"3010 Parkwood Dr",
    "sg:city":"Baytown",
    "sg:classifiers":[
        {
            "category":"Professional",
            "type":"Services"
        }
    ],
    "sg:phone":"+1 281 422 4659",
    "sg:postcode":"77521",
    "sg:province":"TX",
    "wof:name":"Gloria J Naiser",
    "wof:placetype":"venue"
},
  "geometry": {"coordinates":[-94.931663,29.775332],"type":"Point"}
}