{
  "type": "Feature",
  "properties": {
    "iso:country":"US",
    "sg:address":"1914 Lindell Ave",
    "sg:city":"San Angelo",
    "sg:classifiers":[
        {
            "category":"Shopping",
            "subcategory":"Gifts & Souvenirs",
            "type":"Retail Goods"
        }
    ],
    "sg:phone":"+1 325 944 4289",
    "sg:postcode":"76901",
    "sg:province":"TX",
    "wof:name":"Gracie Rushing",
    "wof:placetype":"venue"
},
  "geometry": {"coordinates":[-100.47221500000001,31.466],"type":"Point"}
}