{
  "type": "Feature",
  "properties": {
    "iso:country":"US",
    "sg:address":"1518 Holbech Ln",
    "sg:city":"Channelview",
    "sg:classifiers":[
        {
            "category":"Building & Trades",
            "subcategory":"Landscaping Services",
            "type":"Services"
        }
    ],
    "sg:phone":"+1 281 452 0161",
    "sg:postcode":"77530",
    "sg:province":"TX",
    "wof:name":"Dansbys Tractor Services",
    "wof:placetype":"venue"
},
  "geometry": {"coordinates":[-95.15131100000001,29.804119],"type":"Point"}
}