{
  "type": "Feature",
  "properties": {
    "iso:country":"US",
    "sg:address":"1 World of Tennis Sq",
    "sg:city":"Lakeway",
    "sg:classifiers":[
        {
            "category":"Restaurant",
            "type":"Food & Drink"
        }
    ],
    "sg:phone":"+1 512 261 7274",
    "sg:postcode":"78738",
    "sg:province":"TX",
    "wof:name":"Courtview Restaurant",
    "wof:placetype":"venue"
},
  "geometry": {"coordinates":[-97.996979,30.350697],"type":"Point"}
}