{
  "type": "Feature",
  "properties": {
    "iso:country":"US",
    "sg:address":"9002 Woodlawn Dr",
    "sg:city":"Granbury",
    "sg:classifiers":[
        {
            "category":"Shopping",
            "subcategory":"Used Merchandise",
            "type":"Retail Goods"
        }
    ],
    "sg:phone":"+1 817 573 5675",
    "sg:postcode":"76049",
    "sg:province":"TX",
    "wof:name":"Hortons Antiques",
    "wof:placetype":"venue"
},
  "geometry": {"coordinates":[-97.67662300000001,32.356609],"type":"Point"}
}