{
  "type": "Feature",
  "properties": {
    "iso:country":"US",
    "sg:address":"11423 Lemond Dr",
    "sg:city":"Houston",
    "sg:classifiers":[
        {
            "category":"Professional",
            "subcategory":"Accounting & Tax Preparation",
            "type":"Services"
        }
    ],
    "sg:phone":"+1 281 442 4988",
    "sg:postcode":"77016",
    "sg:province":"TX",
    "wof:name":"Johnnie & Co",
    "wof:placetype":"venue"
},
  "geometry": {"coordinates":[-95.291011,29.8867],"type":"Point"}
}