{
  "type": "Feature",
  "properties": {
    "iso:country":"US",
    "sg:address":"114 Chaparral Dr",
    "sg:city":"Floresville",
    "sg:classifiers":[
        {
            "category":"Professional",
            "subcategory":"Detective & Security Services",
            "type":"Services"
        }
    ],
    "sg:phone":"+1 210 394 5298",
    "sg:postcode":"78114",
    "sg:province":"TX",
    "sg:tags":[
        "car"
    ],
    "wof:name":"Chaparral Investigations",
    "wof:placetype":"venue"
},
  "geometry": {"coordinates":[-98.209444,29.244017],"type":"Point"}
}