{
  "type": "Feature",
  "properties": {
    "iso:country":"US",
    "sg:address":"302 Tillery Sq",
    "sg:city":"Austin",
    "sg:classifiers":[
        {
            "category":"Restaurant",
            "type":"Food & Drink"
        }
    ],
    "sg:phone":"+1 512 386 5670",
    "sg:postcode":"78702",
    "sg:province":"TX",
    "sg:tags":[
        "eating"
    ],
    "wof:name":"Delightfully Blessed",
    "wof:placetype":"venue"
},
  "geometry": {"coordinates":[-97.70854799999999,30.2538],"type":"Point"}
}