{
  "type": "Feature",
  "properties": {
    "iso:country":"US",
    "sg:address":"11065 FM 720",
    "sg:city":"Frisco",
    "sg:classifiers":[
        {
            "category":"Food & Beverages",
            "subcategory":"Groceries & Convenience Stores",
            "type":"Retail Goods"
        }
    ],
    "sg:phone":"+1 214 387 4964",
    "sg:postcode":"75035",
    "sg:province":"TX",
    "wof:name":"7-Eleven",
    "wof:placetype":"venue"
},
  "geometry": {"coordinates":[-96.783171,33.152714],"type":"Point"}
}