{
  "type": "Feature",
  "properties": {
    "iso:country":"US",
    "sg:address":"2103 S Ong St",
    "sg:city":"Amarillo",
    "sg:classifiers":[
        {
            "category":"Professional",
            "subcategory":"Business Services",
            "type":"Services"
        }
    ],
    "sg:phone":"+1 806 379 9152",
    "sg:postcode":"79109",
    "sg:province":"TX",
    "wof:name":"Bar/S Group Inc",
    "wof:placetype":"venue"
},
  "geometry": {"coordinates":[-101.852074,35.189254],"type":"Point"}
}