{
  "type": "Feature",
  "properties": {
    "iso:country":"US",
    "sg:address":"495 Minnesota Rd",
    "sg:city":"Mission",
    "sg:classifiers":[
        {
            "category":"Retail",
            "subcategory":"Auto Repair",
            "type":"Services"
        }
    ],
    "sg:phone":"+1 956 581 3562",
    "sg:postcode":"78572",
    "sg:province":"TX",
    "sg:tags":[
        "wrecker"
    ],
    "wof:name":"Premiere Wrecker Svc",
    "wof:placetype":"venue"
},
  "geometry": {"coordinates":[-98.37990499999999,26.236722],"type":"Point"}
}