{
  "type": "Feature",
  "properties": {
    "iso:country":"US",
    "sg:address":"1012 Symonds Pl",
    "sg:city":"Stamford",
    "sg:classifiers":[
        {
            "category":"Farming",
            "subcategory":"Farm & Veterinary Services",
            "type":"Manufacturing & Wholesale Goods"
        }
    ],
    "sg:phone":"+1 325 773 5045",
    "sg:postcode":"79553",
    "sg:province":"TX",
    "sg:tags":[
        "crop",
        "harvesting"
    ],
    "wof:name":"Hughes Custom Harvesting",
    "wof:placetype":"venue"
},
  "geometry": {"coordinates":[-99.789565,32.939051],"type":"Point"}
}