{
  "type": "Feature",
  "properties": {
    "iso:country":"US",
    "sg:address":"1130 SW Military Dr",
    "sg:city":"San Antonio",
    "sg:classifiers":[
        {
            "category":"Professional",
            "subcategory":"Lawyer & Legal Services",
            "type":"Services"
        }
    ],
    "sg:phone":"+1 210 226 2122",
    "sg:postcode":"78221",
    "sg:province":"TX",
    "sg:tags":[
        "law"
    ],
    "wof:name":"Law Office Manuel E Solis PC",
    "wof:placetype":"venue"
},
  "geometry": {"coordinates":[-98.510379,29.356598],"type":"Point"}
}