{
  "type": "Feature",
  "properties": {
    "iso:country":"US",
    "sg:address":"605 Holt St",
    "sg:city":"Bryan",
    "sg:classifiers":[
        {
            "category":"Organizations",
            "subcategory":"Religious Organization",
            "type":"Services"
        }
    ],
    "sg:phone":"+1 979 823 1735",
    "sg:postcode":"77803",
    "sg:province":"TX",
    "wof:name":"Shalom Ministries",
    "wof:placetype":"venue"
},
  "geometry": {"coordinates":[-96.382452,30.670878],"type":"Point"}
}