{
  "type": "Feature",
  "properties": {
    "iso:country":"US",
    "sg:address":"1009 W Harwood Rd",
    "sg:city":"Euless",
    "sg:classifiers":[
        {
            "category":"Food & Beverages",
            "subcategory":"Bakery",
            "type":"Retail Goods"
        }
    ],
    "sg:phone":"+1 817 283 2288",
    "sg:postcode":"76039",
    "sg:province":"TX",
    "sg:tags":[
        "doughnut"
    ],
    "wof:name":"Donut Palace",
    "wof:placetype":"venue"
},
  "geometry": {"coordinates":[-97.09889699999999,32.851759],"type":"Point"}
}