{
  "type": "Feature",
  "properties": {
    "iso:country":"US",
    "sg:address":"Wal-Mart",
    "sg:city":"Austin",
    "sg:classifiers":[
        {
            "category":"Shopping",
            "subcategory":"Department Store",
            "type":"Retail Goods"
        }
    ],
    "sg:phone":"+1 512 249 5690",
    "sg:postcode":"78701",
    "sg:province":"TX",
    "wof:name":"Smartstyle",
    "wof:placetype":"venue"
},
  "geometry": {"coordinates":[-97.743604,30.269853],"type":"Point"}
}