{
  "type": "Feature",
  "properties": {
    "iso:country":"US",
    "sg:address":"521 Benito St",
    "sg:city":"Rio Grande City",
    "sg:classifiers":[
        {
            "category":"Building & Trades",
            "subcategory":"Construction",
            "type":"Services"
        }
    ],
    "sg:phone":"+1 956 488 0420",
    "sg:postcode":"78582",
    "sg:province":"TX",
    "sg:tags":[
        "marking",
        "maintenance",
        "parking"
    ],
    "wof:name":"South Texas Striping",
    "wof:placetype":"venue"
},
  "geometry": {"coordinates":[-98.637986,26.300665],"type":"Point"}
}