{
  "type": "Feature",
  "properties": {
    "iso:country":"US",
    "sg:address":"701 W 6th St",
    "sg:city":"Plainview",
    "sg:classifiers":[
        {
            "category":"Wholesale",
            "subcategory":"Machinery & Supplies",
            "type":"Manufacturing & Wholesale Goods"
        }
    ],
    "sg:phone":"+1 806 293 0100",
    "sg:postcode":"79072",
    "sg:province":"TX",
    "sg:tags":[
        "industrial"
    ],
    "wof:name":"Motion Industries Inc",
    "wof:placetype":"venue"
},
  "geometry": {"coordinates":[-101.712688,34.185579],"type":"Point"}
}