{
  "type": "Feature",
  "properties": {
    "iso:country":"US",
    "sg:address":"5214 Burleson Rd",
    "sg:city":"Austin",
    "sg:classifiers":[
        {
            "category":"Building & Trades",
            "subcategory":"Construction",
            "type":"Services"
        }
    ],
    "sg:phone":"+1 512 326 3215",
    "sg:postcode":"78744",
    "sg:province":"TX",
    "sg:tags":[
        "bathroom",
        "remodeling"
    ],
    "wof:name":"Re-Bath",
    "wof:placetype":"venue"
},
  "geometry": {"coordinates":[-97.725447,30.20984],"type":"Point"}
}