{
  "type": "Feature",
  "properties": {
    "iso:country":"US",
    "sg:address":"6811 N Eldridge Pkwy",
    "sg:city":"Houston",
    "sg:classifiers":[
        {
            "category":"Building & Trades",
            "subcategory":"Construction",
            "type":"Services"
        }
    ],
    "sg:phone":"+1 713 849 9123",
    "sg:postcode":"77041",
    "sg:province":"TX",
    "sg:tags":[
        "contractor"
    ],
    "wof:name":"Prestige Auto Center",
    "wof:placetype":"venue"
},
  "geometry": {"coordinates":[-95.60847099999999,29.869994],"type":"Point"}
}