{
  "type": "Feature",
  "properties": {
    "iso:country":"US",
    "sg:address":"1504 E Mockingbird Ln",
    "sg:city":"Victoria",
    "sg:classifiers":[
        {
            "category":"Professional",
            "subcategory":"Management & Consulting",
            "type":"Services"
        }
    ],
    "sg:phone":"+1 361 573 4096",
    "sg:postcode":"77904",
    "sg:province":"TX",
    "sg:tags":[
        "business"
    ],
    "wof:name":"Cbt Business Group",
    "wof:placetype":"venue"
},
  "geometry": {"coordinates":[-96.991337,28.836031],"type":"Point"}
}