{
  "type": "Feature",
  "properties": {
    "iso:country":"US",
    "sg:address":"8001 Burgoyne Rd",
    "sg:city":"Houston",
    "sg:classifiers":[
        {
            "category":"Real Estate",
            "subcategory":"Developer",
            "type":"Services"
        }
    ],
    "sg:phone":"+1 713 914 8105",
    "sg:postcode":"77063",
    "sg:province":"TX",
    "wof:name":"Sorefim International Inc",
    "wof:placetype":"venue"
},
  "geometry": {"coordinates":[-95.505898,29.742551],"type":"Point"}
}