{
  "type": "Feature",
  "properties": {
    "iso:country":"US",
    "sg:address":"2702 Forrest Ave",
    "sg:city":"Abilene",
    "sg:classifiers":[
        {
            "category":"Organizations",
            "subcategory":"Religious Organization",
            "type":"Services"
        }
    ],
    "sg:phone":"+1 325 672 1337",
    "sg:postcode":"79603",
    "sg:province":"TX",
    "wof:name":"Oakland Drive Church Of Christ",
    "wof:placetype":"venue"
},
  "geometry": {"coordinates":[-99.749559,32.483124],"type":"Point"}
}