{
  "type": "Feature",
  "properties": {
    "iso:country":"US",
    "sg:address":"1846 Lockhill Selma Rd",
    "sg:city":"San Antonio",
    "sg:classifiers":[
        {
            "category":"Professional",
            "subcategory":"Accounting & Tax Preparation",
            "type":"Services"
        }
    ],
    "sg:phone":"+1 210 377 1040",
    "sg:postcode":"78213",
    "sg:province":"TX",
    "wof:name":"Wilkerson & Associates PC",
    "wof:placetype":"venue"
},
  "geometry": {"coordinates":[-98.52376,29.537524],"type":"Point"}
}