{
  "type": "Feature",
  "properties": {
    "iso:country":"US",
    "sg:address":"606 N Washington St",
    "sg:city":"Round Top",
    "sg:classifiers":[
        {
            "category":"Retail",
            "subcategory":"Repair Shop",
            "type":"Services"
        }
    ],
    "sg:phone":"+1 979 249 4085",
    "sg:postcode":"78954",
    "sg:province":"TX",
    "wof:name":"Round Top Repair Shop",
    "wof:placetype":"venue"
},
  "geometry": {"coordinates":[-96.694441,30.069291],"type":"Point"}
}