{
  "type": "Feature",
  "properties": {
    "iso:country":"US",
    "sg:address":"1217 S Oakes St",
    "sg:city":"San Angelo",
    "sg:classifiers":[
        {
            "category":"Retail",
            "subcategory":"Repair Shop",
            "type":"Services"
        }
    ],
    "sg:phone":"+1 325 655 6182",
    "sg:postcode":"76903",
    "sg:province":"TX",
    "sg:tags":[
        "ironwork"
    ],
    "wof:name":"Ventaire Awning Co",
    "wof:placetype":"venue"
},
  "geometry": {"coordinates":[-100.431837,31.44866],"type":"Point"}
}