{
  "type": "Feature",
  "properties": {
    "iso:country":"US",
    "sg:address":"5362 Bridle Path",
    "sg:city":"Aubrey",
    "sg:classifiers":[
        {
            "category":"Farming",
            "subcategory":"Livestock Farm",
            "type":"Manufacturing & Wholesale Goods"
        }
    ],
    "sg:phone":"+1 940 440 0600",
    "sg:postcode":"76227",
    "sg:province":"TX",
    "sg:tags":[
        "animal",
        "general"
    ],
    "wof:name":"Mc2 Ranch",
    "wof:placetype":"venue"
},
  "geometry": {"coordinates":[-97.016783,33.279164],"type":"Point"}
}