{
  "type": "Feature",
  "properties": {
    "iso:country":"US",
    "sg:address":"4101 FM 2415",
    "sg:city":"Cleburne",
    "sg:classifiers":[
        {
            "category":"Building & Trades",
            "subcategory":"Construction",
            "type":"Services"
        }
    ],
    "sg:phone":"+1 817 641 1545",
    "sg:postcode":"76031",
    "sg:province":"TX",
    "sg:tags":[
        "fence",
        "contractor"
    ],
    "wof:name":"Certified Fence",
    "wof:placetype":"venue"
},
  "geometry": {"coordinates":[-97.288008,32.340029],"type":"Point"}
}