{
  "type": "Feature",
  "properties": {
    "iso:country":"US",
    "sg:address":"520 Pan American Dr",
    "sg:city":"Harker Heights",
    "sg:classifiers":[
        {
            "category":"Restaurant",
            "type":"Food & Drink"
        }
    ],
    "sg:menulink":"http://www.allmenus.com/tx/killeen/70076-pizza-hut/menu/",
    "sg:phone":"+1 254 699 2233",
    "sg:postcode":"76548",
    "sg:province":"TX",
    "sg:tags":[
        "american",
        "pizza"
    ],
    "wof:name":"Pizza Hut",
    "wof:placetype":"venue"
},
  "geometry": {"coordinates":[-97.655732,31.077537],"type":"Point"}
}