{
  "type": "Feature",
  "properties": {
    "iso:country":"US",
    "sg:address":"1531 Karen Dr",
    "sg:city":"Argyle",
    "sg:classifiers":[
        {
            "category":"Shopping",
            "type":"Retail Goods"
        }
    ],
    "sg:phone":"+1 214 616 4868",
    "sg:postcode":"76226",
    "sg:province":"TX",
    "sg:tags":[
        "item",
        "boutique"
    ],
    "wof:name":"Olivia's Boutique",
    "wof:placetype":"venue"
},
  "geometry": {"coordinates":[-97.154922,33.12516],"type":"Point"}
}