{
  "type": "Feature",
  "properties": {
    "iso:country":"US",
    "sg:address":"1225 Central Blvd",
    "sg:city":"Brownsville",
    "sg:classifiers":[
        {
            "category":"Food & Beverages",
            "subcategory":"Specialty",
            "type":"Retail Goods"
        }
    ],
    "sg:phone":"+1 956 550 8386",
    "sg:postcode":"78520",
    "sg:province":"TX",
    "sg:tags":[
        "health",
        "diet"
    ],
    "wof:name":"Shaklee Authorized Distr",
    "wof:placetype":"venue"
},
  "geometry": {"coordinates":[-97.511582,25.925302],"type":"Point"}
}