{
  "type": "Feature",
  "properties": {
    "iso:country":"US",
    "sg:address":"312 Hambrick Rd",
    "sg:city":"Houston",
    "sg:classifiers":[
        {
            "category":"Farming",
            "subcategory":"Farm & Veterinary Services",
            "type":"Manufacturing & Wholesale Goods"
        }
    ],
    "sg:phone":"+1 281 445 0979",
    "sg:postcode":"77060",
    "sg:province":"TX",
    "sg:tags":[
        "livestock"
    ],
    "wof:name":"Black Dog Ranch",
    "wof:placetype":"venue"
},
  "geometry": {"coordinates":[-95.391357,29.909691],"type":"Point"}
}