{
  "type": "Feature",
  "properties": {
    "iso:country":"US",
    "sg:address":"1405 W American Blvd",
    "sg:city":"Muleshoe",
    "sg:classifiers":[
        {
            "category":"Shopping",
            "subcategory":"Bicycles & Sporting Goods",
            "type":"Retail Goods"
        }
    ],
    "sg:phone":"+1 806 272 6853",
    "sg:postcode":"79347",
    "sg:province":"TX",
    "wof:name":"Williams Athletics",
    "wof:placetype":"venue"
},
  "geometry": {"coordinates":[-102.73871,34.234234],"type":"Point"}
}