{
  "type": "Feature",
  "properties": {
    "iso:country":"US",
    "sg:address":"18930 Windsor Lakes Dr",
    "sg:city":"Houston",
    "sg:classifiers":[
        {
            "category":"Banks & Credit Unions",
            "subcategory":"Investment Brokerage",
            "type":"Services"
        }
    ],
    "sg:phone":"+1 281 599 7717",
    "sg:postcode":"77094",
    "sg:province":"TX",
    "sg:tags":[
        "advisory"
    ],
    "wof:name":"American Financial Resources",
    "wof:placetype":"venue"
},
  "geometry": {"coordinates":[-95.70035900000001,29.763218],"type":"Point"}
}