{
  "type": "Feature",
  "properties": {
    "iso:country":"US",
    "sg:address":"13129 Knollcrest St",
    "sg:city":"Houston",
    "sg:classifiers":[
        {
            "category":"Building & Trades",
            "subcategory":"Electrical",
            "type":"Services"
        }
    ],
    "sg:phone":"+1 713 451 7191",
    "sg:postcode":"77015",
    "sg:province":"TX",
    "sg:tags":[
        "electrical",
        "contractor"
    ],
    "wof:name":"R Rocha Electrical Services",
    "wof:placetype":"venue"
},
  "geometry": {"coordinates":[-95.191509,29.778987],"type":"Point"}
}