{
  "type": "Feature",
  "properties": {
    "iso:country":"US",
    "sg:address":"7853 Cup Cir",
    "sg:city":"Dallas",
    "sg:classifiers":[
        {
            "category":"Bars & Pubs",
            "type":"Food & Drink"
        }
    ],
    "sg:phone":"+1 214 398 8097",
    "sg:postcode":"75217",
    "sg:province":"TX",
    "sg:tags":[
        "drinking"
    ],
    "wof:name":"Frogs Leather",
    "wof:placetype":"venue"
},
  "geometry": {"coordinates":[-96.685329,32.69982],"type":"Point"}
}