{
  "type": "Feature",
  "properties": {
    "iso:country":"US",
    "sg:address":"317 Mammoth Springs Ln",
    "sg:city":"Dickinson",
    "sg:classifiers":[
        {
            "category":"Shopping",
            "subcategory":"Hobbies, Toys, & Games",
            "type":"Retail Goods"
        }
    ],
    "sg:phone":"+1 281 309 0515",
    "sg:postcode":"77539",
    "sg:province":"TX",
    "wof:name":"Connye Jo Lenczewski",
    "wof:placetype":"venue"
},
  "geometry": {"coordinates":[-95.096672,29.445418],"type":"Point"}
}