{
  "type": "Feature",
  "properties": {
    "iso:country":"US",
    "sg:address":"406 Janeway Ave",
    "sg:city":"Lufkin",
    "sg:classifiers":[
        {
            "category":"Retail",
            "subcategory":"Auto Repair",
            "type":"Services"
        }
    ],
    "sg:phone":"+1 936 632 6425",
    "sg:postcode":"75904",
    "sg:province":"TX",
    "sg:tags":[
        "glass",
        "coating",
        "tinting"
    ],
    "wof:name":"Mickey's Tint Shop",
    "wof:placetype":"venue"
},
  "geometry": {"coordinates":[-94.73043199999999,31.317068],"type":"Point"}
}