{
  "type": "Feature",
  "properties": {
    "iso:country":"US",
    "sg:address":"402 W 26th St",
    "sg:city":"Bryan",
    "sg:classifiers":[
        {
            "category":"Manufacturing",
            "subcategory":"Lumber",
            "type":"Manufacturing & Wholesale Goods"
        }
    ],
    "sg:phone":"+1 979 822 7296",
    "sg:postcode":"77803",
    "sg:province":"TX",
    "sg:tags":[
        "hardwood",
        "mill"
    ],
    "wof:name":"Ronald M Brimhall",
    "wof:placetype":"venue"
},
  "geometry": {"coordinates":[-96.37724799999999,30.674193],"type":"Point"}
}