{
  "type": "Feature",
  "properties": {
    "iso:country":"US",
    "sg:address":"4510 York St",
    "sg:city":"Wichita Falls",
    "sg:classifiers":[
        {
            "category":"Professional",
            "subcategory":"Secretarial Services",
            "type":"Services"
        }
    ],
    "sg:phone":"+1 940 691 0963",
    "sg:postcode":"76309",
    "sg:province":"TX",
    "sg:tags":[
        "reporting"
    ],
    "wof:name":"Childress Gillespie Arlene",
    "wof:placetype":"venue"
},
  "geometry": {"coordinates":[-98.55812899999999,33.883306],"type":"Point"}
}