{
  "type": "Feature",
  "properties": {
    "iso:country":"US",
    "sg:address":"5040 Commonsgate Blvd",
    "sg:city":"Plano",
    "sg:classifiers":[
        {
            "category":"Social Services",
            "subcategory":"Child Care",
            "type":"Services"
        },
        {
            "category":"Education",
            "subcategory":"Preschool",
            "type":"Public Place"
        },
        {
            "category":"Education",
            "subcategory":"School",
            "type":"Public Place"
        }
    ],
    "sg:phone":"+1 972 403 7766",
    "sg:postcode":"75024",
    "sg:province":"TX",
    "sg:tags":[
        "kindergarten",
        "nursery",
        "k-",
        "private",
        "day"
    ],
    "sg:website":"http://www.prestonparkchild.com",
    "wof:name":"Preston Creek Montessori School",
    "wof:placetype":"venue"
},
  "geometry": {"coordinates":[-96.797265,33.060676],"type":"Point"}
}