{
  "type": "Feature",
  "properties": {
    "iso:country":"US",
    "sg:address":"9151 Rolling Rock Ln",
    "sg:city":"Dallas",
    "sg:classifiers":[
        {
            "category":"Social Services",
            "subcategory":"Child Care",
            "type":"Services"
        }
    ],
    "sg:phone":"+1 214 342 9897",
    "sg:postcode":"75238",
    "sg:province":"TX",
    "sg:tags":[
        "day"
    ],
    "wof:name":"Inner Child Productions",
    "wof:placetype":"venue"
},
  "geometry": {"coordinates":[-96.69391299999999,32.872675],"type":"Point"}
}