{
  "type": "Feature",
  "properties": {
    "iso:country":"US",
    "sg:address":"7216 Coach Light Rd",
    "sg:city":"Dallas",
    "sg:classifiers":[
        {
            "category":"Health Services",
            "subcategory":"Nursing And Care Facility",
            "type":"Services"
        },
        {
            "category":"Social Services",
            "subcategory":"Retirement Home",
            "type":"Services"
        }
    ],
    "sg:phone":"+1 214 718 9315",
    "sg:postcode":"75237",
    "sg:province":"TX",
    "sg:tags":[
        "personal",
        "convalescent"
    ],
    "wof:name":"E Delta Properties",
    "wof:placetype":"venue"
},
  "geometry": {"coordinates":[-96.861823,32.660281],"type":"Point"}
}