{
  "type": "Feature",
  "properties": {
    "iso:country":"US",
    "sg:address":"1902 Country Club Dr",
    "sg:city":"Carrollton",
    "sg:classifiers":[
        {
            "category":"Professional",
            "subcategory":"Management & Consulting",
            "type":"Services"
        }
    ],
    "sg:phone":"+1 972 478 8138",
    "sg:postcode":"75006",
    "sg:province":"TX",
    "wof:name":"Fazen Management Service",
    "wof:placetype":"venue"
},
  "geometry": {"coordinates":[-96.89016599999999,32.960946],"type":"Point"}
}