{
  "type": "Feature",
  "properties": {
    "iso:country":"US",
    "sg:address":"9503 Brians Run",
    "sg:city":"Helotes",
    "sg:classifiers":[
        {
            "category":"Building & Trades",
            "subcategory":"Construction",
            "type":"Services"
        }
    ],
    "sg:phone":"+1 210 695 5454",
    "sg:postcode":"78023",
    "sg:province":"TX",
    "sg:tags":[
        "house"
    ],
    "wof:name":"Barron Connell Custom Homes",
    "wof:placetype":"venue"
},
  "geometry": {"coordinates":[-98.670531,29.570587],"type":"Point"}
}