{
  "type": "Feature",
  "properties": {
    "iso:country":"US",
    "sg:address":"2455 S 4th St",
    "sg:city":"Beaumont",
    "sg:classifiers":[
        {
            "category":"Organizations",
            "subcategory":"Religious Organization",
            "type":"Services"
        }
    ],
    "sg:phone":"+1 409 832 9299",
    "sg:postcode":"77701",
    "sg:province":"TX",
    "wof:name":"Abundant Life Baptist Church",
    "wof:placetype":"venue"
},
  "geometry": {"coordinates":[-94.115557,30.06236],"type":"Point"}
}