{
  "type": "Feature",
  "properties": {
    "iso:country":"US",
    "sg:address":"800 Silverstone Ln",
    "sg:city":"Irving",
    "sg:classifiers":[
        {
            "category":"Professional",
            "subcategory":"Management & Consulting",
            "type":"Services"
        }
    ],
    "sg:phone":"+1 972 444 8773",
    "sg:postcode":"75063",
    "sg:province":"TX",
    "sg:tags":[
        "business"
    ],
    "wof:name":"Kilgore Mis Consulting Service",
    "wof:placetype":"venue"
},
  "geometry": {"coordinates":[-96.94886,32.93678],"type":"Point"}
}