{
  "type": "Feature",
  "properties": {
    "iso:country":"US",
    "sg:address":"411 N Midland Dr",
    "sg:city":"Midland",
    "sg:classifiers":[
        {
            "category":"Shopping",
            "subcategory":"Clothing, Apparel, & Fashions",
            "type":"Retail Goods"
        }
    ],
    "sg:phone":"+1 432 262 3175",
    "sg:postcode":"79703",
    "sg:province":"TX",
    "sg:tags":[
        "lingerie"
    ],
    "wof:name":"Ooh LA LA Lingerie",
    "wof:placetype":"venue"
},
  "geometry": {"coordinates":[-102.134567,31.994697],"type":"Point"}
}