{
  "type": "Feature",
  "properties": {
    "iso:country":"US",
    "sg:address":"2011 Heather Ln",
    "sg:city":"Wichita Falls",
    "sg:classifiers":[
        {
            "category":"Professional",
            "type":"Services"
        }
    ],
    "sg:phone":"+1 940 691 9839",
    "sg:postcode":"76308",
    "sg:province":"TX",
    "wof:name":"Lcog Inc",
    "wof:placetype":"venue"
},
  "geometry": {"coordinates":[-98.512653,33.868098],"type":"Point"}
}