{
  "type": "Feature",
  "properties": {
    "iso:country":"US",
    "sg:address":"103 Abner Jackson Pkwy",
    "sg:city":"Lake Jackson",
    "sg:classifiers":[
        {
            "category":"Building & Trades",
            "subcategory":"Construction",
            "type":"Services"
        }
    ],
    "sg:phone":"+1 979 285 0712",
    "sg:postcode":"77566",
    "sg:province":"TX",
    "sg:tags":[
        "general",
        "contractor"
    ],
    "wof:name":"Elite Construction Group",
    "wof:placetype":"venue"
},
  "geometry": {"coordinates":[-95.456219,29.043368],"type":"Point"}
}