{
  "type": "Feature",
  "properties": {
    "iso:country":"US",
    "sg:address":"2001 Kirby Dr",
    "sg:city":"Houston",
    "sg:classifiers":[
        {
            "category":"Professional",
            "subcategory":"Lawyer & Legal Services",
            "type":"Services"
        }
    ],
    "sg:phone":"+1 713 942 7141",
    "sg:postcode":"77019",
    "sg:province":"TX",
    "wof:name":"Jackson Roger C Atty",
    "wof:placetype":"venue"
},
  "geometry": {"coordinates":[-95.4188,29.7484],"type":"Point"}
}