{
  "type": "Feature",
  "properties": {
    "iso:country":"US",
    "sg:address":"10200 Mystic Oaks Cir",
    "sg:city":"Austin",
    "sg:classifiers":[
        {
            "category":"Professional",
            "type":"Services"
        }
    ],
    "sg:phone":"+1 512 378 4679",
    "sg:postcode":"78750",
    "sg:province":"TX",
    "wof:name":"Robert & Emily Tycast",
    "wof:placetype":"venue"
},
  "geometry": {"coordinates":[-97.802796,30.425642],"type":"Point"}
}