{
  "type": "Feature",
  "properties": {
    "iso:country":"US",
    "sg:address":"6819 Michelle Dr",
    "sg:city":"Amarillo",
    "sg:classifiers":[
        {
            "category":"Building & Trades",
            "subcategory":"Construction",
            "type":"Services"
        }
    ],
    "sg:phone":"+1 806 467 0526",
    "sg:postcode":"79109",
    "sg:province":"TX",
    "sg:tags":[
        "hanging",
        "contractor"
    ],
    "wof:name":"Intex Painting Etc",
    "wof:placetype":"venue"
},
  "geometry": {"coordinates":[-101.913607,35.153004],"type":"Point"}
}