{
  "type": "Feature",
  "properties": {
    "iso:country":"US",
    "sg:address":"520 E Washington St",
    "sg:city":"Denison",
    "sg:classifiers":[
        {
            "category":"Professional",
            "type":"Services"
        }
    ],
    "sg:phone":"+1 903 463 3401",
    "sg:postcode":"75021",
    "sg:province":"TX",
    "wof:name":"Allen Hiner",
    "wof:placetype":"venue"
},
  "geometry": {"coordinates":[-96.527174,33.7645],"type":"Point"}
}