{
  "type": "Feature",
  "properties": {
    "iso:country":"US",
    "sg:address":"5102 Antoine Dr",
    "sg:city":"Houston",
    "sg:classifiers":[
        {
            "category":"Retail",
            "subcategory":"Car Wash",
            "type":"Services"
        }
    ],
    "sg:phone":"+1 713 290 9592",
    "sg:postcode":"77092",
    "sg:province":"TX",
    "sg:tags":[
        "polishing",
        "washing"
    ],
    "wof:name":"Flamingo Express Car Wash",
    "wof:placetype":"venue"
},
  "geometry": {"coordinates":[-95.473116,29.840313],"type":"Point"}
}