{
  "type": "Feature",
  "properties": {
    "iso:country":"US",
    "sg:address":"12879 Westheimer Rd",
    "sg:city":"Houston",
    "sg:classifiers":[
        {
            "category":"Personal",
            "subcategory":"Beauty Salon",
            "type":"Services"
        }
    ],
    "sg:phone":"+1 281 558 8240",
    "sg:postcode":"77077",
    "sg:province":"TX",
    "sg:tags":[
        "shop"
    ],
    "wof:name":"Hair Styling",
    "wof:placetype":"venue"
},
  "geometry": {"coordinates":[-95.612556,29.735959],"type":"Point"}
}