{
  "type": "Feature",
  "properties": {
    "iso:country":"US",
    "sg:address":"145 S L B J Dr",
    "sg:city":"San Marcos",
    "sg:classifiers":[
        {
            "category":"Manufacturing",
            "subcategory":"Printing",
            "type":"Manufacturing & Wholesale Goods"
        }
    ],
    "sg:phone":"+1 512 396 4744",
    "sg:postcode":"78666",
    "sg:province":"TX",
    "sg:tags":[
        "printer"
    ],
    "wof:name":"KWIK KOPY Printing",
    "wof:placetype":"venue"
},
  "geometry": {"coordinates":[-97.939773,29.881258],"type":"Point"}
}