{
  "type": "Feature",
  "properties": {
    "iso:country":"US",
    "sg:address":"5516 Blue Spruce Dr",
    "sg:city":"Arlington",
    "sg:classifiers":[
        {
            "category":"Building & Trades",
            "subcategory":"Construction",
            "type":"Services"
        }
    ],
    "sg:phone":"+1 972 293 8844",
    "sg:postcode":"76018",
    "sg:province":"TX",
    "sg:tags":[
        "pavement",
        "marking"
    ],
    "wof:name":"Squeaky Clean",
    "wof:placetype":"venue"
},
  "geometry": {"coordinates":[-97.10700799999999,32.654215],"type":"Point"}
}