{
  "type": "Feature",
  "properties": {
    "iso:country":"US",
    "sg:address":"9412 Daly Dr",
    "sg:city":"Plano",
    "sg:classifiers":[
        {
            "category":"Shopping",
            "subcategory":"Books",
            "type":"Retail Goods"
        }
    ],
    "sg:phone":"+1 972 390 1000",
    "sg:postcode":"75025",
    "sg:province":"TX",
    "sg:tags":[
        "dealer"
    ],
    "wof:name":"Warmfire Books",
    "wof:placetype":"venue"
},
  "geometry": {"coordinates":[-96.747919,33.10764],"type":"Point"}
}