{
  "type": "Feature",
  "properties": {
    "iso:country":"US",
    "sg:address":"803 N Main St",
    "sg:city":"Rising Star",
    "sg:classifiers":[
        {
            "category":"Retail",
            "subcategory":"Funeral Services",
            "type":"Services"
        }
    ],
    "sg:phone":"+1 254 643 4321",
    "sg:postcode":"76471",
    "sg:province":"TX",
    "sg:tags":[
        "director"
    ],
    "wof:name":"Higginbotham Funeral Home",
    "wof:placetype":"venue"
},
  "geometry": {"coordinates":[-98.96433399999999,32.103942],"type":"Point"}
}