{
  "type": "Feature",
  "properties": {
    "iso:country":"US",
    "sg:address":"9503 Castlewood Dr",
    "sg:city":"Austin",
    "sg:classifiers":[
        {
            "category":"Building & Trades",
            "subcategory":"Construction",
            "type":"Services"
        }
    ],
    "sg:phone":"+1 512 282 1626",
    "sg:postcode":"78748",
    "sg:province":"TX",
    "sg:tags":[
        "house"
    ],
    "wof:name":"Carpenter Remolder",
    "wof:placetype":"venue"
},
  "geometry": {"coordinates":[-97.827513,30.17856],"type":"Point"}
}