{
  "type": "Feature",
  "properties": {
    "iso:country":"US",
    "sg:address":"3504 Morningside St",
    "sg:city":"Victoria",
    "sg:classifiers":[
        {
            "category":"Professional",
            "type":"Services"
        }
    ],
    "sg:phone":"+1 361 575 4831",
    "sg:postcode":"77901",
    "sg:province":"TX",
    "wof:name":"Wagner Services",
    "wof:placetype":"venue"
},
  "geometry": {"coordinates":[-96.967134,28.802556],"type":"Point"}
}