{
  "type": "Feature",
  "properties": {
    "iso:country":"US",
    "sg:address":"3101 N IH 35",
    "sg:city":"Austin",
    "sg:classifiers":[
        {
            "category":"Restaurant",
            "type":"Food & Drink"
        }
    ],
    "sg:phone":"+1 512 478 7107",
    "sg:postcode":"78799",
    "sg:province":"TX",
    "sg:tags":[
        "diner"
    ],
    "sg:website":"www.starseedscafe.com",
    "wof:name":"Star Seeds Cafe",
    "wof:placetype":"venue"
},
  "geometry": {"coordinates":[-97.723198,30.288601],"type":"Point"}
}