{
  "type": "Feature",
  "properties": {
    "iso:country":"US",
    "sg:address":"8650 Yermoland Dr",
    "sg:city":"El Paso",
    "sg:classifiers":[
        {
            "category":"Manufacturing",
            "subcategory":"Tools & Machinery",
            "type":"Manufacturing & Wholesale Goods"
        }
    ],
    "sg:phone":"+1 915 595 2285",
    "sg:postcode":"79907",
    "sg:province":"TX",
    "sg:tags":[
        "die",
        "cutting",
        "mfg"
    ],
    "wof:name":"Mtc",
    "wof:placetype":"venue"
},
  "geometry": {"coordinates":[-106.317863,31.727758],"type":"Point"}
}