{
  "type": "Feature",
  "properties": {
    "iso:country":"US",
    "sg:address":"1020 Spring Cypress Rd",
    "sg:city":"Spring",
    "sg:classifiers":[
        {
            "category":"Retail",
            "subcategory":"Auto Repair",
            "type":"Services"
        }
    ],
    "sg:phone":"+1 281 353 7682",
    "sg:postcode":"77373",
    "sg:province":"TX",
    "sg:tags":[
        "shop",
        "automotive",
        "brake"
    ],
    "sg:website":"http://www.greenandwhiteauto.com",
    "wof:name":"Green & White Automotive",
    "wof:placetype":"venue"
},
  "geometry": {"coordinates":[-95.428467,30.077772],"type":"Point"}
}