{
  "type": "Feature",
  "properties": {
    "iso:country":"US",
    "sg:address":"201 Central Dr",
    "sg:city":"Cedar Park",
    "sg:classifiers":[
        {
            "category":"Professional",
            "subcategory":"Computer Services",
            "type":"Services"
        }
    ],
    "sg:phone":"+1 512 259 9670",
    "sg:postcode":"78613",
    "sg:province":"TX",
    "sg:tags":[
        "internet"
    ],
    "wof:name":"Sharp Edge",
    "wof:placetype":"venue"
},
  "geometry": {"coordinates":[-97.833338,30.524653],"type":"Point"}
}