{
  "type": "Feature",
  "properties": {
    "iso:country":"US",
    "sg:address":"1650 Brockman St",
    "sg:city":"Beaumont",
    "sg:classifiers":[
        {
            "category":"Wholesale",
            "subcategory":"Metals & Minerals",
            "type":"Manufacturing & Wholesale Goods"
        }
    ],
    "sg:phone":"+1 409 833 7878",
    "sg:postcode":"77705",
    "sg:province":"TX",
    "sg:tags":[
        "pipe"
    ],
    "wof:name":"Maverick International",
    "wof:placetype":"venue"
},
  "geometry": {"coordinates":[-94.10076599999999,30.049126],"type":"Point"}
}