{
  "type": "Feature",
  "properties": {
    "iso:country":"US",
    "sg:address":"9534 Meadowglen Ln",
    "sg:city":"Houston",
    "sg:classifiers":[
        {
            "category":"Communications",
            "type":"Services"
        }
    ],
    "sg:phone":"+1 832 252 1846",
    "sg:postcode":"77063",
    "sg:province":"TX",
    "sg:tags":[
        "communication"
    ],
    "wof:name":"Storyteller Communications",
    "wof:placetype":"venue"
},
  "geometry": {"coordinates":[-95.53473099999999,29.732511],"type":"Point"}
}