{
  "type": "Feature",
  "properties": {
    "iso:country":"US",
    "sg:address":"2205 Hurfus Dr",
    "sg:city":"Houston",
    "sg:classifiers":[
        {
            "category":"Building & Trades",
            "subcategory":"Construction",
            "type":"Services"
        }
    ],
    "sg:phone":"+1 713 290 0099",
    "sg:postcode":"77092",
    "sg:province":"TX",
    "sg:tags":[
        "contractor"
    ],
    "wof:name":"Drake Interior Lp",
    "wof:placetype":"venue"
},
  "geometry": {"coordinates":[-95.46019699999999,29.8069],"type":"Point"}
}