{
  "type": "Feature",
  "properties": {
    "iso:country":"US",
    "sg:address":"10901 Ranchstone Dr",
    "sg:city":"Houston",
    "sg:classifiers":[
        {
            "category":"Professional",
            "subcategory":"Computer Services",
            "type":"Services"
        }
    ],
    "sg:phone":"+1 281 970 6476",
    "sg:postcode":"77064",
    "sg:province":"TX",
    "sg:tags":[
        "datum"
    ],
    "wof:name":"Web Aid Intrnet Dsign Cnslting",
    "wof:placetype":"venue"
},
  "geometry": {"coordinates":[-95.58000199999999,29.910793],"type":"Point"}
}