{
  "type": "Feature",
  "properties": {
    "iso:country":"US",
    "sg:address":"2414 Park Ave",
    "sg:city":"Pearland",
    "sg:classifiers":[
        {
            "category":"Professional",
            "subcategory":"Lawyer & Legal Services",
            "type":"Services"
        }
    ],
    "sg:phone":"+1 281 485 0666",
    "sg:postcode":"77581",
    "sg:province":"TX",
    "sg:tags":[
        "attorney"
    ],
    "wof:name":"Benjamin H Best II",
    "wof:placetype":"venue"
},
  "geometry": {"coordinates":[-95.28261500000001,29.563407],"type":"Point"}
}