{
  "type": "Feature",
  "properties": {
    "iso:country":"US",
    "sg:address":"4245 W Airport Fwy",
    "sg:city":"Irving",
    "sg:classifiers":[
        {
            "category":"Travel",
            "subcategory":"Hotels & Motels",
            "type":"Entertainment"
        }
    ],
    "sg:phone":"+1 972 257 1810",
    "sg:postcode":"75062",
    "sg:province":"TX",
    "wof:name":"Humphrey Hospitality Management, Inc.",
    "wof:placetype":"venue"
},
  "geometry": {"coordinates":[-97.01018000000001,32.837888],"type":"Point"}
}