{
  "type": "Feature",
  "properties": {
    "iso:country":"US",
    "sg:address":"100 E Pearl St",
    "sg:city":"Granbury",
    "sg:classifiers":[
        {
            "category":"Government",
            "subcategory":"Office",
            "type":"Public Place"
        }
    ],
    "sg:phone":"+1 817 579 3200",
    "sg:postcode":"76048",
    "sg:province":"TX",
    "sg:tags":[
        "executive"
    ],
    "wof:name":"County of Hood",
    "wof:placetype":"venue"
},
  "geometry": {"coordinates":[-97.787646,32.442208],"type":"Point"}
}