{
  "type": "Feature",
  "properties": {
    "iso:country":"US",
    "sg:address":"5330 Navarro St",
    "sg:city":"Houston",
    "sg:classifiers":[
        {
            "category":"Real Estate",
            "subcategory":"Real Estate Agent",
            "type":"Services"
        }
    ],
    "sg:phone":"+1 713 840 8641",
    "sg:postcode":"77056",
    "sg:province":"TX",
    "wof:name":"Henry S Miller",
    "wof:placetype":"venue"
},
  "geometry": {"coordinates":[-95.47074000000001,29.734515],"type":"Point"}
}