{
  "type": "Feature",
  "properties": {
    "iso:country":"US",
    "sg:address":"3011 E 5th St",
    "sg:city":"Tyler",
    "sg:classifiers":[
        {
            "category":"Personal",
            "subcategory":"Tanning Parlor",
            "type":"Services"
        },
        {
            "category":"Personal",
            "type":"Services"
        }
    ],
    "sg:phone":"+1 903 566 5242",
    "sg:postcode":"75701",
    "sg:province":"TX",
    "sg:tags":[
        "salon"
    ],
    "wof:name":"Electric Beach",
    "wof:placetype":"venue"
},
  "geometry": {"coordinates":[-95.259641,32.332418],"type":"Point"}
}