{
  "type": "Feature",
  "properties": {
    "iso:country":"US",
    "sg:address":"113 E Main Ave",
    "sg:city":"Round Rock",
    "sg:classifiers":[
        {
            "category":"Shopping",
            "subcategory":"Bicycles & Sporting Goods",
            "type":"Retail Goods"
        }
    ],
    "sg:phone":"+1 512 244 1175",
    "sg:postcode":"78664",
    "sg:province":"TX",
    "wof:name":"Cutting Edge",
    "wof:placetype":"venue"
},
  "geometry": {"coordinates":[-97.67785000000001,30.50876],"type":"Point"}
}