{
  "type": "Feature",
  "properties": {
    "iso:country":"US",
    "sg:address":"3713 Guadalupe St",
    "sg:city":"Austin",
    "sg:classifiers":[
        {
            "category":"Food & Beverages",
            "subcategory":"Groceries & Convenience Stores",
            "type":"Retail Goods"
        }
    ],
    "sg:phone":"+1 512 323 9711",
    "sg:postcode":"78705",
    "sg:province":"TX",
    "wof:name":"Good Luck Food Mart",
    "wof:placetype":"venue"
},
  "geometry": {"coordinates":[-97.73840300000001,30.302601],"type":"Point"}
}