{
  "type": "Feature",
  "properties": {
    "iso:country":"US",
    "sg:address":"2713 Glenwood Trl",
    "sg:city":"Cedar Park",
    "sg:classifiers":[
        {
            "category":"Building & Trades",
            "subcategory":"Construction",
            "type":"Services"
        }
    ],
    "sg:phone":"+1 512 331 6132",
    "sg:postcode":"78613",
    "sg:province":"TX",
    "sg:tags":[
        "general",
        "contractor"
    ],
    "wof:name":"Innovative Construction Svc",
    "wof:placetype":"venue"
},
  "geometry": {"coordinates":[-97.831136,30.467247],"type":"Point"}
}