{
  "type": "Feature",
  "properties": {
    "iso:country":"US",
    "sg:address":"6440 W State Loop 220",
    "sg:city":"Plum",
    "sg:classifiers":[
        {
            "category":"Real Estate",
            "subcategory":"Real Estate Agent",
            "type":"Services"
        }
    ],
    "sg:phone":"+1 979 242 3506",
    "sg:postcode":"78945",
    "sg:province":"TX",
    "wof:name":"Appraisal Plus",
    "wof:placetype":"venue"
},
  "geometry": {"coordinates":[-96.96826299999999,29.930857],"type":"Point"}
}