{
  "type": "Feature",
  "properties": {
    "iso:country":"US",
    "sg:address":"2529 5th Ave",
    "sg:city":"Port Arthur",
    "sg:classifiers":[
        {
            "category":"Building & Trades",
            "subcategory":"Construction",
            "type":"Services"
        }
    ],
    "sg:phone":"+1 409 985 4613",
    "sg:postcode":"77642",
    "sg:province":"TX",
    "sg:tags":[
        "roofing",
        "contractor"
    ],
    "wof:name":"Swains Carpentry & Roofing",
    "wof:placetype":"venue"
},
  "geometry": {"coordinates":[-93.93232,29.908642],"type":"Point"}
}