{
  "type": "Feature",
  "properties": {
    "iso:country":"US",
    "sg:address":"1025 W Hebron Pkwy",
    "sg:city":"Carrollton",
    "sg:classifiers":[
        {
            "category":"Insurance",
            "subcategory":"Hazard Insurance",
            "type":"Services"
        },
        {
            "category":"Insurance",
            "subcategory":"Insurance Agent",
            "type":"Services"
        },
        {
            "category":"Insurance",
            "subcategory":"Life Insurance",
            "type":"Services"
        }
    ],
    "sg:phone":"+1 972 492 2559",
    "sg:postcode":"75010",
    "sg:province":"TX",
    "sg:tags":[
        "auto"
    ],
    "sg:website":"http://statefarm.mqgroup.com/url.asp?usr=437083",
    "wof:name":"Daniel, David - State Farm Insurance Agent",
    "wof:placetype":"venue"
},
  "geometry": {"coordinates":[-96.917202,33.0204],"type":"Point"}
}