{
  "type": "Feature",
  "properties": {
    "iso:country":"US",
    "sg:address":"10500 Northwest Fwy",
    "sg:city":"Houston",
    "sg:classifiers":[
        {
            "category":"Ferry",
            "type":"Transportation"
        }
    ],
    "sg:phone":"+1 713 686 1918",
    "sg:postcode":"77092",
    "sg:province":"TX",
    "wof:name":"Mediterranean Shipping Co. USA Inc.",
    "wof:placetype":"venue"
},
  "geometry": {"coordinates":[-95.46064,29.81255],"type":"Point"}
}