{
  "type": "Feature",
  "properties": {
    "iso:country":"US",
    "sg:address":"8617 Burnet Rd",
    "sg:city":"Austin",
    "sg:classifiers":[
        {
            "category":"Shopping",
            "subcategory":"Mobile Phones",
            "type":"Retail Goods"
        }
    ],
    "sg:phone":"+1 512 447 4659",
    "sg:postcode":"78757",
    "sg:province":"TX",
    "wof:name":"Pinky's Wireless",
    "wof:placetype":"venue"
},
  "geometry": {"coordinates":[-97.7276,30.368799],"type":"Point"}
}