{
  "type": "Feature",
  "properties": {
    "iso:country":"US",
    "sg:address":"4409 Lake Hill Dr",
    "sg:city":"Rowlett",
    "sg:classifiers":[
        {
            "category":"Building & Trades",
            "subcategory":"Construction",
            "type":"Services"
        }
    ],
    "sg:phone":"+1 972 475 6222",
    "sg:postcode":"75089",
    "sg:province":"TX",
    "sg:tags":[
        "house"
    ],
    "wof:name":"JW Dickens Home Repair",
    "wof:placetype":"venue"
},
  "geometry": {"coordinates":[-96.559076,32.91807],"type":"Point"}
}