{
  "type": "Feature",
  "properties": {
    "iso:country":"US",
    "sg:address":"2 Rockridge Dr",
    "sg:city":"Spring",
    "sg:classifiers":[
        {
            "category":"Real Estate",
            "subcategory":"Real Estate Operator",
            "type":"Services"
        }
    ],
    "sg:phone":"+1 281 648 7595",
    "sg:postcode":"77381",
    "sg:province":"TX",
    "sg:tags":[
        "building",
        "nonresidential"
    ],
    "wof:name":"Established Properties",
    "wof:placetype":"venue"
},
  "geometry": {"coordinates":[-95.512524,30.170347],"type":"Point"}
}