{
  "type": "Feature",
  "properties": {
    "iso:country":"US",
    "sg:address":"905 Ave B",
    "sg:city":"Sweeny",
    "sg:classifiers":[
        {
            "category":"Shopping",
            "subcategory":"Used Merchandise",
            "type":"Retail Goods"
        }
    ],
    "sg:phone":"+1 979 548 2470",
    "sg:postcode":"77480",
    "sg:province":"TX",
    "wof:name":"Hansons Antiques",
    "wof:placetype":"venue"
},
  "geometry": {"coordinates":[-95.68786,29.044714],"type":"Point"}
}