{
  "type": "Feature",
  "properties": {
    "iso:country":"US",
    "sg:address":"8217 Etienne Dr",
    "sg:city":"Corpus Christi",
    "sg:classifiers":[
        {
            "category":"Home & Garden",
            "subcategory":"Home Furnishings",
            "type":"Retail Goods"
        }
    ],
    "sg:phone":"+1 361 985 7450",
    "sg:postcode":"78414",
    "sg:province":"TX",
    "wof:name":"Bayshop Com",
    "wof:placetype":"venue"
},
  "geometry": {"coordinates":[-97.39098799999999,27.64606],"type":"Point"}
}