{
  "type": "Feature",
  "properties": {
    "iso:country":"US",
    "sg:address":"7317 Boehnemann Rd",
    "sg:city":"Brenham",
    "sg:classifiers":[
        {
            "category":"Shopping",
            "type":"Retail Goods"
        }
    ],
    "sg:phone":"+1 979 836 6237",
    "sg:postcode":"77833",
    "sg:province":"TX",
    "sg:tags":[
        "art",
        "gallery",
        "dealer"
    ],
    "wof:name":"Laser Gallery",
    "wof:placetype":"venue"
},
  "geometry": {"coordinates":[-96.539964,30.132658],"type":"Point"}
}