{
  "type": "Feature",
  "properties": {
    "iso:country":"US",
    "sg:address":"1019 Dragon St",
    "sg:city":"Dallas",
    "sg:classifiers":[
        {
            "category":"Home & Garden",
            "subcategory":"Furniture",
            "type":"Retail Goods"
        }
    ],
    "sg:phone":"+1 214 350 0542",
    "sg:postcode":"75207",
    "sg:province":"TX",
    "sg:tags":[
        "store"
    ],
    "sg:website":"www.sminkinc.com",
    "wof:name":"Smink Inc",
    "wof:placetype":"venue"
},
  "geometry": {"coordinates":[-96.816975,32.787158],"type":"Point"}
}