{
  "type": "Feature",
  "properties": {
    "iso:country":"US",
    "sg:address":"2535 Bandelier Dr",
    "sg:city":"Houston",
    "sg:classifiers":[
        {
            "category":"Professional",
            "type":"Services"
        }
    ],
    "sg:phone":"+1 713 263 9534",
    "sg:postcode":"77080",
    "sg:province":"TX",
    "wof:name":"Sound To Image Inc",
    "wof:placetype":"venue"
},
  "geometry": {"coordinates":[-95.53957200000001,29.817828],"type":"Point"}
}