{
  "type": "Feature",
  "properties": {
    "iso:country":"US",
    "sg:address":"6619 Forest Hill Dr",
    "sg:city":"Fort Worth",
    "sg:classifiers":[
        {
            "category":"Restaurant",
            "type":"Food & Drink"
        }
    ],
    "sg:menulink":"http://www.allmenus.com/tx/fort-worth/65191-cicis-pizza-buffet/menu/",
    "sg:phone":"+1 817 483 3950",
    "sg:postcode":"76140",
    "sg:province":"TX",
    "sg:tags":[
        "american",
        "pizza"
    ],
    "wof:name":"CiCi's Pizza Buffet",
    "wof:placetype":"venue"
},
  "geometry": {"coordinates":[-97.26863299999999,32.658693],"type":"Point"}
}