{
  "type": "Feature",
  "properties": {
    "iso:country":"US",
    "sg:address":"4428 N 19th St",
    "sg:city":"Waco",
    "sg:classifiers":[
        {
            "category":"Government",
            "subcategory":"Post Office",
            "type":"Public Place"
        }
    ],
    "sg:phone":"+1 254 714 1234",
    "sg:postcode":"76708",
    "sg:province":"TX",
    "sg:tags":[
        "postal",
        "us"
    ],
    "wof:name":"US Post Office",
    "wof:placetype":"venue"
},
  "geometry": {"coordinates":[-97.178012,31.586707],"type":"Point"}
}