{
  "type": "Feature",
  "properties": {
    "iso:country":"US",
    "sg:address":"3500 Preston Rd",
    "sg:city":"Plano",
    "sg:classifiers":[
        {
            "category":"Communications",
            "subcategory":"Radio Station",
            "type":"Services"
        }
    ],
    "sg:phone":"+1 972 758 1924",
    "sg:postcode":"75093",
    "sg:province":"TX",
    "sg:tags":[
        "company",
        "broadcasting"
    ],
    "wof:name":"KLUV",
    "wof:placetype":"venue"
},
  "geometry": {"coordinates":[-96.79428799999999,33.046359],"type":"Point"}
}