{
  "type": "Feature",
  "properties": {
    "iso:country":"US",
    "sg:address":"555 Bowers Blvd Apt 913",
    "sg:city":"Huntsville",
    "sg:classifiers":[
        {
            "category":"Real Estate",
            "subcategory":"Real Estate Operator",
            "type":"Services"
        }
    ],
    "sg:phone":"+1 936 295 8343",
    "sg:postcode":"77340",
    "sg:province":"TX",
    "sg:tags":[
        "apartment"
    ],
    "wof:name":"University House",
    "wof:placetype":"venue"
},
  "geometry": {"coordinates":[-95.54158200000001,30.712522],"type":"Point"}
}