{
  "type": "Feature",
  "properties": {
    "iso:country":"US",
    "sg:address":"3012 Windsor Rd",
    "sg:city":"Austin",
    "sg:classifiers":[
        {
            "category":"Building & Trades",
            "subcategory":"Construction",
            "type":"Services"
        }
    ],
    "sg:phone":"+1 512 476 1838",
    "sg:postcode":"78703",
    "sg:province":"TX",
    "sg:tags":[
        "house"
    ],
    "wof:name":"Standifer and Associates Inc",
    "wof:placetype":"venue"
},
  "geometry": {"coordinates":[-97.766251,30.294819],"type":"Point"}
}