{
  "type": "Feature",
  "properties": {
    "iso:country":"US",
    "sg:address":"4303 Nelson Rd",
    "sg:city":"Midland",
    "sg:classifiers":[
        {
            "category":"Personal",
            "type":"Services"
        }
    ],
    "sg:phone":"+1 432 684 5221",
    "sg:postcode":"79707",
    "sg:province":"TX",
    "sg:tags":[
        "control",
        "weight"
    ],
    "wof:name":"Hypnosis Weight Loss Ctr",
    "wof:placetype":"venue"
},
  "geometry": {"coordinates":[-102.139319,32.014943],"type":"Point"}
}