{
  "type": "Feature",
  "properties": {
    "iso:country":"US",
    "sg:address":"4416 Hunters Lodge Dr",
    "sg:city":"Round Rock",
    "sg:classifiers":[
        {
            "category":"Professional",
            "subcategory":"Lawyer & Legal Services",
            "type":"Services"
        }
    ],
    "sg:phone":"+1 512 244 6925",
    "sg:postcode":"78681",
    "sg:province":"TX",
    "wof:name":"Tome Christopher J",
    "wof:placetype":"venue"
},
  "geometry": {"coordinates":[-97.761771,30.550225],"type":"Point"}
}