{
  "type": "Feature",
  "properties": {
    "iso:country":"US",
    "sg:address":"6050 Beldart St",
    "sg:city":"Houston",
    "sg:classifiers":[
        {
            "category":"Place Of Worship",
            "subcategory":"Church",
            "type":"Public Place"
        },
        {
            "category":"Place Of Worship",
            "type":"Public Place"
        }
    ],
    "sg:phone":"+1 713 734 7773",
    "sg:postcode":"77033",
    "sg:province":"TX",
    "sg:tags":[
        "churches-baptist-general",
        "churches-baptist"
    ],
    "sg:website":"http://www.thenewmountcalvarymbc.com",
    "wof:name":"The New Mt Calvary Baptist Church",
    "wof:placetype":"venue"
},
  "geometry": {"coordinates":[-95.321679,29.661955],"type":"Point"}
}