{
  "type": "Feature",
  "properties": {
    "iso:country":"US",
    "sg:address":"12700 Collindale Cove",
    "sg:city":"Austin",
    "sg:classifiers":[
        {
            "category":"Professional",
            "subcategory":"Management & Consulting",
            "type":"Services"
        }
    ],
    "sg:phone":"+1 512 314 5699",
    "sg:postcode":"78753",
    "sg:province":"TX",
    "sg:tags":[
        "business"
    ],
    "wof:name":"Quickstart",
    "wof:placetype":"venue"
},
  "geometry": {"coordinates":[-97.64617200000001,30.39613],"type":"Point"}
}