{
  "type": "Feature",
  "properties": {
    "iso:country":"US",
    "sg:address":"310 E I- 30",
    "sg:city":"Garland",
    "sg:classifiers":[
        {
            "category":"Building & Trades",
            "subcategory":"Construction",
            "type":"Services"
        }
    ],
    "sg:phone":"+1 972 226 4333",
    "sg:postcode":"75043",
    "sg:province":"TX",
    "sg:tags":[
        "builder",
        "operative"
    ],
    "wof:name":"D R Horton Inc",
    "wof:placetype":"venue"
},
  "geometry": {"coordinates":[-96.570189,32.850076],"type":"Point"}
}