{
  "type": "Feature",
  "properties": {
    "iso:country":"US",
    "sg:address":"12800 Hillcrest Rd Ste 216",
    "sg:city":"Dallas",
    "sg:classifiers":[
        {
            "category":"Health Services",
            "subcategory":"Doctor",
            "type":"Services"
        }
    ],
    "sg:phone":"+1 972 239 9252",
    "sg:postcode":"75230",
    "sg:province":"TX",
    "wof:name":"Alexander Drew W",
    "wof:placetype":"venue"
},
  "geometry": {"coordinates":[-96.786102,32.922699],"type":"Point"}
}