{
  "type": "Feature",
  "properties": {
    "iso:country":"US",
    "sg:address":"397 N Sam Houston Pkwy E Suite 2",
    "sg:city":"Houston",
    "sg:classifiers":[
        {
            "category":"Structure",
            "subcategory":"Office Building",
            "type":"Public Place"
        },
        {
            "category":"Professional",
            "subcategory":"Employment Agencies",
            "type":"Services"
        },
        {
            "category":"Professional",
            "subcategory":"Business Services",
            "type":"Services"
        }
    ],
    "sg:phone":"+1 281 847 4300",
    "sg:postcode":"77060",
    "sg:province":"TX",
    "sg:tags":[
        "control",
        "consultant",
        "coach",
        "park",
        "quality"
    ],
    "wof:name":"Nde Quality Systems, Inc.",
    "wof:placetype":"venue"
},
  "geometry": {"coordinates":[-95.39769,29.939779],"type":"Point"}
}