{
  "type": "Feature",
  "properties": {
    "iso:country":"US",
    "sg:address":"6733 Bridge St",
    "sg:city":"Fort Worth",
    "sg:classifiers":[
        {
            "category":"Shopping",
            "subcategory":"Musical Instruments",
            "type":"Retail Goods"
        }
    ],
    "sg:phone":"+1 817 451 6500",
    "sg:postcode":"76112",
    "sg:province":"TX",
    "sg:tags":[
        "compact",
        "record",
        "disc",
        "tape"
    ],
    "wof:name":"Music World Stores",
    "wof:placetype":"venue"
},
  "geometry": {"coordinates":[-97.21527500000001,32.76624],"type":"Point"}
}