{
  "type": "Feature",
  "properties": {
    "iso:country":"US",
    "sg:address":"7449 Lantana Ave",
    "sg:city":"Abilene",
    "sg:classifiers":[
        {
            "category":"Building & Trades",
            "subcategory":"Construction",
            "type":"Services"
        }
    ],
    "sg:phone":"+1 325 692 0516",
    "sg:postcode":"79606",
    "sg:province":"TX",
    "sg:tags":[
        "utility",
        "contractor"
    ],
    "wof:name":"Bill Starks Construction Co",
    "wof:placetype":"venue"
},
  "geometry": {"coordinates":[-99.803349,32.359728],"type":"Point"}
}