{
  "type": "Feature",
  "properties": {
    "iso:country":"US",
    "sg:address":"4822 Purdue Ave",
    "sg:city":"Dallas",
    "sg:classifiers":[
        {
            "category":"Professional",
            "subcategory":"Business Services",
            "type":"Services"
        }
    ],
    "sg:phone":"+1 214 350 7297",
    "sg:postcode":"75209",
    "sg:province":"TX",
    "wof:name":"MB Interests Group LLC",
    "wof:placetype":"venue"
},
  "geometry": {"coordinates":[-96.82554500000001,32.854103],"type":"Point"}
}