{
  "type": "Feature",
  "properties": {
    "iso:country":"US",
    "sg:address":"8101 Elkhorn Mountain Trl",
    "sg:city":"Austin",
    "sg:classifiers":[
        {
            "category":"Retail",
            "subcategory":"Portrait Studio",
            "type":"Services"
        }
    ],
    "sg:phone":"+1 512 789 9098",
    "sg:postcode":"78729",
    "sg:province":"TX",
    "sg:tags":[
        "photo"
    ],
    "wof:name":"Vanryn Photography",
    "wof:placetype":"venue"
},
  "geometry": {"coordinates":[-97.76908,30.443901],"type":"Point"}
}