{
  "type": "Feature",
  "properties": {
    "iso:country":"US",
    "sg:address":"4812 Bryan St",
    "sg:city":"Dallas",
    "sg:classifiers":[
        {
            "category":"Restaurant",
            "type":"Food & Drink"
        }
    ],
    "sg:phone":"+1 214 823 8879",
    "sg:postcode":"75204",
    "sg:province":"TX",
    "sg:tags":[
        "mexican"
    ],
    "wof:name":"Marysol's Mexican Restaurant",
    "wof:placetype":"venue"
},
  "geometry": {"coordinates":[-96.77376,32.803148],"type":"Point"}
}