{
  "type": "Feature",
  "properties": {
    "iso:country":"US",
    "sg:address":"4304 Call Field Rd",
    "sg:city":"Wichita Falls",
    "sg:classifiers":[
        {
            "category":"Retail",
            "subcategory":"Veterinary Services",
            "type":"Services"
        }
    ],
    "sg:phone":"+1 940 692 7000",
    "sg:postcode":"76308",
    "sg:province":"TX",
    "wof:name":"Call Feld Cmpnion Anmal Clinic",
    "wof:placetype":"venue"
},
  "geometry": {"coordinates":[-98.552966,33.871902],"type":"Point"}
}