{
  "type": "Feature",
  "properties": {
    "iso:country":"US",
    "sg:address":"8210 Vernon Ave",
    "sg:city":"Lubbock",
    "sg:classifiers":[
        {
            "category":"Personal",
            "type":"Services"
        }
    ],
    "sg:phone":"+1 806 745 0900",
    "sg:postcode":"79423",
    "sg:province":"TX",
    "wof:name":"Tropical Tan",
    "wof:placetype":"venue"
},
  "geometry": {"coordinates":[-101.86481499999999,33.518765],"type":"Point"}
}