{
  "type": "Feature",
  "properties": {
    "iso:country":"US",
    "sg:address":"13414 Reeveston Rd",
    "sg:city":"Houston",
    "sg:classifiers":[
        {
            "category":"Shopping",
            "subcategory":"Gifts & Souvenirs",
            "type":"Retail Goods"
        }
    ],
    "sg:phone":"+1 281 219 9171",
    "sg:postcode":"77039",
    "sg:province":"TX",
    "wof:name":"Ds Creations",
    "wof:placetype":"venue"
},
  "geometry": {"coordinates":[-95.367717,29.914402],"type":"Point"}
}