{
  "type": "Feature",
  "properties": {
    "iso:country":"US",
    "sg:address":"621 S Central St",
    "sg:city":"Hallsville",
    "sg:classifiers":[
        {
            "category":"Freight",
            "type":"Transportation"
        }
    ],
    "sg:phone":"+1 903 668 1616",
    "sg:postcode":"75650",
    "sg:province":"TX",
    "sg:tags":[
        "special"
    ],
    "wof:name":"Bob Cat Store All",
    "wof:placetype":"venue"
},
  "geometry": {"coordinates":[-94.57445800000001,32.491405],"type":"Point"}
}