{
  "type": "Feature",
  "properties": {
    "iso:country":"US",
    "sg:address":"4412 Buchanan Loop Rd",
    "sg:city":"Texarkana",
    "sg:classifiers":[
        {
            "category":"Wholesale",
            "subcategory":"Machinery & Supplies",
            "type":"Manufacturing & Wholesale Goods"
        }
    ],
    "sg:phone":"+1 903 792 9020",
    "sg:postcode":"75501",
    "sg:province":"TX",
    "wof:name":"Daniel Harold Ray",
    "wof:placetype":"venue"
},
  "geometry": {"coordinates":[-94.096689,33.341715],"type":"Point"}
}