{
  "type": "Feature",
  "properties": {
    "iso:country":"US",
    "sg:address":"515 S Pearl St",
    "sg:city":"Stratford",
    "sg:classifiers":[
        {
            "category":"Organizations",
            "subcategory":"Religious Organization",
            "type":"Services"
        }
    ],
    "sg:phone":"+1 806 366 5687",
    "sg:postcode":"79084",
    "sg:province":"TX",
    "sg:tags":[
        "church"
    ],
    "wof:name":"St Joseph's Catholic Church",
    "wof:placetype":"venue"
},
  "geometry": {"coordinates":[-102.065038,36.330096],"type":"Point"}
}