{
  "type": "Feature",
  "properties": {
    "iso:country":"US",
    "sg:address":"909 Reinli St",
    "sg:city":"Austin",
    "sg:classifiers":[
        {
            "category":"Real Estate",
            "subcategory":"Real Estate Operator",
            "type":"Services"
        }
    ],
    "sg:phone":"+1 512 467 9430",
    "sg:postcode":"78751",
    "sg:province":"TX",
    "sg:tags":[
        "apartment",
        "complex"
    ],
    "wof:name":"Highland Cove",
    "wof:placetype":"venue"
},
  "geometry": {"coordinates":[-97.710899,30.320198],"type":"Point"}
}