{
  "type": "Feature",
  "properties": {
    "iso:country":"US",
    "sg:address":"6701 Sanger Ave",
    "sg:city":"Waco",
    "sg:classifiers":[
        {
            "category":"Real Estate",
            "subcategory":"Architect",
            "type":"Services"
        }
    ],
    "sg:phone":"+1 254 776 7006",
    "sg:postcode":"76710",
    "sg:province":"TX",
    "sg:tags":[
        "building",
        "designer"
    ],
    "wof:name":"Bush Building Corp",
    "wof:placetype":"venue"
},
  "geometry": {"coordinates":[-97.197501,31.520523],"type":"Point"}
}