{
  "type": "Feature",
  "properties": {
    "iso:country":"US",
    "sg:address":"1011 Cresthaven Dr",
    "sg:city":"Lancaster",
    "sg:classifiers":[
        {
            "category":"Freight",
            "type":"Transportation"
        }
    ],
    "sg:phone":"+1 972 218 7477",
    "sg:postcode":"75134",
    "sg:province":"TX",
    "sg:tags":[
        "local",
        "trucking"
    ],
    "wof:name":"Total Praise Moving And Storage",
    "wof:placetype":"venue"
},
  "geometry": {"coordinates":[-96.776578,32.624266],"type":"Point"}
}