{
  "type": "Feature",
  "properties": {
    "iso:country":"US",
    "sg:address":"1411 Hill St",
    "sg:city":"Nederland",
    "sg:classifiers":[
        {
            "category":"Shopping",
            "subcategory":"Bicycles & Sporting Goods",
            "type":"Retail Goods"
        }
    ],
    "sg:phone":"+1 409 727 8908",
    "sg:postcode":"77627",
    "sg:province":"TX",
    "wof:name":"Daves Golf Shop Inc",
    "wof:placetype":"venue"
},
  "geometry": {"coordinates":[-94.008825,29.986497],"type":"Point"}
}