{
  "type": "Feature",
  "properties": {
    "iso:country":"US",
    "sg:address":"4406 Debeney Dr",
    "sg:city":"Houston",
    "sg:classifiers":[
        {
            "category":"Professional",
            "type":"Services"
        }
    ],
    "sg:phone":"+1 281 227 1183",
    "sg:postcode":"77039",
    "sg:province":"TX",
    "sg:tags":[
        "establishment"
    ],
    "wof:name":"Miracle House Of Care",
    "wof:placetype":"venue"
},
  "geometry": {"coordinates":[-95.326195,29.904791],"type":"Point"}
}