{
  "type": "Feature",
  "properties": {
    "iso:country":"US",
    "sg:address":"937 W Bay Area Blvd",
    "sg:city":"Webster",
    "sg:classifiers":[
        {
            "category":"Food & Beverages",
            "subcategory":"Meat & Fish",
            "type":"Retail Goods"
        }
    ],
    "sg:phone":"+1 281 557 8099",
    "sg:postcode":"77598",
    "sg:province":"TX",
    "wof:name":"Omaha Steaks",
    "wof:placetype":"venue"
},
  "geometry": {"coordinates":[-95.13505000000001,29.544263],"type":"Point"}
}