{
  "type": "Feature",
  "properties": {
    "iso:country":"US",
    "sg:address":"1535 West Loop S Ste 322",
    "sg:city":"Houston",
    "sg:classifiers":[
        {
            "category":"Real Estate",
            "subcategory":"Architect",
            "type":"Services"
        }
    ],
    "sg:phone":"+1 713 666 2185",
    "sg:postcode":"77027",
    "sg:province":"TX",
    "wof:name":"Cameron Architects Inc",
    "wof:placetype":"venue"
},
  "geometry": {"coordinates":[-95.454933,29.752264],"type":"Point"}
}