{
  "type": "Feature",
  "properties": {
    "iso:country":"US",
    "sg:address":"12707 Alston Rd",
    "sg:city":"Sugar Land",
    "sg:classifiers":[
        {
            "category":"Social Services",
            "subcategory":"Child Care",
            "type":"Services"
        }
    ],
    "sg:phone":"+1 281 277 7788",
    "sg:postcode":"77478",
    "sg:province":"TX",
    "sg:tags":[
        "day"
    ],
    "wof:name":"New Southwest Montessori Ctr",
    "wof:placetype":"venue"
},
  "geometry": {"coordinates":[-95.609442,29.652582],"type":"Point"}
}