{
  "type": "Feature",
  "properties": {
    "iso:country":"US",
    "sg:address":"6012 Flintshire Ct",
    "sg:city":"Arlington",
    "sg:classifiers":[
        {
            "category":"Professional",
            "subcategory":"Business Services",
            "type":"Services"
        }
    ],
    "sg:phone":"+1 817 478 6262",
    "sg:postcode":"76017",
    "sg:province":"TX",
    "sg:tags":[
        "liquidator"
    ],
    "wof:name":"M J Rodgers Enterprises",
    "wof:placetype":"venue"
},
  "geometry": {"coordinates":[-97.20026,32.668056],"type":"Point"}
}