{
  "type": "Feature",
  "properties": {
    "iso:country":"US",
    "sg:address":"2312 Loch Haven Dr",
    "sg:city":"Plano",
    "sg:classifiers":[
        {
            "category":"Real Estate",
            "subcategory":"Real Estate Agent",
            "type":"Services"
        }
    ],
    "sg:phone":"+1 972 758 7243",
    "sg:postcode":"75023",
    "sg:province":"TX",
    "wof:name":"Millennium Property Management",
    "wof:placetype":"venue"
},
  "geometry": {"coordinates":[-96.73974800000001,33.054067],"type":"Point"}
}