{
  "type": "Feature",
  "properties": {
    "iso:country":"US",
    "sg:address":"4615 Oakfield Way",
    "sg:city":"San Antonio",
    "sg:classifiers":[
        {
            "category":"Professional",
            "subcategory":"Detective & Security Services",
            "type":"Services"
        }
    ],
    "sg:phone":"+1 210 256 1789",
    "sg:postcode":"78251",
    "sg:province":"TX",
    "sg:tags":[
        "guard"
    ],
    "wof:name":"Sandra L Barr",
    "wof:placetype":"venue"
},
  "geometry": {"coordinates":[-98.641831,29.476021],"type":"Point"}
}