{
  "type": "Feature",
  "properties": {
    "iso:country":"US",
    "sg:address":"1631 Co Rd 130",
    "sg:city":"Pearland",
    "sg:classifiers":[
        {
            "category":"Professional",
            "type":"Services"
        }
    ],
    "sg:phone":"+1 281 452 4038",
    "sg:postcode":"77581",
    "sg:province":"TX",
    "wof:name":"Es Co",
    "wof:placetype":"venue"
},
  "geometry": {"coordinates":[-95.238229,29.514673],"type":"Point"}
}