{
  "type": "Feature",
  "properties": {
    "iso:country":"US",
    "sg:address":"1902 9th St",
    "sg:city":"Wichita Falls",
    "sg:classifiers":[
        {
            "category":"Shopping",
            "type":"Retail Goods"
        },
        {
            "category":"Shopping",
            "subcategory":"Beauty & Cosmetics",
            "type":"Retail Goods"
        }
    ],
    "sg:phone":"+1 940 766 1416",
    "sg:postcode":"76301",
    "sg:province":"TX",
    "sg:tags":[
        "merchandise",
        "perfume"
    ],
    "wof:name":"V I P Casual & Beauty",
    "wof:placetype":"venue"
},
  "geometry": {"coordinates":[-98.510397,33.903904],"type":"Point"}
}