{
  "type": "Feature",
  "properties": {
    "iso:country":"US",
    "sg:address":"1903 Church St",
    "sg:city":"Galveston",
    "sg:classifiers":[
        {
            "category":"Social Services",
            "subcategory":"Child Care",
            "type":"Services"
        }
    ],
    "sg:phone":"+1 409 762 8638",
    "sg:postcode":"77550",
    "sg:province":"TX",
    "sg:tags":[
        "day"
    ],
    "wof:name":"East End Pre-School",
    "wof:placetype":"venue"
},
  "geometry": {"coordinates":[-94.78972899999999,29.304509],"type":"Point"}
}