{
  "type": "Feature",
  "properties": {
    "iso:country":"US",
    "sg:address":"1909 W Beauregard Ave",
    "sg:city":"San Angelo",
    "sg:classifiers":[
        {
            "category":"Retail",
            "subcategory":"Auto Repair",
            "type":"Services"
        }
    ],
    "sg:phone":"+1 325 947 9473",
    "sg:postcode":"76901",
    "sg:province":"TX",
    "sg:tags":[
        "body",
        "automobile",
        "painting"
    ],
    "wof:name":"Concho Collision",
    "wof:placetype":"venue"
},
  "geometry": {"coordinates":[-100.46006800000001,31.453466],"type":"Point"}
}