{
  "type": "Feature",
  "properties": {
    "iso:country":"US",
    "sg:address":"110 Pearl St",
    "sg:city":"Center",
    "sg:classifiers":[
        {
            "category":"Personal",
            "subcategory":"Beauty Salon",
            "type":"Services"
        }
    ],
    "sg:phone":"+1 936 598 2670",
    "sg:postcode":"75935",
    "sg:province":"TX",
    "sg:tags":[
        "shop"
    ],
    "wof:name":"Becky's Hair Fashions",
    "wof:placetype":"venue"
},
  "geometry": {"coordinates":[-94.185592,31.800641],"type":"Point"}
}