{
  "type": "Feature",
  "properties": {
    "iso:country":"US",
    "sg:address":"5500 Miramar Ln",
    "sg:city":"Colleyville",
    "sg:phone":"+1 817 540 5155",
    "sg:postcode":"76034",
    "sg:province":"TX",
    "sg:tags":[
        "communications",
        "telegraph"
    ],
    "wof:name":"Dennis Miga",
    "wof:placetype":"venue"
},
  "geometry": {"coordinates":[-97.136585,32.888401],"type":"Point"}
}