{
  "type": "Feature",
  "properties": {
    "iso:country":"US",
    "sg:address":"14888 Old Hwy 105 W",
    "sg:city":"Montgomery",
    "sg:classifiers":[
        {
            "category":"Insurance",
            "subcategory":"Insurance Agent",
            "type":"Services"
        }
    ],
    "sg:phone":"+1 936 588 6668",
    "sg:postcode":"77356",
    "sg:province":"TX",
    "wof:name":"Allstate Insurance",
    "wof:placetype":"venue"
},
  "geometry": {"coordinates":[-95.79277999999999,30.346406],"type":"Point"}
}