{
  "type": "Feature",
  "properties": {
    "iso:country":"US",
    "sg:address":"704 N Berry St",
    "sg:city":"Beeville",
    "sg:classifiers":[
        {
            "category":"Professional",
            "subcategory":"Management & Consulting",
            "type":"Services"
        }
    ],
    "sg:phone":"+1 361 358 1257",
    "sg:postcode":"78102",
    "sg:province":"TX",
    "sg:tags":[
        "business"
    ],
    "wof:name":"Dorsey Consultants Inc",
    "wof:placetype":"venue"
},
  "geometry": {"coordinates":[-97.743571,28.4117],"type":"Point"}
}