{
  "type": "Feature",
  "properties": {
    "iso:country":"US",
    "sg:address":"350 FM 2114",
    "sg:city":"Clifton",
    "sg:classifiers":[
        {
            "category":"Farming",
            "subcategory":"Fish & Marine Products",
            "type":"Manufacturing & Wholesale Goods"
        }
    ],
    "sg:phone":"+1 254 722 1336",
    "sg:postcode":"76691",
    "sg:province":"TX",
    "sg:tags":[
        "pigeon",
        "trapping"
    ],
    "wof:name":"Marvin R Mynar",
    "wof:placetype":"venue"
},
  "geometry": {"coordinates":[-97.08930599999999,31.801892],"type":"Point"}
}