{
  "type": "Feature",
  "properties": {
    "iso:country":"US",
    "sg:address":"503 N College Ave",
    "sg:city":"Snyder",
    "sg:classifiers":[
        {
            "category":"Restaurant",
            "type":"Food & Drink"
        }
    ],
    "sg:phone":"+1 325 573 5555",
    "sg:postcode":"79549",
    "sg:province":"TX",
    "wof:name":"El Ranchito Cafe",
    "wof:placetype":"venue"
},
  "geometry": {"coordinates":[-100.918798,32.746491],"type":"Point"}
}