{
  "type": "Feature",
  "properties": {
    "iso:country":"US",
    "sg:address":"3033 W Parker Rd",
    "sg:city":"Plano",
    "sg:classifiers":[
        {
            "category":"Personal",
            "subcategory":"Beauty Salon",
            "type":"Services"
        }
    ],
    "sg:phone":"+1 972 964 8466",
    "sg:postcode":"75023",
    "sg:province":"TX",
    "sg:tags":[
        "treatment",
        "skin"
    ],
    "wof:name":"Skin Deep & Beyond",
    "wof:placetype":"venue"
},
  "geometry": {"coordinates":[-96.752898,33.041194],"type":"Point"}
}