{
  "type": "Feature",
  "properties": {
    "iso:country":"US",
    "sg:address":"2601 N Navarro St",
    "sg:city":"Victoria",
    "sg:classifiers":[
        {
            "category":"Restaurant",
            "type":"Food & Drink"
        }
    ],
    "sg:menulink":"http://www.allmenus.com/tx/victoria/166015-arbys/menu/",
    "sg:phone":"+1 361 545 2729",
    "sg:postcode":"77901",
    "sg:province":"TX",
    "sg:tags":[
        "burger",
        "american"
    ],
    "wof:name":"Arby's",
    "wof:placetype":"venue"
},
  "geometry": {"coordinates":[-97.000367,28.818713],"type":"Point"}
}