{
  "type": "Feature",
  "properties": {
    "iso:country":"US",
    "sg:address":"5405 S Mccoll Rd",
    "sg:city":"Edinburg",
    "sg:classifiers":[
        {
            "category":"Health Services",
            "subcategory":"Dentist",
            "type":"Services"
        }
    ],
    "sg:phone":"+1 956 668 1780",
    "sg:postcode":"78539",
    "sg:province":"TX",
    "sg:tags":[
        "product",
        "dentists-cosmetic",
        "dental",
        "teeth",
        "dentists-pediatric",
        "clinic",
        "whitening",
        "dentistry",
        "implant",
        "dentists-implantology"
    ],
    "sg:website":"http://www.drdelafuente.com",
    "wof:name":"De La Fuente Julio C., DDS, P.A.",
    "wof:placetype":"venue"
},
  "geometry": {"coordinates":[-98.202538,26.261543],"type":"Point"}
}