{
  "type": "Feature",
  "properties": {
    "iso:country":"US",
    "sg:address":"322 Glenmore St",
    "sg:city":"Corpus Christi",
    "sg:classifiers":[
        {
            "category":"Social Services",
            "subcategory":"Child Care",
            "type":"Services"
        }
    ],
    "sg:phone":"+1 361 986 9933",
    "sg:postcode":"78412",
    "sg:province":"TX",
    "sg:tags":[
        "day"
    ],
    "wof:name":"Funf Kinder Corp",
    "wof:placetype":"venue"
},
  "geometry": {"coordinates":[-97.342812,27.721521],"type":"Point"}
}