{
  "type": "Feature",
  "properties": {
    "iso:country":"US",
    "sg:address":"1417 Palo Duro Rd",
    "sg:city":"Austin",
    "sg:classifiers":[
        {
            "category":"Real Estate",
            "subcategory":"Architect",
            "type":"Services"
        }
    ],
    "sg:phone":"+1 512 323 2017",
    "sg:postcode":"78757",
    "sg:province":"TX",
    "sg:tags":[
        "architectural"
    ],
    "wof:name":"Leighton-Burwell Don",
    "wof:placetype":"venue"
},
  "geometry": {"coordinates":[-97.733906,30.332907],"type":"Point"}
}