{
  "type": "Feature",
  "properties": {
    "iso:country":"US",
    "sg:address":"1816 Sam Houston St",
    "sg:city":"Liberty",
    "sg:classifiers":[
        {
            "category":"Restaurant",
            "type":"Food & Drink"
        }
    ],
    "sg:phone":"+1 936 336 6103",
    "sg:postcode":"77575",
    "sg:province":"TX",
    "wof:name":"Opry Cafe",
    "wof:placetype":"venue"
},
  "geometry": {"coordinates":[-94.797235,30.058724],"type":"Point"}
}