{
  "type": "Feature",
  "properties": {
    "iso:country":"US",
    "sg:address":"1400 S Sherman St",
    "sg:city":"Richardson",
    "sg:classifiers":[
        {
            "category":"Retail",
            "subcategory":"Laundry & Dry Cleaning",
            "type":"Services"
        },
        {
            "category":"Building & Trades",
            "subcategory":"Cleaning & Sanitation",
            "type":"Services"
        }
    ],
    "sg:phone":"+1 972 235 7503",
    "sg:postcode":"75081",
    "sg:province":"TX",
    "sg:tags":[
        "cleaner",
        "upholstery",
        "rug",
        "carpet"
    ],
    "wof:name":"Enviroclean & Restoration",
    "wof:placetype":"venue"
},
  "geometry": {"coordinates":[-96.744722,32.933842],"type":"Point"}
}