{
  "type": "Feature",
  "properties": {
    "iso:country":"US",
    "sg:address":"1114 N Margaret Ave",
    "sg:city":"Kirbyville",
    "sg:classifiers":[
        {
            "category":"Autos & Motor Vehicles",
            "subcategory":"Fuel & Gas Station",
            "type":"Retail Goods"
        }
    ],
    "sg:phone":"+1 409 423 5135",
    "sg:postcode":"75956",
    "sg:province":"TX",
    "sg:tags":[
        "station",
        "gasoline"
    ],
    "wof:name":"Pearson Gulf Service Station",
    "wof:placetype":"venue"
},
  "geometry": {"coordinates":[-93.89363299999999,30.668556],"type":"Point"}
}