{
  "type": "Feature",
  "properties": {
    "iso:country":"US",
    "sg:address":"105 Larue St",
    "sg:city":"Athens",
    "sg:classifiers":[
        {
            "category":"Professional",
            "subcategory":"Accounting & Tax Preparation",
            "type":"Services"
        }
    ],
    "sg:phone":"+1 903 677 3762",
    "sg:postcode":"75751",
    "sg:province":"TX",
    "sg:tags":[
        "return",
        "preparation-business"
    ],
    "wof:name":"Elite Tax Service",
    "wof:placetype":"venue"
},
  "geometry": {"coordinates":[-95.855194,32.20132],"type":"Point"}
}