{
  "type": "Feature",
  "properties": {
    "iso:country":"US",
    "sg:address":"290 N Texas St",
    "sg:city":"De Leon",
    "sg:classifiers":[
        {
            "category":"Professional",
            "type":"Services"
        }
    ],
    "sg:phone":"+1 254 893 7399",
    "sg:postcode":"76444",
    "sg:province":"TX",
    "sg:tags":[
        "establishment"
    ],
    "wof:name":"Deleon Independent Farmers Mkt",
    "wof:placetype":"venue"
},
  "geometry": {"coordinates":[-98.536777,32.109968],"type":"Point"}
}