{
  "type": "Feature",
  "properties": {
    "iso:country":"US",
    "sg:address":"1522 W Sam Rayburn Dr",
    "sg:city":"Bonham",
    "sg:phone":"+1 866 457 2603",
    "sg:postcode":"75418",
    "sg:province":"TX",
    "sg:website":"http://www.bonhamchrysler.com",
    "wof:name":"Bonham Chrysler",
    "wof:placetype":"venue"
},
  "geometry": {"coordinates":[-96.199493,33.57061],"type":"Point"}
}