{
  "type": "Feature",
  "properties": {
    "iso:country":"US",
    "sg:address":"6430 Dew Dr",
    "sg:city":"San Antonio",
    "sg:classifiers":[
        {
            "category":"Building & Trades",
            "subcategory":"Plumbing",
            "type":"Services"
        }
    ],
    "sg:phone":"+1 210 564 0778",
    "sg:postcode":"78239",
    "sg:province":"TX",
    "sg:tags":[
        "conditioning",
        "air",
        "system",
        "contractor"
    ],
    "wof:name":"Ben Aer Of Texas",
    "wof:placetype":"venue"
},
  "geometry": {"coordinates":[-98.36160099999999,29.513788],"type":"Point"}
}