{
  "type": "Feature",
  "properties": {
    "iso:country":"US",
    "sg:address":"239 Canyon Valley Dr",
    "sg:city":"Richardson",
    "sg:classifiers":[
        {
            "category":"Manufacturing",
            "subcategory":"Metals",
            "type":"Manufacturing & Wholesale Goods"
        }
    ],
    "sg:phone":"+1 972 644 0462",
    "sg:postcode":"75080",
    "sg:province":"TX",
    "sg:tags":[
        "blast",
        "furnace",
        "works"
    ],
    "wof:name":"On Line Armory",
    "wof:placetype":"venue"
},
  "geometry": {"coordinates":[-96.716712,32.994172],"type":"Point"}
}