{
  "type": "Feature",
  "properties": {
    "iso:country":"US",
    "sg:address":"6121 Kenwood Ave",
    "sg:city":"Dallas",
    "sg:classifiers":[
        {
            "category":"Health Services",
            "subcategory":"Doctor",
            "type":"Services"
        }
    ],
    "sg:phone":"+1 214 823 8945",
    "sg:postcode":"75214",
    "sg:province":"TX",
    "sg:tags":[
        "dentist"
    ],
    "wof:name":"Carolyn Wilson DDS",
    "wof:placetype":"venue"
},
  "geometry": {"coordinates":[-96.75881200000001,32.833321],"type":"Point"}
}