{
  "type": "Feature",
  "properties": {
    "iso:country":"US",
    "sg:address":"5100 Laguna Cir N",
    "sg:city":"S Padre Island",
    "sg:classifiers":[
        {
            "category":"Utilities",
            "subcategory":"Mobile Phone",
            "type":"Services"
        }
    ],
    "sg:phone":"+1 956 761 6009",
    "sg:postcode":"78597",
    "sg:province":"TX",
    "sg:tags":[
        "telephone",
        "cellular"
    ],
    "wof:name":"Cellular One Of The Rio Grande",
    "wof:placetype":"venue"
},
  "geometry": {"coordinates":[-97.17558,26.131217],"type":"Point"}
}