{
  "type": "Feature",
  "properties": {
    "iso:country":"US",
    "sg:address":"2375 Montgomery Park Blvd",
    "sg:city":"Conroe",
    "sg:classifiers":[
        {
            "category":"Professional",
            "type":"Services"
        }
    ],
    "sg:phone":"+1 936 709 7300",
    "sg:postcode":"77304",
    "sg:province":"TX",
    "sg:tags":[
        "establishment"
    ],
    "wof:name":"Cryar Intermediate",
    "wof:placetype":"venue"
},
  "geometry": {"coordinates":[-95.48685500000001,30.331422],"type":"Point"}
}