{
  "type": "Feature",
  "properties": {
    "iso:country":"US",
    "sg:address":"220 Odell St",
    "sg:city":"San Antonio",
    "sg:classifiers":[
        {
            "category":"Retail",
            "subcategory":"Auto Repair",
            "type":"Services"
        }
    ],
    "sg:phone":"+1 210 930 4117",
    "sg:postcode":"78212",
    "sg:province":"TX",
    "sg:tags":[
        "automotive"
    ],
    "wof:name":"Kevin Flower",
    "wof:placetype":"venue"
},
  "geometry": {"coordinates":[-98.49521,29.473597],"type":"Point"}
}