{
  "type": "Feature",
  "properties": {
    "iso:country":"US",
    "sg:address":"3000 Central Blvd",
    "sg:city":"Brownsville",
    "sg:classifiers":[
        {
            "category":"Banks & Credit Unions",
            "subcategory":"Bank",
            "type":"Services"
        }
    ],
    "sg:phone":"+1 956 542 9858",
    "sg:postcode":"78520",
    "sg:province":"TX",
    "sg:tags":[
        "personal",
        "commercial",
        "ba",
        "mortgage",
        "institution"
    ],
    "wof:name":"Rio National Bank",
    "wof:placetype":"venue"
},
  "geometry": {"coordinates":[-97.508988,25.943586],"type":"Point"}
}