{
  "type": "Feature",
  "properties": {
    "iso:country":"US",
    "sg:address":"11207 Windjammer Dr",
    "sg:city":"Frisco",
    "sg:classifiers":[
        {
            "category":"Shopping",
            "subcategory":"Computers & Home Electronics",
            "type":"Retail Goods"
        }
    ],
    "sg:phone":"+1 972 625 8614",
    "sg:postcode":"75034",
    "sg:province":"TX",
    "sg:tags":[
        "software"
    ],
    "wof:name":"Two By Two Resources",
    "wof:placetype":"venue"
},
  "geometry": {"coordinates":[-96.929329,33.118423],"type":"Point"}
}