{
  "type": "Feature",
  "properties": {
    "iso:country":"US",
    "sg:address":"423 N Main St",
    "sg:city":"Childress",
    "sg:classifiers":[
        {
            "category":"Banks & Credit Unions",
            "subcategory":"Bank",
            "type":"Services"
        }
    ],
    "sg:phone":"+1 940 937 8686",
    "sg:postcode":"79201",
    "sg:province":"TX",
    "sg:tags":[
        "commercial",
        "state",
        "saving",
        "institution",
        "business"
    ],
    "sg:website":"http://www.wellingtonsb.com",
    "wof:name":"Wellington State Bank",
    "wof:placetype":"venue"
},
  "geometry": {"coordinates":[-100.205375,34.424748],"type":"Point"}
}