{
  "type": "Feature",
  "properties": {
    "iso:country":"US",
    "sg:address":"724 S Eddy St",
    "sg:city":"Pecos",
    "sg:classifiers":[
        {
            "category":"Shopping",
            "subcategory":"Gifts & Souvenirs",
            "type":"Retail Goods"
        }
    ],
    "sg:phone":"+1 432 445 4916",
    "sg:postcode":"79772",
    "sg:province":"TX",
    "sg:tags":[
        "shop"
    ],
    "wof:name":"Rediger's Pharmacy",
    "wof:placetype":"venue"
},
  "geometry": {"coordinates":[-103.50228300000001,31.418388],"type":"Point"}
}