{
  "type": "Feature",
  "properties": {
    "iso:country":"US",
    "sg:address":"508 Cupples Rd",
    "sg:city":"San Antonio",
    "sg:classifiers":[
        {
            "category":"Social Services",
            "subcategory":"Child Care",
            "type":"Services"
        }
    ],
    "sg:phone":"+1 210 434 7135",
    "sg:postcode":"78237",
    "sg:province":"TX",
    "sg:tags":[
        "day"
    ],
    "wof:name":"Little Smiles Day Care",
    "wof:placetype":"venue"
},
  "geometry": {"coordinates":[-98.54773400000001,29.40867],"type":"Point"}
}