{
  "type": "Feature",
  "properties": {
    "iso:country":"US",
    "sg:address":"734 Crabb River Rd",
    "sg:city":"Richmond",
    "sg:classifiers":[
        {
            "category":"Restaurant",
            "type":"Food & Drink"
        }
    ],
    "sg:phone":"+1 281 343 9104",
    "sg:postcode":"77469",
    "sg:province":"TX",
    "wof:name":"Nino's Grill",
    "wof:placetype":"venue"
},
  "geometry": {"coordinates":[-95.69883799999999,29.544892],"type":"Point"}
}