{
  "type": "Feature",
  "properties": {
    "iso:country":"US",
    "sg:address":"621 Hardwood Trl",
    "sg:city":"Mesquite",
    "sg:classifiers":[
        {
            "category":"Health Services",
            "subcategory":"Clinic",
            "type":"Services"
        }
    ],
    "sg:phone":"+1 972 270 9851",
    "sg:postcode":"75150",
    "sg:province":"TX",
    "wof:name":"Lewis Unlimited Resources",
    "wof:placetype":"venue"
},
  "geometry": {"coordinates":[-96.604686,32.819174],"type":"Point"}
}