{
  "type": "Feature",
  "properties": {
    "iso:country":"US",
    "sg:address":"109 Halvern Dr",
    "sg:city":"San Antonio",
    "sg:classifiers":[
        {
            "category":"Freight",
            "type":"Transportation"
        }
    ],
    "sg:phone":"+1 210 647 4642",
    "sg:postcode":"78228",
    "sg:province":"TX",
    "sg:tags":[
        "operator",
        "local",
        "trucking"
    ],
    "wof:name":"Amazon Movers",
    "wof:placetype":"venue"
},
  "geometry": {"coordinates":[-98.566689,29.458846],"type":"Point"}
}