{
  "type": "Feature",
  "properties": {
    "iso:country":"US",
    "sg:address":"4733 E Lancaster Ave",
    "sg:city":"Fort Worth",
    "sg:classifiers":[
        {
            "category":"Government",
            "subcategory":"Office",
            "type":"Public Place"
        }
    ],
    "sg:phone":"+1 817 536 3353",
    "sg:postcode":"76103",
    "sg:province":"TX",
    "sg:tags":[
        "program",
        "administrative"
    ],
    "wof:name":"Human Services Texas Dept of",
    "wof:placetype":"venue"
},
  "geometry": {"coordinates":[-97.252577,32.741089],"type":"Point"}
}