{
  "type": "Feature",
  "properties": {
    "iso:country":"US",
    "sg:address":"17492 Northwest Fwy",
    "sg:city":"Houston",
    "sg:classifiers":[
        {
            "category":"Restaurant",
            "type":"Food & Drink"
        }
    ],
    "sg:menulink":"http://www.allmenus.com/tx/houston/45494-willies-grill--icehouse/menu/",
    "sg:phone":"+1 713 937 0456",
    "sg:postcode":"77040",
    "sg:province":"TX",
    "sg:tags":[
        "american"
    ],
    "wof:name":"Willie's Grill & Icehouse",
    "wof:placetype":"venue"
},
  "geometry": {"coordinates":[-95.58407,29.891881],"type":"Point"}
}