{
  "type": "Feature",
  "properties": {
    "iso:country":"US",
    "sg:address":"17000 Dallas Pkwy Ste 211",
    "sg:city":"Dallas",
    "sg:classifiers":[
        {
            "category":"Professional",
            "subcategory":"Lawyer & Legal Services",
            "type":"Services"
        }
    ],
    "sg:phone":"+1 972 267 0300",
    "sg:postcode":"75248",
    "sg:province":"TX",
    "sg:website":"www.lloydsgastwirth.com",
    "wof:name":"Gastwirth Lloyd S Atty",
    "wof:placetype":"venue"
},
  "geometry": {"coordinates":[-96.82849899999999,32.981701],"type":"Point"}
}