{
  "type": "Feature",
  "properties": {
    "iso:country":"US",
    "sg:address":"170 Westcott St",
    "sg:city":"Houston",
    "sg:classifiers":[
        {
            "category":"Professional",
            "subcategory":"Advertising",
            "type":"Services"
        }
    ],
    "sg:phone":"+1 713 880 1533",
    "sg:postcode":"77007",
    "sg:province":"TX",
    "sg:tags":[
        "counselor"
    ],
    "wof:name":"Ensight Marketing Svc",
    "wof:placetype":"venue"
},
  "geometry": {"coordinates":[-95.421431,29.76176],"type":"Point"}
}