{
  "type": "Feature",
  "properties": {
    "iso:country":"US",
    "sg:address":"28209 McLelland Rd",
    "sg:city":"Harlingen",
    "sg:classifiers":[
        {
            "category":"Professional",
            "subcategory":"Management & Consulting",
            "type":"Services"
        }
    ],
    "sg:phone":"+1 956 428 2662",
    "sg:postcode":"78552",
    "sg:province":"TX",
    "sg:tags":[
        "business"
    ],
    "wof:name":"Law Communications",
    "wof:placetype":"venue"
},
  "geometry": {"coordinates":[-97.78648200000001,26.150605],"type":"Point"}
}