{
  "type": "Feature",
  "properties": {
    "iso:country":"US",
    "sg:address":"3320 Hwy 365",
    "sg:city":"Nederland",
    "sg:classifiers":[
        {
            "category":"Home & Garden",
            "subcategory":"Household Appliances",
            "type":"Retail Goods"
        }
    ],
    "sg:phone":"+1 409 721 6760",
    "sg:postcode":"77627",
    "sg:province":"TX",
    "sg:tags":[
        "cleaners",
        "vacuum"
    ],
    "wof:name":"Vacuum City",
    "wof:placetype":"venue"
},
  "geometry": {"coordinates":[-93.990562,29.949741],"type":"Point"}
}