{
  "type": "Feature",
  "properties": {
    "iso:country":"US",
    "sg:address":"2010 N Plano Rd Ste 101",
    "sg:city":"Richardson",
    "sg:classifiers":[
        {
            "category":"Health Services",
            "subcategory":"Chiropractor",
            "type":"Services"
        }
    ],
    "sg:phone":"+1 972 479 1200",
    "sg:postcode":"75082",
    "sg:province":"TX",
    "wof:name":"Stansbury Chiropractic Center PC",
    "wof:placetype":"venue"
},
  "geometry": {"coordinates":[-96.699699,32.975201],"type":"Point"}
}