{
  "type": "Feature",
  "properties": {
    "iso:country":"US",
    "sg:address":"200 S 10th St",
    "sg:city":"Mcallen",
    "sg:classifiers":[
        {
            "category":"Wholesale",
            "subcategory":"Jewelry",
            "type":"Manufacturing & Wholesale Goods"
        }
    ],
    "sg:phone":"+1 956 971 0840",
    "sg:postcode":"78501",
    "sg:province":"TX",
    "sg:tags":[
        "jeweler"
    ],
    "wof:name":"Gold Direct",
    "wof:placetype":"venue"
},
  "geometry": {"coordinates":[-98.23035299999999,26.201584],"type":"Point"}
}