{
  "type": "Feature",
  "properties": {
    "iso:country":"US",
    "sg:address":"910 S Hampton Rd",
    "sg:city":"Dallas",
    "sg:classifiers":[
        {
            "category":"Personal",
            "subcategory":"Beauty Salon",
            "type":"Services"
        }
    ],
    "sg:phone":"+1 214 941 6700",
    "sg:postcode":"75208",
    "sg:province":"TX",
    "sg:tags":[
        "shop"
    ],
    "wof:name":"M C Salon",
    "wof:placetype":"venue"
},
  "geometry": {"coordinates":[-96.856661,32.73491],"type":"Point"}
}