{
  "type": "Feature",
  "properties": {
    "iso:country":"US",
    "sg:address":"9100 Decker Lake Rd",
    "sg:city":"Austin",
    "sg:classifiers":[
        {
            "category":"Farming",
            "subcategory":"Farm & Veterinary Services",
            "type":"Manufacturing & Wholesale Goods"
        }
    ],
    "sg:phone":"+1 512 919 3000",
    "sg:postcode":"78724",
    "sg:province":"TX",
    "sg:tags":[
        "livestock"
    ],
    "wof:name":"Rodeo Austin",
    "wof:placetype":"venue"
},
  "geometry": {"coordinates":[-97.625024,30.289194],"type":"Point"}
}