{
  "type": "Feature",
  "properties": {
    "iso:country":"US",
    "sg:address":"5209 Hill Ridge Dr",
    "sg:city":"Fort Worth",
    "sg:classifiers":[
        {
            "category":"Building & Trades",
            "subcategory":"Construction",
            "type":"Services"
        }
    ],
    "sg:phone":"+1 817 238 6064",
    "sg:postcode":"76135",
    "sg:province":"TX",
    "sg:tags":[
        "marking",
        "maintenance",
        "parking"
    ],
    "wof:name":"All In One Mobile Powerwashing",
    "wof:placetype":"venue"
},
  "geometry": {"coordinates":[-97.42308300000001,32.829353],"type":"Point"}
}