{
  "type": "Feature",
  "properties": {
    "iso:country":"US",
    "sg:address":"1725 S Marrs St",
    "sg:city":"Amarillo",
    "sg:classifiers":[
        {
            "category":"Building & Trades",
            "subcategory":"Cleaning & Sanitation",
            "type":"Services"
        }
    ],
    "sg:phone":"+1 806 376 9328",
    "sg:postcode":"79103",
    "sg:province":"TX",
    "sg:tags":[
        "maintenance"
    ],
    "wof:name":"J D Springs",
    "wof:placetype":"venue"
},
  "geometry": {"coordinates":[-101.801925,35.191125],"type":"Point"}
}