{
  "type": "Feature",
  "properties": {
    "iso:country":"US",
    "sg:address":"16722 Sonoma del Norte Dr",
    "sg:city":"Houston",
    "sg:classifiers":[
        {
            "category":"Building & Trades",
            "subcategory":"Plumbing",
            "type":"Services"
        }
    ],
    "sg:phone":"+1 281 256 0337",
    "sg:postcode":"77095",
    "sg:province":"TX",
    "sg:tags":[
        "contractor"
    ],
    "wof:name":"Total Strength & Conditioning",
    "wof:placetype":"venue"
},
  "geometry": {"coordinates":[-95.670272,29.931472],"type":"Point"}
}