{
  "type": "Feature",
  "properties": {
    "iso:country":"US",
    "sg:address":"5703 Deer Shadow Ct",
    "sg:city":"Houston",
    "sg:classifiers":[
        {
            "category":"Professional",
            "subcategory":"Computer Services",
            "type":"Services"
        }
    ],
    "sg:phone":"+1 713 983 9535",
    "sg:postcode":"77041",
    "sg:province":"TX",
    "sg:tags":[
        "programing",
        "custom"
    ],
    "wof:name":"Petrasoft",
    "wof:placetype":"venue"
},
  "geometry": {"coordinates":[-95.604302,29.854508],"type":"Point"}
}