{
  "type": "Feature",
  "properties": {
    "iso:country":"US",
    "sg:address":"602 S F St",
    "sg:city":"Harlingen",
    "sg:classifiers":[
        {
            "category":"Banks & Credit Unions",
            "subcategory":"Bank",
            "type":"Services"
        }
    ],
    "sg:phone":"+1 956 444 0062",
    "sg:postcode":"78550",
    "sg:province":"TX",
    "sg:tags":[
        "mortgage"
    ],
    "wof:name":"Challange Mortgage Co",
    "wof:placetype":"venue"
},
  "geometry": {"coordinates":[-97.70220999999999,26.18728],"type":"Point"}
}