{
  "type": "Feature",
  "properties": {
    "iso:country":"US",
    "sg:address":"6005 FM 1960 W",
    "sg:city":"Houston",
    "sg:classifiers":[
        {
            "category":"Retail",
            "subcategory":"Auto Repair",
            "type":"Services"
        }
    ],
    "sg:phone":"+1 281 397 0887",
    "sg:postcode":"77069",
    "sg:province":"TX",
    "sg:tags":[
        "automobile",
        "inspection"
    ],
    "wof:name":"Mr Sticker",
    "wof:placetype":"venue"
},
  "geometry": {"coordinates":[-95.516172,29.978124],"type":"Point"}
}