{
  "type": "Feature",
  "properties": {
    "iso:country":"US",
    "sg:address":"2603 S Quail Run Ct",
    "sg:city":"Southlake",
    "sg:classifiers":[
        {
            "category":"Wholesale",
            "subcategory":"Medical Equipment & Supplies",
            "type":"Manufacturing & Wholesale Goods"
        }
    ],
    "sg:phone":"+1 817 424 1744",
    "sg:postcode":"76092",
    "sg:province":"TX",
    "sg:tags":[
        "physician",
        "surgeon"
    ],
    "wof:name":"S W Med Source",
    "wof:placetype":"venue"
},
  "geometry": {"coordinates":[-97.136323,32.975505],"type":"Point"}
}