{
  "type": "Feature",
  "properties": {
    "iso:country":"US",
    "sg:address":"4501 Pyeatt Dr",
    "sg:city":"Gladewater",
    "sg:classifiers":[
        {
            "category":"Shopping",
            "subcategory":"Hobbies, Toys, & Games",
            "type":"Retail Goods"
        }
    ],
    "sg:phone":"+1 903 758 5404",
    "sg:postcode":"75647",
    "sg:province":"TX",
    "sg:tags":[
        "craft"
    ],
    "wof:name":"Illusions By Dawn",
    "wof:placetype":"venue"
},
  "geometry": {"coordinates":[-94.907462,32.565404],"type":"Point"}
}