{
  "type": "Feature",
  "properties": {
    "iso:country":"US",
    "sg:address":"1610 Co Rd 439",
    "sg:city":"Thorndale",
    "sg:classifiers":[
        {
            "category":"Building & Trades",
            "subcategory":"Construction",
            "type":"Services"
        }
    ],
    "sg:phone":"+1 512 898 2141",
    "sg:postcode":"76577",
    "sg:province":"TX",
    "sg:tags":[
        "excavating",
        "contractor"
    ],
    "wof:name":"R A Huber Enterprise",
    "wof:placetype":"venue"
},
  "geometry": {"coordinates":[-97.19341799999999,30.541404],"type":"Point"}
}