{
  "type": "Feature",
  "properties": {
    "iso:country":"US",
    "sg:address":"414 Grapevine Hwy",
    "sg:city":"Hurst",
    "sg:classifiers":[
        {
            "category":"Autos & Motor Vehicles",
            "subcategory":"Auto Supplies",
            "type":"Retail Goods"
        }
    ],
    "sg:phone":"+1 817 581 7409",
    "sg:postcode":"76054",
    "sg:province":"TX",
    "sg:tags":[
        "automobile",
        "parts"
    ],
    "wof:name":"Mike's Xclusive Custom",
    "wof:placetype":"venue"
},
  "geometry": {"coordinates":[-97.172985,32.866575],"type":"Point"}
}