{
  "type": "Feature",
  "properties": {
    "iso:country":"US",
    "sg:address":"243 Black Oak Cir",
    "sg:city":"Coppell",
    "sg:classifiers":[
        {
            "category":"Professional",
            "type":"Services"
        }
    ],
    "sg:phone":"+1 972 304 0093",
    "sg:postcode":"75019",
    "sg:province":"TX",
    "wof:name":"Family First Relo LLC",
    "wof:placetype":"venue"
},
  "geometry": {"coordinates":[-96.995537,32.976062],"type":"Point"}
}