{
  "type": "Feature",
  "properties": {
    "iso:country":"US",
    "sg:address":"1071 E Oak Shores Dr",
    "sg:city":"Crossroads",
    "sg:classifiers":[
        {
            "category":"Wholesale",
            "subcategory":"Groceries",
            "type":"Manufacturing & Wholesale Goods"
        }
    ],
    "sg:phone":"+1 940 365 1328",
    "sg:postcode":"76227",
    "sg:province":"TX",
    "sg:tags":[
        "baker"
    ],
    "wof:name":"Sara Lee",
    "wof:placetype":"venue"
},
  "geometry": {"coordinates":[-97.009781,33.205883],"type":"Point"}
}