{
  "type": "Feature",
  "properties": {
    "iso:country":"US",
    "sg:address":"216 N Houston St",
    "sg:city":"Comanche",
    "sg:classifiers":[
        {
            "category":"Education",
            "subcategory":"School",
            "type":"Public Place"
        }
    ],
    "sg:phone":"+1 325 356 7599",
    "sg:postcode":"76442",
    "sg:province":"TX",
    "wof:name":"Comanche Christian Academy",
    "wof:placetype":"venue"
},
  "geometry": {"coordinates":[-98.60497100000001,31.899207],"type":"Point"}
}