{
  "type": "Feature",
  "properties": {
    "iso:country":"US",
    "sg:address":"5832 Lyle St",
    "sg:city":"Fort Worth",
    "sg:classifiers":[
        {
            "category":"Communications",
            "subcategory":"Film & Video Production",
            "type":"Services"
        }
    ],
    "sg:phone":"+1 817 738 7720",
    "sg:postcode":"76114",
    "sg:province":"TX",
    "sg:tags":[
        "motion"
    ],
    "wof:name":"Lickatoad Productions",
    "wof:placetype":"venue"
},
  "geometry": {"coordinates":[-97.414511,32.757249],"type":"Point"}
}