{
  "type": "Feature",
  "properties": {
    "iso:country":"US",
    "sg:address":"8548 Northview Pass",
    "sg:city":"Fair Oaks Ranch",
    "sg:classifiers":[
        {
            "category":"Professional",
            "subcategory":"Secretarial Services",
            "type":"Services"
        }
    ],
    "sg:phone":"+1 830 981 5545",
    "sg:postcode":"78015",
    "sg:province":"TX",
    "sg:tags":[
        "convention",
        "court",
        "reporter"
    ],
    "wof:name":"Gaddis Court Reporting",
    "wof:placetype":"venue"
},
  "geometry": {"coordinates":[-98.64715200000001,29.732945],"type":"Point"}
}