{
  "type": "Feature",
  "properties": {
    "iso:country":"US",
    "sg:address":"905 Champions Dr",
    "sg:city":"Lufkin",
    "sg:classifiers":[
        {
            "category":"Manufacturing",
            "subcategory":"Lumber",
            "type":"Manufacturing & Wholesale Goods"
        }
    ],
    "sg:phone":"+1 936 637 1254",
    "sg:postcode":"75901",
    "sg:province":"TX",
    "sg:tags":[
        "forestry"
    ],
    "wof:name":"Stiff Applied Technology",
    "wof:placetype":"venue"
},
  "geometry": {"coordinates":[-94.72187,31.281751],"type":"Point"}
}