{
  "type": "Feature",
  "properties": {
    "iso:country":"US",
    "sg:address":"2509 Lakeview Dr",
    "sg:city":"Amarillo",
    "sg:classifiers":[
        {
            "category":"Insurance",
            "subcategory":"Insurance Agent",
            "type":"Services"
        }
    ],
    "sg:phone":"+1 806 468 9550",
    "sg:postcode":"79109",
    "sg:province":"TX",
    "wof:name":"Jill Mathews Insurance",
    "wof:placetype":"venue"
},
  "geometry": {"coordinates":[-101.87490099999999,35.188283],"type":"Point"}
}