{
  "type": "Feature",
  "properties": {
    "iso:country":"US",
    "sg:address":"11916 W Mile 7 Rd",
    "sg:city":"Mission",
    "sg:classifiers":[
        {
            "category":"Structure",
            "subcategory":"Office Building",
            "type":"Public Place"
        }
    ],
    "sg:phone":"+1 956 584 8022",
    "sg:postcode":"78573",
    "sg:province":"TX",
    "sg:tags":[
        "park"
    ],
    "wof:name":"Sequel Properties Ii, Ltd.",
    "wof:placetype":"venue"
},
  "geometry": {"coordinates":[-98.286846,26.313046],"type":"Point"}
}