{
  "type": "Feature",
  "properties": {
    "iso:country":"US",
    "sg:address":"11818 Fairpoint Dr",
    "sg:city":"Houston",
    "sg:classifiers":[
        {
            "category":"Shopping",
            "subcategory":"Clothing, Apparel, & Fashions",
            "type":"Retail Goods"
        }
    ],
    "sg:phone":"+1 281 879 9341",
    "sg:postcode":"77099",
    "sg:province":"TX",
    "wof:name":"Mens Touch",
    "wof:placetype":"venue"
},
  "geometry": {"coordinates":[-95.587098,29.669177],"type":"Point"}
}