{
  "type": "Feature",
  "properties": {
    "iso:country":"US",
    "sg:address":"6457 Sweetgum St",
    "sg:city":"Katy",
    "sg:classifiers":[
        {
            "category":"Professional",
            "subcategory":"Management & Consulting",
            "type":"Services"
        }
    ],
    "sg:phone":"+1 281 391 1122",
    "sg:postcode":"77493",
    "sg:province":"TX",
    "wof:name":"Wayne Scott Management LLC",
    "wof:placetype":"venue"
},
  "geometry": {"coordinates":[-95.832652,29.815951],"type":"Point"}
}