{
  "type": "Feature",
  "properties": {
    "iso:country":"US",
    "sg:address":"2751 S Staples St",
    "sg:city":"Corpus Christi",
    "sg:classifiers":[
        {
            "category":"Home & Garden",
            "subcategory":"Household Appliances",
            "type":"Retail Goods"
        },
        {
            "category":"Retail",
            "subcategory":"Repair Shop",
            "type":"Services"
        }
    ],
    "sg:phone":"+1 361 854 1851",
    "sg:postcode":"78404",
    "sg:province":"TX",
    "sg:tags":[
        "small",
        "electrical"
    ],
    "wof:name":"Brand Appliances & Microwave",
    "wof:placetype":"venue"
},
  "geometry": {"coordinates":[-97.402675,27.761506],"type":"Point"}
}