{
  "type": "Feature",
  "properties": {
    "iso:country":"US",
    "sg:address":"234 E Elizabeth St",
    "sg:city":"Brownsville",
    "sg:classifiers":[
        {
            "category":"Home & Garden",
            "subcategory":"Household Appliances",
            "type":"Retail Goods"
        }
    ],
    "sg:phone":"+1 956 542 3333",
    "sg:postcode":"78520",
    "sg:province":"TX",
    "wof:name":"Stevenson's Appliances",
    "wof:placetype":"venue"
},
  "geometry": {"coordinates":[-97.50483,25.907259],"type":"Point"}
}