{
  "type": "Feature",
  "properties": {
    "iso:country":"US",
    "sg:address":"803 E Main St",
    "sg:city":"Clarksville",
    "sg:classifiers":[
        {
            "category":"Government",
            "subcategory":"Office",
            "type":"Public Place"
        }
    ],
    "sg:phone":"+1 903 427 3867",
    "sg:postcode":"75426",
    "sg:province":"TX",
    "wof:name":"Red River County Agents",
    "wof:placetype":"venue"
},
  "geometry": {"coordinates":[-95.043522,33.611946],"type":"Point"}
}