{
  "type": "Feature",
  "properties": {
    "iso:country":"US",
    "sg:address":"2005 Bayshore Dr",
    "sg:city":"Flower Mound",
    "sg:classifiers":[
        {
            "category":"Professional",
            "subcategory":"Management & Consulting",
            "type":"Services"
        }
    ],
    "sg:phone":"+1 972 724 2810",
    "sg:postcode":"75022",
    "sg:province":"TX",
    "sg:tags":[
        "marketing",
        "consultant"
    ],
    "wof:name":"Ingenuity Plus",
    "wof:placetype":"venue"
},
  "geometry": {"coordinates":[-97.125011,33.018455],"type":"Point"}
}