{
  "type": "Feature",
  "properties": {
    "iso:country":"US",
    "sg:address":"3503 Broadway St",
    "sg:city":"Pearland",
    "sg:classifiers":[
        {
            "category":"Restaurant",
            "type":"Food & Drink"
        }
    ],
    "sg:menulink":"http://www.allmenus.com/tx/alvin-pearland/218054-burger-king/menu/",
    "sg:phone":"+1 281 997 5559",
    "sg:postcode":"77581",
    "sg:province":"TX",
    "sg:tags":[
        "american"
    ],
    "wof:name":"Burger King",
    "wof:placetype":"venue"
},
  "geometry": {"coordinates":[-95.277743,29.562343],"type":"Point"}
}