{
  "type": "Feature",
  "properties": {
    "iso:country":"US",
    "sg:address":"5348 Davis Blvd",
    "sg:city":"N Richland Hills",
    "sg:classifiers":[
        {
            "category":"Insurance",
            "subcategory":"Insurance Agent",
            "type":"Services"
        }
    ],
    "sg:phone":"+1 817 281 6410",
    "sg:postcode":"76180",
    "sg:province":"TX",
    "wof:name":"Dan Sweeney",
    "wof:placetype":"venue"
},
  "geometry": {"coordinates":[-97.21422699999999,32.844683],"type":"Point"}
}