{
  "type": "Feature",
  "properties": {
    "iso:country":"US",
    "sg:address":"6844 1st St",
    "sg:city":"Canutillo",
    "sg:classifiers":[
        {
            "category":"Food & Beverages",
            "subcategory":"Liquor & Beverages",
            "type":"Retail Goods"
        }
    ],
    "sg:phone":"+1 915 877 4555",
    "sg:postcode":"79835",
    "sg:province":"TX",
    "sg:tags":[
        "beer",
        "ale"
    ],
    "wof:name":"Rocky's Beer & Beverage",
    "wof:placetype":"venue"
},
  "geometry": {"coordinates":[-106.599186,31.907737],"type":"Point"}
}