{
  "type": "Feature",
  "properties": {
    "iso:country":"US",
    "sg:address":"2525 Lillian Miller Pkwy",
    "sg:city":"Denton",
    "sg:classifiers":[
        {
            "category":"Health Services",
            "subcategory":"Nursing And Care Facility",
            "type":"Services"
        }
    ],
    "sg:phone":"+1 940 320 1926",
    "sg:postcode":"76210",
    "sg:province":"TX",
    "sg:tags":[
        "home",
        "retirement",
        "community"
    ],
    "wof:name":"Merrill Gardens At Denton",
    "wof:placetype":"venue"
},
  "geometry": {"coordinates":[-97.10829,33.18614],"type":"Point"}
}