{
  "type": "Feature",
  "properties": {
    "iso:country":"US",
    "sg:address":"9226 Premier Row",
    "sg:city":"Dallas",
    "sg:classifiers":[
        {
            "category":"Wholesale",
            "subcategory":"Groceries",
            "type":"Manufacturing & Wholesale Goods"
        }
    ],
    "sg:phone":"+1 214 631 7864",
    "sg:postcode":"75247",
    "sg:province":"TX",
    "sg:tags":[
        "food",
        "packaged",
        "broker"
    ],
    "wof:name":"Royal Food Distributors",
    "wof:placetype":"venue"
},
  "geometry": {"coordinates":[-96.89491200000001,32.817117],"type":"Point"}
}