{
  "type": "Feature",
  "properties": {
    "iso:country":"US",
    "sg:address":"512 E Riverside Drive",
    "sg:city":"Austin",
    "sg:classifiers":[
        {
            "category":"Professional",
            "subcategory":"Lawyer & Legal Services",
            "type":"Services"
        }
    ],
    "sg:phone":"+1 512 912 9233",
    "sg:postcode":"78704",
    "sg:province":"TX",
    "wof:name":"Hardy Law Firm",
    "wof:placetype":"venue"
},
  "geometry": {"coordinates":[-97.764692,30.239196],"type":"Point"}
}