{
  "type": "Feature",
  "properties": {
    "iso:country":"US",
    "sg:address":"541 S Walnut Ave",
    "sg:city":"New Braunfels",
    "sg:classifiers":[
        {
            "category":"Professional",
            "subcategory":"Business Services",
            "type":"Services"
        }
    ],
    "sg:phone":"+1 830 609 9426",
    "sg:postcode":"78130",
    "sg:province":"TX",
    "wof:name":"Yolanda Longoria",
    "wof:placetype":"venue"
},
  "geometry": {"coordinates":[-98.128201,29.690024],"type":"Point"}
}