{
  "type": "Feature",
  "properties": {
    "iso:country":"US",
    "sg:address":"2227 Cheyenne St",
    "sg:city":"Irving",
    "sg:classifiers":[
        {
            "category":"Social Services",
            "subcategory":"Child Care",
            "type":"Services"
        }
    ],
    "sg:phone":"+1 972 594 0005",
    "sg:postcode":"75062",
    "sg:province":"TX",
    "sg:tags":[
        "facility"
    ],
    "wof:name":"Rainbow Academy",
    "wof:placetype":"venue"
},
  "geometry": {"coordinates":[-97.006585,32.839133],"type":"Point"}
}