{
  "type": "Feature",
  "properties": {
    "iso:country":"US",
    "sg:address":"5020 Airline Dr",
    "sg:city":"Houston",
    "sg:classifiers":[
        {
            "category":"Bars & Pubs",
            "type":"Food & Drink"
        }
    ],
    "sg:phone":"+1 713 691 8217",
    "sg:postcode":"77022",
    "sg:province":"TX",
    "sg:tags":[
        "drinking"
    ],
    "wof:name":"Elaines Lounge",
    "wof:placetype":"venue"
},
  "geometry": {"coordinates":[-95.384337,29.839661],"type":"Point"}
}