{
  "type": "Feature",
  "properties": {
    "iso:country":"US",
    "sg:address":"13710 Shannon St",
    "sg:city":"Lindale",
    "sg:classifiers":[
        {
            "category":"Building & Trades",
            "subcategory":"Construction",
            "type":"Services"
        }
    ],
    "sg:phone":"+1 903 882 6225",
    "sg:postcode":"75771",
    "sg:province":"TX",
    "sg:tags":[
        "house"
    ],
    "wof:name":"Custom Remodeling Service",
    "wof:placetype":"venue"
},
  "geometry": {"coordinates":[-95.39299699999999,32.523277],"type":"Point"}
}