{
  "type": "Feature",
  "properties": {
    "iso:country":"US",
    "sg:address":"1321 Rutherford Ln Ste 140",
    "sg:city":"Austin",
    "sg:classifiers":[
        {
            "category":"Shopping",
            "subcategory":"Music",
            "type":"Retail Goods"
        }
    ],
    "sg:phone":"+1 512 491 7000",
    "sg:postcode":"78753",
    "sg:province":"TX",
    "sg:tags":[
        "used",
        "tapes",
        "vintage",
        "records",
        "cd's",
        "store"
    ],
    "wof:name":"Triaz Digital",
    "wof:placetype":"venue"
},
  "geometry": {"coordinates":[-97.686494,30.338842],"type":"Point"}
}