{
  "type": "Feature",
  "properties": {
    "iso:country":"US",
    "sg:address":"102 W Main St",
    "sg:city":"Humble",
    "sg:classifiers":[
        {
            "category":"Professional",
            "subcategory":"Business Services",
            "type":"Services"
        }
    ],
    "sg:phone":"+1 281 446 2051",
    "sg:postcode":"77338",
    "sg:province":"TX",
    "sg:tags":[
        "notary"
    ],
    "wof:name":"Multi Centro Inc",
    "wof:placetype":"venue"
},
  "geometry": {"coordinates":[-95.268276,29.999214],"type":"Point"}
}