{
  "type": "Feature",
  "properties": {
    "iso:country":"US",
    "sg:address":"7700 Tezel Rd",
    "sg:city":"San Antonio",
    "sg:classifiers":[
        {
            "category":"Organizations",
            "subcategory":"Religious Organization",
            "type":"Services"
        }
    ],
    "sg:phone":"+1 210 680 5045",
    "sg:postcode":"78250",
    "sg:province":"TX",
    "sg:tags":[
        "child",
        "day",
        "care"
    ],
    "wof:name":"Tezel Oaks Day Care",
    "wof:placetype":"venue"
},
  "geometry": {"coordinates":[-98.66234,29.511864],"type":"Point"}
}