{
  "type": "Feature",
  "properties": {
    "iso:country":"US",
    "sg:address":"4809 Crawford Dr",
    "sg:city":"Lewisville",
    "sg:classifiers":[
        {
            "category":"Professional",
            "subcategory":"Computer Services",
            "type":"Services"
        }
    ],
    "sg:phone":"+1 972 625 7508",
    "sg:postcode":"75056",
    "sg:province":"TX",
    "wof:name":"Computer Helping & Technology",
    "wof:placetype":"venue"
},
  "geometry": {"coordinates":[-96.887136,33.094975],"type":"Point"}
}