{
  "type": "Feature",
  "properties": {
    "iso:country":"US",
    "sg:address":"11360 Bellaire Blvd",
    "sg:city":"Houston",
    "sg:classifiers":[
        {
            "category":"Health Services",
            "subcategory":"Doctor",
            "type":"Services"
        }
    ],
    "sg:phone":"+1 281 933 9257",
    "sg:postcode":"77072",
    "sg:province":"TX",
    "wof:name":"Hai Tran DDS",
    "wof:placetype":"venue"
},
  "geometry": {"coordinates":[-95.58110000000001,29.703785],"type":"Point"}
}