{
  "type": "Feature",
  "properties": {
    "iso:country":"US",
    "sg:address":"4038 Barnes St",
    "sg:city":"Corpus Christi",
    "sg:classifiers":[
        {
            "category":"Wholesale",
            "subcategory":"Construction Materials",
            "type":"Manufacturing & Wholesale Goods"
        }
    ],
    "sg:phone":"+1 361 857 8048",
    "sg:postcode":"78411",
    "sg:province":"TX",
    "sg:tags":[
        "lumber"
    ],
    "wof:name":"Arso Lumber Exports",
    "wof:placetype":"venue"
},
  "geometry": {"coordinates":[-97.390029,27.728488],"type":"Point"}
}