{
  "type": "Feature",
  "properties": {
    "iso:country":"US",
    "sg:address":"304 Corral Loop",
    "sg:city":"Laredo",
    "sg:classifiers":[
        {
            "category":"Manufacturing",
            "subcategory":"Paper Products",
            "type":"Manufacturing & Wholesale Goods"
        }
    ],
    "sg:phone":"+1 956 726 6219",
    "sg:postcode":"78045",
    "sg:province":"TX",
    "sg:tags":[
        "mill"
    ],
    "wof:name":"Billy Elizondo",
    "wof:placetype":"venue"
},
  "geometry": {"coordinates":[-99.523066,27.587172],"type":"Point"}
}