{
  "type": "Feature",
  "properties": {
    "iso:country":"US",
    "sg:address":"1521 Rosewood Dr",
    "sg:city":"Keller",
    "sg:classifiers":[
        {
            "category":"Professional",
            "type":"Services"
        }
    ],
    "sg:phone":"+1 817 485 2907",
    "sg:postcode":"76248",
    "sg:province":"TX",
    "wof:name":"Almar Diversified",
    "wof:placetype":"venue"
},
  "geometry": {"coordinates":[-97.217403,32.919324],"type":"Point"}
}