{
  "type": "Feature",
  "properties": {
    "iso:country":"US",
    "sg:address":"814 E Irving Blvd",
    "sg:city":"Irving",
    "sg:classifiers":[
        {
            "category":"Health Services",
            "subcategory":"Dentist",
            "type":"Services"
        }
    ],
    "sg:phone":"+1 972 259 4200",
    "sg:postcode":"75060",
    "sg:province":"TX",
    "sg:website":"www.jdcweb.com",
    "wof:name":"Jefferson Dental Clinics",
    "wof:placetype":"venue"
},
  "geometry": {"coordinates":[-96.936029,32.812165],"type":"Point"}
}