{
  "type": "Feature",
  "properties": {
    "iso:country":"US",
    "sg:address":"1301 Boone St",
    "sg:city":"Cleburne",
    "sg:classifiers":[
        {
            "category":"Place Of Worship",
            "subcategory":"Church",
            "type":"Public Place"
        },
        {
            "category":"Place Of Worship",
            "type":"Public Place"
        }
    ],
    "sg:phone":"+1 817 645 7417",
    "sg:postcode":"76031",
    "sg:province":"TX",
    "sg:tags":[
        "covenant",
        "churches-evangelical",
        "churches-covenant"
    ],
    "wof:name":"Clowns For Christ Inc",
    "wof:placetype":"venue"
},
  "geometry": {"coordinates":[-97.372559,32.371868],"type":"Point"}
}