{
  "type": "Feature",
  "properties": {
    "iso:country":"US",
    "sg:address":"1334 Meadow Way",
    "sg:city":"Terrell",
    "sg:classifiers":[
        {
            "category":"Real Estate",
            "subcategory":"Real Estate Operator",
            "type":"Services"
        }
    ],
    "sg:phone":"+1 972 524 5363",
    "sg:postcode":"75160",
    "sg:province":"TX",
    "sg:tags":[
        "building",
        "equipment",
        "apartment"
    ],
    "wof:name":"Pine Rental",
    "wof:placetype":"venue"
},
  "geometry": {"coordinates":[-96.310664,32.681926],"type":"Point"}
}