{
  "type": "Feature",
  "properties": {
    "iso:country":"US",
    "sg:address":"603 N Patterson Ave",
    "sg:city":"Florence",
    "sg:classifiers":[
        {
            "category":"Food & Beverages",
            "subcategory":"Groceries & Convenience Stores",
            "type":"Retail Goods"
        }
    ],
    "sg:phone":"+1 254 793 2161",
    "sg:postcode":"76527",
    "sg:province":"TX",
    "sg:tags":[
        "station",
        "gasoline"
    ],
    "wof:name":"Filling Station",
    "wof:placetype":"venue"
},
  "geometry": {"coordinates":[-97.796486,30.847279],"type":"Point"}
}