{
  "type": "Feature",
  "properties": {
    "iso:country":"US",
    "sg:address":"6717 Leopard St",
    "sg:city":"Corpus Christi",
    "sg:classifiers":[
        {
            "category":"Mining & Drilling",
            "type":"Manufacturing & Wholesale Goods"
        }
    ],
    "sg:phone":"+1 361 289 7300",
    "sg:postcode":"78409",
    "sg:province":"TX",
    "sg:tags":[
        "field"
    ],
    "wof:name":"Austin Explosives Company",
    "wof:placetype":"venue"
},
  "geometry": {"coordinates":[-97.5025,27.807381],"type":"Point"}
}