{
  "type": "Feature",
  "properties": {
    "iso:country":"US",
    "sg:address":"4300 Medical Pwy",
    "sg:city":"Austin",
    "sg:classifiers":[
        {
            "category":"Health Services",
            "subcategory":"Dentist",
            "type":"Services"
        }
    ],
    "sg:phone":"+1 512 453 3100",
    "sg:postcode":"78735",
    "sg:province":"TX",
    "wof:name":"Trey Kaliher, DDS",
    "wof:placetype":"venue"
},
  "geometry": {"coordinates":[-97.742535,30.312794],"type":"Point"}
}