{
  "type": "Feature",
  "properties": {
    "iso:country":"US",
    "sg:address":"7640 Spring Cypress Rd",
    "sg:city":"Spring",
    "sg:classifiers":[
        {
            "category":"Wholesale",
            "subcategory":"Plants",
            "type":"Manufacturing & Wholesale Goods"
        }
    ],
    "sg:phone":"+1 281 370 9141",
    "sg:postcode":"77379",
    "sg:province":"TX",
    "sg:tags":[
        "supply"
    ],
    "wof:name":"Old Time Christmas Tree Farm",
    "wof:placetype":"venue"
},
  "geometry": {"coordinates":[-95.541067,30.044824],"type":"Point"}
}