{
  "type": "Feature",
  "properties": {
    "iso:country":"US",
    "sg:address":"200 E Tyler St",
    "sg:city":"Richardson",
    "sg:classifiers":[
        {
            "category":"Professional",
            "subcategory":"Computer Services",
            "type":"Services"
        }
    ],
    "sg:phone":"+1 972 231 5530",
    "sg:postcode":"75081",
    "sg:province":"TX",
    "sg:tags":[
        "information",
        "retrieval"
    ],
    "wof:name":"Tic International",
    "wof:placetype":"venue"
},
  "geometry": {"coordinates":[-96.729502,32.949142],"type":"Point"}
}