{
  "type": "Feature",
  "properties": {
    "iso:country":"US",
    "sg:address":"100 E Covington Dr",
    "sg:city":"Austin",
    "sg:classifiers":[
        {
            "category":"Landmark",
            "subcategory":"Tourist Attraction",
            "type":"Public Place"
        }
    ],
    "sg:phone":"+1 512 997 9663",
    "sg:postcode":"78753",
    "sg:province":"TX",
    "sg:tags":[
        "tour",
        "sightseeing"
    ],
    "wof:name":"Gitbit Sportfishing",
    "wof:placetype":"venue"
},
  "geometry": {"coordinates":[-97.67884100000001,30.382856],"type":"Point"}
}