{
  "type": "Feature",
  "properties": {
    "iso:country":"US",
    "sg:address":"12514 Hammersmith Dr",
    "sg:city":"Tomball",
    "sg:classifiers":[
        {
            "category":"Manufacturing",
            "subcategory":"Apparel",
            "type":"Manufacturing & Wholesale Goods"
        }
    ],
    "sg:phone":"+1 281 379 3177",
    "sg:postcode":"77377",
    "sg:province":"TX",
    "sg:tags":[
        "outerwear",
        "mfg"
    ],
    "wof:name":"Goddess Goodies",
    "wof:placetype":"venue"
},
  "geometry": {"coordinates":[-95.61662,30.002336],"type":"Point"}
}