{
  "type": "Feature",
  "properties": {
    "iso:country":"US",
    "sg:address":"1720 Regal Row",
    "sg:city":"Dallas",
    "sg:classifiers":[
        {
            "category":"Professional",
            "subcategory":"Advertising",
            "type":"Services"
        }
    ],
    "sg:phone":"+1 214 634 9486",
    "sg:postcode":"75235",
    "sg:province":"TX",
    "sg:tags":[
        "counselor"
    ],
    "wof:name":"G K & A Advertising Inc",
    "wof:placetype":"venue"
},
  "geometry": {"coordinates":[-96.873673,32.836067],"type":"Point"}
}