{
  "type": "Feature",
  "properties": {
    "iso:country":"US",
    "sg:address":"448 Peacock Dr",
    "sg:city":"San Benito",
    "sg:classifiers":[
        {
            "category":"Real Estate",
            "subcategory":"Real Estate Operator",
            "type":"Services"
        }
    ],
    "sg:phone":"+1 956 783 4619",
    "sg:postcode":"78586",
    "sg:province":"TX",
    "sg:tags":[
        "mobile",
        "home",
        "site"
    ],
    "wof:name":"Highland Mobile Home Park",
    "wof:placetype":"venue"
},
  "geometry": {"coordinates":[-97.668532,26.157462],"type":"Point"}
}