{
  "type": "Feature",
  "properties": {
    "iso:country":"US",
    "sg:address":"9652 Old Katy Rd",
    "sg:city":"Houston",
    "sg:classifiers":[
        {
            "category":"Personal",
            "subcategory":"Beauty Salon",
            "type":"Services"
        }
    ],
    "sg:phone":"+1 713 984 2003",
    "sg:postcode":"77055",
    "sg:province":"TX",
    "sg:tags":[
        "shop"
    ],
    "wof:name":"Lassal",
    "wof:placetype":"venue"
},
  "geometry": {"coordinates":[-95.531273,29.784847],"type":"Point"}
}