{
  "type": "Feature",
  "properties": {
    "iso:country":"US",
    "sg:address":"1711 Sutters Mill Dr",
    "sg:city":"Carrollton",
    "sg:classifiers":[
        {
            "category":"Professional",
            "type":"Services"
        }
    ],
    "sg:phone":"+1 972 242 4266",
    "sg:postcode":"75007",
    "sg:province":"TX",
    "wof:name":"Two Girls In Texas Inc",
    "wof:placetype":"venue"
},
  "geometry": {"coordinates":[-96.89781000000001,32.987898],"type":"Point"}
}