{
  "type": "Feature",
  "properties": {
    "iso:country":"US",
    "sg:address":"2215 Commerce St",
    "sg:city":"Dallas",
    "sg:classifiers":[
        {
            "category":"Shopping",
            "subcategory":"Catalog Store",
            "type":"Retail Goods"
        }
    ],
    "sg:phone":"+1 214 939 0067",
    "sg:postcode":"75201",
    "sg:province":"TX",
    "sg:tags":[
        "mail",
        "order",
        "gift",
        "item"
    ],
    "wof:name":"Affluence Unlimited Inc",
    "wof:placetype":"venue"
},
  "geometry": {"coordinates":[-96.78991600000001,32.781902],"type":"Point"}
}