{
  "type": "Feature",
  "properties": {
    "iso:country":"US",
    "sg:address":"1307 Broadmoor Dr",
    "sg:city":"Bryan",
    "sg:classifiers":[
        {
            "category":"Real Estate",
            "subcategory":"Real Estate Agent",
            "type":"Services"
        }
    ],
    "sg:phone":"+1 979 846 2946",
    "sg:postcode":"77802",
    "sg:province":"TX",
    "wof:name":"Est of Gilbert F Vetters",
    "wof:placetype":"venue"
},
  "geometry": {"coordinates":[-96.34326,30.648683],"type":"Point"}
}