{
  "type": "Feature",
  "properties": {
    "iso:country":"US",
    "sg:address":"146 Repose Ln",
    "sg:city":"San Antonio",
    "sg:classifiers":[
        {
            "category":"Building & Trades",
            "subcategory":"Plumbing",
            "type":"Services"
        }
    ],
    "sg:phone":"+1 210 433 0016",
    "sg:postcode":"78228",
    "sg:province":"TX",
    "sg:tags":[
        "plumbing",
        "contractor"
    ],
    "wof:name":"Roland's Plumbing Svc",
    "wof:placetype":"venue"
},
  "geometry": {"coordinates":[-98.57427,29.462943],"type":"Point"}
}