{
  "type": "Feature",
  "properties": {
    "iso:country":"US",
    "sg:address":"2249 Central Dr",
    "sg:city":"Bedford",
    "sg:classifiers":[
        {
            "category":"Autos & Motor Vehicles",
            "subcategory":"Auto Supplies",
            "type":"Retail Goods"
        }
    ],
    "sg:phone":"+1 817 281 3378",
    "sg:postcode":"76021",
    "sg:province":"TX",
    "wof:name":"Speedy",
    "wof:placetype":"venue"
},
  "geometry": {"coordinates":[-97.133561,32.84301],"type":"Point"}
}