{
  "type": "Feature",
  "properties": {
    "iso:country":"US",
    "sg:address":"8503 Broadway",
    "sg:city":"San Antonio",
    "sg:classifiers":[
        {
            "category":"Retail",
            "subcategory":"Auto Rental",
            "type":"Services"
        }
    ],
    "sg:phone":"+1 210 824 9669",
    "sg:postcode":"78217",
    "sg:province":"TX",
    "sg:tags":[
        "renting",
        "automobile"
    ],
    "wof:name":"Super Star Rent A Car",
    "wof:placetype":"venue"
},
  "geometry": {"coordinates":[-98.462974,29.518445],"type":"Point"}
}