{
  "type": "Feature",
  "properties": {
    "iso:country":"US",
    "sg:address":"625 Village Loop",
    "sg:city":"Tow",
    "sg:classifiers":[
        {
            "category":"Shopping",
            "subcategory":"Computers & Home Electronics",
            "type":"Retail Goods"
        }
    ],
    "sg:phone":"+1 325 379 1266",
    "sg:postcode":"78672",
    "sg:province":"TX",
    "wof:name":"Tower Computers",
    "wof:placetype":"venue"
},
  "geometry": {"coordinates":[-98.453737,30.854344],"type":"Point"}
}