{
  "type": "Feature",
  "properties": {
    "iso:country":"US",
    "sg:address":"5100 Mount Houston Rd",
    "sg:city":"Houston",
    "sg:classifiers":[
        {
            "category":"Wholesale",
            "subcategory":"Scrap",
            "type":"Manufacturing & Wholesale Goods"
        }
    ],
    "sg:phone":"+1 281 442 7497",
    "sg:postcode":"77093",
    "sg:province":"TX",
    "sg:tags":[
        "recycling",
        "center"
    ],
    "wof:name":"Fox Glen Tire Co",
    "wof:placetype":"venue"
},
  "geometry": {"coordinates":[-95.316354,29.890998],"type":"Point"}
}