{
  "type": "Feature",
  "properties": {
    "iso:country":"US",
    "sg:address":"1331 Polo Run",
    "sg:city":"Midlothian",
    "sg:classifiers":[
        {
            "category":"Building & Trades",
            "subcategory":"Cleaning & Sanitation",
            "type":"Services"
        }
    ],
    "sg:phone":"+1 214 764 5627",
    "sg:postcode":"76065",
    "sg:province":"TX",
    "sg:tags":[
        "window"
    ],
    "wof:name":"Mc Entire Cleaning",
    "wof:placetype":"venue"
},
  "geometry": {"coordinates":[-97.007058,32.40545],"type":"Point"}
}