{
  "type": "Feature",
  "properties": {
    "iso:country":"US",
    "sg:address":"14288 Co Rd 426",
    "sg:city":"Lindale",
    "sg:classifiers":[
        {
            "category":"Real Estate",
            "subcategory":"Developer",
            "type":"Services"
        }
    ],
    "sg:phone":"+1 903 570 0610",
    "sg:postcode":"75771",
    "sg:province":"TX",
    "wof:name":"Lawhorn Development",
    "wof:placetype":"venue"
},
  "geometry": {"coordinates":[-95.581459,32.482066],"type":"Point"}
}