{
  "type": "Feature",
  "properties": {
    "iso:country":"US",
    "sg:address":"16665 Space Center Blvd",
    "sg:city":"Houston",
    "sg:classifiers":[
        {
            "category":"Professional",
            "subcategory":"Engineering",
            "type":"Services"
        }
    ],
    "sg:phone":"+1 281 228 5300",
    "sg:postcode":"77058",
    "sg:province":"TX",
    "sg:tags":[
        "aerospace"
    ],
    "wof:name":"Oceaneering Space & Thermal",
    "wof:placetype":"venue"
},
  "geometry": {"coordinates":[-95.104883,29.570772],"type":"Point"}
}