{
  "type": "Feature",
  "properties": {
    "iso:country":"US",
    "sg:address":"2213 Earl St",
    "sg:city":"Port Neches",
    "sg:classifiers":[
        {
            "category":"Wholesale",
            "subcategory":"Machinery & Supplies",
            "type":"Manufacturing & Wholesale Goods"
        },
        {
            "category":"Utilities",
            "type":"Services"
        }
    ],
    "sg:phone":"+1 409 722 2274",
    "sg:postcode":"77651",
    "sg:province":"TX",
    "sg:tags":[
        "sanitary",
        "sweeper"
    ],
    "wof:name":"Infrastructure Services Inc",
    "wof:placetype":"venue"
},
  "geometry": {"coordinates":[-93.954369,29.973803],"type":"Point"}
}