{
  "type": "Feature",
  "properties": {
    "iso:country":"US",
    "sg:address":"5300 Westheimer Rd",
    "sg:city":"Houston",
    "sg:classifiers":[
        {
            "category":"Autos & Motor Vehicles",
            "subcategory":"Auto Supplies",
            "type":"Retail Goods"
        }
    ],
    "sg:phone":"+1 713 623 6145",
    "sg:postcode":"77056",
    "sg:province":"TX",
    "sg:tags":[
        "tire"
    ],
    "wof:name":"Firestone Master Care Svc",
    "wof:placetype":"venue"
},
  "geometry": {"coordinates":[-95.468977,29.739827],"type":"Point"}
}