{
  "type": "Feature",
  "properties": {
    "iso:country":"US",
    "sg:address":"5487 Padre Island Hwy",
    "sg:city":"Brownsville",
    "sg:classifiers":[
        {
            "category":"Shopping",
            "subcategory":"Gifts & Souvenirs",
            "type":"Retail Goods"
        }
    ],
    "sg:phone":"+1 956 547 1970",
    "sg:postcode":"78521",
    "sg:province":"TX",
    "sg:tags":[
        "clay"
    ],
    "wof:name":"Milwhite Inc",
    "wof:placetype":"venue"
},
  "geometry": {"coordinates":[-97.453309,25.928465],"type":"Point"}
}