{
  "type": "Feature",
  "properties": {
    "iso:country":"US",
    "sg:address":"401 W 15th St Ste 675",
    "sg:city":"Austin",
    "sg:classifiers":[
        {
            "category":"Health Services",
            "subcategory":"Doctor",
            "type":"Services"
        }
    ],
    "sg:phone":"+1 512 478 0605",
    "sg:postcode":"78701",
    "sg:province":"TX",
    "sg:tags":[
        "psychiatry",
        "physician",
        "surgeon",
        "surgeons"
    ],
    "wof:name":"Texas Society Of Psychiatric Physicians",
    "wof:placetype":"venue"
},
  "geometry": {"coordinates":[-97.743019,30.277861],"type":"Point"}
}