{
  "type": "Feature",
  "properties": {
    "iso:country":"US",
    "sg:address":"2009 Independence Dr",
    "sg:city":"Sherman",
    "sg:classifiers":[
        {
            "category":"Professional",
            "subcategory":"Lawyer & Legal Services",
            "type":"Services"
        }
    ],
    "sg:phone":"+1 903 870 9050",
    "sg:postcode":"75090",
    "sg:province":"TX",
    "sg:tags":[
        "attorney"
    ],
    "wof:name":"Wilson & Coble",
    "wof:placetype":"venue"
},
  "geometry": {"coordinates":[-96.60959800000001,33.656519],"type":"Point"}
}