{
  "type": "Feature",
  "properties": {
    "iso:country":"US",
    "sg:address":"2007 Springcrest Dr",
    "sg:city":"Arlington",
    "sg:classifiers":[
        {
            "category":"Real Estate",
            "subcategory":"Real Estate Operator",
            "type":"Services"
        }
    ],
    "sg:phone":"+1 817 792 3015",
    "sg:postcode":"76010",
    "sg:province":"TX",
    "sg:tags":[
        "building",
        "apartment"
    ],
    "wof:name":"Springcrest Apartments",
    "wof:placetype":"venue"
},
  "geometry": {"coordinates":[-97.07760399999999,32.70647],"type":"Point"}
}