{
  "type": "Feature",
  "properties": {
    "iso:country":"US",
    "sg:address":"1901 Sandy Ln",
    "sg:city":"Irving",
    "sg:classifiers":[
        {
            "category":"Professional",
            "type":"Services"
        }
    ],
    "sg:phone":"+1 972 313 0724",
    "sg:postcode":"75060",
    "sg:province":"TX",
    "sg:tags":[
        "establishment"
    ],
    "wof:name":"Mike Judkins Gpi",
    "wof:placetype":"venue"
},
  "geometry": {"coordinates":[-96.97016600000001,32.800039],"type":"Point"}
}