{
  "type": "Feature",
  "properties": {
    "iso:country":"US",
    "sg:address":"800 S Stemmons Fwy",
    "sg:city":"Lewisville",
    "sg:classifiers":[
        {
            "category":"Health Services",
            "subcategory":"Doctor",
            "type":"Services"
        }
    ],
    "sg:phone":"+1 972 436 2551",
    "sg:postcode":"75067",
    "sg:province":"TX",
    "sg:tags":[
        "medical"
    ],
    "wof:name":"Beste Thomas A & Damon John H",
    "wof:placetype":"venue"
},
  "geometry": {"coordinates":[-97.00067,33.03756],"type":"Point"}
}