{
  "type": "Feature",
  "properties": {
    "iso:country":"US",
    "sg:address":"2911 Creekside Ct",
    "sg:city":"Carrollton",
    "sg:classifiers":[
        {
            "category":"Professional",
            "type":"Services"
        }
    ],
    "sg:phone":"+1 972 446 2423",
    "sg:postcode":"75007",
    "sg:province":"TX",
    "wof:name":"Broussard International E",
    "wof:placetype":"venue"
},
  "geometry": {"coordinates":[-96.898233,32.994936],"type":"Point"}
}