{
  "type": "Feature",
  "properties": {
    "iso:country":"US",
    "sg:address":"600 N Bedell Ave",
    "sg:city":"Del Rio",
    "sg:classifiers":[
        {
            "category":"Professional",
            "subcategory":"Lawyer & Legal Services",
            "type":"Services"
        }
    ],
    "sg:phone":"+1 830 775 3638",
    "sg:postcode":"78840",
    "sg:province":"TX",
    "sg:tags":[
        "attorney"
    ],
    "wof:name":"Donna Stitts Law Office",
    "wof:placetype":"venue"
},
  "geometry": {"coordinates":[-100.891755,29.373354],"type":"Point"}
}