{
  "type": "Feature",
  "properties": {
    "iso:country":"US",
    "sg:address":"2286 W Pleasant Run Rd",
    "sg:city":"Lancaster",
    "sg:classifiers":[
        {
            "category":"Health Services",
            "subcategory":"Clinic",
            "type":"Services"
        },
        {
            "category":"Manufacturing",
            "subcategory":"Tools & Machinery",
            "type":"Manufacturing & Wholesale Goods"
        }
    ],
    "sg:phone":"+1 972 218 9661",
    "sg:postcode":"75146",
    "sg:province":"TX",
    "sg:tags":[
        "equipment",
        "colonic",
        "irrigation",
        "mfg"
    ],
    "wof:name":"Ultimate Colon Cleaning Center",
    "wof:placetype":"venue"
},
  "geometry": {"coordinates":[-96.80416099999999,32.6042],"type":"Point"}
}