{
  "type": "Feature",
  "properties": {
    "iso:country":"US",
    "sg:address":"2605 Texas Blvd",
    "sg:city":"Texarkana",
    "sg:classifiers":[
        {
            "category":"Utilities",
            "subcategory":"Telephone",
            "type":"Services"
        }
    ],
    "sg:phone":"+1 903 793 1690",
    "sg:postcode":"75503",
    "sg:province":"TX",
    "sg:tags":[
        "distance",
        "long"
    ],
    "wof:name":"Ionex Telecommunications",
    "wof:placetype":"venue"
},
  "geometry": {"coordinates":[-94.05317599999999,33.442273],"type":"Point"}
}