{
  "type": "Feature",
  "properties": {
    "iso:country":"US",
    "sg:address":"2613 Lambda Ln",
    "sg:city":"Flower Mound",
    "sg:classifiers":[
        {
            "category":"Building & Trades",
            "subcategory":"Landscaping Services",
            "type":"Services"
        }
    ],
    "sg:phone":"+1 972 539 4758",
    "sg:postcode":"75028",
    "sg:province":"TX",
    "wof:name":"Lawn Tech Enterprises Inc",
    "wof:placetype":"venue"
},
  "geometry": {"coordinates":[-97.066749,33.039124],"type":"Point"}
}