{
  "type": "Feature",
  "properties": {
    "iso:country":"US",
    "sg:address":"461 Fm 922",
    "sg:city":"Forestburg",
    "sg:classifiers":[
        {
            "category":"Place Of Worship",
            "subcategory":"Church",
            "type":"Public Place"
        },
        {
            "category":"Place Of Worship",
            "type":"Public Place"
        }
    ],
    "sg:phone":"+1 940 964 2410",
    "sg:postcode":"76239",
    "sg:province":"TX",
    "sg:tags":[
        "nazarene",
        "churches-church",
        "churches-nazarene"
    ],
    "wof:name":"Prarie Point Church Of Nazarene",
    "wof:placetype":"venue"
},
  "geometry": {"coordinates":[-97.542089,33.530492],"type":"Point"}
}