{
  "type": "Feature",
  "properties": {
    "iso:country":"US",
    "sg:address":"1506 N Lee Trevino Dr",
    "sg:city":"El Paso",
    "sg:classifiers":[
        {
            "category":"Manufacturing",
            "subcategory":"Food",
            "type":"Manufacturing & Wholesale Goods"
        }
    ],
    "sg:phone":"+1 915 599 2828",
    "sg:postcode":"79936",
    "sg:province":"TX",
    "sg:tags":[
        "brewer"
    ],
    "wof:name":"Border City Ale House",
    "wof:placetype":"venue"
},
  "geometry": {"coordinates":[-106.31867699999999,31.751448],"type":"Point"}
}