{
  "type": "Feature",
  "properties": {
    "iso:country":"US",
    "sg:address":"520 W 19th St",
    "sg:city":"San Angelo",
    "sg:classifiers":[
        {
            "category":"Shopping",
            "subcategory":"Clothing, Apparel, & Fashions",
            "type":"Retail Goods"
        }
    ],
    "sg:phone":"+1 325 486 8297",
    "sg:postcode":"76903",
    "sg:province":"TX",
    "wof:name":"White's Clothing",
    "wof:placetype":"venue"
},
  "geometry": {"coordinates":[-100.454489,31.476454],"type":"Point"}
}