{
  "type": "Feature",
  "properties": {
    "iso:country":"US",
    "sg:address":"7398 US Hwy 80",
    "sg:city":"Terrell",
    "sg:classifiers":[
        {
            "category":"Food & Beverages",
            "subcategory":"Groceries & Convenience Stores",
            "type":"Retail Goods"
        },
        {
            "category":"Autos & Motor Vehicles",
            "subcategory":"Fuel & Gas Station",
            "type":"Retail Goods"
        }
    ],
    "sg:phone":"+1 972 551 1378",
    "sg:postcode":"75161",
    "sg:province":"TX",
    "sg:tags":[
        "station",
        "gasoline"
    ],
    "wof:name":"Elmo Food Stop",
    "wof:placetype":"venue"
},
  "geometry": {"coordinates":[-96.16774599999999,32.721682],"type":"Point"}
}