{
  "type": "Feature",
  "properties": {
    "iso:country":"US",
    "sg:address":"Balcones Pool Parking Lot Amherst Ave.",
    "sg:city":"Austin",
    "sg:classifiers":[
        {
            "category":"Food & Beverages",
            "subcategory":"Candy",
            "type":"Retail Goods"
        }
    ],
    "sg:postcode":"78798",
    "sg:province":"TX",
    "sg:tags":[
        "dessert"
    ],
    "wof:name":"Sno Biz",
    "wof:placetype":"venue"
},
  "geometry": {"coordinates":[-97.71804899999999,30.417704],"type":"Point"}
}