{
  "type": "Feature",
  "properties": {
    "iso:country":"US",
    "sg:address":"21618 State Hwy 34",
    "sg:city":"Terrell",
    "sg:classifiers":[
        {
            "category":"Building & Trades",
            "subcategory":"Equipment Rental",
            "type":"Services"
        }
    ],
    "sg:phone":"+1 972 524 9993",
    "sg:postcode":"75161",
    "sg:province":"TX",
    "sg:tags":[
        "toilet"
    ],
    "wof:name":"Nature Calls Inc",
    "wof:placetype":"venue"
},
  "geometry": {"coordinates":[-96.175821,32.833118],"type":"Point"}
}