{
  "type": "Feature",
  "properties": {
    "iso:country":"US",
    "sg:address":"8803 Clifford St",
    "sg:city":"Fort Worth",
    "sg:classifiers":[
        {
            "category":"Personal",
            "subcategory":"Beauty Salon",
            "type":"Services"
        }
    ],
    "sg:phone":"+1 817 246 4907",
    "sg:postcode":"76108",
    "sg:province":"TX",
    "sg:tags":[
        "shop"
    ],
    "wof:name":"Debbie's Hair Salon",
    "wof:placetype":"venue"
},
  "geometry": {"coordinates":[-97.471469,32.766063],"type":"Point"}
}