{
  "type": "Feature",
  "properties": {
    "iso:country":"US",
    "sg:address":"110 S Gordon St",
    "sg:city":"Alvin",
    "sg:classifiers":[
        {
            "category":"Banks & Credit Unions",
            "subcategory":"Investment Brokerage",
            "type":"Services"
        }
    ],
    "sg:phone":"+1 281 331 5260",
    "sg:postcode":"77511",
    "sg:province":"TX",
    "sg:tags":[
        "stock",
        "bond"
    ],
    "wof:name":"Edward Jones Co",
    "wof:placetype":"venue"
},
  "geometry": {"coordinates":[-95.243995,29.423747],"type":"Point"}
}