{
  "type": "Feature",
  "properties": {
    "iso:country":"US",
    "sg:address":"913 Lakewood Hills Ter",
    "sg:city":"Austin",
    "sg:classifiers":[
        {
            "category":"Building & Trades",
            "subcategory":"Construction",
            "type":"Services"
        }
    ],
    "sg:phone":"+1 512 266 8557",
    "sg:postcode":"78732",
    "sg:province":"TX",
    "sg:tags":[
        "contractor"
    ],
    "wof:name":"Partners In Building",
    "wof:placetype":"venue"
},
  "geometry": {"coordinates":[-97.911483,30.355271],"type":"Point"}
}