{
  "type": "Feature",
  "properties": {
    "iso:country":"US",
    "sg:address":"4031 Appian Way",
    "sg:city":"Arlington",
    "sg:classifiers":[
        {
            "category":"Farming",
            "subcategory":"Farm",
            "type":"Manufacturing & Wholesale Goods"
        }
    ],
    "sg:phone":"+1 817 861 6192",
    "sg:postcode":"76013",
    "sg:province":"TX",
    "sg:tags":[
        "crop",
        "general"
    ],
    "wof:name":"Perdue Farms Inc",
    "wof:placetype":"venue"
},
  "geometry": {"coordinates":[-97.168172,32.70805],"type":"Point"}
}