{
  "type": "Feature",
  "properties": {
    "iso:country":"US",
    "sg:address":"1706 Nueces St",
    "sg:city":"Austin",
    "sg:classifiers":[
        {
            "category":"Health Services",
            "subcategory":"Health Practitioner",
            "type":"Services"
        }
    ],
    "sg:phone":"+1 512 474 8317",
    "sg:postcode":"78701",
    "sg:province":"TX",
    "sg:tags":[
        "psychotherapist"
    ],
    "wof:name":"Arlene Montgomery",
    "wof:placetype":"venue"
},
  "geometry": {"coordinates":[-97.744219,30.281195],"type":"Point"}
}