{
  "type": "Feature",
  "properties": {
    "iso:country":"US",
    "sg:address":"101 Hawes St",
    "sg:city":"Wharton",
    "sg:classifiers":[
        {
            "category":"Farming",
            "subcategory":"Farm",
            "type":"Manufacturing & Wholesale Goods"
        }
    ],
    "sg:phone":"+1 979 532 8321",
    "sg:postcode":"77488",
    "sg:province":"TX",
    "wof:name":"Rachunek Brothers Farms",
    "wof:placetype":"venue"
},
  "geometry": {"coordinates":[-96.10036599999999,29.313215],"type":"Point"}
}