{
  "type": "Feature",
  "properties": {
    "iso:country":"US",
    "sg:address":"1201 Louisiana St",
    "sg:city":"Houston",
    "sg:classifiers":[
        {
            "category":"Professional",
            "subcategory":"Printing & Photocopies",
            "type":"Services"
        }
    ],
    "sg:phone":"+1 713 658 8944",
    "sg:postcode":"77002",
    "sg:province":"TX",
    "sg:tags":[
        "duplicating",
        "copying"
    ],
    "wof:name":"Copy Con Corp",
    "wof:placetype":"venue"
},
  "geometry": {"coordinates":[-95.36927799999999,29.75629],"type":"Point"}
}