{
  "type": "Feature",
  "properties": {
    "iso:country":"US",
    "sg:address":"1806 Westheimer Rd",
    "sg:city":"Houston",
    "sg:classifiers":[
        {
            "category":"Autos & Motor Vehicles",
            "subcategory":"Automobile Sales",
            "type":"Retail Goods"
        }
    ],
    "sg:phone":"+1 713 528 2220",
    "sg:postcode":"77098",
    "sg:province":"TX",
    "sg:tags":[
        "used"
    ],
    "wof:name":"Foreign Car Connection",
    "wof:placetype":"venue"
},
  "geometry": {"coordinates":[-95.405226,29.742806],"type":"Point"}
}