{
  "type": "Feature",
  "properties": {
    "iso:country":"US",
    "sg:address":"1524 Dove Ave",
    "sg:city":"Mcallen",
    "sg:classifiers":[
        {
            "category":"Real Estate",
            "subcategory":"Real Estate Operator",
            "type":"Services"
        }
    ],
    "sg:phone":"+1 956 992 9791",
    "sg:postcode":"78504",
    "sg:province":"TX",
    "sg:tags":[
        "building",
        "apartment"
    ],
    "wof:name":"Pines APT",
    "wof:placetype":"venue"
},
  "geometry": {"coordinates":[-98.227891,26.254689],"type":"Point"}
}