{
  "type": "Feature",
  "properties": {
    "iso:country":"US",
    "sg:address":"5000 Quorum Dr",
    "sg:city":"Dallas",
    "sg:classifiers":[
        {
            "category":"Communications",
            "subcategory":"Film & Video Production",
            "type":"Services"
        }
    ],
    "sg:phone":"+1 972 991 5603",
    "sg:postcode":"75254",
    "sg:province":"TX",
    "sg:tags":[
        "taping"
    ],
    "wof:name":"Southwest Captioning Svc",
    "wof:placetype":"venue"
},
  "geometry": {"coordinates":[-96.825504,32.948383],"type":"Point"}
}