{
  "type": "Feature",
  "properties": {
    "iso:country":"US",
    "sg:address":"171 Pasadena Fwy",
    "sg:city":"Pasadena",
    "sg:classifiers":[
        {
            "category":"Shopping",
            "subcategory":"Shoes",
            "type":"Retail Goods"
        }
    ],
    "sg:phone":"+1 713 472 6612",
    "sg:postcode":"77506",
    "sg:province":"TX",
    "wof:name":"Footaction",
    "wof:placetype":"venue"
},
  "geometry": {"coordinates":[-95.21124500000001,29.71126],"type":"Point"}
}