{
  "type": "Feature",
  "properties": {
    "iso:country":"US",
    "sg:address":"102 Scott Ave",
    "sg:city":"Dalhart",
    "sg:classifiers":[
        {
            "category":"Travel",
            "subcategory":"Hotels & Motels",
            "type":"Entertainment"
        }
    ],
    "sg:phone":"+1 806 249 5637",
    "sg:postcode":"79022",
    "sg:province":"TX",
    "sg:website":"www.bestwesterninn.com",
    "wof:name":"Best Western Inn",
    "wof:placetype":"venue"
},
  "geometry": {"coordinates":[-102.519469,36.065182],"type":"Point"}
}