{
  "type": "Feature",
  "properties": {
    "iso:country":"US",
    "sg:address":"2545 Boardwalk St",
    "sg:city":"San Antonio",
    "sg:classifiers":[
        {
            "category":"Professional",
            "subcategory":"Computer Services",
            "type":"Services"
        }
    ],
    "sg:phone":"+1 210 820 8281",
    "sg:postcode":"78217",
    "sg:province":"TX",
    "sg:tags":[
        "design",
        "system"
    ],
    "wof:name":"Patriot Communications",
    "wof:placetype":"venue"
},
  "geometry": {"coordinates":[-98.450836,29.533292],"type":"Point"}
}