{
  "type": "Feature",
  "properties": {
    "iso:country":"US",
    "sg:address":"5209 Smokerise Ct",
    "sg:city":"Arlington",
    "sg:classifiers":[
        {
            "category":"Professional",
            "type":"Services"
        }
    ],
    "sg:phone":"+1 817 429 8844",
    "sg:postcode":"76016",
    "sg:province":"TX",
    "wof:name":"Allen Metallurgical Services",
    "wof:placetype":"venue"
},
  "geometry": {"coordinates":[-97.187335,32.705661],"type":"Point"}
}