{
  "type": "Feature",
  "properties": {
    "iso:country":"US",
    "sg:address":"1301 E Quebec Ave",
    "sg:city":"Mcallen",
    "sg:classifiers":[
        {
            "category":"Health Services",
            "subcategory":"Nursing And Care Facility",
            "type":"Services"
        }
    ],
    "sg:phone":"+1 956 972 0049",
    "sg:postcode":"78503",
    "sg:province":"TX",
    "sg:tags":[
        "home",
        "convalescent"
    ],
    "wof:name":"Las Palams",
    "wof:placetype":"venue"
},
  "geometry": {"coordinates":[-98.20806899999999,26.184673],"type":"Point"}
}