{
  "type": "Feature",
  "properties": {
    "iso:country":"US",
    "sg:address":"4000 Five Points Dr",
    "sg:city":"Arlington",
    "sg:classifiers":[
        {
            "category":"Shopping",
            "subcategory":"Clothing, Apparel, & Fashions",
            "type":"Retail Goods"
        },
        {
            "category":"Shopping",
            "subcategory":"Gifts & Souvenirs",
            "type":"Retail Goods"
        }
    ],
    "sg:phone":"+1 817 468 3883",
    "sg:postcode":"76018",
    "sg:province":"TX",
    "sg:tags":[
        "shop",
        "sportswear"
    ],
    "sg:website":"http://www.rallyhousetexas.com",
    "wof:name":"Rally House Texas",
    "wof:placetype":"venue"
},
  "geometry": {"coordinates":[-97.106628,32.680519],"type":"Point"}
}