{
  "type": "Feature",
  "properties": {
    "iso:country":"US",
    "sg:address":"1610 Woodstead Ct",
    "sg:city":"Spring",
    "sg:classifiers":[
        {
            "category":"Health Services",
            "subcategory":"Clinic",
            "type":"Services"
        }
    ],
    "sg:phone":"+1 281 419 0225",
    "sg:postcode":"77380",
    "sg:province":"TX",
    "wof:name":"Health Associates Inc",
    "wof:placetype":"venue"
},
  "geometry": {"coordinates":[-95.45970699999999,30.154937],"type":"Point"}
}