{
  "type": "Feature",
  "properties": {
    "iso:country":"US",
    "sg:address":"2010 Piper Dr",
    "sg:city":"Denton",
    "sg:classifiers":[
        {
            "category":"Professional",
            "subcategory":"Lawyer & Legal Services",
            "type":"Services"
        }
    ],
    "sg:phone":"+1 940 465 0753",
    "sg:postcode":"76210",
    "sg:province":"TX",
    "wof:name":"Law Office Edward R Barrett",
    "wof:placetype":"venue"
},
  "geometry": {"coordinates":[-97.081464,33.139967],"type":"Point"}
}