{
  "type": "Feature",
  "properties": {
    "iso:country":"US",
    "sg:address":"2113 New York St",
    "sg:city":"Baytown",
    "sg:classifiers":[
        {
            "category":"Shopping",
            "subcategory":"Computers & Home Electronics",
            "type":"Retail Goods"
        }
    ],
    "sg:phone":"+1 281 428 2591",
    "sg:postcode":"77520",
    "sg:province":"TX",
    "wof:name":"Showcase Innovations",
    "wof:placetype":"venue"
},
  "geometry": {"coordinates":[-94.994277,29.71659],"type":"Point"}
}