{
  "type": "Feature",
  "properties": {
    "iso:country":"US",
    "sg:address":"100 Kingfisher Dr",
    "sg:city":"Georgetown",
    "sg:classifiers":[
        {
            "category":"Shopping",
            "subcategory":"Florist",
            "type":"Retail Goods"
        }
    ],
    "sg:phone":"+1 512 868 8416",
    "sg:postcode":"78633",
    "sg:province":"TX",
    "sg:tags":[
        "tree",
        "nurseries-plants"
    ],
    "wof:name":"Festive Florals",
    "wof:placetype":"venue"
},
  "geometry": {"coordinates":[-97.730537,30.722601],"type":"Point"}
}