{
  "type": "Feature",
  "properties": {
    "iso:country":"US",
    "sg:address":"9211 Sunlit Park Dr",
    "sg:city":"Humble",
    "sg:classifiers":[
        {
            "category":"Place Of Worship",
            "type":"Public Place"
        }
    ],
    "sg:phone":"+1 281 961 9243",
    "sg:postcode":"77396",
    "sg:province":"TX",
    "sg:tags":[
        "church"
    ],
    "wof:name":"Greater New Vision Church",
    "wof:placetype":"venue"
},
  "geometry": {"coordinates":[-95.255912,29.943135],"type":"Point"}
}