{
  "type": "Feature",
  "properties": {
    "iso:country":"US",
    "sg:address":"227 4th Ave N",
    "sg:city":"Texas City",
    "sg:classifiers":[
        {
            "category":"Organizations",
            "subcategory":"Religious Organization",
            "type":"Services"
        }
    ],
    "sg:phone":"+1 409 948 1606",
    "sg:postcode":"77590",
    "sg:province":"TX",
    "sg:tags":[
        "church"
    ],
    "wof:name":"Mt Zion Baptist Church",
    "wof:placetype":"venue"
},
  "geometry": {"coordinates":[-94.897655,29.388174],"type":"Point"}
}