{
  "type": "Feature",
  "properties": {
    "iso:country":"US",
    "sg:address":"1607 W Parmer Ln",
    "sg:city":"Austin",
    "sg:classifiers":[
        {
            "category":"Retail",
            "subcategory":"Auto Repair",
            "type":"Services"
        }
    ],
    "sg:phone":"+1 512 835 5555",
    "sg:postcode":"78727",
    "sg:province":"TX",
    "sg:tags":[
        "automobile",
        "lubrication"
    ],
    "wof:name":"Valvoline Express Care",
    "wof:placetype":"venue"
},
  "geometry": {"coordinates":[-97.68944,30.412472],"type":"Point"}
}