{
  "type": "Feature",
  "properties": {
    "iso:country":"US",
    "sg:address":"6966 Green Oaks Rd",
    "sg:city":"Fort Worth",
    "sg:classifiers":[
        {
            "category":"Food & Beverages",
            "subcategory":"Specialty",
            "type":"Retail Goods"
        }
    ],
    "sg:phone":"+1 817 569 1830",
    "sg:postcode":"76116",
    "sg:province":"TX",
    "sg:tags":[
        "vitamin",
        "store"
    ],
    "wof:name":"Smoothie Factory",
    "wof:placetype":"venue"
},
  "geometry": {"coordinates":[-97.436633,32.736293],"type":"Point"}
}