{
  "type": "Feature",
  "properties": {
    "iso:country":"US",
    "sg:address":"6688 Southwest Fwy",
    "sg:city":"Houston",
    "sg:classifiers":[
        {
            "category":"Utilities",
            "subcategory":"Telephone",
            "type":"Services"
        }
    ],
    "sg:phone":"+1 713 974 3838",
    "sg:postcode":"77074",
    "sg:province":"TX",
    "sg:tags":[
        "distance",
        "long"
    ],
    "wof:name":"Texas Communications",
    "wof:placetype":"venue"
},
  "geometry": {"coordinates":[-95.500787,29.71595],"type":"Point"}
}