{
  "type": "Feature",
  "properties": {
    "iso:country":"US",
    "sg:address":"6026 Norfolk Dr",
    "sg:city":"Garland",
    "sg:classifiers":[
        {
            "category":"Shopping",
            "subcategory":"Clothing, Apparel, & Fashions",
            "type":"Retail Goods"
        }
    ],
    "sg:phone":"+1 972 495 0122",
    "sg:postcode":"75044",
    "sg:province":"TX",
    "sg:tags":[
        "family"
    ],
    "wof:name":"Susana 5000",
    "wof:placetype":"venue"
},
  "geometry": {"coordinates":[-96.610376,32.968764],"type":"Point"}
}