{
  "type": "Feature",
  "properties": {
    "iso:country":"US",
    "sg:address":"11320 Pagemill Rd",
    "sg:city":"Dallas",
    "sg:classifiers":[
        {
            "category":"Manufacturing",
            "subcategory":"Printing",
            "type":"Manufacturing & Wholesale Goods"
        }
    ],
    "sg:phone":"+1 214 343 8870",
    "sg:postcode":"75243",
    "sg:province":"TX",
    "sg:tags":[
        "screen"
    ],
    "wof:name":"Quackerbox Creations Inc",
    "wof:placetype":"venue"
},
  "geometry": {"coordinates":[-96.708206,32.902113],"type":"Point"}
}