{
  "type": "Feature",
  "properties": {
    "iso:country":"US",
    "sg:address":"216 N College St",
    "sg:city":"Waxahachie",
    "sg:classifiers":[
        {
            "category":"Organizations",
            "subcategory":"Membership Organization",
            "type":"Services"
        },
        {
            "category":"Government",
            "subcategory":"Police Station",
            "type":"Public Place"
        }
    ],
    "sg:phone":"+1 972 937 4320",
    "sg:postcode":"75165",
    "sg:province":"TX",
    "sg:tags":[
        "department",
        "protection"
    ],
    "wof:name":"Waxahachie Police Department",
    "wof:placetype":"venue"
},
  "geometry": {"coordinates":[-96.84676399999999,32.386386],"type":"Point"}
}