{
  "type": "Feature",
  "properties": {
    "iso:country":"US",
    "sg:address":"2033 Bingle Rd",
    "sg:city":"Houston",
    "sg:classifiers":[
        {
            "category":"Food & Beverages",
            "subcategory":"Bakery",
            "type":"Retail Goods"
        }
    ],
    "sg:phone":"+1 713 932 6273",
    "sg:postcode":"77055",
    "sg:province":"TX",
    "wof:name":"Oroweat Foods",
    "wof:placetype":"venue"
},
  "geometry": {"coordinates":[-95.500934,29.81019],"type":"Point"}
}