{
  "type": "Feature",
  "properties": {
    "iso:country":"US",
    "sg:address":"3701 River Rd",
    "sg:city":"Wimberley",
    "sg:classifiers":[
        {
            "category":"Insurance",
            "subcategory":"Hazard Insurance",
            "type":"Services"
        }
    ],
    "sg:phone":"+1 512 847 5151",
    "sg:postcode":"78676",
    "sg:province":"TX",
    "sg:tags":[
        "carrier"
    ],
    "wof:name":"AIG",
    "wof:placetype":"venue"
},
  "geometry": {"coordinates":[-98.139251,29.981915],"type":"Point"}
}