{
  "type": "Feature",
  "properties": {
    "iso:country":"US",
    "sg:address":"8625 Hwy 377 S",
    "sg:city":"Fort Worth",
    "sg:classifiers":[
        {
            "category":"Manufacturing",
            "subcategory":"Food",
            "type":"Manufacturing & Wholesale Goods"
        }
    ],
    "sg:phone":"+1 817 249 5230",
    "sg:postcode":"76126",
    "sg:province":"TX",
    "sg:tags":[
        "mfg",
        "product",
        "other",
        "bakery",
        "bread"
    ],
    "wof:name":"Mrs Bairds Bakeries",
    "wof:placetype":"venue"
},
  "geometry": {"coordinates":[-97.46271400000001,32.680882],"type":"Point"}
}