{
  "type": "Feature",
  "properties": {
    "iso:country":"US",
    "sg:address":"5303 Live Oak Cove",
    "sg:city":"Round Rock",
    "sg:classifiers":[
        {
            "category":"Professional",
            "subcategory":"Engineering",
            "type":"Services"
        }
    ],
    "sg:phone":"+1 512 259 9778",
    "sg:postcode":"78681",
    "sg:province":"TX",
    "sg:tags":[
        "physical",
        "commercial",
        "research"
    ],
    "wof:name":"Jt Systems",
    "wof:placetype":"venue"
},
  "geometry": {"coordinates":[-97.75841800000001,30.534512],"type":"Point"}
}