{
  "type": "Feature",
  "properties": {
    "iso:country":"US",
    "sg:address":"2125 Hebert Rd",
    "sg:city":"Beaumont",
    "sg:classifiers":[
        {
            "category":"Shopping",
            "subcategory":"Bicycles & Sporting Goods",
            "type":"Retail Goods"
        }
    ],
    "sg:phone":"+1 409 722 1192",
    "sg:postcode":"77705",
    "sg:province":"TX",
    "wof:name":"Mac Shooting Supplies",
    "wof:placetype":"venue"
},
  "geometry": {"coordinates":[-94.06502500000001,29.985424],"type":"Point"}
}