{
  "type": "Feature",
  "properties": {
    "iso:country":"US",
    "sg:address":"408 E 1st St",
    "sg:city":"Sonora",
    "sg:classifiers":[
        {
            "category":"Education",
            "subcategory":"School",
            "type":"Public Place"
        }
    ],
    "sg:phone":"+1 325 387 3780",
    "sg:postcode":"76950",
    "sg:province":"TX",
    "sg:tags":[
        "middle"
    ],
    "wof:name":"Sonora Middle School",
    "wof:placetype":"venue"
},
  "geometry": {"coordinates":[-100.638004,30.566895],"type":"Point"}
}