{
  "type": "Feature",
  "properties": {
    "iso:country":"US",
    "sg:address":"2410 FM 523",
    "sg:city":"Freeport",
    "sg:classifiers":[
        {
            "category":"Building & Trades",
            "subcategory":"Equipment Rental",
            "type":"Services"
        }
    ],
    "sg:phone":"+1 979 233 5481",
    "sg:postcode":"77541",
    "sg:province":"TX",
    "sg:tags":[
        "crane"
    ],
    "wof:name":"Head & Guild Equipment Co Inc",
    "wof:placetype":"venue"
},
  "geometry": {"coordinates":[-95.329511,28.994765],"type":"Point"}
}