{
  "type": "Feature",
  "properties": {
    "iso:country":"US",
    "sg:address":"209 Oak Springs Dr",
    "sg:city":"Seguin",
    "sg:classifiers":[
        {
            "category":"Shopping",
            "type":"Retail Goods"
        }
    ],
    "sg:phone":"+1 830 303 0384",
    "sg:postcode":"78155",
    "sg:province":"TX",
    "sg:tags":[
        "merchandise"
    ],
    "wof:name":"Moon Equipment Sales",
    "wof:placetype":"venue"
},
  "geometry": {"coordinates":[-97.939431,29.622138],"type":"Point"}
}