{
  "type": "Feature",
  "properties": {
    "iso:country":"US",
    "sg:address":"21338 Highland Knolls Dr",
    "sg:city":"Katy",
    "sg:classifiers":[
        {
            "category":"Personal",
            "type":"Services"
        }
    ],
    "sg:phone":"+1 281 599 1502",
    "sg:postcode":"77450",
    "sg:province":"TX",
    "wof:name":"Riders Title Express",
    "wof:placetype":"venue"
},
  "geometry": {"coordinates":[-95.738696,29.759198],"type":"Point"}
}