{
  "type": "Feature",
  "properties": {
    "iso:country":"US",
    "sg:address":"22 Shiloh Rd",
    "sg:city":"Odessa",
    "sg:classifiers":[
        {
            "category":"Wholesale",
            "subcategory":"Electrical",
            "type":"Manufacturing & Wholesale Goods"
        }
    ],
    "sg:phone":"+1 432 362 7983",
    "sg:postcode":"79762",
    "sg:province":"TX",
    "sg:tags":[
        "equipment",
        "electric",
        "supply"
    ],
    "wof:name":"Paccap Inc Elec Eqpt Manufa",
    "wof:placetype":"venue"
},
  "geometry": {"coordinates":[-102.304734,31.893248],"type":"Point"}
}