{
  "type": "Feature",
  "properties": {
    "iso:country":"US",
    "sg:address":"3525 Clearbrook Dr",
    "sg:city":"Fort Worth",
    "sg:classifiers":[
        {
            "category":"Restaurant",
            "type":"Food & Drink"
        }
    ],
    "sg:phone":"+1 817 370 6489",
    "sg:postcode":"76123",
    "sg:province":"TX",
    "sg:tags":[
        "eating"
    ],
    "wof:name":"Kings Table",
    "wof:placetype":"venue"
},
  "geometry": {"coordinates":[-97.372007,32.617586],"type":"Point"}
}