{
  "type": "Feature",
  "properties": {
    "iso:country":"US",
    "sg:address":"16631 W Hardy Rd",
    "sg:city":"Houston",
    "sg:classifiers":[
        {
            "category":"Education",
            "subcategory":"Junior College",
            "type":"Public Place"
        }
    ],
    "sg:phone":"+1 281 873 0980",
    "sg:postcode":"77060",
    "sg:province":"TX",
    "wof:name":"Hellier NDT",
    "wof:placetype":"venue"
},
  "geometry": {"coordinates":[-95.38860699999999,29.954715],"type":"Point"}
}