{
  "type": "Feature",
  "properties": {
    "iso:country":"US",
    "sg:address":"1504 League Line Rd",
    "sg:city":"Conroe",
    "sg:classifiers":[
        {
            "category":"Real Estate",
            "subcategory":"Real Estate Operator",
            "type":"Services"
        }
    ],
    "sg:phone":"+1 936 890 3678",
    "sg:postcode":"77304",
    "sg:province":"TX",
    "sg:tags":[
        "building",
        "operation",
        "commercial"
    ],
    "wof:name":"Highlands Office Park LLC",
    "wof:placetype":"venue"
},
  "geometry": {"coordinates":[-95.487036,30.367432],"type":"Point"}
}