{
  "type": "Feature",
  "properties": {
    "iso:country":"US",
    "sg:address":"9607 Research Blvd Ste 700",
    "sg:city":"Austin",
    "sg:classifiers":[
        {
            "category":"Shopping",
            "subcategory":"Department Store",
            "type":"Retail Goods"
        }
    ],
    "sg:phone":"+1 512 795 9201",
    "sg:postcode":"78759",
    "sg:province":"TX",
    "wof:name":"Crate&Barrel",
    "wof:placetype":"venue"
},
  "geometry": {"coordinates":[-97.74352399999999,30.388616],"type":"Point"}
}