{
  "type": "Feature",
  "properties": {
    "iso:country":"US",
    "sg:address":"112 S College Ave",
    "sg:city":"Tyler",
    "sg:classifiers":[
        {
            "category":"Professional",
            "type":"Services"
        }
    ],
    "sg:phone":"+1 903 595 4101",
    "sg:postcode":"75702",
    "sg:province":"TX",
    "wof:name":"Eltife Oil Company Inc",
    "wof:placetype":"venue"
},
  "geometry": {"coordinates":[-95.301564,32.3498],"type":"Point"}
}