{
  "type": "Feature",
  "properties": {
    "iso:country":"US",
    "sg:address":"1070 Arion Cir",
    "sg:city":"San Antonio",
    "sg:classifiers":[
        {
            "category":"Wholesale",
            "subcategory":"Electrical",
            "type":"Manufacturing & Wholesale Goods"
        }
    ],
    "sg:phone":"+1 210 824 6324",
    "sg:postcode":"78216",
    "sg:province":"TX",
    "sg:tags":[
        "fire",
        "equipment",
        "protection"
    ],
    "wof:name":"Simplexgrinell",
    "wof:placetype":"venue"
},
  "geometry": {"coordinates":[-98.47789400000001,29.550859],"type":"Point"}
}