{
  "type": "Feature",
  "properties": {
    "iso:country":"US",
    "sg:address":"3709 Piedmont Ct",
    "sg:city":"Plano",
    "sg:classifiers":[
        {
            "category":"Shopping",
            "subcategory":"Shoes",
            "type":"Retail Goods"
        }
    ],
    "sg:phone":"+1 972 985 9826",
    "sg:postcode":"75075",
    "sg:province":"TX",
    "wof:name":"Mensusaka Intl Co",
    "wof:placetype":"venue"
},
  "geometry": {"coordinates":[-96.763282,33.023848],"type":"Point"}
}