{
  "type": "Feature",
  "properties": {
    "iso:country":"US",
    "sg:address":"23326 S Warmstone Way",
    "sg:city":"Katy",
    "sg:classifiers":[
        {
            "category":"Farming",
            "subcategory":"Livestock Farm",
            "type":"Manufacturing & Wholesale Goods"
        }
    ],
    "sg:phone":"+1 281 693 4147",
    "sg:postcode":"77494",
    "sg:province":"TX",
    "sg:tags":[
        "beef",
        "feedlot",
        "cattle"
    ],
    "wof:name":"Breast Feeding Solutions",
    "wof:placetype":"venue"
},
  "geometry": {"coordinates":[-95.772475,29.758364],"type":"Point"}
}