{
  "type": "Feature",
  "properties": {
    "iso:country":"US",
    "sg:address":"2326 SE 14th St",
    "sg:city":"Grand Prairie",
    "sg:classifiers":[
        {
            "category":"Retail",
            "subcategory":"Auto Repair",
            "type":"Services"
        }
    ],
    "sg:phone":"+1 972 642 9999",
    "sg:postcode":"75051",
    "sg:province":"TX",
    "sg:tags":[
        "body"
    ],
    "wof:name":"All Import Auto Body Parts",
    "wof:placetype":"venue"
},
  "geometry": {"coordinates":[-96.98551399999999,32.710706],"type":"Point"}
}