{
  "type": "Feature",
  "properties": {
    "iso:country":"US",
    "sg:address":"803 Hurst St",
    "sg:city":"Center",
    "sg:classifiers":[
        {
            "category":"Autos & Motor Vehicles",
            "subcategory":"Fuel & Gas Station",
            "type":"Retail Goods"
        }
    ],
    "sg:phone":"+1 936 598 7704",
    "sg:postcode":"75935",
    "sg:province":"TX",
    "sg:tags":[
        "oil"
    ],
    "wof:name":"Pete's Pro Auto Care",
    "wof:placetype":"venue"
},
  "geometry": {"coordinates":[-94.191472,31.804863],"type":"Point"}
}