{
  "type": "Feature",
  "properties": {
    "iso:country":"US",
    "sg:address":"130 S Central Expy",
    "sg:city":"Mckinney",
    "sg:classifiers":[
        {
            "category":"Health Services",
            "subcategory":"Doctor",
            "type":"Services"
        }
    ],
    "sg:phone":"+1 972 548 5374",
    "sg:postcode":"75070",
    "sg:province":"TX",
    "sg:tags":[
        "physician",
        "oncology",
        "surgeons",
        "surgeon",
        "gynecologic"
    ],
    "wof:name":"Hematology/Oncology Center of North Texas",
    "wof:placetype":"venue"
},
  "geometry": {"coordinates":[-96.639548,33.197478],"type":"Point"}
}