{
  "type": "Feature",
  "properties": {
    "iso:country":"US",
    "sg:address":"1902 Dove Ridge Trl",
    "sg:city":"Leander",
    "sg:classifiers":[
        {
            "category":"Manufacturing",
            "subcategory":"Jewelry",
            "type":"Manufacturing & Wholesale Goods"
        }
    ],
    "sg:phone":"+1 512 260 0174",
    "sg:postcode":"78641",
    "sg:province":"TX",
    "sg:tags":[
        "precious",
        "metal",
        "mfg"
    ],
    "wof:name":"Brag Bracelets",
    "wof:placetype":"venue"
},
  "geometry": {"coordinates":[-97.859949,30.546793],"type":"Point"}
}