{
  "type": "Feature",
  "properties": {
    "iso:country":"US",
    "sg:address":"1953 Austin St",
    "sg:city":"San Angelo",
    "sg:classifiers":[
        {
            "category":"Autos & Motor Vehicles",
            "subcategory":"Boat Sales",
            "type":"Retail Goods"
        }
    ],
    "sg:phone":"+1 325 655 1531",
    "sg:postcode":"76903",
    "sg:province":"TX",
    "sg:tags":[
        "dealer",
        "sales"
    ],
    "wof:name":"Laminated Products Co",
    "wof:placetype":"venue"
},
  "geometry": {"coordinates":[-100.445866,31.441663],"type":"Point"}
}