{
  "type": "Feature",
  "properties": {
    "iso:country":"US",
    "sg:address":"200 S 10th St",
    "sg:city":"Mcallen",
    "sg:classifiers":[
        {
            "category":"Professional",
            "subcategory":"Management & Consulting",
            "type":"Services"
        },
        {
            "category":"Wholesale",
            "subcategory":"Durable Goods & Equipment",
            "type":"Manufacturing & Wholesale Goods"
        }
    ],
    "sg:phone":"+1 956 664 0066",
    "sg:postcode":"78501",
    "sg:province":"TX",
    "sg:tags":[
        "material",
        "representative",
        "manufacturer"
    ],
    "wof:name":"Nexus Technologies",
    "wof:placetype":"venue"
},
  "geometry": {"coordinates":[-98.23035299999999,26.201584],"type":"Point"}
}