{
  "type": "Feature",
  "properties": {
    "iso:country":"US",
    "sg:address":"4012 Bus Park Dr",
    "sg:city":"Amarillo",
    "sg:classifiers":[
        {
            "category":"Building & Trades",
            "subcategory":"Electrical",
            "type":"Services"
        }
    ],
    "sg:phone":"+1 806 352 6607",
    "sg:postcode":"79110",
    "sg:province":"TX",
    "sg:tags":[
        "electrical",
        "contractor"
    ],
    "wof:name":"Total Electric of Amarillo",
    "wof:placetype":"venue"
},
  "geometry": {"coordinates":[-101.882901,35.143975],"type":"Point"}
}