{
  "type": "Feature",
  "properties": {
    "iso:country":"US",
    "sg:address":"24307 Aldine Westfield Rd",
    "sg:city":"Spring",
    "sg:classifiers":[
        {
            "category":"Restaurant",
            "type":"Food & Drink"
        }
    ],
    "sg:menulink":"http://www.allmenus.com/tx/northwest-harris/131333-white-flamingo-restaurant/menu/",
    "sg:phone":"+1 281 907 0778",
    "sg:postcode":"77373",
    "sg:province":"TX",
    "sg:tags":[
        "american"
    ],
    "wof:name":"White Flamingo Restaurant",
    "wof:placetype":"venue"
},
  "geometry": {"coordinates":[-95.398309,30.05848],"type":"Point"}
}