{
  "type": "Feature",
  "properties": {
    "iso:country":"US",
    "sg:address":"1008 W American Blvd",
    "sg:city":"Muleshoe",
    "sg:classifiers":[
        {
            "category":"Restaurant",
            "type":"Food & Drink"
        }
    ],
    "sg:phone":"+1 806 272 7517",
    "sg:postcode":"79347",
    "sg:province":"TX",
    "wof:name":"Old Corral",
    "wof:placetype":"venue"
},
  "geometry": {"coordinates":[-102.73416400000001,34.232463],"type":"Point"}
}