{
  "type": "Feature",
  "properties": {
    "iso:country":"US",
    "sg:address":"6601 Sands Point Dr",
    "sg:city":"Houston",
    "sg:classifiers":[
        {
            "category":"Professional",
            "subcategory":"Accounting & Tax Preparation",
            "type":"Services"
        }
    ],
    "sg:phone":"+1 713 272 8579",
    "sg:postcode":"77074",
    "sg:province":"TX",
    "wof:name":"Revetta Caligone",
    "wof:placetype":"venue"
},
  "geometry": {"coordinates":[-95.49857799999999,29.710987],"type":"Point"}
}