{
  "type": "Feature",
  "properties": {
    "iso:country":"US",
    "sg:address":"1301 W 3a St",
    "sg:city":"Mc Gregor",
    "sg:classifiers":[
        {
            "category":"Freight",
            "type":"Transportation"
        }
    ],
    "sg:phone":"+1 254 840 4498",
    "sg:postcode":"76657",
    "sg:province":"TX",
    "sg:tags":[
        "commercial",
        "storage"
    ],
    "wof:name":"Ace Mini Rentals",
    "wof:placetype":"venue"
},
  "geometry": {"coordinates":[-97.416247,31.434521],"type":"Point"}
}