{
  "type": "Feature",
  "properties": {
    "iso:country":"US",
    "sg:address":"3306 S Eastman Rd",
    "sg:city":"Longview",
    "sg:classifiers":[
        {
            "category":"Restaurant",
            "type":"Food & Drink"
        }
    ],
    "sg:menulink":"http://www.allmenus.com/tx/longview/218009-burger-king/menu/",
    "sg:phone":"+1 903 758 9449",
    "sg:postcode":"75602",
    "sg:province":"TX",
    "sg:tags":[
        "american"
    ],
    "wof:name":"Burger King",
    "wof:placetype":"venue"
},
  "geometry": {"coordinates":[-94.70808700000001,32.452281],"type":"Point"}
}