{
  "type": "Feature",
  "properties": {
    "iso:country":"US",
    "sg:address":"1841 W Division St",
    "sg:city":"Arlington",
    "sg:classifiers":[
        {
            "category":"Home & Garden",
            "subcategory":"Furniture",
            "type":"Retail Goods"
        }
    ],
    "sg:phone":"+1 817 277 8441",
    "sg:postcode":"76012",
    "sg:province":"TX",
    "sg:website":"www.unclaimedfreight.com",
    "wof:name":"Unclaimed Freight Co",
    "wof:placetype":"venue"
},
  "geometry": {"coordinates":[-97.137253,32.735933],"type":"Point"}
}