{
  "type": "Feature",
  "properties": {
    "iso:country":"US",
    "sg:address":"400 W Loop 820 S",
    "sg:city":"Fort Worth",
    "sg:classifiers":[
        {
            "category":"Autos & Motor Vehicles",
            "subcategory":"Automobile Sales",
            "type":"Retail Goods"
        }
    ],
    "sg:phone":"+1 817 367 1000",
    "sg:postcode":"76108",
    "sg:province":"TX",
    "wof:name":"Saturn",
    "wof:placetype":"venue"
},
  "geometry": {"coordinates":[-97.47941899999999,32.755475],"type":"Point"}
}