{
  "type": "Feature",
  "properties": {
    "iso:country":"US",
    "sg:address":"8080 N Central Expy",
    "sg:city":"Dallas",
    "sg:classifiers":[
        {
            "category":"Real Estate",
            "subcategory":"Real Estate Operator",
            "type":"Services"
        }
    ],
    "sg:phone":"+1 214 369 5072",
    "sg:postcode":"75206",
    "sg:province":"TX",
    "sg:tags":[
        "building",
        "leasing",
        "agent",
        "for"
    ],
    "wof:name":"Equity Office Properties Trust",
    "wof:placetype":"venue"
},
  "geometry": {"coordinates":[-96.769772,32.860642],"type":"Point"}
}