{
  "type": "Feature",
  "properties": {
    "iso:country":"US",
    "sg:address":"4828 Lp Central Dr",
    "sg:city":"Houston",
    "sg:classifiers":[
        {
            "category":"Banks & Credit Unions",
            "subcategory":"Bank",
            "type":"Services"
        }
    ],
    "sg:phone":"+1 713 570 2758",
    "sg:postcode":"77081",
    "sg:province":"TX",
    "sg:tags":[
        "financing"
    ],
    "wof:name":"Delta Finance Of Tx",
    "wof:placetype":"venue"
},
  "geometry": {"coordinates":[-95.457227,29.724582],"type":"Point"}
}