{
  "type": "Feature",
  "properties": {
    "iso:country":"US",
    "sg:address":"7301 Santos Dr",
    "sg:city":"Waco",
    "sg:classifiers":[
        {
            "category":"Manufacturing",
            "subcategory":"Buildings",
            "type":"Manufacturing & Wholesale Goods"
        }
    ],
    "sg:phone":"+1 254 399 9919",
    "sg:postcode":"76712",
    "sg:province":"TX",
    "sg:tags":[
        "prefab"
    ],
    "wof:name":"Dave Carter & Assoc",
    "wof:placetype":"venue"
},
  "geometry": {"coordinates":[-97.19273699999999,31.49447],"type":"Point"}
}