{
  "type": "Feature",
  "properties": {
    "iso:country":"US",
    "sg:address":"206 W Polk St",
    "sg:city":"Burnet",
    "sg:classifiers":[
        {
            "category":"Autos & Motor Vehicles",
            "subcategory":"Automobile Sales",
            "type":"Retail Goods"
        }
    ],
    "sg:phone":"+1 512 756 2128",
    "sg:postcode":"78611",
    "sg:province":"TX",
    "wof:name":"Cecil Atkisson Chrysler LLC",
    "wof:placetype":"venue"
},
  "geometry": {"coordinates":[-98.22932400000001,30.757909],"type":"Point"}
}