{
  "type": "Feature",
  "properties": {
    "iso:country":"US",
    "sg:address":"2002 Big Horn Dr",
    "sg:city":"Austin",
    "sg:classifiers":[
        {
            "category":"Manufacturing",
            "subcategory":"Buildings",
            "type":"Manufacturing & Wholesale Goods"
        },
        {
            "category":"Building & Trades",
            "subcategory":"Construction",
            "type":"Services"
        }
    ],
    "sg:phone":"+1 512 266 0887",
    "sg:postcode":"78734",
    "sg:province":"TX",
    "sg:tags":[
        "home",
        "builder",
        "contractor"
    ],
    "wof:name":"5 Star Homes Inc & R W Homes",
    "wof:placetype":"venue"
},
  "geometry": {"coordinates":[-97.915655,30.369056],"type":"Point"}
}