{
  "type": "Feature",
  "properties": {
    "iso:country":"US",
    "sg:address":"19118 Waverdale Ct",
    "sg:city":"Houston",
    "sg:classifiers":[
        {
            "category":"Professional",
            "subcategory":"Computer Services",
            "type":"Services"
        }
    ],
    "sg:phone":"+1 281 578 8397",
    "sg:postcode":"77094",
    "sg:province":"TX",
    "sg:tags":[
        "related"
    ],
    "wof:name":"Data Central LLC",
    "wof:placetype":"venue"
},
  "geometry": {"coordinates":[-95.704577,29.780683],"type":"Point"}
}