{
  "type": "Feature",
  "properties": {
    "iso:country":"US",
    "sg:address":"1623 Spring Meadow Ln",
    "sg:city":"Flower Mound",
    "sg:classifiers":[
        {
            "category":"Wholesale",
            "subcategory":"Electrical",
            "type":"Manufacturing & Wholesale Goods"
        }
    ],
    "sg:phone":"+1 972 539 7717",
    "sg:postcode":"75028",
    "sg:province":"TX",
    "sg:tags":[
        "electronic",
        "power",
        "supply"
    ],
    "wof:name":"Powerware",
    "wof:placetype":"venue"
},
  "geometry": {"coordinates":[-97.057294,33.041272],"type":"Point"}
}