{
  "type": "Feature",
  "properties": {
    "iso:country":"US",
    "sg:address":"4460 Whitehead Rd",
    "sg:city":"Midlothian",
    "sg:classifiers":[
        {
            "category":"Manufacturing",
            "subcategory":"Toys & Sporting Goods",
            "type":"Manufacturing & Wholesale Goods"
        }
    ],
    "sg:phone":"+1 972 723 8756",
    "sg:postcode":"76065",
    "sg:province":"TX",
    "sg:tags":[
        "mfg"
    ],
    "wof:name":"Bat Covers",
    "wof:placetype":"venue"
},
  "geometry": {"coordinates":[-96.976034,32.433509],"type":"Point"}
}