{
  "type": "Feature",
  "properties": {
    "iso:country":"US",
    "sg:address":"211 Woodlawn Dr",
    "sg:city":"Keene",
    "sg:classifiers":[
        {
            "category":"Restaurant",
            "type":"Food & Drink"
        }
    ],
    "sg:phone":"+1 817 645 9031",
    "sg:postcode":"76059",
    "sg:province":"TX",
    "sg:tags":[
        "hot",
        "hamburger",
        "dog",
        "stand"
    ],
    "wof:name":"Burger Bar",
    "wof:placetype":"venue"
},
  "geometry": {"coordinates":[-97.335052,32.394608],"type":"Point"}
}