{
  "type": "Feature",
  "properties": {
    "iso:country":"US",
    "sg:address":"311 Cedar Ridge St",
    "sg:city":"Magnolia",
    "sg:classifiers":[
        {
            "category":"Building & Trades",
            "subcategory":"Construction",
            "type":"Services"
        }
    ],
    "sg:phone":"+1 281 356 4985",
    "sg:postcode":"77354",
    "sg:province":"TX",
    "sg:tags":[
        "home",
        "builder",
        "family"
    ],
    "wof:name":"Allstate Builders",
    "wof:placetype":"venue"
},
  "geometry": {"coordinates":[-95.63276999999999,30.223174],"type":"Point"}
}