{
  "type": "Feature",
  "properties": {
    "iso:country":"US",
    "sg:address":"119 N Greenville Ave",
    "sg:city":"Allen",
    "sg:classifiers":[
        {
            "category":"Building & Trades",
            "subcategory":"Equipment Rental",
            "type":"Services"
        }
    ],
    "sg:phone":"+1 214 509 0429",
    "sg:postcode":"75002",
    "sg:province":"TX",
    "wof:name":"Aarons Sales & Lease",
    "wof:placetype":"venue"
},
  "geometry": {"coordinates":[-96.661963,33.100291],"type":"Point"}
}