{
  "type": "Feature",
  "properties": {
    "iso:country":"US",
    "sg:address":"1506 S Buckner Blvd",
    "sg:city":"Dallas",
    "sg:classifiers":[
        {
            "category":"Food & Beverages",
            "subcategory":"Meat & Fish",
            "type":"Retail Goods"
        }
    ],
    "sg:phone":"+1 214 391 3857",
    "sg:postcode":"75217",
    "sg:province":"TX",
    "sg:tags":[
        "shop"
    ],
    "wof:name":"La Michoacana",
    "wof:placetype":"venue"
},
  "geometry": {"coordinates":[-96.68270099999999,32.738098],"type":"Point"}
}