{
  "type": "Feature",
  "properties": {
    "iso:country":"US",
    "sg:address":"822 Stewart Dr",
    "sg:city":"Dallas",
    "sg:classifiers":[
        {
            "category":"Professional",
            "subcategory":"Computer Services",
            "type":"Services"
        }
    ],
    "sg:phone":"+1 214 941 6236",
    "sg:postcode":"75208",
    "sg:province":"TX",
    "sg:tags":[
        "related"
    ],
    "wof:name":"Genoa Consulting Group Inc",
    "wof:placetype":"venue"
},
  "geometry": {"coordinates":[-96.837104,32.754983],"type":"Point"}
}