{
  "type": "Feature",
  "properties": {
    "iso:country":"US",
    "sg:address":"1140 Randy Dr",
    "sg:city":"Waco",
    "sg:classifiers":[
        {
            "category":"Building & Trades",
            "subcategory":"Construction",
            "type":"Services"
        }
    ],
    "sg:phone":"+1 254 848 5157",
    "sg:postcode":"76712",
    "sg:province":"TX",
    "sg:tags":[
        "maker",
        "cabinet"
    ],
    "wof:name":"Specialty Cabinets",
    "wof:placetype":"venue"
},
  "geometry": {"coordinates":[-97.29328099999999,31.551204],"type":"Point"}
}