{
  "type": "Feature",
  "properties": {
    "iso:country":"US",
    "sg:address":"3700 W 7th St",
    "sg:city":"Fort Worth",
    "sg:classifiers":[
        {
            "category":"Shopping",
            "type":"Retail Goods"
        }
    ],
    "sg:phone":"+1 817 731 6412",
    "sg:postcode":"76107",
    "sg:province":"TX",
    "sg:tags":[
        "art",
        "gallery",
        "merchandise",
        "dealer"
    ],
    "sg:website":"www.esartgal.com",
    "wof:name":"Monticello Fine Arts Gallery",
    "wof:placetype":"venue"
},
  "geometry": {"coordinates":[-97.371495,32.751407],"type":"Point"}
}