{
  "type": "Feature",
  "properties": {
    "iso:country":"US",
    "sg:address":"17011 Woodacre Dr",
    "sg:city":"Houston",
    "sg:classifiers":[
        {
            "category":"Shopping",
            "subcategory":"Discount & Variety Stores",
            "type":"Retail Goods"
        }
    ],
    "sg:phone":"+1 281 456 7399",
    "sg:postcode":"77049",
    "sg:province":"TX",
    "sg:tags":[
        "merchandise",
        "general"
    ],
    "wof:name":"K Kingrey Merchandise",
    "wof:placetype":"venue"
},
  "geometry": {"coordinates":[-95.13337300000001,29.86024],"type":"Point"}
}