{
  "type": "Feature",
  "properties": {
    "iso:country":"US",
    "sg:address":"2100 W William Cannon Dr Ste A",
    "sg:city":"Austin",
    "sg:classifiers":[
        {
            "category":"Personal",
            "type":"Services"
        },
        {
            "category":"Retail",
            "subcategory":"Laundry & Dry Cleaning",
            "type":"Services"
        }
    ],
    "sg:phone":"+1 512 443 8531",
    "sg:postcode":"78745",
    "sg:province":"TX",
    "sg:tags":[
        "sewing",
        "alteration"
    ],
    "sg:website":"www.capitolcleanersaustin.com",
    "wof:name":"Capitol Cleaners and Tailors",
    "wof:placetype":"venue"
},
  "geometry": {"coordinates":[-97.808098,30.2033],"type":"Point"}
}