{
  "type": "Feature",
  "properties": {
    "iso:country":"US",
    "sg:address":"9680 Old Katy Rd",
    "sg:city":"Houston",
    "sg:classifiers":[
        {
            "category":"Shopping",
            "subcategory":"Mobile Phones",
            "type":"Retail Goods"
        }
    ],
    "sg:phone":"+1 281 260 4100",
    "sg:postcode":"77055",
    "sg:province":"TX",
    "wof:name":"Sprint",
    "wof:placetype":"venue"
},
  "geometry": {"coordinates":[-95.531403,29.785],"type":"Point"}
}