{
  "type": "Feature",
  "properties": {
    "iso:country":"US",
    "sg:address":"51 Pvt Rd 928",
    "sg:city":"Thrall",
    "sg:classifiers":[
        {
            "category":"Building & Trades",
            "subcategory":"Construction",
            "type":"Services"
        }
    ],
    "sg:phone":"+1 512 856 1100",
    "sg:postcode":"76578",
    "sg:province":"TX",
    "sg:tags":[
        "house"
    ],
    "wof:name":"TLC Homes",
    "wof:placetype":"venue"
},
  "geometry": {"coordinates":[-97.258067,30.486124],"type":"Point"}
}