{
  "type": "Feature",
  "properties": {
    "iso:country":"US",
    "sg:address":"500 Canyon Ridge Dr",
    "sg:city":"Austin",
    "sg:classifiers":[
        {
            "category":"Restaurant",
            "type":"Food & Drink"
        }
    ],
    "sg:menulink":"http://www.allmenus.com/tx/travis-northeast/89312-subway/menu/",
    "sg:phone":"+1 512 834 9131",
    "sg:postcode":"78753",
    "sg:province":"TX",
    "sg:tags":[
        "american",
        "sandwich"
    ],
    "wof:name":"Subway",
    "wof:placetype":"venue"
},
  "geometry": {"coordinates":[-97.66873099999999,30.400363],"type":"Point"}
}