{
  "type": "Feature",
  "properties": {
    "iso:country":"US",
    "sg:address":"4849 FM 366",
    "sg:city":"Groves",
    "sg:classifiers":[
        {
            "category":"Wholesale",
            "subcategory":"Machinery & Supplies",
            "type":"Manufacturing & Wholesale Goods"
        }
    ],
    "sg:phone":"+1 409 962 0420",
    "sg:postcode":"77619",
    "sg:province":"TX",
    "sg:tags":[
        "equipment",
        "industrial"
    ],
    "wof:name":"American Welding Supply Inc",
    "wof:placetype":"venue"
},
  "geometry": {"coordinates":[-93.91664900000001,29.961925],"type":"Point"}
}