{
  "type": "Feature",
  "properties": {
    "iso:country":"US",
    "sg:address":"1207 Montopolis Dr",
    "sg:city":"Austin",
    "sg:classifiers":[
        {
            "category":"Organizations",
            "subcategory":"Religious Organization",
            "type":"Services"
        }
    ],
    "sg:phone":"+1 512 385 5090",
    "sg:postcode":"78741",
    "sg:province":"TX",
    "sg:tags":[
        "monastery",
        "convent"
    ],
    "wof:name":"Franciscian Convent",
    "wof:placetype":"venue"
},
  "geometry": {"coordinates":[-97.69914900000001,30.231715],"type":"Point"}
}