{
  "type": "Feature",
  "properties": {
    "iso:country":"US",
    "sg:address":"4916 Telephone Rd",
    "sg:city":"Houston",
    "sg:classifiers":[
        {
            "category":"Restaurant",
            "type":"Food & Drink"
        },
        {
            "category":"Shopping",
            "type":"Retail Goods"
        }
    ],
    "sg:phone":"+1 713 847 9312",
    "sg:postcode":"77087",
    "sg:province":"TX",
    "sg:tags":[
        "mexican",
        "eating"
    ],
    "wof:name":"Bella Tapatilla",
    "wof:placetype":"venue"
},
  "geometry": {"coordinates":[-95.298897,29.690901],"type":"Point"}
}