{
  "type": "Feature",
  "properties": {
    "iso:country":"US",
    "sg:address":"1716 S Valley Mills Dr",
    "sg:city":"Waco",
    "sg:classifiers":[
        {
            "category":"Retail",
            "subcategory":"Auto Repair",
            "type":"Services"
        }
    ],
    "sg:phone":"+1 254 754 4481",
    "sg:postcode":"76711",
    "sg:province":"TX",
    "sg:tags":[
        "alternator",
        "generator"
    ],
    "wof:name":"WACO Armature & Generator WRKS",
    "wof:placetype":"venue"
},
  "geometry": {"coordinates":[-97.140649,31.525212],"type":"Point"}
}