{
  "type": "Feature",
  "properties": {
    "iso:country":"US",
    "sg:address":"9802 Westpark Dr",
    "sg:city":"Houston",
    "sg:classifiers":[
        {
            "category":"Autos & Motor Vehicles",
            "subcategory":"Fuel & Gas Station",
            "type":"Retail Goods"
        }
    ],
    "sg:phone":"+1 713 782 2155",
    "sg:postcode":"77063",
    "sg:province":"TX",
    "sg:website":"www.citgo.com",
    "wof:name":"Nancy's Citgo",
    "wof:placetype":"venue"
},
  "geometry": {"coordinates":[-95.53270000000001,29.720501],"type":"Point"}
}