{
  "type": "Feature",
  "properties": {
    "iso:country":"US",
    "sg:address":"1100 Folsom Rd",
    "sg:city":"Amarillo",
    "sg:classifiers":[
        {
            "category":"Travel",
            "subcategory":"Campground",
            "type":"Entertainment"
        }
    ],
    "sg:phone":"+1 806 335 1792",
    "sg:postcode":"79108",
    "sg:province":"TX",
    "sg:tags":[
        "recreational",
        "park",
        "vehicle"
    ],
    "sg:website":"http://www.amarillokoa.com",
    "wof:name":"Amarillo K O A Kampgrounds",
    "wof:placetype":"venue"
},
  "geometry": {"coordinates":[-101.72364,35.221931],"type":"Point"}
}