{
  "type": "Feature",
  "properties": {
    "iso:country":"US",
    "sg:address":"2114 Longwood Ln",
    "sg:city":"Dallas",
    "sg:classifiers":[
        {
            "category":"Professional",
            "type":"Services"
        }
    ],
    "sg:phone":"+1 214 328 5890",
    "sg:postcode":"75228",
    "sg:province":"TX",
    "sg:tags":[
        "scientist"
    ],
    "wof:name":"K P Technical Solutions",
    "wof:placetype":"venue"
},
  "geometry": {"coordinates":[-96.705118,32.809309],"type":"Point"}
}