{
  "type": "Feature",
  "properties": {
    "iso:country":"US",
    "sg:address":"6211 Manor Rd Apt 106",
    "sg:city":"Austin",
    "sg:classifiers":[
        {
            "category":"Professional",
            "subcategory":"Detective & Security Services",
            "type":"Services"
        }
    ],
    "sg:phone":"+1 512 927 8717",
    "sg:postcode":"78723",
    "sg:province":"TX",
    "sg:tags":[
        "information",
        "bureau"
    ],
    "wof:name":"Quality Plumbing Service",
    "wof:placetype":"venue"
},
  "geometry": {"coordinates":[-97.675392,30.308032],"type":"Point"}
}