{
  "type": "Feature",
  "properties": {
    "iso:country":"US",
    "sg:address":"8705 Piney Creek Bend",
    "sg:city":"Austin",
    "sg:classifiers":[
        {
            "category":"Professional",
            "subcategory":"Management & Consulting",
            "type":"Services"
        }
    ],
    "sg:phone":"+1 512 280 8829",
    "sg:postcode":"78745",
    "sg:province":"TX",
    "sg:tags":[
        "retail",
        "direct",
        "sales"
    ],
    "wof:name":"Diana H Owens",
    "wof:placetype":"venue"
},
  "geometry": {"coordinates":[-97.835988,30.193212],"type":"Point"}
}