{
  "type": "Feature",
  "properties": {
    "iso:country":"US",
    "sg:address":"9813 Emma Rd",
    "sg:city":"Needville",
    "sg:classifiers":[
        {
            "category":"Real Estate",
            "subcategory":"Developer",
            "type":"Services"
        }
    ],
    "sg:phone":"+1 979 793 6722",
    "sg:postcode":"77461",
    "sg:province":"TX",
    "sg:tags":[
        "cemetery"
    ],
    "wof:name":"Concord Cemetary of Fairc",
    "wof:placetype":"venue"
},
  "geometry": {"coordinates":[-95.78395,29.43133],"type":"Point"}
}