{
  "type": "Feature",
  "properties": {
    "iso:country":"US",
    "sg:address":"9741 US Hwy 290",
    "sg:city":"Austin",
    "sg:classifiers":[
        {
            "category":"Building & Trades",
            "subcategory":"Construction",
            "type":"Services"
        }
    ],
    "sg:phone":"+1 512 278 0004",
    "sg:postcode":"78724",
    "sg:province":"TX",
    "wof:name":"Ameritech Portable Buildings",
    "wof:placetype":"venue"
},
  "geometry": {"coordinates":[-97.61393,30.332801],"type":"Point"}
}