{
  "type": "Feature",
  "properties": {
    "iso:country":"US",
    "sg:address":"11211 Pembridge Dr",
    "sg:city":"Houston",
    "sg:classifiers":[
        {
            "category":"Arts & Performance",
            "subcategory":"Theater",
            "type":"Entertainment"
        }
    ],
    "sg:phone":"+1 713 772 4529",
    "sg:postcode":"77071",
    "sg:province":"TX",
    "sg:tags":[
        "group"
    ],
    "wof:name":"The Ultimate Entertainment Co",
    "wof:placetype":"venue"
},
  "geometry": {"coordinates":[-95.516848,29.65614],"type":"Point"}
}