{
  "type": "Feature",
  "properties": {
    "iso:country":"US",
    "sg:address":"1107 California Ln",
    "sg:city":"Arlington",
    "sg:classifiers":[
        {
            "category":"Retail",
            "subcategory":"Auto Repair",
            "type":"Services"
        }
    ],
    "sg:phone":"+1 817 274 6663",
    "sg:postcode":"76015",
    "sg:province":"TX",
    "sg:tags":[
        "repairing",
        "automobile"
    ],
    "wof:name":"BHO Auto Repair Shop",
    "wof:placetype":"venue"
},
  "geometry": {"coordinates":[-97.127807,32.699454],"type":"Point"}
}