{
  "type": "Feature",
  "properties": {
    "iso:country":"US",
    "sg:address":"1807 W Braker Ln",
    "sg:city":"Austin",
    "sg:classifiers":[
        {
            "category":"Shopping",
            "type":"Retail Goods"
        }
    ],
    "sg:phone":"+1 512 442 4229",
    "sg:postcode":"78758",
    "sg:province":"TX",
    "sg:tags":[
        "wheel",
        "chair",
        "scooter"
    ],
    "wof:name":"Adorno Mobility",
    "wof:placetype":"venue"
},
  "geometry": {"coordinates":[-97.706906,30.39155],"type":"Point"}
}