{
  "type": "Feature",
  "properties": {
    "iso:country":"US",
    "sg:address":"4020 Buckner Blvd",
    "sg:city":"Dallas",
    "sg:classifiers":[
        {
            "category":"Professional",
            "subcategory":"Business Services",
            "type":"Services"
        }
    ],
    "sg:phone":"+1 214 388 4100",
    "sg:postcode":"75227",
    "sg:province":"TX",
    "wof:name":"Turner Business Solutions Grp",
    "wof:placetype":"venue"
},
  "geometry": {"coordinates":[-96.68261200000001,32.774026],"type":"Point"}
}