{
  "type": "Feature",
  "properties": {
    "iso:country":"US",
    "sg:address":"1212 S Main St",
    "sg:city":"Linden",
    "sg:classifiers":[
        {
            "category":"Real Estate",
            "subcategory":"Real Estate Services",
            "type":"Services"
        }
    ],
    "sg:phone":"+1 903 756 3375",
    "sg:postcode":"75563",
    "sg:province":"TX",
    "sg:tags":[
        "company",
        "title"
    ],
    "wof:name":"Lone Star Title Co Cass Count",
    "wof:placetype":"venue"
},
  "geometry": {"coordinates":[-94.363141,33.002131],"type":"Point"}
}