{
  "type": "Feature",
  "properties": {
    "iso:country":"US",
    "sg:address":"3518 W Vickery Blvd",
    "sg:city":"Fort Worth",
    "sg:classifiers":[
        {
            "category":"Real Estate",
            "subcategory":"Architect",
            "type":"Services"
        }
    ],
    "sg:phone":"+1 817 737 0404",
    "sg:postcode":"76107",
    "sg:province":"TX",
    "sg:tags":[
        "architectural",
        "furniture"
    ],
    "wof:name":"Malone & Company",
    "wof:placetype":"venue"
},
  "geometry": {"coordinates":[-97.36985300000001,32.73013],"type":"Point"}
}