{
  "type": "Feature",
  "properties": {
    "iso:country":"US",
    "sg:address":"319 W Broadway St",
    "sg:city":"Andrews",
    "sg:classifiers":[
        {
            "category":"Mining & Drilling",
            "type":"Manufacturing & Wholesale Goods"
        }
    ],
    "sg:phone":"+1 432 524 6267",
    "sg:postcode":"79714",
    "sg:province":"TX",
    "sg:tags":[
        "oil",
        "gas",
        "producer"
    ],
    "wof:name":"Duke Oil & Gas",
    "wof:placetype":"venue"
},
  "geometry": {"coordinates":[-102.549903,32.317908],"type":"Point"}
}