{
  "type": "Feature",
  "properties": {
    "iso:country":"US",
    "sg:address":"500 W Wall St",
    "sg:city":"Midland",
    "sg:classifiers":[
        {
            "category":"Utilities",
            "subcategory":"Electric",
            "type":"Services"
        }
    ],
    "sg:phone":"+1 432 684 0300",
    "sg:postcode":"79701",
    "sg:province":"TX",
    "sg:tags":[
        "company"
    ],
    "wof:name":"Caprock Electric Co",
    "wof:placetype":"venue"
},
  "geometry": {"coordinates":[-102.080512,31.997376],"type":"Point"}
}