{
  "type": "Feature",
  "properties": {
    "iso:country":"US",
    "sg:address":"14241 Montana Ave",
    "sg:city":"El Paso",
    "sg:classifiers":[
        {
            "category":"Freight",
            "type":"Transportation"
        }
    ],
    "sg:phone":"+1 915 849 1244",
    "sg:postcode":"79938",
    "sg:province":"TX",
    "sg:tags":[
        "mover"
    ],
    "wof:name":"A Quick Moving & Satellite Svc",
    "wof:placetype":"venue"
},
  "geometry": {"coordinates":[-106.181608,31.81797],"type":"Point"}
}