{
  "type": "Feature",
  "properties": {
    "iso:country":"US",
    "sg:address":"5815 John Wayne",
    "sg:city":"San Antonio",
    "sg:classifiers":[
        {
            "category":"Wholesale",
            "subcategory":"Machinery & Supplies",
            "type":"Manufacturing & Wholesale Goods"
        }
    ],
    "sg:phone":"+1 210 684 3268",
    "sg:postcode":"78240",
    "sg:province":"TX",
    "sg:tags":[
        "fitting",
        "valve"
    ],
    "wof:name":"Mexico Valve & Fitting Company",
    "wof:placetype":"venue"
},
  "geometry": {"coordinates":[-98.600146,29.507481],"type":"Point"}
}