{
  "type": "Feature",
  "properties": {
    "iso:country":"US",
    "sg:address":"531 Toronto St",
    "sg:city":"Dallas",
    "sg:classifiers":[
        {
            "category":"Organizations",
            "subcategory":"Religious Organization",
            "type":"Services"
        }
    ],
    "sg:phone":"+1 214 741 1180",
    "sg:postcode":"75212",
    "sg:province":"TX",
    "wof:name":"New Mt Corinth Baptist Church",
    "wof:placetype":"venue"
},
  "geometry": {"coordinates":[-96.83316600000001,32.779628],"type":"Point"}
}