{
  "type": "Feature",
  "properties": {
    "iso:country":"US",
    "sg:address":"1900 State Hwy 356",
    "sg:city":"Irving",
    "sg:classifiers":[
        {
            "category":"Food & Beverages",
            "subcategory":"Groceries & Convenience Stores",
            "type":"Retail Goods"
        }
    ],
    "sg:phone":"+1 972 579 5530",
    "sg:postcode":"75060",
    "sg:province":"TX",
    "wof:name":"Loop 12 Fina",
    "wof:placetype":"venue"
},
  "geometry": {"coordinates":[-96.91727299999999,32.809703],"type":"Point"}
}