{
  "type": "Feature",
  "properties": {
    "iso:country":"US",
    "sg:address":"1411 W Hildebrand Ave",
    "sg:city":"San Antonio",
    "sg:classifiers":[
        {
            "category":"Professional",
            "subcategory":"Business Services",
            "type":"Services"
        }
    ],
    "sg:phone":"+1 210 734 2092",
    "sg:postcode":"78201",
    "sg:province":"TX",
    "sg:tags":[
        "recording",
        "studio"
    ],
    "wof:name":"Suena Bien Inc",
    "wof:placetype":"venue"
},
  "geometry": {"coordinates":[-98.518608,29.466529],"type":"Point"}
}