{
  "type": "Feature",
  "properties": {
    "iso:country":"US",
    "sg:address":"3420 Executive Center Dr # 200",
    "sg:city":"Austin",
    "sg:classifiers":[
        {
            "category":"Banks & Credit Unions",
            "subcategory":"Investment Brokerage",
            "type":"Services"
        },
        {
            "category":"Insurance",
            "subcategory":"Hazard Insurance",
            "type":"Services"
        }
    ],
    "sg:phone":"+1 512 345 7500",
    "sg:postcode":"78731",
    "sg:province":"TX",
    "sg:tags":[
        "agent",
        "resume"
    ],
    "wof:name":"Association Risk Management",
    "wof:placetype":"venue"
},
  "geometry": {"coordinates":[-97.746803,30.358721],"type":"Point"}
}