{
  "type": "Feature",
  "properties": {
    "iso:country":"US",
    "sg:address":"1140 Clear Lake City Blvd",
    "sg:city":"Houston",
    "sg:classifiers":[
        {
            "category":"Health Services",
            "subcategory":"Doctor",
            "type":"Services"
        }
    ],
    "sg:phone":"+1 281 486 8400",
    "sg:postcode":"77062",
    "sg:province":"TX",
    "sg:tags":[
        "dentist"
    ],
    "wof:name":"American Orthodontic Assoc",
    "wof:placetype":"venue"
},
  "geometry": {"coordinates":[-95.156886,29.580784],"type":"Point"}
}