{
  "type": "Feature",
  "properties": {
    "iso:country":"US",
    "sg:address":"8500 Freeport Dr",
    "sg:city":"Dallas",
    "sg:classifiers":[
        {
            "category":"Shopping",
            "subcategory":"Clothing, Apparel, & Fashions",
            "type":"Retail Goods"
        }
    ],
    "sg:phone":"+1 214 596 0204",
    "sg:postcode":"75228",
    "sg:province":"TX",
    "sg:tags":[
        "family"
    ],
    "wof:name":"Marshalls Region Office",
    "wof:placetype":"venue"
},
  "geometry": {"coordinates":[-96.678116,32.809515],"type":"Point"}
}