{
  "type": "Feature",
  "properties": {
    "iso:country":"US",
    "sg:address":"2000 Kinwest Pkwy",
    "sg:city":"Irving",
    "sg:classifiers":[
        {
            "category":"Organizations",
            "subcategory":"Religious Organization",
            "type":"Services"
        }
    ],
    "sg:phone":"+1 972 869 3920",
    "sg:postcode":"75063",
    "sg:province":"TX",
    "sg:tags":[
        "church"
    ],
    "sg:website":"www.hackberrycreekchurch.com",
    "wof:name":"Presbyterian Church",
    "wof:placetype":"venue"
},
  "geometry": {"coordinates":[-96.964574,32.91193],"type":"Point"}
}