{
  "type": "Feature",
  "properties": {
    "iso:country":"US",
    "sg:address":"4424 Edsee St",
    "sg:city":"Houston",
    "sg:classifiers":[
        {
            "category":"Retail",
            "subcategory":"Portrait Studio",
            "type":"Services"
        }
    ],
    "sg:phone":"+1 713 862 6768",
    "sg:postcode":"77009",
    "sg:province":"TX",
    "sg:tags":[
        "photography",
        "store"
    ],
    "wof:name":"Callins Tom Photographer",
    "wof:placetype":"venue"
},
  "geometry": {"coordinates":[-95.3806,29.7978],"type":"Point"}
}