{
  "type": "Feature",
  "properties": {
    "iso:country":"US",
    "sg:address":"1107 Laurence Dr",
    "sg:city":"Rockwall",
    "sg:classifiers":[
        {
            "category":"Freight",
            "type":"Transportation"
        }
    ],
    "sg:phone":"+1 972 771 2017",
    "sg:postcode":"75032",
    "sg:province":"TX",
    "sg:tags":[
        "operator",
        "local",
        "trucking"
    ],
    "wof:name":"B&M Miller Trucking",
    "wof:placetype":"venue"
},
  "geometry": {"coordinates":[-96.470135,32.851627],"type":"Point"}
}