{
  "type": "Feature",
  "properties": {
    "iso:country":"US",
    "sg:address":"3025 S Cravens Rd",
    "sg:city":"Fort Worth",
    "sg:classifiers":[
        {
            "category":"Building & Trades",
            "subcategory":"Equipment Rental",
            "type":"Services"
        }
    ],
    "sg:phone":"+1 817 429 1750",
    "sg:postcode":"76119",
    "sg:province":"TX",
    "sg:tags":[
        "crane"
    ],
    "wof:name":"F B Mc Intire Equipment Co",
    "wof:placetype":"venue"
},
  "geometry": {"coordinates":[-97.22563599999999,32.712493],"type":"Point"}
}