{
  "type": "Feature",
  "properties": {
    "iso:country":"US",
    "sg:address":"105 Jefferson St",
    "sg:city":"Pittsburg",
    "sg:classifiers":[
        {
            "category":"Personal",
            "type":"Services"
        }
    ],
    "sg:phone":"+1 903 856 7779",
    "sg:postcode":"75686",
    "sg:province":"TX",
    "sg:tags":[
        "florist"
    ],
    "wof:name":"Pittsburg Floral & Wedding",
    "wof:placetype":"venue"
},
  "geometry": {"coordinates":[-94.967043,32.995237],"type":"Point"}
}