{
  "type": "Feature",
  "properties": {
    "iso:country":"US",
    "sg:address":"1021 Ranch Rd 620 S",
    "sg:city":"Lakeway",
    "sg:classifiers":[
        {
            "category":"Insurance",
            "subcategory":"Insurance Agent",
            "type":"Services"
        }
    ],
    "sg:phone":"+1 512 306 8814",
    "sg:postcode":"78734",
    "sg:province":"TX",
    "wof:name":"Harold Coleman Agency",
    "wof:placetype":"venue"
},
  "geometry": {"coordinates":[-97.962115,30.352857],"type":"Point"}
}