{
  "type": "Feature",
  "properties": {
    "iso:country":"US",
    "sg:address":"4925 S Nelson Dr",
    "sg:city":"Katy",
    "sg:classifiers":[
        {
            "category":"Banks & Credit Unions",
            "subcategory":"Bank",
            "type":"Services"
        }
    ],
    "sg:phone":"+1 281 391 8711",
    "sg:postcode":"77493",
    "sg:province":"TX",
    "sg:tags":[
        "personal",
        "institution"
    ],
    "wof:name":"Fisher Investment Inc",
    "wof:placetype":"venue"
},
  "geometry": {"coordinates":[-95.80277100000001,29.793051],"type":"Point"}
}