{
  "type": "Feature",
  "properties": {
    "iso:country":"US",
    "sg:address":"6075 Broadway Blvd",
    "sg:city":"Garland",
    "sg:classifiers":[
        {
            "category":"Coffee & Tea",
            "type":"Food & Drink"
        }
    ],
    "sg:menulink":"http://www.allmenus.com/tx/northeast/112884-starbucks-coffee/menu/",
    "sg:phone":"+1 972 303 3723",
    "sg:postcode":"75043",
    "sg:province":"TX",
    "sg:tags":[
        "american"
    ],
    "wof:name":"Starbucks Coffee",
    "wof:placetype":"venue"
},
  "geometry": {"coordinates":[-96.595927,32.842252],"type":"Point"}
}