{
  "type": "Feature",
  "properties": {
    "iso:country":"US",
    "sg:address":"5009 Stanley Keller Rd",
    "sg:city":"Fort Worth",
    "sg:classifiers":[
        {
            "category":"Organizations",
            "subcategory":"Religious Organization",
            "type":"Services"
        }
    ],
    "sg:phone":"+1 817 281 2017",
    "sg:postcode":"76117",
    "sg:province":"TX",
    "sg:tags":[
        "church"
    ],
    "wof:name":"Haltom City Church-Nazarene",
    "wof:placetype":"venue"
},
  "geometry": {"coordinates":[-97.275032,32.824232],"type":"Point"}
}