{
  "type": "Feature",
  "properties": {
    "iso:country":"US",
    "sg:address":"10113 Wild Dunes Dr",
    "sg:city":"Austin",
    "sg:classifiers":[
        {
            "category":"Arts & Performance",
            "subcategory":"Music",
            "type":"Entertainment"
        }
    ],
    "sg:phone":"+1 512 329 5172",
    "sg:postcode":"78747",
    "sg:province":"TX",
    "sg:tags":[
        "band",
        "orchestra"
    ],
    "wof:name":"Texas Swing Kings",
    "wof:placetype":"venue"
},
  "geometry": {"coordinates":[-97.777458,30.147324],"type":"Point"}
}