{
  "type": "Feature",
  "properties": {
    "iso:country":"US",
    "sg:address":"7515 Lemmon Ave",
    "sg:city":"Dallas",
    "sg:classifiers":[
        {
            "category":"Airline",
            "type":"Transportation"
        }
    ],
    "sg:phone":"+1 214 654 9770",
    "sg:postcode":"75204",
    "sg:province":"TX",
    "sg:tags":[
        "scheduled",
        "air"
    ],
    "wof:name":"City Airlines",
    "wof:placetype":"venue"
},
  "geometry": {"coordinates":[-96.838515,32.848366],"type":"Point"}
}