{
  "type": "Feature",
  "properties": {
    "iso:country":"US",
    "sg:address":"6607 Mistflower Ln",
    "sg:city":"Katy",
    "sg:classifiers":[
        {
            "category":"Professional",
            "type":"Services"
        }
    ],
    "sg:phone":"+1 832 594 6624",
    "sg:postcode":"77449",
    "sg:province":"TX",
    "wof:name":"Adrian R Rodriguez",
    "wof:placetype":"venue"
},
  "geometry": {"coordinates":[-95.688372,29.873072],"type":"Point"}
}