{
  "type": "Feature",
  "properties": {
    "iso:country":"US",
    "sg:address":"3615 Washington Blvd",
    "sg:city":"Beaumont",
    "sg:classifiers":[
        {
            "category":"Autos & Motor Vehicles",
            "subcategory":"Auto Supplies",
            "type":"Retail Goods"
        }
    ],
    "sg:phone":"+1 409 842 1794",
    "sg:postcode":"77705",
    "sg:province":"TX",
    "sg:tags":[
        "wheel",
        "automotive",
        "parts",
        "tire"
    ],
    "wof:name":"Modica Brothers Tire & Whl Ctr",
    "wof:placetype":"venue"
},
  "geometry": {"coordinates":[-94.12972000000001,30.05569],"type":"Point"}
}