{
  "type": "Feature",
  "properties": {
    "iso:country":"US",
    "sg:address":"5303 King George Dr",
    "sg:city":"San Antonio",
    "sg:classifiers":[
        {
            "category":"Professional",
            "type":"Services"
        }
    ],
    "sg:phone":"+1 210 614 5923",
    "sg:postcode":"78229",
    "sg:province":"TX",
    "wof:name":"Divine Mercy Center of SA",
    "wof:placetype":"venue"
},
  "geometry": {"coordinates":[-98.59054,29.497188],"type":"Point"}
}