{
  "type": "Feature",
  "properties": {
    "iso:country":"US",
    "sg:address":"1313 Rio Hondo Rd",
    "sg:city":"Harlingen",
    "sg:classifiers":[
        {
            "category":"Professional",
            "type":"Services"
        }
    ],
    "sg:phone":"+1 956 423 8264",
    "sg:postcode":"78550",
    "sg:province":"TX",
    "wof:name":"Kathys Korner",
    "wof:placetype":"venue"
},
  "geometry": {"coordinates":[-97.682515,26.21255],"type":"Point"}
}