{
  "type": "Feature",
  "properties": {
    "iso:country":"US",
    "sg:address":"6111 Willowbend Blvd",
    "sg:city":"Houston",
    "sg:classifiers":[
        {
            "category":"Real Estate",
            "subcategory":"Developer",
            "type":"Services"
        }
    ],
    "sg:phone":"+1 713 772 6575",
    "sg:postcode":"77096",
    "sg:province":"TX",
    "wof:name":"Auburn Regal",
    "wof:placetype":"venue"
},
  "geometry": {"coordinates":[-95.49817899999999,29.666295],"type":"Point"}
}