{
  "type": "Feature",
  "properties": {
    "iso:country":"US",
    "sg:address":"11100 Childress Ave",
    "sg:city":"El Paso",
    "sg:classifiers":[
        {
            "category":"Shopping",
            "subcategory":"Gifts & Souvenirs",
            "type":"Retail Goods"
        }
    ],
    "sg:phone":"+1 915 590 2273",
    "sg:postcode":"79936",
    "sg:province":"TX",
    "sg:tags":[
        "party",
        "supply"
    ],
    "wof:name":"Buddy's Jumping Balloons",
    "wof:placetype":"venue"
},
  "geometry": {"coordinates":[-106.308165,31.796989],"type":"Point"}
}