{
  "type": "Feature",
  "properties": {
    "iso:country":"US",
    "sg:address":"12045 US Hwy 87",
    "sg:city":"Adkins",
    "sg:classifiers":[
        {
            "category":"Building & Trades",
            "subcategory":"Equipment Rental",
            "type":"Services"
        }
    ],
    "sg:phone":"+1 210 649 2006",
    "sg:postcode":"78101",
    "sg:province":"TX",
    "sg:tags":[
        "yard"
    ],
    "wof:name":"Just Married Rentals",
    "wof:placetype":"venue"
},
  "geometry": {"coordinates":[-98.25135,29.367054],"type":"Point"}
}