{
  "type": "Feature",
  "properties": {
    "iso:country":"US",
    "sg:address":"3708 Glade Rd",
    "sg:city":"Colleyville",
    "sg:classifiers":[
        {
            "category":"Place Of Worship",
            "subcategory":"Church",
            "type":"Public Place"
        },
        {
            "category":"Place Of Worship",
            "type":"Public Place"
        }
    ],
    "sg:phone":"+1 817 571 2019",
    "sg:postcode":"76034",
    "sg:province":"TX",
    "sg:tags":[
        "churches-baptist-general",
        "churches-baptist"
    ],
    "wof:name":"Pleasant Glade Baptist Church",
    "wof:placetype":"venue"
},
  "geometry": {"coordinates":[-97.108879,32.881797],"type":"Point"}
}