{
  "type": "Feature",
  "properties": {
    "iso:country":"US",
    "sg:address":"6619 Fireflame Dr",
    "sg:city":"Dallas",
    "sg:classifiers":[
        {
            "category":"Professional",
            "type":"Services"
        }
    ],
    "sg:phone":"+1 972 934 1728",
    "sg:postcode":"75248",
    "sg:province":"TX",
    "sg:tags":[
        "establishment"
    ],
    "wof:name":"Robert Meisels Assoc",
    "wof:placetype":"venue"
},
  "geometry": {"coordinates":[-96.792247,32.960507],"type":"Point"}
}