{
  "type": "Feature",
  "properties": {
    "iso:country":"US",
    "sg:address":"2302 53rd St",
    "sg:city":"Lubbock",
    "sg:classifiers":[
        {
            "category":"Retail",
            "subcategory":"Repair Shop",
            "type":"Services"
        }
    ],
    "sg:phone":"+1 806 744 5333",
    "sg:postcode":"79412",
    "sg:province":"TX",
    "sg:tags":[
        "wholesale",
        "installation",
        "system",
        "radio"
    ],
    "wof:name":"Commercial Radio Company",
    "wof:placetype":"venue"
},
  "geometry": {"coordinates":[-101.870209,33.546126],"type":"Point"}
}