{
  "type": "Feature",
  "properties": {
    "iso:country":"US",
    "sg:address":"354 Fairview Ave",
    "sg:city":"San Antonio",
    "sg:classifiers":[
        {
            "category":"Retail",
            "subcategory":"Portrait Studio",
            "type":"Services"
        }
    ],
    "sg:phone":"+1 210 533 8808",
    "sg:postcode":"78223",
    "sg:province":"TX",
    "sg:tags":[
        "photo"
    ],
    "wof:name":"Michael Cappelli Photography",
    "wof:placetype":"venue"
},
  "geometry": {"coordinates":[-98.47137600000001,29.381965],"type":"Point"}
}