{
  "type": "Feature",
  "properties": {
    "iso:country":"US",
    "sg:address":"3823 Deerbrook Dr",
    "sg:city":"Kingwood",
    "sg:classifiers":[
        {
            "category":"Manufacturing",
            "subcategory":"Paper Products",
            "type":"Manufacturing & Wholesale Goods"
        }
    ],
    "sg:phone":"+1 281 361 8926",
    "sg:postcode":"77339",
    "sg:province":"TX",
    "sg:tags":[
        "bamboo"
    ],
    "wof:name":"Marshall Place",
    "wof:placetype":"venue"
},
  "geometry": {"coordinates":[-95.19199399999999,30.063784],"type":"Point"}
}