{
  "type": "Feature",
  "properties": {
    "iso:country":"US",
    "sg:address":"801 Kessler Cove",
    "sg:city":"Pflugerville",
    "sg:classifiers":[
        {
            "category":"Building & Trades",
            "subcategory":"Plumbing",
            "type":"Services"
        }
    ],
    "sg:phone":"+1 512 844 0626",
    "sg:postcode":"78660",
    "sg:province":"TX",
    "sg:tags":[
        "contractor"
    ],
    "wof:name":"Ronnies Plumbing Services",
    "wof:placetype":"venue"
},
  "geometry": {"coordinates":[-97.63146999999999,30.470862],"type":"Point"}
}