{
  "type": "Feature",
  "properties": {
    "iso:country":"US",
    "sg:address":"408 W Montgomery St",
    "sg:city":"Willis",
    "sg:classifiers":[
        {
            "category":"Health Services",
            "subcategory":"Doctor",
            "type":"Services"
        }
    ],
    "sg:phone":"+1 936 890 4235",
    "sg:postcode":"77378",
    "sg:province":"TX",
    "sg:tags":[
        "medical"
    ],
    "wof:name":"Sadler Clinic",
    "wof:placetype":"venue"
},
  "geometry": {"coordinates":[-95.48306599999999,30.423259],"type":"Point"}
}