{
  "type": "Feature",
  "properties": {
    "iso:country":"US",
    "sg:address":"3333 S US Hwy 75",
    "sg:city":"Sherman",
    "sg:classifiers":[
        {
            "category":"Professional",
            "subcategory":"Business Services",
            "type":"Services"
        }
    ],
    "sg:phone":"+1 903 891 9190",
    "sg:postcode":"75090",
    "sg:province":"TX",
    "wof:name":"Pro Vision Associates",
    "wof:placetype":"venue"
},
  "geometry": {"coordinates":[-96.60977,33.609531],"type":"Point"}
}