{
  "type": "Feature",
  "properties": {
    "iso:country":"US",
    "sg:address":"6817 Cielo Vista Dr",
    "sg:city":"El Paso",
    "sg:classifiers":[
        {
            "category":"Travel",
            "subcategory":"Travel Agent",
            "type":"Entertainment"
        }
    ],
    "sg:phone":"+1 915 775 1455",
    "sg:postcode":"79925",
    "sg:province":"TX",
    "sg:tags":[
        "agency"
    ],
    "wof:name":"Travel Boutique",
    "wof:placetype":"venue"
},
  "geometry": {"coordinates":[-106.39344199999999,31.78806],"type":"Point"}
}