{
  "type": "Feature",
  "properties": {
    "iso:country":"US",
    "sg:address":"8325 Thackery St",
    "sg:city":"Dallas",
    "sg:classifiers":[
        {
            "category":"Personal",
            "type":"Services"
        }
    ],
    "sg:phone":"+1 214 352 1047",
    "sg:postcode":"75225",
    "sg:province":"TX",
    "wof:name":"Neighbors Genealogical Society",
    "wof:placetype":"venue"
},
  "geometry": {"coordinates":[-96.792136,32.864119],"type":"Point"}
}