{
  "type": "Feature",
  "properties": {
    "iso:country":"US",
    "sg:address":"908 Harwood Ct",
    "sg:city":"Euless",
    "sg:classifiers":[
        {
            "category":"Professional",
            "type":"Services"
        }
    ],
    "sg:phone":"+1 817 571 5205",
    "sg:postcode":"76039",
    "sg:province":"TX",
    "wof:name":"Dolly N Rosy Inc",
    "wof:placetype":"venue"
},
  "geometry": {"coordinates":[-97.076078,32.849973],"type":"Point"}
}