{
  "type": "Feature",
  "properties": {
    "iso:country":"US",
    "sg:address":"30070 US Hwy 281",
    "sg:city":"Bulverde",
    "sg:classifiers":[
        {
            "category":"Restaurant",
            "type":"Food & Drink"
        }
    ],
    "sg:phone":"+1 830 438 3458",
    "sg:postcode":"78163",
    "sg:province":"TX",
    "sg:tags":[
        "eating"
    ],
    "wof:name":"Subway",
    "wof:placetype":"venue"
},
  "geometry": {"coordinates":[-98.43958000000001,29.733327],"type":"Point"}
}