{
  "type": "Feature",
  "properties": {
    "iso:country":"US",
    "sg:address":"3350 Olsen Blvd",
    "sg:city":"Amarillo",
    "sg:classifiers":[
        {
            "category":"Organizations",
            "subcategory":"Community Association",
            "type":"Services"
        }
    ],
    "sg:phone":"+1 806 468 9135",
    "sg:postcode":"79109",
    "sg:province":"TX",
    "wof:name":"Baptist Community Svc",
    "wof:placetype":"venue"
},
  "geometry": {"coordinates":[-101.879643,35.185006],"type":"Point"}
}