{
  "type": "Feature",
  "properties": {
    "iso:country":"US",
    "sg:address":"1709 N Sarah Dewitt Dr",
    "sg:city":"Gonzales",
    "sg:classifiers":[
        {
            "category":"Government",
            "subcategory":"Office",
            "type":"Public Place"
        }
    ],
    "sg:phone":"+1 830 672 3328",
    "sg:postcode":"78629",
    "sg:province":"TX",
    "sg:tags":[
        "state",
        "program"
    ],
    "wof:name":"Public Safety Dept",
    "wof:placetype":"venue"
},
  "geometry": {"coordinates":[-97.443873,29.522365],"type":"Point"}
}