{
  "type": "Feature",
  "properties": {
    "iso:country":"US",
    "sg:address":"1639 Navarro Cir",
    "sg:city":"Corsicana",
    "sg:classifiers":[
        {
            "category":"Retail",
            "subcategory":"Repair Shop",
            "type":"Services"
        }
    ],
    "sg:phone":"+1 903 874 2321",
    "sg:postcode":"75110",
    "sg:province":"TX",
    "wof:name":"Bradda",
    "wof:placetype":"venue"
},
  "geometry": {"coordinates":[-96.471621,32.108553],"type":"Point"}
}