{
  "type": "Feature",
  "properties": {
    "iso:country":"US",
    "sg:address":"3064 Norwalk Ave",
    "sg:city":"Dallas",
    "sg:classifiers":[
        {
            "category":"Shopping",
            "subcategory":"Clothing, Apparel, & Fashions",
            "type":"Retail Goods"
        }
    ],
    "sg:phone":"+1 214 902 8907",
    "sg:postcode":"75220",
    "sg:province":"TX",
    "wof:name":"Marthas Crafts",
    "wof:placetype":"venue"
},
  "geometry": {"coordinates":[-96.870221,32.859385],"type":"Point"}
}