{
  "type": "Feature",
  "properties": {
    "iso:country":"US",
    "sg:address":"3754 Weeburn Dr",
    "sg:city":"Dallas",
    "sg:classifiers":[
        {
            "category":"Real Estate",
            "subcategory":"Real Estate Agent",
            "type":"Services"
        }
    ],
    "sg:phone":"+1 214 350 2299",
    "sg:postcode":"75229",
    "sg:province":"TX",
    "wof:name":"Beth Hamilton Inc",
    "wof:placetype":"venue"
},
  "geometry": {"coordinates":[-96.85141900000001,32.907455],"type":"Point"}
}