{
  "type": "Feature",
  "properties": {
    "iso:country":"US",
    "sg:address":"751 E Southlake Blvd",
    "sg:city":"Southlake",
    "sg:classifiers":[
        {
            "category":"Wholesale",
            "subcategory":"Furniture",
            "type":"Manufacturing & Wholesale Goods"
        },
        {
            "category":"Wholesale",
            "subcategory":"Durable Goods & Equipment",
            "type":"Manufacturing & Wholesale Goods"
        }
    ],
    "sg:phone":"+1 817 416 9950",
    "sg:postcode":"76092",
    "sg:province":"TX",
    "sg:tags":[
        "representative",
        "manufacturer"
    ],
    "wof:name":"Joe Bayer & Associates Inc",
    "wof:placetype":"venue"
},
  "geometry": {"coordinates":[-97.134276,32.941015],"type":"Point"}
}