{
  "type": "Feature",
  "properties": {
    "iso:country":"US",
    "sg:address":"2502 Royal Ln Ste 101",
    "sg:city":"Dallas",
    "sg:classifiers":[
        {
            "category":"Food & Beverages",
            "subcategory":"Groceries & Convenience Stores",
            "type":"Retail Goods"
        }
    ],
    "sg:phone":"+1 972 243 3071",
    "sg:postcode":"75229",
    "sg:province":"TX",
    "wof:name":"K Corner Convenience Store",
    "wof:placetype":"venue"
},
  "geometry": {"coordinates":[-96.89589700000001,32.895901],"type":"Point"}
}