{
  "type": "Feature",
  "properties": {
    "iso:country":"US",
    "sg:address":"515 W Veterans Memorial Blvd",
    "sg:city":"Harker Heights",
    "sg:classifiers":[
        {
            "category":"Manufacturing",
            "subcategory":"Printing",
            "type":"Manufacturing & Wholesale Goods"
        }
    ],
    "sg:phone":"+1 254 699 2352",
    "sg:postcode":"76548",
    "sg:province":"TX",
    "sg:tags":[
        "screen"
    ],
    "wof:name":"GRAPHIC Concepts",
    "wof:placetype":"venue"
},
  "geometry": {"coordinates":[-97.670683,31.091353],"type":"Point"}
}