{
  "type": "Feature",
  "properties": {
    "iso:country":"US",
    "sg:address":"2021 Pennington Dr",
    "sg:city":"Arlington",
    "sg:classifiers":[
        {
            "category":"Shopping",
            "subcategory":"Gifts & Souvenirs",
            "type":"Retail Goods"
        }
    ],
    "sg:phone":"+1 817 557 1494",
    "sg:postcode":"76014",
    "sg:province":"TX",
    "sg:tags":[
        "balloon",
        "artist"
    ],
    "wof:name":"Balloon Designs",
    "wof:placetype":"venue"
},
  "geometry": {"coordinates":[-97.07762200000001,32.687494],"type":"Point"}
}