{
  "type": "Feature",
  "properties": {
    "iso:country":"US",
    "sg:address":"1318 Antoine Dr",
    "sg:city":"Houston",
    "sg:classifiers":[
        {
            "category":"Social Services",
            "subcategory":"Child Care",
            "type":"Services"
        }
    ],
    "sg:phone":"+1 713 682 0035",
    "sg:postcode":"77055",
    "sg:province":"TX",
    "wof:name":"Ark Children's Ctr",
    "wof:placetype":"venue"
},
  "geometry": {"coordinates":[-95.475549,29.793136],"type":"Point"}
}