{
  "type": "Feature",
  "properties": {
    "iso:country":"US",
    "sg:address":"12343 Murphy Rd Ste G",
    "sg:city":"Stafford",
    "sg:classifiers":[
        {
            "category":"Food & Beverages",
            "subcategory":"Liquor & Beverages",
            "type":"Retail Goods"
        }
    ],
    "sg:phone":"+1 281 530 1232",
    "sg:postcode":"77477",
    "sg:province":"TX",
    "sg:tags":[
        "beer",
        "spirit",
        "wine"
    ],
    "wof:name":"Evergreen Liquor & Keg Beer Corp",
    "wof:placetype":"venue"
},
  "geometry": {"coordinates":[-95.56458600000001,29.641558],"type":"Point"}
}