{
  "type": "Feature",
  "properties": {
    "iso:country":"US",
    "sg:address":"6103 Larkmount Dr",
    "sg:city":"Spring",
    "sg:classifiers":[
        {
            "category":"Retail",
            "subcategory":"Laundry & Dry Cleaning",
            "type":"Services"
        }
    ],
    "sg:phone":"+1 281 350 1654",
    "sg:postcode":"77389",
    "sg:province":"TX",
    "wof:name":"Advanced Carpet Clean & Dye",
    "wof:placetype":"venue"
},
  "geometry": {"coordinates":[-95.512624,30.11453],"type":"Point"}
}