{
  "type": "Feature",
  "properties": {
    "iso:country":"US",
    "sg:address":"1602 Ave F",
    "sg:city":"Del Rio",
    "sg:classifiers":[
        {
            "category":"Food & Beverages",
            "subcategory":"Groceries & Convenience Stores",
            "type":"Retail Goods"
        }
    ],
    "sg:phone":"+1 830 774 4280",
    "sg:postcode":"78840",
    "sg:province":"TX",
    "wof:name":"Tejano Mart",
    "wof:placetype":"venue"
},
  "geometry": {"coordinates":[-100.904201,29.379554],"type":"Point"}
}