{
  "type": "Feature",
  "properties": {
    "iso:country":"US",
    "sg:address":"5514 Atkinson Cir",
    "sg:city":"Orange",
    "sg:classifiers":[
        {
            "category":"Food & Beverages",
            "subcategory":"Groceries & Convenience Stores",
            "type":"Retail Goods"
        }
    ],
    "sg:phone":"+1 409 745 2290",
    "sg:postcode":"77630",
    "sg:province":"TX",
    "wof:name":"Texas Marine Grocery",
    "wof:placetype":"venue"
},
  "geometry": {"coordinates":[-93.83537699999999,30.102685],"type":"Point"}
}