{
  "type": "Feature",
  "properties": {
    "iso:country":"US",
    "sg:address":"314 W Ellaine Ave",
    "sg:city":"Pasadena",
    "sg:classifiers":[
        {
            "category":"Wholesale",
            "subcategory":"Auto Parts",
            "type":"Manufacturing & Wholesale Goods"
        }
    ],
    "sg:phone":"+1 713 473 7410",
    "sg:postcode":"77506",
    "sg:province":"TX",
    "sg:tags":[
        "tube",
        "tire"
    ],
    "wof:name":"Galvan Brothers Used Tires",
    "wof:placetype":"venue"
},
  "geometry": {"coordinates":[-95.21534200000001,29.69447],"type":"Point"}
}