{
  "type": "Feature",
  "properties": {
    "iso:country":"US",
    "sg:address":"8368 Alameda Ave",
    "sg:city":"El Paso",
    "sg:classifiers":[
        {
            "category":"Retail",
            "subcategory":"Auto Repair",
            "type":"Services"
        }
    ],
    "sg:phone":"+1 915 858 5570",
    "sg:postcode":"79907",
    "sg:province":"TX",
    "sg:tags":[
        "wrecker"
    ],
    "wof:name":"A D Wrecker Svc",
    "wof:placetype":"venue"
},
  "geometry": {"coordinates":[-106.34850400000001,31.7127],"type":"Point"}
}