{
  "type": "Feature",
  "properties": {
    "iso:country":"US",
    "sg:address":"3937 Shadycreek Ln",
    "sg:city":"Dallas",
    "sg:classifiers":[
        {
            "category":"Banks & Credit Unions",
            "subcategory":"Investment Brokerage",
            "type":"Services"
        }
    ],
    "sg:phone":"+1 214 675 9146",
    "sg:postcode":"75229",
    "sg:province":"TX",
    "sg:tags":[
        "advisory",
        "financial"
    ],
    "sg:website":"www.rcslocum.com",
    "wof:name":"E-Signa.Com",
    "wof:placetype":"venue"
},
  "geometry": {"coordinates":[-96.84733199999999,32.890632],"type":"Point"}
}