{
  "type": "Feature",
  "properties": {
    "iso:country":"US",
    "sg:address":"411 S Alamo St",
    "sg:city":"Refugio",
    "sg:classifiers":[
        {
            "category":"Mining & Drilling",
            "type":"Manufacturing & Wholesale Goods"
        }
    ],
    "sg:phone":"+1 361 526 2161",
    "sg:postcode":"78377",
    "sg:province":"TX",
    "sg:tags":[
        "field"
    ],
    "wof:name":"Antique Station",
    "wof:placetype":"venue"
},
  "geometry": {"coordinates":[-97.275902,28.301729],"type":"Point"}
}