{
  "type": "Feature",
  "properties": {
    "iso:country":"US",
    "sg:address":"5624 W Tidwell Rd",
    "sg:city":"Houston",
    "sg:classifiers":[
        {
            "category":"Shopping",
            "subcategory":"Beauty & Cosmetics",
            "type":"Retail Goods"
        }
    ],
    "sg:phone":"+1 713 957 8808",
    "sg:postcode":"77091",
    "sg:province":"TX",
    "sg:tags":[
        "supply"
    ],
    "wof:name":"Q Hair Beauty Supply",
    "wof:placetype":"venue"
},
  "geometry": {"coordinates":[-95.471603,29.848801],"type":"Point"}
}