{
  "type": "Feature",
  "properties": {
    "iso:country":"US",
    "sg:address":"6505 W Park Blvd",
    "sg:city":"Plano",
    "sg:classifiers":[
        {
            "category":"Education",
            "subcategory":"Special Training",
            "type":"Public Place"
        }
    ],
    "sg:phone":"+1 972 781 0111",
    "sg:postcode":"75093",
    "sg:province":"TX",
    "sg:tags":[
        "tutoring"
    ],
    "wof:name":"Kumon Math & Reading Ctr",
    "wof:placetype":"venue"
},
  "geometry": {"coordinates":[-96.84020200000001,33.0276],"type":"Point"}
}