{
  "type": "Feature",
  "properties": {
    "iso:country":"US",
    "sg:address":"3816 Seminole Pl",
    "sg:city":"Carrollton",
    "sg:classifiers":[
        {
            "category":"Professional",
            "subcategory":"Art Services",
            "type":"Services"
        }
    ],
    "sg:phone":"+1 972 395 0110",
    "sg:postcode":"75007",
    "sg:province":"TX",
    "sg:tags":[
        "commercial",
        "design"
    ],
    "wof:name":"Promotional Advertising Works",
    "wof:placetype":"venue"
},
  "geometry": {"coordinates":[-96.916709,33.014658],"type":"Point"}
}