{
  "type": "Feature",
  "properties": {
    "iso:country":"US",
    "sg:address":"13205 Maham Rd",
    "sg:city":"Dallas",
    "sg:classifiers":[
        {
            "category":"Restaurant",
            "type":"Food & Drink"
        }
    ],
    "sg:phone":"+1 972 671 4501",
    "sg:postcode":"75240",
    "sg:province":"TX",
    "wof:name":"Philly Connections",
    "wof:placetype":"venue"
},
  "geometry": {"coordinates":[-96.761301,32.928373],"type":"Point"}
}