{
  "type": "Feature",
  "properties": {
    "iso:country":"US",
    "sg:address":"4215 Seminole St",
    "sg:city":"Pasadena",
    "sg:classifiers":[
        {
            "category":"Professional",
            "subcategory":"Business Services",
            "type":"Services"
        }
    ],
    "sg:phone":"+1 281 487 6037",
    "sg:postcode":"77504",
    "sg:province":"TX",
    "wof:name":"Jim Greer & Assoc Inc",
    "wof:placetype":"venue"
},
  "geometry": {"coordinates":[-95.175872,29.644389],"type":"Point"}
}