{
  "type": "Feature",
  "properties": {
    "iso:country":"US",
    "sg:address":"1212 N Austin St",
    "sg:city":"Seguin",
    "sg:classifiers":[
        {
            "category":"Autos & Motor Vehicles",
            "subcategory":"Automobile Sales",
            "type":"Retail Goods"
        }
    ],
    "sg:phone":"+1 830 379 1718",
    "sg:postcode":"78155",
    "sg:province":"TX",
    "sg:tags":[
        "used",
        "car",
        "metal",
        "nonferrous",
        "produce",
        "dealer",
        "secondary"
    ],
    "wof:name":"Adam's Used Cars",
    "wof:placetype":"venue"
},
  "geometry": {"coordinates":[-97.964844,29.578825],"type":"Point"}
}