{
  "type": "Feature",
  "properties": {
    "iso:country":"US",
    "sg:address":"1611 Co Rd 7200",
    "sg:city":"Lubbock",
    "sg:classifiers":[
        {
            "category":"Professional",
            "type":"Services"
        }
    ],
    "sg:phone":"+1 806 745 6868",
    "sg:postcode":"79404",
    "sg:province":"TX",
    "wof:name":"Diana T Lopez",
    "wof:placetype":"venue"
},
  "geometry": {"coordinates":[-101.823842,33.50538],"type":"Point"}
}