{
  "type": "Feature",
  "properties": {
    "iso:country":"US",
    "sg:address":"1649 W Northwest Hwy",
    "sg:city":"Grapevine",
    "sg:postcode":"76051",
    "sg:province":"TX",
    "sg:website":"http://www.passionlighting.com",
    "wof:name":"Passion Lighting",
    "wof:placetype":"venue"
},
  "geometry": {"coordinates":[-97.09358899999999,32.941109],"type":"Point"}
}