{
  "type": "Feature",
  "properties": {
    "iso:country":"US",
    "sg:address":"1804 B Oakhill Ln",
    "sg:city":"Austin",
    "sg:classifiers":[
        {
            "category":"Autos & Motor Vehicles",
            "subcategory":"Automobile Sales",
            "type":"Retail Goods"
        },
        {
            "category":"Retail",
            "subcategory":"Auto Repair",
            "type":"Services"
        }
    ],
    "sg:phone":"+1 512 282 0055",
    "sg:postcode":"78744",
    "sg:province":"TX",
    "sg:tags":[
        "body",
        "shop",
        "car"
    ],
    "sg:website":"www.austinautorefurb.com",
    "wof:name":"Austin Auto Refurbishing",
    "wof:placetype":"venue"
},
  "geometry": {"coordinates":[-97.78456,30.165526],"type":"Point"}
}