{
  "type": "Feature",
  "properties": {
    "iso:country":"US",
    "sg:address":"1516 Browning Rd",
    "sg:city":"Orange",
    "sg:classifiers":[
        {
            "category":"Real Estate",
            "subcategory":"Real Estate Operator",
            "type":"Services"
        }
    ],
    "sg:phone":"+1 409 883 3411",
    "sg:postcode":"77630",
    "sg:province":"TX",
    "sg:tags":[
        "building",
        "nonresidential"
    ],
    "wof:name":"Odl Properties Ltd",
    "wof:placetype":"venue"
},
  "geometry": {"coordinates":[-93.791735,30.103012],"type":"Point"}
}