{
  "type": "Feature",
  "properties": {
    "iso:country":"US",
    "sg:address":"10802 Vickijohn Ct",
    "sg:city":"Houston",
    "sg:classifiers":[
        {
            "category":"Professional",
            "subcategory":"Engineering",
            "type":"Services"
        }
    ],
    "sg:phone":"+1 713 974 7569",
    "sg:postcode":"77071",
    "sg:province":"TX",
    "sg:tags":[
        "consultant"
    ],
    "wof:name":"Grissom David P E",
    "wof:placetype":"venue"
},
  "geometry": {"coordinates":[-95.512506,29.662561],"type":"Point"}
}