{
  "type": "Feature",
  "properties": {
    "iso:country":"US",
    "sg:address":"720 Bay Area Blvd",
    "sg:city":"League City",
    "sg:classifiers":[
        {
            "category":"Real Estate",
            "subcategory":"Real Estate Agent",
            "type":"Services"
        }
    ],
    "sg:phone":"+1 281 554 8023",
    "sg:postcode":"77573",
    "sg:province":"TX",
    "wof:name":"Greystar Realty Svc",
    "wof:placetype":"venue"
},
  "geometry": {"coordinates":[-95.148066,29.484686],"type":"Point"}
}