{
  "type": "Feature",
  "properties": {
    "iso:country":"US",
    "sg:address":"1009 Southbay Dr",
    "sg:city":"Corpus Christi",
    "sg:classifiers":[
        {
            "category":"Building & Trades",
            "subcategory":"Electrical",
            "type":"Services"
        }
    ],
    "sg:phone":"+1 361 334 9183",
    "sg:postcode":"78412",
    "sg:province":"TX",
    "sg:tags":[
        "electrical",
        "system",
        "contractor"
    ],
    "wof:name":"Complete Intgrated Systems Inc",
    "wof:placetype":"venue"
},
  "geometry": {"coordinates":[-97.318442,27.688264],"type":"Point"}
}