{
  "type": "Feature",
  "properties": {
    "iso:country":"US",
    "sg:address":"1313 Ranch Rd 620 S",
    "sg:city":"Lakeway",
    "sg:classifiers":[
        {
            "category":"Professional",
            "subcategory":"Lawyer & Legal Services",
            "type":"Services"
        }
    ],
    "sg:phone":"+1 512 402 1855",
    "sg:postcode":"78734",
    "sg:province":"TX",
    "sg:tags":[
        "attorney"
    ],
    "wof:name":"Robert M Roller",
    "wof:placetype":"venue"
},
  "geometry": {"coordinates":[-97.963019,30.351277],"type":"Point"}
}