{
  "type": "Feature",
  "properties": {
    "iso:country":"US",
    "sg:address":"156 Quitman St",
    "sg:city":"Pittsburg",
    "sg:classifiers":[
        {
            "category":"Professional",
            "subcategory":"Lawyer & Legal Services",
            "type":"Services"
        }
    ],
    "sg:phone":"+1 903 855 0022",
    "sg:postcode":"75686",
    "sg:province":"TX",
    "sg:tags":[
        "attorney"
    ],
    "wof:name":"Simmons Law Office",
    "wof:placetype":"venue"
},
  "geometry": {"coordinates":[-94.969239,32.996895],"type":"Point"}
}