{
  "type": "Feature",
  "properties": {
    "iso:country":"US",
    "sg:address":"232 N Marsalis Ave",
    "sg:city":"Dallas",
    "sg:classifiers":[
        {
            "category":"Retail",
            "subcategory":"Auto Repair",
            "type":"Services"
        }
    ],
    "sg:phone":"+1 214 946 2039",
    "sg:postcode":"75203",
    "sg:province":"TX",
    "sg:tags":[
        "wrecker"
    ],
    "wof:name":"Javier's Wrecker Svc",
    "wof:placetype":"venue"
},
  "geometry": {"coordinates":[-96.815552,32.750694],"type":"Point"}
}