{
  "type": "Feature",
  "properties": {
    "iso:country":"US",
    "sg:address":"121 Oakwood Dr",
    "sg:city":"Weatherford",
    "sg:classifiers":[
        {
            "category":"Professional",
            "subcategory":"Business Services",
            "type":"Services"
        }
    ],
    "sg:phone":"+1 817 594 3744",
    "sg:postcode":"76086",
    "sg:province":"TX",
    "wof:name":"Phillips Water Hauling",
    "wof:placetype":"venue"
},
  "geometry": {"coordinates":[-97.779482,32.76773],"type":"Point"}
}