{
  "type": "Feature",
  "properties": {
    "iso:country":"US",
    "sg:address":"25630 Running Water Dr",
    "sg:city":"Huffman",
    "sg:classifiers":[
        {
            "category":"Real Estate",
            "subcategory":"Real Estate Agent",
            "type":"Services"
        }
    ],
    "sg:phone":"+1 281 324 3147",
    "sg:postcode":"77336",
    "sg:province":"TX",
    "wof:name":"Stable Property Management",
    "wof:placetype":"venue"
},
  "geometry": {"coordinates":[-95.115489,30.043633],"type":"Point"}
}