{
  "type": "Feature",
  "properties": {
    "iso:country":"US",
    "sg:address":"1016 16th St Ste 19",
    "sg:city":"Wellington",
    "sg:classifiers":[
        {
            "category":"Personal",
            "subcategory":"Beauty Salon",
            "type":"Services"
        }
    ],
    "sg:phone":"+1 806 447 5075",
    "sg:postcode":"79095",
    "sg:province":"TX",
    "sg:tags":[
        "hair",
        "stylist"
    ],
    "wof:name":"His And Her Style Shop",
    "wof:placetype":"venue"
},
  "geometry": {"coordinates":[-100.212898,34.848122],"type":"Point"}
}