{
  "type": "Feature",
  "properties": {
    "iso:country":"US",
    "sg:address":"401 S Bolton St",
    "sg:city":"Jacksonville",
    "sg:classifiers":[
        {
            "category":"Food & Beverages",
            "subcategory":"Groceries & Convenience Stores",
            "type":"Retail Goods"
        }
    ],
    "sg:phone":"+1 903 589 2688",
    "sg:postcode":"75766",
    "sg:province":"TX",
    "wof:name":"Skeeter's 2",
    "wof:placetype":"venue"
},
  "geometry": {"coordinates":[-95.27299499999999,31.961464],"type":"Point"}
}