{
  "type": "Feature",
  "properties": {
    "iso:country":"US",
    "sg:address":"19122 Cypress Flower Dr",
    "sg:city":"Katy",
    "sg:classifiers":[
        {
            "category":"Professional",
            "type":"Services"
        }
    ],
    "sg:phone":"+1 281 550 8108",
    "sg:postcode":"77449",
    "sg:province":"TX",
    "wof:name":"Clints Creations",
    "wof:placetype":"venue"
},
  "geometry": {"coordinates":[-95.707701,29.832861],"type":"Point"}
}