{
  "type": "Feature",
  "properties": {
    "iso:country":"US",
    "sg:address":"4400 Keeter Dr",
    "sg:city":"Fort Worth",
    "sg:classifiers":[
        {
            "category":"Professional",
            "type":"Services"
        }
    ],
    "sg:phone":"+1 817 595 1813",
    "sg:postcode":"76180",
    "sg:province":"TX",
    "wof:name":"Tlp Graphics Plus",
    "wof:placetype":"venue"
},
  "geometry": {"coordinates":[-97.208389,32.829152],"type":"Point"}
}