{
  "type": "Feature",
  "properties": {
    "iso:country":"US",
    "sg:address":"1681 N Central Expy",
    "sg:city":"Richardson",
    "sg:classifiers":[
        {
            "category":"Shopping",
            "subcategory":"Clothing, Apparel, & Fashions",
            "type":"Retail Goods"
        }
    ],
    "sg:phone":"+1 972 542 6599",
    "sg:postcode":"75080",
    "sg:province":"TX",
    "sg:tags":[
        "item",
        "boutique"
    ],
    "wof:name":"Claire's Boutique",
    "wof:placetype":"venue"
},
  "geometry": {"coordinates":[-96.719516,32.970863],"type":"Point"}
}