{
  "type": "Feature",
  "properties": {
    "iso:country":"US",
    "sg:address":"1001 E 2nd St",
    "sg:city":"Alice",
    "sg:classifiers":[
        {
            "category":"Professional",
            "subcategory":"Business Services",
            "type":"Services"
        }
    ],
    "sg:phone":"+1 361 664 1533",
    "sg:postcode":"78332",
    "sg:province":"TX",
    "sg:tags":[
        "consulting"
    ],
    "wof:name":"Chuck Pilkington Consulti",
    "wof:placetype":"venue"
},
  "geometry": {"coordinates":[-98.066348,27.752237],"type":"Point"}
}