{
  "type": "Feature",
  "properties": {
    "iso:country":"US",
    "sg:address":"1015 Roy St",
    "sg:city":"Houston",
    "sg:classifiers":[
        {
            "category":"Building & Trades",
            "subcategory":"Construction",
            "type":"Services"
        }
    ],
    "sg:phone":"+1 713 864 7999",
    "sg:postcode":"77007",
    "sg:province":"TX",
    "sg:tags":[
        "water",
        "waste",
        "treatment",
        "sewage"
    ],
    "wof:name":"Liquid Cleaning Processes Inc",
    "wof:placetype":"venue"
},
  "geometry": {"coordinates":[-95.412581,29.77106],"type":"Point"}
}