{
  "type": "Feature",
  "properties": {
    "iso:country":"US",
    "sg:address":"705 Port America Pl",
    "sg:city":"Grapevine",
    "sg:classifiers":[
        {
            "category":"Freight",
            "type":"Transportation"
        }
    ],
    "sg:phone":"+1 817 424 9080",
    "sg:postcode":"76051",
    "sg:province":"TX",
    "sg:tags":[
        "packing",
        "crating"
    ],
    "wof:name":"GSI Logistics",
    "wof:placetype":"venue"
},
  "geometry": {"coordinates":[-97.065079,32.919233],"type":"Point"}
}