{
  "type": "Feature",
  "properties": {
    "iso:country":"US",
    "sg:address":"508 Colony Creek Dr",
    "sg:city":"Victoria",
    "sg:classifiers":[
        {
            "category":"Building & Trades",
            "subcategory":"Construction",
            "type":"Services"
        }
    ],
    "sg:phone":"+1 361 578 4227",
    "sg:postcode":"77904",
    "sg:province":"TX",
    "sg:tags":[
        "concrete",
        "contractor"
    ],
    "wof:name":"Clay's Construction",
    "wof:placetype":"venue"
},
  "geometry": {"coordinates":[-96.949552,28.831691],"type":"Point"}
}