{
  "type": "Feature",
  "properties": {
    "iso:country":"US",
    "sg:address":"6925 Gregdale Rd",
    "sg:city":"Houston",
    "sg:classifiers":[
        {
            "category":"Wholesale",
            "subcategory":"Vending Machines",
            "type":"Manufacturing & Wholesale Goods"
        }
    ],
    "sg:phone":"+1 281 459 4713",
    "sg:postcode":"77049",
    "sg:province":"TX",
    "sg:tags":[
        "operator"
    ],
    "wof:name":"Homestyle Vending",
    "wof:placetype":"venue"
},
  "geometry": {"coordinates":[-95.211539,29.827072],"type":"Point"}
}