{
  "type": "Feature",
  "properties": {
    "iso:country":"US",
    "sg:address":"2128 Benbrook Dr",
    "sg:city":"Carrollton",
    "sg:classifiers":[
        {
            "category":"Shopping",
            "subcategory":"Shoes",
            "type":"Retail Goods"
        }
    ],
    "sg:phone":"+1 469 892 0779",
    "sg:postcode":"75007",
    "sg:province":"TX",
    "wof:name":"Torres Boots",
    "wof:placetype":"venue"
},
  "geometry": {"coordinates":[-96.881029,32.98826],"type":"Point"}
}