{
  "type": "Feature",
  "properties": {
    "iso:country":"US",
    "sg:address":"1615 Solitude Dr",
    "sg:city":"Dallas",
    "sg:classifiers":[
        {
            "category":"Building & Trades",
            "subcategory":"Plumbing",
            "type":"Services"
        }
    ],
    "sg:phone":"+1 214 371 1317",
    "sg:postcode":"75241",
    "sg:province":"TX",
    "sg:tags":[
        "conditioning",
        "air",
        "system",
        "contractor"
    ],
    "wof:name":"Angel AC Heat & Appliance",
    "wof:placetype":"venue"
},
  "geometry": {"coordinates":[-96.793458,32.675028],"type":"Point"}
}