{
  "type": "Feature",
  "properties": {
    "iso:country":"US",
    "sg:address":"4310 Wiley Post Rd",
    "sg:city":"Addison",
    "sg:classifiers":[
        {
            "category":"Real Estate",
            "subcategory":"Real Estate Agent",
            "type":"Services"
        },
        {
            "category":"Professional",
            "subcategory":"Business Services",
            "type":"Services"
        }
    ],
    "sg:phone":"+1 972 386 7511",
    "sg:postcode":"75001",
    "sg:province":"TX",
    "sg:tags":[
        "appraiser"
    ],
    "wof:name":"Appraisal Depot LLC",
    "wof:placetype":"venue"
},
  "geometry": {"coordinates":[-96.837924,32.96015],"type":"Point"}
}