{
  "type": "Feature",
  "properties": {
    "iso:country":"US",
    "sg:address":"104 Barcelona Ave",
    "sg:city":"Brownsville",
    "sg:classifiers":[
        {
            "category":"Home & Garden",
            "subcategory":"Carpets & Floor Coverings",
            "type":"Retail Goods"
        }
    ],
    "sg:phone":"+1 956 504 3700",
    "sg:postcode":"78526",
    "sg:province":"TX",
    "wof:name":"Alfa Tile & Carpet",
    "wof:placetype":"venue"
},
  "geometry": {"coordinates":[-97.489907,25.960566],"type":"Point"}
}