{
  "type": "Feature",
  "properties": {
    "iso:country":"US",
    "sg:address":"923 Gateside Dr",
    "sg:city":"Houston",
    "sg:classifiers":[
        {
            "category":"Wholesale",
            "subcategory":"Machinery & Supplies",
            "type":"Manufacturing & Wholesale Goods"
        }
    ],
    "sg:phone":"+1 281 449 0575",
    "sg:postcode":"77032",
    "sg:province":"TX",
    "sg:tags":[
        "tool",
        "oil",
        "well",
        "fishing"
    ],
    "wof:name":"Century Fishing & Rental Tools",
    "wof:placetype":"venue"
},
  "geometry": {"coordinates":[-95.376614,29.948311],"type":"Point"}
}