{
  "type": "Feature",
  "properties": {
    "iso:country":"US",
    "sg:address":"2501 E Amarillo Blvd",
    "sg:city":"Amarillo",
    "sg:classifiers":[
        {
            "category":"Shopping",
            "subcategory":"Discount & Variety Stores",
            "type":"Retail Goods"
        }
    ],
    "sg:phone":"+1 806 383 7472",
    "sg:postcode":"79107",
    "sg:province":"TX",
    "sg:tags":[
        "salvage",
        "surplus",
        "merchandise",
        "general"
    ],
    "wof:name":"Tantalus Surplus & Salvage",
    "wof:placetype":"venue"
},
  "geometry": {"coordinates":[-101.808153,35.22199],"type":"Point"}
}