{
  "type": "Feature",
  "properties": {
    "iso:country":"US",
    "sg:address":"6300 Samuell Blvd Ste 125",
    "sg:city":"Dallas",
    "sg:classifiers":[
        {
            "category":"Health Services",
            "subcategory":"Hospital",
            "type":"Services"
        }
    ],
    "sg:phone":"+1 214 388 8690",
    "sg:postcode":"75228",
    "sg:province":"TX",
    "sg:tags":[
        "dialysis"
    ],
    "wof:name":"Village Ii Dialysis Center",
    "wof:placetype":"venue"
},
  "geometry": {"coordinates":[-96.698667,32.792146],"type":"Point"}
}