{
  "type": "Feature",
  "properties": {
    "iso:country":"US",
    "sg:address":"2800 N Alexander Dr",
    "sg:city":"Baytown",
    "sg:classifiers":[
        {
            "category":"Manufacturing",
            "subcategory":"Food",
            "type":"Manufacturing & Wholesale Goods"
        }
    ],
    "sg:phone":"+1 281 424 4315",
    "sg:postcode":"77520",
    "sg:province":"TX",
    "sg:tags":[
        "product",
        "mfg"
    ],
    "wof:name":"Schotts Sunbeam",
    "wof:placetype":"venue"
},
  "geometry": {"coordinates":[-94.943777,29.753031],"type":"Point"}
}