{
  "type": "Feature",
  "properties": {
    "iso:country":"US",
    "sg:address":"6825 Randol Mill Rd",
    "sg:city":"Fort Worth",
    "sg:classifiers":[
        {
            "category":"Building & Trades",
            "subcategory":"Construction",
            "type":"Services"
        }
    ],
    "sg:phone":"+1 817 654 0470",
    "sg:postcode":"76120",
    "sg:province":"TX",
    "wof:name":"Granite Construction Co",
    "wof:placetype":"venue"
},
  "geometry": {"coordinates":[-97.21133500000001,32.778407],"type":"Point"}
}