{
  "type": "Feature",
  "properties": {
    "iso:country":"US",
    "sg:address":"136 Nueces St",
    "sg:city":"Hereford",
    "sg:classifiers":[
        {
            "category":"Real Estate",
            "subcategory":"Real Estate Agent",
            "type":"Services"
        }
    ],
    "sg:phone":"+1 806 363 1479",
    "sg:postcode":"79045",
    "sg:province":"TX",
    "wof:name":"Charlie Kerr Realtor",
    "wof:placetype":"venue"
},
  "geometry": {"coordinates":[-102.426509,34.8249],"type":"Point"}
}