{
  "type": "Feature",
  "properties": {
    "iso:country":"US",
    "sg:address":"3709 Troup Hwy",
    "sg:city":"Tyler",
    "sg:classifiers":[
        {
            "category":"Building & Trades",
            "subcategory":"Construction",
            "type":"Services"
        }
    ],
    "sg:phone":"+1 903 561 9429",
    "sg:postcode":"75703",
    "sg:province":"TX",
    "sg:tags":[
        "waterproofing",
        "contractor"
    ],
    "wof:name":"Exums Waterproofing",
    "wof:placetype":"venue"
},
  "geometry": {"coordinates":[-95.272944,32.309474],"type":"Point"}
}