{
  "type": "Feature",
  "properties": {
    "iso:country":"US",
    "sg:address":"11250 Fallbrook Dr",
    "sg:city":"Houston",
    "sg:classifiers":[
        {
            "category":"Wholesale",
            "subcategory":"Books, Periodicals, & Newspapers",
            "type":"Manufacturing & Wholesale Goods"
        }
    ],
    "sg:phone":"+1 281 807 7188",
    "sg:postcode":"77065",
    "sg:province":"TX",
    "sg:tags":[
        "dealers-wholesale",
        "news"
    ],
    "wof:name":"AP",
    "wof:placetype":"venue"
},
  "geometry": {"coordinates":[-95.587318,29.924999],"type":"Point"}
}