{
  "type": "Feature",
  "properties": {
    "iso:country":"US",
    "sg:address":"4708 Prestwick Dr",
    "sg:city":"Colleyville",
    "sg:classifiers":[
        {
            "category":"Professional",
            "subcategory":"Engineering",
            "type":"Services"
        }
    ],
    "sg:phone":"+1 972 603 9749",
    "sg:postcode":"76034",
    "sg:province":"TX",
    "sg:tags":[
        "aeronautical",
        "engineer"
    ],
    "wof:name":"Lockheed Martin Msl&Fire Ctr",
    "wof:placetype":"venue"
},
  "geometry": {"coordinates":[-97.110326,32.878133],"type":"Point"}
}