{
  "type": "Feature",
  "properties": {
    "iso:country":"US",
    "sg:address":"11811 Bourgeois Forest Dr",
    "sg:city":"Houston",
    "sg:classifiers":[
        {
            "category":"Professional",
            "type":"Services"
        }
    ],
    "sg:phone":"+1 281 580 2251",
    "sg:postcode":"77066",
    "sg:province":"TX",
    "wof:name":"Bourgeois Forest Homeowne",
    "wof:placetype":"venue"
},
  "geometry": {"coordinates":[-95.51091599999999,29.960529],"type":"Point"}
}