{
  "type": "Feature",
  "properties": {
    "iso:country":"US",
    "sg:address":"1910 Broadway St",
    "sg:city":"Houston",
    "sg:classifiers":[
        {
            "category":"Food & Beverages",
            "subcategory":"Groceries & Convenience Stores",
            "type":"Retail Goods"
        }
    ],
    "sg:phone":"+1 713 645 8149",
    "sg:postcode":"77012",
    "sg:province":"TX",
    "wof:name":"Sellers Bros Convenience Stores",
    "wof:placetype":"venue"
},
  "geometry": {"coordinates":[-95.27800000000001,29.709499],"type":"Point"}
}