{
  "type": "Feature",
  "properties": {
    "iso:country":"US",
    "sg:address":"8710 Greenwood Trl",
    "sg:city":"Rowlett",
    "sg:classifiers":[
        {
            "category":"Manufacturing",
            "subcategory":"Toys & Sporting Goods",
            "type":"Manufacturing & Wholesale Goods"
        }
    ],
    "sg:phone":"+1 972 978 0522",
    "sg:postcode":"75088",
    "sg:province":"TX",
    "sg:tags":[
        "mfg"
    ],
    "wof:name":"Gail Forcewater Sports LLC",
    "wof:placetype":"venue"
},
  "geometry": {"coordinates":[-96.51691599999999,32.901303],"type":"Point"}
}