{
  "type": "Feature",
  "properties": {
    "iso:country":"US",
    "sg:address":"929 Myrtle Creek Dr",
    "sg:city":"La Porte",
    "sg:classifiers":[
        {
            "category":"Shopping",
            "subcategory":"Hobbies, Toys, & Games",
            "type":"Retail Goods"
        }
    ],
    "sg:phone":"+1 281 471 1441",
    "sg:postcode":"77571",
    "sg:province":"TX",
    "wof:name":"Prosise",
    "wof:placetype":"venue"
},
  "geometry": {"coordinates":[-95.085633,29.671228],"type":"Point"}
}