{
  "type": "Feature",
  "properties": {
    "iso:country":"US",
    "sg:address":"9806 Lum Ln",
    "sg:city":"Houston",
    "sg:classifiers":[
        {
            "category":"Social Services",
            "subcategory":"Child Care",
            "type":"Services"
        }
    ],
    "sg:phone":"+1 713 635 3882",
    "sg:postcode":"77078",
    "sg:province":"TX",
    "wof:name":"Green Daycare",
    "wof:placetype":"venue"
},
  "geometry": {"coordinates":[-95.257043,29.85437],"type":"Point"}
}