{
  "type": "Feature",
  "properties": {
    "iso:country":"US",
    "sg:address":"15330 Lyndon B Johnson Fwy Ste 208",
    "sg:city":"Mesquite",
    "sg:classifiers":[
        {
            "category":"Shopping",
            "subcategory":"Computers & Home Electronics",
            "type":"Retail Goods"
        }
    ],
    "sg:phone":"+1 972 613 9443",
    "sg:postcode":"75150",
    "sg:province":"TX",
    "wof:name":"Elite Integrated Solutions Inc",
    "wof:placetype":"venue"
},
  "geometry": {"coordinates":[-96.632357,32.842863],"type":"Point"}
}