{
  "type": "Feature",
  "properties": {
    "iso:country":"US",
    "sg:address":"9216 Clover Valley Dr",
    "sg:city":"Dallas",
    "sg:classifiers":[
        {
            "category":"Wholesale",
            "subcategory":"Medical Equipment & Supplies",
            "type":"Manufacturing & Wholesale Goods"
        }
    ],
    "sg:phone":"+1 214 553 1032",
    "sg:postcode":"75243",
    "sg:province":"TX",
    "wof:name":"Laboratory Design & Supply",
    "wof:placetype":"venue"
},
  "geometry": {"coordinates":[-96.73895,32.905175],"type":"Point"}
}