{
  "type": "Feature",
  "properties": {
    "iso:country":"US",
    "sg:address":"1416 Monterrey Ave",
    "sg:city":"Laredo",
    "sg:classifiers":[
        {
            "category":"Manufacturing",
            "subcategory":"Glass & Minerals",
            "type":"Manufacturing & Wholesale Goods"
        }
    ],
    "sg:phone":"+1 956 723 9255",
    "sg:postcode":"78040",
    "sg:province":"TX",
    "sg:tags":[
        "cut",
        "mfg"
    ],
    "wof:name":"Laredo Stone Supply",
    "wof:placetype":"venue"
},
  "geometry": {"coordinates":[-99.496014,27.509206],"type":"Point"}
}