{
  "type": "Feature",
  "properties": {
    "iso:country":"US",
    "sg:address":"8032 Winsford",
    "sg:city":"San Antonio",
    "sg:classifiers":[
        {
            "category":"Professional",
            "subcategory":"Business Services",
            "type":"Services"
        }
    ],
    "sg:phone":"+1 210 946 8477",
    "sg:postcode":"78239",
    "sg:province":"TX",
    "wof:name":"Creative Equations",
    "wof:placetype":"venue"
},
  "geometry": {"coordinates":[-98.350684,29.509283],"type":"Point"}
}