{
  "type": "Feature",
  "properties": {
    "iso:country":"US",
    "sg:address":"209 Cedar Springs Ct",
    "sg:city":"Weatherford",
    "sg:classifiers":[
        {
            "category":"Building & Trades",
            "subcategory":"Cleaning & Sanitation",
            "type":"Services"
        }
    ],
    "sg:phone":"+1 817 851 6283",
    "sg:postcode":"76087",
    "sg:province":"TX",
    "sg:tags":[
        "duct",
        "air"
    ],
    "wof:name":"Total Home Solutions",
    "wof:placetype":"venue"
},
  "geometry": {"coordinates":[-97.797748,32.701739],"type":"Point"}
}