{
  "type": "Feature",
  "properties": {
    "iso:country":"US",
    "sg:address":"1740 E Expy 83",
    "sg:city":"Mercedes",
    "sg:classifiers":[
        {
            "category":"Shopping",
            "subcategory":"Shoes",
            "type":"Retail Goods"
        }
    ],
    "sg:phone":"+1 956 565 2634",
    "sg:postcode":"78570",
    "sg:province":"TX",
    "sg:tags":[
        "boot"
    ],
    "sg:website":"www.riosofmercedesboots.com",
    "wof:name":"Rios Of Mercedes",
    "wof:placetype":"venue"
},
  "geometry": {"coordinates":[-97.90228500000001,26.159338],"type":"Point"}
}