{
  "type": "Feature",
  "properties": {
    "iso:country":"US",
    "sg:address":"5300 Apache Creek Cove",
    "sg:city":"Austin",
    "sg:classifiers":[
        {
            "category":"Education",
            "subcategory":"Library",
            "type":"Public Place"
        }
    ],
    "sg:phone":"+1 512 899 9480",
    "sg:postcode":"78735",
    "sg:province":"TX",
    "wof:name":"Library 3 LLC",
    "wof:placetype":"venue"
},
  "geometry": {"coordinates":[-97.84082600000001,30.248013],"type":"Point"}
}