{
  "type": "Feature",
  "properties": {
    "iso:country":"US",
    "sg:address":"4109 Todd Lane Suite 200",
    "sg:city":"Austin",
    "sg:classifiers":[
        {
            "category":"Health Services",
            "subcategory":"Clinic",
            "type":"Services"
        },
        {
            "category":"Shopping",
            "type":"Retail Goods"
        }
    ],
    "sg:phone":"+1 512 326 9898",
    "sg:postcode":"78744",
    "sg:province":"TX",
    "sg:tags":[
        "medical"
    ],
    "sg:website":"www.providacare.com",
    "wof:name":"ProvidaCare Medical Supply",
    "wof:placetype":"venue"
},
  "geometry": {"coordinates":[-97.737331,30.210602],"type":"Point"}
}