{
  "type": "Feature",
  "properties": {
    "iso:country":"US",
    "sg:address":"1481 S Polk St",
    "sg:city":"Dallas",
    "sg:classifiers":[
        {
            "category":"Shopping",
            "subcategory":"Shoes",
            "type":"Retail Goods"
        }
    ],
    "sg:phone":"+1 214 371 1995",
    "sg:postcode":"75224",
    "sg:province":"TX",
    "wof:name":"Payless Shoe Source",
    "wof:placetype":"venue"
},
  "geometry": {"coordinates":[-96.840144,32.731804],"type":"Point"}
}