{
  "type": "Feature",
  "properties": {
    "iso:country":"US",
    "sg:address":"444 Executive Center Blvd",
    "sg:city":"El Paso",
    "sg:classifiers":[
        {
            "category":"Real Estate",
            "subcategory":"Architect",
            "type":"Services"
        }
    ],
    "sg:phone":"+1 915 544 0040",
    "sg:postcode":"79902",
    "sg:province":"TX",
    "sg:tags":[
        "architectural"
    ],
    "wof:name":"Synthesis Architecture Inc",
    "wof:placetype":"venue"
},
  "geometry": {"coordinates":[-106.515817,31.795348],"type":"Point"}
}