{
  "type": "Feature",
  "properties": {
    "iso:country":"US",
    "sg:address":"3308 Rosefinch Trl",
    "sg:city":"Austin",
    "sg:classifiers":[
        {
            "category":"Retail",
            "subcategory":"Laundry & Dry Cleaning",
            "type":"Services"
        }
    ],
    "sg:phone":"+1 512 328 3957",
    "sg:postcode":"78746",
    "sg:province":"TX",
    "sg:tags":[
        "drycleaning",
        "plant"
    ],
    "wof:name":"Wells Branch Cleaners Inc",
    "wof:placetype":"venue"
},
  "geometry": {"coordinates":[-97.805527,30.273481],"type":"Point"}
}