{
  "type": "Feature",
  "properties": {
    "iso:country":"US",
    "sg:address":"7006 Wesley St",
    "sg:city":"Greenville",
    "sg:classifiers":[
        {
            "category":"Restaurant",
            "type":"Food & Drink"
        }
    ],
    "sg:menulink":"http://www.allmenus.com/tx/greenville/35874-ihop/menu/",
    "sg:phone":"+1 903 454 1135",
    "sg:postcode":"75402",
    "sg:province":"TX",
    "sg:tags":[
        "sandwich",
        "salad",
        "burger",
        "soup",
        "american",
        "steakhouse",
        "wrap"
    ],
    "wof:name":"IHOP",
    "wof:placetype":"venue"
},
  "geometry": {"coordinates":[-96.10983400000001,33.098535],"type":"Point"}
}