{
  "type": "Feature",
  "properties": {
    "iso:country":"US",
    "sg:address":"10747 Black Walnut Dr",
    "sg:city":"Dallas",
    "sg:classifiers":[
        {
            "category":"Social Services",
            "subcategory":"Child Care",
            "type":"Services"
        }
    ],
    "sg:phone":"+1 972 234 3057",
    "sg:postcode":"75243",
    "sg:province":"TX",
    "sg:tags":[
        "day"
    ],
    "wof:name":"Breckinridge Trails Day Camp",
    "wof:placetype":"venue"
},
  "geometry": {"coordinates":[-96.709148,32.914295],"type":"Point"}
}