{
  "type": "Feature",
  "properties": {
    "iso:country":"US",
    "sg:address":"2125 Goodrich Ave",
    "sg:city":"Austin",
    "sg:classifiers":[
        {
            "category":"Wholesale",
            "subcategory":"Machinery & Supplies",
            "type":"Manufacturing & Wholesale Goods"
        },
        {
            "category":"Wholesale",
            "subcategory":"Auto Parts",
            "type":"Manufacturing & Wholesale Goods"
        }
    ],
    "sg:phone":"+1 512 447 0165",
    "sg:postcode":"78704",
    "sg:province":"TX",
    "sg:tags":[
        "body",
        "equipment",
        "painting",
        "shop",
        "automobile"
    ],
    "wof:name":"E A H Spray Equipment",
    "wof:placetype":"venue"
},
  "geometry": {"coordinates":[-97.773433,30.248511],"type":"Point"}
}