{
  "type": "Feature",
  "properties": {
    "iso:country":"US",
    "sg:address":"17419 Heartwind Ct",
    "sg:city":"Houston",
    "sg:classifiers":[
        {
            "category":"Shopping",
            "subcategory":"Clothing, Apparel, & Fashions",
            "type":"Retail Goods"
        }
    ],
    "sg:phone":"+1 713 304 0880",
    "sg:postcode":"77095",
    "sg:province":"TX",
    "sg:tags":[
        "family"
    ],
    "wof:name":"Melvia",
    "wof:placetype":"venue"
},
  "geometry": {"coordinates":[-95.680575,29.930467],"type":"Point"}
}