{
  "type": "Feature",
  "properties": {
    "iso:country":"US",
    "sg:address":"401 N 5th St",
    "sg:city":"Carrizo Springs",
    "sg:classifiers":[
        {
            "category":"Government",
            "subcategory":"Post Office",
            "type":"Public Place"
        }
    ],
    "sg:phone":"+1 830 876 2612",
    "sg:postcode":"78834",
    "sg:province":"TX",
    "wof:name":"US Post Office",
    "wof:placetype":"venue"
},
  "geometry": {"coordinates":[-99.85960900000001,28.523939],"type":"Point"}
}