{
  "type": "Feature",
  "properties": {
    "iso:country":"US",
    "sg:address":"408 13th St",
    "sg:city":"Bridgeport",
    "sg:classifiers":[
        {
            "category":"Professional",
            "subcategory":"Advertising",
            "type":"Services"
        }
    ],
    "sg:phone":"+1 940 683 2158",
    "sg:postcode":"76426",
    "sg:province":"TX",
    "sg:tags":[
        "distribution"
    ],
    "wof:name":"Lynco Control Inc",
    "wof:placetype":"venue"
},
  "geometry": {"coordinates":[-97.75451200000001,33.203107],"type":"Point"}
}