{
  "type": "Feature",
  "properties": {
    "iso:country":"US",
    "sg:address":"3307 Oak Springs Dr",
    "sg:city":"Austin",
    "sg:classifiers":[
        {
            "category":"Personal",
            "subcategory":"Beauty Salon",
            "type":"Services"
        }
    ],
    "sg:phone":"+1 512 928 4179",
    "sg:postcode":"78721",
    "sg:province":"TX",
    "sg:tags":[
        "shop"
    ],
    "wof:name":"Pineda's Beauty Salon",
    "wof:placetype":"venue"
},
  "geometry": {"coordinates":[-97.694833,30.273747],"type":"Point"}
}