{
  "type": "Feature",
  "properties": {
    "iso:country":"US",
    "sg:address":"3505 I- 35 Svc Rd N",
    "sg:city":"Austin",
    "sg:classifiers":[
        {
            "category":"Professional",
            "type":"Services"
        }
    ],
    "sg:phone":"+1 512 542 9860",
    "sg:postcode":"78722",
    "sg:province":"TX",
    "sg:tags":[
        "caterer"
    ],
    "wof:name":"Go Go Gourmet",
    "wof:placetype":"venue"
},
  "geometry": {"coordinates":[-97.72166199999999,30.290805],"type":"Point"}
}