{
  "type": "Feature",
  "properties": {
    "iso:country":"US",
    "sg:address":"1108 Masters Way",
    "sg:city":"Humble",
    "sg:classifiers":[
        {
            "category":"Building & Trades",
            "subcategory":"Construction",
            "type":"Services"
        }
    ],
    "sg:phone":"+1 281 359 1982",
    "sg:postcode":"77339",
    "sg:province":"TX",
    "sg:tags":[
        "hanging",
        "contractor"
    ],
    "wof:name":"Insideout Painting",
    "wof:placetype":"venue"
},
  "geometry": {"coordinates":[-95.236553,30.045021],"type":"Point"}
}