{
  "type": "Feature",
  "properties": {
    "iso:country":"US",
    "sg:address":"501 N Plano Rd",
    "sg:city":"Garland",
    "sg:classifiers":[
        {
            "category":"Fast Food",
            "type":"Food & Drink"
        },
        {
            "category":"Restaurant",
            "type":"Food & Drink"
        }
    ],
    "sg:phone":"+1 972 272 5839",
    "sg:postcode":"75042",
    "sg:province":"TX",
    "sg:tags":[
        "mexican"
    ],
    "sg:website":"www.tacobell.com",
    "wof:name":"Taco Bell",
    "wof:placetype":"venue"
},
  "geometry": {"coordinates":[-96.700543,32.916641],"type":"Point"}
}