{
  "type": "Feature",
  "properties": {
    "iso:country":"US",
    "sg:address":"1000 Burnett St",
    "sg:city":"Wichita Falls",
    "sg:classifiers":[
        {
            "category":"Government",
            "subcategory":"Office",
            "type":"Public Place"
        }
    ],
    "sg:phone":"+1 940 322 5215",
    "sg:postcode":"76301",
    "sg:province":"TX",
    "sg:tags":[
        "federal",
        "human"
    ],
    "wof:name":"US Social Security Adm",
    "wof:placetype":"venue"
},
  "geometry": {"coordinates":[-98.49408,33.906459],"type":"Point"}
}