{
  "type": "Feature",
  "properties": {
    "iso:country":"US",
    "sg:address":"3924 Innisbrook Dr N",
    "sg:city":"Irving",
    "sg:classifiers":[
        {
            "category":"Professional",
            "subcategory":"Management & Consulting",
            "type":"Services"
        }
    ],
    "sg:phone":"+1 972 256 8093",
    "sg:postcode":"75038",
    "sg:province":"TX",
    "wof:name":"H & M Services",
    "wof:placetype":"venue"
},
  "geometry": {"coordinates":[-96.997355,32.875816],"type":"Point"}
}