{
  "type": "Feature",
  "properties": {
    "iso:country":"US",
    "sg:address":"7200 Long Dr",
    "sg:city":"Houston",
    "sg:classifiers":[
        {
            "category":"Manufacturing",
            "subcategory":"Lumber",
            "type":"Manufacturing & Wholesale Goods"
        }
    ],
    "sg:phone":"+1 713 644 3393",
    "sg:postcode":"77087",
    "sg:province":"TX",
    "sg:tags":[
        "logging"
    ],
    "wof:name":"Stumpster Co",
    "wof:placetype":"venue"
},
  "geometry": {"coordinates":[-95.29868500000001,29.685193],"type":"Point"}
}