{
  "type": "Feature",
  "properties": {
    "iso:country":"US",
    "sg:address":"10700 Telge Rd",
    "sg:city":"Houston",
    "sg:classifiers":[
        {
            "category":"Retail",
            "subcategory":"Auto Repair",
            "type":"Services"
        }
    ],
    "sg:phone":"+1 281 345 9575",
    "sg:postcode":"77095",
    "sg:province":"TX",
    "sg:tags":[
        "transmission"
    ],
    "wof:name":"Ryder",
    "wof:placetype":"venue"
},
  "geometry": {"coordinates":[-95.648179,29.931358],"type":"Point"}
}