{
  "type": "Feature",
  "properties": {
    "iso:country":"US",
    "sg:address":"2300 W Morton St",
    "sg:city":"Denison",
    "sg:classifiers":[
        {
            "category":"Manufacturing",
            "subcategory":"Petroleum Products",
            "type":"Manufacturing & Wholesale Goods"
        }
    ],
    "sg:phone":"+1 903 463 1561",
    "sg:postcode":"75020",
    "sg:province":"TX",
    "sg:tags":[
        "refiner"
    ],
    "wof:name":"J & V Mart",
    "wof:placetype":"venue"
},
  "geometry": {"coordinates":[-96.57013999999999,33.760632],"type":"Point"}
}