{
  "type": "Feature",
  "properties": {
    "iso:country":"US",
    "sg:address":"1211 Northwest Blvd",
    "sg:city":"Georgetown",
    "sg:classifiers":[
        {
            "category":"Freight",
            "type":"Transportation"
        }
    ],
    "sg:phone":"+1 512 863 2241",
    "sg:postcode":"78628",
    "sg:province":"TX",
    "wof:name":"Northwest Storage",
    "wof:placetype":"venue"
},
  "geometry": {"coordinates":[-97.676046,30.656182],"type":"Point"}
}