{
  "type": "Feature",
  "properties": {
    "iso:country":"US",
    "sg:address":"10 Sierra Camino",
    "sg:city":"Ballinger",
    "sg:classifiers":[
        {
            "category":"Building & Trades",
            "subcategory":"Plumbing",
            "type":"Services"
        }
    ],
    "sg:phone":"+1 325 365 5234",
    "sg:postcode":"76821",
    "sg:province":"TX",
    "sg:tags":[
        "contractor"
    ],
    "wof:name":"Jones Plumbing",
    "wof:placetype":"venue"
},
  "geometry": {"coordinates":[-99.971327,31.750121],"type":"Point"}
}