{
  "type": "Feature",
  "properties": {
    "iso:country":"US",
    "sg:address":"14642 Lourdes Dr",
    "sg:city":"Houston",
    "sg:classifiers":[
        {
            "category":"Food & Beverages",
            "subcategory":"Meat & Fish",
            "type":"Retail Goods"
        }
    ],
    "sg:phone":"+1 713 524 3850",
    "sg:postcode":"77049",
    "sg:province":"TX",
    "wof:name":"Que Hwong Meat",
    "wof:placetype":"venue"
},
  "geometry": {"coordinates":[-95.187926,29.81119],"type":"Point"}
}