{
  "type": "Feature",
  "properties": {
    "iso:country":"US",
    "sg:address":"5704 Danmire Ct",
    "sg:city":"Plano",
    "sg:classifiers":[
        {
            "category":"Professional",
            "subcategory":"Business Services",
            "type":"Services"
        }
    ],
    "sg:phone":"+1 972 732 9088",
    "sg:postcode":"75093",
    "sg:province":"TX",
    "wof:name":"Syad Partners Inc",
    "wof:placetype":"venue"
},
  "geometry": {"coordinates":[-96.818201,33.020368],"type":"Point"}
}