{
  "type": "Feature",
  "properties": {
    "iso:country":"US",
    "sg:address":"110 Champions Dr",
    "sg:city":"Lufkin",
    "sg:classifiers":[
        {
            "category":"Home & Garden",
            "subcategory":"Garden Supply",
            "type":"Retail Goods"
        }
    ],
    "sg:phone":"+1 936 639 3163",
    "sg:postcode":"75901",
    "sg:province":"TX",
    "wof:name":"Historical Soils",
    "wof:placetype":"venue"
},
  "geometry": {"coordinates":[-94.729761,31.287279],"type":"Point"}
}