{
  "type": "Feature",
  "properties": {
    "iso:country":"US",
    "sg:address":"5800 Granite Pkwy",
    "sg:city":"Plano",
    "sg:classifiers":[
        {
            "category":"Real Estate",
            "subcategory":"Real Estate Agent",
            "type":"Services"
        },
        {
            "category":"Professional",
            "subcategory":"Business Services",
            "type":"Services"
        }
    ],
    "sg:phone":"+1 972 963 5141",
    "sg:postcode":"75024",
    "sg:province":"TX",
    "sg:tags":[
        "relocation"
    ],
    "sg:website":"www.primacy.com",
    "wof:name":"Primacy Relocation LLC",
    "wof:placetype":"venue"
},
  "geometry": {"coordinates":[-96.817476,33.087017],"type":"Point"}
}