{
  "type": "Feature",
  "properties": {
    "iso:country":"US",
    "sg:address":"444 W Elizabeth St",
    "sg:city":"Brownsville",
    "sg:classifiers":[
        {
            "category":"Food & Beverages",
            "subcategory":"Bakery",
            "type":"Retail Goods"
        }
    ],
    "sg:phone":"+1 956 542 4055",
    "sg:postcode":"78520",
    "sg:province":"TX",
    "sg:tags":[
        "baker"
    ],
    "sg:website":"www.lindascakes.com",
    "wof:name":"Linda's Cake Specialty Shop",
    "wof:placetype":"venue"
},
  "geometry": {"coordinates":[-97.51012299999999,25.912293],"type":"Point"}
}