{
  "type": "Feature",
  "properties": {
    "iso:country":"US",
    "sg:address":"9205 Kempler Dr",
    "sg:city":"Austin",
    "sg:classifiers":[
        {
            "category":"Professional",
            "type":"Services"
        }
    ],
    "sg:phone":"+1 512 292 4566",
    "sg:postcode":"78748",
    "sg:province":"TX",
    "wof:name":"Morin Liquidators",
    "wof:placetype":"venue"
},
  "geometry": {"coordinates":[-97.821607,30.180154],"type":"Point"}
}