{
  "type": "Feature",
  "properties": {
    "iso:country":"US",
    "sg:address":"4502 FM 1960 W",
    "sg:city":"Houston",
    "sg:classifiers":[
        {
            "category":"Autos & Motor Vehicles",
            "subcategory":"Fuel & Gas Station",
            "type":"Retail Goods"
        }
    ],
    "sg:phone":"+1 281 587 0795",
    "sg:postcode":"77069",
    "sg:province":"TX",
    "sg:tags":[
        "oil"
    ],
    "wof:name":"Chevron Food Mart",
    "wof:placetype":"venue"
},
  "geometry": {"coordinates":[-95.49845999999999,29.987882],"type":"Point"}
}