{
  "type": "Feature",
  "properties": {
    "iso:country":"US",
    "sg:address":"1601 Cancun Dr",
    "sg:city":"Mansfield",
    "sg:classifiers":[
        {
            "category":"Building & Trades",
            "subcategory":"Electrical",
            "type":"Services"
        }
    ],
    "sg:phone":"+1 817 473 3489",
    "sg:postcode":"76063",
    "sg:province":"TX",
    "sg:tags":[
        "electrical",
        "contractor"
    ],
    "wof:name":"Lasso Electric",
    "wof:placetype":"venue"
},
  "geometry": {"coordinates":[-97.172372,32.586764],"type":"Point"}
}