{
  "type": "Feature",
  "properties": {
    "iso:country":"US",
    "sg:address":"6720 Bertner St",
    "sg:city":"Houston",
    "sg:classifiers":[
        {
            "category":"Manufacturing",
            "subcategory":"Printing",
            "type":"Manufacturing & Wholesale Goods"
        }
    ],
    "sg:phone":"+1 713 794 6585",
    "sg:postcode":"77030",
    "sg:province":"TX",
    "sg:tags":[
        "periodical"
    ],
    "wof:name":"Circulation Journal",
    "wof:placetype":"venue"
},
  "geometry": {"coordinates":[-95.39917199999999,29.707139],"type":"Point"}
}