{
  "type": "Feature",
  "properties": {
    "iso:country":"US",
    "sg:address":"11107 Tupper Lake Dr",
    "sg:city":"Houston",
    "sg:classifiers":[
        {
            "category":"Professional",
            "type":"Services"
        }
    ],
    "sg:phone":"+1 713 978 6805",
    "sg:postcode":"77042",
    "sg:province":"TX",
    "wof:name":"Fossil Oil & Gas LLC",
    "wof:placetype":"venue"
},
  "geometry": {"coordinates":[-95.572934,29.75572],"type":"Point"}
}