{
  "type": "Feature",
  "properties": {
    "iso:country":"US",
    "sg:address":"12 Wade Trl",
    "sg:city":"Texarkana",
    "sg:classifiers":[
        {
            "category":"Professional",
            "subcategory":"Business Services",
            "type":"Services"
        }
    ],
    "sg:phone":"+1 870 773 5948",
    "sg:postcode":"71854",
    "sg:province":"TX",
    "wof:name":"Family Motor Coach Assoc",
    "wof:placetype":"venue"
},
  "geometry": {"coordinates":[-94.01725999999999,33.455808],"type":"Point"}
}