{
  "type": "Feature",
  "properties": {
    "iso:country":"US",
    "sg:address":"3705 North St",
    "sg:city":"Nacogdoches",
    "sg:classifiers":[
        {
            "category":"Government",
            "subcategory":"Office",
            "type":"Public Place"
        }
    ],
    "sg:phone":"+1 936 564 1000",
    "sg:postcode":"75965",
    "sg:province":"TX",
    "sg:tags":[
        "armed",
        "force",
        "recruiting"
    ],
    "wof:name":"US Army Recruiting",
    "wof:placetype":"venue"
},
  "geometry": {"coordinates":[-94.653819,31.639247],"type":"Point"}
}