{
  "type": "Feature",
  "properties": {
    "iso:country":"US",
    "sg:address":"5100 E End Blvd S",
    "sg:city":"Marshall",
    "sg:classifiers":[
        {
            "category":"Travel",
            "subcategory":"Hotels & Motels",
            "type":"Entertainment"
        }
    ],
    "sg:phone":"+1 903 927 0079",
    "sg:postcode":"75672",
    "sg:province":"TX",
    "sg:tags":[
        "operation"
    ],
    "wof:name":"Hilton",
    "wof:placetype":"venue"
},
  "geometry": {"coordinates":[-94.35786299999999,32.495998],"type":"Point"}
}