{
  "type": "Feature",
  "properties": {
    "iso:country":"US",
    "sg:address":"6615 Airport Blvd",
    "sg:city":"Austin",
    "sg:classifiers":[
        {
            "category":"Shopping",
            "subcategory":"Clothing, Apparel, & Fashions",
            "type":"Retail Goods"
        }
    ],
    "sg:phone":"+1 512 450 1514",
    "sg:postcode":"78752",
    "sg:province":"TX",
    "wof:name":"Primo Tailors Of Austin",
    "wof:placetype":"venue"
},
  "geometry": {"coordinates":[-97.715519,30.330595],"type":"Point"}
}