{
  "type": "Feature",
  "properties": {
    "iso:country":"US",
    "sg:address":"3317 Finley Rd",
    "sg:city":"Irving",
    "sg:phone":"+1 972 871 2979",
    "sg:postcode":"75062",
    "sg:province":"TX",
    "wof:name":"Allstate Insurance Company - John Moore",
    "wof:placetype":"venue"
},
  "geometry": {"coordinates":[-96.991362,32.850866],"type":"Point"}
}