{
  "type": "Feature",
  "properties": {
    "iso:country":"US",
    "sg:address":"101 Altamesa Blvd",
    "sg:city":"Fort Worth",
    "sg:classifiers":[
        {
            "category":"Food & Beverages",
            "subcategory":"Groceries & Convenience Stores",
            "type":"Retail Goods"
        }
    ],
    "sg:phone":"+1 817 293 6643",
    "sg:postcode":"76134",
    "sg:province":"TX",
    "wof:name":"Quickway",
    "wof:placetype":"venue"
},
  "geometry": {"coordinates":[-97.322019,32.653338],"type":"Point"}
}