{
  "type": "Feature",
  "properties": {
    "iso:country":"US",
    "sg:address":"10048 Dyer St",
    "sg:city":"El Paso",
    "sg:classifiers":[
        {
            "category":"Restaurant",
            "type":"Food & Drink"
        }
    ],
    "sg:menulink":"http://www.allmenus.com/tx/el-paso/94286-dominos-pizza/menu/",
    "sg:phone":"+1 915 757 3433",
    "sg:postcode":"79924",
    "sg:province":"TX",
    "sg:tags":[
        "american",
        "wing",
        "pizza"
    ],
    "wof:name":"Domino's Pizza",
    "wof:placetype":"venue"
},
  "geometry": {"coordinates":[-106.407211,31.901116],"type":"Point"}
}