{
  "type": "Feature",
  "properties": {
    "iso:country":"US",
    "sg:address":"4230 McCullough Ave",
    "sg:city":"San Antonio",
    "sg:classifiers":[
        {
            "category":"Restaurant",
            "type":"Food & Drink"
        }
    ],
    "sg:phone":"+1 210 829 8880",
    "sg:postcode":"78212",
    "sg:province":"TX",
    "sg:tags":[
        "eating"
    ],
    "wof:name":"Arian Catering",
    "wof:placetype":"venue"
},
  "geometry": {"coordinates":[-98.491615,29.470116],"type":"Point"}
}