{
  "type": "Feature",
  "properties": {
    "iso:country":"US",
    "sg:address":"1510 Ranch Rd 3014",
    "sg:city":"Tow",
    "sg:classifiers":[
        {
            "category":"Professional",
            "type":"Services"
        }
    ],
    "sg:phone":"+1 325 379 3056",
    "sg:postcode":"78672",
    "sg:province":"TX",
    "sg:tags":[
        "establishment"
    ],
    "wof:name":"Harlin Grocery",
    "wof:placetype":"venue"
},
  "geometry": {"coordinates":[-98.449583,30.861001],"type":"Point"}
}