{
  "type": "Feature",
  "properties": {
    "iso:country":"US",
    "sg:address":"11915 Moss Branch Rd",
    "sg:city":"Houston",
    "sg:classifiers":[
        {
            "category":"Professional",
            "type":"Services"
        }
    ],
    "sg:phone":"+1 713 690 2625",
    "sg:postcode":"77043",
    "sg:province":"TX",
    "wof:name":"Everready Enviromental VA",
    "wof:placetype":"venue"
},
  "geometry": {"coordinates":[-95.570578,29.825401],"type":"Point"}
}