{
  "type": "Feature",
  "properties": {
    "iso:country":"US",
    "sg:address":"2813 Central Fwy",
    "sg:city":"Wichita Falls",
    "sg:classifiers":[
        {
            "category":"Education",
            "subcategory":"Vocational School",
            "type":"Public Place"
        }
    ],
    "sg:phone":"+1 940 766 3369",
    "sg:postcode":"76302",
    "sg:province":"TX",
    "sg:tags":[
        "technical",
        "trade"
    ],
    "sg:website":"www.vernoncollege.edu",
    "wof:name":"VRJC Skills Training Ctr",
    "wof:placetype":"venue"
},
  "geometry": {"coordinates":[-98.43078199999999,33.883224],"type":"Point"}
}