{
  "type": "Feature",
  "properties": {
    "iso:country":"US",
    "sg:address":"1018 Ebony Ave",
    "sg:city":"Mcallen",
    "sg:classifiers":[
        {
            "category":"Building & Trades",
            "subcategory":"Construction",
            "type":"Services"
        }
    ],
    "sg:phone":"+1 956 630 5340",
    "sg:postcode":"78501",
    "sg:province":"TX",
    "sg:tags":[
        "house"
    ],
    "wof:name":"Firestar Construction & Svc",
    "wof:placetype":"venue"
},
  "geometry": {"coordinates":[-98.230254,26.207994],"type":"Point"}
}