{
  "type": "Feature",
  "properties": {
    "iso:country":"US",
    "sg:address":"408 S Pearl St",
    "sg:city":"Belton",
    "sg:classifiers":[
        {
            "category":"Retail",
            "subcategory":"Auto Repair",
            "type":"Services"
        }
    ],
    "sg:phone":"+1 254 939 3109",
    "sg:postcode":"76513",
    "sg:province":"TX",
    "sg:tags":[
        "general"
    ],
    "wof:name":"Johnnys Repair Shop",
    "wof:placetype":"venue"
},
  "geometry": {"coordinates":[-97.46572999999999,31.054257],"type":"Point"}
}