{
  "type": "Feature",
  "properties": {
    "iso:country":"US",
    "sg:address":"1002 Morton League Ct",
    "sg:city":"Richmond",
    "sg:classifiers":[
        {
            "category":"Mining & Drilling",
            "type":"Manufacturing & Wholesale Goods"
        }
    ],
    "sg:phone":"+1 281 342 6849",
    "sg:postcode":"77469",
    "sg:province":"TX",
    "sg:tags":[
        "exploration"
    ],
    "wof:name":"Dwight Mackie",
    "wof:placetype":"venue"
},
  "geometry": {"coordinates":[-95.736728,29.620496],"type":"Point"}
}