{
  "type": "Feature",
  "properties": {
    "iso:country":"US",
    "sg:address":"1002 Santa Barbara St",
    "sg:city":"Victoria",
    "sg:classifiers":[
        {
            "category":"Education",
            "subcategory":"School",
            "type":"Public Place"
        }
    ],
    "sg:phone":"+1 361 788 9553",
    "sg:postcode":"77904",
    "sg:province":"TX",
    "wof:name":"De Leon Elementary School",
    "wof:placetype":"venue"
},
  "geometry": {"coordinates":[-96.96731200000001,28.843426],"type":"Point"}
}