{
  "type": "Feature",
  "properties": {
    "iso:country":"US",
    "sg:address":"307 Inverness Dr",
    "sg:city":"Roanoke",
    "sg:classifiers":[
        {
            "category":"Manufacturing",
            "subcategory":"Chemicals & Compounds",
            "type":"Manufacturing & Wholesale Goods"
        }
    ],
    "sg:phone":"+1 817 430 1569",
    "sg:postcode":"76262",
    "sg:province":"TX",
    "wof:name":"Simplot Partners Inc",
    "wof:placetype":"venue"
},
  "geometry": {"coordinates":[-97.173885,32.991894],"type":"Point"}
}