{
  "type": "Feature",
  "properties": {
    "iso:country":"US",
    "sg:address":"201 N Hampton Rd",
    "sg:city":"Crowley",
    "sg:classifiers":[
        {
            "category":"Real Estate",
            "subcategory":"Real Estate Operator",
            "type":"Services"
        }
    ],
    "sg:phone":"+1 817 297 2406",
    "sg:postcode":"76036",
    "sg:province":"TX",
    "sg:tags":[
        "apartment"
    ],
    "wof:name":"Summer Square Apts",
    "wof:placetype":"venue"
},
  "geometry": {"coordinates":[-97.35769999999999,32.580546],"type":"Point"}
}