{
  "type": "Feature",
  "properties": {
    "iso:country":"US",
    "sg:address":"908 Avenue A",
    "sg:city":"Sweeny",
    "sg:classifiers":[
        {
            "category":"Farming",
            "subcategory":"Farm",
            "type":"Manufacturing & Wholesale Goods"
        }
    ],
    "sg:phone":"+1 979 548 6384",
    "sg:postcode":"77480",
    "sg:province":"TX",
    "wof:name":"James E White",
    "wof:placetype":"venue"
},
  "geometry": {"coordinates":[-95.691472,29.042746],"type":"Point"}
}