{
  "type": "Feature",
  "properties": {
    "iso:country":"US",
    "sg:address":"3604 Briarcliff Dr",
    "sg:city":"Plano",
    "sg:classifiers":[
        {
            "category":"Professional",
            "subcategory":"Business Services",
            "type":"Services"
        }
    ],
    "sg:phone":"+1 972 208 0706",
    "sg:postcode":"75025",
    "sg:province":"TX",
    "sg:tags":[
        "interior",
        "consultant",
        "design",
        "decorator"
    ],
    "wof:name":"C & R Creative Designs",
    "wof:placetype":"venue"
},
  "geometry": {"coordinates":[-96.76621799999999,33.084426],"type":"Point"}
}