{
  "type": "Feature",
  "properties": {
    "iso:country":"US",
    "sg:address":"771 Airport Blvd",
    "sg:city":"Austin",
    "sg:classifiers":[
        {
            "category":"Autos & Motor Vehicles",
            "subcategory":"Auto Supplies",
            "type":"Retail Goods"
        }
    ],
    "sg:phone":"+1 512 386 9300",
    "sg:postcode":"78702",
    "sg:province":"TX",
    "sg:tags":[
        "tire"
    ],
    "wof:name":"Leal's Tire Shop",
    "wof:placetype":"venue"
},
  "geometry": {"coordinates":[-97.692486,30.254406],"type":"Point"}
}