{
  "type": "Feature",
  "properties": {
    "iso:country":"US",
    "sg:address":"88 Briggs Ave",
    "sg:city":"San Antonio",
    "sg:classifiers":[
        {
            "category":"Health Services",
            "subcategory":"Doctor",
            "type":"Services"
        }
    ],
    "sg:phone":"+1 210 923 7342",
    "sg:postcode":"78224",
    "sg:province":"TX",
    "sg:tags":[
        "physician",
        "surgeon"
    ],
    "wof:name":"Central Cardiovascular Inst",
    "wof:placetype":"venue"
},
  "geometry": {"coordinates":[-98.547158,29.354931],"type":"Point"}
}