{
  "type": "Feature",
  "properties": {
    "iso:country":"US",
    "sg:address":"401 Coke Ave",
    "sg:city":"Hillsboro",
    "sg:classifiers":[
        {
            "category":"Wholesale",
            "subcategory":"Electrical",
            "type":"Manufacturing & Wholesale Goods"
        }
    ],
    "sg:phone":"+1 254 580 2561",
    "sg:postcode":"76645",
    "sg:province":"TX",
    "sg:tags":[
        "electronic"
    ],
    "wof:name":"Alltel",
    "wof:placetype":"venue"
},
  "geometry": {"coordinates":[-97.09872,32.007652],"type":"Point"}
}