{
  "type": "Feature",
  "properties": {
    "iso:country":"US",
    "sg:address":"545 W 24th St",
    "sg:city":"Houston",
    "sg:classifiers":[
        {
            "category":"Shopping",
            "subcategory":"Bicycles & Sporting Goods",
            "type":"Retail Goods"
        }
    ],
    "sg:phone":"+1 713 864 4847",
    "sg:postcode":"77008",
    "sg:province":"TX",
    "sg:tags":[
        "bike"
    ],
    "wof:name":"Procycle",
    "wof:placetype":"venue"
},
  "geometry": {"coordinates":[-95.40693400000001,29.808047],"type":"Point"}
}