{
  "type": "Feature",
  "properties": {
    "iso:country":"US",
    "sg:address":"603 W 3rd St",
    "sg:city":"Borger",
    "sg:classifiers":[
        {
            "category":"Insurance",
            "subcategory":"Insurance Agent",
            "type":"Services"
        }
    ],
    "sg:phone":"+1 806 273 7564",
    "sg:postcode":"79007",
    "sg:province":"TX",
    "wof:name":"Les Hargis Insurance",
    "wof:placetype":"venue"
},
  "geometry": {"coordinates":[-101.396574,35.668046],"type":"Point"}
}