{
  "type": "Feature",
  "properties": {
    "iso:country":"US",
    "sg:address":"7444 Meiners Rd",
    "sg:city":"Ledbetter",
    "sg:classifiers":[
        {
            "category":"Professional",
            "subcategory":"Accounting & Tax Preparation",
            "type":"Services"
        }
    ],
    "sg:phone":"+1 979 249 5940",
    "sg:postcode":"78946",
    "sg:province":"TX",
    "sg:tags":[
        "return",
        "filing"
    ],
    "wof:name":"Malak Tax & Financial Svc",
    "wof:placetype":"venue"
},
  "geometry": {"coordinates":[-96.801799,30.044782],"type":"Point"}
}