{
  "type": "Feature",
  "properties": {
    "iso:country":"US",
    "sg:address":"113 E 5th St",
    "sg:city":"Bonham",
    "sg:classifiers":[
        {
            "category":"Professional",
            "subcategory":"Lawyer & Legal Services",
            "type":"Services"
        }
    ],
    "sg:phone":"+1 903 640 4963",
    "sg:postcode":"75418",
    "sg:province":"TX",
    "wof:name":"Steven R Miears Atty",
    "wof:placetype":"venue"
},
  "geometry": {"coordinates":[-96.179097,33.578162],"type":"Point"}
}