{
  "type": "Feature",
  "properties": {
    "iso:country":"US",
    "sg:address":"43 S Creekmist Pl",
    "sg:city":"Conroe",
    "sg:classifiers":[
        {
            "category":"Health Services",
            "subcategory":"Doctor",
            "type":"Services"
        }
    ],
    "sg:phone":"+1 936 273 0347",
    "sg:postcode":"77385",
    "sg:province":"TX",
    "sg:tags":[
        "physician",
        "family",
        "practice",
        "surgeons",
        "medicine"
    ],
    "wof:name":"Chi Hiong U Go Md Pa",
    "wof:placetype":"venue"
},
  "geometry": {"coordinates":[-95.44953700000001,30.218875],"type":"Point"}
}