{
  "type": "Feature",
  "properties": {
    "iso:country":"US",
    "sg:address":"200 W Main St",
    "sg:city":"Arlington",
    "sg:classifiers":[
        {
            "category":"Banks & Credit Unions",
            "subcategory":"Bank",
            "type":"Services"
        }
    ],
    "sg:phone":"+1 817 303 5900",
    "sg:postcode":"76010",
    "sg:province":"TX",
    "wof:name":"Worthington National Bank",
    "wof:placetype":"venue"
},
  "geometry": {"coordinates":[-97.10951799999999,32.736697],"type":"Point"}
}