{
  "type": "Feature",
  "properties": {
    "iso:country":"US",
    "sg:address":"1022 Pheasant Dr",
    "sg:city":"Mesquite",
    "sg:classifiers":[
        {
            "category":"Building & Trades",
            "subcategory":"Landscaping Services",
            "type":"Services"
        }
    ],
    "sg:phone":"+1 972 279 9543",
    "sg:postcode":"75150",
    "sg:province":"TX",
    "wof:name":"Total Lawn Care",
    "wof:placetype":"venue"
},
  "geometry": {"coordinates":[-96.61309799999999,32.801953],"type":"Point"}
}