{
  "type": "Feature",
  "properties": {
    "iso:country":"US",
    "sg:address":"3545 FM 150",
    "sg:city":"Kyle",
    "sg:classifiers":[
        {
            "category":"Manufacturing",
            "subcategory":"Apparel",
            "type":"Manufacturing & Wholesale Goods"
        }
    ],
    "sg:phone":"+1 512 268 0822",
    "sg:postcode":"78640",
    "sg:province":"TX",
    "wof:name":"Creative Threads",
    "wof:placetype":"venue"
},
  "geometry": {"coordinates":[-97.900064,30.019277],"type":"Point"}
}