{
  "type": "Feature",
  "properties": {
    "iso:country":"US",
    "sg:address":"1738 S Jackson St",
    "sg:city":"Jacksonville",
    "sg:classifiers":[
        {
            "category":"Insurance",
            "subcategory":"Insurance Agent",
            "type":"Services"
        }
    ],
    "sg:phone":"+1 903 586 9786",
    "sg:postcode":"75766",
    "sg:province":"TX",
    "wof:name":"State Farm Insurance",
    "wof:placetype":"venue"
},
  "geometry": {"coordinates":[-95.26152500000001,31.949013],"type":"Point"}
}