{
  "type": "Feature",
  "properties": {
    "iso:country":"US",
    "sg:address":"14833 Marsh Ln",
    "sg:city":"Dallas",
    "sg:classifiers":[
        {
            "category":"Banks & Credit Unions",
            "subcategory":"Investment Brokerage",
            "type":"Services"
        }
    ],
    "sg:phone":"+1 469 522 0584",
    "sg:postcode":"75234",
    "sg:province":"TX",
    "wof:name":"C & C Investments",
    "wof:placetype":"venue"
},
  "geometry": {"coordinates":[-96.85588199999999,32.948789],"type":"Point"}
}