{
  "type": "Feature",
  "properties": {
    "iso:country":"US",
    "sg:address":"235 E 3rd St",
    "sg:city":"Hereford",
    "sg:classifiers":[
        {
            "category":"Government",
            "subcategory":"Office",
            "type":"Public Place"
        }
    ],
    "sg:phone":"+1 806 363 7075",
    "sg:postcode":"79045",
    "sg:province":"TX",
    "sg:tags":[
        "county",
        "resource"
    ],
    "wof:name":"Deaf Smith Social Svc Dept",
    "wof:placetype":"venue"
},
  "geometry": {"coordinates":[-102.397481,34.81762],"type":"Point"}
}