{
  "type": "Feature",
  "properties": {
    "iso:country":"US",
    "sg:address":"9900 Rowlett Rd",
    "sg:city":"Houston",
    "sg:classifiers":[
        {
            "category":"Retail",
            "subcategory":"Storage",
            "type":"Services"
        },
        {
            "category":"Manufacturing",
            "subcategory":"Paper Products",
            "type":"Manufacturing & Wholesale Goods"
        }
    ],
    "sg:phone":"+1 713 941 0555",
    "sg:postcode":"77075",
    "sg:province":"TX",
    "sg:tags":[
        "fiber",
        "automobile",
        "household",
        "commercial",
        "boxes-corrugated",
        "self",
        "boat"
    ],
    "sg:website":"http://www.ustoreit.com/?utm_source=yellowpages&utm_medium=premium&utm_campaign=yp2010&phid=0179",
    "wof:name":"U-Store-It",
    "wof:placetype":"venue"
},
  "geometry": {"coordinates":[-95.23400700000001,29.624528],"type":"Point"}
}