{
  "type": "Feature",
  "properties": {
    "iso:country":"US",
    "sg:address":"2221 E Main St",
    "sg:city":"Uvalde",
    "sg:classifiers":[
        {
            "category":"Restaurant",
            "type":"Food & Drink"
        },
        {
            "category":"Bakery",
            "type":"Food & Drink"
        }
    ],
    "sg:menulink":"http://www.allmenus.com/tx/uvalde/100291-golden-corral/menu/",
    "sg:phone":"+1 830 278 3465",
    "sg:postcode":"78801",
    "sg:province":"TX",
    "sg:tags":[
        "american",
        "bakery",
        "pastry"
    ],
    "wof:name":"Golden Corral",
    "wof:placetype":"venue"
},
  "geometry": {"coordinates":[-99.766149,29.219536],"type":"Point"}
}