{
  "type": "Feature",
  "properties": {
    "iso:country":"US",
    "sg:address":"14027 Oak Leaf Ln",
    "sg:city":"Houston",
    "sg:classifiers":[
        {
            "category":"Professional",
            "subcategory":"Research",
            "type":"Services"
        }
    ],
    "sg:phone":"+1 713 453 7808",
    "sg:postcode":"77015",
    "sg:province":"TX",
    "sg:tags":[
        "business"
    ],
    "wof:name":"Dya Enterprises",
    "wof:placetype":"venue"
},
  "geometry": {"coordinates":[-95.174589,29.790265],"type":"Point"}
}