{
  "type": "Feature",
  "properties": {
    "iso:country":"US",
    "sg:address":"2120 Ballycastle Dr",
    "sg:city":"Dallas",
    "sg:classifiers":[
        {
            "category":"Manufacturing",
            "subcategory":"Printing",
            "type":"Manufacturing & Wholesale Goods"
        }
    ],
    "sg:phone":"+1 214 328 5389",
    "sg:postcode":"75228",
    "sg:province":"TX",
    "sg:tags":[
        "publishing"
    ],
    "wof:name":"Ballycastle Publishing",
    "wof:placetype":"venue"
},
  "geometry": {"coordinates":[-96.676401,32.83759],"type":"Point"}
}