{
  "type": "Feature",
  "properties": {
    "iso:country":"US",
    "sg:address":"3580 W Alton Gloor Blvd",
    "sg:city":"Brownsville",
    "sg:classifiers":[
        {
            "category":"Restaurant",
            "type":"Food & Drink"
        }
    ],
    "sg:phone":"+1 956 350 8863",
    "sg:postcode":"78520",
    "sg:province":"TX",
    "sg:tags":[
        "eating"
    ],
    "wof:name":"Whataburger",
    "wof:placetype":"venue"
},
  "geometry": {"coordinates":[-97.538713,25.968286],"type":"Point"}
}