{
  "type": "Feature",
  "properties": {
    "iso:country":"US",
    "sg:address":"705 E Lamar St",
    "sg:city":"Sherman",
    "sg:classifiers":[
        {
            "category":"Building & Trades",
            "subcategory":"Plumbing",
            "type":"Services"
        }
    ],
    "sg:phone":"+1 903 892 2493",
    "sg:postcode":"75090",
    "sg:province":"TX",
    "sg:tags":[
        "plumbing",
        "contractor"
    ],
    "wof:name":"Wence Moravec Plumbing Co",
    "wof:placetype":"venue"
},
  "geometry": {"coordinates":[-96.600234,33.637586],"type":"Point"}
}