{
  "type": "Feature",
  "properties": {
    "iso:country":"US",
    "sg:address":"632 Walnut Cir",
    "sg:city":"Athens",
    "sg:classifiers":[
        {
            "category":"Utilities",
            "subcategory":"Fuel Oil & Lpg",
            "type":"Services"
        }
    ],
    "sg:phone":"+1 903 677 3137",
    "sg:postcode":"75751",
    "sg:province":"TX",
    "sg:tags":[
        "liquefied",
        "gas",
        "petroleum"
    ],
    "wof:name":"R&L Propane Services",
    "wof:placetype":"venue"
},
  "geometry": {"coordinates":[-95.86475299999999,32.200235],"type":"Point"}
}