{
  "type": "Feature",
  "properties": {
    "iso:country":"US",
    "sg:address":"3720 W Alabama St",
    "sg:city":"Houston",
    "sg:classifiers":[
        {
            "category":"Professional",
            "subcategory":"Business Services",
            "type":"Services"
        }
    ],
    "sg:phone":"+1 713 622 6487",
    "sg:postcode":"77027",
    "sg:province":"TX",
    "wof:name":"Muneer Sheema",
    "wof:placetype":"venue"
},
  "geometry": {"coordinates":[-95.436964,29.738335],"type":"Point"}
}