{
  "type": "Feature",
  "properties": {
    "iso:country":"US",
    "sg:address":"5725 Tucker St",
    "sg:city":"Houston",
    "sg:classifiers":[
        {
            "category":"Professional",
            "subcategory":"Computer Services",
            "type":"Services"
        }
    ],
    "sg:phone":"+1 713 641 6158",
    "sg:postcode":"77087",
    "sg:province":"TX",
    "sg:tags":[
        "equipment",
        "sales",
        "repair"
    ],
    "wof:name":"Data Plus Inc",
    "wof:placetype":"venue"
},
  "geometry": {"coordinates":[-95.30787100000001,29.681349],"type":"Point"}
}