{
  "type": "Feature",
  "properties": {
    "iso:country":"US",
    "sg:address":"701 N 1st St",
    "sg:city":"Harlingen",
    "sg:classifiers":[
        {
            "category":"Utilities",
            "subcategory":"Mobile Phone",
            "type":"Services"
        }
    ],
    "sg:phone":"+1 956 412 1255",
    "sg:postcode":"78550",
    "sg:province":"TX",
    "sg:tags":[
        "telephone",
        "cellular"
    ],
    "wof:name":"Map Wireless Inc",
    "wof:placetype":"venue"
},
  "geometry": {"coordinates":[-97.69564099999999,26.200654],"type":"Point"}
}