{
  "type": "Feature",
  "properties": {
    "iso:country":"US",
    "sg:address":"8725 Meadowcroft Dr",
    "sg:city":"Houston",
    "sg:classifiers":[
        {
            "category":"Wholesale",
            "subcategory":"Scrap",
            "type":"Manufacturing & Wholesale Goods"
        }
    ],
    "sg:phone":"+1 713 782 7274",
    "sg:postcode":"77063",
    "sg:province":"TX",
    "sg:tags":[
        "metal"
    ],
    "wof:name":"Stainless & Alloy Proc Inc",
    "wof:placetype":"venue"
},
  "geometry": {"coordinates":[-95.516319,29.731696],"type":"Point"}
}