{
  "type": "Feature",
  "properties": {
    "iso:country":"US",
    "sg:address":"440 Overland Dr",
    "sg:city":"Mc Kinney",
    "sg:classifiers":[
        {
            "category":"Utilities",
            "subcategory":"Telephone",
            "type":"Services"
        }
    ],
    "sg:phone":"+1 972 880 6002",
    "sg:postcode":"75069",
    "sg:province":"TX",
    "sg:tags":[
        "equipment"
    ],
    "wof:name":"Ldwidebandcom",
    "wof:placetype":"venue"
},
  "geometry": {"coordinates":[-96.543541,33.163905],"type":"Point"}
}