{
  "type": "Feature",
  "properties": {
    "iso:country":"US",
    "sg:address":"14241 Montana Ave",
    "sg:city":"El Paso",
    "sg:classifiers":[
        {
            "category":"Banks & Credit Unions",
            "subcategory":"Bank",
            "type":"Services"
        }
    ],
    "sg:phone":"+1 915 849 1171",
    "sg:postcode":"79938",
    "sg:province":"TX",
    "sg:tags":[
        "personal",
        "institution"
    ],
    "wof:name":"Montana Vista Finance",
    "wof:placetype":"venue"
},
  "geometry": {"coordinates":[-106.181608,31.81797],"type":"Point"}
}