{
  "type": "Feature",
  "properties": {
    "iso:country":"US",
    "sg:address":"924 E Navarro St",
    "sg:city":"De Leon",
    "sg:classifiers":[
        {
            "category":"Professional",
            "type":"Services"
        }
    ],
    "sg:phone":"+1 254 893 2922",
    "sg:postcode":"76444",
    "sg:province":"TX",
    "sg:tags":[
        "establishment"
    ],
    "wof:name":"Tractor Pull",
    "wof:placetype":"venue"
},
  "geometry": {"coordinates":[-98.523132,32.114753],"type":"Point"}
}