{
  "type": "Feature",
  "properties": {
    "iso:country":"US",
    "sg:address":"1501 Bundrant Dr",
    "sg:city":"Killeen",
    "sg:classifiers":[
        {
            "category":"Social Services",
            "subcategory":"Child Care",
            "type":"Services"
        },
        {
            "category":"Social Services",
            "type":"Services"
        }
    ],
    "sg:phone":"+1 254 699 0091",
    "sg:postcode":"76543",
    "sg:province":"TX",
    "wof:name":"Kay's Day Care",
    "wof:placetype":"venue"
},
  "geometry": {"coordinates":[-97.69783700000001,31.124209],"type":"Point"}
}