{
  "type": "Feature",
  "properties": {
    "iso:country":"US",
    "sg:address":"1004 N Big Spring St",
    "sg:city":"Midland",
    "sg:classifiers":[
        {
            "category":"Government",
            "subcategory":"Police Station",
            "type":"Public Place"
        }
    ],
    "sg:phone":"+1 432 570 0255",
    "sg:postcode":"79701",
    "sg:province":"TX",
    "sg:tags":[
        "federal"
    ],
    "wof:name":"Federal Bureau-Investigation",
    "wof:placetype":"venue"
},
  "geometry": {"coordinates":[-102.079059,32.007727],"type":"Point"}
}