{
  "type": "Feature",
  "properties": {
    "iso:country":"US",
    "sg:address":"819 W Davis St",
    "sg:city":"Dallas",
    "sg:classifiers":[
        {
            "category":"Retail",
            "subcategory":"Auto Repair",
            "type":"Services"
        }
    ],
    "sg:phone":"+1 214 946 2244",
    "sg:postcode":"75208",
    "sg:province":"TX",
    "sg:tags":[
        "general"
    ],
    "wof:name":"Samuel Auto Repair",
    "wof:placetype":"venue"
},
  "geometry": {"coordinates":[-96.837299,32.749558],"type":"Point"}
}