{
  "type": "Feature",
  "properties": {
    "iso:country":"US",
    "sg:address":"2901 Clubhouse Dr",
    "sg:city":"Pearland",
    "sg:classifiers":[
        {
            "category":"Sports & Exercise",
            "subcategory":"Golf",
            "type":"Entertainment"
        }
    ],
    "sg:phone":"+1 713 436 9999",
    "sg:postcode":"77584",
    "sg:province":"TX",
    "sg:tags":[
        "club"
    ],
    "wof:name":"Southwyck Golf Club",
    "wof:placetype":"venue"
},
  "geometry": {"coordinates":[-95.373897,29.545862],"type":"Point"}
}