{
  "type": "Feature",
  "properties": {
    "iso:country":"US",
    "sg:address":"2321 Bay Area Blvd",
    "sg:city":"Houston",
    "sg:classifiers":[
        {
            "category":"Health Services",
            "subcategory":"Dentist",
            "type":"Services"
        }
    ],
    "sg:phone":"+1 877 273 5852",
    "sg:postcode":"77058",
    "sg:province":"TX",
    "sg:tags":[
        "dentists-orthodontists",
        "dental",
        "clinic",
        "dentists-pediatric",
        "dentistry"
    ],
    "sg:website":"http://www-brightnow-com.netsolads.com/?_nsag=32919",
    "wof:name":"Monarch Dental",
    "wof:placetype":"venue"
},
  "geometry": {"coordinates":[-95.10996900000001,29.57167],"type":"Point"}
}