{
  "type": "Feature",
  "properties": {
    "iso:country":"US",
    "sg:address":"8704 Millway Dr",
    "sg:city":"Austin",
    "sg:classifiers":[
        {
            "category":"Food & Beverages",
            "subcategory":"Specialty",
            "type":"Retail Goods"
        }
    ],
    "sg:phone":"+1 512 420 9011",
    "sg:postcode":"78757",
    "sg:province":"TX",
    "sg:tags":[
        "sauce",
        "condiment"
    ],
    "sg:website":"http://www.austinsown.com",
    "wof:name":"Austin's Own, Inc",
    "wof:placetype":"venue"
},
  "geometry": {"coordinates":[-97.73538600000001,30.372528],"type":"Point"}
}