{
  "type": "Feature",
  "properties": {
    "iso:country":"US",
    "sg:address":"4417 Windsor Ridge Dr",
    "sg:city":"Irving",
    "sg:classifiers":[
        {
            "category":"Professional",
            "type":"Services"
        }
    ],
    "sg:phone":"+1 972 650 0329",
    "sg:postcode":"75038",
    "sg:province":"TX",
    "wof:name":"Qti Service Corp",
    "wof:placetype":"venue"
},
  "geometry": {"coordinates":[-96.956861,32.867828],"type":"Point"}
}