{
  "type": "Feature",
  "properties": {
    "iso:country":"US",
    "sg:address":"301 W Missouri Ave",
    "sg:city":"El Paso",
    "sg:classifiers":[
        {
            "category":"Organizations",
            "subcategory":"Community Association",
            "type":"Services"
        }
    ],
    "sg:phone":"+1 915 532 1132",
    "sg:postcode":"79901",
    "sg:province":"TX",
    "sg:tags":[
        "fraternal"
    ],
    "wof:name":"Fraternity Lodge",
    "wof:placetype":"venue"
},
  "geometry": {"coordinates":[-106.491597,31.760601],"type":"Point"}
}