{
  "type": "Feature",
  "properties": {
    "iso:country":"US",
    "sg:address":"128 Creekside Ct",
    "sg:city":"Red Oak",
    "sg:classifiers":[
        {
            "category":"Manufacturing",
            "subcategory":"Printing",
            "type":"Manufacturing & Wholesale Goods"
        }
    ],
    "sg:phone":"+1 972 617 2028",
    "sg:postcode":"75154",
    "sg:province":"TX",
    "sg:tags":[
        "newspaper"
    ],
    "wof:name":"Print Express",
    "wof:placetype":"venue"
},
  "geometry": {"coordinates":[-96.827956,32.523137],"type":"Point"}
}