{
  "type": "Feature",
  "properties": {
    "iso:country":"US",
    "sg:address":"9408 N Loop Fwy",
    "sg:city":"Houston",
    "sg:classifiers":[
        {
            "category":"Wholesale",
            "subcategory":"Auto Parts",
            "type":"Manufacturing & Wholesale Goods"
        }
    ],
    "sg:phone":"+1 713 674 4309",
    "sg:postcode":"77029",
    "sg:province":"TX",
    "wof:name":"Harlow Filter Supply Inc",
    "wof:placetype":"venue"
},
  "geometry": {"coordinates":[-95.26733,29.789394],"type":"Point"}
}