{
  "type": "Feature",
  "properties": {
    "iso:country":"US",
    "sg:address":"3302 Buckner Blvd",
    "sg:city":"Dallas",
    "sg:classifiers":[
        {
            "category":"Utilities",
            "subcategory":"Mobile Phone",
            "type":"Services"
        }
    ],
    "sg:phone":"+1 214 328 5372",
    "sg:postcode":"75228",
    "sg:province":"TX",
    "sg:tags":[
        "telephone",
        "cellular"
    ],
    "wof:name":"Cingular Wireless",
    "wof:placetype":"venue"
},
  "geometry": {"coordinates":[-96.682366,32.80422],"type":"Point"}
}