{
  "type": "Feature",
  "properties": {
    "iso:country":"US",
    "sg:address":"1614 Park Harbor Ct",
    "sg:city":"Houston",
    "sg:classifiers":[
        {
            "category":"Manufacturing",
            "subcategory":"Toys & Sporting Goods",
            "type":"Manufacturing & Wholesale Goods"
        }
    ],
    "sg:phone":"+1 281 398 0535",
    "sg:postcode":"77084",
    "sg:province":"TX",
    "sg:tags":[
        "mfg"
    ],
    "wof:name":"Nuttin Butt Huntin",
    "wof:placetype":"venue"
},
  "geometry": {"coordinates":[-95.70094899999999,29.794048],"type":"Point"}
}