{
  "type": "Feature",
  "properties": {
    "iso:country":"US",
    "sg:address":"6911 Pine Grove Dr",
    "sg:city":"Houston",
    "sg:classifiers":[
        {
            "category":"Freight",
            "type":"Transportation"
        }
    ],
    "sg:phone":"+1 713 460 1630",
    "sg:postcode":"77092",
    "sg:province":"TX",
    "sg:tags":[
        "trucking"
    ],
    "wof:name":"D J Trucking Inc",
    "wof:placetype":"venue"
},
  "geometry": {"coordinates":[-95.493999,29.854022],"type":"Point"}
}