{
  "type": "Feature",
  "properties": {
    "iso:country":"US",
    "sg:address":"9565 Dyer St",
    "sg:city":"El Paso",
    "sg:classifiers":[
        {
            "category":"Social Services",
            "type":"Services"
        }
    ],
    "sg:phone":"+1 915 751 7761",
    "sg:postcode":"79924",
    "sg:province":"TX",
    "sg:tags":[
        "probation"
    ],
    "wof:name":"El Paso Probation Dept",
    "wof:placetype":"venue"
},
  "geometry": {"coordinates":[-106.41992500000001,31.882464],"type":"Point"}
}