{
  "type": "Feature",
  "properties": {
    "iso:country":"US",
    "sg:address":"304 Harris Blvd",
    "sg:city":"Conroe",
    "sg:classifiers":[
        {
            "category":"Autos & Motor Vehicles",
            "subcategory":"Auto Supplies",
            "type":"Retail Goods"
        }
    ],
    "sg:phone":"+1 936 441 7650",
    "sg:postcode":"77301",
    "sg:province":"TX",
    "sg:tags":[
        "automobile",
        "alarm"
    ],
    "wof:name":"Baer Necessities",
    "wof:placetype":"venue"
},
  "geometry": {"coordinates":[-95.463523,30.333208],"type":"Point"}
}