{
  "type": "Feature",
  "properties": {
    "iso:country":"US",
    "sg:address":"109 W Main St",
    "sg:city":"Azle",
    "sg:classifiers":[
        {
            "category":"Manufacturing",
            "subcategory":"Apparel",
            "type":"Manufacturing & Wholesale Goods"
        }
    ],
    "sg:phone":"+1 817 444 9902",
    "sg:postcode":"76020",
    "sg:province":"TX",
    "wof:name":"North Texas Custom Embroidery",
    "wof:placetype":"venue"
},
  "geometry": {"coordinates":[-97.54301,32.890918],"type":"Point"}
}