{
  "type": "Feature",
  "properties": {
    "iso:country":"US",
    "sg:address":"3101 Oakview Dr",
    "sg:city":"Temple",
    "sg:classifiers":[
        {
            "category":"Real Estate",
            "subcategory":"Real Estate Operator",
            "type":"Services"
        }
    ],
    "sg:phone":"+1 254 773 5977",
    "sg:postcode":"76502",
    "sg:province":"TX",
    "sg:tags":[
        "apartment"
    ],
    "wof:name":"Oak View Apartments",
    "wof:placetype":"venue"
},
  "geometry": {"coordinates":[-97.381244,31.072691],"type":"Point"}
}