{
  "type": "Feature",
  "properties": {
    "iso:country":"US",
    "sg:address":"1820 Shiloh Rd",
    "sg:city":"Tyler",
    "sg:classifiers":[
        {
            "category":"Insurance",
            "subcategory":"Insurance Agent",
            "type":"Services"
        }
    ],
    "sg:phone":"+1 903 581 0662",
    "sg:postcode":"75703",
    "sg:province":"TX",
    "sg:tags":[
        "agency"
    ],
    "wof:name":"Equitable Life Assurance",
    "wof:placetype":"venue"
},
  "geometry": {"coordinates":[-95.279439,32.295363],"type":"Point"}
}