{
  "type": "Feature",
  "properties": {
    "iso:country":"US",
    "sg:address":"718 W Davis St",
    "sg:city":"Dallas",
    "sg:classifiers":[
        {
            "category":"Autos & Motor Vehicles",
            "subcategory":"Automobile Sales",
            "type":"Retail Goods"
        },
        {
            "category":"Arts & Performance",
            "subcategory":"Arts Center",
            "type":"Entertainment"
        }
    ],
    "sg:phone":"+1 972 251 0765",
    "sg:postcode":"75208",
    "sg:province":"TX",
    "sg:tags":[
        "automotive"
    ],
    "sg:website":"www.krometics.com",
    "wof:name":"Krometics",
    "wof:placetype":"venue"
},
  "geometry": {"coordinates":[-96.834282,32.749445],"type":"Point"}
}