{
  "type": "Feature",
  "properties": {
    "iso:country":"US",
    "sg:address":"7413 Douglas Ln",
    "sg:city":"Fort Worth",
    "sg:classifiers":[
        {
            "category":"Real Estate",
            "subcategory":"Real Estate Agent",
            "type":"Services"
        }
    ],
    "sg:phone":"+1 817 281 8435",
    "sg:postcode":"76180",
    "sg:province":"TX",
    "sg:tags":[
        "appraiser"
    ],
    "wof:name":"Investment Evaluation Inc",
    "wof:placetype":"venue"
},
  "geometry": {"coordinates":[-97.22505,32.885251],"type":"Point"}
}