{
  "type": "Feature",
  "properties": {
    "iso:country":"US",
    "sg:address":"2220 Highland Rd",
    "sg:city":"Dallas",
    "sg:classifiers":[
        {
            "category":"Food & Beverages",
            "subcategory":"Groceries & Convenience Stores",
            "type":"Retail Goods"
        }
    ],
    "sg:phone":"+1 214 328 9837",
    "sg:postcode":"75228",
    "sg:province":"TX",
    "wof:name":"De Mi Tierra",
    "wof:placetype":"venue"
},
  "geometry": {"coordinates":[-96.71453700000001,32.802354],"type":"Point"}
}