{
  "type": "Feature",
  "properties": {
    "iso:country":"US",
    "sg:address":"1081 E Washington St",
    "sg:city":"Giddings",
    "sg:classifiers":[
        {
            "category":"Manufacturing",
            "subcategory":"Tools & Machinery",
            "type":"Manufacturing & Wholesale Goods"
        }
    ],
    "sg:phone":"+1 979 542 0312",
    "sg:postcode":"78942",
    "sg:province":"TX",
    "sg:tags":[
        "equipment",
        "lighting",
        "mfg"
    ],
    "wof:name":"Jvm Mfg Inc",
    "wof:placetype":"venue"
},
  "geometry": {"coordinates":[-96.926883,30.184952],"type":"Point"}
}