{
  "type": "Feature",
  "properties": {
    "iso:country":"US",
    "sg:address":"1110 N Beaton St",
    "sg:city":"Corsicana",
    "sg:classifiers":[
        {
            "category":"Education",
            "subcategory":"School",
            "type":"Public Place"
        }
    ],
    "sg:phone":"+1 903 874 0400",
    "sg:postcode":"75110",
    "sg:province":"TX",
    "wof:name":"Navarro Christian School",
    "wof:placetype":"venue"
},
  "geometry": {"coordinates":[-96.47059299999999,32.102763],"type":"Point"}
}