{
  "type": "Feature",
  "properties": {
    "iso:country":"US",
    "sg:address":"2100 Pembrooke Pl",
    "sg:city":"Denton",
    "sg:classifiers":[
        {
            "category":"Education",
            "subcategory":"Special Training",
            "type":"Public Place"
        }
    ],
    "sg:phone":"+1 940 383 1902",
    "sg:postcode":"76205",
    "sg:province":"TX",
    "wof:name":"HLT Consultant & Instruction",
    "wof:placetype":"venue"
},
  "geometry": {"coordinates":[-97.12255999999999,33.18755],"type":"Point"}
}