{
  "type": "Feature",
  "properties": {
    "iso:country":"US",
    "sg:address":"11886 Wilcrest Dr",
    "sg:city":"Houston",
    "sg:classifiers":[
        {
            "category":"Sports & Exercise",
            "subcategory":"Bicycle Rental",
            "type":"Entertainment"
        }
    ],
    "sg:phone":"+1 281 879 1466",
    "sg:postcode":"77031",
    "sg:province":"TX",
    "sg:tags":[
        "wear"
    ],
    "sg:website":"www.carterscountry.net",
    "wof:name":"Carter's Country",
    "wof:placetype":"venue"
},
  "geometry": {"coordinates":[-95.56590300000001,29.648399],"type":"Point"}
}