{
  "type": "Feature",
  "properties": {
    "iso:country":"US",
    "sg:address":"2500 Legacy Dr",
    "sg:city":"Frisco",
    "sg:classifiers":[
        {
            "category":"Professional",
            "subcategory":"Management & Consulting",
            "type":"Services"
        },
        {
            "category":"Banks & Credit Unions",
            "subcategory":"Investment Brokerage",
            "type":"Services"
        },
        {
            "category":"Banks & Credit Unions",
            "subcategory":"Bank",
            "type":"Services"
        },
        {
            "category":"Banks & Credit Unions",
            "subcategory":"Financial Services",
            "type":"Services"
        }
    ],
    "sg:phone":"+1 972 712 4500",
    "sg:postcode":"75034",
    "sg:province":"TX",
    "sg:tags":[
        "advisory",
        "financing",
        "planner",
        "consultant",
        "mutual",
        "broker",
        "fund",
        "planning",
        "retirement",
        "security",
        "bond",
        "stock"
    ],
    "sg:website":"https://home.wellsfargoadvisors.com/001_A777?cid=FA090007486",
    "wof:name":"Wells Fargo Advisors",
    "wof:placetype":"venue"
},
  "geometry": {"coordinates":[-96.841888,33.099172],"type":"Point"}
}