{
  "type": "Feature",
  "properties": {
    "iso:country":"US",
    "sg:address":"218 Tansyl Dr",
    "sg:city":"San Antonio",
    "sg:classifiers":[
        {
            "category":"Professional",
            "subcategory":"Art Services",
            "type":"Services"
        }
    ],
    "sg:phone":"+1 210 308 0995",
    "sg:postcode":"78213",
    "sg:province":"TX",
    "sg:tags":[
        "graphic",
        "designer"
    ],
    "wof:name":"Visual Sensations",
    "wof:placetype":"venue"
},
  "geometry": {"coordinates":[-98.54145,29.508542],"type":"Point"}
}