{
  "type": "Feature",
  "properties": {
    "iso:country":"US",
    "sg:address":"2909 Guadalupe Street",
    "sg:city":"Austin",
    "sg:classifiers":[
        {
            "category":"Restaurant",
            "type":"Food & Drink"
        }
    ],
    "sg:phone":"+1 512 476 1021",
    "sg:postcode":"78705",
    "sg:province":"TX",
    "sg:tags":[
        "greek",
        "mediterranean",
        "pizza"
    ],
    "sg:website":"www.miltosmediterraneancafe.com",
    "wof:name":"Milto's Pizza Pub",
    "wof:placetype":"venue"
},
  "geometry": {"coordinates":[-97.74239799999999,30.295641],"type":"Point"}
}