{
  "type": "Feature",
  "properties": {
    "iso:country":"US",
    "sg:address":"2400 W 4th St",
    "sg:city":"Irving",
    "sg:classifiers":[
        {
            "category":"Food & Beverages",
            "subcategory":"Groceries & Convenience Stores",
            "type":"Retail Goods"
        }
    ],
    "sg:phone":"+1 972 986 0186",
    "sg:postcode":"75060",
    "sg:province":"TX",
    "wof:name":"A To Z Food Mart",
    "wof:placetype":"venue"
},
  "geometry": {"coordinates":[-96.97852399999999,32.810609],"type":"Point"}
}