{
  "type": "Feature",
  "properties": {
    "iso:country":"US",
    "sg:address":"1400 Griffin St E",
    "sg:city":"Dallas",
    "sg:classifiers":[
        {
            "category":"Professional",
            "subcategory":"Accounting & Tax Preparation",
            "type":"Services"
        }
    ],
    "sg:phone":"+1 214 565 4102",
    "sg:postcode":"75215",
    "sg:province":"TX",
    "wof:name":"Txu Business Services Co",
    "wof:placetype":"venue"
},
  "geometry": {"coordinates":[-96.79303,32.772523],"type":"Point"}
}