{
  "type": "Feature",
  "properties": {
    "iso:country":"US",
    "sg:address":"304 Glen Rose Ave",
    "sg:city":"Cleburne",
    "sg:classifiers":[
        {
            "category":"Shopping",
            "subcategory":"Beauty & Cosmetics",
            "type":"Retail Goods"
        }
    ],
    "sg:phone":"+1 817 558 7434",
    "sg:postcode":"76033",
    "sg:province":"TX",
    "sg:tags":[
        "merchandise"
    ],
    "wof:name":"Avon Independent Agent",
    "wof:placetype":"venue"
},
  "geometry": {"coordinates":[-97.402856,32.351576],"type":"Point"}
}