{
  "type": "Feature",
  "properties": {
    "iso:country":"US",
    "sg:address":"505 E Davis St",
    "sg:city":"Luling",
    "sg:classifiers":[
        {
            "category":"Personal",
            "subcategory":"Beauty Salon",
            "type":"Services"
        }
    ],
    "sg:phone":"+1 830 875 5306",
    "sg:postcode":"78648",
    "sg:province":"TX",
    "wof:name":"Secrets Hair Nail & Facial",
    "wof:placetype":"venue"
},
  "geometry": {"coordinates":[-97.639555,29.680038],"type":"Point"}
}