{
  "type": "Feature",
  "properties": {
    "iso:country":"US",
    "sg:address":"2239 Joyce Dr",
    "sg:city":"Corpus Christi",
    "sg:classifiers":[
        {
            "category":"Freight",
            "type":"Transportation"
        }
    ],
    "sg:phone":"+1 361 854 1491",
    "sg:postcode":"78417",
    "sg:province":"TX",
    "sg:tags":[
        "operator",
        "general",
        "dwelling",
        "furniture"
    ],
    "wof:name":"Coastal Bend Sales",
    "wof:placetype":"venue"
},
  "geometry": {"coordinates":[-97.43664699999999,27.727017],"type":"Point"}
}