{
  "type": "Feature",
  "properties": {
    "iso:country":"US",
    "sg:address":"8206 Dorrcrest Ln",
    "sg:city":"Houston",
    "sg:classifiers":[
        {
            "category":"Wholesale",
            "subcategory":"Machinery & Supplies",
            "type":"Manufacturing & Wholesale Goods"
        }
    ],
    "sg:phone":"+1 281 807 7622",
    "sg:postcode":"77070",
    "sg:province":"TX",
    "sg:tags":[
        "equipment"
    ],
    "wof:name":"Shores Oil Field Equipment Co",
    "wof:placetype":"venue"
},
  "geometry": {"coordinates":[-95.560721,29.975257],"type":"Point"}
}