{
  "type": "Feature",
  "properties": {
    "iso:country":"US",
    "sg:address":"2311 Bantry Ln",
    "sg:city":"Arlington",
    "sg:classifiers":[
        {
            "category":"Shopping",
            "type":"Retail Goods"
        }
    ],
    "sg:phone":"+1 817 417 7702",
    "sg:postcode":"76002",
    "sg:province":"TX",
    "sg:tags":[
        "merchandise"
    ],
    "wof:name":"Fairways Medical Sups & Eqp",
    "wof:placetype":"venue"
},
  "geometry": {"coordinates":[-97.067432,32.633263],"type":"Point"}
}