{
  "type": "Feature",
  "properties": {
    "iso:country":"US",
    "sg:address":"1516 Red Oak Cir",
    "sg:city":"Azle",
    "sg:classifiers":[
        {
            "category":"Professional",
            "type":"Services"
        }
    ],
    "sg:phone":"+1 817 237 5129",
    "sg:postcode":"76020",
    "sg:province":"TX",
    "wof:name":"Ultra Sharp",
    "wof:placetype":"venue"
},
  "geometry": {"coordinates":[-97.52782000000001,32.86322],"type":"Point"}
}