{
  "type": "Feature",
  "properties": {
    "iso:country":"US",
    "sg:address":"8616 Fannette St",
    "sg:city":"Houston",
    "sg:classifiers":[
        {
            "category":"Banks & Credit Unions",
            "subcategory":"Financial Services",
            "type":"Services"
        }
    ],
    "sg:phone":"+1 713 681 5057",
    "sg:postcode":"77029",
    "sg:province":"TX",
    "sg:tags":[
        "charitable",
        "foundation"
    ],
    "wof:name":"Haiken Grge Elzbeth Foundation",
    "wof:placetype":"venue"
},
  "geometry": {"coordinates":[-95.270476,29.766968],"type":"Point"}
}