{
  "type": "Feature",
  "properties": {
    "iso:country":"US",
    "sg:address":"1620 S 1st St",
    "sg:city":"Garland",
    "sg:classifiers":[
        {
            "category":"Cinema",
            "subcategory":"Movie Rental",
            "type":"Entertainment"
        }
    ],
    "sg:phone":"+1 972 271 2349",
    "sg:postcode":"75040",
    "sg:province":"TX",
    "sg:tags":[
        "video",
        "tape"
    ],
    "wof:name":"Best Video",
    "wof:placetype":"venue"
},
  "geometry": {"coordinates":[-96.63096,32.896276],"type":"Point"}
}