{
  "type": "Feature",
  "properties": {
    "iso:country":"US",
    "sg:address":"2350 Houston St",
    "sg:city":"Grand Prairie",
    "sg:classifiers":[
        {
            "category":"Professional",
            "type":"Services"
        }
    ],
    "sg:phone":"+1 972 602 3800",
    "sg:postcode":"75050",
    "sg:province":"TX",
    "sg:tags":[
        "establishment"
    ],
    "wof:name":"Two Juan's Inc",
    "wof:placetype":"venue"
},
  "geometry": {"coordinates":[-97.037536,32.740854],"type":"Point"}
}