{
  "type": "Feature",
  "properties": {
    "iso:country":"US",
    "sg:address":"8012 Rose Creek Ct",
    "sg:city":"Burleson",
    "sg:classifiers":[
        {
            "category":"Building & Trades",
            "subcategory":"Construction",
            "type":"Services"
        }
    ],
    "sg:phone":"+1 817 477 1361",
    "sg:postcode":"76028",
    "sg:province":"TX",
    "sg:tags":[
        "acoustical",
        "work",
        "drywall",
        "contractor"
    ],
    "wof:name":"Rittenbury Acoustical Drywall",
    "wof:placetype":"venue"
},
  "geometry": {"coordinates":[-97.22272700000001,32.556619],"type":"Point"}
}