{
  "type": "Feature",
  "properties": {
    "iso:country":"US",
    "sg:address":"1005 S University Parks Dr",
    "sg:city":"Waco",
    "sg:classifiers":[
        {
            "category":"Arts & Performance",
            "subcategory":"Theater",
            "type":"Entertainment"
        }
    ],
    "sg:phone":"+1 254 772 1354",
    "sg:postcode":"76706",
    "sg:province":"TX",
    "sg:tags":[
        "group"
    ],
    "wof:name":"Disk Daddy",
    "wof:placetype":"venue"
},
  "geometry": {"coordinates":[-97.119145,31.552443],"type":"Point"}
}