{
  "type": "Feature",
  "properties": {
    "iso:country":"US",
    "sg:address":"910 Brenda St",
    "sg:city":"Houston",
    "sg:classifiers":[
        {
            "category":"Building & Trades",
            "subcategory":"Plumbing",
            "type":"Services"
        }
    ],
    "sg:phone":"+1 713 695 2400",
    "sg:postcode":"77076",
    "sg:province":"TX",
    "sg:tags":[
        "conditioning",
        "air",
        "system",
        "contractor"
    ],
    "sg:website":"www.airtechenvironmental.com",
    "wof:name":"Air Tech Environmental Systems",
    "wof:placetype":"venue"
},
  "geometry": {"coordinates":[-95.386503,29.858527],"type":"Point"}
}