{
  "type": "Feature",
  "properties": {
    "iso:country":"US",
    "sg:address":"201 Co Rd 499",
    "sg:city":"Harlingen",
    "sg:classifiers":[
        {
            "category":"Organizations",
            "subcategory":"Religious Organization",
            "type":"Services"
        }
    ],
    "sg:phone":"+1 956 421 2734",
    "sg:postcode":"78550",
    "sg:province":"TX",
    "sg:tags":[
        "church"
    ],
    "wof:name":"Kingdom Hall Of Jehovah's Witn",
    "wof:placetype":"venue"
},
  "geometry": {"coordinates":[-97.663133,26.19586],"type":"Point"}
}