{
  "type": "Feature",
  "properties": {
    "iso:country":"US",
    "sg:address":"3302 Manitou St",
    "sg:city":"Corpus Christi",
    "sg:classifiers":[
        {
            "category":"Professional",
            "subcategory":"Lawyer & Legal Services",
            "type":"Services"
        }
    ],
    "sg:phone":"+1 361 814 7588",
    "sg:postcode":"78411",
    "sg:province":"TX",
    "sg:tags":[
        "attorney",
        "bureau"
    ],
    "wof:name":"A Plus Litigation Svc",
    "wof:placetype":"venue"
},
  "geometry": {"coordinates":[-97.382161,27.757403],"type":"Point"}
}