{
  "type": "Feature",
  "properties": {
    "iso:country":"US",
    "sg:address":"3523 McKinney Ave",
    "sg:city":"Dallas",
    "sg:classifiers":[
        {
            "category":"Restaurant",
            "type":"Food & Drink"
        }
    ],
    "sg:phone":"+1 214 559 4280",
    "sg:postcode":"75204",
    "sg:province":"TX",
    "sg:tags":[
        "caterer"
    ],
    "wof:name":"Dr Coffee Catering",
    "wof:placetype":"venue"
},
  "geometry": {"coordinates":[-96.797843,32.806738],"type":"Point"}
}