{
  "type": "Feature",
  "properties": {
    "iso:country":"US",
    "sg:address":"10818 Burman St",
    "sg:city":"Houston",
    "sg:classifiers":[
        {
            "category":"Building & Trades",
            "subcategory":"Construction",
            "type":"Services"
        }
    ],
    "sg:phone":"+1 713 453 4140",
    "sg:postcode":"77029",
    "sg:province":"TX",
    "sg:tags":[
        "contractor"
    ],
    "wof:name":"AA Pressure Washing",
    "wof:placetype":"venue"
},
  "geometry": {"coordinates":[-95.238501,29.764589],"type":"Point"}
}