{
  "type": "Feature",
  "properties": {
    "iso:country":"US",
    "sg:address":"7801 Nairn St",
    "sg:city":"Houston",
    "sg:classifiers":[
        {
            "category":"Shopping",
            "subcategory":"Clothing, Apparel, & Fashions",
            "type":"Retail Goods"
        }
    ],
    "sg:phone":"+1 713 771 3984",
    "sg:postcode":"77074",
    "sg:province":"TX",
    "wof:name":"Cromwell",
    "wof:placetype":"venue"
},
  "geometry": {"coordinates":[-95.51810999999999,29.680052],"type":"Point"}
}