{
  "type": "Feature",
  "properties": {
    "iso:country":"US",
    "sg:address":"1501 N Dallas Ave",
    "sg:city":"Lancaster",
    "sg:classifiers":[
        {
            "category":"Government",
            "subcategory":"Police Station",
            "type":"Public Place"
        }
    ],
    "sg:phone":"+1 972 227 2311",
    "sg:postcode":"75134",
    "sg:province":"TX",
    "sg:tags":[
        "department"
    ],
    "wof:name":"Lancaster Police Dept",
    "wof:placetype":"venue"
},
  "geometry": {"coordinates":[-96.76123699999999,32.608131],"type":"Point"}
}