{
  "type": "Feature",
  "properties": {
    "iso:country":"US",
    "sg:address":"4112 Legacy Dr",
    "sg:city":"Plano",
    "sg:classifiers":[
        {
            "category":"Retail",
            "subcategory":"Veterinary Services",
            "type":"Services"
        }
    ],
    "sg:phone":"+1 972 335 9292",
    "sg:postcode":"75024",
    "sg:province":"TX",
    "sg:tags":[
        "veterinarian"
    ],
    "wof:name":"Legacy Veterinary Hospital",
    "wof:placetype":"venue"
},
  "geometry": {"coordinates":[-96.774355,33.071435],"type":"Point"}
}