{
  "type": "Feature",
  "properties": {
    "iso:country":"US",
    "sg:address":"800 Lubbock Rd",
    "sg:city":"Brownfield",
    "sg:classifiers":[
        {
            "category":"Food & Beverages",
            "subcategory":"Groceries & Convenience Stores",
            "type":"Retail Goods"
        }
    ],
    "sg:phone":"+1 806 637 8111",
    "sg:postcode":"79316",
    "sg:province":"TX",
    "sg:website":"www.tcfs.com",
    "wof:name":"Town & Country Food Store 84",
    "wof:placetype":"venue"
},
  "geometry": {"coordinates":[-102.27411600000001,33.187123],"type":"Point"}
}