{
  "type": "Feature",
  "properties": {
    "iso:country":"US",
    "sg:address":"17104 Blanco Rd",
    "sg:city":"San Antonio",
    "sg:classifiers":[
        {
            "category":"Manufacturing",
            "subcategory":"Retail Goods",
            "type":"Manufacturing & Wholesale Goods"
        }
    ],
    "sg:phone":"+1 210 492 5030",
    "sg:postcode":"78232",
    "sg:province":"TX",
    "sg:tags":[
        "product",
        "mfg"
    ],
    "wof:name":"Purple Plus 2000 Corp",
    "wof:placetype":"venue"
},
  "geometry": {"coordinates":[-98.515497,29.586129],"type":"Point"}
}