{
  "type": "Feature",
  "properties": {
    "iso:country":"US",
    "sg:address":"2506 Purdue St",
    "sg:city":"Lubbock",
    "sg:classifiers":[
        {
            "category":"Social Services",
            "subcategory":"Job Training",
            "type":"Services"
        }
    ],
    "sg:phone":"+1 806 775 2775",
    "sg:postcode":"79415",
    "sg:province":"TX",
    "wof:name":"Lubbock Hispanic Peace Officer",
    "wof:placetype":"venue"
},
  "geometry": {"coordinates":[-101.873763,33.641185],"type":"Point"}
}