{
  "type": "Feature",
  "properties": {
    "iso:country":"US",
    "sg:address":"2132 E Belt Line Rd",
    "sg:city":"Richardson",
    "sg:classifiers":[
        {
            "category":"Wholesale",
            "subcategory":"Farm Supplies",
            "type":"Manufacturing & Wholesale Goods"
        },
        {
            "category":"Building & Trades",
            "subcategory":"Pest Control",
            "type":"Services"
        }
    ],
    "sg:phone":"+1 972 238 5875",
    "sg:postcode":"75081",
    "sg:province":"TX",
    "sg:tags":[
        "equipment"
    ],
    "wof:name":"Chaparral Pest Control",
    "wof:placetype":"venue"
},
  "geometry": {"coordinates":[-96.685789,32.945247],"type":"Point"}
}