{
  "type": "Feature",
  "properties": {
    "iso:country":"US",
    "sg:address":"2023 N Willomet Ave",
    "sg:city":"Dallas",
    "sg:classifiers":[
        {
            "category":"Organizations",
            "subcategory":"Religious Organization",
            "type":"Services"
        }
    ],
    "sg:phone":"+1 214 698 8422",
    "sg:postcode":"75208",
    "sg:province":"TX",
    "sg:tags":[
        "church"
    ],
    "wof:name":"Templo Jesus Christ",
    "wof:placetype":"venue"
},
  "geometry": {"coordinates":[-96.83935700000001,32.771244],"type":"Point"}
}