{
  "type": "Feature",
  "properties": {
    "iso:country":"US",
    "sg:address":"419 Gentry St",
    "sg:city":"Spring",
    "sg:classifiers":[
        {
            "category":"Shopping",
            "subcategory":"Gifts & Souvenirs",
            "type":"Retail Goods"
        }
    ],
    "sg:phone":"+1 281 528 8129",
    "sg:postcode":"77373",
    "sg:province":"TX",
    "wof:name":"Seymour Sporkin",
    "wof:placetype":"venue"
},
  "geometry": {"coordinates":[-95.421155,30.078682],"type":"Point"}
}