{
  "type": "Feature",
  "properties": {
    "iso:country":"US",
    "sg:address":"2108 E Ledbetter Dr",
    "sg:city":"Dallas",
    "sg:classifiers":[
        {
            "category":"Wholesale",
            "subcategory":"Machinery & Supplies",
            "type":"Manufacturing & Wholesale Goods"
        },
        {
            "category":"Shopping",
            "subcategory":"Beauty & Cosmetics",
            "type":"Retail Goods"
        }
    ],
    "sg:phone":"+1 214 371 3606",
    "sg:postcode":"75216",
    "sg:province":"TX",
    "sg:tags":[
        "equipment",
        "salon"
    ],
    "wof:name":"Sally Beauty Supply",
    "wof:placetype":"venue"
},
  "geometry": {"coordinates":[-96.789652,32.686103],"type":"Point"}
}