{
  "type": "Feature",
  "properties": {
    "iso:country":"US",
    "sg:address":"5200 Beverly Dr",
    "sg:city":"Waco",
    "sg:classifiers":[
        {
            "category":"Manufacturing",
            "subcategory":"Glass & Minerals",
            "type":"Manufacturing & Wholesale Goods"
        }
    ],
    "sg:phone":"+1 254 754 9502",
    "sg:postcode":"76711",
    "sg:province":"TX",
    "sg:tags":[
        "container",
        "mfg"
    ],
    "wof:name":"Owens-Brockway Glass Container",
    "wof:placetype":"venue"
},
  "geometry": {"coordinates":[-97.17461299999999,31.505626],"type":"Point"}
}