{
  "type": "Feature",
  "properties": {
    "iso:country":"US",
    "sg:address":"1406 Camelot Cir",
    "sg:city":"Austin",
    "sg:classifiers":[
        {
            "category":"Restaurant",
            "type":"Food & Drink"
        }
    ],
    "sg:phone":"+1 512 445 4856",
    "sg:postcode":"78745",
    "sg:province":"TX",
    "sg:tags":[
        "eating"
    ],
    "wof:name":"Chef Bs Personal Chef & Cater",
    "wof:placetype":"venue"
},
  "geometry": {"coordinates":[-97.78656100000001,30.219924],"type":"Point"}
}