{
  "type": "Feature",
  "properties": {
    "iso:country":"US",
    "sg:address":"2825 Lana Cir",
    "sg:city":"Fort Worth",
    "sg:classifiers":[
        {
            "category":"Professional",
            "type":"Services"
        }
    ],
    "sg:phone":"+1 817 293 7388",
    "sg:postcode":"76140",
    "sg:province":"TX",
    "wof:name":"Comtech Services",
    "wof:placetype":"venue"
},
  "geometry": {"coordinates":[-97.28274500000001,32.647969],"type":"Point"}
}