{
  "type": "Feature",
  "properties": {
    "iso:country":"US",
    "sg:address":"107 W 2nd St",
    "sg:city":"Kaufman",
    "sg:classifiers":[
        {
            "category":"Personal",
            "subcategory":"Beauty Salon",
            "type":"Services"
        }
    ],
    "sg:phone":"+1 972 932 2212",
    "sg:postcode":"75142",
    "sg:province":"TX",
    "wof:name":"Archie's Hair Designing",
    "wof:placetype":"venue"
},
  "geometry": {"coordinates":[-96.30993100000001,32.583745],"type":"Point"}
}