{
  "type": "Feature",
  "properties": {
    "iso:country":"US",
    "sg:address":"410 NW 21st St",
    "sg:city":"Seminole",
    "sg:classifiers":[
        {
            "category":"Professional",
            "subcategory":"Management & Consulting",
            "type":"Services"
        },
        {
            "category":"Landmark",
            "subcategory":"Monument",
            "type":"Public Place"
        },
        {
            "category":"Retail",
            "subcategory":"Funeral Services",
            "type":"Services"
        }
    ],
    "sg:phone":"+1 432 758 5440",
    "sg:postcode":"79360",
    "sg:province":"TX",
    "sg:tags":[
        "director",
        "consultant",
        "plans-pre-arranged",
        "embalmer",
        "supply"
    ],
    "sg:website":"http://www.boyerfuneralhome.net",
    "wof:name":"Boyer Funeral Home",
    "wof:placetype":"venue"
},
  "geometry": {"coordinates":[-102.66865799999999,32.718128],"type":"Point"}
}