{
  "type": "Feature",
  "properties": {
    "iso:country":"US",
    "sg:address":"6418 Rosalie Dr",
    "sg:city":"Dallas",
    "sg:classifiers":[
        {
            "category":"Building & Trades",
            "subcategory":"Plumbing",
            "type":"Services"
        }
    ],
    "sg:phone":"+1 972 572 5551",
    "sg:postcode":"75236",
    "sg:province":"TX",
    "sg:tags":[
        "conditioning",
        "air",
        "system",
        "contractor"
    ],
    "wof:name":"MGS Air Conditioning & Htg",
    "wof:placetype":"venue"
},
  "geometry": {"coordinates":[-96.93079299999999,32.677498],"type":"Point"}
}