{
  "type": "Feature",
  "properties": {
    "iso:country":"US",
    "sg:address":"4111 Plains Blvd",
    "sg:city":"Amarillo",
    "sg:classifiers":[
        {
            "category":"Place Of Worship",
            "type":"Public Place"
        }
    ],
    "sg:phone":"+1 806 353 1488",
    "sg:postcode":"79106",
    "sg:province":"TX",
    "sg:tags":[
        "church"
    ],
    "sg:website":"http://amarillo.citysearch.com/profile/external/44910464/amarillo_tx/grace_church_calvary_chapel_amarillo.html?publisher=yellowpages&reference_id=16&placement=ypwebsitemip",
    "wof:name":"Grace Church Calvary Chapel Amarillo",
    "wof:placetype":"venue"
},
  "geometry": {"coordinates":[-101.88107100000001,35.200629],"type":"Point"}
}