{
  "type": "Feature",
  "properties": {
    "iso:country":"US",
    "sg:address":"17101 Kuykendahl Rd",
    "sg:city":"Houston",
    "sg:classifiers":[
        {
            "category":"Professional",
            "subcategory":"Lawyer & Legal Services",
            "type":"Services"
        }
    ],
    "sg:phone":"+1 281 893 9312",
    "sg:postcode":"77068",
    "sg:province":"TX",
    "sg:tags":[
        "attorney"
    ],
    "wof:name":"Marvin King",
    "wof:placetype":"venue"
},
  "geometry": {"coordinates":[-95.475634,30.023065],"type":"Point"}
}