{
  "type": "Feature",
  "properties": {
    "iso:country":"US",
    "sg:address":"808 E Rio Grande St",
    "sg:city":"Victoria",
    "sg:classifiers":[
        {
            "category":"Retail",
            "subcategory":"Auto Repair",
            "type":"Services"
        }
    ],
    "sg:phone":"+1 361 578 0219",
    "sg:postcode":"77901",
    "sg:province":"TX",
    "sg:tags":[
        "alternator",
        "generator"
    ],
    "wof:name":"Commercial Rebuild Inc",
    "wof:placetype":"venue"
},
  "geometry": {"coordinates":[-96.995215,28.806019],"type":"Point"}
}