{
  "type": "Feature",
  "properties": {
    "iso:country":"US",
    "sg:address":"9503 Line Camp Ct",
    "sg:city":"Houston",
    "sg:classifiers":[
        {
            "category":"Manufacturing",
            "subcategory":"Printing",
            "type":"Manufacturing & Wholesale Goods"
        }
    ],
    "sg:phone":"+1 832 237 6890",
    "sg:postcode":"77064",
    "sg:province":"TX",
    "sg:tags":[
        "newspaper"
    ],
    "wof:name":"Daily Internet Marketing",
    "wof:placetype":"venue"
},
  "geometry": {"coordinates":[-95.576249,29.91051],"type":"Point"}
}