{
  "type": "Feature",
  "properties": {
    "iso:country":"US",
    "sg:address":"3523 Oak Lawn Ave",
    "sg:city":"Dallas",
    "sg:classifiers":[
        {
            "category":"Utilities",
            "subcategory":"Mobile Phone",
            "type":"Services"
        }
    ],
    "sg:phone":"+1 214 599 9367",
    "sg:postcode":"75219",
    "sg:province":"TX",
    "sg:tags":[
        "telephone",
        "cellular"
    ],
    "wof:name":"Nextel Retail",
    "wof:placetype":"venue"
},
  "geometry": {"coordinates":[-96.80484800000001,32.81255],"type":"Point"}
}