{
  "type": "Feature",
  "properties": {
    "iso:country":"US",
    "sg:address":"678 Co Rd 3061",
    "sg:city":"Orange Grove",
    "sg:classifiers":[
        {
            "category":"Personal",
            "subcategory":"Beauty Salon",
            "type":"Services"
        }
    ],
    "sg:phone":"+1 361 384 3252",
    "sg:postcode":"78372",
    "sg:province":"TX",
    "sg:tags":[
        "shop"
    ],
    "wof:name":"Precision Cuts",
    "wof:placetype":"venue"
},
  "geometry": {"coordinates":[-97.932408,27.989379],"type":"Point"}
}