{
  "type": "Feature",
  "properties": {
    "iso:country":"US",
    "sg:address":"1380 Stonehollow Dr",
    "sg:city":"Kingwood",
    "sg:classifiers":[
        {
            "category":"Health Services",
            "subcategory":"Health Practitioner",
            "type":"Services"
        }
    ],
    "sg:phone":"+1 281 358 7975",
    "sg:postcode":"77339",
    "sg:province":"TX",
    "sg:tags":[
        "acupuncture"
    ],
    "wof:name":"Kingwood Acupuncture",
    "wof:placetype":"venue"
},
  "geometry": {"coordinates":[-95.237515,30.051469],"type":"Point"}
}