{
  "type": "Feature",
  "properties": {
    "iso:country":"US",
    "sg:address":"2709 Monthaven Dr",
    "sg:city":"Arlington",
    "sg:classifiers":[
        {
            "category":"Professional",
            "subcategory":"Management & Consulting",
            "type":"Services"
        }
    ],
    "sg:phone":"+1 817 303 1994",
    "sg:postcode":"76001",
    "sg:province":"TX",
    "sg:tags":[
        "hispanic",
        "promotional",
        "group",
        "marketing"
    ],
    "wof:name":"Perspectiva Inc",
    "wof:placetype":"venue"
},
  "geometry": {"coordinates":[-97.154135,32.622433],"type":"Point"}
}