{
  "type": "Feature",
  "properties": {
    "iso:country":"US",
    "sg:address":"7480 State Hwy 48",
    "sg:city":"Brownsville",
    "sg:classifiers":[
        {
            "category":"Personal",
            "subcategory":"Beauty Salon",
            "type":"Services"
        }
    ],
    "sg:phone":"+1 956 838 0040",
    "sg:postcode":"78521",
    "sg:province":"TX",
    "wof:name":"Smart Style Family Hair Salon",
    "wof:placetype":"venue"
},
  "geometry": {"coordinates":[-97.427975,25.943269],"type":"Point"}
}