{
  "type": "Feature",
  "properties": {
    "iso:country":"US",
    "sg:address":"5602 Armour Dr",
    "sg:city":"Houston",
    "sg:classifiers":[
        {
            "category":"Shopping",
            "type":"Retail Goods"
        }
    ],
    "sg:phone":"+1 713 923 1300",
    "sg:postcode":"77020",
    "sg:province":"TX",
    "sg:tags":[
        "merchandise"
    ],
    "wof:name":"Derric David",
    "wof:placetype":"venue"
},
  "geometry": {"coordinates":[-95.309405,29.757656],"type":"Point"}
}