{
  "type": "Feature",
  "properties": {
    "iso:country":"US",
    "sg:address":"1303 McCullough Ave",
    "sg:city":"San Antonio",
    "sg:classifiers":[
        {
            "category":"Health Services",
            "subcategory":"Medical Lab",
            "type":"Services"
        }
    ],
    "sg:phone":"+1 210 212 4668",
    "sg:postcode":"78212",
    "sg:province":"TX",
    "sg:tags":[
        "laboratory"
    ],
    "wof:name":"Quest Diagnostics",
    "wof:placetype":"venue"
},
  "geometry": {"coordinates":[-98.491908,29.441684],"type":"Point"}
}