{
  "type": "Feature",
  "properties": {
    "iso:country":"US",
    "sg:address":"1604 Crestwood Trl",
    "sg:city":"Keller",
    "sg:classifiers":[
        {
            "category":"Professional",
            "type":"Services"
        },
        {
            "category":"Farming",
            "subcategory":"Farm & Veterinary Services",
            "type":"Manufacturing & Wholesale Goods"
        }
    ],
    "sg:phone":"+1 817 581 4608",
    "sg:postcode":"76248",
    "sg:province":"TX",
    "sg:tags":[
        "breeder",
        "livestock"
    ],
    "wof:name":"A J Marsh Cattle Co",
    "wof:placetype":"venue"
},
  "geometry": {"coordinates":[-97.21280299999999,32.915806],"type":"Point"}
}