{
  "type": "Feature",
  "properties": {
    "iso:country":"US",
    "sg:address":"3310 Premier Dr",
    "sg:city":"Plano",
    "sg:classifiers":[
        {
            "category":"Banks & Credit Unions",
            "subcategory":"Bank",
            "type":"Services"
        }
    ],
    "sg:phone":"+1 972 422 7100",
    "sg:postcode":"75023",
    "sg:province":"TX",
    "sg:tags":[
        "state",
        "commercial"
    ],
    "wof:name":"Comerica",
    "wof:placetype":"venue"
},
  "geometry": {"coordinates":[-96.708141,33.040684],"type":"Point"}
}