{
  "type": "Feature",
  "properties": {
    "iso:country":"US",
    "sg:address":"1903 Georgia Landing Cv",
    "sg:city":"Austin",
    "sg:classifiers":[
        {
            "category":"Social Services",
            "subcategory":"Adult Care",
            "type":"Services"
        }
    ],
    "sg:phone":"+1 512 328 4319",
    "sg:postcode":"78746",
    "sg:province":"TX",
    "sg:tags":[
        "living",
        "assisted",
        "elder"
    ],
    "wof:name":"Teacher Retirement System",
    "wof:placetype":"venue"
},
  "geometry": {"coordinates":[-97.835065,30.278444],"type":"Point"}
}