{
  "type": "Feature",
  "properties": {
    "iso:country":"US",
    "sg:address":"14026 River Rock Dr",
    "sg:city":"Corpus Christi",
    "sg:classifiers":[
        {
            "category":"Building & Trades",
            "subcategory":"Construction",
            "type":"Services"
        }
    ],
    "sg:phone":"+1 361 387 7893",
    "sg:postcode":"78410",
    "sg:province":"TX",
    "sg:tags":[
        "contractor"
    ],
    "wof:name":"Overall Fence & Deck",
    "wof:placetype":"venue"
},
  "geometry": {"coordinates":[-97.642312,27.853548],"type":"Point"}
}