{
  "type": "Feature",
  "properties": {
    "iso:country":"US",
    "sg:address":"9600 Great Hills Trl Ste 150W",
    "sg:city":"Austin",
    "sg:classifiers":[
        {
            "category":"Real Estate",
            "subcategory":"Real Estate Services",
            "type":"Services"
        },
        {
            "category":"Building & Trades",
            "subcategory":"Equipment Rental",
            "type":"Services"
        }
    ],
    "sg:phone":"+1 800 633 4237",
    "sg:postcode":"78759",
    "sg:province":"TX",
    "sg:tags":[
        "commercial",
        "management",
        "yard",
        "store"
    ],
    "sg:website":"http://www.hq.com",
    "wof:name":"Regus/ HQ",
    "wof:placetype":"venue"
},
  "geometry": {"coordinates":[-97.754707,30.39485],"type":"Point"}
}