{
  "type": "Feature",
  "properties": {
    "iso:country":"US",
    "sg:address":"103 E Princeton Dr",
    "sg:city":"Princeton",
    "sg:classifiers":[
        {
            "category":"Restaurant",
            "type":"Food & Drink"
        }
    ],
    "sg:menulink":"http://www.allmenus.com/tx/princeton/202861-mcdonalds/menu/",
    "sg:postcode":"75407",
    "sg:province":"TX",
    "sg:tags":[
        "burger",
        "american"
    ],
    "wof:name":"McDonald's",
    "wof:placetype":"venue"
},
  "geometry": {"coordinates":[-96.499623,33.174278],"type":"Point"}
}