{
  "type": "Feature",
  "properties": {
    "iso:country":"US",
    "sg:address":"3601 S Congress Ave",
    "sg:city":"Austin",
    "sg:classifiers":[
        {
            "category":"Real Estate",
            "subcategory":"Architect",
            "type":"Services"
        }
    ],
    "sg:phone":"+1 512 851 9753",
    "sg:postcode":"78704",
    "sg:province":"TX",
    "wof:name":"Alexander Patrick Archtct",
    "wof:placetype":"venue"
},
  "geometry": {"coordinates":[-97.76599899999999,30.241199],"type":"Point"}
}