{
  "type": "Feature",
  "properties": {
    "iso:country":"US",
    "sg:address":"1314 Texas St",
    "sg:city":"Houston",
    "sg:classifiers":[
        {
            "category":"Restaurant",
            "type":"Food & Drink"
        }
    ],
    "sg:phone":"+1 713 227 2871",
    "sg:postcode":"77002",
    "sg:province":"TX",
    "wof:name":"Nafaa Restaurants",
    "wof:placetype":"venue"
},
  "geometry": {"coordinates":[-95.35990099999999,29.758301],"type":"Point"}
}