{
  "type": "Feature",
  "properties": {
    "iso:country":"US",
    "sg:address":"7102 Baneway Dr",
    "sg:city":"Houston",
    "sg:classifiers":[
        {
            "category":"Retail",
            "subcategory":"Auto Repair",
            "type":"Services"
        }
    ],
    "sg:phone":"+1 281 498 3952",
    "sg:postcode":"77072",
    "sg:province":"TX",
    "sg:tags":[
        "body",
        "automobile",
        "painting"
    ],
    "wof:name":"Hired Guns Auto Body",
    "wof:placetype":"venue"
},
  "geometry": {"coordinates":[-95.580977,29.70133],"type":"Point"}
}