{
  "type": "Feature",
  "properties": {
    "iso:country":"US",
    "sg:address":"15201 Mason Rd",
    "sg:city":"Cypress",
    "sg:classifiers":[
        {
            "category":"Personal",
            "subcategory":"Beauty Salon",
            "type":"Services"
        }
    ],
    "sg:phone":"+1 281 304 4300",
    "sg:postcode":"77433",
    "sg:province":"TX",
    "wof:name":"Great Clips",
    "wof:placetype":"venue"
},
  "geometry": {"coordinates":[-95.738136,29.994859],"type":"Point"}
}