{
  "type": "Feature",
  "properties": {
    "iso:country":"US",
    "sg:address":"5050 Ambassador Way",
    "sg:city":"Houston",
    "sg:classifiers":[
        {
            "category":"Real Estate",
            "subcategory":"Real Estate Operator",
            "type":"Services"
        }
    ],
    "sg:phone":"+1 713 961 3116",
    "sg:postcode":"77056",
    "sg:province":"TX",
    "sg:tags":[
        "condominium"
    ],
    "wof:name":"Ambassador Condominium",
    "wof:placetype":"venue"
},
  "geometry": {"coordinates":[-95.46225099999999,29.746807],"type":"Point"}
}