{
  "type": "Feature",
  "properties": {
    "iso:country":"US",
    "sg:address":"1002 Plantation Meadows Dr",
    "sg:city":"Richmond",
    "sg:classifiers":[
        {
            "category":"Professional",
            "subcategory":"Business Services",
            "type":"Services"
        }
    ],
    "sg:phone":"+1 281 341 1117",
    "sg:postcode":"77469",
    "sg:province":"TX",
    "wof:name":"Filter Air Sales & Services",
    "wof:placetype":"venue"
},
  "geometry": {"coordinates":[-95.727957,29.609065],"type":"Point"}
}