{
  "type": "Feature",
  "properties": {
    "iso:country":"US",
    "sg:address":"3300 S Fort Hood St",
    "sg:city":"Killeen",
    "sg:classifiers":[
        {
            "category":"Banks & Credit Unions",
            "subcategory":"Bank",
            "type":"Services"
        }
    ],
    "sg:phone":"+1 254 501 9762",
    "sg:postcode":"76542",
    "sg:province":"TX",
    "sg:tags":[
        "machine",
        "teller",
        "automated"
    ],
    "wof:name":"Will Atm",
    "wof:placetype":"venue"
},
  "geometry": {"coordinates":[-97.75567599999999,31.086302],"type":"Point"}
}