{
  "type": "Feature",
  "properties": {
    "iso:country":"US",
    "sg:address":"8114 Green Devon Dr",
    "sg:city":"Houston",
    "sg:classifiers":[
        {
            "category":"Professional",
            "type":"Services"
        }
    ],
    "sg:phone":"+1 281 345 4435",
    "sg:postcode":"77095",
    "sg:province":"TX",
    "wof:name":"Ntlcp",
    "wof:placetype":"venue"
},
  "geometry": {"coordinates":[-95.64364,29.899045],"type":"Point"}
}