{
  "type": "Feature",
  "properties": {
    "iso:country":"US",
    "sg:address":"710 Water St",
    "sg:city":"Bastrop",
    "sg:classifiers":[
        {
            "category":"Professional",
            "subcategory":"Lawyer & Legal Services",
            "type":"Services"
        }
    ],
    "sg:phone":"+1 512 581 7129",
    "sg:postcode":"78602",
    "sg:province":"TX",
    "wof:name":"Anderson & Anderson Attorneys",
    "wof:placetype":"venue"
},
  "geometry": {"coordinates":[-97.318794,30.108317],"type":"Point"}
}