{
  "type": "Feature",
  "properties": {
    "iso:country":"US",
    "sg:address":"703 N Austin St",
    "sg:city":"Seguin",
    "sg:classifiers":[
        {
            "category":"Autos & Motor Vehicles",
            "subcategory":"Automobile Sales",
            "type":"Retail Goods"
        }
    ],
    "sg:phone":"+1 830 303 9620",
    "sg:postcode":"78155",
    "sg:province":"TX",
    "sg:tags":[
        "used"
    ],
    "wof:name":"EZ Credit Autos",
    "wof:placetype":"venue"
},
  "geometry": {"coordinates":[-97.964614,29.573732],"type":"Point"}
}