{
  "type": "Feature",
  "properties": {
    "iso:country":"US",
    "sg:address":"22610 Tuwa Rd",
    "sg:city":"Tomball",
    "sg:classifiers":[
        {
            "category":"Organizations",
            "subcategory":"Religious Organization",
            "type":"Services"
        }
    ],
    "sg:phone":"+1 281 351 9666",
    "sg:postcode":"77375",
    "sg:province":"TX",
    "sg:tags":[
        "church"
    ],
    "wof:name":"Kaiserhof Lutheran Church",
    "wof:placetype":"venue"
},
  "geometry": {"coordinates":[-95.562068,30.090222],"type":"Point"}
}