{
  "type": "Feature",
  "properties": {
    "iso:country":"US",
    "sg:address":"8705 Pegshire Ave",
    "sg:city":"Dallas",
    "sg:classifiers":[
        {
            "category":"Shopping",
            "subcategory":"Gifts & Souvenirs",
            "type":"Retail Goods"
        }
    ],
    "sg:phone":"+1 972 447 0448",
    "sg:postcode":"75231",
    "sg:province":"TX",
    "wof:name":"Collectibles By Laura",
    "wof:placetype":"venue"
},
  "geometry": {"coordinates":[-96.74305699999999,32.879897],"type":"Point"}
}