{
  "type": "Feature",
  "properties": {
    "iso:country":"US",
    "sg:address":"1338 Bandera Hwy",
    "sg:city":"Kerrville",
    "sg:classifiers":[
        {
            "category":"Retail",
            "subcategory":"Auto Repair",
            "type":"Services"
        }
    ],
    "sg:phone":"+1 830 257 8727",
    "sg:postcode":"78028",
    "sg:province":"TX",
    "sg:tags":[
        "repairing",
        "automobile"
    ],
    "wof:name":"Riverhills Automotive Svc Ctr",
    "wof:placetype":"venue"
},
  "geometry": {"coordinates":[-99.14092599999999,30.030275],"type":"Point"}
}