{
  "type": "Feature",
  "properties": {
    "iso:country":"US",
    "sg:address":"4737 Saratoga Blvd",
    "sg:city":"Corpus Christi",
    "sg:classifiers":[
        {
            "category":"Food & Beverages",
            "subcategory":"Bakery",
            "type":"Retail Goods"
        }
    ],
    "sg:phone":"+1 361 852 4980",
    "sg:postcode":"78413",
    "sg:province":"TX",
    "sg:tags":[
        "baker"
    ],
    "wof:name":"H E B Foods",
    "wof:placetype":"venue"
},
  "geometry": {"coordinates":[-97.39898100000001,27.693007],"type":"Point"}
}