{
  "type": "Feature",
  "properties": {
    "iso:country":"US",
    "sg:address":"19703 Encino Knoll St",
    "sg:city":"San Antonio",
    "sg:classifiers":[
        {
            "category":"Shopping",
            "type":"Retail Goods"
        }
    ],
    "sg:phone":"+1 210 497 2719",
    "sg:postcode":"78259",
    "sg:province":"TX",
    "sg:tags":[
        "merchandise"
    ],
    "wof:name":"Love My Candles",
    "wof:placetype":"venue"
},
  "geometry": {"coordinates":[-98.454047,29.626104],"type":"Point"}
}