{
  "type": "Feature",
  "properties": {
    "iso:country":"US",
    "sg:address":"6621 Fannin St",
    "sg:city":"Houston",
    "sg:classifiers":[
        {
            "category":"Banks & Credit Unions",
            "subcategory":"Bank",
            "type":"Services"
        }
    ],
    "sg:phone":"+1 713 797 1851",
    "sg:postcode":"77030",
    "sg:province":"TX",
    "sg:website":"www.wellsfargo.com/",
    "wof:name":"Wells Fargo",
    "wof:placetype":"venue"
},
  "geometry": {"coordinates":[-95.401015,29.7094],"type":"Point"}
}