{
  "type": "Feature",
  "properties": {
    "iso:country":"US",
    "sg:address":"2612 N A St",
    "sg:city":"Midland",
    "sg:classifiers":[
        {
            "category":"Retail",
            "subcategory":"Repair Shop",
            "type":"Services"
        }
    ],
    "sg:phone":"+1 432 687 3714",
    "sg:postcode":"79705",
    "sg:province":"TX",
    "wof:name":"Eagle Eye Shooting",
    "wof:placetype":"venue"
},
  "geometry": {"coordinates":[-102.089758,32.021092],"type":"Point"}
}