{
  "type": "Feature",
  "properties": {
    "iso:country":"US",
    "sg:address":"1900 W University Dr",
    "sg:city":"Edinburg",
    "sg:classifiers":[
        {
            "category":"Freight",
            "type":"Transportation"
        }
    ],
    "sg:phone":"+1 956 383 4040",
    "sg:postcode":"78539",
    "sg:province":"TX",
    "sg:tags":[
        "a",
        "mail",
        "direct",
        "business"
    ],
    "wof:name":"Lasting Impressions",
    "wof:placetype":"venue"
},
  "geometry": {"coordinates":[-98.182356,26.304218],"type":"Point"}
}