{
  "type": "Feature",
  "properties": {
    "iso:country":"US",
    "sg:address":"7100 High Life Dr",
    "sg:city":"Houston",
    "sg:classifiers":[
        {
            "category":"Organizations",
            "subcategory":"Professional Association",
            "type":"Services"
        }
    ],
    "sg:phone":"+1 281 880 2709",
    "sg:postcode":"77066",
    "sg:province":"TX",
    "wof:name":"Beer Alliance Of Texas",
    "wof:placetype":"venue"
},
  "geometry": {"coordinates":[-95.520883,29.946514],"type":"Point"}
}