{
  "type": "Feature",
  "properties": {
    "iso:country":"US",
    "sg:address":"4108 Fannin",
    "sg:city":"Houston",
    "sg:classifiers":[
        {
            "category":"Personal",
            "subcategory":"Beauty Salon",
            "type":"Services"
        }
    ],
    "sg:phone":"+1 713 527 9877",
    "sg:postcode":"77004",
    "sg:province":"TX",
    "sg:tags":[
        "hair"
    ],
    "wof:name":"Dana Hair Salon",
    "wof:placetype":"venue"
},
  "geometry": {"coordinates":[-95.38088999999999,29.735188],"type":"Point"}
}