{
  "type": "Feature",
  "properties": {
    "iso:country":"US",
    "sg:address":"2239 Co Rd 3304",
    "sg:city":"Greenville",
    "sg:classifiers":[
        {
            "category":"Building & Trades",
            "subcategory":"Plumbing",
            "type":"Services"
        }
    ],
    "sg:phone":"+1 903 455 2010",
    "sg:postcode":"75402",
    "sg:province":"TX",
    "sg:tags":[
        "septic"
    ],
    "wof:name":"M & M Svc",
    "wof:placetype":"venue"
},
  "geometry": {"coordinates":[-96.051547,33.056477],"type":"Point"}
}