{
  "type": "Feature",
  "properties": {
    "iso:country":"US",
    "sg:address":"6601 W Montgomery Rd",
    "sg:city":"Houston",
    "sg:classifiers":[
        {
            "category":"Personal",
            "subcategory":"Beauty Salon",
            "type":"Services"
        }
    ],
    "sg:phone":"+1 713 692 9737",
    "sg:postcode":"77091",
    "sg:province":"TX",
    "sg:tags":[
        "shop"
    ],
    "wof:name":"Susies Corner Hair Salon",
    "wof:placetype":"venue"
},
  "geometry": {"coordinates":[-95.42160800000001,29.857934],"type":"Point"}
}