{
  "type": "Feature",
  "properties": {
    "iso:country":"US",
    "sg:address":"6301 W Parmer Lane",
    "sg:city":"Austin",
    "sg:classifiers":[
        {
            "category":"Retail",
            "subcategory":"Laundry & Dry Cleaning",
            "type":"Services"
        }
    ],
    "sg:phone":"+1 512 250 9988",
    "sg:postcode":"78729",
    "sg:province":"TX",
    "wof:name":"Best Cleaners",
    "wof:placetype":"venue"
},
  "geometry": {"coordinates":[-97.743611,30.44603],"type":"Point"}
}