{
  "type": "Feature",
  "properties": {
    "iso:country":"US",
    "sg:address":"301 San Jacinto St",
    "sg:city":"Houston",
    "sg:classifiers":[
        {
            "category":"Government",
            "subcategory":"Court House",
            "type":"Public Place"
        }
    ],
    "sg:phone":"+1 713 755 5125",
    "sg:postcode":"77002",
    "sg:province":"TX",
    "sg:tags":[
        "state",
        "system"
    ],
    "wof:name":"Harris County JP Court 1-2",
    "wof:placetype":"venue"
},
  "geometry": {"coordinates":[-95.35959200000001,29.760451],"type":"Point"}
}