{
  "type": "Feature",
  "properties": {
    "iso:country":"US",
    "sg:address":"3204 S College Ave",
    "sg:city":"Bryan",
    "sg:classifiers":[
        {
            "category":"Restaurant",
            "type":"Food & Drink"
        }
    ],
    "sg:phone":"+1 979 822 3588",
    "sg:postcode":"77801",
    "sg:province":"TX",
    "wof:name":"A Texan's Restaurant",
    "wof:placetype":"venue"
},
  "geometry": {"coordinates":[-96.357941,30.639287],"type":"Point"}
}