{
  "type": "Feature",
  "properties": {
    "iso:country":"US",
    "sg:address":"7062 McCullough Ave",
    "sg:city":"San Antonio",
    "sg:classifiers":[
        {
            "category":"Professional",
            "subcategory":"Computer Services",
            "type":"Services"
        }
    ],
    "sg:phone":"+1 210 826 4591",
    "sg:postcode":"78216",
    "sg:province":"TX",
    "sg:tags":[
        "related"
    ],
    "wof:name":"McNeel Pleas",
    "wof:placetype":"venue"
},
  "geometry": {"coordinates":[-98.491634,29.496586],"type":"Point"}
}