{
  "type": "Feature",
  "properties": {
    "iso:country":"US",
    "sg:address":"3707 Meredith St",
    "sg:city":"Austin",
    "sg:classifiers":[
        {
            "category":"Real Estate",
            "subcategory":"Architect",
            "type":"Services"
        }
    ],
    "sg:phone":"+1 512 482 8400",
    "sg:postcode":"78703",
    "sg:province":"TX",
    "sg:tags":[
        "architectural"
    ],
    "wof:name":"Bentley & Churchill Architects",
    "wof:placetype":"venue"
},
  "geometry": {"coordinates":[-97.78104,30.29998],"type":"Point"}
}