{
  "type": "Feature",
  "properties": {
    "iso:country":"US",
    "sg:address":"900 W Division St",
    "sg:city":"Arlington",
    "sg:phone":"+1 817 460 5510",
    "sg:postcode":"76012",
    "sg:province":"TX",
    "wof:name":"Caves Lounge",
    "wof:placetype":"venue"
},
  "geometry": {"coordinates":[-97.11734,32.73912],"type":"Point"}
}