{
  "type": "Feature",
  "properties": {
    "iso:country":"US",
    "sg:address":"627 Post Oak Dr",
    "sg:city":"Dripping Springs",
    "sg:classifiers":[
        {
            "category":"Shopping",
            "subcategory":"Used Merchandise",
            "type":"Retail Goods"
        }
    ],
    "sg:phone":"+1 512 894 0298",
    "sg:postcode":"78620",
    "sg:province":"TX",
    "sg:tags":[
        "clothing"
    ],
    "wof:name":"Bridal Bit Annies",
    "wof:placetype":"venue"
},
  "geometry": {"coordinates":[-98.08024399999999,30.172172],"type":"Point"}
}