{
  "type": "Feature",
  "properties": {
    "iso:country":"US",
    "sg:address":"352 N Bibb Ave",
    "sg:city":"Eagle Pass",
    "sg:classifiers":[
        {
            "category":"Building & Trades",
            "subcategory":"Equipment Rental",
            "type":"Services"
        }
    ],
    "sg:phone":"+1 830 773 9553",
    "sg:postcode":"78852",
    "sg:province":"TX",
    "wof:name":"Rent-A-Center",
    "wof:placetype":"venue"
},
  "geometry": {"coordinates":[-100.48320200000001,28.710209],"type":"Point"}
}