{
  "type": "Feature",
  "properties": {
    "iso:country":"US",
    "sg:address":"10 Styling Ct",
    "sg:city":"Houston",
    "sg:classifiers":[
        {
            "category":"Retail",
            "subcategory":"Repair Shop",
            "type":"Services"
        }
    ],
    "sg:phone":"+1 713 631 5832",
    "sg:postcode":"77016",
    "sg:province":"TX",
    "sg:tags":[
        "welding"
    ],
    "wof:name":"F E Jordan Welding",
    "wof:placetype":"venue"
},
  "geometry": {"coordinates":[-95.30918699999999,29.859339],"type":"Point"}
}