{
  "type": "Feature",
  "properties": {
    "iso:country":"US",
    "sg:address":"7554 Sand St",
    "sg:city":"Fort Worth",
    "sg:classifiers":[
        {
            "category":"Manufacturing",
            "subcategory":"Tools & Machinery",
            "type":"Manufacturing & Wholesale Goods"
        }
    ],
    "sg:phone":"+1 817 589 0581",
    "sg:postcode":"76118",
    "sg:province":"TX",
    "sg:tags":[
        "consulting",
        "electric",
        "business",
        "mfg"
    ],
    "wof:name":"Texdyne",
    "wof:placetype":"venue"
},
  "geometry": {"coordinates":[-97.212999,32.795678],"type":"Point"}
}