{
  "type": "Feature",
  "properties": {
    "iso:country":"US",
    "sg:address":"4015 Samuell Blvd",
    "sg:city":"Dallas",
    "sg:classifiers":[
        {
            "category":"Wholesale",
            "subcategory":"Auto Parts",
            "type":"Manufacturing & Wholesale Goods"
        }
    ],
    "sg:phone":"+1 214 275 0510",
    "sg:postcode":"75228",
    "sg:province":"TX",
    "sg:tags":[
        "tire"
    ],
    "wof:name":"J R Lee",
    "wof:placetype":"venue"
},
  "geometry": {"coordinates":[-96.724001,32.793162],"type":"Point"}
}