{
  "type": "Feature",
  "properties": {
    "iso:country":"US",
    "sg:address":"2002 Oak Bend Ln",
    "sg:city":"Garland",
    "sg:classifiers":[
        {
            "category":"Building & Trades",
            "subcategory":"Landscaping Services",
            "type":"Services"
        }
    ],
    "sg:phone":"+1 972 495 1534",
    "sg:postcode":"75040",
    "sg:province":"TX",
    "sg:tags":[
        "landscape"
    ],
    "wof:name":"Bhm Landscape",
    "wof:placetype":"venue"
},
  "geometry": {"coordinates":[-96.601212,32.931376],"type":"Point"}
}