{
  "type": "Feature",
  "properties": {
    "iso:country":"US",
    "sg:address":"4200 Glade Rd",
    "sg:city":"Colleyville",
    "sg:classifiers":[
        {
            "category":"Food & Beverages",
            "subcategory":"Fruits & Vegetables",
            "type":"Retail Goods"
        }
    ],
    "sg:phone":"+1 817 267 6803",
    "sg:postcode":"76034",
    "sg:province":"TX",
    "sg:tags":[
        "produce"
    ],
    "wof:name":"Hall's Grocery & Farmers Otlt",
    "wof:placetype":"venue"
},
  "geometry": {"coordinates":[-97.101934,32.88154],"type":"Point"}
}