{
  "type": "Feature",
  "properties": {
    "iso:country":"US",
    "sg:address":"3549 Almeda Genoa Rd",
    "sg:city":"Houston",
    "sg:classifiers":[
        {
            "category":"Retail",
            "subcategory":"Auto Repair",
            "type":"Services"
        }
    ],
    "sg:phone":"+1 713 733 4215",
    "sg:postcode":"77047",
    "sg:province":"TX",
    "sg:tags":[
        "body",
        "shop"
    ],
    "wof:name":"USA Auto Collision Center",
    "wof:placetype":"venue"
},
  "geometry": {"coordinates":[-95.369862,29.61669],"type":"Point"}
}