{
  "type": "Feature",
  "properties": {
    "iso:country":"US",
    "sg:address":"208 Read St",
    "sg:city":"Silsbee",
    "sg:classifiers":[
        {
            "category":"Education",
            "subcategory":"Special Training",
            "type":"Public Place"
        }
    ],
    "sg:phone":"+1 409 385 6346",
    "sg:postcode":"77656",
    "sg:province":"TX",
    "wof:name":"Ratliff Programs",
    "wof:placetype":"venue"
},
  "geometry": {"coordinates":[-94.173823,30.337668],"type":"Point"}
}