{
  "type": "Feature",
  "properties": {
    "iso:country":"US",
    "sg:address":"103 W 7th St",
    "sg:city":"Georgetown",
    "sg:classifiers":[
        {
            "category":"Government",
            "subcategory":"Office",
            "type":"Public Place"
        }
    ],
    "sg:phone":"+1 512 930 3545",
    "sg:postcode":"78626",
    "sg:province":"TX",
    "sg:tags":[
        "village"
    ],
    "wof:name":"Georgetown Convention & Vstrs",
    "wof:placetype":"venue"
},
  "geometry": {"coordinates":[-97.67804099999999,30.637534],"type":"Point"}
}