{
  "type": "Feature",
  "properties": {
    "iso:country":"US",
    "sg:address":"150 N Ohio Ave",
    "sg:city":"Mercedes",
    "sg:classifiers":[
        {
            "category":"Organizations",
            "subcategory":"Community Association",
            "type":"Services"
        }
    ],
    "sg:phone":"+1 956 565 1451",
    "sg:postcode":"78570",
    "sg:province":"TX",
    "sg:tags":[
        "fraternal"
    ],
    "wof:name":"Knights Of Columbus",
    "wof:placetype":"venue"
},
  "geometry": {"coordinates":[-97.91233099999999,26.152207],"type":"Point"}
}