{
  "type": "Feature",
  "properties": {
    "iso:country":"US",
    "sg:address":"4151 Belt Line Rd",
    "sg:city":"Dallas",
    "sg:classifiers":[
        {
            "category":"Professional",
            "subcategory":"Accounting & Tax Preparation",
            "type":"Services"
        }
    ],
    "sg:phone":"+1 972 818 1040",
    "sg:postcode":"75001",
    "sg:province":"TX",
    "sg:tags":[
        "return",
        "filing"
    ],
    "wof:name":"Quick File Tax Svc",
    "wof:placetype":"venue"
},
  "geometry": {"coordinates":[-96.838967,32.954265],"type":"Point"}
}