{
  "type": "Feature",
  "properties": {
    "iso:country":"US",
    "sg:address":"2627 Manor Rd",
    "sg:city":"Austin",
    "sg:classifiers":[
        {
            "category":"Travel",
            "subcategory":"Hotels & Motels",
            "type":"Entertainment"
        }
    ],
    "sg:phone":"+1 512 476 9033",
    "sg:postcode":"78722",
    "sg:province":"TX",
    "sg:tags":[
        "motion",
        "operation",
        "production"
    ],
    "wof:name":"Ace Motel",
    "wof:placetype":"venue"
},
  "geometry": {"coordinates":[-97.715108,30.284945],"type":"Point"}
}