{
  "type": "Feature",
  "properties": {
    "iso:country":"US",
    "sg:address":"1326 Crosscountry Ln",
    "sg:city":"Laredo",
    "sg:classifiers":[
        {
            "category":"Freight",
            "type":"Transportation"
        }
    ],
    "sg:phone":"+1 956 753 3811",
    "sg:postcode":"78045",
    "sg:province":"TX",
    "sg:tags":[
        "broker",
        "customs"
    ],
    "wof:name":"TFS Custom Brokers",
    "wof:placetype":"venue"
},
  "geometry": {"coordinates":[-99.465548,27.590144],"type":"Point"}
}