{
  "type": "Feature",
  "properties": {
    "iso:country":"US",
    "sg:address":"717 Maxey Rd",
    "sg:city":"Houston",
    "sg:classifiers":[
        {
            "category":"Autos & Motor Vehicles",
            "subcategory":"Auto Supplies",
            "type":"Retail Goods"
        }
    ],
    "sg:phone":"+1 713 637 0106",
    "sg:postcode":"77013",
    "sg:province":"TX",
    "sg:tags":[
        "tire"
    ],
    "wof:name":"Carillo's Tires Service",
    "wof:placetype":"venue"
},
  "geometry": {"coordinates":[-95.218372,29.777545],"type":"Point"}
}