{
  "type": "Feature",
  "properties": {
    "iso:country":"US",
    "sg:address":"4101 E 42nd St",
    "sg:city":"Odessa",
    "sg:classifiers":[
        {
            "category":"Shopping",
            "subcategory":"Clothing, Apparel, & Fashions",
            "type":"Retail Goods"
        }
    ],
    "sg:phone":"+1 432 363 8337",
    "sg:postcode":"79762",
    "sg:province":"TX",
    "sg:website":"www.catosfashions.com",
    "wof:name":"Cato",
    "wof:placetype":"venue"
},
  "geometry": {"coordinates":[-102.339144,31.892384],"type":"Point"}
}