{
  "type": "Feature",
  "properties": {
    "iso:country":"US",
    "sg:address":"7101 W Adams Ave",
    "sg:city":"Temple",
    "sg:classifiers":[
        {
            "category":"Place Of Worship",
            "subcategory":"Church",
            "type":"Public Place"
        },
        {
            "category":"Place Of Worship",
            "type":"Public Place"
        }
    ],
    "sg:phone":"+1 254 778 8983",
    "sg:postcode":"76502",
    "sg:province":"TX",
    "sg:tags":[
        "churches-non-denominational"
    ],
    "wof:name":"Trinity Church Of Tempe",
    "wof:placetype":"venue"
},
  "geometry": {"coordinates":[-97.416191,31.117531],"type":"Point"}
}