{
  "type": "Feature",
  "properties": {
    "iso:country":"US",
    "sg:address":"317 Whispering Trl",
    "sg:city":"Mabank",
    "sg:classifiers":[
        {
            "category":"Building & Trades",
            "subcategory":"Construction",
            "type":"Services"
        }
    ],
    "sg:phone":"+1 903 887 1297",
    "sg:postcode":"75156",
    "sg:province":"TX",
    "sg:tags":[
        "house"
    ],
    "wof:name":"Home Improvements",
    "wof:placetype":"venue"
},
  "geometry": {"coordinates":[-96.105673,32.32289],"type":"Point"}
}