{
  "type": "Feature",
  "properties": {
    "iso:country":"US",
    "sg:address":"11623 Karlwood Ln",
    "sg:city":"Houston",
    "sg:classifiers":[
        {
            "category":"Retail",
            "subcategory":"Auto Repair",
            "type":"Services"
        }
    ],
    "sg:phone":"+1 713 666 0807",
    "sg:postcode":"77099",
    "sg:province":"TX",
    "sg:tags":[
        "mechanic"
    ],
    "wof:name":"Antonio Almazan",
    "wof:placetype":"venue"
},
  "geometry": {"coordinates":[-95.584127,29.678214],"type":"Point"}
}