{
  "type": "Feature",
  "properties": {
    "iso:country":"US",
    "sg:address":"1822 Melisa Ln",
    "sg:city":"Corpus Christi",
    "sg:classifiers":[
        {
            "category":"Farming",
            "subcategory":"Aquatic Farm",
            "type":"Manufacturing & Wholesale Goods"
        }
    ],
    "sg:phone":"+1 361 992 7240",
    "sg:postcode":"78412",
    "sg:province":"TX",
    "wof:name":"Reef Art",
    "wof:placetype":"venue"
},
  "geometry": {"coordinates":[-97.36712900000001,27.698672],"type":"Point"}
}