{
  "type": "Feature",
  "properties": {
    "iso:country":"US",
    "sg:address":"8615 Grandview Dr",
    "sg:city":"Leander",
    "sg:classifiers":[
        {
            "category":"Retail",
            "subcategory":"Photofinishing",
            "type":"Services"
        }
    ],
    "sg:phone":"+1 512 267 0268",
    "sg:postcode":"78645",
    "sg:province":"TX",
    "sg:tags":[
        "photography",
        "studio"
    ],
    "wof:name":"Fotofresh",
    "wof:placetype":"venue"
},
  "geometry": {"coordinates":[-97.93916400000001,30.473219],"type":"Point"}
}