{
  "type": "Feature",
  "properties": {
    "iso:country":"US",
    "sg:address":"3311 Hartfield Ln",
    "sg:city":"Spring",
    "sg:classifiers":[
        {
            "category":"Restaurant",
            "type":"Food & Drink"
        }
    ],
    "sg:phone":"+1 281 350 8174",
    "sg:postcode":"77388",
    "sg:province":"TX",
    "sg:tags":[
        "eating"
    ],
    "wof:name":"Naomis Catfish Express",
    "wof:placetype":"venue"
},
  "geometry": {"coordinates":[-95.46736799999999,30.075892],"type":"Point"}
}