{
  "type": "Feature",
  "properties": {
    "iso:country":"US",
    "sg:address":"115 S Jaycee Ave",
    "sg:city":"Denver City",
    "sg:classifiers":[
        {
            "category":"Real Estate",
            "subcategory":"Real Estate Agent",
            "type":"Services"
        }
    ],
    "sg:phone":"+1 806 592 5120",
    "sg:postcode":"79323",
    "sg:province":"TX",
    "sg:tags":[
        "authorities",
        "housing"
    ],
    "wof:name":"Denver City Housing Authority",
    "wof:placetype":"venue"
},
  "geometry": {"coordinates":[-102.824201,32.964258],"type":"Point"}
}