{
  "type": "Feature",
  "properties": {
    "iso:country":"US",
    "sg:address":"205 N Paradise Dr",
    "sg:city":"Overton",
    "sg:classifiers":[
        {
            "category":"Banks & Credit Unions",
            "subcategory":"Investment Brokerage",
            "type":"Services"
        }
    ],
    "sg:phone":"+1 903 834 6736",
    "sg:postcode":"75684",
    "sg:province":"TX",
    "sg:tags":[
        "security"
    ],
    "wof:name":"Sandoval Investments",
    "wof:placetype":"venue"
},
  "geometry": {"coordinates":[-94.988376,32.277276],"type":"Point"}
}