{
  "type": "Feature",
  "properties": {
    "iso:country":"US",
    "sg:address":"1000 Marina Dr",
    "sg:city":"Montgomery",
    "sg:classifiers":[
        {
            "category":"Restaurant",
            "type":"Food & Drink"
        }
    ],
    "sg:menulink":"http://www.allmenus.com/tx/montgomery/57432-el-dorado-jacks-on-the-lake/menu/",
    "sg:phone":"+1 936 588 3767",
    "sg:postcode":"77356",
    "sg:province":"TX",
    "sg:tags":[
        "american"
    ],
    "wof:name":"El Dorado Jacks On The Lake",
    "wof:placetype":"venue"
},
  "geometry": {"coordinates":[-95.594832,30.363504],"type":"Point"}
}