{
  "type": "Feature",
  "properties": {
    "iso:country":"US",
    "sg:address":"622 N Commercial St",
    "sg:city":"Aransas Pass",
    "sg:classifiers":[
        {
            "category":"Travel",
            "subcategory":"Hotels & Motels",
            "type":"Entertainment"
        }
    ],
    "sg:phone":"+1 361 758 4021",
    "sg:postcode":"78336",
    "sg:province":"TX",
    "wof:name":"Villa Bay Motel",
    "wof:placetype":"venue"
},
  "geometry": {"coordinates":[-97.139746,27.912163],"type":"Point"}
}