{
  "type": "Feature",
  "properties": {
    "iso:country":"US",
    "sg:address":"104 Loop 150",
    "sg:city":"Bastrop",
    "sg:classifiers":[
        {
            "category":"Social Services",
            "type":"Services"
        }
    ],
    "sg:phone":"+1 512 303 1116",
    "sg:postcode":"78602",
    "sg:province":"TX",
    "sg:tags":[
        "organization",
        "welfare"
    ],
    "wof:name":"Blue Bonnet Trails Comm Mhmr",
    "wof:placetype":"venue"
},
  "geometry": {"coordinates":[-97.328884,30.105589],"type":"Point"}
}