{
  "type": "Feature",
  "properties": {
    "iso:country":"US",
    "sg:address":"26 Renoir Trail Pl",
    "sg:city":"Spring",
    "sg:classifiers":[
        {
            "category":"Food & Beverages",
            "subcategory":"Specialty",
            "type":"Retail Goods"
        },
        {
            "category":"Food & Beverages",
            "subcategory":"Groceries & Convenience Stores",
            "type":"Retail Goods"
        }
    ],
    "sg:phone":"+1 281 419 1190",
    "sg:postcode":"77382",
    "sg:province":"TX",
    "sg:tags":[
        "grocers-specialty"
    ],
    "wof:name":"Sisters Blooming Kitchen",
    "wof:placetype":"venue"
},
  "geometry": {"coordinates":[-95.577524,30.18159],"type":"Point"}
}