{
  "type": "Feature",
  "properties": {
    "iso:country":"US",
    "sg:address":"11420 Emerald St Ste 103",
    "sg:city":"Dallas",
    "sg:classifiers":[
        {
            "category":"Health Services",
            "subcategory":"Chiropractor",
            "type":"Services"
        }
    ],
    "sg:phone":"+1 214 358 0240",
    "sg:postcode":"75229",
    "sg:province":"TX",
    "wof:name":"Well-Being Chiropractic Clinic",
    "wof:placetype":"venue"
},
  "geometry": {"coordinates":[-96.899056,32.896672],"type":"Point"}
}