{
  "type": "Feature",
  "properties": {
    "iso:country":"US",
    "sg:address":"8346 Alderon Ln",
    "sg:city":"Frisco",
    "sg:classifiers":[
        {
            "category":"Professional",
            "subcategory":"Computer Services",
            "type":"Services"
        }
    ],
    "sg:phone":"+1 972 668 3220",
    "sg:postcode":"75034",
    "sg:province":"TX",
    "sg:tags":[
        "prepackaged",
        "software"
    ],
    "wof:name":"Computech Software",
    "wof:placetype":"venue"
},
  "geometry": {"coordinates":[-96.871673,33.14768],"type":"Point"}
}