{
  "type": "Feature",
  "properties": {
    "iso:country":"US",
    "sg:address":"1051 County Road 290",
    "sg:city":"Leander",
    "sg:classifiers":[
        {
            "category":"Professional",
            "subcategory":"Computer Services",
            "type":"Services"
        }
    ],
    "sg:phone":"+1 512 259 0966",
    "sg:postcode":"78641",
    "sg:province":"TX",
    "sg:tags":[
        "repair"
    ],
    "sg:website":"www.1customsystems.com",
    "wof:name":"Custom Systems",
    "wof:placetype":"venue"
},
  "geometry": {"coordinates":[-97.91330000000001,30.566099],"type":"Point"}
}