{
  "type": "Feature",
  "properties": {
    "iso:country":"US",
    "sg:address":"2600 FM 1764",
    "sg:city":"La Marque",
    "sg:classifiers":[
        {
            "category":"Wholesale",
            "subcategory":"Machinery & Supplies",
            "type":"Manufacturing & Wholesale Goods"
        }
    ],
    "sg:phone":"+1 409 978 2219",
    "sg:postcode":"77568",
    "sg:province":"TX",
    "sg:tags":[
        "salon",
        "beauty"
    ],
    "wof:name":"Sally Beauty Supply",
    "wof:placetype":"venue"
},
  "geometry": {"coordinates":[-95.036491,29.400086],"type":"Point"}
}