{
  "type": "Feature",
  "properties": {
    "iso:country":"US",
    "sg:address":"601 W Cheryl Ave",
    "sg:city":"Hurst",
    "sg:classifiers":[
        {
            "category":"Building & Trades",
            "subcategory":"Pest Control",
            "type":"Services"
        }
    ],
    "sg:phone":"+1 817 282 2188",
    "sg:postcode":"76053",
    "sg:province":"TX",
    "wof:name":"All Seasons Pest Control",
    "wof:placetype":"venue"
},
  "geometry": {"coordinates":[-97.182464,32.827014],"type":"Point"}
}