{
  "type": "Feature",
  "properties": {
    "iso:country":"US",
    "sg:address":"13131 Louetta Rd",
    "sg:city":"Cypress",
    "sg:classifiers":[
        {
            "category":"Restaurant",
            "type":"Food & Drink"
        }
    ],
    "sg:phone":"+1 832 717 4007",
    "sg:postcode":"77429",
    "sg:province":"TX",
    "sg:tags":[
        "eating"
    ],
    "wof:name":"Bond's Sports Grille",
    "wof:placetype":"venue"
},
  "geometry": {"coordinates":[-95.62207600000001,29.995109],"type":"Point"}
}