{
  "type": "Feature",
  "properties": {
    "iso:country":"US",
    "sg:address":"1703 Bertram Dr",
    "sg:city":"Mansfield",
    "sg:classifiers":[
        {
            "category":"Shopping",
            "subcategory":"Gifts & Souvenirs",
            "type":"Retail Goods"
        }
    ],
    "sg:phone":"+1 817 477 0823",
    "sg:postcode":"76063",
    "sg:province":"TX",
    "wof:name":"A ROC Gifts",
    "wof:placetype":"venue"
},
  "geometry": {"coordinates":[-97.17112899999999,32.589836],"type":"Point"}
}