{
  "type": "Feature",
  "properties": {
    "iso:country":"US",
    "sg:address":"306 Bedford Rd",
    "sg:city":"El Paso",
    "sg:classifiers":[
        {
            "category":"Shopping",
            "subcategory":"Hobbies, Toys, & Games",
            "type":"Retail Goods"
        }
    ],
    "sg:phone":"+1 915 587 9382",
    "sg:postcode":"79922",
    "sg:province":"TX",
    "sg:tags":[
        "craft"
    ],
    "wof:name":"TAF & Brooke",
    "wof:placetype":"venue"
},
  "geometry": {"coordinates":[-106.56997800000001,31.817395],"type":"Point"}
}