{
  "type": "Feature",
  "properties": {
    "iso:country":"US",
    "sg:address":"11962 Westheimer Rd",
    "sg:city":"Houston",
    "sg:classifiers":[
        {
            "category":"Shopping",
            "type":"Retail Goods"
        }
    ],
    "sg:phone":"+1 281 920 0094",
    "sg:postcode":"77077",
    "sg:province":"TX",
    "sg:tags":[
        "cosmetic",
        "perfume"
    ],
    "wof:name":"Nixi Beauty Supply",
    "wof:placetype":"venue"
},
  "geometry": {"coordinates":[-95.591362,29.736506],"type":"Point"}
}