{
  "type": "Feature",
  "properties": {
    "iso:country":"US",
    "sg:address":"109 N Post Oak Ln",
    "sg:city":"Houston",
    "sg:classifiers":[
        {
            "category":"Banks & Credit Unions",
            "subcategory":"Investment Brokerage",
            "type":"Services"
        }
    ],
    "sg:phone":"+1 713 957 7000",
    "sg:postcode":"77024",
    "sg:province":"TX",
    "sg:tags":[
        "security"
    ],
    "wof:name":"UBS Financial Services Inc",
    "wof:placetype":"venue"
},
  "geometry": {"coordinates":[-95.457561,29.766088],"type":"Point"}
}