{
  "type": "Feature",
  "properties": {
    "iso:country":"US",
    "sg:address":"203 Creekbend Dr",
    "sg:city":"Brownsville",
    "sg:classifiers":[
        {
            "category":"Shopping",
            "subcategory":"Hobbies, Toys, & Games",
            "type":"Retail Goods"
        }
    ],
    "sg:phone":"+1 956 541 6388",
    "sg:postcode":"78521",
    "sg:province":"TX",
    "wof:name":"Norma Sonia Villalon",
    "wof:placetype":"venue"
},
  "geometry": {"coordinates":[-97.46420999999999,25.93571],"type":"Point"}
}