{
  "type": "Feature",
  "properties": {
    "iso:country":"US",
    "sg:address":"7371 Park Ln",
    "sg:city":"Dallas",
    "sg:classifiers":[
        {
            "category":"Retail",
            "subcategory":"Self-service Laundry",
            "type":"Services"
        }
    ],
    "sg:phone":"+1 214 891 1464",
    "sg:postcode":"75225",
    "sg:province":"TX",
    "sg:tags":[
        "coin"
    ],
    "wof:name":"VS Washette",
    "wof:placetype":"venue"
},
  "geometry": {"coordinates":[-96.77918,32.872136],"type":"Point"}
}