{
  "type": "Feature",
  "properties": {
    "iso:country":"US",
    "sg:address":"6218 Abington Way",
    "sg:city":"Houston",
    "sg:classifiers":[
        {
            "category":"Building & Trades",
            "subcategory":"Construction",
            "type":"Services"
        }
    ],
    "sg:phone":"+1 713 862 5262",
    "sg:postcode":"77008",
    "sg:province":"TX",
    "sg:tags":[
        "carpentry",
        "contractor"
    ],
    "wof:name":"Tejas Contract Carpentry",
    "wof:placetype":"venue"
},
  "geometry": {"coordinates":[-95.42319999999999,29.788748],"type":"Point"}
}