{
  "type": "Feature",
  "properties": {
    "iso:country":"US",
    "sg:address":"607 US Hwy 83",
    "sg:city":"Zapata",
    "sg:classifiers":[
        {
            "category":"Government",
            "subcategory":"Office",
            "type":"Public Place"
        }
    ],
    "sg:phone":"+1 956 765 4851",
    "sg:postcode":"78076",
    "sg:province":"TX",
    "sg:tags":[
        "state",
        "program",
        "health"
    ],
    "wof:name":"Public Health Dept",
    "wof:placetype":"venue"
},
  "geometry": {"coordinates":[-99.267247,26.901789],"type":"Point"}
}