{
  "type": "Feature",
  "properties": {
    "iso:country":"US",
    "sg:address":"19 Thistlewood Pl",
    "sg:city":"Spring",
    "sg:classifiers":[
        {
            "category":"Professional",
            "type":"Services"
        }
    ],
    "sg:phone":"+1 281 292 3505",
    "sg:postcode":"77381",
    "sg:province":"TX",
    "wof:name":"Dambrosio & Co",
    "wof:placetype":"venue"
},
  "geometry": {"coordinates":[-95.50895199999999,30.185852],"type":"Point"}
}