{
  "type": "Feature",
  "properties": {
    "iso:country":"US",
    "sg:address":"14775 Midway Rd",
    "sg:city":"Addison",
    "sg:classifiers":[
        {
            "category":"Professional",
            "type":"Services"
        }
    ],
    "sg:phone":"+1 214 691 4444",
    "sg:postcode":"75001",
    "sg:province":"TX",
    "sg:tags":[
        "caterer"
    ],
    "wof:name":"Wall's Catering & Party Productions",
    "wof:placetype":"venue"
},
  "geometry": {"coordinates":[-96.839117,32.949683],"type":"Point"}
}