{
  "type": "Feature",
  "properties": {
    "iso:country":"US",
    "sg:address":"2300 Karbach St",
    "sg:city":"Houston",
    "sg:classifiers":[
        {
            "category":"Building & Trades",
            "subcategory":"Construction",
            "type":"Services"
        }
    ],
    "sg:phone":"+1 713 680 0344",
    "sg:postcode":"77092",
    "sg:province":"TX",
    "sg:tags":[
        "general",
        "contractor"
    ],
    "wof:name":"Cypress Estate Homs",
    "wof:placetype":"venue"
},
  "geometry": {"coordinates":[-95.461164,29.807583],"type":"Point"}
}