{
  "type": "Feature",
  "properties": {
    "iso:country":"US",
    "sg:address":"3375 N Belt Line Rd",
    "sg:city":"Grand Prairie",
    "sg:classifiers":[
        {
            "category":"Organizations",
            "subcategory":"Community Association",
            "type":"Services"
        }
    ],
    "sg:phone":"+1 972 790 1611",
    "sg:postcode":"75050",
    "sg:province":"TX",
    "sg:tags":[
        "military"
    ],
    "wof:name":"Veterans Of Foreign Wars",
    "wof:placetype":"venue"
},
  "geometry": {"coordinates":[-96.99475,32.773818],"type":"Point"}
}