{
  "type": "Feature",
  "properties": {
    "iso:country":"US",
    "sg:address":"402 W Lamar St",
    "sg:city":"Sherman",
    "sg:classifiers":[
        {
            "category":"Organizations",
            "subcategory":"Community Association",
            "type":"Services"
        }
    ],
    "sg:phone":"+1 903 892 8766",
    "sg:postcode":"75090",
    "sg:province":"TX",
    "sg:tags":[
        "educational"
    ],
    "wof:name":"Junior Achievement Of Grayson",
    "wof:placetype":"venue"
},
  "geometry": {"coordinates":[-96.615144,33.634268],"type":"Point"}
}