{
  "type": "Feature",
  "properties": {
    "iso:country":"US",
    "sg:address":"11330 Sagecreek Dr",
    "sg:city":"Houston",
    "sg:classifiers":[
        {
            "category":"Wholesale",
            "subcategory":"Vending Machines",
            "type":"Manufacturing & Wholesale Goods"
        }
    ],
    "sg:phone":"+1 281 481 6747",
    "sg:postcode":"77089",
    "sg:province":"TX",
    "sg:tags":[
        "operator"
    ],
    "wof:name":"Triple T Enterprises",
    "wof:placetype":"venue"
},
  "geometry": {"coordinates":[-95.215965,29.593074],"type":"Point"}
}