{
  "type": "Feature",
  "properties": {
    "iso:country":"US",
    "sg:address":"2505 7th Ave",
    "sg:city":"Canyon",
    "sg:classifiers":[
        {
            "category":"Shopping",
            "subcategory":"Gifts & Souvenirs",
            "type":"Retail Goods"
        }
    ],
    "sg:phone":"+1 806 655 1740",
    "sg:postcode":"79015",
    "sg:province":"TX",
    "wof:name":"Best of Times",
    "wof:placetype":"venue"
},
  "geometry": {"coordinates":[-101.915538,34.976772],"type":"Point"}
}