{
  "type": "Feature",
  "properties": {
    "iso:country":"US",
    "sg:address":"5 Boca Chica Blvd",
    "sg:city":"Brownsville",
    "sg:classifiers":[
        {
            "category":"Government",
            "subcategory":"Police Station",
            "type":"Public Place"
        }
    ],
    "sg:phone":"+1 956 541 5500",
    "sg:postcode":"78520",
    "sg:province":"TX",
    "sg:tags":[
        "state"
    ],
    "wof:name":"Narcotics Dept",
    "wof:placetype":"venue"
},
  "geometry": {"coordinates":[-97.520064,25.926767],"type":"Point"}
}