{
  "type": "Feature",
  "properties": {
    "iso:country":"US",
    "sg:address":"5529 Weslayan St",
    "sg:city":"Houston",
    "sg:classifiers":[
        {
            "category":"Restaurant",
            "type":"Food & Drink"
        }
    ],
    "sg:menulink":"http://www.allmenus.com/tx/houston/49381-skeeters-mesquite-grill/menu/",
    "sg:phone":"+1 713 660 7090",
    "sg:postcode":"77005",
    "sg:province":"TX",
    "sg:tags":[
        "new",
        "american"
    ],
    "wof:name":"Skeeter's Mesquite Grill",
    "wof:placetype":"venue"
},
  "geometry": {"coordinates":[-95.441247,29.723633],"type":"Point"}
}