{
  "type": "Feature",
  "properties": {
    "iso:country":"US",
    "sg:address":"1609 23rd St",
    "sg:city":"Galveston",
    "sg:classifiers":[
        {
            "category":"Health Services",
            "subcategory":"Clinic",
            "type":"Services"
        }
    ],
    "sg:phone":"+1 409 763 6800",
    "sg:postcode":"77550",
    "sg:province":"TX",
    "sg:tags":[
        "home"
    ],
    "wof:name":"Sigma Health Care Inc",
    "wof:placetype":"venue"
},
  "geometry": {"coordinates":[-94.789962,29.293942],"type":"Point"}
}