{
  "type": "Feature",
  "properties": {
    "iso:country":"US",
    "sg:address":"617 E Davis St",
    "sg:city":"Conroe",
    "sg:classifiers":[
        {
            "category":"Shopping",
            "subcategory":"Bicycles & Sporting Goods",
            "type":"Retail Goods"
        }
    ],
    "sg:phone":"+1 936 539 5106",
    "sg:postcode":"77301",
    "sg:province":"TX",
    "wof:name":"Cowboy Way Rodeo & Tack",
    "wof:placetype":"venue"
},
  "geometry": {"coordinates":[-95.449991,30.314178],"type":"Point"}
}