{
  "type": "Feature",
  "properties": {
    "iso:country":"US",
    "sg:address":"7613 Spring Cypress Rd",
    "sg:city":"Spring",
    "sg:classifiers":[
        {
            "category":"Real Estate",
            "subcategory":"Real Estate Agent",
            "type":"Services"
        }
    ],
    "sg:phone":"+1 281 217 3334",
    "sg:postcode":"77379",
    "sg:province":"TX",
    "wof:name":"Spring Stubner 53 Inc",
    "wof:placetype":"venue"
},
  "geometry": {"coordinates":[-95.54047799999999,30.04493],"type":"Point"}
}