{
  "type": "Feature",
  "properties": {
    "iso:country":"US",
    "sg:address":"2301 Yorktown St",
    "sg:city":"Houston",
    "sg:classifiers":[
        {
            "category":"Retail",
            "subcategory":"Portrait Studio",
            "type":"Services"
        }
    ],
    "sg:phone":"+1 713 961 2840",
    "sg:postcode":"77056",
    "sg:province":"TX",
    "sg:tags":[
        "photo"
    ],
    "wof:name":"Select Studios",
    "wof:placetype":"venue"
},
  "geometry": {"coordinates":[-95.47074499999999,29.743273],"type":"Point"}
}