{
  "type": "Feature",
  "properties": {
    "iso:country":"US",
    "sg:address":"227 N Columbia Dr",
    "sg:city":"West Columbia",
    "sg:classifiers":[
        {
            "category":"Building & Trades",
            "subcategory":"Cleaning & Sanitation",
            "type":"Services"
        }
    ],
    "sg:phone":"+1 979 345 7337",
    "sg:postcode":"77486",
    "sg:province":"TX",
    "sg:tags":[
        "maintenance"
    ],
    "wof:name":"Griggs Cleaning Service",
    "wof:placetype":"venue"
},
  "geometry": {"coordinates":[-95.660006,29.150766],"type":"Point"}
}