{
  "type": "Feature",
  "properties": {
    "iso:country":"US",
    "sg:address":"8300 Hornet Dr",
    "sg:city":"Austin",
    "sg:classifiers":[
        {
            "category":"Shopping",
            "type":"Retail Goods"
        }
    ],
    "sg:phone":"+1 512 291 0025",
    "sg:postcode":"78749",
    "sg:province":"TX",
    "sg:tags":[
        "item",
        "boutique"
    ],
    "wof:name":"Blue Icing",
    "wof:placetype":"venue"
},
  "geometry": {"coordinates":[-97.83972900000001,30.201361],"type":"Point"}
}