{
  "type": "Feature",
  "properties": {
    "iso:country":"US",
    "sg:address":"7004 Sao Paulo Ct",
    "sg:city":"Fort Worth",
    "sg:classifiers":[
        {
            "category":"Building & Trades",
            "subcategory":"Landscaping Services",
            "type":"Services"
        }
    ],
    "sg:phone":"+1 817 428 5360",
    "sg:postcode":"76180",
    "sg:province":"TX",
    "wof:name":"Cates Lawn & Landscaping",
    "wof:placetype":"venue"
},
  "geometry": {"coordinates":[-97.22919899999999,32.848634],"type":"Point"}
}