{
  "type": "Feature",
  "properties": {
    "iso:country":"US",
    "sg:address":"212 N Texas St",
    "sg:city":"Rio Grande City",
    "sg:classifiers":[
        {
            "category":"Banks & Credit Unions",
            "subcategory":"Bank",
            "type":"Services"
        }
    ],
    "sg:phone":"+1 956 716 8774",
    "sg:postcode":"78582",
    "sg:province":"TX",
    "sg:tags":[
        "loan"
    ],
    "wof:name":"World Finance Corp",
    "wof:placetype":"venue"
},
  "geometry": {"coordinates":[-98.82116600000001,26.380963],"type":"Point"}
}