{
  "type": "Feature",
  "properties": {
    "iso:country":"US",
    "sg:address":"3825 Guadalupe St",
    "sg:city":"Austin",
    "sg:classifiers":[
        {
            "category":"Retail",
            "subcategory":"Auto Repair",
            "type":"Services"
        }
    ],
    "sg:phone":"+1 512 452 1108",
    "sg:postcode":"78751",
    "sg:province":"TX",
    "sg:tags":[
        "automobile",
        "lubrication"
    ],
    "wof:name":"Shell Rapid Lube",
    "wof:placetype":"venue"
},
  "geometry": {"coordinates":[-97.737247,30.304002],"type":"Point"}
}