{
  "type": "Feature",
  "properties": {
    "iso:country":"US",
    "sg:address":"8309 Westchester Dr",
    "sg:city":"Dallas",
    "sg:classifiers":[
        {
            "category":"Personal",
            "subcategory":"Nail Salon",
            "type":"Services"
        }
    ],
    "sg:phone":"+1 214 750 6410",
    "sg:postcode":"75225",
    "sg:province":"TX",
    "wof:name":"Hollywood Nail & Spa",
    "wof:placetype":"venue"
},
  "geometry": {"coordinates":[-96.806591,32.864297],"type":"Point"}
}