{
  "type": "Feature",
  "properties": {
    "iso:country":"US",
    "sg:address":"19454 Enchanted Stream Dr",
    "sg:city":"Spring",
    "sg:classifiers":[
        {
            "category":"Real Estate",
            "subcategory":"Real Estate Agent",
            "type":"Services"
        }
    ],
    "sg:phone":"+1 281 350 8261",
    "sg:postcode":"77388",
    "sg:province":"TX",
    "sg:tags":[
        "appraiser"
    ],
    "wof:name":"Southern Appraisal Service",
    "wof:placetype":"venue"
},
  "geometry": {"coordinates":[-95.445117,30.04321],"type":"Point"}
}