{
  "type": "Feature",
  "properties": {
    "iso:country":"US",
    "sg:address":"7258 Fernview",
    "sg:city":"San Antonio",
    "sg:classifiers":[
        {
            "category":"Professional",
            "subcategory":"Business Services",
            "type":"Services"
        }
    ],
    "sg:phone":"+1 210 767 1155",
    "sg:postcode":"78250",
    "sg:province":"TX",
    "sg:tags":[
        "appraiser"
    ],
    "wof:name":"Precision Investigative",
    "wof:placetype":"venue"
},
  "geometry": {"coordinates":[-98.68857,29.506444],"type":"Point"}
}