{
  "type": "Feature",
  "properties": {
    "iso:country":"US",
    "sg:address":"4970 W Highway 290",
    "sg:city":"Austin",
    "sg:classifiers":[
        {
            "category":"Shopping",
            "subcategory":"Tobacco",
            "type":"Retail Goods"
        },
        {
            "category":"Food & Beverages",
            "subcategory":"Liquor & Beverages",
            "type":"Retail Goods"
        }
    ],
    "sg:phone":"+1 512 892 2010",
    "sg:postcode":"78735",
    "sg:province":"TX",
    "sg:tags":[
        "cigar",
        "cigarette",
        "beer",
        "spirit",
        "store",
        "wine"
    ],
    "wof:name":"Specs",
    "wof:placetype":"venue"
},
  "geometry": {"coordinates":[-97.81870600000001,30.233675],"type":"Point"}
}