{
  "type": "Feature",
  "properties": {
    "iso:country":"US",
    "sg:address":"1170 Corporate Dr W",
    "sg:city":"Arlington",
    "sg:classifiers":[
        {
            "category":"Professional",
            "subcategory":"Employment Agencies",
            "type":"Services"
        }
    ],
    "sg:phone":"+1 817 695 9005",
    "sg:postcode":"76006",
    "sg:province":"TX",
    "wof:name":"Prospect Airport Services",
    "wof:placetype":"venue"
},
  "geometry": {"coordinates":[-97.068073,32.763509],"type":"Point"}
}