{
  "type": "Feature",
  "properties": {
    "iso:country":"US",
    "sg:address":"277 Co Rd 37",
    "sg:city":"Tyler",
    "sg:classifiers":[
        {
            "category":"Professional",
            "subcategory":"Detective & Security Services",
            "type":"Services"
        }
    ],
    "sg:phone":"+1 903 531 0190",
    "sg:postcode":"75706",
    "sg:province":"TX",
    "sg:tags":[
        "car"
    ],
    "wof:name":"E F Mark",
    "wof:placetype":"venue"
},
  "geometry": {"coordinates":[-95.283664,32.414311],"type":"Point"}
}