{
  "type": "Feature",
  "properties": {
    "iso:country":"US",
    "sg:address":"2000 San Jacinto Mall",
    "sg:city":"Baytown",
    "sg:classifiers":[
        {
            "category":"Shopping",
            "subcategory":"Department Store",
            "type":"Retail Goods"
        }
    ],
    "sg:phone":"+1 281 421 2354",
    "sg:postcode":"77521",
    "sg:province":"TX",
    "wof:name":"J C Penney Co",
    "wof:placetype":"venue"
},
  "geometry": {"coordinates":[-94.985292,29.803371],"type":"Point"}
}