{
  "type": "Feature",
  "properties": {
    "iso:country":"US",
    "sg:address":"708 Fresno St",
    "sg:city":"Zapata",
    "sg:classifiers":[
        {
            "category":"Personal",
            "subcategory":"Beauty Salon",
            "type":"Services"
        }
    ],
    "sg:phone":"+1 956 765 4980",
    "sg:postcode":"78076",
    "sg:province":"TX",
    "wof:name":"New Look Beauty Salon",
    "wof:placetype":"venue"
},
  "geometry": {"coordinates":[-99.264602,26.903676],"type":"Point"}
}