{
  "type": "Feature",
  "properties": {
    "iso:country":"US",
    "sg:address":"14955 Stonelick Bridge Ln",
    "sg:city":"Sugar Land",
    "sg:classifiers":[
        {
            "category":"Professional",
            "subcategory":"Accounting & Tax Preparation",
            "type":"Services"
        }
    ],
    "sg:phone":"+1 713 459 4326",
    "sg:postcode":"77478",
    "sg:province":"TX",
    "wof:name":"Northwest Billing Corp",
    "wof:placetype":"venue"
},
  "geometry": {"coordinates":[-95.643732,29.659113],"type":"Point"}
}