{
  "type": "Feature",
  "properties": {
    "iso:country":"US",
    "sg:address":"138 Wagon Wheel Rd",
    "sg:city":"Wylie",
    "sg:classifiers":[
        {
            "category":"Professional",
            "type":"Services"
        }
    ],
    "sg:phone":"+1 972 463 1125",
    "sg:postcode":"75098",
    "sg:province":"TX",
    "wof:name":"Joseph Sullivan LLC",
    "wof:placetype":"venue"
},
  "geometry": {"coordinates":[-96.53080799999999,32.974575],"type":"Point"}
}