{
  "type": "Feature",
  "properties": {
    "iso:country":"US",
    "sg:address":"2604 Commerce St",
    "sg:city":"Marble Falls",
    "sg:classifiers":[
        {
            "category":"Professional",
            "type":"Services"
        }
    ],
    "sg:phone":"+1 830 798 8862",
    "sg:postcode":"78654",
    "sg:province":"TX",
    "sg:tags":[
        "wood",
        "specialty"
    ],
    "wof:name":"R & R Custom Woodworks",
    "wof:placetype":"venue"
},
  "geometry": {"coordinates":[-98.269131,30.595934],"type":"Point"}
}