{
  "type": "Feature",
  "properties": {
    "iso:country":"US",
    "sg:address":"4449 Co Rd 207",
    "sg:city":"Liberty Hill",
    "sg:classifiers":[
        {
            "category":"Retail",
            "subcategory":"Repair Shop",
            "type":"Services"
        }
    ],
    "sg:phone":"+1 512 778 6200",
    "sg:postcode":"78642",
    "sg:province":"TX",
    "sg:tags":[
        "appliance"
    ],
    "wof:name":"Service First",
    "wof:placetype":"venue"
},
  "geometry": {"coordinates":[-97.90296499999999,30.76268],"type":"Point"}
}