{
  "type": "Feature",
  "properties": {
    "iso:country":"US",
    "sg:address":"437 Lancer Lake Dr",
    "sg:city":"Brownsville",
    "sg:classifiers":[
        {
            "category":"Building & Trades",
            "subcategory":"Construction",
            "type":"Services"
        }
    ],
    "sg:phone":"+1 956 371 1240",
    "sg:postcode":"78521",
    "sg:province":"TX",
    "sg:tags":[
        "house"
    ],
    "wof:name":"S Espinosa Builders",
    "wof:placetype":"venue"
},
  "geometry": {"coordinates":[-97.475326,25.9275],"type":"Point"}
}