{
  "type": "Feature",
  "properties": {
    "iso:country":"US",
    "sg:address":"110 Triple Creek Dr",
    "sg:city":"Longview",
    "sg:classifiers":[
        {
            "category":"Shopping",
            "subcategory":"Department Store",
            "type":"Retail Goods"
        }
    ],
    "sg:phone":"+1 903 757 6838",
    "sg:postcode":"75601",
    "sg:province":"TX",
    "wof:name":"Wal-Mart",
    "wof:placetype":"venue"
},
  "geometry": {"coordinates":[-94.740005,32.518476],"type":"Point"}
}