{
  "type": "Feature",
  "properties": {
    "iso:country":"US",
    "sg:address":"3608 E 29th St Ste 111",
    "sg:city":"Bryan",
    "sg:classifiers":[
        {
            "category":"Wholesale",
            "subcategory":"Books, Periodicals, & Newspapers",
            "type":"Manufacturing & Wholesale Goods"
        }
    ],
    "sg:phone":"+1 979 422 4096",
    "sg:postcode":"77802",
    "sg:province":"TX",
    "sg:tags":[
        "publisher",
        "book"
    ],
    "wof:name":"Aboutown Press",
    "wof:placetype":"venue"
},
  "geometry": {"coordinates":[-96.335159,30.650986],"type":"Point"}
}