{
  "type": "Feature",
  "properties": {
    "iso:country":"US",
    "sg:address":"1631 Adobe Square Dr",
    "sg:city":"San Antonio",
    "sg:classifiers":[
        {
            "category":"Professional",
            "subcategory":"Computer Services",
            "type":"Services"
        }
    ],
    "sg:phone":"+1 210 288 8547",
    "sg:postcode":"78232",
    "sg:province":"TX",
    "sg:tags":[
        "implementation",
        "procurement",
        "software"
    ],
    "wof:name":"ASAP Consulting Group LLC",
    "wof:placetype":"venue"
},
  "geometry": {"coordinates":[-98.466281,29.564927],"type":"Point"}
}