{
  "type": "Feature",
  "properties": {
    "iso:country":"US",
    "sg:address":"109 N Mount St",
    "sg:city":"Fairfield",
    "sg:classifiers":[
        {
            "category":"Organizations",
            "subcategory":"Religious Organization",
            "type":"Services"
        },
        {
            "category":"Shopping",
            "subcategory":"Books",
            "type":"Retail Goods"
        }
    ],
    "sg:phone":"+1 903 389 2955",
    "sg:postcode":"75840",
    "sg:province":"TX",
    "sg:tags":[
        "dealer"
    ],
    "wof:name":"First Love Mins Bible Bookstor",
    "wof:placetype":"venue"
},
  "geometry": {"coordinates":[-96.160523,31.72707],"type":"Point"}
}