{
  "type": "Feature",
  "properties": {
    "iso:country":"US",
    "sg:address":"5500 Berry Brook Dr",
    "sg:city":"Houston",
    "sg:classifiers":[
        {
            "category":"Wholesale",
            "subcategory":"Computers",
            "type":"Manufacturing & Wholesale Goods"
        }
    ],
    "sg:phone":"+1 713 490 2395",
    "sg:postcode":"77017",
    "sg:province":"TX",
    "sg:website":"www.veritechnology.com",
    "wof:name":"Veritechnology",
    "wof:placetype":"venue"
},
  "geometry": {"coordinates":[-95.24947400000001,29.675055],"type":"Point"}
}