{
  "type": "Feature",
  "properties": {
    "iso:country":"US",
    "sg:address":"713 Kingston Lacy Blvd",
    "sg:city":"Pflugerville",
    "sg:classifiers":[
        {
            "category":"Professional",
            "subcategory":"Business Services",
            "type":"Services"
        }
    ],
    "sg:phone":"+1 512 658 5614",
    "sg:postcode":"78660",
    "sg:province":"TX",
    "wof:name":"Surplus Deals",
    "wof:placetype":"venue"
},
  "geometry": {"coordinates":[-97.612742,30.473097],"type":"Point"}
}