{
  "type": "Feature",
  "properties": {
    "iso:country":"US",
    "sg:address":"1907 Richmond Rd",
    "sg:city":"Texarkana",
    "sg:classifiers":[
        {
            "category":"Personal",
            "subcategory":"Beauty Salon",
            "type":"Services"
        }
    ],
    "sg:phone":"+1 903 223 6648",
    "sg:postcode":"75503",
    "sg:province":"TX",
    "sg:tags":[
        "shop"
    ],
    "wof:name":"All About Face",
    "wof:placetype":"venue"
},
  "geometry": {"coordinates":[-94.082522,33.453312],"type":"Point"}
}