{
  "type": "Feature",
  "properties": {
    "iso:country":"US",
    "sg:address":"1234 Co Rd 416",
    "sg:city":"Nemo",
    "sg:classifiers":[
        {
            "category":"Shopping",
            "subcategory":"Computers & Home Electronics",
            "type":"Retail Goods"
        }
    ],
    "sg:phone":"+1 254 897 3668",
    "sg:postcode":"76070",
    "sg:province":"TX",
    "sg:tags":[
        "software"
    ],
    "wof:name":"John M Joslin Inc",
    "wof:placetype":"venue"
},
  "geometry": {"coordinates":[-97.68493100000001,32.249803],"type":"Point"}
}