{
  "type": "Feature",
  "properties": {
    "iso:country":"US",
    "sg:address":"28890 I- 10 W",
    "sg:city":"Boerne",
    "sg:classifiers":[
        {
            "category":"Wholesale",
            "subcategory":"Construction Materials",
            "type":"Manufacturing & Wholesale Goods"
        }
    ],
    "sg:phone":"+1 830 981 9089",
    "sg:postcode":"78006",
    "sg:province":"TX",
    "sg:tags":[
        "brick",
        "common",
        "face"
    ],
    "wof:name":"Claymex Brick & Tile",
    "wof:placetype":"venue"
},
  "geometry": {"coordinates":[-98.690113,29.740745],"type":"Point"}
}