{
  "type": "Feature",
  "properties": {
    "iso:country":"US",
    "sg:address":"116 S 16th St",
    "sg:city":"Waco",
    "sg:classifiers":[
        {
            "category":"Bars & Pubs",
            "type":"Food & Drink"
        }
    ],
    "sg:phone":"+1 254 752 2027",
    "sg:postcode":"76701",
    "sg:province":"TX",
    "sg:tags":[
        "drinking"
    ],
    "wof:name":"El Ranchito",
    "wof:placetype":"venue"
},
  "geometry": {"coordinates":[-97.140991,31.547297],"type":"Point"}
}