{
  "type": "Feature",
  "properties": {
    "iso:country":"US",
    "sg:address":"12226 Ticonderoga Rd",
    "sg:city":"Houston",
    "sg:classifiers":[
        {
            "category":"Freight",
            "type":"Transportation"
        }
    ],
    "sg:phone":"+1 281 458 6039",
    "sg:postcode":"77044",
    "sg:province":"TX",
    "sg:tags":[
        "operator",
        "local",
        "trucking"
    ],
    "wof:name":"G&S Herrea Trucking",
    "wof:placetype":"venue"
},
  "geometry": {"coordinates":[-95.215785,29.845718],"type":"Point"}
}