{
  "type": "Feature",
  "properties": {
    "iso:country":"US",
    "sg:address":"3635 Willowbend Blvd",
    "sg:city":"Houston",
    "sg:classifiers":[
        {
            "category":"Manufacturing",
            "subcategory":"Rubber & Plastics",
            "type":"Manufacturing & Wholesale Goods"
        },
        {
            "category":"Autos & Motor Vehicles",
            "subcategory":"Auto Supplies",
            "type":"Retail Goods"
        }
    ],
    "sg:phone":"+1 713 660 6600",
    "sg:postcode":"77054",
    "sg:province":"TX",
    "sg:tags":[
        "wheel",
        "tires-wholesale",
        "tire",
        "manufacturer"
    ],
    "sg:website":"http://www.herculestire.com",
    "wof:name":"Tire Dealers Warehouse",
    "wof:placetype":"venue"
},
  "geometry": {"coordinates":[-95.434909,29.663477],"type":"Point"}
}