{
  "type": "Feature",
  "properties": {
    "iso:country":"US",
    "sg:address":"609 S Lamar Blvd",
    "sg:city":"Austin",
    "sg:classifiers":[
        {
            "category":"Organizations",
            "subcategory":"Professional Association",
            "type":"Services"
        }
    ],
    "sg:phone":"+1 512 442 7887",
    "sg:postcode":"78704",
    "sg:province":"TX",
    "sg:website":"www.agcaustin.org",
    "wof:name":"AGC Assoc General Contractors",
    "wof:placetype":"venue"
},
  "geometry": {"coordinates":[-97.758881,30.259851],"type":"Point"}
}