{
  "type": "Feature",
  "properties": {
    "iso:country":"US",
    "sg:address":"19053 I- 45 S",
    "sg:city":"Conroe",
    "sg:classifiers":[
        {
            "category":"Home & Garden",
            "subcategory":"Carpets & Floor Coverings",
            "type":"Retail Goods"
        }
    ],
    "sg:phone":"+1 936 271 0000",
    "sg:postcode":"77385",
    "sg:province":"TX",
    "sg:tags":[
        "dealer",
        "rug"
    ],
    "wof:name":"Roberts Carpet & Fine Floors",
    "wof:placetype":"venue"
},
  "geometry": {"coordinates":[-95.451616,30.180677],"type":"Point"}
}