{
  "type": "Feature",
  "properties": {
    "iso:country":"US",
    "sg:address":"330 Forest Hill Blvd",
    "sg:city":"Houston",
    "sg:classifiers":[
        {
            "category":"Social Services",
            "subcategory":"Child Care",
            "type":"Services"
        }
    ],
    "sg:phone":"+1 713 923 5102",
    "sg:postcode":"77011",
    "sg:province":"TX",
    "wof:name":"Maria Garza",
    "wof:placetype":"venue"
},
  "geometry": {"coordinates":[-95.299117,29.729681],"type":"Point"}
}