{
  "type": "Feature",
  "properties": {
    "iso:country":"US",
    "sg:address":"1032 E 7th St",
    "sg:city":"Houston",
    "sg:classifiers":[
        {
            "category":"Banks & Credit Unions",
            "subcategory":"Bank",
            "type":"Services"
        }
    ],
    "sg:phone":"+1 713 862 6604",
    "sg:postcode":"77009",
    "sg:province":"TX",
    "sg:tags":[
        "mortgage"
    ],
    "wof:name":"Mortgage Contractor Solutions",
    "wof:placetype":"venue"
},
  "geometry": {"coordinates":[-95.385486,29.78341],"type":"Point"}
}