{
  "type": "Feature",
  "properties": {
    "iso:country":"US",
    "sg:address":"6351 N Fwy",
    "sg:city":"Fort Worth",
    "sg:classifiers":[
        {
            "category":"Travel",
            "subcategory":"Hotels & Motels",
            "type":"Entertainment"
        },
        {
            "category":"Retail",
            "subcategory":"Event Space",
            "type":"Services"
        }
    ],
    "sg:phone":"+1 817 234 9033",
    "sg:postcode":"76131",
    "sg:province":"TX",
    "sg:tags":[
        "venue"
    ],
    "sg:website":"www.holidayinnexpress.com",
    "wof:name":"Holiday Inn Express Hotel & Suites in Fort Worth Western Ctr",
    "wof:placetype":"venue"
},
  "geometry": {"coordinates":[-96.65945499999999,32.764517],"type":"Point"}
}