{
  "type": "Feature",
  "properties": {
    "iso:country":"US",
    "sg:address":"327 Las Colinas Blvd E",
    "sg:city":"Irving",
    "sg:classifiers":[
        {
            "category":"Travel",
            "subcategory":"Travel Agent",
            "type":"Entertainment"
        }
    ],
    "sg:phone":"+1 972 556 2072",
    "sg:postcode":"75039",
    "sg:province":"TX",
    "sg:tags":[
        "agency",
        "bureau"
    ],
    "wof:name":"Premier Travel",
    "wof:placetype":"venue"
},
  "geometry": {"coordinates":[-96.937952,32.866358],"type":"Point"}
}