{
  "type": "Feature",
  "properties": {
    "iso:country":"US",
    "sg:address":"4614 Belle Park Dr",
    "sg:city":"Houston",
    "sg:classifiers":[
        {
            "category":"Social Services",
            "subcategory":"Child Care",
            "type":"Services"
        }
    ],
    "sg:phone":"+1 281 879 1234",
    "sg:postcode":"77072",
    "sg:province":"TX",
    "sg:tags":[
        "day"
    ],
    "wof:name":"Seasons In Sun",
    "wof:placetype":"venue"
},
  "geometry": {"coordinates":[-95.583214,29.706462],"type":"Point"}
}