{
  "type": "Feature",
  "properties": {
    "iso:country":"US",
    "sg:address":"3909 I- 35 Svc Rd N",
    "sg:city":"Austin",
    "sg:classifiers":[
        {
            "category":"Retail",
            "subcategory":"Repair Shop",
            "type":"Services"
        }
    ],
    "sg:phone":"+1 512 451 7463",
    "sg:postcode":"78722",
    "sg:province":"TX",
    "sg:tags":[
        "parlor",
        "shoe"
    ],
    "wof:name":"Sammies Shoe Service",
    "wof:placetype":"venue"
},
  "geometry": {"coordinates":[-97.71892099999999,30.295162],"type":"Point"}
}