{
  "type": "Feature",
  "properties": {
    "iso:country":"US",
    "sg:address":"11907 W Highway 290",
    "sg:city":"Austin",
    "sg:phone":"+1 512 288 8539",
    "sg:postcode":"78737",
    "sg:province":"TX",
    "sg:website":"http://www.reidsdrycleaners.com",
    "wof:name":"Reid's Cleaners",
    "wof:placetype":"venue"
},
  "geometry": {"coordinates":[-97.96762699999999,30.21218],"type":"Point"}
}