{
  "type": "Feature",
  "properties": {
    "iso:country":"US",
    "sg:address":"1001 Vancouver Dr",
    "sg:city":"Lewisville",
    "sg:classifiers":[
        {
            "category":"Real Estate",
            "subcategory":"Real Estate Services",
            "type":"Services"
        },
        {
            "category":"Real Estate",
            "subcategory":"Real Estate Agent",
            "type":"Services"
        }
    ],
    "sg:phone":"+1 972 436 6172",
    "sg:postcode":"75077",
    "sg:province":"TX",
    "sg:tags":[
        "management"
    ],
    "wof:name":"Lec Management Inc",
    "wof:placetype":"venue"
},
  "geometry": {"coordinates":[-97.031471,33.056759],"type":"Point"}
}