{
  "type": "Feature",
  "properties": {
    "iso:country":"US",
    "sg:address":"13405 Southwest Fwy",
    "sg:city":"Sugar Land",
    "sg:classifiers":[
        {
            "category":"Building & Trades",
            "subcategory":"Landscaping Services",
            "type":"Services"
        }
    ],
    "sg:phone":"+1 281 565 1199",
    "sg:postcode":"77478",
    "sg:province":"TX",
    "sg:tags":[
        "landscape"
    ],
    "wof:name":"Bernard Oaks Inc",
    "wof:placetype":"venue"
},
  "geometry": {"coordinates":[-95.595866,29.62506],"type":"Point"}
}