{
  "type": "Feature",
  "properties": {
    "iso:country":"US",
    "sg:address":"16411 Haden Crest Ct",
    "sg:city":"Cypress",
    "sg:classifiers":[
        {
            "category":"Professional",
            "subcategory":"Management & Consulting",
            "type":"Services"
        }
    ],
    "sg:phone":"+1 281 225 9035",
    "sg:postcode":"77429",
    "sg:province":"TX",
    "sg:tags":[
        "business"
    ],
    "wof:name":"Mulholland Solutions Corp",
    "wof:placetype":"venue"
},
  "geometry": {"coordinates":[-95.666875,29.972302],"type":"Point"}
}