{
  "type": "Feature",
  "properties": {
    "iso:country":"US",
    "sg:address":"4070 E Rosedale St",
    "sg:city":"Fort Worth",
    "sg:classifiers":[
        {
            "category":"Wholesale",
            "subcategory":"Plants",
            "type":"Manufacturing & Wholesale Goods"
        }
    ],
    "sg:phone":"+1 817 536 1571",
    "sg:postcode":"76105",
    "sg:province":"TX",
    "sg:tags":[
        "florist"
    ],
    "wof:name":"Tinius Floral Inc",
    "wof:placetype":"venue"
},
  "geometry": {"coordinates":[-97.263401,32.731203],"type":"Point"}
}