{
  "type": "Feature",
  "properties": {
    "iso:country":"US",
    "sg:address":"14800 Quorum Dr",
    "sg:city":"Dallas",
    "sg:classifiers":[
        {
            "category":"Health Services",
            "subcategory":"Doctor",
            "type":"Services"
        }
    ],
    "sg:phone":"+1 972 308 8575",
    "sg:postcode":"75254",
    "sg:province":"TX",
    "wof:name":"Nexus Healthcare",
    "wof:placetype":"venue"
},
  "geometry": {"coordinates":[-96.825104,32.948799],"type":"Point"}
}