{
  "type": "Feature",
  "properties": {
    "iso:country":"US",
    "sg:address":"2516 Minnis Dr",
    "sg:city":"Fort Worth",
    "sg:classifiers":[
        {
            "category":"Manufacturing",
            "subcategory":"Metals",
            "type":"Manufacturing & Wholesale Goods"
        }
    ],
    "sg:phone":"+1 817 759 2224",
    "sg:postcode":"76117",
    "sg:province":"TX",
    "sg:tags":[
        "coating",
        "powder"
    ],
    "wof:name":"Clifford's Powder Coating",
    "wof:placetype":"venue"
},
  "geometry": {"coordinates":[-97.245228,32.797032],"type":"Point"}
}