{
  "type": "Feature",
  "properties": {
    "iso:country":"US",
    "sg:address":"1402 Heights Blvd",
    "sg:city":"Houston",
    "sg:classifiers":[
        {
            "category":"Personal",
            "subcategory":"Beauty Salon",
            "type":"Services"
        }
    ],
    "sg:phone":"+1 713 802 1380",
    "sg:postcode":"77008",
    "sg:province":"TX",
    "wof:name":"Rose H Daughtrey",
    "wof:placetype":"venue"
},
  "geometry": {"coordinates":[-95.397751,29.79803],"type":"Point"}
}