{
  "type": "Feature",
  "properties": {
    "iso:country":"US",
    "sg:address":"1810 Clearpoint Dr",
    "sg:city":"Garland",
    "sg:classifiers":[
        {
            "category":"Professional",
            "subcategory":"Business Services",
            "type":"Services"
        }
    ],
    "sg:phone":"+1 972 271 7395",
    "sg:postcode":"75041",
    "sg:province":"TX",
    "wof:name":"Donald M McDonald",
    "wof:placetype":"venue"
},
  "geometry": {"coordinates":[-96.65404599999999,32.865718],"type":"Point"}
}