{
  "type": "Feature",
  "properties": {
    "iso:country":"US",
    "sg:address":"2000 W Anderson Ln",
    "sg:city":"Austin",
    "sg:classifiers":[
        {
            "category":"Professional",
            "subcategory":"Research",
            "type":"Services"
        }
    ],
    "sg:phone":"+1 512 467 9866",
    "sg:postcode":"78757",
    "sg:province":"TX",
    "sg:tags":[
        "laboratory"
    ],
    "wof:name":"Clinical Reference Laboratory",
    "wof:placetype":"venue"
},
  "geometry": {"coordinates":[-97.729347,30.355458],"type":"Point"}
}