{
  "type": "Feature",
  "properties": {
    "iso:country":"US",
    "sg:address":"7181 Parker Ranch Rd",
    "sg:city":"Wichita Falls",
    "sg:classifiers":[
        {
            "category":"Recreation",
            "type":"Entertainment"
        },
        {
            "category":"Banks & Credit Unions",
            "subcategory":"Bank",
            "type":"Services"
        }
    ],
    "sg:phone":"+1 940 692 7400",
    "sg:postcode":"76310",
    "sg:province":"TX",
    "sg:tags":[
        "institution",
        "business",
        "stable"
    ],
    "wof:name":"Hill Country Hourse Boarding",
    "wof:placetype":"venue"
},
  "geometry": {"coordinates":[-98.654635,33.869512],"type":"Point"}
}