{
  "type": "Feature",
  "properties": {
    "iso:country":"US",
    "sg:address":"700 S Connellee Ave",
    "sg:city":"Eastland",
    "sg:classifiers":[
        {
            "category":"Real Estate",
            "subcategory":"Real Estate Operator",
            "type":"Services"
        }
    ],
    "sg:phone":"+1 254 629 1473",
    "sg:postcode":"76448",
    "sg:province":"TX",
    "sg:tags":[
        "building",
        "apartment"
    ],
    "wof:name":"Camelot Square Apartments",
    "wof:placetype":"venue"
},
  "geometry": {"coordinates":[-98.824229,32.393468],"type":"Point"}
}