{
  "type": "Feature",
  "properties": {
    "iso:country":"US",
    "sg:address":"115 W Decatur St",
    "sg:city":"Chico",
    "sg:classifiers":[
        {
            "category":"Shopping",
            "subcategory":"Crafts & Fabrics",
            "type":"Retail Goods"
        }
    ],
    "sg:phone":"+1 940 644 9446",
    "sg:postcode":"76431",
    "sg:province":"TX",
    "sg:tags":[
        "sewing"
    ],
    "wof:name":"On Pins & Needles",
    "wof:placetype":"venue"
},
  "geometry": {"coordinates":[-97.797065,33.293924],"type":"Point"}
}