{
  "type": "Feature",
  "properties": {
    "iso:country":"US",
    "sg:address":"4930 Cash Rd",
    "sg:city":"Dallas",
    "sg:classifiers":[
        {
            "category":"Manufacturing",
            "subcategory":"Metals",
            "type":"Manufacturing & Wholesale Goods"
        }
    ],
    "sg:phone":"+1 877 422 7767",
    "sg:postcode":"75247",
    "sg:province":"TX",
    "sg:tags":[
        "product",
        "exterior",
        "aluminum",
        "mfg"
    ],
    "wof:name":"Metals USA Building Pdts LP",
    "wof:placetype":"venue"
},
  "geometry": {"coordinates":[-96.882254,32.805342],"type":"Point"}
}