{
  "type": "Feature",
  "properties": {
    "iso:country":"US",
    "sg:address":"3402 Silver Spur Dr",
    "sg:city":"San Angelo",
    "sg:classifiers":[
        {
            "category":"Freight",
            "type":"Transportation"
        }
    ],
    "sg:phone":"+1 325 482 5180",
    "sg:postcode":"76904",
    "sg:province":"TX",
    "sg:tags":[
        "special"
    ],
    "wof:name":"J C S Apallo LLC",
    "wof:placetype":"venue"
},
  "geometry": {"coordinates":[-100.497821,31.41074],"type":"Point"}
}