{
  "type": "Feature",
  "properties": {
    "iso:country":"US",
    "sg:address":"7521 Sienna Dr",
    "sg:city":"Fort Worth",
    "sg:classifiers":[
        {
            "category":"Professional",
            "subcategory":"Computer Services",
            "type":"Services"
        }
    ],
    "sg:phone":"+1 817 292 5278",
    "sg:postcode":"76133",
    "sg:province":"TX",
    "sg:tags":[
        "related"
    ],
    "wof:name":"Iron Key Computing Inc",
    "wof:placetype":"venue"
},
  "geometry": {"coordinates":[-97.391296,32.631544],"type":"Point"}
}