{
  "type": "Feature",
  "properties": {
    "iso:country":"US",
    "sg:address":"2214 Badger Ln",
    "sg:city":"Huntsville",
    "sg:classifiers":[
        {
            "category":"Organizations",
            "subcategory":"Religious Organization",
            "type":"Services"
        }
    ],
    "sg:phone":"+1 936 295 5578",
    "sg:postcode":"77320",
    "sg:province":"TX",
    "sg:tags":[
        "church"
    ],
    "wof:name":"Jehovah's Witnesses",
    "wof:placetype":"venue"
},
  "geometry": {"coordinates":[-95.523867,30.735618],"type":"Point"}
}