{
  "type": "Feature",
  "properties": {
    "iso:country":"US",
    "sg:address":"6400 Texoma Pkwy",
    "sg:city":"Sherman",
    "sg:classifiers":[
        {
            "category":"Shopping",
            "subcategory":"Used Merchandise",
            "type":"Retail Goods"
        }
    ],
    "sg:phone":"+1 903 892 2227",
    "sg:postcode":"75090",
    "sg:province":"TX",
    "wof:name":"Best Pawn",
    "wof:placetype":"venue"
},
  "geometry": {"coordinates":[-96.57891600000001,33.691062],"type":"Point"}
}