{
  "type": "Feature",
  "properties": {
    "iso:country":"US",
    "sg:address":"6806 Potomac Pkwy",
    "sg:city":"Arlington",
    "sg:classifiers":[
        {
            "category":"Organizations",
            "subcategory":"Non-profit Organization",
            "type":"Services"
        }
    ],
    "sg:phone":"+1 817 516 0809",
    "sg:postcode":"76017",
    "sg:province":"TX",
    "sg:tags":[
        "medical",
        "management"
    ],
    "wof:name":"Southwest Medical Management",
    "wof:placetype":"venue"
},
  "geometry": {"coordinates":[-97.215293,32.662184],"type":"Point"}
}