{
  "type": "Feature",
  "properties": {
    "iso:country":"US",
    "sg:address":"100 E Avenue E D",
    "sg:city":"Robstown",
    "sg:classifiers":[
        {
            "category":"Shopping",
            "type":"Retail Goods"
        },
        {
            "category":"Food & Beverages",
            "subcategory":"Groceries & Convenience Stores",
            "type":"Retail Goods"
        }
    ],
    "sg:phone":"+1 361 387 9539",
    "sg:postcode":"78380",
    "sg:province":"TX",
    "sg:tags":[
        "merchandise"
    ],
    "wof:name":"Avalos Neighborhood Store",
    "wof:placetype":"venue"
},
  "geometry": {"coordinates":[-97.66841100000001,27.794111],"type":"Point"}
}