{
  "type": "Feature",
  "properties": {
    "iso:country":"US",
    "sg:address":"2505 S Fort Hood St",
    "sg:city":"Killeen",
    "sg:classifiers":[
        {
            "category":"Home & Garden",
            "subcategory":"Furniture",
            "type":"Retail Goods"
        }
    ],
    "sg:phone":"+1 254 554 7890",
    "sg:postcode":"76542",
    "sg:province":"TX",
    "wof:name":"Ashton's Furniture",
    "wof:placetype":"venue"
},
  "geometry": {"coordinates":[-97.754136,31.091414],"type":"Point"}
}