{
  "type": "Feature",
  "properties": {
    "iso:country":"US",
    "sg:address":"8080 Antoine Dr",
    "sg:city":"Houston",
    "sg:classifiers":[
        {
            "category":"Retail",
            "subcategory":"Auto Repair",
            "type":"Services"
        }
    ],
    "sg:phone":"+1 281 999 1461",
    "sg:postcode":"77088",
    "sg:province":"TX",
    "wof:name":"Cherry Park",
    "wof:placetype":"venue"
},
  "geometry": {"coordinates":[-95.47363799999999,29.88492],"type":"Point"}
}