{
  "type": "Feature",
  "properties": {
    "iso:country":"US",
    "sg:address":"117 S Johnson St",
    "sg:city":"Alvin",
    "sg:classifiers":[
        {
            "category":"Professional",
            "subcategory":"Lawyer & Legal Services",
            "type":"Services"
        }
    ],
    "sg:phone":"+1 281 388 0015",
    "sg:postcode":"77511",
    "sg:province":"TX",
    "wof:name":"Dwayne E Colvin PC",
    "wof:placetype":"venue"
},
  "geometry": {"coordinates":[-95.250614,29.423538],"type":"Point"}
}