{
  "type": "Feature",
  "properties": {
    "iso:country":"US",
    "sg:address":"9471 State Hwy 142",
    "sg:city":"Maxwell",
    "sg:classifiers":[
        {
            "category":"Restaurant",
            "type":"Food & Drink"
        }
    ],
    "sg:phone":"+1 512 357 1271",
    "sg:postcode":"78656",
    "sg:province":"TX",
    "sg:tags":[
        "eating"
    ],
    "wof:name":"Alejandros",
    "wof:placetype":"venue"
},
  "geometry": {"coordinates":[-97.789107,29.879284],"type":"Point"}
}