{
  "type": "Feature",
  "properties": {
    "iso:country":"US",
    "sg:address":"16005 Acapulco Dr",
    "sg:city":"Houston",
    "sg:classifiers":[
        {
            "category":"Professional",
            "subcategory":"Computer Services",
            "type":"Services"
        }
    ],
    "sg:phone":"+1 713 466 6155",
    "sg:postcode":"77040",
    "sg:province":"TX",
    "sg:tags":[
        "consultant",
        "designer"
    ],
    "wof:name":"G & J Mc Ginnis & Assoc",
    "wof:placetype":"venue"
},
  "geometry": {"coordinates":[-95.56381399999999,29.885874],"type":"Point"}
}