{
  "type": "Feature",
  "properties": {
    "iso:country":"US",
    "sg:address":"3954 N Texas Ave",
    "sg:city":"Bryan",
    "sg:classifiers":[
        {
            "category":"Retail",
            "subcategory":"Self-service Laundry",
            "type":"Services"
        }
    ],
    "sg:phone":"+1 979 693 6291",
    "sg:postcode":"77803",
    "sg:province":"TX",
    "sg:tags":[
        "coin"
    ],
    "wof:name":"Hallmark Cleaners",
    "wof:placetype":"venue"
},
  "geometry": {"coordinates":[-96.39361700000001,30.704018],"type":"Point"}
}