{
  "type": "Feature",
  "properties": {
    "iso:country":"US",
    "sg:address":"1505 Ottawa Trl",
    "sg:city":"Amarillo",
    "sg:classifiers":[
        {
            "category":"Building & Trades",
            "subcategory":"Construction",
            "type":"Services"
        }
    ],
    "sg:phone":"+1 806 622 3112",
    "sg:postcode":"79118",
    "sg:province":"TX",
    "sg:tags":[
        "residential"
    ],
    "wof:name":"Blasingame & Associates",
    "wof:placetype":"venue"
},
  "geometry": {"coordinates":[-101.822621,35.095311],"type":"Point"}
}