{
  "type": "Feature",
  "properties": {
    "iso:country":"US",
    "sg:address":"2542 Ryan St",
    "sg:city":"Brenham",
    "sg:classifiers":[
        {
            "category":"Personal",
            "type":"Services"
        }
    ],
    "sg:phone":"+1 979 836 2474",
    "sg:postcode":"77833",
    "sg:province":"TX",
    "wof:name":"Sandi Borup Massage Therapist",
    "wof:placetype":"venue"
},
  "geometry": {"coordinates":[-96.37662,30.147653],"type":"Point"}
}