{
  "type": "Feature",
  "properties": {
    "iso:country":"US",
    "sg:address":"3311 Daufuskie Island Rd",
    "sg:city":"Round Rock",
    "sg:classifiers":[
        {
            "category":"Retail",
            "subcategory":"Repair Shop",
            "type":"Services"
        }
    ],
    "sg:phone":"+1 512 218 0095",
    "sg:postcode":"78664",
    "sg:province":"TX",
    "wof:name":"E Tek Inc",
    "wof:placetype":"venue"
},
  "geometry": {"coordinates":[-97.59459699999999,30.517556],"type":"Point"}
}