{
  "type": "Feature",
  "properties": {
    "iso:country":"US",
    "sg:address":"113 Meteor Dr",
    "sg:city":"Austin",
    "sg:classifiers":[
        {
            "category":"Retail",
            "subcategory":"Repair Shop",
            "type":"Services"
        }
    ],
    "sg:phone":"+1 512 442 2147",
    "sg:postcode":"78745",
    "sg:province":"TX",
    "sg:tags":[
        "equipment",
        "refrigeration",
        "conditioning",
        "air"
    ],
    "wof:name":"Messenger Refrigeration",
    "wof:placetype":"venue"
},
  "geometry": {"coordinates":[-97.78168700000001,30.190526],"type":"Point"}
}