{
  "type": "Feature",
  "properties": {
    "iso:country":"US",
    "sg:address":"1924 Carson St",
    "sg:city":"Fort Worth",
    "sg:classifiers":[
        {
            "category":"Autos & Motor Vehicles",
            "subcategory":"Automobile Sales",
            "type":"Retail Goods"
        }
    ],
    "sg:phone":"+1 817 834 1053",
    "sg:postcode":"76117",
    "sg:province":"TX",
    "sg:tags":[
        "used"
    ],
    "wof:name":"Choice Motor Co",
    "wof:placetype":"venue"
},
  "geometry": {"coordinates":[-97.256612,32.787356],"type":"Point"}
}