{
  "type": "Feature",
  "properties": {
    "iso:country":"US",
    "sg:address":"7900 Brookriver Dr",
    "sg:city":"Dallas",
    "sg:classifiers":[
        {
            "category":"Travel",
            "subcategory":"Hotels & Motels",
            "type":"Entertainment"
        }
    ],
    "sg:phone":"+1 214 688 1010",
    "sg:postcode":"75247",
    "sg:province":"TX",
    "wof:name":"Hawthorn Suites Dmc",
    "wof:placetype":"venue"
},
  "geometry": {"coordinates":[-96.864799,32.818401],"type":"Point"}
}