{
  "type": "Feature",
  "properties": {
    "iso:country":"US",
    "sg:address":"2110 Slaughter Ln W Ste 120",
    "sg:city":"Austin",
    "sg:classifiers":[
        {
            "category":"Retail",
            "subcategory":"Veterinary Services",
            "type":"Services"
        }
    ],
    "sg:phone":"+1 512 280 0878",
    "sg:postcode":"78748",
    "sg:province":"TX",
    "sg:tags":[
        "veterinarian"
    ],
    "wof:name":"Tanglewood Pet Hospital",
    "wof:placetype":"venue"
},
  "geometry": {"coordinates":[-97.824997,30.1738],"type":"Point"}
}