{
  "type": "Feature",
  "properties": {
    "iso:country":"US",
    "sg:address":"10000 N Central Expy",
    "sg:city":"Dallas",
    "sg:classifiers":[
        {
            "category":"Professional",
            "subcategory":"Lawyer & Legal Services",
            "type":"Services"
        }
    ],
    "sg:phone":"+1 214 987 0005",
    "sg:postcode":"75231",
    "sg:province":"TX",
    "sg:tags":[
        "attorney"
    ],
    "sg:website":"www.millerandcurtis.com",
    "wof:name":"Miller & Curtis Law Offices",
    "wof:placetype":"venue"
},
  "geometry": {"coordinates":[-96.76970300000001,32.884189],"type":"Point"}
}