{
  "type": "Feature",
  "properties": {
    "iso:country":"US",
    "sg:address":"213 Quail Run",
    "sg:city":"Brownwood",
    "sg:classifiers":[
        {
            "category":"Insurance",
            "subcategory":"Insurance Agent",
            "type":"Services"
        }
    ],
    "sg:phone":"+1 325 646 5098",
    "sg:postcode":"76801",
    "sg:province":"TX",
    "wof:name":"Hars Man Ins",
    "wof:placetype":"venue"
},
  "geometry": {"coordinates":[-98.959833,31.69194],"type":"Point"}
}