{
  "type": "Feature",
  "properties": {
    "iso:country":"US",
    "sg:address":"4001 Ave H",
    "sg:city":"Austin",
    "sg:classifiers":[
        {
            "category":"Professional",
            "type":"Services"
        }
    ],
    "sg:phone":"+1 512 459 7975",
    "sg:postcode":"78751",
    "sg:province":"TX",
    "wof:name":"Wildflower Babies",
    "wof:placetype":"venue"
},
  "geometry": {"coordinates":[-97.72843899999999,30.30285],"type":"Point"}
}