{
  "type": "Feature",
  "properties": {
    "iso:country":"US",
    "sg:address":"1916 Martin Dr",
    "sg:city":"Weatherford",
    "sg:classifiers":[
        {
            "category":"Insurance",
            "subcategory":"Hazard Insurance",
            "type":"Services"
        },
        {
            "category":"Insurance",
            "subcategory":"Insurance Agent",
            "type":"Services"
        },
        {
            "category":"Insurance",
            "subcategory":"Life Insurance",
            "type":"Services"
        }
    ],
    "sg:phone":"+1 817 458 4590",
    "sg:postcode":"76086",
    "sg:province":"TX",
    "sg:tags":[
        "auto"
    ],
    "sg:website":"http://statefarm.mqgroup.com/url.asp?usr=437693",
    "wof:name":"Bagley, Craig Alan - State Farm Insurance Agent",
    "wof:placetype":"venue"
},
  "geometry": {"coordinates":[-97.79216599999999,32.733489],"type":"Point"}
}