{
  "type": "Feature",
  "properties": {
    "iso:country":"US",
    "sg:address":"510 Leicester Ln",
    "sg:city":"Houston",
    "sg:classifiers":[
        {
            "category":"Recreation",
            "type":"Entertainment"
        }
    ],
    "sg:phone":"+1 281 484 5365",
    "sg:postcode":"77034",
    "sg:province":"TX",
    "wof:name":"Miccio Investment Group Inc",
    "wof:placetype":"venue"
},
  "geometry": {"coordinates":[-95.183229,29.59494],"type":"Point"}
}