{
  "type": "Feature",
  "properties": {
    "iso:country":"US",
    "sg:address":"3415 Jasmine Ln",
    "sg:city":"Rowlett",
    "sg:classifiers":[
        {
            "category":"Professional",
            "subcategory":"Business Services",
            "type":"Services"
        }
    ],
    "sg:phone":"+1 972 475 5301",
    "sg:postcode":"75089",
    "sg:province":"TX",
    "sg:tags":[
        "interior",
        "design"
    ],
    "wof:name":"Interior Touch & Design",
    "wof:placetype":"venue"
},
  "geometry": {"coordinates":[-96.56873299999999,32.914558],"type":"Point"}
}