{
  "type": "Feature",
  "properties": {
    "iso:country":"US",
    "sg:address":"4203 Bennedict Ln",
    "sg:city":"Austin",
    "sg:classifiers":[
        {
            "category":"Professional",
            "subcategory":"Management & Consulting",
            "type":"Services"
        }
    ],
    "sg:phone":"+1 512 306 8160",
    "sg:postcode":"78746",
    "sg:province":"TX",
    "wof:name":"Bennedict Oaks Management Co L",
    "wof:placetype":"venue"
},
  "geometry": {"coordinates":[-97.787125,30.31078],"type":"Point"}
}