{
  "type": "Feature",
  "properties": {
    "iso:country":"US",
    "sg:address":"301 Hilltop Ave",
    "sg:city":"Converse",
    "sg:classifiers":[
        {
            "category":"Home & Garden",
            "subcategory":"Building Materials",
            "type":"Retail Goods"
        }
    ],
    "sg:phone":"+1 210 659 4604",
    "sg:postcode":"78109",
    "sg:province":"TX",
    "wof:name":"Durable Steel Overhead Doors",
    "wof:placetype":"venue"
},
  "geometry": {"coordinates":[-98.317465,29.521321],"type":"Point"}
}