{
  "type": "Feature",
  "properties": {
    "iso:country":"US",
    "sg:address":"20007 Rio Villa Dr",
    "sg:city":"Houston",
    "sg:classifiers":[
        {
            "category":"Professional",
            "subcategory":"Business Services",
            "type":"Services"
        }
    ],
    "sg:phone":"+1 281 452 7606",
    "sg:postcode":"77049",
    "sg:province":"TX",
    "sg:tags":[
        "auction"
    ],
    "wof:name":"Ken Garcia Services",
    "wof:placetype":"venue"
},
  "geometry": {"coordinates":[-95.06256500000001,29.829641],"type":"Point"}
}