{
  "type": "Feature",
  "properties": {
    "iso:country":"US",
    "sg:address":"3317 Meadow Oaks Dr",
    "sg:city":"Garland",
    "sg:classifiers":[
        {
            "category":"Travel",
            "subcategory":"Travel Agent",
            "type":"Entertainment"
        }
    ],
    "sg:phone":"+1 972 226 4305",
    "sg:postcode":"75043",
    "sg:province":"TX",
    "sg:tags":[
        "agency"
    ],
    "wof:name":"Travelnstarz",
    "wof:placetype":"venue"
},
  "geometry": {"coordinates":[-96.579729,32.842337],"type":"Point"}
}