{
  "type": "Feature",
  "properties": {
    "iso:country":"US",
    "sg:address":"2912 Legacy Dr",
    "sg:city":"Plano",
    "sg:classifiers":[
        {
            "category":"Shopping",
            "subcategory":"Florist",
            "type":"Retail Goods"
        }
    ],
    "sg:phone":"+1 972 208 2520",
    "sg:postcode":"75023",
    "sg:province":"TX",
    "wof:name":"Z's Florist",
    "wof:placetype":"venue"
},
  "geometry": {"coordinates":[-96.748085,33.071518],"type":"Point"}
}