{
  "type": "Feature",
  "properties": {
    "iso:country":"US",
    "sg:address":"400 E Caney St",
    "sg:city":"Wharton",
    "sg:classifiers":[
        {
            "category":"Real Estate",
            "subcategory":"Real Estate Operator",
            "type":"Services"
        }
    ],
    "sg:phone":"+1 979 532 1095",
    "sg:postcode":"77488",
    "sg:province":"TX",
    "sg:tags":[
        "dwelling"
    ],
    "wof:name":"Frazier Rentals",
    "wof:placetype":"venue"
},
  "geometry": {"coordinates":[-96.096531,29.310831],"type":"Point"}
}