{
  "type": "Feature",
  "properties": {
    "iso:country":"US",
    "sg:address":"4400 Ramsey Ave",
    "sg:city":"Austin",
    "sg:classifiers":[
        {
            "category":"Real Estate",
            "subcategory":"Architect",
            "type":"Services"
        }
    ],
    "sg:phone":"+1 512 452 6440",
    "sg:postcode":"78756",
    "sg:province":"TX",
    "wof:name":"James Robinson Architecture",
    "wof:placetype":"venue"
},
  "geometry": {"coordinates":[-97.743358,30.316229],"type":"Point"}
}