{
  "type": "Feature",
  "properties": {
    "iso:country":"US",
    "sg:address":"4011 E Stan Schlueter Loop",
    "sg:city":"Killeen",
    "sg:classifiers":[
        {
            "category":"Home & Garden",
            "subcategory":"Building Materials",
            "type":"Retail Goods"
        }
    ],
    "sg:phone":"+1 254 699 0888",
    "sg:postcode":"76542",
    "sg:province":"TX",
    "sg:tags":[
        "lumber"
    ],
    "sg:website":"www.foxgal.com",
    "wof:name":"Foxworth Galbraith",
    "wof:placetype":"venue"
},
  "geometry": {"coordinates":[-97.70608799999999,31.074435],"type":"Point"}
}