{
  "type": "Feature",
  "properties": {
    "iso:country":"US",
    "sg:address":"1025 State Hwy 8",
    "sg:city":"New Boston",
    "sg:classifiers":[
        {
            "category":"Retail",
            "subcategory":"Auto Repair",
            "type":"Services"
        }
    ],
    "sg:phone":"+1 903 628 7083",
    "sg:postcode":"75570",
    "sg:province":"TX",
    "sg:tags":[
        "body",
        "automobile",
        "painting"
    ],
    "wof:name":"King's Paint & Body",
    "wof:placetype":"venue"
},
  "geometry": {"coordinates":[-94.41135,33.446662],"type":"Point"}
}