{
  "type": "Feature",
  "properties": {
    "iso:country":"US",
    "sg:address":"4025 Southwestern Blvd",
    "sg:city":"Dallas",
    "sg:classifiers":[
        {
            "category":"Travel",
            "subcategory":"Hotels & Motels",
            "type":"Entertainment"
        }
    ],
    "sg:phone":"+1 214 363 2382",
    "sg:postcode":"75225",
    "sg:province":"TX",
    "wof:name":"Crescent Royalties",
    "wof:placetype":"venue"
},
  "geometry": {"coordinates":[-96.80242,32.856796],"type":"Point"}
}