{
  "type": "Feature",
  "properties": {
    "iso:country":"US",
    "sg:address":"800 N San Jacinto St",
    "sg:city":"Conroe",
    "sg:classifiers":[
        {
            "category":"Retail",
            "subcategory":"Laundry & Dry Cleaning",
            "type":"Services"
        }
    ],
    "sg:phone":"+1 936 760 1507",
    "sg:postcode":"77301",
    "sg:province":"TX",
    "sg:tags":[
        "dressmaker"
    ],
    "wof:name":"Jamoor Enterprises",
    "wof:placetype":"venue"
},
  "geometry": {"coordinates":[-95.45916,30.315741],"type":"Point"}
}