{
  "type": "Feature",
  "properties": {
    "iso:country":"US",
    "sg:address":"9200 Powhatan Dr",
    "sg:city":"San Antonio",
    "sg:classifiers":[
        {
            "category":"Professional",
            "subcategory":"Advertising",
            "type":"Services"
        }
    ],
    "sg:phone":"+1 210 348 6816",
    "sg:postcode":"78230",
    "sg:province":"TX",
    "sg:tags":[
        "representative"
    ],
    "wof:name":"Visions Unlimited",
    "wof:placetype":"venue"
},
  "geometry": {"coordinates":[-98.55171300000001,29.523221],"type":"Point"}
}