{
  "type": "Feature",
  "properties": {
    "iso:country":"US",
    "sg:address":"1001 McKinney St Ste 450",
    "sg:city":"Houston",
    "sg:classifiers":[
        {
            "category":"Parking",
            "type":"Transportation"
        }
    ],
    "sg:phone":"+1 713 951 9348",
    "sg:postcode":"77002",
    "sg:province":"TX",
    "sg:website":"www.centralparkingsystem.com",
    "wof:name":"Central Parking System",
    "wof:placetype":"venue"
},
  "geometry": {"coordinates":[-95.364846,29.757066],"type":"Point"}
}