{
  "type": "Feature",
  "properties": {
    "iso:country":"US",
    "sg:address":"227 Wood Trl",
    "sg:city":"Kerrville",
    "sg:classifiers":[
        {
            "category":"Building & Trades",
            "subcategory":"Construction",
            "type":"Services"
        }
    ],
    "sg:phone":"+1 830 895 2460",
    "sg:postcode":"78028",
    "sg:province":"TX",
    "sg:tags":[
        "home",
        "improvement"
    ],
    "wof:name":"W P Norris Cabinet Maker",
    "wof:placetype":"venue"
},
  "geometry": {"coordinates":[-99.18304000000001,30.105033],"type":"Point"}
}