{
  "type": "Feature",
  "properties": {
    "iso:country":"US",
    "sg:address":"5226 Collingwood Dr",
    "sg:city":"Garland",
    "sg:classifiers":[
        {
            "category":"Freight",
            "type":"Transportation"
        }
    ],
    "sg:phone":"+1 214 869 9550",
    "sg:postcode":"75043",
    "sg:province":"TX",
    "sg:tags":[
        "operator",
        "local",
        "trucking"
    ],
    "wof:name":"Smooth Rider Trucking Co Inc",
    "wof:placetype":"venue"
},
  "geometry": {"coordinates":[-96.61133100000001,32.852882],"type":"Point"}
}