{
  "type": "Feature",
  "properties": {
    "iso:country":"US",
    "sg:address":"1941 Navajo Cir",
    "sg:city":"Abilene",
    "sg:classifiers":[
        {
            "category":"Professional",
            "type":"Services"
        }
    ],
    "sg:phone":"+1 325 673 8740",
    "sg:postcode":"79602",
    "sg:province":"TX",
    "sg:tags":[
        "establishment"
    ],
    "wof:name":"Southwest Regional Fly-In",
    "wof:placetype":"venue"
},
  "geometry": {"coordinates":[-99.689447,32.427828],"type":"Point"}
}