{
  "type": "Feature",
  "properties": {
    "iso:country":"US",
    "sg:address":"7530 Meadowview Dr",
    "sg:city":"Houston",
    "sg:classifiers":[
        {
            "category":"Building & Trades",
            "subcategory":"Construction",
            "type":"Services"
        }
    ],
    "sg:phone":"+1 281 847 9155",
    "sg:postcode":"77037",
    "sg:province":"TX",
    "sg:tags":[
        "hanging",
        "contractor"
    ],
    "wof:name":"S Vega Painting",
    "wof:placetype":"venue"
},
  "geometry": {"coordinates":[-95.399674,29.872276],"type":"Point"}
}