{
  "type": "Feature",
  "properties": {
    "iso:country":"US",
    "sg:address":"6914 Hyde Park Dr",
    "sg:city":"Dallas",
    "sg:classifiers":[
        {
            "category":"Shopping",
            "subcategory":"Gifts & Souvenirs",
            "type":"Retail Goods"
        }
    ],
    "sg:phone":"+1 214 340 3855",
    "sg:postcode":"75231",
    "sg:province":"TX",
    "wof:name":"Hatbox Bakery & Gifts",
    "wof:placetype":"venue"
},
  "geometry": {"coordinates":[-96.735698,32.871927],"type":"Point"}
}