{
  "type": "Feature",
  "properties": {
    "iso:country":"US",
    "sg:address":"5970 Teague Rd",
    "sg:city":"Fort Worth",
    "sg:classifiers":[
        {
            "category":"Building & Trades",
            "subcategory":"Construction",
            "type":"Services"
        }
    ],
    "sg:phone":"+1 817 516 0496",
    "sg:postcode":"76140",
    "sg:province":"TX",
    "sg:tags":[
        "concrete",
        "contractor"
    ],
    "wof:name":"Boone Concrete Inc",
    "wof:placetype":"venue"
},
  "geometry": {"coordinates":[-97.22498400000001,32.594474],"type":"Point"}
}