{
  "type": "Feature",
  "properties": {
    "iso:country":"US",
    "sg:address":"6419 Skillman St",
    "sg:city":"Dallas",
    "sg:classifiers":[
        {
            "category":"Shopping",
            "subcategory":"Optician",
            "type":"Retail Goods"
        }
    ],
    "sg:phone":"+1 214 343 7465",
    "sg:postcode":"75231",
    "sg:province":"TX",
    "sg:tags":[
        "eyewear"
    ],
    "sg:website":"www.target.com",
    "wof:name":"Target Optical",
    "wof:placetype":"venue"
},
  "geometry": {"coordinates":[-96.744499,32.864799],"type":"Point"}
}