{
  "type": "Feature",
  "properties": {
    "iso:country":"US",
    "sg:address":"26824 I- 45",
    "sg:city":"Spring",
    "sg:classifiers":[
        {
            "category":"Food & Beverages",
            "subcategory":"Groceries & Convenience Stores",
            "type":"Retail Goods"
        }
    ],
    "sg:phone":"+1 281 367 7597",
    "sg:postcode":"77386",
    "sg:province":"TX",
    "sg:tags":[
        "ticket",
        "lottery",
        "beer"
    ],
    "wof:name":"Hodges Food Basket",
    "wof:placetype":"venue"
},
  "geometry": {"coordinates":[-95.447537,30.150904],"type":"Point"}
}