{
  "type": "Feature",
  "properties": {
    "iso:country":"US",
    "sg:address":"1707 Colquitt St",
    "sg:city":"Houston",
    "sg:classifiers":[
        {
            "category":"Personal",
            "type":"Services"
        }
    ],
    "sg:phone":"+1 713 527 8422",
    "sg:postcode":"77098",
    "sg:province":"TX",
    "wof:name":"Visa Services of Houston",
    "wof:placetype":"venue"
},
  "geometry": {"coordinates":[-95.404336,29.735106],"type":"Point"}
}