{
  "type": "Feature",
  "properties": {
    "iso:country":"US",
    "sg:address":"943 Pueblo Ct",
    "sg:city":"Brownsville",
    "sg:classifiers":[
        {
            "category":"Place Of Worship",
            "type":"Public Place"
        }
    ],
    "sg:phone":"+1 956 542 3105",
    "sg:postcode":"78526",
    "sg:province":"TX",
    "sg:tags":[
        "church"
    ],
    "wof:name":"Christs Covenant Church Inc",
    "wof:placetype":"venue"
},
  "geometry": {"coordinates":[-97.504165,25.975333],"type":"Point"}
}