{
  "type": "Feature",
  "properties": {
    "iso:country":"US",
    "sg:address":"5314 Waterbeck St",
    "sg:city":"Fulshear",
    "sg:classifiers":[
        {
            "category":"Personal",
            "subcategory":"Barber",
            "type":"Services"
        }
    ],
    "sg:phone":"+1 281 346 1747",
    "sg:postcode":"77441",
    "sg:province":"TX",
    "sg:tags":[
        "shop"
    ],
    "wof:name":"For His Glory Prison Ministry",
    "wof:placetype":"venue"
},
  "geometry": {"coordinates":[-95.9299,29.67594],"type":"Point"}
}