{
  "type": "Feature",
  "properties": {
    "iso:country":"US",
    "sg:address":"8835 S Central Expy",
    "sg:city":"Dallas",
    "sg:classifiers":[
        {
            "category":"Autos & Motor Vehicles",
            "subcategory":"Automobile Sales",
            "type":"Retail Goods"
        },
        {
            "category":"Personal",
            "type":"Services"
        },
        {
            "category":"Autos & Motor Vehicles",
            "subcategory":"Auto Supplies",
            "type":"Retail Goods"
        }
    ],
    "sg:phone":"+1 214 375 5555",
    "sg:postcode":"75241",
    "sg:province":"TX",
    "sg:tags":[
        "cars-wholesale",
        "dealers-used",
        "part",
        "supplies-used",
        "towing",
        "rebuilt",
        "salvage"
    ],
    "sg:website":"http://www.picknpull.com",
    "wof:name":"PickNPull",
    "wof:placetype":"venue"
},
  "geometry": {"coordinates":[-96.742372,32.695193],"type":"Point"}
}