{
  "type": "Feature",
  "properties": {
    "iso:country":"US",
    "sg:address":"112 Williams Ave",
    "sg:city":"Cleburne",
    "sg:classifiers":[
        {
            "category":"Recreation",
            "subcategory":"Amusement Park",
            "type":"Entertainment"
        }
    ],
    "sg:phone":"+1 817 641 4441",
    "sg:postcode":"76033",
    "sg:province":"TX",
    "sg:tags":[
        "bowling"
    ],
    "wof:name":"Cleburne Pin Center Bowl",
    "wof:placetype":"venue"
},
  "geometry": {"coordinates":[-97.38967100000001,32.356464],"type":"Point"}
}