{
  "type": "Feature",
  "properties": {
    "iso:country":"US",
    "sg:address":"2801 W Sunset Dr",
    "sg:city":"Orange",
    "sg:classifiers":[
        {
            "category":"Shopping",
            "subcategory":"Clothing, Apparel, & Fashions",
            "type":"Retail Goods"
        }
    ],
    "sg:phone":"+1 409 883 9809",
    "sg:postcode":"77630",
    "sg:province":"TX",
    "wof:name":"Dylindas Dreams",
    "wof:placetype":"venue"
},
  "geometry": {"coordinates":[-93.758228,30.111733],"type":"Point"}
}