{
  "type": "Feature",
  "properties": {
    "iso:country":"US",
    "sg:address":"909 Frostwood Dr",
    "sg:city":"Houston",
    "sg:classifiers":[
        {
            "category":"Health Services",
            "subcategory":"Medical Lab",
            "type":"Services"
        }
    ],
    "sg:phone":"+1 713 722 8692",
    "sg:postcode":"77024",
    "sg:province":"TX",
    "sg:tags":[
        "laboratory"
    ],
    "wof:name":"Clinical Pathology Lab",
    "wof:placetype":"venue"
},
  "geometry": {"coordinates":[-95.547826,29.77829],"type":"Point"}
}