{
  "type": "Feature",
  "properties": {
    "iso:country":"US",
    "sg:address":"1614 Salem Ct",
    "sg:city":"Richardson",
    "sg:classifiers":[
        {
            "category":"Banks & Credit Unions",
            "subcategory":"Investment Brokerage",
            "type":"Services"
        }
    ],
    "sg:phone":"+1 972 690 4160",
    "sg:postcode":"75080",
    "sg:province":"TX",
    "sg:tags":[
        "advisory"
    ],
    "wof:name":"Professional Right Hand The",
    "wof:placetype":"venue"
},
  "geometry": {"coordinates":[-96.73898800000001,32.971983],"type":"Point"}
}