{
  "type": "Feature",
  "properties": {
    "iso:country":"US",
    "sg:address":"209 W Walnut Ave",
    "sg:city":"Mcallen",
    "sg:classifiers":[
        {
            "category":"Communications",
            "type":"Services"
        }
    ],
    "sg:phone":"+1 956 686 1288",
    "sg:postcode":"78501",
    "sg:province":"TX",
    "sg:tags":[
        "equipment",
        "telephone",
        "systems-repair"
    ],
    "wof:name":"Bucks Communication Service Inc",
    "wof:placetype":"venue"
},
  "geometry": {"coordinates":[-98.217857,26.223015],"type":"Point"}
}