{
  "type": "Feature",
  "properties": {
    "iso:country":"US",
    "sg:address":"1311 Lark Ln",
    "sg:city":"Richmond",
    "sg:classifiers":[
        {
            "category":"Building & Trades",
            "subcategory":"Construction",
            "type":"Services"
        }
    ],
    "sg:phone":"+1 281 239 3643",
    "sg:postcode":"77469",
    "sg:province":"TX",
    "sg:tags":[
        "house"
    ],
    "wof:name":"Class Construction Co Inc",
    "wof:placetype":"venue"
},
  "geometry": {"coordinates":[-95.750938,29.529897],"type":"Point"}
}