{
  "type": "Feature",
  "properties": {
    "iso:country":"US",
    "sg:address":"2901 SE 11th Ave",
    "sg:city":"Amarillo",
    "sg:classifiers":[
        {
            "category":"Manufacturing",
            "subcategory":"Buildings",
            "type":"Manufacturing & Wholesale Goods"
        },
        {
            "category":"Building & Trades",
            "subcategory":"Construction",
            "type":"Services"
        }
    ],
    "sg:phone":"+1 806 376 6295",
    "sg:postcode":"79104",
    "sg:province":"TX",
    "sg:tags":[
        "management",
        "metal",
        "contractor"
    ],
    "sg:website":"http://www.cib-inc.com",
    "wof:name":"CIB Inc",
    "wof:placetype":"venue"
},
  "geometry": {"coordinates":[-101.80444300000001,35.199169],"type":"Point"}
}