{
  "type": "Feature",
  "properties": {
    "iso:country":"US",
    "sg:address":"2021 Housley Dr",
    "sg:city":"Dallas",
    "sg:classifiers":[
        {
            "category":"Communications",
            "subcategory":"Film & Video Production",
            "type":"Services"
        }
    ],
    "sg:phone":"+1 214 328 1902",
    "sg:postcode":"75228",
    "sg:province":"TX",
    "sg:tags":[
        "motion"
    ],
    "wof:name":"Malcolm Audio Services",
    "wof:placetype":"venue"
},
  "geometry": {"coordinates":[-96.673002,32.85251],"type":"Point"}
}