{
  "type": "Feature",
  "properties": {
    "iso:country":"US",
    "sg:address":"1006 Berrywood Dr",
    "sg:city":"Austin",
    "sg:classifiers":[
        {
            "category":"Shopping",
            "subcategory":"Stationery & Office Supplies",
            "type":"Retail Goods"
        }
    ],
    "sg:phone":"+1 512 821 1580",
    "sg:postcode":"78753",
    "sg:province":"TX",
    "sg:tags":[
        "label"
    ],
    "wof:name":"Total Solutions Provider",
    "wof:placetype":"venue"
},
  "geometry": {"coordinates":[-97.66597,30.38085],"type":"Point"}
}