{
  "type": "Feature",
  "properties": {
    "iso:country":"US",
    "sg:address":"12314 Amsterdam Dr",
    "sg:city":"Houston",
    "sg:classifiers":[
        {
            "category":"Freight",
            "type":"Transportation"
        }
    ],
    "sg:phone":"+1 281 464 3197",
    "sg:postcode":"77089",
    "sg:province":"TX",
    "sg:tags":[
        "operator",
        "trucking"
    ],
    "wof:name":"Perez Celio",
    "wof:placetype":"venue"
},
  "geometry": {"coordinates":[-95.20084900000001,29.586378],"type":"Point"}
}