{
  "type": "Feature",
  "properties": {
    "iso:country":"US",
    "sg:address":"7006 Port Phillip Dr",
    "sg:city":"Arlington",
    "sg:classifiers":[
        {
            "category":"Professional",
            "subcategory":"Management & Consulting",
            "type":"Services"
        }
    ],
    "sg:phone":"+1 817 465 0682",
    "sg:postcode":"76002",
    "sg:province":"TX",
    "wof:name":"Mac Wealth Management Inc",
    "wof:placetype":"venue"
},
  "geometry": {"coordinates":[-97.070306,32.633318],"type":"Point"}
}