{
  "type": "Feature",
  "properties": {
    "iso:country":"US",
    "sg:address":"980 Highway 287 N",
    "sg:city":"Mansfield",
    "sg:classifiers":[
        {
            "category":"Shopping",
            "subcategory":"Florist",
            "type":"Retail Goods"
        },
        {
            "category":"Bakery",
            "type":"Food & Drink"
        },
        {
            "category":"Shopping",
            "subcategory":"Pharmacy",
            "type":"Retail Goods"
        },
        {
            "category":"Food & Beverages",
            "subcategory":"Groceries & Convenience Stores",
            "type":"Retail Goods"
        }
    ],
    "sg:phone":"+1 817 453 6770",
    "sg:postcode":"76063",
    "sg:province":"TX",
    "sg:website":"http://www.tomthumb.com",
    "wof:name":"Tom Thumb Food & Pharmacy",
    "wof:placetype":"venue"
},
  "geometry": {"coordinates":[-97.131713,32.582121],"type":"Point"}
}