{
  "type": "Feature",
  "properties": {
    "iso:country":"US",
    "sg:address":"11 N Gulf Blvd",
    "sg:city":"Freeport",
    "sg:classifiers":[
        {
            "category":"Wholesale",
            "subcategory":"Machinery & Supplies",
            "type":"Manufacturing & Wholesale Goods"
        }
    ],
    "sg:phone":"+1 979 233 6223",
    "sg:postcode":"77541",
    "sg:province":"TX",
    "sg:tags":[
        "equipment",
        "industrial"
    ],
    "wof:name":"Specialties Co Of Freeport",
    "wof:placetype":"venue"
},
  "geometry": {"coordinates":[-95.35959,28.9628],"type":"Point"}
}