{
  "type": "Feature",
  "properties": {
    "iso:country":"US",
    "sg:address":"4825 Goldeneye Dr",
    "sg:city":"Corpus Christi",
    "sg:classifiers":[
        {
            "category":"Retail",
            "subcategory":"Auto Repair",
            "type":"Services"
        }
    ],
    "sg:phone":"+1 361 991 6600",
    "sg:postcode":"78413",
    "sg:province":"TX",
    "sg:tags":[
        "general"
    ],
    "wof:name":"Addison Kelleys Gen Auto Adjst",
    "wof:placetype":"venue"
},
  "geometry": {"coordinates":[-97.399012,27.687473],"type":"Point"}
}