{
  "type": "Feature",
  "properties": {
    "iso:country":"US",
    "sg:address":"6810 Deatonhill Dr",
    "sg:city":"Austin",
    "sg:classifiers":[
        {
            "category":"Real Estate",
            "subcategory":"Real Estate Operator",
            "type":"Services"
        }
    ],
    "sg:phone":"+1 512 788 9275",
    "sg:postcode":"78745",
    "sg:province":"TX",
    "sg:tags":[
        "apartment"
    ],
    "sg:website":"deatonhillaustin.com",
    "wof:name":"Deatonhill Condos",
    "wof:placetype":"venue"
},
  "geometry": {"coordinates":[-97.817457,30.209242],"type":"Point"}
}