{
  "type": "Feature",
  "properties": {
    "iso:country":"US",
    "sg:address":"621 W Main St",
    "sg:city":"League City",
    "sg:classifiers":[
        {
            "category":"Retail",
            "subcategory":"Car Wash",
            "type":"Services"
        }
    ],
    "sg:phone":"+1 281 554 4404",
    "sg:postcode":"77573",
    "sg:province":"TX",
    "sg:tags":[
        "carwash",
        "polishing",
        "washing"
    ],
    "wof:name":"Bay Bright Carwash Detail Ctr",
    "wof:placetype":"venue"
},
  "geometry": {"coordinates":[-95.099554,29.506425],"type":"Point"}
}