{
  "type": "Feature",
  "properties": {
    "iso:country":"US",
    "sg:address":"6212 E Highway 290",
    "sg:city":"Giddings",
    "sg:classifiers":[
        {
            "category":"Building & Trades",
            "subcategory":"Electrical",
            "type":"Services"
        }
    ],
    "sg:phone":"+1 979 542 3956",
    "sg:postcode":"78942",
    "sg:province":"TX",
    "sg:tags":[
        "electrician"
    ],
    "wof:name":"Gl&P Industrial, Inc",
    "wof:placetype":"venue"
},
  "geometry": {"coordinates":[-96.86628,30.170815],"type":"Point"}
}