{
  "type": "Feature",
  "properties": {
    "iso:country":"US",
    "sg:address":"5407 Mount Bonnell Rd",
    "sg:city":"Austin",
    "sg:classifiers":[
        {
            "category":"Professional",
            "subcategory":"Computer Services",
            "type":"Services"
        }
    ],
    "sg:phone":"+1 512 452 9155",
    "sg:postcode":"78731",
    "sg:province":"TX",
    "sg:tags":[
        "prepackaged",
        "software"
    ],
    "wof:name":"Samba Holdings Inc",
    "wof:placetype":"venue"
},
  "geometry": {"coordinates":[-97.778829,30.341033],"type":"Point"}
}