{
  "type": "Feature",
  "properties": {
    "iso:country":"US",
    "sg:address":"3443 Burgundy Dr",
    "sg:city":"Brownsville",
    "sg:classifiers":[
        {
            "category":"Communications",
            "type":"Services"
        }
    ],
    "sg:phone":"+1 956 504 1073",
    "sg:postcode":"78526",
    "sg:province":"TX",
    "wof:name":"Teknomedia",
    "wof:placetype":"venue"
},
  "geometry": {"coordinates":[-97.48266099999999,25.959623],"type":"Point"}
}