{
  "type": "Feature",
  "properties": {
    "iso:country":"US",
    "sg:address":"5620 Old Hwy 105 W",
    "sg:city":"Conroe",
    "sg:classifiers":[
        {
            "category":"Restaurant",
            "type":"Food & Drink"
        }
    ],
    "sg:phone":"+1 936 760 1760",
    "sg:postcode":"77304",
    "sg:province":"TX",
    "sg:tags":[
        "eating",
        "station",
        "gasoline"
    ],
    "wof:name":"Pennzoil - Quaker State Co",
    "wof:placetype":"venue"
},
  "geometry": {"coordinates":[-95.554965,30.329162],"type":"Point"}
}