{
  "type": "Feature",
  "properties": {
    "iso:country":"US",
    "sg:address":"4403 Verone St",
    "sg:city":"Bellaire",
    "sg:classifiers":[
        {
            "category":"Education",
            "subcategory":"Vocational School",
            "type":"Public Place"
        }
    ],
    "sg:phone":"+1 713 953 1335",
    "sg:postcode":"77401",
    "sg:province":"TX",
    "sg:tags":[
        "club",
        "gliding"
    ],
    "wof:name":"Soaring Club of Houston",
    "wof:placetype":"venue"
},
  "geometry": {"coordinates":[-95.451134,29.697642],"type":"Point"}
}