{
  "type": "Feature",
  "properties": {
    "iso:country":"US",
    "sg:address":"2208 W Anderson Ln",
    "sg:city":"Austin",
    "sg:classifiers":[
        {
            "category":"Shopping",
            "subcategory":"Jewelry",
            "type":"Retail Goods"
        }
    ],
    "sg:phone":"+1 512 459 4185",
    "sg:postcode":"78757",
    "sg:province":"TX",
    "wof:name":"Ricks Jewelers",
    "wof:placetype":"venue"
},
  "geometry": {"coordinates":[-97.727959,30.354682],"type":"Point"}
}