{
  "type": "Feature",
  "properties": {
    "iso:country":"US",
    "sg:address":"1505 E Mesquite Ln",
    "sg:city":"Victoria",
    "sg:classifiers":[
        {
            "category":"Organizations",
            "subcategory":"Religious Organization",
            "type":"Services"
        }
    ],
    "sg:phone":"+1 361 573 0828",
    "sg:postcode":"77901",
    "sg:province":"TX",
    "sg:tags":[
        "church"
    ],
    "wof:name":"Catholic Diocese Of Victoria",
    "wof:placetype":"venue"
},
  "geometry": {"coordinates":[-96.988293,28.825049],"type":"Point"}
}