{
  "type": "Feature",
  "properties": {
    "iso:country":"US",
    "sg:address":"110 Medical Dr",
    "sg:city":"Hemphill",
    "sg:classifiers":[
        {
            "category":"Farming",
            "subcategory":"Farm",
            "type":"Manufacturing & Wholesale Goods"
        }
    ],
    "sg:phone":"+1 409 787 4907",
    "sg:postcode":"75948",
    "sg:province":"TX",
    "wof:name":"Felts Farms",
    "wof:placetype":"venue"
},
  "geometry": {"coordinates":[-93.83940699999999,31.349336],"type":"Point"}
}