{
  "type": "Feature",
  "properties": {
    "iso:country":"US",
    "sg:address":"5231 Wild Blackberry Dr",
    "sg:city":"Humble",
    "sg:classifiers":[
        {
            "category":"Building & Trades",
            "subcategory":"Construction",
            "type":"Services"
        }
    ],
    "sg:phone":"+1 281 360 4009",
    "sg:postcode":"77345",
    "sg:province":"TX",
    "sg:tags":[
        "contractor"
    ],
    "wof:name":"MRM Contracting",
    "wof:placetype":"venue"
},
  "geometry": {"coordinates":[-95.191232,30.080343],"type":"Point"}
}