{
  "type": "Feature",
  "properties": {
    "iso:country":"US",
    "sg:address":"409 Attaway Dr",
    "sg:city":"Euless",
    "sg:classifiers":[
        {
            "category":"Professional",
            "subcategory":"Computer Services",
            "type":"Services"
        }
    ],
    "sg:phone":"+1 817 540 6213",
    "sg:postcode":"76039",
    "sg:province":"TX",
    "sg:tags":[
        "related"
    ],
    "sg:website":"www.llsystems.com",
    "wof:name":"L & L Systems",
    "wof:placetype":"venue"
},
  "geometry": {"coordinates":[-97.077881,32.851163],"type":"Point"}
}