{
  "type": "Feature",
  "properties": {
    "iso:country":"US",
    "sg:address":"3200 Govalle Ave",
    "sg:city":"Austin",
    "sg:classifiers":[
        {
            "category":"Building & Trades",
            "subcategory":"Construction",
            "type":"Services"
        }
    ],
    "sg:phone":"+1 512 385 5000",
    "sg:postcode":"78702",
    "sg:province":"TX",
    "sg:tags":[
        "repairing",
        "remodeling",
        "contractor"
    ],
    "wof:name":"Chaparral Ceiling & Wall Inc",
    "wof:placetype":"venue"
},
  "geometry": {"coordinates":[-97.70044,30.265369],"type":"Point"}
}