{
  "type": "Feature",
  "properties": {
    "iso:country":"US",
    "sg:address":"7520 Potranco Rd",
    "sg:city":"San Antonio",
    "sg:classifiers":[
        {
            "category":"Real Estate",
            "subcategory":"Real Estate Operator",
            "type":"Services"
        }
    ],
    "sg:phone":"+1 210 647 1037",
    "sg:postcode":"78251",
    "sg:province":"TX",
    "sg:tags":[
        "building",
        "apartment"
    ],
    "wof:name":"Hollows The",
    "wof:placetype":"venue"
},
  "geometry": {"coordinates":[-98.639854,29.452005],"type":"Point"}
}