{
  "type": "Feature",
  "properties": {
    "iso:country":"US",
    "sg:address":"1520 Shely St",
    "sg:city":"Corpus Christi",
    "sg:classifiers":[
        {
            "category":"Recreation",
            "type":"Entertainment"
        }
    ],
    "sg:phone":"+1 361 888 4782",
    "sg:postcode":"78404",
    "sg:province":"TX",
    "wof:name":"Corpus Christi Tennis Assn",
    "wof:placetype":"venue"
},
  "geometry": {"coordinates":[-97.41424499999999,27.764836],"type":"Point"}
}