{
  "type": "Feature",
  "properties": {
    "iso:country":"US",
    "sg:address":"201 S Railroad Ave",
    "sg:city":"Troup",
    "sg:classifiers":[
        {
            "category":"Professional",
            "type":"Services"
        }
    ],
    "sg:phone":"+1 903 842 3662",
    "sg:postcode":"75789",
    "sg:province":"TX",
    "wof:name":"Encore Operating LP",
    "wof:placetype":"venue"
},
  "geometry": {"coordinates":[-95.123722,32.143518],"type":"Point"}
}