{
  "type": "Feature",
  "properties": {
    "iso:country":"US",
    "sg:address":"1255 Pratt Rd",
    "sg:city":"Red Oak",
    "sg:classifiers":[
        {
            "category":"Food & Beverages",
            "subcategory":"Groceries & Convenience Stores",
            "type":"Retail Goods"
        }
    ],
    "sg:phone":"+1 972 617 0600",
    "sg:postcode":"75154",
    "sg:province":"TX",
    "wof:name":"Don's Food Mart",
    "wof:placetype":"venue"
},
  "geometry": {"coordinates":[-96.75412300000001,32.535185],"type":"Point"}
}