{
  "type": "Feature",
  "properties": {
    "iso:country":"US",
    "sg:address":"504 SW 23rd St",
    "sg:city":"Grand Prairie",
    "sg:classifiers":[
        {
            "category":"Real Estate",
            "subcategory":"Real Estate Operator",
            "type":"Services"
        }
    ],
    "sg:phone":"+1 972 641 1466",
    "sg:postcode":"75051",
    "sg:province":"TX",
    "sg:tags":[
        "building",
        "apartment"
    ],
    "wof:name":"Crescent Arms Apartments",
    "wof:placetype":"venue"
},
  "geometry": {"coordinates":[-97.035551,32.737018],"type":"Point"}
}