{
  "type": "Feature",
  "properties": {
    "iso:country":"US",
    "sg:address":"2918 Oak Lawn Ave",
    "sg:city":"Dallas",
    "sg:classifiers":[
        {
            "category":"Shopping",
            "subcategory":"Used Merchandise",
            "type":"Retail Goods"
        }
    ],
    "sg:phone":"+1 214 520 6644",
    "sg:postcode":"75219",
    "sg:province":"TX",
    "sg:tags":[
        "shop",
        "thrift"
    ],
    "wof:name":"Genesis Benefit Thrift Store",
    "wof:placetype":"venue"
},
  "geometry": {"coordinates":[-96.809408,32.808129],"type":"Point"}
}