{
  "type": "Feature",
  "properties": {
    "iso:country":"US",
    "sg:address":"3733 N Josey Ln",
    "sg:city":"Carrollton",
    "sg:classifiers":[
        {
            "category":"Personal",
            "subcategory":"Beauty Salon",
            "type":"Services"
        }
    ],
    "sg:phone":"+1 972 492 7743",
    "sg:postcode":"75007",
    "sg:province":"TX",
    "sg:tags":[
        "shop"
    ],
    "wof:name":"Shear Illusions",
    "wof:placetype":"venue"
},
  "geometry": {"coordinates":[-96.886989,33.009219],"type":"Point"}
}