{
  "type": "Feature",
  "properties": {
    "iso:country":"US",
    "sg:address":"11894 Murphy Rd",
    "sg:city":"Houston",
    "sg:classifiers":[
        {
            "category":"Shopping",
            "subcategory":"Clothing, Apparel, & Fashions",
            "type":"Retail Goods"
        }
    ],
    "sg:phone":"+1 281 495 5656",
    "sg:postcode":"77031",
    "sg:province":"TX",
    "wof:name":"Suitmart",
    "wof:placetype":"venue"
},
  "geometry": {"coordinates":[-95.56687700000001,29.65005],"type":"Point"}
}