{
  "type": "Feature",
  "properties": {
    "iso:country":"US",
    "sg:address":"13809 N US Hwy 183",
    "sg:city":"Austin",
    "sg:classifiers":[
        {
            "category":"Real Estate",
            "subcategory":"Real Estate Agent",
            "type":"Services"
        }
    ],
    "sg:phone":"+1 512 257 7550",
    "sg:postcode":"78750",
    "sg:province":"TX",
    "sg:tags":[
        "management"
    ],
    "wof:name":"Austin Administrative",
    "wof:placetype":"venue"
},
  "geometry": {"coordinates":[-97.794848,30.462612],"type":"Point"}
}