{
  "type": "Feature",
  "properties": {
    "iso:country":"US",
    "sg:address":"5417 Ridge View Dr",
    "sg:city":"Fort Worth",
    "sg:classifiers":[
        {
            "category":"Professional",
            "subcategory":"Business Services",
            "type":"Services"
        }
    ],
    "sg:phone":"+1 817 849 1419",
    "sg:postcode":"76137",
    "sg:province":"TX",
    "wof:name":"ABC Pool Inspections",
    "wof:placetype":"venue"
},
  "geometry": {"coordinates":[-97.270749,32.866113],"type":"Point"}
}