{
  "type": "Feature",
  "properties": {
    "iso:country":"US",
    "sg:address":"8710 Tewantin Dr",
    "sg:city":"Houston",
    "sg:classifiers":[
        {
            "category":"Real Estate",
            "subcategory":"Developer",
            "type":"Services"
        }
    ],
    "sg:phone":"+1 713 553 7789",
    "sg:postcode":"77061",
    "sg:province":"TX",
    "wof:name":"Manticore Development",
    "wof:placetype":"venue"
},
  "geometry": {"coordinates":[-95.292525,29.641779],"type":"Point"}
}