{
  "type": "Feature",
  "properties": {
    "iso:country":"US",
    "sg:address":"1825 23rd St",
    "sg:city":"Galveston",
    "sg:classifiers":[
        {
            "category":"Shopping",
            "subcategory":"Optical Goods",
            "type":"Retail Goods"
        }
    ],
    "sg:phone":"+1 409 762 1300",
    "sg:postcode":"77550",
    "sg:province":"TX",
    "wof:name":"Eye Clinic of Texas The",
    "wof:placetype":"venue"
},
  "geometry": {"coordinates":[-94.78936299999999,29.292212],"type":"Point"}
}