{
  "type": "Feature",
  "properties": {
    "iso:country":"US",
    "sg:address":"3613 N Main St",
    "sg:city":"Victoria",
    "sg:classifiers":[
        {
            "category":"Communications",
            "subcategory":"Radio Station",
            "type":"Services"
        }
    ],
    "sg:phone":"+1 361 576 9300",
    "sg:postcode":"77901",
    "sg:province":"TX",
    "sg:tags":[
        "broadcast"
    ],
    "wof:name":"K P L V 939 FM",
    "wof:placetype":"venue"
},
  "geometry": {"coordinates":[-97.00834,28.828826],"type":"Point"}
}