{
  "type": "Feature",
  "properties": {
    "iso:country":"US",
    "sg:address":"3728 Nederland Ave",
    "sg:city":"Nederland",
    "sg:classifiers":[
        {
            "category":"Restaurant",
            "type":"Food & Drink"
        }
    ],
    "sg:menulink":"http://www.allmenus.com/tx/east-jefferson/202490-mcdonalds/menu/",
    "sg:postcode":"77627",
    "sg:province":"TX",
    "sg:tags":[
        "burger",
        "american"
    ],
    "wof:name":"McDonald's",
    "wof:placetype":"venue"
},
  "geometry": {"coordinates":[-94.00647499999999,29.956274],"type":"Point"}
}