{
  "type": "Feature",
  "properties": {
    "iso:country":"US",
    "sg:address":"2100 Co Rd 802",
    "sg:city":"Brownsville",
    "sg:classifiers":[
        {
            "category":"Utilities",
            "subcategory":"Mobile Phone",
            "type":"Services"
        }
    ],
    "sg:phone":"+1 956 541 3611",
    "sg:postcode":"78521",
    "sg:province":"TX",
    "sg:tags":[
        "telephone",
        "cellular"
    ],
    "wof:name":"Sprint Pcs Personal Comm Svc",
    "wof:placetype":"venue"
},
  "geometry": {"coordinates":[-97.474645,25.949901],"type":"Point"}
}