{
  "type": "Feature",
  "properties": {
    "iso:country":"US",
    "sg:address":"4702 Convict Hill Rd",
    "sg:city":"Austin",
    "sg:classifiers":[
        {
            "category":"Manufacturing",
            "subcategory":"Electronics",
            "type":"Manufacturing & Wholesale Goods"
        },
        {
            "category":"Professional",
            "subcategory":"Printing & Photocopies",
            "type":"Services"
        }
    ],
    "sg:phone":"+1 512 633 6202",
    "sg:postcode":"78749",
    "sg:province":"TX",
    "sg:tags":[
        "printers-equipment",
        "typesetting",
        "supply"
    ],
    "wof:name":"Classic Typesetting",
    "wof:placetype":"venue"
},
  "geometry": {"coordinates":[-97.847993,30.21794],"type":"Point"}
}