{
  "type": "Feature",
  "properties": {
    "iso:country":"US",
    "sg:address":"9344 Fostoria Rd",
    "sg:city":"Cleveland",
    "sg:classifiers":[
        {
            "category":"Professional",
            "subcategory":"Business Services",
            "type":"Services"
        }
    ],
    "sg:phone":"+1 281 593 3365",
    "sg:postcode":"77328",
    "sg:province":"TX",
    "wof:name":"J G Enterprizes",
    "wof:placetype":"venue"
},
  "geometry": {"coordinates":[-95.153345,30.308922],"type":"Point"}
}