{
  "type": "Feature",
  "properties": {
    "iso:country":"US",
    "sg:address":"823 Thornwick Dr",
    "sg:city":"Houston",
    "sg:classifiers":[
        {
            "category":"Professional",
            "subcategory":"Business Services",
            "type":"Services"
        }
    ],
    "sg:phone":"+1 281 556 6174",
    "sg:postcode":"77079",
    "sg:province":"TX",
    "sg:tags":[
        "trade",
        "contractor"
    ],
    "wof:name":"Chriss Pool Service",
    "wof:placetype":"venue"
},
  "geometry": {"coordinates":[-95.610705,29.776488],"type":"Point"}
}