{
  "type": "Feature",
  "properties": {
    "iso:country":"US",
    "sg:address":"604 Princeton Dr",
    "sg:city":"Pflugerville",
    "sg:classifiers":[
        {
            "category":"Retail",
            "subcategory":"Portrait Studio",
            "type":"Services"
        }
    ],
    "sg:phone":"+1 512 252 3984",
    "sg:postcode":"78660",
    "sg:province":"TX",
    "sg:tags":[
        "photographer"
    ],
    "wof:name":"Sunlight Photography",
    "wof:placetype":"venue"
},
  "geometry": {"coordinates":[-97.63050200000001,30.435934],"type":"Point"}
}