{
  "type": "Feature",
  "properties": {
    "iso:country":"US",
    "sg:address":"21418 Park Tree Ln",
    "sg:city":"Katy",
    "sg:classifiers":[
        {
            "category":"Wholesale",
            "subcategory":"Machinery & Supplies",
            "type":"Manufacturing & Wholesale Goods"
        }
    ],
    "sg:phone":"+1 281 492 2904",
    "sg:postcode":"77450",
    "sg:province":"TX",
    "sg:tags":[
        "equipment",
        "establishment"
    ],
    "wof:name":"All American Beauty Supply LLC",
    "wof:placetype":"venue"
},
  "geometry": {"coordinates":[-95.742841,29.766471],"type":"Point"}
}