{
  "type": "Feature",
  "properties": {
    "iso:country":"US",
    "sg:address":"3188 Co Rd 438",
    "sg:city":"Lindsay",
    "sg:classifiers":[
        {
            "category":"Professional",
            "subcategory":"Lawyer & Legal Services",
            "type":"Services"
        }
    ],
    "sg:phone":"+1 940 736 2318",
    "sg:postcode":"76250",
    "sg:province":"TX",
    "sg:tags":[
        "farm",
        "field",
        "crop",
        "beef",
        "cattle"
    ],
    "wof:name":"Zimmerer & Son Farms",
    "wof:placetype":"venue"
},
  "geometry": {"coordinates":[-97.245447,33.627178],"type":"Point"}
}