{
  "type": "Feature",
  "properties": {
    "iso:country":"US",
    "sg:address":"500 S Saint Marys St",
    "sg:city":"San Antonio",
    "sg:classifiers":[
        {
            "category":"Professional",
            "subcategory":"Management & Consulting",
            "type":"Services"
        }
    ],
    "sg:phone":"+1 210 224 5222",
    "sg:postcode":"78205",
    "sg:province":"TX",
    "sg:tags":[
        "fuel"
    ],
    "wof:name":"C & M Lot Management",
    "wof:placetype":"venue"
},
  "geometry": {"coordinates":[-98.49098499999999,29.419762],"type":"Point"}
}