{
  "type": "Feature",
  "properties": {
    "iso:country":"US",
    "sg:address":"116 Shady St",
    "sg:city":"Marlin",
    "sg:classifiers":[
        {
            "category":"Building & Trades",
            "subcategory":"Construction",
            "type":"Services"
        }
    ],
    "sg:phone":"+1 254 803 3013",
    "sg:postcode":"76661",
    "sg:province":"TX",
    "sg:tags":[
        "house"
    ],
    "wof:name":"Warren McQuire Builder Inc",
    "wof:placetype":"venue"
},
  "geometry": {"coordinates":[-96.89814200000001,31.312398],"type":"Point"}
}