{
  "type": "Feature",
  "properties": {
    "iso:country":"US",
    "sg:address":"6 Comanche Ln",
    "sg:city":"Belton",
    "sg:classifiers":[
        {
            "category":"Shopping",
            "subcategory":"Crafts & Fabrics",
            "type":"Retail Goods"
        }
    ],
    "sg:phone":"+1 254 780 3049",
    "sg:postcode":"76513",
    "sg:province":"TX",
    "sg:tags":[
        "sewing"
    ],
    "wof:name":"Sew Delightful By Therisa",
    "wof:placetype":"venue"
},
  "geometry": {"coordinates":[-97.46938299999999,31.134563],"type":"Point"}
}