{
  "type": "Feature",
  "properties": {
    "iso:country":"US",
    "sg:address":"807 W Main St",
    "sg:city":"League City",
    "sg:classifiers":[
        {
            "category":"Health Services",
            "subcategory":"Hospital",
            "type":"Services"
        }
    ],
    "sg:phone":"+1 281 389 5689",
    "sg:postcode":"77573",
    "sg:province":"TX",
    "sg:tags":[
        "specialty"
    ],
    "wof:name":"Family Opportunity Resources",
    "wof:placetype":"venue"
},
  "geometry": {"coordinates":[-95.10174600000001,29.506051],"type":"Point"}
}