{
  "type": "Feature",
  "properties": {
    "iso:country":"US",
    "sg:address":"4416 62nd St",
    "sg:city":"Lubbock",
    "sg:classifiers":[
        {
            "category":"Shopping",
            "type":"Retail Goods"
        }
    ],
    "sg:phone":"+1 806 792 9450",
    "sg:postcode":"79414",
    "sg:province":"TX",
    "sg:tags":[
        "merchandise"
    ],
    "wof:name":"Marvin Lee Moon",
    "wof:placetype":"venue"
},
  "geometry": {"coordinates":[-101.906729,33.537947],"type":"Point"}
}