{
  "type": "Feature",
  "properties": {
    "iso:country":"US",
    "sg:address":"2548 Main Ave",
    "sg:city":"Groves",
    "sg:classifiers":[
        {
            "category":"Retail",
            "subcategory":"Auto Repair",
            "type":"Services"
        }
    ],
    "sg:phone":"+1 409 962 5566",
    "sg:postcode":"77619",
    "sg:province":"TX",
    "sg:tags":[
        "wheel",
        "automotive",
        "alignment",
        "axle"
    ],
    "wof:name":"Twin City Front End",
    "wof:placetype":"venue"
},
  "geometry": {"coordinates":[-93.90684899999999,29.93568],"type":"Point"}
}