{
  "type": "Feature",
  "properties": {
    "iso:country":"US",
    "sg:address":"109 Country Club Ct",
    "sg:city":"Laredo",
    "sg:classifiers":[
        {
            "category":"Building & Trades",
            "subcategory":"Construction",
            "type":"Services"
        }
    ],
    "sg:phone":"+1 956 712 0468",
    "sg:postcode":"78041",
    "sg:province":"TX",
    "sg:tags":[
        "house"
    ],
    "wof:name":"L&M Construction",
    "wof:placetype":"venue"
},
  "geometry": {"coordinates":[-99.454933,27.53094],"type":"Point"}
}