{
  "type": "Feature",
  "properties": {
    "iso:country":"US",
    "sg:address":"20819 Essman Ln No 3",
    "sg:city":"Houston",
    "sg:classifiers":[
        {
            "category":"Home & Garden",
            "subcategory":"Building Materials",
            "type":"Retail Goods"
        },
        {
            "category":"Building & Trades",
            "subcategory":"Construction",
            "type":"Services"
        }
    ],
    "sg:phone":"+1 281 987 9000",
    "sg:postcode":"77073",
    "sg:province":"TX",
    "sg:tags":[
        "roofing",
        "industrial",
        "window",
        "contractor",
        "siding",
        "contractors-commercial",
        "insulation"
    ],
    "sg:website":"http://www.allstarroofsystems.com",
    "wof:name":"All Star Roof Systems Inc",
    "wof:placetype":"venue"
},
  "geometry": {"coordinates":[-95.38994599999999,30.016398],"type":"Point"}
}