{
  "type": "Feature",
  "properties": {
    "iso:country":"US",
    "sg:address":"917 E Jefferson St",
    "sg:city":"Grand Prairie",
    "sg:classifiers":[
        {
            "category":"Retail",
            "subcategory":"Auto Repair",
            "type":"Services"
        }
    ],
    "sg:phone":"+1 972 642 1099",
    "sg:postcode":"75051",
    "sg:province":"TX",
    "sg:tags":[
        "repairing",
        "automobile"
    ],
    "wof:name":"Rob's Auto Svc Ctr",
    "wof:placetype":"venue"
},
  "geometry": {"coordinates":[-96.992744,32.744802],"type":"Point"}
}