{
  "type": "Feature",
  "properties": {
    "iso:country":"US",
    "sg:address":"411 W Annie St",
    "sg:city":"Austin",
    "sg:classifiers":[
        {
            "category":"Real Estate",
            "subcategory":"Real Estate Services",
            "type":"Services"
        }
    ],
    "sg:phone":"+1 512 436 9586",
    "sg:postcode":"78704",
    "sg:province":"TX",
    "sg:tags":[
        "vacancy",
        "apartment",
        "rental",
        "finder",
        "listing"
    ],
    "wof:name":"9 Square Studio",
    "wof:placetype":"venue"
},
  "geometry": {"coordinates":[-97.754032,30.246875],"type":"Point"}
}