{
  "type": "Feature",
  "properties": {
    "iso:country":"US",
    "sg:address":"5900 Dunbury Dr",
    "sg:city":"Austin",
    "sg:classifiers":[
        {
            "category":"Professional",
            "subcategory":"Management & Consulting",
            "type":"Services"
        }
    ],
    "sg:phone":"+1 512 453 4458",
    "sg:postcode":"78723",
    "sg:province":"TX",
    "sg:tags":[
        "business"
    ],
    "wof:name":"Rising Tide Consultant",
    "wof:placetype":"venue"
},
  "geometry": {"coordinates":[-97.693754,30.314681],"type":"Point"}
}