{
  "type": "Feature",
  "properties": {
    "iso:country":"US",
    "sg:address":"714 Huntley St",
    "sg:city":"Dallas",
    "sg:classifiers":[
        {
            "category":"Real Estate",
            "subcategory":"Real Estate Operator",
            "type":"Services"
        }
    ],
    "sg:phone":"+1 214 824 6945",
    "sg:postcode":"75214",
    "sg:province":"TX",
    "sg:tags":[
        "building",
        "nonresidential"
    ],
    "wof:name":"Tbks Property LLC",
    "wof:placetype":"venue"
},
  "geometry": {"coordinates":[-96.761094,32.806828],"type":"Point"}
}