{
  "type": "Feature",
  "properties": {
    "iso:country":"US",
    "sg:address":"14011 Dublin Sq",
    "sg:city":"San Antonio",
    "sg:classifiers":[
        {
            "category":"Retail",
            "subcategory":"Auto Repair",
            "type":"Services"
        }
    ],
    "sg:phone":"+1 210 590 4885",
    "sg:postcode":"78217",
    "sg:province":"TX",
    "sg:tags":[
        "repairing",
        "automobile",
        "general"
    ],
    "wof:name":"Hedding Automotive Service",
    "wof:placetype":"venue"
},
  "geometry": {"coordinates":[-98.41159,29.568951],"type":"Point"}
}