{
  "type": "Feature",
  "properties": {
    "iso:country":"US",
    "sg:address":"3718 Mockingbird Ln",
    "sg:city":"Dallas",
    "sg:classifiers":[
        {
            "category":"Personal",
            "type":"Services"
        }
    ],
    "sg:phone":"+1 214 644 0200",
    "sg:postcode":"75205",
    "sg:province":"TX",
    "sg:tags":[
        "towing"
    ],
    "wof:name":"Towing In Dallas",
    "wof:placetype":"venue"
},
  "geometry": {"coordinates":[-96.794375,32.836591],"type":"Point"}
}