{
  "type": "Feature",
  "properties": {
    "iso:country":"US",
    "sg:address":"4515 Dove Springs Dr",
    "sg:city":"Austin",
    "sg:classifiers":[
        {
            "category":"Building & Trades",
            "subcategory":"Construction",
            "type":"Services"
        }
    ],
    "sg:phone":"+1 512 707 7535",
    "sg:postcode":"78744",
    "sg:province":"TX",
    "sg:tags":[
        "contractor"
    ],
    "wof:name":"Parra Masonry",
    "wof:placetype":"venue"
},
  "geometry": {"coordinates":[-97.751577,30.186563],"type":"Point"}
}