{
  "type": "Feature",
  "properties": {
    "iso:country":"US",
    "sg:address":"1919 San Bernardo Ave",
    "sg:city":"Laredo",
    "sg:classifiers":[
        {
            "category":"Building & Trades",
            "subcategory":"Pest Control",
            "type":"Services"
        }
    ],
    "sg:phone":"+1 956 726 0221",
    "sg:postcode":"78040",
    "sg:province":"TX",
    "sg:tags":[
        "mothproofing"
    ],
    "wof:name":"Pan American Termite & Pest Control",
    "wof:placetype":"venue"
},
  "geometry": {"coordinates":[-99.504535,27.516304],"type":"Point"}
}