{
  "type": "Feature",
  "properties": {
    "iso:country":"US",
    "sg:address":"7909 Fredericksburg Rd",
    "sg:city":"San Antonio",
    "sg:classifiers":[
        {
            "category":"Health Services",
            "subcategory":"Health Practitioner",
            "type":"Services"
        }
    ],
    "sg:phone":"+1 210 614 0345",
    "sg:postcode":"78229",
    "sg:province":"TX",
    "sg:tags":[
        "audiologists"
    ],
    "wof:name":"Pat Westbrook Audiologist",
    "wof:placetype":"venue"
},
  "geometry": {"coordinates":[-98.568907,29.512552],"type":"Point"}
}