{
  "type": "Feature",
  "properties": {
    "iso:country":"US",
    "sg:address":"1614 Wheless Ln",
    "sg:city":"Austin",
    "sg:classifiers":[
        {
            "category":"Autos & Motor Vehicles",
            "subcategory":"Auto Supplies",
            "type":"Retail Goods"
        }
    ],
    "sg:phone":"+1 512 552 6502",
    "sg:postcode":"78723",
    "sg:province":"TX",
    "sg:tags":[
        "glass"
    ],
    "sg:website":"campusautoglass.com",
    "wof:name":"Campus Auto Glass",
    "wof:placetype":"venue"
},
  "geometry": {"coordinates":[-97.690603,30.319392],"type":"Point"}
}