{
  "type": "Feature",
  "properties": {
    "iso:country":"US",
    "sg:address":"2420 Balch Springs Rd",
    "sg:city":"Mesquite",
    "sg:classifiers":[
        {
            "category":"Building & Trades",
            "subcategory":"Construction",
            "type":"Services"
        }
    ],
    "sg:phone":"+1 972 285 2537",
    "sg:postcode":"75180",
    "sg:province":"TX",
    "sg:tags":[
        "painter"
    ],
    "wof:name":"Empire Sandblasting & Painting",
    "wof:placetype":"venue"
},
  "geometry": {"coordinates":[-96.61053699999999,32.736176],"type":"Point"}
}