{
  "type": "Feature",
  "properties": {
    "iso:country":"US",
    "sg:address":"1601 E Alton Gloor Blvd",
    "sg:city":"Brownsville",
    "sg:classifiers":[
        {
            "category":"Arts & Performance",
            "subcategory":"Theater",
            "type":"Entertainment"
        }
    ],
    "sg:phone":"+1 956 986 9070",
    "sg:postcode":"78521",
    "sg:province":"TX",
    "sg:tags":[
        "group"
    ],
    "wof:name":"Imagine & Play LLC",
    "wof:placetype":"venue"
},
  "geometry": {"coordinates":[-97.48504200000001,25.982217],"type":"Point"}
}