{
  "type": "Feature",
  "properties": {
    "iso:country":"US",
    "sg:address":"314 E Twohig Ave",
    "sg:city":"San Angelo",
    "sg:classifiers":[
        {
            "category":"Health Services",
            "subcategory":"Doctor",
            "type":"Services"
        }
    ],
    "sg:phone":"+1 325 653 6944",
    "sg:postcode":"76903",
    "sg:province":"TX",
    "sg:tags":[
        "physician",
        "surgeon"
    ],
    "wof:name":"San Angelo Pediatric Assoc",
    "wof:placetype":"venue"
},
  "geometry": {"coordinates":[-100.431538,31.462637],"type":"Point"}
}