{
  "type": "Feature",
  "properties": {
    "iso:country":"US",
    "sg:address":"55 Waugh Dr",
    "sg:city":"Houston",
    "sg:classifiers":[
        {
            "category":"Professional",
            "subcategory":"Lawyer & Legal Services",
            "type":"Services"
        }
    ],
    "sg:phone":"+1 713 863 8400",
    "sg:postcode":"77007",
    "sg:province":"TX",
    "wof:name":"Sacks David J & Associates",
    "wof:placetype":"venue"
},
  "geometry": {"coordinates":[-95.39810199999999,29.7666],"type":"Point"}
}