{
  "type": "Feature",
  "properties": {
    "iso:country":"US",
    "sg:address":"13331 Preston Rd Ste 2138",
    "sg:city":"Dallas",
    "sg:classifiers":[
        {
            "category":"Shopping",
            "subcategory":"Shoes",
            "type":"Retail Goods"
        }
    ],
    "sg:phone":"+1 972 233 4616",
    "sg:postcode":"75240",
    "sg:province":"TX",
    "sg:tags":[
        "store"
    ],
    "wof:name":"Underground Station",
    "wof:placetype":"venue"
},
  "geometry": {"coordinates":[-96.803774,32.93111],"type":"Point"}
}