{
  "type": "Feature",
  "properties": {
    "iso:country":"US",
    "sg:address":"1525 N Post Oak Rd",
    "sg:city":"Houston",
    "sg:classifiers":[
        {
            "category":"Autos & Motor Vehicles",
            "subcategory":"Automobile Sales",
            "type":"Retail Goods"
        },
        {
            "category":"Autos & Motor Vehicles",
            "subcategory":"Recreational Vehicle Sales",
            "type":"Retail Goods"
        },
        {
            "category":"Retail",
            "subcategory":"Auto Repair",
            "type":"Services"
        }
    ],
    "sg:phone":"+1 713 680 9664",
    "sg:postcode":"77055",
    "sg:province":"TX",
    "sg:tags":[
        "antique",
        "body",
        "classic",
        "car",
        "equipment",
        "air conditioning",
        "equipment-service",
        "painting",
        "repairing"
    ],
    "sg:website":"http://www.customcarcool.com",
    "wof:name":"Custom Car Cool Air-Cond CO",
    "wof:placetype":"venue"
},
  "geometry": {"coordinates":[-95.456986,29.796974],"type":"Point"}
}