{
  "type": "Feature",
  "properties": {
    "iso:country":"US",
    "sg:address":"204 E Weaver Ave",
    "sg:city":"Alvarado",
    "sg:classifiers":[
        {
            "category":"Shopping",
            "subcategory":"Department Store",
            "type":"Retail Goods"
        }
    ],
    "sg:phone":"+1 817 790 2222",
    "sg:postcode":"76009",
    "sg:province":"TX",
    "sg:tags":[
        "shop"
    ],
    "wof:name":"Bill's Dollar Store",
    "wof:placetype":"venue"
},
  "geometry": {"coordinates":[-97.210229,32.40614],"type":"Point"}
}