{
  "type": "Feature",
  "properties": {
    "iso:country":"US",
    "sg:address":"401 E Miller Rd",
    "sg:city":"Garland",
    "sg:classifiers":[
        {
            "category":"Professional",
            "type":"Services"
        }
    ],
    "sg:phone":"+1 972 841 5021",
    "sg:postcode":"75041",
    "sg:province":"TX",
    "sg:tags":[
        "establishment"
    ],
    "wof:name":"Raymax",
    "wof:placetype":"venue"
},
  "geometry": {"coordinates":[-96.628033,32.894197],"type":"Point"}
}