{
  "type": "Feature",
  "properties": {
    "iso:country":"US",
    "sg:address":"6181 Saratoga Cir",
    "sg:city":"Dallas",
    "sg:classifiers":[
        {
            "category":"Restaurant",
            "type":"Food & Drink"
        }
    ],
    "sg:phone":"+1 214 824 5285",
    "sg:postcode":"75214",
    "sg:province":"TX",
    "sg:tags":[
        "eating"
    ],
    "wof:name":"Three Rivers Catering Inc",
    "wof:placetype":"venue"
},
  "geometry": {"coordinates":[-96.760707,32.840436],"type":"Point"}
}