{
  "type": "Feature",
  "properties": {
    "iso:country":"US",
    "sg:address":"801 Commerce St",
    "sg:city":"Robert Lee",
    "sg:classifiers":[
        {
            "category":"Restaurant",
            "type":"Food & Drink"
        }
    ],
    "sg:phone":"+1 325 453 2375",
    "sg:postcode":"76945",
    "sg:province":"TX",
    "wof:name":"Cracker Barrel Old Country Str",
    "wof:placetype":"venue"
},
  "geometry": {"coordinates":[-100.48374800000001,31.894142],"type":"Point"}
}