{
  "type": "Feature",
  "properties": {
    "iso:country":"US",
    "sg:address":"4528 W Vickery Blvd",
    "sg:city":"Fort Worth",
    "sg:classifiers":[
        {
            "category":"Professional",
            "subcategory":"Accounting & Tax Preparation",
            "type":"Services"
        }
    ],
    "sg:phone":"+1 817 877 1337",
    "sg:postcode":"76107",
    "sg:province":"TX",
    "wof:name":"Clinton M Brown Sr PC",
    "wof:placetype":"venue"
},
  "geometry": {"coordinates":[-97.38648000000001,32.719938],"type":"Point"}
}