{
  "type": "Feature",
  "properties": {
    "iso:country":"US",
    "sg:address":"1201 Cleveland Ave",
    "sg:city":"Friona",
    "sg:classifiers":[
        {
            "category":"Health Services",
            "subcategory":"Doctor",
            "type":"Services"
        }
    ],
    "sg:phone":"+1 806 250 3050",
    "sg:postcode":"79035",
    "sg:province":"TX",
    "sg:tags":[
        "dentist"
    ],
    "wof:name":"Jon Mack Rode Inc",
    "wof:placetype":"venue"
},
  "geometry": {"coordinates":[-102.72115599999999,34.642997],"type":"Point"}
}