{
  "type": "Feature",
  "properties": {
    "iso:country":"US",
    "sg:address":"1151 FM 424",
    "sg:city":"Crossroads",
    "sg:classifiers":[
        {
            "category":"Building & Trades",
            "subcategory":"Landscaping Services",
            "type":"Services"
        }
    ],
    "sg:phone":"+1 940 365 2280",
    "sg:postcode":"76227",
    "sg:province":"TX",
    "sg:tags":[
        "mowing"
    ],
    "wof:name":"Anthony's Services",
    "wof:placetype":"venue"
},
  "geometry": {"coordinates":[-96.989138,33.22837],"type":"Point"}
}