{
  "type": "Feature",
  "properties": {
    "iso:country":"US",
    "sg:address":"7250 Alameda Ave",
    "sg:city":"El Paso",
    "sg:classifiers":[
        {
            "category":"Insurance",
            "subcategory":"Insurance Agent",
            "type":"Services"
        }
    ],
    "sg:phone":"+1 915 771 9200",
    "sg:postcode":"79915",
    "sg:province":"TX",
    "wof:name":"Unistar Auto Insurance",
    "wof:placetype":"venue"
},
  "geometry": {"coordinates":[-106.38600700000001,31.748505],"type":"Point"}
}