{
  "type": "Feature",
  "properties": {
    "iso:country":"US",
    "sg:address":"6613 Biltmore Pl",
    "sg:city":"Plano",
    "sg:classifiers":[
        {
            "category":"Autos & Motor Vehicles",
            "subcategory":"Automobile Sales",
            "type":"Retail Goods"
        }
    ],
    "sg:phone":"+1 972 618 7313",
    "sg:postcode":"75023",
    "sg:province":"TX",
    "sg:tags":[
        "limo"
    ],
    "wof:name":"Aadvantage Limousine",
    "wof:placetype":"venue"
},
  "geometry": {"coordinates":[-96.76742299999999,33.255056],"type":"Point"}
}