{
  "type": "Feature",
  "properties": {
    "iso:country":"US",
    "sg:address":"518 E Camp Wisdom Rd",
    "sg:city":"Duncanville",
    "sg:classifiers":[
        {
            "category":"Retail",
            "subcategory":"Auto Repair",
            "type":"Services"
        }
    ],
    "sg:phone":"+1 972 298 0000",
    "sg:postcode":"75116",
    "sg:province":"TX",
    "wof:name":"Garage Radillo",
    "wof:placetype":"venue"
},
  "geometry": {"coordinates":[-96.900006,32.661733],"type":"Point"}
}