{
  "type": "Feature",
  "properties": {
    "iso:country":"US",
    "sg:address":"3105 Afton Dr",
    "sg:city":"Carrollton",
    "sg:classifiers":[
        {
            "category":"Place Of Worship",
            "type":"Public Place"
        }
    ],
    "sg:phone":"+1 972 394 1571",
    "sg:postcode":"75007",
    "sg:province":"TX",
    "sg:tags":[
        "church"
    ],
    "wof:name":"Grace Truth Integrity",
    "wof:placetype":"venue"
},
  "geometry": {"coordinates":[-96.909019,33.000746],"type":"Point"}
}