{
  "type": "Feature",
  "properties": {
    "iso:country":"US",
    "sg:address":"1106 Niagara St",
    "sg:city":"Houston",
    "sg:classifiers":[
        {
            "category":"Banks & Credit Unions",
            "subcategory":"Financial Services",
            "type":"Services"
        }
    ],
    "sg:phone":"+1 713 733 5464",
    "sg:postcode":"77051",
    "sg:province":"TX",
    "sg:tags":[
        "investment",
        "real estate"
    ],
    "wof:name":"Brookhaven Investment Services",
    "wof:placetype":"venue"
},
  "geometry": {"coordinates":[-95.360618,29.674524],"type":"Point"}
}