{
  "type": "Feature",
  "properties": {
    "iso:country":"US",
    "sg:address":"22023 Mossy Oaks Rd",
    "sg:city":"Spring",
    "sg:classifiers":[
        {
            "category":"Wholesale",
            "subcategory":"Machinery & Supplies",
            "type":"Manufacturing & Wholesale Goods"
        }
    ],
    "sg:phone":"+1 281 288 7100",
    "sg:postcode":"77389",
    "sg:province":"TX",
    "sg:tags":[
        "engine",
        "parts",
        "filtration"
    ],
    "wof:name":"Western Filter Co Inc",
    "wof:placetype":"venue"
},
  "geometry": {"coordinates":[-95.479539,30.08581],"type":"Point"}
}