{
  "type": "Feature",
  "properties": {
    "iso:country":"US",
    "sg:address":"15001 Walden Rd",
    "sg:city":"Montgomery",
    "sg:classifiers":[
        {
            "category":"Real Estate",
            "subcategory":"Real Estate Operator",
            "type":"Services"
        }
    ],
    "sg:phone":"+1 936 582 1470",
    "sg:postcode":"77356",
    "sg:province":"TX",
    "sg:tags":[
        "condominium"
    ],
    "sg:website":"www.bestbuy-timeshares.com",
    "wof:name":"International Condominium",
    "wof:placetype":"venue"
},
  "geometry": {"coordinates":[-95.652996,30.394872],"type":"Point"}
}