{
  "type": "Feature",
  "properties": {
    "iso:country":"US",
    "sg:address":"3671 Fm 802",
    "sg:city":"Brownsville",
    "sg:classifiers":[
        {
            "category":"Building & Trades",
            "subcategory":"Construction",
            "type":"Services"
        }
    ],
    "sg:phone":"+1 956 831 8151",
    "sg:postcode":"78526",
    "sg:province":"TX",
    "sg:tags":[
        "system",
        "specialty",
        "heating",
        "contractor",
        "air conditioning"
    ],
    "wof:name":"Carrier Air Conditioning",
    "wof:placetype":"venue"
},
  "geometry": {"coordinates":[-97.46292,25.948915],"type":"Point"}
}