{
  "type": "Feature",
  "properties": {
    "iso:country":"US",
    "sg:address":"8535 Tom Slick",
    "sg:city":"San Antonio",
    "sg:classifiers":[
        {
            "category":"Organizations",
            "subcategory":"Non-profit Organization",
            "type":"Services"
        }
    ],
    "sg:phone":"+1 210 614 7566",
    "sg:postcode":"78229",
    "sg:province":"TX",
    "wof:name":"Mental Health Assn",
    "wof:placetype":"venue"
},
  "geometry": {"coordinates":[-98.575238,29.520157],"type":"Point"}
}