{
  "type": "Feature",
  "properties": {
    "iso:country":"US",
    "sg:address":"234 E Trant Rd",
    "sg:city":"Kingsville",
    "sg:classifiers":[
        {
            "category":"Professional",
            "subcategory":"Engineering",
            "type":"Services"
        }
    ],
    "sg:phone":"+1 361 592 0067",
    "sg:postcode":"78363",
    "sg:province":"TX",
    "wof:name":"Boehm Brothers Engineering",
    "wof:placetype":"venue"
},
  "geometry": {"coordinates":[-97.863266,27.483499],"type":"Point"}
}