{
  "type": "Feature",
  "properties": {
    "iso:country":"US",
    "sg:address":"3141 Horton Rd",
    "sg:city":"Fort Worth",
    "sg:classifiers":[
        {
            "category":"Manufacturing",
            "subcategory":"Rubber & Plastics",
            "type":"Manufacturing & Wholesale Goods"
        }
    ],
    "sg:phone":"+1 817 534 1869",
    "sg:postcode":"76119",
    "sg:province":"TX",
    "sg:tags":[
        "sealing",
        "devices",
        "mfg"
    ],
    "wof:name":"Sealcom Inc",
    "wof:placetype":"venue"
},
  "geometry": {"coordinates":[-97.282712,32.680787],"type":"Point"}
}