{
  "type": "Feature",
  "properties": {
    "iso:country":"US",
    "sg:address":"4914 W 34th St",
    "sg:city":"Houston",
    "sg:classifiers":[
        {
            "category":"Wholesale",
            "subcategory":"Machinery & Supplies",
            "type":"Manufacturing & Wholesale Goods"
        }
    ],
    "sg:phone":"+1 713 688 4200",
    "sg:postcode":"77092",
    "sg:province":"TX",
    "sg:tags":[
        "dry wall",
        "contractor"
    ],
    "wof:name":"Ames Taping Tools Inc",
    "wof:placetype":"venue"
},
  "geometry": {"coordinates":[-95.46307299999999,29.81964],"type":"Point"}
}