{
  "type": "Feature",
  "properties": {
    "iso:country":"US",
    "sg:address":"2106 Old Dallas Rd",
    "sg:city":"Waco",
    "sg:classifiers":[
        {
            "category":"Building & Trades",
            "subcategory":"Plumbing",
            "type":"Services"
        }
    ],
    "sg:phone":"+1 254 799 9690",
    "sg:postcode":"76705",
    "sg:province":"TX",
    "sg:tags":[
        "plumbing",
        "contractor"
    ],
    "wof:name":"A Ok Plumbing Svc",
    "wof:placetype":"venue"
},
  "geometry": {"coordinates":[-97.117301,31.597958],"type":"Point"}
}