{
  "type": "Feature",
  "properties": {
    "iso:country":"US",
    "sg:address":"116 River Frst",
    "sg:city":"Castroville",
    "sg:classifiers":[
        {
            "category":"Building & Trades",
            "subcategory":"Construction",
            "type":"Services"
        }
    ],
    "sg:phone":"+1 830 538 3800",
    "sg:postcode":"78009",
    "sg:province":"TX",
    "sg:tags":[
        "painting",
        "contractor"
    ],
    "wof:name":"Hendrick Painting",
    "wof:placetype":"venue"
},
  "geometry": {"coordinates":[-98.895106,29.353273],"type":"Point"}
}