{
  "type": "Feature",
  "properties": {
    "iso:country":"US",
    "sg:address":"4127 Lively Ln",
    "sg:city":"Dallas",
    "sg:classifiers":[
        {
            "category":"Professional",
            "type":"Services"
        }
    ],
    "sg:phone":"+1 214 351 3444",
    "sg:postcode":"75220",
    "sg:province":"TX",
    "wof:name":"Twin CK Corp",
    "wof:placetype":"venue"
},
  "geometry": {"coordinates":[-96.842581,32.872776],"type":"Point"}
}