{
  "type": "Feature",
  "properties": {
    "iso:country":"US",
    "sg:address":"4503 Werner St",
    "sg:city":"Houston",
    "sg:classifiers":[
        {
            "category":"Real Estate",
            "subcategory":"Real Estate Operator",
            "type":"Services"
        }
    ],
    "sg:phone":"+1 713 697 0628",
    "sg:postcode":"77022",
    "sg:province":"TX",
    "sg:tags":[
        "apartment"
    ],
    "wof:name":"Monterrey Vista Apartments",
    "wof:placetype":"venue"
},
  "geometry": {"coordinates":[-95.396872,29.831123],"type":"Point"}
}