{
  "type": "Feature",
  "properties": {
    "iso:country":"US",
    "sg:address":"101 Sage St",
    "sg:city":"Terrell",
    "sg:classifiers":[
        {
            "category":"Professional",
            "subcategory":"Employment Agencies",
            "type":"Services"
        }
    ],
    "sg:phone":"+1 972 563 3902",
    "sg:postcode":"75160",
    "sg:province":"TX",
    "sg:tags":[
        "opportunity"
    ],
    "wof:name":"Kelly Educational Staffing",
    "wof:placetype":"venue"
},
  "geometry": {"coordinates":[-96.285383,32.739646],"type":"Point"}
}