{
  "type": "Feature",
  "properties": {
    "iso:country":"US",
    "sg:address":"13615 Welch Rd",
    "sg:city":"Dallas",
    "sg:classifiers":[
        {
            "category":"Retail",
            "subcategory":"Repair Shop",
            "type":"Services"
        },
        {
            "category":"Building & Trades",
            "subcategory":"Construction",
            "type":"Services"
        }
    ],
    "sg:phone":"+1 972 404 9984",
    "sg:postcode":"75244",
    "sg:province":"TX",
    "sg:tags":[
        "equipment",
        "installation",
        "elevator"
    ],
    "sg:website":"www.fujitecamerica.com",
    "wof:name":"Fujitec America Inc",
    "wof:placetype":"venue"
},
  "geometry": {"coordinates":[-96.830603,32.934614],"type":"Point"}
}