{
  "type": "Feature",
  "properties": {
    "iso:country":"US",
    "sg:address":"30403 Oak Tree Dr",
    "sg:city":"Georgetown",
    "sg:classifiers":[
        {
            "category":"Restaurant",
            "type":"Food & Drink"
        }
    ],
    "sg:phone":"+1 512 930 5863",
    "sg:postcode":"78628",
    "sg:province":"TX",
    "sg:tags":[
        "eating"
    ],
    "wof:name":"Cicis Pizza",
    "wof:placetype":"venue"
},
  "geometry": {"coordinates":[-97.674656,30.709024],"type":"Point"}
}