{
  "type": "Feature",
  "properties": {
    "iso:country":"US",
    "sg:address":"3823 Pinon Ave",
    "sg:city":"Amarillo",
    "sg:classifiers":[
        {
            "category":"Building & Trades",
            "subcategory":"Construction",
            "type":"Services"
        }
    ],
    "sg:phone":"+1 806 383 6097",
    "sg:postcode":"79107",
    "sg:province":"TX",
    "sg:tags":[
        "contractor"
    ],
    "wof:name":"Affordable Roofing",
    "wof:placetype":"venue"
},
  "geometry": {"coordinates":[-101.79136699999999,35.238411],"type":"Point"}
}