{
  "type": "Feature",
  "properties": {
    "iso:country":"US",
    "sg:address":"5102 E Veterans Memorial Blvd",
    "sg:city":"Killeen",
    "sg:classifiers":[
        {
            "category":"Restaurant",
            "type":"Food & Drink"
        }
    ],
    "sg:menulink":"http://www.allmenus.com/tx/killeen/94575-dominos-pizza/menu/",
    "sg:phone":"+1 254 699 4690",
    "sg:postcode":"76543",
    "sg:province":"TX",
    "sg:tags":[
        "american",
        "wing",
        "pizza"
    ],
    "wof:name":"Domino's Pizza",
    "wof:placetype":"venue"
},
  "geometry": {"coordinates":[-97.68747500000001,31.095105],"type":"Point"}
}