{
  "type": "Feature",
  "properties": {
    "iso:country":"US",
    "sg:address":"205 Industrial Ct",
    "sg:city":"Lake Dallas",
    "sg:classifiers":[
        {
            "category":"Communications",
            "type":"Services"
        }
    ],
    "sg:phone":"+1 940 321 6464",
    "sg:postcode":"75098",
    "sg:province":"TX",
    "wof:name":"Charter Communications",
    "wof:placetype":"venue"
},
  "geometry": {"coordinates":[-96.54124899999999,33.011714],"type":"Point"}
}