{
  "type": "Feature",
  "properties": {
    "iso:country":"US",
    "sg:address":"3526 N Vega Ave",
    "sg:city":"Odessa",
    "sg:classifiers":[
        {
            "category":"Building & Trades",
            "subcategory":"Plumbing",
            "type":"Services"
        }
    ],
    "sg:phone":"+1 432 530 3326",
    "sg:postcode":"79764",
    "sg:province":"TX",
    "sg:tags":[
        "plumber",
        "industrial",
        "contractors-commercial"
    ],
    "wof:name":"Budget Plumbing",
    "wof:placetype":"venue"
},
  "geometry": {"coordinates":[-102.476699,31.852907],"type":"Point"}
}