{
  "type": "Feature",
  "properties": {
    "iso:country":"US",
    "sg:address":"4041 W Wheatland Rd",
    "sg:city":"Dallas",
    "sg:classifiers":[
        {
            "category":"Social Services",
            "subcategory":"Job Training",
            "type":"Services"
        }
    ],
    "sg:phone":"+1 972 296 7789",
    "sg:postcode":"75237",
    "sg:province":"TX",
    "sg:tags":[
        "rehabilitation"
    ],
    "wof:name":"Rehab & Therapy Pegasus",
    "wof:placetype":"venue"
},
  "geometry": {"coordinates":[-96.880965,32.647675],"type":"Point"}
}