{
  "type": "Feature",
  "properties": {
    "iso:country":"US",
    "sg:address":"11900 Wickchester Ln",
    "sg:city":"Houston",
    "sg:classifiers":[
        {
            "category":"Real Estate",
            "subcategory":"Real Estate Operator",
            "type":"Services"
        }
    ],
    "sg:phone":"+1 281 531 6402",
    "sg:postcode":"77043",
    "sg:province":"TX",
    "sg:tags":[
        "apartment"
    ],
    "wof:name":"Eagle Hollow Apartments",
    "wof:placetype":"venue"
},
  "geometry": {"coordinates":[-95.59638200000001,29.788484],"type":"Point"}
}