{
  "type": "Feature",
  "properties": {
    "iso:country":"US",
    "sg:address":"265 N Hill St",
    "sg:city":"Itasca",
    "sg:phone":"+1 254 687 2709",
    "sg:postcode":"76055",
    "sg:province":"TX",
    "sg:tags":[
        "farm",
        "grain",
        "cash"
    ],
    "wof:name":"Bob Bassett",
    "wof:placetype":"venue"
},
  "geometry": {"coordinates":[-97.150902,32.161012],"type":"Point"}
}