{
  "type": "Feature",
  "properties": {
    "iso:country":"US",
    "sg:address":"15603 Kuykendahl Rd",
    "sg:city":"Houston",
    "sg:classifiers":[
        {
            "category":"Insurance",
            "subcategory":"Insurance Agent",
            "type":"Services"
        }
    ],
    "sg:phone":"+1 281 444 5573",
    "sg:postcode":"77068",
    "sg:province":"TX",
    "wof:name":"Bill Brewer Insurance",
    "wof:placetype":"venue"
},
  "geometry": {"coordinates":[-95.46368699999999,30.007089],"type":"Point"}
}