{
  "type": "Feature",
  "properties": {
    "iso:country":"US",
    "sg:address":"600 W Broadway St",
    "sg:city":"Andrews",
    "sg:classifiers":[
        {
            "category":"Retail",
            "subcategory":"Auto Repair",
            "type":"Services"
        }
    ],
    "sg:phone":"+1 432 524 2068",
    "sg:postcode":"79714",
    "sg:province":"TX",
    "sg:tags":[
        "body",
        "automobile",
        "painting"
    ],
    "wof:name":"S & L Collision Specialists",
    "wof:placetype":"venue"
},
  "geometry": {"coordinates":[-102.553696,32.317133],"type":"Point"}
}