{
  "type": "Feature",
  "properties": {
    "iso:country":"US",
    "sg:address":"1103 Riverside Dr",
    "sg:city":"Brownwood",
    "sg:classifiers":[
        {
            "category":"Travel",
            "subcategory":"Hotels & Motels",
            "type":"Entertainment"
        }
    ],
    "sg:phone":"+1 325 641 1122",
    "sg:postcode":"76801",
    "sg:province":"TX",
    "wof:name":"Hampton Inn",
    "wof:placetype":"venue"
},
  "geometry": {"coordinates":[-98.977518,31.728858],"type":"Point"}
}