{
  "type": "Feature",
  "properties": {
    "iso:country":"US",
    "sg:address":"9500 Garland Rd",
    "sg:city":"Dallas",
    "sg:classifiers":[
        {
            "category":"Retail",
            "subcategory":"Repair Shop",
            "type":"Services"
        }
    ],
    "sg:phone":"+1 214 321 5678",
    "sg:postcode":"75218",
    "sg:province":"TX",
    "sg:tags":[
        "lock",
        "locksmith"
    ],
    "wof:name":"A 1 Anytime Locksmith",
    "wof:placetype":"venue"
},
  "geometry": {"coordinates":[-96.702258,32.833827],"type":"Point"}
}