{
  "type": "Feature",
  "properties": {
    "iso:country":"US",
    "sg:address":"620 Northpark Ctr",
    "sg:city":"Dallas",
    "sg:classifiers":[
        {
            "category":"Shopping",
            "subcategory":"Clothing, Apparel, & Fashions",
            "type":"Retail Goods"
        }
    ],
    "sg:phone":"+1 214 373 7523",
    "sg:postcode":"75225",
    "sg:province":"TX",
    "sg:tags":[
        "accessory",
        "clothing",
        "women's"
    ],
    "wof:name":"Express",
    "wof:placetype":"venue"
},
  "geometry": {"coordinates":[-96.773399,32.869301],"type":"Point"}
}