{
  "type": "Feature",
  "properties": {
    "iso:country":"US",
    "sg:address":"2002 US Hwy 281",
    "sg:city":"Marble Falls",
    "sg:classifiers":[
        {
            "category":"Banks & Credit Unions",
            "subcategory":"Bank",
            "type":"Services"
        }
    ],
    "sg:phone":"+1 830 798 0687",
    "sg:postcode":"78654",
    "sg:province":"TX",
    "sg:tags":[
        "loan"
    ],
    "wof:name":"Star Loans",
    "wof:placetype":"venue"
},
  "geometry": {"coordinates":[-98.286432,30.524812],"type":"Point"}
}