{
  "type": "Feature",
  "properties": {
    "iso:country":"US",
    "sg:address":"518 N Interurban St",
    "sg:city":"Richardson",
    "sg:classifiers":[
        {
            "category":"Professional",
            "subcategory":"Advertising",
            "type":"Services"
        }
    ],
    "sg:phone":"+1 972 234 8286",
    "sg:postcode":"75081",
    "sg:province":"TX",
    "wof:name":"Metroplex Distributing",
    "wof:placetype":"venue"
},
  "geometry": {"coordinates":[-96.727389,32.95724],"type":"Point"}
}