{
  "type": "Feature",
  "properties": {
    "iso:country":"US",
    "sg:address":"21010 Secretariat Ridge Ln",
    "sg:city":"Pflugerville",
    "sg:classifiers":[
        {
            "category":"Internet Cafe",
            "subcategory":"None",
            "type":"Food & Drink"
        },
        {
            "category":"Professional",
            "subcategory":"Computer Services",
            "type":"Services"
        }
    ],
    "sg:phone":"+1 512 236 5795",
    "sg:postcode":"78660",
    "sg:province":"TX",
    "sg:tags":[
        "repair",
        "product",
        "data",
        "recovery",
        "equipment-service"
    ],
    "sg:website":"http://austin.citysearch.com/profile/external/603868612/pflugerville_tx/fast_teks_north_austin.html?publisher=yellowpages&reference_id=15&placement=ypwebsitemip",
    "wof:name":"Fast-teks North Austin",
    "wof:placetype":"venue"
},
  "geometry": {"coordinates":[-97.578767,30.494925],"type":"Point"}
}