{
  "type": "Feature",
  "properties": {
    "iso:country":"US",
    "sg:address":"200 S Franklin St",
    "sg:city":"Holland",
    "sg:classifiers":[
        {
            "category":"Food & Beverages",
            "subcategory":"Liquor & Beverages",
            "type":"Retail Goods"
        }
    ],
    "sg:phone":"+1 254 657 2711",
    "sg:postcode":"76534",
    "sg:province":"TX",
    "sg:tags":[
        "alcoholic"
    ],
    "wof:name":"Chief's Liquor & Tobacco Depot",
    "wof:placetype":"venue"
},
  "geometry": {"coordinates":[-97.402069,30.877613],"type":"Point"}
}