{
  "type": "Feature",
  "properties": {
    "iso:country":"US",
    "sg:address":"3231 Co Rd 2502",
    "sg:city":"Caddo Mills",
    "sg:classifiers":[
        {
            "category":"Wholesale",
            "subcategory":"Machinery & Supplies",
            "type":"Manufacturing & Wholesale Goods"
        }
    ],
    "sg:phone":"+1 903 527 4510",
    "sg:postcode":"75135",
    "sg:province":"TX",
    "sg:tags":[
        "lawn",
        "industrial",
        "parts",
        "mower"
    ],
    "wof:name":"H S C Supply Company",
    "wof:placetype":"venue"
},
  "geometry": {"coordinates":[-96.190363,33.011712],"type":"Point"}
}