{
  "type": "Feature",
  "properties": {
    "iso:country":"US",
    "sg:address":"403 Azle Hwy",
    "sg:city":"Weatherford",
    "sg:classifiers":[
        {
            "category":"Autos & Motor Vehicles",
            "subcategory":"Motorcycle Sales",
            "type":"Retail Goods"
        }
    ],
    "sg:phone":"+1 817 596 9350",
    "sg:postcode":"76085",
    "sg:province":"TX",
    "sg:tags":[
        "repair"
    ],
    "wof:name":"DRD Machine",
    "wof:placetype":"venue"
},
  "geometry": {"coordinates":[-97.740756,32.770375],"type":"Point"}
}