{
  "type": "Feature",
  "properties": {
    "iso:country":"US",
    "sg:address":"8502 Willoughby Blvd",
    "sg:city":"Dallas",
    "sg:classifiers":[
        {
            "category":"Social Services",
            "subcategory":"Child Care",
            "type":"Services"
        }
    ],
    "sg:phone":"+1 972 224 0119",
    "sg:postcode":"75232",
    "sg:province":"TX",
    "sg:tags":[
        "day"
    ],
    "wof:name":"Kidz Place Learning Dev",
    "wof:placetype":"venue"
},
  "geometry": {"coordinates":[-96.829223,32.646615],"type":"Point"}
}