{
  "type": "Feature",
  "properties": {
    "iso:country":"US",
    "sg:address":"2862 Warncke Rd",
    "sg:city":"La Vernia",
    "sg:classifiers":[
        {
            "category":"Building & Trades",
            "subcategory":"Construction",
            "type":"Services"
        }
    ],
    "sg:phone":"+1 830 303 5362",
    "sg:postcode":"78121",
    "sg:province":"TX",
    "sg:tags":[
        "contractor"
    ],
    "wof:name":"Bills Welding Service",
    "wof:placetype":"venue"
},
  "geometry": {"coordinates":[-98.07548199999999,29.436893],"type":"Point"}
}