{
  "type": "Feature",
  "properties": {
    "iso:country":"US",
    "sg:address":"5990 College St",
    "sg:city":"Beaumont",
    "sg:classifiers":[
        {
            "category":"Retail",
            "subcategory":"Repair Shop",
            "type":"Services"
        }
    ],
    "sg:phone":"+1 409 860 0038",
    "sg:postcode":"77707",
    "sg:province":"TX",
    "sg:tags":[
        "boat"
    ],
    "wof:name":"Water Crafts Etc",
    "wof:placetype":"venue"
},
  "geometry": {"coordinates":[-94.15992,30.067893],"type":"Point"}
}