{
  "type": "Feature",
  "properties": {
    "iso:country":"US",
    "sg:address":"35823 Post Oak Cir",
    "sg:city":"Magnolia",
    "sg:classifiers":[
        {
            "category":"Freight",
            "type":"Transportation"
        }
    ],
    "sg:phone":"+1 281 252 6732",
    "sg:postcode":"77355",
    "sg:province":"TX",
    "sg:tags":[
        "operator",
        "local",
        "trucking"
    ],
    "wof:name":"Anderson Dump Trucking Inc",
    "wof:placetype":"venue"
},
  "geometry": {"coordinates":[-95.700872,30.168032],"type":"Point"}
}