{
  "type": "Feature",
  "properties": {
    "iso:country":"US",
    "sg:address":"15255 Gulf Fwy",
    "sg:city":"Houston",
    "sg:classifiers":[
        {
            "category":"Professional",
            "subcategory":"Engineering",
            "type":"Services"
        },
        {
            "category":"Home & Garden",
            "subcategory":"Building Materials",
            "type":"Retail Goods"
        },
        {
            "category":"Building & Trades",
            "subcategory":"Construction",
            "type":"Services"
        },
        {
            "category":"Home & Garden",
            "subcategory":"Household Appliances",
            "type":"Retail Goods"
        }
    ],
    "sg:phone":"+1 281 484 3839",
    "sg:postcode":"77034",
    "sg:province":"TX",
    "sg:tags":[
        "repair",
        "systems-repairing",
        "system",
        "specialty",
        "equipment",
        "heat",
        "heating",
        "pump",
        "contractor",
        "air conditioning"
    ],
    "sg:website":"http://www.aaronsac.com",
    "wof:name":"Aaron's AC And Heat",
    "wof:placetype":"venue"
},
  "geometry": {"coordinates":[-95.187254,29.589809],"type":"Point"}
}