{
  "type": "Feature",
  "properties": {
    "iso:country":"US",
    "sg:address":"318 S Cedar St",
    "sg:city":"Pecos",
    "sg:classifiers":[
        {
            "category":"Banks & Credit Unions",
            "subcategory":"Investment Brokerage",
            "type":"Services"
        }
    ],
    "sg:phone":"+1 432 445 2773",
    "sg:postcode":"79772",
    "sg:province":"TX",
    "wof:name":"Bill Hubbs Enterprises",
    "wof:placetype":"venue"
},
  "geometry": {"coordinates":[-103.49418,31.425724],"type":"Point"}
}