{
  "type": "Feature",
  "properties": {
    "iso:country":"US",
    "sg:address":"5221 88th St",
    "sg:city":"Lubbock",
    "sg:phone":"+1 806 794 1695",
    "sg:postcode":"79424",
    "sg:province":"TX",
    "sg:tags":[
        "farm",
        "cotton"
    ],
    "wof:name":"Warren Family Ltd",
    "wof:placetype":"venue"
},
  "geometry": {"coordinates":[-101.924667,33.51347],"type":"Point"}
}