{
  "type": "Feature",
  "properties": {
    "iso:country":"US",
    "sg:address":"526 E Mesquite St",
    "sg:city":"Uvalde",
    "sg:classifiers":[
        {
            "category":"Professional",
            "subcategory":"Art Services",
            "type":"Services"
        }
    ],
    "sg:phone":"+1 830 278 8872",
    "sg:postcode":"78801",
    "sg:province":"TX",
    "sg:tags":[
        "high",
        "end",
        "graphic",
        "electronic",
        "computer"
    ],
    "wof:name":"Touchpoint Digital",
    "wof:placetype":"venue"
},
  "geometry": {"coordinates":[-99.779478,29.216884],"type":"Point"}
}