{
  "type": "Feature",
  "properties": {
    "iso:country":"US",
    "sg:address":"2307 N John Redditt Dr",
    "sg:city":"Lufkin",
    "sg:classifiers":[
        {
            "category":"Real Estate",
            "subcategory":"Real Estate Operator",
            "type":"Services"
        }
    ],
    "sg:phone":"+1 936 639 5715",
    "sg:postcode":"75904",
    "sg:province":"TX",
    "sg:tags":[
        "mobile",
        "home",
        "community"
    ],
    "wof:name":"Pine Valley Mobile Home Vlg",
    "wof:placetype":"venue"
},
  "geometry": {"coordinates":[-94.764036,31.35867],"type":"Point"}
}