{
  "type": "Feature",
  "properties": {
    "iso:country":"US",
    "sg:address":"4378 Lawrence Dr",
    "sg:city":"Garland",
    "sg:classifiers":[
        {
            "category":"Professional",
            "subcategory":"Management & Consulting",
            "type":"Services"
        }
    ],
    "sg:phone":"+1 972 530 3575",
    "sg:postcode":"75044",
    "sg:province":"TX",
    "sg:tags":[
        "business"
    ],
    "wof:name":"Spj Consulting",
    "wof:placetype":"venue"
},
  "geometry": {"coordinates":[-96.667446,32.956292],"type":"Point"}
}