{
  "type": "Feature",
  "properties": {
    "iso:country":"US",
    "sg:address":"303 Sixpence Ln",
    "sg:city":"Euless",
    "sg:classifiers":[
        {
            "category":"Professional",
            "type":"Services"
        }
    ],
    "sg:phone":"+1 817 354 8729",
    "sg:postcode":"76039",
    "sg:province":"TX",
    "wof:name":"Stuff-You-Want Biz",
    "wof:placetype":"venue"
},
  "geometry": {"coordinates":[-97.079767,32.844225],"type":"Point"}
}