{
  "type": "Feature",
  "properties": {
    "iso:country":"US",
    "sg:address":"2145 N Josey Ln",
    "sg:city":"Carrollton",
    "sg:classifiers":[
        {
            "category":"Health Services",
            "subcategory":"Chiropractor",
            "type":"Services"
        }
    ],
    "sg:phone":"+1 972 323 6464",
    "sg:postcode":"75006",
    "sg:province":"TX",
    "wof:name":"Southwest Chiropractic",
    "wof:placetype":"venue"
},
  "geometry": {"coordinates":[-96.88999800000001,32.975506],"type":"Point"}
}