{
  "type": "Feature",
  "properties": {
    "iso:country":"US",
    "sg:address":"167 Howell St",
    "sg:city":"Dallas",
    "sg:classifiers":[
        {
            "category":"Building & Trades",
            "subcategory":"Equipment Rental",
            "type":"Services"
        }
    ],
    "sg:phone":"+1 214 748 1000",
    "sg:postcode":"75207",
    "sg:province":"TX",
    "sg:tags":[
        "leasing"
    ],
    "wof:name":"Nationwide Leasing Corp",
    "wof:placetype":"venue"
},
  "geometry": {"coordinates":[-96.820789,32.787044],"type":"Point"}
}