{
  "type": "Feature",
  "properties": {
    "iso:country":"US",
    "sg:address":"5232 China Garden Dr",
    "sg:city":"Austin",
    "sg:classifiers":[
        {
            "category":"Real Estate",
            "subcategory":"Real Estate Operator",
            "type":"Services"
        }
    ],
    "sg:phone":"+1 512 342 2246",
    "sg:postcode":"78730",
    "sg:province":"TX",
    "sg:tags":[
        "property",
        "lessor"
    ],
    "wof:name":"B N B Group",
    "wof:placetype":"venue"
},
  "geometry": {"coordinates":[-97.84814900000001,30.374141],"type":"Point"}
}