{
  "type": "Feature",
  "properties": {
    "iso:country":"US",
    "sg:address":"10550 Goodnight Ln",
    "sg:city":"Dallas",
    "sg:classifiers":[
        {
            "category":"Wholesale",
            "subcategory":"Scrap",
            "type":"Manufacturing & Wholesale Goods"
        }
    ],
    "sg:phone":"+1 972 444 8669",
    "sg:postcode":"75220",
    "sg:province":"TX",
    "sg:tags":[
        "steel"
    ],
    "wof:name":"Jacobs Usable Steel Sales",
    "wof:placetype":"venue"
},
  "geometry": {"coordinates":[-96.902283,32.870237],"type":"Point"}
}