{
  "type": "Feature",
  "properties": {
    "iso:country":"US",
    "sg:address":"1140 N Tuna Dr",
    "sg:city":"Port Bolivar",
    "sg:classifiers":[
        {
            "category":"Professional",
            "type":"Services"
        }
    ],
    "sg:phone":"+1 409 684 1721",
    "sg:postcode":"77617",
    "sg:province":"TX",
    "sg:tags":[
        "establishment"
    ],
    "wof:name":"Thorp Crab",
    "wof:placetype":"venue"
},
  "geometry": {"coordinates":[-94.579348,29.490579],"type":"Point"}
}