{
  "type": "Feature",
  "properties": {
    "iso:country":"US",
    "sg:address":"2006 Norfolk St",
    "sg:city":"Houston",
    "sg:classifiers":[
        {
            "category":"Professional",
            "subcategory":"Business Services",
            "type":"Services"
        }
    ],
    "sg:phone":"+1 713 528 7517",
    "sg:postcode":"77098",
    "sg:province":"TX",
    "sg:tags":[
        "consulting",
        "computer"
    ],
    "wof:name":"Johnson Jimmy",
    "wof:placetype":"venue"
},
  "geometry": {"coordinates":[-95.408947,29.732654],"type":"Point"}
}