{
  "type": "Feature",
  "properties": {
    "iso:country":"US",
    "sg:address":"424 Johns Rd",
    "sg:city":"Boerne",
    "sg:classifiers":[
        {
            "category":"Recreation",
            "type":"Entertainment"
        }
    ],
    "sg:phone":"+1 830 249 7109",
    "sg:postcode":"78006",
    "sg:province":"TX",
    "sg:tags":[
        "club",
        "baseball"
    ],
    "wof:name":"BYAA Merchant Field",
    "wof:placetype":"venue"
},
  "geometry": {"coordinates":[-98.744438,29.795279],"type":"Point"}
}