{
  "type": "Feature",
  "properties": {
    "iso:country":"US",
    "sg:address":"312 W Alabama St",
    "sg:city":"Mount Pleasant",
    "sg:classifiers":[
        {
            "category":"Organizations",
            "subcategory":"Religious Organization",
            "type":"Services"
        }
    ],
    "sg:phone":"+1 903 575 1124",
    "sg:postcode":"75455",
    "sg:province":"TX",
    "wof:name":"Christian Community Radio",
    "wof:placetype":"venue"
},
  "geometry": {"coordinates":[-94.970917,33.155946],"type":"Point"}
}