{
  "type": "Feature",
  "properties": {
    "iso:country":"US",
    "sg:address":"3435 Marvin D Love Fwy",
    "sg:city":"Dallas",
    "sg:classifiers":[
        {
            "category":"Retail",
            "subcategory":"Veterinary Services",
            "type":"Services"
        }
    ],
    "sg:phone":"+1 214 376 5432",
    "sg:postcode":"75237",
    "sg:province":"TX",
    "sg:tags":[
        "animal"
    ],
    "wof:name":"Pet Coiffure",
    "wof:placetype":"venue"
},
  "geometry": {"coordinates":[-96.832652,32.704468],"type":"Point"}
}