{
  "type": "Feature",
  "properties": {
    "iso:country":"US",
    "sg:address":"2900 Aberdeen Dr",
    "sg:city":"Flower Mound",
    "sg:classifiers":[
        {
            "category":"Shopping",
            "subcategory":"Jewelry",
            "type":"Retail Goods"
        }
    ],
    "sg:phone":"+1 972 874 1246",
    "sg:postcode":"75022",
    "sg:province":"TX",
    "sg:tags":[
        "repair"
    ],
    "wof:name":"Belchers Goldworks Inc",
    "wof:placetype":"venue"
},
  "geometry": {"coordinates":[-97.074089,33.001536],"type":"Point"}
}