{
  "type": "Feature",
  "properties": {
    "iso:country":"US",
    "sg:address":"1728 Briercroft Ct",
    "sg:city":"Carrollton",
    "sg:classifiers":[
        {
            "category":"Wholesale",
            "subcategory":"Non-durable Goods",
            "type":"Manufacturing & Wholesale Goods"
        },
        {
            "category":"Professional",
            "subcategory":"Business Services",
            "type":"Services"
        }
    ],
    "sg:phone":"+1 972 245 6800",
    "sg:postcode":"75006",
    "sg:province":"TX",
    "sg:tags":[
        "broker",
        "merchandise",
        "merchandise-wholesale"
    ],
    "wof:name":"E Tail Surplus",
    "wof:placetype":"venue"
},
  "geometry": {"coordinates":[-96.928631,32.938544],"type":"Point"}
}