{
  "type": "Feature",
  "properties": {
    "iso:country":"US",
    "sg:address":"123 W Collin St",
    "sg:city":"Corsicana",
    "sg:classifiers":[
        {
            "category":"Shopping",
            "subcategory":"Computers & Home Electronics",
            "type":"Retail Goods"
        }
    ],
    "sg:phone":"+1 903 874 6594",
    "sg:postcode":"75110",
    "sg:province":"TX",
    "sg:tags":[
        "equipment",
        "dealer"
    ],
    "wof:name":"Dean Thedford Office Supply",
    "wof:placetype":"venue"
},
  "geometry": {"coordinates":[-96.463798,32.093412],"type":"Point"}
}