{
  "type": "Feature",
  "properties": {
    "iso:country":"US",
    "sg:address":"4125 College St",
    "sg:city":"Beaumont",
    "sg:classifiers":[
        {
            "category":"Autos & Motor Vehicles",
            "subcategory":"Automobile Sales",
            "type":"Retail Goods"
        }
    ],
    "sg:phone":"+1 409 842 0055",
    "sg:postcode":"77707",
    "sg:province":"TX",
    "sg:tags":[
        "car",
        "used"
    ],
    "wof:name":"Taylor Trading Co",
    "wof:placetype":"venue"
},
  "geometry": {"coordinates":[-94.138186,30.068075],"type":"Point"}
}