{
  "type": "Feature",
  "properties": {
    "iso:country":"US",
    "sg:address":"1704 International St",
    "sg:city":"Edinburg",
    "sg:classifiers":[
        {
            "category":"Manufacturing",
            "subcategory":"Glass & Minerals",
            "type":"Manufacturing & Wholesale Goods"
        }
    ],
    "sg:phone":"+1 956 381 0686",
    "sg:postcode":"78539",
    "sg:province":"TX",
    "sg:tags":[
        "product",
        "cut",
        "nonmetallic",
        "mfg"
    ],
    "wof:name":"Sculptures Unlimited",
    "wof:placetype":"venue"
},
  "geometry": {"coordinates":[-98.184715,26.269234],"type":"Point"}
}