{
  "type": "Feature",
  "properties": {
    "iso:country":"US",
    "sg:address":"5810 Fm 603",
    "sg:city":"Clyde",
    "sg:classifiers":[
        {
            "category":"Place Of Worship",
            "subcategory":"Church",
            "type":"Public Place"
        },
        {
            "category":"Place Of Worship",
            "type":"Public Place"
        }
    ],
    "sg:phone":"+1 325 529 4241",
    "sg:postcode":"79510",
    "sg:province":"TX",
    "sg:tags":[
        "churches-methodist"
    ],
    "wof:name":"Eula Methodist Church",
    "wof:placetype":"venue"
},
  "geometry": {"coordinates":[-99.562082,32.34394],"type":"Point"}
}