{
  "type": "Feature",
  "properties": {
    "iso:country":"US",
    "sg:address":"144 Bastrop St",
    "sg:city":"Angleton",
    "sg:classifiers":[
        {
            "category":"Retail",
            "subcategory":"Portrait Studio",
            "type":"Services"
        }
    ],
    "sg:phone":"+1 979 848 0636",
    "sg:postcode":"77515",
    "sg:province":"TX",
    "sg:tags":[
        "photographer",
        "photo"
    ],
    "wof:name":"Scott's Photography",
    "wof:placetype":"venue"
},
  "geometry": {"coordinates":[-95.408041,29.178748],"type":"Point"}
}