{
  "type": "Feature",
  "properties": {
    "iso:country":"US",
    "sg:address":"9355 Winlin Rd",
    "sg:city":"Orange",
    "sg:classifiers":[
        {
            "category":"Wholesale",
            "subcategory":"Durable Goods & Equipment",
            "type":"Manufacturing & Wholesale Goods"
        }
    ],
    "sg:phone":"+1 409 745 1696",
    "sg:postcode":"77632",
    "sg:province":"TX",
    "wof:name":"AB Enterprises",
    "wof:placetype":"venue"
},
  "geometry": {"coordinates":[-93.900841,30.16873],"type":"Point"}
}