{
  "type": "Feature",
  "properties": {
    "iso:country":"US",
    "sg:address":"2833 Trinity Square Dr",
    "sg:city":"Carrollton",
    "sg:classifiers":[
        {
            "category":"Organizations",
            "subcategory":"Religious Organization",
            "type":"Services"
        }
    ],
    "sg:phone":"+1 972 417 3875",
    "sg:postcode":"75006",
    "sg:province":"TX",
    "wof:name":"Assembleia Da Deus Missionaria",
    "wof:placetype":"venue"
},
  "geometry": {"coordinates":[-96.853724,32.983727],"type":"Point"}
}