{
  "type": "Feature",
  "properties": {
    "iso:country":"US",
    "sg:address":"4203 State Hwy 6 S",
    "sg:city":"College Station",
    "sg:classifiers":[
        {
            "category":"Education",
            "subcategory":"School",
            "type":"Public Place"
        }
    ],
    "sg:phone":"+1 979 690 7714",
    "sg:postcode":"77845",
    "sg:province":"TX",
    "sg:website":"www.christ-umc.org",
    "wof:name":"School For Little People",
    "wof:placetype":"venue"
},
  "geometry": {"coordinates":[-96.277812,30.575828],"type":"Point"}
}