{
  "type": "Feature",
  "properties": {
    "iso:country":"US",
    "sg:address":"115 Main St",
    "sg:city":"Lometa",
    "sg:classifiers":[
        {
            "category":"Mining & Drilling",
            "type":"Manufacturing & Wholesale Goods"
        }
    ],
    "sg:phone":"+1 512 752 3444",
    "sg:postcode":"76853",
    "sg:province":"TX",
    "sg:tags":[
        "oil",
        "gas",
        "producer"
    ],
    "wof:name":"Troy Duncan Oil Co",
    "wof:placetype":"venue"
},
  "geometry": {"coordinates":[-98.392938,31.216797],"type":"Point"}
}