{
  "type": "Feature",
  "properties": {
    "iso:country":"US",
    "sg:address":"150 N Sam Houston Pkwy E",
    "sg:city":"Houston",
    "sg:classifiers":[
        {
            "category":"Retail",
            "subcategory":"Auto Repair",
            "type":"Services"
        }
    ],
    "sg:phone":"+1 281 931 0279",
    "sg:postcode":"77060",
    "sg:province":"TX",
    "wof:name":"Q Auto Sales",
    "wof:placetype":"venue"
},
  "geometry": {"coordinates":[-95.408261,29.94007],"type":"Point"}
}