{
  "type": "Feature",
  "properties": {
    "iso:country":"US",
    "sg:address":"885 Berry Ln",
    "sg:city":"Madisonville",
    "sg:classifiers":[
        {
            "category":"Retail",
            "subcategory":"Laundry & Dry Cleaning",
            "type":"Services"
        }
    ],
    "sg:phone":"+1 936 348 2205",
    "sg:postcode":"77864",
    "sg:province":"TX",
    "sg:tags":[
        "cleaner",
        "rug",
        "carpet"
    ],
    "wof:name":"Steves Carpet Cleaning",
    "wof:placetype":"venue"
},
  "geometry": {"coordinates":[-95.925916,31.00596],"type":"Point"}
}