{
  "type": "Feature",
  "properties": {
    "iso:country":"US",
    "sg:address":"2425 Wyman St",
    "sg:city":"Dallas",
    "sg:classifiers":[
        {
            "category":"Professional",
            "subcategory":"Engineering",
            "type":"Services"
        }
    ],
    "sg:phone":"+1 214 654 0251",
    "sg:postcode":"75235",
    "sg:province":"TX",
    "sg:tags":[
        "engineer"
    ],
    "wof:name":"Arinc Inc",
    "wof:placetype":"venue"
},
  "geometry": {"coordinates":[-96.864099,32.842632],"type":"Point"}
}