{
  "type": "Feature",
  "properties": {
    "iso:country":"US",
    "sg:address":"325 Justice Rd",
    "sg:city":"Nacogdoches",
    "sg:classifiers":[
        {
            "category":"Building & Trades",
            "subcategory":"Construction",
            "type":"Services"
        }
    ],
    "sg:phone":"+1 936 560 5103",
    "sg:postcode":"75961",
    "sg:province":"TX",
    "sg:tags":[
        "contractor"
    ],
    "wof:name":"Darrell Kenney Construction",
    "wof:placetype":"venue"
},
  "geometry": {"coordinates":[-94.602969,31.588441],"type":"Point"}
}