{
  "type": "Feature",
  "properties": {
    "iso:country":"US",
    "sg:address":"4001 McEwen Rd",
    "sg:city":"Dallas",
    "sg:classifiers":[
        {
            "category":"Banks & Credit Unions",
            "subcategory":"Bank",
            "type":"Services"
        }
    ],
    "sg:phone":"+1 972 233 8200",
    "sg:postcode":"75244",
    "sg:province":"TX",
    "sg:tags":[
        "lender",
        "loan",
        "student"
    ],
    "wof:name":"Mega Life and Health Insur Co",
    "wof:placetype":"venue"
},
  "geometry": {"coordinates":[-96.83909199999999,32.928849],"type":"Point"}
}