{
  "type": "Feature",
  "properties": {
    "iso:country":"US",
    "sg:address":"1607 Lynnview Dr",
    "sg:city":"Houston",
    "sg:classifiers":[
        {
            "category":"Arts & Performance",
            "subcategory":"Music",
            "type":"Entertainment"
        }
    ],
    "sg:phone":"+1 713 467 7392",
    "sg:postcode":"77055",
    "sg:province":"TX",
    "sg:tags":[
        "dj"
    ],
    "wof:name":"Your D J",
    "wof:placetype":"venue"
},
  "geometry": {"coordinates":[-95.492302,29.799299],"type":"Point"}
}