{
  "type": "Feature",
  "properties": {
    "iso:country":"US",
    "sg:address":"20006 Co Rd 3400",
    "sg:city":"Slaton",
    "sg:classifiers":[
        {
            "category":"Restaurant",
            "type":"Food & Drink"
        }
    ],
    "sg:phone":"+1 806 828 6397",
    "sg:postcode":"79364",
    "sg:province":"TX",
    "sg:tags":[
        "eating"
    ],
    "wof:name":"Road Runner Catering",
    "wof:placetype":"venue"
},
  "geometry": {"coordinates":[-101.65952,33.412492],"type":"Point"}
}