{
  "type": "Feature",
  "properties": {
    "iso:country":"US",
    "sg:address":"215 Fritz Zwicke Rd",
    "sg:city":"Seguin",
    "sg:classifiers":[
        {
            "category":"Building & Trades",
            "subcategory":"Landscaping Services",
            "type":"Services"
        }
    ],
    "sg:phone":"+1 830 914 4738",
    "sg:postcode":"78155",
    "sg:province":"TX",
    "wof:name":"Drb Services",
    "wof:placetype":"venue"
},
  "geometry": {"coordinates":[-98.085881,29.506304],"type":"Point"}
}