{
  "type": "Feature",
  "properties": {
    "iso:country":"US",
    "sg:address":"1116 Wyoming Ave",
    "sg:city":"El Paso",
    "sg:classifiers":[
        {
            "category":"Professional",
            "subcategory":"Business Services",
            "type":"Services"
        }
    ],
    "sg:phone":"+1 915 532 1735",
    "sg:postcode":"79902",
    "sg:province":"TX",
    "wof:name":"El Paso Bid Depository System",
    "wof:placetype":"venue"
},
  "geometry": {"coordinates":[-106.48127100000001,31.768193],"type":"Point"}
}