{
  "type": "Feature",
  "properties": {
    "iso:country":"US",
    "sg:address":"9030 Cosmos Ave",
    "sg:city":"El Paso",
    "sg:classifiers":[
        {
            "category":"Recreation",
            "type":"Entertainment"
        }
    ],
    "sg:phone":"+1 915 541 4331",
    "sg:postcode":"79925",
    "sg:province":"TX",
    "sg:tags":[
        "parks"
    ],
    "wof:name":"Cielo Vista Park",
    "wof:placetype":"venue"
},
  "geometry": {"coordinates":[-106.36554700000001,31.784172],"type":"Point"}
}