{
  "type": "Feature",
  "properties": {
    "iso:country":"US",
    "sg:address":"510 E Bedford St",
    "sg:city":"Dimmitt",
    "sg:classifiers":[
        {
            "category":"Freight",
            "type":"Transportation"
        }
    ],
    "sg:phone":"+1 806 647 2141",
    "sg:postcode":"79027",
    "sg:province":"TX",
    "sg:tags":[
        "grain",
        "elevator"
    ],
    "wof:name":"Agri Farm Ind LLC",
    "wof:placetype":"venue"
},
  "geometry": {"coordinates":[-102.30690800000001,34.550779],"type":"Point"}
}