{
  "type": "Feature",
  "properties": {
    "iso:country":"US",
    "sg:address":"9101 Westminster Glen Ave",
    "sg:city":"Austin",
    "sg:classifiers":[
        {
            "category":"Banks & Credit Unions",
            "subcategory":"Financial Services",
            "type":"Services"
        }
    ],
    "sg:phone":"+1 512 349 2664",
    "sg:postcode":"78730",
    "sg:province":"TX",
    "sg:tags":[
        "investor"
    ],
    "wof:name":"Deckwise Investments LLC",
    "wof:placetype":"venue"
},
  "geometry": {"coordinates":[-97.836167,30.362996],"type":"Point"}
}