{
  "type": "Feature",
  "properties": {
    "iso:country":"US",
    "sg:address":"8501 N Navarro St",
    "sg:city":"Victoria",
    "sg:classifiers":[
        {
            "category":"Fast Food",
            "type":"Food & Drink"
        },
        {
            "category":"Restaurant",
            "type":"Food & Drink"
        }
    ],
    "sg:phone":"+1 361 485 2650",
    "sg:postcode":"77904",
    "sg:province":"TX",
    "sg:tags":[
        "american",
        "hot",
        "hamburger",
        "dog"
    ],
    "sg:website":"http://www.bk.com",
    "wof:name":"Burger King",
    "wof:placetype":"venue"
},
  "geometry": {"coordinates":[-96.997716,28.871871],"type":"Point"}
}