{
  "type": "Feature",
  "properties": {
    "iso:country":"US",
    "sg:address":"3220 Shadow Wood Cir",
    "sg:city":"Lewisville",
    "sg:classifiers":[
        {
            "category":"Professional",
            "subcategory":"Art Services",
            "type":"Services"
        }
    ],
    "sg:phone":"+1 972 966 0312",
    "sg:postcode":"75077",
    "sg:province":"TX",
    "sg:tags":[
        "photography",
        "commercial"
    ],
    "wof:name":"Dave Stock Photography",
    "wof:placetype":"venue"
},
  "geometry": {"coordinates":[-97.07812,33.095059],"type":"Point"}
}