{
  "type": "Feature",
  "properties": {
    "iso:country":"US",
    "sg:address":"1406 Pleasant Dr",
    "sg:city":"Dallas",
    "sg:classifiers":[
        {
            "category":"Social Services",
            "subcategory":"Child Care",
            "type":"Services"
        }
    ],
    "sg:phone":"+1 214 398 3200",
    "sg:postcode":"75217",
    "sg:province":"TX",
    "wof:name":"Pedi Tunes Learning Acdmy II",
    "wof:placetype":"venue"
},
  "geometry": {"coordinates":[-96.67850300000001,32.735769],"type":"Point"}
}