{
  "type": "Feature",
  "properties": {
    "iso:country":"US",
    "sg:address":"4509 E Saint Elmo Rd",
    "sg:city":"Austin",
    "sg:classifiers":[
        {
            "category":"Building & Trades",
            "subcategory":"Construction",
            "type":"Services"
        }
    ],
    "sg:phone":"+1 866 627 8577",
    "sg:postcode":"78744",
    "sg:province":"TX",
    "sg:tags":[
        "plastering",
        "drywall",
        "contractor"
    ],
    "wof:name":"JC Drywall",
    "wof:placetype":"venue"
},
  "geometry": {"coordinates":[-97.738939,30.206145],"type":"Point"}
}