{
  "type": "Feature",
  "properties": {
    "iso:country":"US",
    "sg:address":"13335 White Tail Dr",
    "sg:city":"Tyler",
    "sg:classifiers":[
        {
            "category":"Professional",
            "subcategory":"Business Services",
            "type":"Services"
        }
    ],
    "sg:phone":"+1 903 566 8769",
    "sg:postcode":"75707",
    "sg:province":"TX",
    "wof:name":"White Tail Homeowners Assoc In",
    "wof:placetype":"venue"
},
  "geometry": {"coordinates":[-95.186874,32.319382],"type":"Point"}
}