{
  "type": "Feature",
  "properties": {
    "iso:country":"US",
    "sg:address":"4804 E Rosedale St",
    "sg:city":"Fort Worth",
    "sg:classifiers":[
        {
            "category":"Organizations",
            "subcategory":"Religious Organization",
            "type":"Services"
        },
        {
            "category":"Social Services",
            "subcategory":"Job Training",
            "type":"Services"
        }
    ],
    "sg:phone":"+1 817 536 2793",
    "sg:postcode":"76105",
    "sg:province":"TX",
    "sg:tags":[
        "rehabilitation"
    ],
    "wof:name":"Restoring Hope Center",
    "wof:placetype":"venue"
},
  "geometry": {"coordinates":[-97.251548,32.731143],"type":"Point"}
}