{
  "type": "Feature",
  "properties": {
    "iso:country":"US",
    "sg:address":"911 Glouchester Ln",
    "sg:city":"Houston",
    "sg:classifiers":[
        {
            "category":"Wholesale",
            "subcategory":"Machinery & Supplies",
            "type":"Manufacturing & Wholesale Goods"
        }
    ],
    "sg:phone":"+1 281 443 8504",
    "sg:postcode":"77073",
    "sg:province":"TX",
    "sg:tags":[
        "equipment",
        "industrial",
        "transportation"
    ],
    "wof:name":"Seatech Marine Inc",
    "wof:placetype":"venue"
},
  "geometry": {"coordinates":[-95.415513,30.031665],"type":"Point"}
}