{
  "type": "Feature",
  "properties": {
    "iso:country":"US",
    "sg:address":"6851 West Fwy",
    "sg:city":"Fort Worth",
    "sg:classifiers":[
        {
            "category":"Travel",
            "subcategory":"Hotels & Motels",
            "type":"Entertainment"
        }
    ],
    "sg:phone":"+1 817 731 9600",
    "sg:postcode":"76116",
    "sg:province":"TX",
    "sg:tags":[
        "operation"
    ],
    "wof:name":"Comfort Suites",
    "wof:placetype":"venue"
},
  "geometry": {"coordinates":[-97.435941,32.735301],"type":"Point"}
}