{
  "type": "Feature",
  "properties": {
    "iso:country":"US",
    "sg:address":"118 N Vale St",
    "sg:city":"Jefferson",
    "sg:classifiers":[
        {
            "category":"Organizations",
            "subcategory":"Professional Association",
            "type":"Services"
        }
    ],
    "sg:phone":"+1 903 665 2672",
    "sg:postcode":"75657",
    "sg:province":"TX",
    "sg:tags":[
        "business"
    ],
    "wof:name":"Marion County Chamber Commerce",
    "wof:placetype":"venue"
},
  "geometry": {"coordinates":[-94.345405,32.756416],"type":"Point"}
}