{
  "type": "Feature",
  "properties": {
    "iso:country":"US",
    "sg:address":"905 S Wayside Dr",
    "sg:city":"Houston",
    "sg:classifiers":[
        {
            "category":"Restaurant",
            "type":"Food & Drink"
        }
    ],
    "sg:menulink":"http://www.allmenus.com/tx/houston/193445-taco-bell/menu/",
    "sg:postcode":"77023",
    "sg:province":"TX",
    "sg:tags":[
        "mexican"
    ],
    "wof:name":"Taco Bell",
    "wof:placetype":"venue"
},
  "geometry": {"coordinates":[-95.30930600000001,29.729331],"type":"Point"}
}