{
  "type": "Feature",
  "properties": {
    "iso:country":"US",
    "sg:address":"2701 W 7th St",
    "sg:city":"Texarkana",
    "sg:classifiers":[
        {
            "category":"Retail",
            "subcategory":"Auto Rental",
            "type":"Services"
        }
    ],
    "sg:phone":"+1 903 794 3244",
    "sg:postcode":"75501",
    "sg:province":"TX",
    "sg:tags":[
        "truck"
    ],
    "wof:name":"Idealease Of Texarkana",
    "wof:placetype":"venue"
},
  "geometry": {"coordinates":[-94.07643899999999,33.421324],"type":"Point"}
}