{
  "type": "Feature",
  "properties": {
    "iso:country":"US",
    "sg:address":"4406 N 28th Ln",
    "sg:city":"Mcallen",
    "sg:classifiers":[
        {
            "category":"Professional",
            "subcategory":"Computer Services",
            "type":"Services"
        }
    ],
    "sg:phone":"+1 956 668 8326",
    "sg:postcode":"78504",
    "sg:province":"TX",
    "sg:tags":[
        "related"
    ],
    "wof:name":"Team PC",
    "wof:placetype":"venue"
},
  "geometry": {"coordinates":[-98.246122,26.246523],"type":"Point"}
}