{
  "type": "Feature",
  "properties": {
    "iso:country":"US",
    "sg:address":"957 E Hill St",
    "sg:city":"Bellville",
    "sg:classifiers":[
        {
            "category":"Retail",
            "subcategory":"Veterinary Services",
            "type":"Services"
        }
    ],
    "sg:phone":"+1 979 865 2192",
    "sg:postcode":"77418",
    "sg:province":"TX",
    "sg:tags":[
        "veterinarian",
        "specialty"
    ],
    "wof:name":"Lamp, Jas H",
    "wof:placetype":"venue"
},
  "geometry": {"coordinates":[-96.246954,29.949152],"type":"Point"}
}