{
  "type": "Feature",
  "properties": {
    "iso:country":"US",
    "sg:address":"405 Tawny Dr",
    "sg:city":"Austin",
    "sg:classifiers":[
        {
            "category":"Shopping",
            "subcategory":"Gifts & Souvenirs",
            "type":"Retail Goods"
        }
    ],
    "sg:phone":"+1 512 442 1180",
    "sg:postcode":"78745",
    "sg:province":"TX",
    "wof:name":"Novedades Colombo",
    "wof:placetype":"venue"
},
  "geometry": {"coordinates":[-97.787451,30.190302],"type":"Point"}
}