{
  "type": "Feature",
  "properties": {
    "iso:country":"US",
    "sg:address":"105 Kenning Rd",
    "sg:city":"Crosby",
    "sg:classifiers":[
        {
            "category":"Food & Beverages",
            "subcategory":"Groceries & Convenience Stores",
            "type":"Retail Goods"
        }
    ],
    "sg:phone":"+1 281 328 4864",
    "sg:postcode":"77532",
    "sg:province":"TX",
    "wof:name":"Kroger",
    "wof:placetype":"venue"
},
  "geometry": {"coordinates":[-95.06169800000001,29.888801],"type":"Point"}
}