{
  "type": "Feature",
  "properties": {
    "iso:country":"US",
    "sg:address":"14902 Preston Rd",
    "sg:city":"Dallas",
    "sg:classifiers":[
        {
            "category":"Health Services",
            "subcategory":"Doctor",
            "type":"Services"
        }
    ],
    "sg:phone":"+1 972 661 3322",
    "sg:postcode":"75254",
    "sg:province":"TX",
    "sg:tags":[
        "clinic"
    ],
    "wof:name":"P M & R Clinic",
    "wof:placetype":"venue"
},
  "geometry": {"coordinates":[-96.80362100000001,32.94985],"type":"Point"}
}