{
  "type": "Feature",
  "properties": {
    "iso:country":"US",
    "sg:address":"2962 Sunlake Dr",
    "sg:city":"Abilene",
    "sg:classifiers":[
        {
            "category":"Personal",
            "subcategory":"Barber",
            "type":"Services"
        }
    ],
    "sg:phone":"+1 325 673 7467",
    "sg:postcode":"79601",
    "sg:province":"TX",
    "wof:name":"Fresh Cuts",
    "wof:placetype":"venue"
},
  "geometry": {"coordinates":[-99.759715,32.502188],"type":"Point"}
}