{
  "type": "Feature",
  "properties": {
    "iso:country":"US",
    "sg:address":"14407 Pine St",
    "sg:city":"Santa Fe",
    "sg:classifiers":[
        {
            "category":"Retail",
            "subcategory":"Auto Repair",
            "type":"Services"
        }
    ],
    "sg:phone":"+1 409 316 1353",
    "sg:postcode":"77517",
    "sg:province":"TX",
    "sg:tags":[
        "automotive"
    ],
    "wof:name":"South Texas Towing & Recovery",
    "wof:placetype":"venue"
},
  "geometry": {"coordinates":[-95.115499,29.390312],"type":"Point"}
}