{
  "type": "Feature",
  "properties": {
    "iso:country":"US",
    "sg:address":"1325 S Main St",
    "sg:city":"Keller",
    "sg:classifiers":[
        {
            "category":"Social Services",
            "subcategory":"Child Care",
            "type":"Services"
        }
    ],
    "sg:phone":"+1 817 431 7064",
    "sg:postcode":"76248",
    "sg:province":"TX",
    "sg:tags":[
        "day"
    ],
    "wof:name":"Goldring Childrens Center",
    "wof:placetype":"venue"
},
  "geometry": {"coordinates":[-97.255146,32.916309],"type":"Point"}
}