{
  "type": "Feature",
  "properties": {
    "iso:country":"US",
    "sg:address":"603 FM 2093",
    "sg:city":"Fredericksburg",
    "sg:classifiers":[
        {
            "category":"Manufacturing",
            "subcategory":"Tools & Machinery",
            "type":"Manufacturing & Wholesale Goods"
        }
    ],
    "sg:phone":"+1 830 997 5100",
    "sg:postcode":"78624",
    "sg:province":"TX",
    "sg:tags":[
        "equipment",
        "energy",
        "system",
        "supply"
    ],
    "wof:name":"Advent Power Corp",
    "wof:placetype":"venue"
},
  "geometry": {"coordinates":[-98.91128399999999,30.251826],"type":"Point"}
}