{
  "type": "Feature",
  "properties": {
    "iso:country":"US",
    "sg:address":"300 W 15th St Ste 800",
    "sg:city":"Austin",
    "sg:classifiers":[
        {
            "category":"Government",
            "subcategory":"Court House",
            "type":"Public Place"
        }
    ],
    "sg:phone":"+1 512 463 2002",
    "sg:postcode":"78701",
    "sg:province":"TX",
    "sg:tags":[
        "justice"
    ],
    "sg:website":"http://www.oag.state.tx.us",
    "wof:name":"Capital Litigation Division",
    "wof:placetype":"venue"
},
  "geometry": {"coordinates":[-97.742729,30.277889],"type":"Point"}
}