{
  "type": "Feature",
  "properties": {
    "iso:country":"US",
    "sg:address":"3960 Summit Ct",
    "sg:city":"Mc Kinney",
    "sg:classifiers":[
        {
            "category":"Manufacturing",
            "subcategory":"Toys & Sporting Goods",
            "type":"Manufacturing & Wholesale Goods"
        }
    ],
    "sg:phone":"+1 972 562 2226",
    "sg:postcode":"75069",
    "sg:province":"TX",
    "sg:tags":[
        "mfg"
    ],
    "wof:name":"Dallas Summit Volleyball Club",
    "wof:placetype":"venue"
},
  "geometry": {"coordinates":[-96.58465,33.140507],"type":"Point"}
}