{
  "type": "Feature",
  "properties": {
    "iso:country":"US",
    "sg:address":"12710 Research Blvd",
    "sg:city":"Austin",
    "sg:classifiers":[
        {
            "category":"Health Services",
            "subcategory":"Health Practitioner",
            "type":"Services"
        },
        {
            "category":"Communications",
            "type":"Services"
        }
    ],
    "sg:phone":"+1 512 331 4115",
    "sg:postcode":"78759",
    "sg:province":"TX",
    "sg:tags":[
        "pathologist",
        "speech-language",
        "myofunctional",
        "therapy"
    ],
    "wof:name":"Putnam Jamie Speech Pathologist",
    "wof:placetype":"venue"
},
  "geometry": {"coordinates":[-97.766775,30.432426],"type":"Point"}
}