{
  "type": "Feature",
  "properties": {
    "iso:country":"US",
    "sg:address":"5870 Westover St",
    "sg:city":"Houston",
    "sg:classifiers":[
        {
            "category":"Freight",
            "type":"Transportation"
        }
    ],
    "sg:phone":"+1 713 733 6963",
    "sg:postcode":"77033",
    "sg:province":"TX",
    "sg:tags":[
        "distance",
        "long",
        "trucking"
    ],
    "wof:name":"Rachal Trucking Company",
    "wof:placetype":"venue"
},
  "geometry": {"coordinates":[-95.33143200000001,29.663187],"type":"Point"}
}