{
  "type": "Feature",
  "properties": {
    "iso:country":"US",
    "sg:address":"11265 Allison Ave",
    "sg:city":"Azle",
    "sg:classifiers":[
        {
            "category":"Utilities",
            "subcategory":"Electric",
            "type":"Services"
        }
    ],
    "sg:phone":"+1 817 444 1716",
    "sg:postcode":"76020",
    "sg:province":"TX",
    "sg:tags":[
        "power",
        "gas",
        "broker",
        "real estate"
    ],
    "wof:name":"Kwh Consulting Services Ltd",
    "wof:placetype":"venue"
},
  "geometry": {"coordinates":[-97.526731,32.93114],"type":"Point"}
}