{
  "type": "Feature",
  "properties": {
    "iso:country":"US",
    "sg:address":"8229 Shoal Creek Blvd",
    "sg:city":"Austin",
    "sg:classifiers":[
        {
            "category":"Real Estate",
            "subcategory":"Real Estate Agent",
            "type":"Services"
        }
    ],
    "sg:phone":"+1 512 441 6262",
    "sg:postcode":"78757",
    "sg:province":"TX",
    "sg:tags":[
        "management"
    ],
    "wof:name":"Radec Management Inc",
    "wof:placetype":"venue"
},
  "geometry": {"coordinates":[-97.73767100000001,30.36948],"type":"Point"}
}