{
  "type": "Feature",
  "properties": {
    "iso:country":"US",
    "sg:address":"2570 Eldorado Pkwy",
    "sg:city":"Mc Kinney",
    "sg:classifiers":[
        {
            "category":"Professional",
            "subcategory":"Management & Consulting",
            "type":"Services"
        }
    ],
    "sg:phone":"+1 972 542 5122",
    "sg:postcode":"75070",
    "sg:province":"TX",
    "sg:tags":[
        "educational"
    ],
    "wof:name":"CDG LLC",
    "wof:placetype":"venue"
},
  "geometry": {"coordinates":[-96.646246,33.171202],"type":"Point"}
}