{
  "type": "Feature",
  "properties": {
    "iso:country":"US",
    "sg:address":"2012 Young St",
    "sg:city":"Grand Prairie",
    "sg:classifiers":[
        {
            "category":"Organizations",
            "subcategory":"Religious Organization",
            "type":"Services"
        }
    ],
    "sg:phone":"+1 972 642 0410",
    "sg:postcode":"75050",
    "sg:province":"TX",
    "sg:tags":[
        "church"
    ],
    "wof:name":"Templo Priner AMOR",
    "wof:placetype":"venue"
},
  "geometry": {"coordinates":[-96.97547900000001,32.747076],"type":"Point"}
}