{
  "type": "Feature",
  "properties": {
    "iso:country":"US",
    "sg:address":"4801 N Midland Dr",
    "sg:city":"Midland",
    "sg:classifiers":[
        {
            "category":"Health Services",
            "subcategory":"Doctor",
            "type":"Services"
        }
    ],
    "sg:phone":"+1 432 520 4550",
    "sg:postcode":"79707",
    "sg:province":"TX",
    "sg:tags":[
        "medical"
    ],
    "wof:name":"Santilli Gregg M MD",
    "wof:placetype":"venue"
},
  "geometry": {"coordinates":[-102.147346,32.034076],"type":"Point"}
}