{
  "type": "Feature",
  "properties": {
    "iso:country":"US",
    "sg:address":"4511 Fox Run St",
    "sg:city":"Pearland",
    "sg:classifiers":[
        {
            "category":"Professional",
            "subcategory":"Computer Services",
            "type":"Services"
        }
    ],
    "sg:phone":"+1 832 250 8176",
    "sg:postcode":"77584",
    "sg:province":"TX",
    "sg:tags":[
        "consultant"
    ],
    "wof:name":"Megalith Computer Innovations",
    "wof:placetype":"venue"
},
  "geometry": {"coordinates":[-95.29218299999999,29.543588],"type":"Point"}
}