{
  "type": "Feature",
  "properties": {
    "iso:country":"US",
    "sg:address":"4058 Deerfield Dr",
    "sg:city":"College Station",
    "sg:classifiers":[
        {
            "category":"Shopping",
            "subcategory":"Books",
            "type":"Retail Goods"
        }
    ],
    "sg:phone":"+1 979 776 0249",
    "sg:postcode":"77845",
    "sg:province":"TX",
    "wof:name":"Lacey Publications",
    "wof:placetype":"venue"
},
  "geometry": {"coordinates":[-96.26995700000001,30.649108],"type":"Point"}
}