{
  "type": "Feature",
  "properties": {
    "iso:country":"US",
    "sg:address":"10130 Southfork St",
    "sg:city":"Crowley",
    "sg:classifiers":[
        {
            "category":"Banks & Credit Unions",
            "subcategory":"Bank",
            "type":"Services"
        }
    ],
    "sg:phone":"+1 817 293 3872",
    "sg:postcode":"76036",
    "sg:province":"TX",
    "sg:tags":[
        "mortgage"
    ],
    "wof:name":"RMC",
    "wof:placetype":"venue"
},
  "geometry": {"coordinates":[-97.354511,32.607186],"type":"Point"}
}