{
  "type": "Feature",
  "properties": {
    "iso:country":"US",
    "sg:address":"106 Janet Kay Dr",
    "sg:city":"Longview",
    "sg:classifiers":[
        {
            "category":"Food & Beverages",
            "subcategory":"Specialty",
            "type":"Retail Goods"
        }
    ],
    "sg:phone":"+1 903 663 5504",
    "sg:postcode":"75605",
    "sg:province":"TX",
    "wof:name":"Graces Health Foods",
    "wof:placetype":"venue"
},
  "geometry": {"coordinates":[-94.730977,32.558643],"type":"Point"}
}