{
  "type": "Feature",
  "properties": {
    "iso:country":"US",
    "sg:address":"1108 Vanderbilt Cir",
    "sg:city":"Pflugerville",
    "sg:classifiers":[
        {
            "category":"Professional",
            "subcategory":"Business Services",
            "type":"Services"
        }
    ],
    "sg:phone":"+1 512 251 5091",
    "sg:postcode":"78660",
    "sg:province":"TX",
    "sg:tags":[
        "design",
        "aquarium",
        "maintenance"
    ],
    "wof:name":"Fish Man",
    "wof:placetype":"venue"
},
  "geometry": {"coordinates":[-97.627003,30.428864],"type":"Point"}
}