{
  "type": "Feature",
  "properties": {
    "iso:country":"US",
    "sg:address":"909 Alta Vista St",
    "sg:city":"Amarillo",
    "sg:classifiers":[
        {
            "category":"Education",
            "subcategory":"Special Training",
            "type":"Public Place"
        }
    ],
    "sg:phone":"+1 806 457 0161",
    "sg:postcode":"79106",
    "sg:province":"TX",
    "sg:tags":[
        "instruction",
        "music"
    ],
    "wof:name":"Piano Pizazz",
    "wof:placetype":"venue"
},
  "geometry": {"coordinates":[-101.894391,35.204152],"type":"Point"}
}