{
  "type": "Feature",
  "properties": {
    "iso:country":"US",
    "sg:address":"12206 Rocky Knoll Dr",
    "sg:city":"Houston",
    "sg:classifiers":[
        {
            "category":"Banks & Credit Unions",
            "subcategory":"Financial Services",
            "type":"Services"
        }
    ],
    "sg:phone":"+1 281 558 8257",
    "sg:postcode":"77077",
    "sg:province":"TX",
    "sg:tags":[
        "investor"
    ],
    "wof:name":"Starco Investments Inc",
    "wof:placetype":"venue"
},
  "geometry": {"coordinates":[-95.595581,29.744239],"type":"Point"}
}