{
  "type": "Feature",
  "properties": {
    "iso:country":"US",
    "sg:address":"811 W Pleasant Run Rd",
    "sg:city":"Lancaster",
    "sg:classifiers":[
        {
            "category":"Shopping",
            "subcategory":"Florist",
            "type":"Retail Goods"
        }
    ],
    "sg:phone":"+1 972 227 6295",
    "sg:postcode":"75146",
    "sg:province":"TX",
    "wof:name":"Marthas Florist",
    "wof:placetype":"venue"
},
  "geometry": {"coordinates":[-96.77244,32.605196],"type":"Point"}
}