{
  "type": "Feature",
  "properties": {
    "iso:country":"US",
    "sg:address":"2322 Observation Dr",
    "sg:city":"San Antonio",
    "sg:classifiers":[
        {
            "category":"Shopping",
            "subcategory":"Used Merchandise",
            "type":"Retail Goods"
        }
    ],
    "sg:phone":"+1 210 670 8342",
    "sg:postcode":"78227",
    "sg:province":"TX",
    "wof:name":"Eugene Cornelius Banks",
    "wof:placetype":"venue"
},
  "geometry": {"coordinates":[-98.64678499999999,29.406707],"type":"Point"}
}