{
  "type": "Feature",
  "properties": {
    "iso:country":"US",
    "sg:address":"4825 Bellfort St",
    "sg:city":"Houston",
    "sg:classifiers":[
        {
            "category":"Retail",
            "subcategory":"Auto Repair",
            "type":"Services"
        }
    ],
    "sg:phone":"+1 713 731 8308",
    "sg:postcode":"77033",
    "sg:province":"TX",
    "sg:tags":[
        "automotive"
    ],
    "wof:name":"Superior Car Wash Xpress Lube",
    "wof:placetype":"venue"
},
  "geometry": {"coordinates":[-95.352566,29.667711],"type":"Point"}
}