{
  "type": "Feature",
  "properties": {
    "iso:country":"US",
    "sg:address":"4901 S I- 35 E",
    "sg:city":"Denton",
    "sg:classifiers":[
        {
            "category":"Autos & Motor Vehicles",
            "subcategory":"Automobile Sales",
            "type":"Retail Goods"
        }
    ],
    "sg:phone":"+1 940 382 5404",
    "sg:postcode":"76210",
    "sg:province":"TX",
    "sg:tags":[
        "car",
        "dealer"
    ],
    "sg:website":"www.utterford.com",
    "wof:name":"Bill Utter Ford Inc",
    "wof:placetype":"venue"
},
  "geometry": {"coordinates":[-97.076489,33.163468],"type":"Point"}
}