{
  "type": "Feature",
  "properties": {
    "iso:country":"US",
    "sg:address":"10226 Farrell Dr",
    "sg:city":"Houston",
    "sg:classifiers":[
        {
            "category":"Wholesale",
            "subcategory":"Home Furnishings",
            "type":"Manufacturing & Wholesale Goods"
        }
    ],
    "sg:phone":"+1 281 469 9226",
    "sg:postcode":"77070",
    "sg:province":"TX",
    "sg:tags":[
        "manufacturer",
        "baskets-wholesale"
    ],
    "wof:name":"Michell S Basket Bows Blooms",
    "wof:placetype":"venue"
},
  "geometry": {"coordinates":[-95.571995,29.950742],"type":"Point"}
}