{
  "type": "Feature",
  "properties": {
    "iso:country":"US",
    "sg:address":"402 Lincoln St",
    "sg:city":"Mc Kinney",
    "sg:classifiers":[
        {
            "category":"Social Services",
            "subcategory":"Child Care",
            "type":"Services"
        }
    ],
    "sg:phone":"+1 972 562 5476",
    "sg:postcode":"75069",
    "sg:province":"TX",
    "sg:tags":[
        "kindergarten",
        "academic",
        "school"
    ],
    "wof:name":"Holy Family School",
    "wof:placetype":"venue"
},
  "geometry": {"coordinates":[-96.602543,33.201094],"type":"Point"}
}