{
  "type": "Feature",
  "properties": {
    "iso:country":"US",
    "sg:address":"2819 Co Rd 100",
    "sg:city":"San Marcos",
    "sg:classifiers":[
        {
            "category":"Professional",
            "subcategory":"Business Services",
            "type":"Services"
        }
    ],
    "sg:phone":"+1 512 396 6000",
    "sg:postcode":"78634",
    "sg:province":"TX",
    "sg:tags":[
        "paging",
        "answering"
    ],
    "wof:name":"Direct Telemessaging",
    "wof:placetype":"venue"
},
  "geometry": {"coordinates":[-97.581492,30.617914],"type":"Point"}
}