{
  "type": "Feature",
  "properties": {
    "iso:country":"US",
    "sg:address":"12220 Murphy Rd Ste H",
    "sg:city":"Stafford",
    "sg:classifiers":[
        {
            "category":"Professional",
            "type":"Services"
        },
        {
            "category":"Personal",
            "type":"Services"
        }
    ],
    "sg:phone":"+1 281 498 1355",
    "sg:postcode":"77477",
    "sg:province":"TX",
    "sg:tags":[
        "party",
        "planning",
        "event",
        "caterer"
    ],
    "wof:name":"Parties & More By Allison",
    "wof:placetype":"venue"
},
  "geometry": {"coordinates":[-95.56549200000001,29.644495],"type":"Point"}
}