{
  "type": "Feature",
  "properties": {
    "iso:country":"US",
    "sg:address":"1312 C St",
    "sg:city":"Waller",
    "sg:classifiers":[
        {
            "category":"Building & Trades",
            "subcategory":"Construction",
            "type":"Services"
        }
    ],
    "sg:phone":"+1 936 372 3215",
    "sg:postcode":"77484",
    "sg:province":"TX",
    "sg:tags":[
        "demolition",
        "contractor"
    ],
    "wof:name":"Demolition Sid Recycling",
    "wof:placetype":"venue"
},
  "geometry": {"coordinates":[-95.93131099999999,30.059068],"type":"Point"}
}