{
  "type": "Feature",
  "properties": {
    "iso:country":"US",
    "sg:address":"3939 Bee Caves Rd",
    "sg:city":"Austin",
    "sg:classifiers":[
        {
            "category":"Professional",
            "subcategory":"Advertising",
            "type":"Services"
        }
    ],
    "sg:phone":"+1 512 306 8777",
    "sg:postcode":"78746",
    "sg:province":"TX",
    "wof:name":"Promo Resources",
    "wof:placetype":"venue"
},
  "geometry": {"coordinates":[-97.809605,30.282066],"type":"Point"}
}