{
  "type": "Feature",
  "properties": {
    "iso:country":"US",
    "sg:address":"5512 W Military Dr",
    "sg:city":"San Antonio",
    "sg:classifiers":[
        {
            "category":"Autos & Motor Vehicles",
            "subcategory":"Auto Supplies",
            "type":"Retail Goods"
        }
    ],
    "sg:phone":"+1 210 673 1191",
    "sg:postcode":"78242",
    "sg:province":"TX",
    "sg:tags":[
        "automobile",
        "parts"
    ],
    "sg:website":"www.advanceauto.com",
    "wof:name":"Advance Auto Parts Inc",
    "wof:placetype":"venue"
},
  "geometry": {"coordinates":[-98.61353,29.376777],"type":"Point"}
}