{
  "type": "Feature",
  "properties": {
    "iso:country":"US",
    "sg:address":"6125 Luther Ln",
    "sg:city":"Dallas",
    "sg:classifiers":[
        {
            "category":"Personal",
            "subcategory":"Beauty Salon",
            "type":"Services"
        }
    ],
    "sg:phone":"+1 214 739 2662",
    "sg:postcode":"75225",
    "sg:province":"TX",
    "wof:name":"Whippersnapper Hair Squad",
    "wof:placetype":"venue"
},
  "geometry": {"coordinates":[-96.806144,32.863695],"type":"Point"}
}