{
  "type": "Feature",
  "properties": {
    "iso:country":"US",
    "sg:address":"2600 Mallard Green Cove",
    "sg:city":"Austin",
    "sg:classifiers":[
        {
            "category":"Wholesale",
            "subcategory":"Electrical",
            "type":"Manufacturing & Wholesale Goods"
        }
    ],
    "sg:phone":"+1 512 426 3425",
    "sg:postcode":"78728",
    "sg:province":"TX",
    "sg:tags":[
        "semiconductor",
        "equipment",
        "production"
    ],
    "wof:name":"Imtech Inc",
    "wof:placetype":"venue"
},
  "geometry": {"coordinates":[-97.681685,30.451742],"type":"Point"}
}