{
  "type": "Feature",
  "properties": {
    "iso:country":"US",
    "sg:address":"287 N US Hwy 287",
    "sg:city":"Decatur",
    "sg:classifiers":[
        {
            "category":"Manufacturing",
            "subcategory":"Lumber",
            "type":"Manufacturing & Wholesale Goods"
        }
    ],
    "sg:phone":"+1 940 627 1771",
    "sg:postcode":"76234",
    "sg:province":"TX",
    "sg:tags":[
        "government"
    ],
    "wof:name":"US Forestry Dept",
    "wof:placetype":"venue"
},
  "geometry": {"coordinates":[-97.597444,33.236655],"type":"Point"}
}