{
  "type": "Feature",
  "properties": {
    "iso:country":"US",
    "sg:address":"9001 Hempstead Rd",
    "sg:city":"Houston",
    "sg:classifiers":[
        {
            "category":"Professional",
            "subcategory":"Business Services",
            "type":"Services"
        }
    ],
    "sg:phone":"+1 713 426 9001",
    "sg:postcode":"77008",
    "sg:province":"TX",
    "wof:name":"Lantana Oil & Gas Partners",
    "wof:placetype":"venue"
},
  "geometry": {"coordinates":[-95.44893399999999,29.793329],"type":"Point"}
}