{
  "type": "Feature",
  "properties": {
    "iso:country":"US",
    "sg:address":"2620 Poinsettia Dr",
    "sg:city":"Dallas",
    "sg:classifiers":[
        {
            "category":"Shopping",
            "subcategory":"Jewelry",
            "type":"Retail Goods"
        }
    ],
    "sg:phone":"+1 214 333 2984",
    "sg:postcode":"75211",
    "sg:province":"TX",
    "wof:name":"Maria A Garcia",
    "wof:placetype":"venue"
},
  "geometry": {"coordinates":[-96.863246,32.725116],"type":"Point"}
}