{
  "type": "Feature",
  "properties": {
    "iso:country":"US",
    "sg:address":"1951 Aquarena Springs Dr",
    "sg:city":"San Marcos",
    "sg:classifiers":[
        {
            "category":"Real Estate",
            "subcategory":"Real Estate Operator",
            "type":"Services"
        }
    ],
    "sg:phone":"+1 512 754 8911",
    "sg:postcode":"78666",
    "sg:province":"TX",
    "sg:tags":[
        "building",
        "apartment"
    ],
    "wof:name":"Country Oaks Apartments",
    "wof:placetype":"venue"
},
  "geometry": {"coordinates":[-97.904844,29.891747],"type":"Point"}
}