{
  "type": "Feature",
  "properties": {
    "iso:country":"US",
    "sg:address":"30 Wildflower Trace Pl",
    "sg:city":"Spring",
    "sg:classifiers":[
        {
            "category":"Professional",
            "subcategory":"Management & Consulting",
            "type":"Services"
        }
    ],
    "sg:phone":"+1 281 419 6588",
    "sg:postcode":"77382",
    "sg:province":"TX",
    "sg:tags":[
        "public",
        "relations"
    ],
    "wof:name":"Brandblitz",
    "wof:placetype":"venue"
},
  "geometry": {"coordinates":[-95.545872,30.213521],"type":"Point"}
}