{
  "type": "Feature",
  "properties": {
    "iso:country":"US",
    "sg:address":"1779 Wells Branch Pkwy",
    "sg:city":"Austin",
    "sg:classifiers":[
        {
            "category":"Food & Beverages",
            "subcategory":"Liquor & Beverages",
            "type":"Retail Goods"
        }
    ],
    "sg:phone":"+1 512 428 5826",
    "sg:postcode":"78728",
    "sg:province":"TX",
    "sg:tags":[
        "beer",
        "spirit",
        "wine"
    ],
    "wof:name":"The Liquor Cabinet # 2",
    "wof:placetype":"venue"
},
  "geometry": {"coordinates":[-97.674254,30.436074],"type":"Point"}
}