{
  "type": "Feature",
  "properties": {
    "iso:country":"US",
    "sg:address":"1613 W Airport Fwy",
    "sg:city":"Irving",
    "sg:classifiers":[
        {
            "category":"Building & Trades",
            "subcategory":"Landscaping Services",
            "type":"Services"
        }
    ],
    "sg:phone":"+1 972 252 2414",
    "sg:postcode":"75062",
    "sg:province":"TX",
    "sg:tags":[
        "landscape"
    ],
    "wof:name":"Oasis Concrete & Landscap",
    "wof:placetype":"venue"
},
  "geometry": {"coordinates":[-96.968221,32.837386],"type":"Point"}
}