{
  "type": "Feature",
  "properties": {
    "iso:country":"US",
    "sg:address":"801 Westbrook Dr",
    "sg:city":"Garland",
    "sg:classifiers":[
        {
            "category":"Wholesale",
            "subcategory":"Computers",
            "type":"Manufacturing & Wholesale Goods"
        }
    ],
    "sg:phone":"+1 972 279 6411",
    "sg:postcode":"75043",
    "sg:province":"TX",
    "sg:tags":[
        "peripheral"
    ],
    "wof:name":"A1 Consultants & Computers",
    "wof:placetype":"venue"
},
  "geometry": {"coordinates":[-96.637655,32.851765],"type":"Point"}
}