{
  "type": "Feature",
  "properties": {
    "iso:country":"US",
    "sg:address":"2706 Gillespie",
    "sg:city":"Port Bolivar",
    "sg:classifiers":[
        {
            "category":"Government",
            "subcategory":"Office",
            "type":"Public Place"
        }
    ],
    "sg:phone":"+1 409 684 3145",
    "sg:postcode":"77650",
    "sg:province":"TX",
    "wof:name":"Joe J Fisher US District",
    "wof:placetype":"venue"
},
  "geometry": {"coordinates":[-94.60108700000001,29.466907],"type":"Point"}
}