{
  "type": "Feature",
  "properties": {
    "iso:country":"US",
    "sg:address":"19221 I- 45",
    "sg:city":"Spring",
    "sg:classifiers":[
        {
            "category":"Professional",
            "subcategory":"Accounting & Tax Preparation",
            "type":"Services"
        }
    ],
    "sg:phone":"+1 281 363 0420",
    "sg:postcode":"77388",
    "sg:province":"TX",
    "sg:tags":[
        "return"
    ],
    "wof:name":"Gaylon R Clark CPA",
    "wof:placetype":"venue"
},
  "geometry": {"coordinates":[-95.43085600000001,30.046919],"type":"Point"}
}