{
  "type": "Feature",
  "properties": {
    "iso:country":"US",
    "sg:address":"1100 W 11th St",
    "sg:city":"Quanah",
    "sg:classifiers":[
        {
            "category":"Travel",
            "subcategory":"Hotels & Motels",
            "type":"Entertainment"
        },
        {
            "category":"Travel",
            "subcategory":"Bed & Breakfast",
            "type":"Entertainment"
        }
    ],
    "sg:phone":"+1 940 663 5407",
    "sg:postcode":"79252",
    "sg:province":"TX",
    "sg:tags":[
        "inn",
        "lodging"
    ],
    "sg:website":"http://www.bestwestern.com",
    "wof:name":"Best Western Quanah Inn & Suites",
    "wof:placetype":"venue"
},
  "geometry": {"coordinates":[-99.754738,34.292099],"type":"Point"}
}