{
  "type": "Feature",
  "properties": {
    "iso:country":"US",
    "sg:address":"213 Elliott St",
    "sg:city":"San Antonio",
    "sg:classifiers":[
        {
            "category":"Building & Trades",
            "subcategory":"Landscaping Services",
            "type":"Services"
        }
    ],
    "sg:phone":"+1 210 533 1125",
    "sg:postcode":"78225",
    "sg:province":"TX",
    "sg:tags":[
        "lawn",
        "maintenance",
        "grounds"
    ],
    "wof:name":"Dave's Lawn Svc",
    "wof:placetype":"venue"
},
  "geometry": {"coordinates":[-98.517335,29.392612],"type":"Point"}
}