{
  "type": "Feature",
  "properties": {
    "iso:country":"US",
    "sg:address":"2308 Broken Pt",
    "sg:city":"Mc Kinney",
    "sg:classifiers":[
        {
            "category":"Professional",
            "subcategory":"Management & Consulting",
            "type":"Services"
        }
    ],
    "sg:phone":"+1 972 377 8655",
    "sg:postcode":"75070",
    "sg:province":"TX",
    "sg:tags":[
        "consultant"
    ],
    "wof:name":"Gerocare Consultants",
    "wof:placetype":"venue"
},
  "geometry": {"coordinates":[-96.689401,33.178911],"type":"Point"}
}