{
  "type": "Feature",
  "properties": {
    "iso:country":"US",
    "sg:address":"2323 Montana Ave",
    "sg:city":"El Paso",
    "sg:classifiers":[
        {
            "category":"Wholesale",
            "subcategory":"Medical Equipment & Supplies",
            "type":"Manufacturing & Wholesale Goods"
        }
    ],
    "sg:phone":"+1 915 592 8504",
    "sg:postcode":"79903",
    "sg:province":"TX",
    "sg:tags":[
        "hospital"
    ],
    "wof:name":"G G Medical Inc",
    "wof:placetype":"venue"
},
  "geometry": {"coordinates":[-106.468009,31.779193],"type":"Point"}
}