{
  "type": "Feature",
  "properties": {
    "iso:country":"US",
    "sg:address":"402 Williamson Pl",
    "sg:city":"Corpus Christi",
    "sg:classifiers":[
        {
            "category":"Mining & Drilling",
            "type":"Manufacturing & Wholesale Goods"
        }
    ],
    "sg:phone":"+1 361 857 7176",
    "sg:postcode":"78411",
    "sg:province":"TX",
    "sg:tags":[
        "development",
        "gas",
        "oil",
        "exploration"
    ],
    "wof:name":"Polaris Exploration Corp",
    "wof:placetype":"venue"
},
  "geometry": {"coordinates":[-97.37706799999999,27.737644],"type":"Point"}
}