{
  "type": "Feature",
  "properties": {
    "iso:country":"US",
    "sg:address":"910 N Durham Dr",
    "sg:city":"Houston",
    "sg:classifiers":[
        {
            "category":"Government",
            "subcategory":"Police Station",
            "type":"Public Place"
        }
    ],
    "sg:phone":"+1 713 803 1151",
    "sg:postcode":"77008",
    "sg:province":"TX",
    "sg:tags":[
        "protection"
    ],
    "wof:name":"Police Dept-Heights Substation",
    "wof:placetype":"venue"
},
  "geometry": {"coordinates":[-95.411643,29.786054],"type":"Point"}
}