{
  "type": "Feature",
  "properties": {
    "iso:country":"US",
    "sg:address":"14253 Lee Rd",
    "sg:city":"Houston",
    "sg:classifiers":[
        {
            "category":"Professional",
            "subcategory":"Art Services",
            "type":"Services"
        }
    ],
    "sg:phone":"+1 281 590 1101",
    "sg:postcode":"77032",
    "sg:province":"TX",
    "sg:tags":[
        "photography",
        "studio",
        "limo"
    ],
    "sg:website":"www.dimensionsbydan.com",
    "wof:name":"Dimensions by Dan",
    "wof:placetype":"venue"
},
  "geometry": {"coordinates":[-95.302803,29.9258],"type":"Point"}
}