{
  "type": "Feature",
  "properties": {
    "iso:country":"US",
    "sg:address":"2140 E Southlake Blvd",
    "sg:city":"Southlake",
    "sg:classifiers":[
        {
            "category":"Building & Trades",
            "subcategory":"Construction",
            "type":"Services"
        }
    ],
    "sg:phone":"+1 817 845 7635",
    "sg:postcode":"76092",
    "sg:province":"TX",
    "sg:tags":[
        "repairing",
        "remodeling",
        "contractor"
    ],
    "wof:name":"First Texas Remodeling",
    "wof:placetype":"venue"
},
  "geometry": {"coordinates":[-97.121568,32.941049],"type":"Point"}
}