{
  "type": "Feature",
  "properties": {
    "iso:country":"US",
    "sg:address":"1270 W Dallas Ave",
    "sg:city":"Cooper",
    "sg:classifiers":[
        {
            "category":"Autos & Motor Vehicles",
            "subcategory":"Auto Supplies",
            "type":"Retail Goods"
        }
    ],
    "sg:phone":"+1 903 395 2130",
    "sg:postcode":"75432",
    "sg:province":"TX",
    "sg:tags":[
        "automobile",
        "part"
    ],
    "sg:website":"http://www.partsplus.com",
    "wof:name":"Stewart's Auto Parts",
    "wof:placetype":"venue"
},
  "geometry": {"coordinates":[-95.701222,33.373783],"type":"Point"}
}