{
  "type": "Feature",
  "properties": {
    "iso:country":"US",
    "sg:address":"26215 Lakeshore Dr",
    "sg:city":"Splendora",
    "sg:classifiers":[
        {
            "category":"Wholesale",
            "subcategory":"Photographic Equipment",
            "type":"Manufacturing & Wholesale Goods"
        }
    ],
    "sg:phone":"+1 281 399 5599",
    "sg:postcode":"77372",
    "sg:province":"TX",
    "sg:tags":[
        "photo"
    ],
    "wof:name":"Berg Studio",
    "wof:placetype":"venue"
},
  "geometry": {"coordinates":[-95.182294,30.235176],"type":"Point"}
}