{
  "type": "Feature",
  "properties": {
    "iso:country":"US",
    "sg:address":"1440 Vanderbilt Dr",
    "sg:city":"El Paso",
    "sg:classifiers":[
        {
            "category":"Bus Charters",
            "type":"Transportation"
        }
    ],
    "sg:phone":"+1 915 593 6685",
    "sg:postcode":"79935",
    "sg:province":"TX",
    "sg:tags":[
        "rental"
    ],
    "wof:name":"Southwest Charter Lines",
    "wof:placetype":"venue"
},
  "geometry": {"coordinates":[-106.324922,31.75054],"type":"Point"}
}