{
  "type": "Feature",
  "properties": {
    "iso:country":"US",
    "sg:address":"1718 N 23rd St",
    "sg:city":"Waco",
    "sg:classifiers":[
        {
            "category":"Professional",
            "subcategory":"Management & Consulting",
            "type":"Services"
        }
    ],
    "sg:phone":"+1 254 714 1112",
    "sg:postcode":"76707",
    "sg:province":"TX",
    "sg:tags":[
        "retail",
        "direct",
        "sales"
    ],
    "wof:name":"Sunworld Wholesale",
    "wof:placetype":"venue"
},
  "geometry": {"coordinates":[-97.16225300000001,31.557017],"type":"Point"}
}