{
  "type": "Feature",
  "properties": {
    "iso:country":"US",
    "sg:address":"5303 FM 2100",
    "sg:city":"Crosby",
    "sg:classifiers":[
        {
            "category":"Shopping",
            "subcategory":"Florist",
            "type":"Retail Goods"
        }
    ],
    "sg:phone":"+1 281 328 7087",
    "sg:postcode":"77532",
    "sg:province":"TX",
    "wof:name":"Cowtown Flowers",
    "wof:placetype":"venue"
},
  "geometry": {"coordinates":[-95.05800000000001,29.845654],"type":"Point"}
}