{
  "type": "Feature",
  "properties": {
    "iso:country":"US",
    "sg:address":"4405 Crenshaw Rd",
    "sg:city":"Pasadena",
    "sg:classifiers":[
        {
            "category":"Organizations",
            "subcategory":"Religious Organization",
            "type":"Services"
        }
    ],
    "sg:phone":"+1 281 991 9303",
    "sg:postcode":"77504",
    "sg:province":"TX",
    "wof:name":"Church",
    "wof:placetype":"venue"
},
  "geometry": {"coordinates":[-95.17590300000001,29.640499],"type":"Point"}
}