{
  "type": "Feature",
  "properties": {
    "iso:country":"US",
    "sg:address":"908 S 2nd St",
    "sg:city":"Killeen",
    "sg:classifiers":[
        {
            "category":"Building & Trades",
            "subcategory":"Cleaning & Sanitation",
            "type":"Services"
        }
    ],
    "sg:phone":"+1 254 432 7847",
    "sg:postcode":"76541",
    "sg:province":"TX",
    "sg:tags":[
        "contractor"
    ],
    "wof:name":"AJ Air Duct & Carpet Cleaning",
    "wof:placetype":"venue"
},
  "geometry": {"coordinates":[-97.733806,31.109606],"type":"Point"}
}