{
  "type": "Feature",
  "properties": {
    "iso:country":"US",
    "sg:address":"608 W 10th St",
    "sg:city":"Odessa",
    "sg:classifiers":[
        {
            "category":"Bars & Pubs",
            "type":"Food & Drink"
        }
    ],
    "sg:phone":"+1 432 337 9318",
    "sg:postcode":"79761",
    "sg:province":"TX",
    "wof:name":"Jim's Bamboo",
    "wof:placetype":"venue"
},
  "geometry": {"coordinates":[-102.379065,31.849749],"type":"Point"}
}