{
  "type": "Feature",
  "properties": {
    "iso:country":"US",
    "sg:address":"2707 Cheverny Dr",
    "sg:city":"Mc Kinney",
    "sg:classifiers":[
        {
            "category":"Manufacturing",
            "subcategory":"Jewelry",
            "type":"Manufacturing & Wholesale Goods"
        }
    ],
    "sg:phone":"+1 972 548 6957",
    "sg:postcode":"75070",
    "sg:province":"TX",
    "wof:name":"Adiska Originals",
    "wof:placetype":"venue"
},
  "geometry": {"coordinates":[-96.656764,33.166289],"type":"Point"}
}