{
  "type": "Feature",
  "properties": {
    "iso:country":"US",
    "sg:address":"1305 Thunderbrook Dr",
    "sg:city":"De Soto",
    "sg:classifiers":[
        {
            "category":"Building & Trades",
            "subcategory":"Construction",
            "type":"Services"
        }
    ],
    "sg:phone":"+1 972 223 2807",
    "sg:postcode":"75115",
    "sg:province":"TX",
    "sg:tags":[
        "house"
    ],
    "wof:name":"Bachman Construction",
    "wof:placetype":"venue"
},
  "geometry": {"coordinates":[-96.86523099999999,32.612176],"type":"Point"}
}