{
  "type": "Feature",
  "properties": {
    "iso:country":"US",
    "sg:address":"10928 Co Rd 35",
    "sg:city":"Tyler",
    "sg:classifiers":[
        {
            "category":"Building & Trades",
            "subcategory":"Construction",
            "type":"Services"
        }
    ],
    "sg:phone":"+1 903 593 6059",
    "sg:postcode":"75706",
    "sg:province":"TX",
    "sg:tags":[
        "residential"
    ],
    "wof:name":"S Bar H Construction Inc",
    "wof:placetype":"venue"
},
  "geometry": {"coordinates":[-95.311595,32.430901],"type":"Point"}
}