{
  "type": "Feature",
  "properties": {
    "iso:country":"US",
    "sg:address":"510 State Hwy 27",
    "sg:city":"Ingram",
    "sg:classifiers":[
        {
            "category":"Manufacturing",
            "subcategory":"Food",
            "type":"Manufacturing & Wholesale Goods"
        }
    ],
    "sg:phone":"+1 830 367 3420",
    "sg:postcode":"78025",
    "sg:province":"TX",
    "sg:tags":[
        "winery"
    ],
    "wof:name":"Specialty Blends",
    "wof:placetype":"venue"
},
  "geometry": {"coordinates":[-99.223816,30.073223],"type":"Point"}
}