{
  "type": "Feature",
  "properties": {
    "iso:country":"US",
    "sg:address":"1021 Main St Ste 1370",
    "sg:city":"Houston",
    "sg:classifiers":[
        {
            "category":"Banks & Credit Unions",
            "subcategory":"Bank",
            "type":"Services"
        }
    ],
    "sg:phone":"+1 713 651 1870",
    "sg:postcode":"77002",
    "sg:province":"TX",
    "wof:name":"Bank of Scotland",
    "wof:placetype":"venue"
},
  "geometry": {"coordinates":[-95.364998,29.7568],"type":"Point"}
}