{
  "type": "Feature",
  "properties": {
    "iso:country":"US",
    "sg:address":"113 Simonton St",
    "sg:city":"Conroe",
    "sg:classifiers":[
        {
            "category":"Health Services",
            "subcategory":"Clinic",
            "type":"Services"
        }
    ],
    "sg:phone":"+1 936 756 7400",
    "sg:postcode":"77301",
    "sg:province":"TX",
    "sg:tags":[
        "business"
    ],
    "wof:name":"Winter Joe Investigators Co",
    "wof:placetype":"venue"
},
  "geometry": {"coordinates":[-95.45613,30.311202],"type":"Point"}
}