{
  "type": "Feature",
  "properties": {
    "iso:country":"US",
    "sg:address":"2213 S 1st St.",
    "sg:city":"Austin",
    "sg:classifiers":[
        {
            "category":"Shopping",
            "subcategory":"Antiques",
            "type":"Retail Goods"
        },
        {
            "category":"Shopping",
            "subcategory":"Used Merchandise",
            "type":"Retail Goods"
        }
    ],
    "sg:phone":"+1 512 442 4446",
    "sg:postcode":"78704",
    "sg:province":"TX",
    "sg:tags":[
        "vintage",
        "consignment"
    ],
    "sg:website":"www.ameliasretrovogue.com",
    "wof:name":"Amelia's Retro-Vogue and Relics",
    "wof:placetype":"venue"
},
  "geometry": {"coordinates":[-97.758059,30.243521],"type":"Point"}
}