{
  "type": "Feature",
  "properties": {
    "iso:country":"US",
    "sg:address":"4701 Mangum Rd",
    "sg:city":"Houston",
    "sg:classifiers":[
        {
            "category":"Organizations",
            "subcategory":"Community Association",
            "type":"Services"
        }
    ],
    "sg:phone":"+1 713 686 4443",
    "sg:postcode":"77092",
    "sg:province":"TX",
    "wof:name":"Post 9183",
    "wof:placetype":"venue"
},
  "geometry": {"coordinates":[-95.46285399999999,29.838025],"type":"Point"}
}