{
  "type": "Feature",
  "properties": {
    "iso:country":"US",
    "sg:address":"10324 FM 1972",
    "sg:city":"Gilmer",
    "sg:classifiers":[
        {
            "category":"Building & Trades",
            "subcategory":"Construction",
            "type":"Services"
        }
    ],
    "sg:phone":"+1 903 797 6980",
    "sg:postcode":"75645",
    "sg:province":"TX",
    "sg:tags":[
        "excavating",
        "contractor"
    ],
    "wof:name":"Dorgan Construction Inc",
    "wof:placetype":"venue"
},
  "geometry": {"coordinates":[-94.769955,32.738225],"type":"Point"}
}