{
  "type": "Feature",
  "properties": {
    "iso:country":"US",
    "sg:address":"32811 FM 2978",
    "sg:city":"Magnolia",
    "sg:classifiers":[
        {
            "category":"Banks & Credit Unions",
            "subcategory":"Bank",
            "type":"Services"
        }
    ],
    "sg:phone":"+1 281 252 6261",
    "sg:postcode":"77354",
    "sg:province":"TX",
    "sg:tags":[
        "mortgage"
    ],
    "wof:name":"Mortgages Of Texas",
    "wof:placetype":"venue"
},
  "geometry": {"coordinates":[-95.56823300000001,30.219236],"type":"Point"}
}