{
  "type": "Feature",
  "properties": {
    "iso:country":"US",
    "sg:address":"7322 Southwest Fwy",
    "sg:city":"Houston",
    "sg:classifiers":[
        {
            "category":"Building & Trades",
            "subcategory":"Construction",
            "type":"Services"
        }
    ],
    "sg:phone":"+1 713 995 4997",
    "sg:postcode":"77074",
    "sg:province":"TX",
    "sg:tags":[
        "management",
        "builder",
        "real estate",
        "operative"
    ],
    "wof:name":"Acacia Equities",
    "wof:placetype":"venue"
},
  "geometry": {"coordinates":[-95.51356699999999,29.704552],"type":"Point"}
}