{
  "type": "Feature",
  "properties": {
    "iso:country":"US",
    "sg:address":"4400 Sunbelt Dr",
    "sg:city":"Addison",
    "sg:classifiers":[
        {
            "category":"Wholesale",
            "subcategory":"Machinery & Supplies",
            "type":"Manufacturing & Wholesale Goods"
        }
    ],
    "sg:phone":"+1 972 248 1891",
    "sg:postcode":"75001",
    "sg:province":"TX",
    "sg:tags":[
        "equipment",
        "screen",
        "printing"
    ],
    "wof:name":"Lynn Stephens Assoc",
    "wof:placetype":"venue"
},
  "geometry": {"coordinates":[-96.83592899999999,32.97707],"type":"Point"}
}