{
  "type": "Feature",
  "properties": {
    "iso:country":"US",
    "sg:address":"8262 Abrams Rd",
    "sg:city":"Dallas",
    "sg:classifiers":[
        {
            "category":"Health Services",
            "subcategory":"Doctor",
            "type":"Services"
        }
    ],
    "sg:phone":"+1 214 349 3016",
    "sg:postcode":"75231",
    "sg:province":"TX",
    "sg:tags":[
        "dentist"
    ],
    "wof:name":"Mark Jones DDS",
    "wof:placetype":"venue"
},
  "geometry": {"coordinates":[-96.74092400000001,32.893056],"type":"Point"}
}