{
  "type": "Feature",
  "properties": {
    "iso:country":"US",
    "sg:address":"4800 Texoma Pkwy",
    "sg:city":"Sherman",
    "sg:classifiers":[
        {
            "category":"Shopping",
            "subcategory":"Department Store",
            "type":"Retail Goods"
        }
    ],
    "sg:phone":"+1 903 893 7566",
    "sg:postcode":"75090",
    "sg:province":"TX",
    "sg:website":"www.jcpenney.com",
    "wof:name":"J C Penney Co",
    "wof:placetype":"venue"
},
  "geometry": {"coordinates":[-96.58098,33.687988],"type":"Point"}
}