{
  "type": "Feature",
  "properties": {
    "iso:country":"US",
    "sg:address":"5045 Crestwick Dr",
    "sg:city":"Corpus Christi",
    "sg:classifiers":[
        {
            "category":"Organizations",
            "subcategory":"Religious Organization",
            "type":"Services"
        }
    ],
    "sg:phone":"+1 361 991 5669",
    "sg:postcode":"78413",
    "sg:province":"TX",
    "wof:name":"Gideons International",
    "wof:placetype":"venue"
},
  "geometry": {"coordinates":[-97.386577,27.699852],"type":"Point"}
}