{
  "type": "Feature",
  "properties": {
    "iso:country":"US",
    "sg:address":"617 Norwood Dr",
    "sg:city":"Rockwall",
    "sg:classifiers":[
        {
            "category":"Home & Garden",
            "subcategory":"Building Materials",
            "type":"Retail Goods"
        }
    ],
    "sg:phone":"+1 972 771 2776",
    "sg:postcode":"75032",
    "sg:province":"TX",
    "sg:tags":[
        "garage",
        "opener",
        "door"
    ],
    "wof:name":"Door Service",
    "wof:placetype":"venue"
},
  "geometry": {"coordinates":[-96.454885,32.894261],"type":"Point"}
}