{
  "type": "Feature",
  "properties": {
    "iso:country":"US",
    "sg:address":"1607 Fir Harbor Ct",
    "sg:city":"Allen",
    "sg:classifiers":[
        {
            "category":"Retail",
            "subcategory":"Auto Rental",
            "type":"Services"
        }
    ],
    "sg:phone":"+1 972 359 0247",
    "sg:postcode":"75002",
    "sg:province":"TX",
    "wof:name":"VIP Dallas",
    "wof:placetype":"venue"
},
  "geometry": {"coordinates":[-96.62709099999999,33.07965],"type":"Point"}
}