{
  "type": "Feature",
  "properties": {
    "iso:country":"US",
    "sg:address":"7314 Bridges Ave",
    "sg:city":"Fort Worth",
    "sg:classifiers":[
        {
            "category":"Recreation",
            "type":"Entertainment"
        }
    ],
    "sg:phone":"+1 817 284 0252",
    "sg:postcode":"76118",
    "sg:province":"TX",
    "wof:name":"Safety First",
    "wof:placetype":"venue"
},
  "geometry": {"coordinates":[-97.223651,32.811176],"type":"Point"}
}