{
  "type": "Feature",
  "properties": {
    "iso:country":"US",
    "sg:address":"975 Gulf St",
    "sg:city":"Beaumont",
    "sg:classifiers":[
        {
            "category":"Retail",
            "subcategory":"Auto Repair",
            "type":"Services"
        }
    ],
    "sg:phone":"+1 409 835 5260",
    "sg:postcode":"77703",
    "sg:province":"TX",
    "sg:tags":[
        "repairing",
        "automobile"
    ],
    "wof:name":"Gulf Automotive Repair",
    "wof:placetype":"venue"
},
  "geometry": {"coordinates":[-94.112195,30.090087],"type":"Point"}
}