{
  "type": "Feature",
  "properties": {
    "iso:country":"US",
    "sg:address":"12307 Roxie Dr",
    "sg:city":"Austin",
    "sg:classifiers":[
        {
            "category":"Shopping",
            "subcategory":"Bicycles & Sporting Goods",
            "type":"Retail Goods"
        }
    ],
    "sg:phone":"+1 512 331 2002",
    "sg:postcode":"78729",
    "sg:province":"TX",
    "sg:tags":[
        "mountain",
        "bike",
        "mfg"
    ],
    "wof:name":"Hammerhead Bikes Inc",
    "wof:placetype":"venue"
},
  "geometry": {"coordinates":[-97.780822,30.445874],"type":"Point"}
}