{
  "type": "Feature",
  "properties": {
    "iso:country":"US",
    "sg:address":"441 W 17th St",
    "sg:city":"Houston",
    "sg:classifiers":[
        {
            "category":"Professional",
            "subcategory":"Business Services",
            "type":"Services"
        }
    ],
    "sg:phone":"+1 713 301 8128",
    "sg:postcode":"77008",
    "sg:province":"TX",
    "sg:tags":[
        "consulting",
        "investment"
    ],
    "wof:name":"Three Comma Ventures",
    "wof:placetype":"venue"
},
  "geometry": {"coordinates":[-95.405,29.800897],"type":"Point"}
}