{
  "type": "Feature",
  "properties": {
    "iso:country":"US",
    "sg:address":"600 S Main St",
    "sg:city":"Elgin",
    "sg:classifiers":[
        {
            "category":"Food & Beverages",
            "subcategory":"Meat & Fish",
            "type":"Retail Goods"
        }
    ],
    "sg:phone":"+1 512 285 3331",
    "sg:postcode":"78621",
    "sg:province":"TX",
    "sg:tags":[
        "sausage"
    ],
    "sg:website":"www.elginsausage.com",
    "wof:name":"Meyer Sausage Co",
    "wof:placetype":"venue"
},
  "geometry": {"coordinates":[-97.36762299999999,30.339974],"type":"Point"}
}