{
  "type": "Feature",
  "properties": {
    "iso:country":"US",
    "sg:address":"1105 Foundation Dr",
    "sg:city":"Caldwell",
    "sg:classifiers":[
        {
            "category":"Manufacturing",
            "subcategory":"Metals",
            "type":"Manufacturing & Wholesale Goods"
        }
    ],
    "sg:phone":"+1 713 757 9810",
    "sg:postcode":"77836",
    "sg:province":"TX",
    "sg:website":"www.apf-inc.com",
    "wof:name":"Allied Precision",
    "wof:placetype":"venue"
},
  "geometry": {"coordinates":[-96.71031499999999,30.532425],"type":"Point"}
}