{
  "type": "Feature",
  "properties": {
    "iso:country":"US",
    "sg:address":"8707 Martin Luther King Jr Blvd",
    "sg:city":"Houston",
    "sg:classifiers":[
        {
            "category":"Personal",
            "subcategory":"Beauty Salon",
            "type":"Services"
        }
    ],
    "sg:phone":"+1 713 734 7143",
    "sg:postcode":"77033",
    "sg:province":"TX",
    "wof:name":"Jazmine's Hair Salon",
    "wof:placetype":"venue"
},
  "geometry": {"coordinates":[-95.336383,29.65645],"type":"Point"}
}