{
  "type": "Feature",
  "properties": {
    "iso:country":"US",
    "sg:address":"6102 Oak Pass Dr",
    "sg:city":"Houston",
    "sg:classifiers":[
        {
            "category":"Shopping",
            "subcategory":"Bridal",
            "type":"Retail Goods"
        }
    ],
    "sg:phone":"+1 713 686 5770",
    "sg:postcode":"77091",
    "sg:province":"TX",
    "wof:name":"Bridal Symposium",
    "wof:placetype":"venue"
},
  "geometry": {"coordinates":[-95.46369900000001,29.8566],"type":"Point"}
}