{
  "type": "Feature",
  "properties": {
    "iso:country":"US",
    "sg:address":"2237 W Holcombe Blvd",
    "sg:city":"Houston",
    "sg:classifiers":[
        {
            "category":"Retail",
            "subcategory":"Car Wash",
            "type":"Services"
        }
    ],
    "sg:phone":"+1 713 349 8244",
    "sg:postcode":"77030",
    "sg:province":"TX",
    "wof:name":"Mister Car Wash and Hot Shine",
    "wof:placetype":"venue"
},
  "geometry": {"coordinates":[-95.41100299999999,29.705999],"type":"Point"}
}