{
  "type": "Feature",
  "properties": {
    "iso:country":"US",
    "sg:address":"1586 Co Rd 4721",
    "sg:city":"Wolfe City",
    "sg:classifiers":[
        {
            "category":"Shopping",
            "subcategory":"Used Merchandise",
            "type":"Retail Goods"
        }
    ],
    "sg:phone":"+1 903 496 7647",
    "sg:postcode":"75496",
    "sg:province":"TX",
    "wof:name":"Rural Country Treasures",
    "wof:placetype":"venue"
},
  "geometry": {"coordinates":[-96.05395,33.326462],"type":"Point"}
}