{
  "type": "Feature",
  "properties": {
    "iso:country":"US",
    "sg:address":"300 S Jackson St",
    "sg:city":"Kaufman",
    "sg:classifiers":[
        {
            "category":"Insurance",
            "subcategory":"Insurance Agent",
            "type":"Services"
        }
    ],
    "sg:phone":"+1 972 962 2525",
    "sg:postcode":"75142",
    "sg:province":"TX",
    "wof:name":"Cindy Wallace Insurance",
    "wof:placetype":"venue"
},
  "geometry": {"coordinates":[-96.309951,32.587206],"type":"Point"}
}