{
  "type": "Feature",
  "properties": {
    "iso:country":"US",
    "sg:address":"13302 Redfish Ln",
    "sg:city":"Stafford",
    "sg:classifiers":[
        {
            "category":"Building & Trades",
            "subcategory":"Construction",
            "type":"Services"
        }
    ],
    "sg:phone":"+1 281 499 8823",
    "sg:postcode":"77477",
    "sg:province":"TX",
    "sg:tags":[
        "glass",
        "screen",
        "enclosure"
    ],
    "wof:name":"Sun Fun Enclosures",
    "wof:placetype":"venue"
},
  "geometry": {"coordinates":[-95.559619,29.629635],"type":"Point"}
}