{
  "type": "Feature",
  "properties": {
    "iso:country":"US",
    "sg:address":"1618 23rd St",
    "sg:city":"Galveston",
    "sg:classifiers":[
        {
            "category":"Manufacturing",
            "subcategory":"Printing",
            "type":"Manufacturing & Wholesale Goods"
        }
    ],
    "sg:phone":"+1 409 762 2333",
    "sg:postcode":"77550",
    "sg:province":"TX",
    "sg:tags":[
        "publisher"
    ],
    "wof:name":"Vanjus Press",
    "wof:placetype":"venue"
},
  "geometry": {"coordinates":[-94.789843,29.294073],"type":"Point"}
}