{
  "type": "Feature",
  "properties": {
    "iso:country":"US",
    "sg:address":"2000 N Main St",
    "sg:city":"Midland",
    "sg:classifiers":[
        {
            "category":"Health Services",
            "subcategory":"Nursing And Care Facility",
            "type":"Services"
        }
    ],
    "sg:phone":"+1 432 570 9902",
    "sg:postcode":"79705",
    "sg:province":"TX",
    "sg:tags":[
        "intermediate"
    ],
    "wof:name":"Rockwood Manor",
    "wof:placetype":"venue"
},
  "geometry": {"coordinates":[-102.077842,32.018744],"type":"Point"}
}