{
  "type": "Feature",
  "properties": {
    "iso:country":"US",
    "sg:address":"620 Victoria St",
    "sg:city":"Laredo",
    "sg:classifiers":[
        {
            "category":"Professional",
            "type":"Services"
        },
        {
            "category":"Mining & Drilling",
            "type":"Manufacturing & Wholesale Goods"
        }
    ],
    "sg:phone":"+1 956 725 4246",
    "sg:postcode":"78040",
    "sg:province":"TX",
    "sg:tags":[
        "stone"
    ],
    "wof:name":"Canteras Finas LLC",
    "wof:placetype":"venue"
},
  "geometry": {"coordinates":[-99.502509,27.507917],"type":"Point"}
}