{
  "type": "Feature",
  "properties": {
    "iso:country":"US",
    "sg:address":"2032 Meadow Glen",
    "sg:city":"Irving",
    "sg:classifiers":[
        {
            "category":"Building & Trades",
            "subcategory":"Plumbing",
            "type":"Services"
        }
    ],
    "sg:phone":"+1 972 986 2588",
    "sg:postcode":"75060",
    "sg:province":"TX",
    "sg:tags":[
        "contractor"
    ],
    "wof:name":"Double B Plumbing Co",
    "wof:placetype":"venue"
},
  "geometry": {"coordinates":[-96.971992,32.787434],"type":"Point"}
}