{
  "type": "Feature",
  "properties": {
    "iso:country":"US",
    "sg:address":"151 Co Rd 211",
    "sg:city":"Liberty Hill",
    "sg:classifiers":[
        {
            "category":"Banks & Credit Unions",
            "subcategory":"Bank",
            "type":"Services"
        }
    ],
    "sg:phone":"+1 512 515 7711",
    "sg:postcode":"78642",
    "sg:province":"TX",
    "sg:tags":[
        "short",
        "institution",
        "business"
    ],
    "wof:name":"Coulter Consulting",
    "wof:placetype":"venue"
},
  "geometry": {"coordinates":[-97.88809500000001,30.717923],"type":"Point"}
}