{
  "type": "Feature",
  "properties": {
    "iso:country":"US",
    "sg:address":"8500 Research Boulevard",
    "sg:city":"Austin",
    "sg:classifiers":[
        {
            "category":"Retail",
            "subcategory":"Auto Rental",
            "type":"Services"
        }
    ],
    "sg:phone":"+1 512 836 9292",
    "sg:postcode":"78758",
    "sg:province":"TX",
    "sg:tags":[
        "car"
    ],
    "wof:name":"One Affordable Car Rental & Sales",
    "wof:placetype":"venue"
},
  "geometry": {"coordinates":[-97.73004,30.378574],"type":"Point"}
}