{
  "type": "Feature",
  "properties": {
    "iso:country":"US",
    "sg:address":"514 E Hwy 377",
    "sg:city":"Granbury",
    "sg:classifiers":[
        {
            "category":"Real Estate",
            "subcategory":"Real Estate Services",
            "type":"Services"
        }
    ],
    "sg:phone":"+1 817 573 8882",
    "sg:postcode":"76048",
    "sg:province":"TX",
    "sg:tags":[
        "abstract",
        "title"
    ],
    "wof:name":"Central Texas Title",
    "wof:placetype":"venue"
},
  "geometry": {"coordinates":[-97.785546,32.434095],"type":"Point"}
}