{
  "type": "Feature",
  "properties": {
    "iso:country":"US",
    "sg:address":"917 E 5th Ave",
    "sg:city":"Corsicana",
    "sg:classifiers":[
        {
            "category":"Organizations",
            "subcategory":"Religious Organization",
            "type":"Services"
        }
    ],
    "sg:phone":"+1 903 872 7470",
    "sg:postcode":"75110",
    "sg:province":"TX",
    "sg:tags":[
        "church"
    ],
    "wof:name":"Church Of The Living God Cwff",
    "wof:placetype":"venue"
},
  "geometry": {"coordinates":[-96.4563,32.098304],"type":"Point"}
}