{
  "type": "Feature",
  "properties": {
    "iso:country":"US",
    "sg:address":"16410 Stewart Rd",
    "sg:city":"Austin",
    "sg:classifiers":[
        {
            "category":"Restaurant",
            "type":"Food & Drink"
        },
        {
            "category":"Bars & Pubs",
            "type":"Food & Drink"
        }
    ],
    "sg:phone":"+1 512 266 0331",
    "sg:postcode":"78734",
    "sg:province":"TX",
    "sg:tags":[
        "eating"
    ],
    "wof:name":"Aunt Tilly's Island Cafe & Bar",
    "wof:placetype":"venue"
},
  "geometry": {"coordinates":[-97.95841799999999,30.379697],"type":"Point"}
}