{
  "type": "Feature",
  "properties": {
    "iso:country":"US",
    "sg:address":"516 W Hopkins St",
    "sg:city":"San Marcos",
    "sg:classifiers":[
        {
            "category":"Organizations",
            "subcategory":"Religious Organization",
            "type":"Services"
        }
    ],
    "sg:phone":"+1 512 392 9816",
    "sg:postcode":"78666",
    "sg:province":"TX",
    "wof:name":"Baha'i Faith",
    "wof:placetype":"venue"
},
  "geometry": {"coordinates":[-97.94625499999999,29.881995],"type":"Point"}
}