{
  "type": "Feature",
  "properties": {
    "iso:country":"US",
    "sg:address":"90 Cedar Loop",
    "sg:city":"Hearne",
    "sg:classifiers":[
        {
            "category":"Building & Trades",
            "subcategory":"Cleaning & Sanitation",
            "type":"Services"
        }
    ],
    "sg:phone":"+1 979 279 5842",
    "sg:postcode":"77859",
    "sg:province":"TX",
    "sg:tags":[
        "maintenance"
    ],
    "wof:name":"Emmanuel Cleaning Service",
    "wof:placetype":"venue"
},
  "geometry": {"coordinates":[-96.572452,30.850067],"type":"Point"}
}