{
  "type": "Feature",
  "properties": {
    "iso:country":"US",
    "sg:address":"1022 N Main St",
    "sg:city":"Pearland",
    "sg:classifiers":[
        {
            "category":"Shopping",
            "subcategory":"Florist",
            "type":"Retail Goods"
        }
    ],
    "sg:phone":"+1 281 485 3006",
    "sg:postcode":"77581",
    "sg:province":"TX",
    "wof:name":"Unique Flower Shop",
    "wof:placetype":"venue"
},
  "geometry": {"coordinates":[-95.28658299999999,29.596622],"type":"Point"}
}