{
  "type": "Feature",
  "properties": {
    "iso:country":"US",
    "sg:address":"7509 Chevy Chase Dr",
    "sg:city":"Houston",
    "sg:classifiers":[
        {
            "category":"Real Estate",
            "subcategory":"Real Estate Agent",
            "type":"Services"
        }
    ],
    "sg:phone":"+1 713 974 2010",
    "sg:postcode":"77063",
    "sg:province":"TX",
    "wof:name":"E & P Peeples Co Inc",
    "wof:placetype":"venue"
},
  "geometry": {"coordinates":[-95.501077,29.744624],"type":"Point"}
}