{
  "type": "Feature",
  "properties": {
    "iso:country":"US",
    "sg:address":"727 Cumberland Rd",
    "sg:city":"Tyler",
    "sg:classifiers":[
        {
            "category":"Food & Beverages",
            "subcategory":"Bakery",
            "type":"Retail Goods"
        }
    ],
    "sg:phone":"+1 903 939 8871",
    "sg:postcode":"75703",
    "sg:province":"TX",
    "sg:tags":[
        "grocery"
    ],
    "wof:name":"Golden French Bakeries Inc",
    "wof:placetype":"venue"
},
  "geometry": {"coordinates":[-95.303741,32.25658],"type":"Point"}
}