{
  "type": "Feature",
  "properties": {
    "iso:country":"US",
    "sg:address":"206 Banbridge Ave",
    "sg:city":"San Antonio",
    "sg:classifiers":[
        {
            "category":"Home & Garden",
            "subcategory":"Furniture",
            "type":"Retail Goods"
        }
    ],
    "sg:phone":"+1 210 670 0026",
    "sg:postcode":"78223",
    "sg:province":"TX",
    "wof:name":"Innovative Design",
    "wof:placetype":"venue"
},
  "geometry": {"coordinates":[-98.427364,29.366272],"type":"Point"}
}