{
  "type": "Feature",
  "properties": {
    "iso:country":"US",
    "sg:address":"1535 Quartet Dr",
    "sg:city":"Dallas",
    "sg:classifiers":[
        {
            "category":"Professional",
            "type":"Services"
        }
    ],
    "sg:phone":"+1 214 376 8940",
    "sg:postcode":"75241",
    "sg:province":"TX",
    "wof:name":"Michelles Accessories",
    "wof:placetype":"venue"
},
  "geometry": {"coordinates":[-96.801147,32.666725],"type":"Point"}
}