{
  "type": "Feature",
  "properties": {
    "iso:country":"US",
    "sg:address":"6106 River Mill Ct",
    "sg:city":"Spring",
    "sg:classifiers":[
        {
            "category":"Professional",
            "subcategory":"Business Services",
            "type":"Services"
        }
    ],
    "sg:phone":"+1 281 370 6896",
    "sg:postcode":"77379",
    "sg:province":"TX",
    "wof:name":"European Business Management",
    "wof:placetype":"venue"
},
  "geometry": {"coordinates":[-95.51409,30.037483],"type":"Point"}
}