{
  "type": "Feature",
  "properties": {
    "iso:country":"US",
    "sg:address":"241 Co Rd 219",
    "sg:city":"Orange Grove",
    "sg:classifiers":[
        {
            "category":"Retail",
            "subcategory":"Repair Shop",
            "type":"Services"
        }
    ],
    "sg:phone":"+1 361 384 1473",
    "sg:postcode":"78372",
    "sg:province":"TX",
    "sg:tags":[
        "welding"
    ],
    "wof:name":"Manuels Welding Service",
    "wof:placetype":"venue"
},
  "geometry": {"coordinates":[-97.967276,27.913269],"type":"Point"}
}