{
  "type": "Feature",
  "properties": {
    "iso:country":"US",
    "sg:address":"1905 Junction Hwy",
    "sg:city":"Kerrville",
    "sg:classifiers":[
        {
            "category":"Wholesale",
            "subcategory":"Beer",
            "type":"Manufacturing & Wholesale Goods"
        }
    ],
    "sg:phone":"+1 830 895 3088",
    "sg:postcode":"78028",
    "sg:province":"TX",
    "sg:tags":[
        "distributor",
        "ale"
    ],
    "wof:name":"Carson Distributing Company",
    "wof:placetype":"venue"
},
  "geometry": {"coordinates":[-99.19193199999999,30.072474],"type":"Point"}
}