{
  "type": "Feature",
  "properties": {
    "iso:country":"US",
    "sg:address":"406 Frankston St",
    "sg:city":"Jacksonville",
    "sg:classifiers":[
        {
            "category":"Personal",
            "subcategory":"Beauty Salon",
            "type":"Services"
        }
    ],
    "sg:phone":"+1 903 589 4384",
    "sg:postcode":"75766",
    "sg:province":"TX",
    "wof:name":"Ann's Beauty Ball",
    "wof:placetype":"venue"
},
  "geometry": {"coordinates":[-95.28342600000001,31.974387],"type":"Point"}
}