{
  "type": "Feature",
  "properties": {
    "iso:country":"US",
    "sg:address":"4114 34th St",
    "sg:city":"Lubbock",
    "sg:classifiers":[
        {
            "category":"Shopping",
            "subcategory":"Bicycles & Sporting Goods",
            "type":"Retail Goods"
        }
    ],
    "sg:phone":"+1 806 795 8265",
    "sg:postcode":"79410",
    "sg:province":"TX",
    "sg:tags":[
        "equipment",
        "diver",
        "supply"
    ],
    "wof:name":"Prairie Scuba Adventures",
    "wof:placetype":"venue"
},
  "geometry": {"coordinates":[-101.90154699999999,33.563338],"type":"Point"}
}