{
  "type": "Feature",
  "properties": {
    "iso:country":"US",
    "sg:address":"3521 Raquel Ave",
    "sg:city":"Mcallen",
    "sg:classifiers":[
        {
            "category":"Shopping",
            "subcategory":"Clothing, Apparel, & Fashions",
            "type":"Retail Goods"
        }
    ],
    "sg:phone":"+1 956 702 0425",
    "sg:postcode":"78503",
    "sg:province":"TX",
    "sg:tags":[
        "t"
    ],
    "wof:name":"Original R & G",
    "wof:placetype":"venue"
},
  "geometry": {"coordinates":[-98.26715,26.160674],"type":"Point"}
}