{
  "type": "Feature",
  "properties": {
    "iso:country":"US",
    "sg:address":"2747 Airport Fwy",
    "sg:city":"Fort Worth",
    "sg:classifiers":[
        {
            "category":"Shopping",
            "subcategory":"Computers & Home Electronics",
            "type":"Retail Goods"
        }
    ],
    "sg:phone":"+1 817 831 9221",
    "sg:postcode":"76111",
    "sg:province":"TX",
    "sg:tags":[
        "parts",
        "supply"
    ],
    "wof:name":"P C Components",
    "wof:placetype":"venue"
},
  "geometry": {"coordinates":[-97.307721,32.767935],"type":"Point"}
}