{
  "type": "Feature",
  "properties": {
    "iso:country":"US",
    "sg:address":"600 N Wildwood Dr",
    "sg:city":"Irving",
    "sg:classifiers":[
        {
            "category":"Freight",
            "type":"Transportation"
        },
        {
            "category":"Wholesale",
            "subcategory":"Sporting Goods",
            "type":"Manufacturing & Wholesale Goods"
        }
    ],
    "sg:phone":"+1 972 579 3457",
    "sg:postcode":"75061",
    "sg:province":"TX",
    "sg:tags":[
        "warehouse",
        "shoe",
        "store",
        "footwear"
    ],
    "wof:name":"Close Out Warehouse",
    "wof:placetype":"venue"
},
  "geometry": {"coordinates":[-96.916702,32.820202],"type":"Point"}
}