{
  "type": "Feature",
  "properties": {
    "iso:country":"US",
    "sg:address":"901 Rose St",
    "sg:city":"Crowley",
    "sg:classifiers":[
        {
            "category":"Wholesale",
            "subcategory":"Non-durable Goods",
            "type":"Manufacturing & Wholesale Goods"
        }
    ],
    "sg:phone":"+1 817 297 4727",
    "sg:postcode":"76036",
    "sg:province":"TX",
    "wof:name":"Vickies Imports",
    "wof:placetype":"venue"
},
  "geometry": {"coordinates":[-97.373245,32.575148],"type":"Point"}
}