{
  "type": "Feature",
  "properties": {
    "iso:country":"US",
    "sg:address":"800 Hwy 3 S",
    "sg:city":"League City",
    "sg:classifiers":[
        {
            "category":"Real Estate",
            "subcategory":"Real Estate Operator",
            "type":"Services"
        }
    ],
    "sg:phone":"+1 281 332 9922",
    "sg:postcode":"77573",
    "sg:province":"TX",
    "sg:tags":[
        "mobile",
        "home",
        "site"
    ],
    "wof:name":"Shady Oaks Mobile Home Cmnty",
    "wof:placetype":"venue"
},
  "geometry": {"coordinates":[-95.09017799999999,29.50216],"type":"Point"}
}