{
  "type": "Feature",
  "properties": {
    "iso:country":"US",
    "sg:address":"4915 Grey Hawk St",
    "sg:city":"San Antonio",
    "sg:classifiers":[
        {
            "category":"Building & Trades",
            "subcategory":"Plumbing",
            "type":"Services"
        }
    ],
    "sg:phone":"+1 210 364 6659",
    "sg:postcode":"78217",
    "sg:province":"TX",
    "sg:tags":[
        "plumbing",
        "contractor"
    ],
    "wof:name":"Plumbing Contractors",
    "wof:placetype":"venue"
},
  "geometry": {"coordinates":[-98.389893,29.567769],"type":"Point"}
}