{
  "type": "Feature",
  "properties": {
    "iso:country":"US",
    "sg:address":"205 W Broadway St",
    "sg:city":"Prosper",
    "sg:classifiers":[
        {
            "category":"Building & Trades",
            "subcategory":"Landscaping Services",
            "type":"Services"
        }
    ],
    "sg:phone":"+1 972 346 2696",
    "sg:postcode":"75078",
    "sg:province":"TX",
    "sg:tags":[
        "lawn",
        "maintenance",
        "grounds"
    ],
    "wof:name":"Lawn Tech",
    "wof:placetype":"venue"
},
  "geometry": {"coordinates":[-96.80433499999999,33.236115],"type":"Point"}
}