{
  "type": "Feature",
  "properties": {
    "iso:country":"US",
    "sg:address":"1729 Brittmoore Rd",
    "sg:city":"Houston",
    "sg:classifiers":[
        {
            "category":"Manufacturing",
            "subcategory":"Tools & Machinery",
            "type":"Manufacturing & Wholesale Goods"
        }
    ],
    "sg:phone":"+1 713 461 7622",
    "sg:postcode":"77043",
    "sg:province":"TX",
    "sg:tags":[
        "machine",
        "shop"
    ],
    "wof:name":"Emerald Machine Inc",
    "wof:placetype":"venue"
},
  "geometry": {"coordinates":[-95.569953,29.807701],"type":"Point"}
}