{
  "type": "Feature",
  "properties": {
    "iso:country":"US",
    "sg:address":"630 Morgan St",
    "sg:city":"Meridian",
    "sg:classifiers":[
        {
            "category":"Home & Garden",
            "subcategory":"Furniture",
            "type":"Retail Goods"
        }
    ],
    "sg:phone":"+1 254 435 6848",
    "sg:postcode":"76665",
    "sg:province":"TX",
    "wof:name":"P&P Wood Works",
    "wof:placetype":"venue"
},
  "geometry": {"coordinates":[-97.651601,31.926147],"type":"Point"}
}