{
  "type": "Feature",
  "properties": {
    "iso:country":"US",
    "sg:address":"3326 Burgoyne St",
    "sg:city":"Dallas",
    "sg:classifiers":[
        {
            "category":"Health Services",
            "subcategory":"Nursing And Care Facility",
            "type":"Services"
        }
    ],
    "sg:phone":"+1 214 467 3625",
    "sg:postcode":"75233",
    "sg:province":"TX",
    "sg:tags":[
        "hair",
        "salon",
        "styling"
    ],
    "wof:name":"Lucilles Mnrcare Styling Salon",
    "wof:placetype":"venue"
},
  "geometry": {"coordinates":[-96.875179,32.710632],"type":"Point"}
}