{
  "type": "Feature",
  "properties": {
    "iso:country":"US",
    "sg:address":"1721 Wyoming Ave",
    "sg:city":"El Paso",
    "sg:classifiers":[
        {
            "category":"Building & Trades",
            "subcategory":"Construction",
            "type":"Services"
        }
    ],
    "sg:phone":"+1 915 544 8100",
    "sg:postcode":"79902",
    "sg:province":"TX",
    "sg:tags":[
        "house"
    ],
    "wof:name":"R&D Contractors",
    "wof:placetype":"venue"
},
  "geometry": {"coordinates":[-106.47416200000001,31.772944],"type":"Point"}
}