{
  "type": "Feature",
  "properties": {
    "iso:country":"US",
    "sg:address":"5685 FM 1346",
    "sg:city":"San Antonio",
    "sg:classifiers":[
        {
            "category":"Freight",
            "type":"Transportation"
        }
    ],
    "sg:phone":"+1 210 662 6060",
    "sg:postcode":"78220",
    "sg:province":"TX",
    "sg:tags":[
        "local",
        "without",
        "storage",
        "trucking"
    ],
    "wof:name":"C S E",
    "wof:placetype":"venue"
},
  "geometry": {"coordinates":[-98.374482,29.422435],"type":"Point"}
}