{
  "type": "Feature",
  "properties": {
    "iso:country":"US",
    "sg:address":"6408 Stevenson Ave",
    "sg:city":"Odessa",
    "sg:classifiers":[
        {
            "category":"Retail",
            "subcategory":"Animal Services",
            "type":"Services"
        }
    ],
    "sg:phone":"+1 432 366 4348",
    "sg:postcode":"79762",
    "sg:province":"TX",
    "sg:tags":[
        "pet",
        "grooming",
        "washing"
    ],
    "wof:name":"Rena's Grooming Shop",
    "wof:placetype":"venue"
},
  "geometry": {"coordinates":[-102.385783,31.907239],"type":"Point"}
}