{
  "type": "Feature",
  "properties": {
    "iso:country":"US",
    "sg:address":"3920 Harry Wurzbach Rd",
    "sg:city":"San Antonio",
    "sg:classifiers":[
        {
            "category":"Bakery",
            "type":"Food & Drink"
        }
    ],
    "sg:menulink":"http://www.allmenus.com/tx/san-antonio/14420-crumpets-restaurant--bakery/menu/",
    "sg:phone":"+1 210 821 5600",
    "sg:postcode":"78209",
    "sg:province":"TX",
    "sg:tags":[
        "american",
        "pastry"
    ],
    "wof:name":"Crumpets Restaurant & Bakery",
    "wof:placetype":"venue"
},
  "geometry": {"coordinates":[-98.43445800000001,29.505807],"type":"Point"}
}