{
  "type": "Feature",
  "properties": {
    "iso:country":"US",
    "sg:address":"12 Spurwood Ct",
    "sg:city":"Spring",
    "sg:classifiers":[
        {
            "category":"Shopping",
            "subcategory":"Pets & Pet Supplies",
            "type":"Retail Goods"
        }
    ],
    "sg:phone":"+1 281 419 6854",
    "sg:postcode":"77381",
    "sg:province":"TX",
    "sg:tags":[
        "furnishing",
        "dog",
        "store",
        "cat"
    ],
    "wof:name":"Cee Cees Pet Sitting & More",
    "wof:placetype":"venue"
},
  "geometry": {"coordinates":[-95.496624,30.177182],"type":"Point"}
}