{
  "type": "Feature",
  "properties": {
    "iso:country":"US",
    "sg:address":"4908 Baton Rouge Blvd",
    "sg:city":"Frisco",
    "sg:classifiers":[
        {
            "category":"Professional",
            "subcategory":"Business Services",
            "type":"Services"
        }
    ],
    "sg:phone":"+1 972 335 3954",
    "sg:postcode":"75035",
    "sg:province":"TX",
    "wof:name":"Burg Group LLC",
    "wof:placetype":"venue"
},
  "geometry": {"coordinates":[-96.787334,33.119055],"type":"Point"}
}