{
  "type": "Feature",
  "properties": {
    "iso:country":"US",
    "sg:address":"5527 Richmond Ave",
    "sg:city":"Houston",
    "sg:classifiers":[
        {
            "category":"Shopping",
            "subcategory":"Beauty & Cosmetics",
            "type":"Retail Goods"
        }
    ],
    "sg:phone":"+1 713 789 5453",
    "sg:postcode":"77056",
    "sg:province":"TX",
    "sg:tags":[
        "supply"
    ],
    "wof:name":"Abco Salon Services",
    "wof:placetype":"venue"
},
  "geometry": {"coordinates":[-95.47463500000001,29.731278],"type":"Point"}
}