{
  "type": "Feature",
  "properties": {
    "iso:country":"US",
    "sg:address":"7005 Bennett Ave",
    "sg:city":"Austin",
    "sg:classifiers":[
        {
            "category":"Professional",
            "subcategory":"Business Services",
            "type":"Services"
        }
    ],
    "sg:phone":"+1 512 302 1644",
    "sg:postcode":"78752",
    "sg:province":"TX",
    "wof:name":"Haven Of Hope",
    "wof:placetype":"venue"
},
  "geometry": {"coordinates":[-97.70031899999999,30.331063],"type":"Point"}
}