{
  "type": "Feature",
  "properties": {
    "iso:country":"US",
    "sg:address":"3510 Greenwood Pl",
    "sg:city":"Deer Park",
    "sg:classifiers":[
        {
            "category":"Organizations",
            "subcategory":"Religious Organization",
            "type":"Services"
        }
    ],
    "sg:phone":"+1 281 930 1133",
    "sg:postcode":"77536",
    "sg:province":"TX",
    "sg:tags":[
        "church"
    ],
    "wof:name":"Congregation Beth Ha Shem",
    "wof:placetype":"venue"
},
  "geometry": {"coordinates":[-95.13801599999999,29.680313],"type":"Point"}
}