{
  "type": "Feature",
  "properties": {
    "iso:country":"US",
    "sg:address":"1502 Lakewood Dr",
    "sg:city":"Sherman",
    "sg:classifiers":[
        {
            "category":"Professional",
            "subcategory":"Advertising",
            "type":"Services"
        }
    ],
    "sg:phone":"+1 903 813 0307",
    "sg:postcode":"75092",
    "sg:province":"TX",
    "sg:tags":[
        "marketing",
        "consulting"
    ],
    "wof:name":"Visual Paradigm",
    "wof:placetype":"venue"
},
  "geometry": {"coordinates":[-96.633503,33.661814],"type":"Point"}
}