{
  "type": "Feature",
  "properties": {
    "iso:country":"US",
    "sg:address":"1328 Circle Oak Dr",
    "sg:city":"Schertz",
    "sg:classifiers":[
        {
            "category":"Real Estate",
            "subcategory":"Real Estate Agent",
            "type":"Services"
        }
    ],
    "sg:phone":"+1 210 658 6194",
    "sg:postcode":"78154",
    "sg:province":"TX",
    "wof:name":"C & L Southwest Properties Inc",
    "wof:placetype":"venue"
},
  "geometry": {"coordinates":[-98.268287,29.591571],"type":"Point"}
}