{
  "type": "Feature",
  "properties": {
    "iso:country":"US",
    "sg:address":"286 Pack Saddle Pass",
    "sg:city":"Abilene",
    "sg:classifiers":[
        {
            "category":"Retail",
            "subcategory":"Auto Repair",
            "type":"Services"
        }
    ],
    "sg:phone":"+1 325 695 1312",
    "sg:postcode":"79602",
    "sg:province":"TX",
    "sg:tags":[
        "general"
    ],
    "wof:name":"Griffin Automotive",
    "wof:placetype":"venue"
},
  "geometry": {"coordinates":[-99.706585,32.341505],"type":"Point"}
}