{
  "type": "Feature",
  "properties": {
    "iso:country":"US",
    "sg:address":"1500 Louisiana St",
    "sg:city":"Houston",
    "sg:classifiers":[
        {
            "category":"Professional",
            "subcategory":"Business Services",
            "type":"Services"
        }
    ],
    "sg:phone":"+1 713 756 0150",
    "sg:postcode":"77002",
    "sg:province":"TX",
    "wof:name":"Imico LP",
    "wof:placetype":"venue"
},
  "geometry": {"coordinates":[-95.371056,29.754049],"type":"Point"}
}