{
  "type": "Feature",
  "properties": {
    "iso:country":"US",
    "sg:address":"6101 Ben Rd",
    "sg:city":"Sachse",
    "sg:classifiers":[
        {
            "category":"Recreation",
            "type":"Entertainment"
        }
    ],
    "sg:phone":"+1 972 530 1124",
    "sg:postcode":"75048",
    "sg:province":"TX",
    "sg:tags":[
        "riding",
        "academy"
    ],
    "sg:website":"www.capricornhorse.com",
    "wof:name":"Capricorn Equestrian Ctr",
    "wof:placetype":"venue"
},
  "geometry": {"coordinates":[-96.557975,32.962705],"type":"Point"}
}