{
  "type": "Feature",
  "properties": {
    "iso:country":"US",
    "sg:address":"3703 Fredericksburg Rd",
    "sg:city":"San Antonio",
    "sg:classifiers":[
        {
            "category":"Shopping",
            "subcategory":"Computers & Home Electronics",
            "type":"Retail Goods"
        }
    ],
    "sg:phone":"+1 210 735 3035",
    "sg:postcode":"78201",
    "sg:province":"TX",
    "sg:tags":[
        "equipment",
        "radio"
    ],
    "wof:name":"Curtis Mathis Home Entrmt Ctr",
    "wof:placetype":"venue"
},
  "geometry": {"coordinates":[-98.541984,29.480378],"type":"Point"}
}