{
  "type": "Feature",
  "properties": {
    "iso:country":"US",
    "sg:address":"309 E Church St Ofc",
    "sg:city":"Olney",
    "sg:classifiers":[
        {
            "category":"Personal",
            "subcategory":"Beauty Salon",
            "type":"Services"
        }
    ],
    "sg:phone":"+1 940 564 3541",
    "sg:postcode":"76374",
    "sg:province":"TX",
    "wof:name":"Pat Walker Figure Salon",
    "wof:placetype":"venue"
},
  "geometry": {"coordinates":[-98.751442,33.364699],"type":"Point"}
}