{
  "type": "Feature",
  "properties": {
    "iso:country":"US",
    "sg:address":"11500 E Northwest Hwy",
    "sg:city":"Dallas",
    "sg:classifiers":[
        {
            "category":"Autos & Motor Vehicles",
            "subcategory":"Automobile Sales",
            "type":"Retail Goods"
        }
    ],
    "sg:phone":"+1 214 660 1800",
    "sg:postcode":"75218",
    "sg:province":"TX",
    "sg:tags":[
        "used"
    ],
    "wof:name":"Big D Kia",
    "wof:placetype":"venue"
},
  "geometry": {"coordinates":[-96.678918,32.864145],"type":"Point"}
}