{
  "type": "Feature",
  "properties": {
    "iso:country":"US",
    "sg:address":"502 E Denman Ave",
    "sg:city":"Lufkin",
    "sg:classifiers":[
        {
            "category":"Food & Beverages",
            "subcategory":"Bakery",
            "type":"Retail Goods"
        }
    ],
    "sg:phone":"+1 936 632 7484",
    "sg:postcode":"75901",
    "sg:province":"TX",
    "sg:tags":[
        "doughnut"
    ],
    "wof:name":"Shipley Donuts",
    "wof:placetype":"venue"
},
  "geometry": {"coordinates":[-94.72288,31.330484],"type":"Point"}
}