{
  "type": "Feature",
  "properties": {
    "iso:country":"US",
    "sg:address":"200 Church St",
    "sg:city":"Sulphur Springs",
    "sg:classifiers":[
        {
            "category":"Banks & Credit Unions",
            "subcategory":"Investment Brokerage",
            "type":"Services"
        }
    ],
    "sg:phone":"+1 903 439 2259",
    "sg:postcode":"75482",
    "sg:province":"TX",
    "sg:tags":[
        "security"
    ],
    "wof:name":"B F Ashcroft",
    "wof:placetype":"venue"
},
  "geometry": {"coordinates":[-95.600793,33.139131],"type":"Point"}
}