{
  "type": "Feature",
  "properties": {
    "iso:country":"US",
    "sg:address":"6301 Winn Dr",
    "sg:city":"Fort Worth",
    "sg:classifiers":[
        {
            "category":"Professional",
            "subcategory":"Business Services",
            "type":"Services"
        }
    ],
    "sg:phone":"+1 817 551 5408",
    "sg:postcode":"76134",
    "sg:province":"TX",
    "wof:name":"Sumco Inc",
    "wof:placetype":"venue"
},
  "geometry": {"coordinates":[-97.34020700000001,32.653483],"type":"Point"}
}