{
  "type": "Feature",
  "properties": {
    "iso:country":"US",
    "sg:address":"620 Charles Ct",
    "sg:city":"Arlington",
    "sg:classifiers":[
        {
            "category":"Autos & Motor Vehicles",
            "subcategory":"Automobile Sales",
            "type":"Retail Goods"
        }
    ],
    "sg:phone":"+1 817 274 2009",
    "sg:postcode":"76013",
    "sg:province":"TX",
    "wof:name":"Discount Motors",
    "wof:placetype":"venue"
},
  "geometry": {"coordinates":[-97.13055199999999,32.728883],"type":"Point"}
}