{
  "type": "Feature",
  "properties": {
    "iso:country":"US",
    "sg:address":"6009 Bissonnet St Ste C",
    "sg:city":"Houston",
    "sg:classifiers":[
        {
            "category":"Autos & Motor Vehicles",
            "subcategory":"Automobile Sales",
            "type":"Retail Goods"
        },
        {
            "category":"Retail",
            "subcategory":"Auto Repair",
            "type":"Services"
        }
    ],
    "sg:phone":"+1 713 838 1111",
    "sg:postcode":"77081",
    "sg:province":"TX",
    "sg:tags":[
        "automotive"
    ],
    "wof:name":"Texas Auto Land",
    "wof:placetype":"venue"
},
  "geometry": {"coordinates":[-95.48690000000001,29.6978],"type":"Point"}
}