{
  "type": "Feature",
  "properties": {
    "iso:country":"US",
    "sg:address":"1009 W Rochelle Rd",
    "sg:city":"Irving",
    "sg:classifiers":[
        {
            "category":"Food & Beverages",
            "subcategory":"Farmers Market",
            "type":"Retail Goods"
        },
        {
            "category":"Food & Beverages",
            "subcategory":"Ethnic Foods",
            "type":"Retail Goods"
        },
        {
            "category":"Food & Beverages",
            "subcategory":"Groceries & Convenience Stores",
            "type":"Retail Goods"
        }
    ],
    "sg:phone":"+1 972 570 2504",
    "sg:postcode":"75062",
    "sg:province":"TX",
    "sg:website":"patelbrothersirving.com",
    "wof:name":"Patel Brothers",
    "wof:placetype":"venue"
},
  "geometry": {"coordinates":[-96.95585800000001,32.844272],"type":"Point"}
}