{
  "type": "Feature",
  "properties": {
    "iso:country":"US",
    "sg:address":"4575 Griggs Rd",
    "sg:city":"Houston",
    "sg:classifiers":[
        {
            "category":"Restaurant",
            "type":"Food & Drink"
        }
    ],
    "sg:phone":"+1 713 748 6498",
    "sg:postcode":"77021",
    "sg:province":"TX",
    "sg:tags":[
        "eating"
    ],
    "wof:name":"Church's Fried Chicken",
    "wof:placetype":"venue"
},
  "geometry": {"coordinates":[-95.345901,29.701099],"type":"Point"}
}