{
  "type": "Feature",
  "properties": {
    "iso:country":"US",
    "sg:address":"5634 Woodlark St",
    "sg:city":"Houston",
    "sg:classifiers":[
        {
            "category":"Retail",
            "subcategory":"Repair Shop",
            "type":"Services"
        }
    ],
    "sg:phone":"+1 713 645 5610",
    "sg:postcode":"77017",
    "sg:province":"TX",
    "sg:tags":[
        "television",
        "radio"
    ],
    "wof:name":"Alpha TV Svc",
    "wof:placetype":"venue"
},
  "geometry": {"coordinates":[-95.23442,29.689274],"type":"Point"}
}