{
  "type": "Feature",
  "properties": {
    "iso:country":"US",
    "sg:address":"2511 Wood River Dr",
    "sg:city":"Spring",
    "sg:classifiers":[
        {
            "category":"Wholesale",
            "subcategory":"Groceries",
            "type":"Manufacturing & Wholesale Goods"
        }
    ],
    "sg:phone":"+1 281 350 5337",
    "sg:postcode":"77373",
    "sg:province":"TX",
    "wof:name":"Special Lil Baskets",
    "wof:placetype":"venue"
},
  "geometry": {"coordinates":[-95.391081,30.045072],"type":"Point"}
}