{
  "type": "Feature",
  "properties": {
    "iso:country":"US",
    "sg:address":"200 E 1st St",
    "sg:city":"Bonham",
    "sg:classifiers":[
        {
            "category":"Government",
            "subcategory":"Office",
            "type":"Public Place"
        }
    ],
    "sg:phone":"+1 903 583 9513",
    "sg:postcode":"75418",
    "sg:province":"TX",
    "sg:tags":[
        "federal"
    ],
    "wof:name":"US Consolidated Farm Svc Agcy",
    "wof:placetype":"venue"
},
  "geometry": {"coordinates":[-96.176844,33.574087],"type":"Point"}
}