{
  "type": "Feature",
  "properties": {
    "iso:country":"US",
    "sg:address":"6650 Southwest Pkwy",
    "sg:city":"Wichita Falls",
    "sg:classifiers":[
        {
            "category":"Restaurant",
            "type":"Food & Drink"
        }
    ],
    "sg:phone":"+1 940 692 3758",
    "sg:postcode":"76310",
    "sg:province":"TX",
    "sg:tags":[
        "personal",
        "eating"
    ],
    "wof:name":"Zapatos",
    "wof:placetype":"venue"
},
  "geometry": {"coordinates":[-98.60243699999999,33.861429],"type":"Point"}
}