{
  "type": "Feature",
  "properties": {
    "iso:country":"US",
    "sg:address":"601 N Magnolia St",
    "sg:city":"Rockport",
    "sg:classifiers":[
        {
            "category":"Manufacturing",
            "subcategory":"Apparel",
            "type":"Manufacturing & Wholesale Goods"
        }
    ],
    "sg:phone":"+1 361 729 8575",
    "sg:postcode":"78382",
    "sg:province":"TX",
    "sg:tags":[
        "household",
        "furnishing",
        "mfg"
    ],
    "wof:name":"Pillows With Pizzazz",
    "wof:placetype":"venue"
},
  "geometry": {"coordinates":[-97.05146499999999,28.029127],"type":"Point"}
}