{
  "type": "Feature",
  "properties": {
    "iso:country":"US",
    "sg:address":"7422 Marigold Dr",
    "sg:city":"Irving",
    "sg:classifiers":[
        {
            "category":"Wholesale",
            "subcategory":"Non-durable Goods",
            "type":"Manufacturing & Wholesale Goods"
        }
    ],
    "sg:phone":"+1 214 574 4617",
    "sg:postcode":"75063",
    "sg:province":"TX",
    "sg:tags":[
        "wholesaler"
    ],
    "wof:name":"Jems By Letty",
    "wof:placetype":"venue"
},
  "geometry": {"coordinates":[-96.970269,32.907485],"type":"Point"}
}