{
  "type": "Feature",
  "properties": {
    "iso:country":"US",
    "sg:address":"831 Loganwood Ave",
    "sg:city":"Richardson",
    "sg:classifiers":[
        {
            "category":"Professional",
            "type":"Services"
        }
    ],
    "sg:phone":"+1 972 234 2920",
    "sg:postcode":"75080",
    "sg:province":"TX",
    "wof:name":"Carol L Corgill",
    "wof:placetype":"venue"
},
  "geometry": {"coordinates":[-96.750663,32.976081],"type":"Point"}
}