{
  "type": "Feature",
  "properties": {
    "iso:country":"US",
    "sg:address":"5150 de Zavala Rd",
    "sg:city":"San Antonio",
    "sg:classifiers":[
        {
            "category":"Education",
            "subcategory":"School",
            "type":"Public Place"
        }
    ],
    "sg:phone":"+1 210 561 5150",
    "sg:postcode":"78231",
    "sg:province":"TX",
    "sg:website":"www.nisd.net",
    "wof:name":"Tom C Clark High School",
    "wof:placetype":"venue"
},
  "geometry": {"coordinates":[-98.583483,29.565897],"type":"Point"}
}