{
  "type": "Feature",
  "properties": {
    "iso:country":"US",
    "sg:address":"3704 Billy Dr",
    "sg:city":"Victoria",
    "sg:classifiers":[
        {
            "category":"Wholesale",
            "subcategory":"Groceries",
            "type":"Manufacturing & Wholesale Goods"
        }
    ],
    "sg:phone":"+1 361 575 1721",
    "sg:postcode":"77901",
    "sg:province":"TX",
    "sg:tags":[
        "beverage"
    ],
    "wof:name":"7-Up-Rc-Big Red Of Victoria",
    "wof:placetype":"venue"
},
  "geometry": {"coordinates":[-97.006107,28.830137],"type":"Point"}
}