{
  "type": "Feature",
  "properties": {
    "iso:country":"US",
    "sg:address":"220 Blackbourn St",
    "sg:city":"Hawkins",
    "sg:classifiers":[
        {
            "category":"Organizations",
            "subcategory":"Religious Organization",
            "type":"Services"
        }
    ],
    "sg:phone":"+1 903 769 2973",
    "sg:postcode":"75765",
    "sg:province":"TX",
    "sg:tags":[
        "church"
    ],
    "wof:name":"First United Methodist Church",
    "wof:placetype":"venue"
},
  "geometry": {"coordinates":[-95.203844,32.588288],"type":"Point"}
}