{
  "type": "Feature",
  "properties": {
    "iso:country":"US",
    "sg:address":"10871 Pellicano Dr",
    "sg:city":"El Paso",
    "sg:classifiers":[
        {
            "category":"Wholesale",
            "subcategory":"Chemicals & Plastics",
            "type":"Manufacturing & Wholesale Goods"
        }
    ],
    "sg:phone":"+1 915 593 1373",
    "sg:postcode":"79935",
    "sg:province":"TX",
    "wof:name":"Regal Plastics Supply Co",
    "wof:placetype":"venue"
},
  "geometry": {"coordinates":[-106.332643,31.751939],"type":"Point"}
}