{
  "type": "Feature",
  "properties": {
    "iso:country":"US",
    "sg:address":"100 Probandt St",
    "sg:city":"San Antonio",
    "sg:classifiers":[
        {
            "category":"Wholesale",
            "subcategory":"Groceries",
            "type":"Manufacturing & Wholesale Goods"
        }
    ],
    "sg:phone":"+1 210 212 5727",
    "sg:postcode":"78204",
    "sg:province":"TX",
    "sg:tags":[
        "food",
        "broker"
    ],
    "wof:name":"LA Tuna-Food",
    "wof:placetype":"venue"
},
  "geometry": {"coordinates":[-98.49574200000001,29.407722],"type":"Point"}
}