{
  "type": "Feature",
  "properties": {
    "iso:country":"US",
    "sg:address":"1023 S Georgia St",
    "sg:city":"Amarillo",
    "sg:classifiers":[
        {
            "category":"Travel",
            "subcategory":"Travel Agent",
            "type":"Entertainment"
        },
        {
            "category":"Marine",
            "type":"Transportation"
        }
    ],
    "sg:phone":"+1 806 342 5110",
    "sg:postcode":"79102",
    "sg:province":"TX",
    "sg:tags":[
        "agency",
        "cruise"
    ],
    "sg:website":"http://www.amarilloconsolidatedtravel.com",
    "wof:name":"Amarillo Consolidated Travel",
    "wof:placetype":"venue"
},
  "geometry": {"coordinates":[-101.86627900000001,35.204664],"type":"Point"}
}