{
  "type": "Feature",
  "properties": {
    "iso:country":"US",
    "sg:address":"779 Normandy St",
    "sg:city":"Houston",
    "sg:classifiers":[
        {
            "category":"Real Estate",
            "subcategory":"Real Estate Services",
            "type":"Services"
        }
    ],
    "sg:phone":"+1 713 451 1733",
    "sg:postcode":"77015",
    "sg:province":"TX",
    "sg:tags":[
        "management",
        "property"
    ],
    "wof:name":"Remax of Texas Inc",
    "wof:placetype":"venue"
},
  "geometry": {"coordinates":[-95.205299,29.781401],"type":"Point"}
}