{
  "type": "Feature",
  "properties": {
    "iso:country":"US",
    "sg:address":"4967 Shady Oak Trl",
    "sg:city":"Grand Prairie",
    "sg:classifiers":[
        {
            "category":"Professional",
            "subcategory":"Management & Consulting",
            "type":"Services"
        }
    ],
    "sg:phone":"+1 972 641 0858",
    "sg:postcode":"75052",
    "sg:province":"TX",
    "sg:tags":[
        "eating"
    ],
    "wof:name":"McDonalds",
    "wof:placetype":"venue"
},
  "geometry": {"coordinates":[-97.054383,32.654281],"type":"Point"}
}