{
  "type": "Feature",
  "properties": {
    "iso:country":"US",
    "sg:address":"20719 Nettlebrook Ln",
    "sg:city":"Katy",
    "sg:classifiers":[
        {
            "category":"Wholesale",
            "subcategory":"Sporting Goods",
            "type":"Manufacturing & Wholesale Goods"
        }
    ],
    "sg:phone":"+1 281 647 0427",
    "sg:postcode":"77450",
    "sg:province":"TX",
    "wof:name":"Trailis Inc",
    "wof:placetype":"venue"
},
  "geometry": {"coordinates":[-95.74480800000001,29.706835],"type":"Point"}
}