{
  "type": "Feature",
  "properties": {
    "iso:country":"US",
    "sg:address":"103 N Goliad St",
    "sg:city":"Rockwall",
    "sg:classifiers":[
        {
            "category":"Building & Trades",
            "subcategory":"Electrical",
            "type":"Services"
        }
    ],
    "sg:phone":"+1 972 771 7655",
    "sg:postcode":"75087",
    "sg:province":"TX",
    "sg:tags":[
        "lighting",
        "landscape"
    ],
    "wof:name":"Calcon Lighting Co",
    "wof:placetype":"venue"
},
  "geometry": {"coordinates":[-96.46040000000001,32.93175],"type":"Point"}
}