{
  "type": "Feature",
  "properties": {
    "iso:country":"US",
    "sg:address":"4821 Columbia Ave",
    "sg:city":"Dallas",
    "sg:classifiers":[
        {
            "category":"Professional",
            "type":"Services"
        }
    ],
    "sg:phone":"+1 214 827 7936",
    "sg:postcode":"75226",
    "sg:province":"TX",
    "wof:name":"Beer To Go",
    "wof:placetype":"venue"
},
  "geometry": {"coordinates":[-96.763913,32.795088],"type":"Point"}
}