{
  "type": "Feature",
  "properties": {
    "iso:country":"US",
    "sg:address":"502 N Loop Fwy",
    "sg:city":"Houston",
    "sg:classifiers":[
        {
            "category":"Retail",
            "subcategory":"Auto Repair",
            "type":"Services"
        }
    ],
    "sg:phone":"+1 713 864 8134",
    "sg:postcode":"77008",
    "sg:province":"TX",
    "sg:tags":[
        "body",
        "automobile",
        "painting"
    ],
    "wof:name":"Carney's Corvette Ctr",
    "wof:placetype":"venue"
},
  "geometry": {"coordinates":[-95.39353800000001,29.814268],"type":"Point"}
}