{
  "type": "Feature",
  "properties": {
    "iso:country":"US",
    "sg:address":"3477 Forest Hills Cir",
    "sg:city":"Garland",
    "sg:classifiers":[
        {
            "category":"Manufacturing",
            "subcategory":"Printing",
            "type":"Manufacturing & Wholesale Goods"
        }
    ],
    "sg:phone":"+1 972 414 8796",
    "sg:postcode":"75044",
    "sg:province":"TX",
    "sg:tags":[
        "publishing"
    ],
    "wof:name":"Desktop Publishing",
    "wof:placetype":"venue"
},
  "geometry": {"coordinates":[-96.681439,32.983526],"type":"Point"}
}