{
  "type": "Feature",
  "properties": {
    "iso:country":"US",
    "sg:address":"311 Hedges St",
    "sg:city":"San Antonio",
    "sg:classifiers":[
        {
            "category":"Shopping",
            "subcategory":"Discount & Variety Stores",
            "type":"Retail Goods"
        }
    ],
    "sg:phone":"+1 210 227 2352",
    "sg:postcode":"78203",
    "sg:province":"TX",
    "sg:tags":[
        "merchandise",
        "general"
    ],
    "wof:name":"Knob Hill Auto Supply",
    "wof:placetype":"venue"
},
  "geometry": {"coordinates":[-98.45804200000001,29.417183],"type":"Point"}
}