{
  "type": "Feature",
  "properties": {
    "iso:country":"US",
    "sg:address":"1500 Greenville Ave",
    "sg:city":"Dallas",
    "sg:classifiers":[
        {
            "category":"Wholesale",
            "subcategory":"Computers",
            "type":"Manufacturing & Wholesale Goods"
        }
    ],
    "sg:phone":"+1 214 530 0200",
    "sg:postcode":"75206",
    "sg:province":"TX",
    "sg:tags":[
        "information",
        "retrieval"
    ],
    "sg:website":"www.ameriss.com",
    "wof:name":"Ameriss",
    "wof:placetype":"venue"
},
  "geometry": {"coordinates":[-96.77017499999999,32.808907],"type":"Point"}
}