{
  "type": "Feature",
  "properties": {
    "iso:country":"US",
    "sg:address":"11494 Moran Rd",
    "sg:city":"Azle",
    "sg:classifiers":[
        {
            "category":"Professional",
            "subcategory":"Management & Consulting",
            "type":"Services"
        }
    ],
    "sg:phone":"+1 817 444 4353",
    "sg:postcode":"76020",
    "sg:province":"TX",
    "wof:name":"US Beltway Management Inc",
    "wof:placetype":"venue"
},
  "geometry": {"coordinates":[-97.515947,32.936674],"type":"Point"}
}