{
  "type": "Feature",
  "properties": {
    "iso:country":"US",
    "sg:address":"4421 Gaines St",
    "sg:city":"Corpus Christi",
    "sg:classifiers":[
        {
            "category":"Building & Trades",
            "subcategory":"Cleaning & Sanitation",
            "type":"Services"
        }
    ],
    "sg:phone":"+1 361 991 2281",
    "sg:postcode":"78412",
    "sg:province":"TX",
    "sg:tags":[
        "maintenance"
    ],
    "wof:name":"Discount Maintenance",
    "wof:placetype":"venue"
},
  "geometry": {"coordinates":[-97.36575000000001,27.730788],"type":"Point"}
}