{
  "type": "Feature",
  "properties": {
    "iso:country":"US",
    "sg:address":"115 Martin St",
    "sg:city":"Hillsboro",
    "sg:classifiers":[
        {
            "category":"Professional",
            "subcategory":"Computer Services",
            "type":"Services"
        }
    ],
    "sg:phone":"+1 254 687 2331",
    "sg:postcode":"76645",
    "sg:province":"TX",
    "sg:tags":[
        "internet"
    ],
    "sg:website":"www.hilcozap.net",
    "wof:name":"HILCOZAP.NET",
    "wof:placetype":"venue"
},
  "geometry": {"coordinates":[-97.131404,32.004677],"type":"Point"}
}