{
  "type": "Feature",
  "properties": {
    "iso:country":"US",
    "sg:address":"313 W Tom Landry St",
    "sg:city":"Mission",
    "sg:classifiers":[
        {
            "category":"Banks & Credit Unions",
            "subcategory":"Bank",
            "type":"Services"
        }
    ],
    "sg:phone":"+1 956 581 7700",
    "sg:postcode":"78572",
    "sg:province":"TX",
    "sg:tags":[
        "personal",
        "loan",
        "institution"
    ],
    "wof:name":"R & R Loan Co Inc",
    "wof:placetype":"venue"
},
  "geometry": {"coordinates":[-98.328979,26.216459],"type":"Point"}
}