{
  "type": "Feature",
  "properties": {
    "iso:country":"US",
    "sg:address":"2435 Goodwin Ln",
    "sg:city":"New Braunfels",
    "sg:classifiers":[
        {
            "category":"Manufacturing",
            "subcategory":"Printing",
            "type":"Manufacturing & Wholesale Goods"
        }
    ],
    "sg:phone":"+1 830 609 5500",
    "sg:postcode":"78132",
    "sg:province":"TX",
    "sg:tags":[
        "check"
    ],
    "sg:website":"www.checksinthemail.com",
    "wof:name":"Checks In The Mail Inc",
    "wof:placetype":"venue"
},
  "geometry": {"coordinates":[-98.08419600000001,29.740271],"type":"Point"}
}