{
  "type": "Feature",
  "properties": {
    "iso:country":"US",
    "sg:address":"919 Congress Ave",
    "sg:city":"Austin",
    "sg:classifiers":[
        {
            "category":"Real Estate",
            "subcategory":"Real Estate Services",
            "type":"Services"
        }
    ],
    "sg:phone":"+1 512 476 0919",
    "sg:postcode":"78701",
    "sg:province":"TX",
    "sg:tags":[
        "management",
        "property"
    ],
    "wof:name":"Capitol Center Management Office",
    "wof:placetype":"venue"
},
  "geometry": {"coordinates":[-97.741699,30.271],"type":"Point"}
}