{
  "type": "Feature",
  "properties": {
    "iso:country":"US",
    "sg:address":"1215 E Ferguson Ave",
    "sg:city":"Pharr",
    "sg:classifiers":[
        {
            "category":"Cinema",
            "subcategory":"Movie Rental",
            "type":"Entertainment"
        }
    ],
    "sg:phone":"+1 956 702 9081",
    "sg:postcode":"78577",
    "sg:province":"TX",
    "sg:tags":[
        "video",
        "tape"
    ],
    "wof:name":"High Impact Video",
    "wof:placetype":"venue"
},
  "geometry": {"coordinates":[-98.16761200000001,26.209928],"type":"Point"}
}