{
  "type": "Feature",
  "properties": {
    "iso:country":"US",
    "sg:address":"612 W Marshall Ave",
    "sg:city":"Longview",
    "sg:classifiers":[
        {
            "category":"Shopping",
            "subcategory":"Tobacco",
            "type":"Retail Goods"
        }
    ],
    "sg:phone":"+1 903 236 9905",
    "sg:postcode":"75601",
    "sg:province":"TX",
    "sg:tags":[
        "product",
        "clothing"
    ],
    "wof:name":"R & R Tobacco",
    "wof:placetype":"venue"
},
  "geometry": {"coordinates":[-94.750945,32.49899],"type":"Point"}
}