{
  "type": "Feature",
  "properties": {
    "iso:country":"US",
    "sg:address":"214 W Pierce Ave",
    "sg:city":"Harlingen",
    "sg:classifiers":[
        {
            "category":"Shopping",
            "subcategory":"Jewelry",
            "type":"Retail Goods"
        }
    ],
    "sg:phone":"+1 956 425 9600",
    "sg:postcode":"78550",
    "sg:province":"TX",
    "sg:tags":[
        "jeweler"
    ],
    "wof:name":"Margarita Alexander Jewelry",
    "wof:placetype":"venue"
},
  "geometry": {"coordinates":[-97.69762900000001,26.18548],"type":"Point"}
}