{
  "type": "Feature",
  "properties": {
    "iso:country":"US",
    "sg:address":"3815 S Cooper St",
    "sg:city":"Arlington",
    "sg:classifiers":[
        {
            "category":"Personal",
            "subcategory":"Beauty Salon",
            "type":"Services"
        }
    ],
    "sg:phone":"+1 817 375 8160",
    "sg:postcode":"76015",
    "sg:province":"TX",
    "sg:tags":[
        "shop"
    ],
    "wof:name":"Nails Now",
    "wof:placetype":"venue"
},
  "geometry": {"coordinates":[-97.13324799999999,32.682817],"type":"Point"}
}