{
  "type": "Feature",
  "properties": {
    "iso:country":"US",
    "sg:address":"2701 Dowling St",
    "sg:city":"Houston",
    "sg:classifiers":[
        {
            "category":"Shopping",
            "subcategory":"Clothing, Apparel, & Fashions",
            "type":"Retail Goods"
        },
        {
            "category":"Shopping",
            "subcategory":"Department Store",
            "type":"Retail Goods"
        },
        {
            "category":"Shopping",
            "subcategory":"Jewelry",
            "type":"Retail Goods"
        },
        {
            "category":"Shopping",
            "subcategory":"Shoes",
            "type":"Retail Goods"
        }
    ],
    "sg:phone":"+1 713 659 7656",
    "sg:postcode":"77004",
    "sg:province":"TX",
    "sg:tags":[
        "shop",
        "clothing",
        "men's",
        "hat",
        "jeweler"
    ],
    "sg:website":"http://www.wolfsdepartmentstoreandpawn.com",
    "wof:name":"Wolf's Department Store & Pawn",
    "wof:placetype":"venue"
},
  "geometry": {"coordinates":[-95.362801,29.737301],"type":"Point"}
}