{
  "type": "Feature",
  "properties": {
    "iso:country":"US",
    "sg:address":"9429 Co Rd 3910",
    "sg:city":"Athens",
    "sg:classifiers":[
        {
            "category":"Professional",
            "type":"Services"
        }
    ],
    "sg:phone":"+1 903 675 2224",
    "sg:postcode":"75752",
    "sg:province":"TX",
    "wof:name":"Jack D Reppond",
    "wof:placetype":"venue"
},
  "geometry": {"coordinates":[-95.85714900000001,32.280034],"type":"Point"}
}