{
  "type": "Feature",
  "properties": {
    "iso:country":"US",
    "sg:address":"717 Crestbrook Ln",
    "sg:city":"Grand Prairie",
    "sg:classifiers":[
        {
            "category":"Shopping",
            "subcategory":"Gifts & Souvenirs",
            "type":"Retail Goods"
        }
    ],
    "sg:phone":"+1 972 237 7761",
    "sg:postcode":"75052",
    "sg:province":"TX",
    "wof:name":"Tootsie Gifts",
    "wof:placetype":"venue"
},
  "geometry": {"coordinates":[-97.0147,32.708057],"type":"Point"}
}