{
  "type": "Feature",
  "properties": {
    "iso:country":"US",
    "sg:address":"705 Aquarena Springs Dr",
    "sg:city":"San Marcos",
    "sg:classifiers":[
        {
            "category":"Food & Beverages",
            "subcategory":"Groceries & Convenience Stores",
            "type":"Retail Goods"
        }
    ],
    "sg:phone":"+1 512 396 4819",
    "sg:postcode":"78666",
    "sg:province":"TX",
    "wof:name":"Korner Stop Food Mart",
    "wof:placetype":"venue"
},
  "geometry": {"coordinates":[-97.93208799999999,29.889477],"type":"Point"}
}