{
  "type": "Feature",
  "properties": {
    "iso:country":"US",
    "sg:address":"2310 W Main St",
    "sg:city":"League City",
    "sg:classifiers":[
        {
            "category":"Retail",
            "subcategory":"Veterinary Services",
            "type":"Services"
        }
    ],
    "sg:phone":"+1 281 332 0644",
    "sg:postcode":"77573",
    "sg:province":"TX",
    "sg:tags":[
        "clinic"
    ],
    "wof:name":"League City Animal Clinic",
    "wof:placetype":"venue"
},
  "geometry": {"coordinates":[-95.123864,29.500819],"type":"Point"}
}