{
  "type": "Feature",
  "properties": {
    "iso:country":"US",
    "sg:address":"100 W Live Oak St",
    "sg:city":"Coleman",
    "sg:classifiers":[
        {
            "category":"Government",
            "subcategory":"Office",
            "type":"Public Place"
        }
    ],
    "sg:phone":"+1 325 625 2208",
    "sg:postcode":"76834",
    "sg:province":"TX",
    "sg:tags":[
        "state"
    ],
    "wof:name":"Parks & Wildlife Dept",
    "wof:placetype":"venue"
},
  "geometry": {"coordinates":[-99.423571,31.830968],"type":"Point"}
}