{
  "type": "Feature",
  "properties": {
    "iso:country":"US",
    "sg:address":"14440 Wallisville Rd",
    "sg:city":"Houston",
    "sg:classifiers":[
        {
            "category":"Recreation",
            "type":"Entertainment"
        }
    ],
    "sg:phone":"+1 713 455 9090",
    "sg:postcode":"77049",
    "sg:province":"TX",
    "sg:tags":[
        "club",
        "baseball"
    ],
    "wof:name":"North Channel Little League",
    "wof:placetype":"venue"
},
  "geometry": {"coordinates":[-95.191462,29.80599],"type":"Point"}
}