{
  "type": "Feature",
  "properties": {
    "iso:country":"US",
    "sg:address":"4350 Trinity Mills Rd",
    "sg:city":"Dallas",
    "sg:classifiers":[
        {
            "category":"Health Services",
            "subcategory":"Clinic",
            "type":"Services"
        }
    ],
    "sg:phone":"+1 972 818 2264",
    "sg:postcode":"75287",
    "sg:province":"TX",
    "wof:name":"Complete Nutritional Health",
    "wof:placetype":"venue"
},
  "geometry": {"coordinates":[-96.835469,32.988481],"type":"Point"}
}