{
  "type": "Feature",
  "properties": {
    "iso:country":"US",
    "sg:address":"445 N Cavender St",
    "sg:city":"Dallas",
    "sg:classifiers":[
        {
            "category":"Autos & Motor Vehicles",
            "subcategory":"Automobile Sales",
            "type":"Retail Goods"
        }
    ],
    "sg:phone":"+1 214 426 1111",
    "sg:postcode":"75211",
    "sg:province":"TX",
    "sg:tags":[
        "limo"
    ],
    "wof:name":"Texas Limousines Inc",
    "wof:placetype":"venue"
},
  "geometry": {"coordinates":[-96.86516,32.748786],"type":"Point"}
}