{
  "type": "Feature",
  "properties": {
    "iso:country":"US",
    "sg:address":"4100 Frawley Dr",
    "sg:city":"Fort Worth",
    "sg:classifiers":[
        {
            "category":"Professional",
            "type":"Services"
        }
    ],
    "sg:phone":"+1 817 589 7111",
    "sg:postcode":"76180",
    "sg:province":"TX",
    "wof:name":"L C Nhicc",
    "wof:placetype":"venue"
},
  "geometry": {"coordinates":[-97.216972,32.826215],"type":"Point"}
}