{
  "type": "Feature",
  "properties": {
    "iso:country":"US",
    "sg:address":"624 E Lehigh St",
    "sg:city":"Lubbock",
    "sg:classifiers":[
        {
            "category":"Manufacturing",
            "subcategory":"Metals",
            "type":"Manufacturing & Wholesale Goods"
        }
    ],
    "sg:phone":"+1 806 765 0203",
    "sg:postcode":"79403",
    "sg:province":"TX",
    "sg:tags":[
        "product",
        "formed",
        "coating",
        "powder",
        "custom"
    ],
    "sg:website":"www.qualitycoatingcompany.com",
    "wof:name":"Quality Coatings",
    "wof:placetype":"venue"
},
  "geometry": {"coordinates":[-101.83215199999999,33.613752],"type":"Point"}
}