{
  "type": "Feature",
  "properties": {
    "iso:country":"US",
    "sg:address":"8031 Danette Ct",
    "sg:city":"Spring",
    "sg:classifiers":[
        {
            "category":"Shopping",
            "subcategory":"Gifts & Souvenirs",
            "type":"Retail Goods"
        }
    ],
    "sg:phone":"+1 281 251 2553",
    "sg:postcode":"77379",
    "sg:province":"TX",
    "wof:name":"Sjolin S Baseball Cards",
    "wof:placetype":"venue"
},
  "geometry": {"coordinates":[-95.547828,30.03186],"type":"Point"}
}