{
  "type": "Feature",
  "properties": {
    "iso:country":"US",
    "sg:address":"2904 Pine Forrest St",
    "sg:city":"La Marque",
    "sg:classifiers":[
        {
            "category":"Education",
            "subcategory":"School",
            "type":"Public Place"
        }
    ],
    "sg:phone":"+1 409 762 6525",
    "sg:postcode":"77568",
    "sg:province":"TX",
    "wof:name":"Heritage Christian Academy",
    "wof:placetype":"venue"
},
  "geometry": {"coordinates":[-94.987956,29.354707],"type":"Point"}
}