{
  "type": "Feature",
  "properties": {
    "iso:country":"US",
    "sg:address":"840 Belt Line Rd",
    "sg:city":"Garland",
    "sg:classifiers":[
        {
            "category":"Banks & Credit Unions",
            "subcategory":"Investment Brokerage",
            "type":"Services"
        },
        {
            "category":"Banks & Credit Unions",
            "subcategory":"Bank",
            "type":"Services"
        },
        {
            "category":"Banks & Credit Unions",
            "subcategory":"Financial Services",
            "type":"Services"
        }
    ],
    "sg:phone":"+1 972 530 2466",
    "sg:postcode":"75040",
    "sg:province":"TX",
    "sg:tags":[
        "mutual",
        "retirement",
        "broker",
        "fund",
        "planning",
        "security",
        "bond",
        "stock"
    ],
    "sg:website":"http://www.edwardjones.com/en_US/fa/index.html&CIRN=311596",
    "wof:name":"Edward Jones - Financial Advisor: TONY CAUFIELD",
    "wof:placetype":"venue"
},
  "geometry": {"coordinates":[-96.63931700000001,32.940096],"type":"Point"}
}