{
  "type": "Feature",
  "properties": {
    "iso:country":"US",
    "sg:address":"5925 Kirby Dr Ste 206",
    "sg:city":"Houston",
    "sg:classifiers":[
        {
            "category":"Professional",
            "subcategory":"Accounting & Tax Preparation",
            "type":"Services"
        }
    ],
    "sg:phone":"+1 713 522 4980",
    "sg:postcode":"77005",
    "sg:province":"TX",
    "sg:tags":[
        "accountant"
    ],
    "wof:name":"Wallack Joseph S CPA",
    "wof:placetype":"venue"
},
  "geometry": {"coordinates":[-95.418404,29.7192],"type":"Point"}
}