{
  "type": "Feature",
  "properties": {
    "iso:country":"US",
    "sg:address":"3505 Longmire Dr",
    "sg:city":"College Station",
    "sg:classifiers":[
        {
            "category":"Retail",
            "subcategory":"Laundry & Dry Cleaning",
            "type":"Services"
        }
    ],
    "sg:phone":"+1 979 695 0993",
    "sg:postcode":"77845",
    "sg:province":"TX",
    "sg:tags":[
        "cleaners",
        "plant",
        "drycleaning"
    ],
    "wof:name":"Fabric Care Cleaners",
    "wof:placetype":"venue"
},
  "geometry": {"coordinates":[-96.28630699999999,30.580886],"type":"Point"}
}