{
  "type": "Feature",
  "properties": {
    "iso:country":"US",
    "sg:address":"108 N Main St",
    "sg:city":"Caldwell",
    "sg:classifiers":[
        {
            "category":"Professional",
            "subcategory":"Accounting & Tax Preparation",
            "type":"Services"
        }
    ],
    "sg:phone":"+1 979 567 4974",
    "sg:postcode":"77836",
    "sg:province":"TX",
    "sg:tags":[
        "accountant"
    ],
    "wof:name":"Guy E Huffman CPA",
    "wof:placetype":"venue"
},
  "geometry": {"coordinates":[-96.693961,30.533459],"type":"Point"}
}