{
  "type": "Feature",
  "properties": {
    "iso:country":"US",
    "sg:address":"822 S Commerce St",
    "sg:city":"Kilgore",
    "sg:classifiers":[
        {
            "category":"Manufacturing",
            "subcategory":"Tools & Machinery",
            "type":"Manufacturing & Wholesale Goods"
        },
        {
            "category":"Building & Trades",
            "subcategory":"Equipment Rental",
            "type":"Services"
        }
    ],
    "sg:phone":"+1 903 983 2019",
    "sg:postcode":"75662",
    "sg:province":"TX",
    "sg:tags":[
        "hydraulic",
        "supply"
    ],
    "sg:website":"http://www.dxpe.com",
    "wof:name":"Dxp Enterprises, Inc.",
    "wof:placetype":"venue"
},
  "geometry": {"coordinates":[-94.880762,32.382709],"type":"Point"}
}