{
  "type": "Feature",
  "properties": {
    "iso:country":"US",
    "sg:address":"4739 Oak Club Dr",
    "sg:city":"Arlington",
    "sg:classifiers":[
        {
            "category":"Professional",
            "subcategory":"Advertising",
            "type":"Services"
        }
    ],
    "sg:phone":"+1 817 784 8882",
    "sg:postcode":"76017",
    "sg:province":"TX",
    "sg:tags":[
        "promotion",
        "sale"
    ],
    "sg:website":"http://www.distributorcentral.com/websites/OakLakePromotions/",
    "wof:name":"Oak Lake Promotions",
    "wof:placetype":"venue"
},
  "geometry": {"coordinates":[-97.157213,32.668861],"type":"Point"}
}