{
  "type": "Feature",
  "properties": {
    "iso:country":"US",
    "sg:address":"7619 Bantry Cir",
    "sg:city":"Dallas",
    "sg:classifiers":[
        {
            "category":"Arts & Performance",
            "subcategory":"Music",
            "type":"Entertainment"
        }
    ],
    "sg:phone":"+1 972 407 9220",
    "sg:postcode":"75248",
    "sg:province":"TX",
    "sg:tags":[
        "band",
        "orchestra"
    ],
    "wof:name":"Richardson Area Orchestra Club",
    "wof:placetype":"venue"
},
  "geometry": {"coordinates":[-96.776642,32.985737],"type":"Point"}
}