{
  "type": "Feature",
  "properties": {
    "iso:country":"US",
    "sg:address":"4003 Cynthia Ln",
    "sg:city":"Wichita Falls",
    "sg:classifiers":[
        {
            "category":"Personal",
            "subcategory":"Beauty Salon",
            "type":"Services"
        }
    ],
    "sg:phone":"+1 940 766 5916",
    "sg:postcode":"76302",
    "sg:province":"TX",
    "sg:tags":[
        "shop"
    ],
    "wof:name":"Hair Appliance Co",
    "wof:placetype":"venue"
},
  "geometry": {"coordinates":[-98.490584,33.87309],"type":"Point"}
}