{
  "type": "Feature",
  "properties": {
    "iso:country":"US",
    "sg:address":"1320 N 11th St",
    "sg:city":"Beaumont",
    "sg:classifiers":[
        {
            "category":"Food & Beverages",
            "subcategory":"Groceries & Convenience Stores",
            "type":"Retail Goods"
        }
    ],
    "sg:phone":"+1 409 898 4220",
    "sg:postcode":"77702",
    "sg:province":"TX",
    "wof:name":"Food Spot",
    "wof:placetype":"venue"
},
  "geometry": {"coordinates":[-94.129931,30.094342],"type":"Point"}
}