{
  "type": "Feature",
  "properties": {
    "iso:country":"US",
    "sg:address":"2610 Sweetgum Ln",
    "sg:city":"Beaumont",
    "sg:classifiers":[
        {
            "category":"Organizations",
            "subcategory":"Membership Organization",
            "type":"Services"
        }
    ],
    "sg:phone":"+1 409 899 8991",
    "sg:postcode":"77703",
    "sg:province":"TX",
    "sg:tags":[
        "sorority",
        "fraternity"
    ],
    "wof:name":"El Mina Shrine Nobles",
    "wof:placetype":"venue"
},
  "geometry": {"coordinates":[-94.12829499999999,30.097618],"type":"Point"}
}