{
  "type": "Feature",
  "properties": {
    "iso:country":"US",
    "sg:address":"4316 Main St",
    "sg:city":"Lewisville",
    "sg:classifiers":[
        {
            "category":"Professional",
            "subcategory":"Business Services",
            "type":"Services"
        }
    ],
    "sg:phone":"+1 972 567 6870",
    "sg:postcode":"75056",
    "sg:province":"TX",
    "wof:name":"Manuels Pool Service Inc",
    "wof:placetype":"venue"
},
  "geometry": {"coordinates":[-96.892482,33.07428],"type":"Point"}
}