{
  "type": "Feature",
  "properties": {
    "iso:country":"US",
    "sg:address":"984 E Main St",
    "sg:city":"Lewisville",
    "sg:classifiers":[
        {
            "category":"Manufacturing",
            "subcategory":"Tools & Machinery",
            "type":"Manufacturing & Wholesale Goods"
        }
    ],
    "sg:phone":"+1 972 436 9781",
    "sg:postcode":"75057",
    "sg:province":"TX",
    "sg:tags":[
        "fasteners-industrial"
    ],
    "sg:website":"http://www.ancofastener.com",
    "wof:name":"Anco Fastener Manufacturing, Inc.",
    "wof:placetype":"venue"
},
  "geometry": {"coordinates":[-96.97677899999999,33.039781],"type":"Point"}
}