{
  "type": "Feature",
  "properties": {
    "iso:country":"US",
    "sg:address":"7548 Preston Rd",
    "sg:city":"Frisco",
    "sg:classifiers":[
        {
            "category":"Food & Beverages",
            "subcategory":"Specialty",
            "type":"Retail Goods"
        }
    ],
    "sg:phone":"+1 972 377 0401",
    "sg:postcode":"75034",
    "sg:province":"TX",
    "sg:tags":[
        "vitamin",
        "store"
    ],
    "wof:name":"GNC",
    "wof:placetype":"venue"
},
  "geometry": {"coordinates":[-96.804354,33.139156],"type":"Point"}
}