{
  "type": "Feature",
  "properties": {
    "iso:country":"US",
    "sg:address":"1311 S Marsalis Ave",
    "sg:city":"Dallas",
    "sg:classifiers":[
        {
            "category":"Autos & Motor Vehicles",
            "subcategory":"Automobile Sales",
            "type":"Retail Goods"
        }
    ],
    "sg:phone":"+1 214 946 2673",
    "sg:postcode":"75216",
    "sg:province":"TX",
    "sg:tags":[
        "used"
    ],
    "wof:name":"Acosta Auto Sales",
    "wof:placetype":"venue"
},
  "geometry": {"coordinates":[-96.814537,32.731506],"type":"Point"}
}