{
  "type": "Feature",
  "properties": {
    "iso:country":"US",
    "sg:address":"5068 W Plano Pkwy",
    "sg:city":"Plano",
    "sg:classifiers":[
        {
            "category":"Shopping",
            "subcategory":"Florist",
            "type":"Retail Goods"
        }
    ],
    "sg:phone":"+1 972 680 8582",
    "sg:postcode":"75093",
    "sg:province":"TX",
    "wof:name":"Elegant Custom Florals",
    "wof:placetype":"venue"
},
  "geometry": {"coordinates":[-96.79901599999999,33.016326],"type":"Point"}
}