{
  "type": "Feature",
  "properties": {
    "iso:country":"US",
    "sg:address":"6403 Hillcroft St",
    "sg:city":"Houston",
    "sg:classifiers":[
        {
            "category":"Retail",
            "subcategory":"Laundry & Dry Cleaning",
            "type":"Services"
        }
    ],
    "sg:phone":"+1 713 981 5776",
    "sg:postcode":"77081",
    "sg:province":"TX",
    "sg:tags":[
        "drycleaning"
    ],
    "wof:name":"Super 1 Hour Cleaners",
    "wof:placetype":"venue"
},
  "geometry": {"coordinates":[-95.4944,29.712999],"type":"Point"}
}