{
  "type": "Feature",
  "properties": {
    "iso:country":"US",
    "sg:address":"851 S Bell Blvd",
    "sg:city":"Cedar Park",
    "sg:classifiers":[
        {
            "category":"Shopping",
            "subcategory":"Pharmacy",
            "type":"Retail Goods"
        }
    ],
    "sg:phone":"+1 512 219 9232",
    "sg:postcode":"78613",
    "sg:province":"TX",
    "sg:tags":[
        "drugstore"
    ],
    "sg:website":"www.cvs.com",
    "wof:name":"CVS pharmacy",
    "wof:placetype":"venue"
},
  "geometry": {"coordinates":[-97.817213,30.501601],"type":"Point"}
}