{
  "type": "Feature",
  "properties": {
    "iso:country":"US",
    "sg:address":"2921 W Camp Wisdom Rd",
    "sg:city":"Dallas",
    "sg:classifiers":[
        {
            "category":"Personal",
            "subcategory":"Barber",
            "type":"Services"
        }
    ],
    "sg:phone":"+1 214 331 6900",
    "sg:postcode":"75237",
    "sg:province":"TX",
    "wof:name":"Pick Your Cut",
    "wof:placetype":"venue"
},
  "geometry": {"coordinates":[-96.867582,32.662137],"type":"Point"}
}