{
  "type": "Feature",
  "properties": {
    "iso:country":"US",
    "sg:address":"2404 Yellowhammer Ave",
    "sg:city":"Mcallen",
    "sg:classifiers":[
        {
            "category":"Shopping",
            "subcategory":"Catalog Store",
            "type":"Retail Goods"
        }
    ],
    "sg:phone":"+1 956 971 0288",
    "sg:postcode":"78504",
    "sg:province":"TX",
    "sg:tags":[
        "house",
        "mail"
    ],
    "wof:name":"Halfling Harmonies",
    "wof:placetype":"venue"
},
  "geometry": {"coordinates":[-98.235187,26.27494],"type":"Point"}
}