{
  "type": "Feature",
  "properties": {
    "iso:country":"US",
    "sg:address":"2222 Co Rd 7130",
    "sg:city":"Lubbock",
    "sg:classifiers":[
        {
            "category":"Education",
            "subcategory":"Special Training",
            "type":"Public Place"
        }
    ],
    "sg:phone":"+1 806 745 6018",
    "sg:postcode":"79404",
    "sg:province":"TX",
    "sg:tags":[
        "school",
        "instruction",
        "art"
    ],
    "wof:name":"School Of Art",
    "wof:placetype":"venue"
},
  "geometry": {"coordinates":[-101.814013,33.514154],"type":"Point"}
}