{
  "type": "Feature",
  "properties": {
    "iso:country":"US",
    "sg:address":"9361 Co Rd 2301",
    "sg:city":"Tyler",
    "sg:classifiers":[
        {
            "category":"Building & Trades",
            "subcategory":"Plumbing",
            "type":"Services"
        }
    ],
    "sg:phone":"+1 903 566 1660",
    "sg:postcode":"75750",
    "sg:province":"TX",
    "sg:tags":[
        "tank",
        "septic"
    ],
    "wof:name":"L & M Septic Svc",
    "wof:placetype":"venue"
},
  "geometry": {"coordinates":[-95.13554999999999,32.328262],"type":"Point"}
}