{
  "type": "Feature",
  "properties": {
    "iso:country":"US",
    "sg:address":"5413 Woodview Ave",
    "sg:city":"Austin",
    "sg:classifiers":[
        {
            "category":"Shopping",
            "subcategory":"Used Merchandise",
            "type":"Retail Goods"
        }
    ],
    "sg:phone":"+1 512 289 2392",
    "sg:postcode":"78756",
    "sg:province":"TX",
    "wof:name":"Radio Ranch",
    "wof:placetype":"venue"
},
  "geometry": {"coordinates":[-97.744176,30.329758],"type":"Point"}
}