{
  "type": "Feature",
  "properties": {
    "iso:country":"US",
    "sg:address":"9347 Viscaro Ln",
    "sg:city":"Humble",
    "sg:classifiers":[
        {
            "category":"Freight",
            "type":"Transportation"
        }
    ],
    "sg:phone":"+1 281 441 4640",
    "sg:postcode":"77396",
    "sg:province":"TX",
    "wof:name":"K & G Crating",
    "wof:placetype":"venue"
},
  "geometry": {"coordinates":[-95.253378,29.946971],"type":"Point"}
}