{
  "type": "Feature",
  "properties": {
    "iso:country":"US",
    "sg:address":"444 Cypresswood Dr",
    "sg:city":"Spring",
    "sg:classifiers":[
        {
            "category":"Restaurant",
            "type":"Food & Drink"
        }
    ],
    "sg:menulink":"http://www.allmenus.com/tx/northwest-harris/218102-burger-king/menu/",
    "sg:phone":"+1 281 350 3359",
    "sg:postcode":"77388",
    "sg:province":"TX",
    "sg:tags":[
        "american"
    ],
    "wof:name":"Burger King",
    "wof:placetype":"venue"
},
  "geometry": {"coordinates":[-95.439347,30.048775],"type":"Point"}
}