{
  "type": "Feature",
  "properties": {
    "iso:country":"US",
    "sg:address":"4414 W Fuqua St",
    "sg:city":"Houston",
    "sg:classifiers":[
        {
            "category":"Food & Beverages",
            "subcategory":"Groceries & Convenience Stores",
            "type":"Retail Goods"
        }
    ],
    "sg:phone":"+1 713 433 9637",
    "sg:postcode":"77045",
    "sg:province":"TX",
    "wof:name":"Come N Go Market",
    "wof:placetype":"venue"
},
  "geometry": {"coordinates":[-95.44360399999999,29.613501],"type":"Point"}
}