{
  "type": "Feature",
  "properties": {
    "iso:country":"US",
    "sg:address":"1214 12th St",
    "sg:city":"Huntsville",
    "sg:classifiers":[
        {
            "category":"Social Services",
            "type":"Services"
        }
    ],
    "sg:phone":"+1 936 291 3376",
    "sg:postcode":"77340",
    "sg:province":"TX",
    "sg:tags":[
        "residential",
        "sp",
        "care"
    ],
    "wof:name":"Alcoholics Anonymous",
    "wof:placetype":"venue"
},
  "geometry": {"coordinates":[-95.55269699999999,30.723047],"type":"Point"}
}