{
  "type": "Feature",
  "properties": {
    "iso:country":"US",
    "sg:address":"1604 Crestmont Ave",
    "sg:city":"Corsicana",
    "sg:classifiers":[
        {
            "category":"Wholesale",
            "subcategory":"Durable Goods & Equipment",
            "type":"Manufacturing & Wholesale Goods"
        }
    ],
    "sg:phone":"+1 903 780 5086",
    "sg:postcode":"75110",
    "sg:province":"TX",
    "wof:name":"Texas Dynamics Inc",
    "wof:placetype":"venue"
},
  "geometry": {"coordinates":[-96.49144699999999,32.102494],"type":"Point"}
}