{
  "type": "Feature",
  "properties": {
    "iso:country":"US",
    "sg:address":"1054 Springdale Rd Bldg L",
    "sg:city":"Austin",
    "sg:phone":"+1 512 928 8588",
    "sg:postcode":"78721",
    "sg:province":"TX",
    "sg:website":"http://www.amazingdiscoverychildcare.com",
    "wof:name":"Amazing Discovery Childcare",
    "wof:placetype":"venue"
},
  "geometry": {"coordinates":[-97.691879,30.27132],"type":"Point"}
}