{
  "type": "Feature",
  "properties": {
    "iso:country":"US",
    "sg:address":"10412 Lippitt Ave",
    "sg:city":"Dallas",
    "sg:classifiers":[
        {
            "category":"Wholesale",
            "subcategory":"Hardware",
            "type":"Manufacturing & Wholesale Goods"
        }
    ],
    "sg:phone":"+1 214 327 1224",
    "sg:postcode":"75218",
    "sg:province":"TX",
    "sg:tags":[
        "plumbing",
        "merchandise",
        "w"
    ],
    "wof:name":"Lake Plaza Supply",
    "wof:placetype":"venue"
},
  "geometry": {"coordinates":[-96.701177,32.851897],"type":"Point"}
}