{
  "type": "Feature",
  "properties": {
    "iso:country":"US",
    "sg:address":"801 Austin Ave",
    "sg:city":"Alamo",
    "sg:classifiers":[
        {
            "category":"Retail",
            "subcategory":"Repair Shop",
            "type":"Services"
        }
    ],
    "sg:phone":"+1 956 781 5945",
    "sg:postcode":"78516",
    "sg:province":"TX",
    "sg:tags":[
        "equipment"
    ],
    "wof:name":"Alamo Lock & Key",
    "wof:placetype":"venue"
},
  "geometry": {"coordinates":[-98.11954,26.181286],"type":"Point"}
}