{
  "type": "Feature",
  "properties": {
    "iso:country":"US",
    "sg:address":"3422 Water's Edge Dr",
    "sg:city":"Sugar Land",
    "sg:classifiers":[
        {
            "category":"Professional",
            "subcategory":"Computer Services",
            "type":"Services"
        }
    ],
    "sg:phone":"+1 281 565 8651",
    "sg:postcode":"77478",
    "sg:province":"TX",
    "sg:tags":[
        "information",
        "retrieval"
    ],
    "wof:name":"Www Cpebankcom Network LLC",
    "wof:placetype":"venue"
},
  "geometry": {"coordinates":[-95.595562,29.595207],"type":"Point"}
}