{
  "type": "Feature",
  "properties": {
    "iso:country":"US",
    "sg:address":"1273 N Main St",
    "sg:city":"Vidor",
    "sg:classifiers":[
        {
            "category":"Health Services",
            "subcategory":"Doctor",
            "type":"Services"
        }
    ],
    "sg:phone":"+1 409 769 3046",
    "sg:postcode":"77662",
    "sg:province":"TX",
    "sg:tags":[
        "dentist"
    ],
    "wof:name":"Darrell C Perkins Inc",
    "wof:placetype":"venue"
},
  "geometry": {"coordinates":[-94.015852,30.14209],"type":"Point"}
}