{
  "type": "Feature",
  "properties": {
    "iso:country":"US",
    "sg:address":"104 S Houston St",
    "sg:city":"Grand Saline",
    "sg:classifiers":[
        {
            "category":"Government",
            "subcategory":"Office",
            "type":"Public Place"
        }
    ],
    "sg:phone":"+1 903 962 3773",
    "sg:postcode":"75140",
    "sg:province":"TX",
    "sg:tags":[
        "village"
    ],
    "wof:name":"Grand Saline Nutrition Ctr",
    "wof:placetype":"venue"
},
  "geometry": {"coordinates":[-95.71559600000001,32.672138],"type":"Point"}
}