{
  "type": "Feature",
  "properties": {
    "iso:country":"US",
    "sg:address":"630 S 19th St",
    "sg:city":"Slaton",
    "sg:classifiers":[
        {
            "category":"Health Services",
            "subcategory":"Nursing And Care Facility",
            "type":"Services"
        }
    ],
    "sg:phone":"+1 806 828 6268",
    "sg:postcode":"79364",
    "sg:province":"TX",
    "sg:tags":[
        "home",
        "convalescent"
    ],
    "wof:name":"Slaton Care Center",
    "wof:placetype":"venue"
},
  "geometry": {"coordinates":[-101.655475,33.433714],"type":"Point"}
}