{
  "type": "Feature",
  "properties": {
    "iso:country":"US",
    "sg:address":"16735 Rockbend St",
    "sg:city":"Houston",
    "sg:classifiers":[
        {
            "category":"Shopping",
            "type":"Retail Goods"
        }
    ],
    "sg:phone":"+1 281 856 0597",
    "sg:postcode":"77084",
    "sg:province":"TX",
    "sg:tags":[
        "merchandise"
    ],
    "wof:name":"Cylinders Unlimited",
    "wof:placetype":"venue"
},
  "geometry": {"coordinates":[-95.663127,29.877126],"type":"Point"}
}