{
  "type": "Feature",
  "properties": {
    "iso:country":"US",
    "sg:address":"11420 Ferrell Dr",
    "sg:city":"Dallas",
    "sg:classifiers":[
        {
            "category":"Wholesale",
            "subcategory":"Machinery & Supplies",
            "type":"Manufacturing & Wholesale Goods"
        }
    ],
    "sg:phone":"+1 214 637 9353",
    "sg:postcode":"75234",
    "sg:province":"TX",
    "sg:tags":[
        "equipment",
        "welding"
    ],
    "wof:name":"A & M Welding & Ind Supply",
    "wof:placetype":"venue"
},
  "geometry": {"coordinates":[-96.914592,32.899746],"type":"Point"}
}