{
  "type": "Feature",
  "properties": {
    "iso:country":"US",
    "sg:address":"12779 Jones Rd",
    "sg:city":"Houston",
    "sg:classifiers":[
        {
            "category":"Health Services",
            "subcategory":"Doctor",
            "type":"Services"
        }
    ],
    "sg:phone":"+1 281 955 0000",
    "sg:postcode":"77070",
    "sg:province":"TX",
    "sg:tags":[
        "clinic"
    ],
    "wof:name":"Cy-Fair Med Clinic",
    "wof:placetype":"venue"
},
  "geometry": {"coordinates":[-95.585099,29.958804],"type":"Point"}
}