{
  "type": "Feature",
  "properties": {
    "iso:country":"US",
    "sg:address":"3015 Oak Lawn Ave",
    "sg:city":"Dallas",
    "sg:classifiers":[
        {
            "category":"Restaurant",
            "type":"Food & Drink"
        }
    ],
    "sg:menulink":"http://www.allmenus.com/tx/northeast/268880-the-landmark-restaurant---the-warwick-melrose-hote/menu/",
    "sg:phone":"+1 214 224 3152",
    "sg:postcode":"75219",
    "sg:province":"TX",
    "sg:tags":[
        "american"
    ],
    "wof:name":"The Landmark Restaurant - The Warwick Melrose Hote",
    "wof:placetype":"venue"
},
  "geometry": {"coordinates":[-96.809727,32.80908],"type":"Point"}
}