{
  "type": "Feature",
  "properties": {
    "iso:country":"US",
    "sg:address":"10916 Preston Trail Dr",
    "sg:city":"Austin",
    "sg:classifiers":[
        {
            "category":"Professional",
            "subcategory":"Management & Consulting",
            "type":"Services"
        }
    ],
    "sg:phone":"+1 512 280 0220",
    "sg:postcode":"78747",
    "sg:province":"TX",
    "sg:tags":[
        "business"
    ],
    "wof:name":"Graham Advisory",
    "wof:placetype":"venue"
},
  "geometry": {"coordinates":[-97.791661,30.137612],"type":"Point"}
}