{
  "type": "Feature",
  "properties": {
    "iso:country":"US",
    "sg:address":"14710 Luthe Rd",
    "sg:city":"Houston",
    "sg:classifiers":[
        {
            "category":"Freight",
            "type":"Transportation"
        }
    ],
    "sg:phone":"+1 281 219 7121",
    "sg:postcode":"77039",
    "sg:province":"TX",
    "sg:tags":[
        "distribution",
        "center"
    ],
    "wof:name":"Basic Chemical Solutions LLC",
    "wof:placetype":"venue"
},
  "geometry": {"coordinates":[-95.372013,29.929913],"type":"Point"}
}