{
  "type": "Feature",
  "properties": {
    "iso:country":"US",
    "sg:address":"11471 Alameda Ave",
    "sg:city":"El Paso",
    "sg:classifiers":[
        {
            "category":"Education",
            "subcategory":"School",
            "type":"Public Place"
        }
    ],
    "sg:phone":"+1 915 834 8100",
    "sg:postcode":"79927",
    "sg:province":"TX",
    "wof:name":"Ernesto Serna School",
    "wof:placetype":"venue"
},
  "geometry": {"coordinates":[-106.263541,31.62328],"type":"Point"}
}