{
  "type": "Feature",
  "properties": {
    "iso:country":"US",
    "sg:address":"1913 Copper St",
    "sg:city":"Garland",
    "sg:classifiers":[
        {
            "category":"Retail",
            "subcategory":"Auto Repair",
            "type":"Services"
        }
    ],
    "sg:phone":"+1 972 272 8812",
    "sg:postcode":"75042",
    "sg:province":"TX",
    "sg:tags":[
        "body",
        "automobile",
        "painting"
    ],
    "wof:name":"H & H Auto Body & Paint",
    "wof:placetype":"venue"
},
  "geometry": {"coordinates":[-96.658016,32.912266],"type":"Point"}
}