{
  "type": "Feature",
  "properties": {
    "iso:country":"US",
    "sg:address":"1529 Nall St",
    "sg:city":"Port Neches",
    "sg:classifiers":[
        {
            "category":"Building & Trades",
            "subcategory":"Landscaping Services",
            "type":"Services"
        }
    ],
    "sg:phone":"+1 409 729 0291",
    "sg:postcode":"77651",
    "sg:province":"TX",
    "wof:name":"Another Lawn Service",
    "wof:placetype":"venue"
},
  "geometry": {"coordinates":[-93.959023,29.988086],"type":"Point"}
}