{
  "type": "Feature",
  "properties": {
    "iso:country":"US",
    "sg:address":"9815 Degas Ln",
    "sg:city":"Houston",
    "sg:classifiers":[
        {
            "category":"Shopping",
            "subcategory":"Clothing, Apparel, & Fashions",
            "type":"Retail Goods"
        }
    ],
    "sg:phone":"+1 713 631 2688",
    "sg:postcode":"77016",
    "sg:province":"TX",
    "sg:tags":[
        "dressmaker"
    ],
    "wof:name":"Naomi's Creations",
    "wof:placetype":"venue"
},
  "geometry": {"coordinates":[-95.30837200000001,29.851419],"type":"Point"}
}