{
  "type": "Feature",
  "properties": {
    "iso:country":"US",
    "sg:address":"100 N Central Expy",
    "sg:city":"Richardson",
    "sg:classifiers":[
        {
            "category":"Travel",
            "subcategory":"Travel Agent",
            "type":"Entertainment"
        }
    ],
    "sg:phone":"+1 972 231 5391",
    "sg:postcode":"75080",
    "sg:province":"TX",
    "sg:tags":[
        "agency",
        "bureau",
        "cruise"
    ],
    "sg:website":"http://www.allworldtravel.com",
    "wof:name":"All World Travel Inc",
    "wof:placetype":"venue"
},
  "geometry": {"coordinates":[-96.734177,32.95068],"type":"Point"}
}