{
  "type": "Feature",
  "properties": {
    "iso:country":"US",
    "sg:address":"5900 Rowlett Rd",
    "sg:city":"Rowlett",
    "sg:classifiers":[
        {
            "category":"Banks & Credit Unions",
            "subcategory":"Bank",
            "type":"Services"
        }
    ],
    "sg:phone":"+1 972 463 8300",
    "sg:postcode":"75089",
    "sg:province":"TX",
    "sg:website":"www.communitybank-tx.com",
    "wof:name":"Community Bank",
    "wof:placetype":"venue"
},
  "geometry": {"coordinates":[-96.56999999999999,32.9146],"type":"Point"}
}