{
  "type": "Feature",
  "properties": {
    "iso:country":"US",
    "sg:address":"2800 W Irving Blvd",
    "sg:city":"Irving",
    "sg:classifiers":[
        {
            "category":"Retail",
            "subcategory":"Auto Repair",
            "type":"Services"
        }
    ],
    "sg:phone":"+1 214 325 5739",
    "sg:postcode":"75061",
    "sg:province":"TX",
    "sg:tags":[
        "body",
        "automobile",
        "painting",
        "repairing"
    ],
    "wof:name":"Aaa Auto Body Parts And Accessories",
    "wof:placetype":"venue"
},
  "geometry": {"coordinates":[-96.982033,32.830181],"type":"Point"}
}