{
  "type": "Feature",
  "properties": {
    "iso:country":"US",
    "sg:address":"1444 Prater St",
    "sg:city":"Dallas",
    "sg:classifiers":[
        {
            "category":"Retail",
            "subcategory":"Animal Services",
            "type":"Services"
        }
    ],
    "sg:phone":"+1 972 286 0006",
    "sg:postcode":"75217",
    "sg:province":"TX",
    "sg:tags":[
        "pet",
        "boarding",
        "sitting"
    ],
    "wof:name":"Allen's Ra-Ra-Me Kennels",
    "wof:placetype":"venue"
},
  "geometry": {"coordinates":[-96.64727000000001,32.689172],"type":"Point"}
}