{
  "type": "Feature",
  "properties": {
    "iso:country":"US",
    "sg:address":"617 W Main St",
    "sg:city":"Arlington",
    "sg:classifiers":[
        {
            "category":"Insurance",
            "subcategory":"Insurance Agent",
            "type":"Services"
        }
    ],
    "sg:phone":"+1 817 275 9292",
    "sg:postcode":"76010",
    "sg:province":"TX",
    "wof:name":"Allied National Insurance",
    "wof:placetype":"venue"
},
  "geometry": {"coordinates":[-97.112619,32.736877],"type":"Point"}
}