{
  "type": "Feature",
  "properties": {
    "iso:country":"US",
    "sg:address":"4475 Kirkland Dr",
    "sg:city":"Fort Worth",
    "sg:classifiers":[
        {
            "category":"Professional",
            "subcategory":"Management & Consulting",
            "type":"Services"
        }
    ],
    "sg:phone":"+1 817 975 7235",
    "sg:postcode":"76109",
    "sg:province":"TX",
    "sg:tags":[
        "art"
    ],
    "wof:name":"Ashleys Fine Art",
    "wof:placetype":"venue"
},
  "geometry": {"coordinates":[-97.38901300000001,32.685965],"type":"Point"}
}