{
  "type": "Feature",
  "properties": {
    "iso:country":"US",
    "sg:address":"5470 Braesvalley Dr",
    "sg:city":"Houston",
    "sg:classifiers":[
        {
            "category":"Restaurant",
            "type":"Food & Drink"
        }
    ],
    "sg:phone":"+1 713 283 0325",
    "sg:postcode":"77096",
    "sg:province":"TX",
    "sg:tags":[
        "eating"
    ],
    "wof:name":"Crossroads Coffee LLC",
    "wof:placetype":"venue"
},
  "geometry": {"coordinates":[-95.48327500000001,29.679178],"type":"Point"}
}