{
  "type": "Feature",
  "properties": {
    "iso:country":"US",
    "sg:address":"5401 Chimney Rock Rd",
    "sg:city":"Houston",
    "sg:classifiers":[
        {
            "category":"Freight",
            "type":"Transportation"
        }
    ],
    "sg:phone":"+1 713 839 7290",
    "sg:postcode":"77081",
    "sg:province":"TX",
    "sg:tags":[
        "operator",
        "local",
        "trucking"
    ],
    "wof:name":"Extreme Trucking",
    "wof:placetype":"venue"
},
  "geometry": {"coordinates":[-95.47648599999999,29.722461],"type":"Point"}
}