{
  "type": "Feature",
  "properties": {
    "iso:country":"US",
    "sg:address":"5920 Hillcroft St",
    "sg:city":"Houston",
    "sg:classifiers":[
        {
            "category":"Autos & Motor Vehicles",
            "subcategory":"Automobile Sales",
            "type":"Retail Goods"
        },
        {
            "category":"Home & Garden",
            "subcategory":"Building Materials",
            "type":"Retail Goods"
        }
    ],
    "sg:phone":"+1 713 974 7283",
    "sg:postcode":"77036",
    "sg:province":"TX",
    "sg:tags":[
        "plate",
        "window",
        "used",
        "glass"
    ],
    "sg:website":"www.affordableautoglass.com",
    "wof:name":"Affordable Glass",
    "wof:placetype":"venue"
},
  "geometry": {"coordinates":[-95.501099,29.719101],"type":"Point"}
}