{
  "type": "Feature",
  "properties": {
    "iso:country":"US",
    "sg:address":"10345 Ferguson Rd",
    "sg:city":"Dallas",
    "sg:classifiers":[
        {
            "category":"Personal",
            "subcategory":"Shoe Repair & Shine",
            "type":"Services"
        }
    ],
    "sg:phone":"+1 214 321 0203",
    "sg:postcode":"75228",
    "sg:province":"TX",
    "sg:tags":[
        "repairing",
        "boot"
    ],
    "wof:name":"Walter's Shoe Repair",
    "wof:placetype":"venue"
},
  "geometry": {"coordinates":[-96.67269899999999,32.835701],"type":"Point"}
}