{
  "type": "Feature",
  "properties": {
    "iso:country":"US",
    "sg:address":"13071 W Lake Houston Pkwy",
    "sg:city":"Houston",
    "sg:classifiers":[
        {
            "category":"Sports & Exercise",
            "subcategory":"Gym",
            "type":"Entertainment"
        }
    ],
    "sg:phone":"+1 281 454 7337",
    "sg:postcode":"77044",
    "sg:province":"TX",
    "wof:name":"Curves",
    "wof:placetype":"venue"
},
  "geometry": {"coordinates":[-95.188984,29.92478],"type":"Point"}
}