{
  "type": "Feature",
  "properties": {
    "iso:country":"US",
    "sg:address":"7105 Birkshire Dr",
    "sg:city":"Amarillo",
    "sg:classifiers":[
        {
            "category":"Building & Trades",
            "subcategory":"Landscaping Services",
            "type":"Services"
        }
    ],
    "sg:phone":"+1 806 359 7722",
    "sg:postcode":"79109",
    "sg:province":"TX",
    "wof:name":"Stewart Lawn & Landscape",
    "wof:placetype":"venue"
},
  "geometry": {"coordinates":[-101.91620399999999,35.141408],"type":"Point"}
}