{
  "type": "Feature",
  "properties": {
    "iso:country":"US",
    "sg:address":"810 Firefly St",
    "sg:city":"San Antonio",
    "sg:classifiers":[
        {
            "category":"Professional",
            "subcategory":"Advertising",
            "type":"Services"
        }
    ],
    "sg:phone":"+1 210 349 1246",
    "sg:postcode":"78216",
    "sg:province":"TX",
    "sg:tags":[
        "agency"
    ],
    "wof:name":"Joe Forks Mouse Co",
    "wof:placetype":"venue"
},
  "geometry": {"coordinates":[-98.50643700000001,29.545435],"type":"Point"}
}