{
  "type": "Feature",
  "properties": {
    "iso:country":"US",
    "sg:address":"6706 Stonewater",
    "sg:city":"Houston",
    "sg:classifiers":[
        {
            "category":"Home & Garden",
            "subcategory":"Home Furnishings",
            "type":"Retail Goods"
        }
    ],
    "sg:phone":"+1 281 858 1319",
    "sg:postcode":"77084",
    "sg:province":"TX",
    "sg:tags":[
        "draperies",
        "vertical",
        "blinds-venetian",
        "window",
        "treatment",
        "curtain"
    ],
    "sg:website":"http://www.asapblindsusa.net/",
    "wof:name":"ASAP Blinds USA",
    "wof:placetype":"venue"
},
  "geometry": {"coordinates":[-95.661742,29.874113],"type":"Point"}
}