{
  "type": "Feature",
  "properties": {
    "iso:country":"US",
    "sg:address":"6805 Southwest Fwy",
    "sg:city":"Houston",
    "sg:classifiers":[
        {
            "category":"Professional",
            "subcategory":"Computer Services",
            "type":"Services"
        }
    ],
    "sg:phone":"+1 713 947 2049",
    "sg:postcode":"77074",
    "sg:province":"TX",
    "sg:tags":[
        "stereo",
        "installation"
    ],
    "wof:name":"Car Stereo",
    "wof:placetype":"venue"
},
  "geometry": {"coordinates":[-95.503186,29.712486],"type":"Point"}
}