{
  "type": "Feature",
  "properties": {
    "iso:country":"US",
    "sg:address":"901 E Florida Ave",
    "sg:city":"Midland",
    "sg:classifiers":[
        {
            "category":"Retail",
            "subcategory":"Auto Repair",
            "type":"Services"
        }
    ],
    "sg:phone":"+1 432 682 3960",
    "sg:postcode":"79701",
    "sg:province":"TX",
    "sg:tags":[
        "automobile",
        "diagnostic",
        "general"
    ],
    "wof:name":"Auto Tech Automotive Inc",
    "wof:placetype":"venue"
},
  "geometry": {"coordinates":[-102.06309400000001,31.989341],"type":"Point"}
}