{
  "type": "Feature",
  "properties": {
    "iso:country":"US",
    "sg:address":"10145 Lone Eagle Dr",
    "sg:city":"Fort Worth",
    "sg:classifiers":[
        {
            "category":"Building & Trades",
            "subcategory":"Construction",
            "type":"Services"
        }
    ],
    "sg:phone":"+1 817 246 6907",
    "sg:postcode":"76108",
    "sg:province":"TX",
    "sg:tags":[
        "contractor"
    ],
    "wof:name":"W W Drywall",
    "wof:placetype":"venue"
},
  "geometry": {"coordinates":[-97.4971,32.761661],"type":"Point"}
}