{
  "type": "Feature",
  "properties": {
    "iso:country":"US",
    "sg:address":"100 N Highway 67",
    "sg:city":"Cedar Hill",
    "sg:classifiers":[
        {
            "category":"Food & Beverages",
            "subcategory":"Groceries & Convenience Stores",
            "type":"Retail Goods"
        }
    ],
    "sg:phone":"+1 972 291 8456",
    "sg:postcode":"75104",
    "sg:province":"TX",
    "wof:name":"Speedy Bee Market",
    "wof:placetype":"venue"
},
  "geometry": {"coordinates":[-96.945297,32.589901],"type":"Point"}
}