{
  "type": "Feature",
  "properties": {
    "iso:country":"US",
    "sg:address":"1000 E Pioneer Pkwy",
    "sg:city":"Arlington",
    "sg:classifiers":[
        {
            "category":"Recreation",
            "type":"Entertainment"
        }
    ],
    "sg:phone":"+1 817 860 1122",
    "sg:postcode":"76010",
    "sg:province":"TX",
    "wof:name":"Noon Bingo",
    "wof:placetype":"venue"
},
  "geometry": {"coordinates":[-97.094914,32.707865],"type":"Point"}
}