{
  "type": "Feature",
  "properties": {
    "iso:country":"US",
    "sg:address":"1703 Prairie Mark Ln",
    "sg:city":"Houston",
    "sg:classifiers":[
        {
            "category":"Professional",
            "type":"Services"
        }
    ],
    "sg:phone":"+1 281 752 7566",
    "sg:postcode":"77077",
    "sg:province":"TX",
    "sg:tags":[
        "establishment"
    ],
    "wof:name":"Nielsen & Nielsen",
    "wof:placetype":"venue"
},
  "geometry": {"coordinates":[-95.58313099999999,29.752872],"type":"Point"}
}