{
  "type": "Feature",
  "properties": {
    "iso:country":"US",
    "sg:address":"15800 Galveston Rd",
    "sg:city":"Webster",
    "sg:classifiers":[
        {
            "category":"Wholesale",
            "subcategory":"Computers",
            "type":"Manufacturing & Wholesale Goods"
        }
    ],
    "sg:phone":"+1 281 286 3233",
    "sg:postcode":"77598",
    "sg:province":"TX",
    "sg:tags":[
        "engineering",
        "software"
    ],
    "wof:name":"Erick D Kindred",
    "wof:placetype":"venue"
},
  "geometry": {"coordinates":[-95.13776799999999,29.558666],"type":"Point"}
}