{
  "type": "Feature",
  "properties": {
    "iso:country":"US",
    "sg:address":"9231 Long Barrel Ln",
    "sg:city":"Houston",
    "sg:classifiers":[
        {
            "category":"Organizations",
            "subcategory":"Membership Organization",
            "type":"Services"
        }
    ],
    "sg:phone":"+1 713 466 7308",
    "sg:postcode":"77040",
    "sg:province":"TX",
    "wof:name":"Woodland Oaks Community Associ",
    "wof:placetype":"venue"
},
  "geometry": {"coordinates":[-95.509664,29.875303],"type":"Point"}
}