{
  "type": "Feature",
  "properties": {
    "iso:country":"US",
    "sg:address":"3501 Morenci Rd",
    "sg:city":"El Paso",
    "sg:classifiers":[
        {
            "category":"Organizations",
            "subcategory":"Community Association",
            "type":"Services"
        }
    ],
    "sg:phone":"+1 915 564 3622",
    "sg:postcode":"79903",
    "sg:province":"TX",
    "wof:name":"Optimist Club of Alta Vis",
    "wof:placetype":"venue"
},
  "geometry": {"coordinates":[-106.453013,31.7898],"type":"Point"}
}