{
  "type": "Feature",
  "properties": {
    "iso:country":"US",
    "sg:address":"2219 S Loop 288",
    "sg:city":"Denton",
    "sg:phone":"+1 940 891 0861",
    "sg:postcode":"76205",
    "sg:province":"TX",
    "sg:website":"http://www.cicispizza.com",
    "wof:name":"CiCi's Pizza",
    "wof:placetype":"venue"
},
  "geometry": {"coordinates":[-97.10483600000001,33.188828],"type":"Point"}
}