{
  "type": "Feature",
  "properties": {
    "iso:country":"US",
    "sg:address":"1910 Jefferson St",
    "sg:city":"Commerce",
    "sg:classifiers":[
        {
            "category":"Organizations",
            "subcategory":"Religious Organization",
            "type":"Services"
        }
    ],
    "sg:phone":"+1 903 886 3086",
    "sg:postcode":"75428",
    "sg:province":"TX",
    "sg:tags":[
        "clergy"
    ],
    "wof:name":"David Gibson",
    "wof:placetype":"venue"
},
  "geometry": {"coordinates":[-95.908716,33.238268],"type":"Point"}
}