{
  "type": "Feature",
  "properties": {
    "iso:country":"US",
    "sg:address":"4605 N Braeswood Blvd",
    "sg:city":"Houston",
    "sg:classifiers":[
        {
            "category":"Real Estate",
            "subcategory":"Real Estate Operator",
            "type":"Services"
        }
    ],
    "sg:phone":"+1 713 666 6262",
    "sg:postcode":"77096",
    "sg:province":"TX",
    "sg:tags":[
        "building",
        "apartment"
    ],
    "wof:name":"Gray Star",
    "wof:placetype":"venue"
},
  "geometry": {"coordinates":[-95.45556000000001,29.682957],"type":"Point"}
}