{
  "type": "Feature",
  "properties": {
    "iso:country":"US",
    "sg:address":"4905 Tahoe Dr",
    "sg:city":"Fort Worth",
    "sg:classifiers":[
        {
            "category":"Personal",
            "type":"Services"
        }
    ],
    "sg:phone":"+1 817 531 0477",
    "sg:postcode":"76119",
    "sg:province":"TX",
    "wof:name":"Massage By Detosha",
    "wof:placetype":"venue"
},
  "geometry": {"coordinates":[-97.257171,32.69064],"type":"Point"}
}