{
  "type": "Feature",
  "properties": {
    "iso:country":"US",
    "sg:address":"1744 W 4th St",
    "sg:city":"Freeport",
    "sg:classifiers":[
        {
            "category":"Wholesale",
            "subcategory":"Machinery & Supplies",
            "type":"Manufacturing & Wholesale Goods"
        }
    ],
    "sg:phone":"+1 979 239 3300",
    "sg:postcode":"77541",
    "sg:province":"TX",
    "sg:tags":[
        "actuator",
        "valve"
    ],
    "wof:name":"Flowserve/Davco",
    "wof:placetype":"venue"
},
  "geometry": {"coordinates":[-95.36931300000001,28.954567],"type":"Point"}
}