{
  "type": "Feature",
  "properties": {
    "iso:country":"US",
    "sg:address":"7305 Majestic Manor",
    "sg:city":"Colleyville",
    "sg:classifiers":[
        {
            "category":"Professional",
            "subcategory":"Business Services",
            "type":"Services"
        }
    ],
    "sg:phone":"+1 817 329 0793",
    "sg:postcode":"76034",
    "sg:province":"TX",
    "wof:name":"Smt Enterprises LLC",
    "wof:placetype":"venue"
},
  "geometry": {"coordinates":[-97.14034599999999,32.914158],"type":"Point"}
}