{
  "type": "Feature",
  "properties": {
    "iso:country":"US",
    "sg:address":"1009 Whispering Dr",
    "sg:city":"Round Rock",
    "sg:classifiers":[
        {
            "category":"Building & Trades",
            "subcategory":"Construction",
            "type":"Services"
        }
    ],
    "sg:phone":"+1 512 388 1140",
    "sg:postcode":"78664",
    "sg:province":"TX",
    "sg:tags":[
        "contractor"
    ],
    "wof:name":"D&D Specialty Services",
    "wof:placetype":"venue"
},
  "geometry": {"coordinates":[-97.669847,30.533004],"type":"Point"}
}