{
  "type": "Feature",
  "properties": {
    "iso:country":"US",
    "sg:address":"101 N Shady Shores Dr",
    "sg:city":"Lake Dallas",
    "sg:classifiers":[
        {
            "category":"Personal",
            "subcategory":"Beauty Salon",
            "type":"Services"
        }
    ],
    "sg:phone":"+1 940 321 8851",
    "sg:postcode":"75065",
    "sg:province":"TX",
    "wof:name":"Hairtrax",
    "wof:placetype":"venue"
},
  "geometry": {"coordinates":[-97.03008,33.122589],"type":"Point"}
}