{
  "type": "Feature",
  "properties": {
    "iso:country":"US",
    "sg:address":"1503 N Jacobs St",
    "sg:city":"Carthage",
    "sg:classifiers":[
        {
            "category":"Professional",
            "subcategory":"Business Services",
            "type":"Services"
        }
    ],
    "sg:phone":"+1 903 694 9551",
    "sg:postcode":"75633",
    "sg:province":"TX",
    "sg:tags":[
        "consultant",
        "coach"
    ],
    "wof:name":"Larry Bruster",
    "wof:placetype":"venue"
},
  "geometry": {"coordinates":[-94.351885,32.176861],"type":"Point"}
}