{
  "type": "Feature",
  "properties": {
    "iso:country":"US",
    "sg:address":"1502 Rancho Dominguez Rd",
    "sg:city":"Corinth",
    "sg:classifiers":[
        {
            "category":"Insurance",
            "subcategory":"Insurance Agent",
            "type":"Services"
        }
    ],
    "sg:phone":"+1 940 498 1675",
    "sg:postcode":"76210",
    "sg:province":"TX",
    "wof:name":"Farmers Insurance Group",
    "wof:placetype":"venue"
},
  "geometry": {"coordinates":[-97.087794,33.132544],"type":"Point"}
}