{
  "type": "Feature",
  "properties": {
    "iso:country":"US",
    "sg:address":"2600 E Southlake Blvd",
    "sg:city":"Southlake",
    "sg:classifiers":[
        {
            "category":"Shopping",
            "subcategory":"Bicycles & Sporting Goods",
            "type":"Retail Goods"
        }
    ],
    "sg:phone":"+1 817 748 0333",
    "sg:postcode":"76092",
    "sg:province":"TX",
    "sg:tags":[
        "equipment",
        "exercise"
    ],
    "sg:website":"http://www.hestfitness.com",
    "wof:name":"Hest Fitness Products",
    "wof:placetype":"venue"
},
  "geometry": {"coordinates":[-97.111795,32.939513],"type":"Point"}
}