{
  "type": "Feature",
  "properties": {
    "iso:country":"US",
    "sg:address":"1013 W Bay Area Blvd",
    "sg:city":"Webster",
    "sg:classifiers":[
        {
            "category":"Shopping",
            "subcategory":"Computers & Home Electronics",
            "type":"Retail Goods"
        }
    ],
    "sg:phone":"+1 281 554 8900",
    "sg:postcode":"77598",
    "sg:province":"TX",
    "sg:tags":[
        "hardware",
        "equipment",
        "supply"
    ],
    "sg:website":"http://www.compusa.com",
    "wof:name":"CompUSA",
    "wof:placetype":"venue"
},
  "geometry": {"coordinates":[-95.139195,29.541498],"type":"Point"}
}