{
  "type": "Feature",
  "properties": {
    "iso:country":"US",
    "sg:address":"421 Marconi St",
    "sg:city":"Wichita Falls",
    "sg:classifiers":[
        {
            "category":"Organizations",
            "subcategory":"Religious Organization",
            "type":"Services"
        }
    ],
    "sg:phone":"+1 940 766 2735",
    "sg:postcode":"76301",
    "sg:province":"TX",
    "sg:tags":[
        "catholic",
        "church"
    ],
    "wof:name":"Our Lady Of Guadalupe Church",
    "wof:placetype":"venue"
},
  "geometry": {"coordinates":[-98.480542,33.912867],"type":"Point"}
}