{
  "type": "Feature",
  "properties": {
    "iso:country":"US",
    "sg:address":"1412 Collier St",
    "sg:city":"Austin",
    "sg:classifiers":[
        {
            "category":"Real Estate",
            "subcategory":"Architect",
            "type":"Services"
        }
    ],
    "sg:phone":"+1 512 374 9120",
    "sg:postcode":"78704",
    "sg:province":"TX",
    "wof:name":"HADDON & COWAN",
    "wof:placetype":"venue"
},
  "geometry": {"coordinates":[-97.765424,30.251552],"type":"Point"}
}