{
  "type": "Feature",
  "properties": {
    "iso:country":"US",
    "sg:address":"2616 Martin Luther King Fwy",
    "sg:city":"Fort Worth",
    "sg:classifiers":[
        {
            "category":"Professional",
            "subcategory":"Lawyer & Legal Services",
            "type":"Services"
        }
    ],
    "sg:phone":"+1 817 496 7001",
    "sg:postcode":"76105",
    "sg:province":"TX",
    "sg:tags":[
        "attorney"
    ],
    "wof:name":"Calvin D Johnson",
    "wof:placetype":"venue"
},
  "geometry": {"coordinates":[-97.28769800000001,32.71854],"type":"Point"}
}