{
  "type": "Feature",
  "properties": {
    "iso:country":"US",
    "sg:address":"1612 Lubbock Hwy",
    "sg:city":"Lamesa",
    "sg:classifiers":[
        {
            "category":"Retail",
            "subcategory":"Auto Repair",
            "type":"Services"
        }
    ],
    "sg:phone":"+1 806 872 3637",
    "sg:postcode":"79331",
    "sg:province":"TX",
    "sg:tags":[
        "body",
        "automobile",
        "painting"
    ],
    "wof:name":"Caprock Auto Sales",
    "wof:placetype":"venue"
},
  "geometry": {"coordinates":[-101.951843,32.747552],"type":"Point"}
}