{
  "type": "Feature",
  "properties": {
    "iso:country":"US",
    "sg:address":"1727 Elmwood Blvd",
    "sg:city":"Dallas",
    "sg:classifiers":[
        {
            "category":"Professional",
            "type":"Services"
        }
    ],
    "sg:phone":"+1 214 339 4967",
    "sg:postcode":"75224",
    "sg:province":"TX",
    "sg:tags":[
        "establishment"
    ],
    "wof:name":"View For The New Millenium",
    "wof:placetype":"venue"
},
  "geometry": {"coordinates":[-96.847914,32.727358],"type":"Point"}
}