{
  "type": "Feature",
  "properties": {
    "iso:country":"US",
    "sg:address":"9355 Landis Dr",
    "sg:city":"Beaumont",
    "sg:classifiers":[
        {
            "category":"Shopping",
            "type":"Retail Goods"
        }
    ],
    "sg:phone":"+1 409 860 1724",
    "sg:postcode":"77707",
    "sg:province":"TX",
    "sg:tags":[
        "merchandise"
    ],
    "wof:name":"Touched By Nature",
    "wof:placetype":"venue"
},
  "geometry": {"coordinates":[-94.205016,30.066435],"type":"Point"}
}