{
  "type": "Feature",
  "properties": {
    "iso:country":"US",
    "sg:address":"4051 Fm 389",
    "sg:city":"Brenham",
    "sg:classifiers":[
        {
            "category":"Home & Garden",
            "subcategory":"Household Appliances",
            "type":"Retail Goods"
        },
        {
            "category":"Retail",
            "subcategory":"Repair Shop",
            "type":"Services"
        },
        {
            "category":"Building & Trades",
            "subcategory":"Construction",
            "type":"Services"
        },
        {
            "category":"Professional",
            "subcategory":"Engineering",
            "type":"Services"
        }
    ],
    "sg:phone":"+1 979 251 8545",
    "sg:postcode":"77833",
    "sg:province":"TX",
    "sg:tags":[
        "major",
        "specialty",
        "heating",
        "appliances-small",
        "system",
        "refrigeration",
        "air conditioning",
        "contractor",
        "freezers-repair",
        "refrigerator",
        "engineer"
    ],
    "wof:name":"Jacks Ac & Refrigeration",
    "wof:placetype":"venue"
},
  "geometry": {"coordinates":[-96.464257,30.135662],"type":"Point"}
}