{
  "type": "Feature",
  "properties": {
    "iso:country":"US",
    "sg:address":"2004 US Grant Dr",
    "sg:city":"Killeen",
    "sg:classifiers":[
        {
            "category":"Personal",
            "subcategory":"Beauty Salon",
            "type":"Services"
        }
    ],
    "sg:phone":"+1 254 634 3100",
    "sg:postcode":"76543",
    "sg:province":"TX",
    "wof:name":"Lasha's Braids & More",
    "wof:placetype":"venue"
},
  "geometry": {"coordinates":[-97.704233,31.129754],"type":"Point"}
}