{
  "type": "Feature",
  "properties": {
    "iso:country":"US",
    "sg:address":"401 Trinity River Cir",
    "sg:city":"Dallas",
    "sg:classifiers":[
        {
            "category":"Professional",
            "subcategory":"Lawyer & Legal Services",
            "type":"Services"
        }
    ],
    "sg:phone":"+1 214 942 6420",
    "sg:postcode":"75203",
    "sg:province":"TX",
    "wof:name":"At Location LLC",
    "wof:placetype":"venue"
},
  "geometry": {"coordinates":[-96.81608900000001,32.762792],"type":"Point"}
}