{
  "type": "Feature",
  "properties": {
    "iso:country":"US",
    "sg:address":"6507 Jester Boulevard",
    "sg:city":"Austin",
    "sg:classifiers":[
        {
            "category":"Shopping Center",
            "type":"Public Place"
        }
    ],
    "sg:phone":"+1 512 346 8200",
    "sg:postcode":"78750",
    "sg:province":"TX",
    "wof:name":"Jester Village",
    "wof:placetype":"venue"
},
  "geometry": {"coordinates":[-97.80185899999999,30.369509],"type":"Point"}
}