{
  "type": "Feature",
  "properties": {
    "iso:country":"US",
    "sg:address":"3001 John Ben Shepperd Pkwy",
    "sg:city":"Odessa",
    "sg:classifiers":[
        {
            "category":"Restaurant",
            "type":"Food & Drink"
        }
    ],
    "sg:phone":"+1 432 366 6886",
    "sg:postcode":"79762",
    "sg:province":"TX",
    "wof:name":"Red Sun Super Buffet",
    "wof:placetype":"venue"
},
  "geometry": {"coordinates":[-102.33123500000001,31.883933],"type":"Point"}
}