{
  "type": "Feature",
  "properties": {
    "iso:country":"US",
    "sg:address":"140 W Bolivar St",
    "sg:city":"Vidor",
    "sg:classifiers":[
        {
            "category":"Professional",
            "subcategory":"Management & Consulting",
            "type":"Services"
        }
    ],
    "sg:phone":"+1 409 783 3100",
    "sg:postcode":"77662",
    "sg:province":"TX",
    "sg:tags":[
        "business"
    ],
    "wof:name":"Advantage Curriculum Inc",
    "wof:placetype":"venue"
},
  "geometry": {"coordinates":[-94.014686,30.126835],"type":"Point"}
}