{
  "type": "Feature",
  "properties": {
    "iso:country":"US",
    "sg:address":"27959 Barnett St",
    "sg:city":"New Caney",
    "sg:classifiers":[
        {
            "category":"Retail",
            "subcategory":"Auto Repair",
            "type":"Services"
        }
    ],
    "sg:phone":"+1 281 399 0763",
    "sg:postcode":"77357",
    "sg:province":"TX",
    "sg:tags":[
        "automobile"
    ],
    "wof:name":"Barnett Auto Repair & Salvage",
    "wof:placetype":"venue"
},
  "geometry": {"coordinates":[-95.133593,30.160175],"type":"Point"}
}