{
  "type": "Feature",
  "properties": {
    "iso:country":"US",
    "sg:address":"7349 Royal Cir",
    "sg:city":"Dallas",
    "sg:classifiers":[
        {
            "category":"Professional",
            "subcategory":"Detective & Security Services",
            "type":"Services"
        }
    ],
    "sg:phone":"+1 214 378 6045",
    "sg:postcode":"75230",
    "sg:province":"TX",
    "sg:tags":[
        "system"
    ],
    "wof:name":"CFH Enterprises",
    "wof:placetype":"venue"
},
  "geometry": {"coordinates":[-96.778395,32.895778],"type":"Point"}
}