{
  "type": "Feature",
  "properties": {
    "iso:country":"US",
    "sg:address":"1025 Avenue S",
    "sg:city":"Grand Prairie",
    "sg:classifiers":[
        {
            "category":"Wholesale",
            "subcategory":"Metals & Minerals",
            "type":"Manufacturing & Wholesale Goods"
        }
    ],
    "sg:phone":"+1 972 623 0620",
    "sg:postcode":"75050",
    "sg:province":"TX",
    "sg:tags":[
        "steel",
        "warehouse"
    ],
    "wof:name":"Interwire Texas",
    "wof:placetype":"venue"
},
  "geometry": {"coordinates":[-97.05237700000001,32.788055],"type":"Point"}
}