{
  "type": "Feature",
  "properties": {
    "iso:country":"US",
    "sg:address":"202 S Main St",
    "sg:city":"Cleburne",
    "sg:classifiers":[
        {
            "category":"Professional",
            "subcategory":"Lawyer & Legal Services",
            "type":"Services"
        }
    ],
    "sg:phone":"+1 817 558 3885",
    "sg:postcode":"76033",
    "sg:province":"TX",
    "wof:name":"De Los Santos Richardo Atty L",
    "wof:placetype":"venue"
},
  "geometry": {"coordinates":[-97.386239,32.345325],"type":"Point"}
}