{
  "type": "Feature",
  "properties": {
    "iso:country":"US",
    "sg:address":"11817 Gaston Pkwy",
    "sg:city":"Dallas",
    "sg:classifiers":[
        {
            "category":"Retail",
            "subcategory":"Auto Repair",
            "type":"Services"
        }
    ],
    "sg:phone":"+1 214 319 8686",
    "sg:postcode":"75218",
    "sg:province":"TX",
    "wof:name":"A 1 Car Care",
    "wof:placetype":"venue"
},
  "geometry": {"coordinates":[-96.677269,32.855709],"type":"Point"}
}