{
  "type": "Feature",
  "properties": {
    "iso:country":"US",
    "sg:address":"3425 Ashington Ln",
    "sg:city":"Plano",
    "sg:classifiers":[
        {
            "category":"Education",
            "subcategory":"School",
            "type":"Public Place"
        }
    ],
    "sg:phone":"+1 972 618 8844",
    "sg:postcode":"75023",
    "sg:province":"TX",
    "sg:tags":[
        "child",
        "day",
        "care"
    ],
    "sg:website":"www.montessorischool.com",
    "wof:name":"West Plano Montessori Schl Inc",
    "wof:placetype":"venue"
},
  "geometry": {"coordinates":[-96.76074300000001,33.059763],"type":"Point"}
}