{
  "type": "Feature",
  "properties": {
    "iso:country":"US",
    "sg:address":"4212 Ensign Rd",
    "sg:city":"Ennis",
    "sg:classifiers":[
        {
            "category":"Freight",
            "type":"Transportation"
        }
    ],
    "sg:phone":"+1 972 875 6400",
    "sg:postcode":"75119",
    "sg:province":"TX",
    "sg:tags":[
        "general"
    ],
    "wof:name":"287 & Ensign Self Storage LP",
    "wof:placetype":"venue"
},
  "geometry": {"coordinates":[-96.62202499999999,32.288998],"type":"Point"}
}