{
  "type": "Feature",
  "properties": {
    "iso:country":"US",
    "sg:address":"6011 Burnet Rd",
    "sg:city":"Austin",
    "sg:classifiers":[
        {
            "category":"Personal",
            "subcategory":"Barber",
            "type":"Services"
        }
    ],
    "sg:phone":"+1 512 453 9215",
    "sg:postcode":"78757",
    "sg:province":"TX",
    "sg:tags":[
        "shop"
    ],
    "wof:name":"Pete's Flat Top Shop",
    "wof:placetype":"venue"
},
  "geometry": {"coordinates":[-97.739502,30.33615],"type":"Point"}
}