{
  "type": "Feature",
  "properties": {
    "iso:country":"US",
    "sg:address":"119 Maxey Rd",
    "sg:city":"Houston",
    "sg:classifiers":[
        {
            "category":"Retail",
            "subcategory":"Repair Shop",
            "type":"Services"
        }
    ],
    "sg:phone":"+1 713 453 5351",
    "sg:postcode":"77013",
    "sg:province":"TX",
    "wof:name":"Hawkins TV",
    "wof:placetype":"venue"
},
  "geometry": {"coordinates":[-95.218751,29.798288],"type":"Point"}
}