{
  "type": "Feature",
  "properties": {
    "iso:country":"US",
    "sg:address":"6301 Gaston Ave Ste 400E",
    "sg:city":"Dallas",
    "sg:classifiers":[
        {
            "category":"Health Services",
            "subcategory":"Doctor",
            "type":"Services"
        }
    ],
    "sg:phone":"+1 214 824 2851",
    "sg:postcode":"75214",
    "sg:province":"TX",
    "sg:tags":[
        "medicine",
        "physician",
        "practice",
        "surgeons",
        "family"
    ],
    "wof:name":"Physicians Anesthesia Practice",
    "wof:placetype":"venue"
},
  "geometry": {"coordinates":[-96.754245,32.812656],"type":"Point"}
}