{
  "type": "Feature",
  "properties": {
    "iso:country":"US",
    "sg:address":"922 Pebbleshire Dr",
    "sg:city":"Houston",
    "sg:classifiers":[
        {
            "category":"Professional",
            "type":"Services"
        }
    ],
    "sg:phone":"+1 281 488 4054",
    "sg:postcode":"77062",
    "sg:province":"TX",
    "wof:name":"Legorreta & McDonald Family PR",
    "wof:placetype":"venue"
},
  "geometry": {"coordinates":[-95.134765,29.569663],"type":"Point"}
}