{
  "type": "Feature",
  "properties": {
    "iso:country":"US",
    "sg:address":"7502 Matranga St",
    "sg:city":"Hitchcock",
    "sg:classifiers":[
        {
            "category":"Social Services",
            "subcategory":"Child Care",
            "type":"Services"
        }
    ],
    "sg:phone":"+1 409 986 6037",
    "sg:postcode":"77563",
    "sg:province":"TX",
    "wof:name":"Lydia Fernandez",
    "wof:placetype":"venue"
},
  "geometry": {"coordinates":[-95.024344,29.340817],"type":"Point"}
}