{
  "type": "Feature",
  "properties": {
    "iso:country":"US",
    "sg:address":"6402 E Mockingbird Ln Ste A",
    "sg:city":"Dallas",
    "sg:classifiers":[
        {
            "category":"Food & Beverages",
            "subcategory":"Bakery",
            "type":"Retail Goods"
        }
    ],
    "sg:phone":"+1 214 826 9898",
    "sg:postcode":"75214",
    "sg:province":"TX",
    "sg:tags":[
        "sandwich"
    ],
    "wof:name":"Subway Sandwiches",
    "wof:placetype":"venue"
},
  "geometry": {"coordinates":[-96.75270500000001,32.83625],"type":"Point"}
}