{
  "type": "Feature",
  "properties": {
    "iso:country":"US",
    "sg:address":"2013 Park Place Blvd",
    "sg:city":"Bedford",
    "sg:classifiers":[
        {
            "category":"Professional",
            "subcategory":"Management & Consulting",
            "type":"Services"
        }
    ],
    "sg:phone":"+1 817 571 0976",
    "sg:postcode":"76021",
    "sg:province":"TX",
    "sg:tags":[
        "business"
    ],
    "wof:name":"Azimuth Project",
    "wof:placetype":"venue"
},
  "geometry": {"coordinates":[-97.127343,32.839752],"type":"Point"}
}