{
  "type": "Feature",
  "properties": {
    "iso:country":"US",
    "sg:address":"38 Dunham Dr",
    "sg:city":"Texarkana",
    "sg:classifiers":[
        {
            "category":"Retail",
            "subcategory":"Veterinary Services",
            "type":"Services"
        }
    ],
    "sg:phone":"+1 903 831 7521",
    "sg:postcode":"75503",
    "sg:province":"TX",
    "sg:tags":[
        "clinic",
        "hospital"
    ],
    "wof:name":"Ashdown Veterinary Clinic",
    "wof:placetype":"venue"
},
  "geometry": {"coordinates":[-94.11174,33.491581],"type":"Point"}
}