{
  "type": "Feature",
  "properties": {
    "iso:country":"US",
    "sg:address":"835 Grenshaw St",
    "sg:city":"Houston",
    "sg:classifiers":[
        {
            "category":"Professional",
            "subcategory":"Accounting & Tax Preparation",
            "type":"Services"
        }
    ],
    "sg:phone":"+1 281 999 0788",
    "sg:postcode":"77088",
    "sg:province":"TX",
    "sg:tags":[
        "bookkeeping",
        "general"
    ],
    "wof:name":"A & B Accounting & Bookkeeping",
    "wof:placetype":"venue"
},
  "geometry": {"coordinates":[-95.418616,29.880703],"type":"Point"}
}