{
  "type": "Feature",
  "properties": {
    "iso:country":"US",
    "sg:address":"29315 Stockdick School Rd",
    "sg:city":"Katy",
    "sg:classifiers":[
        {
            "category":"Building & Trades",
            "subcategory":"Construction",
            "type":"Services"
        }
    ],
    "sg:phone":"+1 281 391 9109",
    "sg:postcode":"77493",
    "sg:province":"TX",
    "sg:tags":[
        "masonry",
        "contractor"
    ],
    "wof:name":"Pyramid Masonry and Cnstr",
    "wof:placetype":"venue"
},
  "geometry": {"coordinates":[-95.835618,29.845591],"type":"Point"}
}