{
  "type": "Feature",
  "properties": {
    "iso:country":"US",
    "sg:address":"8044 Shoal Creek Blvd",
    "sg:city":"Austin",
    "sg:classifiers":[
        {
            "category":"Health Services",
            "subcategory":"Doctor",
            "type":"Services"
        }
    ],
    "sg:phone":"+1 512 459 1269",
    "sg:postcode":"78757",
    "sg:province":"TX",
    "sg:tags":[
        "physician",
        "surgeon"
    ],
    "wof:name":"Bryan Townsend MD",
    "wof:placetype":"venue"
},
  "geometry": {"coordinates":[-97.739338,30.364625],"type":"Point"}
}