{
  "type": "Feature",
  "properties": {
    "iso:country":"US",
    "sg:address":"1719 Carolyn Way",
    "sg:city":"Richardson",
    "sg:classifiers":[
        {
            "category":"Professional",
            "subcategory":"Management & Consulting",
            "type":"Services"
        }
    ],
    "sg:phone":"+1 972 690 6573",
    "sg:postcode":"75081",
    "sg:province":"TX",
    "wof:name":"Rpw Enterprises",
    "wof:placetype":"venue"
},
  "geometry": {"coordinates":[-96.685304,32.970479],"type":"Point"}
}