{
  "type": "Feature",
  "properties": {
    "iso:country":"US",
    "sg:address":"8720 Lacrosse Dr",
    "sg:city":"Dallas",
    "sg:classifiers":[
        {
            "category":"Professional",
            "subcategory":"Business Services",
            "type":"Services"
        }
    ],
    "sg:phone":"+1 214 340 7764",
    "sg:postcode":"75231",
    "sg:province":"TX",
    "wof:name":"Stoss Design",
    "wof:placetype":"venue"
},
  "geometry": {"coordinates":[-96.738362,32.882038],"type":"Point"}
}