{
  "type": "Feature",
  "properties": {
    "iso:country":"US",
    "sg:address":"2201 Quitsna Ave",
    "sg:city":"Lubbock",
    "sg:classifiers":[
        {
            "category":"Freight",
            "type":"Transportation"
        }
    ],
    "sg:phone":"+1 806 797 8104",
    "sg:postcode":"79407",
    "sg:province":"TX",
    "sg:tags":[
        "storage"
    ],
    "wof:name":"Elm Grove Storage Ctr",
    "wof:placetype":"venue"
},
  "geometry": {"coordinates":[-102.02650300000001,33.573631],"type":"Point"}
}