{
  "type": "Feature",
  "properties": {
    "iso:country":"US",
    "sg:address":"658 Clover Ln",
    "sg:city":"Keller",
    "sg:classifiers":[
        {
            "category":"Real Estate",
            "subcategory":"Real Estate Agent",
            "type":"Services"
        }
    ],
    "sg:phone":"+1 817 337 5411",
    "sg:postcode":"76248",
    "sg:province":"TX",
    "wof:name":"Famous Tree Realty",
    "wof:placetype":"venue"
},
  "geometry": {"coordinates":[-97.236684,32.929114],"type":"Point"}
}