{
  "type": "Feature",
  "properties": {
    "iso:country":"US",
    "sg:address":"3930 Bee Caves Rd Ste 10",
    "sg:city":"Austin",
    "sg:classifiers":[
        {
            "category":"Retail",
            "subcategory":"Pet Boarding",
            "type":"Services"
        }
    ],
    "sg:phone":"+1 512 327 3170",
    "sg:postcode":"78746",
    "sg:province":"TX",
    "sg:tags":[
        "boarding/pet",
        "sitting"
    ],
    "wof:name":"Westlake Animal Hospital Inc",
    "wof:placetype":"venue"
},
  "geometry": {"coordinates":[-97.80909699999999,30.2819],"type":"Point"}
}