{
  "type": "Feature",
  "properties": {
    "iso:country":"US",
    "sg:address":"2508 Mountain Ave",
    "sg:city":"El Paso",
    "sg:classifiers":[
        {
            "category":"Building & Trades",
            "subcategory":"Construction",
            "type":"Services"
        }
    ],
    "sg:phone":"+1 915 562 7889",
    "sg:postcode":"79930",
    "sg:province":"TX",
    "sg:tags":[
        "contractor",
        "laying",
        "floor",
        "covering"
    ],
    "wof:name":"Marios Floor Covering",
    "wof:placetype":"venue"
},
  "geometry": {"coordinates":[-106.466005,31.808662],"type":"Point"}
}