{
  "type": "Feature",
  "properties": {
    "iso:country":"US",
    "sg:address":"1498 Meyer Rd",
    "sg:city":"Seabrook",
    "sg:classifiers":[
        {
            "category":"Wholesale",
            "subcategory":"Machinery & Supplies",
            "type":"Manufacturing & Wholesale Goods"
        }
    ],
    "sg:phone":"+1 281 474 4530",
    "sg:postcode":"77586",
    "sg:province":"TX",
    "sg:tags":[
        "equipment",
        "transportation"
    ],
    "wof:name":"Ameritrac",
    "wof:placetype":"venue"
},
  "geometry": {"coordinates":[-95.021387,29.563955],"type":"Point"}
}