{
  "type": "Feature",
  "properties": {
    "iso:country":"US",
    "sg:address":"1708 Houston Hwy",
    "sg:city":"Victoria",
    "sg:classifiers":[
        {
            "category":"Home & Garden",
            "subcategory":"Mobile Homes",
            "type":"Retail Goods"
        }
    ],
    "sg:phone":"+1 361 575 2520",
    "sg:postcode":"77901",
    "sg:province":"TX",
    "wof:name":"CMH",
    "wof:placetype":"venue"
},
  "geometry": {"coordinates":[-96.983611,28.807989],"type":"Point"}
}