{
  "type": "Feature",
  "properties": {
    "iso:country":"US",
    "sg:address":"220 E Harrison Ave",
    "sg:city":"Harlingen",
    "sg:classifiers":[
        {
            "category":"Shopping",
            "subcategory":"Pharmacy",
            "type":"Retail Goods"
        }
    ],
    "sg:phone":"+1 956 423 3373",
    "sg:postcode":"78550",
    "sg:province":"TX",
    "sg:tags":[
        "equipment"
    ],
    "wof:name":"Mac Phersons Prescription Ctr",
    "wof:placetype":"venue"
},
  "geometry": {"coordinates":[-97.693601,26.190597],"type":"Point"}
}