{
  "type": "Feature",
  "properties": {
    "iso:country":"US",
    "sg:address":"1550 Centeno Ln",
    "sg:city":"Laredo",
    "sg:classifiers":[
        {
            "category":"Building & Trades",
            "subcategory":"Plumbing",
            "type":"Services"
        }
    ],
    "sg:phone":"+1 956 724 8053",
    "sg:postcode":"78046",
    "sg:province":"TX",
    "sg:tags":[
        "plumber",
        "industrial",
        "contractors-commercial"
    ],
    "wof:name":"Carnrizales Plumbing Rosa",
    "wof:placetype":"venue"
},
  "geometry": {"coordinates":[-99.48456899999999,27.365194],"type":"Point"}
}