{
  "type": "Feature",
  "properties": {
    "iso:country":"US",
    "sg:address":"6024B Dashwood Dr",
    "sg:city":"Houston",
    "sg:classifiers":[
        {
            "category":"Social Services",
            "subcategory":"Retirement Home",
            "type":"Services"
        }
    ],
    "sg:phone":"+1 713 432 1877",
    "sg:postcode":"77081",
    "sg:province":"TX",
    "wof:name":"First Class Home Care Services Inc",
    "wof:placetype":"venue"
},
  "geometry": {"coordinates":[-95.487802,29.707338],"type":"Point"}
}