{
  "type": "Feature",
  "properties": {
    "iso:country":"US",
    "sg:address":"419 S Ravinia Dr",
    "sg:city":"Dallas",
    "sg:classifiers":[
        {
            "category":"Health Services",
            "subcategory":"Health Practitioner",
            "type":"Services"
        }
    ],
    "sg:phone":"+1 214 330 5837",
    "sg:postcode":"75211",
    "sg:province":"TX",
    "sg:tags":[
        "pathology",
        "speech"
    ],
    "wof:name":"Donnell F Johns PHD",
    "wof:placetype":"venue"
},
  "geometry": {"coordinates":[-96.86979700000001,32.741728],"type":"Point"}
}