{
  "type": "Feature",
  "properties": {
    "iso:country":"US",
    "sg:address":"1408 W Koenig Ln",
    "sg:city":"Austin",
    "sg:classifiers":[
        {
            "category":"Health Services",
            "subcategory":"Chiropractor",
            "type":"Services"
        }
    ],
    "sg:phone":"+1 512 407 9355",
    "sg:postcode":"78756",
    "sg:province":"TX",
    "wof:name":"Innovative Health & Life Mssg",
    "wof:placetype":"venue"
},
  "geometry": {"coordinates":[-97.73159200000001,30.330871],"type":"Point"}
}