{
  "type": "Feature",
  "properties": {
    "iso:country":"US",
    "sg:address":"4245 Arbor Ln",
    "sg:city":"Carrollton",
    "sg:classifiers":[
        {
            "category":"Building & Trades",
            "subcategory":"Construction",
            "type":"Services"
        }
    ],
    "sg:phone":"+1 972 395 3065",
    "sg:postcode":"75010",
    "sg:province":"TX",
    "sg:tags":[
        "house"
    ],
    "wof:name":"C&W Remodeling",
    "wof:placetype":"venue"
},
  "geometry": {"coordinates":[-96.902086,33.02588],"type":"Point"}
}