{
  "type": "Feature",
  "properties": {
    "iso:country":"US",
    "sg:address":"807 W Pipeline Rd",
    "sg:city":"Hurst",
    "sg:classifiers":[
        {
            "category":"Shopping",
            "subcategory":"Discount & Variety Stores",
            "type":"Retail Goods"
        }
    ],
    "sg:phone":"+1 817 589 7376",
    "sg:postcode":"76053",
    "sg:province":"TX",
    "sg:tags":[
        "merchandise",
        "general"
    ],
    "wof:name":"Gauri Inc",
    "wof:placetype":"venue"
},
  "geometry": {"coordinates":[-97.19056,32.82358],"type":"Point"}
}