{
  "type": "Feature",
  "properties": {
    "iso:country":"US",
    "sg:address":"406 E Safari Pkwy",
    "sg:city":"Grand Prairie",
    "sg:classifiers":[
        {
            "category":"Travel",
            "subcategory":"Hotels & Motels",
            "type":"Entertainment"
        }
    ],
    "sg:phone":"+1 972 642 9424",
    "sg:postcode":"75050",
    "sg:province":"TX",
    "sg:tags":[
        "operation"
    ],
    "wof:name":"Motel 6",
    "wof:placetype":"venue"
},
  "geometry": {"coordinates":[-97.005752,32.761772],"type":"Point"}
}