{
  "type": "Feature",
  "properties": {
    "iso:country":"US",
    "sg:address":"1310 Ave G",
    "sg:city":"South Houston",
    "sg:classifiers":[
        {
            "category":"Banks & Credit Unions",
            "subcategory":"Financial Services",
            "type":"Services"
        }
    ],
    "sg:phone":"+1 713 910 4798",
    "sg:postcode":"77587",
    "sg:province":"TX",
    "sg:tags":[
        "investor"
    ],
    "wof:name":"Jy Investment Company",
    "wof:placetype":"venue"
},
  "geometry": {"coordinates":[-95.21326500000001,29.660703],"type":"Point"}
}