{
  "type": "Feature",
  "properties": {
    "iso:country":"US",
    "sg:address":"10569 Denton Dr",
    "sg:city":"Dallas",
    "sg:classifiers":[
        {
            "category":"Recreation",
            "type":"Entertainment"
        }
    ],
    "sg:phone":"+1 214 358 1128",
    "sg:postcode":"75220",
    "sg:province":"TX",
    "sg:tags":[
        "club",
        "membership"
    ],
    "wof:name":"LA Tanga",
    "wof:placetype":"venue"
},
  "geometry": {"coordinates":[-96.880844,32.870274],"type":"Point"}
}