{
  "type": "Feature",
  "properties": {
    "iso:country":"US",
    "sg:address":"555 Walnut St",
    "sg:city":"Abilene",
    "sg:classifiers":[
        {
            "category":"Government",
            "subcategory":"Office",
            "type":"Public Place"
        }
    ],
    "sg:phone":"+1 325 676 6237",
    "sg:postcode":"79601",
    "sg:province":"TX",
    "sg:tags":[
        "village"
    ],
    "wof:name":"Abilene City Planning Office",
    "wof:placetype":"venue"
},
  "geometry": {"coordinates":[-99.731193,32.453962],"type":"Point"}
}