{
  "type": "Feature",
  "properties": {
    "iso:country":"US",
    "sg:address":"404 N McCoy Blvd",
    "sg:city":"New Boston",
    "sg:classifiers":[
        {
            "category":"Professional",
            "type":"Services"
        }
    ],
    "sg:phone":"+1 903 628 8002",
    "sg:postcode":"75570",
    "sg:province":"TX",
    "sg:tags":[
        "establishment"
    ],
    "wof:name":"Pony Tales",
    "wof:placetype":"venue"
},
  "geometry": {"coordinates":[-94.408502,33.466362],"type":"Point"}
}