{
  "type": "Feature",
  "properties": {
    "iso:country":"US",
    "sg:address":"6727 Co Rd 112 W",
    "sg:city":"Clyde",
    "sg:classifiers":[
        {
            "category":"Organizations",
            "subcategory":"Religious Organization",
            "type":"Services"
        }
    ],
    "sg:phone":"+1 325 893 5482",
    "sg:postcode":"79510",
    "sg:province":"TX",
    "wof:name":"Northside Church of Christ",
    "wof:placetype":"venue"
},
  "geometry": {"coordinates":[-99.505635,32.430752],"type":"Point"}
}