{
  "type": "Feature",
  "properties": {
    "iso:country":"US",
    "sg:address":"15255 Quorum Dr",
    "sg:city":"Addison",
    "sg:classifiers":[
        {
            "category":"Travel",
            "subcategory":"Hotels & Motels",
            "type":"Entertainment"
        }
    ],
    "sg:phone":"+1 972 774 1010",
    "sg:postcode":"75001",
    "sg:province":"TX",
    "wof:name":"Springhill Suites by Marriott",
    "wof:placetype":"venue"
},
  "geometry": {"coordinates":[-96.826992,32.956999],"type":"Point"}
}