{
  "type": "Feature",
  "properties": {
    "iso:country":"US",
    "sg:address":"20 Knoll Cir",
    "sg:city":"Odessa",
    "sg:classifiers":[
        {
            "category":"Building & Trades",
            "subcategory":"Construction",
            "type":"Services"
        }
    ],
    "sg:phone":"+1 432 362 1030",
    "sg:postcode":"79762",
    "sg:province":"TX",
    "sg:tags":[
        "masonry",
        "contractor"
    ],
    "wof:name":"George Rood Masonry",
    "wof:placetype":"venue"
},
  "geometry": {"coordinates":[-102.334419,31.880814],"type":"Point"}
}