{
  "type": "Feature",
  "properties": {
    "iso:country":"US",
    "sg:address":"206 E Frank Ave",
    "sg:city":"Lufkin",
    "sg:classifiers":[
        {
            "category":"Government",
            "subcategory":"Office",
            "type":"Public Place"
        }
    ],
    "sg:phone":"+1 936 634 5431",
    "sg:postcode":"75901",
    "sg:province":"TX",
    "sg:tags":[
        "county",
        "resource"
    ],
    "wof:name":"Angelina County Welfare Dept",
    "wof:placetype":"venue"
},
  "geometry": {"coordinates":[-94.72729699999999,31.339677],"type":"Point"}
}