{
  "type": "Feature",
  "properties": {
    "iso:country":"US",
    "sg:address":"4301 Broadway",
    "sg:city":"San Antonio",
    "sg:classifiers":[
        {
            "category":"Education",
            "subcategory":"Library",
            "type":"Public Place"
        }
    ],
    "sg:phone":"+1 210 829 3835",
    "sg:postcode":"78209",
    "sg:province":"TX",
    "sg:website":"www.uiw.edu",
    "wof:name":"Je & Le Mabee Library",
    "wof:placetype":"venue"
},
  "geometry": {"coordinates":[-98.463644,29.46667],"type":"Point"}
}