{
  "type": "Feature",
  "properties": {
    "iso:country":"US",
    "sg:address":"410 E 42nd St",
    "sg:city":"Houston",
    "sg:classifiers":[
        {
            "category":"Social Services",
            "subcategory":"Child Care",
            "type":"Services"
        }
    ],
    "sg:phone":"+1 281 888 3304",
    "sg:postcode":"77022",
    "sg:province":"TX",
    "sg:tags":[
        "day"
    ],
    "wof:name":"Ambiance Childcare Learning Center",
    "wof:placetype":"venue"
},
  "geometry": {"coordinates":[-95.394598,29.824054],"type":"Point"}
}