{
  "type": "Feature",
  "properties": {
    "iso:country":"US",
    "sg:address":"8401 Gateway Blvd W",
    "sg:city":"El Paso",
    "sg:classifiers":[
        {
            "category":"Wholesale",
            "subcategory":"Electrical",
            "type":"Manufacturing & Wholesale Goods"
        }
    ],
    "sg:phone":"+1 915 843 4343",
    "sg:postcode":"79935",
    "sg:province":"TX",
    "sg:tags":[
        "communication",
        "radio",
        "system"
    ],
    "wof:name":"First Choice Wireless",
    "wof:placetype":"venue"
},
  "geometry": {"coordinates":[-106.382199,31.774207],"type":"Point"}
}