{
  "type": "Feature",
  "properties": {
    "iso:country":"US",
    "sg:address":"11715 W Bellfort St",
    "sg:city":"Stafford",
    "sg:classifiers":[
        {
            "category":"Food & Beverages",
            "subcategory":"Meat & Fish",
            "type":"Retail Goods"
        }
    ],
    "sg:phone":"+1 281 498 4418",
    "sg:postcode":"77477",
    "sg:province":"TX",
    "sg:tags":[
        "seafood"
    ],
    "wof:name":"New State Seafood",
    "wof:placetype":"venue"
},
  "geometry": {"coordinates":[-95.584148,29.657648],"type":"Point"}
}