{
  "type": "Feature",
  "properties": {
    "iso:country":"US",
    "sg:address":"1314 6th St",
    "sg:city":"Ingleside",
    "sg:classifiers":[
        {
            "category":"Manufacturing",
            "subcategory":"Glass & Minerals",
            "type":"Manufacturing & Wholesale Goods"
        }
    ],
    "sg:phone":"+1 361 776 7753",
    "sg:postcode":"78362",
    "sg:province":"TX",
    "sg:tags":[
        "fabricator",
        "fiber"
    ],
    "wof:name":"Rowland Fiberglass Inc",
    "wof:placetype":"venue"
},
  "geometry": {"coordinates":[-97.192455,27.859931],"type":"Point"}
}