{
  "type": "Feature",
  "properties": {
    "iso:country":"US",
    "sg:address":"2612 Green Tree Ln",
    "sg:city":"Flower Mound",
    "sg:classifiers":[
        {
            "category":"Professional",
            "subcategory":"Business Services",
            "type":"Services"
        }
    ],
    "sg:phone":"+1 817 430 8754",
    "sg:postcode":"75022",
    "sg:province":"TX",
    "wof:name":"J Mueller Design Associates",
    "wof:placetype":"venue"
},
  "geometry": {"coordinates":[-97.14904199999999,33.022969],"type":"Point"}
}