{
  "type": "Feature",
  "properties": {
    "iso:country":"US",
    "sg:address":"5303 Antoine Dr",
    "sg:city":"Houston",
    "sg:classifiers":[
        {
            "category":"Cinema",
            "subcategory":"Movie Rental",
            "type":"Entertainment"
        }
    ],
    "sg:phone":"+1 713 682 1917",
    "sg:postcode":"77091",
    "sg:province":"TX",
    "sg:tags":[
        "video",
        "game",
        "disc",
        "leasing",
        "tape"
    ],
    "wof:name":"E T Video",
    "wof:placetype":"venue"
},
  "geometry": {"coordinates":[-95.47339599999999,29.8417],"type":"Point"}
}