{
  "type": "Feature",
  "properties": {
    "iso:country":"US",
    "sg:address":"5624 Newman Dr",
    "sg:city":"Fort Worth",
    "sg:classifiers":[
        {
            "category":"Professional",
            "subcategory":"Management & Consulting",
            "type":"Services"
        }
    ],
    "sg:phone":"+1 817 581 6580",
    "sg:postcode":"76180",
    "sg:province":"TX",
    "sg:tags":[
        "marketing",
        "consultant"
    ],
    "wof:name":"D F W Marketing & Consulting",
    "wof:placetype":"venue"
},
  "geometry": {"coordinates":[-97.203896,32.848899],"type":"Point"}
}