{
  "type": "Feature",
  "properties": {
    "iso:country":"US",
    "sg:address":"9717 Pepperwood Trl",
    "sg:city":"Denton",
    "sg:classifiers":[
        {
            "category":"Manufacturing",
            "subcategory":"Wood Products",
            "type":"Manufacturing & Wholesale Goods"
        }
    ],
    "sg:phone":"+1 940 262 3023",
    "sg:postcode":"76207",
    "sg:province":"TX",
    "sg:tags":[
        "millwork"
    ],
    "wof:name":"Red River Millwork",
    "wof:placetype":"venue"
},
  "geometry": {"coordinates":[-97.228408,33.137252],"type":"Point"}
}