{
  "type": "Feature",
  "properties": {
    "iso:country":"US",
    "sg:address":"22803 Acorn Valley Dr",
    "sg:city":"Spring",
    "sg:classifiers":[
        {
            "category":"Real Estate",
            "subcategory":"Real Estate Agent",
            "type":"Services"
        }
    ],
    "sg:phone":"+1 281 355 8212",
    "sg:postcode":"77389",
    "sg:province":"TX",
    "sg:tags":[
        "broker"
    ],
    "wof:name":"Charlotte Gilpin Realtors",
    "wof:placetype":"venue"
},
  "geometry": {"coordinates":[-95.474957,30.095071],"type":"Point"}
}