{
  "type": "Feature",
  "properties": {
    "iso:country":"US",
    "sg:address":"30810 Beyette Rd",
    "sg:city":"Magnolia",
    "sg:classifiers":[
        {
            "category":"Travel",
            "subcategory":"Travel Agent",
            "type":"Entertainment"
        }
    ],
    "sg:phone":"+1 281 259 3637",
    "sg:postcode":"77355",
    "sg:province":"TX",
    "sg:tags":[
        "agency",
        "bureau"
    ],
    "sg:website":"www.magnoliatravels.com",
    "wof:name":"MAGNOLIATRAVELS.COM",
    "wof:placetype":"venue"
},
  "geometry": {"coordinates":[-95.72174,30.18967],"type":"Point"}
}