{
  "type": "Feature",
  "properties": {
    "iso:country":"US",
    "sg:address":"539 Clayton St",
    "sg:city":"Grand Prairie",
    "sg:classifiers":[
        {
            "category":"Retail",
            "subcategory":"Laundry & Dry Cleaning",
            "type":"Services"
        }
    ],
    "sg:phone":"+1 972 264 4342",
    "sg:postcode":"75052",
    "sg:province":"TX",
    "sg:tags":[
        "garment",
        "agent"
    ],
    "wof:name":"N & D Enterprises Inc",
    "wof:placetype":"venue"
},
  "geometry": {"coordinates":[-97.000433,32.667392],"type":"Point"}
}