{
  "type": "Feature",
  "properties": {
    "iso:country":"US",
    "sg:address":"5911 Broadway",
    "sg:city":"San Antonio",
    "sg:classifiers":[
        {
            "category":"Shopping",
            "subcategory":"Bicycles & Sporting Goods",
            "type":"Retail Goods"
        }
    ],
    "sg:phone":"+1 210 828 5558",
    "sg:postcode":"78209",
    "sg:province":"TX",
    "sg:tags":[
        "shop",
        "mail",
        "parts",
        "e",
        "order"
    ],
    "wof:name":"Bike World",
    "wof:placetype":"venue"
},
  "geometry": {"coordinates":[-98.465633,29.481765],"type":"Point"}
}