{
  "type": "Feature",
  "properties": {
    "iso:country":"US",
    "sg:address":"1000 Guadalupe St Room 421",
    "sg:city":"Austin",
    "sg:classifiers":[
        {
            "category":"Landmark",
            "subcategory":"Historic",
            "type":"Public Place"
        }
    ],
    "sg:phone":"+1 512 854 9308",
    "sg:postcode":"78701",
    "sg:province":"TX",
    "sg:tags":[
        "building",
        "historical"
    ],
    "sg:website":"www.co.travis.tx.us/courts/civil...",
    "wof:name":"Travis County 53rd Judicial District Civil Court",
    "wof:placetype":"venue"
},
  "geometry": {"coordinates":[-97.74499,30.272967],"type":"Point"}
}