{
  "type": "Feature",
  "properties": {
    "iso:country":"US",
    "sg:address":"1820 S Berlin Rd",
    "sg:city":"Brenham",
    "sg:classifiers":[
        {
            "category":"Insurance",
            "subcategory":"Hazard Insurance",
            "type":"Services"
        }
    ],
    "sg:phone":"+1 979 830 1344",
    "sg:postcode":"77833",
    "sg:province":"TX",
    "wof:name":"Arthur Joswiak",
    "wof:placetype":"venue"
},
  "geometry": {"coordinates":[-96.459847,30.149562],"type":"Point"}
}