{
  "type": "Feature",
  "properties": {
    "iso:country":"US",
    "sg:address":"9554 Campton Farms",
    "sg:city":"San Antonio",
    "sg:classifiers":[
        {
            "category":"Building & Trades",
            "subcategory":"Landscaping Services",
            "type":"Services"
        }
    ],
    "sg:phone":"+1 210 680 8069",
    "sg:postcode":"78250",
    "sg:province":"TX",
    "sg:tags":[
        "landscape"
    ],
    "wof:name":"Williams Landscaping",
    "wof:placetype":"venue"
},
  "geometry": {"coordinates":[-98.67225999999999,29.502765],"type":"Point"}
}