{
  "type": "Feature",
  "properties": {
    "iso:country":"US",
    "sg:address":"3403 US Hwy 90",
    "sg:city":"Schulenburg",
    "sg:classifiers":[
        {
            "category":"Home & Garden",
            "subcategory":"Home Furnishings",
            "type":"Retail Goods"
        }
    ],
    "sg:phone":"+1 979 561 8541",
    "sg:postcode":"78956",
    "sg:province":"TX",
    "sg:tags":[
        "beveled",
        "glass",
        "ornamental"
    ],
    "wof:name":"Fostoria Glass LLC",
    "wof:placetype":"venue"
},
  "geometry": {"coordinates":[-96.84441,29.695646],"type":"Point"}
}