{
  "type": "Feature",
  "properties": {
    "iso:country":"US",
    "sg:address":"10714 Lennox Ln",
    "sg:city":"Dallas",
    "sg:classifiers":[
        {
            "category":"Education",
            "subcategory":"Special Training",
            "type":"Public Place"
        }
    ],
    "sg:phone":"+1 972 974 7744",
    "sg:postcode":"75229",
    "sg:province":"TX",
    "sg:tags":[
        "career",
        "vocational",
        "counseling"
    ],
    "wof:name":"Julie Hersh",
    "wof:placetype":"venue"
},
  "geometry": {"coordinates":[-96.827629,32.893188],"type":"Point"}
}