{
  "type": "Feature",
  "properties": {
    "iso:country":"US",
    "sg:address":"6125 W Park Blvd",
    "sg:city":"Plano",
    "sg:classifiers":[
        {
            "category":"Shopping",
            "subcategory":"Beauty & Cosmetics",
            "type":"Retail Goods"
        }
    ],
    "sg:phone":"+1 972 473 7771",
    "sg:postcode":"75093",
    "sg:province":"TX",
    "sg:tags":[
        "supply"
    ],
    "sg:website":"www.beautybrands.com",
    "wof:name":"Beauty Brands",
    "wof:placetype":"venue"
},
  "geometry": {"coordinates":[-96.833989,33.028164],"type":"Point"}
}