{
  "type": "Feature",
  "properties": {
    "iso:country":"US",
    "sg:address":"3317 McKinney Ave #207",
    "sg:city":"Dallas",
    "sg:classifiers":[
        {
            "category":"Real Estate",
            "subcategory":"Real Estate Operator",
            "type":"Services"
        }
    ],
    "sg:phone":"+1 214 527 7080",
    "sg:postcode":"75204",
    "sg:province":"TX",
    "sg:tags":[
        "apartment"
    ],
    "sg:website":"dfwapartmentfinder.blogspot.com/",
    "wof:name":"Apartment Finder - Dallas",
    "wof:placetype":"venue"
},
  "geometry": {"coordinates":[-96.79926,32.805062],"type":"Point"}
}