{
  "type": "Feature",
  "properties": {
    "iso:country":"US",
    "sg:address":"6702 Blue Ridge Dr",
    "sg:city":"Richmond",
    "sg:classifiers":[
        {
            "category":"Building & Trades",
            "subcategory":"Construction",
            "type":"Services"
        }
    ],
    "sg:phone":"+1 281 343 9410",
    "sg:postcode":"77469",
    "sg:province":"TX",
    "sg:tags":[
        "contractor"
    ],
    "wof:name":"A J C Powerwash",
    "wof:placetype":"venue"
},
  "geometry": {"coordinates":[-95.697305,29.542614],"type":"Point"}
}