{
  "type": "Feature",
  "properties": {
    "iso:country":"US",
    "sg:address":"3807 Southwest Blvd",
    "sg:city":"Fort Worth",
    "sg:classifiers":[
        {
            "category":"Recreation",
            "type":"Entertainment"
        },
        {
            "category":"Shopping",
            "subcategory":"Bicycles & Sporting Goods",
            "type":"Retail Goods"
        }
    ],
    "sg:phone":"+1 817 732 5761",
    "sg:postcode":"76116",
    "sg:province":"TX",
    "sg:tags":[
        "diving",
        "travel",
        "instruction",
        "scuba",
        "gear"
    ],
    "sg:website":"www.scubadivingfortworth.com",
    "wof:name":"Divers-Scuba Supply Ft Worth",
    "wof:placetype":"venue"
},
  "geometry": {"coordinates":[-97.441593,32.716496],"type":"Point"}
}