{
  "type": "Feature",
  "properties": {
    "iso:country":"US",
    "sg:address":"8300 Bissonnet St",
    "sg:city":"Houston",
    "sg:classifiers":[
        {
            "category":"Health Services",
            "subcategory":"Health Practitioner",
            "type":"Services"
        }
    ],
    "sg:phone":"+1 281 835 4868",
    "sg:postcode":"77074",
    "sg:province":"TX",
    "sg:tags":[
        "pathologist",
        "speech"
    ],
    "wof:name":"D W Health Therapy",
    "wof:placetype":"venue"
},
  "geometry": {"coordinates":[-95.52428399999999,29.67905],"type":"Point"}
}