{
  "type": "Feature",
  "properties": {
    "iso:country":"US",
    "sg:address":"219 River Oaks",
    "sg:city":"Seagoville",
    "sg:classifiers":[
        {
            "category":"Real Estate",
            "subcategory":"Architect",
            "type":"Services"
        }
    ],
    "sg:phone":"+1 214 395 6015",
    "sg:postcode":"75159",
    "sg:province":"TX",
    "sg:tags":[
        "architectural"
    ],
    "wof:name":"3j Design Pllc",
    "wof:placetype":"venue"
},
  "geometry": {"coordinates":[-96.498563,32.591517],"type":"Point"}
}