{
  "type": "Feature",
  "properties": {
    "iso:country":"US",
    "sg:address":"12 S Cliffwood Dr",
    "sg:city":"Belton",
    "sg:classifiers":[
        {
            "category":"Communications",
            "subcategory":"Film & Video Production",
            "type":"Services"
        }
    ],
    "sg:phone":"+1 254 780 3780",
    "sg:postcode":"76513",
    "sg:province":"TX",
    "sg:tags":[
        "motion"
    ],
    "wof:name":"Triple B Production",
    "wof:placetype":"venue"
},
  "geometry": {"coordinates":[-97.47845100000001,31.153813],"type":"Point"}
}