{
  "type": "Feature",
  "properties": {
    "iso:country":"US",
    "sg:address":"2019 Berkley Dr",
    "sg:city":"Wichita Falls",
    "sg:classifiers":[
        {
            "category":"Professional",
            "subcategory":"Business Services",
            "type":"Services"
        }
    ],
    "sg:phone":"+1 940 767 3417",
    "sg:postcode":"76308",
    "sg:province":"TX",
    "wof:name":"Louett Co",
    "wof:placetype":"venue"
},
  "geometry": {"coordinates":[-98.511493,33.885179],"type":"Point"}
}