{
  "type": "Feature",
  "properties": {
    "iso:country":"US",
    "sg:address":"4730 Pederson St",
    "sg:city":"Houston",
    "sg:classifiers":[
        {
            "category":"Organizations",
            "subcategory":"Religious Organization",
            "type":"Services"
        }
    ],
    "sg:phone":"+1 713 734 2260",
    "sg:postcode":"77033",
    "sg:province":"TX",
    "sg:tags":[
        "church"
    ],
    "sg:website":"www.mount-moriah.com",
    "wof:name":"Mount Moriah Baptist Church",
    "wof:placetype":"venue"
},
  "geometry": {"coordinates":[-95.35480699999999,29.65341],"type":"Point"}
}