{
  "type": "Feature",
  "properties": {
    "iso:country":"US",
    "sg:address":"1592 Huntsman St",
    "sg:city":"Orange",
    "sg:classifiers":[
        {
            "category":"Building & Trades",
            "subcategory":"Landscaping Services",
            "type":"Services"
        }
    ],
    "sg:phone":"+1 409 883 2381",
    "sg:postcode":"77632",
    "sg:province":"TX",
    "sg:tags":[
        "lawn",
        "maintenance",
        "grounds"
    ],
    "wof:name":"Pat's Lawn Svc",
    "wof:placetype":"venue"
},
  "geometry": {"coordinates":[-93.763593,30.156665],"type":"Point"}
}