{
  "type": "Feature",
  "properties": {
    "iso:country":"US",
    "sg:address":"1213 14th St",
    "sg:city":"Galveston",
    "sg:classifiers":[
        {
            "category":"Building & Trades",
            "subcategory":"Plumbing",
            "type":"Services"
        }
    ],
    "sg:phone":"+1 409 935 5100",
    "sg:postcode":"77550",
    "sg:province":"TX",
    "sg:tags":[
        "conditioning",
        "air",
        "system",
        "contractor"
    ],
    "wof:name":"Bosworth Air Conditioning Inc",
    "wof:placetype":"venue"
},
  "geometry": {"coordinates":[-94.781004,29.300545],"type":"Point"}
}