{
  "type": "Feature",
  "properties": {
    "iso:country":"US",
    "sg:address":"2517 Weaver St",
    "sg:city":"Haltom City",
    "sg:classifiers":[
        {
            "category":"Wholesale",
            "subcategory":"Electrical",
            "type":"Manufacturing & Wholesale Goods"
        }
    ],
    "sg:phone":"+1 817 222 3741",
    "sg:postcode":"76117",
    "sg:province":"TX",
    "sg:tags":[
        "equipment",
        "lighting",
        "system"
    ],
    "sg:website":"www.wtlighting.com",
    "wof:name":"W T Lighting",
    "wof:placetype":"venue"
},
  "geometry": {"coordinates":[-97.247167,32.800791],"type":"Point"}
}