{
  "type": "Feature",
  "properties": {
    "iso:country":"US",
    "sg:address":"824 E Broad St",
    "sg:city":"Mineola",
    "sg:classifiers":[
        {
            "category":"Retail",
            "subcategory":"Auto Repair",
            "type":"Services"
        }
    ],
    "sg:phone":"+1 903 569 9189",
    "sg:postcode":"75773",
    "sg:province":"TX",
    "sg:tags":[
        "body",
        "automobile",
        "painting"
    ],
    "wof:name":"Lee's Used Cars",
    "wof:placetype":"venue"
},
  "geometry": {"coordinates":[-95.47948,32.660944],"type":"Point"}
}