{
  "type": "Feature",
  "properties": {
    "iso:country":"US",
    "sg:address":"302 W 11th St",
    "sg:city":"Houston",
    "sg:classifiers":[
        {
            "category":"Personal",
            "subcategory":"Beauty Salon",
            "type":"Services"
        }
    ],
    "sg:phone":"+1 713 864 3177",
    "sg:postcode":"77008",
    "sg:province":"TX",
    "wof:name":"Dino's Hair Design",
    "wof:placetype":"venue"
},
  "geometry": {"coordinates":[-95.401141,29.790572],"type":"Point"}
}