{
  "type": "Feature",
  "properties": {
    "iso:country":"US",
    "sg:address":"6319 Fawnwood Dr",
    "sg:city":"Spring",
    "sg:classifiers":[
        {
            "category":"Restaurant",
            "type":"Food & Drink"
        }
    ],
    "sg:phone":"+1 281 320 9897",
    "sg:postcode":"77389",
    "sg:province":"TX",
    "sg:tags":[
        "eating"
    ],
    "wof:name":"Remember Expresso",
    "wof:placetype":"venue"
},
  "geometry": {"coordinates":[-95.517278,30.106657],"type":"Point"}
}