{
  "type": "Feature",
  "properties": {
    "iso:country":"US",
    "sg:address":"621 Rollingbrook St Ste 1",
    "sg:city":"Baytown",
    "sg:classifiers":[
        {
            "category":"Personal",
            "subcategory":"Beauty Salon",
            "type":"Services"
        }
    ],
    "sg:phone":"+1 281 427 6360",
    "sg:postcode":"77521",
    "sg:province":"TX",
    "wof:name":"Excellence New Image Inc",
    "wof:placetype":"venue"
},
  "geometry": {"coordinates":[-94.97154999999999,29.76136],"type":"Point"}
}