{
  "type": "Feature",
  "properties": {
    "iso:country":"US",
    "sg:address":"7333 Strawberry Way",
    "sg:city":"Fort Worth",
    "sg:classifiers":[
        {
            "category":"Building & Trades",
            "subcategory":"Landscaping Services",
            "type":"Services"
        }
    ],
    "sg:phone":"+1 817 847 6092",
    "sg:postcode":"76137",
    "sg:province":"TX",
    "wof:name":"Strong Lawn Services",
    "wof:placetype":"venue"
},
  "geometry": {"coordinates":[-97.29804,32.872327],"type":"Point"}
}