{
  "type": "Feature",
  "properties": {
    "iso:country":"US",
    "sg:address":"2110 E US Hwy 80",
    "sg:city":"White Oak",
    "sg:classifiers":[
        {
            "category":"Building & Trades",
            "subcategory":"Equipment Rental",
            "type":"Services"
        }
    ],
    "sg:phone":"+1 903 759 6684",
    "sg:postcode":"75693",
    "sg:province":"TX",
    "sg:tags":[
        "yard"
    ],
    "wof:name":"Pappy's Trailer Sales & Rental",
    "wof:placetype":"venue"
},
  "geometry": {"coordinates":[-94.833378,32.512771],"type":"Point"}
}