{
  "type": "Feature",
  "properties": {
    "iso:country":"US",
    "sg:address":"616 Valle Vista Ct",
    "sg:city":"Keller",
    "sg:classifiers":[
        {
            "category":"Professional",
            "type":"Services"
        }
    ],
    "sg:phone":"+1 817 431 8664",
    "sg:postcode":"76248",
    "sg:province":"TX",
    "wof:name":"Gunfighters",
    "wof:placetype":"venue"
},
  "geometry": {"coordinates":[-97.237714,32.951389],"type":"Point"}
}