{
  "type": "Feature",
  "properties": {
    "iso:country":"US",
    "sg:address":"1007 N Mallard St",
    "sg:city":"Palestine",
    "sg:classifiers":[
        {
            "category":"Professional",
            "subcategory":"Credit Reporting & Collection",
            "type":"Services"
        }
    ],
    "sg:phone":"+1 903 729 6036",
    "sg:postcode":"75801",
    "sg:province":"TX",
    "sg:tags":[
        "agency"
    ],
    "wof:name":"Retail Merchant Assn",
    "wof:placetype":"venue"
},
  "geometry": {"coordinates":[-95.627877,31.770314],"type":"Point"}
}