{
  "type": "Feature",
  "properties": {
    "iso:country":"US",
    "sg:address":"6805 Boeing Dr",
    "sg:city":"El Paso",
    "sg:classifiers":[
        {
            "category":"Airport",
            "type":"Transportation"
        }
    ],
    "sg:phone":"+1 915 772 2900",
    "sg:postcode":"79925",
    "sg:province":"TX",
    "sg:tags":[
        "aircraft"
    ],
    "wof:name":"JAS Inc",
    "wof:placetype":"venue"
},
  "geometry": {"coordinates":[-106.38747600000001,31.792448],"type":"Point"}
}