{
  "type": "Feature",
  "properties": {
    "iso:country":"US",
    "sg:address":"50 Longsford",
    "sg:city":"San Antonio",
    "sg:classifiers":[
        {
            "category":"Building & Trades",
            "subcategory":"Construction",
            "type":"Services"
        }
    ],
    "sg:phone":"+1 210 930 4299",
    "sg:postcode":"78209",
    "sg:province":"TX",
    "sg:tags":[
        "special",
        "contractor"
    ],
    "wof:name":"Med Gas By Design Inc",
    "wof:placetype":"venue"
},
  "geometry": {"coordinates":[-98.471265,29.496973],"type":"Point"}
}