{
  "type": "Feature",
  "properties": {
    "iso:country":"US",
    "sg:address":"711 Bay Area Blvd",
    "sg:city":"Houston",
    "sg:classifiers":[
        {
            "category":"Banks & Credit Unions",
            "subcategory":"Bank",
            "type":"Services"
        }
    ],
    "sg:phone":"+1 281 218 6760",
    "sg:postcode":"77058",
    "sg:province":"TX",
    "sg:tags":[
        "mortgage"
    ],
    "wof:name":"Ameriquest Mortgage",
    "wof:placetype":"venue"
},
  "geometry": {"coordinates":[-95.127787,29.549623],"type":"Point"}
}