{
  "type": "Feature",
  "properties": {
    "iso:country":"US",
    "sg:address":"6004 Paradise Dr",
    "sg:city":"Arlington",
    "sg:classifiers":[
        {
            "category":"Organizations",
            "subcategory":"Non-profit Organization",
            "type":"Services"
        }
    ],
    "sg:phone":"+1 817 483 7714",
    "sg:postcode":"76001",
    "sg:province":"TX",
    "sg:tags":[
        "breastfeeding",
        "information",
        "supply"
    ],
    "wof:name":"Lactation Connection",
    "wof:placetype":"venue"
},
  "geometry": {"coordinates":[-97.16987,32.648997],"type":"Point"}
}