{
  "type": "Feature",
  "properties": {
    "iso:country":"US",
    "sg:address":"510 N Crockett St",
    "sg:city":"Granbury",
    "sg:classifiers":[
        {
            "category":"Real Estate",
            "subcategory":"Real Estate Operator",
            "type":"Services"
        }
    ],
    "sg:phone":"+1 817 579 5182",
    "sg:postcode":"76048",
    "sg:province":"TX",
    "sg:tags":[
        "building",
        "apartment"
    ],
    "wof:name":"Cricket Hollow Apartments",
    "wof:placetype":"venue"
},
  "geometry": {"coordinates":[-97.78646500000001,32.44753],"type":"Point"}
}