{
  "type": "Feature",
  "properties": {
    "iso:country":"US",
    "sg:address":"12610 Riata Trace Pkwy",
    "sg:city":"Austin",
    "sg:classifiers":[
        {
            "category":"Real Estate",
            "subcategory":"Real Estate Operator",
            "type":"Services"
        },
        {
            "category":"Wholesale",
            "subcategory":"Non-durable Goods",
            "type":"Manufacturing & Wholesale Goods"
        }
    ],
    "sg:phone":"+1 512 437 1777",
    "sg:postcode":"78727",
    "sg:province":"TX",
    "sg:tags":[
        "apartment"
    ],
    "wof:name":"Miles Mark At Riata",
    "wof:placetype":"venue"
},
  "geometry": {"coordinates":[-97.739525,30.431312],"type":"Point"}
}