{
  "type": "Feature",
  "properties": {
    "iso:country":"US",
    "sg:address":"701 Melbourne St",
    "sg:city":"Houston",
    "sg:classifiers":[
        {
            "category":"Professional",
            "subcategory":"Lawyer & Legal Services",
            "type":"Services"
        }
    ],
    "sg:phone":"+1 713 695 4774",
    "sg:postcode":"77022",
    "sg:province":"TX",
    "wof:name":"Quintero Helen Atty",
    "wof:placetype":"venue"
},
  "geometry": {"coordinates":[-95.361,29.8165],"type":"Point"}
}