{
  "type": "Feature",
  "properties": {
    "iso:country":"US",
    "sg:address":"409 S 1st St",
    "sg:city":"Lamesa",
    "sg:classifiers":[
        {
            "category":"Personal",
            "subcategory":"Beauty Salon",
            "type":"Services"
        }
    ],
    "sg:phone":"+1 806 872 2378",
    "sg:postcode":"79331",
    "sg:province":"TX",
    "sg:tags":[
        "shop"
    ],
    "wof:name":"Hairsations",
    "wof:placetype":"venue"
},
  "geometry": {"coordinates":[-101.951553,32.732069],"type":"Point"}
}