{
  "type": "Feature",
  "properties": {
    "iso:country":"US",
    "sg:address":"140 Market St",
    "sg:city":"Georgetown",
    "sg:classifiers":[
        {
            "category":"Building & Trades",
            "subcategory":"Construction",
            "type":"Services"
        }
    ],
    "sg:phone":"+1 512 864 2723",
    "sg:postcode":"78626",
    "sg:province":"TX",
    "sg:tags":[
        "contractor"
    ],
    "sg:website":"www.dorseycc.com",
    "wof:name":"Dorsey Construction Corp",
    "wof:placetype":"venue"
},
  "geometry": {"coordinates":[-97.648201,30.691564],"type":"Point"}
}