{
  "type": "Feature",
  "properties": {
    "iso:country":"US",
    "sg:address":"16815 Pescador",
    "sg:city":"Helotes",
    "sg:classifiers":[
        {
            "category":"Building & Trades",
            "subcategory":"Cleaning & Sanitation",
            "type":"Services"
        }
    ],
    "sg:phone":"+1 210 695 2009",
    "sg:postcode":"78023",
    "sg:province":"TX",
    "sg:tags":[
        "food",
        "custodial",
        "grounds"
    ],
    "wof:name":"Apollo Contract Services LP",
    "wof:placetype":"venue"
},
  "geometry": {"coordinates":[-98.71689000000001,29.599306],"type":"Point"}
}