{
  "type": "Feature",
  "properties": {
    "iso:country":"US",
    "sg:address":"701 W Marshall Ave",
    "sg:city":"Longview",
    "sg:classifiers":[
        {
            "category":"Banks & Credit Unions",
            "subcategory":"Bank",
            "type":"Services"
        }
    ],
    "sg:phone":"+1 903 758 1957",
    "sg:postcode":"75601",
    "sg:province":"TX",
    "wof:name":"Southside Bank",
    "wof:placetype":"venue"
},
  "geometry": {"coordinates":[-94.750007,32.499156],"type":"Point"}
}