{
  "type": "Feature",
  "properties": {
    "iso:country":"US",
    "sg:address":"1301 Green Ave",
    "sg:city":"Orange",
    "sg:classifiers":[
        {
            "category":"Shopping",
            "subcategory":"Florist",
            "type":"Retail Goods"
        }
    ],
    "sg:phone":"+1 409 883 5629",
    "sg:postcode":"77630",
    "sg:province":"TX",
    "wof:name":"Black's Orange Floral Shop",
    "wof:placetype":"venue"
},
  "geometry": {"coordinates":[-93.74351299999999,30.093061],"type":"Point"}
}