{
  "type": "Feature",
  "properties": {
    "iso:country":"US",
    "sg:address":"434 Mullins Ave",
    "sg:city":"Lewisville",
    "sg:classifiers":[
        {
            "category":"Shopping",
            "subcategory":"Pets & Pet Supplies",
            "type":"Retail Goods"
        }
    ],
    "sg:phone":"+1 214 604 6681",
    "sg:postcode":"75057",
    "sg:province":"TX",
    "sg:tags":[
        "supplies-leasing",
        "aquarium",
        "maintenance"
    ],
    "wof:name":"Lone Star Aquarium Service",
    "wof:placetype":"venue"
},
  "geometry": {"coordinates":[-97.00367,33.050315],"type":"Point"}
}