{
  "type": "Feature",
  "properties": {
    "iso:country":"US",
    "sg:address":"4311 Pan American Blvd",
    "sg:city":"Laredo",
    "sg:classifiers":[
        {
            "category":"Professional",
            "type":"Services"
        }
    ],
    "sg:phone":"+1 956 725 7948",
    "sg:postcode":"78045",
    "sg:province":"TX",
    "wof:name":"Manzanedo Lzano Lnardo Esteban",
    "wof:placetype":"venue"
},
  "geometry": {"coordinates":[-99.53928999999999,27.634004],"type":"Point"}
}