{
  "type": "Feature",
  "properties": {
    "iso:country":"US",
    "sg:address":"1426 W Hildebrand Ave",
    "sg:city":"San Antonio",
    "sg:classifiers":[
        {
            "category":"Building & Trades",
            "subcategory":"Construction",
            "type":"Services"
        }
    ],
    "sg:phone":"+1 210 733 0161",
    "sg:postcode":"78201",
    "sg:province":"TX",
    "sg:tags":[
        "contractor"
    ],
    "wof:name":"Shhs Corporation",
    "wof:placetype":"venue"
},
  "geometry": {"coordinates":[-98.51709099999999,29.466371],"type":"Point"}
}