{
  "type": "Feature",
  "properties": {
    "iso:country":"US",
    "sg:address":"605 W 4th St",
    "sg:city":"Cameron",
    "sg:classifiers":[
        {
            "category":"Professional",
            "subcategory":"Employment Agencies",
            "type":"Services"
        }
    ],
    "sg:phone":"+1 254 697 3373",
    "sg:postcode":"76520",
    "sg:province":"TX",
    "sg:tags":[
        "opportunity"
    ],
    "wof:name":"Texas Workforce Commission",
    "wof:placetype":"venue"
},
  "geometry": {"coordinates":[-96.980818,30.854278],"type":"Point"}
}