{
  "type": "Feature",
  "properties": {
    "iso:country":"US",
    "sg:address":"1010 Foster St",
    "sg:city":"San Angelo",
    "sg:classifiers":[
        {
            "category":"Home & Garden",
            "subcategory":"Furniture",
            "type":"Retail Goods"
        }
    ],
    "sg:phone":"+1 325 658 7215",
    "sg:postcode":"76903",
    "sg:province":"TX",
    "wof:name":"Texas Forge & Furniture",
    "wof:placetype":"venue"
},
  "geometry": {"coordinates":[-100.448857,31.434235],"type":"Point"}
}