{
  "type": "Feature",
  "properties": {
    "iso:country":"US",
    "sg:address":"8606 Wall St",
    "sg:city":"Austin",
    "sg:classifiers":[
        {
            "category":"Freight",
            "type":"Transportation"
        }
    ],
    "sg:phone":"+1 512 491 8610",
    "sg:postcode":"78754",
    "sg:province":"TX",
    "sg:tags":[
        "arrangement"
    ],
    "wof:name":"Expeditors Intl Wash Inc",
    "wof:placetype":"venue"
},
  "geometry": {"coordinates":[-97.669777,30.342519],"type":"Point"}
}