{
  "type": "Feature",
  "properties": {
    "iso:country":"US",
    "sg:address":"1364 Martin Luther King Dr",
    "sg:city":"Center",
    "sg:classifiers":[
        {
            "category":"Farming",
            "subcategory":"Poultry Farm",
            "type":"Manufacturing & Wholesale Goods"
        }
    ],
    "sg:phone":"+1 936 598 5506",
    "sg:postcode":"75935",
    "sg:province":"TX",
    "wof:name":"Qt Poultry Inc",
    "wof:placetype":"venue"
},
  "geometry": {"coordinates":[-94.167435,31.789815],"type":"Point"}
}