{
  "type": "Feature",
  "properties": {
    "iso:country":"US",
    "sg:address":"2609 FM 765",
    "sg:city":"San Angelo",
    "sg:classifiers":[
        {
            "category":"Banks & Credit Unions",
            "subcategory":"Financial Services",
            "type":"Services"
        }
    ],
    "sg:phone":"+1 325 651 7292",
    "sg:postcode":"76905",
    "sg:province":"TX",
    "sg:tags":[
        "trust",
        "management"
    ],
    "wof:name":"Blake Living Trust",
    "wof:placetype":"venue"
},
  "geometry": {"coordinates":[-100.399253,31.418636],"type":"Point"}
}