{
  "type": "Feature",
  "properties": {
    "iso:country":"US",
    "sg:address":"1821 Thornton St",
    "sg:city":"Mission",
    "sg:classifiers":[
        {
            "category":"Professional",
            "subcategory":"Accounting & Tax Preparation",
            "type":"Services"
        }
    ],
    "sg:phone":"+1 956 585 2161",
    "sg:postcode":"78572",
    "sg:province":"TX",
    "sg:tags":[
        "accountant"
    ],
    "wof:name":"Arturo Longoria CPA",
    "wof:placetype":"venue"
},
  "geometry": {"coordinates":[-98.32927100000001,26.226469],"type":"Point"}
}