{
  "type": "Feature",
  "properties": {
    "iso:country":"US",
    "sg:address":"405 Magnolia St",
    "sg:city":"Denton",
    "sg:classifiers":[
        {
            "category":"Organizations",
            "subcategory":"Professional Association",
            "type":"Services"
        }
    ],
    "sg:phone":"+1 940 566 7937",
    "sg:postcode":"76201",
    "sg:province":"TX",
    "wof:name":"Jack S Frisby",
    "wof:placetype":"venue"
},
  "geometry": {"coordinates":[-97.136588,33.240039],"type":"Point"}
}