{
  "type": "Feature",
  "properties": {
    "iso:country":"US",
    "sg:address":"2611 N Main Ave",
    "sg:city":"San Antonio",
    "sg:classifiers":[
        {
            "category":"Professional",
            "subcategory":"Engineering",
            "type":"Services"
        }
    ],
    "sg:phone":"+1 210 738 0086",
    "sg:postcode":"78212",
    "sg:province":"TX",
    "wof:name":"Earthtech Inc",
    "wof:placetype":"venue"
},
  "geometry": {"coordinates":[-98.494029,29.45474],"type":"Point"}
}