{
  "type": "Feature",
  "properties": {
    "iso:country":"US",
    "sg:address":"135 Burk Rd",
    "sg:city":"Killeen",
    "sg:classifiers":[
        {
            "category":"Retail",
            "subcategory":"Repair Shop",
            "type":"Services"
        }
    ],
    "sg:phone":"+1 254 289 4071",
    "sg:postcode":"76549",
    "sg:province":"TX",
    "wof:name":"Here & Now Jewelry Repair",
    "wof:placetype":"venue"
},
  "geometry": {"coordinates":[-97.773263,31.060212],"type":"Point"}
}