{
  "type": "Feature",
  "properties": {
    "iso:country":"US",
    "sg:address":"501 W Main St",
    "sg:city":"Mesquite",
    "sg:classifiers":[
        {
            "category":"Retail",
            "subcategory":"Repair Shop",
            "type":"Services"
        }
    ],
    "sg:phone":"+1 972 288 3173",
    "sg:postcode":"75149",
    "sg:province":"TX",
    "sg:tags":[
        "household",
        "appliance"
    ],
    "wof:name":"Quality Sewing Machine Co Inc",
    "wof:placetype":"venue"
},
  "geometry": {"coordinates":[-96.60426099999999,32.767257],"type":"Point"}
}