{
  "type": "Feature",
  "properties": {
    "iso:country":"US",
    "sg:address":"902 State Hwy 110",
    "sg:city":"Whitehouse",
    "sg:classifiers":[
        {
            "category":"Wholesale",
            "subcategory":"Scrap",
            "type":"Manufacturing & Wholesale Goods"
        }
    ],
    "sg:phone":"+1 903 839 3515",
    "sg:postcode":"75791",
    "sg:province":"TX",
    "sg:tags":[
        "waste"
    ],
    "wof:name":"Right Way Disposal Svc",
    "wof:placetype":"venue"
},
  "geometry": {"coordinates":[-95.22947000000001,32.239311],"type":"Point"}
}