{
  "type": "Feature",
  "properties": {
    "iso:country":"US",
    "sg:address":"2812 Celinda Cir",
    "sg:city":"College Station",
    "sg:classifiers":[
        {
            "category":"Home & Garden",
            "subcategory":"Mobile Homes",
            "type":"Retail Goods"
        }
    ],
    "sg:phone":"+1 979 693 1265",
    "sg:postcode":"77845",
    "sg:province":"TX",
    "wof:name":"Affordable Mobile Homes",
    "wof:placetype":"venue"
},
  "geometry": {"coordinates":[-96.298404,30.587817],"type":"Point"}
}