{
  "type": "Feature",
  "properties": {
    "iso:country":"US",
    "sg:address":"5601 Bintliff Dr",
    "sg:city":"Houston",
    "sg:classifiers":[
        {
            "category":"Home & Garden",
            "subcategory":"Household Appliances",
            "type":"Retail Goods"
        }
    ],
    "sg:phone":"+1 713 334 6364",
    "sg:postcode":"77036",
    "sg:province":"TX",
    "sg:tags":[
        "repair"
    ],
    "sg:website":"www.lasernetwork.net/",
    "wof:name":"The Laser Network Inc.",
    "wof:placetype":"venue"
},
  "geometry": {"coordinates":[-95.51046100000001,29.720634],"type":"Point"}
}