{
  "type": "Feature",
  "properties": {
    "iso:country":"US",
    "sg:address":"6921 Cullen Blvd",
    "sg:city":"Houston",
    "sg:classifiers":[
        {
            "category":"Restaurant",
            "type":"Food & Drink"
        }
    ],
    "sg:phone":"+1 713 842 6090",
    "sg:postcode":"77021",
    "sg:province":"TX",
    "sg:tags":[
        "eating"
    ],
    "wof:name":"Green Eyes Cafe",
    "wof:placetype":"venue"
},
  "geometry": {"coordinates":[-95.354682,29.686443],"type":"Point"}
}