{
  "type": "Feature",
  "properties": {
    "iso:country":"US",
    "sg:address":"1016 la Vista Ave",
    "sg:city":"Mcallen",
    "sg:classifiers":[
        {
            "category":"Professional",
            "subcategory":"Business Services",
            "type":"Services"
        }
    ],
    "sg:phone":"+1 956 992 9311",
    "sg:postcode":"78501",
    "sg:province":"TX",
    "wof:name":"Kasa Interiors",
    "wof:placetype":"venue"
},
  "geometry": {"coordinates":[-97.45635799999999,25.901457],"type":"Point"}
}