{
  "type": "Feature",
  "properties": {
    "iso:country":"US",
    "sg:address":"2700 Milam St",
    "sg:city":"Houston",
    "sg:classifiers":[
        {
            "category":"Restaurant",
            "type":"Food & Drink"
        }
    ],
    "sg:phone":"+1 713 529 2663",
    "sg:postcode":"77006",
    "sg:province":"TX",
    "wof:name":"Bond Lounge",
    "wof:placetype":"venue"
},
  "geometry": {"coordinates":[-95.376373,29.745729],"type":"Point"}
}