{
  "type": "Feature",
  "properties": {
    "iso:country":"US",
    "sg:address":"11824 Jollyville Rd Ste 300",
    "sg:city":"Austin",
    "sg:classifiers":[
        {
            "category":"Insurance",
            "subcategory":"Hazard Insurance",
            "type":"Services"
        }
    ],
    "sg:phone":"+1 512 250 5533",
    "sg:postcode":"78759",
    "sg:province":"TX",
    "sg:website":"http://statefarm.mqgroup.com/url.asp?usr=536839",
    "wof:name":"State Farm Insurance Agent-Richard Glasco",
    "wof:placetype":"venue"
},
  "geometry": {"coordinates":[-97.755169,30.42236],"type":"Point"}
}