{
  "type": "Feature",
  "properties": {
    "iso:country":"US",
    "sg:address":"11673 Jollyville Rd Ste B101",
    "sg:city":"Austin",
    "sg:classifiers":[
        {
            "category":"Banks & Credit Unions",
            "subcategory":"Financial Services",
            "type":"Services"
        }
    ],
    "sg:phone":"+1 512 658 0222",
    "sg:postcode":"78759",
    "sg:province":"TX",
    "sg:tags":[
        "broker",
        "mortgage"
    ],
    "sg:website":"monumentmtg.com/",
    "wof:name":"Monument Mortgage",
    "wof:placetype":"venue"
},
  "geometry": {"coordinates":[-97.75039099999999,30.418419],"type":"Point"}
}