{
  "type": "Feature",
  "properties": {
    "iso:country":"US",
    "sg:address":"6800 Helen Ct",
    "sg:city":"Plano",
    "sg:classifiers":[
        {
            "category":"Restaurant",
            "type":"Food & Drink"
        }
    ],
    "sg:phone":"+1 972 735 9868",
    "sg:postcode":"75023",
    "sg:province":"TX",
    "sg:tags":[
        "house",
        "eating",
        "mail"
    ],
    "wof:name":"Nicholinis Seafood",
    "wof:placetype":"venue"
},
  "geometry": {"coordinates":[-96.75491100000001,33.067102],"type":"Point"}
}