{
  "type": "Feature",
  "properties": {
    "iso:country":"US",
    "sg:address":"14520 Piping Rock Ln",
    "sg:city":"Houston",
    "sg:classifiers":[
        {
            "category":"Manufacturing",
            "subcategory":"Tools & Machinery",
            "type":"Manufacturing & Wholesale Goods"
        }
    ],
    "sg:phone":"+1 281 293 7570",
    "sg:postcode":"77077",
    "sg:province":"TX",
    "sg:tags":[
        "mfg",
        "ophthalmic"
    ],
    "wof:name":"All Pro Eyeglass Repair",
    "wof:placetype":"venue"
},
  "geometry": {"coordinates":[-95.643918,29.740491],"type":"Point"}
}