{
  "type": "Feature",
  "properties": {
    "iso:country":"US",
    "sg:address":"5851 San Felipe St",
    "sg:city":"Houston",
    "sg:classifiers":[
        {
            "category":"Mining & Drilling",
            "type":"Manufacturing & Wholesale Goods"
        }
    ],
    "sg:phone":"+1 713 781 6974",
    "sg:postcode":"77057",
    "sg:province":"TX",
    "sg:tags":[
        "gas",
        "oil",
        "exploration"
    ],
    "wof:name":"Legends Exploration",
    "wof:placetype":"venue"
},
  "geometry": {"coordinates":[-95.485794,29.749814],"type":"Point"}
}