{
  "type": "Feature",
  "properties": {
    "iso:country":"US",
    "sg:address":"1804 US Hwy 287R Bus",
    "sg:city":"Waxahachie",
    "sg:classifiers":[
        {
            "category":"Retail",
            "subcategory":"Auto Repair",
            "type":"Services"
        }
    ],
    "sg:phone":"+1 972 938 2868",
    "sg:postcode":"75165",
    "sg:province":"TX",
    "sg:tags":[
        "general"
    ],
    "wof:name":"Specialty Auto Repair Inc",
    "wof:placetype":"venue"
},
  "geometry": {"coordinates":[-96.82444599999999,32.373124],"type":"Point"}
}