{
  "type": "Feature",
  "properties": {
    "iso:country":"US",
    "sg:address":"139 S 9th St",
    "sg:city":"Slaton",
    "sg:classifiers":[
        {
            "category":"Manufacturing",
            "subcategory":"Printing",
            "type":"Manufacturing & Wholesale Goods"
        }
    ],
    "sg:phone":"+1 806 828 6201",
    "sg:postcode":"79364",
    "sg:province":"TX",
    "sg:tags":[
        "newspaper"
    ],
    "wof:name":"Slatonite",
    "wof:placetype":"venue"
},
  "geometry": {"coordinates":[-101.644088,33.437363],"type":"Point"}
}