{
  "type": "Feature",
  "properties": {
    "iso:country":"US",
    "sg:address":"900 Gulfway Dr",
    "sg:city":"Port Arthur",
    "sg:classifiers":[
        {
            "category":"Organizations",
            "subcategory":"Religious Organization",
            "type":"Services"
        }
    ],
    "sg:phone":"+1 409 455 7857",
    "sg:postcode":"77640",
    "sg:province":"TX",
    "sg:tags":[
        "church"
    ],
    "wof:name":"Lord Jesus Christ Ministries",
    "wof:placetype":"venue"
},
  "geometry": {"coordinates":[-93.94290599999999,29.883723],"type":"Point"}
}