{
  "type": "Feature",
  "properties": {
    "iso:country":"US",
    "sg:address":"2521 Weaver St",
    "sg:city":"Fort Worth",
    "sg:classifiers":[
        {
            "category":"Building & Trades",
            "subcategory":"Electrical",
            "type":"Services"
        }
    ],
    "sg:phone":"+1 817 834 8466",
    "sg:postcode":"76117",
    "sg:province":"TX",
    "sg:tags":[
        "electrical",
        "electric",
        "contractor"
    ],
    "wof:name":"Concept Services Inc",
    "wof:placetype":"venue"
},
  "geometry": {"coordinates":[-97.247168,32.800735],"type":"Point"}
}