{
  "type": "Feature",
  "properties": {
    "iso:country":"US",
    "sg:address":"508 Main St",
    "sg:city":"Lone Star",
    "sg:classifiers":[
        {
            "category":"Professional",
            "subcategory":"Computer Services",
            "type":"Services"
        }
    ],
    "sg:phone":"+1 903 656 3707",
    "sg:postcode":"75668",
    "sg:province":"TX",
    "sg:tags":[
        "repair"
    ],
    "wof:name":"Computer Works",
    "wof:placetype":"venue"
},
  "geometry": {"coordinates":[-94.710397,32.948987],"type":"Point"}
}