{
  "type": "Feature",
  "properties": {
    "iso:country":"US",
    "sg:address":"3017 Lynn Dell Dr",
    "sg:city":"Tool",
    "sg:classifiers":[
        {
            "category":"Farming",
            "subcategory":"Livestock Farm",
            "type":"Manufacturing & Wholesale Goods"
        }
    ],
    "sg:phone":"+1 903 432 3139",
    "sg:postcode":"75143",
    "sg:province":"TX",
    "sg:tags":[
        "ranch"
    ],
    "wof:name":"J Greenhaw",
    "wof:placetype":"venue"
},
  "geometry": {"coordinates":[-96.183747,32.31298],"type":"Point"}
}