{
  "type": "Feature",
  "properties": {
    "iso:country":"US",
    "sg:address":"101 W Walter Ave",
    "sg:city":"Pflugerville",
    "sg:classifiers":[
        {
            "category":"Professional",
            "subcategory":"Business Services",
            "type":"Services"
        }
    ],
    "sg:phone":"+1 512 251 7431",
    "sg:postcode":"78660",
    "sg:province":"TX",
    "wof:name":"Consider It Dunn",
    "wof:placetype":"venue"
},
  "geometry": {"coordinates":[-97.625092,30.436712],"type":"Point"}
}