{
  "type": "Feature",
  "properties": {
    "iso:country":"US",
    "sg:address":"1617 Cimmarron St",
    "sg:city":"Portland",
    "sg:classifiers":[
        {
            "category":"Organizations",
            "subcategory":"Religious Organization",
            "type":"Services"
        }
    ],
    "sg:phone":"+1 361 643 1002",
    "sg:postcode":"78374",
    "sg:province":"TX",
    "wof:name":"LDS Missionaries",
    "wof:placetype":"venue"
},
  "geometry": {"coordinates":[-97.33024,27.884897],"type":"Point"}
}