{
  "type": "Feature",
  "properties": {
    "iso:country":"US",
    "sg:address":"2204 N Austin St",
    "sg:city":"Seguin",
    "sg:classifiers":[
        {
            "category":"Restaurant",
            "type":"Food & Drink"
        },
        {
            "category":"Food & Beverages",
            "subcategory":"Groceries & Convenience Stores",
            "type":"Retail Goods"
        }
    ],
    "sg:phone":"+1 830 379 9434",
    "sg:postcode":"78155",
    "sg:province":"TX",
    "sg:tags":[
        "american",
        "latin",
        "mexican"
    ],
    "wof:name":"Tijerina Masa Tortilla",
    "wof:placetype":"venue"
},
  "geometry": {"coordinates":[-97.964905,29.590401],"type":"Point"}
}