{
  "type": "Feature",
  "properties": {
    "iso:country":"US",
    "sg:address":"500 W 53rd St",
    "sg:city":"Texarkana",
    "sg:classifiers":[
        {
            "category":"Travel",
            "subcategory":"Campground",
            "type":"Entertainment"
        }
    ],
    "sg:phone":"+1 903 792 5521",
    "sg:postcode":"75503",
    "sg:province":"TX",
    "wof:name":"Texarkana KOA",
    "wof:placetype":"venue"
},
  "geometry": {"coordinates":[-94.048391,33.47081],"type":"Point"}
}