{
  "type": "Feature",
  "properties": {
    "iso:country":"US",
    "sg:address":"9000 Lait Dr",
    "sg:city":"El Paso",
    "sg:classifiers":[
        {
            "category":"Wholesale",
            "subcategory":"Machinery & Supplies",
            "type":"Manufacturing & Wholesale Goods"
        }
    ],
    "sg:phone":"+1 915 598 9428",
    "sg:postcode":"79925",
    "sg:province":"TX",
    "sg:tags":[
        "contractor"
    ],
    "wof:name":"Specialties Suppliers Constr",
    "wof:placetype":"venue"
},
  "geometry": {"coordinates":[-106.36806300000001,31.779905],"type":"Point"}
}