{
  "type": "Feature",
  "properties": {
    "iso:country":"US",
    "sg:address":"7900 Ferguson Rd",
    "sg:city":"Dallas",
    "sg:classifiers":[
        {
            "category":"Professional",
            "subcategory":"Business Services",
            "type":"Services"
        }
    ],
    "sg:phone":"+1 214 321 1255",
    "sg:postcode":"75228",
    "sg:province":"TX",
    "sg:tags":[
        "for",
        "show",
        "trade",
        "sign",
        "painting",
        "display"
    ],
    "wof:name":"Signage Systems",
    "wof:placetype":"venue"
},
  "geometry": {"coordinates":[-96.713967,32.801885],"type":"Point"}
}