{
  "type": "Feature",
  "properties": {
    "iso:country":"US",
    "sg:address":"31202 Bakerlake Dr",
    "sg:city":"Spring",
    "sg:classifiers":[
        {
            "category":"Shopping",
            "subcategory":"Gifts & Souvenirs",
            "type":"Retail Goods"
        }
    ],
    "sg:phone":"+1 281 419 0470",
    "sg:postcode":"77386",
    "sg:province":"TX",
    "wof:name":"Jenifer Grett Jewler",
    "wof:placetype":"venue"
},
  "geometry": {"coordinates":[-95.419145,30.141394],"type":"Point"}
}