{
  "type": "Feature",
  "properties": {
    "iso:country":"US",
    "sg:address":"220 W Kingsley Rd",
    "sg:city":"Garland",
    "sg:classifiers":[
        {
            "category":"Organizations",
            "subcategory":"Religious Organization",
            "type":"Services"
        }
    ],
    "sg:phone":"+1 214 227 4391",
    "sg:postcode":"75041",
    "sg:province":"TX",
    "wof:name":"Iglesia Cristiana El Rey Ya Viene",
    "wof:placetype":"venue"
},
  "geometry": {"coordinates":[-96.63250499999999,32.878593],"type":"Point"}
}