{
  "type": "Feature",
  "properties": {
    "iso:country":"US",
    "sg:address":"2801 W Sunset Dr",
    "sg:city":"Orange",
    "sg:classifiers":[
        {
            "category":"Manufacturing",
            "subcategory":"Printing",
            "type":"Manufacturing & Wholesale Goods"
        }
    ],
    "sg:phone":"+1 409 886 0067",
    "sg:postcode":"77630",
    "sg:province":"TX",
    "sg:tags":[
        "publisher",
        "music"
    ],
    "wof:name":"Showtime",
    "wof:placetype":"venue"
},
  "geometry": {"coordinates":[-93.758228,30.111733],"type":"Point"}
}