{
  "type": "Feature",
  "properties": {
    "iso:country":"US",
    "sg:address":"900 Southland Ave",
    "sg:city":"Fort Worth",
    "sg:classifiers":[
        {
            "category":"Health Services",
            "subcategory":"Hospital",
            "type":"Services"
        }
    ],
    "sg:phone":"+1 817 336 5454",
    "sg:postcode":"76104",
    "sg:province":"TX",
    "sg:tags":[
        "program",
        "orient"
    ],
    "wof:name":"Tcmerf",
    "wof:placetype":"venue"
},
  "geometry": {"coordinates":[-97.342598,32.733756],"type":"Point"}
}