{
  "type": "Feature",
  "properties": {
    "iso:country":"US",
    "sg:address":"4825 E Riverside Dr",
    "sg:city":"Austin",
    "sg:classifiers":[
        {
            "category":"Recreation",
            "type":"Entertainment"
        }
    ],
    "sg:phone":"+1 512 385 5803",
    "sg:postcode":"78741",
    "sg:province":"TX",
    "sg:tags":[
        "psychic",
        "medium"
    ],
    "wof:name":"Card Palm Tarot Reading",
    "wof:placetype":"venue"
},
  "geometry": {"coordinates":[-97.71475599999999,30.23039],"type":"Point"}
}