{
  "type": "Feature",
  "properties": {
    "iso:country":"US",
    "sg:address":"148 N Akard St",
    "sg:city":"Dallas",
    "sg:classifiers":[
        {
            "category":"Building & Trades",
            "subcategory":"Locksmith",
            "type":"Services"
        }
    ],
    "sg:phone":"+1 888 364 6889",
    "sg:postcode":"75346",
    "sg:province":"TX",
    "sg:tags":[
        "key"
    ],
    "sg:website":"www.dallas-locksmith.com/",
    "wof:name":"Locksmith Dallas",
    "wof:placetype":"venue"
},
  "geometry": {"coordinates":[-96.79966,32.780952],"type":"Point"}
}