{
  "type": "Feature",
  "properties": {
    "iso:country":"US",
    "sg:address":"3303 N Midkiff Rd",
    "sg:city":"Midland",
    "sg:classifiers":[
        {
            "category":"Retail",
            "subcategory":"Repair Shop",
            "type":"Services"
        }
    ],
    "sg:phone":"+1 915 520 5364",
    "sg:postcode":"79705",
    "sg:province":"TX",
    "wof:name":"Randys Repair & Remounts",
    "wof:placetype":"venue"
},
  "geometry": {"coordinates":[-102.125725,32.022131],"type":"Point"}
}