{
  "type": "Feature",
  "properties": {
    "iso:country":"US",
    "sg:address":"2324 Table Rock Ct",
    "sg:city":"Arlington",
    "sg:classifiers":[
        {
            "category":"Professional",
            "subcategory":"Computer Services",
            "type":"Services"
        }
    ],
    "sg:phone":"+1 817 640 8520",
    "sg:postcode":"76006",
    "sg:province":"TX",
    "sg:tags":[
        "datum"
    ],
    "wof:name":"Eighttwo",
    "wof:placetype":"venue"
},
  "geometry": {"coordinates":[-97.069092,32.783917],"type":"Point"}
}