{
  "type": "Feature",
  "properties": {
    "iso:country":"US",
    "sg:address":"112 Mulberry Ave",
    "sg:city":"El Paso",
    "sg:classifiers":[
        {
            "category":"Wholesale",
            "subcategory":"Machinery & Supplies",
            "type":"Manufacturing & Wholesale Goods"
        }
    ],
    "sg:phone":"+1 915 833 1507",
    "sg:postcode":"79932",
    "sg:province":"TX",
    "sg:tags":[
        "equipment",
        "industrial",
        "washing",
        "pressure"
    ],
    "wof:name":"Pressure Power Washers Inc",
    "wof:placetype":"venue"
},
  "geometry": {"coordinates":[-106.586139,31.854302],"type":"Point"}
}