{
  "type": "Feature",
  "properties": {
    "iso:country":"US",
    "sg:address":"3217 Franklin Ave",
    "sg:city":"Waco",
    "sg:classifiers":[
        {
            "category":"Wholesale",
            "subcategory":"Office Equipment",
            "type":"Manufacturing & Wholesale Goods"
        }
    ],
    "sg:phone":"+1 254 753 4508",
    "sg:postcode":"76710",
    "sg:province":"TX",
    "sg:tags":[
        "machine",
        "repair"
    ],
    "wof:name":"Carroll-Rogers Elctrnc Bus Mch",
    "wof:placetype":"venue"
},
  "geometry": {"coordinates":[-97.156723,31.533245],"type":"Point"}
}