{
  "type": "Feature",
  "properties": {
    "iso:country":"US",
    "sg:address":"1304 E Alabama St",
    "sg:city":"Pearsall",
    "sg:classifiers":[
        {
            "category":"Manufacturing",
            "subcategory":"Pottery",
            "type":"Manufacturing & Wholesale Goods"
        }
    ],
    "sg:phone":"+1 830 334 2742",
    "sg:postcode":"78061",
    "sg:province":"TX",
    "sg:tags":[
        "product",
        "mfg"
    ],
    "wof:name":"Blancas Imports",
    "wof:placetype":"venue"
},
  "geometry": {"coordinates":[-99.08342399999999,28.894006],"type":"Point"}
}