{
  "type": "Feature",
  "properties": {
    "iso:country":"US",
    "sg:address":"1518 Basse Rd",
    "sg:city":"San Antonio",
    "sg:classifiers":[
        {
            "category":"Personal",
            "subcategory":"Beauty Salon",
            "type":"Services"
        }
    ],
    "sg:phone":"+1 210 738 8976",
    "sg:postcode":"78213",
    "sg:province":"TX",
    "wof:name":"Jessica's Salon",
    "wof:placetype":"venue"
},
  "geometry": {"coordinates":[-98.508922,29.488605],"type":"Point"}
}