{
  "type": "Feature",
  "properties": {
    "iso:country":"US",
    "sg:address":"11011 Spruce Dr N",
    "sg:city":"La Porte",
    "sg:classifiers":[
        {
            "category":"Professional",
            "subcategory":"Business Services",
            "type":"Services"
        }
    ],
    "sg:phone":"+1 281 842 9781",
    "sg:postcode":"77571",
    "sg:province":"TX",
    "wof:name":"Marina Real Estate Insptn Svcs",
    "wof:placetype":"venue"
},
  "geometry": {"coordinates":[-95.05771799999999,29.661436],"type":"Point"}
}