{
  "type": "Feature",
  "properties": {
    "iso:country":"US",
    "sg:address":"1545 E I- 30",
    "sg:city":"Rockwall",
    "sg:classifiers":[
        {
            "category":"Education",
            "subcategory":"School",
            "type":"Public Place"
        }
    ],
    "sg:phone":"+1 972 270 9777",
    "sg:postcode":"75043",
    "sg:province":"TX",
    "wof:name":"Oates Park of Rockwall",
    "wof:placetype":"venue"
},
  "geometry": {"coordinates":[-96.548937,32.860993],"type":"Point"}
}