{
  "type": "Feature",
  "properties": {
    "iso:country":"US",
    "sg:address":"11246 S Post Oak Rd",
    "sg:city":"Houston",
    "sg:classifiers":[
        {
            "category":"Wholesale",
            "subcategory":"Medical Equipment & Supplies",
            "type":"Manufacturing & Wholesale Goods"
        }
    ],
    "sg:phone":"+1 713 729 6904",
    "sg:postcode":"77035",
    "sg:province":"TX",
    "sg:tags":[
        "physician",
        "surgeon"
    ],
    "wof:name":"Citizen's Medical Equipment",
    "wof:placetype":"venue"
},
  "geometry": {"coordinates":[-95.463921,29.655295],"type":"Point"}
}