{
  "type": "Feature",
  "properties": {
    "iso:country":"US",
    "sg:address":"4717 Belladonna Dr",
    "sg:city":"Fort Worth",
    "sg:classifiers":[
        {
            "category":"Professional",
            "subcategory":"Engineering",
            "type":"Services"
        }
    ],
    "sg:phone":"+1 817 423 9082",
    "sg:postcode":"76123",
    "sg:province":"TX",
    "sg:tags":[
        "quick",
        "reaction"
    ],
    "wof:name":"Shadow Systems Inc",
    "wof:placetype":"venue"
},
  "geometry": {"coordinates":[-97.39412900000001,32.625218],"type":"Point"}
}