{
  "type": "Feature",
  "properties": {
    "iso:country":"US",
    "sg:address":"3131 FM 528",
    "sg:city":"Friendswood",
    "sg:classifiers":[
        {
            "category":"Personal",
            "subcategory":"Beauty Salon",
            "type":"Services"
        }
    ],
    "sg:phone":"+1 281 338 6006",
    "sg:postcode":"77546",
    "sg:province":"TX",
    "sg:tags":[
        "shop"
    ],
    "wof:name":"AP Hair Studio",
    "wof:placetype":"venue"
},
  "geometry": {"coordinates":[-95.161597,29.522295],"type":"Point"}
}