{
  "type": "Feature",
  "properties": {
    "iso:country":"US",
    "sg:address":"308 River St",
    "sg:city":"Del Rio",
    "sg:classifiers":[
        {
            "category":"Building & Trades",
            "subcategory":"Construction",
            "type":"Services"
        }
    ],
    "sg:phone":"+1 830 778 1376",
    "sg:postcode":"78840",
    "sg:province":"TX",
    "sg:tags":[
        "insulation",
        "heat",
        "contractor"
    ],
    "wof:name":"T & N Insulation",
    "wof:placetype":"venue"
},
  "geometry": {"coordinates":[-100.947372,29.457263],"type":"Point"}
}