{
  "type": "Feature",
  "properties": {
    "iso:country":"US",
    "sg:address":"11510 Leitrim Way",
    "sg:city":"Houston",
    "sg:classifiers":[
        {
            "category":"Education",
            "subcategory":"School",
            "type":"Public Place"
        }
    ],
    "sg:phone":"+1 281 448 0255",
    "sg:postcode":"77047",
    "sg:province":"TX",
    "wof:name":"Old School Caters",
    "wof:placetype":"venue"
},
  "geometry": {"coordinates":[-95.363258,29.634626],"type":"Point"}
}