{
  "type": "Feature",
  "properties": {
    "iso:country":"US",
    "sg:address":"218 E Jackson St",
    "sg:city":"Burnet",
    "sg:classifiers":[
        {
            "category":"Social Services",
            "subcategory":"Job Training",
            "type":"Services"
        }
    ],
    "sg:phone":"+1 512 756 1484",
    "sg:postcode":"78611",
    "sg:province":"TX",
    "sg:tags":[
        "employment"
    ],
    "wof:name":"Christian Womens Job Corps",
    "wof:placetype":"venue"
},
  "geometry": {"coordinates":[-98.225561,30.756722],"type":"Point"}
}