{
  "type": "Feature",
  "properties": {
    "iso:country":"US",
    "sg:address":"588 Endicott Ln",
    "sg:city":"Conroe",
    "sg:classifiers":[
        {
            "category":"Professional",
            "type":"Services"
        },
        {
            "category":"Mining & Drilling",
            "type":"Manufacturing & Wholesale Goods"
        }
    ],
    "sg:phone":"+1 936 273 4678",
    "sg:postcode":"77302",
    "sg:province":"TX",
    "sg:tags":[
        "establishment",
        "oil",
        "gas",
        "exploration"
    ],
    "wof:name":"C and G Exploration Inc",
    "wof:placetype":"venue"
},
  "geometry": {"coordinates":[-95.435513,30.258866],"type":"Point"}
}