{
  "type": "Feature",
  "properties": {
    "iso:country":"US",
    "sg:address":"520 W Mockingbird Ln",
    "sg:city":"Dallas",
    "sg:classifiers":[
        {
            "category":"Freight",
            "type":"Transportation"
        }
    ],
    "sg:phone":"+1 214 630 2272",
    "sg:postcode":"75247",
    "sg:province":"TX",
    "sg:tags":[
        "delivery",
        "moving",
        "piano",
        "rental"
    ],
    "wof:name":"Keyboards Unlimited",
    "wof:placetype":"venue"
},
  "geometry": {"coordinates":[-96.873586,32.807712],"type":"Point"}
}