{
  "type": "Feature",
  "properties": {
    "iso:country":"US",
    "sg:address":"3417 Sherwood Way",
    "sg:city":"San Angelo",
    "sg:classifiers":[
        {
            "category":"Organizations",
            "subcategory":"Religious Organization",
            "type":"Services"
        }
    ],
    "sg:phone":"+1 325 949 3221",
    "sg:postcode":"76901",
    "sg:province":"TX",
    "sg:tags":[
        "church"
    ],
    "wof:name":"Christ Lutheran Church Inc",
    "wof:placetype":"venue"
},
  "geometry": {"coordinates":[-100.480656,31.444822],"type":"Point"}
}