{
  "type": "Feature",
  "properties": {
    "iso:country":"US",
    "sg:address":"8603 N New Braunfels Ave",
    "sg:city":"San Antonio",
    "sg:classifiers":[
        {
            "category":"Professional",
            "subcategory":"Research",
            "type":"Services"
        }
    ],
    "sg:phone":"+1 210 826 6949",
    "sg:postcode":"78217",
    "sg:province":"TX",
    "sg:tags":[
        "commercial",
        "physical"
    ],
    "wof:name":"Pathfinder Technology Solution",
    "wof:placetype":"venue"
},
  "geometry": {"coordinates":[-98.45779899999999,29.519219],"type":"Point"}
}