{
  "type": "Feature",
  "properties": {
    "iso:country":"US",
    "sg:address":"1635 N 77 Sunshine Strip",
    "sg:city":"Harlingen",
    "sg:phone":"+1 956 412 8334",
    "sg:postcode":"78550",
    "sg:province":"TX",
    "wof:name":"Chapitas Restaurant",
    "wof:placetype":"venue"
},
  "geometry": {"coordinates":[-97.695965,26.208453],"type":"Point"}
}