{
  "type": "Feature",
  "properties": {
    "iso:country":"US",
    "sg:address":"14280 Marsh Ln",
    "sg:city":"Addison",
    "sg:classifiers":[
        {
            "category":"Shopping",
            "subcategory":"Florist",
            "type":"Retail Goods"
        },
        {
            "category":"Bakery",
            "type":"Food & Drink"
        },
        {
            "category":"Food & Beverages",
            "subcategory":"Groceries & Convenience Stores",
            "type":"Retail Goods"
        }
    ],
    "sg:phone":"+1 972 241 4485",
    "sg:postcode":"75001",
    "sg:province":"TX",
    "wof:name":"Tom Thumb Food & Pharmacy",
    "wof:placetype":"venue"
},
  "geometry": {"coordinates":[-96.855598,32.939899],"type":"Point"}
}