{
  "type": "Feature",
  "properties": {
    "iso:country":"US",
    "sg:address":"416 S Johnson St",
    "sg:city":"Alvin",
    "sg:classifiers":[
        {
            "category":"Organizations",
            "subcategory":"Non-profit Organization",
            "type":"Services"
        }
    ],
    "sg:phone":"+1 281 331 0490",
    "sg:postcode":"77511",
    "sg:province":"TX",
    "sg:tags":[
        "health",
        "center",
        "community"
    ],
    "wof:name":"Ache",
    "wof:placetype":"venue"
},
  "geometry": {"coordinates":[-95.250687,29.420674],"type":"Point"}
}