{
  "type": "Feature",
  "properties": {
    "iso:country":"US",
    "sg:address":"910 Mineral Wells St",
    "sg:city":"Terrell",
    "sg:classifiers":[
        {
            "category":"Place Of Worship",
            "subcategory":"Church",
            "type":"Public Place"
        },
        {
            "category":"Place Of Worship",
            "type":"Public Place"
        },
        {
            "category":"Building & Trades",
            "subcategory":"Pest Control",
            "type":"Services"
        }
    ],
    "sg:phone":"+1 972 563 1162",
    "sg:postcode":"75160",
    "sg:province":"TX",
    "sg:tags":[
        "churches-baptist-general",
        "gospel",
        "churches-full",
        "churches-baptist"
    ],
    "wof:name":"Greater New Hope Church",
    "wof:placetype":"venue"
},
  "geometry": {"coordinates":[-96.296336,32.725936],"type":"Point"}
}