{
  "type": "Feature",
  "properties": {
    "iso:country":"US",
    "sg:address":"725 N Pierce St",
    "sg:city":"Amarillo",
    "sg:classifiers":[
        {
            "category":"Restaurant",
            "type":"Food & Drink"
        }
    ],
    "sg:menulink":"http://www.allmenus.com/tx/amarillo/199821-long-john-silvers/menu/",
    "sg:phone":"+1 806 373 5032",
    "sg:postcode":"79107",
    "sg:province":"TX",
    "sg:tags":[
        "seafood",
        "american"
    ],
    "wof:name":"Long John Silver's",
    "wof:placetype":"venue"
},
  "geometry": {"coordinates":[-101.830659,35.220177],"type":"Point"}
}