{
  "type": "Feature",
  "properties": {
    "iso:country":"US",
    "sg:address":"406 Cluck Creek Trl",
    "sg:city":"Cedar Park",
    "sg:classifiers":[
        {
            "category":"Professional",
            "type":"Services"
        }
    ],
    "sg:phone":"+1 512 219 5093",
    "sg:postcode":"78613",
    "sg:province":"TX",
    "wof:name":"Marcia & Co",
    "wof:placetype":"venue"
},
  "geometry": {"coordinates":[-97.82929300000001,30.502636],"type":"Point"}
}