{
  "type": "Feature",
  "properties": {
    "iso:country":"US",
    "sg:address":"2110 White Horse Trl # G",
    "sg:city":"Austin",
    "sg:classifiers":[
        {
            "category":"Arena",
            "subcategory":"Indoor Arena",
            "type":"Entertainment"
        }
    ],
    "sg:phone":"+1 512 474 4469",
    "sg:postcode":"78757",
    "sg:province":"TX",
    "sg:tags":[
        "bureau",
        "concert"
    ],
    "wof:name":"Austin Ticket Co",
    "wof:placetype":"venue"
},
  "geometry": {"coordinates":[-97.739369,30.338539],"type":"Point"}
}