{
  "type": "Feature",
  "properties": {
    "iso:country":"US",
    "sg:address":"14713 Banbridge Trl",
    "sg:city":"Austin",
    "sg:classifiers":[
        {
            "category":"Banks & Credit Unions",
            "subcategory":"Financial Services",
            "type":"Services"
        }
    ],
    "sg:phone":"+1 512 246 7811",
    "sg:postcode":"78717",
    "sg:province":"TX",
    "sg:tags":[
        "investor"
    ],
    "wof:name":"Louis Sharp Investments LLC",
    "wof:placetype":"venue"
},
  "geometry": {"coordinates":[-97.780475,30.499106],"type":"Point"}
}