{
  "type": "Feature",
  "properties": {
    "iso:country":"US",
    "sg:address":"2419 Little Creek Dr",
    "sg:city":"Richardson",
    "sg:classifiers":[
        {
            "category":"Shopping",
            "subcategory":"Books",
            "type":"Retail Goods"
        }
    ],
    "sg:phone":"+1 972 783 9251",
    "sg:postcode":"75080",
    "sg:province":"TX",
    "wof:name":"Bongiorno Books",
    "wof:placetype":"venue"
},
  "geometry": {"coordinates":[-96.727144,32.98568],"type":"Point"}
}