{
  "type": "Feature",
  "properties": {
    "iso:country":"US",
    "sg:address":"530 S Yarbrough Dr",
    "sg:city":"El Paso",
    "sg:classifiers":[
        {
            "category":"Manufacturing",
            "subcategory":"Food",
            "type":"Manufacturing & Wholesale Goods"
        },
        {
            "category":"Food & Beverages",
            "subcategory":"Bakery",
            "type":"Retail Goods"
        }
    ],
    "sg:phone":"+1 915 858 8720",
    "sg:postcode":"79915",
    "sg:province":"TX",
    "sg:tags":[
        "baker",
        "eating",
        "product",
        "mfg"
    ],
    "wof:name":"Valentine's Bakery",
    "wof:placetype":"venue"
},
  "geometry": {"coordinates":[-106.36511299999999,31.715895],"type":"Point"}
}