{
  "type": "Feature",
  "properties": {
    "iso:country":"US",
    "sg:address":"800 Wilcrest Dr",
    "sg:city":"Houston",
    "sg:classifiers":[
        {
            "category":"Wholesale",
            "subcategory":"Machinery & Supplies",
            "type":"Manufacturing & Wholesale Goods"
        },
        {
            "category":"Building & Trades",
            "subcategory":"Equipment Rental",
            "type":"Services"
        }
    ],
    "sg:phone":"+1 713 783 7454",
    "sg:postcode":"77042",
    "sg:province":"TX",
    "sg:tags":[
        "field",
        "industrial",
        "oil"
    ],
    "sg:website":"http://www.sparteksystems.com",
    "wof:name":"Spartek Systems",
    "wof:placetype":"venue"
},
  "geometry": {"coordinates":[-95.57559999999999,29.755671],"type":"Point"}
}