{
  "type": "Feature",
  "properties": {
    "iso:country":"US",
    "sg:address":"851 Ramada Dr",
    "sg:city":"Houston",
    "sg:classifiers":[
        {
            "category":"Manufacturing",
            "subcategory":"Glass & Minerals",
            "type":"Manufacturing & Wholesale Goods"
        }
    ],
    "sg:phone":"+1 281 480 5240",
    "sg:postcode":"77062",
    "sg:province":"TX",
    "sg:tags":[
        "product",
        "mfg"
    ],
    "wof:name":"Stained Glass Expressions",
    "wof:placetype":"venue"
},
  "geometry": {"coordinates":[-95.12608400000001,29.554874],"type":"Point"}
}