{
  "type": "Feature",
  "properties": {
    "iso:country":"US",
    "sg:address":"1006 Cherrywood Ln",
    "sg:city":"Carrollton",
    "sg:classifiers":[
        {
            "category":"Professional",
            "type":"Services"
        }
    ],
    "sg:phone":"+1 972 466 1248",
    "sg:postcode":"75006",
    "sg:province":"TX",
    "wof:name":"Brittanys MI Tiendita",
    "wof:placetype":"venue"
},
  "geometry": {"coordinates":[-96.90570099999999,32.974536],"type":"Point"}
}