{
  "type": "Feature",
  "properties": {
    "iso:country":"US",
    "sg:address":"3501 Gus Thomasson Rd Ste 11",
    "sg:city":"Mesquite",
    "sg:classifiers":[
        {
            "category":"Health Services",
            "subcategory":"Optometrist",
            "type":"Services"
        }
    ],
    "sg:phone":"+1 972 270 5446",
    "sg:postcode":"75150",
    "sg:province":"TX",
    "wof:name":"Spiegler Eye Care",
    "wof:placetype":"venue"
},
  "geometry": {"coordinates":[-96.635839,32.812744],"type":"Point"}
}