{
  "type": "Feature",
  "properties": {
    "iso:country":"US",
    "sg:address":"20 Brookmeadow Dr",
    "sg:city":"Wimberley",
    "sg:classifiers":[
        {
            "category":"Real Estate",
            "subcategory":"Real Estate Agent",
            "type":"Services"
        }
    ],
    "sg:phone":"+1 512 847 7765",
    "sg:postcode":"78676",
    "sg:province":"TX",
    "wof:name":"Holcomb Real Estate",
    "wof:placetype":"venue"
},
  "geometry": {"coordinates":[-98.111115,30.030911],"type":"Point"}
}