{
  "type": "Feature",
  "properties": {
    "iso:country":"US",
    "sg:address":"1605 Corniche St",
    "sg:city":"League City",
    "sg:classifiers":[
        {
            "category":"Manufacturing",
            "subcategory":"Printing",
            "type":"Manufacturing & Wholesale Goods"
        }
    ],
    "sg:phone":"+1 281 334 3124",
    "sg:postcode":"77573",
    "sg:province":"TX",
    "sg:tags":[
        "publishing"
    ],
    "wof:name":"Coffee News",
    "wof:placetype":"venue"
},
  "geometry": {"coordinates":[-95.06657300000001,29.549417],"type":"Point"}
}