{
  "type": "Feature",
  "properties": {
    "iso:country":"US",
    "sg:address":"2505 E 30th St",
    "sg:city":"Brownsville",
    "sg:classifiers":[
        {
            "category":"Home & Garden",
            "subcategory":"Garden Supply",
            "type":"Retail Goods"
        }
    ],
    "sg:phone":"+1 956 546 6834",
    "sg:postcode":"78521",
    "sg:province":"TX",
    "wof:name":"Juanitas Planting House",
    "wof:placetype":"venue"
},
  "geometry": {"coordinates":[-97.463148,25.897432],"type":"Point"}
}