{
  "type": "Feature",
  "properties": {
    "iso:country":"US",
    "sg:address":"1880 S Dairy Ashford St",
    "sg:city":"Houston",
    "sg:classifiers":[
        {
            "category":"Professional",
            "subcategory":"Engineering",
            "type":"Services"
        }
    ],
    "sg:phone":"+1 832 327 0701",
    "sg:postcode":"77077",
    "sg:province":"TX",
    "sg:tags":[
        "civil"
    ],
    "wof:name":"Innovative Engrg Design Inc",
    "wof:placetype":"venue"
},
  "geometry": {"coordinates":[-95.60612500000001,29.746283],"type":"Point"}
}