{
  "type": "Feature",
  "properties": {
    "iso:country":"US",
    "sg:address":"506 E Young St",
    "sg:city":"Llano",
    "sg:classifiers":[
        {
            "category":"Utilities",
            "subcategory":"Fuel Oil & Lpg",
            "type":"Services"
        }
    ],
    "sg:phone":"+1 325 247 4449",
    "sg:postcode":"78643",
    "sg:province":"TX",
    "sg:tags":[
        "gas",
        "butane"
    ],
    "wof:name":"Burnet Butane",
    "wof:placetype":"venue"
},
  "geometry": {"coordinates":[-98.66905199999999,30.759385],"type":"Point"}
}