{
  "type": "Feature",
  "properties": {
    "iso:country":"US",
    "sg:address":"25 Frj Dr",
    "sg:city":"Longview",
    "sg:classifiers":[
        {
            "category":"Organizations",
            "subcategory":"Religious Organization",
            "type":"Services"
        }
    ],
    "sg:phone":"+1 903 234 2075",
    "sg:postcode":"75602",
    "sg:province":"TX",
    "wof:name":"Association Of North American",
    "wof:placetype":"venue"
},
  "geometry": {"coordinates":[-94.690586,32.500403],"type":"Point"}
}