{
  "type": "Feature",
  "properties": {
    "iso:country":"US",
    "sg:address":"6914 Thornwild Rd",
    "sg:city":"Missouri City",
    "sg:classifiers":[
        {
            "category":"Retail",
            "subcategory":"Laundry & Dry Cleaning",
            "type":"Services"
        }
    ],
    "sg:phone":"+1 281 835 0018",
    "sg:postcode":"77489",
    "sg:province":"TX",
    "wof:name":"JJ&j Designs",
    "wof:placetype":"venue"
},
  "geometry": {"coordinates":[-95.490364,29.601454],"type":"Point"}
}