{
  "type": "Feature",
  "properties": {
    "iso:country":"US",
    "sg:address":"5136 Lovell Ave",
    "sg:city":"Fort Worth",
    "sg:classifiers":[
        {
            "category":"Wholesale",
            "subcategory":"Apparel",
            "type":"Manufacturing & Wholesale Goods"
        }
    ],
    "sg:phone":"+1 817 731 8630",
    "sg:postcode":"76107",
    "sg:province":"TX",
    "sg:tags":[
        "florist",
        "piece"
    ],
    "wof:name":"Florals & More",
    "wof:placetype":"venue"
},
  "geometry": {"coordinates":[-97.39814200000001,32.731169],"type":"Point"}
}