{
  "type": "Feature",
  "properties": {
    "iso:country":"US",
    "sg:address":"1213 E Pecan Blvd",
    "sg:city":"Mcallen",
    "sg:phone":"+1 956 688 6290",
    "sg:postcode":"78501",
    "sg:province":"TX",
    "sg:tags":[
        "equipment",
        "supply"
    ],
    "wof:name":"Jean's Restaurant Supply",
    "wof:placetype":"venue"
},
  "geometry": {"coordinates":[-98.202985,26.214676],"type":"Point"}
}