{
  "type": "Feature",
  "properties": {
    "iso:country":"US",
    "sg:address":"1601 Paper Moon Dr",
    "sg:city":"Cedar Park",
    "sg:classifiers":[
        {
            "category":"Building & Trades",
            "subcategory":"Equipment Rental",
            "type":"Services"
        }
    ],
    "sg:phone":"+1 512 257 1138",
    "sg:postcode":"78613",
    "sg:province":"TX",
    "wof:name":"Teksavers Rentals LLC",
    "wof:placetype":"venue"
},
  "geometry": {"coordinates":[-97.83710499999999,30.480753],"type":"Point"}
}