{
  "type": "Feature",
  "properties": {
    "iso:country":"US",
    "sg:address":"2108 109th St",
    "sg:city":"Lubbock",
    "sg:classifiers":[
        {
            "category":"Freight",
            "type":"Transportation"
        }
    ],
    "sg:phone":"+1 806 748 6068",
    "sg:postcode":"79423",
    "sg:province":"TX",
    "sg:tags":[
        "trucking"
    ],
    "wof:name":"K P Trucking",
    "wof:placetype":"venue"
},
  "geometry": {"coordinates":[-101.86179199999999,33.495335],"type":"Point"}
}