{
  "type": "Feature",
  "properties": {
    "iso:country":"US",
    "sg:address":"222 Old Oak Dr",
    "sg:city":"Georgetown",
    "sg:classifiers":[
        {
            "category":"Recreation",
            "type":"Entertainment"
        }
    ],
    "sg:phone":"+1 512 930 0019",
    "sg:postcode":"78628",
    "sg:province":"TX",
    "wof:name":"Hill Cntry Swim Scubing Diving",
    "wof:placetype":"venue"
},
  "geometry": {"coordinates":[-97.731083,30.69137],"type":"Point"}
}