{
  "type": "Feature",
  "properties": {
    "iso:country":"US",
    "sg:address":"712 S Belt Line Rd",
    "sg:city":"Irving",
    "sg:classifiers":[
        {
            "category":"Wholesale",
            "subcategory":"Non-durable Goods",
            "type":"Manufacturing & Wholesale Goods"
        }
    ],
    "sg:phone":"+1 972 313 9444",
    "sg:postcode":"75060",
    "sg:province":"TX",
    "wof:name":"Birds Etc",
    "wof:placetype":"venue"
},
  "geometry": {"coordinates":[-96.994427,32.805196],"type":"Point"}
}