{
  "type": "Feature",
  "properties": {
    "iso:country":"US",
    "sg:address":"5822 Dean Martin",
    "sg:city":"San Antonio",
    "sg:classifiers":[
        {
            "category":"Professional",
            "subcategory":"Computer Services",
            "type":"Services"
        }
    ],
    "sg:phone":"+1 210 523 7587",
    "sg:postcode":"78240",
    "sg:province":"TX",
    "sg:tags":[
        "development",
        "software"
    ],
    "wof:name":"Concepts For Creation Technolo",
    "wof:placetype":"venue"
},
  "geometry": {"coordinates":[-98.60127300000001,29.505763],"type":"Point"}
}