{
  "type": "Feature",
  "properties": {
    "iso:country":"US",
    "sg:address":"2400 Alliance Blvd",
    "sg:city":"Fort Worth",
    "sg:classifiers":[
        {
            "category":"Restaurant",
            "type":"Food & Drink"
        }
    ],
    "sg:phone":"+1 817 337 9696",
    "sg:postcode":"76177",
    "sg:province":"TX",
    "wof:name":"Mc Donald's",
    "wof:placetype":"venue"
},
  "geometry": {"coordinates":[-97.310832,32.98607],"type":"Point"}
}