{
  "type": "Feature",
  "properties": {
    "iso:country":"US",
    "sg:address":"12973 Bucknell Dr",
    "sg:city":"El Paso",
    "sg:classifiers":[
        {
            "category":"Retail",
            "subcategory":"Repair Shop",
            "type":"Services"
        }
    ],
    "sg:phone":"+1 915 852 2874",
    "sg:postcode":"79928",
    "sg:province":"TX",
    "wof:name":"Spark Machine Shop",
    "wof:placetype":"venue"
},
  "geometry": {"coordinates":[-106.237099,31.670249],"type":"Point"}
}