{
  "type": "Feature",
  "properties": {
    "iso:country":"US",
    "sg:address":"395 Sawdust Rd",
    "sg:city":"Spring",
    "sg:classifiers":[
        {
            "category":"Social Services",
            "type":"Services"
        },
        {
            "category":"Professional",
            "subcategory":"Employment Agencies",
            "type":"Services"
        }
    ],
    "sg:phone":"+1 713 540 8773",
    "sg:postcode":"77380",
    "sg:province":"TX",
    "sg:tags":[
        "workers'",
        "placement",
        "volunteer"
    ],
    "wof:name":"Godfrey Educational Foundation",
    "wof:placetype":"venue"
},
  "geometry": {"coordinates":[-95.44780799999999,30.126676],"type":"Point"}
}