{
  "type": "Feature",
  "properties": {
    "iso:country":"US",
    "sg:address":"635 W Campbell Rd",
    "sg:city":"Richardson",
    "sg:classifiers":[
        {
            "category":"Restaurant",
            "type":"Food & Drink"
        }
    ],
    "sg:phone":"+1 972 235 7906",
    "sg:postcode":"75080",
    "sg:province":"TX",
    "sg:tags":[
        "house",
        "steak"
    ],
    "wof:name":"Beaucoup",
    "wof:placetype":"venue"
},
  "geometry": {"coordinates":[-96.741851,32.978081],"type":"Point"}
}