{
  "type": "Feature",
  "properties": {
    "iso:country":"US",
    "sg:address":"5915 Worth St",
    "sg:city":"Dallas",
    "sg:classifiers":[
        {
            "category":"Wholesale",
            "subcategory":"Non-durable Goods",
            "type":"Manufacturing & Wholesale Goods"
        }
    ],
    "sg:phone":"+1 214 826 2047",
    "sg:postcode":"75214",
    "sg:province":"TX",
    "wof:name":"T AM Imports",
    "wof:placetype":"venue"
},
  "geometry": {"coordinates":[-96.754863,32.808248],"type":"Point"}
}