{
  "type": "Feature",
  "properties": {
    "iso:country":"US",
    "sg:address":"1225 N Hwy 377",
    "sg:city":"Pilot Point",
    "sg:classifiers":[
        {
            "category":"Food & Beverages",
            "subcategory":"Groceries & Convenience Stores",
            "type":"Retail Goods"
        }
    ],
    "sg:phone":"+1 940 686 2281",
    "sg:postcode":"76258",
    "sg:province":"TX",
    "wof:name":"Jerry's Convenient Stop",
    "wof:placetype":"venue"
},
  "geometry": {"coordinates":[-96.92768700000001,33.438763],"type":"Point"}
}