{
  "type": "Feature",
  "properties": {
    "iso:country":"US",
    "sg:address":"1310 US Hwy 287",
    "sg:city":"Midlothian",
    "sg:classifiers":[
        {
            "category":"Restaurant",
            "type":"Food & Drink"
        }
    ],
    "sg:phone":"+1 972 775 1974",
    "sg:postcode":"76065",
    "sg:province":"TX",
    "wof:name":"Mc Donald's",
    "wof:placetype":"venue"
},
  "geometry": {"coordinates":[-96.980116,32.475858],"type":"Point"}
}