{
  "type": "Feature",
  "properties": {
    "iso:country":"US",
    "sg:address":"1367 S Loop W",
    "sg:city":"Houston",
    "sg:classifiers":[
        {
            "category":"Animal Shelter",
            "type":"Public Place"
        }
    ],
    "sg:phone":"+1 713 799 1300",
    "sg:postcode":"77054",
    "sg:province":"TX",
    "sg:tags":[
        "adult"
    ],
    "wof:name":"Carmen's Boutique",
    "wof:placetype":"venue"
},
  "geometry": {"coordinates":[-95.396925,29.679226],"type":"Point"}
}