{
  "type": "Feature",
  "properties": {
    "iso:country":"US",
    "sg:address":"519 S East St",
    "sg:city":"Weimar",
    "sg:classifiers":[
        {
            "category":"Building & Trades",
            "subcategory":"Construction",
            "type":"Services"
        }
    ],
    "sg:phone":"+1 979 725 1500",
    "sg:postcode":"78962",
    "sg:province":"TX",
    "sg:tags":[
        "general",
        "contractor"
    ],
    "wof:name":"Pesak Brothers Construction",
    "wof:placetype":"venue"
},
  "geometry": {"coordinates":[-96.775098,29.698147],"type":"Point"}
}