{
  "type": "Feature",
  "properties": {
    "iso:country":"US",
    "sg:address":"2411 Smith St",
    "sg:city":"Houston",
    "sg:classifiers":[
        {
            "category":"Professional",
            "subcategory":"Lawyer & Legal Services",
            "type":"Services"
        }
    ],
    "sg:phone":"+1 713 520 1890",
    "sg:postcode":"77006",
    "sg:province":"TX",
    "wof:name":"Adame Derek Atty",
    "wof:placetype":"venue"
},
  "geometry": {"coordinates":[-95.376801,29.748199],"type":"Point"}
}