{
  "type": "Feature",
  "properties": {
    "iso:country":"US",
    "sg:address":"509 W 12th St",
    "sg:city":"Austin",
    "sg:classifiers":[
        {
            "category":"Manufacturing",
            "subcategory":"Printing",
            "type":"Manufacturing & Wholesale Goods"
        }
    ],
    "sg:phone":"+1 512 435 2256",
    "sg:postcode":"78701",
    "sg:province":"TX",
    "sg:tags":[
        "publishing"
    ],
    "wof:name":"Covington Press",
    "wof:placetype":"venue"
},
  "geometry": {"coordinates":[-97.74623699999999,30.275333],"type":"Point"}
}