{
  "type": "Feature",
  "properties": {
    "iso:country":"US",
    "sg:address":"50 E Elizabeth St",
    "sg:city":"Brownsville",
    "sg:classifiers":[
        {
            "category":"Building & Trades",
            "subcategory":"Electrical",
            "type":"Services"
        }
    ],
    "sg:phone":"+1 956 546 6247",
    "sg:postcode":"78520",
    "sg:province":"TX",
    "sg:tags":[
        "electrician",
        "contractor"
    ],
    "wof:name":"Shumacher Electric Corporation",
    "wof:placetype":"venue"
},
  "geometry": {"coordinates":[-97.506332,25.9088],"type":"Point"}
}