{
  "type": "Feature",
  "properties": {
    "iso:country":"US",
    "sg:address":"1500 Los Sabales Dr",
    "sg:city":"Brownsville",
    "sg:classifiers":[
        {
            "category":"Wholesale",
            "subcategory":"Vending Machines",
            "type":"Manufacturing & Wholesale Goods"
        }
    ],
    "sg:phone":"+1 956 546 7612",
    "sg:postcode":"78520",
    "sg:province":"TX",
    "sg:tags":[
        "operator"
    ],
    "wof:name":"Snaks & More Vending",
    "wof:placetype":"venue"
},
  "geometry": {"coordinates":[-97.51200900000001,25.941267],"type":"Point"}
}