{
  "type": "Feature",
  "properties": {
    "iso:country":"US",
    "sg:address":"1927 E Belt Line Rd Ste 160",
    "sg:city":"Carrollton",
    "sg:classifiers":[
        {
            "category":"Professional",
            "subcategory":"Employment Agencies",
            "type":"Services"
        }
    ],
    "sg:phone":"+1 972 478 5888",
    "sg:postcode":"75006",
    "sg:province":"TX",
    "sg:website":"www.pacesetterpersonnel.com",
    "wof:name":"Pacesetter Personnel Service",
    "wof:placetype":"venue"
},
  "geometry": {"coordinates":[-96.889045,32.95466],"type":"Point"}
}