{
  "type": "Feature",
  "properties": {
    "iso:country":"US",
    "sg:address":"2708 Main St",
    "sg:city":"Dallas",
    "sg:classifiers":[
        {
            "category":"Bars & Pubs",
            "type":"Food & Drink"
        }
    ],
    "sg:phone":"+1 214 742 2216",
    "sg:postcode":"75226",
    "sg:province":"TX",
    "sg:tags":[
        "drinking"
    ],
    "wof:name":"Lazerz",
    "wof:placetype":"venue"
},
  "geometry": {"coordinates":[-96.783503,32.784029],"type":"Point"}
}