{
  "type": "Feature",
  "properties": {
    "iso:country":"US",
    "sg:address":"5125 River Bluff Dr",
    "sg:city":"Fort Worth",
    "sg:classifiers":[
        {
            "category":"Professional",
            "subcategory":"Management & Consulting",
            "type":"Services"
        }
    ],
    "sg:phone":"+1 817 294 1717",
    "sg:postcode":"76132",
    "sg:province":"TX",
    "sg:tags":[
        "business"
    ],
    "wof:name":"Coyote Consulting Inc",
    "wof:placetype":"venue"
},
  "geometry": {"coordinates":[-97.42657699999999,32.671658],"type":"Point"}
}