{
  "type": "Feature",
  "properties": {
    "iso:country":"US",
    "sg:address":"1344 Eastside Dr",
    "sg:city":"Mesquite",
    "sg:classifiers":[
        {
            "category":"Building & Trades",
            "subcategory":"Construction",
            "type":"Services"
        }
    ],
    "sg:phone":"+1 972 288 4414",
    "sg:postcode":"75149",
    "sg:province":"TX",
    "sg:tags":[
        "carpenter"
    ],
    "wof:name":"Derrick's Place",
    "wof:placetype":"venue"
},
  "geometry": {"coordinates":[-96.578812,32.75154],"type":"Point"}
}