{
  "type": "Feature",
  "properties": {
    "iso:country":"US",
    "sg:address":"12012 Wickchester Ln",
    "sg:city":"Houston",
    "sg:classifiers":[
        {
            "category":"Manufacturing",
            "subcategory":"Chemicals & Compounds",
            "type":"Manufacturing & Wholesale Goods"
        }
    ],
    "sg:phone":"+1 281 754 5800",
    "sg:postcode":"77079",
    "sg:province":"TX",
    "sg:tags":[
        "mfg",
        "plastic"
    ],
    "wof:name":"Dexco Polymers",
    "wof:placetype":"venue"
},
  "geometry": {"coordinates":[-95.59954,29.788568],"type":"Point"}
}