{
  "type": "Feature",
  "properties": {
    "iso:country":"US",
    "sg:address":"1201 E Ridge Rd",
    "sg:city":"Mcallen",
    "sg:classifiers":[
        {
            "category":"Wholesale",
            "subcategory":"Medical Equipment & Supplies",
            "type":"Manufacturing & Wholesale Goods"
        },
        {
            "category":"Shopping",
            "subcategory":"Pharmacy",
            "type":"Retail Goods"
        }
    ],
    "sg:phone":"+1 956 618 3313",
    "sg:postcode":"78503",
    "sg:province":"TX",
    "sg:tags":[
        "home",
        "health",
        "care"
    ],
    "wof:name":"Advanced Medical Dme",
    "wof:placetype":"venue"
},
  "geometry": {"coordinates":[-98.209864,26.183929],"type":"Point"}
}