{
  "type": "Feature",
  "properties": {
    "iso:country":"US",
    "sg:address":"160 W Slaughter Ln",
    "sg:city":"Austin",
    "sg:classifiers":[
        {
            "category":"Personal",
            "subcategory":"Beauty Salon",
            "type":"Services"
        }
    ],
    "sg:phone":"+1 512 282 5727",
    "sg:postcode":"78748",
    "sg:province":"TX",
    "sg:tags":[
        "shop"
    ],
    "wof:name":"Salon 101",
    "wof:placetype":"venue"
},
  "geometry": {"coordinates":[-97.791203,30.167344],"type":"Point"}
}