{
  "type": "Feature",
  "properties": {
    "iso:country":"US",
    "sg:address":"1710 Humble Place Dr",
    "sg:city":"Humble",
    "sg:classifiers":[
        {
            "category":"Home & Garden",
            "subcategory":"Household Appliances",
            "type":"Retail Goods"
        },
        {
            "category":"Wholesale",
            "subcategory":"Electrical",
            "type":"Manufacturing & Wholesale Goods"
        }
    ],
    "sg:phone":"+1 281 446 7613",
    "sg:postcode":"77338",
    "sg:province":"TX",
    "sg:tags":[
        "fan",
        "fixture",
        "lighting"
    ],
    "sg:website":"www.carolslighting.com",
    "wof:name":"Carols Lighting and Fan Shop",
    "wof:placetype":"venue"
},
  "geometry": {"coordinates":[-95.24766099999999,29.99519],"type":"Point"}
}