{
  "type": "Feature",
  "properties": {
    "iso:country":"US",
    "sg:address":"150 W Arrowhead Dr",
    "sg:city":"San Antonio",
    "sg:classifiers":[
        {
            "category":"Shopping",
            "subcategory":"Jewelry",
            "type":"Retail Goods"
        }
    ],
    "sg:phone":"+1 210 432 0550",
    "sg:postcode":"78228",
    "sg:province":"TX",
    "wof:name":"Lanctot Mineral Specimens",
    "wof:placetype":"venue"
},
  "geometry": {"coordinates":[-98.576003,29.479413],"type":"Point"}
}