{
  "type": "Feature",
  "properties": {
    "iso:country":"US",
    "sg:address":"2414 Chalk Hill Rd",
    "sg:city":"Dallas",
    "sg:classifiers":[
        {
            "category":"Building & Trades",
            "subcategory":"Construction",
            "type":"Services"
        }
    ],
    "sg:phone":"+1 214 638 3770",
    "sg:postcode":"75212",
    "sg:province":"TX",
    "sg:tags":[
        "general",
        "contractor"
    ],
    "wof:name":"Koedyker and Kenyon Cnstr",
    "wof:placetype":"venue"
},
  "geometry": {"coordinates":[-96.903991,32.773416],"type":"Point"}
}