{
  "type": "Feature",
  "properties": {
    "iso:country":"US",
    "sg:address":"3872 Hemphill St",
    "sg:city":"Fort Worth",
    "sg:classifiers":[
        {
            "category":"Recreation",
            "subcategory":"Marina",
            "type":"Entertainment"
        }
    ],
    "sg:phone":"+1 817 924 5004",
    "sg:postcode":"76110",
    "sg:province":"TX",
    "wof:name":"LA Marina Express",
    "wof:placetype":"venue"
},
  "geometry": {"coordinates":[-97.33180400000001,32.691432],"type":"Point"}
}