{
  "type": "Feature",
  "properties": {
    "iso:country":"US",
    "sg:address":"1701 Ashland Ave",
    "sg:city":"Fort Worth",
    "sg:classifiers":[
        {
            "category":"Professional",
            "subcategory":"Art Services",
            "type":"Services"
        }
    ],
    "sg:phone":"+1 817 377 3555",
    "sg:postcode":"76107",
    "sg:province":"TX",
    "sg:tags":[
        "artist"
    ],
    "wof:name":"Laurie Leisure",
    "wof:placetype":"venue"
},
  "geometry": {"coordinates":[-97.383653,32.743241],"type":"Point"}
}