{
  "type": "Feature",
  "properties": {
    "iso:country":"US",
    "sg:address":"608 E Milam St",
    "sg:city":"Mexia",
    "sg:classifiers":[
        {
            "category":"Building & Trades",
            "subcategory":"Construction",
            "type":"Services"
        }
    ],
    "sg:phone":"+1 254 562 9285",
    "sg:postcode":"76667",
    "sg:province":"TX",
    "sg:tags":[
        "excavation",
        "contractor"
    ],
    "wof:name":"Holloway Dozer Service",
    "wof:placetype":"venue"
},
  "geometry": {"coordinates":[-96.47879,31.684146],"type":"Point"}
}