{
  "type": "Feature",
  "properties": {
    "iso:country":"US",
    "sg:address":"536 S Texas Blvd",
    "sg:city":"Weslaco",
    "sg:classifiers":[
        {
            "category":"Health Services",
            "subcategory":"Clinic",
            "type":"Services"
        }
    ],
    "sg:phone":"+1 956 973 0373",
    "sg:postcode":"78596",
    "sg:province":"TX",
    "sg:tags":[
        "home"
    ],
    "wof:name":"Fey Home Health Svc",
    "wof:placetype":"venue"
},
  "geometry": {"coordinates":[-97.9907,26.156465],"type":"Point"}
}