{
  "type": "Feature",
  "properties": {
    "iso:country":"US",
    "sg:address":"1107 Hillje Ave",
    "sg:city":"Schulenburg",
    "sg:classifiers":[
        {
            "category":"Social Services",
            "type":"Services"
        }
    ],
    "sg:phone":"+1 979 743 4036",
    "sg:postcode":"78956",
    "sg:province":"TX",
    "wof:name":"Schulenberg Community Svc Ctr",
    "wof:placetype":"venue"
},
  "geometry": {"coordinates":[-96.909398,29.674774],"type":"Point"}
}