{
  "type": "Feature",
  "properties": {
    "iso:country":"US",
    "sg:address":"18206 Pickering Rd",
    "sg:city":"Conroe",
    "sg:classifiers":[
        {
            "category":"Manufacturing",
            "subcategory":"Tools & Machinery",
            "type":"Manufacturing & Wholesale Goods"
        }
    ],
    "sg:phone":"+1 281 572 2624",
    "sg:postcode":"77302",
    "sg:province":"TX",
    "sg:tags":[
        "machine",
        "shop"
    ],
    "wof:name":"Hudson Machine",
    "wof:placetype":"venue"
},
  "geometry": {"coordinates":[-95.28522100000001,30.191206],"type":"Point"}
}