{
  "type": "Feature",
  "properties": {
    "iso:country":"US",
    "sg:address":"2243 Pecan Blvd",
    "sg:city":"Mcallen",
    "sg:classifiers":[
        {
            "category":"Food & Beverages",
            "subcategory":"Liquor & Beverages",
            "type":"Retail Goods"
        }
    ],
    "sg:phone":"+1 956 631 3145",
    "sg:postcode":"78501",
    "sg:province":"TX",
    "sg:tags":[
        "beer",
        "ale"
    ],
    "wof:name":"Rumania Drive Thry",
    "wof:placetype":"venue"
},
  "geometry": {"coordinates":[-98.24200399999999,26.218878],"type":"Point"}
}