{
  "type": "Feature",
  "properties": {
    "iso:country":"US",
    "sg:address":"1300 Pasaguarda Dr",
    "sg:city":"Austin",
    "sg:classifiers":[
        {
            "category":"Real Estate",
            "subcategory":"Real Estate Agent",
            "type":"Services"
        }
    ],
    "sg:phone":"+1 512 327 3640",
    "sg:postcode":"78746",
    "sg:province":"TX",
    "wof:name":"Charles A & Linda A Claibure",
    "wof:placetype":"venue"
},
  "geometry": {"coordinates":[-97.809596,30.273295],"type":"Point"}
}