{
  "type": "Feature",
  "properties": {
    "iso:country":"US",
    "sg:address":"709 W Davis St",
    "sg:city":"Conroe",
    "sg:classifiers":[
        {
            "category":"Professional",
            "subcategory":"Printing & Photocopies",
            "type":"Services"
        }
    ],
    "sg:phone":"+1 936 788 1950",
    "sg:postcode":"77301",
    "sg:province":"TX",
    "sg:tags":[
        "duplicating",
        "copying"
    ],
    "wof:name":"Conroe Copy Ctr",
    "wof:placetype":"venue"
},
  "geometry": {"coordinates":[-95.46388399999999,30.312187],"type":"Point"}
}