{
  "type": "Feature",
  "properties": {
    "iso:country":"US",
    "sg:address":"9090 Skillman St Ste 182-A PMB 264",
    "sg:city":"Dallas",
    "sg:classifiers":[
        {
            "category":"Real Estate",
            "subcategory":"Real Estate Services",
            "type":"Services"
        }
    ],
    "sg:phone":"+1 214 343 9403",
    "sg:postcode":"75243",
    "sg:province":"TX",
    "wof:name":"O & Eddy",
    "wof:placetype":"venue"
},
  "geometry": {"coordinates":[-96.71953600000001,32.896924],"type":"Point"}
}