{
  "type": "Feature",
  "properties": {
    "iso:country":"US",
    "sg:address":"9189 Winkler Dr",
    "sg:city":"Houston",
    "sg:classifiers":[
        {
            "category":"Manufacturing",
            "subcategory":"Tools & Machinery",
            "type":"Manufacturing & Wholesale Goods"
        }
    ],
    "sg:phone":"+1 713 946 4334",
    "sg:postcode":"77017",
    "sg:province":"TX",
    "sg:tags":[
        "filling"
    ],
    "wof:name":"Feige Filling Technology USA",
    "wof:placetype":"venue"
},
  "geometry": {"coordinates":[-95.254474,29.670377],"type":"Point"}
}