{
  "type": "Feature",
  "properties": {
    "iso:country":"US",
    "sg:address":"3617 Granada Trl",
    "sg:city":"Denton",
    "sg:classifiers":[
        {
            "category":"Real Estate",
            "subcategory":"Real Estate Agent",
            "type":"Services"
        }
    ],
    "sg:phone":"+1 940 383 8701",
    "sg:postcode":"76205",
    "sg:province":"TX",
    "wof:name":"J John Battaglia",
    "wof:placetype":"venue"
},
  "geometry": {"coordinates":[-97.12233999999999,33.166016],"type":"Point"}
}