{
  "type": "Feature",
  "properties": {
    "iso:country":"US",
    "sg:address":"1717 S Hampton Rd",
    "sg:city":"Glenn Heights",
    "sg:classifiers":[
        {
            "category":"Building & Trades",
            "subcategory":"Construction",
            "type":"Services"
        }
    ],
    "sg:phone":"+1 972 223 0859",
    "sg:postcode":"75154",
    "sg:province":"TX",
    "sg:tags":[
        "contractor"
    ],
    "sg:website":"www.allphaserr.com",
    "wof:name":"All Phase Remodeling & Restoration Company",
    "wof:placetype":"venue"
},
  "geometry": {"coordinates":[-96.856859,32.559022],"type":"Point"}
}