{
  "type": "Feature",
  "properties": {
    "iso:country":"US",
    "sg:address":"10715 Galsworthy Ln",
    "sg:city":"Austin",
    "sg:classifiers":[
        {
            "category":"Building & Trades",
            "subcategory":"Plumbing",
            "type":"Services"
        }
    ],
    "sg:phone":"+1 512 394 1064",
    "sg:postcode":"78739",
    "sg:province":"TX",
    "sg:tags":[
        "contractor"
    ],
    "wof:name":"Dan Thomas/AC",
    "wof:placetype":"venue"
},
  "geometry": {"coordinates":[-97.885164,30.187291],"type":"Point"}
}