{
  "type": "Feature",
  "properties": {
    "iso:country":"US",
    "sg:address":"6804 Vallecito Dr",
    "sg:city":"Austin",
    "sg:classifiers":[
        {
            "category":"Shopping",
            "subcategory":"Beauty & Cosmetics",
            "type":"Retail Goods"
        }
    ],
    "sg:phone":"+1 512 331 7200",
    "sg:postcode":"78759",
    "sg:province":"TX",
    "sg:tags":[
        "equipment",
        "perfume",
        "supply"
    ],
    "wof:name":"Mary Kay Cosmetics",
    "wof:placetype":"venue"
},
  "geometry": {"coordinates":[-97.765568,30.420714],"type":"Point"}
}