{
  "type": "Feature",
  "properties": {
    "iso:country":"US",
    "sg:address":"1830 Bolsover St",
    "sg:city":"Houston",
    "sg:classifiers":[
        {
            "category":"Professional",
            "subcategory":"Lawyer & Legal Services",
            "type":"Services"
        }
    ],
    "sg:phone":"+1 713 522 6326",
    "sg:postcode":"77005",
    "sg:province":"TX",
    "wof:name":"Baldwin J Michael Atty",
    "wof:placetype":"venue"
},
  "geometry": {"coordinates":[-95.404404,29.7215],"type":"Point"}
}