{
  "type": "Feature",
  "properties": {
    "iso:country":"US",
    "sg:address":"1605 US Hwy 87",
    "sg:city":"Lamesa",
    "sg:classifiers":[
        {
            "category":"Wholesale",
            "subcategory":"Machinery & Supplies",
            "type":"Manufacturing & Wholesale Goods"
        }
    ],
    "sg:phone":"+1 806 872 5474",
    "sg:postcode":"79331",
    "sg:province":"TX",
    "sg:tags":[
        "farm",
        "equipment"
    ],
    "wof:name":"B E Implement Co",
    "wof:placetype":"venue"
},
  "geometry": {"coordinates":[-101.951688,32.747577],"type":"Point"}
}