{
  "type": "Feature",
  "properties": {
    "iso:country":"US",
    "sg:address":"2701 Grand Ave",
    "sg:city":"Dallas",
    "sg:classifiers":[
        {
            "category":"Professional",
            "subcategory":"Lawyer & Legal Services",
            "type":"Services"
        }
    ],
    "sg:phone":"+1 214 421 2535",
    "sg:postcode":"75215",
    "sg:province":"TX",
    "wof:name":"Beckles Robert O Atty",
    "wof:placetype":"venue"
},
  "geometry": {"coordinates":[-96.77330000000001,32.770401],"type":"Point"}
}