{
  "type": "Feature",
  "properties": {
    "iso:country":"US",
    "sg:address":"30 Backbay Cir",
    "sg:city":"Galveston",
    "sg:classifiers":[
        {
            "category":"Organizations",
            "subcategory":"Community Association",
            "type":"Services"
        }
    ],
    "sg:phone":"+1 409 740 7191",
    "sg:postcode":"77551",
    "sg:province":"TX",
    "wof:name":"Krewe of Harlequins Inc",
    "wof:placetype":"venue"
},
  "geometry": {"coordinates":[-94.84307099999999,29.275599],"type":"Point"}
}