{
  "type": "Feature",
  "properties": {
    "iso:country":"US",
    "sg:address":"1513 San Patricia Dr",
    "sg:city":"Pharr",
    "sg:classifiers":[
        {
            "category":"Wholesale",
            "subcategory":"Scrap",
            "type":"Manufacturing & Wholesale Goods"
        }
    ],
    "sg:phone":"+1 956 283 7944",
    "sg:postcode":"78577",
    "sg:province":"TX",
    "sg:tags":[
        "recycling",
        "center"
    ],
    "wof:name":"Sale Shapiora",
    "wof:placetype":"venue"
},
  "geometry": {"coordinates":[-98.19761699999999,26.210846],"type":"Point"}
}