{
  "type": "Feature",
  "properties": {
    "iso:country":"US",
    "sg:address":"901 20th St",
    "sg:city":"Plano",
    "sg:classifiers":[
        {
            "category":"Autos & Motor Vehicles",
            "subcategory":"Auto Supplies",
            "type":"Retail Goods"
        }
    ],
    "sg:phone":"+1 972 423 4466",
    "sg:postcode":"75074",
    "sg:province":"TX",
    "sg:tags":[
        "tire"
    ],
    "wof:name":"Naomi Goolsbee",
    "wof:placetype":"venue"
},
  "geometry": {"coordinates":[-96.702744,33.026691],"type":"Point"}
}