{
  "type": "Feature",
  "properties": {
    "iso:country":"US",
    "sg:address":"7155 Roos Rd",
    "sg:city":"Houston",
    "sg:classifiers":[
        {
            "category":"Shopping",
            "subcategory":"Bicycles & Sporting Goods",
            "type":"Retail Goods"
        }
    ],
    "sg:phone":"+1 713 541 4138",
    "sg:postcode":"77074",
    "sg:province":"TX",
    "sg:tags":[
        "equipment",
        "windsurfing"
    ],
    "sg:website":"http://www.sharkbaitsurfwax.com",
    "wof:name":"Sharkbait Surf Supplies",
    "wof:placetype":"venue"
},
  "geometry": {"coordinates":[-95.51030900000001,29.699513],"type":"Point"}
}