{
  "type": "Feature",
  "properties": {
    "iso:country":"US",
    "sg:address":"12226 Oak Hollow Ln",
    "sg:city":"Pinehurst",
    "sg:classifiers":[
        {
            "category":"Building & Trades",
            "subcategory":"Landscaping Services",
            "type":"Services"
        }
    ],
    "sg:phone":"+1 281 356 4746",
    "sg:postcode":"77362",
    "sg:province":"TX",
    "sg:tags":[
        "landscape"
    ],
    "wof:name":"Beyond Landscaping/Beyond Plan",
    "wof:placetype":"venue"
},
  "geometry": {"coordinates":[-95.657258,30.144906],"type":"Point"}
}