{
  "type": "Feature",
  "properties": {
    "iso:country":"US",
    "sg:address":"920 N McGee St",
    "sg:city":"Borger",
    "sg:classifiers":[
        {
            "category":"Professional",
            "subcategory":"Management & Consulting",
            "type":"Services"
        }
    ],
    "sg:phone":"+1 806 274 9491",
    "sg:postcode":"79007",
    "sg:province":"TX",
    "sg:tags":[
        "fire",
        "consultant",
        "protection"
    ],
    "wof:name":"WEBB Murray & Assoc",
    "wof:placetype":"venue"
},
  "geometry": {"coordinates":[-101.39411200000001,35.676533],"type":"Point"}
}