{
  "type": "Feature",
  "properties": {
    "iso:country":"US",
    "sg:address":"3000 N 10th St",
    "sg:city":"Mcallen",
    "sg:classifiers":[
        {
            "category":"Shopping",
            "subcategory":"Shoes",
            "type":"Retail Goods"
        }
    ],
    "sg:phone":"+1 956 687 2694",
    "sg:postcode":"78501",
    "sg:province":"TX",
    "sg:tags":[
        "unisex"
    ],
    "wof:name":"S A S Factory Shoes 41",
    "wof:placetype":"venue"
},
  "geometry": {"coordinates":[-98.225612,26.228629],"type":"Point"}
}