{
  "type": "Feature",
  "properties": {
    "iso:country":"US",
    "sg:address":"1202 Park St",
    "sg:city":"Fort Worth",
    "sg:classifiers":[
        {
            "category":"Building & Trades",
            "subcategory":"Electrical",
            "type":"Services"
        }
    ],
    "sg:phone":"+1 817 624 4420",
    "sg:postcode":"76106",
    "sg:province":"TX",
    "sg:tags":[
        "electrical",
        "contractor"
    ],
    "wof:name":"Dan Wright Electric",
    "wof:placetype":"venue"
},
  "geometry": {"coordinates":[-97.363277,32.775997],"type":"Point"}
}