{
  "type": "Feature",
  "properties": {
    "iso:country":"US",
    "sg:address":"911 Keyport Ln",
    "sg:city":"Houston",
    "sg:classifiers":[
        {
            "category":"Manufacturing",
            "subcategory":"Tools & Machinery",
            "type":"Manufacturing & Wholesale Goods"
        }
    ],
    "sg:phone":"+1 713 637 8220",
    "sg:postcode":"77015",
    "sg:province":"TX",
    "sg:tags":[
        "machine",
        "shop"
    ],
    "wof:name":"M & Y Machine Shop",
    "wof:placetype":"venue"
},
  "geometry": {"coordinates":[-95.215542,29.771022],"type":"Point"}
}