{
  "type": "Feature",
  "properties": {
    "iso:country":"US",
    "sg:address":"304 Edwards St",
    "sg:city":"Riesel",
    "sg:classifiers":[
        {
            "category":"Organizations",
            "subcategory":"Religious Organization",
            "type":"Services"
        }
    ],
    "sg:phone":"+1 254 896 3421",
    "sg:postcode":"76682",
    "sg:province":"TX",
    "sg:tags":[
        "church"
    ],
    "wof:name":"First Baptist Church",
    "wof:placetype":"venue"
},
  "geometry": {"coordinates":[-96.92058400000001,31.476811],"type":"Point"}
}