{
  "type": "Feature",
  "properties": {
    "iso:country":"US",
    "sg:address":"9350 Co Rd 216",
    "sg:city":"Celina",
    "sg:classifiers":[
        {
            "category":"Wholesale",
            "subcategory":"Stationery",
            "type":"Manufacturing & Wholesale Goods"
        }
    ],
    "sg:phone":"+1 972 382 8313",
    "sg:postcode":"75009",
    "sg:province":"TX",
    "sg:tags":[
        "paper"
    ],
    "wof:name":"E M C Distributtion",
    "wof:placetype":"venue"
},
  "geometry": {"coordinates":[-96.648972,33.360073],"type":"Point"}
}