{
  "type": "Feature",
  "properties": {
    "iso:country":"US",
    "sg:address":"1408 Grimes Dr",
    "sg:city":"Carrollton",
    "sg:classifiers":[
        {
            "category":"Professional",
            "subcategory":"Art Services",
            "type":"Services"
        }
    ],
    "sg:phone":"+1 972 939 1377",
    "sg:postcode":"75010",
    "sg:province":"TX",
    "sg:tags":[
        "graphic",
        "designer"
    ],
    "wof:name":"Scribbles Art Svc",
    "wof:placetype":"venue"
},
  "geometry": {"coordinates":[-96.933061,33.014843],"type":"Point"}
}