{
  "type": "Feature",
  "properties": {
    "iso:country":"US",
    "sg:address":"2641 Via Valencia Ste 1",
    "sg:city":"Carrollton",
    "sg:classifiers":[
        {
            "category":"Food & Beverages",
            "subcategory":"Farmers Market",
            "type":"Retail Goods"
        }
    ],
    "sg:phone":"+1 972 416 0338",
    "sg:postcode":"75006",
    "sg:province":"TX",
    "sg:tags":[
        "operator",
        "oil"
    ],
    "wof:name":"Peh Geo Consultants",
    "wof:placetype":"venue"
},
  "geometry": {"coordinates":[-96.86523099999999,32.969238],"type":"Point"}
}