{
  "type": "Feature",
  "properties": {
    "iso:country":"US",
    "sg:address":"2001 S 40th St",
    "sg:city":"Mcallen",
    "sg:classifiers":[
        {
            "category":"Building & Trades",
            "subcategory":"Cleaning & Sanitation",
            "type":"Services"
        }
    ],
    "sg:phone":"+1 956 631 1363",
    "sg:postcode":"78503",
    "sg:province":"TX",
    "sg:tags":[
        "janitorial"
    ],
    "wof:name":"Juan Navarro Janitorial Service",
    "wof:placetype":"venue"
},
  "geometry": {"coordinates":[-98.267747,26.191838],"type":"Point"}
}