{
  "type": "Feature",
  "properties": {
    "iso:country":"US",
    "sg:address":"9033 Premier Row",
    "sg:city":"Dallas",
    "sg:classifiers":[
        {
            "category":"Building & Trades",
            "subcategory":"Construction",
            "type":"Services"
        }
    ],
    "sg:phone":"+1 214 676 5475",
    "sg:postcode":"75247",
    "sg:province":"TX",
    "sg:tags":[
        "home",
        "builder"
    ],
    "wof:name":"Affordable Homes",
    "wof:placetype":"venue"
},
  "geometry": {"coordinates":[-96.896495,32.818179],"type":"Point"}
}