{
  "type": "Feature",
  "properties": {
    "iso:country":"US",
    "sg:address":"1522 Carroll Dr",
    "sg:city":"Garland",
    "sg:classifiers":[
        {
            "category":"Railroad",
            "type":"Transportation"
        }
    ],
    "sg:phone":"+1 972 278 3749",
    "sg:postcode":"75041",
    "sg:province":"TX",
    "sg:tags":[
        "operator",
        "line"
    ],
    "wof:name":"RR Landscape",
    "wof:placetype":"venue"
},
  "geometry": {"coordinates":[-96.651475,32.871936],"type":"Point"}
}