{
  "type": "Feature",
  "properties": {
    "iso:country":"US",
    "sg:address":"1313 E Hackberry Ave",
    "sg:city":"Mcallen",
    "sg:classifiers":[
        {
            "category":"Government",
            "subcategory":"Office",
            "type":"Public Place"
        }
    ],
    "sg:phone":"+1 956 682 2833",
    "sg:postcode":"78501",
    "sg:province":"TX",
    "sg:tags":[
        "marketing",
        "agriculture"
    ],
    "wof:name":"Agriculture United States Dept",
    "wof:placetype":"venue"
},
  "geometry": {"coordinates":[-98.204291,26.207639],"type":"Point"}
}