{
  "type": "Feature",
  "properties": {
    "iso:country":"US",
    "sg:address":"11140 Greenbay St",
    "sg:city":"Houston",
    "sg:classifiers":[
        {
            "category":"Education",
            "subcategory":"Preschool",
            "type":"Public Place"
        },
        {
            "category":"Education",
            "subcategory":"School",
            "type":"Public Place"
        }
    ],
    "sg:phone":"+1 713 465 4657",
    "sg:postcode":"77024",
    "sg:province":"TX",
    "sg:tags":[
        "elementary"
    ],
    "wof:name":"Chapelwood School For Young Children",
    "wof:placetype":"venue"
},
  "geometry": {"coordinates":[-95.509399,29.762699],"type":"Point"}
}