{
  "type": "Feature",
  "properties": {
    "iso:country":"US",
    "sg:address":"1916 Peyco Dr S",
    "sg:city":"Arlington",
    "sg:classifiers":[
        {
            "category":"Professional",
            "type":"Services"
        }
    ],
    "sg:phone":"+1 817 472 6769",
    "sg:postcode":"76001",
    "sg:province":"TX",
    "sg:tags":[
        "establishment"
    ],
    "wof:name":"Fastener Network Inc",
    "wof:placetype":"venue"
},
  "geometry": {"coordinates":[-97.13951900000001,32.632049],"type":"Point"}
}