{
  "type": "Feature",
  "properties": {
    "iso:country":"US",
    "sg:address":"339 Crescent Dr",
    "sg:city":"Fresno",
    "sg:classifiers":[
        {
            "category":"Manufacturing",
            "subcategory":"Metals",
            "type":"Manufacturing & Wholesale Goods"
        }
    ],
    "sg:phone":"+1 281 431 1259",
    "sg:postcode":"77545",
    "sg:province":"TX",
    "sg:tags":[
        "product",
        "fabricated",
        "mfg"
    ],
    "wof:name":"Pena Machine Works",
    "wof:placetype":"venue"
},
  "geometry": {"coordinates":[-95.450422,29.517882],"type":"Point"}
}