{
  "type": "Feature",
  "properties": {
    "iso:country":"US",
    "sg:address":"316 N Highway 377",
    "sg:city":"Roanoke",
    "sg:classifiers":[
        {
            "category":"Insurance",
            "subcategory":"Hazard Insurance",
            "type":"Services"
        }
    ],
    "sg:phone":"+1 817 491 5250",
    "sg:postcode":"76262",
    "sg:province":"TX",
    "sg:tags":[
        "commercial",
        "business"
    ],
    "wof:name":"People's Choice Insurance",
    "wof:placetype":"venue"
},
  "geometry": {"coordinates":[-97.22945900000001,33.000718],"type":"Point"}
}