{
  "type": "Feature",
  "properties": {
    "iso:country":"US",
    "sg:address":"602 Tidwell Rd",
    "sg:city":"Houston",
    "sg:classifiers":[
        {
            "category":"Recreation",
            "subcategory":"Boat Charter",
            "type":"Entertainment"
        },
        {
            "category":"Shopping",
            "subcategory":"Bicycles & Sporting Goods",
            "type":"Retail Goods"
        },
        {
            "category":"Autos & Motor Vehicles",
            "subcategory":"Boat Sales",
            "type":"Retail Goods"
        },
        {
            "category":"Retail",
            "subcategory":"Auto Repair",
            "type":"Services"
        }
    ],
    "sg:phone":"+1 713 697 8661",
    "sg:postcode":"77022",
    "sg:province":"TX",
    "sg:tags":[
        "supply",
        "outboard",
        "equipment",
        "boat-rental",
        "maintenance",
        "motors-repairing"
    ],
    "wof:name":"J & A Marine",
    "wof:placetype":"venue"
},
  "geometry": {"coordinates":[-95.368167,29.846141],"type":"Point"}
}