{
  "type": "Feature",
  "properties": {
    "iso:country":"US",
    "sg:address":"12545 Riata Vista Cir",
    "sg:city":"Austin",
    "sg:classifiers":[
        {
            "category":"Real Estate",
            "subcategory":"Real Estate Operator",
            "type":"Services"
        }
    ],
    "sg:phone":"+1 512 336 9796",
    "sg:postcode":"78727",
    "sg:province":"TX",
    "sg:tags":[
        "building",
        "apartment"
    ],
    "wof:name":"Riata Crossing",
    "wof:placetype":"venue"
},
  "geometry": {"coordinates":[-97.736901,30.430823],"type":"Point"}
}