{
  "type": "Feature",
  "properties": {
    "iso:country":"US",
    "sg:address":"15 N Pines Rd",
    "sg:city":"Spring",
    "sg:classifiers":[
        {
            "category":"Building & Trades",
            "subcategory":"Construction",
            "type":"Services"
        }
    ],
    "sg:phone":"+1 281 364 7289",
    "sg:postcode":"77357",
    "sg:province":"TX",
    "sg:tags":[
        "house"
    ],
    "wof:name":"Lovett Homes",
    "wof:placetype":"venue"
},
  "geometry": {"coordinates":[-95.18682800000001,30.187316],"type":"Point"}
}