{
  "type": "Feature",
  "properties": {
    "iso:country":"US",
    "sg:address":"1026 S Goode St",
    "sg:city":"Midland",
    "sg:classifiers":[
        {
            "category":"Building & Trades",
            "subcategory":"Plumbing",
            "type":"Services"
        }
    ],
    "sg:phone":"+1 432 570 9393",
    "sg:postcode":"79701",
    "sg:province":"TX",
    "sg:tags":[
        "plumbing",
        "contractor"
    ],
    "wof:name":"Lonnie Johns Plumbing",
    "wof:placetype":"venue"
},
  "geometry": {"coordinates":[-102.086715,31.983584],"type":"Point"}
}