{
  "type": "Feature",
  "properties": {
    "iso:country":"US",
    "sg:address":"9807 Vista View Dr",
    "sg:city":"Austin",
    "sg:classifiers":[
        {
            "category":"Place Of Worship",
            "type":"Public Place"
        }
    ],
    "sg:phone":"+1 512 250 0714",
    "sg:postcode":"78750",
    "sg:province":"TX",
    "sg:tags":[
        "church"
    ],
    "wof:name":"Automated Church Systems",
    "wof:placetype":"venue"
},
  "geometry": {"coordinates":[-97.807089,30.429626],"type":"Point"}
}