{
  "type": "Feature",
  "properties": {
    "iso:country":"US",
    "sg:address":"12935 Pelican Blvd",
    "sg:city":"Willis",
    "sg:classifiers":[
        {
            "category":"Retail",
            "subcategory":"Laundry & Dry Cleaning",
            "type":"Services"
        }
    ],
    "sg:phone":"+1 936 890 4166",
    "sg:postcode":"77318",
    "sg:province":"TX",
    "wof:name":"Marys Alterations",
    "wof:placetype":"venue"
},
  "geometry": {"coordinates":[-95.568477,30.431912],"type":"Point"}
}