{
  "type": "Feature",
  "properties": {
    "iso:country":"US",
    "sg:address":"8723 Winding Ln",
    "sg:city":"Fort Worth",
    "sg:classifiers":[
        {
            "category":"Professional",
            "type":"Services"
        }
    ],
    "sg:phone":"+1 817 801 6619",
    "sg:postcode":"76120",
    "sg:province":"TX",
    "wof:name":"Advantage Service Center",
    "wof:placetype":"venue"
},
  "geometry": {"coordinates":[-97.16360299999999,32.764807],"type":"Point"}
}