{
  "type": "Feature",
  "properties": {
    "iso:country":"US",
    "sg:address":"1 Trego Ln",
    "sg:city":"Greenville",
    "sg:classifiers":[
        {
            "category":"Place Of Worship",
            "type":"Public Place"
        }
    ],
    "sg:phone":"+1 903 456 1085",
    "sg:postcode":"75402",
    "sg:province":"TX",
    "sg:tags":[
        "church"
    ],
    "wof:name":"East Africa Zarephath Ministry, Inc.",
    "wof:placetype":"venue"
},
  "geometry": {"coordinates":[-96.080879,33.10685],"type":"Point"}
}