{
  "type": "Feature",
  "properties": {
    "iso:country":"US",
    "sg:address":"2108 Westheimer Rd",
    "sg:city":"Houston",
    "sg:classifiers":[
        {
            "category":"Restaurant",
            "type":"Food & Drink"
        }
    ],
    "sg:phone":"+1 281 293 7442",
    "sg:postcode":"77098",
    "sg:province":"TX",
    "wof:name":"Emporio Brasil",
    "wof:placetype":"venue"
},
  "geometry": {"coordinates":[-95.41117300000001,29.742654],"type":"Point"}
}