{
  "type": "Feature",
  "properties": {
    "iso:country":"US",
    "sg:address":"11900 Barryknoll Ln",
    "sg:city":"Houston",
    "sg:classifiers":[
        {
            "category":"Banks & Credit Unions",
            "subcategory":"Financial Services",
            "type":"Services"
        }
    ],
    "sg:phone":"+1 713 465 6348",
    "sg:postcode":"77024",
    "sg:province":"TX",
    "sg:tags":[
        "trust",
        "management"
    ],
    "wof:name":"Goodwin Living Trust",
    "wof:placetype":"venue"
},
  "geometry": {"coordinates":[-95.53689799999999,29.778578],"type":"Point"}
}