{
  "type": "Feature",
  "properties": {
    "iso:country":"US",
    "sg:address":"811 S West St",
    "sg:city":"Arlington",
    "sg:classifiers":[
        {
            "category":"Health Services",
            "subcategory":"Doctor",
            "type":"Services"
        }
    ],
    "sg:phone":"+1 817 419 8244",
    "sg:postcode":"76010",
    "sg:province":"TX",
    "sg:tags":[
        "clinic",
        "medical"
    ],
    "wof:name":"Bunnell Brent Do",
    "wof:placetype":"venue"
},
  "geometry": {"coordinates":[-97.111024,32.728451],"type":"Point"}
}