{
  "type": "Feature",
  "properties": {
    "iso:country":"US",
    "sg:address":"600 Las Colinas Blvd E",
    "sg:city":"Irving",
    "sg:classifiers":[
        {
            "category":"Professional",
            "subcategory":"Management & Consulting",
            "type":"Services"
        }
    ],
    "sg:phone":"+1 972 401 3190",
    "sg:postcode":"75039",
    "sg:province":"TX",
    "wof:name":"Personnel Decisions Intl",
    "wof:placetype":"venue"
},
  "geometry": {"coordinates":[-96.932469,32.860679],"type":"Point"}
}