{
  "type": "Feature",
  "properties": {
    "iso:country":"US",
    "sg:address":"1737 W Mariposa Dr",
    "sg:city":"San Antonio",
    "sg:classifiers":[
        {
            "category":"Building & Trades",
            "subcategory":"Construction",
            "type":"Services"
        }
    ],
    "sg:phone":"+1 210 734 9200",
    "sg:postcode":"78201",
    "sg:province":"TX",
    "sg:tags":[
        "repairing",
        "remodeling",
        "contractor"
    ],
    "wof:name":"Remodeling Services Inc",
    "wof:placetype":"venue"
},
  "geometry": {"coordinates":[-98.52369299999999,29.480977],"type":"Point"}
}