{
  "type": "Feature",
  "properties": {
    "iso:country":"US",
    "sg:address":"703 N Crockett Ave",
    "sg:city":"Sonora",
    "sg:classifiers":[
        {
            "category":"Autos & Motor Vehicles",
            "subcategory":"Fuel & Gas Station",
            "type":"Retail Goods"
        }
    ],
    "sg:phone":"+1 325 387 5641",
    "sg:postcode":"76950",
    "sg:province":"TX",
    "sg:tags":[
        "oil"
    ],
    "wof:name":"Mack's Shell",
    "wof:placetype":"venue"
},
  "geometry": {"coordinates":[-100.65075400000001,30.574172],"type":"Point"}
}