{
  "type": "Feature",
  "properties": {
    "iso:country":"US",
    "sg:address":"705 S Galloway Ave",
    "sg:city":"Mesquite",
    "sg:classifiers":[
        {
            "category":"Freight",
            "type":"Transportation"
        }
    ],
    "sg:phone":"+1 972 329 9010",
    "sg:postcode":"75149",
    "sg:province":"TX",
    "sg:tags":[
        "full",
        "business",
        "storage",
        "trucking",
        "operator",
        "mover",
        "local"
    ],
    "sg:website":"http://www.dependablemoversandpackers.com",
    "wof:name":"Dependable Movers & Packers",
    "wof:placetype":"venue"
},
  "geometry": {"coordinates":[-96.59874000000001,32.759899],"type":"Point"}
}