{
  "type": "Feature",
  "properties": {
    "iso:country":"US",
    "sg:address":"10420 Eastex Fwy",
    "sg:city":"Houston",
    "sg:classifiers":[
        {
            "category":"Food & Beverages",
            "subcategory":"Groceries & Convenience Stores",
            "type":"Retail Goods"
        }
    ],
    "sg:phone":"+1 713 697 2904",
    "sg:postcode":"77093",
    "sg:province":"TX",
    "wof:name":"Galatian Inc",
    "wof:placetype":"venue"
},
  "geometry": {"coordinates":[-95.332576,29.862875],"type":"Point"}
}