{
  "type": "Feature",
  "properties": {
    "iso:country":"US",
    "sg:address":"1028 Bluebonnet Dr",
    "sg:city":"Irving",
    "sg:classifiers":[
        {
            "category":"Shopping",
            "subcategory":"Used Merchandise",
            "type":"Retail Goods"
        }
    ],
    "sg:phone":"+1 972 579 9702",
    "sg:postcode":"75060",
    "sg:province":"TX",
    "sg:tags":[
        "computer"
    ],
    "wof:name":"Rjm Company",
    "wof:placetype":"venue"
},
  "geometry": {"coordinates":[-96.919207,32.803808],"type":"Point"}
}