{
  "type": "Feature",
  "properties": {
    "iso:country":"US",
    "sg:address":"630 W Little York Rd",
    "sg:city":"Houston",
    "sg:classifiers":[
        {
            "category":"Restaurant",
            "type":"Food & Drink"
        }
    ],
    "sg:phone":"+1 281 447 3595",
    "sg:postcode":"77091",
    "sg:province":"TX",
    "sg:tags":[
        "eating"
    ],
    "wof:name":"Ramexs Restaurant",
    "wof:placetype":"venue"
},
  "geometry": {"coordinates":[-95.41234900000001,29.869407],"type":"Point"}
}