{
  "type": "Feature",
  "properties": {
    "iso:country":"US",
    "sg:address":"9464 Long Point Rd",
    "sg:city":"Houston",
    "sg:classifiers":[
        {
            "category":"Cinema",
            "subcategory":"Movie Rental",
            "type":"Entertainment"
        }
    ],
    "sg:phone":"+1 713 464 0186",
    "sg:postcode":"77055",
    "sg:province":"TX",
    "sg:tags":[
        "game",
        "video"
    ],
    "wof:name":"Lucky Charm Video Games",
    "wof:placetype":"venue"
},
  "geometry": {"coordinates":[-95.525403,29.797618],"type":"Point"}
}