{
  "type": "Feature",
  "properties": {
    "iso:country":"US",
    "sg:address":"1907 Wickersham Dr",
    "sg:city":"Arlington",
    "sg:classifiers":[
        {
            "category":"Building & Trades",
            "subcategory":"Landscaping Services",
            "type":"Services"
        }
    ],
    "sg:phone":"+1 817 274 4170",
    "sg:postcode":"76014",
    "sg:province":"TX",
    "wof:name":"Working Force",
    "wof:placetype":"venue"
},
  "geometry": {"coordinates":[-97.080423,32.698638],"type":"Point"}
}