{
  "type": "Feature",
  "properties": {
    "iso:country":"US",
    "sg:address":"1441 Sunswept Ter",
    "sg:city":"Lewisville",
    "sg:classifiers":[
        {
            "category":"Retail",
            "subcategory":"Car Wash",
            "type":"Services"
        }
    ],
    "sg:phone":"+1 972 221 8186",
    "sg:postcode":"75077",
    "sg:province":"TX",
    "sg:tags":[
        "carwash"
    ],
    "wof:name":"Max Car Wash",
    "wof:placetype":"venue"
},
  "geometry": {"coordinates":[-97.034406,33.05848],"type":"Point"}
}