{
  "type": "Feature",
  "properties": {
    "iso:country":"US",
    "sg:address":"2960 Hollandale Ln",
    "sg:city":"Dallas",
    "sg:classifiers":[
        {
            "category":"Building & Trades",
            "subcategory":"Electrical",
            "type":"Services"
        }
    ],
    "sg:phone":"+1 972 241 7575",
    "sg:postcode":"75234",
    "sg:province":"TX",
    "sg:tags":[
        "electrical",
        "contractor"
    ],
    "wof:name":"Pyramid Electric",
    "wof:placetype":"venue"
},
  "geometry": {"coordinates":[-96.877815,32.943818],"type":"Point"}
}