{
  "type": "Feature",
  "properties": {
    "iso:country":"US",
    "sg:address":"14130 Ivy Bluff Ct",
    "sg:city":"Houston",
    "sg:classifiers":[
        {
            "category":"Communications",
            "subcategory":"Film & Video Production",
            "type":"Services"
        }
    ],
    "sg:phone":"+1 281 461 1776",
    "sg:postcode":"77062",
    "sg:province":"TX",
    "sg:tags":[
        "tv",
        "radio",
        "services-commercial",
        "companies-film"
    ],
    "wof:name":"Nellie Productions",
    "wof:placetype":"venue"
},
  "geometry": {"coordinates":[-95.14483799999999,29.590399],"type":"Point"}
}