{
  "type": "Feature",
  "properties": {
    "iso:country":"US",
    "sg:address":"2004 N Main St",
    "sg:city":"Liberty",
    "sg:classifiers":[
        {
            "category":"Insurance",
            "subcategory":"Insurance Agent",
            "type":"Services"
        }
    ],
    "sg:phone":"+1 936 336 2226",
    "sg:postcode":"77575",
    "sg:province":"TX",
    "wof:name":"State Farm Insurance",
    "wof:placetype":"venue"
},
  "geometry": {"coordinates":[-94.787065,30.071631],"type":"Point"}
}