{
  "type": "Feature",
  "properties": {
    "iso:country":"US",
    "sg:address":"4105 Hwy 121",
    "sg:city":"Bedford",
    "sg:classifiers":[
        {
            "category":"Banks & Credit Unions",
            "subcategory":"Investment Brokerage",
            "type":"Services"
        }
    ],
    "sg:phone":"+1 817 399 8889",
    "sg:postcode":"76021",
    "sg:province":"TX",
    "wof:name":"Edward Jones Co",
    "wof:placetype":"venue"
},
  "geometry": {"coordinates":[-97.105166,32.8604],"type":"Point"}
}