{
  "type": "Feature",
  "properties": {
    "iso:country":"US",
    "sg:address":"402 Greystone Dr",
    "sg:city":"Lorena",
    "sg:classifiers":[
        {
            "category":"Real Estate",
            "subcategory":"Architect",
            "type":"Services"
        }
    ],
    "sg:phone":"+1 254 857 3051",
    "sg:postcode":"76655",
    "sg:province":"TX",
    "sg:tags":[
        "home",
        "planning",
        "design"
    ],
    "wof:name":"Imagination Design",
    "wof:placetype":"venue"
},
  "geometry": {"coordinates":[-97.223927,31.394558],"type":"Point"}
}