{
  "type": "Feature",
  "properties": {
    "iso:country":"US",
    "sg:address":"824 Kentucky St",
    "sg:city":"Graham",
    "sg:classifiers":[
        {
            "category":"Home & Garden",
            "subcategory":"Hardware",
            "type":"Retail Goods"
        }
    ],
    "sg:phone":"+1 940 549 0820",
    "sg:postcode":"76450",
    "sg:province":"TX",
    "wof:name":"Sumner Tool & Equipment",
    "wof:placetype":"venue"
},
  "geometry": {"coordinates":[-98.582998,33.101581],"type":"Point"}
}