{
  "type": "Feature",
  "properties": {
    "iso:country":"US",
    "sg:address":"8526 Ferris Dr",
    "sg:city":"Houston",
    "sg:classifiers":[
        {
            "category":"Professional",
            "type":"Services"
        }
    ],
    "sg:phone":"+1 713 661 4100",
    "sg:postcode":"77096",
    "sg:province":"TX",
    "wof:name":"Romet Inc",
    "wof:placetype":"venue"
},
  "geometry": {"coordinates":[-95.471846,29.689106],"type":"Point"}
}