{
  "type": "Feature",
  "properties": {
    "iso:country":"US",
    "sg:address":"515 Congress Ave Ste 1500",
    "sg:city":"Austin",
    "sg:classifiers":[
        {
            "category":"Food & Beverages",
            "subcategory":"Groceries & Convenience Stores",
            "type":"Retail Goods"
        }
    ],
    "sg:phone":"+1 512 609 1700",
    "sg:postcode":"78701",
    "sg:province":"TX",
    "wof:name":"National Alliance Capital Markets",
    "wof:placetype":"venue"
},
  "geometry": {"coordinates":[-97.742941,30.267212],"type":"Point"}
}