{
  "type": "Feature",
  "properties": {
    "iso:country":"US",
    "sg:address":"7040 N Mesa St",
    "sg:city":"El Paso",
    "sg:classifiers":[
        {
            "category":"Restaurant",
            "type":"Food & Drink"
        }
    ],
    "sg:menulink":"http://www.allmenus.com/tx/el-paso/168780-el-pollo-loco/menu/",
    "sg:phone":"+1 915 832 0600",
    "sg:postcode":"79912",
    "sg:province":"TX",
    "sg:tags":[
        "american",
        "mexican",
        "tex-mex"
    ],
    "wof:name":"El Pollo Loco",
    "wof:placetype":"venue"
},
  "geometry": {"coordinates":[-106.55273200000001,31.836835],"type":"Point"}
}