{
  "type": "Feature",
  "properties": {
    "iso:country":"US",
    "sg:address":"4405 State Hwy 347",
    "sg:city":"Nederland",
    "sg:classifiers":[
        {
            "category":"Professional",
            "subcategory":"Management & Consulting",
            "type":"Services"
        }
    ],
    "sg:phone":"+1 409 727 7640",
    "sg:postcode":"77627",
    "sg:province":"TX",
    "sg:tags":[
        "school",
        "testing",
        "inspection",
        "outside",
        "welding"
    ],
    "wof:name":"M Weeks Welding Lab Tstg & Sch",
    "wof:placetype":"venue"
},
  "geometry": {"coordinates":[-94.023528,30.002172],"type":"Point"}
}