{
  "type": "Feature",
  "properties": {
    "iso:country":"US",
    "sg:address":"2 Northpoint Dr",
    "sg:city":"Houston",
    "sg:classifiers":[
        {
            "category":"Mining & Drilling",
            "type":"Manufacturing & Wholesale Goods"
        }
    ],
    "sg:phone":"+1 281 442 7382",
    "sg:postcode":"77060",
    "sg:province":"TX",
    "sg:tags":[
        "field",
        "management"
    ],
    "wof:name":"Hunting Oilfield Services",
    "wof:placetype":"venue"
},
  "geometry": {"coordinates":[-95.41031599999999,29.937928],"type":"Point"}
}