{
  "type": "Feature",
  "properties": {
    "iso:country":"US",
    "sg:address":"3710 Westway St",
    "sg:city":"Tyler",
    "sg:classifiers":[
        {
            "category":"Building & Trades",
            "subcategory":"Cleaning & Sanitation",
            "type":"Services"
        },
        {
            "category":"Retail",
            "subcategory":"Laundry & Dry Cleaning",
            "type":"Services"
        }
    ],
    "sg:phone":"+1 903 566 7576",
    "sg:postcode":"75703",
    "sg:province":"TX",
    "sg:tags":[
        "cleaner",
        "fire",
        "house",
        "rug",
        "damage",
        "water",
        "restoration",
        "carpet"
    ],
    "sg:website":"http://www.procleanrestoration.net",
    "wof:name":"PRO Clean",
    "wof:placetype":"venue"
},
  "geometry": {"coordinates":[-95.341674,32.298845],"type":"Point"}
}