{
  "type": "Feature",
  "properties": {
    "iso:country":"US",
    "sg:address":"1515 Sandy Spring Rd",
    "sg:city":"Houston",
    "sg:classifiers":[
        {
            "category":"Wholesale",
            "subcategory":"Jewelry",
            "type":"Manufacturing & Wholesale Goods"
        }
    ],
    "sg:phone":"+1 713 532 9194",
    "sg:postcode":"77042",
    "sg:province":"TX",
    "sg:tags":[
        "stone"
    ],
    "wof:name":"Coralnbeads",
    "wof:placetype":"venue"
},
  "geometry": {"coordinates":[-95.57467699999999,29.753807],"type":"Point"}
}