{
  "type": "Feature",
  "properties": {
    "iso:country":"US",
    "sg:address":"420 N 4th St",
    "sg:city":"Silsbee",
    "sg:classifiers":[
        {
            "category":"Professional",
            "subcategory":"Accounting & Tax Preparation",
            "type":"Services"
        }
    ],
    "sg:phone":"+1 409 385 4647",
    "sg:postcode":"77656",
    "sg:province":"TX",
    "sg:tags":[
        "accountant"
    ],
    "wof:name":"William R Gieseke CPA",
    "wof:placetype":"venue"
},
  "geometry": {"coordinates":[-94.17575600000001,30.35145],"type":"Point"}
}