{
  "type": "Feature",
  "properties": {
    "iso:country":"US",
    "sg:address":"2161 NW Military Hwy",
    "sg:city":"San Antonio",
    "sg:classifiers":[
        {
            "category":"Real Estate",
            "subcategory":"Real Estate Agent",
            "type":"Services"
        }
    ],
    "sg:phone":"+1 210 344 0004",
    "sg:postcode":"78213",
    "sg:province":"TX",
    "sg:tags":[
        "broker"
    ],
    "wof:name":"Sky Lilne Realtors",
    "wof:placetype":"venue"
},
  "geometry": {"coordinates":[-98.52231399999999,29.532521],"type":"Point"}
}