{
  "type": "Feature",
  "properties": {
    "iso:country":"US",
    "sg:address":"5106 Shadowridge Dr",
    "sg:city":"Houston",
    "sg:classifiers":[
        {
            "category":"Freight",
            "type":"Transportation"
        }
    ],
    "sg:phone":"+1 281 438 9686",
    "sg:postcode":"77053",
    "sg:province":"TX",
    "sg:tags":[
        "operator",
        "local",
        "trucking"
    ],
    "wof:name":"Roques Trucking Co",
    "wof:placetype":"venue"
},
  "geometry": {"coordinates":[-95.465615,29.584749],"type":"Point"}
}