{
  "type": "Feature",
  "properties": {
    "iso:country":"US",
    "sg:address":"2255 Mangum Rd",
    "sg:city":"Poteet",
    "sg:classifiers":[
        {
            "category":"Farming",
            "subcategory":"Farm & Veterinary Services",
            "type":"Manufacturing & Wholesale Goods"
        }
    ],
    "sg:phone":"+1 830 742 8070",
    "sg:postcode":"78065",
    "sg:province":"TX",
    "sg:tags":[
        "livestock"
    ],
    "wof:name":"Steve Lawson",
    "wof:placetype":"venue"
},
  "geometry": {"coordinates":[-98.579623,29.069612],"type":"Point"}
}