{
  "type": "Feature",
  "properties": {
    "iso:country":"US",
    "sg:address":"4114 W Camp Wisdom Rd",
    "sg:city":"Dallas",
    "sg:classifiers":[
        {
            "category":"Retail",
            "subcategory":"Auto Repair",
            "type":"Services"
        }
    ],
    "sg:phone":"+1 972 283 8468",
    "sg:postcode":"75237",
    "sg:province":"TX",
    "sg:tags":[
        "automotive"
    ],
    "wof:name":"Pauls Artech Window Tinting",
    "wof:placetype":"venue"
},
  "geometry": {"coordinates":[-96.88916999999999,32.6619],"type":"Point"}
}