{
  "type": "Feature",
  "properties": {
    "iso:country":"US",
    "sg:address":"1215 W Belt Line Rd",
    "sg:city":"Richardson",
    "sg:classifiers":[
        {
            "category":"Shopping",
            "subcategory":"Hobbies, Toys, & Games",
            "type":"Retail Goods"
        }
    ],
    "sg:phone":"+1 972 889 8899",
    "sg:postcode":"75080",
    "sg:province":"TX",
    "wof:name":"Doll-EE Shop",
    "wof:placetype":"venue"
},
  "geometry": {"coordinates":[-96.760302,32.951062],"type":"Point"}
}