{
  "type": "Feature",
  "properties": {
    "iso:country":"US",
    "sg:address":"8500 Blazyk Dr",
    "sg:city":"Austin",
    "sg:classifiers":[
        {
            "category":"Professional",
            "subcategory":"Management & Consulting",
            "type":"Services"
        }
    ],
    "sg:phone":"+1 512 288 2359",
    "sg:postcode":"78737",
    "sg:province":"TX",
    "wof:name":"Nashville Cactus Management",
    "wof:placetype":"venue"
},
  "geometry": {"coordinates":[-97.922246,30.202714],"type":"Point"}
}