{
  "type": "Feature",
  "properties": {
    "iso:country":"US",
    "sg:address":"2695 Fm 464",
    "sg:city":"Seguin",
    "sg:classifiers":[
        {
            "category":"Building & Trades",
            "subcategory":"Landscaping Services",
            "type":"Services"
        },
        {
            "category":"Home & Garden",
            "subcategory":"Garden Supply",
            "type":"Retail Goods"
        }
    ],
    "sg:phone":"+1 830 372 4955",
    "sg:postcode":"78155",
    "sg:province":"TX",
    "sg:tags":[
        "lawn",
        "sprinklers-garden",
        "landscape",
        "contractor"
    ],
    "wof:name":"Altex Landscape Construction Inc",
    "wof:placetype":"venue"
},
  "geometry": {"coordinates":[-98.01354000000001,29.571096],"type":"Point"}
}