{
  "type": "Feature",
  "properties": {
    "iso:country":"US",
    "sg:address":"200 E Ridgeway Dr",
    "sg:city":"Midlothian",
    "sg:classifiers":[
        {
            "category":"Freight",
            "type":"Transportation"
        }
    ],
    "sg:phone":"+1 972 723 7879",
    "sg:postcode":"76065",
    "sg:province":"TX",
    "sg:tags":[
        "general"
    ],
    "wof:name":"Midlothian Self Storage",
    "wof:placetype":"venue"
},
  "geometry": {"coordinates":[-96.992222,32.49856],"type":"Point"}
}