{
  "type": "Feature",
  "properties": {
    "iso:country":"US",
    "sg:address":"730 N Cedar Ridge Dr",
    "sg:city":"Duncanville",
    "sg:classifiers":[
        {
            "category":"Place Of Worship",
            "subcategory":"Synagogue",
            "type":"Public Place"
        }
    ],
    "sg:phone":"+1 972 709 8761",
    "sg:postcode":"75116",
    "sg:province":"TX",
    "wof:name":"Bat Zion Messianic Congregation",
    "wof:placetype":"venue"
},
  "geometry": {"coordinates":[-96.925285,32.661011],"type":"Point"}
}