{
  "type": "Feature",
  "properties": {
    "iso:country":"US",
    "sg:address":"102 W Bustamante St",
    "sg:city":"Laredo",
    "sg:classifiers":[
        {
            "category":"Retail",
            "subcategory":"Auto Repair",
            "type":"Services"
        }
    ],
    "sg:phone":"+1 956 722 6404",
    "sg:postcode":"78041",
    "sg:province":"TX",
    "sg:tags":[
        "repairing",
        "tire"
    ],
    "wof:name":"Colorado Tire Svc",
    "wof:placetype":"venue"
},
  "geometry": {"coordinates":[-99.496792,27.534308],"type":"Point"}
}