{
  "type": "Feature",
  "properties": {
    "iso:country":"US",
    "sg:address":"1850 Crooks Ct",
    "sg:city":"Grand Prairie",
    "sg:classifiers":[
        {
            "category":"Building & Trades",
            "subcategory":"Pest Control",
            "type":"Services"
        }
    ],
    "sg:phone":"+1 972 263 0165",
    "sg:postcode":"75051",
    "sg:province":"TX",
    "wof:name":"Beckham's Termite & Pest Cntrl",
    "wof:placetype":"venue"
},
  "geometry": {"coordinates":[-97.003552,32.719045],"type":"Point"}
}