{
  "type": "Feature",
  "properties": {
    "iso:country":"US",
    "sg:address":"507 S Lee St",
    "sg:city":"Valley View",
    "sg:classifiers":[
        {
            "category":"Building & Trades",
            "subcategory":"Construction",
            "type":"Services"
        }
    ],
    "sg:phone":"+1 940 726 5047",
    "sg:postcode":"76272",
    "sg:province":"TX",
    "sg:tags":[
        "house"
    ],
    "wof:name":"J Dugger",
    "wof:placetype":"venue"
},
  "geometry": {"coordinates":[-97.165308,33.485319],"type":"Point"}
}