{
  "type": "Feature",
  "properties": {
    "iso:country":"US",
    "sg:address":"1435 N Bois D Arc Ave",
    "sg:city":"Tyler",
    "sg:classifiers":[
        {
            "category":"Organizations",
            "subcategory":"Religious Organization",
            "type":"Services"
        }
    ],
    "sg:phone":"+1 903 597 6167",
    "sg:postcode":"75702",
    "sg:province":"TX",
    "sg:tags":[
        "church"
    ],
    "wof:name":"Church Of God In Christ",
    "wof:placetype":"venue"
},
  "geometry": {"coordinates":[-95.302744,32.365308],"type":"Point"}
}