{
  "type": "Feature",
  "properties": {
    "iso:country":"US",
    "sg:address":"917 Appletree Ct",
    "sg:city":"Irving",
    "sg:classifiers":[
        {
            "category":"Health Services",
            "subcategory":"Nursing And Care Facility",
            "type":"Services"
        }
    ],
    "sg:phone":"+1 972 445 1856",
    "sg:postcode":"75061",
    "sg:province":"TX",
    "wof:name":"Apple Tree Court",
    "wof:placetype":"venue"
},
  "geometry": {"coordinates":[-96.931293,32.824176],"type":"Point"}
}