{
  "type": "Feature",
  "properties": {
    "iso:country":"US",
    "sg:address":"6040 S Padre Island Dr",
    "sg:city":"Corpus Christi",
    "sg:classifiers":[
        {
            "category":"Personal",
            "type":"Services"
        }
    ],
    "sg:phone":"+1 361 991 6152",
    "sg:postcode":"78412",
    "sg:province":"TX",
    "sg:tags":[
        "electrologist"
    ],
    "wof:name":"Helen White Electrologists",
    "wof:placetype":"venue"
},
  "geometry": {"coordinates":[-97.36274,27.704444],"type":"Point"}
}