{
  "type": "Feature",
  "properties": {
    "iso:country":"US",
    "sg:address":"319 Hortencia Ave",
    "sg:city":"San Antonio",
    "sg:classifiers":[
        {
            "category":"Organizations",
            "subcategory":"Religious Organization",
            "type":"Services"
        }
    ],
    "sg:phone":"+1 210 432 2503",
    "sg:postcode":"78237",
    "sg:province":"TX",
    "sg:tags":[
        "church"
    ],
    "wof:name":"West Mount Calvary Church",
    "wof:placetype":"venue"
},
  "geometry": {"coordinates":[-98.58124599999999,29.437076],"type":"Point"}
}