{
  "type": "Feature",
  "properties": {
    "iso:country":"US",
    "sg:address":"3700 Gulf Blvd",
    "sg:city":"S Padre Island",
    "sg:classifiers":[
        {
            "category":"Real Estate",
            "subcategory":"Real Estate Agent",
            "type":"Services"
        },
        {
            "category":"Real Estate",
            "subcategory":"Real Estate Operator",
            "type":"Services"
        }
    ],
    "sg:phone":"+1 956 761 1903",
    "sg:postcode":"78597",
    "sg:province":"TX",
    "sg:tags":[
        "condominium"
    ],
    "wof:name":"Castaways Condominiums Inc",
    "wof:placetype":"venue"
},
  "geometry": {"coordinates":[-97.165719,26.11102],"type":"Point"}
}