{
  "type": "Feature",
  "properties": {
    "iso:country":"US",
    "sg:address":"400 Indian Paintbrush Way",
    "sg:city":"Southlake",
    "sg:classifiers":[
        {
            "category":"Building & Trades",
            "subcategory":"Construction",
            "type":"Services"
        }
    ],
    "sg:phone":"+1 817 424 4004",
    "sg:postcode":"76092",
    "sg:province":"TX",
    "sg:tags":[
        "house"
    ],
    "wof:name":"Southlake Woods",
    "wof:placetype":"venue"
},
  "geometry": {"coordinates":[-97.177852,32.936942],"type":"Point"}
}