{
  "type": "Feature",
  "properties": {
    "iso:country":"US",
    "sg:address":"2022 Wind Creek Dr",
    "sg:city":"Kingwood",
    "sg:classifiers":[
        {
            "category":"Professional",
            "subcategory":"Lawyer & Legal Services",
            "type":"Services"
        }
    ],
    "sg:phone":"+1 281 361 8784",
    "sg:postcode":"77345",
    "sg:province":"TX",
    "sg:tags":[
        "attorney",
        "practice"
    ],
    "wof:name":"The Holman Law Firm",
    "wof:placetype":"venue"
},
  "geometry": {"coordinates":[-95.173298,30.043059],"type":"Point"}
}