{
  "type": "Feature",
  "properties": {
    "iso:country":"US",
    "sg:address":"18481 Elm Creek Rd",
    "sg:city":"Moody",
    "sg:classifiers":[
        {
            "category":"Retail",
            "subcategory":"Animal Services",
            "type":"Services"
        }
    ],
    "sg:phone":"+1 254 853 2806",
    "sg:postcode":"76657",
    "sg:province":"TX",
    "sg:tags":[
        "breeder",
        "horse"
    ],
    "sg:website":"www.fortstoreyranch.com",
    "wof:name":"Fort Storey Ranch",
    "wof:placetype":"venue"
},
  "geometry": {"coordinates":[-97.350207,31.302359],"type":"Point"}
}