{
  "type": "Feature",
  "properties": {
    "iso:country":"US",
    "sg:address":"613 College Ave",
    "sg:city":"South Houston",
    "sg:classifiers":[
        {
            "category":"Shopping",
            "subcategory":"Books",
            "type":"Retail Goods"
        }
    ],
    "sg:phone":"+1 713 944 9249",
    "sg:postcode":"77587",
    "sg:province":"TX",
    "wof:name":"Braveheart Books & Clergy Sup",
    "wof:placetype":"venue"
},
  "geometry": {"coordinates":[-95.23785700000001,29.661563],"type":"Point"}
}