{
  "type": "Feature",
  "properties": {
    "iso:country":"US",
    "sg:address":"202 E Jackson St",
    "sg:city":"El Campo",
    "sg:classifiers":[
        {
            "category":"Banks & Credit Unions",
            "subcategory":"Financial Services",
            "type":"Services"
        }
    ],
    "sg:phone":"+1 979 543 3812",
    "sg:postcode":"77437",
    "sg:province":"TX",
    "sg:tags":[
        "trust"
    ],
    "wof:name":"Guy F Stovall Trusts",
    "wof:placetype":"venue"
},
  "geometry": {"coordinates":[-96.267816,29.197935],"type":"Point"}
}