{
  "type": "Feature",
  "properties": {
    "iso:country":"US",
    "sg:address":"5760 SW Loop 820",
    "sg:city":"Fort Worth",
    "sg:classifiers":[
        {
            "category":"Restaurant",
            "type":"Food & Drink"
        }
    ],
    "sg:menulink":"http://www.allmenus.com/tx/fort-worth/20060-the-keg/menu/",
    "sg:phone":"+1 817 731 3534",
    "sg:postcode":"76132",
    "sg:province":"TX",
    "sg:tags":[
        "american",
        "steakhouse"
    ],
    "wof:name":"The Keg",
    "wof:placetype":"venue"
},
  "geometry": {"coordinates":[-97.409936,32.684192],"type":"Point"}
}