{
  "type": "Feature",
  "properties": {
    "iso:country":"US",
    "sg:address":"6637 Macintosh Dr",
    "sg:city":"Plano",
    "sg:classifiers":[
        {
            "category":"Professional",
            "subcategory":"Business Services",
            "type":"Services"
        }
    ],
    "sg:phone":"+1 972 517 7603",
    "sg:postcode":"75023",
    "sg:province":"TX",
    "wof:name":"Hingoranee Enterprises",
    "wof:placetype":"venue"
},
  "geometry": {"coordinates":[-96.721953,33.065744],"type":"Point"}
}