{
  "type": "Feature",
  "properties": {
    "iso:country":"US",
    "sg:address":"930 FM 359",
    "sg:city":"Richmond",
    "sg:classifiers":[
        {
            "category":"Shopping",
            "type":"Retail Goods"
        }
    ],
    "sg:phone":"+1 281 238 9002",
    "sg:postcode":"77469",
    "sg:province":"TX",
    "sg:tags":[
        "picture",
        "frame"
    ],
    "wof:name":"Cheryl Faye Custom Framing",
    "wof:placetype":"venue"
},
  "geometry": {"coordinates":[-95.74288,29.611804],"type":"Point"}
}