{
  "type": "Feature",
  "properties": {
    "iso:country":"US",
    "sg:address":"817 S Carroll Ave",
    "sg:city":"Dallas",
    "sg:classifiers":[
        {
            "category":"Retail",
            "subcategory":"Auto Repair",
            "type":"Services"
        }
    ],
    "sg:phone":"+1 214 515 9950",
    "sg:postcode":"75223",
    "sg:province":"TX",
    "wof:name":"Rubin's Garage",
    "wof:placetype":"venue"
},
  "geometry": {"coordinates":[-96.762703,32.787601],"type":"Point"}
}