{
  "type": "Feature",
  "properties": {
    "iso:country":"US",
    "sg:address":"141 W Spring Creek Pkwy",
    "sg:city":"Plano",
    "sg:classifiers":[
        {
            "category":"Real Estate",
            "subcategory":"Real Estate Agent",
            "type":"Services"
        }
    ],
    "sg:phone":"+1 972 312 8443",
    "sg:postcode":"75023",
    "sg:province":"TX",
    "wof:name":"Spectrum Real Estate Svc",
    "wof:placetype":"venue"
},
  "geometry": {"coordinates":[-96.695047,33.057533],"type":"Point"}
}