{
  "type": "Feature",
  "properties": {
    "iso:country":"US",
    "sg:address":"409 S Stephens St",
    "sg:city":"Quitman",
    "sg:classifiers":[
        {
            "category":"Building & Trades",
            "subcategory":"Construction",
            "type":"Services"
        }
    ],
    "sg:phone":"+1 903 763 2918",
    "sg:postcode":"75783",
    "sg:province":"TX",
    "sg:tags":[
        "general",
        "contractor"
    ],
    "wof:name":"Jackson Construction",
    "wof:placetype":"venue"
},
  "geometry": {"coordinates":[-95.451999,32.79157],"type":"Point"}
}