{
  "type": "Feature",
  "properties": {
    "iso:country":"US",
    "sg:address":"4141 North Fwy",
    "sg:city":"Houston",
    "sg:classifiers":[
        {
            "category":"Professional",
            "subcategory":"Lawyer & Legal Services",
            "type":"Services"
        }
    ],
    "sg:phone":"+1 713 692 6114",
    "sg:postcode":"77022",
    "sg:province":"TX",
    "wof:name":"Boyer Toby Attorney At Law",
    "wof:placetype":"venue"
},
  "geometry": {"coordinates":[-95.380501,29.824699],"type":"Point"}
}