{
  "type": "Feature",
  "properties": {
    "iso:country":"US",
    "sg:address":"5411 McPherson Ave",
    "sg:city":"Laredo",
    "sg:classifiers":[
        {
            "category":"Professional",
            "subcategory":"Detective & Security Services",
            "type":"Services"
        }
    ],
    "sg:phone":"+1 956 791 1020",
    "sg:postcode":"78041",
    "sg:province":"TX",
    "sg:tags":[
        "system"
    ],
    "wof:name":"Aet Source",
    "wof:placetype":"venue"
},
  "geometry": {"coordinates":[-99.480925,27.552977],"type":"Point"}
}