{
  "type": "Feature",
  "properties": {
    "iso:country":"US",
    "sg:address":"404 Wheeler Rd",
    "sg:city":"Lufkin",
    "sg:classifiers":[
        {
            "category":"Retail",
            "subcategory":"Repair Shop",
            "type":"Services"
        }
    ],
    "sg:phone":"+1 936 632 1497",
    "sg:postcode":"75901",
    "sg:province":"TX",
    "sg:tags":[
        "sharpening"
    ],
    "wof:name":"Havard's Sharpening Svc",
    "wof:placetype":"venue"
},
  "geometry": {"coordinates":[-94.705044,31.280995],"type":"Point"}
}