{
  "type": "Feature",
  "properties": {
    "iso:country":"US",
    "sg:address":"8033 Clearsprings Rd",
    "sg:city":"Dallas",
    "sg:classifiers":[
        {
            "category":"Shopping",
            "subcategory":"Books",
            "type":"Retail Goods"
        }
    ],
    "sg:phone":"+1 972 231 2607",
    "sg:postcode":"75240",
    "sg:province":"TX",
    "wof:name":"Brian Ader Bookseller",
    "wof:placetype":"venue"
},
  "geometry": {"coordinates":[-96.767421,32.937347],"type":"Point"}
}