{
  "type": "Feature",
  "properties": {
    "iso:country":"US",
    "sg:address":"31638 Deerfield Ter",
    "sg:city":"Bulverde",
    "sg:classifiers":[
        {
            "category":"Food & Beverages",
            "subcategory":"Liquor & Beverages",
            "type":"Retail Goods"
        }
    ],
    "sg:phone":"+1 830 438 8596",
    "sg:postcode":"78163",
    "sg:province":"TX",
    "sg:tags":[
        "alcoholic"
    ],
    "wof:name":"Spirit & Wine Cellar LLC",
    "wof:placetype":"venue"
},
  "geometry": {"coordinates":[-98.44485299999999,29.762321],"type":"Point"}
}