{
  "type": "Feature",
  "properties": {
    "iso:country":"US",
    "sg:address":"14924 Henry Rd",
    "sg:city":"Houston",
    "sg:classifiers":[
        {
            "category":"Retail",
            "subcategory":"Auto Repair",
            "type":"Services"
        }
    ],
    "sg:phone":"+1 281 820 8955",
    "sg:postcode":"77060",
    "sg:province":"TX",
    "sg:tags":[
        "repairing",
        "automobile",
        "general",
        "supply"
    ],
    "wof:name":"Dayspring Automotive Service",
    "wof:placetype":"venue"
},
  "geometry": {"coordinates":[-95.382352,29.916439],"type":"Point"}
}