{
  "type": "Feature",
  "properties": {
    "iso:country":"US",
    "sg:address":"9 Professional Park Dr",
    "sg:city":"Webster",
    "sg:classifiers":[
        {
            "category":"Health Services",
            "subcategory":"Doctor",
            "type":"Services"
        }
    ],
    "sg:phone":"+1 281 332 6502",
    "sg:postcode":"77598",
    "sg:province":"TX",
    "sg:tags":[
        "medical"
    ],
    "wof:name":"Ai-Lahiq Maha",
    "wof:placetype":"venue"
},
  "geometry": {"coordinates":[-95.12736700000001,29.545771],"type":"Point"}
}