{
  "type": "Feature",
  "properties": {
    "iso:country":"US",
    "sg:address":"8014 San Gabriel Dr",
    "sg:city":"Laredo",
    "sg:classifiers":[
        {
            "category":"Retail",
            "subcategory":"Auto Repair",
            "type":"Services"
        }
    ],
    "sg:phone":"+1 956 727 3724",
    "sg:postcode":"78045",
    "sg:province":"TX",
    "sg:tags":[
        "tire",
        "supply"
    ],
    "wof:name":"Murillos Tire Service",
    "wof:placetype":"venue"
},
  "geometry": {"coordinates":[-99.498729,27.592046],"type":"Point"}
}