{
  "type": "Feature",
  "properties": {
    "iso:country":"US",
    "sg:address":"1200 Binz St",
    "sg:city":"Houston",
    "sg:classifiers":[
        {
            "category":"Health Services",
            "subcategory":"Doctor",
            "type":"Services"
        }
    ],
    "sg:phone":"+1 713 650 0400",
    "sg:postcode":"77004",
    "sg:province":"TX",
    "sg:tags":[
        "physician",
        "surgeon"
    ],
    "sg:website":"http://www.gallowaychiropractic.com",
    "wof:name":"Galloway, Robert E, Md - Christopher Medical Clinic",
    "wof:placetype":"venue"
},
  "geometry": {"coordinates":[-95.387871,29.72477],"type":"Point"}
}