{
  "type": "Feature",
  "properties": {
    "iso:country":"US",
    "sg:address":"18020 Old Hwy 105 W",
    "sg:city":"Montgomery",
    "sg:classifiers":[
        {
            "category":"Food & Beverages",
            "subcategory":"Liquor & Beverages",
            "type":"Retail Goods"
        }
    ],
    "sg:phone":"+1 936 582 7792",
    "sg:postcode":"77356",
    "sg:province":"TX",
    "wof:name":"Lone Star Liquor",
    "wof:placetype":"venue"
},
  "geometry": {"coordinates":[-95.79321299999999,30.345661],"type":"Point"}
}