{
  "type": "Feature",
  "properties": {
    "iso:country":"US",
    "sg:address":"3508 Dilido Rd",
    "sg:city":"Dallas",
    "sg:classifiers":[
        {
            "category":"Building & Trades",
            "subcategory":"Cleaning & Sanitation",
            "type":"Services"
        }
    ],
    "sg:phone":"+1 214 321 9495",
    "sg:postcode":"75228",
    "sg:province":"TX",
    "sg:tags":[
        "janitor"
    ],
    "wof:name":"Tolman Building Maintenance",
    "wof:placetype":"venue"
},
  "geometry": {"coordinates":[-96.68814399999999,32.802006],"type":"Point"}
}