{
  "type": "Feature",
  "properties": {
    "iso:country":"US",
    "sg:address":"500 I- 45 N",
    "sg:city":"Huntsville",
    "sg:classifiers":[
        {
            "category":"Autos & Motor Vehicles",
            "subcategory":"Fuel & Gas Station",
            "type":"Retail Goods"
        }
    ],
    "sg:phone":"+1 936 295 2488",
    "sg:postcode":"77358",
    "sg:province":"TX",
    "sg:tags":[
        "plaza",
        "truck",
        "stops"
    ],
    "wof:name":"Hitchin Post Truck Terminal",
    "wof:placetype":"venue"
},
  "geometry": {"coordinates":[-95.494102,30.488264],"type":"Point"}
}