{
  "type": "Feature",
  "properties": {
    "iso:country":"US",
    "sg:address":"28 Windsor Dr",
    "sg:city":"Conroe",
    "sg:classifiers":[
        {
            "category":"Health Services",
            "subcategory":"Doctor",
            "type":"Services"
        }
    ],
    "sg:phone":"+1 936 760 3050",
    "sg:postcode":"77304",
    "sg:province":"TX",
    "wof:name":"Derrick Gus W DDS",
    "wof:placetype":"venue"
},
  "geometry": {"coordinates":[-95.47939100000001,30.2868],"type":"Point"}
}