{
  "type": "Feature",
  "properties": {
    "iso:country":"US",
    "sg:address":"625 Rosewood St",
    "sg:city":"Corpus Christi",
    "sg:classifiers":[
        {
            "category":"Wholesale",
            "subcategory":"Plants",
            "type":"Manufacturing & Wholesale Goods"
        }
    ],
    "sg:phone":"+1 361 884 2610",
    "sg:postcode":"78405",
    "sg:province":"TX",
    "sg:tags":[
        "floral",
        "florist",
        "flower",
        "supply"
    ],
    "wof:name":"Floro Distributing Inc",
    "wof:placetype":"venue"
},
  "geometry": {"coordinates":[-97.42633499999999,27.774773],"type":"Point"}
}