{
  "type": "Feature",
  "properties": {
    "iso:country":"US",
    "sg:address":"6702 Autumn Sage Ln",
    "sg:city":"Abilene",
    "sg:classifiers":[
        {
            "category":"Personal",
            "type":"Services"
        }
    ],
    "sg:phone":"+1 325 698 1952",
    "sg:postcode":"79606",
    "sg:province":"TX",
    "wof:name":"Outlaw Inc",
    "wof:placetype":"venue"
},
  "geometry": {"coordinates":[-99.813078,32.401452],"type":"Point"}
}