{
  "type": "Feature",
  "properties": {
    "iso:country":"US",
    "sg:address":"100 Ken Blaschke Dr",
    "sg:city":"Smithville",
    "sg:classifiers":[
        {
            "category":"Real Estate",
            "subcategory":"Real Estate Agent",
            "type":"Services"
        }
    ],
    "sg:phone":"+1 512 360 3676",
    "sg:postcode":"78957",
    "sg:province":"TX",
    "sg:tags":[
        "authorities",
        "housing"
    ],
    "wof:name":"Smithville City Housing Auth",
    "wof:placetype":"venue"
},
  "geometry": {"coordinates":[-97.151326,29.998693],"type":"Point"}
}