{
  "type": "Feature",
  "properties": {
    "iso:country":"US",
    "sg:address":"5402 Broadway Blvd",
    "sg:city":"Garland",
    "sg:classifiers":[
        {
            "category":"Health Services",
            "subcategory":"Doctor",
            "type":"Services"
        }
    ],
    "sg:phone":"+1 972 303 3600",
    "sg:postcode":"75043",
    "sg:province":"TX",
    "sg:tags":[
        "dentist"
    ],
    "wof:name":"Pearl Dental",
    "wof:placetype":"venue"
},
  "geometry": {"coordinates":[-96.59631400000001,32.847367],"type":"Point"}
}