{
  "type": "Feature",
  "properties": {
    "iso:country":"US",
    "sg:address":"10002 Co Rd 3183",
    "sg:city":"Tyler",
    "sg:classifiers":[
        {
            "category":"Shopping",
            "type":"Retail Goods"
        }
    ],
    "sg:phone":"+1 903 593 2720",
    "sg:postcode":"75708",
    "sg:province":"TX",
    "sg:tags":[
        "merchandise"
    ],
    "wof:name":"Sadlers Scent & Things",
    "wof:placetype":"venue"
},
  "geometry": {"coordinates":[-95.245507,32.369066],"type":"Point"}
}