{
  "type": "Feature",
  "properties": {
    "iso:country":"US",
    "sg:address":"6218 Havendale Dr",
    "sg:city":"Houston",
    "sg:classifiers":[
        {
            "category":"Professional",
            "subcategory":"Accounting & Tax Preparation",
            "type":"Services"
        }
    ],
    "sg:phone":"+1 281 498 3374",
    "sg:postcode":"77072",
    "sg:province":"TX",
    "wof:name":"Danilo Y Pozon CPA",
    "wof:placetype":"venue"
},
  "geometry": {"coordinates":[-95.567498,29.712752],"type":"Point"}
}