{
  "type": "Feature",
  "properties": {
    "iso:country":"US",
    "sg:address":"6508 Fiesta Dr",
    "sg:city":"El Paso",
    "sg:classifiers":[
        {
            "category":"Education",
            "subcategory":"School",
            "type":"Public Place"
        }
    ],
    "sg:phone":"+1 915 584 1159",
    "sg:postcode":"79912",
    "sg:province":"TX",
    "sg:tags":[
        "elementary"
    ],
    "wof:name":"Putnam Elementary School",
    "wof:placetype":"venue"
},
  "geometry": {"coordinates":[-106.542731,31.830617],"type":"Point"}
}