{
  "type": "Feature",
  "properties": {
    "iso:country":"US",
    "sg:address":"29318 Waltham St",
    "sg:city":"Spring",
    "sg:classifiers":[
        {
            "category":"Professional",
            "type":"Services"
        }
    ],
    "sg:phone":"+1 281 288 8550",
    "sg:postcode":"77386",
    "sg:province":"TX",
    "wof:name":"Choice Information",
    "wof:placetype":"venue"
},
  "geometry": {"coordinates":[-95.400893,30.113891],"type":"Point"}
}