{
  "type": "Feature",
  "properties": {
    "iso:country":"US",
    "sg:address":"2705 Sherwood Way",
    "sg:city":"San Angelo",
    "sg:classifiers":[
        {
            "category":"Health Services",
            "subcategory":"Optometrist",
            "type":"Services"
        }
    ],
    "sg:phone":"+1 325 949 5750",
    "sg:postcode":"76901",
    "sg:province":"TX",
    "wof:name":"Larsen Alan C Optometrist",
    "wof:placetype":"venue"
},
  "geometry": {"coordinates":[-100.47317,31.448856],"type":"Point"}
}