{
  "type": "Feature",
  "properties": {
    "iso:country":"US",
    "sg:address":"10344 Tanyard Rd",
    "sg:city":"Willis",
    "sg:classifiers":[
        {
            "category":"Shopping",
            "subcategory":"Used Merchandise",
            "type":"Retail Goods"
        }
    ],
    "sg:phone":"+1 936 856 4860",
    "sg:postcode":"77378",
    "sg:province":"TX",
    "wof:name":"Antiques & Classics",
    "wof:placetype":"venue"
},
  "geometry": {"coordinates":[-95.416111,30.460397],"type":"Point"}
}