{
  "type": "Feature",
  "properties": {
    "iso:country":"US",
    "sg:address":"2825 50th St",
    "sg:city":"Lubbock",
    "sg:classifiers":[
        {
            "category":"Personal",
            "subcategory":"Beauty Salon",
            "type":"Services"
        }
    ],
    "sg:phone":"+1 806 771 1939",
    "sg:postcode":"79413",
    "sg:province":"TX",
    "wof:name":"Cutting Up With Lynx",
    "wof:placetype":"venue"
},
  "geometry": {"coordinates":[-101.877771,33.548647],"type":"Point"}
}