{
  "type": "Feature",
  "properties": {
    "iso:country":"US",
    "sg:address":"1715 Western Ave",
    "sg:city":"Fort Worth",
    "sg:classifiers":[
        {
            "category":"Shopping",
            "subcategory":"Hobbies, Toys, & Games",
            "type":"Retail Goods"
        }
    ],
    "sg:phone":"+1 817 738 5977",
    "sg:postcode":"76107",
    "sg:province":"TX",
    "wof:name":"JP Wolfe",
    "wof:placetype":"venue"
},
  "geometry": {"coordinates":[-97.38628199999999,32.742493],"type":"Point"}
}