{
  "type": "Feature",
  "properties": {
    "iso:country":"US",
    "sg:address":"1009 Humble Rd",
    "sg:city":"San Angelo",
    "sg:classifiers":[
        {
            "category":"Wholesale",
            "subcategory":"Electrical",
            "type":"Manufacturing & Wholesale Goods"
        }
    ],
    "sg:phone":"+1 325 655 6074",
    "sg:postcode":"76903",
    "sg:province":"TX",
    "sg:tags":[
        "fire",
        "equipment",
        "protection"
    ],
    "wof:name":"San Angelo Fire Equipment",
    "wof:placetype":"venue"
},
  "geometry": {"coordinates":[-100.473827,31.492641],"type":"Point"}
}