{
  "type": "Feature",
  "properties": {
    "iso:country":"US",
    "sg:address":"3309 Devonshire Ct",
    "sg:city":"Flower Mound",
    "sg:classifiers":[
        {
            "category":"Professional",
            "subcategory":"Business Services",
            "type":"Services"
        }
    ],
    "sg:phone":"+1 214 725 4082",
    "sg:postcode":"75022",
    "sg:province":"TX",
    "wof:name":"Seven Channels",
    "wof:placetype":"venue"
},
  "geometry": {"coordinates":[-97.072357,33.031446],"type":"Point"}
}