{
  "type": "Feature",
  "properties": {
    "iso:country":"US",
    "sg:address":"1107 Ave H",
    "sg:city":"Rosenberg",
    "sg:classifiers":[
        {
            "category":"Shopping",
            "type":"Retail Goods"
        }
    ],
    "sg:phone":"+1 281 232 2688",
    "sg:postcode":"77471",
    "sg:province":"TX",
    "sg:tags":[
        "durable",
        "merchandise",
        "business",
        "goo"
    ],
    "wof:name":"Championship Trophies",
    "wof:placetype":"venue"
},
  "geometry": {"coordinates":[-95.816227,29.558177],"type":"Point"}
}