{
  "type": "Feature",
  "properties": {
    "iso:country":"US",
    "sg:address":"4437 Tamworth Rd",
    "sg:city":"Fort Worth",
    "sg:classifiers":[
        {
            "category":"Organizations",
            "subcategory":"Membership Organization",
            "type":"Services"
        }
    ],
    "sg:phone":"+1 817 737 7869",
    "sg:postcode":"76116",
    "sg:province":"TX",
    "wof:name":"Cactus Cat Club Inc",
    "wof:placetype":"venue"
},
  "geometry": {"coordinates":[-97.42511500000001,32.708826],"type":"Point"}
}