{
  "type": "Feature",
  "properties": {
    "iso:country":"US",
    "sg:address":"14111 Meadowlark Ln",
    "sg:city":"Tomball",
    "sg:classifiers":[
        {
            "category":"Professional",
            "type":"Services"
        }
    ],
    "sg:phone":"+1 281 357 8398",
    "sg:postcode":"77377",
    "sg:province":"TX",
    "wof:name":"Mary L Acosta",
    "wof:placetype":"venue"
},
  "geometry": {"coordinates":[-95.63578699999999,30.079958],"type":"Point"}
}