{
  "type": "Feature",
  "properties": {
    "iso:country":"US",
    "sg:address":"2301 Guadalupe St",
    "sg:city":"San Antonio",
    "sg:classifiers":[
        {
            "category":"Retail",
            "subcategory":"Auto Repair",
            "type":"Services"
        }
    ],
    "sg:phone":"+1 210 431 3044",
    "sg:postcode":"78207",
    "sg:province":"TX",
    "sg:tags":[
        "repairing",
        "automobile"
    ],
    "wof:name":"J & G Automotive Tire Shop",
    "wof:placetype":"venue"
},
  "geometry": {"coordinates":[-98.52688999999999,29.419514],"type":"Point"}
}