{
  "type": "Feature",
  "properties": {
    "iso:country":"US",
    "sg:address":"421 Willowcrest Dr",
    "sg:city":"Garland",
    "sg:classifiers":[
        {
            "category":"Shopping",
            "type":"Retail Goods"
        }
    ],
    "sg:phone":"+1 972 414 9221",
    "sg:postcode":"75040",
    "sg:province":"TX",
    "sg:tags":[
        "merchandise"
    ],
    "wof:name":"Vernon Communication Services",
    "wof:placetype":"venue"
},
  "geometry": {"coordinates":[-96.635109,32.94542],"type":"Point"}
}