{
  "type": "Feature",
  "properties": {
    "iso:country":"US",
    "sg:address":"1112 E Copeland Rd Ste 400",
    "sg:city":"Arlington",
    "sg:classifiers":[
        {
            "category":"Airline",
            "type":"Transportation"
        },
        {
            "category":"Travel",
            "subcategory":"Travel Agent",
            "type":"Entertainment"
        }
    ],
    "sg:phone":"+1 817 462 0112",
    "sg:postcode":"76011",
    "sg:province":"TX",
    "sg:tags":[
        "ticket",
        "agency"
    ],
    "sg:website":"http://www.etconline.net",
    "wof:name":"Executive Travel Consultant",
    "wof:placetype":"venue"
},
  "geometry": {"coordinates":[-97.093917,32.759121],"type":"Point"}
}