{
  "type": "Feature",
  "properties": {
    "iso:country":"US",
    "sg:address":"7232 Glenview Dr",
    "sg:city":"Fort Worth",
    "sg:classifiers":[
        {
            "category":"Professional",
            "subcategory":"Accounting & Tax Preparation",
            "type":"Services"
        }
    ],
    "sg:phone":"+1 817 589 1120",
    "sg:postcode":"76180",
    "sg:province":"TX",
    "wof:name":"Haynes Ruth E",
    "wof:placetype":"venue"
},
  "geometry": {"coordinates":[-97.225224,32.82375],"type":"Point"}
}