{
  "type": "Feature",
  "properties": {
    "iso:country":"US",
    "sg:address":"400 N Center St",
    "sg:city":"New Boston",
    "sg:classifiers":[
        {
            "category":"Retail",
            "subcategory":"Auto Repair",
            "type":"Services"
        }
    ],
    "sg:phone":"+1 903 628 2914",
    "sg:postcode":"75570",
    "sg:province":"TX",
    "sg:tags":[
        "body",
        "automobile",
        "painting"
    ],
    "wof:name":"Tim Frost Paint & Body Shop",
    "wof:placetype":"venue"
},
  "geometry": {"coordinates":[-94.414818,33.466881],"type":"Point"}
}