{
  "type": "Feature",
  "properties": {
    "iso:country":"US",
    "sg:address":"1800 Victory Dr",
    "sg:city":"Marshall",
    "sg:classifiers":[
        {
            "category":"Banks & Credit Unions",
            "subcategory":"Bank",
            "type":"Services"
        }
    ],
    "sg:phone":"+1 903 935 9669",
    "sg:postcode":"75672",
    "sg:province":"TX",
    "sg:tags":[
        "cashing",
        "check"
    ],
    "wof:name":"Mr Payroll",
    "wof:placetype":"venue"
},
  "geometry": {"coordinates":[-94.349238,32.548339],"type":"Point"}
}