{
  "type": "Feature",
  "properties": {
    "iso:country":"US",
    "sg:address":"1305 2nd St",
    "sg:city":"Eagle Pass",
    "sg:classifiers":[
        {
            "category":"Real Estate",
            "subcategory":"Real Estate Operator",
            "type":"Services"
        }
    ],
    "sg:phone":"+1 830 757 5956",
    "sg:postcode":"78852",
    "sg:province":"TX",
    "sg:tags":[
        "building",
        "apartment"
    ],
    "wof:name":"Baywood Village Apartments",
    "wof:placetype":"venue"
},
  "geometry": {"coordinates":[-100.495385,28.719845],"type":"Point"}
}