{
  "type": "Feature",
  "properties": {
    "iso:country":"US",
    "sg:address":"1209 Canterbury St",
    "sg:city":"Austin",
    "sg:classifiers":[
        {
            "category":"Home & Garden",
            "subcategory":"Building Materials",
            "type":"Retail Goods"
        },
        {
            "category":"Building & Trades",
            "subcategory":"Construction",
            "type":"Services"
        }
    ],
    "sg:phone":"+1 512 474 5526",
    "sg:postcode":"78702",
    "sg:province":"TX",
    "sg:tags":[
        "concrete",
        "staining",
        "contractor"
    ],
    "wof:name":"Javier Castro Concrete",
    "wof:placetype":"venue"
},
  "geometry": {"coordinates":[-97.733245,30.258311],"type":"Point"}
}