{
  "type": "Feature",
  "properties": {
    "iso:country":"US",
    "sg:address":"206 Murphy Rd",
    "sg:city":"Stafford",
    "sg:classifiers":[
        {
            "category":"Personal",
            "subcategory":"Beauty Salon",
            "type":"Services"
        }
    ],
    "sg:phone":"+1 281 499 5544",
    "sg:postcode":"77477",
    "sg:province":"TX",
    "sg:tags":[
        "hair",
        "stylist"
    ],
    "wof:name":"The Hair Machine Inc",
    "wof:placetype":"venue"
},
  "geometry": {"coordinates":[-95.564635,29.618237],"type":"Point"}
}