{
  "type": "Feature",
  "properties": {
    "iso:country":"US",
    "sg:address":"410 Paschall St",
    "sg:city":"Houston",
    "sg:classifiers":[
        {
            "category":"Home & Garden",
            "subcategory":"Carpets & Floor Coverings",
            "type":"Retail Goods"
        }
    ],
    "sg:phone":"+1 713 236 8156",
    "sg:postcode":"77009",
    "sg:province":"TX",
    "wof:name":"Mv Carpet Install",
    "wof:placetype":"venue"
},
  "geometry": {"coordinates":[-95.36362200000001,29.778036],"type":"Point"}
}