{
  "type": "Feature",
  "properties": {
    "iso:country":"US",
    "sg:address":"333 Sam Houston Pkwy",
    "sg:city":"Houston",
    "sg:phone":"+1 281 820 6831",
    "sg:postcode":"77060",
    "sg:province":"TX",
    "sg:tags":[
        "product",
        "petroleum"
    ],
    "wof:name":"Exxon",
    "wof:placetype":"venue"
},
  "geometry": {"coordinates":[-95.398173,29.939901],"type":"Point"}
}