{
  "type": "Feature",
  "properties": {
    "iso:country":"US",
    "sg:address":"1020 Hwy 377 N",
    "sg:city":"Whitesboro",
    "sg:classifiers":[
        {
            "category":"Shopping",
            "subcategory":"Used Merchandise",
            "type":"Retail Goods"
        }
    ],
    "sg:phone":"+1 903 564 5100",
    "sg:postcode":"76273",
    "sg:province":"TX",
    "wof:name":"Jack Pawn Shop",
    "wof:placetype":"venue"
},
  "geometry": {"coordinates":[-96.905845,33.681088],"type":"Point"}
}