{
  "type": "Feature",
  "properties": {
    "iso:country":"US",
    "sg:address":"701 Taylor Dr",
    "sg:city":"Plano",
    "sg:classifiers":[
        {
            "category":"Shopping",
            "subcategory":"Bicycles & Sporting Goods",
            "type":"Retail Goods"
        }
    ],
    "sg:phone":"+1 972 509 1992",
    "sg:postcode":"75074",
    "sg:province":"TX",
    "sg:website":"www.oshmans.com",
    "wof:name":"Sports Authority",
    "wof:placetype":"venue"
},
  "geometry": {"coordinates":[-96.70285,33.008967],"type":"Point"}
}