{
  "type": "Feature",
  "properties": {
    "iso:country":"US",
    "sg:address":"2620 Wolflin Ave",
    "sg:city":"Amarillo",
    "sg:classifiers":[
        {
            "category":"Food & Beverages",
            "subcategory":"Specialty",
            "type":"Retail Goods"
        },
        {
            "category":"Restaurant",
            "type":"Food & Drink"
        }
    ],
    "sg:phone":"+1 806 359 7099",
    "sg:postcode":"79109",
    "sg:province":"TX",
    "sg:tags":[
        "shop",
        "coffee"
    ],
    "sg:website":"www.roasters.biz",
    "wof:name":"Roasters Coffee & Tea",
    "wof:placetype":"venue"
},
  "geometry": {"coordinates":[-101.864226,35.19289],"type":"Point"}
}