{
  "type": "Feature",
  "properties": {
    "iso:country":"US",
    "sg:address":"19710 Topaz Ridge",
    "sg:city":"Magnolia",
    "sg:classifiers":[
        {
            "category":"Professional",
            "type":"Services"
        }
    ],
    "sg:phone":"+1 281 356 3949",
    "sg:postcode":"77355",
    "sg:province":"TX",
    "wof:name":"Annandale Inc",
    "wof:placetype":"venue"
},
  "geometry": {"coordinates":[-95.76196299999999,30.16932],"type":"Point"}
}