{
  "type": "Feature",
  "properties": {
    "iso:country":"US",
    "sg:address":"125 W Huff Ave",
    "sg:city":"San Antonio",
    "sg:classifiers":[
        {
            "category":"Retail",
            "subcategory":"Laundry & Dry Cleaning",
            "type":"Services"
        }
    ],
    "sg:phone":"+1 210 927 1312",
    "sg:postcode":"78214",
    "sg:province":"TX",
    "wof:name":"Clean Carpets R US",
    "wof:placetype":"venue"
},
  "geometry": {"coordinates":[-98.495785,29.363684],"type":"Point"}
}