{
  "type": "Feature",
  "properties": {
    "iso:country":"US",
    "sg:address":"2384 N Chestnut Dr",
    "sg:city":"Pampa",
    "sg:classifiers":[
        {
            "category":"Banks & Credit Unions",
            "subcategory":"Bank",
            "type":"Services"
        }
    ],
    "sg:phone":"+1 806 665 4726",
    "sg:postcode":"79065",
    "sg:province":"TX",
    "sg:tags":[
        "institution",
        "business"
    ],
    "wof:name":"S & S Family Ltd",
    "wof:placetype":"venue"
},
  "geometry": {"coordinates":[-100.959197,35.562949],"type":"Point"}
}