{
  "type": "Feature",
  "properties": {
    "iso:country":"US",
    "sg:address":"12024 Vista Parke Dr",
    "sg:city":"Austin",
    "sg:classifiers":[
        {
            "category":"Education",
            "subcategory":"School",
            "type":"Public Place"
        }
    ],
    "sg:phone":"+1 512 434 7276",
    "sg:postcode":"78701",
    "sg:province":"TX",
    "wof:name":"Leander Independent School District Cedar Park Middle School",
    "wof:placetype":"venue"
},
  "geometry": {"coordinates":[-97.855372,30.416614],"type":"Point"}
}