{
  "type": "Feature",
  "properties": {
    "iso:country":"US",
    "sg:address":"3009 Bomar Ave",
    "sg:city":"Fort Worth",
    "sg:classifiers":[
        {
            "category":"Shopping",
            "subcategory":"Jewelry",
            "type":"Retail Goods"
        }
    ],
    "sg:phone":"+1 817 531 3542",
    "sg:postcode":"76103",
    "sg:province":"TX",
    "sg:tags":[
        "house",
        "mail",
        "costume",
        "mfg"
    ],
    "wof:name":"William S Rae",
    "wof:placetype":"venue"
},
  "geometry": {"coordinates":[-97.281594,32.745833],"type":"Point"}
}