{
  "type": "Feature",
  "properties": {
    "iso:country":"US",
    "sg:address":"8400 Gaylord Pkwy",
    "sg:city":"Little Elm",
    "sg:classifiers":[
        {
            "category":"Professional",
            "type":"Services"
        }
    ],
    "sg:phone":"+1 972 668 6940",
    "sg:postcode":"75034",
    "sg:province":"TX",
    "sg:tags":[
        "establishment"
    ],
    "wof:name":"Leetex Inc",
    "wof:placetype":"venue"
},
  "geometry": {"coordinates":[-96.81362900000001,33.102216],"type":"Point"}
}