{
  "type": "Feature",
  "properties": {
    "iso:country":"US",
    "sg:address":"18052 Martin Dr",
    "sg:city":"Conroe",
    "sg:classifiers":[
        {
            "category":"Banks & Credit Unions",
            "subcategory":"Investment Brokerage",
            "type":"Services"
        }
    ],
    "sg:phone":"+1 936 273 1188",
    "sg:postcode":"77302",
    "sg:province":"TX",
    "sg:tags":[
        "trust"
    ],
    "wof:name":"Vann Family Trust",
    "wof:placetype":"venue"
},
  "geometry": {"coordinates":[-95.29364700000001,30.229661],"type":"Point"}
}