{
  "type": "Feature",
  "properties": {
    "iso:country":"US",
    "sg:address":"9008 Broadway",
    "sg:city":"San Antonio",
    "sg:classifiers":[
        {
            "category":"Retail",
            "subcategory":"Repair Shop",
            "type":"Services"
        }
    ],
    "sg:phone":"+1 210 520 6640",
    "sg:postcode":"78217",
    "sg:province":"TX",
    "wof:name":"Restaurant Repair",
    "wof:placetype":"venue"
},
  "geometry": {"coordinates":[-98.457545,29.523608],"type":"Point"}
}