{
  "type": "Feature",
  "properties": {
    "iso:country":"US",
    "sg:address":"223 Wickhamford Way",
    "sg:city":"Houston",
    "sg:classifiers":[
        {
            "category":"Freight",
            "type":"Transportation"
        }
    ],
    "sg:phone":"+1 713 450 9517",
    "sg:postcode":"77015",
    "sg:province":"TX",
    "sg:tags":[
        "operator",
        "local",
        "trucking"
    ],
    "wof:name":"G M Material Haulers",
    "wof:placetype":"venue"
},
  "geometry": {"coordinates":[-95.170698,29.796358],"type":"Point"}
}