{
  "type": "Feature",
  "properties": {
    "iso:country":"US",
    "sg:address":"300 Trophy Club Dr",
    "sg:city":"Roanoke",
    "sg:classifiers":[
        {
            "category":"Health Services",
            "subcategory":"Doctor",
            "type":"Services"
        }
    ],
    "sg:phone":"+1 817 491 3344",
    "sg:postcode":"76262",
    "sg:province":"TX",
    "sg:tags":[
        "a",
        "as",
        "dentist",
        "operates"
    ],
    "wof:name":"David L Crumpton DDS",
    "wof:placetype":"venue"
},
  "geometry": {"coordinates":[-97.186701,32.995738],"type":"Point"}
}