{
  "type": "Feature",
  "properties": {
    "iso:country":"US",
    "sg:address":"10404 Wommack Rd",
    "sg:city":"Austin",
    "sg:classifiers":[
        {
            "category":"Shopping",
            "subcategory":"Florist",
            "type":"Retail Goods"
        }
    ],
    "sg:phone":"+1 512 291 0748",
    "sg:postcode":"78748",
    "sg:province":"TX",
    "wof:name":"Twin Oaks Florist",
    "wof:placetype":"venue"
},
  "geometry": {"coordinates":[-97.832956,30.17006],"type":"Point"}
}