{
  "type": "Feature",
  "properties": {
    "iso:country":"US",
    "sg:address":"3110 Utah Ave",
    "sg:city":"Dallas",
    "sg:classifiers":[
        {
            "category":"Health Services",
            "subcategory":"Nursing And Care Facility",
            "type":"Services"
        }
    ],
    "sg:phone":"+1 214 375 6160",
    "sg:postcode":"75216",
    "sg:province":"TX",
    "wof:name":"Thomas Housing",
    "wof:placetype":"venue"
},
  "geometry": {"coordinates":[-96.809423,32.706158],"type":"Point"}
}