{
  "type": "Feature",
  "properties": {
    "iso:country":"US",
    "sg:address":"7820 Old Hwy 87",
    "sg:city":"Orange",
    "sg:classifiers":[
        {
            "category":"Building & Trades",
            "subcategory":"Construction",
            "type":"Services"
        }
    ],
    "sg:phone":"+1 409 882 9778",
    "sg:postcode":"77632",
    "sg:province":"TX",
    "sg:tags":[
        "asbestos",
        "removal"
    ],
    "wof:name":"Superior Abatement",
    "wof:placetype":"venue"
},
  "geometry": {"coordinates":[-93.757087,30.180476],"type":"Point"}
}