{
  "type": "Feature",
  "properties": {
    "iso:country":"US",
    "sg:address":"610 Miles St",
    "sg:city":"Hereford",
    "sg:classifiers":[
        {
            "category":"Building & Trades",
            "subcategory":"Electrical",
            "type":"Services"
        }
    ],
    "sg:phone":"+1 806 364 2642",
    "sg:postcode":"79045",
    "sg:province":"TX",
    "sg:tags":[
        "electric",
        "contractor"
    ],
    "wof:name":"Lucero Electric Corp",
    "wof:placetype":"venue"
},
  "geometry": {"coordinates":[-102.402817,34.819698],"type":"Point"}
}