{
  "type": "Feature",
  "properties": {
    "iso:country":"US",
    "sg:address":"6507 Jester Boulevard Suite 507",
    "sg:city":"Austin",
    "sg:classifiers":[
        {
            "category":"Banks & Credit Unions",
            "subcategory":"Investment Brokerage",
            "type":"Services"
        }
    ],
    "sg:phone":"+1 512 231 0800",
    "sg:postcode":"78750",
    "sg:province":"TX",
    "sg:tags":[
        "investing"
    ],
    "sg:website":"www.frankbeck.com",
    "wof:name":"Capital Financial Group",
    "wof:placetype":"venue"
},
  "geometry": {"coordinates":[-97.80185899999999,30.369509],"type":"Point"}
}