{
  "type": "Feature",
  "properties": {
    "iso:country":"US",
    "sg:address":"6209 Hwy 146",
    "sg:city":"Dayton",
    "sg:classifiers":[
        {
            "category":"Building & Trades",
            "subcategory":"Construction",
            "type":"Services"
        }
    ],
    "sg:phone":"+1 936 257 2656",
    "sg:postcode":"77535",
    "sg:province":"TX",
    "sg:tags":[
        "builder",
        "operative"
    ],
    "wof:name":"A R C Structures",
    "wof:placetype":"venue"
},
  "geometry": {"coordinates":[-94.896568,29.899023],"type":"Point"}
}