{
  "type": "Feature",
  "properties": {
    "iso:country":"US",
    "sg:address":"715 Jones St",
    "sg:city":"Fort Worth",
    "sg:classifiers":[
        {
            "category":"Professional",
            "subcategory":"Management & Consulting",
            "type":"Services"
        }
    ],
    "sg:phone":"+1 817 336 3385",
    "sg:postcode":"76102",
    "sg:province":"TX",
    "sg:tags":[
        "business"
    ],
    "wof:name":"Jalapeno Consulting",
    "wof:placetype":"venue"
},
  "geometry": {"coordinates":[-97.327585,32.753893],"type":"Point"}
}