{
  "type": "Feature",
  "properties": {
    "iso:country":"US",
    "sg:address":"1705 Metrocrest Dr",
    "sg:city":"Carrollton",
    "sg:classifiers":[
        {
            "category":"Manufacturing",
            "subcategory":"Metals",
            "type":"Manufacturing & Wholesale Goods"
        }
    ],
    "sg:phone":"+1 972 731 8278",
    "sg:postcode":"75006",
    "sg:province":"TX",
    "wof:name":"Silver Gallery",
    "wof:placetype":"venue"
},
  "geometry": {"coordinates":[-96.886482,32.956838],"type":"Point"}
}