{
  "type": "Feature",
  "properties": {
    "iso:country":"US",
    "sg:address":"2459 Rio Grande Dr",
    "sg:city":"Grand Prairie",
    "sg:classifiers":[
        {
            "category":"Food & Beverages",
            "subcategory":"Groceries & Convenience Stores",
            "type":"Retail Goods"
        }
    ],
    "sg:phone":"+1 972 660 6920",
    "sg:postcode":"75052",
    "sg:province":"TX",
    "wof:name":"Quick Deli",
    "wof:placetype":"venue"
},
  "geometry": {"coordinates":[-97.038715,32.684542],"type":"Point"}
}