{
  "type": "Feature",
  "properties": {
    "iso:country":"US",
    "sg:address":"15104 Blanchard Dr",
    "sg:city":"Austin",
    "sg:classifiers":[
        {
            "category":"Marine",
            "type":"Transportation"
        }
    ],
    "sg:phone":"+1 512 784 7924",
    "sg:postcode":"78734",
    "sg:province":"TX",
    "sg:tags":[
        "towing"
    ],
    "wof:name":"Hudson Bend Marine Svc",
    "wof:placetype":"venue"
},
  "geometry": {"coordinates":[-97.931995,30.391949],"type":"Point"}
}