{
  "type": "Feature",
  "properties": {
    "iso:country":"US",
    "sg:address":"4005 Lullwood Rd",
    "sg:city":"Austin",
    "sg:classifiers":[
        {
            "category":"Professional",
            "subcategory":"Advertising",
            "type":"Services"
        }
    ],
    "sg:phone":"+1 512 477 3378",
    "sg:postcode":"78722",
    "sg:province":"TX",
    "sg:tags":[
        "marketing"
    ],
    "wof:name":"Jam Latino",
    "wof:placetype":"venue"
},
  "geometry": {"coordinates":[-97.713111,30.296078],"type":"Point"}
}