{
  "type": "Feature",
  "properties": {
    "iso:country":"US",
    "sg:address":"2828 E Trinity Mills Rd",
    "sg:city":"Carrollton",
    "sg:classifiers":[
        {
            "category":"Insurance",
            "subcategory":"Insurance Agent",
            "type":"Services"
        },
        {
            "category":"Insurance",
            "subcategory":"Hazard Insurance",
            "type":"Services"
        },
        {
            "category":"Insurance",
            "subcategory":"Title Insurance",
            "type":"Services"
        },
        {
            "category":"Insurance",
            "subcategory":"Life Insurance",
            "type":"Services"
        }
    ],
    "sg:phone":"+1 214 390 1998",
    "sg:postcode":"75006",
    "sg:province":"TX",
    "sg:tags":[
        "business",
        "auto",
        "commercial",
        "homeowner",
        "motorcycle",
        "renter"
    ],
    "wof:name":"Allstate Insurance Company - Bryan Smith",
    "wof:placetype":"venue"
},
  "geometry": {"coordinates":[-96.853849,32.987059],"type":"Point"}
}