{
  "type": "Feature",
  "properties": {
    "iso:country":"US",
    "sg:address":"2904 S 23rd St",
    "sg:city":"Mcallen",
    "sg:classifiers":[
        {
            "category":"Home & Garden",
            "subcategory":"Furniture",
            "type":"Retail Goods"
        }
    ],
    "sg:phone":"+1 956 631 8900",
    "sg:postcode":"78503",
    "sg:province":"TX",
    "wof:name":"Gonzalez Furniture Inc",
    "wof:placetype":"venue"
},
  "geometry": {"coordinates":[-98.249398,26.180692],"type":"Point"}
}