{
  "type": "Feature",
  "properties": {
    "iso:country":"US",
    "sg:address":"12878 State Hwy 155",
    "sg:city":"Tyler",
    "sg:classifiers":[
        {
            "category":"Building & Trades",
            "subcategory":"Plumbing",
            "type":"Services"
        }
    ],
    "sg:phone":"+1 903 561 3363",
    "sg:postcode":"75703",
    "sg:province":"TX",
    "sg:tags":[
        "conditioning",
        "air",
        "system",
        "contractor"
    ],
    "wof:name":"Precision Refrigeration",
    "wof:placetype":"venue"
},
  "geometry": {"coordinates":[-95.34994399999999,32.292541],"type":"Point"}
}