{
  "type": "Feature",
  "properties": {
    "iso:country":"US",
    "sg:address":"19 Hollinger's Island Ct",
    "sg:city":"Katy",
    "sg:classifiers":[
        {
            "category":"Building & Trades",
            "subcategory":"Landscaping Services",
            "type":"Services"
        }
    ],
    "sg:phone":"+1 281 480 2469",
    "sg:postcode":"77450",
    "sg:province":"TX",
    "sg:tags":[
        "planting",
        "tree"
    ],
    "wof:name":"South Texas Tree Sales Inc",
    "wof:placetype":"venue"
},
  "geometry": {"coordinates":[-95.75800700000001,29.743582],"type":"Point"}
}