{
  "type": "Feature",
  "properties": {
    "iso:country":"US",
    "sg:address":"336 W Coll St",
    "sg:city":"New Braunfels",
    "sg:classifiers":[
        {
            "category":"Travel",
            "subcategory":"Campground",
            "type":"Entertainment"
        }
    ],
    "sg:phone":"+1 830 606 4262",
    "sg:postcode":"78130",
    "sg:province":"TX",
    "sg:tags":[
        "camp"
    ],
    "wof:name":"Deer Creek Camp",
    "wof:placetype":"venue"
},
  "geometry": {"coordinates":[-98.124182,29.698908],"type":"Point"}
}