{
  "type": "Feature",
  "properties": {
    "iso:country":"US",
    "sg:address":"2209 Gulf Ave",
    "sg:city":"Midland",
    "sg:classifiers":[
        {
            "category":"Manufacturing",
            "subcategory":"Food",
            "type":"Manufacturing & Wholesale Goods"
        }
    ],
    "sg:phone":"+1 432 570 4454",
    "sg:postcode":"79705",
    "sg:province":"TX",
    "sg:tags":[
        "oil",
        "soybean",
        "mfg"
    ],
    "wof:name":"ADM",
    "wof:placetype":"venue"
},
  "geometry": {"coordinates":[-102.105059,32.013884],"type":"Point"}
}