{
  "type": "Feature",
  "properties": {
    "iso:country":"US",
    "sg:address":"6203 Highland Hills Dr",
    "sg:city":"Austin",
    "sg:classifiers":[
        {
            "category":"Utilities",
            "subcategory":"Mobile Phone",
            "type":"Services"
        }
    ],
    "sg:phone":"+1 512 346 3222",
    "sg:postcode":"78731",
    "sg:province":"TX",
    "sg:tags":[
        "telephone",
        "cellular"
    ],
    "wof:name":"Wireless Dimensions Corp",
    "wof:placetype":"venue"
},
  "geometry": {"coordinates":[-97.76054000000001,30.349583],"type":"Point"}
}