{
  "type": "Feature",
  "properties": {
    "iso:country":"US",
    "sg:address":"2901 S Capital of Texas Hwy",
    "sg:city":"Austin",
    "sg:classifiers":[
        {
            "category":"Shopping",
            "subcategory":"Computers & Home Electronics",
            "type":"Retail Goods"
        }
    ],
    "sg:phone":"+1 512 347 7373",
    "sg:postcode":"78746",
    "sg:province":"TX",
    "sg:tags":[
        "equipment",
        "dealer"
    ],
    "wof:name":"Apple Store",
    "wof:placetype":"venue"
},
  "geometry": {"coordinates":[-97.80790399999999,30.252976],"type":"Point"}
}