{
  "type": "Feature",
  "properties": {
    "iso:country":"US",
    "sg:address":"544 Rosenfeld Rd",
    "sg:city":"Waco",
    "sg:classifiers":[
        {
            "category":"Wholesale",
            "subcategory":"Construction Materials",
            "type":"Manufacturing & Wholesale Goods"
        }
    ],
    "sg:phone":"+1 254 662 1025",
    "sg:postcode":"76706",
    "sg:province":"TX",
    "sg:tags":[
        "sand",
        "gravel"
    ],
    "wof:name":"Trinity Materials Inc",
    "wof:placetype":"venue"
},
  "geometry": {"coordinates":[-97.066171,31.490127],"type":"Point"}
}