{
  "type": "Feature",
  "properties": {
    "iso:country":"US",
    "sg:address":"114 W Adoue St",
    "sg:city":"Alvin",
    "sg:classifiers":[
        {
            "category":"Home & Garden",
            "subcategory":"Furniture",
            "type":"Retail Goods"
        }
    ],
    "sg:phone":"+1 281 331 8090",
    "sg:postcode":"77511",
    "sg:province":"TX",
    "wof:name":"Brindlys Furniture",
    "wof:placetype":"venue"
},
  "geometry": {"coordinates":[-95.244646,29.420356],"type":"Point"}
}