{
  "type": "Feature",
  "properties": {
    "iso:country":"US",
    "sg:address":"4919 Greenwood St",
    "sg:city":"San Antonio",
    "sg:classifiers":[
        {
            "category":"Shopping",
            "type":"Retail Goods"
        }
    ],
    "sg:phone":"+1 210 924 5931",
    "sg:postcode":"78214",
    "sg:province":"TX",
    "sg:tags":[
        "merchandise"
    ],
    "wof:name":"Trophies By Marg",
    "wof:placetype":"venue"
},
  "geometry": {"coordinates":[-98.498091,29.375656],"type":"Point"}
}