{
  "type": "Feature",
  "properties": {
    "iso:country":"US",
    "sg:address":"9 SW 2nd Ave",
    "sg:city":"Perryton",
    "sg:classifiers":[
        {
            "category":"Farming",
            "subcategory":"Farm",
            "type":"Manufacturing & Wholesale Goods"
        }
    ],
    "sg:phone":"+1 806 435 2901",
    "sg:postcode":"79070",
    "sg:province":"TX",
    "sg:tags":[
        "crop",
        "general"
    ],
    "wof:name":"Texas Farm Feedmill",
    "wof:placetype":"venue"
},
  "geometry": {"coordinates":[-100.80278,36.398465],"type":"Point"}
}