{
  "type": "Feature",
  "properties": {
    "iso:country":"US",
    "sg:address":"3924 Country Rd",
    "sg:city":"Pasadena",
    "sg:classifiers":[
        {
            "category":"Education",
            "subcategory":"Dance Studio",
            "type":"Public Place"
        }
    ],
    "sg:phone":"+1 281 998 2222",
    "sg:postcode":"77505",
    "sg:province":"TX",
    "wof:name":"Twin Arts Dance Studio",
    "wof:placetype":"venue"
},
  "geometry": {"coordinates":[-95.149373,29.654499],"type":"Point"}
}