{
  "type": "Feature",
  "properties": {
    "iso:country":"US",
    "sg:address":"1415 Co Rd 4857",
    "sg:city":"Dilley",
    "sg:classifiers":[
        {
            "category":"Farming",
            "subcategory":"Farm",
            "type":"Manufacturing & Wholesale Goods"
        }
    ],
    "sg:phone":"+1 830 378 5520",
    "sg:postcode":"78017",
    "sg:province":"TX",
    "wof:name":"Chiodo Farms",
    "wof:placetype":"venue"
},
  "geometry": {"coordinates":[-99.34622299999999,28.686892],"type":"Point"}
}