{
  "type": "Feature",
  "properties": {
    "iso:country":"US",
    "sg:address":"8008 Cedar Springs Rd Ste 21",
    "sg:city":"Dallas",
    "sg:classifiers":[
        {
            "category":"Communications",
            "subcategory":"Newspaper",
            "type":"Services"
        }
    ],
    "sg:phone":"+1 214 358 1270",
    "sg:postcode":"75235",
    "sg:province":"TX",
    "sg:tags":[
        "print",
        "medium"
    ],
    "wof:name":"Hudson News",
    "wof:placetype":"venue"
},
  "geometry": {"coordinates":[-96.848707,32.843717],"type":"Point"}
}