{
  "type": "Feature",
  "properties": {
    "iso:country":"US",
    "sg:address":"622 Westwood Dr",
    "sg:city":"San Antonio",
    "sg:classifiers":[
        {
            "category":"Professional",
            "subcategory":"Management & Consulting",
            "type":"Services"
        }
    ],
    "sg:phone":"+1 210 734 7908",
    "sg:postcode":"78212",
    "sg:province":"TX",
    "sg:tags":[
        "retail",
        "direct",
        "sales"
    ],
    "wof:name":"Raye Miller",
    "wof:placetype":"venue"
},
  "geometry": {"coordinates":[-98.502723,29.469648],"type":"Point"}
}