{
  "type": "Feature",
  "properties": {
    "iso:country":"US",
    "sg:address":"3319 E Belknap St",
    "sg:city":"Fort Worth",
    "sg:classifiers":[
        {
            "category":"Parking",
            "type":"Transportation"
        },
        {
            "category":"Autos & Motor Vehicles",
            "subcategory":"Fuel & Gas Station",
            "type":"Retail Goods"
        }
    ],
    "sg:phone":"+1 817 831 2556",
    "sg:postcode":"76111",
    "sg:province":"TX",
    "sg:tags":[
        "automobile",
        "oil"
    ],
    "wof:name":"Toney's Fina Station",
    "wof:placetype":"venue"
},
  "geometry": {"coordinates":[-97.299859,32.774419],"type":"Point"}
}