{
  "type": "Feature",
  "properties": {
    "iso:country":"US",
    "sg:address":"80 Spring Creek Vlg",
    "sg:city":"Dallas",
    "sg:classifiers":[
        {
            "category":"Restaurant",
            "type":"Food & Drink"
        }
    ],
    "sg:phone":"+1 972 404 1116",
    "sg:postcode":"75248",
    "sg:province":"TX",
    "sg:tags":[
        "pizza"
    ],
    "wof:name":"Pizza Hut",
    "wof:placetype":"venue"
},
  "geometry": {"coordinates":[-96.77159899999999,32.952],"type":"Point"}
}