{
  "type": "Feature",
  "properties": {
    "iso:country":"US",
    "sg:address":"400 Scott Ave",
    "sg:city":"Wichita Falls",
    "sg:classifiers":[
        {
            "category":"Restaurant",
            "type":"Food & Drink"
        }
    ],
    "sg:phone":"+1 940 322 3531",
    "sg:postcode":"76301",
    "sg:province":"TX",
    "sg:tags":[
        "eating"
    ],
    "wof:name":"Pat's Drive Inn",
    "wof:placetype":"venue"
},
  "geometry": {"coordinates":[-98.494455,33.91485],"type":"Point"}
}