{
  "type": "Feature",
  "properties": {
    "iso:country":"US",
    "sg:address":"3508 Westcliff Rd S",
    "sg:city":"Fort Worth",
    "sg:classifiers":[
        {
            "category":"Shopping",
            "subcategory":"Used Merchandise",
            "type":"Retail Goods"
        }
    ],
    "sg:phone":"+1 817 926 5410",
    "sg:postcode":"76109",
    "sg:province":"TX",
    "wof:name":"Anns Antiques Etc",
    "wof:placetype":"venue"
},
  "geometry": {"coordinates":[-97.369708,32.700666],"type":"Point"}
}