{
  "type": "Feature",
  "properties": {
    "iso:country":"US",
    "sg:address":"502 N 11th St",
    "sg:city":"Mcallen",
    "sg:classifiers":[
        {
            "category":"Professional",
            "subcategory":"Lawyer & Legal Services",
            "type":"Services"
        }
    ],
    "sg:phone":"+1 956 687 8888",
    "sg:postcode":"78501",
    "sg:province":"TX",
    "sg:tags":[
        "attorney"
    ],
    "wof:name":"Carlos H Ochoa Law Office",
    "wof:placetype":"venue"
},
  "geometry": {"coordinates":[-98.230158,26.208859],"type":"Point"}
}