{
  "type": "Feature",
  "properties": {
    "iso:country":"US",
    "sg:address":"4550 N Shepherd Dr",
    "sg:city":"Houston",
    "sg:classifiers":[
        {
            "category":"Restaurant",
            "type":"Food & Drink"
        }
    ],
    "sg:phone":"+1 713 695 9423",
    "sg:postcode":"77018",
    "sg:province":"TX",
    "sg:tags":[
        "barbeque"
    ],
    "wof:name":"Taqueria El Tapatio",
    "wof:placetype":"venue"
},
  "geometry": {"coordinates":[-95.4105,29.8304],"type":"Point"}
}