{
  "type": "Feature",
  "properties": {
    "iso:country":"US",
    "sg:address":"8280 Sheldon Rd",
    "sg:city":"Channelview",
    "sg:classifiers":[
        {
            "category":"Building & Trades",
            "subcategory":"Equipment Rental",
            "type":"Services"
        }
    ],
    "sg:phone":"+1 281 457 2078",
    "sg:postcode":"77530",
    "sg:province":"TX",
    "sg:tags":[
        "heavy",
        "construction"
    ],
    "wof:name":"RSC",
    "wof:placetype":"venue"
},
  "geometry": {"coordinates":[-95.127628,29.844055],"type":"Point"}
}