{
  "type": "Feature",
  "properties": {
    "iso:country":"US",
    "sg:address":"518 W San Antonio St",
    "sg:city":"Lockhart",
    "sg:classifiers":[
        {
            "category":"Home & Garden",
            "subcategory":"Hardware",
            "type":"Retail Goods"
        }
    ],
    "sg:phone":"+1 512 398 4815",
    "sg:postcode":"78644",
    "sg:province":"TX",
    "wof:name":"Acme Ace Hardware",
    "wof:placetype":"venue"
},
  "geometry": {"coordinates":[-97.677352,29.883819],"type":"Point"}
}