{
  "type": "Feature",
  "properties": {
    "iso:country":"US",
    "sg:address":"3110 Baywood Park Dr",
    "sg:city":"Houston",
    "sg:classifiers":[
        {
            "category":"Professional",
            "subcategory":"Printing & Photocopies",
            "type":"Services"
        }
    ],
    "sg:phone":"+1 281 880 6464",
    "sg:postcode":"77068",
    "sg:province":"TX",
    "sg:tags":[
        "medal",
        "plaque",
        "trophies"
    ],
    "wof:name":"Loria Associates",
    "wof:placetype":"venue"
},
  "geometry": {"coordinates":[-95.485721,30.011677],"type":"Point"}
}