{
  "type": "Feature",
  "properties": {
    "iso:country":"US",
    "sg:address":"1801 Sapphire Cove",
    "sg:city":"Cedar Park",
    "sg:classifiers":[
        {
            "category":"Freight",
            "type":"Transportation"
        }
    ],
    "sg:phone":"+1 512 250 9325",
    "sg:postcode":"78613",
    "sg:province":"TX",
    "sg:tags":[
        "shipping",
        "agent"
    ],
    "wof:name":"DMH Talent",
    "wof:placetype":"venue"
},
  "geometry": {"coordinates":[-97.83873199999999,30.479447],"type":"Point"}
}