{
  "type": "Feature",
  "properties": {
    "iso:country":"US",
    "sg:address":"7362 Birchtree Forest Dr",
    "sg:city":"Houston",
    "sg:classifiers":[
        {
            "category":"Restaurant",
            "type":"Food & Drink"
        }
    ],
    "sg:phone":"+1 281 445 7501",
    "sg:postcode":"77088",
    "sg:province":"TX",
    "sg:tags":[
        "eating"
    ],
    "wof:name":"Royal Priest Hood",
    "wof:placetype":"venue"
},
  "geometry": {"coordinates":[-95.45953799999999,29.868661],"type":"Point"}
}