{
  "type": "Feature",
  "properties": {
    "iso:country":"US",
    "sg:address":"105 W Boyd Dr",
    "sg:city":"Allen",
    "sg:classifiers":[
        {
            "category":"Retail",
            "subcategory":"Repair Shop",
            "type":"Services"
        }
    ],
    "sg:phone":"+1 972 727 9026",
    "sg:postcode":"75013",
    "sg:province":"TX",
    "sg:tags":[
        "equipment",
        "electronic",
        "supply"
    ],
    "wof:name":"Q C Svc",
    "wof:placetype":"venue"
},
  "geometry": {"coordinates":[-96.671734,33.104125],"type":"Point"}
}