{
  "type": "Feature",
  "properties": {
    "iso:country":"US",
    "sg:address":"2200 Hancock Dr",
    "sg:city":"Austin",
    "sg:classifiers":[
        {
            "category":"Education",
            "subcategory":"Library",
            "type":"Public Place"
        }
    ],
    "sg:phone":"+1 512 454 7208",
    "sg:postcode":"78756",
    "sg:province":"TX",
    "wof:name":"Yarbrough Library",
    "wof:placetype":"venue"
},
  "geometry": {"coordinates":[-97.74069900000001,30.322917],"type":"Point"}
}