{
  "type": "Feature",
  "properties": {
    "iso:country":"US",
    "sg:address":"2014 Speedway Ave",
    "sg:city":"Wichita Falls",
    "sg:classifiers":[
        {
            "category":"Professional",
            "subcategory":"Advertising",
            "type":"Services"
        }
    ],
    "sg:phone":"+1 940 761 4747",
    "sg:postcode":"76301",
    "sg:province":"TX",
    "sg:tags":[
        "counselor"
    ],
    "sg:website":"www.hammersdesign.com",
    "wof:name":"Hammers Design Agency",
    "wof:placetype":"venue"
},
  "geometry": {"coordinates":[-98.51167100000001,33.888183],"type":"Point"}
}