{
  "type": "Feature",
  "properties": {
    "iso:country":"US",
    "sg:address":"4508 Dyer St",
    "sg:city":"El Paso",
    "sg:classifiers":[
        {
            "category":"Retail",
            "subcategory":"Auto Repair",
            "type":"Services"
        }
    ],
    "sg:phone":"+1 915 564 5317",
    "sg:postcode":"79930",
    "sg:province":"TX",
    "sg:tags":[
        "automotive"
    ],
    "wof:name":"California Luber & Brake",
    "wof:placetype":"venue"
},
  "geometry": {"coordinates":[-106.444585,31.817261],"type":"Point"}
}