{
  "type": "Feature",
  "properties": {
    "iso:country":"US",
    "sg:address":"1101 FM 1825",
    "sg:city":"Pflugerville",
    "sg:classifiers":[
        {
            "category":"Building & Trades",
            "subcategory":"Construction",
            "type":"Services"
        }
    ],
    "sg:phone":"+1 512 251 7690",
    "sg:postcode":"78660",
    "sg:province":"TX",
    "sg:tags":[
        "roofing",
        "contractor"
    ],
    "wof:name":"Roofing Contractors Assn-Texas",
    "wof:placetype":"venue"
},
  "geometry": {"coordinates":[-97.62954999999999,30.443876],"type":"Point"}
}