{
  "type": "Feature",
  "properties": {
    "iso:country":"US",
    "sg:address":"1609 Astor Pl",
    "sg:city":"Austin",
    "sg:classifiers":[
        {
            "category":"Communications",
            "subcategory":"Film & Video Production",
            "type":"Services"
        }
    ],
    "sg:phone":"+1 512 694 4514",
    "sg:postcode":"78721",
    "sg:province":"TX",
    "sg:tags":[
        "motion"
    ],
    "wof:name":"Blue Tone Pictures",
    "wof:placetype":"venue"
},
  "geometry": {"coordinates":[-97.686378,30.28517],"type":"Point"}
}