{
  "type": "Feature",
  "properties": {
    "iso:country":"US",
    "sg:address":"4554 FM 2813",
    "sg:city":"Flint",
    "sg:classifiers":[
        {
            "category":"Organizations",
            "subcategory":"Religious Organization",
            "type":"Services"
        }
    ],
    "sg:phone":"+1 903 839 3535",
    "sg:postcode":"75762",
    "sg:province":"TX",
    "sg:tags":[
        "church"
    ],
    "wof:name":"Tyler Presbyterian Church",
    "wof:placetype":"venue"
},
  "geometry": {"coordinates":[-95.31917,32.239402],"type":"Point"}
}