{
  "type": "Feature",
  "properties": {
    "iso:country":"US",
    "sg:address":"12240 Inwood Rd",
    "sg:city":"Dallas",
    "sg:classifiers":[
        {
            "category":"Personal",
            "subcategory":"Beauty Salon",
            "type":"Services"
        }
    ],
    "sg:phone":"+1 972 387 8077",
    "sg:postcode":"75244",
    "sg:province":"TX",
    "wof:name":"Hairdini",
    "wof:placetype":"venue"
},
  "geometry": {"coordinates":[-96.81826,32.916489],"type":"Point"}
}