{
  "type": "Feature",
  "properties": {
    "iso:country":"US",
    "sg:address":"2418 E Main St",
    "sg:city":"Gatesville",
    "sg:classifiers":[
        {
            "category":"Retail",
            "subcategory":"Laundry & Dry Cleaning",
            "type":"Services"
        }
    ],
    "sg:phone":"+1 254 865 5213",
    "sg:postcode":"76528",
    "sg:province":"TX",
    "sg:tags":[
        "cleaner",
        "commercial"
    ],
    "wof:name":"Valet Cleaners",
    "wof:placetype":"venue"
},
  "geometry": {"coordinates":[-97.722094,31.434698],"type":"Point"}
}