{
  "type": "Feature",
  "properties": {
    "iso:country":"US",
    "sg:address":"1125 Mineral Springs Rd",
    "sg:city":"Arlington",
    "sg:classifiers":[
        {
            "category":"Building & Trades",
            "subcategory":"Construction",
            "type":"Services"
        }
    ],
    "sg:phone":"+1 817 784 1825",
    "sg:postcode":"76001",
    "sg:province":"TX",
    "sg:tags":[
        "steel",
        "erection",
        "structural"
    ],
    "wof:name":"S Rebar Ranches Inc",
    "wof:placetype":"venue"
},
  "geometry": {"coordinates":[-97.12694,32.644975],"type":"Point"}
}