{
  "type": "Feature",
  "properties": {
    "iso:country":"US",
    "sg:address":"708 Main St",
    "sg:city":"Houston",
    "sg:classifiers":[
        {
            "category":"Professional",
            "subcategory":"Lawyer & Legal Services",
            "type":"Services"
        }
    ],
    "sg:phone":"+1 713 222 0733",
    "sg:postcode":"77002",
    "sg:province":"TX",
    "wof:name":"Manor Rogdrick atty",
    "wof:placetype":"venue"
},
  "geometry": {"coordinates":[-95.36339,29.759247],"type":"Point"}
}