{
  "type": "Feature",
  "properties": {
    "iso:country":"US",
    "sg:address":"1913 N Main St",
    "sg:city":"Liberty",
    "sg:classifiers":[
        {
            "category":"Autos & Motor Vehicles",
            "subcategory":"Automobile Sales",
            "type":"Retail Goods"
        }
    ],
    "sg:phone":"+1 936 336 6500",
    "sg:postcode":"77575",
    "sg:province":"TX",
    "sg:tags":[
        "car",
        "dealer"
    ],
    "wof:name":"Carter Auto Inc",
    "wof:placetype":"venue"
},
  "geometry": {"coordinates":[-94.788245,30.071092],"type":"Point"}
}