{
  "type": "Feature",
  "properties": {
    "iso:country":"US",
    "sg:address":"110 W William Cannon Dr",
    "sg:city":"Austin",
    "sg:classifiers":[
        {
            "category":"Health Services",
            "subcategory":"Doctor",
            "type":"Services"
        }
    ],
    "sg:phone":"+1 512 474 2660",
    "sg:postcode":"78745",
    "sg:province":"TX",
    "sg:tags":[
        "medical"
    ],
    "wof:name":"Manuel A Torres MD PA",
    "wof:placetype":"venue"
},
  "geometry": {"coordinates":[-97.77936699999999,30.193346],"type":"Point"}
}