{
  "type": "Feature",
  "properties": {
    "iso:country":"US",
    "sg:address":"7002 Autumn Chase St",
    "sg:city":"San Antonio",
    "sg:classifiers":[
        {
            "category":"Building & Trades",
            "subcategory":"Construction",
            "type":"Services"
        }
    ],
    "sg:phone":"+1 210 554 5310",
    "sg:postcode":"78238",
    "sg:province":"TX",
    "sg:tags":[
        "house"
    ],
    "wof:name":"Roth Enterprises",
    "wof:placetype":"venue"
},
  "geometry": {"coordinates":[-98.62774899999999,29.496129],"type":"Point"}
}