{
  "type": "Feature",
  "properties": {
    "iso:country":"US",
    "sg:address":"517 E Oltorf Street",
    "sg:city":"Austin",
    "sg:classifiers":[
        {
            "category":"Organizations",
            "subcategory":"Religious Organization",
            "type":"Services"
        }
    ],
    "sg:phone":"+1 512 462 3313",
    "sg:postcode":"78704",
    "sg:province":"TX",
    "wof:name":"South Austin Apostolic Church",
    "wof:placetype":"venue"
},
  "geometry": {"coordinates":[-97.75103300000001,30.237401],"type":"Point"}
}