{
  "type": "Feature",
  "properties": {
    "iso:country":"US",
    "sg:address":"113 W Trammell Ave",
    "sg:city":"Fort Worth",
    "sg:classifiers":[
        {
            "category":"Retail",
            "subcategory":"Repair Shop",
            "type":"Services"
        }
    ],
    "sg:phone":"+1 817 293 3353",
    "sg:postcode":"76140",
    "sg:province":"TX",
    "sg:tags":[
        "refinishing",
        "furniture"
    ],
    "wof:name":"Refinishing Shop",
    "wof:placetype":"venue"
},
  "geometry": {"coordinates":[-97.283653,32.631931],"type":"Point"}
}