{
  "type": "Feature",
  "properties": {
    "iso:country":"US",
    "sg:address":"6020 Wyche Blvd",
    "sg:city":"Dallas",
    "sg:classifiers":[
        {
            "category":"Wholesale",
            "subcategory":"Machinery & Supplies",
            "type":"Manufacturing & Wholesale Goods"
        }
    ],
    "sg:phone":"+1 214 631 7983",
    "sg:postcode":"75235",
    "sg:province":"TX",
    "sg:tags":[
        "mfg",
        "industrial",
        "general"
    ],
    "wof:name":"Womack Machine Supply Co",
    "wof:placetype":"venue"
},
  "geometry": {"coordinates":[-96.85129499999999,32.819077],"type":"Point"}
}