{
  "type": "Feature",
  "properties": {
    "iso:country":"US",
    "sg:address":"13444 FM 718",
    "sg:city":"Fort Worth",
    "sg:classifiers":[
        {
            "category":"Retail",
            "subcategory":"Car Wash",
            "type":"Services"
        }
    ],
    "sg:phone":"+1 817 489 5459",
    "sg:postcode":"76179",
    "sg:province":"TX",
    "sg:tags":[
        "truck",
        "cleaning"
    ],
    "wof:name":"Central Dallas Truck Wash",
    "wof:placetype":"venue"
},
  "geometry": {"coordinates":[-97.42209699999999,32.968021],"type":"Point"}
}