{
  "type": "Feature",
  "properties": {
    "iso:country":"US",
    "sg:address":"7394 Regency Square Ct",
    "sg:city":"Houston",
    "sg:classifiers":[
        {
            "category":"Building & Trades",
            "subcategory":"Construction",
            "type":"Services"
        }
    ],
    "sg:phone":"+1 713 266 6314",
    "sg:postcode":"77036",
    "sg:province":"TX",
    "sg:tags":[
        "house"
    ],
    "wof:name":"Ivy Builders LLC",
    "wof:placetype":"venue"
},
  "geometry": {"coordinates":[-95.511715,29.715527],"type":"Point"}
}