{
  "type": "Feature",
  "properties": {
    "iso:country":"US",
    "sg:address":"3910 Eagle Lake Ct",
    "sg:city":"Arlington",
    "sg:classifiers":[
        {
            "category":"Professional",
            "type":"Services"
        }
    ],
    "sg:phone":"+1 817 561 4520",
    "sg:postcode":"76016",
    "sg:province":"TX",
    "sg:tags":[
        "establishment"
    ],
    "wof:name":"Laut Su",
    "wof:placetype":"venue"
},
  "geometry": {"coordinates":[-97.165339,32.684444],"type":"Point"}
}