{
  "type": "Feature",
  "properties": {
    "iso:country":"US",
    "sg:address":"600 Key St",
    "sg:city":"Brenham",
    "sg:classifiers":[
        {
            "category":"Utilities",
            "subcategory":"Telephone",
            "type":"Services"
        }
    ],
    "sg:phone":"+1 409 942 8677",
    "sg:postcode":"77833",
    "sg:province":"TX",
    "sg:tags":[
        "communications"
    ],
    "wof:name":"Southwestern Bell Telephone LP",
    "wof:placetype":"venue"
},
  "geometry": {"coordinates":[-96.402333,30.163338],"type":"Point"}
}