{
  "type": "Feature",
  "properties": {
    "iso:country":"US",
    "sg:address":"15401 FM 2769",
    "sg:city":"Leander",
    "sg:classifiers":[
        {
            "category":"Food & Beverages",
            "subcategory":"Groceries & Convenience Stores",
            "type":"Retail Goods"
        }
    ],
    "sg:phone":"+1 512 258 1633",
    "sg:postcode":"78641",
    "sg:province":"TX",
    "sg:tags":[
        "grocer"
    ],
    "wof:name":"V J Cafe & Store",
    "wof:placetype":"venue"
},
  "geometry": {"coordinates":[-97.90436800000001,30.435796],"type":"Point"}
}