{
  "type": "Feature",
  "properties": {
    "iso:country":"US",
    "sg:address":"317 SW Wilshire Blvd",
    "sg:city":"Burleson",
    "sg:classifiers":[
        {
            "category":"Retail",
            "subcategory":"Animal Services",
            "type":"Services"
        }
    ],
    "sg:phone":"+1 817 447 2143",
    "sg:postcode":"76028",
    "sg:province":"TX",
    "sg:tags":[
        "pet",
        "grooming",
        "washing"
    ],
    "wof:name":"Hot Dog Groomers",
    "wof:placetype":"venue"
},
  "geometry": {"coordinates":[-97.330733,32.541349],"type":"Point"}
}