{
  "type": "Feature",
  "properties": {
    "iso:country":"US",
    "sg:address":"183 N Belknap St",
    "sg:city":"Stephenville",
    "sg:classifiers":[
        {
            "category":"Shopping",
            "subcategory":"Stationery & Office Supplies",
            "type":"Retail Goods"
        }
    ],
    "sg:phone":"+1 254 968 0085",
    "sg:postcode":"76401",
    "sg:province":"TX",
    "sg:tags":[
        "album",
        "scrapbook"
    ],
    "wof:name":"All Things Creative",
    "wof:placetype":"venue"
},
  "geometry": {"coordinates":[-98.20292000000001,32.220431],"type":"Point"}
}