{
  "type": "Feature",
  "properties": {
    "iso:country":"US",
    "sg:address":"414 Spencer Hwy",
    "sg:city":"South Houston",
    "sg:classifiers":[
        {
            "category":"Autos & Motor Vehicles",
            "subcategory":"Automobile Sales",
            "type":"Retail Goods"
        }
    ],
    "sg:phone":"+1 713 910 7777",
    "sg:postcode":"77587",
    "sg:province":"TX",
    "sg:tags":[
        "car",
        "dealer"
    ],
    "wof:name":"AMC Americar Motor Co",
    "wof:placetype":"venue"
},
  "geometry": {"coordinates":[-95.226437,29.664429],"type":"Point"}
}