{
  "type": "Feature",
  "properties": {
    "iso:country":"US",
    "sg:address":"424 S R L Thornton Fwy",
    "sg:city":"Dallas",
    "sg:classifiers":[
        {
            "category":"Autos & Motor Vehicles",
            "subcategory":"Fuel & Gas Station",
            "type":"Retail Goods"
        }
    ],
    "sg:phone":"+1 214 946 9810",
    "sg:postcode":"75203",
    "sg:province":"TX",
    "sg:tags":[
        "station",
        "gasoline",
        "oil"
    ],
    "wof:name":"R L Thornton Shell",
    "wof:placetype":"venue"
},
  "geometry": {"coordinates":[-96.80891699999999,32.752204],"type":"Point"}
}