{
  "type": "Feature",
  "properties": {
    "iso:country":"US",
    "sg:address":"114 N Dixie Dr",
    "sg:city":"Lake Jackson",
    "sg:classifiers":[
        {
            "category":"Personal",
            "subcategory":"Tanning Parlor",
            "type":"Services"
        }
    ],
    "sg:phone":"+1 979 299 6368",
    "sg:postcode":"77566",
    "sg:province":"TX",
    "sg:tags":[
        "salon"
    ],
    "wof:name":"Pretty Nails & Tanning Salon",
    "wof:placetype":"venue"
},
  "geometry": {"coordinates":[-95.42058299999999,29.020584],"type":"Point"}
}