{
  "type": "Feature",
  "properties": {
    "iso:country":"US",
    "sg:address":"3119 Chisholm Trl",
    "sg:city":"Austin",
    "sg:classifiers":[
        {
            "category":"Retail",
            "subcategory":"Portrait Studio",
            "type":"Services"
        }
    ],
    "sg:phone":"+1 512 266 9840",
    "sg:postcode":"78734",
    "sg:province":"TX",
    "sg:tags":[
        "photo"
    ],
    "wof:name":"LFC Photographic",
    "wof:placetype":"venue"
},
  "geometry": {"coordinates":[-97.91863499999999,30.384325],"type":"Point"}
}