{
  "type": "Feature",
  "properties": {
    "iso:country":"US",
    "sg:address":"710 W Ave A",
    "sg:city":"Hooks",
    "sg:classifiers":[
        {
            "category":"Government",
            "subcategory":"Court House",
            "type":"Public Place"
        }
    ],
    "sg:phone":"+1 903 547 6900",
    "sg:postcode":"75561",
    "sg:province":"TX",
    "sg:tags":[
        "justice",
        "peace"
    ],
    "wof:name":"Justice Of Peace",
    "wof:placetype":"venue"
},
  "geometry": {"coordinates":[-94.290223,33.466253],"type":"Point"}
}