{
  "type": "Feature",
  "properties": {
    "iso:country":"US",
    "sg:address":"1023 N Houston Ave",
    "sg:city":"Humble",
    "sg:classifiers":[
        {
            "category":"Building & Trades",
            "subcategory":"Construction",
            "type":"Services"
        }
    ],
    "sg:phone":"+1 281 540 2411",
    "sg:postcode":"77338",
    "sg:province":"TX",
    "sg:tags":[
        "contractor"
    ],
    "sg:website":"www.dt-construction.com",
    "wof:name":"D T Construction Inc",
    "wof:placetype":"venue"
},
  "geometry": {"coordinates":[-95.258459,30.004026],"type":"Point"}
}