{
  "type": "Feature",
  "properties": {
    "iso:country":"US",
    "sg:address":"300 Pressler St",
    "sg:city":"Austin",
    "sg:phone":"+1 512 477 5274",
    "sg:postcode":"78703",
    "sg:province":"TX",
    "wof:name":"Austin Duck Adventures",
    "wof:placetype":"venue"
},
  "geometry": {"coordinates":[-97.761261,30.271879],"type":"Point"}
}