{
  "type": "Feature",
  "properties": {
    "iso:country":"US",
    "sg:address":"4315 W Pipeline Rd",
    "sg:city":"Euless",
    "sg:classifiers":[
        {
            "category":"Personal",
            "subcategory":"Beauty Salon",
            "type":"Services"
        }
    ],
    "sg:phone":"+1 817 282 9015",
    "sg:postcode":"76040",
    "sg:province":"TX",
    "wof:name":"Tijeritas Unisex",
    "wof:placetype":"venue"
},
  "geometry": {"coordinates":[-97.15504,32.823229],"type":"Point"}
}