{
  "type": "Feature",
  "properties": {
    "iso:country":"US",
    "sg:address":"1513 3rd St",
    "sg:city":"Seabrook",
    "sg:classifiers":[
        {
            "category":"Organizations",
            "subcategory":"Religious Organization",
            "type":"Services"
        }
    ],
    "sg:phone":"+1 281 474 2851",
    "sg:postcode":"77586",
    "sg:province":"TX",
    "wof:name":"Seabrook United Methdst Church",
    "wof:placetype":"venue"
},
  "geometry": {"coordinates":[-95.024553,29.561861],"type":"Point"}
}