{
  "type": "Feature",
  "properties": {
    "iso:country":"US",
    "sg:address":"2926 Ventura Dr",
    "sg:city":"Abilene",
    "sg:classifiers":[
        {
            "category":"Real Estate",
            "subcategory":"Real Estate Agent",
            "type":"Services"
        }
    ],
    "sg:phone":"+1 325 692 7475",
    "sg:postcode":"79605",
    "sg:province":"TX",
    "wof:name":"MD Totco",
    "wof:placetype":"venue"
},
  "geometry": {"coordinates":[-99.767172,32.41622],"type":"Point"}
}