{
  "type": "Feature",
  "properties": {
    "iso:country":"US",
    "sg:address":"1002 N 38th St",
    "sg:city":"Killeen",
    "sg:classifiers":[
        {
            "category":"Banks & Credit Unions",
            "subcategory":"Bank",
            "type":"Services"
        }
    ],
    "sg:phone":"+1 254 554 6699",
    "sg:postcode":"76543",
    "sg:province":"TX",
    "sg:tags":[
        "saving",
        "commercial"
    ],
    "sg:website":"http://www.1stcb.com",
    "wof:name":"First National Bank Texas",
    "wof:placetype":"venue"
},
  "geometry": {"coordinates":[-97.698427,31.11843],"type":"Point"}
}