{
  "type": "Feature",
  "properties": {
    "iso:country":"US",
    "sg:address":"2090 Colleen Dr",
    "sg:city":"New Braunfels",
    "sg:classifiers":[
        {
            "category":"Professional",
            "subcategory":"Management & Consulting",
            "type":"Services"
        }
    ],
    "sg:phone":"+1 830 832 7874",
    "sg:postcode":"78133",
    "sg:province":"TX",
    "sg:tags":[
        "business"
    ],
    "wof:name":"Reed Consulting Services",
    "wof:placetype":"venue"
},
  "geometry": {"coordinates":[-98.227056,29.862111],"type":"Point"}
}