{
  "type": "Feature",
  "properties": {
    "iso:country":"US",
    "sg:address":"7018 Spring Cypress Rd",
    "sg:city":"Spring",
    "sg:classifiers":[
        {
            "category":"Building & Trades",
            "subcategory":"Construction",
            "type":"Services"
        }
    ],
    "sg:phone":"+1 281 376 5252",
    "sg:postcode":"77379",
    "sg:province":"TX",
    "sg:tags":[
        "roofing",
        "contractor"
    ],
    "wof:name":"Patrick Roofing",
    "wof:placetype":"venue"
},
  "geometry": {"coordinates":[-95.53094900000001,30.048586],"type":"Point"}
}