{
  "type": "Feature",
  "properties": {
    "iso:country":"US",
    "sg:address":"4220 Forbes Dr",
    "sg:city":"Plano",
    "sg:classifiers":[
        {
            "category":"Health Services",
            "subcategory":"Clinic",
            "type":"Services"
        }
    ],
    "sg:phone":"+1 972 612 8711",
    "sg:postcode":"75093",
    "sg:province":"TX",
    "sg:tags":[
        "nutrition",
        "specialist",
        "consultant"
    ],
    "wof:name":"Health Management Service",
    "wof:placetype":"venue"
},
  "geometry": {"coordinates":[-96.77452,33.047239],"type":"Point"}
}