{
  "type": "Feature",
  "properties": {
    "iso:country":"US",
    "sg:address":"4001 Halsey St",
    "sg:city":"Victoria",
    "sg:classifiers":[
        {
            "category":"Professional",
            "type":"Services"
        }
    ],
    "sg:phone":"+1 361 485 0526",
    "sg:postcode":"77901",
    "sg:province":"TX",
    "sg:tags":[
        "establishment"
    ],
    "wof:name":"Vistavolunteer",
    "wof:placetype":"venue"
},
  "geometry": {"coordinates":[-96.987764,28.831139],"type":"Point"}
}