{
  "type": "Feature",
  "properties": {
    "iso:country":"US",
    "sg:address":"3402 Lewis Ln",
    "sg:city":"Amarillo",
    "sg:classifiers":[
        {
            "category":"Building & Trades",
            "subcategory":"Pest Control",
            "type":"Services"
        }
    ],
    "sg:phone":"+1 806 359 0811",
    "sg:postcode":"79109",
    "sg:province":"TX",
    "wof:name":"Tony Smeaton Pest Control",
    "wof:placetype":"venue"
},
  "geometry": {"coordinates":[-101.872832,35.176509],"type":"Point"}
}