{
  "type": "Feature",
  "properties": {
    "iso:country":"US",
    "sg:address":"2726 S Padre Island Dr",
    "sg:city":"Corpus Christi",
    "sg:classifiers":[
        {
            "category":"Retail",
            "subcategory":"Auto Repair",
            "type":"Services"
        }
    ],
    "sg:phone":"+1 361 855 6421",
    "sg:postcode":"78415",
    "sg:province":"TX",
    "sg:tags":[
        "repairing",
        "automobile"
    ],
    "wof:name":"Import Service Ctr",
    "wof:placetype":"venue"
},
  "geometry": {"coordinates":[-97.422275,27.733601],"type":"Point"}
}