{
  "type": "Feature",
  "properties": {
    "iso:country":"US",
    "sg:address":"12202 Whittington Dr",
    "sg:city":"Houston",
    "sg:classifiers":[
        {
            "category":"Building & Trades",
            "subcategory":"Construction",
            "type":"Services"
        }
    ],
    "sg:phone":"+1 281 497 7283",
    "sg:postcode":"77077",
    "sg:province":"TX",
    "sg:tags":[
        "house"
    ],
    "wof:name":"Bunce Home Repair",
    "wof:placetype":"venue"
},
  "geometry": {"coordinates":[-95.596113,29.747736],"type":"Point"}
}