{
  "type": "Feature",
  "properties": {
    "iso:country":"US",
    "sg:address":"6121 Berkshire Ln",
    "sg:city":"Dallas",
    "sg:classifiers":[
        {
            "category":"Building & Trades",
            "subcategory":"Construction",
            "type":"Services"
        }
    ],
    "sg:phone":"+1 214 265 0001",
    "sg:postcode":"75225",
    "sg:province":"TX",
    "sg:tags":[
        "home",
        "builder"
    ],
    "wof:name":"Nickey Oates Co",
    "wof:placetype":"venue"
},
  "geometry": {"coordinates":[-96.805474,32.864925],"type":"Point"}
}