{
  "type": "Feature",
  "properties": {
    "iso:country":"US",
    "sg:address":"1224 Leopard St",
    "sg:city":"Corpus Christi",
    "sg:classifiers":[
        {
            "category":"Professional",
            "subcategory":"Business Services",
            "type":"Services"
        }
    ],
    "sg:phone":"+1 361 653 1030",
    "sg:postcode":"78401",
    "sg:province":"TX",
    "wof:name":"Amrus Group Inc",
    "wof:placetype":"venue"
},
  "geometry": {"coordinates":[-97.403859,27.796484],"type":"Point"}
}