{
  "type": "Feature",
  "properties": {
    "iso:country":"US",
    "sg:address":"1711 Purple Sage Dr",
    "sg:city":"Cedar Park",
    "sg:classifiers":[
        {
            "category":"Professional",
            "subcategory":"Business Services",
            "type":"Services"
        }
    ],
    "sg:phone":"+1 512 260 6965",
    "sg:postcode":"78681",
    "sg:province":"TX",
    "wof:name":"Saramak Outdoor Projects",
    "wof:placetype":"venue"
},
  "geometry": {"coordinates":[-97.681293,30.492],"type":"Point"}
}