{
  "type": "Feature",
  "properties": {
    "iso:country":"US",
    "sg:address":"624 Fort Worth Ave",
    "sg:city":"Dallas",
    "sg:classifiers":[
        {
            "category":"Retail",
            "subcategory":"Auto Repair",
            "type":"Services"
        }
    ],
    "sg:phone":"+1 214 651 7610",
    "sg:postcode":"75208",
    "sg:province":"TX",
    "sg:tags":[
        "body",
        "automobile",
        "painting"
    ],
    "wof:name":"Juan's Body & Frame",
    "wof:placetype":"venue"
},
  "geometry": {"coordinates":[-96.83250200000001,32.772611],"type":"Point"}
}