{
  "type": "Feature",
  "properties": {
    "iso:country":"US",
    "sg:address":"510 E Pierce St",
    "sg:city":"Luling",
    "sg:classifiers":[
        {
            "category":"Health Services",
            "subcategory":"Hospital",
            "type":"Services"
        }
    ],
    "sg:phone":"+1 830 875 5700",
    "sg:postcode":"78648",
    "sg:province":"TX",
    "sg:tags":[
        "mental"
    ],
    "wof:name":"Bluebonnet Trails Community",
    "wof:placetype":"venue"
},
  "geometry": {"coordinates":[-97.640387,29.679741],"type":"Point"}
}