{
  "type": "Feature",
  "properties": {
    "iso:country":"US",
    "sg:address":"124 N Saint Marys St",
    "sg:city":"Falfurrias",
    "sg:classifiers":[
        {
            "category":"Organizations",
            "subcategory":"Professional Association",
            "type":"Services"
        }
    ],
    "sg:phone":"+1 361 325 3333",
    "sg:postcode":"78355",
    "sg:province":"TX",
    "sg:tags":[
        "chambers",
        "commerce"
    ],
    "wof:name":"Chamber Of Commerce",
    "wof:placetype":"venue"
},
  "geometry": {"coordinates":[-98.144114,27.226995],"type":"Point"}
}