{
  "type": "Feature",
  "properties": {
    "iso:country":"US",
    "sg:address":"903 W 12th St",
    "sg:city":"Freeport",
    "sg:classifiers":[
        {
            "category":"Wholesale",
            "subcategory":"Computers",
            "type":"Manufacturing & Wholesale Goods"
        }
    ],
    "sg:phone":"+1 979 233 1264",
    "sg:postcode":"77541",
    "sg:province":"TX",
    "sg:tags":[
        "equipment",
        "processing",
        "datum"
    ],
    "wof:name":"Hawk's Computers",
    "wof:placetype":"venue"
},
  "geometry": {"coordinates":[-95.36019400000001,28.944551],"type":"Point"}
}