{
  "type": "Feature",
  "properties": {
    "iso:country":"US",
    "sg:address":"507 Royal St",
    "sg:city":"Cleburne",
    "sg:classifiers":[
        {
            "category":"Organizations",
            "subcategory":"Religious Organization",
            "type":"Services"
        }
    ],
    "sg:phone":"+1 817 645 3730",
    "sg:postcode":"76031",
    "sg:province":"TX",
    "wof:name":"St Pauls Chrstn Methdst Church",
    "wof:placetype":"venue"
},
  "geometry": {"coordinates":[-97.37806500000001,32.353235],"type":"Point"}
}