{
  "type": "Feature",
  "properties": {
    "iso:country":"US",
    "sg:address":"3617 Brazos St",
    "sg:city":"Damon",
    "sg:classifiers":[
        {
            "category":"Utilities",
            "subcategory":"Water",
            "type":"Services"
        }
    ],
    "sg:phone":"+1 979 742 3343",
    "sg:postcode":"77430",
    "sg:province":"TX",
    "sg:tags":[
        "company",
        "sewage"
    ],
    "wof:name":"Brazoria County Fresh Water",
    "wof:placetype":"venue"
},
  "geometry": {"coordinates":[-95.73244200000001,29.290326],"type":"Point"}
}