{
  "type": "Feature",
  "properties": {
    "iso:country":"US",
    "sg:address":"5480 Walzem Rd",
    "sg:city":"San Antonio",
    "sg:classifiers":[
        {
            "category":"Personal",
            "type":"Services"
        }
    ],
    "sg:phone":"+1 210 650 5300",
    "sg:postcode":"78218",
    "sg:province":"TX",
    "sg:tags":[
        "control",
        "weight"
    ],
    "wof:name":"Jenny Craig Weight Loss Ctr",
    "wof:placetype":"venue"
},
  "geometry": {"coordinates":[-98.381086,29.510208],"type":"Point"}
}