{
  "type": "Feature",
  "properties": {
    "iso:country":"US",
    "sg:address":"19803 Belle Way Dr",
    "sg:city":"Humble",
    "sg:classifiers":[
        {
            "category":"Professional",
            "type":"Services"
        }
    ],
    "sg:phone":"+1 281 852 8084",
    "sg:postcode":"77338",
    "sg:province":"TX",
    "wof:name":"Aurora Service Co",
    "wof:placetype":"venue"
},
  "geometry": {"coordinates":[-95.223398,30.009033],"type":"Point"}
}