{
  "type": "Feature",
  "properties": {
    "iso:country":"US",
    "sg:address":"30444 FM 3009",
    "sg:city":"New Braunfels",
    "sg:classifiers":[
        {
            "category":"Communications",
            "subcategory":"Radio Station",
            "type":"Services"
        }
    ],
    "sg:phone":"+1 830 885 2735",
    "sg:postcode":"78132",
    "sg:province":"TX",
    "sg:tags":[
        "charitable",
        "religious",
        "organization"
    ],
    "wof:name":"Light Shine Ministries",
    "wof:placetype":"venue"
},
  "geometry": {"coordinates":[-98.30447599999999,29.753928],"type":"Point"}
}