{
  "type": "Feature",
  "properties": {
    "iso:country":"US",
    "sg:address":"4722 Grand Lake Dr",
    "sg:city":"Corpus Christi",
    "sg:classifiers":[
        {
            "category":"Personal",
            "type":"Services"
        }
    ],
    "sg:phone":"+1 361 850 9786",
    "sg:postcode":"78413",
    "sg:province":"TX",
    "wof:name":"C&D Enterprises",
    "wof:placetype":"venue"
},
  "geometry": {"coordinates":[-97.41186399999999,27.67344],"type":"Point"}
}