{
  "type": "Feature",
  "properties": {
    "iso:country":"US",
    "sg:address":"708 N Locust St",
    "sg:city":"Denton",
    "sg:classifiers":[
        {
            "category":"Personal",
            "subcategory":"Beauty Salon",
            "type":"Services"
        }
    ],
    "sg:phone":"+1 940 382 8430",
    "sg:postcode":"76201",
    "sg:province":"TX",
    "wof:name":"Exclusive Hair Design",
    "wof:placetype":"venue"
},
  "geometry": {"coordinates":[-97.132254,33.220045],"type":"Point"}
}