{
  "type": "Feature",
  "properties": {
    "iso:country":"US",
    "sg:address":"10922 Checkerboard St",
    "sg:city":"Houston",
    "sg:classifiers":[
        {
            "category":"Professional",
            "subcategory":"Secretarial Services",
            "type":"Services"
        }
    ],
    "sg:phone":"+1 713 721 6086",
    "sg:postcode":"77096",
    "sg:province":"TX",
    "sg:tags":[
        "convention",
        "reporting",
        "reporters-court"
    ],
    "wof:name":"Wright, David",
    "wof:placetype":"venue"
},
  "geometry": {"coordinates":[-95.480148,29.661452],"type":"Point"}
}