{
  "type": "Feature",
  "properties": {
    "iso:country":"US",
    "sg:address":"1201 Westheimer Rd",
    "sg:city":"Houston",
    "sg:classifiers":[
        {
            "category":"Personal",
            "subcategory":"Beauty Salon",
            "type":"Services"
        }
    ],
    "sg:phone":"+1 713 524 7785",
    "sg:postcode":"77006",
    "sg:province":"TX",
    "sg:tags":[
        "shop"
    ],
    "wof:name":"Four Star Hair Productions",
    "wof:placetype":"venue"
},
  "geometry": {"coordinates":[-95.394374,29.744152],"type":"Point"}
}