{
  "type": "Feature",
  "properties": {
    "iso:country":"US",
    "sg:address":"1270 Lakey Dr",
    "sg:city":"Silsbee",
    "sg:classifiers":[
        {
            "category":"Retail",
            "subcategory":"Car Wash",
            "type":"Services"
        }
    ],
    "sg:phone":"+1 409 651 3670",
    "sg:postcode":"77656",
    "sg:province":"TX",
    "sg:tags":[
        "carwash"
    ],
    "wof:name":"Under Pressure",
    "wof:placetype":"venue"
},
  "geometry": {"coordinates":[-94.156233,30.333818],"type":"Point"}
}