{
  "type": "Feature",
  "properties": {
    "iso:country":"US",
    "sg:address":"519 Woodbend Ln",
    "sg:city":"Houston",
    "sg:classifiers":[
        {
            "category":"Wholesale",
            "subcategory":"Computers",
            "type":"Manufacturing & Wholesale Goods"
        }
    ],
    "sg:phone":"+1 281 293 0847",
    "sg:postcode":"77079",
    "sg:province":"TX",
    "sg:tags":[
        "services-wholesale",
        "software"
    ],
    "wof:name":"King Expert Data Systems",
    "wof:placetype":"venue"
},
  "geometry": {"coordinates":[-95.589113,29.765155],"type":"Point"}
}