{
  "type": "Feature",
  "properties": {
    "iso:country":"US",
    "sg:address":"1302 Las Vacas St",
    "sg:city":"Del Rio",
    "sg:classifiers":[
        {
            "category":"Shopping",
            "subcategory":"Used Merchandise",
            "type":"Retail Goods"
        }
    ],
    "sg:phone":"+1 830 775 1922",
    "sg:postcode":"78840",
    "sg:province":"TX",
    "wof:name":"Las Tres B",
    "wof:placetype":"venue"
},
  "geometry": {"coordinates":[-100.91051299999999,29.351132],"type":"Point"}
}