{
  "type": "Feature",
  "properties": {
    "iso:country":"US",
    "sg:address":"5346 Ash Ln",
    "sg:city":"Dallas",
    "sg:classifiers":[
        {
            "category":"Building & Trades",
            "subcategory":"Construction",
            "type":"Services"
        }
    ],
    "sg:phone":"+1 214 680 0999",
    "sg:postcode":"75223",
    "sg:province":"TX",
    "sg:tags":[
        "painting",
        "contractor"
    ],
    "sg:website":"http://www.alexispainting.net",
    "wof:name":"Alexis Painting Dallas Tx",
    "wof:placetype":"venue"
},
  "geometry": {"coordinates":[-96.755162,32.795618],"type":"Point"}
}