{
  "type": "Feature",
  "properties": {
    "iso:country":"US",
    "sg:address":"2102 Royal Ln",
    "sg:city":"Longview",
    "sg:classifiers":[
        {
            "category":"Insurance",
            "subcategory":"Insurance Agent",
            "type":"Services"
        }
    ],
    "sg:phone":"+1 903 759 2900",
    "sg:postcode":"75604",
    "sg:province":"TX",
    "wof:name":"Worksite Concepts",
    "wof:placetype":"venue"
},
  "geometry": {"coordinates":[-94.806178,32.530199],"type":"Point"}
}