{
  "type": "Feature",
  "properties": {
    "iso:country":"US",
    "sg:address":"3414 Easy St",
    "sg:city":"Dallas",
    "sg:classifiers":[
        {
            "category":"Wholesale",
            "subcategory":"Machinery & Supplies",
            "type":"Manufacturing & Wholesale Goods"
        }
    ],
    "sg:phone":"+1 214 634 2040",
    "sg:postcode":"75247",
    "sg:province":"TX",
    "sg:tags":[
        "tool"
    ],
    "wof:name":"A A Tool Sales",
    "wof:placetype":"venue"
},
  "geometry": {"coordinates":[-96.875614,32.807451],"type":"Point"}
}