{
  "type": "Feature",
  "properties": {
    "iso:country":"US",
    "sg:address":"822 E 9th St",
    "sg:city":"Dallas",
    "sg:classifiers":[
        {
            "category":"Building & Trades",
            "subcategory":"Plumbing",
            "type":"Services"
        }
    ],
    "sg:phone":"+1 214 941 0129",
    "sg:postcode":"75203",
    "sg:province":"TX",
    "sg:tags":[
        "contractor"
    ],
    "wof:name":"Emmett Plumbing Service",
    "wof:placetype":"venue"
},
  "geometry": {"coordinates":[-96.81199599999999,32.7495],"type":"Point"}
}