{
  "type": "Feature",
  "properties": {
    "iso:country":"US",
    "sg:address":"1006 Burning Tree Rd",
    "sg:city":"Kingwood",
    "sg:classifiers":[
        {
            "category":"Health Services",
            "subcategory":"Clinic",
            "type":"Services"
        },
        {
            "category":"Health Services",
            "subcategory":"Health Practitioner",
            "type":"Services"
        },
        {
            "category":"Community Center",
            "subcategory":"Social",
            "type":"Public Place"
        }
    ],
    "sg:phone":"+1 281 358 3700",
    "sg:postcode":"77339",
    "sg:province":"TX",
    "sg:tags":[
        "information",
        "smoker",
        "hypnotherapy",
        "treatment",
        "welfare",
        "hypnotist"
    ],
    "wof:name":"Path Foundation",
    "wof:placetype":"venue"
},
  "geometry": {"coordinates":[-95.24472900000001,30.033225],"type":"Point"}
}