{
  "type": "Feature",
  "properties": {
    "iso:country":"US",
    "sg:address":"500 E 31st St",
    "sg:city":"Bryan",
    "sg:classifiers":[
        {
            "category":"Insurance",
            "subcategory":"Insurance Agent",
            "type":"Services"
        }
    ],
    "sg:phone":"+1 979 823 7476",
    "sg:postcode":"77803",
    "sg:province":"TX",
    "wof:name":"John W Bradley Jr Office",
    "wof:placetype":"venue"
},
  "geometry": {"coordinates":[-96.36872700000001,30.666504],"type":"Point"}
}