{
  "type": "Feature",
  "properties": {
    "iso:country":"US",
    "sg:address":"16233 Clay Rd",
    "sg:city":"Houston",
    "sg:phone":"+1 281 550 3066",
    "sg:postcode":"77084",
    "sg:province":"TX",
    "wof:name":"24 Hour Fitness",
    "wof:placetype":"venue"
},
  "geometry": {"coordinates":[-95.647758,29.835951],"type":"Point"}
}