{
  "type": "Feature",
  "properties": {
    "iso:country":"US",
    "sg:address":"2315 N Main St",
    "sg:city":"Houston",
    "sg:classifiers":[
        {
            "category":"Wholesale",
            "subcategory":"Auto Parts",
            "type":"Manufacturing & Wholesale Goods"
        }
    ],
    "sg:phone":"+1 713 227 6175",
    "sg:postcode":"77009",
    "sg:province":"TX",
    "sg:tags":[
        "used"
    ],
    "wof:name":"North Main Auto Supply Inc",
    "wof:placetype":"venue"
},
  "geometry": {"coordinates":[-95.364299,29.781499],"type":"Point"}
}