{
  "type": "Feature",
  "properties": {
    "iso:country":"US",
    "sg:address":"1102 S Oakes St",
    "sg:city":"San Angelo",
    "sg:classifiers":[
        {
            "category":"Autos & Motor Vehicles",
            "subcategory":"Auto Supplies",
            "type":"Retail Goods"
        }
    ],
    "sg:phone":"+1 325 655 5319",
    "sg:postcode":"76903",
    "sg:province":"TX",
    "wof:name":"Hawkins Battery Shop",
    "wof:placetype":"venue"
},
  "geometry": {"coordinates":[-100.431676,31.449674],"type":"Point"}
}