{
  "type": "Feature",
  "properties": {
    "iso:country":"US",
    "sg:address":"8724 Barrow Glen Loop",
    "sg:city":"Austin",
    "sg:classifiers":[
        {
            "category":"Recreation",
            "type":"Entertainment"
        }
    ],
    "sg:phone":"+1 512 280 2861",
    "sg:postcode":"78749",
    "sg:province":"TX",
    "sg:tags":[
        "guide"
    ],
    "wof:name":"Git Bit Fishing Guide Svc",
    "wof:placetype":"venue"
},
  "geometry": {"coordinates":[-97.85723900000001,30.204021],"type":"Point"}
}