{
  "type": "Feature",
  "properties": {
    "iso:country":"US",
    "sg:address":"1120 McRae Blvd",
    "sg:city":"El Paso",
    "sg:classifiers":[
        {
            "category":"Shopping",
            "type":"Retail Goods"
        }
    ],
    "sg:phone":"+1 915 629 9700",
    "sg:postcode":"79925",
    "sg:province":"TX",
    "sg:tags":[
        "telephone",
        "cellular"
    ],
    "wof:name":"T Mobile Mc Rae Ctr",
    "wof:placetype":"venue"
},
  "geometry": {"coordinates":[-106.354975,31.761087],"type":"Point"}
}