{
  "type": "Feature",
  "properties": {
    "iso:country":"US",
    "sg:address":"10531 Sagebluff Dr",
    "sg:city":"Houston",
    "sg:classifiers":[
        {
            "category":"Shopping",
            "subcategory":"Clothing, Apparel, & Fashions",
            "type":"Retail Goods"
        }
    ],
    "sg:phone":"+1 281 481 9300",
    "sg:postcode":"77089",
    "sg:province":"TX",
    "wof:name":"Patco Services Inc",
    "wof:placetype":"venue"
},
  "geometry": {"coordinates":[-95.236834,29.593533],"type":"Point"}
}