{
  "type": "Feature",
  "properties": {
    "iso:country":"US",
    "sg:address":"1714 Yorkshire Dr",
    "sg:city":"Richardson",
    "sg:classifiers":[
        {
            "category":"Building & Trades",
            "subcategory":"Construction",
            "type":"Services"
        }
    ],
    "sg:phone":"+1 972 479 9940",
    "sg:postcode":"75082",
    "sg:province":"TX",
    "sg:tags":[
        "contractor"
    ],
    "wof:name":"Gold Shield Insulation In",
    "wof:placetype":"venue"
},
  "geometry": {"coordinates":[-96.691779,32.977982],"type":"Point"}
}