{
  "type": "Feature",
  "properties": {
    "iso:country":"US",
    "sg:address":"Rose Dental Group 6211 W William Cannon Dr",
    "sg:city":"Austin",
    "sg:classifiers":[
        {
            "category":"Health Services",
            "subcategory":"Dentist",
            "type":"Services"
        }
    ],
    "sg:phone":"+1 512 288 4447",
    "sg:postcode":"78798",
    "sg:province":"TX",
    "sg:website":"www.rosedental.net/",
    "wof:name":"Celina Calvillo-Sanchez, DDS",
    "wof:placetype":"venue"
},
  "geometry": {"coordinates":[-97.864884,30.23033],"type":"Point"}
}