{
  "type": "Feature",
  "properties": {
    "iso:country":"US",
    "sg:address":"7347 Drury Cross Rd",
    "sg:city":"Burleson",
    "sg:classifiers":[
        {
            "category":"Shopping",
            "type":"Retail Goods"
        }
    ],
    "sg:phone":"+1 817 483 8635",
    "sg:postcode":"76028",
    "sg:province":"TX",
    "sg:tags":[
        "merchandise"
    ],
    "wof:name":"D & N Fireworks",
    "wof:placetype":"venue"
},
  "geometry": {"coordinates":[-97.215763,32.565722],"type":"Point"}
}