{
  "type": "Feature",
  "properties": {
    "iso:country":"US",
    "sg:address":"14 E St",
    "sg:city":"Mercedes",
    "sg:classifiers":[
        {
            "category":"Freight",
            "type":"Transportation"
        }
    ],
    "sg:phone":"+1 956 565 2770",
    "sg:postcode":"78552",
    "sg:province":"TX",
    "sg:tags":[
        "commercial",
        "storage"
    ],
    "wof:name":"Heggen Self Storage",
    "wof:placetype":"venue"
},
  "geometry": {"coordinates":[-97.781525,26.170053],"type":"Point"}
}