{
  "type": "Feature",
  "properties": {
    "iso:country":"US",
    "sg:address":"1008 Pecan Blvd",
    "sg:city":"Mcallen",
    "sg:classifiers":[
        {
            "category":"Shopping",
            "subcategory":"Stationery & Office Supplies",
            "type":"Retail Goods"
        }
    ],
    "sg:phone":"+1 956 682 6306",
    "sg:postcode":"78501",
    "sg:province":"TX",
    "wof:name":"DOS Business Products",
    "wof:placetype":"venue"
},
  "geometry": {"coordinates":[-98.22756,26.217776],"type":"Point"}
}