{
  "type": "Feature",
  "properties": {
    "iso:country":"US",
    "sg:address":"14011 FM 2920",
    "sg:city":"Tomball",
    "sg:classifiers":[
        {
            "category":"Shopping",
            "subcategory":"Used Merchandise",
            "type":"Retail Goods"
        }
    ],
    "sg:phone":"+1 281 351 2662",
    "sg:postcode":"77377",
    "sg:province":"TX",
    "sg:tags":[
        "shop",
        "pawn"
    ],
    "wof:name":"Tomball Pawn & Jewelry",
    "wof:placetype":"venue"
},
  "geometry": {"coordinates":[-95.632457,30.089416],"type":"Point"}
}