{
  "type": "Feature",
  "properties": {
    "iso:country":"US",
    "sg:address":"102 E Texas Ave",
    "sg:city":"Baytown",
    "sg:classifiers":[
        {
            "category":"Shopping",
            "subcategory":"Clothing, Apparel, & Fashions",
            "type":"Retail Goods"
        }
    ],
    "sg:phone":"+1 281 422 8385",
    "sg:postcode":"77520",
    "sg:province":"TX",
    "sg:tags":[
        "a",
        "leather",
        "retailer",
        "operates",
        "as",
        "sh",
        "western",
        "wear"
    ],
    "wof:name":"Anderson Shoe & Saddle Repair",
    "wof:placetype":"venue"
},
  "geometry": {"coordinates":[-94.96574099999999,29.7315],"type":"Point"}
}