{
  "type": "Feature",
  "properties": {
    "iso:country":"US",
    "sg:address":"1150 S Mason Rd",
    "sg:city":"Katy",
    "sg:classifiers":[
        {
            "category":"Banks & Credit Unions",
            "subcategory":"Investment Brokerage",
            "type":"Services"
        }
    ],
    "sg:phone":"+1 281 392 1055",
    "sg:postcode":"77450",
    "sg:province":"TX",
    "sg:tags":[
        "security"
    ],
    "wof:name":"Edward Jones 14108",
    "wof:placetype":"venue"
},
  "geometry": {"coordinates":[-95.75170300000001,29.762987],"type":"Point"}
}