{
  "type": "Feature",
  "properties": {
    "iso:country":"US",
    "sg:address":"108 Sidney St",
    "sg:city":"Houston",
    "sg:classifiers":[
        {
            "category":"Freight",
            "type":"Transportation"
        }
    ],
    "sg:phone":"+1 713 926 1901",
    "sg:postcode":"77003",
    "sg:province":"TX",
    "sg:tags":[
        "operator",
        "local",
        "trucking"
    ],
    "wof:name":"AB Direct",
    "wof:placetype":"venue"
},
  "geometry": {"coordinates":[-95.33215800000001,29.747456],"type":"Point"}
}