{
  "type": "Feature",
  "properties": {
    "iso:country":"US",
    "sg:address":"543 10th St",
    "sg:city":"Floresville",
    "sg:classifiers":[
        {
            "category":"Health Services",
            "subcategory":"Clinic",
            "type":"Services"
        }
    ],
    "sg:phone":"+1 830 393 4010",
    "sg:postcode":"78114",
    "sg:province":"TX",
    "sg:tags":[
        "kidney",
        "dialysis",
        "center"
    ],
    "wof:name":"Gambro Hlthcare Ptent Svcs Inc",
    "wof:placetype":"venue"
},
  "geometry": {"coordinates":[-98.16385699999999,29.151345],"type":"Point"}
}