{
  "type": "Feature",
  "properties": {
    "iso:country":"US",
    "sg:address":"14812 Avery Ranch Blvd # 5",
    "sg:city":"Austin",
    "sg:classifiers":[
        {
            "category":"Retail",
            "subcategory":"Driving School",
            "type":"Services"
        }
    ],
    "sg:phone":"+1 512 671 8600",
    "sg:postcode":"78717",
    "sg:province":"TX",
    "sg:tags":[
        "instruction",
        "traffic"
    ],
    "wof:name":"A Dee Light Defensive Driving",
    "wof:placetype":"venue"
},
  "geometry": {"coordinates":[-97.778899,30.497096],"type":"Point"}
}