{
  "type": "Feature",
  "properties": {
    "iso:country":"US",
    "sg:address":"910 Kyle Dr",
    "sg:city":"Athens",
    "sg:classifiers":[
        {
            "category":"Organizations",
            "subcategory":"Religious Organization",
            "type":"Services"
        }
    ],
    "sg:phone":"+1 903 677 2438",
    "sg:postcode":"75751",
    "sg:province":"TX",
    "wof:name":"Bill & Kathy Watson",
    "wof:placetype":"venue"
},
  "geometry": {"coordinates":[-95.839665,32.190563],"type":"Point"}
}