{
  "type": "Feature",
  "properties": {
    "iso:country":"US",
    "sg:address":"109 N Oregon St",
    "sg:city":"El Paso",
    "sg:classifiers":[
        {
            "category":"Restaurant",
            "type":"Food & Drink"
        }
    ],
    "sg:phone":"+1 915 545 2233",
    "sg:postcode":"79901",
    "sg:province":"TX",
    "sg:website":"www.cafecentral.com",
    "wof:name":"Cafe Central",
    "wof:placetype":"venue"
},
  "geometry": {"coordinates":[-106.488017,31.758298],"type":"Point"}
}