{
  "type": "Feature",
  "properties": {
    "iso:country":"US",
    "sg:address":"802 Meyer St",
    "sg:city":"Sealy",
    "sg:classifiers":[
        {
            "category":"Shopping",
            "subcategory":"Pharmacy",
            "type":"Retail Goods"
        }
    ],
    "sg:phone":"+1 979 885 3538",
    "sg:postcode":"77474",
    "sg:province":"TX",
    "sg:tags":[
        "drug",
        "store"
    ],
    "wof:name":"Eckerd",
    "wof:placetype":"venue"
},
  "geometry": {"coordinates":[-96.156282,29.776039],"type":"Point"}
}