{
  "type": "Feature",
  "properties": {
    "iso:country":"US",
    "sg:address":"3488 N 1st St",
    "sg:city":"Abilene",
    "sg:classifiers":[
        {
            "category":"Personal",
            "subcategory":"Beauty Salon",
            "type":"Services"
        }
    ],
    "sg:phone":"+1 325 676 8426",
    "sg:postcode":"79603",
    "sg:province":"TX",
    "sg:tags":[
        "spa",
        "day"
    ],
    "wof:name":"Pat Burton",
    "wof:placetype":"venue"
},
  "geometry": {"coordinates":[-99.765691,32.452217],"type":"Point"}
}