{
  "type": "Feature",
  "properties": {
    "iso:country":"US",
    "sg:address":"5800 Kell Blvd",
    "sg:city":"Wichita Falls",
    "sg:classifiers":[
        {
            "category":"Health Services",
            "subcategory":"Clinic",
            "type":"Services"
        }
    ],
    "sg:phone":"+1 940 692 9824",
    "sg:postcode":"76310",
    "sg:province":"TX",
    "sg:tags":[
        "home"
    ],
    "wof:name":"Best Care Health Svc Inc",
    "wof:placetype":"venue"
},
  "geometry": {"coordinates":[-98.58269,33.872445],"type":"Point"}
}