{
  "type": "Feature",
  "properties": {
    "iso:country":"US",
    "sg:address":"6580 Southwest Fwy",
    "sg:city":"Houston",
    "sg:classifiers":[
        {
            "category":"Autos & Motor Vehicles",
            "subcategory":"Auto Supplies",
            "type":"Retail Goods"
        }
    ],
    "sg:phone":"+1 713 270 5001",
    "sg:postcode":"77074",
    "sg:province":"TX",
    "sg:tags":[
        "tire"
    ],
    "sg:website":"www.discounttire.com/makeappt",
    "wof:name":"Discount Tire Co of Texas Inc",
    "wof:placetype":"venue"
},
  "geometry": {"coordinates":[-95.49892699999999,29.718016],"type":"Point"}
}