{
  "type": "Feature",
  "properties": {
    "iso:country":"US",
    "sg:address":"229 Huisache Ave",
    "sg:city":"Rio Hondo",
    "sg:classifiers":[
        {
            "category":"Organizations",
            "subcategory":"Religious Organization",
            "type":"Services"
        }
    ],
    "sg:phone":"+1 956 748 2234",
    "sg:postcode":"78583",
    "sg:province":"TX",
    "sg:tags":[
        "church"
    ],
    "wof:name":"Church St Helen",
    "wof:placetype":"venue"
},
  "geometry": {"coordinates":[-97.579227,26.236969],"type":"Point"}
}