{
  "type": "Feature",
  "properties": {
    "iso:country":"US",
    "sg:address":"605 S Frio St",
    "sg:city":"Lockhart",
    "sg:classifiers":[
        {
            "category":"Farming",
            "subcategory":"Livestock Farm",
            "type":"Manufacturing & Wholesale Goods"
        }
    ],
    "sg:phone":"+1 512 398 5460",
    "sg:postcode":"78644",
    "sg:province":"TX",
    "sg:tags":[
        "beef",
        "feedlot",
        "cattle"
    ],
    "wof:name":"Lyndon R Homann",
    "wof:placetype":"venue"
},
  "geometry": {"coordinates":[-97.677285,29.879676],"type":"Point"}
}