{
  "type": "Feature",
  "properties": {
    "iso:country":"US",
    "sg:address":"108 S William Barnett Ave",
    "sg:city":"Cleveland",
    "sg:classifiers":[
        {
            "category":"Health Services",
            "subcategory":"Doctor",
            "type":"Services"
        },
        {
            "category":"Health Services",
            "subcategory":"Clinic",
            "type":"Services"
        },
        {
            "category":"Community Center",
            "type":"Public Place"
        }
    ],
    "sg:phone":"+1 281 592 9775",
    "sg:postcode":"77327",
    "sg:province":"TX",
    "sg:tags":[
        "physician",
        "family",
        "medical",
        "practice",
        "surgeons",
        "medicine"
    ],
    "wof:name":"Calvary Medical Clinic",
    "wof:placetype":"venue"
},
  "geometry": {"coordinates":[-95.08526500000001,30.34112],"type":"Point"}
}