{
  "type": "Feature",
  "properties": {
    "iso:country":"US",
    "sg:address":"404 McKinney Pkwy",
    "sg:city":"Mc Kinney",
    "sg:classifiers":[
        {
            "category":"Professional",
            "subcategory":"Art Services",
            "type":"Services"
        }
    ],
    "sg:phone":"+1 972 562 0605",
    "sg:postcode":"75071",
    "sg:province":"TX",
    "sg:tags":[
        "calligrapher"
    ],
    "wof:name":"Ken Brown Studio",
    "wof:placetype":"venue"
},
  "geometry": {"coordinates":[-96.609058,33.212806],"type":"Point"}
}