{
  "type": "Feature",
  "properties": {
    "iso:country":"US",
    "sg:address":"500 Jefferson St",
    "sg:city":"Houston",
    "sg:classifiers":[
        {
            "category":"Personal",
            "subcategory":"Beauty Salon",
            "type":"Services"
        }
    ],
    "sg:phone":"+1 713 659 6032",
    "sg:postcode":"77002",
    "sg:province":"TX",
    "sg:tags":[
        "shop"
    ],
    "wof:name":"Hair It Is Downtown",
    "wof:placetype":"venue"
},
  "geometry": {"coordinates":[-95.374371,29.75399],"type":"Point"}
}