{
  "type": "Feature",
  "properties": {
    "iso:country":"US",
    "sg:address":"1421 Chaparral Rd",
    "sg:city":"Burkburnett",
    "sg:classifiers":[
        {
            "category":"Restaurant",
            "type":"Food & Drink"
        }
    ],
    "sg:phone":"+1 940 569 0157",
    "sg:postcode":"76354",
    "sg:province":"TX",
    "sg:tags":[
        "eating"
    ],
    "wof:name":"Jackies Kitchen",
    "wof:placetype":"venue"
},
  "geometry": {"coordinates":[-98.589304,34.074287],"type":"Point"}
}