{
  "type": "Feature",
  "properties": {
    "iso:country":"US",
    "sg:address":"9807 Robin St",
    "sg:city":"La Porte",
    "sg:classifiers":[
        {
            "category":"Recreation",
            "type":"Entertainment"
        }
    ],
    "sg:phone":"+1 281 470 2997",
    "sg:postcode":"77571",
    "sg:province":"TX",
    "wof:name":"Riptide Guide Service",
    "wof:placetype":"venue"
},
  "geometry": {"coordinates":[-95.080556,29.675332],"type":"Point"}
}