{
  "type": "Feature",
  "properties": {
    "iso:country":"US",
    "sg:address":"319 Corpus Christi St",
    "sg:city":"Laredo",
    "sg:classifiers":[
        {
            "category":"Insurance",
            "subcategory":"Insurance Agent",
            "type":"Services"
        }
    ],
    "sg:phone":"+1 956 753 3773",
    "sg:postcode":"78040",
    "sg:province":"TX",
    "wof:name":"Farmers Insurance",
    "wof:placetype":"venue"
},
  "geometry": {"coordinates":[-99.493011,27.508322],"type":"Point"}
}