{
  "type": "Feature",
  "properties": {
    "iso:country":"US",
    "sg:address":"2816 James Louis Dr",
    "sg:city":"Amarillo",
    "sg:classifiers":[
        {
            "category":"Building & Trades",
            "subcategory":"Cleaning & Sanitation",
            "type":"Services"
        }
    ],
    "sg:phone":"+1 806 359 8233",
    "sg:postcode":"79110",
    "sg:province":"TX",
    "sg:tags":[
        "maintenance"
    ],
    "wof:name":"Wcs Janitorial",
    "wof:placetype":"venue"
},
  "geometry": {"coordinates":[-101.86957,35.158822],"type":"Point"}
}