{
  "type": "Feature",
  "properties": {
    "iso:country":"US",
    "sg:address":"210 W Katherine P Raines Rd",
    "sg:city":"Cleburne",
    "sg:classifiers":[
        {
            "category":"Restaurant",
            "type":"Food & Drink"
        }
    ],
    "sg:menulink":"http://www.allmenus.com/tx/cleburne/106928-soup-man/menu/",
    "sg:phone":"+1 817 641 2002",
    "sg:postcode":"76033",
    "sg:province":"TX",
    "sg:tags":[
        "soup",
        "american",
        "salad"
    ],
    "wof:name":"Soup Man",
    "wof:placetype":"venue"
},
  "geometry": {"coordinates":[-97.42753500000001,32.373411],"type":"Point"}
}