{
  "type": "Feature",
  "properties": {
    "iso:country":"US",
    "sg:address":"8014 Darkwood",
    "sg:city":"San Antonio",
    "sg:classifiers":[
        {
            "category":"Social Services",
            "type":"Services"
        }
    ],
    "sg:phone":"+1 210 521 6392",
    "sg:postcode":"78250",
    "sg:province":"TX",
    "sg:tags":[
        "counseling"
    ],
    "wof:name":"Almo Area Home Counseling Svcs",
    "wof:placetype":"venue"
},
  "geometry": {"coordinates":[-98.669476,29.513703],"type":"Point"}
}