{
  "type": "Feature",
  "properties": {
    "iso:country":"US",
    "sg:address":"604 S Seguin Ave",
    "sg:city":"New Braunfels",
    "sg:classifiers":[
        {
            "category":"Real Estate",
            "subcategory":"Real Estate Agent",
            "type":"Services"
        }
    ],
    "sg:phone":"+1 830 625 8061",
    "sg:postcode":"78130",
    "sg:province":"TX",
    "sg:website":"www.century21-action.com",
    "wof:name":"Century 21 United Action Realt",
    "wof:placetype":"venue"
},
  "geometry": {"coordinates":[-98.116631,29.697457],"type":"Point"}
}