{
  "type": "Feature",
  "properties": {
    "iso:country":"US",
    "sg:address":"1502 Knob Hill Dr",
    "sg:city":"Garland",
    "sg:classifiers":[
        {
            "category":"Building & Trades",
            "subcategory":"Construction",
            "type":"Services"
        }
    ],
    "sg:phone":"+1 972 303 1570",
    "sg:postcode":"75043",
    "sg:province":"TX",
    "sg:tags":[
        "contractor"
    ],
    "wof:name":"Partners Constructors Inc",
    "wof:placetype":"venue"
},
  "geometry": {"coordinates":[-96.58234299999999,32.857915],"type":"Point"}
}