{
  "type": "Feature",
  "properties": {
    "iso:country":"US",
    "sg:address":"811 Orange Ave",
    "sg:city":"Weslaco",
    "sg:classifiers":[
        {
            "category":"Real Estate",
            "subcategory":"Real Estate Operator",
            "type":"Services"
        }
    ],
    "sg:phone":"+1 956 968 7221",
    "sg:postcode":"78596",
    "sg:province":"TX",
    "sg:tags":[
        "property",
        "lessor"
    ],
    "wof:name":"Bruce Edwards",
    "wof:placetype":"venue"
},
  "geometry": {"coordinates":[-97.983346,26.151763],"type":"Point"}
}