{
  "type": "Feature",
  "properties": {
    "iso:country":"US",
    "sg:address":"7930 Hanna St",
    "sg:city":"Houston",
    "sg:classifiers":[
        {
            "category":"Social Services",
            "type":"Services"
        }
    ],
    "sg:phone":"+1 713 672 4766",
    "sg:postcode":"77028",
    "sg:province":"TX",
    "wof:name":"Mommys Daycare",
    "wof:placetype":"venue"
},
  "geometry": {"coordinates":[-95.28184899999999,29.81313],"type":"Point"}
}