{
  "type": "Feature",
  "properties": {
    "iso:country":"US",
    "sg:address":"3322 Clarksburg Dr",
    "sg:city":"Austin",
    "sg:classifiers":[
        {
            "category":"Professional",
            "subcategory":"Art Services",
            "type":"Services"
        }
    ],
    "sg:phone":"+1 512 282 8181",
    "sg:postcode":"78745",
    "sg:province":"TX",
    "sg:tags":[
        "graphic",
        "designer"
    ],
    "wof:name":"Divine Design",
    "wof:placetype":"venue"
},
  "geometry": {"coordinates":[-97.833083,30.207063],"type":"Point"}
}