{
  "type": "Feature",
  "properties": {
    "iso:country":"US",
    "sg:address":"6314 Wade Rd",
    "sg:city":"Baytown",
    "sg:classifiers":[
        {
            "category":"Building & Trades",
            "subcategory":"Construction",
            "type":"Services"
        }
    ],
    "sg:phone":"+1 281 424 4699",
    "sg:postcode":"77521",
    "sg:province":"TX",
    "sg:tags":[
        "contractor"
    ],
    "wof:name":"Scaffolding Painting Insulating Inc",
    "wof:placetype":"venue"
},
  "geometry": {"coordinates":[-95.016502,29.791201],"type":"Point"}
}