{
  "type": "Feature",
  "properties": {
    "iso:country":"US",
    "sg:address":"120 Val Verde St",
    "sg:city":"El Paso",
    "sg:classifiers":[
        {
            "category":"Wholesale",
            "subcategory":"Machinery & Supplies",
            "type":"Manufacturing & Wholesale Goods"
        },
        {
            "category":"Shopping",
            "type":"Retail Goods"
        }
    ],
    "sg:phone":"+1 915 772 4141",
    "sg:postcode":"79905",
    "sg:province":"TX",
    "sg:tags":[
        "equipment",
        "dairy",
        "merchandise"
    ],
    "wof:name":"Crouch Supply Co Inc",
    "wof:placetype":"venue"
},
  "geometry": {"coordinates":[-106.43271900000001,31.769306],"type":"Point"}
}