{
  "type": "Feature",
  "properties": {
    "iso:country":"US",
    "sg:address":"4460 Trinity Mills Rd",
    "sg:city":"Dallas",
    "sg:classifiers":[
        {
            "category":"Real Estate",
            "subcategory":"Real Estate Agent",
            "type":"Services"
        }
    ],
    "sg:phone":"+1 972 818 0957",
    "sg:postcode":"75287",
    "sg:province":"TX",
    "sg:tags":[
        "finding",
        "apartment",
        "rental"
    ],
    "wof:name":"Spectrum Apartment Locators",
    "wof:placetype":"venue"
},
  "geometry": {"coordinates":[-96.83234,32.98973],"type":"Point"}
}