{
  "type": "Feature",
  "properties": {
    "iso:country":"US",
    "sg:address":"5050 W Commerce St",
    "sg:city":"San Antonio",
    "sg:classifiers":[
        {
            "category":"Wholesale",
            "subcategory":"Groceries",
            "type":"Manufacturing & Wholesale Goods"
        }
    ],
    "sg:phone":"+1 210 433 7889",
    "sg:postcode":"78237",
    "sg:province":"TX",
    "sg:tags":[
        "tortilla"
    ],
    "wof:name":"Tortilleria Del Barrio",
    "wof:placetype":"venue"
},
  "geometry": {"coordinates":[-98.56062900000001,29.431246],"type":"Point"}
}