{
  "type": "Feature",
  "properties": {
    "iso:country":"US",
    "sg:address":"4145 S Cooper St",
    "sg:city":"Arlington",
    "sg:classifiers":[
        {
            "category":"Home & Garden",
            "subcategory":"Home Furnishings",
            "type":"Retail Goods"
        }
    ],
    "sg:phone":"+1 817 472 8282",
    "sg:postcode":"76015",
    "sg:province":"TX",
    "wof:name":"Pier 1",
    "wof:placetype":"venue"
},
  "geometry": {"coordinates":[-97.134618,32.68014],"type":"Point"}
}