{
  "type": "Feature",
  "properties": {
    "iso:country":"US",
    "sg:address":"16283 Old Hwy 105 W",
    "sg:city":"Montgomery",
    "sg:classifiers":[
        {
            "category":"Building & Trades",
            "subcategory":"Construction",
            "type":"Services"
        }
    ],
    "sg:phone":"+1 936 273 3623",
    "sg:postcode":"77356",
    "sg:province":"TX",
    "sg:tags":[
        "coping",
        "plastering",
        "tiling",
        "pool",
        "swimming"
    ],
    "wof:name":"Arnold-Wise Pool Svc Inc",
    "wof:placetype":"venue"
},
  "geometry": {"coordinates":[-95.792973,30.346074],"type":"Point"}
}