{
  "type": "Feature",
  "properties": {
    "iso:country":"US",
    "sg:address":"7 Star Fern Pl",
    "sg:city":"Spring",
    "sg:classifiers":[
        {
            "category":"Wholesale",
            "subcategory":"Hardware",
            "type":"Manufacturing & Wholesale Goods"
        }
    ],
    "sg:phone":"+1 281 364 0011",
    "sg:postcode":"77380",
    "sg:province":"TX",
    "sg:tags":[
        "mfr",
        "rep"
    ],
    "wof:name":"Hydro Tech Inc",
    "wof:placetype":"venue"
},
  "geometry": {"coordinates":[-95.460159,30.148562],"type":"Point"}
}