{
  "type": "Feature",
  "properties": {
    "iso:country":"US",
    "sg:address":"13404 US Hwy 87",
    "sg:city":"Lubbock",
    "sg:classifiers":[
        {
            "category":"Wholesale",
            "subcategory":"Chemicals & Plastics",
            "type":"Manufacturing & Wholesale Goods"
        }
    ],
    "sg:phone":"+1 806 745 9447",
    "sg:postcode":"79423",
    "sg:province":"TX",
    "wof:name":"B M C T A S C O Chemicals",
    "wof:placetype":"venue"
},
  "geometry": {"coordinates":[-101.84454700000001,33.4618],"type":"Point"}
}