{
  "type": "Feature",
  "properties": {
    "iso:country":"US",
    "sg:address":"17115 Co Rd 831",
    "sg:city":"Pearland",
    "sg:classifiers":[
        {
            "category":"Building & Trades",
            "subcategory":"Construction",
            "type":"Services"
        }
    ],
    "sg:phone":"+1 281 489 4977",
    "sg:postcode":"77584",
    "sg:province":"TX",
    "sg:tags":[
        "underground",
        "excavating",
        "contractor",
        "utility"
    ],
    "wof:name":"C N C Trenching Co",
    "wof:placetype":"venue"
},
  "geometry": {"coordinates":[-95.319318,29.520057],"type":"Point"}
}