{
  "type": "Feature",
  "properties": {
    "iso:country":"US",
    "sg:address":"2815 W Clarendon Dr",
    "sg:city":"Dallas",
    "sg:classifiers":[
        {
            "category":"Personal",
            "subcategory":"Beauty Salon",
            "type":"Services"
        }
    ],
    "sg:phone":"+1 214 330 4084",
    "sg:postcode":"75211",
    "sg:province":"TX",
    "sg:tags":[
        "shop"
    ],
    "wof:name":"Demoras Beauty Salon",
    "wof:placetype":"venue"
},
  "geometry": {"coordinates":[-96.868566,32.734484],"type":"Point"}
}