{
  "type": "Feature",
  "properties": {
    "iso:country":"US",
    "sg:address":"3800 Andrews Hwy",
    "sg:city":"Odessa",
    "sg:classifiers":[
        {
            "category":"Restaurant",
            "type":"Food & Drink"
        }
    ],
    "sg:menulink":"http://www.allmenus.com/tx/odessa/13424-churchs-chicken/menu/",
    "sg:phone":"+1 432 362 6413",
    "sg:postcode":"79762",
    "sg:province":"TX",
    "sg:tags":[
        "chicken",
        "wing"
    ],
    "wof:name":"Church's Chicken",
    "wof:placetype":"venue"
},
  "geometry": {"coordinates":[-102.38408,31.879873],"type":"Point"}
}