{
  "type": "Feature",
  "properties": {
    "iso:country":"US",
    "sg:address":"3711 Montana Ave",
    "sg:city":"El Paso",
    "sg:classifiers":[
        {
            "category":"Cinema",
            "subcategory":"Movie Rental",
            "type":"Entertainment"
        }
    ],
    "sg:phone":"+1 915 566 4665",
    "sg:postcode":"79903",
    "sg:province":"TX",
    "sg:tags":[
        "leasing",
        "video",
        "disc",
        "tape"
    ],
    "wof:name":"Bible Society Video-Bookstore",
    "wof:placetype":"venue"
},
  "geometry": {"coordinates":[-106.448185,31.783747],"type":"Point"}
}