{
  "type": "Feature",
  "properties": {
    "iso:country":"US",
    "sg:address":"2005 Broadway St",
    "sg:city":"Houston",
    "sg:classifiers":[
        {
            "category":"Shopping",
            "subcategory":"Gifts & Souvenirs",
            "type":"Retail Goods"
        }
    ],
    "sg:phone":"+1 713 643 3764",
    "sg:postcode":"77012",
    "sg:province":"TX",
    "sg:tags":[
        "party",
        "supply"
    ],
    "wof:name":"Jumpin Frogs Party Rentals",
    "wof:placetype":"venue"
},
  "geometry": {"coordinates":[-95.278019,29.708837],"type":"Point"}
}