{
  "type": "Feature",
  "properties": {
    "iso:country":"US",
    "sg:address":"500 Broadnax St",
    "sg:city":"Daingerfield",
    "sg:classifiers":[
        {
            "category":"Government",
            "subcategory":"Office",
            "type":"Public Place"
        }
    ],
    "sg:phone":"+1 903 645 3696",
    "sg:postcode":"75638",
    "sg:province":"TX",
    "sg:tags":[
        "state"
    ],
    "wof:name":"Parks & Wildlife Dept",
    "wof:placetype":"venue"
},
  "geometry": {"coordinates":[-94.725838,33.035986],"type":"Point"}
}