{
  "type": "Feature",
  "properties": {
    "iso:country":"US",
    "sg:address":"12100 Metric Blvd Apt 916",
    "sg:city":"Austin",
    "sg:classifiers":[
        {
            "category":"Building & Trades",
            "subcategory":"Construction",
            "type":"Services"
        }
    ],
    "sg:phone":"+1 512 373 6653",
    "sg:postcode":"78758",
    "sg:province":"TX",
    "sg:tags":[
        "wallcoverings-installation",
        "wallpaper",
        "painting",
        "contractor"
    ],
    "wof:name":"Cj's Painting And More",
    "wof:placetype":"venue"
},
  "geometry": {"coordinates":[-97.69856,30.404299],"type":"Point"}
}