{
  "type": "Feature",
  "properties": {
    "iso:country":"US",
    "sg:address":"140 Co Rd 216",
    "sg:city":"Sweetwater",
    "sg:classifiers":[
        {
            "category":"Building & Trades",
            "subcategory":"Construction",
            "type":"Services"
        }
    ],
    "sg:phone":"+1 325 235 4863",
    "sg:postcode":"79556",
    "sg:province":"TX",
    "sg:tags":[
        "general",
        "nonresidential",
        "contractor"
    ],
    "wof:name":"Coe Construction Company",
    "wof:placetype":"venue"
},
  "geometry": {"coordinates":[-100.414055,32.442353],"type":"Point"}
}