{
  "type": "Feature",
  "properties": {
    "iso:country":"US",
    "sg:address":"8407 Bandera Rd",
    "sg:city":"San Antonio",
    "sg:classifiers":[
        {
            "category":"Shopping",
            "subcategory":"Stationery & Office Supplies",
            "type":"Retail Goods"
        }
    ],
    "sg:phone":"+1 210 572 2380",
    "sg:postcode":"78250",
    "sg:province":"TX",
    "sg:tags":[
        "album",
        "scrapbook"
    ],
    "sg:website":"www.scrapbook-heaven.com",
    "wof:name":"Scrapbook Heaven",
    "wof:placetype":"venue"
},
  "geometry": {"coordinates":[-98.638389,29.521983],"type":"Point"}
}