{
  "type": "Feature",
  "properties": {
    "iso:country":"US",
    "sg:address":"1811 Texas Ave S",
    "sg:city":"Bryan",
    "sg:classifiers":[
        {
            "category":"Retail",
            "subcategory":"Auto Rental",
            "type":"Services"
        }
    ],
    "sg:phone":"+1 979 823 2967",
    "sg:postcode":"77802",
    "sg:province":"TX",
    "sg:tags":[
        "renting",
        "passenger",
        "leasing",
        "car",
        "automobile"
    ],
    "wof:name":"Enterprise Rent-A-Car Company",
    "wof:placetype":"venue"
},
  "geometry": {"coordinates":[-96.36286800000001,30.652449],"type":"Point"}
}