{
  "type": "Feature",
  "properties": {
    "iso:country":"US",
    "sg:address":"2519 National Dr",
    "sg:city":"Garland",
    "sg:classifiers":[
        {
            "category":"Professional",
            "type":"Services"
        }
    ],
    "sg:phone":"+1 972 219 0000",
    "sg:postcode":"75041",
    "sg:province":"TX",
    "wof:name":"Florian Tudor",
    "wof:placetype":"venue"
},
  "geometry": {"coordinates":[-96.671558,32.885729],"type":"Point"}
}