{
  "type": "Feature",
  "properties": {
    "iso:country":"US",
    "sg:address":"4220 W William Cannon Ste 140",
    "sg:city":"Austin",
    "sg:classifiers":[
        {
            "category":"Personal",
            "subcategory":"Beauty Salon",
            "type":"Services"
        }
    ],
    "sg:phone":"+1 512 453 4140",
    "sg:postcode":"78749",
    "sg:province":"TX",
    "sg:tags":[
        "spa"
    ],
    "sg:website":"www.cobaltbluesalon.com",
    "wof:name":"Cobalt Blue Hair Salon",
    "wof:placetype":"venue"
},
  "geometry": {"coordinates":[-97.837744,30.222219],"type":"Point"}
}