{
  "type": "Feature",
  "properties": {
    "iso:country":"US",
    "sg:address":"1107 Littleport Ln",
    "sg:city":"Channelview",
    "sg:classifiers":[
        {
            "category":"Wholesale",
            "subcategory":"Stationery",
            "type":"Manufacturing & Wholesale Goods"
        }
    ],
    "sg:phone":"+1 281 458 5238",
    "sg:postcode":"77530",
    "sg:province":"TX",
    "sg:tags":[
        "business",
        "form",
        "system"
    ],
    "wof:name":"A Jones",
    "wof:placetype":"venue"
},
  "geometry": {"coordinates":[-95.15039899999999,29.796155],"type":"Point"}
}