{
  "type": "Feature",
  "properties": {
    "iso:country":"US",
    "sg:address":"200 Barnes Bridge Rd",
    "sg:city":"Mesquite",
    "sg:classifiers":[
        {
            "category":"Museum",
            "type":"Entertainment"
        }
    ],
    "sg:phone":"+1 972 226 6494",
    "sg:postcode":"75182",
    "sg:province":"TX",
    "sg:tags":[
        "gallery"
    ],
    "wof:name":"Mollage Studio",
    "wof:placetype":"venue"
},
  "geometry": {"coordinates":[-96.588371,32.82298],"type":"Point"}
}