{
  "type": "Feature",
  "properties": {
    "iso:country":"US",
    "sg:address":"6121 W Park Blvd",
    "sg:city":"Plano",
    "sg:classifiers":[
        {
            "category":"Shopping",
            "type":"Retail Goods"
        }
    ],
    "sg:phone":"+1 972 202 8350",
    "sg:postcode":"75093",
    "sg:province":"TX",
    "sg:tags":[
        "candle"
    ],
    "wof:name":"Yankee Candle Company Inc",
    "wof:placetype":"venue"
},
  "geometry": {"coordinates":[-96.831943,33.027758],"type":"Point"}
}