{
  "type": "Feature",
  "properties": {
    "iso:country":"US",
    "sg:address":"4411 Plains Blvd",
    "sg:city":"Amarillo",
    "sg:classifiers":[
        {
            "category":"Personal",
            "subcategory":"Beauty Salon",
            "type":"Services"
        }
    ],
    "sg:phone":"+1 806 467 2412",
    "sg:postcode":"79106",
    "sg:province":"TX",
    "wof:name":"Shaynah Scissorhands Salon",
    "wof:placetype":"venue"
},
  "geometry": {"coordinates":[-101.886279,35.198763],"type":"Point"}
}