{
  "type": "Feature",
  "properties": {
    "iso:country":"US",
    "sg:address":"224 W Commerce St",
    "sg:city":"Dallas",
    "sg:classifiers":[
        {
            "category":"Mining & Drilling",
            "type":"Manufacturing & Wholesale Goods"
        }
    ],
    "sg:phone":"+1 214 747 0262",
    "sg:postcode":"75208",
    "sg:province":"TX",
    "sg:tags":[
        "oil",
        "gas",
        "producer"
    ],
    "wof:name":"Freestone Resources Inc",
    "wof:placetype":"venue"
},
  "geometry": {"coordinates":[-96.82634299999999,32.774066],"type":"Point"}
}