{
  "type": "Feature",
  "properties": {
    "iso:country":"US",
    "sg:address":"7437 Canal St",
    "sg:city":"Houston",
    "sg:classifiers":[
        {
            "category":"Professional",
            "subcategory":"Business Services",
            "type":"Services"
        }
    ],
    "sg:phone":"+1 713 921 2167",
    "sg:postcode":"77011",
    "sg:province":"TX",
    "wof:name":"Garza L",
    "wof:placetype":"venue"
},
  "geometry": {"coordinates":[-95.29110300000001,29.736844],"type":"Point"}
}