{
  "type": "Feature",
  "properties": {
    "iso:country":"US",
    "sg:address":"12 Greenway Plz Ste 1400",
    "sg:city":"Houston",
    "sg:classifiers":[
        {
            "category":"Real Estate",
            "subcategory":"Real Estate Services",
            "type":"Services"
        }
    ],
    "sg:phone":"+1 713 965 2900",
    "sg:postcode":"77046",
    "sg:province":"TX",
    "sg:tags":[
        "management",
        "property"
    ],
    "sg:website":"www.senterra.com",
    "wof:name":"Senterra",
    "wof:placetype":"venue"
},
  "geometry": {"coordinates":[-95.440247,29.729622],"type":"Point"}
}