{
  "type": "Feature",
  "properties": {
    "iso:country":"US",
    "sg:address":"2021 E Southeast Loop 323",
    "sg:city":"Tyler",
    "sg:classifiers":[
        {
            "category":"Restaurant",
            "type":"Food & Drink"
        }
    ],
    "sg:menulink":"http://www.allmenus.com/tx/tyler/130541-subway/menu/",
    "sg:phone":"+1 903 509 9800",
    "sg:postcode":"75701",
    "sg:province":"TX",
    "sg:tags":[
        "american",
        "sandwich"
    ],
    "wof:name":"Subway",
    "wof:placetype":"venue"
},
  "geometry": {"coordinates":[-95.276211,32.309855],"type":"Point"}
}