{
  "type": "Feature",
  "properties": {
    "iso:country":"US",
    "sg:address":"2460 Douglas Dr",
    "sg:city":"San Angelo",
    "sg:classifiers":[
        {
            "category":"Arts & Performance",
            "subcategory":"Theater",
            "type":"Entertainment"
        }
    ],
    "sg:phone":"+1 325 942 9147",
    "sg:postcode":"76904",
    "sg:province":"TX",
    "sg:tags":[
        "group",
        "business"
    ],
    "wof:name":"Shirley L Boatright",
    "wof:placetype":"venue"
},
  "geometry": {"coordinates":[-100.46453099999999,31.438282],"type":"Point"}
}