{
  "type": "Feature",
  "properties": {
    "iso:country":"US",
    "sg:address":"1125 Brockdale Park",
    "sg:city":"Allen",
    "sg:classifiers":[
        {
            "category":"Wholesale",
            "subcategory":"Durable Goods & Equipment",
            "type":"Manufacturing & Wholesale Goods"
        }
    ],
    "sg:phone":"+1 972 429 3639",
    "sg:postcode":"75002",
    "sg:province":"TX",
    "sg:tags":[
        "representative",
        "manufacturer"
    ],
    "wof:name":"M P Marketing Inc",
    "wof:placetype":"venue"
},
  "geometry": {"coordinates":[-96.56077500000001,33.080671],"type":"Point"}
}