{
  "type": "Feature",
  "properties": {
    "iso:country":"US",
    "sg:address":"1300 NE 35th St",
    "sg:city":"Fort Worth",
    "sg:classifiers":[
        {
            "category":"Education",
            "subcategory":"Library",
            "type":"Public Place"
        }
    ],
    "sg:phone":"+1 817 624 7331",
    "sg:postcode":"76106",
    "sg:province":"TX",
    "wof:name":"Public Library",
    "wof:placetype":"venue"
},
  "geometry": {"coordinates":[-97.33728499999999,32.809415],"type":"Point"}
}