{
  "type": "Feature",
  "properties": {
    "iso:country":"US",
    "sg:address":"268 Becker Ln",
    "sg:city":"Seguin",
    "sg:classifiers":[
        {
            "category":"Organizations",
            "subcategory":"Community Association",
            "type":"Services"
        }
    ],
    "sg:phone":"+1 830 379 6907",
    "sg:postcode":"78155",
    "sg:province":"TX",
    "wof:name":"Lake Placid Estates Assn",
    "wof:placetype":"venue"
},
  "geometry": {"coordinates":[-98.012911,29.559695],"type":"Point"}
}