{
  "type": "Feature",
  "properties": {
    "iso:country":"US",
    "sg:address":"2165 Crockett Dr",
    "sg:city":"Denton",
    "sg:classifiers":[
        {
            "category":"Professional",
            "subcategory":"Business Services",
            "type":"Services"
        }
    ],
    "sg:phone":"+1 940 321 4401",
    "sg:postcode":"76210",
    "sg:province":"TX",
    "wof:name":"Lunar Industrial Products",
    "wof:placetype":"venue"
},
  "geometry": {"coordinates":[-97.076919,33.136901],"type":"Point"}
}