{
  "type": "Feature",
  "properties": {
    "iso:country":"US",
    "sg:address":"2417 Suffolk Ln",
    "sg:city":"Lancaster",
    "sg:classifiers":[
        {
            "category":"Professional",
            "type":"Services"
        }
    ],
    "sg:phone":"+1 972 218 7190",
    "sg:postcode":"75134",
    "sg:province":"TX",
    "wof:name":"Lylehouse Foundation",
    "wof:placetype":"venue"
},
  "geometry": {"coordinates":[-96.769133,32.614287],"type":"Point"}
}