{
  "type": "Feature",
  "properties": {
    "iso:country":"US",
    "sg:address":"1716 W Washington St",
    "sg:city":"Denison",
    "sg:classifiers":[
        {
            "category":"Building & Trades",
            "subcategory":"Electrical",
            "type":"Services"
        }
    ],
    "sg:phone":"+1 903 465 2001",
    "sg:postcode":"75020",
    "sg:province":"TX",
    "sg:tags":[
        "electrical",
        "contractor"
    ],
    "wof:name":"McManigell Electric Service",
    "wof:placetype":"venue"
},
  "geometry": {"coordinates":[-96.561425,33.765624],"type":"Point"}
}