{
  "type": "Feature",
  "properties": {
    "iso:country":"US",
    "sg:address":"1846 Fredericksburg Rd",
    "sg:city":"San Antonio",
    "sg:classifiers":[
        {
            "category":"Shopping",
            "subcategory":"Florist",
            "type":"Retail Goods"
        }
    ],
    "sg:phone":"+1 210 737 2998",
    "sg:postcode":"78201",
    "sg:province":"TX",
    "wof:name":"All 4 Seasons Florist",
    "wof:placetype":"venue"
},
  "geometry": {"coordinates":[-98.52379000000001,29.462393],"type":"Point"}
}