{
  "type": "Feature",
  "properties": {
    "iso:country":"US",
    "sg:address":"1302 E Texas Ave",
    "sg:city":"Mart",
    "sg:classifiers":[
        {
            "category":"Shopping",
            "type":"Retail Goods"
        }
    ],
    "sg:phone":"+1 254 876 3226",
    "sg:postcode":"76664",
    "sg:province":"TX",
    "sg:tags":[
        "merchandise"
    ],
    "wof:name":"Mart Trophy Co",
    "wof:placetype":"venue"
},
  "geometry": {"coordinates":[-96.823105,31.547604],"type":"Point"}
}