{
  "type": "Feature",
  "properties": {
    "iso:country":"US",
    "sg:address":"1022 Iowa St",
    "sg:city":"San Antonio",
    "sg:classifiers":[
        {
            "category":"Professional",
            "subcategory":"Business Services",
            "type":"Services"
        }
    ],
    "sg:phone":"+1 210 532 1940",
    "sg:postcode":"78203",
    "sg:province":"TX",
    "wof:name":"D C Services",
    "wof:placetype":"venue"
},
  "geometry": {"coordinates":[-98.465542,29.411929],"type":"Point"}
}