{
  "type": "Feature",
  "properties": {
    "iso:country":"US",
    "sg:address":"112 Medical Dr",
    "sg:city":"Palestine",
    "sg:classifiers":[
        {
            "category":"Health Services",
            "subcategory":"Doctor",
            "type":"Services"
        }
    ],
    "sg:phone":"+1 903 729 0444",
    "sg:postcode":"75801",
    "sg:province":"TX",
    "sg:tags":[
        "physician",
        "surgeon"
    ],
    "wof:name":"First Med Choice",
    "wof:placetype":"venue"
},
  "geometry": {"coordinates":[-95.62929099999999,31.731724],"type":"Point"}
}