{
  "type": "Feature",
  "properties": {
    "iso:country":"US",
    "sg:address":"3609 University Blvd",
    "sg:city":"Dallas",
    "sg:classifiers":[
        {
            "category":"Real Estate",
            "subcategory":"Real Estate Operator",
            "type":"Services"
        }
    ],
    "sg:phone":"+1 214 526 6955",
    "sg:postcode":"75205",
    "sg:province":"TX",
    "sg:tags":[
        "building",
        "nonresidential"
    ],
    "wof:name":"Kathryn Properties LLC",
    "wof:placetype":"venue"
},
  "geometry": {"coordinates":[-96.795349,32.844963],"type":"Point"}
}