{
  "type": "Feature",
  "properties": {
    "iso:country":"US",
    "sg:address":"1939 Haymarket Rd",
    "sg:city":"Dallas",
    "sg:classifiers":[
        {
            "category":"Real Estate",
            "subcategory":"Real Estate Agent",
            "type":"Services"
        }
    ],
    "sg:phone":"+1 972 286 5875",
    "sg:postcode":"75253",
    "sg:province":"TX",
    "wof:name":"Home Search Realty",
    "wof:placetype":"venue"
},
  "geometry": {"coordinates":[-96.641166,32.672135],"type":"Point"}
}