{
  "type": "Feature",
  "properties": {
    "iso:country":"US",
    "sg:address":"4755 Fieldwood Ln",
    "sg:city":"Beaumont",
    "sg:classifiers":[
        {
            "category":"Personal",
            "subcategory":"Beauty Salon",
            "type":"Services"
        }
    ],
    "sg:phone":"+1 409 899 4123",
    "sg:postcode":"77706",
    "sg:province":"TX",
    "sg:tags":[
        "shop"
    ],
    "wof:name":"Gift Gals",
    "wof:placetype":"venue"
},
  "geometry": {"coordinates":[-94.152427,30.098688],"type":"Point"}
}