{
  "type": "Feature",
  "properties": {
    "iso:country":"US",
    "sg:address":"207 S Peking St",
    "sg:city":"Mcallen",
    "sg:classifiers":[
        {
            "category":"Retail",
            "subcategory":"Auto Repair",
            "type":"Services"
        }
    ],
    "sg:phone":"+1 956 686 6742",
    "sg:postcode":"78501",
    "sg:province":"TX",
    "sg:tags":[
        "automotive"
    ],
    "wof:name":"Valley Radiator Service",
    "wof:placetype":"venue"
},
  "geometry": {"coordinates":[-98.21854500000001,26.199058],"type":"Point"}
}