{
  "type": "Feature",
  "properties": {
    "iso:country":"US",
    "sg:address":"5004 Chelsea Dr",
    "sg:city":"Colleyville",
    "sg:classifiers":[
        {
            "category":"Wholesale",
            "subcategory":"Groceries",
            "type":"Manufacturing & Wholesale Goods"
        }
    ],
    "sg:phone":"+1 817 355 0688",
    "sg:postcode":"76034",
    "sg:province":"TX",
    "sg:tags":[
        "salsa"
    ],
    "wof:name":"Hooks U Salsa",
    "wof:placetype":"venue"
},
  "geometry": {"coordinates":[-97.14097099999999,32.881871],"type":"Point"}
}