{
  "type": "Feature",
  "properties": {
    "iso:country":"US",
    "sg:address":"509 E Goliad Ave",
    "sg:city":"Crockett",
    "sg:classifiers":[
        {
            "category":"Restaurant",
            "type":"Food & Drink"
        }
    ],
    "sg:phone":"+1 936 544 7601",
    "sg:postcode":"75835",
    "sg:province":"TX",
    "sg:tags":[
        "eating"
    ],
    "wof:name":"Benton New Orlean Creole/Itial",
    "wof:placetype":"venue"
},
  "geometry": {"coordinates":[-95.456971,31.317612],"type":"Point"}
}