{
  "type": "Feature",
  "properties": {
    "iso:country":"US",
    "sg:address":"9904 Whitley Bay Dr",
    "sg:city":"Austin",
    "sg:classifiers":[
        {
            "category":"Communications",
            "subcategory":"Newspaper",
            "type":"Services"
        }
    ],
    "sg:phone":"+1 512 821 1900",
    "sg:postcode":"78717",
    "sg:province":"TX",
    "sg:website":"http://www.realtylineonline.com",
    "wof:name":"Realty Line of Austin",
    "wof:placetype":"venue"
},
  "geometry": {"coordinates":[-97.76000500000001,30.502246],"type":"Point"}
}