{
  "type": "Feature",
  "properties": {
    "iso:country":"US",
    "sg:address":"3207 Hunter Rd",
    "sg:city":"San Marcos",
    "sg:classifiers":[
        {
            "category":"Travel",
            "subcategory":"Hotels & Motels",
            "type":"Entertainment"
        }
    ],
    "sg:phone":"+1 512 392 4060",
    "sg:postcode":"78666",
    "sg:province":"TX",
    "sg:tags":[
        "operation"
    ],
    "wof:name":"Joyce Ables Texas House Bed &",
    "wof:placetype":"venue"
},
  "geometry": {"coordinates":[-97.98539599999999,29.840932],"type":"Point"}
}