{
  "type": "Feature",
  "properties": {
    "iso:country":"US",
    "sg:address":"109 Richland Dr",
    "sg:city":"Palestine",
    "sg:classifiers":[
        {
            "category":"Restaurant",
            "type":"Food & Drink"
        }
    ],
    "sg:phone":"+1 903 723 2500",
    "sg:postcode":"75801",
    "sg:province":"TX",
    "sg:tags":[
        "eating"
    ],
    "wof:name":"Chinatown Restaurant",
    "wof:placetype":"venue"
},
  "geometry": {"coordinates":[-95.590486,31.729848],"type":"Point"}
}