{
  "type": "Feature",
  "properties": {
    "iso:country":"US",
    "sg:address":"4409 Tobago St",
    "sg:city":"Wichita Falls",
    "sg:classifiers":[
        {
            "category":"Mining & Drilling",
            "type":"Manufacturing & Wholesale Goods"
        }
    ],
    "sg:phone":"+1 940 691 5787",
    "sg:postcode":"76308",
    "sg:province":"TX",
    "sg:tags":[
        "well"
    ],
    "wof:name":"Rick Clay",
    "wof:placetype":"venue"
},
  "geometry": {"coordinates":[-98.513987,33.864292],"type":"Point"}
}