{
  "type": "Feature",
  "properties": {
    "iso:country":"US",
    "sg:address":"8 Edgemere Dr",
    "sg:city":"Roanoke",
    "sg:classifiers":[
        {
            "category":"Professional",
            "subcategory":"Business Services",
            "type":"Services"
        }
    ],
    "sg:phone":"+1 682 831 0534",
    "sg:postcode":"76262",
    "sg:province":"TX",
    "wof:name":"Ingar Enterprises",
    "wof:placetype":"venue"
},
  "geometry": {"coordinates":[-97.167777,32.998463],"type":"Point"}
}