{
  "type": "Feature",
  "properties": {
    "iso:country":"US",
    "sg:address":"5910 N MacArthur Blvd",
    "sg:city":"Irving",
    "sg:classifiers":[
        {
            "category":"Restaurant",
            "type":"Food & Drink"
        }
    ],
    "sg:phone":"+1 972 402 0225",
    "sg:postcode":"75039",
    "sg:province":"TX",
    "sg:tags":[
        "barbeque"
    ],
    "wof:name":"Red-Hot & Blues Barbecue",
    "wof:placetype":"venue"
},
  "geometry": {"coordinates":[-96.960375,32.892809],"type":"Point"}
}