{
  "type": "Feature",
  "properties": {
    "iso:country":"US",
    "sg:address":"6201 Bellaire Blvd",
    "sg:city":"Houston",
    "sg:classifiers":[
        {
            "category":"Shopping",
            "subcategory":"Music",
            "type":"Retail Goods"
        }
    ],
    "sg:phone":"+1 713 981 0046",
    "sg:postcode":"77081",
    "sg:province":"TX",
    "sg:tags":[
        "dvd's"
    ],
    "wof:name":"Ritmo Latino",
    "wof:placetype":"venue"
},
  "geometry": {"coordinates":[-95.4897,29.7055],"type":"Point"}
}