{
  "type": "Feature",
  "properties": {
    "iso:country":"US",
    "sg:address":"13306 Roaring Springs Ln",
    "sg:city":"Dallas",
    "sg:classifiers":[
        {
            "category":"Shopping",
            "type":"Retail Goods"
        }
    ],
    "sg:phone":"+1 972 404 9570",
    "sg:postcode":"75240",
    "sg:province":"TX",
    "sg:tags":[
        "health",
        "merchandise"
    ],
    "wof:name":"Bodywork/Biofeedback",
    "wof:placetype":"venue"
},
  "geometry": {"coordinates":[-96.775435,32.929319],"type":"Point"}
}