{
  "type": "Feature",
  "properties": {
    "iso:country":"US",
    "sg:address":"4344 State Hwy 6",
    "sg:city":"Houston",
    "sg:classifiers":[
        {
            "category":"Personal",
            "subcategory":"Beauty Salon",
            "type":"Services"
        }
    ],
    "sg:phone":"+1 281 855 1425",
    "sg:postcode":"77084",
    "sg:province":"TX",
    "sg:tags":[
        "shop"
    ],
    "wof:name":"Magic Salon",
    "wof:placetype":"venue"
},
  "geometry": {"coordinates":[-95.645546,29.837409],"type":"Point"}
}