{
  "type": "Feature",
  "properties": {
    "iso:country":"US",
    "sg:address":"10231 Pony Express Rd",
    "sg:city":"Houston",
    "sg:classifiers":[
        {
            "category":"Building & Trades",
            "subcategory":"Plumbing",
            "type":"Services"
        }
    ],
    "sg:phone":"+1 281 894 4051",
    "sg:postcode":"77064",
    "sg:province":"TX",
    "sg:tags":[
        "contractor"
    ],
    "wof:name":"Plb Management Inc",
    "wof:placetype":"venue"
},
  "geometry": {"coordinates":[-95.57237000000001,29.921169],"type":"Point"}
}