{
  "type": "Feature",
  "properties": {
    "iso:country":"US",
    "sg:address":"1332 Marie Ln",
    "sg:city":"White Settlement",
    "sg:classifiers":[
        {
            "category":"Building & Trades",
            "subcategory":"Construction",
            "type":"Services"
        }
    ],
    "sg:phone":"+1 817 246 2010",
    "sg:postcode":"76108",
    "sg:province":"TX",
    "sg:tags":[
        "home",
        "builder"
    ],
    "wof:name":"Optima Homes Inc",
    "wof:placetype":"venue"
},
  "geometry": {"coordinates":[-97.474766,32.744371],"type":"Point"}
}