{
  "type": "Feature",
  "properties": {
    "iso:country":"US",
    "sg:address":"336 Lakewood Ct",
    "sg:city":"Coppell",
    "sg:classifiers":[
        {
            "category":"Manufacturing",
            "subcategory":"Chemicals & Compounds",
            "type":"Manufacturing & Wholesale Goods"
        }
    ],
    "sg:phone":"+1 469 464 0526",
    "sg:postcode":"75019",
    "sg:province":"TX",
    "sg:tags":[
        "product",
        "mfg"
    ],
    "wof:name":"CA Custom Coating",
    "wof:placetype":"venue"
},
  "geometry": {"coordinates":[-96.991927,32.962614],"type":"Point"}
}