{
  "type": "Feature",
  "properties": {
    "iso:country":"US",
    "sg:address":"11551 Forest Central Dr Ste 300",
    "sg:city":"Dallas",
    "sg:classifiers":[
        {
            "category":"Professional",
            "subcategory":"Lawyer & Legal Services",
            "type":"Services"
        }
    ],
    "sg:phone":"+1 214 373 3761",
    "sg:postcode":"75243",
    "sg:province":"TX",
    "sg:website":"www.morganweisbrod.com",
    "wof:name":"Morgan & Weisbrod",
    "wof:placetype":"venue"
},
  "geometry": {"coordinates":[-96.76750199999999,32.905614],"type":"Point"}
}