{
  "type": "Feature",
  "properties": {
    "iso:country":"US",
    "sg:address":"3501 Long Prairie Rd",
    "sg:city":"Flower Mound",
    "sg:classifiers":[
        {
            "category":"Real Estate",
            "subcategory":"Real Estate Services",
            "type":"Services"
        }
    ],
    "sg:phone":"+1 972 434 3100",
    "sg:postcode":"75022",
    "sg:province":"TX",
    "sg:tags":[
        "company",
        "title"
    ],
    "wof:name":"Sierra Title Of N Texas",
    "wof:placetype":"venue"
},
  "geometry": {"coordinates":[-97.07084500000001,33.032391],"type":"Point"}
}