{
  "type": "Feature",
  "properties": {
    "iso:country":"US",
    "sg:address":"1882 S Clack St",
    "sg:city":"Abilene",
    "sg:classifiers":[
        {
            "category":"Restaurant",
            "type":"Food & Drink"
        }
    ],
    "sg:phone":"+1 325 695 1770",
    "sg:postcode":"79605",
    "sg:province":"TX",
    "sg:tags":[
        "drinking",
        "eating"
    ],
    "wof:name":"Bedford Street Restaurant",
    "wof:placetype":"venue"
},
  "geometry": {"coordinates":[-99.787357,32.427258],"type":"Point"}
}