{
  "type": "Feature",
  "properties": {
    "iso:country":"US",
    "sg:address":"30751 High Meadow Dr",
    "sg:city":"Magnolia",
    "sg:classifiers":[
        {
            "category":"Real Estate",
            "subcategory":"Developer",
            "type":"Services"
        }
    ],
    "sg:phone":"+1 281 356 3048",
    "sg:postcode":"77354",
    "sg:province":"TX",
    "wof:name":"JJACOD & I",
    "wof:placetype":"venue"
},
  "geometry": {"coordinates":[-95.704323,30.191227],"type":"Point"}
}