{
  "type": "Feature",
  "properties": {
    "iso:country":"US",
    "sg:address":"2227 Central Blvd",
    "sg:city":"Brownsville",
    "sg:classifiers":[
        {
            "category":"Personal",
            "subcategory":"Tattoo Parlor",
            "type":"Services"
        }
    ],
    "sg:phone":"+1 956 986 0502",
    "sg:postcode":"78520",
    "sg:province":"TX",
    "sg:tags":[
        "tattooing"
    ],
    "wof:name":"Dark Side Of The Moon",
    "wof:placetype":"venue"
},
  "geometry": {"coordinates":[-97.51019100000001,25.937189],"type":"Point"}
}