{
  "type": "Feature",
  "properties": {
    "iso:country":"US",
    "sg:address":"8335 Westchester Dr",
    "sg:city":"Dallas",
    "sg:classifiers":[
        {
            "category":"Personal",
            "subcategory":"Beauty Salon",
            "type":"Services"
        }
    ],
    "sg:phone":"+1 214 361 8510",
    "sg:postcode":"75225",
    "sg:province":"TX",
    "wof:name":"Tony Fielding Studio",
    "wof:placetype":"venue"
},
  "geometry": {"coordinates":[-96.80663699999999,32.864436],"type":"Point"}
}