{
  "type": "Feature",
  "properties": {
    "iso:country":"US",
    "sg:address":"2428 FM 1387",
    "sg:city":"Midlothian",
    "sg:classifiers":[
        {
            "category":"Shopping",
            "type":"Retail Goods"
        }
    ],
    "sg:phone":"+1 972 775 1724",
    "sg:postcode":"76065",
    "sg:province":"TX",
    "sg:tags":[
        "pet",
        "shop"
    ],
    "wof:name":"Pets Of Perfection",
    "wof:placetype":"venue"
},
  "geometry": {"coordinates":[-96.962918,32.488853],"type":"Point"}
}