{
  "type": "Feature",
  "properties": {
    "iso:country":"US",
    "sg:address":"1003 S Van Buren Ave",
    "sg:city":"Mc Gregor",
    "sg:classifiers":[
        {
            "category":"Wholesale",
            "subcategory":"Non-durable Goods",
            "type":"Manufacturing & Wholesale Goods"
        }
    ],
    "sg:phone":"+1 254 840 4536",
    "sg:postcode":"76657",
    "sg:province":"TX",
    "wof:name":"Aguilla Creek Trading Co",
    "wof:placetype":"venue"
},
  "geometry": {"coordinates":[-97.407601,31.431022],"type":"Point"}
}