{
  "type": "Feature",
  "properties": {
    "iso:country":"US",
    "sg:address":"13518 Sable Ln",
    "sg:city":"Houston",
    "sg:classifiers":[
        {
            "category":"Social Services",
            "type":"Services"
        }
    ],
    "sg:phone":"+1 281 580 1836",
    "sg:postcode":"77014",
    "sg:province":"TX",
    "wof:name":"Christian Sitting Services",
    "wof:placetype":"venue"
},
  "geometry": {"coordinates":[-95.485742,29.973727],"type":"Point"}
}