{
  "type": "Feature",
  "properties": {
    "iso:country":"US",
    "sg:address":"8701 Bluegrass Dr",
    "sg:city":"Austin",
    "sg:classifiers":[
        {
            "category":"Wholesale",
            "subcategory":"Computers",
            "type":"Manufacturing & Wholesale Goods"
        }
    ],
    "sg:phone":"+1 512 418 8380",
    "sg:postcode":"78759",
    "sg:province":"TX",
    "sg:tags":[
        "high",
        "performance",
        "design",
        "software"
    ],
    "wof:name":"Dyver",
    "wof:placetype":"venue"
},
  "geometry": {"coordinates":[-97.76822,30.387868],"type":"Point"}
}