{
  "type": "Feature",
  "properties": {
    "iso:country":"US",
    "sg:address":"1022 Clover St",
    "sg:city":"Waco",
    "sg:classifiers":[
        {
            "category":"Building & Trades",
            "subcategory":"Equipment Rental",
            "type":"Services"
        }
    ],
    "sg:phone":"+1 254 799 2887",
    "sg:postcode":"76705",
    "sg:province":"TX",
    "sg:tags":[
        "yard",
        "leasing",
        "store"
    ],
    "wof:name":"Sharp Rentals",
    "wof:placetype":"venue"
},
  "geometry": {"coordinates":[-97.090147,31.600687],"type":"Point"}
}