{
  "type": "Feature",
  "properties": {
    "iso:country":"US",
    "sg:address":"5211 50th St",
    "sg:city":"Lubbock",
    "sg:classifiers":[
        {
            "category":"Retail",
            "subcategory":"Car Wash",
            "type":"Services"
        }
    ],
    "sg:phone":"+1 806 784 0191",
    "sg:postcode":"79414",
    "sg:province":"TX",
    "sg:tags":[
        "polishing",
        "washing"
    ],
    "wof:name":"Parkway Car Wash",
    "wof:placetype":"venue"
},
  "geometry": {"coordinates":[-101.926473,33.548667],"type":"Point"}
}