{
  "type": "Feature",
  "properties": {
    "iso:country":"US",
    "sg:address":"3358 Lakeview Pkwy",
    "sg:city":"Rowlett",
    "sg:classifiers":[
        {
            "category":"Retail",
            "subcategory":"Laundry & Dry Cleaning",
            "type":"Services"
        }
    ],
    "sg:phone":"+1 972 607 1353",
    "sg:postcode":"75088",
    "sg:province":"TX",
    "wof:name":"We Can Too Cleaners & Tuxedo Rentals",
    "wof:placetype":"venue"
},
  "geometry": {"coordinates":[-96.571701,32.907501],"type":"Point"}
}