{
  "type": "Feature",
  "properties": {
    "iso:country":"US",
    "sg:address":"1210 Yale St",
    "sg:city":"Fort Worth",
    "sg:classifiers":[
        {
            "category":"Personal",
            "subcategory":"Beauty Salon",
            "type":"Services"
        }
    ],
    "sg:phone":"+1 817 626 7133",
    "sg:postcode":"76114",
    "sg:province":"TX",
    "sg:tags":[
        "shop",
        "mill"
    ],
    "wof:name":"Kellis Kut Outs",
    "wof:placetype":"venue"
},
  "geometry": {"coordinates":[-97.402208,32.780636],"type":"Point"}
}