{
  "type": "Feature",
  "properties": {
    "iso:country":"US",
    "sg:address":"9513 Bayou Brook St",
    "sg:city":"Houston",
    "sg:classifiers":[
        {
            "category":"Health Services",
            "subcategory":"Doctor",
            "type":"Services"
        }
    ],
    "sg:phone":"+1 713 782 5255",
    "sg:postcode":"77063",
    "sg:province":"TX",
    "sg:tags":[
        "medical"
    ],
    "wof:name":"MD Bailey Foundation",
    "wof:placetype":"venue"
},
  "geometry": {"coordinates":[-95.534131,29.748163],"type":"Point"}
}