{
  "type": "Feature",
  "properties": {
    "iso:country":"US",
    "sg:address":"100 W Pioneer Pkwy",
    "sg:city":"Arlington",
    "sg:classifiers":[
        {
            "category":"Health Services",
            "subcategory":"Doctor",
            "type":"Services"
        },
        {
            "category":"Health Services",
            "subcategory":"Nursing And Care Facility",
            "type":"Services"
        },
        {
            "category":"Health Services",
            "subcategory":"Health Practitioner",
            "type":"Services"
        }
    ],
    "sg:phone":"+1 817 860 6888",
    "sg:postcode":"76010",
    "sg:province":"TX",
    "sg:tags":[
        "control",
        "management",
        "pain",
        "weight",
        "allergy",
        "medicine",
        "treatment",
        "acupuncture",
        "injury",
        "sport"
    ],
    "sg:website":"http://www.dallasacupuncturist.com",
    "wof:name":"Dallas Acupuncture & Nasal Treatment Center",
    "wof:placetype":"venue"
},
  "geometry": {"coordinates":[-97.10762800000001,32.708038],"type":"Point"}
}