{
  "type": "Feature",
  "properties": {
    "iso:country":"US",
    "sg:address":"10411 North Fwy",
    "sg:city":"Houston",
    "sg:classifiers":[
        {
            "category":"Banks & Credit Unions",
            "subcategory":"Bank",
            "type":"Services"
        }
    ],
    "sg:phone":"+1 281 999 3221",
    "sg:postcode":"77037",
    "sg:province":"TX",
    "sg:website":"www.1stcb.com",
    "wof:name":"First Convenience Bank",
    "wof:placetype":"venue"
},
  "geometry": {"coordinates":[-95.413101,29.917601],"type":"Point"}
}