{
  "type": "Feature",
  "properties": {
    "iso:country":"US",
    "sg:address":"9215 Denbridge Dr",
    "sg:city":"Houston",
    "sg:classifiers":[
        {
            "category":"Professional",
            "subcategory":"Management & Consulting",
            "type":"Services"
        }
    ],
    "sg:phone":"+1 281 568 9155",
    "sg:postcode":"77083",
    "sg:province":"TX",
    "sg:tags":[
        "business"
    ],
    "wof:name":"Ems Environmental MGT Systems",
    "wof:placetype":"venue"
},
  "geometry": {"coordinates":[-95.635103,29.678562],"type":"Point"}
}