{
  "type": "Feature",
  "properties": {
    "iso:country":"US",
    "sg:address":"333 Quentin Dr",
    "sg:city":"San Antonio",
    "sg:classifiers":[
        {
            "category":"Professional",
            "subcategory":"Business Services",
            "type":"Services"
        }
    ],
    "sg:phone":"+1 210 736 1051",
    "sg:postcode":"78201",
    "sg:province":"TX",
    "sg:tags":[
        "translator"
    ],
    "wof:name":"Lydia M Muniz",
    "wof:placetype":"venue"
},
  "geometry": {"coordinates":[-98.53694,29.46886],"type":"Point"}
}