{
  "type": "Feature",
  "properties": {
    "iso:country":"US",
    "sg:address":"6917 Doniphan Dr",
    "sg:city":"Canutillo",
    "sg:classifiers":[
        {
            "category":"Utilities",
            "subcategory":"Mobile Phone",
            "type":"Services"
        }
    ],
    "sg:phone":"+1 915 877 1951",
    "sg:postcode":"79835",
    "sg:province":"TX",
    "sg:tags":[
        "communication",
        "radiotelephone"
    ],
    "wof:name":"Lone Star Wireless Canutillo",
    "wof:placetype":"venue"
},
  "geometry": {"coordinates":[-106.60060799999999,31.91298],"type":"Point"}
}