{
  "type": "Feature",
  "properties": {
    "iso:country":"US",
    "sg:address":"7115 Bremerton Ct",
    "sg:city":"Dallas",
    "sg:classifiers":[
        {
            "category":"Mining & Drilling",
            "type":"Manufacturing & Wholesale Goods"
        }
    ],
    "sg:phone":"+1 972 713 6499",
    "sg:postcode":"75252",
    "sg:province":"TX",
    "sg:tags":[
        "oil",
        "gas",
        "producer"
    ],
    "wof:name":"Winkler Acquisition",
    "wof:placetype":"venue"
},
  "geometry": {"coordinates":[-96.78017800000001,32.995545],"type":"Point"}
}