{
  "type": "Feature",
  "properties": {
    "iso:country":"US",
    "sg:address":"8700 Yacht Club Rd",
    "sg:city":"Groves",
    "sg:classifiers":[
        {
            "category":"Manufacturing",
            "subcategory":"Watercraft",
            "type":"Manufacturing & Wholesale Goods"
        }
    ],
    "sg:phone":"+1 409 962 6322",
    "sg:postcode":"77643",
    "sg:province":"TX",
    "wof:name":"Neches Dry Dock",
    "wof:placetype":"venue"
},
  "geometry": {"coordinates":[-93.86016600000001,29.970086],"type":"Point"}
}