{
  "type": "Feature",
  "properties": {
    "iso:country":"US",
    "sg:address":"1312 N New Rd",
    "sg:city":"Waco",
    "sg:classifiers":[
        {
            "category":"Autos & Motor Vehicles",
            "subcategory":"Automobile Sales",
            "type":"Retail Goods"
        },
        {
            "category":"Banks & Credit Unions",
            "subcategory":"Bank",
            "type":"Services"
        }
    ],
    "sg:phone":"+1 254 399 0281",
    "sg:postcode":"76710",
    "sg:province":"TX",
    "sg:tags":[
        "car",
        "financing",
        "dealer"
    ],
    "wof:name":"Consumer Auto Finance Sales",
    "wof:placetype":"venue"
},
  "geometry": {"coordinates":[-97.179143,31.538296],"type":"Point"}
}