{
  "type": "Feature",
  "properties": {
    "iso:country":"US",
    "sg:address":"5803 Wanakah Dr",
    "sg:city":"Houston",
    "sg:classifiers":[
        {
            "category":"Professional",
            "type":"Services"
        }
    ],
    "sg:phone":"+1 281 580 1513",
    "sg:postcode":"77069",
    "sg:province":"TX",
    "wof:name":"Terry Fator Inc",
    "wof:placetype":"venue"
},
  "geometry": {"coordinates":[-95.52045099999999,29.98359],"type":"Point"}
}