{
  "type": "Feature",
  "properties": {
    "iso:country":"US",
    "sg:address":"10014 Gilson Ln",
    "sg:city":"Houston",
    "sg:classifiers":[
        {
            "category":"Building & Trades",
            "subcategory":"Plumbing",
            "type":"Services"
        }
    ],
    "sg:phone":"+1 281 440 8077",
    "sg:postcode":"77086",
    "sg:province":"TX",
    "sg:tags":[
        "systems-repairing",
        "system",
        "contractor",
        "equipment",
        "heating",
        "air conditioning"
    ],
    "sg:website":"http://www.airchampion.com",
    "wof:name":"Airchampion Air Conditioning Inc",
    "wof:placetype":"venue"
},
  "geometry": {"coordinates":[-95.513211,29.925664],"type":"Point"}
}