{
  "type": "Feature",
  "properties": {
    "iso:country":"US",
    "sg:address":"1533 Westheimer Rd",
    "sg:city":"Houston",
    "sg:classifiers":[
        {
            "category":"Manufacturing",
            "subcategory":"Printing",
            "type":"Manufacturing & Wholesale Goods"
        }
    ],
    "sg:phone":"+1 713 874 1044",
    "sg:postcode":"77006",
    "sg:province":"TX",
    "sg:tags":[
        "periodical"
    ],
    "wof:name":"Free Press Houston",
    "wof:placetype":"venue"
},
  "geometry": {"coordinates":[-95.398174,29.742796],"type":"Point"}
}