{
  "type": "Feature",
  "properties": {
    "iso:country":"US",
    "sg:address":"34185 Co Rd 106",
    "sg:city":"Rio Hondo",
    "sg:classifiers":[
        {
            "category":"Restaurant",
            "type":"Food & Drink"
        }
    ],
    "sg:phone":"+1 956 748 3411",
    "sg:postcode":"78583",
    "sg:province":"TX",
    "sg:tags":[
        "eating",
        "grocery",
        "station",
        "gasoline"
    ],
    "wof:name":"Economy Drive Inn",
    "wof:placetype":"venue"
},
  "geometry": {"coordinates":[-97.472402,26.218439],"type":"Point"}
}