{
  "type": "Feature",
  "properties": {
    "iso:country":"US",
    "sg:address":"1183 Bezner Ln",
    "sg:city":"Texline",
    "sg:classifiers":[
        {
            "category":"Food & Beverages",
            "subcategory":"Meat & Fish",
            "type":"Retail Goods"
        }
    ],
    "sg:phone":"+1 806 377 6323",
    "sg:postcode":"79087",
    "sg:province":"TX",
    "wof:name":"Bexner Beef Mill",
    "wof:placetype":"venue"
},
  "geometry": {"coordinates":[-102.852833,36.242385],"type":"Point"}
}