{
  "type": "Feature",
  "properties": {
    "iso:country":"US",
    "sg:address":"4012 W 7th St",
    "sg:city":"Fort Worth",
    "sg:classifiers":[
        {
            "category":"Professional",
            "subcategory":"Accounting & Tax Preparation",
            "type":"Services"
        }
    ],
    "sg:phone":"+1 817 763 5656",
    "sg:postcode":"76107",
    "sg:province":"TX",
    "sg:tags":[
        "accountant"
    ],
    "wof:name":"Michael W Hewatt",
    "wof:placetype":"venue"
},
  "geometry": {"coordinates":[-97.37809300000001,32.751569],"type":"Point"}
}