{
  "type": "Feature",
  "properties": {
    "iso:country":"US",
    "sg:address":"1020 Chatwood Dr",
    "sg:city":"Beaumont",
    "sg:classifiers":[
        {
            "category":"Education",
            "subcategory":"Special Training",
            "type":"Public Place"
        }
    ],
    "sg:phone":"+1 409 866 9544",
    "sg:postcode":"77706",
    "sg:province":"TX",
    "wof:name":"Kathy Harris Piano Studio",
    "wof:placetype":"venue"
},
  "geometry": {"coordinates":[-94.17752900000001,30.087441],"type":"Point"}
}