{
  "type": "Feature",
  "properties": {
    "iso:country":"US",
    "sg:address":"1660 S Stemmons Fwy",
    "sg:city":"Lewisville",
    "sg:classifiers":[
        {
            "category":"Insurance",
            "subcategory":"Insurance Agent",
            "type":"Services"
        }
    ],
    "sg:phone":"+1 972 436 9576",
    "sg:postcode":"75067",
    "sg:province":"TX",
    "sg:tags":[
        "life"
    ],
    "wof:name":"Crawford Financial Group",
    "wof:placetype":"venue"
},
  "geometry": {"coordinates":[-96.98839,33.026259],"type":"Point"}
}