{
  "type": "Feature",
  "properties": {
    "iso:country":"US",
    "sg:address":"4940 Grapeland Dr",
    "sg:city":"El Paso",
    "sg:classifiers":[
        {
            "category":"Wholesale",
            "subcategory":"Office Equipment",
            "type":"Manufacturing & Wholesale Goods"
        }
    ],
    "sg:phone":"+1 915 821 0997",
    "sg:postcode":"79924",
    "sg:province":"TX",
    "wof:name":"Business Essentials",
    "wof:placetype":"venue"
},
  "geometry": {"coordinates":[-106.430257,31.924352],"type":"Point"}
}