{
  "type": "Feature",
  "properties": {
    "iso:country":"US",
    "sg:address":"2700 Airport Fwy",
    "sg:city":"Fort Worth",
    "sg:classifiers":[
        {
            "category":"Professional",
            "subcategory":"Lawyer & Legal Services",
            "type":"Services"
        }
    ],
    "sg:phone":"+1 817 332 2030",
    "sg:postcode":"76111",
    "sg:province":"TX",
    "sg:tags":[
        "attorney"
    ],
    "wof:name":"Daniel R Barrett Law Offices",
    "wof:placetype":"venue"
},
  "geometry": {"coordinates":[-97.306969,32.767052],"type":"Point"}
}