{
  "type": "Feature",
  "properties": {
    "iso:country":"US",
    "sg:address":"10901 Co Rd 305",
    "sg:city":"Terrell",
    "sg:classifiers":[
        {
            "category":"Home & Garden",
            "subcategory":"Building Materials",
            "type":"Retail Goods"
        }
    ],
    "sg:phone":"+1 972 551 3903",
    "sg:postcode":"75160",
    "sg:province":"TX",
    "sg:tags":[
        "mixed",
        "concrete"
    ],
    "wof:name":"Txi",
    "wof:placetype":"venue"
},
  "geometry": {"coordinates":[-96.326615,32.711979],"type":"Point"}
}