{
  "type": "Feature",
  "properties": {
    "iso:country":"US",
    "sg:address":"810 Caldwell St",
    "sg:city":"Manor",
    "sg:classifiers":[
        {
            "category":"Manufacturing",
            "subcategory":"Printing",
            "type":"Manufacturing & Wholesale Goods"
        }
    ],
    "sg:phone":"+1 512 272 5330",
    "sg:postcode":"78653",
    "sg:province":"TX",
    "sg:tags":[
        "print",
        "newspaper",
        "medium"
    ],
    "wof:name":"Manor Messenger",
    "wof:placetype":"venue"
},
  "geometry": {"coordinates":[-97.556918,30.347548],"type":"Point"}
}