{
  "type": "Feature",
  "properties": {
    "iso:country":"US",
    "sg:address":"3115 College Park Dr",
    "sg:city":"Conroe",
    "sg:classifiers":[
        {
            "category":"Health Services",
            "subcategory":"Doctor",
            "type":"Services"
        },
        {
            "category":"Health Services",
            "subcategory":"Clinic",
            "type":"Services"
        },
        {
            "category":"Health Services",
            "subcategory":"Health Practitioner",
            "type":"Services"
        },
        {
            "category":"Community Center",
            "type":"Public Place"
        },
        {
            "category":"Health Services",
            "subcategory":"Chiropractor",
            "type":"Services"
        }
    ],
    "sg:phone":"+1 936 271 2555",
    "sg:postcode":"77384",
    "sg:province":"TX",
    "sg:tags":[
        "physician",
        "chiropractic",
        "medical",
        "therapist",
        "therapy",
        "surgeon",
        "physical"
    ],
    "wof:name":"Eric Lebouef Dc",
    "wof:placetype":"venue"
},
  "geometry": {"coordinates":[-95.464254,30.206989],"type":"Point"}
}