{
  "type": "Feature",
  "properties": {
    "iso:country":"US",
    "sg:address":"4216 Marys Creek Dr",
    "sg:city":"Fort Worth",
    "sg:classifiers":[
        {
            "category":"Banks & Credit Unions",
            "subcategory":"Financial Services",
            "type":"Services"
        }
    ],
    "sg:phone":"+1 817 560 7425",
    "sg:postcode":"76116",
    "sg:province":"TX",
    "sg:tags":[
        "trust",
        "investment",
        "real estate"
    ],
    "wof:name":"LLC Blue Wolf",
    "wof:placetype":"venue"
},
  "geometry": {"coordinates":[-97.467392,32.709809],"type":"Point"}
}