{
  "type": "Feature",
  "properties": {
    "iso:country":"US",
    "sg:address":"308 Greene Rd",
    "sg:city":"Lancaster",
    "sg:classifiers":[
        {
            "category":"Parking",
            "subcategory":"Garage",
            "type":"Transportation"
        },
        {
            "category":"Building & Trades",
            "subcategory":"Construction",
            "type":"Services"
        }
    ],
    "sg:phone":"+1 972 617 7717",
    "sg:postcode":"75146",
    "sg:province":"TX",
    "sg:tags":[
        "asphalt",
        "excavation",
        "contractor",
        "paving",
        "garages-construction",
        "sealcoating"
    ],
    "sg:website":"http://www.kayasphaltpaving.com",
    "wof:name":"Kay Asphalt & Concrete Inc",
    "wof:placetype":"venue"
},
  "geometry": {"coordinates":[-96.69579299999999,32.595534],"type":"Point"}
}