{
  "type": "Feature",
  "properties": {
    "iso:country":"US",
    "sg:address":"1517 Montana Ave",
    "sg:city":"El Paso",
    "sg:classifiers":[
        {
            "category":"Professional",
            "subcategory":"Accounting & Tax Preparation",
            "type":"Services"
        }
    ],
    "sg:phone":"+1 915 532 1257",
    "sg:postcode":"79902",
    "sg:province":"TX",
    "sg:tags":[
        "medical",
        "billing"
    ],
    "wof:name":"El Paso Medical Billing Tllc",
    "wof:placetype":"venue"
},
  "geometry": {"coordinates":[-106.477813,31.772869],"type":"Point"}
}