{
  "type": "Feature",
  "properties": {
    "iso:country":"US",
    "sg:address":"1711 Chenault St",
    "sg:city":"Dallas",
    "sg:classifiers":[
        {
            "category":"Manufacturing",
            "subcategory":"Tools & Machinery",
            "type":"Manufacturing & Wholesale Goods"
        }
    ],
    "sg:phone":"+1 214 324 0461",
    "sg:postcode":"75228",
    "sg:province":"TX",
    "sg:tags":[
        "mfg",
        "equipment",
        "industrial",
        "mach"
    ],
    "wof:name":"Danhard Inc",
    "wof:placetype":"venue"
},
  "geometry": {"coordinates":[-96.685186,32.802751],"type":"Point"}
}