{
  "type": "Feature",
  "properties": {
    "iso:country":"US",
    "sg:address":"5313 50th St",
    "sg:city":"Lubbock",
    "sg:classifiers":[
        {
            "category":"Wholesale",
            "subcategory":"Medical Equipment & Supplies",
            "type":"Manufacturing & Wholesale Goods"
        }
    ],
    "sg:phone":"+1 806 281 9181",
    "sg:postcode":"79414",
    "sg:province":"TX",
    "sg:tags":[
        "physician",
        "surgeon"
    ],
    "wof:name":"Alexander Vann Home Med Sups",
    "wof:placetype":"venue"
},
  "geometry": {"coordinates":[-101.924648,33.548653],"type":"Point"}
}