{
  "type": "Feature",
  "properties": {
    "iso:country":"US",
    "sg:address":"2919 Quenby Ave",
    "sg:city":"West University Place",
    "sg:classifiers":[
        {
            "category":"Health Services",
            "subcategory":"Doctor",
            "type":"Services"
        }
    ],
    "sg:phone":"+1 713 663 7099",
    "sg:postcode":"77005",
    "sg:province":"TX",
    "wof:name":"Giralt Sergio A MD",
    "wof:placetype":"venue"
},
  "geometry": {"coordinates":[-95.42421299999999,29.721445],"type":"Point"}
}