{
  "type": "Feature",
  "properties": {
    "iso:country":"US",
    "sg:address":"919 E Koenig Ln I-35 at Exit 238A",
    "sg:city":"Austin",
    "sg:classifiers":[
        {
            "category":"Travel",
            "subcategory":"Hotels & Motels",
            "type":"Entertainment"
        }
    ],
    "sg:phone":"+1 512 454 1144",
    "sg:postcode":"78751",
    "sg:province":"TX",
    "sg:website":"www.ramada.com/Ramada/control/Bo...",
    "wof:name":"Ramada - Austin Central",
    "wof:placetype":"venue"
},
  "geometry": {"coordinates":[-97.710027,30.32072],"type":"Point"}
}