{
  "type": "Feature",
  "properties": {
    "iso:country":"US",
    "sg:address":"16022 Rainbow Lake Rd",
    "sg:city":"Houston",
    "sg:classifiers":[
        {
            "category":"Shopping",
            "subcategory":"Jewelry",
            "type":"Retail Goods"
        }
    ],
    "sg:phone":"+1 281 463 4311",
    "sg:postcode":"77095",
    "sg:province":"TX",
    "wof:name":"Alone Star Jewelry",
    "wof:placetype":"venue"
},
  "geometry": {"coordinates":[-95.650509,29.891677],"type":"Point"}
}