{
  "type": "Feature",
  "properties": {
    "iso:country":"US",
    "sg:address":"296 Pleascocke Rd",
    "sg:city":"Longview",
    "sg:classifiers":[
        {
            "category":"Professional",
            "type":"Services"
        }
    ],
    "sg:phone":"+1 903 643 7017",
    "sg:postcode":"75603",
    "sg:province":"TX",
    "sg:tags":[
        "establishment"
    ],
    "wof:name":"Bobbie Nell's Spot",
    "wof:placetype":"venue"
},
  "geometry": {"coordinates":[-94.693529,32.384392],"type":"Point"}
}