{
  "type": "Feature",
  "properties": {
    "iso:country":"US",
    "sg:address":"1250 Bay Area Blvd",
    "sg:city":"Houston",
    "sg:classifiers":[
        {
            "category":"Shopping",
            "subcategory":"Clothing, Apparel, & Fashions",
            "type":"Retail Goods"
        },
        {
            "category":"Professional",
            "subcategory":"Art Services",
            "type":"Services"
        }
    ],
    "sg:phone":"+1 281 282 9144",
    "sg:postcode":"77058",
    "sg:province":"TX",
    "sg:tags":[
        "designer",
        "display",
        "producer"
    ],
    "wof:name":"Mep Green Designs P",
    "wof:placetype":"venue"
},
  "geometry": {"coordinates":[-95.11653099999999,29.559],"type":"Point"}
}