{
  "type": "Feature",
  "properties": {
    "iso:country":"US",
    "sg:address":"1231 Ridge Rock Ln",
    "sg:city":"Duncanville",
    "sg:classifiers":[
        {
            "category":"Professional",
            "subcategory":"Management & Consulting",
            "type":"Services"
        }
    ],
    "sg:phone":"+1 972 296 2285",
    "sg:postcode":"75116",
    "sg:province":"TX",
    "sg:tags":[
        "consultant",
        "business"
    ],
    "wof:name":"Choate Management Co",
    "wof:placetype":"venue"
},
  "geometry": {"coordinates":[-96.91971599999999,32.669939],"type":"Point"}
}