{
  "type": "Feature",
  "properties": {
    "iso:country":"US",
    "sg:address":"4100 Brick Plant Rd",
    "sg:city":"Snyder",
    "sg:classifiers":[
        {
            "category":"Real Estate",
            "subcategory":"Real Estate Operator",
            "type":"Services"
        }
    ],
    "sg:phone":"+1 325 573 9605",
    "sg:postcode":"79549",
    "sg:province":"TX",
    "sg:tags":[
        "building",
        "apartment"
    ],
    "wof:name":"Lawposada Apartments",
    "wof:placetype":"venue"
},
  "geometry": {"coordinates":[-100.884749,32.700998],"type":"Point"}
}