{
  "type": "Feature",
  "properties": {
    "iso:country":"US",
    "sg:address":"3837 Arundel Ave",
    "sg:city":"Fort Worth",
    "sg:classifiers":[
        {
            "category":"Wholesale",
            "subcategory":"Sporting Goods",
            "type":"Manufacturing & Wholesale Goods"
        }
    ],
    "sg:phone":"+1 817 921 6868",
    "sg:postcode":"76109",
    "sg:province":"TX",
    "wof:name":"Chris Watson & Associates",
    "wof:placetype":"venue"
},
  "geometry": {"coordinates":[-97.37759200000001,32.69302],"type":"Point"}
}