{
  "type": "Feature",
  "properties": {
    "iso:country":"US",
    "sg:address":"3303 Oak Aly",
    "sg:city":"Austin",
    "sg:classifiers":[
        {
            "category":"Building & Trades",
            "subcategory":"Construction",
            "type":"Services"
        }
    ],
    "sg:phone":"+1 512 282 5347",
    "sg:postcode":"78745",
    "sg:province":"TX",
    "sg:tags":[
        "painter"
    ],
    "wof:name":"Able Home Renovations",
    "wof:placetype":"venue"
},
  "geometry": {"coordinates":[-97.833028,30.197988],"type":"Point"}
}