{
  "type": "Feature",
  "properties": {
    "iso:country":"US",
    "sg:address":"9000 W Bellfort St",
    "sg:city":"Houston",
    "sg:classifiers":[
        {
            "category":"Personal",
            "subcategory":"Beauty Salon",
            "type":"Services"
        }
    ],
    "sg:phone":"+1 713 772 2408",
    "sg:postcode":"77031",
    "sg:province":"TX",
    "sg:tags":[
        "shop",
        "school"
    ],
    "wof:name":"Jones Cosmetology College",
    "wof:placetype":"venue"
},
  "geometry": {"coordinates":[-95.534814,29.656391],"type":"Point"}
}