{
  "type": "Feature",
  "properties": {
    "iso:country":"US",
    "sg:address":"12721 Lyndon B Johnson Frwy",
    "sg:city":"Garland",
    "sg:classifiers":[
        {
            "category":"Travel",
            "subcategory":"Hotels & Motels",
            "type":"Entertainment"
        }
    ],
    "sg:phone":"+1 972 271 7581",
    "sg:postcode":"75041",
    "sg:province":"TX",
    "sg:website":"www.lq.com",
    "wof:name":"La Quinta",
    "wof:placetype":"venue"
},
  "geometry": {"coordinates":[-96.660977,32.865651],"type":"Point"}
}