{
  "type": "Feature",
  "properties": {
    "iso:country":"US",
    "sg:address":"121 NW Newton Dr",
    "sg:city":"Burleson",
    "sg:classifiers":[
        {
            "category":"Real Estate",
            "subcategory":"Real Estate Services",
            "type":"Services"
        }
    ],
    "sg:phone":"+1 817 447 2191",
    "sg:postcode":"76028",
    "sg:province":"TX",
    "sg:tags":[
        "company",
        "abstract",
        "title"
    ],
    "wof:name":"Middlebrook Title Company Inc",
    "wof:placetype":"venue"
},
  "geometry": {"coordinates":[-97.330551,32.541491],"type":"Point"}
}