{
  "type": "Feature",
  "properties": {
    "iso:country":"US",
    "sg:address":"8600 N Macarthur Blvd",
    "sg:city":"Irving",
    "sg:classifiers":[
        {
            "category":"Real Estate",
            "subcategory":"Real Estate Agent",
            "type":"Services"
        }
    ],
    "sg:phone":"+1 972 432 9595",
    "sg:postcode":"75063",
    "sg:province":"TX",
    "wof:name":"Corr Properties",
    "wof:placetype":"venue"
},
  "geometry": {"coordinates":[-96.9552,32.92373],"type":"Point"}
}