{
  "type": "Feature",
  "properties": {
    "iso:country":"US",
    "sg:address":"815 S Bridgefarmer Rd",
    "sg:city":"Mc Kinney",
    "sg:classifiers":[
        {
            "category":"Professional",
            "subcategory":"Management & Consulting",
            "type":"Services"
        }
    ],
    "sg:phone":"+1 972 529 2419",
    "sg:postcode":"75069",
    "sg:province":"TX",
    "sg:tags":[
        "consultant",
        "educational"
    ],
    "wof:name":"Multimedia Learning Systems",
    "wof:placetype":"venue"
},
  "geometry": {"coordinates":[-96.54629300000001,33.176954],"type":"Point"}
}