{
  "type": "Feature",
  "properties": {
    "iso:country":"US",
    "sg:address":"14519 Oakmont Dr",
    "sg:city":"Dallas",
    "sg:classifiers":[
        {
            "category":"Retail",
            "subcategory":"Auto Rental",
            "type":"Services"
        }
    ],
    "sg:phone":"+1 972 247 2222",
    "sg:postcode":"75234",
    "sg:province":"TX",
    "sg:tags":[
        "renting",
        "leasing",
        "trailer"
    ],
    "wof:name":"Ajb Corp.",
    "wof:placetype":"venue"
},
  "geometry": {"coordinates":[-96.856481,32.943666],"type":"Point"}
}