{
  "type": "Feature",
  "properties": {
    "iso:country":"US",
    "sg:address":"602 Walton Dr",
    "sg:city":"Texarkana",
    "sg:classifiers":[
        {
            "category":"Building & Trades",
            "subcategory":"Equipment Rental",
            "type":"Services"
        }
    ],
    "sg:phone":"+1 903 838 1780",
    "sg:postcode":"75501",
    "sg:province":"TX",
    "sg:tags":[
        "yard",
        "leasing",
        "store"
    ],
    "sg:website":"http://www.rentacenter.com",
    "wof:name":"Rent-A-Center",
    "wof:placetype":"venue"
},
  "geometry": {"coordinates":[-94.09826700000001,33.448343],"type":"Point"}
}