{
  "type": "Feature",
  "properties": {
    "iso:country":"US",
    "sg:address":"605 Austin Ave",
    "sg:city":"Waco",
    "sg:classifiers":[
        {
            "category":"Real Estate",
            "subcategory":"Real Estate Agent",
            "type":"Services"
        }
    ],
    "sg:phone":"+1 254 752 7834",
    "sg:postcode":"76701",
    "sg:province":"TX",
    "wof:name":"Hoppenstien Properties",
    "wof:placetype":"venue"
},
  "geometry": {"coordinates":[-97.13355199999999,31.555343],"type":"Point"}
}