{
  "type": "Feature",
  "properties": {
    "iso:country":"US",
    "sg:address":"2305 Grant Ave",
    "sg:city":"El Paso",
    "sg:classifiers":[
        {
            "category":"Manufacturing",
            "subcategory":"Printing",
            "type":"Manufacturing & Wholesale Goods"
        }
    ],
    "sg:phone":"+1 915 587 4000",
    "sg:postcode":"79930",
    "sg:province":"TX",
    "sg:tags":[
        "commercial"
    ],
    "wof:name":"Masters Design",
    "wof:placetype":"venue"
},
  "geometry": {"coordinates":[-106.469053,31.780349],"type":"Point"}
}