{
  "type": "Feature",
  "properties": {
    "iso:country":"US",
    "sg:address":"2450 Holcombe Blvd",
    "sg:city":"Houston",
    "sg:classifiers":[
        {
            "category":"Professional",
            "subcategory":"Research",
            "type":"Services"
        }
    ],
    "sg:phone":"+1 713 794 8601",
    "sg:postcode":"77030",
    "sg:province":"TX",
    "sg:tags":[
        "organization",
        "noncommercial"
    ],
    "wof:name":"Houston Ctr Quality CARe&utlz",
    "wof:placetype":"venue"
},
  "geometry": {"coordinates":[-95.384517,29.705538],"type":"Point"}
}