{
  "type": "Feature",
  "properties": {
    "iso:country":"US",
    "sg:address":"1429 Midwestern Pkwy",
    "sg:city":"Wichita Falls",
    "sg:classifiers":[
        {
            "category":"Manufacturing",
            "subcategory":"Printing",
            "type":"Manufacturing & Wholesale Goods"
        }
    ],
    "sg:phone":"+1 940 322 3347",
    "sg:postcode":"76302",
    "sg:province":"TX",
    "sg:tags":[
        "lithographic",
        "screen",
        "commercial"
    ],
    "wof:name":"Promark Screenprinting",
    "wof:placetype":"venue"
},
  "geometry": {"coordinates":[-98.493533,33.877111],"type":"Point"}
}