{
  "type": "Feature",
  "properties": {
    "iso:country":"US",
    "sg:address":"5115 State Highway 317",
    "sg:city":"Belton",
    "sg:classifiers":[
        {
            "category":"Wholesale",
            "subcategory":"Computers",
            "type":"Manufacturing & Wholesale Goods"
        }
    ],
    "sg:phone":"+1 254 780 2380",
    "sg:postcode":"76513",
    "sg:province":"TX",
    "sg:tags":[
        "equipment"
    ],
    "wof:name":"E-Fact Data Services",
    "wof:placetype":"venue"
},
  "geometry": {"coordinates":[-97.451526,31.101152],"type":"Point"}
}