{
  "type": "Feature",
  "properties": {
    "iso:country":"US",
    "sg:address":"10815 Allison Ln",
    "sg:city":"Atascosa",
    "sg:classifiers":[
        {
            "category":"Building & Trades",
            "subcategory":"Electrical",
            "type":"Services"
        }
    ],
    "sg:phone":"+1 210 622 5799",
    "sg:postcode":"78002",
    "sg:province":"TX",
    "sg:tags":[
        "work",
        "electrical",
        "electric",
        "contractor"
    ],
    "wof:name":"Yourman's Electric Inc",
    "wof:placetype":"venue"
},
  "geometry": {"coordinates":[-98.770591,29.315807],"type":"Point"}
}