{
  "type": "Feature",
  "properties": {
    "iso:country":"US",
    "sg:address":"5410 Bell St",
    "sg:city":"Amarillo",
    "sg:classifiers":[
        {
            "category":"Banks & Credit Unions",
            "subcategory":"Bank",
            "type":"Services"
        }
    ],
    "sg:phone":"+1 806 353 4024",
    "sg:postcode":"79109",
    "sg:province":"TX",
    "sg:tags":[
        "loan",
        "real estate"
    ],
    "wof:name":"Rabo Agrifinancial",
    "wof:placetype":"venue"
},
  "geometry": {"coordinates":[-101.902019,35.146698],"type":"Point"}
}