{
  "type": "Feature",
  "properties": {
    "iso:country":"US",
    "sg:address":"510 Cannon Rd",
    "sg:city":"Victoria",
    "sg:classifiers":[
        {
            "category":"Building & Trades",
            "subcategory":"Construction",
            "type":"Services"
        }
    ],
    "sg:phone":"+1 361 575 7873",
    "sg:postcode":"77904",
    "sg:province":"TX",
    "sg:tags":[
        "contractor"
    ],
    "wof:name":"Felmar Fabrication Inc",
    "wof:placetype":"venue"
},
  "geometry": {"coordinates":[-96.999961,28.874435],"type":"Point"}
}