{
  "type": "Feature",
  "properties": {
    "iso:country":"US",
    "sg:address":"1734 Gladiola Ln",
    "sg:city":"Laredo",
    "sg:classifiers":[
        {
            "category":"Food & Beverages",
            "subcategory":"Groceries & Convenience Stores",
            "type":"Retail Goods"
        }
    ],
    "sg:phone":"+1 956 725 6540",
    "sg:postcode":"78046",
    "sg:province":"TX",
    "sg:tags":[
        "grocer"
    ],
    "wof:name":"Cadena Groceries",
    "wof:placetype":"venue"
},
  "geometry": {"coordinates":[-99.494091,27.364184],"type":"Point"}
}