{
  "type": "Feature",
  "properties": {
    "iso:country":"US",
    "sg:address":"5130 S Cage Blvd",
    "sg:city":"Edinburg",
    "sg:classifiers":[
        {
            "category":"Building & Trades",
            "subcategory":"Construction",
            "type":"Services"
        }
    ],
    "sg:phone":"+1 956 787 0080",
    "sg:postcode":"78577",
    "sg:province":"TX",
    "sg:tags":[
        "boring",
        "contractor"
    ],
    "wof:name":"Valley Road Boring Svc",
    "wof:placetype":"venue"
},
  "geometry": {"coordinates":[-98.192741,26.143305],"type":"Point"}
}