{
  "type": "Feature",
  "properties": {
    "iso:country":"US",
    "sg:address":"113 N Greer Blvd",
    "sg:city":"Pittsburg",
    "sg:classifiers":[
        {
            "category":"Shopping",
            "subcategory":"Department Store",
            "type":"Retail Goods"
        }
    ],
    "sg:phone":"+1 903 855 1477",
    "sg:postcode":"75686",
    "sg:province":"TX",
    "sg:tags":[
        "shop"
    ],
    "wof:name":"Fred's Store",
    "wof:placetype":"venue"
},
  "geometry": {"coordinates":[-94.958459,32.999005],"type":"Point"}
}