{
  "type": "Feature",
  "properties": {
    "iso:country":"US",
    "sg:address":"325 Skyview Dr W",
    "sg:city":"San Antonio",
    "sg:classifiers":[
        {
            "category":"Shopping",
            "type":"Retail Goods"
        }
    ],
    "sg:phone":"+1 210 433 7777",
    "sg:postcode":"78228",
    "sg:province":"TX",
    "sg:tags":[
        "stamp",
        "collector",
        "for"
    ],
    "wof:name":"Spee-D Stamp Co",
    "wof:placetype":"venue"
},
  "geometry": {"coordinates":[-98.57837600000001,29.477019],"type":"Point"}
}