{
  "type": "Feature",
  "properties": {
    "iso:country":"US",
    "sg:address":"1911 Junction Hwy",
    "sg:city":"Kerrville",
    "sg:classifiers":[
        {
            "category":"Professional",
            "subcategory":"Art Services",
            "type":"Services"
        }
    ],
    "sg:phone":"+1 830 895 3707",
    "sg:postcode":"78028",
    "sg:province":"TX",
    "sg:tags":[
        "commercial",
        "design"
    ],
    "wof:name":"Round Up Graphics",
    "wof:placetype":"venue"
},
  "geometry": {"coordinates":[-99.19172,30.07236],"type":"Point"}
}