{
  "type": "Feature",
  "properties": {
    "iso:country":"US",
    "sg:address":"329 Guadalupe Dr",
    "sg:city":"Saginaw",
    "sg:classifiers":[
        {
            "category":"Shopping",
            "type":"Retail Goods"
        }
    ],
    "sg:phone":"+1 817 847 8650",
    "sg:postcode":"76179",
    "sg:province":"TX",
    "sg:tags":[
        "merchandising"
    ],
    "wof:name":"Janice Krucky",
    "wof:placetype":"venue"
},
  "geometry": {"coordinates":[-97.374194,32.85426],"type":"Point"}
}