{
  "type": "Feature",
  "properties": {
    "iso:country":"US",
    "sg:address":"2234 Nall St",
    "sg:city":"Port Neches",
    "sg:classifiers":[
        {
            "category":"Health Services",
            "subcategory":"Doctor",
            "type":"Services"
        }
    ],
    "sg:phone":"+1 409 722 2233",
    "sg:postcode":"77651",
    "sg:province":"TX",
    "wof:name":"Kubitz Michael A",
    "wof:placetype":"venue"
},
  "geometry": {"coordinates":[-93.96288199999999,29.980037],"type":"Point"}
}