{
  "type": "Feature",
  "properties": {
    "iso:country":"US",
    "sg:address":"3500 Easy St",
    "sg:city":"Dallas",
    "sg:classifiers":[
        {
            "category":"Retail",
            "subcategory":"Repair Shop",
            "type":"Services"
        }
    ],
    "sg:phone":"+1 214 819 9733",
    "sg:postcode":"75247",
    "sg:province":"TX",
    "sg:tags":[
        "lock",
        "locksmith"
    ],
    "wof:name":"Associated Locksmith-America",
    "wof:placetype":"venue"
},
  "geometry": {"coordinates":[-96.878243,32.807563],"type":"Point"}
}