{
  "type": "Feature",
  "properties": {
    "iso:country":"US",
    "sg:address":"17480 Dallas Pkwy Ste 200",
    "sg:city":"Dallas",
    "sg:classifiers":[
        {
            "category":"Banks & Credit Unions",
            "subcategory":"Financial Services",
            "type":"Services"
        }
    ],
    "sg:phone":"+1 469 916 7850",
    "sg:postcode":"75287",
    "sg:province":"TX",
    "sg:tags":[
        "broker",
        "mortgage"
    ],
    "wof:name":"Benchmark Mortgage Frisco",
    "wof:placetype":"venue"
},
  "geometry": {"coordinates":[-96.82820100000001,32.988701],"type":"Point"}
}