{
  "type": "Feature",
  "properties": {
    "iso:country":"US",
    "sg:address":"2310 Crows Nest Dr",
    "sg:city":"League City",
    "sg:classifiers":[
        {
            "category":"Shopping",
            "subcategory":"Jewelry",
            "type":"Retail Goods"
        }
    ],
    "sg:phone":"+1 281 535 0633",
    "sg:postcode":"77573",
    "sg:province":"TX",
    "sg:tags":[
        "jeweler"
    ],
    "wof:name":"Forever & A Day",
    "wof:placetype":"venue"
},
  "geometry": {"coordinates":[-95.07548800000001,29.535158],"type":"Point"}
}