{
  "type": "Feature",
  "properties": {
    "iso:country":"US",
    "sg:address":"103 E Mc Mullen St",
    "sg:city":"Three Rivers",
    "sg:classifiers":[
        {
            "category":"Personal",
            "subcategory":"Beauty Salon",
            "type":"Services"
        }
    ],
    "sg:phone":"+1 361 786 3473",
    "sg:postcode":"78071",
    "sg:province":"TX",
    "wof:name":"Dixie Nail Designs",
    "wof:placetype":"venue"
},
  "geometry": {"coordinates":[-98.18035399999999,28.466964],"type":"Point"}
}