{
  "type": "Feature",
  "properties": {
    "iso:country":"US",
    "sg:address":"1519 Texas Ave",
    "sg:city":"El Paso",
    "sg:classifiers":[
        {
            "category":"Wholesale",
            "subcategory":"Machinery & Supplies",
            "type":"Manufacturing & Wholesale Goods"
        }
    ],
    "sg:phone":"+1 915 543 9006",
    "sg:postcode":"79901",
    "sg:province":"TX",
    "sg:tags":[
        "equipment",
        "parts",
        "tractor"
    ],
    "wof:name":"Turbo Tractor Equipment",
    "wof:placetype":"venue"
},
  "geometry": {"coordinates":[-106.473685,31.767585],"type":"Point"}
}