{
  "type": "Feature",
  "properties": {
    "iso:country":"US",
    "sg:address":"501 S 14th St",
    "sg:city":"Alpine",
    "sg:classifiers":[
        {
            "category":"Shopping",
            "subcategory":"Florist",
            "type":"Retail Goods"
        }
    ],
    "sg:phone":"+1 432 837 5035",
    "sg:postcode":"79830",
    "sg:province":"TX",
    "wof:name":"Casa De Flores",
    "wof:placetype":"venue"
},
  "geometry": {"coordinates":[-103.668983,30.351327],"type":"Point"}
}