{
  "type": "Feature",
  "properties": {
    "iso:country":"US",
    "sg:address":"102 Dickard Trl",
    "sg:city":"Longview",
    "sg:classifiers":[
        {
            "category":"Insurance",
            "subcategory":"Insurance Agent",
            "type":"Services"
        }
    ],
    "sg:phone":"+1 903 663 1179",
    "sg:postcode":"75605",
    "sg:province":"TX",
    "wof:name":"Longview South Rotary CLU",
    "wof:placetype":"venue"
},
  "geometry": {"coordinates":[-94.71502599999999,32.553088],"type":"Point"}
}