{
  "type": "Feature",
  "properties": {
    "iso:country":"US",
    "sg:address":"410 Lincoln Sq",
    "sg:city":"Arlington",
    "sg:classifiers":[
        {
            "category":"Shopping",
            "subcategory":"Jewelry",
            "type":"Retail Goods"
        }
    ],
    "sg:phone":"+1 817 460 6136",
    "sg:postcode":"76011",
    "sg:province":"TX",
    "sg:tags":[
        "repair"
    ],
    "wof:name":"Quik Set Jewelry Repair",
    "wof:placetype":"venue"
},
  "geometry": {"coordinates":[-97.098781,32.757374],"type":"Point"}
}