{
  "type": "Feature",
  "properties": {
    "iso:country":"US",
    "sg:address":"2814 Sable Dr",
    "sg:city":"Pearland",
    "sg:classifiers":[
        {
            "category":"Education",
            "subcategory":"Special Training",
            "type":"Public Place"
        }
    ],
    "sg:phone":"+1 713 436 3960",
    "sg:postcode":"77584",
    "sg:province":"TX",
    "sg:tags":[
        "professor"
    ],
    "wof:name":"Mohan Radhe",
    "wof:placetype":"venue"
},
  "geometry": {"coordinates":[-95.37690000000001,29.54542],"type":"Point"}
}