{
  "type": "Feature",
  "properties": {
    "iso:country":"US",
    "sg:address":"3400 Mankins Ave",
    "sg:city":"Odessa",
    "sg:classifiers":[
        {
            "category":"Mining & Drilling",
            "type":"Manufacturing & Wholesale Goods"
        }
    ],
    "sg:phone":"+1 432 550 3138",
    "sg:postcode":"79764",
    "sg:province":"TX",
    "sg:tags":[
        "oil",
        "well"
    ],
    "wof:name":"Pool Well Svc",
    "wof:placetype":"venue"
},
  "geometry": {"coordinates":[-102.408359,31.873832],"type":"Point"}
}