{
  "type": "Feature",
  "properties": {
    "iso:country":"US",
    "sg:address":"801 W Francis Ave",
    "sg:city":"Pampa",
    "sg:classifiers":[
        {
            "category":"Freight",
            "type":"Transportation"
        }
    ],
    "sg:phone":"+1 806 665 8694",
    "sg:postcode":"79065",
    "sg:province":"TX",
    "sg:tags":[
        "warehouse"
    ],
    "wof:name":"Johnson Warehouse",
    "wof:placetype":"venue"
},
  "geometry": {"coordinates":[-100.97015,35.534337],"type":"Point"}
}