{
  "type": "Feature",
  "properties": {
    "iso:country":"US",
    "sg:address":"1942 Cheyenne Dr",
    "sg:city":"Carrollton",
    "sg:classifiers":[
        {
            "category":"Insurance",
            "subcategory":"Insurance Agent",
            "type":"Services"
        }
    ],
    "sg:phone":"+1 972 395 7553",
    "sg:postcode":"75010",
    "sg:province":"TX",
    "wof:name":"Diversified Insur Mkgt Interna",
    "wof:placetype":"venue"
},
  "geometry": {"coordinates":[-96.880421,33.027834],"type":"Point"}
}