{
  "type": "Feature",
  "properties": {
    "iso:country":"US",
    "sg:address":"106 Pine Hl",
    "sg:city":"Frankston",
    "sg:classifiers":[
        {
            "category":"Personal",
            "subcategory":"Barber",
            "type":"Services"
        }
    ],
    "sg:phone":"+1 903 876 4406",
    "sg:postcode":"75763",
    "sg:province":"TX",
    "wof:name":"Tammy's Place",
    "wof:placetype":"venue"
},
  "geometry": {"coordinates":[-95.53921099999999,31.977296],"type":"Point"}
}