{
  "type": "Feature",
  "properties": {
    "iso:country":"US",
    "sg:address":"4708 Salem Dr",
    "sg:city":"Mesquite",
    "sg:classifiers":[
        {
            "category":"Wholesale",
            "subcategory":"Machinery & Supplies",
            "type":"Manufacturing & Wholesale Goods"
        }
    ],
    "sg:phone":"+1 972 270 9782",
    "sg:postcode":"75150",
    "sg:province":"TX",
    "sg:tags":[
        "mfg",
        "equipment",
        "industrial",
        "general"
    ],
    "wof:name":"Vick Sales Co",
    "wof:placetype":"venue"
},
  "geometry": {"coordinates":[-96.641126,32.832512],"type":"Point"}
}