{
  "type": "Feature",
  "properties": {
    "iso:country":"US",
    "sg:address":"4682 Newman Rd",
    "sg:city":"Abilene",
    "sg:classifiers":[
        {
            "category":"Airport",
            "type":"Transportation"
        }
    ],
    "sg:phone":"+1 325 672 5115",
    "sg:postcode":"79601",
    "sg:province":"TX",
    "wof:name":"Angel Aviation Inc",
    "wof:placetype":"venue"
},
  "geometry": {"coordinates":[-99.65253800000001,32.445323],"type":"Point"}
}