{
  "type": "Feature",
  "properties": {
    "iso:country":"US",
    "sg:address":"4400 Moulton St",
    "sg:city":"Greenville",
    "sg:classifiers":[
        {
            "category":"Education",
            "subcategory":"Dance Studio",
            "type":"Public Place"
        }
    ],
    "sg:phone":"+1 903 454 6989",
    "sg:postcode":"75401",
    "sg:province":"TX",
    "sg:tags":[
        "instruction",
        "dancing"
    ],
    "wof:name":"Danceworks",
    "wof:placetype":"venue"
},
  "geometry": {"coordinates":[-96.09848599999999,33.12482],"type":"Point"}
}