{
  "type": "Feature",
  "properties": {
    "iso:country":"US",
    "sg:address":"7920 Belt Line Rd",
    "sg:city":"Dallas",
    "sg:classifiers":[
        {
            "category":"Banks & Credit Unions",
            "subcategory":"Bank",
            "type":"Services"
        }
    ],
    "sg:phone":"+1 972 392 7800",
    "sg:postcode":"75254",
    "sg:province":"TX",
    "sg:tags":[
        "loan",
        "real estate"
    ],
    "wof:name":"Sunset Mortgage",
    "wof:placetype":"venue"
},
  "geometry": {"coordinates":[-96.769818,32.95064],"type":"Point"}
}