{
  "type": "Feature",
  "properties": {
    "iso:country":"US",
    "sg:address":"1812 Water St",
    "sg:city":"Gonzales",
    "sg:classifiers":[
        {
            "category":"Government",
            "subcategory":"Office",
            "type":"Public Place"
        }
    ],
    "sg:phone":"+1 830 672 2834",
    "sg:postcode":"78629",
    "sg:province":"TX",
    "wof:name":"Poultry Disease Lab",
    "wof:placetype":"venue"
},
  "geometry": {"coordinates":[-97.46232500000001,29.51393],"type":"Point"}
}