{
  "type": "Feature",
  "properties": {
    "iso:country":"US",
    "sg:address":"1500 Binz St",
    "sg:city":"Houston",
    "sg:classifiers":[
        {
            "category":"Museum",
            "type":"Entertainment"
        }
    ],
    "sg:phone":"+1 713 522 1138",
    "sg:postcode":"77004",
    "sg:province":"TX",
    "sg:website":"cmhouston.org",
    "wof:name":"The Children's Museum of Houston",
    "wof:placetype":"venue"
},
  "geometry": {"coordinates":[-95.3853,29.7232],"type":"Point"}
}