{
  "type": "Feature",
  "properties": {
    "iso:country":"US",
    "sg:address":"1115 Faris St",
    "sg:city":"San Marcos",
    "sg:classifiers":[
        {
            "category":"Wholesale",
            "subcategory":"Non-durable Goods",
            "type":"Manufacturing & Wholesale Goods"
        }
    ],
    "sg:phone":"+1 512 396 3396",
    "sg:postcode":"78666",
    "sg:province":"TX",
    "wof:name":"Touch of Air",
    "wof:placetype":"venue"
},
  "geometry": {"coordinates":[-97.949511,29.872444],"type":"Point"}
}