{
  "type": "Feature",
  "properties": {
    "iso:country":"US",
    "sg:address":"505 110th St",
    "sg:city":"Arlington",
    "sg:classifiers":[
        {
            "category":"Wholesale",
            "subcategory":"Vending Machines",
            "type":"Manufacturing & Wholesale Goods"
        }
    ],
    "sg:phone":"+1 817 608 0804",
    "sg:postcode":"76011",
    "sg:province":"TX",
    "wof:name":"SPG Vending Solutions",
    "wof:placetype":"venue"
},
  "geometry": {"coordinates":[-97.05169600000001,32.74863],"type":"Point"}
}