{
  "type": "Feature",
  "properties": {
    "iso:country":"US",
    "sg:address":"9458 FM 724",
    "sg:city":"Tyler",
    "sg:classifiers":[
        {
            "category":"Building & Trades",
            "subcategory":"Plumbing",
            "type":"Services"
        }
    ],
    "sg:phone":"+1 903 593 1591",
    "sg:postcode":"75704",
    "sg:province":"TX",
    "sg:tags":[
        "tank",
        "septic"
    ],
    "wof:name":"L E Harris & Son Septic Tank",
    "wof:placetype":"venue"
},
  "geometry": {"coordinates":[-95.46780699999999,32.408185],"type":"Point"}
}