{
  "type": "Feature",
  "properties": {
    "iso:country":"US",
    "sg:address":"300 W Hillside Rd",
    "sg:city":"Laredo",
    "sg:classifiers":[
        {
            "category":"Manufacturing",
            "subcategory":"Jewelry",
            "type":"Manufacturing & Wholesale Goods"
        }
    ],
    "sg:phone":"+1 956 753 5195",
    "sg:postcode":"78041",
    "sg:province":"TX",
    "sg:tags":[
        "precious",
        "metal",
        "mfg"
    ],
    "wof:name":"Unique Treasures",
    "wof:placetype":"venue"
},
  "geometry": {"coordinates":[-99.497671,27.54712],"type":"Point"}
}