{
  "type": "Feature",
  "properties": {
    "iso:country":"US",
    "sg:address":"56 Oakwell Farms Pkwy",
    "sg:city":"San Antonio",
    "sg:classifiers":[
        {
            "category":"Banks & Credit Unions",
            "subcategory":"Investment Brokerage",
            "type":"Services"
        }
    ],
    "sg:phone":"+1 210 930 2771",
    "sg:postcode":"78218",
    "sg:province":"TX",
    "sg:tags":[
        "security"
    ],
    "wof:name":"Xl Investments",
    "wof:placetype":"venue"
},
  "geometry": {"coordinates":[-98.43154699999999,29.501979],"type":"Point"}
}