{
  "type": "Feature",
  "properties": {
    "iso:country":"US",
    "sg:address":"3803 Mount Bonnell Rd",
    "sg:city":"Austin",
    "sg:classifiers":[
        {
            "category":"Professional",
            "subcategory":"Computer Services",
            "type":"Services"
        }
    ],
    "sg:phone":"+1 512 454 1140",
    "sg:postcode":"78731",
    "sg:province":"TX",
    "sg:tags":[
        "development",
        "software"
    ],
    "wof:name":"Novosoft Inc",
    "wof:placetype":"venue"
},
  "geometry": {"coordinates":[-97.77316500000001,30.322373],"type":"Point"}
}