{
  "type": "Feature",
  "properties": {
    "iso:country":"US",
    "sg:address":"243 NE 28th St",
    "sg:city":"Fort Worth",
    "sg:classifiers":[
        {
            "category":"Restaurant",
            "type":"Food & Drink"
        }
    ],
    "sg:phone":"+1 817 378 9988",
    "sg:postcode":"76164",
    "sg:province":"TX",
    "sg:tags":[
        "eating"
    ],
    "wof:name":"China Buffet",
    "wof:placetype":"venue"
},
  "geometry": {"coordinates":[-97.34586400000001,32.795211],"type":"Point"}
}