{
  "type": "Feature",
  "properties": {
    "iso:country":"US",
    "sg:address":"13130 Louetta Rd",
    "sg:city":"Cypress",
    "sg:classifiers":[
        {
            "category":"Retail",
            "subcategory":"Laundry & Dry Cleaning",
            "type":"Services"
        }
    ],
    "sg:phone":"+1 281 379 6362",
    "sg:postcode":"77429",
    "sg:province":"TX",
    "sg:tags":[
        "cleaner"
    ],
    "wof:name":"Nesbit's Cleaners",
    "wof:placetype":"venue"
},
  "geometry": {"coordinates":[-95.62287600000001,29.995097],"type":"Point"}
}