{
  "type": "Feature",
  "properties": {
    "iso:country":"US",
    "sg:address":"2316 N Alexander Dr",
    "sg:city":"Baytown",
    "sg:classifiers":[
        {
            "category":"Shopping",
            "subcategory":"Computers & Home Electronics",
            "type":"Retail Goods"
        }
    ],
    "sg:phone":"+1 281 427 6169",
    "sg:postcode":"77520",
    "sg:province":"TX",
    "wof:name":"Radio Shack",
    "wof:placetype":"venue"
},
  "geometry": {"coordinates":[-94.94897899999999,29.74595],"type":"Point"}
}