{
  "type": "Feature",
  "properties": {
    "iso:country":"US",
    "sg:address":"911 S Bishop Rd",
    "sg:city":"Wake Village",
    "sg:classifiers":[
        {
            "category":"Manufacturing",
            "subcategory":"Lumber",
            "type":"Manufacturing & Wholesale Goods"
        }
    ],
    "sg:phone":"+1 903 831 5200",
    "sg:postcode":"75501",
    "sg:province":"TX",
    "sg:tags":[
        "forester"
    ],
    "wof:name":"Kingwood Forestry Svc Inc",
    "wof:placetype":"venue"
},
  "geometry": {"coordinates":[-94.098045,33.412186],"type":"Point"}
}