{
  "type": "Feature",
  "properties": {
    "iso:country":"US",
    "sg:address":"2109 W Parker Rd",
    "sg:city":"Plano",
    "sg:classifiers":[
        {
            "category":"Health Services",
            "subcategory":"Chiropractor",
            "type":"Services"
        }
    ],
    "sg:phone":"+1 972 612 2225",
    "sg:postcode":"75023",
    "sg:province":"TX",
    "wof:name":"Action Chiropractic Inc",
    "wof:placetype":"venue"
},
  "geometry": {"coordinates":[-96.73348900000001,33.04092],"type":"Point"}
}