{
  "type": "Feature",
  "properties": {
    "iso:country":"US",
    "sg:address":"2400 W Michigan Ave",
    "sg:city":"Midland",
    "sg:classifiers":[
        {
            "category":"Autos & Motor Vehicles",
            "subcategory":"Auto Supplies",
            "type":"Retail Goods"
        }
    ],
    "sg:phone":"+1 432 683 0093",
    "sg:postcode":"79701",
    "sg:province":"TX",
    "sg:tags":[
        "parts"
    ],
    "wof:name":"Autozone",
    "wof:placetype":"venue"
},
  "geometry": {"coordinates":[-102.10395800000001,31.997193],"type":"Point"}
}