{
  "type": "Feature",
  "properties": {
    "iso:country":"US",
    "sg:address":"5210 Blanco Rd",
    "sg:city":"San Antonio",
    "sg:classifiers":[
        {
            "category":"Restaurant",
            "type":"Food & Drink"
        }
    ],
    "sg:phone":"+1 210 308 7300",
    "sg:postcode":"78216",
    "sg:province":"TX",
    "sg:tags":[
        "eating"
    ],
    "wof:name":"Malt House Cafe",
    "wof:placetype":"venue"
},
  "geometry": {"coordinates":[-98.507746,29.494544],"type":"Point"}
}