{
  "type": "Feature",
  "properties": {
    "iso:country":"US",
    "sg:address":"3900 S Georgia St",
    "sg:city":"Amarillo",
    "sg:classifiers":[
        {
            "category":"Insurance",
            "subcategory":"Insurance Agent",
            "type":"Services"
        }
    ],
    "sg:phone":"+1 806 355 2429",
    "sg:postcode":"79109",
    "sg:province":"TX",
    "wof:name":"Primerica Financial Svc",
    "wof:placetype":"venue"
},
  "geometry": {"coordinates":[-101.866069,35.172788],"type":"Point"}
}