{
  "type": "Feature",
  "properties": {
    "iso:country":"US",
    "sg:address":"6610 Burnet Rd",
    "sg:city":"Austin",
    "sg:classifiers":[
        {
            "category":"Personal",
            "type":"Services"
        },
        {
            "category":"Building & Trades",
            "subcategory":"Pest Control",
            "type":"Services"
        }
    ],
    "sg:phone":"+1 512 929 9000",
    "sg:postcode":"78757",
    "sg:province":"TX",
    "sg:tags":[
        "home"
    ],
    "sg:website":"mosquitonixaustin.com/",
    "wof:name":"MosquitoNix - Austin Mosquito Control",
    "wof:placetype":"venue"
},
  "geometry": {"coordinates":[-97.738962,30.342276],"type":"Point"}
}