{
  "type": "Feature",
  "properties": {
    "iso:country":"US",
    "sg:address":"9460 State Hwy 6 Bus",
    "sg:city":"Navasota",
    "sg:classifiers":[
        {
            "category":"Travel",
            "subcategory":"Hotels & Motels",
            "type":"Entertainment"
        }
    ],
    "sg:phone":"+1 936 825 7775",
    "sg:postcode":"77868",
    "sg:province":"TX",
    "sg:tags":[
        "operation"
    ],
    "wof:name":"Super 8 Motel",
    "wof:placetype":"venue"
},
  "geometry": {"coordinates":[-96.076774,30.366564],"type":"Point"}
}