{
  "type": "Feature",
  "properties": {
    "iso:country":"US",
    "sg:address":"721 Canongate Dr",
    "sg:city":"Flower Mound",
    "sg:classifiers":[
        {
            "category":"Wholesale",
            "subcategory":"Furniture",
            "type":"Manufacturing & Wholesale Goods"
        }
    ],
    "sg:phone":"+1 972 539 0406",
    "sg:postcode":"75022",
    "sg:province":"TX",
    "wof:name":"Bethany Group",
    "wof:placetype":"venue"
},
  "geometry": {"coordinates":[-97.07238,32.995936],"type":"Point"}
}