{
  "type": "Feature",
  "properties": {
    "iso:country":"US",
    "sg:address":"3505 Belmont St",
    "sg:city":"Denton",
    "sg:classifiers":[
        {
            "category":"Professional",
            "subcategory":"Management & Consulting",
            "type":"Services"
        }
    ],
    "sg:phone":"+1 940 591 1517",
    "sg:postcode":"76210",
    "sg:province":"TX",
    "wof:name":"Gunnar Philipp",
    "wof:placetype":"venue"
},
  "geometry": {"coordinates":[-97.13248400000001,33.168011],"type":"Point"}
}