{
  "type": "Feature",
  "properties": {
    "iso:country":"US",
    "sg:address":"1722 Port Neches Ave",
    "sg:city":"Port Neches",
    "sg:classifiers":[
        {
            "category":"Building & Trades",
            "subcategory":"Plumbing",
            "type":"Services"
        }
    ],
    "sg:phone":"+1 409 724 0933",
    "sg:postcode":"77651",
    "sg:province":"TX",
    "sg:tags":[
        "commercial",
        "air",
        "refrigeration",
        "condition",
        "contractor"
    ],
    "wof:name":"Moore Service Co",
    "wof:placetype":"venue"
},
  "geometry": {"coordinates":[-93.96566799999999,29.990694],"type":"Point"}
}