{
  "type": "Feature",
  "properties": {
    "iso:country":"US",
    "sg:address":"1305 George St",
    "sg:city":"Rosenberg",
    "sg:classifiers":[
        {
            "category":"Building & Trades",
            "subcategory":"Construction",
            "type":"Services"
        }
    ],
    "sg:phone":"+1 281 232 6095",
    "sg:postcode":"77471",
    "sg:province":"TX",
    "sg:tags":[
        "contractor"
    ],
    "wof:name":"Charlie Boettcher & Sons",
    "wof:placetype":"venue"
},
  "geometry": {"coordinates":[-95.816356,29.554928],"type":"Point"}
}