{
  "type": "Feature",
  "properties": {
    "iso:country":"US",
    "sg:address":"806 E Division St",
    "sg:city":"Arlington",
    "sg:classifiers":[
        {
            "category":"Autos & Motor Vehicles",
            "subcategory":"Auto Supplies",
            "type":"Retail Goods"
        }
    ],
    "sg:phone":"+1 817 801 0206",
    "sg:postcode":"76011",
    "sg:province":"TX",
    "sg:tags":[
        "tire"
    ],
    "wof:name":"Speedy Tires & Wheels",
    "wof:placetype":"venue"
},
  "geometry": {"coordinates":[-97.09900500000001,32.738711],"type":"Point"}
}