{
  "type": "Feature",
  "properties": {
    "iso:country":"US",
    "sg:address":"112 E Market St",
    "sg:city":"Lockhart",
    "sg:classifiers":[
        {
            "category":"Insurance",
            "subcategory":"Hazard Insurance",
            "type":"Services"
        },
        {
            "category":"Professional",
            "subcategory":"Business Services",
            "type":"Services"
        }
    ],
    "sg:phone":"+1 512 398 2400",
    "sg:postcode":"78644",
    "sg:province":"TX",
    "sg:tags":[
        "bond"
    ],
    "wof:name":"Yanez Bonding Company",
    "wof:placetype":"venue"
},
  "geometry": {"coordinates":[-97.671316,29.883925],"type":"Point"}
}