{
  "type": "Feature",
  "properties": {
    "iso:country":"US",
    "sg:address":"245 Fm 3351 N",
    "sg:city":"Bergheim",
    "sg:classifiers":[
        {
            "category":"Building & Trades",
            "subcategory":"Construction",
            "type":"Services"
        }
    ],
    "sg:phone":"+1 210 745 2743",
    "sg:postcode":"78004",
    "sg:province":"TX",
    "sg:tags":[
        "contractor",
        "grading"
    ],
    "sg:website":"http://www.cedareater.com",
    "wof:name":"Cedar Eaters Of Texas",
    "wof:placetype":"venue"
},
  "geometry": {"coordinates":[-98.571251,29.83997],"type":"Point"}
}