{
  "type": "Feature",
  "properties": {
    "iso:country":"US",
    "sg:address":"701 N Saint Gall St",
    "sg:city":"Fort Stockton",
    "sg:classifiers":[
        {
            "category":"Organizations",
            "subcategory":"Religious Organization",
            "type":"Services"
        }
    ],
    "sg:phone":"+1 432 336 6743",
    "sg:postcode":"79735",
    "sg:province":"TX",
    "sg:tags":[
        "church"
    ],
    "wof:name":"Immanuel Baptist Church",
    "wof:placetype":"venue"
},
  "geometry": {"coordinates":[-102.87486699999999,30.891989],"type":"Point"}
}