{
  "type": "Feature",
  "properties": {
    "iso:country":"US",
    "sg:address":"412 Dowdy Ferry Rd",
    "sg:city":"Dallas",
    "sg:classifiers":[
        {
            "category":"Building & Trades",
            "subcategory":"Construction",
            "type":"Services"
        }
    ],
    "sg:phone":"+1 214 309 1119",
    "sg:postcode":"75217",
    "sg:province":"TX",
    "sg:tags":[
        "hanging",
        "contractor"
    ],
    "wof:name":"Jesus & Sons Painting & Contr",
    "wof:placetype":"venue"
},
  "geometry": {"coordinates":[-96.679148,32.705203],"type":"Point"}
}