{
  "type": "Feature",
  "properties": {
    "iso:country":"US",
    "sg:address":"1414 SE 58th Ave",
    "sg:city":"Amarillo",
    "sg:classifiers":[
        {
            "category":"Autos & Motor Vehicles",
            "subcategory":"Auto Supplies",
            "type":"Retail Goods"
        }
    ],
    "sg:phone":"+1 806 372 6268",
    "sg:postcode":"79118",
    "sg:province":"TX",
    "sg:tags":[
        "repair",
        "general"
    ],
    "wof:name":"Skips Automotive Inc",
    "wof:placetype":"venue"
},
  "geometry": {"coordinates":[-101.822023,35.149437],"type":"Point"}
}