{
  "type": "Feature",
  "properties": {
    "iso:country":"US",
    "sg:address":"5803 Margewood Dr",
    "sg:city":"Dallas",
    "sg:classifiers":[
        {
            "category":"Professional",
            "type":"Services"
        }
    ],
    "sg:phone":"+1 972 298 3359",
    "sg:postcode":"75236",
    "sg:province":"TX",
    "wof:name":"Tackett Stasey",
    "wof:placetype":"venue"
},
  "geometry": {"coordinates":[-96.922917,32.701471],"type":"Point"}
}