{
  "type": "Feature",
  "properties": {
    "iso:country":"US",
    "sg:address":"12727 Mountain Air",
    "sg:city":"San Antonio",
    "sg:classifiers":[
        {
            "category":"Retail",
            "subcategory":"Veterinary Services",
            "type":"Services"
        }
    ],
    "sg:phone":"+1 210 696 1700",
    "sg:postcode":"78249",
    "sg:province":"TX",
    "wof:name":"Ten West Bird & Animal Hosp",
    "wof:placetype":"venue"
},
  "geometry": {"coordinates":[-98.60083,29.561653],"type":"Point"}
}