{
  "type": "Feature",
  "properties": {
    "iso:country":"US",
    "sg:address":"228 Chamberlain St",
    "sg:city":"Irving",
    "sg:classifiers":[
        {
            "category":"Autos & Motor Vehicles",
            "subcategory":"Auto Supplies",
            "type":"Retail Goods"
        }
    ],
    "sg:phone":"+1 972 579 9707",
    "sg:postcode":"75060",
    "sg:province":"TX",
    "sg:tags":[
        "tire"
    ],
    "wof:name":"City of Irving",
    "wof:placetype":"venue"
},
  "geometry": {"coordinates":[-96.945049,32.80356],"type":"Point"}
}