{
  "type": "Feature",
  "properties": {
    "iso:country":"US",
    "sg:address":"1925 E Belt Line Rd Ste 217",
    "sg:city":"Carrollton",
    "sg:classifiers":[
        {
            "category":"Banks & Credit Unions",
            "subcategory":"Financial Services",
            "type":"Services"
        }
    ],
    "sg:phone":"+1 972 478 2021",
    "sg:postcode":"75006",
    "sg:province":"TX",
    "sg:tags":[
        "broker",
        "mortgage"
    ],
    "wof:name":"Mi Casa Mortgage & Financial Services",
    "wof:placetype":"venue"
},
  "geometry": {"coordinates":[-96.887828,32.953857],"type":"Point"}
}