{
  "type": "Feature",
  "properties": {
    "iso:country":"US",
    "sg:address":"10106 Bretton Dr",
    "sg:city":"Houston",
    "sg:classifiers":[
        {
            "category":"Building & Trades",
            "subcategory":"Construction",
            "type":"Services"
        }
    ],
    "sg:phone":"+1 713 635 1379",
    "sg:postcode":"77016",
    "sg:province":"TX",
    "sg:tags":[
        "house"
    ],
    "wof:name":"Urban Improvement Comm",
    "wof:placetype":"venue"
},
  "geometry": {"coordinates":[-95.30403099999999,29.858041],"type":"Point"}
}