{
  "type": "Feature",
  "properties": {
    "iso:country":"US",
    "sg:address":"111 Tillery St",
    "sg:city":"Austin",
    "sg:classifiers":[
        {
            "category":"Building & Trades",
            "subcategory":"Construction",
            "type":"Services"
        }
    ],
    "sg:phone":"+1 512 220 5430",
    "sg:postcode":"78702",
    "sg:province":"TX",
    "sg:tags":[
        "house"
    ],
    "wof:name":"Hectors Painting & Home Repair",
    "wof:placetype":"venue"
},
  "geometry": {"coordinates":[-97.70715,30.25527],"type":"Point"}
}