{
  "type": "Feature",
  "properties": {
    "iso:country":"US",
    "sg:address":"3415 Northland Dr",
    "sg:city":"Austin",
    "sg:classifiers":[
        {
            "category":"Retail",
            "subcategory":"Laundry & Dry Cleaning",
            "type":"Services"
        }
    ],
    "sg:phone":"+1 512 452 4765",
    "sg:postcode":"78731",
    "sg:province":"TX",
    "sg:tags":[
        "drycleaning",
        "plant",
        "parlor",
        "shoe"
    ],
    "sg:website":"www.jackbrowncleaners.com",
    "wof:name":"Jack Brown Cleaners",
    "wof:placetype":"venue"
},
  "geometry": {"coordinates":[-97.758196,30.337841],"type":"Point"}
}