{
  "type": "Feature",
  "properties": {
    "iso:country":"US",
    "sg:address":"3939 Belt Line Rd",
    "sg:city":"Addison",
    "sg:classifiers":[
        {
            "category":"Insurance",
            "subcategory":"Insurance Agent",
            "type":"Services"
        }
    ],
    "sg:phone":"+1 972 488 3333",
    "sg:postcode":"75001",
    "sg:province":"TX",
    "wof:name":"United Texcare",
    "wof:placetype":"venue"
},
  "geometry": {"coordinates":[-96.849071,32.953227],"type":"Point"}
}