{
  "type": "Feature",
  "properties": {
    "iso:country":"US",
    "sg:address":"803 Pine St",
    "sg:city":"Abilene",
    "sg:phone":"+1 325 672 5868",
    "sg:postcode":"79601",
    "sg:province":"TX",
    "sg:tags":[
        "equipment",
        "commercial",
        "kitchen"
    ],
    "wof:name":"Abilene Commercial Kitchens",
    "wof:placetype":"venue"
},
  "geometry": {"coordinates":[-99.73206999999999,32.458342],"type":"Point"}
}