{
  "type": "Feature",
  "properties": {
    "iso:country":"US",
    "sg:address":"5531 Bonsrell St",
    "sg:city":"Houston",
    "sg:classifiers":[
        {
            "category":"Shopping",
            "subcategory":"Music",
            "type":"Retail Goods"
        }
    ],
    "sg:phone":"+1 713 921 5129",
    "sg:postcode":"77023",
    "sg:province":"TX",
    "wof:name":"I B Recording",
    "wof:placetype":"venue"
},
  "geometry": {"coordinates":[-95.31970800000001,29.723448],"type":"Point"}
}