{
  "type": "Feature",
  "properties": {
    "iso:country":"US",
    "sg:address":"111 E Co Rd 132",
    "sg:city":"Midland",
    "sg:classifiers":[
        {
            "category":"Building & Trades",
            "subcategory":"Construction",
            "type":"Services"
        }
    ],
    "sg:phone":"+1 432 570 1704",
    "sg:postcode":"79706",
    "sg:province":"TX",
    "sg:tags":[
        "excavating",
        "contractor"
    ],
    "wof:name":"Advance Backhoe Svc",
    "wof:placetype":"venue"
},
  "geometry": {"coordinates":[-102.061381,31.940737],"type":"Point"}
}