{
  "type": "Feature",
  "properties": {
    "iso:country":"US",
    "sg:address":"307 Center Ave",
    "sg:city":"Brownwood",
    "sg:classifiers":[
        {
            "category":"Recreation",
            "type":"Entertainment"
        }
    ],
    "sg:phone":"+1 325 646 1977",
    "sg:postcode":"76801",
    "sg:province":"TX",
    "sg:tags":[
        "martial",
        "arts",
        "instruction"
    ],
    "wof:name":"Kickin' For Christ Martial",
    "wof:placetype":"venue"
},
  "geometry": {"coordinates":[-98.982029,31.720902],"type":"Point"}
}