{
  "type": "Feature",
  "properties": {
    "iso:country":"US",
    "sg:address":"17702 Booners Cove Ct",
    "sg:city":"Humble",
    "sg:classifiers":[
        {
            "category":"Manufacturing",
            "subcategory":"Tools & Machinery",
            "type":"Manufacturing & Wholesale Goods"
        }
    ],
    "sg:phone":"+1 832 644 9215",
    "sg:postcode":"77346",
    "sg:province":"TX",
    "sg:tags":[
        "springs-wholesale",
        "manufacturer"
    ],
    "wof:name":"Lennar Eagle Springs Model",
    "wof:placetype":"venue"
},
  "geometry": {"coordinates":[-95.184641,29.973469],"type":"Point"}
}