{
  "type": "Feature",
  "properties": {
    "iso:country":"US",
    "sg:address":"1106 Mc Callum Dr",
    "sg:city":"Garland",
    "sg:classifiers":[
        {
            "category":"Food & Beverages",
            "subcategory":"Groceries & Convenience Stores",
            "type":"Retail Goods"
        }
    ],
    "sg:phone":"+1 972 272 6363",
    "sg:postcode":"75042",
    "sg:province":"TX",
    "wof:name":"Bigelow Sales & Marketing",
    "wof:placetype":"venue"
},
  "geometry": {"coordinates":[-96.675282,32.922641],"type":"Point"}
}