{
  "type": "Feature",
  "properties": {
    "iso:country":"US",
    "sg:address":"4317 W Illinois Ave",
    "sg:city":"Midland",
    "sg:classifiers":[
        {
            "category":"Restaurant",
            "type":"Food & Drink"
        }
    ],
    "sg:phone":"+1 432 689 9702",
    "sg:postcode":"79703",
    "sg:province":"TX",
    "sg:tags":[
        "grill",
        "bar"
    ],
    "wof:name":"Wadley & A St",
    "wof:placetype":"venue"
},
  "geometry": {"coordinates":[-102.130004,31.988356],"type":"Point"}
}