{
  "type": "Feature",
  "properties": {
    "iso:country":"US",
    "sg:address":"127 Fuller Ln",
    "sg:city":"Del Valle",
    "sg:classifiers":[
        {
            "category":"Building & Trades",
            "subcategory":"Cleaning & Sanitation",
            "type":"Services"
        }
    ],
    "sg:phone":"+1 512 619 1577",
    "sg:postcode":"78617",
    "sg:province":"TX",
    "sg:tags":[
        "maintenance"
    ],
    "wof:name":"Ultimate Cleaning Services",
    "wof:placetype":"venue"
},
  "geometry": {"coordinates":[-97.58852899999999,30.111113],"type":"Point"}
}