{
  "type": "Feature",
  "properties": {
    "iso:country":"US",
    "sg:address":"300 S Bibb Ave",
    "sg:city":"Eagle Pass",
    "sg:classifiers":[
        {
            "category":"Shopping",
            "subcategory":"Hobbies, Toys, & Games",
            "type":"Retail Goods"
        }
    ],
    "sg:phone":"+1 830 758 1906",
    "sg:postcode":"78852",
    "sg:province":"TX",
    "sg:tags":[
        "supply"
    ],
    "wof:name":"Game Crazy",
    "wof:placetype":"venue"
},
  "geometry": {"coordinates":[-100.48322,28.705789],"type":"Point"}
}