{
  "type": "Feature",
  "properties": {
    "iso:country":"US",
    "sg:address":"9204 Markville Dr",
    "sg:city":"Dallas",
    "sg:classifiers":[
        {
            "category":"Professional",
            "subcategory":"Accounting & Tax Preparation",
            "type":"Services"
        }
    ],
    "sg:phone":"+1 214 340 4295",
    "sg:postcode":"75243",
    "sg:province":"TX",
    "sg:tags":[
        "return"
    ],
    "wof:name":"Sierra Shopping Gift & Tax Svc",
    "wof:placetype":"venue"
},
  "geometry": {"coordinates":[-96.739825,32.913631],"type":"Point"}
}