{
  "type": "Feature",
  "properties": {
    "iso:country":"US",
    "sg:address":"6205 Delaney Rd",
    "sg:city":"Hitchcock",
    "sg:classifiers":[
        {
            "category":"Professional",
            "type":"Services"
        }
    ],
    "sg:phone":"+1 409 986 7029",
    "sg:postcode":"77563",
    "sg:province":"TX",
    "sg:tags":[
        "establishment"
    ],
    "wof:name":"Child Evangelism Fellowship",
    "wof:placetype":"venue"
},
  "geometry": {"coordinates":[-95.020325,29.355877],"type":"Point"}
}