{
  "type": "Feature",
  "properties": {
    "iso:country":"US",
    "sg:address":"24803 Bauer Hockley Rd",
    "sg:city":"Hockley",
    "sg:classifiers":[
        {
            "category":"Manufacturing",
            "subcategory":"Building Materials",
            "type":"Manufacturing & Wholesale Goods"
        }
    ],
    "sg:phone":"+1 281 373 4945",
    "sg:postcode":"77447",
    "sg:province":"TX",
    "sg:tags":[
        "mfg",
        "wood",
        "kitchen",
        "cabinet"
    ],
    "wof:name":"Kustom Kitchens",
    "wof:placetype":"venue"
},
  "geometry": {"coordinates":[-95.81304299999999,30.036716],"type":"Point"}
}