{
  "type": "Feature",
  "properties": {
    "iso:country":"US",
    "sg:address":"26603 N Carrol Ln",
    "sg:city":"Magnolia",
    "sg:classifiers":[
        {
            "category":"Food & Beverages",
            "subcategory":"Groceries & Convenience Stores",
            "type":"Retail Goods"
        }
    ],
    "sg:phone":"+1 281 356 3837",
    "sg:postcode":"77355",
    "sg:province":"TX",
    "sg:tags":[
        "grocer"
    ],
    "wof:name":"K C's Convenience Store",
    "wof:placetype":"venue"
},
  "geometry": {"coordinates":[-95.743059,30.137546],"type":"Point"}
}