{
  "type": "Feature",
  "properties": {
    "iso:country":"US",
    "sg:address":"1215 Chicago Ave",
    "sg:city":"Mcallen",
    "sg:classifiers":[
        {
            "category":"Shopping",
            "subcategory":"Clothing, Apparel, & Fashions",
            "type":"Retail Goods"
        }
    ],
    "sg:phone":"+1 956 664 1435",
    "sg:postcode":"78501",
    "sg:province":"TX",
    "sg:tags":[
        "shop",
        "bridal"
    ],
    "wof:name":"Los Gatitos Bridal Shop",
    "wof:placetype":"venue"
},
  "geometry": {"coordinates":[-98.233642,26.20118],"type":"Point"}
}