{
  "type": "Feature",
  "properties": {
    "iso:country":"US",
    "sg:address":"7601 Lakeview Pkwy",
    "sg:city":"Rowlett",
    "sg:classifiers":[
        {
            "category":"Autos & Motor Vehicles",
            "subcategory":"Fuel & Gas Station",
            "type":"Retail Goods"
        },
        {
            "category":"Autos & Motor Vehicles",
            "subcategory":"Auto Supplies",
            "type":"Retail Goods"
        },
        {
            "category":"Retail",
            "subcategory":"Auto Repair",
            "type":"Services"
        }
    ],
    "sg:phone":"+1 972 463 8475",
    "sg:postcode":"75088",
    "sg:province":"TX",
    "sg:tags":[
        "automobile",
        "part",
        "accessory"
    ],
    "sg:website":"http://acdelco.com",
    "wof:name":"Parkway Car Care",
    "wof:placetype":"venue"
},
  "geometry": {"coordinates":[-96.528965,32.912001],"type":"Point"}
}