{
  "type": "Feature",
  "properties": {
    "iso:country":"US",
    "sg:address":"4945 Gulfway Dr",
    "sg:city":"Port Arthur",
    "sg:classifiers":[
        {
            "category":"Organizations",
            "subcategory":"Religious Organization",
            "type":"Services"
        }
    ],
    "sg:phone":"+1 409 983 5230",
    "sg:postcode":"77642",
    "sg:province":"TX",
    "wof:name":"Zoe Ministries",
    "wof:placetype":"venue"
},
  "geometry": {"coordinates":[-93.911867,29.916851],"type":"Point"}
}