{
  "type": "Feature",
  "properties": {
    "iso:country":"US",
    "sg:address":"4600 McKinney Ave",
    "sg:city":"Dallas",
    "sg:classifiers":[
        {
            "category":"Shopping",
            "subcategory":"Pharmacy",
            "type":"Retail Goods"
        }
    ],
    "sg:phone":"+1 214 521 3101",
    "sg:postcode":"75205",
    "sg:province":"TX",
    "sg:tags":[
        "drug",
        "store"
    ],
    "wof:name":"Eckerd",
    "wof:placetype":"venue"
},
  "geometry": {"coordinates":[-96.786535,32.82459],"type":"Point"}
}