{
  "type": "Feature",
  "properties": {
    "iso:country":"US",
    "sg:address":"4301 Westbank Drive Suite 350",
    "sg:city":"Austin",
    "sg:classifiers":[
        {
            "category":"Communications",
            "subcategory":"Radio Station",
            "type":"Services"
        }
    ],
    "sg:phone":"+1 512 329 5523",
    "sg:postcode":"78746",
    "sg:province":"TX",
    "wof:name":"Kkmj",
    "wof:placetype":"venue"
},
  "geometry": {"coordinates":[-97.816637,30.276254],"type":"Point"}
}