{
  "type": "Feature",
  "properties": {
    "iso:country":"US",
    "sg:address":"4105 Hunter Rd",
    "sg:city":"San Marcos",
    "sg:classifiers":[
        {
            "category":"Manufacturing",
            "subcategory":"Printing",
            "type":"Manufacturing & Wholesale Goods"
        }
    ],
    "sg:phone":"+1 512 392 3383",
    "sg:postcode":"78666",
    "sg:province":"TX",
    "sg:tags":[
        "newspaper"
    ],
    "wof:name":"Houston Chronicle",
    "wof:placetype":"venue"
},
  "geometry": {"coordinates":[-98.00724700000001,29.821962],"type":"Point"}
}