{
  "type": "Feature",
  "properties": {
    "iso:country":"US",
    "sg:address":"1301 San Bernardo Ave",
    "sg:city":"Laredo",
    "sg:classifiers":[
        {
            "category":"Autos & Motor Vehicles",
            "subcategory":"Auto Supplies",
            "type":"Retail Goods"
        }
    ],
    "sg:phone":"+1 956 723 4722",
    "sg:postcode":"78040",
    "sg:province":"TX",
    "sg:tags":[
        "tire"
    ],
    "wof:name":"Jesse Martinez Auto Parts",
    "wof:placetype":"venue"
},
  "geometry": {"coordinates":[-99.50454499999999,27.511539],"type":"Point"}
}