{
  "type": "Feature",
  "properties": {
    "iso:country":"US",
    "sg:address":"1807 Medina Dr",
    "sg:city":"College Station",
    "sg:classifiers":[
        {
            "category":"Organizations",
            "subcategory":"Religious Organization",
            "type":"Services"
        }
    ],
    "sg:phone":"+1 979 693 1850",
    "sg:postcode":"77840",
    "sg:province":"TX",
    "wof:name":"Gideons International",
    "wof:placetype":"venue"
},
  "geometry": {"coordinates":[-96.318901,30.594958],"type":"Point"}
}