{
  "type": "Feature",
  "properties": {
    "iso:country":"US",
    "sg:address":"3435 Finley Rd",
    "sg:city":"Irving",
    "sg:classifiers":[
        {
            "category":"Real Estate",
            "subcategory":"Real Estate Services",
            "type":"Services"
        },
        {
            "category":"Real Estate",
            "subcategory":"Real Estate Agent",
            "type":"Services"
        }
    ],
    "sg:phone":"+1 972 259 8787",
    "sg:postcode":"75062",
    "sg:province":"TX",
    "sg:tags":[
        "buyer",
        "broker"
    ],
    "wof:name":"Capitalcorp, Inc.",
    "wof:placetype":"venue"
},
  "geometry": {"coordinates":[-96.992707,32.850941],"type":"Point"}
}