{
  "type": "Feature",
  "properties": {
    "iso:country":"US",
    "sg:address":"5901 Loop 256",
    "sg:city":"Palestine",
    "sg:classifiers":[
        {
            "category":"Shopping",
            "type":"Retail Goods"
        }
    ],
    "sg:phone":"+1 903 723 2368",
    "sg:postcode":"75801",
    "sg:province":"TX",
    "sg:tags":[
        "merchandise"
    ],
    "wof:name":"Saunas For Health",
    "wof:placetype":"venue"
},
  "geometry": {"coordinates":[-95.608414,31.770911],"type":"Point"}
}