{
  "type": "Feature",
  "properties": {
    "iso:country":"US",
    "sg:address":"1219 S Lamar Blvd",
    "sg:city":"Austin",
    "sg:classifiers":[
        {
            "category":"Restaurant",
            "type":"Food & Drink"
        },
        {
            "category":"Food Court",
            "type":"Food & Drink"
        }
    ],
    "sg:phone":"+1 512 695 6922",
    "sg:postcode":"78704",
    "sg:province":"TX",
    "sg:tags":[
        "new",
        "american",
        "stand"
    ],
    "sg:website":"www.farmtotrailer.com",
    "wof:name":"Odd Duck Farm To Trailer",
    "wof:placetype":"venue"
},
  "geometry": {"coordinates":[-97.762238,30.254091],"type":"Point"}
}