{
  "type": "Feature",
  "properties": {
    "iso:country":"US",
    "sg:address":"201 N Cedar St",
    "sg:city":"Kermit",
    "sg:classifiers":[
        {
            "category":"Autos & Motor Vehicles",
            "subcategory":"Auto Supplies",
            "type":"Retail Goods"
        },
        {
            "category":"Retail",
            "subcategory":"Auto Repair",
            "type":"Services"
        }
    ],
    "sg:phone":"+1 432 586 6787",
    "sg:postcode":"79745",
    "sg:province":"TX",
    "sg:tags":[
        "alternator",
        "automobile",
        "body",
        "generators-automotive",
        "painting",
        "repairing"
    ],
    "wof:name":"Jcs Auto Shop",
    "wof:placetype":"venue"
},
  "geometry": {"coordinates":[-103.092651,31.859051],"type":"Point"}
}