{
  "type": "Feature",
  "properties": {
    "iso:country":"US",
    "sg:address":"7421 Frankford Rd",
    "sg:city":"Dallas",
    "sg:classifiers":[
        {
            "category":"Professional",
            "subcategory":"Management & Consulting",
            "type":"Services"
        }
    ],
    "sg:phone":"+1 214 226 0889",
    "sg:postcode":"75252",
    "sg:province":"TX",
    "sg:tags":[
        "sales"
    ],
    "wof:name":"Elefant Boogerz",
    "wof:placetype":"venue"
},
  "geometry": {"coordinates":[-96.776826,32.997819],"type":"Point"}
}