{
  "type": "Feature",
  "properties": {
    "iso:country":"US",
    "sg:address":"3600 Mount Vernon St",
    "sg:city":"Houston",
    "sg:classifiers":[
        {
            "category":"Professional",
            "subcategory":"Accounting & Tax Preparation",
            "type":"Services"
        }
    ],
    "sg:phone":"+1 713 520 8099",
    "sg:postcode":"77006",
    "sg:province":"TX",
    "wof:name":"Julie Sysco C P A",
    "wof:placetype":"venue"
},
  "geometry": {"coordinates":[-95.39375099999999,29.739601],"type":"Point"}
}