{
  "type": "Feature",
  "properties": {
    "iso:country":"US",
    "sg:address":"6415 N Mesa St",
    "sg:city":"El Paso",
    "sg:classifiers":[
        {
            "category":"Professional",
            "subcategory":"Business Services",
            "type":"Services"
        }
    ],
    "sg:phone":"+1 915 845 5991",
    "sg:postcode":"79912",
    "sg:province":"TX",
    "sg:tags":[
        "interior",
        "consultant",
        "design",
        "decorator"
    ],
    "wof:name":"Designs Unlimited",
    "wof:placetype":"venue"
},
  "geometry": {"coordinates":[-106.53769800000001,31.833023],"type":"Point"}
}