{
  "type": "Feature",
  "properties": {
    "iso:country":"US",
    "sg:address":"4701 Monterey Oaks Blvd",
    "sg:city":"Austin",
    "sg:classifiers":[
        {
            "category":"Real Estate",
            "subcategory":"Real Estate Operator",
            "type":"Services"
        }
    ],
    "sg:phone":"+1 512 899 9300",
    "sg:postcode":"78749",
    "sg:province":"TX",
    "sg:tags":[
        "building",
        "apartment"
    ],
    "wof:name":"Amli At Monterey Oaks",
    "wof:placetype":"venue"
},
  "geometry": {"coordinates":[-97.840352,30.232325],"type":"Point"}
}