{
  "type": "Feature",
  "properties": {
    "iso:country":"US",
    "sg:address":"16934 Nevisway St",
    "sg:city":"Houston",
    "sg:classifiers":[
        {
            "category":"Banks & Credit Unions",
            "subcategory":"Bank",
            "type":"Services"
        }
    ],
    "sg:phone":"+1 281 550 4228",
    "sg:postcode":"77084",
    "sg:province":"TX",
    "wof:name":"Lions Eye Bank Of Texas",
    "wof:placetype":"venue"
},
  "geometry": {"coordinates":[-95.660223,29.843168],"type":"Point"}
}