{
  "type": "Feature",
  "properties": {
    "iso:country":"US",
    "sg:address":"4650 Woodrow Bean Transmountain Rd",
    "sg:city":"El Paso",
    "sg:classifiers":[
        {
            "category":"Banks & Credit Unions",
            "subcategory":"Bank",
            "type":"Services"
        }
    ],
    "sg:phone":"+1 915 759 6075",
    "sg:postcode":"79924",
    "sg:province":"TX",
    "sg:tags":[
        "financing"
    ],
    "wof:name":"American General Finance",
    "wof:placetype":"venue"
},
  "geometry": {"coordinates":[-106.43533499999999,31.898456],"type":"Point"}
}