{
  "type": "Feature",
  "properties": {
    "iso:country":"US",
    "sg:address":"20 Meridian Dr",
    "sg:city":"Wimberley",
    "sg:classifiers":[
        {
            "category":"Professional",
            "subcategory":"Computer Services",
            "type":"Services"
        }
    ],
    "sg:phone":"+1 512 847 0842",
    "sg:postcode":"78676",
    "sg:province":"TX",
    "sg:tags":[
        "prepackaged",
        "software"
    ],
    "wof:name":"Blue Streak Software Co",
    "wof:placetype":"venue"
},
  "geometry": {"coordinates":[-98.079471,29.978094],"type":"Point"}
}