{
  "type": "Feature",
  "properties": {
    "iso:country":"US",
    "sg:address":"220 E Alamo St",
    "sg:city":"Brenham",
    "sg:classifiers":[
        {
            "category":"Food & Beverages",
            "subcategory":"Specialty",
            "type":"Retail Goods"
        }
    ],
    "sg:phone":"+1 979 277 9997",
    "sg:postcode":"77833",
    "sg:province":"TX",
    "wof:name":"J M C Health Corporation",
    "wof:placetype":"venue"
},
  "geometry": {"coordinates":[-96.396823,30.166859],"type":"Point"}
}