{
  "type": "Feature",
  "properties": {
    "iso:country":"US",
    "sg:address":"114 N 31st St",
    "sg:city":"Temple",
    "sg:classifiers":[
        {
            "category":"Restaurant",
            "type":"Food & Drink"
        }
    ],
    "sg:menulink":"http://www.allmenus.com/tx/temple/179407-chick-fil-a/menu/",
    "sg:phone":"+1 254 771 2020",
    "sg:postcode":"76504",
    "sg:province":"TX",
    "sg:tags":[
        "wrap",
        "soup",
        "american",
        "sandwich",
        "salad"
    ],
    "wof:name":"Chick-fil-A",
    "wof:placetype":"venue"
},
  "geometry": {"coordinates":[-97.357209,31.102413],"type":"Point"}
}