{
  "type": "Feature",
  "properties": {
    "iso:country":"US",
    "sg:address":"2012 W Nathan Lowe Rd",
    "sg:city":"Arlington",
    "sg:classifiers":[
        {
            "category":"Restaurant",
            "type":"Food & Drink"
        }
    ],
    "sg:phone":"+1 817 927 2867",
    "sg:postcode":"76017",
    "sg:province":"TX",
    "sg:tags":[
        "management"
    ],
    "wof:name":"H2 LLC",
    "wof:placetype":"venue"
},
  "geometry": {"coordinates":[-97.138289,32.655101],"type":"Point"}
}