{
  "type": "Feature",
  "properties": {
    "iso:country":"US",
    "sg:address":"7208 Gaston Ave",
    "sg:city":"Dallas",
    "sg:classifiers":[
        {
            "category":"Education",
            "subcategory":"University",
            "type":"Public Place"
        }
    ],
    "sg:phone":"+1 214 321 5585",
    "sg:postcode":"75214",
    "sg:province":"TX",
    "sg:tags":[
        "college"
    ],
    "wof:name":"Sam Houston State University Dallas Office",
    "wof:placetype":"venue"
},
  "geometry": {"coordinates":[-96.732617,32.812945],"type":"Point"}
}