{
  "type": "Feature",
  "properties": {
    "iso:country":"US",
    "sg:address":"9988 Alexa Pl",
    "sg:city":"San Antonio",
    "sg:classifiers":[
        {
            "category":"Professional",
            "type":"Services"
        }
    ],
    "sg:phone":"+1 210 520 4640",
    "sg:postcode":"78251",
    "sg:province":"TX",
    "wof:name":"Dtg Games",
    "wof:placetype":"venue"
},
  "geometry": {"coordinates":[-98.680987,29.482616],"type":"Point"}
}