{
  "type": "Feature",
  "properties": {
    "iso:country":"US",
    "sg:address":"7111 Harwin Dr",
    "sg:city":"Houston",
    "sg:classifiers":[
        {
            "category":"Professional",
            "subcategory":"Management & Consulting",
            "type":"Services"
        }
    ],
    "sg:phone":"+1 281 235 4790",
    "sg:postcode":"77036",
    "sg:province":"TX",
    "sg:tags":[
        "manages",
        "residential",
        "property",
        "unit",
        "owns"
    ],
    "wof:name":"Southern Meadows Rlty & Dev Co",
    "wof:placetype":"venue"
},
  "geometry": {"coordinates":[-95.50909299999999,29.717903],"type":"Point"}
}