{
  "type": "Feature",
  "properties": {
    "iso:country":"US",
    "sg:address":"700 Rockmead Dr",
    "sg:city":"Humble",
    "sg:classifiers":[
        {
            "category":"Professional",
            "type":"Services"
        }
    ],
    "sg:phone":"+1 281 359 6334",
    "sg:postcode":"77339",
    "sg:province":"TX",
    "sg:tags":[
        "establishment"
    ],
    "wof:name":"Matrixx LTD",
    "wof:placetype":"venue"
},
  "geometry": {"coordinates":[-95.24420600000001,30.053232],"type":"Point"}
}