{
  "type": "Feature",
  "properties": {
    "iso:country":"US",
    "sg:address":"1665 Fox Ln",
    "sg:city":"Burleson",
    "sg:classifiers":[
        {
            "category":"Professional",
            "type":"Services"
        }
    ],
    "sg:phone":"+1 817 927 0012",
    "sg:postcode":"76028",
    "sg:province":"TX",
    "wof:name":"Lacadena Inc",
    "wof:placetype":"venue"
},
  "geometry": {"coordinates":[-97.277458,32.542175],"type":"Point"}
}