{
  "type": "Feature",
  "properties": {
    "iso:country":"US",
    "sg:address":"112 E Murray St",
    "sg:city":"Denison",
    "sg:classifiers":[
        {
            "category":"Professional",
            "type":"Services"
        }
    ],
    "sg:phone":"+1 903 463 9754",
    "sg:postcode":"75021",
    "sg:province":"TX",
    "wof:name":"Standing Eagle",
    "wof:placetype":"venue"
},
  "geometry": {"coordinates":[-96.534513,33.741854],"type":"Point"}
}