{
  "type": "Feature",
  "properties": {
    "iso:country":"US",
    "sg:address":"9109 Long Point Rd",
    "sg:city":"Houston",
    "sg:classifiers":[
        {
            "category":"Banks & Credit Unions",
            "subcategory":"Bank",
            "type":"Services"
        }
    ],
    "sg:phone":"+1 713 365 9133",
    "sg:postcode":"77055",
    "sg:province":"TX",
    "sg:tags":[
        "loan"
    ],
    "wof:name":"Atlas Credit Co",
    "wof:placetype":"venue"
},
  "geometry": {"coordinates":[-95.51436200000001,29.799953],"type":"Point"}
}