{
  "type": "Feature",
  "properties": {
    "iso:country":"US",
    "sg:address":"3252 Darvany Dr",
    "sg:city":"Dallas",
    "sg:classifiers":[
        {
            "category":"Building & Trades",
            "subcategory":"Landscaping Services",
            "type":"Services"
        }
    ],
    "sg:phone":"+1 214 956 8314",
    "sg:postcode":"75220",
    "sg:province":"TX",
    "sg:tags":[
        "lawn",
        "maintenance",
        "grounds"
    ],
    "wof:name":"Rick's Lawn Care",
    "wof:placetype":"venue"
},
  "geometry": {"coordinates":[-96.869135,32.878052],"type":"Point"}
}