{
  "type": "Feature",
  "properties": {
    "iso:country":"US",
    "sg:address":"3101 Senior Rd",
    "sg:city":"Missouri City",
    "sg:classifiers":[
        {
            "category":"Communications",
            "subcategory":"Television Station",
            "type":"Services"
        }
    ],
    "sg:phone":"+1 281 835 3181",
    "sg:postcode":"77459",
    "sg:province":"TX",
    "wof:name":"Channel 61",
    "wof:placetype":"venue"
},
  "geometry": {"coordinates":[-95.50409999999999,29.553067],"type":"Point"}
}