{
  "type": "Feature",
  "properties": {
    "iso:country":"US",
    "sg:address":"814 Castle Ridge Rd",
    "sg:city":"Austin",
    "sg:classifiers":[
        {
            "category":"Professional",
            "type":"Services"
        }
    ],
    "sg:phone":"+1 512 328 1668",
    "sg:postcode":"78746",
    "sg:province":"TX",
    "wof:name":"Ireplicate Inc",
    "wof:placetype":"venue"
},
  "geometry": {"coordinates":[-97.83189299999999,30.291889],"type":"Point"}
}