{
  "type": "Feature",
  "properties": {
    "iso:country":"US",
    "sg:address":"4802 Balcones Dr",
    "sg:city":"Austin",
    "sg:classifiers":[
        {
            "category":"Real Estate",
            "subcategory":"Architect",
            "type":"Services"
        }
    ],
    "sg:phone":"+1 512 451 9880",
    "sg:postcode":"78731",
    "sg:province":"TX",
    "sg:tags":[
        "commercial",
        "design",
        "architectural"
    ],
    "wof:name":"Studio B",
    "wof:placetype":"venue"
},
  "geometry": {"coordinates":[-97.76306099999999,30.331838],"type":"Point"}
}