{
  "type": "Feature",
  "properties": {
    "iso:country":"US",
    "sg:address":"4553 Crooked Ridge Dr",
    "sg:city":"Lewisville",
    "sg:classifiers":[
        {
            "category":"Communications",
            "subcategory":"Film & Video Production",
            "type":"Services"
        }
    ],
    "sg:phone":"+1 972 625 0437",
    "sg:postcode":"75056",
    "sg:province":"TX",
    "sg:tags":[
        "motion"
    ],
    "wof:name":"Axis Productions",
    "wof:placetype":"venue"
},
  "geometry": {"coordinates":[-96.898126,33.07189],"type":"Point"}
}