{
  "type": "Feature",
  "properties": {
    "iso:country":"US",
    "sg:address":"6410 Spanish Earth",
    "sg:city":"San Antonio",
    "sg:classifiers":[
        {
            "category":"Professional",
            "subcategory":"Computer Services",
            "type":"Services"
        }
    ],
    "sg:phone":"+1 210 656 3014",
    "sg:postcode":"78233",
    "sg:province":"TX",
    "wof:name":"Digital Fortress Inc",
    "wof:placetype":"venue"
},
  "geometry": {"coordinates":[-98.365325,29.578623],"type":"Point"}
}