{
  "type": "Feature",
  "properties": {
    "iso:country":"US",
    "sg:address":"6002 Slide Rd",
    "sg:city":"Lubbock",
    "sg:classifiers":[
        {
            "category":"Shopping",
            "type":"Retail Goods"
        }
    ],
    "sg:phone":"+1 806 792 4189",
    "sg:postcode":"79414",
    "sg:province":"TX",
    "sg:tags":[
        "telephone",
        "cellular"
    ],
    "wof:name":"Radio Shack",
    "wof:placetype":"venue"
},
  "geometry": {"coordinates":[-101.92247399999999,33.538754],"type":"Point"}
}