{
  "type": "Feature",
  "properties": {
    "iso:country":"US",
    "sg:address":"6619 Chimney Rock Rd",
    "sg:city":"Houston",
    "sg:classifiers":[
        {
            "category":"Food & Beverages",
            "subcategory":"Meat & Fish",
            "type":"Retail Goods"
        }
    ],
    "sg:phone":"+1 713 666 4204",
    "sg:postcode":"77081",
    "sg:province":"TX",
    "sg:tags":[
        "shop"
    ],
    "wof:name":"Quick Stop Meat Market",
    "wof:placetype":"venue"
},
  "geometry": {"coordinates":[-95.476097,29.708599],"type":"Point"}
}