{
  "type": "Feature",
  "properties": {
    "iso:country":"US",
    "sg:address":"1221 McKinney St Ste 4300",
    "sg:city":"Houston",
    "sg:classifiers":[
        {
            "category":"Professional",
            "subcategory":"Lawyer & Legal Services",
            "type":"Services"
        }
    ],
    "sg:phone":"+1 713 222 9542",
    "sg:postcode":"77010",
    "sg:province":"TX",
    "wof:name":"Book William C Atty",
    "wof:placetype":"venue"
},
  "geometry": {"coordinates":[-95.362999,29.7558],"type":"Point"}
}