{
  "type": "Feature",
  "properties": {
    "iso:country":"US",
    "sg:address":"10610 Bobbie Ln",
    "sg:city":"Pilot Point",
    "sg:classifiers":[
        {
            "category":"Professional",
            "type":"Services"
        }
    ],
    "sg:phone":"+1 940 686 0603",
    "sg:postcode":"76258",
    "sg:province":"TX",
    "wof:name":"Ronald B Riney",
    "wof:placetype":"venue"
},
  "geometry": {"coordinates":[-96.936233,33.36109],"type":"Point"}
}