{
  "type": "Feature",
  "properties": {
    "iso:country":"US",
    "sg:address":"4500 Highway 6 N # D",
    "sg:city":"Houston",
    "sg:classifiers":[
        {
            "category":"Health Services",
            "subcategory":"Health Practitioner",
            "type":"Services"
        },
        {
            "category":"Health Services",
            "subcategory":"Chiropractor",
            "type":"Services"
        }
    ],
    "sg:phone":"+1 866 844 9304",
    "sg:postcode":"77084",
    "sg:province":"TX",
    "sg:tags":[
        "homeopathic",
        "chiropractic"
    ],
    "sg:website":"http://local.ingenio.com/Listings/Details.aspx?NUM=a%3a9803803%3a13%3a4859924%3a14%3a0%3a7",
    "wof:name":"Chiropractic Plus",
    "wof:placetype":"venue"
},
  "geometry": {"coordinates":[-95.64568300000001,29.839727],"type":"Point"}
}