{
  "type": "Feature",
  "properties": {
    "iso:country":"US",
    "sg:address":"4800 Spring Ave",
    "sg:city":"Dallas",
    "sg:classifiers":[
        {
            "category":"Organizations",
            "subcategory":"Religious Organization",
            "type":"Services"
        }
    ],
    "sg:phone":"+1 214 426 5595",
    "sg:postcode":"75210",
    "sg:province":"TX",
    "wof:name":"Urban Action Center",
    "wof:placetype":"venue"
},
  "geometry": {"coordinates":[-96.739746,32.776322],"type":"Point"}
}