{
  "type": "Feature",
  "properties": {
    "iso:country":"US",
    "sg:address":"1919 Sealy St",
    "sg:city":"Galveston",
    "sg:classifiers":[
        {
            "category":"Professional",
            "subcategory":"Lawyer & Legal Services",
            "type":"Services"
        }
    ],
    "sg:phone":"+1 409 762 8960",
    "sg:postcode":"77550",
    "sg:province":"TX",
    "sg:tags":[
        "attorney",
        "criminal",
        "law"
    ],
    "sg:website":"http://www.walker-law-firm.com",
    "wof:name":"Walker, David, Law Offices Of",
    "wof:placetype":"venue"
},
  "geometry": {"coordinates":[-94.78790600000001,29.302185],"type":"Point"}
}