{
  "type": "Feature",
  "properties": {
    "iso:country":"US",
    "sg:address":"5102 Michael Dr",
    "sg:city":"Houston",
    "sg:classifiers":[
        {
            "category":"Retail",
            "subcategory":"Repair Shop",
            "type":"Services"
        }
    ],
    "sg:phone":"+1 713 649 3214",
    "sg:postcode":"77017",
    "sg:province":"TX",
    "wof:name":"National S E M Service",
    "wof:placetype":"venue"
},
  "geometry": {"coordinates":[-95.250317,29.688385],"type":"Point"}
}