{
  "type": "Feature",
  "properties": {
    "iso:country":"US",
    "sg:address":"4817 Bissonnet St",
    "sg:city":"Bellaire",
    "sg:classifiers":[
        {
            "category":"Shopping",
            "subcategory":"Used Merchandise",
            "type":"Retail Goods"
        }
    ],
    "sg:phone":"+1 713 661 2222",
    "sg:postcode":"77401",
    "sg:province":"TX",
    "sg:tags":[
        "antique"
    ],
    "wof:name":"Bellaux Antiques",
    "wof:placetype":"venue"
},
  "geometry": {"coordinates":[-95.463481,29.709837],"type":"Point"}
}