{
  "type": "Feature",
  "properties": {
    "iso:country":"US",
    "sg:address":"622 Ogden Ln",
    "sg:city":"San Antonio",
    "sg:classifiers":[
        {
            "category":"Banks & Credit Unions",
            "subcategory":"Financial Services",
            "type":"Services"
        }
    ],
    "sg:phone":"+1 210 930 6932",
    "sg:postcode":"78209",
    "sg:province":"TX",
    "sg:tags":[
        "trust",
        "nonprofit",
        "management"
    ],
    "wof:name":"Collins Family Foundation",
    "wof:placetype":"venue"
},
  "geometry": {"coordinates":[-98.474908,29.481215],"type":"Point"}
}