{
  "type": "Feature",
  "properties": {
    "iso:country":"US",
    "sg:address":"421 S Main St",
    "sg:city":"Big Spring",
    "sg:classifiers":[
        {
            "category":"Shopping",
            "subcategory":"Stationery & Office Supplies",
            "type":"Retail Goods"
        }
    ],
    "sg:phone":"+1 432 263 3509",
    "sg:postcode":"79720",
    "sg:province":"TX",
    "sg:tags":[
        "furniture"
    ],
    "wof:name":"Concho Business Solutions Inc",
    "wof:placetype":"venue"
},
  "geometry": {"coordinates":[-101.476114,32.251304],"type":"Point"}
}