{
  "type": "Feature",
  "properties": {
    "iso:country":"US",
    "sg:address":"8500 Hillcrest Ave",
    "sg:city":"Dallas",
    "sg:classifiers":[
        {
            "category":"Organizations",
            "subcategory":"Religious Organization",
            "type":"Services"
        }
    ],
    "sg:phone":"+1 214 706 0027",
    "sg:postcode":"75225",
    "sg:province":"TX",
    "sg:tags":[
        "clergy"
    ],
    "wof:name":"Gerald Klein",
    "wof:placetype":"venue"
},
  "geometry": {"coordinates":[-96.786682,32.865589],"type":"Point"}
}