{
  "type": "Feature",
  "properties": {
    "iso:country":"US",
    "sg:address":"4844 White Settlement Rd",
    "sg:city":"Fort Worth",
    "sg:classifiers":[
        {
            "category":"Autos & Motor Vehicles",
            "subcategory":"Auto Supplies",
            "type":"Retail Goods"
        }
    ],
    "sg:phone":"+1 817 989 8121",
    "sg:postcode":"76114",
    "sg:province":"TX",
    "wof:name":"White Settlement Tire Auto Svc",
    "wof:placetype":"venue"
},
  "geometry": {"coordinates":[-97.394632,32.760085],"type":"Point"}
}