{
  "type": "Feature",
  "properties": {
    "iso:country":"US",
    "sg:address":"147 Greenhill Pass",
    "sg:city":"San Antonio",
    "sg:classifiers":[
        {
            "category":"Building & Trades",
            "subcategory":"Construction",
            "type":"Services"
        }
    ],
    "sg:phone":"+1 210 340 5174",
    "sg:postcode":"78213",
    "sg:province":"TX",
    "sg:tags":[
        "concrete",
        "contractor"
    ],
    "wof:name":"Conco Concrete",
    "wof:placetype":"venue"
},
  "geometry": {"coordinates":[-98.528576,29.508211],"type":"Point"}
}