{
  "type": "Feature",
  "properties": {
    "iso:country":"US",
    "sg:address":"136 Parkwood Ave",
    "sg:city":"Arlington",
    "sg:classifiers":[
        {
            "category":"Manufacturing",
            "subcategory":"Metals",
            "type":"Manufacturing & Wholesale Goods"
        }
    ],
    "sg:phone":"+1 817 247 6877",
    "sg:postcode":"76013",
    "sg:province":"TX",
    "sg:tags":[
        "product",
        "primary"
    ],
    "wof:name":"Dreamsmith Metalworks",
    "wof:placetype":"venue"
},
  "geometry": {"coordinates":[-97.129189,32.729785],"type":"Point"}
}