{
  "type": "Feature",
  "properties": {
    "iso:country":"US",
    "sg:address":"1206 Sam Houston Ave",
    "sg:city":"Huntsville",
    "sg:classifiers":[
        {
            "category":"Professional",
            "subcategory":"Accounting & Tax Preparation",
            "type":"Services"
        },
        {
            "category":"Banks & Credit Unions",
            "subcategory":"Financial Services",
            "type":"Services"
        }
    ],
    "sg:phone":"+1 936 291 2291",
    "sg:postcode":"77340",
    "sg:province":"TX",
    "sg:tags":[
        "financing",
        "return",
        "loan",
        "preparation-business"
    ],
    "sg:website":"http://www.security-finance.com",
    "wof:name":"Sunbelt Credit",
    "wof:placetype":"venue"
},
  "geometry": {"coordinates":[-95.551433,30.722719],"type":"Point"}
}