{
  "type": "Feature",
  "properties": {
    "iso:country":"US",
    "sg:address":"146 Industrial St",
    "sg:city":"Lancaster",
    "sg:classifiers":[
        {
            "category":"Wholesale",
            "subcategory":"Chemicals & Plastics",
            "type":"Manufacturing & Wholesale Goods"
        }
    ],
    "sg:phone":"+1 972 227 4466",
    "sg:postcode":"75134",
    "sg:province":"TX",
    "wof:name":"Anko Products Inc",
    "wof:placetype":"venue"
},
  "geometry": {"coordinates":[-96.73968600000001,32.612983],"type":"Point"}
}