{
  "type": "Feature",
  "properties": {
    "iso:country":"US",
    "sg:address":"2105 Buena Vista St",
    "sg:city":"San Antonio",
    "sg:classifiers":[
        {
            "category":"Organizations",
            "subcategory":"Religious Organization",
            "type":"Services"
        }
    ],
    "sg:phone":"+1 210 226 9965",
    "sg:postcode":"78207",
    "sg:province":"TX",
    "sg:tags":[
        "church"
    ],
    "wof:name":"Victory Temple",
    "wof:placetype":"venue"
},
  "geometry": {"coordinates":[-98.522459,29.426728],"type":"Point"}
}