{
  "type": "Feature",
  "properties": {
    "iso:country":"US",
    "sg:address":"1004 Jarvis Ln",
    "sg:city":"Azle",
    "sg:classifiers":[
        {
            "category":"Professional",
            "subcategory":"Computer Services",
            "type":"Services"
        }
    ],
    "sg:phone":"+1 817 270 0227",
    "sg:postcode":"76020",
    "sg:province":"TX",
    "wof:name":"Express On Site Computers",
    "wof:placetype":"venue"
},
  "geometry": {"coordinates":[-97.524771,32.893145],"type":"Point"}
}