{
  "type": "Feature",
  "properties": {
    "iso:country":"US",
    "sg:address":"5928 Cabrillo Dr",
    "sg:city":"El Paso",
    "sg:classifiers":[
        {
            "category":"Organizations",
            "subcategory":"Community Association",
            "type":"Services"
        }
    ],
    "sg:phone":"+1 915 581 8909",
    "sg:postcode":"79912",
    "sg:province":"TX",
    "wof:name":"Kiwanis Club of Mt Frankl",
    "wof:placetype":"venue"
},
  "geometry": {"coordinates":[-106.539751,31.822682],"type":"Point"}
}