{
  "type": "Feature",
  "properties": {
    "iso:country":"US",
    "sg:address":"2261 Crown Rd",
    "sg:city":"Dallas",
    "sg:classifiers":[
        {
            "category":"Building & Trades",
            "subcategory":"Construction",
            "type":"Services"
        }
    ],
    "sg:phone":"+1 972 247 7919",
    "sg:postcode":"75229",
    "sg:province":"TX",
    "sg:tags":[
        "designer",
        "contractor",
        "pool",
        "dealer",
        "merchandise",
        "swimming"
    ],
    "wof:name":"Southwestern Tile and Coping",
    "wof:placetype":"venue"
},
  "geometry": {"coordinates":[-96.90452500000001,32.900535],"type":"Point"}
}