{
  "type": "Feature",
  "properties": {
    "iso:country":"US",
    "sg:address":"5813 Esplanade Dr",
    "sg:city":"Corpus Christi",
    "sg:classifiers":[
        {
            "category":"Social Services",
            "subcategory":"Adult Care",
            "type":"Services"
        }
    ],
    "sg:phone":"+1 361 991 9600",
    "sg:postcode":"78414",
    "sg:province":"TX",
    "sg:tags":[
        "residential",
        "developer"
    ],
    "wof:name":"Merrill Gardens",
    "wof:placetype":"venue"
},
  "geometry": {"coordinates":[-97.37768800000001,27.687511],"type":"Point"}
}