{
  "type": "Feature",
  "properties": {
    "iso:country":"US",
    "sg:address":"17665 Briarpatch",
    "sg:city":"Lindale",
    "sg:classifiers":[
        {
            "category":"Insurance",
            "subcategory":"Insurance Agent",
            "type":"Services"
        }
    ],
    "sg:phone":"+1 903 882 1113",
    "sg:postcode":"75771",
    "sg:province":"TX",
    "wof:name":"Educators Financial Seminars",
    "wof:placetype":"venue"
},
  "geometry": {"coordinates":[-95.379976,32.525576],"type":"Point"}
}