{
  "type": "Feature",
  "properties": {
    "iso:country":"US",
    "sg:address":"1500 Lakeshore Dr",
    "sg:city":"Port Arthur",
    "sg:classifiers":[
        {
            "category":"Education",
            "subcategory":"School",
            "type":"Public Place"
        }
    ],
    "sg:phone":"+1 409 985 9347",
    "sg:postcode":"77640",
    "sg:province":"TX",
    "wof:name":"Woodrow Wilson Middle School",
    "wof:placetype":"venue"
},
  "geometry": {"coordinates":[-93.92549699999999,29.879744],"type":"Point"}
}