{
  "type": "Feature",
  "properties": {
    "iso:country":"US",
    "sg:address":"15839 Nedra Way",
    "sg:city":"Dallas",
    "sg:classifiers":[
        {
            "category":"Professional",
            "subcategory":"Management & Consulting",
            "type":"Services"
        }
    ],
    "sg:phone":"+1 972 980 8047",
    "sg:postcode":"75248",
    "sg:province":"TX",
    "sg:tags":[
        "public",
        "relations"
    ],
    "wof:name":"Cindy Birne Productions",
    "wof:placetype":"venue"
},
  "geometry": {"coordinates":[-96.79262799999999,32.965644],"type":"Point"}
}