{
  "type": "Feature",
  "properties": {
    "iso:country":"US",
    "sg:address":"805 Plymouth Ln",
    "sg:city":"Laredo",
    "sg:classifiers":[
        {
            "category":"Real Estate",
            "subcategory":"Real Estate Agent",
            "type":"Services"
        }
    ],
    "sg:phone":"+1 956 722 7989",
    "sg:postcode":"78041",
    "sg:province":"TX",
    "wof:name":"Visual Realty",
    "wof:placetype":"venue"
},
  "geometry": {"coordinates":[-99.474727,27.567375],"type":"Point"}
}