{
  "type": "Feature",
  "properties": {
    "iso:country":"US",
    "sg:address":"2116 Broadway St",
    "sg:city":"Lubbock",
    "sg:classifiers":[
        {
            "category":"Insurance",
            "subcategory":"Insurance Agent",
            "type":"Services"
        }
    ],
    "sg:phone":"+1 806 741 1050",
    "sg:postcode":"79401",
    "sg:province":"TX",
    "wof:name":"Scioli Group",
    "wof:placetype":"venue"
},
  "geometry": {"coordinates":[-101.86380699999999,33.584539],"type":"Point"}
}