{
  "type": "Feature",
  "properties": {
    "iso:country":"US",
    "sg:address":"9314 Puritan Way",
    "sg:city":"Rosharon",
    "sg:classifiers":[
        {
            "category":"Professional",
            "subcategory":"Art Services",
            "type":"Services"
        }
    ],
    "sg:phone":"+1 281 431 0907",
    "sg:postcode":"77583",
    "sg:province":"TX",
    "sg:tags":[
        "graphic",
        "commercial",
        "designer",
        "artist"
    ],
    "wof:name":"Dvr Graphics",
    "wof:placetype":"venue"
},
  "geometry": {"coordinates":[-95.403181,29.448047],"type":"Point"}
}