{
  "type": "Feature",
  "properties": {
    "iso:country":"US",
    "sg:address":"3925 Delaware St",
    "sg:city":"Beaumont",
    "sg:classifiers":[
        {
            "category":"Shopping",
            "subcategory":"Florist",
            "type":"Retail Goods"
        }
    ],
    "sg:phone":"+1 409 898 7740",
    "sg:postcode":"77706",
    "sg:province":"TX",
    "wof:name":"Beaumont Greenery",
    "wof:placetype":"venue"
},
  "geometry": {"coordinates":[-94.14407799999999,30.104353],"type":"Point"}
}