{
  "type": "Feature",
  "properties": {
    "iso:country":"US",
    "sg:address":"10716 Fm 902",
    "sg:city":"Collinsville",
    "sg:classifiers":[
        {
            "category":"Building & Trades",
            "subcategory":"Electrical",
            "type":"Services"
        }
    ],
    "sg:phone":"+1 903 429 9115",
    "sg:postcode":"76233",
    "sg:province":"TX",
    "sg:tags":[
        "control",
        "regulator",
        "system",
        "controls"
    ],
    "wof:name":"Regulatory Management Systems",
    "wof:placetype":"venue"
},
  "geometry": {"coordinates":[-96.949152,33.553848],"type":"Point"}
}