{
  "type": "Feature",
  "properties": {
    "iso:country":"US",
    "sg:address":"1006 W University Dr",
    "sg:city":"Denton",
    "sg:classifiers":[
        {
            "category":"Restaurant",
            "type":"Food & Drink"
        }
    ],
    "sg:phone":"+1 940 383 3832",
    "sg:postcode":"76201",
    "sg:province":"TX",
    "sg:tags":[
        "eating"
    ],
    "wof:name":"Evergreen Super Buffet",
    "wof:placetype":"venue"
},
  "geometry": {"coordinates":[-97.14308800000001,33.229786],"type":"Point"}
}