{
  "type": "Feature",
  "properties": {
    "iso:country":"US",
    "sg:address":"7026 Scott St",
    "sg:city":"Houston",
    "sg:classifiers":[
        {
            "category":"Food & Beverages",
            "subcategory":"Groceries & Convenience Stores",
            "type":"Retail Goods"
        }
    ],
    "sg:phone":"+1 713 747 3828",
    "sg:postcode":"77021",
    "sg:province":"TX",
    "wof:name":"Good Mart Food Store",
    "wof:placetype":"venue"
},
  "geometry": {"coordinates":[-95.36370100000001,29.688999],"type":"Point"}
}