{
  "type": "Feature",
  "properties": {
    "iso:country":"US",
    "sg:address":"708 E 15th St",
    "sg:city":"Plano",
    "sg:classifiers":[
        {
            "category":"Health Services",
            "subcategory":"Optometrist",
            "type":"Services"
        }
    ],
    "sg:phone":"+1 972 509 8555",
    "sg:postcode":"75074",
    "sg:province":"TX",
    "wof:name":"Jenny Fan OD Pa",
    "wof:placetype":"venue"
},
  "geometry": {"coordinates":[-96.70560399999999,33.019568],"type":"Point"}
}