{
  "type": "Feature",
  "properties": {
    "iso:country":"US",
    "sg:address":"7355 Alabonson Rd",
    "sg:city":"Houston",
    "sg:classifiers":[
        {
            "category":"Food & Beverages",
            "subcategory":"Groceries & Convenience Stores",
            "type":"Retail Goods"
        }
    ],
    "sg:phone":"+1 713 937 8668",
    "sg:postcode":"77088",
    "sg:province":"TX",
    "wof:name":"Exprees Stop No 3",
    "wof:placetype":"venue"
},
  "geometry": {"coordinates":[-95.482803,29.8764],"type":"Point"}
}