{
  "type": "Feature",
  "properties": {
    "iso:country":"US",
    "sg:address":"702 S Bivins St",
    "sg:city":"Amarillo",
    "sg:classifiers":[
        {
            "category":"Building & Trades",
            "subcategory":"Construction",
            "type":"Services"
        }
    ],
    "sg:phone":"+1 806 371 0811",
    "sg:postcode":"79104",
    "sg:province":"TX",
    "sg:tags":[
        "concrete",
        "contractor"
    ],
    "wof:name":"Alamo Brothers Concrete",
    "wof:placetype":"venue"
},
  "geometry": {"coordinates":[-101.808443,35.20249],"type":"Point"}
}