{
  "type": "Feature",
  "properties": {
    "iso:country":"US",
    "sg:address":"506 N Main St",
    "sg:city":"Sweeny",
    "sg:classifiers":[
        {
            "category":"Restaurant",
            "type":"Food & Drink"
        }
    ],
    "sg:phone":"+1 979 548 4344",
    "sg:postcode":"77480",
    "sg:province":"TX",
    "sg:tags":[
        "asian",
        "chinese",
        "pan"
    ],
    "wof:name":"Golden Dragon",
    "wof:placetype":"venue"
},
  "geometry": {"coordinates":[-95.701258,29.040995],"type":"Point"}
}