{
  "type": "Feature",
  "properties": {
    "iso:country":"US",
    "sg:address":"3001 Twin Creek Dr",
    "sg:city":"Corpus Christi",
    "sg:classifiers":[
        {
            "category":"Building & Trades",
            "subcategory":"Construction",
            "type":"Services"
        }
    ],
    "sg:phone":"+1 361 992 9108",
    "sg:postcode":"78414",
    "sg:province":"TX",
    "sg:tags":[
        "residential"
    ],
    "wof:name":"MBS",
    "wof:placetype":"venue"
},
  "geometry": {"coordinates":[-97.353174,27.666528],"type":"Point"}
}