{
  "type": "Feature",
  "properties": {
    "iso:country":"US",
    "sg:address":"4500 Brass Way",
    "sg:city":"Dallas",
    "sg:classifiers":[
        {
            "category":"Wholesale",
            "subcategory":"Electrical",
            "type":"Manufacturing & Wholesale Goods"
        }
    ],
    "sg:phone":"+1 214 330 4791",
    "sg:postcode":"75236",
    "sg:province":"TX",
    "sg:tags":[
        "electric",
        "motor"
    ],
    "wof:name":"Texas Electric Motors Inc",
    "wof:placetype":"venue"
},
  "geometry": {"coordinates":[-96.896591,32.684359],"type":"Point"}
}