{
  "type": "Feature",
  "properties": {
    "iso:country":"US",
    "sg:address":"195 E Stenger St",
    "sg:city":"San Benito",
    "sg:classifiers":[
        {
            "category":"Retail",
            "subcategory":"Auto Repair",
            "type":"Services"
        }
    ],
    "sg:phone":"+1 956 399 9941",
    "sg:postcode":"78586",
    "sg:province":"TX",
    "sg:tags":[
        "shop",
        "automotive",
        "general"
    ],
    "wof:name":"Circle Y Garage",
    "wof:placetype":"venue"
},
  "geometry": {"coordinates":[-97.630951,26.132583],"type":"Point"}
}