{
  "type": "Feature",
  "properties": {
    "iso:country":"US",
    "sg:address":"2315 E Oltorp Congress",
    "sg:city":"Austin",
    "sg:classifiers":[
        {
            "category":"Shopping",
            "subcategory":"Florist",
            "type":"Retail Goods"
        }
    ],
    "sg:phone":"+1 512 444 7559",
    "sg:postcode":"78704",
    "sg:province":"TX",
    "wof:name":"Twin Oaks Florist",
    "wof:placetype":"venue"
},
  "geometry": {"coordinates":[-97.730862,30.229636],"type":"Point"}
}