{
  "type": "Feature",
  "properties": {
    "iso:country":"US",
    "sg:address":"15607 Township Glen Ln",
    "sg:city":"Cypress",
    "sg:classifiers":[
        {
            "category":"Freight",
            "type":"Transportation"
        }
    ],
    "sg:phone":"+1 281 373 3703",
    "sg:postcode":"77433",
    "sg:province":"TX",
    "sg:tags":[
        "operator",
        "local",
        "trucking"
    ],
    "wof:name":"Mangels Trucking Inc",
    "wof:placetype":"venue"
},
  "geometry": {"coordinates":[-95.739159,30.00038],"type":"Point"}
}