{
  "type": "Feature",
  "properties": {
    "iso:country":"US",
    "sg:address":"3774 Lake St",
    "sg:city":"Houston",
    "sg:classifiers":[
        {
            "category":"Building & Trades",
            "subcategory":"Construction",
            "type":"Services"
        }
    ],
    "sg:phone":"+1 713 942 9349",
    "sg:postcode":"77098",
    "sg:province":"TX",
    "sg:tags":[
        "house"
    ],
    "wof:name":"Paige Construction LLC",
    "wof:placetype":"venue"
},
  "geometry": {"coordinates":[-95.41992999999999,29.732957],"type":"Point"}
}