{
  "type": "Feature",
  "properties": {
    "iso:country":"US",
    "sg:address":"4207 Burnet Rd",
    "sg:city":"Austin",
    "sg:classifiers":[
        {
            "category":"Shopping",
            "subcategory":"Pharmacy",
            "type":"Retail Goods"
        }
    ],
    "sg:phone":"+1 512 706 1946",
    "sg:postcode":"78756",
    "sg:province":"TX",
    "wof:name":"Mariner",
    "wof:placetype":"venue"
},
  "geometry": {"coordinates":[-97.74244299999999,30.313881],"type":"Point"}
}