{
  "type": "Feature",
  "properties": {
    "iso:country":"US",
    "sg:address":"167 Fernwood St",
    "sg:city":"Bridge City",
    "sg:classifiers":[
        {
            "category":"Manufacturing",
            "subcategory":"Apparel",
            "type":"Manufacturing & Wholesale Goods"
        }
    ],
    "sg:phone":"+1 409 735 5044",
    "sg:postcode":"77611",
    "sg:province":"TX",
    "sg:tags":[
        "outerwear",
        "mfg"
    ],
    "wof:name":"Goodfellas",
    "wof:placetype":"venue"
},
  "geometry": {"coordinates":[-93.857236,30.036376],"type":"Point"}
}