{
  "type": "Feature",
  "properties": {
    "iso:country":"US",
    "sg:address":"3307 W Davis St",
    "sg:city":"Conroe",
    "sg:classifiers":[
        {
            "category":"Real Estate",
            "subcategory":"Real Estate Agent",
            "type":"Services"
        },
        {
            "category":"Professional",
            "subcategory":"Business Services",
            "type":"Services"
        }
    ],
    "sg:phone":"+1 936 441 1632",
    "sg:postcode":"77304",
    "sg:province":"TX",
    "sg:tags":[
        "preparation",
        "tax",
        "return",
        "appraiser"
    ],
    "wof:name":"Hogue Bernie L 3 & Assoc",
    "wof:placetype":"venue"
},
  "geometry": {"coordinates":[-95.485921,30.321008],"type":"Point"}
}