{
  "type": "Feature",
  "properties": {
    "iso:country":"US",
    "sg:address":"3200 Balboa Ave",
    "sg:city":"Mcallen",
    "sg:classifiers":[
        {
            "category":"Food & Beverages",
            "subcategory":"Groceries & Convenience Stores",
            "type":"Retail Goods"
        }
    ],
    "sg:phone":"+1 956 682 3870",
    "sg:postcode":"78503",
    "sg:province":"TX",
    "sg:tags":[
        "grocer"
    ],
    "wof:name":"Lee Drive-In Grocery",
    "wof:placetype":"venue"
},
  "geometry": {"coordinates":[-98.26181699999999,26.172138],"type":"Point"}
}