{
  "type": "Feature",
  "properties": {
    "iso:country":"US",
    "sg:address":"305 Wilson St",
    "sg:city":"Crowley",
    "sg:classifiers":[
        {
            "category":"Building & Trades",
            "subcategory":"Cleaning & Sanitation",
            "type":"Services"
        }
    ],
    "sg:phone":"+1 817 297 4525",
    "sg:postcode":"76036",
    "sg:province":"TX",
    "sg:tags":[
        "maintenance"
    ],
    "wof:name":"Ceiling & Wall Specialists",
    "wof:placetype":"venue"
},
  "geometry": {"coordinates":[-97.37074200000001,32.575489],"type":"Point"}
}