{
  "type": "Feature",
  "properties": {
    "iso:country":"US",
    "sg:address":"1517 Nantucket Dr",
    "sg:city":"Houston",
    "sg:classifiers":[
        {
            "category":"Professional",
            "type":"Services"
        }
    ],
    "sg:phone":"+1 713 334 6130",
    "sg:postcode":"77057",
    "sg:province":"TX",
    "wof:name":"Frank & Brenda Gallagher",
    "wof:placetype":"venue"
},
  "geometry": {"coordinates":[-95.487341,29.752076],"type":"Point"}
}