{
  "type": "Feature",
  "properties": {
    "iso:country":"US",
    "sg:address":"1220 Montana Ave",
    "sg:city":"El Paso",
    "sg:classifiers":[
        {
            "category":"Real Estate",
            "subcategory":"Real Estate Agent",
            "type":"Services"
        }
    ],
    "sg:phone":"+1 915 833 4000",
    "sg:postcode":"79902",
    "sg:province":"TX",
    "wof:name":"International Real Estate Cons",
    "wof:placetype":"venue"
},
  "geometry": {"coordinates":[-106.481267,31.770477],"type":"Point"}
}