{
  "type": "Feature",
  "properties": {
    "iso:country":"US",
    "sg:address":"209 South St",
    "sg:city":"Nevada",
    "sg:classifiers":[
        {
            "category":"Freight",
            "type":"Transportation"
        }
    ],
    "sg:phone":"+1 972 843 0172",
    "sg:postcode":"75173",
    "sg:province":"TX",
    "sg:tags":[
        "operator",
        "trucking"
    ],
    "wof:name":"Lugrand & Sons",
    "wof:placetype":"venue"
},
  "geometry": {"coordinates":[-96.37641000000001,33.035856],"type":"Point"}
}