{
  "type": "Feature",
  "properties": {
    "iso:country":"US",
    "sg:address":"1711 San Jacinto Blvd # 201",
    "sg:city":"Austin",
    "sg:classifiers":[
        {
            "category":"Government",
            "subcategory":"Office",
            "type":"Public Place"
        }
    ],
    "sg:phone":"+1 512 463 3960",
    "sg:postcode":"78701",
    "sg:province":"TX",
    "sg:website":"http://www.tfc.state.tx.us",
    "wof:name":"General Council",
    "wof:placetype":"venue"
},
  "geometry": {"coordinates":[-97.73634300000001,30.278303],"type":"Point"}
}