{
  "type": "Feature",
  "properties": {
    "iso:country":"US",
    "sg:address":"11668 Wild Rose Ln",
    "sg:city":"Anna",
    "sg:classifiers":[
        {
            "category":"Freight",
            "type":"Transportation"
        }
    ],
    "sg:phone":"+1 972 924 4804",
    "sg:postcode":"75409",
    "sg:province":"TX",
    "sg:tags":[
        "broker",
        "trucking"
    ],
    "wof:name":"CRST",
    "wof:placetype":"venue"
},
  "geometry": {"coordinates":[-96.488952,33.338808],"type":"Point"}
}