{
  "type": "Feature",
  "properties": {
    "iso:country":"US",
    "sg:address":"6899 Us Highway 190 W",
    "sg:city":"Pointblank",
    "sg:classifiers":[
        {
            "category":"Restaurant",
            "type":"Food & Drink"
        }
    ],
    "sg:menulink":"http://www.allmenus.com/tx/point-blank/66947-pizza-pro/menu/",
    "sg:phone":"+1 936 377 4400",
    "sg:postcode":"77364",
    "sg:province":"TX",
    "sg:tags":[
        "american",
        "pizza"
    ],
    "wof:name":"Pizza Pro",
    "wof:placetype":"venue"
},
  "geometry": {"coordinates":[-95.22150999999999,30.74755],"type":"Point"}
}