{
  "type": "Feature",
  "properties": {
    "iso:country":"US",
    "sg:address":"14915 Stuebner Airline Rd",
    "sg:city":"Houston",
    "sg:classifiers":[
        {
            "category":"Wholesale",
            "subcategory":"Office Equipment",
            "type":"Manufacturing & Wholesale Goods"
        }
    ],
    "sg:phone":"+1 281 893 3086",
    "sg:postcode":"77069",
    "sg:province":"TX",
    "sg:tags":[
        "system",
        "automation"
    ],
    "wof:name":"Business Equipment Repair Ctr",
    "wof:placetype":"venue"
},
  "geometry": {"coordinates":[-95.506855,29.999463],"type":"Point"}
}