{
  "type": "Feature",
  "properties": {
    "iso:country":"US",
    "sg:address":"1315 Central Fwy",
    "sg:city":"Wichita Falls",
    "sg:classifiers":[
        {
            "category":"Real Estate",
            "subcategory":"Real Estate Operator",
            "type":"Services"
        }
    ],
    "sg:phone":"+1 940 766 2838",
    "sg:postcode":"76302",
    "sg:province":"TX",
    "sg:tags":[
        "building",
        "apartment",
        "operates",
        "an"
    ],
    "wof:name":"Medlock Southwest Mgt Corp",
    "wof:placetype":"venue"
},
  "geometry": {"coordinates":[-98.46702000000001,33.885068],"type":"Point"}
}