{
  "type": "Feature",
  "properties": {
    "iso:country":"US",
    "sg:address":"1446 E Highway 377",
    "sg:city":"Granbury",
    "sg:classifiers":[
        {
            "category":"Shopping",
            "subcategory":"Beauty & Cosmetics",
            "type":"Retail Goods"
        }
    ],
    "sg:phone":"+1 817 573 5407",
    "sg:postcode":"76048",
    "sg:province":"TX",
    "sg:tags":[
        "perfume",
        "salons-equipment",
        "supply"
    ],
    "wof:name":"Merle Norman Cosmetics",
    "wof:placetype":"venue"
},
  "geometry": {"coordinates":[-97.764472,32.438469],"type":"Point"}
}