{
  "type": "Feature",
  "properties": {
    "iso:country":"US",
    "sg:address":"104 Isabella Dr",
    "sg:city":"El Paso",
    "sg:classifiers":[
        {
            "category":"Retail",
            "subcategory":"Repair Shop",
            "type":"Services"
        }
    ],
    "sg:phone":"+1 915 833 8583",
    "sg:postcode":"79912",
    "sg:province":"TX",
    "sg:tags":[
        "electrical"
    ],
    "wof:name":"Wayne D Rogers",
    "wof:placetype":"venue"
},
  "geometry": {"coordinates":[-106.536422,31.829053],"type":"Point"}
}