{
  "type": "Feature",
  "properties": {
    "iso:country":"US",
    "sg:address":"1612 Bedfordshire",
    "sg:city":"Bedford",
    "sg:classifiers":[
        {
            "category":"Manufacturing",
            "subcategory":"Chemicals & Compounds",
            "type":"Manufacturing & Wholesale Goods"
        }
    ],
    "sg:phone":"+1 817 283 1313",
    "sg:postcode":"76021",
    "sg:province":"TX",
    "sg:tags":[
        "chemicals-wholesale",
        "manufacturer"
    ],
    "wof:name":"Ray-Lin Enterprises",
    "wof:placetype":"venue"
},
  "geometry": {"coordinates":[-97.142285,32.847841],"type":"Point"}
}