{
  "type": "Feature",
  "properties": {
    "iso:country":"US",
    "sg:address":"708 Canyon Creek Trl",
    "sg:city":"Fort Worth",
    "sg:classifiers":[
        {
            "category":"Building & Trades",
            "subcategory":"Construction",
            "type":"Services"
        }
    ],
    "sg:phone":"+1 817 308 8361",
    "sg:postcode":"76112",
    "sg:province":"TX",
    "sg:tags":[
        "contractor"
    ],
    "wof:name":"Shane Jones Masonry",
    "wof:placetype":"venue"
},
  "geometry": {"coordinates":[-97.22073399999999,32.771474],"type":"Point"}
}