{
  "type": "Feature",
  "properties": {
    "iso:country":"US",
    "sg:address":"1385 Cuba Rd",
    "sg:city":"Bridgeport",
    "sg:classifiers":[
        {
            "category":"Organizations",
            "subcategory":"Religious Organization",
            "type":"Services"
        }
    ],
    "sg:phone":"+1 940 683 2085",
    "sg:postcode":"76426",
    "sg:province":"TX",
    "wof:name":"Lake Bridgeport Cmnty Church",
    "wof:placetype":"venue"
},
  "geometry": {"coordinates":[-97.70057799999999,33.228415],"type":"Point"}
}