{
  "type": "Feature",
  "properties": {
    "iso:country":"US",
    "sg:address":"11655 Gullwood Dr",
    "sg:city":"Houston",
    "sg:classifiers":[
        {
            "category":"Professional",
            "subcategory":"Accounting & Tax Preparation",
            "type":"Services"
        }
    ],
    "sg:phone":"+1 281 464 3899",
    "sg:postcode":"77089",
    "sg:province":"TX",
    "sg:tags":[
        "billing"
    ],
    "wof:name":"Aim Billing Services",
    "wof:placetype":"venue"
},
  "geometry": {"coordinates":[-95.209518,29.588372],"type":"Point"}
}