{
  "type": "Feature",
  "properties": {
    "iso:country":"US",
    "sg:address":"15819 Kenbriar Dr",
    "sg:city":"Missouri City",
    "sg:classifiers":[
        {
            "category":"Wholesale",
            "subcategory":"Vending Machines",
            "type":"Manufacturing & Wholesale Goods"
        }
    ],
    "sg:phone":"+1 281 415 1224",
    "sg:postcode":"77489",
    "sg:province":"TX",
    "sg:tags":[
        "operator"
    ],
    "wof:name":"Mc Enterprise",
    "wof:placetype":"venue"
},
  "geometry": {"coordinates":[-95.49582100000001,29.596963],"type":"Point"}
}