{
  "type": "Feature",
  "properties": {
    "iso:country":"US",
    "sg:address":"14403 Potts Dr",
    "sg:city":"Amarillo",
    "sg:classifiers":[
        {
            "category":"Building & Trades",
            "subcategory":"Construction",
            "type":"Services"
        }
    ],
    "sg:phone":"+1 806 655 2945",
    "sg:postcode":"79118",
    "sg:province":"TX",
    "sg:tags":[
        "repairing",
        "remodeling",
        "contractor"
    ],
    "wof:name":"A West Brothers Construction",
    "wof:placetype":"venue"
},
  "geometry": {"coordinates":[-101.910664,35.054406],"type":"Point"}
}