{
  "type": "Feature",
  "properties": {
    "iso:country":"US",
    "sg:address":"5953 Highland Hills Dr",
    "sg:city":"Austin",
    "sg:classifiers":[
        {
            "category":"Real Estate",
            "subcategory":"Architect",
            "type":"Services"
        }
    ],
    "sg:phone":"+1 512 453 8775",
    "sg:postcode":"78731",
    "sg:province":"TX",
    "wof:name":"Crier Jack S Archtct",
    "wof:placetype":"venue"
},
  "geometry": {"coordinates":[-97.757401,30.3463],"type":"Point"}
}