{
  "type": "Feature",
  "properties": {
    "iso:country":"US",
    "sg:address":"840 N Cage Blvd",
    "sg:city":"Pharr",
    "sg:classifiers":[
        {
            "category":"Banks & Credit Unions",
            "subcategory":"Bank",
            "type":"Services"
        }
    ],
    "sg:phone":"+1 956 668 3100",
    "sg:postcode":"78577",
    "sg:province":"TX",
    "sg:tags":[
        "saving",
        "commercial"
    ],
    "wof:name":"Frost National Bank",
    "wof:placetype":"venue"
},
  "geometry": {"coordinates":[-98.182659,26.202778],"type":"Point"}
}