{
  "type": "Feature",
  "properties": {
    "iso:country":"US",
    "sg:address":"1940 W Kilpatrick St",
    "sg:city":"Cleburne",
    "sg:classifiers":[
        {
            "category":"Real Estate",
            "subcategory":"Real Estate Agent",
            "type":"Services"
        }
    ],
    "sg:phone":"+1 817 645 7466",
    "sg:postcode":"76033",
    "sg:province":"TX",
    "sg:tags":[
        "management"
    ],
    "wof:name":"Nolan Ridge Property Mgmt",
    "wof:placetype":"venue"
},
  "geometry": {"coordinates":[-97.414575,32.360893],"type":"Point"}
}