{
  "type": "Feature",
  "properties": {
    "iso:country":"US",
    "sg:address":"2218 W Beauregard Ave",
    "sg:city":"San Angelo",
    "sg:classifiers":[
        {
            "category":"Personal",
            "subcategory":"Barber",
            "type":"Services"
        }
    ],
    "sg:phone":"+1 325 949 1888",
    "sg:postcode":"76901",
    "sg:province":"TX",
    "wof:name":"Village Barber Shop",
    "wof:placetype":"venue"
},
  "geometry": {"coordinates":[-100.465557,31.450641],"type":"Point"}
}