{
  "type": "Feature",
  "properties": {
    "iso:country":"US",
    "sg:address":"8814 Alameda Ave",
    "sg:city":"El Paso",
    "sg:classifiers":[
        {
            "category":"Shopping",
            "subcategory":"Florist",
            "type":"Retail Goods"
        }
    ],
    "sg:phone":"+1 915 858 6077",
    "sg:postcode":"79907",
    "sg:province":"TX",
    "wof:name":"Paradise Florists",
    "wof:placetype":"venue"
},
  "geometry": {"coordinates":[-106.335599,31.694828],"type":"Point"}
}