{
  "type": "Feature",
  "properties": {
    "iso:country":"US",
    "sg:address":"502 S 3rd St",
    "sg:city":"Bellaire",
    "sg:classifiers":[
        {
            "category":"Organizations",
            "subcategory":"Non-profit Organization",
            "type":"Services"
        }
    ],
    "sg:phone":"+1 713 839 1612",
    "sg:postcode":"77401",
    "sg:province":"TX",
    "sg:tags":[
        "social"
    ],
    "wof:name":"Youth Achievement of Houston",
    "wof:placetype":"venue"
},
  "geometry": {"coordinates":[-95.466762,29.69853],"type":"Point"}
}