{
  "type": "Feature",
  "properties": {
    "iso:country":"US",
    "sg:address":"1437 Irene Ave",
    "sg:city":"Lancaster",
    "sg:classifiers":[
        {
            "category":"Real Estate",
            "subcategory":"Real Estate Agent",
            "type":"Services"
        }
    ],
    "sg:phone":"+1 972 227 1898",
    "sg:postcode":"75134",
    "sg:province":"TX",
    "wof:name":"Joshua Appraisal Co",
    "wof:placetype":"venue"
},
  "geometry": {"coordinates":[-96.77424600000001,32.609137],"type":"Point"}
}