{
  "type": "Feature",
  "properties": {
    "iso:country":"US",
    "sg:address":"2802 N Macarthur Blvd",
    "sg:city":"Irving",
    "sg:classifiers":[
        {
            "category":"Banks & Credit Unions",
            "subcategory":"Bank",
            "type":"Services"
        }
    ],
    "sg:phone":"+1 972 252 8626",
    "sg:postcode":"75062",
    "sg:province":"TX",
    "sg:tags":[
        "cashing",
        "sell",
        "money",
        "order",
        "check"
    ],
    "wof:name":"ACE Cash Express",
    "wof:placetype":"venue"
},
  "geometry": {"coordinates":[-96.95898,32.845493],"type":"Point"}
}