{
  "type": "Feature",
  "properties": {
    "iso:country":"US",
    "sg:address":"600 N Marienfeld St",
    "sg:city":"Midland",
    "sg:classifiers":[
        {
            "category":"Wholesale",
            "subcategory":"Machinery & Supplies",
            "type":"Manufacturing & Wholesale Goods"
        }
    ],
    "sg:phone":"+1 432 570 5135",
    "sg:postcode":"79701",
    "sg:province":"TX",
    "sg:tags":[
        "equipment",
        "oil",
        "well"
    ],
    "wof:name":"Flexbar Inc",
    "wof:placetype":"venue"
},
  "geometry": {"coordinates":[-102.07946,32.003676],"type":"Point"}
}