{
  "type": "Feature",
  "properties": {
    "iso:country":"US",
    "sg:address":"13200 N I H 35",
    "sg:city":"Austin",
    "sg:classifiers":[
        {
            "category":"Banks & Credit Unions",
            "subcategory":"Bank",
            "type":"Services"
        }
    ],
    "sg:phone":"+1 512 973 3091",
    "sg:postcode":"78753",
    "sg:province":"TX",
    "wof:name":"Comerica Bank",
    "wof:placetype":"venue"
},
  "geometry": {"coordinates":[-97.67353799999999,30.416601],"type":"Point"}
}