{
  "type": "Feature",
  "properties": {
    "iso:country":"US",
    "sg:address":"100 Cotton Creek Way",
    "sg:city":"Hutto",
    "sg:classifiers":[
        {
            "category":"Professional",
            "subcategory":"Business Services",
            "type":"Services"
        }
    ],
    "sg:phone":"+1 512 759 1882",
    "sg:postcode":"78634",
    "sg:province":"TX",
    "wof:name":"Smart Home Services",
    "wof:placetype":"venue"
},
  "geometry": {"coordinates":[-97.540695,30.537951],"type":"Point"}
}