{
  "type": "Feature",
  "properties": {
    "iso:country":"US",
    "sg:address":"2431 Rice Blvd",
    "sg:city":"Houston",
    "sg:classifiers":[
        {
            "category":"Shopping",
            "subcategory":"Bridal",
            "type":"Retail Goods"
        }
    ],
    "sg:phone":"+1 713 527 8285",
    "sg:postcode":"77005",
    "sg:province":"TX",
    "sg:website":"www.maisondemode.com",
    "wof:name":"Maison de Mode",
    "wof:placetype":"venue"
},
  "geometry": {"coordinates":[-95.415471,29.717465],"type":"Point"}
}