{
  "type": "Feature",
  "properties": {
    "iso:country":"US",
    "sg:address":"5324 Gorman Rd",
    "sg:city":"Beaumont",
    "sg:classifiers":[
        {
            "category":"Building & Trades",
            "subcategory":"Construction",
            "type":"Services"
        }
    ],
    "sg:phone":"+1 409 842 9022",
    "sg:postcode":"77705",
    "sg:province":"TX",
    "sg:tags":[
        "general",
        "contractor"
    ],
    "wof:name":"A & B Builders Inc",
    "wof:placetype":"venue"
},
  "geometry": {"coordinates":[-94.09745100000001,30.031778],"type":"Point"}
}