{
  "type": "Feature",
  "properties": {
    "iso:country":"US",
    "sg:address":"1115 Sandy Creek Dr",
    "sg:city":"Allen",
    "sg:classifiers":[
        {
            "category":"Professional",
            "type":"Services"
        }
    ],
    "sg:phone":"+1 972 359 9015",
    "sg:postcode":"75002",
    "sg:province":"TX",
    "wof:name":"Protea Lee Services Inc",
    "wof:placetype":"venue"
},
  "geometry": {"coordinates":[-96.644486,33.113899],"type":"Point"}
}