{
  "type": "Feature",
  "properties": {
    "iso:country":"US",
    "sg:address":"1515 N Zarzamora",
    "sg:city":"San Antonio",
    "sg:classifiers":[
        {
            "category":"Autos & Motor Vehicles",
            "subcategory":"Automobile Sales",
            "type":"Retail Goods"
        }
    ],
    "sg:phone":"+1 210 785 8170",
    "sg:postcode":"78207",
    "sg:province":"TX",
    "sg:tags":[
        "car",
        "dealer"
    ],
    "wof:name":"M Cak Used Car Lot & Auto Rpr",
    "wof:placetype":"venue"
},
  "geometry": {"coordinates":[-98.52513500000001,29.443945],"type":"Point"}
}