{
  "type": "Feature",
  "properties": {
    "iso:country":"US",
    "sg:address":"706 Teal Dr",
    "sg:city":"Grand Prairie",
    "sg:classifiers":[
        {
            "category":"Retail",
            "subcategory":"Repair Shop",
            "type":"Services"
        }
    ],
    "sg:phone":"+1 972 263 3547",
    "sg:postcode":"75052",
    "sg:province":"TX",
    "sg:tags":[
        "electrical"
    ],
    "wof:name":"L&S Appliance Repair",
    "wof:placetype":"venue"
},
  "geometry": {"coordinates":[-96.99785199999999,32.697722],"type":"Point"}
}