{
  "type": "Feature",
  "properties": {
    "iso:country":"US",
    "sg:address":"1030 Heights Blvd",
    "sg:city":"Houston",
    "sg:classifiers":[
        {
            "category":"Coffee & Tea",
            "type":"Food & Drink"
        }
    ],
    "sg:phone":"+1 713 869 0700",
    "sg:postcode":"77008",
    "sg:province":"TX",
    "sg:website":"www.myspace.com/waldoscoffee",
    "wof:name":"Waldo's Coffee House",
    "wof:placetype":"venue"
},
  "geometry": {"coordinates":[-95.397195,29.790124],"type":"Point"}
}