{
  "type": "Feature",
  "properties": {
    "iso:country":"US",
    "sg:address":"6529 Midway Rd",
    "sg:city":"Fort Worth",
    "sg:classifiers":[
        {
            "category":"Building & Trades",
            "subcategory":"Equipment Rental",
            "type":"Services"
        }
    ],
    "sg:phone":"+1 817 838 6966",
    "sg:postcode":"76117",
    "sg:province":"TX",
    "sg:tags":[
        "product",
        "petroleum"
    ],
    "wof:name":"Safety-Kleen",
    "wof:placetype":"venue"
},
  "geometry": {"coordinates":[-97.23796900000001,32.7949],"type":"Point"}
}