{
  "type": "Feature",
  "properties": {
    "iso:country":"US",
    "sg:address":"9492M N Garden Dr",
    "sg:city":"Beaumont",
    "sg:classifiers":[
        {
            "category":"Building & Trades",
            "subcategory":"Construction",
            "type":"Services"
        }
    ],
    "sg:phone":"+1 409 722 9508",
    "sg:postcode":"77705",
    "sg:province":"TX",
    "sg:tags":[
        "wallcoverings-installation",
        "wallpaper",
        "painting",
        "contractor"
    ],
    "wof:name":"Charlton Painting",
    "wof:placetype":"venue"
},
  "geometry": {"coordinates":[-94.03489399999999,29.963141],"type":"Point"}
}