{
  "type": "Feature",
  "properties": {
    "iso:country":"US",
    "sg:address":"115 Main St",
    "sg:city":"Naples",
    "sg:classifiers":[
        {
            "category":"Home & Garden",
            "subcategory":"Household Appliances",
            "type":"Retail Goods"
        },
        {
            "category":"Utilities",
            "subcategory":"Fuel Oil & Lpg",
            "type":"Services"
        },
        {
            "category":"Utilities",
            "subcategory":"Natural Gas",
            "type":"Services"
        }
    ],
    "sg:phone":"+1 903 897 5687",
    "sg:postcode":"75568",
    "sg:province":"TX",
    "sg:tags":[
        "propane",
        "bulk",
        "major",
        "petroleum-bottled",
        "gas-liquefied"
    ],
    "sg:website":"http://www.welchgas.com",
    "wof:name":"Welchgas Inc",
    "wof:placetype":"venue"
},
  "geometry": {"coordinates":[-94.67055999999999,33.215528],"type":"Point"}
}