{
  "type": "Feature",
  "properties": {
    "iso:country":"US",
    "sg:address":"3334 W 7th St",
    "sg:city":"Fort Worth",
    "sg:classifiers":[
        {
            "category":"Wholesale",
            "subcategory":"Computers",
            "type":"Manufacturing & Wholesale Goods"
        },
        {
            "category":"Shopping",
            "type":"Retail Goods"
        }
    ],
    "sg:phone":"+1 817 870 2921",
    "sg:postcode":"76107",
    "sg:province":"TX",
    "sg:tags":[
        "equipment",
        "telephone",
        "supply"
    ],
    "sg:website":"www.univ-computers.com",
    "wof:name":"University Computers Acrocom",
    "wof:placetype":"venue"
},
  "geometry": {"coordinates":[-97.36659299999999,32.751371],"type":"Point"}
}