{
  "type": "Feature",
  "properties": {
    "iso:country":"US",
    "sg:address":"1131 Main St",
    "sg:city":"Mont Belvieu",
    "sg:classifiers":[
        {
            "category":"Home & Garden",
            "subcategory":"Building Materials",
            "type":"Retail Goods"
        }
    ],
    "sg:phone":"+1 281 385 0882",
    "sg:postcode":"77575",
    "sg:province":"TX",
    "sg:tags":[
        "glass",
        "window",
        "plate"
    ],
    "wof:name":"Blystone Glass Co",
    "wof:placetype":"venue"
},
  "geometry": {"coordinates":[-94.795496,30.065834],"type":"Point"}
}