{
  "type": "Feature",
  "properties": {
    "iso:country":"US",
    "sg:address":"100 S Main St",
    "sg:city":"Cleburne",
    "sg:classifiers":[
        {
            "category":"Shopping",
            "type":"Retail Goods"
        }
    ],
    "sg:phone":"+1 817 558 0342",
    "sg:postcode":"76033",
    "sg:province":"TX",
    "sg:tags":[
        "merchandise"
    ],
    "wof:name":"B BS Trophies",
    "wof:placetype":"venue"
},
  "geometry": {"coordinates":[-97.386375,32.346061],"type":"Point"}
}