{
  "type": "Feature",
  "properties": {
    "iso:country":"US",
    "sg:address":"1648 Walnut St",
    "sg:city":"Grand Prairie",
    "sg:classifiers":[
        {
            "category":"Personal",
            "subcategory":"Beauty Salon",
            "type":"Services"
        }
    ],
    "sg:phone":"+1 972 642 3485",
    "sg:postcode":"75050",
    "sg:province":"TX",
    "wof:name":"Xochitl Beauty Salon",
    "wof:placetype":"venue"
},
  "geometry": {"coordinates":[-96.982877,32.756388],"type":"Point"}
}