{
  "type": "Feature",
  "properties": {
    "iso:country":"US",
    "sg:address":"17559 Summer Pl",
    "sg:city":"Whitehouse",
    "sg:classifiers":[
        {
            "category":"Professional",
            "subcategory":"Business Services",
            "type":"Services"
        }
    ],
    "sg:phone":"+1 903 839 4948",
    "sg:postcode":"75791",
    "sg:province":"TX",
    "wof:name":"Harry Dale Hamblett",
    "wof:placetype":"venue"
},
  "geometry": {"coordinates":[-95.240787,32.223867],"type":"Point"}
}