{
  "type": "Feature",
  "properties": {
    "iso:country":"US",
    "sg:address":"3333 Samoa Dr",
    "sg:city":"Corpus Christi",
    "sg:classifiers":[
        {
            "category":"Building & Trades",
            "subcategory":"Construction",
            "type":"Services"
        }
    ],
    "sg:phone":"+1 361 937 6765",
    "sg:postcode":"78418",
    "sg:province":"TX",
    "sg:tags":[
        "house"
    ],
    "wof:name":"J B Creations",
    "wof:placetype":"venue"
},
  "geometry": {"coordinates":[-97.29498599999999,27.625426],"type":"Point"}
}