{
  "type": "Feature",
  "properties": {
    "iso:country":"US",
    "sg:address":"5555 West Loop S",
    "sg:city":"Bellaire",
    "sg:classifiers":[
        {
            "category":"Banks & Credit Unions",
            "subcategory":"Investment Brokerage",
            "type":"Services"
        }
    ],
    "sg:phone":"+1 713 664 5920",
    "sg:postcode":"77401",
    "sg:province":"TX",
    "sg:tags":[
        "investing"
    ],
    "wof:name":"C A S Financial Services",
    "wof:placetype":"venue"
},
  "geometry": {"coordinates":[-95.459626,29.722336],"type":"Point"}
}