{
  "type": "Feature",
  "properties": {
    "iso:country":"US",
    "sg:address":"20450 State Hwy 46",
    "sg:city":"Spring Branch",
    "sg:classifiers":[
        {
            "category":"Health Services",
            "subcategory":"Doctor",
            "type":"Services"
        }
    ],
    "sg:phone":"+1 830 438 2273",
    "sg:postcode":"78070",
    "sg:province":"TX",
    "sg:tags":[
        "dentist"
    ],
    "wof:name":"Bulverde North Family Dental",
    "wof:placetype":"venue"
},
  "geometry": {"coordinates":[-98.426849,29.798417],"type":"Point"}
}