{
  "type": "Feature",
  "properties": {
    "iso:country":"US",
    "sg:address":"706 Tulipan",
    "sg:city":"Hidalgo",
    "sg:classifiers":[
        {
            "category":"Building & Trades",
            "subcategory":"Construction",
            "type":"Services"
        }
    ],
    "sg:phone":"+1 956 843 4649",
    "sg:postcode":"78557",
    "sg:province":"TX",
    "sg:tags":[
        "house"
    ],
    "wof:name":"Aguirre Framing & Construction",
    "wof:placetype":"venue"
},
  "geometry": {"coordinates":[-98.25376300000001,26.104761],"type":"Point"}
}