{
  "type": "Feature",
  "properties": {
    "iso:country":"US",
    "sg:address":"149 W Rowson St",
    "sg:city":"San Benito",
    "sg:classifiers":[
        {
            "category":"Restaurant",
            "type":"Food & Drink"
        }
    ],
    "sg:phone":"+1 956 276 9797",
    "sg:postcode":"78586",
    "sg:province":"TX",
    "wof:name":"Cazuelas",
    "wof:placetype":"venue"
},
  "geometry": {"coordinates":[-97.632586,26.132027],"type":"Point"}
}