{
  "type": "Feature",
  "properties": {
    "iso:country":"US",
    "sg:address":"108 Elmore Dr",
    "sg:city":"Waco",
    "sg:classifiers":[
        {
            "category":"Professional",
            "subcategory":"Business Services",
            "type":"Services"
        }
    ],
    "sg:phone":"+1 254 848 9068",
    "sg:postcode":"76712",
    "sg:province":"TX",
    "wof:name":"CC Young Designs",
    "wof:placetype":"venue"
},
  "geometry": {"coordinates":[-97.284042,31.559992],"type":"Point"}
}