{
  "type": "Feature",
  "properties": {
    "iso:country":"US",
    "sg:address":"322 S Gaston St",
    "sg:city":"Crane",
    "sg:classifiers":[
        {
            "category":"Retail",
            "subcategory":"Auto Repair",
            "type":"Services"
        }
    ],
    "sg:phone":"+1 432 558 7290",
    "sg:postcode":"79731",
    "sg:province":"TX",
    "sg:tags":[
        "recap",
        "retread",
        "tire"
    ],
    "wof:name":"Leo's Tire Service",
    "wof:placetype":"venue"
},
  "geometry": {"coordinates":[-102.351129,31.400078],"type":"Point"}
}