{
  "type": "Feature",
  "properties": {
    "iso:country":"US",
    "sg:address":"1603 Buena Vista Dr",
    "sg:city":"Tyler",
    "sg:classifiers":[
        {
            "category":"Building & Trades",
            "subcategory":"Cleaning & Sanitation",
            "type":"Services"
        }
    ],
    "sg:phone":"+1 903 596 0688",
    "sg:postcode":"75701",
    "sg:province":"TX",
    "sg:tags":[
        "cleaners-interior"
    ],
    "wof:name":"Ed's Building Maintenence",
    "wof:placetype":"venue"
},
  "geometry": {"coordinates":[-95.31909,32.32008],"type":"Point"}
}