{
  "type": "Feature",
  "properties": {
    "iso:country":"US",
    "sg:address":"610 Murphy Rd",
    "sg:city":"Stafford",
    "sg:classifiers":[
        {
            "category":"Shopping",
            "subcategory":"Clothing, Apparel, & Fashions",
            "type":"Retail Goods"
        }
    ],
    "sg:phone":"+1 281 499 1109",
    "sg:postcode":"77477",
    "sg:province":"TX",
    "sg:tags":[
        "shop",
        "bridal"
    ],
    "wof:name":"Victorias Bridal Shop",
    "wof:placetype":"venue"
},
  "geometry": {"coordinates":[-95.564543,29.610272],"type":"Point"}
}