{
  "type": "Feature",
  "properties": {
    "iso:country":"US",
    "sg:address":"4132 Ave M",
    "sg:city":"Fort Worth",
    "sg:classifiers":[
        {
            "category":"Retail",
            "subcategory":"Repair Shop",
            "type":"Services"
        }
    ],
    "sg:phone":"+1 817 534 5533",
    "sg:postcode":"76105",
    "sg:province":"TX",
    "sg:tags":[
        "armature",
        "rewinding"
    ],
    "wof:name":"24/7 Electric Motor Service",
    "wof:placetype":"venue"
},
  "geometry": {"coordinates":[-97.262171,32.724649],"type":"Point"}
}