{
  "type": "Feature",
  "properties": {
    "iso:country":"US",
    "sg:address":"2548 US Hwy 290",
    "sg:city":"Mc Dade",
    "sg:classifiers":[
        {
            "category":"Utilities",
            "subcategory":"Refuse",
            "type":"Services"
        }
    ],
    "sg:phone":"+1 512 273 2108",
    "sg:postcode":"78650",
    "sg:province":"TX",
    "sg:tags":[
        "garbage",
        "collection"
    ],
    "wof:name":"Cam Disposal",
    "wof:placetype":"venue"
},
  "geometry": {"coordinates":[-97.211688,30.240905],"type":"Point"}
}