{
  "type": "Feature",
  "properties": {
    "iso:country":"US",
    "sg:address":"7502 Fondren Rd",
    "sg:city":"Houston",
    "sg:classifiers":[
        {
            "category":"Education",
            "subcategory":"University",
            "type":"Public Place"
        }
    ],
    "sg:phone":"+1 281 649 3000",
    "sg:postcode":"77074",
    "sg:province":"TX",
    "sg:tags":[
        "college"
    ],
    "wof:name":"Houston Baptist University",
    "wof:placetype":"venue"
},
  "geometry": {"coordinates":[-95.515503,29.698099],"type":"Point"}
}