{
  "type": "Feature",
  "properties": {
    "iso:country":"US",
    "sg:address":"1022 Dragon St",
    "sg:city":"Dallas",
    "sg:classifiers":[
        {
            "category":"Home & Garden",
            "subcategory":"Furniture",
            "type":"Retail Goods"
        }
    ],
    "sg:phone":"+1 214 653 1951",
    "sg:postcode":"75207",
    "sg:province":"TX",
    "sg:tags":[
        "store"
    ],
    "wof:name":"Sedersi Inc",
    "wof:placetype":"venue"
},
  "geometry": {"coordinates":[-96.816597,32.787399],"type":"Point"}
}