{
  "type": "Feature",
  "properties": {
    "iso:country":"US",
    "sg:address":"1623 Main St",
    "sg:city":"La Marque",
    "sg:classifiers":[
        {
            "category":"Wholesale",
            "subcategory":"Office Equipment",
            "type":"Manufacturing & Wholesale Goods"
        }
    ],
    "sg:phone":"+1 713 516 5679",
    "sg:postcode":"77568",
    "sg:province":"TX",
    "sg:tags":[
        "repair",
        "electrical"
    ],
    "wof:name":"Ehresman Office Systems",
    "wof:placetype":"venue"
},
  "geometry": {"coordinates":[-94.967658,29.358065],"type":"Point"}
}