{
  "type": "Feature",
  "properties": {
    "iso:country":"US",
    "sg:address":"5501 N Lamar Blvd Ste A-111",
    "sg:city":"Austin",
    "sg:classifiers":[
        {
            "category":"Education",
            "subcategory":"Music School",
            "type":"Public Place"
        }
    ],
    "sg:phone":"+1 512 442 2880",
    "sg:postcode":"78751",
    "sg:province":"TX",
    "sg:tags":[
        "instrument",
        "teacher",
        "musical"
    ],
    "sg:website":"www.austinguitarschool.com",
    "wof:name":"Austin Guitar School",
    "wof:placetype":"venue"
},
  "geometry": {"coordinates":[-97.728105,30.322894],"type":"Point"}
}