{
  "type": "Feature",
  "properties": {
    "iso:country":"US",
    "sg:address":"608 Oakwood Ave",
    "sg:city":"Hurst",
    "sg:classifiers":[
        {
            "category":"Professional",
            "subcategory":"Business Services",
            "type":"Services"
        }
    ],
    "sg:phone":"+1 817 282 0289",
    "sg:postcode":"76053",
    "sg:province":"TX",
    "wof:name":"G & S Copier Sales",
    "wof:placetype":"venue"
},
  "geometry": {"coordinates":[-97.18174999999999,32.81776],"type":"Point"}
}