{
  "type": "Feature",
  "properties": {
    "iso:country":"US",
    "sg:address":"9752 Cloister Dr",
    "sg:city":"Dallas",
    "sg:classifiers":[
        {
            "category":"Retail",
            "subcategory":"Repair Shop",
            "type":"Services"
        }
    ],
    "sg:phone":"+1 214 321 6626",
    "sg:postcode":"75228",
    "sg:province":"TX",
    "wof:name":"John A Hill Repair Svc",
    "wof:placetype":"venue"
},
  "geometry": {"coordinates":[-96.68934900000001,32.82825],"type":"Point"}
}