{
  "type": "Feature",
  "properties": {
    "iso:country":"US",
    "sg:address":"4933 Belt Line Rd",
    "sg:city":"Addison",
    "sg:classifiers":[
        {
            "category":"Restaurant",
            "type":"Food & Drink"
        }
    ],
    "sg:phone":"+1 972 702 6426",
    "sg:postcode":"75001",
    "sg:province":"TX",
    "sg:tags":[
        "mexican"
    ],
    "sg:website":"www.mcrowd.com/tacodiner.html",
    "wof:name":"Taco Diner",
    "wof:placetype":"venue"
},
  "geometry": {"coordinates":[-96.82486900000001,32.954185],"type":"Point"}
}