{
  "type": "Feature",
  "properties": {
    "iso:country":"US",
    "sg:address":"8743 Fannette St",
    "sg:city":"Houston",
    "sg:classifiers":[
        {
            "category":"Arts & Performance",
            "subcategory":"Dance",
            "type":"Entertainment"
        }
    ],
    "sg:phone":"+1 713 673 6395",
    "sg:postcode":"77029",
    "sg:province":"TX",
    "sg:tags":[
        "instruction",
        "dancing"
    ],
    "wof:name":"Dance Giant Steps Inc",
    "wof:placetype":"venue"
},
  "geometry": {"coordinates":[-95.26867900000001,29.767029],"type":"Point"}
}