{
  "type": "Feature",
  "properties": {
    "iso:country":"US",
    "sg:address":"1204 E Euless Blvd",
    "sg:city":"Euless",
    "sg:classifiers":[
        {
            "category":"Freight",
            "type":"Transportation"
        }
    ],
    "sg:phone":"+1 817 545 0733",
    "sg:postcode":"76040",
    "sg:province":"TX",
    "sg:tags":[
        "storage",
        "self",
        "rental",
        "public",
        "facility"
    ],
    "wof:name":"Susa Partnership LP",
    "wof:placetype":"venue"
},
  "geometry": {"coordinates":[-97.105617,32.826675],"type":"Point"}
}