{
  "type": "Feature",
  "properties": {
    "iso:country":"US",
    "sg:address":"107 N Austin Ave",
    "sg:city":"Throckmorton",
    "sg:classifiers":[
        {
            "category":"Retail",
            "subcategory":"Funeral Services",
            "type":"Services"
        }
    ],
    "sg:phone":"+1 940 849 4021",
    "sg:postcode":"76483",
    "sg:province":"TX",
    "sg:tags":[
        "director"
    ],
    "wof:name":"Merriman-Archer Funeral Home",
    "wof:placetype":"venue"
},
  "geometry": {"coordinates":[-99.18222299999999,33.179877],"type":"Point"}
}