{
  "type": "Feature",
  "properties": {
    "iso:country":"US",
    "sg:address":"3611 Graustark St",
    "sg:city":"Houston",
    "sg:classifiers":[
        {
            "category":"Health Services",
            "subcategory":"Clinic",
            "type":"Services"
        }
    ],
    "sg:phone":"+1 713 942 8910",
    "sg:postcode":"77006",
    "sg:province":"TX",
    "sg:website":"www.ipcm.com",
    "wof:name":"Ipc Div Of The Hospitalist",
    "wof:placetype":"venue"
},
  "geometry": {"coordinates":[-95.39467399999999,29.739681],"type":"Point"}
}