{
  "type": "Feature",
  "properties": {
    "iso:country":"US",
    "sg:address":"1400 Preston Rd",
    "sg:city":"Plano",
    "sg:classifiers":[
        {
            "category":"Professional",
            "subcategory":"Lawyer & Legal Services",
            "type":"Services"
        }
    ],
    "sg:phone":"+1 972 985 9992",
    "sg:postcode":"75093",
    "sg:province":"TX",
    "sg:tags":[
        "attorney"
    ],
    "wof:name":"J Mark Scarborough PC",
    "wof:placetype":"venue"
},
  "geometry": {"coordinates":[-96.795199,33.016883],"type":"Point"}
}