{
  "type": "Feature",
  "properties": {
    "iso:country":"US",
    "sg:address":"2200 S Fannin St",
    "sg:city":"Amarillo",
    "sg:classifiers":[
        {
            "category":"Banks & Credit Unions",
            "subcategory":"Investment Brokerage",
            "type":"Services"
        }
    ],
    "sg:phone":"+1 806 355 1260",
    "sg:postcode":"79109",
    "sg:province":"TX",
    "wof:name":"Bell Investment Group",
    "wof:placetype":"venue"
},
  "geometry": {"coordinates":[-101.860131,35.187318],"type":"Point"}
}