{
  "type": "Feature",
  "properties": {
    "iso:country":"US",
    "sg:address":"3909 Olympia St",
    "sg:city":"Irving",
    "sg:classifiers":[
        {
            "category":"Organizations",
            "subcategory":"Religious Organization",
            "type":"Services"
        }
    ],
    "sg:phone":"+1 972 255 2072",
    "sg:postcode":"75062",
    "sg:province":"TX",
    "wof:name":"Chris Calvery",
    "wof:placetype":"venue"
},
  "geometry": {"coordinates":[-97.004659,32.841106],"type":"Point"}
}