{
  "type": "Feature",
  "properties": {
    "iso:country":"US",
    "sg:address":"11262 Leo Ln",
    "sg:city":"Dallas",
    "sg:classifiers":[
        {
            "category":"Professional",
            "subcategory":"Business Services",
            "type":"Services"
        }
    ],
    "sg:phone":"+1 972 243 2220",
    "sg:postcode":"75229",
    "sg:province":"TX",
    "sg:tags":[
        "trade",
        "exposition",
        "fair",
        "show"
    ],
    "wof:name":"Office Expo",
    "wof:placetype":"venue"
},
  "geometry": {"coordinates":[-96.886202,32.893054],"type":"Point"}
}