{
  "type": "Feature",
  "properties": {
    "iso:country":"US",
    "sg:address":"2010 4th Ave",
    "sg:city":"Canyon",
    "sg:classifiers":[
        {
            "category":"Shopping",
            "subcategory":"Florist",
            "type":"Retail Goods"
        }
    ],
    "sg:phone":"+1 806 655 2587",
    "sg:postcode":"79015",
    "sg:province":"TX",
    "wof:name":"H R's Flowers & Gifts Inc",
    "wof:placetype":"venue"
},
  "geometry": {"coordinates":[-101.922392,34.979786],"type":"Point"}
}