{
  "type": "Feature",
  "properties": {
    "iso:country":"US",
    "sg:address":"635 Washington St",
    "sg:city":"Hempstead",
    "sg:classifiers":[
        {
            "category":"Retail",
            "subcategory":"Auto Repair",
            "type":"Services"
        }
    ],
    "sg:phone":"+1 979 826 8374",
    "sg:postcode":"77445",
    "sg:province":"TX",
    "sg:tags":[
        "repairing",
        "automotive",
        "radiator",
        "automobile"
    ],
    "wof:name":"Freitags Radiator Shop",
    "wof:placetype":"venue"
},
  "geometry": {"coordinates":[-96.074697,30.094412],"type":"Point"}
}