{
  "type": "Feature",
  "properties": {
    "iso:country":"US",
    "sg:address":"444 Executive Center Blvd",
    "sg:city":"El Paso",
    "sg:classifiers":[
        {
            "category":"Professional",
            "subcategory":"Accounting & Tax Preparation",
            "type":"Services"
        }
    ],
    "sg:phone":"+1 915 534 9126",
    "sg:postcode":"79902",
    "sg:province":"TX",
    "sg:tags":[
        "accountant"
    ],
    "wof:name":"Marlin R Buchanan CPA",
    "wof:placetype":"venue"
},
  "geometry": {"coordinates":[-106.515817,31.795348],"type":"Point"}
}