{
  "type": "Feature",
  "properties": {
    "iso:country":"US",
    "sg:address":"502 Crystal Falls Pkwy Ste B",
    "sg:city":"Leander",
    "sg:classifiers":[
        {
            "category":"Health Services",
            "subcategory":"Health Practitioner",
            "type":"Services"
        }
    ],
    "sg:phone":"+1 512 528 0800",
    "sg:postcode":"78641",
    "sg:province":"TX",
    "sg:tags":[
        "therapy",
        "physical"
    ],
    "wof:name":"Leander Physical Therapy",
    "wof:placetype":"venue"
},
  "geometry": {"coordinates":[-97.84964100000001,30.556037],"type":"Point"}
}