{
  "type": "Feature",
  "properties": {
    "iso:country":"US",
    "sg:address":"16025 Oleta Ln",
    "sg:city":"Sugar Land",
    "sg:classifiers":[
        {
            "category":"Building & Trades",
            "subcategory":"Construction",
            "type":"Services"
        }
    ],
    "sg:phone":"+1 281 277 3075",
    "sg:postcode":"77478",
    "sg:province":"TX",
    "sg:tags":[
        "residential"
    ],
    "wof:name":"D M V Construction",
    "wof:placetype":"venue"
},
  "geometry": {"coordinates":[-95.665778,29.65342],"type":"Point"}
}