{
  "type": "Feature",
  "properties": {
    "iso:country":"US",
    "sg:address":"7031 N Shepherd Dr",
    "sg:city":"Houston",
    "sg:classifiers":[
        {
            "category":"Food & Beverages",
            "subcategory":"Groceries & Convenience Stores",
            "type":"Retail Goods"
        }
    ],
    "sg:phone":"+1 713 691 2755",
    "sg:postcode":"77091",
    "sg:province":"TX",
    "sg:tags":[
        "station",
        "gasoline"
    ],
    "wof:name":"Handee Stop Drive In",
    "wof:placetype":"venue"
},
  "geometry": {"coordinates":[-95.412706,29.863868],"type":"Point"}
}