{
  "type": "Feature",
  "properties": {
    "iso:country":"US",
    "sg:address":"2750 Virginia Pkwy",
    "sg:city":"Mc Kinney",
    "sg:classifiers":[
        {
            "category":"Real Estate",
            "subcategory":"Real Estate Agent",
            "type":"Services"
        }
    ],
    "sg:phone":"+1 972 542 9345",
    "sg:postcode":"75071",
    "sg:province":"TX",
    "sg:tags":[
        "consultant"
    ],
    "wof:name":"United Country Real Estate",
    "wof:placetype":"venue"
},
  "geometry": {"coordinates":[-96.651082,33.198967],"type":"Point"}
}