{
  "type": "Feature",
  "properties": {
    "iso:country":"US",
    "sg:address":"9424 Prairieview Dr",
    "sg:city":"Fort Worth",
    "sg:classifiers":[
        {
            "category":"Wholesale",
            "subcategory":"Durable Goods & Equipment",
            "type":"Manufacturing & Wholesale Goods"
        }
    ],
    "sg:phone":"+1 817 551 6069",
    "sg:postcode":"76134",
    "sg:province":"TX",
    "wof:name":"Judy Carol Weed Retailer",
    "wof:placetype":"venue"
},
  "geometry": {"coordinates":[-97.34561600000001,32.617637],"type":"Point"}
}