{
  "type": "Feature",
  "properties": {
    "iso:country":"US",
    "sg:address":"2401 Rice Blvd",
    "sg:city":"Houston",
    "sg:classifiers":[
        {
            "category":"Shopping",
            "subcategory":"Clothing, Apparel, & Fashions",
            "type":"Retail Goods"
        }
    ],
    "sg:phone":"+1 713 524 3700",
    "sg:postcode":"77005",
    "sg:province":"TX",
    "sg:tags":[
        "children's",
        "clothing",
        "wear",
        "maternity"
    ],
    "sg:website":"www.awomanswork.com",
    "wof:name":"Woman's Work",
    "wof:placetype":"venue"
},
  "geometry": {"coordinates":[-95.415001,29.7174],"type":"Point"}
}