{
  "type": "Feature",
  "properties": {
    "iso:country":"US",
    "sg:address":"105 E 2nd St",
    "sg:city":"Brady",
    "sg:classifiers":[
        {
            "category":"Professional",
            "subcategory":"Business Services",
            "type":"Services"
        }
    ],
    "sg:phone":"+1 325 597 0212",
    "sg:postcode":"76825",
    "sg:province":"TX",
    "wof:name":"Time & Temperature",
    "wof:placetype":"venue"
},
  "geometry": {"coordinates":[-99.334109,31.133049],"type":"Point"}
}