{
  "type": "Feature",
  "properties": {
    "iso:country":"US",
    "sg:address":"5928 E Lancaster Ave",
    "sg:city":"Fort Worth",
    "sg:classifiers":[
        {
            "category":"Home & Garden",
            "subcategory":"Carpets & Floor Coverings",
            "type":"Retail Goods"
        }
    ],
    "sg:phone":"+1 817 451 5441",
    "sg:postcode":"76112",
    "sg:province":"TX",
    "sg:tags":[
        "flooring"
    ],
    "wof:name":"Meadowbrook Carpets Inc",
    "wof:placetype":"venue"
},
  "geometry": {"coordinates":[-97.228735,32.736088],"type":"Point"}
}