{
  "type": "Feature",
  "properties": {
    "iso:country":"US",
    "sg:address":"601 TX-110 N",
    "sg:city":"Whitehouse",
    "sg:classifiers":[
        {
            "category":"Restaurant",
            "type":"Food & Drink"
        }
    ],
    "sg:menulink":"http://www.allmenus.com/tx/whitehouse/66973-pizza-pro/menu/",
    "sg:phone":"+1 903 839 3422",
    "sg:postcode":"75791",
    "sg:province":"TX",
    "sg:tags":[
        "american",
        "pizza"
    ],
    "wof:name":"Pizza Pro",
    "wof:placetype":"venue"
},
  "geometry": {"coordinates":[-95.230874,32.241836],"type":"Point"}
}