{
  "type": "Feature",
  "properties": {
    "iso:country":"US",
    "sg:address":"2021 Orchid Ave",
    "sg:city":"Mcallen",
    "sg:classifiers":[
        {
            "category":"Bars & Pubs",
            "type":"Food & Drink"
        }
    ],
    "sg:phone":"+1 956 682 2005",
    "sg:postcode":"78504",
    "sg:province":"TX",
    "sg:tags":[
        "club",
        "night"
    ],
    "wof:name":"Metropolis",
    "wof:placetype":"venue"
},
  "geometry": {"coordinates":[-98.23440600000001,26.242333],"type":"Point"}
}