{
  "type": "Feature",
  "properties": {
    "iso:country":"US",
    "sg:address":"12720 Covington Trl",
    "sg:city":"Austin",
    "sg:classifiers":[
        {
            "category":"Building & Trades",
            "subcategory":"Construction",
            "type":"Services"
        }
    ],
    "sg:phone":"+1 512 258 3979",
    "sg:postcode":"78727",
    "sg:province":"TX",
    "sg:tags":[
        "contractor"
    ],
    "wof:name":"Austin Roof Clearance",
    "wof:placetype":"venue"
},
  "geometry": {"coordinates":[-97.742711,30.435329],"type":"Point"}
}