{
  "type": "Feature",
  "properties": {
    "iso:country":"US",
    "sg:address":"23211 Kuykendahl Rd",
    "sg:city":"Tomball",
    "sg:classifiers":[
        {
            "category":"Food & Beverages",
            "subcategory":"Liquor & Beverages",
            "type":"Retail Goods"
        }
    ],
    "sg:phone":"+1 281 320 8744",
    "sg:postcode":"77375",
    "sg:province":"TX",
    "sg:tags":[
        "store"
    ],
    "wof:name":"Speedy Pak Liquors",
    "wof:placetype":"venue"
},
  "geometry": {"coordinates":[-95.54131700000001,30.099975],"type":"Point"}
}