{
  "type": "Feature",
  "properties": {
    "iso:country":"US",
    "sg:address":"1423 Northpark Dr",
    "sg:city":"Humble",
    "sg:classifiers":[
        {
            "category":"Autos & Motor Vehicles",
            "subcategory":"Auto Supplies",
            "type":"Retail Goods"
        }
    ],
    "sg:phone":"+1 281 354 6800",
    "sg:postcode":"77339",
    "sg:province":"TX",
    "sg:tags":[
        "merchandise"
    ],
    "wof:name":"Texas Truck Accessories",
    "wof:placetype":"venue"
},
  "geometry": {"coordinates":[-95.23280800000001,30.068683],"type":"Point"}
}