{
  "type": "Feature",
  "properties": {
    "iso:country":"US",
    "sg:address":"315 W Commerce St",
    "sg:city":"Fairfield",
    "sg:classifiers":[
        {
            "category":"Building & Trades",
            "subcategory":"Construction",
            "type":"Services"
        }
    ],
    "sg:phone":"+1 903 389 6330",
    "sg:postcode":"75840",
    "sg:province":"TX",
    "sg:tags":[
        "downspouts",
        "gutter",
        "contractor"
    ],
    "wof:name":"Superior Siding & Remodeling",
    "wof:placetype":"venue"
},
  "geometry": {"coordinates":[-96.163479,31.724828],"type":"Point"}
}