{
  "type": "Feature",
  "properties": {
    "iso:country":"US",
    "sg:address":"1411 Natches Dr",
    "sg:city":"Arlington",
    "sg:classifiers":[
        {
            "category":"Shopping",
            "subcategory":"Gifts & Souvenirs",
            "type":"Retail Goods"
        }
    ],
    "sg:phone":"+1 817 465 3791",
    "sg:postcode":"76014",
    "sg:province":"TX",
    "wof:name":"Myart Studio",
    "wof:placetype":"venue"
},
  "geometry": {"coordinates":[-97.089252,32.696767],"type":"Point"}
}