{
  "type": "Feature",
  "properties": {
    "iso:country":"US",
    "sg:address":"446 Walnut Heights Blvd",
    "sg:city":"New Braunfels",
    "sg:classifiers":[
        {
            "category":"Wholesale",
            "subcategory":"Toys & Hobbies",
            "type":"Manufacturing & Wholesale Goods"
        }
    ],
    "sg:phone":"+1 830 609 0555",
    "sg:postcode":"78130",
    "sg:province":"TX",
    "wof:name":"Laura Thetford",
    "wof:placetype":"venue"
},
  "geometry": {"coordinates":[-98.11304,29.682911],"type":"Point"}
}