{
  "type": "Feature",
  "properties": {
    "iso:country":"US",
    "sg:address":"16104 Palm St",
    "sg:city":"Channelview",
    "sg:classifiers":[
        {
            "category":"Professional",
            "subcategory":"Computer Services",
            "type":"Services"
        }
    ],
    "sg:phone":"+1 281 457 1415",
    "sg:postcode":"77530",
    "sg:province":"TX",
    "sg:tags":[
        "design",
        "system"
    ],
    "wof:name":"HI Tech Theater Systems",
    "wof:placetype":"venue"
},
  "geometry": {"coordinates":[-95.114836,29.795925],"type":"Point"}
}