{
  "type": "Feature",
  "properties": {
    "iso:country":"US",
    "sg:address":"2412 Berkett Dr",
    "sg:city":"Austin",
    "sg:classifiers":[
        {
            "category":"Freight",
            "type":"Transportation"
        }
    ],
    "sg:phone":"+1 512 916 9066",
    "sg:postcode":"78745",
    "sg:province":"TX",
    "wof:name":"Tasmanian Transportation Inc",
    "wof:placetype":"venue"
},
  "geometry": {"coordinates":[-97.80747,30.212593],"type":"Point"}
}