{
  "type": "Feature",
  "properties": {
    "iso:country":"US",
    "sg:address":"816 S 6th St",
    "sg:city":"Nederland",
    "sg:classifiers":[
        {
            "category":"Wholesale",
            "subcategory":"Hardware",
            "type":"Manufacturing & Wholesale Goods"
        }
    ],
    "sg:phone":"+1 409 722 7236",
    "sg:postcode":"77627",
    "sg:province":"TX",
    "sg:tags":[
        "purifying",
        "cleaning",
        "air"
    ],
    "wof:name":"SER Clean Air & Home System",
    "wof:placetype":"venue"
},
  "geometry": {"coordinates":[-93.979229,29.977173],"type":"Point"}
}