{
  "type": "Feature",
  "properties": {
    "iso:country":"US",
    "sg:address":"14318 Carolcrest St",
    "sg:city":"Houston",
    "sg:classifiers":[
        {
            "category":"Professional",
            "subcategory":"Management & Consulting",
            "type":"Services"
        }
    ],
    "sg:phone":"+1 281 870 0548",
    "sg:postcode":"77079",
    "sg:province":"TX",
    "wof:name":"Wyatt JC Marketing",
    "wof:placetype":"venue"
},
  "geometry": {"coordinates":[-95.59993900000001,29.766293],"type":"Point"}
}