{
  "type": "Feature",
  "properties": {
    "iso:country":"US",
    "sg:address":"902 Normandy St",
    "sg:city":"Houston",
    "sg:classifiers":[
        {
            "category":"Health Services",
            "subcategory":"Dentist",
            "type":"Services"
        }
    ],
    "sg:phone":"+1 713 453 9926",
    "sg:postcode":"77015",
    "sg:province":"TX",
    "wof:name":"Ideal Smiles",
    "wof:placetype":"venue"
},
  "geometry": {"coordinates":[-95.20656700000001,29.773943],"type":"Point"}
}