{
  "type": "Feature",
  "properties": {
    "iso:country":"US",
    "sg:address":"143 E Nopal St",
    "sg:city":"Uvalde",
    "sg:classifiers":[
        {
            "category":"Professional",
            "subcategory":"Management & Consulting",
            "type":"Services"
        }
    ],
    "sg:phone":"+1 830 278 3009",
    "sg:postcode":"78801",
    "sg:province":"TX",
    "wof:name":"Y2marketing",
    "wof:placetype":"venue"
},
  "geometry": {"coordinates":[-99.78484899999999,29.21159],"type":"Point"}
}