{
  "type": "Feature",
  "properties": {
    "iso:country":"US",
    "sg:address":"26630 Betka Rd",
    "sg:city":"Waller",
    "sg:classifiers":[
        {
            "category":"Place Of Worship",
            "subcategory":"Church",
            "type":"Public Place"
        },
        {
            "category":"Place Of Worship",
            "type":"Public Place"
        }
    ],
    "sg:phone":"+1 936 931 9414",
    "sg:postcode":"77484",
    "sg:province":"TX",
    "sg:tags":[
        "churches-baptist-general",
        "churches-baptist"
    ],
    "wof:name":"Mount Zion Baptist Church",
    "wof:placetype":"venue"
},
  "geometry": {"coordinates":[-95.96876899999999,30.021913],"type":"Point"}
}