{
  "type": "Feature",
  "properties": {
    "iso:country":"US",
    "sg:address":"4512 Lewis Dr",
    "sg:city":"Port Arthur",
    "sg:classifiers":[
        {
            "category":"Food & Beverages",
            "subcategory":"Groceries & Convenience Stores",
            "type":"Retail Goods"
        },
        {
            "category":"Restaurant",
            "type":"Food & Drink"
        }
    ],
    "sg:phone":"+1 409 982 1823",
    "sg:postcode":"77642",
    "sg:province":"TX",
    "sg:tags":[
        "delicatessen",
        "eating"
    ],
    "wof:name":"Antonio's Deli",
    "wof:placetype":"venue"
},
  "geometry": {"coordinates":[-93.90790699999999,29.912173],"type":"Point"}
}