{
  "type": "Feature",
  "properties": {
    "iso:country":"US",
    "sg:address":"6519 N Lamar Blvd",
    "sg:city":"Austin",
    "sg:classifiers":[
        {
            "category":"Restaurant",
            "type":"Food & Drink"
        }
    ],
    "sg:phone":"+1 512 302 3149",
    "sg:postcode":"78752",
    "sg:province":"TX",
    "sg:tags":[
        "korean",
        "asian",
        "pan"
    ],
    "wof:name":"Korea Garden",
    "wof:placetype":"venue"
},
  "geometry": {"coordinates":[-97.72169100000001,30.333344],"type":"Point"}
}