{
  "type": "Feature",
  "properties": {
    "iso:country":"US",
    "sg:address":"2418 Kristen Dr",
    "sg:city":"Dallas",
    "sg:classifiers":[
        {
            "category":"Shopping",
            "subcategory":"Clothing, Apparel, & Fashions",
            "type":"Retail Goods"
        }
    ],
    "sg:phone":"+1 214 376 6790",
    "sg:postcode":"75216",
    "sg:province":"TX",
    "sg:tags":[
        "family"
    ],
    "wof:name":"Grays Clothing",
    "wof:placetype":"venue"
},
  "geometry": {"coordinates":[-96.779927,32.692958],"type":"Point"}
}