{
  "type": "Feature",
  "properties": {
    "iso:country":"US",
    "sg:address":"4722 Chibcha Ct",
    "sg:city":"Laredo",
    "sg:classifiers":[
        {
            "category":"Professional",
            "type":"Services"
        }
    ],
    "sg:phone":"+1 956 717 3576",
    "sg:postcode":"78046",
    "sg:province":"TX",
    "wof:name":"Cnv Service Co LLC",
    "wof:placetype":"venue"
},
  "geometry": {"coordinates":[-99.458552,27.450353],"type":"Point"}
}