{
  "type": "Feature",
  "properties": {
    "iso:country":"US",
    "sg:address":"111 Blue Bell Rd",
    "sg:city":"Houston",
    "sg:classifiers":[
        {
            "category":"Autos & Motor Vehicles",
            "subcategory":"Automobile Sales",
            "type":"Retail Goods"
        }
    ],
    "sg:phone":"+1 281 847 0768",
    "sg:postcode":"77037",
    "sg:province":"TX",
    "sg:tags":[
        "car",
        "dealer"
    ],
    "wof:name":"A G Auto Sales",
    "wof:placetype":"venue"
},
  "geometry": {"coordinates":[-95.40848200000001,29.907253],"type":"Point"}
}