{
  "type": "Feature",
  "properties": {
    "iso:country":"US",
    "sg:address":"8410 North Fwy",
    "sg:city":"Houston",
    "sg:classifiers":[
        {
            "category":"Insurance",
            "subcategory":"Hazard Insurance",
            "type":"Services"
        }
    ],
    "sg:phone":"+1 281 931 3000",
    "sg:postcode":"77037",
    "sg:province":"TX",
    "sg:website":"www.pjtrailers.com",
    "wof:name":"Nationwide Trailers",
    "wof:placetype":"venue"
},
  "geometry": {"coordinates":[-95.411404,29.882748],"type":"Point"}
}