{
  "type": "Feature",
  "properties": {
    "iso:country":"US",
    "sg:address":"1620 Flaming Oak Dr",
    "sg:city":"New Braunfels",
    "sg:classifiers":[
        {
            "category":"Real Estate",
            "subcategory":"Real Estate Operator",
            "type":"Services"
        }
    ],
    "sg:phone":"+1 830 620 6521",
    "sg:postcode":"78132",
    "sg:province":"TX",
    "sg:tags":[
        "mobile",
        "home",
        "park"
    ],
    "wof:name":"Four D Mobile Home Park",
    "wof:placetype":"venue"
},
  "geometry": {"coordinates":[-98.10297799999999,29.767414],"type":"Point"}
}