{
  "type": "Feature",
  "properties": {
    "iso:country":"US",
    "sg:address":"136 S Main St",
    "sg:city":"Irving",
    "sg:classifiers":[
        {
            "category":"Professional",
            "subcategory":"Computer Services",
            "type":"Services"
        }
    ],
    "sg:phone":"+1 972 259 3322",
    "sg:postcode":"75060",
    "sg:province":"TX",
    "sg:tags":[
        "repair"
    ],
    "wof:name":"Laviance Computer Technologies",
    "wof:placetype":"venue"
},
  "geometry": {"coordinates":[-96.94611500000001,32.8132],"type":"Point"}
}