{
  "type": "Feature",
  "properties": {
    "iso:country":"US",
    "sg:address":"1315 Coggin Ave",
    "sg:city":"Brownwood",
    "sg:classifiers":[
        {
            "category":"Freight",
            "type":"Transportation"
        }
    ],
    "sg:phone":"+1 325 752 8600",
    "sg:postcode":"76801",
    "sg:province":"TX",
    "sg:tags":[
        "commercial",
        "storage"
    ],
    "wof:name":"A-1 Mini Storage",
    "wof:placetype":"venue"
},
  "geometry": {"coordinates":[-98.97990299999999,31.707772],"type":"Point"}
}