{
  "type": "Feature",
  "properties": {
    "iso:country":"US",
    "sg:address":"209 N Preston St",
    "sg:city":"Van Alstyne",
    "sg:classifiers":[
        {
            "category":"Government",
            "subcategory":"Police Station",
            "type":"Public Place"
        }
    ],
    "sg:phone":"+1 903 482 5251",
    "sg:postcode":"75495",
    "sg:province":"TX",
    "sg:tags":[
        "department"
    ],
    "sg:website":"www.vanalstynepolice.com",
    "wof:name":"Van Alstyne Police Dept",
    "wof:placetype":"venue"
},
  "geometry": {"coordinates":[-96.577049,33.423765],"type":"Point"}
}