{
  "type": "Feature",
  "properties": {
    "iso:country":"US",
    "sg:address":"703 E 17th St",
    "sg:city":"Cameron",
    "sg:classifiers":[
        {
            "category":"Organizations",
            "subcategory":"Community Association",
            "type":"Services"
        }
    ],
    "sg:phone":"+1 254 697 8141",
    "sg:postcode":"76520",
    "sg:province":"TX",
    "wof:name":"Order of Sons of Hermann",
    "wof:placetype":"venue"
},
  "geometry": {"coordinates":[-96.967043,30.861365],"type":"Point"}
}