{
  "type": "Feature",
  "properties": {
    "iso:country":"US",
    "sg:address":"14 Inwood Manor",
    "sg:city":"San Antonio",
    "sg:classifiers":[
        {
            "category":"Building & Trades",
            "subcategory":"Construction",
            "type":"Services"
        }
    ],
    "sg:phone":"+1 210 492 9448",
    "sg:postcode":"78248",
    "sg:province":"TX",
    "sg:tags":[
        "home",
        "family"
    ],
    "wof:name":"Bill Kulesza Homes Inc",
    "wof:placetype":"venue"
},
  "geometry": {"coordinates":[-98.53840599999999,29.58649],"type":"Point"}
}