{
  "type": "Feature",
  "properties": {
    "iso:country":"US",
    "sg:address":"4100 Westheimer Rd",
    "sg:city":"Houston",
    "sg:classifiers":[
        {
            "category":"Professional",
            "subcategory":"Management & Consulting",
            "type":"Services"
        }
    ],
    "sg:phone":"+1 713 993 9898",
    "sg:postcode":"77027",
    "sg:province":"TX",
    "sg:tags":[
        "business"
    ],
    "wof:name":"AMR Travel Inc",
    "wof:placetype":"venue"
},
  "geometry": {"coordinates":[-95.44826500000001,29.741623],"type":"Point"}
}