{
  "type": "Feature",
  "properties": {
    "iso:country":"US",
    "sg:address":"509 Elm St",
    "sg:city":"Dallas",
    "sg:classifiers":[
        {
            "category":"Restaurant",
            "type":"Food & Drink"
        }
    ],
    "sg:menulink":"http://www.allmenus.com/tx/northeast/62557-subway/menu/",
    "sg:phone":"+1 214 651 9268",
    "sg:postcode":"75202",
    "sg:province":"TX",
    "sg:tags":[
        "american",
        "sandwich"
    ],
    "wof:name":"Subway",
    "wof:placetype":"venue"
},
  "geometry": {"coordinates":[-96.807928,32.779592],"type":"Point"}
}