{
  "type": "Feature",
  "properties": {
    "iso:country":"US",
    "sg:address":"5606 N Navarro St",
    "sg:city":"Victoria",
    "sg:classifiers":[
        {
            "category":"Professional",
            "subcategory":"Accounting & Tax Preparation",
            "type":"Services"
        }
    ],
    "sg:phone":"+1 361 485 6631",
    "sg:postcode":"77904",
    "sg:province":"TX",
    "sg:tags":[
        "return",
        "filing"
    ],
    "wof:name":"National Tax Solutions Acctg",
    "wof:placetype":"venue"
},
  "geometry": {"coordinates":[-96.998632,28.847338],"type":"Point"}
}