{
  "type": "Feature",
  "properties": {
    "iso:country":"US",
    "sg:address":"2706 Burning Ridge St",
    "sg:city":"San Antonio",
    "sg:classifiers":[
        {
            "category":"Local Transit",
            "type":"Transportation"
        }
    ],
    "sg:phone":"+1 210 496 7448",
    "sg:postcode":"78247",
    "sg:province":"TX",
    "sg:tags":[
        "bus",
        "charter"
    ],
    "wof:name":"Bg Tours & Transportation",
    "wof:placetype":"venue"
},
  "geometry": {"coordinates":[-98.446744,29.569892],"type":"Point"}
}