{
  "type": "Feature",
  "properties": {
    "iso:country":"US",
    "sg:address":"3215 Canton St",
    "sg:city":"Dallas",
    "sg:classifiers":[
        {
            "category":"Home & Garden",
            "subcategory":"Home Furnishings",
            "type":"Retail Goods"
        },
        {
            "category":"Building & Trades",
            "subcategory":"Construction",
            "type":"Services"
        },
        {
            "category":"Manufacturing",
            "subcategory":"Building Materials",
            "type":"Manufacturing & Wholesale Goods"
        }
    ],
    "sg:phone":"+1 214 742 4218",
    "sg:postcode":"75226",
    "sg:province":"TX",
    "sg:tags":[
        "industrial",
        "cabinetmakers-commercial",
        "cabinet",
        "refacing",
        "resurfacing",
        "maker",
        "cabinets-refinishing",
        "kitchen"
    ],
    "wof:name":"Jackson Cabinet & Fixtures",
    "wof:placetype":"venue"
},
  "geometry": {"coordinates":[-96.777241,32.783461],"type":"Point"}
}