{
  "type": "Feature",
  "properties": {
    "iso:country":"US",
    "sg:address":"101 N Dillard St",
    "sg:city":"Bryan",
    "sg:classifiers":[
        {
            "category":"Restaurant",
            "type":"Food & Drink"
        }
    ],
    "sg:phone":"+1 979 774 5928",
    "sg:postcode":"77803",
    "sg:province":"TX",
    "sg:tags":[
        "eating"
    ],
    "wof:name":"Cafe Espresso",
    "wof:placetype":"venue"
},
  "geometry": {"coordinates":[-96.360102,30.669462],"type":"Point"}
}