{
  "type": "Feature",
  "properties": {
    "iso:country":"US",
    "sg:address":"1333 Slocum St",
    "sg:city":"Dallas",
    "sg:classifiers":[
        {
            "category":"Retail",
            "subcategory":"Repair Shop",
            "type":"Services"
        }
    ],
    "sg:phone":"+1 214 744 5488",
    "sg:postcode":"75207",
    "sg:province":"TX",
    "sg:tags":[
        "lighting",
        "fixture"
    ],
    "wof:name":"Crow Chandelier Svc",
    "wof:placetype":"venue"
},
  "geometry": {"coordinates":[-96.817179,32.790564],"type":"Point"}
}