{
  "type": "Feature",
  "properties": {
    "iso:country":"US",
    "sg:address":"621 Navigation Blvd",
    "sg:city":"Corpus Christi",
    "sg:classifiers":[
        {
            "category":"Wholesale",
            "subcategory":"Machinery & Supplies",
            "type":"Manufacturing & Wholesale Goods"
        }
    ],
    "sg:phone":"+1 361 289 1255",
    "sg:postcode":"78408",
    "sg:province":"TX",
    "sg:tags":[
        "equipment",
        "transformer",
        "industrial",
        "mfg"
    ],
    "wof:name":"Fisher Controls Co",
    "wof:placetype":"venue"
},
  "geometry": {"coordinates":[-97.453025,27.799945],"type":"Point"}
}