{
  "type": "Feature",
  "properties": {
    "iso:country":"US",
    "sg:address":"14214 Cairns Ct",
    "sg:city":"Sugar Land",
    "sg:classifiers":[
        {
            "category":"Professional",
            "subcategory":"Business Services",
            "type":"Services"
        }
    ],
    "sg:phone":"+1 281 565 2915",
    "sg:postcode":"77478",
    "sg:province":"TX",
    "wof:name":"Lalani Aziz",
    "wof:placetype":"venue"
},
  "geometry": {"coordinates":[-95.681595,29.608652],"type":"Point"}
}