{
  "type": "Feature",
  "properties": {
    "iso:country":"US",
    "sg:address":"2218 Creekside Cir N",
    "sg:city":"Irving",
    "sg:classifiers":[
        {
            "category":"Health Services",
            "subcategory":"Doctor",
            "type":"Services"
        }
    ],
    "sg:phone":"+1 972 401 9099",
    "sg:postcode":"75063",
    "sg:province":"TX",
    "wof:name":"Michael McWatters",
    "wof:placetype":"venue"
},
  "geometry": {"coordinates":[-96.974024,32.907364],"type":"Point"}
}