{
  "type": "Feature",
  "properties": {
    "iso:country":"US",
    "sg:address":"2208 Tilden Ave",
    "sg:city":"Laredo",
    "sg:classifiers":[
        {
            "category":"Shopping",
            "subcategory":"Gifts & Souvenirs",
            "type":"Retail Goods"
        }
    ],
    "sg:phone":"+1 956 722 5307",
    "sg:postcode":"78040",
    "sg:province":"TX",
    "wof:name":"Specially For You",
    "wof:placetype":"venue"
},
  "geometry": {"coordinates":[-99.48763700000001,27.516594],"type":"Point"}
}