{
  "type": "Feature",
  "properties": {
    "iso:country":"US",
    "sg:address":"6710 Bryn Mawr Dr",
    "sg:city":"Austin",
    "sg:classifiers":[
        {
            "category":"Personal",
            "type":"Services"
        }
    ],
    "sg:phone":"+1 512 929 0757",
    "sg:postcode":"78723",
    "sg:province":"TX",
    "wof:name":"Harleys Helping Hand",
    "wof:placetype":"venue"
},
  "geometry": {"coordinates":[-97.671054,30.314299],"type":"Point"}
}