{
  "type": "Feature",
  "properties": {
    "iso:country":"US",
    "sg:address":"245 Keller Pkwy",
    "sg:city":"Keller",
    "sg:classifiers":[
        {
            "category":"Building & Trades",
            "subcategory":"Landscaping Services",
            "type":"Services"
        }
    ],
    "sg:phone":"+1 817 431 0135",
    "sg:postcode":"76248",
    "sg:province":"TX",
    "sg:tags":[
        "landscape",
        "contractor"
    ],
    "wof:name":"Ozark Tree Care Inc",
    "wof:placetype":"venue"
},
  "geometry": {"coordinates":[-97.249405,32.934531],"type":"Point"}
}