{
  "type": "Feature",
  "properties": {
    "iso:country":"US",
    "sg:address":"291 Grand Ave",
    "sg:city":"Southlake",
    "sg:classifiers":[
        {
            "category":"Restaurant",
            "type":"Food & Drink"
        }
    ],
    "sg:phone":"+1 817 310 3116",
    "sg:postcode":"76092",
    "sg:province":"TX",
    "sg:tags":[
        "pizza"
    ],
    "wof:name":"Campania Pizza",
    "wof:placetype":"venue"
},
  "geometry": {"coordinates":[-97.13054700000001,32.943508],"type":"Point"}
}