{
  "type": "Feature",
  "properties": {
    "iso:country":"US",
    "sg:address":"1509 Proctor Ave",
    "sg:city":"Waco",
    "sg:classifiers":[
        {
            "category":"Social Services",
            "subcategory":"Child Care",
            "type":"Services"
        }
    ],
    "sg:phone":"+1 254 235 5637",
    "sg:postcode":"76708",
    "sg:province":"TX",
    "wof:name":"Little Kings & Queens",
    "wof:placetype":"venue"
},
  "geometry": {"coordinates":[-97.157291,31.567818],"type":"Point"}
}