{
  "type": "Feature",
  "properties": {
    "iso:country":"US",
    "sg:address":"12200 Carl Rd",
    "sg:city":"Creedmoor",
    "sg:classifiers":[
        {
            "category":"Utilities",
            "subcategory":"Refuse",
            "type":"Services"
        }
    ],
    "sg:phone":"+1 512 392 1515",
    "sg:postcode":"78610",
    "sg:province":"TX",
    "sg:tags":[
        "garbage",
        "collection"
    ],
    "sg:website":"www.texasdisposal.com",
    "wof:name":"Texas Disposal Systems Inc",
    "wof:placetype":"venue"
},
  "geometry": {"coordinates":[-97.754493,30.103239],"type":"Point"}
}