{
  "type": "Feature",
  "properties": {
    "iso:country":"US",
    "sg:address":"507 S Main St",
    "sg:city":"Duncanville",
    "sg:classifiers":[
        {
            "category":"Restaurant",
            "type":"Food & Drink"
        }
    ],
    "sg:phone":"+1 972 298 3156",
    "sg:postcode":"75116",
    "sg:province":"TX",
    "sg:tags":[
        "fast"
    ],
    "sg:website":"www.sonicdrivein.com",
    "wof:name":"Sonic Drive-In",
    "wof:placetype":"venue"
},
  "geometry": {"coordinates":[-96.90830200000001,32.647499],"type":"Point"}
}