{
  "type": "Feature",
  "properties": {
    "iso:country":"US",
    "sg:address":"1409 E Main St",
    "sg:city":"Gatesville",
    "sg:classifiers":[
        {
            "category":"Cinema",
            "subcategory":"Movie Rental",
            "type":"Entertainment"
        }
    ],
    "sg:phone":"+1 254 248 1448",
    "sg:postcode":"76528",
    "sg:province":"TX",
    "sg:tags":[
        "leasing",
        "video",
        "disc",
        "tape"
    ],
    "wof:name":"Movie Gallery",
    "wof:placetype":"venue"
},
  "geometry": {"coordinates":[-97.74221,31.434977],"type":"Point"}
}