{
  "type": "Feature",
  "properties": {
    "iso:country":"US",
    "sg:address":"1281 Sunset Cir",
    "sg:city":"Center",
    "sg:classifiers":[
        {
            "category":"Real Estate",
            "subcategory":"Real Estate Services",
            "type":"Services"
        },
        {
            "category":"Real Estate",
            "subcategory":"Real Estate Operator",
            "type":"Services"
        }
    ],
    "sg:phone":"+1 936 598 4655",
    "sg:postcode":"75935",
    "sg:province":"TX",
    "sg:tags":[
        "vacancy",
        "apartment",
        "rental",
        "listing"
    ],
    "wof:name":"Paradise Villa",
    "wof:placetype":"venue"
},
  "geometry": {"coordinates":[-94.16415000000001,31.808213],"type":"Point"}
}