{
  "type": "Feature",
  "properties": {
    "iso:country":"US",
    "sg:address":"2108 Bonham Ave",
    "sg:city":"Odessa",
    "sg:classifiers":[
        {
            "category":"Organizations",
            "subcategory":"Religious Organization",
            "type":"Services"
        }
    ],
    "sg:phone":"+1 432 367 9344",
    "sg:postcode":"79761",
    "sg:province":"TX",
    "wof:name":"Saint Stephens Chrsmtc Epscpl",
    "wof:placetype":"venue"
},
  "geometry": {"coordinates":[-102.3506,31.872789],"type":"Point"}
}