{
  "type": "Feature",
  "properties": {
    "iso:country":"US",
    "sg:address":"126 W Central Ave",
    "sg:city":"Comanche",
    "sg:classifiers":[
        {
            "category":"Shopping",
            "subcategory":"Clothing, Apparel, & Fashions",
            "type":"Retail Goods"
        }
    ],
    "sg:phone":"+1 325 356 3151",
    "sg:postcode":"76442",
    "sg:province":"TX",
    "sg:tags":[
        "department",
        "store"
    ],
    "wof:name":"Harrys Department Store 2",
    "wof:placetype":"venue"
},
  "geometry": {"coordinates":[-98.60474499999999,31.897345],"type":"Point"}
}