{
  "type": "Feature",
  "properties": {
    "iso:country":"US",
    "sg:address":"22515 Bucktrout Ln",
    "sg:city":"Katy",
    "sg:classifiers":[
        {
            "category":"Manufacturing",
            "subcategory":"Glass & Minerals",
            "type":"Manufacturing & Wholesale Goods"
        }
    ],
    "sg:phone":"+1 281 347 7675",
    "sg:postcode":"77449",
    "sg:province":"TX",
    "sg:tags":[
        "tile",
        "cut",
        "ceramic",
        "mfg"
    ],
    "wof:name":"Benchco Services",
    "wof:placetype":"venue"
},
  "geometry": {"coordinates":[-95.763082,29.795927],"type":"Point"}
}