{
  "type": "Feature",
  "properties": {
    "iso:country":"US",
    "sg:address":"5830 Bandera Rd",
    "sg:city":"San Antonio",
    "sg:classifiers":[
        {
            "category":"Shopping",
            "subcategory":"Stationery & Office Supplies",
            "type":"Retail Goods"
        }
    ],
    "sg:phone":"+1 210 521 1123",
    "sg:postcode":"78238",
    "sg:province":"TX",
    "sg:tags":[
        "furniture"
    ],
    "wof:name":"Office Max",
    "wof:placetype":"venue"
},
  "geometry": {"coordinates":[-98.59918399999999,29.482161],"type":"Point"}
}