{
  "type": "Feature",
  "properties": {
    "iso:country":"US",
    "sg:address":"320 S R L Thornton Fwy",
    "sg:city":"Dallas",
    "sg:classifiers":[
        {
            "category":"Professional",
            "subcategory":"Lawyer & Legal Services",
            "type":"Services"
        }
    ],
    "sg:phone":"+1 214 941 1881",
    "sg:postcode":"75203",
    "sg:province":"TX",
    "sg:tags":[
        "attorney"
    ],
    "sg:website":"www.wglegal.com",
    "wof:name":"West & Gooden PC",
    "wof:placetype":"venue"
},
  "geometry": {"coordinates":[-96.808857,32.75516],"type":"Point"}
}