{
  "type": "Feature",
  "properties": {
    "iso:country":"US",
    "sg:address":"3607 College Ave",
    "sg:city":"Snyder",
    "sg:classifiers":[
        {
            "category":"Autos & Motor Vehicles",
            "subcategory":"Auto Supplies",
            "type":"Retail Goods"
        }
    ],
    "sg:phone":"+1 325 573 1651",
    "sg:postcode":"79549",
    "sg:province":"TX",
    "sg:tags":[
        "automobile",
        "parts"
    ],
    "sg:website":"www.oreillyautoparts.com",
    "wof:name":"O'Reilly Auto Parts",
    "wof:placetype":"venue"
},
  "geometry": {"coordinates":[-100.91917599999999,32.705616],"type":"Point"}
}