{
  "type": "Feature",
  "properties": {
    "iso:country":"US",
    "sg:address":"12422 Wedgehill Ln",
    "sg:city":"Houston",
    "sg:classifiers":[
        {
            "category":"Building & Trades",
            "subcategory":"Construction",
            "type":"Services"
        }
    ],
    "sg:phone":"+1 281 497 0398",
    "sg:postcode":"77077",
    "sg:province":"TX",
    "sg:tags":[
        "residential"
    ],
    "wof:name":"Young Construction & Home",
    "wof:placetype":"venue"
},
  "geometry": {"coordinates":[-95.601866,29.748358],"type":"Point"}
}