{
  "type": "Feature",
  "properties": {
    "iso:country":"US",
    "sg:address":"517 State Hwy 323 NE",
    "sg:city":"Tyler",
    "sg:classifiers":[
        {
            "category":"Wholesale",
            "subcategory":"Auto Parts",
            "type":"Manufacturing & Wholesale Goods"
        }
    ],
    "sg:phone":"+1 903 595 3495",
    "sg:postcode":"75706",
    "sg:province":"TX",
    "sg:tags":[
        "equipment",
        "truck"
    ],
    "wof:name":"Tyler Truck & Trailer Inc",
    "wof:placetype":"venue"
},
  "geometry": {"coordinates":[-95.28984199999999,32.39],"type":"Point"}
}