{
  "type": "Feature",
  "properties": {
    "iso:country":"US",
    "sg:address":"803 W Pipeline Rd",
    "sg:city":"Hurst",
    "sg:classifiers":[
        {
            "category":"Retail",
            "subcategory":"Laundry & Dry Cleaning",
            "type":"Services"
        }
    ],
    "sg:phone":"+1 817 284 7101",
    "sg:postcode":"76053",
    "sg:province":"TX",
    "sg:tags":[
        "garment",
        "agent"
    ],
    "wof:name":"Comet Cleaners",
    "wof:placetype":"venue"
},
  "geometry": {"coordinates":[-97.19078,32.823579],"type":"Point"}
}