{
  "type": "Feature",
  "properties": {
    "iso:country":"US",
    "sg:address":"1655 Fm 85",
    "sg:city":"Ennis",
    "sg:classifiers":[
        {
            "category":"Building & Trades",
            "subcategory":"Construction",
            "type":"Services"
        }
    ],
    "sg:phone":"+1 972 878 4543",
    "sg:postcode":"75119",
    "sg:province":"TX",
    "sg:tags":[
        "road",
        "contractor"
    ],
    "wof:name":"Spence Dozer Service",
    "wof:placetype":"venue"
},
  "geometry": {"coordinates":[-96.566087,32.316572],"type":"Point"}
}