{
  "type": "Feature",
  "properties": {
    "iso:country":"US",
    "sg:address":"3301 Oak Lawn Ave",
    "sg:city":"Dallas",
    "sg:classifiers":[
        {
            "category":"Personal",
            "subcategory":"Beauty Salon",
            "type":"Services"
        }
    ],
    "sg:phone":"+1 214 520 0116",
    "sg:postcode":"75219",
    "sg:province":"TX",
    "sg:tags":[
        "shop"
    ],
    "wof:name":"William Carr Salon",
    "wof:placetype":"venue"
},
  "geometry": {"coordinates":[-96.80666600000001,32.810966],"type":"Point"}
}