{
  "type": "Feature",
  "properties": {
    "iso:country":"US",
    "sg:address":"6814 Portuguese Bend Dr",
    "sg:city":"Missouri City",
    "sg:classifiers":[
        {
            "category":"Restaurant",
            "type":"Food & Drink"
        }
    ],
    "sg:phone":"+1 281 208 0610",
    "sg:postcode":"77459",
    "sg:province":"TX",
    "sg:tags":[
        "eating"
    ],
    "wof:name":"Dim Sum To Go Inc",
    "wof:placetype":"venue"
},
  "geometry": {"coordinates":[-95.565414,29.557564],"type":"Point"}
}