{
  "type": "Feature",
  "properties": {
    "iso:country":"US",
    "sg:address":"6434 E Mockingbird Ln Ste 107",
    "sg:city":"Dallas",
    "sg:classifiers":[
        {
            "category":"Health Services",
            "subcategory":"Clinic",
            "type":"Services"
        }
    ],
    "sg:postcode":"75214",
    "sg:province":"TX",
    "sg:tags":[
        "loss",
        "weight"
    ],
    "sg:website":"www.weightwatchers.com",
    "wof:name":"Weight Watchers",
    "wof:placetype":"venue"
},
  "geometry": {"coordinates":[-96.751988,32.836398],"type":"Point"}
}