{
  "type": "Feature",
  "properties": {
    "iso:country":"US",
    "sg:address":"814 Stratford Dr",
    "sg:city":"Southlake",
    "sg:classifiers":[
        {
            "category":"Shopping",
            "subcategory":"Florist",
            "type":"Retail Goods"
        }
    ],
    "sg:phone":"+1 817 251 8076",
    "sg:postcode":"76092",
    "sg:province":"TX",
    "wof:name":"Heavenly Meadows",
    "wof:placetype":"venue"
},
  "geometry": {"coordinates":[-97.165848,32.934899],"type":"Point"}
}