{
  "type": "Feature",
  "properties": {
    "iso:country":"US",
    "sg:address":"10015 Military Dr",
    "sg:city":"Conroe",
    "sg:classifiers":[
        {
            "category":"Airport",
            "type":"Transportation"
        }
    ],
    "sg:phone":"+1 936 788 7333",
    "sg:postcode":"77303",
    "sg:province":"TX",
    "sg:tags":[
        "aircraft",
        "maintenance"
    ],
    "sg:website":"www.avionicsunlimited.com",
    "wof:name":"Avionics Unlimited",
    "wof:placetype":"venue"
},
  "geometry": {"coordinates":[-95.423349,30.347714],"type":"Point"}
}