{
  "type": "Feature",
  "properties": {
    "iso:country":"US",
    "sg:address":"2819 S Zarzamora",
    "sg:city":"San Antonio",
    "sg:classifiers":[
        {
            "category":"Retail",
            "subcategory":"Auto Repair",
            "type":"Services"
        }
    ],
    "sg:phone":"+1 210 927 4501",
    "sg:postcode":"78225",
    "sg:province":"TX",
    "sg:tags":[
        "general"
    ],
    "wof:name":"Johns A A A Garage",
    "wof:placetype":"venue"
},
  "geometry": {"coordinates":[-98.532141,29.394774],"type":"Point"}
}