{
  "type": "Feature",
  "properties": {
    "iso:country":"US",
    "sg:address":"1100 N Collett Ave",
    "sg:city":"Dallas",
    "sg:classifiers":[
        {
            "category":"Professional",
            "subcategory":"Lawyer & Legal Services",
            "type":"Services"
        }
    ],
    "sg:phone":"+1 972 366 0213",
    "sg:postcode":"75214",
    "sg:province":"TX",
    "sg:website":"www.pelleylaw.com",
    "wof:name":"Pelley Law Office",
    "wof:placetype":"venue"
},
  "geometry": {"coordinates":[-96.769125,32.80285],"type":"Point"}
}