{
  "type": "Feature",
  "properties": {
    "iso:country":"US",
    "sg:address":"210 Mandan St",
    "sg:city":"Buda",
    "sg:classifiers":[
        {
            "category":"Building & Trades",
            "subcategory":"Construction",
            "type":"Services"
        }
    ],
    "sg:phone":"+1 512 312 1110",
    "sg:postcode":"78610",
    "sg:province":"TX",
    "sg:tags":[
        "general",
        "contractor"
    ],
    "wof:name":"Lyndale Builders Inc",
    "wof:placetype":"venue"
},
  "geometry": {"coordinates":[-97.83883299999999,30.078156],"type":"Point"}
}