{
  "type": "Feature",
  "properties": {
    "iso:country":"US",
    "sg:address":"1275 Glenoak Dr",
    "sg:city":"Corpus Christi",
    "sg:classifiers":[
        {
            "category":"Restaurant",
            "type":"Food & Drink"
        }
    ],
    "sg:phone":"+1 361 937 7028",
    "sg:postcode":"78418",
    "sg:province":"TX",
    "sg:tags":[
        "eating"
    ],
    "wof:name":"Captn Bo Bo N Sissys Inc",
    "wof:placetype":"venue"
},
  "geometry": {"coordinates":[-97.310901,27.649247],"type":"Point"}
}