{
  "type": "Feature",
  "properties": {
    "iso:country":"US",
    "sg:address":"3530 Forest Ln",
    "sg:city":"Dallas",
    "sg:classifiers":[
        {
            "category":"Professional",
            "subcategory":"Management & Consulting",
            "type":"Services"
        }
    ],
    "sg:phone":"+1 214 350 0465",
    "sg:postcode":"75234",
    "sg:province":"TX",
    "sg:tags":[
        "business"
    ],
    "wof:name":"Dallas North Consulting Group",
    "wof:placetype":"venue"
},
  "geometry": {"coordinates":[-96.860592,32.90964],"type":"Point"}
}