{
  "type": "Feature",
  "properties": {
    "iso:country":"US",
    "sg:address":"201 Larkspur St",
    "sg:city":"Lake Jackson",
    "sg:classifiers":[
        {
            "category":"Professional",
            "subcategory":"Engineering",
            "type":"Services"
        }
    ],
    "sg:phone":"+1 979 285 9331",
    "sg:postcode":"77566",
    "sg:province":"TX",
    "wof:name":"New World Engineering Inc",
    "wof:placetype":"venue"
},
  "geometry": {"coordinates":[-95.43561200000001,29.057409],"type":"Point"}
}