{
  "type": "Feature",
  "properties": {
    "iso:country":"US",
    "sg:address":"29035 FM 1462",
    "sg:city":"Damon",
    "sg:classifiers":[
        {
            "category":"Farming",
            "subcategory":"Farm & Veterinary Services",
            "type":"Manufacturing & Wholesale Goods"
        }
    ],
    "sg:phone":"+1 979 742 3166",
    "sg:postcode":"77430",
    "sg:province":"TX",
    "sg:tags":[
        "gin",
        "cotton"
    ],
    "wof:name":"Damon Farmers Gin",
    "wof:placetype":"venue"
},
  "geometry": {"coordinates":[-95.732533,29.298976],"type":"Point"}
}