{
  "type": "Feature",
  "properties": {
    "iso:country":"US",
    "sg:address":"4531 Ayers St",
    "sg:city":"Corpus Christi",
    "sg:classifiers":[
        {
            "category":"Wholesale",
            "subcategory":"Machinery & Supplies",
            "type":"Manufacturing & Wholesale Goods"
        }
    ],
    "sg:phone":"+1 361 814 4540",
    "sg:postcode":"78415",
    "sg:province":"TX",
    "sg:tags":[
        "equipment",
        "laundry"
    ],
    "wof:name":"Texas Laundry",
    "wof:placetype":"venue"
},
  "geometry": {"coordinates":[-97.421814,27.744564],"type":"Point"}
}