{
  "type": "Feature",
  "properties": {
    "iso:country":"US",
    "sg:address":"8506 Hwy 377 S",
    "sg:city":"Benbrook",
    "sg:classifiers":[
        {
            "category":"Restaurant",
            "type":"Food & Drink"
        }
    ],
    "sg:phone":"+1 817 249 2244",
    "sg:postcode":"76126",
    "sg:province":"TX",
    "wof:name":"Whataburger",
    "wof:placetype":"venue"
},
  "geometry": {"coordinates":[-97.46412100000001,32.679194],"type":"Point"}
}