{
  "type": "Feature",
  "properties": {
    "iso:country":"US",
    "sg:address":"1514 Pat Booker Rd",
    "sg:city":"Universal City",
    "sg:classifiers":[
        {
            "category":"Food & Beverages",
            "subcategory":"Groceries & Convenience Stores",
            "type":"Retail Goods"
        }
    ],
    "sg:phone":"+1 210 658 4629",
    "sg:postcode":"78148",
    "sg:province":"TX",
    "wof:name":"Nullinson's Convenience Store",
    "wof:placetype":"venue"
},
  "geometry": {"coordinates":[-98.303921,29.552142],"type":"Point"}
}