{
  "type": "Feature",
  "properties": {
    "iso:country":"US",
    "sg:address":"4727 Hondo Pass Ave",
    "sg:city":"El Paso",
    "sg:classifiers":[
        {
            "category":"Education",
            "subcategory":"Special Training",
            "type":"Public Place"
        }
    ],
    "sg:phone":"+1 915 755 8800",
    "sg:postcode":"79904",
    "sg:province":"TX",
    "sg:tags":[
        "instruction",
        "driving"
    ],
    "wof:name":"El Paso Northeast Driving Schl",
    "wof:placetype":"venue"
},
  "geometry": {"coordinates":[-106.433009,31.869856],"type":"Point"}
}