{
  "type": "Feature",
  "properties": {
    "iso:country":"US",
    "sg:address":"849 Sunfish St",
    "sg:city":"Austin",
    "sg:classifiers":[
        {
            "category":"Professional",
            "subcategory":"Business Services",
            "type":"Services"
        }
    ],
    "sg:phone":"+1 512 261 4250",
    "sg:postcode":"78734",
    "sg:province":"TX",
    "sg:tags":[
        "interior",
        "design"
    ],
    "wof:name":"Gateway Interiors",
    "wof:placetype":"venue"
},
  "geometry": {"coordinates":[-97.98229600000001,30.366119],"type":"Point"}
}