{
  "type": "Feature",
  "properties": {
    "iso:country":"US",
    "sg:address":"1602 W Kings Hwy",
    "sg:city":"San Antonio",
    "sg:classifiers":[
        {
            "category":"Wholesale",
            "subcategory":"Photographic Equipment",
            "type":"Manufacturing & Wholesale Goods"
        },
        {
            "category":"Building & Trades",
            "subcategory":"Equipment Rental",
            "type":"Services"
        }
    ],
    "sg:phone":"+1 210 736 1714",
    "sg:postcode":"78201",
    "sg:province":"TX",
    "sg:tags":[
        "player",
        "visual",
        "video",
        "rent",
        "recorder",
        "audio"
    ],
    "wof:name":"Bear Audio Visual Co Inc",
    "wof:placetype":"venue"
},
  "geometry": {"coordinates":[-98.523054,29.460115],"type":"Point"}
}