{
  "type": "Feature",
  "properties": {
    "iso:country":"US",
    "sg:address":"1239 US Hwy 281",
    "sg:city":"Falfurrias",
    "sg:classifiers":[
        {
            "category":"Retail",
            "subcategory":"Veterinary Services",
            "type":"Services"
        }
    ],
    "sg:phone":"+1 361 325 3048",
    "sg:postcode":"78355",
    "sg:province":"TX",
    "sg:tags":[
        "veterinarian"
    ],
    "wof:name":"Las Palmas Veterinary Hospital",
    "wof:placetype":"venue"
},
  "geometry": {"coordinates":[-98.143692,27.213091],"type":"Point"}
}