{
  "type": "Feature",
  "properties": {
    "iso:country":"US",
    "sg:address":"3600 Esters Rd",
    "sg:city":"Irving",
    "sg:classifiers":[
        {
            "category":"Organizations",
            "subcategory":"Religious Organization",
            "type":"Services"
        }
    ],
    "sg:phone":"+1 972 257 1234",
    "sg:postcode":"75062",
    "sg:province":"TX",
    "sg:tags":[
        "church"
    ],
    "wof:name":"Church In Irving",
    "wof:placetype":"venue"
},
  "geometry": {"coordinates":[-97.007857,32.855884],"type":"Point"}
}