{
  "type": "Feature",
  "properties": {
    "iso:country":"US",
    "sg:address":"6863 Sonoma",
    "sg:city":"Irving",
    "sg:classifiers":[
        {
            "category":"Professional",
            "subcategory":"Computer Services",
            "type":"Services"
        }
    ],
    "sg:phone":"+1 415 203 6011",
    "sg:postcode":"75039",
    "sg:province":"TX",
    "sg:tags":[
        "insidepoint",
        "ci",
        "competitive-intelligence"
    ],
    "wof:name":"InsidePoint",
    "wof:placetype":"venue"
},
  "geometry": {"coordinates":[-96.934089,32.905027],"type":"Point"}
}