{
  "type": "Feature",
  "properties": {
    "iso:country":"US",
    "sg:address":"6003 Brown Rock Trl",
    "sg:city":"Austin",
    "sg:classifiers":[
        {
            "category":"Professional",
            "subcategory":"Lawyer & Legal Services",
            "type":"Services"
        }
    ],
    "sg:phone":"+1 512 288 0793",
    "sg:postcode":"78749",
    "sg:province":"TX",
    "wof:name":"George H Watson",
    "wof:placetype":"venue"
},
  "geometry": {"coordinates":[-97.870029,30.21612],"type":"Point"}
}