{
  "type": "Feature",
  "properties": {
    "iso:country":"US",
    "sg:address":"150 Boca Raton Way",
    "sg:city":"Lancaster",
    "sg:classifiers":[
        {
            "category":"Place Of Worship",
            "type":"Public Place"
        }
    ],
    "sg:phone":"+1 972 230 4358",
    "sg:postcode":"75146",
    "sg:province":"TX",
    "sg:tags":[
        "church"
    ],
    "wof:name":"Corrine's Touch Of Class",
    "wof:placetype":"venue"
},
  "geometry": {"coordinates":[-96.81554300000001,32.593311],"type":"Point"}
}