{
  "type": "Feature",
  "properties": {
    "iso:country":"US",
    "sg:address":"1750 Valley View Ln",
    "sg:city":"Dallas",
    "sg:classifiers":[
        {
            "category":"Real Estate",
            "subcategory":"Real Estate Agent",
            "type":"Services"
        },
        {
            "category":"Professional",
            "subcategory":"Management & Consulting",
            "type":"Services"
        }
    ],
    "sg:phone":"+1 972 243 7648",
    "sg:postcode":"75234",
    "sg:province":"TX",
    "sg:tags":[
        "fuel",
        "residential",
        "manager"
    ],
    "wof:name":"Sunridge Management Group Inc",
    "wof:placetype":"venue"
},
  "geometry": {"coordinates":[-96.921139,32.919356],"type":"Point"}
}