{
  "type": "Feature",
  "properties": {
    "iso:country":"US",
    "sg:address":"6706 Sawmill Rd",
    "sg:city":"Dallas",
    "sg:classifiers":[
        {
            "category":"Shopping",
            "subcategory":"Books",
            "type":"Retail Goods"
        }
    ],
    "sg:phone":"+1 214 369 1345",
    "sg:postcode":"75252",
    "sg:province":"TX",
    "sg:tags":[
        "dealer"
    ],
    "sg:website":"www.sbdbooks.com",
    "wof:name":"SBD Spanish Book Distr",
    "wof:placetype":"venue"
},
  "geometry": {"coordinates":[-96.784678,32.992813],"type":"Point"}
}