{
  "type": "Feature",
  "properties": {
    "iso:country":"US",
    "sg:address":"3230 S Gessner Rd",
    "sg:city":"Houston",
    "sg:classifiers":[
        {
            "category":"Wholesale",
            "subcategory":"Vending Machines",
            "type":"Manufacturing & Wholesale Goods"
        }
    ],
    "sg:phone":"+1 832 252 6554",
    "sg:postcode":"77063",
    "sg:province":"TX",
    "sg:tags":[
        "operator"
    ],
    "wof:name":"Sun Glow Vending",
    "wof:placetype":"venue"
},
  "geometry": {"coordinates":[-95.53919500000001,29.729595],"type":"Point"}
}