{
  "type": "Feature",
  "properties": {
    "iso:country":"US",
    "sg:address":"824 Exposition Ave",
    "sg:city":"Dallas",
    "sg:classifiers":[
        {
            "category":"Professional",
            "type":"Services"
        }
    ],
    "sg:phone":"+1 469 621 2895",
    "sg:postcode":"75226",
    "sg:province":"TX",
    "sg:tags":[
        "caterer"
    ],
    "wof:name":"Mobile Gourmet",
    "wof:placetype":"venue"
},
  "geometry": {"coordinates":[-96.7677,32.782501],"type":"Point"}
}