{
  "type": "Feature",
  "properties": {
    "iso:country":"US",
    "sg:address":"3600 Gus Thomasson Rd",
    "sg:city":"Mesquite",
    "sg:classifiers":[
        {
            "category":"Personal",
            "subcategory":"Beauty Salon",
            "type":"Services"
        }
    ],
    "sg:phone":"+1 972 686 1437",
    "sg:postcode":"75150",
    "sg:province":"TX",
    "sg:tags":[
        "shop"
    ],
    "wof:name":"Hairstyles By Alma",
    "wof:placetype":"venue"
},
  "geometry": {"coordinates":[-96.634075,32.808878],"type":"Point"}
}