{
  "type": "Feature",
  "properties": {
    "iso:country":"US",
    "sg:address":"5233 S Acres Dr",
    "sg:city":"Houston",
    "sg:classifiers":[
        {
            "category":"Building & Trades",
            "subcategory":"Construction",
            "type":"Services"
        }
    ],
    "sg:phone":"+1 713 738 0513",
    "sg:postcode":"77048",
    "sg:province":"TX",
    "sg:tags":[
        "carpentry",
        "contractor"
    ],
    "wof:name":"Paul Richard Construction Co",
    "wof:placetype":"venue"
},
  "geometry": {"coordinates":[-95.343159,29.642419],"type":"Point"}
}