{
  "type": "Feature",
  "properties": {
    "iso:country":"US",
    "sg:address":"5585 Boca Chica Blvd",
    "sg:city":"Brownsville",
    "sg:classifiers":[
        {
            "category":"Autos & Motor Vehicles",
            "subcategory":"Auto Supplies",
            "type":"Retail Goods"
        }
    ],
    "sg:phone":"+1 956 838 1990",
    "sg:postcode":"78521",
    "sg:province":"TX",
    "sg:tags":[
        "tire"
    ],
    "wof:name":"Perez Tires",
    "wof:placetype":"venue"
},
  "geometry": {"coordinates":[-97.432199,25.916194],"type":"Point"}
}