{
  "type": "Feature",
  "properties": {
    "iso:country":"US",
    "sg:address":"600 Shepherd Dr",
    "sg:city":"Houston",
    "sg:classifiers":[
        {
            "category":"Wholesale",
            "subcategory":"Groceries",
            "type":"Manufacturing & Wholesale Goods"
        }
    ],
    "sg:phone":"+1 713 863 8183",
    "sg:postcode":"77007",
    "sg:province":"TX",
    "sg:tags":[
        "general"
    ],
    "wof:name":"Sales Coordinated Intl",
    "wof:placetype":"venue"
},
  "geometry": {"coordinates":[-95.40942099999999,29.768265],"type":"Point"}
}