{
  "type": "Feature",
  "properties": {
    "iso:country":"US",
    "sg:address":"1500 US Hwy 281",
    "sg:city":"Marble Falls",
    "sg:classifiers":[
        {
            "category":"Retail",
            "subcategory":"Repair Shop",
            "type":"Services"
        }
    ],
    "sg:phone":"+1 830 693 3025",
    "sg:postcode":"78654",
    "sg:province":"TX",
    "sg:tags":[
        "taxidermist"
    ],
    "wof:name":"Highland Lakes Taxidermy",
    "wof:placetype":"venue"
},
  "geometry": {"coordinates":[-98.285888,30.526009],"type":"Point"}
}