{
  "type": "Feature",
  "properties": {
    "iso:country":"US",
    "sg:address":"300 Hackberry Ln",
    "sg:city":"Austin",
    "sg:classifiers":[
        {
            "category":"Building & Trades",
            "subcategory":"Construction",
            "type":"Services"
        }
    ],
    "sg:phone":"+1 512 799 5885",
    "sg:postcode":"78753",
    "sg:province":"TX",
    "sg:tags":[
        "wallcoverings-installation",
        "wallpaper",
        "painting",
        "contractor"
    ],
    "wof:name":"Edgars Painting",
    "wof:placetype":"venue"
},
  "geometry": {"coordinates":[-97.69300800000001,30.35956],"type":"Point"}
}