{
  "type": "Feature",
  "properties": {
    "iso:country":"US",
    "sg:address":"6 Kitty Hawk St W",
    "sg:city":"Richmond",
    "sg:classifiers":[
        {
            "category":"Food & Beverages",
            "subcategory":"Groceries & Convenience Stores",
            "type":"Retail Goods"
        }
    ],
    "sg:phone":"+1 281 341 5004",
    "sg:postcode":"77469",
    "sg:province":"TX",
    "wof:name":"Valu Max Inc",
    "wof:placetype":"venue"
},
  "geometry": {"coordinates":[-95.84171499999999,29.685677],"type":"Point"}
}