{
  "type": "Feature",
  "properties": {
    "iso:country":"US",
    "sg:address":"2605 Saint St",
    "sg:city":"Houston",
    "sg:classifiers":[
        {
            "category":"Manufacturing",
            "subcategory":"Furniture",
            "type":"Manufacturing & Wholesale Goods"
        }
    ],
    "sg:phone":"+1 713 961 1130",
    "sg:postcode":"77027",
    "sg:province":"TX",
    "sg:tags":[
        "household",
        "wood",
        "mfg"
    ],
    "wof:name":"Martin Programme Inc",
    "wof:placetype":"venue"
},
  "geometry": {"coordinates":[-95.435152,29.739725],"type":"Point"}
}