{
  "type": "Feature",
  "properties": {
    "iso:country":"US",
    "sg:address":"1203 Green Hills Rd",
    "sg:city":"Duncanville",
    "sg:classifiers":[
        {
            "category":"Banks & Credit Unions",
            "subcategory":"Financial Services",
            "type":"Services"
        }
    ],
    "sg:phone":"+1 972 780 5639",
    "sg:postcode":"75137",
    "sg:province":"TX",
    "sg:tags":[
        "company",
        "holding"
    ],
    "wof:name":"Turning Pt Prprty Holdings LLC",
    "wof:placetype":"venue"
},
  "geometry": {"coordinates":[-96.939655,32.636662],"type":"Point"}
}