{
  "type": "Feature",
  "properties": {
    "iso:country":"US",
    "sg:address":"4436 Red Barn",
    "sg:city":"Richardson",
    "sg:classifiers":[
        {
            "category":"Building & Trades",
            "subcategory":"Landscaping Services",
            "type":"Services"
        }
    ],
    "sg:phone":"+1 972 238 8535",
    "sg:postcode":"75082",
    "sg:province":"TX",
    "wof:name":"Truelove Maintenance",
    "wof:placetype":"venue"
},
  "geometry": {"coordinates":[-96.639606,33.004575],"type":"Point"}
}