{
  "type": "Feature",
  "properties": {
    "iso:country":"US",
    "sg:address":"9500 Westview Dr",
    "sg:city":"Houston",
    "sg:classifiers":[
        {
            "category":"Manufacturing",
            "subcategory":"Printing",
            "type":"Manufacturing & Wholesale Goods"
        }
    ],
    "sg:phone":"+1 713 827 0590",
    "sg:postcode":"77055",
    "sg:province":"TX",
    "sg:tags":[
        "printer",
        "commercial"
    ],
    "wof:name":"B & G Printing",
    "wof:placetype":"venue"
},
  "geometry": {"coordinates":[-95.524771,29.79291],"type":"Point"}
}