{
  "type": "Feature",
  "properties": {
    "iso:country":"US",
    "sg:address":"11237 Pellicano Dr",
    "sg:city":"El Paso",
    "sg:classifiers":[
        {
            "category":"Wholesale",
            "subcategory":"Machinery & Supplies",
            "type":"Manufacturing & Wholesale Goods"
        }
    ],
    "sg:phone":"+1 915 590 6263",
    "sg:postcode":"79935",
    "sg:province":"TX",
    "sg:tags":[
        "equipment",
        "industrial"
    ],
    "wof:name":"P S G",
    "wof:placetype":"venue"
},
  "geometry": {"coordinates":[-106.320554,31.747894],"type":"Point"}
}