{
  "type": "Feature",
  "properties": {
    "iso:country":"US",
    "sg:address":"915 W Noel St",
    "sg:city":"Memphis",
    "sg:classifiers":[
        {
            "category":"Personal",
            "subcategory":"Beauty Salon",
            "type":"Services"
        }
    ],
    "sg:phone":"+1 806 259 3816",
    "sg:postcode":"79245",
    "sg:province":"TX",
    "sg:tags":[
        "shop"
    ],
    "wof:name":"256 Connection",
    "wof:placetype":"venue"
},
  "geometry": {"coordinates":[-100.543899,34.724256],"type":"Point"}
}