{
  "type": "Feature",
  "properties": {
    "iso:country":"US",
    "sg:address":"7 Switchbud Pl",
    "sg:city":"Spring",
    "sg:classifiers":[
        {
            "category":"Professional",
            "subcategory":"Business Services",
            "type":"Services"
        }
    ],
    "sg:phone":"+1 281 367 0291",
    "sg:postcode":"77380",
    "sg:province":"TX",
    "sg:tags":[
        "box",
        "mail",
        "rental"
    ],
    "wof:name":"UPS Stores 577",
    "wof:placetype":"venue"
},
  "geometry": {"coordinates":[-95.470883,30.140489],"type":"Point"}
}