{
  "type": "Feature",
  "properties": {
    "iso:country":"US",
    "sg:address":"745 S Lamont St",
    "sg:city":"Aransas Pass",
    "sg:classifiers":[
        {
            "category":"Real Estate",
            "subcategory":"Real Estate Agent",
            "type":"Services"
        }
    ],
    "sg:phone":"+1 361 888 8891",
    "sg:postcode":"78336",
    "sg:province":"TX",
    "sg:tags":[
        "property",
        "appraisal"
    ],
    "wof:name":"Terrence F Wood Company",
    "wof:placetype":"venue"
},
  "geometry": {"coordinates":[-97.154021,27.901379],"type":"Point"}
}