{
  "type": "Feature",
  "properties": {
    "iso:country":"US",
    "sg:address":"10039 Bissonnet St",
    "sg:city":"Houston",
    "sg:classifiers":[
        {
            "category":"Professional",
            "subcategory":"Management & Consulting",
            "type":"Services"
        }
    ],
    "sg:phone":"+1 713 771 1115",
    "sg:postcode":"77036",
    "sg:province":"TX",
    "sg:tags":[
        "marketing",
        "consultant"
    ],
    "wof:name":"HCDO Marketing",
    "wof:placetype":"venue"
},
  "geometry": {"coordinates":[-95.555432,29.674896],"type":"Point"}
}