{
  "type": "Feature",
  "properties": {
    "iso:country":"US",
    "sg:address":"3625 Dresage Ln",
    "sg:city":"Flower Mound",
    "sg:classifiers":[
        {
            "category":"Professional",
            "type":"Services"
        }
    ],
    "sg:phone":"+1 972 355 4053",
    "sg:postcode":"75022",
    "sg:province":"TX",
    "wof:name":"Russell T Hicks",
    "wof:placetype":"venue"
},
  "geometry": {"coordinates":[-97.08797300000001,33.023295],"type":"Point"}
}