{
  "type": "Feature",
  "properties": {
    "iso:country":"US",
    "sg:address":"429 N Texana St",
    "sg:city":"Hallettsville",
    "sg:classifiers":[
        {
            "category":"Autos & Motor Vehicles",
            "subcategory":"Automobile Sales",
            "type":"Retail Goods"
        }
    ],
    "sg:phone":"+1 361 798 4000",
    "sg:postcode":"77964",
    "sg:province":"TX",
    "sg:tags":[
        "used"
    ],
    "wof:name":"Auto Brite",
    "wof:placetype":"venue"
},
  "geometry": {"coordinates":[-96.941416,29.449588],"type":"Point"}
}