{
  "type": "Feature",
  "properties": {
    "iso:country":"US",
    "sg:address":"2809 Benchmark Trl",
    "sg:city":"Killeen",
    "sg:classifiers":[
        {
            "category":"Social Services",
            "subcategory":"Child Care",
            "type":"Services"
        }
    ],
    "sg:phone":"+1 254 690 0025",
    "sg:postcode":"76543",
    "sg:province":"TX",
    "wof:name":"Tear Drop Daycare",
    "wof:placetype":"venue"
},
  "geometry": {"coordinates":[-97.69107099999999,31.137548],"type":"Point"}
}