{
  "type": "Feature",
  "properties": {
    "iso:country":"US",
    "sg:address":"115 West Rd",
    "sg:city":"Houston",
    "sg:classifiers":[
        {
            "category":"Organizations",
            "subcategory":"Religious Organization",
            "type":"Services"
        }
    ],
    "sg:phone":"+1 281 448 8496",
    "sg:postcode":"77037",
    "sg:province":"TX",
    "sg:tags":[
        "church"
    ],
    "sg:website":"www.adventpc.org",
    "wof:name":"Advent Presbyterian Church",
    "wof:placetype":"venue"
},
  "geometry": {"coordinates":[-95.40607900000001,29.915345],"type":"Point"}
}