{
  "type": "Feature",
  "properties": {
    "iso:country":"US",
    "sg:address":"9906 Mandeville Cir",
    "sg:city":"Austin",
    "sg:classifiers":[
        {
            "category":"Wholesale",
            "subcategory":"Vending Machines",
            "type":"Manufacturing & Wholesale Goods"
        }
    ],
    "sg:phone":"+1 512 258 1900",
    "sg:postcode":"78750",
    "sg:province":"TX",
    "sg:tags":[
        "operator"
    ],
    "wof:name":"D L Vending Co",
    "wof:placetype":"venue"
},
  "geometry": {"coordinates":[-97.803009,30.439369],"type":"Point"}
}