{
  "type": "Feature",
  "properties": {
    "iso:country":"US",
    "sg:address":"1401 W Main St",
    "sg:city":"Eastland",
    "sg:classifiers":[
        {
            "category":"Personal",
            "subcategory":"Beauty Salon",
            "type":"Services"
        }
    ],
    "sg:phone":"+1 254 629 2220",
    "sg:postcode":"76448",
    "sg:province":"TX",
    "wof:name":"Mane Street Salon",
    "wof:placetype":"venue"
},
  "geometry": {"coordinates":[-98.834557,32.401718],"type":"Point"}
}