{
  "type": "Feature",
  "properties": {
    "iso:country":"US",
    "sg:address":"7428 Yolanda Dr",
    "sg:city":"Fort Worth",
    "sg:classifiers":[
        {
            "category":"Banks & Credit Unions",
            "subcategory":"Financial Services",
            "type":"Services"
        }
    ],
    "sg:phone":"+1 817 451 9222",
    "sg:postcode":"76112",
    "sg:province":"TX",
    "sg:tags":[
        "investor"
    ],
    "wof:name":"Pp &B Investments LLC",
    "wof:placetype":"venue"
},
  "geometry": {"coordinates":[-97.196107,32.752143],"type":"Point"}
}