{
  "type": "Feature",
  "properties": {
    "iso:country":"US",
    "sg:address":"11851 Bandera Rd",
    "sg:city":"Helotes",
    "sg:classifiers":[
        {
            "category":"Restaurant",
            "type":"Food & Drink"
        }
    ],
    "sg:phone":"+1 210 372 0400",
    "sg:postcode":"78023",
    "sg:province":"TX",
    "wof:name":"Wings To Go",
    "wof:placetype":"venue"
},
  "geometry": {"coordinates":[-98.66738100000001,29.553747],"type":"Point"}
}