{
  "type": "Feature",
  "properties": {
    "iso:country":"US",
    "sg:address":"2515 Irving Blvd",
    "sg:city":"Dallas",
    "sg:classifiers":[
        {
            "category":"Taxi",
            "type":"Transportation"
        }
    ],
    "sg:phone":"+1 214 350 4445",
    "sg:postcode":"75207",
    "sg:province":"TX",
    "wof:name":"Terminal Taxi",
    "wof:placetype":"venue"
},
  "geometry": {"coordinates":[-96.840897,32.799],"type":"Point"}
}