{
  "type": "Feature",
  "properties": {
    "iso:country":"US",
    "sg:address":"807 Wink Ave",
    "sg:city":"Odessa",
    "sg:classifiers":[
        {
            "category":"Freight",
            "type":"Transportation"
        }
    ],
    "sg:phone":"+1 432 337 2334",
    "sg:postcode":"79761",
    "sg:province":"TX",
    "sg:tags":[
        "commercial",
        "storage"
    ],
    "wof:name":"Crenshaw Self Storage",
    "wof:placetype":"venue"
},
  "geometry": {"coordinates":[-102.360642,31.857577],"type":"Point"}
}