{
  "type": "Feature",
  "properties": {
    "iso:country":"US",
    "sg:address":"4214 Pleasant Oaks Ct",
    "sg:city":"Arlington",
    "sg:classifiers":[
        {
            "category":"Manufacturing",
            "subcategory":"Printing",
            "type":"Manufacturing & Wholesale Goods"
        }
    ],
    "sg:phone":"+1 817 516 0312",
    "sg:postcode":"76016",
    "sg:province":"TX",
    "sg:tags":[
        "lithographic",
        "commercial"
    ],
    "wof:name":"Proforma One Source Printing",
    "wof:placetype":"venue"
},
  "geometry": {"coordinates":[-97.188982,32.681098],"type":"Point"}
}