{
  "type": "Feature",
  "properties": {
    "iso:country":"US",
    "sg:address":"154 W Rhapsody Dr",
    "sg:city":"San Antonio",
    "sg:classifiers":[
        {
            "category":"Education",
            "subcategory":"School",
            "type":"Public Place"
        }
    ],
    "sg:phone":"+1 210 344 4852",
    "sg:postcode":"78216",
    "sg:province":"TX",
    "wof:name":"Chinese School of San Antonio",
    "wof:placetype":"venue"
},
  "geometry": {"coordinates":[-98.497777,29.546099],"type":"Point"}
}