{
  "type": "Feature",
  "properties": {
    "iso:country":"US",
    "sg:address":"708 US Hwy 62",
    "sg:city":"Wolfforth",
    "sg:classifiers":[
        {
            "category":"Personal",
            "subcategory":"Beauty Salon",
            "type":"Services"
        }
    ],
    "sg:phone":"+1 806 866 0201",
    "sg:postcode":"79382",
    "sg:province":"TX",
    "wof:name":"Kuts & Kurls",
    "wof:placetype":"venue"
},
  "geometry": {"coordinates":[-102.01497999999999,33.5006],"type":"Point"}
}