{
  "type": "Feature",
  "properties": {
    "iso:country":"US",
    "sg:address":"1116 E Main St",
    "sg:city":"League City",
    "sg:classifiers":[
        {
            "category":"Retail",
            "subcategory":"Auto Rental",
            "type":"Services"
        }
    ],
    "sg:phone":"+1 281 557 3313",
    "sg:postcode":"77573",
    "sg:province":"TX",
    "sg:tags":[
        "renting",
        "truck",
        "leasing"
    ],
    "wof:name":"Ryder Truck & Rental Service",
    "wof:placetype":"venue"
},
  "geometry": {"coordinates":[-95.085898,29.514644],"type":"Point"}
}