{
  "type": "Feature",
  "properties": {
    "iso:country":"US",
    "sg:address":"2054 W Main St",
    "sg:city":"Houston",
    "sg:classifiers":[
        {
            "category":"Professional",
            "subcategory":"Advertising",
            "type":"Services"
        }
    ],
    "sg:phone":"+1 713 526 3758",
    "sg:postcode":"77098",
    "sg:province":"TX",
    "sg:tags":[
        "agency"
    ],
    "wof:name":"T-Visions",
    "wof:placetype":"venue"
},
  "geometry": {"coordinates":[-95.40941100000001,29.73605],"type":"Point"}
}