{
  "type": "Feature",
  "properties": {
    "iso:country":"US",
    "sg:address":"18 Mangrove Cir",
    "sg:city":"Brownsville",
    "sg:classifiers":[
        {
            "category":"Real Estate",
            "subcategory":"Real Estate Operator",
            "type":"Services"
        }
    ],
    "sg:phone":"+1 956 541 5166",
    "sg:postcode":"78521",
    "sg:province":"TX",
    "sg:tags":[
        "building",
        "apartment"
    ],
    "wof:name":"Blanche Apts",
    "wof:placetype":"venue"
},
  "geometry": {"coordinates":[-97.482388,25.941275],"type":"Point"}
}