{
  "type": "Feature",
  "properties": {
    "iso:country":"US",
    "sg:address":"12400 Almeda Rd",
    "sg:city":"Houston",
    "sg:classifiers":[
        {
            "category":"Retail",
            "subcategory":"Laundry & Dry Cleaning",
            "type":"Services"
        }
    ],
    "sg:phone":"+1 713 434 0255",
    "sg:postcode":"77045",
    "sg:province":"TX",
    "wof:name":"Advance Cleaners",
    "wof:placetype":"venue"
},
  "geometry": {"coordinates":[-95.41411600000001,29.627739],"type":"Point"}
}