{
  "type": "Feature",
  "properties": {
    "iso:country":"US",
    "sg:address":"5250 Keystone St",
    "sg:city":"Houston",
    "sg:classifiers":[
        {
            "category":"Organizations",
            "subcategory":"Religious Organization",
            "type":"Services"
        }
    ],
    "sg:phone":"+1 713 644 2010",
    "sg:postcode":"77021",
    "sg:province":"TX",
    "wof:name":"Mighty God International Trade",
    "wof:placetype":"venue"
},
  "geometry": {"coordinates":[-95.33684,29.693774],"type":"Point"}
}