{
  "type": "Feature",
  "properties": {
    "iso:country":"US",
    "sg:address":"4427 State Hwy 105",
    "sg:city":"Brenham",
    "sg:classifiers":[
        {
            "category":"Home & Garden",
            "subcategory":"Home Furnishings",
            "type":"Retail Goods"
        }
    ],
    "sg:phone":"+1 979 836 9553",
    "sg:postcode":"77833",
    "sg:province":"TX",
    "wof:name":"Verdell A Toll Upholstery",
    "wof:placetype":"venue"
},
  "geometry": {"coordinates":[-96.35281999999999,30.203165],"type":"Point"}
}