{
  "type": "Feature",
  "properties": {
    "iso:country":"US",
    "sg:address":"2114 Shady Branch Dr",
    "sg:city":"Kingwood",
    "sg:classifiers":[
        {
            "category":"Place Of Worship",
            "type":"Public Place"
        }
    ],
    "sg:phone":"+1 281 312 0342",
    "sg:postcode":"77339",
    "sg:province":"TX",
    "sg:tags":[
        "church"
    ],
    "wof:name":"Christian Bible Church Of Kingwood, Texas",
    "wof:placetype":"venue"
},
  "geometry": {"coordinates":[-95.22412,30.035392],"type":"Point"}
}