{
  "type": "Feature",
  "properties": {
    "iso:country":"US",
    "sg:address":"4006 Tiger Dr",
    "sg:city":"Killeen",
    "sg:classifiers":[
        {
            "category":"Wholesale",
            "subcategory":"Non-durable Goods",
            "type":"Manufacturing & Wholesale Goods"
        }
    ],
    "sg:phone":"+1 254 526 8869",
    "sg:postcode":"76549",
    "sg:province":"TX",
    "sg:tags":[
        "merchandise-wholesale"
    ],
    "wof:name":"Internationnal Imports",
    "wof:placetype":"venue"
},
  "geometry": {"coordinates":[-97.784896,31.10344],"type":"Point"}
}