{
  "type": "Feature",
  "properties": {
    "iso:country":"US",
    "sg:address":"9262 Scenic Bluff Dr",
    "sg:city":"Austin",
    "sg:classifiers":[
        {
            "category":"Professional",
            "subcategory":"Art Services",
            "type":"Services"
        }
    ],
    "sg:phone":"+1 512 263 5506",
    "sg:postcode":"78733",
    "sg:province":"TX",
    "sg:tags":[
        "graphic",
        "design"
    ],
    "wof:name":"Advantage Graphics",
    "wof:placetype":"venue"
},
  "geometry": {"coordinates":[-97.890378,30.304082],"type":"Point"}
}