{
  "type": "Feature",
  "properties": {
    "iso:country":"US",
    "sg:address":"10135 Comanche Ln",
    "sg:city":"Houston",
    "sg:classifiers":[
        {
            "category":"Restaurant",
            "type":"Food & Drink"
        }
    ],
    "sg:phone":"+1 713 460 8024",
    "sg:postcode":"77041",
    "sg:province":"TX",
    "sg:tags":[
        "eating"
    ],
    "wof:name":"J&V Custom Bar B Que & Special",
    "wof:placetype":"venue"
},
  "geometry": {"coordinates":[-95.54183999999999,29.855394],"type":"Point"}
}