{
  "type": "Feature",
  "properties": {
    "iso:country":"US",
    "sg:address":"2544 Barrow St",
    "sg:city":"Abilene",
    "sg:classifiers":[
        {
            "category":"Shopping",
            "subcategory":"Used Merchandise",
            "type":"Retail Goods"
        }
    ],
    "sg:phone":"+1 325 692 2422",
    "sg:postcode":"79605",
    "sg:province":"TX",
    "sg:tags":[
        "antique"
    ],
    "wof:name":"Antique Gallery",
    "wof:placetype":"venue"
},
  "geometry": {"coordinates":[-99.75962800000001,32.417777],"type":"Point"}
}