{
  "type": "Feature",
  "properties": {
    "iso:country":"US",
    "sg:address":"4700 19th St",
    "sg:city":"Bacliff",
    "sg:classifiers":[
        {
            "category":"Shopping",
            "subcategory":"Bicycles & Sporting Goods",
            "type":"Retail Goods"
        }
    ],
    "sg:phone":"+1 281 559 4145",
    "sg:postcode":"77518",
    "sg:province":"TX",
    "wof:name":"Spillway Bait & Tackle",
    "wof:placetype":"venue"
},
  "geometry": {"coordinates":[-94.991608,29.497508],"type":"Point"}
}