{
  "type": "Feature",
  "properties": {
    "iso:country":"US",
    "sg:address":"3402 Chimney Rock Rd",
    "sg:city":"Houston",
    "sg:classifiers":[
        {
            "category":"Retail",
            "subcategory":"Laundry & Dry Cleaning",
            "type":"Services"
        }
    ],
    "sg:phone":"+1 832 251 0900",
    "sg:postcode":"77056",
    "sg:province":"TX",
    "sg:tags":[
        "cleaners"
    ],
    "wof:name":"Boss Cleaners",
    "wof:placetype":"venue"
},
  "geometry": {"coordinates":[-95.476478,29.727979],"type":"Point"}
}