{
  "type": "Feature",
  "properties": {
    "iso:country":"US",
    "sg:address":"6610 N Lamar Blvd",
    "sg:city":"Austin",
    "sg:classifiers":[
        {
            "category":"Real Estate",
            "subcategory":"Real Estate Agent",
            "type":"Services"
        }
    ],
    "sg:phone":"+1 512 467 8467",
    "sg:postcode":"78752",
    "sg:province":"TX",
    "wof:name":"Discount Cigs 21",
    "wof:placetype":"venue"
},
  "geometry": {"coordinates":[-97.72030700000001,30.335581],"type":"Point"}
}