{
  "type": "Feature",
  "properties": {
    "iso:country":"US",
    "sg:address":"438 Tresvant Dr",
    "sg:city":"Webster",
    "sg:classifiers":[
        {
            "category":"Professional",
            "subcategory":"Management & Consulting",
            "type":"Services"
        }
    ],
    "sg:phone":"+1 281 480 3914",
    "sg:postcode":"77598",
    "sg:province":"TX",
    "sg:tags":[
        "retail",
        "direct",
        "sales"
    ],
    "wof:name":"Mary Kay Cosmetics",
    "wof:placetype":"venue"
},
  "geometry": {"coordinates":[-95.149884,29.559381],"type":"Point"}
}