{
  "type": "Feature",
  "properties": {
    "iso:country":"US",
    "sg:address":"1631 Dorchester Dr",
    "sg:city":"Plano",
    "sg:classifiers":[
        {
            "category":"Real Estate",
            "subcategory":"Real Estate Services",
            "type":"Services"
        },
        {
            "category":"Real Estate",
            "subcategory":"Real Estate Agent",
            "type":"Services"
        }
    ],
    "sg:phone":"+1 972 964 5185",
    "sg:postcode":"75075",
    "sg:province":"TX",
    "sg:tags":[
        "buyer",
        "management",
        "broker"
    ],
    "wof:name":"Cambridge Real Estate",
    "wof:placetype":"venue"
},
  "geometry": {"coordinates":[-96.74617600000001,33.020538],"type":"Point"}
}