{
  "type": "Feature",
  "properties": {
    "iso:country":"US",
    "sg:address":"7227 Foxbrook Dr",
    "sg:city":"Humble",
    "sg:classifiers":[
        {
            "category":"Professional",
            "subcategory":"Art Services",
            "type":"Services"
        },
        {
            "category":"Professional",
            "subcategory":"Printing & Photocopies",
            "type":"Services"
        }
    ],
    "sg:phone":"+1 281 441 6226",
    "sg:postcode":"77338",
    "sg:province":"TX",
    "sg:tags":[
        "graphic",
        "services-commercial",
        "designer"
    ],
    "wof:name":"Million Miles Productions Digital Document Service",
    "wof:placetype":"venue"
},
  "geometry": {"coordinates":[-95.316468,30.018993],"type":"Point"}
}