{
  "type": "Feature",
  "properties": {
    "iso:country":"US",
    "sg:address":"2627 Pleasanton Rd",
    "sg:city":"San Antonio",
    "sg:classifiers":[
        {
            "category":"Restaurant",
            "type":"Food & Drink"
        }
    ],
    "sg:phone":"+1 210 921 2745",
    "sg:postcode":"78221",
    "sg:province":"TX",
    "sg:tags":[
        "eating"
    ],
    "wof:name":"B & B Smokehouse",
    "wof:placetype":"venue"
},
  "geometry": {"coordinates":[-98.503961,29.352722],"type":"Point"}
}