{
  "type": "Feature",
  "properties": {
    "iso:country":"US",
    "sg:address":"1212 14th St",
    "sg:city":"Huntsville",
    "sg:classifiers":[
        {
            "category":"Home & Garden",
            "subcategory":"Carpets & Floor Coverings",
            "type":"Retail Goods"
        }
    ],
    "sg:phone":"+1 936 291 9930",
    "sg:postcode":"77340",
    "sg:province":"TX",
    "sg:tags":[
        "material"
    ],
    "wof:name":"Carpet Store",
    "wof:placetype":"venue"
},
  "geometry": {"coordinates":[-95.552716,30.720419],"type":"Point"}
}