{
  "type": "Feature",
  "properties": {
    "iso:country":"US",
    "sg:address":"421 E Walnut St",
    "sg:city":"Fredericksburg",
    "sg:classifiers":[
        {
            "category":"Building & Trades",
            "subcategory":"Construction",
            "type":"Services"
        }
    ],
    "sg:phone":"+1 830 997 7923",
    "sg:postcode":"78624",
    "sg:province":"TX",
    "sg:tags":[
        "roofing",
        "contractor"
    ],
    "wof:name":"Nixon Roofing Inc",
    "wof:placetype":"venue"
},
  "geometry": {"coordinates":[-98.87333,30.26632],"type":"Point"}
}