{
  "type": "Feature",
  "properties": {
    "iso:country":"US",
    "sg:address":"313 State Hwy 100",
    "sg:city":"Port Isabel",
    "sg:classifiers":[
        {
            "category":"Retail",
            "subcategory":"Auto Repair",
            "type":"Services"
        }
    ],
    "sg:phone":"+1 956 943 5759",
    "sg:postcode":"78578",
    "sg:province":"TX",
    "sg:tags":[
        "body",
        "automobile",
        "painting"
    ],
    "wof:name":"M & M Body Shop",
    "wof:placetype":"venue"
},
  "geometry": {"coordinates":[-97.212324,26.074495],"type":"Point"}
}