{
  "type": "Feature",
  "properties": {
    "iso:country":"US",
    "sg:address":"3008 Story Rd W",
    "sg:city":"Irving",
    "sg:classifiers":[
        {
            "category":"Professional",
            "type":"Services"
        }
    ],
    "sg:phone":"+1 972 594 0510",
    "sg:postcode":"75038",
    "sg:province":"TX",
    "wof:name":"Techsource",
    "wof:placetype":"venue"
},
  "geometry": {"coordinates":[-96.98509300000001,32.871368],"type":"Point"}
}