{
  "type": "Feature",
  "properties": {
    "iso:country":"US",
    "sg:address":"10106 Sagecourt Dr",
    "sg:city":"Houston",
    "sg:classifiers":[
        {
            "category":"Professional",
            "subcategory":"Management & Consulting",
            "type":"Services"
        }
    ],
    "sg:phone":"+1 281 484 1243",
    "sg:postcode":"77089",
    "sg:province":"TX",
    "wof:name":"Larry J Riley Consulting",
    "wof:placetype":"venue"
},
  "geometry": {"coordinates":[-95.221098,29.578522],"type":"Point"}
}