{
  "type": "Feature",
  "properties": {
    "iso:country":"US",
    "sg:address":"212 N Liberty St",
    "sg:city":"Montgomery",
    "sg:classifiers":[
        {
            "category":"Farming",
            "subcategory":"Farm & Veterinary Services",
            "type":"Manufacturing & Wholesale Goods"
        }
    ],
    "sg:phone":"+1 936 597 8700",
    "sg:postcode":"77356",
    "sg:province":"TX",
    "sg:tags":[
        "used",
        "cotton",
        "merchandise",
        "ginning"
    ],
    "wof:name":"Old Cotton Gin Antiques",
    "wof:placetype":"venue"
},
  "geometry": {"coordinates":[-95.699198,30.399027],"type":"Point"}
}