{
  "type": "Feature",
  "properties": {
    "iso:country":"US",
    "sg:address":"2113 Wickiup Trl",
    "sg:city":"Harker Heights",
    "sg:classifiers":[
        {
            "category":"Health Services",
            "subcategory":"Doctor",
            "type":"Services"
        }
    ],
    "sg:phone":"+1 254 519 2438",
    "sg:postcode":"76548",
    "sg:province":"TX",
    "wof:name":"DMD Imports Inc",
    "wof:placetype":"venue"
},
  "geometry": {"coordinates":[-97.672307,31.067686],"type":"Point"}
}