{
  "type": "Feature",
  "properties": {
    "iso:country":"US",
    "sg:address":"1605 Richey St",
    "sg:city":"Pasadena",
    "sg:classifiers":[
        {
            "category":"Banks & Credit Unions",
            "subcategory":"Investment Brokerage",
            "type":"Services"
        }
    ],
    "sg:phone":"+1 713 920 0330",
    "sg:postcode":"77502",
    "sg:province":"TX",
    "sg:tags":[
        "consultant",
        "planning",
        "financial"
    ],
    "wof:name":"D & Y Financial Svc Conslnt",
    "wof:placetype":"venue"
},
  "geometry": {"coordinates":[-95.22088599999999,29.687327],"type":"Point"}
}