{
  "type": "Feature",
  "properties": {
    "iso:country":"US",
    "sg:address":"999 S McKinley Ave",
    "sg:city":"Hereford",
    "sg:classifiers":[
        {
            "category":"Government",
            "subcategory":"Office",
            "type":"Public Place"
        }
    ],
    "sg:phone":"+1 806 363 7133",
    "sg:postcode":"79045",
    "sg:province":"TX",
    "sg:tags":[
        "village"
    ],
    "wof:name":"Hereford Water Production",
    "wof:placetype":"venue"
},
  "geometry": {"coordinates":[-102.389301,34.803851],"type":"Point"}
}