{
  "type": "Feature",
  "properties": {
    "iso:country":"US",
    "sg:address":"103 Ave D",
    "sg:city":"Liberty",
    "sg:classifiers":[
        {
            "category":"Mining & Drilling",
            "type":"Manufacturing & Wholesale Goods"
        }
    ],
    "sg:phone":"+1 936 336 7717",
    "sg:postcode":"77575",
    "sg:province":"TX",
    "sg:tags":[
        "field",
        "oil"
    ],
    "wof:name":"B & J Consultants",
    "wof:placetype":"venue"
},
  "geometry": {"coordinates":[-94.770545,30.05327],"type":"Point"}
}