{
  "type": "Feature",
  "properties": {
    "iso:country":"US",
    "sg:address":"21126 Wildcroft Dr",
    "sg:city":"Katy",
    "sg:classifiers":[
        {
            "category":"Manufacturing",
            "subcategory":"Printing",
            "type":"Manufacturing & Wholesale Goods"
        }
    ],
    "sg:phone":"+1 281 855 2867",
    "sg:postcode":"77449",
    "sg:province":"TX",
    "sg:tags":[
        "lithographic",
        "commercial"
    ],
    "wof:name":"Pride Printing",
    "wof:placetype":"venue"
},
  "geometry": {"coordinates":[-95.72056600000001,29.852472],"type":"Point"}
}