{
  "type": "Feature",
  "properties": {
    "iso:country":"US",
    "sg:address":"1009 W Industrial Ave",
    "sg:city":"Midland",
    "sg:classifiers":[
        {
            "category":"Professional",
            "subcategory":"Business Services",
            "type":"Services"
        }
    ],
    "sg:phone":"+1 432 683 2262",
    "sg:postcode":"79701",
    "sg:province":"TX",
    "sg:tags":[
        "auctioneer"
    ],
    "wof:name":"Auctions & Svc Unlimited",
    "wof:placetype":"venue"
},
  "geometry": {"coordinates":[-102.08448,31.989994],"type":"Point"}
}