{
  "type": "Feature",
  "properties": {
    "iso:country":"US",
    "sg:address":"117 E Spicer Dr",
    "sg:city":"Kerrville",
    "sg:classifiers":[
        {
            "category":"Building & Trades",
            "subcategory":"Landscaping Services",
            "type":"Services"
        }
    ],
    "sg:phone":"+1 830 896 7615",
    "sg:postcode":"78028",
    "sg:province":"TX",
    "wof:name":"Robert & Pamela Jung",
    "wof:placetype":"venue"
},
  "geometry": {"coordinates":[-99.203965,29.980465],"type":"Point"}
}