{
  "type": "Feature",
  "properties": {
    "iso:country":"US",
    "sg:address":"1000 US Hwy 277",
    "sg:city":"Carrizo Springs",
    "sg:classifiers":[
        {
            "category":"Autos & Motor Vehicles",
            "subcategory":"Automobile Sales",
            "type":"Retail Goods"
        }
    ],
    "sg:phone":"+1 830 876 3588",
    "sg:postcode":"78834",
    "sg:province":"TX",
    "sg:tags":[
        "car",
        "dealer"
    ],
    "wof:name":"Bear Motor Sales",
    "wof:placetype":"venue"
},
  "geometry": {"coordinates":[-99.86434,28.523074],"type":"Point"}
}