{
  "type": "Feature",
  "properties": {
    "iso:country":"US",
    "sg:address":"20128 Pine Ln",
    "sg:city":"Montgomery",
    "sg:classifiers":[
        {
            "category":"Building & Trades",
            "subcategory":"Construction",
            "type":"Services"
        }
    ],
    "sg:phone":"+1 936 443 8559",
    "sg:postcode":"77356",
    "sg:province":"TX",
    "sg:tags":[
        "house"
    ],
    "wof:name":"Keane Custom Homes",
    "wof:placetype":"venue"
},
  "geometry": {"coordinates":[-95.670638,30.473874],"type":"Point"}
}