{
  "type": "Feature",
  "properties": {
    "iso:country":"US",
    "sg:address":"1601 W 11th Pl",
    "sg:city":"Big Spring",
    "sg:classifiers":[
        {
            "category":"Health Services",
            "subcategory":"Hospital",
            "type":"Services"
        }
    ],
    "sg:phone":"+1 432 263 0074",
    "sg:postcode":"79720",
    "sg:province":"TX",
    "sg:tags":[
        "general"
    ],
    "wof:name":"Reflections Program",
    "wof:placetype":"venue"
},
  "geometry": {"coordinates":[-101.49651799999999,32.238917],"type":"Point"}
}