{
  "type": "Feature",
  "properties": {
    "iso:country":"US",
    "sg:address":"2205 Fannin St",
    "sg:city":"Houston",
    "sg:classifiers":[
        {
            "category":"Sports & Exercise",
            "subcategory":"Gym",
            "type":"Entertainment"
        }
    ],
    "sg:phone":"+1 713 659 4998",
    "sg:postcode":"77002",
    "sg:province":"TX",
    "sg:tags":[
        "facility",
        "physical",
        "adult",
        "fitness"
    ],
    "wof:name":"Club Houston",
    "wof:placetype":"venue"
},
  "geometry": {"coordinates":[-95.371101,29.747299],"type":"Point"}
}