{
  "type": "Feature",
  "properties": {
    "iso:country":"US",
    "sg:address":"2827 Barrel Oak St",
    "sg:city":"San Antonio",
    "sg:classifiers":[
        {
            "category":"Professional",
            "subcategory":"Management & Consulting",
            "type":"Services"
        }
    ],
    "sg:phone":"+1 210 492 9976",
    "sg:postcode":"78231",
    "sg:province":"TX",
    "sg:tags":[
        "public",
        "relations"
    ],
    "wof:name":"Folkloric Artesian Internation",
    "wof:placetype":"venue"
},
  "geometry": {"coordinates":[-98.53681400000001,29.574639],"type":"Point"}
}