{
  "type": "Feature",
  "properties": {
    "iso:country":"US",
    "sg:address":"100 E 3rd St",
    "sg:city":"Sweetwater",
    "sg:classifiers":[
        {
            "category":"Government",
            "subcategory":"Court House",
            "type":"Public Place"
        }
    ],
    "sg:phone":"+1 325 235 3133",
    "sg:postcode":"79556",
    "sg:province":"TX",
    "wof:name":"District Judge",
    "wof:placetype":"venue"
},
  "geometry": {"coordinates":[-100.40792399999999,32.471499],"type":"Point"}
}