{
  "type": "Feature",
  "properties": {
    "iso:country":"US",
    "sg:address":"1806 S Saint Marys St",
    "sg:city":"San Antonio",
    "sg:classifiers":[
        {
            "category":"Retail",
            "subcategory":"Auto Repair",
            "type":"Services"
        }
    ],
    "sg:phone":"+1 210 533 5788",
    "sg:postcode":"78210",
    "sg:province":"TX",
    "sg:tags":[
        "glass",
        "replacement"
    ],
    "wof:name":"Lunas Glass Works Inc",
    "wof:placetype":"venue"
},
  "geometry": {"coordinates":[-98.485332,29.403189],"type":"Point"}
}