{
  "type": "Feature",
  "properties": {
    "iso:country":"US",
    "sg:address":"2230 7th St",
    "sg:city":"Port Arthur",
    "sg:classifiers":[
        {
            "category":"Professional",
            "subcategory":"Computer Services",
            "type":"Services"
        }
    ],
    "sg:phone":"+1 409 985 9056",
    "sg:postcode":"77640",
    "sg:province":"TX",
    "sg:tags":[
        "datum"
    ],
    "wof:name":"Prints Unlimited",
    "wof:placetype":"venue"
},
  "geometry": {"coordinates":[-93.92440000000001,29.887445],"type":"Point"}
}