{
  "type": "Feature",
  "properties": {
    "iso:country":"US",
    "sg:address":"150 W Parker Rd",
    "sg:city":"Houston",
    "sg:classifiers":[
        {
            "category":"Health Services",
            "subcategory":"Doctor",
            "type":"Services"
        }
    ],
    "sg:phone":"+1 713 685 1868",
    "sg:postcode":"77076",
    "sg:province":"TX",
    "sg:tags":[
        "clinic"
    ],
    "wof:name":"Houston Med Clinic",
    "wof:placetype":"venue"
},
  "geometry": {"coordinates":[-95.397768,29.859645],"type":"Point"}
}