{
  "type": "Feature",
  "properties": {
    "iso:country":"US",
    "sg:address":"3530 Forest Ln",
    "sg:city":"Dallas",
    "sg:classifiers":[
        {
            "category":"Banks & Credit Unions",
            "subcategory":"Financial Services",
            "type":"Services"
        },
        {
            "category":"Social Services",
            "type":"Services"
        }
    ],
    "sg:phone":"+1 214 351 4595",
    "sg:postcode":"75234",
    "sg:province":"TX",
    "sg:tags":[
        "organization",
        "trust",
        "management",
        "welfare"
    ],
    "wof:name":"Hemophilia National Foundation",
    "wof:placetype":"venue"
},
  "geometry": {"coordinates":[-96.860592,32.90964],"type":"Point"}
}