{
  "type": "Feature",
  "properties": {
    "iso:country":"US",
    "sg:address":"301 N N St",
    "sg:city":"Midland",
    "sg:classifiers":[
        {
            "category":"Health Services",
            "subcategory":"Doctor",
            "type":"Services"
        }
    ],
    "sg:phone":"+1 432 263 7491",
    "sg:postcode":"79701",
    "sg:province":"TX",
    "sg:tags":[
        "medical"
    ],
    "wof:name":"Highland Park Medical Bldg",
    "wof:placetype":"venue"
},
  "geometry": {"coordinates":[-102.097846,31.996945],"type":"Point"}
}