{
  "type": "Feature",
  "properties": {
    "iso:country":"US",
    "sg:address":"12946 Dairy Ashford Rd",
    "sg:city":"Sugar Land",
    "sg:classifiers":[
        {
            "category":"Professional",
            "type":"Services"
        },
        {
            "category":"Utilities",
            "type":"Services"
        }
    ],
    "sg:phone":"+1 281 276 3000",
    "sg:postcode":"77478",
    "sg:province":"TX",
    "sg:tags":[
        "sanitary"
    ],
    "wof:name":"Philip Services Corporation",
    "wof:placetype":"venue"
},
  "geometry": {"coordinates":[-95.59789000000001,29.631218],"type":"Point"}
}