{
  "type": "Feature",
  "properties": {
    "iso:country":"US",
    "sg:address":"206 McBride St",
    "sg:city":"Winnie",
    "sg:classifiers":[
        {
            "category":"Retail",
            "subcategory":"Auto Repair",
            "type":"Services"
        }
    ],
    "sg:phone":"+1 409 296 2935",
    "sg:postcode":"77665",
    "sg:province":"TX",
    "sg:tags":[
        "body"
    ],
    "wof:name":"Budro Restorations",
    "wof:placetype":"venue"
},
  "geometry": {"coordinates":[-94.387165,29.808715],"type":"Point"}
}