{
  "type": "Feature",
  "properties": {
    "iso:country":"US",
    "sg:address":"4002 Loop 256",
    "sg:city":"Palestine",
    "sg:classifiers":[
        {
            "category":"Health Services",
            "subcategory":"Doctor",
            "type":"Services"
        }
    ],
    "sg:phone":"+1 903 723 2311",
    "sg:postcode":"75801",
    "sg:province":"TX",
    "sg:tags":[
        "physician",
        "surgeon"
    ],
    "wof:name":"Family Practice Medical Clinic",
    "wof:placetype":"venue"
},
  "geometry": {"coordinates":[-95.64666099999999,31.741573],"type":"Point"}
}