{
  "type": "Feature",
  "properties": {
    "iso:country":"US",
    "sg:address":"16321 Addison Rd",
    "sg:city":"Addison",
    "sg:classifiers":[
        {
            "category":"Airport",
            "type":"Transportation"
        }
    ],
    "sg:phone":"+1 972 490 8555",
    "sg:postcode":"75001",
    "sg:province":"TX",
    "sg:tags":[
        "aircraft",
        "storage"
    ],
    "wof:name":"Alternative Air Inc",
    "wof:placetype":"venue"
},
  "geometry": {"coordinates":[-96.830348,32.971322],"type":"Point"}
}