{
  "type": "Feature",
  "properties": {
    "iso:country":"US",
    "sg:address":"16200 Addison Rd",
    "sg:city":"Addison",
    "sg:classifiers":[
        {
            "category":"Personal",
            "type":"Services"
        }
    ],
    "sg:phone":"+1 214 461 0101",
    "sg:postcode":"75001",
    "sg:province":"TX",
    "sg:tags":[
        "credit",
        "debt",
        "counseling"
    ],
    "wof:name":"Debt Relief USA",
    "wof:placetype":"venue"
},
  "geometry": {"coordinates":[-96.83034000000001,32.973816],"type":"Point"}
}