{
  "type": "Feature",
  "properties": {
    "iso:country":"US",
    "sg:address":"3 N 29th St",
    "sg:city":"Temple",
    "sg:classifiers":[
        {
            "category":"Restaurant",
            "type":"Food & Drink"
        }
    ],
    "sg:menulink":"http://www.allmenus.com/tx/temple/130672-subway/menu/",
    "sg:phone":"+1 254 742 1040",
    "sg:postcode":"76504",
    "sg:province":"TX",
    "sg:tags":[
        "american",
        "sandwich"
    ],
    "wof:name":"Subway",
    "wof:placetype":"venue"
},
  "geometry": {"coordinates":[-97.356515,31.10094],"type":"Point"}
}