{
  "type": "Feature",
  "properties": {
    "iso:country":"US",
    "sg:address":"49 Coffee Tavern Rd",
    "sg:city":"Bedford",
    "sg:classifiers":[
        {
            "category":"Professional",
            "subcategory":"Business Services",
            "type":"Services"
        }
    ],
    "sg:phone":"+1 817 268 0813",
    "sg:postcode":"76022",
    "sg:province":"TX",
    "wof:name":"Bilingual Spanish Service",
    "wof:placetype":"venue"
},
  "geometry": {"coordinates":[-97.15693899999999,32.834326],"type":"Point"}
}