{
  "type": "Feature",
  "properties": {
    "iso:country":"US",
    "sg:address":"908 W 12th St",
    "sg:city":"Austin",
    "sg:classifiers":[
        {
            "category":"Retail",
            "subcategory":"Auto Repair",
            "type":"Services"
        },
        {
            "category":"Shopping",
            "subcategory":"Gifts & Souvenirs",
            "type":"Retail Goods"
        }
    ],
    "sg:phone":"+1 512 480 0996",
    "sg:postcode":"78703",
    "sg:province":"TX",
    "sg:tags":[
        "shop",
        "general"
    ],
    "wof:name":"Foreign Accents",
    "wof:placetype":"venue"
},
  "geometry": {"coordinates":[-97.751284,30.276934],"type":"Point"}
}