{
  "type": "Feature",
  "properties": {
    "iso:country":"US",
    "sg:address":"9521 FM 1097 W",
    "sg:city":"Willis",
    "sg:classifiers":[
        {
            "category":"Professional",
            "type":"Services"
        }
    ],
    "sg:phone":"+1 936 890 9600",
    "sg:postcode":"77378",
    "sg:province":"TX",
    "sg:tags":[
        "establishment"
    ],
    "wof:name":"Dent Center",
    "wof:placetype":"venue"
},
  "geometry": {"coordinates":[-95.49475700000001,30.420496],"type":"Point"}
}