{
  "type": "Feature",
  "properties": {
    "iso:country":"US",
    "sg:address":"2005 E Cesar Chavez St",
    "sg:city":"Austin",
    "sg:classifiers":[
        {
            "category":"Organizations",
            "subcategory":"Membership Organization",
            "type":"Services"
        }
    ],
    "sg:phone":"+1 512 306 9241",
    "sg:postcode":"78702",
    "sg:province":"TX",
    "sg:tags":[
        "workers'",
        "placement",
        "volunteer"
    ],
    "wof:name":"Giocosa Foundation",
    "wof:placetype":"venue"
},
  "geometry": {"coordinates":[-97.723099,30.256579],"type":"Point"}
}