{
  "type": "Feature",
  "properties": {
    "iso:country":"US",
    "sg:address":"772 S Ranch Road 783",
    "sg:city":"Harper",
    "sg:classifiers":[
        {
            "category":"Food & Beverages",
            "subcategory":"Candy",
            "type":"Retail Goods"
        },
        {
            "category":"Manufacturing",
            "subcategory":"Food",
            "type":"Manufacturing & Wholesale Goods"
        }
    ],
    "sg:phone":"+1 830 864 4364",
    "sg:postcode":"78631",
    "sg:province":"TX",
    "sg:tags":[
        "confectionery-wholesale",
        "confectionery",
        "manufacturer"
    ],
    "wof:name":"Kramer Wholesale",
    "wof:placetype":"venue"
},
  "geometry": {"coordinates":[-99.15855000000001,30.165365],"type":"Point"}
}