{
  "type": "Feature",
  "properties": {
    "iso:country":"US",
    "sg:address":"4564 Hitching Post Ln",
    "sg:city":"Plano",
    "sg:classifiers":[
        {
            "category":"Professional",
            "subcategory":"Research",
            "type":"Services"
        }
    ],
    "sg:phone":"+1 972 618 0925",
    "sg:postcode":"75024",
    "sg:province":"TX",
    "sg:tags":[
        "organization",
        "noncommercial"
    ],
    "wof:name":"Sanders Research Institut",
    "wof:placetype":"venue"
},
  "geometry": {"coordinates":[-96.783717,33.073296],"type":"Point"}
}