{
  "type": "Feature",
  "properties": {
    "iso:country":"US",
    "sg:address":"2207 4th St",
    "sg:city":"Rosenberg",
    "sg:classifiers":[
        {
            "category":"Real Estate",
            "subcategory":"Real Estate Operator",
            "type":"Services"
        }
    ],
    "sg:phone":"+1 281 342 3044",
    "sg:postcode":"77471",
    "sg:province":"TX",
    "sg:tags":[
        "mobile",
        "home",
        "site"
    ],
    "wof:name":"Briland West Mobile Home Park",
    "wof:placetype":"venue"
},
  "geometry": {"coordinates":[-95.805272,29.545851],"type":"Point"}
}