{
  "type": "Feature",
  "properties": {
    "iso:country":"US",
    "sg:address":"310 W Lake Dr",
    "sg:city":"Hamlin",
    "sg:classifiers":[
        {
            "category":"Food & Beverages",
            "subcategory":"Groceries & Convenience Stores",
            "type":"Retail Goods"
        }
    ],
    "sg:phone":"+1 325 576 2830",
    "sg:postcode":"79520",
    "sg:province":"TX",
    "sg:tags":[
        "market"
    ],
    "wof:name":"City Food Mkt. Office",
    "wof:placetype":"venue"
},
  "geometry": {"coordinates":[-100.13073199999999,32.883861],"type":"Point"}
}