{
  "type": "Feature",
  "properties": {
    "iso:country":"US",
    "sg:address":"5214 68th St",
    "sg:city":"Lubbock",
    "sg:classifiers":[
        {
            "category":"Health Services",
            "subcategory":"Clinic",
            "type":"Services"
        }
    ],
    "sg:phone":"+1 806 798 7118",
    "sg:postcode":"79424",
    "sg:province":"TX",
    "sg:tags":[
        "home",
        "care"
    ],
    "wof:name":"Northwest Texas Home Health",
    "wof:placetype":"venue"
},
  "geometry": {"coordinates":[-101.922741,33.533],"type":"Point"}
}