{
  "type": "Feature",
  "properties": {
    "iso:country":"US",
    "sg:address":"10922 Preston Trails Dr",
    "sg:city":"Austin",
    "sg:classifiers":[
        {
            "category":"Banks & Credit Unions",
            "subcategory":"Investment Brokerage",
            "type":"Services"
        },
        {
            "category":"Insurance",
            "subcategory":"Hazard Insurance",
            "type":"Services"
        }
    ],
    "sg:phone":"+1 512 794 1350",
    "sg:postcode":"78747",
    "sg:province":"TX",
    "sg:tags":[
        "agent",
        "resume"
    ],
    "wof:name":"Gary R Rodgers",
    "wof:placetype":"venue"
},
  "geometry": {"coordinates":[-97.791522,30.137125],"type":"Point"}
}