{
  "type": "Feature",
  "properties": {
    "iso:country":"US",
    "sg:address":"1000 Post N Paddock St",
    "sg:city":"Grand Prairie",
    "sg:classifiers":[
        {
            "category":"Insurance",
            "subcategory":"Insurance Agent",
            "type":"Services"
        }
    ],
    "sg:phone":"+1 972 641 6636",
    "sg:postcode":"75050",
    "sg:province":"TX",
    "wof:name":"Wake Financial Group Inc",
    "wof:placetype":"venue"
},
  "geometry": {"coordinates":[-97.048708,32.793285],"type":"Point"}
}