{
  "type": "Feature",
  "properties": {
    "iso:country":"US",
    "sg:address":"6630 Co Rd 120",
    "sg:city":"Marble Falls",
    "sg:classifiers":[
        {
            "category":"Building & Trades",
            "subcategory":"Electrical",
            "type":"Services"
        }
    ],
    "sg:phone":"+1 830 693 6128",
    "sg:postcode":"78654",
    "sg:province":"TX",
    "sg:tags":[
        "electric",
        "contractor"
    ],
    "wof:name":"Stepco Electric",
    "wof:placetype":"venue"
},
  "geometry": {"coordinates":[-98.299598,30.641317],"type":"Point"}
}