{
  "type": "Feature",
  "properties": {
    "iso:country":"US",
    "sg:address":"703 W 11th St",
    "sg:city":"Austin",
    "sg:classifiers":[
        {
            "category":"Social Services",
            "type":"Services"
        }
    ],
    "sg:phone":"+1 512 479 6460",
    "sg:postcode":"78701",
    "sg:province":"TX",
    "wof:name":"Identity Crisis",
    "wof:placetype":"venue"
},
  "geometry": {"coordinates":[-97.748858,30.274831],"type":"Point"}
}