{
  "type": "Feature",
  "properties": {
    "iso:country":"US",
    "sg:address":"217 E Commerce St",
    "sg:city":"Jacksonville",
    "sg:classifiers":[
        {
            "category":"Insurance",
            "subcategory":"Insurance Agent",
            "type":"Services"
        }
    ],
    "sg:phone":"+1 903 586 8586",
    "sg:postcode":"75766",
    "sg:province":"TX",
    "wof:name":"Mark Kerzee Insurance",
    "wof:placetype":"venue"
},
  "geometry": {"coordinates":[-95.27204399999999,31.963939],"type":"Point"}
}