{
  "type": "Feature",
  "properties": {
    "iso:country":"US",
    "sg:address":"3632 Frankford Rd Ste 180",
    "sg:city":"Dallas",
    "sg:classifiers":[
        {
            "category":"Recreation",
            "subcategory":"Amusement Park",
            "type":"Entertainment"
        },
        {
            "category":"Personal",
            "type":"Services"
        }
    ],
    "sg:phone":"+1 972 820 0777",
    "sg:postcode":"75287",
    "sg:province":"TX",
    "sg:tags":[
        "party",
        "planning",
        "event"
    ],
    "sg:website":"www.pumpitupparty.com",
    "wof:name":"Pump It Up",
    "wof:placetype":"venue"
},
  "geometry": {"coordinates":[-96.85134600000001,32.996762],"type":"Point"}
}