{
  "type": "Feature",
  "properties": {
    "iso:country":"US",
    "sg:address":"203 W 3rd St",
    "sg:city":"Texarkana",
    "sg:classifiers":[
        {
            "category":"Building & Trades",
            "subcategory":"Construction",
            "type":"Services"
        }
    ],
    "sg:phone":"+1 806 558 5211",
    "sg:postcode":"75501",
    "sg:province":"TX",
    "sg:tags":[
        "elevator"
    ],
    "wof:name":"Farmers Elevator",
    "wof:placetype":"venue"
},
  "geometry": {"coordinates":[-94.044464,33.42181],"type":"Point"}
}