{
  "type": "Feature",
  "properties": {
    "iso:country":"US",
    "sg:address":"7025 Goforth St",
    "sg:city":"Houston",
    "sg:classifiers":[
        {
            "category":"Retail",
            "subcategory":"Auto Repair",
            "type":"Services"
        }
    ],
    "sg:phone":"+1 713 748 0380",
    "sg:postcode":"77021",
    "sg:province":"TX",
    "sg:tags":[
        "general"
    ],
    "wof:name":"Bourgeois Auto & Wrckr Svc",
    "wof:placetype":"venue"
},
  "geometry": {"coordinates":[-95.357207,29.686846],"type":"Point"}
}