{
  "type": "Feature",
  "properties": {
    "iso:country":"US",
    "sg:address":"840 Oscar Ragon Rd",
    "sg:city":"Harleton",
    "sg:classifiers":[
        {
            "category":"Building & Trades",
            "subcategory":"Construction",
            "type":"Services"
        }
    ],
    "sg:phone":"+1 903 777 2761",
    "sg:postcode":"75651",
    "sg:province":"TX",
    "sg:tags":[
        "nonresidential"
    ],
    "wof:name":"Echols Construction",
    "wof:placetype":"venue"
},
  "geometry": {"coordinates":[-94.573213,32.698834],"type":"Point"}
}