{
  "type": "Feature",
  "properties": {
    "iso:country":"US",
    "sg:address":"21414 Golden Dove Dr",
    "sg:city":"Spring",
    "sg:classifiers":[
        {
            "category":"Insurance",
            "subcategory":"Insurance Agent",
            "type":"Services"
        }
    ],
    "sg:phone":"+1 713 206 7958",
    "sg:postcode":"77388",
    "sg:province":"TX",
    "wof:name":"Siboney Trevino",
    "wof:placetype":"venue"
},
  "geometry": {"coordinates":[-95.46806599999999,30.073656],"type":"Point"}
}