{
  "type": "Feature",
  "properties": {
    "iso:country":"US",
    "sg:address":"1031 Westminister Ave",
    "sg:city":"Murphy",
    "sg:classifiers":[
        {
            "category":"Building & Trades",
            "subcategory":"Construction",
            "type":"Services"
        }
    ],
    "sg:phone":"+1 972 678 0800",
    "sg:postcode":"75094",
    "sg:province":"TX",
    "sg:tags":[
        "home",
        "builder"
    ],
    "sg:website":"www.englehomes.com",
    "wof:name":"Engel Homes-Hunters Landing",
    "wof:placetype":"venue"
},
  "geometry": {"coordinates":[-96.61896400000001,33.030351],"type":"Point"}
}