{
  "type": "Feature",
  "properties": {
    "iso:country":"US",
    "sg:address":"3810 Bonita Ln",
    "sg:city":"La Porte",
    "sg:classifiers":[
        {
            "category":"Shopping",
            "subcategory":"Bicycles & Sporting Goods",
            "type":"Retail Goods"
        }
    ],
    "sg:phone":"+1 281 471 1488",
    "sg:postcode":"77571",
    "sg:province":"TX",
    "wof:name":"Freds Firearms",
    "wof:placetype":"venue"
},
  "geometry": {"coordinates":[-95.001497,29.616753],"type":"Point"}
}