{
  "type": "Feature",
  "properties": {
    "iso:country":"US",
    "sg:address":"5934 Royal Ln Ste 214",
    "sg:city":"Dallas",
    "sg:classifiers":[
        {
            "category":"Personal",
            "type":"Services"
        }
    ],
    "sg:phone":"+1 214 696 5600",
    "sg:postcode":"75230",
    "sg:province":"TX",
    "sg:tags":[
        "sewing",
        "alteration"
    ],
    "wof:name":"Ronaldo's Tailor & Alteration",
    "wof:placetype":"venue"
},
  "geometry": {"coordinates":[-96.806484,32.894773],"type":"Point"}
}