{
  "type": "Feature",
  "properties": {
    "iso:country":"US",
    "sg:address":"1925 Richmond Ave",
    "sg:city":"Houston",
    "sg:classifiers":[
        {
            "category":"Community Center",
            "type":"Public Place"
        }
    ],
    "sg:phone":"+1 832 380 8614",
    "sg:postcode":"77098",
    "sg:province":"TX",
    "sg:tags":[
        "instrument",
        "weather"
    ],
    "sg:website":"http://www.lsstnr.com",
    "wof:name":"Land Sea & Sky",
    "wof:placetype":"venue"
},
  "geometry": {"coordinates":[-95.40801999999999,29.7342],"type":"Point"}
}