{
  "type": "Feature",
  "properties": {
    "iso:country":"US",
    "sg:address":"3534 Riomar Ct",
    "sg:city":"Abilene",
    "sg:classifiers":[
        {
            "category":"Professional",
            "subcategory":"Accounting & Tax Preparation",
            "type":"Services"
        }
    ],
    "sg:phone":"+1 325 698 3810",
    "sg:postcode":"79606",
    "sg:province":"TX",
    "sg:tags":[
        "billing"
    ],
    "wof:name":"Mas Business Service",
    "wof:placetype":"venue"
},
  "geometry": {"coordinates":[-99.76814299999999,32.371816],"type":"Point"}
}