{
  "type": "Feature",
  "properties": {
    "iso:country":"US",
    "sg:address":"3102 Morris Sheppard Dr",
    "sg:city":"Brownwood",
    "sg:classifiers":[
        {
            "category":"Building & Trades",
            "subcategory":"Equipment Rental",
            "type":"Services"
        }
    ],
    "sg:phone":"+1 325 646 7732",
    "sg:postcode":"76801",
    "sg:province":"TX",
    "sg:tags":[
        "yard"
    ],
    "wof:name":"Roberson Rent-All",
    "wof:placetype":"venue"
},
  "geometry": {"coordinates":[-98.984381,31.676678],"type":"Point"}
}