{
  "type": "Feature",
  "properties": {
    "iso:country":"US",
    "sg:address":"9085 Main St",
    "sg:city":"Batson",
    "sg:classifiers":[
        {
            "category":"Cinema",
            "subcategory":"Movie Rental",
            "type":"Entertainment"
        }
    ],
    "sg:phone":"+1 936 262 8007",
    "sg:postcode":"77519",
    "sg:province":"TX",
    "sg:tags":[
        "leasing",
        "video",
        "disc",
        "tape"
    ],
    "wof:name":"Rufnek Videos",
    "wof:placetype":"venue"
},
  "geometry": {"coordinates":[-94.60700300000001,30.250718],"type":"Point"}
}