{
  "type": "Feature",
  "properties": {
    "iso:country":"US",
    "sg:address":"1001 N Mockingbird Ln",
    "sg:city":"Abilene",
    "sg:classifiers":[
        {
            "category":"Building & Trades",
            "subcategory":"Construction",
            "type":"Services"
        }
    ],
    "sg:phone":"+1 325 670 0604",
    "sg:postcode":"79603",
    "sg:province":"TX",
    "sg:tags":[
        "house"
    ],
    "wof:name":"Gary Goldsmith Construction",
    "wof:placetype":"venue"
},
  "geometry": {"coordinates":[-99.757852,32.46316],"type":"Point"}
}