{
  "type": "Feature",
  "properties": {
    "iso:country":"US",
    "sg:address":"2121 E 6th St Apt 102",
    "sg:city":"Austin",
    "sg:classifiers":[
        {
            "category":"Health Services",
            "subcategory":"Doctor",
            "type":"Services"
        }
    ],
    "sg:phone":"+1 512 473 4180",
    "sg:postcode":"78702",
    "sg:province":"TX",
    "wof:name":"Zamora Santiago MD",
    "wof:placetype":"venue"
},
  "geometry": {"coordinates":[-97.718493,30.260104],"type":"Point"}
}