{
  "type": "Feature",
  "properties": {
    "iso:country":"US",
    "sg:address":"6 Country Pl",
    "sg:city":"Bedford",
    "sg:classifiers":[
        {
            "category":"Professional",
            "subcategory":"Management & Consulting",
            "type":"Services"
        }
    ],
    "sg:phone":"+1 817 267 0214",
    "sg:postcode":"76021",
    "sg:province":"TX",
    "wof:name":"Select Benefit Resources",
    "wof:placetype":"venue"
},
  "geometry": {"coordinates":[-97.14242400000001,32.859471],"type":"Point"}
}