{
  "type": "Feature",
  "properties": {
    "iso:country":"US",
    "sg:address":"10602 Longmont Dr",
    "sg:city":"Houston",
    "sg:classifiers":[
        {
            "category":"Health Services",
            "subcategory":"Hospital",
            "type":"Services"
        }
    ],
    "sg:phone":"+1 713 334 6860",
    "sg:postcode":"77042",
    "sg:province":"TX",
    "sg:tags":[
        "specialty"
    ],
    "wof:name":"Adolescents In Recovery Air",
    "wof:placetype":"venue"
},
  "geometry": {"coordinates":[-95.567145,29.749754],"type":"Point"}
}