{
  "type": "Feature",
  "properties": {
    "iso:country":"US",
    "sg:address":"104 N College St",
    "sg:city":"Marshall",
    "sg:classifiers":[
        {
            "category":"Banks & Credit Unions",
            "subcategory":"Bank",
            "type":"Services"
        },
        {
            "category":"Shopping",
            "subcategory":"Used Merchandise",
            "type":"Retail Goods"
        }
    ],
    "sg:phone":"+1 903 935 7322",
    "sg:postcode":"75670",
    "sg:province":"TX",
    "sg:tags":[
        "resale",
        "shop",
        "second",
        "hand"
    ],
    "wof:name":"Petticoat Junktion",
    "wof:placetype":"venue"
},
  "geometry": {"coordinates":[-94.37297100000001,32.54494],"type":"Point"}
}