{
  "type": "Feature",
  "properties": {
    "iso:country":"US",
    "sg:address":"5220 Texas St",
    "sg:city":"Houston",
    "sg:classifiers":[
        {
            "category":"Building & Trades",
            "subcategory":"Plumbing",
            "type":"Services"
        },
        {
            "category":"Wholesale",
            "subcategory":"Machinery & Supplies",
            "type":"Manufacturing & Wholesale Goods"
        }
    ],
    "sg:phone":"+1 713 926 9623",
    "sg:postcode":"77011",
    "sg:province":"TX",
    "sg:tags":[
        "equipment",
        "boilers-repair",
        "part",
        "boiler",
        "clean"
    ],
    "sg:website":"http://www.able-huber.com",
    "wof:name":"Huber Construction Company, Inc.",
    "wof:placetype":"venue"
},
  "geometry": {"coordinates":[-95.32378300000001,29.741333],"type":"Point"}
}