{
  "type": "Feature",
  "properties": {
    "iso:country":"US",
    "sg:address":"3309 E Lake Rd",
    "sg:city":"Abilene",
    "sg:classifiers":[
        {
            "category":"Farming",
            "subcategory":"Farm",
            "type":"Manufacturing & Wholesale Goods"
        }
    ],
    "sg:phone":"+1 325 673 9446",
    "sg:postcode":"79601",
    "sg:province":"TX",
    "sg:tags":[
        "crop",
        "general"
    ],
    "wof:name":"Z Cooper Farm",
    "wof:placetype":"venue"
},
  "geometry": {"coordinates":[-99.690675,32.493321],"type":"Point"}
}