{
  "type": "Feature",
  "properties": {
    "iso:country":"US",
    "sg:address":"3726 Piping Rock Ln",
    "sg:city":"Houston",
    "sg:classifiers":[
        {
            "category":"Mining & Drilling",
            "type":"Manufacturing & Wholesale Goods"
        }
    ],
    "sg:phone":"+1 713 961 0666",
    "sg:postcode":"77027",
    "sg:province":"TX",
    "sg:tags":[
        "exploration"
    ],
    "wof:name":"British Gas",
    "wof:placetype":"venue"
},
  "geometry": {"coordinates":[-95.441183,29.745619],"type":"Point"}
}