{
  "type": "Feature",
  "properties": {
    "iso:country":"US",
    "sg:address":"17659 Sunmeadow Dr",
    "sg:city":"Dallas",
    "sg:classifiers":[
        {
            "category":"Shopping",
            "subcategory":"Gifts & Souvenirs",
            "type":"Retail Goods"
        }
    ],
    "sg:phone":"+1 972 248 4873",
    "sg:postcode":"75252",
    "sg:province":"TX",
    "sg:tags":[
        "stuffed",
        "animal"
    ],
    "wof:name":"Connection Channel",
    "wof:placetype":"venue"
},
  "geometry": {"coordinates":[-96.80233200000001,32.992587],"type":"Point"}
}