{
  "type": "Feature",
  "properties": {
    "iso:country":"US",
    "sg:address":"215 W Bandera Rd",
    "sg:city":"Boerne",
    "sg:classifiers":[
        {
            "category":"Professional",
            "type":"Services"
        }
    ],
    "sg:phone":"+1 830 336 3997",
    "sg:postcode":"78006",
    "sg:province":"TX",
    "wof:name":"Pgm",
    "wof:placetype":"venue"
},
  "geometry": {"coordinates":[-98.731402,29.78039],"type":"Point"}
}