{
  "type": "Feature",
  "properties": {
    "iso:country":"US",
    "sg:address":"2910 W Michigan Ave",
    "sg:city":"Midland",
    "sg:classifiers":[
        {
            "category":"Real Estate",
            "subcategory":"Real Estate Operator",
            "type":"Services"
        }
    ],
    "sg:phone":"+1 432 697 3510",
    "sg:postcode":"79701",
    "sg:province":"TX",
    "sg:tags":[
        "building",
        "apartment"
    ],
    "wof:name":"Simpatico Apartments",
    "wof:placetype":"venue"
},
  "geometry": {"coordinates":[-102.111198,31.995548],"type":"Point"}
}