{
  "type": "Feature",
  "properties": {
    "iso:country":"US",
    "sg:address":"12755 Cogburn",
    "sg:city":"San Antonio",
    "sg:classifiers":[
        {
            "category":"Building & Trades",
            "subcategory":"Electrical",
            "type":"Services"
        }
    ],
    "sg:phone":"+1 210 696 4040",
    "sg:postcode":"78249",
    "sg:province":"TX",
    "sg:tags":[
        "electric",
        "contractor"
    ],
    "wof:name":"Cappadonna Electrical Contr",
    "wof:placetype":"venue"
},
  "geometry": {"coordinates":[-98.59973599999999,29.564024],"type":"Point"}
}