{
  "type": "Feature",
  "properties": {
    "iso:country":"US",
    "sg:address":"4508 Village Ct",
    "sg:city":"Granbury",
    "sg:classifiers":[
        {
            "category":"Building & Trades",
            "subcategory":"Plumbing",
            "type":"Services"
        }
    ],
    "sg:phone":"+1 817 910 2108",
    "sg:postcode":"76049",
    "sg:province":"TX",
    "sg:tags":[
        "plumber",
        "contractor"
    ],
    "wof:name":"Cliff's Plumbing",
    "wof:placetype":"venue"
},
  "geometry": {"coordinates":[-97.71602,32.45824],"type":"Point"}
}