{
  "type": "Feature",
  "properties": {
    "iso:country":"US",
    "sg:address":"4702 Willowbrook Dr",
    "sg:city":"Corpus Christi",
    "sg:classifiers":[
        {
            "category":"Home & Garden",
            "subcategory":"Garden Supply",
            "type":"Retail Goods"
        },
        {
            "category":"Building & Trades",
            "subcategory":"Landscaping Services",
            "type":"Services"
        }
    ],
    "sg:phone":"+1 361 992 9791",
    "sg:postcode":"78411",
    "sg:province":"TX",
    "sg:tags":[
        "sprinkler"
    ],
    "wof:name":"South Texas Lawn Sprinkler Co",
    "wof:placetype":"venue"
},
  "geometry": {"coordinates":[-97.38057999999999,27.717125],"type":"Point"}
}