{
  "type": "Feature",
  "properties": {
    "iso:country":"US",
    "sg:address":"215 Spacious Sky",
    "sg:city":"San Antonio",
    "sg:classifiers":[
        {
            "category":"Building & Trades",
            "subcategory":"Plumbing",
            "type":"Services"
        }
    ],
    "sg:phone":"+1 210 497 2594",
    "sg:postcode":"78260",
    "sg:province":"TX",
    "sg:tags":[
        "contractor"
    ],
    "wof:name":"Legend Refrigeration",
    "wof:placetype":"venue"
},
  "geometry": {"coordinates":[-98.508276,29.686204],"type":"Point"}
}