{
  "type": "Feature",
  "properties": {
    "iso:country":"US",
    "sg:address":"6923 Queensclub Dr",
    "sg:city":"Houston",
    "sg:classifiers":[
        {
            "category":"Professional",
            "subcategory":"Engineering",
            "type":"Services"
        }
    ],
    "sg:phone":"+1 281 580 2278",
    "sg:postcode":"77069",
    "sg:province":"TX",
    "wof:name":"BR Engineering Consultant",
    "wof:placetype":"venue"
},
  "geometry": {"coordinates":[-95.542704,29.986003],"type":"Point"}
}