{
  "type": "Feature",
  "properties": {
    "iso:country":"US",
    "sg:address":"1501 E 6th St",
    "sg:city":"Austin",
    "sg:phone":"+1 512 479 0097",
    "sg:postcode":"78702",
    "sg:province":"TX",
    "wof:name":"Nuevo Leon Mexican Restaurant",
    "wof:placetype":"venue"
},
  "geometry": {"coordinates":[-97.727509,30.26338],"type":"Point"}
}