{
  "type": "Feature",
  "properties": {
    "iso:country":"US",
    "sg:address":"502 Mc Clendon St",
    "sg:city":"Corpus Christi",
    "sg:classifiers":[
        {
            "category":"Social Services",
            "type":"Services"
        }
    ],
    "sg:phone":"+1 361 855 9058",
    "sg:postcode":"78404",
    "sg:province":"TX",
    "wof:name":"Nueces Cnty Chld Advocacy Ctr",
    "wof:placetype":"venue"
},
  "geometry": {"coordinates":[-97.393682,27.758557],"type":"Point"}
}