{
  "type": "Feature",
  "properties": {
    "iso:country":"US",
    "sg:address":"900 S Casa Rd",
    "sg:city":"Pharr",
    "sg:classifiers":[
        {
            "category":"Shopping",
            "type":"Retail Goods"
        }
    ],
    "sg:phone":"+1 956 787 9298",
    "sg:postcode":"78577",
    "sg:province":"TX",
    "sg:tags":[
        "merchandise"
    ],
    "wof:name":"Accessories Etc",
    "wof:placetype":"venue"
},
  "geometry": {"coordinates":[-98.20061800000001,26.187312],"type":"Point"}
}