{
  "type": "Feature",
  "properties": {
    "iso:country":"US",
    "sg:address":"1607 Mattie Ln",
    "sg:city":"Caldwell",
    "sg:classifiers":[
        {
            "category":"Manufacturing",
            "subcategory":"Buildings",
            "type":"Manufacturing & Wholesale Goods"
        },
        {
            "category":"Building & Trades",
            "subcategory":"Construction",
            "type":"Services"
        }
    ],
    "sg:phone":"+1 979 567 9528",
    "sg:postcode":"77836",
    "sg:province":"TX",
    "sg:tags":[
        "home",
        "builder",
        "contractor"
    ],
    "wof:name":"Ron S Construction",
    "wof:placetype":"venue"
},
  "geometry": {"coordinates":[-96.713765,30.525593],"type":"Point"}
}