{
  "type": "Feature",
  "properties": {
    "iso:country":"US",
    "sg:address":"2 Northglen Rd",
    "sg:city":"Breckenridge",
    "sg:classifiers":[
        {
            "category":"Professional",
            "type":"Services"
        }
    ],
    "sg:phone":"+1 254 559 5690",
    "sg:postcode":"76424",
    "sg:province":"TX",
    "wof:name":"Country Charm",
    "wof:placetype":"venue"
},
  "geometry": {"coordinates":[-98.94215699999999,32.762727],"type":"Point"}
}