{
  "type": "Feature",
  "properties": {
    "iso:country":"US",
    "sg:address":"679 I- 30",
    "sg:city":"Sulphur Springs",
    "sg:classifiers":[
        {
            "category":"Professional",
            "type":"Services"
        }
    ],
    "sg:phone":"+1 903 438 9000",
    "sg:postcode":"75402",
    "sg:province":"TX",
    "wof:name":"Sulphur Springs Dealers Auctn",
    "wof:placetype":"venue"
},
  "geometry": {"coordinates":[-96.080523,33.130892],"type":"Point"}
}