{
  "type": "Feature",
  "properties": {
    "iso:country":"US",
    "sg:address":"16607 San Pedro Ave",
    "sg:city":"San Antonio",
    "sg:classifiers":[
        {
            "category":"Autos & Motor Vehicles",
            "subcategory":"Fuel & Gas Station",
            "type":"Retail Goods"
        }
    ],
    "sg:phone":"+1 210 494 0056",
    "sg:postcode":"78232",
    "sg:province":"TX",
    "sg:tags":[
        "station",
        "gasoline"
    ],
    "wof:name":"Hollywood Park Texaco",
    "wof:placetype":"venue"
},
  "geometry": {"coordinates":[-98.47330700000001,29.592853],"type":"Point"}
}