{
  "type": "Feature",
  "properties": {
    "iso:country":"US",
    "sg:address":"1625 College St",
    "sg:city":"Beaumont",
    "sg:classifiers":[
        {
            "category":"Autos & Motor Vehicles",
            "subcategory":"Motorcycle Sales",
            "type":"Retail Goods"
        }
    ],
    "sg:phone":"+1 409 838 4746",
    "sg:postcode":"77701",
    "sg:province":"TX",
    "sg:tags":[
        "scooter",
        "dealer"
    ],
    "sg:website":"www.gtcyclecenter.com",
    "wof:name":"Golden Triangle Cycle Center",
    "wof:placetype":"venue"
},
  "geometry": {"coordinates":[-94.10700199999999,30.071141],"type":"Point"}
}