{
  "type": "Feature",
  "properties": {
    "iso:country":"US",
    "sg:address":"5320 N Main St",
    "sg:city":"Vidor",
    "sg:classifiers":[
        {
            "category":"Food & Beverages",
            "subcategory":"Bakery",
            "type":"Retail Goods"
        }
    ],
    "sg:phone":"+1 409 681 9199",
    "sg:postcode":"77662",
    "sg:province":"TX",
    "sg:tags":[
        "doughnut"
    ],
    "wof:name":"Donut Palace",
    "wof:placetype":"venue"
},
  "geometry": {"coordinates":[-94.021224,30.200688],"type":"Point"}
}