{
  "type": "Feature",
  "properties": {
    "iso:country":"US",
    "sg:address":"14114 Dallas Pkwy Ste 260",
    "sg:city":"Dallas",
    "sg:classifiers":[
        {
            "category":"Health Services",
            "subcategory":"Doctor",
            "type":"Services"
        }
    ],
    "sg:phone":"+1 972 774 0221",
    "sg:postcode":"75254",
    "sg:province":"TX",
    "wof:name":"Schanz Anne PHD",
    "wof:placetype":"venue"
},
  "geometry": {"coordinates":[-96.8218,32.9398],"type":"Point"}
}