{
  "type": "Feature",
  "properties": {
    "iso:country":"US",
    "sg:address":"5604 RM 2222",
    "sg:city":"Austin",
    "sg:classifiers":[
        {
            "category":"Building & Trades",
            "subcategory":"Construction",
            "type":"Services"
        }
    ],
    "sg:phone":"+1 512 892 5150",
    "sg:postcode":"78731",
    "sg:province":"TX",
    "sg:tags":[
        "hanging",
        "contractor"
    ],
    "wof:name":"Lonestar Exteriors & Cllctn",
    "wof:placetype":"venue"
},
  "geometry": {"coordinates":[-97.787948,30.359005],"type":"Point"}
}