{
  "type": "Feature",
  "properties": {
    "iso:country":"US",
    "sg:address":"217 E Fm 1382",
    "sg:city":"Cedar Hill",
    "sg:classifiers":[
        {
            "category":"Banks & Credit Unions",
            "subcategory":"Bank",
            "type":"Services"
        }
    ],
    "sg:phone":"+1 972 291 6246",
    "sg:postcode":"75104",
    "sg:province":"TX",
    "wof:name":"Mainbank",
    "wof:placetype":"venue"
},
  "geometry": {"coordinates":[-96.941902,32.598301],"type":"Point"}
}