{
  "type": "Feature",
  "properties": {
    "iso:country":"US",
    "sg:address":"1315 W Polk Ave",
    "sg:city":"Pharr",
    "sg:classifiers":[
        {
            "category":"Professional",
            "subcategory":"Management & Consulting",
            "type":"Services"
        }
    ],
    "sg:phone":"+1 956 781 3695",
    "sg:postcode":"78577",
    "sg:province":"TX",
    "sg:tags":[
        "business"
    ],
    "wof:name":"Grupo Microanalisis",
    "wof:placetype":"venue"
},
  "geometry": {"coordinates":[-98.202611,26.207257],"type":"Point"}
}