{
  "type": "Feature",
  "properties": {
    "iso:country":"US",
    "sg:address":"2472 Fm 1844",
    "sg:city":"Longview",
    "sg:classifiers":[
        {
            "category":"Place Of Worship",
            "subcategory":"Church",
            "type":"Public Place"
        },
        {
            "category":"Place Of Worship",
            "type":"Public Place"
        }
    ],
    "sg:phone":"+1 903 663 2438",
    "sg:postcode":"75605",
    "sg:province":"TX",
    "sg:tags":[
        "churches-christian-disciples",
        "churches-interdenominational",
        "denomination",
        "churches-various",
        "christ"
    ],
    "wof:name":"Woodland Christian Church",
    "wof:placetype":"venue"
},
  "geometry": {"coordinates":[-94.752106,32.587301],"type":"Point"}
}