{
  "type": "Feature",
  "properties": {
    "iso:country":"US",
    "sg:address":"8214 Westchester Dr",
    "sg:city":"Dallas",
    "sg:classifiers":[
        {
            "category":"Professional",
            "subcategory":"Computer Services",
            "type":"Services"
        }
    ],
    "sg:phone":"+1 214 500 7151",
    "sg:postcode":"75225",
    "sg:province":"TX",
    "sg:tags":[
        "allied",
        "networking"
    ],
    "wof:name":"Dallas Trushaben Inc",
    "wof:placetype":"venue"
},
  "geometry": {"coordinates":[-96.806494,32.863415],"type":"Point"}
}