{
  "type": "Feature",
  "properties": {
    "iso:country":"US",
    "sg:address":"831 Proctor Blvd",
    "sg:city":"San Antonio",
    "sg:classifiers":[
        {
            "category":"Shopping",
            "type":"Retail Goods"
        }
    ],
    "sg:phone":"+1 210 373 6703",
    "sg:postcode":"78221",
    "sg:province":"TX",
    "sg:tags":[
        "merchandise"
    ],
    "wof:name":"Danea & Phoenix Distribution",
    "wof:placetype":"venue"
},
  "geometry": {"coordinates":[-98.52427299999999,29.341633],"type":"Point"}
}