{
  "type": "Feature",
  "properties": {
    "iso:country":"US",
    "sg:address":"400 High St",
    "sg:city":"Brenham",
    "sg:classifiers":[
        {
            "category":"Organizations",
            "subcategory":"Community Association",
            "type":"Services"
        }
    ],
    "sg:phone":"+1 979 836 2910",
    "sg:postcode":"77833",
    "sg:province":"TX",
    "wof:name":"Grand Court Order of Cala",
    "wof:placetype":"venue"
},
  "geometry": {"coordinates":[-96.407179,30.162853],"type":"Point"}
}