{
  "type": "Feature",
  "properties": {
    "iso:country":"US",
    "sg:address":"6210 6th St",
    "sg:city":"Lubbock",
    "sg:classifiers":[
        {
            "category":"Building & Trades",
            "subcategory":"Construction",
            "type":"Services"
        }
    ],
    "sg:phone":"+1 806 687 5676",
    "sg:postcode":"79416",
    "sg:province":"TX",
    "sg:tags":[
        "repairing",
        "remodeling",
        "contractor"
    ],
    "wof:name":"Above & Beyond Remodeling",
    "wof:placetype":"venue"
},
  "geometry": {"coordinates":[-101.95370200000001,33.590426],"type":"Point"}
}