{
  "type": "Feature",
  "properties": {
    "iso:country":"US",
    "sg:address":"6020 Riverview Way",
    "sg:city":"Houston",
    "sg:classifiers":[
        {
            "category":"Banks & Credit Unions",
            "subcategory":"Financial Services",
            "type":"Services"
        }
    ],
    "sg:phone":"+1 713 977 6587",
    "sg:postcode":"77057",
    "sg:province":"TX",
    "sg:tags":[
        "investor"
    ],
    "wof:name":"Hhj Investments Ltd",
    "wof:placetype":"venue"
},
  "geometry": {"coordinates":[-95.482681,29.761483],"type":"Point"}
}