{
  "type": "Feature",
  "properties": {
    "iso:country":"US",
    "sg:address":"800 E Main St",
    "sg:city":"Humble",
    "sg:classifiers":[
        {
            "category":"Social Services",
            "subcategory":"Child Care",
            "type":"Services"
        }
    ],
    "sg:phone":"+1 281 540 7000",
    "sg:postcode":"77338",
    "sg:province":"TX",
    "sg:tags":[
        "kindergarten",
        "academic",
        "school",
        "day"
    ],
    "wof:name":"Children's Weekday Ministries",
    "wof:placetype":"venue"
},
  "geometry": {"coordinates":[-95.258495,29.996156],"type":"Point"}
}