{
  "type": "Feature",
  "properties": {
    "iso:country":"US",
    "sg:address":"505 Bradford Ave",
    "sg:city":"Kemah",
    "sg:classifiers":[
        {
            "category":"Real Estate",
            "subcategory":"Real Estate Agent",
            "type":"Services"
        }
    ],
    "sg:phone":"+1 281 334 5556",
    "sg:postcode":"77565",
    "sg:province":"TX",
    "wof:name":"L&L Realty",
    "wof:placetype":"venue"
},
  "geometry": {"coordinates":[-95.018542,29.544581],"type":"Point"}
}