{
  "type": "Feature",
  "properties": {
    "iso:country":"US",
    "sg:address":"1914 Pequeno St",
    "sg:city":"Austin",
    "sg:classifiers":[
        {
            "category":"Food & Beverages",
            "subcategory":"Supermarket",
            "type":"Retail Goods"
        }
    ],
    "sg:phone":"+1 512 300 4252",
    "sg:postcode":"78757",
    "sg:province":"TX",
    "sg:tags":[
        "super",
        "store"
    ],
    "wof:name":"Ate Foods",
    "wof:placetype":"venue"
},
  "geometry": {"coordinates":[-97.735022,30.33718],"type":"Point"}
}