{
  "type": "Feature",
  "properties": {
    "iso:country":"US",
    "sg:address":"2700 Sir Lancelot Blvd",
    "sg:city":"Lewisville",
    "sg:classifiers":[
        {
            "category":"Building & Trades",
            "subcategory":"Construction",
            "type":"Services"
        }
    ],
    "sg:phone":"+1 972 899 5901",
    "sg:postcode":"75056",
    "sg:province":"TX",
    "sg:tags":[
        "home",
        "builder"
    ],
    "wof:name":"Huntington Homes",
    "wof:placetype":"venue"
},
  "geometry": {"coordinates":[-96.891869,33.03593],"type":"Point"}
}