{
  "type": "Feature",
  "properties": {
    "iso:country":"US",
    "sg:address":"2150 S Edmonds Ln",
    "sg:city":"Lewisville",
    "sg:classifiers":[
        {
            "category":"Education",
            "subcategory":"Special Training",
            "type":"Public Place"
        }
    ],
    "sg:phone":"+1 972 316 0336",
    "sg:postcode":"75067",
    "sg:province":"TX",
    "sg:tags":[
        "child"
    ],
    "wof:name":"Footsteps",
    "wof:placetype":"venue"
},
  "geometry": {"coordinates":[-97.005071,33.008319],"type":"Point"}
}