{
  "type": "Feature",
  "properties": {
    "iso:country":"US",
    "sg:address":"506 Franklin Ave",
    "sg:city":"Waco",
    "sg:classifiers":[
        {
            "category":"Professional",
            "subcategory":"Lawyer & Legal Services",
            "type":"Services"
        }
    ],
    "sg:phone":"+1 254 753 2419",
    "sg:postcode":"76701",
    "sg:province":"TX",
    "wof:name":"Dan Francis",
    "wof:placetype":"venue"
},
  "geometry": {"coordinates":[-97.131677,31.555146],"type":"Point"}
}