{
  "type": "Feature",
  "properties": {
    "iso:country":"US",
    "sg:address":"6922 Alder Dr",
    "sg:city":"Houston",
    "sg:classifiers":[
        {
            "category":"Autos & Motor Vehicles",
            "subcategory":"Auto Supplies",
            "type":"Retail Goods"
        }
    ],
    "sg:phone":"+1 713 432 7969",
    "sg:postcode":"77081",
    "sg:province":"TX",
    "sg:tags":[
        "filter",
        "gas"
    ],
    "sg:website":"www.filterwarehouse.com",
    "wof:name":"Filter Warehouse Co",
    "wof:placetype":"venue"
},
  "geometry": {"coordinates":[-95.48052199999999,29.704646],"type":"Point"}
}