{
  "type": "Feature",
  "properties": {
    "iso:country":"US",
    "sg:address":"2046 N Shiloh Rd",
    "sg:city":"Garland",
    "sg:classifiers":[
        {
            "category":"Real Estate",
            "subcategory":"Real Estate Operator",
            "type":"Services"
        }
    ],
    "sg:phone":"+1 972 495 0348",
    "sg:postcode":"75044",
    "sg:province":"TX",
    "wof:name":"Courtyard Apartments",
    "wof:placetype":"venue"
},
  "geometry": {"coordinates":[-96.665052,32.931916],"type":"Point"}
}