{
  "type": "Feature",
  "properties": {
    "iso:country":"US",
    "sg:address":"3800 Burleson Retta Rd",
    "sg:city":"Burleson",
    "sg:classifiers":[
        {
            "category":"Retail",
            "subcategory":"Repair Shop",
            "type":"Services"
        }
    ],
    "sg:phone":"+1 817 561 1306",
    "sg:postcode":"76028",
    "sg:province":"TX",
    "wof:name":"Classic Furniture Restoration",
    "wof:placetype":"venue"
},
  "geometry": {"coordinates":[-97.25404399999999,32.556087],"type":"Point"}
}