{
  "type": "Feature",
  "properties": {
    "iso:country":"US",
    "sg:address":"19 N Peak Rd",
    "sg:city":"Austin",
    "sg:classifiers":[
        {
            "category":"Manufacturing",
            "subcategory":"Apparel",
            "type":"Manufacturing & Wholesale Goods"
        }
    ],
    "sg:phone":"+1 512 327 2869",
    "sg:postcode":"78746",
    "sg:province":"TX",
    "sg:tags":[
        "clothing"
    ],
    "wof:name":"Scots",
    "wof:placetype":"venue"
},
  "geometry": {"coordinates":[-97.79428900000001,30.276619],"type":"Point"}
}