{
  "type": "Feature",
  "properties": {
    "iso:country":"US",
    "sg:address":"3 Lakeridge Dr",
    "sg:city":"Spring",
    "sg:classifiers":[
        {
            "category":"Professional",
            "subcategory":"Business Services",
            "type":"Services"
        }
    ],
    "sg:phone":"+1 281 367 4761",
    "sg:postcode":"77381",
    "sg:province":"TX",
    "wof:name":"Greek Loft",
    "wof:placetype":"venue"
},
  "geometry": {"coordinates":[-95.504051,30.175412],"type":"Point"}
}