{
  "type": "Feature",
  "properties": {
    "iso:country":"US",
    "sg:address":"9307 York Creek Cir",
    "sg:city":"San Antonio",
    "sg:classifiers":[
        {
            "category":"Banks & Credit Unions",
            "subcategory":"Investment Brokerage",
            "type":"Services"
        }
    ],
    "sg:phone":"+1 210 341 3070",
    "sg:postcode":"78230",
    "sg:province":"TX",
    "sg:tags":[
        "commodity",
        "contract"
    ],
    "wof:name":"San Antonio Commodities",
    "wof:placetype":"venue"
},
  "geometry": {"coordinates":[-98.543632,29.529247],"type":"Point"}
}