{
  "type": "Feature",
  "properties": {
    "iso:country":"US",
    "sg:address":"4107 Kirby St",
    "sg:city":"Rowlett",
    "sg:classifiers":[
        {
            "category":"Personal",
            "subcategory":"Beauty Salon",
            "type":"Services"
        }
    ],
    "sg:phone":"+1 972 475 3498",
    "sg:postcode":"75088",
    "sg:province":"TX",
    "sg:tags":[
        "shop"
    ],
    "wof:name":"Stella's Beauty Shop",
    "wof:placetype":"venue"
},
  "geometry": {"coordinates":[-96.56072899999999,32.902447],"type":"Point"}
}