{
  "type": "Feature",
  "properties": {
    "iso:country":"US",
    "sg:address":"1034 Elberta St",
    "sg:city":"Houston",
    "sg:classifiers":[
        {
            "category":"Building & Trades",
            "subcategory":"Construction",
            "type":"Services"
        }
    ],
    "sg:phone":"+1 713 734 5400",
    "sg:postcode":"77051",
    "sg:province":"TX",
    "sg:tags":[
        "contractor"
    ],
    "wof:name":"H G A Contractor Inc",
    "wof:placetype":"venue"
},
  "geometry": {"coordinates":[-95.36134300000001,29.679482],"type":"Point"}
}