{
  "type": "Feature",
  "properties": {
    "iso:country":"US",
    "sg:address":"1221 N Hopson St",
    "sg:city":"Sherman",
    "sg:classifiers":[
        {
            "category":"Professional",
            "subcategory":"Business Services",
            "type":"Services"
        }
    ],
    "sg:phone":"+1 903 892 9327",
    "sg:postcode":"75092",
    "sg:province":"TX",
    "wof:name":"Tawni Hodge Interiors",
    "wof:placetype":"venue"
},
  "geometry": {"coordinates":[-96.61636900000001,33.647324],"type":"Point"}
}