{
  "type": "Feature",
  "properties": {
    "iso:country":"US",
    "sg:address":"17060 Dallas Pkwy",
    "sg:city":"Dallas",
    "sg:classifiers":[
        {
            "category":"Real Estate",
            "subcategory":"Real Estate Services",
            "type":"Services"
        }
    ],
    "sg:phone":"+1 972 248 6130",
    "sg:postcode":"75248",
    "sg:province":"TX",
    "sg:tags":[
        "management",
        "property"
    ],
    "wof:name":"Sealy Real Estate Alarm Line",
    "wof:placetype":"venue"
},
  "geometry": {"coordinates":[-96.828098,32.980129],"type":"Point"}
}