{
  "type": "Feature",
  "properties": {
    "iso:country":"US",
    "sg:address":"5405 High Ridge Rd",
    "sg:city":"Fort Worth",
    "sg:classifiers":[
        {
            "category":"Cinema",
            "subcategory":"Movie Theater",
            "type":"Entertainment"
        }
    ],
    "sg:phone":"+1 817 478 9012",
    "sg:postcode":"76140",
    "sg:province":"TX",
    "sg:tags":[
        "motion",
        "picture",
        "book"
    ],
    "wof:name":"Log Cabin Adult Theater",
    "wof:placetype":"venue"
},
  "geometry": {"coordinates":[-97.23929099999999,32.6624],"type":"Point"}
}