{
  "type": "Feature",
  "properties": {
    "iso:country":"US",
    "sg:address":"400 Dove Hollow Dr",
    "sg:city":"Kyle",
    "sg:classifiers":[
        {
            "category":"Building & Trades",
            "subcategory":"Construction",
            "type":"Services"
        }
    ],
    "sg:phone":"+1 512 268 2174",
    "sg:postcode":"78640",
    "sg:province":"TX",
    "sg:tags":[
        "woodworker"
    ],
    "wof:name":"Just Woodworks",
    "wof:placetype":"venue"
},
  "geometry": {"coordinates":[-97.896455,30.0181],"type":"Point"}
}