{
  "type": "Feature",
  "properties": {
    "iso:country":"US",
    "sg:address":"7887 W. Tidwell Rd",
    "sg:city":"Houston",
    "sg:classifiers":[
        {
            "category":"Travel",
            "subcategory":"Hotels & Motels",
            "type":"Entertainment"
        }
    ],
    "sg:phone":"+1 713 690 1493",
    "sg:postcode":"77040",
    "sg:province":"TX",
    "wof:name":"Comfort Inn Houston NW/290",
    "wof:placetype":"venue"
},
  "geometry": {"coordinates":[-95.510497,29.850231],"type":"Point"}
}