{
  "type": "Feature",
  "properties": {
    "iso:country":"US",
    "sg:address":"920 E 6th Ave",
    "sg:city":"Belton",
    "sg:classifiers":[
        {
            "category":"Wholesale",
            "subcategory":"Machinery & Supplies",
            "type":"Manufacturing & Wholesale Goods"
        }
    ],
    "sg:phone":"+1 254 939 3731",
    "sg:postcode":"76513",
    "sg:province":"TX",
    "sg:tags":[
        "farm",
        "equipment"
    ],
    "wof:name":"Ag-Meier Inc Belton",
    "wof:placetype":"venue"
},
  "geometry": {"coordinates":[-97.45318899999999,31.059369],"type":"Point"}
}