{
  "type": "Feature",
  "properties": {
    "iso:country":"US",
    "sg:address":"4699 Fossil Vista Dr",
    "sg:city":"Haltom City",
    "sg:classifiers":[
        {
            "category":"Real Estate",
            "subcategory":"Real Estate Operator",
            "type":"Services"
        }
    ],
    "sg:phone":"+1 817 514 0229",
    "sg:postcode":"76137",
    "sg:province":"TX",
    "sg:tags":[
        "apartment"
    ],
    "wof:name":"Amesbury Court Apartments",
    "wof:placetype":"venue"
},
  "geometry": {"coordinates":[-97.28531599999999,32.841451],"type":"Point"}
}