{
  "type": "Feature",
  "properties": {
    "iso:country":"US",
    "sg:address":"1900 SE Loop 820",
    "sg:city":"Fort Worth",
    "sg:classifiers":[
        {
            "category":"Manufacturing",
            "subcategory":"Tools & Machinery",
            "type":"Manufacturing & Wholesale Goods"
        }
    ],
    "sg:phone":"+1 817 293 4600",
    "sg:postcode":"76140",
    "sg:province":"TX",
    "sg:tags":[
        "equipment",
        "mfg",
        "m",
        "automotive",
        "repair"
    ],
    "wof:name":"Four Ssns- Fort Wrth Oprations",
    "wof:placetype":"venue"
},
  "geometry": {"coordinates":[-97.30211199999999,32.668847],"type":"Point"}
}