{
  "type": "Feature",
  "properties": {
    "iso:country":"US",
    "sg:address":"444 E Pipeline Rd",
    "sg:city":"Hurst",
    "sg:classifiers":[
        {
            "category":"Organizations",
            "subcategory":"Religious Organization",
            "type":"Services"
        }
    ],
    "sg:phone":"+1 817 285 8774",
    "sg:postcode":"76053",
    "sg:province":"TX",
    "sg:tags":[
        "church"
    ],
    "wof:name":"Hope In Christ Intl Church",
    "wof:placetype":"venue"
},
  "geometry": {"coordinates":[-97.162978,32.823475],"type":"Point"}
}