{
  "type": "Feature",
  "properties": {
    "iso:country":"US",
    "sg:address":"1950 N Stemmons Fwy",
    "sg:city":"Dallas",
    "sg:classifiers":[
        {
            "category":"Banks & Credit Unions",
            "subcategory":"Investment Brokerage",
            "type":"Services"
        }
    ],
    "sg:phone":"+1 214 746 4705",
    "sg:postcode":"75207",
    "sg:province":"TX",
    "wof:name":"Health Care Systems Inc",
    "wof:placetype":"venue"
},
  "geometry": {"coordinates":[-96.82155,32.79957],"type":"Point"}
}