{
  "type": "Feature",
  "properties": {
    "iso:country":"US",
    "sg:address":"120 Circle Way St",
    "sg:city":"Lake Jackson",
    "sg:classifiers":[
        {
            "category":"Insurance",
            "subcategory":"Insurance Agent",
            "type":"Services"
        }
    ],
    "sg:phone":"+1 979 297 5100",
    "sg:postcode":"77566",
    "sg:province":"TX",
    "wof:name":"Allstate Insurance",
    "wof:placetype":"venue"
},
  "geometry": {"coordinates":[-95.448671,29.03846],"type":"Point"}
}