{
  "type": "Feature",
  "properties": {
    "iso:country":"US",
    "sg:address":"3917 Wentwood Dr",
    "sg:city":"Dallas",
    "sg:classifiers":[
        {
            "category":"Professional",
            "subcategory":"Lawyer & Legal Services",
            "type":"Services"
        }
    ],
    "sg:phone":"+1 214 691 1186",
    "sg:postcode":"75225",
    "sg:province":"TX",
    "wof:name":"Read W Michael",
    "wof:placetype":"venue"
},
  "geometry": {"coordinates":[-96.799768,32.863083],"type":"Point"}
}