{
  "type": "Feature",
  "properties": {
    "iso:country":"US",
    "sg:address":"1930 E Mills Ave",
    "sg:city":"El Paso",
    "sg:classifiers":[
        {
            "category":"Manufacturing",
            "subcategory":"Apparel",
            "type":"Manufacturing & Wholesale Goods"
        }
    ],
    "sg:phone":"+1 915 838 8118",
    "sg:postcode":"79901",
    "sg:province":"TX",
    "sg:tags":[
        "tarpaulin"
    ],
    "sg:website":"www.milrs.com",
    "wof:name":"Military Resource Svc Inc",
    "wof:placetype":"venue"
},
  "geometry": {"coordinates":[-106.46913000000001,31.771464],"type":"Point"}
}