{
  "type": "Feature",
  "properties": {
    "iso:country":"US",
    "sg:address":"9609 Boat Club Rd",
    "sg:city":"Fort Worth",
    "sg:classifiers":[
        {
            "category":"Professional",
            "subcategory":"Management & Consulting",
            "type":"Services"
        }
    ],
    "sg:phone":"+1 817 236 6000",
    "sg:postcode":"76179",
    "sg:province":"TX",
    "sg:tags":[
        "construction"
    ],
    "wof:name":"B-C Co",
    "wof:placetype":"venue"
},
  "geometry": {"coordinates":[-97.476054,32.90179],"type":"Point"}
}