{
  "type": "Feature",
  "properties": {
    "iso:country":"US",
    "sg:address":"6626 Flowermound Dr",
    "sg:city":"Sugar Land",
    "sg:classifiers":[
        {
            "category":"Building & Trades",
            "subcategory":"Pest Control",
            "type":"Services"
        }
    ],
    "sg:phone":"+1 281 879 6201",
    "sg:postcode":"77479",
    "sg:province":"TX",
    "wof:name":"Crusader Pest Control",
    "wof:placetype":"venue"
},
  "geometry": {"coordinates":[-95.69487700000001,29.550083],"type":"Point"}
}