{
  "type": "Feature",
  "properties": {
    "iso:country":"US",
    "sg:address":"114 S Church St",
    "sg:city":"Hillsboro",
    "sg:classifiers":[
        {
            "category":"Personal",
            "subcategory":"Beauty Salon",
            "type":"Services"
        }
    ],
    "sg:phone":"+1 254 580 9400",
    "sg:postcode":"76645",
    "sg:province":"TX",
    "sg:tags":[
        "shop"
    ],
    "wof:name":"Place Salon & Spa",
    "wof:placetype":"venue"
},
  "geometry": {"coordinates":[-97.12844200000001,32.010007],"type":"Point"}
}