{
  "type": "Feature",
  "properties": {
    "iso:country":"US",
    "sg:address":"202 Broadway",
    "sg:city":"Nordheim",
    "sg:classifiers":[
        {
            "category":"Personal",
            "subcategory":"Beauty Salon",
            "type":"Services"
        },
        {
            "category":"Personal",
            "subcategory":"Barber",
            "type":"Services"
        }
    ],
    "sg:phone":"+1 361 938 5882",
    "sg:postcode":"78141",
    "sg:province":"TX",
    "sg:tags":[
        "hair",
        "stylist"
    ],
    "wof:name":"Oralia's Hair Station",
    "wof:placetype":"venue"
},
  "geometry": {"coordinates":[-97.61021700000001,28.921824],"type":"Point"}
}