{
  "type": "Feature",
  "properties": {
    "iso:country":"US",
    "sg:address":"3134 E Crosstimbers St",
    "sg:city":"Houston",
    "sg:classifiers":[
        {
            "category":"Food & Beverages",
            "subcategory":"Groceries & Convenience Stores",
            "type":"Retail Goods"
        }
    ],
    "sg:phone":"+1 713 742 5656",
    "sg:postcode":"77093",
    "sg:province":"TX",
    "wof:name":"S S Food Mart",
    "wof:placetype":"venue"
},
  "geometry": {"coordinates":[-95.338228,29.829108],"type":"Point"}
}