{
  "type": "Feature",
  "properties": {
    "iso:country":"US",
    "sg:address":"1806 Bangor Ave",
    "sg:city":"Lubbock",
    "sg:classifiers":[
        {
            "category":"Insurance",
            "subcategory":"Insurance Agent",
            "type":"Services"
        }
    ],
    "sg:phone":"+1 806 792 2321",
    "sg:postcode":"79416",
    "sg:province":"TX",
    "wof:name":"John Hancock Life Insurance Co",
    "wof:placetype":"venue"
},
  "geometry": {"coordinates":[-101.92710099999999,33.578458],"type":"Point"}
}