{
  "type": "Feature",
  "properties": {
    "iso:country":"US",
    "sg:address":"4814 96th St",
    "sg:city":"Lubbock",
    "sg:classifiers":[
        {
            "category":"Professional",
            "type":"Services"
        }
    ],
    "sg:phone":"+1 806 794 5228",
    "sg:postcode":"79424",
    "sg:province":"TX",
    "wof:name":"Npk Ltd",
    "wof:placetype":"venue"
},
  "geometry": {"coordinates":[-101.915111,33.506643],"type":"Point"}
}