{
  "type": "Feature",
  "properties": {
    "iso:country":"US",
    "sg:address":"9840 Carnegie Ave",
    "sg:city":"El Paso",
    "sg:classifiers":[
        {
            "category":"Manufacturing",
            "subcategory":"Apparel",
            "type":"Manufacturing & Wholesale Goods"
        },
        {
            "category":"Home & Garden",
            "subcategory":"Home Furnishings",
            "type":"Retail Goods"
        }
    ],
    "sg:phone":"+1 915 598 7070",
    "sg:postcode":"79925",
    "sg:province":"TX",
    "sg:tags":[
        "mfg",
        "curtain",
        "made",
        "drapery",
        "custom"
    ],
    "wof:name":"Octavio's Custom Drapery Inc",
    "wof:placetype":"venue"
},
  "geometry": {"coordinates":[-106.35325,31.796351],"type":"Point"}
}