{
  "type": "Feature",
  "properties": {
    "iso:country":"US",
    "sg:address":"519 Porfirio Diaz St",
    "sg:city":"El Paso",
    "sg:classifiers":[
        {
            "category":"Building & Trades",
            "subcategory":"Construction",
            "type":"Services"
        }
    ],
    "sg:phone":"+1 915 532 1170",
    "sg:postcode":"79902",
    "sg:province":"TX",
    "sg:tags":[
        "roofing",
        "contractor"
    ],
    "wof:name":"Ricky Hernandez General Contr",
    "wof:placetype":"venue"
},
  "geometry": {"coordinates":[-106.502258,31.764322],"type":"Point"}
}