{
  "type": "Feature",
  "properties": {
    "iso:country":"US",
    "sg:address":"13900 Midway Rd",
    "sg:city":"Dallas",
    "sg:classifiers":[
        {
            "category":"Utilities",
            "subcategory":"Mobile Phone",
            "type":"Services"
        }
    ],
    "sg:phone":"+1 972 661 5260",
    "sg:postcode":"75244",
    "sg:province":"TX",
    "sg:tags":[
        "telephone",
        "cellular"
    ],
    "wof:name":"Cingular Wireless",
    "wof:placetype":"venue"
},
  "geometry": {"coordinates":[-96.83893500000001,32.938956],"type":"Point"}
}