{
  "type": "Feature",
  "properties": {
    "iso:country":"US",
    "sg:address":"105 Mesa Springs Rd",
    "sg:city":"Weatherford",
    "sg:classifiers":[
        {
            "category":"Utilities",
            "subcategory":"Telephone",
            "type":"Services"
        }
    ],
    "sg:phone":"+1 817 441 6080",
    "sg:postcode":"76087",
    "sg:province":"TX",
    "sg:tags":[
        "communications"
    ],
    "wof:name":"Marksports Co",
    "wof:placetype":"venue"
},
  "geometry": {"coordinates":[-97.63117699999999,32.740907],"type":"Point"}
}