{
  "type": "Feature",
  "properties": {
    "iso:country":"US",
    "sg:address":"5111 Airport Blvd",
    "sg:city":"Austin",
    "sg:classifiers":[
        {
            "category":"Restaurant",
            "type":"Food & Drink"
        }
    ],
    "sg:phone":"+1 512 600 4999",
    "sg:postcode":"78751",
    "sg:province":"TX",
    "sg:tags":[
        "pizza"
    ],
    "sg:website":"www.housepizzeria.com",
    "wof:name":"House Pizzeria",
    "wof:placetype":"venue"
},
  "geometry": {"coordinates":[-97.715068,30.312814],"type":"Point"}
}