{
  "type": "Feature",
  "properties": {
    "iso:country":"US",
    "sg:address":"204 Sheldon Rd",
    "sg:city":"Channelview",
    "sg:classifiers":[
        {
            "category":"Wholesale",
            "subcategory":"Electrical",
            "type":"Manufacturing & Wholesale Goods"
        }
    ],
    "sg:phone":"+1 281 457 1100",
    "sg:postcode":"77530",
    "sg:province":"TX",
    "sg:tags":[
        "alarm",
        "burglar",
        "system"
    ],
    "wof:name":"Link Tech",
    "wof:placetype":"venue"
},
  "geometry": {"coordinates":[-95.124332,29.774486],"type":"Point"}
}