{
  "type": "Feature",
  "properties": {
    "iso:country":"US",
    "sg:address":"8770 E State Hwy 21",
    "sg:city":"Bryan",
    "sg:classifiers":[
        {
            "category":"Utilities",
            "subcategory":"Water",
            "type":"Services"
        }
    ],
    "sg:phone":"+1 979 589 3030",
    "sg:postcode":"77808",
    "sg:province":"TX",
    "sg:tags":[
        "company",
        "sewage"
    ],
    "sg:website":"www.wicksoncreek.com",
    "wof:name":"Wickson Creek Special Utility",
    "wof:placetype":"venue"
},
  "geometry": {"coordinates":[-96.30916499999999,30.747123],"type":"Point"}
}