{
  "type": "Feature",
  "properties": {
    "iso:country":"US",
    "sg:address":"1011 San Jacinto Blvd",
    "sg:city":"Austin",
    "sg:classifiers":[
        {
            "category":"Professional",
            "subcategory":"Advertising",
            "type":"Services"
        }
    ],
    "sg:phone":"+1 512 462 3366",
    "sg:postcode":"78701",
    "sg:province":"TX",
    "sg:tags":[
        "agency",
        "specialty"
    ],
    "wof:name":"The Ampersand Agency",
    "wof:placetype":"venue"
},
  "geometry": {"coordinates":[-97.73883499999999,30.27159],"type":"Point"}
}