{
  "type": "Feature",
  "properties": {
    "iso:country":"US",
    "sg:address":"815 Serna Dr",
    "sg:city":"New Braunfels",
    "sg:classifiers":[
        {
            "category":"Shopping",
            "subcategory":"Florist",
            "type":"Retail Goods"
        }
    ],
    "sg:phone":"+1 830 606 0140",
    "sg:postcode":"78130",
    "sg:province":"TX",
    "wof:name":"A Hint Of Romance",
    "wof:placetype":"venue"
},
  "geometry": {"coordinates":[-98.07523399999999,29.675417],"type":"Point"}
}