{
  "type": "Feature",
  "properties": {
    "iso:country":"US",
    "sg:address":"4 Bramlette Pl",
    "sg:city":"Longview",
    "sg:classifiers":[
        {
            "category":"Professional",
            "subcategory":"Business Services",
            "type":"Services"
        }
    ],
    "sg:phone":"+1 903 757 6008",
    "sg:postcode":"75601",
    "sg:province":"TX",
    "wof:name":"D Hurst Ltd Partnership",
    "wof:placetype":"venue"
},
  "geometry": {"coordinates":[-94.748062,32.525718],"type":"Point"}
}