{
  "type": "Feature",
  "properties": {
    "iso:country":"US",
    "sg:address":"4170 Lavon Dr",
    "sg:city":"Garland",
    "sg:classifiers":[
        {
            "category":"Restaurant",
            "type":"Food & Drink"
        }
    ],
    "sg:phone":"+1 972 202 5490",
    "sg:postcode":"75040",
    "sg:province":"TX",
    "sg:tags":[
        "chinese"
    ],
    "sg:website":"www.peiwei.com",
    "wof:name":"Pei Wei",
    "wof:placetype":"venue"
},
  "geometry": {"coordinates":[-96.61743199999999,32.955627],"type":"Point"}
}