{
  "type": "Feature",
  "properties": {
    "iso:country":"US",
    "sg:address":"6 Oakcreek Dr",
    "sg:city":"Temple",
    "sg:classifiers":[
        {
            "category":"Shopping",
            "subcategory":"Jewelry",
            "type":"Retail Goods"
        }
    ],
    "sg:phone":"+1 254 771 5446",
    "sg:postcode":"76504",
    "sg:province":"TX",
    "wof:name":"Pams Jewelry Connection & Mor",
    "wof:placetype":"venue"
},
  "geometry": {"coordinates":[-97.380354,31.108447],"type":"Point"}
}