{
  "type": "Feature",
  "properties": {
    "iso:country":"US",
    "sg:address":"510 Redbud Ln",
    "sg:city":"Mount Pleasant",
    "sg:classifiers":[
        {
            "category":"Building & Trades",
            "subcategory":"Construction",
            "type":"Services"
        }
    ],
    "sg:phone":"+1 903 572 6516",
    "sg:postcode":"75455",
    "sg:province":"TX",
    "sg:tags":[
        "house"
    ],
    "wof:name":"Swearengin Construction Co",
    "wof:placetype":"venue"
},
  "geometry": {"coordinates":[-94.958831,33.139422],"type":"Point"}
}