{
  "type": "Feature",
  "properties": {
    "iso:country":"US",
    "sg:address":"8201 Katy Fwy",
    "sg:city":"Houston",
    "sg:classifiers":[
        {
            "category":"Shopping",
            "subcategory":"Pharmacy",
            "type":"Retail Goods"
        }
    ],
    "sg:phone":"+1 713 957 7500",
    "sg:postcode":"77024",
    "sg:province":"TX",
    "sg:tags":[
        "drugstore"
    ],
    "sg:website":"www.cvs.com",
    "wof:name":"CVS pharmacy",
    "wof:placetype":"venue"
},
  "geometry": {"coordinates":[-95.485091,29.783302],"type":"Point"}
}