{
  "type": "Feature",
  "properties": {
    "iso:country":"US",
    "sg:address":"19615 FM 2920",
    "sg:city":"Tomball",
    "sg:classifiers":[
        {
            "category":"Building & Trades",
            "subcategory":"Construction",
            "type":"Services"
        }
    ],
    "sg:phone":"+1 281 820 0396",
    "sg:postcode":"77377",
    "sg:province":"TX",
    "sg:tags":[
        "merchandise",
        "contractor"
    ],
    "wof:name":"Buster Crabbe Pools of Houston",
    "wof:placetype":"venue"
},
  "geometry": {"coordinates":[-95.729601,30.081373],"type":"Point"}
}