{
  "type": "Feature",
  "properties": {
    "iso:country":"US",
    "sg:address":"2225 Hidden Woods",
    "sg:city":"Arlington",
    "sg:classifiers":[
        {
            "category":"Shopping",
            "subcategory":"Bicycles & Sporting Goods",
            "type":"Retail Goods"
        }
    ],
    "sg:phone":"+1 214 537 5848",
    "sg:postcode":"76006",
    "sg:province":"TX",
    "sg:tags":[
        "equipment",
        "golf",
        "supply"
    ],
    "wof:name":"Time For Golf",
    "wof:placetype":"venue"
},
  "geometry": {"coordinates":[-97.073251,32.77748],"type":"Point"}
}