{
  "type": "Feature",
  "properties": {
    "iso:country":"US",
    "sg:address":"7750 N Macarthur Blvd # 180",
    "sg:city":"Irving",
    "sg:classifiers":[
        {
            "category":"Shopping",
            "subcategory":"Bicycles & Sporting Goods",
            "type":"Retail Goods"
        },
        {
            "category":"Sports & Exercise",
            "subcategory":"Golf",
            "type":"Entertainment"
        }
    ],
    "sg:phone":"+1 972 869 2380",
    "sg:postcode":"75063",
    "sg:province":"TX",
    "sg:tags":[
        "equipment",
        "course",
        "equipment-repairing",
        "supply"
    ],
    "sg:website":"http://www.golfetc.com",
    "wof:name":"Golf Etc. Las Colinas",
    "wof:placetype":"venue"
},
  "geometry": {"coordinates":[-96.958583,32.912085],"type":"Point"}
}