{
  "type": "Feature",
  "properties": {
    "iso:country":"US",
    "sg:address":"1910 Hilltree Ln",
    "sg:city":"Cedar Park",
    "sg:classifiers":[
        {
            "category":"Retail",
            "subcategory":"Car Wash",
            "type":"Services"
        }
    ],
    "sg:phone":"+1 512 422 8007",
    "sg:postcode":"78613",
    "sg:province":"TX",
    "sg:tags":[
        "carwash"
    ],
    "wof:name":"On Spot Power Washing",
    "wof:placetype":"venue"
},
  "geometry": {"coordinates":[-97.850346,30.527594],"type":"Point"}
}