{
  "type": "Feature",
  "properties": {
    "iso:country":"US",
    "sg:address":"8500 Cook Rd",
    "sg:city":"Houston",
    "sg:classifiers":[
        {
            "category":"Shopping",
            "type":"Retail Goods"
        }
    ],
    "sg:phone":"+1 281 495 5328",
    "sg:postcode":"77072",
    "sg:province":"TX",
    "sg:tags":[
        "merchandise"
    ],
    "wof:name":"Jungle Video Games",
    "wof:placetype":"venue"
},
  "geometry": {"coordinates":[-95.595894,29.684755],"type":"Point"}
}