{
  "type": "Feature",
  "properties": {
    "iso:country":"US",
    "sg:address":"414 Olive St",
    "sg:city":"Jasper",
    "sg:classifiers":[
        {
            "category":"Professional",
            "type":"Services"
        }
    ],
    "sg:phone":"+1 409 384 4567",
    "sg:postcode":"75951",
    "sg:province":"TX",
    "wof:name":"Main Street Gallery",
    "wof:placetype":"venue"
},
  "geometry": {"coordinates":[-94.006522,30.925831],"type":"Point"}
}