{
  "type": "Feature",
  "properties": {
    "iso:country":"US",
    "sg:address":"10634 Gulfdale St",
    "sg:city":"San Antonio",
    "sg:classifiers":[
        {
            "category":"Organizations",
            "subcategory":"Religious Organization",
            "type":"Services"
        }
    ],
    "sg:phone":"+1 210 342 1625",
    "sg:postcode":"78216",
    "sg:province":"TX",
    "wof:name":"Vision Chapel",
    "wof:placetype":"venue"
},
  "geometry": {"coordinates":[-98.48894199999999,29.535963],"type":"Point"}
}