{
  "type": "Feature",
  "properties": {
    "iso:country":"US",
    "sg:address":"1004 96th St",
    "sg:city":"Houston",
    "sg:classifiers":[
        {
            "category":"Professional",
            "subcategory":"Management & Consulting",
            "type":"Services"
        },
        {
            "category":"Professional",
            "subcategory":"Engineering",
            "type":"Services"
        }
    ],
    "sg:phone":"+1 713 921 2282",
    "sg:postcode":"77012",
    "sg:province":"TX",
    "sg:tags":[
        "environmental",
        "ecological",
        "engineer",
        "consultant"
    ],
    "wof:name":"Innovative Cleaning Solutions, Inc.",
    "wof:placetype":"venue"
},
  "geometry": {"coordinates":[-95.25595,29.717862],"type":"Point"}
}