{
  "type": "Feature",
  "properties": {
    "iso:country":"US",
    "sg:address":"20911 Pecan Bend Rd",
    "sg:city":"Damon",
    "sg:classifiers":[
        {
            "category":"Professional",
            "type":"Services"
        }
    ],
    "sg:phone":"+1 979 553 4640",
    "sg:postcode":"77430",
    "sg:province":"TX",
    "wof:name":"Dorothy Petrosky",
    "wof:placetype":"venue"
},
  "geometry": {"coordinates":[-95.607338,29.356257],"type":"Point"}
}