{
  "type": "Feature",
  "properties": {
    "iso:country":"US",
    "sg:address":"777 S Central Expy",
    "sg:city":"Richardson",
    "sg:classifiers":[
        {
            "category":"Taxi",
            "type":"Transportation"
        }
    ],
    "sg:phone":"+1 972 644 5437",
    "sg:postcode":"75080",
    "sg:province":"TX",
    "wof:name":"Going My Way",
    "wof:placetype":"venue"
},
  "geometry": {"coordinates":[-96.73862200000001,32.9451],"type":"Point"}
}