{
  "type": "Feature",
  "properties": {
    "iso:country":"US",
    "sg:address":"19895 Scott Gardner Rd",
    "sg:city":"New Caney",
    "sg:classifiers":[
        {
            "category":"Recreation",
            "type":"Entertainment"
        }
    ],
    "sg:phone":"+1 281 399 4422",
    "sg:postcode":"77357",
    "sg:province":"TX",
    "sg:tags":[
        "stable"
    ],
    "wof:name":"Magnolia Acres Farm & Stables",
    "wof:placetype":"venue"
},
  "geometry": {"coordinates":[-95.178039,30.155914],"type":"Point"}
}