{
  "type": "Feature",
  "properties": {
    "iso:country":"US",
    "sg:address":"107 Edgewater Cove",
    "sg:city":"Austin",
    "sg:classifiers":[
        {
            "category":"Professional",
            "subcategory":"Business Services",
            "type":"Services"
        }
    ],
    "sg:phone":"+1 512 261 3520",
    "sg:postcode":"78734",
    "sg:province":"TX",
    "wof:name":"Cawoods Liquor",
    "wof:placetype":"venue"
},
  "geometry": {"coordinates":[-97.977198,30.381943],"type":"Point"}
}