{
  "type": "Feature",
  "properties": {
    "iso:country":"US",
    "sg:address":"6424 Bayway Dr",
    "sg:city":"Baytown",
    "sg:classifiers":[
        {
            "category":"Building & Trades",
            "subcategory":"Pest Control",
            "type":"Services"
        }
    ],
    "sg:phone":"+1 281 424 7622",
    "sg:postcode":"77520",
    "sg:province":"TX",
    "wof:name":"Agri-Rodent Shield",
    "wof:placetype":"venue"
},
  "geometry": {"coordinates":[-95.033798,29.758301],"type":"Point"}
}