{
  "type": "Feature",
  "properties": {
    "iso:country":"US",
    "sg:address":"2200 S Gordon St",
    "sg:city":"Alvin",
    "sg:phone":"+1 281 388 2850",
    "sg:postcode":"77511",
    "sg:province":"TX",
    "wof:name":"Bubs Sports Bar",
    "wof:placetype":"venue"
},
  "geometry": {"coordinates":[-95.245242,29.402409],"type":"Point"}
}