{
  "type": "Feature",
  "properties": {
    "iso:country":"US",
    "sg:address":"14030 Almeda Rd",
    "sg:city":"Houston",
    "sg:classifiers":[
        {
            "category":"Food & Beverages",
            "subcategory":"Groceries & Convenience Stores",
            "type":"Retail Goods"
        }
    ],
    "sg:phone":"+1 713 434 8124",
    "sg:postcode":"77053",
    "sg:province":"TX",
    "sg:tags":[
        "grocer"
    ],
    "wof:name":"La Potosina Grocery Store",
    "wof:placetype":"venue"
},
  "geometry": {"coordinates":[-95.42379800000001,29.603201],"type":"Point"}
}