{
  "type": "Feature",
  "properties": {
    "iso:country":"US",
    "sg:address":"2420 Ave A",
    "sg:city":"Nederland",
    "sg:classifiers":[
        {
            "category":"Professional",
            "subcategory":"Business Services",
            "type":"Services"
        }
    ],
    "sg:phone":"+1 409 722 7958",
    "sg:postcode":"77627",
    "sg:province":"TX",
    "wof:name":"Maxey Valda Artist",
    "wof:placetype":"venue"
},
  "geometry": {"coordinates":[-93.996633,29.965533],"type":"Point"}
}