{
  "type": "Feature",
  "properties": {
    "iso:country":"US",
    "sg:address":"2611 Baltimore Rd",
    "sg:city":"Wichita Falls",
    "sg:classifiers":[
        {
            "category":"Manufacturing",
            "subcategory":"Retail Goods",
            "type":"Manufacturing & Wholesale Goods"
        }
    ],
    "sg:phone":"+1 940 692 7256",
    "sg:postcode":"76309",
    "sg:province":"TX",
    "sg:tags":[
        "assembly",
        "fabricating"
    ],
    "wof:name":"Fairview Assembly - God Prsng",
    "wof:placetype":"venue"
},
  "geometry": {"coordinates":[-98.53725300000001,33.886863],"type":"Point"}
}