{
  "type": "Feature",
  "properties": {
    "iso:country":"US",
    "sg:address":"9626 Center Rd",
    "sg:city":"Laredo",
    "sg:classifiers":[
        {
            "category":"Retail",
            "subcategory":"Auto Repair",
            "type":"Services"
        }
    ],
    "sg:phone":"+1 956 727 2979",
    "sg:postcode":"78045",
    "sg:province":"TX",
    "sg:tags":[
        "automotive"
    ],
    "wof:name":"Phoenix Automotive",
    "wof:placetype":"venue"
},
  "geometry": {"coordinates":[-99.52220699999999,27.587939],"type":"Point"}
}