{
  "type": "Feature",
  "properties": {
    "iso:country":"US",
    "sg:address":"2499 E 11th St",
    "sg:city":"Odessa",
    "sg:classifiers":[
        {
            "category":"Health Services",
            "subcategory":"Doctor",
            "type":"Services"
        }
    ],
    "sg:phone":"+1 432 337 7951",
    "sg:postcode":"79761",
    "sg:province":"TX",
    "wof:name":"Dana L Walker DDS",
    "wof:placetype":"venue"
},
  "geometry": {"coordinates":[-102.34244200000001,31.864355],"type":"Point"}
}