{
  "type": "Feature",
  "properties": {
    "iso:country":"US",
    "sg:address":"3610 105th St",
    "sg:city":"Lubbock",
    "sg:classifiers":[
        {
            "category":"Farming",
            "subcategory":"Farm",
            "type":"Manufacturing & Wholesale Goods"
        }
    ],
    "sg:phone":"+1 806 748 3936",
    "sg:postcode":"79423",
    "sg:province":"TX",
    "sg:tags":[
        "crop",
        "general"
    ],
    "wof:name":"McGehee Farms",
    "wof:placetype":"venue"
},
  "geometry": {"coordinates":[-101.894206,33.499212],"type":"Point"}
}