{
  "type": "Feature",
  "properties": {
    "iso:country":"US",
    "sg:address":"402 W Bowie St",
    "sg:city":"Marshall",
    "sg:classifiers":[
        {
            "category":"Health Services",
            "subcategory":"Doctor",
            "type":"Services"
        }
    ],
    "sg:phone":"+1 903 938 5561",
    "sg:postcode":"75670",
    "sg:province":"TX",
    "wof:name":"Emory S Timmins DDS",
    "wof:placetype":"venue"
},
  "geometry": {"coordinates":[-94.371264,32.544113],"type":"Point"}
}