{
  "type": "Feature",
  "properties": {
    "iso:country":"US",
    "sg:address":"313 E Criner St",
    "sg:city":"Grandview",
    "sg:classifiers":[
        {
            "category":"Food & Beverages",
            "subcategory":"Groceries & Convenience Stores",
            "type":"Retail Goods"
        }
    ],
    "sg:phone":"+1 817 866 3372",
    "sg:postcode":"76050",
    "sg:province":"TX",
    "sg:tags":[
        "grocer"
    ],
    "wof:name":"David's Supermarket",
    "wof:placetype":"venue"
},
  "geometry": {"coordinates":[-97.17813,32.270277],"type":"Point"}
}