{
  "type": "Feature",
  "properties": {
    "iso:country":"US",
    "sg:address":"511 Schweikhardt St",
    "sg:city":"Houston",
    "sg:classifiers":[
        {
            "category":"Food & Beverages",
            "subcategory":"Groceries & Convenience Stores",
            "type":"Retail Goods"
        }
    ],
    "sg:phone":"+1 713 673 2359",
    "sg:postcode":"77020",
    "sg:province":"TX",
    "wof:name":"Golden Food Market",
    "wof:placetype":"venue"
},
  "geometry": {"coordinates":[-95.323196,29.7673],"type":"Point"}
}