{
  "type": "Feature",
  "properties": {
    "iso:country":"US",
    "sg:address":"26 Horseshoe Dr",
    "sg:city":"Lewisville",
    "sg:classifiers":[
        {
            "category":"Communications",
            "type":"Services"
        }
    ],
    "sg:phone":"+1 214 908 6251",
    "sg:postcode":"75077",
    "sg:province":"TX",
    "sg:tags":[
        "data"
    ],
    "wof:name":"D&B Communications, Inc.",
    "wof:placetype":"venue"
},
  "geometry": {"coordinates":[-97.047248,33.095739],"type":"Point"}
}