{
  "type": "Feature",
  "properties": {
    "iso:country":"US",
    "sg:address":"2119 Dallas St",
    "sg:city":"Houston",
    "sg:classifiers":[
        {
            "category":"Wholesale",
            "subcategory":"Fruits & Vegetables",
            "type":"Manufacturing & Wholesale Goods"
        }
    ],
    "sg:phone":"+1 713 221 5447",
    "sg:postcode":"77003",
    "sg:province":"TX",
    "sg:tags":[
        "vegetables-wholesale"
    ],
    "wof:name":"Kim Organic Farm",
    "wof:placetype":"venue"
},
  "geometry": {"coordinates":[-95.356488,29.749674],"type":"Point"}
}