{
  "type": "Feature",
  "properties": {
    "iso:country":"US",
    "sg:address":"304 Gilbert St",
    "sg:city":"Pasadena",
    "sg:classifiers":[
        {
            "category":"Building & Trades",
            "subcategory":"Construction",
            "type":"Services"
        }
    ],
    "sg:phone":"+1 713 473 4917",
    "sg:postcode":"77506",
    "sg:province":"TX",
    "sg:tags":[
        "contractor"
    ],
    "wof:name":"Jimenez Portable Welding",
    "wof:placetype":"venue"
},
  "geometry": {"coordinates":[-95.199178,29.70851],"type":"Point"}
}