{
  "type": "Feature",
  "properties": {
    "iso:country":"US",
    "sg:address":"11301 Lake June Rd",
    "sg:city":"Mesquite",
    "sg:classifiers":[
        {
            "category":"Retail",
            "subcategory":"Auto Repair",
            "type":"Services"
        }
    ],
    "sg:phone":"+1 972 289 2905",
    "sg:postcode":"75180",
    "sg:province":"TX",
    "sg:tags":[
        "general"
    ],
    "wof:name":"T DS Automotive & Towing",
    "wof:placetype":"venue"
},
  "geometry": {"coordinates":[-96.63255700000001,32.734167],"type":"Point"}
}