{
  "type": "Feature",
  "properties": {
    "iso:country":"US",
    "sg:address":"4514 Travis St",
    "sg:city":"Dallas",
    "sg:classifiers":[
        {
            "category":"Home & Garden",
            "subcategory":"Home Furnishings",
            "type":"Retail Goods"
        }
    ],
    "sg:phone":"+1 214 528 0700",
    "sg:postcode":"75205",
    "sg:province":"TX",
    "sg:tags":[
        "decor"
    ],
    "wof:name":"Home, James!",
    "wof:placetype":"venue"
},
  "geometry": {"coordinates":[-96.79103600000001,32.822312],"type":"Point"}
}