{
  "type": "Feature",
  "properties": {
    "iso:country":"US",
    "sg:address":"4601 Washington Ave",
    "sg:city":"Houston",
    "sg:classifiers":[
        {
            "category":"Autos & Motor Vehicles",
            "subcategory":"Automobile Sales",
            "type":"Retail Goods"
        }
    ],
    "sg:phone":"+1 713 869 1443",
    "sg:postcode":"77007",
    "sg:province":"TX",
    "sg:tags":[
        "car",
        "dealer"
    ],
    "wof:name":"Clark Motors",
    "wof:placetype":"venue"
},
  "geometry": {"coordinates":[-95.408344,29.770471],"type":"Point"}
}