{
  "type": "Feature",
  "properties": {
    "iso:country":"US",
    "sg:address":"1613 S Cooper St",
    "sg:city":"Arlington",
    "sg:classifiers":[
        {
            "category":"Wholesale",
            "subcategory":"Groceries",
            "type":"Manufacturing & Wholesale Goods"
        }
    ],
    "sg:phone":"+1 817 801 3327",
    "sg:postcode":"76010",
    "sg:province":"TX",
    "sg:tags":[
        "confectionery"
    ],
    "wof:name":"Prime Wholesale",
    "wof:placetype":"venue"
},
  "geometry": {"coordinates":[-97.11459600000001,32.717062],"type":"Point"}
}