{
  "type": "Feature",
  "properties": {
    "iso:country":"US",
    "sg:address":"811 Dallas St",
    "sg:city":"Houston",
    "sg:classifiers":[
        {
            "category":"Mining & Drilling",
            "type":"Manufacturing & Wholesale Goods"
        }
    ],
    "sg:phone":"+1 713 757 7883",
    "sg:postcode":"77002",
    "sg:province":"TX",
    "sg:tags":[
        "gas",
        "oil",
        "exploration",
        "production"
    ],
    "wof:name":"Trace Oil and Gas Inc",
    "wof:placetype":"venue"
},
  "geometry": {"coordinates":[-95.367007,29.756114],"type":"Point"}
}