{
  "type": "Feature",
  "properties": {
    "iso:country":"US",
    "sg:address":"15002 South Dr",
    "sg:city":"Channelview",
    "sg:classifiers":[
        {
            "category":"Building & Trades",
            "subcategory":"Plumbing",
            "type":"Services"
        }
    ],
    "sg:phone":"+1 281 452 1900",
    "sg:postcode":"77530",
    "sg:province":"TX",
    "wof:name":"First Choice Plumbing",
    "wof:placetype":"venue"
},
  "geometry": {"coordinates":[-95.149607,29.779329],"type":"Point"}
}