{
  "type": "Feature",
  "properties": {
    "iso:country":"US",
    "sg:address":"1903 Redlands St",
    "sg:city":"Austin",
    "sg:classifiers":[
        {
            "category":"Building & Trades",
            "subcategory":"Equipment Rental",
            "type":"Services"
        }
    ],
    "sg:phone":"+1 512 452 2930",
    "sg:postcode":"78757",
    "sg:province":"TX",
    "wof:name":"Curry Philip",
    "wof:placetype":"venue"
},
  "geometry": {"coordinates":[-97.734037,30.341446],"type":"Point"}
}