{
  "type": "Feature",
  "properties": {
    "iso:country":"US",
    "sg:address":"100 Bridlewood Ct",
    "sg:city":"Irving",
    "sg:classifiers":[
        {
            "category":"Professional",
            "subcategory":"Research",
            "type":"Services"
        }
    ],
    "sg:phone":"+1 972 506 9258",
    "sg:postcode":"75063",
    "sg:province":"TX",
    "sg:tags":[
        "nonphysical",
        "commercial"
    ],
    "wof:name":"Mary E Burkhardt",
    "wof:placetype":"venue"
},
  "geometry": {"coordinates":[-96.979089,32.909005],"type":"Point"}
}