{
  "type": "Feature",
  "properties": {
    "iso:country":"US",
    "sg:address":"14637 Pebble Bend Dr",
    "sg:city":"Houston",
    "sg:classifiers":[
        {
            "category":"Education",
            "subcategory":"School",
            "type":"Public Place"
        }
    ],
    "sg:phone":"+1 281 444 6192",
    "sg:postcode":"77068",
    "sg:province":"TX",
    "wof:name":"Christian Academy-Montessori",
    "wof:placetype":"venue"
},
  "geometry": {"coordinates":[-95.486994,29.995036],"type":"Point"}
}