{
  "type": "Feature",
  "properties": {
    "iso:country":"US",
    "sg:address":"125 Branchwood Trl",
    "sg:city":"Coppell",
    "sg:classifiers":[
        {
            "category":"Shopping",
            "subcategory":"Jewelry",
            "type":"Retail Goods"
        }
    ],
    "sg:phone":"+1 972 393 3320",
    "sg:postcode":"75019",
    "sg:province":"TX",
    "wof:name":"Unique Treasures",
    "wof:placetype":"venue"
},
  "geometry": {"coordinates":[-97.011909,32.970991],"type":"Point"}
}