{
  "type": "Feature",
  "properties": {
    "iso:country":"US",
    "sg:address":"260 W Richey Rd",
    "sg:city":"Houston",
    "sg:classifiers":[
        {
            "category":"Communications",
            "type":"Services"
        }
    ],
    "sg:phone":"+1 281 583 1556",
    "sg:postcode":"77090",
    "sg:province":"TX",
    "sg:tags":[
        "carrier"
    ],
    "wof:name":"Crown Communications",
    "wof:placetype":"venue"
},
  "geometry": {"coordinates":[-95.42903099999999,29.997399],"type":"Point"}
}