{
  "type": "Feature",
  "properties": {
    "iso:country":"US",
    "sg:address":"10720 E Miller Rd",
    "sg:city":"Dallas",
    "sg:classifiers":[
        {
            "category":"Home & Garden",
            "subcategory":"Household Appliances",
            "type":"Retail Goods"
        }
    ],
    "sg:phone":"+1 214 343 3722",
    "sg:postcode":"75238",
    "sg:province":"TX",
    "sg:tags":[
        "equipment"
    ],
    "wof:name":"Water Tech Services",
    "wof:placetype":"venue"
},
  "geometry": {"coordinates":[-96.698509,32.894505],"type":"Point"}
}