{
  "type": "Feature",
  "properties": {
    "iso:country":"US",
    "sg:address":"3334 State Hwy 111 N",
    "sg:city":"Edna",
    "sg:phone":"+1 361 782 7241",
    "sg:postcode":"77957",
    "sg:province":"TX",
    "sg:tags":[
        "farm",
        "rice",
        "beef",
        "feedlot",
        "cattle"
    ],
    "wof:name":"Hafernick Farms Inc",
    "wof:placetype":"venue"
},
  "geometry": {"coordinates":[-96.66651299999999,29.029558],"type":"Point"}
}