{
  "type": "Feature",
  "properties": {
    "iso:country":"US",
    "sg:address":"14212 Highway 3 Ste C",
    "sg:city":"Webster",
    "sg:classifiers":[
        {
            "category":"Professional",
            "subcategory":"Lawyer & Legal Services",
            "type":"Services"
        }
    ],
    "sg:phone":"+1 281 488 6271",
    "sg:postcode":"77598",
    "sg:province":"TX",
    "sg:tags":[
        "attorney",
        "practice"
    ],
    "wof:name":"Michael D Inlow",
    "wof:placetype":"venue"
},
  "geometry": {"coordinates":[-95.15456500000001,29.576734],"type":"Point"}
}