{
  "type": "Feature",
  "properties": {
    "iso:country":"US",
    "sg:address":"13719 Tosca Ln",
    "sg:city":"Houston",
    "sg:classifiers":[
        {
            "category":"Professional",
            "subcategory":"Management & Consulting",
            "type":"Services"
        }
    ],
    "sg:phone":"+1 713 467 7683",
    "sg:postcode":"77079",
    "sg:province":"TX",
    "wof:name":"Management Stratagies",
    "wof:placetype":"venue"
},
  "geometry": {"coordinates":[-95.584518,29.771045],"type":"Point"}
}