{
  "type": "Feature",
  "properties": {
    "iso:country":"US",
    "sg:address":"10212 N 12th St",
    "sg:city":"Mcallen",
    "sg:classifiers":[
        {
            "category":"Building & Trades",
            "subcategory":"Construction",
            "type":"Services"
        }
    ],
    "sg:phone":"+1 956 386 0755",
    "sg:postcode":"78504",
    "sg:province":"TX",
    "sg:tags":[
        "house"
    ],
    "wof:name":"DH Construction",
    "wof:placetype":"venue"
},
  "geometry": {"coordinates":[-98.215954,26.296662],"type":"Point"}
}