{
  "type": "Feature",
  "properties": {
    "iso:country":"US",
    "sg:address":"222 N Johnson St",
    "sg:city":"Alice",
    "sg:classifiers":[
        {
            "category":"Wholesale",
            "subcategory":"Machinery & Supplies",
            "type":"Manufacturing & Wholesale Goods"
        }
    ],
    "sg:phone":"+1 361 664 3621",
    "sg:postcode":"78332",
    "sg:province":"TX",
    "sg:tags":[
        "equipment",
        "industrial",
        "merchandise"
    ],
    "wof:name":"AOC",
    "wof:placetype":"venue"
},
  "geometry": {"coordinates":[-98.082622,27.752883],"type":"Point"}
}