{
  "type": "Feature",
  "properties": {
    "iso:country":"US",
    "sg:address":"8800 Lava Hill Road Suite 104",
    "sg:city":"Austin",
    "sg:classifiers":[
        {
            "category":"Retail",
            "subcategory":"Auto Repair",
            "type":"Services"
        }
    ],
    "sg:phone":"+1 512 243 5230",
    "sg:postcode":"78744",
    "sg:province":"TX",
    "wof:name":"Satisfied Automotive",
    "wof:placetype":"venue"
},
  "geometry": {"coordinates":[-97.697069,30.153125],"type":"Point"}
}