{
  "type": "Feature",
  "properties": {
    "iso:country":"US",
    "sg:address":"7403 Irvington Blvd",
    "sg:city":"Houston",
    "sg:classifiers":[
        {
            "category":"Retail",
            "subcategory":"Auto Repair",
            "type":"Services"
        }
    ],
    "sg:phone":"+1 713 692 2232",
    "sg:postcode":"77022",
    "sg:province":"TX",
    "sg:tags":[
        "automotive",
        "general"
    ],
    "wof:name":"Salazar Radiator Shop",
    "wof:placetype":"venue"
},
  "geometry": {"coordinates":[-95.361412,29.828885],"type":"Point"}
}