{
  "type": "Feature",
  "properties": {
    "iso:country":"US",
    "sg:address":"801 E Broadway St",
    "sg:city":"Sweetwater",
    "sg:classifiers":[
        {
            "category":"Shopping",
            "subcategory":"Stationery & Office Supplies",
            "type":"Retail Goods"
        }
    ],
    "sg:phone":"+1 325 235 3411",
    "sg:postcode":"79556",
    "sg:province":"TX",
    "wof:name":"Kinsey Printing & Office Supls",
    "wof:placetype":"venue"
},
  "geometry": {"coordinates":[-100.39981899999999,32.474179],"type":"Point"}
}