{
  "type": "Feature",
  "properties": {
    "iso:country":"US",
    "sg:address":"301 W 2nd St",
    "sg:city":"Austin",
    "sg:classifiers":[
        {
            "category":"Government",
            "subcategory":"Office",
            "type":"Public Place"
        }
    ],
    "sg:phone":"+1 512 974 2220",
    "sg:postcode":"78701",
    "sg:province":"TX",
    "sg:tags":[
        "village"
    ],
    "wof:name":"Austin Public Information Ofc",
    "wof:placetype":"venue"
},
  "geometry": {"coordinates":[-97.74767199999999,30.265286],"type":"Point"}
}