{
  "type": "Feature",
  "properties": {
    "iso:country":"US",
    "sg:address":"604 Pratt Rd",
    "sg:city":"Red Oak",
    "sg:classifiers":[
        {
            "category":"Banks & Credit Unions",
            "subcategory":"Investment Brokerage",
            "type":"Services"
        }
    ],
    "sg:phone":"+1 972 576 2250",
    "sg:postcode":"75154",
    "sg:province":"TX",
    "sg:tags":[
        "consultant",
        "planning",
        "financial"
    ],
    "wof:name":"Solomon Wealth Management",
    "wof:placetype":"venue"
},
  "geometry": {"coordinates":[-96.753986,32.512763],"type":"Point"}
}