{
  "type": "Feature",
  "properties": {
    "iso:country":"US",
    "sg:address":"428 Christopher Ave",
    "sg:city":"El Paso",
    "sg:classifiers":[
        {
            "category":"Professional",
            "type":"Services"
        }
    ],
    "sg:phone":"+1 915 584 5320",
    "sg:postcode":"79912",
    "sg:province":"TX",
    "wof:name":"Vino Nuevo Inc",
    "wof:placetype":"venue"
},
  "geometry": {"coordinates":[-106.540139,31.828399],"type":"Point"}
}