{
  "type": "Feature",
  "properties": {
    "iso:country":"US",
    "sg:address":"807 Saybrook",
    "sg:city":"Houston",
    "sg:classifiers":[
        {
            "category":"Real Estate",
            "subcategory":"Real Estate Operator",
            "type":"Services"
        }
    ],
    "sg:phone":"+1 713 464 6759",
    "sg:postcode":"77024",
    "sg:province":"TX",
    "sg:tags":[
        "building",
        "nonresidential"
    ],
    "wof:name":"Rio Guadalupe Properties LLC",
    "wof:placetype":"venue"
},
  "geometry": {"coordinates":[-95.51411400000001,29.779193],"type":"Point"}
}