{
  "type": "Feature",
  "properties": {
    "iso:country":"US",
    "sg:address":"202 E Washington St",
    "sg:city":"Rockwall",
    "sg:classifiers":[
        {
            "category":"Shopping",
            "subcategory":"Computers & Home Electronics",
            "type":"Retail Goods"
        }
    ],
    "sg:phone":"+1 972 772 2820",
    "sg:postcode":"75087",
    "sg:province":"TX",
    "sg:tags":[
        "equipment",
        "dealer"
    ],
    "wof:name":"Y 2 Pcs",
    "wof:placetype":"venue"
},
  "geometry": {"coordinates":[-96.45864899999999,32.930266],"type":"Point"}
}