{
  "type": "Feature",
  "properties": {
    "iso:country":"US",
    "sg:address":"14203 Luthe Rd",
    "sg:city":"Houston",
    "sg:classifiers":[
        {
            "category":"Home & Garden",
            "subcategory":"Home Furnishings",
            "type":"Retail Goods"
        },
        {
            "category":"Building & Trades",
            "subcategory":"Construction",
            "type":"Services"
        },
        {
            "category":"Manufacturing",
            "subcategory":"Building Materials",
            "type":"Manufacturing & Wholesale Goods"
        }
    ],
    "sg:phone":"+1 281 442 7767",
    "sg:postcode":"77039",
    "sg:province":"TX",
    "sg:tags":[
        "industrial",
        "cabinetmakers-commercial",
        "cabinet",
        "refacing",
        "resurfacing",
        "maker",
        "cabinets-refinishing",
        "kitchen"
    ],
    "wof:name":"Ameritek Design Inc",
    "wof:placetype":"venue"
},
  "geometry": {"coordinates":[-95.37201,29.922177],"type":"Point"}
}