{
  "type": "Feature",
  "properties": {
    "iso:country":"US",
    "sg:address":"4965 Martin Luther King Jr Blvd",
    "sg:city":"Houston",
    "sg:classifiers":[
        {
            "category":"Education",
            "subcategory":"College",
            "type":"Public Place"
        },
        {
            "category":"Personal",
            "subcategory":"Beauty Salon",
            "type":"Services"
        }
    ],
    "sg:phone":"+1 713 645 9060",
    "sg:postcode":"77021",
    "sg:province":"TX",
    "sg:tags":[
        "academic",
        "school",
        "cosmetology"
    ],
    "sg:website":"www.thefranklinbeautyschool.com",
    "wof:name":"Franklin Beauty Schools Inc",
    "wof:placetype":"venue"
},
  "geometry": {"coordinates":[-95.33515300000001,29.706972],"type":"Point"}
}