{
  "type": "Feature",
  "properties": {
    "iso:country":"US",
    "sg:address":"1088 Co Rd 770",
    "sg:city":"Natalia",
    "sg:classifiers":[
        {
            "category":"Professional",
            "type":"Services"
        }
    ],
    "sg:phone":"+1 830 663 5503",
    "sg:postcode":"78059",
    "sg:province":"TX",
    "wof:name":"Pate Professional Services",
    "wof:placetype":"venue"
},
  "geometry": {"coordinates":[-98.838531,29.148541],"type":"Point"}
}