{
  "type": "Feature",
  "properties": {
    "iso:country":"US",
    "sg:address":"1446 Halsey Way",
    "sg:city":"Carrollton",
    "sg:classifiers":[
        {
            "category":"Professional",
            "subcategory":"Accounting & Tax Preparation",
            "type":"Services"
        }
    ],
    "sg:phone":"+1 214 415 2967",
    "sg:postcode":"75007",
    "sg:province":"TX",
    "sg:tags":[
        "bookkeeping",
        "general"
    ],
    "sg:website":"www.uscorporateaccounting.com",
    "wof:name":"U S Corporate Accounting",
    "wof:placetype":"venue"
},
  "geometry": {"coordinates":[-96.922256,32.987836],"type":"Point"}
}