{
  "type": "Feature",
  "properties": {
    "iso:country":"US",
    "sg:address":"100 Main St",
    "sg:city":"Spring",
    "sg:classifiers":[
        {
            "category":"Fast Food",
            "type":"Food & Drink"
        },
        {
            "category":"Restaurant",
            "type":"Food & Drink"
        },
        {
            "category":"Food & Beverages",
            "subcategory":"Groceries & Convenience Stores",
            "type":"Retail Goods"
        }
    ],
    "sg:phone":"+1 281 350 3376",
    "sg:postcode":"77373",
    "sg:province":"TX",
    "sg:tags":[
        "shop",
        "style",
        "sandwich",
        "hamburger",
        "family",
        "dog",
        "hot",
        "health",
        "american"
    ],
    "sg:website":"http://www.puffabellys.com",
    "wof:name":"Puffabellys Restaurant",
    "wof:placetype":"venue"
},
  "geometry": {"coordinates":[-95.417671,30.07971],"type":"Point"}
}