{
  "type": "Feature",
  "properties": {
    "iso:country":"US",
    "sg:address":"363 W Cameron Ave",
    "sg:city":"Rockdale",
    "sg:classifiers":[
        {
            "category":"Retail",
            "subcategory":"Auto Repair",
            "type":"Services"
        }
    ],
    "sg:phone":"+1 512 446 5701",
    "sg:postcode":"76567",
    "sg:province":"TX",
    "sg:tags":[
        "muffler",
        "exhaust",
        "system"
    ],
    "wof:name":"Robert's Muffler Shop",
    "wof:placetype":"venue"
},
  "geometry": {"coordinates":[-97.00417299999999,30.65421],"type":"Point"}
}