{
  "type": "Feature",
  "properties": {
    "iso:country":"US",
    "sg:address":"1103 E Cotton St",
    "sg:city":"Longview",
    "sg:classifiers":[
        {
            "category":"Organizations",
            "subcategory":"Religious Organization",
            "type":"Services"
        }
    ],
    "sg:phone":"+1 903 234 9975",
    "sg:postcode":"75602",
    "sg:province":"TX",
    "wof:name":"True Believers Baptist Church",
    "wof:placetype":"venue"
},
  "geometry": {"coordinates":[-94.725882,32.492169],"type":"Point"}
}