{
  "type": "Feature",
  "properties": {
    "iso:country":"US",
    "sg:address":"7019 Wake Forrest Dr",
    "sg:city":"Dallas",
    "sg:classifiers":[
        {
            "category":"Professional",
            "type":"Services"
        }
    ],
    "sg:phone":"+1 214 342 9899",
    "sg:postcode":"75214",
    "sg:province":"TX",
    "wof:name":"Mary M Petty",
    "wof:placetype":"venue"
},
  "geometry": {"coordinates":[-96.739858,32.854386],"type":"Point"}
}