{
  "type": "Feature",
  "properties": {
    "iso:country":"US",
    "sg:address":"4016 Rocky Rd",
    "sg:city":"Dallas",
    "sg:classifiers":[
        {
            "category":"Retail",
            "subcategory":"Repair Shop",
            "type":"Services"
        }
    ],
    "sg:phone":"+1 972 243 7395",
    "sg:postcode":"75244",
    "sg:province":"TX",
    "wof:name":"Zamunda International P/L",
    "wof:placetype":"venue"
},
  "geometry": {"coordinates":[-96.839586,32.923387],"type":"Point"}
}