{
  "type": "Feature",
  "properties": {
    "iso:country":"US",
    "sg:address":"5727 SW Green Oaks Blvd",
    "sg:city":"Arlington",
    "sg:classifiers":[
        {
            "category":"Wholesale",
            "subcategory":"Machinery & Supplies",
            "type":"Manufacturing & Wholesale Goods"
        }
    ],
    "sg:phone":"+1 817 561 4505",
    "sg:postcode":"76017",
    "sg:province":"TX",
    "sg:tags":[
        "shop",
        "equipment",
        "establishment",
        "beauty"
    ],
    "wof:name":"Beauty Market",
    "wof:placetype":"venue"
},
  "geometry": {"coordinates":[-97.19305300000001,32.672875],"type":"Point"}
}