{
  "type": "Feature",
  "properties": {
    "iso:country":"US",
    "sg:address":"1111 Francitas Dr",
    "sg:city":"Houston",
    "sg:classifiers":[
        {
            "category":"Building & Trades",
            "subcategory":"Construction",
            "type":"Services"
        }
    ],
    "sg:phone":"+1 281 447 3067",
    "sg:postcode":"77038",
    "sg:province":"TX",
    "sg:tags":[
        "house"
    ],
    "wof:name":"R&A Boring & Welding Const",
    "wof:placetype":"venue"
},
  "geometry": {"coordinates":[-95.44108,29.916676],"type":"Point"}
}