{
  "type": "Feature",
  "properties": {
    "iso:country":"US",
    "sg:address":"1010 Staffordshire Rd",
    "sg:city":"Stafford",
    "sg:classifiers":[
        {
            "category":"Personal",
            "type":"Services"
        }
    ],
    "sg:phone":"+1 281 208 4445",
    "sg:postcode":"77477",
    "sg:province":"TX",
    "wof:name":"Massage Envy",
    "wof:placetype":"venue"
},
  "geometry": {"coordinates":[-95.550158,29.605853],"type":"Point"}
}