{
  "type": "Feature",
  "properties": {
    "iso:country":"US",
    "sg:address":"9403 Shields Dr",
    "sg:city":"San Antonio",
    "sg:classifiers":[
        {
            "category":"Manufacturing",
            "subcategory":"Printing",
            "type":"Manufacturing & Wholesale Goods"
        }
    ],
    "sg:phone":"+1 210 674 0269",
    "sg:postcode":"78245",
    "sg:province":"TX",
    "sg:tags":[
        "book"
    ],
    "wof:name":"Ken Syl Creative Consulta",
    "wof:placetype":"venue"
},
  "geometry": {"coordinates":[-98.668344,29.411987],"type":"Point"}
}