{
  "type": "Feature",
  "properties": {
    "iso:country":"US",
    "sg:address":"5414 Montrose Dr",
    "sg:city":"Dallas",
    "sg:classifiers":[
        {
            "category":"Travel",
            "subcategory":"Hotels & Motels",
            "type":"Entertainment"
        }
    ],
    "sg:phone":"+1 214 522 5599",
    "sg:postcode":"75209",
    "sg:province":"TX",
    "sg:tags":[
        "operation"
    ],
    "wof:name":"Brownstone Htl & Resorts Inc",
    "wof:placetype":"venue"
},
  "geometry": {"coordinates":[-96.81744999999999,32.83758],"type":"Point"}
}