{
  "type": "Feature",
  "properties": {
    "iso:country":"US",
    "sg:address":"4835 Camas",
    "sg:city":"San Antonio",
    "sg:classifiers":[
        {
            "category":"Professional",
            "subcategory":"Computer Services",
            "type":"Services"
        }
    ],
    "sg:phone":"+1 210 481 0297",
    "sg:postcode":"78247",
    "sg:province":"TX",
    "sg:tags":[
        "related"
    ],
    "wof:name":"Microtexs",
    "wof:placetype":"venue"
},
  "geometry": {"coordinates":[-98.40084899999999,29.58591],"type":"Point"}
}