{
  "type": "Feature",
  "properties": {
    "iso:country":"US",
    "sg:address":"203 W Randol Mill Rd",
    "sg:city":"Arlington",
    "sg:classifiers":[
        {
            "category":"Health Services",
            "subcategory":"Doctor",
            "type":"Services"
        }
    ],
    "sg:phone":"+1 817 275 7787",
    "sg:postcode":"76011",
    "sg:province":"TX",
    "sg:tags":[
        "clinic"
    ],
    "wof:name":"Tarrant Dialysis Of Arlington",
    "wof:placetype":"venue"
},
  "geometry": {"coordinates":[-97.108092,32.750137],"type":"Point"}
}