{
  "type": "Feature",
  "properties": {
    "iso:country":"US",
    "sg:address":"3911 S Eva Ave",
    "sg:city":"Monahans",
    "sg:classifiers":[
        {
            "category":"Mining & Drilling",
            "type":"Manufacturing & Wholesale Goods"
        }
    ],
    "sg:phone":"+1 432 943 6132",
    "sg:postcode":"79756",
    "sg:province":"TX",
    "sg:tags":[
        "oil",
        "well"
    ],
    "wof:name":"Buster's Well Svc Inc",
    "wof:placetype":"venue"
},
  "geometry": {"coordinates":[-102.893766,31.553723],"type":"Point"}
}