{
  "type": "Feature",
  "properties": {
    "iso:country":"US",
    "sg:address":"26547 Short St",
    "sg:city":"Splendora",
    "sg:classifiers":[
        {
            "category":"Building & Trades",
            "subcategory":"Construction",
            "type":"Services"
        }
    ],
    "sg:phone":"+1 281 689 1543",
    "sg:postcode":"77372",
    "sg:province":"TX",
    "sg:tags":[
        "restoration",
        "cleaning",
        "patio",
        "deck"
    ],
    "wof:name":"Rainbow Pressure Washing",
    "wof:placetype":"venue"
},
  "geometry": {"coordinates":[-95.14204599999999,30.196733],"type":"Point"}
}