{
  "type": "Feature",
  "properties": {
    "iso:country":"US",
    "sg:address":"151 Cypresswood Dr",
    "sg:city":"Spring",
    "sg:classifiers":[
        {
            "category":"Utilities",
            "subcategory":"Mobile Phone",
            "type":"Services"
        },
        {
            "category":"Shopping",
            "type":"Retail Goods"
        }
    ],
    "sg:phone":"+1 281 353 7373",
    "sg:postcode":"77388",
    "sg:province":"TX",
    "sg:tags":[
        "sales",
        "telephone",
        "cellular",
        "accessory"
    ],
    "wof:name":"Nextel Pronto Communications",
    "wof:placetype":"venue"
},
  "geometry": {"coordinates":[-95.433701,30.052759],"type":"Point"}
}