{
  "type": "Feature",
  "properties": {
    "iso:country":"US",
    "sg:address":"202 Green Ave",
    "sg:city":"Taft",
    "sg:classifiers":[
        {
            "category":"Health Services",
            "subcategory":"Health Practitioner",
            "type":"Services"
        }
    ],
    "sg:phone":"+1 361 528 3018",
    "sg:postcode":"78390",
    "sg:province":"TX",
    "wof:name":"Physical Therapy Clinic",
    "wof:placetype":"venue"
},
  "geometry": {"coordinates":[-97.394391,27.979339],"type":"Point"}
}