{
  "type": "Feature",
  "properties": {
    "iso:country":"US",
    "sg:address":"444 W Main St",
    "sg:city":"Uvalde",
    "sg:classifiers":[
        {
            "category":"Fast Food",
            "type":"Food & Drink"
        },
        {
            "category":"Restaurant",
            "type":"Food & Drink"
        }
    ],
    "sg:phone":"+1 830 278 3188",
    "sg:postcode":"78801",
    "sg:province":"TX",
    "sg:tags":[
        "shop",
        "hamburger",
        "dog",
        "hot",
        "fountain",
        "soda",
        "american"
    ],
    "sg:website":"http://www.awrestaurants.com",
    "wof:name":"A & W Restaurants",
    "wof:placetype":"venue"
},
  "geometry": {"coordinates":[-99.792734,29.207357],"type":"Point"}
}