{
  "type": "Feature",
  "properties": {
    "iso:country":"US",
    "sg:address":"1514 Live Oak St",
    "sg:city":"Commerce",
    "sg:classifiers":[
        {
            "category":"Shopping",
            "subcategory":"Clothing, Apparel, & Fashions",
            "type":"Retail Goods"
        }
    ],
    "sg:phone":"+1 903 886 7777",
    "sg:postcode":"75428",
    "sg:province":"TX",
    "wof:name":"Cathys Dress To A T",
    "wof:placetype":"venue"
},
  "geometry": {"coordinates":[-95.90293699999999,33.247322],"type":"Point"}
}