{
  "type": "Feature",
  "properties": {
    "iso:country":"US",
    "sg:address":"203 N Arroyo Blvd",
    "sg:city":"Los Fresnos",
    "sg:classifiers":[
        {
            "category":"Organizations",
            "subcategory":"Professional Association",
            "type":"Services"
        }
    ],
    "sg:phone":"+1 956 233 4488",
    "sg:postcode":"78566",
    "sg:province":"TX",
    "sg:tags":[
        "chambers",
        "business",
        "commerce"
    ],
    "wof:name":"Los Fresnos Chamber Commerce",
    "wof:placetype":"venue"
},
  "geometry": {"coordinates":[-97.476174,26.073459],"type":"Point"}
}