{
  "type": "Feature",
  "properties": {
    "iso:country":"US",
    "sg:address":"3515 22nd St",
    "sg:city":"Lubbock",
    "sg:classifiers":[
        {
            "category":"Health Services",
            "subcategory":"Doctor",
            "type":"Services"
        }
    ],
    "sg:phone":"+1 806 799 8830",
    "sg:postcode":"79410",
    "sg:province":"TX",
    "sg:tags":[
        "medical"
    ],
    "wof:name":"Shaw Gwen Counselor Lmsw",
    "wof:placetype":"venue"
},
  "geometry": {"coordinates":[-101.891842,33.574957],"type":"Point"}
}