{
  "type": "Feature",
  "properties": {
    "iso:country":"US",
    "sg:address":"1413 W 5th St",
    "sg:city":"Plainview",
    "sg:classifiers":[
        {
            "category":"Shopping",
            "subcategory":"Clothing, Apparel, & Fashions",
            "type":"Retail Goods"
        }
    ],
    "sg:phone":"+1 806 293 4318",
    "sg:postcode":"79072",
    "sg:province":"TX",
    "sg:tags":[
        "sale",
        "rental",
        "wear",
        "formal"
    ],
    "wof:name":"Casa Ilusion",
    "wof:placetype":"venue"
},
  "geometry": {"coordinates":[-101.72001400000001,34.184146],"type":"Point"}
}