{
  "type": "Feature",
  "properties": {
    "iso:country":"US",
    "sg:address":"353 Long Creek Rd",
    "sg:city":"Mesquite",
    "sg:classifiers":[
        {
            "category":"Building & Trades",
            "subcategory":"Construction",
            "type":"Services"
        }
    ],
    "sg:phone":"+1 972 226 4440",
    "sg:postcode":"75182",
    "sg:province":"TX",
    "sg:tags":[
        "sheet",
        "work",
        "metal",
        "contractor"
    ],
    "wof:name":"Beach Sheet Metal Company",
    "wof:placetype":"venue"
},
  "geometry": {"coordinates":[-96.565636,32.772567],"type":"Point"}
}