{
  "type": "Feature",
  "properties": {
    "iso:country":"US",
    "sg:address":"1302 N Graves St",
    "sg:city":"Mc Kinney",
    "sg:classifiers":[
        {
            "category":"Professional",
            "type":"Services"
        }
    ],
    "sg:phone":"+1 972 548 8061",
    "sg:postcode":"75069",
    "sg:province":"TX",
    "wof:name":"Bee Bags",
    "wof:placetype":"venue"
},
  "geometry": {"coordinates":[-96.628618,33.208301],"type":"Point"}
}