{
  "type": "Feature",
  "properties": {
    "iso:country":"US",
    "sg:address":"4408 S Clack St",
    "sg:city":"Abilene",
    "sg:classifiers":[
        {
            "category":"Building & Trades",
            "subcategory":"Cleaning & Sanitation",
            "type":"Services"
        },
        {
            "category":"Building & Trades",
            "subcategory":"Construction",
            "type":"Services"
        },
        {
            "category":"Manufacturing",
            "subcategory":"Building Materials",
            "type":"Manufacturing & Wholesale Goods"
        }
    ],
    "sg:phone":"+1 325 676 5511",
    "sg:postcode":"79606",
    "sg:province":"TX",
    "sg:tags":[
        "repair",
        "duct",
        "system",
        "specialty",
        "heating",
        "contractor",
        "fireplace",
        "air conditioning"
    ],
    "sg:website":"http://www.preunl.com",
    "wof:name":"Precision Unlimited, Inc.",
    "wof:placetype":"venue"
},
  "geometry": {"coordinates":[-99.757109,32.40012],"type":"Point"}
}