{
  "type": "Feature",
  "properties": {
    "iso:country":"US",
    "sg:address":"4125 Broadway Blvd",
    "sg:city":"Garland",
    "sg:classifiers":[
        {
            "category":"Government",
            "subcategory":"Police Station",
            "type":"Public Place"
        }
    ],
    "sg:phone":"+1 972 240 3011",
    "sg:postcode":"75043",
    "sg:province":"TX",
    "sg:tags":[
        "state"
    ],
    "wof:name":"Tx State Troopers Assoc",
    "wof:placetype":"venue"
},
  "geometry": {"coordinates":[-96.603988,32.863346],"type":"Point"}
}