{
  "type": "Feature",
  "properties": {
    "iso:country":"US",
    "sg:address":"480 Cherokee Ct S",
    "sg:city":"Keller",
    "sg:classifiers":[
        {
            "category":"Insurance",
            "subcategory":"Insurance Agent",
            "type":"Services"
        }
    ],
    "sg:phone":"+1 817 379 0599",
    "sg:postcode":"76248",
    "sg:province":"TX",
    "sg:tags":[
        "sales"
    ],
    "wof:name":"Stephens Dnald Wyne Lnda Jntte",
    "wof:placetype":"venue"
},
  "geometry": {"coordinates":[-97.24492499999999,32.930381],"type":"Point"}
}