{
  "type": "Feature",
  "properties": {
    "iso:country":"US",
    "sg:address":"203 Wolf Run Rd",
    "sg:city":"Argyle",
    "sg:classifiers":[
        {
            "category":"Professional",
            "type":"Services"
        }
    ],
    "sg:phone":"+1 817 430 4552",
    "sg:postcode":"76226",
    "sg:province":"TX",
    "wof:name":"Miller Waste Mills Inc",
    "wof:placetype":"venue"
},
  "geometry": {"coordinates":[-97.12585199999999,33.072503],"type":"Point"}
}