{
  "type": "Feature",
  "properties": {
    "iso:country":"US",
    "sg:address":"1210 28th St",
    "sg:city":"Hondo",
    "sg:classifiers":[
        {
            "category":"Farming",
            "subcategory":"Livestock Farm",
            "type":"Manufacturing & Wholesale Goods"
        }
    ],
    "sg:phone":"+1 830 426 3239",
    "sg:postcode":"78861",
    "sg:province":"TX",
    "sg:tags":[
        "beef",
        "feedlot",
        "cattle"
    ],
    "wof:name":"Martin Rothe",
    "wof:placetype":"venue"
},
  "geometry": {"coordinates":[-99.143241,29.339372],"type":"Point"}
}