{
  "type": "Feature",
  "properties": {
    "iso:country":"US",
    "sg:address":"3765 S Alameda St",
    "sg:city":"Corpus Christi",
    "sg:classifiers":[
        {
            "category":"Utilities",
            "subcategory":"Mobile Phone",
            "type":"Services"
        }
    ],
    "sg:phone":"+1 361 854 7797",
    "sg:postcode":"78411",
    "sg:province":"TX",
    "sg:tags":[
        "telephone",
        "cellular"
    ],
    "wof:name":"Cingular Wireless",
    "wof:placetype":"venue"
},
  "geometry": {"coordinates":[-97.381973,27.744769],"type":"Point"}
}