{
  "type": "Feature",
  "properties": {
    "iso:country":"US",
    "sg:address":"401 Wallis Dr",
    "sg:city":"Austin",
    "sg:classifiers":[
        {
            "category":"Professional",
            "type":"Services"
        }
    ],
    "sg:phone":"+1 512 328 0696",
    "sg:postcode":"78746",
    "sg:province":"TX",
    "wof:name":"Beth Obert",
    "wof:placetype":"venue"
},
  "geometry": {"coordinates":[-97.78496199999999,30.275654],"type":"Point"}
}