{
  "type": "Feature",
  "properties": {
    "iso:country":"US",
    "sg:address":"512 Mariners Dr",
    "sg:city":"Kemah",
    "sg:classifiers":[
        {
            "category":"Manufacturing",
            "subcategory":"Watercraft",
            "type":"Manufacturing & Wholesale Goods"
        }
    ],
    "sg:phone":"+1 281 538 2215",
    "sg:postcode":"77565",
    "sg:province":"TX",
    "wof:name":"Blue Water Restoration",
    "wof:placetype":"venue"
},
  "geometry": {"coordinates":[-95.04279,29.547808],"type":"Point"}
}