{
  "type": "Feature",
  "properties": {
    "iso:country":"US",
    "sg:address":"6955 Limerick Dr",
    "sg:city":"Beaumont",
    "sg:classifiers":[
        {
            "category":"Place Of Worship",
            "type":"Public Place"
        },
        {
            "category":"Place Of Worship",
            "subcategory":"Temple",
            "type":"Public Place"
        }
    ],
    "sg:phone":"+1 409 866 0806",
    "sg:postcode":"77706",
    "sg:province":"TX",
    "sg:tags":[
        "church"
    ],
    "wof:name":"Temple Of The Jedi Order",
    "wof:placetype":"venue"
},
  "geometry": {"coordinates":[-94.18621400000001,30.090211],"type":"Point"}
}