{
  "type": "Feature",
  "properties": {
    "iso:country":"US",
    "sg:address":"1019 W Oak St",
    "sg:city":"Palestine",
    "sg:classifiers":[
        {
            "category":"Autos & Motor Vehicles",
            "subcategory":"Motorcycle Sales",
            "type":"Retail Goods"
        }
    ],
    "sg:phone":"+1 903 723 3034",
    "sg:postcode":"75801",
    "sg:province":"TX",
    "sg:tags":[
        "scooter"
    ],
    "wof:name":"D & M Cycle Ctr",
    "wof:placetype":"venue"
},
  "geometry": {"coordinates":[-95.64197,31.760907],"type":"Point"}
}