{
  "type": "Feature",
  "properties": {
    "iso:country":"US",
    "sg:address":"4910 Oregon Trl",
    "sg:city":"Amarillo",
    "sg:classifiers":[
        {
            "category":"Personal",
            "subcategory":"Beauty Salon",
            "type":"Services"
        }
    ],
    "sg:phone":"+1 806 355 6869",
    "sg:postcode":"79109",
    "sg:province":"TX",
    "wof:name":"Bobbies Cut & Curl",
    "wof:placetype":"venue"
},
  "geometry": {"coordinates":[-101.887407,35.15396],"type":"Point"}
}