{
  "type": "Feature",
  "properties": {
    "iso:country":"US",
    "sg:address":"402 W Nueva St",
    "sg:city":"San Antonio",
    "sg:classifiers":[
        {
            "category":"Shopping",
            "subcategory":"Clothing, Apparel, & Fashions",
            "type":"Retail Goods"
        }
    ],
    "sg:phone":"+1 210 354 4000",
    "sg:postcode":"78207",
    "sg:province":"TX",
    "sg:tags":[
        "leather"
    ],
    "wof:name":"Gibson & Barnes",
    "wof:placetype":"venue"
},
  "geometry": {"coordinates":[-98.50041899999999,29.42342],"type":"Point"}
}