{
  "type": "Feature",
  "properties": {
    "iso:country":"US",
    "sg:address":"3814 Trailwood Dr",
    "sg:city":"Temple",
    "sg:classifiers":[
        {
            "category":"Arts & Performance",
            "subcategory":"Theater",
            "type":"Entertainment"
        }
    ],
    "sg:phone":"+1 254 774 8032",
    "sg:postcode":"76502",
    "sg:province":"TX",
    "sg:tags":[
        "group"
    ],
    "wof:name":"XCEL Entertainment LLC",
    "wof:placetype":"venue"
},
  "geometry": {"coordinates":[-97.396654,31.071326],"type":"Point"}
}