{
  "type": "Feature",
  "properties": {
    "iso:country":"US",
    "sg:address":"6702 Buchanan Loop Rd",
    "sg:city":"Texarkana",
    "sg:classifiers":[
        {
            "category":"Manufacturing",
            "subcategory":"Glass & Minerals",
            "type":"Manufacturing & Wholesale Goods"
        }
    ],
    "sg:phone":"+1 903 791 8181",
    "sg:postcode":"75501",
    "sg:province":"TX",
    "sg:tags":[
        "refractory"
    ],
    "wof:name":"RAB Inc",
    "wof:placetype":"venue"
},
  "geometry": {"coordinates":[-94.122651,33.359649],"type":"Point"}
}