{
  "type": "Feature",
  "properties": {
    "iso:country":"US",
    "sg:address":"329 Harbour Way",
    "sg:city":"Lakehills",
    "sg:classifiers":[
        {
            "category":"Organizations",
            "subcategory":"Religious Organization",
            "type":"Services"
        }
    ],
    "sg:phone":"+1 830 612 2454",
    "sg:postcode":"78063",
    "sg:province":"TX",
    "sg:tags":[
        "church"
    ],
    "wof:name":"Church United Methodist",
    "wof:placetype":"venue"
},
  "geometry": {"coordinates":[-98.934489,29.597338],"type":"Point"}
}