{
  "type": "Feature",
  "properties": {
    "iso:country":"US",
    "sg:address":"1801 Sunset Blvd",
    "sg:city":"Houston",
    "sg:classifiers":[
        {
            "category":"Banks & Credit Unions",
            "subcategory":"Financial Services",
            "type":"Services"
        }
    ],
    "sg:phone":"+1 713 523 3368",
    "sg:postcode":"77005",
    "sg:province":"TX",
    "sg:tags":[
        "company",
        "holding"
    ],
    "wof:name":"Lle Holding Pllc",
    "wof:placetype":"venue"
},
  "geometry": {"coordinates":[-95.405135,29.723035],"type":"Point"}
}