{
  "type": "Feature",
  "properties": {
    "iso:country":"US",
    "sg:address":"9715 Gross St",
    "sg:city":"Beaumont",
    "sg:classifiers":[
        {
            "category":"Recreation",
            "type":"Entertainment"
        }
    ],
    "sg:phone":"+1 409 673 4218",
    "sg:postcode":"77707",
    "sg:province":"TX",
    "wof:name":"Russells Racquet",
    "wof:placetype":"venue"
},
  "geometry": {"coordinates":[-94.207082,30.067975],"type":"Point"}
}