{
  "type": "Feature",
  "properties": {
    "iso:country":"US",
    "sg:address":"706 Memorial City Way",
    "sg:city":"Houston",
    "sg:classifiers":[
        {
            "category":"Shopping",
            "subcategory":"Clothing, Apparel, & Fashions",
            "type":"Retail Goods"
        }
    ],
    "sg:phone":"+1 713 461 8079",
    "sg:postcode":"77024",
    "sg:province":"TX",
    "wof:name":"Lerner New York",
    "wof:placetype":"venue"
},
  "geometry": {"coordinates":[-95.535944,29.781547],"type":"Point"}
}