{
  "type": "Feature",
  "properties": {
    "iso:country":"US",
    "sg:address":"109 Wicker Hill Rd",
    "sg:city":"Burleson",
    "sg:classifiers":[
        {
            "category":"Building & Trades",
            "subcategory":"Plumbing",
            "type":"Services"
        }
    ],
    "sg:phone":"+1 817 426 4673",
    "sg:postcode":"76028",
    "sg:province":"TX",
    "sg:tags":[
        "conditioning",
        "air",
        "system",
        "contractor"
    ],
    "wof:name":"A Team Hope Co",
    "wof:placetype":"venue"
},
  "geometry": {"coordinates":[-97.365538,32.506318],"type":"Point"}
}