{
  "type": "Feature",
  "properties": {
    "iso:country":"US",
    "sg:address":"13 Fairway Oaks Blvd",
    "sg:city":"Abilene",
    "sg:classifiers":[
        {
            "category":"Professional",
            "subcategory":"Lawyer & Legal Services",
            "type":"Services"
        }
    ],
    "sg:phone":"+1 325 698 4230",
    "sg:postcode":"79606",
    "sg:province":"TX",
    "sg:tags":[
        "attorney",
        "practice"
    ],
    "wof:name":"Watson, Michael B, Atty At Law",
    "wof:placetype":"venue"
},
  "geometry": {"coordinates":[-99.75962800000001,32.381439],"type":"Point"}
}