{
  "type": "Feature",
  "properties": {
    "iso:country":"US",
    "sg:address":"6218 Pebble Beach Dr",
    "sg:city":"Corpus Christi",
    "sg:classifiers":[
        {
            "category":"Retail",
            "subcategory":"Portrait Studio",
            "type":"Services"
        }
    ],
    "sg:phone":"+1 361 808 7306",
    "sg:postcode":"78413",
    "sg:province":"TX",
    "sg:tags":[
        "photo"
    ],
    "wof:name":"Do Hope Shop",
    "wof:placetype":"venue"
},
  "geometry": {"coordinates":[-97.399259,27.697285],"type":"Point"}
}