{
  "type": "Feature",
  "properties": {
    "iso:country":"US",
    "sg:address":"3423 N State Line Ave",
    "sg:city":"Texarkana",
    "sg:classifiers":[
        {
            "category":"Wholesale",
            "subcategory":"Office Equipment",
            "type":"Manufacturing & Wholesale Goods"
        }
    ],
    "sg:phone":"+1 903 792 7368",
    "sg:postcode":"75503",
    "sg:province":"TX",
    "sg:tags":[
        "machine",
        "duplicating",
        "copying"
    ],
    "sg:website":"www.kbmnet.com",
    "wof:name":"Knowles Business Machines Inc",
    "wof:placetype":"venue"
},
  "geometry": {"coordinates":[-94.043198,33.450548],"type":"Point"}
}