{
  "type": "Feature",
  "properties": {
    "iso:country":"US",
    "sg:address":"16315 Lookout Rd",
    "sg:city":"Schertz",
    "sg:classifiers":[
        {
            "category":"Wholesale",
            "subcategory":"Groceries",
            "type":"Manufacturing & Wholesale Goods"
        }
    ],
    "sg:phone":"+1 210 651 1981",
    "sg:postcode":"78154",
    "sg:province":"TX",
    "sg:tags":[
        "food",
        "broker"
    ],
    "wof:name":"Comlat Inc",
    "wof:placetype":"venue"
},
  "geometry": {"coordinates":[-98.294994,29.59889],"type":"Point"}
}