{
  "type": "Feature",
  "properties": {
    "iso:country":"US",
    "sg:address":"1614 3rd St",
    "sg:city":"Brownwood",
    "sg:classifiers":[
        {
            "category":"Building & Trades",
            "subcategory":"Plumbing",
            "type":"Services"
        }
    ],
    "sg:phone":"+1 325 643 2155",
    "sg:postcode":"76801",
    "sg:province":"TX",
    "sg:tags":[
        "contractor"
    ],
    "wof:name":"Carroll Refrigeration",
    "wof:placetype":"venue"
},
  "geometry": {"coordinates":[-98.980234,31.704615],"type":"Point"}
}