{
  "type": "Feature",
  "properties": {
    "iso:country":"US",
    "sg:address":"10620 FM 41",
    "sg:city":"Wolfforth",
    "sg:classifiers":[
        {
            "category":"Recreation",
            "type":"Entertainment"
        }
    ],
    "sg:phone":"+1 806 863 2607",
    "sg:postcode":"79382",
    "sg:province":"TX",
    "sg:tags":[
        "stable"
    ],
    "wof:name":"R & B Stables",
    "wof:placetype":"venue"
},
  "geometry": {"coordinates":[-102.049075,33.413683],"type":"Point"}
}