{
  "type": "Feature",
  "properties": {
    "iso:country":"US",
    "sg:address":"502 Drummond Rd",
    "sg:city":"Abilene",
    "sg:classifiers":[
        {
            "category":"Autos & Motor Vehicles",
            "subcategory":"Fuel & Gas Station",
            "type":"Retail Goods"
        }
    ],
    "sg:phone":"+1 325 690 0452",
    "sg:postcode":"79606",
    "sg:province":"TX",
    "sg:tags":[
        "oil"
    ],
    "wof:name":"Chevron Pipe Line Co",
    "wof:placetype":"venue"
},
  "geometry": {"coordinates":[-99.871067,32.393341],"type":"Point"}
}