{
  "type": "Feature",
  "properties": {
    "iso:country":"US",
    "sg:address":"8817 Prairie View Dr",
    "sg:city":"Houston",
    "sg:classifiers":[
        {
            "category":"Organizations",
            "subcategory":"Religious Organization",
            "type":"Services"
        }
    ],
    "sg:phone":"+1 281 447 1284",
    "sg:postcode":"77088",
    "sg:province":"TX",
    "wof:name":"True Vine Holiness",
    "wof:placetype":"venue"
},
  "geometry": {"coordinates":[-95.42832300000001,29.881982],"type":"Point"}
}