{
  "type": "Feature",
  "properties": {
    "iso:country":"US",
    "sg:address":"5400 Westheimer Ct",
    "sg:city":"Houston",
    "sg:classifiers":[
        {
            "category":"Building & Trades",
            "subcategory":"Construction",
            "type":"Services"
        }
    ],
    "sg:phone":"+1 713 627 5400",
    "sg:postcode":"77056",
    "sg:province":"TX",
    "sg:tags":[
        "pipe",
        "line"
    ],
    "sg:website":"http://www.defieldservices.com",
    "wof:name":"Panhandle Field Services Co",
    "wof:placetype":"venue"
},
  "geometry": {"coordinates":[-95.47068,29.74016],"type":"Point"}
}