{
  "type": "Feature",
  "properties": {
    "iso:country":"US",
    "sg:address":"120 Windmill Dr",
    "sg:city":"Floresville",
    "sg:classifiers":[
        {
            "category":"Professional",
            "subcategory":"Detective & Security Services",
            "type":"Services"
        }
    ],
    "sg:phone":"+1 830 393 4183",
    "sg:postcode":"78114",
    "sg:province":"TX",
    "sg:tags":[
        "information",
        "bureau"
    ],
    "wof:name":"Aquasource Services & Technolo",
    "wof:placetype":"venue"
},
  "geometry": {"coordinates":[-98.241147,29.23804],"type":"Point"}
}