{
  "type": "Feature",
  "properties": {
    "iso:country":"US",
    "sg:address":"18111 Preston Rd",
    "sg:city":"Dallas",
    "sg:classifiers":[
        {
            "category":"Communications",
            "type":"Services"
        }
    ],
    "sg:phone":"+1 972 588 3500",
    "sg:postcode":"75252",
    "sg:province":"TX",
    "wof:name":"Cypress Communications",
    "wof:placetype":"venue"
},
  "geometry": {"coordinates":[-96.79692799999999,32.999963],"type":"Point"}
}