{
  "type": "Feature",
  "properties": {
    "iso:country":"US",
    "sg:address":"203 Link Rd",
    "sg:city":"League City",
    "sg:classifiers":[
        {
            "category":"Wholesale",
            "subcategory":"Electrical",
            "type":"Manufacturing & Wholesale Goods"
        }
    ],
    "sg:phone":"+1 281 338 4417",
    "sg:postcode":"77573",
    "sg:province":"TX",
    "sg:tags":[
        "fire",
        "alarm",
        "system"
    ],
    "wof:name":"D & N Svc Inc",
    "wof:placetype":"venue"
},
  "geometry": {"coordinates":[-95.083443,29.491258],"type":"Point"}
}