{
  "type": "Feature",
  "properties": {
    "iso:country":"US",
    "sg:address":"512 Shadyway Dr",
    "sg:city":"Dallas",
    "sg:classifiers":[
        {
            "category":"Professional",
            "subcategory":"Management & Consulting",
            "type":"Services"
        }
    ],
    "sg:phone":"+1 972 224 3282",
    "sg:postcode":"75232",
    "sg:province":"TX",
    "sg:tags":[
        "business"
    ],
    "wof:name":"Booshway Enterprises Inc",
    "wof:placetype":"venue"
},
  "geometry": {"coordinates":[-96.831361,32.651708],"type":"Point"}
}