{
  "type": "Feature",
  "properties": {
    "iso:country":"US",
    "sg:address":"3116 Hopi Ct",
    "sg:city":"Plano",
    "sg:classifiers":[
        {
            "category":"Building & Trades",
            "subcategory":"Construction",
            "type":"Services"
        }
    ],
    "sg:phone":"+1 972 422 7566",
    "sg:postcode":"75074",
    "sg:province":"TX",
    "sg:tags":[
        "contractor"
    ],
    "wof:name":"Chavez Construction Co",
    "wof:placetype":"venue"
},
  "geometry": {"coordinates":[-96.68597200000001,33.039534],"type":"Point"}
}