{
  "type": "Feature",
  "properties": {
    "iso:country":"US",
    "sg:address":"21235 Waymare Ln",
    "sg:city":"Spring",
    "sg:classifiers":[
        {
            "category":"Shopping",
            "subcategory":"Jewelry",
            "type":"Retail Goods"
        }
    ],
    "sg:phone":"+1 281 353 8127",
    "sg:postcode":"77388",
    "sg:province":"TX",
    "wof:name":"Old World Arts & Jewelry",
    "wof:placetype":"venue"
},
  "geometry": {"coordinates":[-95.492484,30.061484],"type":"Point"}
}