{
  "type": "Feature",
  "properties": {
    "iso:country":"US",
    "sg:address":"7829 US Hwy 281",
    "sg:city":"Burnet",
    "sg:classifiers":[
        {
            "category":"Manufacturing",
            "subcategory":"Glass & Minerals",
            "type":"Manufacturing & Wholesale Goods"
        }
    ],
    "sg:phone":"+1 512 756 8668",
    "sg:postcode":"78611",
    "sg:province":"TX",
    "sg:tags":[
        "lime"
    ],
    "sg:website":"www.chemicallime.com",
    "wof:name":"Chemical Lime Co",
    "wof:placetype":"venue"
},
  "geometry": {"coordinates":[-98.233625,30.777149],"type":"Point"}
}