{
  "type": "Feature",
  "properties": {
    "iso:country":"US",
    "sg:address":"817 W Embercrest Dr",
    "sg:city":"Arlington",
    "sg:classifiers":[
        {
            "category":"Professional",
            "subcategory":"Business Services",
            "type":"Services"
        }
    ],
    "sg:phone":"+1 817 419 0997",
    "sg:postcode":"76017",
    "sg:province":"TX",
    "wof:name":"Bullfrog Express Ltd",
    "wof:placetype":"venue"
},
  "geometry": {"coordinates":[-97.119576,32.668131],"type":"Point"}
}