{
  "type": "Feature",
  "properties": {
    "iso:country":"US",
    "sg:address":"2326 Goat Creek Run",
    "sg:city":"San Antonio",
    "sg:classifiers":[
        {
            "category":"Wholesale",
            "subcategory":"Stationery",
            "type":"Manufacturing & Wholesale Goods"
        }
    ],
    "sg:phone":"+1 210 481 3653",
    "sg:postcode":"78232",
    "sg:province":"TX",
    "sg:tags":[
        "product",
        "paper"
    ],
    "wof:name":"America's Best Paper",
    "wof:placetype":"venue"
},
  "geometry": {"coordinates":[-98.454493,29.58633],"type":"Point"}
}