{
  "type": "Feature",
  "properties": {
    "iso:country":"US",
    "sg:address":"7130 Pittswood Ln",
    "sg:city":"Houston",
    "sg:classifiers":[
        {
            "category":"Social Services",
            "subcategory":"Child Care",
            "type":"Services"
        }
    ],
    "sg:phone":"+1 281 987 1664",
    "sg:postcode":"77016",
    "sg:province":"TX",
    "wof:name":"Kiss and Play Child Dev Ctr",
    "wof:placetype":"venue"
},
  "geometry": {"coordinates":[-95.281283,29.879017],"type":"Point"}
}