{
  "type": "Feature",
  "properties": {
    "iso:country":"US",
    "sg:address":"3140 Irving Blvd",
    "sg:city":"Dallas",
    "sg:classifiers":[
        {
            "category":"Autos & Motor Vehicles",
            "subcategory":"Automobile Sales",
            "type":"Retail Goods"
        }
    ],
    "sg:phone":"+1 214 951 0122",
    "sg:postcode":"75247",
    "sg:province":"TX",
    "sg:tags":[
        "used"
    ],
    "wof:name":"Ats",
    "wof:placetype":"venue"
},
  "geometry": {"coordinates":[-96.864205,32.807768],"type":"Point"}
}