{
  "type": "Feature",
  "properties": {
    "iso:country":"US",
    "sg:address":"4801 Arbor Glen Dr",
    "sg:city":"Mckinney",
    "sg:classifiers":[
        {
            "category":"Insurance",
            "subcategory":"Insurance Agent",
            "type":"Services"
        }
    ],
    "sg:phone":"+1 972 562 3457",
    "sg:postcode":"75070",
    "sg:province":"TX",
    "wof:name":"Arag Group",
    "wof:placetype":"venue"
},
  "geometry": {"coordinates":[-96.681712,33.175577],"type":"Point"}
}