{
  "type": "Feature",
  "properties": {
    "iso:country":"US",
    "sg:address":"19206 Birdsong E",
    "sg:city":"San Antonio",
    "sg:classifiers":[
        {
            "category":"Social Services",
            "type":"Services"
        }
    ],
    "sg:phone":"+1 210 262 7854",
    "sg:postcode":"78258",
    "sg:province":"TX",
    "wof:name":"Shared Vision Inc",
    "wof:placetype":"venue"
},
  "geometry": {"coordinates":[-98.495228,29.623321],"type":"Point"}
}