{
  "type": "Feature",
  "properties": {
    "iso:country":"US",
    "sg:address":"4825 50th St",
    "sg:city":"Lubbock",
    "sg:classifiers":[
        {
            "category":"Health Services",
            "subcategory":"Chiropractor",
            "type":"Services"
        }
    ],
    "sg:phone":"+1 806 785 7246",
    "sg:postcode":"79414",
    "sg:province":"TX",
    "wof:name":"All Family Chiropractic",
    "wof:placetype":"venue"
},
  "geometry": {"coordinates":[-101.917631,33.548678],"type":"Point"}
}