{
  "type": "Feature",
  "properties": {
    "iso:country":"US",
    "sg:address":"1860 Dolphin Dr",
    "sg:city":"Seabrook",
    "sg:classifiers":[
        {
            "category":"Building & Trades",
            "subcategory":"Landscaping Services",
            "type":"Services"
        }
    ],
    "sg:phone":"+1 281 474 3880",
    "sg:postcode":"77586",
    "sg:province":"TX",
    "wof:name":"Shade and Shrub Landscaping",
    "wof:placetype":"venue"
},
  "geometry": {"coordinates":[-95.022789,29.569544],"type":"Point"}
}