{
  "type": "Feature",
  "properties": {
    "iso:country":"US",
    "sg:address":"6269 Co Rd 437",
    "sg:city":"Princeton",
    "sg:classifiers":[
        {
            "category":"Travel",
            "subcategory":"Campground",
            "type":"Entertainment"
        }
    ],
    "sg:phone":"+1 972 736 2635",
    "sg:postcode":"75407",
    "sg:province":"TX",
    "sg:tags":[
        "trailer"
    ],
    "wof:name":"Lafons R V Park",
    "wof:placetype":"venue"
},
  "geometry": {"coordinates":[-96.515396,33.086405],"type":"Point"}
}