{
  "type": "Feature",
  "properties": {
    "iso:country":"US",
    "sg:address":"3302 W Front St",
    "sg:city":"Midland",
    "sg:classifiers":[
        {
            "category":"Travel",
            "subcategory":"Hotels & Motels",
            "type":"Entertainment"
        }
    ],
    "sg:phone":"+1 432 689 6886",
    "sg:postcode":"79701",
    "sg:province":"TX",
    "wof:name":"Executive Lodge",
    "wof:placetype":"venue"
},
  "geometry": {"coordinates":[-102.10849,31.98083],"type":"Point"}
}