{
  "type": "Feature",
  "properties": {
    "iso:country":"US",
    "sg:address":"5508 Community Dr",
    "sg:city":"Houston",
    "sg:classifiers":[
        {
            "category":"Professional",
            "subcategory":"Detective & Security Services",
            "type":"Services"
        }
    ],
    "sg:phone":"+1 713 622 6313",
    "sg:postcode":"77005",
    "sg:province":"TX",
    "sg:tags":[
        "car"
    ],
    "wof:name":"All Around Entertainers",
    "wof:placetype":"venue"
},
  "geometry": {"coordinates":[-95.44722,29.722964],"type":"Point"}
}