{
  "type": "Feature",
  "properties": {
    "iso:country":"US",
    "sg:address":"12113 Garland Rd",
    "sg:city":"Dallas",
    "sg:classifiers":[
        {
            "category":"Retail",
            "subcategory":"Auto Repair",
            "type":"Services"
        }
    ],
    "sg:phone":"+1 214 321 6655",
    "sg:postcode":"75218",
    "sg:province":"TX",
    "wof:name":"Ramco Transmissions",
    "wof:placetype":"venue"
},
  "geometry": {"coordinates":[-96.672558,32.861834],"type":"Point"}
}