{
  "type": "Feature",
  "properties": {
    "iso:country":"US",
    "sg:address":"216 Dandelion Ln",
    "sg:city":"San Antonio",
    "sg:classifiers":[
        {
            "category":"Building & Trades",
            "subcategory":"Construction",
            "type":"Services"
        }
    ],
    "sg:phone":"+1 210 340 4906",
    "sg:postcode":"78213",
    "sg:province":"TX",
    "sg:tags":[
        "house"
    ],
    "wof:name":"Ackerman Builders",
    "wof:placetype":"venue"
},
  "geometry": {"coordinates":[-98.52241600000001,29.51482],"type":"Point"}
}