{
  "type": "Feature",
  "properties": {
    "iso:country":"US",
    "sg:address":"2021 Old Mill Run",
    "sg:city":"Garland",
    "sg:classifiers":[
        {
            "category":"Recreation",
            "type":"Entertainment"
        }
    ],
    "sg:phone":"+1 972 414 3281",
    "sg:postcode":"75044",
    "sg:province":"TX",
    "sg:tags":[
        "hall",
        "auditorium"
    ],
    "wof:name":"Harari Community Ctr",
    "wof:placetype":"venue"
},
  "geometry": {"coordinates":[-96.651821,32.932765],"type":"Point"}
}