{
  "type": "Feature",
  "properties": {
    "iso:country":"US",
    "sg:address":"14313 Main St",
    "sg:city":"Houston",
    "sg:classifiers":[
        {
            "category":"Building & Trades",
            "subcategory":"Plumbing",
            "type":"Services"
        }
    ],
    "sg:phone":"+1 713 729 9775",
    "sg:postcode":"77035",
    "sg:province":"TX",
    "sg:tags":[
        "conditioning",
        "air",
        "system",
        "contractor"
    ],
    "wof:name":"AAS America AC Systems",
    "wof:placetype":"venue"
},
  "geometry": {"coordinates":[-95.50000300000001,29.633577],"type":"Point"}
}