{
  "type": "Feature",
  "properties": {
    "iso:country":"US",
    "sg:address":"2307 McCullough Ave",
    "sg:city":"San Antonio",
    "sg:classifiers":[
        {
            "category":"Travel",
            "subcategory":"Hotels & Motels",
            "type":"Entertainment"
        }
    ],
    "sg:phone":"+1 210 737 2786",
    "sg:postcode":"78212",
    "sg:province":"TX",
    "sg:tags":[
        "breakfast",
        "accommodation",
        "bed"
    ],
    "wof:name":"Christmas House Bed & Brkfst",
    "wof:placetype":"venue"
},
  "geometry": {"coordinates":[-98.491877,29.451475],"type":"Point"}
}