{
  "type": "Feature",
  "properties": {
    "iso:country":"US",
    "sg:address":"2000 W Oak St",
    "sg:city":"Palestine",
    "sg:classifiers":[
        {
            "category":"Retail",
            "subcategory":"Repair Shop",
            "type":"Services"
        }
    ],
    "sg:phone":"+1 903 729 3313",
    "sg:postcode":"75801",
    "sg:province":"TX",
    "wof:name":"Westwood Key & Lock",
    "wof:placetype":"venue"
},
  "geometry": {"coordinates":[-95.65002699999999,31.750093],"type":"Point"}
}