{
  "type": "Feature",
  "properties": {
    "iso:country":"US",
    "sg:address":"2905 Crystal Springs St",
    "sg:city":"Bedford",
    "sg:classifiers":[
        {
            "category":"Retail",
            "subcategory":"Auto Rental",
            "type":"Services"
        }
    ],
    "sg:phone":"+1 817 318 7867",
    "sg:postcode":"76021",
    "sg:province":"TX",
    "sg:tags":[
        "truck"
    ],
    "wof:name":"Stor-A-Away",
    "wof:placetype":"venue"
},
  "geometry": {"coordinates":[-97.112495,32.851833],"type":"Point"}
}