{
  "type": "Feature",
  "properties": {
    "iso:country":"US",
    "sg:address":"7009 Guadalupe St",
    "sg:city":"Austin",
    "sg:classifiers":[
        {
            "category":"Communications",
            "subcategory":"Film & Video Production",
            "type":"Services"
        }
    ],
    "sg:phone":"+1 512 380 9906",
    "sg:postcode":"78752",
    "sg:province":"TX",
    "sg:tags":[
        "motion"
    ],
    "wof:name":"Weatherrock Productions LLC",
    "wof:placetype":"venue"
},
  "geometry": {"coordinates":[-97.715271,30.336433],"type":"Point"}
}