{
  "type": "Feature",
  "properties": {
    "iso:country":"US",
    "sg:address":"900 Harvey St",
    "sg:city":"Mcallen",
    "sg:classifiers":[
        {
            "category":"Insurance",
            "subcategory":"Insurance Agent",
            "type":"Services"
        },
        {
            "category":"Insurance",
            "subcategory":"Hazard Insurance",
            "type":"Services"
        },
        {
            "category":"Insurance",
            "subcategory":"Title Insurance",
            "type":"Services"
        },
        {
            "category":"Insurance",
            "subcategory":"Life Insurance",
            "type":"Services"
        }
    ],
    "sg:phone":"+1 210 682 3456",
    "sg:postcode":"78501",
    "sg:province":"TX",
    "sg:tags":[
        "business",
        "auto",
        "commercial",
        "homeowner",
        "motorcycle",
        "renter"
    ],
    "wof:name":"Allstate Insurance Company - Ruben Elizondo",
    "wof:placetype":"venue"
},
  "geometry": {"coordinates":[-98.224915,26.228491],"type":"Point"}
}