{
  "type": "Feature",
  "properties": {
    "iso:country":"US",
    "sg:address":"8020 Fairbanks N Houston Rd",
    "sg:city":"Houston",
    "sg:classifiers":[
        {
            "category":"Food & Beverages",
            "subcategory":"Meat & Fish",
            "type":"Retail Goods"
        }
    ],
    "sg:phone":"+1 713 937 0818",
    "sg:postcode":"77064",
    "sg:province":"TX",
    "sg:tags":[
        "shop"
    ],
    "wof:name":"La Esperanza Meat Market",
    "wof:placetype":"venue"
},
  "geometry": {"coordinates":[-95.524641,29.89715],"type":"Point"}
}