{
  "type": "Feature",
  "properties": {
    "iso:country":"US",
    "sg:address":"1619 S Flores St",
    "sg:city":"San Antonio",
    "sg:classifiers":[
        {
            "category":"Organizations",
            "subcategory":"Religious Organization",
            "type":"Services"
        }
    ],
    "sg:phone":"+1 210 225 6877",
    "sg:postcode":"78204",
    "sg:province":"TX",
    "sg:tags":[
        "church"
    ],
    "wof:name":"St Henry's Catholic Church",
    "wof:placetype":"venue"
},
  "geometry": {"coordinates":[-98.50163999999999,29.40812],"type":"Point"}
}