{
  "type": "Feature",
  "properties": {
    "iso:country":"US",
    "sg:address":"14438 Robert I Walker Blvd",
    "sg:city":"Austin",
    "sg:classifiers":[
        {
            "category":"Restaurant",
            "type":"Food & Drink"
        }
    ],
    "sg:phone":"+1 512 506 1999",
    "sg:postcode":"78728",
    "sg:province":"TX",
    "sg:tags":[
        "pizza"
    ],
    "wof:name":"Red Brick Pizza",
    "wof:placetype":"venue"
},
  "geometry": {"coordinates":[-97.68521,30.43979],"type":"Point"}
}