{
  "type": "Feature",
  "properties": {
    "iso:country":"US",
    "sg:address":"9528 Brentgate Dr",
    "sg:city":"Dallas",
    "sg:classifiers":[
        {
            "category":"Building & Trades",
            "subcategory":"Landscaping Services",
            "type":"Services"
        }
    ],
    "sg:phone":"+1 214 348 7227",
    "sg:postcode":"75238",
    "sg:province":"TX",
    "wof:name":"Daughertys Lawn Service",
    "wof:placetype":"venue"
},
  "geometry": {"coordinates":[-96.726878,32.8802],"type":"Point"}
}