{
  "type": "Feature",
  "properties": {
    "iso:country":"US",
    "sg:address":"8802 Manus St",
    "sg:city":"Houston",
    "sg:classifiers":[
        {
            "category":"Building & Trades",
            "subcategory":"Construction",
            "type":"Services"
        }
    ],
    "sg:phone":"+1 713 699 8239",
    "sg:postcode":"77093",
    "sg:province":"TX",
    "sg:tags":[
        "house"
    ],
    "wof:name":"Tu Johnson Construction Co",
    "wof:placetype":"venue"
},
  "geometry": {"coordinates":[-95.336938,29.840617],"type":"Point"}
}