{
  "type": "Feature",
  "properties": {
    "iso:country":"US",
    "sg:address":"8989 Westheimer Rd",
    "sg:city":"Houston",
    "sg:classifiers":[
        {
            "category":"Banks & Credit Unions",
            "subcategory":"Bank",
            "type":"Services"
        }
    ],
    "sg:phone":"+1 713 787 6800",
    "sg:postcode":"77063",
    "sg:province":"TX",
    "sg:tags":[
        "broker",
        "mortgage"
    ],
    "wof:name":"Kays Financial Services",
    "wof:placetype":"venue"
},
  "geometry": {"coordinates":[-95.522345,29.737245],"type":"Point"}
}