{
  "type": "Feature",
  "properties": {
    "iso:country":"US",
    "sg:address":"2649 Main St",
    "sg:city":"Dallas",
    "sg:classifiers":[
        {
            "category":"Manufacturing",
            "subcategory":"Motor Vehicles & Parts",
            "type":"Manufacturing & Wholesale Goods"
        }
    ],
    "sg:phone":"+1 214 742 2568",
    "sg:postcode":"75226",
    "sg:province":"TX",
    "sg:tags":[
        "automobile",
        "radiator"
    ],
    "sg:website":"www.texasautorad.com",
    "wof:name":"Click's Radiator Svc",
    "wof:placetype":"venue"
},
  "geometry": {"coordinates":[-96.78505,32.783533],"type":"Point"}
}