{
  "type": "Feature",
  "properties": {
    "iso:country":"US",
    "sg:address":"104 NW 2nd St",
    "sg:city":"Smithville",
    "sg:classifiers":[
        {
            "category":"Insurance",
            "subcategory":"Hazard Insurance",
            "type":"Services"
        }
    ],
    "sg:phone":"+1 512 237 3998",
    "sg:postcode":"78957",
    "sg:province":"TX",
    "wof:name":"Shelly Hardy Insurance Agency Inc",
    "wof:placetype":"venue"
},
  "geometry": {"coordinates":[-97.160045,30.007668],"type":"Point"}
}