{
  "type": "Feature",
  "properties": {
    "iso:country":"US",
    "sg:address":"802 Ventura Ave",
    "sg:city":"Midland",
    "sg:classifiers":[
        {
            "category":"Social Services",
            "subcategory":"Job Training",
            "type":"Services"
        }
    ],
    "sg:phone":"+1 432 498 2053",
    "sg:postcode":"79705",
    "sg:province":"TX",
    "sg:tags":[
        "rehabilitation"
    ],
    "wof:name":"Midland Children's Rehab Ctr",
    "wof:placetype":"venue"
},
  "geometry": {"coordinates":[-102.09166500000001,32.02288],"type":"Point"}
}