{
  "type": "Feature",
  "properties": {
    "iso:country":"US",
    "sg:address":"15127 Beechnut St",
    "sg:city":"Houston",
    "sg:classifiers":[
        {
            "category":"Professional",
            "subcategory":"Business Services",
            "type":"Services"
        }
    ],
    "sg:phone":"+1 281 575 7230",
    "sg:postcode":"77083",
    "sg:province":"TX",
    "wof:name":"Sona International",
    "wof:placetype":"venue"
},
  "geometry": {"coordinates":[-95.654088,29.689326],"type":"Point"}
}