{
  "type": "Feature",
  "properties": {
    "iso:country":"US",
    "sg:address":"8801 Cullen Blvd",
    "sg:city":"Houston",
    "sg:classifiers":[
        {
            "category":"Retail",
            "subcategory":"Auto Repair",
            "type":"Services"
        }
    ],
    "sg:phone":"+1 713 733 1022",
    "sg:postcode":"77051",
    "sg:province":"TX",
    "sg:tags":[
        "general"
    ],
    "wof:name":"Superb Automotive",
    "wof:placetype":"venue"
},
  "geometry": {"coordinates":[-95.355588,29.663245],"type":"Point"}
}