{
  "type": "Feature",
  "properties": {
    "iso:country":"US",
    "sg:address":"502 Jester St",
    "sg:city":"Corpus Christi",
    "sg:classifiers":[
        {
            "category":"Real Estate",
            "subcategory":"Real Estate Agent",
            "type":"Services"
        }
    ],
    "sg:phone":"+1 254 786 2450",
    "sg:postcode":"78418",
    "sg:province":"TX",
    "sg:tags":[
        "authorities",
        "housing"
    ],
    "wof:name":"Us Government Housing Auth",
    "wof:placetype":"venue"
},
  "geometry": {"coordinates":[-97.27685099999999,27.674159],"type":"Point"}
}