{
  "type": "Feature",
  "properties": {
    "iso:country":"US",
    "sg:address":"210 N General Bruce Dr",
    "sg:city":"Temple",
    "sg:classifiers":[
        {
            "category":"Organizations",
            "subcategory":"Religious Organization",
            "type":"Services"
        }
    ],
    "sg:phone":"+1 254 778 4246",
    "sg:postcode":"76504",
    "sg:province":"TX",
    "sg:tags":[
        "church"
    ],
    "sg:website":"www.westernhillsonline.org",
    "wof:name":"Church Of Christ Western Hills",
    "wof:placetype":"venue"
},
  "geometry": {"coordinates":[-97.359748,31.104492],"type":"Point"}
}