{
  "type": "Feature",
  "properties": {
    "iso:country":"US",
    "sg:address":"914 W Lee St",
    "sg:city":"Floydada",
    "sg:classifiers":[
        {
            "category":"Professional",
            "type":"Services"
        }
    ],
    "sg:phone":"+1 806 983 6038",
    "sg:postcode":"79235",
    "sg:province":"TX",
    "wof:name":"Clear Horizon Inc",
    "wof:placetype":"venue"
},
  "geometry": {"coordinates":[-101.348888,33.988855],"type":"Point"}
}