{
  "type": "Feature",
  "properties": {
    "iso:country":"US",
    "sg:address":"1802 Summerwood Dr",
    "sg:city":"San Antonio",
    "sg:classifiers":[
        {
            "category":"Real Estate",
            "subcategory":"Real Estate Agent",
            "type":"Services"
        }
    ],
    "sg:phone":"+1 210 545 5406",
    "sg:postcode":"78232",
    "sg:province":"TX",
    "wof:name":"Micah Dufner Realtors",
    "wof:placetype":"venue"
},
  "geometry": {"coordinates":[-98.464382,29.596636],"type":"Point"}
}