{
  "type": "Feature",
  "properties": {
    "iso:country":"US",
    "sg:address":"10261 State Highway 149",
    "sg:city":"Longview",
    "sg:classifiers":[
        {
            "category":"Government",
            "subcategory":"Fire Station",
            "type":"Public Place"
        },
        {
            "category":"Retail",
            "subcategory":"Laundry & Dry Cleaning",
            "type":"Services"
        },
        {
            "category":"Building & Trades",
            "subcategory":"Cleaning & Sanitation",
            "type":"Services"
        }
    ],
    "sg:phone":"+1 903 643 9034",
    "sg:postcode":"75603",
    "sg:province":"TX",
    "sg:tags":[
        "cleaner",
        "disaster",
        "recovery",
        "damage",
        "rug",
        "water",
        "restoration",
        "relief",
        "carpet"
    ],
    "wof:name":"Texas Flood",
    "wof:placetype":"venue"
},
  "geometry": {"coordinates":[-94.61469099999999,32.370975],"type":"Point"}
}