{
  "type": "Feature",
  "properties": {
    "iso:country":"US",
    "sg:address":"3500 Robin Rd",
    "sg:city":"Plano",
    "sg:phone":"+1 972 985 0258",
    "sg:postcode":"75075",
    "sg:province":"TX",
    "sg:tags":[
        "product",
        "petroleum"
    ],
    "wof:name":"Core Oil & Gas Inc",
    "wof:placetype":"venue"
},
  "geometry": {"coordinates":[-96.75844600000001,33.013507],"type":"Point"}
}