{
  "type": "Feature",
  "properties": {
    "iso:country":"US",
    "sg:address":"688 Grapevine Hwy",
    "sg:city":"Hurst",
    "sg:classifiers":[
        {
            "category":"Retail",
            "subcategory":"Veterinary Services",
            "type":"Services"
        }
    ],
    "sg:phone":"+1 817 427 8484",
    "sg:postcode":"76054",
    "sg:province":"TX",
    "wof:name":"Moses Animal Clinic",
    "wof:placetype":"venue"
},
  "geometry": {"coordinates":[-97.17975300000001,32.861076],"type":"Point"}
}