{
  "type": "Feature",
  "properties": {
    "iso:country":"US",
    "sg:address":"2216 Solona St",
    "sg:city":"Fort Worth",
    "sg:classifiers":[
        {
            "category":"Autos & Motor Vehicles",
            "subcategory":"Automobile Sales",
            "type":"Retail Goods"
        },
        {
            "category":"Retail",
            "subcategory":"Auto Repair",
            "type":"Services"
        }
    ],
    "sg:phone":"+1 817 589 7974",
    "sg:postcode":"76117",
    "sg:province":"TX",
    "sg:tags":[
        "repairing"
    ],
    "sg:website":"www.britauto.com",
    "wof:name":"British Auto Specialists Inc",
    "wof:placetype":"venue"
},
  "geometry": {"coordinates":[-97.251561,32.792238],"type":"Point"}
}