{
  "type": "Feature",
  "properties": {
    "iso:country":"US",
    "sg:address":"1503 26th St",
    "sg:city":"Snyder",
    "sg:classifiers":[
        {
            "category":"Shopping",
            "subcategory":"Used Merchandise",
            "type":"Retail Goods"
        }
    ],
    "sg:phone":"+1 325 573 8870",
    "sg:postcode":"79549",
    "sg:province":"TX",
    "sg:tags":[
        "shop",
        "consignment"
    ],
    "wof:name":"Noah's Attic",
    "wof:placetype":"venue"
},
  "geometry": {"coordinates":[-100.91593,32.716151],"type":"Point"}
}