{
  "type": "Feature",
  "properties": {
    "iso:country":"US",
    "sg:address":"710 Ft. Worth Ave",
    "sg:city":"Dallas",
    "sg:classifiers":[
        {
            "category":"Fast Food",
            "type":"Food & Drink"
        }
    ],
    "sg:phone":"+1 214 748 7376",
    "sg:postcode":"75208",
    "sg:province":"TX",
    "sg:tags":[
        "burger"
    ],
    "sg:website":"burguesaburger.com",
    "wof:name":"Burguesa Burger",
    "wof:placetype":"venue"
},
  "geometry": {"coordinates":[-96.834823,32.76689],"type":"Point"}
}