{
  "type": "Feature",
  "properties": {
    "iso:country":"US",
    "sg:address":"1015 Beecave Woods Dr",
    "sg:city":"Austin",
    "sg:classifiers":[
        {
            "category":"Banks & Credit Unions",
            "subcategory":"Bank",
            "type":"Services"
        }
    ],
    "sg:phone":"+1 512 263 4222",
    "sg:postcode":"78746",
    "sg:province":"TX",
    "sg:tags":[
        "term",
        "finance",
        "lessor",
        "auto",
        "long",
        "truck"
    ],
    "wof:name":"Leasing Associates Inc",
    "wof:placetype":"venue"
},
  "geometry": {"coordinates":[-97.797511,30.270543],"type":"Point"}
}