{
  "type": "Feature",
  "properties": {
    "iso:country":"US",
    "sg:address":"3 Harbor Cove Dr",
    "sg:city":"Spring",
    "sg:classifiers":[
        {
            "category":"Professional",
            "type":"Services"
        }
    ],
    "sg:phone":"+1 281 419 7875",
    "sg:postcode":"77381",
    "sg:province":"TX",
    "sg:tags":[
        "establishment"
    ],
    "wof:name":"Robert Giammelle Assoc",
    "wof:placetype":"venue"
},
  "geometry": {"coordinates":[-95.48853699999999,30.157083],"type":"Point"}
}