{
  "type": "Feature",
  "properties": {
    "iso:country":"US",
    "sg:address":"2728 S Congress Ave",
    "sg:city":"Austin",
    "sg:classifiers":[
        {
            "category":"Restaurant",
            "type":"Food & Drink"
        }
    ],
    "sg:phone":"+1 512 443 4253",
    "sg:postcode":"78704",
    "sg:province":"TX",
    "sg:tags":[
        "cuban",
        "caribbean"
    ],
    "sg:website":"www.habana.com",
    "wof:name":"Habana Soco Restaurant",
    "wof:placetype":"venue"
},
  "geometry": {"coordinates":[-97.755017,30.237936],"type":"Point"}
}