{
  "type": "Feature",
  "properties": {
    "iso:country":"US",
    "sg:address":"302 N 6th St",
    "sg:city":"Nolanville",
    "sg:classifiers":[
        {
            "category":"Personal",
            "type":"Services"
        }
    ],
    "sg:phone":"+1 254 698 6052",
    "sg:postcode":"76559",
    "sg:province":"TX",
    "sg:tags":[
        "therapist",
        "massage"
    ],
    "wof:name":"A Soothing Touch Massage",
    "wof:placetype":"venue"
},
  "geometry": {"coordinates":[-97.602062,31.07996],"type":"Point"}
}