{
  "type": "Feature",
  "properties": {
    "iso:country":"US",
    "sg:address":"3814 Jewel St",
    "sg:city":"Garland",
    "sg:classifiers":[
        {
            "category":"Professional",
            "type":"Services"
        }
    ],
    "sg:phone":"+1 972 496 6979",
    "sg:postcode":"75048",
    "sg:province":"TX",
    "wof:name":"Canopus Creations",
    "wof:placetype":"venue"
},
  "geometry": {"coordinates":[-96.586913,32.976834],"type":"Point"}
}