{
  "type": "Feature",
  "properties": {
    "iso:country":"US",
    "sg:address":"316 Pecore St",
    "sg:city":"Houston",
    "sg:classifiers":[
        {
            "category":"Professional",
            "type":"Services"
        }
    ],
    "sg:phone":"+1 713 863 0578",
    "sg:postcode":"77009",
    "sg:province":"TX",
    "sg:tags":[
        "establishment"
    ],
    "wof:name":"Creole Field Office",
    "wof:placetype":"venue"
},
  "geometry": {"coordinates":[-95.376606,29.790523],"type":"Point"}
}