{
  "type": "Feature",
  "properties": {
    "iso:country":"US",
    "sg:address":"1707 Norwich Ave",
    "sg:city":"Lubbock",
    "sg:classifiers":[
        {
            "category":"Organizations",
            "subcategory":"Religious Organization",
            "type":"Services"
        }
    ],
    "sg:phone":"+1 806 744 6162",
    "sg:postcode":"79416",
    "sg:province":"TX",
    "wof:name":"Primitive Baptist Church",
    "wof:placetype":"venue"
},
  "geometry": {"coordinates":[-101.962621,33.582168],"type":"Point"}
}