{
  "type": "Feature",
  "properties": {
    "iso:country":"US",
    "sg:address":"339 Lindenwood Ln S",
    "sg:city":"Hewitt",
    "sg:classifiers":[
        {
            "category":"Building & Trades",
            "subcategory":"Construction",
            "type":"Services"
        }
    ],
    "sg:phone":"+1 254 666 2639",
    "sg:postcode":"76643",
    "sg:province":"TX",
    "sg:tags":[
        "contractor"
    ],
    "wof:name":"Sunproof Window Tinting",
    "wof:placetype":"venue"
},
  "geometry": {"coordinates":[-97.208789,31.468738],"type":"Point"}
}