{
  "type": "Feature",
  "properties": {
    "iso:country":"US",
    "sg:address":"21303 Park York Dr",
    "sg:city":"Katy",
    "sg:classifiers":[
        {
            "category":"Restaurant",
            "type":"Food & Drink"
        }
    ],
    "sg:phone":"+1 281 647 8101",
    "sg:postcode":"77450",
    "sg:province":"TX",
    "sg:tags":[
        "house",
        "steak",
        "barbecue"
    ],
    "wof:name":"Big Mike S Bbq",
    "wof:placetype":"venue"
},
  "geometry": {"coordinates":[-95.739115,29.763116],"type":"Point"}
}