{
  "type": "Feature",
  "properties": {
    "iso:country":"US",
    "sg:address":"12250 Abrams Rd",
    "sg:city":"Dallas",
    "sg:classifiers":[
        {
            "category":"Restaurant",
            "type":"Food & Drink"
        }
    ],
    "sg:phone":"+1 972 931 2575",
    "sg:postcode":"75243",
    "sg:province":"TX",
    "sg:tags":[
        "eating"
    ],
    "wof:name":"Luigis Pasta & Pizza",
    "wof:placetype":"venue"
},
  "geometry": {"coordinates":[-96.735542,32.914119],"type":"Point"}
}