{
  "type": "Feature",
  "properties": {
    "iso:country":"US",
    "sg:address":"6400 W Little York Rd",
    "sg:city":"Houston",
    "sg:classifiers":[
        {
            "category":"Professional",
            "type":"Services"
        }
    ],
    "sg:phone":"+1 713 586 8838",
    "sg:postcode":"77091",
    "sg:province":"TX",
    "sg:tags":[
        "establishment"
    ],
    "wof:name":"L L Bennett",
    "wof:placetype":"venue"
},
  "geometry": {"coordinates":[-95.486772,29.865751],"type":"Point"}
}