{
  "type": "Feature",
  "properties": {
    "iso:country":"US",
    "sg:address":"616 Barnett St",
    "sg:city":"Kerrville",
    "sg:classifiers":[
        {
            "category":"Social Services",
            "type":"Services"
        }
    ],
    "sg:phone":"+1 830 257 3009",
    "sg:postcode":"78028",
    "sg:province":"TX",
    "sg:tags":[
        "health"
    ],
    "wof:name":"Hill Cntry Chrstn Cnseling Ctr",
    "wof:placetype":"venue"
},
  "geometry": {"coordinates":[-99.137854,30.051488],"type":"Point"}
}