{
  "type": "Feature",
  "properties": {
    "iso:country":"US",
    "sg:address":"407 Hammack Dr",
    "sg:city":"Austin",
    "sg:classifiers":[
        {
            "category":"Banks & Credit Unions",
            "subcategory":"Financial Services",
            "type":"Services"
        }
    ],
    "sg:phone":"+1 512 476 7170",
    "sg:postcode":"78752",
    "sg:province":"TX",
    "sg:tags":[
        "investor"
    ],
    "wof:name":"Bsh Investments LLC",
    "wof:placetype":"venue"
},
  "geometry": {"coordinates":[-97.719419,30.329337],"type":"Point"}
}