{
  "type": "Feature",
  "properties": {
    "iso:country":"US",
    "sg:address":"9931 Chimney Hill Ln",
    "sg:city":"Dallas",
    "sg:classifiers":[
        {
            "category":"Retail",
            "subcategory":"Auto Rental",
            "type":"Services"
        }
    ],
    "sg:phone":"+1 214 575 5022",
    "sg:postcode":"75243",
    "sg:province":"TX",
    "sg:tags":[
        "trailer",
        "utility"
    ],
    "wof:name":"Eddlemons Rentals",
    "wof:placetype":"venue"
},
  "geometry": {"coordinates":[-96.72394300000001,32.916058],"type":"Point"}
}