{
  "type": "Feature",
  "properties": {
    "iso:country":"US",
    "sg:address":"11250 Charles Rd",
    "sg:city":"Houston",
    "sg:classifiers":[
        {
            "category":"Building & Trades",
            "subcategory":"Construction",
            "type":"Services"
        }
    ],
    "sg:phone":"+1 713 856 8900",
    "sg:postcode":"77041",
    "sg:province":"TX",
    "sg:tags":[
        "nonresidential"
    ],
    "wof:name":"JAMES-EGGLESTON BUILDERS",
    "wof:placetype":"venue"
},
  "geometry": {"coordinates":[-95.580073,29.884176],"type":"Point"}
}