{
  "type": "Feature",
  "properties": {
    "iso:country":"US",
    "sg:address":"1809 Tracy Miller Ln",
    "sg:city":"Cedar Park",
    "sg:classifiers":[
        {
            "category":"Building & Trades",
            "subcategory":"Construction",
            "type":"Services"
        }
    ],
    "sg:phone":"+1 512 258 2869",
    "sg:postcode":"78613",
    "sg:province":"TX",
    "sg:tags":[
        "home",
        "builder"
    ],
    "wof:name":"Custom Homes",
    "wof:placetype":"venue"
},
  "geometry": {"coordinates":[-97.83930599999999,30.474062],"type":"Point"}
}