{
  "type": "Feature",
  "properties": {
    "iso:country":"US",
    "sg:address":"4221 N Garland Ave",
    "sg:city":"Garland",
    "sg:classifiers":[
        {
            "category":"Manufacturing",
            "subcategory":"Petroleum Products",
            "type":"Manufacturing & Wholesale Goods"
        }
    ],
    "sg:phone":"+1 972 495 4244",
    "sg:postcode":"75040",
    "sg:province":"TX",
    "sg:tags":[
        "asphalt",
        "mfg"
    ],
    "wof:name":"APAC",
    "wof:placetype":"venue"
},
  "geometry": {"coordinates":[-96.65610599999999,32.95417],"type":"Point"}
}