{
  "type": "Feature",
  "properties": {
    "iso:country":"US",
    "sg:address":"2502 Alexander Ln",
    "sg:city":"Pearland",
    "sg:classifiers":[
        {
            "category":"Professional",
            "subcategory":"Management & Consulting",
            "type":"Services"
        }
    ],
    "sg:phone":"+1 281 997 6968",
    "sg:postcode":"77581",
    "sg:province":"TX",
    "sg:tags":[
        "business"
    ],
    "wof:name":"DMS Consulting",
    "wof:placetype":"venue"
},
  "geometry": {"coordinates":[-95.26812700000001,29.561827],"type":"Point"}
}