{
  "type": "Feature",
  "properties": {
    "iso:country":"US",
    "sg:address":"54 Chicon St",
    "sg:city":"Austin",
    "sg:classifiers":[
        {
            "category":"Health Services",
            "subcategory":"Hospital",
            "type":"Services"
        }
    ],
    "sg:phone":"+1 512 472 1008",
    "sg:postcode":"78702",
    "sg:province":"TX",
    "sg:tags":[
        "mental"
    ],
    "wof:name":"Sims Foundation",
    "wof:placetype":"venue"
},
  "geometry": {"coordinates":[-97.726536,30.253093],"type":"Point"}
}