{
  "type": "Feature",
  "properties": {
    "iso:country":"US",
    "sg:address":"2725 Timberline Dr",
    "sg:city":"Fort Worth",
    "sg:classifiers":[
        {
            "category":"Shopping",
            "subcategory":"Hobbies, Toys, & Games",
            "type":"Retail Goods"
        }
    ],
    "sg:phone":"+1 817 535 1507",
    "sg:postcode":"76119",
    "sg:province":"TX",
    "wof:name":"Camile Bouti",
    "wof:placetype":"venue"
},
  "geometry": {"coordinates":[-97.28386999999999,32.695026],"type":"Point"}
}