{
  "type": "Feature",
  "properties": {
    "iso:country":"US",
    "sg:address":"711 Lawrence St",
    "sg:city":"Jacksonville",
    "sg:classifiers":[
        {
            "category":"Organizations",
            "subcategory":"Religious Organization",
            "type":"Services"
        }
    ],
    "sg:phone":"+1 903 586 4734",
    "sg:postcode":"75766",
    "sg:province":"TX",
    "wof:name":"Cosby Oliver Evangelistic",
    "wof:placetype":"venue"
},
  "geometry": {"coordinates":[-95.28625099999999,31.969122],"type":"Point"}
}