{
  "type": "Feature",
  "properties": {
    "iso:country":"US",
    "sg:address":"2700 Earl Rudder Fwy S",
    "sg:city":"College Station",
    "sg:classifiers":[
        {
            "category":"Education",
            "subcategory":"College",
            "type":"Public Place"
        }
    ],
    "sg:phone":"+1 979 845 3854",
    "sg:postcode":"77845",
    "sg:province":"TX",
    "wof:name":"Sea Grant Program",
    "wof:placetype":"venue"
},
  "geometry": {"coordinates":[-96.289518,30.600882],"type":"Point"}
}