{
  "type": "Feature",
  "properties": {
    "iso:country":"US",
    "sg:address":"32641 San Carlos Rd",
    "sg:city":"San Benito",
    "sg:classifiers":[
        {
            "category":"Real Estate",
            "subcategory":"Real Estate Agent",
            "type":"Services"
        }
    ],
    "sg:phone":"+1 956 399 8684",
    "sg:postcode":"78586",
    "sg:province":"TX",
    "wof:name":"Rose Jordan Inc",
    "wof:placetype":"venue"
},
  "geometry": {"coordinates":[-97.54294299999999,26.085593],"type":"Point"}
}