{
  "type": "Feature",
  "properties": {
    "iso:country":"US",
    "sg:address":"5707 Forest Shade",
    "sg:city":"San Antonio",
    "sg:classifiers":[
        {
            "category":"Building & Trades",
            "subcategory":"Cleaning & Sanitation",
            "type":"Services"
        }
    ],
    "sg:phone":"+1 210 682 3184",
    "sg:postcode":"78250",
    "sg:province":"TX",
    "sg:tags":[
        "maintenance"
    ],
    "wof:name":"Priscillas Janitorial Service",
    "wof:placetype":"venue"
},
  "geometry": {"coordinates":[-98.654759,29.499428],"type":"Point"}
}