{
  "type": "Feature",
  "properties": {
    "iso:country":"US",
    "sg:address":"3368 Sam Rayburn Run",
    "sg:city":"Carrollton",
    "sg:classifiers":[
        {
            "category":"Shopping",
            "subcategory":"Jewelry",
            "type":"Retail Goods"
        }
    ],
    "sg:phone":"+1 972 662 2558",
    "sg:postcode":"75007",
    "sg:province":"TX",
    "wof:name":"Kathleen Joy Designs",
    "wof:placetype":"venue"
},
  "geometry": {"coordinates":[-96.86878900000001,33.008078],"type":"Point"}
}