{
  "type": "Feature",
  "properties": {
    "iso:country":"US",
    "sg:address":"4803 Ramus St",
    "sg:city":"Houston",
    "sg:classifiers":[
        {
            "category":"Autos & Motor Vehicles",
            "subcategory":"Automobile Sales",
            "type":"Retail Goods"
        },
        {
            "category":"Retail",
            "subcategory":"Auto Repair",
            "type":"Services"
        }
    ],
    "sg:phone":"+1 713 688 7525",
    "sg:postcode":"77092",
    "sg:province":"TX",
    "sg:tags":[
        "equipment",
        "truck",
        "equipment-service",
        "air conditioning"
    ],
    "wof:name":"Cool Flow Inc",
    "wof:placetype":"venue"
},
  "geometry": {"coordinates":[-95.46137400000001,29.810599],"type":"Point"}
}