{
  "type": "Feature",
  "properties": {
    "iso:country":"US",
    "sg:address":"14205 Stewart Rd",
    "sg:city":"Galveston",
    "sg:classifiers":[
        {
            "category":"Building & Trades",
            "subcategory":"Construction",
            "type":"Services"
        }
    ],
    "sg:phone":"+1 409 737 3253",
    "sg:postcode":"77554",
    "sg:province":"TX",
    "sg:tags":[
        "home",
        "improvement"
    ],
    "wof:name":"Pirates Beach Maintenance",
    "wof:placetype":"venue"
},
  "geometry": {"coordinates":[-94.941148,29.210477],"type":"Point"}
}