{
  "type": "Feature",
  "properties": {
    "iso:country":"US",
    "sg:address":"451 Poindexter Ln",
    "sg:city":"Plano",
    "sg:classifiers":[
        {
            "category":"Professional",
            "type":"Services"
        }
    ],
    "sg:phone":"+1 972 423 6621",
    "sg:postcode":"75094",
    "sg:province":"TX",
    "wof:name":"Take 2",
    "wof:placetype":"venue"
},
  "geometry": {"coordinates":[-96.607353,33.018967],"type":"Point"}
}