{
  "type": "Feature",
  "properties": {
    "iso:country":"US",
    "sg:address":"2215 Century Cir",
    "sg:city":"Irving",
    "sg:classifiers":[
        {
            "category":"Freight",
            "type":"Transportation"
        }
    ],
    "sg:phone":"+1 972 438 5353",
    "sg:postcode":"75062",
    "sg:province":"TX",
    "sg:tags":[
        "building",
        "industrial",
        "construct",
        "general"
    ],
    "wof:name":"Conduit Pipe Products Company",
    "wof:placetype":"venue"
},
  "geometry": {"coordinates":[-96.897632,32.84281],"type":"Point"}
}