{
  "type": "Feature",
  "properties": {
    "iso:country":"US",
    "sg:address":"7532 Sand St",
    "sg:city":"Fort Worth",
    "sg:classifiers":[
        {
            "category":"Retail",
            "subcategory":"Auto Repair",
            "type":"Services"
        }
    ],
    "sg:phone":"+1 817 590 0308",
    "sg:postcode":"76118",
    "sg:province":"TX",
    "sg:tags":[
        "automotive",
        "wrecker"
    ],
    "wof:name":"J L Milner Wrecker Service",
    "wof:placetype":"venue"
},
  "geometry": {"coordinates":[-97.21971600000001,32.79602],"type":"Point"}
}