{
  "type": "Feature",
  "properties": {
    "iso:country":"US",
    "sg:address":"1730 Richey St",
    "sg:city":"Pasadena",
    "sg:classifiers":[
        {
            "category":"Professional",
            "subcategory":"Secretarial Services",
            "type":"Services"
        }
    ],
    "sg:phone":"+1 713 472 1916",
    "sg:postcode":"77502",
    "sg:province":"TX",
    "sg:tags":[
        "reporting"
    ],
    "wof:name":"Techtype",
    "wof:placetype":"venue"
},
  "geometry": {"coordinates":[-95.222393,29.685999],"type":"Point"}
}