{
  "type": "Feature",
  "properties": {
    "iso:country":"US",
    "sg:address":"1401 FM 1496",
    "sg:city":"De Leon",
    "sg:classifiers":[
        {
            "category":"Wholesale",
            "subcategory":"Farm Supplies",
            "type":"Manufacturing & Wholesale Goods"
        }
    ],
    "sg:phone":"+1 254 893 2034",
    "sg:postcode":"76444",
    "sg:province":"TX",
    "sg:tags":[
        "peanut",
        "product"
    ],
    "sg:website":"www.goldenpeanut.com",
    "wof:name":"Golden Peanut Co",
    "wof:placetype":"venue"
},
  "geometry": {"coordinates":[-98.461698,32.068699],"type":"Point"}
}