{
  "type": "Feature",
  "properties": {
    "iso:country":"US",
    "sg:address":"612 W Dickinson Blvd",
    "sg:city":"Fort Stockton",
    "sg:classifiers":[
        {
            "category":"Shopping",
            "subcategory":"Musical Instruments",
            "type":"Retail Goods"
        }
    ],
    "sg:phone":"+1 432 336 0388",
    "sg:postcode":"79735",
    "sg:province":"TX",
    "wof:name":"Escandalo Musical",
    "wof:placetype":"venue"
},
  "geometry": {"coordinates":[-102.88551099999999,30.894018],"type":"Point"}
}