{
  "type": "Feature",
  "properties": {
    "iso:country":"US",
    "sg:address":"1505 N Laurent St",
    "sg:city":"Victoria",
    "sg:classifiers":[
        {
            "category":"Retail",
            "subcategory":"Funeral Services",
            "type":"Services"
        }
    ],
    "sg:phone":"+1 361 575 6180",
    "sg:postcode":"77901",
    "sg:province":"TX",
    "sg:tags":[
        "director"
    ],
    "wof:name":"Barefield Funeral Home",
    "wof:placetype":"venue"
},
  "geometry": {"coordinates":[-96.99109199999999,28.808068],"type":"Point"}
}