{
  "type": "Feature",
  "properties": {
    "iso:country":"US",
    "sg:address":"3524 Pershing Dr",
    "sg:city":"El Paso",
    "sg:classifiers":[
        {
            "category":"Restaurant",
            "type":"Food & Drink"
        }
    ],
    "sg:phone":"+1 915 566 1103",
    "sg:postcode":"79903",
    "sg:province":"TX",
    "sg:tags":[
        "eating"
    ],
    "wof:name":"Oasis Family Restaurant",
    "wof:placetype":"venue"
},
  "geometry": {"coordinates":[-106.45172100000001,31.786846],"type":"Point"}
}