{
  "type": "Feature",
  "properties": {
    "iso:country":"US",
    "sg:address":"4118 Aransas St",
    "sg:city":"Dallas",
    "sg:classifiers":[
        {
            "category":"Organizations",
            "subcategory":"Religious Organization",
            "type":"Services"
        }
    ],
    "sg:phone":"+1 214 631 3245",
    "sg:postcode":"75212",
    "sg:province":"TX",
    "sg:tags":[
        "church"
    ],
    "wof:name":"Believers Tabernacle",
    "wof:placetype":"venue"
},
  "geometry": {"coordinates":[-96.874893,32.791076],"type":"Point"}
}