{
  "type": "Feature",
  "properties": {
    "iso:country":"US",
    "sg:address":"1830 Conner Dr",
    "sg:city":"Dallas",
    "sg:classifiers":[
        {
            "category":"Building & Trades",
            "subcategory":"Cleaning & Sanitation",
            "type":"Services"
        },
        {
            "category":"Building & Trades",
            "subcategory":"Construction",
            "type":"Services"
        }
    ],
    "sg:phone":"+1 214 398 5694",
    "sg:postcode":"75217",
    "sg:province":"TX",
    "sg:tags":[
        "refinishing",
        "tile-cleaning",
        "contractor",
        "tile-contractors",
        "sealing",
        "mason",
        "marble",
        "terrazzo"
    ],
    "wof:name":"Leal Tile & Marble",
    "wof:placetype":"venue"
},
  "geometry": {"coordinates":[-96.68093500000001,32.741674],"type":"Point"}
}