{
  "type": "Feature",
  "properties": {
    "iso:country":"US",
    "sg:address":"4830 S Lancaster Rd",
    "sg:city":"Dallas",
    "sg:classifiers":[
        {
            "category":"Retail",
            "subcategory":"Funeral Services",
            "type":"Services"
        }
    ],
    "sg:phone":"+1 214 374 5500",
    "sg:postcode":"75216",
    "sg:province":"TX",
    "sg:tags":[
        "director"
    ],
    "wof:name":"Gregory W Spencer Meml Chapel",
    "wof:placetype":"venue"
},
  "geometry": {"coordinates":[-96.79087800000001,32.688854],"type":"Point"}
}