{
  "type": "Feature",
  "properties": {
    "iso:country":"US",
    "sg:address":"11600 Montana Ave",
    "sg:city":"El Paso",
    "sg:classifiers":[
        {
            "category":"Freight",
            "type":"Transportation"
        }
    ],
    "sg:phone":"+1 915 855 8397",
    "sg:postcode":"79936",
    "sg:province":"TX",
    "sg:tags":[
        "operator",
        "trucking"
    ],
    "wof:name":"Hawkeye Transport",
    "wof:placetype":"venue"
},
  "geometry": {"coordinates":[-106.2872,31.803727],"type":"Point"}
}