{
  "type": "Feature",
  "properties": {
    "iso:country":"US",
    "sg:address":"102 W Main St",
    "sg:city":"Trinity",
    "sg:classifiers":[
        {
            "category":"Banks & Credit Unions",
            "subcategory":"Investment Brokerage",
            "type":"Services"
        },
        {
            "category":"Banks & Credit Unions",
            "subcategory":"Bank",
            "type":"Services"
        },
        {
            "category":"Banks & Credit Unions",
            "subcategory":"Financial Services",
            "type":"Services"
        },
        {
            "category":"Insurance",
            "subcategory":"Insurance Agent",
            "type":"Services"
        },
        {
            "category":"Insurance",
            "subcategory":"Life Insurance",
            "type":"Services"
        },
        {
            "category":"Professional",
            "subcategory":"Management & Consulting",
            "type":"Services"
        },
        {
            "category":"Insurance",
            "subcategory":"Hazard Insurance",
            "type":"Services"
        }
    ],
    "sg:phone":"+1 936 594 5700",
    "sg:postcode":"75862",
    "sg:province":"TX",
    "sg:tags":[
        "advisory",
        "mutual",
        "retirement",
        "planner",
        "profit",
        "transfer",
        "sharing",
        "broker",
        "pension",
        "fund",
        "consultant",
        "planning",
        "plan",
        "annuity",
        "bond",
        "counseling",
        "security",
        "debt",
        "analyst",
        "financing",
        "stock"
    ],
    "sg:website":"http://edwardjones.com",
    "wof:name":"Edward Jones - PAULA A WINZER",
    "wof:placetype":"venue"
},
  "geometry": {"coordinates":[-95.37568400000001,30.945074],"type":"Point"}
}