{
  "type": "Feature",
  "properties": {
    "iso:country":"US",
    "sg:address":"3202 San Pedro Ave",
    "sg:city":"San Antonio",
    "sg:classifiers":[
        {
            "category":"Professional",
            "subcategory":"Business Services",
            "type":"Services"
        }
    ],
    "sg:phone":"+1 210 732 5100",
    "sg:postcode":"78212",
    "sg:province":"TX",
    "wof:name":"Bromley Medical Group",
    "wof:placetype":"venue"
},
  "geometry": {"coordinates":[-98.499207,29.465612],"type":"Point"}
}