{
  "type": "Feature",
  "properties": {
    "iso:country":"US",
    "sg:address":"1609 Shoal Creek Blvd",
    "sg:city":"Austin",
    "sg:classifiers":[
        {
            "category":"Organizations",
            "subcategory":"Political Organization",
            "type":"Services"
        }
    ],
    "sg:phone":"+1 512 476 4141",
    "sg:postcode":"78701",
    "sg:province":"TX",
    "wof:name":"Republican Club Of Austin",
    "wof:placetype":"venue"
},
  "geometry": {"coordinates":[-97.750027,30.280569],"type":"Point"}
}