{
  "type": "Feature",
  "properties": {
    "iso:country":"US",
    "sg:address":"14334 Broadgreen Dr",
    "sg:city":"Houston",
    "sg:classifiers":[
        {
            "category":"Professional",
            "type":"Services"
        }
    ],
    "sg:phone":"+1 281 558 3592",
    "sg:postcode":"77079",
    "sg:province":"TX",
    "wof:name":"Goview Co Inc",
    "wof:placetype":"venue"
},
  "geometry": {"coordinates":[-95.598677,29.767706],"type":"Point"}
}