{
  "type": "Feature",
  "properties": {
    "iso:country":"US",
    "sg:address":"1507 White Post Dr",
    "sg:city":"Cedar Park",
    "sg:classifiers":[
        {
            "category":"Home & Garden",
            "subcategory":"Building Materials",
            "type":"Retail Goods"
        }
    ],
    "sg:phone":"+1 512 473 6758",
    "sg:postcode":"78613",
    "sg:province":"TX",
    "wof:name":"Matthews Electrical Supplies",
    "wof:placetype":"venue"
},
  "geometry": {"coordinates":[-97.816109,30.467363],"type":"Point"}
}