{
  "type": "Feature",
  "properties": {
    "iso:country":"US",
    "sg:address":"4325 Effie St",
    "sg:city":"Bellaire",
    "sg:classifiers":[
        {
            "category":"Professional",
            "subcategory":"Business Services",
            "type":"Services"
        },
        {
            "category":"Professional",
            "subcategory":"Printing & Photocopies",
            "type":"Services"
        }
    ],
    "sg:phone":"+1 713 665 5837",
    "sg:postcode":"77401",
    "sg:province":"TX",
    "sg:tags":[
        "system",
        "form",
        "printers-business"
    ],
    "wof:name":"Southwest Business Forms",
    "wof:placetype":"venue"
},
  "geometry": {"coordinates":[-95.447901,29.695652],"type":"Point"}
}