{
  "type": "Feature",
  "properties": {
    "iso:country":"US",
    "sg:address":"1637 Westheimer",
    "sg:city":"Houston",
    "sg:classifiers":[
        {
            "category":"Shopping",
            "subcategory":"Used Merchandise",
            "type":"Retail Goods"
        }
    ],
    "sg:phone":"+1 713 521 9100",
    "sg:postcode":"77006",
    "sg:province":"TX",
    "sg:tags":[
        "vintage",
        "consignment"
    ],
    "sg:website":"www.myspace.com/blackbirdtradingco",
    "wof:name":"Blackbird Trading Co.",
    "wof:placetype":"venue"
},
  "geometry": {"coordinates":[-95.400802,29.742551],"type":"Point"}
}