{
  "type": "Feature",
  "properties": {
    "iso:country":"US",
    "sg:address":"1915 Skillman St",
    "sg:city":"Dallas",
    "sg:classifiers":[
        {
            "category":"Shopping",
            "subcategory":"Shoes",
            "type":"Retail Goods"
        },
        {
            "category":"Personal",
            "subcategory":"Shoe Repair & Shine",
            "type":"Services"
        }
    ],
    "sg:phone":"+1 214 821 0360",
    "sg:postcode":"75206",
    "sg:province":"TX",
    "sg:tags":[
        "repairing",
        "boot"
    ],
    "wof:name":"Skillman Shoe & Boot Service",
    "wof:placetype":"venue"
},
  "geometry": {"coordinates":[-96.761703,32.813702],"type":"Point"}
}