{
  "type": "Feature",
  "properties": {
    "iso:country":"US",
    "sg:address":"1201 Navarro St",
    "sg:city":"San Antonio",
    "sg:classifiers":[
        {
            "category":"Education",
            "subcategory":"Special Training",
            "type":"Public Place"
        }
    ],
    "sg:phone":"+1 210 271 3374",
    "sg:postcode":"78205",
    "sg:province":"TX",
    "sg:tags":[
        "school",
        "instruction",
        "art"
    ],
    "wof:name":"Southwest School Of Art",
    "wof:placetype":"venue"
},
  "geometry": {"coordinates":[-98.492858,29.432807],"type":"Point"}
}