{
  "type": "Feature",
  "properties": {
    "iso:country":"US",
    "sg:address":"3333 Lee Pkwy",
    "sg:city":"Dallas",
    "sg:classifiers":[
        {
            "category":"Professional",
            "subcategory":"Lawyer & Legal Services",
            "type":"Services"
        }
    ],
    "sg:phone":"+1 214 742 1200",
    "sg:postcode":"75219",
    "sg:province":"TX",
    "sg:tags":[
        "attorney"
    ],
    "wof:name":"Sifford Anderson & Vice",
    "wof:placetype":"venue"
},
  "geometry": {"coordinates":[-96.804886,32.809013],"type":"Point"}
}