{
  "type": "Feature",
  "properties": {
    "iso:country":"US",
    "sg:address":"5314 Maybrook Park Ln",
    "sg:city":"Katy",
    "sg:classifiers":[
        {
            "category":"Shopping",
            "subcategory":"Gifts & Souvenirs",
            "type":"Retail Goods"
        }
    ],
    "sg:phone":"+1 281 635 8039",
    "sg:postcode":"77450",
    "sg:province":"TX",
    "sg:tags":[
        "party",
        "supply"
    ],
    "wof:name":"Mr Margarita-KATY",
    "wof:placetype":"venue"
},
  "geometry": {"coordinates":[-95.76401799999999,29.716167],"type":"Point"}
}