{
  "type": "Feature",
  "properties": {
    "iso:country":"US",
    "sg:address":"810 Bard Dr",
    "sg:city":"Garland",
    "sg:classifiers":[
        {
            "category":"Personal",
            "subcategory":"Beauty Salon",
            "type":"Services"
        }
    ],
    "sg:phone":"+1 972 926 9820",
    "sg:postcode":"75040",
    "sg:province":"TX",
    "sg:tags":[
        "shop",
        "business"
    ],
    "wof:name":"Bjs Business/Special Event SE",
    "wof:placetype":"venue"
},
  "geometry": {"coordinates":[-96.61257999999999,32.904979],"type":"Point"}
}