{
  "type": "Feature",
  "properties": {
    "iso:country":"US",
    "sg:address":"1341 W Mockingbird Ln",
    "sg:city":"Dallas",
    "sg:classifiers":[
        {
            "category":"Professional",
            "subcategory":"Detective & Security Services",
            "type":"Services"
        }
    ],
    "sg:phone":"+1 214 637 2290",
    "sg:postcode":"75247",
    "sg:province":"TX",
    "sg:tags":[
        "guard",
        "patrol"
    ],
    "sg:website":"www.abm.com",
    "wof:name":"American Commercial Security",
    "wof:placetype":"venue"
},
  "geometry": {"coordinates":[-96.86484900000001,32.821907],"type":"Point"}
}