{
  "type": "Feature",
  "properties": {
    "iso:country":"US",
    "sg:address":"108 W Corpus Christi St",
    "sg:city":"Beeville",
    "sg:classifiers":[
        {
            "category":"Professional",
            "type":"Services"
        }
    ],
    "sg:phone":"+1 361 362 1904",
    "sg:postcode":"78102",
    "sg:province":"TX",
    "sg:tags":[
        "establishment"
    ],
    "wof:name":"Institute Of Rising Stars",
    "wof:placetype":"venue"
},
  "geometry": {"coordinates":[-97.748238,28.402083],"type":"Point"}
}