{
  "type": "Feature",
  "properties": {
    "iso:country":"US",
    "sg:address":"4343 W Camp Wisdom Rd Ste 124",
    "sg:city":"Dallas",
    "sg:classifiers":[
        {
            "category":"Food & Beverages",
            "subcategory":"Groceries & Convenience Stores",
            "type":"Retail Goods"
        }
    ],
    "sg:phone":"+1 972 298 0687",
    "sg:postcode":"75237",
    "sg:province":"TX",
    "wof:name":"Dalia Foodmart",
    "wof:placetype":"venue"
},
  "geometry": {"coordinates":[-96.89070100000001,32.662102],"type":"Point"}
}