{
  "type": "Feature",
  "properties": {
    "iso:country":"US",
    "sg:address":"3125 Country Club Rd",
    "sg:city":"San Angelo",
    "sg:classifiers":[
        {
            "category":"Professional",
            "subcategory":"Business Services",
            "type":"Services"
        }
    ],
    "sg:phone":"+1 325 944 2266",
    "sg:postcode":"76904",
    "sg:province":"TX",
    "wof:name":"MA Hoelscher Enterprises",
    "wof:placetype":"venue"
},
  "geometry": {"coordinates":[-100.46754199999999,31.377686],"type":"Point"}
}