{
  "type": "Feature",
  "properties": {
    "iso:country":"US",
    "sg:address":"16801 FM 2920",
    "sg:city":"Tomball",
    "sg:classifiers":[
        {
            "category":"Wholesale",
            "subcategory":"Machinery & Supplies",
            "type":"Manufacturing & Wholesale Goods"
        }
    ],
    "sg:phone":"+1 281 351 9109",
    "sg:postcode":"77377",
    "sg:province":"TX",
    "sg:tags":[
        "building",
        "material",
        "lumber"
    ],
    "wof:name":"Forest Tomball Products Inc",
    "wof:placetype":"venue"
},
  "geometry": {"coordinates":[-95.67921,30.079451],"type":"Point"}
}