{
  "type": "Feature",
  "properties": {
    "iso:country":"US",
    "sg:address":"2911 Medical Arts St Ste 3",
    "sg:city":"Austin",
    "sg:classifiers":[
        {
            "category":"Health Services",
            "subcategory":"Doctor",
            "type":"Services"
        }
    ],
    "sg:phone":"+1 512 476 9195",
    "sg:postcode":"78705",
    "sg:province":"TX",
    "sg:tags":[
        "dermatologist"
    ],
    "wof:name":"Fox John Jr MD",
    "wof:placetype":"venue"
},
  "geometry": {"coordinates":[-97.728996,30.2885],"type":"Point"}
}