{
  "type": "Feature",
  "properties": {
    "iso:country":"US",
    "sg:address":"1120 Santa Ursula Ave",
    "sg:city":"Laredo",
    "sg:classifiers":[
        {
            "category":"Restaurant",
            "type":"Food & Drink"
        }
    ],
    "sg:phone":"+1 956 724 4911",
    "sg:postcode":"78040",
    "sg:province":"TX",
    "sg:tags":[
        "eating"
    ],
    "wof:name":"McDonalds",
    "wof:placetype":"venue"
},
  "geometry": {"coordinates":[-99.503508,27.509724],"type":"Point"}
}