{
  "type": "Feature",
  "properties": {
    "iso:country":"US",
    "sg:address":"119 N Main St",
    "sg:city":"Grand Saline",
    "sg:classifiers":[
        {
            "category":"Professional",
            "type":"Services"
        }
    ],
    "sg:phone":"+1 903 962 3206",
    "sg:postcode":"75140",
    "sg:province":"TX",
    "sg:tags":[
        "establishment"
    ],
    "wof:name":"Sonshine Place",
    "wof:placetype":"venue"
},
  "geometry": {"coordinates":[-95.7097,32.673355],"type":"Point"}
}