{
  "type": "Feature",
  "properties": {
    "iso:country":"US",
    "sg:address":"2224 US Hwy 77X Bus",
    "sg:city":"Harlingen",
    "sg:classifiers":[
        {
            "category":"Building & Trades",
            "subcategory":"Cleaning & Sanitation",
            "type":"Services"
        }
    ],
    "sg:phone":"+1 956 421 4927",
    "sg:postcode":"78550",
    "sg:province":"TX",
    "sg:tags":[
        "maintenance"
    ],
    "wof:name":"Dolly Maid",
    "wof:placetype":"venue"
},
  "geometry": {"coordinates":[-97.710144,26.214997],"type":"Point"}
}