{
  "type": "Feature",
  "properties": {
    "iso:country":"US",
    "sg:address":"4808 Dacoma St",
    "sg:city":"Houston",
    "sg:classifiers":[
        {
            "category":"Wholesale",
            "subcategory":"Hardware",
            "type":"Manufacturing & Wholesale Goods"
        }
    ],
    "sg:phone":"+1 713 812 0006",
    "sg:postcode":"77092",
    "sg:province":"TX",
    "sg:tags":[
        "fastener"
    ],
    "wof:name":"Fastenal Co",
    "wof:placetype":"venue"
},
  "geometry": {"coordinates":[-95.462176,29.806872],"type":"Point"}
}