{
  "type": "Feature",
  "properties": {
    "iso:country":"US",
    "sg:address":"533 E Broad St",
    "sg:city":"Mineola",
    "sg:classifiers":[
        {
            "category":"Travel",
            "subcategory":"Hotels & Motels",
            "type":"Entertainment"
        }
    ],
    "sg:phone":"+1 903 569 5445",
    "sg:postcode":"75773",
    "sg:province":"TX",
    "wof:name":"Lakeland Lodge",
    "wof:placetype":"venue"
},
  "geometry": {"coordinates":[-95.49383899999999,32.664583],"type":"Point"}
}