{
  "type": "Feature",
  "properties": {
    "iso:country":"US",
    "sg:address":"1925 Trawood Dr",
    "sg:city":"El Paso",
    "sg:classifiers":[
        {
            "category":"Wholesale",
            "subcategory":"Chemicals & Plastics",
            "type":"Manufacturing & Wholesale Goods"
        }
    ],
    "sg:phone":"+1 915 594 9030",
    "sg:postcode":"79935",
    "sg:province":"TX",
    "wof:name":"FP International Supply",
    "wof:placetype":"venue"
},
  "geometry": {"coordinates":[-106.335291,31.765676],"type":"Point"}
}