{
  "type": "Feature",
  "properties": {
    "iso:country":"US",
    "sg:address":"2211 Hilliard Rd",
    "sg:city":"San Marcos",
    "sg:classifiers":[
        {
            "category":"Real Estate",
            "subcategory":"Architect",
            "type":"Services"
        }
    ],
    "sg:phone":"+1 512 353 3479",
    "sg:postcode":"78666",
    "sg:province":"TX",
    "sg:tags":[
        "architectural"
    ],
    "wof:name":"Delanie Broadwater",
    "wof:placetype":"venue"
},
  "geometry": {"coordinates":[-97.981092,29.964334],"type":"Point"}
}