{
  "type": "Feature",
  "properties": {
    "iso:country":"US",
    "sg:address":"25 Burwood Ln",
    "sg:city":"San Antonio",
    "sg:classifiers":[
        {
            "category":"Education",
            "subcategory":"Special Training",
            "type":"Public Place"
        }
    ],
    "sg:phone":"+1 210 342 4674",
    "sg:postcode":"78216",
    "sg:province":"TX",
    "sg:tags":[
        "organization",
        "religious"
    ],
    "wof:name":"Feast",
    "wof:placetype":"venue"
},
  "geometry": {"coordinates":[-98.504606,29.494403],"type":"Point"}
}