{
  "type": "Feature",
  "properties": {
    "iso:country":"US",
    "sg:address":"1600 W 35th St",
    "sg:city":"Austin",
    "sg:classifiers":[
        {
            "category":"Restaurant",
            "type":"Food & Drink"
        }
    ],
    "sg:phone":"+1 512 323 5215",
    "sg:postcode":"78703",
    "sg:province":"TX",
    "sg:tags":[
        "pizza"
    ],
    "wof:name":"Austin's Pizza",
    "wof:placetype":"venue"
},
  "geometry": {"coordinates":[-97.750647,30.307357],"type":"Point"}
}