{
  "type": "Feature",
  "properties": {
    "iso:country":"US",
    "sg:address":"5242 Holly Rd",
    "sg:city":"Corpus Christi",
    "sg:classifiers":[
        {
            "category":"Real Estate",
            "subcategory":"Real Estate Agent",
            "type":"Services"
        }
    ],
    "sg:phone":"+1 361 993 5778",
    "sg:postcode":"78411",
    "sg:province":"TX",
    "wof:name":"Tim Voorkamp",
    "wof:placetype":"venue"
},
  "geometry": {"coordinates":[-97.383477,27.702142],"type":"Point"}
}