{
  "type": "Feature",
  "properties": {
    "iso:country":"US",
    "sg:address":"1810 Bench Mark Dr",
    "sg:city":"Austin",
    "sg:phone":"+1 512 402 0024",
    "sg:postcode":"78728",
    "sg:province":"TX",
    "wof:name":"Advanced Towing & Recovery",
    "wof:placetype":"venue"
},
  "geometry": {"coordinates":[-97.678523,30.431041],"type":"Point"}
}