{
  "type": "Feature",
  "properties": {
    "iso:country":"US",
    "sg:address":"5547 Pine Pl",
    "sg:city":"Austin",
    "sg:classifiers":[
        {
            "category":"Building & Trades",
            "subcategory":"Construction",
            "type":"Services"
        }
    ],
    "sg:phone":"+1 512 444 0901",
    "sg:postcode":"78744",
    "sg:province":"TX",
    "sg:tags":[
        "house"
    ],
    "wof:name":"Urestis Rmdlg/Rfg",
    "wof:placetype":"venue"
},
  "geometry": {"coordinates":[-97.747719,30.195116],"type":"Point"}
}