{
  "type": "Feature",
  "properties": {
    "iso:country":"US",
    "sg:address":"401 Center Ave",
    "sg:city":"Brownwood",
    "sg:classifiers":[
        {
            "category":"Shopping",
            "subcategory":"Jewelry",
            "type":"Retail Goods"
        }
    ],
    "sg:phone":"+1 325 643 5711",
    "sg:postcode":"76801",
    "sg:province":"TX",
    "wof:name":"Wittig Jewelers",
    "wof:placetype":"venue"
},
  "geometry": {"coordinates":[-98.98252599999999,31.720367],"type":"Point"}
}