{
  "type": "Feature",
  "properties": {
    "iso:country":"US",
    "sg:address":"8411 Tyhurst Dr",
    "sg:city":"Austin",
    "sg:classifiers":[
        {
            "category":"Professional",
            "subcategory":"Business Services",
            "type":"Services"
        }
    ],
    "sg:phone":"+1 512 892 0540",
    "sg:postcode":"78749",
    "sg:province":"TX",
    "wof:name":"Rice Cleaning Solutions",
    "wof:placetype":"venue"
},
  "geometry": {"coordinates":[-97.86678000000001,30.212531],"type":"Point"}
}