{
  "type": "Feature",
  "properties": {
    "iso:country":"US",
    "sg:address":"1231 6th St SE",
    "sg:city":"Paris",
    "sg:classifiers":[
        {
            "category":"Wholesale",
            "subcategory":"Farm Supplies",
            "type":"Manufacturing & Wholesale Goods"
        }
    ],
    "sg:phone":"+1 903 784 6661",
    "sg:postcode":"75460",
    "sg:province":"TX",
    "sg:tags":[
        "fertilizer"
    ],
    "wof:name":"American Plant Food Corp",
    "wof:placetype":"venue"
},
  "geometry": {"coordinates":[-95.550349,33.650678],"type":"Point"}
}