{
  "type": "Feature",
  "properties": {
    "iso:country":"US",
    "sg:address":"4930 Irma Ave",
    "sg:city":"San Antonio",
    "sg:classifiers":[
        {
            "category":"Professional",
            "type":"Services"
        }
    ],
    "sg:phone":"+1 210 433 4532",
    "sg:postcode":"78237",
    "sg:province":"TX",
    "wof:name":"Reyes Oralia",
    "wof:placetype":"venue"
},
  "geometry": {"coordinates":[-98.586082,29.420186],"type":"Point"}
}