{
  "type": "Feature",
  "properties": {
    "iso:country":"US",
    "sg:address":"9806 Diamond Cliff Dr",
    "sg:city":"Helotes",
    "sg:classifiers":[
        {
            "category":"Building & Trades",
            "subcategory":"Equipment Rental",
            "type":"Services"
        }
    ],
    "sg:phone":"+1 210 695 4634",
    "sg:postcode":"78023",
    "sg:province":"TX",
    "wof:name":"Bounce & More",
    "wof:placetype":"venue"
},
  "geometry": {"coordinates":[-98.67489399999999,29.551445],"type":"Point"}
}