{
  "type": "Feature",
  "properties": {
    "iso:country":"US",
    "sg:address":"1818 Independence Pkwy S",
    "sg:city":"La Porte",
    "sg:classifiers":[
        {
            "category":"Food & Beverages",
            "subcategory":"Groceries & Convenience Stores",
            "type":"Retail Goods"
        }
    ],
    "sg:phone":"+1 281 476 1571",
    "sg:postcode":"77571",
    "sg:province":"TX",
    "wof:name":"Total Petroleum",
    "wof:placetype":"venue"
},
  "geometry": {"coordinates":[-95.08973400000001,29.726347],"type":"Point"}
}