{
  "type": "Feature",
  "properties": {
    "iso:country":"US",
    "sg:address":"9269 Scenic Bluff Dr",
    "sg:city":"Austin",
    "sg:classifiers":[
        {
            "category":"Wholesale",
            "subcategory":"Office Equipment",
            "type":"Manufacturing & Wholesale Goods"
        }
    ],
    "sg:phone":"+1 512 402 9315",
    "sg:postcode":"78733",
    "sg:province":"TX",
    "sg:tags":[
        "scanning",
        "code",
        "bar"
    ],
    "wof:name":"ACSIS Inc",
    "wof:placetype":"venue"
},
  "geometry": {"coordinates":[-97.890484,30.304201],"type":"Point"}
}