{
  "type": "Feature",
  "properties": {
    "iso:country":"US",
    "sg:address":"2313 Westforest Dr",
    "sg:city":"Austin",
    "sg:classifiers":[
        {
            "category":"Building & Trades",
            "subcategory":"Cleaning & Sanitation",
            "type":"Services"
        }
    ],
    "sg:phone":"+1 512 444 5505",
    "sg:postcode":"78704",
    "sg:province":"TX",
    "sg:tags":[
        "maintenance"
    ],
    "wof:name":"Sunn Window & Gutter Cleaning",
    "wof:placetype":"venue"
},
  "geometry": {"coordinates":[-97.784274,30.24279],"type":"Point"}
}