{
  "type": "Feature",
  "properties": {
    "iso:country":"US",
    "sg:address":"300 E Belt Line Rd",
    "sg:city":"Desoto",
    "sg:classifiers":[
        {
            "category":"Autos & Motor Vehicles",
            "subcategory":"Auto Supplies",
            "type":"Retail Goods"
        },
        {
            "category":"Retail",
            "subcategory":"Auto Repair",
            "type":"Services"
        }
    ],
    "sg:phone":"+1 972 274 3237",
    "sg:postcode":"75115",
    "sg:province":"TX",
    "sg:tags":[
        "repairing",
        "automobile"
    ],
    "wof:name":"Discount Auto Care",
    "wof:placetype":"venue"
},
  "geometry": {"coordinates":[-96.850168,32.589715],"type":"Point"}
}