{
  "type": "Feature",
  "properties": {
    "iso:country":"US",
    "sg:address":"2808 E 11th St",
    "sg:city":"Dallas",
    "sg:classifiers":[
        {
            "category":"Professional",
            "subcategory":"Lawyer & Legal Services",
            "type":"Services"
        }
    ],
    "sg:phone":"+1 214 946 2421",
    "sg:postcode":"75203",
    "sg:province":"TX",
    "sg:tags":[
        "notary"
    ],
    "wof:name":"Cedar Crest Business Office",
    "wof:placetype":"venue"
},
  "geometry": {"coordinates":[-96.788839,32.746201],"type":"Point"}
}