{
  "type": "Feature",
  "properties": {
    "iso:country":"US",
    "sg:address":"5104 Abbey Glen Dr",
    "sg:city":"Flower Mound",
    "sg:classifiers":[
        {
            "category":"Professional",
            "subcategory":"Detective & Security Services",
            "type":"Services"
        },
        {
            "category":"Professional",
            "subcategory":"Computer Services",
            "type":"Services"
        }
    ],
    "sg:phone":"+1 972 491 2904",
    "sg:postcode":"75028",
    "sg:province":"TX",
    "sg:tags":[
        "information",
        "investigating",
        "retrieval",
        "private",
        "investigator"
    ],
    "sg:website":"www.investigativeassociates.com",
    "wof:name":"Investigative Associates Inc",
    "wof:placetype":"venue"
},
  "geometry": {"coordinates":[-97.089664,33.056504],"type":"Point"}
}