{
  "type": "Feature",
  "properties": {
    "iso:country":"US",
    "sg:address":"5619 Longshadow Dr",
    "sg:city":"Dickinson",
    "sg:classifiers":[
        {
            "category":"Building & Trades",
            "subcategory":"Construction",
            "type":"Services"
        }
    ],
    "sg:phone":"+1 281 534 8863",
    "sg:postcode":"77539",
    "sg:province":"TX",
    "sg:tags":[
        "house"
    ],
    "wof:name":"Greenough Construction",
    "wof:placetype":"venue"
},
  "geometry": {"coordinates":[-95.054889,29.447621],"type":"Point"}
}