{
  "type": "Feature",
  "properties": {
    "iso:country":"US",
    "sg:address":"1911 E Division St",
    "sg:city":"Arlington",
    "sg:classifiers":[
        {
            "category":"Autos & Motor Vehicles",
            "subcategory":"Automobile Sales",
            "type":"Retail Goods"
        }
    ],
    "sg:phone":"+1 817 469 1945",
    "sg:postcode":"76011",
    "sg:province":"TX",
    "sg:tags":[
        "car",
        "dealer"
    ],
    "wof:name":"Texans Can Cars",
    "wof:placetype":"venue"
},
  "geometry": {"coordinates":[-97.076419,32.742753],"type":"Point"}
}