{
  "type": "Feature",
  "properties": {
    "iso:country":"US",
    "sg:address":"401 E Lufkin Ave",
    "sg:city":"Lufkin",
    "sg:classifiers":[
        {
            "category":"Personal",
            "subcategory":"Beauty Salon",
            "type":"Services"
        }
    ],
    "sg:phone":"+1 936 639 2005",
    "sg:postcode":"75901",
    "sg:province":"TX",
    "wof:name":"Sassy Reds",
    "wof:placetype":"venue"
},
  "geometry": {"coordinates":[-94.72554,31.33811],"type":"Point"}
}