{
  "type": "Feature",
  "properties": {
    "iso:country":"US",
    "sg:address":"5601 Irvington Blvd",
    "sg:city":"Houston",
    "sg:classifiers":[
        {
            "category":"Professional",
            "subcategory":"Lawyer & Legal Services",
            "type":"Services"
        }
    ],
    "sg:phone":"+1 713 742 6500",
    "sg:postcode":"77009",
    "sg:province":"TX",
    "sg:tags":[
        "attorney"
    ],
    "wof:name":"H V Villegas & Co",
    "wof:placetype":"venue"
},
  "geometry": {"coordinates":[-95.36121,29.810924],"type":"Point"}
}