{
  "type": "Feature",
  "properties": {
    "iso:country":"US",
    "sg:address":"201 Wilcrest Dr",
    "sg:city":"Houston",
    "sg:classifiers":[
        {
            "category":"Professional",
            "subcategory":"Printing & Photocopies",
            "type":"Services"
        }
    ],
    "sg:phone":"+1 713 334 9028",
    "sg:postcode":"77042",
    "sg:province":"TX",
    "sg:tags":[
        "photocopying"
    ],
    "wof:name":"Gh Copier Service",
    "wof:placetype":"venue"
},
  "geometry": {"coordinates":[-95.57601099999999,29.76586],"type":"Point"}
}