{
  "type": "Feature",
  "properties": {
    "iso:country":"US",
    "sg:address":"16073 Treasure Cove",
    "sg:city":"Bullard",
    "sg:classifiers":[
        {
            "category":"Professional",
            "type":"Services"
        }
    ],
    "sg:phone":"+1 903 825 6256",
    "sg:postcode":"75757",
    "sg:province":"TX",
    "wof:name":"Transamerica Real Est Tax Svc",
    "wof:placetype":"venue"
},
  "geometry": {"coordinates":[-95.43819999999999,32.139171],"type":"Point"}
}