{
  "type": "Feature",
  "properties": {
    "iso:country":"US",
    "sg:address":"505 W Wheatland Rd",
    "sg:city":"Duncanville",
    "sg:classifiers":[
        {
            "category":"Health Services",
            "subcategory":"Doctor",
            "type":"Services"
        }
    ],
    "sg:phone":"+1 972 298 8997",
    "sg:postcode":"75116",
    "sg:province":"TX",
    "sg:tags":[
        "surgeon",
        "oral"
    ],
    "sg:website":"www.rodneycookdds.com",
    "wof:name":"Cook Rodney W DDS",
    "wof:placetype":"venue"
},
  "geometry": {"coordinates":[-96.91770200000001,32.646],"type":"Point"}
}