{
  "type": "Feature",
  "properties": {
    "iso:country":"US",
    "sg:address":"2605 19th St",
    "sg:city":"Hondo",
    "sg:classifiers":[
        {
            "category":"Retail",
            "subcategory":"Auto Repair",
            "type":"Services"
        }
    ],
    "sg:phone":"+1 830 426 4777",
    "sg:postcode":"78861",
    "sg:province":"TX",
    "sg:tags":[
        "general"
    ],
    "wof:name":"H Town Automotive & Performanc",
    "wof:placetype":"venue"
},
  "geometry": {"coordinates":[-99.15689999999999,29.345979],"type":"Point"}
}