{
  "type": "Feature",
  "properties": {
    "iso:country":"US",
    "sg:address":"234 Nas Dr",
    "sg:city":"Corpus Christi",
    "sg:classifiers":[
        {
            "category":"Autos & Motor Vehicles",
            "subcategory":"Automobile Sales",
            "type":"Retail Goods"
        }
    ],
    "sg:phone":"+1 361 937 5900",
    "sg:postcode":"78418",
    "sg:province":"TX",
    "sg:tags":[
        "car",
        "dealer"
    ],
    "wof:name":"Ace Motor Sales",
    "wof:placetype":"venue"
},
  "geometry": {"coordinates":[-97.275723,27.679112],"type":"Point"}
}