{
  "type": "Feature",
  "properties": {
    "iso:country":"US",
    "sg:address":"110 N Clark Rd",
    "sg:city":"Cedar Hill",
    "sg:classifiers":[
        {
            "category":"Autos & Motor Vehicles",
            "subcategory":"Auto Supplies",
            "type":"Retail Goods"
        }
    ],
    "sg:phone":"+1 972 293 2222",
    "sg:postcode":"75104",
    "sg:province":"TX",
    "sg:tags":[
        "tire"
    ],
    "wof:name":"American Auto Repair & Tire",
    "wof:placetype":"venue"
},
  "geometry": {"coordinates":[-96.9422,32.5905],"type":"Point"}
}