{
  "type": "Feature",
  "properties": {
    "iso:country":"US",
    "sg:address":"4115 Spring Ave",
    "sg:city":"Dallas",
    "sg:classifiers":[
        {
            "category":"Organizations",
            "subcategory":"Religious Organization",
            "type":"Services"
        }
    ],
    "sg:phone":"+1 214 565 9204",
    "sg:postcode":"75210",
    "sg:province":"TX",
    "wof:name":"Ekklesia Mssnary Baptst Church",
    "wof:placetype":"venue"
},
  "geometry": {"coordinates":[-96.74618599999999,32.771409],"type":"Point"}
}