{
  "type": "Feature",
  "properties": {
    "iso:country":"US",
    "sg:address":"5206 Mimosa Ln",
    "sg:city":"Richmond",
    "sg:classifiers":[
        {
            "category":"Restaurant",
            "type":"Food & Drink"
        }
    ],
    "sg:phone":"+1 281 342 0355",
    "sg:postcode":"77469",
    "sg:province":"TX",
    "sg:tags":[
        "eating"
    ],
    "wof:name":"Captain Toms Sea Fd Oyster Bar",
    "wof:placetype":"venue"
},
  "geometry": {"coordinates":[-95.790391,29.639017],"type":"Point"}
}