{
  "type": "Feature",
  "properties": {
    "iso:country":"US",
    "sg:address":"1717 Main St",
    "sg:city":"Dallas",
    "sg:classifiers":[
        {
            "category":"Professional",
            "subcategory":"Management & Consulting",
            "type":"Services"
        }
    ],
    "sg:phone":"+1 214 758 1880",
    "sg:postcode":"75201",
    "sg:province":"TX",
    "sg:tags":[
        "consultant"
    ],
    "wof:name":"Mercer Mngt Consulting",
    "wof:placetype":"venue"
},
  "geometry": {"coordinates":[-96.795799,32.781431],"type":"Point"}
}