{
  "type": "Feature",
  "properties": {
    "iso:country":"US",
    "sg:address":"8241 W FM 455",
    "sg:city":"Celina",
    "sg:classifiers":[
        {
            "category":"Shopping",
            "subcategory":"Clothing, Apparel, & Fashions",
            "type":"Retail Goods"
        }
    ],
    "sg:phone":"+1 972 382 2140",
    "sg:postcode":"75009",
    "sg:province":"TX",
    "sg:tags":[
        "cloth",
        "work",
        "mfg"
    ],
    "wof:name":"8241 Ranch Designs",
    "wof:placetype":"venue"
},
  "geometry": {"coordinates":[-96.70661699999999,33.34456],"type":"Point"}
}