{
  "type": "Feature",
  "properties": {
    "iso:country":"US",
    "sg:address":"2120 E Southlake Blvd",
    "sg:city":"Southlake",
    "sg:classifiers":[
        {
            "category":"Restaurant",
            "type":"Food & Drink"
        }
    ],
    "sg:phone":"+1 817 488 5144",
    "sg:postcode":"76092",
    "sg:province":"TX",
    "sg:tags":[
        "eating"
    ],
    "wof:name":"ME & Eds Pizza",
    "wof:placetype":"venue"
},
  "geometry": {"coordinates":[-97.121287,32.941045],"type":"Point"}
}