{
  "type": "Feature",
  "properties": {
    "iso:country":"US",
    "sg:address":"8325 Broadway St",
    "sg:city":"Pearland",
    "sg:classifiers":[
        {
            "category":"Professional",
            "subcategory":"Management & Consulting",
            "type":"Services"
        }
    ],
    "sg:phone":"+1 281 489 1201",
    "sg:postcode":"77581",
    "sg:province":"TX",
    "sg:tags":[
        "consultant",
        "financial"
    ],
    "wof:name":"Applied Resource Partners",
    "wof:placetype":"venue"
},
  "geometry": {"coordinates":[-95.347763,29.559079],"type":"Point"}
}