{
  "type": "Feature",
  "properties": {
    "iso:country":"US",
    "sg:address":"12577 FM 16 W",
    "sg:city":"Lindale",
    "sg:classifiers":[
        {
            "category":"Social Services",
            "subcategory":"Child Care",
            "type":"Services"
        }
    ],
    "sg:phone":"+1 903 882 8152",
    "sg:postcode":"75771",
    "sg:province":"TX",
    "sg:tags":[
        "day"
    ],
    "wof:name":"Little Britches Day Care",
    "wof:placetype":"venue"
},
  "geometry": {"coordinates":[-95.37415900000001,32.51658],"type":"Point"}
}