{
  "type": "Feature",
  "properties": {
    "iso:country":"US",
    "sg:address":"3303 Lanarc Dr",
    "sg:city":"Plano",
    "sg:classifiers":[
        {
            "category":"Real Estate",
            "subcategory":"Real Estate Agent",
            "type":"Services"
        }
    ],
    "sg:phone":"+1 972 596 6900",
    "sg:postcode":"75023",
    "sg:province":"TX",
    "wof:name":"Signatures Hoems LLC",
    "wof:placetype":"venue"
},
  "geometry": {"coordinates":[-96.757148,33.04114],"type":"Point"}
}