{
  "type": "Feature",
  "properties": {
    "iso:country":"US",
    "sg:address":"200 E Nopal St",
    "sg:city":"Uvalde",
    "sg:classifiers":[
        {
            "category":"Professional",
            "subcategory":"Business Services",
            "type":"Services"
        }
    ],
    "sg:phone":"+1 830 278 8242",
    "sg:postcode":"78801",
    "sg:province":"TX",
    "sg:tags":[
        "water",
        "conservation"
    ],
    "wof:name":"Underground Water Conservation",
    "wof:placetype":"venue"
},
  "geometry": {"coordinates":[-99.782731,29.212342],"type":"Point"}
}