{
  "type": "Feature",
  "properties": {
    "iso:country":"US",
    "sg:address":"5980 Kensington Dr",
    "sg:city":"Plano",
    "sg:classifiers":[
        {
            "category":"Manufacturing",
            "subcategory":"Electronics",
            "type":"Manufacturing & Wholesale Goods"
        }
    ],
    "sg:phone":"+1 972 378 9160",
    "sg:postcode":"75093",
    "sg:province":"TX",
    "sg:tags":[
        "electronic",
        "component",
        "mfg"
    ],
    "wof:name":"South East Engineering Assoc",
    "wof:placetype":"venue"
},
  "geometry": {"coordinates":[-96.82566199999999,33.04187],"type":"Point"}
}