{
  "type": "Feature",
  "properties": {
    "iso:country":"US",
    "sg:address":"642 Brunswick Blvd",
    "sg:city":"San Antonio",
    "sg:classifiers":[
        {
            "category":"Building & Trades",
            "subcategory":"Plumbing",
            "type":"Services"
        }
    ],
    "sg:phone":"+1 210 771 5625",
    "sg:postcode":"78214",
    "sg:province":"TX",
    "sg:tags":[
        "conditioning",
        "air",
        "system",
        "contractor"
    ],
    "wof:name":"ACH Air",
    "wof:placetype":"venue"
},
  "geometry": {"coordinates":[-98.51018000000001,29.371182],"type":"Point"}
}