{
  "type": "Feature",
  "properties": {
    "iso:country":"US",
    "sg:address":"2791 Ridge Rd",
    "sg:city":"Rockwall",
    "sg:classifiers":[
        {
            "category":"Shopping",
            "subcategory":"Computers & Home Electronics",
            "type":"Retail Goods"
        }
    ],
    "sg:phone":"+1 972 722 3378",
    "sg:postcode":"75032",
    "sg:province":"TX",
    "wof:name":"Gamestop",
    "wof:placetype":"venue"
},
  "geometry": {"coordinates":[-96.47339599999999,32.887946],"type":"Point"}
}