{
  "type": "Feature",
  "properties": {
    "iso:country":"US",
    "sg:address":"7230 Colima Dr",
    "sg:city":"Houston",
    "sg:classifiers":[
        {
            "category":"Arts & Performance",
            "subcategory":"Theater",
            "type":"Entertainment"
        }
    ],
    "sg:phone":"+1 281 277 7596",
    "sg:postcode":"77083",
    "sg:province":"TX",
    "sg:tags":[
        "group"
    ],
    "wof:name":"Isla De Patmos",
    "wof:placetype":"venue"
},
  "geometry": {"coordinates":[-95.682743,29.698081],"type":"Point"}
}