{
  "type": "Feature",
  "properties": {
    "iso:country":"US",
    "sg:address":"9710 Cottle Dr",
    "sg:city":"Austin",
    "sg:classifiers":[
        {
            "category":"Wholesale",
            "subcategory":"Music Publishers",
            "type":"Manufacturing & Wholesale Goods"
        }
    ],
    "sg:phone":"+1 512 835 9101",
    "sg:postcode":"78753",
    "sg:province":"TX",
    "sg:tags":[
        "distribution"
    ],
    "wof:name":"Je Sa Music",
    "wof:placetype":"venue"
},
  "geometry": {"coordinates":[-97.680035,30.358069],"type":"Point"}
}