{
  "type": "Feature",
  "properties": {
    "iso:country":"US",
    "sg:address":"1126 W Borgfeld Rd",
    "sg:city":"Bulverde",
    "sg:classifiers":[
        {
            "category":"Government",
            "subcategory":"Fire Station",
            "type":"Public Place"
        }
    ],
    "sg:phone":"+1 830 980 4733",
    "sg:postcode":"78108",
    "sg:province":"TX",
    "sg:tags":[
        "department"
    ],
    "wof:name":"Bexar Bulverde Vfd",
    "wof:placetype":"venue"
},
  "geometry": {"coordinates":[-98.240664,29.571362],"type":"Point"}
}