{
  "type": "Feature",
  "properties": {
    "iso:country":"US",
    "sg:address":"2633 76th St",
    "sg:city":"Lubbock",
    "sg:classifiers":[
        {
            "category":"Personal",
            "subcategory":"Beauty Salon",
            "type":"Services"
        }
    ],
    "sg:phone":"+1 806 745 1495",
    "sg:postcode":"79423",
    "sg:province":"TX",
    "wof:name":"Leon J Hanlon & Betty Jo",
    "wof:placetype":"venue"
},
  "geometry": {"coordinates":[-101.872165,33.525019],"type":"Point"}
}