{
  "type": "Feature",
  "properties": {
    "iso:country":"US",
    "sg:address":"10800 Sharpview Dr",
    "sg:city":"Houston",
    "sg:classifiers":[
        {
            "category":"Organizations",
            "subcategory":"Religious Organization",
            "type":"Services"
        }
    ],
    "sg:phone":"+1 281 498 1370",
    "sg:postcode":"77072",
    "sg:province":"TX",
    "wof:name":"Wilcrest Baptist Church",
    "wof:placetype":"venue"
},
  "geometry": {"coordinates":[-95.569914,29.699201],"type":"Point"}
}