{
  "type": "Feature",
  "properties": {
    "iso:country":"US",
    "sg:address":"10500 Valley Forge Dr",
    "sg:city":"Houston",
    "sg:classifiers":[
        {
            "category":"Professional",
            "subcategory":"Business Services",
            "type":"Services"
        }
    ],
    "sg:phone":"+1 713 783 6418",
    "sg:postcode":"77042",
    "sg:province":"TX",
    "wof:name":"Catapolte Development Solution",
    "wof:placetype":"venue"
},
  "geometry": {"coordinates":[-95.563215,29.750272],"type":"Point"}
}