{
  "type": "Feature",
  "properties": {
    "iso:country":"US",
    "sg:address":"1981 Fort Worth Ave",
    "sg:city":"Dallas",
    "sg:classifiers":[
        {
            "category":"Restaurant",
            "type":"Food & Drink"
        }
    ],
    "sg:menulink":"http://www.allmenus.com/tx/southwest/192017-wendys/menu/",
    "sg:phone":"+1 214 948 7905",
    "sg:postcode":"75208",
    "sg:province":"TX",
    "sg:tags":[
        "burger",
        "american",
        "soup"
    ],
    "wof:name":"Wendy's",
    "wof:placetype":"venue"
},
  "geometry": {"coordinates":[-96.853931,32.763747],"type":"Point"}
}