{
  "type": "Feature",
  "properties": {
    "iso:country":"US",
    "sg:address":"103 E Pecan St",
    "sg:city":"Celina",
    "sg:classifiers":[
        {
            "category":"Food & Beverages",
            "subcategory":"Groceries & Convenience Stores",
            "type":"Retail Goods"
        }
    ],
    "sg:phone":"+1 972 382 2162",
    "sg:postcode":"75009",
    "sg:province":"TX",
    "sg:website":"www.stop-n-go.com",
    "wof:name":"Bobcat Kuntry Stop & Go",
    "wof:placetype":"venue"
},
  "geometry": {"coordinates":[-96.784148,33.324548],"type":"Point"}
}