{
  "type": "Feature",
  "properties": {
    "iso:country":"US",
    "sg:address":"1629 E Houston St",
    "sg:city":"San Antonio",
    "sg:classifiers":[
        {
            "category":"Banks & Credit Unions",
            "subcategory":"Bank",
            "type":"Services"
        }
    ],
    "sg:phone":"+1 210 270 9780",
    "sg:postcode":"78202",
    "sg:province":"TX",
    "sg:tags":[
        "cashing",
        "check"
    ],
    "wof:name":"Tax Cash Express",
    "wof:placetype":"venue"
},
  "geometry": {"coordinates":[-98.47214,29.425139],"type":"Point"}
}