{
  "type": "Feature",
  "properties": {
    "iso:country":"US",
    "sg:address":"110 Nelson Dr",
    "sg:city":"Copperas Cove",
    "sg:classifiers":[
        {
            "category":"Shopping",
            "subcategory":"Clothing, Apparel, & Fashions",
            "type":"Retail Goods"
        }
    ],
    "sg:phone":"+1 254 542 2830",
    "sg:postcode":"76522",
    "sg:province":"TX",
    "wof:name":"On & Poppin Fashions",
    "wof:placetype":"venue"
},
  "geometry": {"coordinates":[-97.890953,31.130493],"type":"Point"}
}