{
  "type": "Feature",
  "properties": {
    "iso:country":"US",
    "sg:address":"202 Walker St",
    "sg:city":"Waco",
    "sg:classifiers":[
        {
            "category":"Shopping",
            "subcategory":"Clothing, Apparel, & Fashions",
            "type":"Retail Goods"
        }
    ],
    "sg:phone":"+1 254 867 8023",
    "sg:postcode":"76704",
    "sg:province":"TX",
    "wof:name":"First Lady",
    "wof:placetype":"venue"
},
  "geometry": {"coordinates":[-97.115329,31.576714],"type":"Point"}
}