{
  "type": "Feature",
  "properties": {
    "iso:country":"US",
    "sg:address":"5527 100th St",
    "sg:city":"Lubbock",
    "sg:classifiers":[
        {
            "category":"Shopping",
            "subcategory":"Clothing, Apparel, & Fashions",
            "type":"Retail Goods"
        }
    ],
    "sg:phone":"+1 806 794 1217",
    "sg:postcode":"79424",
    "sg:province":"TX",
    "sg:tags":[
        "wear"
    ],
    "wof:name":"Little Princess Dress Shop",
    "wof:placetype":"venue"
},
  "geometry": {"coordinates":[-101.934032,33.503292],"type":"Point"}
}