{
  "type": "Feature",
  "properties": {
    "iso:country":"US",
    "sg:address":"424 Tennessee St",
    "sg:city":"Graham",
    "sg:classifiers":[
        {
            "category":"Shopping",
            "subcategory":"Discount & Variety Stores",
            "type":"Retail Goods"
        }
    ],
    "sg:phone":"+1 940 549 2580",
    "sg:postcode":"76450",
    "sg:province":"TX",
    "wof:name":"Laura Mayes Variety Store",
    "wof:placetype":"venue"
},
  "geometry": {"coordinates":[-98.579381,33.107958],"type":"Point"}
}