{
  "type": "Feature",
  "properties": {
    "iso:country":"US",
    "sg:address":"5401 Exeter Dr",
    "sg:city":"Richardson",
    "sg:classifiers":[
        {
            "category":"Shopping",
            "subcategory":"Gifts & Souvenirs",
            "type":"Retail Goods"
        }
    ],
    "sg:phone":"+1 972 231 2327",
    "sg:postcode":"75082",
    "sg:province":"TX",
    "wof:name":"Unique Creations",
    "wof:placetype":"venue"
},
  "geometry": {"coordinates":[-96.62088799999999,32.996865],"type":"Point"}
}