{
  "type": "Feature",
  "properties": {
    "iso:country":"US",
    "sg:address":"701 E 55th St",
    "sg:city":"Austin",
    "sg:classifiers":[
        {
            "category":"Autos & Motor Vehicles",
            "subcategory":"Auto Supplies",
            "type":"Retail Goods"
        }
    ],
    "sg:phone":"+1 512 454 9515",
    "sg:postcode":"78751",
    "sg:province":"TX",
    "sg:tags":[
        "automobile",
        "parts"
    ],
    "wof:name":"Leif Johnson Parts Superstore",
    "wof:placetype":"venue"
},
  "geometry": {"coordinates":[-97.71412100000001,30.317126],"type":"Point"}
}