{
  "type": "Feature",
  "properties": {
    "iso:country":"US",
    "sg:address":"3118 Lausanne Ave",
    "sg:city":"Pasadena",
    "sg:classifiers":[
        {
            "category":"Real Estate",
            "subcategory":"Real Estate Operator",
            "type":"Services"
        }
    ],
    "sg:phone":"+1 281 487 5122",
    "sg:postcode":"77505",
    "sg:province":"TX",
    "sg:tags":[
        "mobile",
        "home",
        "site"
    ],
    "wof:name":"Mark Styrin",
    "wof:placetype":"venue"
},
  "geometry": {"coordinates":[-95.17120199999999,29.662859],"type":"Point"}
}