{
  "type": "Feature",
  "properties": {
    "iso:country":"US",
    "sg:address":"6322 W 34th St",
    "sg:city":"Houston",
    "sg:classifiers":[
        {
            "category":"Manufacturing",
            "subcategory":"Metals",
            "type":"Manufacturing & Wholesale Goods"
        }
    ],
    "sg:phone":"+1 713 686 4325",
    "sg:postcode":"77092",
    "sg:province":"TX",
    "sg:tags":[
        "steel",
        "fabricates",
        "erects",
        "structural"
    ],
    "wof:name":"Hollywood Steel Inc",
    "wof:placetype":"venue"
},
  "geometry": {"coordinates":[-95.483266,29.818336],"type":"Point"}
}