{
  "type": "Feature",
  "properties": {
    "iso:country":"US",
    "sg:address":"526 E Commerce St",
    "sg:city":"Fairfield",
    "sg:classifiers":[
        {
            "category":"Health Services",
            "subcategory":"Doctor",
            "type":"Services"
        }
    ],
    "sg:phone":"+1 903 389 5885",
    "sg:postcode":"75840",
    "sg:province":"TX",
    "sg:tags":[
        "physician",
        "cardiology",
        "thoracic",
        "surgeons",
        "surgeon",
        "surgery",
        "cardiovascular"
    ],
    "wof:name":"McFarlane Robert F MD",
    "wof:placetype":"venue"
},
  "geometry": {"coordinates":[-96.152438,31.72515],"type":"Point"}
}