{
  "type": "Feature",
  "properties": {
    "iso:country":"US",
    "sg:address":"1015 S Hollow Dr",
    "sg:city":"Southlake",
    "sg:classifiers":[
        {
            "category":"Professional",
            "subcategory":"Business Services",
            "type":"Services"
        }
    ],
    "sg:phone":"+1 817 424 5752",
    "sg:postcode":"76092",
    "sg:province":"TX",
    "wof:name":"Kcnd Enterprises",
    "wof:placetype":"venue"
},
  "geometry": {"coordinates":[-97.12568899999999,32.928713],"type":"Point"}
}