{
  "type": "Feature",
  "properties": {
    "iso:country":"US",
    "sg:address":"1801 W Farmers Ave",
    "sg:city":"Amarillo",
    "sg:classifiers":[
        {
            "category":"Railroad",
            "type":"Transportation"
        }
    ],
    "sg:phone":"+1 806 374 3946",
    "sg:postcode":"79118",
    "sg:province":"TX",
    "wof:name":"BNSF Railway Co",
    "wof:placetype":"venue"
},
  "geometry": {"coordinates":[-101.85323099999999,35.134916],"type":"Point"}
}