{
  "type": "Feature",
  "properties": {
    "iso:country":"US",
    "sg:address":"9800 Brown Ln",
    "sg:city":"Austin",
    "sg:classifiers":[
        {
            "category":"Home & Garden",
            "subcategory":"Garden Supply",
            "type":"Retail Goods"
        }
    ],
    "sg:phone":"+1 512 491 6799",
    "sg:postcode":"78754",
    "sg:province":"TX",
    "sg:tags":[
        "nursery",
        "gardening"
    ],
    "wof:name":"Maldonado Nursery & Landscaping",
    "wof:placetype":"venue"
},
  "geometry": {"coordinates":[-97.668105,30.353464],"type":"Point"}
}