{
  "type": "Feature",
  "properties": {
    "iso:country":"US",
    "sg:address":"2900 Smith St",
    "sg:city":"Houston",
    "sg:classifiers":[
        {
            "category":"Professional",
            "subcategory":"Lawyer & Legal Services",
            "type":"Services"
        }
    ],
    "sg:phone":"+1 713 237 0654",
    "sg:postcode":"77006",
    "sg:province":"TX",
    "wof:name":"Law Office",
    "wof:placetype":"venue"
},
  "geometry": {"coordinates":[-95.379577,29.744868],"type":"Point"}
}