{
  "type": "Feature",
  "properties": {
    "iso:country":"US",
    "sg:address":"7511 FM 1960 W",
    "sg:city":"Houston",
    "sg:classifiers":[
        {
            "category":"Restaurant",
            "type":"Food & Drink"
        }
    ],
    "sg:phone":"+1 281 469 6476",
    "sg:postcode":"77070",
    "sg:province":"TX",
    "wof:name":"Fuddruckers",
    "wof:placetype":"venue"
},
  "geometry": {"coordinates":[-95.541327,29.964796],"type":"Point"}
}