{
  "type": "Feature",
  "properties": {
    "iso:country":"US",
    "sg:address":"4011 S FM 1752",
    "sg:city":"Savoy",
    "sg:classifiers":[
        {
            "category":"Building & Trades",
            "subcategory":"Construction",
            "type":"Services"
        }
    ],
    "sg:phone":"+1 903 965 4341",
    "sg:postcode":"75479",
    "sg:province":"TX",
    "sg:tags":[
        "contractor"
    ],
    "wof:name":"Taylor Jt Contractor",
    "wof:placetype":"venue"
},
  "geometry": {"coordinates":[-96.346785,33.56189],"type":"Point"}
}