{
  "type": "Feature",
  "properties": {
    "iso:country":"US",
    "sg:address":"1221 McKinney St",
    "sg:city":"Houston",
    "sg:classifiers":[
        {
            "category":"Banks & Credit Unions",
            "subcategory":"Investment Brokerage",
            "type":"Services"
        },
        {
            "category":"Professional",
            "subcategory":"Business Services",
            "type":"Services"
        }
    ],
    "sg:phone":"+1 713 839 6200",
    "sg:postcode":"77010",
    "sg:province":"TX",
    "sg:tags":[
        "advisory",
        "financial"
    ],
    "wof:name":"Chiron Financial Group Inc",
    "wof:placetype":"venue"
},
  "geometry": {"coordinates":[-95.362437,29.755558],"type":"Point"}
}