{
  "type": "Feature",
  "properties": {
    "iso:country":"US",
    "sg:address":"1401 E Marshall Ave",
    "sg:city":"Longview",
    "sg:classifiers":[
        {
            "category":"Autos & Motor Vehicles",
            "subcategory":"Automobile Sales",
            "type":"Retail Goods"
        }
    ],
    "sg:phone":"+1 903 757 3645",
    "sg:postcode":"75601",
    "sg:province":"TX",
    "sg:tags":[
        "car",
        "dealer"
    ],
    "wof:name":"East End Auto Sales",
    "wof:placetype":"venue"
},
  "geometry": {"coordinates":[-94.71550499999999,32.50441],"type":"Point"}
}