{
  "type": "Feature",
  "properties": {
    "iso:country":"US",
    "sg:address":"1662 N Valley Pkwy",
    "sg:city":"Lewisville",
    "sg:classifiers":[
        {
            "category":"Professional",
            "subcategory":"Business Services",
            "type":"Services"
        }
    ],
    "sg:phone":"+1 972 221 0577",
    "sg:postcode":"75077",
    "sg:province":"TX",
    "wof:name":"Stencileo Interiors",
    "wof:placetype":"venue"
},
  "geometry": {"coordinates":[-97.04231,33.059998],"type":"Point"}
}