{
  "type": "Feature",
  "properties": {
    "iso:country":"US",
    "sg:address":"1300 Olive St",
    "sg:city":"Baytown",
    "sg:classifiers":[
        {
            "category":"Shopping",
            "subcategory":"Music",
            "type":"Retail Goods"
        }
    ],
    "sg:phone":"+1 281 427 7290",
    "sg:postcode":"77520",
    "sg:province":"TX",
    "wof:name":"First Choice Records",
    "wof:placetype":"venue"
},
  "geometry": {"coordinates":[-94.949682,29.734517],"type":"Point"}
}