{
  "type": "Feature",
  "properties": {
    "iso:country":"US",
    "sg:address":"200 W Cesar Chavez St",
    "sg:city":"Austin",
    "sg:classifiers":[
        {
            "category":"Train Station",
            "subcategory":"Rail",
            "type":"Transportation"
        }
    ],
    "sg:phone":"+1 512 480 0549",
    "sg:postcode":"78701",
    "sg:province":"TX",
    "sg:tags":[
        "equipment",
        "part",
        "tractor"
    ],
    "wof:name":"Caterpillar",
    "wof:placetype":"venue"
},
  "geometry": {"coordinates":[-97.74588,30.26368],"type":"Point"}
}