{
  "type": "Feature",
  "properties": {
    "iso:country":"US",
    "sg:address":"4445 N Mesa St",
    "sg:city":"El Paso",
    "sg:classifiers":[
        {
            "category":"Banks & Credit Unions",
            "subcategory":"Bank",
            "type":"Services"
        }
    ],
    "sg:phone":"+1 915 532 1077",
    "sg:postcode":"79902",
    "sg:province":"TX",
    "sg:tags":[
        "short",
        "institution",
        "business"
    ],
    "wof:name":"Ford",
    "wof:placetype":"venue"
},
  "geometry": {"coordinates":[-106.510876,31.799601],"type":"Point"}
}