{
  "type": "Feature",
  "properties": {
    "iso:country":"US",
    "sg:address":"5132 Bragg Ave",
    "sg:city":"El Paso",
    "sg:classifiers":[
        {
            "category":"Shopping",
            "subcategory":"Used Merchandise",
            "type":"Retail Goods"
        }
    ],
    "sg:phone":"+1 915 757 0628",
    "sg:postcode":"79904",
    "sg:province":"TX",
    "wof:name":"Catalina Valenzuela Ortiz",
    "wof:placetype":"venue"
},
  "geometry": {"coordinates":[-106.41838799999999,31.853867],"type":"Point"}
}