{
  "type": "Feature",
  "properties": {
    "iso:country":"US",
    "sg:address":"1124 Griggs Ave",
    "sg:city":"Fort Worth",
    "sg:classifiers":[
        {
            "category":"Building & Trades",
            "subcategory":"Landscaping Services",
            "type":"Services"
        }
    ],
    "sg:phone":"+1 817 534 4350",
    "sg:postcode":"76105",
    "sg:province":"TX",
    "sg:tags":[
        "landscape",
        "contractor"
    ],
    "wof:name":"Outdoor Concepts Corp",
    "wof:placetype":"venue"
},
  "geometry": {"coordinates":[-97.25833799999999,32.731632],"type":"Point"}
}