{
  "type": "Feature",
  "properties": {
    "iso:country":"US",
    "sg:address":"3811 Turtle Creek Blvd",
    "sg:city":"Dallas",
    "sg:classifiers":[
        {
            "category":"Professional",
            "subcategory":"Lawyer & Legal Services",
            "type":"Services"
        }
    ],
    "sg:phone":"+1 214 651 4260",
    "sg:postcode":"75219",
    "sg:province":"TX",
    "wof:name":"McLarty Mary Alice",
    "wof:placetype":"venue"
},
  "geometry": {"coordinates":[-96.800623,32.813951],"type":"Point"}
}