{
  "type": "Feature",
  "properties": {
    "iso:country":"US",
    "sg:address":"195 N Clark Rd",
    "sg:city":"Cedar Hill",
    "sg:classifiers":[
        {
            "category":"Social Services",
            "subcategory":"Child Care",
            "type":"Services"
        }
    ],
    "sg:phone":"+1 972 291 3560",
    "sg:postcode":"75104",
    "sg:province":"TX",
    "sg:tags":[
        "day"
    ],
    "wof:name":"La Petite Academy 743",
    "wof:placetype":"venue"
},
  "geometry": {"coordinates":[-96.942241,32.590939],"type":"Point"}
}