{
  "type": "Feature",
  "properties": {
    "iso:country":"US",
    "sg:address":"12005 Ford Rd",
    "sg:city":"Dallas",
    "sg:classifiers":[
        {
            "category":"Deli",
            "type":"Food & Drink"
        },
        {
            "category":"Food & Beverages",
            "subcategory":"Bakery",
            "type":"Retail Goods"
        }
    ],
    "sg:phone":"+1 972 243 0508",
    "sg:postcode":"75234",
    "sg:province":"TX",
    "sg:tags":[
        "sandwich"
    ],
    "wof:name":"Northpoint Deli",
    "wof:placetype":"venue"
},
  "geometry": {"coordinates":[-96.89166299999999,32.914686],"type":"Point"}
}