{
  "type": "Feature",
  "properties": {
    "iso:country":"US",
    "sg:address":"2901 Downing St",
    "sg:city":"Flower Mound",
    "sg:classifiers":[
        {
            "category":"Professional",
            "subcategory":"Computer Services",
            "type":"Services"
        }
    ],
    "sg:phone":"+1 972 539 6907",
    "sg:postcode":"75028",
    "sg:province":"TX",
    "sg:tags":[
        "prepackaged",
        "software"
    ],
    "wof:name":"Duncan Forrest Software",
    "wof:placetype":"venue"
},
  "geometry": {"coordinates":[-97.07503800000001,33.044982],"type":"Point"}
}