{
  "type": "Feature",
  "properties": {
    "iso:country":"US",
    "sg:address":"173 E Price Rd",
    "sg:city":"Brownsville",
    "sg:classifiers":[
        {
            "category":"Professional",
            "subcategory":"Accounting & Tax Preparation",
            "type":"Services"
        }
    ],
    "sg:phone":"+1 956 541 5272",
    "sg:postcode":"78521",
    "sg:province":"TX",
    "wof:name":"Zamora Roberto R",
    "wof:placetype":"venue"
},
  "geometry": {"coordinates":[-97.467433,25.93182],"type":"Point"}
}