{
  "type": "Feature",
  "properties": {
    "iso:country":"US",
    "sg:address":"1014 W Marshall Ave",
    "sg:city":"Longview",
    "sg:classifiers":[
        {
            "category":"Autos & Motor Vehicles",
            "subcategory":"Automobile Sales",
            "type":"Retail Goods"
        }
    ],
    "sg:phone":"+1 903 236 3100",
    "sg:postcode":"75604",
    "sg:province":"TX",
    "wof:name":"Double M Auto Sales",
    "wof:placetype":"venue"
},
  "geometry": {"coordinates":[-94.760474,32.502238],"type":"Point"}
}