{
  "type": "Feature",
  "properties": {
    "iso:country":"US",
    "sg:address":"10231 Belknap Rd",
    "sg:city":"Sugar Land",
    "sg:classifiers":[
        {
            "category":"Wholesale",
            "subcategory":"Machinery & Supplies",
            "type":"Manufacturing & Wholesale Goods"
        }
    ],
    "sg:phone":"+1 281 498 4652",
    "sg:postcode":"77478",
    "sg:province":"TX",
    "sg:tags":[
        "equipment"
    ],
    "wof:name":"Dwc Drilling Equipment LLC",
    "wof:placetype":"venue"
},
  "geometry": {"coordinates":[-95.62311699999999,29.665709],"type":"Point"}
}