{
  "type": "Feature",
  "properties": {
    "iso:country":"US",
    "sg:address":"2406 Mozelle Ln",
    "sg:city":"Austin",
    "sg:classifiers":[
        {
            "category":"Retail",
            "subcategory":"Auto Repair",
            "type":"Services"
        }
    ],
    "sg:phone":"+1 512 280 1563",
    "sg:postcode":"78744",
    "sg:province":"TX",
    "sg:tags":[
        "truck",
        "general"
    ],
    "wof:name":"York's Truck & Trailer",
    "wof:placetype":"venue"
},
  "geometry": {"coordinates":[-97.772181,30.166538],"type":"Point"}
}