{
  "type": "Feature",
  "properties": {
    "iso:country":"US",
    "sg:address":"711 E Taylor St",
    "sg:city":"Sherman",
    "sg:classifiers":[
        {
            "category":"Wholesale",
            "subcategory":"Painting Supplies",
            "type":"Manufacturing & Wholesale Goods"
        },
        {
            "category":"Manufacturing",
            "subcategory":"Tools & Machinery",
            "type":"Manufacturing & Wholesale Goods"
        },
        {
            "category":"Building & Trades",
            "subcategory":"Construction",
            "type":"Services"
        },
        {
            "category":"Home & Garden",
            "subcategory":"Building Materials",
            "type":"Retail Goods"
        },
        {
            "category":"Manufacturing",
            "subcategory":"Chemicals & Compounds",
            "type":"Manufacturing & Wholesale Goods"
        },
        {
            "category":"Autos & Motor Vehicles",
            "subcategory":"Auto Supplies",
            "type":"Retail Goods"
        },
        {
            "category":"Building & Trades",
            "subcategory":"Equipment Rental",
            "type":"Services"
        },
        {
            "category":"Manufacturing",
            "subcategory":"Building Materials",
            "type":"Manufacturing & Wholesale Goods"
        }
    ],
    "sg:phone":"+1 903 893 7481",
    "sg:postcode":"75090",
    "sg:province":"TX",
    "sg:tags":[
        "shop",
        "body",
        "spraying",
        "wall",
        "automobile",
        "wallpaper",
        "coating",
        "improvement",
        "paint-wholesale",
        "paint",
        "wallcoverings-installation",
        "wallcoverings",
        "contractor",
        "equipment-renting",
        "painter",
        "manufacturer"
    ],
    "sg:website":"http://national.citysearch.com/profile/external/9551269/sherman_tx/sherwin_williams.html?publisher=yellowpages&reference_id=1&placement=ypwebsitemip",
    "wof:name":"Sherwin-Williams",
    "wof:placetype":"venue"
},
  "geometry": {"coordinates":[-96.606071,33.657159],"type":"Point"}
}