{
  "type": "Feature",
  "properties": {
    "iso:country":"US",
    "sg:address":"10103 Metronome Dr",
    "sg:city":"Houston",
    "sg:classifiers":[
        {
            "category":"Personal",
            "subcategory":"Beauty Salon",
            "type":"Services"
        }
    ],
    "sg:phone":"+1 713 722 9333",
    "sg:postcode":"77080",
    "sg:province":"TX",
    "sg:tags":[
        "shop"
    ],
    "wof:name":"Cabello",
    "wof:placetype":"venue"
},
  "geometry": {"coordinates":[-95.54121600000001,29.807775],"type":"Point"}
}