{
  "type": "Feature",
  "properties": {
    "iso:country":"US",
    "sg:address":"10606 Sheldon Rd",
    "sg:city":"Houston",
    "sg:classifiers":[
        {
            "category":"Personal",
            "subcategory":"Barber",
            "type":"Services"
        }
    ],
    "sg:phone":"+1 713 451 0003",
    "sg:postcode":"77044",
    "sg:province":"TX",
    "sg:tags":[
        "shop"
    ],
    "wof:name":"H Diamond Trucking",
    "wof:placetype":"venue"
},
  "geometry": {"coordinates":[-95.128146,29.869749],"type":"Point"}
}