{
  "type": "Feature",
  "properties": {
    "iso:country":"US",
    "sg:address":"1350 E Arapaho Rd",
    "sg:city":"Richardson",
    "sg:classifiers":[
        {
            "category":"Professional",
            "subcategory":"Management & Consulting",
            "type":"Services"
        }
    ],
    "sg:phone":"+1 972 470 0807",
    "sg:postcode":"75081",
    "sg:province":"TX",
    "sg:tags":[
        "personnel",
        "consultant"
    ],
    "wof:name":"Cellular Work Staffing",
    "wof:placetype":"venue"
},
  "geometry": {"coordinates":[-96.70156799999999,32.960504],"type":"Point"}
}