{
  "type": "Feature",
  "properties": {
    "iso:country":"US",
    "sg:address":"2121 Ave G",
    "sg:city":"Bay City",
    "sg:classifiers":[
        {
            "category":"Shopping",
            "subcategory":"Jewelry",
            "type":"Retail Goods"
        }
    ],
    "sg:phone":"+1 979 245 2598",
    "sg:postcode":"77414",
    "sg:province":"TX",
    "sg:tags":[
        "store"
    ],
    "wof:name":"Green Bros Jewelers Victoria",
    "wof:placetype":"venue"
},
  "geometry": {"coordinates":[-95.968706,28.982805],"type":"Point"}
}