{
  "type": "Feature",
  "properties": {
    "iso:country":"US",
    "sg:address":"1514 Kincross Ct",
    "sg:city":"Katy",
    "sg:classifiers":[
        {
            "category":"Building & Trades",
            "subcategory":"Construction",
            "type":"Services"
        }
    ],
    "sg:phone":"+1 281 497 4742",
    "sg:postcode":"77450",
    "sg:province":"TX",
    "sg:tags":[
        "heavy"
    ],
    "wof:name":"Pond Works",
    "wof:placetype":"venue"
},
  "geometry": {"coordinates":[-95.76234599999999,29.75916],"type":"Point"}
}