{
  "type": "Feature",
  "properties": {
    "iso:country":"US",
    "sg:address":"3206 Reid Dr",
    "sg:city":"Corpus Christi",
    "sg:classifiers":[
        {
            "category":"Professional",
            "subcategory":"Computer Services",
            "type":"Services"
        }
    ],
    "sg:phone":"+1 361 765 4892",
    "sg:postcode":"78404",
    "sg:province":"TX",
    "sg:tags":[
        "credit",
        "card"
    ],
    "wof:name":"Xpress Payment Solutions",
    "wof:placetype":"venue"
},
  "geometry": {"coordinates":[-97.391637,27.755717],"type":"Point"}
}