{
  "type": "Feature",
  "properties": {
    "iso:country":"US",
    "sg:address":"302 N Market St",
    "sg:city":"Dallas",
    "sg:classifiers":[
        {
            "category":"Professional",
            "subcategory":"Management & Consulting",
            "type":"Services"
        }
    ],
    "sg:phone":"+1 214 720 0642",
    "sg:postcode":"75202",
    "sg:province":"TX",
    "sg:tags":[
        "consultant",
        "business"
    ],
    "wof:name":"Turner Financial Group",
    "wof:placetype":"venue"
},
  "geometry": {"coordinates":[-96.806623,32.781415],"type":"Point"}
}