{
  "type": "Feature",
  "properties": {
    "iso:country":"US",
    "sg:address":"9160 Guilbeau Rd",
    "sg:city":"San Antonio",
    "sg:classifiers":[
        {
            "category":"Banks & Credit Unions",
            "subcategory":"Bank",
            "type":"Services"
        }
    ],
    "sg:phone":"+1 210 518 2500",
    "sg:postcode":"78250",
    "sg:province":"TX",
    "wof:name":"International Bank Of Commerce",
    "wof:placetype":"venue"
},
  "geometry": {"coordinates":[-98.663267,29.518942],"type":"Point"}
}