{
  "type": "Feature",
  "properties": {
    "iso:country":"US",
    "sg:address":"7321 Bear Creek Rd",
    "sg:city":"Aledo",
    "sg:classifiers":[
        {
            "category":"Farming",
            "subcategory":"Livestock Farm",
            "type":"Manufacturing & Wholesale Goods"
        }
    ],
    "sg:phone":"+1 817 441 7382",
    "sg:postcode":"76008",
    "sg:province":"TX",
    "sg:tags":[
        "raw",
        "product",
        "equine"
    ],
    "wof:name":"Moncrief Quarter Horses",
    "wof:placetype":"venue"
},
  "geometry": {"coordinates":[-97.679615,32.657724],"type":"Point"}
}