{
  "type": "Feature",
  "properties": {
    "iso:country":"US",
    "sg:address":"307 Columbia Dr",
    "sg:city":"Rockwall",
    "sg:classifiers":[
        {
            "category":"Professional",
            "subcategory":"Detective & Security Services",
            "type":"Services"
        }
    ],
    "sg:phone":"+1 972 772 9466",
    "sg:postcode":"75032",
    "sg:province":"TX",
    "sg:tags":[
        "car"
    ],
    "wof:name":"Fraud Solutions Inc",
    "wof:placetype":"venue"
},
  "geometry": {"coordinates":[-96.479619,32.879422],"type":"Point"}
}