{
  "type": "Feature",
  "properties": {
    "iso:country":"US",
    "sg:address":"206 Wild Basin Rd",
    "sg:city":"Austin",
    "sg:classifiers":[
        {
            "category":"Park",
            "type":"Public Place"
        }
    ],
    "sg:phone":"+1 512 328 7589",
    "sg:postcode":"78746",
    "sg:province":"TX",
    "wof:name":"Wild Basin Rd Offices",
    "wof:placetype":"venue"
},
  "geometry": {"coordinates":[-97.829283,30.304447],"type":"Point"}
}