{
  "type": "Feature",
  "properties": {
    "iso:country":"US",
    "sg:address":"510 S Big Spring St",
    "sg:city":"Midland",
    "sg:classifiers":[
        {
            "category":"Autos & Motor Vehicles",
            "subcategory":"Auto Supplies",
            "type":"Retail Goods"
        }
    ],
    "sg:phone":"+1 432 682 7971",
    "sg:postcode":"79701",
    "sg:province":"TX",
    "wof:name":"E & D Tire Champion",
    "wof:placetype":"venue"
},
  "geometry": {"coordinates":[-102.077989,31.992317],"type":"Point"}
}