{
  "type": "Feature",
  "properties": {
    "iso:country":"US",
    "sg:address":"17331 Gaucho Dr",
    "sg:city":"Houston",
    "sg:classifiers":[
        {
            "category":"Professional",
            "subcategory":"Computer Services",
            "type":"Services"
        }
    ],
    "sg:phone":"+1 281 277 2176",
    "sg:postcode":"77083",
    "sg:province":"TX",
    "wof:name":"Zbyte Computers",
    "wof:placetype":"venue"
},
  "geometry": {"coordinates":[-95.684517,29.687689],"type":"Point"}
}