{
  "type": "Feature",
  "properties": {
    "iso:country":"US",
    "sg:address":"963 Westwood Rd",
    "sg:city":"Lockhart",
    "sg:classifiers":[
        {
            "category":"Manufacturing",
            "subcategory":"Retail Goods",
            "type":"Manufacturing & Wholesale Goods"
        }
    ],
    "sg:phone":"+1 512 376 9419",
    "sg:postcode":"78644",
    "sg:province":"TX",
    "sg:tags":[
        "manufacturer"
    ],
    "wof:name":"Jewell Wind Flags",
    "wof:placetype":"venue"
},
  "geometry": {"coordinates":[-97.689711,29.812489],"type":"Point"}
}