{
  "type": "Feature",
  "properties": {
    "iso:country":"US",
    "sg:address":"4348 Eastpark Dr",
    "sg:city":"Houston",
    "sg:classifiers":[
        {
            "category":"Wholesale",
            "subcategory":"Scrap",
            "type":"Manufacturing & Wholesale Goods"
        }
    ],
    "sg:phone":"+1 713 672 1227",
    "sg:postcode":"77028",
    "sg:province":"TX",
    "sg:tags":[
        "plastic"
    ],
    "wof:name":"Hugesen Enterprise USA Inc",
    "wof:placetype":"venue"
},
  "geometry": {"coordinates":[-95.29928700000001,29.799349],"type":"Point"}
}