{
  "type": "Feature",
  "properties": {
    "iso:country":"US",
    "sg:address":"12212 State Hwy 31",
    "sg:city":"Tyler",
    "sg:classifiers":[
        {
            "category":"Shopping",
            "subcategory":"Used Merchandise",
            "type":"Retail Goods"
        },
        {
            "category":"Professional",
            "subcategory":"Business Services",
            "type":"Services"
        }
    ],
    "sg:phone":"+1 903 596 7920",
    "sg:postcode":"75709",
    "sg:province":"TX",
    "sg:tags":[
        "flea",
        "market"
    ],
    "wof:name":"Mimi's Flea Market",
    "wof:placetype":"venue"
},
  "geometry": {"coordinates":[-95.36992499999999,32.339799],"type":"Point"}
}