{
  "type": "Feature",
  "properties": {
    "iso:country":"US",
    "sg:address":"6015 Andrews Hwy",
    "sg:city":"Odessa",
    "sg:classifiers":[
        {
            "category":"Professional",
            "type":"Services"
        }
    ],
    "sg:phone":"+1 432 366 2871",
    "sg:postcode":"79762",
    "sg:province":"TX",
    "sg:tags":[
        "establishment"
    ],
    "wof:name":"Rowan Co Inc",
    "wof:placetype":"venue"
},
  "geometry": {"coordinates":[-102.390258,31.898311],"type":"Point"}
}