{
  "type": "Feature",
  "properties": {
    "iso:country":"US",
    "sg:address":"1611 Hart Ct",
    "sg:city":"Southlake",
    "sg:classifiers":[
        {
            "category":"Building & Trades",
            "subcategory":"Construction",
            "type":"Services"
        }
    ],
    "sg:phone":"+1 817 442 4811",
    "sg:postcode":"76092",
    "sg:province":"TX",
    "sg:tags":[
        "house",
        "general",
        "contractor"
    ],
    "wof:name":"Talisman Homes Inc",
    "wof:placetype":"venue"
},
  "geometry": {"coordinates":[-97.12633,32.924059],"type":"Point"}
}