{
  "type": "Feature",
  "properties": {
    "iso:country":"US",
    "sg:address":"1420 W Mockingbird Ln Ste 765",
    "sg:city":"Dallas",
    "sg:classifiers":[
        {
            "category":"Education",
            "subcategory":"University",
            "type":"Public Place"
        }
    ],
    "sg:phone":"+1 214 630 8324",
    "sg:postcode":"75247",
    "sg:province":"TX",
    "sg:tags":[
        "college"
    ],
    "wof:name":"Texas Tech University-Regional Center",
    "wof:placetype":"venue"
},
  "geometry": {"coordinates":[-96.86370100000001,32.822102],"type":"Point"}
}