{
  "type": "Feature",
  "properties": {
    "iso:country":"US",
    "sg:address":"8779 9th Ave",
    "sg:city":"Port Arthur",
    "sg:classifiers":[
        {
            "category":"Health Services",
            "subcategory":"Medical Lab",
            "type":"Services"
        }
    ],
    "sg:phone":"+1 409 729 5548",
    "sg:postcode":"77642",
    "sg:province":"TX",
    "sg:tags":[
        "laboratory"
    ],
    "wof:name":"Quest Diagnostics",
    "wof:placetype":"venue"
},
  "geometry": {"coordinates":[-93.985201,29.95363],"type":"Point"}
}