{
  "type": "Feature",
  "properties": {
    "iso:country":"US",
    "sg:address":"11901 US Hwy 380",
    "sg:city":"Crossroads",
    "sg:classifiers":[
        {
            "category":"Home & Garden",
            "subcategory":"Furniture",
            "type":"Retail Goods"
        }
    ],
    "sg:phone":"+1 940 440 0455",
    "sg:postcode":"76227",
    "sg:province":"TX",
    "wof:name":"Rustic Furniture Depot",
    "wof:placetype":"venue"
},
  "geometry": {"coordinates":[-97.252607,33.235256],"type":"Point"}
}