{
  "type": "Feature",
  "properties": {
    "iso:country":"US",
    "sg:address":"920 N Highway 67",
    "sg:city":"Cedar Hill",
    "sg:classifiers":[
        {
            "category":"Retail",
            "subcategory":"Auto Repair",
            "type":"Services"
        }
    ],
    "sg:phone":"+1 972 293 3488",
    "sg:postcode":"75104",
    "sg:province":"TX",
    "wof:name":"Quality Auto Care",
    "wof:placetype":"venue"
},
  "geometry": {"coordinates":[-96.930199,32.604599],"type":"Point"}
}