{
  "type": "Feature",
  "properties": {
    "iso:country":"US",
    "sg:address":"2922 Esquire Ln",
    "sg:city":"Garland",
    "sg:classifiers":[
        {
            "category":"Professional",
            "subcategory":"Engineering",
            "type":"Services"
        }
    ],
    "sg:phone":"+1 972 231 4551",
    "sg:postcode":"75044",
    "sg:province":"TX",
    "sg:tags":[
        "engineer"
    ],
    "wof:name":"M L Mitchell & Associates",
    "wof:placetype":"venue"
},
  "geometry": {"coordinates":[-96.673388,32.953043],"type":"Point"}
}