{
  "type": "Feature",
  "properties": {
    "iso:country":"US",
    "sg:address":"18 Pinehurst Ct",
    "sg:city":"Missouri City",
    "sg:classifiers":[
        {
            "category":"Insurance",
            "subcategory":"Insurance Agent",
            "type":"Services"
        }
    ],
    "sg:phone":"+1 281 499 2751",
    "sg:postcode":"77459",
    "sg:province":"TX",
    "wof:name":"Forte & Assoc",
    "wof:placetype":"venue"
},
  "geometry": {"coordinates":[-95.56148399999999,29.583906],"type":"Point"}
}