{
  "type": "Feature",
  "properties": {
    "iso:country":"US",
    "sg:address":"202 Walton Way",
    "sg:city":"Cedar Park",
    "sg:classifiers":[
        {
            "category":"Restaurant",
            "type":"Food & Drink"
        }
    ],
    "sg:phone":"+1 512 528 9876",
    "sg:postcode":"78613",
    "sg:province":"TX",
    "sg:tags":[
        "pizza",
        "italian"
    ],
    "wof:name":"Little Caesars",
    "wof:placetype":"venue"
},
  "geometry": {"coordinates":[-97.832846,30.521264],"type":"Point"}
}