{
  "type": "Feature",
  "properties": {
    "iso:country":"US",
    "sg:address":"606 N Ed Carey Dr",
    "sg:city":"Harlingen",
    "sg:classifiers":[
        {
            "category":"Shopping",
            "subcategory":"Pharmacy",
            "type":"Retail Goods"
        }
    ],
    "sg:phone":"+1 956 364 2600",
    "sg:postcode":"78550",
    "sg:province":"TX",
    "wof:name":"Harlingen Clinic Pharmacy",
    "wof:placetype":"venue"
},
  "geometry": {"coordinates":[-97.663078,26.209229],"type":"Point"}
}