{
  "type": "Feature",
  "properties": {
    "iso:country":"US",
    "sg:address":"14032 Memorial Dr",
    "sg:city":"Houston",
    "sg:classifiers":[
        {
            "category":"Manufacturing",
            "subcategory":"Pet Food",
            "type":"Manufacturing & Wholesale Goods"
        }
    ],
    "sg:phone":"+1 281 293 0959",
    "sg:postcode":"77079",
    "sg:province":"TX",
    "sg:tags":[
        "feed",
        "mfg",
        "prepared"
    ],
    "wof:name":"Wild Birds Unlimited",
    "wof:placetype":"venue"
},
  "geometry": {"coordinates":[-95.590373,29.770959],"type":"Point"}
}