{
  "type": "Feature",
  "properties": {
    "iso:country":"US",
    "sg:address":"3850 County Road 1",
    "sg:city":"Hereford",
    "sg:classifiers":[
        {
            "category":"Building & Trades",
            "subcategory":"Pest Control",
            "type":"Services"
        }
    ],
    "sg:phone":"+1 860 344 6222",
    "sg:postcode":"79045",
    "sg:province":"TX",
    "sg:tags":[
        "mothproofing"
    ],
    "wof:name":"Dan's Spraying Service",
    "wof:placetype":"venue"
},
  "geometry": {"coordinates":[-102.379915,34.748905],"type":"Point"}
}