{
  "type": "Feature",
  "properties": {
    "iso:country":"US",
    "sg:address":"1902 Buckner Dr",
    "sg:city":"Longview",
    "sg:classifiers":[
        {
            "category":"Autos & Motor Vehicles",
            "subcategory":"Recreational Vehicle Sales",
            "type":"Retail Goods"
        }
    ],
    "sg:phone":"+1 903 759 7239",
    "sg:postcode":"75604",
    "sg:province":"TX",
    "sg:tags":[
        "product",
        "wood",
        "mfg"
    ],
    "wof:name":"Woodwork Etc",
    "wof:placetype":"venue"
},
  "geometry": {"coordinates":[-94.79797000000001,32.531699],"type":"Point"}
}