{
  "type": "Feature",
  "properties": {
    "iso:country":"US",
    "sg:address":"108 W Greens Rd",
    "sg:city":"Houston",
    "sg:classifiers":[
        {
            "category":"Restaurant",
            "type":"Food & Drink"
        }
    ],
    "sg:menulink":"http://www.allmenus.com/tx/houston/50835-lubys/menu/",
    "sg:phone":"+1 281 873 0820",
    "sg:postcode":"77067",
    "sg:province":"TX",
    "sg:tags":[
        "new",
        "american"
    ],
    "wof:name":"Luby's",
    "wof:placetype":"venue"
},
  "geometry": {"coordinates":[-95.42107300000001,29.949042],"type":"Point"}
}