{
  "type": "Feature",
  "properties": {
    "iso:country":"US",
    "sg:address":"114 Roundup Dr",
    "sg:city":"Boerne",
    "sg:classifiers":[
        {
            "category":"Building & Trades",
            "subcategory":"Construction",
            "type":"Services"
        }
    ],
    "sg:phone":"+1 830 537 4016",
    "sg:postcode":"78006",
    "sg:province":"TX",
    "sg:tags":[
        "general"
    ],
    "wof:name":"Dspain Construction Company",
    "wof:placetype":"venue"
},
  "geometry": {"coordinates":[-98.747604,29.845166],"type":"Point"}
}