{
  "type": "Feature",
  "properties": {
    "iso:country":"US",
    "sg:address":"301 N Pinkerton St",
    "sg:city":"Athens",
    "sg:classifiers":[
        {
            "category":"Home & Garden",
            "subcategory":"Garden Supply",
            "type":"Retail Goods"
        }
    ],
    "sg:phone":"+1 903 677 8455",
    "sg:postcode":"75751",
    "sg:province":"TX",
    "wof:name":"Hoovers Small Engine Repair",
    "wof:placetype":"venue"
},
  "geometry": {"coordinates":[-95.856241,32.208283],"type":"Point"}
}