{
  "type": "Feature",
  "properties": {
    "iso:country":"US",
    "sg:address":"11218 S Pipeline Rd",
    "sg:city":"Euless",
    "sg:classifiers":[
        {
            "category":"Government",
            "subcategory":"Fire Station",
            "type":"Public Place"
        },
        {
            "category":"Retail",
            "subcategory":"Laundry & Dry Cleaning",
            "type":"Services"
        },
        {
            "category":"Retail",
            "subcategory":"Repair Shop",
            "type":"Services"
        }
    ],
    "sg:phone":"+1 817 989 6449",
    "sg:postcode":"76040",
    "sg:province":"TX",
    "sg:tags":[
        "cleaner",
        "disaster",
        "recovery",
        "rug",
        "relief",
        "carpet"
    ],
    "sg:website":"http://local.puroclean.com/water-damage-in-Fort-Worth-Arlington-TX/572",
    "wof:name":"PuroClean First Response",
    "wof:placetype":"venue"
},
  "geometry": {"coordinates":[-97.126626,32.814668],"type":"Point"}
}