{
  "type": "Feature",
  "properties": {
    "iso:country":"US",
    "sg:address":"1707 Brazos St",
    "sg:city":"Wichita Falls",
    "sg:classifiers":[
        {
            "category":"Professional",
            "subcategory":"Business Services",
            "type":"Services"
        }
    ],
    "sg:phone":"+1 940 692 5103",
    "sg:postcode":"76309",
    "sg:province":"TX",
    "wof:name":"Creative Solutions By Design",
    "wof:placetype":"venue"
},
  "geometry": {"coordinates":[-98.551925,33.901579],"type":"Point"}
}