{
  "type": "Feature",
  "properties": {
    "iso:country":"US",
    "sg:address":"18093 Upper Bay Rd",
    "sg:city":"Houston",
    "sg:classifiers":[
        {
            "category":"Shopping",
            "subcategory":"Used Merchandise",
            "type":"Retail Goods"
        }
    ],
    "sg:phone":"+1 281 333 4497",
    "sg:postcode":"77058",
    "sg:province":"TX",
    "sg:tags":[
        "clothing"
    ],
    "wof:name":"Nearly New Shop The",
    "wof:placetype":"venue"
},
  "geometry": {"coordinates":[-95.08957700000001,29.549856],"type":"Point"}
}