{
  "type": "Feature",
  "properties": {
    "iso:country":"US",
    "sg:address":"2402 E Washington Ave Ste B",
    "sg:city":"Harlingen",
    "sg:classifiers":[
        {
            "category":"Professional",
            "subcategory":"Computer Services",
            "type":"Services"
        }
    ],
    "sg:phone":"+1 956 425 1556",
    "sg:postcode":"78550",
    "sg:province":"TX",
    "sg:tags":[
        "isp",
        "provider",
        "internet"
    ],
    "wof:name":"P & L Imports",
    "wof:placetype":"venue"
},
  "geometry": {"coordinates":[-97.670784,26.198009],"type":"Point"}
}