{
  "type": "Feature",
  "properties": {
    "iso:country":"US",
    "sg:address":"2100 Alamo Rd",
    "sg:city":"Richardson",
    "sg:classifiers":[
        {
            "category":"Shopping",
            "subcategory":"Books",
            "type":"Retail Goods"
        }
    ],
    "sg:phone":"+1 972 234 4286",
    "sg:postcode":"75080",
    "sg:province":"TX",
    "sg:tags":[
        "dealer"
    ],
    "sg:website":"www.halfpricebooks.com",
    "wof:name":"Half Price Books Records Mags",
    "wof:placetype":"venue"
},
  "geometry": {"coordinates":[-96.717288,32.978806],"type":"Point"}
}