{
  "type": "Feature",
  "properties": {
    "iso:country":"US",
    "sg:address":"6700 Blacksmith Ln",
    "sg:city":"Amarillo",
    "sg:classifiers":[
        {
            "category":"Wholesale",
            "subcategory":"Electrical",
            "type":"Manufacturing & Wholesale Goods"
        }
    ],
    "sg:phone":"+1 806 355 5866",
    "sg:postcode":"79109",
    "sg:province":"TX",
    "sg:tags":[
        "sound",
        "equipment",
        "system"
    ],
    "wof:name":"Tumbleweed Sound & Lights",
    "wof:placetype":"venue"
},
  "geometry": {"coordinates":[-101.912633,35.135726],"type":"Point"}
}