{
  "type": "Feature",
  "properties": {
    "iso:country":"US",
    "sg:address":"500 Winscott Rd",
    "sg:city":"Benbrook",
    "sg:classifiers":[
        {
            "category":"Wholesale",
            "subcategory":"Machinery & Supplies",
            "type":"Manufacturing & Wholesale Goods"
        },
        {
            "category":"Building & Trades",
            "subcategory":"Equipment Rental",
            "type":"Services"
        }
    ],
    "sg:phone":"+1 817 249 1391",
    "sg:postcode":"76126",
    "sg:province":"TX",
    "sg:tags":[
        "field",
        "industrial",
        "oil"
    ],
    "sg:website":"http://www.compressionsolutions.com",
    "wof:name":"Weatherford International, Inc.",
    "wof:placetype":"venue"
},
  "geometry": {"coordinates":[-97.451988,32.689251],"type":"Point"}
}