{
  "type": "Feature",
  "properties": {
    "iso:country":"US",
    "sg:address":"15257 Saddlewood Dr",
    "sg:city":"Conroe",
    "sg:classifiers":[
        {
            "category":"Community Center",
            "subcategory":"Ethnic",
            "type":"Public Place"
        }
    ],
    "sg:phone":"+1 936 273 6573",
    "sg:postcode":"77384",
    "sg:province":"TX",
    "sg:tags":[
        "turbine",
        "part"
    ],
    "wof:name":"Wind Turbine Group",
    "wof:placetype":"venue"
},
  "geometry": {"coordinates":[-95.535712,30.227331],"type":"Point"}
}