{
  "type": "Feature",
  "properties": {
    "iso:country":"US",
    "sg:address":"6065 Hillcroft St Ste 101",
    "sg:city":"Houston",
    "sg:classifiers":[
        {
            "category":"Health Services",
            "subcategory":"Doctor",
            "type":"Services"
        }
    ],
    "sg:phone":"+1 713 772 3783",
    "sg:postcode":"77081",
    "sg:province":"TX",
    "sg:tags":[
        "surgeon",
        "oral"
    ],
    "wof:name":"Katz Bernard DDS",
    "wof:placetype":"venue"
},
  "geometry": {"coordinates":[-95.497704,29.715599],"type":"Point"}
}