{
  "type": "Feature",
  "properties": {
    "iso:country":"US",
    "sg:address":"1501 Enderly Pl",
    "sg:city":"Fort Worth",
    "sg:classifiers":[
        {
            "category":"Education",
            "subcategory":"Vocational School",
            "type":"Public Place"
        }
    ],
    "sg:phone":"+1 817 926 1101",
    "sg:postcode":"76104",
    "sg:province":"TX",
    "wof:name":"Tarleton State University",
    "wof:placetype":"venue"
},
  "geometry": {"coordinates":[-97.345252,32.727731],"type":"Point"}
}