{
  "type": "Feature",
  "properties": {
    "iso:country":"US",
    "sg:address":"6231 Fm 317",
    "sg:city":"Athens",
    "sg:classifiers":[
        {
            "category":"Professional",
            "subcategory":"Advertising",
            "type":"Services"
        }
    ],
    "sg:phone":"+1 903 677 0308",
    "sg:postcode":"75752",
    "sg:province":"TX",
    "sg:tags":[
        "promotion",
        "sale"
    ],
    "wof:name":"Advanced Promotions",
    "wof:placetype":"venue"
},
  "geometry": {"coordinates":[-95.75442200000001,32.233936],"type":"Point"}
}