{
  "type": "Feature",
  "properties": {
    "iso:country":"US",
    "sg:address":"3700 Buffalo Speedway",
    "sg:city":"Houston",
    "sg:classifiers":[
        {
            "category":"Health Services",
            "subcategory":"Doctor",
            "type":"Services"
        }
    ],
    "sg:phone":"+1 713 627 1200",
    "sg:postcode":"77005",
    "sg:province":"TX",
    "sg:tags":[
        "physician",
        "surgeon"
    ],
    "wof:name":"Michael Ciaravino MD",
    "wof:placetype":"venue"
},
  "geometry": {"coordinates":[-95.42882,29.732392],"type":"Point"}
}