{
  "type": "Feature",
  "properties": {
    "iso:country":"US",
    "sg:address":"1001 Shady Grove Rd",
    "sg:city":"Burnet",
    "sg:classifiers":[
        {
            "category":"Education",
            "subcategory":"School",
            "type":"Public Place"
        }
    ],
    "sg:phone":"+1 512 756 8090",
    "sg:postcode":"78611",
    "sg:province":"TX",
    "sg:website":"www.burnet.txed.net",
    "wof:name":"Shady Grove Elementary School",
    "wof:placetype":"venue"
},
  "geometry": {"coordinates":[-98.17478199999999,30.789605],"type":"Point"}
}