{
  "type": "Feature",
  "properties": {
    "iso:country":"US",
    "sg:address":"2201 Civic Cir",
    "sg:city":"Amarillo",
    "sg:classifiers":[
        {
            "category":"Professional",
            "type":"Services"
        }
    ],
    "sg:phone":"+1 806 352 0082",
    "sg:postcode":"79109",
    "sg:province":"TX",
    "wof:name":"APT Warriors Inc",
    "wof:placetype":"venue"
},
  "geometry": {"coordinates":[-101.866151,35.190566],"type":"Point"}
}