{
  "type": "Feature",
  "properties": {
    "iso:country":"US",
    "sg:address":"2314 W Ave M",
    "sg:city":"Temple",
    "sg:classifiers":[
        {
            "category":"Manufacturing",
            "subcategory":"Buildings",
            "type":"Manufacturing & Wholesale Goods"
        }
    ],
    "sg:phone":"+1 254 899 9663",
    "sg:postcode":"76504",
    "sg:province":"TX",
    "sg:tags":[
        "trade",
        "prefabricated",
        "contractor",
        "wood",
        "mfg"
    ],
    "wof:name":"Treeline Woodshop",
    "wof:placetype":"venue"
},
  "geometry": {"coordinates":[-97.370859,31.091113],"type":"Point"}
}