{
  "type": "Feature",
  "properties": {
    "iso:country":"US",
    "sg:address":"2507 Phillip Cove",
    "sg:city":"Leander",
    "sg:classifiers":[
        {
            "category":"Wholesale",
            "subcategory":"Vending Machines",
            "type":"Manufacturing & Wholesale Goods"
        }
    ],
    "sg:phone":"+1 512 259 2439",
    "sg:postcode":"78641",
    "sg:province":"TX",
    "sg:tags":[
        "operator"
    ],
    "wof:name":"Rjk Vending",
    "wof:placetype":"venue"
},
  "geometry": {"coordinates":[-97.832865,30.548085],"type":"Point"}
}