{
  "type": "Feature",
  "properties": {
    "iso:country":"US",
    "sg:address":"1211 E Central Ave",
    "sg:city":"Comanche",
    "sg:classifiers":[
        {
            "category":"Retail",
            "subcategory":"Car Wash",
            "type":"Services"
        }
    ],
    "sg:phone":"+1 325 356 3622",
    "sg:postcode":"76442",
    "sg:province":"TX",
    "sg:tags":[
        "polishing",
        "washing"
    ],
    "wof:name":"Comanche Laser Wash",
    "wof:placetype":"venue"
},
  "geometry": {"coordinates":[-98.588172,31.897952],"type":"Point"}
}