{
  "type": "Feature",
  "properties": {
    "iso:country":"US",
    "sg:address":"116 W Erwin St",
    "sg:city":"Tyler",
    "sg:classifiers":[
        {
            "category":"Real Estate",
            "subcategory":"Real Estate Services",
            "type":"Services"
        },
        {
            "category":"Real Estate",
            "subcategory":"Real Estate Agent",
            "type":"Services"
        }
    ],
    "sg:phone":"+1 903 593 2367",
    "sg:postcode":"75702",
    "sg:province":"TX",
    "sg:tags":[
        "vacancy",
        "management",
        "rental",
        "listing"
    ],
    "sg:website":"http://www.heinesrealestate.com",
    "wof:name":"Heines Martin Properties",
    "wof:placetype":"venue"
},
  "geometry": {"coordinates":[-95.30082,32.35075],"type":"Point"}
}