{
  "type": "Feature",
  "properties": {
    "iso:country":"US",
    "sg:address":"1401 Chestnut St",
    "sg:city":"Bastrop",
    "sg:classifiers":[
        {
            "category":"Wholesale",
            "subcategory":"Farm Supplies",
            "type":"Manufacturing & Wholesale Goods"
        }
    ],
    "sg:phone":"+1 512 321 1438",
    "sg:postcode":"78602",
    "sg:province":"TX",
    "sg:tags":[
        "feed",
        "hardware",
        "merchandise",
        "re"
    ],
    "wof:name":"Discount Feeds & Supplies",
    "wof:placetype":"venue"
},
  "geometry": {"coordinates":[-97.31026,30.110661],"type":"Point"}
}