{
  "type": "Feature",
  "properties": {
    "iso:country":"US",
    "sg:address":"710 Voss Ave",
    "sg:city":"Odem",
    "sg:classifiers":[
        {
            "category":"Food & Beverages",
            "subcategory":"Groceries & Convenience Stores",
            "type":"Retail Goods"
        }
    ],
    "sg:phone":"+1 361 368 7015",
    "sg:postcode":"78370",
    "sg:province":"TX",
    "wof:name":"Tod's Shop # 2",
    "wof:placetype":"venue"
},
  "geometry": {"coordinates":[-97.58035099999999,27.952876],"type":"Point"}
}