{
  "type": "Feature",
  "properties": {
    "iso:country":"US",
    "sg:address":"4100 W 15th St",
    "sg:city":"Plano",
    "sg:classifiers":[
        {
            "category":"Health Services",
            "subcategory":"Doctor",
            "type":"Services"
        }
    ],
    "sg:phone":"+1 972 596 2616",
    "sg:postcode":"75093",
    "sg:province":"TX",
    "sg:tags":[
        "physician",
        "medical",
        "surgeon"
    ],
    "wof:name":"Clinical Neurology Assocts PA",
    "wof:placetype":"venue"
},
  "geometry": {"coordinates":[-96.77068199999999,33.017755],"type":"Point"}
}