{
  "type": "Feature",
  "properties": {
    "iso:country":"US",
    "sg:address":"4107 Gus Dr",
    "sg:city":"Killeen",
    "sg:classifiers":[
        {
            "category":"Real Estate",
            "subcategory":"Real Estate Agent",
            "type":"Services"
        }
    ],
    "sg:phone":"+1 254 628 1115",
    "sg:postcode":"76549",
    "sg:province":"TX",
    "wof:name":"Pamela Woodward Real Estate",
    "wof:placetype":"venue"
},
  "geometry": {"coordinates":[-97.794095,31.089951],"type":"Point"}
}