{
  "type": "Feature",
  "properties": {
    "iso:country":"US",
    "sg:address":"7777 Forest Ln",
    "sg:city":"Dallas",
    "sg:classifiers":[
        {
            "category":"Health Services",
            "subcategory":"Doctor",
            "type":"Services"
        }
    ],
    "sg:phone":"+1 972 566 7733",
    "sg:postcode":"75230",
    "sg:province":"TX",
    "sg:tags":[
        "cardiologist"
    ],
    "wof:name":"Underwood Ronald H MD",
    "wof:placetype":"venue"
},
  "geometry": {"coordinates":[-96.772797,32.909599],"type":"Point"}
}