{
  "type": "Feature",
  "properties": {
    "iso:country":"US",
    "sg:address":"2242 Forest Park Blvd",
    "sg:city":"Fort Worth",
    "sg:classifiers":[
        {
            "category":"Real Estate",
            "subcategory":"Real Estate Agent",
            "type":"Services"
        }
    ],
    "sg:phone":"+1 817 923 7321",
    "sg:postcode":"76110",
    "sg:province":"TX",
    "sg:website":"www.helenpainter.com",
    "wof:name":"Helen Painter & Co Realtors",
    "wof:placetype":"venue"
},
  "geometry": {"coordinates":[-97.351969,32.718675],"type":"Point"}
}