{
  "type": "Feature",
  "properties": {
    "iso:country":"US",
    "sg:address":"117 Fate Main Pl",
    "sg:city":"Fate",
    "sg:classifiers":[
        {
            "category":"Restaurant",
            "type":"Food & Drink"
        }
    ],
    "sg:phone":"+1 972 772 3316",
    "sg:postcode":"75132",
    "sg:province":"TX",
    "sg:tags":[
        "eating"
    ],
    "wof:name":"Fate Restaurant",
    "wof:placetype":"venue"
},
  "geometry": {"coordinates":[-96.38271899999999,32.941531],"type":"Point"}
}