{
  "type": "Feature",
  "properties": {
    "iso:country":"US",
    "sg:address":"607 Harvey St",
    "sg:city":"Gainesville",
    "sg:classifiers":[
        {
            "category":"Building & Trades",
            "subcategory":"Cleaning & Sanitation",
            "type":"Services"
        }
    ],
    "sg:phone":"+1 940 665 0456",
    "sg:postcode":"76240",
    "sg:province":"TX",
    "sg:tags":[
        "janitor"
    ],
    "wof:name":"A J's Cleaning Svc",
    "wof:placetype":"venue"
},
  "geometry": {"coordinates":[-97.150488,33.634961],"type":"Point"}
}