{
  "type": "Feature",
  "properties": {
    "iso:country":"US",
    "sg:address":"2503 Santa Rita Ave",
    "sg:city":"Laredo",
    "sg:classifiers":[
        {
            "category":"Wholesale",
            "subcategory":"Machinery & Supplies",
            "type":"Manufacturing & Wholesale Goods"
        }
    ],
    "sg:phone":"+1 956 717 1092",
    "sg:postcode":"78040",
    "sg:province":"TX",
    "sg:tags":[
        "equipment",
        "industrial"
    ],
    "wof:name":"Atm Industrial Supply",
    "wof:placetype":"venue"
},
  "geometry": {"coordinates":[-99.513976,27.522714],"type":"Point"}
}