{
  "type": "Feature",
  "properties": {
    "iso:country":"US",
    "sg:address":"2217 Canal St",
    "sg:city":"Houston",
    "sg:classifiers":[
        {
            "category":"Shopping",
            "type":"Retail Goods"
        }
    ],
    "sg:phone":"+1 713 224 6174",
    "sg:postcode":"77003",
    "sg:province":"TX",
    "sg:tags":[
        "plastic"
    ],
    "wof:name":"Nation Plastics Inc",
    "wof:placetype":"venue"
},
  "geometry": {"coordinates":[-95.348067,29.759011],"type":"Point"}
}