{
  "type": "Feature",
  "properties": {
    "iso:country":"US",
    "sg:address":"4909 47th St",
    "sg:city":"Lubbock",
    "sg:classifiers":[
        {
            "category":"Retail",
            "subcategory":"Laundry & Dry Cleaning",
            "type":"Services"
        }
    ],
    "sg:phone":"+1 806 792 2619",
    "sg:postcode":"79414",
    "sg:province":"TX",
    "wof:name":"Rebeccas Alterations",
    "wof:placetype":"venue"
},
  "geometry": {"coordinates":[-101.920089,33.551444],"type":"Point"}
}