{
  "type": "Feature",
  "properties": {
    "iso:country":"US",
    "sg:address":"222 Wonder Pkwy",
    "sg:city":"San Antonio",
    "sg:classifiers":[
        {
            "category":"Professional",
            "type":"Services"
        }
    ],
    "sg:phone":"+1 210 340 4736",
    "sg:postcode":"78213",
    "sg:province":"TX",
    "wof:name":"Davidson South Texas",
    "wof:placetype":"venue"
},
  "geometry": {"coordinates":[-98.529352,29.491854],"type":"Point"}
}