{
  "type": "Feature",
  "properties": {
    "iso:country":"US",
    "sg:address":"5723 Trailwood Dr",
    "sg:city":"Dallas",
    "sg:classifiers":[
        {
            "category":"Manufacturing",
            "subcategory":"Printing",
            "type":"Manufacturing & Wholesale Goods"
        }
    ],
    "sg:phone":"+1 972 333 5514",
    "sg:postcode":"75241",
    "sg:province":"TX",
    "sg:tags":[
        "commercial"
    ],
    "wof:name":"All DOT Designs",
    "wof:placetype":"venue"
},
  "geometry": {"coordinates":[-96.818198,32.676566],"type":"Point"}
}