{
  "type": "Feature",
  "properties": {
    "iso:country":"US",
    "sg:address":"2626 30th Ave N",
    "sg:city":"Texas City",
    "sg:classifiers":[
        {
            "category":"Personal",
            "type":"Services"
        }
    ],
    "sg:phone":"+1 409 945 3548",
    "sg:postcode":"77590",
    "sg:province":"TX",
    "wof:name":"Miller Fountain Inc",
    "wof:placetype":"venue"
},
  "geometry": {"coordinates":[-94.93346,29.411756],"type":"Point"}
}