{
  "type": "Feature",
  "properties": {
    "iso:country":"US",
    "sg:address":"1773 Wells Branch Pkwy",
    "sg:city":"Austin",
    "sg:classifiers":[
        {
            "category":"Retail",
            "subcategory":"Auto Repair",
            "type":"Services"
        }
    ],
    "sg:phone":"+1 512 990 5814",
    "sg:postcode":"78728",
    "sg:province":"TX",
    "sg:tags":[
        "automotive"
    ],
    "wof:name":"Extra Effort Installation",
    "wof:placetype":"venue"
},
  "geometry": {"coordinates":[-97.673098,30.437511],"type":"Point"}
}