{
  "type": "Feature",
  "properties": {
    "iso:country":"US",
    "sg:address":"12360 Richmond Ave",
    "sg:city":"Houston",
    "sg:classifiers":[
        {
            "category":"Professional",
            "subcategory":"Management & Consulting",
            "type":"Services"
        }
    ],
    "sg:phone":"+1 281 870 1604",
    "sg:postcode":"77082",
    "sg:province":"TX",
    "wof:name":"Ax Management Inc",
    "wof:placetype":"venue"
},
  "geometry": {"coordinates":[-95.59902700000001,29.729925],"type":"Point"}
}