{
  "type": "Feature",
  "properties": {
    "iso:country":"US",
    "sg:address":"400 W Ennis Ave",
    "sg:city":"Ennis",
    "sg:classifiers":[
        {
            "category":"Health Services",
            "subcategory":"Doctor",
            "type":"Services"
        }
    ],
    "sg:phone":"+1 972 875 9031",
    "sg:postcode":"75119",
    "sg:province":"TX",
    "sg:tags":[
        "dentist"
    ],
    "wof:name":"Durbin Stephen C DDS",
    "wof:placetype":"venue"
},
  "geometry": {"coordinates":[-96.629955,32.32642],"type":"Point"}
}