{
  "type": "Feature",
  "properties": {
    "iso:country":"US",
    "sg:address":"1700 W 33rd St",
    "sg:city":"Austin",
    "sg:classifiers":[
        {
            "category":"Shopping",
            "type":"Retail Goods"
        }
    ],
    "sg:phone":"+1 512 467 9400",
    "sg:postcode":"78703",
    "sg:province":"TX",
    "sg:tags":[
        "consultant",
        "galleries",
        "art",
        "gallery"
    ],
    "sg:website":"www.globalgallery.com",
    "wof:name":"Global Gallery",
    "wof:placetype":"venue"
},
  "geometry": {"coordinates":[-97.75312,30.305309],"type":"Point"}
}