{
  "type": "Feature",
  "properties": {
    "iso:country":"US",
    "sg:address":"911 E Rusk St",
    "sg:city":"Jacksonville",
    "sg:classifiers":[
        {
            "category":"Wholesale",
            "subcategory":"Hardware",
            "type":"Manufacturing & Wholesale Goods"
        },
        {
            "category":"Home & Garden",
            "subcategory":"Garden Supply",
            "type":"Retail Goods"
        },
        {
            "category":"Retail",
            "subcategory":"Repair Shop",
            "type":"Services"
        }
    ],
    "sg:phone":"+1 903 586 1166",
    "sg:postcode":"75766",
    "sg:province":"TX",
    "sg:tags":[
        "renting",
        "lawn",
        "outdoor",
        "power",
        "landscaping",
        "equipment-sales",
        "equipment",
        "saw"
    ],
    "sg:website":"http://www.stihldealer.net/default-dealer-025299.aspx",
    "wof:name":"Tennison's Foster Saw And Repair",
    "wof:placetype":"venue"
},
  "geometry": {"coordinates":[-95.2628,31.966197],"type":"Point"}
}