{
  "type": "Feature",
  "properties": {
    "iso:country":"US",
    "sg:address":"2121 Utica Dr",
    "sg:city":"Dallas",
    "sg:classifiers":[
        {
            "category":"Shopping",
            "subcategory":"Clothing, Apparel, & Fashions",
            "type":"Retail Goods"
        }
    ],
    "sg:phone":"+1 214 388 7317",
    "sg:postcode":"75227",
    "sg:province":"TX",
    "sg:tags":[
        "family"
    ],
    "wof:name":"Sandy M Quiroz",
    "wof:placetype":"venue"
},
  "geometry": {"coordinates":[-96.685675,32.752102],"type":"Point"}
}