{
  "type": "Feature",
  "properties": {
    "iso:country":"US",
    "sg:address":"9801 S Washington St",
    "sg:city":"Amarillo",
    "sg:classifiers":[
        {
            "category":"Building & Trades",
            "subcategory":"Construction",
            "type":"Services"
        }
    ],
    "sg:phone":"+1 806 622 8201",
    "sg:postcode":"79118",
    "sg:province":"TX",
    "sg:tags":[
        "maker",
        "cabinet"
    ],
    "wof:name":"Reed's Cabinet Co Inc",
    "wof:placetype":"venue"
},
  "geometry": {"coordinates":[-101.84823799999999,35.117269],"type":"Point"}
}