{
  "type": "Feature",
  "properties": {
    "iso:country":"US",
    "sg:address":"805 N Greenville Ave",
    "sg:city":"Allen",
    "sg:classifiers":[
        {
            "category":"Building & Trades",
            "subcategory":"Construction",
            "type":"Services"
        }
    ],
    "sg:phone":"+1 972 390 1131",
    "sg:postcode":"75002",
    "sg:province":"TX",
    "sg:tags":[
        "foundation"
    ],
    "sg:website":"www.powerliftfoundation.com",
    "wof:name":"Power Lift Foundation",
    "wof:placetype":"venue"
},
  "geometry": {"coordinates":[-96.65314600000001,33.114584],"type":"Point"}
}