{
  "type": "Feature",
  "properties": {
    "iso:country":"US",
    "sg:address":"375 Peach Creek Rd",
    "sg:city":"Rosanky",
    "sg:classifiers":[
        {
            "category":"Farming",
            "subcategory":"Livestock Farm",
            "type":"Manufacturing & Wholesale Goods"
        }
    ],
    "sg:phone":"+1 830 839 4810",
    "sg:postcode":"78953",
    "sg:province":"TX",
    "sg:tags":[
        "ranch"
    ],
    "sg:website":"http://www.peachcreekfarm.com",
    "wof:name":"Peach Creek Farm",
    "wof:placetype":"venue"
},
  "geometry": {"coordinates":[-97.33313699999999,29.881532],"type":"Point"}
}