{
  "type": "Feature",
  "properties": {
    "iso:country":"US",
    "sg:address":"350 Garden Acres Dr",
    "sg:city":"Fort Worth",
    "sg:classifiers":[
        {
            "category":"Home & Garden",
            "subcategory":"Garden Supply",
            "type":"Retail Goods"
        }
    ],
    "sg:phone":"+1 817 293 1253",
    "sg:postcode":"76140",
    "sg:province":"TX",
    "sg:tags":[
        "nursery",
        "gardening"
    ],
    "wof:name":"IRG Garden acres Sindsor",
    "wof:placetype":"venue"
},
  "geometry": {"coordinates":[-97.31644900000001,32.599122],"type":"Point"}
}