{
  "type": "Feature",
  "properties": {
    "iso:country":"US",
    "sg:address":"553 State Hwy 303",
    "sg:city":"Grand Prairie",
    "sg:classifiers":[
        {
            "category":"Restaurant",
            "type":"Food & Drink"
        }
    ],
    "sg:phone":"+1 972 642 6769",
    "sg:postcode":"75051",
    "sg:province":"TX",
    "sg:tags":[
        "eating"
    ],
    "wof:name":"Sandwackers Restaurant",
    "wof:placetype":"venue"
},
  "geometry": {"coordinates":[-97.01029200000001,32.709525],"type":"Point"}
}