{
  "type": "Feature",
  "properties": {
    "iso:country":"US",
    "sg:address":"2464 Crown Rd",
    "sg:city":"Dallas",
    "sg:classifiers":[
        {
            "category":"Retail",
            "subcategory":"Auto Repair",
            "type":"Services"
        }
    ],
    "sg:phone":"+1 972 919 4625",
    "sg:postcode":"75229",
    "sg:province":"TX",
    "wof:name":"Eghbalpour Enterprises Inc",
    "wof:placetype":"venue"
},
  "geometry": {"coordinates":[-96.8964,32.900299],"type":"Point"}
}