{
  "type": "Feature",
  "properties": {
    "iso:country":"US",
    "sg:address":"11111 Katy Fwy Ste 1012",
    "sg:city":"Houston",
    "sg:classifiers":[
        {
            "category":"Professional",
            "subcategory":"Management & Consulting",
            "type":"Services"
        },
        {
            "category":"Professional",
            "subcategory":"Advertising",
            "type":"Services"
        }
    ],
    "sg:phone":"+1 713 647 7600",
    "sg:postcode":"77079",
    "sg:province":"TX",
    "sg:tags":[
        "marketing",
        "program",
        "consultant"
    ],
    "sg:website":"http://www.wesinad.com",
    "wof:name":"North American Division",
    "wof:placetype":"venue"
},
  "geometry": {"coordinates":[-95.578377,29.78414],"type":"Point"}
}