{
  "type": "Feature",
  "properties": {
    "iso:country":"US",
    "sg:address":"4338 Campbell Rd",
    "sg:city":"Houston",
    "sg:classifiers":[
        {
            "category":"Manufacturing",
            "subcategory":"Glass & Minerals",
            "type":"Manufacturing & Wholesale Goods"
        }
    ],
    "sg:phone":"+1 713 690 6030",
    "sg:postcode":"77041",
    "sg:province":"TX",
    "sg:tags":[
        "plate",
        "shape",
        "glass-wholesale",
        "window",
        "special",
        "circle",
        "glass-auto",
        "manufacturer"
    ],
    "sg:website":"http://www.signatureglass.org",
    "wof:name":"Signature Glass",
    "wof:placetype":"venue"
},
  "geometry": {"coordinates":[-95.529707,29.833262],"type":"Point"}
}