{
  "type": "Feature",
  "properties": {
    "iso:country":"US",
    "sg:address":"4205 Robinson Rd",
    "sg:city":"Grand Prairie",
    "sg:classifiers":[
        {
            "category":"Organizations",
            "subcategory":"Religious Organization",
            "type":"Services"
        }
    ],
    "sg:phone":"+1 972 642 9125",
    "sg:postcode":"75052",
    "sg:province":"TX",
    "sg:tags":[
        "church"
    ],
    "wof:name":"Faith Fellowship Baptist Chr",
    "wof:placetype":"venue"
},
  "geometry": {"coordinates":[-97.01527900000001,32.672398],"type":"Point"}
}