{
  "type": "Feature",
  "properties": {
    "iso:country":"US",
    "sg:address":"697 Redbud Ln",
    "sg:city":"Jasper",
    "sg:classifiers":[
        {
            "category":"Building & Trades",
            "subcategory":"Construction",
            "type":"Services"
        }
    ],
    "sg:phone":"+1 409 384 5224",
    "sg:postcode":"75951",
    "sg:province":"TX",
    "wof:name":"Clark Services",
    "wof:placetype":"venue"
},
  "geometry": {"coordinates":[-93.96328099999999,30.923189],"type":"Point"}
}