{
  "type": "Feature",
  "properties": {
    "iso:country":"US",
    "sg:address":"6780 Southwest Fwy",
    "sg:city":"Houston",
    "sg:classifiers":[
        {
            "category":"Travel",
            "subcategory":"Hotels & Motels",
            "type":"Entertainment"
        }
    ],
    "sg:phone":"+1 713 977 7911",
    "sg:postcode":"77074",
    "sg:province":"TX",
    "wof:name":"Hilton Houston Southwest",
    "wof:placetype":"venue"
},
  "geometry": {"coordinates":[-95.502296,29.7145],"type":"Point"}
}