{
  "type": "Feature",
  "properties": {
    "iso:country":"US",
    "sg:address":"800 Elmridge Dr",
    "sg:city":"Tyler",
    "sg:classifiers":[
        {
            "category":"Professional",
            "type":"Services"
        }
    ],
    "sg:phone":"+1 903 561 3863",
    "sg:postcode":"75703",
    "sg:province":"TX",
    "sg:tags":[
        "establishment"
    ],
    "wof:name":"Dianne Stewart Furnishing",
    "wof:placetype":"venue"
},
  "geometry": {"coordinates":[-95.314904,32.289001],"type":"Point"}
}