{
  "type": "Feature",
  "properties": {
    "iso:country":"US",
    "sg:address":"1081 W Main St",
    "sg:city":"Lewisville",
    "sg:classifiers":[
        {
            "category":"Restaurant",
            "type":"Food & Drink"
        }
    ],
    "sg:phone":"+1 972 221 2300",
    "sg:postcode":"75067",
    "sg:province":"TX",
    "sg:tags":[
        "eating"
    ],
    "wof:name":"Pizza Hut",
    "wof:placetype":"venue"
},
  "geometry": {"coordinates":[-97.01964599999999,33.042267],"type":"Point"}
}