{
  "type": "Feature",
  "properties": {
    "iso:country":"US",
    "sg:address":"1036 Town East Mall",
    "sg:city":"Mesquite",
    "sg:classifiers":[
        {
            "category":"Health Services",
            "subcategory":"Dentist",
            "type":"Services"
        }
    ],
    "sg:phone":"+1 972 613 5757",
    "sg:postcode":"75150",
    "sg:province":"TX",
    "sg:tags":[
        "orthodontist"
    ],
    "wof:name":"Castle Dental",
    "wof:placetype":"venue"
},
  "geometry": {"coordinates":[-96.626503,32.8088],"type":"Point"}
}