{
  "type": "Feature",
  "properties": {
    "iso:country":"US",
    "sg:address":"4001 Southwest Blvd",
    "sg:city":"San Angelo",
    "sg:classifiers":[
        {
            "category":"Shopping",
            "type":"Retail Goods"
        }
    ],
    "sg:phone":"+1 325 224 8310",
    "sg:postcode":"76904",
    "sg:province":"TX",
    "sg:tags":[
        "cards",
        "sport",
        "baseball",
        "memorabilia"
    ],
    "wof:name":"Sportsmaniac Cards & Collecta",
    "wof:placetype":"venue"
},
  "geometry": {"coordinates":[-100.494919,31.42731],"type":"Point"}
}