{
  "type": "Feature",
  "properties": {
    "iso:country":"US",
    "sg:address":"3401 S Collins St",
    "sg:city":"Arlington",
    "sg:classifiers":[
        {
            "category":"Shopping",
            "subcategory":"Pharmacy",
            "type":"Retail Goods"
        }
    ],
    "sg:phone":"+1 817 472 5002",
    "sg:postcode":"76014",
    "sg:province":"TX",
    "wof:name":"CVS",
    "wof:placetype":"venue"
},
  "geometry": {"coordinates":[-97.096278,32.68835],"type":"Point"}
}