{
  "type": "Feature",
  "properties": {
    "iso:country":"US",
    "sg:address":"103 Rio Vista Dr",
    "sg:city":"Laredo",
    "sg:classifiers":[
        {
            "category":"Insurance",
            "subcategory":"Hazard Insurance",
            "type":"Services"
        }
    ],
    "sg:phone":"+1 956 718 2544",
    "sg:postcode":"78041",
    "sg:province":"TX",
    "sg:tags":[
        "bond"
    ],
    "wof:name":"J & J Bail Bonds",
    "wof:placetype":"venue"
},
  "geometry": {"coordinates":[-99.516351,27.539143],"type":"Point"}
}