{
  "type": "Feature",
  "properties": {
    "iso:country":"US",
    "sg:address":"7710 Pennyburn Dr",
    "sg:city":"Dallas",
    "sg:classifiers":[
        {
            "category":"Professional",
            "subcategory":"Management & Consulting",
            "type":"Services"
        }
    ],
    "sg:phone":"+1 972 980 7622",
    "sg:postcode":"75248",
    "sg:province":"TX",
    "wof:name":"Trivision International",
    "wof:placetype":"venue"
},
  "geometry": {"coordinates":[-96.772566,32.982999],"type":"Point"}
}