{
  "type": "Feature",
  "properties": {
    "iso:country":"US",
    "sg:address":"3405 Guadalupe St",
    "sg:city":"Austin",
    "sg:classifiers":[
        {
            "category":"Personal",
            "subcategory":"Beauty Salon",
            "type":"Services"
        },
        {
            "category":"Personal",
            "subcategory":"Barber",
            "type":"Services"
        },
        {
            "category":"Personal",
            "subcategory":"Hair Removal",
            "type":"Services"
        },
        {
            "category":"Personal",
            "subcategory":"Nail Salon",
            "type":"Services"
        }
    ],
    "sg:phone":"+1 877 819 8034",
    "sg:postcode":"78705",
    "sg:province":"TX",
    "sg:tags":[
        "braiding",
        "stylist"
    ],
    "sg:website":"http://austin.citysearch.com/profile/external/37377826/austin_tx/capelli_salon.html?publisher=yellowpages&reference_id=1&placement=ypwebsitemip",
    "wof:name":"Capelli Salon",
    "wof:placetype":"venue"
},
  "geometry": {"coordinates":[-97.739592,30.3005],"type":"Point"}
}