{
  "type": "Feature",
  "properties": {
    "iso:country":"US",
    "sg:address":"611 Clay St",
    "sg:city":"Houston",
    "sg:classifiers":[
        {
            "category":"Retail",
            "subcategory":"Laundry & Dry Cleaning",
            "type":"Services"
        }
    ],
    "sg:phone":"+1 713 336 0529",
    "sg:postcode":"77002",
    "sg:province":"TX",
    "sg:tags":[
        "drycleaning",
        "plant"
    ],
    "wof:name":"Pilgrim Cleaners Inc",
    "wof:placetype":"venue"
},
  "geometry": {"coordinates":[-95.36991399999999,29.755645],"type":"Point"}
}