{
  "type": "Feature",
  "properties": {
    "iso:country":"US",
    "sg:address":"1102 Kingston Dr",
    "sg:city":"Lewisville",
    "sg:classifiers":[
        {
            "category":"Professional",
            "subcategory":"Computer Services",
            "type":"Services"
        }
    ],
    "sg:phone":"+1 972 436 0333",
    "sg:postcode":"75067",
    "sg:province":"TX",
    "wof:name":"Minteer Micro Systems",
    "wof:placetype":"venue"
},
  "geometry": {"coordinates":[-97.02753300000001,33.031324],"type":"Point"}
}