{
  "type": "Feature",
  "properties": {
    "iso:country":"US",
    "sg:address":"3412 Thomason Dr",
    "sg:city":"Midland",
    "sg:classifiers":[
        {
            "category":"Personal",
            "subcategory":"Barber",
            "type":"Services"
        }
    ],
    "sg:phone":"+1 432 262 3795",
    "sg:postcode":"79703",
    "sg:province":"TX",
    "wof:name":"Talking Heads",
    "wof:placetype":"venue"
},
  "geometry": {"coordinates":[-102.114092,31.978427],"type":"Point"}
}