{
  "type": "Feature",
  "properties": {
    "iso:country":"US",
    "sg:address":"8435 Westglen Dr",
    "sg:city":"Houston",
    "sg:classifiers":[
        {
            "category":"Real Estate",
            "subcategory":"Real Estate Agent",
            "type":"Services"
        }
    ],
    "sg:phone":"+1 713 783 3200",
    "sg:postcode":"77063",
    "sg:province":"TX",
    "wof:name":"Magjik Holdings Lc",
    "wof:placetype":"venue"
},
  "geometry": {"coordinates":[-95.51132200000001,29.724613],"type":"Point"}
}