{
  "type": "Feature",
  "properties": {
    "iso:country":"US",
    "sg:address":"2221 Chadbourne Dr",
    "sg:city":"Plano",
    "sg:classifiers":[
        {
            "category":"Shopping",
            "subcategory":"Gifts & Souvenirs",
            "type":"Retail Goods"
        }
    ],
    "sg:phone":"+1 972 618 8174",
    "sg:postcode":"75023",
    "sg:province":"TX",
    "wof:name":"Your Memorabilia Connection",
    "wof:placetype":"venue"
},
  "geometry": {"coordinates":[-96.73905600000001,33.06703],"type":"Point"}
}