{
  "type": "Feature",
  "properties": {
    "iso:country":"US",
    "sg:address":"200 Taylor St",
    "sg:city":"Tye",
    "sg:classifiers":[
        {
            "category":"Government",
            "subcategory":"Post Office",
            "type":"Public Place"
        }
    ],
    "sg:phone":"+1 325 698 4100",
    "sg:postcode":"79563",
    "sg:province":"TX",
    "wof:name":"US Post Office",
    "wof:placetype":"venue"
},
  "geometry": {"coordinates":[-99.867683,32.458714],"type":"Point"}
}