{
  "type": "Feature",
  "properties": {
    "iso:country":"US",
    "sg:address":"274 Co Rd 3505",
    "sg:city":"Pecan Gap",
    "sg:classifiers":[
        {
            "category":"Building & Trades",
            "subcategory":"Construction",
            "type":"Services"
        }
    ],
    "sg:phone":"+1 903 455 1461",
    "sg:postcode":"75469",
    "sg:province":"TX",
    "wof:name":"A Cut Above Metal Buildings",
    "wof:placetype":"venue"
},
  "geometry": {"coordinates":[-95.77549999999999,33.472037],"type":"Point"}
}