{
  "type": "Feature",
  "properties": {
    "iso:country":"US",
    "sg:address":"1937 N Broadway St",
    "sg:city":"Carrollton",
    "sg:classifiers":[
        {
            "category":"Building & Trades",
            "subcategory":"Plumbing",
            "type":"Services"
        }
    ],
    "sg:phone":"+1 972 242 0601",
    "sg:postcode":"75006",
    "sg:province":"TX",
    "sg:tags":[
        "conditioning",
        "air",
        "system",
        "contractor"
    ],
    "sg:website":"www.transairinc.com",
    "wof:name":"Transair Air Conditioning Inc",
    "wof:placetype":"venue"
},
  "geometry": {"coordinates":[-96.916161,32.96611],"type":"Point"}
}