{
  "type": "Feature",
  "properties": {
    "iso:country":"US",
    "sg:address":"2828 Brown Trl",
    "sg:city":"Bedford",
    "sg:classifiers":[
        {
            "category":"Shopping",
            "subcategory":"Computers & Home Electronics",
            "type":"Retail Goods"
        },
        {
            "category":"Professional",
            "subcategory":"Computer Services",
            "type":"Services"
        }
    ],
    "sg:phone":"+1 817 267 7021",
    "sg:postcode":"76021",
    "sg:province":"TX",
    "sg:tags":[
        "equipment",
        "dealer"
    ],
    "sg:website":"www.bluecandle.com",
    "wof:name":"Blue Candle Computers",
    "wof:placetype":"venue"
},
  "geometry": {"coordinates":[-97.159907,32.852166],"type":"Point"}
}