{
  "type": "Feature",
  "properties": {
    "iso:country":"US",
    "sg:address":"990 E Fm 628",
    "sg:city":"Riviera",
    "sg:classifiers":[
        {
            "category":"Travel",
            "subcategory":"Hotels & Motels",
            "type":"Entertainment"
        },
        {
            "category":"Travel",
            "subcategory":"Bed & Breakfast",
            "type":"Entertainment"
        }
    ],
    "sg:phone":"+1 361 297 5158",
    "sg:postcode":"78379",
    "sg:province":"TX",
    "sg:tags":[
        "inn",
        "lodging"
    ],
    "wof:name":"Baffin Bay Inn",
    "wof:placetype":"venue"
},
  "geometry": {"coordinates":[-97.692261,27.331125],"type":"Point"}
}