{
  "type": "Feature",
  "properties": {
    "iso:country":"US",
    "sg:address":"1915 Green Valley Rd",
    "sg:city":"Cibolo",
    "sg:classifiers":[
        {
            "category":"Professional",
            "subcategory":"Management & Consulting",
            "type":"Services"
        }
    ],
    "sg:phone":"+1 210 566 1958",
    "sg:postcode":"78108",
    "sg:province":"TX",
    "sg:tags":[
        "consultant"
    ],
    "wof:name":"Sharon M Fisk Consulting Svc",
    "wof:placetype":"venue"
},
  "geometry": {"coordinates":[-98.25539499999999,29.591982],"type":"Point"}
}