{
  "type": "Feature",
  "properties": {
    "iso:country":"US",
    "sg:address":"32350 State Highway 249",
    "sg:city":"Pinehurst",
    "sg:classifiers":[
        {
            "category":"Sports & Exercise",
            "subcategory":"Gym",
            "type":"Entertainment"
        },
        {
            "category":"Arena",
            "subcategory":"Sports Club",
            "type":"Entertainment"
        }
    ],
    "sg:phone":"+1 281 259 4620",
    "sg:postcode":"77362",
    "sg:province":"TX",
    "sg:tags":[
        "program",
        "health",
        "gymnasium",
        "physical",
        "fitness"
    ],
    "wof:name":"Tomball Fitness",
    "wof:placetype":"venue"
},
  "geometry": {"coordinates":[-95.65508,30.136231],"type":"Point"}
}