{
  "type": "Feature",
  "properties": {
    "iso:country":"US",
    "sg:address":"200 E Mayer St",
    "sg:city":"Stockdale",
    "sg:classifiers":[
        {
            "category":"Building & Trades",
            "subcategory":"Construction",
            "type":"Services"
        }
    ],
    "sg:phone":"+1 830 996 1465",
    "sg:postcode":"78160",
    "sg:province":"TX",
    "sg:tags":[
        "paving",
        "road",
        "contractor"
    ],
    "wof:name":"Cotter Resources, Inc.",
    "wof:placetype":"venue"
},
  "geometry": {"coordinates":[-97.95903,29.235291],"type":"Point"}
}