{
  "type": "Feature",
  "properties": {
    "iso:country":"US",
    "sg:address":"9002 N Navarro St",
    "sg:city":"Victoria",
    "sg:classifiers":[
        {
            "category":"Health Services",
            "subcategory":"Optometrist",
            "type":"Services"
        }
    ],
    "sg:phone":"+1 361 575 6766",
    "sg:postcode":"77904",
    "sg:province":"TX",
    "wof:name":"Access Eye Care",
    "wof:placetype":"venue"
},
  "geometry": {"coordinates":[-96.99706399999999,28.877373],"type":"Point"}
}