{
  "type": "Feature",
  "properties": {
    "iso:country":"US",
    "sg:address":"23221 Aldine Westfield Rd L",
    "sg:city":"Spring",
    "sg:classifiers":[
        {
            "category":"Banks & Credit Unions",
            "subcategory":"Investment Brokerage",
            "type":"Services"
        }
    ],
    "sg:phone":"+1 281 353 0187",
    "sg:postcode":"77373",
    "sg:province":"TX",
    "sg:tags":[
        "tape",
        "video",
        "sale",
        "dvds-rental"
    ],
    "wof:name":"Movie Gallery",
    "wof:placetype":"venue"
},
  "geometry": {"coordinates":[-95.387989,30.050271],"type":"Point"}
}