{
  "type": "Feature",
  "properties": {
    "iso:country":"US",
    "sg:address":"13249 Montfort Dr",
    "sg:city":"Dallas",
    "sg:classifiers":[
        {
            "category":"Banks & Credit Unions",
            "subcategory":"Bank",
            "type":"Services"
        }
    ],
    "sg:phone":"+1 972 934 1682",
    "sg:postcode":"75240",
    "sg:province":"TX",
    "sg:tags":[
        "alternative",
        "loan"
    ],
    "sg:website":"http://www.cashstore.com/TX/Trademark/yp.com",
    "wof:name":"Cash Store",
    "wof:placetype":"venue"
},
  "geometry": {"coordinates":[-96.8113,32.928185],"type":"Point"}
}