{
  "type": "Feature",
  "properties": {
    "iso:country":"US",
    "sg:address":"907 Elmwood Trl",
    "sg:city":"Cedar Park",
    "sg:classifiers":[
        {
            "category":"Building & Trades",
            "subcategory":"Pest Control",
            "type":"Services"
        }
    ],
    "sg:phone":"+1 512 567 0001",
    "sg:postcode":"78613",
    "sg:province":"TX",
    "wof:name":"Bottom-Line Termite & Pest",
    "wof:placetype":"venue"
},
  "geometry": {"coordinates":[-97.83164600000001,30.494847],"type":"Point"}
}