{
  "type": "Feature",
  "properties": {
    "iso:country":"US",
    "sg:address":"401 W Sanford St",
    "sg:city":"Arlington",
    "sg:classifiers":[
        {
            "category":"Organizations",
            "subcategory":"Community Association",
            "type":"Services"
        }
    ],
    "sg:phone":"+1 817 274 3488",
    "sg:postcode":"76011",
    "sg:province":"TX",
    "sg:tags":[
        "a",
        "boy",
        "girl",
        "for",
        "operates"
    ],
    "wof:name":"Camp Fire USA Frst Txas Cuncil",
    "wof:placetype":"venue"
},
  "geometry": {"coordinates":[-97.111283,32.742841],"type":"Point"}
}