{
  "type": "Feature",
  "properties": {
    "iso:country":"US",
    "sg:address":"1307 26th St",
    "sg:city":"Snyder",
    "sg:classifiers":[
        {
            "category":"Insurance",
            "subcategory":"Hazard Insurance",
            "type":"Services"
        }
    ],
    "sg:phone":"+1 325 573 3046",
    "sg:postcode":"79549",
    "sg:province":"TX",
    "sg:tags":[
        "bond"
    ],
    "wof:name":"Road Runner Bail Bonds",
    "wof:placetype":"venue"
},
  "geometry": {"coordinates":[-100.911688,32.716107],"type":"Point"}
}