{
  "type": "Feature",
  "properties": {
    "iso:country":"US",
    "sg:address":"512 N Wayside Dr",
    "sg:city":"Houston",
    "sg:classifiers":[
        {
            "category":"Personal",
            "subcategory":"Beauty Salon",
            "type":"Services"
        }
    ],
    "sg:phone":"+1 713 514 0710",
    "sg:postcode":"77011",
    "sg:province":"TX",
    "sg:tags":[
        "shop"
    ],
    "wof:name":"Peluqueria Michoacan No 1",
    "wof:placetype":"venue"
},
  "geometry": {"coordinates":[-95.30483599999999,29.740231],"type":"Point"}
}