{
  "type": "Feature",
  "properties": {
    "iso:country":"US",
    "sg:address":"21310 Park Bishop Dr",
    "sg:city":"Katy",
    "sg:classifiers":[
        {
            "category":"Building & Trades",
            "subcategory":"Landscaping Services",
            "type":"Services"
        }
    ],
    "sg:phone":"+1 281 599 8733",
    "sg:postcode":"77450",
    "sg:province":"TX",
    "wof:name":"Houston Arbor Care Tree Servic",
    "wof:placetype":"venue"
},
  "geometry": {"coordinates":[-95.73752500000001,29.758625],"type":"Point"}
}