{
  "type": "Feature",
  "properties": {
    "iso:country":"US",
    "sg:address":"397 N Sam Houston Pkwy E Ste 325",
    "sg:city":"Houston",
    "sg:classifiers":[
        {
            "category":"Professional",
            "subcategory":"Lawyer & Legal Services",
            "type":"Services"
        }
    ],
    "sg:phone":"+1 832 448 1148",
    "sg:postcode":"77060",
    "sg:province":"TX",
    "wof:name":"Musick & Musick LLP",
    "wof:placetype":"venue"
},
  "geometry": {"coordinates":[-95.397141,29.939791],"type":"Point"}
}