{
  "type": "Feature",
  "properties": {
    "iso:country":"US",
    "sg:address":"302 Enterprise St",
    "sg:city":"Longview",
    "sg:classifiers":[
        {
            "category":"Wholesale",
            "subcategory":"Machinery & Supplies",
            "type":"Manufacturing & Wholesale Goods"
        }
    ],
    "sg:phone":"+1 903 291 1663",
    "sg:postcode":"75604",
    "sg:province":"TX",
    "sg:tags":[
        "forklift",
        "pa",
        "vehicle",
        "warehouse",
        "retail",
        "lease"
    ],
    "wof:name":"Darr Lift",
    "wof:placetype":"venue"
},
  "geometry": {"coordinates":[-94.786226,32.500851],"type":"Point"}
}