{
  "type": "Feature",
  "properties": {
    "iso:country":"US",
    "sg:address":"6270 Oakmont Blvd",
    "sg:city":"Fort Worth",
    "sg:classifiers":[
        {
            "category":"Personal",
            "subcategory":"Beauty Salon",
            "type":"Services"
        }
    ],
    "sg:phone":"+1 817 294 7722",
    "sg:postcode":"76132",
    "sg:province":"TX",
    "wof:name":"LA Bella Salon",
    "wof:placetype":"venue"
},
  "geometry": {"coordinates":[-97.403857,32.662867],"type":"Point"}
}