{
  "type": "Feature",
  "properties": {
    "iso:country":"US",
    "sg:address":"7230 Kingsway Dr",
    "sg:city":"Houston",
    "sg:classifiers":[
        {
            "category":"Professional",
            "subcategory":"Computer Services",
            "type":"Services"
        }
    ],
    "sg:phone":"+1 713 242 6625",
    "sg:postcode":"77087",
    "sg:province":"TX",
    "sg:tags":[
        "datum",
        "processing",
        "administration",
        "secretarial"
    ],
    "wof:name":"Cdc Secretarial Services",
    "wof:placetype":"venue"
},
  "geometry": {"coordinates":[-95.297651,29.678337],"type":"Point"}
}