{
  "type": "Feature",
  "properties": {
    "iso:country":"US",
    "sg:address":"204 N Dooley St",
    "sg:city":"Grapevine",
    "sg:classifiers":[
        {
            "category":"Autos & Motor Vehicles",
            "subcategory":"Auto Supplies",
            "type":"Retail Goods"
        }
    ],
    "sg:phone":"+1 972 986 0271",
    "sg:postcode":"76051",
    "sg:province":"TX",
    "sg:tags":[
        "accessories-wholesale",
        "automobile",
        "part",
        "parts",
        "manufacturer"
    ],
    "wof:name":"Auto Facts",
    "wof:placetype":"venue"
},
  "geometry": {"coordinates":[-97.073359,32.941927],"type":"Point"}
}