{
  "type": "Feature",
  "properties": {
    "iso:country":"US",
    "sg:address":"1311 N Ave F",
    "sg:city":"Denver City",
    "sg:classifiers":[
        {
            "category":"Professional",
            "subcategory":"Computer Services",
            "type":"Services"
        }
    ],
    "sg:phone":"+1 806 592 5182",
    "sg:postcode":"79323",
    "sg:province":"TX",
    "sg:tags":[
        "internet"
    ],
    "wof:name":"Midtech",
    "wof:placetype":"venue"
},
  "geometry": {"coordinates":[-102.835256,32.978084],"type":"Point"}
}