{
  "type": "Feature",
  "properties": {
    "iso:country":"US",
    "sg:address":"17808 FM 1314",
    "sg:city":"Conroe",
    "sg:classifiers":[
        {
            "category":"Retail",
            "subcategory":"Auto Repair",
            "type":"Services"
        }
    ],
    "sg:phone":"+1 281 429 7222",
    "sg:postcode":"77302",
    "sg:province":"TX",
    "sg:tags":[
        "repairing",
        "automobile",
        "general"
    ],
    "wof:name":"Scott's Auto Repair",
    "wof:placetype":"venue"
},
  "geometry": {"coordinates":[-95.340245,30.192219],"type":"Point"}
}