{
  "type": "Feature",
  "properties": {
    "iso:country":"US",
    "sg:address":"2375 Oldbridge Dr",
    "sg:city":"Dallas",
    "sg:classifiers":[
        {
            "category":"Wholesale",
            "subcategory":"Motor Vehicles",
            "type":"Manufacturing & Wholesale Goods"
        }
    ],
    "sg:phone":"+1 214 328 2570",
    "sg:postcode":"75228",
    "sg:province":"TX",
    "sg:tags":[
        "scooter"
    ],
    "wof:name":"Harry B Fairley",
    "wof:placetype":"venue"
},
  "geometry": {"coordinates":[-96.70236199999999,32.808369],"type":"Point"}
}