{
  "type": "Feature",
  "properties": {
    "iso:country":"US",
    "sg:address":"1220 Newberry Dr",
    "sg:city":"Allen",
    "sg:classifiers":[
        {
            "category":"Shopping",
            "type":"Retail Goods"
        }
    ],
    "sg:phone":"+1 972 390 9429",
    "sg:postcode":"75013",
    "sg:province":"TX",
    "sg:tags":[
        "cosmetic",
        "perfume"
    ],
    "wof:name":"Sandra Conarty",
    "wof:placetype":"venue"
},
  "geometry": {"coordinates":[-96.69837800000001,33.095071],"type":"Point"}
}