{
  "type": "Feature",
  "properties": {
    "iso:country":"US",
    "sg:address":"509 E Main St",
    "sg:city":"Little River",
    "sg:classifiers":[
        {
            "category":"Government",
            "subcategory":"Office",
            "type":"Public Place"
        }
    ],
    "sg:phone":"+1 254 982 4248",
    "sg:postcode":"76554",
    "sg:province":"TX",
    "sg:tags":[
        "village"
    ],
    "wof:name":"Little River-Academy Police",
    "wof:placetype":"venue"
},
  "geometry": {"coordinates":[-97.34786800000001,30.982636],"type":"Point"}
}