{
  "type": "Feature",
  "properties": {
    "iso:country":"US",
    "sg:address":"1201 W Arbrook Blvd",
    "sg:city":"Arlington",
    "sg:classifiers":[
        {
            "category":"Shopping",
            "subcategory":"Shoes",
            "type":"Retail Goods"
        }
    ],
    "sg:phone":"+1 817 467 7338",
    "sg:postcode":"76015",
    "sg:province":"TX",
    "wof:name":"Discount Dugout 996",
    "wof:placetype":"venue"
},
  "geometry": {"coordinates":[-97.12969200000001,32.683235],"type":"Point"}
}