{
  "type": "Feature",
  "properties": {
    "iso:country":"US",
    "sg:address":"4410 Seawall Blvd",
    "sg:city":"Galveston",
    "sg:classifiers":[
        {
            "category":"Health Services",
            "subcategory":"Doctor",
            "type":"Services"
        }
    ],
    "sg:phone":"+1 409 763 8444",
    "sg:postcode":"77550",
    "sg:province":"TX",
    "sg:tags":[
        "dentist"
    ],
    "wof:name":"David Colombo DDS PC",
    "wof:placetype":"venue"
},
  "geometry": {"coordinates":[-94.80781399999999,29.27744],"type":"Point"}
}