{
  "type": "Feature",
  "properties": {
    "iso:country":"US",
    "sg:address":"3809 W Waco Dr",
    "sg:city":"Waco",
    "sg:classifiers":[
        {
            "category":"Professional",
            "subcategory":"Lawyer & Legal Services",
            "type":"Services"
        }
    ],
    "sg:phone":"+1 254 759 8600",
    "sg:postcode":"76710",
    "sg:province":"TX",
    "sg:tags":[
        "attorney"
    ],
    "wof:name":"Montez John A Atty. at Law",
    "wof:placetype":"venue"
},
  "geometry": {"coordinates":[-97.186813,31.51432],"type":"Point"}
}