{
  "type": "Feature",
  "properties": {
    "iso:country":"US",
    "sg:address":"14111 Misty Meadow Ln",
    "sg:city":"Houston",
    "sg:classifiers":[
        {
            "category":"Shopping",
            "type":"Retail Goods"
        }
    ],
    "sg:phone":"+1 713 825 4141",
    "sg:postcode":"77079",
    "sg:province":"TX",
    "sg:tags":[
        "cosmetic",
        "perfume"
    ],
    "wof:name":"Mary Kay Cosmetics",
    "wof:placetype":"venue"
},
  "geometry": {"coordinates":[-95.59604,29.780139],"type":"Point"}
}