{
  "type": "Feature",
  "properties": {
    "iso:country":"US",
    "sg:address":"2517 Franklin Dr",
    "sg:city":"Mesquite",
    "sg:classifiers":[
        {
            "category":"Building & Trades",
            "subcategory":"Plumbing",
            "type":"Services"
        }
    ],
    "sg:phone":"+1 972 288 9601",
    "sg:postcode":"75150",
    "sg:province":"TX",
    "wof:name":"Accelerated Mechanical Services",
    "wof:placetype":"venue"
},
  "geometry": {"coordinates":[-96.61923299999999,32.797933],"type":"Point"}
}