{
  "type": "Feature",
  "properties": {
    "iso:country":"US",
    "sg:address":"2802 Stonewall St",
    "sg:city":"Greenville",
    "sg:classifiers":[
        {
            "category":"Professional",
            "subcategory":"Business Services",
            "type":"Services"
        }
    ],
    "sg:phone":"+1 903 454 2663",
    "sg:postcode":"75401",
    "sg:province":"TX",
    "sg:tags":[
        "bail",
        "bond"
    ],
    "wof:name":"Bargain Bail Bonds",
    "wof:placetype":"venue"
},
  "geometry": {"coordinates":[-96.107337,33.137619],"type":"Point"}
}