{
  "type": "Feature",
  "properties": {
    "iso:country":"US",
    "sg:address":"3801 Kirby Dr",
    "sg:city":"Houston",
    "sg:classifiers":[
        {
            "category":"Professional",
            "subcategory":"Secretarial Services",
            "type":"Services"
        }
    ],
    "sg:phone":"+1 713 521 1117",
    "sg:postcode":"77098",
    "sg:province":"TX",
    "sg:tags":[
        "reporting"
    ],
    "wof:name":"CRS",
    "wof:placetype":"venue"
},
  "geometry": {"coordinates":[-95.418649,29.732051],"type":"Point"}
}