{
  "type": "Feature",
  "properties": {
    "iso:country":"US",
    "sg:address":"3410 Taft Blvd",
    "sg:city":"Wichita Falls",
    "sg:classifiers":[
        {
            "category":"Building & Trades",
            "subcategory":"Construction",
            "type":"Services"
        }
    ],
    "sg:phone":"+1 940 631 5063",
    "sg:postcode":"76308",
    "sg:province":"TX",
    "sg:tags":[
        "carpentry"
    ],
    "wof:name":"Jason Carnahan",
    "wof:placetype":"venue"
},
  "geometry": {"coordinates":[-98.51857699999999,33.876672],"type":"Point"}
}