{
  "type": "Feature",
  "properties": {
    "iso:country":"US",
    "sg:address":"2001 Coit Rd",
    "sg:city":"Plano",
    "sg:classifiers":[
        {
            "category":"Health Services",
            "subcategory":"Chiropractor",
            "type":"Services"
        }
    ],
    "sg:phone":"+1 972 612 0707",
    "sg:postcode":"75075",
    "sg:province":"TX",
    "wof:name":"Davis Glenn Dr DC",
    "wof:placetype":"venue"
},
  "geometry": {"coordinates":[-96.77015,33.026854],"type":"Point"}
}