{
  "type": "Feature",
  "properties": {
    "iso:country":"US",
    "sg:address":"4716 Holiday Ln W",
    "sg:city":"Fort Worth",
    "sg:classifiers":[
        {
            "category":"Retail",
            "subcategory":"Portrait Studio",
            "type":"Services"
        }
    ],
    "sg:phone":"+1 817 498 2234",
    "sg:postcode":"76180",
    "sg:province":"TX",
    "sg:tags":[
        "photo"
    ],
    "wof:name":"Red Velvet Armadillo Photograp",
    "wof:placetype":"venue"
},
  "geometry": {"coordinates":[-97.230498,32.832411],"type":"Point"}
}