{
  "type": "Feature",
  "properties": {
    "iso:country":"US",
    "sg:address":"1013 Bertrand St",
    "sg:city":"Conroe",
    "sg:classifiers":[
        {
            "category":"Building & Trades",
            "subcategory":"Construction",
            "type":"Services"
        }
    ],
    "sg:phone":"+1 936 539 3512",
    "sg:postcode":"77301",
    "sg:province":"TX",
    "sg:tags":[
        "house"
    ],
    "wof:name":"Fuentes Construction",
    "wof:placetype":"venue"
},
  "geometry": {"coordinates":[-95.455539,30.300033],"type":"Point"}
}