{
  "type": "Feature",
  "properties": {
    "iso:country":"US",
    "sg:address":"913 Willow Way",
    "sg:city":"Benbrook",
    "sg:classifiers":[
        {
            "category":"Professional",
            "subcategory":"Management & Consulting",
            "type":"Services"
        }
    ],
    "sg:phone":"+1 817 249 7356",
    "sg:postcode":"76126",
    "sg:province":"TX",
    "sg:tags":[
        "party",
        "planning"
    ],
    "wof:name":"Lady Bug Bounce",
    "wof:placetype":"venue"
},
  "geometry": {"coordinates":[-97.43641100000001,32.674981],"type":"Point"}
}