{
  "type": "Feature",
  "properties": {
    "iso:country":"US",
    "sg:address":"8533 Beechnut St",
    "sg:city":"Houston",
    "sg:classifiers":[
        {
            "category":"Bars & Pubs",
            "type":"Food & Drink"
        }
    ],
    "sg:phone":"+1 713 777 1488",
    "sg:postcode":"77036",
    "sg:province":"TX",
    "sg:tags":[
        "club",
        "night"
    ],
    "wof:name":"Huetamo Night Club",
    "wof:placetype":"venue"
},
  "geometry": {"coordinates":[-95.535999,29.691011],"type":"Point"}
}