{
  "type": "Feature",
  "properties": {
    "iso:country":"US",
    "sg:address":"2936 Trenton Rd",
    "sg:city":"Houston",
    "sg:classifiers":[
        {
            "category":"Building & Trades",
            "subcategory":"Cleaning & Sanitation",
            "type":"Services"
        }
    ],
    "sg:phone":"+1 713 694 7646",
    "sg:postcode":"77093",
    "sg:province":"TX",
    "sg:tags":[
        "maintenance"
    ],
    "wof:name":"Itb Cleaning Services",
    "wof:placetype":"venue"
},
  "geometry": {"coordinates":[-95.33883899999999,29.872204],"type":"Point"}
}