{
  "type": "Feature",
  "properties": {
    "iso:country":"US",
    "sg:address":"2148 Waldron Rd",
    "sg:city":"Corpus Christi",
    "sg:classifiers":[
        {
            "category":"Professional",
            "subcategory":"Employment Agencies",
            "type":"Services"
        }
    ],
    "sg:phone":"+1 361 937 6800",
    "sg:postcode":"78418",
    "sg:province":"TX",
    "sg:tags":[
        "labor",
        "supply"
    ],
    "wof:name":"Labor Ready 1435",
    "wof:placetype":"venue"
},
  "geometry": {"coordinates":[-97.29245299999999,27.652321],"type":"Point"}
}