{
  "type": "Feature",
  "properties": {
    "iso:country":"US",
    "sg:address":"9663 S Fm 225",
    "sg:city":"Nacogdoches",
    "sg:classifiers":[
        {
            "category":"Farming",
            "subcategory":"Farm",
            "type":"Manufacturing & Wholesale Goods"
        }
    ],
    "sg:phone":"+1 936 564 3583",
    "sg:postcode":"75964",
    "sg:province":"TX",
    "wof:name":"Farm Residence",
    "wof:placetype":"venue"
},
  "geometry": {"coordinates":[-94.79095,31.583707],"type":"Point"}
}