{
  "type": "Feature",
  "properties": {
    "iso:country":"US",
    "sg:address":"115 W Glenview Dr",
    "sg:city":"San Antonio",
    "sg:classifiers":[
        {
            "category":"Retail",
            "subcategory":"Car Wash",
            "type":"Services"
        }
    ],
    "sg:phone":"+1 210 738 2712",
    "sg:postcode":"78228",
    "sg:province":"TX",
    "sg:tags":[
        "polishing",
        "washing"
    ],
    "wof:name":"E H Krahn",
    "wof:placetype":"venue"
},
  "geometry": {"coordinates":[-98.561002,29.484461],"type":"Point"}
}