{
  "type": "Feature",
  "properties": {
    "iso:country":"US",
    "sg:address":"3006 W Beauregard Ave",
    "sg:city":"San Angelo",
    "sg:classifiers":[
        {
            "category":"Insurance",
            "subcategory":"Insurance Agent",
            "type":"Services"
        }
    ],
    "sg:phone":"+1 325 949 8994",
    "sg:postcode":"76901",
    "sg:province":"TX",
    "wof:name":"Jenkins & Assoc Insur Agcy",
    "wof:placetype":"venue"
},
  "geometry": {"coordinates":[-100.476472,31.444709],"type":"Point"}
}