{
  "type": "Feature",
  "properties": {
    "iso:country":"US",
    "sg:address":"209 E Ben White Blvd",
    "sg:city":"Austin",
    "sg:classifiers":[
        {
            "category":"Home & Garden",
            "subcategory":"Carpets & Floor Coverings",
            "type":"Retail Goods"
        }
    ],
    "sg:phone":"+1 512 440 7179",
    "sg:postcode":"78704",
    "sg:province":"TX",
    "sg:tags":[
        "dealer",
        "rug"
    ],
    "sg:website":"www.butlerfloors.com",
    "wof:name":"Butler Floors",
    "wof:placetype":"venue"
},
  "geometry": {"coordinates":[-97.762062,30.222349],"type":"Point"}
}