{
  "type": "Feature",
  "properties": {
    "iso:country":"US",
    "sg:address":"1021 N Main St",
    "sg:city":"Taylor",
    "sg:classifiers":[
        {
            "category":"Shopping",
            "subcategory":"Department Store",
            "type":"Retail Goods"
        },
        {
            "category":"Shopping",
            "subcategory":"Discount & Variety Stores",
            "type":"Retail Goods"
        }
    ],
    "sg:phone":"+1 512 352 3337",
    "sg:postcode":"76574",
    "sg:province":"TX",
    "sg:website":"http://www.kmart.com",
    "wof:name":"G K Mart",
    "wof:placetype":"venue"
},
  "geometry": {"coordinates":[-97.410251,30.57637],"type":"Point"}
}