{
  "type": "Feature",
  "properties": {
    "iso:country":"US",
    "sg:address":"604 State Hwy 36",
    "sg:city":"Rogers",
    "sg:classifiers":[
        {
            "category":"Building & Trades",
            "subcategory":"Plumbing",
            "type":"Services"
        }
    ],
    "sg:phone":"+1 254 642 3463",
    "sg:postcode":"76569",
    "sg:province":"TX",
    "sg:tags":[
        "plumbing",
        "contractor"
    ],
    "wof:name":"Young's Air Conditioning Htg",
    "wof:placetype":"venue"
},
  "geometry": {"coordinates":[-97.232657,30.935941],"type":"Point"}
}