{
  "type": "Feature",
  "properties": {
    "iso:country":"US",
    "sg:address":"528 W Bay Area Blvd",
    "sg:city":"Webster",
    "sg:classifiers":[
        {
            "category":"Bakery",
            "type":"Food & Drink"
        }
    ],
    "sg:menulink":"http://www.allmenus.com/tx/houston/15711-kolache-factory/menu/",
    "sg:phone":"+1 281 557 2253",
    "sg:postcode":"77598",
    "sg:province":"TX",
    "sg:tags":[
        "new",
        "american",
        "pastry"
    ],
    "wof:name":"Kolache Factory",
    "wof:placetype":"venue"
},
  "geometry": {"coordinates":[-95.133483,29.545341],"type":"Point"}
}