{
  "type": "Feature",
  "properties": {
    "iso:country":"US",
    "sg:address":"7748 Dentcrest Dr",
    "sg:city":"Dallas",
    "sg:classifiers":[
        {
            "category":"Home & Garden",
            "subcategory":"Building Materials",
            "type":"Retail Goods"
        }
    ],
    "sg:phone":"+1 972 788 9021",
    "sg:postcode":"75254",
    "sg:province":"TX",
    "sg:tags":[
        "windows"
    ],
    "wof:name":"Window Wizards",
    "wof:placetype":"venue"
},
  "geometry": {"coordinates":[-96.77332,32.949723],"type":"Point"}
}