{
  "type": "Feature",
  "properties": {
    "iso:country":"US",
    "sg:address":"479 S Minter St",
    "sg:city":"Stephenville",
    "sg:classifiers":[
        {
            "category":"Retail",
            "subcategory":"Auto Repair",
            "type":"Services"
        }
    ],
    "sg:phone":"+1 254 965 4647",
    "sg:postcode":"76401",
    "sg:province":"TX",
    "sg:tags":[
        "towing",
        "wrecker"
    ],
    "wof:name":"Lightnin's Body Shop & Wrecker Service",
    "wof:placetype":"venue"
},
  "geometry": {"coordinates":[-98.19555800000001,32.220625],"type":"Point"}
}