{
  "type": "Feature",
  "properties": {
    "iso:country":"US",
    "sg:address":"4400 Town Plaza Dr Ste 106",
    "sg:city":"Houston",
    "sg:classifiers":[
        {
            "category":"Personal",
            "type":"Services"
        }
    ],
    "sg:phone":"+1 713 726 8963",
    "sg:postcode":"77045",
    "sg:province":"TX",
    "sg:tags":[
        "party",
        "planning",
        "event"
    ],
    "sg:website":"www.margaritatyme.com",
    "wof:name":"Margarita Tyme",
    "wof:placetype":"venue"
},
  "geometry": {"coordinates":[-95.444796,29.645889],"type":"Point"}
}