{
  "type": "Feature",
  "properties": {
    "iso:country":"US",
    "sg:address":"1015 Western Meadows Dr",
    "sg:city":"Katy",
    "sg:classifiers":[
        {
            "category":"Building & Trades",
            "subcategory":"Pest Control",
            "type":"Services"
        }
    ],
    "sg:phone":"+1 281 395 3333",
    "sg:postcode":"77450",
    "sg:province":"TX",
    "sg:tags":[
        "industrial",
        "services-commercial"
    ],
    "sg:website":"http://springbranchexterminators.com",
    "wof:name":"Spring Branch Exterminators",
    "wof:placetype":"venue"
},
  "geometry": {"coordinates":[-95.766687,29.767171],"type":"Point"}
}