{
  "type": "Feature",
  "properties": {
    "iso:country":"US",
    "sg:address":"4201 E Lancaster Ave",
    "sg:city":"Fort Worth",
    "sg:classifiers":[
        {
            "category":"Autos & Motor Vehicles",
            "subcategory":"Fuel & Gas Station",
            "type":"Retail Goods"
        }
    ],
    "sg:phone":"+1 817 536 2556",
    "sg:postcode":"76103",
    "sg:province":"TX",
    "sg:tags":[
        "grocery",
        "station",
        "gasoline"
    ],
    "wof:name":"J & J Quick Stop",
    "wof:placetype":"venue"
},
  "geometry": {"coordinates":[-97.257796,32.740966],"type":"Point"}
}