{
  "type": "Feature",
  "properties": {
    "iso:country":"US",
    "sg:address":"525 Century Dr W",
    "sg:city":"Laredo",
    "sg:classifiers":[
        {
            "category":"Freight",
            "type":"Transportation"
        }
    ],
    "sg:phone":"+1 956 717 0107",
    "sg:postcode":"78046",
    "sg:province":"TX",
    "sg:tags":[
        "arrangement"
    ],
    "wof:name":"Sb International Shipping Co",
    "wof:placetype":"venue"
},
  "geometry": {"coordinates":[-99.454494,27.487157],"type":"Point"}
}