{
  "type": "Feature",
  "properties": {
    "iso:country":"US",
    "sg:address":"223 Sunset Blvd",
    "sg:city":"Sherman",
    "sg:classifiers":[
        {
            "category":"Personal",
            "subcategory":"Beauty Salon",
            "type":"Services"
        }
    ],
    "sg:phone":"+1 903 868 2779",
    "sg:postcode":"75092",
    "sg:province":"TX",
    "sg:tags":[
        "shop"
    ],
    "wof:name":"Only Nails",
    "wof:placetype":"venue"
},
  "geometry": {"coordinates":[-96.628204,33.633506],"type":"Point"}
}