{
  "type": "Feature",
  "properties": {
    "iso:country":"US",
    "sg:address":"6338 Lake Worth Blvd",
    "sg:city":"Fort Worth",
    "sg:classifiers":[
        {
            "category":"Restaurant",
            "type":"Food & Drink"
        }
    ],
    "sg:menulink":"http://www.allmenus.com/tx/fort-worth/90977-wingstop/menu/",
    "sg:phone":"+1 817 237 2500",
    "sg:postcode":"76135",
    "sg:province":"TX",
    "sg:tags":[
        "american",
        "wing"
    ],
    "wof:name":"Wingstop",
    "wof:placetype":"venue"
},
  "geometry": {"coordinates":[-97.423119,32.81005],"type":"Point"}
}