{
  "type": "Feature",
  "properties": {
    "iso:country":"US",
    "sg:address":"804 US Hwy 83",
    "sg:city":"Zapata",
    "sg:classifiers":[
        {
            "category":"Mining & Drilling",
            "type":"Manufacturing & Wholesale Goods"
        }
    ],
    "sg:phone":"+1 956 765 0931",
    "sg:postcode":"78076",
    "sg:province":"TX",
    "sg:tags":[
        "oil",
        "gas",
        "producer"
    ],
    "wof:name":"Aspen Exploration Inc",
    "wof:placetype":"venue"
},
  "geometry": {"coordinates":[-99.26862199999999,26.903729],"type":"Point"}
}