{
  "type": "Feature",
  "properties": {
    "iso:country":"US",
    "sg:address":"301 N 5th St",
    "sg:city":"Raymondville",
    "sg:classifiers":[
        {
            "category":"Organizations",
            "subcategory":"Religious Organization",
            "type":"Services"
        }
    ],
    "sg:phone":"+1 956 689 2911",
    "sg:postcode":"78580",
    "sg:province":"TX",
    "sg:tags":[
        "church"
    ],
    "wof:name":"First Baptist Church",
    "wof:placetype":"venue"
},
  "geometry": {"coordinates":[-97.78546799999999,26.484925],"type":"Point"}
}