{
  "type": "Feature",
  "properties": {
    "iso:country":"US",
    "sg:address":"1807 E Levee St",
    "sg:city":"Dallas",
    "sg:classifiers":[
        {
            "category":"Manufacturing",
            "subcategory":"Tools & Machinery",
            "type":"Manufacturing & Wholesale Goods"
        }
    ],
    "sg:phone":"+1 214 748 3877",
    "sg:postcode":"75207",
    "sg:province":"TX",
    "sg:tags":[
        "model",
        "maker"
    ],
    "wof:name":"To Scale",
    "wof:placetype":"venue"
},
  "geometry": {"coordinates":[-96.828259,32.79142],"type":"Point"}
}