{
  "type": "Feature",
  "properties": {
    "iso:country":"US",
    "sg:address":"13 Club Estates Pkwy",
    "sg:city":"Austin",
    "sg:classifiers":[
        {
            "category":"Professional",
            "subcategory":"Management & Consulting",
            "type":"Services"
        }
    ],
    "sg:phone":"+1 512 261 5494",
    "sg:postcode":"78738",
    "sg:province":"TX",
    "wof:name":"Allen Real Estate LP",
    "wof:placetype":"venue"
},
  "geometry": {"coordinates":[-97.99374899999999,30.348838],"type":"Point"}
}