{
  "type": "Feature",
  "properties": {
    "iso:country":"US",
    "sg:address":"2300 Maxfield Ln",
    "sg:city":"Carrollton",
    "sg:classifiers":[
        {
            "category":"Shopping",
            "type":"Retail Goods"
        }
    ],
    "sg:phone":"+1 972 253 6000",
    "sg:postcode":"75006",
    "sg:province":"TX",
    "sg:tags":[
        "equipment",
        "telephone",
        "supply"
    ],
    "wof:name":"Telephone Technical Svc",
    "wof:placetype":"venue"
},
  "geometry": {"coordinates":[-96.882859,32.978811],"type":"Point"}
}