{
  "type": "Feature",
  "properties": {
    "iso:country":"US",
    "sg:address":"6973 FM 1082",
    "sg:city":"Abilene",
    "sg:phone":"+1 325 537 2467",
    "sg:postcode":"79525",
    "sg:province":"TX",
    "sg:tags":[
        "farm",
        "wheat"
    ],
    "wof:name":"Bob Keesee",
    "wof:placetype":"venue"
},
  "geometry": {"coordinates":[-99.730547,32.59943],"type":"Point"}
}