{
  "type": "Feature",
  "properties": {
    "iso:country":"US",
    "sg:address":"1501 Gaylord Trl",
    "sg:city":"Grapevine",
    "sg:phone":"+1 817 756 1837",
    "sg:postcode":"76051",
    "sg:province":"TX",
    "sg:website":"http://fortworth.citysearch.com/profile/external/43055786/grapevine_tx/old_hickory.html?publisher=yellowpages&reference_id=1&placement=ypwebsitemip",
    "wof:name":"Old Hickory",
    "wof:placetype":"venue"
},
  "geometry": {"coordinates":[-97.06240099999999,32.955139],"type":"Point"}
}