{
  "type": "Feature",
  "properties": {
    "iso:country":"US",
    "sg:address":"3737 E Jefferson St",
    "sg:city":"Grand Prairie",
    "sg:classifiers":[
        {
            "category":"Home & Garden",
            "subcategory":"Household Appliances",
            "type":"Retail Goods"
        }
    ],
    "sg:phone":"+1 972 262 6161",
    "sg:postcode":"75051",
    "sg:province":"TX",
    "wof:name":"Walker Hating-Air Conditioning",
    "wof:placetype":"venue"
},
  "geometry": {"coordinates":[-96.94347,32.746658],"type":"Point"}
}