{
  "type": "Feature",
  "properties": {
    "iso:country":"US",
    "sg:address":"8080 N Stadium Dr",
    "sg:city":"Houston",
    "sg:classifiers":[
        {
            "category":"Professional",
            "subcategory":"Research",
            "type":"Services"
        }
    ],
    "sg:phone":"+1 713 467 8500",
    "sg:postcode":"77054",
    "sg:province":"TX",
    "sg:tags":[
        "biological",
        "laboratory",
        "biotechnology"
    ],
    "wof:name":"Spectral Genomics Inc",
    "wof:placetype":"venue"
},
  "geometry": {"coordinates":[-95.40779000000001,29.691548],"type":"Point"}
}