{
  "type": "Feature",
  "properties": {
    "iso:country":"US",
    "sg:address":"3804 John Stockbauer Dr",
    "sg:city":"Victoria",
    "sg:classifiers":[
        {
            "category":"Personal",
            "subcategory":"Beauty Salon",
            "type":"Services"
        }
    ],
    "sg:phone":"+1 361 580 3113",
    "sg:postcode":"77904",
    "sg:province":"TX",
    "sg:tags":[
        "shop",
        "manicuring"
    ],
    "wof:name":"Nail Spa",
    "wof:placetype":"venue"
},
  "geometry": {"coordinates":[-96.94687999999999,28.817815],"type":"Point"}
}