{
  "type": "Feature",
  "properties": {
    "iso:country":"US",
    "sg:address":"150 S Bell Blvd",
    "sg:city":"Cedar Park",
    "sg:classifiers":[
        {
            "category":"Banks & Credit Unions",
            "subcategory":"Bank",
            "type":"Services"
        }
    ],
    "sg:phone":"+1 512 258 7720",
    "sg:postcode":"78613",
    "sg:province":"TX",
    "sg:tags":[
        "national"
    ],
    "wof:name":"Bank of America",
    "wof:placetype":"venue"
},
  "geometry": {"coordinates":[-97.822845,30.508316],"type":"Point"}
}