{
  "type": "Feature",
  "properties": {
    "iso:country":"US",
    "sg:address":"5805 Callaghan Rd",
    "sg:city":"San Antonio",
    "sg:classifiers":[
        {
            "category":"Personal",
            "type":"Services"
        },
        {
            "category":"Sports & Exercise",
            "subcategory":"Gym",
            "type":"Entertainment"
        }
    ],
    "sg:phone":"+1 210 647 0000",
    "sg:postcode":"78228",
    "sg:province":"TX",
    "sg:tags":[
        "therapist",
        "fitness",
        "physical",
        "massage",
        "facility"
    ],
    "wof:name":"Art of Touch Massage",
    "wof:placetype":"venue"
},
  "geometry": {"coordinates":[-98.57863999999999,29.485132],"type":"Point"}
}