{
  "type": "Feature",
  "properties": {
    "iso:country":"US",
    "sg:address":"2209 Robinhood St",
    "sg:city":"Houston",
    "sg:classifiers":[
        {
            "category":"Mining & Drilling",
            "type":"Manufacturing & Wholesale Goods"
        }
    ],
    "sg:phone":"+1 713 521 0239",
    "sg:postcode":"77005",
    "sg:province":"TX",
    "sg:tags":[
        "field"
    ],
    "wof:name":"Sea Spirit Ventures Inc",
    "wof:placetype":"venue"
},
  "geometry": {"coordinates":[-95.41256,29.721052],"type":"Point"}
}