{
  "type": "Feature",
  "properties": {
    "iso:country":"US",
    "sg:address":"14707 Kings Head Dr",
    "sg:city":"Houston",
    "sg:classifiers":[
        {
            "category":"Banks & Credit Unions",
            "subcategory":"Financial Services",
            "type":"Services"
        }
    ],
    "sg:phone":"+1 281 458 3416",
    "sg:postcode":"77044",
    "sg:province":"TX",
    "sg:tags":[
        "investor"
    ],
    "wof:name":"Aaron Investments",
    "wof:placetype":"venue"
},
  "geometry": {"coordinates":[-95.18499199999999,29.932043],"type":"Point"}
}