{
  "type": "Feature",
  "properties": {
    "iso:country":"US",
    "sg:address":"4300 Kemp Blvd",
    "sg:city":"Wichita Falls",
    "sg:classifiers":[
        {
            "category":"Shopping",
            "subcategory":"Clothing, Apparel, & Fashions",
            "type":"Retail Goods"
        }
    ],
    "sg:phone":"+1 940 691 6012",
    "sg:postcode":"76308",
    "sg:province":"TX",
    "sg:tags":[
        "western"
    ],
    "wof:name":"Cooley's Western Wear",
    "wof:placetype":"venue"
},
  "geometry": {"coordinates":[-98.53600900000001,33.864298],"type":"Point"}
}