{
  "type": "Feature",
  "properties": {
    "iso:country":"US",
    "sg:address":"3606 Maple Ave",
    "sg:city":"Dallas",
    "sg:classifiers":[
        {
            "category":"Organizations",
            "subcategory":"Non-profit Organization",
            "type":"Services"
        }
    ],
    "sg:phone":"+1 214 521 2193",
    "sg:postcode":"75219",
    "sg:province":"TX",
    "sg:tags":[
        "info",
        "addiction",
        "abuse",
        "treatment",
        "drug"
    ],
    "wof:name":"Cornell Corrections Of Texas",
    "wof:placetype":"venue"
},
  "geometry": {"coordinates":[-96.81317900000001,32.803225],"type":"Point"}
}