{
  "type": "Feature",
  "properties": {
    "iso:country":"US",
    "sg:address":"337 Stein Ct",
    "sg:city":"New Braunfels",
    "sg:classifiers":[
        {
            "category":"Banks & Credit Unions",
            "subcategory":"Bank",
            "type":"Services"
        }
    ],
    "sg:phone":"+1 830 608 1180",
    "sg:postcode":"78130",
    "sg:province":"TX",
    "sg:tags":[
        "loan",
        "real estate"
    ],
    "wof:name":"First Alliance Mortgage",
    "wof:placetype":"venue"
},
  "geometry": {"coordinates":[-98.120088,29.702156],"type":"Point"}
}