{
  "type": "Feature",
  "properties": {
    "iso:country":"US",
    "sg:address":"404 E Carolanne Blvd",
    "sg:city":"Marshall",
    "sg:classifiers":[
        {
            "category":"Building & Trades",
            "subcategory":"Construction",
            "type":"Services"
        }
    ],
    "sg:phone":"+1 903 935 2938",
    "sg:postcode":"75672",
    "sg:province":"TX",
    "sg:tags":[
        "concrete",
        "contractor"
    ],
    "wof:name":"Tex Mex Concrete",
    "wof:placetype":"venue"
},
  "geometry": {"coordinates":[-94.35668800000001,32.516949],"type":"Point"}
}