{
  "type": "Feature",
  "properties": {
    "iso:country":"US",
    "sg:address":"4114 Texoma Pkwy",
    "sg:city":"Sherman",
    "sg:classifiers":[
        {
            "category":"Building & Trades",
            "subcategory":"Plumbing",
            "type":"Services"
        }
    ],
    "sg:phone":"+1 903 893 5588",
    "sg:postcode":"75090",
    "sg:province":"TX",
    "sg:tags":[
        "conditioning",
        "air",
        "system",
        "contractor"
    ],
    "sg:website":"www.graysonclimate.com",
    "wof:name":"Grayson Climate Engineers Inc",
    "wof:placetype":"venue"
},
  "geometry": {"coordinates":[-96.585224,33.681897],"type":"Point"}
}