{
  "type": "Feature",
  "properties": {
    "iso:country":"US",
    "sg:address":"405 N Carrizo St",
    "sg:city":"Midland",
    "sg:classifiers":[
        {
            "category":"Real Estate",
            "subcategory":"Real Estate Operator",
            "type":"Services"
        }
    ],
    "sg:phone":"+1 432 683 1091",
    "sg:postcode":"79701",
    "sg:province":"TX",
    "sg:tags":[
        "apartment"
    ],
    "wof:name":"Ocotillo Apartments",
    "wof:placetype":"venue"
},
  "geometry": {"coordinates":[-102.081937,32.001484],"type":"Point"}
}