{
  "type": "Feature",
  "properties": {
    "iso:country":"US",
    "sg:address":"1115 Coke St",
    "sg:city":"Laredo",
    "sg:classifiers":[
        {
            "category":"Professional",
            "subcategory":"Business Services",
            "type":"Services"
        }
    ],
    "sg:phone":"+1 956 723 4532",
    "sg:postcode":"78040",
    "sg:province":"TX",
    "wof:name":"Lares Bail Bonds",
    "wof:placetype":"venue"
},
  "geometry": {"coordinates":[-99.50733700000001,27.511492],"type":"Point"}
}