{
  "type": "Feature",
  "properties": {
    "iso:country":"US",
    "sg:address":"6214 Bardet St",
    "sg:city":"Pearland",
    "sg:classifiers":[
        {
            "category":"Retail",
            "subcategory":"Auto Repair",
            "type":"Services"
        }
    ],
    "sg:phone":"+1 281 485 3509",
    "sg:postcode":"77584",
    "sg:province":"TX",
    "sg:tags":[
        "truck"
    ],
    "wof:name":"Kliesing Diesel Svc",
    "wof:placetype":"venue"
},
  "geometry": {"coordinates":[-95.310811,29.554921],"type":"Point"}
}