{
  "type": "Feature",
  "properties": {
    "iso:country":"US",
    "sg:address":"630 Maxey Rd",
    "sg:city":"Houston",
    "sg:classifiers":[
        {
            "category":"Retail",
            "subcategory":"Auto Repair",
            "type":"Services"
        }
    ],
    "sg:phone":"+1 713 451 3444",
    "sg:postcode":"77013",
    "sg:province":"TX",
    "sg:tags":[
        "transmission"
    ],
    "wof:name":"Millenium Transmissions",
    "wof:placetype":"venue"
},
  "geometry": {"coordinates":[-95.21859000000001,29.780647],"type":"Point"}
}