{
  "type": "Feature",
  "properties": {
    "iso:country":"US",
    "sg:address":"1140 Westmont Dr",
    "sg:city":"Houston",
    "sg:classifiers":[
        {
            "category":"Shopping",
            "subcategory":"Optical Goods",
            "type":"Retail Goods"
        }
    ],
    "sg:phone":"+1 713 453 8499",
    "sg:postcode":"77015",
    "sg:province":"TX",
    "wof:name":"East Houston Optical",
    "wof:placetype":"venue"
},
  "geometry": {"coordinates":[-95.194512,29.773365],"type":"Point"}
}