{
  "type": "Feature",
  "properties": {
    "iso:country":"US",
    "sg:address":"5956 Sherry Ln",
    "sg:city":"Dallas",
    "sg:classifiers":[
        {
            "category":"Mining & Drilling",
            "type":"Manufacturing & Wholesale Goods"
        }
    ],
    "sg:phone":"+1 214 346 2991",
    "sg:postcode":"75225",
    "sg:province":"TX",
    "sg:tags":[
        "security",
        "exploration"
    ],
    "wof:name":"Doman Capital Partners Inc",
    "wof:placetype":"venue"
},
  "geometry": {"coordinates":[-96.810238,32.862216],"type":"Point"}
}