{
  "type": "Feature",
  "properties": {
    "iso:country":"US",
    "sg:address":"323 N Main St",
    "sg:city":"Sweeny",
    "sg:classifiers":[
        {
            "category":"Shopping",
            "subcategory":"Discount & Variety Stores",
            "type":"Retail Goods"
        },
        {
            "category":"Shopping",
            "subcategory":"Department Store",
            "type":"Retail Goods"
        }
    ],
    "sg:phone":"+1 979 548 2821",
    "sg:postcode":"77480",
    "sg:province":"TX",
    "sg:tags":[
        "shop"
    ],
    "wof:name":"Family Dollar Stores",
    "wof:placetype":"venue"
},
  "geometry": {"coordinates":[-95.70029599999999,29.04008],"type":"Point"}
}