{
  "type": "Feature",
  "properties": {
    "iso:country":"US",
    "sg:address":"9401 Mixon Dr",
    "sg:city":"Dallas",
    "sg:classifiers":[
        {
            "category":"Real Estate",
            "subcategory":"Real Estate Operator",
            "type":"Services"
        }
    ],
    "sg:phone":"+1 214 352 7773",
    "sg:postcode":"75220",
    "sg:province":"TX",
    "sg:tags":[
        "apartment"
    ],
    "wof:name":"Richelieu Apartments",
    "wof:placetype":"venue"
},
  "geometry": {"coordinates":[-96.853014,32.861711],"type":"Point"}
}