{
  "type": "Feature",
  "properties": {
    "iso:country":"US",
    "sg:address":"25911 I- 45",
    "sg:city":"Spring",
    "sg:classifiers":[
        {
            "category":"Health Services",
            "subcategory":"Clinic",
            "type":"Services"
        }
    ],
    "sg:phone":"+1 281 363 0783",
    "sg:postcode":"77380",
    "sg:province":"TX",
    "sg:tags":[
        "hypnotherapy"
    ],
    "wof:name":"Woodlands Hypnosis",
    "wof:placetype":"venue"
},
  "geometry": {"coordinates":[-95.44605300000001,30.137919],"type":"Point"}
}