{
  "type": "Feature",
  "properties": {
    "iso:country":"US",
    "sg:address":"109 E Main St",
    "sg:city":"Fredericksburg",
    "sg:classifiers":[
        {
            "category":"Shopping",
            "subcategory":"Gifts & Souvenirs",
            "type":"Retail Goods"
        }
    ],
    "sg:phone":"+1 830 997 6444",
    "sg:postcode":"78624",
    "sg:province":"TX",
    "sg:tags":[
        "shop"
    ],
    "wof:name":"Remember Me Too",
    "wof:placetype":"venue"
},
  "geometry": {"coordinates":[-98.87221099999999,30.274942],"type":"Point"}
}