{
  "type": "Feature",
  "properties": {
    "iso:country":"US",
    "sg:address":"4245 Kemp Blvd",
    "sg:city":"Wichita Falls",
    "sg:classifiers":[
        {
            "category":"Insurance",
            "subcategory":"Insurance Agent",
            "type":"Services"
        }
    ],
    "sg:phone":"+1 940 692 0777",
    "sg:postcode":"76308",
    "sg:province":"TX",
    "wof:name":"Met Life",
    "wof:placetype":"venue"
},
  "geometry": {"coordinates":[-98.535905,33.869751],"type":"Point"}
}