{
  "type": "Feature",
  "properties": {
    "iso:country":"US",
    "sg:address":"3315 Ozark St",
    "sg:city":"Houston",
    "sg:classifiers":[
        {
            "category":"Social Services",
            "subcategory":"Child Care",
            "type":"Services"
        }
    ],
    "sg:phone":"+1 713 747 5118",
    "sg:postcode":"77021",
    "sg:province":"TX",
    "sg:tags":[
        "day"
    ],
    "wof:name":"Foster Stars Lrng & Resource",
    "wof:placetype":"venue"
},
  "geometry": {"coordinates":[-95.368771,29.705924],"type":"Point"}
}