{
  "type": "Feature",
  "properties": {
    "iso:country":"US",
    "sg:address":"5153 E Berry St",
    "sg:city":"Fort Worth",
    "sg:classifiers":[
        {
            "category":"Organizations",
            "subcategory":"Religious Organization",
            "type":"Services"
        }
    ],
    "sg:phone":"+1 817 496 1039",
    "sg:postcode":"76119",
    "sg:province":"TX",
    "sg:tags":[
        "church"
    ],
    "wof:name":"Shekinah House Of Worship",
    "wof:placetype":"venue"
},
  "geometry": {"coordinates":[-97.24298,32.709216],"type":"Point"}
}