{
  "type": "Feature",
  "properties": {
    "iso:country":"US",
    "sg:address":"4217 Barnsley Dr",
    "sg:city":"Plano",
    "sg:classifiers":[
        {
            "category":"Professional",
            "subcategory":"Computer Services",
            "type":"Services"
        }
    ],
    "sg:phone":"+1 972 312 1889",
    "sg:postcode":"75093",
    "sg:province":"TX",
    "sg:tags":[
        "system",
        "integration"
    ],
    "wof:name":"Ewings Technologies Inc",
    "wof:placetype":"venue"
},
  "geometry": {"coordinates":[-96.77474100000001,33.039692],"type":"Point"}
}