{
  "type": "Feature",
  "properties": {
    "iso:country":"US",
    "sg:address":"1055 Clarksville St",
    "sg:city":"Paris",
    "sg:classifiers":[
        {
            "category":"Health Services",
            "subcategory":"Doctor",
            "type":"Services"
        }
    ],
    "sg:phone":"+1 903 739 7300",
    "sg:postcode":"75460",
    "sg:province":"TX",
    "sg:tags":[
        "physician",
        "medical",
        "surgeon"
    ],
    "wof:name":"Kyle E Jones MD",
    "wof:placetype":"venue"
},
  "geometry": {"coordinates":[-95.545299,33.659952],"type":"Point"}
}