{
  "type": "Feature",
  "properties": {
    "iso:country":"US",
    "sg:address":"711 W Bay Area Blvd Ste 105",
    "sg:city":"Webster",
    "sg:classifiers":[
        {
            "category":"Insurance",
            "subcategory":"Insurance Agent",
            "type":"Services"
        },
        {
            "category":"Insurance",
            "subcategory":"Hazard Insurance",
            "type":"Services"
        },
        {
            "category":"Insurance",
            "subcategory":"Health Insurance",
            "type":"Services"
        }
    ],
    "sg:phone":"+1 281 557 3330",
    "sg:postcode":"77598",
    "sg:province":"TX",
    "sg:tags":[
        "employee",
        "auto",
        "benefit",
        "commercial",
        "business"
    ],
    "sg:website":"http://www.farmersagent.com/wfinley",
    "wof:name":"Weldon Finley - Farmers Insurance",
    "wof:placetype":"venue"
},
  "geometry": {"coordinates":[-95.134795,29.544204],"type":"Point"}
}