{
  "type": "Feature",
  "properties": {
    "iso:country":"US",
    "sg:address":"419 W Broad St",
    "sg:city":"Freeport",
    "sg:classifiers":[
        {
            "category":"Social Services",
            "subcategory":"Child Care",
            "type":"Services"
        }
    ],
    "sg:phone":"+1 979 230 9933",
    "sg:postcode":"77541",
    "sg:province":"TX",
    "wof:name":"Luna Daycare",
    "wof:placetype":"venue"
},
  "geometry": {"coordinates":[-95.35083400000001,28.950502],"type":"Point"}
}