{
  "type": "Feature",
  "properties": {
    "iso:country":"US",
    "sg:address":"47 The Oval St",
    "sg:city":"Sugar Land",
    "sg:classifiers":[
        {
            "category":"Professional",
            "subcategory":"Business Services",
            "type":"Services"
        }
    ],
    "sg:phone":"+1 281 313 1957",
    "sg:postcode":"77479",
    "sg:province":"TX",
    "sg:tags":[
        "interior",
        "design",
        "furniture"
    ],
    "wof:name":"Griffin Fine Interiors",
    "wof:placetype":"venue"
},
  "geometry": {"coordinates":[-95.61489899999999,29.569792],"type":"Point"}
}