{
  "type": "Feature",
  "properties": {
    "iso:country":"US",
    "sg:address":"1321 N Richmond Rd",
    "sg:city":"Wharton",
    "sg:classifiers":[
        {
            "category":"Restaurant",
            "type":"Food & Drink"
        },
        {
            "category":"Ice Cream",
            "type":"Food & Drink"
        }
    ],
    "sg:menulink":"http://www.allmenus.com/tx/wharton/162582-dairy-queen/menu/",
    "sg:phone":"+1 409 532 5180",
    "sg:postcode":"77488",
    "sg:province":"TX",
    "sg:tags":[
        "burger",
        "american",
        "ice",
        "cream"
    ],
    "wof:name":"Dairy Queen",
    "wof:placetype":"venue"
},
  "geometry": {"coordinates":[-96.098271,29.322602],"type":"Point"}
}