{
  "type": "Feature",
  "properties": {
    "iso:country":"US",
    "sg:address":"6905 Hyde Park Dr",
    "sg:city":"Dallas",
    "sg:classifiers":[
        {
            "category":"Shopping",
            "subcategory":"Pets & Pet Supplies",
            "type":"Retail Goods"
        }
    ],
    "sg:phone":"+1 214 348 3852",
    "sg:postcode":"75231",
    "sg:province":"TX",
    "sg:tags":[
        "furnishing",
        "dog",
        "store",
        "cat"
    ],
    "wof:name":"Seniors' Pet Assistance Network",
    "wof:placetype":"venue"
},
  "geometry": {"coordinates":[-96.737099,32.871828],"type":"Point"}
}