{
  "type": "Feature",
  "properties": {
    "iso:country":"US",
    "sg:address":"4445 Alpha Rd",
    "sg:city":"Dallas",
    "sg:classifiers":[
        {
            "category":"Insurance",
            "subcategory":"Insurance Agent",
            "type":"Services"
        }
    ],
    "sg:phone":"+1 972 233 5100",
    "sg:postcode":"75244",
    "sg:province":"TX",
    "wof:name":"Forsythe Appraisals",
    "wof:placetype":"venue"
},
  "geometry": {"coordinates":[-96.834969,32.933112],"type":"Point"}
}