{
  "type": "Feature",
  "properties": {
    "iso:country":"US",
    "sg:address":"5307 Kayway Dr",
    "sg:city":"Greenville",
    "sg:classifiers":[
        {
            "category":"Professional",
            "subcategory":"Business Services",
            "type":"Services"
        }
    ],
    "sg:phone":"+1 903 454 4416",
    "sg:postcode":"75402",
    "sg:province":"TX",
    "wof:name":"Crd",
    "wof:placetype":"venue"
},
  "geometry": {"coordinates":[-96.105886,33.11696],"type":"Point"}
}