{
  "type": "Feature",
  "properties": {
    "iso:country":"US",
    "sg:address":"822 25th St",
    "sg:city":"Galveston",
    "sg:classifiers":[
        {
            "category":"Professional",
            "subcategory":"Advertising",
            "type":"Services"
        }
    ],
    "sg:phone":"+1 409 795 2218",
    "sg:postcode":"77550",
    "sg:province":"TX",
    "sg:tags":[
        "distribution"
    ],
    "wof:name":"Del Papa Distributors",
    "wof:placetype":"venue"
},
  "geometry": {"coordinates":[-94.79477300000001,29.301094],"type":"Point"}
}