{
  "type": "Feature",
  "properties": {
    "iso:country":"US",
    "sg:address":"32826 Crestlake Blvd",
    "sg:city":"Magnolia",
    "sg:classifiers":[
        {
            "category":"Organizations",
            "subcategory":"Religious Organization",
            "type":"Services"
        }
    ],
    "sg:phone":"+1 281 750 6078",
    "sg:postcode":"77354",
    "sg:province":"TX",
    "wof:name":"The Woodlands Christian Counseling Center Inc",
    "wof:placetype":"venue"
},
  "geometry": {"coordinates":[-95.62704100000001,30.217185],"type":"Point"}
}