{
  "type": "Feature",
  "properties": {
    "iso:country":"US",
    "sg:address":"1001 Ave B",
    "sg:city":"Lubbock",
    "sg:classifiers":[
        {
            "category":"Manufacturing",
            "subcategory":"Textiles",
            "type":"Manufacturing & Wholesale Goods"
        },
        {
            "category":"Manufacturing",
            "subcategory":"Furniture",
            "type":"Manufacturing & Wholesale Goods"
        }
    ],
    "sg:phone":"+1 806 747 9800",
    "sg:postcode":"79401",
    "sg:province":"TX",
    "sg:tags":[
        "blind",
        "mini",
        "vertical",
        "mfg",
        "window",
        "shade",
        "curtain"
    ],
    "wof:name":"J B Wholesale Windowcoverings",
    "wof:placetype":"venue"
},
  "geometry": {"coordinates":[-101.837502,33.585516],"type":"Point"}
}