{
  "type": "Feature",
  "properties": {
    "iso:country":"US",
    "sg:address":"1421 S Columbia Dr",
    "sg:city":"West Columbia",
    "sg:classifiers":[
        {
            "category":"Building & Trades",
            "subcategory":"Landscaping Services",
            "type":"Services"
        }
    ],
    "sg:phone":"+1 979 345 4457",
    "sg:postcode":"77486",
    "sg:province":"TX",
    "sg:tags":[
        "grass"
    ],
    "wof:name":"River Creek Farms",
    "wof:placetype":"venue"
},
  "geometry": {"coordinates":[-95.648752,29.129387],"type":"Point"}
}