{
  "type": "Feature",
  "properties": {
    "iso:country":"US",
    "sg:address":"312 S Rose St",
    "sg:city":"Texas City",
    "sg:classifiers":[
        {
            "category":"Organizations",
            "subcategory":"Religious Organization",
            "type":"Services"
        }
    ],
    "sg:phone":"+1 409 935 8121",
    "sg:postcode":"77591",
    "sg:province":"TX",
    "sg:tags":[
        "church"
    ],
    "wof:name":"Fellowship Baptist Church",
    "wof:placetype":"venue"
},
  "geometry": {"coordinates":[-94.985894,29.381576],"type":"Point"}
}