{
  "type": "Feature",
  "properties": {
    "iso:country":"US",
    "sg:address":"6931 Chasewood Dr",
    "sg:city":"Missouri City",
    "sg:classifiers":[
        {
            "category":"Professional",
            "subcategory":"Business Services",
            "type":"Services"
        }
    ],
    "sg:phone":"+1 281 416 0628",
    "sg:postcode":"77489",
    "sg:province":"TX",
    "sg:tags":[
        "liquidator"
    ],
    "wof:name":"Kh Liquidating",
    "wof:placetype":"venue"
},
  "geometry": {"coordinates":[-95.49373900000001,29.605086],"type":"Point"}
}