{
  "type": "Feature",
  "properties": {
    "iso:country":"US",
    "sg:address":"2227 Handley Ederville Rd",
    "sg:city":"Fort Worth",
    "sg:classifiers":[
        {
            "category":"Building & Trades",
            "subcategory":"Electrical",
            "type":"Services"
        }
    ],
    "sg:phone":"+1 817 284 5767",
    "sg:postcode":"76118",
    "sg:province":"TX",
    "sg:tags":[
        "electric",
        "contractor"
    ],
    "sg:website":"www.jmdnow.com",
    "wof:name":"JMD & Assoc",
    "wof:placetype":"venue"
},
  "geometry": {"coordinates":[-97.21751399999999,32.779163],"type":"Point"}
}