{
  "type": "Feature",
  "properties": {
    "iso:country":"US",
    "sg:address":"915 Strickland St",
    "sg:city":"Vidor",
    "sg:classifiers":[
        {
            "category":"Building & Trades",
            "subcategory":"Construction",
            "type":"Services"
        }
    ],
    "sg:phone":"+1 409 769 9993",
    "sg:postcode":"77662",
    "sg:province":"TX",
    "wof:name":"K Wisby Asphalt Paving",
    "wof:placetype":"venue"
},
  "geometry": {"coordinates":[-93.971811,30.138963],"type":"Point"}
}