{
  "type": "Feature",
  "properties": {
    "iso:country":"US",
    "sg:address":"1309 Reagan Dr",
    "sg:city":"Laredo",
    "sg:classifiers":[
        {
            "category":"Shopping",
            "subcategory":"Gifts & Souvenirs",
            "type":"Retail Goods"
        }
    ],
    "sg:phone":"+1 956 721 0646",
    "sg:postcode":"78046",
    "sg:province":"TX",
    "wof:name":"Gifts & Gifts",
    "wof:placetype":"venue"
},
  "geometry": {"coordinates":[-99.458142,27.48416],"type":"Point"}
}