{
  "type": "Feature",
  "properties": {
    "iso:country":"US",
    "sg:address":"2201 Jacksboro Hwy",
    "sg:city":"Fort Worth",
    "sg:classifiers":[
        {
            "category":"Health Services",
            "subcategory":"Chiropractor",
            "type":"Services"
        }
    ],
    "sg:phone":"+1 817 624 4883",
    "sg:postcode":"76114",
    "sg:province":"TX",
    "sg:tags":[
        "clinic",
        "chiropractic"
    ],
    "wof:name":"Chiropractic Clinic Northside",
    "wof:placetype":"venue"
},
  "geometry": {"coordinates":[-97.378863,32.783351],"type":"Point"}
}