{
  "type": "Feature",
  "properties": {
    "iso:country":"US",
    "sg:address":"4547 Kornegay Rd",
    "sg:city":"San Benito",
    "sg:classifiers":[
        {
            "category":"Building & Trades",
            "subcategory":"Construction",
            "type":"Services"
        }
    ],
    "sg:phone":"+1 956 399 3039",
    "sg:postcode":"78586",
    "sg:province":"TX",
    "sg:tags":[
        "house"
    ],
    "wof:name":"Homes For Today Inc",
    "wof:placetype":"venue"
},
  "geometry": {"coordinates":[-97.591645,26.164133],"type":"Point"}
}