{
  "type": "Feature",
  "properties": {
    "iso:country":"US",
    "sg:address":"1007 Green Meadow Dr",
    "sg:city":"Richardson",
    "sg:classifiers":[
        {
            "category":"Real Estate",
            "subcategory":"Real Estate Agent",
            "type":"Services"
        }
    ],
    "sg:phone":"+1 972 761 9257",
    "sg:postcode":"75081",
    "sg:province":"TX",
    "wof:name":"L R Harrington Rltrs",
    "wof:placetype":"venue"
},
  "geometry": {"coordinates":[-96.687355,32.934454],"type":"Point"}
}