{
  "type": "Feature",
  "properties": {
    "iso:country":"US",
    "sg:address":"6601 Tara Dr",
    "sg:city":"Austin",
    "sg:classifiers":[
        {
            "category":"Taxi",
            "type":"Transportation"
        }
    ],
    "sg:phone":"+1 512 233 4621",
    "sg:postcode":"78747",
    "sg:province":"TX",
    "wof:name":"Roy S Taxi",
    "wof:placetype":"venue"
},
  "geometry": {"coordinates":[-97.7397,30.161989],"type":"Point"}
}