{
  "type": "Feature",
  "properties": {
    "iso:country":"US",
    "sg:address":"109 Methodist Encampment Rd",
    "sg:city":"Kerrville",
    "sg:classifiers":[
        {
            "category":"Retail",
            "subcategory":"Veterinary Services",
            "type":"Services"
        }
    ],
    "sg:phone":"+1 830 895 5533",
    "sg:postcode":"78028",
    "sg:province":"TX",
    "sg:tags":[
        "veterinarian",
        "specialty"
    ],
    "wof:name":"Robert Dittmar",
    "wof:placetype":"venue"
},
  "geometry": {"coordinates":[-99.173709,30.06495],"type":"Point"}
}