{
  "type": "Feature",
  "properties": {
    "iso:country":"US",
    "sg:address":"811 N 5th St",
    "sg:city":"Silsbee",
    "sg:classifiers":[
        {
            "category":"Utilities",
            "subcategory":"Fuel Oil & Lpg",
            "type":"Services"
        }
    ],
    "sg:phone":"+1 409 385 2411",
    "sg:postcode":"77656",
    "sg:province":"TX",
    "sg:tags":[
        "liquefied",
        "gas",
        "petroleum"
    ],
    "wof:name":"Silsbee Propane",
    "wof:placetype":"venue"
},
  "geometry": {"coordinates":[-94.17569399999999,30.355374],"type":"Point"}
}