{
  "type": "Feature",
  "properties": {
    "iso:country":"US",
    "sg:address":"2733 Whitmore St",
    "sg:city":"Fort Worth",
    "sg:classifiers":[
        {
            "category":"Professional",
            "subcategory":"Engineering",
            "type":"Services"
        }
    ],
    "sg:phone":"+1 817 332 3400",
    "sg:postcode":"76107",
    "sg:province":"TX",
    "sg:tags":[
        "industrial"
    ],
    "wof:name":"Bettico Inc",
    "wof:placetype":"venue"
},
  "geometry": {"coordinates":[-97.35590500000001,32.758043],"type":"Point"}
}