{
  "type": "Feature",
  "properties": {
    "iso:country":"US",
    "sg:address":"2709 Elmira Ave",
    "sg:city":"Mcallen",
    "sg:classifiers":[
        {
            "category":"Home & Garden",
            "subcategory":"Household Appliances",
            "type":"Retail Goods"
        }
    ],
    "sg:phone":"+1 956 618 0867",
    "sg:postcode":"78503",
    "sg:province":"TX",
    "sg:tags":[
        "equipment",
        "industrial"
    ],
    "wof:name":"Lopez Sewing Center",
    "wof:placetype":"venue"
},
  "geometry": {"coordinates":[-98.258133,26.168927],"type":"Point"}
}