{
  "type": "Feature",
  "properties": {
    "iso:country":"US",
    "sg:address":"104 E Collins Ave",
    "sg:city":"San Diego",
    "sg:classifiers":[
        {
            "category":"Banks & Credit Unions",
            "subcategory":"Bank",
            "type":"Services"
        }
    ],
    "sg:phone":"+1 361 279 3722",
    "sg:postcode":"78384",
    "sg:province":"TX",
    "sg:tags":[
        "small",
        "lender",
        "loan"
    ],
    "wof:name":"LA Rosita Finance Co",
    "wof:placetype":"venue"
},
  "geometry": {"coordinates":[-98.23917299999999,27.763071],"type":"Point"}
}