{
  "type": "Feature",
  "properties": {
    "iso:country":"US",
    "sg:address":"693 N Market St",
    "sg:city":"Brenham",
    "sg:classifiers":[
        {
            "category":"Health Services",
            "subcategory":"Medical Lab",
            "type":"Services"
        }
    ],
    "sg:phone":"+1 979 830 8113",
    "sg:postcode":"77833",
    "sg:province":"TX",
    "sg:tags":[
        "resonance",
        "magnetic",
        "imaging"
    ],
    "wof:name":"Hasskarl-Giddings Imaging Ctr",
    "wof:placetype":"venue"
},
  "geometry": {"coordinates":[-96.397807,30.172102],"type":"Point"}
}