{
  "type": "Feature",
  "properties": {
    "iso:country":"US",
    "sg:address":"6013 S FM 565",
    "sg:city":"Baytown",
    "sg:classifiers":[
        {
            "category":"Food & Beverages",
            "subcategory":"Groceries & Convenience Stores",
            "type":"Retail Goods"
        }
    ],
    "sg:phone":"+1 281 573 3300",
    "sg:postcode":"77520",
    "sg:province":"TX",
    "wof:name":"MSM Food Mart",
    "wof:placetype":"venue"
},
  "geometry": {"coordinates":[-94.834883,29.808329],"type":"Point"}
}