{
  "type": "Feature",
  "properties": {
    "iso:country":"US",
    "sg:address":"5 Brampton Ct",
    "sg:city":"Conroe",
    "sg:classifiers":[
        {
            "category":"Professional",
            "subcategory":"Art Services",
            "type":"Services"
        }
    ],
    "sg:phone":"+1 936 441 4680",
    "sg:postcode":"77304",
    "sg:province":"TX",
    "sg:tags":[
        "photography",
        "commercial"
    ],
    "wof:name":"Bolack Photography",
    "wof:placetype":"venue"
},
  "geometry": {"coordinates":[-95.52139,30.350275],"type":"Point"}
}