{
  "type": "Feature",
  "properties": {
    "iso:country":"US",
    "sg:address":"3131 Edloe St",
    "sg:city":"Houston",
    "sg:classifiers":[
        {
            "category":"Organizations",
            "subcategory":"Religious Organization",
            "type":"Services"
        }
    ],
    "sg:phone":"+1 281 286 7729",
    "sg:postcode":"77027",
    "sg:province":"TX",
    "sg:tags":[
        "catholic",
        "church"
    ],
    "wof:name":"St Clare Assisi Cathlic Church",
    "wof:placetype":"venue"
},
  "geometry": {"coordinates":[-95.433413,29.73725],"type":"Point"}
}