{
  "type": "Feature",
  "properties": {
    "iso:country":"US",
    "sg:address":"2611 E Cherry St",
    "sg:city":"Paris",
    "sg:classifiers":[
        {
            "category":"Organizations",
            "subcategory":"Religious Organization",
            "type":"Services"
        }
    ],
    "sg:phone":"+1 903 785 1882",
    "sg:postcode":"75460",
    "sg:province":"TX",
    "wof:name":"Peniel Methodist Church",
    "wof:placetype":"venue"
},
  "geometry": {"coordinates":[-95.527832,33.665698],"type":"Point"}
}