{
  "type": "Feature",
  "properties": {
    "iso:country":"US",
    "sg:address":"17314 Nevelson Cir",
    "sg:city":"Spring",
    "sg:classifiers":[
        {
            "category":"Professional",
            "subcategory":"Management & Consulting",
            "type":"Services"
        }
    ],
    "sg:phone":"+1 281 251 5653",
    "sg:postcode":"77379",
    "sg:province":"TX",
    "sg:tags":[
        "business"
    ],
    "wof:name":"J&A Consultants",
    "wof:placetype":"venue"
},
  "geometry": {"coordinates":[-95.535274,30.022867],"type":"Point"}
}