{
  "type": "Feature",
  "properties": {
    "iso:country":"US",
    "sg:address":"8038 Exchange Dr",
    "sg:city":"Austin",
    "sg:classifiers":[
        {
            "category":"Professional",
            "subcategory":"Management & Consulting",
            "type":"Services"
        }
    ],
    "sg:phone":"+1 512 933 0386",
    "sg:postcode":"78754",
    "sg:province":"TX",
    "sg:tags":[
        "to",
        "providing",
        "expertise",
        "public",
        "private"
    ],
    "wof:name":"Lolis Sanzanna",
    "wof:placetype":"venue"
},
  "geometry": {"coordinates":[-97.666065,30.330874],"type":"Point"}
}