{
  "type": "Feature",
  "properties": {
    "iso:country":"US",
    "sg:address":"5546 S Hampton Rd",
    "sg:city":"Dallas",
    "sg:classifiers":[
        {
            "category":"Shopping",
            "type":"Retail Goods"
        }
    ],
    "sg:phone":"+1 214 337 3277",
    "sg:postcode":"75232",
    "sg:province":"TX",
    "sg:tags":[
        "cosmetic",
        "perfume"
    ],
    "wof:name":"Avon Products Inc",
    "wof:placetype":"venue"
},
  "geometry": {"coordinates":[-96.856871,32.6792],"type":"Point"}
}