{
  "type": "Feature",
  "properties": {
    "iso:country":"US",
    "sg:address":"5323 E Mockingbird Ln",
    "sg:city":"Dallas",
    "sg:classifiers":[
        {
            "category":"Shopping",
            "subcategory":"Music",
            "type":"Retail Goods"
        }
    ],
    "sg:phone":"+1 214 615 3887",
    "sg:postcode":"75206",
    "sg:province":"TX",
    "sg:tags":[
        "vintage",
        "used",
        "cd's",
        "tapes",
        "records"
    ],
    "wof:name":"Virgin Entertainment",
    "wof:placetype":"venue"
},
  "geometry": {"coordinates":[-96.777485,32.836529],"type":"Point"}
}