{
  "type": "Feature",
  "properties": {
    "iso:country":"US",
    "sg:address":"5729 Lebanon Road, Ste. 144 #226",
    "sg:city":"Frisco",
    "sg:classifiers":[
        {
            "category":"Professional",
            "subcategory":"Computer Services",
            "type":"Services"
        }
    ],
    "sg:phone":"+1 214 530 5359",
    "sg:postcode":"75034",
    "sg:province":"TX",
    "sg:tags":[
        "electronic-signatures",
        "saas",
        "e-signatures",
        "video-signatures"
    ],
    "sg:website":"http://www.vignature.com",
    "wof:name":"Vignature",
    "wof:placetype":"venue"
},
  "geometry": {"coordinates":[-96.828789,33.118204],"type":"Point"}
}