{
  "type": "Feature",
  "properties": {
    "iso:country":"US",
    "sg:address":"11419 Mathis Ave",
    "sg:city":"Dallas",
    "sg:classifiers":[
        {
            "category":"Building & Trades",
            "subcategory":"Plumbing",
            "type":"Services"
        }
    ],
    "sg:phone":"+1 972 831 8144",
    "sg:postcode":"75234",
    "sg:province":"TX",
    "sg:tags":[
        "contractor"
    ],
    "wof:name":"DC Sprinklers LLC",
    "wof:placetype":"venue"
},
  "geometry": {"coordinates":[-96.912818,32.896454],"type":"Point"}
}