{
  "type": "Feature",
  "properties": {
    "iso:country":"US",
    "sg:address":"109 N Gillespie St",
    "sg:city":"Pampa",
    "sg:classifiers":[
        {
            "category":"Organizations",
            "subcategory":"Religious Organization",
            "type":"Services"
        }
    ],
    "sg:phone":"+1 806 669 7821",
    "sg:postcode":"79065",
    "sg:province":"TX",
    "sg:tags":[
        "church"
    ],
    "wof:name":"United Methodist Church",
    "wof:placetype":"venue"
},
  "geometry": {"coordinates":[-100.959785,35.5377],"type":"Point"}
}