{
  "type": "Feature",
  "properties": {
    "iso:country":"US",
    "sg:address":"5705 Kettering Ct",
    "sg:city":"Richardson",
    "sg:classifiers":[
        {
            "category":"Professional",
            "type":"Services"
        }
    ],
    "sg:phone":"+1 972 234 1127",
    "sg:postcode":"75082",
    "sg:province":"TX",
    "wof:name":"Denos Inc",
    "wof:placetype":"venue"
},
  "geometry": {"coordinates":[-96.614735,32.992814],"type":"Point"}
}