{
  "type": "Feature",
  "properties": {
    "iso:country":"US",
    "sg:address":"2006 S Main St",
    "sg:city":"Mcallen",
    "sg:classifiers":[
        {
            "category":"Shopping",
            "subcategory":"Jewelry",
            "type":"Retail Goods"
        }
    ],
    "sg:phone":"+1 956 618 3307",
    "sg:postcode":"78503",
    "sg:province":"TX",
    "wof:name":"Living Jewelry",
    "wof:placetype":"venue"
},
  "geometry": {"coordinates":[-98.23781200000001,26.184905],"type":"Point"}
}