{
  "type": "Feature",
  "properties": {
    "iso:country":"US",
    "sg:address":"3675 College St",
    "sg:city":"Beaumont",
    "sg:classifiers":[
        {
            "category":"Retail",
            "subcategory":"Repair Shop",
            "type":"Services"
        }
    ],
    "sg:phone":"+1 409 212 9911",
    "sg:postcode":"77701",
    "sg:province":"TX",
    "sg:tags":[
        "welding"
    ],
    "wof:name":"P B Fabrication & Welding",
    "wof:placetype":"venue"
},
  "geometry": {"coordinates":[-94.13249,30.068159],"type":"Point"}
}