{
  "type": "Feature",
  "properties": {
    "iso:country":"US",
    "sg:address":"5 Mills Ct",
    "sg:city":"Mansfield",
    "sg:classifiers":[
        {
            "category":"Professional",
            "type":"Services"
        }
    ],
    "sg:phone":"+1 817 473 2132",
    "sg:postcode":"76063",
    "sg:province":"TX",
    "sg:tags":[
        "establishment"
    ],
    "wof:name":"Bombardier",
    "wof:placetype":"venue"
},
  "geometry": {"coordinates":[-97.11229299999999,32.592697],"type":"Point"}
}