{
  "type": "Feature",
  "properties": {
    "iso:country":"US",
    "sg:address":"The Shops At Arbor Trails 4301 W William Cannon Dr",
    "sg:city":"Austin",
    "sg:classifiers":[
        {
            "category":"Personal",
            "subcategory":"Beauty Salon",
            "type":"Services"
        }
    ],
    "sg:phone":"+1 512 892 1113",
    "sg:postcode":"78749",
    "sg:province":"TX",
    "sg:tags":[
        "hair"
    ],
    "sg:website":"www.supercuts.com",
    "wof:name":"Supercuts",
    "wof:placetype":"venue"
},
  "geometry": {"coordinates":[-97.839107,30.222143],"type":"Point"}
}