{
  "type": "Feature",
  "properties": {
    "iso:country":"US",
    "sg:address":"104 W Oklahoma Ave",
    "sg:city":"Sweetwater",
    "sg:classifiers":[
        {
            "category":"Personal",
            "subcategory":"Beauty Salon",
            "type":"Services"
        }
    ],
    "sg:phone":"+1 325 235 8808",
    "sg:postcode":"79556",
    "sg:province":"TX",
    "sg:tags":[
        "shop"
    ],
    "wof:name":"Villa's Hair Connection",
    "wof:placetype":"venue"
},
  "geometry": {"coordinates":[-100.40063600000001,32.458012],"type":"Point"}
}