{
  "type": "Feature",
  "properties": {
    "iso:country":"US",
    "sg:address":"800 Link Dr",
    "sg:city":"Duncanville",
    "sg:classifiers":[
        {
            "category":"Wholesale",
            "subcategory":"Non-durable Goods",
            "type":"Manufacturing & Wholesale Goods"
        }
    ],
    "sg:phone":"+1 972 298 2236",
    "sg:postcode":"75116",
    "sg:province":"TX",
    "sg:tags":[
        "advertising"
    ],
    "wof:name":"Divine Mission Ventures Inc",
    "wof:placetype":"venue"
},
  "geometry": {"coordinates":[-96.91403099999999,32.661867],"type":"Point"}
}