{
  "type": "Feature",
  "properties": {
    "iso:country":"US",
    "sg:address":"5155 Blanco Rd",
    "sg:city":"San Antonio",
    "sg:classifiers":[
        {
            "category":"Retail",
            "subcategory":"Auto Repair",
            "type":"Services"
        }
    ],
    "sg:phone":"+1 210 340 4592",
    "sg:postcode":"78216",
    "sg:province":"TX",
    "sg:tags":[
        "repairing",
        "automobile",
        "general"
    ],
    "wof:name":"Triple J Automotive Inc",
    "wof:placetype":"venue"
},
  "geometry": {"coordinates":[-98.507896,29.495925],"type":"Point"}
}