{
  "type": "Feature",
  "properties": {
    "iso:country":"US",
    "sg:address":"5001 Spring Valley Rd",
    "sg:city":"Dallas",
    "sg:classifiers":[
        {
            "category":"Restaurant",
            "type":"Food & Drink"
        }
    ],
    "sg:phone":"+1 972 715 1715",
    "sg:postcode":"75244",
    "sg:province":"TX",
    "sg:tags":[
        "delicatessen"
    ],
    "wof:name":"Bay Street Deli",
    "wof:placetype":"venue"
},
  "geometry": {"coordinates":[-96.825773,32.939597],"type":"Point"}
}