{
  "type": "Feature",
  "properties": {
    "iso:country":"US",
    "sg:address":"2220 Hancock Dr",
    "sg:city":"Austin",
    "sg:classifiers":[
        {
            "category":"Health Services",
            "subcategory":"Clinic",
            "type":"Services"
        }
    ],
    "sg:phone":"+1 512 452 7881",
    "sg:postcode":"78756",
    "sg:province":"TX",
    "sg:tags":[
        "kidney",
        "dialysis",
        "center"
    ],
    "wof:name":"Renal Care Group",
    "wof:placetype":"venue"
},
  "geometry": {"coordinates":[-97.74253899999999,30.324232],"type":"Point"}
}