{
  "type": "Feature",
  "properties": {
    "iso:country":"US",
    "sg:address":"4529 Stonewall St",
    "sg:city":"Greenville",
    "sg:classifiers":[
        {
            "category":"Building & Trades",
            "subcategory":"Construction",
            "type":"Services"
        }
    ],
    "sg:phone":"+1 903 454 1998",
    "sg:postcode":"75401",
    "sg:province":"TX",
    "sg:tags":[
        "contractor"
    ],
    "wof:name":"Glenn H Johnson Construction",
    "wof:placetype":"venue"
},
  "geometry": {"coordinates":[-96.107435,33.124163],"type":"Point"}
}