{
  "type": "Feature",
  "properties": {
    "iso:country":"US",
    "sg:address":"4425 San Gabriel Dr",
    "sg:city":"Dallas",
    "sg:classifiers":[
        {
            "category":"Professional",
            "subcategory":"Business Services",
            "type":"Services"
        }
    ],
    "sg:phone":"+1 214 351 6713",
    "sg:postcode":"75229",
    "sg:province":"TX",
    "sg:tags":[
        "interior",
        "consultant",
        "design",
        "decorator"
    ],
    "wof:name":"Lbo River Road",
    "wof:placetype":"venue"
},
  "geometry": {"coordinates":[-96.83009,32.899787],"type":"Point"}
}