{
  "type": "Feature",
  "properties": {
    "iso:country":"US",
    "sg:address":"1700 Cresthill Dr",
    "sg:city":"Rockwall",
    "sg:classifiers":[
        {
            "category":"Professional",
            "subcategory":"Accounting & Tax Preparation",
            "type":"Services"
        }
    ],
    "sg:phone":"+1 972 771 9134",
    "sg:postcode":"75087",
    "sg:province":"TX",
    "wof:name":"Savy Bookkeeping Services",
    "wof:placetype":"venue"
},
  "geometry": {"coordinates":[-96.477548,32.944308],"type":"Point"}
}