{
  "type": "Feature",
  "properties": {
    "iso:country":"US",
    "sg:address":"1107 S Gabriel Dr",
    "sg:city":"Leander",
    "sg:classifiers":[
        {
            "category":"Real Estate",
            "subcategory":"Real Estate Services",
            "type":"Services"
        },
        {
            "category":"Real Estate",
            "subcategory":"Real Estate Agent",
            "type":"Services"
        }
    ],
    "sg:phone":"+1 512 259 2297",
    "sg:postcode":"78641",
    "sg:province":"TX",
    "sg:tags":[
        "management"
    ],
    "wof:name":"Mickler & Assoc Inc",
    "wof:placetype":"venue"
},
  "geometry": {"coordinates":[-97.847782,30.615997],"type":"Point"}
}