{
  "type": "Feature",
  "properties": {
    "iso:country":"US",
    "sg:address":"1113 Driftwood Ln",
    "sg:city":"Fort Worth",
    "sg:classifiers":[
        {
            "category":"Shopping",
            "subcategory":"Clothing, Apparel, & Fashions",
            "type":"Retail Goods"
        }
    ],
    "sg:phone":"+1 817 293 4722",
    "sg:postcode":"76140",
    "sg:province":"TX",
    "wof:name":"Vernon L Darty",
    "wof:placetype":"venue"
},
  "geometry": {"coordinates":[-97.299998,32.602059],"type":"Point"}
}