{
  "type": "Feature",
  "properties": {
    "iso:country":"US",
    "sg:address":"3110 Red River St",
    "sg:city":"Austin",
    "sg:classifiers":[
        {
            "category":"Real Estate",
            "subcategory":"Real Estate Operator",
            "type":"Services"
        }
    ],
    "sg:phone":"+1 512 469 6003",
    "sg:postcode":"78705",
    "sg:province":"TX",
    "sg:tags":[
        "apartment"
    ],
    "wof:name":"Chaparosa Apartments",
    "wof:placetype":"venue"
},
  "geometry": {"coordinates":[-97.72721,30.291067],"type":"Point"}
}