{
  "type": "Feature",
  "properties": {
    "iso:country":"US",
    "sg:address":"7503 FM 1488",
    "sg:city":"Magnolia",
    "sg:classifiers":[
        {
            "category":"Home & Garden",
            "subcategory":"Carpets & Floor Coverings",
            "type":"Retail Goods"
        }
    ],
    "sg:phone":"+1 281 259 3570",
    "sg:postcode":"77354",
    "sg:province":"TX",
    "wof:name":"All Star Carpets & More",
    "wof:placetype":"venue"
},
  "geometry": {"coordinates":[-95.507817,30.230065],"type":"Point"}
}