{
  "type": "Feature",
  "properties": {
    "iso:country":"US",
    "sg:address":"201 Eddings Ln",
    "sg:city":"Lufkin",
    "sg:classifiers":[
        {
            "category":"Building & Trades",
            "subcategory":"Construction",
            "type":"Services"
        }
    ],
    "sg:phone":"+1 936 632 2655",
    "sg:postcode":"75904",
    "sg:province":"TX",
    "sg:tags":[
        "acoustical",
        "insulation",
        "contractor"
    ],
    "wof:name":"Eddings, Joe Ed Precison Ceiling",
    "wof:placetype":"venue"
},
  "geometry": {"coordinates":[-94.746399,31.40912],"type":"Point"}
}