{
  "type": "Feature",
  "properties": {
    "iso:country":"US",
    "sg:address":"247 Co Rd 250",
    "sg:city":"Burnet",
    "sg:classifiers":[
        {
            "category":"Building & Trades",
            "subcategory":"Construction",
            "type":"Services"
        }
    ],
    "sg:phone":"+1 512 756 7377",
    "sg:postcode":"78611",
    "sg:province":"TX",
    "sg:tags":[
        "contractor"
    ],
    "wof:name":"Carline Custom Building",
    "wof:placetype":"venue"
},
  "geometry": {"coordinates":[-98.21033799999999,30.758603],"type":"Point"}
}