{
  "type": "Feature",
  "properties": {
    "iso:country":"US",
    "sg:address":"4263 Simonton Rd",
    "sg:city":"Dallas",
    "sg:classifiers":[
        {
            "category":"Home & Garden",
            "subcategory":"Furniture",
            "type":"Retail Goods"
        }
    ],
    "sg:phone":"+1 972 788 3200",
    "sg:postcode":"75244",
    "sg:province":"TX",
    "sg:tags":[
        "store"
    ],
    "wof:name":"Furniture For Less",
    "wof:placetype":"venue"
},
  "geometry": {"coordinates":[-96.832658,32.930923],"type":"Point"}
}