{
  "type": "Feature",
  "properties": {
    "iso:country":"US",
    "sg:address":"16413 Bratton Ln",
    "sg:city":"Austin",
    "sg:classifiers":[
        {
            "category":"Manufacturing",
            "subcategory":"Building Materials",
            "type":"Manufacturing & Wholesale Goods"
        }
    ],
    "sg:phone":"+1 512 244 3364",
    "sg:postcode":"78728",
    "sg:province":"TX",
    "sg:tags":[
        "cabinet"
    ],
    "wof:name":"Custom Cabinets",
    "wof:placetype":"venue"
},
  "geometry": {"coordinates":[-97.676193,30.46745],"type":"Point"}
}