{
  "type": "Feature",
  "properties": {
    "iso:country":"US",
    "sg:address":"8600 N Loop Dr",
    "sg:city":"El Paso",
    "sg:classifiers":[
        {
            "category":"Food & Beverages",
            "subcategory":"Bakery",
            "type":"Retail Goods"
        }
    ],
    "sg:phone":"+1 915 858 8783",
    "sg:postcode":"79907",
    "sg:province":"TX",
    "wof:name":"1 Stop Bakery",
    "wof:placetype":"venue"
},
  "geometry": {"coordinates":[-106.324225,31.712736],"type":"Point"}
}