{
  "type": "Feature",
  "properties": {
    "iso:country":"US",
    "sg:address":"4105 Dowlen Rd",
    "sg:city":"Beaumont",
    "sg:classifiers":[
        {
            "category":"Shopping",
            "subcategory":"Optical Goods",
            "type":"Retail Goods"
        },
        {
            "category":"Manufacturing",
            "subcategory":"Tools & Machinery",
            "type":"Manufacturing & Wholesale Goods"
        }
    ],
    "sg:phone":"+1 409 899 9999",
    "sg:postcode":"77706",
    "sg:province":"TX",
    "sg:tags":[
        "mfg"
    ],
    "wof:name":"Texas State Optical",
    "wof:placetype":"venue"
},
  "geometry": {"coordinates":[-94.16486999999999,30.121735],"type":"Point"}
}