{
  "type": "Feature",
  "properties": {
    "iso:country":"US",
    "sg:address":"2508 Appleby Sand Rd",
    "sg:city":"Nacogdoches",
    "sg:classifiers":[
        {
            "category":"Organizations",
            "subcategory":"Religious Organization",
            "type":"Services"
        }
    ],
    "sg:phone":"+1 936 564 7807",
    "sg:postcode":"75965",
    "sg:province":"TX",
    "sg:tags":[
        "catholic",
        "church"
    ],
    "wof:name":"Sacred Heart Catholic Church",
    "wof:placetype":"venue"
},
  "geometry": {"coordinates":[-94.63236999999999,31.624655],"type":"Point"}
}