{
  "type": "Feature",
  "properties": {
    "iso:country":"US",
    "sg:address":"118 E Filmore Ave",
    "sg:city":"Harlingen",
    "sg:classifiers":[
        {
            "category":"Building & Trades",
            "subcategory":"Construction",
            "type":"Services"
        }
    ],
    "sg:phone":"+1 956 412 1113",
    "sg:postcode":"78550",
    "sg:province":"TX",
    "sg:tags":[
        "restoration",
        "cleaning",
        "patio",
        "deck"
    ],
    "wof:name":"JBR Power Wash",
    "wof:placetype":"venue"
},
  "geometry": {"coordinates":[-97.69467899999999,26.186411],"type":"Point"}
}