{
  "type": "Feature",
  "properties": {
    "iso:country":"US",
    "sg:address":"4617 Montrose Blvd",
    "sg:city":"Houston",
    "sg:classifiers":[
        {
            "category":"Manufacturing",
            "subcategory":"Printing",
            "type":"Manufacturing & Wholesale Goods"
        }
    ],
    "sg:phone":"+1 713 526 6016",
    "sg:postcode":"77006",
    "sg:province":"TX",
    "sg:tags":[
        "commercial"
    ],
    "wof:name":"AlphaGraphics",
    "wof:placetype":"venue"
},
  "geometry": {"coordinates":[-95.390997,29.730708],"type":"Point"}
}