{
  "type": "Feature",
  "properties": {
    "iso:country":"US",
    "sg:address":"3939 San Felipe St",
    "sg:city":"Houston",
    "sg:classifiers":[
        {
            "category":"Restaurant",
            "type":"Food & Drink"
        }
    ],
    "sg:menulink":"http://www.allmenus.com/tx/houston/266899-ouisies-table/menu/",
    "sg:phone":"+1 713 528 2264",
    "sg:postcode":"77027",
    "sg:province":"TX",
    "sg:tags":[
        "american",
        "southern"
    ],
    "wof:name":"Ouisie's Table",
    "wof:placetype":"venue"
},
  "geometry": {"coordinates":[-95.44336,29.746726],"type":"Point"}
}