{
  "type": "Feature",
  "properties": {
    "iso:country":"US",
    "sg:address":"113 Colglazier Ave",
    "sg:city":"San Antonio",
    "sg:classifiers":[
        {
            "category":"Manufacturing",
            "subcategory":"Printing",
            "type":"Manufacturing & Wholesale Goods"
        }
    ],
    "sg:phone":"+1 210 533 1476",
    "sg:postcode":"78223",
    "sg:province":"TX",
    "sg:tags":[
        "lithographic",
        "commercial"
    ],
    "wof:name":"Pages Printing",
    "wof:placetype":"venue"
},
  "geometry": {"coordinates":[-98.440594,29.372445],"type":"Point"}
}