{
  "type": "Feature",
  "properties": {
    "iso:country":"US",
    "sg:address":"7445 Airport Fwy",
    "sg:city":"Fort Worth",
    "sg:classifiers":[
        {
            "category":"Wholesale",
            "subcategory":"Motor Vehicles",
            "type":"Manufacturing & Wholesale Goods"
        },
        {
            "category":"Manufacturing",
            "subcategory":"Motor Vehicles & Parts",
            "type":"Manufacturing & Wholesale Goods"
        }
    ],
    "sg:phone":"+1 817 589 1180",
    "sg:postcode":"76118",
    "sg:province":"TX",
    "sg:tags":[
        "motorcycle"
    ],
    "wof:name":"Kawasaki Motors Corp USA",
    "wof:placetype":"venue"
},
  "geometry": {"coordinates":[-97.21680499999999,32.803575],"type":"Point"}
}