{
  "type": "Feature",
  "properties": {
    "iso:country":"US",
    "sg:address":"1058 Co Rd 263",
    "sg:city":"Gainesville",
    "sg:classifiers":[
        {
            "category":"Arts & Performance",
            "subcategory":"Theater",
            "type":"Entertainment"
        }
    ],
    "sg:phone":"+1 903 429 3004",
    "sg:postcode":"76240",
    "sg:province":"TX",
    "sg:tags":[
        "bureau"
    ],
    "wof:name":"E Z Entertainment Karaoke",
    "wof:placetype":"venue"
},
  "geometry": {"coordinates":[-96.975087,33.575911],"type":"Point"}
}