{
  "type": "Feature",
  "properties": {
    "iso:country":"US",
    "sg:address":"512 Coronado Dr",
    "sg:city":"Denton",
    "sg:classifiers":[
        {
            "category":"Real Estate",
            "subcategory":"Real Estate Services",
            "type":"Services"
        },
        {
            "category":"Retail",
            "subcategory":"Laundry & Dry Cleaning",
            "type":"Services"
        },
        {
            "category":"Building & Trades",
            "subcategory":"Cleaning & Sanitation",
            "type":"Services"
        }
    ],
    "sg:phone":"+1 940 484 7777",
    "sg:postcode":"76209",
    "sg:province":"TX",
    "sg:tags":[
        "cleaner",
        "fire",
        "house",
        "rug",
        "damage",
        "water",
        "restoration",
        "maintenance",
        "cleaners-interior",
        "carpet"
    ],
    "sg:website":"http://www.astroscleaning.com",
    "wof:name":"Astros Carpet Cleaning",
    "wof:placetype":"venue"
},
  "geometry": {"coordinates":[-97.12655100000001,33.239398],"type":"Point"}
}