{
  "type": "Feature",
  "properties": {
    "iso:country":"US",
    "sg:address":"901 S Mo-Pac Expy",
    "sg:city":"Austin",
    "sg:classifiers":[
        {
            "category":"Real Estate",
            "subcategory":"Real Estate Agent",
            "type":"Services"
        }
    ],
    "sg:phone":"+1 512 306 1342",
    "sg:postcode":"78746",
    "sg:province":"TX",
    "wof:name":"Crescent Real Estate",
    "wof:placetype":"venue"
},
  "geometry": {"coordinates":[-97.783118,30.26624],"type":"Point"}
}