{
  "type": "Feature",
  "properties": {
    "iso:country":"US",
    "sg:address":"1810 Shiloh Rd",
    "sg:city":"Tyler",
    "sg:classifiers":[
        {
            "category":"Insurance",
            "subcategory":"Insurance Agent",
            "type":"Services"
        }
    ],
    "sg:phone":"+1 903 561 6632",
    "sg:postcode":"75703",
    "sg:province":"TX",
    "wof:name":"Bankers Life",
    "wof:placetype":"venue"
},
  "geometry": {"coordinates":[-95.27917100000001,32.295362],"type":"Point"}
}