{
  "type": "Feature",
  "properties": {
    "iso:country":"US",
    "sg:address":"300 Hospital Dr",
    "sg:city":"Anahuac",
    "sg:classifiers":[
        {
            "category":"Health Services",
            "subcategory":"Nursing And Care Facility",
            "type":"Services"
        }
    ],
    "sg:phone":"+1 409 267 3164",
    "sg:postcode":"77514",
    "sg:province":"TX",
    "sg:tags":[
        "home",
        "convalescent"
    ],
    "wof:name":"Anahuac Health Care Ctr",
    "wof:placetype":"venue"
},
  "geometry": {"coordinates":[-94.686814,29.753075],"type":"Point"}
}