{
  "type": "Feature",
  "properties": {
    "iso:country":"US",
    "sg:address":"677 NE Alsbury Blvd",
    "sg:city":"Burleson",
    "sg:classifiers":[
        {
            "category":"Social Services",
            "subcategory":"Child Care",
            "type":"Services"
        }
    ],
    "sg:phone":"+1 817 426 5151",
    "sg:postcode":"76028",
    "sg:province":"TX",
    "wof:name":"Kid's Kampus",
    "wof:placetype":"venue"
},
  "geometry": {"coordinates":[-97.329649,32.560464],"type":"Point"}
}