{
  "type": "Feature",
  "properties": {
    "iso:country":"US",
    "sg:address":"613 Norma St",
    "sg:city":"Nacogdoches",
    "sg:classifiers":[
        {
            "category":"Education",
            "subcategory":"Vocational School",
            "type":"Public Place"
        },
        {
            "category":"Organizations",
            "subcategory":"Professional Association",
            "type":"Services"
        }
    ],
    "sg:phone":"+1 936 569 7557",
    "sg:postcode":"75965",
    "sg:province":"TX",
    "sg:tags":[
        "training",
        "computer",
        "business"
    ],
    "sg:website":"www.journalofebusiness.com",
    "wof:name":"Academy of E Commerce Inc",
    "wof:placetype":"venue"
},
  "geometry": {"coordinates":[-94.647187,31.641457],"type":"Point"}
}