{
  "type": "Feature",
  "properties": {
    "iso:country":"US",
    "sg:address":"1314 W Kentucky Ave",
    "sg:city":"Pampa",
    "sg:classifiers":[
        {
            "category":"Building & Trades",
            "subcategory":"Electrical",
            "type":"Services"
        }
    ],
    "sg:phone":"+1 806 669 9532",
    "sg:postcode":"79065",
    "sg:province":"TX",
    "sg:tags":[
        "electric",
        "contractor"
    ],
    "wof:name":"Larry Beck Electric",
    "wof:placetype":"venue"
},
  "geometry": {"coordinates":[-100.978492,35.547798],"type":"Point"}
}