{
  "type": "Feature",
  "properties": {
    "iso:country":"US",
    "sg:address":"1 Remington Ln",
    "sg:city":"Houston",
    "sg:classifiers":[
        {
            "category":"Professional",
            "type":"Services"
        }
    ],
    "sg:phone":"+1 713 526 1418",
    "sg:postcode":"77005",
    "sg:province":"TX",
    "wof:name":"Boyd Morse Foundation",
    "wof:placetype":"venue"
},
  "geometry": {"coordinates":[-95.39453399999999,29.723035],"type":"Point"}
}