{
  "type": "Feature",
  "properties": {
    "iso:country":"US",
    "sg:address":"507 S Broadway St",
    "sg:city":"Post",
    "sg:classifiers":[
        {
            "category":"Restaurant",
            "type":"Food & Drink"
        }
    ],
    "sg:phone":"+1 806 495 3205",
    "sg:postcode":"79356",
    "sg:province":"TX",
    "sg:tags":[
        "eating"
    ],
    "wof:name":"Tommy Joe Cole",
    "wof:placetype":"venue"
},
  "geometry": {"coordinates":[-101.37829000000001,33.185924],"type":"Point"}
}