{
  "type": "Feature",
  "properties": {
    "iso:country":"US",
    "sg:address":"1621 Prime West Pkwy",
    "sg:city":"Katy",
    "sg:classifiers":[
        {
            "category":"Wholesale",
            "subcategory":"Machinery & Supplies",
            "type":"Manufacturing & Wholesale Goods"
        }
    ],
    "sg:phone":"+1 281 578 6523",
    "sg:postcode":"77449",
    "sg:province":"TX",
    "sg:tags":[
        "equipment",
        "industrial"
    ],
    "wof:name":"C&L Pipeline Equipment Inc",
    "wof:placetype":"venue"
},
  "geometry": {"coordinates":[-95.746252,29.794686],"type":"Point"}
}