{
  "type": "Feature",
  "properties": {
    "iso:country":"US",
    "sg:address":"10620 E NW Hwy",
    "sg:city":"Dallas",
    "sg:classifiers":[
        {
            "category":"Professional",
            "subcategory":"Computer Services",
            "type":"Services"
        }
    ],
    "sg:phone":"+1 214 660 0670",
    "sg:postcode":"75238",
    "sg:province":"TX",
    "sg:tags":[
        "repair"
    ],
    "sg:website":"www.owcronline.com",
    "wof:name":"On Wheels Computer Repair Company",
    "wof:placetype":"venue"
},
  "geometry": {"coordinates":[-96.701899,32.863835],"type":"Point"}
}