{
  "type": "Feature",
  "properties": {
    "iso:country":"US",
    "sg:address":"640 Sardis St",
    "sg:city":"Midlothian",
    "sg:classifiers":[
        {
            "category":"Place Of Worship",
            "subcategory":"Church",
            "type":"Public Place"
        },
        {
            "category":"Place Of Worship",
            "type":"Public Place"
        }
    ],
    "sg:phone":"+1 972 937 5784",
    "sg:postcode":"76065",
    "sg:province":"TX",
    "sg:tags":[
        "churches-methodist"
    ],
    "wof:name":"Sardis Methodist Church",
    "wof:placetype":"venue"
},
  "geometry": {"coordinates":[-96.90355700000001,32.43045],"type":"Point"}
}