{
  "type": "Feature",
  "properties": {
    "iso:country":"US",
    "sg:address":"25700 I- 45",
    "sg:city":"Spring",
    "sg:classifiers":[
        {
            "category":"Wholesale",
            "subcategory":"Vending Machines",
            "type":"Manufacturing & Wholesale Goods"
        }
    ],
    "sg:phone":"+1 281 362 8985",
    "sg:postcode":"77386",
    "sg:province":"TX",
    "sg:tags":[
        "operator"
    ],
    "wof:name":"Flanagan Products",
    "wof:placetype":"venue"
},
  "geometry": {"coordinates":[-95.44475300000001,30.136971],"type":"Point"}
}