{
  "type": "Feature",
  "properties": {
    "iso:country":"US",
    "sg:address":"5623 Barkaloo Rd",
    "sg:city":"Baytown",
    "sg:classifiers":[
        {
            "category":"Communications",
            "type":"Services"
        }
    ],
    "sg:phone":"+1 281 421 4512",
    "sg:postcode":"77521",
    "sg:province":"TX",
    "sg:tags":[
        "communication"
    ],
    "wof:name":"Comcast Cable Holdings LLC",
    "wof:placetype":"venue"
},
  "geometry": {"coordinates":[-94.95838999999999,29.789331],"type":"Point"}
}