{
  "type": "Feature",
  "properties": {
    "iso:country":"US",
    "sg:address":"16945 Northchase Dr",
    "sg:city":"Houston",
    "sg:classifiers":[
        {
            "category":"Professional",
            "subcategory":"Business Services",
            "type":"Services"
        }
    ],
    "sg:phone":"+1 281 876 5876",
    "sg:postcode":"77060",
    "sg:province":"TX",
    "sg:tags":[
        "financial",
        "institution"
    ],
    "wof:name":"Toyota Motor Credit",
    "wof:placetype":"venue"
},
  "geometry": {"coordinates":[-95.405143,29.946773],"type":"Point"}
}