{
  "type": "Feature",
  "properties": {
    "iso:country":"US",
    "sg:address":"14503 Chadbourne Dr",
    "sg:city":"Houston",
    "sg:classifiers":[
        {
            "category":"Professional",
            "type":"Services"
        }
    ],
    "sg:phone":"+1 281 497 7766",
    "sg:postcode":"77079",
    "sg:province":"TX",
    "sg:tags":[
        "establishment"
    ],
    "wof:name":"A Brink & Co",
    "wof:placetype":"venue"
},
  "geometry": {"coordinates":[-95.60618700000001,29.768929],"type":"Point"}
}