{
  "type": "Feature",
  "properties": {
    "iso:country":"US",
    "sg:address":"217 Birch St",
    "sg:city":"Waco",
    "sg:classifiers":[
        {
            "category":"Building & Trades",
            "subcategory":"Plumbing",
            "type":"Services"
        }
    ],
    "sg:phone":"+1 254 772 8011",
    "sg:postcode":"76705",
    "sg:province":"TX",
    "sg:tags":[
        "plumbing",
        "contractor"
    ],
    "wof:name":"Discount Plumbing-Central Tx",
    "wof:placetype":"venue"
},
  "geometry": {"coordinates":[-97.10469399999999,31.627901],"type":"Point"}
}