{
  "type": "Feature",
  "properties": {
    "iso:country":"US",
    "sg:address":"2919 Deer Hollow Dr",
    "sg:city":"Humble",
    "sg:classifiers":[
        {
            "category":"Professional",
            "type":"Services"
        }
    ],
    "sg:phone":"+1 281 360 1677",
    "sg:postcode":"77345",
    "sg:province":"TX",
    "wof:name":"Deer Hollow Assoc Inc",
    "wof:placetype":"venue"
},
  "geometry": {"coordinates":[-95.17504700000001,30.056952],"type":"Point"}
}