{
  "type": "Feature",
  "properties": {
    "iso:country":"US",
    "sg:address":"3105 Carter Ave",
    "sg:city":"Wichita Falls",
    "sg:classifiers":[
        {
            "category":"Personal",
            "subcategory":"Beauty Salon",
            "type":"Services"
        }
    ],
    "sg:phone":"+1 940 692 3802",
    "sg:postcode":"76308",
    "sg:province":"TX",
    "sg:tags":[
        "shop"
    ],
    "wof:name":"Hair Dimensions",
    "wof:placetype":"venue"
},
  "geometry": {"coordinates":[-98.53357800000001,33.872176],"type":"Point"}
}