{
  "type": "Feature",
  "properties": {
    "iso:country":"US",
    "sg:address":"13112 Nacogdoches Rd",
    "sg:city":"San Antonio",
    "sg:classifiers":[
        {
            "category":"Insurance",
            "subcategory":"Insurance Agent",
            "type":"Services"
        }
    ],
    "sg:phone":"+1 210 656 2834",
    "sg:postcode":"78217",
    "sg:province":"TX",
    "wof:name":"Anda Agency Farmers Insurance",
    "wof:placetype":"venue"
},
  "geometry": {"coordinates":[-98.39414600000001,29.560867],"type":"Point"}
}