{
  "type": "Feature",
  "properties": {
    "iso:country":"US",
    "sg:address":"800 S 9th St",
    "sg:city":"Alamo",
    "sg:classifiers":[
        {
            "category":"Government",
            "subcategory":"Office",
            "type":"Public Place"
        }
    ],
    "sg:phone":"+1 956 787 2232",
    "sg:postcode":"78516",
    "sg:province":"TX",
    "sg:tags":[
        "management"
    ],
    "wof:name":"Water Plant",
    "wof:placetype":"venue"
},
  "geometry": {"coordinates":[-98.120615,26.175266],"type":"Point"}
}