{
  "type": "Feature",
  "properties": {
    "iso:country":"US",
    "sg:address":"14903 Park Almeda Dr",
    "sg:city":"Houston",
    "sg:classifiers":[
        {
            "category":"Building & Trades",
            "subcategory":"Construction",
            "type":"Services"
        }
    ],
    "sg:phone":"+1 713 413 3022",
    "sg:postcode":"77047",
    "sg:province":"TX",
    "sg:tags":[
        "resurfacing",
        "laying",
        "refinishing",
        "floor"
    ],
    "wof:name":"Gypsum Floors",
    "wof:placetype":"venue"
},
  "geometry": {"coordinates":[-95.420688,29.591431],"type":"Point"}
}