{
  "type": "Feature",
  "properties": {
    "iso:country":"US",
    "sg:address":"701 Short St",
    "sg:city":"Ferris",
    "sg:classifiers":[
        {
            "category":"Organizations",
            "subcategory":"Religious Organization",
            "type":"Services"
        }
    ],
    "sg:phone":"+1 972 544 8046",
    "sg:postcode":"75125",
    "sg:province":"TX",
    "sg:tags":[
        "church"
    ],
    "wof:name":"God's Kingdom United Methodist",
    "wof:placetype":"venue"
},
  "geometry": {"coordinates":[-96.671156,32.539289],"type":"Point"}
}