{
  "type": "Feature",
  "properties": {
    "iso:country":"US",
    "sg:address":"201 N Campus Blvd",
    "sg:city":"San Angelo",
    "sg:classifiers":[
        {
            "category":"Organizations",
            "subcategory":"Religious Organization",
            "type":"Services"
        }
    ],
    "sg:phone":"+1 325 949 1033",
    "sg:postcode":"76901",
    "sg:province":"TX",
    "sg:tags":[
        "church"
    ],
    "wof:name":"Assembly Of God Evangel Temple",
    "wof:placetype":"venue"
},
  "geometry": {"coordinates":[-100.47228200000001,31.451476],"type":"Point"}
}