{
  "type": "Feature",
  "properties": {
    "iso:country":"US",
    "sg:address":"705 E Felt St",
    "sg:city":"Brownfield",
    "sg:classifiers":[
        {
            "category":"Health Services",
            "subcategory":"Hospital",
            "type":"Services"
        }
    ],
    "sg:phone":"+1 806 637 3551",
    "sg:postcode":"79316",
    "sg:province":"TX",
    "sg:website":"www.brownfield-rmc.org",
    "wof:name":"Brownfield Regional Med Ctr",
    "wof:placetype":"venue"
},
  "geometry": {"coordinates":[-102.267651,33.18714],"type":"Point"}
}