{
  "type": "Feature",
  "properties": {
    "iso:country":"US",
    "sg:address":"35 N York Gate Ct",
    "sg:city":"Spring",
    "sg:classifiers":[
        {
            "category":"Mining & Drilling",
            "type":"Manufacturing & Wholesale Goods"
        }
    ],
    "sg:phone":"+1 936 321 1836",
    "sg:postcode":"77382",
    "sg:province":"TX",
    "sg:tags":[
        "field"
    ],
    "wof:name":"Providence Works Inc",
    "wof:placetype":"venue"
},
  "geometry": {"coordinates":[-95.515621,30.219867],"type":"Point"}
}