{
  "type": "Feature",
  "properties": {
    "iso:country":"US",
    "sg:address":"714 1st St",
    "sg:city":"Marble Falls",
    "sg:classifiers":[
        {
            "category":"Health Services",
            "subcategory":"Chiropractor",
            "type":"Services"
        }
    ],
    "sg:phone":"+1 830 798 1489",
    "sg:postcode":"78654",
    "sg:province":"TX",
    "wof:name":"Bayside Chrpractic Kinesiology",
    "wof:placetype":"venue"
},
  "geometry": {"coordinates":[-98.27711600000001,30.569367],"type":"Point"}
}