{
  "type": "Feature",
  "properties": {
    "iso:country":"US",
    "sg:address":"2600 W 2nd St",
    "sg:city":"Taylor",
    "sg:classifiers":[
        {
            "category":"Travel",
            "subcategory":"Hotels & Motels",
            "type":"Entertainment"
        }
    ],
    "sg:phone":"+1 877 574 2464",
    "sg:postcode":"76574",
    "sg:province":"TX",
    "sg:tags":[
        "lodging"
    ],
    "sg:website":"http://book.bestwestern.com/bestwestern/priceAvail.do?propertyCode=44550&cm_mmc=IYP-_-YP-_-property-_-44550",
    "wof:name":"Best Western Taylor Inn",
    "wof:placetype":"venue"
},
  "geometry": {"coordinates":[-97.443726,30.565109],"type":"Point"}
}