{
  "type": "Feature",
  "properties": {
    "iso:country":"US",
    "sg:address":"716 Shady Creek Trl",
    "sg:city":"Mesquite",
    "sg:classifiers":[
        {
            "category":"Building & Trades",
            "subcategory":"Construction",
            "type":"Services"
        }
    ],
    "sg:phone":"+1 972 681 1837",
    "sg:postcode":"75150",
    "sg:province":"TX",
    "sg:tags":[
        "contractor"
    ],
    "wof:name":"Taylor Built Fence",
    "wof:placetype":"venue"
},
  "geometry": {"coordinates":[-96.60823499999999,32.810791],"type":"Point"}
}