{
  "type": "Feature",
  "properties": {
    "iso:country":"US",
    "sg:address":"2017 Septiembre Dr",
    "sg:city":"El Paso",
    "sg:classifiers":[
        {
            "category":"Professional",
            "subcategory":"Advertising",
            "type":"Services"
        }
    ],
    "sg:phone":"+1 915 593 7853",
    "sg:postcode":"79935",
    "sg:province":"TX",
    "sg:tags":[
        "agency"
    ],
    "wof:name":"E L R Enterprises",
    "wof:placetype":"venue"
},
  "geometry": {"coordinates":[-106.328914,31.770642],"type":"Point"}
}