{
  "type": "Feature",
  "properties": {
    "iso:country":"US",
    "sg:address":"111 N Hasler Blvd Ste 200",
    "sg:city":"Bastrop",
    "sg:classifiers":[
        {
            "category":"Insurance",
            "subcategory":"Hazard Insurance",
            "type":"Services"
        }
    ],
    "sg:phone":"+1 512 581 3939",
    "sg:postcode":"78602",
    "sg:province":"TX",
    "sg:tags":[
        "commercial",
        "business"
    ],
    "sg:website":"http://www.statefarm.com",
    "wof:name":"State Farm Insurance",
    "wof:placetype":"venue"
},
  "geometry": {"coordinates":[-97.3344,30.107409],"type":"Point"}
}