{
  "type": "Feature",
  "properties": {
    "iso:country":"US",
    "sg:address":"1107 Castleman Dr",
    "sg:city":"Cedar Hill",
    "sg:classifiers":[
        {
            "category":"Professional",
            "subcategory":"Business Services",
            "type":"Services"
        }
    ],
    "sg:phone":"+1 469 337 2331",
    "sg:postcode":"75104",
    "sg:province":"TX",
    "sg:tags":[
        "technical",
        "broad"
    ],
    "wof:name":"Puro Technology",
    "wof:placetype":"venue"
},
  "geometry": {"coordinates":[-96.923863,32.571405],"type":"Point"}
}