{
  "type": "Feature",
  "properties": {
    "iso:country":"US",
    "sg:address":"1309 Wheatfield Dr",
    "sg:city":"Mesquite",
    "sg:classifiers":[
        {
            "category":"Retail",
            "subcategory":"Repair Shop",
            "type":"Services"
        }
    ],
    "sg:phone":"+1 972 216 3747",
    "sg:postcode":"75149",
    "sg:province":"TX",
    "wof:name":"Platinum Cleaning Concepts",
    "wof:placetype":"venue"
},
  "geometry": {"coordinates":[-96.57542599999999,32.779086],"type":"Point"}
}