{
  "type": "Feature",
  "properties": {
    "iso:country":"US",
    "sg:address":"711 Porter St",
    "sg:city":"Taylor",
    "sg:classifiers":[
        {
            "category":"Building & Trades",
            "subcategory":"Cleaning & Sanitation",
            "type":"Services"
        }
    ],
    "sg:phone":"+1 512 365 1279",
    "sg:postcode":"76574",
    "sg:province":"TX",
    "sg:tags":[
        "maintenance"
    ],
    "wof:name":"Jackson & Jackson Enterpr",
    "wof:placetype":"venue"
},
  "geometry": {"coordinates":[-97.409025,30.574383],"type":"Point"}
}