{
  "type": "Feature",
  "properties": {
    "iso:country":"US",
    "sg:address":"22602 Aldine Westfield Rd",
    "sg:city":"Spring",
    "sg:classifiers":[
        {
            "category":"Personal",
            "subcategory":"Beauty Salon",
            "type":"Services"
        }
    ],
    "sg:phone":"+1 281 350 6168",
    "sg:postcode":"77373",
    "sg:province":"TX",
    "sg:tags":[
        "shop"
    ],
    "wof:name":"Season Nails",
    "wof:placetype":"venue"
},
  "geometry": {"coordinates":[-95.384216,30.04405],"type":"Point"}
}