{
  "type": "Feature",
  "properties": {
    "iso:country":"US",
    "sg:address":"9740 Co Rd 105",
    "sg:city":"Grandview",
    "sg:classifiers":[
        {
            "category":"Retail",
            "subcategory":"Repair Shop",
            "type":"Services"
        }
    ],
    "sg:phone":"+1 817 866 4204",
    "sg:postcode":"76050",
    "sg:province":"TX",
    "wof:name":"Black Tractor Service",
    "wof:placetype":"venue"
},
  "geometry": {"coordinates":[-97.169911,32.281143],"type":"Point"}
}