{
  "type": "Feature",
  "properties": {
    "iso:country":"US",
    "sg:address":"4404 Village Way",
    "sg:city":"Odessa",
    "sg:classifiers":[
        {
            "category":"Building & Trades",
            "subcategory":"Construction",
            "type":"Services"
        }
    ],
    "sg:phone":"+1 432 363 9502",
    "sg:postcode":"79762",
    "sg:province":"TX",
    "sg:tags":[
        "concrete",
        "contractor"
    ],
    "wof:name":"Concrete Creations",
    "wof:placetype":"venue"
},
  "geometry": {"coordinates":[-102.350849,31.897523],"type":"Point"}
}