{
  "type": "Feature",
  "properties": {
    "iso:country":"US",
    "sg:address":"305 Fenton Rd",
    "sg:city":"Longview",
    "sg:classifiers":[
        {
            "category":"Personal",
            "subcategory":"Beauty Salon",
            "type":"Services"
        }
    ],
    "sg:phone":"+1 903 759 9392",
    "sg:postcode":"75604",
    "sg:province":"TX",
    "sg:tags":[
        "shop"
    ],
    "wof:name":"Billie's Beauty Shop",
    "wof:placetype":"venue"
},
  "geometry": {"coordinates":[-94.805385,32.562596],"type":"Point"}
}