{
  "type": "Feature",
  "properties": {
    "iso:country":"US",
    "sg:address":"5012 Canal St",
    "sg:city":"Houston",
    "sg:classifiers":[
        {
            "category":"Personal",
            "subcategory":"Beauty Salon",
            "type":"Services"
        }
    ],
    "sg:phone":"+1 713 926 1515",
    "sg:postcode":"77011",
    "sg:province":"TX",
    "sg:tags":[
        "shop"
    ],
    "wof:name":"Dalilah Beauty Shop",
    "wof:placetype":"venue"
},
  "geometry": {"coordinates":[-95.322874,29.746692],"type":"Point"}
}