{
  "type": "Feature",
  "properties": {
    "iso:country":"US",
    "sg:address":"300 E Midway Dr",
    "sg:city":"Euless",
    "sg:classifiers":[
        {
            "category":"Professional",
            "subcategory":"Accounting & Tax Preparation",
            "type":"Services"
        }
    ],
    "sg:phone":"+1 817 571 6290",
    "sg:postcode":"76039",
    "sg:province":"TX",
    "wof:name":"Intuit Employer Services Inc",
    "wof:placetype":"venue"
},
  "geometry": {"coordinates":[-97.078866,32.844462],"type":"Point"}
}