{
  "type": "Feature",
  "properties": {
    "iso:country":"US",
    "sg:address":"48 Highland Dr",
    "sg:city":"Angleton",
    "sg:classifiers":[
        {
            "category":"Shopping",
            "type":"Retail Goods"
        }
    ],
    "sg:phone":"+1 281 788 7999",
    "sg:postcode":"77515",
    "sg:province":"TX",
    "sg:tags":[
        "merchandise"
    ],
    "wof:name":"Big Boy Fireworks",
    "wof:placetype":"venue"
},
  "geometry": {"coordinates":[-95.4802,29.221506],"type":"Point"}
}