{
  "type": "Feature",
  "properties": {
    "iso:country":"US",
    "sg:address":"13810 Bluff Ln",
    "sg:city":"San Antonio",
    "sg:classifiers":[
        {
            "category":"Real Estate",
            "subcategory":"Real Estate Agent",
            "type":"Services"
        }
    ],
    "sg:phone":"+1 210 495 1542",
    "sg:postcode":"78216",
    "sg:province":"TX",
    "wof:name":"John Thurman Real Estate",
    "wof:placetype":"venue"
},
  "geometry": {"coordinates":[-98.50006399999999,29.570957],"type":"Point"}
}