{
  "type": "Feature",
  "properties": {
    "iso:country":"US",
    "sg:address":"435 W Sunset Rd",
    "sg:city":"San Antonio",
    "sg:classifiers":[
        {
            "category":"Home & Garden",
            "subcategory":"Building Materials",
            "type":"Retail Goods"
        }
    ],
    "sg:phone":"+1 210 824 9677",
    "sg:postcode":"78209",
    "sg:province":"TX",
    "wof:name":"Home Depot",
    "wof:placetype":"venue"
},
  "geometry": {"coordinates":[-98.477031,29.507727],"type":"Point"}
}