{
  "type": "Feature",
  "properties": {
    "iso:country":"US",
    "sg:address":"5010 91st St",
    "sg:city":"Lubbock",
    "sg:classifiers":[
        {
            "category":"Health Services",
            "subcategory":"Doctor",
            "type":"Services"
        }
    ],
    "sg:phone":"+1 806 687 6336",
    "sg:postcode":"79424",
    "sg:province":"TX",
    "sg:tags":[
        "physician"
    ],
    "wof:name":"Lamb County Medical Assoc",
    "wof:placetype":"venue"
},
  "geometry": {"coordinates":[-101.918937,33.511348],"type":"Point"}
}