{
  "type": "Feature",
  "properties": {
    "iso:country":"US",
    "sg:address":"2929 Mossrock Dr",
    "sg:city":"San Antonio",
    "sg:classifiers":[
        {
            "category":"Banks & Credit Unions",
            "subcategory":"Bank",
            "type":"Services"
        }
    ],
    "sg:phone":"+1 210 349 2102",
    "sg:postcode":"78230",
    "sg:province":"TX",
    "sg:tags":[
        "loan",
        "real estate"
    ],
    "wof:name":"Sterling Mortgage Svc",
    "wof:placetype":"venue"
},
  "geometry": {"coordinates":[-98.540515,29.510303],"type":"Point"}
}