{
  "type": "Feature",
  "properties": {
    "iso:country":"US",
    "sg:address":"1707 Cordova Dr",
    "sg:city":"Mesquite",
    "sg:classifiers":[
        {
            "category":"Professional",
            "type":"Services"
        }
    ],
    "sg:phone":"+1 972 682 0698",
    "sg:postcode":"75150",
    "sg:province":"TX",
    "wof:name":"Urban Creations",
    "wof:placetype":"venue"
},
  "geometry": {"coordinates":[-96.631182,32.843113],"type":"Point"}
}