{
  "type": "Feature",
  "properties": {
    "iso:country":"US",
    "sg:address":"10215 Asheboro St",
    "sg:city":"Frisco",
    "sg:classifiers":[
        {
            "category":"Restaurant",
            "type":"Food & Drink"
        }
    ],
    "sg:phone":"+1 972 335 9042",
    "sg:postcode":"75035",
    "sg:province":"TX",
    "sg:tags":[
        "eating"
    ],
    "wof:name":"Tropical Taste of Texas Inc",
    "wof:placetype":"venue"
},
  "geometry": {"coordinates":[-96.79227899999999,33.118376],"type":"Point"}
}