{
  "type": "Feature",
  "properties": {
    "iso:country":"US",
    "sg:address":"1720 Pantigo Dr",
    "sg:city":"Plano",
    "sg:classifiers":[
        {
            "category":"Professional",
            "subcategory":"Computer Services",
            "type":"Services"
        }
    ],
    "sg:phone":"+1 972 516 4845",
    "sg:postcode":"75075",
    "sg:province":"TX",
    "sg:tags":[
        "datum"
    ],
    "wof:name":"4site",
    "wof:placetype":"venue"
},
  "geometry": {"coordinates":[-96.729857,33.023614],"type":"Point"}
}