{
  "type": "Feature",
  "properties": {
    "iso:country":"US",
    "sg:address":"5609 Aldine Bender Rd",
    "sg:city":"Houston",
    "sg:classifiers":[
        {
            "category":"Shopping",
            "subcategory":"Florist",
            "type":"Retail Goods"
        }
    ],
    "sg:phone":"+1 281 590 0045",
    "sg:postcode":"77032",
    "sg:province":"TX",
    "wof:name":"Flowers",
    "wof:placetype":"venue"
},
  "geometry": {"coordinates":[-95.308109,29.930617],"type":"Point"}
}