{
  "type": "Feature",
  "properties": {
    "iso:country":"US",
    "sg:address":"1001 Main St",
    "sg:city":"Palacios",
    "sg:classifiers":[
        {
            "category":"Travel",
            "subcategory":"Hotels & Motels",
            "type":"Entertainment"
        }
    ],
    "sg:phone":"+1 361 972 5454",
    "sg:postcode":"77465",
    "sg:province":"TX",
    "sg:tags":[
        "resort",
        "operation"
    ],
    "wof:name":"Serendipity Bay Resort",
    "wof:placetype":"venue"
},
  "geometry": {"coordinates":[-96.22466799999999,28.701432],"type":"Point"}
}