{
  "type": "Feature",
  "properties": {
    "iso:country":"US",
    "sg:address":"1019 Euclid St",
    "sg:city":"Houston",
    "sg:classifiers":[
        {
            "category":"Professional",
            "subcategory":"Business Services",
            "type":"Services"
        }
    ],
    "sg:phone":"+1 713 880 5960",
    "sg:postcode":"77009",
    "sg:province":"TX",
    "wof:name":"Esplanade Partners LLC",
    "wof:placetype":"venue"
},
  "geometry": {"coordinates":[-95.385552,29.785308],"type":"Point"}
}