{
  "type": "Feature",
  "properties": {
    "iso:country":"US",
    "sg:address":"1301 Hill St",
    "sg:city":"Bastrop",
    "sg:classifiers":[
        {
            "category":"Professional",
            "subcategory":"Business Services",
            "type":"Services"
        }
    ],
    "sg:phone":"+1 512 303 4456",
    "sg:postcode":"78602",
    "sg:province":"TX",
    "wof:name":"Weir Enterprises",
    "wof:placetype":"venue"
},
  "geometry": {"coordinates":[-97.31509200000001,30.115116],"type":"Point"}
}