{
  "type": "Feature",
  "properties": {
    "iso:country":"US",
    "sg:address":"228 Marina Bay Dr",
    "sg:city":"Kemah",
    "sg:classifiers":[
        {
            "category":"Wholesale",
            "subcategory":"Non-durable Goods",
            "type":"Manufacturing & Wholesale Goods"
        }
    ],
    "sg:phone":"+1 281 334 9822",
    "sg:postcode":"77565",
    "sg:province":"TX",
    "sg:tags":[
        "advertising"
    ],
    "sg:website":"www.seaprints.com",
    "wof:name":"Seaprints Inc",
    "wof:placetype":"venue"
},
  "geometry": {"coordinates":[-95.021683,29.540898],"type":"Point"}
}