{
  "type": "Feature",
  "properties": {
    "iso:country":"US",
    "sg:address":"3501 Fossil Park Dr",
    "sg:city":"Fort Worth",
    "sg:classifiers":[
        {
            "category":"Professional",
            "type":"Services"
        }
    ],
    "sg:phone":"+1 817 306 8833",
    "sg:postcode":"76137",
    "sg:province":"TX",
    "wof:name":"Robson Robert W Jr Wendy",
    "wof:placetype":"venue"
},
  "geometry": {"coordinates":[-97.30471799999999,32.865718],"type":"Point"}
}