{
  "type": "Feature",
  "properties": {
    "iso:country":"US",
    "sg:address":"1107 Shady Oaks Dr",
    "sg:city":"Denton",
    "sg:classifiers":[
        {
            "category":"Government",
            "subcategory":"Post Office",
            "type":"Public Place"
        }
    ],
    "sg:phone":"+1 940 591 1979",
    "sg:postcode":"76205",
    "sg:province":"TX",
    "sg:tags":[
        "postal",
        "us"
    ],
    "wof:name":"Fed/Afwa Station",
    "wof:placetype":"venue"
},
  "geometry": {"coordinates":[-97.118135,33.200282],"type":"Point"}
}