{
  "type": "Feature",
  "properties": {
    "iso:country":"US",
    "sg:address":"9223 Willow Meadow Dr",
    "sg:city":"Houston",
    "sg:classifiers":[
        {
            "category":"Autos & Motor Vehicles",
            "subcategory":"Auto Supplies",
            "type":"Retail Goods"
        }
    ],
    "sg:phone":"+1 832 814 8494",
    "sg:postcode":"77031",
    "sg:province":"TX",
    "wof:name":"Parts Authority Inc",
    "wof:placetype":"venue"
},
  "geometry": {"coordinates":[-95.53892999999999,29.665911],"type":"Point"}
}