{
  "type": "Feature",
  "properties": {
    "iso:country":"US",
    "sg:address":"701 Solo St",
    "sg:city":"Houston",
    "sg:classifiers":[
        {
            "category":"Education",
            "subcategory":"School",
            "type":"Public Place"
        }
    ],
    "sg:phone":"+1 713 671 4195",
    "sg:postcode":"77020",
    "sg:province":"TX",
    "sg:tags":[
        "high",
        "middle",
        "elementary"
    ],
    "sg:website":"www.houstonisd.org",
    "wof:name":"Houston Independent School District",
    "wof:placetype":"venue"
},
  "geometry": {"coordinates":[-95.321257,29.768448],"type":"Point"}
}