{
  "type": "Feature",
  "properties": {
    "iso:country":"US",
    "sg:address":"1301 N Ave P",
    "sg:city":"Snyder",
    "sg:classifiers":[
        {
            "category":"Home & Garden",
            "subcategory":"Household Appliances",
            "type":"Retail Goods"
        },
        {
            "category":"Retail",
            "subcategory":"Repair Shop",
            "type":"Services"
        }
    ],
    "sg:phone":"+1 325 573 2273",
    "sg:postcode":"79549",
    "sg:province":"TX",
    "wof:name":"Johnny's Appliance",
    "wof:placetype":"venue"
},
  "geometry": {"coordinates":[-100.915188,32.755626],"type":"Point"}
}