{
  "type": "Feature",
  "properties": {
    "iso:country":"US",
    "sg:address":"6907 Meadow Creek Dr",
    "sg:city":"Dallas",
    "sg:classifiers":[
        {
            "category":"Freight",
            "type":"Transportation"
        }
    ],
    "sg:phone":"+1 972 385 4036",
    "sg:postcode":"75254",
    "sg:province":"TX",
    "sg:tags":[
        "general"
    ],
    "wof:name":"Ardmore Self Storage Llc",
    "wof:placetype":"venue"
},
  "geometry": {"coordinates":[-96.78531099999999,32.94235],"type":"Point"}
}