{
  "type": "Feature",
  "properties": {
    "iso:country":"US",
    "sg:address":"1200 Golden Key Cir",
    "sg:city":"El Paso",
    "sg:classifiers":[
        {
            "category":"Manufacturing",
            "subcategory":"Printing",
            "type":"Manufacturing & Wholesale Goods"
        }
    ],
    "sg:phone":"+1 915 594 7467",
    "sg:postcode":"79925",
    "sg:province":"TX",
    "sg:tags":[
        "publisher",
        "guide"
    ],
    "wof:name":"Haas Publishing Co",
    "wof:placetype":"venue"
},
  "geometry": {"coordinates":[-106.37197500000001,31.774682],"type":"Point"}
}