{
  "type": "Feature",
  "properties": {
    "iso:country":"US",
    "sg:address":"4119 Hillcrest Plz",
    "sg:city":"Vernon",
    "sg:classifiers":[
        {
            "category":"Cinema",
            "subcategory":"Movie Rental",
            "type":"Entertainment"
        }
    ],
    "sg:phone":"+1 434 634 3964",
    "sg:postcode":"76384",
    "sg:province":"TX",
    "sg:tags":[
        "video",
        "store"
    ],
    "wof:name":"Movie Gallery",
    "wof:placetype":"venue"
},
  "geometry": {"coordinates":[-99.313002,34.160094],"type":"Point"}
}