{
  "type": "Feature",
  "properties": {
    "iso:country":"US",
    "sg:address":"304 Whitehouse Dr",
    "sg:city":"Lufkin",
    "sg:classifiers":[
        {
            "category":"Organizations",
            "subcategory":"Religious Organization",
            "type":"Services"
        }
    ],
    "sg:phone":"+1 936 632 1392",
    "sg:postcode":"75901",
    "sg:province":"TX",
    "sg:tags":[
        "church"
    ],
    "wof:name":"Long Chapel CME Chr Parsonage",
    "wof:placetype":"venue"
},
  "geometry": {"coordinates":[-94.720934,31.298452],"type":"Point"}
}