{
  "type": "Feature",
  "properties": {
    "iso:country":"US",
    "sg:address":"2200 Hickory St",
    "sg:city":"Abilene",
    "sg:classifiers":[
        {
            "category":"Social Services",
            "type":"Services"
        }
    ],
    "sg:phone":"+1 325 670 1531",
    "sg:postcode":"79698",
    "sg:province":"TX",
    "sg:tags":[
        "counselor",
        "marriage",
        "family"
    ],
    "wof:name":"Family Psychology Ctr",
    "wof:placetype":"venue"
},
  "geometry": {"coordinates":[-99.73584099999999,32.475791],"type":"Point"}
}