{
  "type": "Feature",
  "properties": {
    "iso:country":"US",
    "sg:address":"622 US Hwy 90 Alt",
    "sg:city":"Sealy",
    "sg:classifiers":[
        {
            "category":"Food & Beverages",
            "subcategory":"Groceries & Convenience Stores",
            "type":"Retail Goods"
        }
    ],
    "sg:phone":"+1 979 885 2151",
    "sg:postcode":"77434",
    "sg:province":"TX",
    "wof:name":"Bkw Convenience Store Inc",
    "wof:placetype":"venue"
},
  "geometry": {"coordinates":[-96.330569,29.585339],"type":"Point"}
}