{
  "type": "Feature",
  "properties": {
    "iso:country":"US",
    "sg:address":"106 E Heritage Dr",
    "sg:city":"Tyler",
    "sg:classifiers":[
        {
            "category":"Professional",
            "subcategory":"Accounting & Tax Preparation",
            "type":"Services"
        }
    ],
    "sg:phone":"+1 903 509 0443",
    "sg:postcode":"75703",
    "sg:province":"TX",
    "sg:tags":[
        "return",
        "filing"
    ],
    "wof:name":"Peoples Tax Svc",
    "wof:placetype":"venue"
},
  "geometry": {"coordinates":[-95.30615400000001,32.266479],"type":"Point"}
}