{
  "type": "Feature",
  "properties": {
    "iso:country":"US",
    "sg:address":"900 8th St",
    "sg:city":"Wichita Falls",
    "sg:classifiers":[
        {
            "category":"Building & Trades",
            "subcategory":"Construction",
            "type":"Services"
        }
    ],
    "sg:phone":"+1 940 766 5599",
    "sg:postcode":"76301",
    "sg:province":"TX",
    "sg:tags":[
        "elevator"
    ],
    "wof:name":"Aspen Elevator Inc",
    "wof:placetype":"venue"
},
  "geometry": {"coordinates":[-98.49430599999999,33.91065],"type":"Point"}
}