{
  "type": "Feature",
  "properties": {
    "iso:country":"US",
    "sg:address":"2829 W 7th Ave",
    "sg:city":"Corsicana",
    "sg:classifiers":[
        {
            "category":"Professional",
            "subcategory":"Computer Services",
            "type":"Services"
        }
    ],
    "sg:phone":"+1 903 257 0970",
    "sg:postcode":"75110",
    "sg:province":"TX",
    "sg:tags":[
        "isp",
        "provider",
        "internet"
    ],
    "wof:name":"Wi-Fi 45 Wireless High Speed Internet",
    "wof:placetype":"venue"
},
  "geometry": {"coordinates":[-96.491646,32.078113],"type":"Point"}
}