{
  "type": "Feature",
  "properties": {
    "iso:country":"US",
    "sg:address":"1201 4th Ave",
    "sg:city":"Canyon",
    "sg:classifiers":[
        {
            "category":"Personal",
            "subcategory":"Barber",
            "type":"Services"
        }
    ],
    "sg:phone":"+1 806 655 4031",
    "sg:postcode":"79015",
    "sg:province":"TX",
    "sg:website":"www.universitybarbers.com",
    "wof:name":"University Barber Shop",
    "wof:placetype":"venue"
},
  "geometry": {"coordinates":[-101.93236899999999,34.980166],"type":"Point"}
}