{
  "type": "Feature",
  "properties": {
    "iso:country":"US",
    "sg:address":"202 E Broadway St",
    "sg:city":"Andrews",
    "sg:classifiers":[
        {
            "category":"Shopping",
            "subcategory":"Clothing, Apparel, & Fashions",
            "type":"Retail Goods"
        }
    ],
    "sg:phone":"+1 432 523 5059",
    "sg:postcode":"79714",
    "sg:province":"TX",
    "sg:tags":[
        "t"
    ],
    "wof:name":"T Shirt Shoppe",
    "wof:placetype":"venue"
},
  "geometry": {"coordinates":[-102.54532,32.318946],"type":"Point"}
}