{
  "type": "Feature",
  "properties": {
    "iso:country":"US",
    "sg:address":"11252 Goodnight Ln Ste 500",
    "sg:city":"Dallas",
    "sg:classifiers":[
        {
            "category":"Building & Trades",
            "subcategory":"Electrical",
            "type":"Services"
        }
    ],
    "sg:phone":"+1 972 484 7272",
    "sg:postcode":"75229",
    "sg:province":"TX",
    "sg:tags":[
        "electrician"
    ],
    "wof:name":"West Electrical Services",
    "wof:placetype":"venue"
},
  "geometry": {"coordinates":[-96.901802,32.891399],"type":"Point"}
}