{
  "type": "Feature",
  "properties": {
    "iso:country":"US",
    "sg:address":"401 Frankford Ave",
    "sg:city":"Lubbock",
    "sg:classifiers":[
        {
            "category":"Restaurant",
            "type":"Food & Drink"
        }
    ],
    "sg:phone":"+1 806 797 2449",
    "sg:postcode":"79416",
    "sg:province":"TX",
    "sg:website":"www.wendys.com",
    "wof:name":"Wendy's",
    "wof:placetype":"venue"
},
  "geometry": {"coordinates":[-101.939769,33.592272],"type":"Point"}
}