{
  "type": "Feature",
  "properties": {
    "iso:country":"US",
    "sg:address":"1141 Wilderness Trl",
    "sg:city":"Richardson",
    "sg:classifiers":[
        {
            "category":"Real Estate",
            "subcategory":"Real Estate Operator",
            "type":"Services"
        }
    ],
    "sg:phone":"+1 972 783 8631",
    "sg:postcode":"75080",
    "sg:province":"TX",
    "sg:tags":[
        "building",
        "apartment"
    ],
    "wof:name":"Synergy Realty Partners",
    "wof:placetype":"venue"
},
  "geometry": {"coordinates":[-96.743509,32.985173],"type":"Point"}
}