{
  "type": "Feature",
  "properties": {
    "iso:country":"US",
    "sg:address":"404 S Adams St",
    "sg:city":"Kemp",
    "sg:classifiers":[
        {
            "category":"Education",
            "subcategory":"School",
            "type":"Public Place"
        }
    ],
    "sg:phone":"+1 903 498 2555",
    "sg:postcode":"75143",
    "sg:province":"TX",
    "wof:name":"Learning Zone Private School",
    "wof:placetype":"venue"
},
  "geometry": {"coordinates":[-96.22760599999999,32.440751],"type":"Point"}
}