{
  "type": "Feature",
  "properties": {
    "iso:country":"US",
    "sg:address":"1401 Ruthven St",
    "sg:city":"Houston",
    "sg:classifiers":[
        {
            "category":"Organizations",
            "subcategory":"Religious Organization",
            "type":"Services"
        }
    ],
    "sg:phone":"+1 713 651 1257",
    "sg:postcode":"77019",
    "sg:province":"TX",
    "sg:tags":[
        "church"
    ],
    "wof:name":"Macedonia Missionary Baptist",
    "wof:placetype":"venue"
},
  "geometry": {"coordinates":[-95.382199,29.755134],"type":"Point"}
}