{
  "type": "Feature",
  "properties": {
    "iso:country":"US",
    "sg:address":"900 E Levee St",
    "sg:city":"Brownsville",
    "sg:classifiers":[
        {
            "category":"Banks & Credit Unions",
            "subcategory":"Bank",
            "type":"Services"
        }
    ],
    "sg:phone":"+1 956 548 1002",
    "sg:postcode":"78520",
    "sg:province":"TX",
    "wof:name":"St Francis Distribution",
    "wof:placetype":"venue"
},
  "geometry": {"coordinates":[-97.501007,25.902479],"type":"Point"}
}