{
  "type": "Feature",
  "properties": {
    "iso:country":"US",
    "sg:address":"3343 West Ave",
    "sg:city":"San Antonio",
    "sg:classifiers":[
        {
            "category":"Restaurant",
            "type":"Food & Drink"
        }
    ],
    "sg:phone":"+1 210 340 2762",
    "sg:postcode":"78213",
    "sg:province":"TX",
    "wof:name":"LA Playa Seafood",
    "wof:placetype":"venue"
},
  "geometry": {"coordinates":[-98.52605699999999,29.491107],"type":"Point"}
}