{
  "type": "Feature",
  "properties": {
    "iso:country":"US",
    "sg:address":"1731 Westminster Way",
    "sg:city":"Cedar Park",
    "sg:classifiers":[
        {
            "category":"Health Services",
            "subcategory":"Doctor",
            "type":"Services"
        }
    ],
    "sg:phone":"+1 512 260 8825",
    "sg:postcode":"78613",
    "sg:province":"TX",
    "sg:tags":[
        "physician",
        "surgeon"
    ],
    "wof:name":"Complete Pulmonary Diagnostic",
    "wof:placetype":"venue"
},
  "geometry": {"coordinates":[-97.856942,30.52358],"type":"Point"}
}