{
  "type": "Feature",
  "properties": {
    "iso:country":"US",
    "sg:address":"2632 Dunbar Dr",
    "sg:city":"Mc Kinney",
    "sg:classifiers":[
        {
            "category":"Banks & Credit Unions",
            "subcategory":"Bank",
            "type":"Services"
        }
    ],
    "sg:phone":"+1 214 592 9140",
    "sg:postcode":"75070",
    "sg:province":"TX",
    "sg:tags":[
        "loan",
        "real estate"
    ],
    "wof:name":"Benchmark Mortgage",
    "wof:placetype":"venue"
},
  "geometry": {"coordinates":[-96.696558,33.176951],"type":"Point"}
}