{
  "type": "Feature",
  "properties": {
    "iso:country":"US",
    "sg:address":"1322 Casa Verde Dr",
    "sg:city":"Corpus Christi",
    "sg:classifiers":[
        {
            "category":"Retail",
            "subcategory":"Repair Shop",
            "type":"Services"
        }
    ],
    "sg:phone":"+1 361 854 7767",
    "sg:postcode":"78411",
    "sg:province":"TX",
    "wof:name":"Seacoast Taxidermy",
    "wof:placetype":"venue"
},
  "geometry": {"coordinates":[-97.395791,27.746808],"type":"Point"}
}