{
  "type": "Feature",
  "properties": {
    "iso:country":"US",
    "sg:address":"312 Paulus St",
    "sg:city":"Schulenburg",
    "sg:classifiers":[
        {
            "category":"Professional",
            "subcategory":"Detective & Security Services",
            "type":"Services"
        }
    ],
    "sg:phone":"+1 979 743 3274",
    "sg:postcode":"78956",
    "sg:province":"TX",
    "sg:tags":[
        "car"
    ],
    "wof:name":"Highway Patrol",
    "wof:placetype":"venue"
},
  "geometry": {"coordinates":[-96.90319700000001,29.682999],"type":"Point"}
}