{
  "type": "Feature",
  "properties": {
    "iso:country":"US",
    "sg:address":"1000 Dowling St",
    "sg:city":"Houston",
    "sg:classifiers":[
        {
            "category":"Shopping",
            "type":"Retail Goods"
        }
    ],
    "sg:phone":"+1 713 828 6071",
    "sg:postcode":"77003",
    "sg:province":"TX",
    "sg:tags":[
        "merchandise"
    ],
    "wof:name":"Mpt Equipment Inc",
    "wof:placetype":"venue"
},
  "geometry": {"coordinates":[-95.35351199999999,29.748959],"type":"Point"}
}