{
  "type": "Feature",
  "properties": {
    "iso:country":"US",
    "sg:address":"2803 Slide Rd",
    "sg:city":"Lubbock",
    "sg:classifiers":[
        {
            "category":"Personal",
            "subcategory":"Beauty Salon",
            "type":"Services"
        }
    ],
    "sg:phone":"+1 806 792 4321",
    "sg:postcode":"79407",
    "sg:province":"TX",
    "sg:tags":[
        "hair",
        "stylist"
    ],
    "wof:name":"House Of Hair",
    "wof:placetype":"venue"
},
  "geometry": {"coordinates":[-101.92243999999999,33.56873],"type":"Point"}
}