{
  "type": "Feature",
  "properties": {
    "iso:country":"US",
    "sg:address":"1220 W Cleburne Rd",
    "sg:city":"Crowley",
    "sg:classifiers":[
        {
            "category":"Professional",
            "subcategory":"Management & Consulting",
            "type":"Services"
        }
    ],
    "sg:phone":"+1 817 297 3811",
    "sg:postcode":"76036",
    "sg:province":"TX",
    "wof:name":"Optimized Pipeline Solutions",
    "wof:placetype":"venue"
},
  "geometry": {"coordinates":[-97.412891,32.5568],"type":"Point"}
}