{
  "type": "Feature",
  "properties": {
    "iso:country":"US",
    "sg:address":"209 Porter Ct",
    "sg:city":"Crowley",
    "sg:classifiers":[
        {
            "category":"Building & Trades",
            "subcategory":"Cleaning & Sanitation",
            "type":"Services"
        }
    ],
    "sg:phone":"+1 817 297 2046",
    "sg:postcode":"76036",
    "sg:province":"TX",
    "sg:tags":[
        "landscaping",
        "janitorial"
    ],
    "wof:name":"C & S Services",
    "wof:placetype":"venue"
},
  "geometry": {"coordinates":[-97.360015,32.570842],"type":"Point"}
}