{
  "type": "Feature",
  "properties": {
    "iso:country":"US",
    "sg:address":"1232 N Hackberry",
    "sg:city":"San Antonio",
    "sg:classifiers":[
        {
            "category":"Wholesale",
            "subcategory":"Electrical",
            "type":"Manufacturing & Wholesale Goods"
        }
    ],
    "sg:phone":"+1 210 223 2675",
    "sg:postcode":"78202",
    "sg:province":"TX",
    "sg:tags":[
        "appliance"
    ],
    "wof:name":"Appliance Part Co",
    "wof:placetype":"venue"
},
  "geometry": {"coordinates":[-98.473187,29.434822],"type":"Point"}
}