{
  "type": "Feature",
  "properties": {
    "iso:country":"US",
    "sg:address":"4312 Live Oak St",
    "sg:city":"Dallas",
    "sg:classifiers":[
        {
            "category":"Wholesale",
            "subcategory":"Auto Parts",
            "type":"Manufacturing & Wholesale Goods"
        }
    ],
    "sg:phone":"+1 214 827 0750",
    "sg:postcode":"75204",
    "sg:province":"TX",
    "sg:tags":[
        "body",
        "automobile",
        "shop"
    ],
    "wof:name":"Ellis Color Supply Inc",
    "wof:placetype":"venue"
},
  "geometry": {"coordinates":[-96.77654,32.799161],"type":"Point"}
}