{
  "type": "Feature",
  "properties": {
    "iso:country":"US",
    "sg:address":"6001 W Waco Dr",
    "sg:city":"Waco",
    "sg:classifiers":[
        {
            "category":"Shopping",
            "subcategory":"Clothing, Apparel, & Fashions",
            "type":"Retail Goods"
        }
    ],
    "sg:phone":"+1 254 772 9774",
    "sg:postcode":"76710",
    "sg:province":"TX",
    "sg:tags":[
        "maternity"
    ],
    "wof:name":"Motherhood Maternity",
    "wof:placetype":"venue"
},
  "geometry": {"coordinates":[-97.182498,31.518083],"type":"Point"}
}