{
  "type": "Feature",
  "properties": {
    "iso:country":"US",
    "sg:address":"10845 Harry Hines Blvd",
    "sg:city":"Dallas",
    "sg:classifiers":[
        {
            "category":"Professional",
            "type":"Services"
        }
    ],
    "sg:phone":"+1 214 654 9226",
    "sg:postcode":"75220",
    "sg:province":"TX",
    "sg:tags":[
        "establishment"
    ],
    "wof:name":"H & P Intl Inc",
    "wof:placetype":"venue"
},
  "geometry": {"coordinates":[-96.884511,32.876994],"type":"Point"}
}