{
  "type": "Feature",
  "properties": {
    "iso:country":"US",
    "sg:address":"2218 Benson Dr",
    "sg:city":"Galena Park",
    "sg:classifiers":[
        {
            "category":"Arts & Performance",
            "subcategory":"Theater",
            "type":"Entertainment"
        }
    ],
    "sg:phone":"+1 713 672 2103",
    "sg:postcode":"77547",
    "sg:province":"TX",
    "sg:tags":[
        "group"
    ],
    "wof:name":"Zima",
    "wof:placetype":"venue"
},
  "geometry": {"coordinates":[-95.24629299999999,29.745201],"type":"Point"}
}