{
  "type": "Feature",
  "properties": {
    "iso:country":"US",
    "sg:address":"712 E Red River St",
    "sg:city":"Victoria",
    "sg:classifiers":[
        {
            "category":"Building & Trades",
            "subcategory":"Pest Control",
            "type":"Services"
        }
    ],
    "sg:phone":"+1 361 573 1041",
    "sg:postcode":"77901",
    "sg:province":"TX",
    "wof:name":"Cash Pest & Termite Company",
    "wof:placetype":"venue"
},
  "geometry": {"coordinates":[-96.99754900000001,28.813209],"type":"Point"}
}