{
  "type": "Feature",
  "properties": {
    "iso:country":"US",
    "sg:address":"1914 E 12th St",
    "sg:city":"Austin",
    "sg:classifiers":[
        {
            "category":"Restaurant",
            "type":"Food & Drink"
        }
    ],
    "sg:phone":"+1 512 482 0757",
    "sg:postcode":"78702",
    "sg:province":"TX",
    "sg:tags":[
        "eating",
        "soul"
    ],
    "wof:name":"Galloway's Sandwich Shop",
    "wof:placetype":"venue"
},
  "geometry": {"coordinates":[-97.7192,30.2738],"type":"Point"}
}