{
  "type": "Feature",
  "properties": {
    "iso:country":"US",
    "sg:address":"206 Little York Rd",
    "sg:city":"Houston",
    "sg:classifiers":[
        {
            "category":"Autos & Motor Vehicles",
            "subcategory":"Automobile Sales",
            "type":"Retail Goods"
        }
    ],
    "sg:phone":"+1 713 742 9755",
    "sg:postcode":"77076",
    "sg:province":"TX",
    "sg:tags":[
        "used"
    ],
    "wof:name":"Immaculate Auto Sales",
    "wof:placetype":"venue"
},
  "geometry": {"coordinates":[-95.381586,29.87],"type":"Point"}
}