{
  "type": "Feature",
  "properties": {
    "iso:country":"US",
    "sg:address":"2221 Cross Timbers Rd",
    "sg:city":"Flower Mound",
    "sg:classifiers":[
        {
            "category":"Health Services",
            "subcategory":"Chiropractor",
            "type":"Services"
        }
    ],
    "sg:phone":"+1 972 724 7247",
    "sg:postcode":"75028",
    "sg:province":"TX",
    "wof:name":"DC Mary Jo Ellig",
    "wof:placetype":"venue"
},
  "geometry": {"coordinates":[-97.065287,33.03483],"type":"Point"}
}