{
  "type": "Feature",
  "properties": {
    "iso:country":"US",
    "sg:address":"2220 Coit Rd",
    "sg:city":"Plano",
    "sg:classifiers":[
        {
            "category":"Professional",
            "subcategory":"Computer Services",
            "type":"Services"
        }
    ],
    "sg:phone":"+1 972 985 4235",
    "sg:postcode":"75075",
    "sg:province":"TX",
    "sg:tags":[
        "related"
    ],
    "wof:name":"System Managed LLP",
    "wof:placetype":"venue"
},
  "geometry": {"coordinates":[-96.76994000000001,33.028309],"type":"Point"}
}