{
  "type": "Feature",
  "properties": {
    "iso:country":"US",
    "sg:address":"116 W Fabra Ln",
    "sg:city":"Boerne",
    "sg:classifiers":[
        {
            "category":"Social Services",
            "subcategory":"Child Care",
            "type":"Services"
        },
        {
            "category":"Social Services",
            "subcategory":"Adult Care",
            "type":"Services"
        }
    ],
    "sg:phone":"+1 830 249 4866",
    "sg:postcode":"78006",
    "sg:province":"TX",
    "sg:tags":[
        "nursery",
        "centers-adult",
        "day"
    ],
    "wof:name":"Hill Country Adult Day Care Center",
    "wof:placetype":"venue"
},
  "geometry": {"coordinates":[-98.76115299999999,29.829408],"type":"Point"}
}