{
  "type": "Feature",
  "properties": {
    "iso:country":"US",
    "sg:address":"1371 Co Rd 2320",
    "sg:city":"Decatur",
    "sg:classifiers":[
        {
            "category":"Organizations",
            "subcategory":"Religious Organization",
            "type":"Services"
        }
    ],
    "sg:phone":"+1 940 627 2400",
    "sg:postcode":"76234",
    "sg:province":"TX",
    "wof:name":"Sycamore Baptist Church",
    "wof:placetype":"venue"
},
  "geometry": {"coordinates":[-97.45093300000001,33.286152],"type":"Point"}
}