{
  "type": "Feature",
  "properties": {
    "iso:country":"US",
    "sg:address":"2206 Alberton Ln",
    "sg:city":"Pearland",
    "sg:classifiers":[
        {
            "category":"Manufacturing",
            "subcategory":"Apparel",
            "type":"Manufacturing & Wholesale Goods"
        }
    ],
    "sg:phone":"+1 281 997 3613",
    "sg:postcode":"77584",
    "sg:province":"TX",
    "sg:tags":[
        "mfg"
    ],
    "wof:name":"Anointed Apparel Houston",
    "wof:placetype":"venue"
},
  "geometry": {"coordinates":[-95.366046,29.554988],"type":"Point"}
}