{
  "type": "Feature",
  "properties": {
    "iso:country":"US",
    "sg:address":"4801 Pebble Brook St",
    "sg:city":"Baytown",
    "sg:classifiers":[
        {
            "category":"Insurance",
            "subcategory":"Insurance Agent",
            "type":"Services"
        }
    ],
    "sg:phone":"+1 281 422 9983",
    "sg:postcode":"77521",
    "sg:province":"TX",
    "wof:name":"Lancaster & Assoc",
    "wof:placetype":"venue"
},
  "geometry": {"coordinates":[-95.00094900000001,29.762318],"type":"Point"}
}