{
  "type": "Feature",
  "properties": {
    "iso:country":"US",
    "sg:address":"3813 Buffalo Speedway",
    "sg:city":"Houston",
    "sg:classifiers":[
        {
            "category":"Building & Trades",
            "subcategory":"Construction",
            "type":"Services"
        }
    ],
    "sg:phone":"+1 713 523 9194",
    "sg:postcode":"77098",
    "sg:province":"TX",
    "sg:tags":[
        "contractor"
    ],
    "sg:website":"www.missionconstructors.com",
    "wof:name":"Mission Constructors",
    "wof:placetype":"venue"
},
  "geometry": {"coordinates":[-95.428101,29.730801],"type":"Point"}
}