{
  "type": "Feature",
  "properties": {
    "iso:country":"US",
    "sg:address":"1712 Ravenwood Dr",
    "sg:city":"Arlington",
    "sg:classifiers":[
        {
            "category":"Professional",
            "subcategory":"Business Services",
            "type":"Services"
        }
    ],
    "sg:phone":"+1 817 861 2878",
    "sg:postcode":"76013",
    "sg:province":"TX",
    "wof:name":"Deedles Room Recording",
    "wof:placetype":"venue"
},
  "geometry": {"coordinates":[-97.140162,32.717803],"type":"Point"}
}