{
  "type": "Feature",
  "properties": {
    "iso:country":"US",
    "sg:address":"1710 Fm 528 Rd",
    "sg:city":"Webster",
    "sg:classifiers":[
        {
            "category":"Autos & Motor Vehicles",
            "subcategory":"Fuel & Gas Station",
            "type":"Retail Goods"
        },
        {
            "category":"Retail",
            "subcategory":"Auto Repair",
            "type":"Services"
        }
    ],
    "sg:phone":"+1 281 338 9945",
    "sg:postcode":"77598",
    "sg:province":"TX",
    "wof:name":"Nasa Oil Inc",
    "wof:placetype":"venue"
},
  "geometry": {"coordinates":[-95.152885,29.523279],"type":"Point"}
}