{
  "type": "Feature",
  "properties": {
    "iso:country":"US",
    "sg:address":"10707 Shady Trl",
    "sg:city":"Dallas",
    "sg:classifiers":[
        {
            "category":"Autos & Motor Vehicles",
            "subcategory":"Automobile Sales",
            "type":"Retail Goods"
        },
        {
            "category":"Retail",
            "subcategory":"Auto Repair",
            "type":"Services"
        }
    ],
    "sg:phone":"+1 214 904 9595",
    "sg:postcode":"75220",
    "sg:province":"TX",
    "sg:tags":[
        "car"
    ],
    "wof:name":"Car Clinic Center",
    "wof:placetype":"venue"
},
  "geometry": {"coordinates":[-96.890663,32.872077],"type":"Point"}
}