{
  "type": "Feature",
  "properties": {
    "iso:country":"US",
    "sg:address":"3100 5th St",
    "sg:city":"Wichita Falls",
    "sg:classifiers":[
        {
            "category":"Organizations",
            "subcategory":"Non-profit Organization",
            "type":"Services"
        },
        {
            "category":"Health Services",
            "subcategory":"Hospital",
            "type":"Services"
        }
    ],
    "sg:phone":"+1 940 767 0423",
    "sg:postcode":"76301",
    "sg:province":"TX",
    "sg:tags":[
        "information",
        "treatment",
        "alcoholism",
        "specialty"
    ],
    "wof:name":"Serenity House Inc",
    "wof:placetype":"venue"
},
  "geometry": {"coordinates":[-98.526921,33.909659],"type":"Point"}
}