{
  "type": "Feature",
  "properties": {
    "iso:country":"US",
    "sg:address":"110 I- 35 Svc Rd",
    "sg:city":"Round Rock",
    "sg:classifiers":[
        {
            "category":"Health Services",
            "subcategory":"Chiropractor",
            "type":"Services"
        }
    ],
    "sg:phone":"+1 512 341 9303",
    "sg:postcode":"78681",
    "sg:province":"TX",
    "wof:name":"Muto Chiropractic",
    "wof:placetype":"venue"
},
  "geometry": {"coordinates":[-97.68610200000001,30.508006],"type":"Point"}
}