{
  "type": "Feature",
  "properties": {
    "iso:country":"US",
    "sg:address":"3920 Santa Ursula Ave",
    "sg:city":"Laredo",
    "sg:classifiers":[
        {
            "category":"Wholesale",
            "subcategory":"Non-durable Goods",
            "type":"Manufacturing & Wholesale Goods"
        },
        {
            "category":"Wholesale",
            "subcategory":"Durable Goods & Equipment",
            "type":"Manufacturing & Wholesale Goods"
        }
    ],
    "sg:phone":"+1 956 725 1244",
    "sg:postcode":"78041",
    "sg:province":"TX",
    "sg:tags":[
        "importer",
        "store",
        "furniture"
    ],
    "wof:name":"Ethan's Imports",
    "wof:placetype":"venue"
},
  "geometry": {"coordinates":[-99.503325,27.534772],"type":"Point"}
}