{
  "type": "Feature",
  "properties": {
    "iso:country":"US",
    "sg:address":"11711 Wallstreet",
    "sg:city":"San Antonio",
    "sg:classifiers":[
        {
            "category":"Education",
            "subcategory":"Dance Studio",
            "type":"Public Place"
        }
    ],
    "sg:phone":"+1 210 690 3382",
    "sg:postcode":"78230",
    "sg:province":"TX",
    "wof:name":"Jamie Marie Goodwin",
    "wof:placetype":"venue"
},
  "geometry": {"coordinates":[-98.561849,29.550506],"type":"Point"}
}