{
  "type": "Feature",
  "properties": {
    "iso:country":"US",
    "sg:address":"3213 79th St",
    "sg:city":"Lubbock",
    "sg:classifiers":[
        {
            "category":"Shopping",
            "subcategory":"Clothing, Apparel, & Fashions",
            "type":"Retail Goods"
        }
    ],
    "sg:phone":"+1 806 792 2540",
    "sg:postcode":"79423",
    "sg:province":"TX",
    "wof:name":"TNT Fashions",
    "wof:placetype":"venue"
},
  "geometry": {"coordinates":[-101.885158,33.522492],"type":"Point"}
}