{
  "type": "Feature",
  "properties": {
    "iso:country":"US",
    "sg:address":"2300 Chalet Trl",
    "sg:city":"Kerrville",
    "sg:classifiers":[
        {
            "category":"Building & Trades",
            "subcategory":"Construction",
            "type":"Services"
        },
        {
            "category":"Real Estate",
            "subcategory":"Real Estate Operator",
            "type":"Services"
        },
        {
            "category":"Health Services",
            "subcategory":"Nursing And Care Facility",
            "type":"Services"
        },
        {
            "category":"Health Services",
            "subcategory":"Hospice",
            "type":"Services"
        },
        {
            "category":"Social Services",
            "subcategory":"Retirement Home",
            "type":"Services"
        }
    ],
    "sg:phone":"+1 830 896 0322",
    "sg:postcode":"78028",
    "sg:province":"TX",
    "sg:tags":[
        "living",
        "life",
        "apartment",
        "assisted",
        "condominium",
        "community",
        "convalescent",
        "bureau",
        "homes-information"
    ],
    "sg:website":"http://www.thehillskerrville.com",
    "wof:name":"Hills Of Kerrville Apt Villas The",
    "wof:placetype":"venue"
},
  "geometry": {"coordinates":[-99.111977,30.065796],"type":"Point"}
}