{
  "type": "Feature",
  "properties": {
    "iso:country":"US",
    "sg:address":"7402 Creekbluff Dr",
    "sg:city":"Austin",
    "sg:classifiers":[
        {
            "category":"Manufacturing",
            "subcategory":"Retail Goods",
            "type":"Manufacturing & Wholesale Goods"
        }
    ],
    "sg:phone":"+1 512 345 9540",
    "sg:postcode":"78750",
    "sg:province":"TX",
    "sg:tags":[
        "product",
        "mfg"
    ],
    "wof:name":"Designs By Cyndi Kitson",
    "wof:placetype":"venue"
},
  "geometry": {"coordinates":[-97.785673,30.373363],"type":"Point"}
}