{
  "type": "Feature",
  "properties": {
    "iso:country":"US",
    "sg:address":"6230 Evergreen St",
    "sg:city":"Houston",
    "sg:classifiers":[
        {
            "category":"Shopping",
            "subcategory":"Gifts & Souvenirs",
            "type":"Retail Goods"
        }
    ],
    "sg:phone":"+1 713 771 1127",
    "sg:postcode":"77081",
    "sg:province":"TX",
    "sg:tags":[
        "collectible"
    ],
    "wof:name":"Bunker Militaria",
    "wof:placetype":"venue"
},
  "geometry": {"coordinates":[-95.49160999999999,29.698292],"type":"Point"}
}