{
  "type": "Feature",
  "properties": {
    "iso:country":"US",
    "sg:address":"7509 Pebble Dr",
    "sg:city":"Fort Worth",
    "sg:classifiers":[
        {
            "category":"Wholesale",
            "subcategory":"Hardware",
            "type":"Manufacturing & Wholesale Goods"
        }
    ],
    "sg:phone":"+1 817 284 1700",
    "sg:postcode":"76118",
    "sg:province":"TX",
    "wof:name":"Tyl Inc",
    "wof:placetype":"venue"
},
  "geometry": {"coordinates":[-97.218642,32.793049],"type":"Point"}
}