{
  "type": "Feature",
  "properties": {
    "iso:country":"US",
    "sg:address":"6832 Megan Ln",
    "sg:city":"Fort Worth",
    "sg:classifiers":[
        {
            "category":"Building & Trades",
            "subcategory":"Construction",
            "type":"Services"
        }
    ],
    "sg:phone":"+1 817 656 8879",
    "sg:postcode":"76180",
    "sg:province":"TX",
    "sg:tags":[
        "house"
    ],
    "wof:name":"Platinum Custom Homes Inc",
    "wof:placetype":"venue"
},
  "geometry": {"coordinates":[-97.232203,32.868288],"type":"Point"}
}