{
  "type": "Feature",
  "properties": {
    "iso:country":"US",
    "sg:address":"903 Redbud Ln",
    "sg:city":"Humble",
    "sg:classifiers":[
        {
            "category":"Professional",
            "subcategory":"Business Services",
            "type":"Services"
        }
    ],
    "sg:phone":"+1 281 358 1450",
    "sg:postcode":"77339",
    "sg:province":"TX",
    "wof:name":"Ckr Enterprises Inc",
    "wof:placetype":"venue"
},
  "geometry": {"coordinates":[-95.233576,30.030036],"type":"Point"}
}