{
  "type": "Feature",
  "properties": {
    "iso:country":"US",
    "sg:address":"1604 W Lincoln Dr",
    "sg:city":"Wylie",
    "sg:classifiers":[
        {
            "category":"Communications",
            "subcategory":"Film & Video Production",
            "type":"Services"
        }
    ],
    "sg:phone":"+1 972 442 7960",
    "sg:postcode":"75098",
    "sg:province":"TX",
    "sg:tags":[
        "motion"
    ],
    "wof:name":"Kalvaitis Productions",
    "wof:placetype":"venue"
},
  "geometry": {"coordinates":[-96.56964499999999,33.025249],"type":"Point"}
}