{
  "type": "Feature",
  "properties": {
    "iso:country":"US",
    "sg:address":"1800 19th St",
    "sg:city":"Huntsville",
    "sg:classifiers":[
        {
            "category":"Education",
            "subcategory":"School",
            "type":"Public Place"
        }
    ],
    "sg:phone":"+1 936 293 2837",
    "sg:postcode":"77340",
    "sg:province":"TX",
    "sg:website":"www.huntsville-isd.org",
    "wof:name":"Gibbs Elementary School",
    "wof:placetype":"venue"
},
  "geometry": {"coordinates":[-95.55983500000001,30.71397],"type":"Point"}
}