{
  "type": "Feature",
  "properties": {
    "iso:country":"US",
    "sg:address":"6931 Sparta Rd",
    "sg:city":"Belton",
    "sg:classifiers":[
        {
            "category":"Professional",
            "subcategory":"Business Services",
            "type":"Services"
        }
    ],
    "sg:phone":"+1 254 939 6009",
    "sg:postcode":"76513",
    "sg:province":"TX",
    "wof:name":"Stevens Business Svc",
    "wof:placetype":"venue"
},
  "geometry": {"coordinates":[-97.52375000000001,31.109458],"type":"Point"}
}