{
  "type": "Feature",
  "properties": {
    "iso:country":"US",
    "sg:address":"415 N Bonner Ave",
    "sg:city":"Tyler",
    "sg:classifiers":[
        {
            "category":"Wholesale",
            "subcategory":"Furniture",
            "type":"Manufacturing & Wholesale Goods"
        }
    ],
    "sg:phone":"+1 903 595 1991",
    "sg:postcode":"75702",
    "sg:province":"TX",
    "sg:website":"www.storywrighttyler.com",
    "wof:name":"Story-Wright Inc",
    "wof:placetype":"venue"
},
  "geometry": {"coordinates":[-95.30601,32.354603],"type":"Point"}
}