{
  "type": "Feature",
  "properties": {
    "iso:country":"US",
    "sg:address":"625 Chase Dr",
    "sg:city":"Tyler",
    "sg:classifiers":[
        {
            "category":"Real Estate",
            "subcategory":"Real Estate Agent",
            "type":"Services"
        }
    ],
    "sg:phone":"+1 903 581 8544",
    "sg:postcode":"75701",
    "sg:province":"TX",
    "wof:name":"Master Realty & Land Co",
    "wof:placetype":"venue"
},
  "geometry": {"coordinates":[-95.30843299999999,32.307121],"type":"Point"}
}