{
  "type": "Feature",
  "properties": {
    "iso:country":"US",
    "sg:address":"610 Shenandoah Dr",
    "sg:city":"Spring",
    "sg:classifiers":[
        {
            "category":"Shopping",
            "subcategory":"Computers & Home Electronics",
            "type":"Retail Goods"
        }
    ],
    "sg:phone":"+1 281 419 5066",
    "sg:postcode":"77381",
    "sg:province":"TX",
    "sg:tags":[
        "equipment",
        "dealer"
    ],
    "wof:name":"Tripp Lite",
    "wof:placetype":"venue"
},
  "geometry": {"coordinates":[-95.460481,30.180884],"type":"Point"}
}