{
  "type": "Feature",
  "properties": {
    "iso:country":"US",
    "sg:address":"3713 1st St",
    "sg:city":"Brownwood",
    "sg:classifiers":[
        {
            "category":"Professional",
            "type":"Services"
        }
    ],
    "sg:phone":"+1 325 646 4351",
    "sg:postcode":"76801",
    "sg:province":"TX",
    "wof:name":"Judson McMillan",
    "wof:placetype":"venue"
},
  "geometry": {"coordinates":[-98.961653,31.683486],"type":"Point"}
}