{
  "type": "Feature",
  "properties": {
    "iso:country":"US",
    "sg:address":"4122 Duval St",
    "sg:city":"Houston",
    "sg:classifiers":[
        {
            "category":"Retail",
            "subcategory":"Animal Services",
            "type":"Services"
        }
    ],
    "sg:phone":"+1 713 644 2696",
    "sg:postcode":"77087",
    "sg:province":"TX",
    "sg:tags":[
        "pet",
        "boarding/pet",
        "sitting"
    ],
    "wof:name":"Cat Tenders",
    "wof:placetype":"venue"
},
  "geometry": {"coordinates":[-95.3069,29.7022],"type":"Point"}
}