{
  "type": "Feature",
  "properties": {
    "iso:country":"US",
    "sg:address":"6220 Indian Creek Dr",
    "sg:city":"Fort Worth",
    "sg:classifiers":[
        {
            "category":"Professional",
            "type":"Services"
        }
    ],
    "sg:phone":"+1 817 738 3980",
    "sg:postcode":"76107",
    "sg:province":"TX",
    "wof:name":"O L Pitts",
    "wof:placetype":"venue"
},
  "geometry": {"coordinates":[-97.419832,32.749362],"type":"Point"}
}