{
  "type": "Feature",
  "properties": {
    "iso:country":"US",
    "sg:address":"2000 Silber Rd",
    "sg:city":"Houston",
    "sg:classifiers":[
        {
            "category":"Freight",
            "type":"Transportation"
        }
    ],
    "sg:phone":"+1 713 476 9937",
    "sg:postcode":"77055",
    "sg:province":"TX",
    "sg:tags":[
        "trucking"
    ],
    "wof:name":"A & E Motor Freight",
    "wof:placetype":"venue"
},
  "geometry": {"coordinates":[-95.46822,29.804661],"type":"Point"}
}