{
  "type": "Feature",
  "properties": {
    "iso:country":"US",
    "sg:address":"3100 Balch Springs Rd",
    "sg:city":"Mesquite",
    "sg:classifiers":[
        {
            "category":"Organizations",
            "subcategory":"Religious Organization",
            "type":"Services"
        }
    ],
    "sg:phone":"+1 972 557 2039",
    "sg:postcode":"75180",
    "sg:province":"TX",
    "wof:name":"Monte Los Olivios Church",
    "wof:placetype":"venue"
},
  "geometry": {"coordinates":[-96.610901,32.726398],"type":"Point"}
}