{
  "type": "Feature",
  "properties": {
    "iso:country":"US",
    "sg:address":"727 Mello Oak",
    "sg:city":"San Antonio",
    "sg:classifiers":[
        {
            "category":"Retail",
            "subcategory":"Car Wash",
            "type":"Services"
        }
    ],
    "sg:phone":"+1 210 481 0610",
    "sg:postcode":"78258",
    "sg:province":"TX",
    "sg:tags":[
        "carwash"
    ],
    "wof:name":"Kaylar Enterprises LLC",
    "wof:placetype":"venue"
},
  "geometry": {"coordinates":[-98.504204,29.625987],"type":"Point"}
}