{
  "type": "Feature",
  "properties": {
    "iso:country":"US",
    "sg:address":"2602 S Padre Island Dr",
    "sg:city":"Corpus Christi",
    "sg:classifiers":[
        {
            "category":"Autos & Motor Vehicles",
            "subcategory":"Fuel & Gas Station",
            "type":"Retail Goods"
        }
    ],
    "sg:phone":"+1 361 853 4952",
    "sg:postcode":"78415",
    "sg:province":"TX",
    "sg:tags":[
        "grocery",
        "station",
        "gasoline"
    ],
    "wof:name":"Diamond Shamrock",
    "wof:placetype":"venue"
},
  "geometry": {"coordinates":[-97.420162,27.732489],"type":"Point"}
}