{
  "type": "Feature",
  "properties": {
    "iso:country":"US",
    "sg:address":"209 S Austin St",
    "sg:city":"De Leon",
    "sg:classifiers":[
        {
            "category":"Retail",
            "subcategory":"Auto Repair",
            "type":"Services"
        }
    ],
    "sg:phone":"+1 254 893 5171",
    "sg:postcode":"76444",
    "sg:province":"TX",
    "sg:tags":[
        "repairing",
        "automobile",
        "radiator"
    ],
    "wof:name":"De Leon Radiator Shop",
    "wof:placetype":"venue"
},
  "geometry": {"coordinates":[-98.53829,32.108236],"type":"Point"}
}