{
  "type": "Feature",
  "properties": {
    "iso:country":"US",
    "sg:address":"1418 San Francisco St",
    "sg:city":"San Antonio",
    "sg:classifiers":[
        {
            "category":"Building & Trades",
            "subcategory":"Construction",
            "type":"Services"
        }
    ],
    "sg:phone":"+1 210 733 5908",
    "sg:postcode":"78201",
    "sg:province":"TX",
    "sg:tags":[
        "resurfacing",
        "laying",
        "refinishing",
        "floor"
    ],
    "wof:name":"Design Center Remolding",
    "wof:placetype":"venue"
},
  "geometry": {"coordinates":[-98.518822,29.468651],"type":"Point"}
}