{
  "type": "Feature",
  "properties": {
    "iso:country":"US",
    "sg:address":"1318 Canterlane Dr",
    "sg:city":"Houston",
    "sg:classifiers":[
        {
            "category":"Retail",
            "subcategory":"Repair Shop",
            "type":"Services"
        }
    ],
    "sg:phone":"+1 713 433 0310",
    "sg:postcode":"77047",
    "sg:province":"TX",
    "sg:tags":[
        "welding"
    ],
    "wof:name":"4ds Welding",
    "wof:placetype":"venue"
},
  "geometry": {"coordinates":[-95.403114,29.619164],"type":"Point"}
}