{
  "type": "Feature",
  "properties": {
    "iso:country":"US",
    "sg:address":"8115 Tahoe Parke Cir",
    "sg:city":"Austin",
    "sg:classifiers":[
        {
            "category":"Retail",
            "subcategory":"Repair Shop",
            "type":"Services"
        }
    ],
    "sg:phone":"+1 512 258 5591",
    "sg:postcode":"78726",
    "sg:province":"TX",
    "wof:name":"Low Overhead",
    "wof:placetype":"venue"
},
  "geometry": {"coordinates":[-97.857435,30.421088],"type":"Point"}
}