{
  "type": "Feature",
  "properties": {
    "iso:country":"US",
    "sg:address":"1201 Chicago Ave",
    "sg:city":"Mcallen",
    "sg:classifiers":[
        {
            "category":"Personal",
            "type":"Services"
        }
    ],
    "sg:phone":"+1 956 631 2873",
    "sg:postcode":"78501",
    "sg:province":"TX",
    "wof:name":"Texas Tuxedo Rental No 2",
    "wof:placetype":"venue"
},
  "geometry": {"coordinates":[-98.233773,26.201276],"type":"Point"}
}