{
  "type": "Feature",
  "properties": {
    "iso:country":"US",
    "sg:address":"4317 Ave O",
    "sg:city":"Galveston",
    "sg:classifiers":[
        {
            "category":"Building & Trades",
            "subcategory":"Construction",
            "type":"Services"
        }
    ],
    "sg:phone":"+1 281 531 8499",
    "sg:postcode":"77550",
    "sg:province":"TX",
    "sg:tags":[
        "nonresidential"
    ],
    "wof:name":"Cbm International Inc",
    "wof:placetype":"venue"
},
  "geometry": {"coordinates":[-94.81377500000001,29.287552],"type":"Point"}
}