{
  "type": "Feature",
  "properties": {
    "iso:country":"US",
    "sg:address":"3001 Fadal Ave",
    "sg:city":"Waco",
    "sg:classifiers":[
        {
            "category":"Manufacturing",
            "subcategory":"Musical Instruments",
            "type":"Manufacturing & Wholesale Goods"
        }
    ],
    "sg:phone":"+1 254 756 7197",
    "sg:postcode":"76708",
    "sg:province":"TX",
    "sg:tags":[
        "mfg"
    ],
    "wof:name":"GCB",
    "wof:placetype":"venue"
},
  "geometry": {"coordinates":[-97.18057899999999,31.565589],"type":"Point"}
}