{
  "type": "Feature",
  "properties": {
    "iso:country":"US",
    "sg:address":"1236 Ripple Creek Dr",
    "sg:city":"Houston",
    "sg:classifiers":[
        {
            "category":"Home & Garden",
            "subcategory":"Building Materials",
            "type":"Retail Goods"
        }
    ],
    "sg:phone":"+1 713 974 2704",
    "sg:postcode":"77057",
    "sg:province":"TX",
    "wof:name":"Its Unique",
    "wof:placetype":"venue"
},
  "geometry": {"coordinates":[-95.49621999999999,29.75228],"type":"Point"}
}