{
  "type": "Feature",
  "properties": {
    "iso:country":"US",
    "sg:address":"1013 S Birch St",
    "sg:city":"Perryton",
    "sg:classifiers":[
        {
            "category":"Retail",
            "subcategory":"Auto Repair",
            "type":"Services"
        }
    ],
    "sg:phone":"+1 806 435 3057",
    "sg:postcode":"79070",
    "sg:province":"TX",
    "sg:tags":[
        "repairing",
        "automobile"
    ],
    "wof:name":"Brown's Auto Repair",
    "wof:placetype":"venue"
},
  "geometry": {"coordinates":[-100.799937,36.39008],"type":"Point"}
}