{
  "type": "Feature",
  "properties": {
    "iso:country":"US",
    "sg:address":"138 N Main St",
    "sg:city":"Mansfield",
    "sg:classifiers":[
        {
            "category":"Retail",
            "subcategory":"Laundry & Dry Cleaning",
            "type":"Services"
        }
    ],
    "sg:phone":"+1 817 473 7544",
    "sg:postcode":"76063",
    "sg:province":"TX",
    "sg:tags":[
        "drycleaning",
        "plant"
    ],
    "wof:name":"Circle S Cleaners & Laundry",
    "wof:placetype":"venue"
},
  "geometry": {"coordinates":[-97.141774,32.564072],"type":"Point"}
}