{
  "type": "Feature",
  "properties": {
    "iso:country":"US",
    "sg:address":"5400 Woodway Dr",
    "sg:city":"Fort Worth",
    "sg:classifiers":[
        {
            "category":"Food & Beverages",
            "subcategory":"Bakery",
            "type":"Retail Goods"
        }
    ],
    "sg:phone":"+1 817 370 1469",
    "sg:postcode":"76133",
    "sg:province":"TX",
    "sg:tags":[
        "product",
        "doughnut",
        "mfg"
    ],
    "wof:name":"Donut Palace",
    "wof:placetype":"venue"
},
  "geometry": {"coordinates":[-97.376953,32.668501],"type":"Point"}
}