{
  "type": "Feature",
  "properties": {
    "iso:country":"US",
    "sg:address":"11341 Indian Trl",
    "sg:city":"Dallas",
    "sg:classifiers":[
        {
            "category":"Wholesale",
            "subcategory":"Construction Materials",
            "type":"Manufacturing & Wholesale Goods"
        }
    ],
    "sg:phone":"+1 972 247 6499",
    "sg:postcode":"75229",
    "sg:province":"TX",
    "sg:tags":[
        "insulation"
    ],
    "wof:name":"Moore Products LLC",
    "wof:placetype":"venue"
},
  "geometry": {"coordinates":[-96.889004,32.902356],"type":"Point"}
}