{
  "type": "Feature",
  "properties": {
    "iso:country":"US",
    "sg:address":"925 University Dr",
    "sg:city":"Fort Worth",
    "sg:classifiers":[
        {
            "category":"Manufacturing",
            "subcategory":"Apparel",
            "type":"Manufacturing & Wholesale Goods"
        }
    ],
    "sg:phone":"+1 817 877 4445",
    "sg:postcode":"76107",
    "sg:province":"TX",
    "sg:tags":[
        "clothing"
    ],
    "wof:name":"FWTX",
    "wof:placetype":"venue"
},
  "geometry": {"coordinates":[-97.361806,32.74949],"type":"Point"}
}