{
  "type": "Feature",
  "properties": {
    "iso:country":"US",
    "sg:address":"5134 Weber Rd",
    "sg:city":"Corpus Christi",
    "sg:classifiers":[
        {
            "category":"Retail",
            "subcategory":"Car Wash",
            "type":"Services"
        }
    ],
    "sg:phone":"+1 361 853 6342",
    "sg:postcode":"78411",
    "sg:province":"TX",
    "sg:tags":[
        "carwash"
    ],
    "wof:name":"Miracle Wash and Detail",
    "wof:placetype":"venue"
},
  "geometry": {"coordinates":[-97.39962800000001,27.719856],"type":"Point"}
}