{
  "type": "Feature",
  "properties": {
    "iso:country":"US",
    "sg:address":"205 N Main St",
    "sg:city":"Shamrock",
    "sg:classifiers":[
        {
            "category":"Shopping",
            "subcategory":"Clothing, Apparel, & Fashions",
            "type":"Retail Goods"
        }
    ],
    "sg:phone":"+1 806 256 3501",
    "sg:postcode":"79079",
    "sg:province":"TX",
    "wof:name":"Sanders Mens Store Inc",
    "wof:placetype":"venue"
},
  "geometry": {"coordinates":[-100.249213,35.216472],"type":"Point"}
}