{
  "type": "Feature",
  "properties": {
    "iso:country":"US",
    "sg:address":"3610 Skyranch Dr",
    "sg:city":"Alvin",
    "sg:classifiers":[
        {
            "category":"Professional",
            "type":"Services"
        }
    ],
    "sg:phone":"+1 281 331 5665",
    "sg:postcode":"77511",
    "sg:province":"TX",
    "wof:name":"Julie A Pyburn",
    "wof:placetype":"venue"
},
  "geometry": {"coordinates":[-95.281189,29.39283],"type":"Point"}
}