{
  "type": "Feature",
  "properties": {
    "iso:country":"US",
    "sg:address":"5910 Heather Blossom Ln",
    "sg:city":"Humble",
    "sg:classifiers":[
        {
            "category":"Professional",
            "type":"Services"
        }
    ],
    "sg:phone":"+1 281 360 5811",
    "sg:postcode":"77345",
    "sg:province":"TX",
    "wof:name":"Gray Menagerie",
    "wof:placetype":"venue"
},
  "geometry": {"coordinates":[-95.146027,30.042802],"type":"Point"}
}