{
  "type": "Feature",
  "properties": {
    "iso:country":"US",
    "sg:address":"16244 S Post Oak Rd",
    "sg:city":"Houston",
    "sg:classifiers":[
        {
            "category":"Retail",
            "subcategory":"Portrait Studio",
            "type":"Services"
        },
        {
            "category":"Shopping",
            "subcategory":"Pharmacy",
            "type":"Retail Goods"
        }
    ],
    "sg:phone":"+1 281 835 3420",
    "sg:postcode":"77053",
    "sg:province":"TX",
    "sg:tags":[
        "photography",
        "drugstore",
        "store"
    ],
    "sg:website":"www.walgreens.com",
    "wof:name":"Walgreens",
    "wof:placetype":"venue"
},
  "geometry": {"coordinates":[-95.469922,29.591203],"type":"Point"}
}