{
  "type": "Feature",
  "properties": {
    "iso:country":"US",
    "sg:address":"307 S 8th St",
    "sg:city":"Skidmore",
    "sg:classifiers":[
        {
            "category":"Shopping",
            "subcategory":"Discount & Variety Stores",
            "type":"Retail Goods"
        }
    ],
    "sg:phone":"+1 361 287 0303",
    "sg:postcode":"78389",
    "sg:province":"TX",
    "wof:name":"Verity Shop",
    "wof:placetype":"venue"
},
  "geometry": {"coordinates":[-97.685018,28.252107],"type":"Point"}
}