{
  "type": "Feature",
  "properties": {
    "iso:country":"US",
    "sg:address":"3307 23rd St",
    "sg:city":"Snyder",
    "sg:classifiers":[
        {
            "category":"Professional",
            "subcategory":"Detective & Security Services",
            "type":"Services"
        }
    ],
    "sg:phone":"+1 325 574 1372",
    "sg:postcode":"79549",
    "sg:province":"TX",
    "sg:tags":[
        "information",
        "bureau"
    ],
    "wof:name":"Gearhart Production Svc.",
    "wof:placetype":"venue"
},
  "geometry": {"coordinates":[-100.93400200000001,32.719337],"type":"Point"}
}