{
  "type": "Feature",
  "properties": {
    "iso:country":"US",
    "sg:address":"719 Scott Ave",
    "sg:city":"Wichita Falls",
    "sg:classifiers":[
        {
            "category":"Manufacturing",
            "subcategory":"Buildings",
            "type":"Manufacturing & Wholesale Goods"
        }
    ],
    "sg:phone":"+1 940 723 5523",
    "sg:postcode":"76301",
    "sg:province":"TX",
    "sg:tags":[
        "mobile",
        "home"
    ],
    "sg:website":"www.cavhomesinc.com",
    "wof:name":"Cavalier Homes Inc",
    "wof:placetype":"venue"
},
  "geometry": {"coordinates":[-98.492143,33.912128],"type":"Point"}
}