{
  "type": "Feature",
  "properties": {
    "iso:country":"US",
    "sg:address":"1979 Van Buren Ln",
    "sg:city":"San Antonio",
    "sg:classifiers":[
        {
            "category":"Education",
            "subcategory":"Special Training",
            "type":"Public Place"
        }
    ],
    "sg:phone":"+1 210 822 4486",
    "sg:postcode":"78217",
    "sg:province":"TX",
    "wof:name":"Red Barn Arts & Crafts",
    "wof:placetype":"venue"
},
  "geometry": {"coordinates":[-98.44926100000001,29.525233],"type":"Point"}
}