{
  "type": "Feature",
  "properties": {
    "iso:country":"US",
    "sg:address":"1101 W Erwin St",
    "sg:city":"Tyler",
    "sg:classifiers":[
        {
            "category":"Autos & Motor Vehicles",
            "subcategory":"Automobile Sales",
            "type":"Retail Goods"
        }
    ],
    "sg:phone":"+1 903 597 4842",
    "sg:postcode":"75702",
    "sg:province":"TX",
    "sg:tags":[
        "used"
    ],
    "wof:name":"Wayne Brown Used Cars",
    "wof:placetype":"venue"
},
  "geometry": {"coordinates":[-95.313367,32.350664],"type":"Point"}
}