{
  "type": "Feature",
  "properties": {
    "iso:country":"US",
    "sg:address":"149 Cherry Tree Ln",
    "sg:city":"Friendswood",
    "sg:classifiers":[
        {
            "category":"Professional",
            "type":"Services"
        }
    ],
    "sg:phone":"+1 281 682 2867",
    "sg:postcode":"77546",
    "sg:province":"TX",
    "wof:name":"Bumpit Inc",
    "wof:placetype":"venue"
},
  "geometry": {"coordinates":[-95.199715,29.541449],"type":"Point"}
}