{
  "type": "Feature",
  "properties": {
    "iso:country":"US",
    "sg:address":"501 Hillmont Ranch Rd",
    "sg:city":"Aledo",
    "sg:classifiers":[
        {
            "category":"Retail",
            "subcategory":"Animal Services",
            "type":"Services"
        }
    ],
    "sg:phone":"+1 817 441 8289",
    "sg:postcode":"76008",
    "sg:province":"TX",
    "sg:tags":[
        "farm",
        "raw",
        "product",
        "material"
    ],
    "wof:name":"Greystone Arabians",
    "wof:placetype":"venue"
},
  "geometry": {"coordinates":[-97.667008,32.719198],"type":"Point"}
}