{
  "type": "Feature",
  "properties": {
    "iso:country":"US",
    "sg:address":"202 E Main St",
    "sg:city":"Edna",
    "sg:classifiers":[
        {
            "category":"Health Services",
            "subcategory":"Clinic",
            "type":"Services"
        }
    ],
    "sg:phone":"+1 361 782 5288",
    "sg:postcode":"77957",
    "sg:province":"TX",
    "sg:tags":[
        "welfare"
    ],
    "wof:name":"Texas State Of Human Services Department",
    "wof:placetype":"venue"
},
  "geometry": {"coordinates":[-96.64539600000001,28.979092],"type":"Point"}
}