{
  "type": "Feature",
  "properties": {
    "iso:country":"US",
    "sg:address":"323 Commodore Way",
    "sg:city":"Houston",
    "sg:classifiers":[
        {
            "category":"Professional",
            "type":"Services"
        }
    ],
    "sg:phone":"+1 281 497 5565",
    "sg:postcode":"77079",
    "sg:province":"TX",
    "wof:name":"Flec Way Designs",
    "wof:placetype":"venue"
},
  "geometry": {"coordinates":[-95.636399,29.781654],"type":"Point"}
}