{
  "type": "Feature",
  "properties": {
    "iso:country":"US",
    "sg:address":"1031 Emerald Sound Blvd",
    "sg:city":"Little Elm",
    "sg:classifiers":[
        {
            "category":"Banks & Credit Unions",
            "subcategory":"Investment Brokerage",
            "type":"Services"
        }
    ],
    "sg:phone":"+1 972 292 0457",
    "sg:postcode":"75068",
    "sg:province":"TX",
    "wof:name":"Level Four Group LLC",
    "wof:placetype":"venue"
},
  "geometry": {"coordinates":[-97.00649300000001,33.193019],"type":"Point"}
}