{
  "type": "Feature",
  "properties": {
    "iso:country":"US",
    "sg:address":"916 S Oakes St",
    "sg:city":"San Angelo",
    "sg:classifiers":[
        {
            "category":"Retail",
            "subcategory":"Auto Repair",
            "type":"Services"
        }
    ],
    "sg:phone":"+1 325 657 0479",
    "sg:postcode":"76903",
    "sg:province":"TX",
    "sg:tags":[
        "automobile",
        "electric",
        "automotive"
    ],
    "wof:name":"Penfield Auto Electric Inc",
    "wof:placetype":"venue"
},
  "geometry": {"coordinates":[-100.43165,31.451677],"type":"Point"}
}