{
  "type": "Feature",
  "properties": {
    "iso:country":"US",
    "sg:address":"446 Co Rd 334",
    "sg:city":"Sutherland Springs",
    "sg:classifiers":[
        {
            "category":"Shopping",
            "subcategory":"Gifts & Souvenirs",
            "type":"Retail Goods"
        }
    ],
    "sg:phone":"+1 830 217 4768",
    "sg:postcode":"78161",
    "sg:province":"TX",
    "wof:name":"Palermos Concretes Pinat",
    "wof:placetype":"venue"
},
  "geometry": {"coordinates":[-98.01802000000001,29.282843],"type":"Point"}
}