{
  "type": "Feature",
  "properties": {
    "iso:country":"US",
    "sg:address":"120 N Bryan St",
    "sg:city":"Houston",
    "sg:classifiers":[
        {
            "category":"Manufacturing",
            "subcategory":"Signs",
            "type":"Manufacturing & Wholesale Goods"
        }
    ],
    "sg:phone":"+1 713 926 3122",
    "sg:postcode":"77011",
    "sg:province":"TX",
    "sg:tags":[
        "leaf",
        "gold"
    ],
    "wof:name":"Commercial Sign & Advertising",
    "wof:placetype":"venue"
},
  "geometry": {"coordinates":[-95.32294,29.748501],"type":"Point"}
}