{
  "type": "Feature",
  "properties": {
    "iso:country":"US",
    "sg:address":"206 Bridle Dr",
    "sg:city":"Copperas Cove",
    "sg:classifiers":[
        {
            "category":"Shopping",
            "subcategory":"Computers & Home Electronics",
            "type":"Retail Goods"
        }
    ],
    "sg:phone":"+1 254 542 7456",
    "sg:postcode":"76522",
    "sg:province":"TX",
    "wof:name":"Murphree Distributing",
    "wof:placetype":"venue"
},
  "geometry": {"coordinates":[-97.92230600000001,31.14403],"type":"Point"}
}