{
  "type": "Feature",
  "properties": {
    "iso:country":"US",
    "sg:address":"221 W Oak St",
    "sg:city":"Denton",
    "sg:classifiers":[
        {
            "category":"Food & Beverages",
            "subcategory":"Liquor & Beverages",
            "type":"Retail Goods"
        }
    ],
    "sg:phone":"+1 940 898 0434",
    "sg:postcode":"76201",
    "sg:province":"TX",
    "sg:tags":[
        "beer",
        "ale"
    ],
    "wof:name":"Bushwackers",
    "wof:placetype":"venue"
},
  "geometry": {"coordinates":[-97.134388,33.215516],"type":"Point"}
}