{
  "type": "Feature",
  "properties": {
    "iso:country":"US",
    "sg:address":"705 Main St",
    "sg:city":"Houston",
    "sg:classifiers":[
        {
            "category":"Professional",
            "subcategory":"Accounting & Tax Preparation",
            "type":"Services"
        }
    ],
    "sg:phone":"+1 713 928 8165",
    "sg:postcode":"77002",
    "sg:province":"TX",
    "sg:tags":[
        "return"
    ],
    "wof:name":"Frank Aleman Jr",
    "wof:placetype":"venue"
},
  "geometry": {"coordinates":[-95.363659,29.758435],"type":"Point"}
}