{
  "type": "Feature",
  "properties": {
    "iso:country":"US",
    "sg:address":"3911 Mission Valley Dr",
    "sg:city":"Missouri City",
    "sg:classifiers":[
        {
            "category":"Professional",
            "type":"Services"
        }
    ],
    "sg:phone":"+1 281 438 0085",
    "sg:postcode":"77459",
    "sg:province":"TX",
    "wof:name":"Rs Services Inc",
    "wof:placetype":"venue"
},
  "geometry": {"coordinates":[-95.53036400000001,29.565417],"type":"Point"}
}