{
  "type": "Feature",
  "properties": {
    "iso:country":"US",
    "sg:address":"1802 Brightlake Way",
    "sg:city":"Missouri City",
    "sg:classifiers":[
        {
            "category":"Restaurant",
            "type":"Food & Drink"
        }
    ],
    "sg:phone":"+1 281 499 4784",
    "sg:postcode":"77459",
    "sg:province":"TX",
    "sg:tags":[
        "eating"
    ],
    "wof:name":"Yaman Treats Catering",
    "wof:placetype":"venue"
},
  "geometry": {"coordinates":[-95.574985,29.593883],"type":"Point"}
}