{
  "type": "Feature",
  "properties": {
    "iso:country":"US",
    "sg:address":"4631 Vance Jackson Rd",
    "sg:city":"San Antonio",
    "sg:classifiers":[
        {
            "category":"Insurance",
            "subcategory":"Hazard Insurance",
            "type":"Services"
        }
    ],
    "sg:phone":"+1 210 732 6333",
    "sg:postcode":"78230",
    "sg:province":"TX",
    "sg:tags":[
        "casualty"
    ],
    "wof:name":"American National Prop & Cslty",
    "wof:placetype":"venue"
},
  "geometry": {"coordinates":[-98.535439,29.520981],"type":"Point"}
}