{
  "type": "Feature",
  "properties": {
    "iso:country":"US",
    "sg:address":"2244 Jacksboro Hwy",
    "sg:city":"Fort Worth",
    "sg:classifiers":[
        {
            "category":"Autos & Motor Vehicles",
            "subcategory":"Fuel & Gas Station",
            "type":"Retail Goods"
        }
    ],
    "sg:phone":"+1 817 624 1113",
    "sg:postcode":"76114",
    "sg:province":"TX",
    "sg:tags":[
        "station",
        "gasoline"
    ],
    "wof:name":"Tire & Auto Station",
    "wof:placetype":"venue"
},
  "geometry": {"coordinates":[-97.377287,32.782959],"type":"Point"}
}