{
  "type": "Feature",
  "properties": {
    "iso:country":"US",
    "sg:address":"6029 Trone Trl",
    "sg:city":"San Antonio",
    "sg:classifiers":[
        {
            "category":"Organizations",
            "subcategory":"Membership Organization",
            "type":"Services"
        }
    ],
    "sg:phone":"+1 210 681 0551",
    "sg:postcode":"78238",
    "sg:province":"TX",
    "wof:name":"Society of Descendants Span",
    "wof:placetype":"venue"
},
  "geometry": {"coordinates":[-98.606336,29.491744],"type":"Point"}
}