{
  "type": "Feature",
  "properties": {
    "iso:country":"US",
    "sg:address":"15405 Fortuna Bay Dr",
    "sg:city":"Corpus Christi",
    "sg:classifiers":[
        {
            "category":"Real Estate",
            "subcategory":"Real Estate Agent",
            "type":"Services"
        }
    ],
    "sg:phone":"+1 361 949 7554",
    "sg:postcode":"78418",
    "sg:province":"TX",
    "wof:name":"Fortuna Bay",
    "wof:placetype":"venue"
},
  "geometry": {"coordinates":[-97.232157,27.596243],"type":"Point"}
}