{
  "type": "Feature",
  "properties": {
    "iso:country":"US",
    "sg:address":"1414 Lakeview Dr",
    "sg:city":"Sour Lake",
    "sg:classifiers":[
        {
            "category":"Professional",
            "type":"Services"
        }
    ],
    "sg:phone":"+1 409 753 3200",
    "sg:postcode":"77659",
    "sg:province":"TX",
    "sg:tags":[
        "motion",
        "picture"
    ],
    "wof:name":"Hindsfeet Music Co Inc",
    "wof:placetype":"venue"
},
  "geometry": {"coordinates":[-94.323764,30.166336],"type":"Point"}
}