{
  "type": "Feature",
  "properties": {
    "iso:country":"US",
    "sg:address":"909 Westway Dr",
    "sg:city":"Temple",
    "sg:classifiers":[
        {
            "category":"Farming",
            "subcategory":"Livestock Farm",
            "type":"Manufacturing & Wholesale Goods"
        }
    ],
    "sg:phone":"+1 254 681 9965",
    "sg:postcode":"76502",
    "sg:province":"TX",
    "sg:tags":[
        "beef",
        "feedlot",
        "cattle"
    ],
    "wof:name":"Lagarde Cattle Co",
    "wof:placetype":"venue"
},
  "geometry": {"coordinates":[-97.43510999999999,31.111877],"type":"Point"}
}