{
  "type": "Feature",
  "properties": {
    "iso:country":"US",
    "sg:address":"27906 Copper Crst",
    "sg:city":"San Antonio",
    "sg:classifiers":[
        {
            "category":"Professional",
            "type":"Services"
        }
    ],
    "sg:phone":"+1 830 980 4969",
    "sg:postcode":"78260",
    "sg:province":"TX",
    "wof:name":"Zadie Inc",
    "wof:placetype":"venue"
},
  "geometry": {"coordinates":[-98.49881600000001,29.71886],"type":"Point"}
}