{
  "type": "Feature",
  "properties": {
    "iso:country":"US",
    "sg:address":"701 Tokio Rd",
    "sg:city":"West",
    "sg:classifiers":[
        {
            "category":"Real Estate",
            "subcategory":"Real Estate Operator",
            "type":"Services"
        }
    ],
    "sg:phone":"+1 254 826 3853",
    "sg:postcode":"76691",
    "sg:province":"TX",
    "sg:tags":[
        "building",
        "apartment"
    ],
    "wof:name":"West Apartments Ltd",
    "wof:placetype":"venue"
},
  "geometry": {"coordinates":[-97.1003,31.789251],"type":"Point"}
}