{
  "type": "Feature",
  "properties": {
    "iso:country":"US",
    "sg:address":"200 Rancho Viejo Blvd",
    "sg:city":"Brownsville",
    "sg:classifiers":[
        {
            "category":"Professional",
            "subcategory":"Computer Services",
            "type":"Services"
        },
        {
            "category":"Shopping",
            "subcategory":"Computers & Home Electronics",
            "type":"Retail Goods"
        }
    ],
    "sg:phone":"+1 956 831 9080",
    "sg:postcode":"78526",
    "sg:province":"TX",
    "sg:tags":[
        "programing",
        "custom"
    ],
    "wof:name":"Settle & Associates",
    "wof:placetype":"venue"
},
  "geometry": {"coordinates":[-97.43514999999999,25.971954],"type":"Point"}
}