{
  "type": "Feature",
  "properties": {
    "iso:country":"US",
    "sg:address":"12524 Seagoville Rd",
    "sg:city":"Mesquite",
    "sg:classifiers":[
        {
            "category":"Farming",
            "subcategory":"Farm",
            "type":"Manufacturing & Wholesale Goods"
        }
    ],
    "sg:phone":"+1 972 286 4607",
    "sg:postcode":"75180",
    "sg:province":"TX",
    "sg:tags":[
        "crop",
        "general"
    ],
    "wof:name":"Charles Yates",
    "wof:placetype":"venue"
},
  "geometry": {"coordinates":[-96.61038499999999,32.704774],"type":"Point"}
}