{
  "type": "Feature",
  "properties": {
    "iso:country":"US",
    "sg:address":"8708 Airport Fwy",
    "sg:city":"Hurst",
    "sg:classifiers":[
        {
            "category":"Personal",
            "type":"Services"
        },
        {
            "category":"Shopping",
            "subcategory":"Clothing, Apparel, & Fashions",
            "type":"Retail Goods"
        }
    ],
    "sg:phone":"+1 817 284 9165",
    "sg:postcode":"76053",
    "sg:province":"TX",
    "sg:tags":[
        "tuxedo"
    ],
    "wof:name":"Al's Formal Wear",
    "wof:placetype":"venue"
},
  "geometry": {"coordinates":[-97.19555099999999,32.836438],"type":"Point"}
}