{
  "type": "Feature",
  "properties": {
    "iso:country":"US",
    "sg:address":"3830 Fernglade Dr",
    "sg:city":"Houston",
    "sg:classifiers":[
        {
            "category":"Professional",
            "subcategory":"Lawyer & Legal Services",
            "type":"Services"
        }
    ],
    "sg:phone":"+1 281 444 9250",
    "sg:postcode":"77068",
    "sg:province":"TX",
    "sg:tags":[
        "attorney"
    ],
    "wof:name":"Jeffrey H Ewalt",
    "wof:placetype":"venue"
},
  "geometry": {"coordinates":[-95.491776,29.997265],"type":"Point"}
}