{
  "type": "Feature",
  "properties": {
    "iso:country":"US",
    "sg:address":"509 Rio Grande St",
    "sg:city":"Austin",
    "sg:classifiers":[
        {
            "category":"Retail",
            "subcategory":"Repair Shop",
            "type":"Services"
        }
    ],
    "sg:phone":"+1 512 472 6273",
    "sg:postcode":"78701",
    "sg:province":"TX",
    "sg:tags":[
        "bicycle",
        "store",
        "locksmith"
    ],
    "wof:name":"COTHRONS BIKE SHOP",
    "wof:placetype":"venue"
},
  "geometry": {"coordinates":[-97.749477,30.269845],"type":"Point"}
}