{
  "type": "Feature",
  "properties": {
    "iso:country":"US",
    "sg:address":"1301 Lincoln St",
    "sg:city":"Alice",
    "sg:classifiers":[
        {
            "category":"Museum",
            "subcategory":"Botanical Garden",
            "type":"Entertainment"
        }
    ],
    "sg:phone":"+1 361 664 6131",
    "sg:postcode":"78332",
    "sg:province":"TX",
    "wof:name":"Texas Garden Clubs Inc",
    "wof:placetype":"venue"
},
  "geometry": {"coordinates":[-98.055306,27.767603],"type":"Point"}
}