{
  "type": "Feature",
  "properties": {
    "iso:country":"US",
    "sg:address":"5606 Weeping Willow Rd",
    "sg:city":"Houston",
    "sg:classifiers":[
        {
            "category":"Building & Trades",
            "subcategory":"Construction",
            "type":"Services"
        }
    ],
    "sg:phone":"+1 713 688 1984",
    "sg:postcode":"77092",
    "sg:province":"TX",
    "sg:tags":[
        "house",
        "contractor"
    ],
    "wof:name":"Longoria's Construction Co",
    "wof:placetype":"venue"
},
  "geometry": {"coordinates":[-95.472702,29.837999],"type":"Point"}
}