{
  "type": "Feature",
  "properties": {
    "iso:country":"US",
    "sg:address":"15350 North Fwy",
    "sg:city":"Houston",
    "sg:classifiers":[
        {
            "category":"Autos & Motor Vehicles",
            "subcategory":"Automobile Sales",
            "type":"Retail Goods"
        }
    ],
    "sg:phone":"+1 281 821 1222",
    "sg:postcode":"77090",
    "sg:province":"TX",
    "sg:tags":[
        "specializing",
        "car",
        "corvette",
        "used"
    ],
    "wof:name":"Corvettes of Dallas",
    "wof:placetype":"venue"
},
  "geometry": {"coordinates":[-95.423869,29.98822],"type":"Point"}
}