{
  "type": "Feature",
  "properties": {
    "iso:country":"US",
    "sg:address":"6137 South Loop E",
    "sg:city":"Houston",
    "sg:classifiers":[
        {
            "category":"Restaurant",
            "type":"Food & Drink"
        }
    ],
    "sg:menulink":"http://www.allmenus.com/tx/houston/192246-wendys/menu/",
    "sg:phone":"+1 713 644 4506",
    "sg:postcode":"77087",
    "sg:province":"TX",
    "sg:tags":[
        "burger",
        "american",
        "soup"
    ],
    "wof:name":"Wendy's",
    "wof:placetype":"venue"
},
  "geometry": {"coordinates":[-95.320746,29.695015],"type":"Point"}
}