{
  "type": "Feature",
  "properties": {
    "iso:country":"US",
    "sg:address":"5601 Bandera Rd",
    "sg:city":"San Antonio",
    "sg:classifiers":[
        {
            "category":"Wholesale",
            "subcategory":"Machinery & Supplies",
            "type":"Manufacturing & Wholesale Goods"
        }
    ],
    "sg:phone":"+1 210 647 1000",
    "sg:postcode":"78238",
    "sg:province":"TX",
    "sg:tags":[
        "janitor"
    ],
    "wof:name":"Cleaning Ideas Corp",
    "wof:placetype":"venue"
},
  "geometry": {"coordinates":[-98.595017,29.480707],"type":"Point"}
}