{
  "type": "Feature",
  "properties": {
    "iso:country":"US",
    "sg:address":"8201 S Gessner Dr",
    "sg:city":"Houston",
    "sg:classifiers":[
        {
            "category":"Shopping",
            "subcategory":"Mobile Phones",
            "type":"Retail Goods"
        }
    ],
    "sg:phone":"+1 713 271 0252",
    "sg:postcode":"77036",
    "sg:province":"TX",
    "sg:website":"www.t-mobile.com",
    "wof:name":"T-Mobile",
    "wof:placetype":"venue"
},
  "geometry": {"coordinates":[-95.5335,29.690003],"type":"Point"}
}