{
  "type": "Feature",
  "properties": {
    "iso:country":"US",
    "sg:address":"5202 FM 2378",
    "sg:city":"Lubbock",
    "sg:classifiers":[
        {
            "category":"Building & Trades",
            "subcategory":"Landscaping Services",
            "type":"Services"
        }
    ],
    "sg:phone":"+1 806 885 1422",
    "sg:postcode":"79407",
    "sg:province":"TX",
    "sg:tags":[
        "lawn",
        "maintenance",
        "grounds"
    ],
    "wof:name":"Clean Cut Lawn Svc",
    "wof:placetype":"venue"
},
  "geometry": {"coordinates":[-102.078446,33.546776],"type":"Point"}
}