{
  "type": "Feature",
  "properties": {
    "iso:country":"US",
    "sg:address":"229 N Seven Points Dr",
    "sg:city":"Kemp",
    "sg:classifiers":[
        {
            "category":"Coffee & Tea",
            "type":"Food & Drink"
        },
        {
            "category":"Restaurant",
            "type":"Food & Drink"
        }
    ],
    "sg:phone":"+1 903 432 9555",
    "sg:postcode":"75143",
    "sg:province":"TX",
    "sg:tags":[
        "espresso"
    ],
    "wof:name":"Yellow Rose Cafe",
    "wof:placetype":"venue"
},
  "geometry": {"coordinates":[-96.19172399999999,32.326788],"type":"Point"}
}