{
  "type": "Feature",
  "properties": {
    "iso:country":"US",
    "sg:address":"305 Mahan Ave",
    "sg:city":"Wharton",
    "sg:classifiers":[
        {
            "category":"Organizations",
            "subcategory":"Religious Organization",
            "type":"Services"
        }
    ],
    "sg:phone":"+1 979 532 5604",
    "sg:postcode":"77488",
    "sg:province":"TX",
    "sg:tags":[
        "church"
    ],
    "wof:name":"St James Miss Jesus Bapt Chr",
    "wof:placetype":"venue"
},
  "geometry": {"coordinates":[-96.086074,29.309664],"type":"Point"}
}