{
  "type": "Feature",
  "properties": {
    "iso:country":"US",
    "sg:address":"4323 Gloster Rd",
    "sg:city":"Dallas",
    "sg:classifiers":[
        {
            "category":"Professional",
            "subcategory":"Business Services",
            "type":"Services"
        }
    ],
    "sg:phone":"+1 214 352 6933",
    "sg:postcode":"75220",
    "sg:province":"TX",
    "wof:name":"Sandra Prater Interiors",
    "wof:placetype":"venue"
},
  "geometry": {"coordinates":[-96.83626700000001,32.868816],"type":"Point"}
}