{
  "type": "Feature",
  "properties": {
    "iso:country":"US",
    "sg:address":"321 N Wilbarger St",
    "sg:city":"Electra",
    "sg:classifiers":[
        {
            "category":"Organizations",
            "subcategory":"Religious Organization",
            "type":"Services"
        }
    ],
    "sg:phone":"+1 940 495 2622",
    "sg:postcode":"76360",
    "sg:province":"TX",
    "wof:name":"Bible Baptist Church",
    "wof:placetype":"venue"
},
  "geometry": {"coordinates":[-98.914902,34.031388],"type":"Point"}
}