{
  "type": "Feature",
  "properties": {
    "iso:country":"US",
    "sg:address":"4109 Airline Dr",
    "sg:city":"Houston",
    "sg:classifiers":[
        {
            "category":"Professional",
            "subcategory":"Advertising",
            "type":"Services"
        },
        {
            "category":"Restaurant",
            "type":"Food & Drink"
        }
    ],
    "sg:phone":"+1 713 440 9933",
    "sg:postcode":"77022",
    "sg:province":"TX",
    "sg:tags":[
        "shop",
        "distribution",
        "eating",
        "meat",
        "grocery"
    ],
    "wof:name":"Dave's Deli Products Inc",
    "wof:placetype":"venue"
},
  "geometry": {"coordinates":[-95.38453199999999,29.824495],"type":"Point"}
}