{
  "type": "Feature",
  "properties": {
    "iso:country":"US",
    "sg:address":"1225 Capital Dr",
    "sg:city":"Carrollton",
    "sg:classifiers":[
        {
            "category":"Wholesale",
            "subcategory":"Machinery & Supplies",
            "type":"Manufacturing & Wholesale Goods"
        }
    ],
    "sg:phone":"+1 972 446 4042",
    "sg:postcode":"75006",
    "sg:province":"TX",
    "sg:tags":[
        "equipment",
        "industrial"
    ],
    "wof:name":"C&S Litho Supply",
    "wof:placetype":"venue"
},
  "geometry": {"coordinates":[-96.91925999999999,32.954648],"type":"Point"}
}