{
  "type": "Feature",
  "properties": {
    "iso:country":"US",
    "sg:address":"304 E Rio Grande St",
    "sg:city":"Victoria",
    "sg:classifiers":[
        {
            "category":"Restaurant",
            "type":"Food & Drink"
        }
    ],
    "sg:phone":"+1 361 578 5161",
    "sg:postcode":"77901",
    "sg:province":"TX",
    "sg:tags":[
        "preparation",
        "grocery",
        "eating",
        "mfg"
    ],
    "wof:name":"Venturas Tamales & Specialties",
    "wof:placetype":"venue"
},
  "geometry": {"coordinates":[-97.00105499999999,28.805683],"type":"Point"}
}