{
  "type": "Feature",
  "properties": {
    "iso:country":"US",
    "sg:address":"400 Ackerman St",
    "sg:city":"Rockdale",
    "sg:classifiers":[
        {
            "category":"Personal",
            "subcategory":"Beauty Salon",
            "type":"Services"
        }
    ],
    "sg:phone":"+1 512 446 3066",
    "sg:postcode":"76567",
    "sg:province":"TX",
    "sg:tags":[
        "hair",
        "stylist"
    ],
    "wof:name":"Hair Country",
    "wof:placetype":"venue"
},
  "geometry": {"coordinates":[-97.001419,30.65782],"type":"Point"}
}