{
  "type": "Feature",
  "properties": {
    "iso:country":"US",
    "sg:address":"1603 E Earle St",
    "sg:city":"Tyler",
    "sg:classifiers":[
        {
            "category":"Organizations",
            "subcategory":"Religious Organization",
            "type":"Services"
        }
    ],
    "sg:phone":"+1 903 597 0005",
    "sg:postcode":"75702",
    "sg:province":"TX",
    "wof:name":"Ark Ministries Of Tyler",
    "wof:placetype":"venue"
},
  "geometry": {"coordinates":[-95.282028,32.348003],"type":"Point"}
}