{
  "type": "Feature",
  "properties": {
    "iso:country":"US",
    "sg:address":"3215 Gilbert St",
    "sg:city":"Austin",
    "sg:classifiers":[
        {
            "category":"Real Estate",
            "subcategory":"Real Estate Services",
            "type":"Services"
        },
        {
            "category":"Real Estate",
            "subcategory":"Developer",
            "type":"Services"
        },
        {
            "category":"Real Estate",
            "subcategory":"Real Estate Agent",
            "type":"Services"
        }
    ],
    "sg:phone":"+1 512 342 1700",
    "sg:postcode":"78703",
    "sg:province":"TX",
    "sg:tags":[
        "investing",
        "management"
    ],
    "wof:name":"Pearson Equity",
    "wof:placetype":"venue"
},
  "geometry": {"coordinates":[-97.77287699999999,30.298224],"type":"Point"}
}