{
  "type": "Feature",
  "properties": {
    "iso:country":"US",
    "sg:address":"14407 Investment Ave",
    "sg:city":"Laredo",
    "sg:classifiers":[
        {
            "category":"Professional",
            "type":"Services"
        }
    ],
    "sg:phone":"+1 956 753 3348",
    "sg:postcode":"78045",
    "sg:province":"TX",
    "wof:name":"Lomelin Trasport LLC",
    "wof:placetype":"venue"
},
  "geometry": {"coordinates":[-99.53364000000001,27.630618],"type":"Point"}
}