{
  "type": "Feature",
  "properties": {
    "iso:country":"US",
    "sg:address":"1201 E 40th St",
    "sg:city":"Lubbock",
    "sg:classifiers":[
        {
            "category":"Freight",
            "type":"Transportation"
        }
    ],
    "sg:phone":"+1 806 747 7071",
    "sg:postcode":"79404",
    "sg:province":"TX",
    "sg:tags":[
        "trucking"
    ],
    "wof:name":"K & M Transportation",
    "wof:placetype":"venue"
},
  "geometry": {"coordinates":[-101.82256700000001,33.557904],"type":"Point"}
}