{
  "type": "Feature",
  "properties": {
    "iso:country":"US",
    "sg:address":"106 E Marshall Ave",
    "sg:city":"Longview",
    "sg:classifiers":[
        {
            "category":"Restaurant",
            "type":"Food & Drink"
        }
    ],
    "sg:phone":"+1 903 753 8081",
    "sg:postcode":"75601",
    "sg:province":"TX",
    "sg:tags":[
        "eating"
    ],
    "wof:name":"Hot Dog Express",
    "wof:placetype":"venue"
},
  "geometry": {"coordinates":[-94.737139,32.50051],"type":"Point"}
}