{
  "type": "Feature",
  "properties": {
    "iso:country":"US",
    "sg:address":"1329 Dandelion Trl",
    "sg:city":"Burleson",
    "sg:classifiers":[
        {
            "category":"Banks & Credit Unions",
            "subcategory":"Investment Brokerage",
            "type":"Services"
        },
        {
            "category":"Banks & Credit Unions",
            "subcategory":"Financial Services",
            "type":"Services"
        }
    ],
    "sg:phone":"+1 817 706 1221",
    "sg:postcode":"76028",
    "sg:province":"TX",
    "sg:tags":[
        "advisory",
        "planner"
    ],
    "wof:name":"Streib Diversified Financial, Inc.",
    "wof:placetype":"venue"
},
  "geometry": {"coordinates":[-97.345811,32.563023],"type":"Point"}
}