{
  "type": "Feature",
  "properties": {
    "iso:country":"US",
    "sg:address":"4026 Manordale Dr",
    "sg:city":"Houston",
    "sg:classifiers":[
        {
            "category":"Social Services",
            "subcategory":"Child Care",
            "type":"Services"
        }
    ],
    "sg:phone":"+1 832 876 3137",
    "sg:postcode":"77082",
    "sg:province":"TX",
    "wof:name":"Caring Hands Daycare",
    "wof:placetype":"venue"
},
  "geometry": {"coordinates":[-95.658931,29.712719],"type":"Point"}
}