{
  "type": "Feature",
  "properties": {
    "iso:country":"US",
    "sg:address":"8130 Ceberry Dr",
    "sg:city":"Austin",
    "sg:classifiers":[
        {
            "category":"Travel",
            "subcategory":"Travel Agent",
            "type":"Entertainment"
        }
    ],
    "sg:phone":"+1 512 345 1878",
    "sg:postcode":"78759",
    "sg:province":"TX",
    "sg:tags":[
        "agency"
    ],
    "wof:name":"Hooman Travel Center",
    "wof:placetype":"venue"
},
  "geometry": {"coordinates":[-97.746152,30.366937],"type":"Point"}
}