{
  "type": "Feature",
  "properties": {
    "iso:country":"US",
    "sg:address":"10308 US Hwy 80",
    "sg:city":"Forney",
    "sg:classifiers":[
        {
            "category":"Restaurant",
            "type":"Food & Drink"
        }
    ],
    "sg:phone":"+1 972 564 5028",
    "sg:postcode":"75126",
    "sg:province":"TX",
    "sg:tags":[
        "eating"
    ],
    "wof:name":"Zak's Burger Shak",
    "wof:placetype":"venue"
},
  "geometry": {"coordinates":[-96.432592,32.741247],"type":"Point"}
}