{
  "type": "Feature",
  "properties": {
    "iso:country":"US",
    "sg:address":"6010 Elm St",
    "sg:city":"Houston",
    "sg:classifiers":[
        {
            "category":"Building & Trades",
            "subcategory":"Construction",
            "type":"Services"
        }
    ],
    "sg:phone":"+1 713 660 9670",
    "sg:postcode":"77081",
    "sg:province":"TX",
    "sg:tags":[
        "contractor"
    ],
    "wof:name":"Oliveras Drywall",
    "wof:placetype":"venue"
},
  "geometry": {"coordinates":[-95.48871,29.712824],"type":"Point"}
}