{
  "type": "Feature",
  "properties": {
    "iso:country":"US",
    "sg:address":"12123 West Rd",
    "sg:city":"Houston",
    "sg:classifiers":[
        {
            "category":"Food & Beverages",
            "subcategory":"Groceries & Convenience Stores",
            "type":"Retail Goods"
        }
    ],
    "sg:phone":"+1 281 469 8971",
    "sg:postcode":"77065",
    "sg:province":"TX",
    "wof:name":"Danny Mart",
    "wof:placetype":"venue"
},
  "geometry": {"coordinates":[-95.596833,29.902592],"type":"Point"}
}