{
  "type": "Feature",
  "properties": {
    "iso:country":"US",
    "sg:address":"2106 Dillard St",
    "sg:city":"Fort Worth",
    "sg:classifiers":[
        {
            "category":"Organizations",
            "subcategory":"Religious Organization",
            "type":"Services"
        }
    ],
    "sg:phone":"+1 817 535 8350",
    "sg:postcode":"76105",
    "sg:province":"TX",
    "sg:tags":[
        "church"
    ],
    "wof:name":"Larkin Memorial I M E Church",
    "wof:placetype":"venue"
},
  "geometry": {"coordinates":[-97.242919,32.721184],"type":"Point"}
}