{
  "type": "Feature",
  "properties": {
    "iso:country":"US",
    "sg:address":"14622 Vaughnville Dr",
    "sg:city":"Houston",
    "sg:classifiers":[
        {
            "category":"Retail",
            "subcategory":"Laundry & Dry Cleaning",
            "type":"Services"
        }
    ],
    "sg:phone":"+1 281 345 2806",
    "sg:postcode":"77084",
    "sg:province":"TX",
    "wof:name":"Jbs Custom Sewing & Alte",
    "wof:placetype":"venue"
},
  "geometry": {"coordinates":[-95.62788999999999,29.871509],"type":"Point"}
}