{
  "type": "Feature",
  "properties": {
    "iso:country":"US",
    "sg:address":"4313 Pan American Blvd",
    "sg:city":"Laredo",
    "sg:classifiers":[
        {
            "category":"Freight",
            "type":"Transportation"
        }
    ],
    "sg:phone":"+1 956 729 7932",
    "sg:postcode":"78045",
    "sg:province":"TX",
    "wof:name":"Gafi Forwarding",
    "wof:placetype":"venue"
},
  "geometry": {"coordinates":[-99.539197,27.63405],"type":"Point"}
}