{
  "type": "Feature",
  "properties": {
    "iso:country":"US",
    "sg:address":"3708 Trillium Dr",
    "sg:city":"Plano",
    "sg:classifiers":[
        {
            "category":"Banks & Credit Unions",
            "subcategory":"Bank",
            "type":"Services"
        }
    ],
    "sg:phone":"+1 972 985 2370",
    "sg:postcode":"75093",
    "sg:province":"TX",
    "sg:tags":[
        "loan",
        "real estate"
    ],
    "wof:name":"Dream Works Mtg & Financial",
    "wof:placetype":"venue"
},
  "geometry": {"coordinates":[-96.780642,33.048671],"type":"Point"}
}