{
  "type": "Feature",
  "properties": {
    "iso:country":"US",
    "sg:address":"9701 Dessau Rd",
    "sg:city":"Austin",
    "sg:classifiers":[
        {
            "category":"Manufacturing",
            "subcategory":"Printing",
            "type":"Manufacturing & Wholesale Goods"
        }
    ],
    "sg:phone":"+1 512 339 2644",
    "sg:postcode":"78754",
    "sg:province":"TX",
    "sg:tags":[
        "printer"
    ],
    "wof:name":"Custom Envelopes",
    "wof:placetype":"venue"
},
  "geometry": {"coordinates":[-97.67296399999999,30.355081],"type":"Point"}
}