{
  "type": "Feature",
  "properties": {
    "iso:country":"US",
    "sg:address":"600 N Roberts St",
    "sg:city":"Amarillo",
    "sg:classifiers":[
        {
            "category":"Freight",
            "type":"Transportation"
        }
    ],
    "sg:phone":"+1 806 376 9057",
    "sg:postcode":"79107",
    "sg:province":"TX",
    "sg:tags":[
        "carrier",
        "commodity",
        "motor",
        "general"
    ],
    "wof:name":"USFreightways",
    "wof:placetype":"venue"
},
  "geometry": {"coordinates":[-101.817251,35.217696],"type":"Point"}
}