{
  "type": "Feature",
  "properties": {
    "iso:country":"US",
    "sg:address":"118 Eastland Ln",
    "sg:city":"Wichita Falls",
    "sg:classifiers":[
        {
            "category":"Building & Trades",
            "subcategory":"Construction",
            "type":"Services"
        }
    ],
    "sg:phone":"+1 940 723 2239",
    "sg:postcode":"76305",
    "sg:province":"TX",
    "sg:tags":[
        "sandblasting"
    ],
    "wof:name":"Smith's Sandblasting Svc",
    "wof:placetype":"venue"
},
  "geometry": {"coordinates":[-98.446123,33.941381],"type":"Point"}
}