{
  "type": "Feature",
  "properties": {
    "iso:country":"US",
    "sg:address":"130 S 4th St",
    "sg:city":"La Porte",
    "sg:classifiers":[
        {
            "category":"Organizations",
            "subcategory":"Religious Organization",
            "type":"Services"
        }
    ],
    "sg:phone":"+1 281 470 2366",
    "sg:postcode":"77571",
    "sg:province":"TX",
    "sg:tags":[
        "church"
    ],
    "wof:name":"Glory Ministries",
    "wof:placetype":"venue"
},
  "geometry": {"coordinates":[-95.023613,29.664995],"type":"Point"}
}