{
  "type": "Feature",
  "properties": {
    "iso:country":"US",
    "sg:address":"7317 Potters Trl",
    "sg:city":"Austin",
    "sg:classifiers":[
        {
            "category":"Professional",
            "subcategory":"Business Services",
            "type":"Services"
        }
    ],
    "sg:phone":"+1 512 323 5316",
    "sg:postcode":"78729",
    "sg:province":"TX",
    "wof:name":"Masthead Funding Group",
    "wof:placetype":"venue"
},
  "geometry": {"coordinates":[-97.75830000000001,30.443413],"type":"Point"}
}