{
  "type": "Feature",
  "properties": {
    "iso:country":"US",
    "sg:address":"216 Shelley Dr",
    "sg:city":"Tyler",
    "sg:classifiers":[
        {
            "category":"Real Estate",
            "subcategory":"Real Estate Agent",
            "type":"Services"
        }
    ],
    "sg:phone":"+1 903 581 8716",
    "sg:postcode":"75701",
    "sg:province":"TX",
    "wof:name":"Copeland Woods",
    "wof:placetype":"venue"
},
  "geometry": {"coordinates":[-95.303876,32.304393],"type":"Point"}
}