{
  "type": "Feature",
  "properties": {
    "iso:country":"US",
    "sg:address":"5029 Norfolk Dr",
    "sg:city":"Plano",
    "sg:classifiers":[
        {
            "category":"Real Estate",
            "subcategory":"Architect",
            "type":"Services"
        }
    ],
    "sg:phone":"+1 972 516 1154",
    "sg:postcode":"75023",
    "sg:province":"TX",
    "sg:tags":[
        "architectural"
    ],
    "wof:name":"Allen Assoc",
    "wof:placetype":"venue"
},
  "geometry": {"coordinates":[-96.726274,33.054634],"type":"Point"}
}