{
  "type": "Feature",
  "properties": {
    "iso:country":"US",
    "sg:address":"10530 Montwood Dr",
    "sg:city":"El Paso",
    "sg:classifiers":[
        {
            "category":"Wholesale",
            "subcategory":"Vending Machines",
            "type":"Manufacturing & Wholesale Goods"
        }
    ],
    "sg:phone":"+1 915 593 0808",
    "sg:postcode":"79935",
    "sg:province":"TX",
    "sg:tags":[
        "operator"
    ],
    "wof:name":"Central Vending",
    "wof:placetype":"venue"
},
  "geometry": {"coordinates":[-106.33598499999999,31.771947],"type":"Point"}
}