{
  "type": "Feature",
  "properties": {
    "iso:country":"US",
    "sg:address":"101 Sweet Pea Ct",
    "sg:city":"Mount Pleasant",
    "sg:classifiers":[
        {
            "category":"Organizations",
            "subcategory":"Religious Organization",
            "type":"Services"
        }
    ],
    "sg:phone":"+1 903 577 8622",
    "sg:postcode":"75455",
    "sg:province":"TX",
    "wof:name":"Franklin St Church of Ch",
    "wof:placetype":"venue"
},
  "geometry": {"coordinates":[-94.964579,33.185491],"type":"Point"}
}