{
  "type": "Feature",
  "properties": {
    "iso:country":"US",
    "sg:address":"3902 Heights Way",
    "sg:city":"San Antonio",
    "sg:classifiers":[
        {
            "category":"Professional",
            "subcategory":"Management & Consulting",
            "type":"Services"
        }
    ],
    "sg:phone":"+1 210 408 7508",
    "sg:postcode":"78230",
    "sg:province":"TX",
    "sg:tags":[
        "consultant",
        "energy",
        "conservation"
    ],
    "wof:name":"Inter-Tech Energy Progress Inc",
    "wof:placetype":"venue"
},
  "geometry": {"coordinates":[-98.56291899999999,29.565331],"type":"Point"}
}