{
  "type": "Feature",
  "properties": {
    "iso:country":"US",
    "sg:address":"3146 5th St",
    "sg:city":"Wichita Falls",
    "sg:classifiers":[
        {
            "category":"Banks & Credit Unions",
            "subcategory":"Bank",
            "type":"Services"
        }
    ],
    "sg:phone":"+1 940 322 1771",
    "sg:postcode":"76301",
    "sg:province":"TX",
    "sg:tags":[
        "institution",
        "business"
    ],
    "wof:name":"Sun Loan Company",
    "wof:placetype":"venue"
},
  "geometry": {"coordinates":[-98.525357,33.90978],"type":"Point"}
}