{
  "type": "Feature",
  "properties": {
    "iso:country":"US",
    "sg:address":"6006 Samual Bluff Ct",
    "sg:city":"Sugar Land",
    "sg:classifiers":[
        {
            "category":"Shopping",
            "subcategory":"Pharmacy",
            "type":"Retail Goods"
        }
    ],
    "sg:phone":"+1 281 565 0626",
    "sg:postcode":"77479",
    "sg:province":"TX",
    "wof:name":"Amex Pharmacy No 2 Inc",
    "wof:placetype":"venue"
},
  "geometry": {"coordinates":[-95.66866899999999,29.599152],"type":"Point"}
}