{
  "type": "Feature",
  "properties": {
    "iso:country":"US",
    "sg:address":"14570 Forum Pkwy",
    "sg:city":"Schertz",
    "sg:classifiers":[
        {
            "category":"Restaurant",
            "type":"Food & Drink"
        }
    ],
    "sg:menulink":"http://www.allmenus.com/tx/san-antonio/114970-chilis/menu/",
    "sg:phone":"+1 210 566 4584",
    "sg:postcode":"78154",
    "sg:province":"TX",
    "sg:tags":[
        "burger",
        "american",
        "sandwich",
        "tex-mex",
        "soup"
    ],
    "wof:name":"Chili's",
    "wof:placetype":"venue"
},
  "geometry": {"coordinates":[-98.326729,29.572354],"type":"Point"}
}