{
  "type": "Feature",
  "properties": {
    "iso:country":"US",
    "sg:address":"1940 Schilder Dr",
    "sg:city":"Houston",
    "sg:classifiers":[
        {
            "category":"Building & Trades",
            "subcategory":"Construction",
            "type":"Services"
        }
    ],
    "sg:phone":"+1 281 799 1742",
    "sg:postcode":"77093",
    "sg:province":"TX",
    "sg:tags":[
        "house",
        "leveling"
    ],
    "wof:name":"Affordable Foundation Repair",
    "wof:placetype":"venue"
},
  "geometry": {"coordinates":[-95.35503799999999,29.855232],"type":"Point"}
}