{
  "type": "Feature",
  "properties": {
    "iso:country":"US",
    "sg:address":"3413 Canal St",
    "sg:city":"Houston",
    "sg:classifiers":[
        {
            "category":"Health Services",
            "subcategory":"Doctor",
            "type":"Services"
        }
    ],
    "sg:phone":"+1 713 224 8131",
    "sg:postcode":"77003",
    "sg:province":"TX",
    "sg:tags":[
        "clinic"
    ],
    "wof:name":"Clinica Guadalupe",
    "wof:placetype":"venue"
},
  "geometry": {"coordinates":[-95.337107,29.752281],"type":"Point"}
}