{
  "type": "Feature",
  "properties": {
    "iso:country":"US",
    "sg:address":"12950 Royal Dr",
    "sg:city":"Stafford",
    "sg:classifiers":[
        {
            "category":"Manufacturing",
            "subcategory":"Metals",
            "type":"Manufacturing & Wholesale Goods"
        }
    ],
    "sg:phone":"+1 281 261 5700",
    "sg:postcode":"77477",
    "sg:province":"TX",
    "sg:tags":[
        "valve"
    ],
    "sg:website":"www.cookmanley.com",
    "wof:name":"Cook Manley",
    "wof:placetype":"venue"
},
  "geometry": {"coordinates":[-95.578577,29.633229],"type":"Point"}
}