{
  "type": "Feature",
  "properties": {
    "iso:country":"US",
    "sg:address":"12233 Ranch Road 620 N",
    "sg:city":"Austin",
    "sg:classifiers":[
        {
            "category":"Restaurant",
            "type":"Food & Drink"
        }
    ],
    "sg:phone":"+1 512 918 9464",
    "sg:postcode":"78750",
    "sg:province":"TX",
    "wof:name":"Rc Fowlers",
    "wof:placetype":"venue"
},
  "geometry": {"coordinates":[-97.81553599999999,30.462296],"type":"Point"}
}