{
  "type": "Feature",
  "properties": {
    "iso:country":"US",
    "sg:address":"4508 Cliffstone Cove",
    "sg:city":"Austin",
    "sg:classifiers":[
        {
            "category":"Professional",
            "type":"Services"
        }
    ],
    "sg:phone":"+1 512 892 2713",
    "sg:postcode":"78735",
    "sg:province":"TX",
    "wof:name":"Atkins Hanschen Inc",
    "wof:placetype":"venue"
},
  "geometry": {"coordinates":[-97.823937,30.243463],"type":"Point"}
}