{
  "type": "Feature",
  "properties": {
    "iso:country":"US",
    "sg:address":"1116 Hedgecoke Dr",
    "sg:city":"Borger",
    "sg:classifiers":[
        {
            "category":"Professional",
            "subcategory":"Detective & Security Services",
            "type":"Services"
        }
    ],
    "sg:phone":"+1 806 382 2557",
    "sg:postcode":"79007",
    "sg:province":"TX",
    "sg:tags":[
        "information",
        "bureau"
    ],
    "wof:name":"Stevens Electrical Service",
    "wof:placetype":"venue"
},
  "geometry": {"coordinates":[-101.392021,35.6577],"type":"Point"}
}