{
  "type": "Feature",
  "properties": {
    "iso:country":"US",
    "sg:address":"3721 Winifred Dr",
    "sg:city":"Fort Worth",
    "sg:classifiers":[
        {
            "category":"Organizations",
            "subcategory":"Professional Association",
            "type":"Services"
        }
    ],
    "sg:phone":"+1 817 292 1320",
    "sg:postcode":"76133",
    "sg:province":"TX",
    "sg:tags":[
        "business"
    ],
    "wof:name":"Fort Worth Mrtg Bankers Assn",
    "wof:placetype":"venue"
},
  "geometry": {"coordinates":[-97.373479,32.66544],"type":"Point"}
}