{
  "type": "Feature",
  "properties": {
    "iso:country":"US",
    "sg:address":"7821 Rankin Rd",
    "sg:city":"Humble",
    "sg:classifiers":[
        {
            "category":"Retail",
            "subcategory":"Auto Repair",
            "type":"Services"
        }
    ],
    "sg:phone":"+1 281 987 8697",
    "sg:postcode":"77396",
    "sg:province":"TX",
    "sg:tags":[
        "wrecker"
    ],
    "wof:name":"Atascocita Wrecker Svc",
    "wof:placetype":"venue"
},
  "geometry": {"coordinates":[-95.269974,29.965234],"type":"Point"}
}