{
  "type": "Feature",
  "properties": {
    "iso:country":"US",
    "sg:address":"101 W Main St",
    "sg:city":"Crosbyton",
    "sg:classifiers":[
        {
            "category":"Organizations",
            "subcategory":"Community Association",
            "type":"Services"
        }
    ],
    "sg:phone":"+1 806 675 2331",
    "sg:postcode":"79322",
    "sg:province":"TX",
    "sg:tags":[
        "gallery"
    ],
    "wof:name":"Museum",
    "wof:placetype":"venue"
},
  "geometry": {"coordinates":[-101.239351,33.659991],"type":"Point"}
}