{
  "type": "Feature",
  "properties": {
    "iso:country":"US",
    "sg:address":"7612 W Hwy 71",
    "sg:city":"Austin",
    "sg:classifiers":[
        {
            "category":"Professional",
            "subcategory":"Accounting & Tax Preparation",
            "type":"Services"
        }
    ],
    "sg:phone":"+1 512 288 0434",
    "sg:postcode":"78735",
    "sg:province":"TX",
    "sg:tags":[
        "accountant"
    ],
    "wof:name":"John Wyatt & Assoc",
    "wof:placetype":"venue"
},
  "geometry": {"coordinates":[-97.88178600000001,30.24173],"type":"Point"}
}