{
  "type": "Feature",
  "properties": {
    "iso:country":"US",
    "sg:address":"6298 Madison Blvd",
    "sg:city":"Groves",
    "sg:classifiers":[
        {
            "category":"Farming",
            "subcategory":"Fish & Marine Products",
            "type":"Manufacturing & Wholesale Goods"
        }
    ],
    "sg:phone":"+1 409 963 0991",
    "sg:postcode":"77619",
    "sg:province":"TX",
    "sg:tags":[
        "shellfish",
        "fishing"
    ],
    "wof:name":"Harrington",
    "wof:placetype":"venue"
},
  "geometry": {"coordinates":[-93.92366800000001,29.949959],"type":"Point"}
}