{
  "type": "Feature",
  "properties": {
    "iso:country":"US",
    "sg:address":"3838 Oak Lawn Ave",
    "sg:city":"Dallas",
    "sg:classifiers":[
        {
            "category":"Professional",
            "subcategory":"Lawyer & Legal Services",
            "type":"Services"
        }
    ],
    "sg:phone":"+1 214 520 1920",
    "sg:postcode":"75219",
    "sg:province":"TX",
    "wof:name":"Bonney Saml R Atty",
    "wof:placetype":"venue"
},
  "geometry": {"coordinates":[-96.802299,32.815201],"type":"Point"}
}