{
  "type": "Feature",
  "properties": {
    "iso:country":"US",
    "sg:address":"4665 Garth Rd",
    "sg:city":"Baytown",
    "sg:classifiers":[
        {
            "category":"Health Services",
            "subcategory":"Doctor",
            "type":"Services"
        }
    ],
    "sg:phone":"+1 713 662 0152",
    "sg:postcode":"77521",
    "sg:province":"TX",
    "sg:tags":[
        "physician",
        "surgeon",
        "kidneys",
        "surgeons",
        "nephrology"
    ],
    "wof:name":"Nephrology And Hypertension Specialists Pa",
    "wof:placetype":"venue"
},
  "geometry": {"coordinates":[-94.97771400000001,29.774756],"type":"Point"}
}