{
  "type": "Feature",
  "properties": {
    "iso:country":"US",
    "sg:address":"16610 San Pedro Ave",
    "sg:city":"San Antonio",
    "sg:classifiers":[
        {
            "category":"Personal",
            "subcategory":"Beauty Salon",
            "type":"Services"
        }
    ],
    "sg:phone":"+1 210 494 8838",
    "sg:postcode":"78232",
    "sg:province":"TX",
    "sg:tags":[
        "shop"
    ],
    "wof:name":"La Nails",
    "wof:placetype":"venue"
},
  "geometry": {"coordinates":[-98.473321,29.592794],"type":"Point"}
}