{
  "type": "Feature",
  "properties": {
    "iso:country":"US",
    "sg:address":"1201 E Washington St",
    "sg:city":"Brownsville",
    "sg:classifiers":[
        {
            "category":"Shopping",
            "subcategory":"Discount & Variety Stores",
            "type":"Retail Goods"
        }
    ],
    "sg:phone":"+1 956 546 5630",
    "sg:postcode":"78520",
    "sg:province":"TX",
    "wof:name":"Eliz Dollar PLU",
    "wof:placetype":"venue"
},
  "geometry": {"coordinates":[-97.49661999999999,25.900919],"type":"Point"}
}