{
  "type": "Feature",
  "properties": {
    "iso:country":"US",
    "sg:address":"4300 Forney Rd",
    "sg:city":"Mesquite",
    "sg:classifiers":[
        {
            "category":"Banks & Credit Unions",
            "subcategory":"Investment Brokerage",
            "type":"Services"
        }
    ],
    "sg:phone":"+1 214 388 0863",
    "sg:postcode":"75149",
    "sg:province":"TX",
    "wof:name":"P C Investments",
    "wof:placetype":"venue"
},
  "geometry": {"coordinates":[-96.658351,32.783425],"type":"Point"}
}