{
  "type": "Feature",
  "properties": {
    "iso:country":"US",
    "sg:address":"5445 Co Rd 5710",
    "sg:city":"Devine",
    "sg:classifiers":[
        {
            "category":"Museum",
            "type":"Entertainment"
        }
    ],
    "sg:phone":"+1 830 931 3837",
    "sg:postcode":"78016",
    "sg:province":"TX",
    "sg:tags":[
        "gallery"
    ],
    "wof:name":"Shooting Star Museum & Co",
    "wof:placetype":"venue"
},
  "geometry": {"coordinates":[-98.922178,29.262257],"type":"Point"}
}