{
  "type": "Feature",
  "properties": {
    "iso:country":"US",
    "sg:address":"225 N 7th St",
    "sg:city":"Abilene",
    "sg:classifiers":[
        {
            "category":"Professional",
            "type":"Services"
        }
    ],
    "sg:phone":"+1 325 672 9921",
    "sg:postcode":"79601",
    "sg:province":"TX",
    "wof:name":"Starfire Performance",
    "wof:placetype":"venue"
},
  "geometry": {"coordinates":[-99.72353699999999,32.454965],"type":"Point"}
}