{
  "type": "Feature",
  "properties": {
    "iso:country":"US",
    "sg:address":"3401 Dever Dr",
    "sg:city":"Waco",
    "sg:classifiers":[
        {
            "category":"Professional",
            "subcategory":"Management & Consulting",
            "type":"Services"
        }
    ],
    "sg:phone":"+1 254 755 8100",
    "sg:postcode":"76708",
    "sg:province":"TX",
    "sg:tags":[
        "consultant",
        "business"
    ],
    "wof:name":"Carden Group",
    "wof:placetype":"venue"
},
  "geometry": {"coordinates":[-97.186105,31.566932],"type":"Point"}
}