{
  "type": "Feature",
  "properties": {
    "iso:country":"US",
    "sg:address":"16116 College Oak Dr",
    "sg:city":"San Antonio",
    "sg:classifiers":[
        {
            "category":"Wholesale",
            "subcategory":"Chemicals & Plastics",
            "type":"Manufacturing & Wholesale Goods"
        }
    ],
    "sg:phone":"+1 210 432 0202",
    "sg:postcode":"78249",
    "sg:province":"TX",
    "sg:tags":[
        "oxygen"
    ],
    "wof:name":"Lifegas Limited",
    "wof:placetype":"venue"
},
  "geometry": {"coordinates":[-98.579617,29.588412],"type":"Point"}
}