{
  "type": "Feature",
  "properties": {
    "iso:country":"US",
    "sg:address":"504 S 5th St",
    "sg:city":"Conroe",
    "sg:classifiers":[
        {
            "category":"Real Estate",
            "subcategory":"Developer",
            "type":"Services"
        }
    ],
    "sg:phone":"+1 936 689 0782",
    "sg:postcode":"77301",
    "sg:province":"TX",
    "sg:tags":[
        "cemetery"
    ],
    "wof:name":"Imperial Cemetery Service",
    "wof:placetype":"venue"
},
  "geometry": {"coordinates":[-95.447197,30.308294],"type":"Point"}
}