{
  "type": "Feature",
  "properties": {
    "iso:country":"US",
    "sg:address":"4420 N Mesa St",
    "sg:city":"El Paso",
    "sg:classifiers":[
        {
            "category":"Freight",
            "type":"Transportation"
        }
    ],
    "sg:phone":"+1 915 351 6704",
    "sg:postcode":"79902",
    "sg:province":"TX",
    "sg:tags":[
        "operator",
        "local",
        "trucking"
    ],
    "wof:name":"Superior Trucking Services",
    "wof:placetype":"venue"
},
  "geometry": {"coordinates":[-106.51038200000001,31.800047],"type":"Point"}
}