{
  "type": "Feature",
  "properties": {
    "iso:country":"US",
    "sg:address":"608 W 6th St",
    "sg:city":"Post",
    "sg:classifiers":[
        {
            "category":"Local Transit",
            "type":"Transportation"
        }
    ],
    "sg:phone":"+1 806 495 1195",
    "sg:postcode":"79356",
    "sg:province":"TX",
    "sg:tags":[
        "passenger"
    ],
    "wof:name":"Ambulance Department",
    "wof:placetype":"venue"
},
  "geometry": {"coordinates":[-101.38485799999999,33.187125],"type":"Point"}
}