{
  "type": "Feature",
  "properties": {
    "iso:country":"US",
    "sg:address":"11709 Boulder Ln",
    "sg:city":"Austin",
    "sg:classifiers":[
        {
            "category":"Organizations",
            "subcategory":"Religious Organization",
            "type":"Services"
        },
        {
            "category":"Banks & Credit Unions",
            "subcategory":"Financial Services",
            "type":"Services"
        }
    ],
    "sg:phone":"+1 512 331 9971",
    "sg:postcode":"78726",
    "sg:province":"TX",
    "sg:tags":[
        "trust",
        "nonprofit",
        "management"
    ],
    "sg:website":"www.tmf-fdn.org",
    "wof:name":"Texas Methodist Foundation",
    "wof:placetype":"venue"
},
  "geometry": {"coordinates":[-97.832094,30.442932],"type":"Point"}
}