{
  "type": "Feature",
  "properties": {
    "iso:country":"US",
    "sg:address":"702 Park St",
    "sg:city":"Commerce",
    "sg:classifiers":[
        {
            "category":"Food & Beverages",
            "subcategory":"Groceries & Convenience Stores",
            "type":"Retail Goods"
        }
    ],
    "sg:phone":"+1 903 886 8373",
    "sg:postcode":"75428",
    "sg:province":"TX",
    "wof:name":"909 Mark",
    "wof:placetype":"venue"
},
  "geometry": {"coordinates":[-95.898027,33.255444],"type":"Point"}
}