{
  "type": "Feature",
  "properties": {
    "iso:country":"US",
    "sg:address":"13719 Wilderness Creek Dr",
    "sg:city":"San Antonio",
    "sg:classifiers":[
        {
            "category":"Professional",
            "subcategory":"Business Services",
            "type":"Services"
        }
    ],
    "sg:phone":"+1 210 408 6519",
    "sg:postcode":"78231",
    "sg:province":"TX",
    "wof:name":"Ics Sales",
    "wof:placetype":"venue"
},
  "geometry": {"coordinates":[-98.53100999999999,29.572517],"type":"Point"}
}