{
  "type": "Feature",
  "properties": {
    "iso:country":"US",
    "sg:address":"407 J St",
    "sg:city":"San Antonio",
    "sg:classifiers":[
        {
            "category":"Building & Trades",
            "subcategory":"Construction",
            "type":"Services"
        }
    ],
    "sg:phone":"+1 210 337 1606",
    "sg:postcode":"78220",
    "sg:province":"TX",
    "sg:tags":[
        "steam",
        "cleaning"
    ],
    "wof:name":"Cisneros Water Blasting Svc",
    "wof:placetype":"venue"
},
  "geometry": {"coordinates":[-98.44275,29.404534],"type":"Point"}
}