{
  "type": "Feature",
  "properties": {
    "iso:country":"US",
    "sg:address":"925 Northwood St",
    "sg:city":"Baytown",
    "sg:classifiers":[
        {
            "category":"Real Estate",
            "subcategory":"Real Estate Operator",
            "type":"Services"
        }
    ],
    "sg:phone":"+1 281 428 1322",
    "sg:postcode":"77521",
    "sg:province":"TX",
    "sg:tags":[
        "apartment",
        "complex"
    ],
    "wof:name":"Avalon Bay Apartment Homes",
    "wof:placetype":"venue"
},
  "geometry": {"coordinates":[-94.983756,29.756009],"type":"Point"}
}