{
  "type": "Feature",
  "properties": {
    "iso:country":"US",
    "sg:address":"802 Farmers Rd",
    "sg:city":"Brenham",
    "sg:classifiers":[
        {
            "category":"Travel",
            "subcategory":"Campground",
            "type":"Entertainment"
        }
    ],
    "sg:phone":"+1 979 836 0887",
    "sg:postcode":"77833",
    "sg:province":"TX",
    "sg:tags":[
        "camp"
    ],
    "wof:name":"Alma House",
    "wof:placetype":"venue"
},
  "geometry": {"coordinates":[-96.425589,30.155488],"type":"Point"}
}