{
  "type": "Feature",
  "properties": {
    "iso:country":"US",
    "sg:address":"17060 Dallas Pkwy Ste 101",
    "sg:city":"Dallas",
    "sg:classifiers":[
        {
            "category":"Professional",
            "subcategory":"Lawyer & Legal Services",
            "type":"Services"
        }
    ],
    "sg:phone":"+1 877 843 7331",
    "sg:postcode":"75248",
    "sg:province":"TX",
    "sg:website":"www.yourcommunity.com",
    "wof:name":"YOUR COMMUNITY PHONEBOOK",
    "wof:placetype":"venue"
},
  "geometry": {"coordinates":[-96.828098,32.980129],"type":"Point"}
}