{
  "type": "Feature",
  "properties": {
    "iso:country":"US",
    "sg:address":"3108 W 6th St",
    "sg:city":"Fort Worth",
    "sg:classifiers":[
        {
            "category":"Real Estate",
            "subcategory":"Developer",
            "type":"Services"
        }
    ],
    "sg:phone":"+1 817 335 7955",
    "sg:postcode":"76107",
    "sg:province":"TX",
    "wof:name":"Andy Edwards Investments",
    "wof:placetype":"venue"
},
  "geometry": {"coordinates":[-97.361976,32.752231],"type":"Point"}
}