{
  "type": "Feature",
  "properties": {
    "iso:country":"US",
    "sg:address":"2665 Perth St",
    "sg:city":"Dallas",
    "sg:classifiers":[
        {
            "category":"Manufacturing",
            "subcategory":"Furniture",
            "type":"Manufacturing & Wholesale Goods"
        },
        {
            "category":"Manufacturing",
            "subcategory":"Building Materials",
            "type":"Manufacturing & Wholesale Goods"
        }
    ],
    "sg:phone":"+1 214 358 1770",
    "sg:postcode":"75220",
    "sg:province":"TX",
    "sg:tags":[
        "mfg",
        "wood",
        "lu",
        "kitchen",
        "cabinet"
    ],
    "wof:name":"Metroplex Millworks Inc",
    "wof:placetype":"venue"
},
  "geometry": {"coordinates":[-96.886556,32.877159],"type":"Point"}
}