{
  "type": "Feature",
  "properties": {
    "iso:country":"US",
    "sg:address":"605 S Main St",
    "sg:city":"Kemp",
    "sg:classifiers":[
        {
            "category":"Place Of Worship",
            "subcategory":"Church",
            "type":"Public Place"
        },
        {
            "category":"Place Of Worship",
            "type":"Public Place"
        }
    ],
    "sg:phone":"+1 903 498 8651",
    "sg:postcode":"75143",
    "sg:province":"TX",
    "sg:tags":[
        "testament",
        "christ-new",
        "churches-church",
        "christ"
    ],
    "wof:name":"Kemp Church Of Christ",
    "wof:placetype":"venue"
},
  "geometry": {"coordinates":[-96.229585,32.439083],"type":"Point"}
}