{
  "type": "Feature",
  "properties": {
    "iso:country":"US",
    "sg:address":"110 N Bynum St",
    "sg:city":"Lufkin",
    "sg:classifiers":[
        {
            "category":"Health Services",
            "subcategory":"Doctor",
            "type":"Services"
        }
    ],
    "sg:phone":"+1 936 632 1250",
    "sg:postcode":"75904",
    "sg:province":"TX",
    "sg:tags":[
        "medical"
    ],
    "wof:name":"Angelina County Cities Health",
    "wof:placetype":"venue"
},
  "geometry": {"coordinates":[-94.739064,31.337319],"type":"Point"}
}