{
  "type": "Feature",
  "properties": {
    "iso:country":"US",
    "sg:address":"5615 Rachel Ct",
    "sg:city":"Arlington",
    "sg:classifiers":[
        {
            "category":"Professional",
            "subcategory":"Computer Services",
            "type":"Services"
        }
    ],
    "sg:phone":"+1 817 483 5836",
    "sg:postcode":"76017",
    "sg:province":"TX",
    "sg:tags":[
        "related"
    ],
    "wof:name":"Micro Age",
    "wof:placetype":"venue"
},
  "geometry": {"coordinates":[-97.159584,32.65555],"type":"Point"}
}