{
  "type": "Feature",
  "properties": {
    "iso:country":"US",
    "sg:address":"14000 Renaissance Ct",
    "sg:city":"Austin",
    "sg:classifiers":[
        {
            "category":"Professional",
            "subcategory":"Computer Services",
            "type":"Services"
        }
    ],
    "sg:phone":"+1 512 432 8971",
    "sg:postcode":"78728",
    "sg:province":"TX",
    "sg:tags":[
        "programing",
        "custom"
    ],
    "wof:name":"Compaq Computers",
    "wof:placetype":"venue"
},
  "geometry": {"coordinates":[-97.685581,30.436262],"type":"Point"}
}