{
  "type": "Feature",
  "properties": {
    "iso:country":"US",
    "sg:address":"9020 Jones Rd",
    "sg:city":"Houston",
    "sg:classifiers":[
        {
            "category":"Retail",
            "subcategory":"Car Wash",
            "type":"Services"
        }
    ],
    "sg:phone":"+1 281 469 6233",
    "sg:postcode":"77065",
    "sg:province":"TX",
    "sg:tags":[
        "carwash"
    ],
    "wof:name":"Laserwash",
    "wof:placetype":"venue"
},
  "geometry": {"coordinates":[-95.58444299999999,29.903604],"type":"Point"}
}