{
  "type": "Feature",
  "properties": {
    "iso:country":"US",
    "sg:address":"206 N C M Allen Pkwy",
    "sg:city":"San Marcos",
    "sg:classifiers":[
        {
            "category":"Professional",
            "type":"Services"
        }
    ],
    "sg:phone":"+1 512 393 8423",
    "sg:postcode":"78666",
    "sg:province":"TX",
    "sg:tags":[
        "establishment"
    ],
    "wof:name":"Old Fish Hatchery Comm Bldg",
    "wof:placetype":"venue"
},
  "geometry": {"coordinates":[-97.93726599999999,29.884618],"type":"Point"}
}