{
  "type": "Feature",
  "properties": {
    "iso:country":"US",
    "sg:address":"1005 Forest Ave",
    "sg:city":"Dallas",
    "sg:classifiers":[
        {
            "category":"Building & Trades",
            "subcategory":"Construction",
            "type":"Services"
        }
    ],
    "sg:phone":"+1 214 428 1989",
    "sg:postcode":"75215",
    "sg:province":"TX",
    "sg:tags":[
        "concrete",
        "contractor"
    ],
    "wof:name":"Image Concrete",
    "wof:placetype":"venue"
},
  "geometry": {"coordinates":[-96.781226,32.758173],"type":"Point"}
}