{
  "type": "Feature",
  "properties": {
    "iso:country":"US",
    "sg:address":"509 N Bishop Ave",
    "sg:city":"Dallas",
    "sg:classifiers":[
        {
            "category":"Shopping",
            "subcategory":"Clothing, Apparel, & Fashions",
            "type":"Retail Goods"
        }
    ],
    "sg:phone":"+1 214 948 9219",
    "sg:postcode":"75208",
    "sg:province":"TX",
    "sg:tags":[
        "item",
        "boutique"
    ],
    "wof:name":"Eleshion Boutique",
    "wof:placetype":"venue"
},
  "geometry": {"coordinates":[-96.828377,32.749405],"type":"Point"}
}