{
  "type": "Feature",
  "properties": {
    "iso:country":"US",
    "sg:address":"6301 E Lancaster Ave",
    "sg:city":"Fort Worth",
    "sg:classifiers":[
        {
            "category":"Wholesale",
            "subcategory":"Machinery & Supplies",
            "type":"Manufacturing & Wholesale Goods"
        }
    ],
    "sg:phone":"+1 817 451 6000",
    "sg:postcode":"76112",
    "sg:province":"TX",
    "wof:name":"Wickham Supply",
    "wof:placetype":"venue"
},
  "geometry": {"coordinates":[-97.22135299999999,32.733423],"type":"Point"}
}