{
  "type": "Feature",
  "properties": {
    "iso:country":"US",
    "sg:address":"9104 Diplomacy Row",
    "sg:city":"Dallas",
    "sg:classifiers":[
        {
            "category":"Manufacturing",
            "subcategory":"Tools & Machinery",
            "type":"Manufacturing & Wholesale Goods"
        }
    ],
    "sg:phone":"+1 214 637 2763",
    "sg:postcode":"75247",
    "sg:province":"TX",
    "sg:tags":[
        "control",
        "time",
        "access",
        "clocks",
        "mechanical",
        "parking"
    ],
    "wof:name":"Associated Time & Prkg Contrls",
    "wof:placetype":"venue"
},
  "geometry": {"coordinates":[-96.89534999999999,32.819485],"type":"Point"}
}