{
  "type": "Feature",
  "properties": {
    "iso:country":"US",
    "sg:address":"6359 Jonquil St",
    "sg:city":"Fort Worth",
    "sg:classifiers":[
        {
            "category":"Social Services",
            "subcategory":"Child Care",
            "type":"Services"
        }
    ],
    "sg:phone":"+1 817 361 1504",
    "sg:postcode":"76133",
    "sg:province":"TX",
    "wof:name":"Demetric's Daycare",
    "wof:placetype":"venue"
},
  "geometry": {"coordinates":[-97.37318999999999,32.651312],"type":"Point"}
}