{
  "type": "Feature",
  "properties": {
    "iso:country":"US",
    "sg:address":"1906 Wood Crest Cir",
    "sg:city":"Grapevine",
    "sg:classifiers":[
        {
            "category":"Professional",
            "subcategory":"Business Services",
            "type":"Services"
        }
    ],
    "sg:phone":"+1 817 488 1758",
    "sg:postcode":"76051",
    "sg:province":"TX",
    "wof:name":"Romar Group Inc",
    "wof:placetype":"venue"
},
  "geometry": {"coordinates":[-97.104502,32.915058],"type":"Point"}
}