{
  "type": "Feature",
  "properties": {
    "iso:country":"US",
    "sg:address":"3415 S Collins St",
    "sg:city":"Arlington",
    "sg:classifiers":[
        {
            "category":"Personal",
            "subcategory":"Beauty Salon",
            "type":"Services"
        }
    ],
    "sg:phone":"+1 817 557 9117",
    "sg:postcode":"76014",
    "sg:province":"TX",
    "wof:name":"Salon Stations Co LLC",
    "wof:placetype":"venue"
},
  "geometry": {"coordinates":[-97.09646499999999,32.688839],"type":"Point"}
}