{
  "type": "Feature",
  "properties": {
    "iso:country":"US",
    "sg:address":"1229 Corporate Dr",
    "sg:city":"Rosenberg",
    "sg:classifiers":[
        {
            "category":"Health Services",
            "subcategory":"Doctor",
            "type":"Services"
        }
    ],
    "sg:phone":"+1 281 342 1126",
    "sg:postcode":"77471",
    "sg:province":"TX",
    "sg:tags":[
        "physician",
        "family",
        "practice",
        "surgeons",
        "medicine",
        "surgeon"
    ],
    "wof:name":"Vaughns Family Ctr",
    "wof:placetype":"venue"
},
  "geometry": {"coordinates":[-95.77593899999999,29.562163],"type":"Point"}
}