{
  "type": "Feature",
  "properties": {
    "iso:country":"US",
    "sg:address":"1013 N 8th St",
    "sg:city":"Killeen",
    "sg:classifiers":[
        {
            "category":"Restaurant",
            "type":"Food & Drink"
        }
    ],
    "sg:phone":"+1 254 526 6999",
    "sg:postcode":"76541",
    "sg:province":"TX",
    "sg:tags":[
        "eating"
    ],
    "wof:name":"A Geckos Pizza",
    "wof:placetype":"venue"
},
  "geometry": {"coordinates":[-97.724707,31.126232],"type":"Point"}
}