{
  "type": "Feature",
  "properties": {
    "iso:country":"US",
    "sg:address":"7033 Greenville Ave",
    "sg:city":"Dallas",
    "sg:classifiers":[
        {
            "category":"Health Services",
            "subcategory":"Dentist",
            "type":"Services"
        }
    ],
    "sg:phone":"+1 214 750 7775",
    "sg:postcode":"75231",
    "sg:province":"TX",
    "wof:name":"Daily Smiles PC",
    "wof:placetype":"venue"
},
  "geometry": {"coordinates":[-96.762839,32.874375],"type":"Point"}
}