{
  "type": "Feature",
  "properties": {
    "iso:country":"US",
    "sg:address":"2800 Carriage Ln",
    "sg:city":"Carrollton",
    "sg:classifiers":[
        {
            "category":"Cinema",
            "subcategory":"Movie Rental",
            "type":"Entertainment"
        }
    ],
    "sg:phone":"+1 972 418 7235",
    "sg:postcode":"75006",
    "sg:province":"TX",
    "sg:tags":[
        "game",
        "video"
    ],
    "wof:name":"Cll Video Services",
    "wof:placetype":"venue"
},
  "geometry": {"coordinates":[-96.859802,32.965],"type":"Point"}
}