{
  "type": "Feature",
  "properties": {
    "iso:country":"US",
    "sg:address":"9421 Burnet Rd # B",
    "sg:city":"Austin",
    "sg:classifiers":[
        {
            "category":"Arena",
            "subcategory":"Sports Club",
            "type":"Entertainment"
        }
    ],
    "sg:phone":"+1 512 837 5425",
    "sg:postcode":"78758",
    "sg:province":"TX",
    "sg:tags":[
        "martial art"
    ],
    "wof:name":"Ab Karate-America's Best Karate",
    "wof:placetype":"venue"
},
  "geometry": {"coordinates":[-97.72530399999999,30.378099],"type":"Point"}
}