{
  "type": "Feature",
  "properties": {
    "iso:country":"US",
    "sg:address":"4915 Saddleback Rd",
    "sg:city":"Arlington",
    "sg:classifiers":[
        {
            "category":"Professional",
            "subcategory":"Management & Consulting",
            "type":"Services"
        }
    ],
    "sg:phone":"+1 817 561 7074",
    "sg:postcode":"76017",
    "sg:province":"TX",
    "sg:tags":[
        "consultant",
        "medical",
        "legal"
    ],
    "wof:name":"Certified Legal Nurse Conslnt",
    "wof:placetype":"venue"
},
  "geometry": {"coordinates":[-97.18722,32.657],"type":"Point"}
}