{
  "type": "Feature",
  "properties": {
    "iso:country":"US",
    "sg:address":"15204 State Hwy 1604",
    "sg:city":"San Antonio",
    "sg:classifiers":[
        {
            "category":"Retail",
            "subcategory":"Auto Repair",
            "type":"Services"
        }
    ],
    "sg:phone":"+1 210 635 7350",
    "sg:postcode":"78223",
    "sg:province":"TX",
    "sg:tags":[
        "body",
        "automobile",
        "painting"
    ],
    "wof:name":"Preferred Auto & Truck",
    "wof:placetype":"venue"
},
  "geometry": {"coordinates":[-98.302172,29.270853],"type":"Point"}
}