{
  "type": "Feature",
  "properties": {
    "iso:country":"US",
    "sg:address":"12701 US Hwy 287P Bus",
    "sg:city":"Fort Worth",
    "sg:classifiers":[
        {
            "category":"Recreation",
            "type":"Entertainment"
        }
    ],
    "sg:phone":"+1 817 439 4091",
    "sg:postcode":"76179",
    "sg:province":"TX",
    "sg:tags":[
        "parlor",
        "billiard"
    ],
    "wof:name":"Fat Alberts",
    "wof:placetype":"venue"
},
  "geometry": {"coordinates":[-97.420824,32.946102],"type":"Point"}
}