{
  "type": "Feature",
  "properties": {
    "iso:country":"US",
    "sg:address":"2631 Wyoming Ave",
    "sg:city":"El Paso",
    "sg:classifiers":[
        {
            "category":"Retail",
            "subcategory":"Laundry & Dry Cleaning",
            "type":"Services"
        }
    ],
    "sg:phone":"+1 915 565 1407",
    "sg:postcode":"79903",
    "sg:province":"TX",
    "sg:tags":[
        "power"
    ],
    "wof:name":"Eagle Cleaners",
    "wof:placetype":"venue"
},
  "geometry": {"coordinates":[-106.46339500000001,31.779857],"type":"Point"}
}