{
  "type": "Feature",
  "properties": {
    "iso:country":"US",
    "sg:address":"3439 Maybeth St",
    "sg:city":"Dallas",
    "sg:classifiers":[
        {
            "category":"Food & Beverages",
            "subcategory":"Groceries & Convenience Stores",
            "type":"Retail Goods"
        }
    ],
    "sg:phone":"+1 214 879 0435",
    "sg:postcode":"75212",
    "sg:province":"TX",
    "wof:name":"R & J Grocery Store",
    "wof:placetype":"venue"
},
  "geometry": {"coordinates":[-96.903676,32.784372],"type":"Point"}
}