{
  "type": "Feature",
  "properties": {
    "iso:country":"US",
    "sg:address":"3715 Pageant Pl",
    "sg:city":"Dallas",
    "sg:classifiers":[
        {
            "category":"Real Estate",
            "subcategory":"Real Estate Agent",
            "type":"Services"
        }
    ],
    "sg:phone":"+1 972 620 1404",
    "sg:postcode":"75244",
    "sg:province":"TX",
    "wof:name":"Citimark Realty",
    "wof:placetype":"venue"
},
  "geometry": {"coordinates":[-96.85388,32.913888],"type":"Point"}
}