{
  "type": "Feature",
  "properties": {
    "iso:country":"US",
    "sg:address":"1110 18th St",
    "sg:city":"Hondo",
    "sg:classifiers":[
        {
            "category":"Shopping",
            "subcategory":"Computers & Home Electronics",
            "type":"Retail Goods"
        }
    ],
    "sg:phone":"+1 830 426 2662",
    "sg:postcode":"78861",
    "sg:province":"TX",
    "sg:tags":[
        "equipment",
        "electronic",
        "supply"
    ],
    "wof:name":"Radio Shack",
    "wof:placetype":"venue"
},
  "geometry": {"coordinates":[-99.14071199999999,29.348376],"type":"Point"}
}