{
  "type": "Feature",
  "properties": {
    "iso:country":"US",
    "sg:address":"517 Moran St",
    "sg:city":"Bryan",
    "sg:classifiers":[
        {
            "category":"Professional",
            "type":"Services"
        }
    ],
    "sg:phone":"+1 979 846 0040",
    "sg:postcode":"77801",
    "sg:province":"TX",
    "sg:tags":[
        "arts",
        "artist"
    ],
    "sg:website":"www.margitilikaart.com",
    "wof:name":"Margit Ilika Retailer",
    "wof:placetype":"venue"
},
  "geometry": {"coordinates":[-96.35134499999999,30.638537],"type":"Point"}
}