{
  "type": "Feature",
  "properties": {
    "iso:country":"US",
    "sg:address":"2901 N 10th St",
    "sg:city":"Mcallen",
    "sg:classifiers":[
        {
            "category":"Home & Garden",
            "subcategory":"Furniture",
            "type":"Retail Goods"
        }
    ],
    "sg:phone":"+1 956 682 5266",
    "sg:postcode":"78501",
    "sg:province":"TX",
    "wof:name":"Lacks",
    "wof:placetype":"venue"
},
  "geometry": {"coordinates":[-98.2256,26.229534],"type":"Point"}
}