{
  "type": "Feature",
  "properties": {
    "iso:country":"US",
    "sg:address":"8055 FM 359",
    "sg:city":"Fulshear",
    "sg:classifiers":[
        {
            "category":"Government",
            "subcategory":"Post Office",
            "type":"Public Place"
        }
    ],
    "sg:phone":"+1 281 533 9146",
    "sg:postcode":"77441",
    "sg:province":"TX",
    "wof:name":"US Post Office",
    "wof:placetype":"venue"
},
  "geometry": {"coordinates":[-95.903126,29.69812],"type":"Point"}
}