{
  "type": "Feature",
  "properties": {
    "iso:country":"US",
    "sg:address":"6420 Richmond Ave",
    "sg:city":"Houston",
    "sg:classifiers":[
        {
            "category":"Professional",
            "type":"Services"
        },
        {
            "category":"Real Estate",
            "subcategory":"Real Estate Operator",
            "type":"Services"
        }
    ],
    "sg:phone":"+1 713 782 4842",
    "sg:postcode":"77057",
    "sg:province":"TX",
    "sg:tags":[
        "apartment"
    ],
    "wof:name":"La Guia De Apartamentos",
    "wof:placetype":"venue"
},
  "geometry": {"coordinates":[-95.49894399999999,29.731778],"type":"Point"}
}