{
  "type": "Feature",
  "properties": {
    "iso:country":"US",
    "sg:address":"2406 Gravel Dr",
    "sg:city":"Fort Worth",
    "sg:classifiers":[
        {
            "category":"Shopping",
            "subcategory":"Computers & Home Electronics",
            "type":"Retail Goods"
        }
    ],
    "sg:phone":"+1 817 590 2400",
    "sg:postcode":"76118",
    "sg:province":"TX",
    "sg:tags":[
        "equipment",
        "video"
    ],
    "wof:name":"Texas Video Amusement Co",
    "wof:placetype":"venue"
},
  "geometry": {"coordinates":[-97.217302,32.793909],"type":"Point"}
}