{
  "type": "Feature",
  "properties": {
    "iso:country":"US",
    "sg:address":"110 N Bernice St",
    "sg:city":"Spearman",
    "sg:classifiers":[
        {
            "category":"Utilities",
            "subcategory":"Telephone",
            "type":"Services"
        }
    ],
    "sg:phone":"+1 806 659 1006",
    "sg:postcode":"79081",
    "sg:province":"TX",
    "sg:tags":[
        "telecommunication"
    ],
    "wof:name":"Valor Telecom",
    "wof:placetype":"venue"
},
  "geometry": {"coordinates":[-101.192196,36.199663],"type":"Point"}
}