{
  "type": "Feature",
  "properties": {
    "iso:country":"US",
    "sg:address":"13322 Glacier Falls Ct",
    "sg:city":"Austin",
    "sg:classifiers":[
        {
            "category":"Building & Trades",
            "subcategory":"Construction",
            "type":"Services"
        }
    ],
    "sg:phone":"+1 512 989 6591",
    "sg:postcode":"78727",
    "sg:province":"TX",
    "sg:tags":[
        "home",
        "builder"
    ],
    "wof:name":"Newmark Homes",
    "wof:placetype":"venue"
},
  "geometry": {"coordinates":[-97.683127,30.422967],"type":"Point"}
}