{
  "type": "Feature",
  "properties": {
    "iso:country":"US",
    "sg:address":"1063 Paige St",
    "sg:city":"Aubrey",
    "sg:classifiers":[
        {
            "category":"Building & Trades",
            "subcategory":"Electrical",
            "type":"Services"
        }
    ],
    "sg:phone":"+1 940 365 2116",
    "sg:postcode":"76227",
    "sg:province":"TX",
    "sg:tags":[
        "electrician"
    ],
    "wof:name":"Ecnotec Electric",
    "wof:placetype":"venue"
},
  "geometry": {"coordinates":[-96.991371,33.288559],"type":"Point"}
}