{
  "type": "Feature",
  "properties": {
    "iso:country":"US",
    "sg:address":"10100 West Rd",
    "sg:city":"Houston",
    "sg:classifiers":[
        {
            "category":"Education",
            "subcategory":"Special Training",
            "type":"Public Place"
        }
    ],
    "sg:phone":"+1 281 955 6284",
    "sg:postcode":"77064",
    "sg:province":"TX",
    "sg:tags":[
        "tutoring"
    ],
    "wof:name":"Kumon Math and Reading",
    "wof:placetype":"venue"
},
  "geometry": {"coordinates":[-95.567802,29.909901],"type":"Point"}
}