{
  "type": "Feature",
  "properties": {
    "iso:country":"US",
    "sg:address":"124 SE 9th St",
    "sg:city":"Plainview",
    "sg:classifiers":[
        {
            "category":"Building & Trades",
            "subcategory":"Plumbing",
            "type":"Services"
        }
    ],
    "sg:phone":"+1 806 293 8670",
    "sg:postcode":"79072",
    "sg:province":"TX",
    "sg:tags":[
        "contractor"
    ],
    "wof:name":"Quality Air Service Center",
    "wof:placetype":"venue"
},
  "geometry": {"coordinates":[-101.699724,34.171338],"type":"Point"}
}