{
  "type": "Feature",
  "properties": {
    "iso:country":"US",
    "sg:address":"5038 Stanhope Dr",
    "sg:city":"Houston",
    "sg:classifiers":[
        {
            "category":"Freight",
            "type":"Transportation"
        }
    ],
    "sg:phone":"+1 281 859 2956",
    "sg:postcode":"77084",
    "sg:province":"TX",
    "sg:tags":[
        "operator",
        "local",
        "trucking"
    ],
    "wof:name":"Cortes Trucking",
    "wof:placetype":"venue"
},
  "geometry": {"coordinates":[-95.636634,29.849556],"type":"Point"}
}