{
  "type": "Feature",
  "properties": {
    "iso:country":"US",
    "sg:address":"117 W Main St",
    "sg:city":"Allen",
    "sg:classifiers":[
        {
            "category":"Professional",
            "subcategory":"Lawyer & Legal Services",
            "type":"Services"
        }
    ],
    "sg:phone":"+1 972 727 4993",
    "sg:postcode":"75013",
    "sg:province":"TX",
    "sg:tags":[
        "attorney"
    ],
    "wof:name":"John T Helm",
    "wof:placetype":"venue"
},
  "geometry": {"coordinates":[-96.670768,33.103051],"type":"Point"}
}