{
  "type": "Feature",
  "properties": {
    "iso:country":"US",
    "sg:address":"2241 Pasadena Blvd",
    "sg:city":"Pasadena",
    "sg:classifiers":[
        {
            "category":"Personal",
            "subcategory":"Beauty Salon",
            "type":"Services"
        }
    ],
    "sg:phone":"+1 713 534 9398",
    "sg:postcode":"77502",
    "sg:province":"TX",
    "sg:tags":[
        "shop"
    ],
    "wof:name":"Pasadena Hair Design",
    "wof:placetype":"venue"
},
  "geometry": {"coordinates":[-95.17972399999999,29.682242],"type":"Point"}
}