{
  "type": "Feature",
  "properties": {
    "iso:country":"US",
    "sg:address":"1359 E 8th St",
    "sg:city":"Odessa",
    "sg:classifiers":[
        {
            "category":"Retail",
            "subcategory":"Laundry & Dry Cleaning",
            "type":"Services"
        }
    ],
    "sg:phone":"+1 432 332 4701",
    "sg:postcode":"79761",
    "sg:province":"TX",
    "sg:tags":[
        "drycleaning",
        "plant",
        "power"
    ],
    "wof:name":"Globe Cleaners",
    "wof:placetype":"venue"
},
  "geometry": {"coordinates":[-102.355581,31.858967],"type":"Point"}
}