{
  "type": "Feature",
  "properties": {
    "iso:country":"US",
    "sg:address":"200 W San Antonio Ave",
    "sg:city":"El Paso",
    "sg:classifiers":[
        {
            "category":"Local Transit",
            "type":"Transportation"
        }
    ],
    "sg:phone":"+1 915 542 1355",
    "sg:postcode":"79901",
    "sg:province":"TX",
    "sg:tags":[
        "bus",
        "line",
        "commercial"
    ],
    "wof:name":"Greyhound Bus Lines",
    "wof:placetype":"venue"
},
  "geometry": {"coordinates":[-106.491001,31.75698],"type":"Point"}
}