{
  "type": "Feature",
  "properties": {
    "iso:country":"US",
    "sg:address":"203 Schletze St",
    "sg:city":"Encinal",
    "sg:classifiers":[
        {
            "category":"Government",
            "subcategory":"Office",
            "type":"Public Place"
        }
    ],
    "sg:phone":"+1 956 948 5222",
    "sg:postcode":"78019",
    "sg:province":"TX",
    "wof:name":"LA Salle County JP Precinct 2",
    "wof:placetype":"venue"
},
  "geometry": {"coordinates":[-99.359056,28.038319],"type":"Point"}
}