{
  "type": "Feature",
  "properties": {
    "iso:country":"US",
    "sg:address":"17390 Preston Rd",
    "sg:city":"Dallas",
    "sg:classifiers":[
        {
            "category":"Home & Garden",
            "subcategory":"Furniture",
            "type":"Retail Goods"
        }
    ],
    "sg:phone":"+1 972 931 9270",
    "sg:postcode":"75252",
    "sg:province":"TX",
    "wof:name":"Inside Outlet Patio Store",
    "wof:placetype":"venue"
},
  "geometry": {"coordinates":[-96.802691,32.98778],"type":"Point"}
}