{
  "type": "Feature",
  "properties": {
    "iso:country":"US",
    "sg:address":"6111 N Shepherd Dr",
    "sg:city":"Houston",
    "sg:classifiers":[
        {
            "category":"Home & Garden",
            "subcategory":"Building Materials",
            "type":"Retail Goods"
        }
    ],
    "sg:phone":"+1 713 699 2182",
    "sg:postcode":"77091",
    "sg:province":"TX",
    "sg:tags":[
        "plate",
        "window",
        "auto",
        "glass"
    ],
    "wof:name":"Juan's Auto Glass",
    "wof:placetype":"venue"
},
  "geometry": {"coordinates":[-95.412598,29.8531],"type":"Point"}
}