{
  "type": "Feature",
  "properties": {
    "iso:country":"US",
    "sg:address":"206 Gibbs Sprawl Rd",
    "sg:city":"Converse",
    "sg:classifiers":[
        {
            "category":"Professional",
            "subcategory":"Engineering",
            "type":"Services"
        }
    ],
    "sg:phone":"+1 210 658 7250",
    "sg:postcode":"78109",
    "sg:province":"TX",
    "sg:tags":[
        "engineer"
    ],
    "wof:name":"Grubb Engineering Inc",
    "wof:placetype":"venue"
},
  "geometry": {"coordinates":[-98.315938,29.516497],"type":"Point"}
}