{
  "type": "Feature",
  "properties": {
    "iso:country":"US",
    "sg:address":"1302 W Davis St",
    "sg:city":"Conroe",
    "sg:classifiers":[
        {
            "category":"Banks & Credit Unions",
            "subcategory":"Bank",
            "type":"Services"
        }
    ],
    "sg:phone":"+1 936 756 0699",
    "sg:postcode":"77304",
    "sg:province":"TX",
    "sg:tags":[
        "financing"
    ],
    "wof:name":"Citi Financial",
    "wof:placetype":"venue"
},
  "geometry": {"coordinates":[-95.48015100000001,30.318674],"type":"Point"}
}