{
  "type": "Feature",
  "properties": {
    "iso:country":"US",
    "sg:address":"3215 Junction Hwy",
    "sg:city":"Ingram",
    "sg:classifiers":[
        {
            "category":"Fast Food",
            "type":"Food & Drink"
        },
        {
            "category":"Restaurant",
            "type":"Food & Drink"
        }
    ],
    "sg:phone":"+1 830 367 3557",
    "sg:postcode":"78025",
    "sg:province":"TX",
    "sg:tags":[
        "american",
        "hot",
        "hamburger",
        "dog"
    ],
    "sg:website":"http://www.whataburger.com",
    "wof:name":"Whataburger Restaurants",
    "wof:placetype":"venue"
},
  "geometry": {"coordinates":[-99.229517,30.073364],"type":"Point"}
}