{
  "type": "Feature",
  "properties": {
    "iso:country":"US",
    "sg:address":"1162 Allen Genoa Rd",
    "sg:city":"Houston",
    "sg:classifiers":[
        {
            "category":"Food & Beverages",
            "subcategory":"Liquor & Beverages",
            "type":"Retail Goods"
        }
    ],
    "sg:phone":"+1 713 634 0500",
    "sg:postcode":"77017",
    "sg:province":"TX",
    "sg:tags":[
        "beer",
        "spirit",
        "wine"
    ],
    "wof:name":"Beverage Mart II",
    "wof:placetype":"venue"
},
  "geometry": {"coordinates":[-95.235703,29.691799],"type":"Point"}
}