{
  "type": "Feature",
  "properties": {
    "iso:country":"US",
    "sg:address":"215 County Road 800A",
    "sg:city":"Joshua",
    "sg:classifiers":[
        {
            "category":"Retail",
            "subcategory":"Pet Boarding",
            "type":"Services"
        }
    ],
    "sg:phone":"+1 817 875 0087",
    "sg:postcode":"76058",
    "sg:province":"TX",
    "sg:tags":[
        "boarding/pet",
        "sitting"
    ],
    "sg:website":"www.thepinespet.com",
    "wof:name":"THE PINES PET PAMPERING & BOARDING",
    "wof:placetype":"venue"
},
  "geometry": {"coordinates":[-97.374567,32.45797],"type":"Point"}
}