{
  "type": "Feature",
  "properties": {
    "iso:country":"US",
    "sg:address":"214 Elm St",
    "sg:city":"Texhoma",
    "sg:classifiers":[
        {
            "category":"Organizations",
            "subcategory":"Religious Organization",
            "type":"Services"
        }
    ],
    "sg:phone":"+1 580 423 7540",
    "sg:postcode":"73949",
    "sg:province":"TX",
    "sg:tags":[
        "church"
    ],
    "wof:name":"Texhoma Church Of Christ",
    "wof:placetype":"venue"
},
  "geometry": {"coordinates":[-101.783948,36.507033],"type":"Point"}
}