{
  "type": "Feature",
  "properties": {
    "iso:country":"US",
    "sg:address":"1144 N Yarbrough Dr",
    "sg:city":"El Paso",
    "sg:classifiers":[
        {
            "category":"Retail",
            "subcategory":"Portrait Studio",
            "type":"Services"
        }
    ],
    "sg:phone":"+1 915 594 3804",
    "sg:postcode":"79925",
    "sg:province":"TX",
    "sg:tags":[
        "photo"
    ],
    "wof:name":"Walmart Portrait Studio",
    "wof:placetype":"venue"
},
  "geometry": {"coordinates":[-106.344066,31.754154],"type":"Point"}
}