{
  "type": "Feature",
  "properties": {
    "iso:country":"US",
    "sg:address":"3465 W Alabama St",
    "sg:city":"Houston",
    "sg:classifiers":[
        {
            "category":"Health Services",
            "subcategory":"Doctor",
            "type":"Services"
        }
    ],
    "sg:phone":"+1 713 623 4070",
    "sg:postcode":"77027",
    "sg:province":"TX",
    "wof:name":"Wolk David MD",
    "wof:placetype":"venue"
},
  "geometry": {"coordinates":[-95.4328,29.738199],"type":"Point"}
}