{
  "type": "Feature",
  "properties": {
    "iso:country":"US",
    "sg:address":"605 State Hwy 276",
    "sg:city":"Quinlan",
    "sg:classifiers":[
        {
            "category":"Organizations",
            "subcategory":"Professional Association",
            "type":"Services"
        }
    ],
    "sg:phone":"+1 903 447 3020",
    "sg:postcode":"75474",
    "sg:province":"TX",
    "sg:tags":[
        "chambers",
        "commerce"
    ],
    "wof:name":"Tawakoni Chamber Of Commerce",
    "wof:placetype":"venue"
},
  "geometry": {"coordinates":[-96.141492,32.910291],"type":"Point"}
}