{
  "type": "Feature",
  "properties": {
    "iso:country":"US",
    "sg:address":"3537 S I- 35 E",
    "sg:city":"Denton",
    "sg:classifiers":[
        {
            "category":"Health Services",
            "subcategory":"Doctor",
            "type":"Services"
        }
    ],
    "sg:phone":"+1 940 387 7588",
    "sg:postcode":"76210",
    "sg:province":"TX",
    "sg:tags":[
        "medical"
    ],
    "wof:name":"Mizer G Lavell",
    "wof:placetype":"venue"
},
  "geometry": {"coordinates":[-97.091683,33.175288],"type":"Point"}
}