{
  "type": "Feature",
  "properties": {
    "iso:country":"US",
    "sg:address":"4208 Canterwood Dr",
    "sg:city":"Houston",
    "sg:classifiers":[
        {
            "category":"Professional",
            "subcategory":"Business Services",
            "type":"Services"
        }
    ],
    "sg:phone":"+1 281 580 0115",
    "sg:postcode":"77068",
    "sg:province":"TX",
    "wof:name":"Cassidy Professional Group LLC",
    "wof:placetype":"venue"
},
  "geometry": {"coordinates":[-95.5038,30.004018],"type":"Point"}
}