{
  "type": "Feature",
  "properties": {
    "iso:country":"US",
    "sg:address":"134 Co Rd 118",
    "sg:city":"Burnet",
    "sg:classifiers":[
        {
            "category":"Shopping",
            "type":"Retail Goods"
        }
    ],
    "sg:phone":"+1 512 756 9296",
    "sg:postcode":"78611",
    "sg:province":"TX",
    "sg:tags":[
        "merchandise"
    ],
    "wof:name":"Sportart By Vicki",
    "wof:placetype":"venue"
},
  "geometry": {"coordinates":[-98.383258,30.714144],"type":"Point"}
}