{
  "type": "Feature",
  "properties": {
    "iso:country":"US",
    "sg:address":"224 Rick Rd",
    "sg:city":"Perrin",
    "sg:classifiers":[
        {
            "category":"Professional",
            "type":"Services"
        }
    ],
    "sg:phone":"+1 940 798 9263",
    "sg:postcode":"76486",
    "sg:province":"TX",
    "wof:name":"Serenity Falls",
    "wof:placetype":"venue"
},
  "geometry": {"coordinates":[-98.07657399999999,33.032344],"type":"Point"}
}