{
  "type": "Feature",
  "properties": {
    "iso:country":"US",
    "sg:address":"221 W 6th St",
    "sg:city":"Austin",
    "sg:classifiers":[
        {
            "category":"Insurance",
            "subcategory":"Insurance Agent",
            "type":"Services"
        }
    ],
    "sg:phone":"+1 512 499 0411",
    "sg:postcode":"78701",
    "sg:province":"TX",
    "wof:name":"Babb & Romine",
    "wof:placetype":"venue"
},
  "geometry": {"coordinates":[-97.745035,30.268583],"type":"Point"}
}