{
  "type": "Feature",
  "properties": {
    "iso:country":"US",
    "sg:address":"2506 Tracy Cove",
    "sg:city":"Leander",
    "sg:classifiers":[
        {
            "category":"Shopping",
            "type":"Retail Goods"
        }
    ],
    "sg:phone":"+1 512 259 5171",
    "sg:postcode":"78641",
    "sg:province":"TX",
    "sg:tags":[
        "merchandise"
    ],
    "wof:name":"Ribbons & Roses",
    "wof:placetype":"venue"
},
  "geometry": {"coordinates":[-97.83364,30.547632],"type":"Point"}
}