{
  "type": "Feature",
  "properties": {
    "iso:country":"US",
    "sg:address":"810 W Brenda Ln",
    "sg:city":"Magnolia",
    "sg:classifiers":[
        {
            "category":"Building & Trades",
            "subcategory":"Construction",
            "type":"Services"
        }
    ],
    "sg:phone":"+1 281 252 6565",
    "sg:postcode":"77354",
    "sg:province":"TX",
    "sg:tags":[
        "concrete",
        "pumping"
    ],
    "wof:name":"Gooding Concrete Pumping",
    "wof:placetype":"venue"
},
  "geometry": {"coordinates":[-95.767989,30.225265],"type":"Point"}
}