{
  "type": "Feature",
  "properties": {
    "iso:country":"US",
    "sg:address":"227 W 7th Ave",
    "sg:city":"Amarillo",
    "sg:classifiers":[
        {
            "category":"Cinema",
            "subcategory":"Movie Rental",
            "type":"Entertainment"
        }
    ],
    "sg:phone":"+1 806 379 5345",
    "sg:postcode":"79101",
    "sg:province":"AR",
    "sg:tags":[
        "leasing",
        "video",
        "disc",
        "tape"
    ],
    "wof:name":"C & M Video",
    "wof:placetype":"venue"
},
  "geometry": {"coordinates":[-101.839412,35.20678],"type":"Point"}
}