{
  "type": "Feature",
  "properties": {
    "iso:country":"US",
    "sg:address":"1120 Whitewing Ave",
    "sg:city":"Mcallen",
    "sg:classifiers":[
        {
            "category":"Building & Trades",
            "subcategory":"Landscaping Services",
            "type":"Services"
        }
    ],
    "sg:phone":"+1 956 686 4074",
    "sg:postcode":"78501",
    "sg:province":"TX",
    "wof:name":"Mikes Lawn Care",
    "wof:placetype":"venue"
},
  "geometry": {"coordinates":[-98.22701000000001,26.227922],"type":"Point"}
}