{
  "type": "Feature",
  "properties": {
    "iso:country":"US",
    "sg:address":"922 NE 31st St",
    "sg:city":"Grand Prairie",
    "sg:classifiers":[
        {
            "category":"Banks & Credit Unions",
            "subcategory":"Financial Services",
            "type":"Services"
        }
    ],
    "sg:phone":"+1 972 262 5615",
    "sg:postcode":"75050",
    "sg:province":"TX",
    "sg:tags":[
        "trust",
        "management"
    ],
    "wof:name":"Bennett Living Trust",
    "wof:placetype":"venue"
},
  "geometry": {"coordinates":[-96.95845300000001,32.761008],"type":"Point"}
}