{
  "type": "Feature",
  "properties": {
    "iso:country":"US",
    "sg:address":"2714 Bomar Ave",
    "sg:city":"Dallas",
    "sg:classifiers":[
        {
            "category":"Shopping",
            "subcategory":"Catalog Store",
            "type":"Retail Goods"
        }
    ],
    "sg:phone":"+1 214 351 2091",
    "sg:postcode":"75235",
    "sg:province":"TX",
    "sg:tags":[
        "mail",
        "order",
        "online"
    ],
    "wof:name":"General Snap Co",
    "wof:placetype":"venue"
},
  "geometry": {"coordinates":[-96.83919,32.826582],"type":"Point"}
}