{
  "type": "Feature",
  "properties": {
    "iso:country":"US",
    "sg:address":"6322 Highway 6",
    "sg:city":"Hitchcock",
    "sg:classifiers":[
        {
            "category":"Social Services",
            "subcategory":"Child Care",
            "type":"Services"
        },
        {
            "category":"Education",
            "subcategory":"Preschool",
            "type":"Public Place"
        }
    ],
    "sg:phone":"+1 409 986 8322",
    "sg:postcode":"77563",
    "sg:province":"TX",
    "sg:tags":[
        "kindergarten",
        "nursery",
        "day"
    ],
    "wof:name":"K B Kids",
    "wof:placetype":"venue"
},
  "geometry": {"coordinates":[-94.995453,29.342132],"type":"Point"}
}