{
  "type": "Feature",
  "properties": {
    "iso:country":"US",
    "sg:address":"8908 White Settlement Rd",
    "sg:city":"Fort Worth",
    "sg:classifiers":[
        {
            "category":"Personal",
            "subcategory":"Beauty Salon",
            "type":"Services"
        }
    ],
    "sg:phone":"+1 817 246 9072",
    "sg:postcode":"76108",
    "sg:province":"TX",
    "sg:tags":[
        "shop"
    ],
    "wof:name":"Lou-Jean's Beauty Shop",
    "wof:placetype":"venue"
},
  "geometry": {"coordinates":[-97.47056000000001,32.759914],"type":"Point"}
}