{
  "type": "Feature",
  "properties": {
    "iso:country":"US",
    "sg:address":"3303 55th St",
    "sg:city":"Lubbock",
    "sg:classifiers":[
        {
            "category":"Insurance",
            "subcategory":"Insurance Agent",
            "type":"Services"
        }
    ],
    "sg:phone":"+1 806 799 8700",
    "sg:postcode":"79413",
    "sg:province":"TX",
    "wof:name":"Squaw Creek Healthclaims",
    "wof:placetype":"venue"
},
  "geometry": {"coordinates":[-101.887691,33.544138],"type":"Point"}
}