{
  "type": "Feature",
  "properties": {
    "iso:country":"US",
    "sg:address":"1002 Intervale Dr",
    "sg:city":"Garland",
    "sg:classifiers":[
        {
            "category":"Professional",
            "type":"Services"
        }
    ],
    "sg:phone":"+1 972 613 0751",
    "sg:postcode":"75043",
    "sg:province":"TX",
    "wof:name":"L & S Custom Services",
    "wof:placetype":"venue"
},
  "geometry": {"coordinates":[-96.643672,32.853573],"type":"Point"}
}