{
  "type": "Feature",
  "properties": {
    "iso:country":"US",
    "sg:address":"8330 Meadow Rd",
    "sg:city":"Dallas",
    "sg:classifiers":[
        {
            "category":"Health Services",
            "subcategory":"Health Practitioner",
            "type":"Services"
        }
    ],
    "sg:phone":"+1 214 368 5855",
    "sg:postcode":"75231",
    "sg:province":"TX",
    "sg:tags":[
        "psychologist"
    ],
    "wof:name":"Adele H Hurst PHD",
    "wof:placetype":"venue"
},
  "geometry": {"coordinates":[-96.758546,32.885592],"type":"Point"}
}