{
  "type": "Feature",
  "properties": {
    "iso:country":"US",
    "sg:address":"200 Horseshoe Dr",
    "sg:city":"Springtown",
    "sg:classifiers":[
        {
            "category":"Insurance",
            "subcategory":"Insurance Agent",
            "type":"Services"
        }
    ],
    "sg:phone":"+1 817 220 4946",
    "sg:postcode":"76082",
    "sg:province":"TX",
    "wof:name":"Tammy Dahm Insurance Agency",
    "wof:placetype":"venue"
},
  "geometry": {"coordinates":[-97.70572199999999,32.963845],"type":"Point"}
}