{
  "type": "Feature",
  "properties": {
    "iso:country":"US",
    "sg:address":"5302 Wesley St",
    "sg:city":"Greenville",
    "sg:classifiers":[
        {
            "category":"Shopping",
            "subcategory":"Books",
            "type":"Retail Goods"
        }
    ],
    "sg:phone":"+1 903 454 9199",
    "sg:postcode":"75402",
    "sg:province":"TX",
    "wof:name":"Book Nook",
    "wof:placetype":"venue"
},
  "geometry": {"coordinates":[-96.109511,33.117282],"type":"Point"}
}