{
  "type": "Feature",
  "properties": {
    "iso:country":"US",
    "sg:address":"411 W Mesquite St",
    "sg:city":"Nocona",
    "sg:classifiers":[
        {
            "category":"Shopping",
            "subcategory":"Gifts & Souvenirs",
            "type":"Retail Goods"
        }
    ],
    "sg:phone":"+1 940 825 6930",
    "sg:postcode":"76255",
    "sg:province":"TX",
    "wof:name":"Connies Specialty Gifts",
    "wof:placetype":"venue"
},
  "geometry": {"coordinates":[-97.728753,33.784713],"type":"Point"}
}