{
  "type": "Feature",
  "properties": {
    "iso:country":"US",
    "sg:address":"3323 Colonel Court Dr",
    "sg:city":"Richmond",
    "sg:classifiers":[
        {
            "category":"Retail",
            "subcategory":"Laundry & Dry Cleaning",
            "type":"Services"
        }
    ],
    "sg:phone":"+1 281 342 9199",
    "sg:postcode":"77469",
    "sg:province":"TX",
    "wof:name":"Carpet Technicain",
    "wof:placetype":"venue"
},
  "geometry": {"coordinates":[-95.73496299999999,29.640838],"type":"Point"}
}