{
  "type": "Feature",
  "properties": {
    "iso:country":"US",
    "sg:address":"2533 Leprechaun St",
    "sg:city":"Houston",
    "sg:classifiers":[
        {
            "category":"Professional",
            "subcategory":"Detective & Security Services",
            "type":"Services"
        }
    ],
    "sg:phone":"+1 713 944 4590",
    "sg:postcode":"77017",
    "sg:province":"TX",
    "sg:tags":[
        "system"
    ],
    "wof:name":"Ascot Inc Alarm Signal Co-Tx",
    "wof:placetype":"venue"
},
  "geometry": {"coordinates":[-95.228944,29.67144],"type":"Point"}
}