{
  "type": "Feature",
  "properties": {
    "iso:country":"US",
    "sg:address":"401 Hill St",
    "sg:city":"Del Rio",
    "sg:classifiers":[
        {
            "category":"Building & Trades",
            "subcategory":"Equipment Rental",
            "type":"Services"
        }
    ],
    "sg:phone":"+1 830 775 3420",
    "sg:postcode":"78840",
    "sg:province":"TX",
    "wof:name":"Cox Rentals Olga",
    "wof:placetype":"venue"
},
  "geometry": {"coordinates":[-100.910785,29.354218],"type":"Point"}
}