{
  "type": "Feature",
  "properties": {
    "iso:country":"US",
    "sg:address":"11044 Research Blvd",
    "sg:city":"Austin",
    "sg:classifiers":[
        {
            "category":"Professional",
            "subcategory":"Employment Agencies",
            "type":"Services"
        }
    ],
    "sg:phone":"+1 512 231 3600",
    "sg:postcode":"78759",
    "sg:province":"TX",
    "wof:name":"Kforce",
    "wof:placetype":"venue"
},
  "geometry": {"coordinates":[-97.746043,30.404497],"type":"Point"}
}