{
  "type": "Feature",
  "properties": {
    "iso:country":"US",
    "sg:address":"9158 Garden Ridge Dr",
    "sg:city":"San Antonio",
    "sg:classifiers":[
        {
            "category":"Health Services",
            "subcategory":"Clinic",
            "type":"Services"
        }
    ],
    "sg:phone":"+1 210 651 6700",
    "sg:postcode":"78266",
    "sg:province":"TX",
    "wof:name":"Parallel Health Co Inc",
    "wof:placetype":"venue"
},
  "geometry": {"coordinates":[-98.306124,29.628033],"type":"Point"}
}