{
  "type": "Feature",
  "properties": {
    "iso:country":"US",
    "sg:address":"951 N Resler Dr",
    "sg:city":"El Paso",
    "sg:classifiers":[
        {
            "category":"Professional",
            "subcategory":"Accounting & Tax Preparation",
            "type":"Services"
        }
    ],
    "sg:phone":"+1 915 842 9151",
    "sg:postcode":"79912",
    "sg:province":"TX",
    "sg:tags":[
        "return",
        "filing"
    ],
    "wof:name":"Tax Time Tax Svc",
    "wof:placetype":"venue"
},
  "geometry": {"coordinates":[-106.558061,31.861738],"type":"Point"}
}