{
  "type": "Feature",
  "properties": {
    "iso:country":"US",
    "sg:address":"203 Nolan St",
    "sg:city":"San Antonio",
    "sg:classifiers":[
        {
            "category":"Organizations",
            "subcategory":"Religious Organization",
            "type":"Services"
        }
    ],
    "sg:phone":"+1 210 227 9842",
    "sg:postcode":"78202",
    "sg:province":"TX",
    "sg:tags":[
        "monastery",
        "convent"
    ],
    "wof:name":"St Peter Claver Convent",
    "wof:placetype":"venue"
},
  "geometry": {"coordinates":[-98.479221,29.427693],"type":"Point"}
}