{
  "type": "Feature",
  "properties": {
    "iso:country":"US",
    "sg:address":"1812 Wood St",
    "sg:city":"Dallas",
    "sg:classifiers":[
        {
            "category":"Professional",
            "subcategory":"Management & Consulting",
            "type":"Services"
        }
    ],
    "sg:phone":"+1 214 812 4600",
    "sg:postcode":"75201",
    "sg:province":"TX",
    "sg:tags":[
        "marketing",
        "program"
    ],
    "wof:name":"TXU Processing Co",
    "wof:placetype":"venue"
},
  "geometry": {"coordinates":[-96.794162,32.77942],"type":"Point"}
}