{
  "type": "Feature",
  "properties": {
    "iso:country":"US",
    "sg:address":"4820 Strack Rd",
    "sg:city":"Houston",
    "sg:classifiers":[
        {
            "category":"Social Services",
            "type":"Services"
        }
    ],
    "sg:phone":"+1 281 444 5404",
    "sg:postcode":"77069",
    "sg:province":"TX",
    "wof:name":"Mary W Wakefield",
    "wof:placetype":"venue"
},
  "geometry": {"coordinates":[-95.515066,30.000489],"type":"Point"}
}