{
  "type": "Feature",
  "properties": {
    "iso:country":"US",
    "sg:address":"4605 Matador Trl",
    "sg:city":"Amarillo",
    "sg:classifiers":[
        {
            "category":"Retail",
            "subcategory":"Laundry & Dry Cleaning",
            "type":"Services"
        }
    ],
    "sg:phone":"+1 806 355 9655",
    "sg:postcode":"79109",
    "sg:province":"TX",
    "wof:name":"Raef Oriental Rug Repair",
    "wof:placetype":"venue"
},
  "geometry": {"coordinates":[-101.888182,35.158959],"type":"Point"}
}