{
  "type": "Feature",
  "properties": {
    "iso:country":"US",
    "sg:address":"11 Alpha",
    "sg:city":"Rockport",
    "sg:classifiers":[
        {
            "category":"Professional",
            "subcategory":"Business Services",
            "type":"Services"
        }
    ],
    "sg:phone":"+1 361 727 2165",
    "sg:postcode":"78382",
    "sg:province":"TX",
    "wof:name":"Kay Mosier Enterprises",
    "wof:placetype":"venue"
},
  "geometry": {"coordinates":[-97.05094200000001,28.042493],"type":"Point"}
}