{
  "type": "Feature",
  "properties": {
    "iso:country":"US",
    "sg:address":"1007 Winchester Bend",
    "sg:city":"Huffman",
    "sg:classifiers":[
        {
            "category":"Health Services",
            "subcategory":"Health Practitioner",
            "type":"Services"
        }
    ],
    "sg:phone":"+1 281 540 7777",
    "sg:postcode":"77336",
    "sg:province":"TX",
    "wof:name":"Alacrity Inc",
    "wof:placetype":"venue"
},
  "geometry": {"coordinates":[-95.12026,30.068357],"type":"Point"}
}