{
  "type": "Feature",
  "properties": {
    "iso:country":"US",
    "sg:address":"2939 Beech Plain Dr",
    "sg:city":"San Antonio",
    "sg:classifiers":[
        {
            "category":"Professional",
            "subcategory":"Business Services",
            "type":"Services"
        }
    ],
    "sg:phone":"+1 210 673 8008",
    "sg:postcode":"78245",
    "sg:province":"TX",
    "wof:name":"Mark Snow Enterprises",
    "wof:placetype":"venue"
},
  "geometry": {"coordinates":[-98.682524,29.402003],"type":"Point"}
}