{
  "type": "Feature",
  "properties": {
    "iso:country":"US",
    "sg:address":"15903 Reston Bridge Dr",
    "sg:city":"Cypress",
    "sg:classifiers":[
        {
            "category":"Professional",
            "type":"Services"
        }
    ],
    "sg:phone":"+1 281 256 6393",
    "sg:postcode":"77429",
    "sg:province":"TX",
    "wof:name":"Allred Project Services",
    "wof:placetype":"venue"
},
  "geometry": {"coordinates":[-95.665491,29.986684],"type":"Point"}
}