{
  "type": "Feature",
  "properties": {
    "iso:country":"US",
    "sg:address":"2205 W Parker Rd",
    "sg:city":"Plano",
    "sg:classifiers":[
        {
            "category":"Restaurant",
            "type":"Food & Drink"
        }
    ],
    "sg:menulink":"http://www.allmenus.com/tx/plano/50330-el-norte/menu/",
    "sg:phone":"+1 972 596 6783",
    "sg:postcode":"75023",
    "sg:province":"TX",
    "sg:tags":[
        "mexican"
    ],
    "wof:name":"El Norte",
    "wof:placetype":"venue"
},
  "geometry": {"coordinates":[-96.736104,33.041226],"type":"Point"}
}