{
  "type": "Feature",
  "properties": {
    "iso:country":"US",
    "sg:address":"7101 Mcneil Dr",
    "sg:city":"Austin",
    "sg:classifiers":[
        {
            "category":"Building & Trades",
            "subcategory":"Landscaping Services",
            "type":"Services"
        }
    ],
    "sg:phone":"+1 512 257 0999",
    "sg:postcode":"78729",
    "sg:province":"TX",
    "sg:tags":[
        "consultant",
        "designer",
        "landscape"
    ],
    "wof:name":"Grass Patch The Inc.",
    "wof:placetype":"venue"
},
  "geometry": {"coordinates":[-97.763458,30.436403],"type":"Point"}
}