{
  "type": "Feature",
  "properties": {
    "iso:country":"US",
    "sg:address":"817 N 4th St",
    "sg:city":"Lamesa",
    "sg:classifiers":[
        {
            "category":"Food & Beverages",
            "subcategory":"Bakery",
            "type":"Retail Goods"
        }
    ],
    "sg:phone":"+1 806 872 0568",
    "sg:postcode":"79331",
    "sg:province":"TX",
    "sg:tags":[
        "baker"
    ],
    "wof:name":"Donut Shop",
    "wof:placetype":"venue"
},
  "geometry": {"coordinates":[-101.95781700000001,32.735166],"type":"Point"}
}