{
  "type": "Feature",
  "properties": {
    "iso:country":"US",
    "sg:address":"1073 Silber Rd",
    "sg:city":"Houston",
    "sg:classifiers":[
        {
            "category":"Wholesale",
            "subcategory":"Groceries",
            "type":"Manufacturing & Wholesale Goods"
        }
    ],
    "sg:phone":"+1 713 681 8467",
    "sg:postcode":"77055",
    "sg:province":"TX",
    "wof:name":"Paulies Cookies",
    "wof:placetype":"venue"
},
  "geometry": {"coordinates":[-95.46813400000001,29.787793],"type":"Point"}
}