{
  "type": "Feature",
  "properties": {
    "iso:country":"US",
    "sg:address":"2555 Walnut Hill Lane Suite 500",
    "sg:city":"Dallas",
    "sg:classifiers":[
        {
            "category":"Food & Beverages",
            "subcategory":"Bakery",
            "type":"Retail Goods"
        }
    ],
    "sg:phone":"+1 214 366 7728",
    "sg:postcode":"75229",
    "sg:province":"TX",
    "sg:tags":[
        "sandwich"
    ],
    "sg:website":"www.lennys.com",
    "wof:name":"Lenny's Sub Shop",
    "wof:placetype":"venue"
},
  "geometry": {"coordinates":[-96.89140399999999,32.881569],"type":"Point"}
}