{
  "type": "Feature",
  "properties": {
    "iso:country":"US",
    "sg:address":"1322 Lost Creek Blvd",
    "sg:city":"Austin",
    "sg:classifiers":[
        {
            "category":"Manufacturing",
            "subcategory":"Tools & Machinery",
            "type":"Manufacturing & Wholesale Goods"
        }
    ],
    "sg:phone":"+1 512 306 8899",
    "sg:postcode":"78746",
    "sg:province":"TX",
    "sg:tags":[
        "physician",
        "surgeon"
    ],
    "sg:website":"www.kellygr.com",
    "wof:name":"Kelly Graphics",
    "wof:placetype":"venue"
},
  "geometry": {"coordinates":[-97.833096,30.2841],"type":"Point"}
}