{
  "type": "Feature",
  "properties": {
    "iso:country":"US",
    "sg:address":"910 N Vista Ridge Blvd",
    "sg:city":"Cedar Park",
    "sg:classifiers":[
        {
            "category":"Social Services",
            "subcategory":"Child Care",
            "type":"Services"
        },
        {
            "category":"Education",
            "subcategory":"Preschool",
            "type":"Public Place"
        }
    ],
    "sg:phone":"+1 512 260 0708",
    "sg:postcode":"78613",
    "sg:province":"TX",
    "sg:tags":[
        "day"
    ],
    "sg:website":"www.primrosevistaridge.com",
    "wof:name":"Primrose School at Vista Ridge",
    "wof:placetype":"venue"
},
  "geometry": {"coordinates":[-97.79075400000001,30.531064],"type":"Point"}
}