{
  "type": "Feature",
  "properties": {
    "iso:country":"US",
    "sg:address":"3311 89th St",
    "sg:city":"Lubbock",
    "sg:classifiers":[
        {
            "category":"Social Services",
            "subcategory":"Job Training",
            "type":"Services"
        },
        {
            "category":"Health Services",
            "subcategory":"Nursing And Care Facility",
            "type":"Services"
        },
        {
            "category":"Social Services",
            "subcategory":"Adult Care",
            "type":"Services"
        }
    ],
    "sg:phone":"+1 806 796 2397",
    "sg:postcode":"79423",
    "sg:province":"TX",
    "sg:tags":[
        "living",
        "nurses-home",
        "homes-skilled",
        "people",
        "assisted",
        "elder",
        "centers-adult",
        "homes-elderly",
        "day"
    ],
    "wof:name":"Compassionate Care For Elderly",
    "wof:placetype":"venue"
},
  "geometry": {"coordinates":[-101.886123,33.51362],"type":"Point"}
}