{
  "type": "Feature",
  "properties": {
    "iso:country":"US",
    "sg:address":"13640 State Hwy 249",
    "sg:city":"Houston",
    "sg:classifiers":[
        {
            "category":"Professional",
            "subcategory":"Accounting & Tax Preparation",
            "type":"Services"
        }
    ],
    "sg:phone":"+1 281 591 1842",
    "sg:postcode":"77086",
    "sg:province":"TX",
    "sg:tags":[
        "return",
        "filing"
    ],
    "wof:name":"Express Ttax",
    "wof:placetype":"venue"
},
  "geometry": {"coordinates":[-95.488285,29.916402],"type":"Point"}
}