{
  "type": "Feature",
  "properties": {
    "iso:country":"US",
    "sg:address":"2000 West Loop S",
    "sg:city":"Houston",
    "sg:classifiers":[
        {
            "category":"Wholesale",
            "subcategory":"Computers",
            "type":"Manufacturing & Wholesale Goods"
        }
    ],
    "sg:phone":"+1 214 439 5300",
    "sg:postcode":"77027",
    "sg:province":"TX",
    "wof:name":"Hewlett-Packard",
    "wof:placetype":"venue"
},
  "geometry": {"coordinates":[-95.457292,29.746884],"type":"Point"}
}