{
  "type": "Feature",
  "properties": {
    "iso:country":"US",
    "sg:address":"2816 Cetti St",
    "sg:city":"Houston",
    "sg:classifiers":[
        {
            "category":"Organizations",
            "subcategory":"Religious Organization",
            "type":"Services"
        }
    ],
    "sg:phone":"+1 713 227 2805",
    "sg:postcode":"77009",
    "sg:province":"TX",
    "sg:tags":[
        "church"
    ],
    "wof:name":"El Mesias Methodist Church",
    "wof:placetype":"venue"
},
  "geometry": {"coordinates":[-95.358554,29.787858],"type":"Point"}
}