{
  "type": "Feature",
  "properties": {
    "iso:country":"US",
    "sg:address":"11713 Fidelia Ct",
    "sg:city":"Houston",
    "sg:classifiers":[
        {
            "category":"Professional",
            "subcategory":"Business Services",
            "type":"Services"
        }
    ],
    "sg:phone":"+1 713 780 8279",
    "sg:postcode":"77024",
    "sg:province":"TX",
    "wof:name":"G&B Bluestone Partnership Ltd",
    "wof:placetype":"venue"
},
  "geometry": {"coordinates":[-95.527675,29.754919],"type":"Point"}
}