{
  "type": "Feature",
  "properties": {
    "iso:country":"US",
    "sg:address":"180 Southfield Ln",
    "sg:city":"Marshall",
    "sg:classifiers":[
        {
            "category":"Building & Trades",
            "subcategory":"Equipment Rental",
            "type":"Services"
        }
    ],
    "sg:phone":"+1 903 938 1458",
    "sg:postcode":"75672",
    "sg:province":"TX",
    "sg:tags":[
        "leasing",
        "television",
        "radio-renting"
    ],
    "wof:name":"Big Star Rentals",
    "wof:placetype":"venue"
},
  "geometry": {"coordinates":[-94.349577,32.452732],"type":"Point"}
}