{
  "type": "Feature",
  "properties": {
    "iso:country":"US",
    "sg:address":"8918 Bent Spur Ln",
    "sg:city":"Houston",
    "sg:classifiers":[
        {
            "category":"Building & Trades",
            "subcategory":"Construction",
            "type":"Services"
        }
    ],
    "sg:phone":"+1 281 890 5138",
    "sg:postcode":"77064",
    "sg:province":"TX",
    "sg:tags":[
        "nonresidential"
    ],
    "wof:name":"L&J Ventures Inc",
    "wof:placetype":"venue"
},
  "geometry": {"coordinates":[-95.57689000000001,29.902993],"type":"Point"}
}