{
  "type": "Feature",
  "properties": {
    "iso:country":"US",
    "sg:address":"2347 Broadgreen Dr",
    "sg:city":"Missouri City",
    "sg:classifiers":[
        {
            "category":"Cinema",
            "subcategory":"Movie Rental",
            "type":"Entertainment"
        }
    ],
    "sg:phone":"+1 281 261 4903",
    "sg:postcode":"77489",
    "sg:province":"TX",
    "sg:tags":[
        "motion",
        "video",
        "production",
        "tape"
    ],
    "wof:name":"Mc Gill & Mc Gill Video",
    "wof:placetype":"venue"
},
  "geometry": {"coordinates":[-95.538584,29.588911],"type":"Point"}
}