{
  "type": "Feature",
  "properties": {
    "iso:country":"US",
    "sg:address":"6530 Dykes Way",
    "sg:city":"Dallas",
    "sg:classifiers":[
        {
            "category":"Professional",
            "subcategory":"Business Services",
            "type":"Services"
        }
    ],
    "sg:phone":"+1 972 233 0515",
    "sg:postcode":"75230",
    "sg:province":"TX",
    "wof:name":"David Abramson P A",
    "wof:placetype":"venue"
},
  "geometry": {"coordinates":[-96.79253300000001,32.919599],"type":"Point"}
}