{
  "type": "Feature",
  "properties": {
    "iso:country":"US",
    "sg:address":"2111 Orchard Ln",
    "sg:city":"Midland",
    "sg:classifiers":[
        {
            "category":"Shopping",
            "type":"Retail Goods"
        }
    ],
    "sg:phone":"+1 432 687 1622",
    "sg:postcode":"79701",
    "sg:province":"TX",
    "sg:tags":[
        "merchandise"
    ],
    "wof:name":"Advanced Water Treatment",
    "wof:placetype":"venue"
},
  "geometry": {"coordinates":[-102.053454,32.007368],"type":"Point"}
}