{
  "type": "Feature",
  "properties": {
    "iso:country":"US",
    "sg:address":"104 W Broad St",
    "sg:city":"Mineola",
    "sg:classifiers":[
        {
            "category":"Banks & Credit Unions",
            "subcategory":"Bank",
            "type":"Services"
        }
    ],
    "sg:phone":"+1 903 569 0278",
    "sg:postcode":"75773",
    "sg:province":"TX",
    "sg:tags":[
        "loan",
        "real estate"
    ],
    "wof:name":"Banksource Mortgage",
    "wof:placetype":"venue"
},
  "geometry": {"coordinates":[-95.490251,32.663769],"type":"Point"}
}