{
  "type": "Feature",
  "properties": {
    "iso:country":"US",
    "sg:address":"2501 Judson Rd",
    "sg:city":"Longview",
    "sg:classifiers":[
        {
            "category":"Personal",
            "subcategory":"Beauty Salon",
            "type":"Services"
        }
    ],
    "sg:phone":"+1 903 757 8733",
    "sg:postcode":"75605",
    "sg:province":"TX",
    "sg:tags":[
        "nail"
    ],
    "wof:name":"T Nail",
    "wof:placetype":"venue"
},
  "geometry": {"coordinates":[-94.746241,32.54141],"type":"Point"}
}