{
  "type": "Feature",
  "properties": {
    "iso:country":"US",
    "sg:address":"1959 W Northwest Hwy",
    "sg:city":"Dallas",
    "sg:classifiers":[
        {
            "category":"Utilities",
            "subcategory":"Mobile Phone",
            "type":"Services"
        }
    ],
    "sg:phone":"+1 214 574 5279",
    "sg:postcode":"75220",
    "sg:province":"TX",
    "sg:tags":[
        "communication",
        "radiotelephone",
        "merchandise"
    ],
    "sg:website":"www.wireless-retail.com",
    "wof:name":"Wireless Retail Inc",
    "wof:placetype":"venue"
},
  "geometry": {"coordinates":[-96.91100299999999,32.868401],"type":"Point"}
}