{
  "type": "Feature",
  "properties": {
    "iso:country":"US",
    "sg:address":"4146 Sweet Gum Trl",
    "sg:city":"Humble",
    "sg:classifiers":[
        {
            "category":"Building & Trades",
            "subcategory":"Construction",
            "type":"Services"
        }
    ],
    "sg:phone":"+1 281 359 4361",
    "sg:postcode":"77339",
    "sg:province":"TX",
    "wof:name":"Menade Incorporated",
    "wof:placetype":"venue"
},
  "geometry": {"coordinates":[-95.201444,30.074333],"type":"Point"}
}