{
  "type": "Feature",
  "properties": {
    "iso:country":"US",
    "sg:address":"1910 Eastgate Dr",
    "sg:city":"Garland",
    "sg:classifiers":[
        {
            "category":"Retail",
            "subcategory":"Funeral Services",
            "type":"Services"
        }
    ],
    "sg:phone":"+1 972 270 6116",
    "sg:postcode":"75041",
    "sg:province":"TX",
    "sg:tags":[
        "cemetery"
    ],
    "wof:name":"Eastgate Funeral Home & Cremation Services",
    "wof:placetype":"venue"
},
  "geometry": {"coordinates":[-96.65679900000001,32.8619],"type":"Point"}
}