{
  "type": "Feature",
  "properties": {
    "iso:country":"US",
    "sg:address":"2912 Parkhaven Dr",
    "sg:city":"Flower Mound",
    "sg:classifiers":[
        {
            "category":"Shopping",
            "type":"Retail Goods"
        }
    ],
    "sg:phone":"+1 972 539 3836",
    "sg:postcode":"75022",
    "sg:province":"TX",
    "sg:tags":[
        "merchandise"
    ],
    "wof:name":"Distinctive Designs By Sherry",
    "wof:placetype":"venue"
},
  "geometry": {"coordinates":[-97.08031800000001,33.025188],"type":"Point"}
}