{
  "type": "Feature",
  "properties": {
    "iso:country":"US",
    "sg:address":"1005 Salem Dr",
    "sg:city":"Corpus Christi",
    "sg:classifiers":[
        {
            "category":"Retail",
            "subcategory":"Auto Repair",
            "type":"Services"
        }
    ],
    "sg:phone":"+1 361 854 7040",
    "sg:postcode":"78412",
    "sg:province":"TX",
    "sg:tags":[
        "body"
    ],
    "wof:name":"Chrome Pros",
    "wof:placetype":"venue"
},
  "geometry": {"coordinates":[-97.366844,27.713593],"type":"Point"}
}