{
  "type": "Feature",
  "properties": {
    "iso:country":"US",
    "sg:address":"2229 Ave J",
    "sg:city":"Arlington",
    "sg:classifiers":[
        {
            "category":"Travel",
            "subcategory":"Travel Agent",
            "type":"Entertainment"
        }
    ],
    "sg:phone":"+1 817 608 0022",
    "sg:postcode":"76006",
    "sg:province":"TX",
    "sg:tags":[
        "agency"
    ],
    "wof:name":"National Vacations Inc",
    "wof:placetype":"venue"
},
  "geometry": {"coordinates":[-97.070588,32.767248],"type":"Point"}
}