{
  "type": "Feature",
  "properties": {
    "iso:country":"US",
    "sg:address":"8304 Kromer St",
    "sg:city":"Austin",
    "sg:classifiers":[
        {
            "category":"Professional",
            "subcategory":"Printing & Photocopies",
            "type":"Services"
        }
    ],
    "sg:phone":"+1 512 529 7719",
    "sg:postcode":"78757",
    "sg:province":"TX",
    "sg:tags":[
        "lithographer"
    ],
    "wof:name":"Kilowatt Screen Print",
    "wof:placetype":"venue"
},
  "geometry": {"coordinates":[-97.719109,30.357941],"type":"Point"}
}