{
  "type": "Feature",
  "properties": {
    "iso:country":"US",
    "sg:address":"2930 Preston Rd",
    "sg:city":"Frisco",
    "sg:classifiers":[
        {
            "category":"Manufacturing",
            "subcategory":"Printing",
            "type":"Manufacturing & Wholesale Goods"
        },
        {
            "category":"Professional",
            "subcategory":"Advertising",
            "type":"Services"
        },
        {
            "category":"Retail",
            "subcategory":"Repair Shop",
            "type":"Services"
        },
        {
            "category":"Manufacturing",
            "subcategory":"Signs",
            "type":"Manufacturing & Wholesale Goods"
        }
    ],
    "sg:phone":"+1 972 335 9977",
    "sg:postcode":"75034",
    "sg:province":"TX",
    "sg:tags":[
        "advertising-promotional",
        "product",
        "signs-maintenance",
        "imaging",
        "digital"
    ],
    "sg:website":"http://www.signaramafrisco.com",
    "wof:name":"Frisco Signarama",
    "wof:placetype":"venue"
},
  "geometry": {"coordinates":[-96.80549600000001,33.103042],"type":"Point"}
}