{
  "type": "Feature",
  "properties": {
    "iso:country":"US",
    "sg:address":"2642 Freewood Dr",
    "sg:city":"Dallas",
    "sg:classifiers":[
        {
            "category":"Wholesale",
            "subcategory":"Electrical",
            "type":"Manufacturing & Wholesale Goods"
        }
    ],
    "sg:phone":"+1 214 351 1954",
    "sg:postcode":"75220",
    "sg:province":"TX",
    "sg:tags":[
        "electronic"
    ],
    "wof:name":"Lii",
    "wof:placetype":"venue"
},
  "geometry": {"coordinates":[-96.883893,32.870383],"type":"Point"}
}