{
  "type": "Feature",
  "properties": {
    "iso:country":"US",
    "sg:address":"1200 FM 1845 S",
    "sg:city":"Longview",
    "sg:classifiers":[
        {
            "category":"Wholesale",
            "subcategory":"Machinery & Supplies",
            "type":"Manufacturing & Wholesale Goods"
        }
    ],
    "sg:phone":"+1 903 242 9494",
    "sg:postcode":"75603",
    "sg:province":"TX",
    "sg:tags":[
        "farm",
        "equipment"
    ],
    "wof:name":"Williams Tractor Sales",
    "wof:placetype":"venue"
},
  "geometry": {"coordinates":[-94.75765199999999,32.466057],"type":"Point"}
}