{
  "type": "Feature",
  "properties": {
    "iso:country":"US",
    "sg:address":"6519 Preston Trail Dr",
    "sg:city":"Houston",
    "sg:classifiers":[
        {
            "category":"Shopping",
            "subcategory":"Clothing, Apparel, & Fashions",
            "type":"Retail Goods"
        }
    ],
    "sg:phone":"+1 281 233 4445",
    "sg:postcode":"77069",
    "sg:province":"TX",
    "wof:name":"Spree Ventures Inc",
    "wof:placetype":"venue"
},
  "geometry": {"coordinates":[-95.533835,29.982564],"type":"Point"}
}