{
  "type": "Feature",
  "properties": {
    "iso:country":"US",
    "sg:address":"3600 FM 1488",
    "sg:city":"Conroe",
    "sg:classifiers":[
        {
            "category":"Food & Beverages",
            "subcategory":"Liquor & Beverages",
            "type":"Retail Goods"
        }
    ],
    "sg:phone":"+1 281 807 1316",
    "sg:postcode":"77384",
    "sg:province":"TX",
    "sg:tags":[
        "alcoholic"
    ],
    "wof:name":"Plaza Liquor Inc",
    "wof:placetype":"venue"
},
  "geometry": {"coordinates":[-95.47860900000001,30.235436],"type":"Point"}
}