{
  "type": "Feature",
  "properties": {
    "iso:country":"US",
    "sg:address":"1328 Post Office St",
    "sg:city":"Galveston",
    "sg:classifiers":[
        {
            "category":"Retail",
            "subcategory":"Auto Repair",
            "type":"Services"
        }
    ],
    "sg:phone":"+1 409 763 1515",
    "sg:postcode":"77550",
    "sg:province":"TX",
    "sg:tags":[
        "general"
    ],
    "wof:name":"International Car Care",
    "wof:placetype":"venue"
},
  "geometry": {"coordinates":[-94.782939,29.307378],"type":"Point"}
}