{
  "type": "Feature",
  "properties": {
    "iso:country":"US",
    "sg:address":"1945 Calder Ave",
    "sg:city":"Beaumont",
    "sg:classifiers":[
        {
            "category":"Retail",
            "subcategory":"Portrait Studio",
            "type":"Services"
        },
        {
            "category":"Retail",
            "subcategory":"Photofinishing",
            "type":"Services"
        }
    ],
    "sg:phone":"+1 409 833 8420",
    "sg:postcode":"77701",
    "sg:province":"TX",
    "sg:tags":[
        "motion",
        "laboratory",
        "photographer"
    ],
    "wof:name":"Image Specialists Inc",
    "wof:placetype":"venue"
},
  "geometry": {"coordinates":[-94.115268,30.085812],"type":"Point"}
}