{
  "type": "Feature",
  "properties": {
    "iso:country":"US",
    "sg:address":"2161 NW Military Hwy",
    "sg:city":"San Antonio",
    "sg:classifiers":[
        {
            "category":"Professional",
            "subcategory":"Advertising",
            "type":"Services"
        }
    ],
    "sg:phone":"+1 210 474 7400",
    "sg:postcode":"78213",
    "sg:province":"TX",
    "sg:tags":[
        "marketing",
        "agency",
        "public",
        "relations"
    ],
    "wof:name":"Parker & Wood",
    "wof:placetype":"venue"
},
  "geometry": {"coordinates":[-98.52231399999999,29.532521],"type":"Point"}
}