{
  "type": "Feature",
  "properties": {
    "iso:country":"US",
    "sg:address":"5437 Mercedes Ave",
    "sg:city":"Dallas",
    "sg:classifiers":[
        {
            "category":"Real Estate",
            "subcategory":"Real Estate Agent",
            "type":"Services"
        }
    ],
    "sg:phone":"+1 214 361 8530",
    "sg:postcode":"75206",
    "sg:province":"TX",
    "wof:name":"Muriel Hughes Realtors",
    "wof:placetype":"venue"
},
  "geometry": {"coordinates":[-96.775643,32.828276],"type":"Point"}
}