{
  "type": "Feature",
  "properties": {
    "iso:country":"US",
    "sg:address":"1306 W Cherry Ave",
    "sg:city":"Orange",
    "sg:classifiers":[
        {
            "category":"Restaurant",
            "type":"Food & Drink"
        }
    ],
    "sg:phone":"+1 409 988 0652",
    "sg:postcode":"77630",
    "sg:province":"TX",
    "wof:name":"Mary",
    "wof:placetype":"venue"
},
  "geometry": {"coordinates":[-93.742486,30.097909],"type":"Point"}
}