{
  "type": "Feature",
  "properties": {
    "iso:country":"US",
    "sg:address":"1160 Lake View Dr",
    "sg:city":"Montgomery",
    "sg:classifiers":[
        {
            "category":"Real Estate",
            "subcategory":"Real Estate Services",
            "type":"Services"
        },
        {
            "category":"Real Estate",
            "subcategory":"Real Estate Agent",
            "type":"Services"
        }
    ],
    "sg:phone":"+1 936 448 5993",
    "sg:postcode":"77356",
    "sg:province":"TX",
    "sg:tags":[
        "buyer",
        "broker"
    ],
    "wof:name":"Texas Real Estate Classes",
    "wof:placetype":"venue"
},
  "geometry": {"coordinates":[-95.64785000000001,30.387464],"type":"Point"}
}