{
  "type": "Feature",
  "properties": {
    "iso:country":"US",
    "sg:address":"14018 Fairway Oaks",
    "sg:city":"San Antonio",
    "sg:classifiers":[
        {
            "category":"Professional",
            "subcategory":"Business Services",
            "type":"Services"
        }
    ],
    "sg:phone":"+1 210 946 9134",
    "sg:postcode":"78217",
    "sg:province":"TX",
    "wof:name":"Architel Technologies Inc",
    "wof:placetype":"venue"
},
  "geometry": {"coordinates":[-98.409272,29.566156],"type":"Point"}
}