{
  "type": "Feature",
  "properties": {
    "iso:country":"US",
    "sg:address":"6643 Velasco Ave",
    "sg:city":"Dallas",
    "sg:classifiers":[
        {
            "category":"Professional",
            "subcategory":"Employment Agencies",
            "type":"Services"
        }
    ],
    "sg:phone":"+1 214 826 2004",
    "sg:postcode":"75214",
    "sg:province":"TX",
    "wof:name":"Lasky & Company",
    "wof:placetype":"venue"
},
  "geometry": {"coordinates":[-96.74733000000001,32.821165],"type":"Point"}
}