{
  "type": "Feature",
  "properties": {
    "iso:country":"US",
    "sg:address":"3310 Kay St",
    "sg:city":"Austin",
    "sg:classifiers":[
        {
            "category":"Building & Trades",
            "subcategory":"Cleaning & Sanitation",
            "type":"Services"
        }
    ],
    "sg:phone":"+1 512 926 3343",
    "sg:postcode":"78702",
    "sg:province":"TX",
    "sg:tags":[
        "carpet"
    ],
    "wof:name":"Vibra Vac Steam Cleaning & Water Pickup",
    "wof:placetype":"venue"
},
  "geometry": {"coordinates":[-97.698502,30.2696],"type":"Point"}
}