{
  "type": "Feature",
  "properties": {
    "iso:country":"US",
    "sg:address":"8205 Broadway St",
    "sg:city":"Houston",
    "sg:classifiers":[
        {
            "category":"Shopping",
            "subcategory":"Jewelry",
            "type":"Retail Goods"
        }
    ],
    "sg:phone":"+1 713 644 0649",
    "sg:postcode":"77061",
    "sg:province":"TX",
    "sg:tags":[
        "designer"
    ],
    "wof:name":"Mosqueda's Jewelry",
    "wof:placetype":"venue"
},
  "geometry": {"coordinates":[-95.27712099999999,29.673083],"type":"Point"}
}