{
  "type": "Feature",
  "properties": {
    "iso:country":"US",
    "sg:address":"1920 S 3rd St",
    "sg:city":"Mabank",
    "sg:classifiers":[
        {
            "category":"Autos & Motor Vehicles",
            "subcategory":"Boat Sales",
            "type":"Retail Goods"
        }
    ],
    "sg:phone":"+1 903 887 8909",
    "sg:postcode":"75147",
    "sg:province":"TX",
    "sg:tags":[
        "parts",
        "accessory"
    ],
    "wof:name":"Motor Pro Marine",
    "wof:placetype":"venue"
},
  "geometry": {"coordinates":[-96.107793,32.345627],"type":"Point"}
}