{
  "type": "Feature",
  "properties": {
    "iso:country":"US",
    "sg:address":"2814 Aldine Bender Rd",
    "sg:city":"Houston",
    "sg:classifiers":[
        {
            "category":"Social Services",
            "type":"Services"
        }
    ],
    "sg:phone":"+1 281 442 7202",
    "sg:postcode":"77032",
    "sg:province":"TX",
    "wof:name":"Waymaker North Inc",
    "wof:placetype":"venue"
},
  "geometry": {"coordinates":[-95.33941799999999,29.930131],"type":"Point"}
}