{
  "type": "Feature",
  "properties": {
    "iso:country":"US",
    "sg:address":"16801 Gower St",
    "sg:city":"Pflugerville",
    "sg:classifiers":[
        {
            "category":"Organizations",
            "subcategory":"Professional Association",
            "type":"Services"
        }
    ],
    "sg:phone":"+1 512 251 9462",
    "sg:postcode":"78660",
    "sg:province":"TX",
    "wof:name":"Windermere Homeowners Assn",
    "wof:placetype":"venue"
},
  "geometry": {"coordinates":[-97.64023899999999,30.458062],"type":"Point"}
}