{
  "type": "Feature",
  "properties": {
    "iso:country":"US",
    "sg:address":"999 Peyton Rd",
    "sg:city":"El Paso",
    "sg:classifiers":[
        {
            "category":"Wholesale",
            "subcategory":"Auto Parts",
            "type":"Manufacturing & Wholesale Goods"
        }
    ],
    "sg:phone":"+1 915 852 2717",
    "sg:postcode":"79928",
    "sg:province":"TX",
    "sg:tags":[
        "automobile",
        "rebuilt"
    ],
    "wof:name":"Chihuahua Salvage",
    "wof:placetype":"venue"
},
  "geometry": {"coordinates":[-106.240252,31.668608],"type":"Point"}
}