{
  "type": "Feature",
  "properties": {
    "iso:country":"US",
    "sg:address":"604 W Church St",
    "sg:city":"Livingston",
    "sg:classifiers":[
        {
            "category":"Shopping",
            "type":"Retail Goods"
        }
    ],
    "sg:phone":"+1 936 291 1287",
    "sg:postcode":"77351",
    "sg:province":"TX",
    "sg:tags":[
        "ice"
    ],
    "wof:name":"Fair Ice Svc",
    "wof:placetype":"venue"
},
  "geometry": {"coordinates":[-94.93955200000001,30.711012],"type":"Point"}
}