{
  "type": "Feature",
  "properties": {
    "iso:country":"US",
    "sg:address":"2712 Webb Chapel Exn",
    "sg:city":"Dallas",
    "sg:classifiers":[
        {
            "category":"Bars & Pubs",
            "type":"Food & Drink"
        }
    ],
    "sg:phone":"+1 214 956 7600",
    "sg:postcode":"75220",
    "sg:province":"TX",
    "sg:tags":[
        "club",
        "night"
    ],
    "wof:name":"LA Guira Night Club",
    "wof:placetype":"venue"
},
  "geometry": {"coordinates":[-96.871516,32.855922],"type":"Point"}
}