{
  "type": "Feature",
  "properties": {
    "iso:country":"US",
    "sg:address":"5103 S Flores St",
    "sg:city":"San Antonio",
    "sg:classifiers":[
        {
            "category":"Food & Beverages",
            "subcategory":"Groceries & Convenience Stores",
            "type":"Retail Goods"
        }
    ],
    "sg:phone":"+1 210 923 7791",
    "sg:postcode":"78214",
    "sg:province":"TX",
    "wof:name":"La Fiest Supermarket 10",
    "wof:placetype":"venue"
},
  "geometry": {"coordinates":[-98.498734,29.374995],"type":"Point"}
}