{
  "type": "Feature",
  "properties": {
    "iso:country":"US",
    "sg:address":"576 Co Rd 3791",
    "sg:city":"Paradise",
    "sg:classifiers":[
        {
            "category":"Insurance",
            "subcategory":"Insurance Agent",
            "type":"Services"
        }
    ],
    "sg:phone":"+1 940 683 3540",
    "sg:postcode":"76073",
    "sg:province":"TX",
    "sg:tags":[
        "property",
        "casualty"
    ],
    "wof:name":"Bone Insurance Agency",
    "wof:placetype":"venue"
},
  "geometry": {"coordinates":[-97.74487499999999,33.043734],"type":"Point"}
}