{
  "type": "Feature",
  "properties": {
    "iso:country":"US",
    "sg:address":"7802 Hillcroft St",
    "sg:city":"Houston",
    "sg:classifiers":[
        {
            "category":"Autos & Motor Vehicles",
            "subcategory":"Fuel & Gas Station",
            "type":"Retail Goods"
        }
    ],
    "sg:phone":"+1 713 270 9042",
    "sg:postcode":"77081",
    "sg:province":"TX",
    "sg:tags":[
        "oil"
    ],
    "wof:name":"Neft Inc",
    "wof:placetype":"venue"
},
  "geometry": {"coordinates":[-95.493202,29.694599],"type":"Point"}
}