{
  "type": "Feature",
  "properties": {
    "iso:country":"US",
    "sg:address":"6412 Edgemere Blvd",
    "sg:city":"El Paso",
    "sg:classifiers":[
        {
            "category":"Real Estate",
            "subcategory":"Real Estate Operator",
            "type":"Services"
        }
    ],
    "sg:phone":"+1 915 779 1950",
    "sg:postcode":"79925",
    "sg:province":"TX",
    "sg:tags":[
        "building",
        "apartment"
    ],
    "wof:name":"Villa Alegre Apartments",
    "wof:placetype":"venue"
},
  "geometry": {"coordinates":[-106.40620699999999,31.783667],"type":"Point"}
}