{
  "type": "Feature",
  "properties": {
    "iso:country":"US",
    "sg:address":"3145 Tracy Ave",
    "sg:city":"Beaumont",
    "sg:classifiers":[
        {
            "category":"Professional",
            "subcategory":"Business Services",
            "type":"Services"
        }
    ],
    "sg:phone":"+1 409 833 6848",
    "sg:postcode":"77703",
    "sg:province":"TX",
    "wof:name":"Nelda C Dumas Notory",
    "wof:placetype":"venue"
},
  "geometry": {"coordinates":[-94.11121199999999,30.10944],"type":"Point"}
}