{
  "type": "Feature",
  "properties": {
    "iso:country":"US",
    "sg:address":"5000 Quorum Dr",
    "sg:city":"Dallas",
    "sg:classifiers":[
        {
            "category":"Shopping",
            "subcategory":"Computers & Home Electronics",
            "type":"Retail Goods"
        }
    ],
    "sg:phone":"+1 469 374 7666",
    "sg:postcode":"75254",
    "sg:province":"TX",
    "wof:name":"Mobius Partners",
    "wof:placetype":"venue"
},
  "geometry": {"coordinates":[-96.825504,32.948383],"type":"Point"}
}