{
  "type": "Feature",
  "properties": {
    "iso:country":"US",
    "sg:address":"8805 Jonquil Dr",
    "sg:city":"Waco",
    "sg:classifiers":[
        {
            "category":"Building & Trades",
            "subcategory":"Construction",
            "type":"Services"
        }
    ],
    "sg:phone":"+1 254 296 4605",
    "sg:postcode":"76708",
    "sg:province":"TX",
    "sg:tags":[
        "general",
        "contractor"
    ],
    "wof:name":"Frazier Family Homes",
    "wof:placetype":"venue"
},
  "geometry": {"coordinates":[-97.24489199999999,31.604632],"type":"Point"}
}