{
  "type": "Feature",
  "properties": {
    "iso:country":"US",
    "sg:address":"1700 George Bush Dr",
    "sg:city":"College Station",
    "sg:classifiers":[
        {
            "category":"Professional",
            "subcategory":"Computer Services",
            "type":"Services"
        }
    ],
    "sg:phone":"+1 979 846 4565",
    "sg:postcode":"77840",
    "sg:province":"TX",
    "sg:tags":[
        "programing",
        "related",
        "custom"
    ],
    "wof:name":"Dynamic Information Systems",
    "wof:placetype":"venue"
},
  "geometry": {"coordinates":[-96.324248,30.617822],"type":"Point"}
}