{
  "type": "Feature",
  "properties": {
    "iso:country":"US",
    "sg:address":"20210 Apache Gardens Ln",
    "sg:city":"Katy",
    "sg:classifiers":[
        {
            "category":"Building & Trades",
            "subcategory":"Construction",
            "type":"Services"
        }
    ],
    "sg:phone":"+1 281 398 4699",
    "sg:postcode":"77449",
    "sg:province":"TX",
    "sg:tags":[
        "carpentry",
        "contractor"
    ],
    "wof:name":"Affordable Overhead Doors Co",
    "wof:placetype":"venue"
},
  "geometry": {"coordinates":[-95.731926,29.796037],"type":"Point"}
}