{
  "type": "Feature",
  "properties": {
    "iso:country":"US",
    "sg:address":"2616 South Loop West Suite 625",
    "sg:city":"Houston",
    "sg:classifiers":[
        {
            "category":"Professional",
            "subcategory":"Lawyer & Legal Services",
            "type":"Services"
        }
    ],
    "sg:phone":"+1 713 665 4977",
    "sg:postcode":"77054",
    "sg:province":"TX",
    "sg:tags":[
        "litigation"
    ],
    "wof:name":"Citizen Law Firm",
    "wof:placetype":"venue"
},
  "geometry": {"coordinates":[-95.419898,29.67855],"type":"Point"}
}