{
  "type": "Feature",
  "properties": {
    "iso:country":"US",
    "sg:address":"8930 Chatsworth Dr",
    "sg:city":"Houston",
    "sg:classifiers":[
        {
            "category":"Professional",
            "subcategory":"Management & Consulting",
            "type":"Services"
        }
    ],
    "sg:phone":"+1 713 263 9688",
    "sg:postcode":"77024",
    "sg:province":"TX",
    "wof:name":"Zenith Consulting Corp",
    "wof:placetype":"venue"
},
  "geometry": {"coordinates":[-95.461431,29.780342],"type":"Point"}
}