{
  "type": "Feature",
  "properties": {
    "iso:country":"US",
    "sg:address":"424 Tarpey Rd",
    "sg:city":"Texas City",
    "sg:classifiers":[
        {
            "category":"Health Services",
            "subcategory":"Nursing And Care Facility",
            "type":"Services"
        }
    ],
    "sg:phone":"+1 409 938 8431",
    "sg:postcode":"77591",
    "sg:province":"TX",
    "sg:tags":[
        "home",
        "convalescent"
    ],
    "sg:website":"www.newbell.com",
    "wof:name":"Bay Oaks Health Care Ctr",
    "wof:placetype":"venue"
},
  "geometry": {"coordinates":[-95.004769,29.385866],"type":"Point"}
}