{
  "type": "Feature",
  "properties": {
    "iso:country":"US",
    "sg:address":"14432 Melody Ln",
    "sg:city":"Forney",
    "sg:classifiers":[
        {
            "category":"Education",
            "subcategory":"Vocational School",
            "type":"Public Place"
        }
    ],
    "sg:phone":"+1 972 564 4326",
    "sg:postcode":"75126",
    "sg:province":"TX",
    "sg:tags":[
        "processing",
        "datum"
    ],
    "wof:name":"Cyber Seniors USA",
    "wof:placetype":"venue"
},
  "geometry": {"coordinates":[-96.477919,32.731025],"type":"Point"}
}