{
  "type": "Feature",
  "properties": {
    "iso:country":"US",
    "sg:address":"114 S 20th St",
    "sg:city":"Corsicana",
    "sg:classifiers":[
        {
            "category":"Personal",
            "subcategory":"Beauty Salon",
            "type":"Services"
        }
    ],
    "sg:phone":"+1 903 872 1150",
    "sg:postcode":"75110",
    "sg:province":"TX",
    "sg:tags":[
        "hair",
        "stylist"
    ],
    "wof:name":"The Hair Bender",
    "wof:placetype":"venue"
},
  "geometry": {"coordinates":[-96.473833,32.088276],"type":"Point"}
}