{
  "type": "Feature",
  "properties": {
    "iso:country":"US",
    "sg:address":"4913 S 24th St",
    "sg:city":"Mcallen",
    "sg:classifiers":[
        {
            "category":"Building & Trades",
            "subcategory":"Pest Control",
            "type":"Services"
        }
    ],
    "sg:phone":"+1 956 683 7378",
    "sg:postcode":"78503",
    "sg:province":"TX",
    "wof:name":"Kill A Bug Pest Control",
    "wof:placetype":"venue"
},
  "geometry": {"coordinates":[-98.2539,26.162622],"type":"Point"}
}