{
  "type": "Feature",
  "properties": {
    "iso:country":"US",
    "sg:address":"1401 Enid Dr",
    "sg:city":"Vernon",
    "sg:classifiers":[
        {
            "category":"Professional",
            "subcategory":"Business Services",
            "type":"Services"
        }
    ],
    "sg:phone":"+1 817 996 9243",
    "sg:postcode":"76384",
    "sg:province":"TX",
    "sg:tags":[
        "liquidator"
    ],
    "wof:name":"Asset Buyers",
    "wof:placetype":"venue"
},
  "geometry": {"coordinates":[-99.27073,34.155548],"type":"Point"}
}