{
  "type": "Feature",
  "properties": {
    "iso:country":"US",
    "sg:address":"1204 Texas Ave",
    "sg:city":"El Paso",
    "sg:classifiers":[
        {
            "category":"Manufacturing",
            "subcategory":"Tools & Machinery",
            "type":"Manufacturing & Wholesale Goods"
        }
    ],
    "sg:phone":"+1 915 544 8780",
    "sg:postcode":"79901",
    "sg:province":"TX",
    "sg:tags":[
        "machine",
        "shop"
    ],
    "wof:name":"R's Industrial Machining",
    "wof:placetype":"venue"
},
  "geometry": {"coordinates":[-106.476755,31.765444],"type":"Point"}
}