{
  "type": "Feature",
  "properties": {
    "iso:country":"US",
    "sg:address":"10805 Telephone Rd",
    "sg:city":"Houston",
    "sg:classifiers":[
        {
            "category":"Retail",
            "subcategory":"Auto Repair",
            "type":"Services"
        }
    ],
    "sg:phone":"+1 713 987 2338",
    "sg:postcode":"77075",
    "sg:province":"TX",
    "sg:tags":[
        "repairing",
        "automobile"
    ],
    "wof:name":"C & C Auto Repair",
    "wof:placetype":"venue"
},
  "geometry": {"coordinates":[-95.285599,29.608801],"type":"Point"}
}