{
  "type": "Feature",
  "properties": {
    "iso:country":"US",
    "sg:address":"10405 Hartsook St",
    "sg:city":"Houston",
    "sg:classifiers":[
        {
            "category":"Wholesale",
            "subcategory":"Electrical",
            "type":"Manufacturing & Wholesale Goods"
        }
    ],
    "sg:phone":"+1 713 941 6500",
    "sg:postcode":"77034",
    "sg:province":"TX",
    "sg:tags":[
        "television"
    ],
    "wof:name":"Citadel Industries Inc",
    "wof:placetype":"venue"
},
  "geometry": {"coordinates":[-95.229451,29.634796],"type":"Point"}
}