{
  "type": "Feature",
  "properties": {
    "iso:country":"US",
    "sg:address":"302 S Friendswood Dr",
    "sg:city":"Friendswood",
    "sg:classifiers":[
        {
            "category":"Restaurant",
            "type":"Food & Drink"
        }
    ],
    "sg:menulink":"http://www.allmenus.com/tx/texas-city-league-city/202419-mcdonalds/menu/",
    "sg:postcode":"77546",
    "sg:province":"TX",
    "sg:tags":[
        "burger",
        "american"
    ],
    "wof:name":"McDonald's",
    "wof:placetype":"venue"
},
  "geometry": {"coordinates":[-95.20312199999999,29.530498],"type":"Point"}
}