{
  "type": "Feature",
  "properties": {
    "iso:country":"US",
    "sg:address":"4501 E Highway 377",
    "sg:city":"Granbury",
    "sg:classifiers":[
        {
            "category":"Building & Trades",
            "subcategory":"Plumbing",
            "type":"Services"
        }
    ],
    "sg:phone":"+1 817 573 2234",
    "sg:postcode":"76049",
    "sg:province":"TX",
    "sg:tags":[
        "plumber",
        "tank",
        "system",
        "septic"
    ],
    "wof:name":"Mowrey Wastewater Equipment",
    "wof:placetype":"venue"
},
  "geometry": {"coordinates":[-97.717033,32.462379],"type":"Point"}
}