{
  "type": "Feature",
  "properties": {
    "iso:country":"US",
    "sg:address":"4519 N Garfield St",
    "sg:city":"Midland",
    "sg:classifiers":[
        {
            "category":"Banks & Credit Unions",
            "subcategory":"Bank",
            "type":"Services"
        }
    ],
    "sg:phone":"+1 432 697 1226",
    "sg:postcode":"79705",
    "sg:province":"TX",
    "sg:tags":[
        "loan",
        "real estate"
    ],
    "sg:website":"www.countrywide.com",
    "wof:name":"Countrywide Home Loans",
    "wof:placetype":"venue"
},
  "geometry": {"coordinates":[-102.112869,32.037779],"type":"Point"}
}