{
  "type": "Feature",
  "properties": {
    "iso:country":"US",
    "sg:address":"505 Aileen Dr",
    "sg:city":"Red Oak",
    "sg:classifiers":[
        {
            "category":"Retail",
            "subcategory":"Repair Shop",
            "type":"Services"
        }
    ],
    "sg:phone":"+1 972 617 9244",
    "sg:postcode":"75154",
    "sg:province":"TX",
    "wof:name":"Tru Colors",
    "wof:placetype":"venue"
},
  "geometry": {"coordinates":[-96.788652,32.530291],"type":"Point"}
}