{
  "type": "Feature",
  "properties": {
    "iso:country":"US",
    "sg:address":"1800 N Galloway Ave Ste 200",
    "sg:city":"Mesquite",
    "sg:classifiers":[
        {
            "category":"Insurance",
            "subcategory":"Hazard Insurance",
            "type":"Services"
        }
    ],
    "sg:phone":"+1 972 285 8821",
    "sg:postcode":"75149",
    "sg:province":"TX",
    "sg:website":"www.bogueagency.com/",
    "wof:name":"State Farm Insurance - Scott Bogue",
    "wof:placetype":"venue"
},
  "geometry": {"coordinates":[-96.60579199999999,32.787262],"type":"Point"}
}