{
  "type": "Feature",
  "properties": {
    "iso:country":"US",
    "sg:address":"3706 E Walnut St",
    "sg:city":"Pearland",
    "sg:classifiers":[
        {
            "category":"Shopping",
            "subcategory":"Hobbies, Toys, & Games",
            "type":"Retail Goods"
        }
    ],
    "sg:phone":"+1 281 412 2677",
    "sg:postcode":"77581",
    "sg:province":"TX",
    "sg:tags":[
        "shop",
        "hobby",
        "model"
    ],
    "wof:name":"Ultimate Retail",
    "wof:placetype":"venue"
},
  "geometry": {"coordinates":[-95.28272800000001,29.559999],"type":"Point"}
}