{
  "type": "Feature",
  "properties": {
    "iso:country":"US",
    "sg:address":"8700 Stults Rd",
    "sg:city":"Dallas",
    "sg:classifiers":[
        {
            "category":"Education",
            "subcategory":"School",
            "type":"Public Place"
        }
    ],
    "sg:phone":"+1 469 593 2500",
    "sg:postcode":"75243",
    "sg:province":"TX",
    "sg:tags":[
        "high",
        "middle",
        "elementary"
    ],
    "sg:website":"www.richardson.k12.tx.us/adminis...",
    "wof:name":"Richardson Independent School District",
    "wof:placetype":"venue"
},
  "geometry": {"coordinates":[-96.754293,32.904702],"type":"Point"}
}