{
  "type": "Feature",
  "properties": {
    "iso:country":"US",
    "sg:address":"11661 Preston Rd Ste 154",
    "sg:city":"Dallas",
    "sg:classifiers":[
        {
            "category":"Science Facility",
            "type":"Public Place"
        }
    ],
    "sg:phone":"+1 214 365 9165",
    "sg:postcode":"75230",
    "sg:province":"TX",
    "sg:tags":[
        "development",
        "laboratories-research"
    ],
    "sg:website":"http://www.commoncares.org",
    "wof:name":"Common Cares Cancer Found",
    "wof:placetype":"venue"
},
  "geometry": {"coordinates":[-96.804248,32.90783],"type":"Point"}
}