{
  "type": "Feature",
  "properties": {
    "iso:country":"US",
    "sg:address":"3210 Belt Line Rd Ste 124",
    "sg:city":"Dallas",
    "sg:classifiers":[
        {
            "category":"Professional",
            "subcategory":"Computer Services",
            "type":"Services"
        }
    ],
    "sg:phone":"+1 972 361 4030",
    "sg:postcode":"75234",
    "sg:province":"TX",
    "sg:tags":[
        "repair"
    ],
    "wof:name":"Phoenix Networking Solutions",
    "wof:placetype":"venue"
},
  "geometry": {"coordinates":[-96.8685,32.948502],"type":"Point"}
}