{
  "type": "Feature",
  "properties": {
    "iso:country":"US",
    "sg:address":"307 N Wall St",
    "sg:city":"Iowa Park",
    "sg:classifiers":[
        {
            "category":"Mining & Drilling",
            "type":"Manufacturing & Wholesale Goods"
        }
    ],
    "sg:phone":"+1 940 592 5471",
    "sg:postcode":"76367",
    "sg:province":"TX",
    "sg:tags":[
        "oil",
        "well"
    ],
    "wof:name":"Spruiell Drilling Co Inc",
    "wof:placetype":"venue"
},
  "geometry": {"coordinates":[-98.667823,33.953184],"type":"Point"}
}