{
  "type": "Feature",
  "properties": {
    "iso:country":"US",
    "sg:address":"106 S Echols St",
    "sg:city":"Caldwell",
    "sg:classifiers":[
        {
            "category":"Real Estate",
            "subcategory":"Real Estate Services",
            "type":"Services"
        }
    ],
    "sg:phone":"+1 979 567 3251",
    "sg:postcode":"77836",
    "sg:province":"TX",
    "sg:tags":[
        "company",
        "title"
    ],
    "wof:name":"Caperton & Towslee Title Co",
    "wof:placetype":"venue"
},
  "geometry": {"coordinates":[-96.69332799999999,30.531343],"type":"Point"}
}