{
  "type": "Feature",
  "properties": {
    "iso:country":"US",
    "sg:address":"11900 Metric Boulevard Suite L",
    "sg:city":"Austin",
    "sg:classifiers":[
        {
            "category":"Food & Beverages",
            "subcategory":"Groceries & Convenience Stores",
            "type":"Retail Goods"
        }
    ],
    "sg:phone":"+1 512 833 6977",
    "sg:postcode":"78758",
    "sg:province":"TX",
    "wof:name":"Dandy's 5",
    "wof:placetype":"venue"
},
  "geometry": {"coordinates":[-97.70402,30.39916],"type":"Point"}
}