{
  "type": "Feature",
  "properties": {
    "iso:country":"US",
    "sg:address":"5630 Richmond Ave",
    "sg:city":"Houston",
    "sg:classifiers":[
        {
            "category":"Food & Beverages",
            "subcategory":"Liquor & Beverages",
            "type":"Retail Goods"
        }
    ],
    "sg:phone":"+1 713 783 3344",
    "sg:postcode":"77057",
    "sg:province":"TX",
    "sg:tags":[
        "beer",
        "spirit",
        "wine"
    ],
    "sg:website":"www.richardsliquors.com",
    "wof:name":"RICHARD'S LIQUORS & FINE WINES",
    "wof:placetype":"venue"
},
  "geometry": {"coordinates":[-95.47763,29.731747],"type":"Point"}
}