{
  "type": "Feature",
  "properties": {
    "iso:country":"US",
    "sg:address":"8491 US Hwy 277",
    "sg:city":"Hawley",
    "sg:classifiers":[
        {
            "category":"Building & Trades",
            "subcategory":"Construction",
            "type":"Services"
        }
    ],
    "sg:phone":"+1 325 537 2949",
    "sg:postcode":"79525",
    "sg:province":"TX",
    "sg:tags":[
        "excavation",
        "contractor"
    ],
    "wof:name":"Kenneth Walker Dozer Services",
    "wof:placetype":"venue"
},
  "geometry": {"coordinates":[-99.773934,32.546377],"type":"Point"}
}