{
  "type": "Feature",
  "properties": {
    "iso:country":"US",
    "sg:address":"800 E Pike Blvd",
    "sg:city":"Weslaco",
    "sg:classifiers":[
        {
            "category":"Food & Beverages",
            "subcategory":"Bakery",
            "type":"Retail Goods"
        }
    ],
    "sg:phone":"+1 956 968 9854",
    "sg:postcode":"78596",
    "sg:province":"TX",
    "sg:tags":[
        "baker"
    ],
    "wof:name":"El Mexicano Bakery",
    "wof:placetype":"venue"
},
  "geometry": {"coordinates":[-97.980817,26.170106],"type":"Point"}
}