{
  "type": "Feature",
  "properties": {
    "iso:country":"US",
    "sg:address":"1549 Mountain Laurel Ln",
    "sg:city":"Desoto",
    "sg:classifiers":[
        {
            "category":"Real Estate",
            "subcategory":"Real Estate Agent",
            "type":"Services"
        }
    ],
    "sg:phone":"+1 972 230 4150",
    "sg:postcode":"75115",
    "sg:province":"TX",
    "wof:name":"Real Estate By Letitia",
    "wof:placetype":"venue"
},
  "geometry": {"coordinates":[-96.89859199999999,32.584911],"type":"Point"}
}