{
  "type": "Feature",
  "properties": {
    "iso:country":"US",
    "sg:address":"9202 Converse Business Ln",
    "sg:city":"Converse",
    "sg:classifiers":[
        {
            "category":"Retail",
            "subcategory":"Repair Shop",
            "type":"Services"
        }
    ],
    "sg:phone":"+1 210 945 9633",
    "sg:postcode":"78109",
    "sg:province":"TX",
    "sg:tags":[
        "rebuild",
        "industrial",
        "machinery"
    ],
    "wof:name":"Tenntex Sales Service Co Inc",
    "wof:placetype":"venue"
},
  "geometry": {"coordinates":[-98.304535,29.51319],"type":"Point"}
}