{
  "type": "Feature",
  "properties": {
    "iso:country":"US",
    "sg:address":"7457 Harwin Dr",
    "sg:city":"Houston",
    "sg:classifiers":[
        {
            "category":"Professional",
            "type":"Services"
        }
    ],
    "sg:phone":"+1 832 252 8399",
    "sg:postcode":"77036",
    "sg:province":"TX",
    "sg:tags":[
        "establishment"
    ],
    "wof:name":"June Star Inc",
    "wof:placetype":"venue"
},
  "geometry": {"coordinates":[-95.515283,29.717593],"type":"Point"}
}