{
  "type": "Feature",
  "properties": {
    "iso:country":"US",
    "sg:address":"4393 Sunbelt Dr",
    "sg:city":"Addison",
    "sg:classifiers":[
        {
            "category":"Real Estate",
            "subcategory":"Real Estate Agent",
            "type":"Services"
        }
    ],
    "sg:phone":"+1 972 248 0637",
    "sg:postcode":"75001",
    "sg:province":"TX",
    "wof:name":"Polaris Realty Investments",
    "wof:placetype":"venue"
},
  "geometry": {"coordinates":[-96.836049,32.977224],"type":"Point"}
}