{
  "type": "Feature",
  "properties": {
    "iso:country":"US",
    "sg:address":"109 E Main St",
    "sg:city":"Henderson",
    "sg:classifiers":[
        {
            "category":"Banks & Credit Unions",
            "subcategory":"Investment Brokerage",
            "type":"Services"
        }
    ],
    "sg:phone":"+1 903 657 6539",
    "sg:postcode":"75652",
    "sg:province":"TX",
    "wof:name":"Afford Investments",
    "wof:placetype":"venue"
},
  "geometry": {"coordinates":[-94.79942800000001,32.153317],"type":"Point"}
}