{
  "type": "Feature",
  "properties": {
    "iso:country":"US",
    "sg:address":"10934 Tulip Garden Ct",
    "sg:city":"Houston",
    "sg:classifiers":[
        {
            "category":"Banks & Credit Unions",
            "subcategory":"Investment Brokerage",
            "type":"Services"
        }
    ],
    "sg:phone":"+1 281 894 1837",
    "sg:postcode":"77065",
    "sg:province":"TX",
    "sg:tags":[
        "advisory"
    ],
    "wof:name":"Sinta Financial Services Inc",
    "wof:placetype":"venue"
},
  "geometry": {"coordinates":[-95.617858,29.929681],"type":"Point"}
}