{
  "type": "Feature",
  "properties": {
    "iso:country":"US",
    "sg:address":"3673 Westcenter Dr",
    "sg:city":"Houston",
    "sg:classifiers":[
        {
            "category":"Real Estate",
            "subcategory":"Real Estate Agent",
            "type":"Services"
        }
    ],
    "sg:phone":"+1 713 334 3040",
    "sg:postcode":"77042",
    "sg:province":"TX",
    "sg:tags":[
        "appraiser"
    ],
    "wof:name":"East West Appraisal Svc",
    "wof:placetype":"venue"
},
  "geometry": {"coordinates":[-95.55389,29.724365],"type":"Point"}
}