{
  "type": "Feature",
  "properties": {
    "iso:country":"US",
    "sg:address":"501 Schilling St",
    "sg:city":"Baytown",
    "sg:classifiers":[
        {
            "category":"Arts & Performance",
            "subcategory":"Theater",
            "type":"Entertainment"
        }
    ],
    "sg:phone":"+1 281 420 1218",
    "sg:postcode":"77520",
    "sg:province":"TX",
    "sg:tags":[
        "entertainers-family",
        "group",
        "business"
    ],
    "wof:name":"Ghetto Dreamz Productions",
    "wof:placetype":"venue"
},
  "geometry": {"coordinates":[-94.971039,29.74901],"type":"Point"}
}