{
  "type": "Feature",
  "properties": {
    "iso:country":"US",
    "sg:address":"8678 Louetta Rd",
    "sg:city":"Spring",
    "sg:classifiers":[
        {
            "category":"Health Services",
            "subcategory":"Doctor",
            "type":"Services"
        }
    ],
    "sg:phone":"+1 281 444 3033",
    "sg:postcode":"77379",
    "sg:province":"TX",
    "wof:name":"Leblanc Kelly M",
    "wof:placetype":"venue"
},
  "geometry": {"coordinates":[-95.541546,30.011249],"type":"Point"}
}