{
  "type": "Feature",
  "properties": {
    "iso:country":"US",
    "sg:address":"9506 Bamboo Rd",
    "sg:city":"Houston",
    "sg:classifiers":[
        {
            "category":"Autos & Motor Vehicles",
            "subcategory":"Auto Supplies",
            "type":"Retail Goods"
        },
        {
            "category":"Wholesale",
            "subcategory":"Auto Parts",
            "type":"Manufacturing & Wholesale Goods"
        }
    ],
    "sg:phone":"+1 713 460 5078",
    "sg:postcode":"77041",
    "sg:province":"TX",
    "sg:tags":[
        "wheel",
        "automotive",
        "cover"
    ],
    "sg:website":"www.americaneaglewheel.com",
    "wof:name":"American Eagle Wheel Corp",
    "wof:placetype":"venue"
},
  "geometry": {"coordinates":[-95.52959799999999,29.848315],"type":"Point"}
}