{
  "type": "Feature",
  "properties": {
    "iso:country":"US",
    "sg:address":"1500 Buena Vista Dr",
    "sg:city":"Denton",
    "sg:classifiers":[
        {
            "category":"Building & Trades",
            "subcategory":"Construction",
            "type":"Services"
        }
    ],
    "sg:phone":"+1 214 668 4638",
    "sg:postcode":"76210",
    "sg:province":"TX",
    "sg:tags":[
        "residential"
    ],
    "wof:name":"Marroquin Circle M Enterprise",
    "wof:placetype":"venue"
},
  "geometry": {"coordinates":[-97.11635699999999,33.147745],"type":"Point"}
}