{
  "type": "Feature",
  "properties": {
    "iso:country":"US",
    "sg:address":"2308 Spurlock Rd",
    "sg:city":"Nederland",
    "sg:classifiers":[
        {
            "category":"Autos & Motor Vehicles",
            "subcategory":"Automobile Sales",
            "type":"Retail Goods"
        },
        {
            "category":"Autos & Motor Vehicles",
            "subcategory":"Auto Supplies",
            "type":"Retail Goods"
        },
        {
            "category":"Shopping",
            "subcategory":"Discount & Variety Stores",
            "type":"Retail Goods"
        },
        {
            "category":"Wholesale",
            "subcategory":"Auto Parts",
            "type":"Manufacturing & Wholesale Goods"
        }
    ],
    "sg:phone":"+1 409 727 5679",
    "sg:postcode":"77627",
    "sg:province":"TX",
    "sg:tags":[
        "surplus",
        "rebuilt-wholesale",
        "supplies-used",
        "rebuilt",
        "salvage",
        "merchandise",
        "manufacturer"
    ],
    "wof:name":"American Auto Salvage",
    "wof:placetype":"venue"
},
  "geometry": {"coordinates":[-94.01642699999999,29.980076],"type":"Point"}
}