{
  "type": "Feature",
  "properties": {
    "iso:country":"US",
    "sg:address":"1909 Hollister St",
    "sg:city":"Houston",
    "sg:classifiers":[
        {
            "category":"Building & Trades",
            "subcategory":"Plumbing",
            "type":"Services"
        }
    ],
    "sg:phone":"+1 713 465 0667",
    "sg:postcode":"77080",
    "sg:province":"TX",
    "sg:tags":[
        "contractor"
    ],
    "wof:name":"Bill Roberts Co",
    "wof:placetype":"venue"
},
  "geometry": {"coordinates":[-95.50662199999999,29.80763],"type":"Point"}
}