{
  "type": "Feature",
  "properties": {
    "iso:country":"US",
    "sg:address":"8511 Copperbluff",
    "sg:city":"Converse",
    "sg:classifiers":[
        {
            "category":"Personal",
            "type":"Services"
        }
    ],
    "sg:phone":"+1 210 659 8683",
    "sg:postcode":"78109",
    "sg:province":"TX",
    "sg:tags":[
        "equipment"
    ],
    "wof:name":"Jupiter Jumps",
    "wof:placetype":"venue"
},
  "geometry": {"coordinates":[-98.295141,29.508185],"type":"Point"}
}