{
  "type": "Feature",
  "properties": {
    "iso:country":"US",
    "sg:address":"508 S Van Buren St",
    "sg:city":"Henderson",
    "sg:classifiers":[
        {
            "category":"Food & Beverages",
            "subcategory":"Groceries & Convenience Stores",
            "type":"Retail Goods"
        },
        {
            "category":"Shopping",
            "subcategory":"Tobacco",
            "type":"Retail Goods"
        },
        {
            "category":"Autos & Motor Vehicles",
            "subcategory":"Fuel & Gas Station",
            "type":"Retail Goods"
        }
    ],
    "sg:phone":"+1 903 657 9621",
    "sg:postcode":"75654",
    "sg:province":"TX",
    "sg:tags":[
        "cigarette",
        "station",
        "cigar",
        "gasoline",
        "dealer"
    ],
    "wof:name":"Brookshire Brothers Tobacco",
    "wof:placetype":"venue"
},
  "geometry": {"coordinates":[-94.80116700000001,32.147548],"type":"Point"}
}