{
  "type": "Feature",
  "properties": {
    "iso:country":"US",
    "sg:address":"22114 Gosling Rd",
    "sg:city":"Spring",
    "sg:classifiers":[
        {
            "category":"Building & Trades",
            "subcategory":"Plumbing",
            "type":"Services"
        },
        {
            "category":"Home & Garden",
            "subcategory":"Garden Supply",
            "type":"Retail Goods"
        }
    ],
    "sg:phone":"+1 281 353 0881",
    "sg:postcode":"77389",
    "sg:province":"TX",
    "sg:tags":[
        "sprinkler",
        "contractor"
    ],
    "sg:website":"www.diverseirrigation.com",
    "wof:name":"Diverse Irrigation Group Inc",
    "wof:placetype":"venue"
},
  "geometry": {"coordinates":[-95.506923,30.087543],"type":"Point"}
}