{
  "type": "Feature",
  "properties": {
    "iso:country":"US",
    "sg:address":"8127 Sweetgum Trace Dr",
    "sg:city":"Houston",
    "sg:classifiers":[
        {
            "category":"Personal",
            "type":"Services"
        }
    ],
    "sg:phone":"+1 713 466 9866",
    "sg:postcode":"77040",
    "sg:province":"TX",
    "sg:tags":[
        "dating"
    ],
    "sg:website":"www.tlcworldwide.net",
    "wof:name":"TLC Worldwide Inc",
    "wof:placetype":"venue"
},
  "geometry": {"coordinates":[-95.51552100000001,29.885777],"type":"Point"}
}