{
  "type": "Feature",
  "properties": {
    "iso:country":"US",
    "sg:address":"503 S 25th St",
    "sg:city":"Temple",
    "sg:classifiers":[
        {
            "category":"Building & Trades",
            "subcategory":"Construction",
            "type":"Services"
        }
    ],
    "sg:phone":"+1 254 771 5500",
    "sg:postcode":"76504",
    "sg:province":"TX",
    "sg:tags":[
        "altering",
        "builder",
        "contractor",
        "remodeling",
        "deck"
    ],
    "wof:name":"Richard Stearns Deck's-Patio's",
    "wof:placetype":"venue"
},
  "geometry": {"coordinates":[-97.356055,31.095274],"type":"Point"}
}