{
  "type": "Feature",
  "properties": {
    "iso:country":"US",
    "sg:address":"105 N Llano St",
    "sg:city":"Fredericksburg",
    "sg:classifiers":[
        {
            "category":"Food & Beverages",
            "subcategory":"Candy",
            "type":"Retail Goods"
        }
    ],
    "sg:phone":"+1 830 997 0533",
    "sg:postcode":"78624",
    "sg:province":"TX",
    "sg:tags":[
        "confectionery"
    ],
    "sg:website":"www.fbgfudge.com",
    "wof:name":"Fredericksburg Fudge",
    "wof:placetype":"venue"
},
  "geometry": {"coordinates":[-98.869525,30.27486],"type":"Point"}
}