{
  "type": "Feature",
  "properties": {
    "iso:country":"US",
    "sg:address":"5000 Bowser Ave",
    "sg:city":"Dallas",
    "sg:classifiers":[
        {
            "category":"Real Estate",
            "subcategory":"Real Estate Operator",
            "type":"Services"
        }
    ],
    "sg:phone":"+1 214 520 9907",
    "sg:postcode":"75209",
    "sg:province":"TX",
    "sg:tags":[
        "building",
        "apartment"
    ],
    "wof:name":"New Oasis Apartments",
    "wof:placetype":"venue"
},
  "geometry": {"coordinates":[-96.818917,32.825],"type":"Point"}
}