{
  "type": "Feature",
  "properties": {
    "iso:country":"US",
    "sg:address":"12015 Indian Wells Dr",
    "sg:city":"Houston",
    "sg:classifiers":[
        {
            "category":"Retail",
            "subcategory":"Portrait Studio",
            "type":"Services"
        }
    ],
    "sg:phone":"+1 281 444 4499",
    "sg:postcode":"77066",
    "sg:province":"TX",
    "sg:tags":[
        "photo"
    ],
    "wof:name":"Bill Franklin Photography",
    "wof:placetype":"venue"
},
  "geometry": {"coordinates":[-95.51054600000001,29.965396],"type":"Point"}
}