{
  "type": "Feature",
  "properties": {
    "iso:country":"US",
    "sg:address":"2808 Walnut Ln",
    "sg:city":"Hurst",
    "sg:classifiers":[
        {
            "category":"Banks & Credit Unions",
            "subcategory":"Bank",
            "type":"Services"
        }
    ],
    "sg:phone":"+1 817 577 4245",
    "sg:postcode":"76054",
    "sg:province":"TX",
    "sg:tags":[
        "loan",
        "real estate"
    ],
    "sg:website":"www.amaloans.com",
    "wof:name":"American Mortgage Specialists",
    "wof:placetype":"venue"
},
  "geometry": {"coordinates":[-97.172433,32.871046],"type":"Point"}
}