{
  "type": "Feature",
  "properties": {
    "iso:country":"US",
    "sg:address":"815 Simon Dr",
    "sg:city":"Cedar Hill",
    "sg:classifiers":[
        {
            "category":"Professional",
            "subcategory":"Computer Services",
            "type":"Services"
        }
    ],
    "sg:phone":"+1 972 291 6737",
    "sg:postcode":"75104",
    "sg:province":"TX",
    "sg:tags":[
        "prepackaged",
        "software"
    ],
    "wof:name":"MBB Solutions",
    "wof:placetype":"venue"
},
  "geometry": {"coordinates":[-96.93073699999999,32.574574],"type":"Point"}
}