{
  "type": "Feature",
  "properties": {
    "iso:country":"US",
    "sg:address":"1121 Willard St",
    "sg:city":"Houston",
    "sg:classifiers":[
        {
            "category":"Professional",
            "type":"Services"
        }
    ],
    "sg:phone":"+1 713 529 3691",
    "sg:postcode":"77006",
    "sg:province":"TX",
    "wof:name":"Zeitbauen",
    "wof:placetype":"venue"
},
  "geometry": {"coordinates":[-95.39338499999999,29.751003],"type":"Point"}
}