{
  "type": "Feature",
  "properties": {
    "iso:country":"US",
    "sg:address":"1017 Churchill Rd",
    "sg:city":"Fort Worth",
    "sg:classifiers":[
        {
            "category":"Shopping",
            "type":"Retail Goods"
        }
    ],
    "sg:phone":"+1 817 625 5872",
    "sg:postcode":"76114",
    "sg:province":"TX",
    "sg:tags":[
        "merchandise"
    ],
    "wof:name":"Violas Custom Drapery",
    "wof:placetype":"venue"
},
  "geometry": {"coordinates":[-97.389718,32.776893],"type":"Point"}
}