{
  "type": "Feature",
  "properties": {
    "iso:country":"US",
    "sg:address":"634 Crystal City Hwy",
    "sg:city":"Uvalde",
    "sg:classifiers":[
        {
            "category":"Food & Beverages",
            "subcategory":"Groceries & Convenience Stores",
            "type":"Retail Goods"
        },
        {
            "category":"Food & Beverages",
            "subcategory":"Liquor & Beverages",
            "type":"Retail Goods"
        }
    ],
    "sg:phone":"+1 830 591 0706",
    "sg:postcode":"78801",
    "sg:province":"TX",
    "sg:tags":[
        "alcoholic"
    ],
    "wof:name":"Felipe's Beverage Barn",
    "wof:placetype":"venue"
},
  "geometry": {"coordinates":[-99.79032599999999,29.19116],"type":"Point"}
}