{
  "type": "Feature",
  "properties": {
    "iso:country":"US",
    "sg:address":"1901 Village Court Ln",
    "sg:city":"Rosenberg",
    "sg:classifiers":[
        {
            "category":"Professional",
            "subcategory":"Employment Agencies",
            "type":"Services"
        }
    ],
    "sg:phone":"+1 281 239 7710",
    "sg:postcode":"77471",
    "sg:province":"TX",
    "wof:name":"Verdict Search Texas",
    "wof:placetype":"venue"
},
  "geometry": {"coordinates":[-95.77842099999999,29.551501],"type":"Point"}
}