{
  "type": "Feature",
  "properties": {
    "iso:country":"US",
    "sg:address":"778 Fish Farm Rd",
    "sg:city":"Orange",
    "sg:classifiers":[
        {
            "category":"Building & Trades",
            "subcategory":"Plumbing",
            "type":"Services"
        }
    ],
    "sg:phone":"+1 409 886 1726",
    "sg:postcode":"77632",
    "sg:province":"TX",
    "sg:tags":[
        "contractor"
    ],
    "wof:name":"Davids AC & Htg Sls & Svc",
    "wof:placetype":"venue"
},
  "geometry": {"coordinates":[-93.82007,30.121585],"type":"Point"}
}