{
  "type": "Feature",
  "properties": {
    "iso:country":"US",
    "sg:address":"611 S Clay St",
    "sg:city":"Ennis",
    "sg:classifiers":[
        {
            "category":"Professional",
            "subcategory":"Accounting & Tax Preparation",
            "type":"Services"
        }
    ],
    "sg:phone":"+1 972 878 2611",
    "sg:postcode":"75119",
    "sg:province":"TX",
    "sg:tags":[
        "accountant"
    ],
    "sg:website":"www.wywcpa.com",
    "wof:name":"Witherspoon Yendell & Wilson",
    "wof:placetype":"venue"
},
  "geometry": {"coordinates":[-96.630036,32.32096],"type":"Point"}
}