{
  "type": "Feature",
  "properties": {
    "iso:country":"US",
    "sg:address":"11450 Eastex Fwy",
    "sg:city":"Beaumont",
    "sg:classifiers":[
        {
            "category":"Manufacturing",
            "subcategory":"Food",
            "type":"Manufacturing & Wholesale Goods"
        }
    ],
    "sg:phone":"+1 409 899 5080",
    "sg:postcode":"77708",
    "sg:province":"TX",
    "sg:tags":[
        "bottler"
    ],
    "wof:name":"Coca-Cola Bottling Co",
    "wof:placetype":"venue"
},
  "geometry": {"coordinates":[-94.185205,30.174976],"type":"Point"}
}