{
  "type": "Feature",
  "properties": {
    "iso:country":"US",
    "sg:address":"7500 Fall Creek Hwy",
    "sg:city":"Granbury",
    "sg:classifiers":[
        {
            "category":"Recreation",
            "type":"Entertainment"
        }
    ],
    "sg:phone":"+1 817 326 4677",
    "sg:postcode":"76049",
    "sg:province":"TX",
    "sg:tags":[
        "club",
        "membership"
    ],
    "wof:name":"Pecan Plantation Security Gate",
    "wof:placetype":"venue"
},
  "geometry": {"coordinates":[-97.655084,32.396983],"type":"Point"}
}