{
  "type": "Feature",
  "properties": {
    "iso:country":"US",
    "sg:address":"2313 Brookhollow Plaza Dr",
    "sg:city":"Arlington",
    "sg:classifiers":[
        {
            "category":"Wholesale",
            "subcategory":"Electrical",
            "type":"Manufacturing & Wholesale Goods"
        }
    ],
    "sg:phone":"+1 817 640 8200",
    "sg:postcode":"76006",
    "sg:province":"TX",
    "sg:tags":[
        "rep",
        "parts",
        "electronic",
        "mfg"
    ],
    "wof:name":"Comptech Sales Inc",
    "wof:placetype":"venue"
},
  "geometry": {"coordinates":[-97.071367,32.763466],"type":"Point"}
}