{
  "type": "Feature",
  "properties": {
    "iso:country":"US",
    "sg:address":"6347 Tally Gate",
    "sg:city":"San Antonio",
    "sg:classifiers":[
        {
            "category":"Building & Trades",
            "subcategory":"Construction",
            "type":"Services"
        }
    ],
    "sg:phone":"+1 210 520 3291",
    "sg:postcode":"78240",
    "sg:province":"TX",
    "sg:tags":[
        "house"
    ],
    "wof:name":"Kbh Home Repair",
    "wof:placetype":"venue"
},
  "geometry": {"coordinates":[-98.605277,29.505579],"type":"Point"}
}