{
  "type": "Feature",
  "properties": {
    "iso:country":"US",
    "sg:address":"4115 N Kings Hwy",
    "sg:city":"Texarkana",
    "sg:classifiers":[
        {
            "category":"Restaurant",
            "type":"Food & Drink"
        }
    ],
    "sg:phone":"+1 903 223 0841",
    "sg:postcode":"75503",
    "sg:province":"TX",
    "wof:name":"Dixie Diner",
    "wof:placetype":"venue"
},
  "geometry": {"coordinates":[-94.13116599999999,33.458217],"type":"Point"}
}