{
  "type": "Feature",
  "properties": {
    "iso:country":"US",
    "sg:address":"702 N Main St",
    "sg:city":"Victoria",
    "sg:classifiers":[
        {
            "category":"Government",
            "subcategory":"Office",
            "type":"Public Place"
        }
    ],
    "sg:phone":"+1 361 572 2722",
    "sg:postcode":"77901",
    "sg:province":"TX",
    "sg:tags":[
        "village"
    ],
    "wof:name":"Victoria Engineering",
    "wof:placetype":"venue"
},
  "geometry": {"coordinates":[-97.003445,28.805424],"type":"Point"}
}