{
  "type": "Feature",
  "properties": {
    "iso:country":"US",
    "sg:address":"7659 Preston Rd",
    "sg:city":"Frisco",
    "sg:classifiers":[
        {
            "category":"Organizations",
            "subcategory":"Religious Organization",
            "type":"Services"
        }
    ],
    "sg:phone":"+1 972 377 2146",
    "sg:postcode":"75034",
    "sg:province":"TX",
    "sg:tags":[
        "church"
    ],
    "sg:website":"www.friscofumc.org",
    "wof:name":"First United Methodist Church",
    "wof:placetype":"venue"
},
  "geometry": {"coordinates":[-96.80473499999999,33.143096],"type":"Point"}
}