{
  "type": "Feature",
  "properties": {
    "iso:country":"US",
    "sg:address":"813 E 4th St",
    "sg:city":"Monahans",
    "sg:classifiers":[
        {
            "category":"Health Services",
            "subcategory":"Doctor",
            "type":"Services"
        }
    ],
    "sg:phone":"+1 432 943 6785",
    "sg:postcode":"79756",
    "sg:province":"TX",
    "sg:tags":[
        "physician",
        "surgeon"
    ],
    "wof:name":"Hoon Rowe MD",
    "wof:placetype":"venue"
},
  "geometry": {"coordinates":[-102.88284,31.594594],"type":"Point"}
}