{
  "type": "Feature",
  "properties": {
    "iso:country":"US",
    "sg:address":"6630 Glendora Ave",
    "sg:city":"Dallas",
    "sg:classifiers":[
        {
            "category":"Health Services",
            "subcategory":"Health Practitioner",
            "type":"Services"
        }
    ],
    "sg:phone":"+1 469 232 9947",
    "sg:postcode":"75230",
    "sg:province":"TX",
    "sg:tags":[
        "info",
        "eating",
        "disorder",
        "treatment"
    ],
    "wof:name":"Human Solutions",
    "wof:placetype":"venue"
},
  "geometry": {"coordinates":[-96.791735,32.885171],"type":"Point"}
}