{
  "type": "Feature",
  "properties": {
    "iso:country":"US",
    "sg:address":"10201 Gateway Blvd W",
    "sg:city":"El Paso",
    "sg:classifiers":[
        {
            "category":"Health Services",
            "subcategory":"Doctor",
            "type":"Services"
        }
    ],
    "sg:phone":"+1 915 593 9800",
    "sg:postcode":"79935",
    "sg:province":"TX",
    "sg:tags":[
        "physician",
        "surgeon"
    ],
    "wof:name":"Halsted Surgical Assoc",
    "wof:placetype":"venue"
},
  "geometry": {"coordinates":[-106.354128,31.758627],"type":"Point"}
}