{
  "type": "Feature",
  "properties": {
    "iso:country":"US",
    "sg:address":"2611 Howellwood Way",
    "sg:city":"Austin",
    "sg:classifiers":[
        {
            "category":"Building & Trades",
            "subcategory":"Construction",
            "type":"Services"
        }
    ],
    "sg:phone":"+1 512 903 0470",
    "sg:postcode":"78748",
    "sg:province":"TX",
    "sg:tags":[
        "painter"
    ],
    "sg:website":"athenapaint.com/",
    "wof:name":"Athena Paint Company",
    "wof:placetype":"venue"
},
  "geometry": {"coordinates":[-97.834059,30.175779],"type":"Point"}
}