{
  "type": "Feature",
  "properties": {
    "iso:country":"US",
    "sg:address":"63 Sunset Lake Rd Ste A",
    "sg:city":"Huntsville",
    "sg:classifiers":[
        {
            "category":"Retail",
            "subcategory":"Laundry & Dry Cleaning",
            "type":"Services"
        },
        {
            "category":"Building & Trades",
            "subcategory":"Cleaning & Sanitation",
            "type":"Services"
        }
    ],
    "sg:phone":"+1 936 291 0968",
    "sg:postcode":"77340",
    "sg:province":"TX",
    "sg:tags":[
        "cleaner",
        "fire",
        "damage",
        "rug",
        "water",
        "restoration",
        "carpet"
    ],
    "sg:website":"http://www.rainbowintl.com",
    "wof:name":"Rainbow International",
    "wof:placetype":"venue"
},
  "geometry": {"coordinates":[-95.575822,30.652489],"type":"Point"}
}