{
  "type": "Feature",
  "properties": {
    "iso:country":"US",
    "sg:address":"3007 N Lamar Blvd",
    "sg:city":"Austin",
    "sg:classifiers":[
        {
            "category":"Food & Beverages",
            "subcategory":"Liquor & Beverages",
            "type":"Retail Goods"
        }
    ],
    "sg:phone":"+1 512 236 0060",
    "sg:postcode":"78705",
    "sg:province":"TX",
    "wof:name":"Coursetrends",
    "wof:placetype":"venue"
},
  "geometry": {"coordinates":[-97.746674,30.299509],"type":"Point"}
}