{
  "type": "Feature",
  "properties": {
    "iso:country":"US",
    "sg:address":"1000 Pueblo St",
    "sg:city":"Odessa",
    "sg:classifiers":[
        {
            "category":"Building & Trades",
            "subcategory":"Landscaping Services",
            "type":"Services"
        }
    ],
    "sg:phone":"+1 432 580 0110",
    "sg:postcode":"79761",
    "sg:province":"TX",
    "sg:tags":[
        "landscape",
        "contractor"
    ],
    "wof:name":"Basin Wood & Lawn Co",
    "wof:placetype":"venue"
},
  "geometry": {"coordinates":[-102.33053700000001,31.865641],"type":"Point"}
}