{
  "type": "Feature",
  "properties": {
    "iso:country":"US",
    "sg:address":"10003 Derringer Trl",
    "sg:city":"Austin",
    "sg:classifiers":[
        {
            "category":"Restaurant",
            "type":"Food & Drink"
        }
    ],
    "sg:phone":"+1 512 834 8982",
    "sg:postcode":"78753",
    "sg:province":"TX",
    "sg:tags":[
        "eating"
    ],
    "wof:name":"Taqueria Y Restaurant Losalto",
    "wof:placetype":"venue"
},
  "geometry": {"coordinates":[-97.687826,30.367686],"type":"Point"}
}