{
  "type": "Feature",
  "properties": {
    "iso:country":"US",
    "sg:address":"141 N Church St",
    "sg:city":"Winters",
    "sg:classifiers":[
        {
            "category":"Organizations",
            "subcategory":"Religious Organization",
            "type":"Services"
        }
    ],
    "sg:phone":"+1 325 754 5213",
    "sg:postcode":"79567",
    "sg:province":"TX",
    "wof:name":"1st United Methodist Church",
    "wof:placetype":"venue"
},
  "geometry": {"coordinates":[-99.964279,31.958516],"type":"Point"}
}