{
  "type": "Feature",
  "properties": {
    "iso:country":"US",
    "sg:address":"2434 Brockton St",
    "sg:city":"San Antonio",
    "sg:classifiers":[
        {
            "category":"Shopping",
            "type":"Retail Goods"
        }
    ],
    "sg:phone":"+1 210 822 8387",
    "sg:postcode":"78217",
    "sg:province":"TX",
    "sg:tags":[
        "equipment",
        "medical",
        "rental",
        "merchandise"
    ],
    "wof:name":"Choice One Medical Equipment",
    "wof:placetype":"venue"
},
  "geometry": {"coordinates":[-98.45194499999999,29.529944],"type":"Point"}
}