{
  "type": "Feature",
  "properties": {
    "iso:country":"US",
    "sg:address":"1328 N Jim Miller Rd Ofc",
    "sg:city":"Dallas",
    "sg:classifiers":[
        {
            "category":"Restaurant",
            "type":"Food & Drink"
        }
    ],
    "sg:phone":"+1 214 398 9191",
    "sg:postcode":"75217",
    "sg:province":"TX",
    "sg:tags":[
        "pizza"
    ],
    "wof:name":"Pizza Pizza",
    "wof:placetype":"venue"
},
  "geometry": {"coordinates":[-96.700104,32.735199],"type":"Point"}
}