{
  "type": "Feature",
  "properties": {
    "iso:country":"US",
    "sg:address":"2120 Denton Dr",
    "sg:city":"Austin",
    "sg:classifiers":[
        {
            "category":"Building & Trades",
            "subcategory":"Construction",
            "type":"Services"
        }
    ],
    "sg:phone":"+1 512 453 5858",
    "sg:postcode":"78758",
    "sg:province":"TX",
    "sg:tags":[
        "contractor",
        "nonresidential"
    ],
    "wof:name":"Statewide Siding",
    "wof:placetype":"venue"
},
  "geometry": {"coordinates":[-97.716053,30.38679],"type":"Point"}
}