{
  "type": "Feature",
  "properties": {
    "iso:country":"US",
    "sg:address":"6718 State Highway 97 E",
    "sg:city":"Floresville",
    "sg:classifiers":[
        {
            "category":"Place Of Worship",
            "type":"Public Place"
        }
    ],
    "sg:phone":"+1 830 947 3602",
    "sg:postcode":"78114",
    "sg:province":"TX",
    "sg:tags":[
        "church"
    ],
    "wof:name":"Southwestern District Church Of God Seventh Day",
    "wof:placetype":"venue"
},
  "geometry": {"coordinates":[-98.079927,29.209067],"type":"Point"}
}