{
  "type": "Feature",
  "properties": {
    "iso:country":"US",
    "sg:address":"1502 Galveston St",
    "sg:city":"South Houston",
    "sg:classifiers":[
        {
            "category":"Bus Charters",
            "type":"Transportation"
        }
    ],
    "sg:phone":"+1 713 947 2877",
    "sg:postcode":"77587",
    "sg:province":"TX",
    "sg:tags":[
        "shuttle",
        "airport"
    ],
    "sg:website":"www.sierratrailways.com",
    "wof:name":"American Bus Company",
    "wof:placetype":"venue"
},
  "geometry": {"coordinates":[-95.243797,29.655399],"type":"Point"}
}