{
  "type": "Feature",
  "properties": {
    "iso:country":"US",
    "sg:address":"300 NE 1st St",
    "sg:city":"Smithville",
    "sg:classifiers":[
        {
            "category":"Railroad",
            "type":"Transportation"
        }
    ],
    "sg:phone":"+1 512 360 5063",
    "sg:postcode":"78957",
    "sg:province":"TX",
    "wof:name":"Union Pacific Railroad",
    "wof:placetype":"venue"
},
  "geometry": {"coordinates":[-97.158581,30.005958],"type":"Point"}
}