{
  "type": "Feature",
  "properties": {
    "iso:country":"US",
    "sg:address":"1302 16th St",
    "sg:city":"Huntsville",
    "sg:classifiers":[
        {
            "category":"Education",
            "subcategory":"Music School",
            "type":"Public Place"
        },
        {
            "category":"Education",
            "subcategory":"School",
            "type":"Public Place"
        }
    ],
    "sg:phone":"+1 936 291 7553",
    "sg:postcode":"77340",
    "sg:province":"TX",
    "wof:name":"Burdett Music Studio",
    "wof:placetype":"venue"
},
  "geometry": {"coordinates":[-95.55290100000001,30.717791],"type":"Point"}
}