{
  "type": "Feature",
  "properties": {
    "iso:country":"US",
    "sg:address":"5809 Leopard St",
    "sg:city":"Corpus Christi",
    "sg:classifiers":[
        {
            "category":"Wholesale",
            "subcategory":"Machinery & Supplies",
            "type":"Manufacturing & Wholesale Goods"
        }
    ],
    "sg:phone":"+1 361 289 6033",
    "sg:postcode":"78408",
    "sg:province":"TX",
    "sg:tags":[
        "engine",
        "equipment",
        "product",
        "industrial",
        "petroleum"
    ],
    "sg:website":"www.drivediesel.com",
    "wof:name":"Coastal Diesel Injection Svcs",
    "wof:placetype":"venue"
},
  "geometry": {"coordinates":[-97.47477600000001,27.797608],"type":"Point"}
}