{
  "type": "Feature",
  "properties": {
    "iso:country":"US",
    "sg:address":"2308 Edgewater Ct",
    "sg:city":"Rockport",
    "sg:classifiers":[
        {
            "category":"Building & Trades",
            "subcategory":"Plumbing",
            "type":"Services"
        }
    ],
    "sg:phone":"+1 361 727 0025",
    "sg:postcode":"78382",
    "sg:province":"TX",
    "sg:tags":[
        "contractor"
    ],
    "wof:name":"Samuel J Chiapetta",
    "wof:placetype":"venue"
},
  "geometry": {"coordinates":[-97.03628500000001,28.04907],"type":"Point"}
}