{
  "type": "Feature",
  "properties": {
    "iso:country":"US",
    "sg:address":"3613 Greenville Ave",
    "sg:city":"Dallas",
    "sg:classifiers":[
        {
            "category":"Wholesale",
            "subcategory":"Apparel",
            "type":"Manufacturing & Wholesale Goods"
        },
        {
            "category":"Professional",
            "subcategory":"Business Services",
            "type":"Services"
        }
    ],
    "sg:phone":"+1 214 887 0707",
    "sg:postcode":"75206",
    "sg:province":"TX",
    "sg:tags":[
        "clothing"
    ],
    "wof:name":"Red Hot Designs",
    "wof:placetype":"venue"
},
  "geometry": {"coordinates":[-96.77023699999999,32.831232],"type":"Point"}
}