{
  "type": "Feature",
  "properties": {
    "iso:country":"US",
    "sg:address":"1225 North Loop W",
    "sg:city":"Houston",
    "sg:classifiers":[
        {
            "category":"Insurance",
            "subcategory":"Title Insurance",
            "type":"Services"
        }
    ],
    "sg:phone":"+1 832 673 3000",
    "sg:postcode":"77008",
    "sg:province":"TX",
    "sg:tags":[
        "mortgage"
    ],
    "sg:website":"http://www.chicagotitleco.com",
    "wof:name":"Chicago Title",
    "wof:placetype":"venue"
},
  "geometry": {"coordinates":[-95.42065599999999,29.812372],"type":"Point"}
}