{
  "type": "Feature",
  "properties": {
    "iso:country":"US",
    "sg:address":"165 Applecross Ln",
    "sg:city":"Pottsboro",
    "sg:classifiers":[
        {
            "category":"Wholesale",
            "subcategory":"Auto Parts",
            "type":"Manufacturing & Wholesale Goods"
        }
    ],
    "sg:phone":"+1 903 786 4449",
    "sg:postcode":"75076",
    "sg:province":"TX",
    "sg:tags":[
        "truck",
        "accessory"
    ],
    "wof:name":"Voltminder Inc",
    "wof:placetype":"venue"
},
  "geometry": {"coordinates":[-96.67307,33.851695],"type":"Point"}
}