{
  "type": "Feature",
  "properties": {
    "iso:country":"US",
    "sg:address":"601 E Ash Ln",
    "sg:city":"Euless",
    "sg:classifiers":[
        {
            "category":"Banks & Credit Unions",
            "subcategory":"Bank",
            "type":"Services"
        }
    ],
    "sg:phone":"+1 817 643 1020",
    "sg:postcode":"76039",
    "sg:province":"TX",
    "sg:tags":[
        "loan",
        "real estate"
    ],
    "wof:name":"Right Mortgage Co",
    "wof:placetype":"venue"
},
  "geometry": {"coordinates":[-97.072891,32.858877],"type":"Point"}
}