{
  "type": "Feature",
  "properties": {
    "iso:country":"US",
    "sg:address":"9879 S Whitehall Rd",
    "sg:city":"Temple",
    "sg:classifiers":[
        {
            "category":"Manufacturing",
            "subcategory":"Musical Instruments",
            "type":"Manufacturing & Wholesale Goods"
        }
    ],
    "sg:phone":"+1 254 986 2519",
    "sg:postcode":"76502",
    "sg:province":"TX",
    "sg:tags":[
        "mfg"
    ],
    "wof:name":"Bruton Souza Cradle Etc",
    "wof:placetype":"venue"
},
  "geometry": {"coordinates":[-97.42630699999999,31.201145],"type":"Point"}
}