{
  "type": "Feature",
  "properties": {
    "iso:country":"US",
    "sg:address":"735 Virgin Oak",
    "sg:city":"San Antonio",
    "sg:classifiers":[
        {
            "category":"Arena",
            "subcategory":"Sports Club",
            "type":"Entertainment"
        }
    ],
    "sg:phone":"+1 210 497 7775",
    "sg:postcode":"78258",
    "sg:province":"TX",
    "sg:tags":[
        "soccer"
    ],
    "wof:name":"Alamo Area Youth Soccer Assoc",
    "wof:placetype":"venue"
},
  "geometry": {"coordinates":[-98.50586300000001,29.628007],"type":"Point"}
}