{
  "type": "Feature",
  "properties": {
    "iso:country":"US",
    "sg:address":"14403 Pavilion Pt",
    "sg:city":"Houston",
    "sg:classifiers":[
        {
            "category":"Communications",
            "type":"Services"
        }
    ],
    "sg:phone":"+1 832 876 7497",
    "sg:postcode":"77099",
    "sg:province":"TX",
    "sg:tags":[
        "communication"
    ],
    "wof:name":"Ibanez Communications",
    "wof:placetype":"venue"
},
  "geometry": {"coordinates":[-95.642185,29.692921],"type":"Point"}
}