{
  "type": "Feature",
  "properties": {
    "iso:country":"US",
    "sg:address":"1203 Trailwood Ln",
    "sg:city":"Longview",
    "sg:classifiers":[
        {
            "category":"Manufacturing",
            "subcategory":"Retail Goods",
            "type":"Manufacturing & Wholesale Goods"
        }
    ],
    "sg:phone":"+1 903 297 3456",
    "sg:postcode":"75605",
    "sg:province":"TX",
    "sg:tags":[
        "product",
        "mfg"
    ],
    "wof:name":"Soft Reflections",
    "wof:placetype":"venue"
},
  "geometry": {"coordinates":[-94.790666,32.542299],"type":"Point"}
}