{
  "type": "Feature",
  "properties": {
    "iso:country":"US",
    "sg:address":"102 Advance Rd",
    "sg:city":"Weatherford",
    "sg:classifiers":[
        {
            "category":"Building & Trades",
            "subcategory":"Construction",
            "type":"Services"
        }
    ],
    "sg:phone":"+1 817 598 1883",
    "sg:postcode":"76088",
    "sg:province":"TX",
    "sg:tags":[
        "insulation",
        "drywall",
        "contractor"
    ],
    "wof:name":"American Plaster Service",
    "wof:placetype":"venue"
},
  "geometry": {"coordinates":[-97.92186100000001,32.887984],"type":"Point"}
}