{
  "type": "Feature",
  "properties": {
    "iso:country":"US",
    "sg:address":"10829 Canyon Dr",
    "sg:city":"Amarillo",
    "sg:classifiers":[
        {
            "category":"Recreation",
            "type":"Entertainment"
        }
    ],
    "sg:phone":"+1 806 622 2445",
    "sg:postcode":"79119",
    "sg:province":"TX",
    "sg:tags":[
        "amusement"
    ],
    "wof:name":"Amarillo Sand Drag",
    "wof:placetype":"venue"
},
  "geometry": {"coordinates":[-101.91554600000001,35.087132],"type":"Point"}
}