{
  "type": "Feature",
  "properties": {
    "iso:country":"US",
    "sg:address":"228 NE Wilshire Blvd",
    "sg:city":"Burleson",
    "sg:classifiers":[
        {
            "category":"Utilities",
            "subcategory":"Fuel Oil & Lpg",
            "type":"Services"
        }
    ],
    "sg:phone":"+1 817 426 6333",
    "sg:postcode":"76028",
    "sg:province":"TX",
    "sg:tags":[
        "development",
        "exploration",
        "gas"
    ],
    "wof:name":"Mesa Well Servicing LP",
    "wof:placetype":"venue"
},
  "geometry": {"coordinates":[-97.329802,32.542573],"type":"Point"}
}