{
  "type": "Feature",
  "properties": {
    "iso:country":"US",
    "sg:address":"1810 Murchison Dr",
    "sg:city":"El Paso",
    "sg:classifiers":[
        {
            "category":"Wholesale",
            "subcategory":"Drugs",
            "type":"Manufacturing & Wholesale Goods"
        }
    ],
    "sg:phone":"+1 915 544 0096",
    "sg:postcode":"79902",
    "sg:province":"TX",
    "wof:name":"Cardinal Health 414 Inc",
    "wof:placetype":"venue"
},
  "geometry": {"coordinates":[-106.476603,31.782247],"type":"Point"}
}