{
  "type": "Feature",
  "properties": {
    "iso:country":"US",
    "sg:address":"406 Chelsea Bay",
    "sg:city":"Coppell",
    "sg:classifiers":[
        {
            "category":"Freight",
            "type":"Transportation"
        }
    ],
    "sg:phone":"+1 972 393 2537",
    "sg:postcode":"75019",
    "sg:province":"TX",
    "sg:tags":[
        "operator",
        "trucking"
    ],
    "wof:name":"Cardinal Freight Carriers",
    "wof:placetype":"venue"
},
  "geometry": {"coordinates":[-96.96633799999999,32.978243],"type":"Point"}
}