{
  "type": "Feature",
  "properties": {
    "iso:country":"US",
    "sg:address":"4860 SW Loop 820",
    "sg:city":"Fort Worth",
    "sg:classifiers":[
        {
            "category":"Restaurant",
            "type":"Food & Drink"
        }
    ],
    "sg:menulink":"http://www.allmenus.com/tx/fort-worth/64502-chuck-e-cheeses/menu/",
    "sg:phone":"+1 817 732 8315",
    "sg:postcode":"76109",
    "sg:province":"TX",
    "sg:tags":[
        "american",
        "pizza"
    ],
    "wof:name":"Chuck E. Cheese's",
    "wof:placetype":"venue"
},
  "geometry": {"coordinates":[-97.400436,32.6853],"type":"Point"}
}