{
  "type": "Feature",
  "properties": {
    "iso:country":"US",
    "sg:address":"2304 Ridge Rd",
    "sg:city":"Rockwall",
    "sg:classifiers":[
        {
            "category":"Wholesale",
            "subcategory":"Jewelry",
            "type":"Manufacturing & Wholesale Goods"
        }
    ],
    "sg:phone":"+1 972 771 4515",
    "sg:postcode":"75032",
    "sg:province":"TX",
    "sg:tags":[
        "beads"
    ],
    "sg:website":"www.ballybead.com",
    "wof:name":"Bally Bead Co",
    "wof:placetype":"venue"
},
  "geometry": {"coordinates":[-96.46902,32.899149],"type":"Point"}
}