{
  "type": "Feature",
  "properties": {
    "iso:country":"US",
    "sg:address":"806 Oakridge Ct",
    "sg:city":"Keller",
    "sg:classifiers":[
        {
            "category":"Building & Trades",
            "subcategory":"Construction",
            "type":"Services"
        }
    ],
    "sg:phone":"+1 817 281 2031",
    "sg:postcode":"76248",
    "sg:province":"TX",
    "sg:tags":[
        "roofing",
        "contractor"
    ],
    "wof:name":"Green Michael Roofing LLC",
    "wof:placetype":"venue"
},
  "geometry": {"coordinates":[-97.23495,32.917396],"type":"Point"}
}