{
  "type": "Feature",
  "properties": {
    "iso:country":"US",
    "sg:address":"1 Bayou Bend Pl",
    "sg:city":"Beaumont",
    "sg:classifiers":[
        {
            "category":"Structure",
            "subcategory":"Office Building",
            "type":"Public Place"
        }
    ],
    "sg:phone":"+1 409 899 2984",
    "sg:postcode":"77706",
    "sg:province":"TX",
    "sg:tags":[
        "park"
    ],
    "wof:name":"Ll&A River Ridge Properties",
    "wof:placetype":"venue"
},
  "geometry": {"coordinates":[-94.156548,30.10383],"type":"Point"}
}