{
  "type": "Feature",
  "properties": {
    "iso:country":"US",
    "sg:address":"5201 N Lamar Blvd",
    "sg:city":"Austin",
    "sg:classifiers":[
        {
            "category":"Professional",
            "subcategory":"Printing & Photocopies",
            "type":"Services"
        },
        {
            "category":"Professional",
            "subcategory":"Credit Reporting & Collection",
            "type":"Services"
        }
    ],
    "sg:phone":"+1 512 452 9940",
    "sg:postcode":"78751",
    "sg:province":"TX",
    "sg:tags":[
        "engraving",
        "plaque",
        "medal",
        "award",
        "trophies"
    ],
    "sg:website":"http://www.lonestarawards.com",
    "wof:name":"Lone Star Awards",
    "wof:placetype":"venue"
},
  "geometry": {"coordinates":[-97.73020200000001,30.31983],"type":"Point"}
}