{
  "type": "Feature",
  "properties": {
    "iso:country":"US",
    "sg:address":"4505 York St",
    "sg:city":"Wichita Falls",
    "sg:classifiers":[
        {
            "category":"Real Estate",
            "subcategory":"Real Estate Agent",
            "type":"Services"
        }
    ],
    "sg:phone":"+1 940 692 2728",
    "sg:postcode":"76309",
    "sg:province":"TX",
    "wof:name":"Texas Realty",
    "wof:placetype":"venue"
},
  "geometry": {"coordinates":[-98.559023,33.883097],"type":"Point"}
}