{
  "type": "Feature",
  "properties": {
    "iso:country":"US",
    "sg:address":"14450 Memorial Dr",
    "sg:city":"Houston",
    "sg:classifiers":[
        {
            "category":"Restaurant",
            "type":"Food & Drink"
        }
    ],
    "sg:menulink":"http://www.allmenus.com/tx/houston/203024-mcdonalds/menu/",
    "sg:postcode":"77079",
    "sg:province":"TX",
    "sg:tags":[
        "burger",
        "american"
    ],
    "wof:name":"McDonald's",
    "wof:placetype":"venue"
},
  "geometry": {"coordinates":[-95.60157599999999,29.770569],"type":"Point"}
}