{
  "type": "Feature",
  "properties": {
    "iso:country":"US",
    "sg:address":"400 W Jefferson St",
    "sg:city":"Waxahachie",
    "sg:classifiers":[
        {
            "category":"Retail",
            "subcategory":"Repair Shop",
            "type":"Services"
        }
    ],
    "sg:phone":"+1 972 937 3900",
    "sg:postcode":"75165",
    "sg:province":"TX",
    "wof:name":"Ellis Sewing Machine Repair",
    "wof:placetype":"venue"
},
  "geometry": {"coordinates":[-96.85172300000001,32.386252],"type":"Point"}
}