{
  "type": "Feature",
  "properties": {
    "iso:country":"US",
    "sg:address":"1500 7th St",
    "sg:city":"Bay City",
    "sg:classifiers":[
        {
            "category":"Banks & Credit Unions",
            "subcategory":"Investment Brokerage",
            "type":"Services"
        }
    ],
    "sg:phone":"+1 979 245 3999",
    "sg:postcode":"77414",
    "sg:province":"TX",
    "sg:tags":[
        "security"
    ],
    "wof:name":"Edward Jones 07742",
    "wof:placetype":"venue"
},
  "geometry": {"coordinates":[-95.972459,28.982923],"type":"Point"}
}