{
  "type": "Feature",
  "properties": {
    "iso:country":"US",
    "sg:address":"6316 Babcock Rd",
    "sg:city":"San Antonio",
    "sg:classifiers":[
        {
            "category":"Organizations",
            "subcategory":"Religious Organization",
            "type":"Services"
        }
    ],
    "sg:phone":"+1 210 690 8884",
    "sg:postcode":"78240",
    "sg:province":"TX",
    "wof:name":"Babcock Road Christian Church",
    "wof:placetype":"venue"
},
  "geometry": {"coordinates":[-98.61272,29.541805],"type":"Point"}
}