{
  "type": "Feature",
  "properties": {
    "iso:country":"US",
    "sg:address":"650 Meadowgreen Dr",
    "sg:city":"Port Neches",
    "sg:classifiers":[
        {
            "category":"Building & Trades",
            "subcategory":"Construction",
            "type":"Services"
        }
    ],
    "sg:phone":"+1 409 722 8605",
    "sg:postcode":"77651",
    "sg:province":"TX",
    "sg:tags":[
        "house"
    ],
    "wof:name":"Indium Construction Co Inc",
    "wof:placetype":"venue"
},
  "geometry": {"coordinates":[-93.960621,29.96158],"type":"Point"}
}