{
  "type": "Feature",
  "properties": {
    "iso:country":"US",
    "sg:address":"12402 Meadow Briar Dr",
    "sg:city":"Stafford",
    "sg:classifiers":[
        {
            "category":"Professional",
            "subcategory":"Art Services",
            "type":"Services"
        }
    ],
    "sg:phone":"+1 281 240 6236",
    "sg:postcode":"77477",
    "sg:province":"TX",
    "sg:tags":[
        "commercial",
        "design"
    ],
    "wof:name":"Brad Follis",
    "wof:placetype":"venue"
},
  "geometry": {"coordinates":[-95.59357300000001,29.640602],"type":"Point"}
}