{
  "type": "Feature",
  "properties": {
    "iso:country":"US",
    "sg:address":"225 E Spring St",
    "sg:city":"Weatherford",
    "sg:classifiers":[
        {
            "category":"Shopping",
            "subcategory":"Florist",
            "type":"Retail Goods"
        },
        {
            "category":"Bakery",
            "type":"Food & Drink"
        },
        {
            "category":"Food & Beverages",
            "subcategory":"Groceries & Convenience Stores",
            "type":"Retail Goods"
        }
    ],
    "sg:phone":"+1 817 594 9390",
    "sg:postcode":"76086",
    "sg:province":"TX",
    "wof:name":"Albertsons Floral",
    "wof:placetype":"venue"
},
  "geometry": {"coordinates":[-97.795081,32.760506],"type":"Point"}
}