{
  "type": "Feature",
  "properties": {
    "iso:country":"US",
    "sg:address":"400 S Lafayette St",
    "sg:city":"Marshall",
    "sg:classifiers":[
        {
            "category":"Organizations",
            "subcategory":"Religious Organization",
            "type":"Services"
        }
    ],
    "sg:phone":"+1 903 935 7417",
    "sg:postcode":"75670",
    "sg:province":"TX",
    "sg:tags":[
        "church"
    ],
    "wof:name":"First Assembly Of God",
    "wof:placetype":"venue"
},
  "geometry": {"coordinates":[-94.36532699999999,32.542521],"type":"Point"}
}