{
  "type": "Feature",
  "properties": {
    "iso:country":"US",
    "sg:address":"4704 San Pedro Ave",
    "sg:city":"San Antonio",
    "sg:classifiers":[
        {
            "category":"Social Services",
            "subcategory":"Child Care",
            "type":"Services"
        }
    ],
    "sg:phone":"+1 210 821 5337",
    "sg:postcode":"78212",
    "sg:province":"TX",
    "sg:tags":[
        "day"
    ],
    "wof:name":"Fun Factory Learning Center 1",
    "wof:placetype":"venue"
},
  "geometry": {"coordinates":[-98.499216,29.477533],"type":"Point"}
}