{
  "type": "Feature",
  "properties": {
    "iso:country":"US",
    "sg:address":"224 E 4th St",
    "sg:city":"Texarkana",
    "sg:classifiers":[
        {
            "category":"Banks & Credit Unions",
            "subcategory":"Bank",
            "type":"Services"
        }
    ],
    "sg:phone":"+1 870 773 4561",
    "sg:postcode":"71854",
    "sg:province":"TX",
    "sg:website":"www.cnbtxk.com",
    "wof:name":"Commercial National Bank",
    "wof:placetype":"venue"
},
  "geometry": {"coordinates":[-94.041113,33.424523],"type":"Point"}
}