{
  "type": "Feature",
  "properties": {
    "iso:country":"US",
    "sg:address":"10909 Greenwillow St",
    "sg:city":"Houston",
    "sg:classifiers":[
        {
            "category":"Wholesale",
            "subcategory":"Machinery & Supplies",
            "type":"Manufacturing & Wholesale Goods"
        }
    ],
    "sg:phone":"+1 713 729 4371",
    "sg:postcode":"77035",
    "sg:province":"TX",
    "sg:tags":[
        "equipment",
        "safety",
        "clothing"
    ],
    "wof:name":"Richard Jernigan",
    "wof:placetype":"venue"
},
  "geometry": {"coordinates":[-95.44880499999999,29.662165],"type":"Point"}
}