{
  "type": "Feature",
  "properties": {
    "iso:country":"US",
    "sg:address":"600 Luther Dr",
    "sg:city":"Georgetown",
    "sg:classifiers":[
        {
            "category":"Real Estate",
            "subcategory":"Real Estate Operator",
            "type":"Services"
        }
    ],
    "sg:phone":"+1 512 869 2876",
    "sg:postcode":"78628",
    "sg:province":"TX",
    "sg:tags":[
        "building",
        "apartment"
    ],
    "wof:name":"Indian Creek Apartments Ltd",
    "wof:placetype":"venue"
},
  "geometry": {"coordinates":[-97.69213000000001,30.613667],"type":"Point"}
}