{
  "type": "Feature",
  "properties": {
    "iso:country":"US",
    "sg:address":"6556 W Park Blvd",
    "sg:city":"Plano",
    "sg:classifiers":[
        {
            "category":"Restaurant",
            "type":"Food & Drink"
        }
    ],
    "sg:menulink":"http://www.allmenus.com/tx/plano/50239-roti-grill/menu/",
    "sg:phone":"+1 972 403 7600",
    "sg:postcode":"75093",
    "sg:province":"TX",
    "sg:tags":[
        "indian",
        "asian"
    ],
    "wof:name":"Roti Grill",
    "wof:placetype":"venue"
},
  "geometry": {"coordinates":[-96.842347,33.026089],"type":"Point"}
}