{
  "type": "Feature",
  "properties": {
    "iso:country":"US",
    "sg:address":"2630 Fountain View Dr",
    "sg:city":"Houston",
    "sg:classifiers":[
        {
            "category":"Insurance",
            "subcategory":"Hazard Insurance",
            "type":"Services"
        },
        {
            "category":"Insurance",
            "subcategory":"Insurance Agent",
            "type":"Services"
        },
        {
            "category":"Insurance",
            "subcategory":"Life Insurance",
            "type":"Services"
        },
        {
            "category":"Insurance",
            "subcategory":"Title Insurance",
            "type":"Services"
        }
    ],
    "sg:phone":"+1 713 781 3051",
    "sg:postcode":"77057",
    "sg:province":"TX",
    "sg:tags":[
        "auto",
        "commercial",
        "business",
        "homeowner"
    ],
    "sg:website":"http://www.farmersagent.com/hkhan/",
    "wof:name":"Haseeb Khan - Farmers Insurance",
    "wof:placetype":"venue"
},
  "geometry": {"coordinates":[-95.48448399999999,29.738719],"type":"Point"}
}