{
  "type": "Feature",
  "properties": {
    "iso:country":"US",
    "sg:address":"514 E Commerce St",
    "sg:city":"Jacksonville",
    "sg:classifiers":[
        {
            "category":"Health Services",
            "subcategory":"Clinic",
            "type":"Services"
        }
    ],
    "sg:phone":"+1 903 586 1428",
    "sg:postcode":"75766",
    "sg:province":"TX",
    "sg:tags":[
        "specialty",
        "outpatient"
    ],
    "wof:name":"Community Rhbltation Prof Svcs",
    "wof:placetype":"venue"
},
  "geometry": {"coordinates":[-95.268486,31.965499],"type":"Point"}
}