{
  "type": "Feature",
  "properties": {
    "iso:country":"US",
    "sg:address":"3528 N Hampton Rd",
    "sg:city":"Dallas",
    "sg:classifiers":[
        {
            "category":"Shopping",
            "subcategory":"Pharmacy",
            "type":"Retail Goods"
        }
    ],
    "sg:phone":"+1 214 630 3014",
    "sg:postcode":"75212",
    "sg:province":"TX",
    "sg:tags":[
        "drugstore"
    ],
    "wof:name":"Cut-Rate Pharmacy",
    "wof:placetype":"venue"
},
  "geometry": {"coordinates":[-96.8563,32.785999],"type":"Point"}
}