{
  "type": "Feature",
  "properties": {
    "iso:country":"US",
    "sg:address":"821 Willow Ct",
    "sg:city":"Saginaw",
    "sg:classifiers":[
        {
            "category":"Professional",
            "type":"Services"
        }
    ],
    "sg:phone":"+1 817 232 3067",
    "sg:postcode":"76179",
    "sg:province":"TX",
    "sg:tags":[
        "establishment"
    ],
    "wof:name":"Woodpecker's Dog Show Supplies",
    "wof:placetype":"venue"
},
  "geometry": {"coordinates":[-97.37726600000001,32.852726],"type":"Point"}
}