{
  "type": "Feature",
  "properties": {
    "iso:country":"US",
    "sg:address":"809 Majestic Oaks Ct",
    "sg:city":"Mansfield",
    "sg:classifiers":[
        {
            "category":"Shopping",
            "type":"Retail Goods"
        },
        {
            "category":"Shopping",
            "subcategory":"Beauty & Cosmetics",
            "type":"Retail Goods"
        }
    ],
    "sg:phone":"+1 817 477 4477",
    "sg:postcode":"76063",
    "sg:province":"TX",
    "sg:tags":[
        "merchandise",
        "perfume"
    ],
    "wof:name":"King-Stark Darlene Cosmetics",
    "wof:placetype":"venue"
},
  "geometry": {"coordinates":[-97.153426,32.612195],"type":"Point"}
}