{
  "type": "Feature",
  "properties": {
    "iso:country":"US",
    "sg:address":"1011 San Jacinto Blvd. Suite 202",
    "sg:city":"Austin",
    "sg:classifiers":[
        {
            "category":"Professional",
            "subcategory":"Advertising",
            "type":"Services"
        }
    ],
    "sg:phone":"+1 888 570 1134",
    "sg:postcode":"78701",
    "sg:province":"TX",
    "sg:website":"http://www.collidermedia.com/",
    "wof:name":"Collider Media",
    "wof:placetype":"venue"
},
  "geometry": {"coordinates":[-97.73861100000001,30.271941],"type":"Point"}
}