{
  "type": "Feature",
  "properties": {
    "iso:country":"US",
    "sg:address":"1210 Old Hwy 418",
    "sg:city":"Silsbee",
    "sg:classifiers":[
        {
            "category":"Building & Trades",
            "subcategory":"Pest Control",
            "type":"Services"
        }
    ],
    "sg:phone":"+1 409 386 2027",
    "sg:postcode":"77656",
    "sg:province":"TX",
    "wof:name":"El Matador Pest Control",
    "wof:placetype":"venue"
},
  "geometry": {"coordinates":[-94.188648,30.359644],"type":"Point"}
}