{
  "type": "Feature",
  "properties": {
    "iso:country":"US",
    "sg:address":"2819 Forest Ridge Dr",
    "sg:city":"Bedford",
    "sg:classifiers":[
        {
            "category":"Museum",
            "type":"Entertainment"
        }
    ],
    "sg:phone":"+1 817 283 0089",
    "sg:postcode":"76021",
    "sg:province":"TX",
    "sg:tags":[
        "organization",
        "arts",
        "information"
    ],
    "wof:name":"Arts Council Of Ne Tarrant Cty",
    "wof:placetype":"venue"
},
  "geometry": {"coordinates":[-97.143485,32.85015],"type":"Point"}
}