{
  "type": "Feature",
  "properties": {
    "iso:country":"US",
    "sg:address":"8911 N Capital of Texas Hwy",
    "sg:city":"Austin",
    "sg:classifiers":[
        {
            "category":"Travel",
            "subcategory":"Bed & Breakfast",
            "type":"Entertainment"
        }
    ],
    "sg:phone":"+1 512 343 1475",
    "sg:postcode":"78759",
    "sg:province":"TX",
    "sg:tags":[
        "corporate",
        "lodging"
    ],
    "wof:name":"Oakwood Corporate Housing",
    "wof:placetype":"venue"
},
  "geometry": {"coordinates":[-97.754513,30.387919],"type":"Point"}
}