{
  "type": "Feature",
  "properties": {
    "iso:country":"US",
    "sg:address":"11005 Indian Trl",
    "sg:city":"Dallas",
    "sg:classifiers":[
        {
            "category":"Retail",
            "subcategory":"Auto Repair",
            "type":"Services"
        }
    ],
    "sg:phone":"+1 972 243 6042",
    "sg:postcode":"75229",
    "sg:province":"TX",
    "sg:tags":[
        "automotive"
    ],
    "wof:name":"James L Byron",
    "wof:placetype":"venue"
},
  "geometry": {"coordinates":[-96.88370399999999,32.896614],"type":"Point"}
}