{
  "type": "Feature",
  "properties": {
    "iso:country":"US",
    "sg:address":"2705 Clarksville St",
    "sg:city":"Paris",
    "sg:classifiers":[
        {
            "category":"Shopping",
            "subcategory":"Computers & Home Electronics",
            "type":"Retail Goods"
        }
    ],
    "sg:phone":"+1 903 737 9696",
    "sg:postcode":"75460",
    "sg:province":"TX",
    "sg:tags":[
        "equipment",
        "dealer"
    ],
    "wof:name":"Professional Business Systems",
    "wof:placetype":"venue"
},
  "geometry": {"coordinates":[-95.526927,33.651892],"type":"Point"}
}