{
  "type": "Feature",
  "properties": {
    "iso:country":"US",
    "sg:address":"16314 Redwicke Ln",
    "sg:city":"Houston",
    "sg:classifiers":[
        {
            "category":"Professional",
            "subcategory":"Management & Consulting",
            "type":"Services"
        }
    ],
    "sg:phone":"+1 281 855 1196",
    "sg:postcode":"77084",
    "sg:province":"TX",
    "wof:name":"Apex Funding Solution LLC",
    "wof:placetype":"venue"
},
  "geometry": {"coordinates":[-95.65432699999999,29.86643],"type":"Point"}
}