{
  "type": "Feature",
  "properties": {
    "iso:country":"US",
    "sg:address":"6100 Hillcroft St Fl 3",
    "sg:city":"Houston",
    "sg:classifiers":[
        {
            "category":"Real Estate",
            "subcategory":"Surveying",
            "type":"Services"
        }
    ],
    "sg:phone":"+1 713 773 5670",
    "sg:postcode":"77081",
    "sg:province":"TX",
    "sg:tags":[
        "surveyor",
        "land",
        "engineer"
    ],
    "wof:name":"Fugro",
    "wof:placetype":"venue"
},
  "geometry": {"coordinates":[-95.49722300000001,29.714861],"type":"Point"}
}