{
  "type": "Feature",
  "properties": {
    "iso:country":"US",
    "sg:address":"1107 Chartres St",
    "sg:city":"Houston",
    "sg:classifiers":[
        {
            "category":"Arts & Performance",
            "subcategory":"Arts Center",
            "type":"Entertainment"
        }
    ],
    "sg:phone":"+1 713 547 0126",
    "sg:postcode":"77003",
    "sg:province":"TX",
    "sg:tags":[
        "performing"
    ],
    "wof:name":"Silver House Theatre",
    "wof:placetype":"venue"
},
  "geometry": {"coordinates":[-95.356903,29.750999],"type":"Point"}
}