{
  "type": "Feature",
  "properties": {
    "iso:country":"US",
    "sg:address":"2835 E Illinois Ave",
    "sg:city":"Dallas",
    "sg:classifiers":[
        {
            "category":"Travel",
            "subcategory":"Hotels & Motels",
            "type":"Entertainment"
        }
    ],
    "sg:phone":"+1 214 374 1675",
    "sg:postcode":"75216",
    "sg:province":"TX",
    "wof:name":"Aloha Motel",
    "wof:placetype":"venue"
},
  "geometry": {"coordinates":[-96.78040300000001,32.7169],"type":"Point"}
}