{
  "type": "Feature",
  "properties": {
    "iso:country":"US",
    "sg:address":"2506 Sutherland St",
    "sg:city":"Houston",
    "sg:classifiers":[
        {
            "category":"Organizations",
            "subcategory":"Labor Organization",
            "type":"Services"
        }
    ],
    "sg:phone":"+1 713 926 8897",
    "sg:postcode":"77023",
    "sg:province":"TX",
    "sg:tags":[
        "union",
        "professional"
    ],
    "wof:name":"Community Services Program",
    "wof:placetype":"venue"
},
  "geometry": {"coordinates":[-95.318461,29.710915],"type":"Point"}
}