{
  "type": "Feature",
  "properties": {
    "iso:country":"US",
    "sg:address":"1132 State Hwy 34",
    "sg:city":"Terrell",
    "sg:classifiers":[
        {
            "category":"Retail",
            "subcategory":"Auto Repair",
            "type":"Services"
        }
    ],
    "sg:phone":"+1 972 551 1311",
    "sg:postcode":"75160",
    "sg:province":"TX",
    "sg:tags":[
        "truck",
        "general"
    ],
    "wof:name":"Lyman's Diesel & Truck",
    "wof:placetype":"venue"
},
  "geometry": {"coordinates":[-96.276946,32.726427],"type":"Point"}
}