{
  "type": "Feature",
  "properties": {
    "iso:country":"US",
    "sg:address":"3033 Tangle Aire Ln",
    "sg:city":"Amarillo",
    "sg:classifiers":[
        {
            "category":"Building & Trades",
            "subcategory":"Construction",
            "type":"Services"
        }
    ],
    "sg:phone":"+1 806 622 8499",
    "sg:postcode":"79118",
    "sg:province":"TX",
    "sg:tags":[
        "carpentry",
        "contractor"
    ],
    "wof:name":"Dudleys Framing Inc",
    "wof:placetype":"venue"
},
  "geometry": {"coordinates":[-101.80341199999999,35.071588],"type":"Point"}
}