{
  "type": "Feature",
  "properties": {
    "iso:country":"US",
    "sg:address":"5413 Palace Dr",
    "sg:city":"Richardson",
    "sg:classifiers":[
        {
            "category":"Shopping",
            "subcategory":"Jewelry",
            "type":"Retail Goods"
        }
    ],
    "sg:phone":"+1 972 699 3980",
    "sg:postcode":"75082",
    "sg:province":"TX",
    "wof:name":"Pearls By Eden",
    "wof:placetype":"venue"
},
  "geometry": {"coordinates":[-96.620515,33.004441],"type":"Point"}
}