{
  "type": "Feature",
  "properties": {
    "iso:country":"US",
    "sg:address":"16668 Champion Forest Dr",
    "sg:city":"Spring",
    "sg:classifiers":[
        {
            "category":"Education",
            "subcategory":"School",
            "type":"Public Place"
        }
    ],
    "sg:phone":"+1 281 320 1120",
    "sg:postcode":"77379",
    "sg:province":"TX",
    "sg:tags":[
        "dance"
    ],
    "wof:name":"Studio of Dance",
    "wof:placetype":"venue"
},
  "geometry": {"coordinates":[-95.53746599999999,30.011336],"type":"Point"}
}