{
  "type": "Feature",
  "properties": {
    "iso:country":"US",
    "sg:address":"708 N 7th St",
    "sg:city":"Longview",
    "sg:classifiers":[
        {
            "category":"Professional",
            "type":"Services"
        }
    ],
    "sg:phone":"+1 903 758 0595",
    "sg:postcode":"75601",
    "sg:province":"TX",
    "wof:name":"Cathy C Jones",
    "wof:placetype":"venue"
},
  "geometry": {"coordinates":[-94.727958,32.500507],"type":"Point"}
}