{
  "type": "Feature",
  "properties": {
    "iso:country":"US",
    "sg:address":"1802 N Plano Rd",
    "sg:city":"Garland",
    "sg:classifiers":[
        {
            "category":"Social Services",
            "subcategory":"Child Care",
            "type":"Services"
        },
        {
            "category":"Education",
            "subcategory":"Preschool",
            "type":"Public Place"
        },
        {
            "category":"Education",
            "subcategory":"School",
            "type":"Public Place"
        }
    ],
    "sg:phone":"+1 972 272 3143",
    "sg:postcode":"75042",
    "sg:province":"TX",
    "sg:tags":[
        "elementary",
        "day"
    ],
    "wof:name":"Kindercare Learning Centers",
    "wof:placetype":"venue"
},
  "geometry": {"coordinates":[-96.699898,32.9296],"type":"Point"}
}