{
  "type": "Feature",
  "properties": {
    "iso:country":"US",
    "sg:address":"13711 Long Meadow Dr",
    "sg:city":"Pflugerville",
    "sg:classifiers":[
        {
            "category":"Freight",
            "type":"Transportation"
        }
    ],
    "sg:phone":"+1 512 252 3449",
    "sg:postcode":"78660",
    "sg:province":"TX",
    "sg:tags":[
        "operator",
        "local",
        "trucking"
    ],
    "wof:name":"Fernandez Trucking",
    "wof:placetype":"venue"
},
  "geometry": {"coordinates":[-97.63343999999999,30.406107],"type":"Point"}
}