{
  "type": "Feature",
  "properties": {
    "iso:country":"US",
    "sg:address":"410 E Main St",
    "sg:city":"Atlanta",
    "sg:classifiers":[
        {
            "category":"Personal",
            "subcategory":"Beauty Salon",
            "type":"Services"
        }
    ],
    "sg:phone":"+1 903 796 8888",
    "sg:postcode":"75551",
    "sg:province":"TX",
    "sg:tags":[
        "shop"
    ],
    "wof:name":"At Salon With Kelle",
    "wof:placetype":"venue"
},
  "geometry": {"coordinates":[-94.15852599999999,33.112522],"type":"Point"}
}