{
  "type": "Feature",
  "properties": {
    "iso:country":"US",
    "sg:address":"1110 Green Oaks Rd",
    "sg:city":"Fort Worth",
    "sg:classifiers":[
        {
            "category":"Insurance",
            "subcategory":"Insurance Agent",
            "type":"Services"
        }
    ],
    "sg:phone":"+1 817 738 7200",
    "sg:postcode":"76116",
    "sg:province":"TX",
    "wof:name":"State Farm Insurance",
    "wof:placetype":"venue"
},
  "geometry": {"coordinates":[-97.43412499999999,32.74951],"type":"Point"}
}