{
  "type": "Feature",
  "properties": {
    "iso:country":"US",
    "sg:address":"4647 Leston St",
    "sg:city":"Dallas",
    "sg:classifiers":[
        {
            "category":"Professional",
            "type":"Services"
        },
        {
            "category":"Retail",
            "subcategory":"Repair Shop",
            "type":"Services"
        }
    ],
    "sg:phone":"+1 214 637 4849",
    "sg:postcode":"75247",
    "sg:province":"TX",
    "sg:tags":[
        "sharpening",
        "saws-sharpen"
    ],
    "wof:name":"Cutting Solutions",
    "wof:placetype":"venue"
},
  "geometry": {"coordinates":[-96.89762,32.810429],"type":"Point"}
}