{
  "type": "Feature",
  "properties": {
    "iso:country":"US",
    "sg:address":"308 N Pearl St",
    "sg:city":"Big Sandy",
    "sg:classifiers":[
        {
            "category":"Manufacturing",
            "subcategory":"Furniture",
            "type":"Manufacturing & Wholesale Goods"
        }
    ],
    "sg:phone":"+1 903 636 9983",
    "sg:postcode":"75755",
    "sg:province":"TX",
    "sg:tags":[
        "home",
        "mfg",
        "accessory"
    ],
    "wof:name":"Jeffreys",
    "wof:placetype":"venue"
},
  "geometry": {"coordinates":[-95.105588,32.587215],"type":"Point"}
}