{
  "type": "Feature",
  "properties": {
    "iso:country":"US",
    "sg:address":"1102 NW 13th St",
    "sg:city":"Andrews",
    "sg:classifiers":[
        {
            "category":"Shopping",
            "subcategory":"Clothing, Apparel, & Fashions",
            "type":"Retail Goods"
        }
    ],
    "sg:phone":"+1 432 524 6146",
    "sg:postcode":"79714",
    "sg:province":"TX",
    "wof:name":"Briar Patch",
    "wof:placetype":"venue"
},
  "geometry": {"coordinates":[-102.56636899999999,32.327171],"type":"Point"}
}