{
  "type": "Feature",
  "properties": {
    "iso:country":"US",
    "sg:address":"12791 Honey Locust Cir",
    "sg:city":"Euless",
    "sg:classifiers":[
        {
            "category":"Professional",
            "type":"Services"
        }
    ],
    "sg:phone":"+1 817 399 0653",
    "sg:postcode":"76040",
    "sg:province":"TX",
    "wof:name":"Alpha Word",
    "wof:placetype":"venue"
},
  "geometry": {"coordinates":[-97.086197,32.82202],"type":"Point"}
}