{
  "type": "Feature",
  "properties": {
    "iso:country":"US",
    "sg:address":"7763 San Felipe St",
    "sg:city":"Houston",
    "sg:classifiers":[
        {
            "category":"Retail",
            "subcategory":"Portrait Studio",
            "type":"Services"
        }
    ],
    "sg:phone":"+1 832 251 1204",
    "sg:postcode":"77063",
    "sg:province":"TX",
    "sg:tags":[
        "photographer"
    ],
    "wof:name":"3 Stars Visas LLC",
    "wof:placetype":"venue"
},
  "geometry": {"coordinates":[-95.504026,29.750607],"type":"Point"}
}