{
  "type": "Feature",
  "properties": {
    "iso:country":"US",
    "sg:address":"6114 US Hwy 183",
    "sg:city":"Austin",
    "sg:classifiers":[
        {
            "category":"Personal",
            "subcategory":"Beauty Salon",
            "type":"Services"
        }
    ],
    "sg:phone":"+1 512 243 8023",
    "sg:postcode":"78744",
    "sg:province":"TX",
    "sg:tags":[
        "shop"
    ],
    "wof:name":"Ralph's Hair Styling",
    "wof:placetype":"venue"
},
  "geometry": {"coordinates":[-97.692155,30.167555],"type":"Point"}
}