{
  "type": "Feature",
  "properties": {
    "iso:country":"US",
    "sg:address":"6020 Waldham Grove Ln",
    "sg:city":"Bryan",
    "sg:classifiers":[
        {
            "category":"Building & Trades",
            "subcategory":"Landscaping Services",
            "type":"Services"
        }
    ],
    "sg:phone":"+1 979 774 9529",
    "sg:postcode":"77802",
    "sg:province":"TX",
    "wof:name":"Brazos Valley Mowing Serv",
    "wof:placetype":"venue"
},
  "geometry": {"coordinates":[-96.29165999999999,30.678011],"type":"Point"}
}