{
  "type": "Feature",
  "properties": {
    "iso:country":"US",
    "sg:address":"710 Timber Ln",
    "sg:city":"Laredo",
    "sg:classifiers":[
        {
            "category":"Wholesale",
            "subcategory":"Machinery & Supplies",
            "type":"Manufacturing & Wholesale Goods"
        }
    ],
    "sg:phone":"+1 956 723 2663",
    "sg:postcode":"78045",
    "sg:province":"TX",
    "sg:tags":[
        "machine",
        "equipment",
        "establishment",
        "vending",
        "op"
    ],
    "wof:name":"Steed Vending & Amus Mch Co",
    "wof:placetype":"venue"
},
  "geometry": {"coordinates":[-99.47979100000001,27.578206],"type":"Point"}
}