{
  "type": "Feature",
  "properties": {
    "iso:country":"US",
    "sg:address":"802 N Saint Marie St",
    "sg:city":"Mission",
    "sg:classifiers":[
        {
            "category":"Home & Garden",
            "subcategory":"Building Materials",
            "type":"Retail Goods"
        }
    ],
    "sg:phone":"+1 956 585 9094",
    "sg:postcode":"78572",
    "sg:province":"TX",
    "wof:name":"Figueroa Glass Work",
    "wof:placetype":"venue"
},
  "geometry": {"coordinates":[-98.320137,26.213732],"type":"Point"}
}