{
  "type": "Feature",
  "properties": {
    "iso:country":"US",
    "sg:address":"11938 Amblewood Dr",
    "sg:city":"Stafford",
    "sg:classifiers":[
        {
            "category":"Restaurant",
            "type":"Food & Drink"
        }
    ],
    "sg:phone":"+1 281 495 7976",
    "sg:postcode":"77477",
    "sg:province":"TX",
    "sg:tags":[
        "eating"
    ],
    "wof:name":"The Hub",
    "wof:placetype":"venue"
},
  "geometry": {"coordinates":[-95.588173,29.651238],"type":"Point"}
}