{
  "type": "Feature",
  "properties": {
    "iso:country":"US",
    "sg:address":"2805 Galleria Dr",
    "sg:city":"Arlington",
    "sg:classifiers":[
        {
            "category":"Organizations",
            "subcategory":"Religious Organization",
            "type":"Services"
        }
    ],
    "sg:phone":"+1 817 652 4466",
    "sg:postcode":"76011",
    "sg:province":"TX",
    "sg:tags":[
        "church"
    ],
    "wof:name":"Cornerstone Evangel Intl Chr",
    "wof:placetype":"venue"
},
  "geometry": {"coordinates":[-97.058145,32.746463],"type":"Point"}
}