{
  "type": "Feature",
  "properties": {
    "iso:country":"US",
    "sg:address":"8402 Mesa Dr",
    "sg:city":"Houston",
    "sg:classifiers":[
        {
            "category":"Government",
            "subcategory":"Office",
            "type":"Public Place"
        }
    ],
    "sg:phone":"+1 713 635 6296",
    "sg:postcode":"77028",
    "sg:province":"TX",
    "sg:tags":[
        "smog",
        "check"
    ],
    "wof:name":"Mynar Inspection Auto Center",
    "wof:placetype":"venue"
},
  "geometry": {"coordinates":[-95.262051,29.838077],"type":"Point"}
}