{
  "type": "Feature",
  "properties": {
    "iso:country":"US",
    "sg:address":"925 S Mason Rd",
    "sg:city":"Katy",
    "sg:classifiers":[
        {
            "category":"Professional",
            "subcategory":"Business Services",
            "type":"Services"
        }
    ],
    "sg:phone":"+1 281 693 3421",
    "sg:postcode":"77450",
    "sg:province":"TX",
    "wof:name":"Submit Mgr Co",
    "wof:placetype":"venue"
},
  "geometry": {"coordinates":[-95.751608,29.768658],"type":"Point"}
}