{
  "type": "Feature",
  "properties": {
    "iso:country":"US",
    "sg:address":"1003 Lonesome Trl",
    "sg:city":"Driftwood",
    "sg:classifiers":[
        {
            "category":"Freight",
            "type":"Transportation"
        }
    ],
    "sg:phone":"+1 512 847 1323",
    "sg:postcode":"78619",
    "sg:province":"TX",
    "sg:tags":[
        "broker",
        "customs"
    ],
    "wof:name":"Kenny Therrien's Custom Hm",
    "wof:placetype":"venue"
},
  "geometry": {"coordinates":[-98.027321,30.0607],"type":"Point"}
}