{
  "type": "Feature",
  "properties": {
    "iso:country":"US",
    "sg:address":"5707 92nd St",
    "sg:city":"Lubbock",
    "sg:classifiers":[
        {
            "category":"Building & Trades",
            "subcategory":"Plumbing",
            "type":"Services"
        }
    ],
    "sg:phone":"+1 806 794 6869",
    "sg:postcode":"79424",
    "sg:province":"TX",
    "sg:tags":[
        "contractor"
    ],
    "wof:name":"Cool Water Enterprises",
    "wof:placetype":"venue"
},
  "geometry": {"coordinates":[-101.936256,33.509911],"type":"Point"}
}