{
  "type": "Feature",
  "properties": {
    "iso:country":"US",
    "sg:address":"204 E Carson St",
    "sg:city":"Bryan",
    "sg:classifiers":[
        {
            "category":"Building & Trades",
            "subcategory":"Cleaning & Sanitation",
            "type":"Services"
        }
    ],
    "sg:phone":"+1 979 823 2504",
    "sg:postcode":"77801",
    "sg:province":"TX",
    "sg:tags":[
        "janitor"
    ],
    "wof:name":"Todaro's Building Maintenance",
    "wof:placetype":"venue"
},
  "geometry": {"coordinates":[-96.364131,30.651025],"type":"Point"}
}