{
  "type": "Feature",
  "properties": {
    "iso:country":"US",
    "sg:address":"5302 E Belknap St",
    "sg:city":"Fort Worth",
    "sg:classifiers":[
        {
            "category":"Restaurant",
            "type":"Food & Drink"
        }
    ],
    "sg:phone":"+1 817 831 0886",
    "sg:postcode":"76117",
    "sg:province":"TX",
    "sg:tags":[
        "eating"
    ],
    "wof:name":"Cafe Bon Thuong",
    "wof:placetype":"venue"
},
  "geometry": {"coordinates":[-97.269392,32.796094],"type":"Point"}
}