{
  "type": "Feature",
  "properties": {
    "iso:country":"US",
    "sg:address":"1266 Eastgate Rd Ste 150",
    "sg:city":"Midlothian",
    "sg:classifiers":[
        {
            "category":"Manufacturing",
            "subcategory":"Metals",
            "type":"Manufacturing & Wholesale Goods"
        },
        {
            "category":"Building & Trades",
            "subcategory":"Construction",
            "type":"Services"
        }
    ],
    "sg:phone":"+1 972 775 1585",
    "sg:postcode":"76065",
    "sg:province":"TX",
    "sg:tags":[
        "steel",
        "detailers",
        "structural",
        "manufacturer",
        "metal-wholesale"
    ],
    "wof:name":"James L. Frakes",
    "wof:placetype":"venue"
},
  "geometry": {"coordinates":[-96.95311700000001,32.469421],"type":"Point"}
}