{
  "type": "Feature",
  "properties": {
    "iso:country":"US",
    "sg:address":"449 US Hwy 62",
    "sg:city":"Lubbock",
    "sg:classifiers":[
        {
            "category":"Manufacturing",
            "subcategory":"Tools & Machinery",
            "type":"Manufacturing & Wholesale Goods"
        }
    ],
    "sg:phone":"+1 806 747 8686",
    "sg:postcode":"79401",
    "sg:province":"TX",
    "sg:tags":[
        "ginning",
        "cotton",
        "supply"
    ],
    "wof:name":"Beck Equipment",
    "wof:placetype":"venue"
},
  "geometry": {"coordinates":[-101.83921100000001,33.577703],"type":"Point"}
}