{
  "type": "Feature",
  "properties": {
    "iso:country":"US",
    "sg:address":"11823 Sawmill Stream Cir",
    "sg:city":"Houston",
    "sg:classifiers":[
        {
            "category":"Personal",
            "subcategory":"Beauty Salon",
            "type":"Services"
        }
    ],
    "sg:phone":"+1 281 895 9302",
    "sg:postcode":"77067",
    "sg:province":"TX",
    "sg:tags":[
        "shop"
    ],
    "wof:name":"Juliana Hair Braids",
    "wof:placetype":"venue"
},
  "geometry": {"coordinates":[-95.468265,29.955495],"type":"Point"}
}