{
  "type": "Feature",
  "properties": {
    "iso:country":"US",
    "sg:address":"1623 Nightingale Ln",
    "sg:city":"Denton",
    "sg:classifiers":[
        {
            "category":"Banks & Credit Unions",
            "subcategory":"Financial Services",
            "type":"Services"
        }
    ],
    "sg:phone":"+1 940 498 4984",
    "sg:postcode":"76210",
    "sg:province":"TX",
    "sg:tags":[
        "investor"
    ],
    "wof:name":"Hfr Investments LLC",
    "wof:placetype":"venue"
},
  "geometry": {"coordinates":[-97.084361,33.140953],"type":"Point"}
}