{
  "type": "Feature",
  "properties": {
    "iso:country":"US",
    "sg:address":"9762 Skillman St",
    "sg:city":"Dallas",
    "sg:classifiers":[
        {
            "category":"Wholesale",
            "subcategory":"Machinery & Supplies",
            "type":"Manufacturing & Wholesale Goods"
        }
    ],
    "sg:phone":"+1 214 343 6471",
    "sg:postcode":"75243",
    "sg:province":"TX",
    "sg:tags":[
        "firm",
        "representation",
        "mfg"
    ],
    "wof:name":"Hudson-Rush Co Inc",
    "wof:placetype":"venue"
},
  "geometry": {"coordinates":[-96.706718,32.908392],"type":"Point"}
}