{
  "type": "Feature",
  "properties": {
    "iso:country":"US",
    "sg:address":"1110 E Van Buren Ave",
    "sg:city":"Harlingen",
    "sg:classifiers":[
        {
            "category":"Retail",
            "subcategory":"Repair Shop",
            "type":"Services"
        }
    ],
    "sg:phone":"+1 956 412 2100",
    "sg:postcode":"78550",
    "sg:province":"TX",
    "sg:tags":[
        "electrical"
    ],
    "wof:name":"J & S Enterprises",
    "wof:placetype":"venue"
},
  "geometry": {"coordinates":[-97.68378,26.191666],"type":"Point"}
}