{
  "type": "Feature",
  "properties": {
    "iso:country":"US",
    "sg:address":"1107 6th St",
    "sg:city":"Madisonville",
    "sg:classifiers":[
        {
            "category":"Retail",
            "subcategory":"Auto Repair",
            "type":"Services"
        }
    ],
    "sg:phone":"+1 936 348 2012",
    "sg:postcode":"77864",
    "sg:province":"TX",
    "sg:tags":[
        "body",
        "shop",
        "automotive"
    ],
    "wof:name":"J B Burn Auto Body Inc",
    "wof:placetype":"venue"
},
  "geometry": {"coordinates":[-95.924184,30.938384],"type":"Point"}
}