{
  "type": "Feature",
  "properties": {
    "iso:country":"US",
    "sg:address":"1903 W Frank Ave",
    "sg:city":"Lufkin",
    "sg:classifiers":[
        {
            "category":"Restaurant",
            "type":"Food & Drink"
        }
    ],
    "sg:menulink":"http://www.allmenus.com/tx/lufkin/177640-jack-in-the-box/menu/",
    "sg:phone":"+1 936 634 1985",
    "sg:postcode":"75904",
    "sg:province":"TX",
    "sg:tags":[
        "burger",
        "american"
    ],
    "wof:name":"Jack in the Box",
    "wof:placetype":"venue"
},
  "geometry": {"coordinates":[-94.757015,31.333222],"type":"Point"}
}