{
  "type": "Feature",
  "properties": {
    "iso:country":"US",
    "sg:address":"1220 Cambridge St",
    "sg:city":"Fort Worth",
    "sg:classifiers":[
        {
            "category":"Building & Trades",
            "subcategory":"Construction",
            "type":"Services"
        }
    ],
    "sg:phone":"+1 817 624 0935",
    "sg:postcode":"76114",
    "sg:province":"TX",
    "sg:tags":[
        "hanging",
        "contractor"
    ],
    "wof:name":"Blumes Custom Painting & Rmdlg",
    "wof:placetype":"venue"
},
  "geometry": {"coordinates":[-97.403339,32.780458],"type":"Point"}
}