{
  "type": "Feature",
  "properties": {
    "iso:country":"US",
    "sg:address":"3800 Buffalo Speedway",
    "sg:city":"Houston",
    "sg:classifiers":[
        {
            "category":"Building & Trades",
            "subcategory":"Cleaning & Sanitation",
            "type":"Services"
        }
    ],
    "sg:phone":"+1 713 572 8004",
    "sg:postcode":"77005",
    "sg:province":"TX",
    "sg:tags":[
        "janitor"
    ],
    "sg:website":"www.abm.com",
    "wof:name":"ABM Janitorial Svc",
    "wof:placetype":"venue"
},
  "geometry": {"coordinates":[-95.42843000000001,29.730922],"type":"Point"}
}