{
  "type": "Feature",
  "properties": {
    "iso:country":"US",
    "sg:address":"2122 Winberie Ct",
    "sg:city":"Katy",
    "sg:classifiers":[
        {
            "category":"Professional",
            "subcategory":"Management & Consulting",
            "type":"Services"
        }
    ],
    "sg:phone":"+1 281 693 0554",
    "sg:postcode":"77450",
    "sg:province":"TX",
    "wof:name":"Lhe Inc",
    "wof:placetype":"venue"
},
  "geometry": {"coordinates":[-95.75455599999999,29.750106],"type":"Point"}
}