{
  "type": "Feature",
  "properties": {
    "iso:country":"US",
    "sg:address":"224 W Beauregard Ave",
    "sg:city":"San Angelo",
    "sg:classifiers":[
        {
            "category":"Organizations",
            "subcategory":"Non-profit Organization",
            "type":"Services"
        }
    ],
    "sg:phone":"+1 325 659 1155",
    "sg:postcode":"76903",
    "sg:province":"TX",
    "sg:tags":[
        "information",
        "alcoholism",
        "treatment"
    ],
    "wof:name":"West Texas Recovery Ctr",
    "wof:placetype":"venue"
},
  "geometry": {"coordinates":[-100.44175199999999,31.46107],"type":"Point"}
}