{
  "type": "Feature",
  "properties": {
    "iso:country":"US",
    "sg:address":"903 S Ww White Rd",
    "sg:city":"San Antonio",
    "sg:classifiers":[
        {
            "category":"Social Services",
            "subcategory":"Child Care",
            "type":"Services"
        }
    ],
    "sg:phone":"+1 210 333 0166",
    "sg:postcode":"78220",
    "sg:province":"TX",
    "wof:name":"Eman Day & Nite Child Care",
    "wof:placetype":"venue"
},
  "geometry": {"coordinates":[-98.405618,29.414744],"type":"Point"}
}