{
  "type": "Feature",
  "properties": {
    "iso:country":"US",
    "sg:address":"6713 Briarwood Dr",
    "sg:city":"Amarillo",
    "sg:classifiers":[
        {
            "category":"Farming",
            "subcategory":"Livestock Farm",
            "type":"Manufacturing & Wholesale Goods"
        }
    ],
    "sg:phone":"+1 806 356 9072",
    "sg:postcode":"79124",
    "sg:province":"TX",
    "sg:tags":[
        "beef",
        "feedlot",
        "cattle"
    ],
    "wof:name":"Apple Cattle Co",
    "wof:placetype":"venue"
},
  "geometry": {"coordinates":[-101.91191499999999,35.231891],"type":"Point"}
}