{
  "type": "Feature",
  "properties": {
    "iso:country":"US",
    "sg:address":"2917 Bushnell Dr",
    "sg:city":"Austin",
    "sg:classifiers":[
        {
            "category":"Retail",
            "subcategory":"Portrait Studio",
            "type":"Services"
        }
    ],
    "sg:phone":"+1 512 264 0503",
    "sg:postcode":"78745",
    "sg:province":"TX",
    "sg:tags":[
        "photo"
    ],
    "wof:name":"Burto Pritzker Photography",
    "wof:placetype":"venue"
},
  "geometry": {"coordinates":[-97.817307,30.213244],"type":"Point"}
}