{
  "type": "Feature",
  "properties": {
    "iso:country":"US",
    "sg:address":"950 Colgate Dr",
    "sg:city":"College Station",
    "sg:classifiers":[
        {
            "category":"Real Estate",
            "subcategory":"Real Estate Operator",
            "type":"Services"
        }
    ],
    "sg:phone":"+1 979 764 8999",
    "sg:postcode":"77840",
    "sg:province":"TX",
    "sg:tags":[
        "apartment"
    ],
    "sg:website":"www.universitycommons.com",
    "wof:name":"University Commons Apartments",
    "wof:placetype":"venue"
},
  "geometry": {"coordinates":[-96.301078,30.618455],"type":"Point"}
}