{
  "type": "Feature",
  "properties": {
    "iso:country":"US",
    "sg:address":"4948 Broadway",
    "sg:city":"San Antonio",
    "sg:classifiers":[
        {
            "category":"Retail",
            "subcategory":"Laundry & Dry Cleaning",
            "type":"Services"
        }
    ],
    "sg:phone":"+1 210 821 5552",
    "sg:postcode":"78209",
    "sg:province":"TX",
    "sg:tags":[
        "cleaners",
        "agent",
        "garment"
    ],
    "wof:name":"Comet 1 Hour Cleaners",
    "wof:placetype":"venue"
},
  "geometry": {"coordinates":[-98.462903,29.472261],"type":"Point"}
}