{
  "type": "Feature",
  "properties": {
    "iso:country":"US",
    "sg:address":"7279 Crockett Martin Rd",
    "sg:city":"Conroe",
    "sg:classifiers":[
        {
            "category":"Retail",
            "subcategory":"Animal Services",
            "type":"Services"
        }
    ],
    "sg:phone":"+1 936 264 3642",
    "sg:postcode":"77306",
    "sg:province":"TX",
    "wof:name":"Primate Paradise Sanctuary",
    "wof:placetype":"venue"
},
  "geometry": {"coordinates":[-95.319351,30.313089],"type":"Point"}
}