{
  "type": "Feature",
  "properties": {
    "iso:country":"US",
    "sg:address":"506 S 7th St",
    "sg:city":"Harlingen",
    "sg:classifiers":[
        {
            "category":"Travel",
            "subcategory":"Hotels & Motels",
            "type":"Entertainment"
        }
    ],
    "sg:phone":"+1 956 425 1717",
    "sg:postcode":"78550",
    "sg:province":"TX",
    "sg:tags":[
        "breakfast",
        "bed"
    ],
    "wof:name":"Sims and Company",
    "wof:placetype":"venue"
},
  "geometry": {"coordinates":[-97.689227,26.187604],"type":"Point"}
}