{
  "type": "Feature",
  "properties": {
    "iso:country":"US",
    "sg:address":"3720 Old Spanish Trl",
    "sg:city":"Houston",
    "sg:classifiers":[
        {
            "category":"Fast Food",
            "type":"Food & Drink"
        },
        {
            "category":"Restaurant",
            "type":"Food & Drink"
        }
    ],
    "sg:phone":"+1 713 842 2137",
    "sg:postcode":"77021",
    "sg:province":"TX",
    "sg:tags":[
        "mexican"
    ],
    "wof:name":"Taco Bell",
    "wof:placetype":"venue"
},
  "geometry": {"coordinates":[-95.361065,29.701961],"type":"Point"}
}