{
  "type": "Feature",
  "properties": {
    "iso:country":"US",
    "sg:address":"1994 Airport Loop",
    "sg:city":"Kerrville",
    "sg:classifiers":[
        {
            "category":"Wholesale",
            "subcategory":"Farm Supplies",
            "type":"Manufacturing & Wholesale Goods"
        },
        {
            "category":"Manufacturing",
            "subcategory":"Tools & Machinery",
            "type":"Manufacturing & Wholesale Goods"
        }
    ],
    "sg:phone":"+1 830 895 9800",
    "sg:postcode":"78028",
    "sg:province":"TX",
    "sg:tags":[
        "feed",
        "control",
        "mfg",
        "sport",
        "f"
    ],
    "sg:website":"www.remingtonfeeders.com",
    "wof:name":"B & A Products",
    "wof:placetype":"venue"
},
  "geometry": {"coordinates":[-99.08294600000001,29.978185],"type":"Point"}
}