{
  "type": "Feature",
  "properties": {
    "iso:country":"US",
    "sg:address":"412 Hurst Creek Rd",
    "sg:city":"Austin",
    "sg:classifiers":[
        {
            "category":"Freight",
            "type":"Transportation"
        }
    ],
    "sg:phone":"+1 512 261 1110",
    "sg:postcode":"78734",
    "sg:province":"TX",
    "sg:tags":[
        "operator",
        "hauling",
        "trucking"
    ],
    "wof:name":"Robbins Motor Transportation",
    "wof:placetype":"venue"
},
  "geometry": {"coordinates":[-97.970189,30.376163],"type":"Point"}
}