{
  "type": "Feature",
  "properties": {
    "iso:country":"US",
    "sg:address":"2501 E Mayfield Rd",
    "sg:city":"Arlington",
    "sg:classifiers":[
        {
            "category":"Personal",
            "subcategory":"Beauty Salon",
            "type":"Services"
        }
    ],
    "sg:phone":"+1 817 419 8208",
    "sg:postcode":"76014",
    "sg:province":"TX",
    "sg:tags":[
        "manicuring"
    ],
    "wof:name":"Paris Nails",
    "wof:placetype":"venue"
},
  "geometry": {"coordinates":[-97.066766,32.69151],"type":"Point"}
}