{
  "type": "Feature",
  "properties": {
    "iso:country":"US",
    "sg:address":"20222 Co Rd 173",
    "sg:city":"Bullard",
    "sg:classifiers":[
        {
            "category":"Professional",
            "subcategory":"Art Services",
            "type":"Services"
        }
    ],
    "sg:phone":"+1 903 894 6944",
    "sg:postcode":"75757",
    "sg:province":"TX",
    "sg:tags":[
        "graphic",
        "designer"
    ],
    "wof:name":"EMH Graphic Design",
    "wof:placetype":"venue"
},
  "geometry": {"coordinates":[-95.359605,32.184887],"type":"Point"}
}