{
  "type": "Feature",
  "properties": {
    "iso:country":"US",
    "sg:address":"5030 E Paisano Dr",
    "sg:city":"El Paso",
    "sg:classifiers":[
        {
            "category":"Autos & Motor Vehicles",
            "subcategory":"Automobile Sales",
            "type":"Retail Goods"
        }
    ],
    "sg:phone":"+1 915 771 7905",
    "sg:postcode":"79905",
    "sg:province":"TX",
    "sg:tags":[
        "used"
    ],
    "wof:name":"Courtesy Motors",
    "wof:placetype":"venue"
},
  "geometry": {"coordinates":[-106.429924,31.768314],"type":"Point"}
}