{
  "type": "Feature",
  "properties": {
    "iso:country":"US",
    "sg:address":"207 Lackey St",
    "sg:city":"Cuero",
    "sg:classifiers":[
        {
            "category":"Home & Garden",
            "subcategory":"Home Furnishings",
            "type":"Retail Goods"
        }
    ],
    "sg:phone":"+1 361 275 5052",
    "sg:postcode":"77954",
    "sg:province":"TX",
    "sg:tags":[
        "repair"
    ],
    "wof:name":"Cano Upholstery",
    "wof:placetype":"venue"
},
  "geometry": {"coordinates":[-97.282132,29.087805],"type":"Point"}
}