{
  "type": "Feature",
  "properties": {
    "iso:country":"US",
    "sg:address":"229 E Main St",
    "sg:city":"Fredericksburg",
    "sg:classifiers":[
        {
            "category":"Banks & Credit Unions",
            "subcategory":"Bank",
            "type":"Services"
        },
        {
            "category":"Shopping",
            "subcategory":"Used Merchandise",
            "type":"Retail Goods"
        }
    ],
    "sg:phone":"+1 830 990 8266",
    "sg:postcode":"78624",
    "sg:province":"TX",
    "sg:tags":[
        "resale",
        "shop",
        "second",
        "hand"
    ],
    "wof:name":"Lauren Bade Antiques",
    "wof:placetype":"venue"
},
  "geometry": {"coordinates":[-98.870172,30.273507],"type":"Point"}
}