{
  "type": "Feature",
  "properties": {
    "iso:country":"US",
    "sg:address":"1204 N Wayside Dr",
    "sg:city":"Houston",
    "sg:classifiers":[
        {
            "category":"Shopping",
            "subcategory":"Hobbies, Toys, & Games",
            "type":"Retail Goods"
        }
    ],
    "sg:phone":"+1 713 670 9457",
    "sg:postcode":"77011",
    "sg:province":"TX",
    "sg:tags":[
        "supply"
    ],
    "wof:name":"Games Inc",
    "wof:placetype":"venue"
},
  "geometry": {"coordinates":[-95.30283799999999,29.745051],"type":"Point"}
}