{
  "type": "Feature",
  "properties": {
    "iso:country":"US",
    "sg:address":"2109 Grand Cayman Way",
    "sg:city":"Mesquite",
    "sg:classifiers":[
        {
            "category":"Banks & Credit Unions",
            "subcategory":"Financial Services",
            "type":"Services"
        }
    ],
    "sg:phone":"+1 972 289 8613",
    "sg:postcode":"75149",
    "sg:province":"TX",
    "sg:tags":[
        "trust",
        "investment",
        "real estate"
    ],
    "wof:name":"Donalson Resources",
    "wof:placetype":"venue"
},
  "geometry": {"coordinates":[-96.568484,32.757676],"type":"Point"}
}