{
  "type": "Feature",
  "properties": {
    "iso:country":"US",
    "sg:address":"20130 US Hwy 59",
    "sg:city":"Humble",
    "sg:classifiers":[
        {
            "category":"Shopping",
            "type":"Retail Goods"
        }
    ],
    "sg:phone":"+1 281 319 4494",
    "sg:postcode":"77338",
    "sg:province":"TX",
    "sg:tags":[
        "merchandise"
    ],
    "wof:name":"Simply Wireless Inc",
    "wof:placetype":"venue"
},
  "geometry": {"coordinates":[-95.266426,30.006971],"type":"Point"}
}