{
  "type": "Feature",
  "properties": {
    "iso:country":"US",
    "sg:address":"2022 W Northwest Hwy",
    "sg:city":"Grapevine",
    "sg:classifiers":[
        {
            "category":"Insurance",
            "subcategory":"Insurance Agent",
            "type":"Services"
        }
    ],
    "sg:phone":"+1 817 421 3230",
    "sg:postcode":"76051",
    "sg:province":"TX",
    "wof:name":"Fivash Insurance Group",
    "wof:placetype":"venue"
},
  "geometry": {"coordinates":[-97.09687700000001,32.941204],"type":"Point"}
}