{
  "type": "Feature",
  "properties": {
    "iso:country":"US",
    "sg:address":"5901 New York Ave",
    "sg:city":"Arlington",
    "sg:classifiers":[
        {
            "category":"Organizations",
            "subcategory":"Religious Organization",
            "type":"Services"
        }
    ],
    "sg:phone":"+1 817 468 2580",
    "sg:postcode":"76018",
    "sg:province":"TX",
    "sg:tags":[
        "church"
    ],
    "wof:name":"Beautiful Savior Luth Chr",
    "wof:placetype":"venue"
},
  "geometry": {"coordinates":[-97.07703600000001,32.650962],"type":"Point"}
}