{
  "type": "Feature",
  "properties": {
    "iso:country":"US",
    "sg:address":"706 N 13th St",
    "sg:city":"Haskell",
    "sg:classifiers":[
        {
            "category":"Personal",
            "subcategory":"Beauty Salon",
            "type":"Services"
        }
    ],
    "sg:phone":"+1 940 864 2587",
    "sg:postcode":"79521",
    "sg:province":"TX",
    "sg:tags":[
        "shop"
    ],
    "wof:name":"The Beauty Parlor",
    "wof:placetype":"venue"
},
  "geometry": {"coordinates":[-99.736266,33.16916],"type":"Point"}
}