{
  "type": "Feature",
  "properties": {
    "iso:country":"US",
    "sg:address":"610 Oak St",
    "sg:city":"Graham",
    "sg:classifiers":[
        {
            "category":"Insurance",
            "subcategory":"Insurance Agent",
            "type":"Services"
        }
    ],
    "sg:phone":"+1 940 549 5701",
    "sg:postcode":"76450",
    "sg:province":"TX",
    "wof:name":"Johnson Financial Consultants",
    "wof:placetype":"venue"
},
  "geometry": {"coordinates":[-98.591307,33.105779],"type":"Point"}
}