{
  "type": "Feature",
  "properties": {
    "iso:country":"US",
    "sg:address":"5317 Maple St",
    "sg:city":"Houston",
    "sg:classifiers":[
        {
            "category":"Shopping",
            "subcategory":"Gifts & Souvenirs",
            "type":"Retail Goods"
        }
    ],
    "sg:phone":"+1 713 664 3538",
    "sg:postcode":"77096",
    "sg:province":"TX",
    "wof:name":"Nature Speaks",
    "wof:placetype":"venue"
},
  "geometry": {"coordinates":[-95.478925,29.690962],"type":"Point"}
}