{
  "type": "Feature",
  "properties": {
    "iso:country":"US",
    "sg:address":"911 S Chestnut St",
    "sg:city":"Lufkin",
    "sg:classifiers":[
        {
            "category":"Communications",
            "type":"Services"
        }
    ],
    "sg:phone":"+1 936 632 6218",
    "sg:postcode":"75901",
    "sg:province":"TX",
    "wof:name":"Communications Workers Afl-Cio Local Union 6218",
    "wof:placetype":"venue"
},
  "geometry": {"coordinates":[-94.716505,31.329208],"type":"Point"}
}