{
  "type": "Feature",
  "properties": {
    "iso:country":"US",
    "sg:address":"704 Gresham St",
    "sg:city":"Smithville",
    "sg:classifiers":[
        {
            "category":"Professional",
            "type":"Services"
        }
    ],
    "sg:phone":"+1 512 360 2424",
    "sg:postcode":"78957",
    "sg:province":"TX",
    "wof:name":"Lori P Lancaster",
    "wof:placetype":"venue"
},
  "geometry": {"coordinates":[-97.155096,30.011969],"type":"Point"}
}