{
  "type": "Feature",
  "properties": {
    "iso:country":"US",
    "sg:address":"314 Biscayne Blvd",
    "sg:city":"Seabrook",
    "sg:classifiers":[
        {
            "category":"Manufacturing",
            "subcategory":"Apparel",
            "type":"Manufacturing & Wholesale Goods"
        }
    ],
    "sg:phone":"+1 281 326 0287",
    "sg:postcode":"77586",
    "sg:province":"TX",
    "wof:name":"Embroidery Magic",
    "wof:placetype":"venue"
},
  "geometry": {"coordinates":[-95.04524600000001,29.567265],"type":"Point"}
}