{
  "type": "Feature",
  "properties": {
    "iso:country":"US",
    "sg:address":"246 Caroline St",
    "sg:city":"Houston",
    "sg:classifiers":[
        {
            "category":"Retail",
            "subcategory":"Veterinary Services",
            "type":"Services"
        }
    ],
    "sg:phone":"+1 713 672 1790",
    "sg:postcode":"77002",
    "sg:province":"TX",
    "sg:tags":[
        "hospital",
        "animal"
    ],
    "wof:name":"All Gods Creature Veterinary C",
    "wof:placetype":"venue"
},
  "geometry": {"coordinates":[-95.357957,29.761089],"type":"Point"}
}