{
  "type": "Feature",
  "properties": {
    "iso:country":"US",
    "sg:address":"1112 N Zang Blvd",
    "sg:city":"Dallas",
    "sg:classifiers":[
        {
            "category":"Professional",
            "subcategory":"Art Services",
            "type":"Services"
        }
    ],
    "sg:phone":"+1 214 942 0440",
    "sg:postcode":"75203",
    "sg:province":"TX",
    "sg:tags":[
        "commercial",
        "photography",
        "design"
    ],
    "wof:name":"Wilder Studios",
    "wof:placetype":"venue"
},
  "geometry": {"coordinates":[-96.821843,32.757283],"type":"Point"}
}