{
  "type": "Feature",
  "properties": {
    "iso:country":"US",
    "sg:address":"309 S Benton St",
    "sg:city":"Big Spring",
    "sg:classifiers":[
        {
            "category":"Wholesale",
            "subcategory":"Home Furnishings",
            "type":"Manufacturing & Wholesale Goods"
        }
    ],
    "sg:phone":"+1 432 267 5000",
    "sg:postcode":"79720",
    "sg:province":"TX",
    "wof:name":"Hope House Inspirational Pdts",
    "wof:placetype":"venue"
},
  "geometry": {"coordinates":[-101.47004099999999,32.255115],"type":"Point"}
}