{
  "type": "Feature",
  "properties": {
    "iso:country":"US",
    "sg:address":"222 Mandalay Canal",
    "sg:city":"Irving",
    "sg:classifiers":[
        {
            "category":"Professional",
            "subcategory":"Computer Services",
            "type":"Services"
        }
    ],
    "sg:phone":"+1 469 420 3100",
    "sg:postcode":"75039",
    "sg:province":"TX",
    "sg:tags":[
        "related"
    ],
    "wof:name":"Didata (dc) Inc",
    "wof:placetype":"venue"
},
  "geometry": {"coordinates":[-96.93940600000001,32.865673],"type":"Point"}
}