{
  "type": "Feature",
  "properties": {
    "iso:country":"US",
    "sg:address":"1012 W 3rd St",
    "sg:city":"Big Spring",
    "sg:classifiers":[
        {
            "category":"Food & Beverages",
            "subcategory":"Liquor & Beverages",
            "type":"Retail Goods"
        }
    ],
    "sg:phone":"+1 432 267 9171",
    "sg:postcode":"79720",
    "sg:province":"TX",
    "sg:tags":[
        "alcoholic"
    ],
    "wof:name":"Lous Cafe",
    "wof:placetype":"venue"
},
  "geometry": {"coordinates":[-101.48746199999999,32.248475],"type":"Point"}
}