{
  "type": "Feature",
  "properties": {
    "iso:country":"US",
    "sg:address":"3621 Colbath Ave",
    "sg:city":"Mcallen",
    "sg:classifiers":[
        {
            "category":"Shopping",
            "subcategory":"Clothing, Apparel, & Fashions",
            "type":"Retail Goods"
        }
    ],
    "sg:phone":"+1 956 682 6182",
    "sg:postcode":"78503",
    "sg:province":"TX",
    "wof:name":"Wild Closet",
    "wof:placetype":"venue"
},
  "geometry": {"coordinates":[-98.264071,26.192],"type":"Point"}
}