{
  "type": "Feature",
  "properties": {
    "iso:country":"US",
    "sg:address":"719 SW 35th St",
    "sg:city":"San Antonio",
    "sg:classifiers":[
        {
            "category":"Retail",
            "subcategory":"Photofinishing",
            "type":"Services"
        }
    ],
    "sg:phone":"+1 210 431 0983",
    "sg:postcode":"78237",
    "sg:province":"TX",
    "sg:tags":[
        "photo",
        "finishing"
    ],
    "wof:name":"Unidos Action Shots",
    "wof:placetype":"venue"
},
  "geometry": {"coordinates":[-98.571708,29.415776],"type":"Point"}
}