{
  "type": "Feature",
  "properties": {
    "iso:country":"US",
    "sg:address":"915 Layfair Pl",
    "sg:city":"Friendswood",
    "sg:classifiers":[
        {
            "category":"Wholesale",
            "subcategory":"Farm Supplies",
            "type":"Manufacturing & Wholesale Goods"
        }
    ],
    "sg:phone":"+1 281 992 5331",
    "sg:postcode":"77546",
    "sg:province":"TX",
    "sg:tags":[
        "chemical",
        "agricultural"
    ],
    "wof:name":"Dow Agro Sciences",
    "wof:placetype":"venue"
},
  "geometry": {"coordinates":[-95.19470099999999,29.500169],"type":"Point"}
}