{
  "type": "Feature",
  "properties": {
    "iso:country":"US",
    "sg:address":"114 Ralph Ablanedo Dr",
    "sg:city":"Austin",
    "sg:classifiers":[
        {
            "category":"Professional",
            "subcategory":"Management & Consulting",
            "type":"Services"
        }
    ],
    "sg:phone":"+1 512 383 2800",
    "sg:postcode":"78748",
    "sg:province":"TX",
    "wof:name":"Wattinger Management Co Inc",
    "wof:placetype":"venue"
},
  "geometry": {"coordinates":[-97.789143,30.174359],"type":"Point"}
}