{
  "type": "Feature",
  "properties": {
    "iso:country":"US",
    "sg:address":"5128 Horseshoe Trl",
    "sg:city":"Dallas",
    "sg:classifiers":[
        {
            "category":"Home & Garden",
            "subcategory":"Home Furnishings",
            "type":"Retail Goods"
        }
    ],
    "sg:phone":"+1 214 351 0381",
    "sg:postcode":"75209",
    "sg:province":"TX",
    "sg:tags":[
        "baths-equipment",
        "supply"
    ],
    "wof:name":"Restroom Equip. Co.",
    "wof:placetype":"venue"
},
  "geometry": {"coordinates":[-96.823408,32.859058],"type":"Point"}
}