{
  "type": "Feature",
  "properties": {
    "iso:country":"US",
    "sg:address":"3401 Altamesa Blvd",
    "sg:city":"Fort Worth",
    "sg:classifiers":[
        {
            "category":"Professional",
            "subcategory":"Business Services",
            "type":"Services"
        }
    ],
    "sg:phone":"+1 817 292 8589",
    "sg:postcode":"76133",
    "sg:province":"TX",
    "sg:tags":[
        "telemarketing"
    ],
    "wof:name":"Telcom Productions Inc",
    "wof:placetype":"venue"
},
  "geometry": {"coordinates":[-97.36596,32.649388],"type":"Point"}
}