{
  "type": "Feature",
  "properties": {
    "iso:country":"US",
    "sg:address":"2333 Klattenhoff Dr",
    "sg:city":"Austin",
    "sg:classifiers":[
        {
            "category":"Professional",
            "subcategory":"Management & Consulting",
            "type":"Services"
        }
    ],
    "sg:phone":"+1 512 251 6644",
    "sg:postcode":"78728",
    "sg:province":"TX",
    "wof:name":"Weikal Media",
    "wof:placetype":"venue"
},
  "geometry": {"coordinates":[-97.683859,30.441618],"type":"Point"}
}