{
  "type": "Feature",
  "properties": {
    "iso:country":"US",
    "sg:address":"2525 Richmond Ave",
    "sg:city":"El Paso",
    "sg:classifiers":[
        {
            "category":"Professional",
            "subcategory":"Engineering",
            "type":"Services"
        }
    ],
    "sg:phone":"+1 915 562 3616",
    "sg:postcode":"79930",
    "sg:province":"TX",
    "wof:name":"Technical Strategies Inc",
    "wof:placetype":"venue"
},
  "geometry": {"coordinates":[-106.466252,31.795985],"type":"Point"}
}