{
  "type": "Feature",
  "properties": {
    "iso:country":"US",
    "sg:address":"4308 Bragg Pl",
    "sg:city":"Plano",
    "sg:classifiers":[
        {
            "category":"Personal",
            "subcategory":"Beauty Salon",
            "type":"Services"
        }
    ],
    "sg:phone":"+1 972 618 4010",
    "sg:postcode":"75024",
    "sg:province":"TX",
    "sg:tags":[
        "shop"
    ],
    "wof:name":"A Professional Electrolysis",
    "wof:placetype":"venue"
},
  "geometry": {"coordinates":[-96.775266,33.066257],"type":"Point"}
}