{
  "type": "Feature",
  "properties": {
    "iso:country":"US",
    "sg:address":"3002 N Arkansas Ave",
    "sg:city":"Laredo",
    "sg:classifiers":[
        {
            "category":"Autos & Motor Vehicles",
            "subcategory":"Automobile Sales",
            "type":"Retail Goods"
        }
    ],
    "sg:phone":"+1 956 724 6311",
    "sg:postcode":"78043",
    "sg:province":"TX",
    "sg:tags":[
        "car",
        "dealer"
    ],
    "wof:name":"Laurel Used Cars",
    "wof:placetype":"venue"
},
  "geometry": {"coordinates":[-99.468068,27.524072],"type":"Point"}
}