{
  "type": "Feature",
  "properties": {
    "iso:country":"US",
    "sg:address":"8660 Santa Clara Dr",
    "sg:city":"Frisco",
    "sg:classifiers":[
        {
            "category":"Building & Trades",
            "subcategory":"Construction",
            "type":"Services"
        }
    ],
    "sg:phone":"+1 972 335 3451",
    "sg:postcode":"75034",
    "sg:province":"TX",
    "sg:tags":[
        "house"
    ],
    "wof:name":"Zimmerman Construction",
    "wof:placetype":"venue"
},
  "geometry": {"coordinates":[-96.80971700000001,33.154887],"type":"Point"}
}