{
  "type": "Feature",
  "properties": {
    "iso:country":"US",
    "sg:address":"325 W King Ave",
    "sg:city":"Kingsville",
    "sg:classifiers":[
        {
            "category":"Retail",
            "subcategory":"Repair Shop",
            "type":"Services"
        }
    ],
    "sg:phone":"+1 361 592 2561",
    "sg:postcode":"78363",
    "sg:province":"TX",
    "sg:tags":[
        "appliance"
    ],
    "wof:name":"S & G Appliances",
    "wof:placetype":"venue"
},
  "geometry": {"coordinates":[-97.871689,27.515458],"type":"Point"}
}