{
  "type": "Feature",
  "properties": {
    "iso:country":"US",
    "sg:address":"2820 57th St",
    "sg:city":"Lubbock",
    "sg:classifiers":[
        {
            "category":"Autos & Motor Vehicles",
            "subcategory":"Automobile Sales",
            "type":"Retail Goods"
        }
    ],
    "sg:phone":"+1 806 785 1285",
    "sg:postcode":"79413",
    "sg:province":"TX",
    "sg:tags":[
        "aircraft"
    ],
    "wof:name":"Nettech Aviation",
    "wof:placetype":"venue"
},
  "geometry": {"coordinates":[-101.87859,33.542262],"type":"Point"}
}