{
  "type": "Feature",
  "properties": {
    "iso:country":"US",
    "sg:address":"4116 Voss Hills Pl",
    "sg:city":"Dallas",
    "sg:classifiers":[
        {
            "category":"Professional",
            "subcategory":"Business Services",
            "type":"Services"
        }
    ],
    "sg:phone":"+1 972 733 3688",
    "sg:postcode":"75287",
    "sg:province":"TX",
    "wof:name":"Opulence",
    "wof:placetype":"venue"
},
  "geometry": {"coordinates":[-96.840388,33.010062],"type":"Point"}
}