{
  "type": "Feature",
  "properties": {
    "iso:country":"US",
    "sg:address":"10017 Regal Park Ln",
    "sg:city":"Dallas",
    "sg:classifiers":[
        {
            "category":"Retail",
            "subcategory":"Repair Shop",
            "type":"Services"
        }
    ],
    "sg:phone":"+1 214 691 7475",
    "sg:postcode":"75230",
    "sg:province":"TX",
    "wof:name":"Gary Bauchman Piano Servi",
    "wof:placetype":"venue"
},
  "geometry": {"coordinates":[-96.77313100000001,32.885189],"type":"Point"}
}