{
  "type": "Feature",
  "properties": {
    "iso:country":"US",
    "sg:address":"303 Gessner Rd",
    "sg:city":"Houston",
    "sg:classifiers":[
        {
            "category":"Shopping",
            "subcategory":"Clothing, Apparel, & Fashions",
            "type":"Retail Goods"
        }
    ],
    "sg:phone":"+1 713 463 8751",
    "sg:postcode":"77024",
    "sg:province":"TX",
    "sg:website":"www.jjill.com",
    "wof:name":"J Jill",
    "wof:placetype":"venue"
},
  "geometry": {"coordinates":[-95.544949,29.761532],"type":"Point"}
}