{
  "type": "Feature",
  "properties": {
    "iso:country":"US",
    "sg:address":"4022 Sun Valley Dr",
    "sg:city":"Dallas",
    "sg:classifiers":[
        {
            "category":"Autos & Motor Vehicles",
            "subcategory":"Auto Supplies",
            "type":"Retail Goods"
        }
    ],
    "sg:phone":"+1 214 662 7853",
    "sg:postcode":"75216",
    "sg:province":"TX",
    "wof:name":"Cowboy Tire Shine",
    "wof:placetype":"venue"
},
  "geometry": {"coordinates":[-96.821133,32.694683],"type":"Point"}
}