{
  "type": "Feature",
  "properties": {
    "iso:country":"US",
    "sg:address":"400 N 13th St",
    "sg:city":"West Columbia",
    "sg:classifiers":[
        {
            "category":"Local Transit",
            "type":"Transportation"
        }
    ],
    "sg:phone":"+1 979 345 2390",
    "sg:postcode":"77486",
    "sg:province":"TX",
    "sg:tags":[
        "ambulance"
    ],
    "wof:name":"Central Emergency Medical Svcs",
    "wof:placetype":"venue"
},
  "geometry": {"coordinates":[-95.64143900000001,29.148007],"type":"Point"}
}