{
  "type": "Feature",
  "properties": {
    "iso:country":"US",
    "sg:address":"2750 State Hwy 1604",
    "sg:city":"San Antonio",
    "sg:classifiers":[
        {
            "category":"Food & Beverages",
            "subcategory":"Groceries & Convenience Stores",
            "type":"Retail Goods"
        }
    ],
    "sg:phone":"+1 210 624 2135",
    "sg:postcode":"78264",
    "sg:province":"TX",
    "sg:tags":[
        "station",
        "gasoline"
    ],
    "wof:name":"Oak Island Ice House",
    "wof:placetype":"venue"
},
  "geometry": {"coordinates":[-98.45272199999999,29.22028],"type":"Point"}
}