{
  "type": "Feature",
  "properties": {
    "iso:country":"US",
    "sg:address":"2611 Clark Blvd",
    "sg:city":"Laredo",
    "sg:classifiers":[
        {
            "category":"Banks & Credit Unions",
            "subcategory":"Financial Services",
            "type":"Services"
        }
    ],
    "sg:phone":"+1 956 725 9819",
    "sg:postcode":"78043",
    "sg:province":"TX",
    "sg:tags":[
        "investor"
    ],
    "wof:name":"Joseph M Jackson Investments",
    "wof:placetype":"venue"
},
  "geometry": {"coordinates":[-99.46912500000001,27.516572],"type":"Point"}
}