{
  "type": "Feature",
  "properties": {
    "iso:country":"US",
    "sg:address":"1328 Inwood Rd",
    "sg:city":"Dallas",
    "sg:classifiers":[
        {
            "category":"Communications",
            "subcategory":"Film & Video Production",
            "type":"Services"
        }
    ],
    "sg:phone":"+1 214 688 5935",
    "sg:postcode":"75247",
    "sg:province":"TX",
    "sg:tags":[
        "motion"
    ],
    "wof:name":"Spindle Top Productions Inc",
    "wof:placetype":"venue"
},
  "geometry": {"coordinates":[-96.851902,32.806982],"type":"Point"}
}