{
  "type": "Feature",
  "properties": {
    "iso:country":"US",
    "sg:address":"1207 W Cameron Ave",
    "sg:city":"Rockdale",
    "sg:classifiers":[
        {
            "category":"Autos & Motor Vehicles",
            "subcategory":"Automobile Sales",
            "type":"Retail Goods"
        }
    ],
    "sg:phone":"+1 512 446 4600",
    "sg:postcode":"76567",
    "sg:province":"TX",
    "sg:tags":[
        "used"
    ],
    "wof:name":"D & D Automart",
    "wof:placetype":"venue"
},
  "geometry": {"coordinates":[-97.01433900000001,30.649529],"type":"Point"}
}