{
  "type": "Feature",
  "properties": {
    "iso:country":"US",
    "sg:address":"1916 Seaview Dr",
    "sg:city":"Flower Mound",
    "sg:classifiers":[
        {
            "category":"Wholesale",
            "subcategory":"Medical Equipment & Supplies",
            "type":"Manufacturing & Wholesale Goods"
        }
    ],
    "sg:phone":"+1 972 539 2862",
    "sg:postcode":"75022",
    "sg:province":"TX",
    "wof:name":"Steel Enterprises",
    "wof:placetype":"venue"
},
  "geometry": {"coordinates":[-97.104105,33.009724],"type":"Point"}
}