{
  "type": "Feature",
  "properties": {
    "iso:country":"US",
    "sg:address":"13511 Regional Dr",
    "sg:city":"Laredo",
    "sg:classifiers":[
        {
            "category":"Wholesale",
            "subcategory":"Construction Materials",
            "type":"Manufacturing & Wholesale Goods"
        }
    ],
    "sg:phone":"+1 956 725 4737",
    "sg:postcode":"78045",
    "sg:province":"TX",
    "wof:name":"Capitol Aggregates Inc (del)",
    "wof:placetype":"venue"
},
  "geometry": {"coordinates":[-99.45668999999999,27.69286],"type":"Point"}
}