{
  "type": "Feature",
  "properties": {
    "iso:country":"US",
    "sg:address":"507 Baker Rd",
    "sg:city":"Houston",
    "sg:classifiers":[
        {
            "category":"Banks & Credit Unions",
            "subcategory":"Bank",
            "type":"Services"
        }
    ],
    "sg:phone":"+1 713 867 2114",
    "sg:postcode":"77094",
    "sg:province":"TX",
    "wof:name":"Compass Bank",
    "wof:placetype":"venue"
},
  "geometry": {"coordinates":[-95.701824,29.780008],"type":"Point"}
}