{
  "type": "Feature",
  "properties": {
    "iso:country":"US",
    "sg:address":"800 E Loop 281",
    "sg:city":"Longview",
    "sg:classifiers":[
        {
            "category":"Organizations",
            "subcategory":"Religious Organization",
            "type":"Services"
        }
    ],
    "sg:phone":"+1 903 753 3768",
    "sg:postcode":"75605",
    "sg:province":"TX",
    "wof:name":"Longview Mssnary Baptst Church",
    "wof:placetype":"venue"
},
  "geometry": {"coordinates":[-94.705513,32.530018],"type":"Point"}
}