{
  "type": "Feature",
  "properties": {
    "iso:country":"US",
    "sg:address":"2005 W University Dr",
    "sg:city":"Edinburg",
    "sg:classifiers":[
        {
            "category":"Health Services",
            "subcategory":"Doctor",
            "type":"Services"
        }
    ],
    "sg:phone":"+1 956 318 1400",
    "sg:postcode":"78539",
    "sg:province":"TX",
    "sg:tags":[
        "physician",
        "surgeon",
        "eye",
        "clinic",
        "surgery"
    ],
    "wof:name":"University Eye Center",
    "wof:placetype":"venue"
},
  "geometry": {"coordinates":[-98.184753,26.304713],"type":"Point"}
}