{
  "type": "Feature",
  "properties": {
    "iso:country":"US",
    "sg:address":"506 Vis Cove",
    "sg:city":"Victoria",
    "sg:classifiers":[
        {
            "category":"Professional",
            "subcategory":"Business Services",
            "type":"Services"
        }
    ],
    "sg:phone":"+1 361 572 0414",
    "sg:postcode":"77904",
    "sg:province":"TX",
    "wof:name":"Korczynski Enterprizes",
    "wof:placetype":"venue"
},
  "geometry": {"coordinates":[-97.00915999999999,28.867814],"type":"Point"}
}