{
  "type": "Feature",
  "properties": {
    "iso:country":"US",
    "sg:address":"13239 Shorecliff St",
    "sg:city":"San Antonio",
    "sg:classifiers":[
        {
            "category":"Recreation",
            "type":"Entertainment"
        }
    ],
    "sg:phone":"+1 210 492 9014",
    "sg:postcode":"78248",
    "sg:province":"TX",
    "wof:name":"Churchill Frest Recreation Ctr",
    "wof:placetype":"venue"
},
  "geometry": {"coordinates":[-98.52574799999999,29.566718],"type":"Point"}
}