{
  "type": "Feature",
  "properties": {
    "iso:country":"US",
    "sg:address":"1809 US Hwy 87",
    "sg:city":"Big Spring",
    "sg:classifiers":[
        {
            "category":"Health Services",
            "subcategory":"Nursing And Care Facility",
            "type":"Services"
        }
    ],
    "sg:phone":"+1 432 268 8387",
    "sg:postcode":"79720",
    "sg:province":"TX",
    "wof:name":"Lamun Lusk Sanchez Texas State",
    "wof:placetype":"venue"
},
  "geometry": {"coordinates":[-101.47254,32.237012],"type":"Point"}
}