{
  "type": "Feature",
  "properties": {
    "iso:country":"US",
    "sg:address":"100 Denise Dr",
    "sg:city":"Marshall",
    "sg:classifiers":[
        {
            "category":"Wholesale",
            "subcategory":"Machinery & Supplies",
            "type":"Manufacturing & Wholesale Goods"
        }
    ],
    "sg:phone":"+1 903 938 4545",
    "sg:postcode":"75672",
    "sg:province":"TX",
    "sg:tags":[
        "compressor",
        "gas"
    ],
    "wof:name":"Compressor Engineering Corp",
    "wof:placetype":"venue"
},
  "geometry": {"coordinates":[-94.301261,32.526136],"type":"Point"}
}