{
  "type": "Feature",
  "properties": {
    "iso:country":"US",
    "sg:address":"112 E FM 2410",
    "sg:city":"Harker Heights",
    "sg:classifiers":[
        {
            "category":"Restaurant",
            "type":"Food & Drink"
        }
    ],
    "sg:phone":"+1 254 699 2361",
    "sg:postcode":"76548",
    "sg:province":"TX",
    "sg:tags":[
        "eating"
    ],
    "wof:name":"Dairy Queen",
    "wof:placetype":"venue"
},
  "geometry": {"coordinates":[-97.672605,31.073224],"type":"Point"}
}