{
  "type": "Feature",
  "properties": {
    "iso:country":"US",
    "sg:address":"4214 N Capital of Texas Hwy",
    "sg:city":"Austin",
    "sg:classifiers":[
        {
            "category":"Real Estate",
            "subcategory":"Developer",
            "type":"Services"
        },
        {
            "category":"Retail",
            "subcategory":"Funeral Services",
            "type":"Services"
        }
    ],
    "sg:phone":"+1 512 329 6007",
    "sg:postcode":"78746",
    "sg:province":"TX",
    "sg:tags":[
        "cemetery"
    ],
    "wof:name":"Remembrance Gardens",
    "wof:placetype":"venue"
},
  "geometry": {"coordinates":[-97.80243299999999,30.341457],"type":"Point"}
}