{
  "type": "Feature",
  "properties": {
    "iso:country":"US",
    "sg:address":"720 Sheldon Rd",
    "sg:city":"Channelview",
    "sg:classifiers":[
        {
            "category":"Retail",
            "subcategory":"Auto Repair",
            "type":"Services"
        }
    ],
    "sg:phone":"+1 281 457 5656",
    "sg:postcode":"77530",
    "sg:province":"TX",
    "sg:tags":[
        "automobile",
        "lubrication",
        "automotive"
    ],
    "wof:name":"Lojo Express Oil & Lube Inc",
    "wof:placetype":"venue"
},
  "geometry": {"coordinates":[-95.124572,29.786959],"type":"Point"}
}