{
  "type": "Feature",
  "properties": {
    "iso:country":"US",
    "sg:address":"100 N College St",
    "sg:city":"Waxahachie",
    "sg:classifiers":[
        {
            "category":"Personal",
            "subcategory":"Barber",
            "type":"Services"
        }
    ],
    "sg:phone":"+1 972 937 8993",
    "sg:postcode":"75165",
    "sg:province":"TX",
    "wof:name":"The Elm Street Barber Shop",
    "wof:placetype":"venue"
},
  "geometry": {"coordinates":[-96.847313,32.385639],"type":"Point"}
}