{
  "type": "Feature",
  "properties": {
    "iso:country":"US",
    "sg:address":"7724 Nardo Goodman Dr",
    "sg:city":"El Paso",
    "sg:classifiers":[
        {
            "category":"Professional",
            "type":"Services"
        }
    ],
    "sg:phone":"+1 915 585 8438",
    "sg:postcode":"79912",
    "sg:province":"TX",
    "wof:name":"Pride A Red Ltd",
    "wof:placetype":"venue"
},
  "geometry": {"coordinates":[-106.561787,31.873986],"type":"Point"}
}