{
  "type": "Feature",
  "properties": {
    "iso:country":"US",
    "sg:address":"7001 E Lancaster Ave",
    "sg:city":"Fort Worth",
    "sg:classifiers":[
        {
            "category":"Building & Trades",
            "subcategory":"Construction",
            "type":"Services"
        }
    ],
    "sg:phone":"+1 817 654 1200",
    "sg:postcode":"76112",
    "sg:province":"TX",
    "sg:tags":[
        "contractor"
    ],
    "wof:name":"Simbesco Builders",
    "wof:placetype":"venue"
},
  "geometry": {"coordinates":[-97.207601,32.730101],"type":"Point"}
}