{
  "type": "Feature",
  "properties": {
    "iso:country":"US",
    "sg:address":"159 Mill Stream Ln",
    "sg:city":"Houston",
    "sg:classifiers":[
        {
            "category":"Building & Trades",
            "subcategory":"Construction",
            "type":"Services"
        }
    ],
    "sg:phone":"+1 281 448 9171",
    "sg:postcode":"77060",
    "sg:province":"TX",
    "sg:tags":[
        "house"
    ],
    "wof:name":"Alvarengas Remodeling",
    "wof:placetype":"venue"
},
  "geometry": {"coordinates":[-95.40482900000001,29.93048],"type":"Point"}
}