{
  "type": "Feature",
  "properties": {
    "iso:country":"US",
    "sg:address":"1446 FM 1750",
    "sg:city":"Abilene",
    "sg:classifiers":[
        {
            "category":"Manufacturing",
            "subcategory":"Food",
            "type":"Manufacturing & Wholesale Goods"
        }
    ],
    "sg:phone":"+1 325 529 3723",
    "sg:postcode":"79602",
    "sg:province":"TX",
    "sg:tags":[
        "product",
        "dairy",
        "mfg"
    ],
    "wof:name":"Charles G Hogsett",
    "wof:placetype":"venue"
},
  "geometry": {"coordinates":[-99.682472,32.328663],"type":"Point"}
}