{
  "type": "Feature",
  "properties": {
    "iso:country":"US",
    "sg:address":"10715 Gulfdale St",
    "sg:city":"San Antonio",
    "sg:classifiers":[
        {
            "category":"Communications",
            "subcategory":"Film & Video Production",
            "type":"Services"
        }
    ],
    "sg:phone":"+1 210 979 7687",
    "sg:postcode":"78216",
    "sg:province":"TX",
    "sg:tags":[
        "taping"
    ],
    "wof:name":"Cal Productions",
    "wof:placetype":"venue"
},
  "geometry": {"coordinates":[-98.48787799999999,29.535168],"type":"Point"}
}