{
  "type": "Feature",
  "properties": {
    "iso:country":"US",
    "sg:address":"4102 Center St",
    "sg:city":"Deer Park",
    "sg:classifiers":[
        {
            "category":"Professional",
            "type":"Services"
        }
    ],
    "sg:phone":"+1 281 479 7460",
    "sg:postcode":"77536",
    "sg:province":"TX",
    "wof:name":"Ba Lender",
    "wof:placetype":"venue"
},
  "geometry": {"coordinates":[-95.123277,29.6749],"type":"Point"}
}