{
  "type": "Feature",
  "properties": {
    "iso:country":"US",
    "sg:address":"8457 Sassman Rd",
    "sg:city":"Austin",
    "sg:classifiers":[
        {
            "category":"Professional",
            "subcategory":"Advertising",
            "type":"Services"
        },
        {
            "category":"Manufacturing",
            "subcategory":"Signs",
            "type":"Manufacturing & Wholesale Goods"
        }
    ],
    "sg:phone":"+1 512 243 2854",
    "sg:postcode":"78747",
    "sg:province":"TX",
    "sg:tags":[
        "signs-erectors",
        "hanger",
        "specialty"
    ],
    "wof:name":"J Y Sign Svc",
    "wof:placetype":"venue"
},
  "geometry": {"coordinates":[-97.71659,30.132544],"type":"Point"}
}