{
  "type": "Feature",
  "properties": {
    "iso:country":"US",
    "sg:address":"3724 95th St",
    "sg:city":"Lubbock",
    "sg:classifiers":[
        {
            "category":"Professional",
            "subcategory":"Accounting & Tax Preparation",
            "type":"Services"
        }
    ],
    "sg:phone":"+1 806 792 7173",
    "sg:postcode":"79423",
    "sg:province":"TX",
    "sg:tags":[
        "bookkeeping",
        "general"
    ],
    "wof:name":"M & W Business Svc",
    "wof:placetype":"venue"
},
  "geometry": {"coordinates":[-101.894531,33.508593],"type":"Point"}
}