{
  "type": "Feature",
  "properties": {
    "iso:country":"US",
    "sg:address":"6210 Orleans Dr",
    "sg:city":"Austin",
    "sg:classifiers":[
        {
            "category":"Building & Trades",
            "subcategory":"Landscaping Services",
            "type":"Services"
        }
    ],
    "sg:phone":"+1 512 280 2959",
    "sg:postcode":"78744",
    "sg:province":"TX",
    "sg:tags":[
        "tree"
    ],
    "wof:name":"Out On A Limb Tree Service",
    "wof:placetype":"venue"
},
  "geometry": {"coordinates":[-97.73988799999999,30.169028],"type":"Point"}
}