{
  "type": "Feature",
  "properties": {
    "iso:country":"US",
    "sg:address":"1418 Orchid Ave",
    "sg:city":"Mcallen",
    "sg:classifiers":[
        {
            "category":"Professional",
            "subcategory":"Testing Lab",
            "type":"Services"
        }
    ],
    "sg:phone":"+1 956 631 5140",
    "sg:postcode":"78504",
    "sg:province":"TX",
    "sg:tags":[
        "laboratory"
    ],
    "wof:name":"Instrument Services Co",
    "wof:placetype":"venue"
},
  "geometry": {"coordinates":[-98.230367,26.241247],"type":"Point"}
}