{
  "type": "Feature",
  "properties": {
    "iso:country":"US",
    "sg:address":"501 Mays St",
    "sg:city":"Jasper",
    "sg:classifiers":[
        {
            "category":"Travel",
            "subcategory":"Hotels & Motels",
            "type":"Entertainment"
        }
    ],
    "sg:phone":"+1 409 384 3428",
    "sg:postcode":"75951",
    "sg:province":"TX",
    "sg:tags":[
        "operation"
    ],
    "wof:name":"Traveler's Motel",
    "wof:placetype":"venue"
},
  "geometry": {"coordinates":[-93.99520099999999,30.90996],"type":"Point"}
}