{
  "type": "Feature",
  "properties": {
    "iso:country":"US",
    "sg:address":"5506 Cowhorn Creek Rd",
    "sg:city":"Texarkana",
    "sg:classifiers":[
        {
            "category":"Insurance",
            "subcategory":"Hazard Insurance",
            "type":"Services"
        },
        {
            "category":"Insurance",
            "subcategory":"Insurance Agent",
            "type":"Services"
        },
        {
            "category":"Insurance",
            "subcategory":"Life Insurance",
            "type":"Services"
        }
    ],
    "sg:phone":"+1 903 223 3737",
    "sg:postcode":"75503",
    "sg:province":"TX",
    "sg:tags":[
        "auto"
    ],
    "sg:website":"http://statefarm.mqgroup.com/url.asp?usr=439404",
    "wof:name":"State Farm Insurance Agent-Larry Oxford",
    "wof:placetype":"venue"
},
  "geometry": {"coordinates":[-94.07804899999999,33.47078],"type":"Point"}
}