{
  "type": "Feature",
  "properties": {
    "iso:country":"US",
    "sg:address":"12195 US Hwy 287P Bus",
    "sg:city":"Fort Worth",
    "sg:classifiers":[
        {
            "category":"Wholesale",
            "subcategory":"Machinery & Supplies",
            "type":"Manufacturing & Wholesale Goods"
        }
    ],
    "sg:phone":"+1 817 439 5908",
    "sg:postcode":"76179",
    "sg:province":"TX",
    "sg:tags":[
        "equipment",
        "hydraulic"
    ],
    "wof:name":"Johnson Hydraulics",
    "wof:placetype":"venue"
},
  "geometry": {"coordinates":[-97.42084,32.943756],"type":"Point"}
}