{
  "type": "Feature",
  "properties": {
    "iso:country":"US",
    "sg:address":"2211 Norfolk St",
    "sg:city":"Houston",
    "sg:classifiers":[
        {
            "category":"Professional",
            "subcategory":"Management & Consulting",
            "type":"Services"
        }
    ],
    "sg:phone":"+1 713 807 0660",
    "sg:postcode":"77098",
    "sg:province":"TX",
    "sg:tags":[
        "consultant"
    ],
    "wof:name":"Transystems Advisors Inc",
    "wof:placetype":"venue"
},
  "geometry": {"coordinates":[-95.41497200000001,29.732642],"type":"Point"}
}