{
  "type": "Feature",
  "properties": {
    "iso:country":"US",
    "sg:address":"109 W 6th St",
    "sg:city":"Cisco",
    "sg:classifiers":[
        {
            "category":"Local Transit",
            "type":"Transportation"
        }
    ],
    "sg:phone":"+1 254 442 3543",
    "sg:postcode":"76437",
    "sg:province":"TX",
    "sg:tags":[
        "ambulance"
    ],
    "wof:name":"Cisco EMS",
    "wof:placetype":"venue"
},
  "geometry": {"coordinates":[-98.980407,32.389636],"type":"Point"}
}