{
  "type": "Feature",
  "properties": {
    "iso:country":"US",
    "sg:address":"2625 S 18th St",
    "sg:city":"Waco",
    "sg:classifiers":[
        {
            "category":"Organizations",
            "subcategory":"Religious Organization",
            "type":"Services"
        }
    ],
    "sg:phone":"+1 254 754 0660",
    "sg:postcode":"76706",
    "sg:province":"TX",
    "sg:tags":[
        "church"
    ],
    "wof:name":"Great Zion Missionary Baptist",
    "wof:placetype":"venue"
},
  "geometry": {"coordinates":[-97.120181,31.526684],"type":"Point"}
}