{
  "type": "Feature",
  "properties": {
    "iso:country":"US",
    "sg:address":"1325 Whitlock Ln",
    "sg:city":"Carrollton",
    "sg:classifiers":[
        {
            "category":"Wholesale",
            "subcategory":"Medical Equipment & Supplies",
            "type":"Manufacturing & Wholesale Goods"
        }
    ],
    "sg:phone":"+1 972 466 0800",
    "sg:postcode":"75006",
    "sg:province":"TX",
    "sg:tags":[
        "physician",
        "surgeon"
    ],
    "wof:name":"F & R Medical Solutions",
    "wof:placetype":"venue"
},
  "geometry": {"coordinates":[-96.910422,32.968456],"type":"Point"}
}