{
  "type": "Feature",
  "properties": {
    "iso:country":"US",
    "sg:address":"518 Elizabeth Ln",
    "sg:city":"Mansfield",
    "sg:classifiers":[
        {
            "category":"Building & Trades",
            "subcategory":"Landscaping Services",
            "type":"Services"
        }
    ],
    "sg:phone":"+1 817 453 4694",
    "sg:postcode":"76063",
    "sg:province":"TX",
    "sg:tags":[
        "landscape",
        "contractor"
    ],
    "wof:name":"Quick Landscape Lawn Maintenace",
    "wof:placetype":"venue"
},
  "geometry": {"coordinates":[-97.143843,32.557577],"type":"Point"}
}