{
  "type": "Feature",
  "properties": {
    "iso:country":"US",
    "sg:address":"707 Inwood Dr",
    "sg:city":"Bryan",
    "sg:classifiers":[
        {
            "category":"Professional",
            "subcategory":"Business Services",
            "type":"Services"
        }
    ],
    "sg:phone":"+1 979 846 3112",
    "sg:postcode":"77802",
    "sg:province":"TX",
    "wof:name":"A V D Lonestar",
    "wof:placetype":"venue"
},
  "geometry": {"coordinates":[-96.340644,30.635146],"type":"Point"}
}