{
  "type": "Feature",
  "properties": {
    "iso:country":"US",
    "sg:address":"13702 Gamma Rd",
    "sg:city":"Dallas",
    "sg:classifiers":[
        {
            "category":"Wholesale",
            "subcategory":"Computers",
            "type":"Manufacturing & Wholesale Goods"
        }
    ],
    "sg:phone":"+1 972 239 8511",
    "sg:postcode":"75244",
    "sg:province":"TX",
    "wof:name":"Gamma Group",
    "wof:placetype":"venue"
},
  "geometry": {"coordinates":[-96.836601,32.935398],"type":"Point"}
}