{
  "type": "Feature",
  "properties": {
    "iso:country":"US",
    "sg:address":"7111 Running Rope",
    "sg:city":"Austin",
    "sg:classifiers":[
        {
            "category":"Banks & Credit Unions",
            "subcategory":"Financial Services",
            "type":"Services"
        }
    ],
    "sg:phone":"+1 512 345 2764",
    "sg:postcode":"78731",
    "sg:province":"TX",
    "sg:tags":[
        "trust",
        "management"
    ],
    "wof:name":"SGB Management LLC",
    "wof:placetype":"venue"
},
  "geometry": {"coordinates":[-97.764315,30.36086],"type":"Point"}
}