{
  "type": "Feature",
  "properties": {
    "iso:country":"US",
    "sg:address":"2523 Nacogdoches Rd",
    "sg:city":"San Antonio",
    "sg:classifiers":[
        {
            "category":"Health Services",
            "subcategory":"Doctor",
            "type":"Services"
        }
    ],
    "sg:phone":"+1 210 822 1407",
    "sg:postcode":"78217",
    "sg:province":"TX",
    "wof:name":"Linton N Weens DDS",
    "wof:placetype":"venue"
},
  "geometry": {"coordinates":[-98.449331,29.518961],"type":"Point"}
}