{
  "type": "Feature",
  "properties": {
    "iso:country":"US",
    "sg:address":"15407 Woodcote Ct",
    "sg:city":"Houston",
    "sg:classifiers":[
        {
            "category":"Manufacturing",
            "subcategory":"Musical Instruments",
            "type":"Manufacturing & Wholesale Goods"
        }
    ],
    "sg:phone":"+1 281 480 8468",
    "sg:postcode":"77062",
    "sg:province":"TX",
    "sg:tags":[
        "mfg"
    ],
    "wof:name":"Drum-Tex",
    "wof:placetype":"venue"
},
  "geometry": {"coordinates":[-95.14158399999999,29.566261],"type":"Point"}
}