{
  "type": "Feature",
  "properties": {
    "iso:country":"US",
    "sg:address":"1910 S Saint Andrews Ct",
    "sg:city":"Arlington",
    "sg:classifiers":[
        {
            "category":"Banks & Credit Unions",
            "subcategory":"Financial Services",
            "type":"Services"
        }
    ],
    "sg:phone":"+1 817 274 7963",
    "sg:postcode":"76011",
    "sg:province":"TX",
    "sg:tags":[
        "investment",
        "closed"
    ],
    "wof:name":"Dry Creek Investment Co",
    "wof:placetype":"venue"
},
  "geometry": {"coordinates":[-97.11385,32.765672],"type":"Point"}
}