{
  "type": "Feature",
  "properties": {
    "iso:country":"US",
    "sg:address":"13802 Hokanson Rd",
    "sg:city":"Del Valle",
    "sg:classifiers":[
        {
            "category":"Building & Trades",
            "subcategory":"Landscaping Services",
            "type":"Services"
        }
    ],
    "sg:phone":"+1 512 243 3012",
    "sg:postcode":"78617",
    "sg:province":"TX",
    "sg:tags":[
        "landscape"
    ],
    "wof:name":"Genesis Landscaping Company",
    "wof:placetype":"venue"
},
  "geometry": {"coordinates":[-97.637477,30.099893],"type":"Point"}
}