{
  "type": "Feature",
  "properties": {
    "iso:country":"US",
    "sg:address":"2200 FM 1980",
    "sg:city":"Marble Falls",
    "sg:classifiers":[
        {
            "category":"Autos & Motor Vehicles",
            "subcategory":"Automobile Sales",
            "type":"Retail Goods"
        }
    ],
    "sg:phone":"+1 830 798 1686",
    "sg:postcode":"78654",
    "sg:province":"TX",
    "sg:tags":[
        "used"
    ],
    "wof:name":"Trading Post Auto Sales",
    "wof:placetype":"venue"
},
  "geometry": {"coordinates":[-98.30913700000001,30.615667],"type":"Point"}
}