{
  "type": "Feature",
  "properties": {
    "iso:country":"US",
    "sg:address":"105 W Morningside Dr",
    "sg:city":"S Padre Island",
    "sg:classifiers":[
        {
            "category":"Professional",
            "subcategory":"Lawyer & Legal Services",
            "type":"Services"
        }
    ],
    "sg:phone":"+1 956 761 2289",
    "sg:postcode":"78597",
    "sg:province":"TX",
    "sg:tags":[
        "attorney"
    ],
    "wof:name":"Rio Services",
    "wof:placetype":"venue"
},
  "geometry": {"coordinates":[-97.170963,26.126998],"type":"Point"}
}