{
  "type": "Feature",
  "properties": {
    "iso:country":"US",
    "sg:address":"14402 Export Rd",
    "sg:city":"Laredo",
    "sg:classifiers":[
        {
            "category":"Freight",
            "type":"Transportation"
        }
    ],
    "sg:phone":"+1 956 725 2244",
    "sg:postcode":"78045",
    "sg:province":"TX",
    "sg:tags":[
        "arrangement"
    ],
    "wof:name":"Martinez Alonzo Forwarding Co",
    "wof:placetype":"venue"
},
  "geometry": {"coordinates":[-99.540628,27.625041],"type":"Point"}
}