{
  "type": "Feature",
  "properties": {
    "iso:country":"US",
    "sg:address":"4014 S Broadway Ave",
    "sg:city":"Tyler",
    "sg:classifiers":[
        {
            "category":"Restaurant",
            "type":"Food & Drink"
        }
    ],
    "sg:menulink":"http://www.allmenus.com/tx/tyler/202518-mcdonalds/menu/",
    "sg:postcode":"75701",
    "sg:province":"TX",
    "sg:tags":[
        "burger",
        "american"
    ],
    "wof:name":"McDonald's",
    "wof:placetype":"venue"
},
  "geometry": {"coordinates":[-95.30068799999999,32.306498],"type":"Point"}
}