{
  "type": "Feature",
  "properties": {
    "iso:country":"US",
    "sg:address":"4079 Honey Bear Loop",
    "sg:city":"Round Rock",
    "sg:classifiers":[
        {
            "category":"Personal",
            "type":"Services"
        }
    ],
    "sg:phone":"+1 512 388 1587",
    "sg:postcode":"78681",
    "sg:province":"TX",
    "sg:tags":[
        "consultant",
        "wedding"
    ],
    "wof:name":"Debi's Secret Garden",
    "wof:placetype":"venue"
},
  "geometry": {"coordinates":[-97.75158399999999,30.551685],"type":"Point"}
}