{
  "type": "Feature",
  "properties": {
    "iso:country":"US",
    "sg:address":"1890 Lakeview Ln",
    "sg:city":"Denton",
    "sg:classifiers":[
        {
            "category":"Professional",
            "subcategory":"Business Services",
            "type":"Services"
        }
    ],
    "sg:phone":"+1 940 382 6054",
    "sg:postcode":"76208",
    "sg:province":"TX",
    "wof:name":"One Plus One Assoc",
    "wof:placetype":"venue"
},
  "geometry": {"coordinates":[-97.047558,33.190947],"type":"Point"}
}