{
  "type": "Feature",
  "properties": {
    "iso:country":"US",
    "sg:address":"7948 San Jose Rd",
    "sg:city":"El Paso",
    "sg:classifiers":[
        {
            "category":"Freight",
            "type":"Transportation"
        }
    ],
    "sg:phone":"+1 915 633 1441",
    "sg:postcode":"79915",
    "sg:province":"TX",
    "sg:tags":[
        "trucking"
    ],
    "wof:name":"TFC Trucking",
    "wof:placetype":"venue"
},
  "geometry": {"coordinates":[-106.35476,31.729684],"type":"Point"}
}