{
  "type": "Feature",
  "properties": {
    "iso:country":"US",
    "sg:address":"12527 Overcup Dr",
    "sg:city":"Houston",
    "sg:classifiers":[
        {
            "category":"Professional",
            "subcategory":"Business Services",
            "type":"Services"
        }
    ],
    "sg:phone":"+1 713 467 6604",
    "sg:postcode":"77024",
    "sg:province":"TX",
    "wof:name":"Penache Unlimited",
    "wof:placetype":"venue"
},
  "geometry": {"coordinates":[-95.552244,29.770817],"type":"Point"}
}