{
  "type": "Feature",
  "properties": {
    "iso:country":"US",
    "sg:address":"603 N 1st St",
    "sg:city":"Robstown",
    "sg:classifiers":[
        {
            "category":"Organizations",
            "subcategory":"Religious Organization",
            "type":"Services"
        }
    ],
    "sg:phone":"+1 361 387 3705",
    "sg:postcode":"78380",
    "sg:province":"TX",
    "wof:name":"St John Nepomuco",
    "wof:placetype":"venue"
},
  "geometry": {"coordinates":[-97.66832100000001,27.795113],"type":"Point"}
}