{
  "type": "Feature",
  "properties": {
    "iso:country":"US",
    "sg:address":"88 Oakmont Cir",
    "sg:city":"Belton",
    "sg:classifiers":[
        {
            "category":"Building & Trades",
            "subcategory":"Construction",
            "type":"Services"
        }
    ],
    "sg:phone":"+1 254 780 1012",
    "sg:postcode":"76513",
    "sg:province":"TX",
    "sg:tags":[
        "home",
        "builder"
    ],
    "wof:name":"Bill Elliott Homes",
    "wof:placetype":"venue"
},
  "geometry": {"coordinates":[-97.462929,31.147982],"type":"Point"}
}