{
  "type": "Feature",
  "properties": {
    "iso:country":"US",
    "sg:address":"2618 Guatemozin St",
    "sg:city":"Laredo",
    "sg:classifiers":[
        {
            "category":"Building & Trades",
            "subcategory":"Electrical",
            "type":"Services"
        }
    ],
    "sg:phone":"+1 956 723 9251",
    "sg:postcode":"78043",
    "sg:province":"TX",
    "sg:tags":[
        "electrical",
        "contractor"
    ],
    "wof:name":"Heights Electric Shop",
    "wof:placetype":"venue"
},
  "geometry": {"coordinates":[-99.46929799999999,27.502052],"type":"Point"}
}