{
  "type": "Feature",
  "properties": {
    "iso:country":"US",
    "sg:address":"2200 S 10th St",
    "sg:city":"Mcallen",
    "sg:classifiers":[
        {
            "category":"Shopping",
            "type":"Retail Goods"
        }
    ],
    "sg:phone":"+1 956 686 6848",
    "sg:postcode":"78503",
    "sg:province":"TX",
    "sg:tags":[
        "sunglasses",
        "accessory"
    ],
    "wof:name":"Sunglass Hut 884",
    "wof:placetype":"venue"
},
  "geometry": {"coordinates":[-98.23356,26.183135],"type":"Point"}
}