{
  "type": "Feature",
  "properties": {
    "iso:country":"US",
    "sg:address":"9201 Crowley Rd",
    "sg:city":"Fort Worth",
    "sg:classifiers":[
        {
            "category":"Shopping",
            "subcategory":"Computers & Home Electronics",
            "type":"Retail Goods"
        },
        {
            "category":"Professional",
            "subcategory":"Computer Services",
            "type":"Services"
        }
    ],
    "sg:phone":"+1 817 568 9300",
    "sg:postcode":"76134",
    "sg:province":"TX",
    "sg:tags":[
        "stereo",
        "installation"
    ],
    "wof:name":"Lone Star Auto Sound & Security",
    "wof:placetype":"venue"
},
  "geometry": {"coordinates":[-97.34839599999999,32.621498],"type":"Point"}
}