{
  "type": "Feature",
  "properties": {
    "iso:country":"US",
    "sg:address":"104 W Texas Ave",
    "sg:city":"Baytown",
    "sg:classifiers":[
        {
            "category":"Shopping",
            "subcategory":"Clothing, Apparel, & Fashions",
            "type":"Retail Goods"
        }
    ],
    "sg:phone":"+1 281 420 2015",
    "sg:postcode":"77520",
    "sg:province":"TX",
    "wof:name":"Da Unit Clothing",
    "wof:placetype":"venue"
},
  "geometry": {"coordinates":[-94.968591,29.732433],"type":"Point"}
}