{
  "type": "Feature",
  "properties": {
    "iso:country":"US",
    "sg:address":"1404 W Elliott St",
    "sg:city":"Breckenridge",
    "sg:classifiers":[
        {
            "category":"Mining & Drilling",
            "type":"Manufacturing & Wholesale Goods"
        }
    ],
    "sg:phone":"+1 254 559 9643",
    "sg:postcode":"76424",
    "sg:province":"TX",
    "sg:tags":[
        "gas",
        "oil",
        "oilfield",
        "producer"
    ],
    "wof:name":"Mayes Operating Co",
    "wof:placetype":"venue"
},
  "geometry": {"coordinates":[-98.921094,32.751743],"type":"Point"}
}