{
  "type": "Feature",
  "properties": {
    "iso:country":"US",
    "sg:address":"4950 Woodway Dr",
    "sg:city":"Houston",
    "sg:classifiers":[
        {
            "category":"Wholesale",
            "subcategory":"Non-durable Goods",
            "type":"Manufacturing & Wholesale Goods"
        }
    ],
    "sg:phone":"+1 713 201 0883",
    "sg:postcode":"77056",
    "sg:province":"TX",
    "wof:name":"Shyamrock Imports Ltd",
    "wof:placetype":"venue"
},
  "geometry": {"coordinates":[-95.463019,29.76249],"type":"Point"}
}