{
  "type": "Feature",
  "properties": {
    "iso:country":"US",
    "sg:address":"7378 Co Rd 4293",
    "sg:city":"Tenaha",
    "sg:classifiers":[
        {
            "category":"Shopping",
            "subcategory":"Clothing, Apparel, & Fashions",
            "type":"Retail Goods"
        }
    ],
    "sg:phone":"+1 936 598 3344",
    "sg:postcode":"75974",
    "sg:province":"TX",
    "sg:tags":[
        "wear"
    ],
    "wof:name":"Belle & Beaus Childrens Consi",
    "wof:placetype":"venue"
},
  "geometry": {"coordinates":[-94.261303,31.874785],"type":"Point"}
}