{
  "type": "Feature",
  "properties": {
    "iso:country":"US",
    "sg:address":"6369 del Monte Dr",
    "sg:city":"Houston",
    "sg:classifiers":[
        {
            "category":"Manufacturing",
            "subcategory":"Jewelry",
            "type":"Manufacturing & Wholesale Goods"
        }
    ],
    "sg:phone":"+1 713 787 9621",
    "sg:postcode":"77057",
    "sg:province":"TX",
    "sg:tags":[
        "costume",
        "mfg"
    ],
    "wof:name":"Roseneath",
    "wof:placetype":"venue"
},
  "geometry": {"coordinates":[-95.496486,29.745408],"type":"Point"}
}