{
  "type": "Feature",
  "properties": {
    "iso:country":"US",
    "sg:address":"11800 Scott St",
    "sg:city":"Houston",
    "sg:classifiers":[
        {
            "category":"Recreation",
            "type":"Entertainment"
        }
    ],
    "sg:phone":"+1 713 733 4581",
    "sg:postcode":"77047",
    "sg:province":"TX",
    "sg:tags":[
        "hall",
        "auditorium"
    ],
    "wof:name":"Cloverland Community Ctr",
    "wof:placetype":"venue"
},
  "geometry": {"coordinates":[-95.36805,29.631971],"type":"Point"}
}