{
  "type": "Feature",
  "properties": {
    "iso:country":"US",
    "sg:address":"205 Southridge St",
    "sg:city":"Edgewood",
    "sg:classifiers":[
        {
            "category":"Place Of Worship",
            "subcategory":"Church",
            "type":"Public Place"
        },
        {
            "category":"Place Of Worship",
            "type":"Public Place"
        }
    ],
    "sg:phone":"+1 903 896 4340",
    "sg:postcode":"75117",
    "sg:province":"TX",
    "sg:tags":[
        "churches-methodist"
    ],
    "wof:name":"Methodist Church",
    "wof:placetype":"venue"
},
  "geometry": {"coordinates":[-95.878619,32.68298],"type":"Point"}
}