{
  "type": "Feature",
  "properties": {
    "iso:country":"US",
    "sg:address":"1229 Deaf Smith St",
    "sg:city":"Vernon",
    "sg:classifiers":[
        {
            "category":"Retail",
            "subcategory":"Car Wash",
            "type":"Services"
        },
        {
            "category":"Retail",
            "subcategory":"Auto Repair",
            "type":"Services"
        }
    ],
    "sg:phone":"+1 940 553 1601",
    "sg:postcode":"76384",
    "sg:province":"TX",
    "sg:tags":[
        "body",
        "automobile",
        "detail",
        "clean"
    ],
    "wof:name":"Leija's Auto Clean-Up",
    "wof:placetype":"venue"
},
  "geometry": {"coordinates":[-99.286689,34.158058],"type":"Point"}
}