{
  "type": "Feature",
  "properties": {
    "iso:country":"US",
    "sg:address":"2700 FM 1379",
    "sg:city":"Midland",
    "sg:classifiers":[
        {
            "category":"Organizations",
            "subcategory":"Non-profit Organization",
            "type":"Services"
        },
        {
            "category":"Education",
            "subcategory":"School",
            "type":"Public Place"
        }
    ],
    "sg:phone":"+1 432 683 6461",
    "sg:postcode":"79706",
    "sg:province":"TX",
    "sg:tags":[
        "elementary",
        "secondary",
        "program",
        "prevention",
        "crime"
    ],
    "wof:name":"Greenwood Campus Crime Stopper",
    "wof:placetype":"venue"
},
  "geometry": {"coordinates":[-101.89379099999999,32.021591],"type":"Point"}
}