{
  "type": "Feature",
  "properties": {
    "iso:country":"US",
    "sg:address":"13809 N Highway 183",
    "sg:city":"Austin",
    "sg:classifiers":[
        {
            "category":"Shopping",
            "subcategory":"Florist",
            "type":"Retail Goods"
        }
    ],
    "sg:phone":"+1 512 331 5667",
    "sg:postcode":"78750",
    "sg:province":"TX",
    "wof:name":"Daystar Oil & Gas Corporation",
    "wof:placetype":"venue"
},
  "geometry": {"coordinates":[-97.800162,30.460862],"type":"Point"}
}