{
  "type": "Feature",
  "properties": {
    "iso:country":"US",
    "sg:address":"1308 Crescent St",
    "sg:city":"Denton",
    "sg:classifiers":[
        {
            "category":"Health Services",
            "subcategory":"Doctor",
            "type":"Services"
        }
    ],
    "sg:phone":"+1 940 566 3368",
    "sg:postcode":"76201",
    "sg:province":"TX",
    "sg:tags":[
        "dentist"
    ],
    "wof:name":"Denton Dental",
    "wof:placetype":"venue"
},
  "geometry": {"coordinates":[-97.148308,33.226033],"type":"Point"}
}