{
  "type": "Feature",
  "properties": {
    "iso:country":"US",
    "sg:address":"3241 Lipscomb St",
    "sg:city":"Fort Worth",
    "sg:classifiers":[
        {
            "category":"Professional",
            "subcategory":"Art Services",
            "type":"Services"
        }
    ],
    "sg:phone":"+1 817 924 1011",
    "sg:postcode":"76110",
    "sg:province":"TX",
    "sg:tags":[
        "graphic",
        "designer"
    ],
    "wof:name":"Buckdesign",
    "wof:placetype":"venue"
},
  "geometry": {"coordinates":[-97.334216,32.703027],"type":"Point"}
}