{
  "type": "Feature",
  "properties": {
    "iso:country":"US",
    "sg:address":"8718 Botts Ln",
    "sg:city":"San Antonio",
    "sg:classifiers":[
        {
            "category":"Professional",
            "subcategory":"Research",
            "type":"Services"
        }
    ],
    "sg:phone":"+1 210 821 5977",
    "sg:postcode":"78217",
    "sg:province":"TX",
    "sg:tags":[
        "environmental",
        "ecological"
    ],
    "wof:name":"Bio Stim LLC",
    "wof:placetype":"venue"
},
  "geometry": {"coordinates":[-98.459653,29.518742],"type":"Point"}
}