{
  "type": "Feature",
  "properties": {
    "iso:country":"US",
    "sg:address":"1205 Zaragosa St",
    "sg:city":"Laredo",
    "sg:classifiers":[
        {
            "category":"Shopping",
            "type":"Retail Goods"
        }
    ],
    "sg:phone":"+1 956 725 4626",
    "sg:postcode":"78040",
    "sg:province":"TX",
    "sg:tags":[
        "cosmetic",
        "perfume"
    ],
    "wof:name":"LA Versailles Fragrances",
    "wof:placetype":"venue"
},
  "geometry": {"coordinates":[-99.508511,27.502068],"type":"Point"}
}