{
  "type": "Feature",
  "properties": {
    "iso:country":"US",
    "sg:address":"7606 Fairdale Ln",
    "sg:city":"Houston",
    "sg:classifiers":[
        {
            "category":"Real Estate",
            "subcategory":"Real Estate Agent",
            "type":"Services"
        }
    ],
    "sg:phone":"+1 713 781 2778",
    "sg:postcode":"77063",
    "sg:province":"TX",
    "wof:name":"Jack Butera Realty Inc",
    "wof:placetype":"venue"
},
  "geometry": {"coordinates":[-95.504963,29.731807],"type":"Point"}
}