{
  "type": "Feature",
  "properties": {
    "iso:country":"US",
    "sg:address":"210 N Mason St",
    "sg:city":"Bowie",
    "sg:classifiers":[
        {
            "category":"Shopping",
            "subcategory":"Used Merchandise",
            "type":"Retail Goods"
        }
    ],
    "sg:phone":"+1 940 872 4717",
    "sg:postcode":"76230",
    "sg:province":"TX",
    "sg:tags":[
        "antique"
    ],
    "wof:name":"Antique Express",
    "wof:placetype":"venue"
},
  "geometry": {"coordinates":[-97.848157,33.559833],"type":"Point"}
}