{
  "type": "Feature",
  "properties": {
    "iso:country":"US",
    "sg:address":"3824 50th St",
    "sg:city":"Lubbock",
    "sg:phone":"+1 806 792 9961",
    "sg:postcode":"79413",
    "sg:province":"TX",
    "wof:name":"Designers Group Salon",
    "wof:placetype":"venue"
},
  "geometry": {"coordinates":[-101.900665,33.548947],"type":"Point"}
}