{
  "type": "Feature",
  "properties": {
    "iso:country":"US",
    "sg:address":"115 Munger St",
    "sg:city":"Pasadena",
    "sg:classifiers":[
        {
            "category":"Manufacturing",
            "subcategory":"Printing",
            "type":"Manufacturing & Wholesale Goods"
        }
    ],
    "sg:phone":"+1 713 472 3639",
    "sg:postcode":"77506",
    "sg:province":"TX",
    "sg:tags":[
        "printer"
    ],
    "sg:website":"www.drakeprinting.com",
    "wof:name":"Drake Printing Co",
    "wof:placetype":"venue"
},
  "geometry": {"coordinates":[-95.210551,29.712405],"type":"Point"}
}