{
  "type": "Feature",
  "properties": {
    "iso:country":"US",
    "sg:address":"8015 C F Hawn Fwy",
    "sg:city":"Dallas",
    "sg:classifiers":[
        {
            "category":"Food & Beverages",
            "subcategory":"Groceries & Convenience Stores",
            "type":"Retail Goods"
        }
    ],
    "sg:phone":"+1 214 398 0305",
    "sg:postcode":"75217",
    "sg:province":"TX",
    "sg:website":"www.shell.com",
    "wof:name":"Shell Food Mart",
    "wof:placetype":"venue"
},
  "geometry": {"coordinates":[-96.68456999999999,32.713456],"type":"Point"}
}