{
  "type": "Feature",
  "properties": {
    "iso:country":"US",
    "sg:address":"320 N Broadway",
    "sg:city":"Dimmitt",
    "sg:classifiers":[
        {
            "category":"Travel",
            "subcategory":"Hotels & Motels",
            "type":"Entertainment"
        }
    ],
    "sg:phone":"+1 806 647 2177",
    "sg:postcode":"79027",
    "sg:province":"TX",
    "sg:tags":[
        "operation"
    ],
    "wof:name":"Colonial Inn Motel",
    "wof:placetype":"venue"
},
  "geometry": {"coordinates":[-102.312257,34.554053],"type":"Point"}
}