{
  "type": "Feature",
  "properties": {
    "iso:country":"US",
    "sg:address":"280 S Wheeler St",
    "sg:city":"Jasper",
    "sg:classifiers":[
        {
            "category":"Utilities",
            "subcategory":"Mobile Phone",
            "type":"Services"
        }
    ],
    "sg:phone":"+1 409 384 7300",
    "sg:postcode":"75951",
    "sg:province":"TX",
    "sg:tags":[
        "telephone",
        "cellular"
    ],
    "wof:name":"Delta Loans & Tax Svc",
    "wof:placetype":"venue"
},
  "geometry": {"coordinates":[-93.99673199999999,30.918575],"type":"Point"}
}