{
  "type": "Feature",
  "properties": {
    "iso:country":"US",
    "sg:address":"303 N Jones St",
    "sg:city":"Navasota",
    "sg:classifiers":[
        {
            "category":"Professional",
            "subcategory":"Business Services",
            "type":"Services"
        }
    ],
    "sg:phone":"+1 936 825 8548",
    "sg:postcode":"77868",
    "sg:province":"TX",
    "sg:tags":[
        "consultant",
        "coach"
    ],
    "wof:name":"Coe & Associates Inc",
    "wof:placetype":"venue"
},
  "geometry": {"coordinates":[-96.083012,30.393768],"type":"Point"}
}