{
  "type": "Feature",
  "properties": {
    "iso:country":"US",
    "sg:address":"2012 Center St Suite A",
    "sg:city":"Houston",
    "sg:classifiers":[
        {
            "category":"Home & Garden",
            "subcategory":"Carpets & Floor Coverings",
            "type":"Retail Goods"
        }
    ],
    "sg:phone":"+1 713 885 5477",
    "sg:postcode":"77007",
    "sg:province":"TX",
    "sg:tags":[
        "flooring"
    ],
    "sg:website":"www.installyourfloors.com",
    "wof:name":"installyourfloors.com",
    "wof:placetype":"venue"
},
  "geometry": {"coordinates":[-95.37885900000001,29.768833],"type":"Point"}
}