{
  "type": "Feature",
  "properties": {
    "iso:country":"US",
    "sg:address":"517 Helen St",
    "sg:city":"Garland",
    "sg:classifiers":[
        {
            "category":"Organizations",
            "subcategory":"Religious Organization",
            "type":"Services"
        }
    ],
    "sg:phone":"+1 972 276 7146",
    "sg:postcode":"75040",
    "sg:province":"TX",
    "sg:tags":[
        "church"
    ],
    "wof:name":"El Bethel Chr Of God In Christ",
    "wof:placetype":"venue"
},
  "geometry": {"coordinates":[-96.624646,32.908503],"type":"Point"}
}