{
  "type": "Feature",
  "properties": {
    "iso:country":"US",
    "sg:address":"327 Tennessee St",
    "sg:city":"Houston",
    "sg:classifiers":[
        {
            "category":"Organizations",
            "subcategory":"Religious Organization",
            "type":"Services"
        }
    ],
    "sg:phone":"+1 713 676 0084",
    "sg:postcode":"77029",
    "sg:province":"TX",
    "sg:tags":[
        "church"
    ],
    "wof:name":"New Jerusalem Holiness Church",
    "wof:placetype":"venue"
},
  "geometry": {"coordinates":[-95.25577199999999,29.744466],"type":"Point"}
}