{
  "type": "Feature",
  "properties": {
    "iso:country":"US",
    "sg:address":"4503 Ranch Rd 620 N",
    "sg:city":"Austin",
    "sg:classifiers":[
        {
            "category":"Professional",
            "subcategory":"Computer Services",
            "type":"Services"
        },
        {
            "category":"Shopping",
            "subcategory":"Computers & Home Electronics",
            "type":"Retail Goods"
        }
    ],
    "sg:phone":"+1 512 266 7787",
    "sg:postcode":"78732",
    "sg:province":"TX",
    "sg:tags":[
        "prepackaged",
        "software"
    ],
    "sg:website":"www.envworld.com",
    "wof:name":"Envision Utilities Software",
    "wof:placetype":"venue"
},
  "geometry": {"coordinates":[-97.89422999999999,30.38765],"type":"Point"}
}