{
  "type": "Feature",
  "properties": {
    "iso:country":"US",
    "sg:address":"515 E Avenue E D",
    "sg:city":"Robstown",
    "sg:classifiers":[
        {
            "category":"Manufacturing",
            "subcategory":"Buildings",
            "type":"Manufacturing & Wholesale Goods"
        },
        {
            "category":"Building & Trades",
            "subcategory":"Construction",
            "type":"Services"
        }
    ],
    "sg:phone":"+1 361 387 3505",
    "sg:postcode":"78380",
    "sg:province":"TX",
    "sg:tags":[
        "home",
        "builder",
        "contractor"
    ],
    "wof:name":"Mungia Construction",
    "wof:placetype":"venue"
},
  "geometry": {"coordinates":[-97.662761,27.793327],"type":"Point"}
}