{
  "type": "Feature",
  "properties": {
    "iso:country":"US",
    "sg:address":"1001 N Main St",
    "sg:city":"Cleburne",
    "sg:classifiers":[
        {
            "category":"Banks & Credit Unions",
            "subcategory":"Bank",
            "type":"Services"
        }
    ],
    "sg:phone":"+1 817 558 2469",
    "sg:postcode":"76033",
    "sg:province":"TX",
    "sg:tags":[
        "cashing",
        "check"
    ],
    "wof:name":"Easy Check Cashing 2698",
    "wof:placetype":"venue"
},
  "geometry": {"coordinates":[-97.38349700000001,32.33929],"type":"Point"}
}