{
  "type": "Feature",
  "properties": {
    "iso:country":"US",
    "sg:address":"5349 Amesbury Dr",
    "sg:city":"Dallas",
    "sg:classifiers":[
        {
            "category":"Professional",
            "subcategory":"Engineering",
            "type":"Services"
        }
    ],
    "sg:phone":"+1 214 373 8115",
    "sg:postcode":"75206",
    "sg:province":"TX",
    "sg:tags":[
        "engineer"
    ],
    "wof:name":"Duplechain Consulting Svc",
    "wof:placetype":"venue"
},
  "geometry": {"coordinates":[-96.76446799999999,32.852385],"type":"Point"}
}