{
  "type": "Feature",
  "properties": {
    "iso:country":"US",
    "sg:address":"2301 L Don Dodson Dr",
    "sg:city":"Bedford",
    "sg:classifiers":[
        {
            "category":"Real Estate",
            "subcategory":"Real Estate Operator",
            "type":"Services"
        }
    ],
    "sg:phone":"+1 817 540 1677",
    "sg:postcode":"76021",
    "sg:province":"TX",
    "sg:tags":[
        "building",
        "apartment"
    ],
    "wof:name":"Summerstone",
    "wof:placetype":"venue"
},
  "geometry": {"coordinates":[-97.127015,32.841056],"type":"Point"}
}