{
  "type": "Feature",
  "properties": {
    "iso:country":"US",
    "sg:address":"1833 Suntide Rd",
    "sg:city":"Corpus Christi",
    "sg:classifiers":[
        {
            "category":"Building & Trades",
            "subcategory":"Equipment Rental",
            "type":"Services"
        }
    ],
    "sg:phone":"+1 361 241 3797",
    "sg:postcode":"78409",
    "sg:province":"TX",
    "wof:name":"NES Rentals",
    "wof:placetype":"venue"
},
  "geometry": {"coordinates":[-97.520285,27.81599],"type":"Point"}
}