{
  "type": "Feature",
  "properties": {
    "iso:country":"US",
    "sg:address":"701 E Harrison Ave",
    "sg:city":"Harlingen",
    "sg:classifiers":[
        {
            "category":"Insurance",
            "subcategory":"Insurance Agent",
            "type":"Services"
        }
    ],
    "sg:phone":"+1 956 423 4956",
    "sg:postcode":"78550",
    "sg:province":"TX",
    "wof:name":"Jefferson-Pilot Financial",
    "wof:placetype":"venue"
},
  "geometry": {"coordinates":[-97.68807200000001,26.190685],"type":"Point"}
}