{
  "type": "Feature",
  "properties": {
    "iso:country":"US",
    "sg:address":"1206 Frontier Ln",
    "sg:city":"Friendswood",
    "sg:classifiers":[
        {
            "category":"Health Services",
            "subcategory":"Chiropractor",
            "type":"Services"
        }
    ],
    "sg:phone":"+1 281 996 7973",
    "sg:postcode":"77546",
    "sg:province":"TX",
    "sg:tags":[
        "chiropractic"
    ],
    "wof:name":"Innategirl Chiropractic Care, P",
    "wof:placetype":"venue"
},
  "geometry": {"coordinates":[-95.20813800000001,29.505434],"type":"Point"}
}