{
  "type": "Feature",
  "properties": {
    "iso:country":"US",
    "sg:address":"6207 Breeze Way",
    "sg:city":"Austin",
    "sg:classifiers":[
        {
            "category":"Organizations",
            "subcategory":"Professional Association",
            "type":"Services"
        }
    ],
    "sg:phone":"+1 512 929 0322",
    "sg:postcode":"78723",
    "sg:province":"TX",
    "sg:tags":[
        "agency",
        "bureau",
        "entertainment"
    ],
    "wof:name":"Gospel Explosion",
    "wof:placetype":"venue"
},
  "geometry": {"coordinates":[-97.678202,30.309108],"type":"Point"}
}