{
  "type": "Feature",
  "properties": {
    "iso:country":"US",
    "sg:address":"15018 Mintz Ln",
    "sg:city":"Houston",
    "sg:classifiers":[
        {
            "category":"Manufacturing",
            "subcategory":"Printing",
            "type":"Manufacturing & Wholesale Goods"
        }
    ],
    "sg:phone":"+1 281 440 0278",
    "sg:postcode":"77014",
    "sg:province":"TX",
    "sg:tags":[
        "typesetting"
    ],
    "wof:name":"Doyle Publishing Co",
    "wof:placetype":"venue"
},
  "geometry": {"coordinates":[-95.47655399999999,29.998595],"type":"Point"}
}