{
  "type": "Feature",
  "properties": {
    "iso:country":"US",
    "sg:address":"1409 Jupiter Rd",
    "sg:city":"Plano",
    "sg:classifiers":[
        {
            "category":"Arts & Performance",
            "subcategory":"Theater",
            "type":"Entertainment"
        }
    ],
    "sg:phone":"+1 972 509 0256",
    "sg:postcode":"75074",
    "sg:province":"TX",
    "sg:tags":[
        "group"
    ],
    "wof:name":"256 Entertainment",
    "wof:placetype":"venue"
},
  "geometry": {"coordinates":[-96.682609,33.0185],"type":"Point"}
}