{
  "type": "Feature",
  "properties": {
    "iso:country":"US",
    "sg:address":"13111 E Fwy Ste 215",
    "sg:city":"Houston",
    "sg:classifiers":[
        {
            "category":"Personal",
            "subcategory":"Adult",
            "type":"Services"
        }
    ],
    "sg:phone":"+1 713 393 2276",
    "sg:postcode":"77030",
    "sg:province":"TX",
    "sg:tags":[
        "midwife"
    ],
    "wof:name":"Laura Reedy, CNM, MSN",
    "wof:placetype":"venue"
},
  "geometry": {"coordinates":[-95.194654,29.771915],"type":"Point"}
}