{
  "type": "Feature",
  "properties": {
    "iso:country":"US",
    "sg:address":"3321 Hancock Dr",
    "sg:city":"Austin",
    "sg:classifiers":[
        {
            "category":"Personal",
            "subcategory":"Massage",
            "type":"Services"
        },
        {
            "category":"Health Services",
            "subcategory":"Clinic",
            "type":"Services"
        },
        {
            "category":"Health Services",
            "subcategory":"Health Practitioner",
            "type":"Services"
        }
    ],
    "sg:phone":"+1 512 419 9992",
    "sg:postcode":"78731",
    "sg:province":"TX",
    "sg:tags":[
        "therapist",
        "therapy",
        "physical"
    ],
    "wof:name":"Harmony Balance",
    "wof:placetype":"venue"
},
  "geometry": {"coordinates":[-97.75885,30.332324],"type":"Point"}
}