{
  "type": "Feature",
  "properties": {
    "iso:country":"US",
    "sg:address":"1209 W 5th Street",
    "sg:city":"Austin",
    "sg:classifiers":[
        {
            "category":"Professional",
            "subcategory":"Accounting & Tax Preparation",
            "type":"Services"
        }
    ],
    "sg:phone":"+1 512 476 2221",
    "sg:postcode":"78703",
    "sg:province":"TX",
    "sg:tags":[
        "accountant"
    ],
    "wof:name":"Montemayor Arturo III CPA",
    "wof:placetype":"venue"
},
  "geometry": {"coordinates":[-97.75828300000001,30.27174],"type":"Point"}
}