{
  "type": "Feature",
  "properties": {
    "iso:country":"US",
    "sg:address":"9531 Flying Eagle Ct",
    "sg:city":"Houston",
    "sg:classifiers":[
        {
            "category":"Professional",
            "subcategory":"Employment Agencies",
            "type":"Services"
        }
    ],
    "sg:phone":"+1 713 273 2118",
    "sg:postcode":"77083",
    "sg:province":"TX",
    "sg:tags":[
        "recruiting"
    ],
    "wof:name":"Taylor-Mcgowan Recruiting",
    "wof:placetype":"venue"
},
  "geometry": {"coordinates":[-95.666489,29.676474],"type":"Point"}
}