{
  "type": "Feature",
  "properties": {
    "iso:country":"US",
    "sg:address":"606 N Main St",
    "sg:city":"Perryton",
    "sg:classifiers":[
        {
            "category":"Wholesale",
            "subcategory":"Machinery & Supplies",
            "type":"Manufacturing & Wholesale Goods"
        }
    ],
    "sg:phone":"+1 806 435 6755",
    "sg:postcode":"79070",
    "sg:province":"TX",
    "sg:tags":[
        "equipment",
        "oil",
        "well"
    ],
    "wof:name":"Ranger Pump",
    "wof:placetype":"venue"
},
  "geometry": {"coordinates":[-100.802792,36.420048],"type":"Point"}
}