{
  "type": "Feature",
  "properties": {
    "iso:country":"US",
    "sg:address":"2104 Stevenson Ln",
    "sg:city":"Flower Mound",
    "sg:classifiers":[
        {
            "category":"Professional",
            "subcategory":"Business Services",
            "type":"Services"
        }
    ],
    "sg:phone":"+1 972 355 5972",
    "sg:postcode":"75028",
    "sg:province":"TX",
    "wof:name":"EZ Care",
    "wof:placetype":"venue"
},
  "geometry": {"coordinates":[-97.05932,33.065065],"type":"Point"}
}