{
  "type": "Feature",
  "properties": {
    "iso:country":"US",
    "sg:address":"2423 Crest Ave",
    "sg:city":"Dallas",
    "sg:classifiers":[
        {
            "category":"Social Services",
            "type":"Services"
        }
    ],
    "sg:phone":"+1 214 374 1574",
    "sg:postcode":"75216",
    "sg:province":"TX",
    "sg:tags":[
        "care",
        "center",
        "day"
    ],
    "wof:name":"Good Haven Adult Day Care Ctr",
    "wof:placetype":"venue"
},
  "geometry": {"coordinates":[-96.803268,32.718233],"type":"Point"}
}