{
  "type": "Feature",
  "properties": {
    "iso:country":"US",
    "sg:address":"814 Arion Pkwy",
    "sg:city":"San Antonio",
    "sg:classifiers":[
        {
            "category":"Banks & Credit Unions",
            "subcategory":"Bank",
            "type":"Services"
        }
    ],
    "sg:phone":"+1 210 403 9217",
    "sg:postcode":"78216",
    "sg:province":"TX",
    "wof:name":"Washington Mutual",
    "wof:placetype":"venue"
},
  "geometry": {"coordinates":[-98.480577,29.550292],"type":"Point"}
}