{
  "type": "Feature",
  "properties": {
    "iso:country":"US",
    "sg:address":"423 25th St",
    "sg:city":"Galveston",
    "sg:classifiers":[
        {
            "category":"Shopping",
            "subcategory":"Used Merchandise",
            "type":"Retail Goods"
        }
    ],
    "sg:phone":"+1 409 762 8620",
    "sg:postcode":"77550",
    "sg:province":"TX",
    "sg:tags":[
        "antique"
    ],
    "wof:name":"Antique Warehouse",
    "wof:placetype":"venue"
},
  "geometry": {"coordinates":[-94.795934,29.303996],"type":"Point"}
}