{
  "type": "Feature",
  "properties": {
    "iso:country":"US",
    "sg:address":"8058 S Gessner Rd",
    "sg:city":"Houston",
    "sg:classifiers":[
        {
            "category":"Cinema",
            "subcategory":"Movie Rental",
            "type":"Entertainment"
        }
    ],
    "sg:phone":"+1 713 272 8600",
    "sg:postcode":"77036",
    "sg:province":"TX",
    "sg:tags":[
        "video",
        "tape"
    ],
    "wof:name":"Senor Video",
    "wof:placetype":"venue"
},
  "geometry": {"coordinates":[-95.53498500000001,29.690913],"type":"Point"}
}