{
  "type": "Feature",
  "properties": {
    "iso:country":"US",
    "sg:address":"5829 Sam Houston Pkwy",
    "sg:city":"Houston",
    "sg:classifiers":[
        {
            "category":"Building & Trades",
            "subcategory":"Plumbing",
            "type":"Services"
        }
    ],
    "sg:phone":"+1 713 896 4422",
    "sg:postcode":"77049",
    "sg:province":"TX",
    "sg:tags":[
        "contractor"
    ],
    "wof:name":"R & R Group",
    "wof:placetype":"venue"
},
  "geometry": {"coordinates":[-95.163325,29.809375],"type":"Point"}
}