{
  "type": "Feature",
  "properties": {
    "iso:country":"US",
    "sg:address":"10026 Trout Ridge Dr",
    "sg:city":"Converse",
    "sg:classifiers":[
        {
            "category":"Social Services",
            "subcategory":"Adult Care",
            "type":"Services"
        }
    ],
    "sg:phone":"+1 210 590 3909",
    "sg:postcode":"78109",
    "sg:province":"TX",
    "sg:tags":[
        "home",
        "group"
    ],
    "wof:name":"Council Oaks Cmnty Options LLC",
    "wof:placetype":"venue"
},
  "geometry": {"coordinates":[-98.34347699999999,29.533659],"type":"Point"}
}