{
  "type": "Feature",
  "properties": {
    "iso:country":"US",
    "sg:address":"700 Louisiana St",
    "sg:city":"Houston",
    "sg:classifiers":[
        {
            "category":"Building & Trades",
            "subcategory":"Equipment Rental",
            "type":"Services"
        }
    ],
    "sg:phone":"+1 713 237 1132",
    "sg:postcode":"77002",
    "sg:province":"TX",
    "sg:tags":[
        "leasing"
    ],
    "wof:name":"Cit",
    "wof:placetype":"venue"
},
  "geometry": {"coordinates":[-95.365753,29.760771],"type":"Point"}
}