{
  "type": "Feature",
  "properties": {
    "iso:country":"US",
    "sg:address":"4908 S Co Rd 1180",
    "sg:city":"Midland",
    "sg:classifiers":[
        {
            "category":"Professional",
            "subcategory":"Detective & Security Services",
            "type":"Services"
        }
    ],
    "sg:phone":"+1 432 684 4112",
    "sg:postcode":"79706",
    "sg:province":"TX",
    "sg:tags":[
        "investigator"
    ],
    "wof:name":"Web Detective Agency Inc",
    "wof:placetype":"venue"
},
  "geometry": {"coordinates":[-102.045905,31.94002],"type":"Point"}
}