{
  "type": "Feature",
  "properties": {
    "iso:country":"US",
    "sg:address":"9121 Heron Dr",
    "sg:city":"Fort Worth",
    "sg:classifiers":[
        {
            "category":"Travel",
            "subcategory":"Hotels & Motels",
            "type":"Entertainment"
        }
    ],
    "sg:phone":"+1 817 367 3433",
    "sg:postcode":"76108",
    "sg:province":"TX",
    "sg:tags":[
        "operation"
    ],
    "wof:name":"El Paisano Resort Htl Cor",
    "wof:placetype":"venue"
},
  "geometry": {"coordinates":[-97.483324,32.795595],"type":"Point"}
}