{
  "type": "Feature",
  "properties": {
    "iso:country":"US",
    "sg:address":"5225 Katy Fwy",
    "sg:city":"Houston",
    "sg:classifiers":[
        {
            "category":"Building & Trades",
            "subcategory":"Construction",
            "type":"Services"
        }
    ],
    "sg:phone":"+1 713 880 2225",
    "sg:postcode":"77007",
    "sg:province":"TX",
    "sg:tags":[
        "contractor"
    ],
    "wof:name":"Waterford Custom Homes",
    "wof:placetype":"venue"
},
  "geometry": {"coordinates":[-95.40830200000001,29.7703],"type":"Point"}
}