{
  "type": "Feature",
  "properties": {
    "iso:country":"US",
    "sg:address":"6415 Stuebner Airline Rd",
    "sg:city":"Houston",
    "sg:classifiers":[
        {
            "category":"Building & Trades",
            "subcategory":"Locksmith",
            "type":"Services"
        }
    ],
    "sg:phone":"+1 713 742 8000",
    "sg:postcode":"77091",
    "sg:province":"TX",
    "sg:tags":[
        "key"
    ],
    "wof:name":"24 HR LOCk & Key",
    "wof:placetype":"venue"
},
  "geometry": {"coordinates":[-95.409593,29.857346],"type":"Point"}
}