{
  "type": "Feature",
  "properties": {
    "iso:country":"US",
    "sg:address":"2036 Water St",
    "sg:city":"Gonzales",
    "sg:classifiers":[
        {
            "category":"Professional",
            "type":"Services"
        }
    ],
    "sg:phone":"+1 830 672 9186",
    "sg:postcode":"78629",
    "sg:province":"TX",
    "wof:name":"Dynamic Studio",
    "wof:placetype":"venue"
},
  "geometry": {"coordinates":[-97.46361400000001,29.516922],"type":"Point"}
}