{
  "type": "Feature",
  "properties": {
    "iso:country":"US",
    "sg:address":"9219 Garland Rd Ste 2107",
    "sg:city":"Dallas",
    "sg:classifiers":[
        {
            "category":"Health Services",
            "subcategory":"Doctor",
            "type":"Services"
        }
    ],
    "sg:phone":"+1 469 341 5676",
    "sg:postcode":"75218",
    "sg:province":"TX",
    "sg:website":"www.lakewoodorthoandsportsmed.com",
    "wof:name":"Orthopaedics & Sports Medicine Lakewood",
    "wof:placetype":"venue"
},
  "geometry": {"coordinates":[-96.706784,32.830397],"type":"Point"}
}