{
  "type": "Feature",
  "properties": {
    "iso:country":"US",
    "sg:address":"2310 W Highway 90",
    "sg:city":"Alpine",
    "sg:classifiers":[
        {
            "category":"Travel",
            "subcategory":"Hotels & Motels",
            "type":"Entertainment"
        }
    ],
    "sg:phone":"+1 432 837 2451",
    "sg:postcode":"79830",
    "sg:province":"TX",
    "sg:tags":[
        "lodging"
    ],
    "sg:website":"http://www.antelopelodge.com",
    "wof:name":"Antelope Lodge",
    "wof:placetype":"venue"
},
  "geometry": {"coordinates":[-103.685806,30.35503],"type":"Point"}
}