{
  "type": "Feature",
  "properties": {
    "iso:country":"US",
    "sg:address":"224 Reid St",
    "sg:city":"Gonzales",
    "sg:classifiers":[
        {
            "category":"Retail",
            "subcategory":"Repair Shop",
            "type":"Services"
        }
    ],
    "sg:phone":"+1 830 672 7333",
    "sg:postcode":"78629",
    "sg:province":"TX",
    "sg:tags":[
        "gun"
    ],
    "wof:name":"Garys Gun Repair",
    "wof:placetype":"venue"
},
  "geometry": {"coordinates":[-97.432355,29.505799],"type":"Point"}
}