{
  "type": "Feature",
  "properties": {
    "iso:country":"US",
    "sg:address":"702 W el Rancho Blanco Rd",
    "sg:city":"Pharr",
    "sg:classifiers":[
        {
            "category":"Health Services",
            "subcategory":"Clinic",
            "type":"Services"
        }
    ],
    "sg:phone":"+1 956 781 1499",
    "sg:postcode":"78577",
    "sg:province":"TX",
    "sg:tags":[
        "home",
        "care"
    ],
    "wof:name":"Med-Care Home Health Inc",
    "wof:placetype":"venue"
},
  "geometry": {"coordinates":[-98.1999,26.160605],"type":"Point"}
}