{
  "type": "Feature",
  "properties": {
    "iso:country":"US",
    "sg:address":"4715 Texas Blvd",
    "sg:city":"Texarkana",
    "sg:classifiers":[
        {
            "category":"Shopping",
            "subcategory":"Beauty & Cosmetics",
            "type":"Retail Goods"
        }
    ],
    "sg:phone":"+1 903 793 5791",
    "sg:postcode":"75503",
    "sg:province":"TX",
    "sg:tags":[
        "e",
        "merchandise"
    ],
    "wof:name":"Sally Beauty Supply",
    "wof:placetype":"venue"
},
  "geometry": {"coordinates":[-94.046431,33.460657],"type":"Point"}
}