{
  "type": "Feature",
  "properties": {
    "iso:country":"US",
    "sg:address":"655 Guilford Park",
    "sg:city":"Conroe",
    "sg:classifiers":[
        {
            "category":"Building & Trades",
            "subcategory":"Construction",
            "type":"Services"
        }
    ],
    "sg:phone":"+1 936 321 2784",
    "sg:postcode":"77302",
    "sg:province":"TX",
    "sg:tags":[
        "residential"
    ],
    "wof:name":"Jetstream Development Inc",
    "wof:placetype":"venue"
},
  "geometry": {"coordinates":[-95.439465,30.258699],"type":"Point"}
}