{
  "type": "Feature",
  "properties": {
    "iso:country":"US",
    "sg:address":"5256 Tetons Dr",
    "sg:city":"El Paso",
    "sg:classifiers":[
        {
            "category":"Building & Trades",
            "subcategory":"Construction",
            "type":"Services"
        }
    ],
    "sg:phone":"+1 915 757 9808",
    "sg:postcode":"79904",
    "sg:province":"TX",
    "sg:tags":[
        "asbestos",
        "removal"
    ],
    "wof:name":"Environmental Reconditioning",
    "wof:placetype":"venue"
},
  "geometry": {"coordinates":[-106.415724,31.859008],"type":"Point"}
}