{
  "type": "Feature",
  "properties": {
    "iso:country":"US",
    "sg:address":"1211 N Pacific St",
    "sg:city":"Mineola",
    "sg:classifiers":[
        {
            "category":"Retail",
            "subcategory":"Auto Repair",
            "type":"Services"
        }
    ],
    "sg:phone":"+1 903 569 6141",
    "sg:postcode":"75773",
    "sg:province":"TX",
    "sg:tags":[
        "automobile",
        "lubrication"
    ],
    "wof:name":"K & L Investments Inc",
    "wof:placetype":"venue"
},
  "geometry": {"coordinates":[-95.484701,32.676538],"type":"Point"}
}