{
  "type": "Feature",
  "properties": {
    "iso:country":"US",
    "sg:address":"200 Evergreen Cir",
    "sg:city":"Georgetown",
    "sg:classifiers":[
        {
            "category":"Building & Trades",
            "subcategory":"Construction",
            "type":"Services"
        }
    ],
    "sg:phone":"+1 512 818 1774",
    "sg:postcode":"78626",
    "sg:province":"TX",
    "sg:tags":[
        "contractor"
    ],
    "wof:name":"H Diamond Services",
    "wof:placetype":"venue"
},
  "geometry": {"coordinates":[-97.656864,30.672001],"type":"Point"}
}