{
  "type": "Feature",
  "properties": {
    "iso:country":"US",
    "sg:address":"206 Bauer Dr",
    "sg:city":"Port Lavaca",
    "sg:classifiers":[
        {
            "category":"Social Services",
            "subcategory":"Adult Care",
            "type":"Services"
        }
    ],
    "sg:phone":"+1 361 552 5229",
    "sg:postcode":"77979",
    "sg:province":"TX",
    "sg:tags":[
        "residential"
    ],
    "wof:name":"Gulf Ben Industries",
    "wof:placetype":"venue"
},
  "geometry": {"coordinates":[-96.639178,28.606557],"type":"Point"}
}