{
  "type": "Feature",
  "properties": {
    "iso:country":"US",
    "sg:address":"7547 Leroy Way",
    "sg:city":"Amarillo",
    "sg:classifiers":[
        {
            "category":"Bars & Pubs",
            "type":"Food & Drink"
        }
    ],
    "sg:phone":"+1 806 383 3568",
    "sg:postcode":"79108",
    "sg:province":"TX",
    "sg:tags":[
        "drinking"
    ],
    "wof:name":"After Hours Stained Glass",
    "wof:placetype":"venue"
},
  "geometry": {"coordinates":[-101.840084,35.286769],"type":"Point"}
}