{
  "type": "Feature",
  "properties": {
    "iso:country":"US",
    "sg:address":"1840 N Lee Trevino Dr",
    "sg:city":"El Paso",
    "sg:classifiers":[
        {
            "category":"Restaurant",
            "type":"Food & Drink"
        }
    ],
    "sg:menulink":"http://www.allmenus.com/tx/el-paso/217888-burger-king/menu/",
    "sg:phone":"+1 915 591 3642",
    "sg:postcode":"79936",
    "sg:province":"TX",
    "sg:tags":[
        "american"
    ],
    "wof:name":"Burger King",
    "wof:placetype":"venue"
},
  "geometry": {"coordinates":[-106.31762500000001,31.767021],"type":"Point"}
}