{
  "type": "Feature",
  "properties": {
    "iso:country":"US",
    "sg:address":"605 E Crestwood Dr",
    "sg:city":"Victoria",
    "sg:classifiers":[
        {
            "category":"Retail",
            "subcategory":"Auto Repair",
            "type":"Services"
        }
    ],
    "sg:phone":"+1 361 573 5009",
    "sg:postcode":"77901",
    "sg:province":"TX",
    "sg:tags":[
        "body"
    ],
    "wof:name":"Deluxe Auto Top & Trim",
    "wof:placetype":"venue"
},
  "geometry": {"coordinates":[-96.99987,28.827936],"type":"Point"}
}