{
  "type": "Feature",
  "properties": {
    "iso:country":"US",
    "sg:address":"705 S Big Spring St",
    "sg:city":"Midland",
    "sg:classifiers":[
        {
            "category":"Autos & Motor Vehicles",
            "subcategory":"Fuel & Gas Station",
            "type":"Retail Goods"
        }
    ],
    "sg:phone":"+1 432 682 6051",
    "sg:postcode":"79701",
    "sg:province":"TX",
    "sg:tags":[
        "station",
        "gasoline"
    ],
    "wof:name":"Chatman Joe A",
    "wof:placetype":"venue"
},
  "geometry": {"coordinates":[-102.077776,31.990161],"type":"Point"}
}