{
  "type": "Feature",
  "properties": {
    "iso:country":"US",
    "sg:address":"3312 Stuart Dr",
    "sg:city":"Fort Worth",
    "sg:classifiers":[
        {
            "category":"Wholesale",
            "subcategory":"Chemicals & Plastics",
            "type":"Manufacturing & Wholesale Goods"
        }
    ],
    "sg:phone":"+1 817 926 9448",
    "sg:postcode":"76110",
    "sg:province":"TX",
    "sg:tags":[
        "specializing",
        "cleaning",
        "supply"
    ],
    "wof:name":"Bruhn Equipment & Supply Inc",
    "wof:placetype":"venue"
},
  "geometry": {"coordinates":[-97.3244,32.700646],"type":"Point"}
}