{
  "type": "Feature",
  "properties": {
    "iso:country":"US",
    "sg:address":"2208 Barbee St",
    "sg:city":"Houston",
    "sg:classifiers":[
        {
            "category":"Building & Trades",
            "subcategory":"Construction",
            "type":"Services"
        }
    ],
    "sg:phone":"+1 713 529 2684",
    "sg:postcode":"77004",
    "sg:province":"TX",
    "sg:tags":[
        "residential"
    ],
    "wof:name":"S&R Customer Services",
    "wof:placetype":"venue"
},
  "geometry": {"coordinates":[-95.37144000000001,29.728034],"type":"Point"}
}