{
  "type": "Feature",
  "properties": {
    "iso:country":"US",
    "sg:address":"1608 S 43rd St",
    "sg:city":"Temple",
    "sg:classifiers":[
        {
            "category":"Professional",
            "type":"Services"
        }
    ],
    "sg:phone":"+1 254 773 7074",
    "sg:postcode":"76504",
    "sg:province":"TX",
    "wof:name":"James W Lewis",
    "wof:placetype":"venue"
},
  "geometry": {"coordinates":[-97.370631,31.085905],"type":"Point"}
}