{
  "type": "Feature",
  "properties": {
    "iso:country":"US",
    "sg:address":"3612 Co Rd 161",
    "sg:city":"Alvin",
    "sg:classifiers":[
        {
            "category":"Building & Trades",
            "subcategory":"Pest Control",
            "type":"Services"
        }
    ],
    "sg:phone":"+1 281 824 0088",
    "sg:postcode":"77511",
    "sg:province":"TX",
    "sg:tags":[
        "spraying"
    ],
    "wof:name":"El Campo Spraying Svc",
    "wof:placetype":"venue"
},
  "geometry": {"coordinates":[-95.227457,29.378356],"type":"Point"}
}