{
  "type": "Feature",
  "properties": {
    "iso:country":"US",
    "sg:address":"3904 Elm St",
    "sg:city":"Dallas",
    "sg:classifiers":[
        {
            "category":"Professional",
            "subcategory":"Art Services",
            "type":"Services"
        }
    ],
    "sg:phone":"+1 214 827 6680",
    "sg:postcode":"75226",
    "sg:province":"TX",
    "sg:tags":[
        "graphic",
        "designer"
    ],
    "wof:name":"Kendall's Creative Shop",
    "wof:placetype":"venue"
},
  "geometry": {"coordinates":[-96.7727,32.788383],"type":"Point"}
}