{
  "type": "Feature",
  "properties": {
    "iso:country":"US",
    "sg:address":"2401 Boca Chica Blvd",
    "sg:city":"Brownsville",
    "sg:classifiers":[
        {
            "category":"Retail",
            "subcategory":"Repair Shop",
            "type":"Services"
        }
    ],
    "sg:phone":"+1 956 544 0492",
    "sg:postcode":"78521",
    "sg:province":"TX",
    "sg:tags":[
        "supply"
    ],
    "wof:name":"Lopez Lawnmower Service",
    "wof:placetype":"venue"
},
  "geometry": {"coordinates":[-97.48195800000001,25.921637],"type":"Point"}
}