{
  "type": "Feature",
  "properties": {
    "iso:country":"US",
    "sg:address":"4200 Newton Ave",
    "sg:city":"Dallas",
    "sg:classifiers":[
        {
            "category":"Professional",
            "subcategory":"Business Services",
            "type":"Services"
        }
    ],
    "sg:phone":"+1 214 528 2931",
    "sg:postcode":"75219",
    "sg:province":"TX",
    "wof:name":"Eljae Design",
    "wof:placetype":"venue"
},
  "geometry": {"coordinates":[-96.80237200000001,32.818573],"type":"Point"}
}