{
  "type": "Feature",
  "properties": {
    "iso:country":"US",
    "sg:address":"210 International Blvd",
    "sg:city":"Hidalgo",
    "sg:classifiers":[
        {
            "category":"Insurance",
            "subcategory":"Insurance Agent",
            "type":"Services"
        }
    ],
    "sg:phone":"+1 956 843 8747",
    "sg:postcode":"78557",
    "sg:province":"TX",
    "wof:name":"Sanborns Insurance Service",
    "wof:placetype":"venue"
},
  "geometry": {"coordinates":[-98.26591999999999,26.104549],"type":"Point"}
}