{
  "type": "Feature",
  "properties": {
    "iso:country":"US",
    "sg:address":"2233 N Prairie Creek Rd",
    "sg:city":"Dallas",
    "sg:classifiers":[
        {
            "category":"Shopping",
            "subcategory":"Computers & Home Electronics",
            "type":"Retail Goods"
        }
    ],
    "sg:phone":"+1 214 275 0404",
    "sg:postcode":"75227",
    "sg:province":"TX",
    "sg:tags":[
        "high",
        "fidelity",
        "stereophonic"
    ],
    "wof:name":"Young Stereo",
    "wof:placetype":"venue"
},
  "geometry": {"coordinates":[-96.66555,32.749771],"type":"Point"}
}