{
  "type": "Feature",
  "properties": {
    "iso:country":"US",
    "sg:address":"4800 Calhoun Rd",
    "sg:city":"Houston",
    "sg:classifiers":[
        {
            "category":"Restaurant",
            "type":"Food & Drink"
        }
    ],
    "sg:phone":"+1 713 743 5271",
    "sg:postcode":"77004",
    "sg:province":"TX",
    "sg:tags":[
        "dining"
    ],
    "wof:name":"Chartwells",
    "wof:placetype":"venue"
},
  "geometry": {"coordinates":[-95.338043,29.721696],"type":"Point"}
}