{
  "type": "Feature",
  "properties": {
    "iso:country":"US",
    "sg:address":"4717 Inwood Rd",
    "sg:city":"Fort Worth",
    "sg:classifiers":[
        {
            "category":"Banks & Credit Unions",
            "subcategory":"Investment Brokerage",
            "type":"Services"
        }
    ],
    "sg:phone":"+1 817 924 5747",
    "sg:postcode":"76109",
    "sg:province":"TX",
    "sg:tags":[
        "advisory"
    ],
    "wof:name":"Jss Financial Ltd",
    "wof:placetype":"venue"
},
  "geometry": {"coordinates":[-97.379479,32.682933],"type":"Point"}
}