{
  "type": "Feature",
  "properties": {
    "iso:country":"US",
    "sg:address":"400 E 7th St",
    "sg:city":"Odessa",
    "sg:classifiers":[
        {
            "category":"Retail",
            "subcategory":"Laundry & Dry Cleaning",
            "type":"Services"
        }
    ],
    "sg:phone":"+1 432 332 4242",
    "sg:postcode":"79761",
    "sg:province":"TX",
    "sg:tags":[
        "drycleaning",
        "plant"
    ],
    "wof:name":"A-1 Cleaners",
    "wof:placetype":"venue"
},
  "geometry": {"coordinates":[-102.36657099999999,31.852361],"type":"Point"}
}