{
  "type": "Feature",
  "properties": {
    "iso:country":"US",
    "sg:address":"3736 Ben Creek Ct",
    "sg:city":"Aledo",
    "sg:classifiers":[
        {
            "category":"Farming",
            "subcategory":"Livestock Farm",
            "type":"Manufacturing & Wholesale Goods"
        }
    ],
    "sg:phone":"+1 817 696 0138",
    "sg:postcode":"76008",
    "sg:province":"TX",
    "sg:tags":[
        "animal",
        "general"
    ],
    "wof:name":"HI Ru Incorporated",
    "wof:placetype":"venue"
},
  "geometry": {"coordinates":[-97.521895,32.714949],"type":"Point"}
}