{
  "type": "Feature",
  "properties": {
    "iso:country":"US",
    "sg:address":"330 E Polk St",
    "sg:city":"Richardson",
    "sg:classifiers":[
        {
            "category":"Professional",
            "type":"Services"
        }
    ],
    "sg:phone":"+1 972 907 3795",
    "sg:postcode":"75081",
    "sg:province":"TX",
    "sg:tags":[
        "establishment"
    ],
    "wof:name":"Mai Loc",
    "wof:placetype":"venue"
},
  "geometry": {"coordinates":[-96.72823200000001,32.947286],"type":"Point"}
}