{
  "type": "Feature",
  "properties": {
    "iso:country":"US",
    "sg:address":"604 NE Main St",
    "sg:city":"Ennis",
    "sg:classifiers":[
        {
            "category":"Social Services",
            "type":"Services"
        }
    ],
    "sg:phone":"+1 972 875 0218",
    "sg:postcode":"75119",
    "sg:province":"TX",
    "sg:tags":[
        "organization",
        "welfare"
    ],
    "wof:name":"Helping Hands Of Ennis",
    "wof:placetype":"venue"
},
  "geometry": {"coordinates":[-96.62907,32.33218],"type":"Point"}
}