{
  "type": "Feature",
  "properties": {
    "iso:country":"US",
    "sg:address":"1900 Long Prairie Rd",
    "sg:city":"Flower Mound",
    "sg:classifiers":[
        {
            "category":"Personal",
            "subcategory":"Beauty Salon",
            "type":"Services"
        }
    ],
    "sg:phone":"+1 972 691 5403",
    "sg:postcode":"75022",
    "sg:province":"TX",
    "sg:tags":[
        "manicuring"
    ],
    "wof:name":"T K Nails",
    "wof:placetype":"venue"
},
  "geometry": {"coordinates":[-97.070729,33.010438],"type":"Point"}
}