{
  "type": "Feature",
  "properties": {
    "iso:country":"US",
    "sg:address":"301 Hesters Crossing Rd",
    "sg:city":"Round Rock",
    "sg:classifiers":[
        {
            "category":"Building & Trades",
            "subcategory":"Construction",
            "type":"Services"
        }
    ],
    "sg:phone":"+1 512 733 5352",
    "sg:postcode":"78681",
    "sg:province":"TX",
    "sg:tags":[
        "masonry",
        "contractor"
    ],
    "wof:name":"Tejano Construction Inc",
    "wof:placetype":"venue"
},
  "geometry": {"coordinates":[-97.67775899999999,30.488528],"type":"Point"}
}