{
  "type": "Feature",
  "properties": {
    "iso:country":"US",
    "sg:address":"1031 W Lake Dr",
    "sg:city":"Hamlin",
    "sg:phone":"+1 325 576 3940",
    "sg:postcode":"79520",
    "sg:province":"TX",
    "sg:tags":[
        "farm",
        "wheat",
        "cotton"
    ],
    "wof:name":"Steve G Reynolds",
    "wof:placetype":"venue"
},
  "geometry": {"coordinates":[-100.140034,32.882567],"type":"Point"}
}