{
  "type": "Feature",
  "properties": {
    "iso:country":"US",
    "sg:address":"2847 Central Dr",
    "sg:city":"Bedford",
    "sg:classifiers":[
        {
            "category":"Shopping",
            "subcategory":"Pharmacy",
            "type":"Retail Goods"
        }
    ],
    "sg:phone":"+1 817 571 7979",
    "sg:postcode":"76021",
    "sg:province":"TX",
    "sg:tags":[
        "drug",
        "store"
    ],
    "wof:name":"Eckerd",
    "wof:placetype":"venue"
},
  "geometry": {"coordinates":[-97.132015,32.850742],"type":"Point"}
}