{
  "type": "Feature",
  "properties": {
    "iso:country":"US",
    "sg:address":"351 Peysen Rd",
    "sg:city":"Windthorst",
    "sg:classifiers":[
        {
            "category":"Government",
            "subcategory":"Office",
            "type":"Public Place"
        }
    ],
    "sg:phone":"+1 940 423 6423",
    "sg:postcode":"76389",
    "sg:province":"TX",
    "sg:tags":[
        "parish",
        "government-county"
    ],
    "wof:name":"Archer County Precinct 2",
    "wof:placetype":"venue"
},
  "geometry": {"coordinates":[-98.44790500000001,33.592949],"type":"Point"}
}