{
  "type": "Feature",
  "properties": {
    "iso:country":"US",
    "sg:address":"2545 Benrus Blvd",
    "sg:city":"San Antonio",
    "sg:classifiers":[
        {
            "category":"Organizations",
            "subcategory":"Religious Organization",
            "type":"Services"
        }
    ],
    "sg:phone":"+1 210 435 0745",
    "sg:postcode":"78228",
    "sg:province":"TX",
    "sg:tags":[
        "church"
    ],
    "wof:name":"Jehovah's Witnesses",
    "wof:placetype":"venue"
},
  "geometry": {"coordinates":[-98.58457900000001,29.469343],"type":"Point"}
}