{
  "type": "Feature",
  "properties": {
    "iso:country":"US",
    "sg:address":"4545 Louetta Rd",
    "sg:city":"Spring",
    "sg:classifiers":[
        {
            "category":"Real Estate",
            "subcategory":"Real Estate Operator",
            "type":"Services"
        }
    ],
    "sg:phone":"+1 866 354 8288",
    "sg:postcode":"77388",
    "sg:province":"TX",
    "sg:tags":[
        "apartment"
    ],
    "sg:website":"http://www.OakFalls.com",
    "wof:name":"Oak Falls Condominiums",
    "wof:placetype":"venue"
},
  "geometry": {"coordinates":[-95.483188,30.043382],"type":"Point"}
}