{
  "type": "Feature",
  "properties": {
    "iso:country":"US",
    "sg:address":"2517 N Masters Dr",
    "sg:city":"Dallas",
    "sg:classifiers":[
        {
            "category":"Building & Trades",
            "subcategory":"Construction",
            "type":"Services"
        }
    ],
    "sg:phone":"+1 972 329 6666",
    "sg:postcode":"75227",
    "sg:province":"TX",
    "sg:tags":[
        "utility",
        "contractor"
    ],
    "wof:name":"J V Rodriguez Inc",
    "wof:placetype":"venue"
},
  "geometry": {"coordinates":[-96.648123,32.756837],"type":"Point"}
}