{
  "type": "Feature",
  "properties": {
    "iso:country":"US",
    "sg:address":"633 W Phillips Ct",
    "sg:city":"Grand Prairie",
    "sg:classifiers":[
        {
            "category":"Professional",
            "type":"Services"
        }
    ],
    "sg:phone":"+1 972 263 2037",
    "sg:postcode":"75051",
    "sg:province":"TX",
    "wof:name":"A Home Away From Home",
    "wof:placetype":"venue"
},
  "geometry": {"coordinates":[-97.014765,32.723054],"type":"Point"}
}