{
  "type": "Feature",
  "properties": {
    "iso:country":"US",
    "sg:address":"18740 Stone Oak Pkwy",
    "sg:city":"San Antonio",
    "sg:classifiers":[
        {
            "category":"Restaurant",
            "type":"Food & Drink"
        }
    ],
    "sg:phone":"+1 210 403 2100",
    "sg:postcode":"78258",
    "sg:province":"TX",
    "sg:tags":[
        "eating"
    ],
    "wof:name":"Panificio Reggianos",
    "wof:placetype":"venue"
},
  "geometry": {"coordinates":[-98.49318599999999,29.611347],"type":"Point"}
}