{
  "type": "Feature",
  "properties": {
    "iso:country":"US",
    "sg:address":"9306 Nells Farm",
    "sg:city":"Helotes",
    "sg:classifiers":[
        {
            "category":"Banks & Credit Unions",
            "subcategory":"Bank",
            "type":"Services"
        }
    ],
    "sg:phone":"+1 210 695 3592",
    "sg:postcode":"78023",
    "sg:province":"TX",
    "sg:tags":[
        "mortgage"
    ],
    "wof:name":"Mortgage First Funding Lc",
    "wof:placetype":"venue"
},
  "geometry": {"coordinates":[-98.667368,29.57014],"type":"Point"}
}