{
  "type": "Feature",
  "properties": {
    "iso:country":"US",
    "sg:address":"2660 Bering Dr",
    "sg:city":"Houston",
    "sg:classifiers":[
        {
            "category":"Professional",
            "subcategory":"Detective & Security Services",
            "type":"Services"
        }
    ],
    "sg:phone":"+1 713 443 8428",
    "sg:postcode":"77057",
    "sg:province":"TX",
    "sg:tags":[
        "information"
    ],
    "wof:name":"Information Shield Inc",
    "wof:placetype":"venue"
},
  "geometry": {"coordinates":[-95.479499,29.739453],"type":"Point"}
}