{
  "type": "Feature",
  "properties": {
    "iso:country":"US",
    "sg:address":"345 S Adams St",
    "sg:city":"Eagle Pass",
    "sg:classifiers":[
        {
            "category":"Health Services",
            "subcategory":"Hospital",
            "type":"Services"
        }
    ],
    "sg:phone":"+1 830 758 4890",
    "sg:postcode":"78852",
    "sg:province":"TX",
    "wof:name":"Xavier Perez Cadena Memorial",
    "wof:placetype":"venue"
},
  "geometry": {"coordinates":[-100.503868,28.70434],"type":"Point"}
}