{
  "type": "Feature",
  "properties": {
    "iso:country":"US",
    "sg:address":"2625 Donald Rd",
    "sg:city":"Burleson",
    "sg:classifiers":[
        {
            "category":"Manufacturing",
            "subcategory":"Printing",
            "type":"Manufacturing & Wholesale Goods"
        }
    ],
    "sg:phone":"+1 817 447 0136",
    "sg:postcode":"76028",
    "sg:province":"TX",
    "sg:tags":[
        "lithographic",
        "commercial"
    ],
    "wof:name":"Clear Image Press",
    "wof:placetype":"venue"
},
  "geometry": {"coordinates":[-97.26799,32.521865],"type":"Point"}
}