{
  "type": "Feature",
  "properties": {
    "iso:country":"US",
    "sg:address":"2417 State Hwy 71",
    "sg:city":"Columbus",
    "sg:classifiers":[
        {
            "category":"Food & Beverages",
            "subcategory":"Groceries & Convenience Stores",
            "type":"Retail Goods"
        }
    ],
    "sg:phone":"+1 979 732 5780",
    "sg:postcode":"78934",
    "sg:province":"TX",
    "wof:name":"Colorado City/Diamond Shamrock",
    "wof:placetype":"venue"
},
  "geometry": {"coordinates":[-96.53926800000001,29.692026],"type":"Point"}
}