{
  "type": "Feature",
  "properties": {
    "iso:country":"US",
    "sg:address":"12402 Currin Forest Dr",
    "sg:city":"Houston",
    "sg:classifiers":[
        {
            "category":"Building & Trades",
            "subcategory":"Landscaping Services",
            "type":"Services"
        }
    ],
    "sg:phone":"+1 281 459 3226",
    "sg:postcode":"77044",
    "sg:province":"TX",
    "sg:tags":[
        "lawn",
        "maintenance",
        "grounds"
    ],
    "wof:name":"Dair Lawn Svc & Landscaping",
    "wof:placetype":"venue"
},
  "geometry": {"coordinates":[-95.21996300000001,29.900881],"type":"Point"}
}