{
  "type": "Feature",
  "properties": {
    "iso:country":"US",
    "sg:address":"2425 Canton St",
    "sg:city":"Dallas",
    "sg:classifiers":[
        {
            "category":"Wholesale",
            "subcategory":"Fruits & Vegetables",
            "type":"Manufacturing & Wholesale Goods"
        }
    ],
    "sg:phone":"+1 214 748 6333",
    "sg:postcode":"75226",
    "sg:province":"TX",
    "wof:name":"Market Distributing Co",
    "wof:placetype":"venue"
},
  "geometry": {"coordinates":[-96.78788400000001,32.781425],"type":"Point"}
}