{
  "type": "Feature",
  "properties": {
    "iso:country":"US",
    "sg:address":"7400 Fannin St",
    "sg:city":"Houston",
    "sg:classifiers":[
        {
            "category":"Health Services",
            "subcategory":"Doctor",
            "type":"Services"
        }
    ],
    "sg:phone":"+1 713 792 2121",
    "sg:postcode":"77054",
    "sg:province":"TX",
    "sg:tags":[
        "physician",
        "surgeon"
    ],
    "wof:name":"Gildy Babiera MD",
    "wof:placetype":"venue"
},
  "geometry": {"coordinates":[-95.400808,29.695646],"type":"Point"}
}