{
  "type": "Feature",
  "properties": {
    "iso:country":"US",
    "sg:address":"1504 E 29th St",
    "sg:city":"Bryan",
    "sg:classifiers":[
        {
            "category":"Building & Trades",
            "subcategory":"Plumbing",
            "type":"Services"
        }
    ],
    "sg:phone":"+1 979 823 0878",
    "sg:postcode":"77802",
    "sg:province":"TX",
    "sg:tags":[
        "refrigeration",
        "contractor"
    ],
    "wof:name":"Williams Don AC Svc",
    "wof:placetype":"venue"
},
  "geometry": {"coordinates":[-96.35781799999999,30.661722],"type":"Point"}
}