{
  "type": "Feature",
  "properties": {
    "iso:country":"US",
    "sg:address":"1948 S Main St",
    "sg:city":"Weatherford",
    "sg:classifiers":[
        {
            "category":"Banks & Credit Unions",
            "subcategory":"Financial Services",
            "type":"Services"
        }
    ],
    "sg:phone":"+1 817 599 3663",
    "sg:postcode":"76086",
    "sg:province":"TX",
    "sg:tags":[
        "alternative",
        "loan",
        "payday"
    ],
    "sg:website":"http://www.cashstore.com/TX/Trademark/yp.com",
    "wof:name":"Cash Store",
    "wof:placetype":"venue"
},
  "geometry": {"coordinates":[-97.79549,32.735647],"type":"Point"}
}