{
  "type": "Feature",
  "properties": {
    "iso:country":"US",
    "sg:address":"3662 W Camp Wisdom Rd",
    "sg:city":"Dallas",
    "sg:classifiers":[
        {
            "category":"Shopping",
            "subcategory":"Books",
            "type":"Retail Goods"
        }
    ],
    "sg:phone":"+1 972 296 2712",
    "sg:postcode":"75232",
    "sg:province":"TX",
    "sg:tags":[
        "store"
    ],
    "wof:name":"Waldenbooks",
    "wof:placetype":"venue"
},
  "geometry": {"coordinates":[-96.880066,32.661946],"type":"Point"}
}