{
  "type": "Feature",
  "properties": {
    "iso:country":"US",
    "sg:address":"12903 Westheimer Rd",
    "sg:city":"Houston",
    "sg:classifiers":[
        {
            "category":"Manufacturing",
            "subcategory":"Signs",
            "type":"Manufacturing & Wholesale Goods"
        }
    ],
    "sg:phone":"+1 281 752 7446",
    "sg:postcode":"77077",
    "sg:province":"TX",
    "sg:tags":[
        "specialty",
        "mfg"
    ],
    "wof:name":"Affordable Signs",
    "wof:placetype":"venue"
},
  "geometry": {"coordinates":[-95.613603,29.735932],"type":"Point"}
}