{
  "type": "Feature",
  "properties": {
    "iso:country":"US",
    "sg:address":"8215 University Ave",
    "sg:city":"Lubbock",
    "sg:classifiers":[
        {
            "category":"Restaurant",
            "type":"Food & Drink"
        }
    ],
    "sg:menulink":"http://www.allmenus.com/tx/lubbock/88443-pizza-patron/menu/",
    "sg:phone":"+1 806 745 9191",
    "sg:postcode":"79423",
    "sg:province":"TX",
    "sg:tags":[
        "american",
        "pizza"
    ],
    "wof:name":"Pizza Patron",
    "wof:placetype":"venue"
},
  "geometry": {"coordinates":[-101.870324,33.519453],"type":"Point"}
}