{
  "type": "Feature",
  "properties": {
    "iso:country":"US",
    "sg:address":"612 Cardinal Dr",
    "sg:city":"Red Oak",
    "sg:classifiers":[
        {
            "category":"Home & Garden",
            "subcategory":"Home Furnishings",
            "type":"Retail Goods"
        }
    ],
    "sg:phone":"+1 972 617 3828",
    "sg:postcode":"75154",
    "sg:province":"TX",
    "wof:name":"Cindys Draperies",
    "wof:placetype":"venue"
},
  "geometry": {"coordinates":[-96.873374,32.526697],"type":"Point"}
}