{
  "type": "Feature",
  "properties": {
    "iso:country":"US",
    "sg:address":"2301 Eldorado Pkwy",
    "sg:city":"Mc Kinney",
    "sg:classifiers":[
        {
            "category":"Health Services",
            "subcategory":"Doctor",
            "type":"Services"
        }
    ],
    "sg:phone":"+1 972 542 3005",
    "sg:postcode":"75070",
    "sg:province":"TX",
    "sg:tags":[
        "dentist"
    ],
    "wof:name":"Michael C Imboden Pa",
    "wof:placetype":"venue"
},
  "geometry": {"coordinates":[-96.644583,33.171888],"type":"Point"}
}