{
  "type": "Feature",
  "properties": {
    "iso:country":"US",
    "sg:address":"1533 Sam Houston Pkwy",
    "sg:city":"Houston",
    "sg:classifiers":[
        {
            "category":"Health Services",
            "subcategory":"Doctor",
            "type":"Services"
        }
    ],
    "sg:phone":"+1 713 789 0133",
    "sg:postcode":"77042",
    "sg:province":"TX",
    "sg:tags":[
        "physician",
        "surgeon"
    ],
    "wof:name":"Luis E Guerrero MD",
    "wof:placetype":"venue"
},
  "geometry": {"coordinates":[-95.55847,29.747276],"type":"Point"}
}