{
  "type": "Feature",
  "properties": {
    "iso:country":"US",
    "sg:address":"7301 Ranch Rd 620 N",
    "sg:city":"Austin",
    "sg:classifiers":[
        {
            "category":"Cinema",
            "subcategory":"Movie Rental",
            "type":"Entertainment"
        }
    ],
    "sg:phone":"+1 512 336 2035",
    "sg:postcode":"78726",
    "sg:province":"TX",
    "sg:tags":[
        "video",
        "tape"
    ],
    "wof:name":"Hollywood Video",
    "wof:placetype":"venue"
},
  "geometry": {"coordinates":[-97.853364,30.404897],"type":"Point"}
}