{
  "type": "Feature",
  "properties": {
    "iso:country":"US",
    "sg:address":"13 SW 8th Ave",
    "sg:city":"Perryton",
    "sg:classifiers":[
        {
            "category":"Home & Garden",
            "subcategory":"Carpets & Floor Coverings",
            "type":"Retail Goods"
        }
    ],
    "sg:phone":"+1 806 435 3019",
    "sg:postcode":"79070",
    "sg:province":"TX",
    "sg:tags":[
        "material"
    ],
    "wof:name":"Schwalk Floor Covering & Glass",
    "wof:placetype":"venue"
},
  "geometry": {"coordinates":[-100.803909,36.392164],"type":"Point"}
}