{
  "type": "Feature",
  "properties": {
    "iso:country":"US",
    "sg:address":"125 North St",
    "sg:city":"New Boston",
    "sg:classifiers":[
        {
            "category":"Shopping",
            "subcategory":"Clothing, Apparel, & Fashions",
            "type":"Retail Goods"
        }
    ],
    "sg:phone":"+1 903 628 1010",
    "sg:postcode":"75570",
    "sg:province":"TX",
    "wof:name":"Factory Connection 83",
    "wof:placetype":"venue"
},
  "geometry": {"coordinates":[-94.41757699999999,33.462246],"type":"Point"}
}