{
  "type": "Feature",
  "properties": {
    "iso:country":"US",
    "sg:address":"15607 Tarpon Springs Ct",
    "sg:city":"Houston",
    "sg:classifiers":[
        {
            "category":"Restaurant",
            "type":"Food & Drink"
        }
    ],
    "sg:phone":"+1 281 498 5252",
    "sg:postcode":"77095",
    "sg:province":"TX",
    "sg:tags":[
        "caterer"
    ],
    "wof:name":"Food Works",
    "wof:placetype":"venue"
},
  "geometry": {"coordinates":[-95.63893400000001,29.907933],"type":"Point"}
}