{
  "type": "Feature",
  "properties": {
    "iso:country":"US",
    "sg:address":"7919 Marbach Rd",
    "sg:city":"San Antonio",
    "sg:classifiers":[
        {
            "category":"Restaurant",
            "type":"Food & Drink"
        }
    ],
    "sg:phone":"+1 210 673 0080",
    "sg:postcode":"78227",
    "sg:province":"TX",
    "sg:tags":[
        "eating"
    ],
    "wof:name":"Church's Chicken",
    "wof:placetype":"venue"
},
  "geometry": {"coordinates":[-98.646805,29.417891],"type":"Point"}
}