{
  "type": "Feature",
  "properties": {
    "iso:country":"US",
    "sg:address":"802 Oak St",
    "sg:city":"Jourdanton",
    "sg:classifiers":[
        {
            "category":"Restaurant",
            "type":"Food & Drink"
        }
    ],
    "sg:phone":"+1 830 769 9226",
    "sg:postcode":"78026",
    "sg:province":"TX",
    "sg:tags":[
        "eating"
    ],
    "wof:name":"Jalisco Mexican Restaurant 2",
    "wof:placetype":"venue"
},
  "geometry": {"coordinates":[-98.54728,28.917924],"type":"Point"}
}