{
  "type": "Feature",
  "properties": {
    "iso:country":"US",
    "sg:address":"5525 Sherwood Way",
    "sg:city":"San Angelo",
    "sg:classifiers":[
        {
            "category":"Professional",
            "type":"Services"
        }
    ],
    "sg:phone":"+1 325 947 7874",
    "sg:postcode":"76901",
    "sg:province":"TX",
    "sg:tags":[
        "establishment"
    ],
    "wof:name":"Additech",
    "wof:placetype":"venue"
},
  "geometry": {"coordinates":[-100.510182,31.429065],"type":"Point"}
}