{
  "type": "Feature",
  "properties": {
    "iso:country":"US",
    "sg:address":"2261 Country Club Rd",
    "sg:city":"San Angelo",
    "sg:phone":"+1 325 651 7309",
    "sg:postcode":"76904",
    "sg:province":"TX",
    "sg:tags":[
        "farm",
        "ranch"
    ],
    "wof:name":"Steven H Hoelscher Farms",
    "wof:placetype":"venue"
},
  "geometry": {"coordinates":[-100.453425,31.381544],"type":"Point"}
}