{
  "type": "Feature",
  "properties": {
    "iso:country":"US",
    "sg:address":"6622 Stewart Rd",
    "sg:city":"Galveston",
    "sg:classifiers":[
        {
            "category":"Manufacturing",
            "subcategory":"Printing",
            "type":"Manufacturing & Wholesale Goods"
        }
    ],
    "sg:phone":"+1 409 771 9461",
    "sg:postcode":"77551",
    "sg:province":"TX",
    "sg:tags":[
        "typesetting"
    ],
    "wof:name":"Art & Type Studio",
    "wof:placetype":"venue"
},
  "geometry": {"coordinates":[-94.83668299999999,29.273308],"type":"Point"}
}