{
  "type": "Feature",
  "properties": {
    "iso:country":"US",
    "sg:address":"805 Hudson Dr",
    "sg:city":"Garland",
    "sg:classifiers":[
        {
            "category":"Professional",
            "type":"Services"
        }
    ],
    "sg:phone":"+1 972 686 4420",
    "sg:postcode":"75043",
    "sg:province":"TX",
    "sg:tags":[
        "freelance",
        "calligrapher"
    ],
    "wof:name":"Bohlin Sue",
    "wof:placetype":"venue"
},
  "geometry": {"coordinates":[-96.63245999999999,32.846566],"type":"Point"}
}