{
  "type": "Feature",
  "properties": {
    "iso:country":"US",
    "sg:address":"3265 Roosevelt Ave",
    "sg:city":"San Antonio",
    "sg:classifiers":[
        {
            "category":"Health Services",
            "subcategory":"Doctor",
            "type":"Services"
        }
    ],
    "sg:phone":"+1 210 922 9377",
    "sg:postcode":"78214",
    "sg:province":"TX",
    "sg:tags":[
        "osteopathic"
    ],
    "wof:name":"Howard H Galarneau Do",
    "wof:placetype":"venue"
},
  "geometry": {"coordinates":[-98.481476,29.36056],"type":"Point"}
}