{
  "type": "Feature",
  "properties": {
    "iso:country":"US",
    "sg:address":"17300 Dallas Pkwy",
    "sg:city":"Dallas",
    "sg:classifiers":[
        {
            "category":"Government",
            "subcategory":"Office",
            "type":"Public Place"
        }
    ],
    "sg:phone":"+1 972 735 8467",
    "sg:postcode":"75248",
    "sg:province":"TX",
    "sg:tags":[
        "regulatory",
        "banking"
    ],
    "wof:name":"Dallas-North Field Office",
    "wof:placetype":"venue"
},
  "geometry": {"coordinates":[-96.82830199999999,32.985793],"type":"Point"}
}