{
  "type": "Feature",
  "properties": {
    "iso:country":"US",
    "sg:address":"406 Virginia Ave",
    "sg:city":"Corpus Christi",
    "sg:classifiers":[
        {
            "category":"Organizations",
            "subcategory":"Religious Organization",
            "type":"Services"
        }
    ],
    "sg:phone":"+1 361 882 8459",
    "sg:postcode":"78405",
    "sg:province":"TX",
    "sg:tags":[
        "church"
    ],
    "wof:name":"Primera Iglesia Del Nazareno",
    "wof:placetype":"venue"
},
  "geometry": {"coordinates":[-97.430886,27.779397],"type":"Point"}
}