{
  "type": "Feature",
  "properties": {
    "iso:country":"US",
    "sg:address":"601 Jefferson St",
    "sg:city":"Houston",
    "sg:classifiers":[
        {
            "category":"Professional",
            "subcategory":"Management & Consulting",
            "type":"Services"
        }
    ],
    "sg:phone":"+1 713 753 2000",
    "sg:postcode":"77002",
    "sg:province":"TX",
    "sg:tags":[
        "marketing",
        "program"
    ],
    "wof:name":"KBR Corp",
    "wof:placetype":"venue"
},
  "geometry": {"coordinates":[-95.37224399999999,29.752547],"type":"Point"}
}