{
  "type": "Feature",
  "properties": {
    "iso:country":"US",
    "sg:address":"5829 Reiger Ave",
    "sg:city":"Dallas",
    "sg:classifiers":[
        {
            "category":"Professional",
            "subcategory":"Management & Consulting",
            "type":"Services"
        }
    ],
    "sg:phone":"+1 214 826 8696",
    "sg:postcode":"75214",
    "sg:province":"TX",
    "sg:tags":[
        "science",
        "consultant",
        "academic"
    ],
    "wof:name":"Texas Honeybee Guild",
    "wof:placetype":"venue"
},
  "geometry": {"coordinates":[-96.753987,32.804696],"type":"Point"}
}