{
  "type": "Feature",
  "properties": {
    "iso:country":"US",
    "sg:address":"2713 W 5th St",
    "sg:city":"Fort Worth",
    "sg:classifiers":[
        {
            "category":"Retail",
            "subcategory":"Car Wash",
            "type":"Services"
        }
    ],
    "sg:phone":"+1 817 335 2011",
    "sg:postcode":"76107",
    "sg:province":"TX",
    "sg:tags":[
        "automobile",
        "detail",
        "clean"
    ],
    "wof:name":"Overspray Removal",
    "wof:placetype":"venue"
},
  "geometry": {"coordinates":[-97.356308,32.752924],"type":"Point"}
}