{
  "type": "Feature",
  "properties": {
    "iso:country":"US",
    "sg:address":"111 N Austin St",
    "sg:city":"Seguin",
    "sg:classifiers":[
        {
            "category":"Retail",
            "subcategory":"Auto Repair",
            "type":"Services"
        }
    ],
    "sg:phone":"+1 830 372 9933",
    "sg:postcode":"78155",
    "sg:province":"TX",
    "sg:tags":[
        "general"
    ],
    "wof:name":"Deuce Coupe Automotive",
    "wof:placetype":"venue"
},
  "geometry": {"coordinates":[-97.964572,29.569587],"type":"Point"}
}