{
  "type": "Feature",
  "properties": {
    "iso:country":"US",
    "sg:address":"2501 N Eastman Rd",
    "sg:city":"Longview",
    "sg:classifiers":[
        {
            "category":"Professional",
            "subcategory":"Computer Services",
            "type":"Services"
        }
    ],
    "sg:phone":"+1 903 553 9774",
    "sg:postcode":"75605",
    "sg:province":"TX",
    "sg:tags":[
        "related"
    ],
    "wof:name":"Zron Consulting Technical Svc",
    "wof:placetype":"venue"
},
  "geometry": {"coordinates":[-94.719369,32.525034],"type":"Point"}
}