{
  "type": "Feature",
  "properties": {
    "iso:country":"US",
    "sg:address":"2777 N Stemmons Fwy Ste 1220",
    "sg:city":"Dallas",
    "sg:classifiers":[
        {
            "category":"Banks & Credit Unions",
            "subcategory":"Investment Brokerage",
            "type":"Services"
        }
    ],
    "sg:phone":"+1 214 638 8280",
    "sg:postcode":"75207",
    "sg:province":"TX",
    "sg:tags":[
        "investing"
    ],
    "wof:name":"Capital Alliance Corporation",
    "wof:placetype":"venue"
},
  "geometry": {"coordinates":[-96.846199,32.809101],"type":"Point"}
}