{
  "type": "Feature",
  "properties": {
    "iso:country":"US",
    "sg:address":"542 N Main St",
    "sg:city":"Duncanville",
    "sg:classifiers":[
        {
            "category":"Shopping",
            "subcategory":"Books",
            "type":"Retail Goods"
        }
    ],
    "sg:phone":"+1 972 296 5411",
    "sg:postcode":"75116",
    "sg:province":"TX",
    "sg:tags":[
        "dealer"
    ],
    "wof:name":"Hidden Treasures Christians",
    "wof:placetype":"venue"
},
  "geometry": {"coordinates":[-96.907787,32.655393],"type":"Point"}
}