{
  "type": "Feature",
  "properties": {
    "iso:country":"US",
    "sg:address":"300 Buttercup Ln",
    "sg:city":"Wimberley",
    "sg:classifiers":[
        {
            "category":"Manufacturing",
            "subcategory":"Retail Goods",
            "type":"Manufacturing & Wholesale Goods"
        }
    ],
    "sg:phone":"+1 512 847 7105",
    "sg:postcode":"78676",
    "sg:province":"TX",
    "sg:tags":[
        "lead",
        "mfg"
    ],
    "wof:name":"Lillian D Arnold",
    "wof:placetype":"venue"
},
  "geometry": {"coordinates":[-98.075525,29.999636],"type":"Point"}
}