{
  "type": "Feature",
  "properties": {
    "iso:country":"US",
    "sg:address":"6385 Calder Ave",
    "sg:city":"Beaumont",
    "sg:classifiers":[
        {
            "category":"Banks & Credit Unions",
            "subcategory":"Investment Brokerage",
            "type":"Services"
        }
    ],
    "sg:phone":"+1 409 861 2329",
    "sg:postcode":"77706",
    "sg:province":"TX",
    "sg:tags":[
        "security"
    ],
    "wof:name":"Edward Jones Co",
    "wof:placetype":"venue"
},
  "geometry": {"coordinates":[-94.169177,30.076893],"type":"Point"}
}