{
  "type": "Feature",
  "properties": {
    "iso:country":"US",
    "sg:address":"207 E 7th St",
    "sg:city":"Prosper",
    "sg:classifiers":[
        {
            "category":"Building & Trades",
            "subcategory":"Construction",
            "type":"Services"
        }
    ],
    "sg:phone":"+1 972 347 2702",
    "sg:postcode":"75078",
    "sg:province":"TX",
    "sg:tags":[
        "contractor"
    ],
    "wof:name":"Reece Construction Co Inc",
    "wof:placetype":"venue"
},
  "geometry": {"coordinates":[-96.799823,33.239449],"type":"Point"}
}