{
  "type": "Feature",
  "properties": {
    "iso:country":"US",
    "sg:address":"106 W Pasadena Blvd",
    "sg:city":"Deer Park",
    "sg:classifiers":[
        {
            "category":"Health Services",
            "subcategory":"Doctor",
            "type":"Services"
        }
    ],
    "sg:phone":"+1 281 479 5555",
    "sg:postcode":"77536",
    "sg:province":"TX",
    "sg:tags":[
        "medical"
    ],
    "wof:name":"Bas Nair",
    "wof:placetype":"venue"
},
  "geometry": {"coordinates":[-95.123316,29.679127],"type":"Point"}
}