{
  "type": "Feature",
  "properties": {
    "iso:country":"US",
    "sg:address":"124 E Gonzales St",
    "sg:city":"Yoakum",
    "sg:classifiers":[
        {
            "category":"Social Services",
            "subcategory":"Child Care",
            "type":"Services"
        }
    ],
    "sg:phone":"+1 361 293 7415",
    "sg:postcode":"77995",
    "sg:province":"TX",
    "sg:tags":[
        "day"
    ],
    "wof:name":"Learning Tree",
    "wof:placetype":"venue"
},
  "geometry": {"coordinates":[-97.14799499999999,29.290812],"type":"Point"}
}