{
  "type": "Feature",
  "properties": {
    "iso:country":"US",
    "sg:address":"207 Produce",
    "sg:city":"Hidalgo",
    "sg:classifiers":[
        {
            "category":"Wholesale",
            "subcategory":"Fruits & Vegetables",
            "type":"Manufacturing & Wholesale Goods"
        }
    ],
    "sg:phone":"+1 956 843 2283",
    "sg:postcode":"78557",
    "sg:province":"TX",
    "wof:name":"G M Super Sales Co",
    "wof:placetype":"venue"
},
  "geometry": {"coordinates":[-98.25565400000001,26.111538],"type":"Point"}
}