{
  "type": "Feature",
  "properties": {
    "iso:country":"US",
    "sg:address":"13971 Millmac Rd",
    "sg:city":"Conroe",
    "sg:classifiers":[
        {
            "category":"Mining & Drilling",
            "type":"Manufacturing & Wholesale Goods"
        }
    ],
    "sg:phone":"+1 409 697 7318",
    "sg:postcode":"77303",
    "sg:province":"TX",
    "sg:tags":[
        "field",
        "oil"
    ],
    "wof:name":"Mre Specialties",
    "wof:placetype":"venue"
},
  "geometry": {"coordinates":[-95.35230799999999,30.338639],"type":"Point"}
}