{
  "type": "Feature",
  "properties": {
    "iso:country":"US",
    "sg:address":"105 Russell St",
    "sg:city":"Fort Worth",
    "sg:classifiers":[
        {
            "category":"Building & Trades",
            "subcategory":"Electrical",
            "type":"Services"
        }
    ],
    "sg:phone":"+1 817 246 0126",
    "sg:postcode":"76108",
    "sg:province":"TX",
    "sg:tags":[
        "electrical",
        "electric",
        "contractor"
    ],
    "wof:name":"B-Brothers Electric Inc",
    "wof:placetype":"venue"
},
  "geometry": {"coordinates":[-97.46085100000001,32.762608],"type":"Point"}
}