{
  "type": "Feature",
  "properties": {
    "iso:country":"US",
    "sg:address":"2001 Lindbergh Dr",
    "sg:city":"Tyler",
    "sg:classifiers":[
        {
            "category":"Professional",
            "subcategory":"Management & Consulting",
            "type":"Services"
        }
    ],
    "sg:phone":"+1 903 581 2260",
    "sg:postcode":"75703",
    "sg:province":"TX",
    "sg:tags":[
        "medical",
        "administration",
        "business"
    ],
    "wof:name":"Pro Health Research Ctr",
    "wof:placetype":"venue"
},
  "geometry": {"coordinates":[-95.271818,32.30717],"type":"Point"}
}