{
  "type": "Feature",
  "properties": {
    "iso:country":"US",
    "sg:address":"1025 S Rosemont Ave",
    "sg:city":"Dallas",
    "sg:classifiers":[
        {
            "category":"Professional",
            "subcategory":"Accounting & Tax Preparation",
            "type":"Services"
        }
    ],
    "sg:phone":"+1 214 946 5505",
    "sg:postcode":"75208",
    "sg:province":"TX",
    "sg:tags":[
        "return",
        "prep"
    ],
    "wof:name":"Gainer Tax Service",
    "wof:placetype":"venue"
},
  "geometry": {"coordinates":[-96.848054,32.735513],"type":"Point"}
}