{
  "type": "Feature",
  "properties": {
    "iso:country":"US",
    "sg:address":"621 Estate Dr",
    "sg:city":"Belton",
    "sg:classifiers":[
        {
            "category":"Professional",
            "subcategory":"Management & Consulting",
            "type":"Services"
        }
    ],
    "sg:phone":"+1 254 780 4040",
    "sg:postcode":"76513",
    "sg:province":"TX",
    "sg:tags":[
        "consultant",
        "lighting"
    ],
    "wof:name":"Able-I Illumination",
    "wof:placetype":"venue"
},
  "geometry": {"coordinates":[-97.456036,31.08484],"type":"Point"}
}