{
  "type": "Feature",
  "properties": {
    "iso:country":"US",
    "sg:address":"22973 Continental Quarters",
    "sg:city":"Montgomery",
    "sg:classifiers":[
        {
            "category":"Building & Trades",
            "subcategory":"Plumbing",
            "type":"Services"
        }
    ],
    "sg:phone":"+1 936 597 5558",
    "sg:postcode":"77316",
    "sg:province":"TX",
    "sg:tags":[
        "contractor"
    ],
    "wof:name":"Sterling Environmental",
    "wof:placetype":"venue"
},
  "geometry": {"coordinates":[-95.72269900000001,30.341418],"type":"Point"}
}