{
  "type": "Feature",
  "properties": {
    "iso:country":"US",
    "sg:address":"7407 Castle Throne Dr",
    "sg:city":"San Antonio",
    "sg:classifiers":[
        {
            "category":"Shopping",
            "subcategory":"Clothing, Apparel, & Fashions",
            "type":"Retail Goods"
        }
    ],
    "sg:phone":"+1 210 657 5463",
    "sg:postcode":"78218",
    "sg:province":"TX",
    "wof:name":"Adrianas Clothing & Acce",
    "wof:placetype":"venue"
},
  "geometry": {"coordinates":[-98.381308,29.501759],"type":"Point"}
}