{
  "type": "Feature",
  "properties": {
    "iso:country":"US",
    "sg:address":"1535 Parr St",
    "sg:city":"Amarillo",
    "sg:classifiers":[
        {
            "category":"Wholesale",
            "subcategory":"Durable Goods & Equipment",
            "type":"Manufacturing & Wholesale Goods"
        }
    ],
    "sg:phone":"+1 806 355 4259",
    "sg:postcode":"79106",
    "sg:province":"TX",
    "wof:name":"Prairie Home Antiques",
    "wof:placetype":"venue"
},
  "geometry": {"coordinates":[-101.901357,35.194952],"type":"Point"}
}