{
  "type": "Feature",
  "properties": {
    "iso:country":"US",
    "sg:address":"1517 Hawk Ct",
    "sg:city":"Garland",
    "sg:classifiers":[
        {
            "category":"Professional",
            "subcategory":"Art Services",
            "type":"Services"
        }
    ],
    "sg:phone":"+1 972 840 0563",
    "sg:postcode":"75040",
    "sg:province":"TX",
    "sg:tags":[
        "commercial",
        "design"
    ],
    "wof:name":"KB Design Link",
    "wof:placetype":"venue"
},
  "geometry": {"coordinates":[-96.61074600000001,32.895563],"type":"Point"}
}