{
  "type": "Feature",
  "properties": {
    "iso:country":"US",
    "sg:address":"111 N Post Oak Ln",
    "sg:city":"Houston",
    "sg:classifiers":[
        {
            "category":"Restaurant",
            "type":"Food & Drink"
        }
    ],
    "sg:phone":"+1 713 685 6713",
    "sg:postcode":"77024",
    "sg:province":"TX",
    "wof:name":"Olivette At the Houstonian",
    "wof:placetype":"venue"
},
  "geometry": {"coordinates":[-95.45760300000001,29.7684],"type":"Point"}
}