{
  "type": "Feature",
  "properties": {
    "iso:country":"US",
    "sg:address":"925 Lindy Ct",
    "sg:city":"Irving",
    "sg:classifiers":[
        {
            "category":"Freight",
            "type":"Transportation"
        }
    ],
    "sg:phone":"+1 214 789 4059",
    "sg:postcode":"75060",
    "sg:province":"TX",
    "sg:tags":[
        "mover"
    ],
    "wof:name":"Devco Moving",
    "wof:placetype":"venue"
},
  "geometry": {"coordinates":[-96.934867,32.804129],"type":"Point"}
}