{
  "type": "Feature",
  "properties": {
    "iso:country":"US",
    "sg:address":"2004 Hwy 190 W",
    "sg:city":"Livingston",
    "sg:classifiers":[
        {
            "category":"Insurance",
            "subcategory":"Insurance Agent",
            "type":"Services"
        }
    ],
    "sg:phone":"+1 936 628 3731",
    "sg:postcode":"77351",
    "sg:province":"TX",
    "wof:name":"J David Brown Insurance",
    "wof:placetype":"venue"
},
  "geometry": {"coordinates":[-94.9532,30.711956],"type":"Point"}
}