{
  "type": "Feature",
  "properties": {
    "iso:country":"US",
    "sg:address":"108 E Main St",
    "sg:city":"Itasca",
    "sg:classifiers":[
        {
            "category":"Retail",
            "subcategory":"Car Wash",
            "type":"Services"
        }
    ],
    "sg:phone":"+1 817 645 2920",
    "sg:postcode":"76055",
    "sg:province":"TX",
    "sg:tags":[
        "carwash"
    ],
    "wof:name":"Hjr Incorporated",
    "wof:placetype":"venue"
},
  "geometry": {"coordinates":[-97.149168,32.159926],"type":"Point"}
}