{
  "type": "Feature",
  "properties": {
    "iso:country":"US",
    "sg:address":"12901 N I 35 # 1200",
    "sg:city":"Austin",
    "sg:classifiers":[
        {
            "category":"Fast Food",
            "type":"Food & Drink"
        },
        {
            "category":"Restaurant",
            "type":"Food & Drink"
        }
    ],
    "sg:phone":"+1 512 989 3154",
    "sg:postcode":"78753",
    "sg:province":"TX",
    "sg:tags":[
        "burger",
        "pizza"
    ],
    "sg:website":"planksaustin.com",
    "wof:name":"Planks",
    "wof:placetype":"venue"
},
  "geometry": {"coordinates":[-97.67187300000001,30.416718],"type":"Point"}
}