{
  "type": "Feature",
  "properties": {
    "iso:country":"US",
    "sg:address":"2097 Sunset Dr",
    "sg:city":"Zapata",
    "sg:classifiers":[
        {
            "category":"Organizations",
            "subcategory":"Community Association",
            "type":"Services"
        }
    ],
    "sg:phone":"+1 956 765 8210",
    "sg:postcode":"78076",
    "sg:province":"TX",
    "sg:tags":[
        "club"
    ],
    "wof:name":"Falcon Lake Estates Club Inc",
    "wof:placetype":"venue"
},
  "geometry": {"coordinates":[-99.256299,26.870693],"type":"Point"}
}