{
  "type": "Feature",
  "properties": {
    "iso:country":"US",
    "sg:address":"4506 Normandy Way",
    "sg:city":"Grand Prairie",
    "sg:classifiers":[
        {
            "category":"Professional",
            "subcategory":"Management & Consulting",
            "type":"Services"
        },
        {
            "category":"Wholesale",
            "subcategory":"Non-durable Goods",
            "type":"Manufacturing & Wholesale Goods"
        }
    ],
    "sg:phone":"+1 972 606 4525",
    "sg:postcode":"75052",
    "sg:province":"TX",
    "sg:tags":[
        "public",
        "relations",
        "advertising"
    ],
    "wof:name":"Branding Iron Promotions LLC",
    "wof:placetype":"venue"
},
  "geometry": {"coordinates":[-97.05897899999999,32.662541],"type":"Point"}
}