{
  "type": "Feature",
  "properties": {
    "iso:country":"US",
    "sg:address":"8907 Trone Cir",
    "sg:city":"Austin",
    "sg:classifiers":[
        {
            "category":"Manufacturing",
            "subcategory":"Toys & Sporting Goods",
            "type":"Manufacturing & Wholesale Goods"
        }
    ],
    "sg:phone":"+1 512 834 9000",
    "sg:postcode":"78758",
    "sg:province":"TX",
    "sg:tags":[
        "mfg"
    ],
    "wof:name":"Affinity Enterprises",
    "wof:placetype":"venue"
},
  "geometry": {"coordinates":[-97.71003899999999,30.363837],"type":"Point"}
}