{
  "type": "Feature",
  "properties": {
    "iso:country":"US",
    "sg:address":"1120 Silber Rd",
    "sg:city":"Houston",
    "sg:classifiers":[
        {
            "category":"Government",
            "subcategory":"Fire Station",
            "type":"Public Place"
        }
    ],
    "sg:phone":"+1 713 222 7643",
    "sg:postcode":"77055",
    "sg:province":"TX",
    "sg:tags":[
        "protection"
    ],
    "wof:name":"Fire Dept-Station 38",
    "wof:placetype":"venue"
},
  "geometry": {"coordinates":[-95.468137,29.789131],"type":"Point"}
}