{
  "type": "Feature",
  "properties": {
    "iso:country":"US",
    "sg:address":"1409 N Oak St",
    "sg:city":"Pearsall",
    "sg:classifiers":[
        {
            "category":"Restaurant",
            "type":"Food & Drink"
        }
    ],
    "sg:phone":"+1 830 334 2320",
    "sg:postcode":"78061",
    "sg:province":"TX",
    "sg:tags":[
        "mexican"
    ],
    "wof:name":"Guadalajara Mexican Restaurant",
    "wof:placetype":"venue"
},
  "geometry": {"coordinates":[-99.092434,28.901168],"type":"Point"}
}