{
  "type": "Feature",
  "properties": {
    "iso:country":"US",
    "sg:address":"702 S I- 35 E",
    "sg:city":"Denton",
    "sg:classifiers":[
        {
            "category":"Professional",
            "type":"Services"
        },
        {
            "category":"Organizations",
            "subcategory":"Professional Association",
            "type":"Services"
        }
    ],
    "sg:phone":"+1 940 382 7200",
    "sg:postcode":"76205",
    "sg:province":"TX",
    "wof:name":"Texas Emancipation Parade Assn",
    "wof:placetype":"venue"
},
  "geometry": {"coordinates":[-97.124077,33.193044],"type":"Point"}
}