{
  "type": "Feature",
  "properties": {
    "iso:country":"US",
    "sg:address":"33851 FM 429",
    "sg:city":"Quinlan",
    "sg:classifiers":[
        {
            "category":"Building & Trades",
            "subcategory":"Construction",
            "type":"Services"
        }
    ],
    "sg:phone":"+1 972 563 1918",
    "sg:postcode":"75160",
    "sg:province":"TX",
    "sg:tags":[
        "general",
        "contractor"
    ],
    "wof:name":"General Contractors",
    "wof:placetype":"venue"
},
  "geometry": {"coordinates":[-96.085481,32.833439],"type":"Point"}
}