{
  "type": "Feature",
  "properties": {
    "iso:country":"US",
    "sg:address":"2033 W Mcdermott Dr",
    "sg:city":"Allen",
    "sg:classifiers":[
        {
            "category":"Restaurant",
            "type":"Food & Drink"
        }
    ],
    "sg:menulink":"http://www.allmenus.com/tx/plano/130548-subway/menu/",
    "sg:phone":"+1 972 747 9379",
    "sg:postcode":"75013",
    "sg:province":"TX",
    "sg:tags":[
        "american",
        "sandwich"
    ],
    "wof:name":"Subway",
    "wof:placetype":"venue"
},
  "geometry": {"coordinates":[-96.73124300000001,33.100789],"type":"Point"}
}