{
  "type": "Feature",
  "properties": {
    "iso:country":"US",
    "sg:address":"538 N Willow Dr",
    "sg:city":"Houston",
    "sg:classifiers":[
        {
            "category":"Autos & Motor Vehicles",
            "subcategory":"Automobile Sales",
            "type":"Retail Goods"
        }
    ],
    "sg:phone":"+1 281 821 9462",
    "sg:postcode":"77073",
    "sg:province":"TX",
    "sg:tags":[
        "used"
    ],
    "wof:name":"Canchola Auto Sales",
    "wof:placetype":"venue"
},
  "geometry": {"coordinates":[-95.419167,30.00751],"type":"Point"}
}