{
  "type": "Feature",
  "properties": {
    "iso:country":"US",
    "sg:address":"2700 Via Fortuna",
    "sg:city":"Austin",
    "sg:classifiers":[
        {
            "category":"Real Estate",
            "subcategory":"Real Estate Services",
            "type":"Services"
        }
    ],
    "sg:phone":"+1 512 458 8100",
    "sg:postcode":"78746",
    "sg:province":"TX",
    "sg:tags":[
        "management",
        "property"
    ],
    "wof:name":"Colliers Oxford Commercial Property Management",
    "wof:placetype":"venue"
},
  "geometry": {"coordinates":[-97.799797,30.253799],"type":"Point"}
}