{
  "type": "Feature",
  "properties": {
    "iso:country":"US",
    "sg:address":"26519 Oak Ridge Dr",
    "sg:city":"Spring",
    "sg:classifiers":[
        {
            "category":"Personal",
            "subcategory":"Beauty Salon",
            "type":"Services"
        },
        {
            "category":"Personal",
            "subcategory":"Nail Salon",
            "type":"Services"
        }
    ],
    "sg:phone":"+1 281 364 9487",
    "sg:postcode":"77380",
    "sg:province":"TX",
    "sg:tags":[
        "hair",
        "stylist"
    ],
    "wof:name":"Wade & Company",
    "wof:placetype":"venue"
},
  "geometry": {"coordinates":[-95.449203,30.148219],"type":"Point"}
}