{
  "type": "Feature",
  "properties": {
    "iso:country":"US",
    "sg:address":"2305 Fuller Ln",
    "sg:city":"Harker Heights",
    "sg:classifiers":[
        {
            "category":"Building & Trades",
            "subcategory":"Landscaping Services",
            "type":"Services"
        }
    ],
    "sg:phone":"+1 254 698 3069",
    "sg:postcode":"76548",
    "sg:province":"TX",
    "wof:name":"Rook Lawn & Tree Service",
    "wof:placetype":"venue"
},
  "geometry": {"coordinates":[-97.632114,31.027113],"type":"Point"}
}