{
  "type": "Feature",
  "properties": {
    "iso:country":"US",
    "sg:address":"1408 San Antonio St",
    "sg:city":"Clint",
    "sg:classifiers":[
        {
            "category":"Food & Beverages",
            "subcategory":"Specialty",
            "type":"Retail Goods"
        }
    ],
    "sg:phone":"+1 915 851 3364",
    "sg:postcode":"79849",
    "sg:province":"TX",
    "sg:tags":[
        "herb"
    ],
    "wof:name":"Amparan Carolina",
    "wof:placetype":"venue"
},
  "geometry": {"coordinates":[-106.272237,31.588222],"type":"Point"}
}