{
  "type": "Feature",
  "properties": {
    "iso:country":"US",
    "sg:address":"1966 S Main St",
    "sg:city":"Weatherford",
    "sg:classifiers":[
        {
            "category":"Shopping",
            "subcategory":"Clothing, Apparel, & Fashions",
            "type":"Retail Goods"
        }
    ],
    "sg:phone":"+1 817 594 9777",
    "sg:postcode":"76086",
    "sg:province":"TX",
    "wof:name":"Eye Candy Boutique",
    "wof:placetype":"venue"
},
  "geometry": {"coordinates":[-97.793789,32.733855],"type":"Point"}
}