{
  "type": "Feature",
  "properties": {
    "iso:country":"US",
    "sg:address":"4472 Spring Valley Rd",
    "sg:city":"Dallas",
    "sg:classifiers":[
        {
            "category":"Professional",
            "subcategory":"Accounting & Tax Preparation",
            "type":"Services"
        }
    ],
    "sg:phone":"+1 972 233 0045",
    "sg:postcode":"75244",
    "sg:province":"TX",
    "sg:tags":[
        "accountant"
    ],
    "wof:name":"Signal Microsystems",
    "wof:placetype":"venue"
},
  "geometry": {"coordinates":[-96.830952,32.939436],"type":"Point"}
}