{
  "type": "Feature",
  "properties": {
    "iso:country":"US",
    "sg:address":"212 Valley Ln",
    "sg:city":"Kennedale",
    "sg:classifiers":[
        {
            "category":"Building & Trades",
            "subcategory":"Construction",
            "type":"Services"
        }
    ],
    "sg:phone":"+1 817 478 8962",
    "sg:postcode":"76060",
    "sg:province":"TX",
    "sg:tags":[
        "maker",
        "cabinet"
    ],
    "wof:name":"Cruz Cabinet Shop",
    "wof:placetype":"venue"
},
  "geometry": {"coordinates":[-97.23806500000001,32.654748],"type":"Point"}
}