{
  "type": "Feature",
  "properties": {
    "iso:country":"US",
    "sg:address":"3702 S Alameda St",
    "sg:city":"Corpus Christi",
    "sg:classifiers":[
        {
            "category":"Health Services",
            "subcategory":"Doctor",
            "type":"Services"
        }
    ],
    "sg:phone":"+1 361 561 0635",
    "sg:postcode":"78411",
    "sg:province":"TX",
    "sg:tags":[
        "physician",
        "surgeon"
    ],
    "wof:name":"Corpus Christi MRI Ctr",
    "wof:placetype":"venue"
},
  "geometry": {"coordinates":[-97.38225300000001,27.745426],"type":"Point"}
}