{
  "type": "Feature",
  "properties": {
    "iso:country":"US",
    "sg:address":"5605 Mccarty Ln",
    "sg:city":"Austin",
    "sg:classifiers":[
        {
            "category":"Real Estate",
            "subcategory":"Architect",
            "type":"Services"
        }
    ],
    "sg:phone":"+1 512 758 5564",
    "sg:postcode":"78749",
    "sg:province":"TX",
    "sg:tags":[
        "architects'",
        "specification",
        "construction",
        "builders'",
        "architectural"
    ],
    "wof:name":"Trb Architecture",
    "wof:placetype":"venue"
},
  "geometry": {"coordinates":[-97.855408,30.230844],"type":"Point"}
}