{
  "type": "Feature",
  "properties": {
    "iso:country":"US",
    "sg:address":"2111 W Braker Ln Ste 200",
    "sg:city":"Austin",
    "sg:classifiers":[
        {
            "category":"Professional",
            "subcategory":"Engineering",
            "type":"Services"
        },
        {
            "category":"Professional",
            "subcategory":"Computer Services",
            "type":"Services"
        }
    ],
    "sg:phone":"+1 512 417 0645",
    "sg:postcode":"78758",
    "sg:province":"TX",
    "sg:tags":[
        "engineer",
        "consultant",
        "designer",
        "system",
        "integration"
    ],
    "wof:name":"Computer Enhancement Professionals",
    "wof:placetype":"venue"
},
  "geometry": {"coordinates":[-97.710932,30.393061],"type":"Point"}
}