{
  "type": "Feature",
  "properties": {
    "iso:country":"US",
    "sg:address":"2201 Shea St",
    "sg:city":"Brenham",
    "sg:classifiers":[
        {
            "category":"Manufacturing",
            "subcategory":"Signs",
            "type":"Manufacturing & Wholesale Goods"
        }
    ],
    "sg:phone":"+1 979 277 9237",
    "sg:postcode":"77833",
    "sg:province":"TX",
    "sg:tags":[
        "specialty",
        "mfg"
    ],
    "wof:name":"Dollar Signs LLC",
    "wof:placetype":"venue"
},
  "geometry": {"coordinates":[-96.381558,30.150415],"type":"Point"}
}