{
  "type": "Feature",
  "properties": {
    "iso:country":"US",
    "sg:address":"4471 Wildcat Rd",
    "sg:city":"Aubrey",
    "sg:classifiers":[
        {
            "category":"Building & Trades",
            "subcategory":"Construction",
            "type":"Services"
        }
    ],
    "sg:phone":"+1 940 440 4100",
    "sg:postcode":"76227",
    "sg:province":"TX",
    "sg:tags":[
        "contractor",
        "general",
        "nonresidential"
    ],
    "wof:name":"Tricon Construction Inc",
    "wof:placetype":"venue"
},
  "geometry": {"coordinates":[-97.026976,33.284121],"type":"Point"}
}