{
  "type": "Feature",
  "properties": {
    "iso:country":"US",
    "sg:address":"9223 State Hwy 225",
    "sg:city":"La Porte",
    "sg:classifiers":[
        {
            "category":"Building & Trades",
            "subcategory":"Construction",
            "type":"Services"
        }
    ],
    "sg:phone":"+1 281 930 8135",
    "sg:postcode":"77571",
    "sg:province":"TX",
    "sg:tags":[
        "frozen",
        "food",
        "warehouse"
    ],
    "wof:name":"NOCS West Gulf Inc",
    "wof:placetype":"venue"
},
  "geometry": {"coordinates":[-95.076793,29.699655],"type":"Point"}
}