{
  "type": "Feature",
  "properties": {
    "iso:country":"US",
    "sg:address":"140 Fallbrook Dr",
    "sg:city":"Houston",
    "sg:classifiers":[
        {
            "category":"Wholesale",
            "subcategory":"Toys & Hobbies",
            "type":"Manufacturing & Wholesale Goods"
        }
    ],
    "sg:phone":"+1 281 447 2300",
    "sg:postcode":"77038",
    "sg:province":"TX",
    "sg:tags":[
        "wholesaler"
    ],
    "wof:name":"Gulf Wholesale 2",
    "wof:placetype":"venue"
},
  "geometry": {"coordinates":[-95.41434099999999,29.931701],"type":"Point"}
}