{
  "type": "Feature",
  "properties": {
    "iso:country":"US",
    "sg:address":"1904 W 3rd St",
    "sg:city":"Odessa",
    "sg:classifiers":[
        {
            "category":"Manufacturing",
            "subcategory":"Tools & Machinery",
            "type":"Manufacturing & Wholesale Goods"
        }
    ],
    "sg:phone":"+1 432 337 4737",
    "sg:postcode":"79763",
    "sg:province":"TX",
    "sg:tags":[
        "filter"
    ],
    "wof:name":"Hatfield &Co",
    "wof:placetype":"venue"
},
  "geometry": {"coordinates":[-102.387862,31.836563],"type":"Point"}
}