{
  "type": "Feature",
  "properties": {
    "iso:country":"US",
    "sg:address":"601 Mary Dr",
    "sg:city":"Hurst",
    "sg:classifiers":[
        {
            "category":"Recreation",
            "type":"Entertainment"
        }
    ],
    "sg:phone":"+1 817 282 2752",
    "sg:postcode":"76053",
    "sg:province":"TX",
    "wof:name":"Central Park Swimming Pool",
    "wof:placetype":"venue"
},
  "geometry": {"coordinates":[-97.17589099999999,32.820847],"type":"Point"}
}