{
  "type": "Feature",
  "properties": {
    "iso:country":"US",
    "sg:address":"8338 W 42nd St",
    "sg:city":"Odessa",
    "sg:classifiers":[
        {
            "category":"Wholesale",
            "subcategory":"Scrap",
            "type":"Manufacturing & Wholesale Goods"
        }
    ],
    "sg:phone":"+1 432 530 0640",
    "sg:postcode":"79764",
    "sg:province":"TX",
    "sg:tags":[
        "automotive",
        "wrecking"
    ],
    "wof:name":"Mullins Car Crushing",
    "wof:placetype":"venue"
},
  "geometry": {"coordinates":[-102.477039,31.861627],"type":"Point"}
}