{
  "type": "Feature",
  "properties": {
    "iso:country":"US",
    "sg:address":"4312 Miramar Dr",
    "sg:city":"Georgetown",
    "sg:classifiers":[
        {
            "category":"Professional",
            "subcategory":"Business Services",
            "type":"Services"
        }
    ],
    "sg:phone":"+1 512 863 8178",
    "sg:postcode":"78628",
    "sg:province":"TX",
    "wof:name":"5w Enterprises Inc",
    "wof:placetype":"venue"
},
  "geometry": {"coordinates":[-97.71194,30.682256],"type":"Point"}
}