{
  "type": "Feature",
  "properties": {
    "iso:country":"US",
    "sg:address":"106 Lakewood Trl",
    "sg:city":"Leander",
    "sg:classifiers":[
        {
            "category":"Travel",
            "subcategory":"Travel Agent",
            "type":"Entertainment"
        }
    ],
    "sg:phone":"+1 512 259 7911",
    "sg:postcode":"78641",
    "sg:province":"TX",
    "sg:tags":[
        "agency"
    ],
    "wof:name":"Hahn Blue Sky Travel",
    "wof:placetype":"venue"
},
  "geometry": {"coordinates":[-97.80869,30.543613],"type":"Point"}
}