{
  "type": "Feature",
  "properties": {
    "iso:country":"US",
    "sg:address":"121 Prairie Ave",
    "sg:city":"Cleburne",
    "sg:classifiers":[
        {
            "category":"Personal",
            "subcategory":"Beauty Salon",
            "type":"Services"
        }
    ],
    "sg:phone":"+1 817 556 2044",
    "sg:postcode":"76033",
    "sg:province":"TX",
    "wof:name":"Salon Refinery",
    "wof:placetype":"venue"
},
  "geometry": {"coordinates":[-97.39259800000001,32.344809],"type":"Point"}
}