{
  "type": "Feature",
  "properties": {
    "iso:country":"US",
    "sg:address":"209 S San Marcus St",
    "sg:city":"Whitney",
    "sg:classifiers":[
        {
            "category":"Organizations",
            "subcategory":"Religious Organization",
            "type":"Services"
        }
    ],
    "sg:phone":"+1 254 694 2555",
    "sg:postcode":"76692",
    "sg:province":"TX",
    "wof:name":"First Baptist Church",
    "wof:placetype":"venue"
},
  "geometry": {"coordinates":[-97.323319,31.948366],"type":"Point"}
}