{
  "type": "Feature",
  "properties": {
    "iso:country":"US",
    "sg:address":"144 W 3rd St",
    "sg:city":"Hereford",
    "sg:classifiers":[
        {
            "category":"Professional",
            "type":"Services"
        }
    ],
    "sg:phone":"+1 806 364 8836",
    "sg:postcode":"79045",
    "sg:province":"TX",
    "sg:tags":[
        "establishment"
    ],
    "wof:name":"Anipro",
    "wof:placetype":"venue"
},
  "geometry": {"coordinates":[-102.399725,34.816531],"type":"Point"}
}