{
  "type": "Feature",
  "properties": {
    "iso:country":"US",
    "sg:address":"6420 Buena Vista Dr",
    "sg:city":"Granbury",
    "sg:classifiers":[
        {
            "category":"Shopping",
            "subcategory":"Bicycles & Sporting Goods",
            "type":"Retail Goods"
        }
    ],
    "sg:phone":"+1 817 579 0650",
    "sg:postcode":"76049",
    "sg:province":"TX",
    "wof:name":"Glenn Rey Sport Guns",
    "wof:placetype":"venue"
},
  "geometry": {"coordinates":[-97.681726,32.350622],"type":"Point"}
}