{
  "type": "Feature",
  "properties": {
    "iso:country":"US",
    "sg:address":"1510 N Hampton Rd",
    "sg:city":"Dallas",
    "sg:classifiers":[
        {
            "category":"Real Estate",
            "subcategory":"Real Estate Agent",
            "type":"Services"
        }
    ],
    "sg:phone":"+1 972 298 8941",
    "sg:postcode":"75208",
    "sg:province":"TX",
    "wof:name":"Henry S Miller",
    "wof:placetype":"venue"
},
  "geometry": {"coordinates":[-96.856433,32.765694],"type":"Point"}
}