{
  "type": "Feature",
  "properties": {
    "iso:country":"US",
    "sg:address":"801 Camelot Ct",
    "sg:city":"Lewisville",
    "sg:classifiers":[
        {
            "category":"Manufacturing",
            "subcategory":"Wood Products",
            "type":"Manufacturing & Wholesale Goods"
        }
    ],
    "sg:phone":"+1 972 317 9927",
    "sg:postcode":"75077",
    "sg:province":"TX",
    "sg:tags":[
        "mfg"
    ],
    "wof:name":"Sisters Sensations",
    "wof:placetype":"venue"
},
  "geometry": {"coordinates":[-97.08203899999999,33.092869],"type":"Point"}
}