{
  "type": "Feature",
  "properties": {
    "iso:country":"US",
    "sg:address":"7003 Leslie",
    "sg:city":"San Antonio",
    "sg:classifiers":[
        {
            "category":"Manufacturing",
            "subcategory":"Glass & Minerals",
            "type":"Manufacturing & Wholesale Goods"
        }
    ],
    "sg:phone":"+1 210 688 3311",
    "sg:postcode":"78254",
    "sg:province":"TX",
    "sg:tags":[
        "ready",
        "concrete",
        "product",
        "mfg"
    ],
    "wof:name":"Alamo Concrete Products L",
    "wof:placetype":"venue"
},
  "geometry": {"coordinates":[-98.704095,29.497002],"type":"Point"}
}