{
  "type": "Feature",
  "properties": {
    "iso:country":"US",
    "sg:address":"602 S Raguet St",
    "sg:city":"Lufkin",
    "sg:classifiers":[
        {
            "category":"Banks & Credit Unions",
            "subcategory":"Investment Brokerage",
            "type":"Services"
        }
    ],
    "sg:phone":"+1 936 639 3067",
    "sg:postcode":"75904",
    "sg:province":"TX",
    "sg:tags":[
        "advisory",
        "business"
    ],
    "wof:name":"Veritrust Financial",
    "wof:placetype":"venue"
},
  "geometry": {"coordinates":[-94.731875,31.332731],"type":"Point"}
}