{
  "type": "Feature",
  "properties": {
    "iso:country":"US",
    "sg:address":"14633 Waterview Cir",
    "sg:city":"Addison",
    "sg:classifiers":[
        {
            "category":"Wholesale",
            "subcategory":"Chemicals & Plastics",
            "type":"Manufacturing & Wholesale Goods"
        }
    ],
    "sg:phone":"+1 972 481 1438",
    "sg:postcode":"75001",
    "sg:province":"TX",
    "wof:name":"Nalco Diversitify Technol",
    "wof:placetype":"venue"
},
  "geometry": {"coordinates":[-96.848102,32.944799],"type":"Point"}
}