{
  "type": "Feature",
  "properties": {
    "iso:country":"US",
    "sg:address":"216 Northcrest Dr",
    "sg:city":"San Antonio",
    "sg:classifiers":[
        {
            "category":"Banks & Credit Unions",
            "subcategory":"Bank",
            "type":"Services"
        }
    ],
    "sg:phone":"+1 210 270 2940",
    "sg:postcode":"78213",
    "sg:province":"TX",
    "sg:tags":[
        "loan"
    ],
    "wof:name":"American Finance",
    "wof:placetype":"venue"
},
  "geometry": {"coordinates":[-98.50701599999999,29.524576],"type":"Point"}
}