{
  "type": "Feature",
  "properties": {
    "iso:country":"US",
    "sg:address":"4414 82nd St",
    "sg:city":"Lubbock",
    "sg:classifiers":[
        {
            "category":"Shopping",
            "subcategory":"Jewelry",
            "type":"Retail Goods"
        }
    ],
    "sg:phone":"+1 806 799 8572",
    "sg:postcode":"79424",
    "sg:province":"TX",
    "sg:tags":[
        "jeweler"
    ],
    "wof:name":"Misschif",
    "wof:placetype":"venue"
},
  "geometry": {"coordinates":[-101.90535,33.519824],"type":"Point"}
}