{
  "type": "Feature",
  "properties": {
    "iso:country":"US",
    "sg:address":"3354 Mansfield Hwy",
    "sg:city":"Fort Worth",
    "sg:classifiers":[
        {
            "category":"Restaurant",
            "type":"Food & Drink"
        }
    ],
    "sg:phone":"+1 817 531 9600",
    "sg:postcode":"76119",
    "sg:province":"TX",
    "wof:name":"Glady's Soul Food",
    "wof:placetype":"venue"
},
  "geometry": {"coordinates":[-97.276067,32.681276],"type":"Point"}
}