{
  "type": "Feature",
  "properties": {
    "iso:country":"US",
    "sg:address":"4151 Belt Line Rd",
    "sg:city":"Addison",
    "sg:classifiers":[
        {
            "category":"Shopping",
            "subcategory":"Computers & Home Electronics",
            "type":"Retail Goods"
        }
    ],
    "sg:phone":"+1 972 934 1740",
    "sg:postcode":"75001",
    "sg:province":"TX",
    "sg:tags":[
        "system"
    ],
    "wof:name":"Av-Dallas",
    "wof:placetype":"venue"
},
  "geometry": {"coordinates":[-96.838967,32.954265],"type":"Point"}
}