{
  "type": "Feature",
  "properties": {
    "iso:country":"US",
    "sg:address":"1621 E Missouri Ave",
    "sg:city":"Dallas",
    "sg:classifiers":[
        {
            "category":"Building & Trades",
            "subcategory":"Landscaping Services",
            "type":"Services"
        }
    ],
    "sg:phone":"+1 214 374 1031",
    "sg:postcode":"75216",
    "sg:province":"TX",
    "wof:name":"Landscaping & Hauling",
    "wof:placetype":"venue"
},
  "geometry": {"coordinates":[-96.798552,32.718796],"type":"Point"}
}