{
  "type": "Feature",
  "properties": {
    "iso:country":"US",
    "sg:address":"2 Marella Dr",
    "sg:city":"San Antonio",
    "sg:classifiers":[
        {
            "category":"Professional",
            "subcategory":"Management & Consulting",
            "type":"Services"
        }
    ],
    "sg:phone":"+1 210 479 4121",
    "sg:postcode":"78248",
    "sg:province":"TX",
    "sg:tags":[
        "consultant",
        "training"
    ],
    "wof:name":"Itec International Trainers",
    "wof:placetype":"venue"
},
  "geometry": {"coordinates":[-98.533615,29.585742],"type":"Point"}
}