{
  "type": "Feature",
  "properties": {
    "iso:country":"US",
    "sg:address":"1721 W Morton St",
    "sg:city":"Denison",
    "sg:classifiers":[
        {
            "category":"Sports & Exercise",
            "subcategory":"Tennis Court",
            "type":"Entertainment"
        }
    ],
    "sg:phone":"+1 903 327 8300",
    "sg:postcode":"75020",
    "sg:province":"TX",
    "wof:name":"Big Daddy's",
    "wof:placetype":"venue"
},
  "geometry": {"coordinates":[-96.560158,33.760331],"type":"Point"}
}