{
  "type": "Feature",
  "properties": {
    "iso:country":"US",
    "sg:address":"1601 E Saint Elmo Road",
    "sg:city":"Austin",
    "sg:classifiers":[
        {
            "category":"Autos & Motor Vehicles",
            "subcategory":"Fuel & Gas Station",
            "type":"Retail Goods"
        }
    ],
    "sg:phone":"+1 512 441 8832",
    "sg:postcode":"78744",
    "sg:province":"TX",
    "wof:name":"Triple S Petroleum",
    "wof:placetype":"venue"
},
  "geometry": {"coordinates":[-97.743994,30.209497],"type":"Point"}
}