{
  "type": "Feature",
  "properties": {
    "iso:country":"US",
    "sg:address":"3936 Centenary Ave",
    "sg:city":"Dallas",
    "sg:classifiers":[
        {
            "category":"Shopping",
            "subcategory":"Gifts & Souvenirs",
            "type":"Retail Goods"
        }
    ],
    "sg:phone":"+1 214 528 9962",
    "sg:postcode":"75225",
    "sg:province":"TX",
    "wof:name":"Lott Card Co",
    "wof:placetype":"venue"
},
  "geometry": {"coordinates":[-96.800725,32.862419],"type":"Point"}
}