{
  "type": "Feature",
  "properties": {
    "iso:country":"US",
    "sg:address":"459 Big Hawg Dr",
    "sg:city":"Trinity",
    "sg:classifiers":[
        {
            "category":"Manufacturing",
            "subcategory":"Buildings",
            "type":"Manufacturing & Wholesale Goods"
        },
        {
            "category":"Building & Trades",
            "subcategory":"Construction",
            "type":"Services"
        }
    ],
    "sg:phone":"+1 936 200 4156",
    "sg:postcode":"75862",
    "sg:province":"TX",
    "sg:tags":[
        "home",
        "builder",
        "contractor"
    ],
    "wof:name":"Troy Clark Construction",
    "wof:placetype":"venue"
},
  "geometry": {"coordinates":[-95.20196,30.848422],"type":"Point"}
}