{
  "type": "Feature",
  "properties": {
    "iso:country":"US",
    "sg:address":"1216 Texas Ave",
    "sg:city":"Lubbock",
    "sg:classifiers":[
        {
            "category":"Real Estate",
            "subcategory":"Real Estate Services",
            "type":"Services"
        }
    ],
    "sg:phone":"+1 806 763 0431",
    "sg:postcode":"79401",
    "sg:province":"TX",
    "sg:tags":[
        "abstract",
        "company"
    ],
    "wof:name":"Lubbock Abstract & Title Co",
    "wof:placetype":"venue"
},
  "geometry": {"coordinates":[-101.84571099999999,33.58369],"type":"Point"}
}