{
  "type": "Feature",
  "properties": {
    "iso:country":"US",
    "sg:address":"9611 Maidenstone Dr",
    "sg:city":"San Antonio",
    "sg:classifiers":[
        {
            "category":"Professional",
            "type":"Services"
        }
    ],
    "sg:phone":"+1 210 509 1752",
    "sg:postcode":"78250",
    "sg:province":"TX",
    "wof:name":"Al Affordable Svc",
    "wof:placetype":"venue"
},
  "geometry": {"coordinates":[-98.67613900000001,29.504515],"type":"Point"}
}