{
  "type": "Feature",
  "properties": {
    "iso:country":"US",
    "sg:address":"28240 Ruby Way",
    "sg:city":"Huffman",
    "sg:classifiers":[
        {
            "category":"Farming",
            "subcategory":"Nursery",
            "type":"Manufacturing & Wholesale Goods"
        }
    ],
    "sg:phone":"+1 281 324 4447",
    "sg:postcode":"77336",
    "sg:province":"TX",
    "sg:tags":[
        "ornamental"
    ],
    "wof:name":"Jimco Diversified Enterpr",
    "wof:placetype":"venue"
},
  "geometry": {"coordinates":[-95.136634,30.061239],"type":"Point"}
}