{
  "type": "Feature",
  "properties": {
    "iso:country":"US",
    "sg:address":"800 E State Hwy 29",
    "sg:city":"Georgetown",
    "sg:classifiers":[
        {
            "category":"Manufacturing",
            "subcategory":"Furniture",
            "type":"Manufacturing & Wholesale Goods"
        }
    ],
    "sg:phone":"+1 512 863 2304",
    "sg:postcode":"78626",
    "sg:province":"TX",
    "sg:tags":[
        "household",
        "wood",
        "mfg"
    ],
    "wof:name":"Jonah Woodcrafters",
    "wof:placetype":"venue"
},
  "geometry": {"coordinates":[-97.52285999999999,30.636608],"type":"Point"}
}