{
  "type": "Feature",
  "properties": {
    "iso:country":"US",
    "sg:address":"157 Joleen St",
    "sg:city":"San Marcos",
    "sg:classifiers":[
        {
            "category":"Organizations",
            "subcategory":"Religious Organization",
            "type":"Services"
        }
    ],
    "sg:phone":"+1 512 754 9360",
    "sg:postcode":"78666",
    "sg:province":"TX",
    "sg:tags":[
        "church"
    ],
    "wof:name":"Church Of Christ Jesus",
    "wof:placetype":"venue"
},
  "geometry": {"coordinates":[-97.909036,29.81661],"type":"Point"}
}