{
  "type": "Feature",
  "properties": {
    "iso:country":"US",
    "sg:address":"14910 Aldine Westfield Rd",
    "sg:city":"Houston",
    "sg:classifiers":[
        {
            "category":"Education",
            "subcategory":"School",
            "type":"Public Place"
        }
    ],
    "sg:phone":"+1 281 449 1011",
    "sg:postcode":"77032",
    "sg:province":"TX",
    "wof:name":"Aldine ISD",
    "wof:placetype":"venue"
},
  "geometry": {"coordinates":[-95.356178,29.932736],"type":"Point"}
}