{
  "type": "Feature",
  "properties": {
    "iso:country":"US",
    "sg:address":"1509 McDowell Bend",
    "sg:city":"Leander",
    "sg:classifiers":[
        {
            "category":"Shopping",
            "subcategory":"Pharmacy",
            "type":"Retail Goods"
        }
    ],
    "sg:phone":"+1 512 528 0820",
    "sg:postcode":"78641",
    "sg:province":"TX",
    "wof:name":"Rx Lone Star Pharmacy Solution",
    "wof:placetype":"venue"
},
  "geometry": {"coordinates":[-97.820408,30.548292],"type":"Point"}
}