{
  "type": "Feature",
  "properties": {
    "iso:country":"US",
    "sg:address":"724 International Blvd",
    "sg:city":"Houston",
    "sg:classifiers":[
        {
            "category":"Autos & Motor Vehicles",
            "subcategory":"Automobile Sales",
            "type":"Retail Goods"
        }
    ],
    "sg:phone":"+1 713 681 5466",
    "sg:postcode":"77024",
    "sg:province":"TX",
    "sg:tags":[
        "limo"
    ],
    "wof:name":"Aztex Limo",
    "wof:placetype":"venue"
},
  "geometry": {"coordinates":[-95.47743199999999,29.78008],"type":"Point"}
}