{
  "type": "Feature",
  "properties": {
    "iso:country":"US",
    "sg:address":"4025 Mapleshade Ln",
    "sg:city":"Plano",
    "sg:classifiers":[
        {
            "category":"Restaurant",
            "type":"Food & Drink"
        }
    ],
    "sg:menulink":"http://www.allmenus.com/tx/plano/204330-sonic/menu/",
    "sg:phone":"+1 972 519 0332",
    "sg:postcode":"75075",
    "sg:province":"TX",
    "sg:tags":[
        "burger",
        "american"
    ],
    "wof:name":"Sonic",
    "wof:placetype":"venue"
},
  "geometry": {"coordinates":[-96.769396,33.003195],"type":"Point"}
}