{
  "type": "Feature",
  "properties": {
    "iso:country":"US",
    "sg:address":"24622 Brill Ln",
    "sg:city":"Tomball",
    "sg:classifiers":[
        {
            "category":"Restaurant",
            "type":"Food & Drink"
        }
    ],
    "sg:phone":"+1 281 351 6844",
    "sg:postcode":"77375",
    "sg:province":"TX",
    "sg:tags":[
        "eating"
    ],
    "wof:name":"Cha Cha Shop",
    "wof:placetype":"venue"
},
  "geometry": {"coordinates":[-95.58669500000001,30.121639],"type":"Point"}
}