{
  "type": "Feature",
  "properties": {
    "iso:country":"US",
    "sg:address":"25226 Brewer Dr",
    "sg:city":"San Antonio",
    "sg:classifiers":[
        {
            "category":"Building & Trades",
            "subcategory":"Landscaping Services",
            "type":"Services"
        }
    ],
    "sg:phone":"+1 210 698 6601",
    "sg:postcode":"78257",
    "sg:province":"TX",
    "sg:tags":[
        "lawn",
        "maintenance",
        "grounds"
    ],
    "wof:name":"C & A Grounds Svc",
    "wof:placetype":"venue"
},
  "geometry": {"coordinates":[-98.62702400000001,29.676398],"type":"Point"}
}