{
  "type": "Feature",
  "properties": {
    "iso:country":"US",
    "sg:address":"440 E Houston St",
    "sg:city":"Jasper",
    "sg:classifiers":[
        {
            "category":"Personal",
            "type":"Services"
        }
    ],
    "sg:phone":"+1 409 384 2510",
    "sg:postcode":"75951",
    "sg:province":"TX",
    "wof:name":"Total Eclipse Airbrush Tans",
    "wof:placetype":"venue"
},
  "geometry": {"coordinates":[-93.99637,30.920849],"type":"Point"}
}