{
  "type": "Feature",
  "properties": {
    "iso:country":"US",
    "sg:address":"916 S Valley Mills Dr",
    "sg:city":"Waco",
    "sg:classifiers":[
        {
            "category":"Shopping",
            "subcategory":"Used Merchandise",
            "type":"Retail Goods"
        }
    ],
    "sg:phone":"+1 254 754 1484",
    "sg:postcode":"76711",
    "sg:province":"TX",
    "wof:name":"EZ Pawn 236",
    "wof:placetype":"venue"
},
  "geometry": {"coordinates":[-97.14885700000001,31.526116],"type":"Point"}
}