{
  "type": "Feature",
  "properties": {
    "iso:country":"US",
    "sg:address":"212 W Cook Ave",
    "sg:city":"Pampa",
    "sg:classifiers":[
        {
            "category":"Education",
            "subcategory":"School",
            "type":"Public Place"
        }
    ],
    "sg:phone":"+1 806 669 4750",
    "sg:postcode":"79065",
    "sg:province":"TX",
    "wof:name":"Pampa Learning Center",
    "wof:placetype":"venue"
},
  "geometry": {"coordinates":[-100.967367,35.543137],"type":"Point"}
}