{
  "type": "Feature",
  "properties": {
    "iso:country":"US",
    "sg:address":"8031 Airport Blvd",
    "sg:city":"Houston",
    "sg:classifiers":[
        {
            "category":"Wholesale",
            "subcategory":"Machinery & Supplies",
            "type":"Manufacturing & Wholesale Goods"
        }
    ],
    "sg:phone":"+1 713 640 2353",
    "sg:postcode":"77061",
    "sg:province":"TX",
    "sg:tags":[
        "equipment",
        "consulting",
        "management",
        "transportation"
    ],
    "wof:name":"Priority 1 Aviation Inc",
    "wof:placetype":"venue"
},
  "geometry": {"coordinates":[-95.27230900000001,29.65798],"type":"Point"}
}