{
  "type": "Feature",
  "properties": {
    "iso:country":"US",
    "sg:address":"16615 North Fwy",
    "sg:city":"Houston",
    "sg:classifiers":[
        {
            "category":"Real Estate",
            "subcategory":"Real Estate Agent",
            "type":"Services"
        }
    ],
    "sg:phone":"+1 281 444 7267",
    "sg:postcode":"77090",
    "sg:province":"TX",
    "wof:name":"R H Nagy & Company",
    "wof:placetype":"venue"
},
  "geometry": {"coordinates":[-95.42869,30.016913],"type":"Point"}
}