{
  "type": "Feature",
  "properties": {
    "iso:country":"US",
    "sg:address":"110 Laburnum Dr",
    "sg:city":"San Antonio",
    "sg:classifiers":[
        {
            "category":"Professional",
            "subcategory":"Lawyer & Legal Services",
            "type":"Services"
        }
    ],
    "sg:phone":"+1 210 822 7251",
    "sg:postcode":"78209",
    "sg:province":"TX",
    "sg:tags":[
        "attorney"
    ],
    "wof:name":"Harold F Duncan Jr",
    "wof:placetype":"venue"
},
  "geometry": {"coordinates":[-98.455896,29.513276],"type":"Point"}
}