{
  "type": "Feature",
  "properties": {
    "iso:country":"US",
    "sg:address":"109 N Mesa St",
    "sg:city":"El Paso",
    "sg:classifiers":[
        {
            "category":"Shopping",
            "type":"Retail Goods"
        }
    ],
    "sg:phone":"+1 915 351 9598",
    "sg:postcode":"79901",
    "sg:province":"TX",
    "sg:tags":[
        "art",
        "gallery",
        "dealer"
    ],
    "wof:name":"Art Studio",
    "wof:placetype":"venue"
},
  "geometry": {"coordinates":[-106.487188,31.758746],"type":"Point"}
}