{
  "type": "Feature",
  "properties": {
    "iso:country":"US",
    "sg:address":"4407 122nd St",
    "sg:city":"Lubbock",
    "sg:classifiers":[
        {
            "category":"Building & Trades",
            "subcategory":"Plumbing",
            "type":"Services"
        }
    ],
    "sg:phone":"+1 806 794 8977",
    "sg:postcode":"79424",
    "sg:province":"TX",
    "sg:tags":[
        "plumber",
        "industrial",
        "contractors-commercial"
    ],
    "wof:name":"Young Plumbing",
    "wof:placetype":"venue"
},
  "geometry": {"coordinates":[-101.905005,33.483391],"type":"Point"}
}