{
  "type": "Feature",
  "properties": {
    "iso:country":"US",
    "sg:address":"1929 E Boling Hwy",
    "sg:city":"Wharton",
    "sg:classifiers":[
        {
            "category":"Professional",
            "subcategory":"Engineering",
            "type":"Services"
        },
        {
            "category":"Building & Trades",
            "subcategory":"Construction",
            "type":"Services"
        }
    ],
    "sg:phone":"+1 979 532 8150",
    "sg:postcode":"77488",
    "sg:province":"TX",
    "sg:tags":[
        "system",
        "specialty",
        "heating",
        "equipment",
        "contractor",
        "air conditioning"
    ],
    "wof:name":"Eldridge Air Conditioning & Heating",
    "wof:placetype":"venue"
},
  "geometry": {"coordinates":[-96.071595,29.319508],"type":"Point"}
}