{
  "type": "Feature",
  "properties": {
    "iso:country":"US",
    "sg:address":"37 Watermill Pl",
    "sg:city":"Sugar Land",
    "sg:classifiers":[
        {
            "category":"Retail",
            "subcategory":"Self-service Laundry",
            "type":"Services"
        }
    ],
    "sg:phone":"+1 281 491 1074",
    "sg:postcode":"77479",
    "sg:province":"TX",
    "sg:tags":[
        "coin"
    ],
    "wof:name":"Autonation Washateria Ltd",
    "wof:placetype":"venue"
},
  "geometry": {"coordinates":[-95.66906,29.600979],"type":"Point"}
}