{
  "type": "Feature",
  "properties": {
    "iso:country":"US",
    "sg:address":"1717 State Hwy 1604",
    "sg:city":"San Antonio",
    "sg:classifiers":[
        {
            "category":"Professional",
            "subcategory":"Management & Consulting",
            "type":"Services"
        }
    ],
    "sg:phone":"+1 210 495 6161",
    "sg:postcode":"78232",
    "sg:province":"TX",
    "sg:tags":[
        "consultant",
        "educational"
    ],
    "wof:name":"American Council For Constr Ed",
    "wof:placetype":"venue"
},
  "geometry": {"coordinates":[-98.468092,29.609261],"type":"Point"}
}