{
  "type": "Feature",
  "properties": {
    "iso:country":"US",
    "sg:address":"408 County Road 116",
    "sg:city":"Comanche",
    "sg:classifiers":[
        {
            "category":"Farming",
            "subcategory":"Livestock Farm",
            "type":"Manufacturing & Wholesale Goods"
        }
    ],
    "sg:phone":"+1 254 842 5648",
    "sg:postcode":"76442",
    "sg:province":"TX",
    "sg:tags":[
        "ranch"
    ],
    "wof:name":"Campana Cattle Company",
    "wof:placetype":"venue"
},
  "geometry": {"coordinates":[-98.706818,32.033961],"type":"Point"}
}