{
  "type": "Feature",
  "properties": {
    "iso:country":"US",
    "sg:address":"1545 Goodyear Dr",
    "sg:city":"El Paso",
    "sg:classifiers":[
        {
            "category":"Wholesale",
            "subcategory":"Construction Materials",
            "type":"Manufacturing & Wholesale Goods"
        }
    ],
    "sg:phone":"+1 915 858 1991",
    "sg:postcode":"79936",
    "sg:province":"TX",
    "sg:tags":[
        "kitchen",
        "cabinet"
    ],
    "wof:name":"A-1 Kitchens By Sierra",
    "wof:placetype":"venue"
},
  "geometry": {"coordinates":[-106.31200200000001,31.743544],"type":"Point"}
}