{
  "type": "Feature",
  "properties": {
    "iso:country":"US",
    "sg:address":"10456 Brian Mooney Ave",
    "sg:city":"El Paso",
    "sg:classifiers":[
        {
            "category":"Professional",
            "subcategory":"Research",
            "type":"Services"
        }
    ],
    "sg:phone":"+1 915 591 4777",
    "sg:postcode":"79935",
    "sg:province":"TX",
    "sg:tags":[
        "nonphysical",
        "commercial"
    ],
    "wof:name":"AIM Research",
    "wof:placetype":"venue"
},
  "geometry": {"coordinates":[-106.337722,31.771131],"type":"Point"}
}