{
  "type": "Feature",
  "properties": {
    "iso:country":"US",
    "sg:address":"1722 Mildred St",
    "sg:city":"Kingsville",
    "sg:classifiers":[
        {
            "category":"Insurance",
            "subcategory":"Life Insurance",
            "type":"Services"
        }
    ],
    "sg:phone":"+1 361 592 0476",
    "sg:postcode":"78363",
    "sg:province":"TX",
    "sg:tags":[
        "carrier"
    ],
    "wof:name":"A W A",
    "wof:placetype":"venue"
},
  "geometry": {"coordinates":[-97.845386,27.507299],"type":"Point"}
}