{
  "type": "Feature",
  "properties": {
    "iso:country":"US",
    "sg:address":"15115 FM 1488",
    "sg:city":"Magnolia",
    "sg:classifiers":[
        {
            "category":"Freight",
            "type":"Transportation"
        }
    ],
    "sg:phone":"+1 281 290 7500",
    "sg:postcode":"77354",
    "sg:province":"TX",
    "sg:tags":[
        "general"
    ],
    "wof:name":"AAA Allsafe Mini Storage",
    "wof:placetype":"venue"
},
  "geometry": {"coordinates":[-95.704748,30.228512],"type":"Point"}
}