{
  "type": "Feature",
  "properties": {
    "iso:country":"US",
    "sg:address":"7934 White Blvd",
    "sg:city":"Abilene",
    "sg:classifiers":[
        {
            "category":"Recreation",
            "type":"Entertainment"
        }
    ],
    "sg:phone":"+1 325 692 6255",
    "sg:postcode":"79606",
    "sg:province":"TX",
    "sg:tags":[
        "club",
        "membership"
    ],
    "wof:name":"West Central Texas Skiers",
    "wof:placetype":"venue"
},
  "geometry": {"coordinates":[-99.774613,32.353722],"type":"Point"}
}