{
  "type": "Feature",
  "properties": {
    "iso:country":"US",
    "sg:address":"505 Deep Eddy Ave",
    "sg:city":"Austin",
    "sg:classifiers":[
        {
            "category":"Building & Trades",
            "subcategory":"Pest Control",
            "type":"Services"
        }
    ],
    "sg:phone":"+1 512 538 0410",
    "sg:postcode":"78703",
    "sg:province":"TX",
    "wof:name":"Outsmart Holdings",
    "wof:placetype":"venue"
},
  "geometry": {"coordinates":[-97.77233200000001,30.277996],"type":"Point"}
}