{
  "type": "Feature",
  "properties": {
    "iso:country":"US",
    "sg:address":"9015 Meadow Vista Blvd",
    "sg:city":"Houston",
    "sg:classifiers":[
        {
            "category":"Retail",
            "subcategory":"Auto Repair",
            "type":"Services"
        }
    ],
    "sg:phone":"+1 281 469 7875",
    "sg:postcode":"77064",
    "sg:province":"TX",
    "sg:tags":[
        "general"
    ],
    "wof:name":"Roberts Complete Auto Repair",
    "wof:placetype":"venue"
},
  "geometry": {"coordinates":[-95.555578,29.948101],"type":"Point"}
}