{
  "type": "Feature",
  "properties": {
    "iso:country":"US",
    "sg:address":"1901 Legacy Dr",
    "sg:city":"Plano",
    "sg:classifiers":[
        {
            "category":"Utilities",
            "subcategory":"Telephone",
            "type":"Services"
        }
    ],
    "sg:phone":"+1 972 527 5815",
    "sg:postcode":"75023",
    "sg:province":"TX",
    "sg:tags":[
        "distance",
        "long"
    ],
    "wof:name":"A T & T",
    "wof:placetype":"venue"
},
  "geometry": {"coordinates":[-96.73021799999999,33.07156],"type":"Point"}
}