{
  "type": "Feature",
  "properties": {
    "iso:country":"US",
    "sg:address":"2922 E Cesar Chavez St",
    "sg:city":"Austin",
    "sg:classifiers":[
        {
            "category":"Retail",
            "subcategory":"Auto Repair",
            "type":"Services"
        }
    ],
    "sg:phone":"+1 512 385 8039",
    "sg:postcode":"78702",
    "sg:province":"TX",
    "sg:tags":[
        "automotive"
    ],
    "wof:name":"Capital Electric Rebuilders",
    "wof:placetype":"venue"
},
  "geometry": {"coordinates":[-97.71097399999999,30.252464],"type":"Point"}
}