{
  "type": "Feature",
  "properties": {
    "iso:country":"US",
    "sg:address":"811 W John Ave",
    "sg:city":"Orange",
    "sg:classifiers":[
        {
            "category":"Personal",
            "subcategory":"Beauty Salon",
            "type":"Services"
        },
        {
            "category":"Shopping",
            "subcategory":"Clothing, Apparel, & Fashions",
            "type":"Retail Goods"
        }
    ],
    "sg:phone":"+1 409 883 7288",
    "sg:postcode":"77630",
    "sg:province":"TX",
    "sg:tags":[
        "shop"
    ],
    "wof:name":"A & G Fashions Inc",
    "wof:placetype":"venue"
},
  "geometry": {"coordinates":[-93.73693299999999,30.10063],"type":"Point"}
}