{
  "type": "Feature",
  "properties": {
    "iso:country":"US",
    "sg:address":"1701 Avenue N",
    "sg:city":"Cisco",
    "sg:classifiers":[
        {
            "category":"Organizations",
            "subcategory":"Religious Organization",
            "type":"Services"
        }
    ],
    "sg:phone":"+1 254 442 1450",
    "sg:postcode":"76437",
    "sg:province":"TX",
    "sg:tags":[
        "church"
    ],
    "wof:name":"Church Of Christ",
    "wof:placetype":"venue"
},
  "geometry": {"coordinates":[-98.98494700000001,32.375754],"type":"Point"}
}