{
  "type": "Feature",
  "properties": {
    "iso:country":"US",
    "sg:address":"8604 Coastal Dr",
    "sg:city":"Austin",
    "sg:classifiers":[
        {
            "category":"Social Services",
            "subcategory":"Job Training",
            "type":"Services"
        }
    ],
    "sg:phone":"+1 512 280 8405",
    "sg:postcode":"78749",
    "sg:province":"TX",
    "wof:name":"Virgilhealth",
    "wof:placetype":"venue"
},
  "geometry": {"coordinates":[-97.847914,30.198965],"type":"Point"}
}