{
  "type": "Feature",
  "properties": {
    "iso:country":"US",
    "sg:address":"1771 Upland Dr",
    "sg:city":"Houston",
    "sg:classifiers":[
        {
            "category":"Real Estate",
            "subcategory":"Real Estate Operator",
            "type":"Services"
        }
    ],
    "sg:phone":"+1 713 984 0199",
    "sg:postcode":"77043",
    "sg:province":"TX",
    "sg:tags":[
        "owner",
        "property",
        "commercial"
    ],
    "wof:name":"E T S Properties Inc",
    "wof:placetype":"venue"
},
  "geometry": {"coordinates":[-95.57668200000001,29.793402],"type":"Point"}
}