{
  "type": "Feature",
  "properties": {
    "iso:country":"US",
    "sg:address":"3034 Villa Sur Trl",
    "sg:city":"Dallas",
    "sg:classifiers":[
        {
            "category":"Professional",
            "subcategory":"Computer Services",
            "type":"Services"
        }
    ],
    "sg:phone":"+1 214 553 8923",
    "sg:postcode":"75228",
    "sg:province":"TX",
    "sg:tags":[
        "related"
    ],
    "wof:name":"J P Designs",
    "wof:placetype":"venue"
},
  "geometry": {"coordinates":[-96.66108,32.854711],"type":"Point"}
}