{
  "type": "Feature",
  "properties": {
    "iso:country":"US",
    "sg:address":"411 Texas Ave S",
    "sg:city":"College Station",
    "sg:classifiers":[
        {
            "category":"Real Estate",
            "subcategory":"Real Estate Agent",
            "type":"Services"
        }
    ],
    "sg:phone":"+1 979 846 8400",
    "sg:postcode":"77840",
    "sg:province":"TX",
    "wof:name":"Sandion  Ltd",
    "wof:placetype":"venue"
},
  "geometry": {"coordinates":[-96.33538299999999,30.628395],"type":"Point"}
}