{
  "type": "Feature",
  "properties": {
    "iso:country":"US",
    "sg:address":"1025 N Texas Blvd",
    "sg:city":"Weslaco",
    "sg:classifiers":[
        {
            "category":"Banks & Credit Unions",
            "subcategory":"Bank",
            "type":"Services"
        }
    ],
    "sg:phone":"+1 956 447 9813",
    "sg:postcode":"78596",
    "sg:province":"TX",
    "sg:tags":[
        "financing"
    ],
    "wof:name":"Regional Finance Corp",
    "wof:placetype":"venue"
},
  "geometry": {"coordinates":[-97.991043,26.172417],"type":"Point"}
}