{
  "type": "Feature",
  "properties": {
    "iso:country":"US",
    "sg:address":"1011 W 5th St Ste 110",
    "sg:city":"Austin",
    "sg:classifiers":[
        {
            "category":"Sports & Exercise",
            "subcategory":"Bicycle Rental",
            "type":"Entertainment"
        }
    ],
    "sg:phone":"+1 512 474 0022",
    "sg:postcode":"78701",
    "sg:province":"TX",
    "sg:tags":[
        "wear"
    ],
    "sg:website":"www.therunningcompany.net/austin...",
    "wof:name":"Texas Running Company",
    "wof:placetype":"venue"
},
  "geometry": {"coordinates":[-97.754751,30.270331],"type":"Point"}
}