{
  "type": "Feature",
  "properties": {
    "iso:country":"US",
    "sg:address":"4408 Pleasantview Dr",
    "sg:city":"Arlington",
    "sg:classifiers":[
        {
            "category":"Professional",
            "type":"Services"
        }
    ],
    "sg:phone":"+1 817 478 0483",
    "sg:postcode":"76017",
    "sg:province":"TX",
    "wof:name":"The Sroc",
    "wof:placetype":"venue"
},
  "geometry": {"coordinates":[-97.173457,32.672878],"type":"Point"}
}