{
  "type": "Feature",
  "properties": {
    "iso:country":"US",
    "sg:address":"8605 Devine Ln",
    "sg:city":"Austin",
    "sg:classifiers":[
        {
            "category":"Wholesale",
            "subcategory":"Books, Periodicals, & Newspapers",
            "type":"Manufacturing & Wholesale Goods"
        }
    ],
    "sg:phone":"+1 512 292 0890",
    "sg:postcode":"78748",
    "sg:province":"TX",
    "wof:name":"Drastic Mag",
    "wof:placetype":"venue"
},
  "geometry": {"coordinates":[-97.811379,30.183538],"type":"Point"}
}