{
  "type": "Feature",
  "properties": {
    "iso:country":"US",
    "sg:address":"4323 W Pipeline Rd",
    "sg:city":"Euless",
    "sg:classifiers":[
        {
            "category":"Organizations",
            "subcategory":"Religious Organization",
            "type":"Services"
        }
    ],
    "sg:phone":"+1 817 590 8185",
    "sg:postcode":"76040",
    "sg:province":"TX",
    "sg:tags":[
        "church"
    ],
    "wof:name":"Early Church",
    "wof:placetype":"venue"
},
  "geometry": {"coordinates":[-97.15500400000001,32.823218],"type":"Point"}
}