{
  "type": "Feature",
  "properties": {
    "iso:country":"US",
    "sg:address":"806 E Houston St",
    "sg:city":"Beeville",
    "sg:classifiers":[
        {
            "category":"Cinema",
            "subcategory":"Movie Theater",
            "type":"Entertainment"
        }
    ],
    "sg:phone":"+1 361 358 9373",
    "sg:postcode":"78102",
    "sg:province":"TX",
    "wof:name":"Rio 6 Cinema",
    "wof:placetype":"venue"
},
  "geometry": {"coordinates":[-97.738559,28.405198],"type":"Point"}
}