{
  "type": "Feature",
  "properties": {
    "iso:country":"US",
    "sg:address":"913 Glen Rose Dr",
    "sg:city":"Allen",
    "sg:classifiers":[
        {
            "category":"Shopping",
            "subcategory":"Computers & Home Electronics",
            "type":"Retail Goods"
        }
    ],
    "sg:phone":"+1 972 396 8424",
    "sg:postcode":"75013",
    "sg:province":"TX",
    "sg:tags":[
        "software"
    ],
    "sg:website":"www.sharedcontent.com",
    "wof:name":"Satori Associates Inc",
    "wof:placetype":"venue"
},
  "geometry": {"coordinates":[-96.709221,33.110734],"type":"Point"}
}