{
  "type": "Feature",
  "properties": {
    "iso:country":"US",
    "sg:address":"1300 Baker St",
    "sg:city":"Houston",
    "sg:classifiers":[
        {
            "category":"Manufacturing",
            "subcategory":"Metals",
            "type":"Manufacturing & Wholesale Goods"
        }
    ],
    "sg:phone":"+1 713 225 0555",
    "sg:postcode":"77002",
    "sg:province":"TX",
    "sg:tags":[
        "fabrication",
        "structural"
    ],
    "wof:name":"Texas Cold Finished Steel",
    "wof:placetype":"venue"
},
  "geometry": {"coordinates":[-95.35432,29.763375],"type":"Point"}
}