{
  "type": "Feature",
  "properties": {
    "iso:country":"US",
    "sg:address":"1411 Alpha Ln",
    "sg:city":"Crosby",
    "sg:classifiers":[
        {
            "category":"Building & Trades",
            "subcategory":"Construction",
            "type":"Services"
        }
    ],
    "sg:phone":"+1 281 328 8447",
    "sg:postcode":"77532",
    "sg:province":"TX",
    "sg:tags":[
        "residential"
    ],
    "wof:name":"Quiksilver Construction",
    "wof:placetype":"venue"
},
  "geometry": {"coordinates":[-95.046965,29.913783],"type":"Point"}
}