{
  "type": "Feature",
  "properties": {
    "iso:country":"US",
    "sg:address":"2613 Brennan Ct",
    "sg:city":"Plano",
    "sg:classifiers":[
        {
            "category":"Manufacturing",
            "subcategory":"Tools & Machinery",
            "type":"Manufacturing & Wholesale Goods"
        }
    ],
    "sg:phone":"+1 972 596 7378",
    "sg:postcode":"75075",
    "sg:province":"TX",
    "sg:tags":[
        "computer",
        "electronic",
        "mfg"
    ],
    "wof:name":"Tiger Mapping Llc",
    "wof:placetype":"venue"
},
  "geometry": {"coordinates":[-96.743765,33.024186],"type":"Point"}
}