{
  "type": "Feature",
  "properties": {
    "iso:country":"US",
    "sg:address":"125 E Kerria Ave",
    "sg:city":"Mcallen",
    "sg:classifiers":[
        {
            "category":"Health Services",
            "subcategory":"Doctor",
            "type":"Services"
        }
    ],
    "sg:phone":"+1 956 686 4824",
    "sg:postcode":"78501",
    "sg:province":"TX",
    "sg:tags":[
        "clinic",
        "medical"
    ],
    "wof:name":"Valley Allergy & Asthma Center",
    "wof:placetype":"venue"
},
  "geometry": {"coordinates":[-98.21275199999999,26.235301],"type":"Point"}
}