{
  "type": "Feature",
  "properties": {
    "iso:country":"US",
    "sg:address":"2327 57th St",
    "sg:city":"Lubbock",
    "sg:classifiers":[
        {
            "category":"Building & Trades",
            "subcategory":"Cleaning & Sanitation",
            "type":"Services"
        }
    ],
    "sg:phone":"+1 806 792 7155",
    "sg:postcode":"79412",
    "sg:province":"TX",
    "sg:tags":[
        "ventilating",
        "system"
    ],
    "wof:name":"A & A Chimney Sweeps",
    "wof:placetype":"venue"
},
  "geometry": {"coordinates":[-101.869782,33.542332],"type":"Point"}
}