{
  "type": "Feature",
  "properties": {
    "iso:country":"US",
    "sg:address":"3505 Forest Ln",
    "sg:city":"Garland",
    "sg:classifiers":[
        {
            "category":"Retail",
            "subcategory":"Auto Repair",
            "type":"Services"
        },
        {
            "category":"Wholesale",
            "subcategory":"Auto Parts",
            "type":"Manufacturing & Wholesale Goods"
        }
    ],
    "sg:phone":"+1 972 494 3948",
    "sg:postcode":"75042",
    "sg:province":"TX",
    "sg:tags":[
        "body",
        "automobile",
        "painting"
    ],
    "sg:website":"www.lpcollision.com",
    "wof:name":"L & P Collision Repair",
    "wof:placetype":"venue"
},
  "geometry": {"coordinates":[-96.68682699999999,32.909169],"type":"Point"}
}