{
  "type": "Feature",
  "properties": {
    "iso:country":"US",
    "sg:address":"2011 W Spring Creek Pkwy",
    "sg:city":"Plano",
    "sg:classifiers":[
        {
            "category":"Personal",
            "subcategory":"Beauty Salon",
            "type":"Services"
        }
    ],
    "sg:phone":"+1 972 527 2151",
    "sg:postcode":"75023",
    "sg:province":"TX",
    "sg:tags":[
        "shop",
        "manicuring"
    ],
    "wof:name":"Only Nails",
    "wof:placetype":"venue"
},
  "geometry": {"coordinates":[-96.73141099999999,33.058912],"type":"Point"}
}