{
  "type": "Feature",
  "properties": {
    "iso:country":"US",
    "sg:address":"10914 C F Hawn Fwy",
    "sg:city":"Dallas",
    "sg:classifiers":[
        {
            "category":"Recreation",
            "subcategory":"Picnic Area",
            "type":"Entertainment"
        }
    ],
    "sg:phone":"+1 972 286 3015",
    "sg:postcode":"75217",
    "sg:province":"TX",
    "sg:tags":[
        "place",
        "arcade",
        "amusement"
    ],
    "wof:name":"Sidewinders",
    "wof:placetype":"venue"
},
  "geometry": {"coordinates":[-96.638706,32.694283],"type":"Point"}
}