{
  "type": "Feature",
  "properties": {
    "iso:country":"US",
    "sg:address":"102 Regency Ct",
    "sg:city":"Harlingen",
    "sg:classifiers":[
        {
            "category":"Shopping",
            "subcategory":"Pets & Pet Supplies",
            "type":"Retail Goods"
        }
    ],
    "sg:phone":"+1 956 425 6658",
    "sg:postcode":"78550",
    "sg:province":"TX",
    "sg:tags":[
        "food"
    ],
    "wof:name":"Yippy Yappy Gourmet Barkery",
    "wof:placetype":"venue"
},
  "geometry": {"coordinates":[-97.695679,26.2216],"type":"Point"}
}