{
  "type": "Feature",
  "properties": {
    "iso:country":"US",
    "sg:address":"3613 Glacier Ln",
    "sg:city":"Garland",
    "sg:classifiers":[
        {
            "category":"Professional",
            "subcategory":"Engineering",
            "type":"Services"
        }
    ],
    "sg:phone":"+1 972 276 2001",
    "sg:postcode":"75042",
    "sg:province":"TX",
    "wof:name":"Stanley E Prichard Jr",
    "wof:placetype":"venue"
},
  "geometry": {"coordinates":[-96.68561200000001,32.910821],"type":"Point"}
}