{
  "type": "Feature",
  "properties": {
    "iso:country":"US",
    "sg:address":"2225 Madison Dr",
    "sg:city":"Arlington",
    "sg:classifiers":[
        {
            "category":"Professional",
            "type":"Services"
        }
    ],
    "sg:phone":"+1 817 548 9353",
    "sg:postcode":"76011",
    "sg:province":"TX",
    "sg:tags":[
        "establishment"
    ],
    "wof:name":"Homeowners Associations",
    "wof:placetype":"venue"
},
  "geometry": {"coordinates":[-97.098615,32.770555],"type":"Point"}
}