{
  "type": "Feature",
  "properties": {
    "iso:country":"US",
    "sg:address":"450 Goforth Rd",
    "sg:city":"Fort Worth",
    "sg:classifiers":[
        {
            "category":"Farming",
            "subcategory":"Livestock Farm",
            "type":"Manufacturing & Wholesale Goods"
        }
    ],
    "sg:phone":"+1 817 443 3900",
    "sg:postcode":"76126",
    "sg:province":"TX",
    "sg:tags":[
        "equine"
    ],
    "wof:name":"Jose Escapite",
    "wof:placetype":"venue"
},
  "geometry": {"coordinates":[-97.57376499999999,32.590104],"type":"Point"}
}