{
  "type": "Feature",
  "properties": {
    "iso:country":"US",
    "sg:address":"2008 Carriage Ln",
    "sg:city":"Brenham",
    "sg:classifiers":[
        {
            "category":"Building & Trades",
            "subcategory":"Construction",
            "type":"Services"
        }
    ],
    "sg:phone":"+1 979 836 3634",
    "sg:postcode":"77833",
    "sg:province":"TX",
    "sg:tags":[
        "carpentry",
        "contractor"
    ],
    "wof:name":"Faske Woodworks",
    "wof:placetype":"venue"
},
  "geometry": {"coordinates":[-96.392528,30.149649],"type":"Point"}
}