{
  "type": "Feature",
  "properties": {
    "iso:country":"US",
    "sg:address":"3307 Bedford Forrest Ct",
    "sg:city":"Missouri City",
    "sg:classifiers":[
        {
            "category":"Building & Trades",
            "subcategory":"Construction",
            "type":"Services"
        }
    ],
    "sg:phone":"+1 281 437 4516",
    "sg:postcode":"77459",
    "sg:province":"TX",
    "sg:tags":[
        "carpentry",
        "contractor"
    ],
    "wof:name":"Wood Essence Inc",
    "wof:placetype":"venue"
},
  "geometry": {"coordinates":[-95.509032,29.542112],"type":"Point"}
}