{
  "type": "Feature",
  "properties": {
    "iso:country":"US",
    "sg:address":"3201 Premier Dr",
    "sg:city":"Irving",
    "sg:classifiers":[
        {
            "category":"Professional",
            "subcategory":"Advertising",
            "type":"Services"
        }
    ],
    "sg:phone":"+1 972 751 1500",
    "sg:postcode":"75063",
    "sg:province":"TX",
    "sg:tags":[
        "marketing",
        "printing"
    ],
    "wof:name":"Quixotic Dgital Mktg Solutions",
    "wof:placetype":"venue"
},
  "geometry": {"coordinates":[-96.98642,32.897364],"type":"Point"}
}