{
  "type": "Feature",
  "properties": {
    "iso:country":"US",
    "sg:address":"1101 W Hwy 199",
    "sg:city":"Springtown",
    "sg:classifiers":[
        {
            "category":"Retail",
            "subcategory":"Repair Shop",
            "type":"Services"
        }
    ],
    "sg:phone":"+1 817 220 1190",
    "sg:postcode":"76082",
    "sg:province":"TX",
    "sg:tags":[
        "welding"
    ],
    "wof:name":"Overland Welding Svc",
    "wof:placetype":"venue"
},
  "geometry": {"coordinates":[-97.70414700000001,32.968275],"type":"Point"}
}