{
  "type": "Feature",
  "properties": {
    "iso:country":"US",
    "sg:address":"705 State Hwy 323 SE",
    "sg:city":"Tyler",
    "sg:classifiers":[
        {
            "category":"Home & Garden",
            "subcategory":"Building Materials",
            "type":"Retail Goods"
        }
    ],
    "sg:phone":"+1 903 526 0507",
    "sg:postcode":"75702",
    "sg:province":"TX",
    "sg:tags":[
        "lumber"
    ],
    "wof:name":"Cassity Jones Lumber",
    "wof:placetype":"venue"
},
  "geometry": {"coordinates":[-95.267296,32.341863],"type":"Point"}
}