{
  "type": "Feature",
  "properties": {
    "iso:country":"US",
    "sg:address":"3211 Appleby Sand Rd",
    "sg:city":"Nacogdoches",
    "sg:classifiers":[
        {
            "category":"Personal",
            "subcategory":"Barber",
            "type":"Services"
        }
    ],
    "sg:phone":"+1 936 560 3200",
    "sg:postcode":"75965",
    "sg:province":"TX",
    "sg:tags":[
        "shop"
    ],
    "wof:name":"Tiffany Rae Umphenour",
    "wof:placetype":"venue"
},
  "geometry": {"coordinates":[-94.62984899999999,31.631673],"type":"Point"}
}