{
  "type": "Feature",
  "properties": {
    "iso:country":"US",
    "sg:address":"1076 E Los Ebanos Blvd",
    "sg:city":"Brownsville",
    "sg:classifiers":[
        {
            "category":"Health Services",
            "subcategory":"Doctor",
            "type":"Services"
        }
    ],
    "sg:phone":"+1 956 544 2001",
    "sg:postcode":"78520",
    "sg:province":"TX",
    "sg:tags":[
        "medical"
    ],
    "wof:name":"Womens Health Care Group",
    "wof:placetype":"venue"
},
  "geometry": {"coordinates":[-97.506153,25.932138],"type":"Point"}
}