{
  "type": "Feature",
  "properties": {
    "iso:country":"US",
    "sg:address":"1545 E Southlake Blvd",
    "sg:city":"Southlake",
    "sg:classifiers":[
        {
            "category":"Health Services",
            "subcategory":"Doctor",
            "type":"Services"
        }
    ],
    "sg:phone":"+1 817 749 0655",
    "sg:postcode":"76092",
    "sg:province":"TX",
    "sg:tags":[
        "physician",
        "surgeon"
    ],
    "wof:name":"Breast Center Of North Texas",
    "wof:placetype":"venue"
},
  "geometry": {"coordinates":[-97.126296,32.940906],"type":"Point"}
}