{
  "type": "Feature",
  "properties": {
    "iso:country":"US",
    "sg:address":"4834 W Commerce St",
    "sg:city":"San Antonio",
    "sg:classifiers":[
        {
            "category":"Bars & Pubs",
            "type":"Food & Drink"
        }
    ],
    "sg:phone":"+1 210 436 5170",
    "sg:postcode":"78237",
    "sg:province":"TX",
    "wof:name":"LA Frontera",
    "wof:placetype":"venue"
},
  "geometry": {"coordinates":[-98.556844,29.430944],"type":"Point"}
}