{
  "type": "Feature",
  "properties": {
    "iso:country":"US",
    "sg:address":"11625 Columbia Center Dr",
    "sg:city":"Dallas",
    "sg:classifiers":[
        {
            "category":"Professional",
            "subcategory":"Business Services",
            "type":"Services"
        }
    ],
    "sg:phone":"+1 972 406 1444",
    "sg:postcode":"75229",
    "sg:province":"TX",
    "sg:tags":[
        "record"
    ],
    "wof:name":"Advanced Data Analysis Prsrvtn",
    "wof:placetype":"venue"
},
  "geometry": {"coordinates":[-96.90460299999999,32.905986],"type":"Point"}
}