{
  "type": "Feature",
  "properties": {
    "iso:country":"US",
    "sg:address":"2417 Loving Ave",
    "sg:city":"Dallas",
    "sg:classifiers":[
        {
            "category":"Manufacturing",
            "subcategory":"Tools & Machinery",
            "type":"Manufacturing & Wholesale Goods"
        }
    ],
    "sg:phone":"+1 214 324 2600",
    "sg:postcode":"75214",
    "sg:province":"TX",
    "sg:tags":[
        "industrial",
        "mfg"
    ],
    "wof:name":"Zivco Mfg Inc",
    "wof:placetype":"venue"
},
  "geometry": {"coordinates":[-96.73326400000001,32.815719],"type":"Point"}
}