{
  "type": "Feature",
  "properties": {
    "iso:country":"US",
    "sg:address":"909 S Poplar St",
    "sg:city":"Kermit",
    "sg:classifiers":[
        {
            "category":"Restaurant",
            "type":"Food & Drink"
        }
    ],
    "sg:phone":"+1 432 586 6119",
    "sg:postcode":"79745",
    "sg:province":"TX",
    "sg:tags":[
        "mexican"
    ],
    "wof:name":"La Cabana Restaurant",
    "wof:placetype":"venue"
},
  "geometry": {"coordinates":[-103.087141,31.848925],"type":"Point"}
}