{
  "type": "Feature",
  "properties": {
    "iso:country":"US",
    "sg:address":"807 Gateshead Ct",
    "sg:city":"Southlake",
    "sg:classifiers":[
        {
            "category":"Manufacturing",
            "subcategory":"Retail Goods",
            "type":"Manufacturing & Wholesale Goods"
        }
    ],
    "sg:phone":"+1 817 442 5522",
    "sg:postcode":"76092",
    "sg:province":"TX",
    "sg:tags":[
        "product",
        "mfg"
    ],
    "wof:name":"Texas Best Nix Wix",
    "wof:placetype":"venue"
},
  "geometry": {"coordinates":[-97.139428,32.94186],"type":"Point"}
}