{
  "type": "Feature",
  "properties": {
    "iso:country":"US",
    "sg:address":"1605 Barclay Dr",
    "sg:city":"Austin",
    "sg:classifiers":[
        {
            "category":"Professional",
            "subcategory":"Management & Consulting",
            "type":"Services"
        }
    ],
    "sg:phone":"+1 512 347 0503",
    "sg:postcode":"78746",
    "sg:province":"TX",
    "wof:name":"Cahill & Associates",
    "wof:placetype":"venue"
},
  "geometry": {"coordinates":[-97.824749,30.276855],"type":"Point"}
}