{
  "type": "Feature",
  "properties": {
    "iso:country":"US",
    "sg:address":"2880 Galilee Rd",
    "sg:city":"Hallsville",
    "sg:classifiers":[
        {
            "category":"Freight",
            "type":"Transportation"
        }
    ],
    "sg:phone":"+1 903 668 5402",
    "sg:postcode":"75650",
    "sg:province":"TX",
    "sg:tags":[
        "hauling",
        "trucking"
    ],
    "wof:name":"Laird John Trucking",
    "wof:placetype":"venue"
},
  "geometry": {"coordinates":[-94.544259,32.470891],"type":"Point"}
}