{
  "type": "Feature",
  "properties": {
    "iso:country":"US",
    "sg:address":"726 Beechbend Dr",
    "sg:city":"Missouri City",
    "sg:classifiers":[
        {
            "category":"Health Services",
            "subcategory":"Nursing And Care Facility",
            "type":"Services"
        }
    ],
    "sg:phone":"+1 281 499 2273",
    "sg:postcode":"77489",
    "sg:province":"TX",
    "sg:tags":[
        "home",
        "retirement",
        "community"
    ],
    "wof:name":"Martha Care Ctr III",
    "wof:placetype":"venue"
},
  "geometry": {"coordinates":[-95.512033,29.596603],"type":"Point"}
}