{
  "type": "Feature",
  "properties": {
    "iso:country":"US",
    "sg:address":"1605 Forest Trl",
    "sg:city":"Temple",
    "sg:classifiers":[
        {
            "category":"Health Services",
            "subcategory":"Doctor",
            "type":"Services"
        }
    ],
    "sg:phone":"+1 254 778 3751",
    "sg:postcode":"76502",
    "sg:province":"TX",
    "wof:name":"Forest Trail Dental Care",
    "wof:placetype":"venue"
},
  "geometry": {"coordinates":[-97.373693,31.067819],"type":"Point"}
}