{
  "type": "Feature",
  "properties": {
    "iso:country":"US",
    "sg:address":"1776 Yorktown St Ste 600",
    "sg:city":"Houston",
    "sg:classifiers":[
        {
            "category":"Real Estate",
            "subcategory":"Real Estate Services",
            "type":"Services"
        }
    ],
    "sg:phone":"+1 713 523 7111",
    "sg:postcode":"77056",
    "sg:province":"TX",
    "sg:tags":[
        "management",
        "property"
    ],
    "wof:name":"Pmr Companies",
    "wof:placetype":"venue"
},
  "geometry": {"coordinates":[-95.471007,29.747917],"type":"Point"}
}