{
  "type": "Feature",
  "properties": {
    "iso:country":"US",
    "sg:address":"4501 S Co Rd 1310",
    "sg:city":"Odessa",
    "sg:classifiers":[
        {
            "category":"Utilities",
            "subcategory":"Refuse",
            "type":"Services"
        }
    ],
    "sg:phone":"+1 432 561 8998",
    "sg:postcode":"79765",
    "sg:province":"TX",
    "sg:tags":[
        "disposal",
        "waste"
    ],
    "sg:website":"www.piwsinc.com",
    "wof:name":"Positive Impact Waste",
    "wof:placetype":"venue"
},
  "geometry": {"coordinates":[-102.262687,31.89837],"type":"Point"}
}