{
  "type": "Feature",
  "properties": {
    "iso:country":"US",
    "sg:address":"741 Arnold Blvd",
    "sg:city":"Abilene",
    "sg:classifiers":[
        {
            "category":"Retail",
            "subcategory":"Laundry & Dry Cleaning",
            "type":"Services"
        },
        {
            "category":"Shopping",
            "subcategory":"Clothing, Apparel, & Fashions",
            "type":"Retail Goods"
        }
    ],
    "sg:phone":"+1 325 692 4977",
    "sg:postcode":"79605",
    "sg:province":"TX",
    "sg:tags":[
        "alteration"
    ],
    "wof:name":"Sally's Alterations",
    "wof:placetype":"venue"
},
  "geometry": {"coordinates":[-99.808629,32.444088],"type":"Point"}
}