{
  "type": "Feature",
  "properties": {
    "iso:country":"US",
    "sg:address":"4087 Valley Vw",
    "sg:city":"Lone Oak",
    "sg:classifiers":[
        {
            "category":"Restaurant",
            "type":"Food & Drink"
        }
    ],
    "sg:phone":"+1 903 447 3618",
    "sg:postcode":"75453",
    "sg:province":"TX",
    "sg:tags":[
        "eating"
    ],
    "wof:name":"Jordan Health Care",
    "wof:placetype":"venue"
},
  "geometry": {"coordinates":[-95.972228,32.942554],"type":"Point"}
}