{
  "type": "Feature",
  "properties": {
    "iso:country":"US",
    "sg:address":"202 Ellis Dr",
    "sg:city":"Allen",
    "sg:classifiers":[
        {
            "category":"Shopping",
            "subcategory":"Pets & Pet Supplies",
            "type":"Retail Goods"
        }
    ],
    "sg:phone":"+1 972 727 5423",
    "sg:postcode":"75002",
    "sg:province":"TX",
    "sg:tags":[
        "furnishing",
        "dog",
        "store",
        "cat"
    ],
    "wof:name":"Cherish Your Pets",
    "wof:placetype":"venue"
},
  "geometry": {"coordinates":[-96.669518,33.09922],"type":"Point"}
}