{
  "type": "Feature",
  "properties": {
    "iso:country":"US",
    "sg:address":"8460 Gran Vista Dr",
    "sg:city":"El Paso",
    "sg:classifiers":[
        {
            "category":"Autos & Motor Vehicles",
            "subcategory":"Recreational Vehicle Sales",
            "type":"Retail Goods"
        }
    ],
    "sg:phone":"+1 915 545 2720",
    "sg:postcode":"79907",
    "sg:province":"TX",
    "sg:tags":[
        "parts",
        "trailer"
    ],
    "wof:name":"Cequent Trailer Products",
    "wof:placetype":"venue"
},
  "geometry": {"coordinates":[-106.32448100000001,31.735087],"type":"Point"}
}