{
  "type": "Feature",
  "properties": {
    "iso:country":"US",
    "sg:address":"13831 Northwest Fwy",
    "sg:city":"Houston",
    "sg:classifiers":[
        {
            "category":"Wholesale",
            "subcategory":"Non-durable Goods",
            "type":"Manufacturing & Wholesale Goods"
        }
    ],
    "sg:phone":"+1 713 681 7479",
    "sg:postcode":"77040",
    "sg:province":"TX",
    "wof:name":"Cousins Trading Co Ltd",
    "wof:placetype":"venue"
},
  "geometry": {"coordinates":[-95.515281,29.853918],"type":"Point"}
}