{
  "type": "Feature",
  "properties": {
    "iso:country":"US",
    "sg:address":"3327 Deeds Rd",
    "sg:city":"Houston",
    "sg:classifiers":[
        {
            "category":"Professional",
            "subcategory":"Management & Consulting",
            "type":"Services"
        }
    ],
    "sg:phone":"+1 281 647 0672",
    "sg:postcode":"77084",
    "sg:province":"TX",
    "sg:tags":[
        "consultant",
        "educational"
    ],
    "wof:name":"Bill Handlin",
    "wof:placetype":"venue"
},
  "geometry": {"coordinates":[-95.691253,29.816856],"type":"Point"}
}