{
  "type": "Feature",
  "properties": {
    "iso:country":"US",
    "sg:address":"1410 W Grant Ave",
    "sg:city":"Harlingen",
    "sg:classifiers":[
        {
            "category":"Food & Beverages",
            "subcategory":"Groceries & Convenience Stores",
            "type":"Retail Goods"
        },
        {
            "category":"Wholesale",
            "subcategory":"Groceries",
            "type":"Manufacturing & Wholesale Goods"
        }
    ],
    "sg:phone":"+1 956 421 2679",
    "sg:postcode":"78550",
    "sg:province":"TX",
    "sg:tags":[
        "preparation",
        "tortilla",
        "mfg"
    ],
    "wof:name":"Moreno's Tortillas & Grocery",
    "wof:placetype":"venue"
},
  "geometry": {"coordinates":[-97.71002799999999,26.181594],"type":"Point"}
}