{
  "type": "Feature",
  "properties": {
    "iso:country":"US",
    "sg:address":"250 N FM 154",
    "sg:city":"Muldoon",
    "sg:classifiers":[
        {
            "category":"Government",
            "subcategory":"Post Office",
            "type":"Public Place"
        }
    ],
    "sg:phone":"+1 361 865 2660",
    "sg:postcode":"78949",
    "sg:province":"TX",
    "wof:name":"US Post Office",
    "wof:placetype":"venue"
},
  "geometry": {"coordinates":[-97.069383,29.817788],"type":"Point"}
}