{
  "type": "Feature",
  "properties": {
    "iso:country":"US",
    "sg:address":"908 S Main St",
    "sg:city":"Weatherford",
    "sg:classifiers":[
        {
            "category":"Personal",
            "subcategory":"Beauty Salon",
            "type":"Services"
        }
    ],
    "sg:phone":"+1 817 594 1304",
    "sg:postcode":"76086",
    "sg:province":"TX",
    "wof:name":"Reflections Salon",
    "wof:placetype":"venue"
},
  "geometry": {"coordinates":[-97.797562,32.749832],"type":"Point"}
}