{
  "type": "Feature",
  "properties": {
    "iso:country":"US",
    "sg:address":"5002 Oso Pkwy",
    "sg:city":"Corpus Christi",
    "sg:classifiers":[
        {
            "category":"Arena",
            "subcategory":"Sports Club",
            "type":"Entertainment"
        }
    ],
    "sg:phone":"+1 361 991 0499",
    "sg:postcode":"78413",
    "sg:province":"TX",
    "sg:tags":[
        "soccer"
    ],
    "wof:name":"Padre Soccer League",
    "wof:placetype":"venue"
},
  "geometry": {"coordinates":[-97.409156,27.666648],"type":"Point"}
}