{
  "type": "Feature",
  "properties": {
    "iso:country":"US",
    "sg:address":"219 Magnolia St",
    "sg:city":"Channelview",
    "sg:classifiers":[
        {
            "category":"Retail",
            "subcategory":"Repair Shop",
            "type":"Services"
        }
    ],
    "sg:phone":"+1 281 452 1449",
    "sg:postcode":"77530",
    "sg:province":"TX",
    "sg:tags":[
        "refrigeration"
    ],
    "wof:name":"Ballew Air & Heat",
    "wof:placetype":"venue"
},
  "geometry": {"coordinates":[-95.089697,29.79584],"type":"Point"}
}