{
  "type": "Feature",
  "properties": {
    "iso:country":"US",
    "sg:address":"2909 Forest Ln",
    "sg:city":"Dallas",
    "sg:classifiers":[
        {
            "category":"Shopping",
            "subcategory":"Mobile Phones",
            "type":"Retail Goods"
        }
    ],
    "sg:phone":"+1 972 243 7010",
    "sg:postcode":"75234",
    "sg:province":"TX",
    "wof:name":"Sprint",
    "wof:placetype":"venue"
},
  "geometry": {"coordinates":[-96.879806,32.909637],"type":"Point"}
}