{
  "type": "Feature",
  "properties": {
    "iso:country":"US",
    "sg:address":"209 N 17th St",
    "sg:city":"Lamesa",
    "sg:classifiers":[
        {
            "category":"Building & Trades",
            "subcategory":"Construction",
            "type":"Services"
        }
    ],
    "sg:phone":"+1 806 872 5605",
    "sg:postcode":"79331",
    "sg:province":"TX",
    "sg:tags":[
        "carpentry",
        "contractor"
    ],
    "wof:name":"Furlew Construction",
    "wof:placetype":"venue"
},
  "geometry": {"coordinates":[-101.95438,32.748787],"type":"Point"}
}