{
  "type": "Feature",
  "properties": {
    "iso:country":"US",
    "sg:address":"6505 Sudbury Rd",
    "sg:city":"Plano",
    "sg:classifiers":[
        {
            "category":"Professional",
            "type":"Services"
        }
    ],
    "sg:phone":"+1 972 608 4781",
    "sg:postcode":"75024",
    "sg:province":"TX",
    "wof:name":"Doug Gruenberg Inc",
    "wof:placetype":"venue"
},
  "geometry": {"coordinates":[-96.85088,33.065273],"type":"Point"}
}