{
  "type": "Feature",
  "properties": {
    "iso:country":"US",
    "sg:address":"4112 Mangum Rd",
    "sg:city":"Houston",
    "sg:classifiers":[
        {
            "category":"Real Estate",
            "subcategory":"Real Estate Agent",
            "type":"Services"
        }
    ],
    "sg:phone":"+1 713 956 2222",
    "sg:postcode":"77092",
    "sg:province":"TX",
    "wof:name":"All American Properties",
    "wof:placetype":"venue"
},
  "geometry": {"coordinates":[-95.46206599999999,29.828489],"type":"Point"}
}