{
  "type": "Feature",
  "properties": {
    "iso:country":"US",
    "sg:address":"1122 W Dallas St",
    "sg:city":"Conroe",
    "sg:classifiers":[
        {
            "category":"Shopping",
            "subcategory":"Jewelry",
            "type":"Retail Goods"
        }
    ],
    "sg:phone":"+1 936 539 4367",
    "sg:postcode":"77301",
    "sg:province":"TX",
    "wof:name":"Camillos Fine Jewelry Inc",
    "wof:placetype":"venue"
},
  "geometry": {"coordinates":[-95.468842,30.316211],"type":"Point"}
}