{
  "type": "Feature",
  "properties": {
    "iso:country":"US",
    "sg:address":"1502 E Royall Blvd",
    "sg:city":"Malakoff",
    "sg:classifiers":[
        {
            "category":"Manufacturing",
            "subcategory":"Tools & Machinery",
            "type":"Manufacturing & Wholesale Goods"
        }
    ],
    "sg:phone":"+1 903 489 1405",
    "sg:postcode":"75148",
    "sg:province":"TX",
    "sg:tags":[
        "process",
        "control",
        "mfg",
        "instrument"
    ],
    "wof:name":"Tms",
    "wof:placetype":"venue"
},
  "geometry": {"coordinates":[-95.994737,32.174869],"type":"Point"}
}