{
  "type": "Feature",
  "properties": {
    "iso:country":"US",
    "sg:address":"902 Lakewood Dr",
    "sg:city":"Mc Kinney",
    "sg:classifiers":[
        {
            "category":"Real Estate",
            "subcategory":"Real Estate Agent",
            "type":"Services"
        }
    ],
    "sg:phone":"+1 972 529 5286",
    "sg:postcode":"75070",
    "sg:province":"TX",
    "wof:name":"William R Henry & Company",
    "wof:placetype":"venue"
},
  "geometry": {"coordinates":[-96.682531,33.184843],"type":"Point"}
}