{
  "type": "Feature",
  "properties": {
    "iso:country":"US",
    "sg:address":"1208 Pine Tree Rd",
    "sg:city":"Longview",
    "sg:classifiers":[
        {
            "category":"Social Services",
            "subcategory":"Child Care",
            "type":"Services"
        }
    ],
    "sg:phone":"+1 903 759 3085",
    "sg:postcode":"75604",
    "sg:province":"TX",
    "sg:tags":[
        "day"
    ],
    "wof:name":"Jordan Country Day School",
    "wof:placetype":"venue"
},
  "geometry": {"coordinates":[-94.80052499999999,32.518728],"type":"Point"}
}