{
  "type": "Feature",
  "properties": {
    "iso:country":"US",
    "sg:address":"2000 Magnolia Dr",
    "sg:city":"Round Rock",
    "sg:classifiers":[
        {
            "category":"Manufacturing",
            "subcategory":"Electronics",
            "type":"Manufacturing & Wholesale Goods"
        }
    ],
    "sg:phone":"+1 512 918 3709",
    "sg:postcode":"78664",
    "sg:province":"TX",
    "sg:tags":[
        "prerecorded",
        "theatrical",
        "mfg"
    ],
    "wof:name":"Startex Records",
    "wof:placetype":"venue"
},
  "geometry": {"coordinates":[-97.67252000000001,30.493323],"type":"Point"}
}