{
  "type": "Feature",
  "properties": {
    "iso:country":"US",
    "sg:address":"8319 Chelsea Bend Ct",
    "sg:city":"Houston",
    "sg:classifiers":[
        {
            "category":"Shopping",
            "type":"Retail Goods"
        }
    ],
    "sg:phone":"+1 281 277 4118",
    "sg:postcode":"77083",
    "sg:province":"TX",
    "sg:tags":[
        "miscellaneous",
        "store"
    ],
    "wof:name":"New Century Marketing",
    "wof:placetype":"venue"
},
  "geometry": {"coordinates":[-95.679506,29.684754],"type":"Point"}
}