{
  "type": "Feature",
  "properties": {
    "iso:country":"US",
    "sg:address":"10501 FM 720",
    "sg:city":"Frisco",
    "sg:classifiers":[
        {
            "category":"Manufacturing",
            "subcategory":"Electronics",
            "type":"Manufacturing & Wholesale Goods"
        }
    ],
    "sg:phone":"+1 972 335 9841",
    "sg:postcode":"75035",
    "sg:province":"TX",
    "sg:tags":[
        "boards",
        "mfg",
        "component",
        "printed",
        "circuit",
        "electronic"
    ],
    "wof:name":"P C Dynamics of Texas Inc",
    "wof:placetype":"venue"
},
  "geometry": {"coordinates":[-96.78850799999999,33.152794],"type":"Point"}
}