{
  "type": "Feature",
  "properties": {
    "iso:country":"US",
    "sg:address":"11515 Lands Pond",
    "sg:city":"San Antonio",
    "sg:classifiers":[
        {
            "category":"Professional",
            "subcategory":"Management & Consulting",
            "type":"Services"
        }
    ],
    "sg:phone":"+1 210 493 1339",
    "sg:postcode":"78253",
    "sg:province":"TX",
    "sg:tags":[
        "consultant",
        "business"
    ],
    "wof:name":"New Concept Mortgage Svc",
    "wof:placetype":"venue"
},
  "geometry": {"coordinates":[-98.720688,29.438395],"type":"Point"}
}