{
  "type": "Feature",
  "properties": {
    "iso:country":"US",
    "sg:address":"721 E Davis St",
    "sg:city":"Conroe",
    "sg:classifiers":[
        {
            "category":"Banks & Credit Unions",
            "subcategory":"Bank",
            "type":"Services"
        }
    ],
    "sg:phone":"+1 936 756 4494",
    "sg:postcode":"77301",
    "sg:province":"TX",
    "sg:tags":[
        "small",
        "loan",
        "company",
        "licensed"
    ],
    "wof:name":"Security Finance Corp",
    "wof:placetype":"venue"
},
  "geometry": {"coordinates":[-95.44711700000001,30.31468],"type":"Point"}
}