{
  "type": "Feature",
  "properties": {
    "iso:country":"US",
    "sg:address":"2801 Guadalupe St",
    "sg:city":"Corpus Christi",
    "sg:classifiers":[
        {
            "category":"Professional",
            "type":"Services"
        }
    ],
    "sg:phone":"+1 361 876 1669",
    "sg:postcode":"78405",
    "sg:province":"TX",
    "wof:name":"Big Daddy Trucking",
    "wof:placetype":"venue"
},
  "geometry": {"coordinates":[-97.42808100000001,27.768254],"type":"Point"}
}