{
  "type": "Feature",
  "properties": {
    "iso:country":"US",
    "sg:address":"1209 Moore Rd",
    "sg:city":"Stafford",
    "sg:classifiers":[
        {
            "category":"Manufacturing",
            "subcategory":"Tools & Machinery",
            "type":"Manufacturing & Wholesale Goods"
        }
    ],
    "sg:phone":"+1 281 261 4747",
    "sg:postcode":"77477",
    "sg:province":"TX",
    "sg:tags":[
        "equipment",
        "janitor",
        "supply"
    ],
    "sg:website":"www.sunbelt-labs.com",
    "wof:name":"Sunbelt Laboratories",
    "wof:placetype":"venue"
},
  "geometry": {"coordinates":[-95.552249,29.601122],"type":"Point"}
}