{
  "type": "Feature",
  "properties": {
    "iso:country":"US",
    "sg:address":"109 Bonham St",
    "sg:city":"Port Lavaca",
    "sg:classifiers":[
        {
            "category":"Retail",
            "subcategory":"Auto Repair",
            "type":"Services"
        }
    ],
    "sg:phone":"+1 361 552 2730",
    "sg:postcode":"77979",
    "sg:province":"TX",
    "sg:tags":[
        "body"
    ],
    "wof:name":"Body Shop",
    "wof:placetype":"venue"
},
  "geometry": {"coordinates":[-96.629611,28.628328],"type":"Point"}
}