{
  "type": "Feature",
  "properties": {
    "iso:country":"US",
    "sg:address":"7200 Eastex Fwy",
    "sg:city":"Houston",
    "sg:classifiers":[
        {
            "category":"Personal",
            "type":"Services"
        }
    ],
    "sg:phone":"+1 713 695 8119",
    "sg:postcode":"77093",
    "sg:province":"TX",
    "sg:tags":[
        "towing"
    ],
    "wof:name":"Miller & Sons Wrecker Service",
    "wof:placetype":"venue"
},
  "geometry": {"coordinates":[-95.33470199999999,29.827],"type":"Point"}
}