{
  "type": "Feature",
  "properties": {
    "iso:country":"US",
    "sg:address":"2220 Worthington St",
    "sg:city":"Dallas",
    "sg:classifiers":[
        {
            "category":"Building & Trades",
            "subcategory":"Construction",
            "type":"Services"
        }
    ],
    "sg:phone":"+1 214 369 4900",
    "sg:postcode":"75204",
    "sg:province":"TX",
    "sg:tags":[
        "home",
        "builder"
    ],
    "wof:name":"Lexington Luxury Builders",
    "wof:placetype":"venue"
},
  "geometry": {"coordinates":[-96.797952,32.795811],"type":"Point"}
}