{
  "type": "Feature",
  "properties": {
    "iso:country":"US",
    "sg:address":"3757 US Hwy 281",
    "sg:city":"Alice",
    "sg:classifiers":[
        {
            "category":"Mining & Drilling",
            "type":"Manufacturing & Wholesale Goods"
        }
    ],
    "sg:phone":"+1 361 668 8580",
    "sg:postcode":"78332",
    "sg:province":"TX",
    "sg:tags":[
        "field",
        "oil"
    ],
    "wof:name":"Copano Field Svc",
    "wof:placetype":"venue"
},
  "geometry": {"coordinates":[-98.08364,27.822567],"type":"Point"}
}