{
  "type": "Feature",
  "properties": {
    "iso:country":"US",
    "sg:address":"8204 N Lamar Boulevard",
    "sg:city":"Austin",
    "sg:classifiers":[
        {
            "category":"Wholesale",
            "subcategory":"Computers",
            "type":"Manufacturing & Wholesale Goods"
        }
    ],
    "sg:phone":"+1 512 490 6700",
    "sg:postcode":"78753",
    "sg:province":"TX",
    "wof:name":"Nu Image Corporation",
    "wof:placetype":"venue"
},
  "geometry": {"coordinates":[-97.70905,30.351006],"type":"Point"}
}