{
  "type": "Feature",
  "properties": {
    "iso:country":"US",
    "sg:address":"8903 Melfrank Dr",
    "sg:city":"Amarillo",
    "sg:classifiers":[
        {
            "category":"Building & Trades",
            "subcategory":"Landscaping Services",
            "type":"Services"
        }
    ],
    "sg:phone":"+1 806 353 8476",
    "sg:postcode":"79124",
    "sg:province":"TX",
    "sg:tags":[
        "lawn",
        "landscape",
        "contractor"
    ],
    "wof:name":"Barker Landscape",
    "wof:placetype":"venue"
},
  "geometry": {"coordinates":[-101.94531600000001,35.256575],"type":"Point"}
}