{
  "type": "Feature",
  "properties": {
    "iso:country":"US",
    "sg:address":"722 S Polk St",
    "sg:city":"Amarillo",
    "sg:classifiers":[
        {
            "category":"Health Services",
            "subcategory":"Clinic",
            "type":"Services"
        }
    ],
    "sg:phone":"+1 806 353 9907",
    "sg:postcode":"79101",
    "sg:province":"AR",
    "sg:tags":[
        "home",
        "care"
    ],
    "wof:name":"Outreach Health Services",
    "wof:placetype":"venue"
},
  "geometry": {"coordinates":[-101.837384,35.205791],"type":"Point"}
}