{
  "type": "Feature",
  "properties": {
    "iso:country":"US",
    "sg:address":"1228 Monterey Cir",
    "sg:city":"Plano",
    "sg:classifiers":[
        {
            "category":"Professional",
            "subcategory":"Management & Consulting",
            "type":"Services"
        }
    ],
    "sg:phone":"+1 469 569 4485",
    "sg:postcode":"75075",
    "sg:province":"TX",
    "sg:tags":[
        "product",
        "advertising",
        "specialty",
        "promotional"
    ],
    "wof:name":"ADS To Give",
    "wof:placetype":"venue"
},
  "geometry": {"coordinates":[-96.730859,33.016305],"type":"Point"}
}