{
  "type": "Feature",
  "properties": {
    "iso:country":"US",
    "sg:address":"108 S Broadway St",
    "sg:city":"Brownwood",
    "sg:classifiers":[
        {
            "category":"Shopping",
            "subcategory":"Gifts & Souvenirs",
            "type":"Retail Goods"
        }
    ],
    "sg:phone":"+1 325 646 4885",
    "sg:postcode":"76801",
    "sg:province":"TX",
    "sg:tags":[
        "shop"
    ],
    "wof:name":"Miller Christmas Store",
    "wof:placetype":"venue"
},
  "geometry": {"coordinates":[-98.98206500000001,31.722818],"type":"Point"}
}