{
  "type": "Feature",
  "properties": {
    "iso:country":"US",
    "sg:address":"2229 Air Base Rd",
    "sg:city":"Waco",
    "sg:classifiers":[
        {
            "category":"Personal",
            "subcategory":"Beauty Salon",
            "type":"Services"
        }
    ],
    "sg:phone":"+1 254 799 5188",
    "sg:postcode":"76705",
    "sg:province":"TX",
    "sg:tags":[
        "shop"
    ],
    "wof:name":"Tammy's Hair Salon",
    "wof:placetype":"venue"
},
  "geometry": {"coordinates":[-97.094061,31.629389],"type":"Point"}
}