{
  "type": "Feature",
  "properties": {
    "iso:country":"US",
    "sg:address":"1777 Westerham Dr",
    "sg:city":"Dallas",
    "sg:classifiers":[
        {
            "category":"Shopping",
            "subcategory":"Catalog Store",
            "type":"Retail Goods"
        }
    ],
    "sg:phone":"+1 214 331 8669",
    "sg:postcode":"75232",
    "sg:province":"TX",
    "sg:tags":[
        "mail",
        "house"
    ],
    "wof:name":"Always Class",
    "wof:placetype":"venue"
},
  "geometry": {"coordinates":[-96.849507,32.66251],"type":"Point"}
}