{
  "type": "Feature",
  "properties": {
    "iso:country":"US",
    "sg:address":"2470 Jacksboro Hwy",
    "sg:city":"Fort Worth",
    "sg:classifiers":[
        {
            "category":"Health Services",
            "subcategory":"Doctor",
            "type":"Services"
        }
    ],
    "sg:phone":"+1 817 625 2892",
    "sg:postcode":"76114",
    "sg:province":"TX",
    "sg:tags":[
        "clinic"
    ],
    "wof:name":"Planned Parenthood",
    "wof:placetype":"venue"
},
  "geometry": {"coordinates":[-97.38602899999999,32.787764],"type":"Point"}
}