{
  "type": "Feature",
  "properties": {
    "iso:country":"US",
    "sg:address":"525 Canal Rd",
    "sg:city":"El Paso",
    "sg:classifiers":[
        {
            "category":"Freight",
            "type":"Transportation"
        }
    ],
    "sg:phone":"+1 915 541 8697",
    "sg:postcode":"79901",
    "sg:province":"TX",
    "sg:tags":[
        "trucking"
    ],
    "wof:name":"Lee Trucking",
    "wof:placetype":"venue"
},
  "geometry": {"coordinates":[-106.491409,31.751644],"type":"Point"}
}