{
  "type": "Feature",
  "properties": {
    "iso:country":"US",
    "sg:address":"1701 Woodrow Rd",
    "sg:city":"Lubbock",
    "sg:classifiers":[
        {
            "category":"Organizations",
            "subcategory":"Religious Organization",
            "type":"Services"
        }
    ],
    "sg:phone":"+1 806 863 2929",
    "sg:postcode":"79423",
    "sg:province":"TX",
    "sg:tags":[
        "church"
    ],
    "wof:name":"Cooper Church Of Christ",
    "wof:placetype":"venue"
},
  "geometry": {"coordinates":[-101.863001,33.447141],"type":"Point"}
}