{
  "type": "Feature",
  "properties": {
    "iso:country":"US",
    "sg:address":"606 N Ed Carey Dr",
    "sg:city":"Harlingen",
    "sg:classifiers":[
        {
            "category":"Professional",
            "subcategory":"Employment Agencies",
            "type":"Services"
        }
    ],
    "sg:phone":"+1 956 412 1156",
    "sg:postcode":"78550",
    "sg:province":"TX",
    "sg:tags":[
        "supply",
        "help",
        "contractor"
    ],
    "wof:name":"Kelly Services Inc",
    "wof:placetype":"venue"
},
  "geometry": {"coordinates":[-97.663078,26.209229],"type":"Point"}
}