{
  "type": "Feature",
  "properties": {
    "iso:country":"US",
    "sg:address":"169 Fm 517 Rd W",
    "sg:city":"Dickinson",
    "sg:classifiers":[
        {
            "category":"Restaurant",
            "type":"Food & Drink"
        }
    ],
    "sg:menulink":"http://www.allmenus.com/tx/texas-city-league-city/203908-sonic/menu/",
    "sg:phone":"+1 281 614 0886",
    "sg:postcode":"77539",
    "sg:province":"TX",
    "sg:tags":[
        "burger",
        "american"
    ],
    "wof:name":"Sonic",
    "wof:placetype":"venue"
},
  "geometry": {"coordinates":[-95.080375,29.447594],"type":"Point"}
}