{
  "type": "Feature",
  "properties": {
    "iso:country":"US",
    "sg:address":"4265 San Felipe St Ste 1100",
    "sg:city":"Houston",
    "sg:classifiers":[
        {
            "category":"Banks & Credit Unions",
            "subcategory":"Financial Services",
            "type":"Services"
        }
    ],
    "sg:phone":"+1 713 968 9847",
    "sg:postcode":"77027",
    "sg:province":"TX",
    "sg:tags":[
        "broker",
        "mortgage"
    ],
    "wof:name":"Mortgage Focus",
    "wof:placetype":"venue"
},
  "geometry": {"coordinates":[-95.449997,29.746599],"type":"Point"}
}