{
  "type": "Feature",
  "properties": {
    "iso:country":"US",
    "sg:address":"2819 Lakeview Dr",
    "sg:city":"Missouri City",
    "sg:classifiers":[
        {
            "category":"Manufacturing",
            "subcategory":"Tools & Machinery",
            "type":"Manufacturing & Wholesale Goods"
        }
    ],
    "sg:phone":"+1 281 468 4889",
    "sg:postcode":"77459",
    "sg:province":"TX",
    "sg:tags":[
        "devices",
        "mfg"
    ],
    "wof:name":"R & R Technology",
    "wof:placetype":"venue"
},
  "geometry": {"coordinates":[-95.54721600000001,29.564457],"type":"Point"}
}