{
  "type": "Feature",
  "properties": {
    "iso:country":"US",
    "sg:address":"727 Mc Dougal Ave",
    "sg:city":"San Antonio",
    "sg:classifiers":[
        {
            "category":"Social Services",
            "type":"Services"
        }
    ],
    "sg:phone":"+1 210 532 2019",
    "sg:postcode":"78223",
    "sg:province":"TX",
    "sg:tags":[
        "organization",
        "welfare"
    ],
    "wof:name":"Partners Resource Network Inc",
    "wof:placetype":"venue"
},
  "geometry": {"coordinates":[-98.43665300000001,29.381364],"type":"Point"}
}