{
  "type": "Feature",
  "properties": {
    "iso:country":"US",
    "sg:address":"10433 Oak Gate Ln",
    "sg:city":"Dallas",
    "sg:classifiers":[
        {
            "category":"Professional",
            "subcategory":"Accounting & Tax Preparation",
            "type":"Services"
        }
    ],
    "sg:phone":"+1 214 729 3871",
    "sg:postcode":"75217",
    "sg:province":"TX",
    "sg:tags":[
        "bookkeeping",
        "general"
    ],
    "wof:name":"C & C Enterprises",
    "wof:placetype":"venue"
},
  "geometry": {"coordinates":[-96.645635,32.742648],"type":"Point"}
}