{
  "type": "Feature",
  "properties": {
    "iso:country":"US",
    "sg:address":"12524 Darrington Rd",
    "sg:city":"Horizon City",
    "sg:classifiers":[
        {
            "category":"Freight",
            "type":"Transportation"
        }
    ],
    "sg:phone":"+1 915 852 3357",
    "sg:postcode":"79928",
    "sg:province":"TX",
    "sg:tags":[
        "trucking"
    ],
    "wof:name":"Covenant Transport",
    "wof:placetype":"venue"
},
  "geometry": {"coordinates":[-106.192971,31.672843],"type":"Point"}
}