{
  "type": "Feature",
  "properties": {
    "iso:country":"US",
    "sg:address":"3434 Swiss Ave",
    "sg:city":"Dallas",
    "sg:classifiers":[
        {
            "category":"Health Services",
            "subcategory":"Doctor",
            "type":"Services"
        }
    ],
    "sg:phone":"+1 214 828 5050",
    "sg:postcode":"75204",
    "sg:province":"TX",
    "sg:tags":[
        "medical"
    ],
    "wof:name":"John G Casey MD",
    "wof:placetype":"venue"
},
  "geometry": {"coordinates":[-96.781626,32.792073],"type":"Point"}
}