{
  "type": "Feature",
  "properties": {
    "iso:country":"US",
    "sg:address":"2202 Glen Heights Dr",
    "sg:city":"Garland",
    "sg:classifiers":[
        {
            "category":"Professional",
            "type":"Services"
        },
        {
            "category":"Professional",
            "subcategory":"Business Services",
            "type":"Services"
        }
    ],
    "sg:phone":"+1 972 414 5587",
    "sg:postcode":"75044",
    "sg:province":"TX",
    "sg:tags":[
        "establishment"
    ],
    "wof:name":"Ell Jay Enterprises",
    "wof:placetype":"venue"
},
  "geometry": {"coordinates":[-96.66185900000001,32.961145],"type":"Point"}
}