{
  "type": "Feature",
  "properties": {
    "iso:country":"US",
    "sg:address":"1699 Sam Houston Pkwy",
    "sg:city":"Houston",
    "sg:classifiers":[
        {
            "category":"Wholesale",
            "subcategory":"Jewelry",
            "type":"Manufacturing & Wholesale Goods"
        }
    ],
    "sg:phone":"+1 713 783 4333",
    "sg:postcode":"77042",
    "sg:province":"TX",
    "sg:tags":[
        "stone",
        "costume",
        "mfg"
    ],
    "wof:name":"Jean F Pinnelli",
    "wof:placetype":"venue"
},
  "geometry": {"coordinates":[-95.558414,29.745911],"type":"Point"}
}