{
  "type": "Feature",
  "properties": {
    "iso:country":"US",
    "sg:address":"8086 Hummingbird Dr",
    "sg:city":"Frisco",
    "sg:classifiers":[
        {
            "category":"Building & Trades",
            "subcategory":"Construction",
            "type":"Services"
        }
    ],
    "sg:phone":"+1 972 335 9077",
    "sg:postcode":"75034",
    "sg:province":"TX",
    "sg:tags":[
        "painter"
    ],
    "wof:name":"Painting By SDW",
    "wof:placetype":"venue"
},
  "geometry": {"coordinates":[-96.814594,33.146857],"type":"Point"}
}