{
  "type": "Feature",
  "properties": {
    "iso:country":"US",
    "sg:address":"2814 N Main St Ste 200",
    "sg:city":"Baytown",
    "sg:classifiers":[
        {
            "category":"Personal",
            "subcategory":"Beauty Salon",
            "type":"Services"
        }
    ],
    "sg:phone":"+1 281 837 5583",
    "sg:postcode":"77521",
    "sg:province":"TX",
    "sg:tags":[
        "hair",
        "stylist"
    ],
    "wof:name":"Total Image Hair Studio",
    "wof:placetype":"venue"
},
  "geometry": {"coordinates":[-94.96386,29.752425],"type":"Point"}
}