{
  "type": "Feature",
  "properties": {
    "iso:country":"US",
    "sg:address":"2810 Lake Oak",
    "sg:city":"San Antonio",
    "sg:classifiers":[
        {
            "category":"Professional",
            "type":"Services"
        }
    ],
    "sg:phone":"+1 210 507 3989",
    "sg:postcode":"78222",
    "sg:province":"TX",
    "wof:name":"Networx",
    "wof:placetype":"venue"
},
  "geometry": {"coordinates":[-98.378985,29.391749],"type":"Point"}
}