{
  "type": "Feature",
  "properties": {
    "iso:country":"US",
    "sg:address":"3435 N Belt Line Rd",
    "sg:city":"Irving",
    "sg:classifiers":[
        {
            "category":"Restaurant",
            "type":"Food & Drink"
        }
    ],
    "sg:phone":"+1 972 255 3671",
    "sg:postcode":"75062",
    "sg:province":"TX",
    "sg:tags":[
        "eating"
    ],
    "wof:name":"Tai-Pan Chinese Cuisine",
    "wof:placetype":"venue"
},
  "geometry": {"coordinates":[-96.992199,32.850896],"type":"Point"}
}