{
  "type": "Feature",
  "properties": {
    "iso:country":"US",
    "sg:address":"3237 W Northwest Hwy",
    "sg:city":"Dallas",
    "sg:classifiers":[
        {
            "category":"Bars & Pubs",
            "subcategory":"Sports Bar",
            "type":"Food & Drink"
        }
    ],
    "sg:phone":"+1 214 351 3610",
    "sg:postcode":"75220",
    "sg:province":"TX",
    "sg:tags":[
        "hall",
        "pool"
    ],
    "wof:name":"Villares Circulo 33",
    "wof:placetype":"venue"
},
  "geometry": {"coordinates":[-96.86559800000001,32.855717],"type":"Point"}
}