{
  "type": "Feature",
  "properties": {
    "iso:country":"US",
    "sg:address":"15730 Spring Forest Dr",
    "sg:city":"Houston",
    "sg:classifiers":[
        {
            "category":"Building & Trades",
            "subcategory":"Plumbing",
            "type":"Services"
        }
    ],
    "sg:phone":"+1 281 461 8117",
    "sg:postcode":"77059",
    "sg:province":"TX",
    "sg:tags":[
        "plumbing",
        "contractor"
    ],
    "wof:name":"Ingram Plumbing Co",
    "wof:placetype":"venue"
},
  "geometry": {"coordinates":[-95.118911,29.601021],"type":"Point"}
}