{
  "type": "Feature",
  "properties": {
    "iso:country":"US",
    "sg:address":"6200 W Parker Rd",
    "sg:city":"Plano",
    "sg:classifiers":[
        {
            "category":"Professional",
            "type":"Services"
        }
    ],
    "sg:phone":"+1 469 467 0340",
    "sg:postcode":"75093",
    "sg:province":"TX",
    "sg:tags":[
        "treatment",
        "cancer",
        "center"
    ],
    "wof:name":"Texas Oncology Pa",
    "wof:placetype":"venue"
},
  "geometry": {"coordinates":[-96.834778,33.045139],"type":"Point"}
}