{
  "type": "Feature",
  "properties": {
    "iso:country":"US",
    "sg:address":"3640 Westchase Dr",
    "sg:city":"Houston",
    "sg:classifiers":[
        {
            "category":"Shopping",
            "subcategory":"Computers & Home Electronics",
            "type":"Retail Goods"
        }
    ],
    "sg:phone":"+1 713 784 5700",
    "sg:postcode":"77042",
    "sg:province":"TX",
    "sg:tags":[
        "parts",
        "supply"
    ],
    "wof:name":"Lantech Inc",
    "wof:placetype":"venue"
},
  "geometry": {"coordinates":[-95.551097,29.724469],"type":"Point"}
}