{
  "type": "Feature",
  "properties": {
    "iso:country":"US",
    "sg:address":"5109 Queen's Ct",
    "sg:city":"Corpus Christi",
    "sg:classifiers":[
        {
            "category":"Professional",
            "type":"Services"
        }
    ],
    "sg:phone":"+1 361 857 2950",
    "sg:postcode":"78413",
    "sg:province":"TX",
    "sg:tags":[
        "establishment"
    ],
    "sg:website":"www.unboundword.com",
    "wof:name":"Unbound Word",
    "wof:placetype":"venue"
},
  "geometry": {"coordinates":[-97.40065800000001,27.67447],"type":"Point"}
}