{
  "type": "Feature",
  "properties": {
    "iso:country":"US",
    "sg:address":"5508 US Hwy 290",
    "sg:city":"Austin",
    "sg:classifiers":[
        {
            "category":"Professional",
            "subcategory":"Lawyer & Legal Services",
            "type":"Services"
        }
    ],
    "sg:phone":"+1 512 899 1848",
    "sg:postcode":"78735",
    "sg:province":"TX",
    "sg:tags":[
        "attorney"
    ],
    "wof:name":"Charles Peisell",
    "wof:placetype":"venue"
},
  "geometry": {"coordinates":[-97.845446,30.236116],"type":"Point"}
}