{
  "type": "Feature",
  "properties": {
    "iso:country":"US",
    "sg:address":"507 US Hwy 80 E",
    "sg:city":"Mesquite",
    "sg:classifiers":[
        {
            "category":"Retail",
            "subcategory":"Auto Rental",
            "type":"Services"
        }
    ],
    "sg:phone":"+1 972 203 9151",
    "sg:postcode":"75149",
    "sg:province":"TX",
    "sg:tags":[
        "renting",
        "leasing",
        "trailer"
    ],
    "wof:name":"Citi Capital Trailer Rental",
    "wof:placetype":"venue"
},
  "geometry": {"coordinates":[-96.599985,32.790801],"type":"Point"}
}