{
  "type": "Feature",
  "properties": {
    "iso:country":"US",
    "sg:address":"100 Lc Martin Dr Ofc",
    "sg:city":"Devine",
    "sg:classifiers":[
        {
            "category":"Real Estate",
            "subcategory":"Real Estate Operator",
            "type":"Services"
        }
    ],
    "sg:phone":"+1 830 663 5731",
    "sg:postcode":"78016",
    "sg:province":"TX",
    "sg:tags":[
        "apartment"
    ],
    "wof:name":"Devine Plaza Apartments",
    "wof:placetype":"venue"
},
  "geometry": {"coordinates":[-98.89671300000001,29.132231],"type":"Point"}
}