{
  "type": "Feature",
  "properties": {
    "iso:country":"US",
    "sg:address":"500 Trinity St",
    "sg:city":"Coleman",
    "sg:classifiers":[
        {
            "category":"Home & Garden",
            "subcategory":"Building Materials",
            "type":"Retail Goods"
        },
        {
            "category":"Manufacturing",
            "subcategory":"Glass & Minerals",
            "type":"Manufacturing & Wholesale Goods"
        }
    ],
    "sg:phone":"+1 325 625 4222",
    "sg:postcode":"76834",
    "sg:province":"TX",
    "sg:tags":[
        "ready",
        "concrete",
        "mfg",
        "mixed",
        "mix"
    ],
    "wof:name":"Coleman Ready Mix Inc",
    "wof:placetype":"venue"
},
  "geometry": {"coordinates":[-99.430269,31.835527],"type":"Point"}
}