{
  "type": "Feature",
  "properties": {
    "iso:country":"US",
    "sg:address":"1524 50th St",
    "sg:city":"Lubbock",
    "sg:classifiers":[
        {
            "category":"Building & Trades",
            "subcategory":"Equipment Rental",
            "type":"Services"
        }
    ],
    "sg:phone":"+1 806 763 0088",
    "sg:postcode":"79412",
    "sg:province":"TX",
    "sg:tags":[
        "home",
        "furniture",
        "appliance",
        "entertainment"
    ],
    "wof:name":"Timely Sales & Rentals",
    "wof:placetype":"venue"
},
  "geometry": {"coordinates":[-101.8522,33.548815],"type":"Point"}
}