{
  "type": "Feature",
  "properties": {
    "iso:country":"US",
    "sg:address":"807 S Central Expy",
    "sg:city":"Richardson",
    "sg:classifiers":[
        {
            "category":"Restaurant",
            "type":"Food & Drink"
        }
    ],
    "sg:phone":"+1 972 881 8600",
    "sg:postcode":"75080",
    "sg:province":"TX",
    "sg:tags":[
        "eating"
    ],
    "wof:name":"El Paso Cantina",
    "wof:placetype":"venue"
},
  "geometry": {"coordinates":[-96.74412599999999,32.940536],"type":"Point"}
}