{
  "type": "Feature",
  "properties": {
    "iso:country":"US",
    "sg:address":"1515 S 37th St",
    "sg:city":"Nederland",
    "sg:classifiers":[
        {
            "category":"Arena",
            "subcategory":"Sports Club",
            "type":"Entertainment"
        }
    ],
    "sg:phone":"+1 409 962 4811",
    "sg:postcode":"77627",
    "sg:province":"TX",
    "wof:name":"Bellaire Girls Softball League",
    "wof:placetype":"venue"
},
  "geometry": {"coordinates":[-93.995473,29.948864],"type":"Point"}
}