{
  "type": "Feature",
  "properties": {
    "iso:country":"US",
    "sg:address":"540 Keller Pkwy",
    "sg:city":"Keller",
    "sg:classifiers":[
        {
            "category":"Food & Beverages",
            "subcategory":"Groceries & Convenience Stores",
            "type":"Retail Goods"
        }
    ],
    "sg:phone":"+1 817 431 5171",
    "sg:postcode":"76248",
    "sg:province":"TX",
    "wof:name":"Diamond Convenience Store",
    "wof:placetype":"venue"
},
  "geometry": {"coordinates":[-97.24239300000001,32.934294],"type":"Point"}
}