{
  "type": "Feature",
  "properties": {
    "iso:country":"US",
    "sg:address":"1550 W Berry St",
    "sg:city":"Fort Worth",
    "sg:classifiers":[
        {
            "category":"Food & Beverages",
            "subcategory":"Bakery",
            "type":"Retail Goods"
        }
    ],
    "sg:phone":"+1 817 921 1413",
    "sg:postcode":"76110",
    "sg:province":"TX",
    "sg:tags":[
        "baker"
    ],
    "wof:name":"LA Gardenia Bakery",
    "wof:placetype":"venue"
},
  "geometry": {"coordinates":[-97.34387099999999,32.706044],"type":"Point"}
}