{
  "type": "Feature",
  "properties": {
    "iso:country":"US",
    "sg:address":"11900 Socorro Rd",
    "sg:city":"San Elizario",
    "sg:classifiers":[
        {
            "category":"Autos & Motor Vehicles",
            "subcategory":"Automobile Sales",
            "type":"Retail Goods"
        }
    ],
    "sg:phone":"+1 915 851 0981",
    "sg:postcode":"79849",
    "sg:province":"TX",
    "sg:tags":[
        "car",
        "used",
        "dealer"
    ],
    "wof:name":"Martin Motors",
    "wof:placetype":"venue"
},
  "geometry": {"coordinates":[-106.276034,31.602488],"type":"Point"}
}