{
  "type": "Feature",
  "properties": {
    "iso:country":"US",
    "sg:address":"1805 Tartar Way",
    "sg:city":"Austin",
    "sg:classifiers":[
        {
            "category":"Building & Trades",
            "subcategory":"Construction",
            "type":"Services"
        }
    ],
    "sg:phone":"+1 512 263 9425",
    "sg:postcode":"78733",
    "sg:province":"TX",
    "sg:tags":[
        "house"
    ],
    "wof:name":"Equity Home Builders",
    "wof:placetype":"venue"
},
  "geometry": {"coordinates":[-97.865157,30.342284],"type":"Point"}
}