{
  "type": "Feature",
  "properties": {
    "iso:country":"US",
    "sg:address":"1440 Harold St",
    "sg:city":"Houston",
    "sg:classifiers":[
        {
            "category":"Organizations",
            "subcategory":"Religious Organization",
            "type":"Services"
        }
    ],
    "sg:phone":"+1 713 526 1017",
    "sg:postcode":"77006",
    "sg:province":"TX",
    "wof:name":"Bering Memorial United Methodist Church",
    "wof:placetype":"venue"
},
  "geometry": {"coordinates":[-95.39720199999999,29.7414],"type":"Point"}
}