{
  "type": "Feature",
  "properties": {
    "iso:country":"US",
    "sg:address":"4801 Woodway Dr Ste 360W",
    "sg:city":"Houston",
    "sg:classifiers":[
        {
            "category":"Professional",
            "subcategory":"Lawyer & Legal Services",
            "type":"Services"
        }
    ],
    "sg:phone":"+1 713 572 3482",
    "sg:postcode":"77056",
    "sg:province":"TX",
    "wof:name":"Knop Kenneth H Atty",
    "wof:placetype":"venue"
},
  "geometry": {"coordinates":[-95.45970199999999,29.763901],"type":"Point"}
}