{
  "type": "Feature",
  "properties": {
    "iso:country":"US",
    "sg:address":"9530 Viscount Blvd",
    "sg:city":"El Paso",
    "sg:classifiers":[
        {
            "category":"Personal",
            "subcategory":"Beauty Salon",
            "type":"Services"
        }
    ],
    "sg:phone":"+1 915 599 8805",
    "sg:postcode":"79925",
    "sg:province":"TX",
    "wof:name":"Galmour Cuts",
    "wof:placetype":"venue"
},
  "geometry": {"coordinates":[-106.363822,31.767598],"type":"Point"}
}