{
  "type": "Feature",
  "properties": {
    "iso:country":"US",
    "sg:address":"12115 State Hwy 107",
    "sg:city":"Adkins",
    "sg:classifiers":[
        {
            "category":"Organizations",
            "subcategory":"Religious Organization",
            "type":"Services"
        }
    ],
    "sg:phone":"+1 210 649 3766",
    "sg:postcode":"78101",
    "sg:province":"TX",
    "sg:tags":[
        "church"
    ],
    "wof:name":"Crossroads Life Changing Otrch",
    "wof:placetype":"venue"
},
  "geometry": {"coordinates":[-98.24510100000001,29.367209],"type":"Point"}
}