{
  "type": "Feature",
  "properties": {
    "iso:country":"US",
    "sg:address":"2700 E Ellis St",
    "sg:city":"Levelland",
    "sg:classifiers":[
        {
            "category":"Freight",
            "type":"Transportation"
        }
    ],
    "sg:phone":"+1 806 894 8745",
    "sg:postcode":"79336",
    "sg:province":"TX",
    "sg:tags":[
        "local",
        "trucking"
    ],
    "wof:name":"Garcia Rene Trucking Co Inc",
    "wof:placetype":"venue"
},
  "geometry": {"coordinates":[-102.310835,33.600412],"type":"Point"}
}