{
  "type": "Feature",
  "properties": {
    "iso:country":"US",
    "sg:address":"3493 FM 539",
    "sg:city":"Floresville",
    "sg:classifiers":[
        {
            "category":"Farming",
            "subcategory":"Livestock Farm",
            "type":"Manufacturing & Wholesale Goods"
        }
    ],
    "sg:phone":"+1 830 947 3396",
    "sg:postcode":"78121",
    "sg:province":"TX",
    "sg:tags":[
        "feeding"
    ],
    "wof:name":"Texana Feeders LTD",
    "wof:placetype":"venue"
},
  "geometry": {"coordinates":[-98.062262,29.404911],"type":"Point"}
}