{
  "type": "Feature",
  "properties": {
    "iso:country":"US",
    "sg:address":"7701 Wilshire Place Dr",
    "sg:city":"Houston",
    "sg:classifiers":[
        {
            "category":"Professional",
            "subcategory":"Employment Agencies",
            "type":"Services"
        }
    ],
    "sg:phone":"+1 713 580 3621",
    "sg:postcode":"77040",
    "sg:province":"TX",
    "sg:tags":[
        "opportunity"
    ],
    "wof:name":"Burnett Staffing Specialists",
    "wof:placetype":"venue"
},
  "geometry": {"coordinates":[-95.508691,29.858797],"type":"Point"}
}