{
  "type": "Feature",
  "properties": {
    "iso:country":"US",
    "sg:address":"2082 FM 2725",
    "sg:city":"Ingleside",
    "sg:classifiers":[
        {
            "category":"Retail",
            "subcategory":"Auto Repair",
            "type":"Services"
        }
    ],
    "sg:phone":"+1 361 758 7198",
    "sg:postcode":"78362",
    "sg:province":"TX",
    "sg:tags":[
        "engine"
    ],
    "sg:website":"www.fdgm.com",
    "wof:name":"FDGM Inc",
    "wof:placetype":"venue"
},
  "geometry": {"coordinates":[-97.171127,27.87194],"type":"Point"}
}