{
  "type": "Feature",
  "properties": {
    "iso:country":"US",
    "sg:address":"8527 N Capital of Texas Hwy",
    "sg:city":"Austin",
    "sg:classifiers":[
        {
            "category":"Real Estate",
            "subcategory":"Real Estate Operator",
            "type":"Services"
        }
    ],
    "sg:phone":"+1 512 346 4911",
    "sg:postcode":"78759",
    "sg:province":"TX",
    "sg:tags":[
        "building",
        "apartment"
    ],
    "wof:name":"Aspen Hills Apartments",
    "wof:placetype":"venue"
},
  "geometry": {"coordinates":[-97.76276900000001,30.387552],"type":"Point"}
}