{
  "type": "Feature",
  "properties": {
    "iso:country":"US",
    "sg:address":"1404 Tad St",
    "sg:city":"Ennis",
    "sg:classifiers":[
        {
            "category":"Shopping",
            "subcategory":"Jewelry",
            "type":"Retail Goods"
        }
    ],
    "sg:phone":"+1 972 878 0686",
    "sg:postcode":"75119",
    "sg:province":"TX",
    "wof:name":"Beatys Jewelry & Watch Repair",
    "wof:placetype":"venue"
},
  "geometry": {"coordinates":[-96.655638,32.344821],"type":"Point"}
}