{
  "type": "Feature",
  "properties": {
    "iso:country":"US",
    "sg:address":"2244 Luna Rd",
    "sg:city":"Carrollton",
    "sg:classifiers":[
        {
            "category":"Building & Trades",
            "subcategory":"Plumbing",
            "type":"Services"
        }
    ],
    "sg:phone":"+1 214 273 5110",
    "sg:postcode":"75006",
    "sg:province":"TX",
    "sg:tags":[
        "conditioning",
        "air",
        "system",
        "contractor"
    ],
    "sg:website":"www.comfortsupply.com",
    "wof:name":"Comfort Supply Inc",
    "wof:placetype":"venue"
},
  "geometry": {"coordinates":[-96.925263,32.930641],"type":"Point"}
}