{
  "type": "Feature",
  "properties": {
    "iso:country":"US",
    "sg:address":"4503 Shavano Hollow",
    "sg:city":"San Antonio",
    "sg:classifiers":[
        {
            "category":"Home & Garden",
            "subcategory":"Home Furnishings",
            "type":"Retail Goods"
        }
    ],
    "sg:phone":"+1 210 493 6314",
    "sg:postcode":"78230",
    "sg:province":"TX",
    "wof:name":"Pamela Kern",
    "wof:placetype":"venue"
},
  "geometry": {"coordinates":[-98.57181,29.569757],"type":"Point"}
}