{
  "type": "Feature",
  "properties": {
    "iso:country":"US",
    "sg:address":"1901 W William Cannon Ste 125",
    "sg:city":"Austin",
    "sg:classifiers":[
        {
            "category":"Health Services",
            "subcategory":"Doctor",
            "type":"Services"
        }
    ],
    "sg:phone":"+1 512 301 6400",
    "sg:postcode":"78745",
    "sg:province":"TX",
    "sg:tags":[
        "practice",
        "family"
    ],
    "wof:name":"Dr Kevin Lewis",
    "wof:placetype":"venue"
},
  "geometry": {"coordinates":[-97.805862,30.201789],"type":"Point"}
}