{
  "type": "Feature",
  "properties": {
    "iso:country":"US",
    "sg:address":"4906 Burleson Rd",
    "sg:city":"Austin",
    "sg:classifiers":[
        {
            "category":"Autos & Motor Vehicles",
            "subcategory":"Fuel & Gas Station",
            "type":"Retail Goods"
        },
        {
            "category":"Manufacturing",
            "subcategory":"Petroleum Products",
            "type":"Manufacturing & Wholesale Goods"
        }
    ],
    "sg:phone":"+1 512 444 1941",
    "sg:postcode":"78744",
    "sg:province":"TX",
    "sg:tags":[
        "lubricating",
        "oil",
        "diesel"
    ],
    "sg:website":"http://www.texconoil.com",
    "wof:name":"Tex-Con Oil Company",
    "wof:placetype":"venue"
},
  "geometry": {"coordinates":[-97.73,30.211956],"type":"Point"}
}