{
  "type": "Feature",
  "properties": {
    "iso:country":"US",
    "sg:address":"1306 E 34th St",
    "sg:city":"Lubbock",
    "sg:classifiers":[
        {
            "category":"Wholesale",
            "subcategory":"Machinery & Supplies",
            "type":"Manufacturing & Wholesale Goods"
        }
    ],
    "sg:phone":"+1 806 747 3539",
    "sg:postcode":"79404",
    "sg:province":"TX",
    "sg:tags":[
        "farm",
        "equipment"
    ],
    "wof:name":"Phares & Wilkins Mfg Inc",
    "wof:placetype":"venue"
},
  "geometry": {"coordinates":[-101.820699,33.563259],"type":"Point"}
}