{
  "type": "Feature",
  "properties": {
    "iso:country":"US",
    "sg:address":"8474 Fm 2450",
    "sg:city":"Sanger",
    "sg:classifiers":[
        {
            "category":"Retail",
            "subcategory":"Auto Repair",
            "type":"Services"
        }
    ],
    "sg:phone":"+1 940 536 3979",
    "sg:postcode":"76266",
    "sg:province":"TX",
    "sg:tags":[
        "body",
        "automobile",
        "removal",
        "dent",
        "painting",
        "repairing"
    ],
    "sg:website":"http://www.yext.com/p/superpages/economotor-paint-body-sanger-texas.html",
    "wof:name":"Economotor Paint & Body",
    "wof:placetype":"venue"
},
  "geometry": {"coordinates":[-97.238669,33.331488],"type":"Point"}
}