{
  "type": "Feature",
  "properties": {
    "iso:country":"US",
    "sg:address":"820 W Wheeler Ave",
    "sg:city":"Aransas Pass",
    "sg:classifiers":[
        {
            "category":"Personal",
            "subcategory":"Beauty Salon",
            "type":"Services"
        }
    ],
    "sg:phone":"+1 361 758 2808",
    "sg:postcode":"78336",
    "sg:province":"TX",
    "sg:tags":[
        "shop"
    ],
    "wof:name":"Kimmie's Kuts",
    "wof:placetype":"venue"
},
  "geometry": {"coordinates":[-97.152451,27.910842],"type":"Point"}
}