{
  "type": "Feature",
  "properties": {
    "iso:country":"US",
    "sg:address":"600 W 9th Street",
    "sg:city":"Austin",
    "sg:classifiers":[
        {
            "category":"Professional",
            "subcategory":"Lawyer & Legal Services",
            "type":"Services"
        }
    ],
    "sg:phone":"+1 512 476 2494",
    "sg:postcode":"78701",
    "sg:province":"TX",
    "wof:name":"Gunter Law Offices",
    "wof:placetype":"venue"
},
  "geometry": {"coordinates":[-97.74738499999999,30.272465],"type":"Point"}
}