{
  "type": "Feature",
  "properties": {
    "iso:country":"US",
    "sg:address":"7006 University Ave",
    "sg:city":"Lubbock",
    "sg:classifiers":[
        {
            "category":"Restaurant",
            "type":"Food & Drink"
        }
    ],
    "sg:phone":"+1 806 745 2205",
    "sg:postcode":"79413",
    "sg:province":"TX",
    "wof:name":"Fortune Cookie Chinese Rstrnt",
    "wof:placetype":"venue"
},
  "geometry": {"coordinates":[-101.870482,33.530442],"type":"Point"}
}