{
  "type": "Feature",
  "properties": {
    "iso:country":"US",
    "sg:address":"4604 Denton Hwy",
    "sg:city":"Fort Worth",
    "sg:classifiers":[
        {
            "category":"Recreation",
            "type":"Entertainment"
        }
    ],
    "sg:phone":"+1 817 485 8380",
    "sg:postcode":"76117",
    "sg:province":"TX",
    "sg:tags":[
        "martial",
        "arts",
        "instruction"
    ],
    "wof:name":"Extreme Grappling",
    "wof:placetype":"venue"
},
  "geometry": {"coordinates":[-97.26416999999999,32.831791],"type":"Point"}
}