{
  "type": "Feature",
  "properties": {
    "iso:country":"US",
    "sg:address":"705 Runners Ridge",
    "sg:city":"Pflugerville",
    "sg:classifiers":[
        {
            "category":"Building & Trades",
            "subcategory":"Landscaping Services",
            "type":"Services"
        }
    ],
    "sg:phone":"+1 512 670 5296",
    "sg:postcode":"78660",
    "sg:province":"TX",
    "wof:name":"Allscapes",
    "wof:placetype":"venue"
},
  "geometry": {"coordinates":[-97.637394,30.439682],"type":"Point"}
}