{
  "type": "Feature",
  "properties": {
    "iso:country":"US",
    "sg:address":"1506 E 31st St",
    "sg:city":"Bryan",
    "sg:classifiers":[
        {
            "category":"Building & Trades",
            "subcategory":"Construction",
            "type":"Services"
        }
    ],
    "sg:phone":"+1 979 775 1506",
    "sg:postcode":"77802",
    "sg:province":"TX",
    "sg:tags":[
        "concrete",
        "contractor"
    ],
    "wof:name":"Coyote Concrete Construction",
    "wof:placetype":"venue"
},
  "geometry": {"coordinates":[-96.358429,30.657933],"type":"Point"}
}