{
  "type": "Feature",
  "properties": {
    "iso:country":"US",
    "sg:address":"3530A Spencer Hwy",
    "sg:city":"Pasadena",
    "sg:classifiers":[
        {
            "category":"Coffee & Tea",
            "type":"Food & Drink"
        }
    ],
    "sg:phone":"+1 713 944 0980",
    "sg:postcode":"77504",
    "sg:province":"TX",
    "wof:name":"Starbucks",
    "wof:placetype":"venue"
},
  "geometry": {"coordinates":[-95.189939,29.665076],"type":"Point"}
}