{
  "type": "Feature",
  "properties": {
    "iso:country":"US",
    "sg:address":"844 Nederland Ave",
    "sg:city":"Nederland",
    "sg:classifiers":[
        {
            "category":"Building & Trades",
            "subcategory":"Equipment Rental",
            "type":"Services"
        }
    ],
    "sg:phone":"+1 409 722 7282",
    "sg:postcode":"77627",
    "sg:province":"TX",
    "sg:tags":[
        "leasing",
        "furniture"
    ],
    "wof:name":"Aarons Sales & Lease Ownership",
    "wof:placetype":"venue"
},
  "geometry": {"coordinates":[-93.985303,29.979133],"type":"Point"}
}