{
  "type": "Feature",
  "properties": {
    "iso:country":"US",
    "sg:address":"1201 W Loop St",
    "sg:city":"El Campo",
    "sg:classifiers":[
        {
            "category":"Personal",
            "subcategory":"Beauty Salon",
            "type":"Services"
        }
    ],
    "sg:phone":"+1 979 543 5595",
    "sg:postcode":"77437",
    "sg:province":"TX",
    "sg:tags":[
        "shop"
    ],
    "wof:name":"Hairanoia Salon & Tanning",
    "wof:placetype":"venue"
},
  "geometry": {"coordinates":[-96.29343900000001,29.194715],"type":"Point"}
}