{
  "type": "Feature",
  "properties": {
    "iso:country":"US",
    "sg:address":"9108 Bellaire Blvd Ste A",
    "sg:city":"Houston",
    "sg:classifiers":[
        {
            "category":"Restaurant",
            "type":"Food & Drink"
        }
    ],
    "sg:phone":"+1 713 772 9633",
    "sg:postcode":"77036",
    "sg:province":"TX",
    "sg:tags":[
        "chinese"
    ],
    "wof:name":"Hong Kong's Cafe",
    "wof:placetype":"venue"
},
  "geometry": {"coordinates":[-95.54445800000001,29.705032],"type":"Point"}
}