{
  "type": "Feature",
  "properties": {
    "iso:country":"US",
    "sg:address":"9101 Lipan Rd Ste 206",
    "sg:city":"Houston",
    "sg:classifiers":[
        {
            "category":"Building & Trades",
            "subcategory":"Construction",
            "type":"Services"
        }
    ],
    "sg:phone":"+1 281 633 0400",
    "sg:postcode":"77063",
    "sg:province":"TX",
    "sg:tags":[
        "air",
        "heating",
        "conditioning/hvac"
    ],
    "sg:website":"http://www.climatedesignac.net",
    "wof:name":"Climate Design Air Conditioning & Heating",
    "wof:placetype":"venue"
},
  "geometry": {"coordinates":[-95.524002,29.7237],"type":"Point"}
}