{
  "type": "Feature",
  "properties": {
    "iso:country":"US",
    "sg:address":"2905 Gilmer Rd",
    "sg:city":"Longview",
    "sg:classifiers":[
        {
            "category":"Travel",
            "subcategory":"Hotels & Motels",
            "type":"Entertainment"
        }
    ],
    "sg:phone":"+1 903 295 6629",
    "sg:postcode":"75604",
    "sg:province":"TX",
    "sg:tags":[
        "resort"
    ],
    "wof:name":"Camcam Resorts",
    "wof:placetype":"venue"
},
  "geometry": {"coordinates":[-94.791309,32.538651],"type":"Point"}
}