{
  "type": "Feature",
  "properties": {
    "iso:country":"US",
    "sg:address":"12705 Manorwood Ln",
    "sg:city":"Cypress",
    "sg:classifiers":[
        {
            "category":"Wholesale",
            "subcategory":"Non-durable Goods",
            "type":"Manufacturing & Wholesale Goods"
        }
    ],
    "sg:phone":"+1 281 970 3285",
    "sg:postcode":"77429",
    "sg:province":"TX",
    "wof:name":"Ross Crafts",
    "wof:placetype":"venue"
},
  "geometry": {"coordinates":[-95.61699900000001,29.952084],"type":"Point"}
}