{
  "type": "Feature",
  "properties": {
    "iso:country":"US",
    "sg:address":"400 E Cypress Creek Rd",
    "sg:city":"Cedar Park",
    "sg:classifiers":[
        {
            "category":"Real Estate",
            "subcategory":"Real Estate Agent",
            "type":"Services"
        }
    ],
    "sg:phone":"+1 512 257 8070",
    "sg:postcode":"78613",
    "sg:province":"TX",
    "wof:name":"Toney Professional Svc",
    "wof:placetype":"venue"
},
  "geometry": {"coordinates":[-97.825879,30.494465],"type":"Point"}
}