{
  "type": "Feature",
  "properties": {
    "iso:country":"US",
    "sg:address":"17106 Copper Shore Dr",
    "sg:city":"Houston",
    "sg:classifiers":[
        {
            "category":"Professional",
            "type":"Services"
        },
        {
            "category":"Professional",
            "subcategory":"Business Services",
            "type":"Services"
        }
    ],
    "sg:phone":"+1 281 345 4300",
    "sg:postcode":"77095",
    "sg:province":"TX",
    "sg:tags":[
        "establishment"
    ],
    "wof:name":"Amagine Technologies LLC",
    "wof:placetype":"venue"
},
  "geometry": {"coordinates":[-95.671183,29.898596],"type":"Point"}
}