{
  "type": "Feature",
  "properties": {
    "iso:country":"US",
    "sg:address":"4749 Odom Rd",
    "sg:city":"Beaumont",
    "sg:classifiers":[
        {
            "category":"Real Estate",
            "subcategory":"Real Estate Agent",
            "type":"Services"
        }
    ],
    "sg:phone":"+1 409 898 8800",
    "sg:postcode":"77706",
    "sg:province":"TX",
    "sg:tags":[
        "consulting",
        "management",
        "appraiser"
    ],
    "wof:name":"Bishop Real Estate Appraisers",
    "wof:placetype":"venue"
},
  "geometry": {"coordinates":[-94.152967,30.122957],"type":"Point"}
}