{
  "type": "Feature",
  "properties": {
    "iso:country":"US",
    "sg:address":"478 Acacia Pkwy",
    "sg:city":"Spring Branch",
    "sg:classifiers":[
        {
            "category":"Building & Trades",
            "subcategory":"Construction",
            "type":"Services"
        }
    ],
    "sg:phone":"+1 830 228 5111",
    "sg:postcode":"78070",
    "sg:province":"TX",
    "sg:tags":[
        "residential",
        "remodeling",
        "commercial",
        "con",
        "new"
    ],
    "wof:name":"Stone General Contractors",
    "wof:placetype":"venue"
},
  "geometry": {"coordinates":[-98.43233499999999,29.863174],"type":"Point"}
}