{
  "type": "Feature",
  "properties": {
    "iso:country":"US",
    "sg:address":"3245 W Pentagon Pkwy",
    "sg:city":"Dallas",
    "sg:classifiers":[
        {
            "category":"Social Services",
            "type":"Services"
        }
    ],
    "sg:phone":"+1 214 331 5440",
    "sg:postcode":"75233",
    "sg:province":"TX",
    "wof:name":"Girls Inc Metropolitan Dalla",
    "wof:placetype":"venue"
},
  "geometry": {"coordinates":[-96.874178,32.706911],"type":"Point"}
}