{
  "type": "Feature",
  "properties": {
    "iso:country":"US",
    "sg:address":"1212 Annapolis Dr",
    "sg:city":"Richardson",
    "sg:classifiers":[
        {
            "category":"Professional",
            "subcategory":"Research",
            "type":"Services"
        }
    ],
    "sg:phone":"+1 972 699 0443",
    "sg:postcode":"75081",
    "sg:province":"TX",
    "sg:tags":[
        "development",
        "alternative",
        "energy"
    ],
    "wof:name":"Clean Power Systems Inc",
    "wof:placetype":"venue"
},
  "geometry": {"coordinates":[-96.704444,32.931906],"type":"Point"}
}