{
  "type": "Feature",
  "properties": {
    "iso:country":"US",
    "sg:address":"321 Old Elkhart Rd",
    "sg:city":"Palestine",
    "sg:classifiers":[
        {
            "category":"Real Estate",
            "subcategory":"Real Estate Operator",
            "type":"Services"
        }
    ],
    "sg:phone":"+1 903 723 2831",
    "sg:postcode":"75801",
    "sg:province":"TX",
    "sg:tags":[
        "apartment"
    ],
    "wof:name":"Sycamore Lane Apartments",
    "wof:placetype":"venue"
},
  "geometry": {"coordinates":[-95.61639700000001,31.740393],"type":"Point"}
}