{
  "type": "Feature",
  "properties": {
    "iso:country":"US",
    "sg:address":"1915 Plantation Bend Dr",
    "sg:city":"Sugar Land",
    "sg:classifiers":[
        {
            "category":"Building & Trades",
            "subcategory":"Construction",
            "type":"Services"
        }
    ],
    "sg:phone":"+1 281 565 2006",
    "sg:postcode":"77478",
    "sg:province":"TX",
    "sg:tags":[
        "house"
    ],
    "wof:name":"Cazac Homes",
    "wof:placetype":"venue"
},
  "geometry": {"coordinates":[-95.583663,29.597358],"type":"Point"}
}