{
  "type": "Feature",
  "properties": {
    "iso:country":"US",
    "sg:address":"2233 Robinhood Dr",
    "sg:city":"Port Arthur",
    "sg:classifiers":[
        {
            "category":"Professional",
            "subcategory":"Management & Consulting",
            "type":"Services"
        }
    ],
    "sg:phone":"+1 409 736 2761",
    "sg:postcode":"77640",
    "sg:province":"TX",
    "sg:tags":[
        "business"
    ],
    "wof:name":"Sutton Consulting",
    "wof:placetype":"venue"
},
  "geometry": {"coordinates":[-94.01015200000001,29.882419],"type":"Point"}
}