{
  "type": "Feature",
  "properties": {
    "iso:country":"US",
    "sg:address":"2601 S Braeswood Blvd Apt 306",
    "sg:city":"Houston",
    "sg:classifiers":[
        {
            "category":"Food & Beverages",
            "subcategory":"Specialty",
            "type":"Retail Goods"
        }
    ],
    "sg:phone":"+1 713 201 4845",
    "sg:postcode":"77025",
    "sg:province":"TX",
    "sg:tags":[
        "product",
        "health",
        "diet"
    ],
    "wof:name":"Dianna Roberts, Authorized Herbalife Distributor",
    "wof:placetype":"venue"
},
  "geometry": {"coordinates":[-95.41930499999999,29.695584],"type":"Point"}
}