{
  "type": "Feature",
  "properties": {
    "iso:country":"US",
    "sg:address":"2626 Calder St",
    "sg:city":"Beaumont",
    "sg:classifiers":[
        {
            "category":"Place Of Worship",
            "subcategory":"Church",
            "type":"Public Place"
        },
        {
            "category":"Place Of Worship",
            "type":"Public Place"
        },
        {
            "category":"Organizations",
            "subcategory":"Religious Organization",
            "type":"Services"
        }
    ],
    "sg:phone":"+1 409 813 1789",
    "sg:postcode":"77702",
    "sg:province":"TX",
    "sg:tags":[
        "churches-non-denominational"
    ],
    "wof:name":"Love And Compassion Ministries",
    "wof:placetype":"venue"
},
  "geometry": {"coordinates":[-94.12761500000001,30.085673],"type":"Point"}
}