{
  "type": "Feature",
  "properties": {
    "iso:country":"US",
    "sg:address":"2415 Whitman Way Dr",
    "sg:city":"Friendswood",
    "sg:classifiers":[
        {
            "category":"Retail",
            "subcategory":"Portrait Studio",
            "type":"Services"
        }
    ],
    "sg:phone":"+1 281 482 7924",
    "sg:postcode":"77546",
    "sg:province":"TX",
    "sg:tags":[
        "photo"
    ],
    "wof:name":"Ldt Photographics",
    "wof:placetype":"venue"
},
  "geometry": {"coordinates":[-95.16403699999999,29.537307],"type":"Point"}
}