{
  "type": "Feature",
  "properties": {
    "iso:country":"US",
    "sg:address":"7405 State Highway 75 S",
    "sg:city":"Huntsville",
    "sg:classifiers":[
        {
            "category":"Government",
            "subcategory":"Office",
            "type":"Public Place"
        }
    ],
    "sg:phone":"+1 936 295 6331",
    "sg:postcode":"77340",
    "sg:province":"TX",
    "wof:name":"Goree Unit",
    "wof:placetype":"venue"
},
  "geometry": {"coordinates":[-95.516158,30.67087],"type":"Point"}
}