{
  "type": "Feature",
  "properties": {
    "iso:country":"US",
    "sg:address":"801 S Greenville Ave",
    "sg:city":"Allen",
    "sg:classifiers":[
        {
            "category":"Building & Trades",
            "subcategory":"Electrical",
            "type":"Services"
        }
    ],
    "sg:phone":"+1 972 727 8263",
    "sg:postcode":"75002",
    "sg:province":"TX",
    "sg:tags":[
        "electric",
        "contractor"
    ],
    "wof:name":"Mega Electric Co",
    "wof:placetype":"venue"
},
  "geometry": {"coordinates":[-96.67111800000001,33.087497],"type":"Point"}
}