{
  "type": "Feature",
  "properties": {
    "iso:country":"US",
    "sg:address":"4906 Doss Rd",
    "sg:city":"Austin",
    "sg:classifiers":[
        {
            "category":"Retail",
            "subcategory":"Auto Rental",
            "type":"Services"
        },
        {
            "category":"Retail",
            "subcategory":"Storage",
            "type":"Services"
        }
    ],
    "sg:phone":"+1 512 266 5774",
    "sg:postcode":"78734",
    "sg:province":"TX",
    "sg:tags":[
        "moving-self",
        "truck"
    ],
    "wof:name":"U-Haul International",
    "wof:placetype":"venue"
},
  "geometry": {"coordinates":[-97.930634,30.410571],"type":"Point"}
}