{
  "type": "Feature",
  "properties": {
    "iso:country":"US",
    "sg:address":"20011 Deer Creek Rd",
    "sg:city":"Crosby",
    "sg:classifiers":[
        {
            "category":"Retail",
            "subcategory":"Repair Shop",
            "type":"Services"
        }
    ],
    "sg:phone":"+1 281 328 5198",
    "sg:postcode":"77532",
    "sg:province":"TX",
    "sg:tags":[
        "welding"
    ],
    "wof:name":"Ray Charping Welding Services",
    "wof:placetype":"venue"
},
  "geometry": {"coordinates":[-95.01333099999999,29.970481],"type":"Point"}
}