{
  "type": "Feature",
  "properties": {
    "iso:country":"US",
    "sg:address":"4311 Oak Lawn Ave",
    "sg:city":"Dallas",
    "sg:classifiers":[
        {
            "category":"Professional",
            "type":"Services"
        }
    ],
    "sg:phone":"+1 214 987 9797",
    "sg:postcode":"75219",
    "sg:province":"TX",
    "wof:name":"Eoc Finance Corp",
    "wof:placetype":"venue"
},
  "geometry": {"coordinates":[-96.80242800000001,32.821398],"type":"Point"}
}