{
  "type": "Feature",
  "properties": {
    "iso:country":"US",
    "sg:address":"503 N Kentucky St",
    "sg:city":"Mc Kinney",
    "sg:classifiers":[
        {
            "category":"Recreation",
            "type":"Entertainment"
        }
    ],
    "sg:phone":"+1 214 544 6876",
    "sg:postcode":"75069",
    "sg:province":"TX",
    "sg:tags":[
        "instruction",
        "swimming"
    ],
    "wof:name":"Metroplex Aquatics",
    "wof:placetype":"venue"
},
  "geometry": {"coordinates":[-96.615914,33.201239],"type":"Point"}
}