{
  "type": "Feature",
  "properties": {
    "iso:country":"US",
    "sg:address":"760 W Mockingbird Ln",
    "sg:city":"Dallas",
    "sg:classifiers":[
        {
            "category":"Wholesale",
            "subcategory":"Apparel",
            "type":"Manufacturing & Wholesale Goods"
        }
    ],
    "sg:phone":"+1 214 630 0156",
    "sg:postcode":"75247",
    "sg:province":"TX",
    "sg:tags":[
        "clothing"
    ],
    "wof:name":"Bill Kahn",
    "wof:placetype":"venue"
},
  "geometry": {"coordinates":[-96.87358999999999,32.809013],"type":"Point"}
}