{
  "type": "Feature",
  "properties": {
    "iso:country":"US",
    "sg:address":"3001 Victory Dr",
    "sg:city":"Marshall",
    "sg:classifiers":[
        {
            "category":"Health Services",
            "subcategory":"Doctor",
            "type":"Services"
        }
    ],
    "sg:phone":"+1 903 935 7884",
    "sg:postcode":"75672",
    "sg:province":"TX",
    "sg:tags":[
        "dentist"
    ],
    "wof:name":"Eddie B Shaw Jr DDS",
    "wof:placetype":"venue"
},
  "geometry": {"coordinates":[-94.33399199999999,32.543587],"type":"Point"}
}