{
  "type": "Feature",
  "properties": {
    "iso:country":"US",
    "sg:address":"102 N Sunset Strip St",
    "sg:city":"Kenedy",
    "sg:classifiers":[
        {
            "category":"Local Transit",
            "type":"Transportation"
        }
    ],
    "sg:phone":"+1 830 583 9019",
    "sg:postcode":"78119",
    "sg:province":"TX",
    "sg:tags":[
        "terminal",
        "bus"
    ],
    "wof:name":"Valley Transit Co Inc",
    "wof:placetype":"venue"
},
  "geometry": {"coordinates":[-97.858671,28.817021],"type":"Point"}
}