{
  "type": "Feature",
  "properties": {
    "iso:country":"US",
    "sg:address":"13503 Southwest Fwy",
    "sg:city":"Sugar Land",
    "sg:classifiers":[
        {
            "category":"Shopping",
            "subcategory":"Used Merchandise",
            "type":"Retail Goods"
        }
    ],
    "sg:phone":"+1 281 494 4651",
    "sg:postcode":"77478",
    "sg:province":"TX",
    "sg:tags":[
        "shop",
        "thrift"
    ],
    "wof:name":"Goodwill Inc",
    "wof:placetype":"venue"
},
  "geometry": {"coordinates":[-95.5977,29.623786],"type":"Point"}
}