{
  "type": "Feature",
  "properties": {
    "iso:country":"US",
    "sg:address":"201 S Macarthur Blvd",
    "sg:city":"Coppell",
    "sg:classifiers":[
        {
            "category":"Professional",
            "type":"Services"
        }
    ],
    "sg:phone":"+1 972 304 8517",
    "sg:postcode":"75019",
    "sg:province":"TX",
    "wof:name":"MRC International Corp",
    "wof:placetype":"venue"
},
  "geometry": {"coordinates":[-96.95964499999999,32.968001],"type":"Point"}
}