{
  "type": "Feature",
  "properties": {
    "iso:country":"US",
    "sg:address":"703 Shadwell Dr",
    "sg:city":"San Antonio",
    "sg:classifiers":[
        {
            "category":"Farming",
            "subcategory":"Livestock Farm",
            "type":"Manufacturing & Wholesale Goods"
        }
    ],
    "sg:phone":"+1 210 735 8359",
    "sg:postcode":"78228",
    "sg:province":"TX",
    "sg:tags":[
        "cattle",
        "farmer"
    ],
    "wof:name":"Boyd Farms",
    "wof:placetype":"venue"
},
  "geometry": {"coordinates":[-98.554271,29.469191],"type":"Point"}
}