{
  "type": "Feature",
  "properties": {
    "iso:country":"US",
    "sg:address":"3701 5th Ave N",
    "sg:city":"Texas City",
    "sg:classifiers":[
        {
            "category":"Wholesale",
            "subcategory":"Electrical",
            "type":"Manufacturing & Wholesale Goods"
        }
    ],
    "sg:phone":"+1 409 945 8441",
    "sg:postcode":"77590",
    "sg:province":"TX",
    "sg:tags":[
        "control"
    ],
    "wof:name":"Process Control Svc",
    "wof:placetype":"venue"
},
  "geometry": {"coordinates":[-94.95107899999999,29.388083],"type":"Point"}
}