{
  "type": "Feature",
  "properties": {
    "iso:country":"US",
    "sg:address":"1418 Antoine Dr",
    "sg:city":"Houston",
    "sg:classifiers":[
        {
            "category":"Shopping",
            "subcategory":"Bicycles & Sporting Goods",
            "type":"Retail Goods"
        }
    ],
    "sg:phone":"+1 713 721 4227",
    "sg:postcode":"77055",
    "sg:province":"TX",
    "wof:name":"Dipsticks Inc",
    "wof:placetype":"venue"
},
  "geometry": {"coordinates":[-95.47561399999999,29.795975],"type":"Point"}
}