{
  "type": "Feature",
  "properties": {
    "iso:country":"US",
    "sg:address":"2729 Fondren Rd Ste C",
    "sg:city":"Houston",
    "sg:classifiers":[
        {
            "category":"Personal",
            "subcategory":"Nail Salon",
            "type":"Services"
        }
    ],
    "sg:phone":"+1 713 789 2310",
    "sg:postcode":"77063",
    "sg:province":"TX",
    "wof:name":"Every Nail",
    "wof:placetype":"venue"
},
  "geometry": {"coordinates":[-95.521004,29.7367],"type":"Point"}
}