{
  "type": "Feature",
  "properties": {
    "iso:country":"US",
    "sg:address":"1200 W Wall St",
    "sg:city":"Midland",
    "sg:classifiers":[
        {
            "category":"Health Services",
            "subcategory":"Doctor",
            "type":"Services"
        }
    ],
    "sg:phone":"+1 432 682 0574",
    "sg:postcode":"79701",
    "sg:province":"TX",
    "sg:tags":[
        "medical"
    ],
    "wof:name":"Khouri Daniel MD Frcs Dabu",
    "wof:placetype":"venue"
},
  "geometry": {"coordinates":[-102.08790500000001,31.995987],"type":"Point"}
}