{
  "type": "Feature",
  "properties": {
    "iso:country":"US",
    "sg:address":"8626 Berrywest Ct",
    "sg:city":"San Antonio",
    "sg:classifiers":[
        {
            "category":"Building & Trades",
            "subcategory":"Construction",
            "type":"Services"
        }
    ],
    "sg:phone":"+1 210 558 7635",
    "sg:postcode":"78240",
    "sg:province":"TX",
    "sg:tags":[
        "home",
        "remodeling"
    ],
    "wof:name":"Butler Remodeling",
    "wof:placetype":"venue"
},
  "geometry": {"coordinates":[-98.613731,29.521833],"type":"Point"}
}