{
  "type": "Feature",
  "properties": {
    "iso:country":"US",
    "sg:address":"224 S Caddo St",
    "sg:city":"Lipan",
    "sg:classifiers":[
        {
            "category":"Wholesale",
            "subcategory":"Hardware",
            "type":"Manufacturing & Wholesale Goods"
        }
    ],
    "sg:phone":"+1 254 646 2783",
    "sg:postcode":"76462",
    "sg:province":"TX",
    "wof:name":"Matlock Tool Sales",
    "wof:placetype":"venue"
},
  "geometry": {"coordinates":[-98.049057,32.514549],"type":"Point"}
}