{
  "type": "Feature",
  "properties": {
    "iso:country":"US",
    "sg:address":"5682 E I- 20",
    "sg:city":"Abilene",
    "sg:classifiers":[
        {
            "category":"Manufacturing",
            "subcategory":"Printing",
            "type":"Manufacturing & Wholesale Goods"
        }
    ],
    "sg:phone":"+1 325 672 1402",
    "sg:postcode":"79601",
    "sg:province":"TX",
    "sg:tags":[
        "screen"
    ],
    "wof:name":"James Garner & Son's Screen",
    "wof:placetype":"venue"
},
  "geometry": {"coordinates":[-99.62850400000001,32.436813],"type":"Point"}
}