{
  "type": "Feature",
  "properties": {
    "iso:country":"US",
    "sg:address":"3202 Olton Rd",
    "sg:city":"Plainview",
    "sg:classifiers":[
        {
            "category":"Insurance",
            "subcategory":"Insurance Agent",
            "type":"Services"
        }
    ],
    "sg:phone":"+1 806 293 8845",
    "sg:postcode":"79072",
    "sg:province":"TX",
    "wof:name":"AFLAC",
    "wof:placetype":"venue"
},
  "geometry": {"coordinates":[-101.74295499999999,34.18566],"type":"Point"}
}