{
  "type": "Feature",
  "properties": {
    "iso:country":"US",
    "sg:address":"130 Express St",
    "sg:city":"Dallas",
    "sg:classifiers":[
        {
            "category":"Shopping",
            "subcategory":"Optical Goods",
            "type":"Retail Goods"
        }
    ],
    "sg:phone":"+1 214 741 6660",
    "sg:postcode":"75207",
    "sg:province":"TX",
    "sg:tags":[
        "optician",
        "eyewear"
    ],
    "wof:name":"Optical Factory the",
    "wof:placetype":"venue"
},
  "geometry": {"coordinates":[-96.82849899999999,32.793701],"type":"Point"}
}