{
  "type": "Feature",
  "properties": {
    "iso:country":"US",
    "sg:address":"7421 Mesquite Ln",
    "sg:city":"Kaufman",
    "sg:classifiers":[
        {
            "category":"Professional",
            "type":"Services"
        }
    ],
    "sg:phone":"+1 972 962 6749",
    "sg:postcode":"75142",
    "sg:province":"TX",
    "wof:name":"Bmg Inc",
    "wof:placetype":"venue"
},
  "geometry": {"coordinates":[-96.240855,32.542267],"type":"Point"}
}