{
  "type": "Feature",
  "properties": {
    "iso:country":"US",
    "sg:address":"1600 Shepherd Dr",
    "sg:city":"Houston",
    "sg:classifiers":[
        {
            "category":"Personal",
            "type":"Services"
        }
    ],
    "sg:phone":"+1 713 802 9808",
    "sg:postcode":"77007",
    "sg:province":"TX",
    "sg:tags":[
        "shop",
        "beauty"
    ],
    "wof:name":"Heavenlee Hands By Betty",
    "wof:placetype":"venue"
},
  "geometry": {"coordinates":[-95.409543,29.775565],"type":"Point"}
}