{
  "type": "Feature",
  "properties": {
    "iso:country":"US",
    "sg:address":"13018 Woodforest Blvd",
    "sg:city":"Houston",
    "sg:classifiers":[
        {
            "category":"Banks & Credit Unions",
            "subcategory":"Investment Brokerage",
            "type":"Services"
        }
    ],
    "sg:phone":"+1 713 899 0285",
    "sg:postcode":"77015",
    "sg:province":"TX",
    "sg:tags":[
        "advisory",
        "financial"
    ],
    "wof:name":"Amerigos Financial Inc",
    "wof:placetype":"venue"
},
  "geometry": {"coordinates":[-95.193668,29.794034],"type":"Point"}
}