{
  "type": "Feature",
  "properties": {
    "iso:country":"US",
    "sg:address":"1915 W Harris Rd",
    "sg:city":"Arlington",
    "sg:classifiers":[
        {
            "category":"Banks & Credit Unions",
            "subcategory":"Financial Services",
            "type":"Services"
        }
    ],
    "sg:phone":"+1 817 467 0937",
    "sg:postcode":"76001",
    "sg:province":"TX",
    "sg:tags":[
        "investor"
    ],
    "wof:name":"Calm Harbor Investments Inc",
    "wof:placetype":"venue"
},
  "geometry": {"coordinates":[-97.136105,32.626988],"type":"Point"}
}