{
  "type": "Feature",
  "properties": {
    "iso:country":"US",
    "sg:address":"2120 W 34th St",
    "sg:city":"Houston",
    "sg:classifiers":[
        {
            "category":"Shopping",
            "subcategory":"Pets & Pet Supplies",
            "type":"Retail Goods"
        },
        {
            "category":"Retail",
            "subcategory":"Veterinary Services",
            "type":"Services"
        },
        {
            "category":"Retail",
            "subcategory":"Pet Boarding",
            "type":"Services"
        }
    ],
    "sg:phone":"+1 713 682 6351",
    "sg:postcode":"77018",
    "sg:province":"TX",
    "sg:tags":[
        "veterinarian",
        "boarding/pet",
        "groomers",
        "sitting"
    ],
    "sg:website":"www.oakforestvetclinic.com",
    "wof:name":"Oak Forest Veterinary Clinic",
    "wof:placetype":"venue"
},
  "geometry": {"coordinates":[-95.43710299999999,29.8174],"type":"Point"}
}