{
  "type": "Feature",
  "properties": {
    "iso:country":"US",
    "sg:address":"1439 Mack Dr",
    "sg:city":"Jefferson",
    "sg:classifiers":[
        {
            "category":"Manufacturing",
            "subcategory":"Lumber",
            "type":"Manufacturing & Wholesale Goods"
        }
    ],
    "sg:phone":"+1 903 672 3380",
    "sg:postcode":"75683",
    "sg:province":"TX",
    "sg:tags":[
        "mill"
    ],
    "wof:name":"Rogers Saw Mill",
    "wof:placetype":"venue"
},
  "geometry": {"coordinates":[-94.712858,32.844647],"type":"Point"}
}