{
  "type": "Feature",
  "properties": {
    "iso:country":"US",
    "sg:address":"10501 State Hwy 150",
    "sg:city":"Shepherd",
    "sg:classifiers":[
        {
            "category":"Building & Trades",
            "subcategory":"Plumbing",
            "type":"Services"
        }
    ],
    "sg:phone":"+1 936 628 3330",
    "sg:postcode":"77371",
    "sg:province":"TX",
    "sg:tags":[
        "conditioning",
        "air",
        "system",
        "contractor"
    ],
    "wof:name":"Bullock Air Cond & Electrical",
    "wof:placetype":"venue"
},
  "geometry": {"coordinates":[-95.006838,30.50017],"type":"Point"}
}