{
  "type": "Feature",
  "properties": {
    "iso:country":"US",
    "sg:address":"1493 el Indio Hwy",
    "sg:city":"Eagle Pass",
    "sg:classifiers":[
        {
            "category":"Food & Beverages",
            "subcategory":"Groceries & Convenience Stores",
            "type":"Retail Goods"
        }
    ],
    "sg:phone":"+1 830 773 2703",
    "sg:postcode":"78852",
    "sg:province":"TX",
    "sg:tags":[
        "product",
        "snack"
    ],
    "wof:name":"Tom's Foods Inc",
    "wof:placetype":"venue"
},
  "geometry": {"coordinates":[-100.494444,28.701632],"type":"Point"}
}