{
  "type": "Feature",
  "properties": {
    "iso:country":"US",
    "sg:address":"6205 Coit Rd",
    "sg:city":"Plano",
    "sg:classifiers":[
        {
            "category":"Restaurant",
            "type":"Food & Drink"
        }
    ],
    "sg:phone":"+1 972 612 3800",
    "sg:postcode":"75024",
    "sg:province":"TX",
    "sg:tags":[
        "mexican"
    ],
    "wof:name":"Juabangos",
    "wof:placetype":"venue"
},
  "geometry": {"coordinates":[-96.770557,33.057995],"type":"Point"}
}