{
  "type": "Feature",
  "properties": {
    "iso:country":"US",
    "sg:address":"409 S Morgan St",
    "sg:city":"Granbury",
    "sg:classifiers":[
        {
            "category":"Health Services",
            "subcategory":"Doctor",
            "type":"Services"
        }
    ],
    "sg:phone":"+1 817 579 0177",
    "sg:postcode":"76048",
    "sg:province":"TX",
    "sg:tags":[
        "dental"
    ],
    "wof:name":"Kyle W Rogers D D S Inc",
    "wof:placetype":"venue"
},
  "geometry": {"coordinates":[-97.794185,32.439381],"type":"Point"}
}