{
  "type": "Feature",
  "properties": {
    "iso:country":"US",
    "sg:address":"7126 Orville St",
    "sg:city":"Houston",
    "sg:classifiers":[
        {
            "category":"Food & Beverages",
            "subcategory":"Bakery",
            "type":"Retail Goods"
        }
    ],
    "sg:phone":"+1 713 633 4984",
    "sg:postcode":"77028",
    "sg:province":"TX",
    "wof:name":"Cakes By Vernell",
    "wof:placetype":"venue"
},
  "geometry": {"coordinates":[-95.29835799999999,29.832603],"type":"Point"}
}