{
  "type": "Feature",
  "properties": {
    "iso:country":"US",
    "sg:address":"2300 Pool Rd",
    "sg:city":"Grapevine",
    "sg:classifiers":[
        {
            "category":"Health Services",
            "subcategory":"Clinic",
            "type":"Services"
        },
        {
            "category":"Health Services",
            "subcategory":"Nursing And Care Facility",
            "type":"Services"
        },
        {
            "category":"Health Services",
            "subcategory":"Health Practitioner",
            "type":"Services"
        }
    ],
    "sg:phone":"+1 817 310 3708",
    "sg:postcode":"76051",
    "sg:province":"TX",
    "sg:tags":[
        "home",
        "eldercare-home",
        "welfare"
    ],
    "wof:name":"Grace Home Health",
    "wof:placetype":"venue"
},
  "geometry": {"coordinates":[-97.12586400000001,32.913733],"type":"Point"}
}