{
  "type": "Feature",
  "properties": {
    "iso:country":"US",
    "sg:address":"1323 N Ave F",
    "sg:city":"Freeport",
    "sg:classifiers":[
        {
            "category":"Shopping",
            "subcategory":"Used Merchandise",
            "type":"Retail Goods"
        }
    ],
    "sg:phone":"+1 979 233 6991",
    "sg:postcode":"77541",
    "sg:province":"TX",
    "wof:name":"Wise Enterprises",
    "wof:placetype":"venue"
},
  "geometry": {"coordinates":[-95.371831,28.971084],"type":"Point"}
}