{
  "type": "Feature",
  "properties": {
    "iso:country":"US",
    "sg:address":"700 Lavaca Ste 405",
    "sg:city":"Austin",
    "sg:classifiers":[
        {
            "category":"Professional",
            "subcategory":"Lawyer & Legal Services",
            "type":"Services"
        }
    ],
    "sg:phone":"+1 512 478 0006",
    "sg:postcode":"78701",
    "sg:province":"TX",
    "sg:tags":[
        "litigation",
        "attorney",
        "family",
        "divorce",
        "law"
    ],
    "sg:website":"www.lipshylaw.com",
    "wof:name":"Lipshy & Escamilla, LLP",
    "wof:placetype":"venue"
},
  "geometry": {"coordinates":[-97.74523000000001,30.270284],"type":"Point"}
}