{
  "type": "Feature",
  "properties": {
    "iso:country":"US",
    "sg:address":"908 Lathrop St",
    "sg:city":"Houston",
    "sg:classifiers":[
        {
            "category":"Cinema",
            "subcategory":"Movie Rental",
            "type":"Entertainment"
        }
    ],
    "sg:phone":"+1 713 672 2800",
    "sg:postcode":"77020",
    "sg:province":"TX",
    "sg:tags":[
        "video",
        "tape"
    ],
    "wof:name":"Lathrop Laundromat",
    "wof:placetype":"venue"
},
  "geometry": {"coordinates":[-95.301227,29.772332],"type":"Point"}
}