{
  "type": "Feature",
  "properties": {
    "iso:country":"US",
    "sg:address":"1101 State Hwy 6",
    "sg:city":"Houston",
    "sg:classifiers":[
        {
            "category":"Health Services",
            "subcategory":"Doctor",
            "type":"Services"
        }
    ],
    "sg:phone":"+1 281 498 3566",
    "sg:postcode":"77077",
    "sg:province":"TX",
    "sg:tags":[
        "physician",
        "orthopedic"
    ],
    "wof:name":"Dafonte Medical Services LLC",
    "wof:placetype":"venue"
},
  "geometry": {"coordinates":[-95.64375,29.767629],"type":"Point"}
}