{
  "type": "Feature",
  "properties": {
    "iso:country":"US",
    "sg:address":"3314 Branard St",
    "sg:city":"Houston",
    "sg:classifiers":[
        {
            "category":"Shopping",
            "type":"Retail Goods"
        }
    ],
    "sg:phone":"+1 713 524 4924",
    "sg:postcode":"77098",
    "sg:province":"TX",
    "sg:tags":[
        "miscellaneous",
        "store"
    ],
    "wof:name":"Russell Frame Shop",
    "wof:placetype":"venue"
},
  "geometry": {"coordinates":[-95.42703400000001,29.736583],"type":"Point"}
}