{
  "type": "Feature",
  "properties": {
    "iso:country":"US",
    "sg:address":"5150 State Hwy 1604",
    "sg:city":"San Antonio",
    "sg:classifiers":[
        {
            "category":"Banks & Credit Unions",
            "subcategory":"Bank",
            "type":"Services"
        }
    ],
    "sg:phone":"+1 210 493 3095",
    "sg:postcode":"78249",
    "sg:province":"TX",
    "sg:tags":[
        "banker",
        "mortgage"
    ],
    "wof:name":"Cbh Mortgage Inc",
    "wof:placetype":"venue"
},
  "geometry": {"coordinates":[-98.586941,29.592017],"type":"Point"}
}