{
  "type": "Feature",
  "properties": {
    "iso:country":"US",
    "sg:address":"3220 S Port Ave",
    "sg:city":"Corpus Christi",
    "sg:classifiers":[
        {
            "category":"Professional",
            "subcategory":"Employment Agencies",
            "type":"Services"
        }
    ],
    "sg:phone":"+1 361 882 8880",
    "sg:postcode":"78415",
    "sg:province":"TX",
    "sg:tags":[
        "temp",
        "labor"
    ],
    "wof:name":"Labor Ready",
    "wof:placetype":"venue"
},
  "geometry": {"coordinates":[-97.42008,27.761955],"type":"Point"}
}