{
  "type": "Feature",
  "properties": {
    "iso:country":"US",
    "sg:address":"5116 E Fm 4",
    "sg:city":"Grandview",
    "sg:classifiers":[
        {
            "category":"Building & Trades",
            "subcategory":"Landscaping Services",
            "type":"Services"
        }
    ],
    "sg:phone":"+1 817 714 3283",
    "sg:postcode":"76050",
    "sg:province":"TX",
    "sg:tags":[
        "lawn"
    ],
    "wof:name":"Rich Port Landscape",
    "wof:placetype":"venue"
},
  "geometry": {"coordinates":[-97.26702899999999,32.312374],"type":"Point"}
}