{
  "type": "Feature",
  "properties": {
    "iso:country":"US",
    "sg:address":"15301 Greg St",
    "sg:city":"Amarillo",
    "sg:classifiers":[
        {
            "category":"Freight",
            "type":"Transportation"
        }
    ],
    "sg:phone":"+1 806 655 7222",
    "sg:postcode":"79118",
    "sg:province":"TX",
    "sg:tags":[
        "mobile",
        "home",
        "transport"
    ],
    "wof:name":"Scarecrow Inc",
    "wof:placetype":"venue"
},
  "geometry": {"coordinates":[-101.909205,35.043223],"type":"Point"}
}