{
  "type": "Feature",
  "properties": {
    "iso:country":"US",
    "sg:address":"5005 Riverway Dr",
    "sg:city":"Houston",
    "sg:classifiers":[
        {
            "category":"Real Estate",
            "subcategory":"Real Estate Operator",
            "type":"Services"
        }
    ],
    "sg:phone":"+1 713 621 6477",
    "sg:postcode":"77056",
    "sg:province":"TX",
    "sg:tags":[
        "commercial"
    ],
    "wof:name":"Arlington Oaks",
    "wof:placetype":"venue"
},
  "geometry": {"coordinates":[-95.465597,29.761211],"type":"Point"}
}