{
  "type": "Feature",
  "properties": {
    "iso:country":"US",
    "sg:address":"10109 Long Point Rd",
    "sg:city":"Houston",
    "sg:classifiers":[
        {
            "category":"Retail",
            "subcategory":"Veterinary Services",
            "type":"Services"
        }
    ],
    "sg:phone":"+1 713 461 2511",
    "sg:postcode":"77043",
    "sg:province":"TX",
    "sg:tags":[
        "veterinarian"
    ],
    "wof:name":"A-C & D Veterinary Clinic",
    "wof:placetype":"venue"
},
  "geometry": {"coordinates":[-95.545502,29.7941],"type":"Point"}
}