{
  "type": "Feature",
  "properties": {
    "iso:country":"US",
    "sg:address":"5055 Burke Rd",
    "sg:city":"Pasadena",
    "sg:classifiers":[
        {
            "category":"Home & Garden",
            "subcategory":"Building Materials",
            "type":"Retail Goods"
        }
    ],
    "sg:phone":"+1 281 487 7009",
    "sg:postcode":"77504",
    "sg:province":"TX",
    "sg:tags":[
        "portable"
    ],
    "wof:name":"Precision Structures Inc",
    "wof:placetype":"venue"
},
  "geometry": {"coordinates":[-95.18123799999999,29.635753],"type":"Point"}
}