{
  "type": "Feature",
  "properties": {
    "iso:country":"US",
    "sg:address":"7824 Robincreek Dr",
    "sg:city":"Dallas",
    "sg:classifiers":[
        {
            "category":"Professional",
            "type":"Services"
        }
    ],
    "sg:phone":"+1 214 946 7578",
    "sg:postcode":"75232",
    "sg:province":"TX",
    "wof:name":"Paul Childs Designs",
    "wof:placetype":"venue"
},
  "geometry": {"coordinates":[-96.82957500000001,32.653121],"type":"Point"}
}