{
  "type": "Feature",
  "properties": {
    "iso:country":"US",
    "sg:address":"535 N Park St",
    "sg:city":"Uvalde",
    "sg:classifiers":[
        {
            "category":"Health Services",
            "subcategory":"Nursing And Care Facility",
            "type":"Services"
        }
    ],
    "sg:phone":"+1 830 278 2505",
    "sg:postcode":"78801",
    "sg:province":"TX",
    "sg:tags":[
        "home",
        "convalescent"
    ],
    "wof:name":"Uvalde Healthcare",
    "wof:placetype":"venue"
},
  "geometry": {"coordinates":[-99.79339899999999,29.214953],"type":"Point"}
}