{
  "type": "Feature",
  "properties": {
    "iso:country":"US",
    "sg:address":"714 N Bedell Ave",
    "sg:city":"Del Rio",
    "sg:classifiers":[
        {
            "category":"Shopping",
            "subcategory":"Pharmacy",
            "type":"Retail Goods"
        }
    ],
    "sg:phone":"+1 830 774 5303",
    "sg:postcode":"78840",
    "sg:province":"TX",
    "wof:name":"Vital Care of SW Texas",
    "wof:placetype":"venue"
},
  "geometry": {"coordinates":[-100.892293,29.373714],"type":"Point"}
}