{
  "type": "Feature",
  "properties": {
    "iso:country":"US",
    "sg:address":"244 N Commerce St",
    "sg:city":"Burleson",
    "sg:classifiers":[
        {
            "category":"Autos & Motor Vehicles",
            "subcategory":"Automobile Sales",
            "type":"Retail Goods"
        }
    ],
    "sg:phone":"+1 817 295 3240",
    "sg:postcode":"76028",
    "sg:province":"TX",
    "sg:tags":[
        "car",
        "dealer"
    ],
    "wof:name":"Clearmark Truck & Auto Sales",
    "wof:placetype":"venue"
},
  "geometry": {"coordinates":[-97.320457,32.545357],"type":"Point"}
}