{
  "type": "Feature",
  "properties": {
    "iso:country":"US",
    "sg:address":"907 Old Austin Hutto Rd",
    "sg:city":"Pflugerville",
    "sg:classifiers":[
        {
            "category":"Building & Trades",
            "subcategory":"Landscaping Services",
            "type":"Services"
        }
    ],
    "sg:phone":"+1 512 251 0190",
    "sg:postcode":"78660",
    "sg:province":"TX",
    "sg:tags":[
        "landscape",
        "contractor"
    ],
    "wof:name":"Austin Nursery & Landscape",
    "wof:placetype":"venue"
},
  "geometry": {"coordinates":[-97.607169,30.44311],"type":"Point"}
}