{
  "type": "Feature",
  "properties": {
    "iso:country":"US",
    "sg:address":"7974 Ann Ln",
    "sg:city":"Silsbee",
    "sg:classifiers":[
        {
            "category":"Social Services",
            "type":"Services"
        },
        {
            "category":"Professional",
            "subcategory":"Employment Agencies",
            "type":"Services"
        }
    ],
    "sg:phone":"+1 409 386 0837",
    "sg:postcode":"77656",
    "sg:province":"TX",
    "sg:tags":[
        "workers'",
        "placement",
        "volunteer"
    ],
    "wof:name":"Macon Macon Foundation Spec",
    "wof:placetype":"venue"
},
  "geometry": {"coordinates":[-94.17925,30.403664],"type":"Point"}
}