{
  "type": "Feature",
  "properties": {
    "iso:country":"US",
    "sg:address":"3809 Miller Rd",
    "sg:city":"Rowlett",
    "sg:classifiers":[
        {
            "category":"Retail",
            "subcategory":"Laundry & Dry Cleaning",
            "type":"Services"
        }
    ],
    "sg:phone":"+1 214 607 4949",
    "sg:postcode":"75088",
    "sg:province":"TX",
    "sg:tags":[
        "carpet"
    ],
    "wof:name":"Response Restoration",
    "wof:placetype":"venue"
},
  "geometry": {"coordinates":[-96.565866,32.893855],"type":"Point"}
}