{
  "type": "Feature",
  "properties": {
    "iso:country":"US",
    "sg:address":"512 S Main St",
    "sg:city":"Ferris",
    "sg:classifiers":[
        {
            "category":"Personal",
            "subcategory":"Beauty Salon",
            "type":"Services"
        }
    ],
    "sg:phone":"+1 972 449 3300",
    "sg:postcode":"75125",
    "sg:province":"TX",
    "sg:tags":[
        "hair",
        "shop",
        "stylist"
    ],
    "wof:name":"Joey's House Of Style",
    "wof:placetype":"venue"
},
  "geometry": {"coordinates":[-96.665256,32.530896],"type":"Point"}
}