{
  "type": "Feature",
  "properties": {
    "iso:country":"US",
    "sg:address":"1313 Hillcrest Dr N",
    "sg:city":"Sulphur Springs",
    "sg:classifiers":[
        {
            "category":"Government",
            "subcategory":"Office",
            "type":"Public Place"
        }
    ],
    "sg:phone":"+1 903 438 9369",
    "sg:postcode":"75482",
    "sg:province":"TX",
    "sg:tags":[
        "village"
    ],
    "wof:name":"Control Animal",
    "wof:placetype":"venue"
},
  "geometry": {"coordinates":[-95.61302000000001,33.15788],"type":"Point"}
}