{
  "type": "Feature",
  "properties": {
    "iso:country":"US",
    "sg:address":"916 Fannin St",
    "sg:city":"Columbus",
    "sg:classifiers":[
        {
            "category":"Organizations",
            "subcategory":"Religious Organization",
            "type":"Services"
        }
    ],
    "sg:phone":"+1 979 732 3653",
    "sg:postcode":"78934",
    "sg:province":"TX",
    "sg:tags":[
        "church"
    ],
    "wof:name":"St Paul United Methodist Chr",
    "wof:placetype":"venue"
},
  "geometry": {"coordinates":[-96.546959,29.708125],"type":"Point"}
}