{
  "type": "Feature",
  "properties": {
    "iso:country":"US",
    "sg:address":"10101 US Hwy 87",
    "sg:city":"Lubbock",
    "sg:classifiers":[
        {
            "category":"Food & Beverages",
            "subcategory":"Liquor & Beverages",
            "type":"Retail Goods"
        }
    ],
    "sg:phone":"+1 806 745 1515",
    "sg:postcode":"79423",
    "sg:province":"TX",
    "sg:tags":[
        "alcoholic"
    ],
    "wof:name":"Docs Liquor Store",
    "wof:placetype":"venue"
},
  "geometry": {"coordinates":[-101.84466399999999,33.49861],"type":"Point"}
}