{
  "type": "Feature",
  "properties": {
    "iso:country":"US",
    "sg:address":"821 Capitol Ave",
    "sg:city":"San Antonio",
    "sg:classifiers":[
        {
            "category":"Retail",
            "subcategory":"Auto Repair",
            "type":"Services"
        }
    ],
    "sg:phone":"+1 210 320 4957",
    "sg:postcode":"78201",
    "sg:province":"TX",
    "sg:tags":[
        "truck"
    ],
    "wof:name":"J & A Truck Repair",
    "wof:placetype":"venue"
},
  "geometry": {"coordinates":[-98.51393899999999,29.459436],"type":"Point"}
}