{
  "type": "Feature",
  "properties": {
    "iso:country":"US",
    "sg:address":"701 Rein Dr",
    "sg:city":"Killeen",
    "sg:classifiers":[
        {
            "category":"Shopping",
            "type":"Retail Goods"
        }
    ],
    "sg:phone":"+1 254 526 6394",
    "sg:postcode":"76542",
    "sg:province":"TX",
    "sg:tags":[
        "miscellaneous",
        "store"
    ],
    "wof:name":"Coddington's Corner",
    "wof:placetype":"venue"
},
  "geometry": {"coordinates":[-97.7509,31.062833],"type":"Point"}
}