{
  "type": "Feature",
  "properties": {
    "iso:country":"US",
    "sg:address":"1925 Bear Springs Dr",
    "sg:city":"Haslet",
    "sg:classifiers":[
        {
            "category":"Restaurant",
            "type":"Food & Drink"
        }
    ],
    "sg:phone":"+1 817 825 4514",
    "sg:postcode":"76052",
    "sg:province":"TX",
    "wof:name":"Personal Pizazz",
    "wof:placetype":"venue"
},
  "geometry": {"coordinates":[-97.401977,32.977834],"type":"Point"}
}