{
  "type": "Feature",
  "properties": {
    "iso:country":"US",
    "sg:address":"725 Randolph Cir",
    "sg:city":"Beaumont",
    "sg:classifiers":[
        {
            "category":"Shopping",
            "subcategory":"Computers & Home Electronics",
            "type":"Retail Goods"
        }
    ],
    "sg:phone":"+1 409 866 5734",
    "sg:postcode":"77706",
    "sg:province":"TX",
    "wof:name":"Computer Helper of Beaumo",
    "wof:placetype":"venue"
},
  "geometry": {"coordinates":[-94.172459,30.082144],"type":"Point"}
}