{
  "type": "Feature",
  "properties": {
    "iso:country":"US",
    "sg:address":"1121 Capitol St",
    "sg:city":"Houston",
    "sg:classifiers":[
        {
            "category":"Professional",
            "subcategory":"Lawyer & Legal Services",
            "type":"Services"
        }
    ],
    "sg:phone":"+1 713 236 8600",
    "sg:postcode":"77002",
    "sg:province":"TX",
    "sg:tags":[
        "attorney"
    ],
    "wof:name":"Baker & Baker",
    "wof:placetype":"venue"
},
  "geometry": {"coordinates":[-95.361507,29.75832],"type":"Point"}
}