{
  "type": "Feature",
  "properties": {
    "iso:country":"US",
    "sg:address":"202 S 1st St",
    "sg:city":"Copperas Cove",
    "sg:classifiers":[
        {
            "category":"Building & Trades",
            "subcategory":"Construction",
            "type":"Services"
        }
    ],
    "sg:phone":"+1 254 547 0172",
    "sg:postcode":"76522",
    "sg:province":"TX",
    "sg:tags":[
        "home",
        "builder"
    ],
    "sg:website":"www.donlierealestate.com",
    "wof:name":"Donlie Mc Mullin Real Estate",
    "wof:placetype":"venue"
},
  "geometry": {"coordinates":[-97.90404100000001,31.123502],"type":"Point"}
}