{
  "type": "Feature",
  "properties": {
    "iso:country":"US",
    "sg:address":"2233 Austin Hwy",
    "sg:city":"San Antonio",
    "sg:classifiers":[
        {
            "category":"Manufacturing",
            "subcategory":"Buildings",
            "type":"Manufacturing & Wholesale Goods"
        }
    ],
    "sg:phone":"+1 210 507 9096",
    "sg:postcode":"78218",
    "sg:province":"TX",
    "sg:tags":[
        "mobile",
        "home",
        "mfg"
    ],
    "wof:name":"Fleetwood Dealer",
    "wof:placetype":"venue"
},
  "geometry": {"coordinates":[-98.41399,29.505614],"type":"Point"}
}