{
  "type": "Feature",
  "properties": {
    "iso:country":"US",
    "sg:address":"7109 N 25th Ln",
    "sg:city":"Mcallen",
    "sg:classifiers":[
        {
            "category":"Home & Garden",
            "subcategory":"Building Materials",
            "type":"Retail Goods"
        }
    ],
    "sg:phone":"+1 956 664 2101",
    "sg:postcode":"78504",
    "sg:province":"TX",
    "wof:name":"A-1 Garage Doors",
    "wof:placetype":"venue"
},
  "geometry": {"coordinates":[-98.237557,26.273161],"type":"Point"}
}