{
  "type": "Feature",
  "properties": {
    "iso:country":"US",
    "sg:address":"2307 Las Cruces Ln",
    "sg:city":"Dallas",
    "sg:classifiers":[
        {
            "category":"Professional",
            "subcategory":"Management & Consulting",
            "type":"Services"
        }
    ],
    "sg:phone":"+1 214 388 0253",
    "sg:postcode":"75227",
    "sg:province":"TX",
    "sg:tags":[
        "retail",
        "direct",
        "sales"
    ],
    "wof:name":"Cheryl Ann Mick Artist",
    "wof:placetype":"venue"
},
  "geometry": {"coordinates":[-96.692644,32.754613],"type":"Point"}
}