{
  "type": "Feature",
  "properties": {
    "iso:country":"US",
    "sg:address":"1003 Ash St",
    "sg:city":"Plainview",
    "sg:classifiers":[
        {
            "category":"Retail",
            "subcategory":"Auto Repair",
            "type":"Services"
        }
    ],
    "sg:phone":"+1 806 293 5633",
    "sg:postcode":"79072",
    "sg:province":"TX",
    "sg:tags":[
        "shop",
        "automotive"
    ],
    "wof:name":"Bill Brown Brake & Alignment",
    "wof:placetype":"venue"
},
  "geometry": {"coordinates":[-101.701896,34.192378],"type":"Point"}
}