{
  "type": "Feature",
  "properties": {
    "iso:country":"US",
    "sg:address":"209 Fairway Dr",
    "sg:city":"Gatesville",
    "sg:classifiers":[
        {
            "category":"Organizations",
            "subcategory":"Community Association",
            "type":"Services"
        }
    ],
    "sg:phone":"+1 254 865 5809",
    "sg:postcode":"76528",
    "sg:province":"TX",
    "wof:name":"TX Assoc Community College",
    "wof:placetype":"venue"
},
  "geometry": {"coordinates":[-97.725067,31.407973],"type":"Point"}
}