{
  "type": "Feature",
  "properties": {
    "iso:country":"US",
    "sg:address":"15158 Grassington Dr",
    "sg:city":"Channelview",
    "sg:classifiers":[
        {
            "category":"Professional",
            "subcategory":"Business Services",
            "type":"Services"
        }
    ],
    "sg:phone":"+1 281 452 1402",
    "sg:postcode":"77530",
    "sg:province":"TX",
    "wof:name":"Nicherson Enterprises",
    "wof:placetype":"venue"
},
  "geometry": {"coordinates":[-95.147666,29.789796],"type":"Point"}
}