{
  "type": "Feature",
  "properties": {
    "iso:country":"US",
    "sg:address":"16006 Coe Loop",
    "sg:city":"Magnolia",
    "sg:classifiers":[
        {
            "category":"Banks & Credit Unions",
            "subcategory":"Financial Services",
            "type":"Services"
        }
    ],
    "sg:phone":"+1 281 259 4662",
    "sg:postcode":"77355",
    "sg:province":"TX",
    "sg:tags":[
        "trust",
        "management"
    ],
    "wof:name":"Vann Oil Field Services Inc",
    "wof:placetype":"venue"
},
  "geometry": {"coordinates":[-95.717336,30.110382],"type":"Point"}
}