{
  "type": "Feature",
  "properties": {
    "iso:country":"US",
    "sg:address":"2221 Vivroux Ranch Rd",
    "sg:city":"Seguin",
    "sg:classifiers":[
        {
            "category":"Building & Trades",
            "subcategory":"Construction",
            "type":"Services"
        }
    ],
    "sg:phone":"+1 830 379 0009",
    "sg:postcode":"78155",
    "sg:province":"TX",
    "sg:tags":[
        "bulldozing"
    ],
    "wof:name":"David Jackson Bulldozing Svc",
    "wof:placetype":"venue"
},
  "geometry": {"coordinates":[-97.803258,29.499825],"type":"Point"}
}