{
  "type": "Feature",
  "properties": {
    "iso:country":"US",
    "sg:address":"6258 State Hwy 6",
    "sg:city":"Missouri City",
    "sg:classifiers":[
        {
            "category":"Shopping",
            "type":"Retail Goods"
        },
        {
            "category":"Building & Trades",
            "subcategory":"Construction",
            "type":"Services"
        }
    ],
    "sg:phone":"+1 281 403 1946",
    "sg:postcode":"77459",
    "sg:province":"TX",
    "sg:tags":[
        "designer",
        "contractor",
        "merchandise",
        "dealer",
        "pool",
        "swimming"
    ],
    "wof:name":"Anthony & Sylvan Pools Corp",
    "wof:placetype":"venue"
},
  "geometry": {"coordinates":[-95.56456799999999,29.565696],"type":"Point"}
}