{
  "type": "Feature",
  "properties": {
    "iso:country":"US",
    "sg:address":"2320 S Lamar Blvd",
    "sg:city":"Austin",
    "sg:classifiers":[
        {
            "category":"Shopping",
            "subcategory":"Bicycles & Sporting Goods",
            "type":"Retail Goods"
        }
    ],
    "sg:phone":"+1 512 916 4653",
    "sg:postcode":"78704",
    "sg:province":"TX",
    "sg:website":"http://www.teegolfclub.com",
    "wof:name":"The Golf Club",
    "wof:placetype":"venue"
},
  "geometry": {"coordinates":[-97.775479,30.247553],"type":"Point"}
}