{
  "type": "Feature",
  "properties": {
    "iso:country":"US",
    "sg:address":"4741 State Hwy 6",
    "sg:city":"Houston",
    "sg:classifiers":[
        {
            "category":"Shopping",
            "subcategory":"Computers & Home Electronics",
            "type":"Retail Goods"
        }
    ],
    "sg:phone":"+1 281 463 6865",
    "sg:postcode":"77084",
    "sg:province":"TX",
    "wof:name":"Radio Shack",
    "wof:placetype":"venue"
},
  "geometry": {"coordinates":[-95.645796,29.84492],"type":"Point"}
}