{
  "type": "Feature",
  "properties": {
    "iso:country":"US",
    "sg:address":"114 Mamie Dr",
    "sg:city":"Malakoff",
    "sg:classifiers":[
        {
            "category":"Shopping",
            "subcategory":"Hobbies, Toys, & Games",
            "type":"Retail Goods"
        }
    ],
    "sg:phone":"+1 903 489 1363",
    "sg:postcode":"75148",
    "sg:province":"TX",
    "wof:name":"End of Trail Sales",
    "wof:placetype":"venue"
},
  "geometry": {"coordinates":[-96.026021,32.231474],"type":"Point"}
}