{
  "type": "Feature",
  "properties": {
    "iso:country":"US",
    "sg:address":"922 14th St N",
    "sg:city":"Texas City",
    "sg:classifiers":[
        {
            "category":"Insurance",
            "subcategory":"Insurance Agent",
            "type":"Services"
        }
    ],
    "sg:phone":"+1 409 948 3456",
    "sg:postcode":"77590",
    "sg:province":"TX",
    "wof:name":"State Farm Insurance",
    "wof:placetype":"venue"
},
  "geometry": {"coordinates":[-94.914731,29.394328],"type":"Point"}
}