{
  "type": "Feature",
  "properties": {
    "iso:country":"US",
    "sg:address":"314 Scarlett Cir",
    "sg:city":"Harlingen",
    "sg:classifiers":[
        {
            "category":"Professional",
            "subcategory":"Detective & Security Services",
            "type":"Services"
        }
    ],
    "sg:phone":"+1 956 440 7780",
    "sg:postcode":"78552",
    "sg:province":"TX",
    "sg:tags":[
        "control",
        "monitoring",
        "system"
    ],
    "wof:name":"Surveillance Solutions",
    "wof:placetype":"venue"
},
  "geometry": {"coordinates":[-97.77069899999999,26.168213],"type":"Point"}
}