{
  "type": "Feature",
  "properties": {
    "iso:country":"US",
    "sg:address":"5200 Hooper Dr",
    "sg:city":"Wichita Falls",
    "sg:classifiers":[
        {
            "category":"Education",
            "subcategory":"School",
            "type":"Public Place"
        }
    ],
    "sg:phone":"+1 940 855 3221",
    "sg:postcode":"76306",
    "sg:province":"TX",
    "wof:name":"John G Tower Elementary School",
    "wof:placetype":"venue"
},
  "geometry": {"coordinates":[-98.52817899999999,33.981445],"type":"Point"}
}