{
  "type": "Feature",
  "properties": {
    "iso:country":"US",
    "sg:address":"906 E Ave D",
    "sg:city":"Robstown",
    "sg:classifiers":[
        {
            "category":"Health Services",
            "subcategory":"Clinic",
            "type":"Services"
        }
    ],
    "sg:phone":"+1 361 816 5613",
    "sg:postcode":"78380",
    "sg:province":"TX",
    "wof:name":"Tejas Medical Equipment",
    "wof:placetype":"venue"
},
  "geometry": {"coordinates":[-97.654848,27.791074],"type":"Point"}
}