{
  "type": "Feature",
  "properties": {
    "iso:country":"US",
    "sg:address":"2922 Highwood Dr",
    "sg:city":"Dallas",
    "sg:classifiers":[
        {
            "category":"Retail",
            "subcategory":"Repair Shop",
            "type":"Services"
        }
    ],
    "sg:phone":"+1 972 279 5390",
    "sg:postcode":"75228",
    "sg:province":"TX",
    "sg:tags":[
        "equipment"
    ],
    "wof:name":"Sawyer Technologies",
    "wof:placetype":"venue"
},
  "geometry": {"coordinates":[-96.66479,32.830205],"type":"Point"}
}