{
  "type": "Feature",
  "properties": {
    "iso:country":"US",
    "sg:address":"2301 Sunny Slope Dr",
    "sg:city":"Austin",
    "sg:classifiers":[
        {
            "category":"Professional",
            "subcategory":"Business Services",
            "type":"Services"
        }
    ],
    "sg:phone":"+1 512 443 6683",
    "sg:postcode":"78703",
    "sg:province":"TX",
    "wof:name":"Cameron Paul Group LLC",
    "wof:placetype":"venue"
},
  "geometry": {"coordinates":[-97.761725,30.298811],"type":"Point"}
}