{
  "type": "Feature",
  "properties": {
    "iso:country":"US",
    "sg:address":"511 W US Hwy 83",
    "sg:city":"Weslaco",
    "sg:classifiers":[
        {
            "category":"Shopping",
            "subcategory":"Discount & Variety Stores",
            "type":"Retail Goods"
        },
        {
            "category":"Shopping",
            "subcategory":"Department Store",
            "type":"Retail Goods"
        }
    ],
    "sg:phone":"+1 956 969 3325",
    "sg:postcode":"78596",
    "sg:province":"TX",
    "sg:tags":[
        "shop"
    ],
    "wof:name":"Family Dollar Stores",
    "wof:placetype":"venue"
},
  "geometry": {"coordinates":[-97.996655,26.16049],"type":"Point"}
}