{
  "type": "Feature",
  "properties": {
    "iso:country":"US",
    "sg:address":"2923 W Northwest Hwy",
    "sg:city":"Dallas",
    "sg:classifiers":[
        {
            "category":"Food & Beverages",
            "subcategory":"Groceries & Convenience Stores",
            "type":"Retail Goods"
        }
    ],
    "sg:phone":"+1 214 902 0673",
    "sg:postcode":"75220",
    "sg:province":"TX",
    "wof:name":"Stop N Go 655",
    "wof:placetype":"venue"
},
  "geometry": {"coordinates":[-96.871797,32.856417],"type":"Point"}
}