{
  "type": "Feature",
  "properties": {
    "iso:country":"US",
    "sg:address":"1205 Case Dr",
    "sg:city":"Mesquite",
    "sg:classifiers":[
        {
            "category":"Home & Garden",
            "subcategory":"Furniture",
            "type":"Retail Goods"
        }
    ],
    "sg:phone":"+1 972 222 0737",
    "sg:postcode":"75181",
    "sg:province":"TX",
    "sg:tags":[
        "bedding"
    ],
    "wof:name":"Oser Mike Enterprises Inc",
    "wof:placetype":"venue"
},
  "geometry": {"coordinates":[-96.561018,32.75327],"type":"Point"}
}