{
  "type": "Feature",
  "properties": {
    "iso:country":"US",
    "sg:address":"6721 Telephone Rd",
    "sg:city":"Houston",
    "sg:classifiers":[
        {
            "category":"Food & Beverages",
            "subcategory":"Groceries & Convenience Stores",
            "type":"Retail Goods"
        }
    ],
    "sg:phone":"+1 713 644 7000",
    "sg:postcode":"77061",
    "sg:province":"TX",
    "wof:name":"Speedy Mart 3",
    "wof:placetype":"venue"
},
  "geometry": {"coordinates":[-95.288803,29.6661],"type":"Point"}
}