{
  "type": "Feature",
  "properties": {
    "iso:country":"US",
    "sg:address":"25200 I- 45",
    "sg:city":"Spring",
    "sg:classifiers":[
        {
            "category":"Building & Trades",
            "subcategory":"Plumbing",
            "type":"Services"
        }
    ],
    "sg:phone":"+1 281 367 4310",
    "sg:postcode":"77386",
    "sg:province":"TX",
    "sg:tags":[
        "conditioning",
        "air",
        "system",
        "contractor"
    ],
    "wof:name":"T's Air-Conditioning & Heating",
    "wof:placetype":"venue"
},
  "geometry": {"coordinates":[-95.443089,30.128968],"type":"Point"}
}