{
  "type": "Feature",
  "properties": {
    "iso:country":"US",
    "sg:address":"1436 Parkwood Dr",
    "sg:city":"Carrollton",
    "sg:classifiers":[
        {
            "category":"Wholesale",
            "subcategory":"Machinery & Supplies",
            "type":"Manufacturing & Wholesale Goods"
        }
    ],
    "sg:phone":"+1 972 395 7738",
    "sg:postcode":"75007",
    "sg:province":"TX",
    "sg:tags":[
        "equipment",
        "establishment"
    ],
    "wof:name":"Curl Floor Equipment & Supply",
    "wof:placetype":"venue"
},
  "geometry": {"coordinates":[-96.92362199999999,33.007835],"type":"Point"}
}