{
  "type": "Feature",
  "properties": {
    "iso:country":"US",
    "sg:address":"1130 E Mulberry Ave",
    "sg:city":"San Antonio",
    "sg:classifiers":[
        {
            "category":"Real Estate",
            "subcategory":"Real Estate Operator",
            "type":"Services"
        }
    ],
    "sg:phone":"+1 210 829 5353",
    "sg:postcode":"78209",
    "sg:province":"TX",
    "sg:tags":[
        "apartment"
    ],
    "wof:name":"Mulberry Hill Apartments",
    "wof:placetype":"venue"
},
  "geometry": {"coordinates":[-98.469204,29.453021],"type":"Point"}
}