{
  "type": "Feature",
  "properties": {
    "iso:country":"US",
    "sg:address":"5150 Broadway",
    "sg:city":"San Antonio",
    "sg:classifiers":[
        {
            "category":"Professional",
            "subcategory":"Art Services",
            "type":"Services"
        }
    ],
    "sg:phone":"+1 210 271 0049",
    "sg:postcode":"78209",
    "sg:province":"TX",
    "sg:tags":[
        "artist"
    ],
    "wof:name":"Citizens For Special Artist",
    "wof:placetype":"venue"
},
  "geometry": {"coordinates":[-98.46268000000001,29.474121],"type":"Point"}
}