{
  "type": "Feature",
  "properties": {
    "iso:country":"US",
    "sg:address":"2659 Manana Dr",
    "sg:city":"Dallas",
    "sg:classifiers":[
        {
            "category":"Wholesale",
            "subcategory":"Machinery & Supplies",
            "type":"Manufacturing & Wholesale Goods"
        }
    ],
    "sg:phone":"+1 214 350 6800",
    "sg:postcode":"75220",
    "sg:province":"TX",
    "sg:tags":[
        "salon",
        "beauty"
    ],
    "wof:name":"E One Trading",
    "wof:placetype":"venue"
},
  "geometry": {"coordinates":[-96.884691,32.873871],"type":"Point"}
}