{
  "type": "Feature",
  "properties": {
    "iso:country":"US",
    "sg:address":"2801 Memorial Blvd",
    "sg:city":"Port Arthur",
    "sg:classifiers":[
        {
            "category":"Retail",
            "subcategory":"Auto Repair",
            "type":"Services"
        }
    ],
    "sg:phone":"+1 409 982 1011",
    "sg:postcode":"77640",
    "sg:province":"TX",
    "sg:tags":[
        "automotive",
        "exhaust",
        "general"
    ],
    "wof:name":"Muffler Shop",
    "wof:placetype":"venue"
},
  "geometry": {"coordinates":[-93.94029399999999,29.907057],"type":"Point"}
}