{
  "type": "Feature",
  "properties": {
    "iso:country":"US",
    "sg:address":"5815 Jacksboro Hwy",
    "sg:city":"Fort Worth",
    "sg:classifiers":[
        {
            "category":"Wholesale",
            "subcategory":"Construction Materials",
            "type":"Manufacturing & Wholesale Goods"
        }
    ],
    "sg:phone":"+1 817 740 9539",
    "sg:postcode":"76114",
    "sg:province":"TX",
    "sg:tags":[
        "gates"
    ],
    "wof:name":"Gate Service By Gene Cozart",
    "wof:placetype":"venue"
},
  "geometry": {"coordinates":[-97.410296,32.802595],"type":"Point"}
}