{
  "type": "Feature",
  "properties": {
    "iso:country":"US",
    "sg:address":"2509 E Amarillo Blvd",
    "sg:city":"Amarillo",
    "sg:classifiers":[
        {
            "category":"Restaurant",
            "type":"Food & Drink"
        }
    ],
    "sg:phone":"+1 806 383 6753",
    "sg:postcode":"79107",
    "sg:province":"TX",
    "sg:tags":[
        "eating"
    ],
    "wof:name":"Don Miguel Taco's",
    "wof:placetype":"venue"
},
  "geometry": {"coordinates":[-101.807301,35.222064],"type":"Point"}
}