{
  "type": "Feature",
  "properties": {
    "iso:country":"US",
    "sg:address":"214 N Main St",
    "sg:city":"Highlands",
    "sg:classifiers":[
        {
            "category":"Retail",
            "subcategory":"Laundry & Dry Cleaning",
            "type":"Services"
        }
    ],
    "sg:phone":"+1 281 426 5811",
    "sg:postcode":"77562",
    "sg:province":"TX",
    "sg:tags":[
        "cleaner",
        "commercial",
        "operated",
        "dryer",
        "laundries-self",
        "washer",
        "coin"
    ],
    "wof:name":"Highland Washateria",
    "wof:placetype":"venue"
},
  "geometry": {"coordinates":[-95.05727899999999,29.817668],"type":"Point"}
}