{
  "type": "Feature",
  "properties": {
    "iso:country":"US",
    "sg:address":"6655 Hillcroft St Ste 109",
    "sg:city":"Houston",
    "sg:classifiers":[
        {
            "category":"Health Services",
            "subcategory":"Doctor",
            "type":"Services"
        }
    ],
    "sg:phone":"+1 713 988 3027",
    "sg:postcode":"77081",
    "sg:province":"TX",
    "wof:name":"Fortin-Magana Romeo MD",
    "wof:placetype":"venue"
},
  "geometry": {"coordinates":[-95.49299600000001,29.7083],"type":"Point"}
}