{
  "type": "Feature",
  "properties": {
    "iso:country":"US",
    "sg:address":"907 Olney Dr",
    "sg:city":"San Antonio",
    "sg:classifiers":[
        {
            "category":"Real Estate",
            "subcategory":"Real Estate Agent",
            "type":"Services"
        }
    ],
    "sg:phone":"+1 210 824 3880",
    "sg:postcode":"78218",
    "sg:province":"TX",
    "wof:name":"Mabel Stewart Estate",
    "wof:placetype":"venue"
},
  "geometry": {"coordinates":[-98.42626199999999,29.490263],"type":"Point"}
}