{
  "type": "Feature",
  "properties": {
    "iso:country":"US",
    "sg:address":"1024 E Broad St",
    "sg:city":"Mansfield",
    "sg:classifiers":[
        {
            "category":"Sports & Exercise",
            "subcategory":"Gym",
            "type":"Entertainment"
        }
    ],
    "sg:phone":"+1 817 453 0447",
    "sg:postcode":"76063",
    "sg:province":"TX",
    "sg:tags":[
        "club",
        "health",
        "studio",
        "gymnasium"
    ],
    "wof:name":"Curves For Women",
    "wof:placetype":"venue"
},
  "geometry": {"coordinates":[-97.12894900000001,32.565212],"type":"Point"}
}