{
  "type": "Feature",
  "properties": {
    "iso:country":"US",
    "sg:address":"1445 Nardo Goodman Dr",
    "sg:city":"El Paso",
    "sg:classifiers":[
        {
            "category":"Education",
            "subcategory":"School",
            "type":"Public Place"
        }
    ],
    "sg:phone":"+1 915 832 4880",
    "sg:postcode":"79912",
    "sg:province":"TX",
    "sg:tags":[
        "high",
        "middle",
        "elementary"
    ],
    "sg:website":"www.episd.org",
    "wof:name":"El Paso Independent School District",
    "wof:placetype":"venue"
},
  "geometry": {"coordinates":[-106.559213,31.879389],"type":"Point"}
}