{
  "type": "Feature",
  "properties": {
    "iso:country":"US",
    "sg:address":"202 Hwy 332",
    "sg:city":"Clute",
    "sg:classifiers":[
        {
            "category":"Utilities",
            "subcategory":"Electric",
            "type":"Services"
        }
    ],
    "sg:phone":"+1 979 265 3600",
    "sg:postcode":"77531",
    "sg:province":"TX",
    "sg:tags":[
        "center"
    ],
    "wof:name":"Brazosport Service Center",
    "wof:placetype":"venue"
},
  "geometry": {"coordinates":[-95.396224,29.006977],"type":"Point"}
}