{
  "type": "Feature",
  "properties": {
    "iso:country":"US",
    "sg:address":"6310 Glen Echo Ln",
    "sg:city":"Arlington",
    "sg:classifiers":[
        {
            "category":"Shopping",
            "subcategory":"Used Merchandise",
            "type":"Retail Goods"
        }
    ],
    "sg:phone":"+1 817 561 1227",
    "sg:postcode":"76001",
    "sg:province":"TX",
    "wof:name":"Brazos Trading Co",
    "wof:placetype":"venue"
},
  "geometry": {"coordinates":[-97.170783,32.642173],"type":"Point"}
}