{
  "type": "Feature",
  "properties": {
    "iso:country":"US",
    "sg:address":"1715 Carol Stream Dr",
    "sg:city":"Richardson",
    "sg:classifiers":[
        {
            "category":"Professional",
            "subcategory":"Employment Agencies",
            "type":"Services"
        }
    ],
    "sg:phone":"+1 972 479 9820",
    "sg:postcode":"75081",
    "sg:province":"TX",
    "wof:name":"Barrett Group Inc",
    "wof:placetype":"venue"
},
  "geometry": {"coordinates":[-96.69432,32.971445],"type":"Point"}
}