{
  "type": "Feature",
  "properties": {
    "iso:country":"US",
    "sg:address":"6106 Fieldcrest Ln",
    "sg:city":"Garland",
    "sg:classifiers":[
        {
            "category":"Building & Trades",
            "subcategory":"Construction",
            "type":"Services"
        }
    ],
    "sg:phone":"+1 972 442 9536",
    "sg:postcode":"75048",
    "sg:province":"TX",
    "sg:tags":[
        "contractor"
    ],
    "wof:name":"Xstream Csr LLC",
    "wof:placetype":"venue"
},
  "geometry": {"coordinates":[-96.564992,32.975021],"type":"Point"}
}