{
  "type": "Feature",
  "properties": {
    "iso:country":"US",
    "sg:address":"2855 W Lake Houston Pkwy # 112",
    "sg:city":"Kingwood",
    "sg:classifiers":[
        {
            "category":"Utilities",
            "subcategory":"Mobile Phone",
            "type":"Services"
        },
        {
            "category":"Communications",
            "type":"Services"
        }
    ],
    "sg:phone":"+1 281 361 8020",
    "sg:postcode":"77339",
    "sg:province":"TX",
    "sg:tags":[
        "telephone",
        "cellular"
    ],
    "sg:website":"http://www.gte.com",
    "wof:name":"Gte",
    "wof:placetype":"venue"
},
  "geometry": {"coordinates":[-95.183339,30.047702],"type":"Point"}
}