{
  "type": "Feature",
  "properties": {
    "iso:country":"US",
    "sg:address":"3421 S US Hwy 77",
    "sg:city":"Schulenburg",
    "sg:classifiers":[
        {
            "category":"Building & Trades",
            "subcategory":"Construction",
            "type":"Services"
        }
    ],
    "sg:phone":"+1 979 743 3782",
    "sg:postcode":"78956",
    "sg:province":"TX",
    "sg:tags":[
        "contractor"
    ],
    "wof:name":"L and W Weatherstripping LLC",
    "wof:placetype":"venue"
},
  "geometry": {"coordinates":[-96.897834,29.632593],"type":"Point"}
}