{
  "type": "Feature",
  "properties": {
    "iso:country":"US",
    "sg:address":"1200 W 15th Ave",
    "sg:city":"Amarillo",
    "sg:classifiers":[
        {
            "category":"Health Services",
            "subcategory":"Optometrist",
            "type":"Services"
        }
    ],
    "sg:phone":"+1 806 379 8384",
    "sg:postcode":"79102",
    "sg:province":"TX",
    "sg:tags":[
        "optical",
        "good"
    ],
    "wof:name":"Edward P Brandenburg OD",
    "wof:placetype":"venue"
},
  "geometry": {"coordinates":[-101.852177,35.19959],"type":"Point"}
}