{
  "type": "Feature",
  "properties": {
    "iso:country":"US",
    "sg:address":"8614 Parkfield Dr",
    "sg:city":"Austin",
    "sg:classifiers":[
        {
            "category":"Building & Trades",
            "subcategory":"Cleaning & Sanitation",
            "type":"Services"
        }
    ],
    "sg:phone":"+1 512 832 7862",
    "sg:postcode":"78758",
    "sg:province":"TX",
    "wof:name":"Johnson Johnson Customized Clg",
    "wof:placetype":"venue"
},
  "geometry": {"coordinates":[-97.710776,30.360726],"type":"Point"}
}