{
  "type": "Feature",
  "properties": {
    "iso:country":"US",
    "sg:address":"1185 Stacewood Dr",
    "sg:city":"Beaumont",
    "sg:classifiers":[
        {
            "category":"Shopping",
            "subcategory":"Gifts & Souvenirs",
            "type":"Retail Goods"
        }
    ],
    "sg:phone":"+1 409 866 4448",
    "sg:postcode":"77706",
    "sg:province":"TX",
    "wof:name":"La Cruise",
    "wof:placetype":"venue"
},
  "geometry": {"coordinates":[-94.178338,30.084502],"type":"Point"}
}