{
  "type": "Feature",
  "properties": {
    "iso:country":"US",
    "sg:address":"108 N Locust St",
    "sg:city":"Denton",
    "sg:classifiers":[
        {
            "category":"Shopping",
            "subcategory":"Jewelry",
            "type":"Retail Goods"
        }
    ],
    "sg:phone":"+1 940 381 0474",
    "sg:postcode":"76201",
    "sg:province":"TX",
    "sg:tags":[
        "jeweler"
    ],
    "wof:name":"Gems By Marie",
    "wof:placetype":"venue"
},
  "geometry": {"coordinates":[-97.132372,33.214602],"type":"Point"}
}