{
  "type": "Feature",
  "properties": {
    "iso:country":"US",
    "sg:address":"1201 E Grand Ave",
    "sg:city":"Marshall",
    "sg:classifiers":[
        {
            "category":"Home & Garden",
            "subcategory":"Hardware",
            "type":"Retail Goods"
        }
    ],
    "sg:phone":"+1 903 938 6713",
    "sg:postcode":"75672",
    "sg:province":"TX",
    "sg:website":"www.marshalltruevalue.com",
    "wof:name":"Marshall Hardware & Supply",
    "wof:placetype":"venue"
},
  "geometry": {"coordinates":[-94.356149,32.548468],"type":"Point"}
}