{
  "type": "Feature",
  "properties": {
    "iso:country":"US",
    "sg:address":"5492 US Highway 59 S",
    "sg:city":"Texarkana",
    "sg:classifiers":[
        {
            "category":"Education",
            "subcategory":"School",
            "type":"Public Place"
        }
    ],
    "sg:phone":"+1 903 831 5390",
    "sg:postcode":"75501",
    "sg:province":"TX",
    "sg:tags":[
        "elementary"
    ],
    "wof:name":"Liberty-eylau Pri Elementary School",
    "wof:placetype":"venue"
},
  "geometry": {"coordinates":[-94.116221,33.379378],"type":"Point"}
}