{
  "type": "Feature",
  "properties": {
    "iso:country":"US",
    "sg:address":"17818 Crestline Rd",
    "sg:city":"Humble",
    "sg:classifiers":[
        {
            "category":"Organizations",
            "subcategory":"Religious Organization",
            "type":"Services"
        }
    ],
    "sg:phone":"+1 281 436 0312",
    "sg:postcode":"77396",
    "sg:province":"TX",
    "sg:tags":[
        "place",
        "worship",
        "church"
    ],
    "wof:name":"Assembly Line Co",
    "wof:placetype":"venue"
},
  "geometry": {"coordinates":[-95.21674899999999,29.977856],"type":"Point"}
}