{
  "type": "Feature",
  "properties": {
    "iso:country":"US",
    "sg:address":"601 N 25 Mile Ave",
    "sg:city":"Hereford",
    "sg:classifiers":[
        {
            "category":"Education",
            "subcategory":"School",
            "type":"Public Place"
        }
    ],
    "sg:phone":"+1 806 363 7600",
    "sg:postcode":"79045",
    "sg:province":"TX",
    "wof:name":"Hereford Special Education",
    "wof:placetype":"venue"
},
  "geometry": {"coordinates":[-102.40538599999999,34.837254],"type":"Point"}
}