{
  "type": "Feature",
  "properties": {
    "iso:country":"US",
    "sg:address":"2510 Cayenne Dr",
    "sg:city":"Mc Kinney",
    "sg:classifiers":[
        {
            "category":"Professional",
            "subcategory":"Lawyer & Legal Services",
            "type":"Services"
        }
    ],
    "sg:phone":"+1 972 369 1300",
    "sg:postcode":"75070",
    "sg:province":"TX",
    "sg:tags":[
        "attorney"
    ],
    "wof:name":"Michael R Nichols Law Office",
    "wof:placetype":"venue"
},
  "geometry": {"coordinates":[-96.65376000000001,33.170108],"type":"Point"}
}