{
  "type": "Feature",
  "properties": {
    "iso:country":"US",
    "sg:address":"2652 Homannville Trl",
    "sg:city":"Lockhart",
    "sg:phone":"+1 512 398 3838",
    "sg:postcode":"78644",
    "sg:province":"TX",
    "sg:tags":[
        "farm",
        "field",
        "crop"
    ],
    "wof:name":"Homann Farms",
    "wof:placetype":"venue"
},
  "geometry": {"coordinates":[-97.662268,29.98141],"type":"Point"}
}