{
  "type": "Feature",
  "properties": {
    "iso:country":"US",
    "sg:address":"5131 Summerhill Rd",
    "sg:city":"Texarkana",
    "sg:classifiers":[
        {
            "category":"Insurance",
            "subcategory":"Insurance Agent",
            "type":"Services"
        }
    ],
    "sg:phone":"+1 903 831 3493",
    "sg:postcode":"75503",
    "sg:province":"TX",
    "wof:name":"Barry Insurance",
    "wof:placetype":"venue"
},
  "geometry": {"coordinates":[-94.06805199999999,33.468179],"type":"Point"}
}