{
  "type": "Feature",
  "properties": {
    "iso:country":"US",
    "sg:address":"607 Kelsie Cir",
    "sg:city":"De Soto",
    "sg:classifiers":[
        {
            "category":"Manufacturing",
            "subcategory":"Printing",
            "type":"Manufacturing & Wholesale Goods"
        }
    ],
    "sg:phone":"+1 972 230 9231",
    "sg:postcode":"75115",
    "sg:province":"TX",
    "sg:tags":[
        "publishing"
    ],
    "wof:name":"Dialmonds & Sapphires Publishi",
    "wof:placetype":"venue"
},
  "geometry": {"coordinates":[-96.864971,32.579387],"type":"Point"}
}