{
  "type": "Feature",
  "properties": {
    "iso:country":"US",
    "sg:address":"4209 S Industrial Dr",
    "sg:city":"Austin",
    "sg:classifiers":[
        {
            "category":"Home & Garden",
            "subcategory":"Carpets & Floor Coverings",
            "type":"Retail Goods"
        }
    ],
    "sg:phone":"+1 512 916 9324",
    "sg:postcode":"78744",
    "sg:province":"TX",
    "sg:tags":[
        "flooring",
        "contractor"
    ],
    "wof:name":"Blue Linx Hardwood",
    "wof:placetype":"venue"
},
  "geometry": {"coordinates":[-97.74361,30.210086],"type":"Point"}
}