{
  "type": "Feature",
  "properties": {
    "iso:country":"US",
    "sg:address":"317 Forestwood Dr",
    "sg:city":"Forney",
    "sg:classifiers":[
        {
            "category":"Transit Center",
            "subcategory":"Freight",
            "type":"Transportation"
        },
        {
            "category":"Freight",
            "type":"Transportation"
        }
    ],
    "sg:phone":"+1 972 564 3029",
    "sg:postcode":"75126",
    "sg:province":"TX",
    "sg:tags":[
        "local",
        "trucking-motor",
        "trucking"
    ],
    "wof:name":"Steele Trucking",
    "wof:placetype":"venue"
},
  "geometry": {"coordinates":[-96.460695,32.761194],"type":"Point"}
}