{
  "type": "Feature",
  "properties": {
    "iso:country":"US",
    "sg:address":"9539 Ponderosa Ln",
    "sg:city":"Houston",
    "sg:classifiers":[
        {
            "category":"Retail",
            "subcategory":"Auto Repair",
            "type":"Services"
        }
    ],
    "sg:phone":"+1 713 988 9777",
    "sg:postcode":"77036",
    "sg:province":"TX",
    "sg:tags":[
        "transmission"
    ],
    "wof:name":"Astro Transmissions Inc",
    "wof:placetype":"venue"
},
  "geometry": {"coordinates":[-95.545782,29.67448],"type":"Point"}
}