{
  "type": "Feature",
  "properties": {
    "iso:country":"US",
    "sg:address":"801 Santa Fe Dr",
    "sg:city":"Weatherford",
    "sg:classifiers":[
        {
            "category":"Government",
            "subcategory":"Police Station",
            "type":"Public Place"
        },
        {
            "category":"Organizations",
            "subcategory":"Community Association",
            "type":"Services"
        }
    ],
    "sg:phone":"+1 817 599 5555",
    "sg:postcode":"76086",
    "sg:province":"TX",
    "sg:tags":[
        "department"
    ],
    "wof:name":"Parker County Crime Stoppers",
    "wof:placetype":"venue"
},
  "geometry": {"coordinates":[-97.78584499999999,32.750758],"type":"Point"}
}