{
  "type": "Feature",
  "properties": {
    "iso:country":"US",
    "sg:address":"915 Lincoln St",
    "sg:city":"Laredo",
    "sg:classifiers":[
        {
            "category":"Freight",
            "type":"Transportation"
        }
    ],
    "sg:phone":"+1 956 753 2666",
    "sg:postcode":"78040",
    "sg:province":"TX",
    "wof:name":"Intl Taxi's & Trnsprtn",
    "wof:placetype":"venue"
},
  "geometry": {"coordinates":[-99.505527,27.504155],"type":"Point"}
}