{
  "type": "Feature",
  "properties": {
    "iso:country":"US",
    "sg:address":"419 N Bailey Ave",
    "sg:city":"Fort Worth",
    "sg:classifiers":[
        {
            "category":"Manufacturing",
            "subcategory":"Chemicals & Compounds",
            "type":"Manufacturing & Wholesale Goods"
        }
    ],
    "sg:phone":"+1 817 740 8646",
    "sg:postcode":"76107",
    "sg:province":"TX",
    "sg:tags":[
        "preparation",
        "mfg"
    ],
    "wof:name":"Etched In Time",
    "wof:placetype":"venue"
},
  "geometry": {"coordinates":[-97.37314600000001,32.763576],"type":"Point"}
}