{
  "type": "Feature",
  "properties": {
    "iso:country":"US",
    "sg:address":"1012 Parkview Cir",
    "sg:city":"Hewitt",
    "sg:classifiers":[
        {
            "category":"Health Services",
            "subcategory":"Doctor",
            "type":"Services"
        }
    ],
    "sg:phone":"+1 254 666 9243",
    "sg:postcode":"76643",
    "sg:province":"TX",
    "sg:tags":[
        "physician",
        "family",
        "practice",
        "surgeons",
        "medicine"
    ],
    "wof:name":"Bennett Jr Md Robert S",
    "wof:placetype":"venue"
},
  "geometry": {"coordinates":[-97.206521,31.447895],"type":"Point"}
}