{
  "type": "Feature",
  "properties": {
    "iso:country":"US",
    "sg:address":"6478 Lindell Ave",
    "sg:city":"Fort Worth",
    "sg:classifiers":[
        {
            "category":"Restaurant",
            "type":"Food & Drink"
        }
    ],
    "sg:phone":"+1 817 732 1527",
    "sg:postcode":"76116",
    "sg:province":"TX",
    "sg:tags":[
        "eating"
    ],
    "wof:name":"Dortha C Hardee",
    "wof:placetype":"venue"
},
  "geometry": {"coordinates":[-97.42630200000001,32.726589],"type":"Point"}
}