{
  "type": "Feature",
  "properties": {
    "iso:country":"US",
    "sg:address":"5724 SW Green Oaks Blvd",
    "sg:city":"Arlington",
    "sg:classifiers":[
        {
            "category":"Retail",
            "subcategory":"Animal Services",
            "type":"Services"
        }
    ],
    "sg:phone":"+1 817 561 1801",
    "sg:postcode":"76017",
    "sg:province":"TX",
    "wof:name":"Dog Wash",
    "wof:placetype":"venue"
},
  "geometry": {"coordinates":[-97.19319900000001,32.672836],"type":"Point"}
}