{
  "type": "Feature",
  "properties": {
    "iso:country":"US",
    "sg:address":"1428 N Cesar Chavez Rd",
    "sg:city":"Alamo",
    "sg:classifiers":[
        {
            "category":"Home & Garden",
            "subcategory":"Building Materials",
            "type":"Retail Goods"
        }
    ],
    "sg:phone":"+1 956 782 1925",
    "sg:postcode":"78516",
    "sg:province":"TX",
    "wof:name":"Materiales Casares Inc",
    "wof:placetype":"venue"
},
  "geometry": {"coordinates":[-98.130194,26.213801],"type":"Point"}
}