{
  "type": "Feature",
  "properties": {
    "iso:country":"US",
    "sg:address":"909 Silber",
    "sg:city":"Houston",
    "sg:classifiers":[
        {
            "category":"Social Services",
            "subcategory":"Job Training",
            "type":"Services"
        },
        {
            "category":"Professional",
            "subcategory":"Employment Agencies",
            "type":"Services"
        }
    ],
    "sg:phone":"+1 832 482 9579",
    "sg:postcode":"77024",
    "sg:province":"TX",
    "sg:tags":[
        "career",
        "counseling"
    ],
    "wof:name":"Grant Marshall Group",
    "wof:placetype":"venue"
},
  "geometry": {"coordinates":[-95.46870199999999,29.782037],"type":"Point"}
}