{
  "type": "Feature",
  "properties": {
    "iso:country":"US",
    "sg:address":"5034 Frankford Ave",
    "sg:city":"Lubbock",
    "sg:classifiers":[
        {
            "category":"Shopping",
            "subcategory":"Clothing, Apparel, & Fashions",
            "type":"Retail Goods"
        }
    ],
    "sg:phone":"+1 806 795 7106",
    "sg:postcode":"79415",
    "sg:province":"TX",
    "wof:name":"Luskeys/Ryons",
    "wof:placetype":"venue"
},
  "geometry": {"coordinates":[-101.939798,33.648929],"type":"Point"}
}