{
  "type": "Feature",
  "properties": {
    "iso:country":"US",
    "sg:address":"2101 N Collins St",
    "sg:city":"Arlington",
    "sg:classifiers":[
        {
            "category":"Bakery",
            "type":"Food & Drink"
        }
    ],
    "sg:menulink":"http://www.allmenus.com/tx/arlington/32537-la-madeleine/menu/",
    "sg:phone":"+1 817 461 3634",
    "sg:postcode":"76011",
    "sg:province":"TX",
    "sg:tags":[
        "american",
        "pastry",
        "french"
    ],
    "wof:name":"La Madeleine",
    "wof:placetype":"venue"
},
  "geometry": {"coordinates":[-97.09712399999999,32.767407],"type":"Point"}
}