{
  "type": "Feature",
  "properties": {
    "iso:country":"US",
    "sg:address":"1130 Pendale Rd",
    "sg:city":"El Paso",
    "sg:classifiers":[
        {
            "category":"Retail",
            "subcategory":"Repair Shop",
            "type":"Services"
        }
    ],
    "sg:phone":"+1 915 594 4030",
    "sg:postcode":"79907",
    "sg:province":"TX",
    "sg:tags":[
        "tractor"
    ],
    "wof:name":"Pendale Tractor-Trailer Svc",
    "wof:placetype":"venue"
},
  "geometry": {"coordinates":[-106.31779400000001,31.731288],"type":"Point"}
}