{
  "type": "Feature",
  "properties": {
    "iso:country":"US",
    "sg:address":"1109 N Main St",
    "sg:city":"Fort Worth",
    "sg:classifiers":[
        {
            "category":"Professional",
            "type":"Services"
        }
    ],
    "sg:phone":"+1 817 625 6931",
    "sg:postcode":"76106",
    "sg:province":"TX",
    "sg:tags":[
        "art",
        "studio"
    ],
    "wof:name":"Vernon Fisher Art Studio",
    "wof:placetype":"venue"
},
  "geometry": {"coordinates":[-97.343644,32.773159],"type":"Point"}
}