{
  "type": "Feature",
  "properties": {
    "iso:country":"US",
    "sg:address":"1017 W Irving St",
    "sg:city":"Rio Grande City",
    "sg:classifiers":[
        {
            "category":"Retail",
            "subcategory":"Auto Repair",
            "type":"Services"
        }
    ],
    "sg:phone":"+1 956 716 6422",
    "sg:postcode":"78582",
    "sg:province":"TX",
    "sg:tags":[
        "repairing",
        "automobile"
    ],
    "wof:name":"Martinez Auto Svc",
    "wof:placetype":"venue"
},
  "geometry": {"coordinates":[-98.840041,26.388716],"type":"Point"}
}