{
  "type": "Feature",
  "properties": {
    "iso:country":"US",
    "sg:address":"6009 Belt Line Rd Ste 142",
    "sg:city":"Dallas",
    "sg:classifiers":[
        {
            "category":"Professional",
            "subcategory":"Accounting & Tax Preparation",
            "type":"Services"
        }
    ],
    "sg:phone":"+1 972 490 4929",
    "sg:postcode":"75254",
    "sg:province":"TX",
    "sg:tags":[
        "accountant"
    ],
    "wof:name":"Teherani Siroos CPA",
    "wof:placetype":"venue"
},
  "geometry": {"coordinates":[-96.803596,32.9496],"type":"Point"}
}