{
  "type": "Feature",
  "properties": {
    "iso:country":"US",
    "sg:address":"7800 N Navarro St",
    "sg:city":"Victoria",
    "sg:classifiers":[
        {
            "category":"Utilities",
            "subcategory":"Mobile Phone",
            "type":"Services"
        }
    ],
    "sg:phone":"+1 361 573 0222",
    "sg:postcode":"77904",
    "sg:province":"TX",
    "sg:tags":[
        "telephone",
        "cellular"
    ],
    "wof:name":"Verizon Wireless",
    "wof:placetype":"venue"
},
  "geometry": {"coordinates":[-96.997362,28.867797],"type":"Point"}
}