{
  "type": "Feature",
  "properties": {
    "iso:country":"US",
    "sg:address":"1511 W 6th St",
    "sg:city":"Austin",
    "sg:classifiers":[
        {
            "category":"Professional",
            "type":"Services"
        }
    ],
    "sg:phone":"+1 512 472 6017",
    "sg:postcode":"78703",
    "sg:province":"TX",
    "sg:tags":[
        "interior",
        "design"
    ],
    "wof:name":"Vitali Design Studio",
    "wof:placetype":"venue"
},
  "geometry": {"coordinates":[-97.762199,30.274599],"type":"Point"}
}