{
  "type": "Feature",
  "properties": {
    "iso:country":"US",
    "sg:address":"55 Asbury Park",
    "sg:city":"Sugar Land",
    "sg:classifiers":[
        {
            "category":"Professional",
            "type":"Services"
        }
    ],
    "sg:phone":"+1 281 242 9813",
    "sg:postcode":"77479",
    "sg:province":"TX",
    "sg:tags":[
        "establishment"
    ],
    "wof:name":"International Telecommunicat",
    "wof:placetype":"venue"
},
  "geometry": {"coordinates":[-95.59263,29.567311],"type":"Point"}
}