{
  "type": "Feature",
  "properties": {
    "iso:country":"US",
    "sg:address":"7 Glenbrook Cir",
    "sg:city":"Allen",
    "sg:classifiers":[
        {
            "category":"Personal",
            "subcategory":"Beauty Salon",
            "type":"Services"
        }
    ],
    "sg:phone":"+1 972 727 2573",
    "sg:postcode":"75002",
    "sg:province":"TX",
    "sg:tags":[
        "shop"
    ],
    "wof:name":"Gene Hair",
    "wof:placetype":"venue"
},
  "geometry": {"coordinates":[-96.59929700000001,33.100622],"type":"Point"}
}