{
  "type": "Feature",
  "properties": {
    "iso:country":"US",
    "sg:address":"2310 SW Military Dr",
    "sg:city":"San Antonio",
    "sg:classifiers":[
        {
            "category":"Bakery",
            "type":"Food & Drink"
        }
    ],
    "sg:menulink":"http://www.allmenus.com/tx/san-antonio/230624-great-american-cookies/menu/",
    "sg:phone":"+1 210 928 2447",
    "sg:postcode":"78224",
    "sg:province":"TX",
    "sg:tags":[
        "american",
        "pastry"
    ],
    "wof:name":"Great American Cookies",
    "wof:placetype":"venue"
},
  "geometry": {"coordinates":[-98.530654,29.354029],"type":"Point"}
}