{
  "type": "Feature",
  "properties": {
    "iso:country":"US",
    "sg:address":"3401 Custer Rd",
    "sg:city":"Plano",
    "sg:classifiers":[
        {
            "category":"Banks & Credit Unions",
            "subcategory":"Bank",
            "type":"Services"
        }
    ],
    "sg:phone":"+1 972 943 9064",
    "sg:postcode":"75023",
    "sg:province":"TX",
    "sg:tags":[
        "loan",
        "real estate"
    ],
    "wof:name":"Allied Home Mortgage Capital",
    "wof:placetype":"venue"
},
  "geometry": {"coordinates":[-96.73347,33.043016],"type":"Point"}
}