{
  "type": "Feature",
  "properties": {
    "iso:country":"US",
    "sg:address":"1171 S Burleson Blvd",
    "sg:city":"Burleson",
    "sg:classifiers":[
        {
            "category":"Freight",
            "type":"Transportation"
        }
    ],
    "sg:phone":"+1 817 426 6800",
    "sg:postcode":"76028",
    "sg:province":"TX",
    "sg:tags":[
        "recreational",
        "vehicle"
    ],
    "wof:name":"Burleson Rv Storage",
    "wof:placetype":"venue"
},
  "geometry": {"coordinates":[-97.30663699999999,32.51959],"type":"Point"}
}