{
  "type": "Feature",
  "properties": {
    "iso:country":"US",
    "sg:address":"105 S Chenango St",
    "sg:city":"Angleton",
    "sg:classifiers":[
        {
            "category":"Real Estate",
            "subcategory":"Real Estate Agent",
            "type":"Services"
        }
    ],
    "sg:phone":"+1 979 849 1234",
    "sg:postcode":"77515",
    "sg:province":"TX",
    "wof:name":"Peltier Bob & Assoc",
    "wof:placetype":"venue"
},
  "geometry": {"coordinates":[-95.430319,29.164503],"type":"Point"}
}