{
  "type": "Feature",
  "properties": {
    "iso:country":"US",
    "sg:address":"12820 Roy Harris Loop",
    "sg:city":"Conroe",
    "sg:classifiers":[
        {
            "category":"Retail",
            "subcategory":"Auto Rental",
            "type":"Services"
        },
        {
            "category":"Airport",
            "type":"Transportation"
        },
        {
            "category":"Local Transit",
            "type":"Transportation"
        }
    ],
    "sg:phone":"+1 936 539 9182",
    "sg:postcode":"77306",
    "sg:province":"TX",
    "sg:tags":[
        "shuttle",
        "limousine"
    ],
    "wof:name":"Montgomery County Limo Svc",
    "wof:placetype":"venue"
},
  "geometry": {"coordinates":[-95.37933200000001,30.30261],"type":"Point"}
}