{
  "type": "Feature",
  "properties": {
    "iso:country":"US",
    "sg:address":"1310 N Sarah Dewitt Dr",
    "sg:city":"Gonzales",
    "sg:classifiers":[
        {
            "category":"Freight",
            "type":"Transportation"
        }
    ],
    "sg:phone":"+1 830 672 7695",
    "sg:postcode":"78629",
    "sg:province":"TX",
    "sg:tags":[
        "commercial",
        "storage"
    ],
    "wof:name":"Security Storage",
    "wof:placetype":"venue"
},
  "geometry": {"coordinates":[-97.444519,29.52142],"type":"Point"}
}