{
  "type": "Feature",
  "properties": {
    "iso:country":"US",
    "sg:address":"17126 Camberwell Green Ln",
    "sg:city":"Houston",
    "sg:classifiers":[
        {
            "category":"Building & Trades",
            "subcategory":"Plumbing",
            "type":"Services"
        }
    ],
    "sg:phone":"+1 281 374 7039",
    "sg:postcode":"77070",
    "sg:province":"TX",
    "sg:tags":[
        "contractor"
    ],
    "wof:name":"Schields Plumbing Co",
    "wof:placetype":"venue"
},
  "geometry": {"coordinates":[-95.569757,30.012821],"type":"Point"}
}