{
  "type": "Feature",
  "properties": {
    "iso:country":"US",
    "sg:address":"1550 E Palestine Ave",
    "sg:city":"Palestine",
    "sg:classifiers":[
        {
            "category":"Professional",
            "subcategory":"Employment Agencies",
            "type":"Services"
        }
    ],
    "sg:phone":"+1 903 729 5545",
    "sg:postcode":"75801",
    "sg:province":"TX",
    "sg:tags":[
        "help",
        "supply"
    ],
    "wof:name":"Workco Staffing Services",
    "wof:placetype":"venue"
},
  "geometry": {"coordinates":[-95.610637,31.781648],"type":"Point"}
}