{
  "type": "Feature",
  "properties": {
    "iso:country":"US",
    "sg:address":"5121 Hiltonview Rd",
    "sg:city":"Houston",
    "sg:classifiers":[
        {
            "category":"Manufacturing",
            "subcategory":"Metals",
            "type":"Manufacturing & Wholesale Goods"
        },
        {
            "category":"Manufacturing",
            "subcategory":"Building Materials",
            "type":"Manufacturing & Wholesale Goods"
        }
    ],
    "sg:phone":"+1 832 375 1800",
    "sg:postcode":"77086",
    "sg:province":"TX",
    "sg:tags":[
        "work-manufacturers",
        "fabricator",
        "work",
        "sheet"
    ],
    "sg:website":"http://www.tifab.com",
    "wof:name":"Phx Grp - Txas Div Ttanium Fab",
    "wof:placetype":"venue"
},
  "geometry": {"coordinates":[-95.49812,29.935261],"type":"Point"}
}