{
  "type": "Feature",
  "properties": {
    "iso:country":"US",
    "sg:address":"110 Kaufman St",
    "sg:city":"Waxahachie",
    "sg:classifiers":[
        {
            "category":"Organizations",
            "subcategory":"Religious Organization",
            "type":"Services"
        }
    ],
    "sg:phone":"+1 972 937 2436",
    "sg:postcode":"75165",
    "sg:province":"TX",
    "sg:tags":[
        "church"
    ],
    "wof:name":"Ark-Prayer Prophetic Ministry",
    "wof:placetype":"venue"
},
  "geometry": {"coordinates":[-96.845145,32.384829],"type":"Point"}
}