{
  "type": "Feature",
  "properties": {
    "iso:country":"US",
    "sg:address":"2214 Swift Blvd",
    "sg:city":"Houston",
    "sg:classifiers":[
        {
            "category":"Shopping",
            "subcategory":"Catalog Store",
            "type":"Retail Goods"
        }
    ],
    "sg:phone":"+1 713 664 6567",
    "sg:postcode":"77030",
    "sg:province":"TX",
    "sg:tags":[
        "mail",
        "house"
    ],
    "wof:name":"Aegean Accents",
    "wof:placetype":"venue"
},
  "geometry": {"coordinates":[-95.41085099999999,29.7127],"type":"Point"}
}