{
  "type": "Feature",
  "properties": {
    "iso:country":"US",
    "sg:address":"4845 Dumas Dr",
    "sg:city":"Amarillo",
    "sg:classifiers":[
        {
            "category":"Shopping",
            "subcategory":"Bicycles & Sporting Goods",
            "type":"Retail Goods"
        }
    ],
    "sg:phone":"+1 806 383 5688",
    "sg:postcode":"79108",
    "sg:province":"TX",
    "wof:name":"Aggression Paintball",
    "wof:placetype":"venue"
},
  "geometry": {"coordinates":[-101.833944,35.260253],"type":"Point"}
}