{
  "type": "Feature",
  "properties": {
    "iso:country":"US",
    "sg:address":"2900 Helena Ave",
    "sg:city":"Mcallen",
    "sg:classifiers":[
        {
            "category":"Shopping",
            "subcategory":"Florist",
            "type":"Retail Goods"
        }
    ],
    "sg:phone":"+1 956 630 1591",
    "sg:postcode":"78503",
    "sg:province":"TX",
    "wof:name":"Ramos Flower Shop",
    "wof:placetype":"venue"
},
  "geometry": {"coordinates":[-98.26384299999999,26.167301],"type":"Point"}
}