{
  "type": "Feature",
  "properties": {
    "iso:country":"US",
    "sg:address":"2604 Leopard Dr",
    "sg:city":"Texarkana",
    "sg:classifiers":[
        {
            "category":"Organizations",
            "subcategory":"Religious Organization",
            "type":"Services"
        }
    ],
    "sg:phone":"+1 903 832 1106",
    "sg:postcode":"75501",
    "sg:province":"TX",
    "sg:tags":[
        "church"
    ],
    "wof:name":"Liberty Mssnry Baptist Church",
    "wof:placetype":"venue"
},
  "geometry": {"coordinates":[-94.092197,33.392638],"type":"Point"}
}