{
  "type": "Feature",
  "properties": {
    "iso:country":"US",
    "sg:address":"218 Nolan St",
    "sg:city":"Tye",
    "sg:classifiers":[
        {
            "category":"Building & Trades",
            "subcategory":"Electrical",
            "type":"Services"
        }
    ],
    "sg:phone":"+1 325 795 0969",
    "sg:postcode":"79563",
    "sg:province":"TX",
    "sg:tags":[
        "electric",
        "contractor"
    ],
    "wof:name":"Goodgion Electric",
    "wof:placetype":"venue"
},
  "geometry": {"coordinates":[-99.868528,32.455927],"type":"Point"}
}