{
  "type": "Feature",
  "properties": {
    "iso:country":"US",
    "sg:address":"1038 W Little York Rd",
    "sg:city":"Houston",
    "sg:classifiers":[
        {
            "category":"Retail",
            "subcategory":"Repair Shop",
            "type":"Services"
        }
    ],
    "sg:phone":"+1 713 695 3163",
    "sg:postcode":"77091",
    "sg:province":"TX",
    "sg:tags":[
        "reupholstery",
        "furniture"
    ],
    "sg:website":"www.abbyupholstery.com",
    "wof:name":"Abby Upholstery",
    "wof:placetype":"venue"
},
  "geometry": {"coordinates":[-95.426102,29.8645],"type":"Point"}
}