{
  "type": "Feature",
  "properties": {
    "iso:country":"US",
    "sg:address":"1001 Jan Ellyn Ln",
    "sg:city":"El Paso",
    "sg:classifiers":[
        {
            "category":"Manufacturing",
            "subcategory":"Tools & Machinery",
            "type":"Manufacturing & Wholesale Goods"
        }
    ],
    "sg:phone":"+1 915 845 0179",
    "sg:postcode":"79912",
    "sg:province":"TX",
    "sg:tags":[
        "machine",
        "shop"
    ],
    "wof:name":"Eagle Precision Tools",
    "wof:placetype":"venue"
},
  "geometry": {"coordinates":[-106.553893,31.864031],"type":"Point"}
}