{
  "type": "Feature",
  "properties": {
    "iso:country":"US",
    "sg:address":"20 Stillforest St",
    "sg:city":"Houston",
    "sg:classifiers":[
        {
            "category":"Shopping",
            "subcategory":"Gifts & Souvenirs",
            "type":"Retail Goods"
        }
    ],
    "sg:phone":"+1 713 465 0274",
    "sg:postcode":"77024",
    "sg:province":"TX",
    "wof:name":"Evenson Enterprises",
    "wof:placetype":"venue"
},
  "geometry": {"coordinates":[-95.51430499999999,29.750898],"type":"Point"}
}