{
  "type": "Feature",
  "properties": {
    "iso:country":"US",
    "sg:address":"4515 S Georgia St",
    "sg:city":"Amarillo",
    "sg:classifiers":[
        {
            "category":"Personal",
            "subcategory":"Barber",
            "type":"Services"
        }
    ],
    "sg:phone":"+1 806 353 3940",
    "sg:postcode":"79110",
    "sg:province":"TX",
    "wof:name":"Jerry's South Ga Barber Shop",
    "wof:placetype":"venue"
},
  "geometry": {"coordinates":[-101.866225,35.16181],"type":"Point"}
}