{
  "type": "Feature",
  "properties": {
    "iso:country":"US",
    "sg:address":"931 S Jackson St",
    "sg:city":"Jacksonville",
    "sg:classifiers":[
        {
            "category":"Autos & Motor Vehicles",
            "subcategory":"Auto Supplies",
            "type":"Retail Goods"
        },
        {
            "category":"Manufacturing",
            "subcategory":"Motor Vehicles & Parts",
            "type":"Manufacturing & Wholesale Goods"
        },
        {
            "category":"Retail",
            "subcategory":"Auto Repair",
            "type":"Services"
        }
    ],
    "sg:phone":"+1 903 586 4326",
    "sg:postcode":"75766",
    "sg:province":"TX",
    "sg:tags":[
        "body",
        "buses-distributors",
        "shop",
        "automobile",
        "buses-parts",
        "equipment",
        "parts",
        "accessories-wholesale",
        "painting",
        "repairing",
        "manufacturer"
    ],
    "wof:name":"H & J Body Shop",
    "wof:placetype":"venue"
},
  "geometry": {"coordinates":[-95.266496,31.955895],"type":"Point"}
}