{
  "type": "Feature",
  "properties": {
    "iso:country":"US",
    "sg:address":"6600 N. Mesa Suite 604",
    "sg:city":"El Paso",
    "sg:classifiers":[
        {
            "category":"Personal",
            "subcategory":"Massage",
            "type":"Services"
        }
    ],
    "sg:phone":"+1 915 584 8883",
    "sg:postcode":"79912",
    "sg:province":"TX",
    "wof:name":"Shanghai Tea Spa",
    "wof:placetype":"venue"
},
  "geometry": {"coordinates":[-106.541072,31.834464],"type":"Point"}
}