{
  "type": "Feature",
  "properties": {
    "iso:country":"US",
    "sg:address":"7311 Galveston Rd",
    "sg:city":"Houston",
    "sg:classifiers":[
        {
            "category":"Building & Trades",
            "subcategory":"Construction",
            "type":"Services"
        }
    ],
    "sg:phone":"+1 713 946 9264",
    "sg:postcode":"77034",
    "sg:province":"TX",
    "sg:tags":[
        "contractor"
    ],
    "wof:name":"Service",
    "wof:placetype":"venue"
},
  "geometry": {"coordinates":[-95.22399900000001,29.6509],"type":"Point"}
}