{
  "type": "Feature",
  "properties": {
    "iso:country":"US",
    "sg:address":"2066 Candlewood Cir",
    "sg:city":"Lewisville",
    "sg:classifiers":[
        {
            "category":"Professional",
            "type":"Services"
        }
    ],
    "sg:phone":"+1 972 315 0968",
    "sg:postcode":"75067",
    "sg:province":"TX",
    "wof:name":"Mark E Stark",
    "wof:placetype":"venue"
},
  "geometry": {"coordinates":[-97.008972,33.010905],"type":"Point"}
}