{
  "type": "Feature",
  "properties": {
    "iso:country":"US",
    "sg:address":"8066 S Gessner Dr",
    "sg:city":"Houston",
    "sg:classifiers":[
        {
            "category":"Shopping",
            "subcategory":"Department Store",
            "type":"Retail Goods"
        }
    ],
    "sg:phone":"+1 713 272 9306",
    "sg:postcode":"77036",
    "sg:province":"TX",
    "sg:website":"www.rossstores.com",
    "wof:name":"Ross Dress For Less",
    "wof:placetype":"venue"
},
  "geometry": {"coordinates":[-95.53469800000001,29.690399],"type":"Point"}
}