{
  "type": "Feature",
  "properties": {
    "iso:country":"US",
    "sg:address":"130 E Daugherty St",
    "sg:city":"Denton",
    "sg:classifiers":[
        {
            "category":"Wholesale",
            "subcategory":"Groceries",
            "type":"Manufacturing & Wholesale Goods"
        }
    ],
    "sg:phone":"+1 940 382 0898",
    "sg:postcode":"76205",
    "sg:province":"TX",
    "sg:tags":[
        "frozen",
        "food"
    ],
    "wof:name":"Schwan's Sales Enterprises",
    "wof:placetype":"venue"
},
  "geometry": {"coordinates":[-97.13141,33.200911],"type":"Point"}
}