{
  "type": "Feature",
  "properties": {
    "iso:country":"US",
    "sg:address":"7804 Chimayo Cove",
    "sg:city":"Austin",
    "sg:classifiers":[
        {
            "category":"Building & Trades",
            "subcategory":"Construction",
            "type":"Services"
        }
    ],
    "sg:phone":"+1 512 458 6830",
    "sg:postcode":"78729",
    "sg:province":"TX",
    "sg:tags":[
        "contractor"
    ],
    "wof:name":"Mandalay Bay Pools & Spas",
    "wof:placetype":"venue"
},
  "geometry": {"coordinates":[-97.767623,30.439188],"type":"Point"}
}