{
  "type": "Feature",
  "properties": {
    "iso:country":"US",
    "sg:address":"3401 Greenbriar",
    "sg:city":"Midland",
    "sg:classifiers":[
        {
            "category":"Health Services",
            "subcategory":"Doctor",
            "type":"Services"
        }
    ],
    "sg:phone":"+1 432 686 0000",
    "sg:postcode":"79707",
    "sg:province":"TX",
    "sg:tags":[
        "physician",
        "surgeon"
    ],
    "wof:name":"Diabetes Center Of The Southwest",
    "wof:placetype":"venue"
},
  "geometry": {"coordinates":[-102.137688,32.01804],"type":"Point"}
}