{
  "type": "Feature",
  "properties": {
    "iso:country":"US",
    "sg:address":"8901 Bissonnet St",
    "sg:city":"Houston",
    "sg:classifiers":[
        {
            "category":"Real Estate",
            "subcategory":"Real Estate Operator",
            "type":"Services"
        }
    ],
    "sg:phone":"+1 713 772 6225",
    "sg:postcode":"77074",
    "sg:province":"TX",
    "sg:tags":[
        "building",
        "apartment"
    ],
    "wof:name":"Stoneriver Apartments",
    "wof:placetype":"venue"
},
  "geometry": {"coordinates":[-95.532912,29.67633],"type":"Point"}
}