{
  "type": "Feature",
  "properties": {
    "iso:country":"US",
    "sg:address":"5465 Blair Rd",
    "sg:city":"Dallas",
    "sg:classifiers":[
        {
            "category":"Real Estate",
            "subcategory":"Real Estate Agent",
            "type":"Services"
        }
    ],
    "sg:phone":"+1 214 750 0012",
    "sg:postcode":"75231",
    "sg:province":"TX",
    "wof:name":"Woodmere Properties",
    "wof:placetype":"venue"
},
  "geometry": {"coordinates":[-96.765685,32.885078],"type":"Point"}
}