{
  "type": "Feature",
  "properties": {
    "iso:country":"US",
    "sg:address":"1941 Torrey Pine Dr",
    "sg:city":"Flower Mound",
    "sg:classifiers":[
        {
            "category":"Professional",
            "type":"Services"
        }
    ],
    "sg:phone":"+1 972 874 7946",
    "sg:postcode":"75028",
    "sg:province":"TX",
    "wof:name":"Rebecca K McKnight Inc",
    "wof:placetype":"venue"
},
  "geometry": {"coordinates":[-97.059034,33.051115],"type":"Point"}
}