{
  "type": "Feature",
  "properties": {
    "iso:country":"US",
    "sg:address":"409 Talbot Ave Ste B",
    "sg:city":"Canutillo",
    "sg:classifiers":[
        {
            "category":"Home & Garden",
            "subcategory":"Household Appliances",
            "type":"Retail Goods"
        },
        {
            "category":"Communications",
            "subcategory":"Radio Station",
            "type":"Services"
        },
        {
            "category":"Building & Trades",
            "subcategory":"Equipment Rental",
            "type":"Services"
        },
        {
            "category":"Home & Garden",
            "subcategory":"Furniture",
            "type":"Retail Goods"
        }
    ],
    "sg:phone":"+1 915 877 7009",
    "sg:postcode":"79835",
    "sg:province":"TX",
    "sg:tags":[
        "renting",
        "television",
        "yard",
        "dryers-rental",
        "leasing",
        "washer",
        "radio-renting",
        "store",
        "lease"
    ],
    "wof:name":"Payless Rent To Own",
    "wof:placetype":"venue"
},
  "geometry": {"coordinates":[-106.59724,31.908234],"type":"Point"}
}