{
  "type": "Feature",
  "properties": {
    "iso:country":"US",
    "sg:address":"6246 Rufe Snow Dr",
    "sg:city":"Fort Worth",
    "sg:classifiers":[
        {
            "category":"Shopping",
            "subcategory":"Discount & Variety Stores",
            "type":"Retail Goods"
        }
    ],
    "sg:phone":"+1 817 427 2299",
    "sg:postcode":"76148",
    "sg:province":"TX",
    "sg:tags":[
        "merchandise",
        "general"
    ],
    "wof:name":"99 Cent Only Store",
    "wof:placetype":"venue"
},
  "geometry": {"coordinates":[-97.237927,32.860059],"type":"Point"}
}