{
  "type": "Feature",
  "properties": {
    "iso:country":"US",
    "sg:address":"7112 Alameda Ave",
    "sg:city":"El Paso",
    "sg:classifiers":[
        {
            "category":"Retail",
            "subcategory":"Repair Shop",
            "type":"Services"
        }
    ],
    "sg:phone":"+1 915 772 9988",
    "sg:postcode":"79915",
    "sg:province":"TX",
    "sg:tags":[
        "lock",
        "locksmith"
    ],
    "wof:name":"Valdez Lock & Key Shop",
    "wof:placetype":"venue"
},
  "geometry": {"coordinates":[-106.390181,31.751862],"type":"Point"}
}