{
  "type": "Feature",
  "properties": {
    "iso:country":"US",
    "sg:address":"1309 Nicklaus Loop N",
    "sg:city":"Laredo",
    "sg:classifiers":[
        {
            "category":"Professional",
            "type":"Services"
        }
    ],
    "sg:phone":"+1 956 724 7048",
    "sg:postcode":"78045",
    "sg:province":"TX",
    "wof:name":"Laredo Pro Source Inc",
    "wof:placetype":"venue"
},
  "geometry": {"coordinates":[-99.469093,27.578792],"type":"Point"}
}