{
  "type": "Feature",
  "properties": {
    "iso:country":"US",
    "sg:address":"9533 Crowley Rd",
    "sg:city":"Fort Worth",
    "sg:classifiers":[
        {
            "category":"Autos & Motor Vehicles",
            "subcategory":"Automobile Sales",
            "type":"Retail Goods"
        }
    ],
    "sg:phone":"+1 817 568 8108",
    "sg:postcode":"76134",
    "sg:province":"TX",
    "sg:tags":[
        "car",
        "dealer"
    ],
    "wof:name":"American Auto Sales & Repair",
    "wof:placetype":"venue"
},
  "geometry": {"coordinates":[-97.3485,32.616603],"type":"Point"}
}