{
  "type": "Feature",
  "properties": {
    "iso:country":"US",
    "sg:address":"2805 Canton St",
    "sg:city":"Dallas",
    "sg:classifiers":[
        {
            "category":"Organizations",
            "subcategory":"Labor Organization",
            "type":"Services"
        }
    ],
    "sg:phone":"+1 214 747 4792",
    "sg:postcode":"75226",
    "sg:province":"TX",
    "wof:name":"Dallas Stage Employees",
    "wof:placetype":"venue"
},
  "geometry": {"coordinates":[-96.781774,32.782573],"type":"Point"}
}