{
  "type": "Feature",
  "properties": {
    "iso:country":"US",
    "sg:address":"107 W Center St",
    "sg:city":"Kyle",
    "sg:classifiers":[
        {
            "category":"Personal",
            "subcategory":"Beauty Salon",
            "type":"Services"
        }
    ],
    "sg:phone":"+1 512 268 1143",
    "sg:postcode":"78640",
    "sg:province":"TX",
    "sg:tags":[
        "shop"
    ],
    "wof:name":"Snips & Tips",
    "wof:placetype":"venue"
},
  "geometry": {"coordinates":[-97.875766,29.988526],"type":"Point"}
}