{
  "type": "Feature",
  "properties": {
    "iso:country":"US",
    "sg:address":"710 West Avenue",
    "sg:city":"Austin",
    "sg:classifiers":[
        {
            "category":"Professional",
            "subcategory":"Lawyer & Legal Services",
            "type":"Services"
        }
    ],
    "sg:phone":"+1 512 320 8844",
    "sg:postcode":"78701",
    "sg:province":"TX",
    "wof:name":"Geiger Richard B Law Office",
    "wof:placetype":"venue"
},
  "geometry": {"coordinates":[-97.749948,30.271725],"type":"Point"}
}