{
  "type": "Feature",
  "properties": {
    "iso:country":"US",
    "sg:address":"21240 Foster Rd",
    "sg:city":"Spring",
    "sg:classifiers":[
        {
            "category":"Wholesale",
            "subcategory":"Hardware",
            "type":"Manufacturing & Wholesale Goods"
        }
    ],
    "sg:phone":"+1 281 651 1580",
    "sg:postcode":"77388",
    "sg:province":"TX",
    "sg:tags":[
        "hardware-wholesale",
        "manufacturer"
    ],
    "wof:name":"Hardware Resources",
    "wof:placetype":"venue"
},
  "geometry": {"coordinates":[-95.453827,30.067596],"type":"Point"}
}