{
  "type": "Feature",
  "properties": {
    "iso:country":"US",
    "sg:address":"1901 S 2nd St",
    "sg:city":"Mcallen",
    "sg:classifiers":[
        {
            "category":"Health Services",
            "subcategory":"Medical Lab",
            "type":"Services"
        }
    ],
    "sg:phone":"+1 956 668 1041",
    "sg:postcode":"78503",
    "sg:province":"TX",
    "sg:tags":[
        "laboratory"
    ],
    "wof:name":"US Oncology  Inc",
    "wof:placetype":"venue"
},
  "geometry": {"coordinates":[-98.22429099999999,26.184419],"type":"Point"}
}