{
  "type": "Feature",
  "properties": {
    "iso:country":"US",
    "sg:address":"4702 Lockwood Dr",
    "sg:city":"Houston",
    "sg:classifiers":[
        {
            "category":"Shopping",
            "subcategory":"Beauty & Cosmetics",
            "type":"Retail Goods"
        }
    ],
    "sg:phone":"+1 713 672 0706",
    "sg:postcode":"77026",
    "sg:province":"TX",
    "sg:tags":[
        "supply"
    ],
    "wof:name":"Supreme Beauty Supply",
    "wof:placetype":"venue"
},
  "geometry": {"coordinates":[-95.31683700000001,29.803103],"type":"Point"}
}