{
  "type": "Feature",
  "properties": {
    "iso:country":"US",
    "sg:address":"715 S College Ave",
    "sg:city":"Tyler",
    "sg:classifiers":[
        {
            "category":"Shopping",
            "subcategory":"Gifts & Souvenirs",
            "type":"Retail Goods"
        }
    ],
    "sg:phone":"+1 903 533 1771",
    "sg:postcode":"75701",
    "sg:province":"TX",
    "wof:name":"Crafts & Quilting Etc",
    "wof:placetype":"venue"
},
  "geometry": {"coordinates":[-95.30247,32.343],"type":"Point"}
}