{
  "type": "Feature",
  "properties": {
    "iso:country":"US",
    "sg:address":"756 N Carroll Ave",
    "sg:city":"Southlake",
    "sg:classifiers":[
        {
            "category":"Building & Trades",
            "subcategory":"Construction",
            "type":"Services"
        }
    ],
    "sg:phone":"+1 817 424 0888",
    "sg:postcode":"76092",
    "sg:province":"TX",
    "sg:tags":[
        "general",
        "commercial",
        "contractor"
    ],
    "wof:name":"Landmark General Contractors",
    "wof:placetype":"venue"
},
  "geometry": {"coordinates":[-97.13416599999999,32.947814],"type":"Point"}
}