{
  "type": "Feature",
  "properties": {
    "iso:country":"US",
    "sg:address":"2804 Julian Blvd",
    "sg:city":"Amarillo",
    "sg:classifiers":[
        {
            "category":"Health Services",
            "subcategory":"Health Practitioner",
            "type":"Services"
        }
    ],
    "sg:phone":"+1 806 379 9332",
    "sg:postcode":"79102",
    "sg:province":"TX",
    "sg:tags":[
        "hypnotist"
    ],
    "wof:name":"Inner Resource Self Hypnosis",
    "wof:placetype":"venue"
},
  "geometry": {"coordinates":[-101.86852399999999,35.202344],"type":"Point"}
}