{
  "type": "Feature",
  "properties": {
    "iso:country":"US",
    "sg:address":"10683 Huebner Rd",
    "sg:city":"San Antonio",
    "sg:classifiers":[
        {
            "category":"Autos & Motor Vehicles",
            "subcategory":"Fuel & Gas Station",
            "type":"Retail Goods"
        }
    ],
    "sg:phone":"+1 210 877 0738",
    "sg:postcode":"78240",
    "sg:province":"TX",
    "sg:tags":[
        "oil"
    ],
    "wof:name":"Shell",
    "wof:placetype":"venue"
},
  "geometry": {"coordinates":[-98.581441,29.542277],"type":"Point"}
}