{
  "type": "Feature",
  "properties": {
    "iso:country":"US",
    "sg:address":"10612 Sentinel St",
    "sg:city":"San Antonio",
    "sg:classifiers":[
        {
            "category":"Freight",
            "type":"Transportation"
        }
    ],
    "sg:phone":"+1 210 599 3100",
    "sg:postcode":"78217",
    "sg:province":"TX",
    "sg:tags":[
        "shipping",
        "agent"
    ],
    "wof:name":"Air Today Inc",
    "wof:placetype":"venue"
},
  "geometry": {"coordinates":[-98.445098,29.539108],"type":"Point"}
}