{
  "type": "Feature",
  "properties": {
    "iso:country":"US",
    "sg:address":"2701 Laurel Creek Way",
    "sg:city":"Pearland",
    "sg:classifiers":[
        {
            "category":"Wholesale",
            "subcategory":"Construction Materials",
            "type":"Manufacturing & Wholesale Goods"
        },
        {
            "category":"Manufacturing",
            "subcategory":"Glass & Minerals",
            "type":"Manufacturing & Wholesale Goods"
        }
    ],
    "sg:phone":"+1 281 485 3333",
    "sg:postcode":"77581",
    "sg:province":"TX",
    "sg:tags":[
        "stone",
        "cut",
        "product",
        "terrazzo",
        "mfg"
    ],
    "wof:name":"Southwest Stone Associates",
    "wof:placetype":"venue"
},
  "geometry": {"coordinates":[-95.23571,29.55463],"type":"Point"}
}