{
  "type": "Feature",
  "properties": {
    "iso:country":"US",
    "sg:address":"2713 S Henderson Blvd",
    "sg:city":"Kilgore",
    "sg:classifiers":[
        {
            "category":"Shopping",
            "subcategory":"Gifts & Souvenirs",
            "type":"Retail Goods"
        }
    ],
    "sg:phone":"+1 903 983 3583",
    "sg:postcode":"75662",
    "sg:province":"TX",
    "wof:name":"Corners",
    "wof:placetype":"venue"
},
  "geometry": {"coordinates":[-94.86906999999999,32.363714],"type":"Point"}
}