{
  "type": "Feature",
  "properties": {
    "iso:country":"US",
    "sg:address":"3600 Halifax Dr",
    "sg:city":"Arlington",
    "sg:classifiers":[
        {
            "category":"Health Services",
            "subcategory":"Clinic",
            "type":"Services"
        }
    ],
    "sg:phone":"+1 817 303 8597",
    "sg:postcode":"76013",
    "sg:province":"TX",
    "wof:name":"Derma Spa Laser Clinic Inc",
    "wof:placetype":"venue"
},
  "geometry": {"coordinates":[-97.163416,32.722788],"type":"Point"}
}