{
  "type": "Feature",
  "properties": {
    "iso:country":"US",
    "sg:address":"531 Talbot Ave",
    "sg:city":"Canutillo",
    "sg:classifiers":[
        {
            "category":"Shopping",
            "subcategory":"Gifts & Souvenirs",
            "type":"Retail Goods"
        }
    ],
    "sg:phone":"+1 915 877 3276",
    "sg:postcode":"79835",
    "sg:province":"TX",
    "wof:name":"Super Fiesta",
    "wof:placetype":"venue"
},
  "geometry": {"coordinates":[-106.596954,31.908295],"type":"Point"}
}