{
  "type": "Feature",
  "properties": {
    "iso:country":"US",
    "sg:address":"931 Wax Myrtle Ln",
    "sg:city":"Houston",
    "sg:classifiers":[
        {
            "category":"Shopping",
            "subcategory":"Books",
            "type":"Retail Goods"
        }
    ],
    "sg:phone":"+1 713 465 6569",
    "sg:postcode":"77079",
    "sg:province":"TX",
    "wof:name":"Marshel Cooks",
    "wof:placetype":"venue"
},
  "geometry": {"coordinates":[-95.567065,29.778394],"type":"Point"}
}