{
  "type": "Feature",
  "properties": {
    "iso:country":"US",
    "sg:address":"12907 Agency Dr",
    "sg:city":"San Antonio",
    "sg:classifiers":[
        {
            "category":"Wholesale",
            "subcategory":"Metals & Minerals",
            "type":"Manufacturing & Wholesale Goods"
        }
    ],
    "sg:phone":"+1 210 490 2552",
    "sg:postcode":"78247",
    "sg:province":"TX",
    "sg:tags":[
        "steel",
        "casting",
        "mfg",
        "roll",
        "doe",
        "fabrication"
    ],
    "wof:name":"Gimsa International Inc",
    "wof:placetype":"venue"
},
  "geometry": {"coordinates":[-98.428118,29.558392],"type":"Point"}
}