{
  "type": "Feature",
  "properties": {
    "iso:country":"US",
    "sg:address":"250 W Houston St",
    "sg:city":"San Antonio",
    "sg:classifiers":[
        {
            "category":"Restaurant",
            "type":"Food & Drink"
        }
    ],
    "sg:menulink":"http://www.allmenus.com/tx/san-antonio/94467-dominos-pizza/menu/",
    "sg:phone":"+1 210 527 9505",
    "sg:postcode":"78205",
    "sg:province":"TX",
    "sg:tags":[
        "american",
        "wing",
        "pizza"
    ],
    "wof:name":"Domino's Pizza",
    "wof:placetype":"venue"
},
  "geometry": {"coordinates":[-98.495903,29.426444],"type":"Point"}
}