{
  "type": "Feature",
  "properties": {
    "iso:country":"US",
    "sg:address":"301 S Rose Ave",
    "sg:city":"Breckenridge",
    "sg:classifiers":[
        {
            "category":"Organizations",
            "subcategory":"Religious Organization",
            "type":"Services"
        }
    ],
    "sg:phone":"+1 254 559 8954",
    "sg:postcode":"76424",
    "sg:province":"TX",
    "wof:name":"First Baptist Church Parsonage",
    "wof:placetype":"venue"
},
  "geometry": {"coordinates":[-98.90506999999999,32.753524],"type":"Point"}
}