{
  "type": "Feature",
  "properties": {
    "iso:country":"US",
    "sg:address":"1105 Tinker Rd",
    "sg:city":"Colleyville",
    "sg:classifiers":[
        {
            "category":"Shopping",
            "type":"Retail Goods"
        }
    ],
    "sg:phone":"+1 817 488 7891",
    "sg:postcode":"76034",
    "sg:province":"TX",
    "sg:tags":[
        "miscellaneous",
        "store"
    ],
    "wof:name":"Been Piddlin",
    "wof:placetype":"venue"
},
  "geometry": {"coordinates":[-97.154324,32.90027],"type":"Point"}
}