{
  "type": "Feature",
  "properties": {
    "iso:country":"US",
    "sg:address":"711 N Carancahua St",
    "sg:city":"Corpus Christi",
    "sg:classifiers":[
        {
            "category":"Wholesale",
            "subcategory":"Machinery & Supplies",
            "type":"Manufacturing & Wholesale Goods"
        }
    ],
    "sg:phone":"+1 361 887 0861",
    "sg:postcode":"78475",
    "sg:province":"TX",
    "sg:tags":[
        "field",
        "oil"
    ],
    "wof:name":"Padre Tubular Inc",
    "wof:placetype":"venue"
},
  "geometry": {"coordinates":[-97.39749399999999,27.797162],"type":"Point"}
}