{
  "type": "Feature",
  "properties": {
    "iso:country":"US",
    "sg:address":"101 N Shoreline Blvd",
    "sg:city":"Corpus Christi",
    "sg:classifiers":[
        {
            "category":"Banks & Credit Unions",
            "subcategory":"Investment Brokerage",
            "type":"Services"
        }
    ],
    "sg:phone":"+1 361 904 0941",
    "sg:postcode":"78401",
    "sg:province":"TX",
    "sg:tags":[
        "land",
        "oil",
        "lease"
    ],
    "wof:name":"Jdmi",
    "wof:placetype":"venue"
},
  "geometry": {"coordinates":[-97.392573,27.789982],"type":"Point"}
}