{
  "type": "Feature",
  "properties": {
    "iso:country":"US",
    "sg:address":"10981 FM 20",
    "sg:city":"Kingsbury",
    "sg:classifiers":[
        {
            "category":"Farming",
            "subcategory":"Farm",
            "type":"Manufacturing & Wholesale Goods"
        }
    ],
    "sg:phone":"+1 830 639 4686",
    "sg:postcode":"78638",
    "sg:province":"TX",
    "wof:name":"Pomrenke Farms",
    "wof:placetype":"venue"
},
  "geometry": {"coordinates":[-97.879532,29.687834],"type":"Point"}
}