{
  "type": "Feature",
  "properties": {
    "iso:country":"US",
    "sg:address":"2460 W Norman Cir",
    "sg:city":"Orange",
    "sg:classifiers":[
        {
            "category":"Real Estate",
            "subcategory":"Real Estate Operator",
            "type":"Services"
        }
    ],
    "sg:phone":"+1 409 882 9719",
    "sg:postcode":"77630",
    "sg:province":"TX",
    "sg:tags":[
        "property",
        "lessor"
    ],
    "wof:name":"Triple SSS Rentals Inc",
    "wof:placetype":"venue"
},
  "geometry": {"coordinates":[-93.81124800000001,30.07863],"type":"Point"}
}