{
  "type": "Feature",
  "properties": {
    "iso:country":"US",
    "sg:address":"2713 Moffett Ct",
    "sg:city":"Plano",
    "sg:classifiers":[
        {
            "category":"Health Services",
            "subcategory":"Clinic",
            "type":"Services"
        }
    ],
    "sg:phone":"+1 972 608 8721",
    "sg:postcode":"75093",
    "sg:province":"TX",
    "wof:name":"Plano Medical Management Inc",
    "wof:placetype":"venue"
},
  "geometry": {"coordinates":[-96.814865,33.038063],"type":"Point"}
}