{
  "type": "Feature",
  "properties": {
    "iso:country":"US",
    "sg:address":"5624 87th Pl",
    "sg:city":"Lubbock",
    "sg:classifiers":[
        {
            "category":"Building & Trades",
            "subcategory":"Electrical",
            "type":"Services"
        }
    ],
    "sg:phone":"+1 806 798 7077",
    "sg:postcode":"79424",
    "sg:province":"TX",
    "sg:tags":[
        "electric",
        "contractor"
    ],
    "wof:name":"Biles Electric",
    "wof:placetype":"venue"
},
  "geometry": {"coordinates":[-101.934274,33.513995],"type":"Point"}
}