{
  "type": "Feature",
  "properties": {
    "iso:country":"US",
    "sg:address":"3125 Wroxton Rd",
    "sg:city":"Houston",
    "sg:classifiers":[
        {
            "category":"Building & Trades",
            "subcategory":"Construction",
            "type":"Services"
        }
    ],
    "sg:phone":"+1 713 667 3494",
    "sg:postcode":"77005",
    "sg:province":"TX",
    "sg:tags":[
        "interior",
        "design"
    ],
    "wof:name":"Graul Karen Design, ASID",
    "wof:placetype":"venue"
},
  "geometry": {"coordinates":[-95.427299,29.7244],"type":"Point"}
}