{
  "type": "Feature",
  "properties": {
    "iso:country":"US",
    "sg:address":"2601 Saratoga",
    "sg:city":"Mc Kinney",
    "sg:classifiers":[
        {
            "category":"Professional",
            "subcategory":"Computer Services",
            "type":"Services"
        }
    ],
    "sg:phone":"+1 972 544 8360",
    "sg:postcode":"75070",
    "sg:province":"TX",
    "sg:tags":[
        "prepackaged",
        "software"
    ],
    "wof:name":"Gregory Coffin",
    "wof:placetype":"venue"
},
  "geometry": {"coordinates":[-96.65056199999999,33.167156],"type":"Point"}
}