{
  "type": "Feature",
  "properties": {
    "iso:country":"US",
    "sg:address":"7358 Alameda Ave",
    "sg:city":"El Paso",
    "sg:classifiers":[
        {
            "category":"Autos & Motor Vehicles",
            "subcategory":"Automobile Sales",
            "type":"Retail Goods"
        }
    ],
    "sg:phone":"+1 915 772 4747",
    "sg:postcode":"79915",
    "sg:province":"TX",
    "sg:tags":[
        "car",
        "used"
    ],
    "wof:name":"Torresday Auto Sales",
    "wof:placetype":"venue"
},
  "geometry": {"coordinates":[-106.378743,31.742763],"type":"Point"}
}