{
  "type": "Feature",
  "properties": {
    "iso:country":"US",
    "sg:address":"2602 Texas Ave",
    "sg:city":"Texas City",
    "sg:classifiers":[
        {
            "category":"Professional",
            "subcategory":"Testing Lab",
            "type":"Services"
        }
    ],
    "sg:phone":"+1 409 948 1012",
    "sg:postcode":"77590",
    "sg:province":"TX",
    "sg:tags":[
        "x",
        "business",
        "laboratory"
    ],
    "wof:name":"Blazer Inspection Inc",
    "wof:placetype":"venue"
},
  "geometry": {"coordinates":[-94.933806,29.383934],"type":"Point"}
}