{
  "type": "Feature",
  "properties": {
    "iso:country":"US",
    "sg:address":"3 Jesse James Dr",
    "sg:city":"Belton",
    "sg:classifiers":[
        {
            "category":"Building & Trades",
            "subcategory":"Cleaning & Sanitation",
            "type":"Services"
        }
    ],
    "sg:phone":"+1 254 760 7144",
    "sg:postcode":"76513",
    "sg:province":"TX",
    "sg:tags":[
        "duct",
        "maintenance",
        "air"
    ],
    "wof:name":"Smith Air Duct Cleaning",
    "wof:placetype":"venue"
},
  "geometry": {"coordinates":[-97.470072,31.146465],"type":"Point"}
}