{
  "type": "Feature",
  "properties": {
    "iso:country":"US",
    "sg:address":"7485 Redbud Ln",
    "sg:city":"Fort Worth",
    "sg:classifiers":[
        {
            "category":"Professional",
            "subcategory":"Business Services",
            "type":"Services"
        }
    ],
    "sg:phone":"+1 817 238 7253",
    "sg:postcode":"76135",
    "sg:province":"TX",
    "wof:name":"Jean Bockstein Interiors",
    "wof:placetype":"venue"
},
  "geometry": {"coordinates":[-97.529901,32.834509],"type":"Point"}
}