{
  "type": "Feature",
  "properties": {
    "iso:country":"US",
    "sg:address":"517 Miramar Pl",
    "sg:city":"Corpus Christi",
    "sg:classifiers":[
        {
            "category":"Retail",
            "subcategory":"Portrait Studio",
            "type":"Services"
        }
    ],
    "sg:phone":"+1 361 852 1905",
    "sg:postcode":"78411",
    "sg:province":"TX",
    "sg:tags":[
        "photographer",
        "commercial",
        "photo"
    ],
    "wof:name":"Dick Wittliff's Photography",
    "wof:placetype":"venue"
},
  "geometry": {"coordinates":[-97.377273,27.733296],"type":"Point"}
}