{
  "type": "Feature",
  "properties": {
    "iso:country":"US",
    "sg:address":"115 NW Newton Dr",
    "sg:city":"Burleson",
    "sg:classifiers":[
        {
            "category":"Professional",
            "subcategory":"Lawyer & Legal Services",
            "type":"Services"
        }
    ],
    "sg:phone":"+1 817 295 9003",
    "sg:postcode":"76028",
    "sg:province":"TX",
    "wof:name":"Shanks George M Jr PC",
    "wof:placetype":"venue"
},
  "geometry": {"coordinates":[-97.3293,32.539501],"type":"Point"}
}