{
  "type": "Feature",
  "properties": {
    "iso:country":"US",
    "sg:address":"1217 S Hewitt Dr",
    "sg:city":"Hewitt",
    "sg:classifiers":[
        {
            "category":"Personal",
            "subcategory":"Beauty Salon",
            "type":"Services"
        }
    ],
    "sg:phone":"+1 254 224 6771",
    "sg:postcode":"76643",
    "sg:province":"TX",
    "wof:name":"Dream Escape",
    "wof:placetype":"venue"
},
  "geometry": {"coordinates":[-97.20556000000001,31.443196],"type":"Point"}
}