{
  "type": "Feature",
  "properties": {
    "iso:country":"US",
    "sg:address":"3243 Topeka St",
    "sg:city":"Corpus Christi",
    "sg:classifiers":[
        {
            "category":"Building & Trades",
            "subcategory":"Plumbing",
            "type":"Services"
        }
    ],
    "sg:phone":"+1 361 887 6762",
    "sg:postcode":"78404",
    "sg:province":"TX",
    "sg:tags":[
        "plumbing",
        "contractor"
    ],
    "wof:name":"Doc's Sewer & Drain",
    "wof:placetype":"venue"
},
  "geometry": {"coordinates":[-97.38821,27.755866],"type":"Point"}
}