{
  "type": "Feature",
  "properties": {
    "iso:country":"US",
    "sg:address":"507 E 42nd St",
    "sg:city":"Austin",
    "sg:classifiers":[
        {
            "category":"Recreation",
            "type":"Entertainment"
        }
    ],
    "sg:phone":"+1 512 454 1428",
    "sg:postcode":"78751",
    "sg:province":"TX",
    "wof:name":"Hyde Park Doll Shop",
    "wof:placetype":"venue"
},
  "geometry": {"coordinates":[-97.726223,30.30256],"type":"Point"}
}