{
  "type": "Feature",
  "properties": {
    "iso:country":"US",
    "sg:address":"762 Co Rd 403",
    "sg:city":"Floresville",
    "sg:classifiers":[
        {
            "category":"Farming",
            "subcategory":"Farm",
            "type":"Manufacturing & Wholesale Goods"
        }
    ],
    "sg:phone":"+1 830 393 6022",
    "sg:postcode":"78114",
    "sg:province":"TX",
    "wof:name":"Rhew Farms",
    "wof:placetype":"venue"
},
  "geometry": {"coordinates":[-98.09381399999999,29.179203],"type":"Point"}
}