{
  "type": "Feature",
  "properties": {
    "iso:country":"US",
    "sg:address":"49 Country Oaks Dr",
    "sg:city":"Buda",
    "sg:classifiers":[
        {
            "category":"Restaurant",
            "type":"Food & Drink"
        }
    ],
    "sg:phone":"+1 512 445 5117",
    "sg:postcode":"78610",
    "sg:province":"TX",
    "sg:tags":[
        "eating"
    ],
    "wof:name":"Beilei Restaurants LLC",
    "wof:placetype":"venue"
},
  "geometry": {"coordinates":[-97.884486,30.121595],"type":"Point"}
}