{
  "type": "Feature",
  "properties": {
    "iso:country":"US",
    "sg:address":"7550 Fm 1960 Rd W",
    "sg:city":"Houston",
    "sg:classifiers":[
        {
            "category":"Shopping",
            "subcategory":"Department Store",
            "type":"Retail Goods"
        }
    ],
    "sg:phone":"+1 281 477 8100",
    "sg:postcode":"77070",
    "sg:province":"TX",
    "sg:website":"http://www.rossstores.com/",
    "wof:name":"Ross Dress for Less",
    "wof:placetype":"venue"
},
  "geometry": {"coordinates":[-95.541517,29.964816],"type":"Point"}
}