{
  "type": "Feature",
  "properties": {
    "iso:country":"US",
    "sg:address":"902 Capitol St",
    "sg:city":"Houston",
    "sg:classifiers":[
        {
            "category":"Bars & Pubs",
            "subcategory":"Dive Bar",
            "type":"Food & Drink"
        }
    ],
    "sg:phone":"+1 713 224 3200",
    "sg:postcode":"77002",
    "sg:province":"TX",
    "sg:website":"www.sunnysbar.com",
    "wof:name":"Sunny's Bar",
    "wof:placetype":"venue"
},
  "geometry": {"coordinates":[-95.364012,29.759681],"type":"Point"}
}