{
  "type": "Feature",
  "properties": {
    "iso:country":"US",
    "sg:address":"16635 Huebner Rd",
    "sg:city":"San Antonio",
    "sg:classifiers":[
        {
            "category":"Real Estate",
            "subcategory":"Real Estate Agent",
            "type":"Services"
        }
    ],
    "sg:phone":"+1 210 408 2000",
    "sg:postcode":"78248",
    "sg:province":"TX",
    "wof:name":"Re/Max Associates 2000",
    "wof:placetype":"venue"
},
  "geometry": {"coordinates":[-98.527056,29.595499],"type":"Point"}
}