{
  "type": "Feature",
  "properties": {
    "iso:country":"US",
    "sg:address":"6634 Sylvan Rd",
    "sg:city":"Houston",
    "sg:classifiers":[
        {
            "category":"Retail",
            "subcategory":"Funeral Services",
            "type":"Services"
        }
    ],
    "sg:phone":"+1 713 928 5134",
    "sg:postcode":"77023",
    "sg:province":"TX",
    "sg:tags":[
        "crematory"
    ],
    "wof:name":"First Cremations",
    "wof:placetype":"venue"
},
  "geometry": {"coordinates":[-95.312398,29.718298],"type":"Point"}
}