{
  "type": "Feature",
  "properties": {
    "iso:country":"US",
    "sg:address":"2601 Preston Rd",
    "sg:city":"Frisco",
    "sg:classifiers":[
        {
            "category":"Food & Beverages",
            "subcategory":"Bakery",
            "type":"Retail Goods"
        }
    ],
    "sg:phone":"+1 972 668 1570",
    "sg:postcode":"75034",
    "sg:province":"TX",
    "sg:tags":[
        "cookie",
        "grocery",
        "cracker"
    ],
    "wof:name":"Great American Cookie Co",
    "wof:placetype":"venue"
},
  "geometry": {"coordinates":[-96.805673,33.099351],"type":"Point"}
}