{
  "type": "Feature",
  "properties": {
    "iso:country":"US",
    "sg:address":"2458 Little York Rd",
    "sg:city":"Houston",
    "sg:classifiers":[
        {
            "category":"Building & Trades",
            "subcategory":"Plumbing",
            "type":"Services"
        }
    ],
    "sg:phone":"+1 713 937 1200",
    "sg:postcode":"77093",
    "sg:province":"TX",
    "sg:tags":[
        "pipe",
        "inspection"
    ],
    "sg:website":"http://www.natoil.com",
    "wof:name":"National Oilwell Varco, Inc.",
    "wof:placetype":"venue"
},
  "geometry": {"coordinates":[-95.347964,29.871009],"type":"Point"}
}