{
  "type": "Feature",
  "properties": {
    "iso:country":"US",
    "sg:address":"1600 11th St",
    "sg:city":"Wichita Falls",
    "sg:classifiers":[
        {
            "category":"Health Services",
            "subcategory":"Hospital",
            "type":"Services"
        }
    ],
    "sg:phone":"+1 940 764 7000",
    "sg:postcode":"76301",
    "sg:province":"TX",
    "sg:tags":[
        "general"
    ],
    "wof:name":"11th Street Campus Hospital",
    "wof:placetype":"venue"
},
  "geometry": {"coordinates":[-98.5027,33.901609],"type":"Point"}
}