{
  "type": "Feature",
  "properties": {
    "iso:country":"US",
    "sg:address":"411 Crockett Dr",
    "sg:city":"Killeen",
    "sg:classifiers":[
        {
            "category":"Building & Trades",
            "subcategory":"Landscaping Services",
            "type":"Services"
        }
    ],
    "sg:phone":"+1 254 634 2231",
    "sg:postcode":"76541",
    "sg:province":"TX",
    "sg:tags":[
        "agricultural"
    ],
    "wof:name":"Karls Lawn Service",
    "wof:placetype":"venue"
},
  "geometry": {"coordinates":[-97.713526,31.119619],"type":"Point"}
}