{
  "type": "Feature",
  "properties": {
    "iso:country":"US",
    "sg:address":"2155 N Macgregor Way",
    "sg:city":"Houston",
    "sg:classifiers":[
        {
            "category":"Real Estate",
            "subcategory":"Developer",
            "type":"Services"
        }
    ],
    "sg:phone":"+1 713 523 9372",
    "sg:postcode":"77004",
    "sg:province":"TX",
    "wof:name":"Christians Development Co",
    "wof:placetype":"venue"
},
  "geometry": {"coordinates":[-95.38402000000001,29.713207],"type":"Point"}
}