{
  "type": "Feature",
  "properties": {
    "iso:country":"US",
    "sg:address":"8316 Rain Forest Ln",
    "sg:city":"Fort Worth",
    "sg:classifiers":[
        {
            "category":"Professional",
            "subcategory":"Management & Consulting",
            "type":"Services"
        }
    ],
    "sg:phone":"+1 817 370 2282",
    "sg:postcode":"76123",
    "sg:province":"TX",
    "wof:name":"Nas Newssenior Marketing",
    "wof:placetype":"venue"
},
  "geometry": {"coordinates":[-97.372365,32.619617],"type":"Point"}
}