{
  "type": "Feature",
  "properties": {
    "iso:country":"US",
    "sg:address":"212 Robert E Lee Dr",
    "sg:city":"Tyler",
    "sg:classifiers":[
        {
            "category":"Shopping",
            "type":"Retail Goods"
        }
    ],
    "sg:phone":"+1 903 581 6652",
    "sg:postcode":"75703",
    "sg:province":"TX",
    "sg:tags":[
        "merchandise"
    ],
    "wof:name":"Good Stuff For Man and Beast",
    "wof:placetype":"venue"
},
  "geometry": {"coordinates":[-95.305105,32.277728],"type":"Point"}
}