{
  "type": "Feature",
  "properties": {
    "iso:country":"US",
    "sg:address":"125 5th Ave",
    "sg:city":"Nederland",
    "sg:classifiers":[
        {
            "category":"Professional",
            "type":"Services"
        }
    ],
    "sg:phone":"+1 409 722 7080",
    "sg:postcode":"77627",
    "sg:province":"TX",
    "wof:name":"FAA Inc",
    "wof:placetype":"venue"
},
  "geometry": {"coordinates":[-94.020397,29.995981],"type":"Point"}
}