{
  "type": "Feature",
  "properties": {
    "iso:country":"US",
    "sg:address":"2535 E Southlake Blvd",
    "sg:city":"Southlake",
    "sg:classifiers":[
        {
            "category":"Banks & Credit Unions",
            "subcategory":"Bank",
            "type":"Services"
        }
    ],
    "sg:phone":"+1 817 745 5626",
    "sg:postcode":"76092",
    "sg:province":"TX",
    "sg:tags":[
        "residential",
        "commercial",
        "mortgage"
    ],
    "wof:name":"Liberty Lending Home Loans LLC",
    "wof:placetype":"venue"
},
  "geometry": {"coordinates":[-97.111963,32.939493],"type":"Point"}
}