{
  "type": "Feature",
  "properties": {
    "iso:country":"US",
    "sg:address":"610 Boyce Rd",
    "sg:city":"Waxahachie",
    "sg:classifiers":[
        {
            "category":"Farming",
            "subcategory":"Livestock Farm",
            "type":"Manufacturing & Wholesale Goods"
        }
    ],
    "sg:phone":"+1 972 938 8747",
    "sg:postcode":"75165",
    "sg:province":"TX",
    "sg:tags":[
        "beef",
        "feedlot",
        "cattle"
    ],
    "wof:name":"Stille Nacht Farms",
    "wof:placetype":"venue"
},
  "geometry": {"coordinates":[-96.770872,32.402007],"type":"Point"}
}