{
  "type": "Feature",
  "properties": {
    "iso:country":"US",
    "sg:address":"9105 W Sam Houston Pkwy N",
    "sg:city":"Houston",
    "sg:phone":"+1 281 640 9946",
    "sg:postcode":"77064",
    "sg:province":"TX",
    "sg:website":"http://www.lafitness.com/",
    "wof:name":"La Fitness",
    "wof:placetype":"venue"
},
  "geometry": {"coordinates":[-95.552944,29.903065],"type":"Point"}
}