{
  "type": "Feature",
  "properties": {
    "iso:country":"US",
    "sg:address":"1801 Old Nacogdoches Rd",
    "sg:city":"Henderson",
    "sg:classifiers":[
        {
            "category":"Organizations",
            "subcategory":"Religious Organization",
            "type":"Services"
        }
    ],
    "sg:phone":"+1 903 657 8277",
    "sg:postcode":"75654",
    "sg:province":"TX",
    "sg:tags":[
        "church"
    ],
    "wof:name":"Southside Baptist Church Inc",
    "wof:placetype":"venue"
},
  "geometry": {"coordinates":[-94.79745699999999,32.134845],"type":"Point"}
}