{
  "type": "Feature",
  "properties": {
    "iso:country":"US",
    "sg:address":"1325 Audubon Pl",
    "sg:city":"Beaumont",
    "sg:classifiers":[
        {
            "category":"Professional",
            "type":"Services"
        }
    ],
    "sg:phone":"+1 409 866 9854",
    "sg:postcode":"77706",
    "sg:province":"TX",
    "wof:name":"Bayou Adventures Inc",
    "wof:placetype":"venue"
},
  "geometry": {"coordinates":[-94.16927200000001,30.092896],"type":"Point"}
}