{
  "type": "Feature",
  "properties": {
    "iso:country":"US",
    "sg:address":"238 Crest Circle Dr",
    "sg:city":"San Marcos",
    "sg:classifiers":[
        {
            "category":"Building & Trades",
            "subcategory":"Plumbing",
            "type":"Services"
        }
    ],
    "sg:phone":"+1 512 353 3737",
    "sg:postcode":"78666",
    "sg:province":"TX",
    "sg:tags":[
        "contractor"
    ],
    "wof:name":"Jack Ulbricht Plumber",
    "wof:placetype":"venue"
},
  "geometry": {"coordinates":[-97.96488100000001,29.783168],"type":"Point"}
}