{
  "type": "Feature",
  "properties": {
    "iso:country":"US",
    "sg:address":"240 E 3rd St",
    "sg:city":"Hereford",
    "sg:classifiers":[
        {
            "category":"Shopping",
            "subcategory":"Stationery & Office Supplies",
            "type":"Retail Goods"
        }
    ],
    "sg:phone":"+1 806 364 1090",
    "sg:postcode":"79045",
    "sg:province":"TX",
    "sg:tags":[
        "furniture"
    ],
    "wof:name":"First Printing Co & Office Sup",
    "wof:placetype":"venue"
},
  "geometry": {"coordinates":[-102.397462,34.817457],"type":"Point"}
}