{
  "type": "Feature",
  "properties": {
    "iso:country":"US",
    "sg:address":"310 Guadalupe St",
    "sg:city":"Laredo",
    "sg:classifiers":[
        {
            "category":"Professional",
            "subcategory":"Lawyer & Legal Services",
            "type":"Services"
        }
    ],
    "sg:phone":"+1 956 724 1000",
    "sg:postcode":"78040",
    "sg:province":"TX",
    "sg:tags":[
        "attorney"
    ],
    "wof:name":"Ricardo Gonzalez Law Office",
    "wof:placetype":"venue"
},
  "geometry": {"coordinates":[-99.49349599999999,27.50664],"type":"Point"}
}