{
  "type": "Feature",
  "properties": {
    "iso:country":"US",
    "sg:address":"2807 S Westmoreland Rd",
    "sg:city":"Dallas",
    "sg:classifiers":[
        {
            "category":"Professional",
            "subcategory":"Employment Agencies",
            "type":"Services"
        }
    ],
    "sg:phone":"+1 214 623 8190",
    "sg:postcode":"75233",
    "sg:province":"TX",
    "wof:name":"Pdq Temporaries",
    "wof:placetype":"venue"
},
  "geometry": {"coordinates":[-96.87471600000001,32.716218],"type":"Point"}
}