{
  "type": "Feature",
  "properties": {
    "iso:country":"US",
    "sg:address":"1553 Greg Powers Dr",
    "sg:city":"El Paso",
    "sg:classifiers":[
        {
            "category":"Building & Trades",
            "subcategory":"Construction",
            "type":"Services"
        }
    ],
    "sg:phone":"+1 915 855 2684",
    "sg:postcode":"79936",
    "sg:province":"TX",
    "sg:tags":[
        "nonresidential"
    ],
    "wof:name":"Elite Remodeling",
    "wof:placetype":"venue"
},
  "geometry": {"coordinates":[-106.297254,31.74725],"type":"Point"}
}