{
  "type": "Feature",
  "properties": {
    "iso:country":"US",
    "sg:address":"6015 Canyon Dr",
    "sg:city":"Amarillo",
    "sg:classifiers":[
        {
            "category":"Retail",
            "subcategory":"Auto Repair",
            "type":"Services"
        }
    ],
    "sg:phone":"+1 806 355 4009",
    "sg:postcode":"79110",
    "sg:province":"TX",
    "sg:tags":[
        "transmission"
    ],
    "wof:name":"Five Star Transmission",
    "wof:placetype":"venue"
},
  "geometry": {"coordinates":[-101.88629400000001,35.146493],"type":"Point"}
}