{
  "type": "Feature",
  "properties": {
    "iso:country":"US",
    "sg:address":"1950 Alpha Dr",
    "sg:city":"Rockwall",
    "sg:classifiers":[
        {
            "category":"Organizations",
            "subcategory":"Religious Organization",
            "type":"Services"
        }
    ],
    "sg:phone":"+1 972 722 7941",
    "sg:postcode":"75087",
    "sg:province":"TX",
    "sg:tags":[
        "church"
    ],
    "wof:name":"Rockwall Friendship Bapt Chr",
    "wof:placetype":"venue"
},
  "geometry": {"coordinates":[-96.445182,32.914431],"type":"Point"}
}