{
  "type": "Feature",
  "properties": {
    "iso:country":"US",
    "sg:address":"207 Coronet St",
    "sg:city":"San Antonio",
    "sg:classifiers":[
        {
            "category":"Organizations",
            "subcategory":"Community Association",
            "type":"Services"
        }
    ],
    "sg:phone":"+1 210 342 0348",
    "sg:postcode":"78216",
    "sg:province":"TX",
    "wof:name":"Crown Hill Park Neighborhood A",
    "wof:placetype":"venue"
},
  "geometry": {"coordinates":[-98.49282599999999,29.523556],"type":"Point"}
}