{
  "type": "Feature",
  "properties": {
    "iso:country":"US",
    "sg:address":"2721 Terrell Rd",
    "sg:city":"Greenville",
    "sg:classifiers":[
        {
            "category":"Retail",
            "subcategory":"Veterinary Services",
            "type":"Services"
        }
    ],
    "sg:phone":"+1 903 454 1563",
    "sg:postcode":"75402",
    "sg:province":"TX",
    "sg:tags":[
        "veterinarian"
    ],
    "wof:name":"Kimberlin Larry Dvm",
    "wof:placetype":"venue"
},
  "geometry": {"coordinates":[-96.109568,33.106294],"type":"Point"}
}