{
  "type": "Feature",
  "properties": {
    "iso:country":"US",
    "sg:address":"903 E Ogden St",
    "sg:city":"Del Rio",
    "sg:classifiers":[
        {
            "category":"Building & Trades",
            "subcategory":"Plumbing",
            "type":"Services"
        }
    ],
    "sg:phone":"+1 830 774 7149",
    "sg:postcode":"78840",
    "sg:province":"TX",
    "sg:tags":[
        "contractor"
    ],
    "wof:name":"Western Electrical",
    "wof:placetype":"venue"
},
  "geometry": {"coordinates":[-100.890612,29.366319],"type":"Point"}
}