{
  "type": "Feature",
  "properties": {
    "iso:country":"US",
    "sg:address":"2163 Little Cedar Dr",
    "sg:city":"Humble",
    "sg:classifiers":[
        {
            "category":"Building & Trades",
            "subcategory":"Construction",
            "type":"Services"
        }
    ],
    "sg:phone":"+1 281 358 6616",
    "sg:postcode":"77339",
    "sg:province":"TX",
    "sg:tags":[
        "house"
    ],
    "wof:name":"Bluff Creek Homes",
    "wof:placetype":"venue"
},
  "geometry": {"coordinates":[-95.215952,30.059679],"type":"Point"}
}