{
  "type": "Feature",
  "properties": {
    "iso:country":"US",
    "sg:address":"809 S 2nd St",
    "sg:city":"Killeen",
    "sg:classifiers":[
        {
            "category":"Professional",
            "type":"Services"
        }
    ],
    "sg:phone":"+1 254 526 7726",
    "sg:postcode":"76541",
    "sg:province":"TX",
    "wof:name":"Rosa Robledo",
    "wof:placetype":"venue"
},
  "geometry": {"coordinates":[-97.733773,31.110004],"type":"Point"}
}