{
  "type": "Feature",
  "properties": {
    "iso:country":"US",
    "sg:address":"4707 Creekmoor Dr",
    "sg:city":"San Antonio",
    "sg:classifiers":[
        {
            "category":"Restaurant",
            "type":"Food & Drink"
        }
    ],
    "sg:phone":"+1 210 648 1212",
    "sg:postcode":"78220",
    "sg:province":"TX",
    "sg:tags":[
        "eating"
    ],
    "wof:name":"Rafael J Menchaca",
    "wof:placetype":"venue"
},
  "geometry": {"coordinates":[-98.403677,29.404398],"type":"Point"}
}