{
  "type": "Feature",
  "properties": {
    "iso:country":"US",
    "sg:address":"300 Old Bayou Dr",
    "sg:city":"Dickinson",
    "sg:classifiers":[
        {
            "category":"Professional",
            "subcategory":"Detective & Security Services",
            "type":"Services"
        }
    ],
    "sg:phone":"+1 281 337 5120",
    "sg:postcode":"77539",
    "sg:province":"TX",
    "sg:tags":[
        "information",
        "bureau"
    ],
    "wof:name":"Techn 4 U Technical Services Inc",
    "wof:placetype":"venue"
},
  "geometry": {"coordinates":[-95.071899,29.44672],"type":"Point"}
}