{
  "type": "Feature",
  "properties": {
    "iso:country":"US",
    "sg:address":"1907 Mistletoe Ln",
    "sg:city":"Rockdale",
    "sg:classifiers":[
        {
            "category":"Shopping",
            "type":"Retail Goods"
        }
    ],
    "sg:phone":"+1 512 446 6260",
    "sg:postcode":"76567",
    "sg:province":"TX",
    "sg:tags":[
        "merchandise"
    ],
    "wof:name":"L Greene",
    "wof:placetype":"venue"
},
  "geometry": {"coordinates":[-97.022723,30.650742],"type":"Point"}
}