{
  "type": "Feature",
  "properties": {
    "iso:country":"US",
    "sg:address":"5306 N Main St",
    "sg:city":"Houston",
    "sg:classifiers":[
        {
            "category":"Government",
            "subcategory":"Fire Station",
            "type":"Public Place"
        }
    ],
    "sg:phone":"+1 713 861 0222",
    "sg:postcode":"77009",
    "sg:province":"TX",
    "sg:tags":[
        "department",
        "protection"
    ],
    "sg:website":"http://www.houstonconventionctr.com",
    "wof:name":"Fire Dept-Station 15",
    "wof:placetype":"venue"
},
  "geometry": {"coordinates":[-95.386948,29.802561],"type":"Point"}
}