{
  "type": "Feature",
  "properties": {
    "iso:country":"US",
    "sg:address":"2534 Castroville Rd",
    "sg:city":"San Antonio",
    "sg:classifiers":[
        {
            "category":"Government",
            "subcategory":"Office",
            "type":"Public Place"
        }
    ],
    "sg:phone":"+1 210 436 4392",
    "sg:postcode":"78237",
    "sg:province":"TX",
    "sg:tags":[
        "state",
        "resource"
    ],
    "wof:name":"Human Service Dept",
    "wof:placetype":"venue"
},
  "geometry": {"coordinates":[-98.578177,29.410966],"type":"Point"}
}