{
  "type": "Feature",
  "properties": {
    "iso:country":"US",
    "sg:address":"22670 Co Rd 181",
    "sg:city":"Bullard",
    "sg:classifiers":[
        {
            "category":"Autos & Motor Vehicles",
            "subcategory":"Automobile Sales",
            "type":"Retail Goods"
        }
    ],
    "sg:phone":"+1 903 894 8111",
    "sg:postcode":"75757",
    "sg:province":"TX",
    "sg:tags":[
        "car",
        "dealer"
    ],
    "wof:name":"Mc Kibben Auto Sales",
    "wof:placetype":"venue"
},
  "geometry": {"coordinates":[-95.37381600000001,32.149417],"type":"Point"}
}