{
  "type": "Feature",
  "properties": {
    "iso:country":"US",
    "sg:address":"1300 W Mockingbird Ln",
    "sg:city":"Dallas",
    "sg:classifiers":[
        {
            "category":"Insurance",
            "subcategory":"Insurance Agent",
            "type":"Services"
        }
    ],
    "sg:phone":"+1 214 905 5035",
    "sg:postcode":"75247",
    "sg:province":"TX",
    "wof:name":"National Life Annuity Sales",
    "wof:placetype":"venue"
},
  "geometry": {"coordinates":[-96.86370599999999,32.822218],"type":"Point"}
}