{
  "type": "Feature",
  "properties": {
    "iso:country":"US",
    "sg:address":"120 S Ruekle Rd",
    "sg:city":"New Braunfels",
    "sg:classifiers":[
        {
            "category":"Shopping",
            "subcategory":"Clothing, Apparel, & Fashions",
            "type":"Retail Goods"
        }
    ],
    "sg:phone":"+1 830 609 0206",
    "sg:postcode":"78130",
    "sg:province":"TX",
    "wof:name":"Alteration Shop",
    "wof:placetype":"venue"
},
  "geometry": {"coordinates":[-98.15340999999999,29.672248],"type":"Point"}
}