{
  "type": "Feature",
  "properties": {
    "iso:country":"US",
    "sg:address":"305 River Fern Ave",
    "sg:city":"Garland",
    "sg:classifiers":[
        {
            "category":"Real Estate",
            "subcategory":"Real Estate Operator",
            "type":"Services"
        }
    ],
    "sg:phone":"+1 972 530 0354",
    "sg:postcode":"75040",
    "sg:province":"TX",
    "sg:tags":[
        "apartment"
    ],
    "wof:name":"Parkside At Firewheel",
    "wof:placetype":"venue"
},
  "geometry": {"coordinates":[-96.611285,32.954579],"type":"Point"}
}