{
  "type": "Feature",
  "properties": {
    "iso:country":"US",
    "sg:address":"1208 Gessner Dr",
    "sg:city":"Houston",
    "sg:classifiers":[
        {
            "category":"Autos & Motor Vehicles",
            "subcategory":"Auto Supplies",
            "type":"Retail Goods"
        },
        {
            "category":"Professional",
            "subcategory":"Computer Services",
            "type":"Services"
        }
    ],
    "sg:phone":"+1 713 467 7000",
    "sg:postcode":"77055",
    "sg:province":"TX",
    "sg:tags":[
        "glass",
        "stereo",
        "installation"
    ],
    "sg:website":"xmhouston.com",
    "wof:name":"Executive Tint",
    "wof:placetype":"venue"
},
  "geometry": {"coordinates":[-95.54419799999999,29.790562],"type":"Point"}
}