{
  "type": "Feature",
  "properties": {
    "iso:country":"US",
    "sg:address":"1611 Northwood Rd",
    "sg:city":"Austin",
    "sg:classifiers":[
        {
            "category":"Manufacturing",
            "subcategory":"Buildings",
            "type":"Manufacturing & Wholesale Goods"
        },
        {
            "category":"Building & Trades",
            "subcategory":"Construction",
            "type":"Services"
        }
    ],
    "sg:phone":"+1 512 657 0675",
    "sg:postcode":"78703",
    "sg:province":"TX",
    "sg:tags":[
        "home",
        "builder",
        "contractor"
    ],
    "wof:name":"Managed Home Connections",
    "wof:placetype":"venue"
},
  "geometry": {"coordinates":[-97.75478699999999,30.299444],"type":"Point"}
}