{
  "type": "Feature",
  "properties": {
    "iso:country":"US",
    "sg:address":"9461 Lyndon B Johnson Fwy",
    "sg:city":"Dallas",
    "sg:classifiers":[
        {
            "category":"Insurance",
            "subcategory":"Insurance Agent",
            "type":"Services"
        }
    ],
    "sg:phone":"+1 469 330 2370",
    "sg:postcode":"75243",
    "sg:province":"TX",
    "wof:name":"Allstate Insurance",
    "wof:placetype":"venue"
},
  "geometry": {"coordinates":[-96.73412,32.909788],"type":"Point"}
}