{
  "type": "Feature",
  "properties": {
    "iso:country":"US",
    "sg:address":"604 Walnut St",
    "sg:city":"Bowie",
    "sg:classifiers":[
        {
            "category":"Professional",
            "type":"Services"
        }
    ],
    "sg:phone":"+1 940 872 2138",
    "sg:postcode":"76230",
    "sg:province":"TX",
    "wof:name":"Silver Wear",
    "wof:placetype":"venue"
},
  "geometry": {"coordinates":[-97.853071,33.563875],"type":"Point"}
}