{
  "type": "Feature",
  "properties": {
    "iso:country":"US",
    "sg:address":"2101 Fountain View Dr",
    "sg:city":"Houston",
    "sg:classifiers":[
        {
            "category":"Home & Garden",
            "subcategory":"Home Furnishings",
            "type":"Retail Goods"
        }
    ],
    "sg:phone":"+1 713 975 1958",
    "sg:postcode":"77057",
    "sg:province":"TX",
    "sg:tags":[
        "venetian",
        "blind"
    ],
    "wof:name":"Elegant Touch Blinds & Shades",
    "wof:placetype":"venue"
},
  "geometry": {"coordinates":[-95.485433,29.742191],"type":"Point"}
}