{
  "type": "Feature",
  "properties": {
    "iso:country":"US",
    "sg:address":"9211 Waterford Centre Blvd",
    "sg:city":"Austin",
    "sg:classifiers":[
        {
            "category":"Real Estate",
            "subcategory":"Real Estate Services",
            "type":"Services"
        }
    ],
    "sg:phone":"+1 512 215 6007",
    "sg:postcode":"78758",
    "sg:province":"TX",
    "sg:tags":[
        "apartment",
        "vacancy",
        "listing",
        "rental",
        "finder"
    ],
    "wof:name":"Midnight Studios",
    "wof:placetype":"venue"
},
  "geometry": {"coordinates":[-97.72869300000001,30.377439],"type":"Point"}
}