{
  "type": "Feature",
  "properties": {
    "iso:country":"US",
    "sg:address":"4466 State Hwy 6",
    "sg:city":"Houston",
    "sg:classifiers":[
        {
            "category":"Bars & Pubs",
            "type":"Food & Drink"
        }
    ],
    "sg:phone":"+1 713 697 9129",
    "sg:postcode":"77084",
    "sg:province":"TX",
    "sg:tags":[
        "drinking"
    ],
    "wof:name":"Discoteca Analuz",
    "wof:placetype":"venue"
},
  "geometry": {"coordinates":[-95.645618,29.839235],"type":"Point"}
}