{
  "type": "Feature",
  "properties": {
    "iso:country":"US",
    "sg:address":"5922 Cedar Springs Rd",
    "sg:city":"Dallas",
    "sg:classifiers":[
        {
            "category":"Restaurant",
            "type":"Food & Drink"
        }
    ],
    "sg:phone":"+1 214 902 8080",
    "sg:postcode":"75235",
    "sg:province":"TX",
    "wof:name":"Ruth's Chris Steak House",
    "wof:placetype":"venue"
},
  "geometry": {"coordinates":[-96.833504,32.8279],"type":"Point"}
}