{
  "type": "Feature",
  "properties": {
    "iso:country":"US",
    "sg:address":"2300 Richmond Avenue #441",
    "sg:city":"Houston",
    "sg:classifiers":[
        {
            "category":"Sports & Exercise",
            "subcategory":"Bicycle Rental",
            "type":"Entertainment"
        },
        {
            "category":"Travel",
            "subcategory":"Travel Agent",
            "type":"Entertainment"
        }
    ],
    "sg:phone":"+1 800 737 5760",
    "sg:postcode":"77098",
    "sg:province":"TX",
    "sg:tags":[
        "bike",
        "vacation"
    ],
    "wof:name":"Active Cultures Travel",
    "wof:placetype":"venue"
},
  "geometry": {"coordinates":[-95.41558499999999,29.734788],"type":"Point"}
}