{
  "type": "Feature",
  "properties": {
    "iso:country":"US",
    "sg:address":"2441 61st St",
    "sg:city":"Port Arthur",
    "sg:classifiers":[
        {
            "category":"Education",
            "subcategory":"School",
            "type":"Public Place"
        }
    ],
    "sg:phone":"+1 409 736 1521",
    "sg:postcode":"77640",
    "sg:province":"TX",
    "sg:tags":[
        "combined"
    ],
    "wof:name":"Austin Middle-High School",
    "wof:placetype":"venue"
},
  "geometry": {"coordinates":[-94.022575,29.899358],"type":"Point"}
}