{
  "type": "Feature",
  "properties": {
    "iso:country":"US",
    "sg:address":"9610 Windy Hollow Dr",
    "sg:city":"Irving",
    "sg:classifiers":[
        {
            "category":"Professional",
            "subcategory":"Management & Consulting",
            "type":"Services"
        }
    ],
    "sg:phone":"+1 972 444 0767",
    "sg:postcode":"75063",
    "sg:province":"TX",
    "wof:name":"Esoteric Solutions",
    "wof:placetype":"venue"
},
  "geometry": {"coordinates":[-96.96191,32.938983],"type":"Point"}
}