{
  "type": "Feature",
  "properties": {
    "iso:country":"US",
    "sg:address":"3801 Lakeview Pkwy Ste 700",
    "sg:city":"Rowlett",
    "sg:classifiers":[
        {
            "category":"Restaurant",
            "type":"Food & Drink"
        }
    ],
    "sg:phone":"+1 972 412 8226",
    "sg:postcode":"75088",
    "sg:province":"TX",
    "sg:tags":[
        "mexican"
    ],
    "sg:website":"www.fuzzystacoshop.com",
    "wof:name":"Fuzzy's Taco Shop",
    "wof:placetype":"venue"
},
  "geometry": {"coordinates":[-96.567001,32.907998],"type":"Point"}
}