{
  "type": "Feature",
  "properties": {
    "iso:country":"US",
    "sg:address":"2000 North Loop W",
    "sg:city":"Houston",
    "sg:classifiers":[
        {
            "category":"Professional",
            "subcategory":"Art Services",
            "type":"Services"
        },
        {
            "category":"Real Estate",
            "subcategory":"Architect",
            "type":"Services"
        }
    ],
    "sg:phone":"+1 713 316 9210",
    "sg:postcode":"77018",
    "sg:province":"TX",
    "sg:tags":[
        "architects'",
        "designer",
        "specification",
        "builders'",
        "construction",
        "architectural",
        "interior",
        "decorator"
    ],
    "sg:website":"http://www.vickarchitect.com",
    "wof:name":"Carol Vick Architect",
    "wof:placetype":"venue"
},
  "geometry": {"coordinates":[-95.436131,29.811556],"type":"Point"}
}