{
  "type": "Feature",
  "properties": {
    "iso:country":"US",
    "sg:address":"701 Pasadena Fwy",
    "sg:city":"Pasadena",
    "sg:classifiers":[
        {
            "category":"Building & Trades",
            "subcategory":"Equipment Rental",
            "type":"Services"
        }
    ],
    "sg:phone":"+1 713 472 1515",
    "sg:postcode":"77506",
    "sg:province":"TX",
    "sg:tags":[
        "yard"
    ],
    "wof:name":"National Rental Svc Inc",
    "wof:placetype":"venue"
},
  "geometry": {"coordinates":[-95.203311,29.711921],"type":"Point"}
}