{
  "type": "Feature",
  "properties": {
    "iso:country":"US",
    "sg:address":"7001 Queens Dr",
    "sg:city":"Edinburg",
    "sg:classifiers":[
        {
            "category":"Banks & Credit Unions",
            "subcategory":"Investment Brokerage",
            "type":"Services"
        }
    ],
    "sg:phone":"+1 956 316 2552",
    "sg:postcode":"78542",
    "sg:province":"TX",
    "sg:tags":[
        "advisory"
    ],
    "wof:name":"Locha's Investments, Inc.",
    "wof:placetype":"venue"
},
  "geometry": {"coordinates":[-98.086838,26.3092],"type":"Point"}
}