{
  "type": "Feature",
  "properties": {
    "iso:country":"US",
    "sg:address":"5713 Trinity Ln",
    "sg:city":"Fort Worth",
    "sg:classifiers":[
        {
            "category":"Home & Garden",
            "subcategory":"Furniture",
            "type":"Retail Goods"
        }
    ],
    "sg:phone":"+1 817 427 2420",
    "sg:postcode":"76137",
    "sg:province":"TX",
    "wof:name":"Chipman Custom Woodcraft",
    "wof:placetype":"venue"
},
  "geometry": {"coordinates":[-97.278119,32.851598],"type":"Point"}
}