{
  "type": "Feature",
  "properties": {
    "iso:country":"US",
    "sg:address":"239 N Madison St",
    "sg:city":"La Grange",
    "sg:classifiers":[
        {
            "category":"Home & Garden",
            "subcategory":"Household Appliances",
            "type":"Retail Goods"
        }
    ],
    "sg:phone":"+1 979 968 8804",
    "sg:postcode":"78945",
    "sg:province":"TX",
    "sg:tags":[
        "machine",
        "sewing"
    ],
    "wof:name":"Quilters Cottage",
    "wof:placetype":"venue"
},
  "geometry": {"coordinates":[-96.875648,29.908138],"type":"Point"}
}