{
  "type": "Feature",
  "properties": {
    "iso:country":"US",
    "sg:address":"1400 W Mayfield Rd",
    "sg:city":"Arlington",
    "sg:classifiers":[
        {
            "category":"Real Estate",
            "subcategory":"Developer",
            "type":"Services"
        }
    ],
    "sg:phone":"+1 817 466 3131",
    "sg:postcode":"76015",
    "sg:province":"TX",
    "wof:name":"Tak Enterprises Inc",
    "wof:placetype":"venue"
},
  "geometry": {"coordinates":[-97.13016399999999,32.692062],"type":"Point"}
}