{
  "type": "Feature",
  "properties": {
    "iso:country":"US",
    "sg:address":"6503 Brittany Park Ln",
    "sg:city":"Houston",
    "sg:classifiers":[
        {
            "category":"Government",
            "subcategory":"Office",
            "type":"Public Place"
        }
    ],
    "sg:phone":"+1 281 895 9911",
    "sg:postcode":"77066",
    "sg:province":"TX",
    "sg:tags":[
        "executive"
    ],
    "wof:name":"Greater Harris County",
    "wof:placetype":"venue"
},
  "geometry": {"coordinates":[-95.51105099999999,29.95024],"type":"Point"}
}