{
  "type": "Feature",
  "properties": {
    "iso:country":"US",
    "sg:address":"124 Juniper St",
    "sg:city":"Lake Jackson",
    "sg:classifiers":[
        {
            "category":"Professional",
            "subcategory":"Management & Consulting",
            "type":"Services"
        }
    ],
    "sg:phone":"+1 979 265 3786",
    "sg:postcode":"77566",
    "sg:province":"TX",
    "sg:tags":[
        "business"
    ],
    "wof:name":"Roy A Wooten Consultants",
    "wof:placetype":"venue"
},
  "geometry": {"coordinates":[-95.415531,29.040768],"type":"Point"}
}