{
  "type": "Feature",
  "properties": {
    "iso:country":"US",
    "sg:address":"1733 Briarcrest Dr",
    "sg:city":"Bryan",
    "sg:classifiers":[
        {
            "category":"Insurance",
            "subcategory":"Hazard Insurance",
            "type":"Services"
        }
    ],
    "sg:phone":"+1 979 776 2626",
    "sg:postcode":"77802",
    "sg:province":"TX",
    "sg:tags":[
        "commercial",
        "business"
    ],
    "wof:name":"Alexarder Sid",
    "wof:placetype":"venue"
},
  "geometry": {"coordinates":[-96.339499,30.652609],"type":"Point"}
}