{
  "type": "Feature",
  "properties": {
    "iso:country":"US",
    "sg:address":"12012 Wickchester Ln Suite 150",
    "sg:city":"Houston",
    "sg:classifiers":[
        {
            "category":"Shopping",
            "subcategory":"Stationery & Office Supplies",
            "type":"Retail Goods"
        },
        {
            "category":"Wholesale",
            "subcategory":"Computers",
            "type":"Manufacturing & Wholesale Goods"
        }
    ],
    "sg:phone":"+1 281 493 2553",
    "sg:postcode":"77079",
    "sg:province":"TX",
    "sg:tags":[
        "machine",
        "equipment",
        "copy"
    ],
    "sg:website":"http://findxeroxagents.com/copiers-in-houston-texas_770",
    "wof:name":"Southwest Document Solutions, LLC",
    "wof:placetype":"venue"
},
  "geometry": {"coordinates":[-95.599414,29.7885],"type":"Point"}
}