{
  "type": "Feature",
  "properties": {
    "iso:country":"US",
    "sg:address":"1812 Shenandoah Ct S",
    "sg:city":"Longview",
    "sg:classifiers":[
        {
            "category":"Real Estate",
            "subcategory":"Real Estate Agent",
            "type":"Services"
        }
    ],
    "sg:phone":"+1 903 295 1827",
    "sg:postcode":"75605",
    "sg:province":"TX",
    "wof:name":"Roy Seymore",
    "wof:placetype":"venue"
},
  "geometry": {"coordinates":[-94.772414,32.537832],"type":"Point"}
}