{
  "type": "Feature",
  "properties": {
    "iso:country":"US",
    "sg:address":"350 W College St",
    "sg:city":"Lewisville",
    "sg:classifiers":[
        {
            "category":"Education",
            "subcategory":"School",
            "type":"Public Place"
        }
    ],
    "sg:phone":"+1 972 436 1912",
    "sg:postcode":"75057",
    "sg:province":"TX",
    "sg:tags":[
        "elementary"
    ],
    "wof:name":"College Street Elementary Schl",
    "wof:placetype":"venue"
},
  "geometry": {"coordinates":[-97.00135899999999,33.049349],"type":"Point"}
}