{
  "type": "Feature",
  "properties": {
    "iso:country":"US",
    "sg:address":"3816 Mediterranean St",
    "sg:city":"Rockwall",
    "sg:classifiers":[
        {
            "category":"Building & Trades",
            "subcategory":"Construction",
            "type":"Services"
        }
    ],
    "sg:phone":"+1 972 772 5667",
    "sg:postcode":"75087",
    "sg:province":"TX",
    "sg:tags":[
        "house"
    ],
    "wof:name":"Jdt Construction Services Inc",
    "wof:placetype":"venue"
},
  "geometry": {"coordinates":[-96.47996999999999,32.898252],"type":"Point"}
}