{
  "type": "Feature",
  "properties": {
    "iso:country":"US",
    "sg:address":"4000 Lincoln Ave",
    "sg:city":"Groves",
    "sg:classifiers":[
        {
            "category":"Autos & Motor Vehicles",
            "subcategory":"Fuel & Gas Station",
            "type":"Retail Goods"
        }
    ],
    "sg:phone":"+1 409 962 9443",
    "sg:postcode":"77619",
    "sg:province":"TX",
    "sg:tags":[
        "oil"
    ],
    "wof:name":"Wolfe's Texaco",
    "wof:placetype":"venue"
},
  "geometry": {"coordinates":[-93.91963699999999,29.947094],"type":"Point"}
}