{
  "type": "Feature",
  "properties": {
    "iso:country":"US",
    "sg:address":"6425 S Padre Island Dr",
    "sg:city":"Corpus Christi",
    "sg:classifiers":[
        {
            "category":"Bars & Pubs",
            "type":"Food & Drink"
        }
    ],
    "sg:phone":"+1 361 985 8822",
    "sg:postcode":"78412",
    "sg:province":"TX",
    "sg:tags":[
        "drinking"
    ],
    "wof:name":"Sunsets Fantasy",
    "wof:placetype":"venue"
},
  "geometry": {"coordinates":[-97.354159,27.699571],"type":"Point"}
}