{
  "type": "Feature",
  "properties": {
    "iso:country":"US",
    "sg:address":"7 Valley Wood Ct",
    "sg:city":"Roanoke",
    "sg:classifiers":[
        {
            "category":"Professional",
            "type":"Services"
        }
    ],
    "sg:phone":"+1 817 430 1420",
    "sg:postcode":"76262",
    "sg:province":"TX",
    "wof:name":"Page Creations",
    "wof:placetype":"venue"
},
  "geometry": {"coordinates":[-97.17348800000001,32.990099],"type":"Point"}
}