{
  "type": "Feature",
  "properties": {
    "iso:country":"US",
    "sg:address":"2224 W Park Row Dr",
    "sg:city":"Arlington",
    "sg:classifiers":[
        {
            "category":"Retail",
            "subcategory":"Laundry & Dry Cleaning",
            "type":"Services"
        }
    ],
    "sg:phone":"+1 817 861 4337",
    "sg:postcode":"76013",
    "sg:province":"TX",
    "sg:tags":[
        "drycleaning",
        "plant",
        "cleaners"
    ],
    "wof:name":"Unique Cleaners",
    "wof:placetype":"venue"
},
  "geometry": {"coordinates":[-97.142481,32.721204],"type":"Point"}
}