{
  "type": "Feature",
  "properties": {
    "iso:country":"US",
    "sg:address":"1307 Sandy Ln",
    "sg:city":"Baytown",
    "sg:classifiers":[
        {
            "category":"Shopping",
            "type":"Retail Goods"
        }
    ],
    "sg:phone":"+1 281 420 7476",
    "sg:postcode":"77520",
    "sg:province":"TX",
    "sg:tags":[
        "merchandise"
    ],
    "wof:name":"Basket Dreams",
    "wof:placetype":"venue"
},
  "geometry": {"coordinates":[-94.947732,29.74887],"type":"Point"}
}