{
  "type": "Feature",
  "properties": {
    "iso:country":"US",
    "sg:address":"3801 Padre Blvd",
    "sg:city":"South Padre Island",
    "sg:classifiers":[
        {
            "category":"Restaurant",
            "type":"Food & Drink"
        }
    ],
    "sg:phone":"+1 956 772 1000",
    "sg:postcode":"78597",
    "sg:province":"TX",
    "sg:tags":[
        "eating"
    ],
    "wof:name":"Dominos Pizza",
    "wof:placetype":"venue"
},
  "geometry": {"coordinates":[-97.16952499999999,26.114159],"type":"Point"}
}