{
  "type": "Feature",
  "properties": {
    "iso:country":"US",
    "sg:address":"2858 Red Bluff Cir",
    "sg:city":"San Angelo",
    "sg:classifiers":[
        {
            "category":"Insurance",
            "subcategory":"Insurance Agent",
            "type":"Services"
        }
    ],
    "sg:phone":"+1 325 942 1208",
    "sg:postcode":"76904",
    "sg:province":"TX",
    "wof:name":"Bob Pulley Insurance",
    "wof:placetype":"venue"
},
  "geometry": {"coordinates":[-100.50579399999999,31.382538],"type":"Point"}
}