{
  "type": "Feature",
  "properties": {
    "iso:country":"US",
    "sg:address":"1114 84th St",
    "sg:city":"Lubbock",
    "sg:classifiers":[
        {
            "category":"Place Of Worship",
            "subcategory":"Church",
            "type":"Public Place"
        },
        {
            "category":"Place Of Worship",
            "type":"Public Place"
        },
        {
            "category":"Organizations",
            "subcategory":"Religious Organization",
            "type":"Services"
        }
    ],
    "sg:phone":"+1 806 745 1280",
    "sg:postcode":"79423",
    "sg:province":"TX",
    "sg:tags":[
        "god",
        "god-independent",
        "churches-assemblies"
    ],
    "wof:name":"Grace Assembly of God",
    "wof:placetype":"venue"
},
  "geometry": {"coordinates":[-101.846889,33.517809],"type":"Point"}
}