{
  "type": "Feature",
  "properties": {
    "iso:country":"US",
    "sg:address":"1628 Martin Luther King Jr Blvd",
    "sg:city":"Dallas",
    "sg:classifiers":[
        {
            "category":"Home & Garden",
            "subcategory":"Carpets & Floor Coverings",
            "type":"Retail Goods"
        }
    ],
    "sg:phone":"+1 214 426 0026",
    "sg:postcode":"75215",
    "sg:province":"TX",
    "sg:tags":[
        "rug"
    ],
    "wof:name":"King's Carpet",
    "wof:placetype":"venue"
},
  "geometry": {"coordinates":[-96.77734599999999,32.761436],"type":"Point"}
}