{
  "type": "Feature",
  "properties": {
    "iso:country":"US",
    "sg:address":"3415 Homer St",
    "sg:city":"Dallas",
    "sg:classifiers":[
        {
            "category":"Professional",
            "type":"Services"
        }
    ],
    "sg:phone":"+1 214 824 1168",
    "sg:postcode":"75206",
    "sg:province":"TX",
    "wof:name":"V Les Visuals",
    "wof:placetype":"venue"
},
  "geometry": {"coordinates":[-96.781222,32.829604],"type":"Point"}
}