{
  "type": "Feature",
  "properties": {
    "iso:country":"US",
    "sg:address":"218 Ferndale Dr",
    "sg:city":"Lewisville",
    "sg:classifiers":[
        {
            "category":"Travel",
            "subcategory":"Travel Agent",
            "type":"Entertainment"
        }
    ],
    "sg:phone":"+1 972 317 6741",
    "sg:postcode":"75077",
    "sg:province":"TX",
    "sg:tags":[
        "agency"
    ],
    "wof:name":"Travel By Starr",
    "wof:placetype":"venue"
},
  "geometry": {"coordinates":[-97.047145,33.084531],"type":"Point"}
}