{
  "type": "Feature",
  "properties": {
    "iso:country":"US",
    "sg:address":"2601 Summerhill Rd",
    "sg:city":"Texarkana",
    "sg:classifiers":[
        {
            "category":"Wholesale",
            "subcategory":"Office Equipment",
            "type":"Manufacturing & Wholesale Goods"
        },
        {
            "category":"Shopping",
            "subcategory":"Computers & Home Electronics",
            "type":"Retail Goods"
        }
    ],
    "sg:phone":"+1 903 793 1997",
    "sg:postcode":"75503",
    "sg:province":"TX",
    "sg:tags":[
        "repair",
        "fax",
        "copier",
        "duplicating",
        "machine",
        "copying",
        "mach",
        "typewriter"
    ],
    "sg:website":"www.3n1.com",
    "wof:name":"3-N-1 Office Products Inc",
    "wof:placetype":"venue"
},
  "geometry": {"coordinates":[-94.06401700000001,33.442231],"type":"Point"}
}