{
  "type": "Feature",
  "properties": {
    "iso:country":"US",
    "sg:address":"1106 San Antonio St",
    "sg:city":"Austin",
    "sg:classifiers":[
        {
            "category":"Personal",
            "type":"Services"
        }
    ],
    "sg:phone":"+1 512 686 4644",
    "sg:postcode":"78701",
    "sg:province":"TX",
    "sg:tags":[
        "local"
    ],
    "sg:website":"www.austinbailbonds.biz",
    "wof:name":"Austin Bail Bonds",
    "wof:placetype":"venue"
},
  "geometry": {"coordinates":[-97.745678,30.274483],"type":"Point"}
}