{
  "type": "Feature",
  "properties": {
    "iso:country":"US",
    "sg:address":"7835 Bent Briar",
    "sg:city":"San Antonio",
    "sg:classifiers":[
        {
            "category":"Retail",
            "subcategory":"Auto Rental",
            "type":"Services"
        }
    ],
    "sg:phone":"+1 210 521 7029",
    "sg:postcode":"78250",
    "sg:province":"TX",
    "sg:tags":[
        "passenger",
        "car"
    ],
    "wof:name":"Not So New Car Rental",
    "wof:placetype":"venue"
},
  "geometry": {"coordinates":[-98.66646900000001,29.514281],"type":"Point"}
}