{
  "type": "Feature",
  "properties": {
    "iso:country":"US",
    "sg:address":"1725 Brun St",
    "sg:city":"Houston",
    "sg:classifiers":[
        {
            "category":"Shopping",
            "subcategory":"Gifts & Souvenirs",
            "type":"Retail Goods"
        }
    ],
    "sg:phone":"+1 713 520 5823",
    "sg:postcode":"77019",
    "sg:province":"TX",
    "wof:name":"Joys Specialties",
    "wof:placetype":"venue"
},
  "geometry": {"coordinates":[-95.40877500000001,29.74932],"type":"Point"}
}