{
  "type": "Feature",
  "properties": {
    "iso:country":"US",
    "sg:address":"2025 N Main Ave",
    "sg:city":"San Antonio",
    "sg:classifiers":[
        {
            "category":"Professional",
            "subcategory":"Business Services",
            "type":"Services"
        }
    ],
    "sg:phone":"+1 210 738 1188",
    "sg:postcode":"78212",
    "sg:province":"TX",
    "wof:name":"Alamo Fiesta Co",
    "wof:placetype":"venue"
},
  "geometry": {"coordinates":[-98.494303,29.448886],"type":"Point"}
}