{
  "type": "Feature",
  "properties": {
    "iso:country":"US",
    "sg:address":"1371 Rich Ln",
    "sg:city":"Buda",
    "sg:classifiers":[
        {
            "category":"Professional",
            "subcategory":"Business Services",
            "type":"Services"
        }
    ],
    "sg:phone":"+1 512 295 5072",
    "sg:postcode":"78610",
    "sg:province":"TX",
    "wof:name":"Hamaket Construction Inc",
    "wof:placetype":"venue"
},
  "geometry": {"coordinates":[-97.776004,30.065914],"type":"Point"}
}