{
  "type": "Feature",
  "properties": {
    "iso:country":"US",
    "sg:address":"324 A St",
    "sg:city":"Kerrville",
    "sg:classifiers":[
        {
            "category":"Building & Trades",
            "subcategory":"Construction",
            "type":"Services"
        }
    ],
    "sg:phone":"+1 830 257 8929",
    "sg:postcode":"78028",
    "sg:province":"TX",
    "sg:tags":[
        "contractor"
    ],
    "wof:name":"Avila Construction",
    "wof:placetype":"venue"
},
  "geometry": {"coordinates":[-99.134838,30.042973],"type":"Point"}
}