{
  "type": "Feature",
  "properties": {
    "iso:country":"US",
    "sg:address":"11300 Roszell St",
    "sg:city":"San Antonio",
    "sg:classifiers":[
        {
            "category":"Home & Garden",
            "subcategory":"Building Materials",
            "type":"Retail Goods"
        }
    ],
    "sg:phone":"+1 210 656 1043",
    "sg:postcode":"78217",
    "sg:province":"TX",
    "sg:tags":[
        "repair",
        "door"
    ],
    "wof:name":"Garage Door Repair Co",
    "wof:placetype":"venue"
},
  "geometry": {"coordinates":[-98.413721,29.542756],"type":"Point"}
}