{
  "type": "Feature",
  "properties": {
    "iso:country":"US",
    "sg:address":"10240 Bauman Rd",
    "sg:city":"Houston",
    "sg:classifiers":[
        {
            "category":"Food & Beverages",
            "subcategory":"Groceries & Convenience Stores",
            "type":"Retail Goods"
        }
    ],
    "sg:phone":"+1 713 697 9217",
    "sg:postcode":"77076",
    "sg:province":"TX",
    "wof:name":"Sunny's Food Store",
    "wof:placetype":"venue"
},
  "geometry": {"coordinates":[-95.371803,29.8542],"type":"Point"}
}