{
  "type": "Feature",
  "properties": {
    "iso:country":"US",
    "sg:address":"11722 Marsh Ln",
    "sg:city":"Dallas",
    "sg:classifiers":[
        {
            "category":"Retail",
            "subcategory":"Veterinary Services",
            "type":"Services"
        }
    ],
    "sg:phone":"+1 214 350 1233",
    "sg:postcode":"75229",
    "sg:province":"TX",
    "wof:name":"Animal Medical Care",
    "wof:placetype":"venue"
},
  "geometry": {"coordinates":[-96.856094,32.909039],"type":"Point"}
}