{
  "type": "Feature",
  "properties": {
    "iso:country":"US",
    "sg:address":"300 Polk St",
    "sg:city":"Luling",
    "sg:classifiers":[
        {
            "category":"Bars & Pubs",
            "subcategory":"Nightclub",
            "type":"Food & Drink"
        }
    ],
    "sg:phone":"+1 830 875 5654",
    "sg:postcode":"78648",
    "sg:province":"TX",
    "sg:tags":[
        "club",
        "night"
    ],
    "wof:name":"Monte's",
    "wof:placetype":"venue"
},
  "geometry": {"coordinates":[-97.653481,29.6754],"type":"Point"}
}