{
  "type": "Feature",
  "properties": {
    "iso:country":"US",
    "sg:address":"6431 Green Top Dr",
    "sg:city":"San Antonio",
    "sg:classifiers":[
        {
            "category":"Shopping",
            "type":"Retail Goods"
        }
    ],
    "sg:phone":"+1 210 637 5387",
    "sg:postcode":"78233",
    "sg:province":"TX",
    "sg:tags":[
        "picture",
        "frame"
    ],
    "wof:name":"Frame Concepts",
    "wof:placetype":"venue"
},
  "geometry": {"coordinates":[-98.361895,29.573658],"type":"Point"}
}