{
  "type": "Feature",
  "properties": {
    "iso:country":"US",
    "sg:address":"11914 Gallant Forest Dr",
    "sg:city":"San Antonio",
    "sg:classifiers":[
        {
            "category":"Communications",
            "subcategory":"Film & Video Production",
            "type":"Services"
        }
    ],
    "sg:phone":"+1 210 697 9213",
    "sg:postcode":"78249",
    "sg:province":"TX",
    "sg:tags":[
        "motion"
    ],
    "wof:name":"A Room",
    "wof:placetype":"venue"
},
  "geometry": {"coordinates":[-98.613517,29.552713],"type":"Point"}
}