{
  "type": "Feature",
  "properties": {
    "iso:country":"US",
    "sg:address":"225 S 32nd St Ste 3",
    "sg:city":"Waco",
    "sg:classifiers":[
        {
            "category":"Autos & Motor Vehicles",
            "subcategory":"Auto Supplies",
            "type":"Retail Goods"
        }
    ],
    "sg:phone":"+1 254 755 7580",
    "sg:postcode":"76710",
    "sg:province":"TX",
    "sg:tags":[
        "automobile",
        "part"
    ],
    "wof:name":"California Style Detailin",
    "wof:placetype":"venue"
},
  "geometry": {"coordinates":[-97.155575,31.532959],"type":"Point"}
}