{
  "type": "Feature",
  "properties": {
    "iso:country":"US",
    "sg:address":"2815 Speight Ave",
    "sg:city":"Waco",
    "sg:classifiers":[
        {
            "category":"Education",
            "subcategory":"Library",
            "type":"Public Place"
        }
    ],
    "sg:phone":"+1 254 750 8621",
    "sg:postcode":"76711",
    "sg:province":"TX",
    "wof:name":"South WACO Library",
    "wof:placetype":"venue"
},
  "geometry": {"coordinates":[-97.140423,31.526202],"type":"Point"}
}