{
  "type": "Feature",
  "properties": {
    "iso:country":"US",
    "sg:address":"11423 Sagewhite Dr",
    "sg:city":"Houston",
    "sg:classifiers":[
        {
            "category":"Shopping",
            "subcategory":"Books",
            "type":"Retail Goods"
        }
    ],
    "sg:phone":"+1 281 484 4656",
    "sg:postcode":"77089",
    "sg:province":"TX",
    "wof:name":"Kamala Mastery of Light",
    "wof:placetype":"venue"
},
  "geometry": {"coordinates":[-95.230451,29.579571],"type":"Point"}
}