{
  "type": "Feature",
  "properties": {
    "iso:country":"US",
    "sg:address":"10247 Warren Pkwy",
    "sg:city":"Frisco",
    "sg:classifiers":[
        {
            "category":"Education",
            "subcategory":"School",
            "type":"Public Place"
        }
    ],
    "sg:phone":"+1 214 387 8202",
    "sg:postcode":"75035",
    "sg:province":"TX",
    "sg:tags":[
        "k-",
        "private"
    ],
    "sg:website":"http://www.warrenmontessori.com",
    "wof:name":"Warren Montessori School",
    "wof:placetype":"venue"
},
  "geometry": {"coordinates":[-96.79113,33.109016],"type":"Point"}
}