{
  "type": "Feature",
  "properties": {
    "iso:country":"US",
    "sg:address":"8715 Spring Cypress Rd",
    "sg:city":"Spring",
    "sg:classifiers":[
        {
            "category":"Coffee & Tea",
            "type":"Food & Drink"
        }
    ],
    "sg:menulink":"http://www.allmenus.com/tx/northwest-harris/113166-starbucks-coffee/menu/",
    "sg:phone":"+1 281 379 1244",
    "sg:postcode":"77379",
    "sg:province":"TX",
    "sg:tags":[
        "american"
    ],
    "wof:name":"Starbucks Coffee",
    "wof:placetype":"venue"
},
  "geometry": {"coordinates":[-95.5578,30.030035],"type":"Point"}
}