{
  "type": "Feature",
  "properties": {
    "iso:country":"US",
    "sg:address":"8645 Brucks Ln",
    "sg:city":"Converse",
    "sg:classifiers":[
        {
            "category":"Social Services",
            "subcategory":"Child Care",
            "type":"Services"
        }
    ],
    "sg:phone":"+1 210 310 1010",
    "sg:postcode":"78109",
    "sg:province":"TX",
    "wof:name":"Peek A Boo Hideout Learning",
    "wof:placetype":"venue"
},
  "geometry": {"coordinates":[-98.319137,29.500025],"type":"Point"}
}