{
  "type": "Feature",
  "properties": {
    "iso:country":"US",
    "sg:address":"2300 Cold Springs Rd",
    "sg:city":"Fort Worth",
    "sg:classifiers":[
        {
            "category":"Retail",
            "subcategory":"Car Wash",
            "type":"Services"
        }
    ],
    "sg:phone":"+1 817 625 6443",
    "sg:postcode":"76106",
    "sg:province":"TX",
    "sg:tags":[
        "truck",
        "cleaning"
    ],
    "sg:website":"www.steamaway.com",
    "wof:name":"Steamaway Inc",
    "wof:placetype":"venue"
},
  "geometry": {"coordinates":[-97.32467800000001,32.787729],"type":"Point"}
}