{
  "type": "Feature",
  "properties": {
    "iso:country":"US",
    "sg:address":"2200 25th St",
    "sg:city":"Snyder",
    "sg:classifiers":[
        {
            "category":"Building & Trades",
            "subcategory":"Plumbing",
            "type":"Services"
        }
    ],
    "sg:phone":"+1 325 573 4997",
    "sg:postcode":"79549",
    "sg:province":"TX",
    "sg:tags":[
        "conditioning",
        "air",
        "system",
        "contractor"
    ],
    "wof:name":"Dea Heating & Air",
    "wof:placetype":"venue"
},
  "geometry": {"coordinates":[-100.923618,32.71725],"type":"Point"}
}