{
  "type": "Feature",
  "properties": {
    "iso:country":"US",
    "sg:address":"1650 Gruene Cove",
    "sg:city":"New Braunfels",
    "sg:classifiers":[
        {
            "category":"Freight",
            "type":"Transportation"
        }
    ],
    "sg:phone":"+1 830 626 2063",
    "sg:postcode":"78130",
    "sg:province":"TX",
    "sg:tags":[
        "operator",
        "trucking"
    ],
    "wof:name":"Dennis Gibson Inc",
    "wof:placetype":"venue"
},
  "geometry": {"coordinates":[-98.10297199999999,29.732802],"type":"Point"}
}