{
  "type": "Feature",
  "properties": {
    "iso:country":"US",
    "sg:address":"1501 E Simonds Rd",
    "sg:city":"Seagoville",
    "sg:classifiers":[
        {
            "category":"Retail",
            "subcategory":"Repair Shop",
            "type":"Services"
        }
    ],
    "sg:phone":"+1 972 287 2049",
    "sg:postcode":"75159",
    "sg:province":"TX",
    "sg:tags":[
        "welding"
    ],
    "wof:name":"Seago Welding Inc",
    "wof:placetype":"venue"
},
  "geometry": {"coordinates":[-96.54825,32.673726],"type":"Point"}
}