{
  "type": "Feature",
  "properties": {
    "iso:country":"US",
    "sg:address":"811 W Dallas Ave",
    "sg:city":"Cooper",
    "sg:classifiers":[
        {
            "category":"Utilities",
            "subcategory":"Fuel Oil & Lpg",
            "type":"Services"
        }
    ],
    "sg:phone":"+1 903 395 2615",
    "sg:postcode":"75432",
    "sg:province":"TX",
    "sg:tags":[
        "propane",
        "gas",
        "diesel"
    ],
    "wof:name":"Cooper Automatic Gas Co",
    "wof:placetype":"venue"
},
  "geometry": {"coordinates":[-95.694979,33.373821],"type":"Point"}
}