{
  "type": "Feature",
  "properties": {
    "iso:country":"US",
    "sg:address":"1426 Glade Point Dr",
    "sg:city":"Coppell",
    "sg:classifiers":[
        {
            "category":"Health Services",
            "subcategory":"Clinic",
            "type":"Services"
        }
    ],
    "sg:phone":"+1 972 745 8862",
    "sg:postcode":"75019",
    "sg:province":"TX",
    "wof:name":"Southwest Medical System",
    "wof:placetype":"venue"
},
  "geometry": {"coordinates":[-96.947018,32.964154],"type":"Point"}
}