{
  "type": "Feature",
  "properties": {
    "iso:country":"US",
    "sg:address":"10841 Estate Ln",
    "sg:city":"Dallas",
    "sg:classifiers":[
        {
            "category":"Retail",
            "subcategory":"Auto Repair",
            "type":"Services"
        }
    ],
    "sg:phone":"+1 866 730 5464",
    "sg:postcode":"75238",
    "sg:province":"TX",
    "sg:tags":[
        "body",
        "shop"
    ],
    "sg:website":"www.serviceking.com",
    "wof:name":"Service King Collision Repair Centers",
    "wof:placetype":"venue"
},
  "geometry": {"coordinates":[-96.697557,32.882886],"type":"Point"}
}