{
  "type": "Feature",
  "properties": {
    "iso:country":"US",
    "sg:address":"3834 Spencer Hwy",
    "sg:city":"Pasadena",
    "sg:classifiers":[
        {
            "category":"Restaurant",
            "type":"Food & Drink"
        }
    ],
    "sg:phone":"+1 713 946 6310",
    "sg:postcode":"77504",
    "sg:province":"TX",
    "sg:tags":[
        "eating"
    ],
    "wof:name":"Burger King",
    "wof:placetype":"venue"
},
  "geometry": {"coordinates":[-95.185712,29.665021],"type":"Point"}
}