{
  "type": "Feature",
  "properties": {
    "iso:country":"US",
    "sg:address":"11295 Tantor Rd",
    "sg:city":"Dallas",
    "sg:classifiers":[
        {
            "category":"Autos & Motor Vehicles",
            "subcategory":"Automobile Sales",
            "type":"Retail Goods"
        }
    ],
    "sg:phone":"+1 214 742 5221",
    "sg:postcode":"75229",
    "sg:province":"TX",
    "sg:tags":[
        "equipment",
        "wrecker"
    ],
    "wof:name":"Coker Equipment Sales Inc",
    "wof:placetype":"venue"
},
  "geometry": {"coordinates":[-96.911737,32.895627],"type":"Point"}
}