{
  "type": "Feature",
  "properties": {
    "iso:country":"US",
    "sg:address":"15080 E Beltwood Pkwy Ste 111",
    "sg:city":"Addison",
    "sg:classifiers":[
        {
            "category":"Sports & Exercise",
            "subcategory":"Gym",
            "type":"Entertainment"
        },
        {
            "category":"Arena",
            "subcategory":"Sports Club",
            "type":"Entertainment"
        }
    ],
    "sg:phone":"+1 972 387 8500",
    "sg:postcode":"75001",
    "sg:province":"TX",
    "sg:tags":[
        "martial art"
    ],
    "sg:website":"www.trainerselite.net/",
    "wof:name":"Trainers Elite",
    "wof:placetype":"venue"
},
  "geometry": {"coordinates":[-96.83171400000001,32.953298],"type":"Point"}
}