{
  "type": "Feature",
  "properties": {
    "iso:country":"US",
    "sg:address":"7505 Karl May Dr",
    "sg:city":"Waco",
    "sg:classifiers":[
        {
            "category":"Manufacturing",
            "subcategory":"Aerospace",
            "type":"Manufacturing & Wholesale Goods"
        }
    ],
    "sg:phone":"+1 254 752 8381",
    "sg:postcode":"76708",
    "sg:province":"TX",
    "sg:tags":[
        "engine",
        "aircraft",
        "parts"
    ],
    "sg:website":"www.ramaircraft.com",
    "wof:name":"RAM Aircraft Corp",
    "wof:placetype":"venue"
},
  "geometry": {"coordinates":[-97.217298,31.606899],"type":"Point"}
}