{
  "type": "Feature",
  "properties": {
    "iso:country":"US",
    "sg:address":"3301 Northland Dr Ste 500",
    "sg:city":"Austin",
    "sg:classifiers":[
        {
            "category":"Real Estate",
            "subcategory":"Real Estate Services",
            "type":"Services"
        },
        {
            "category":"Real Estate",
            "subcategory":"Real Estate Agent",
            "type":"Services"
        }
    ],
    "sg:phone":"+1 512 750 2523",
    "sg:postcode":"78731",
    "sg:province":"TX",
    "sg:website":"www.ESGRealty.com",
    "wof:name":"ESG Realty Advisors",
    "wof:placetype":"venue"
},
  "geometry": {"coordinates":[-97.756535,30.335661],"type":"Point"}
}