{
  "type": "Feature",
  "properties": {
    "iso:country":"US",
    "sg:address":"6816 Harmonson Rd",
    "sg:city":"Fort Worth",
    "sg:classifiers":[
        {
            "category":"Building & Trades",
            "subcategory":"Construction",
            "type":"Services"
        }
    ],
    "sg:phone":"+1 817 589 7601",
    "sg:postcode":"76180",
    "sg:province":"TX",
    "sg:tags":[
        "water",
        "work",
        "utility",
        "sewer",
        "contractor"
    ],
    "wof:name":"M-Co Construction Inc",
    "wof:placetype":"venue"
},
  "geometry": {"coordinates":[-97.23468099999999,32.820514],"type":"Point"}
}