{
  "type": "Feature",
  "properties": {
    "iso:country":"US",
    "sg:address":"4735 Denton Dr",
    "sg:city":"Dallas",
    "sg:classifiers":[
        {
            "category":"Real Estate",
            "subcategory":"Real Estate Operator",
            "type":"Services"
        }
    ],
    "sg:phone":"+1 214 528 3401",
    "sg:postcode":"75219",
    "sg:province":"TX",
    "sg:tags":[
        "building",
        "apartment"
    ],
    "wof:name":"Denton Oaks Apts",
    "wof:placetype":"venue"
},
  "geometry": {"coordinates":[-96.825142,32.816006],"type":"Point"}
}