{
  "type": "Feature",
  "properties": {
    "iso:country":"US",
    "sg:address":"4406 Wendell St",
    "sg:city":"Bellaire",
    "sg:classifiers":[
        {
            "category":"Home & Garden",
            "subcategory":"Home Furnishings",
            "type":"Retail Goods"
        }
    ],
    "sg:phone":"+1 713 665 5237",
    "sg:postcode":"77401",
    "sg:province":"TX",
    "wof:name":"Creations By Sandra",
    "wof:placetype":"venue"
},
  "geometry": {"coordinates":[-95.451114,29.698506],"type":"Point"}
}