{
  "type": "Feature",
  "properties": {
    "iso:country":"US",
    "sg:address":"1800 Bimini Way",
    "sg:city":"Seabrook",
    "sg:classifiers":[
        {
            "category":"Professional",
            "type":"Services"
        }
    ],
    "sg:phone":"+1 281 474 4913",
    "sg:postcode":"77586",
    "sg:province":"TX",
    "wof:name":"Lutco Products",
    "wof:placetype":"venue"
},
  "geometry": {"coordinates":[-95.020431,29.56826],"type":"Point"}
}