{
  "type": "Feature",
  "properties": {
    "iso:country":"US",
    "sg:address":"2504 Hemphill St",
    "sg:city":"Greenville",
    "sg:classifiers":[
        {
            "category":"Home & Garden",
            "subcategory":"Household Appliances",
            "type":"Retail Goods"
        }
    ],
    "sg:phone":"+1 903 455 3706",
    "sg:postcode":"75401",
    "sg:province":"TX",
    "sg:tags":[
        "repair",
        "electrical"
    ],
    "wof:name":"Curtis Appliance",
    "wof:placetype":"venue"
},
  "geometry": {"coordinates":[-96.106472,33.133311],"type":"Point"}
}