{
  "type": "Feature",
  "properties": {
    "iso:country":"US",
    "sg:address":"3514 State Hwy 6",
    "sg:city":"Sugar Land",
    "sg:classifiers":[
        {
            "category":"Home & Garden",
            "subcategory":"Home Furnishings",
            "type":"Retail Goods"
        }
    ],
    "sg:phone":"+1 281 980 1098",
    "sg:postcode":"77478",
    "sg:province":"TX",
    "sg:tags":[
        "mfg"
    ],
    "wof:name":"D & D Drapery Co",
    "wof:placetype":"venue"
},
  "geometry": {"coordinates":[-95.600508,29.590379],"type":"Point"}
}