{
  "type": "Feature",
  "properties": {
    "iso:country":"US",
    "sg:address":"12910 W Bellfort Ave",
    "sg:city":"Houston",
    "sg:classifiers":[
        {
            "category":"Organizations",
            "subcategory":"Religious Organization",
            "type":"Services"
        }
    ],
    "sg:phone":"+1 281 933 6340",
    "sg:postcode":"77099",
    "sg:province":"TX",
    "wof:name":"Southwest Clvary Baptst Church",
    "wof:placetype":"venue"
},
  "geometry": {"coordinates":[-95.609894,29.661432],"type":"Point"}
}