{
  "type": "Feature",
  "properties": {
    "iso:country":"US",
    "sg:address":"15607 Lone Tree Dr",
    "sg:city":"Houston",
    "sg:classifiers":[
        {
            "category":"Building & Trades",
            "subcategory":"Plumbing",
            "type":"Services"
        }
    ],
    "sg:phone":"+1 281 463 2735",
    "sg:postcode":"77084",
    "sg:province":"TX",
    "sg:tags":[
        "contractor"
    ],
    "wof:name":"Hausler Plumbing Company",
    "wof:placetype":"venue"
},
  "geometry": {"coordinates":[-95.63256,29.847823],"type":"Point"}
}