{
  "type": "Feature",
  "properties": {
    "iso:country":"US",
    "sg:address":"404 Cumberland Dr",
    "sg:city":"Nacogdoches",
    "sg:classifiers":[
        {
            "category":"Building & Trades",
            "subcategory":"Construction",
            "type":"Services"
        }
    ],
    "sg:phone":"+1 936 569 0367",
    "sg:postcode":"75965",
    "sg:province":"TX",
    "wof:name":"Danny Powell Inc",
    "wof:placetype":"venue"
},
  "geometry": {"coordinates":[-94.65469899999999,31.678763],"type":"Point"}
}