{
  "type": "Feature",
  "properties": {
    "iso:country":"US",
    "sg:address":"10777 Co Rd 3168",
    "sg:city":"Winona",
    "sg:classifiers":[
        {
            "category":"Building & Trades",
            "subcategory":"Construction",
            "type":"Services"
        }
    ],
    "sg:phone":"+1 903 984 9034",
    "sg:postcode":"75792",
    "sg:province":"TX",
    "sg:tags":[
        "maker",
        "cabinet"
    ],
    "wof:name":"R & R Custom Cabinetry",
    "wof:placetype":"venue"
},
  "geometry": {"coordinates":[-95.005797,32.417253],"type":"Point"}
}