{
  "type": "Feature",
  "properties": {
    "iso:country":"US",
    "sg:address":"400 S Main St",
    "sg:city":"Andrews",
    "sg:classifiers":[
        {
            "category":"Restaurant",
            "type":"Food & Drink"
        }
    ],
    "sg:phone":"+1 432 524 5074",
    "sg:postcode":"79714",
    "sg:province":"TX",
    "wof:name":"B's S Home Style Cooking",
    "wof:placetype":"venue"
},
  "geometry": {"coordinates":[-102.545558,32.315503],"type":"Point"}
}