{
  "type": "Feature",
  "properties": {
    "iso:country":"US",
    "sg:address":"5532 Glenwick Ln",
    "sg:city":"Dallas",
    "sg:classifiers":[
        {
            "category":"Professional",
            "type":"Services"
        }
    ],
    "sg:phone":"+1 214 358 1950",
    "sg:postcode":"75209",
    "sg:province":"TX",
    "sg:tags":[
        "establishment"
    ],
    "wof:name":"Wendy Wilson Designs",
    "wof:placetype":"venue"
},
  "geometry": {"coordinates":[-96.814798,32.847283],"type":"Point"}
}