{
  "type": "Feature",
  "properties": {
    "iso:country":"US",
    "sg:address":"11823 Park Creek Dr",
    "sg:city":"Houston",
    "sg:classifiers":[
        {
            "category":"Professional",
            "subcategory":"Business Services",
            "type":"Services"
        }
    ],
    "sg:phone":"+1 281 374 9294",
    "sg:postcode":"77070",
    "sg:province":"TX",
    "wof:name":"Bullfrogs To Butterflies",
    "wof:placetype":"venue"
},
  "geometry": {"coordinates":[-95.59904400000001,29.992119],"type":"Point"}
}