{
  "type": "Feature",
  "properties": {
    "iso:country":"US",
    "sg:address":"6216 Berthoud Pass",
    "sg:city":"Dallas",
    "sg:classifiers":[
        {
            "category":"Real Estate",
            "subcategory":"Real Estate Agent",
            "type":"Services"
        }
    ],
    "sg:phone":"+1 972 407 0833",
    "sg:postcode":"75252",
    "sg:province":"TX",
    "sg:tags":[
        "inspection"
    ],
    "wof:name":"Professional Home Inspections",
    "wof:placetype":"venue"
},
  "geometry": {"coordinates":[-96.798374,32.991529],"type":"Point"}
}