{
  "type": "Feature",
  "properties": {
    "iso:country":"US",
    "sg:address":"2121 San Jacinto St",
    "sg:city":"Dallas",
    "sg:classifiers":[
        {
            "category":"Manufacturing",
            "subcategory":"Petroleum Products",
            "type":"Manufacturing & Wholesale Goods"
        }
    ],
    "sg:phone":"+1 214 953 0180",
    "sg:postcode":"75201",
    "sg:province":"TX",
    "sg:tags":[
        "oil",
        "refiner"
    ],
    "wof:name":"Border Refining",
    "wof:placetype":"venue"
},
  "geometry": {"coordinates":[-96.796982,32.787264],"type":"Point"}
}