{
  "type": "Feature",
  "properties": {
    "iso:country":"US",
    "sg:address":"5902 Arboles Dr",
    "sg:city":"Houston",
    "sg:classifiers":[
        {
            "category":"Professional",
            "subcategory":"Management & Consulting",
            "type":"Services"
        }
    ],
    "sg:phone":"+1 713 721 3051",
    "sg:postcode":"77035",
    "sg:province":"TX",
    "wof:name":"D P Consulting",
    "wof:placetype":"venue"
},
  "geometry": {"coordinates":[-95.494878,29.654641],"type":"Point"}
}