{
  "type": "Feature",
  "properties": {
    "iso:country":"US",
    "sg:address":"857 Keller Pkwy",
    "sg:city":"Keller",
    "sg:classifiers":[
        {
            "category":"Shopping",
            "type":"Retail Goods"
        }
    ],
    "sg:phone":"+1 817 431 6467",
    "sg:postcode":"76248",
    "sg:province":"TX",
    "sg:tags":[
        "merchandise"
    ],
    "wof:name":"Hearing and Balance Center",
    "wof:placetype":"venue"
},
  "geometry": {"coordinates":[-97.23461,32.934437],"type":"Point"}
}