{
  "type": "Feature",
  "properties": {
    "iso:country":"US",
    "sg:address":"8521 Adirondack Tr",
    "sg:city":"Austin",
    "sg:classifiers":[
        {
            "category":"Real Estate",
            "subcategory":"Real Estate Services",
            "type":"Services"
        }
    ],
    "sg:phone":"+1 512 636 6962",
    "sg:postcode":"78759",
    "sg:province":"TX",
    "sg:tags":[
        "home",
        "inspector"
    ],
    "sg:website":"www.360inspection.com/",
    "wof:name":"360 Home Inspection",
    "wof:placetype":"venue"
},
  "geometry": {"coordinates":[-97.76195300000001,30.383373],"type":"Point"}
}