{
  "type": "Feature",
  "properties": {
    "iso:country":"US",
    "sg:address":"4413 Pearl Ct",
    "sg:city":"Plano",
    "sg:classifiers":[
        {
            "category":"Shopping",
            "subcategory":"Gifts & Souvenirs",
            "type":"Retail Goods"
        }
    ],
    "sg:phone":"+1 972 989 4866",
    "sg:postcode":"75024",
    "sg:province":"TX",
    "wof:name":"Speranza Design Gallery",
    "wof:placetype":"venue"
},
  "geometry": {"coordinates":[-96.77962100000001,33.084484],"type":"Point"}
}