{
  "type": "Feature",
  "properties": {
    "iso:country":"US",
    "sg:address":"2902 Tinaja St",
    "sg:city":"Laredo",
    "sg:classifiers":[
        {
            "category":"Home & Garden",
            "subcategory":"Building Materials",
            "type":"Retail Goods"
        }
    ],
    "sg:phone":"+1 956 723 8979",
    "sg:postcode":"78046",
    "sg:province":"TX",
    "wof:name":"New York Building Materials",
    "wof:placetype":"venue"
},
  "geometry": {"coordinates":[-99.465377,27.473194],"type":"Point"}
}