{
  "type": "Feature",
  "properties": {
    "iso:country":"US",
    "sg:address":"424 Gatewood Rd",
    "sg:city":"Garland",
    "sg:classifiers":[
        {
            "category":"Real Estate",
            "subcategory":"Real Estate Operator",
            "type":"Services"
        }
    ],
    "sg:phone":"+1 972 240 8973",
    "sg:postcode":"75043",
    "sg:province":"TX",
    "sg:tags":[
        "apartment"
    ],
    "wof:name":"Gatewood Village Apartments",
    "wof:placetype":"venue"
},
  "geometry": {"coordinates":[-96.60642199999999,32.854332],"type":"Point"}
}