{
  "type": "Feature",
  "properties": {
    "iso:country":"US",
    "sg:address":"4300 Town Center Pl",
    "sg:city":"Kingwood",
    "sg:classifiers":[
        {
            "category":"Bars & Pubs",
            "type":"Food & Drink"
        },
        {
            "category":"Restaurant",
            "type":"Food & Drink"
        },
        {
            "category":"Bars & Pubs",
            "subcategory":"Lounge",
            "type":"Food & Drink"
        }
    ],
    "sg:phone":"+1 281 360 1789",
    "sg:postcode":"77339",
    "sg:province":"TX",
    "sg:tags":[
        "grill",
        "mexican",
        "brew",
        "cocktail"
    ],
    "wof:name":"Chachi's Mexican Bar And Grill",
    "wof:placetype":"venue"
},
  "geometry": {"coordinates":[-95.185593,30.04777],"type":"Point"}
}