{
  "type": "Feature",
  "properties": {
    "iso:country":"US",
    "sg:address":"9892 W University Blvd",
    "sg:city":"Odessa",
    "sg:classifiers":[
        {
            "category":"Shopping",
            "subcategory":"Hobbies, Toys, & Games",
            "type":"Retail Goods"
        }
    ],
    "sg:phone":"+1 432 381 3144",
    "sg:postcode":"79764",
    "sg:province":"TX",
    "sg:tags":[
        "product",
        "ceramic"
    ],
    "wof:name":"Sugar N Spice Ceramics",
    "wof:placetype":"venue"
},
  "geometry": {"coordinates":[-102.491581,31.843224],"type":"Point"}
}