{
  "type": "Feature",
  "properties": {
    "iso:country":"US",
    "sg:address":"2222 Rio Grande Ste 200",
    "sg:city":"Austin",
    "sg:classifiers":[
        {
            "category":"Real Estate",
            "subcategory":"Real Estate Services",
            "type":"Services"
        }
    ],
    "sg:phone":"+1 512 531 0123",
    "sg:postcode":"78705",
    "sg:province":"TX",
    "wof:name":"The Quarters on Campus",
    "wof:placetype":"venue"
},
  "geometry": {"coordinates":[-97.744803,30.286701],"type":"Point"}
}