{
  "type": "Feature",
  "properties": {
    "iso:country":"US",
    "sg:address":"405 US Hwy 281",
    "sg:city":"Hamilton",
    "sg:classifiers":[
        {
            "category":"Retail",
            "subcategory":"Veterinary Services",
            "type":"Services"
        }
    ],
    "sg:phone":"+1 254 386 8195",
    "sg:postcode":"76531",
    "sg:province":"TX",
    "wof:name":"Hamilton Cnty Vterinary Clinic",
    "wof:placetype":"venue"
},
  "geometry": {"coordinates":[-98.125325,31.700931],"type":"Point"}
}