{
  "type": "Feature",
  "properties": {
    "iso:country":"US",
    "sg:address":"2610 Sam Houston Pkwy",
    "sg:city":"Houston",
    "sg:classifiers":[
        {
            "category":"Shopping",
            "subcategory":"Computers & Home Electronics",
            "type":"Retail Goods"
        }
    ],
    "sg:phone":"+1 713 974 5050",
    "sg:postcode":"77042",
    "sg:province":"TX",
    "sg:tags":[
        "equipment",
        "dealer"
    ],
    "wof:name":"UBM Computer Systems",
    "wof:placetype":"venue"
},
  "geometry": {"coordinates":[-95.55847199999999,29.73677],"type":"Point"}
}