{
  "type": "Feature",
  "properties": {
    "iso:country":"US",
    "sg:address":"1404 Timber Ridge Dr",
    "sg:city":"Euless",
    "sg:classifiers":[
        {
            "category":"Professional",
            "subcategory":"Business Services",
            "type":"Services"
        }
    ],
    "sg:phone":"+1 817 267 3194",
    "sg:postcode":"76039",
    "sg:province":"TX",
    "wof:name":"Deventer Technology LLC",
    "wof:placetype":"venue"
},
  "geometry": {"coordinates":[-97.096917,32.856664],"type":"Point"}
}