{
  "type": "Feature",
  "properties": {
    "iso:country":"US",
    "sg:address":"901 S Amy Ln",
    "sg:city":"Harker Heights",
    "sg:classifiers":[
        {
            "category":"Professional",
            "subcategory":"Business Services",
            "type":"Services"
        },
        {
            "category":"Building & Trades",
            "subcategory":"Construction",
            "type":"Services"
        }
    ],
    "sg:phone":"+1 254 699 6345",
    "sg:postcode":"76548",
    "sg:province":"TX",
    "sg:tags":[
        "residential",
        "designer"
    ],
    "wof:name":"Curtis Cook Residential Design",
    "wof:placetype":"venue"
},
  "geometry": {"coordinates":[-97.66476299999999,31.08024],"type":"Point"}
}