{
  "type": "Feature",
  "properties": {
    "iso:country":"US",
    "sg:address":"2503 Blanco Rd",
    "sg:city":"San Antonio",
    "sg:classifiers":[
        {
            "category":"Education",
            "subcategory":"Vocational School",
            "type":"Public Place"
        },
        {
            "category":"Organizations",
            "subcategory":"Labor Organization",
            "type":"Services"
        }
    ],
    "sg:phone":"+1 210 225 8900",
    "sg:postcode":"78212",
    "sg:province":"TX",
    "wof:name":"South Texas Electrical J A T C",
    "wof:placetype":"venue"
},
  "geometry": {"coordinates":[-98.507941,29.470588],"type":"Point"}
}