{
  "type": "Feature",
  "properties": {
    "iso:country":"US",
    "sg:address":"7814 S US Hwy 277",
    "sg:city":"San Angelo",
    "sg:phone":"+1 325 651 7345",
    "sg:postcode":"76904",
    "sg:province":"TX",
    "sg:tags":[
        "farm",
        "grain",
        "cash",
        "cotton"
    ],
    "wof:name":"Beach John",
    "wof:placetype":"venue"
},
  "geometry": {"coordinates":[-100.433488,31.369708],"type":"Point"}
}