{
  "type": "Feature",
  "properties": {
    "iso:country":"US",
    "sg:address":"5501 S 1st St",
    "sg:city":"Abilene",
    "sg:classifiers":[
        {
            "category":"Autos & Motor Vehicles",
            "subcategory":"Automobile Sales",
            "type":"Retail Goods"
        }
    ],
    "sg:phone":"+1 325 695 8166",
    "sg:postcode":"79605",
    "sg:province":"TX",
    "sg:tags":[
        "car",
        "used",
        "dealer"
    ],
    "wof:name":"B & L Auto Sales",
    "wof:placetype":"venue"
},
  "geometry": {"coordinates":[-99.799646,32.453035],"type":"Point"}
}