{
  "type": "Feature",
  "properties": {
    "iso:country":"US",
    "sg:address":"8435 Hidden Meadow Dr",
    "sg:city":"San Antonio",
    "sg:classifiers":[
        {
            "category":"Personal",
            "type":"Services"
        }
    ],
    "sg:phone":"+1 210 366 2453",
    "sg:postcode":"78230",
    "sg:province":"TX",
    "wof:name":"Lori S Binz",
    "wof:placetype":"venue"
},
  "geometry": {"coordinates":[-98.54813300000001,29.517149],"type":"Point"}
}