{
  "type": "Feature",
  "properties": {
    "iso:country":"US",
    "sg:address":"2828 Southampton Way",
    "sg:city":"Round Rock",
    "sg:classifiers":[
        {
            "category":"Real Estate",
            "subcategory":"Real Estate Agent",
            "type":"Services"
        }
    ],
    "sg:phone":"+1 512 796 3288",
    "sg:postcode":"78664",
    "sg:province":"TX",
    "wof:name":"Greenmark Properties LTD",
    "wof:placetype":"venue"
},
  "geometry": {"coordinates":[-97.621849,30.490403],"type":"Point"}
}