{
  "type": "Feature",
  "properties": {
    "iso:country":"US",
    "sg:address":"1302 Griner St",
    "sg:city":"Del Rio",
    "sg:classifiers":[
        {
            "category":"Education",
            "subcategory":"Dance Studio",
            "type":"Public Place"
        }
    ],
    "sg:phone":"+1 830 734 7984",
    "sg:postcode":"78840",
    "sg:province":"TX",
    "sg:tags":[
        "instruction",
        "dancing"
    ],
    "wof:name":"Georga's School Of Dance",
    "wof:placetype":"venue"
},
  "geometry": {"coordinates":[-100.89936299999999,29.352047],"type":"Point"}
}