{
  "type": "Feature",
  "properties": {
    "iso:country":"US",
    "sg:address":"9130 State Hwy 6",
    "sg:city":"Hitchcock",
    "sg:classifiers":[
        {
            "category":"Recreation",
            "subcategory":"Arcade",
            "type":"Entertainment"
        }
    ],
    "sg:phone":"+1 409 986 8392",
    "sg:postcode":"77563",
    "sg:province":"TX",
    "sg:tags":[
        "video"
    ],
    "wof:name":"Winner's Circle",
    "wof:placetype":"venue"
},
  "geometry": {"coordinates":[-95.034705,29.354027],"type":"Point"}
}