{
  "type": "Feature",
  "properties": {
    "iso:country":"US",
    "sg:address":"3686 Woodville Rd",
    "sg:city":"Bryan",
    "sg:classifiers":[
        {
            "category":"Food & Beverages",
            "subcategory":"Specialty",
            "type":"Retail Goods"
        }
    ],
    "sg:phone":"+1 979 778 0202",
    "sg:postcode":"77808",
    "sg:province":"TX",
    "wof:name":"Lake Limestone Coves Wate",
    "wof:placetype":"venue"
},
  "geometry": {"coordinates":[-96.38384000000001,30.718141],"type":"Point"}
}