{
  "type": "Feature",
  "properties": {
    "iso:country":"US",
    "sg:address":"1752 Haverford Dr",
    "sg:city":"Allen",
    "sg:classifiers":[
        {
            "category":"Building & Trades",
            "subcategory":"Construction",
            "type":"Services"
        }
    ],
    "sg:phone":"+1 214 509 9230",
    "sg:postcode":"75013",
    "sg:province":"TX",
    "sg:tags":[
        "contractor",
        "painting",
        "hanging"
    ],
    "wof:name":"William Patterson Painter/Prin",
    "wof:placetype":"venue"
},
  "geometry": {"coordinates":[-96.72071,33.090181],"type":"Point"}
}