{
  "type": "Feature",
  "properties": {
    "iso:country":"US",
    "sg:address":"3412 Binyon Ave",
    "sg:city":"Fort Worth",
    "sg:classifiers":[
        {
            "category":"Professional",
            "subcategory":"Business Services",
            "type":"Services"
        }
    ],
    "sg:phone":"+1 817 926 2291",
    "sg:postcode":"76133",
    "sg:province":"TX",
    "wof:name":"Farmer Owned Enterprises",
    "wof:placetype":"venue"
},
  "geometry": {"coordinates":[-97.369007,32.679068],"type":"Point"}
}