{
  "type": "Feature",
  "properties": {
    "iso:country":"US",
    "sg:address":"22429 Kidd Cemetery Rd",
    "sg:city":"New Caney",
    "sg:classifiers":[
        {
            "category":"Health Services",
            "subcategory":"Doctor",
            "type":"Services"
        }
    ],
    "sg:phone":"+1 281 446 4529",
    "sg:postcode":"77357",
    "sg:province":"TX",
    "wof:name":"Carl Panzarella DDS",
    "wof:placetype":"venue"
},
  "geometry": {"coordinates":[-95.227993,30.160475],"type":"Point"}
}