{
  "type": "Feature",
  "properties": {
    "iso:country":"US",
    "sg:address":"10959 Newton Cir",
    "sg:city":"Conroe",
    "sg:classifiers":[
        {
            "category":"Wholesale",
            "subcategory":"Machinery & Supplies",
            "type":"Manufacturing & Wholesale Goods"
        }
    ],
    "sg:phone":"+1 936 788 1400",
    "sg:postcode":"77303",
    "sg:province":"TX",
    "sg:tags":[
        "fitting",
        "hose",
        "coupling"
    ],
    "wof:name":"Dew Enterprises",
    "wof:placetype":"venue"
},
  "geometry": {"coordinates":[-95.27593899999999,30.389276],"type":"Point"}
}