{
  "type": "Feature",
  "properties": {
    "iso:country":"US",
    "sg:address":"228 Willow Creek Dr",
    "sg:city":"Weatherford",
    "sg:classifiers":[
        {
            "category":"Personal",
            "type":"Services"
        }
    ],
    "sg:phone":"+1 817 599 4275",
    "sg:postcode":"76085",
    "sg:province":"TX",
    "sg:tags":[
        "counseling"
    ],
    "wof:name":"Safe Harbor Counseling Center",
    "wof:placetype":"venue"
},
  "geometry": {"coordinates":[-97.749809,32.759869],"type":"Point"}
}