{
  "type": "Feature",
  "properties": {
    "iso:country":"US",
    "sg:address":"104 W Polk St",
    "sg:city":"Burnet",
    "sg:classifiers":[
        {
            "category":"Personal",
            "subcategory":"Beauty Salon",
            "type":"Services"
        }
    ],
    "sg:phone":"+1 512 715 8200",
    "sg:postcode":"78611",
    "sg:province":"TX",
    "sg:tags":[
        "hair",
        "stylist"
    ],
    "sg:website":"http://www.cuttingedgetools.com",
    "wof:name":"The Cutting Edge",
    "wof:placetype":"venue"
},
  "geometry": {"coordinates":[-98.227779,30.75831],"type":"Point"}
}