{
  "type": "Feature",
  "properties": {
    "iso:country":"US",
    "sg:address":"5653 W Riverpark Dr",
    "sg:city":"Sugar Land",
    "sg:classifiers":[
        {
            "category":"Education",
            "subcategory":"Dance Studio",
            "type":"Public Place"
        }
    ],
    "sg:phone":"+1 281 265 3100",
    "sg:postcode":"77479",
    "sg:province":"TX",
    "sg:tags":[
        "instruction",
        "dancing"
    ],
    "wof:name":"Reni Antley School Of Dance",
    "wof:placetype":"venue"
},
  "geometry": {"coordinates":[-95.794701,29.626111],"type":"Point"}
}