{
  "type": "Feature",
  "properties": {
    "iso:country":"US",
    "sg:address":"13092 Veterans Memorial Dr",
    "sg:city":"Houston",
    "sg:classifiers":[
        {
            "category":"Home & Garden",
            "subcategory":"Furniture",
            "type":"Retail Goods"
        }
    ],
    "sg:phone":"+1 281 893 1999",
    "sg:postcode":"77014",
    "sg:province":"TX",
    "wof:name":"V T M Furniture",
    "wof:placetype":"venue"
},
  "geometry": {"coordinates":[-95.490309,29.977018],"type":"Point"}
}