{
  "type": "Feature",
  "properties": {
    "iso:country":"US",
    "sg:address":"3939 Hartsdale Dr",
    "sg:city":"Houston",
    "sg:classifiers":[
        {
            "category":"Real Estate",
            "subcategory":"Real Estate Operator",
            "type":"Services"
        }
    ],
    "sg:phone":"+1 713 783 7343",
    "sg:postcode":"77063",
    "sg:province":"TX",
    "sg:tags":[
        "building",
        "apartment"
    ],
    "wof:name":"Papadopoulos Assoc",
    "wof:placetype":"venue"
},
  "geometry": {"coordinates":[-95.507654,29.723641],"type":"Point"}
}