{
  "type": "Feature",
  "properties": {
    "iso:country":"US",
    "sg:address":"735 W Chestnut St",
    "sg:city":"Denison",
    "sg:classifiers":[
        {
            "category":"Professional",
            "subcategory":"Accounting & Tax Preparation",
            "type":"Services"
        }
    ],
    "sg:phone":"+1 903 463 5051",
    "sg:postcode":"75020",
    "sg:province":"TX",
    "sg:tags":[
        "return"
    ],
    "wof:name":"H & R Block",
    "wof:placetype":"venue"
},
  "geometry": {"coordinates":[-96.545708,33.754739],"type":"Point"}
}