{
  "type": "Feature",
  "properties": {
    "iso:country":"US",
    "sg:address":"820 N Zang Blvd",
    "sg:city":"Dallas",
    "sg:classifiers":[
        {
            "category":"Health Services",
            "subcategory":"Doctor",
            "type":"Services"
        }
    ],
    "sg:phone":"+1 214 946 1515",
    "sg:postcode":"75208",
    "sg:province":"TX",
    "sg:tags":[
        "clinic"
    ],
    "wof:name":"North Zang Medical Clinic",
    "wof:placetype":"venue"
},
  "geometry": {"coordinates":[-96.82405799999999,32.753462],"type":"Point"}
}