{
  "type": "Feature",
  "properties": {
    "iso:country":"US",
    "sg:address":"602 Sawyer St",
    "sg:city":"Houston",
    "sg:classifiers":[
        {
            "category":"Personal",
            "type":"Services"
        }
    ],
    "sg:phone":"+1 281 829 4161",
    "sg:postcode":"77007",
    "sg:province":"TX",
    "sg:tags":[
        "mover"
    ],
    "wof:name":"Houston Moving",
    "wof:placetype":"venue"
},
  "geometry": {"coordinates":[-95.380921,29.764681],"type":"Point"}
}