{
  "type": "Feature",
  "properties": {
    "iso:country":"US",
    "sg:address":"5705 Carry Back Ln",
    "sg:city":"Austin",
    "sg:classifiers":[
        {
            "category":"Professional",
            "subcategory":"Business Services",
            "type":"Services"
        }
    ],
    "sg:phone":"+1 512 327 2566",
    "sg:postcode":"78746",
    "sg:province":"TX",
    "sg:tags":[
        "interior",
        "consultant",
        "design",
        "decorator"
    ],
    "wof:name":"Ann Temple Interiors",
    "wof:placetype":"venue"
},
  "geometry": {"coordinates":[-97.80131900000001,30.332099],"type":"Point"}
}