{
  "type": "Feature",
  "properties": {
    "iso:country":"US",
    "sg:address":"18351 FM 150 W",
    "sg:city":"Driftwood",
    "sg:classifiers":[
        {
            "category":"Real Estate",
            "subcategory":"Real Estate Operator",
            "type":"Services"
        }
    ],
    "sg:phone":"+1 512 858 2205",
    "sg:postcode":"78619",
    "sg:province":"TX",
    "sg:tags":[
        "building",
        "nonresidential"
    ],
    "wof:name":"Driftwood Properties LLC",
    "wof:placetype":"venue"
},
  "geometry": {"coordinates":[-98.046314,30.14379],"type":"Point"}
}