{
  "type": "Feature",
  "properties": {
    "iso:country":"US",
    "sg:address":"9000 Benbrook Blvd",
    "sg:city":"Benbrook",
    "sg:classifiers":[
        {
            "category":"Restaurant",
            "type":"Food & Drink"
        }
    ],
    "sg:phone":"+1 817 249 3320",
    "sg:postcode":"76126",
    "sg:province":"TX",
    "sg:tags":[
        "house",
        "steak",
        "barbecue"
    ],
    "sg:website":"http://www.risckys.com",
    "wof:name":"Risckys Deli",
    "wof:placetype":"venue"
},
  "geometry": {"coordinates":[-97.467781,32.67511],"type":"Point"}
}