{
  "type": "Feature",
  "properties": {
    "iso:country":"US",
    "sg:address":"1239 Porter Rd",
    "sg:city":"Flower Mound",
    "sg:classifiers":[
        {
            "category":"Shopping",
            "type":"Retail Goods"
        },
        {
            "category":"Wholesale",
            "subcategory":"Non-durable Goods",
            "type":"Manufacturing & Wholesale Goods"
        }
    ],
    "sg:phone":"+1 817 491 4942",
    "sg:postcode":"75022",
    "sg:province":"TX",
    "sg:tags":[
        "tropical",
        "fish"
    ],
    "wof:name":"Tropical Warehouses Inc",
    "wof:placetype":"venue"
},
  "geometry": {"coordinates":[-97.14605400000001,33.055464],"type":"Point"}
}