{
  "type": "Feature",
  "properties": {
    "iso:country":"US",
    "sg:address":"516 Ferry Rd",
    "sg:city":"Galveston",
    "sg:classifiers":[
        {
            "category":"Health Services",
            "subcategory":"Clinic",
            "type":"Services"
        }
    ],
    "sg:phone":"+1 409 877 2409",
    "sg:postcode":"77550",
    "sg:province":"TX",
    "sg:tags":[
        "welfare"
    ],
    "wof:name":"Open Hands Foundation, The",
    "wof:placetype":"venue"
},
  "geometry": {"coordinates":[-94.770554,29.321461],"type":"Point"}
}