{
  "type": "Feature",
  "properties": {
    "iso:country":"US",
    "sg:address":"8202 Beechnut St",
    "sg:city":"Houston",
    "sg:classifiers":[
        {
            "category":"Food & Beverages",
            "subcategory":"Liquor & Beverages",
            "type":"Retail Goods"
        }
    ],
    "sg:phone":"+1 713 988 6563",
    "sg:postcode":"77036",
    "sg:province":"TX",
    "sg:tags":[
        "alcoholic"
    ],
    "wof:name":"World Freedom Shrimp BT",
    "wof:placetype":"venue"
},
  "geometry": {"coordinates":[-95.528357,29.692469],"type":"Point"}
}