{
  "type": "Feature",
  "properties": {
    "iso:country":"US",
    "sg:address":"740 S Sherman St",
    "sg:city":"Richardson",
    "sg:classifiers":[
        {
            "category":"Professional",
            "subcategory":"Lawyer & Legal Services",
            "type":"Services"
        }
    ],
    "sg:phone":"+1 972 231 4279",
    "sg:postcode":"75081",
    "sg:province":"TX",
    "wof:name":"Jeanes Wesley Atty",
    "wof:placetype":"venue"
},
  "geometry": {"coordinates":[-96.739799,32.941799],"type":"Point"}
}