{
  "type": "Feature",
  "properties": {
    "iso:country":"US",
    "sg:address":"2416 Yorktown St",
    "sg:city":"Houston",
    "sg:classifiers":[
        {
            "category":"Manufacturing",
            "subcategory":"Retail Goods",
            "type":"Manufacturing & Wholesale Goods"
        }
    ],
    "sg:phone":"+1 713 877 9060",
    "sg:postcode":"77056",
    "sg:province":"TX",
    "sg:tags":[
        "assembly",
        "fabricating"
    ],
    "wof:name":"Magnolia Industrial Fab",
    "wof:placetype":"venue"
},
  "geometry": {"coordinates":[-95.47081,29.742432],"type":"Point"}
}