{
  "type": "Feature",
  "properties": {
    "iso:country":"US",
    "sg:address":"6809 Permian Ln",
    "sg:city":"Fort Worth",
    "sg:classifiers":[
        {
            "category":"Shopping",
            "type":"Retail Goods"
        }
    ],
    "sg:phone":"+1 817 683 4431",
    "sg:postcode":"76137",
    "sg:province":"TX",
    "sg:tags":[
        "merchandise"
    ],
    "wof:name":"Candleworks",
    "wof:placetype":"venue"
},
  "geometry": {"coordinates":[-97.307086,32.869337],"type":"Point"}
}