{
  "type": "Feature",
  "properties": {
    "iso:country":"US",
    "sg:address":"7808 Richard Frank Way",
    "sg:city":"San Antonio",
    "sg:classifiers":[
        {
            "category":"Building & Trades",
            "subcategory":"Construction",
            "type":"Services"
        }
    ],
    "sg:phone":"+1 210 720 0140",
    "sg:postcode":"78240",
    "sg:province":"TX",
    "sg:tags":[
        "hanging",
        "contractor"
    ],
    "wof:name":"Sciarrettas Painting",
    "wof:placetype":"venue"
},
  "geometry": {"coordinates":[-98.62064700000001,29.516707],"type":"Point"}
}