{
  "type": "Feature",
  "properties": {
    "iso:country":"US",
    "sg:address":"7931 Southwest Fwy",
    "sg:city":"Houston",
    "sg:classifiers":[
        {
            "category":"Autos & Motor Vehicles",
            "subcategory":"Auto Supplies",
            "type":"Retail Goods"
        }
    ],
    "sg:phone":"+1 713 270 5001",
    "sg:postcode":"77074",
    "sg:province":"TX",
    "sg:tags":[
        "tire"
    ],
    "sg:website":"www.tires.com",
    "wof:name":"Discount Tire Co",
    "wof:placetype":"venue"
},
  "geometry": {"coordinates":[-95.525842,29.692542],"type":"Point"}
}