{
  "type": "Feature",
  "properties": {
    "iso:country":"US",
    "sg:address":"202 NE 19th St",
    "sg:city":"Grand Prairie",
    "sg:classifiers":[
        {
            "category":"Retail",
            "subcategory":"Auto Repair",
            "type":"Services"
        }
    ],
    "sg:phone":"+1 972 262 2878",
    "sg:postcode":"75050",
    "sg:province":"TX",
    "sg:tags":[
        "exhaust"
    ],
    "wof:name":"Mejia Muffler & Radiator Shop",
    "wof:placetype":"venue"
},
  "geometry": {"coordinates":[-96.977918,32.750668],"type":"Point"}
}