{
  "type": "Feature",
  "properties": {
    "iso:country":"US",
    "sg:address":"1402 N Loop 336 W Ste B",
    "sg:city":"Conroe",
    "sg:classifiers":[
        {
            "category":"Shopping",
            "subcategory":"Pets & Pet Supplies",
            "type":"Retail Goods"
        },
        {
            "category":"Retail",
            "subcategory":"Veterinary Services",
            "type":"Services"
        },
        {
            "category":"Retail",
            "subcategory":"Animal Services",
            "type":"Services"
        }
    ],
    "sg:phone":"+1 936 756 0304",
    "sg:postcode":"77304",
    "sg:province":"TX",
    "sg:tags":[
        "grooming",
        "cat",
        "specialty",
        "dog"
    ],
    "wof:name":"Derusha, Randall Dvm",
    "wof:placetype":"venue"
},
  "geometry": {"coordinates":[-95.479799,30.333121],"type":"Point"}
}