{
  "type": "Feature",
  "properties": {
    "iso:country":"US",
    "sg:address":"12220 Dwight Eisenhower St",
    "sg:city":"Manor",
    "sg:classifiers":[
        {
            "category":"Real Estate",
            "subcategory":"Real Estate Agent",
            "type":"Services"
        }
    ],
    "sg:phone":"+1 512 278 0372",
    "sg:postcode":"78653",
    "sg:province":"TX",
    "wof:name":"Goodwin Management",
    "wof:placetype":"venue"
},
  "geometry": {"coordinates":[-97.525475,30.35382],"type":"Point"}
}