{
  "type": "Feature",
  "properties": {
    "iso:country":"US",
    "sg:address":"555 Klappenbach Rd",
    "sg:city":"Johnson City",
    "sg:classifiers":[
        {
            "category":"Farming",
            "subcategory":"Farm",
            "type":"Manufacturing & Wholesale Goods"
        }
    ],
    "sg:phone":"+1 830 868 4457",
    "sg:postcode":"78636",
    "sg:province":"TX",
    "sg:tags":[
        "crop",
        "general"
    ],
    "wof:name":"Herman Klappenbach",
    "wof:placetype":"venue"
},
  "geometry": {"coordinates":[-98.44235,30.246106],"type":"Point"}
}