{
  "type": "Feature",
  "properties": {
    "iso:country":"US",
    "sg:address":"800 S Main Ave",
    "sg:city":"Freer",
    "sg:classifiers":[
        {
            "category":"Personal",
            "subcategory":"Beauty Salon",
            "type":"Services"
        }
    ],
    "sg:phone":"+1 361 394 7228",
    "sg:postcode":"78357",
    "sg:province":"TX",
    "sg:tags":[
        "shop"
    ],
    "wof:name":"Angelita's Beauty Shop",
    "wof:placetype":"venue"
},
  "geometry": {"coordinates":[-98.615645,27.875739],"type":"Point"}
}