{
  "type": "Feature",
  "properties": {
    "iso:country":"US",
    "sg:address":"6951 Forest Glade Cir",
    "sg:city":"Dallas",
    "sg:classifiers":[
        {
            "category":"Shopping",
            "subcategory":"Clothing, Apparel, & Fashions",
            "type":"Retail Goods"
        }
    ],
    "sg:phone":"+1 214 365 0714",
    "sg:postcode":"75230",
    "sg:province":"TX",
    "sg:tags":[
        "apparel",
        "sportswear",
        "women's"
    ],
    "wof:name":"Asterisk Wear",
    "wof:placetype":"venue"
},
  "geometry": {"coordinates":[-96.786243,32.893808],"type":"Point"}
}