{
  "type": "Feature",
  "properties": {
    "iso:country":"US",
    "sg:address":"19711 Ivory Mills Ln",
    "sg:city":"Houston",
    "sg:classifiers":[
        {
            "category":"Shopping",
            "type":"Retail Goods"
        }
    ],
    "sg:phone":"+1 281 492 0990",
    "sg:postcode":"77094",
    "sg:province":"TX",
    "sg:tags":[
        "merchandise"
    ],
    "wof:name":"2c Beads & More",
    "wof:placetype":"venue"
},
  "geometry": {"coordinates":[-95.711291,29.760971],"type":"Point"}
}