{
  "type": "Feature",
  "properties": {
    "iso:country":"US",
    "sg:address":"5435 E Grand Ave",
    "sg:city":"Dallas",
    "sg:classifiers":[
        {
            "category":"Shopping",
            "subcategory":"Clothing, Apparel, & Fashions",
            "type":"Retail Goods"
        }
    ],
    "sg:phone":"+1 214 929 1791",
    "sg:postcode":"75223",
    "sg:province":"TX",
    "sg:tags":[
        "shop",
        "bridal"
    ],
    "wof:name":"Jessica's Bridals",
    "wof:placetype":"venue"
},
  "geometry": {"coordinates":[-96.748592,32.79268],"type":"Point"}
}