{
  "type": "Feature",
  "properties": {
    "iso:country":"US",
    "sg:address":"6214 Nyoka St",
    "sg:city":"Houston",
    "sg:classifiers":[
        {
            "category":"Retail",
            "subcategory":"Auto Repair",
            "type":"Services"
        }
    ],
    "sg:phone":"+1 713 937 8210",
    "sg:postcode":"77041",
    "sg:province":"TX",
    "sg:tags":[
        "truck"
    ],
    "wof:name":"Hank's Mobile Mechanics Inc",
    "wof:placetype":"venue"
},
  "geometry": {"coordinates":[-95.547628,29.861262],"type":"Point"}
}