{
  "type": "Feature",
  "properties": {
    "iso:country":"US",
    "sg:address":"14525 Fm 529 Rd Ste 205",
    "sg:city":"Houston",
    "sg:classifiers":[
        {
            "category":"Real Estate",
            "subcategory":"Real Estate Services",
            "type":"Services"
        },
        {
            "category":"Real Estate",
            "subcategory":"Real Estate Agent",
            "type":"Services"
        }
    ],
    "sg:phone":"+1 281 856 0445",
    "sg:postcode":"77095",
    "sg:province":"TX",
    "sg:tags":[
        "buyer",
        "broker"
    ],
    "wof:name":"Country Community Services, Inc",
    "wof:placetype":"venue"
},
  "geometry": {"coordinates":[-95.62783899999999,29.879437],"type":"Point"}
}