{
  "type": "Feature",
  "properties": {
    "iso:country":"US",
    "sg:address":"235 Sunset Dr",
    "sg:city":"Red Oak",
    "sg:classifiers":[
        {
            "category":"Shopping",
            "subcategory":"Gifts & Souvenirs",
            "type":"Retail Goods"
        }
    ],
    "sg:phone":"+1 972 617 3036",
    "sg:postcode":"75154",
    "sg:province":"TX",
    "wof:name":"Inspired By Ivanna",
    "wof:placetype":"venue"
},
  "geometry": {"coordinates":[-96.852445,32.536453],"type":"Point"}
}