{
  "type": "Feature",
  "properties": {
    "iso:country":"US",
    "sg:address":"9330 Amberton Pkwy",
    "sg:city":"Dallas",
    "sg:classifiers":[
        {
            "category":"Local Transit",
            "type":"Transportation"
        }
    ],
    "sg:phone":"+1 972 238 5400",
    "sg:postcode":"75243",
    "sg:province":"TX",
    "sg:tags":[
        "passenger"
    ],
    "wof:name":"Farmer Logistics and Trnsp",
    "wof:placetype":"venue"
},
  "geometry": {"coordinates":[-96.740577,32.91911],"type":"Point"}
}