{
  "type": "Feature",
  "properties": {
    "iso:country":"US",
    "sg:address":"2622 Gerol Ct",
    "sg:city":"Galveston",
    "sg:classifiers":[
        {
            "category":"Manufacturing",
            "subcategory":"Printing",
            "type":"Manufacturing & Wholesale Goods"
        }
    ],
    "sg:phone":"+1 409 744 7848",
    "sg:postcode":"77551",
    "sg:province":"TX",
    "sg:tags":[
        "publishing"
    ],
    "wof:name":"What We Do Best LLC",
    "wof:placetype":"venue"
},
  "geometry": {"coordinates":[-94.84469199999999,29.267826],"type":"Point"}
}