{
  "type": "Feature",
  "properties": {
    "iso:country":"US",
    "sg:address":"939 W Pioneer Pkwy",
    "sg:city":"Arlington",
    "sg:classifiers":[
        {
            "category":"Building & Trades",
            "subcategory":"Equipment Rental",
            "type":"Services"
        }
    ],
    "sg:phone":"+1 817 275 3600",
    "sg:postcode":"76013",
    "sg:province":"TX",
    "sg:tags":[
        "appliance",
        "electronics",
        "leasing",
        "furniture"
    ],
    "wof:name":"Rent-A-Center",
    "wof:placetype":"venue"
},
  "geometry": {"coordinates":[-97.122923,32.708969],"type":"Point"}
}