{
  "type": "Feature",
  "properties": {
    "iso:country":"US",
    "sg:address":"16922 Colony Creek Dr",
    "sg:city":"Spring",
    "sg:classifiers":[
        {
            "category":"Shopping",
            "subcategory":"Clothing, Apparel, & Fashions",
            "type":"Retail Goods"
        }
    ],
    "sg:phone":"+1 281 370 6115",
    "sg:postcode":"77379",
    "sg:province":"TX",
    "wof:name":"Nellys",
    "wof:placetype":"venue"
},
  "geometry": {"coordinates":[-95.549891,30.007668],"type":"Point"}
}