{
  "type": "Feature",
  "properties": {
    "iso:country":"US",
    "sg:address":"113 Oak St",
    "sg:city":"Sweetwater",
    "sg:classifiers":[
        {
            "category":"Shopping",
            "subcategory":"Used Merchandise",
            "type":"Retail Goods"
        }
    ],
    "sg:phone":"+1 325 236 8857",
    "sg:postcode":"79556",
    "sg:province":"TX",
    "sg:tags":[
        "antique"
    ],
    "wof:name":"Treasure Chest",
    "wof:placetype":"venue"
},
  "geometry": {"coordinates":[-100.408394,32.469952],"type":"Point"}
}