{
  "type": "Feature",
  "properties": {
    "iso:country":"US",
    "sg:address":"873 Walnut St",
    "sg:city":"Abilene",
    "sg:classifiers":[
        {
            "category":"Freight",
            "type":"Transportation"
        }
    ],
    "sg:phone":"+1 325 673 5321",
    "sg:postcode":"79601",
    "sg:province":"TX",
    "sg:tags":[
        "commercial",
        "storage"
    ],
    "wof:name":"A-Plus Self Storage",
    "wof:placetype":"venue"
},
  "geometry": {"coordinates":[-99.73069700000001,32.458844],"type":"Point"}
}