{
  "type": "Feature",
  "properties": {
    "iso:country":"US",
    "sg:address":"1802 Beltway 8",
    "sg:city":"Pasadena",
    "sg:classifiers":[
        {
            "category":"Health Services",
            "subcategory":"Chiropractor",
            "type":"Services"
        }
    ],
    "sg:phone":"+1 713 477 2555",
    "sg:postcode":"77503",
    "sg:province":"TX",
    "wof:name":"Baker Chiropractic Clinic",
    "wof:placetype":"venue"
},
  "geometry": {"coordinates":[-95.155115,29.683778],"type":"Point"}
}