{
  "type": "Feature",
  "properties": {
    "iso:country":"US",
    "sg:address":"411 W 7th St",
    "sg:city":"Fort Worth",
    "sg:classifiers":[
        {
            "category":"Real Estate",
            "subcategory":"Real Estate Agent",
            "type":"Services"
        }
    ],
    "sg:phone":"+1 817 885 8262",
    "sg:postcode":"76102",
    "sg:province":"TX",
    "wof:name":"Bedrock Co",
    "wof:placetype":"venue"
},
  "geometry": {"coordinates":[-97.33290599999999,32.751132],"type":"Point"}
}