{
  "type": "Feature",
  "properties": {
    "iso:country":"US",
    "sg:address":"8585 S Gessner Dr",
    "sg:city":"Houston",
    "sg:classifiers":[
        {
            "category":"Banks & Credit Unions",
            "subcategory":"Bank",
            "type":"Services"
        }
    ],
    "sg:phone":"+1 713 779 3388",
    "sg:postcode":"77074",
    "sg:province":"TX",
    "sg:tags":[
        "commercial"
    ],
    "wof:name":"United Central Bank",
    "wof:placetype":"venue"
},
  "geometry": {"coordinates":[-95.52942299999999,29.687195],"type":"Point"}
}