{
  "type": "Feature",
  "properties": {
    "iso:country":"US",
    "sg:address":"1212 Denton Dr",
    "sg:city":"Euless",
    "sg:classifiers":[
        {
            "category":"Government",
            "subcategory":"Post Office",
            "type":"Public Place"
        }
    ],
    "sg:phone":"+1 817 571 4440",
    "sg:postcode":"76039",
    "sg:province":"TX",
    "sg:tags":[
        "list",
        "mailing"
    ],
    "wof:name":"Trinary Info",
    "wof:placetype":"venue"
},
  "geometry": {"coordinates":[-97.087563,32.854062],"type":"Point"}
}