{
  "type": "Feature",
  "properties": {
    "iso:country":"US",
    "sg:address":"6811 Woodard Ave",
    "sg:city":"Dallas",
    "sg:classifiers":[
        {
            "category":"Professional",
            "subcategory":"Management & Consulting",
            "type":"Services"
        }
    ],
    "sg:phone":"+1 214 388 5105",
    "sg:postcode":"75227",
    "sg:province":"TX",
    "sg:tags":[
        "automotive"
    ],
    "wof:name":"C Racking Wrecker Service",
    "wof:placetype":"venue"
},
  "geometry": {"coordinates":[-96.701885,32.771846],"type":"Point"}
}