{
  "type": "Feature",
  "properties": {
    "iso:country":"US",
    "sg:address":"8510 New Laredo Hwy",
    "sg:city":"San Antonio",
    "sg:classifiers":[
        {
            "category":"Food & Beverages",
            "subcategory":"Groceries & Convenience Stores",
            "type":"Retail Goods"
        }
    ],
    "sg:phone":"+1 210 927 6441",
    "sg:postcode":"78211",
    "sg:province":"TX",
    "wof:name":"Padilla's Ice House",
    "wof:placetype":"venue"
},
  "geometry": {"coordinates":[-98.568787,29.351095],"type":"Point"}
}