{
  "type": "Feature",
  "properties": {
    "iso:country":"US",
    "sg:address":"809 Trailwood Dr",
    "sg:city":"Hurst",
    "sg:classifiers":[
        {
            "category":"Personal",
            "subcategory":"Barber",
            "type":"Services"
        }
    ],
    "sg:phone":"+1 817 282 8979",
    "sg:postcode":"76053",
    "sg:province":"TX",
    "sg:tags":[
        "shop"
    ],
    "wof:name":"Esquire Barber Shop",
    "wof:placetype":"venue"
},
  "geometry": {"coordinates":[-97.181529,32.825238],"type":"Point"}
}