{
  "type": "Feature",
  "properties": {
    "iso:country":"US",
    "sg:address":"2107 W Grand Ave",
    "sg:city":"Marshall",
    "sg:classifiers":[
        {
            "category":"Retail",
            "subcategory":"Car Wash",
            "type":"Services"
        }
    ],
    "sg:phone":"+1 903 935 1988",
    "sg:postcode":"75670",
    "sg:province":"TX",
    "sg:tags":[
        "carwash"
    ],
    "wof:name":"Lynn JS Detail Like New",
    "wof:placetype":"venue"
},
  "geometry": {"coordinates":[-94.386883,32.548577],"type":"Point"}
}