{
  "type": "Feature",
  "properties": {
    "iso:country":"US",
    "sg:address":"2106 Meadow Pkwy N",
    "sg:city":"League City",
    "sg:classifiers":[
        {
            "category":"Banks & Credit Unions",
            "subcategory":"Investment Brokerage",
            "type":"Services"
        }
    ],
    "sg:phone":"+1 281 635 6960",
    "sg:postcode":"77573",
    "sg:province":"TX",
    "sg:tags":[
        "professional",
        "consulting",
        "reporting",
        "grant"
    ],
    "wof:name":"Stellar Grants Inc",
    "wof:placetype":"venue"
},
  "geometry": {"coordinates":[-95.05501599999999,29.527295],"type":"Point"}
}