{
  "type": "Feature",
  "properties": {
    "iso:country":"US",
    "sg:address":"6831 State Hwy 6",
    "sg:city":"Houston",
    "sg:classifiers":[
        {
            "category":"Health Services",
            "subcategory":"Doctor",
            "type":"Services"
        }
    ],
    "sg:phone":"+1 281 861 7054",
    "sg:postcode":"77084",
    "sg:province":"TX",
    "sg:tags":[
        "dentist"
    ],
    "wof:name":"Castle Dental Ctr",
    "wof:placetype":"venue"
},
  "geometry": {"coordinates":[-95.64523,29.874101],"type":"Point"}
}