{
  "type": "Feature",
  "properties": {
    "iso:country":"US",
    "sg:address":"1118 Atlanta Ave",
    "sg:city":"Nederland",
    "sg:classifiers":[
        {
            "category":"Real Estate",
            "subcategory":"Real Estate Agent",
            "type":"Services"
        }
    ],
    "sg:phone":"+1 409 722 7537",
    "sg:postcode":"77627",
    "sg:province":"TX",
    "wof:name":"Rachel Lofton Real Estate",
    "wof:placetype":"venue"
},
  "geometry": {"coordinates":[-93.990109,29.975444],"type":"Point"}
}