{
  "type": "Feature",
  "properties": {
    "iso:country":"US",
    "sg:address":"307 Zimmerman Ave",
    "sg:city":"Bastrop",
    "sg:classifiers":[
        {
            "category":"Shopping",
            "type":"Retail Goods"
        }
    ],
    "sg:phone":"+1 512 303 1804",
    "sg:postcode":"78602",
    "sg:province":"TX",
    "sg:tags":[
        "merchandise"
    ],
    "wof:name":"Cheryl Weber",
    "wof:placetype":"venue"
},
  "geometry": {"coordinates":[-97.29925900000001,30.204251],"type":"Point"}
}