{
  "type": "Feature",
  "properties": {
    "iso:country":"US",
    "sg:address":"11200 Lakeline Mall Dr Ste B8",
    "sg:city":"Cedar Park",
    "sg:classifiers":[
        {
            "category":"Shopping",
            "subcategory":"Clothing, Apparel, & Fashions",
            "type":"Retail Goods"
        }
    ],
    "sg:phone":"+1 512 219 5877",
    "sg:postcode":"78613",
    "sg:province":"TX",
    "sg:tags":[
        "children's",
        "accessory",
        "clothing",
        "women's"
    ],
    "wof:name":"Limited Too",
    "wof:placetype":"venue"
},
  "geometry": {"coordinates":[-97.808018,30.469833],"type":"Point"}
}