{
  "type": "Feature",
  "properties": {
    "iso:country":"US",
    "sg:address":"208 Gale St",
    "sg:city":"Houston",
    "sg:classifiers":[
        {
            "category":"Personal",
            "subcategory":"Beauty Salon",
            "type":"Services"
        }
    ],
    "sg:phone":"+1 713 692 8660",
    "sg:postcode":"77009",
    "sg:province":"TX",
    "sg:tags":[
        "shop"
    ],
    "wof:name":"Jimmy Haircuts",
    "wof:placetype":"venue"
},
  "geometry": {"coordinates":[-95.36531600000001,29.805628],"type":"Point"}
}