{
  "type": "Feature",
  "properties": {
    "iso:country":"US",
    "sg:address":"12225 Greenville Ave",
    "sg:city":"Dallas",
    "sg:classifiers":[
        {
            "category":"Social Services",
            "type":"Services"
        }
    ],
    "sg:phone":"+1 214 575 4373",
    "sg:postcode":"75243",
    "sg:province":"TX",
    "sg:tags":[
        "agency",
        "adoption"
    ],
    "wof:name":"Living Legacy Adoption",
    "wof:placetype":"venue"
},
  "geometry": {"coordinates":[-96.74545500000001,32.913098],"type":"Point"}
}