{
  "type": "Feature",
  "properties": {
    "iso:country":"US",
    "sg:address":"5007 Fulton St",
    "sg:city":"Houston",
    "sg:classifiers":[
        {
            "category":"Farming",
            "subcategory":"Livestock Farm",
            "type":"Manufacturing & Wholesale Goods"
        }
    ],
    "sg:phone":"+1 713 691 3177",
    "sg:postcode":"77009",
    "sg:province":"TX",
    "sg:tags":[
        "ranch"
    ],
    "wof:name":"Amigo Ranch",
    "wof:placetype":"venue"
},
  "geometry": {"coordinates":[-95.368545,29.803338],"type":"Point"}
}