{
  "type": "Feature",
  "properties": {
    "iso:country":"US",
    "sg:address":"2800 S 5th St",
    "sg:city":"Garland",
    "sg:classifiers":[
        {
            "category":"Building & Trades",
            "subcategory":"Construction",
            "type":"Services"
        }
    ],
    "sg:phone":"+1 972 271 2091",
    "sg:postcode":"75041",
    "sg:province":"TX",
    "sg:tags":[
        "residential"
    ],
    "wof:name":"Hisaw & Associates",
    "wof:placetype":"venue"
},
  "geometry": {"coordinates":[-96.63386,32.882894],"type":"Point"}
}