{
  "type": "Feature",
  "properties": {
    "iso:country":"US",
    "sg:address":"8556 Katy Fwy",
    "sg:city":"Houston",
    "sg:classifiers":[
        {
            "category":"Professional",
            "type":"Services"
        }
    ],
    "sg:phone":"+1 713 467 5378",
    "sg:postcode":"77024",
    "sg:province":"TX",
    "sg:tags":[
        "establishment"
    ],
    "wof:name":"C S & Atpc Conference",
    "wof:placetype":"venue"
},
  "geometry": {"coordinates":[-95.49341200000001,29.784277],"type":"Point"}
}