{
  "type": "Feature",
  "properties": {
    "iso:country":"US",
    "sg:address":"200 E Dimmit St",
    "sg:city":"Crystal City",
    "sg:classifiers":[
        {
            "category":"Government",
            "subcategory":"Office",
            "type":"Public Place"
        }
    ],
    "sg:phone":"+1 830 374 2351",
    "sg:postcode":"78839",
    "sg:province":"TX",
    "sg:tags":[
        "county",
        "taxation"
    ],
    "wof:name":"Tax Office",
    "wof:placetype":"venue"
},
  "geometry": {"coordinates":[-99.826325,28.679218],"type":"Point"}
}