{
  "type": "Feature",
  "properties": {
    "iso:country":"US",
    "sg:address":"7555 US Hwy 87",
    "sg:city":"San Antonio",
    "sg:classifiers":[
        {
            "category":"Autos & Motor Vehicles",
            "subcategory":"Automobile Sales",
            "type":"Retail Goods"
        }
    ],
    "sg:phone":"+1 210 648 6822",
    "sg:postcode":"78263",
    "sg:province":"TX",
    "sg:tags":[
        "car",
        "used",
        "dealer"
    ],
    "wof:name":"Miller's Auto Sales",
    "wof:placetype":"venue"
},
  "geometry": {"coordinates":[-98.343034,29.386943],"type":"Point"}
}