{
  "type": "Feature",
  "properties": {
    "iso:country":"US",
    "sg:address":"2603 Wooldridge Dr",
    "sg:city":"Austin",
    "sg:classifiers":[
        {
            "category":"Shopping",
            "subcategory":"Florist",
            "type":"Retail Goods"
        }
    ],
    "sg:phone":"+1 512 478 8484",
    "sg:postcode":"78703",
    "sg:province":"TX",
    "wof:name":"Karcher S Flowers",
    "wof:placetype":"venue"
},
  "geometry": {"coordinates":[-97.750524,30.295473],"type":"Point"}
}