{
  "type": "Feature",
  "properties": {
    "iso:country":"US",
    "sg:address":"6020 Guadalupe St",
    "sg:city":"Houston",
    "sg:classifiers":[
        {
            "category":"Social Services",
            "subcategory":"Child Care",
            "type":"Services"
        }
    ],
    "sg:phone":"+1 281 442 4006",
    "sg:postcode":"77016",
    "sg:province":"TX",
    "sg:tags":[
        "day"
    ],
    "wof:name":"Pre Jean",
    "wof:placetype":"venue"
},
  "geometry": {"coordinates":[-95.299525,29.883388],"type":"Point"}
}