{
  "type": "Feature",
  "properties": {
    "iso:country":"US",
    "sg:address":"22999 US Hwy 59",
    "sg:city":"Humble",
    "sg:classifiers":[
        {
            "category":"Health Services",
            "subcategory":"Doctor",
            "type":"Services"
        }
    ],
    "sg:phone":"+1 281 348 3327",
    "sg:postcode":"77339",
    "sg:province":"TX",
    "sg:tags":[
        "medical"
    ],
    "wof:name":"Fleming James J MD Facs PA",
    "wof:placetype":"venue"
},
  "geometry": {"coordinates":[-95.254991,30.037036],"type":"Point"}
}