{
  "type": "Feature",
  "properties": {
    "iso:country":"US",
    "sg:address":"13397 Murphy Rd Ste B",
    "sg:city":"Stafford",
    "sg:classifiers":[
        {
            "category":"Autos & Motor Vehicles",
            "subcategory":"Automobile Sales",
            "type":"Retail Goods"
        },
        {
            "category":"Autos & Motor Vehicles",
            "subcategory":"Auto Supplies",
            "type":"Retail Goods"
        }
    ],
    "sg:phone":"+1 281 261 7586",
    "sg:postcode":"77477",
    "sg:province":"TX",
    "sg:tags":[
        "body",
        "shop",
        "car",
        "accessory",
        "equipment",
        "part",
        "new"
    ],
    "wof:name":"Dnt Auto Body Parts",
    "wof:placetype":"venue"
},
  "geometry": {"coordinates":[-95.564899,29.628381],"type":"Point"}
}