{
  "type": "Feature",
  "properties": {
    "iso:country":"US",
    "sg:address":"2710 N Brompton Dr",
    "sg:city":"Pearland",
    "sg:classifiers":[
        {
            "category":"Freight",
            "type":"Transportation"
        }
    ],
    "sg:phone":"+1 281 980 1728",
    "sg:postcode":"77584",
    "sg:province":"TX",
    "wof:name":"Ok Forwarding Co",
    "wof:placetype":"venue"
},
  "geometry": {"coordinates":[-95.379105,29.57478],"type":"Point"}
}