{
  "type": "Feature",
  "properties": {
    "iso:country":"US",
    "sg:address":"127 Fawn Trl",
    "sg:city":"Graham",
    "sg:classifiers":[
        {
            "category":"Personal",
            "subcategory":"Beauty Salon",
            "type":"Services"
        }
    ],
    "sg:phone":"+1 940 549 5513",
    "sg:postcode":"76450",
    "sg:province":"TX",
    "wof:name":"Color I Consultant",
    "wof:placetype":"venue"
},
  "geometry": {"coordinates":[-98.603516,33.114391],"type":"Point"}
}