{
  "type": "Feature",
  "properties": {
    "iso:country":"US",
    "sg:address":"5724 Ellison Ave",
    "sg:city":"Fort Worth",
    "sg:classifiers":[
        {
            "category":"Arts & Performance",
            "subcategory":"Theater",
            "type":"Entertainment"
        }
    ],
    "sg:phone":"+1 817 831 6370",
    "sg:postcode":"76117",
    "sg:province":"TX",
    "sg:tags":[
        "choir",
        "direction"
    ],
    "wof:name":"Anita E Martinez",
    "wof:placetype":"venue"
},
  "geometry": {"coordinates":[-97.257412,32.798161],"type":"Point"}
}