{
  "type": "Feature",
  "properties": {
    "iso:country":"US",
    "sg:address":"3124 S Eastman Rd",
    "sg:city":"Longview",
    "sg:classifiers":[
        {
            "category":"Shopping",
            "subcategory":"Music",
            "type":"Retail Goods"
        }
    ],
    "sg:phone":"+1 903 758 7116",
    "sg:postcode":"75602",
    "sg:province":"TX",
    "sg:tags":[
        "compact",
        "record",
        "disc",
        "tape"
    ],
    "wof:name":"Rev E TS Gospel Music Store",
    "wof:placetype":"venue"
},
  "geometry": {"coordinates":[-94.70725400000001,32.460405],"type":"Point"}
}