{
  "type": "Feature",
  "properties": {
    "iso:country":"US",
    "sg:address":"210 E Polk St",
    "sg:city":"Livingston",
    "sg:classifiers":[
        {
            "category":"Real Estate",
            "subcategory":"Surveying",
            "type":"Services"
        }
    ],
    "sg:phone":"+1 936 327 3816",
    "sg:postcode":"77351",
    "sg:province":"TX",
    "sg:tags":[
        "mapping"
    ],
    "wof:name":"Livingston Surveying & Mapping",
    "wof:placetype":"venue"
},
  "geometry": {"coordinates":[-94.931995,30.711894],"type":"Point"}
}