{
  "type": "Feature",
  "properties": {
    "iso:country":"US",
    "sg:address":"2206 Blalock Rd",
    "sg:city":"Houston",
    "sg:classifiers":[
        {
            "category":"Retail",
            "subcategory":"Repair Shop",
            "type":"Services"
        }
    ],
    "sg:phone":"+1 713 465 1934",
    "sg:postcode":"77080",
    "sg:province":"TX",
    "sg:tags":[
        "reupholstery",
        "furniture"
    ],
    "wof:name":"Galvez-Auto Trim & Furniture Upholstery",
    "wof:placetype":"venue"
},
  "geometry": {"coordinates":[-95.5243,29.811899],"type":"Point"}
}