{
  "type": "Feature",
  "properties": {
    "iso:country":"US",
    "sg:address":"3109 Executive Dr",
    "sg:city":"San Angelo",
    "sg:classifiers":[
        {
            "category":"Sports & Exercise",
            "subcategory":"Gym",
            "type":"Entertainment"
        }
    ],
    "sg:phone":"+1 325 947 0819",
    "sg:postcode":"76904",
    "sg:province":"TX",
    "sg:tags":[
        "club",
        "health"
    ],
    "wof:name":"Southwest Spa",
    "wof:placetype":"venue"
},
  "geometry": {"coordinates":[-100.46389499999999,31.422103],"type":"Point"}
}