{
  "type": "Feature",
  "properties": {
    "iso:country":"US",
    "sg:address":"509 S Main St",
    "sg:city":"Crandall",
    "sg:classifiers":[
        {
            "category":"Shopping",
            "type":"Retail Goods"
        }
    ],
    "sg:phone":"+1 972 427 9949",
    "sg:postcode":"75114",
    "sg:province":"TX",
    "sg:tags":[
        "merchandise"
    ],
    "wof:name":"Killer Ridez",
    "wof:placetype":"venue"
},
  "geometry": {"coordinates":[-96.454114,32.623556],"type":"Point"}
}