{
  "type": "Feature",
  "properties": {
    "iso:country":"US",
    "sg:address":"3703 Cromwell Dr",
    "sg:city":"Carrollton",
    "sg:classifiers":[
        {
            "category":"Manufacturing",
            "subcategory":"Glass & Minerals",
            "type":"Manufacturing & Wholesale Goods"
        }
    ],
    "sg:phone":"+1 972 492 9058",
    "sg:postcode":"75007",
    "sg:province":"TX",
    "sg:tags":[
        "glassware-wholesale",
        "manufacturer",
        "mfg"
    ],
    "wof:name":"Kc&P Enterprises",
    "wof:placetype":"venue"
},
  "geometry": {"coordinates":[-96.904701,33.011956],"type":"Point"}
}