{
  "type": "Feature",
  "properties": {
    "iso:country":"US",
    "sg:address":"500 E Mann Rd",
    "sg:city":"Laredo",
    "sg:classifiers":[
        {
            "category":"Health Services",
            "subcategory":"Hospital",
            "type":"Services"
        }
    ],
    "sg:phone":"+1 956 723 1131",
    "sg:postcode":"78041",
    "sg:province":"TX",
    "wof:name":"Doctor's Hospital Of Laredo",
    "wof:placetype":"venue"
},
  "geometry": {"coordinates":[-99.499955,27.558085],"type":"Point"}
}