{
  "type": "Feature",
  "properties": {
    "iso:country":"US",
    "sg:address":"1407 E Cesar Chavez St",
    "sg:city":"Austin",
    "sg:classifiers":[
        {
            "category":"Real Estate",
            "subcategory":"Real Estate Operator",
            "type":"Services"
        },
        {
            "category":"Building & Trades",
            "subcategory":"Construction",
            "type":"Services"
        },
        {
            "category":"Manufacturing",
            "subcategory":"Building Materials",
            "type":"Manufacturing & Wholesale Goods"
        }
    ],
    "sg:phone":"+1 512 478 8226",
    "sg:postcode":"78702",
    "sg:province":"TX",
    "sg:tags":[
        "coating",
        "contractor",
        "gunite",
        "exterior",
        "distributor",
        "grouting",
        "stucco",
        "manufacturer"
    ],
    "wof:name":"New Image Stucco",
    "wof:placetype":"venue"
},
  "geometry": {"coordinates":[-97.730481,30.259152],"type":"Point"}
}