{
  "type": "Feature",
  "properties": {
    "iso:country":"US",
    "sg:address":"6101 FM 1105",
    "sg:city":"Georgetown",
    "sg:classifiers":[
        {
            "category":"Education",
            "subcategory":"School",
            "type":"Public Place"
        }
    ],
    "sg:phone":"+1 512 863 5345",
    "sg:postcode":"78626",
    "sg:province":"TX",
    "wof:name":"Zion Lutheran School",
    "wof:placetype":"venue"
},
  "geometry": {"coordinates":[-97.600044,30.746443],"type":"Point"}
}