{
  "type": "Feature",
  "properties": {
    "iso:country":"US",
    "sg:address":"3821 Farnham St",
    "sg:city":"Houston",
    "sg:classifiers":[
        {
            "category":"Coffee & Tea",
            "type":"Food & Drink"
        }
    ],
    "sg:menulink":"http://www.allmenus.com/tx/houston/112967-starbucks-coffee/menu/",
    "sg:phone":"+1 713 524 3535",
    "sg:postcode":"77098",
    "sg:province":"TX",
    "sg:tags":[
        "american"
    ],
    "wof:name":"Starbucks Coffee",
    "wof:placetype":"venue"
},
  "geometry": {"coordinates":[-95.412244,29.732386],"type":"Point"}
}