{
  "type": "Feature",
  "properties": {
    "iso:country":"US",
    "sg:address":"16118 Shadybank Dr",
    "sg:city":"Dallas",
    "sg:classifiers":[
        {
            "category":"Museum",
            "type":"Entertainment"
        }
    ],
    "sg:phone":"+1 972 503 5662",
    "sg:postcode":"75248",
    "sg:province":"TX",
    "sg:tags":[
        "gallery",
        "merchandise"
    ],
    "wof:name":"Adani Gallery Framing",
    "wof:placetype":"venue"
},
  "geometry": {"coordinates":[-96.796644,32.971595],"type":"Point"}
}