{
  "type": "Feature",
  "properties": {
    "iso:country":"US",
    "sg:address":"510 Barbers Hill Rd",
    "sg:city":"Highlands",
    "sg:classifiers":[
        {
            "category":"Building & Trades",
            "subcategory":"Construction",
            "type":"Services"
        }
    ],
    "sg:phone":"+1 281 843 2526",
    "sg:postcode":"77562",
    "sg:province":"TX",
    "wof:name":"Rogers Pipeline Services Inc",
    "wof:placetype":"venue"
},
  "geometry": {"coordinates":[-95.04974,29.841649],"type":"Point"}
}