{
  "type": "Feature",
  "properties": {
    "iso:country":"US",
    "sg:address":"459 Paloma St",
    "sg:city":"Corpus Christi",
    "sg:classifiers":[
        {
            "category":"Professional",
            "subcategory":"Lawyer & Legal Services",
            "type":"Services"
        }
    ],
    "sg:phone":"+1 361 881 9800",
    "sg:postcode":"78412",
    "sg:province":"TX",
    "sg:tags":[
        "attorney"
    ],
    "wof:name":"Jeanne Chastain PC",
    "wof:placetype":"venue"
},
  "geometry": {"coordinates":[-97.359318,27.724623],"type":"Point"}
}