{
  "type": "Feature",
  "properties": {
    "iso:country":"US",
    "sg:address":"5211 N Shepherd Dr",
    "sg:city":"Houston",
    "sg:classifiers":[
        {
            "category":"Shopping",
            "subcategory":"Used Merchandise",
            "type":"Retail Goods"
        }
    ],
    "sg:phone":"+1 713 694 7070",
    "sg:postcode":"77091",
    "sg:province":"TX",
    "wof:name":"E & R Resale Thrift Store",
    "wof:placetype":"venue"
},
  "geometry": {"coordinates":[-95.411024,29.843521],"type":"Point"}
}