{
  "type": "Feature",
  "properties": {
    "iso:country":"US",
    "sg:address":"205 E Toronto Ave",
    "sg:city":"Mcallen",
    "sg:classifiers":[
        {
            "category":"Health Services",
            "subcategory":"Doctor",
            "type":"Services"
        }
    ],
    "sg:phone":"+1 956 687 6155",
    "sg:postcode":"78503",
    "sg:province":"TX",
    "sg:tags":[
        "physician",
        "family",
        "practice",
        "surgeons",
        "medicine",
        "surgeon"
    ],
    "wof:name":"Family Medical Center",
    "wof:placetype":"venue"
},
  "geometry": {"coordinates":[-98.221334,26.183336],"type":"Point"}
}