{
  "type": "Feature",
  "properties": {
    "iso:country":"US",
    "sg:address":"3901 Twin Falls St",
    "sg:city":"Irving",
    "sg:classifiers":[
        {
            "category":"Organizations",
            "subcategory":"Religious Organization",
            "type":"Services"
        }
    ],
    "sg:phone":"+1 972 255 4650",
    "sg:postcode":"75062",
    "sg:province":"TX",
    "wof:name":"Joyce Temple Melva",
    "wof:placetype":"venue"
},
  "geometry": {"coordinates":[-97.003315,32.854188],"type":"Point"}
}