{
  "type": "Feature",
  "properties": {
    "iso:country":"US",
    "sg:address":"850 N Dorothy Dr",
    "sg:city":"Richardson",
    "sg:classifiers":[
        {
            "category":"Personal",
            "type":"Services"
        }
    ],
    "sg:phone":"+1 972 690 1115",
    "sg:postcode":"75081",
    "sg:province":"TX",
    "sg:tags":[
        "club",
        "consumer",
        "buying"
    ],
    "wof:name":"Troutman Management Inc",
    "wof:placetype":"venue"
},
  "geometry": {"coordinates":[-96.722461,32.959138],"type":"Point"}
}