{
  "type": "Feature",
  "properties": {
    "iso:country":"US",
    "sg:address":"4108 Clay Ave",
    "sg:city":"Fort Worth",
    "sg:classifiers":[
        {
            "category":"Building & Trades",
            "subcategory":"Plumbing",
            "type":"Services"
        }
    ],
    "sg:phone":"+1 817 485 7575",
    "sg:postcode":"76117",
    "sg:province":"TX",
    "sg:tags":[
        "contractor"
    ],
    "wof:name":"Truman Dansby",
    "wof:placetype":"venue"
},
  "geometry": {"coordinates":[-97.284773,32.829074],"type":"Point"}
}