{
  "type": "Feature",
  "properties": {
    "iso:country":"US",
    "sg:address":"902 N San Jacinto St",
    "sg:city":"Conroe",
    "sg:classifiers":[
        {
            "category":"Retail",
            "subcategory":"Portrait Studio",
            "type":"Services"
        }
    ],
    "sg:phone":"+1 936 756 3818",
    "sg:postcode":"77301",
    "sg:province":"TX",
    "sg:tags":[
        "photo"
    ],
    "wof:name":"Studio 902",
    "wof:placetype":"venue"
},
  "geometry": {"coordinates":[-95.459052,30.31756],"type":"Point"}
}