{
  "type": "Feature",
  "properties": {
    "iso:country":"US",
    "sg:address":"751 Apple Ln",
    "sg:city":"Midlothian",
    "sg:classifiers":[
        {
            "category":"Farming",
            "subcategory":"Farm & Veterinary Services",
            "type":"Manufacturing & Wholesale Goods"
        }
    ],
    "sg:phone":"+1 972 723 8245",
    "sg:postcode":"76065",
    "sg:province":"TX",
    "sg:tags":[
        "livestock"
    ],
    "wof:name":"Mountain Peak Angus",
    "wof:placetype":"venue"
},
  "geometry": {"coordinates":[-97.0013,32.441726],"type":"Point"}
}