{
  "type": "Feature",
  "properties": {
    "iso:country":"US",
    "sg:address":"630 S Corinth St",
    "sg:city":"Dallas",
    "sg:classifiers":[
        {
            "category":"Organizations",
            "subcategory":"Religious Organization",
            "type":"Services"
        }
    ],
    "sg:phone":"+1 214 942 4302",
    "sg:postcode":"75203",
    "sg:province":"TX",
    "wof:name":"Iglesia El Salvador",
    "wof:placetype":"venue"
},
  "geometry": {"coordinates":[-96.79844199999999,32.741288],"type":"Point"}
}