{
  "type": "Feature",
  "properties": {
    "iso:country":"US",
    "sg:address":"14526 Old Katy Rd",
    "sg:city":"Houston",
    "sg:classifiers":[
        {
            "category":"Real Estate",
            "subcategory":"Real Estate Services",
            "type":"Services"
        }
    ],
    "sg:phone":"+1 281 493 9336",
    "sg:postcode":"77079",
    "sg:province":"TX",
    "sg:tags":[
        "company",
        "title"
    ],
    "wof:name":"First Southwestern Title Co",
    "wof:placetype":"venue"
},
  "geometry": {"coordinates":[-95.643657,29.786026],"type":"Point"}
}