{
  "type": "Feature",
  "properties": {
    "iso:country":"US",
    "sg:address":"202 Vinewood Ln",
    "sg:city":"Longview",
    "sg:classifiers":[
        {
            "category":"Banks & Credit Unions",
            "subcategory":"Financial Services",
            "type":"Services"
        }
    ],
    "sg:phone":"+1 903 759 5653",
    "sg:postcode":"75604",
    "sg:province":"TX",
    "sg:tags":[
        "company",
        "holding"
    ],
    "wof:name":"McDaniel Holdings LLC",
    "wof:placetype":"venue"
},
  "geometry": {"coordinates":[-94.797864,32.519054],"type":"Point"}
}