{
  "type": "Feature",
  "properties": {
    "iso:country":"US",
    "sg:address":"122 S Main St",
    "sg:city":"Weatherford",
    "sg:classifiers":[
        {
            "category":"Building & Trades",
            "subcategory":"Construction",
            "type":"Services"
        }
    ],
    "sg:phone":"+1 817 594 8122",
    "sg:postcode":"76086",
    "sg:province":"TX",
    "sg:tags":[
        "installs",
        "retail",
        "floor",
        "covering"
    ],
    "wof:name":"Carpet Place",
    "wof:placetype":"venue"
},
  "geometry": {"coordinates":[-97.797388,32.758133],"type":"Point"}
}