{
  "type": "Feature",
  "properties": {
    "iso:country":"US",
    "sg:address":"305 S Andrews Dr",
    "sg:city":"Waco",
    "sg:classifiers":[
        {
            "category":"Health Services",
            "subcategory":"Nursing And Care Facility",
            "type":"Services"
        }
    ],
    "sg:phone":"+1 254 662 4010",
    "sg:postcode":"76706",
    "sg:province":"TX",
    "sg:tags":[
        "skilled"
    ],
    "wof:name":"Robinson Nursing & Dev Ctr",
    "wof:placetype":"venue"
},
  "geometry": {"coordinates":[-97.11230399999999,31.468868],"type":"Point"}
}