{
  "type": "Feature",
  "properties": {
    "iso:country":"US",
    "sg:address":"8238 Summer Side Dr",
    "sg:city":"Austin",
    "sg:classifiers":[
        {
            "category":"Professional",
            "type":"Services"
        }
    ],
    "sg:phone":"+1 512 602 3206",
    "sg:postcode":"78759",
    "sg:province":"TX",
    "wof:name":"Mike Zent",
    "wof:placetype":"venue"
},
  "geometry": {"coordinates":[-97.74552300000001,30.371147],"type":"Point"}
}