{
  "type": "Feature",
  "properties": {
    "iso:country":"US",
    "sg:address":"5106 Cedar St",
    "sg:city":"Bellaire",
    "sg:classifiers":[
        {
            "category":"Personal",
            "subcategory":"Barber",
            "type":"Services"
        }
    ],
    "sg:phone":"+1 713 665 9203",
    "sg:postcode":"77401",
    "sg:province":"TX",
    "sg:tags":[
        "shop"
    ],
    "wof:name":"Frenchy's Barber Shop",
    "wof:placetype":"venue"
},
  "geometry": {"coordinates":[-95.468654,29.707063],"type":"Point"}
}