{
  "type": "Feature",
  "properties": {
    "iso:country":"US",
    "sg:address":"6323 Camp Bowie Blvd",
    "sg:city":"Fort Worth",
    "sg:classifiers":[
        {
            "category":"Shopping",
            "subcategory":"Musical Instruments",
            "type":"Retail Goods"
        }
    ],
    "sg:phone":"+1 817 377 3379",
    "sg:postcode":"76116",
    "sg:province":"TX",
    "sg:tags":[
        "piano"
    ],
    "wof:name":"Steinway Hall Tarrant Co",
    "wof:placetype":"venue"
},
  "geometry": {"coordinates":[-97.418998,32.727196],"type":"Point"}
}