{
  "type": "Feature",
  "properties": {
    "iso:country":"US",
    "sg:address":"600 S Velasco St",
    "sg:city":"Angleton",
    "sg:classifiers":[
        {
            "category":"Building & Trades",
            "subcategory":"Plumbing",
            "type":"Services"
        }
    ],
    "sg:phone":"+1 979 849 9665",
    "sg:postcode":"77515",
    "sg:province":"TX",
    "sg:tags":[
        "plumbing",
        "contractor"
    ],
    "wof:name":"W & T Plumbing Inc",
    "wof:placetype":"venue"
},
  "geometry": {"coordinates":[-95.43145800000001,29.159416],"type":"Point"}
}