{
  "type": "Feature",
  "properties": {
    "iso:country":"US",
    "sg:address":"2700 E Griffin Pkwy",
    "sg:city":"Mission",
    "sg:classifiers":[
        {
            "category":"Social Services",
            "subcategory":"Child Care",
            "type":"Services"
        },
        {
            "category":"Social Services",
            "type":"Services"
        }
    ],
    "sg:phone":"+1 956 664 2663",
    "sg:postcode":"78572",
    "sg:province":"TX",
    "sg:tags":[
        "center",
        "day"
    ],
    "wof:name":"Happy Valley II Adult Day Care",
    "wof:placetype":"venue"
},
  "geometry": {"coordinates":[-98.275958,26.223039],"type":"Point"}
}