{
  "type": "Feature",
  "properties": {
    "iso:country":"US",
    "sg:address":"2523 Hudspeth Ave",
    "sg:city":"Dallas",
    "sg:classifiers":[
        {
            "category":"Professional",
            "type":"Services"
        }
    ],
    "sg:phone":"+1 214 375 7120",
    "sg:postcode":"75216",
    "sg:province":"TX",
    "sg:tags":[
        "establishment"
    ],
    "wof:name":"Price Beal",
    "wof:placetype":"venue"
},
  "geometry": {"coordinates":[-96.788366,32.707355],"type":"Point"}
}