{
  "type": "Feature",
  "properties": {
    "iso:country":"US",
    "sg:address":"10323 Lake Creek Pkwy",
    "sg:city":"Austin",
    "sg:classifiers":[
        {
            "category":"Professional",
            "type":"Services"
        }
    ],
    "sg:phone":"+1 512 401 0687",
    "sg:postcode":"78750",
    "sg:province":"TX",
    "sg:tags":[
        "establishment"
    ],
    "wof:name":"Affiniscape Inc",
    "wof:placetype":"venue"
},
  "geometry": {"coordinates":[-97.79756399999999,30.460431],"type":"Point"}
}