{
  "type": "Feature",
  "properties": {
    "iso:country":"US",
    "sg:address":"635 W Broad St",
    "sg:city":"Mineola",
    "sg:classifiers":[
        {
            "category":"Shopping",
            "subcategory":"Antiques",
            "type":"Retail Goods"
        }
    ],
    "sg:phone":"+1 903 569 0951",
    "sg:postcode":"75773",
    "sg:province":"TX",
    "sg:website":"http://www.bargainbarn.com",
    "wof:name":"Bargain Barn Antiques",
    "wof:placetype":"venue"
},
  "geometry": {"coordinates":[-95.49445,32.66462],"type":"Point"}
}