{
  "type": "Feature",
  "properties": {
    "iso:country":"US",
    "sg:address":"3135 Executive Dr",
    "sg:city":"San Angelo",
    "sg:classifiers":[
        {
            "category":"Social Services",
            "subcategory":"Adult Care",
            "type":"Services"
        }
    ],
    "sg:phone":"+1 254 947 3152",
    "sg:postcode":"76904",
    "sg:province":"TX",
    "sg:tags":[
        "residential",
        "religious",
        "organization"
    ],
    "wof:name":"Lighthouse Family Network Inc",
    "wof:placetype":"venue"
},
  "geometry": {"coordinates":[-100.46279800000001,31.423141],"type":"Point"}
}