{
  "type": "Feature",
  "properties": {
    "iso:country":"US",
    "sg:address":"3118 Fm 2259",
    "sg:city":"Nacogdoches",
    "sg:classifiers":[
        {
            "category":"Retail",
            "subcategory":"Auto Repair",
            "type":"Services"
        }
    ],
    "sg:phone":"+1 936 462 1925",
    "sg:postcode":"75961",
    "sg:province":"TX",
    "sg:tags":[
        "body",
        "painting",
        "repairing",
        "automobile"
    ],
    "wof:name":"Dent Solutions",
    "wof:placetype":"venue"
},
  "geometry": {"coordinates":[-94.62723200000001,31.570588],"type":"Point"}
}