{
  "type": "Feature",
  "properties": {
    "iso:country":"US",
    "sg:address":"11735 Kilkirk Ln",
    "sg:city":"Dallas",
    "sg:classifiers":[
        {
            "category":"Building & Trades",
            "subcategory":"Construction",
            "type":"Services"
        }
    ],
    "sg:phone":"+1 972 279 0747",
    "sg:postcode":"75228",
    "sg:province":"TX",
    "sg:tags":[
        "contractor"
    ],
    "wof:name":"Jvc Remodeling Repair",
    "wof:placetype":"venue"
},
  "geometry": {"coordinates":[-96.66316399999999,32.850868],"type":"Point"}
}