{
  "type": "Feature",
  "properties": {
    "iso:country":"US",
    "sg:address":"601 W Young St",
    "sg:city":"Llano",
    "sg:classifiers":[
        {
            "category":"Food & Beverages",
            "subcategory":"Groceries & Convenience Stores",
            "type":"Retail Goods"
        }
    ],
    "sg:phone":"+1 325 247 4711",
    "sg:postcode":"78643",
    "sg:province":"TX",
    "wof:name":"Payless",
    "wof:placetype":"venue"
},
  "geometry": {"coordinates":[-98.68274599999999,30.759532],"type":"Point"}
}