{
  "type": "Feature",
  "properties": {
    "iso:country":"US",
    "sg:address":"1210 Autrey St",
    "sg:city":"Houston",
    "sg:classifiers":[
        {
            "category":"Social Services",
            "subcategory":"Child Care",
            "type":"Services"
        }
    ],
    "sg:phone":"+1 713 529 0999",
    "sg:postcode":"77006",
    "sg:province":"TX",
    "wof:name":"Catholic Charities Daycare",
    "wof:placetype":"venue"
},
  "geometry": {"coordinates":[-95.39369000000001,29.730933],"type":"Point"}
}