{
  "type": "Feature",
  "properties": {
    "iso:country":"US",
    "sg:address":"501 E Byron Nelson Blvd",
    "sg:city":"Roanoke",
    "sg:classifiers":[
        {
            "category":"Restaurant",
            "type":"Food & Drink"
        }
    ],
    "sg:phone":"+1 817 491 9000",
    "sg:postcode":"76262",
    "sg:province":"TX",
    "sg:tags":[
        "french",
        "italian"
    ],
    "wof:name":"Italian Bistro",
    "wof:placetype":"venue"
},
  "geometry": {"coordinates":[-97.22235999999999,33.002879],"type":"Point"}
}