{
  "type": "Feature",
  "properties": {
    "iso:country":"US",
    "sg:address":"2145 N Hobart St",
    "sg:city":"Pampa",
    "sg:classifiers":[
        {
            "category":"Utilities",
            "subcategory":"Mobile Phone",
            "type":"Services"
        }
    ],
    "sg:phone":"+1 806 669 1551",
    "sg:postcode":"79065",
    "sg:province":"TX",
    "sg:tags":[
        "communication",
        "radiotelephone"
    ],
    "wof:name":"Communication Connection",
    "wof:placetype":"venue"
},
  "geometry": {"coordinates":[-100.972014,35.559693],"type":"Point"}
}