{
  "type": "Feature",
  "properties": {
    "iso:country":"US",
    "sg:address":"911 N Walnut Creek Dr",
    "sg:city":"Mansfield",
    "sg:classifiers":[
        {
            "category":"Retail",
            "subcategory":"Veterinary Services",
            "type":"Services"
        }
    ],
    "sg:phone":"+1 817 473 1168",
    "sg:postcode":"76063",
    "sg:province":"TX",
    "wof:name":"Campbell Catherine",
    "wof:placetype":"venue"
},
  "geometry": {"coordinates":[-97.13258500000001,32.578586],"type":"Point"}
}