{
  "type": "Feature",
  "properties": {
    "iso:country":"US",
    "sg:address":"197 W Sandy Lake Rd",
    "sg:city":"Coppell",
    "sg:classifiers":[
        {
            "category":"Shopping",
            "subcategory":"Hobbies, Toys, & Games",
            "type":"Retail Goods"
        }
    ],
    "sg:phone":"+1 972 304 6240",
    "sg:postcode":"75019",
    "sg:province":"TX",
    "sg:tags":[
        "craft",
        "supply"
    ],
    "wof:name":"Micheals Stores",
    "wof:placetype":"venue"
},
  "geometry": {"coordinates":[-96.994817,32.969261],"type":"Point"}
}