{
  "type": "Feature",
  "properties": {
    "iso:country":"US",
    "sg:address":"14711 Main St",
    "sg:city":"Houston",
    "sg:classifiers":[
        {
            "category":"Autos & Motor Vehicles",
            "subcategory":"Fuel & Gas Station",
            "type":"Retail Goods"
        },
        {
            "category":"Food & Beverages",
            "subcategory":"Groceries & Convenience Stores",
            "type":"Retail Goods"
        }
    ],
    "sg:phone":"+1 713 283 6100",
    "sg:postcode":"77035",
    "sg:province":"TX",
    "sg:website":"www.texaco.com",
    "wof:name":"Texaco",
    "wof:placetype":"venue"
},
  "geometry": {"coordinates":[-95.507637,29.630141],"type":"Point"}
}