{
  "type": "Feature",
  "properties": {
    "iso:country":"US",
    "sg:address":"1216 N 5th St",
    "sg:city":"Mcallen",
    "sg:classifiers":[
        {
            "category":"Professional",
            "subcategory":"Business Services",
            "type":"Services"
        }
    ],
    "sg:phone":"+1 956 682 7956",
    "sg:postcode":"78501",
    "sg:province":"TX",
    "wof:name":"Ivana Enterprises",
    "wof:placetype":"venue"
},
  "geometry": {"coordinates":[-98.22236100000001,26.215102],"type":"Point"}
}