{
  "type": "Feature",
  "properties": {
    "iso:country":"US",
    "sg:address":"4125 E Belknap St",
    "sg:city":"Haltom City",
    "sg:classifiers":[
        {
            "category":"Insurance",
            "subcategory":"Insurance Agent",
            "type":"Services"
        }
    ],
    "sg:phone":"+1 817 838 4204",
    "sg:postcode":"76111",
    "sg:province":"TX",
    "wof:name":"Farmers Insurance Group",
    "wof:placetype":"venue"
},
  "geometry": {"coordinates":[-97.286885,32.783749],"type":"Point"}
}