{
  "type": "Feature",
  "properties": {
    "iso:country":"US",
    "sg:address":"8995 FM 3369",
    "sg:city":"Temple",
    "sg:classifiers":[
        {
            "category":"Organizations",
            "subcategory":"Religious Organization",
            "type":"Services"
        }
    ],
    "sg:phone":"+1 254 583 4438",
    "sg:postcode":"76501",
    "sg:province":"TX",
    "sg:tags":[
        "church"
    ],
    "wof:name":"Salem Lutheran Church",
    "wof:placetype":"venue"
},
  "geometry": {"coordinates":[-97.22547,31.122456],"type":"Point"}
}