{
  "type": "Feature",
  "properties": {
    "iso:country":"US",
    "sg:address":"602 E Goode St",
    "sg:city":"Quitman",
    "sg:classifiers":[
        {
            "category":"Building & Trades",
            "subcategory":"Equipment Rental",
            "type":"Services"
        }
    ],
    "sg:phone":"+1 903 763 4465",
    "sg:postcode":"75783",
    "sg:province":"TX",
    "sg:tags":[
        "yard"
    ],
    "wof:name":"Lake Area Rentals",
    "wof:placetype":"venue"
},
  "geometry": {"coordinates":[-95.44564699999999,32.795878],"type":"Point"}
}