{
  "type": "Feature",
  "properties": {
    "iso:country":"US",
    "sg:address":"1225 N Ave E",
    "sg:city":"Shiner",
    "sg:classifiers":[
        {
            "category":"Insurance",
            "subcategory":"Insurance Agent",
            "type":"Services"
        }
    ],
    "sg:phone":"+1 361 594 3400",
    "sg:postcode":"77984",
    "sg:province":"TX",
    "wof:name":"Farmers Insurance",
    "wof:placetype":"venue"
},
  "geometry": {"coordinates":[-97.177561,29.435076],"type":"Point"}
}