{
  "type": "Feature",
  "properties": {
    "iso:country":"US",
    "sg:address":"11328 S Post Oak Rd",
    "sg:city":"Houston",
    "sg:classifiers":[
        {
            "category":"Building & Trades",
            "subcategory":"Construction",
            "type":"Services"
        }
    ],
    "sg:phone":"+1 713 726 9144",
    "sg:postcode":"77035",
    "sg:province":"TX",
    "sg:tags":[
        "hanging",
        "contractor"
    ],
    "wof:name":"Painters Choice LLC",
    "wof:placetype":"venue"
},
  "geometry": {"coordinates":[-95.463911,29.651716],"type":"Point"}
}