{
  "type": "Feature",
  "properties": {
    "iso:country":"US",
    "sg:address":"1600 W Groesbeck St",
    "sg:city":"Stephenville",
    "sg:classifiers":[
        {
            "category":"Retail",
            "subcategory":"Laundry & Dry Cleaning",
            "type":"Services"
        }
    ],
    "sg:phone":"+1 254 965 5003",
    "sg:postcode":"76401",
    "sg:province":"TX",
    "sg:tags":[
        "cleaner",
        "rug",
        "carpet"
    ],
    "wof:name":"Chem-Dry",
    "wof:placetype":"venue"
},
  "geometry": {"coordinates":[-98.21431699999999,32.207642],"type":"Point"}
}