{
  "type": "Feature",
  "properties": {
    "iso:country":"US",
    "sg:address":"6505 State Hwy 6",
    "sg:city":"Houston",
    "sg:classifiers":[
        {
            "category":"Shopping",
            "subcategory":"Clothing, Apparel, & Fashions",
            "type":"Retail Goods"
        }
    ],
    "sg:phone":"+1 832 593 9988",
    "sg:postcode":"77084",
    "sg:province":"TX",
    "sg:tags":[
        "wear"
    ],
    "wof:name":"Giggles Childrens Boutique",
    "wof:placetype":"venue"
},
  "geometry": {"coordinates":[-95.64528900000001,29.872806],"type":"Point"}
}