{
  "type": "Feature",
  "properties": {
    "iso:country":"US",
    "sg:address":"923 US Hwy 77X Bus",
    "sg:city":"Harlingen",
    "sg:classifiers":[
        {
            "category":"Health Services",
            "subcategory":"Optometrist",
            "type":"Services"
        }
    ],
    "sg:phone":"+1 956 428 2103",
    "sg:postcode":"78550",
    "sg:province":"TX",
    "wof:name":"Optical Reflections",
    "wof:placetype":"venue"
},
  "geometry": {"coordinates":[-97.682097,26.201147],"type":"Point"}
}