{
  "type": "Feature",
  "properties": {
    "iso:country":"US",
    "sg:address":"9852 Goby St",
    "sg:city":"El Paso",
    "sg:classifiers":[
        {
            "category":"Professional",
            "subcategory":"Accounting & Tax Preparation",
            "type":"Services"
        }
    ],
    "sg:phone":"+1 915 757 2078",
    "sg:postcode":"79924",
    "sg:province":"TX",
    "wof:name":"Jeans Tax & Bookkeeping",
    "wof:placetype":"venue"
},
  "geometry": {"coordinates":[-106.39913799999999,31.896609],"type":"Point"}
}