{
  "type": "Feature",
  "properties": {
    "iso:country":"US",
    "sg:address":"2836 Bent Oaks Dr",
    "sg:city":"Burleson",
    "sg:classifiers":[
        {
            "category":"Real Estate",
            "subcategory":"Real Estate Services",
            "type":"Services"
        },
        {
            "category":"Real Estate",
            "subcategory":"Real Estate Agent",
            "type":"Services"
        }
    ],
    "sg:phone":"+1 817 295 3400",
    "sg:postcode":"76028",
    "sg:province":"TX",
    "sg:tags":[
        "management"
    ],
    "wof:name":"Carol Clayton",
    "wof:placetype":"venue"
},
  "geometry": {"coordinates":[-97.26554899999999,32.542801],"type":"Point"}
}