{
  "type": "Feature",
  "properties": {
    "iso:country":"US",
    "sg:address":"1112 NE Loop 289",
    "sg:city":"Lubbock",
    "sg:classifiers":[
        {
            "category":"Manufacturing",
            "subcategory":"Tools & Machinery",
            "type":"Manufacturing & Wholesale Goods"
        },
        {
            "category":"Building & Trades",
            "subcategory":"Equipment Rental",
            "type":"Services"
        }
    ],
    "sg:phone":"+1 806 762 0609",
    "sg:postcode":"79403",
    "sg:province":"TX",
    "sg:tags":[
        "construction",
        "contractors'"
    ],
    "sg:website":"http://www.vermeertexas.com",
    "wof:name":"Vermeer Sales & Service",
    "wof:placetype":"venue"
},
  "geometry": {"coordinates":[-101.82347900000001,33.616257],"type":"Point"}
}