{
  "type": "Feature",
  "properties": {
    "iso:country":"US",
    "sg:address":"21471 Coyote Trl",
    "sg:city":"Leander",
    "sg:classifiers":[
        {
            "category":"Autos & Motor Vehicles",
            "subcategory":"Auto Supplies",
            "type":"Retail Goods"
        }
    ],
    "sg:phone":"+1 512 267 1055",
    "sg:postcode":"78645",
    "sg:province":"TX",
    "wof:name":"Highrevracingcom",
    "wof:placetype":"venue"
},
  "geometry": {"coordinates":[-97.989464,30.473853],"type":"Point"}
}