{
  "type": "Feature",
  "properties": {
    "iso:country":"US",
    "sg:address":"3801 Ram Blvd",
    "sg:city":"Mineral Wells",
    "sg:classifiers":[
        {
            "category":"Education",
            "subcategory":"School",
            "type":"Public Place"
        }
    ],
    "sg:phone":"+1 940 325 6432",
    "sg:postcode":"76067",
    "sg:province":"TX",
    "wof:name":"Mineral Wells School District",
    "wof:placetype":"venue"
},
  "geometry": {"coordinates":[-98.08056999999999,32.813755],"type":"Point"}
}