{
  "type": "Feature",
  "properties": {
    "iso:country":"US",
    "sg:address":"6413 Blacktree Dr",
    "sg:city":"Plano",
    "sg:classifiers":[
        {
            "category":"Organizations",
            "subcategory":"Labor Organization",
            "type":"Services"
        }
    ],
    "sg:phone":"+1 972 403 9036",
    "sg:postcode":"75093",
    "sg:province":"TX",
    "wof:name":"Center Partners Lc",
    "wof:placetype":"venue"
},
  "geometry": {"coordinates":[-96.84111799999999,33.048948],"type":"Point"}
}