{
  "type": "Feature",
  "properties": {
    "iso:country":"US",
    "sg:address":"15297 Fenwick Ln",
    "sg:city":"Conroe",
    "sg:classifiers":[
        {
            "category":"Building & Trades",
            "subcategory":"Construction",
            "type":"Services"
        }
    ],
    "sg:phone":"+1 281 363 3826",
    "sg:postcode":"77384",
    "sg:province":"TX",
    "sg:tags":[
        "general",
        "contractor"
    ],
    "wof:name":"RAMM Construction",
    "wof:placetype":"venue"
},
  "geometry": {"coordinates":[-95.50465,30.234396],"type":"Point"}
}