{
  "type": "Feature",
  "properties": {
    "iso:country":"US",
    "sg:address":"412 Grace St",
    "sg:city":"San Angelo",
    "sg:classifiers":[
        {
            "category":"Manufacturing",
            "subcategory":"Wood Products",
            "type":"Manufacturing & Wholesale Goods"
        }
    ],
    "sg:phone":"+1 325 659 5031",
    "sg:postcode":"76901",
    "sg:province":"TX",
    "sg:tags":[
        "mfg"
    ],
    "wof:name":"Country Keepsakes",
    "wof:placetype":"venue"
},
  "geometry": {"coordinates":[-100.45761,31.450298],"type":"Point"}
}