{
  "type": "Feature",
  "properties": {
    "iso:country":"US",
    "sg:address":"3417 Brown Trl",
    "sg:city":"Bedford",
    "sg:classifiers":[
        {
            "category":"Transit Center",
            "subcategory":"Freight",
            "type":"Transportation"
        },
        {
            "category":"Freight",
            "type":"Transportation"
        }
    ],
    "sg:phone":"+1 817 427 3662",
    "sg:postcode":"76021",
    "sg:province":"TX",
    "sg:tags":[
        "local",
        "trucking-motor",
        "trucking"
    ],
    "wof:name":"John Park Trucking",
    "wof:placetype":"venue"
},
  "geometry": {"coordinates":[-97.159897,32.858471],"type":"Point"}
}