{
  "type": "Feature",
  "properties": {
    "iso:country":"US",
    "sg:address":"4212 Stagecoach Trl",
    "sg:city":"Temple",
    "sg:classifiers":[
        {
            "category":"Organizations",
            "subcategory":"Religious Organization",
            "type":"Services"
        }
    ],
    "sg:phone":"+1 254 773 5547",
    "sg:postcode":"76502",
    "sg:province":"TX",
    "wof:name":"Music Club of Temple",
    "wof:placetype":"venue"
},
  "geometry": {"coordinates":[-97.381364,31.061622],"type":"Point"}
}