{
  "type": "Feature",
  "properties": {
    "iso:country":"US",
    "sg:address":"222 E Van Buren Ave",
    "sg:city":"Harlingen",
    "sg:classifiers":[
        {
            "category":"Health Services",
            "subcategory":"Clinic",
            "type":"Services"
        }
    ],
    "sg:phone":"+1 956 423 9400",
    "sg:postcode":"78550",
    "sg:province":"TX",
    "wof:name":"Churchill Medical Inc",
    "wof:placetype":"venue"
},
  "geometry": {"coordinates":[-97.693628,26.191647],"type":"Point"}
}