{
  "type": "Feature",
  "properties": {
    "iso:country":"US",
    "sg:address":"1318 Sealane Dr",
    "sg:city":"Corpus Christi",
    "sg:classifiers":[
        {
            "category":"Building & Trades",
            "subcategory":"Electrical",
            "type":"Services"
        }
    ],
    "sg:phone":"+1 361 937 5020",
    "sg:postcode":"78412",
    "sg:province":"TX",
    "sg:tags":[
        "electric",
        "contractor"
    ],
    "wof:name":"Wright Electric",
    "wof:placetype":"venue"
},
  "geometry": {"coordinates":[-97.320019,27.687572],"type":"Point"}
}