{
  "type": "Feature",
  "properties": {
    "iso:country":"US",
    "sg:address":"3911 Walnut Grove Ln",
    "sg:city":"Carrollton",
    "sg:classifiers":[
        {
            "category":"Insurance",
            "subcategory":"Hazard Insurance",
            "type":"Services"
        }
    ],
    "sg:phone":"+1 972 394 3540",
    "sg:postcode":"75007",
    "sg:province":"TX",
    "sg:tags":[
        "carrier",
        "surety"
    ],
    "wof:name":"Nick Young Insurance Agency In",
    "wof:placetype":"venue"
},
  "geometry": {"coordinates":[-96.917502,33.01649],"type":"Point"}
}