{
  "type": "Feature",
  "properties": {
    "iso:country":"US",
    "sg:address":"3051 Horse Ranch Rd",
    "sg:city":"San Antonio",
    "sg:classifiers":[
        {
            "category":"Freight",
            "type":"Transportation"
        }
    ],
    "sg:phone":"+1 210 621 0797",
    "sg:postcode":"78264",
    "sg:province":"TX",
    "sg:tags":[
        "operator",
        "local",
        "trucking"
    ],
    "wof:name":"Cnr Trucking Co",
    "wof:placetype":"venue"
},
  "geometry": {"coordinates":[-98.432675,29.154096],"type":"Point"}
}