{
  "type": "Feature",
  "properties": {
    "iso:country":"US",
    "sg:address":"8338 Bent Meadow Dr",
    "sg:city":"Converse",
    "sg:classifiers":[
        {
            "category":"Shopping",
            "subcategory":"Books",
            "type":"Retail Goods"
        }
    ],
    "sg:phone":"+1 210 662 9688",
    "sg:postcode":"78109",
    "sg:province":"TX",
    "wof:name":"J & R Books Plus",
    "wof:placetype":"venue"
},
  "geometry": {"coordinates":[-98.321325,29.492324],"type":"Point"}
}