{
  "type": "Feature",
  "properties": {
    "iso:country":"US",
    "sg:address":"5025 Wesley St",
    "sg:city":"Greenville",
    "sg:classifiers":[
        {
            "category":"Banks & Credit Unions",
            "subcategory":"Bank",
            "type":"Services"
        }
    ],
    "sg:phone":"+1 903 454 8723",
    "sg:postcode":"75402",
    "sg:province":"TX",
    "sg:tags":[
        "personal",
        "institution"
    ],
    "wof:name":"Advance America",
    "wof:placetype":"venue"
},
  "geometry": {"coordinates":[-96.10917600000001,33.120265],"type":"Point"}
}