{
  "type": "Feature",
  "properties": {
    "iso:country":"US",
    "sg:address":"440 Benmar Dr",
    "sg:city":"Houston",
    "sg:classifiers":[
        {
            "category":"Building & Trades",
            "subcategory":"Construction",
            "type":"Services"
        }
    ],
    "sg:phone":"+1 281 397 6614",
    "sg:postcode":"77060",
    "sg:province":"TX",
    "sg:tags":[
        "roofing",
        "contractor"
    ],
    "wof:name":"All Type Roofing Inc",
    "wof:placetype":"venue"
},
  "geometry": {"coordinates":[-95.398763,29.943907],"type":"Point"}
}