{
  "type": "Feature",
  "properties": {
    "iso:country":"US",
    "sg:address":"1501 Independence Ave",
    "sg:city":"Bryan",
    "sg:classifiers":[
        {
            "category":"Wholesale",
            "subcategory":"Beer",
            "type":"Manufacturing & Wholesale Goods"
        }
    ],
    "sg:phone":"+1 979 775 6322",
    "sg:postcode":"77803",
    "sg:province":"TX",
    "sg:tags":[
        "drink",
        "natural",
        "ale",
        "packaged",
        "water",
        "can",
        "soft"
    ],
    "wof:name":"Kristen Distributing Co Inc",
    "wof:placetype":"venue"
},
  "geometry": {"coordinates":[-96.412094,30.65837],"type":"Point"}
}