{
  "type": "Feature",
  "properties": {
    "iso:country":"US",
    "sg:address":"4021 Bellmead Dr",
    "sg:city":"Waco",
    "sg:classifiers":[
        {
            "category":"Shopping",
            "subcategory":"Hobbies, Toys, & Games",
            "type":"Retail Goods"
        }
    ],
    "sg:phone":"+1 254 867 9848",
    "sg:postcode":"76705",
    "sg:province":"TX",
    "sg:tags":[
        "darts",
        "boards",
        "dart"
    ],
    "wof:name":"Smokers Billiard",
    "wof:placetype":"venue"
},
  "geometry": {"coordinates":[-97.090311,31.598235],"type":"Point"}
}