{
  "type": "Feature",
  "properties": {
    "iso:country":"US",
    "sg:address":"759 Driftwood Ln",
    "sg:city":"Marble Falls",
    "sg:classifiers":[
        {
            "category":"Organizations",
            "subcategory":"Religious Organization",
            "type":"Services"
        }
    ],
    "sg:phone":"+1 830 693 3117",
    "sg:postcode":"78657",
    "sg:province":"TX",
    "wof:name":"Cottonwood Community Chur",
    "wof:placetype":"venue"
},
  "geometry": {"coordinates":[-98.320184,30.555862],"type":"Point"}
}