{
  "type": "Feature",
  "properties": {
    "iso:country":"US",
    "sg:address":"14100 San Pedro Ave",
    "sg:city":"San Antonio",
    "sg:classifiers":[
        {
            "category":"Wholesale",
            "subcategory":"Electrical",
            "type":"Manufacturing & Wholesale Goods"
        }
    ],
    "sg:phone":"+1 210 494 9336",
    "sg:postcode":"78232",
    "sg:province":"TX",
    "sg:tags":[
        "repair",
        "electronic"
    ],
    "wof:name":"HP",
    "wof:placetype":"venue"
},
  "geometry": {"coordinates":[-98.47955899999999,29.573676],"type":"Point"}
}