{
  "type": "Feature",
  "properties": {
    "iso:country":"US",
    "sg:address":"773 State Hwy 205",
    "sg:city":"Terrell",
    "sg:classifiers":[
        {
            "category":"Recreation",
            "type":"Entertainment"
        }
    ],
    "sg:phone":"+1 972 524 1747",
    "sg:postcode":"75160",
    "sg:province":"TX",
    "sg:tags":[
        "club",
        "membership"
    ],
    "wof:name":"Experimental Aircraft Assn",
    "wof:placetype":"venue"
},
  "geometry": {"coordinates":[-96.307542,32.755829],"type":"Point"}
}