{
  "type": "Feature",
  "properties": {
    "iso:country":"US",
    "sg:address":"9344 Locarno Dr",
    "sg:city":"Dallas",
    "sg:classifiers":[
        {
            "category":"Social Services",
            "type":"Services"
        }
    ],
    "sg:phone":"+1 214 348 5886",
    "sg:postcode":"75243",
    "sg:province":"TX",
    "sg:tags":[
        "counselor",
        "marriage",
        "family"
    ],
    "wof:name":"Victoria L Harvey",
    "wof:placetype":"venue"
},
  "geometry": {"coordinates":[-96.74223000000001,32.899469],"type":"Point"}
}