{
  "type": "Feature",
  "properties": {
    "iso:country":"US",
    "sg:address":"511 Springdale Rd",
    "sg:city":"Austin",
    "sg:classifiers":[
        {
            "category":"Utilities",
            "subcategory":"Telephone",
            "type":"Services"
        }
    ],
    "sg:phone":"+1 800 235 9800",
    "sg:postcode":"78702",
    "sg:province":"TX",
    "sg:tags":[
        "communication"
    ],
    "sg:website":"http://www.swbell.com",
    "wof:name":"Southwestern Bell Telephone, L.P.",
    "wof:placetype":"venue"
},
  "geometry": {"coordinates":[-97.70299199999999,30.25399],"type":"Point"}
}