{
  "type": "Feature",
  "properties": {
    "iso:country":"US",
    "sg:address":"5249 Broadway Blvd",
    "sg:city":"Garland",
    "sg:classifiers":[
        {
            "category":"Professional",
            "type":"Services"
        }
    ],
    "sg:phone":"+1 972 240 8069",
    "sg:postcode":"75043",
    "sg:province":"TX",
    "sg:tags":[
        "establishment"
    ],
    "wof:name":"Mr Money USA",
    "wof:placetype":"venue"
},
  "geometry": {"coordinates":[-96.598911,32.85148],"type":"Point"}
}