{
  "type": "Feature",
  "properties": {
    "iso:country":"US",
    "sg:address":"700 S I- 35 E",
    "sg:city":"Denton",
    "sg:classifiers":[
        {
            "category":"Food & Beverages",
            "subcategory":"Groceries & Convenience Stores",
            "type":"Retail Goods"
        }
    ],
    "sg:phone":"+1 940 382 5679",
    "sg:postcode":"76205",
    "sg:province":"TX",
    "wof:name":"Lone Star Food Store",
    "wof:placetype":"venue"
},
  "geometry": {"coordinates":[-97.124083,33.19312],"type":"Point"}
}