{
  "type": "Feature",
  "properties": {
    "iso:country":"US",
    "sg:address":"309 N Burnett St",
    "sg:city":"Wichita Falls",
    "sg:classifiers":[
        {
            "category":"Organizations",
            "subcategory":"Religious Organization",
            "type":"Services"
        }
    ],
    "sg:phone":"+1 940 322 3265",
    "sg:postcode":"76306",
    "sg:province":"TX",
    "sg:tags":[
        "church"
    ],
    "wof:name":"Ebenezer Baptist Church",
    "wof:placetype":"venue"
},
  "geometry": {"coordinates":[-98.50336799999999,33.917849],"type":"Point"}
}