{
  "type": "Feature",
  "properties": {
    "iso:country":"US",
    "sg:address":"32815 FM 2978",
    "sg:city":"Magnolia",
    "sg:classifiers":[
        {
            "category":"Manufacturing",
            "subcategory":"Metals",
            "type":"Manufacturing & Wholesale Goods"
        }
    ],
    "sg:phone":"+1 281 259 6881",
    "sg:postcode":"77354",
    "sg:province":"TX",
    "sg:tags":[
        "metalwork",
        "architectural",
        "mfg"
    ],
    "wof:name":"Rocking R Ironworks",
    "wof:placetype":"venue"
},
  "geometry": {"coordinates":[-95.56823199999999,30.219192],"type":"Point"}
}