{
  "type": "Feature",
  "properties": {
    "iso:country":"US",
    "sg:address":"2525 Wallingwood Dr",
    "sg:city":"Austin",
    "sg:classifiers":[
        {
            "category":"Health Services",
            "subcategory":"Doctor",
            "type":"Services"
        }
    ],
    "sg:phone":"+1 512 306 0002",
    "sg:postcode":"78746",
    "sg:province":"TX",
    "sg:tags":[
        "medical"
    ],
    "wof:name":"Gary Lusk",
    "wof:placetype":"venue"
},
  "geometry": {"coordinates":[-97.783019,30.264912],"type":"Point"}
}