{
  "type": "Feature",
  "properties": {
    "iso:country":"US",
    "sg:address":"7315 W Elizabeth Ln",
    "sg:city":"Fort Worth",
    "sg:classifiers":[
        {
            "category":"Building & Trades",
            "subcategory":"Construction",
            "type":"Services"
        }
    ],
    "sg:phone":"+1 817 244 7730",
    "sg:postcode":"76116",
    "sg:province":"TX",
    "sg:tags":[
        "general",
        "contractor"
    ],
    "wof:name":"Horizon General Contractors",
    "wof:placetype":"venue"
},
  "geometry": {"coordinates":[-97.443449,32.724121],"type":"Point"}
}