{
  "type": "Feature",
  "properties": {
    "iso:country":"US",
    "sg:address":"702 Herder Ave",
    "sg:city":"Schulenburg",
    "sg:classifiers":[
        {
            "category":"Social Services",
            "subcategory":"Child Care",
            "type":"Services"
        }
    ],
    "sg:phone":"+1 979 743 4369",
    "sg:postcode":"78956",
    "sg:province":"TX",
    "sg:tags":[
        "nursery",
        "day"
    ],
    "wof:name":"Almost Home",
    "wof:placetype":"venue"
},
  "geometry": {"coordinates":[-96.90032100000001,29.681008],"type":"Point"}
}