{
  "type": "Feature",
  "properties": {
    "iso:country":"US",
    "sg:address":"4619 Wee Lassie Ln",
    "sg:city":"Houston",
    "sg:classifiers":[
        {
            "category":"Shopping",
            "subcategory":"Hobbies, Toys, & Games",
            "type":"Retail Goods"
        }
    ],
    "sg:phone":"+1 281 861 8428",
    "sg:postcode":"77084",
    "sg:province":"TX",
    "sg:tags":[
        "craft"
    ],
    "wof:name":"J & B Creations",
    "wof:placetype":"venue"
},
  "geometry": {"coordinates":[-95.64818,29.842143],"type":"Point"}
}