{
  "type": "Feature",
  "properties": {
    "iso:country":"US",
    "sg:address":"906 Kelley St",
    "sg:city":"Houston",
    "sg:classifiers":[
        {
            "category":"Professional",
            "subcategory":"Lawyer & Legal Services",
            "type":"Services"
        }
    ],
    "sg:phone":"+1 713 457 2405",
    "sg:postcode":"77009",
    "sg:province":"TX",
    "sg:tags":[
        "attorney"
    ],
    "wof:name":"Elihu H Dodier",
    "wof:placetype":"venue"
},
  "geometry": {"coordinates":[-95.358115,29.813134],"type":"Point"}
}