{
  "type": "Feature",
  "properties": {
    "iso:country":"US",
    "sg:address":"4402 Mineral Wells Hwy",
    "sg:city":"Weatherford",
    "sg:classifiers":[
        {
            "category":"Autos & Motor Vehicles",
            "subcategory":"Automobile Sales",
            "type":"Retail Goods"
        }
    ],
    "sg:phone":"+1 817 594 3111",
    "sg:postcode":"76088",
    "sg:province":"TX",
    "sg:tags":[
        "car",
        "dealer"
    ],
    "wof:name":"Sessum Motors",
    "wof:placetype":"venue"
},
  "geometry": {"coordinates":[-97.87735499999999,32.773615],"type":"Point"}
}