{
  "type": "Feature",
  "properties": {
    "iso:country":"US",
    "sg:address":"13723 Smokey Trail Dr",
    "sg:city":"Houston",
    "sg:classifiers":[
        {
            "category":"Professional",
            "type":"Services"
        }
    ],
    "sg:phone":"+1 713 466 8396",
    "sg:postcode":"77041",
    "sg:province":"TX",
    "wof:name":"Danny Bennett Services",
    "wof:placetype":"venue"
},
  "geometry": {"coordinates":[-95.617442,29.885604],"type":"Point"}
}