{
  "type": "Feature",
  "properties": {
    "iso:country":"US",
    "sg:address":"2114 Briargreen Dr",
    "sg:city":"Houston",
    "sg:classifiers":[
        {
            "category":"Social Services",
            "type":"Services"
        }
    ],
    "sg:phone":"+1 281 493 3780",
    "sg:postcode":"77077",
    "sg:province":"TX",
    "wof:name":"Latin American Service",
    "wof:placetype":"venue"
},
  "geometry": {"coordinates":[-95.638389,29.741722],"type":"Point"}
}