{
  "type": "Feature",
  "properties": {
    "iso:country":"US",
    "sg:address":"104 S Lutterloh Ave",
    "sg:city":"Gatesville",
    "sg:classifiers":[
        {
            "category":"Health Services",
            "subcategory":"Doctor",
            "type":"Services"
        }
    ],
    "sg:phone":"+1 254 248 1952",
    "sg:postcode":"76528",
    "sg:province":"TX",
    "sg:tags":[
        "clinic"
    ],
    "wof:name":"Outreach Health Svc-Wic Clinic",
    "wof:placetype":"venue"
},
  "geometry": {"coordinates":[-97.744377,31.434889],"type":"Point"}
}