{
  "type": "Feature",
  "properties": {
    "iso:country":"US",
    "sg:address":"1643 Ash Ln",
    "sg:city":"Denton",
    "sg:classifiers":[
        {
            "category":"Personal",
            "subcategory":"Beauty Salon",
            "type":"Services"
        }
    ],
    "sg:phone":"+1 940 321 0073",
    "sg:postcode":"76210",
    "sg:province":"TX",
    "sg:tags":[
        "shop"
    ],
    "wof:name":"Pep Professional Event Plg",
    "wof:placetype":"venue"
},
  "geometry": {"coordinates":[-97.084333,33.141779],"type":"Point"}
}