{
  "type": "Feature",
  "properties": {
    "iso:country":"US",
    "sg:address":"1606 E Regis St",
    "sg:city":"Lubbock",
    "sg:classifiers":[
        {
            "category":"Retail",
            "subcategory":"Auto Rental",
            "type":"Services"
        }
    ],
    "sg:phone":"+1 806 763 6472",
    "sg:postcode":"79403",
    "sg:province":"TX",
    "sg:tags":[
        "passenger",
        "leasing",
        "car"
    ],
    "wof:name":"Budget Rent-A-Car",
    "wof:placetype":"venue"
},
  "geometry": {"coordinates":[-101.823063,33.643298],"type":"Point"}
}