{
  "type": "Feature",
  "properties": {
    "iso:country":"US",
    "sg:address":"5708 Cliff Haven Dr",
    "sg:city":"Dallas",
    "sg:classifiers":[
        {
            "category":"Professional",
            "subcategory":"Business Services",
            "type":"Services"
        },
        {
            "category":"Wholesale",
            "subcategory":"Durable Goods & Equipment",
            "type":"Manufacturing & Wholesale Goods"
        }
    ],
    "sg:phone":"+1 972 296 1938",
    "sg:postcode":"75236",
    "sg:province":"TX",
    "sg:tags":[
        "importer"
    ],
    "wof:name":"Mano River Enterprises Intl",
    "wof:placetype":"venue"
},
  "geometry": {"coordinates":[-96.929376,32.677081],"type":"Point"}
}