{
  "type": "Feature",
  "properties": {
    "iso:country":"US",
    "sg:address":"2006 N Jackson Rd",
    "sg:city":"Pharr",
    "sg:classifiers":[
        {
            "category":"Building & Trades",
            "subcategory":"Construction",
            "type":"Services"
        }
    ],
    "sg:phone":"+1 956 631 5617",
    "sg:postcode":"78577",
    "sg:province":"TX",
    "sg:tags":[
        "general",
        "contractor"
    ],
    "wof:name":"Amtex Inc",
    "wof:placetype":"venue"
},
  "geometry": {"coordinates":[-98.201278,26.215141],"type":"Point"}
}