{
  "type": "Feature",
  "properties": {
    "iso:country":"US",
    "sg:address":"800 Maplewood Ct",
    "sg:city":"Euless",
    "sg:classifiers":[
        {
            "category":"Autos & Motor Vehicles",
            "subcategory":"Automobile Sales",
            "type":"Retail Goods"
        }
    ],
    "sg:phone":"+1 817 300 7297",
    "sg:postcode":"76039",
    "sg:province":"TX",
    "sg:tags":[
        "aircraft"
    ],
    "wof:name":"Prewitt Aircraft Sales Co",
    "wof:placetype":"venue"
},
  "geometry": {"coordinates":[-97.09530700000001,32.852334],"type":"Point"}
}