{
  "type": "Feature",
  "properties": {
    "iso:country":"US",
    "sg:address":"510 Glenburnie Dr",
    "sg:city":"Houston",
    "sg:classifiers":[
        {
            "category":"Freight",
            "type":"Transportation"
        }
    ],
    "sg:phone":"+1 713 694 0795",
    "sg:postcode":"77022",
    "sg:province":"TX",
    "sg:tags":[
        "operator",
        "local",
        "trucking"
    ],
    "wof:name":"Harrell C & E Trucking",
    "wof:placetype":"venue"
},
  "geometry": {"coordinates":[-95.391104,29.838486],"type":"Point"}
}