{
  "type": "Feature",
  "properties": {
    "iso:country":"US",
    "sg:address":"8300 Gaylord Pkwy",
    "sg:city":"Frisco",
    "sg:classifiers":[
        {
            "category":"Health Services",
            "subcategory":"Doctor",
            "type":"Services"
        },
        {
            "category":"Health Services",
            "subcategory":"Dentist",
            "type":"Services"
        }
    ],
    "sg:phone":"+1 972 335 7666",
    "sg:postcode":"75034",
    "sg:province":"TX",
    "sg:tags":[
        "physician",
        "denture",
        "dental",
        "surgeons",
        "clinic",
        "surgery",
        "oral",
        "dentists-prosthodontists"
    ],
    "wof:name":"Accent Dental",
    "wof:placetype":"venue"
},
  "geometry": {"coordinates":[-96.81232,33.102655],"type":"Point"}
}