{
  "type": "Feature",
  "properties": {
    "iso:country":"US",
    "sg:address":"14243 Stuebner Airline Rd",
    "sg:city":"Houston",
    "sg:classifiers":[
        {
            "category":"Shopping",
            "subcategory":"Clothing, Apparel, & Fashions",
            "type":"Retail Goods"
        },
        {
            "category":"Retail",
            "subcategory":"Laundry & Dry Cleaning",
            "type":"Services"
        }
    ],
    "sg:phone":"+1 281 583 8044",
    "sg:postcode":"77069",
    "sg:province":"TX",
    "sg:tags":[
        "cleaner",
        "tailor",
        "alterations-clothing"
    ],
    "wof:name":"Ann's Tailor",
    "wof:placetype":"venue"
},
  "geometry": {"coordinates":[-95.500505,29.990716],"type":"Point"}
}