{
  "type": "Feature",
  "properties": {
    "iso:country":"US",
    "sg:address":"1512 S 5th St",
    "sg:city":"Merkel",
    "sg:classifiers":[
        {
            "category":"Education",
            "subcategory":"School",
            "type":"Public Place"
        }
    ],
    "sg:phone":"+1 325 928 4795",
    "sg:postcode":"79536",
    "sg:province":"TX",
    "wof:name":"Merkel Elementary School",
    "wof:placetype":"venue"
},
  "geometry": {"coordinates":[-100.020674,32.466353],"type":"Point"}
}