{
  "type": "Feature",
  "properties": {
    "iso:country":"US",
    "sg:address":"492 W San Antonio St",
    "sg:city":"New Braunfels",
    "sg:classifiers":[
        {
            "category":"Professional",
            "subcategory":"Accounting & Tax Preparation",
            "type":"Services"
        }
    ],
    "sg:phone":"+1 830 609 6686",
    "sg:postcode":"78130",
    "sg:province":"TX",
    "sg:tags":[
        "accountant"
    ],
    "wof:name":"Vol F Mc Glothlin CPA",
    "wof:placetype":"venue"
},
  "geometry": {"coordinates":[-98.12765400000001,29.699435],"type":"Point"}
}