{
  "type": "Feature",
  "properties": {
    "iso:country":"US",
    "sg:address":"509 Cypress St",
    "sg:city":"Teague",
    "sg:classifiers":[
        {
            "category":"Home & Garden",
            "subcategory":"Building Materials",
            "type":"Retail Goods"
        }
    ],
    "sg:phone":"+1 254 739 3651",
    "sg:postcode":"75860",
    "sg:province":"TX",
    "sg:tags":[
        "sand",
        "gravel"
    ],
    "wof:name":"Nichols Sand and Gravel",
    "wof:placetype":"venue"
},
  "geometry": {"coordinates":[-96.282338,31.631183],"type":"Point"}
}