{
  "type": "Feature",
  "properties": {
    "iso:country":"US",
    "sg:address":"9143 Penn Manor Ct",
    "sg:city":"Houston",
    "sg:classifiers":[
        {
            "category":"Manufacturing",
            "subcategory":"Metals",
            "type":"Manufacturing & Wholesale Goods"
        },
        {
            "category":"Manufacturing",
            "subcategory":"Building Materials",
            "type":"Manufacturing & Wholesale Goods"
        }
    ],
    "sg:phone":"+1 713 675 7555",
    "sg:postcode":"77055",
    "sg:province":"TX",
    "sg:tags":[
        "work-manufacturers",
        "fabricator",
        "work",
        "sheet"
    ],
    "sg:website":"http://www.m3p.com",
    "wof:name":"M3p",
    "wof:placetype":"venue"
},
  "geometry": {"coordinates":[-95.516699,29.786104],"type":"Point"}
}