{
  "type": "Feature",
  "properties": {
    "iso:country":"US",
    "sg:address":"4719 Swiss Ave",
    "sg:city":"Dallas",
    "sg:classifiers":[
        {
            "category":"Shopping",
            "subcategory":"Gifts & Souvenirs",
            "type":"Retail Goods"
        }
    ],
    "sg:phone":"+1 214 821 7689",
    "sg:postcode":"75204",
    "sg:province":"TX",
    "wof:name":"House of Joy Gifts",
    "wof:placetype":"venue"
},
  "geometry": {"coordinates":[-96.772369,32.799986],"type":"Point"}
}