{
  "type": "Feature",
  "properties": {
    "iso:country":"US",
    "sg:address":"8401 Forest Heights Ln",
    "sg:city":"Austin",
    "sg:classifiers":[
        {
            "category":"Manufacturing",
            "subcategory":"Musical Instruments",
            "type":"Manufacturing & Wholesale Goods"
        }
    ],
    "sg:phone":"+1 512 906 5348",
    "sg:postcode":"78749",
    "sg:province":"TX",
    "sg:tags":[
        "instruments-wholesale",
        "manufacturer"
    ],
    "wof:name":"Trumpet Bags",
    "wof:placetype":"venue"
},
  "geometry": {"coordinates":[-97.866623,30.212561],"type":"Point"}
}