{
  "type": "Feature",
  "properties": {
    "iso:country":"US",
    "sg:address":"5177 Richmond Ave",
    "sg:city":"Houston",
    "sg:classifiers":[
        {
            "category":"Health Services",
            "subcategory":"Dentist",
            "type":"Services"
        }
    ],
    "sg:phone":"+1 713 629 6700",
    "sg:postcode":"77056",
    "sg:province":"TX",
    "sg:tags":[
        "equipment",
        "dental",
        "supply"
    ],
    "wof:name":"Genuine Professional Supplies Inc",
    "wof:placetype":"venue"
},
  "geometry": {"coordinates":[-95.465801,29.731551],"type":"Point"}
}