{
  "type": "Feature",
  "properties": {
    "iso:country":"US",
    "sg:address":"16826 Dutch Ridge Dr",
    "sg:city":"Sugar Land",
    "sg:classifiers":[
        {
            "category":"Professional",
            "subcategory":"Management & Consulting",
            "type":"Services"
        }
    ],
    "sg:phone":"+1 281 277 1535",
    "sg:postcode":"77478",
    "sg:province":"TX",
    "sg:tags":[
        "business"
    ],
    "wof:name":"Energy Wise",
    "wof:placetype":"venue"
},
  "geometry": {"coordinates":[-95.664315,29.641728],"type":"Point"}
}