{
  "type": "Feature",
  "properties": {
    "iso:country":"US",
    "sg:address":"14173 Northwest Freeway",
    "sg:city":"Houston",
    "sg:classifiers":[
        {
            "category":"Home & Garden",
            "subcategory":"Household Appliances",
            "type":"Retail Goods"
        }
    ],
    "sg:phone":"+1 877 244 4580",
    "sg:postcode":"77040",
    "sg:province":"TX",
    "sg:tags":[
        "repair"
    ],
    "sg:website":"www.houstonappliancerepair.net",
    "wof:name":"Houston Appliance",
    "wof:placetype":"venue"
},
  "geometry": {"coordinates":[-95.52703,29.860424],"type":"Point"}
}