{
  "type": "Feature",
  "properties": {
    "iso:country":"US",
    "sg:address":"4694 Sun Bird Rd",
    "sg:city":"Chandler",
    "sg:classifiers":[
        {
            "category":"Restaurant",
            "type":"Food & Drink"
        }
    ],
    "sg:phone":"+1 903 849 5052",
    "sg:postcode":"75758",
    "sg:province":"TX",
    "sg:tags":[
        "eating"
    ],
    "wof:name":"Holy Smoke Barbeque",
    "wof:placetype":"venue"
},
  "geometry": {"coordinates":[-95.51275699999999,32.184048],"type":"Point"}
}