{
  "type": "Feature",
  "properties": {
    "iso:country":"US",
    "sg:address":"1805 5th St",
    "sg:city":"Bay City",
    "sg:classifiers":[
        {
            "category":"Professional",
            "subcategory":"Lawyer & Legal Services",
            "type":"Services"
        }
    ],
    "sg:phone":"+1 979 245 6313",
    "sg:postcode":"77414",
    "sg:province":"TX",
    "sg:tags":[
        "attorney"
    ],
    "wof:name":"Herbert W Henry",
    "wof:placetype":"venue"
},
  "geometry": {"coordinates":[-95.96751999999999,28.980972],"type":"Point"}
}