{
  "type": "Feature",
  "properties": {
    "iso:country":"US",
    "sg:address":"2201 Valley Mill",
    "sg:city":"Carrollton",
    "sg:classifiers":[
        {
            "category":"Professional",
            "subcategory":"Computer Services",
            "type":"Services"
        }
    ],
    "sg:phone":"+1 972 416 1623",
    "sg:postcode":"75006",
    "sg:province":"TX",
    "sg:tags":[
        "prepackaged",
        "software"
    ],
    "wof:name":"Youngs System Software",
    "wof:placetype":"venue"
},
  "geometry": {"coordinates":[-96.87647699999999,32.98111],"type":"Point"}
}