{
  "type": "Feature",
  "properties": {
    "iso:country":"US",
    "sg:address":"1309 W Airport Fwy",
    "sg:city":"Irving",
    "sg:classifiers":[
        {
            "category":"Banks & Credit Unions",
            "subcategory":"Bank",
            "type":"Services"
        }
    ],
    "sg:phone":"+1 972 258 1567",
    "sg:postcode":"75062",
    "sg:province":"TX",
    "sg:tags":[
        "federal",
        "savings",
        "institution"
    ],
    "wof:name":"Washington Mutual Training Ctr",
    "wof:placetype":"venue"
},
  "geometry": {"coordinates":[-96.967416,32.837391],"type":"Point"}
}