{
  "type": "Feature",
  "properties": {
    "iso:country":"US",
    "sg:address":"201 Apollo Rd",
    "sg:city":"Garland",
    "sg:classifiers":[
        {
            "category":"Shopping",
            "type":"Retail Goods"
        }
    ],
    "sg:phone":"+1 972 495 8341",
    "sg:postcode":"75040",
    "sg:province":"TX",
    "sg:tags":[
        "merchandising"
    ],
    "wof:name":"Gayle Brandt",
    "wof:placetype":"venue"
},
  "geometry": {"coordinates":[-96.630493,32.940941],"type":"Point"}
}