{
  "type": "Feature",
  "properties": {
    "iso:country":"US",
    "sg:address":"3629 Fort Ave",
    "sg:city":"Waco",
    "sg:classifiers":[
        {
            "category":"Professional",
            "type":"Services"
        }
    ],
    "sg:phone":"+1 254 759 2300",
    "sg:postcode":"76710",
    "sg:province":"TX",
    "wof:name":"1st Rgs Corp",
    "wof:placetype":"venue"
},
  "geometry": {"coordinates":[-97.165666,31.535857],"type":"Point"}
}