{
  "type": "Feature",
  "properties": {
    "iso:country":"US",
    "sg:address":"3204 Valley St",
    "sg:city":"Carrizo Springs",
    "sg:classifiers":[
        {
            "category":"Utilities",
            "subcategory":"Electric",
            "type":"Services"
        }
    ],
    "sg:phone":"+1 830 876 2513",
    "sg:postcode":"78834",
    "sg:province":"TX",
    "sg:tags":[
        "company"
    ],
    "sg:website":"www.rgec.com",
    "wof:name":"Rio Grande Electric Co-Op Inc",
    "wof:placetype":"venue"
},
  "geometry": {"coordinates":[-99.880083,28.530147],"type":"Point"}
}