{
  "type": "Feature",
  "properties": {
    "iso:country":"US",
    "sg:address":"11562 Cypress North Houston Rd",
    "sg:city":"Cypress",
    "sg:classifiers":[
        {
            "category":"Professional",
            "subcategory":"Management & Consulting",
            "type":"Services"
        }
    ],
    "sg:phone":"+1 281 955 2080",
    "sg:postcode":"77429",
    "sg:province":"TX",
    "wof:name":"Ad Dynamics",
    "wof:placetype":"venue"
},
  "geometry": {"coordinates":[-95.59456900000001,29.952529],"type":"Point"}
}