{
  "type": "Feature",
  "properties": {
    "iso:country":"US",
    "sg:address":"10434 Jennys Jump Dr",
    "sg:city":"Austin",
    "sg:classifiers":[
        {
            "category":"Professional",
            "type":"Services"
        }
    ],
    "sg:phone":"+1 512 263 0933",
    "sg:postcode":"78733",
    "sg:province":"TX",
    "sg:tags":[
        "establishment"
    ],
    "wof:name":"Schweber Hexcel",
    "wof:placetype":"venue"
},
  "geometry": {"coordinates":[-97.878871,30.336582],"type":"Point"}
}