{
  "type": "Feature",
  "properties": {
    "iso:country":"US",
    "sg:address":"3212 Spencer Hwy",
    "sg:city":"Pasadena",
    "sg:classifiers":[
        {
            "category":"Restaurant",
            "type":"Food & Drink"
        }
    ],
    "sg:phone":"+1 713 910 8692",
    "sg:postcode":"77504",
    "sg:province":"TX",
    "sg:tags":[
        "eating"
    ],
    "wof:name":"Mi Pueblito Taqueria",
    "wof:placetype":"venue"
},
  "geometry": {"coordinates":[-95.19424600000001,29.66492],"type":"Point"}
}