{
  "type": "Feature",
  "properties": {
    "iso:country":"US",
    "sg:address":"5215 Woodrow Ave",
    "sg:city":"Austin",
    "sg:classifiers":[
        {
            "category":"Insurance",
            "subcategory":"Health Insurance",
            "type":"Services"
        }
    ],
    "sg:phone":"+1 512 454 1620",
    "sg:postcode":"78756",
    "sg:province":"TX",
    "sg:tags":[
        "plan"
    ],
    "wof:name":"Dental Alliance Resources Inc",
    "wof:placetype":"venue"
},
  "geometry": {"coordinates":[-97.7358,30.324129],"type":"Point"}
}