{
  "type": "Feature",
  "properties": {
    "iso:country":"US",
    "sg:address":"303 Stonebridge Dr",
    "sg:city":"Richardson",
    "sg:classifiers":[
        {
            "category":"Professional",
            "subcategory":"Management & Consulting",
            "type":"Services"
        }
    ],
    "sg:phone":"+1 972 234 0865",
    "sg:postcode":"75080",
    "sg:province":"TX",
    "sg:tags":[
        "business"
    ],
    "wof:name":"Blythe Hughes Consulting",
    "wof:placetype":"venue"
},
  "geometry": {"coordinates":[-96.721418,32.982261],"type":"Point"}
}