{
  "type": "Feature",
  "properties": {
    "iso:country":"US",
    "sg:address":"3102 Oak Lawn Ave Ste 700",
    "sg:city":"Dallas",
    "sg:classifiers":[
        {
            "category":"Banks & Credit Unions",
            "subcategory":"Financial Services",
            "type":"Services"
        }
    ],
    "sg:phone":"+1 214 560 2280",
    "sg:postcode":"75219",
    "sg:province":"TX",
    "sg:tags":[
        "broker",
        "mortgage"
    ],
    "wof:name":"Mortgages Direct",
    "wof:placetype":"venue"
},
  "geometry": {"coordinates":[-96.80847199999999,32.809035],"type":"Point"}
}