{
  "type": "Feature",
  "properties": {
    "iso:country":"US",
    "sg:address":"8120 Research Boulevard",
    "sg:city":"Austin",
    "sg:classifiers":[
        {
            "category":"Ice Cream",
            "type":"Food & Drink"
        }
    ],
    "sg:phone":"+1 512 407 9009",
    "sg:postcode":"78758",
    "sg:province":"TX",
    "sg:tags":[
        "frozen",
        "yogurt"
    ],
    "wof:name":"La Delicias Paleteria Y Neveria",
    "wof:placetype":"venue"
},
  "geometry": {"coordinates":[-97.71550999999999,30.355579],"type":"Point"}
}