{
  "type": "Feature",
  "properties": {
    "iso:country":"US",
    "sg:address":"40318 Community Rd",
    "sg:city":"Magnolia",
    "sg:classifiers":[
        {
            "category":"Building & Trades",
            "subcategory":"Construction",
            "type":"Services"
        }
    ],
    "sg:phone":"+1 281 356 8417",
    "sg:postcode":"77354",
    "sg:province":"TX",
    "sg:tags":[
        "road",
        "contractor"
    ],
    "wof:name":"Deanco Inc",
    "wof:placetype":"venue"
},
  "geometry": {"coordinates":[-95.671184,30.228833],"type":"Point"}
}