{
  "type": "Feature",
  "properties": {
    "iso:country":"US",
    "sg:address":"6154 Royal Breeze",
    "sg:city":"San Antonio",
    "sg:classifiers":[
        {
            "category":"Social Services",
            "subcategory":"Child Care",
            "type":"Services"
        }
    ],
    "sg:phone":"+1 210 657 6990",
    "sg:postcode":"78239",
    "sg:province":"TX",
    "sg:tags":[
        "day"
    ],
    "wof:name":"Day Road Corp",
    "wof:placetype":"venue"
},
  "geometry": {"coordinates":[-98.36611600000001,29.536579],"type":"Point"}
}