{
  "type": "Feature",
  "properties": {
    "iso:country":"US",
    "sg:address":"310 S Broadway St",
    "sg:city":"Joshua",
    "sg:classifiers":[
        {
            "category":"Personal",
            "subcategory":"Beauty Salon",
            "type":"Services"
        },
        {
            "category":"Sports & Exercise",
            "subcategory":"Gym",
            "type":"Entertainment"
        }
    ],
    "sg:phone":"+1 817 774 3208",
    "sg:postcode":"76058",
    "sg:province":"TX",
    "sg:tags":[
        "fitness",
        "physical",
        "facility"
    ],
    "wof:name":"Picture Perfect Day Spa",
    "wof:placetype":"venue"
},
  "geometry": {"coordinates":[-97.38455,32.45805],"type":"Point"}
}