{
  "type": "Feature",
  "properties": {
    "iso:country":"US",
    "sg:address":"3826 Troup Hwy",
    "sg:city":"Tyler",
    "sg:classifiers":[
        {
            "category":"Shopping",
            "subcategory":"Discount & Variety Stores",
            "type":"Retail Goods"
        }
    ],
    "sg:phone":"+1 903 534 8121",
    "sg:postcode":"75703",
    "sg:province":"TX",
    "wof:name":"Dollar Tree",
    "wof:placetype":"venue"
},
  "geometry": {"coordinates":[-95.272228,32.308243],"type":"Point"}
}