{
  "type": "Feature",
  "properties": {
    "iso:country":"US",
    "sg:address":"4033 Oak Arbor Dr",
    "sg:city":"Dallas",
    "sg:classifiers":[
        {
            "category":"Building & Trades",
            "subcategory":"Construction",
            "type":"Services"
        }
    ],
    "sg:phone":"+1 214 337 0622",
    "sg:postcode":"75233",
    "sg:province":"TX",
    "sg:tags":[
        "repairing",
        "carpentry",
        "contractor",
        "remodeling",
        "nonresidential"
    ],
    "wof:name":"Kountry Karpenters",
    "wof:placetype":"venue"
},
  "geometry": {"coordinates":[-96.88600599999999,32.694116],"type":"Point"}
}