{
  "type": "Feature",
  "properties": {
    "iso:country":"US",
    "sg:address":"8629 Amhurst Ct",
    "sg:city":"Fort Worth",
    "sg:classifiers":[
        {
            "category":"Professional",
            "type":"Services"
        }
    ],
    "sg:phone":"+1 817 581 3764",
    "sg:postcode":"76180",
    "sg:province":"TX",
    "wof:name":"Galler Inc",
    "wof:placetype":"venue"
},
  "geometry": {"coordinates":[-97.19864800000001,32.90468],"type":"Point"}
}