{
  "type": "Feature",
  "properties": {
    "iso:country":"US",
    "sg:address":"1610 Marilyn St",
    "sg:city":"Alvin",
    "sg:classifiers":[
        {
            "category":"Retail",
            "subcategory":"Repair Shop",
            "type":"Services"
        }
    ],
    "sg:phone":"+1 281 331 2350",
    "sg:postcode":"77511",
    "sg:province":"TX",
    "wof:name":"E&P Computer Graphics",
    "wof:placetype":"venue"
},
  "geometry": {"coordinates":[-95.32120999999999,29.342882],"type":"Point"}
}