{
  "type": "Feature",
  "properties": {
    "iso:country":"US",
    "sg:address":"101 Hays St",
    "sg:city":"Dripping Springs",
    "sg:classifiers":[
        {
            "category":"Professional",
            "subcategory":"Accounting & Tax Preparation",
            "type":"Services"
        }
    ],
    "sg:phone":"+1 512 894 4257",
    "sg:postcode":"78620",
    "sg:province":"TX",
    "sg:tags":[
        "accountant"
    ],
    "wof:name":"Roy D Pursley CPA",
    "wof:placetype":"venue"
},
  "geometry": {"coordinates":[-98.087508,30.190693],"type":"Point"}
}