{
  "type": "Feature",
  "properties": {
    "iso:country":"US",
    "sg:address":"607 N Hwy 175",
    "sg:city":"Seagoville",
    "sg:classifiers":[
        {
            "category":"Shopping",
            "subcategory":"Department Store",
            "type":"Retail Goods"
        }
    ],
    "sg:phone":"+1 972 287 0300",
    "sg:postcode":"75159",
    "sg:province":"TX",
    "sg:tags":[
        "shop"
    ],
    "wof:name":"Dollar General",
    "wof:placetype":"venue"
},
  "geometry": {"coordinates":[-96.543891,32.648858],"type":"Point"}
}