{
  "type": "Feature",
  "properties": {
    "iso:country":"US",
    "sg:address":"6321 Carrizo Dr",
    "sg:city":"Granbury",
    "sg:classifiers":[
        {
            "category":"Building & Trades",
            "subcategory":"Construction",
            "type":"Services"
        }
    ],
    "sg:phone":"+1 817 705 7383",
    "sg:postcode":"76049",
    "sg:province":"TX",
    "sg:tags":[
        "roofing",
        "contractor"
    ],
    "sg:website":"http://www.dtroofing.net",
    "wof:name":"DT Roofing",
    "wof:placetype":"venue"
},
  "geometry": {"coordinates":[-97.690341,32.436196],"type":"Point"}
}