{
  "type": "Feature",
  "properties": {
    "iso:country":"US",
    "sg:address":"1307 W Abram St",
    "sg:city":"Arlington",
    "sg:classifiers":[
        {
            "category":"Professional",
            "type":"Services"
        }
    ],
    "sg:phone":"+1 817 460 8060",
    "sg:postcode":"76013",
    "sg:province":"TX",
    "wof:name":"Ruddys Horse Heaven Roun",
    "wof:placetype":"venue"
},
  "geometry": {"coordinates":[-97.12758700000001,32.735888],"type":"Point"}
}