{
  "type": "Feature",
  "properties": {
    "iso:country":"US",
    "sg:address":"202 N Oak St",
    "sg:city":"Pearsall",
    "sg:classifiers":[
        {
            "category":"Shopping",
            "type":"Retail Goods"
        }
    ],
    "sg:phone":"+1 830 334 8305",
    "sg:postcode":"78061",
    "sg:province":"TX",
    "sg:tags":[
        "merchandise"
    ],
    "wof:name":"Galaxy Wireless",
    "wof:placetype":"venue"
},
  "geometry": {"coordinates":[-99.094532,28.893936],"type":"Point"}
}