{
  "type": "Feature",
  "properties": {
    "iso:country":"US",
    "sg:address":"6601 Auburndale St",
    "sg:city":"Austin",
    "sg:classifiers":[
        {
            "category":"Personal",
            "subcategory":"Massage",
            "type":"Services"
        }
    ],
    "sg:phone":"+1 512 926 7312",
    "sg:postcode":"78723",
    "sg:province":"TX",
    "wof:name":"Owl S Flight Massage, Pllc",
    "wof:placetype":"venue"
},
  "geometry": {"coordinates":[-97.67530600000001,30.313063],"type":"Point"}
}