{
  "type": "Feature",
  "properties": {
    "iso:country":"US",
    "sg:address":"19702 FM 1093",
    "sg:city":"Richmond",
    "sg:classifiers":[
        {
            "category":"Retail",
            "subcategory":"Laundry & Dry Cleaning",
            "type":"Services"
        }
    ],
    "sg:phone":"+1 281 829 2266",
    "sg:postcode":"77469",
    "sg:province":"TX",
    "sg:tags":[
        "cleaners"
    ],
    "wof:name":"Sunshine Cleaners",
    "wof:placetype":"venue"
},
  "geometry": {"coordinates":[-95.730383,29.704214],"type":"Point"}
}