{
  "type": "Feature",
  "properties": {
    "iso:country":"US",
    "sg:address":"12536 Westheimer Rd",
    "sg:city":"Houston",
    "sg:classifiers":[
        {
            "category":"Personal",
            "subcategory":"Beauty Salon",
            "type":"Services"
        }
    ],
    "sg:phone":"+1 713 339 1247",
    "sg:postcode":"77077",
    "sg:province":"TX",
    "wof:name":"Elaine's Salon",
    "wof:placetype":"venue"
},
  "geometry": {"coordinates":[-95.604242,29.736221],"type":"Point"}
}