{
  "type": "Feature",
  "properties": {
    "iso:country":"US",
    "sg:address":"12240 Murphy Rd Ste J",
    "sg:city":"Stafford",
    "sg:classifiers":[
        {
            "category":"Health Services",
            "subcategory":"Doctor",
            "type":"Services"
        },
        {
            "category":"Arena",
            "subcategory":"Sports Club",
            "type":"Entertainment"
        }
    ],
    "sg:phone":"+1 281 983 9901",
    "sg:postcode":"77477",
    "sg:province":"TX",
    "sg:tags":[
        "martial art"
    ],
    "wof:name":"Traditional Tang Soo DO",
    "wof:placetype":"venue"
},
  "geometry": {"coordinates":[-95.56549800000001,29.645599],"type":"Point"}
}