{
  "type": "Feature",
  "properties": {
    "iso:country":"US",
    "sg:address":"2714 Belt Loop",
    "sg:city":"Killeen",
    "sg:classifiers":[
        {
            "category":"Organizations",
            "subcategory":"Religious Organization",
            "type":"Services"
        }
    ],
    "sg:phone":"+1 254 466 6193",
    "sg:postcode":"76543",
    "sg:province":"TX",
    "wof:name":"Calvary Fellowship",
    "wof:placetype":"venue"
},
  "geometry": {"coordinates":[-97.696381,31.136267],"type":"Point"}
}