{
  "type": "Feature",
  "properties": {
    "iso:country":"US",
    "sg:address":"2500 Federal Ave",
    "sg:city":"El Paso",
    "sg:classifiers":[
        {
            "category":"Shopping",
            "type":"Retail Goods"
        }
    ],
    "sg:phone":"+1 915 309 5120",
    "sg:postcode":"79930",
    "sg:province":"TX",
    "sg:tags":[
        "merchandise"
    ],
    "wof:name":"Fish On Go",
    "wof:placetype":"venue"
},
  "geometry": {"coordinates":[-106.465958,31.791382],"type":"Point"}
}