{
  "type": "Feature",
  "properties": {
    "iso:country":"US",
    "sg:address":"1907 Hether St Unit B",
    "sg:city":"Austin",
    "sg:classifiers":[
        {
            "category":"Wholesale",
            "subcategory":"Non-durable Goods",
            "type":"Manufacturing & Wholesale Goods"
        }
    ],
    "sg:phone":"+1 512 382 7593",
    "sg:postcode":"78704",
    "sg:province":"TX",
    "sg:tags":[
        "dry",
        "goods-wholesale"
    ],
    "wof:name":"Orion Surgical Supply",
    "wof:placetype":"venue"
},
  "geometry": {"coordinates":[-97.77253899999999,30.252165],"type":"Point"}
}