{
  "type": "Feature",
  "properties": {
    "iso:country":"US",
    "sg:address":"2121 N Grand Blvd",
    "sg:city":"Pearland",
    "sg:classifiers":[
        {
            "category":"Social Services",
            "subcategory":"Child Care",
            "type":"Services"
        }
    ],
    "sg:phone":"+1 281 485 3567",
    "sg:postcode":"77581",
    "sg:province":"TX",
    "sg:tags":[
        "montessori",
        "school"
    ],
    "wof:name":"Montessori School Of Downtown",
    "wof:placetype":"venue"
},
  "geometry": {"coordinates":[-95.283901,29.568897],"type":"Point"}
}