{
  "type": "Feature",
  "properties": {
    "iso:country":"US",
    "sg:address":"5004 48th St",
    "sg:city":"Lubbock",
    "sg:classifiers":[
        {
            "category":"Professional",
            "subcategory":"Lawyer & Legal Services",
            "type":"Services"
        }
    ],
    "sg:phone":"+1 806 722 2007",
    "sg:postcode":"79414",
    "sg:province":"TX",
    "sg:tags":[
        "attorney"
    ],
    "wof:name":"Kyle Walker Attorney",
    "wof:placetype":"venue"
},
  "geometry": {"coordinates":[-101.92015600000001,33.550724],"type":"Point"}
}