{
  "type": "Feature",
  "properties": {
    "iso:country":"US",
    "sg:address":"16843 Fm 2493",
    "sg:city":"Tyler",
    "sg:classifiers":[
        {
            "category":"Autos & Motor Vehicles",
            "subcategory":"Automobile Sales",
            "type":"Retail Goods"
        }
    ],
    "sg:phone":"+1 903 534 5459",
    "sg:postcode":"75703",
    "sg:province":"TX",
    "sg:tags":[
        "dealers-used",
        "car",
        "used",
        "cars-wholesale"
    ],
    "wof:name":"Cars On Broadway",
    "wof:placetype":"venue"
},
  "geometry": {"coordinates":[-95.34899,32.235137],"type":"Point"}
}