{
  "type": "Feature",
  "properties": {
    "iso:country":"US",
    "sg:address":"210 W del Mar Blvd",
    "sg:city":"Laredo",
    "sg:classifiers":[
        {
            "category":"Insurance",
            "subcategory":"Insurance Agent",
            "type":"Services"
        }
    ],
    "sg:phone":"+1 956 718 0007",
    "sg:postcode":"78041",
    "sg:province":"TX",
    "wof:name":"Fred Loya Insurance",
    "wof:placetype":"venue"
},
  "geometry": {"coordinates":[-99.496681,27.567954],"type":"Point"}
}