{
  "type": "Feature",
  "properties": {
    "iso:country":"US",
    "sg:address":"710 W Phillips Rd",
    "sg:city":"Angleton",
    "sg:classifiers":[
        {
            "category":"Building & Trades",
            "subcategory":"Electrical",
            "type":"Services"
        },
        {
            "category":"Building & Trades",
            "subcategory":"Construction",
            "type":"Services"
        }
    ],
    "sg:phone":"+1 979 849 1719",
    "sg:postcode":"77515",
    "sg:province":"TX",
    "sg:tags":[
        "home",
        "improvement",
        "electric",
        "contractor"
    ],
    "wof:name":"R G Electrical Svc",
    "wof:placetype":"venue"
},
  "geometry": {"coordinates":[-95.43925,29.137246],"type":"Point"}
}