{
  "type": "Feature",
  "properties": {
    "iso:country":"US",
    "sg:address":"3609 Bond St",
    "sg:city":"Rowlett",
    "sg:classifiers":[
        {
            "category":"Government",
            "subcategory":"Office",
            "type":"Public Place"
        }
    ],
    "sg:phone":"+1 972 475 7305",
    "sg:postcode":"75088",
    "sg:province":"TX",
    "sg:tags":[
        "management"
    ],
    "wof:name":"Douglas K Bales",
    "wof:placetype":"venue"
},
  "geometry": {"coordinates":[-96.57616899999999,32.894428],"type":"Point"}
}