{
  "type": "Feature",
  "properties": {
    "iso:country":"US",
    "sg:address":"303 N Waco St",
    "sg:city":"Hillsboro",
    "sg:classifiers":[
        {
            "category":"Organizations",
            "subcategory":"Non-profit Organization",
            "type":"Services"
        }
    ],
    "sg:phone":"+1 254 582 7426",
    "sg:postcode":"76645",
    "sg:province":"TX",
    "sg:tags":[
        "program",
        "prevention",
        "crime"
    ],
    "wof:name":"Crime Stoppers",
    "wof:placetype":"venue"
},
  "geometry": {"coordinates":[-97.130152,32.015947],"type":"Point"}
}