{
  "type": "Feature",
  "properties": {
    "iso:country":"US",
    "sg:address":"10509 Burnet Rd",
    "sg:city":"Austin",
    "sg:classifiers":[
        {
            "category":"Building & Trades",
            "subcategory":"Equipment Rental",
            "type":"Services"
        }
    ],
    "sg:phone":"+1 512 836 9100",
    "sg:postcode":"78758",
    "sg:province":"TX",
    "wof:name":"Rent Equip Inc",
    "wof:placetype":"venue"
},
  "geometry": {"coordinates":[-97.723631,30.385485],"type":"Point"}
}