{
  "type": "Feature",
  "properties": {
    "iso:country":"US",
    "sg:address":"4305 W Illinois Ave",
    "sg:city":"Midland",
    "sg:classifiers":[
        {
            "category":"Restaurant",
            "type":"Food & Drink"
        }
    ],
    "sg:phone":"+1 432 689 4134",
    "sg:postcode":"79703",
    "sg:province":"TX",
    "wof:name":"Cocina Economica",
    "wof:placetype":"venue"
},
  "geometry": {"coordinates":[-102.132266,31.987762],"type":"Point"}
}