{
  "type": "Feature",
  "properties": {
    "iso:country":"US",
    "sg:address":"3210 Miller Ave",
    "sg:city":"Fort Worth",
    "sg:classifiers":[
        {
            "category":"Government",
            "subcategory":"Jail",
            "type":"Public Place"
        }
    ],
    "sg:phone":"+1 817 531 5601",
    "sg:postcode":"76119",
    "sg:province":"TX",
    "sg:tags":[
        "correctional",
        "institution"
    ],
    "wof:name":"Community Supervision",
    "wof:placetype":"venue"
},
  "geometry": {"coordinates":[-97.262947,32.712448],"type":"Point"}
}