{
  "type": "Feature",
  "properties": {
    "iso:country":"US",
    "sg:address":"725 McDivitt Dr",
    "sg:city":"Garland",
    "sg:classifiers":[
        {
            "category":"Professional",
            "subcategory":"Engineering",
            "type":"Services"
        }
    ],
    "sg:phone":"+1 972 495 4151",
    "sg:postcode":"75040",
    "sg:province":"TX",
    "wof:name":"Hawk Engineering",
    "wof:placetype":"venue"
},
  "geometry": {"coordinates":[-96.62359600000001,32.931622],"type":"Point"}
}