{
  "type": "Feature",
  "properties": {
    "iso:country":"US",
    "sg:address":"6030 Jacksboro Hwy",
    "sg:city":"Fort Worth",
    "sg:classifiers":[
        {
            "category":"Insurance",
            "subcategory":"Insurance Agent",
            "type":"Services"
        }
    ],
    "sg:phone":"+1 817 237 8282",
    "sg:postcode":"76135",
    "sg:province":"TX",
    "wof:name":"Al Boenker Insurance Agency",
    "wof:placetype":"venue"
},
  "geometry": {"coordinates":[-97.412969,32.804923],"type":"Point"}
}