{
  "type": "Feature",
  "properties": {
    "iso:country":"US",
    "sg:address":"1126 W BUSINESS",
    "sg:city":"Harlingen",
    "sg:classifiers":[
        {
            "category":"Shopping",
            "subcategory":"Department Store",
            "type":"Retail Goods"
        },
        {
            "category":"Shopping",
            "subcategory":"Clothing, Apparel, & Fashions",
            "type":"Retail Goods"
        },
        {
            "category":"Shopping",
            "subcategory":"Discount & Variety Stores",
            "type":"Retail Goods"
        },
        {
            "category":"Food & Beverages",
            "subcategory":"Supermarket",
            "type":"Retail Goods"
        },
        {
            "category":"Shopping",
            "type":"Retail Goods"
        }
    ],
    "sg:phone":"+1 956 777 8586",
    "sg:postcode":"78550",
    "sg:province":"TX",
    "sg:tags":[
        "clothing",
        "super",
        "merchandise"
    ],
    "sg:website":"http://www.walmart.com",
    "wof:name":"Wal-Mart Supercenter",
    "wof:placetype":"venue"
},
  "geometry": {"coordinates":[-97.703239,26.219465],"type":"Point"}
}