{
  "type": "Feature",
  "properties": {
    "iso:country":"US",
    "sg:address":"28 Cleveland St",
    "sg:city":"Texarkana",
    "sg:classifiers":[
        {
            "category":"Organizations",
            "subcategory":"Religious Organization",
            "type":"Services"
        }
    ],
    "sg:phone":"+1 870 772 8075",
    "sg:postcode":"71854",
    "sg:province":"TX",
    "sg:tags":[
        "church"
    ],
    "wof:name":"Halls United Mthodist Church",
    "wof:placetype":"venue"
},
  "geometry": {"coordinates":[-94.022426,33.421471],"type":"Point"}
}