{
  "type": "Feature",
  "properties": {
    "iso:country":"US",
    "sg:address":"3208 FM 528",
    "sg:city":"Friendswood",
    "sg:classifiers":[
        {
            "category":"Education",
            "subcategory":"Vocational School",
            "type":"Public Place"
        }
    ],
    "sg:phone":"+1 281 648 0880",
    "sg:postcode":"77546",
    "sg:province":"TX",
    "sg:website":"www.tsb.edu",
    "wof:name":"Texas School Of Business",
    "wof:placetype":"venue"
},
  "geometry": {"coordinates":[-95.222634,29.471168],"type":"Point"}
}