{
  "type": "Feature",
  "properties": {
    "iso:country":"US",
    "sg:address":"119 W 3rd St",
    "sg:city":"Taylor",
    "sg:classifiers":[
        {
            "category":"Manufacturing",
            "subcategory":"Printing",
            "type":"Manufacturing & Wholesale Goods"
        }
    ],
    "sg:phone":"+1 512 352 5568",
    "sg:postcode":"76574",
    "sg:province":"TX",
    "sg:tags":[
        "commercial"
    ],
    "wof:name":"Taylor Office Products Inc",
    "wof:placetype":"venue"
},
  "geometry": {"coordinates":[-97.409767,30.56959],"type":"Point"}
}