{
  "type": "Feature",
  "properties": {
    "iso:country":"US",
    "sg:address":"2300 Grayson Dr",
    "sg:city":"Grapevine",
    "sg:classifiers":[
        {
            "category":"Retail",
            "subcategory":"Repair Shop",
            "type":"Services"
        }
    ],
    "sg:phone":"+1 817 488 1063",
    "sg:postcode":"76051",
    "sg:province":"TX",
    "sg:tags":[
        "equipment",
        "conditioning",
        "air"
    ],
    "wof:name":"Excell A/C Heating",
    "wof:placetype":"venue"
},
  "geometry": {"coordinates":[-97.100697,32.913189],"type":"Point"}
}