{
  "type": "Feature",
  "properties": {
    "iso:country":"US",
    "sg:address":"2009 W Wheeler Ave",
    "sg:city":"Aransas Pass",
    "sg:classifiers":[
        {
            "category":"Shopping",
            "type":"Retail Goods"
        }
    ],
    "sg:phone":"+1 361 758 2603",
    "sg:postcode":"78336",
    "sg:province":"TX",
    "sg:tags":[
        "picture",
        "frame"
    ],
    "wof:name":"Treasured Times",
    "wof:placetype":"venue"
},
  "geometry": {"coordinates":[-97.16528,27.917858],"type":"Point"}
}