{
  "type": "Feature",
  "properties": {
    "iso:country":"US",
    "sg:address":"611 US Hwy 77 Alt",
    "sg:city":"Yoakum",
    "sg:classifiers":[
        {
            "category":"Food & Beverages",
            "subcategory":"Groceries & Convenience Stores",
            "type":"Retail Goods"
        }
    ],
    "sg:phone":"+1 361 293 7948",
    "sg:postcode":"77995",
    "sg:province":"TX",
    "wof:name":"Store",
    "wof:placetype":"venue"
},
  "geometry": {"coordinates":[-97.159888,29.296881],"type":"Point"}
}