{
  "type": "Feature",
  "properties": {
    "iso:country":"US",
    "sg:address":"2701 Ave E E",
    "sg:city":"Arlington",
    "sg:classifiers":[
        {
            "category":"Real Estate",
            "subcategory":"Real Estate Agent",
            "type":"Services"
        }
    ],
    "sg:phone":"+1 817 640 4223",
    "sg:postcode":"76011",
    "sg:province":"TX",
    "sg:tags":[
        "management"
    ],
    "wof:name":"Gateway Plaza",
    "wof:placetype":"venue"
},
  "geometry": {"coordinates":[-97.059989,32.756504],"type":"Point"}
}