{
  "type": "Feature",
  "properties": {
    "iso:country":"US",
    "sg:address":"6427 Lynngate Dr",
    "sg:city":"Spring",
    "sg:classifiers":[
        {
            "category":"Professional",
            "type":"Services"
        }
    ],
    "sg:phone":"+1 281 859 7815",
    "sg:postcode":"77373",
    "sg:province":"TX",
    "wof:name":"Our Glass",
    "wof:placetype":"venue"
},
  "geometry": {"coordinates":[-95.328829,30.039378],"type":"Point"}
}