{
  "type": "Feature",
  "properties": {
    "iso:country":"US",
    "sg:address":"3409 Worth St",
    "sg:city":"Dallas",
    "sg:classifiers":[
        {
            "category":"Health Services",
            "subcategory":"Doctor",
            "type":"Services"
        }
    ],
    "sg:phone":"+1 214 826 3370",
    "sg:postcode":"75246",
    "sg:province":"TX",
    "sg:tags":[
        "physician",
        "surgeon"
    ],
    "wof:name":"North Texas Infectious Disease",
    "wof:placetype":"venue"
},
  "geometry": {"coordinates":[-96.77919,32.7885],"type":"Point"}
}