{
  "type": "Feature",
  "properties": {
    "iso:country":"US",
    "sg:address":"5829 Sam Houston Pkwy",
    "sg:city":"Houston",
    "sg:classifiers":[
        {
            "category":"Home & Garden",
            "subcategory":"Building Materials",
            "type":"Retail Goods"
        }
    ],
    "sg:phone":"+1 832 467 9993",
    "sg:postcode":"77049",
    "sg:province":"TX",
    "sg:tags":[
        "lumber"
    ],
    "wof:name":"Lumber Liquidators",
    "wof:placetype":"venue"
},
  "geometry": {"coordinates":[-95.163325,29.809375],"type":"Point"}
}