{
  "type": "Feature",
  "properties": {
    "iso:country":"US",
    "sg:address":"1506 E 10th Ave",
    "sg:city":"Amarillo",
    "sg:classifiers":[
        {
            "category":"Shopping",
            "subcategory":"Used Merchandise",
            "type":"Retail Goods"
        }
    ],
    "sg:phone":"+1 806 376 4394",
    "sg:postcode":"79102",
    "sg:province":"TX",
    "wof:name":"Erwins Pawn Shop",
    "wof:placetype":"venue"
},
  "geometry": {"coordinates":[-101.82044999999999,35.201058],"type":"Point"}
}