{
  "type": "Feature",
  "properties": {
    "iso:country":"US",
    "sg:address":"700 Highlander Blvd",
    "sg:city":"Arlington",
    "sg:classifiers":[
        {
            "category":"Banks & Credit Unions",
            "subcategory":"Bank",
            "type":"Services"
        }
    ],
    "sg:phone":"+1 817 548 4705",
    "sg:postcode":"76015",
    "sg:province":"TX",
    "sg:tags":[
        "depository",
        "banking"
    ],
    "wof:name":"Ifmx International Money Exch",
    "wof:placetype":"venue"
},
  "geometry": {"coordinates":[-97.117226,32.682151],"type":"Point"}
}