{
  "type": "Feature",
  "properties": {
    "iso:country":"US",
    "sg:address":"3105 Fox Meadow Trl",
    "sg:city":"Grand Prairie",
    "sg:classifiers":[
        {
            "category":"Real Estate",
            "subcategory":"Real Estate Operator",
            "type":"Services"
        }
    ],
    "sg:phone":"+1 972 602 8075",
    "sg:postcode":"75052",
    "sg:province":"TX",
    "sg:tags":[
        "building",
        "nonresidential"
    ],
    "wof:name":"Strong Property",
    "wof:placetype":"venue"
},
  "geometry": {"coordinates":[-97.02913100000001,32.696362],"type":"Point"}
}