{
  "type": "Feature",
  "properties": {
    "iso:country":"US",
    "sg:address":"8317 Andrews Hwy",
    "sg:city":"Odessa",
    "sg:classifiers":[
        {
            "category":"Manufacturing",
            "subcategory":"Rubber & Plastics",
            "type":"Manufacturing & Wholesale Goods"
        }
    ],
    "sg:phone":"+1 432 337 1452",
    "sg:postcode":"79765",
    "sg:province":"TX",
    "sg:tags":[
        "supply"
    ],
    "wof:name":"Triple M Oil Tool Inc",
    "wof:placetype":"venue"
},
  "geometry": {"coordinates":[-102.40030299999999,31.929222],"type":"Point"}
}