{
  "type": "Feature",
  "properties": {
    "iso:country":"US",
    "sg:address":"6819 Atwell Dr",
    "sg:city":"Houston",
    "sg:classifiers":[
        {
            "category":"Retail",
            "subcategory":"Auto Repair",
            "type":"Services"
        }
    ],
    "sg:phone":"+1 713 665 6582",
    "sg:postcode":"77081",
    "sg:province":"TX",
    "sg:tags":[
        "body",
        "shop"
    ],
    "wof:name":"Allstate Auto & Body",
    "wof:placetype":"venue"
},
  "geometry": {"coordinates":[-95.482399,29.7052],"type":"Point"}
}