{
  "type": "Feature",
  "properties": {
    "iso:country":"US",
    "sg:address":"8234 Broadway",
    "sg:city":"San Antonio",
    "sg:classifiers":[
        {
            "category":"Restaurant",
            "type":"Food & Drink"
        }
    ],
    "sg:phone":"+1 210 829 0180",
    "sg:postcode":"78209",
    "sg:province":"TX",
    "sg:tags":[
        "eating"
    ],
    "wof:name":"Taqueria Ballarta",
    "wof:placetype":"venue"
},
  "geometry": {"coordinates":[-98.46602900000001,29.512916],"type":"Point"}
}