{
  "type": "Feature",
  "properties": {
    "iso:country":"US",
    "sg:address":"9534 Beckleyview Ave",
    "sg:city":"Dallas",
    "sg:classifiers":[
        {
            "category":"Manufacturing",
            "subcategory":"Retail Goods",
            "type":"Manufacturing & Wholesale Goods"
        }
    ],
    "sg:phone":"+1 972 224 2594",
    "sg:postcode":"75232",
    "sg:province":"TX",
    "sg:tags":[
        "marking",
        "devices",
        "merchandise",
        "mfg"
    ],
    "wof:name":"Precision Rubber Stamp Gr",
    "wof:placetype":"venue"
},
  "geometry": {"coordinates":[-96.83210099999999,32.631493],"type":"Point"}
}