{
  "type": "Feature",
  "properties": {
    "iso:country":"US",
    "sg:address":"1616 Mockingbird Ln",
    "sg:city":"Desoto",
    "sg:classifiers":[
        {
            "category":"Professional",
            "subcategory":"Art Services",
            "type":"Services"
        }
    ],
    "sg:phone":"+1 972 230 8819",
    "sg:postcode":"75115",
    "sg:province":"TX",
    "sg:tags":[
        "graphic",
        "commercial",
        "designer",
        "artist"
    ],
    "wof:name":"Sisters",
    "wof:placetype":"venue"
},
  "geometry": {"coordinates":[-96.84161400000001,32.566319],"type":"Point"}
}