{
  "type": "Feature",
  "properties": {
    "iso:country":"US",
    "sg:address":"34 Fairway Oaks Blvd",
    "sg:city":"Abilene",
    "sg:classifiers":[
        {
            "category":"Sports & Exercise",
            "subcategory":"Golf",
            "type":"Entertainment"
        }
    ],
    "sg:phone":"+1 325 698 4971",
    "sg:postcode":"79606",
    "sg:province":"TX",
    "sg:tags":[
        "course"
    ],
    "wof:name":"Fairway Oaks Country Club",
    "wof:placetype":"venue"
},
  "geometry": {"coordinates":[-99.759683,32.376402],"type":"Point"}
}