{
  "type": "Feature",
  "properties": {
    "iso:country":"US",
    "sg:address":"2395 E Saunders St",
    "sg:city":"Laredo",
    "sg:classifiers":[
        {
            "category":"Shopping",
            "subcategory":"Computers & Home Electronics",
            "type":"Retail Goods"
        }
    ],
    "sg:phone":"+1 956 725 0282",
    "sg:postcode":"78041",
    "sg:province":"TX",
    "sg:tags":[
        "equipment",
        "electronic",
        "supply"
    ],
    "wof:name":"Radio Shack",
    "wof:placetype":"venue"
},
  "geometry": {"coordinates":[-99.471835,27.530456],"type":"Point"}
}