{
  "type": "Feature",
  "properties": {
    "iso:country":"US",
    "sg:address":"502 W Pike Blvd",
    "sg:city":"Weslaco",
    "sg:classifiers":[
        {
            "category":"Restaurant",
            "type":"Food & Drink"
        }
    ],
    "sg:phone":"+1 956 968 1777",
    "sg:postcode":"78596",
    "sg:province":"TX",
    "wof:name":"Casa De Marisco",
    "wof:placetype":"venue"
},
  "geometry": {"coordinates":[-97.99532499999999,26.169944],"type":"Point"}
}