{
  "type": "Feature",
  "properties": {
    "iso:country":"US",
    "sg:address":"9819 Penton Dr",
    "sg:city":"Sugar Land",
    "sg:classifiers":[
        {
            "category":"Shopping",
            "subcategory":"Florist",
            "type":"Retail Goods"
        }
    ],
    "sg:phone":"+1 281 558 2100",
    "sg:postcode":"77478",
    "sg:province":"TX",
    "sg:tags":[
        "floral",
        "shop"
    ],
    "wof:name":"Memorial Florist",
    "wof:placetype":"venue"
},
  "geometry": {"coordinates":[-95.644884,29.669246],"type":"Point"}
}