{
  "type": "Feature",
  "properties": {
    "iso:country":"US",
    "sg:address":"9950 Memorial Blvd",
    "sg:city":"Humble",
    "sg:classifiers":[
        {
            "category":"Health Services",
            "subcategory":"Clinic",
            "type":"Services"
        }
    ],
    "sg:phone":"+1 281 973 4858",
    "sg:postcode":"77338",
    "sg:province":"TX",
    "sg:tags":[
        "medical",
        "welfare"
    ],
    "wof:name":"North Houston Respiratory Consultants PA",
    "wof:placetype":"venue"
},
  "geometry": {"coordinates":[-95.273602,29.993885],"type":"Point"}
}