{
  "type": "Feature",
  "properties": {
    "iso:country":"US",
    "sg:address":"3408 Orchid Ln",
    "sg:city":"Rowlett",
    "sg:classifiers":[
        {
            "category":"Professional",
            "subcategory":"Research",
            "type":"Services"
        }
    ],
    "sg:phone":"+1 972 412 8760",
    "sg:postcode":"75089",
    "sg:province":"TX",
    "sg:tags":[
        "marketing",
        "consulting"
    ],
    "wof:name":"Mpi Research",
    "wof:placetype":"venue"
},
  "geometry": {"coordinates":[-96.570148,32.915545],"type":"Point"}
}