{
  "type": "Feature",
  "properties": {
    "iso:country":"US",
    "sg:address":"4916 Laurel St",
    "sg:city":"Bellaire",
    "sg:classifiers":[
        {
            "category":"Professional",
            "subcategory":"Management & Consulting",
            "type":"Services"
        }
    ],
    "sg:phone":"+1 713 839 8788",
    "sg:postcode":"77401",
    "sg:province":"TX",
    "sg:tags":[
        "public",
        "relations"
    ],
    "wof:name":"S A McHugh Company",
    "wof:placetype":"venue"
},
  "geometry": {"coordinates":[-95.466425,29.70359],"type":"Point"}
}