{
  "type": "Feature",
  "properties": {
    "iso:country":"US",
    "sg:address":"2950 Turtle Creek Dr",
    "sg:city":"Port Arthur",
    "sg:classifiers":[
        {
            "category":"Real Estate",
            "subcategory":"Real Estate Services",
            "type":"Services"
        }
    ],
    "sg:phone":"+1 409 727 8871",
    "sg:postcode":"77642",
    "sg:province":"TX",
    "sg:tags":[
        "company",
        "abstract",
        "title"
    ],
    "wof:name":"Port Arthur Abstract Title Co",
    "wof:placetype":"venue"
},
  "geometry": {"coordinates":[-93.98708499999999,29.94257],"type":"Point"}
}