{
  "type": "Feature",
  "properties": {
    "iso:country":"US",
    "sg:address":"6363 Woodway Dr",
    "sg:city":"Houston",
    "sg:classifiers":[
        {
            "category":"Professional",
            "subcategory":"Art Services",
            "type":"Services"
        }
    ],
    "sg:phone":"+1 713 782 9110",
    "sg:postcode":"77057",
    "sg:province":"TX",
    "sg:tags":[
        "graphic",
        "designer"
    ],
    "wof:name":"Lance Brown Design Inc",
    "wof:placetype":"venue"
},
  "geometry": {"coordinates":[-95.49775,29.755648],"type":"Point"}
}