{
  "type": "Feature",
  "properties": {
    "iso:country":"US",
    "sg:address":"6619 Martin Luther King Jr Blvd",
    "sg:city":"Houston",
    "sg:classifiers":[
        {
            "category":"Real Estate",
            "subcategory":"Real Estate Agent",
            "type":"Services"
        }
    ],
    "sg:phone":"+1 713 734 5151",
    "sg:postcode":"77033",
    "sg:province":"TX",
    "wof:name":"Newbuyers Real Estate",
    "wof:placetype":"venue"
},
  "geometry": {"coordinates":[-95.33975599999999,29.682609],"type":"Point"}
}