{
  "type": "Feature",
  "properties": {
    "iso:country":"US",
    "sg:address":"2401 Grandview Dr",
    "sg:city":"Richardson",
    "sg:classifiers":[
        {
            "category":"Real Estate",
            "subcategory":"Architect",
            "type":"Services"
        }
    ],
    "sg:phone":"+1 972 235 6171",
    "sg:postcode":"75080",
    "sg:province":"TX",
    "sg:tags":[
        "architectural"
    ],
    "wof:name":"Dan W Lee & Associates",
    "wof:placetype":"venue"
},
  "geometry": {"coordinates":[-96.726062,32.983697],"type":"Point"}
}