{
  "type": "Feature",
  "properties": {
    "iso:country":"US",
    "sg:address":"6402 W FM 1462",
    "sg:city":"Rosharon",
    "sg:classifiers":[
        {
            "category":"Manufacturing",
            "subcategory":"Retail Goods",
            "type":"Manufacturing & Wholesale Goods"
        }
    ],
    "sg:phone":"+1 281 369 3234",
    "sg:postcode":"77583",
    "sg:province":"TX",
    "sg:tags":[
        "product",
        "mfg"
    ],
    "wof:name":"Delightful Scents",
    "wof:placetype":"venue"
},
  "geometry": {"coordinates":[-95.560581,29.350477],"type":"Point"}
}