{
  "type": "Feature",
  "properties": {
    "iso:country":"US",
    "sg:address":"633 6th St",
    "sg:city":"Honey Grove",
    "sg:classifiers":[
        {
            "category":"Government",
            "subcategory":"Office",
            "type":"Public Place"
        }
    ],
    "sg:phone":"+1 903 378 2222",
    "sg:postcode":"75446",
    "sg:province":"TX",
    "sg:tags":[
        "city"
    ],
    "wof:name":"Police Department",
    "wof:placetype":"venue"
},
  "geometry": {"coordinates":[-95.909252,33.584438],"type":"Point"}
}