{
  "type": "Feature",
  "properties": {
    "iso:country":"US",
    "sg:address":"2404 Roosevelt Dr",
    "sg:city":"Arlington",
    "sg:classifiers":[
        {
            "category":"Professional",
            "subcategory":"Business Services",
            "type":"Services"
        },
        {
            "category":"Retail",
            "subcategory":"Auto Repair",
            "type":"Services"
        }
    ],
    "sg:phone":"+1 817 860 1805",
    "sg:postcode":"76016",
    "sg:province":"TX",
    "sg:tags":[
        "repairing",
        "automobile"
    ],
    "wof:name":"Sigman Automotive LLC",
    "wof:placetype":"venue"
},
  "geometry": {"coordinates":[-97.155998,32.70491],"type":"Point"}
}