{
  "type": "Feature",
  "properties": {
    "iso:country":"US",
    "sg:address":"5765 Co Rd 570",
    "sg:city":"Farmersville",
    "sg:classifiers":[
        {
            "category":"Real Estate",
            "subcategory":"Real Estate Operator",
            "type":"Services"
        }
    ],
    "sg:phone":"+1 972 736 2785",
    "sg:postcode":"75442",
    "sg:province":"TX",
    "sg:tags":[
        "property",
        "lessor"
    ],
    "wof:name":"Johnnie McTee",
    "wof:placetype":"venue"
},
  "geometry": {"coordinates":[-96.420391,33.242095],"type":"Point"}
}