{
  "type": "Feature",
  "properties": {
    "iso:country":"US",
    "sg:address":"510 W Austin St",
    "sg:city":"Kermit",
    "sg:classifiers":[
        {
            "category":"Retail",
            "subcategory":"Repair Shop",
            "type":"Services"
        }
    ],
    "sg:phone":"+1 432 586 3391",
    "sg:postcode":"79745",
    "sg:province":"TX",
    "sg:tags":[
        "upholsterer"
    ],
    "wof:name":"Whitling's Trim & Upholstery",
    "wof:placetype":"venue"
},
  "geometry": {"coordinates":[-103.098378,31.85646],"type":"Point"}
}