{
  "type": "Feature",
  "properties": {
    "iso:country":"US",
    "sg:address":"3614 E 29th St",
    "sg:city":"Bryan",
    "sg:classifiers":[
        {
            "category":"Personal",
            "subcategory":"Beauty Salon",
            "type":"Services"
        }
    ],
    "sg:phone":"+1 979 691 2552",
    "sg:postcode":"77802",
    "sg:province":"TX",
    "wof:name":"Salon Essentials",
    "wof:placetype":"venue"
},
  "geometry": {"coordinates":[-96.33482600000001,30.64995],"type":"Point"}
}