{
  "type": "Feature",
  "properties": {
    "iso:country":"US",
    "sg:address":"3010 Bayshore Blvd",
    "sg:city":"Pasadena",
    "sg:classifiers":[
        {
            "category":"Education",
            "subcategory":"Special Training",
            "type":"Public Place"
        }
    ],
    "sg:phone":"+1 713 948 4400",
    "sg:postcode":"77502",
    "sg:province":"TX",
    "wof:name":"Guidance Center",
    "wof:placetype":"venue"
},
  "geometry": {"coordinates":[-95.18463300000001,29.666859],"type":"Point"}
}