{
  "type": "Feature",
  "properties": {
    "iso:country":"US",
    "sg:address":"2600 S Gessner Rd Ste 317",
    "sg:city":"Houston",
    "sg:classifiers":[
        {
            "category":"Shopping",
            "subcategory":"Beauty & Cosmetics",
            "type":"Retail Goods"
        }
    ],
    "sg:phone":"+1 713 467 3988",
    "sg:postcode":"77063",
    "sg:province":"TX",
    "sg:tags":[
        "perfume",
        "salons-equipment",
        "supply"
    ],
    "wof:name":"Jeanette Coon",
    "wof:placetype":"venue"
},
  "geometry": {"coordinates":[-95.53893600000001,29.737888],"type":"Point"}
}