{
  "type": "Feature",
  "properties": {
    "iso:country":"US",
    "sg:address":"105 S Bowser Rd",
    "sg:city":"Richardson",
    "sg:classifiers":[
        {
            "category":"Real Estate",
            "subcategory":"Real Estate Operator",
            "type":"Services"
        }
    ],
    "sg:phone":"+1 972 669 8333",
    "sg:postcode":"75081",
    "sg:province":"TX",
    "sg:tags":[
        "building",
        "apartment"
    ],
    "wof:name":"Heather Glen Apartments",
    "wof:placetype":"venue"
},
  "geometry": {"coordinates":[-96.7135,32.945638],"type":"Point"}
}