{
  "type": "Feature",
  "properties": {
    "iso:country":"US",
    "sg:address":"10923 Albeon Park Dr S",
    "sg:city":"San Antonio",
    "sg:classifiers":[
        {
            "category":"Real Estate",
            "subcategory":"Real Estate Agent",
            "type":"Services"
        }
    ],
    "sg:phone":"+1 210 696 8666",
    "sg:postcode":"78249",
    "sg:province":"TX",
    "wof:name":"Bogars Real Estate Services",
    "wof:placetype":"venue"
},
  "geometry": {"coordinates":[-98.642083,29.546355],"type":"Point"}
}