{
  "type": "Feature",
  "properties": {
    "iso:country":"US",
    "sg:address":"2222 Jefferson St",
    "sg:city":"Laredo",
    "sg:classifiers":[
        {
            "category":"Freight",
            "type":"Transportation"
        }
    ],
    "sg:phone":"+1 956 723 0111",
    "sg:postcode":"78040",
    "sg:province":"TX",
    "sg:website":"www.gomsa.com",
    "wof:name":"Jefferson Forwarding",
    "wof:placetype":"venue"
},
  "geometry": {"coordinates":[-99.517788,27.523763],"type":"Point"}
}