{
  "type": "Feature",
  "properties": {
    "iso:country":"US",
    "sg:address":"1001 Schriewer",
    "sg:city":"Seguin",
    "sg:classifiers":[
        {
            "category":"Wholesale",
            "subcategory":"Motor Vehicles",
            "type":"Manufacturing & Wholesale Goods"
        }
    ],
    "sg:phone":"+1 830 303 5036",
    "sg:postcode":"78155",
    "sg:province":"TX",
    "sg:tags":[
        "automobile"
    ],
    "wof:name":"Greenleaf Seguin Inc",
    "wof:placetype":"venue"
},
  "geometry": {"coordinates":[-97.94854599999999,29.594671],"type":"Point"}
}