{
  "type": "Feature",
  "properties": {
    "iso:country":"US",
    "sg:address":"4350 N Beltwood Pkwy",
    "sg:city":"Dallas",
    "sg:classifiers":[
        {
            "category":"Autos & Motor Vehicles",
            "subcategory":"Automobile Sales",
            "type":"Retail Goods"
        }
    ],
    "sg:phone":"+1 972 248 6606",
    "sg:postcode":"75244",
    "sg:province":"TX",
    "sg:tags":[
        "used",
        "legal"
    ],
    "wof:name":"Scott Hawkins PC",
    "wof:placetype":"venue"
},
  "geometry": {"coordinates":[-96.83520900000001,32.95018],"type":"Point"}
}