{
  "type": "Feature",
  "properties": {
    "iso:country":"US",
    "sg:address":"3526 FM 528",
    "sg:city":"Friendswood",
    "sg:classifiers":[
        {
            "category":"Professional",
            "subcategory":"Research",
            "type":"Services"
        }
    ],
    "sg:phone":"+1 281 482 9786",
    "sg:postcode":"77546",
    "sg:province":"TX",
    "sg:tags":[
        "development",
        "electronic"
    ],
    "wof:name":"Cooper Consulting Svc",
    "wof:placetype":"venue"
},
  "geometry": {"coordinates":[-95.167115,29.521812],"type":"Point"}
}