{
  "type": "Feature",
  "properties": {
    "iso:country":"US",
    "sg:address":"6419 Wilderness Ct",
    "sg:city":"Arlington",
    "sg:classifiers":[
        {
            "category":"Professional",
            "subcategory":"Business Services",
            "type":"Services"
        }
    ],
    "sg:phone":"+1 817 784 8394",
    "sg:postcode":"76001",
    "sg:province":"TX",
    "wof:name":"Texas Home Theater Design",
    "wof:placetype":"venue"
},
  "geometry": {"coordinates":[-97.155682,32.6418],"type":"Point"}
}