{
  "type": "Feature",
  "properties": {
    "iso:country":"US",
    "sg:address":"714 Uvalde Rd",
    "sg:city":"Houston",
    "sg:classifiers":[
        {
            "category":"Food & Beverages",
            "subcategory":"Groceries & Convenience Stores",
            "type":"Retail Goods"
        }
    ],
    "sg:phone":"+1 713 455 2410",
    "sg:postcode":"77015",
    "sg:province":"TX",
    "wof:name":"Uvalde Superette",
    "wof:placetype":"venue"
},
  "geometry": {"coordinates":[-95.18699599999999,29.7834],"type":"Point"}
}