{
  "type": "Feature",
  "properties": {
    "iso:country":"US",
    "sg:address":"6606 Ashland Dr",
    "sg:city":"Austin",
    "sg:classifiers":[
        {
            "category":"Insurance",
            "subcategory":"Insurance Agent",
            "type":"Services"
        }
    ],
    "sg:phone":"+1 512 926 4050",
    "sg:postcode":"78723",
    "sg:province":"TX",
    "wof:name":"I & S Health Claims Consultant",
    "wof:placetype":"venue"
},
  "geometry": {"coordinates":[-97.66406000000001,30.308755],"type":"Point"}
}