{
  "type": "Feature",
  "properties": {
    "iso:country":"US",
    "sg:address":"1009 S 1st St",
    "sg:city":"Muleshoe",
    "sg:classifiers":[
        {
            "category":"Retail",
            "subcategory":"Repair Shop",
            "type":"Services"
        }
    ],
    "sg:phone":"+1 806 272 4660",
    "sg:postcode":"79347",
    "sg:province":"TX",
    "sg:tags":[
        "upholsterer"
    ],
    "wof:name":"Mc Cormick's Upholstery",
    "wof:placetype":"venue"
},
  "geometry": {"coordinates":[-102.73052199999999,34.218541],"type":"Point"}
}