{
  "type": "Feature",
  "properties": {
    "iso:country":"US",
    "sg:address":"3617 Broadway Blvd",
    "sg:city":"Garland",
    "sg:classifiers":[
        {
            "category":"Social Services",
            "type":"Services"
        }
    ],
    "sg:phone":"+1 972 840 6299",
    "sg:postcode":"75043",
    "sg:province":"TX",
    "sg:tags":[
        "health"
    ],
    "wof:name":"Counseling & Social Svcs Ctr",
    "wof:placetype":"venue"
},
  "geometry": {"coordinates":[-96.612455,32.870776],"type":"Point"}
}