{
  "type": "Feature",
  "properties": {
    "iso:country":"US",
    "sg:address":"301 E Calvert Ave",
    "sg:city":"Karnes City",
    "sg:classifiers":[
        {
            "category":"Banks & Credit Unions",
            "subcategory":"Bank",
            "type":"Services"
        }
    ],
    "sg:phone":"+1 830 780 3317",
    "sg:postcode":"78118",
    "sg:province":"TX",
    "wof:name":"Karnes County National Bank",
    "wof:placetype":"venue"
},
  "geometry": {"coordinates":[-97.898983,28.884867],"type":"Point"}
}