{
  "type": "Feature",
  "properties": {
    "iso:country":"US",
    "sg:address":"202 E House St",
    "sg:city":"Alvin",
    "sg:classifiers":[
        {
            "category":"Health Services",
            "subcategory":"Doctor",
            "type":"Services"
        }
    ],
    "sg:phone":"+1 281 331 5592",
    "sg:postcode":"77511",
    "sg:province":"TX",
    "sg:tags":[
        "medical"
    ],
    "wof:name":"Memorial Hosp SE Alvin Physica",
    "wof:placetype":"venue"
},
  "geometry": {"coordinates":[-95.239481,29.418706],"type":"Point"}
}