{
  "type": "Feature",
  "properties": {
    "iso:country":"US",
    "sg:address":"230 S Texas Ave",
    "sg:city":"Mercedes",
    "sg:classifiers":[
        {
            "category":"Manufacturing",
            "subcategory":"Printing",
            "type":"Manufacturing & Wholesale Goods"
        }
    ],
    "sg:phone":"+1 956 565 2425",
    "sg:postcode":"78570",
    "sg:province":"TX",
    "sg:tags":[
        "newspaper"
    ],
    "wof:name":"Mercedes Enterprise",
    "wof:placetype":"venue"
},
  "geometry": {"coordinates":[-97.91337900000001,26.149678],"type":"Point"}
}