{
  "type": "Feature",
  "properties": {
    "iso:country":"US",
    "sg:address":"1715 Harris Dr",
    "sg:city":"College Station",
    "sg:classifiers":[
        {
            "category":"Building & Trades",
            "subcategory":"Construction",
            "type":"Services"
        }
    ],
    "sg:phone":"+1 979 690 0190",
    "sg:postcode":"77845",
    "sg:province":"TX",
    "sg:tags":[
        "house"
    ],
    "wof:name":"Greg Pound Custom Homes",
    "wof:placetype":"venue"
},
  "geometry": {"coordinates":[-96.25837300000001,30.584544],"type":"Point"}
}