{
  "type": "Feature",
  "properties": {
    "iso:country":"US",
    "sg:address":"2607 Steck Ave",
    "sg:city":"Austin",
    "sg:classifiers":[
        {
            "category":"Professional",
            "type":"Services"
        }
    ],
    "sg:phone":"+1 512 237 5998",
    "sg:postcode":"78757",
    "sg:province":"TX",
    "wof:name":"Casey Alexander Publishin",
    "wof:placetype":"venue"
},
  "geometry": {"coordinates":[-97.732601,30.363367],"type":"Point"}
}