{
  "type": "Feature",
  "properties": {
    "iso:country":"US",
    "sg:address":"12989 Jupiter Rd Ste 203",
    "sg:city":"Dallas",
    "sg:classifiers":[
        {
            "category":"Banks & Credit Unions",
            "subcategory":"Investment Brokerage",
            "type":"Services"
        },
        {
            "category":"Banks & Credit Unions",
            "subcategory":"Bank",
            "type":"Services"
        },
        {
            "category":"Banks & Credit Unions",
            "subcategory":"Financial Services",
            "type":"Services"
        }
    ],
    "sg:phone":"+1 214 349 6973",
    "sg:postcode":"75238",
    "sg:province":"TX",
    "sg:tags":[
        "advisory",
        "planner",
        "consultant",
        "broker",
        "retirement",
        "planning",
        "bond",
        "stock"
    ],
    "sg:website":"http://www.firstcanterbury.com",
    "wof:name":"First Canterbury Securities Inc.",
    "wof:placetype":"venue"
},
  "geometry": {"coordinates":[-96.683167,32.87336],"type":"Point"}
}