{
  "type": "Feature",
  "properties": {
    "iso:country":"US",
    "sg:address":"3326 S Western St",
    "sg:city":"Amarillo",
    "sg:classifiers":[
        {
            "category":"Home & Garden",
            "subcategory":"Building Materials",
            "type":"Retail Goods"
        },
        {
            "category":"Building & Trades",
            "subcategory":"Construction",
            "type":"Services"
        }
    ],
    "sg:phone":"+1 806 354 2663",
    "sg:postcode":"79109",
    "sg:province":"TX",
    "sg:tags":[
        "downspouts",
        "roofing",
        "gutter",
        "contractor"
    ],
    "wof:name":"Rhino Roofing",
    "wof:placetype":"venue"
},
  "geometry": {"coordinates":[-101.883977,35.178144],"type":"Point"}
}