{
  "type": "Feature",
  "properties": {
    "iso:country":"US",
    "sg:address":"1794 N Graham St",
    "sg:city":"Stephenville",
    "sg:classifiers":[
        {
            "category":"Social Services",
            "type":"Services"
        }
    ],
    "sg:phone":"+1 254 965 4357",
    "sg:postcode":"76401",
    "sg:province":"TX",
    "sg:tags":[
        "organization",
        "welfare"
    ],
    "wof:name":"Cross Timbers Family Svc",
    "wof:placetype":"venue"
},
  "geometry": {"coordinates":[-98.21289400000001,32.235364],"type":"Point"}
}