{
  "type": "Feature",
  "properties": {
    "iso:country":"US",
    "sg:address":"218 Cloudmont Dr",
    "sg:city":"San Antonio",
    "sg:classifiers":[
        {
            "category":"Freight",
            "type":"Transportation"
        }
    ],
    "sg:phone":"+1 210 637 0530",
    "sg:postcode":"78239",
    "sg:province":"TX",
    "wof:name":"Gram's Kids Transportation",
    "wof:placetype":"venue"
},
  "geometry": {"coordinates":[-98.391902,29.515836],"type":"Point"}
}