{
  "type": "Feature",
  "properties": {
    "iso:country":"US",
    "sg:address":"9400 Wade Blvd",
    "sg:city":"Frisco",
    "sg:classifiers":[
        {
            "category":"Building & Trades",
            "subcategory":"Construction",
            "type":"Services"
        }
    ],
    "sg:phone":"+1 972 668 4116",
    "sg:postcode":"75035",
    "sg:province":"TX",
    "sg:tags":[
        "house"
    ],
    "wof:name":"Cloud Construction",
    "wof:placetype":"venue"
},
  "geometry": {"coordinates":[-96.798889,33.129812],"type":"Point"}
}