{
  "type": "Feature",
  "properties": {
    "iso:country":"US",
    "sg:address":"1601 S Morgan St",
    "sg:city":"Granbury",
    "sg:classifiers":[
        {
            "category":"Shopping",
            "subcategory":"Discount & Variety Stores",
            "type":"Retail Goods"
        }
    ],
    "sg:phone":"+1 817 573 1415",
    "sg:postcode":"76048",
    "sg:province":"TX",
    "wof:name":"Dollar General",
    "wof:placetype":"venue"
},
  "geometry": {"coordinates":[-97.793308,32.427785],"type":"Point"}
}