{
  "type": "Feature",
  "properties": {
    "iso:country":"US",
    "sg:address":"2500 Daniel McCall Dr",
    "sg:city":"Lufkin",
    "sg:classifiers":[
        {
            "category":"Health Services",
            "subcategory":"Optometrist",
            "type":"Services"
        }
    ],
    "sg:phone":"+1 936 639 6044",
    "sg:postcode":"75904",
    "sg:province":"TX",
    "wof:name":"S J Charendoff",
    "wof:placetype":"venue"
},
  "geometry": {"coordinates":[-94.72801200000001,31.297627],"type":"Point"}
}