{
  "type": "Feature",
  "properties": {
    "iso:country":"US",
    "sg:address":"12350 Rendon Rd",
    "sg:city":"Burleson",
    "sg:classifiers":[
        {
            "category":"Education",
            "subcategory":"School",
            "type":"Public Place"
        }
    ],
    "sg:phone":"+1 817 561 3850",
    "sg:postcode":"76028",
    "sg:province":"TX",
    "sg:website":"www.mansfieldisd.org",
    "wof:name":"Mansfield Independent School District",
    "wof:placetype":"venue"
},
  "geometry": {"coordinates":[-97.241699,32.5737],"type":"Point"}
}