{
  "type": "Feature",
  "properties": {
    "iso:country":"US",
    "sg:address":"4600 Olin Rd",
    "sg:city":"Dallas",
    "sg:classifiers":[
        {
            "category":"Building & Trades",
            "subcategory":"Plumbing",
            "type":"Services"
        }
    ],
    "sg:phone":"+1 972 661 1088",
    "sg:postcode":"75244",
    "sg:province":"TX",
    "sg:tags":[
        "conditioning",
        "air",
        "system",
        "contractor"
    ],
    "wof:name":"Friedrich Air Conditioning Co",
    "wof:placetype":"venue"
},
  "geometry": {"coordinates":[-96.82933800000001,32.937796],"type":"Point"}
}