{
  "type": "Feature",
  "properties": {
    "iso:country":"US",
    "sg:address":"5750 W Gulf Bank Rd",
    "sg:city":"Houston",
    "sg:classifiers":[
        {
            "category":"Food & Beverages",
            "subcategory":"Groceries & Convenience Stores",
            "type":"Retail Goods"
        }
    ],
    "sg:phone":"+1 281 999 6017",
    "sg:postcode":"77088",
    "sg:province":"TX",
    "wof:name":"Stop N Go 2616",
    "wof:placetype":"venue"
},
  "geometry": {"coordinates":[-95.47931699999999,29.88488],"type":"Point"}
}