{
  "type": "Feature",
  "properties": {
    "iso:country":"US",
    "sg:address":"812 Airport Blvd",
    "sg:city":"Austin",
    "sg:classifiers":[
        {
            "category":"Building & Trades",
            "subcategory":"Construction",
            "type":"Services"
        }
    ],
    "sg:phone":"+1 512 385 2215",
    "sg:postcode":"78702",
    "sg:province":"TX",
    "sg:tags":[
        "maker",
        "cabinet"
    ],
    "wof:name":"AAA Mill Inc",
    "wof:placetype":"venue"
},
  "geometry": {"coordinates":[-97.693213,30.257074],"type":"Point"}
}