{
  "type": "Feature",
  "properties": {
    "iso:country":"US",
    "sg:address":"3130 Stagg Dr",
    "sg:city":"Beaumont",
    "sg:classifiers":[
        {
            "category":"Health Services",
            "subcategory":"Nursing And Care Facility",
            "type":"Services"
        },
        {
            "category":"Health Services",
            "subcategory":"Health Practitioner",
            "type":"Services"
        }
    ],
    "sg:phone":"+1 409 838 0045",
    "sg:postcode":"77701",
    "sg:province":"TX",
    "sg:tags":[
        "home",
        "nurse",
        "eldercare-home"
    ],
    "wof:name":"Texas Home Health of America Inc.",
    "wof:placetype":"venue"
},
  "geometry": {"coordinates":[-94.12484600000001,30.070129],"type":"Point"}
}