{
  "type": "Feature",
  "properties": {
    "iso:country":"US",
    "sg:address":"802 W 9th St",
    "sg:city":"Del Rio",
    "sg:classifiers":[
        {
            "category":"Building & Trades",
            "subcategory":"Construction",
            "type":"Services"
        }
    ],
    "sg:phone":"+1 830 775 3655",
    "sg:postcode":"78840",
    "sg:province":"TX",
    "sg:tags":[
        "house"
    ],
    "wof:name":"Southwestern Construction",
    "wof:placetype":"venue"
},
  "geometry": {"coordinates":[-100.913297,29.369989],"type":"Point"}
}