{
  "type": "Feature",
  "properties": {
    "iso:country":"US",
    "sg:address":"2137 Stradivarius Ln",
    "sg:city":"Carrollton",
    "sg:classifiers":[
        {
            "category":"Professional",
            "subcategory":"Accounting & Tax Preparation",
            "type":"Services"
        }
    ],
    "sg:phone":"+1 972 492 2301",
    "sg:postcode":"75007",
    "sg:province":"TX",
    "wof:name":"Kathy Hazard CPA",
    "wof:placetype":"venue"
},
  "geometry": {"coordinates":[-96.86834899999999,33.01495],"type":"Point"}
}