{
  "type": "Feature",
  "properties": {
    "iso:country":"US",
    "sg:address":"5537 Loyola Lane",
    "sg:city":"Austin",
    "sg:classifiers":[
        {
            "category":"Organizations",
            "subcategory":"Religious Organization",
            "type":"Services"
        }
    ],
    "sg:phone":"+1 512 926 5898",
    "sg:postcode":"78724",
    "sg:province":"TX",
    "wof:name":"God's Power In Christian Fellowship",
    "wof:placetype":"venue"
},
  "geometry": {"coordinates":[-97.660467,30.302719],"type":"Point"}
}