{
  "type": "Feature",
  "properties": {
    "iso:country":"US",
    "sg:address":"1514 Antoine Dr",
    "sg:city":"Houston",
    "sg:classifiers":[
        {
            "category":"Manufacturing",
            "subcategory":"Buildings",
            "type":"Manufacturing & Wholesale Goods"
        },
        {
            "category":"Building & Trades",
            "subcategory":"Construction",
            "type":"Services"
        }
    ],
    "sg:phone":"+1 713 681 1514",
    "sg:postcode":"77055",
    "sg:province":"TX",
    "sg:tags":[
        "industrial",
        "altering",
        "consultant",
        "builder",
        "contractor",
        "contractors-commercial",
        "home",
        "remodeling"
    ],
    "sg:website":"www.camdeninc.com",
    "wof:name":"Camden Construction Inc",
    "wof:placetype":"venue"
},
  "geometry": {"coordinates":[-95.47550200000001,29.7967],"type":"Point"}
}