{
  "type": "Feature",
  "properties": {
    "iso:country":"US",
    "sg:address":"202 N Center St",
    "sg:city":"Weimar",
    "sg:classifiers":[
        {
            "category":"Food & Beverages",
            "subcategory":"Groceries & Convenience Stores",
            "type":"Retail Goods"
        }
    ],
    "sg:phone":"+1 979 725 8275",
    "sg:postcode":"78962",
    "sg:province":"TX",
    "sg:tags":[
        "grocer"
    ],
    "wof:name":"Weimar Foodstore",
    "wof:placetype":"venue"
},
  "geometry": {"coordinates":[-96.780511,29.704657],"type":"Point"}
}