{
  "type": "Feature",
  "properties": {
    "iso:country":"US",
    "sg:address":"507 N Lee Ave",
    "sg:city":"Odessa",
    "sg:classifiers":[
        {
            "category":"Professional",
            "type":"Services"
        }
    ],
    "sg:phone":"+1 432 335 0771",
    "sg:postcode":"79761",
    "sg:province":"TX",
    "sg:tags":[
        "establishment"
    ],
    "wof:name":"Tex-Plastic Inc",
    "wof:placetype":"venue"
},
  "geometry": {"coordinates":[-102.371302,31.848615],"type":"Point"}
}