{
  "type": "Feature",
  "properties": {
    "iso:country":"US",
    "sg:address":"13119 Bexhill Dr",
    "sg:city":"Houston",
    "sg:classifiers":[
        {
            "category":"Organizations",
            "subcategory":"Religious Organization",
            "type":"Services"
        }
    ],
    "sg:phone":"+1 281 970 8527",
    "sg:postcode":"77065",
    "sg:province":"TX",
    "sg:tags":[
        "medical"
    ],
    "wof:name":"Trinity Dosimetry Services",
    "wof:placetype":"venue"
},
  "geometry": {"coordinates":[-95.619848,29.94372],"type":"Point"}
}