{
  "type": "Feature",
  "properties": {
    "iso:country":"US",
    "sg:address":"4620 Montana Ave",
    "sg:city":"El Paso",
    "sg:classifiers":[
        {
            "category":"Organizations",
            "subcategory":"Religious Organization",
            "type":"Services"
        }
    ],
    "sg:phone":"+1 915 595 8716",
    "sg:postcode":"79903",
    "sg:province":"TX",
    "sg:tags":[
        "church"
    ],
    "wof:name":"New Life Christian Ctr",
    "wof:placetype":"venue"
},
  "geometry": {"coordinates":[-106.435076,31.783644],"type":"Point"}
}