{
  "type": "Feature",
  "properties": {
    "iso:country":"US",
    "sg:address":"775 S 6th St",
    "sg:city":"Silsbee",
    "sg:classifiers":[
        {
            "category":"Shopping",
            "subcategory":"Used Merchandise",
            "type":"Retail Goods"
        }
    ],
    "sg:phone":"+1 409 385 2943",
    "sg:postcode":"77656",
    "sg:province":"TX",
    "wof:name":"Sunshine Resale Shop",
    "wof:placetype":"venue"
},
  "geometry": {"coordinates":[-94.182901,30.343303],"type":"Point"}
}