{
  "type": "Feature",
  "properties": {
    "iso:country":"US",
    "sg:address":"1400 N Shepherd Dr",
    "sg:city":"Houston",
    "sg:phone":"+1 713 869 7999",
    "sg:postcode":"77008",
    "sg:province":"TX",
    "wof:name":"Alvarez & Montes, PLLC",
    "wof:placetype":"venue"
},
  "geometry": {"coordinates":[-95.409988,29.79604],"type":"Point"}
}