{
  "type": "Feature",
  "properties": {
    "iso:country":"US",
    "sg:address":"800 N I- 35 E",
    "sg:city":"Denton",
    "sg:classifiers":[
        {
            "category":"Wholesale",
            "subcategory":"Hardware",
            "type":"Manufacturing & Wholesale Goods"
        }
    ],
    "sg:phone":"+1 940 382 9622",
    "sg:postcode":"76205",
    "sg:province":"TX",
    "sg:tags":[
        "air",
        "parts",
        "conditioning",
        "supply"
    ],
    "wof:name":"Weathertrol Supply Co",
    "wof:placetype":"venue"
},
  "geometry": {"coordinates":[-97.14315999999999,33.198789],"type":"Point"}
}