{
  "type": "Feature",
  "properties": {
    "iso:country":"US",
    "sg:address":"10655 Six Pines Rd",
    "sg:city":"Spring",
    "sg:classifiers":[
        {
            "category":"Social Services",
            "type":"Services"
        }
    ],
    "sg:phone":"+1 281 367 2579",
    "sg:postcode":"77380",
    "sg:province":"TX",
    "wof:name":"Foxall Prof Counseling Svcs",
    "wof:placetype":"venue"
},
  "geometry": {"coordinates":[-95.46128400000001,30.15321],"type":"Point"}
}