{
  "type": "Feature",
  "properties": {
    "iso:country":"US",
    "sg:address":"2614 Ridgecrest",
    "sg:city":"Kilgore",
    "sg:classifiers":[
        {
            "category":"Building & Trades",
            "subcategory":"Construction",
            "type":"Services"
        }
    ],
    "sg:phone":"+1 903 984 5644",
    "sg:postcode":"75662",
    "sg:province":"TX",
    "sg:tags":[
        "house"
    ],
    "wof:name":"Wilson Custom Homes",
    "wof:placetype":"venue"
},
  "geometry": {"coordinates":[-94.85127199999999,32.376034],"type":"Point"}
}