{
  "type": "Feature",
  "properties": {
    "iso:country":"US",
    "sg:address":"3880 US Hwy 281",
    "sg:city":"Three Rivers",
    "sg:classifiers":[
        {
            "category":"Professional",
            "type":"Services"
        }
    ],
    "sg:phone":"+1 361 786 4325",
    "sg:postcode":"78071",
    "sg:province":"TX",
    "sg:tags":[
        "establishment"
    ],
    "wof:name":"Grubstake LTD",
    "wof:placetype":"venue"
},
  "geometry": {"coordinates":[-98.175614,28.41896],"type":"Point"}
}