{
  "type": "Feature",
  "properties": {
    "iso:country":"US",
    "sg:address":"13088 Ranchette Rd",
    "sg:city":"Montgomery",
    "sg:classifiers":[
        {
            "category":"Wholesale",
            "subcategory":"Construction Materials",
            "type":"Manufacturing & Wholesale Goods"
        }
    ],
    "sg:phone":"+1 936 597 5275",
    "sg:postcode":"77356",
    "sg:province":"TX",
    "sg:tags":[
        "timberland",
        "company",
        "timber"
    ],
    "wof:name":"Bryant Forestry",
    "wof:placetype":"venue"
},
  "geometry": {"coordinates":[-95.66770200000001,30.432195],"type":"Point"}
}