{
  "type": "Feature",
  "properties": {
    "iso:country":"US",
    "sg:address":"2828 Routh St",
    "sg:city":"Dallas",
    "sg:classifiers":[
        {
            "category":"Professional",
            "subcategory":"Lawyer & Legal Services",
            "type":"Services"
        }
    ],
    "sg:phone":"+1 214 739 6733",
    "sg:postcode":"75201",
    "sg:province":"TX",
    "wof:name":"McElroy Dan Atty",
    "wof:placetype":"venue"
},
  "geometry": {"coordinates":[-96.803832,32.798359],"type":"Point"}
}