{
  "type": "Feature",
  "properties": {
    "iso:country":"US",
    "sg:address":"12400 State Hwy 71 W Ste 706",
    "sg:city":"Bee Cave",
    "sg:classifiers":[
        {
            "category":"Ice Cream",
            "type":"Food & Drink"
        }
    ],
    "sg:phone":"+1 512 263 9909",
    "sg:postcode":"78738",
    "sg:province":"TX",
    "sg:tags":[
        "frozen",
        "yogurt"
    ],
    "wof:name":"Vista Yogurt",
    "wof:placetype":"venue"
},
  "geometry": {"coordinates":[-97.932148,30.304357],"type":"Point"}
}