{
  "type": "Feature",
  "properties": {
    "iso:country":"US",
    "sg:address":"6013 Stetson Cir",
    "sg:city":"Corpus Christi",
    "sg:classifiers":[
        {
            "category":"Building & Trades",
            "subcategory":"Construction",
            "type":"Services"
        }
    ],
    "sg:phone":"+1 361 985 0100",
    "sg:postcode":"78414",
    "sg:province":"TX",
    "sg:tags":[
        "home",
        "builder"
    ],
    "wof:name":"Hogan Homes",
    "wof:placetype":"venue"
},
  "geometry": {"coordinates":[-97.384002,27.668856],"type":"Point"}
}