{
  "type": "Feature",
  "properties": {
    "iso:country":"US",
    "sg:address":"2104 River Ridge Rd",
    "sg:city":"Arlington",
    "sg:classifiers":[
        {
            "category":"Health Services",
            "subcategory":"Doctor",
            "type":"Services"
        }
    ],
    "sg:phone":"+1 817 465 5553",
    "sg:postcode":"76017",
    "sg:province":"TX",
    "sg:tags":[
        "physician",
        "surgeon"
    ],
    "wof:name":"Walter G Osborne MD",
    "wof:placetype":"venue"
},
  "geometry": {"coordinates":[-97.14122,32.663156],"type":"Point"}
}