{
  "type": "Feature",
  "properties": {
    "iso:country":"US",
    "sg:address":"3630 Corine Ct",
    "sg:city":"Katy",
    "sg:classifiers":[
        {
            "category":"Building & Trades",
            "subcategory":"Electrical",
            "type":"Services"
        }
    ],
    "sg:phone":"+1 281 398 5854",
    "sg:postcode":"77449",
    "sg:province":"TX",
    "sg:tags":[
        "electrical",
        "contractor"
    ],
    "wof:name":"Technology Resources of Texas",
    "wof:placetype":"venue"
},
  "geometry": {"coordinates":[-95.7159,29.825086],"type":"Point"}
}