{
  "type": "Feature",
  "properties": {
    "iso:country":"US",
    "sg:address":"719 Madison St",
    "sg:city":"Coppell",
    "sg:classifiers":[
        {
            "category":"Professional",
            "subcategory":"Art Services",
            "type":"Services"
        }
    ],
    "sg:phone":"+1 972 899 1474",
    "sg:postcode":"75019",
    "sg:province":"TX",
    "sg:tags":[
        "commercial",
        "design"
    ],
    "wof:name":"Dollar Kari Photography",
    "wof:placetype":"venue"
},
  "geometry": {"coordinates":[-96.998707,32.985183],"type":"Point"}
}