{
  "type": "Feature",
  "properties": {
    "iso:country":"US",
    "sg:address":"2216 Commerce St",
    "sg:city":"Dallas",
    "sg:classifiers":[
        {
            "category":"Personal",
            "subcategory":"Beauty Salon",
            "type":"Services"
        }
    ],
    "sg:phone":"+1 214 742 7300",
    "sg:postcode":"75201",
    "sg:province":"TX",
    "wof:name":"Salon Gossip",
    "wof:placetype":"venue"
},
  "geometry": {"coordinates":[-96.789891,32.781753],"type":"Point"}
}