{
  "type": "Feature",
  "properties": {
    "iso:country":"US",
    "sg:address":"4037 Co Rd 616",
    "sg:city":"Alvarado",
    "sg:classifiers":[
        {
            "category":"Farming",
            "subcategory":"Livestock Farm",
            "type":"Manufacturing & Wholesale Goods"
        }
    ],
    "sg:phone":"+1 817 282 3051",
    "sg:postcode":"76009",
    "sg:province":"TX",
    "sg:tags":[
        "ranch"
    ],
    "wof:name":"Holiday Ranch",
    "wof:placetype":"venue"
},
  "geometry": {"coordinates":[-97.157971,32.501291],"type":"Point"}
}