{
  "type": "Feature",
  "properties": {
    "iso:country":"US",
    "sg:address":"1324 S 3rd St",
    "sg:city":"Conroe",
    "sg:classifiers":[
        {
            "category":"Building & Trades",
            "subcategory":"Construction",
            "type":"Services"
        }
    ],
    "sg:phone":"+1 936 441 4377",
    "sg:postcode":"77301",
    "sg:province":"TX",
    "sg:tags":[
        "contractor"
    ],
    "wof:name":"Gordons Tile Service",
    "wof:placetype":"venue"
},
  "geometry": {"coordinates":[-95.447498,30.298886],"type":"Point"}
}