{
  "type": "Feature",
  "properties": {
    "iso:country":"US",
    "sg:address":"1909 Avenue G",
    "sg:city":"Rosenberg",
    "sg:classifiers":[
        {
            "category":"Shopping",
            "subcategory":"Antiques",
            "type":"Retail Goods"
        }
    ],
    "sg:phone":"+1 281 342 6804",
    "sg:postcode":"77471",
    "sg:province":"TX",
    "wof:name":"Vogelsang Antique Emporium",
    "wof:placetype":"venue"
},
  "geometry": {"coordinates":[-95.807706,29.559312],"type":"Point"}
}