{
  "type": "Feature",
  "properties": {
    "iso:country":"US",
    "sg:address":"1901 Central Dr",
    "sg:city":"Bedford",
    "sg:classifiers":[
        {
            "category":"Utilities",
            "subcategory":"Telephone",
            "type":"Services"
        },
        {
            "category":"Professional",
            "type":"Services"
        }
    ],
    "sg:phone":"+1 817 358 7580",
    "sg:postcode":"76021",
    "sg:province":"TX",
    "sg:tags":[
        "prepackaged",
        "communications",
        "establishment",
        "software"
    ],
    "sg:website":"www.playnet.com",
    "wof:name":"Playnet Inc",
    "wof:placetype":"venue"
},
  "geometry": {"coordinates":[-97.13345200000001,32.840035],"type":"Point"}
}