{
  "type": "Feature",
  "properties": {
    "iso:country":"US",
    "sg:address":"2075 McDaniel Dr",
    "sg:city":"Carrollton",
    "sg:classifiers":[
        {
            "category":"Wholesale",
            "subcategory":"Hardware",
            "type":"Manufacturing & Wholesale Goods"
        }
    ],
    "sg:phone":"+1 972 243 8266",
    "sg:postcode":"75006",
    "sg:province":"TX",
    "sg:tags":[
        "equipment",
        "air",
        "conditioning",
        "heating"
    ],
    "wof:name":"Lennox",
    "wof:placetype":"venue"
},
  "geometry": {"coordinates":[-96.92182200000001,32.933395],"type":"Point"}
}