{
  "type": "Feature",
  "properties": {
    "iso:country":"US",
    "sg:address":"215 Airpark Dr",
    "sg:city":"La Vernia",
    "sg:classifiers":[
        {
            "category":"Building & Trades",
            "subcategory":"Construction",
            "type":"Services"
        }
    ],
    "sg:phone":"+1 830 420 3491",
    "sg:postcode":"78121",
    "sg:province":"TX",
    "sg:tags":[
        "hanging",
        "contractor"
    ],
    "wof:name":"Skyart",
    "wof:placetype":"venue"
},
  "geometry": {"coordinates":[-98.132987,29.428381],"type":"Point"}
}