{
  "type": "Feature",
  "properties": {
    "iso:country":"US",
    "sg:address":"9777 Harwin Dr",
    "sg:city":"Houston",
    "sg:classifiers":[
        {
            "category":"Wholesale",
            "subcategory":"Toys & Hobbies",
            "type":"Manufacturing & Wholesale Goods"
        }
    ],
    "sg:phone":"+1 832 242 6223",
    "sg:postcode":"77036",
    "sg:province":"TX",
    "sg:tags":[
        "wholesaler"
    ],
    "wof:name":"1 Import Inc",
    "wof:placetype":"venue"
},
  "geometry": {"coordinates":[-95.535656,29.717677],"type":"Point"}
}