{
  "type": "Feature",
  "properties": {
    "iso:country":"US",
    "sg:address":"629 The Meadows Pkwy",
    "sg:city":"De Soto",
    "sg:classifiers":[
        {
            "category":"Shopping",
            "subcategory":"Clothing, Apparel, & Fashions",
            "type":"Retail Goods"
        }
    ],
    "sg:phone":"+1 972 230 9935",
    "sg:postcode":"75115",
    "sg:province":"TX",
    "sg:tags":[
        "family"
    ],
    "wof:name":"Bag Enterprise",
    "wof:placetype":"venue"
},
  "geometry": {"coordinates":[-96.836788,32.597395],"type":"Point"}
}