{
  "type": "Feature",
  "properties": {
    "iso:country":"US",
    "sg:address":"6855 Southwest Fwy",
    "sg:city":"Houston",
    "sg:classifiers":[
        {
            "category":"Restaurant",
            "type":"Food & Drink"
        }
    ],
    "sg:phone":"+1 713 772 0084",
    "sg:postcode":"77074",
    "sg:province":"TX",
    "wof:name":"Thali",
    "wof:placetype":"venue"
},
  "geometry": {"coordinates":[-95.503891,29.712122],"type":"Point"}
}