{
  "type": "Feature",
  "properties": {
    "iso:country":"US",
    "sg:address":"7311 Grover Ave",
    "sg:city":"Austin",
    "sg:classifiers":[
        {
            "category":"Building & Trades",
            "subcategory":"Construction",
            "type":"Services"
        }
    ],
    "sg:phone":"+1 512 467 2241",
    "sg:postcode":"78757",
    "sg:province":"TX",
    "sg:tags":[
        "finishing",
        "wood"
    ],
    "wof:name":"L & S Interior Trim Carpenters Inc",
    "wof:placetype":"venue"
},
  "geometry": {"coordinates":[-97.721683,30.342436],"type":"Point"}
}