{
  "type": "Feature",
  "properties": {
    "iso:country":"US",
    "sg:address":"3105 W 15th St",
    "sg:city":"Plano",
    "sg:classifiers":[
        {
            "category":"Health Services",
            "subcategory":"Doctor",
            "type":"Services"
        }
    ],
    "sg:phone":"+1 972 596 3903",
    "sg:postcode":"75075",
    "sg:province":"TX",
    "sg:tags":[
        "dentist"
    ],
    "wof:name":"Joseph H Hildago Jr DDS",
    "wof:placetype":"venue"
},
  "geometry": {"coordinates":[-96.754321,33.01944],"type":"Point"}
}