{
  "type": "Feature",
  "properties": {
    "iso:country":"US",
    "sg:address":"405 S Burnet Dr",
    "sg:city":"Baytown",
    "sg:classifiers":[
        {
            "category":"Building & Trades",
            "subcategory":"Construction",
            "type":"Services"
        }
    ],
    "sg:phone":"+1 281 424 5409",
    "sg:postcode":"77520",
    "sg:province":"TX",
    "sg:tags":[
        "tile",
        "dealer",
        "contractor"
    ],
    "wof:name":"Morales Tile Co",
    "wof:placetype":"venue"
},
  "geometry": {"coordinates":[-95.040903,29.770646],"type":"Point"}
}