{
  "type": "Feature",
  "properties": {
    "iso:country":"US",
    "sg:address":"4621 Briarhaven Rd",
    "sg:city":"Fort Worth",
    "sg:classifiers":[
        {
            "category":"Education",
            "subcategory":"Dance Studio",
            "type":"Public Place"
        }
    ],
    "sg:phone":"+1 817 926 5086",
    "sg:postcode":"76109",
    "sg:province":"TX",
    "wof:name":"Aradhana Dance Co",
    "wof:placetype":"venue"
},
  "geometry": {"coordinates":[-97.392897,32.68887],"type":"Point"}
}