{
  "type": "Feature",
  "properties": {
    "iso:country":"US",
    "sg:address":"2862 S Alameda St",
    "sg:city":"Corpus Christi",
    "sg:classifiers":[
        {
            "category":"Health Services",
            "subcategory":"Doctor",
            "type":"Services"
        }
    ],
    "sg:phone":"+1 361 882 5353",
    "sg:postcode":"78404",
    "sg:province":"TX",
    "wof:name":"Corpus Christi Endodontics",
    "wof:placetype":"venue"
},
  "geometry": {"coordinates":[-97.394032,27.762987],"type":"Point"}
}