{
  "type": "Feature",
  "properties": {
    "iso:country":"US",
    "sg:address":"405 S 15th St",
    "sg:city":"Mcallen",
    "sg:classifiers":[
        {
            "category":"Banks & Credit Unions",
            "subcategory":"Bank",
            "type":"Services"
        }
    ],
    "sg:phone":"+1 956 687 4921",
    "sg:postcode":"78501",
    "sg:province":"TX",
    "sg:tags":[
        "loan",
        "institution",
        "business"
    ],
    "wof:name":"Bell Finance Co",
    "wof:placetype":"venue"
},
  "geometry": {"coordinates":[-98.236238,26.199723],"type":"Point"}
}