{
  "type": "Feature",
  "properties": {
    "iso:country":"US",
    "sg:address":"515 Bending Bough Dr",
    "sg:city":"Spring",
    "sg:classifiers":[
        {
            "category":"Shopping",
            "subcategory":"Pets & Pet Supplies",
            "type":"Retail Goods"
        }
    ],
    "sg:phone":"+1 281 528 9250",
    "sg:postcode":"77388",
    "sg:province":"TX",
    "sg:tags":[
        "furnishing",
        "dog",
        "store",
        "cat"
    ],
    "wof:name":"Passionate Pet Care",
    "wof:placetype":"venue"
},
  "geometry": {"coordinates":[-95.447227,30.05089],"type":"Point"}
}