{
  "type": "Feature",
  "properties": {
    "iso:country":"US",
    "sg:address":"20215 Prince Creek Dr",
    "sg:city":"Katy",
    "sg:classifiers":[
        {
            "category":"Banks & Credit Unions",
            "subcategory":"Financial Services",
            "type":"Services"
        }
    ],
    "sg:phone":"+1 281 398 3923",
    "sg:postcode":"77450",
    "sg:province":"TX",
    "sg:tags":[
        "company",
        "bank",
        "holding"
    ],
    "wof:name":"Katy Sports",
    "wof:placetype":"venue"
},
  "geometry": {"coordinates":[-95.72386,29.770019],"type":"Point"}
}