{
  "type": "Feature",
  "properties": {
    "iso:country":"US",
    "sg:address":"1304 N Main St",
    "sg:city":"Jewett",
    "sg:classifiers":[
        {
            "category":"Personal",
            "subcategory":"Beauty Salon",
            "type":"Services"
        }
    ],
    "sg:phone":"+1 903 626 5560",
    "sg:postcode":"75846",
    "sg:province":"TX",
    "wof:name":"Hair Barn",
    "wof:placetype":"venue"
},
  "geometry": {"coordinates":[-96.14006000000001,31.368533],"type":"Point"}
}