{
  "type": "Feature",
  "properties": {
    "iso:country":"US",
    "sg:address":"10041 Regal Row Ste 100",
    "sg:city":"Houston",
    "sg:classifiers":[
        {
            "category":"Shopping",
            "subcategory":"Computers & Home Electronics",
            "type":"Retail Goods"
        }
    ],
    "sg:phone":"+1 281 550 4040",
    "sg:postcode":"77040",
    "sg:province":"TX",
    "wof:name":"Godish",
    "wof:placetype":"venue"
},
  "geometry": {"coordinates":[-95.550262,29.873696],"type":"Point"}
}