{
  "type": "Feature",
  "properties": {
    "iso:country":"US",
    "sg:address":"2612 Scott St",
    "sg:city":"Houston",
    "sg:classifiers":[
        {
            "category":"Coffee & Tea",
            "type":"Food & Drink"
        },
        {
            "category":"Restaurant",
            "type":"Food & Drink"
        }
    ],
    "sg:phone":"+1 713 658 9191",
    "sg:postcode":"77004",
    "sg:province":"TX",
    "sg:tags":[
        "cafeteria",
        "espresso"
    ],
    "wof:name":"Conscious Cafe",
    "wof:placetype":"venue"
},
  "geometry": {"coordinates":[-95.34858699999999,29.732413],"type":"Point"}
}