{
  "type": "Feature",
  "properties": {
    "iso:country":"US",
    "sg:address":"605 Shea St",
    "sg:city":"Laredo",
    "sg:classifiers":[
        {
            "category":"Retail",
            "subcategory":"Repair Shop",
            "type":"Services"
        }
    ],
    "sg:phone":"+1 956 722 3142",
    "sg:postcode":"78040",
    "sg:province":"TX",
    "sg:tags":[
        "automotive",
        "refrigeration",
        "trucking"
    ],
    "wof:name":"Garcia Truck Refrigeration",
    "wof:placetype":"venue"
},
  "geometry": {"coordinates":[-99.502528,27.520723],"type":"Point"}
}