{
  "type": "Feature",
  "properties": {
    "iso:country":"US",
    "sg:address":"1433 Winterwood Dr",
    "sg:city":"Allen",
    "sg:classifiers":[
        {
            "category":"Professional",
            "type":"Services"
        }
    ],
    "sg:phone":"+1 972 747 0021",
    "sg:postcode":"75002",
    "sg:province":"TX",
    "wof:name":"Svr Tech Inc",
    "wof:placetype":"venue"
},
  "geometry": {"coordinates":[-96.635623,33.10391],"type":"Point"}
}