{
  "type": "Feature",
  "properties": {
    "iso:country":"US",
    "sg:address":"4710 Perrin Creek Pump",
    "sg:city":"San Antonio",
    "sg:classifiers":[
        {
            "category":"Building & Trades",
            "subcategory":"Construction",
            "type":"Services"
        }
    ],
    "sg:phone":"+1 210 650 9670",
    "sg:postcode":"78217",
    "sg:province":"TX",
    "sg:tags":[
        "layer",
        "carpet"
    ],
    "sg:website":"www.intertechflooring.com",
    "wof:name":"Intertech Flooring",
    "wof:placetype":"venue"
},
  "geometry": {"coordinates":[-98.400481,29.524188],"type":"Point"}
}