{
  "type": "Feature",
  "properties": {
    "iso:country":"US",
    "sg:address":"3005 Race St",
    "sg:city":"Fort Worth",
    "sg:classifiers":[
        {
            "category":"Professional",
            "subcategory":"Business Services",
            "type":"Services"
        }
    ],
    "sg:phone":"+1 817 885 8756",
    "sg:postcode":"76111",
    "sg:province":"TX",
    "sg:tags":[
        "record",
        "medical"
    ],
    "wof:name":"Medical Records By Ron Wright",
    "wof:placetype":"venue"
},
  "geometry": {"coordinates":[-97.303704,32.773182],"type":"Point"}
}