{
  "type": "Feature",
  "properties": {
    "iso:country":"US",
    "sg:address":"2838 Reynolds Ln",
    "sg:city":"Port Neches",
    "sg:classifiers":[
        {
            "category":"Professional",
            "subcategory":"Advertising",
            "type":"Services"
        }
    ],
    "sg:phone":"+1 409 729 7200",
    "sg:postcode":"77651",
    "sg:province":"TX",
    "wof:name":"Advantage Media Inc",
    "wof:placetype":"venue"
},
  "geometry": {"coordinates":[-93.956523,29.960063],"type":"Point"}
}