{
  "type": "Feature",
  "properties": {
    "iso:country":"US",
    "sg:address":"7018 Joyce Way",
    "sg:city":"Dallas",
    "sg:classifiers":[
        {
            "category":"Professional",
            "subcategory":"Business Services",
            "type":"Services"
        }
    ],
    "sg:phone":"+1 214 750 4499",
    "sg:postcode":"75225",
    "sg:province":"TX",
    "wof:name":"Icf Group Keri Hall",
    "wof:placetype":"venue"
},
  "geometry": {"coordinates":[-96.784684,32.87929],"type":"Point"}
}