{
  "type": "Feature",
  "properties": {
    "iso:country":"US",
    "sg:address":"6672 Ruxton Ln",
    "sg:city":"Austin",
    "sg:classifiers":[
        {
            "category":"Food & Beverages",
            "subcategory":"Specialty",
            "type":"Retail Goods"
        }
    ],
    "sg:phone":"+1 512 301 0340",
    "sg:postcode":"78749",
    "sg:province":"TX",
    "sg:tags":[
        "dessert",
        "health",
        "diet"
    ],
    "sg:website":"www.kakesbykim.com/",
    "wof:name":"Kakes by Kim",
    "wof:placetype":"venue"
},
  "geometry": {"coordinates":[-97.88450899999999,30.212221],"type":"Point"}
}