{
  "type": "Feature",
  "properties": {
    "iso:country":"US",
    "sg:address":"3414 Garth Rd",
    "sg:city":"Baytown",
    "sg:classifiers":[
        {
            "category":"Retail",
            "subcategory":"Auto Repair",
            "type":"Services"
        }
    ],
    "sg:phone":"+1 281 837 8780",
    "sg:postcode":"77521",
    "sg:province":"TX",
    "sg:website":"http://www.jiffylube.com",
    "wof:name":"Jiffy Lube",
    "wof:placetype":"venue"
},
  "geometry": {"coordinates":[-94.977334,29.758245],"type":"Point"}
}