{
  "type": "Feature",
  "properties": {
    "iso:country":"US",
    "sg:address":"4919 W 7th St",
    "sg:city":"Texarkana",
    "sg:classifiers":[
        {
            "category":"Wholesale",
            "subcategory":"Office Equipment",
            "type":"Manufacturing & Wholesale Goods"
        }
    ],
    "sg:phone":"+1 903 832 4346",
    "sg:postcode":"75501",
    "sg:province":"TX",
    "sg:tags":[
        "used",
        "copier"
    ],
    "wof:name":"Action Wholesale Copiers",
    "wof:placetype":"venue"
},
  "geometry": {"coordinates":[-94.10275900000001,33.417764],"type":"Point"}
}