{
  "type": "Feature",
  "properties": {
    "iso:country":"US",
    "sg:address":"18735 Haughland Dr",
    "sg:city":"Cypress",
    "sg:classifiers":[
        {
            "category":"Professional",
            "type":"Services"
        }
    ],
    "sg:phone":"+1 281 859 2273",
    "sg:postcode":"77433",
    "sg:province":"TX",
    "wof:name":"Gerald Maxwell Services",
    "wof:placetype":"venue"
},
  "geometry": {"coordinates":[-95.69623199999999,29.883331],"type":"Point"}
}