{
  "type": "Feature",
  "properties": {
    "iso:country":"US",
    "sg:address":"5650 FM 1960 W",
    "sg:city":"Houston",
    "sg:classifiers":[
        {
            "category":"Home & Garden",
            "subcategory":"Home Furnishings",
            "type":"Retail Goods"
        }
    ],
    "sg:phone":"+1 281 440 7351",
    "sg:postcode":"77069",
    "sg:province":"TX",
    "sg:tags":[
        "furniture"
    ],
    "wof:name":"Pier 1",
    "wof:placetype":"venue"
},
  "geometry": {"coordinates":[-95.510593,29.981194],"type":"Point"}
}