{
  "type": "Feature",
  "properties": {
    "iso:country":"US",
    "sg:address":"3280 North Fwy",
    "sg:city":"Fort Worth",
    "sg:classifiers":[
        {
            "category":"Building & Trades",
            "subcategory":"Electrical",
            "type":"Services"
        }
    ],
    "sg:phone":"+1 817 831 2221",
    "sg:postcode":"76111",
    "sg:province":"TX",
    "sg:tags":[
        "specialist",
        "cabling",
        "datum",
        "general",
        "electrical",
        "contractor"
    ],
    "wof:name":"McBride Electric Inc",
    "wof:placetype":"venue"
},
  "geometry": {"coordinates":[-97.315991,32.805598],"type":"Point"}
}