{
  "type": "Feature",
  "properties": {
    "iso:country":"US",
    "sg:address":"11409 Ladera Vista Dr",
    "sg:city":"Austin",
    "sg:classifiers":[
        {
            "category":"Professional",
            "subcategory":"Management & Consulting",
            "type":"Services"
        }
    ],
    "sg:phone":"+1 512 719 3028",
    "sg:postcode":"78759",
    "sg:province":"TX",
    "sg:tags":[
        "consultant",
        "energy",
        "conservation"
    ],
    "wof:name":"Custom Energy Solutions Inc",
    "wof:placetype":"venue"
},
  "geometry": {"coordinates":[-97.75561399999999,30.414811],"type":"Point"}
}