{
  "type": "Feature",
  "properties": {
    "iso:country":"US",
    "sg:address":"1409 Blalock Rd",
    "sg:city":"Houston",
    "sg:classifiers":[
        {
            "category":"Retail",
            "subcategory":"Auto Repair",
            "type":"Services"
        }
    ],
    "sg:phone":"+1 713 467 7587",
    "sg:postcode":"77055",
    "sg:province":"TX",
    "sg:tags":[
        "general"
    ],
    "wof:name":"Swedish Craftsman Garage Inc",
    "wof:placetype":"venue"
},
  "geometry": {"coordinates":[-95.523368,29.795522],"type":"Point"}
}