{
  "type": "Feature",
  "properties": {
    "iso:country":"US",
    "sg:address":"2908 E Wallisville Rd",
    "sg:city":"Highlands",
    "sg:classifiers":[
        {
            "category":"Retail",
            "subcategory":"Storage",
            "type":"Services"
        }
    ],
    "sg:phone":"+1 281 426 2473",
    "sg:postcode":"77562",
    "sg:province":"TX",
    "sg:tags":[
        "self"
    ],
    "wof:name":"San Jacinto Boat & Rv Storage",
    "wof:placetype":"venue"
},
  "geometry": {"coordinates":[-95.020314,29.81961],"type":"Point"}
}