{
  "type": "Feature",
  "properties": {
    "iso:country":"US",
    "sg:address":"4641 Production Dr",
    "sg:city":"Dallas",
    "sg:classifiers":[
        {
            "category":"Organizations",
            "subcategory":"Professional Association",
            "type":"Services"
        }
    ],
    "sg:phone":"+1 214 630 0553",
    "sg:postcode":"75235",
    "sg:province":"TX",
    "sg:tags":[
        "business",
        "trade"
    ],
    "wof:name":"Casa Bayla",
    "wof:placetype":"venue"
},
  "geometry": {"coordinates":[-96.828495,32.807723],"type":"Point"}
}