{
  "type": "Feature",
  "properties": {
    "iso:country":"US",
    "sg:address":"711 E Tyler St",
    "sg:city":"Athens",
    "sg:classifiers":[
        {
            "category":"Professional",
            "type":"Services"
        }
    ],
    "sg:phone":"+1 903 675 5633",
    "sg:postcode":"75751",
    "sg:province":"TX",
    "wof:name":"Wcp Energy Inc",
    "wof:placetype":"venue"
},
  "geometry": {"coordinates":[-95.844393,32.205808],"type":"Point"}
}