{
  "type": "Feature",
  "properties": {
    "iso:country":"US",
    "sg:address":"221 W Colorado Blvd Ste 212",
    "sg:city":"Dallas",
    "sg:classifiers":[
        {
            "category":"Health Services",
            "subcategory":"Doctor",
            "type":"Services"
        }
    ],
    "sg:phone":"+1 214 941 6228",
    "sg:postcode":"75208",
    "sg:province":"TX",
    "wof:name":"Michelle Reyna MD",
    "wof:placetype":"venue"
},
  "geometry": {"coordinates":[-96.825563,32.759405],"type":"Point"}
}