{
  "type": "Feature",
  "properties": {
    "iso:country":"US",
    "sg:address":"2600 W Trimmier Rd",
    "sg:city":"Killeen",
    "sg:classifiers":[
        {
            "category":"Restaurant",
            "type":"Food & Drink"
        }
    ],
    "sg:phone":"+1 254 554 7009",
    "sg:postcode":"76542",
    "sg:province":"TX",
    "sg:tags":[
        "parlor",
        "ice",
        "cream"
    ],
    "wof:name":"Texas Star Creamery",
    "wof:placetype":"venue"
},
  "geometry": {"coordinates":[-97.734718,31.088479],"type":"Point"}
}