{
  "type": "Feature",
  "properties": {
    "iso:country":"US",
    "sg:address":"402 E Van Buren Ave",
    "sg:city":"Harlingen",
    "sg:classifiers":[
        {
            "category":"Professional",
            "subcategory":"Computer Services",
            "type":"Services"
        }
    ],
    "sg:phone":"+1 956 412 6600",
    "sg:postcode":"78550",
    "sg:province":"TX",
    "sg:tags":[
        "website",
        "design"
    ],
    "wof:name":"Tom Rowe & Assoc",
    "wof:placetype":"venue"
},
  "geometry": {"coordinates":[-97.691388,26.191652],"type":"Point"}
}