{
  "type": "Feature",
  "properties": {
    "iso:country":"US",
    "sg:address":"3415 El Salido Parkway Suite B",
    "sg:city":"Cedar Park",
    "sg:classifiers":[
        {
            "category":"Health Services",
            "subcategory":"Dentist",
            "type":"Services"
        }
    ],
    "sg:phone":"+1 512 219 5200",
    "sg:postcode":"78613",
    "sg:province":"TX",
    "wof:name":"Austin Endodontics Llp",
    "wof:placetype":"venue"
},
  "geometry": {"coordinates":[-97.824921,30.458401],"type":"Point"}
}