{
  "type": "Feature",
  "properties": {
    "iso:country":"US",
    "sg:address":"934 W 14th St",
    "sg:city":"Port Arthur",
    "sg:classifiers":[
        {
            "category":"Organizations",
            "subcategory":"Community Association",
            "type":"Services"
        }
    ],
    "sg:phone":"+1 409 982 3568",
    "sg:postcode":"77640",
    "sg:province":"TX",
    "wof:name":"Prince Hall Village Nghbrhd",
    "wof:placetype":"venue"
},
  "geometry": {"coordinates":[-93.95485600000001,29.867688],"type":"Point"}
}