{
  "type": "Feature",
  "properties": {
    "iso:country":"US",
    "sg:address":"2216 FM 1960 W",
    "sg:city":"Houston",
    "sg:classifiers":[
        {
            "category":"Shopping",
            "subcategory":"Discount & Variety Stores",
            "type":"Retail Goods"
        }
    ],
    "sg:phone":"+1 281 586 9999",
    "sg:postcode":"77090",
    "sg:province":"TX",
    "sg:tags":[
        "merchandise",
        "general"
    ],
    "wof:name":"K F Ninety-Nine Cents Store",
    "wof:placetype":"venue"
},
  "geometry": {"coordinates":[-95.46092,30.00892],"type":"Point"}
}