{
  "type": "Feature",
  "properties": {
    "iso:country":"US",
    "sg:address":"5107 W McCormick Rd",
    "sg:city":"Amarillo",
    "sg:classifiers":[
        {
            "category":"Wholesale",
            "subcategory":"Construction Materials",
            "type":"Manufacturing & Wholesale Goods"
        }
    ],
    "sg:phone":"+1 806 622 1562",
    "sg:postcode":"79118",
    "sg:province":"TX",
    "sg:tags":[
        "building",
        "fabricated"
    ],
    "wof:name":"Ltd Portable Building",
    "wof:placetype":"venue"
},
  "geometry": {"coordinates":[-101.892538,35.07226],"type":"Point"}
}