{
  "type": "Feature",
  "properties": {
    "iso:country":"US",
    "sg:address":"377 W Campbell Rd",
    "sg:city":"Richardson",
    "sg:classifiers":[
        {
            "category":"Insurance",
            "subcategory":"Insurance Agent",
            "type":"Services"
        }
    ],
    "sg:phone":"+1 972 644 5665",
    "sg:postcode":"75080",
    "sg:province":"TX",
    "sg:website":"www.farmersinsurance.com",
    "wof:name":"Farmers Insurance Group",
    "wof:placetype":"venue"
},
  "geometry": {"coordinates":[-96.726142,32.975299],"type":"Point"}
}