{
  "type": "Feature",
  "properties": {
    "iso:country":"US",
    "sg:address":"624 N Madison Ave",
    "sg:city":"Dallas",
    "sg:classifiers":[
        {
            "category":"Building & Trades",
            "subcategory":"Cleaning & Sanitation",
            "type":"Services"
        }
    ],
    "sg:phone":"+1 214 946 3334",
    "sg:postcode":"75208",
    "sg:province":"TX",
    "sg:tags":[
        "house"
    ],
    "wof:name":"House Keeping By Sylvia",
    "wof:placetype":"venue"
},
  "geometry": {"coordinates":[-96.826508,32.750395],"type":"Point"}
}