{
  "type": "Feature",
  "properties": {
    "iso:country":"US",
    "sg:address":"115 Adams Ave",
    "sg:city":"Port O Connor",
    "sg:classifiers":[
        {
            "category":"Travel",
            "subcategory":"Hotels & Motels",
            "type":"Entertainment"
        }
    ],
    "sg:phone":"+1 361 983 2897",
    "sg:postcode":"77982",
    "sg:province":"TX",
    "sg:tags":[
        "tourist",
        "accommodation"
    ],
    "wof:name":"Port O'Connor Fishing Club",
    "wof:placetype":"venue"
},
  "geometry": {"coordinates":[-96.405703,28.448594],"type":"Point"}
}