{
  "type": "Feature",
  "properties": {
    "iso:country":"US",
    "sg:address":"313 E 12th St",
    "sg:city":"Austin",
    "sg:classifiers":[
        {
            "category":"Health Services",
            "subcategory":"Doctor",
            "type":"Services"
        }
    ],
    "sg:phone":"+1 512 324 8880",
    "sg:postcode":"78701",
    "sg:province":"TX",
    "sg:tags":[
        "medicine",
        "internal"
    ],
    "sg:website":"utexasphysicians.com",
    "wof:name":"Beth W. Miller, MD",
    "wof:placetype":"venue"
},
  "geometry": {"coordinates":[-97.737634,30.272703],"type":"Point"}
}