{
  "type": "Feature",
  "properties": {
    "iso:country":"US",
    "sg:address":"1815 W Tarrant Rd",
    "sg:city":"Grand Prairie",
    "sg:classifiers":[
        {
            "category":"Shopping",
            "subcategory":"Used Merchandise",
            "type":"Retail Goods"
        }
    ],
    "sg:phone":"+1 972 336 0200",
    "sg:postcode":"75050",
    "sg:province":"TX",
    "sg:tags":[
        "business"
    ],
    "wof:name":"Americash Communications",
    "wof:placetype":"venue"
},
  "geometry": {"coordinates":[-97.028267,32.756916],"type":"Point"}
}