{
  "type": "Feature",
  "properties": {
    "iso:country":"US",
    "sg:address":"2571 Highview Ter",
    "sg:city":"Fort Worth",
    "sg:classifiers":[
        {
            "category":"Education",
            "subcategory":"Special Training",
            "type":"Public Place"
        }
    ],
    "sg:phone":"+1 817 924 0373",
    "sg:postcode":"76109",
    "sg:province":"TX",
    "wof:name":"Show Plant Service",
    "wof:placetype":"venue"
},
  "geometry": {"coordinates":[-97.367953,32.714699],"type":"Point"}
}