{
  "type": "Feature",
  "properties": {
    "iso:country":"US",
    "sg:address":"8706 Weiser Dr",
    "sg:city":"Austin",
    "sg:classifiers":[
        {
            "category":"Retail",
            "subcategory":"Repair Shop",
            "type":"Services"
        }
    ],
    "sg:phone":"+1 512 258 1500",
    "sg:postcode":"78729",
    "sg:province":"TX",
    "sg:tags":[
        "equipment",
        "conditioning",
        "air"
    ],
    "wof:name":"New Results",
    "wof:placetype":"venue"
},
  "geometry": {"coordinates":[-97.77695799999999,30.446791],"type":"Point"}
}