{
  "type": "Feature",
  "properties": {
    "iso:country":"US",
    "sg:address":"4834 Top Line Dr",
    "sg:city":"Dallas",
    "sg:classifiers":[
        {
            "category":"Wholesale",
            "subcategory":"Auto Parts",
            "type":"Manufacturing & Wholesale Goods"
        }
    ],
    "sg:phone":"+1 214 631 1433",
    "sg:postcode":"75247",
    "sg:province":"TX",
    "sg:tags":[
        "engine"
    ],
    "wof:name":"H R Enterprises Inc",
    "wof:placetype":"venue"
},
  "geometry": {"coordinates":[-96.883805,32.807216],"type":"Point"}
}