{
  "type": "Feature",
  "properties": {
    "iso:country":"US",
    "sg:address":"3619 Crosby Cedar Bayou Rd",
    "sg:city":"Baytown",
    "sg:classifiers":[
        {
            "category":"Professional",
            "subcategory":"Business Services",
            "type":"Services"
        }
    ],
    "sg:phone":"+1 281 422 2218",
    "sg:postcode":"77521",
    "sg:province":"TX",
    "wof:name":"Brenda Purswell",
    "wof:placetype":"venue"
},
  "geometry": {"coordinates":[-94.93953999999999,29.765738],"type":"Point"}
}