{
  "type": "Feature",
  "properties": {
    "iso:country":"US",
    "sg:address":"2201 Monterrey Ave",
    "sg:city":"Laredo",
    "sg:classifiers":[
        {
            "category":"Personal",
            "subcategory":"Beauty Salon",
            "type":"Services"
        }
    ],
    "sg:phone":"+1 956 727 5016",
    "sg:postcode":"78040",
    "sg:province":"TX",
    "wof:name":"Dsexy By Manuelitas",
    "wof:placetype":"venue"
},
  "geometry": {"coordinates":[-99.49588799999999,27.515779],"type":"Point"}
}