{
  "type": "Feature",
  "properties": {
    "iso:country":"US",
    "sg:address":"1200 Lake Woodlands Dr",
    "sg:city":"Spring",
    "sg:classifiers":[
        {
            "category":"Shopping",
            "subcategory":"Clothing, Apparel, & Fashions",
            "type":"Retail Goods"
        }
    ],
    "sg:phone":"+1 281 364 8227",
    "sg:postcode":"77380",
    "sg:province":"TX",
    "wof:name":"Lerner New York",
    "wof:placetype":"venue"
},
  "geometry": {"coordinates":[-95.455091,30.167612],"type":"Point"}
}