{
  "type": "Feature",
  "properties": {
    "iso:country":"US",
    "sg:address":"285 Mesquite Dr",
    "sg:city":"Cedar Creek",
    "sg:classifiers":[
        {
            "category":"Shopping",
            "subcategory":"Computers & Home Electronics",
            "type":"Retail Goods"
        }
    ],
    "sg:phone":"+1 512 581 3069",
    "sg:postcode":"78612",
    "sg:province":"TX",
    "sg:tags":[
        "repair"
    ],
    "wof:name":"Daystar Satellite",
    "wof:placetype":"venue"
},
  "geometry": {"coordinates":[-97.52065399999999,30.062067],"type":"Point"}
}