{
  "type": "Feature",
  "properties": {
    "iso:country":"US",
    "sg:address":"11125 Avering Ln",
    "sg:city":"Austin",
    "sg:classifiers":[
        {
            "category":"Restaurant",
            "type":"Food & Drink"
        }
    ],
    "sg:phone":"+1 512 272 5193",
    "sg:postcode":"78754",
    "sg:province":"TX",
    "sg:tags":[
        "cafeteria",
        "contract"
    ],
    "wof:name":"Happy Goods Inc",
    "wof:placetype":"venue"
},
  "geometry": {"coordinates":[-97.61042399999999,30.343545],"type":"Point"}
}