{
  "type": "Feature",
  "properties": {
    "iso:country":"US",
    "sg:address":"6805 Falcata Cove",
    "sg:city":"Austin",
    "sg:classifiers":[
        {
            "category":"Real Estate",
            "subcategory":"Real Estate Agent",
            "type":"Services"
        }
    ],
    "sg:phone":"+1 512 658 7287",
    "sg:postcode":"78750",
    "sg:province":"TX",
    "wof:name":"American Affordable Homes LP",
    "wof:placetype":"venue"
},
  "geometry": {"coordinates":[-97.79571300000001,30.374746],"type":"Point"}
}