{
  "type": "Feature",
  "properties": {
    "iso:country":"US",
    "sg:address":"706 Main St Bsmt",
    "sg:city":"Dallas",
    "sg:classifiers":[
        {
            "category":"Professional",
            "subcategory":"Advertising",
            "type":"Services"
        },
        {
            "category":"Communications",
            "subcategory":"Newspaper",
            "type":"Services"
        }
    ],
    "sg:phone":"+1 214 741 6366",
    "sg:postcode":"75202",
    "sg:province":"TX",
    "sg:tags":[
        "print",
        "medium"
    ],
    "sg:website":"www.dailycommercialrecord.com",
    "wof:name":"Daily Commercial Record",
    "wof:placetype":"venue"
},
  "geometry": {"coordinates":[-96.806,32.779202],"type":"Point"}
}