{
  "type": "Feature",
  "properties": {
    "iso:country":"US",
    "sg:address":"623 el Dorado Blvd",
    "sg:city":"Houston",
    "sg:classifiers":[
        {
            "category":"Building & Trades",
            "subcategory":"Landscaping Services",
            "type":"Services"
        }
    ],
    "sg:phone":"+1 281 488 4888",
    "sg:postcode":"77062",
    "sg:province":"TX",
    "wof:name":"Cost Cutters Lawnservice",
    "wof:placetype":"venue"
},
  "geometry": {"coordinates":[-95.13967,29.562689],"type":"Point"}
}