{
  "type": "Feature",
  "properties": {
    "iso:country":"US",
    "sg:address":"436 State Highway 72 E",
    "sg:city":"Yorktown",
    "sg:classifiers":[
        {
            "category":"Travel",
            "subcategory":"Hotels & Motels",
            "type":"Entertainment"
        }
    ],
    "sg:phone":"+1 361 564 2421",
    "sg:postcode":"78164",
    "sg:province":"TX",
    "wof:name":"White Top Motel",
    "wof:placetype":"venue"
},
  "geometry": {"coordinates":[-97.49738600000001,28.98199],"type":"Point"}
}