{
  "type": "Feature",
  "properties": {
    "iso:country":"US",
    "sg:address":"2525 S Shore Blvd",
    "sg:city":"League City",
    "sg:classifiers":[
        {
            "category":"Health Services",
            "subcategory":"Doctor",
            "type":"Services"
        }
    ],
    "sg:phone":"+1 281 538 6600",
    "sg:postcode":"77573",
    "sg:province":"TX",
    "sg:tags":[
        "medical"
    ],
    "wof:name":"S Texas Asthtic Enchncment Ctr",
    "wof:placetype":"venue"
},
  "geometry": {"coordinates":[-95.06412899999999,29.542084],"type":"Point"}
}