{
  "type": "Feature",
  "properties": {
    "iso:country":"US",
    "sg:address":"24507 Rolling Meadow Dr",
    "sg:city":"Tomball",
    "sg:classifiers":[
        {
            "category":"Shopping",
            "subcategory":"Crafts & Fabrics",
            "type":"Retail Goods"
        }
    ],
    "sg:phone":"+1 281 357 0758",
    "sg:postcode":"77375",
    "sg:province":"TX",
    "sg:tags":[
        "supply"
    ],
    "wof:name":"Just My Thing",
    "wof:placetype":"venue"
},
  "geometry": {"coordinates":[-95.58577099999999,30.114529],"type":"Point"}
}