{
  "type": "Feature",
  "properties": {
    "iso:country":"US",
    "sg:address":"2304 Elderoaks Ln",
    "sg:city":"Dallas",
    "sg:classifiers":[
        {
            "category":"Shopping",
            "subcategory":"Clothing, Apparel, & Fashions",
            "type":"Retail Goods"
        }
    ],
    "sg:phone":"+1 214 330 7381",
    "sg:postcode":"75232",
    "sg:province":"TX",
    "wof:name":"Clothing Leaders O Tomorrow",
    "wof:placetype":"venue"
},
  "geometry": {"coordinates":[-96.85511200000001,32.663231],"type":"Point"}
}