{
  "type": "Feature",
  "properties": {
    "iso:country":"US",
    "sg:address":"28486 Preakness Ln",
    "sg:city":"Fair Oaks Ranch",
    "sg:classifiers":[
        {
            "category":"Building & Trades",
            "subcategory":"Construction",
            "type":"Services"
        }
    ],
    "sg:phone":"+1 210 698 2774",
    "sg:postcode":"78015",
    "sg:province":"TX",
    "sg:tags":[
        "home",
        "builder"
    ],
    "wof:name":"Essick Enterprises Inc",
    "wof:placetype":"venue"
},
  "geometry": {"coordinates":[-98.63009,29.724732],"type":"Point"}
}