{
  "type": "Feature",
  "properties": {
    "iso:country":"US",
    "sg:address":"151 Fox Rd",
    "sg:city":"Weatherford",
    "sg:classifiers":[
        {
            "category":"Communications",
            "subcategory":"Radio Station",
            "type":"Services"
        }
    ],
    "sg:phone":"+1 940 325 9509",
    "sg:postcode":"76068",
    "sg:province":"TX",
    "sg:tags":[
        "company",
        "broadcasting"
    ],
    "wof:name":"KYXS",
    "wof:placetype":"venue"
},
  "geometry": {"coordinates":[-97.910456,32.780961],"type":"Point"}
}