{
  "type": "Feature",
  "properties": {
    "iso:country":"US",
    "sg:address":"5508 W Highway 290",
    "sg:city":"Austin",
    "sg:classifiers":[
        {
            "category":"Banks & Credit Unions",
            "subcategory":"Financial Services",
            "type":"Services"
        }
    ],
    "sg:phone":"+1 512 327 3447",
    "sg:postcode":"78735",
    "sg:province":"TX",
    "sg:tags":[
        "broker",
        "mortgage"
    ],
    "sg:website":"www.rapiddocs.com",
    "wof:name":"Rapiddocs",
    "wof:placetype":"venue"
},
  "geometry": {"coordinates":[-97.87660200000001,30.256599],"type":"Point"}
}