{
  "type": "Feature",
  "properties": {
    "iso:country":"US",
    "sg:address":"2412 Arbuckle Ct",
    "sg:city":"Dallas",
    "sg:classifiers":[
        {
            "category":"Health Services",
            "subcategory":"Medical Lab",
            "type":"Services"
        }
    ],
    "sg:phone":"+1 972 241 1388",
    "sg:postcode":"75229",
    "sg:province":"TX",
    "sg:tags":[
        "laboratories-pathological",
        "laboratory"
    ],
    "wof:name":"Alternative Biomedical Solutions Gp",
    "wof:placetype":"venue"
},
  "geometry": {"coordinates":[-96.894606,32.885061],"type":"Point"}
}