{
  "type": "Feature",
  "properties": {
    "iso:country":"US",
    "sg:address":"3333 Hansboro Ave",
    "sg:city":"Dallas",
    "sg:classifiers":[
        {
            "category":"Personal",
            "subcategory":"Beauty Salon",
            "type":"Services"
        }
    ],
    "sg:phone":"+1 214 467 9112",
    "sg:postcode":"75233",
    "sg:province":"TX",
    "wof:name":"Debra Clark",
    "wof:placetype":"venue"
},
  "geometry": {"coordinates":[-96.875721,32.715573],"type":"Point"}
}