{
  "type": "Feature",
  "properties": {
    "iso:country":"US",
    "sg:address":"5809 Royal Ridge",
    "sg:city":"San Antonio",
    "sg:classifiers":[
        {
            "category":"Building & Trades",
            "subcategory":"Construction",
            "type":"Services"
        }
    ],
    "sg:phone":"+1 210 967 4427",
    "sg:postcode":"78239",
    "sg:province":"TX",
    "sg:tags":[
        "home",
        "builder"
    ],
    "wof:name":"Saco Homes",
    "wof:placetype":"venue"
},
  "geometry": {"coordinates":[-98.374543,29.534375],"type":"Point"}
}