{
  "type": "Feature",
  "properties": {
    "iso:country":"US",
    "sg:address":"1530 Forest Ln S",
    "sg:city":"Garland",
    "sg:classifiers":[
        {
            "category":"Health Services",
            "subcategory":"Dentist",
            "type":"Services"
        }
    ],
    "sg:phone":"+1 972 272 8571",
    "sg:postcode":"75042",
    "sg:province":"TX",
    "wof:name":"McNeill Robert G DDS MD PA",
    "wof:placetype":"venue"
},
  "geometry": {"coordinates":[-96.64895199999999,32.908837],"type":"Point"}
}