{
  "type": "Feature",
  "properties": {
    "iso:country":"US",
    "sg:address":"7405 Carrie Ln",
    "sg:city":"Deer Park",
    "sg:classifiers":[
        {
            "category":"Health Services",
            "subcategory":"Clinic",
            "type":"Services"
        }
    ],
    "sg:phone":"+1 281 476 4196",
    "sg:postcode":"77536",
    "sg:province":"TX",
    "wof:name":"EZ Access Mental Health Care E",
    "wof:placetype":"venue"
},
  "geometry": {"coordinates":[-95.124842,29.665943],"type":"Point"}
}