{
  "type": "Feature",
  "properties": {
    "iso:country":"US",
    "sg:address":"2959 S Buckner Blvd",
    "sg:city":"Dallas",
    "sg:classifiers":[
        {
            "category":"Health Services",
            "subcategory":"Doctor",
            "type":"Services"
        }
    ],
    "sg:phone":"+1 214 623 6406",
    "sg:postcode":"75227",
    "sg:province":"TX",
    "wof:name":"Familia Care",
    "wof:placetype":"venue"
},
  "geometry": {"coordinates":[-96.682954,32.762021],"type":"Point"}
}