{
  "type": "Feature",
  "properties": {
    "iso:country":"US",
    "sg:address":"3310 N 27th St",
    "sg:city":"Waco",
    "sg:classifiers":[
        {
            "category":"Building & Trades",
            "subcategory":"Landscaping Services",
            "type":"Services"
        }
    ],
    "sg:phone":"+1 254 753 4719",
    "sg:postcode":"76708",
    "sg:province":"TX",
    "sg:tags":[
        "landscape",
        "contractor"
    ],
    "wof:name":"Mohan Lawn Co",
    "wof:placetype":"venue"
},
  "geometry": {"coordinates":[-97.18052400000001,31.573477],"type":"Point"}
}