{
  "type": "Feature",
  "properties": {
    "iso:country":"US",
    "sg:address":"101 S Dallas St",
    "sg:city":"Ennis",
    "sg:classifiers":[
        {
            "category":"Shopping",
            "subcategory":"Gifts & Souvenirs",
            "type":"Retail Goods"
        }
    ],
    "sg:phone":"+1 972 875 4903",
    "sg:postcode":"75119",
    "sg:province":"TX",
    "sg:tags":[
        "shop"
    ],
    "wof:name":"On The Mezzanine",
    "wof:placetype":"venue"
},
  "geometry": {"coordinates":[-96.628073,32.327351],"type":"Point"}
}