{
  "type": "Feature",
  "properties": {
    "iso:country":"US",
    "sg:address":"1314 34th St",
    "sg:city":"Lubbock",
    "sg:classifiers":[
        {
            "category":"Building & Trades",
            "subcategory":"Construction",
            "type":"Services"
        }
    ],
    "sg:phone":"+1 806 747 9545",
    "sg:postcode":"79411",
    "sg:province":"TX",
    "sg:tags":[
        "contractor"
    ],
    "wof:name":"Johns Body & Paint",
    "wof:placetype":"venue"
},
  "geometry": {"coordinates":[-101.85094100000001,33.563279],"type":"Point"}
}