{
  "type": "Feature",
  "properties": {
    "iso:country":"US",
    "sg:address":"45 Teakwood Ln",
    "sg:city":"Abilene",
    "sg:classifiers":[
        {
            "category":"Building & Trades",
            "subcategory":"Construction",
            "type":"Services"
        }
    ],
    "sg:phone":"+1 325 676 8381",
    "sg:postcode":"79601",
    "sg:province":"TX",
    "sg:tags":[
        "floor",
        "laying",
        "contractor"
    ],
    "wof:name":"Laying On of Hands",
    "wof:placetype":"venue"
},
  "geometry": {"coordinates":[-99.698104,32.460731],"type":"Point"}
}