{
  "type": "Feature",
  "properties": {
    "iso:country":"US",
    "sg:address":"205 E Ave J",
    "sg:city":"Silsbee",
    "sg:classifiers":[
        {
            "category":"Communications",
            "subcategory":"Television Station",
            "type":"Services"
        }
    ],
    "sg:phone":"+1 409 385 5953",
    "sg:postcode":"77656",
    "sg:province":"TX",
    "sg:tags":[
        "broadcasting",
        "co"
    ],
    "wof:name":"Time Warner Communications",
    "wof:placetype":"venue"
},
  "geometry": {"coordinates":[-94.17751800000001,30.347507],"type":"Point"}
}