{
  "type": "Feature",
  "properties": {
    "iso:country":"US",
    "sg:address":"4215 Calder Ave",
    "sg:city":"Beaumont",
    "sg:classifiers":[
        {
            "category":"Home & Garden",
            "subcategory":"Building Materials",
            "type":"Retail Goods"
        }
    ],
    "sg:phone":"+1 409 892 4686",
    "sg:postcode":"77706",
    "sg:province":"TX",
    "sg:tags":[
        "wallpaper"
    ],
    "wof:name":"Wallpapers & Etc",
    "wof:placetype":"venue"
},
  "geometry": {"coordinates":[-94.14749500000001,30.085953],"type":"Point"}
}