{
  "type": "Feature",
  "properties": {
    "iso:country":"US",
    "sg:address":"1413 S 3rd St",
    "sg:city":"Temple",
    "sg:classifiers":[
        {
            "category":"Shopping",
            "subcategory":"Gifts & Souvenirs",
            "type":"Retail Goods"
        }
    ],
    "sg:phone":"+1 254 778 7832",
    "sg:postcode":"76504",
    "sg:province":"TX",
    "wof:name":"Gwen Dumas Gifts",
    "wof:placetype":"venue"
},
  "geometry": {"coordinates":[-97.348403,31.082776],"type":"Point"}
}