{
  "type": "Feature",
  "properties": {
    "iso:country":"US",
    "sg:address":"2621 Jones Rd",
    "sg:city":"Austin",
    "sg:classifiers":[
        {
            "category":"Home & Garden",
            "subcategory":"Building Materials",
            "type":"Retail Goods"
        }
    ],
    "sg:phone":"+1 512 288 2848",
    "sg:postcode":"78745",
    "sg:province":"TX",
    "sg:tags":[
        "energy",
        "conservation",
        "prod"
    ],
    "wof:name":"Austin Air Duct",
    "wof:placetype":"venue"
},
  "geometry": {"coordinates":[-97.802812,30.224979],"type":"Point"}
}