{
  "type": "Feature",
  "properties": {
    "iso:country":"US",
    "sg:address":"3740 N Josey Ln Ste 118",
    "sg:city":"Carrollton",
    "sg:classifiers":[
        {
            "category":"Health Services",
            "subcategory":"Dentist",
            "type":"Services"
        }
    ],
    "sg:phone":"+1 972 394 9224",
    "sg:postcode":"75007",
    "sg:province":"TX",
    "sg:website":"www.scaggsdds.com",
    "wof:name":"Scaggs Melissa S DDS",
    "wof:placetype":"venue"
},
  "geometry": {"coordinates":[-96.886743,33.400661],"type":"Point"}
}