{
  "type": "Feature",
  "properties": {
    "iso:country":"US",
    "sg:address":"3205 Lakeview St",
    "sg:city":"Bryan",
    "sg:classifiers":[
        {
            "category":"Organizations",
            "subcategory":"Religious Organization",
            "type":"Services"
        }
    ],
    "sg:phone":"+1 979 823 5747",
    "sg:postcode":"77801",
    "sg:province":"TX",
    "wof:name":"Central Christian Church",
    "wof:placetype":"venue"
},
  "geometry": {"coordinates":[-96.35950099999999,30.638136],"type":"Point"}
}