{
  "type": "Feature",
  "properties": {
    "iso:country":"US",
    "sg:address":"7432 Reindeer Trl",
    "sg:city":"San Antonio",
    "sg:classifiers":[
        {
            "category":"Restaurant",
            "type":"Food & Drink"
        }
    ],
    "sg:phone":"+1 210 256 6690",
    "sg:postcode":"78238",
    "sg:province":"TX",
    "wof:name":"Villarreal Distributors",
    "wof:placetype":"venue"
},
  "geometry": {"coordinates":[-98.62970199999999,29.500846],"type":"Point"}
}