{
  "type": "Feature",
  "properties": {
    "iso:country":"US",
    "sg:address":"130 Farm Dale Ct",
    "sg:city":"Georgetown",
    "sg:classifiers":[
        {
            "category":"Social Services",
            "subcategory":"Child Care",
            "type":"Services"
        }
    ],
    "sg:phone":"+1 512 746 4220",
    "sg:postcode":"78626",
    "sg:province":"TX",
    "sg:tags":[
        "day"
    ],
    "wof:name":"Patricia Pena Childcare",
    "wof:placetype":"venue"
},
  "geometry": {"coordinates":[-97.62359499999999,30.730489],"type":"Point"}
}