{
  "type": "Feature",
  "properties": {
    "iso:country":"US",
    "sg:address":"2506 Brittany Dr",
    "sg:city":"Rowlett",
    "sg:classifiers":[
        {
            "category":"Shopping",
            "type":"Retail Goods"
        }
    ],
    "sg:phone":"+1 972 463 6819",
    "sg:postcode":"75088",
    "sg:province":"TX",
    "sg:tags":[
        "merchandise"
    ],
    "wof:name":"Peace of Mind Pet Care LLC",
    "wof:placetype":"venue"
},
  "geometry": {"coordinates":[-96.55755600000001,32.88482],"type":"Point"}
}