{
  "type": "Feature",
  "properties": {
    "iso:country":"US",
    "sg:address":"301 State Hwy 323 NW",
    "sg:city":"Tyler",
    "sg:classifiers":[
        {
            "category":"Wholesale",
            "subcategory":"Construction Materials",
            "type":"Manufacturing & Wholesale Goods"
        },
        {
            "category":"Manufacturing",
            "subcategory":"Building Materials",
            "type":"Manufacturing & Wholesale Goods"
        }
    ],
    "sg:phone":"+1 903 597 2203",
    "sg:postcode":"75702",
    "sg:province":"TX",
    "sg:tags":[
        "supply"
    ],
    "wof:name":"Tyler Millwork & Supply Inc",
    "wof:placetype":"venue"
},
  "geometry": {"coordinates":[-95.343273,32.357774],"type":"Point"}
}