{
  "type": "Feature",
  "properties": {
    "iso:country":"US",
    "sg:address":"9842 Audelia Rd",
    "sg:city":"Dallas",
    "sg:classifiers":[
        {
            "category":"Arts & Performance",
            "subcategory":"Theater",
            "type":"Entertainment"
        }
    ],
    "sg:phone":"+1 469 364 9433",
    "sg:postcode":"75238",
    "sg:province":"TX",
    "sg:tags":[
        "bureau"
    ],
    "wof:name":"Dre Ski Entertainment",
    "wof:placetype":"venue"
},
  "geometry": {"coordinates":[-96.717879,32.880487],"type":"Point"}
}