{
  "type": "Feature",
  "properties": {
    "iso:country":"US",
    "sg:address":"1274 Blake Rd",
    "sg:city":"Conroe",
    "sg:classifiers":[
        {
            "category":"Professional",
            "subcategory":"Business Services",
            "type":"Services"
        }
    ],
    "sg:phone":"+1 281 353 8146",
    "sg:postcode":"77304",
    "sg:province":"TX",
    "sg:tags":[
        "interior",
        "mfg",
        "designer",
        "drapery",
        "custom"
    ],
    "wof:name":"Tippi Reinhardt Interiors",
    "wof:placetype":"venue"
},
  "geometry": {"coordinates":[-95.55470200000001,30.338212],"type":"Point"}
}