{
  "type": "Feature",
  "properties": {
    "iso:country":"US",
    "sg:address":"2325 Bethlehem Rd",
    "sg:city":"Lufkin",
    "sg:classifiers":[
        {
            "category":"Building & Trades",
            "subcategory":"Construction",
            "type":"Services"
        }
    ],
    "sg:phone":"+1 936 875 2772",
    "sg:postcode":"75904",
    "sg:province":"TX",
    "sg:tags":[
        "excavating",
        "contractor"
    ],
    "wof:name":"C & L Trucking Co",
    "wof:placetype":"venue"
},
  "geometry": {"coordinates":[-94.823052,31.355933],"type":"Point"}
}