{
  "type": "Feature",
  "properties": {
    "iso:country":"US",
    "sg:address":"3250 W Pleasant Run Rd",
    "sg:city":"Lancaster",
    "sg:classifiers":[
        {
            "category":"Food & Beverages",
            "subcategory":"Specialty",
            "type":"Retail Goods"
        }
    ],
    "sg:phone":"+1 972 230 2610",
    "sg:postcode":"75146",
    "sg:province":"TX",
    "sg:tags":[
        "tea",
        "coffee"
    ],
    "wof:name":"Java Jacks",
    "wof:placetype":"venue"
},
  "geometry": {"coordinates":[-96.820763,32.60418],"type":"Point"}
}