{
  "type": "Feature",
  "properties": {
    "iso:country":"US",
    "sg:address":"110 Lee St",
    "sg:city":"Irving",
    "sg:classifiers":[
        {
            "category":"Shopping",
            "subcategory":"Computers & Home Electronics",
            "type":"Retail Goods"
        }
    ],
    "sg:phone":"+1 972 579 1227",
    "sg:postcode":"75060",
    "sg:province":"TX",
    "wof:name":"Larry Bell Consulting",
    "wof:placetype":"venue"
},
  "geometry": {"coordinates":[-96.93724400000001,32.813001],"type":"Point"}
}