{
  "type": "Feature",
  "properties": {
    "iso:country":"US",
    "sg:address":"1212 Harrison Ave",
    "sg:city":"Arlington",
    "sg:classifiers":[
        {
            "category":"Utilities",
            "subcategory":"Refuse",
            "type":"Services"
        },
        {
            "category":"Utilities",
            "subcategory":"Recycling",
            "type":"Services"
        }
    ],
    "sg:phone":"+1 817 317 2000",
    "sg:postcode":"76011",
    "sg:province":"TX",
    "sg:tags":[
        "trash",
        "container",
        "rubbish",
        "garbage",
        "disposal",
        "hauling",
        "collection",
        "removal",
        "equipment",
        "dumpster",
        "waste"
    ],
    "sg:website":"http://www-duncandisposal-com.netsolads.com/?_nsag=40664",
    "wof:name":"Duncan Disposal - Arlington",
    "wof:placetype":"venue"
},
  "geometry": {"coordinates":[-97.09220999999999,32.738118],"type":"Point"}
}