{
  "type": "Feature",
  "properties": {
    "iso:country":"US",
    "sg:address":"2210 Milam St",
    "sg:city":"Uvalde",
    "sg:classifiers":[
        {
            "category":"Professional",
            "type":"Services"
        }
    ],
    "sg:phone":"+1 830 591 0141",
    "sg:postcode":"78801",
    "sg:province":"TX",
    "sg:tags":[
        "establishment"
    ],
    "wof:name":"Middle Rio Grande Workforce",
    "wof:placetype":"venue"
},
  "geometry": {"coordinates":[-99.791954,29.2377],"type":"Point"}
}