{
  "type": "Feature",
  "properties": {
    "iso:country":"US",
    "sg:address":"555 Venture Blvd S",
    "sg:city":"Leander",
    "sg:classifiers":[
        {
            "category":"Organizations",
            "subcategory":"Community Association",
            "type":"Services"
        }
    ],
    "sg:phone":"+1 512 267 1128",
    "sg:postcode":"78645",
    "sg:province":"TX",
    "sg:tags":[
        "owner",
        "property"
    ],
    "wof:name":"Point Venture Property Owners",
    "wof:placetype":"venue"
},
  "geometry": {"coordinates":[-97.995441,30.380221],"type":"Point"}
}