{
  "type": "Feature",
  "properties": {
    "iso:country":"US",
    "sg:address":"301 E Tom Landry St",
    "sg:city":"Mission",
    "sg:classifiers":[
        {
            "category":"Professional",
            "subcategory":"Lawyer & Legal Services",
            "type":"Services"
        }
    ],
    "sg:phone":"+1 956 585 1622",
    "sg:postcode":"78572",
    "sg:province":"TX",
    "sg:tags":[
        "attorney",
        "practice",
        "plan"
    ],
    "wof:name":"Garcia, Esmeralda",
    "wof:placetype":"venue"
},
  "geometry": {"coordinates":[-98.323402,26.215622],"type":"Point"}
}