{
  "type": "Feature",
  "properties": {
    "iso:country":"US",
    "sg:address":"2333 Hillsboro Ave",
    "sg:city":"Dallas",
    "sg:classifiers":[
        {
            "category":"Retail",
            "subcategory":"Auto Repair",
            "type":"Services"
        }
    ],
    "sg:phone":"+1 214 827 2006",
    "sg:postcode":"75228",
    "sg:province":"TX",
    "sg:tags":[
        "automotive"
    ],
    "wof:name":"Energy In Tune",
    "wof:placetype":"venue"
},
  "geometry": {"coordinates":[-96.67371,32.816082],"type":"Point"}
}