{
  "type": "Feature",
  "properties": {
    "iso:country":"US",
    "sg:address":"7205 W 34th Ave",
    "sg:city":"Amarillo",
    "sg:classifiers":[
        {
            "category":"Retail",
            "subcategory":"Auto Repair",
            "type":"Services"
        }
    ],
    "sg:phone":"+1 806 358 2727",
    "sg:postcode":"79109",
    "sg:province":"TX",
    "sg:tags":[
        "automobile",
        "lube",
        "lubrication"
    ],
    "wof:name":"Precision Lube Inc",
    "wof:placetype":"venue"
},
  "geometry": {"coordinates":[-101.91790399999999,35.176447],"type":"Point"}
}