{
  "type": "Feature",
  "properties": {
    "iso:country":"US",
    "sg:address":"209 W Hickory St",
    "sg:city":"Denton",
    "sg:classifiers":[
        {
            "category":"Shopping",
            "subcategory":"Gifts & Souvenirs",
            "type":"Retail Goods"
        }
    ],
    "sg:phone":"+1 940 387 8863",
    "sg:postcode":"76201",
    "sg:province":"TX",
    "wof:name":"Garden Gate",
    "wof:placetype":"venue"
},
  "geometry": {"coordinates":[-97.134287,33.21457],"type":"Point"}
}