{
  "type": "Feature",
  "properties": {
    "iso:country":"US",
    "sg:address":"8506 Speedway Dr",
    "sg:city":"San Antonio",
    "sg:classifiers":[
        {
            "category":"Building & Trades",
            "subcategory":"Construction",
            "type":"Services"
        }
    ],
    "sg:phone":"+1 210 366 4299",
    "sg:postcode":"78230",
    "sg:province":"TX",
    "wof:name":"Tidewater Contracting LLC",
    "wof:placetype":"venue"
},
  "geometry": {"coordinates":[-98.531448,29.51581],"type":"Point"}
}