{
  "type": "Feature",
  "properties": {
    "iso:country":"US",
    "sg:address":"4988 Hondo Pass Ave",
    "sg:city":"El Paso",
    "sg:classifiers":[
        {
            "category":"Food & Beverages",
            "subcategory":"Meat & Fish",
            "type":"Retail Goods"
        }
    ],
    "sg:phone":"+1 915 757 0577",
    "sg:postcode":"79924",
    "sg:province":"TX",
    "wof:name":"Aurora Meat Market",
    "wof:placetype":"venue"
},
  "geometry": {"coordinates":[-106.4273,31.869781],"type":"Point"}
}