{
  "type": "Feature",
  "properties": {
    "iso:country":"US",
    "sg:address":"12755 Satinwood",
    "sg:city":"Beaumont",
    "sg:classifiers":[
        {
            "category":"Education",
            "subcategory":"Special Training",
            "type":"Public Place"
        }
    ],
    "sg:phone":"+1 409 753 3541",
    "sg:postcode":"77713",
    "sg:province":"TX",
    "wof:name":"Jch Piano Studio",
    "wof:placetype":"venue"
},
  "geometry": {"coordinates":[-94.248493,30.140955],"type":"Point"}
}