{
  "type": "Feature",
  "properties": {
    "iso:country":"US",
    "sg:address":"1505 Ford St",
    "sg:city":"Llano",
    "sg:classifiers":[
        {
            "category":"Wholesale",
            "subcategory":"Farm Supplies",
            "type":"Manufacturing & Wholesale Goods"
        },
        {
            "category":"Shopping",
            "type":"Retail Goods"
        }
    ],
    "sg:phone":"+1 325 247 5000",
    "sg:postcode":"78643",
    "sg:province":"TX",
    "sg:tags":[
        "feed",
        "item",
        "nursery",
        "seed"
    ],
    "wof:name":"Winkel's Feed",
    "wof:placetype":"venue"
},
  "geometry": {"coordinates":[-98.675968,30.743305],"type":"Point"}
}