{
  "type": "Feature",
  "properties": {
    "iso:country":"US",
    "sg:address":"800 Peterstow Dr",
    "sg:city":"Euless",
    "sg:classifiers":[
        {
            "category":"Professional",
            "subcategory":"Management & Consulting",
            "type":"Services"
        }
    ],
    "sg:phone":"+1 817 545 1396",
    "sg:postcode":"76039",
    "sg:province":"TX",
    "sg:tags":[
        "business"
    ],
    "wof:name":"Santiago Creative",
    "wof:placetype":"venue"
},
  "geometry": {"coordinates":[-97.096446,32.849092],"type":"Point"}
}