{
  "type": "Feature",
  "properties": {
    "iso:country":"US",
    "sg:address":"4730 14th St",
    "sg:city":"Bacliff",
    "sg:classifiers":[
        {
            "category":"Building & Trades",
            "subcategory":"Construction",
            "type":"Services"
        }
    ],
    "sg:phone":"+1 281 559 4282",
    "sg:postcode":"77518",
    "sg:province":"TX",
    "sg:tags":[
        "nonresidential"
    ],
    "wof:name":"Living Interscapes",
    "wof:placetype":"venue"
},
  "geometry": {"coordinates":[-94.98905499999999,29.501569],"type":"Point"}
}