{
  "type": "Feature",
  "properties": {
    "iso:country":"US",
    "sg:address":"4618 Blanco Rd",
    "sg:city":"San Antonio",
    "sg:classifiers":[
        {
            "category":"Retail",
            "subcategory":"Repair Shop",
            "type":"Services"
        }
    ],
    "sg:phone":"+1 210 434 0282",
    "sg:postcode":"78212",
    "sg:province":"TX",
    "sg:tags":[
        "appliance"
    ],
    "wof:name":"A & S Appliance",
    "wof:placetype":"venue"
},
  "geometry": {"coordinates":[-98.507757,29.490196],"type":"Point"}
}