{
  "type": "Feature",
  "properties": {
    "iso:country":"US",
    "sg:address":"120 W Nash St",
    "sg:city":"Terrell",
    "sg:classifiers":[
        {
            "category":"Recreation",
            "type":"Entertainment"
        }
    ],
    "sg:phone":"+1 972 563 6826",
    "sg:postcode":"75160",
    "sg:province":"TX",
    "sg:tags":[
        "hall",
        "auditorium"
    ],
    "wof:name":"Independent Order-Odd Fellows",
    "wof:placetype":"venue"
},
  "geometry": {"coordinates":[-96.277283,32.737551],"type":"Point"}
}