{
  "type": "Feature",
  "properties": {
    "iso:country":"US",
    "sg:address":"7676 Hillmont St",
    "sg:city":"Houston",
    "sg:classifiers":[
        {
            "category":"Banks & Credit Unions",
            "subcategory":"Financial Services",
            "type":"Services"
        }
    ],
    "sg:phone":"+1 713 860 6811",
    "sg:postcode":"77040",
    "sg:province":"TX",
    "sg:tags":[
        "company",
        "holding"
    ],
    "wof:name":"Senequier Holdings LP",
    "wof:placetype":"venue"
},
  "geometry": {"coordinates":[-95.50558700000001,29.843719],"type":"Point"}
}