{
  "type": "Feature",
  "properties": {
    "iso:country":"US",
    "sg:address":"7111 Harwin Dr Ste 270",
    "sg:city":"Houston",
    "sg:classifiers":[
        {
            "category":"Communications",
            "subcategory":"Radio Station",
            "type":"Services"
        }
    ],
    "sg:phone":"+1 713 781 5868",
    "sg:postcode":"77036",
    "sg:province":"TX",
    "wof:name":"Tnt Radio Houston",
    "wof:placetype":"venue"
},
  "geometry": {"coordinates":[-95.507797,29.7181],"type":"Point"}
}