{
  "type": "Feature",
  "properties": {
    "iso:country":"US",
    "sg:address":"605 N Main St",
    "sg:city":"Corsicana",
    "sg:classifiers":[
        {
            "category":"Social Services",
            "type":"Services"
        }
    ],
    "sg:phone":"+1 903 872 9112",
    "sg:postcode":"75110",
    "sg:province":"TX",
    "sg:tags":[
        "organization",
        "welfare"
    ],
    "wof:name":"Medical Social Svc",
    "wof:placetype":"venue"
},
  "geometry": {"coordinates":[-96.46932,32.099746],"type":"Point"}
}