{
  "type": "Feature",
  "properties": {
    "iso:country":"US",
    "sg:address":"175 Charles Ave",
    "sg:city":"Bridge City",
    "sg:classifiers":[
        {
            "category":"Shopping",
            "subcategory":"Hobbies, Toys, & Games",
            "type":"Retail Goods"
        }
    ],
    "sg:phone":"+1 409 697 3790",
    "sg:postcode":"77611",
    "sg:province":"TX",
    "wof:name":"A Pocket of Stars",
    "wof:placetype":"venue"
},
  "geometry": {"coordinates":[-93.836313,30.029225],"type":"Point"}
}