{
  "type": "Feature",
  "properties": {
    "iso:country":"US",
    "sg:address":"1155 N Zaragoza Rd",
    "sg:city":"El Paso",
    "sg:classifiers":[
        {
            "category":"Shopping",
            "subcategory":"Florist",
            "type":"Retail Goods"
        }
    ],
    "sg:phone":"+1 915 790 2121",
    "sg:postcode":"79907",
    "sg:province":"TX",
    "wof:name":"Floral & Balloon Design",
    "wof:placetype":"venue"
},
  "geometry": {"coordinates":[-106.307552,31.716859],"type":"Point"}
}