{
  "type": "Feature",
  "properties": {
    "iso:country":"US",
    "sg:address":"4245 N Central Expy",
    "sg:city":"Dallas",
    "sg:classifiers":[
        {
            "category":"Professional",
            "subcategory":"Management & Consulting",
            "type":"Services"
        }
    ],
    "sg:phone":"+1 214 521 8596",
    "sg:postcode":"75205",
    "sg:province":"TX",
    "sg:tags":[
        "counselor",
        "public",
        "relations"
    ],
    "sg:website":"www.mbapr.com",
    "wof:name":"Michael A Burns & Assoc",
    "wof:placetype":"venue"
},
  "geometry": {"coordinates":[-96.789514,32.816273],"type":"Point"}
}