{
  "type": "Feature",
  "properties": {
    "iso:country":"US",
    "sg:address":"211 26th St",
    "sg:city":"Lubbock",
    "sg:classifiers":[
        {
            "category":"Wholesale",
            "subcategory":"Stationery",
            "type":"Manufacturing & Wholesale Goods"
        }
    ],
    "sg:phone":"+1 806 749 7002",
    "sg:postcode":"79404",
    "sg:province":"TX",
    "sg:tags":[
        "packaging",
        "material"
    ],
    "wof:name":"Packaging Solutions",
    "wof:placetype":"venue"
},
  "geometry": {"coordinates":[-101.83689,33.570428],"type":"Point"}
}