{
  "type": "Feature",
  "properties": {
    "iso:country":"US",
    "sg:address":"15107 Oakmere St",
    "sg:city":"San Antonio",
    "sg:classifiers":[
        {
            "category":"Professional",
            "type":"Services"
        }
    ],
    "sg:phone":"+1 210 496 1406",
    "sg:postcode":"78232",
    "sg:province":"TX",
    "wof:name":"Rivara Inamaria",
    "wof:placetype":"venue"
},
  "geometry": {"coordinates":[-98.455918,29.578347],"type":"Point"}
}