{
  "type": "Feature",
  "properties": {
    "iso:country":"US",
    "sg:address":"1222 W Harrison Ave",
    "sg:city":"Harlingen",
    "sg:classifiers":[
        {
            "category":"Professional",
            "subcategory":"Lawyer & Legal Services",
            "type":"Services"
        }
    ],
    "sg:phone":"+1 956 440 8007",
    "sg:postcode":"78550",
    "sg:province":"TX",
    "sg:tags":[
        "attorney"
    ],
    "wof:name":"Ignacia Crowe",
    "wof:placetype":"venue"
},
  "geometry": {"coordinates":[-97.70926900000001,26.190719],"type":"Point"}
}