{
  "type": "Feature",
  "properties": {
    "iso:country":"US",
    "sg:address":"5204 Live Oak St",
    "sg:city":"Houston",
    "sg:classifiers":[
        {
            "category":"Restaurant",
            "type":"Food & Drink"
        }
    ],
    "sg:phone":"+1 713 529 3741",
    "sg:postcode":"77004",
    "sg:province":"TX",
    "sg:tags":[
        "eating"
    ],
    "wof:name":"Luddingtons Fine Foods",
    "wof:placetype":"venue"
},
  "geometry": {"coordinates":[-95.373288,29.71899],"type":"Point"}
}