{
  "type": "Feature",
  "properties": {
    "iso:country":"US",
    "sg:address":"300 W Main St",
    "sg:city":"Fredericksburg",
    "sg:classifiers":[
        {
            "category":"Banks & Credit Unions",
            "subcategory":"Bank",
            "type":"Services"
        }
    ],
    "sg:phone":"+1 830 997 2121",
    "sg:postcode":"78624",
    "sg:province":"TX",
    "sg:tags":[
        "federal",
        "savings",
        "institution"
    ],
    "wof:name":"Guaranty Bank",
    "wof:placetype":"venue"
},
  "geometry": {"coordinates":[-98.87734399999999,30.278803],"type":"Point"}
}