{
  "type": "Feature",
  "properties": {
    "iso:country":"US",
    "sg:address":"1204 W Expy 83",
    "sg:city":"Pharr",
    "sg:classifiers":[
        {
            "category":"Home & Garden",
            "subcategory":"Furniture",
            "type":"Retail Goods"
        }
    ],
    "sg:phone":"+1 956 283 9876",
    "sg:postcode":"78577",
    "sg:province":"TX",
    "wof:name":"Big Sur Waterbeds",
    "wof:placetype":"venue"
},
  "geometry": {"coordinates":[-98.197399,26.204405],"type":"Point"}
}