{
  "type": "Feature",
  "properties": {
    "iso:country":"US",
    "sg:address":"8501 Loomis Dr",
    "sg:city":"Plano",
    "sg:classifiers":[
        {
            "category":"Manufacturing",
            "subcategory":"Printing",
            "type":"Manufacturing & Wholesale Goods"
        }
    ],
    "sg:phone":"+1 972 335 1425",
    "sg:postcode":"75024",
    "sg:province":"TX",
    "sg:tags":[
        "publishing"
    ],
    "wof:name":"Mark Wessels Publications",
    "wof:placetype":"venue"
},
  "geometry": {"coordinates":[-96.783452,33.093731],"type":"Point"}
}