{
  "type": "Feature",
  "properties": {
    "iso:country":"US",
    "sg:address":"112 E Prairie St",
    "sg:city":"Denton",
    "sg:classifiers":[
        {
            "category":"Real Estate",
            "subcategory":"Real Estate Agent",
            "type":"Services"
        }
    ],
    "sg:phone":"+1 940 591 7774",
    "sg:postcode":"76201",
    "sg:province":"TX",
    "wof:name":"D Quad Properties",
    "wof:placetype":"venue"
},
  "geometry": {"coordinates":[-97.132375,33.210616],"type":"Point"}
}