{
  "type": "Feature",
  "properties": {
    "iso:country":"US",
    "sg:address":"2710 S Hulen St",
    "sg:city":"Fort Worth",
    "sg:classifiers":[
        {
            "category":"Restaurant",
            "type":"Food & Drink"
        }
    ],
    "sg:phone":"+1 817 921 4500",
    "sg:postcode":"76109",
    "sg:province":"TX",
    "wof:name":"Yogis Bagel Cafe Inc",
    "wof:placetype":"venue"
},
  "geometry": {"coordinates":[-97.386149,32.71143],"type":"Point"}
}