{
  "type": "Feature",
  "properties": {
    "iso:country":"US",
    "sg:address":"18410 Tranquility Dr",
    "sg:city":"Humble",
    "sg:classifiers":[
        {
            "category":"Wholesale",
            "subcategory":"Metals & Minerals",
            "type":"Manufacturing & Wholesale Goods"
        }
    ],
    "sg:phone":"+1 281 812 6753",
    "sg:postcode":"77346",
    "sg:province":"TX",
    "sg:tags":[
        "wa",
        "for",
        "fabricated",
        "water",
        "piping",
        "treatment"
    ],
    "wof:name":"Plant Piping Product Inc",
    "wof:placetype":"venue"
},
  "geometry": {"coordinates":[-95.15082,29.993663],"type":"Point"}
}