{
  "type": "Feature",
  "properties": {
    "iso:country":"US",
    "sg:address":"6929 Airport Blvd Ste 127",
    "sg:city":"Austin",
    "sg:classifiers":[
        {
            "category":"Food & Beverages",
            "subcategory":"Groceries & Convenience Stores",
            "type":"Retail Goods"
        }
    ],
    "sg:phone":"+1 512 421 1125",
    "sg:postcode":"78752",
    "sg:province":"TX",
    "sg:website":"www.heb.com",
    "wof:name":"H-E-B",
    "wof:placetype":"venue"
},
  "geometry": {"coordinates":[-97.717698,30.335853],"type":"Point"}
}