{
  "type": "Feature",
  "properties": {
    "iso:country":"US",
    "sg:address":"473 State Hwy 285",
    "sg:city":"Hebbronville",
    "sg:classifiers":[
        {
            "category":"Health Services",
            "subcategory":"Doctor",
            "type":"Services"
        }
    ],
    "sg:phone":"+1 361 527 4053",
    "sg:postcode":"78361",
    "sg:province":"TX",
    "sg:tags":[
        "physician",
        "surgeon"
    ],
    "wof:name":"Community Action Council Of Tx",
    "wof:placetype":"venue"
},
  "geometry": {"coordinates":[-98.67415099999999,27.299733],"type":"Point"}
}