{
  "type": "Feature",
  "properties": {
    "iso:country":"US",
    "sg:address":"495 Craig St",
    "sg:city":"Beaumont",
    "sg:classifiers":[
        {
            "category":"Professional",
            "subcategory":"Detective & Security Services",
            "type":"Services"
        }
    ],
    "sg:phone":"+1 409 832 0588",
    "sg:postcode":"77701",
    "sg:province":"TX",
    "sg:tags":[
        "investigator"
    ],
    "wof:name":"Linmarie Garsee & Assoc",
    "wof:placetype":"venue"
},
  "geometry": {"coordinates":[-94.09291899999999,30.071216],"type":"Point"}
}