{
  "type": "Feature",
  "properties": {
    "iso:country":"US",
    "sg:address":"1906 S Date St",
    "sg:city":"Plainview",
    "sg:classifiers":[
        {
            "category":"Professional",
            "type":"Services"
        }
    ],
    "sg:phone":"+1 806 293 1348",
    "sg:postcode":"79072",
    "sg:province":"TX",
    "wof:name":"Dan Holt",
    "wof:placetype":"venue"
},
  "geometry": {"coordinates":[-101.696399,34.16191],"type":"Point"}
}