{
  "type": "Feature",
  "properties": {
    "iso:country":"US",
    "sg:address":"511 Wayne Dr",
    "sg:city":"Woodway",
    "sg:classifiers":[
        {
            "category":"Sports & Exercise",
            "subcategory":"Gym",
            "type":"Entertainment"
        }
    ],
    "sg:phone":"+1 254 744 7157",
    "sg:postcode":"76712",
    "sg:province":"TX",
    "sg:tags":[
        "club",
        "health",
        "studio",
        "gymnasium"
    ],
    "wof:name":"Yoga Place",
    "wof:placetype":"venue"
},
  "geometry": {"coordinates":[-97.22689699999999,31.500871],"type":"Point"}
}