{
  "type": "Feature",
  "properties": {
    "iso:country":"US",
    "sg:address":"7501 Independence Pkwy",
    "sg:city":"Plano",
    "sg:classifiers":[
        {
            "category":"Education",
            "subcategory":"Library",
            "type":"Public Place"
        }
    ],
    "sg:phone":"+1 972 208 8000",
    "sg:postcode":"75025",
    "sg:province":"TX",
    "sg:website":"www.planolibrary.org",
    "wof:name":"Maribelle Davis Library",
    "wof:placetype":"venue"
},
  "geometry": {"coordinates":[-96.750148,33.08108],"type":"Point"}
}