{
  "type": "Feature",
  "properties": {
    "iso:country":"US",
    "sg:address":"2211 Maloney Ave",
    "sg:city":"Bryan",
    "sg:classifiers":[
        {
            "category":"Shopping",
            "subcategory":"Used Merchandise",
            "type":"Retail Goods"
        }
    ],
    "sg:phone":"+1 979 775 8122",
    "sg:postcode":"77801",
    "sg:province":"TX",
    "sg:tags":[
        "building",
        "material"
    ],
    "wof:name":"Re Store",
    "wof:placetype":"venue"
},
  "geometry": {"coordinates":[-96.361197,30.649143],"type":"Point"}
}