{
  "type": "Feature",
  "properties": {
    "iso:country":"US",
    "sg:address":"7710 Madonna Dr",
    "sg:city":"San Antonio",
    "sg:classifiers":[
        {
            "category":"Real Estate",
            "subcategory":"Real Estate Operator",
            "type":"Services"
        }
    ],
    "sg:phone":"+1 210 824 0165",
    "sg:postcode":"78216",
    "sg:province":"TX",
    "sg:tags":[
        "housing",
        "elderly"
    ],
    "wof:name":"Madonna Apartments",
    "wof:placetype":"venue"
},
  "geometry": {"coordinates":[-98.50135,29.504602],"type":"Point"}
}