{
  "type": "Feature",
  "properties": {
    "iso:country":"US",
    "sg:address":"9030 Betel Dr",
    "sg:city":"El Paso",
    "sg:classifiers":[
        {
            "category":"Professional",
            "subcategory":"Computer Services",
            "type":"Services"
        }
    ],
    "sg:phone":"+1 915 637 6441",
    "sg:postcode":"79907",
    "sg:province":"TX",
    "sg:tags":[
        "repair"
    ],
    "wof:name":"M & T Technologies",
    "wof:placetype":"venue"
},
  "geometry": {"coordinates":[-106.312746,31.706103],"type":"Point"}
}