{
  "type": "Feature",
  "properties": {
    "iso:country":"US",
    "sg:address":"1950 Highway 3",
    "sg:city":"Dickinson",
    "sg:classifiers":[
        {
            "category":"Place Of Worship",
            "subcategory":"Church",
            "type":"Public Place"
        },
        {
            "category":"Place Of Worship",
            "type":"Public Place"
        }
    ],
    "sg:phone":"+1 281 337 0895",
    "sg:postcode":"77539",
    "sg:province":"TX",
    "sg:tags":[
        "churches-baptist-general",
        "churches-baptist"
    ],
    "wof:name":"New Beginning Church",
    "wof:placetype":"venue"
},
  "geometry": {"coordinates":[-95.067509,29.477857],"type":"Point"}
}