{
  "type": "Feature",
  "properties": {
    "iso:country":"US",
    "sg:address":"1381 E College St",
    "sg:city":"Seguin",
    "sg:classifiers":[
        {
            "category":"Manufacturing",
            "subcategory":"Metals",
            "type":"Manufacturing & Wholesale Goods"
        },
        {
            "category":"Professional",
            "subcategory":"Business Services",
            "type":"Services"
        }
    ],
    "sg:phone":"+1 830 372 2330",
    "sg:postcode":"78155",
    "sg:province":"TX",
    "sg:tags":[
        "engraver"
    ],
    "wof:name":"Seguin Laser Art & Engraving",
    "wof:placetype":"venue"
},
  "geometry": {"coordinates":[-97.947821,29.574673],"type":"Point"}
}