{
  "type": "Feature",
  "properties": {
    "iso:country":"US",
    "sg:address":"3228 Keller Hicks Rd",
    "sg:city":"Keller",
    "sg:classifiers":[
        {
            "category":"Professional",
            "type":"Services"
        }
    ],
    "sg:phone":"+1 817 337 0163",
    "sg:postcode":"76248",
    "sg:province":"TX",
    "wof:name":"Six Nlab",
    "wof:placetype":"venue"
},
  "geometry": {"coordinates":[-97.29322500000001,32.938907],"type":"Point"}
}