{
  "type": "Feature",
  "properties": {
    "iso:country":"US",
    "sg:address":"1924 N Los Ebanos Rd",
    "sg:city":"Mission",
    "sg:classifiers":[
        {
            "category":"Retail",
            "subcategory":"Auto Repair",
            "type":"Services"
        }
    ],
    "sg:phone":"+1 956 580 3980",
    "sg:postcode":"78572",
    "sg:province":"TX",
    "sg:tags":[
        "wrecker"
    ],
    "wof:name":"Mission Towing",
    "wof:placetype":"venue"
},
  "geometry": {"coordinates":[-98.33958800000001,26.230184],"type":"Point"}
}