{
  "type": "Feature",
  "properties": {
    "iso:country":"US",
    "sg:address":"2050 Space Park Dr",
    "sg:city":"Houston",
    "sg:phone":"+1 281 333 5503",
    "sg:postcode":"77058",
    "sg:province":"TX",
    "wof:name":"St. John Hospital",
    "wof:placetype":"venue"
},
  "geometry": {"coordinates":[-95.087474,29.548027],"type":"Point"}
}