{
  "type": "Feature",
  "properties": {
    "iso:country":"US",
    "sg:address":"6433 McCart Ave",
    "sg:city":"Fort Worth",
    "sg:classifiers":[
        {
            "category":"Professional",
            "type":"Services"
        }
    ],
    "sg:phone":"+1 817 423 1200",
    "sg:postcode":"76133",
    "sg:province":"TX",
    "wof:name":"Apsi 1639",
    "wof:placetype":"venue"
},
  "geometry": {"coordinates":[-97.366269,32.650967],"type":"Point"}
}