{
  "type": "Feature",
  "properties": {
    "iso:country":"US",
    "sg:address":"6500 Summerhill Rd",
    "sg:city":"Texarkana",
    "sg:classifiers":[
        {
            "category":"Education",
            "subcategory":"Dance Studio",
            "type":"Public Place"
        }
    ],
    "sg:phone":"+1 903 793 1234",
    "sg:postcode":"75503",
    "sg:province":"TX",
    "sg:tags":[
        "instruction",
        "dancing"
    ],
    "wof:name":"Joni's Gymnastics & Dance Ctr",
    "wof:placetype":"venue"
},
  "geometry": {"coordinates":[-94.074631,33.486134],"type":"Point"}
}