{
  "type": "Feature",
  "properties": {
    "iso:country":"US",
    "sg:address":"101 E Marvin Ave",
    "sg:city":"Waxahachie",
    "sg:classifiers":[
        {
            "category":"Education",
            "subcategory":"School",
            "type":"Public Place"
        }
    ],
    "sg:phone":"+1 972 923 4676",
    "sg:postcode":"75165",
    "sg:province":"TX",
    "sg:tags":[
        "k-",
        "private"
    ],
    "wof:name":"Waxahachie Independent School District Administrative Offices",
    "wof:placetype":"venue"
},
  "geometry": {"coordinates":[-96.84343,32.392078],"type":"Point"}
}