{
  "type": "Feature",
  "properties": {
    "iso:country":"US",
    "sg:address":"1325 George Dieter Dr",
    "sg:city":"El Paso",
    "sg:classifiers":[
        {
            "category":"Coffee & Tea",
            "type":"Food & Drink"
        }
    ],
    "sg:menulink":"http://www.allmenus.com/tx/el-paso-east/112832-starbucks-coffee/menu/",
    "sg:phone":"+1 915 633 6565",
    "sg:postcode":"79936",
    "sg:province":"TX",
    "sg:tags":[
        "american"
    ],
    "wof:name":"Starbucks Coffee",
    "wof:placetype":"venue"
},
  "geometry": {"coordinates":[-106.302913,31.724802],"type":"Point"}
}