{
  "type": "Feature",
  "properties": {
    "iso:country":"US",
    "sg:address":"620 S Fulton Beach Rd",
    "sg:city":"Rockport",
    "sg:classifiers":[
        {
            "category":"Professional",
            "subcategory":"Lawyer & Legal Services",
            "type":"Services"
        }
    ],
    "sg:phone":"+1 361 790 5566",
    "sg:postcode":"78382",
    "sg:province":"TX",
    "wof:name":"Speck Wayne Frazier Law Off PC",
    "wof:placetype":"venue"
},
  "geometry": {"coordinates":[-97.033706,28.054923],"type":"Point"}
}