{
  "type": "Feature",
  "properties": {
    "iso:country":"US",
    "sg:address":"7801 N Capital of Texas Hwy",
    "sg:city":"Austin",
    "sg:classifiers":[
        {
            "category":"Shopping",
            "subcategory":"Computers & Home Electronics",
            "type":"Retail Goods"
        }
    ],
    "sg:phone":"+1 512 418 0239",
    "sg:postcode":"78731",
    "sg:province":"TX",
    "sg:tags":[
        "software"
    ],
    "wof:name":"Baxter Planning",
    "wof:placetype":"venue"
},
  "geometry": {"coordinates":[-97.781122,30.375665],"type":"Point"}
}