{
  "type": "Feature",
  "properties": {
    "iso:country":"US",
    "sg:address":"14663 Lourdes Dr",
    "sg:city":"Houston",
    "sg:classifiers":[
        {
            "category":"Freight",
            "type":"Transportation"
        }
    ],
    "sg:phone":"+1 281 458 4078",
    "sg:postcode":"77049",
    "sg:province":"TX",
    "sg:tags":[
        "operator",
        "trucking"
    ],
    "wof:name":"Slo Trucking",
    "wof:placetype":"venue"
},
  "geometry": {"coordinates":[-95.187011,29.811341],"type":"Point"}
}