{
  "type": "Feature",
  "properties": {
    "iso:country":"US",
    "sg:address":"2515 Waugh Dr",
    "sg:city":"Houston",
    "sg:postcode":"77006",
    "sg:province":"TX",
    "sg:website":"www.centralcityco-op.com",
    "wof:name":"Central City Co-Op",
    "wof:placetype":"venue"
},
  "geometry": {"coordinates":[-95.39383599999999,29.746382],"type":"Point"}
}