{
  "type": "Feature",
  "properties": {
    "iso:country":"US",
    "sg:address":"4149 Countryside Dr",
    "sg:city":"Grapevine",
    "sg:classifiers":[
        {
            "category":"Professional",
            "subcategory":"Art Services",
            "type":"Services"
        }
    ],
    "sg:phone":"+1 817 354 5860",
    "sg:postcode":"76051",
    "sg:province":"TX",
    "sg:tags":[
        "commercial",
        "design"
    ],
    "wof:name":"Landers Graphics",
    "wof:placetype":"venue"
},
  "geometry": {"coordinates":[-97.12020099999999,32.890754],"type":"Point"}
}