{
  "type": "Feature",
  "properties": {
    "iso:country":"US",
    "sg:address":"409 N 8th St",
    "sg:city":"Alpine",
    "sg:classifiers":[
        {
            "category":"Shopping",
            "subcategory":"Gifts & Souvenirs",
            "type":"Retail Goods"
        }
    ],
    "sg:phone":"+1 432 837 5214",
    "sg:postcode":"79830",
    "sg:province":"TX",
    "sg:tags":[
        "party",
        "supply"
    ],
    "wof:name":"Texas Crackers",
    "wof:placetype":"venue"
},
  "geometry": {"coordinates":[-103.66578199999999,30.360114],"type":"Point"}
}