{
  "type": "Feature",
  "properties": {
    "iso:country":"US",
    "sg:address":"1802 Pinetree Ln",
    "sg:city":"San Antonio",
    "sg:classifiers":[
        {
            "category":"Autos & Motor Vehicles",
            "subcategory":"Auto Supplies",
            "type":"Retail Goods"
        }
    ],
    "sg:phone":"+1 210 496 3682",
    "sg:postcode":"78232",
    "sg:province":"TX",
    "sg:tags":[
        "ind",
        "gasoline",
        "additive"
    ],
    "wof:name":"Enviro Fuels & Lubricants Intl",
    "wof:placetype":"venue"
},
  "geometry": {"coordinates":[-98.46276899999999,29.564991],"type":"Point"}
}