{
  "type": "Feature",
  "properties": {
    "iso:country":"US",
    "sg:address":"1114 Lake Estates Dr",
    "sg:city":"Sugar Land",
    "sg:classifiers":[
        {
            "category":"Retail",
            "subcategory":"Car Wash",
            "type":"Services"
        }
    ],
    "sg:phone":"+1 281 242 5928",
    "sg:postcode":"77478",
    "sg:province":"TX",
    "sg:tags":[
        "carwash"
    ],
    "wof:name":"Titan Car Wash Corp",
    "wof:placetype":"venue"
},
  "geometry": {"coordinates":[-95.63597900000001,29.633017],"type":"Point"}
}