{
  "type": "Feature",
  "properties": {
    "iso:country":"US",
    "sg:address":"985 E Nasa Pkwy",
    "sg:city":"Houston",
    "sg:classifiers":[
        {
            "category":"Shopping",
            "subcategory":"Musical Instruments",
            "type":"Retail Goods"
        }
    ],
    "sg:phone":"+1 281 218 8633",
    "sg:postcode":"77058",
    "sg:province":"TX",
    "sg:tags":[
        "equipment",
        "school"
    ],
    "wof:name":"Allegro Music Co",
    "wof:placetype":"venue"
},
  "geometry": {"coordinates":[-95.10641200000001,29.545938],"type":"Point"}
}