{
  "type": "Feature",
  "properties": {
    "iso:country":"US",
    "sg:address":"1308 Norwood Rd",
    "sg:city":"Austin",
    "sg:classifiers":[
        {
            "category":"Coffee & Tea",
            "type":"Food & Drink"
        }
    ],
    "sg:phone":"+1 512 423 4343",
    "sg:postcode":"78722",
    "sg:province":"TX",
    "sg:tags":[
        "supply",
        "brewing",
        "devices-wholesale",
        "break",
        "device",
        "manufacturer"
    ],
    "wof:name":"Austin Coffee Concierge",
    "wof:placetype":"venue"
},
  "geometry": {"coordinates":[-97.71032700000001,30.302892],"type":"Point"}
}