{
  "type": "Feature",
  "properties": {
    "iso:country":"US",
    "sg:address":"3515 Decatur Ave",
    "sg:city":"Fort Worth",
    "sg:classifiers":[
        {
            "category":"Retail",
            "subcategory":"Laundry & Dry Cleaning",
            "type":"Services"
        }
    ],
    "sg:phone":"+1 817 626 8870",
    "sg:postcode":"76106",
    "sg:province":"TX",
    "sg:tags":[
        "cleaners"
    ],
    "wof:name":"One Day Cleaners",
    "wof:placetype":"venue"
},
  "geometry": {"coordinates":[-97.33936199999999,32.808583],"type":"Point"}
}