{
  "type": "Feature",
  "properties": {
    "iso:country":"US",
    "sg:address":"402 N 2nd St",
    "sg:city":"Albany",
    "sg:classifiers":[
        {
            "category":"Education",
            "subcategory":"Library",
            "type":"Public Place"
        }
    ],
    "sg:phone":"+1 325 762 2672",
    "sg:postcode":"76430",
    "sg:province":"TX",
    "wof:name":"Shackelford County Library",
    "wof:placetype":"venue"
},
  "geometry": {"coordinates":[-99.29681100000001,32.728045],"type":"Point"}
}