{
  "type": "Feature",
  "properties": {
    "iso:country":"US",
    "sg:address":"3404 E Belknap St",
    "sg:city":"Fort Worth",
    "sg:classifiers":[
        {
            "category":"Autos & Motor Vehicles",
            "subcategory":"Automobile Sales",
            "type":"Retail Goods"
        }
    ],
    "sg:phone":"+1 817 831 3425",
    "sg:postcode":"76111",
    "sg:province":"TX",
    "sg:tags":[
        "car",
        "dealer"
    ],
    "wof:name":"Dave Malone Motor Co",
    "wof:placetype":"venue"
},
  "geometry": {"coordinates":[-97.30144799999999,32.773175],"type":"Point"}
}