{
  "type": "Feature",
  "properties": {
    "iso:country":"US",
    "sg:address":"7525 Chase St",
    "sg:city":"Houston",
    "sg:classifiers":[
        {
            "category":"Shopping",
            "subcategory":"Clothing, Apparel, & Fashions",
            "type":"Retail Goods"
        }
    ],
    "sg:phone":"+1 713 742 8182",
    "sg:postcode":"77093",
    "sg:province":"TX",
    "wof:name":"JD Tailoring",
    "wof:placetype":"venue"
},
  "geometry": {"coordinates":[-95.34634,29.826832],"type":"Point"}
}