{
  "type": "Feature",
  "properties": {
    "iso:country":"US",
    "sg:address":"802 Squires Ln",
    "sg:city":"Aubrey",
    "sg:classifiers":[
        {
            "category":"Education",
            "subcategory":"Dance Studio",
            "type":"Public Place"
        }
    ],
    "sg:phone":"+1 940 365 9803",
    "sg:postcode":"76227",
    "sg:province":"TX",
    "wof:name":"First Steps Dance Co",
    "wof:placetype":"venue"
},
  "geometry": {"coordinates":[-96.995653,33.279105],"type":"Point"}
}