{
  "type": "Feature",
  "properties": {
    "iso:country":"US",
    "sg:address":"4312 Shady Oak Ln",
    "sg:city":"Schertz",
    "sg:classifiers":[
        {
            "category":"Manufacturing",
            "subcategory":"Buildings",
            "type":"Manufacturing & Wholesale Goods"
        }
    ],
    "sg:phone":"+1 210 659 2000",
    "sg:postcode":"78154",
    "sg:province":"TX",
    "sg:tags":[
        "fabricated"
    ],
    "wof:name":"Certified Modular Technology",
    "wof:placetype":"venue"
},
  "geometry": {"coordinates":[-98.269626,29.592093],"type":"Point"}
}