{
  "type": "Feature",
  "properties": {
    "iso:country":"US",
    "sg:address":"2330 Southland St",
    "sg:city":"Dallas",
    "sg:classifiers":[
        {
            "category":"Food & Beverages",
            "subcategory":"Groceries & Convenience Stores",
            "type":"Retail Goods"
        }
    ],
    "sg:phone":"+1 214 421 1112",
    "sg:postcode":"75215",
    "sg:province":"TX",
    "wof:name":"South Dallas Grocery",
    "wof:placetype":"venue"
},
  "geometry": {"coordinates":[-96.759901,32.751466],"type":"Point"}
}