{
  "type": "Feature",
  "properties": {
    "iso:country":"US",
    "sg:address":"8331 Fm 1960 Bypass Rd W Ste E",
    "sg:city":"Humble",
    "sg:classifiers":[
        {
            "category":"Professional",
            "subcategory":"Lawyer & Legal Services",
            "type":"Services"
        }
    ],
    "sg:phone":"+1 281 852 2214",
    "sg:postcode":"77338",
    "sg:province":"TX",
    "sg:tags":[
        "process",
        "server"
    ],
    "wof:name":"Financing Available",
    "wof:placetype":"venue"
},
  "geometry": {"coordinates":[-95.29723799999999,30.00486],"type":"Point"}
}