{
  "type": "Feature",
  "properties": {
    "iso:country":"US",
    "sg:address":"519 Martin St",
    "sg:city":"Houston",
    "sg:classifiers":[
        {
            "category":"Retail",
            "subcategory":"Repair Shop",
            "type":"Services"
        },
        {
            "category":"Wholesale",
            "subcategory":"Construction Materials",
            "type":"Manufacturing & Wholesale Goods"
        }
    ],
    "sg:phone":"+1 713 691 3719",
    "sg:postcode":"77018",
    "sg:province":"TX",
    "sg:tags":[
        "refinish",
        "furniture",
        "caning",
        "supply"
    ],
    "sg:website":"http://raymundoalvarado.services.officelive.com",
    "wof:name":"Restoration Alvarado",
    "wof:placetype":"venue"
},
  "geometry": {"coordinates":[-95.407202,29.834741],"type":"Point"}
}