{
  "type": "Feature",
  "properties": {
    "iso:country":"US",
    "sg:address":"100 W Corporate Dr",
    "sg:city":"Lewisville",
    "sg:classifiers":[
        {
            "category":"Retail",
            "subcategory":"Photofinishing",
            "type":"Services"
        },
        {
            "category":"Shopping",
            "subcategory":"Pharmacy",
            "type":"Retail Goods"
        },
        {
            "category":"Food & Beverages",
            "subcategory":"Groceries & Convenience Stores",
            "type":"Retail Goods"
        }
    ],
    "sg:phone":"+1 972 459 7725",
    "sg:postcode":"75067",
    "sg:province":"TX",
    "sg:tags":[
        "supply",
        "photo",
        "aid",
        "finishing",
        "drugstore",
        "first"
    ],
    "sg:website":"www.cvs.com",
    "wof:name":"CVS Pharmacy",
    "wof:placetype":"venue"
},
  "geometry": {"coordinates":[-96.993103,33.0121],"type":"Point"}
}