{
  "type": "Feature",
  "properties": {
    "iso:country":"US",
    "sg:address":"331 Wickes St",
    "sg:city":"San Antonio",
    "sg:classifiers":[
        {
            "category":"Health Services",
            "subcategory":"Clinic",
            "type":"Services"
        }
    ],
    "sg:phone":"+1 210 256 0262",
    "sg:postcode":"78210",
    "sg:province":"TX",
    "sg:tags":[
        "home",
        "care"
    ],
    "wof:name":"Bbm Senior Service Inc",
    "wof:placetype":"venue"
},
  "geometry": {"coordinates":[-98.490801,29.407107],"type":"Point"}
}