{
  "type": "Feature",
  "properties": {
    "iso:country":"US",
    "sg:address":"9707 Springview Ln",
    "sg:city":"Houston",
    "sg:classifiers":[
        {
            "category":"Organizations",
            "subcategory":"Religious Organization",
            "type":"Services"
        }
    ],
    "sg:phone":"+1 713 462 0191",
    "sg:postcode":"77080",
    "sg:province":"TX",
    "wof:name":"Sue Hamilton Ministries",
    "wof:placetype":"venue"
},
  "geometry": {"coordinates":[-95.531998,29.8297],"type":"Point"}
}