{
  "type": "Feature",
  "properties": {
    "iso:country":"US",
    "sg:address":"2415 FM 1960 E",
    "sg:city":"Humble",
    "sg:classifiers":[
        {
            "category":"Building & Trades",
            "subcategory":"Construction",
            "type":"Services"
        }
    ],
    "sg:phone":"+1 281 446 3111",
    "sg:postcode":"77338",
    "sg:province":"TX",
    "sg:tags":[
        "foundation"
    ],
    "wof:name":"A-A-A Delta-Rodney E Goss Ent",
    "wof:placetype":"venue"
},
  "geometry": {"coordinates":[-95.388133,30.022343],"type":"Point"}
}