{
  "type": "Feature",
  "properties": {
    "iso:country":"US",
    "sg:address":"6207 Wiethorn Dr",
    "sg:city":"Waco",
    "sg:classifiers":[
        {
            "category":"Shopping",
            "subcategory":"Gifts & Souvenirs",
            "type":"Retail Goods"
        }
    ],
    "sg:phone":"+1 254 776 1647",
    "sg:postcode":"76710",
    "sg:province":"TX",
    "wof:name":"C&G Crafts",
    "wof:placetype":"venue"
},
  "geometry": {"coordinates":[-97.19520199999999,31.519194],"type":"Point"}
}