{
  "type": "Feature",
  "properties": {
    "iso:country":"US",
    "sg:address":"2401 Fir Ct",
    "sg:city":"Longview",
    "sg:classifiers":[
        {
            "category":"Shopping",
            "subcategory":"Hobbies, Toys, & Games",
            "type":"Retail Goods"
        }
    ],
    "sg:phone":"+1 903 759 8078",
    "sg:postcode":"75604",
    "sg:province":"TX",
    "sg:tags":[
        "doll"
    ],
    "wof:name":"Randy's Pouty Dolls Etc",
    "wof:placetype":"venue"
},
  "geometry": {"coordinates":[-94.79512800000001,32.532784],"type":"Point"}
}