{
  "type": "Feature",
  "properties": {
    "iso:country":"US",
    "sg:address":"3940 Hwy 190 W",
    "sg:city":"Livingston",
    "sg:classifiers":[
        {
            "category":"Shopping",
            "type":"Retail Goods"
        }
    ],
    "sg:phone":"+1 936 967 8505",
    "sg:postcode":"77351",
    "sg:province":"TX",
    "sg:tags":[
        "miscellaneous",
        "store"
    ],
    "wof:name":"Allie's Little Mexico",
    "wof:placetype":"venue"
},
  "geometry": {"coordinates":[-94.95433800000001,30.712704],"type":"Point"}
}