{
  "type": "Feature",
  "properties": {
    "iso:country":"US",
    "sg:address":"306 E Kay St",
    "sg:city":"Dayton",
    "sg:classifiers":[
        {
            "category":"Shopping",
            "subcategory":"Gifts & Souvenirs",
            "type":"Retail Goods"
        }
    ],
    "sg:phone":"+1 936 258 4635",
    "sg:postcode":"77535",
    "sg:province":"TX",
    "wof:name":"Likeminds",
    "wof:placetype":"venue"
},
  "geometry": {"coordinates":[-94.887626,30.050467],"type":"Point"}
}