{
  "type": "Feature",
  "properties": {
    "iso:country":"US",
    "sg:address":"3205 W Industrial Ave",
    "sg:city":"Midland",
    "sg:classifiers":[
        {
            "category":"Bars & Pubs",
            "type":"Food & Drink"
        },
        {
            "category":"Restaurant",
            "type":"Food & Drink"
        }
    ],
    "sg:phone":"+1 432 687 0703",
    "sg:postcode":"79701",
    "sg:province":"TX",
    "sg:tags":[
        "tavern",
        "grill",
        "brew"
    ],
    "wof:name":"The Field Office",
    "wof:placetype":"venue"
},
  "geometry": {"coordinates":[-102.10812300000001,31.977789],"type":"Point"}
}