{
  "type": "Feature",
  "properties": {
    "iso:country":"US",
    "sg:address":"1400 E 8th St",
    "sg:city":"Odessa",
    "sg:classifiers":[
        {
            "category":"Professional",
            "subcategory":"Lawyer & Legal Services",
            "type":"Services"
        }
    ],
    "sg:phone":"+1 432 580 7338",
    "sg:postcode":"79761",
    "sg:province":"TX",
    "sg:tags":[
        "attorney"
    ],
    "wof:name":"Gary Garrison",
    "wof:placetype":"venue"
},
  "geometry": {"coordinates":[-102.353633,31.859325],"type":"Point"}
}