{
  "type": "Feature",
  "properties": {
    "iso:country":"US",
    "sg:address":"1002 Old Lake Rd",
    "sg:city":"Smithville",
    "sg:classifiers":[
        {
            "category":"Real Estate",
            "subcategory":"Real Estate Operator",
            "type":"Services"
        }
    ],
    "sg:phone":"+1 512 360 3085",
    "sg:postcode":"78957",
    "sg:province":"TX",
    "sg:tags":[
        "building",
        "apartment"
    ],
    "wof:name":"Smithville Gardens Apartments",
    "wof:placetype":"venue"
},
  "geometry": {"coordinates":[-97.134297,29.984001],"type":"Point"}
}