{
  "type": "Feature",
  "properties": {
    "iso:country":"US",
    "sg:address":"6467 Southwest Blvd",
    "sg:city":"Fort Worth",
    "sg:classifiers":[
        {
            "category":"Wholesale",
            "subcategory":"Home Furnishings",
            "type":"Manufacturing & Wholesale Goods"
        }
    ],
    "sg:phone":"+1 817 377 2270",
    "sg:postcode":"76132",
    "sg:province":"TX",
    "wof:name":"Cartianis Inc",
    "wof:placetype":"venue"
},
  "geometry": {"coordinates":[-97.419707,32.691966],"type":"Point"}
}