{
  "type": "Feature",
  "properties": {
    "iso:country":"US",
    "sg:address":"3701 Olsen Blvd",
    "sg:city":"Amarillo",
    "sg:classifiers":[
        {
            "category":"Shopping",
            "subcategory":"Jewelry",
            "type":"Retail Goods"
        },
        {
            "category":"Manufacturing",
            "subcategory":"Jewelry",
            "type":"Manufacturing & Wholesale Goods"
        },
        {
            "category":"Retail",
            "subcategory":"Repair Shop",
            "type":"Services"
        }
    ],
    "sg:phone":"+1 806 351 2634",
    "sg:postcode":"79109",
    "sg:province":"TX",
    "sg:tags":[
        "repairing",
        "jeweler",
        "designer",
        "clock"
    ],
    "wof:name":"Goodin's Jewelry Inc",
    "wof:placetype":"venue"
},
  "geometry": {"coordinates":[-101.880064,35.185062],"type":"Point"}
}