{
  "type": "Feature",
  "properties": {
    "iso:country":"US",
    "sg:address":"2419 Arroyo Rd",
    "sg:city":"Waco",
    "sg:classifiers":[
        {
            "category":"Real Estate",
            "subcategory":"Real Estate Agent",
            "type":"Services"
        }
    ],
    "sg:phone":"+1 254 772 1945",
    "sg:postcode":"76710",
    "sg:province":"TX",
    "wof:name":"Daveler Inc",
    "wof:placetype":"venue"
},
  "geometry": {"coordinates":[-97.200754,31.546524],"type":"Point"}
}