{
  "type": "Feature",
  "properties": {
    "iso:country":"US",
    "sg:address":"10930 Alder Cir",
    "sg:city":"Dallas",
    "sg:classifiers":[
        {
            "category":"Autos & Motor Vehicles",
            "subcategory":"Auto Supplies",
            "type":"Retail Goods"
        }
    ],
    "sg:phone":"+1 972 907 1166",
    "sg:postcode":"75238",
    "sg:province":"TX",
    "wof:name":"B & B Radiator & Condensor",
    "wof:placetype":"venue"
},
  "geometry": {"coordinates":[-96.69246099999999,32.900204],"type":"Point"}
}