{
  "type": "Feature",
  "properties": {
    "iso:country":"US",
    "sg:address":"401 S el Paso St",
    "sg:city":"El Paso",
    "sg:classifiers":[
        {
            "category":"Shopping",
            "subcategory":"Clothing, Apparel, & Fashions",
            "type":"Retail Goods"
        }
    ],
    "sg:phone":"+1 915 544 9933",
    "sg:postcode":"79901",
    "sg:province":"TX",
    "wof:name":"World Sports",
    "wof:placetype":"venue"
},
  "geometry": {"coordinates":[-106.48789499999999,31.754279],"type":"Point"}
}