{
  "type": "Feature",
  "properties": {
    "iso:country":"US",
    "sg:address":"2136 Roy Rd",
    "sg:city":"Tyler",
    "sg:classifiers":[
        {
            "category":"Retail",
            "subcategory":"Repair Shop",
            "type":"Services"
        }
    ],
    "sg:phone":"+1 903 581 7750",
    "sg:postcode":"75707",
    "sg:province":"TX",
    "sg:tags":[
        "lining",
        "coating",
        "tank"
    ],
    "wof:name":"Wheless Co",
    "wof:placetype":"venue"
},
  "geometry": {"coordinates":[-95.277935,32.273869],"type":"Point"}
}