{
  "type": "Feature",
  "properties": {
    "iso:country":"US",
    "sg:address":"509 Whitetail Dr",
    "sg:city":"Georgetown",
    "sg:classifiers":[
        {
            "category":"Shopping",
            "subcategory":"Books",
            "type":"Retail Goods"
        }
    ],
    "sg:phone":"+1 512 259 1517",
    "sg:postcode":"78628",
    "sg:province":"TX",
    "wof:name":"Fames Eternal Books LLC",
    "wof:placetype":"venue"
},
  "geometry": {"coordinates":[-97.755442,30.580039],"type":"Point"}
}