{
  "type": "Feature",
  "properties": {
    "iso:country":"US",
    "sg:address":"27903 W Oak Ridge Rd",
    "sg:city":"Kemp",
    "sg:classifiers":[
        {
            "category":"Manufacturing",
            "subcategory":"Petroleum Products",
            "type":"Manufacturing & Wholesale Goods"
        }
    ],
    "sg:phone":"+1 903 498 4347",
    "sg:postcode":"75143",
    "sg:province":"TX",
    "sg:tags":[
        "candles-wholesale",
        "manufacturer"
    ],
    "wof:name":"Country Chunkie Candles",
    "wof:placetype":"venue"
},
  "geometry": {"coordinates":[-96.17993199999999,32.307636],"type":"Point"}
}