{
  "type": "Feature",
  "properties": {
    "iso:country":"US",
    "sg:address":"4253 Hunt Dr",
    "sg:city":"Carrollton",
    "sg:classifiers":[
        {
            "category":"Personal",
            "type":"Services"
        }
    ],
    "sg:phone":"+1 972 394 4971",
    "sg:postcode":"75010",
    "sg:province":"TX",
    "sg:tags":[
        "consultant",
        "wedding"
    ],
    "wof:name":"One Stop Wedding Planner",
    "wof:placetype":"venue"
},
  "geometry": {"coordinates":[-96.94080700000001,33.027445],"type":"Point"}
}