{
  "type": "Feature",
  "properties": {
    "iso:country":"US",
    "sg:address":"725 Yorkshire St",
    "sg:city":"Houston",
    "sg:classifiers":[
        {
            "category":"Retail",
            "subcategory":"Repair Shop",
            "type":"Services"
        }
    ],
    "sg:phone":"+1 713 695 2198",
    "sg:postcode":"77022",
    "sg:province":"TX",
    "sg:tags":[
        "welding"
    ],
    "wof:name":"Metal Eagle Fabricators Inc",
    "wof:placetype":"venue"
},
  "geometry": {"coordinates":[-95.36369999999999,29.827714],"type":"Point"}
}