{
  "type": "Feature",
  "properties": {
    "iso:country":"US",
    "sg:address":"400 E Pine St",
    "sg:city":"Jacksboro",
    "sg:classifiers":[
        {
            "category":"Social Services",
            "type":"Services"
        }
    ],
    "sg:phone":"+1 940 567 2607",
    "sg:postcode":"76458",
    "sg:province":"TX",
    "wof:name":"American Cancer Society",
    "wof:placetype":"venue"
},
  "geometry": {"coordinates":[-98.1508,33.217219],"type":"Point"}
}