{
  "type": "Feature",
  "properties": {
    "iso:country":"US",
    "sg:address":"1310 W Davis St",
    "sg:city":"Dallas",
    "sg:classifiers":[
        {
            "category":"Professional",
            "subcategory":"Accounting & Tax Preparation",
            "type":"Services"
        }
    ],
    "sg:phone":"+1 214 946 9663",
    "sg:postcode":"75208",
    "sg:province":"TX",
    "sg:tags":[
        "return",
        "filing"
    ],
    "wof:name":"Madrid Tax Svc",
    "wof:placetype":"venue"
},
  "geometry": {"coordinates":[-96.84393799999999,32.749426],"type":"Point"}
}