{
  "type": "Feature",
  "properties": {
    "iso:country":"US",
    "sg:address":"3 Rockridge Ct",
    "sg:city":"Spring",
    "sg:classifiers":[
        {
            "category":"Arts & Performance",
            "subcategory":"Theater",
            "type":"Entertainment"
        }
    ],
    "sg:phone":"+1 281 362 8781",
    "sg:postcode":"77381",
    "sg:province":"TX",
    "sg:tags":[
        "live",
        "music"
    ],
    "wof:name":"Woodlands D J's",
    "wof:placetype":"venue"
},
  "geometry": {"coordinates":[-95.512573,30.170421],"type":"Point"}
}