{
  "type": "Feature",
  "properties": {
    "iso:country":"US",
    "sg:address":"620 Thomas Arnold Rd",
    "sg:city":"Salado",
    "sg:classifiers":[
        {
            "category":"Education",
            "subcategory":"School",
            "type":"Public Place"
        }
    ],
    "sg:phone":"+1 254 947 5429",
    "sg:postcode":"76571",
    "sg:province":"TX",
    "wof:name":"Salado Independent School",
    "wof:placetype":"venue"
},
  "geometry": {"coordinates":[-97.548675,30.949821],"type":"Point"}
}