{
  "type": "Feature",
  "properties": {
    "iso:country":"US",
    "sg:address":"4 Horizon Ct",
    "sg:city":"Rockwall",
    "sg:classifiers":[
        {
            "category":"Communications",
            "type":"Services"
        }
    ],
    "sg:phone":"+1 972 771 0303",
    "sg:postcode":"75032",
    "sg:province":"TX",
    "wof:name":"Two W G Media",
    "wof:placetype":"venue"
},
  "geometry": {"coordinates":[-96.446268,32.870266],"type":"Point"}
}