{
  "type": "Feature",
  "properties": {
    "iso:country":"US",
    "sg:address":"3508 Caruth Blvd",
    "sg:city":"Dallas",
    "sg:classifiers":[
        {
            "category":"Professional",
            "type":"Services"
        }
    ],
    "sg:phone":"+1 214 363 3224",
    "sg:postcode":"75225",
    "sg:province":"TX",
    "wof:name":"T Walter Dale",
    "wof:placetype":"venue"
},
  "geometry": {"coordinates":[-96.792509,32.859309],"type":"Point"}
}