{
  "type": "Feature",
  "properties": {
    "iso:country":"US",
    "sg:address":"3317 Belt Line Rd",
    "sg:city":"Garland",
    "sg:classifiers":[
        {
            "category":"Manufacturing",
            "subcategory":"Printing",
            "type":"Manufacturing & Wholesale Goods"
        }
    ],
    "sg:phone":"+1 972 675 4383",
    "sg:postcode":"75044",
    "sg:province":"TX",
    "sg:tags":[
        "publisher"
    ],
    "wof:name":"Cultural & Sports Magazine",
    "wof:placetype":"venue"
},
  "geometry": {"coordinates":[-96.68231900000001,32.945205],"type":"Point"}
}