{
  "type": "Feature",
  "properties": {
    "iso:country":"US",
    "sg:address":"471 W 38th St",
    "sg:city":"Houston",
    "sg:classifiers":[
        {
            "category":"Home & Garden",
            "subcategory":"Building Materials",
            "type":"Retail Goods"
        },
        {
            "category":"Shopping",
            "subcategory":"Computers & Home Electronics",
            "type":"Retail Goods"
        }
    ],
    "sg:phone":"+1 713 682 6820",
    "sg:postcode":"77018",
    "sg:province":"TX",
    "sg:tags":[
        "equipment",
        "fixture",
        "lighting"
    ],
    "sg:website":"www.goprosound.com",
    "wof:name":"Pro Sound",
    "wof:placetype":"venue"
},
  "geometry": {"coordinates":[-95.40615099999999,29.821025],"type":"Point"}
}