{
  "type": "Feature",
  "properties": {
    "iso:country":"US",
    "sg:address":"8316 Winthrop St",
    "sg:city":"Houston",
    "sg:classifiers":[
        {
            "category":"Retail",
            "subcategory":"Repair Shop",
            "type":"Services"
        }
    ],
    "sg:phone":"+1 713 991 0647",
    "sg:postcode":"77075",
    "sg:province":"TX",
    "wof:name":"Laras Company",
    "wof:placetype":"venue"
},
  "geometry": {"coordinates":[-95.26709200000001,29.628182],"type":"Point"}
}