{
  "type": "Feature",
  "properties": {
    "iso:country":"US",
    "sg:address":"4334 Lemac Dr",
    "sg:city":"Houston",
    "sg:classifiers":[
        {
            "category":"Professional",
            "subcategory":"Management & Consulting",
            "type":"Services"
        }
    ],
    "sg:phone":"+1 713 721 6313",
    "sg:postcode":"77096",
    "sg:province":"TX",
    "wof:name":"Investech",
    "wof:placetype":"venue"
},
  "geometry": {"coordinates":[-95.45090500000001,29.678182],"type":"Point"}
}