{
  "type": "Feature",
  "properties": {
    "iso:country":"US",
    "sg:address":"4308 Grants Glen St",
    "sg:city":"Wichita Falls",
    "sg:classifiers":[
        {
            "category":"Professional",
            "subcategory":"Business Services",
            "type":"Services"
        }
    ],
    "sg:phone":"+1 940 696 5696",
    "sg:postcode":"76309",
    "sg:province":"TX",
    "wof:name":"Macha Donley Enterprises",
    "wof:placetype":"venue"
},
  "geometry": {"coordinates":[-98.554399,33.90201],"type":"Point"}
}