{
  "type": "Feature",
  "properties": {
    "iso:country":"US",
    "sg:address":"526 Sawdust Rd",
    "sg:city":"Spring",
    "sg:classifiers":[
        {
            "category":"Banks & Credit Unions",
            "subcategory":"Bank",
            "type":"Services"
        }
    ],
    "sg:phone":"+1 281 367 2599",
    "sg:postcode":"77380",
    "sg:province":"TX",
    "sg:tags":[
        "federal",
        "savings",
        "institution"
    ],
    "wof:name":"Washington Mutual Bank",
    "wof:placetype":"venue"
},
  "geometry": {"coordinates":[-95.451751,30.126775],"type":"Point"}
}