{
  "type": "Feature",
  "properties": {
    "iso:country":"US",
    "sg:address":"947 E Sunshine Dr",
    "sg:city":"San Antonio",
    "sg:classifiers":[
        {
            "category":"Retail",
            "subcategory":"Repair Shop",
            "type":"Services"
        }
    ],
    "sg:phone":"+1 210 494 9032",
    "sg:postcode":"78228",
    "sg:province":"TX",
    "sg:tags":[
        "electrical"
    ],
    "wof:name":"Appliance Service",
    "wof:placetype":"venue"
},
  "geometry": {"coordinates":[-98.56254800000001,29.473954],"type":"Point"}
}