{
  "type": "Feature",
  "properties": {
    "iso:country":"US",
    "sg:address":"14238 Westheimer Rd",
    "sg:city":"Houston",
    "sg:classifiers":[
        {
            "category":"Retail",
            "subcategory":"Repair Shop",
            "type":"Services"
        }
    ],
    "sg:phone":"+1 281 293 7786",
    "sg:postcode":"77077",
    "sg:province":"TX",
    "sg:tags":[
        "television",
        "radio"
    ],
    "wof:name":"Alfa TV & VCR Repair",
    "wof:placetype":"venue"
},
  "geometry": {"coordinates":[-95.63950699999999,29.735634],"type":"Point"}
}