{
  "type": "Feature",
  "properties": {
    "iso:country":"US",
    "sg:address":"512 S Columbia Dr",
    "sg:city":"West Columbia",
    "sg:classifiers":[
        {
            "category":"Government",
            "subcategory":"Office",
            "type":"Public Place"
        }
    ],
    "sg:phone":"+1 979 345 3123",
    "sg:postcode":"77486",
    "sg:province":"TX",
    "sg:tags":[
        "city"
    ],
    "wof:name":"West Columbia City Hall",
    "wof:placetype":"venue"
},
  "geometry": {"coordinates":[-95.654764,29.140697],"type":"Point"}
}