{
  "type": "Feature",
  "properties": {
    "iso:country":"US",
    "sg:address":"4108 Ave F",
    "sg:city":"Bay City",
    "sg:classifiers":[
        {
            "category":"Retail",
            "subcategory":"Repair Shop",
            "type":"Services"
        }
    ],
    "sg:phone":"+1 979 245 0157",
    "sg:postcode":"77414",
    "sg:province":"TX",
    "sg:tags":[
        "water",
        "equipment",
        "softening"
    ],
    "wof:name":"Texas Environmental Water WRKS",
    "wof:placetype":"venue"
},
  "geometry": {"coordinates":[-95.96938299999999,28.961418],"type":"Point"}
}