{
  "type": "Feature",
  "properties": {
    "iso:country":"US",
    "sg:address":"5237 Sweetwater Dr",
    "sg:city":"El Paso",
    "sg:classifiers":[
        {
            "category":"Wholesale",
            "subcategory":"Machinery & Supplies",
            "type":"Manufacturing & Wholesale Goods"
        }
    ],
    "sg:phone":"+1 915 204 8316",
    "sg:postcode":"79924",
    "sg:province":"TX",
    "sg:tags":[
        "equipment",
        "plastic"
    ],
    "wof:name":"Kpi Products",
    "wof:placetype":"venue"
},
  "geometry": {"coordinates":[-106.421505,31.927778],"type":"Point"}
}