{
  "type": "Feature",
  "properties": {
    "iso:country":"US",
    "sg:address":"1545 Lincolnshire Way",
    "sg:city":"Fort Worth",
    "sg:classifiers":[
        {
            "category":"Building & Trades",
            "subcategory":"Construction",
            "type":"Services"
        }
    ],
    "sg:phone":"+1 817 568 2385",
    "sg:postcode":"76134",
    "sg:province":"TX",
    "sg:tags":[
        "hanging",
        "contractor"
    ],
    "wof:name":"Lets Face It Face Painting",
    "wof:placetype":"venue"
},
  "geometry": {"coordinates":[-97.342747,32.624795],"type":"Point"}
}