{
  "type": "Feature",
  "properties": {
    "iso:country":"US",
    "sg:address":"500 W William Cannon Dr",
    "sg:city":"Austin",
    "sg:classifiers":[
        {
            "category":"Shopping",
            "subcategory":"Clothing, Apparel, & Fashions",
            "type":"Retail Goods"
        }
    ],
    "sg:phone":"+1 512 416 7111",
    "sg:postcode":"78745",
    "sg:province":"TX",
    "wof:name":"L J Fashion",
    "wof:placetype":"venue"
},
  "geometry": {"coordinates":[-97.78683700000001,30.196775],"type":"Point"}
}