{
  "type": "Feature",
  "properties": {
    "iso:country":"US",
    "sg:address":"202 N Mesquite St",
    "sg:city":"Muenster",
    "sg:classifiers":[
        {
            "category":"Retail",
            "subcategory":"Auto Repair",
            "type":"Services"
        }
    ],
    "sg:phone":"+1 940 759 4597",
    "sg:postcode":"76252",
    "sg:province":"TX",
    "sg:tags":[
        "body",
        "automobile",
        "painting"
    ],
    "wof:name":"Glenn's Paint & Body Shop",
    "wof:placetype":"venue"
},
  "geometry": {"coordinates":[-97.367773,33.661767],"type":"Point"}
}