{
  "type": "Feature",
  "properties": {
    "iso:country":"US",
    "sg:address":"618 Market St",
    "sg:city":"Laredo",
    "sg:classifiers":[
        {
            "category":"Autos & Motor Vehicles",
            "subcategory":"Fuel & Gas Station",
            "type":"Retail Goods"
        }
    ],
    "sg:phone":"+1 956 724 4231",
    "sg:postcode":"78040",
    "sg:province":"TX",
    "sg:tags":[
        "station",
        "gasoline"
    ],
    "wof:name":"Diamond Shamrock",
    "wof:placetype":"venue"
},
  "geometry": {"coordinates":[-99.48986499999999,27.503891],"type":"Point"}
}