{
  "type": "Feature",
  "properties": {
    "iso:country":"US",
    "sg:address":"400 Fm 2325",
    "sg:city":"Wimberley",
    "sg:classifiers":[
        {
            "category":"Education",
            "subcategory":"Library",
            "type":"Public Place"
        }
    ],
    "sg:phone":"+1 512 847 2188",
    "sg:postcode":"78676",
    "sg:province":"TX",
    "sg:website":"http://www.wimberleylibrary.org",
    "wof:name":"Wimberley Village Library",
    "wof:placetype":"venue"
},
  "geometry": {"coordinates":[-98.104556,30.002306],"type":"Point"}
}