{
  "type": "Feature",
  "properties": {
    "iso:country":"US",
    "sg:address":"3402 E Veterans Memorial Blvd",
    "sg:city":"Killeen",
    "sg:classifiers":[
        {
            "category":"Insurance",
            "subcategory":"Insurance Agent",
            "type":"Services"
        }
    ],
    "sg:phone":"+1 254 699 9600",
    "sg:postcode":"76543",
    "sg:province":"TX",
    "wof:name":"Herring Insurance",
    "wof:placetype":"venue"
},
  "geometry": {"coordinates":[-97.702747,31.102891],"type":"Point"}
}