{
  "type": "Feature",
  "properties": {
    "iso:country":"US",
    "sg:address":"1400 E Ave H",
    "sg:city":"Nolanville",
    "sg:classifiers":[
        {
            "category":"Real Estate",
            "subcategory":"Real Estate Operator",
            "type":"Services"
        }
    ],
    "sg:phone":"+1 254 698 3183",
    "sg:postcode":"76559",
    "sg:province":"TX",
    "sg:tags":[
        "mobile",
        "home",
        "community"
    ],
    "wof:name":"Cimarron Mobile Home Park",
    "wof:placetype":"venue"
},
  "geometry": {"coordinates":[-97.59633700000001,31.075388],"type":"Point"}
}