{
  "type": "Feature",
  "properties": {
    "iso:country":"US",
    "sg:address":"1704 S Cooper St",
    "sg:city":"Arlington",
    "sg:classifiers":[
        {
            "category":"Real Estate",
            "subcategory":"Real Estate Agent",
            "type":"Services"
        }
    ],
    "sg:phone":"+1 817 804 3217",
    "sg:postcode":"76013",
    "sg:province":"TX",
    "wof:name":"David Vega",
    "wof:placetype":"venue"
},
  "geometry": {"coordinates":[-97.114795,32.717972],"type":"Point"}
}