{
  "type": "Feature",
  "properties": {
    "iso:country":"US",
    "sg:address":"4940 Saucer Dr",
    "sg:city":"Fort Worth",
    "sg:classifiers":[
        {
            "category":"Building & Trades",
            "subcategory":"Construction",
            "type":"Services"
        }
    ],
    "sg:phone":"+1 817 788 9026",
    "sg:postcode":"76117",
    "sg:province":"TX",
    "sg:tags":[
        "painting",
        "installation"
    ],
    "wof:name":"Artistic Wall Designs",
    "wof:placetype":"venue"
},
  "geometry": {"coordinates":[-97.27472899999999,32.834124],"type":"Point"}
}