{
  "type": "Feature",
  "properties": {
    "iso:country":"US",
    "sg:address":"1901 E Spring Creek Pkwy",
    "sg:city":"Plano",
    "sg:classifiers":[
        {
            "category":"Retail",
            "subcategory":"Car Wash",
            "type":"Services"
        }
    ],
    "sg:phone":"+1 214 532 7260",
    "sg:postcode":"75074",
    "sg:province":"TX",
    "sg:tags":[
        "carwash"
    ],
    "wof:name":"Centre Car Wash",
    "wof:placetype":"venue"
},
  "geometry": {"coordinates":[-96.689656,33.057178],"type":"Point"}
}