{
  "type": "Feature",
  "properties": {
    "iso:country":"US",
    "sg:address":"9219 Garland Rd Ste 2109",
    "sg:city":"Dallas",
    "sg:classifiers":[
        {
            "category":"Shopping",
            "subcategory":"Antiques",
            "type":"Retail Goods"
        }
    ],
    "sg:phone":"+1 214 321 9331",
    "sg:postcode":"75218",
    "sg:province":"TX",
    "sg:website":"www.tictocclockshop.com",
    "wof:name":"Tick Tock Clock Shop",
    "wof:placetype":"venue"
},
  "geometry": {"coordinates":[-96.706776,32.830842],"type":"Point"}
}