{
  "type": "Feature",
  "properties": {
    "iso:country":"US",
    "sg:address":"2408 Belmeade St",
    "sg:city":"Brownwood",
    "sg:classifiers":[
        {
            "category":"Shopping",
            "subcategory":"Stationery & Office Supplies",
            "type":"Retail Goods"
        }
    ],
    "sg:phone":"+1 325 643 5885",
    "sg:postcode":"76801",
    "sg:province":"TX",
    "sg:website":"www.officeinks.com",
    "wof:name":"Office Inks",
    "wof:placetype":"venue"
},
  "geometry": {"coordinates":[-98.974135,31.696273],"type":"Point"}
}