{
  "type": "Feature",
  "properties": {
    "iso:country":"US",
    "sg:address":"6613 Sam Houston Pkwy",
    "sg:city":"Houston",
    "sg:classifiers":[
        {
            "category":"Banks & Credit Unions",
            "subcategory":"Bank",
            "type":"Services"
        }
    ],
    "sg:phone":"+1 281 752 7160",
    "sg:postcode":"77085",
    "sg:province":"TX",
    "sg:tags":[
        "loan",
        "real estate"
    ],
    "wof:name":"Equity Link Mortgage",
    "wof:placetype":"venue"
},
  "geometry": {"coordinates":[-95.484044,29.609125],"type":"Point"}
}