{
  "type": "Feature",
  "properties": {
    "iso:country":"US",
    "sg:address":"4123 Hollister St",
    "sg:city":"Houston",
    "sg:classifiers":[
        {
            "category":"Retail",
            "subcategory":"Repair Shop",
            "type":"Services"
        }
    ],
    "sg:phone":"+1 713 868 6246",
    "sg:postcode":"77080",
    "sg:province":"TX",
    "sg:tags":[
        "grease",
        "trap"
    ],
    "wof:name":"Biostim Of Houston",
    "wof:placetype":"venue"
},
  "geometry": {"coordinates":[-95.50936799999999,29.830235],"type":"Point"}
}