{
  "type": "Feature",
  "properties": {
    "iso:country":"US",
    "sg:address":"6103 Waterwalk Ct",
    "sg:city":"Richmond",
    "sg:classifiers":[
        {
            "category":"Farming",
            "subcategory":"Livestock Farm",
            "type":"Manufacturing & Wholesale Goods"
        }
    ],
    "sg:phone":"+1 281 238 4651",
    "sg:postcode":"77469",
    "sg:province":"TX",
    "sg:tags":[
        "beef",
        "feedlot",
        "cattle"
    ],
    "wof:name":"Happys Dream Ranch",
    "wof:placetype":"venue"
},
  "geometry": {"coordinates":[-95.704863,29.522305],"type":"Point"}
}