{
  "type": "Feature",
  "properties": {
    "iso:country":"US",
    "sg:address":"302 W Irving Blvd",
    "sg:city":"Irving",
    "sg:classifiers":[
        {
            "category":"Restaurant",
            "type":"Food & Drink"
        }
    ],
    "sg:menulink":"http://www.allmenus.com/tx/southwest/202420-mcdonalds/menu/",
    "sg:postcode":"75060",
    "sg:province":"TX",
    "sg:tags":[
        "burger",
        "american"
    ],
    "wof:name":"McDonald's",
    "wof:placetype":"venue"
},
  "geometry": {"coordinates":[-96.94905900000001,32.81333],"type":"Point"}
}