{
  "type": "Feature",
  "properties": {
    "iso:country":"US",
    "sg:address":"1006 Barry Ln",
    "sg:city":"Cleburne",
    "sg:classifiers":[
        {
            "category":"Real Estate",
            "subcategory":"Real Estate Agent",
            "type":"Services"
        }
    ],
    "sg:phone":"+1 817 558 2875",
    "sg:postcode":"76031",
    "sg:province":"TX",
    "wof:name":"Home Run Realty & Management",
    "wof:placetype":"venue"
},
  "geometry": {"coordinates":[-97.371915,32.416961],"type":"Point"}
}