{
  "type": "Feature",
  "properties": {
    "iso:country":"US",
    "sg:address":"11801 Mines Rd",
    "sg:city":"Laredo",
    "sg:classifiers":[
        {
            "category":"Food & Beverages",
            "subcategory":"Groceries & Convenience Stores",
            "type":"Retail Goods"
        }
    ],
    "sg:phone":"+1 956 729 0777",
    "sg:postcode":"78045",
    "sg:province":"TX",
    "wof:name":"Speedy Stop",
    "wof:placetype":"venue"
},
  "geometry": {"coordinates":[-99.52012999999999,27.608873],"type":"Point"}
}