{
  "type": "Feature",
  "properties": {
    "iso:country":"US",
    "sg:address":"412 E Upas Ave",
    "sg:city":"Mcallen",
    "sg:classifiers":[
        {
            "category":"Professional",
            "type":"Services"
        }
    ],
    "sg:phone":"+1 956 493 5456",
    "sg:postcode":"78501",
    "sg:province":"TX",
    "wof:name":"Maleys Guide Service",
    "wof:placetype":"venue"
},
  "geometry": {"coordinates":[-98.21083900000001,26.219883],"type":"Point"}
}