{
  "type": "Feature",
  "properties": {
    "iso:country":"US",
    "sg:address":"3419 Knight St",
    "sg:city":"Dallas",
    "sg:classifiers":[
        {
            "category":"Shopping",
            "subcategory":"Thrift Store",
            "type":"Retail Goods"
        },
        {
            "category":"Banks & Credit Unions",
            "subcategory":"Bank",
            "type":"Services"
        },
        {
            "category":"Shopping",
            "subcategory":"Used Merchandise",
            "type":"Retail Goods"
        }
    ],
    "sg:phone":"+1 214 520 6644",
    "sg:postcode":"75219",
    "sg:province":"TX",
    "sg:tags":[
        "shop",
        "vintage",
        "hand",
        "resale",
        "second",
        "consignment"
    ],
    "sg:website":"www.genesisshelter.org",
    "wof:name":"Genesis Benefit Thrift Store",
    "wof:placetype":"venue"
},
  "geometry": {"coordinates":[-96.809777,32.814183],"type":"Point"}
}