{
  "type": "Feature",
  "properties": {
    "iso:country":"US",
    "sg:address":"910 S Alamo St",
    "sg:city":"San Antonio",
    "sg:classifiers":[
        {
            "category":"Professional",
            "type":"Services"
        }
    ],
    "sg:phone":"+1 210 271 3103",
    "sg:postcode":"78205",
    "sg:province":"TX",
    "wof:name":"Rey Willys Burgers Y Mas",
    "wof:placetype":"venue"
},
  "geometry": {"coordinates":[-98.49057500000001,29.414332],"type":"Point"}
}