{
  "type": "Feature",
  "properties": {
    "iso:country":"US",
    "sg:address":"424 Eloise Dr",
    "sg:city":"Rockport",
    "sg:classifiers":[
        {
            "category":"Building & Trades",
            "subcategory":"Construction",
            "type":"Services"
        }
    ],
    "sg:phone":"+1 361 729 7955",
    "sg:postcode":"78382",
    "sg:province":"TX",
    "sg:tags":[
        "general",
        "contractor"
    ],
    "wof:name":"S S Construction Co",
    "wof:placetype":"venue"
},
  "geometry": {"coordinates":[-97.06002100000001,28.015324],"type":"Point"}
}