{
  "type": "Feature",
  "properties": {
    "iso:country":"US",
    "sg:address":"115 Taylor George Rd",
    "sg:city":"Longview",
    "sg:classifiers":[
        {
            "category":"Building & Trades",
            "subcategory":"Construction",
            "type":"Services"
        }
    ],
    "sg:phone":"+1 903 663 0130",
    "sg:postcode":"75605",
    "sg:province":"TX",
    "sg:tags":[
        "hanging",
        "contractor"
    ],
    "wof:name":"Ken Wynn Painting",
    "wof:placetype":"venue"
},
  "geometry": {"coordinates":[-94.711527,32.545271],"type":"Point"}
}