{
  "type": "Feature",
  "properties": {
    "iso:country":"US",
    "sg:address":"1202 W 6th St",
    "sg:city":"Austin",
    "sg:classifiers":[
        {
            "category":"Professional",
            "subcategory":"Lawyer & Legal Services",
            "type":"Services"
        }
    ],
    "sg:phone":"+1 512 477 4800",
    "sg:postcode":"78703",
    "sg:province":"TX",
    "wof:name":"Tomlinson Denise P",
    "wof:placetype":"venue"
},
  "geometry": {"coordinates":[-97.757475,30.272965],"type":"Point"}
}