{
  "type": "Feature",
  "properties": {
    "iso:country":"US",
    "sg:address":"6540 122nd St",
    "sg:city":"Lubbock",
    "sg:classifiers":[
        {
            "category":"Professional",
            "subcategory":"Business Services",
            "type":"Services"
        }
    ],
    "sg:phone":"+1 806 789 5616",
    "sg:postcode":"79424",
    "sg:province":"TX",
    "sg:tags":[
        "repairing",
        "sign"
    ],
    "wof:name":"Bob's Sign Svc",
    "wof:placetype":"venue"
},
  "geometry": {"coordinates":[-101.960391,33.482616],"type":"Point"}
}