{
  "type": "Feature",
  "properties": {
    "iso:country":"US",
    "sg:address":"607 English Oak Dr",
    "sg:city":"Allen",
    "sg:classifiers":[
        {
            "category":"Real Estate",
            "subcategory":"Real Estate Agent",
            "type":"Services"
        }
    ],
    "sg:phone":"+1 972 727 7055",
    "sg:postcode":"75002",
    "sg:province":"TX",
    "wof:name":"Heritage Properties",
    "wof:placetype":"venue"
},
  "geometry": {"coordinates":[-96.665094,33.087608],"type":"Point"}
}