{
  "type": "Feature",
  "properties": {
    "iso:country":"US",
    "sg:address":"121 Plz de Armas",
    "sg:city":"San Antonio",
    "sg:classifiers":[
        {
            "category":"Restaurant",
            "type":"Food & Drink"
        }
    ],
    "sg:phone":"+1 210 222 2650",
    "sg:postcode":"78205",
    "sg:province":"TX",
    "wof:name":"Panchito's Restaurant Cantina",
    "wof:placetype":"venue"
},
  "geometry": {"coordinates":[-98.49566900000001,29.4243],"type":"Point"}
}