{
  "type": "Feature",
  "properties": {
    "iso:country":"US",
    "sg:address":"12023 Sagecliff Dr",
    "sg:city":"Houston",
    "sg:classifiers":[
        {
            "category":"Building & Trades",
            "subcategory":"Plumbing",
            "type":"Services"
        }
    ],
    "sg:phone":"+1 281 481 3447",
    "sg:postcode":"77089",
    "sg:province":"TX",
    "sg:tags":[
        "contractor"
    ],
    "wof:name":"Petes Air Service",
    "wof:placetype":"venue"
},
  "geometry": {"coordinates":[-95.216928,29.60398],"type":"Point"}
}