{
  "type": "Feature",
  "properties": {
    "iso:country":"US",
    "sg:address":"3328 Bewley St",
    "sg:city":"Fort Worth",
    "sg:classifiers":[
        {
            "category":"Manufacturing",
            "subcategory":"Toys & Sporting Goods",
            "type":"Manufacturing & Wholesale Goods"
        }
    ],
    "sg:phone":"+1 817 838 5035",
    "sg:postcode":"76117",
    "sg:province":"TX",
    "sg:tags":[
        "mfg"
    ],
    "wof:name":"Steward Stevenson Sales",
    "wof:placetype":"venue"
},
  "geometry": {"coordinates":[-97.25767399999999,32.810222],"type":"Point"}
}