{
  "type": "Feature",
  "properties": {
    "iso:country":"US",
    "sg:address":"15914 Midway Rd",
    "sg:city":"Addison",
    "sg:classifiers":[
        {
            "category":"Banks & Credit Unions",
            "subcategory":"Bank",
            "type":"Services"
        }
    ],
    "sg:phone":"+1 972 503 4343",
    "sg:postcode":"75001",
    "sg:province":"TX",
    "sg:tags":[
        "personal",
        "institution"
    ],
    "wof:name":"Hearthstone Financial Inc",
    "wof:placetype":"venue"
},
  "geometry": {"coordinates":[-96.83999900000001,32.966832],"type":"Point"}
}