{
  "type": "Feature",
  "properties": {
    "iso:country":"US",
    "sg:address":"2708 Carrolton St",
    "sg:city":"Houston",
    "sg:classifiers":[
        {
            "category":"Freight",
            "type":"Transportation"
        }
    ],
    "sg:phone":"+1 713 301 1314",
    "sg:postcode":"77023",
    "sg:province":"TX",
    "wof:name":"Precision Outlets LLC",
    "wof:placetype":"venue"
},
  "geometry": {"coordinates":[-95.322095,29.713971],"type":"Point"}
}