{
  "type": "Feature",
  "properties": {
    "iso:country":"US",
    "sg:address":"514 Morales",
    "sg:city":"Laredo",
    "sg:classifiers":[
        {
            "category":"Freight",
            "type":"Transportation"
        }
    ],
    "sg:phone":"+1 956 791 2563",
    "sg:postcode":"78046",
    "sg:province":"TX",
    "sg:tags":[
        "arrangement"
    ],
    "wof:name":"Rosa Garcia Elia",
    "wof:placetype":"venue"
},
  "geometry": {"coordinates":[-99.499469,27.331065],"type":"Point"}
}