{
  "type": "Feature",
  "properties": {
    "iso:country":"US",
    "sg:address":"615 N River St",
    "sg:city":"Seguin",
    "sg:classifiers":[
        {
            "category":"Social Services",
            "subcategory":"Child Care",
            "type":"Services"
        }
    ],
    "sg:phone":"+1 830 379 4122",
    "sg:postcode":"78155",
    "sg:province":"TX",
    "sg:tags":[
        "day"
    ],
    "wof:name":"Little Red Barn Play School",
    "wof:placetype":"venue"
},
  "geometry": {"coordinates":[-97.96376600000001,29.573635],"type":"Point"}
}