{
  "type": "Feature",
  "properties": {
    "iso:country":"US",
    "sg:address":"103 E Niblick St",
    "sg:city":"Longview",
    "sg:classifiers":[
        {
            "category":"Wholesale",
            "subcategory":"Machinery & Supplies",
            "type":"Manufacturing & Wholesale Goods"
        }
    ],
    "sg:phone":"+1 903 759 9497",
    "sg:postcode":"75604",
    "sg:province":"TX",
    "sg:tags":[
        "equipment",
        "welding"
    ],
    "wof:name":"United Welding Specialties Inc",
    "wof:placetype":"venue"
},
  "geometry": {"coordinates":[-94.793789,32.508205],"type":"Point"}
}