{
  "type": "Feature",
  "properties": {
    "iso:country":"US",
    "sg:address":"6300 Skylark Cir",
    "sg:city":"Fort Worth",
    "sg:classifiers":[
        {
            "category":"Building & Trades",
            "subcategory":"Construction",
            "type":"Services"
        }
    ],
    "sg:phone":"+1 817 849 8065",
    "sg:postcode":"76180",
    "sg:province":"TX",
    "sg:tags":[
        "concrete",
        "contractor"
    ],
    "wof:name":"Cen Concrete Construction Co",
    "wof:placetype":"venue"
},
  "geometry": {"coordinates":[-97.248543,32.835551],"type":"Point"}
}