{
  "type": "Feature",
  "properties": {
    "iso:country":"US",
    "sg:address":"4602 Waring St",
    "sg:city":"Houston",
    "sg:classifiers":[
        {
            "category":"Manufacturing",
            "subcategory":"Tools & Machinery",
            "type":"Manufacturing & Wholesale Goods"
        }
    ],
    "sg:phone":"+1 832 563 6215",
    "sg:postcode":"77027",
    "sg:province":"TX",
    "sg:tags":[
        "electricity",
        "supply"
    ],
    "wof:name":"Clear Choice Energy LLC",
    "wof:placetype":"venue"
},
  "geometry": {"coordinates":[-95.457837,29.733835],"type":"Point"}
}