{
  "type": "Feature",
  "properties": {
    "iso:country":"US",
    "sg:address":"2125 Woodbrook St",
    "sg:city":"Denton",
    "sg:classifiers":[
        {
            "category":"Banks & Credit Unions",
            "subcategory":"Investment Brokerage",
            "type":"Services"
        }
    ],
    "sg:phone":"+1 940 382 1350",
    "sg:postcode":"76205",
    "sg:province":"TX",
    "sg:tags":[
        "advisory",
        "financial"
    ],
    "wof:name":"Washington Investment Mgmt Co",
    "wof:placetype":"venue"
},
  "geometry": {"coordinates":[-97.12039799999999,33.184923],"type":"Point"}
}