{
  "type": "Feature",
  "properties": {
    "iso:country":"US",
    "sg:address":"6601 Sands Point Dr # 35",
    "sg:city":"Houston",
    "sg:classifiers":[
        {
            "category":"Professional",
            "subcategory":"Accounting & Tax Preparation",
            "type":"Services"
        }
    ],
    "sg:phone":"+1 713 357 4449",
    "sg:postcode":"77074",
    "sg:province":"TX",
    "sg:tags":[
        "bookkeeping",
        "billing"
    ],
    "wof:name":"Medical Billing And Consulting Services, Ltd",
    "wof:placetype":"venue"
},
  "geometry": {"coordinates":[-95.498222,29.71105],"type":"Point"}
}