{
  "type": "Feature",
  "properties": {
    "iso:country":"US",
    "sg:address":"2437 N Main St",
    "sg:city":"Belton",
    "sg:classifiers":[
        {
            "category":"Food & Beverages",
            "subcategory":"Groceries & Convenience Stores",
            "type":"Retail Goods"
        }
    ],
    "sg:phone":"+1 254 933 8923",
    "sg:postcode":"76513",
    "sg:province":"TX",
    "wof:name":"Minit Prinit Co",
    "wof:placetype":"venue"
},
  "geometry": {"coordinates":[-97.457318,31.078904],"type":"Point"}
}