{
  "type": "Feature",
  "properties": {
    "iso:country":"US",
    "sg:address":"4216 Centergate St",
    "sg:city":"San Antonio",
    "sg:classifiers":[
        {
            "category":"Professional",
            "subcategory":"Business Services",
            "type":"Services"
        }
    ],
    "sg:phone":"+1 210 657 1017",
    "sg:postcode":"78217",
    "sg:province":"TX",
    "wof:name":"Comprehensive Imaging Corp",
    "wof:placetype":"venue"
},
  "geometry": {"coordinates":[-98.40886399999999,29.520437],"type":"Point"}
}