{
  "type": "Feature",
  "properties": {
    "iso:country":"US",
    "sg:address":"4303 San Felipe St",
    "sg:city":"Houston",
    "sg:classifiers":[
        {
            "category":"Autos & Motor Vehicles",
            "subcategory":"Auto Supplies",
            "type":"Retail Goods"
        }
    ],
    "sg:phone":"+1 281 610 3542",
    "sg:postcode":"77027",
    "sg:province":"TX",
    "sg:tags":[
        "glass"
    ],
    "wof:name":"Houston Auto Glass Replacement & Repair",
    "wof:placetype":"venue"
},
  "geometry": {"coordinates":[-95.452269,29.746607],"type":"Point"}
}