{
  "type": "Feature",
  "properties": {
    "iso:country":"US",
    "sg:address":"1350 N Main St",
    "sg:city":"Euless",
    "sg:classifiers":[
        {
            "category":"Real Estate",
            "subcategory":"Real Estate Operator",
            "type":"Services"
        }
    ],
    "sg:phone":"+1 817 355 6100",
    "sg:postcode":"76039",
    "sg:province":"TX",
    "sg:tags":[
        "building",
        "apartment"
    ],
    "wof:name":"Oak Park Apartments",
    "wof:placetype":"venue"
},
  "geometry": {"coordinates":[-97.082452,32.852128],"type":"Point"}
}