{
  "type": "Feature",
  "properties": {
    "iso:country":"US",
    "sg:address":"2925 Alameda Ave",
    "sg:city":"El Paso",
    "sg:classifiers":[
        {
            "category":"Wholesale",
            "subcategory":"Stationery",
            "type":"Manufacturing & Wholesale Goods"
        }
    ],
    "sg:phone":"+1 915 577 9222",
    "sg:postcode":"79905",
    "sg:province":"TX",
    "sg:tags":[
        "equipment",
        "price",
        "marking",
        "supply"
    ],
    "wof:name":"Pricing Equipment",
    "wof:placetype":"venue"
},
  "geometry": {"coordinates":[-106.461158,31.773603],"type":"Point"}
}