{
  "type": "Feature",
  "properties": {
    "iso:country":"US",
    "sg:address":"5405 Cliff Haven Ct",
    "sg:city":"Dallas",
    "sg:classifiers":[
        {
            "category":"Freight",
            "type":"Transportation"
        }
    ],
    "sg:phone":"+1 972 283 8625",
    "sg:postcode":"75236",
    "sg:province":"TX",
    "sg:tags":[
        "operator",
        "local",
        "trucking"
    ],
    "wof:name":"Ken Brewer Hauling",
    "wof:placetype":"venue"
},
  "geometry": {"coordinates":[-96.92932999999999,32.681119],"type":"Point"}
}