{
  "type": "Feature",
  "properties": {
    "iso:country":"US",
    "sg:address":"478 Sussex Ave",
    "sg:city":"San Antonio",
    "sg:classifiers":[
        {
            "category":"Organizations",
            "subcategory":"Religious Organization",
            "type":"Services"
        }
    ],
    "sg:phone":"+1 210 922 4933",
    "sg:postcode":"78221",
    "sg:province":"TX",
    "sg:tags":[
        "church"
    ],
    "wof:name":"Door Christian Fellowship Chr",
    "wof:placetype":"venue"
},
  "geometry": {"coordinates":[-98.489681,29.353093],"type":"Point"}
}