{
  "type": "Feature",
  "properties": {
    "iso:country":"US",
    "sg:address":"2410 S Church St",
    "sg:city":"Paris",
    "sg:classifiers":[
        {
            "category":"Building & Trades",
            "subcategory":"Construction",
            "type":"Services"
        }
    ],
    "sg:phone":"+1 903 784 1101",
    "sg:postcode":"75460",
    "sg:province":"TX",
    "sg:tags":[
        "carpentry",
        "contractor"
    ],
    "wof:name":"Counter Tops and Supplies",
    "wof:placetype":"venue"
},
  "geometry": {"coordinates":[-95.557063,33.635861],"type":"Point"}
}