{
  "type": "Feature",
  "properties": {
    "iso:country":"US",
    "sg:address":"7702 Thompson Rd",
    "sg:city":"Highlands",
    "sg:classifiers":[
        {
            "category":"Building & Trades",
            "subcategory":"Landscaping Services",
            "type":"Services"
        }
    ],
    "sg:phone":"+1 281 426 5861",
    "sg:postcode":"77562",
    "sg:province":"TX",
    "sg:tags":[
        "tree"
    ],
    "wof:name":"Hagan's Tree Svc",
    "wof:placetype":"venue"
},
  "geometry": {"coordinates":[-95.03264,29.809811],"type":"Point"}
}