{
  "type": "Feature",
  "properties": {
    "iso:country":"US",
    "sg:address":"251 Co Rd 133",
    "sg:city":"Alice",
    "sg:classifiers":[
        {
            "category":"Retail",
            "subcategory":"Auto Repair",
            "type":"Services"
        },
        {
            "category":"Building & Trades",
            "subcategory":"Plumbing",
            "type":"Services"
        }
    ],
    "sg:phone":"+1 361 668 1445",
    "sg:postcode":"78332",
    "sg:province":"TX",
    "sg:tags":[
        "engine",
        "mechanical",
        "contractor"
    ],
    "wof:name":"Saenz Diesel Mechanic",
    "wof:placetype":"venue"
},
  "geometry": {"coordinates":[-98.133596,27.742615],"type":"Point"}
}