{
  "type": "Feature",
  "properties": {
    "iso:country":"US",
    "sg:address":"409 Colebrook Ln",
    "sg:city":"Dickinson",
    "sg:classifiers":[
        {
            "category":"Professional",
            "subcategory":"Business Services",
            "type":"Services"
        }
    ],
    "sg:phone":"+1 281 614 0374",
    "sg:postcode":"77539",
    "sg:province":"TX",
    "wof:name":"Jenkins Enterprize",
    "wof:placetype":"venue"
},
  "geometry": {"coordinates":[-95.092681,29.444316],"type":"Point"}
}