{
  "type": "Feature",
  "properties": {
    "iso:country":"US",
    "sg:address":"19330 Twin Buttes Dr",
    "sg:city":"Tomball",
    "sg:classifiers":[
        {
            "category":"Manufacturing",
            "subcategory":"Tools & Machinery",
            "type":"Manufacturing & Wholesale Goods"
        }
    ],
    "sg:phone":"+1 281 516 0610",
    "sg:postcode":"77375",
    "sg:province":"TX",
    "sg:tags":[
        "industrial",
        "mfg"
    ],
    "wof:name":"Walsh Machine Works",
    "wof:placetype":"venue"
},
  "geometry": {"coordinates":[-95.60705,30.043638],"type":"Point"}
}