{
  "type": "Feature",
  "properties": {
    "iso:country":"US",
    "sg:address":"1304 W Walnut Hill Ln",
    "sg:city":"Irving",
    "sg:classifiers":[
        {
            "category":"Insurance",
            "subcategory":"Insurance Agent",
            "type":"Services"
        }
    ],
    "sg:phone":"+1 972 751 0000",
    "sg:postcode":"75038",
    "sg:province":"TX",
    "sg:tags":[
        "agency"
    ],
    "wof:name":"Agape Halthcare Insur Svcs Inc",
    "wof:placetype":"venue"
},
  "geometry": {"coordinates":[-96.968154,32.88497],"type":"Point"}
}