{
  "type": "Feature",
  "properties": {
    "iso:country":"US",
    "sg:address":"610 Maryland Dr",
    "sg:city":"Athens",
    "sg:classifiers":[
        {
            "category":"Professional",
            "subcategory":"Lawyer & Legal Services",
            "type":"Services"
        }
    ],
    "sg:phone":"+1 903 675 4529",
    "sg:postcode":"75751",
    "sg:province":"TX",
    "wof:name":"Mayhall Danna Kirk Attorney",
    "wof:placetype":"venue"
},
  "geometry": {"coordinates":[-95.85285500000001,32.186232],"type":"Point"}
}