{
  "type": "Feature",
  "properties": {
    "iso:country":"US",
    "sg:address":"2004 Houston Ave",
    "sg:city":"Houston",
    "sg:classifiers":[
        {
            "category":"Food & Beverages",
            "subcategory":"Groceries & Convenience Stores",
            "type":"Retail Goods"
        }
    ],
    "sg:phone":"+1 713 861 2031",
    "sg:postcode":"77007",
    "sg:province":"TX",
    "wof:name":"Oscar Food Mart",
    "wof:placetype":"venue"
},
  "geometry": {"coordinates":[-95.372242,29.775361],"type":"Point"}
}