{
  "type": "Feature",
  "properties": {
    "iso:country":"US",
    "sg:address":"6003 Bandera Rd",
    "sg:city":"San Antonio",
    "sg:classifiers":[
        {
            "category":"Restaurant",
            "type":"Food & Drink"
        }
    ],
    "sg:phone":"+1 210 509 7611",
    "sg:postcode":"78238",
    "sg:province":"TX",
    "sg:tags":[
        "eating"
    ],
    "wof:name":"Taqueria Jaslisco 11",
    "wof:placetype":"venue"
},
  "geometry": {"coordinates":[-98.603866,29.484026],"type":"Point"}
}