{
  "type": "Feature",
  "properties": {
    "iso:country":"US",
    "sg:address":"1906 Scarlett Ct",
    "sg:city":"Arlington",
    "sg:classifiers":[
        {
            "category":"Retail",
            "subcategory":"Portrait Studio",
            "type":"Services"
        }
    ],
    "sg:phone":"+1 817 274 1792",
    "sg:postcode":"76012",
    "sg:province":"TX",
    "sg:tags":[
        "photo"
    ],
    "wof:name":"Bethune Photographicsent",
    "wof:placetype":"venue"
},
  "geometry": {"coordinates":[-97.117386,32.766057],"type":"Point"}
}