{
  "type": "Feature",
  "properties": {
    "iso:country":"US",
    "sg:address":"26214 Glen Loch Dr",
    "sg:city":"Spring",
    "sg:classifiers":[
        {
            "category":"Retail",
            "subcategory":"Car Wash",
            "type":"Services"
        }
    ],
    "sg:phone":"+1 281 419 9274",
    "sg:postcode":"77380",
    "sg:province":"TX",
    "sg:tags":[
        "polishing",
        "washing"
    ],
    "wof:name":"H & M Carwash",
    "wof:placetype":"venue"
},
  "geometry": {"coordinates":[-95.48900999999999,30.146755],"type":"Point"}
}