{
  "type": "Feature",
  "properties": {
    "iso:country":"US",
    "sg:address":"6342 Royalton Dr",
    "sg:city":"Dallas",
    "sg:classifiers":[
        {
            "category":"Manufacturing",
            "subcategory":"Toys & Sporting Goods",
            "type":"Manufacturing & Wholesale Goods"
        }
    ],
    "sg:phone":"+1 214 373 1500",
    "sg:postcode":"75230",
    "sg:province":"TX",
    "sg:tags":[
        "mfg"
    ],
    "wof:name":"Maverick Multisport",
    "wof:placetype":"venue"
},
  "geometry": {"coordinates":[-96.798557,32.897945],"type":"Point"}
}