{
  "type": "Feature",
  "properties": {
    "iso:country":"US",
    "sg:address":"117 W Cleveland Ave",
    "sg:city":"Electra",
    "sg:classifiers":[
        {
            "category":"Shopping",
            "subcategory":"Gifts & Souvenirs",
            "type":"Retail Goods"
        }
    ],
    "sg:phone":"+1 940 495 3427",
    "sg:postcode":"76360",
    "sg:province":"TX",
    "sg:tags":[
        "shop",
        "florist"
    ],
    "wof:name":"Lilacs & Old Lace",
    "wof:placetype":"venue"
},
  "geometry": {"coordinates":[-98.91880500000001,34.029885],"type":"Point"}
}