{
  "type": "Feature",
  "properties": {
    "iso:country":"US",
    "sg:address":"10408 W Hwy 290",
    "sg:city":"Austin",
    "sg:classifiers":[
        {
            "category":"Building & Trades",
            "subcategory":"Construction",
            "type":"Services"
        }
    ],
    "sg:phone":"+1 512 394 1191",
    "sg:postcode":"78736",
    "sg:province":"TX",
    "sg:tags":[
        "house"
    ],
    "wof:name":"Brath Construction",
    "wof:placetype":"venue"
},
  "geometry": {"coordinates":[-97.952467,30.223793],"type":"Point"}
}