{
  "type": "Feature",
  "properties": {
    "iso:country":"US",
    "sg:address":"535 E Fernhurst Dr",
    "sg:city":"Katy",
    "sg:classifiers":[
        {
            "category":"Building & Trades",
            "subcategory":"Landscaping Services",
            "type":"Services"
        }
    ],
    "sg:phone":"+1 281 392 1999",
    "sg:postcode":"77450",
    "sg:province":"TX",
    "wof:name":"Tree Amigos Landscaping",
    "wof:placetype":"venue"
},
  "geometry": {"coordinates":[-95.77441,29.778005],"type":"Point"}
}