{
  "type": "Feature",
  "properties": {
    "iso:country":"US",
    "sg:address":"1825 S Washington St",
    "sg:city":"Beeville",
    "sg:classifiers":[
        {
            "category":"Building & Trades",
            "subcategory":"Pest Control",
            "type":"Services"
        }
    ],
    "sg:phone":"+1 361 358 1199",
    "sg:postcode":"78102",
    "sg:province":"TX",
    "wof:name":"Rogers Moreland Pest Control",
    "wof:placetype":"venue"
},
  "geometry": {"coordinates":[-97.736554,28.388248],"type":"Point"}
}