{
  "type": "Feature",
  "properties": {
    "iso:country":"US",
    "sg:address":"2231 Michigan Ave",
    "sg:city":"Arlington",
    "sg:classifiers":[
        {
            "category":"Manufacturing",
            "subcategory":"Metals",
            "type":"Manufacturing & Wholesale Goods"
        },
        {
            "category":"Wholesale",
            "subcategory":"Durable Goods & Equipment",
            "type":"Manufacturing & Wholesale Goods"
        }
    ],
    "sg:phone":"+1 817 461 1055",
    "sg:postcode":"76013",
    "sg:province":"TX",
    "sg:tags":[
        "hardware",
        "rep",
        "mfg",
        "representative",
        "manufacturer"
    ],
    "sg:website":"www.dlcollinsassociates.com",
    "wof:name":"D L Collins Associates Inc",
    "wof:placetype":"venue"
},
  "geometry": {"coordinates":[-97.15716,32.707887],"type":"Point"}
}