{
  "type": "Feature",
  "properties": {
    "iso:country":"US",
    "sg:address":"14867 State Highway 155 S",
    "sg:city":"Tyler",
    "sg:classifiers":[
        {
            "category":"Professional",
            "type":"Services"
        },
        {
            "category":"Shopping",
            "subcategory":"Bicycles & Sporting Goods",
            "type":"Retail Goods"
        },
        {
            "category":"Wholesale",
            "subcategory":"Chemicals & Plastics",
            "type":"Manufacturing & Wholesale Goods"
        }
    ],
    "sg:phone":"+1 903 534 1919",
    "sg:postcode":"75703",
    "sg:province":"TX",
    "sg:tags":[
        "supply",
        "tubs-repair",
        "equipment",
        "hot",
        "spa",
        "manufacturer",
        "supplies-wholesale",
        "pool",
        "swimming"
    ],
    "sg:website":"http://www.bluehavenpoolstyler.com",
    "wof:name":"Blue Haven Pools - A BioGuard Platinum Dealer",
    "wof:placetype":"venue"
},
  "geometry": {"coordinates":[-95.378805,32.265169],"type":"Point"}
}