{
  "type": "Feature",
  "properties": {
    "iso:country":"US",
    "sg:address":"8700 Clay Rd",
    "sg:city":"Houston",
    "sg:classifiers":[
        {
            "category":"Home & Garden",
            "subcategory":"Carpets & Floor Coverings",
            "type":"Retail Goods"
        }
    ],
    "sg:phone":"+1 713 996 7050",
    "sg:postcode":"77080",
    "sg:province":"TX",
    "sg:tags":[
        "a",
        "flooring",
        "wholesale",
        "material",
        "as",
        "operates",
        "subcontractor"
    ],
    "wof:name":"Metro Wholesale Flooring",
    "wof:placetype":"venue"
},
  "geometry": {"coordinates":[-95.506722,29.832839],"type":"Point"}
}