{
  "type": "Feature",
  "properties": {
    "iso:country":"US",
    "sg:address":"6343 S Padre Island Dr",
    "sg:city":"Corpus Christi",
    "sg:classifiers":[
        {
            "category":"Shopping",
            "subcategory":"Jewelry",
            "type":"Retail Goods"
        }
    ],
    "sg:phone":"+1 361 991 1264",
    "sg:postcode":"78412",
    "sg:province":"TX",
    "sg:tags":[
        "repair",
        "met",
        "jeweler",
        "precious",
        "mfg"
    ],
    "wof:name":"Habeeb's Jewelers",
    "wof:placetype":"venue"
},
  "geometry": {"coordinates":[-97.35610200000001,27.700569],"type":"Point"}
}