{
  "type": "Feature",
  "properties": {
    "iso:country":"US",
    "sg:address":"201 E 2nd St",
    "sg:city":"Austin",
    "sg:classifiers":[
        {
            "category":"Shopping",
            "subcategory":"Computers & Home Electronics",
            "type":"Retail Goods"
        }
    ],
    "sg:phone":"+1 512 524 3447",
    "sg:postcode":"78701",
    "sg:province":"TX",
    "wof:name":"DISH Network",
    "wof:placetype":"venue"
},
  "geometry": {"coordinates":[-97.742892,30.263817],"type":"Point"}
}