{
  "type": "Feature",
  "properties": {
    "iso:country":"US",
    "sg:address":"7499 Bayway Dr",
    "sg:city":"Baytown",
    "sg:classifiers":[
        {
            "category":"Retail",
            "subcategory":"Auto Repair",
            "type":"Services"
        }
    ],
    "sg:phone":"+1 281 424 4141",
    "sg:postcode":"77520",
    "sg:province":"TX",
    "sg:tags":[
        "truck"
    ],
    "wof:name":"Lindseys Wrecker Service",
    "wof:placetype":"venue"
},
  "geometry": {"coordinates":[-95.03184899999999,29.769861],"type":"Point"}
}