{
  "type": "Feature",
  "properties": {
    "iso:country":"US",
    "sg:address":"444 North St",
    "sg:city":"Brownsville",
    "sg:classifiers":[
        {
            "category":"Professional",
            "subcategory":"Detective & Security Services",
            "type":"Services"
        }
    ],
    "sg:phone":"+1 956 541 9632",
    "sg:postcode":"78521",
    "sg:province":"TX",
    "sg:tags":[
        "car"
    ],
    "wof:name":"Interstate Investigations",
    "wof:placetype":"venue"
},
  "geometry": {"coordinates":[-97.48512599999999,25.926101],"type":"Point"}
}