{
  "type": "Feature",
  "properties": {
    "iso:country":"US",
    "sg:address":"121 Quapaw Dr",
    "sg:city":"Harker Heights",
    "sg:classifiers":[
        {
            "category":"Arts & Performance",
            "subcategory":"Theater",
            "type":"Entertainment"
        }
    ],
    "sg:phone":"+1 254 699 0276",
    "sg:postcode":"76548",
    "sg:province":"TX",
    "sg:tags":[
        "military",
        "pianist",
        "at",
        "base"
    ],
    "wof:name":"Betty L Phillips",
    "wof:placetype":"venue"
},
  "geometry": {"coordinates":[-97.674378,31.067632],"type":"Point"}
}