{
  "type": "Feature",
  "properties": {
    "iso:country":"US",
    "sg:address":"823 Office Park Cir",
    "sg:city":"Lewisville",
    "sg:classifiers":[
        {
            "category":"Home & Garden",
            "subcategory":"Furniture",
            "type":"Retail Goods"
        }
    ],
    "sg:phone":"+1 972 420 9919",
    "sg:postcode":"75057",
    "sg:province":"TX",
    "sg:tags":[
        "stationery"
    ],
    "wof:name":"Office Pro",
    "wof:placetype":"venue"
},
  "geometry": {"coordinates":[-96.99791399999999,33.052289],"type":"Point"}
}