{
  "type": "Feature",
  "properties": {
    "iso:country":"US",
    "sg:address":"13536 Old China Spring Rd",
    "sg:city":"Waco",
    "sg:classifiers":[
        {
            "category":"Farming",
            "subcategory":"Aquatic Farm",
            "type":"Manufacturing & Wholesale Goods"
        }
    ],
    "sg:phone":"+1 254 836 1131",
    "sg:postcode":"76708",
    "sg:province":"TX",
    "sg:tags":[
        "fish"
    ],
    "wof:name":"Fishermens Dream",
    "wof:placetype":"venue"
},
  "geometry": {"coordinates":[-97.28316599999999,31.644798],"type":"Point"}
}