{
  "type": "Feature",
  "properties": {
    "iso:country":"US",
    "sg:address":"2197 N Hwy 35 Byp",
    "sg:city":"Alvin",
    "sg:classifiers":[
        {
            "category":"Real Estate",
            "subcategory":"Real Estate Agent",
            "type":"Services"
        }
    ],
    "sg:phone":"+1 281 388 1900",
    "sg:postcode":"77511",
    "sg:province":"TX",
    "wof:name":"Prudential",
    "wof:placetype":"venue"
},
  "geometry": {"coordinates":[-95.237593,29.445663],"type":"Point"}
}