{
  "type": "Feature",
  "properties": {
    "iso:country":"US",
    "sg:address":"303 Hill St",
    "sg:city":"Farmersville",
    "sg:classifiers":[
        {
            "category":"Professional",
            "type":"Services"
        }
    ],
    "sg:phone":"+1 972 782 8131",
    "sg:postcode":"75442",
    "sg:province":"TX",
    "wof:name":"Centennial I Farmersville",
    "wof:placetype":"venue"
},
  "geometry": {"coordinates":[-96.357141,33.161517],"type":"Point"}
}