{
  "type": "Feature",
  "properties": {
    "iso:country":"US",
    "sg:address":"401 Woodward St",
    "sg:city":"Austin",
    "sg:classifiers":[
        {
            "category":"Communications",
            "subcategory":"Television Station",
            "type":"Services"
        }
    ],
    "sg:phone":"+1 512 326 5897",
    "sg:postcode":"78704",
    "sg:province":"TX",
    "wof:name":"Austinights",
    "wof:placetype":"venue"
},
  "geometry": {"coordinates":[-97.75458399999999,30.226988],"type":"Point"}
}