{
  "type": "Feature",
  "properties": {
    "iso:country":"US",
    "sg:address":"3322 Laurel Fork Dr",
    "sg:city":"Humble",
    "sg:classifiers":[
        {
            "category":"Professional",
            "subcategory":"Business Services",
            "type":"Services"
        }
    ],
    "sg:phone":"+1 281 359 3444",
    "sg:postcode":"77339",
    "sg:province":"TX",
    "wof:name":"Rawson Pool Service",
    "wof:placetype":"venue"
},
  "geometry": {"coordinates":[-95.192564,30.071565],"type":"Point"}
}