{
  "type": "Feature",
  "properties": {
    "iso:country":"US",
    "sg:address":"713 Melos Ln",
    "sg:city":"Palmview",
    "sg:classifiers":[
        {
            "category":"Restaurant",
            "type":"Food & Drink"
        }
    ],
    "sg:phone":"+1 956 580 3028",
    "sg:postcode":"78574",
    "sg:province":"TX",
    "sg:tags":[
        "mexican"
    ],
    "wof:name":"Joel Garcia",
    "wof:placetype":"venue"
},
  "geometry": {"coordinates":[-98.38679500000001,26.238666],"type":"Point"}
}