{
  "type": "Feature",
  "properties": {
    "iso:country":"US",
    "sg:address":"1811 US Hwy 259",
    "sg:city":"Kilgore",
    "sg:classifiers":[
        {
            "category":"Farming",
            "subcategory":"Livestock Farm",
            "type":"Manufacturing & Wholesale Goods"
        }
    ],
    "sg:phone":"+1 903 983 3200",
    "sg:postcode":"75662",
    "sg:province":"TX",
    "sg:tags":[
        "ranch"
    ],
    "wof:name":"Atwoods Ranch & Home Supply",
    "wof:placetype":"venue"
},
  "geometry": {"coordinates":[-94.854519,32.396687],"type":"Point"}
}