{
  "type": "Feature",
  "properties": {
    "iso:country":"US",
    "sg:address":"6560 Fannin St",
    "sg:city":"Houston",
    "sg:classifiers":[
        {
            "category":"Health Services",
            "subcategory":"Doctor",
            "type":"Services"
        }
    ],
    "sg:phone":"+1 713 798 3880",
    "sg:postcode":"77030",
    "sg:province":"TX",
    "sg:tags":[
        "ophthalmologist"
    ],
    "wof:name":"Holz Eric R MD",
    "wof:placetype":"venue"
},
  "geometry": {"coordinates":[-95.399255,29.712009],"type":"Point"}
}