{
  "type": "Feature",
  "properties": {
    "iso:country":"US",
    "sg:address":"901 Cincinnati Ave",
    "sg:city":"San Antonio",
    "sg:classifiers":[
        {
            "category":"Restaurant",
            "type":"Food & Drink"
        }
    ],
    "sg:phone":"+1 210 735 1501",
    "sg:postcode":"78201",
    "sg:province":"TX",
    "sg:tags":[
        "eating"
    ],
    "wof:name":"Tacos Rio Grande 2 Mobile",
    "wof:placetype":"venue"
},
  "geometry": {"coordinates":[-98.526659,29.449738],"type":"Point"}
}