{
  "type": "Feature",
  "properties": {
    "iso:country":"US",
    "sg:address":"2001 W Parker Rd",
    "sg:city":"Plano",
    "sg:classifiers":[
        {
            "category":"Retail",
            "subcategory":"Laundry & Dry Cleaning",
            "type":"Services"
        }
    ],
    "sg:phone":"+1 972 867 1117",
    "sg:postcode":"75023",
    "sg:province":"TX",
    "sg:tags":[
        "cleaners"
    ],
    "wof:name":"Town & Country Cleaners",
    "wof:placetype":"venue"
},
  "geometry": {"coordinates":[-96.73185100000001,33.041163],"type":"Point"}
}