{
  "type": "Feature",
  "properties": {
    "iso:country":"US",
    "sg:address":"7020 Hillwood Dr",
    "sg:city":"Garland",
    "sg:classifiers":[
        {
            "category":"Professional",
            "subcategory":"Business Services",
            "type":"Services"
        }
    ],
    "sg:phone":"+1 972 429 8774",
    "sg:postcode":"75048",
    "sg:province":"TX",
    "wof:name":"Advanced Merchant Solutions",
    "wof:placetype":"venue"
},
  "geometry": {"coordinates":[-96.562093,32.984923],"type":"Point"}
}