{
  "type": "Feature",
  "properties": {
    "iso:country":"US",
    "sg:address":"311 N Market St Ste 200",
    "sg:city":"Dallas",
    "sg:classifiers":[
        {
            "category":"Professional",
            "subcategory":"Employment Agencies",
            "type":"Services"
        }
    ],
    "sg:phone":"+1 214 744 5627",
    "sg:postcode":"75202",
    "sg:province":"TX",
    "sg:website":"www.frontlinesourcegroup.com",
    "wof:name":"Frontline Source Group",
    "wof:placetype":"venue"
},
  "geometry": {"coordinates":[-96.80516900000001,32.783316],"type":"Point"}
}