{
  "type": "Feature",
  "properties": {
    "iso:country":"US",
    "sg:address":"2104 Pipestone Dr",
    "sg:city":"San Antonio",
    "sg:classifiers":[
        {
            "category":"Social Services",
            "subcategory":"Adult Care",
            "type":"Services"
        }
    ],
    "sg:phone":"+1 210 545 6272",
    "sg:postcode":"78232",
    "sg:province":"TX",
    "sg:tags":[
        "home",
        "residential"
    ],
    "wof:name":"Pipestone Place",
    "wof:placetype":"venue"
},
  "geometry": {"coordinates":[-98.455935,29.593908],"type":"Point"}
}