{
  "type": "Feature",
  "properties": {
    "iso:country":"US",
    "sg:address":"125 Ave B",
    "sg:city":"Brownsville",
    "sg:classifiers":[
        {
            "category":"Personal",
            "subcategory":"Beauty Salon",
            "type":"Services"
        }
    ],
    "sg:phone":"+1 956 546 6635",
    "sg:postcode":"78520",
    "sg:province":"TX",
    "wof:name":"Maxis Hair Designer Center",
    "wof:placetype":"venue"
},
  "geometry": {"coordinates":[-97.514673,25.910262],"type":"Point"}
}