{
  "type": "Feature",
  "properties": {
    "iso:country":"US",
    "sg:address":"1603 Honeyweed St",
    "sg:city":"Cedar Park",
    "sg:classifiers":[
        {
            "category":"Home & Garden",
            "subcategory":"Furniture",
            "type":"Retail Goods"
        }
    ],
    "sg:phone":"+1 512 250 1317",
    "sg:postcode":"78613",
    "sg:province":"TX",
    "wof:name":"Casa Saltillo",
    "wof:placetype":"venue"
},
  "geometry": {"coordinates":[-97.830189,30.464562],"type":"Point"}
}