{
  "type": "Feature",
  "properties": {
    "iso:country":"US",
    "sg:address":"103 E Creek St",
    "sg:city":"Fredericksburg",
    "sg:classifiers":[
        {
            "category":"Building & Trades",
            "subcategory":"Construction",
            "type":"Services"
        }
    ],
    "sg:phone":"+1 830 997 7812",
    "sg:postcode":"78624",
    "sg:province":"TX",
    "sg:tags":[
        "hanging",
        "contractor"
    ],
    "wof:name":"Criterion Dry Wall & Paint",
    "wof:placetype":"venue"
},
  "geometry": {"coordinates":[-98.874284,30.272859],"type":"Point"}
}