{
  "type": "Feature",
  "properties": {
    "iso:country":"US",
    "sg:address":"617 Irvine St",
    "sg:city":"Yoakum",
    "sg:classifiers":[
        {
            "category":"Retail",
            "subcategory":"Car Wash",
            "type":"Services"
        }
    ],
    "sg:phone":"+1 361 293 6950",
    "sg:postcode":"77995",
    "sg:province":"TX",
    "sg:tags":[
        "automobile",
        "detail",
        "clean"
    ],
    "wof:name":"Marcus's Detailing & Lube",
    "wof:placetype":"venue"
},
  "geometry": {"coordinates":[-97.152084,29.288677],"type":"Point"}
}