{
  "type": "Feature",
  "properties": {
    "iso:country":"US",
    "sg:address":"705 Bradfield Dr",
    "sg:city":"Garland",
    "sg:classifiers":[
        {
            "category":"Food & Beverages",
            "subcategory":"Groceries & Convenience Stores",
            "type":"Retail Goods"
        }
    ],
    "sg:phone":"+1 972 272 6378",
    "sg:postcode":"75042",
    "sg:province":"TX",
    "wof:name":"B&G Groceries Inc",
    "wof:placetype":"venue"
},
  "geometry": {"coordinates":[-96.69169100000001,32.920135],"type":"Point"}
}