{
  "type": "Feature",
  "properties": {
    "iso:country":"US",
    "sg:address":"111 N Johnson St",
    "sg:city":"Farmersville",
    "sg:classifiers":[
        {
            "category":"Health Services",
            "subcategory":"Doctor",
            "type":"Services"
        }
    ],
    "sg:phone":"+1 972 782 6131",
    "sg:postcode":"75442",
    "sg:province":"TX",
    "sg:tags":[
        "physician",
        "surgeon",
        "family"
    ],
    "wof:name":"Farmersville Family Med Clinic",
    "wof:placetype":"venue"
},
  "geometry": {"coordinates":[-96.36296400000001,33.165235],"type":"Point"}
}