{
  "type": "Feature",
  "properties": {
    "iso:country":"US",
    "sg:address":"5827 Loma Linda St",
    "sg:city":"Houston",
    "sg:classifiers":[
        {
            "category":"Retail",
            "subcategory":"Repair Shop",
            "type":"Services"
        }
    ],
    "sg:phone":"+1 713 728 1611",
    "sg:postcode":"77085",
    "sg:province":"TX",
    "sg:tags":[
        "equipment",
        "refrigeration",
        "conditioning",
        "air"
    ],
    "wof:name":"Allahar's A/C & Heating",
    "wof:placetype":"venue"
},
  "geometry": {"coordinates":[-95.46903,29.613587],"type":"Point"}
}