{
  "type": "Feature",
  "properties": {
    "iso:country":"US",
    "sg:address":"600 S 2nd Ave",
    "sg:city":"Mansfield",
    "sg:classifiers":[
        {
            "category":"Retail",
            "subcategory":"Repair Shop",
            "type":"Services"
        },
        {
            "category":"Wholesale",
            "subcategory":"Construction Materials",
            "type":"Manufacturing & Wholesale Goods"
        },
        {
            "category":"Home & Garden",
            "subcategory":"Furniture",
            "type":"Retail Goods"
        }
    ],
    "sg:phone":"+1 817 477 4118",
    "sg:postcode":"76063",
    "sg:province":"TX",
    "sg:tags":[
        "supply",
        "refinish",
        "caning",
        "equipment-household",
        "cabinet",
        "store",
        "kitchen"
    ],
    "sg:website":"http://www.rodco-brandt.com",
    "wof:name":"Rodco Brandt Mfg Millet",
    "wof:placetype":"venue"
},
  "geometry": {"coordinates":[-97.14482099999999,32.55867],"type":"Point"}
}