{
  "type": "Feature",
  "properties": {
    "iso:country":"US",
    "sg:address":"11422 Bay Cedar Dr",
    "sg:city":"Houston",
    "sg:classifiers":[
        {
            "category":"Professional",
            "subcategory":"Accounting & Tax Preparation",
            "type":"Services"
        }
    ],
    "sg:phone":"+1 713 738 2985",
    "sg:postcode":"77048",
    "sg:province":"TX",
    "wof:name":"Gina DS",
    "wof:placetype":"venue"
},
  "geometry": {"coordinates":[-95.351674,29.636143],"type":"Point"}
}