{
  "type": "Feature",
  "properties": {
    "iso:country":"US",
    "sg:address":"4102 Shady Valley Dr",
    "sg:city":"Arlington",
    "sg:classifiers":[
        {
            "category":"Banks & Credit Unions",
            "subcategory":"Bank",
            "type":"Services"
        }
    ],
    "sg:phone":"+1 817 265 1226",
    "sg:postcode":"76013",
    "sg:province":"TX",
    "sg:tags":[
        "institution",
        "business"
    ],
    "wof:name":"Ruff Investments Inc",
    "wof:placetype":"venue"
},
  "geometry": {"coordinates":[-97.168736,32.720841],"type":"Point"}
}