{
  "type": "Feature",
  "properties": {
    "iso:country":"US",
    "sg:address":"6837 Cliffbrook Dr",
    "sg:city":"Dallas",
    "sg:classifiers":[
        {
            "category":"Building & Trades",
            "subcategory":"Landscaping Services",
            "type":"Services"
        }
    ],
    "sg:phone":"+1 972 960 1723",
    "sg:postcode":"75254",
    "sg:province":"TX",
    "sg:tags":[
        "landscape"
    ],
    "wof:name":"Shaketree Ldscpg & Lawn Care",
    "wof:placetype":"venue"
},
  "geometry": {"coordinates":[-96.788371,32.94475],"type":"Point"}
}