{
  "type": "Feature",
  "properties": {
    "iso:country":"US",
    "sg:address":"1705 S Austin Ave",
    "sg:city":"Denison",
    "sg:classifiers":[
        {
            "category":"Restaurant",
            "type":"Food & Drink"
        }
    ],
    "sg:phone":"+1 903 337 0272",
    "sg:postcode":"75020",
    "sg:province":"TX",
    "sg:tags":[
        "eating"
    ],
    "wof:name":"Rjs Wings Restaurant",
    "wof:placetype":"venue"
},
  "geometry": {"coordinates":[-96.53815,33.73782],"type":"Point"}
}