{
  "type": "Feature",
  "properties": {
    "iso:country":"US",
    "sg:address":"2206 Gleneagles Dr",
    "sg:city":"League City",
    "sg:classifiers":[
        {
            "category":"Professional",
            "subcategory":"Business Services",
            "type":"Services"
        }
    ],
    "sg:phone":"+1 281 334 2984",
    "sg:postcode":"77573",
    "sg:province":"TX",
    "wof:name":"Skellenger Design Associates",
    "wof:placetype":"venue"
},
  "geometry": {"coordinates":[-95.05623799999999,29.528889],"type":"Point"}
}