{
  "type": "Feature",
  "properties": {
    "iso:country":"US",
    "sg:address":"10506 Dunbrook Dr",
    "sg:city":"Houston",
    "sg:classifiers":[
        {
            "category":"Professional",
            "subcategory":"Research",
            "type":"Services"
        }
    ],
    "sg:phone":"+1 281 469 5292",
    "sg:postcode":"77070",
    "sg:province":"TX",
    "sg:tags":[
        "environmental",
        "ecological"
    ],
    "wof:name":"Freedom Environmental Group",
    "wof:placetype":"venue"
},
  "geometry": {"coordinates":[-95.577868,29.973506],"type":"Point"}
}