{
  "type": "Feature",
  "properties": {
    "iso:country":"US",
    "sg:address":"204 Elkington Loop",
    "sg:city":"Laredo",
    "sg:classifiers":[
        {
            "category":"Real Estate",
            "subcategory":"Developer",
            "type":"Services"
        }
    ],
    "sg:phone":"+1 956 729 7282",
    "sg:postcode":"78045",
    "sg:province":"TX",
    "wof:name":"H&N Development Lc",
    "wof:placetype":"venue"
},
  "geometry": {"coordinates":[-99.463882,27.58532],"type":"Point"}
}