{
  "type": "Feature",
  "properties": {
    "iso:country":"US",
    "sg:address":"1500 Brittmoore Rd",
    "sg:city":"Houston",
    "sg:classifiers":[
        {
            "category":"Building & Trades",
            "subcategory":"Construction",
            "type":"Services"
        }
    ],
    "sg:phone":"+1 713 647 0455",
    "sg:postcode":"77043",
    "sg:province":"TX",
    "sg:tags":[
        "contractor"
    ],
    "wof:name":"American Countertops",
    "wof:placetype":"venue"
},
  "geometry": {"coordinates":[-95.56986999999999,29.802083],"type":"Point"}
}