{
  "type": "Feature",
  "properties": {
    "iso:country":"US",
    "sg:address":"101 N Rogers Rd",
    "sg:city":"Irving",
    "sg:classifiers":[
        {
            "category":"Real Estate",
            "subcategory":"Real Estate Operator",
            "type":"Services"
        }
    ],
    "sg:phone":"+1 972 253 0973",
    "sg:postcode":"75061",
    "sg:province":"TX",
    "sg:tags":[
        "dwelling"
    ],
    "wof:name":"Bealls Properties",
    "wof:placetype":"venue"
},
  "geometry": {"coordinates":[-96.963454,32.817611],"type":"Point"}
}