{
  "type": "Feature",
  "properties": {
    "iso:country":"US",
    "sg:address":"2245 Co Rd 495",
    "sg:city":"Princeton",
    "sg:classifiers":[
        {
            "category":"Wholesale",
            "subcategory":"Construction Materials",
            "type":"Manufacturing & Wholesale Goods"
        }
    ],
    "sg:phone":"+1 972 734 6258",
    "sg:postcode":"75407",
    "sg:province":"TX",
    "sg:tags":[
        "sand",
        "gravel"
    ],
    "wof:name":"Kenneth Dickson Sand & Gravel",
    "wof:placetype":"venue"
},
  "geometry": {"coordinates":[-96.445764,33.198548],"type":"Point"}
}