{
  "type": "Feature",
  "properties": {
    "iso:country":"US",
    "sg:address":"12301 Research Blvd Ste 3",
    "sg:city":"Austin",
    "sg:classifiers":[
        {
            "category":"Home & Garden",
            "subcategory":"Hardware",
            "type":"Retail Goods"
        }
    ],
    "sg:phone":"+1 512 835 2190",
    "sg:postcode":"78759",
    "sg:province":"TX",
    "sg:tags":[
        "measuring",
        "device"
    ],
    "wof:name":"Emerson Process Management",
    "wof:placetype":"venue"
},
  "geometry": {"coordinates":[-97.75372299999999,30.426821],"type":"Point"}
}