{
  "type": "Feature",
  "properties": {
    "iso:country":"US",
    "sg:address":"21003 Auburn Ridge Ln",
    "sg:city":"Spring",
    "sg:classifiers":[
        {
            "category":"Autos & Motor Vehicles",
            "subcategory":"Automobile Sales",
            "type":"Retail Goods"
        }
    ],
    "sg:phone":"+1 281 251 8936",
    "sg:postcode":"77379",
    "sg:province":"TX",
    "sg:tags":[
        "used"
    ],
    "wof:name":"R & H Enterprices",
    "wof:placetype":"venue"
},
  "geometry": {"coordinates":[-95.519407,30.070698],"type":"Point"}
}