{
  "type": "Feature",
  "properties": {
    "iso:country":"US",
    "sg:address":"14501 Montfort Dr",
    "sg:city":"Dallas",
    "sg:classifiers":[
        {
            "category":"Travel",
            "subcategory":"Travel Agent",
            "type":"Entertainment"
        }
    ],
    "sg:phone":"+1 972 702 8305",
    "sg:postcode":"75254",
    "sg:province":"TX",
    "sg:tags":[
        "operator",
        "tour"
    ],
    "wof:name":"Destiny Travel & Tours",
    "wof:placetype":"venue"
},
  "geometry": {"coordinates":[-96.816076,32.946326],"type":"Point"}
}