{
  "type": "Feature",
  "properties": {
    "iso:country":"US",
    "sg:address":"6909 Rowlett Rd Ste 100",
    "sg:city":"Rowlett",
    "sg:classifiers":[
        {
            "category":"Retail",
            "subcategory":"Laundry & Dry Cleaning",
            "type":"Services"
        }
    ],
    "sg:phone":"+1 972 463 4466",
    "sg:postcode":"75089",
    "sg:province":"TX",
    "wof:name":"Miracle Cleaners",
    "wof:placetype":"venue"
},
  "geometry": {"coordinates":[-96.577499,32.921001],"type":"Point"}
}