{
  "type": "Feature",
  "properties": {
    "iso:country":"US",
    "sg:address":"215 Squirrel Run Rd",
    "sg:city":"Argyle",
    "sg:classifiers":[
        {
            "category":"Retail",
            "subcategory":"Photofinishing",
            "type":"Services"
        }
    ],
    "sg:phone":"+1 940 464 9969",
    "sg:postcode":"76226",
    "sg:province":"TX",
    "sg:tags":[
        "photographic",
        "video",
        "analysis"
    ],
    "wof:name":"Christian Images & Slides",
    "wof:placetype":"venue"
},
  "geometry": {"coordinates":[-97.198303,33.112049],"type":"Point"}
}