{
  "type": "Feature",
  "properties": {
    "iso:country":"US",
    "sg:address":"1621 SE 4th St",
    "sg:city":"Grand Prairie",
    "sg:classifiers":[
        {
            "category":"Food & Beverages",
            "subcategory":"Bakery",
            "type":"Retail Goods"
        }
    ],
    "sg:phone":"+1 972 262 9019",
    "sg:postcode":"75051",
    "sg:province":"TX",
    "wof:name":"Dream Creations",
    "wof:placetype":"venue"
},
  "geometry": {"coordinates":[-97.001411,32.72069],"type":"Point"}
}