{
  "type": "Feature",
  "properties": {
    "iso:country":"US",
    "sg:address":"3500 W Davis St",
    "sg:city":"Conroe",
    "sg:classifiers":[
        {
            "category":"Banks & Credit Unions",
            "subcategory":"Investment Brokerage",
            "type":"Services"
        }
    ],
    "sg:phone":"+1 936 441 4955",
    "sg:postcode":"77304",
    "sg:province":"TX",
    "sg:tags":[
        "security"
    ],
    "wof:name":"Bill R Roberts",
    "wof:placetype":"venue"
},
  "geometry": {"coordinates":[-95.484638,30.320513],"type":"Point"}
}