{
  "type": "Feature",
  "properties": {
    "iso:country":"US",
    "sg:address":"3103 Greenwood St",
    "sg:city":"Dallas",
    "sg:classifiers":[
        {
            "category":"Building & Trades",
            "subcategory":"Construction",
            "type":"Services"
        }
    ],
    "sg:phone":"+1 214 370 0444",
    "sg:postcode":"75204",
    "sg:province":"TX",
    "sg:tags":[
        "house"
    ],
    "wof:name":"Emergency Home Repair",
    "wof:placetype":"venue"
},
  "geometry": {"coordinates":[-96.78532199999999,32.790494],"type":"Point"}
}