{
  "type": "Feature",
  "properties": {
    "iso:country":"US",
    "sg:address":"2150 Co Rd 316",
    "sg:city":"Jarrell",
    "sg:classifiers":[
        {
            "category":"Professional",
            "type":"Services"
        }
    ],
    "sg:phone":"+1 512 863 5350",
    "sg:postcode":"76537",
    "sg:province":"TX",
    "wof:name":"Johnnie J Simek",
    "wof:placetype":"venue"
},
  "geometry": {"coordinates":[-97.586316,30.765982],"type":"Point"}
}