{
  "type": "Feature",
  "properties": {
    "iso:country":"US",
    "sg:address":"3540 9th Ave",
    "sg:city":"Port Arthur",
    "sg:classifiers":[
        {
            "category":"Recreation",
            "type":"Entertainment"
        }
    ],
    "sg:phone":"+1 409 985 6432",
    "sg:postcode":"77642",
    "sg:province":"TX",
    "sg:tags":[
        "hall",
        "auditorium"
    ],
    "wof:name":"Pear Ridge Community Ctr",
    "wof:placetype":"venue"
},
  "geometry": {"coordinates":[-93.936153,29.919028],"type":"Point"}
}