{
  "type": "Feature",
  "properties": {
    "iso:country":"US",
    "sg:address":"11782 Jollyville Rd",
    "sg:city":"Austin",
    "sg:classifiers":[
        {
            "category":"Insurance",
            "subcategory":"Hazard Insurance",
            "type":"Services"
        }
    ],
    "sg:phone":"+1 254 751 9545",
    "sg:postcode":"78759",
    "sg:province":"TX",
    "sg:website":"austininsurancetx.com#cid=yelp",
    "wof:name":"Pinnacle Insurance Group Inc",
    "wof:placetype":"venue"
},
  "geometry": {"coordinates":[-97.75440999999999,30.421062],"type":"Point"}
}