{
  "type": "Feature",
  "properties": {
    "iso:country":"US",
    "sg:address":"5010 Crenshaw Rd. Suite 130",
    "sg:city":"Houston",
    "sg:classifiers":[
        {
            "category":"Health Services",
            "subcategory":"Doctor",
            "type":"Services"
        },
        {
            "category":"Health Services",
            "subcategory":"Nursing And Care Facility",
            "type":"Services"
        }
    ],
    "sg:phone":"+1 281 991 2200",
    "sg:postcode":"77055",
    "sg:province":"TX",
    "sg:tags":[
        "physician",
        "management",
        "pain",
        "anesthesiology",
        "surgeons"
    ],
    "wof:name":"R P K Anesthesia",
    "wof:placetype":"venue"
},
  "geometry": {"coordinates":[-95.41180300000001,29.778467],"type":"Point"}
}