{
  "type": "Feature",
  "properties": {
    "iso:country":"US",
    "sg:address":"5704 Bay Club Dr",
    "sg:city":"Arlington",
    "sg:classifiers":[
        {
            "category":"Real Estate",
            "subcategory":"Real Estate Agent",
            "type":"Services"
        }
    ],
    "sg:phone":"+1 817 429 2134",
    "sg:postcode":"76013",
    "sg:province":"TX",
    "wof:name":"Acres of Sunshine Ltd",
    "wof:placetype":"venue"
},
  "geometry": {"coordinates":[-97.19502199999999,32.713228],"type":"Point"}
}