{
  "type": "Feature",
  "properties": {
    "iso:country":"US",
    "sg:address":"2811 McKinney Ave",
    "sg:city":"Dallas",
    "sg:classifiers":[
        {
            "category":"Professional",
            "subcategory":"Management & Consulting",
            "type":"Services"
        }
    ],
    "sg:phone":"+1 214 855 5140",
    "sg:postcode":"75204",
    "sg:province":"TX",
    "sg:tags":[
        "public",
        "relations"
    ],
    "wof:name":"Tiller Martin Public Relations",
    "wof:placetype":"venue"
},
  "geometry": {"coordinates":[-96.80096500000001,32.799626],"type":"Point"}
}