{
  "type": "Feature",
  "properties": {
    "iso:country":"US",
    "sg:address":"1001 Belleview St",
    "sg:city":"Dallas",
    "sg:classifiers":[
        {
            "category":"Manufacturing",
            "subcategory":"Food",
            "type":"Manufacturing & Wholesale Goods"
        },
        {
            "category":"Food & Beverages",
            "subcategory":"Supermarket",
            "type":"Retail Goods"
        }
    ],
    "sg:phone":"+1 214 928 9051",
    "sg:postcode":"75215",
    "sg:province":"TX",
    "sg:tags":[
        "product",
        "super",
        "store"
    ],
    "wof:name":"Cerp Foods",
    "wof:placetype":"venue"
},
  "geometry": {"coordinates":[-96.794937,32.768581],"type":"Point"}
}