{
  "type": "Feature",
  "properties": {
    "iso:country":"US",
    "sg:address":"1116 Barclay Dr",
    "sg:city":"Leander",
    "sg:classifiers":[
        {
            "category":"Communications",
            "type":"Services"
        }
    ],
    "sg:phone":"+1 512 818 2813",
    "sg:postcode":"78641",
    "sg:province":"TX",
    "wof:name":"Crucial Crossing Communications",
    "wof:placetype":"venue"
},
  "geometry": {"coordinates":[-97.875497,30.586567],"type":"Point"}
}