{
  "type": "Feature",
  "properties": {
    "iso:country":"US",
    "sg:address":"1506 Alexander St",
    "sg:city":"Sherman",
    "sg:classifiers":[
        {
            "category":"Shopping",
            "subcategory":"Gifts & Souvenirs",
            "type":"Retail Goods"
        }
    ],
    "sg:phone":"+1 903 891 3558",
    "sg:postcode":"75092",
    "sg:province":"TX",
    "wof:name":"Avon Representative",
    "wof:placetype":"venue"
},
  "geometry": {"coordinates":[-96.618092,33.650415],"type":"Point"}
}