{
  "type": "Feature",
  "properties": {
    "iso:country":"US",
    "sg:address":"14651 Sycamore Rd",
    "sg:city":"Cat Spring",
    "sg:classifiers":[
        {
            "category":"Retail",
            "subcategory":"Animal Services",
            "type":"Services"
        }
    ],
    "sg:phone":"+1 979 992 3980",
    "sg:postcode":"78933",
    "sg:province":"TX",
    "sg:tags":[
        "breeder",
        "boxers"
    ],
    "wof:name":"Tummelin Boxers",
    "wof:placetype":"venue"
},
  "geometry": {"coordinates":[-96.32998499999999,29.881274],"type":"Point"}
}