{
  "type": "Feature",
  "properties": {
    "iso:country":"US",
    "sg:address":"1203 E Russell Ave",
    "sg:city":"Carrollton",
    "sg:classifiers":[
        {
            "category":"Building & Trades",
            "subcategory":"Plumbing",
            "type":"Services"
        }
    ],
    "sg:phone":"+1 972 446 1114",
    "sg:postcode":"75006",
    "sg:province":"TX",
    "sg:tags":[
        "contractor"
    ],
    "wof:name":"A & M Plumbing",
    "wof:placetype":"venue"
},
  "geometry": {"coordinates":[-96.900396,32.965552],"type":"Point"}
}