{
  "type": "Feature",
  "properties": {
    "iso:country":"US",
    "sg:address":"6004 Ojo De Agua Dr",
    "sg:city":"El Paso",
    "sg:classifiers":[
        {
            "category":"Professional",
            "subcategory":"Lawyer & Legal Services",
            "type":"Services"
        }
    ],
    "sg:phone":"+1 915 581 9010",
    "sg:postcode":"79912",
    "sg:province":"TX",
    "wof:name":"Montrose Gerard Atty",
    "wof:placetype":"venue"
},
  "geometry": {"coordinates":[-106.520442,31.862648],"type":"Point"}
}