{
  "type": "Feature",
  "properties": {
    "iso:country":"US",
    "sg:address":"100 Perkins Ave",
    "sg:city":"League City",
    "sg:classifiers":[
        {
            "category":"Restaurant",
            "type":"Food & Drink"
        }
    ],
    "sg:phone":"+1 281 316 1444",
    "sg:postcode":"77573",
    "sg:province":"TX",
    "wof:name":"Salsas Mexican Restaurant",
    "wof:placetype":"venue"
},
  "geometry": {"coordinates":[-95.09263300000001,29.509959],"type":"Point"}
}