{
  "type": "Feature",
  "properties": {
    "iso:country":"US",
    "sg:address":"16411 Ledge Pt",
    "sg:city":"San Antonio",
    "sg:classifiers":[
        {
            "category":"Personal",
            "type":"Services"
        }
    ],
    "sg:phone":"+1 210 481 3373",
    "sg:postcode":"78232",
    "sg:province":"TX",
    "sg:tags":[
        "consultant",
        "wedding"
    ],
    "sg:website":"www.sawedpages.com",
    "wof:name":"Knot",
    "wof:placetype":"venue"
},
  "geometry": {"coordinates":[-98.453321,29.592474],"type":"Point"}
}