{
  "type": "Feature",
  "properties": {
    "iso:country":"US",
    "sg:address":"5721 W Commerce St",
    "sg:city":"San Antonio",
    "sg:classifiers":[
        {
            "category":"Building & Trades",
            "subcategory":"Construction",
            "type":"Services"
        }
    ],
    "sg:phone":"+1 210 434 3999",
    "sg:postcode":"78237",
    "sg:province":"TX",
    "sg:tags":[
        "general",
        "contractor"
    ],
    "wof:name":"Geldyager Company",
    "wof:placetype":"venue"
},
  "geometry": {"coordinates":[-98.57472,29.432802],"type":"Point"}
}