{
  "type": "Feature",
  "properties": {
    "iso:country":"US",
    "sg:address":"3304 Wiley Post Rd",
    "sg:city":"Carrollton",
    "sg:classifiers":[
        {
            "category":"Retail",
            "subcategory":"Auto Repair",
            "type":"Services"
        }
    ],
    "sg:phone":"+1 972 991 0035",
    "sg:postcode":"75006",
    "sg:province":"TX",
    "wof:name":"Tim's Auto Repair Center",
    "wof:placetype":"venue"
},
  "geometry": {"coordinates":[-96.845901,32.9604],"type":"Point"}
}