{
  "type": "Feature",
  "properties": {
    "iso:country":"US",
    "sg:address":"6830 66th St",
    "sg:city":"Lubbock",
    "sg:classifiers":[
        {
            "category":"Museum",
            "type":"Entertainment"
        }
    ],
    "sg:phone":"+1 806 794 3571",
    "sg:postcode":"79424",
    "sg:province":"TX",
    "sg:tags":[
        "gallery",
        "merchandise"
    ],
    "wof:name":"Jerry P House",
    "wof:placetype":"venue"
},
  "geometry": {"coordinates":[-101.964904,33.534253],"type":"Point"}
}