{
  "type": "Feature",
  "properties": {
    "iso:country":"US",
    "sg:address":"3327 Mangum Rd",
    "sg:city":"Houston",
    "sg:classifiers":[
        {
            "category":"Restaurant",
            "type":"Food & Drink"
        }
    ],
    "sg:phone":"+1 713 686 1688",
    "sg:postcode":"77092",
    "sg:province":"TX",
    "sg:tags":[
        "eating"
    ],
    "wof:name":"China Feast Restaurant",
    "wof:placetype":"venue"
},
  "geometry": {"coordinates":[-95.45934,29.814313],"type":"Point"}
}