{
  "type": "Feature",
  "properties": {
    "iso:country":"US",
    "sg:address":"13302 Langtry St",
    "sg:city":"San Antonio",
    "sg:classifiers":[
        {
            "category":"Professional",
            "subcategory":"Research",
            "type":"Services"
        }
    ],
    "sg:phone":"+1 210 493 7452",
    "sg:postcode":"78248",
    "sg:province":"TX",
    "wof:name":"Hyperion Biotechnology Inc",
    "wof:placetype":"venue"
},
  "geometry": {"coordinates":[-98.525139,29.565137],"type":"Point"}
}