{
  "type": "Feature",
  "properties": {
    "iso:country":"US",
    "sg:address":"110 Valley View Trl",
    "sg:city":"Comfort",
    "sg:classifiers":[
        {
            "category":"Building & Trades",
            "subcategory":"Construction",
            "type":"Services"
        }
    ],
    "sg:phone":"+1 830 995 4545",
    "sg:postcode":"78013",
    "sg:province":"TX",
    "sg:tags":[
        "water",
        "well",
        "drilling"
    ],
    "wof:name":"T Bar Drilling",
    "wof:placetype":"venue"
},
  "geometry": {"coordinates":[-98.779584,30.014847],"type":"Point"}
}