{
  "type": "Feature",
  "properties": {
    "iso:country":"US",
    "sg:address":"6102 Centralcrest St",
    "sg:city":"Houston",
    "sg:classifiers":[
        {
            "category":"Manufacturing",
            "subcategory":"Glass & Minerals",
            "type":"Manufacturing & Wholesale Goods"
        }
    ],
    "sg:phone":"+1 713 682 6600",
    "sg:postcode":"77092",
    "sg:province":"TX",
    "sg:tags":[
        "manufacturer",
        "glassware-wholesale"
    ],
    "sg:website":"http://www.spectraglass.net",
    "wof:name":"Spectra Glass",
    "wof:placetype":"venue"
},
  "geometry": {"coordinates":[-95.475965,29.815719],"type":"Point"}
}