{
  "type": "Feature",
  "properties": {
    "iso:country":"US",
    "sg:address":"1003 Frederick Dr",
    "sg:city":"Edna",
    "sg:classifiers":[
        {
            "category":"Retail",
            "subcategory":"Repair Shop",
            "type":"Services"
        }
    ],
    "sg:phone":"+1 361 782 6414",
    "sg:postcode":"77957",
    "sg:province":"TX",
    "wof:name":"Jakes Taxidermy",
    "wof:placetype":"venue"
},
  "geometry": {"coordinates":[-96.637173,28.96973],"type":"Point"}
}