{
  "type": "Feature",
  "properties": {
    "iso:country":"US",
    "sg:address":"11618 West Ave",
    "sg:city":"San Antonio",
    "sg:classifiers":[
        {
            "category":"Restaurant",
            "type":"Food & Drink"
        }
    ],
    "sg:phone":"+1 210 340 7196",
    "sg:postcode":"78213",
    "sg:province":"TX",
    "sg:tags":[
        "eating"
    ],
    "wof:name":"Burger King",
    "wof:placetype":"venue"
},
  "geometry": {"coordinates":[-98.510081,29.545041],"type":"Point"}
}