{
  "type": "Feature",
  "properties": {
    "iso:country":"US",
    "sg:address":"11360 Harry Hines Blvd",
    "sg:city":"Dallas",
    "sg:classifiers":[
        {
            "category":"Home & Garden",
            "subcategory":"Carpets & Floor Coverings",
            "type":"Retail Goods"
        }
    ],
    "sg:phone":"+1 972 243 3976",
    "sg:postcode":"75229",
    "sg:province":"TX",
    "sg:tags":[
        "carpeting"
    ],
    "wof:name":"Rug Expo Outlet",
    "wof:placetype":"venue"
},
  "geometry": {"coordinates":[-96.8908,32.894699],"type":"Point"}
}