{
  "type": "Feature",
  "properties": {
    "iso:country":"US",
    "sg:address":"216 W 9th St",
    "sg:city":"Houston",
    "sg:classifiers":[
        {
            "category":"Manufacturing",
            "subcategory":"Retail Goods",
            "type":"Manufacturing & Wholesale Goods"
        }
    ],
    "sg:phone":"+1 713 530 0561",
    "sg:postcode":"77007",
    "sg:province":"TX",
    "sg:tags":[
        "product",
        "mfg"
    ],
    "wof:name":"Murberry Candles",
    "wof:placetype":"venue"
},
  "geometry": {"coordinates":[-95.39985299999999,29.786902],"type":"Point"}
}