{
  "type": "Feature",
  "properties": {
    "iso:country":"US",
    "sg:address":"400 W 15th St",
    "sg:city":"Austin",
    "sg:classifiers":[
        {
            "category":"Professional",
            "type":"Services"
        },
        {
            "category":"Utilities",
            "subcategory":"Fuel Oil & Lpg",
            "type":"Services"
        }
    ],
    "sg:phone":"+1 512 391 0900",
    "sg:postcode":"78701",
    "sg:province":"TX",
    "sg:tags":[
        "development",
        "field",
        "exploration",
        "gas"
    ],
    "sg:website":"http://www.oculusenergy.com",
    "wof:name":"Oculus Energy",
    "wof:placetype":"venue"
},
  "geometry": {"coordinates":[-97.74299600000001,30.277969],"type":"Point"}
}