{
  "type": "Feature",
  "properties": {
    "iso:country":"US",
    "sg:address":"404 Northvalley Dr",
    "sg:city":"San Antonio",
    "sg:classifiers":[
        {
            "category":"Professional",
            "type":"Services"
        }
    ],
    "sg:phone":"+1 210 344 7945",
    "sg:postcode":"78216",
    "sg:province":"TX",
    "wof:name":"Martha Trevino",
    "wof:placetype":"venue"
},
  "geometry": {"coordinates":[-98.49966000000001,29.53063],"type":"Point"}
}