{
  "type": "Feature",
  "properties": {
    "iso:country":"US",
    "sg:address":"10117 Loving Trail Dr",
    "sg:city":"Frisco",
    "sg:classifiers":[
        {
            "category":"Food & Beverages",
            "subcategory":"Specialty",
            "type":"Retail Goods"
        }
    ],
    "sg:phone":"+1 972 731 5600",
    "sg:postcode":"75035",
    "sg:province":"TX",
    "sg:tags":[
        "product",
        "health",
        "diet"
    ],
    "wof:name":"Rowdy Distribution",
    "wof:placetype":"venue"
},
  "geometry": {"coordinates":[-96.792029,33.120998],"type":"Point"}
}