{
  "type": "Feature",
  "properties": {
    "iso:country":"US",
    "sg:address":"913 Meyer Rd",
    "sg:city":"Seabrook",
    "sg:classifiers":[
        {
            "category":"Insurance",
            "subcategory":"Insurance Agent",
            "type":"Services"
        }
    ],
    "sg:phone":"+1 281 474 4949",
    "sg:postcode":"77586",
    "sg:province":"TX",
    "wof:name":"Andrews Insurance",
    "wof:placetype":"venue"
},
  "geometry": {"coordinates":[-95.02471199999999,29.56065],"type":"Point"}
}