{
  "type": "Feature",
  "properties": {
    "iso:country":"US",
    "sg:address":"6703 Fort Davis Cove",
    "sg:city":"Austin",
    "sg:classifiers":[
        {
            "category":"Arts & Performance",
            "subcategory":"Theater",
            "type":"Entertainment"
        }
    ],
    "sg:phone":"+1 512 343 6299",
    "sg:postcode":"78731",
    "sg:province":"TX",
    "sg:tags":[
        "theatrical"
    ],
    "wof:name":"Maximus Entertainment",
    "wof:placetype":"venue"
},
  "geometry": {"coordinates":[-97.779819,30.363157],"type":"Point"}
}