{
  "type": "Feature",
  "properties": {
    "iso:country":"US",
    "sg:address":"7313 S Kirkwood Rd",
    "sg:city":"Houston",
    "sg:classifiers":[
        {
            "category":"Personal",
            "subcategory":"Beauty Salon",
            "type":"Services"
        }
    ],
    "sg:phone":"+1 281 879 0856",
    "sg:postcode":"77072",
    "sg:province":"TX",
    "sg:tags":[
        "shop"
    ],
    "wof:name":"Lydia's Coiffure",
    "wof:placetype":"venue"
},
  "geometry": {"coordinates":[-95.58763999999999,29.696953],"type":"Point"}
}