{
  "type": "Feature",
  "properties": {
    "iso:country":"US",
    "sg:address":"50 Briar Hollow Ln",
    "sg:city":"Houston",
    "sg:classifiers":[
        {
            "category":"Professional",
            "subcategory":"Advertising",
            "type":"Services"
        }
    ],
    "sg:phone":"+1 713 627 2727",
    "sg:postcode":"77027",
    "sg:province":"TX",
    "sg:tags":[
        "counselor"
    ],
    "wof:name":"Casper Creative Consulting",
    "wof:placetype":"venue"
},
  "geometry": {"coordinates":[-95.45195,29.752445],"type":"Point"}
}