{
  "type": "Feature",
  "properties": {
    "iso:country":"US",
    "sg:address":"935 Iowa St",
    "sg:city":"San Antonio",
    "sg:classifiers":[
        {
            "category":"Organizations",
            "subcategory":"Religious Organization",
            "type":"Services"
        }
    ],
    "sg:phone":"+1 210 533 5261",
    "sg:postcode":"78203",
    "sg:province":"TX",
    "sg:tags":[
        "church"
    ],
    "wof:name":"Friendship Baptist Church",
    "wof:placetype":"venue"
},
  "geometry": {"coordinates":[-98.46740699999999,29.412076],"type":"Point"}
}