{
  "type": "Feature",
  "properties": {
    "iso:country":"US",
    "sg:address":"6002 Town Hill Dr",
    "sg:city":"San Antonio",
    "sg:classifiers":[
        {
            "category":"Building & Trades",
            "subcategory":"Plumbing",
            "type":"Services"
        }
    ],
    "sg:phone":"+1 210 823 8770",
    "sg:postcode":"78238",
    "sg:province":"TX",
    "sg:tags":[
        "conditioning",
        "contractor",
        "system",
        "air"
    ],
    "wof:name":"Bravo Air & Heat",
    "wof:placetype":"venue"
},
  "geometry": {"coordinates":[-98.605414,29.45851],"type":"Point"}
}