{
  "type": "Feature",
  "properties": {
    "iso:country":"US",
    "sg:address":"11 E Main St",
    "sg:city":"Bellville",
    "sg:classifiers":[
        {
            "category":"Shopping",
            "subcategory":"Gifts & Souvenirs",
            "type":"Retail Goods"
        }
    ],
    "sg:phone":"+1 979 865 1701",
    "sg:postcode":"77418",
    "sg:province":"TX",
    "sg:tags":[
        "shop"
    ],
    "wof:name":"A Blast From The Past Too",
    "wof:placetype":"venue"
},
  "geometry": {"coordinates":[-96.257631,29.950338],"type":"Point"}
}