{
  "type": "Feature",
  "properties": {
    "iso:country":"US",
    "sg:address":"5200 Mitchelldale St Ste D1",
    "sg:city":"Houston",
    "sg:classifiers":[
        {
            "category":"Cinema",
            "subcategory":"Movie Rental",
            "type":"Entertainment"
        }
    ],
    "sg:phone":"+1 713 290 1260",
    "sg:postcode":"77092",
    "sg:province":"TX",
    "sg:tags":[
        "game",
        "video"
    ],
    "wof:name":"The New Release",
    "wof:placetype":"venue"
},
  "geometry": {"coordinates":[-95.465913,29.814513],"type":"Point"}
}