{
  "type": "Feature",
  "properties": {
    "iso:country":"US",
    "sg:address":"217 S Jennings Ave",
    "sg:city":"Fort Worth",
    "sg:classifiers":[
        {
            "category":"Recreation",
            "type":"Entertainment"
        },
        {
            "category":"Shopping",
            "subcategory":"Crafts & Fabrics",
            "type":"Retail Goods"
        }
    ],
    "sg:phone":"+1 817 878 2740",
    "sg:postcode":"76104",
    "sg:province":"TX",
    "sg:tags":[
        "sewing",
        "yarn"
    ],
    "wof:name":"Jenningstreet Yarns LLC",
    "wof:placetype":"venue"
},
  "geometry": {"coordinates":[-97.329899,32.742162],"type":"Point"}
}