{
  "type": "Feature",
  "properties": {
    "iso:country":"US",
    "sg:address":"711 Ferris Ave",
    "sg:city":"Waxahachie",
    "sg:classifiers":[
        {
            "category":"Insurance",
            "subcategory":"Hazard Insurance",
            "type":"Services"
        },
        {
            "category":"Insurance",
            "subcategory":"Life Insurance",
            "type":"Services"
        }
    ],
    "sg:phone":"+1 972 937 9907",
    "sg:postcode":"75165",
    "sg:province":"TX",
    "sg:tags":[
        "group"
    ],
    "wof:name":"Woodmen Insurance Agency, Inc.",
    "wof:placetype":"venue"
},
  "geometry": {"coordinates":[-96.84656699999999,32.394297],"type":"Point"}
}