{
  "type": "Feature",
  "properties": {
    "iso:country":"US",
    "sg:address":"5002 Spencer Hwy",
    "sg:city":"Pasadena",
    "sg:classifiers":[
        {
            "category":"Bars & Pubs",
            "type":"Food & Drink"
        }
    ],
    "sg:phone":"+1 281 998 7975",
    "sg:postcode":"77505",
    "sg:province":"TX",
    "wof:name":"E & D's Pub",
    "wof:placetype":"venue"
},
  "geometry": {"coordinates":[-95.16641300000001,29.66535],"type":"Point"}
}