{
  "type": "Feature",
  "properties": {
    "iso:country":"US",
    "sg:address":"4007 James Casey St",
    "sg:city":"Austin",
    "sg:classifiers":[
        {
            "category":"Health Services",
            "subcategory":"Doctor",
            "type":"Services"
        }
    ],
    "sg:phone":"+1 512 441 4400",
    "sg:postcode":"78745",
    "sg:province":"TX",
    "sg:tags":[
        "physician",
        "surgeon"
    ],
    "wof:name":"Family Practice Assoc",
    "wof:placetype":"venue"
},
  "geometry": {"coordinates":[-97.773804,30.225765],"type":"Point"}
}