{
  "type": "Feature",
  "properties": {
    "iso:country":"US",
    "sg:address":"795 N Winningkoff Rd",
    "sg:city":"Allen",
    "sg:classifiers":[
        {
            "category":"Banks & Credit Unions",
            "subcategory":"Financial Services",
            "type":"Services"
        }
    ],
    "sg:phone":"+1 972 727 3050",
    "sg:postcode":"75002",
    "sg:province":"TX",
    "sg:tags":[
        "investor"
    ],
    "wof:name":"Stretcher & Abernathy",
    "wof:placetype":"venue"
},
  "geometry": {"coordinates":[-96.568603,33.094681],"type":"Point"}
}