{
  "type": "Feature",
  "properties": {
    "iso:country":"US",
    "sg:address":"7219 Lugary Dr",
    "sg:city":"Houston",
    "sg:classifiers":[
        {
            "category":"Professional",
            "type":"Services"
        }
    ],
    "sg:phone":"+1 713 398 9578",
    "sg:postcode":"77036",
    "sg:province":"TX",
    "wof:name":"Foro 4",
    "wof:placetype":"venue"
},
  "geometry": {"coordinates":[-95.519285,29.700431],"type":"Point"}
}