{
  "type": "Feature",
  "properties": {
    "iso:country":"US",
    "sg:address":"27650 State Hwy 249",
    "sg:city":"Tomball",
    "sg:classifiers":[
        {
            "category":"Restaurant",
            "type":"Food & Drink"
        }
    ],
    "sg:phone":"+1 281 516 0730",
    "sg:postcode":"77375",
    "sg:province":"TX",
    "wof:name":"Mc Donald's",
    "wof:placetype":"venue"
},
  "geometry": {"coordinates":[-95.625235,30.070602],"type":"Point"}
}