{
  "type": "Feature",
  "properties": {
    "iso:country":"US",
    "sg:address":"4121 Colleyville Blvd Ste. 12",
    "sg:city":"Colleyville",
    "sg:classifiers":[
        {
            "category":"Insurance",
            "subcategory":"Hazard Insurance",
            "type":"Services"
        },
        {
            "category":"Insurance",
            "subcategory":"Insurance Agent",
            "type":"Services"
        },
        {
            "category":"Insurance",
            "subcategory":"Life Insurance",
            "type":"Services"
        },
        {
            "category":"Insurance",
            "subcategory":"Title Insurance",
            "type":"Services"
        }
    ],
    "sg:phone":"+1 817 656 0885",
    "sg:postcode":"76034",
    "sg:province":"TX",
    "sg:tags":[
        "auto",
        "motorcycle",
        "homeowner"
    ],
    "sg:website":"http://clickserve.dartsearch.net/link/click?lid=43000000319050570",
    "wof:name":"Mark Jameson, CLTC - Allstate Insurance Company",
    "wof:placetype":"venue"
},
  "geometry": {"coordinates":[-97.168334,32.870301],"type":"Point"}
}