{
  "type": "Feature",
  "properties": {
    "iso:country":"US",
    "sg:address":"16023 East Fwy",
    "sg:city":"Channelview",
    "sg:classifiers":[
        {
            "category":"Freight",
            "type":"Transportation"
        }
    ],
    "sg:phone":"+1 281 452 9062",
    "sg:postcode":"77530",
    "sg:province":"TX",
    "sg:tags":[
        "general"
    ],
    "wof:name":"Braun Realty",
    "wof:placetype":"venue"
},
  "geometry": {"coordinates":[-95.117417,29.781044],"type":"Point"}
}