{
  "type": "Feature",
  "properties": {
    "iso:country":"US",
    "sg:address":"2521 N Loop 35",
    "sg:city":"Alvin",
    "sg:classifiers":[
        {
            "category":"Wholesale",
            "subcategory":"Hardware",
            "type":"Manufacturing & Wholesale Goods"
        }
    ],
    "sg:phone":"+1 281 331 9296",
    "sg:postcode":"77511",
    "sg:province":"TX",
    "sg:tags":[
        "stapler",
        "tacker",
        "staple"
    ],
    "wof:name":"Southern Fastening Systems LLC",
    "wof:placetype":"venue"
},
  "geometry": {"coordinates":[-95.23635400000001,29.444002],"type":"Point"}
}