{
  "type": "Feature",
  "properties": {
    "iso:country":"US",
    "sg:address":"301 W Taylor Ave",
    "sg:city":"Round Rock",
    "sg:classifiers":[
        {
            "category":"Restaurant",
            "type":"Food & Drink"
        }
    ],
    "sg:phone":"+1 512 310 1992",
    "sg:postcode":"78664",
    "sg:province":"TX",
    "wof:name":"El Arroyo-Del Norte",
    "wof:placetype":"venue"
},
  "geometry": {"coordinates":[-97.68449,30.517513],"type":"Point"}
}