{
  "type": "Feature",
  "properties": {
    "iso:country":"US",
    "sg:address":"3300 McCart Ave",
    "sg:city":"Fort Worth",
    "sg:classifiers":[
        {
            "category":"Home & Garden",
            "subcategory":"Building Materials",
            "type":"Retail Goods"
        }
    ],
    "sg:phone":"+1 817 924 4444",
    "sg:postcode":"76110",
    "sg:province":"TX",
    "sg:tags":[
        "glass",
        "window",
        "plate"
    ],
    "sg:website":"www.aaa-glass.com",
    "wof:name":"AAA Glass Co",
    "wof:placetype":"venue"
},
  "geometry": {"coordinates":[-97.35341699999999,32.701279],"type":"Point"}
}