{
  "type": "Feature",
  "properties": {
    "iso:country":"US",
    "sg:address":"1855 Fountain View Dr",
    "sg:city":"Houston",
    "sg:classifiers":[
        {
            "category":"Local Transit",
            "type":"Transportation"
        }
    ],
    "sg:phone":"+1 281 920 0011",
    "sg:postcode":"77057",
    "sg:province":"TX",
    "sg:tags":[
        "passenger"
    ],
    "wof:name":"Diamond Town Car",
    "wof:placetype":"venue"
},
  "geometry": {"coordinates":[-95.485904,29.747952],"type":"Point"}
}