{
  "type": "Feature",
  "properties": {
    "iso:country":"US",
    "sg:address":"7405 Las Colinas Blvd",
    "sg:city":"Irving",
    "sg:classifiers":[
        {
            "category":"Banks & Credit Unions",
            "subcategory":"Bank",
            "type":"Services"
        }
    ],
    "sg:phone":"+1 972 501 0176",
    "sg:postcode":"75063",
    "sg:province":"TX",
    "sg:tags":[
        "commercial",
        "saving"
    ],
    "wof:name":"Morgan Keegan & Co Inc",
    "wof:placetype":"venue"
},
  "geometry": {"coordinates":[-96.953778,32.908812],"type":"Point"}
}