{
  "type": "Feature",
  "properties": {
    "iso:country":"US",
    "sg:address":"18302 Pamela Way",
    "sg:city":"Spring",
    "sg:classifiers":[
        {
            "category":"Food & Beverages",
            "subcategory":"Groceries & Convenience Stores",
            "type":"Retail Goods"
        }
    ],
    "sg:phone":"+1 281 370 1723",
    "sg:postcode":"77379",
    "sg:province":"TX",
    "wof:name":"Marthas Market",
    "wof:placetype":"venue"
},
  "geometry": {"coordinates":[-95.50452,30.033867],"type":"Point"}
}