{
  "type": "Feature",
  "properties": {
    "iso:country":"US",
    "sg:address":"4315 Woodvalley Dr",
    "sg:city":"Houston",
    "sg:classifiers":[
        {
            "category":"Professional",
            "type":"Services"
        }
    ],
    "sg:phone":"+1 713 721 0424",
    "sg:postcode":"77096",
    "sg:province":"TX",
    "wof:name":"Wayne Howard Corp",
    "wof:placetype":"venue"
},
  "geometry": {"coordinates":[-95.45204,29.680098],"type":"Point"}
}