{
  "type": "Feature",
  "properties": {
    "iso:country":"US",
    "sg:address":"301 Mimosa Dr",
    "sg:city":"Denton",
    "sg:classifiers":[
        {
            "category":"Building & Trades",
            "subcategory":"Plumbing",
            "type":"Services"
        }
    ],
    "sg:phone":"+1 940 382 5580",
    "sg:postcode":"76201",
    "sg:province":"TX",
    "sg:tags":[
        "air",
        "conditioning",
        "heating"
    ],
    "wof:name":"Wilson Heating & AC",
    "wof:placetype":"venue"
},
  "geometry": {"coordinates":[-97.1344,33.23899],"type":"Point"}
}