{
  "type": "Feature",
  "properties": {
    "iso:country":"US",
    "sg:address":"21726 Park Valley Dr",
    "sg:city":"Katy",
    "sg:classifiers":[
        {
            "category":"Shopping",
            "subcategory":"Hobbies, Toys, & Games",
            "type":"Retail Goods"
        }
    ],
    "sg:phone":"+1 281 647 9866",
    "sg:postcode":"77450",
    "sg:province":"TX",
    "wof:name":"Persimmon Branch",
    "wof:placetype":"venue"
},
  "geometry": {"coordinates":[-95.747641,29.760888],"type":"Point"}
}