{
  "type": "Feature",
  "properties": {
    "iso:country":"US",
    "sg:address":"13304 State Hwy 110",
    "sg:city":"Tyler",
    "sg:classifiers":[
        {
            "category":"Building & Trades",
            "subcategory":"Construction",
            "type":"Services"
        }
    ],
    "sg:phone":"+1 903 561 7835",
    "sg:postcode":"75707",
    "sg:province":"TX",
    "sg:tags":[
        "contractor"
    ],
    "wof:name":"Premier Plastering Inc",
    "wof:placetype":"venue"
},
  "geometry": {"coordinates":[-95.25157,32.28625],"type":"Point"}
}