{
  "type": "Feature",
  "properties": {
    "iso:country":"US",
    "sg:address":"4701 W Cuthbert Ave",
    "sg:city":"Midland",
    "sg:classifiers":[
        {
            "category":"Recreation",
            "type":"Entertainment"
        }
    ],
    "sg:phone":"+1 432 522 1426",
    "sg:postcode":"79703",
    "sg:province":"TX",
    "wof:name":"Babes Batting Cage",
    "wof:placetype":"venue"
},
  "geometry": {"coordinates":[-102.142921,31.992825],"type":"Point"}
}