{
  "type": "Feature",
  "properties": {
    "iso:country":"US",
    "sg:address":"2719 Texas Ave",
    "sg:city":"Texas City",
    "sg:classifiers":[
        {
            "category":"Manufacturing",
            "subcategory":"Signs",
            "type":"Manufacturing & Wholesale Goods"
        },
        {
            "category":"Wholesale",
            "subcategory":"Non-durable Goods",
            "type":"Manufacturing & Wholesale Goods"
        }
    ],
    "sg:phone":"+1 409 945 4929",
    "sg:postcode":"77590",
    "sg:province":"TX",
    "sg:tags":[
        "mfg"
    ],
    "wof:name":"Creative Signs and Display",
    "wof:placetype":"venue"
},
  "geometry": {"coordinates":[-94.934724,29.383819],"type":"Point"}
}