{
  "type": "Feature",
  "properties": {
    "iso:country":"US",
    "sg:address":"9111 Hufsmith Kuykendahl Rd",
    "sg:city":"Tomball",
    "sg:classifiers":[
        {
            "category":"Restaurant",
            "type":"Food & Drink"
        }
    ],
    "sg:phone":"+1 281 516 7977",
    "sg:postcode":"77375",
    "sg:province":"TX",
    "wof:name":"Gumbeaux's",
    "wof:placetype":"venue"
},
  "geometry": {"coordinates":[-95.561358,30.106206],"type":"Point"}
}