{
  "type": "Feature",
  "properties": {
    "iso:country":"US",
    "sg:address":"1542 Saddle Club Dr",
    "sg:city":"Kerrville",
    "sg:classifiers":[
        {
            "category":"Professional",
            "subcategory":"Lawyer & Legal Services",
            "type":"Services"
        }
    ],
    "sg:phone":"+1 830 896 7703",
    "sg:postcode":"78028",
    "sg:province":"TX",
    "wof:name":"Mike Joplin PC",
    "wof:placetype":"venue"
},
  "geometry": {"coordinates":[-99.123065,29.970285],"type":"Point"}
}