{
  "type": "Feature",
  "properties": {
    "iso:country":"US",
    "sg:address":"301 Mattison St",
    "sg:city":"Pittsburg",
    "sg:classifiers":[
        {
            "category":"Wholesale",
            "subcategory":"Durable Goods & Equipment",
            "type":"Manufacturing & Wholesale Goods"
        }
    ],
    "sg:phone":"+1 903 856 0505",
    "sg:postcode":"75686",
    "sg:province":"TX",
    "sg:tags":[
        "representative",
        "manufacturer"
    ],
    "wof:name":"Pittsburg Manufacturing Co",
    "wof:placetype":"venue"
},
  "geometry": {"coordinates":[-94.971267,33.002429],"type":"Point"}
}