{
  "type": "Feature",
  "properties": {
    "iso:country":"US",
    "sg:address":"6322 Goliad Ave",
    "sg:city":"Dallas",
    "sg:classifiers":[
        {
            "category":"Building & Trades",
            "subcategory":"Electrical",
            "type":"Services"
        }
    ],
    "sg:phone":"+1 214 826 9810",
    "sg:postcode":"75214",
    "sg:province":"TX",
    "sg:tags":[
        "electrical",
        "contractor"
    ],
    "wof:name":"Jordans Blessings",
    "wof:placetype":"venue"
},
  "geometry": {"coordinates":[-96.75356499999999,32.81806],"type":"Point"}
}