{
  "type": "Feature",
  "properties": {
    "iso:country":"US",
    "sg:address":"19203 Foxtree Ln",
    "sg:city":"Houston",
    "sg:classifiers":[
        {
            "category":"Manufacturing",
            "subcategory":"Paper Products",
            "type":"Manufacturing & Wholesale Goods"
        }
    ],
    "sg:phone":"+1 281 647 0300",
    "sg:postcode":"77094",
    "sg:province":"TX",
    "sg:tags":[
        "mill"
    ],
    "wof:name":"Paper Moon Enterprises",
    "wof:placetype":"venue"
},
  "geometry": {"coordinates":[-95.703155,29.763141],"type":"Point"}
}