{
  "type": "Feature",
  "properties": {
    "iso:country":"US",
    "sg:address":"2505 Sherman St",
    "sg:city":"Grand Prairie",
    "sg:classifiers":[
        {
            "category":"Organizations",
            "subcategory":"Labor Organization",
            "type":"Services"
        }
    ],
    "sg:phone":"+1 972 647 1282",
    "sg:postcode":"75051",
    "sg:province":"TX",
    "wof:name":"UAW",
    "wof:placetype":"venue"
},
  "geometry": {"coordinates":[-97.04134500000001,32.734969],"type":"Point"}
}