{
  "type": "Feature",
  "properties": {
    "iso:country":"US",
    "sg:address":"18250 Marsh Ln",
    "sg:city":"Dallas",
    "sg:classifiers":[
        {
            "category":"Wholesale",
            "subcategory":"Durable Goods & Equipment",
            "type":"Manufacturing & Wholesale Goods"
        }
    ],
    "sg:phone":"+1 214 335 3456",
    "sg:postcode":"75287",
    "sg:province":"TX",
    "sg:tags":[
        "medical",
        "scientific",
        "supply"
    ],
    "wof:name":"American Liberty Corporation",
    "wof:placetype":"venue"
},
  "geometry": {"coordinates":[-96.855504,32.999469],"type":"Point"}
}