{
  "type": "Feature",
  "properties": {
    "iso:country":"US",
    "sg:address":"4231 Gulfway Dr",
    "sg:city":"Port Arthur",
    "sg:classifiers":[
        {
            "category":"Restaurant",
            "type":"Food & Drink"
        }
    ],
    "sg:phone":"+1 409 983 7545",
    "sg:postcode":"77642",
    "sg:province":"TX",
    "sg:tags":[
        "eating"
    ],
    "wof:name":"Tequila's Mexican Restaurant",
    "wof:placetype":"venue"
},
  "geometry": {"coordinates":[-93.910197,29.918907],"type":"Point"}
}