{
  "type": "Feature",
  "properties": {
    "iso:country":"US",
    "sg:address":"6417 Tara Dr",
    "sg:city":"Austin",
    "sg:classifiers":[
        {
            "category":"Home & Garden",
            "subcategory":"Household Appliances",
            "type":"Retail Goods"
        },
        {
            "category":"Wholesale",
            "subcategory":"Machinery & Supplies",
            "type":"Manufacturing & Wholesale Goods"
        },
        {
            "category":"Retail",
            "subcategory":"Repair Shop",
            "type":"Services"
        }
    ],
    "sg:phone":"+1 512 450 2643",
    "sg:postcode":"78747",
    "sg:province":"TX",
    "sg:tags":[
        "major",
        "part",
        "refinishing"
    ],
    "sg:website":"http://www.frankiesappliancerepair.com",
    "wof:name":"Frankies Appliance Repair",
    "wof:placetype":"venue"
},
  "geometry": {"coordinates":[-97.74224100000001,30.163169],"type":"Point"}
}