{
  "type": "Feature",
  "properties": {
    "iso:country":"US",
    "sg:address":"4806 Evans Ave",
    "sg:city":"Austin",
    "sg:classifiers":[
        {
            "category":"Professional",
            "subcategory":"Computer Services",
            "type":"Services"
        }
    ],
    "sg:phone":"+1 512 453 9633",
    "sg:postcode":"78751",
    "sg:province":"TX",
    "sg:tags":[
        "datum"
    ],
    "wof:name":"Norris Harrell",
    "wof:placetype":"venue"
},
  "geometry": {"coordinates":[-97.72103799999999,30.310896],"type":"Point"}
}