{
  "type": "Feature",
  "properties": {
    "iso:country":"US",
    "sg:address":"7122 Las Ventanas Dr",
    "sg:city":"Austin",
    "sg:classifiers":[
        {
            "category":"Health Services",
            "subcategory":"Doctor",
            "type":"Services"
        }
    ],
    "sg:phone":"+1 512 346 5875",
    "sg:postcode":"73301",
    "sg:province":"TX",
    "wof:name":"Young Stephen W MD",
    "wof:placetype":"venue"
},
  "geometry": {"coordinates":[-97.74900100000001,30.2201],"type":"Point"}
}