{
  "type": "Feature",
  "properties": {
    "iso:country":"US",
    "sg:address":"10060 Rushing Rd",
    "sg:city":"El Paso",
    "sg:classifiers":[
        {
            "category":"Food & Beverages",
            "subcategory":"Groceries & Convenience Stores",
            "type":"Retail Goods"
        }
    ],
    "sg:phone":"+1 915 757 0476",
    "sg:postcode":"79924",
    "sg:province":"TX",
    "sg:tags":[
        "grocer"
    ],
    "wof:name":"Smith's Food & Drug",
    "wof:placetype":"venue"
},
  "geometry": {"coordinates":[-106.420849,31.900739],"type":"Point"}
}