{
  "type": "Feature",
  "properties": {
    "iso:country":"US",
    "sg:address":"817 W Howard Lane",
    "sg:city":"Austin",
    "sg:classifiers":[
        {
            "category":"Communications",
            "subcategory":"Film & Video Production",
            "type":"Services"
        },
        {
            "category":"Professional",
            "subcategory":"Art Services",
            "type":"Services"
        },
        {
            "category":"Shopping",
            "subcategory":"Computers & Home Electronics",
            "type":"Retail Goods"
        },
        {
            "category":"Professional",
            "subcategory":"Printing & Photocopies",
            "type":"Services"
        }
    ],
    "sg:phone":"+1 512 251 7778",
    "sg:postcode":"78753",
    "sg:province":"TX",
    "sg:tags":[
        "supply",
        "dvd",
        "duplicating",
        "cd",
        "equipment",
        "cassette",
        "copying",
        "creative",
        "audio-visual"
    ],
    "wof:name":"Omega Broadcast Group",
    "wof:placetype":"venue"
},
  "geometry": {"coordinates":[-97.66399699999999,30.420802],"type":"Point"}
}