{
  "type": "Feature",
  "properties": {
    "iso:country":"US",
    "sg:address":"7315 Nordling Rd",
    "sg:city":"Houston",
    "sg:classifiers":[
        {
            "category":"Home & Garden",
            "subcategory":"Hardware",
            "type":"Retail Goods"
        }
    ],
    "sg:phone":"+1 713 699 2277",
    "sg:postcode":"77076",
    "sg:province":"TX",
    "wof:name":"Autoware",
    "wof:placetype":"venue"
},
  "geometry": {"coordinates":[-95.391288,29.869924],"type":"Point"}
}