{
  "type": "Feature",
  "properties": {
    "iso:country":"US",
    "sg:address":"2727 San Jose Ave",
    "sg:city":"El Paso",
    "sg:classifiers":[
        {
            "category":"Freight",
            "type":"Transportation"
        }
    ],
    "sg:phone":"+1 915 867 3061",
    "sg:postcode":"79930",
    "sg:province":"TX",
    "sg:tags":[
        "operator",
        "vault",
        "safe",
        "local",
        "trucking"
    ],
    "wof:name":"Mowad Moving Co",
    "wof:placetype":"venue"
},
  "geometry": {"coordinates":[-106.462951,31.786913],"type":"Point"}
}