{
  "type": "Feature",
  "properties": {
    "iso:country":"US",
    "sg:address":"1715 N Woods St",
    "sg:city":"Sherman",
    "sg:classifiers":[
        {
            "category":"Retail",
            "subcategory":"Auto Repair",
            "type":"Services"
        }
    ],
    "sg:phone":"+1 903 893 4303",
    "sg:postcode":"75092",
    "sg:province":"TX",
    "sg:tags":[
        "repairing",
        "automobile"
    ],
    "wof:name":"Anthony's Family Car Clinic",
    "wof:placetype":"venue"
},
  "geometry": {"coordinates":[-96.619984,33.652395],"type":"Point"}
}