{
  "type": "Feature",
  "properties": {
    "iso:country":"US",
    "sg:address":"25231 Grogans Mill Rd",
    "sg:city":"Spring",
    "sg:classifiers":[
        {
            "category":"Mining & Drilling",
            "type":"Manufacturing & Wholesale Goods"
        }
    ],
    "sg:phone":"+1 281 362 8600",
    "sg:postcode":"77380",
    "sg:province":"TX",
    "sg:tags":[
        "oil",
        "gas",
        "producer"
    ],
    "wof:name":"Locin Oil Corp",
    "wof:placetype":"venue"
},
  "geometry": {"coordinates":[-95.45693799999999,30.128745],"type":"Point"}
}