{
  "type": "Feature",
  "properties": {
    "iso:country":"US",
    "sg:address":"6016 Dunn Dr",
    "sg:city":"Lewisville",
    "sg:classifiers":[
        {
            "category":"Professional",
            "subcategory":"Computer Services",
            "type":"Services"
        }
    ],
    "sg:phone":"+1 972 625 0245",
    "sg:postcode":"75056",
    "sg:province":"TX",
    "sg:tags":[
        "related"
    ],
    "wof:name":"Clear Screen Computer Service",
    "wof:placetype":"venue"
},
  "geometry": {"coordinates":[-96.857613,33.10439],"type":"Point"}
}