{
  "type": "Feature",
  "properties": {
    "iso:country":"US",
    "sg:address":"610 Canyon Rim Dr # B",
    "sg:city":"Austin",
    "sg:classifiers":[
        {
            "category":"Banks & Credit Unions",
            "subcategory":"Financial Services",
            "type":"Services"
        }
    ],
    "sg:phone":"+1 512 329 8011",
    "sg:postcode":"78746",
    "sg:province":"TX",
    "sg:tags":[
        "broker",
        "mortgage"
    ],
    "sg:website":"www.bartoncreekmtg.com",
    "wof:name":"BARTON CREEK MORTGAGE",
    "wof:placetype":"venue"
},
  "geometry": {"coordinates":[-97.84701099999999,30.295735],"type":"Point"}
}