{
  "type": "Feature",
  "properties": {
    "iso:country":"US",
    "sg:address":"6555 Meadow Creek Dr",
    "sg:city":"Dallas",
    "sg:classifiers":[
        {
            "category":"Professional",
            "subcategory":"Management & Consulting",
            "type":"Services"
        }
    ],
    "sg:phone":"+1 972 490 9357",
    "sg:postcode":"75254",
    "sg:province":"TX",
    "wof:name":"Real Estate Marketing Assoc",
    "wof:placetype":"venue"
},
  "geometry": {"coordinates":[-96.792914,32.945712],"type":"Point"}
}