{
  "type": "Feature",
  "properties": {
    "iso:country":"US",
    "sg:address":"11909 Wishing Well Ct",
    "sg:city":"Frisco",
    "sg:classifiers":[
        {
            "category":"Restaurant",
            "type":"Food & Drink"
        }
    ],
    "sg:phone":"+1 972 335 3565",
    "sg:postcode":"75035",
    "sg:province":"TX",
    "sg:tags":[
        "caterer"
    ],
    "wof:name":"Custom Cuisine Catering",
    "wof:placetype":"venue"
},
  "geometry": {"coordinates":[-96.77324400000001,33.123713],"type":"Point"}
}