{
  "type": "Feature",
  "properties": {
    "iso:country":"US",
    "sg:address":"9131 Westbend Rd",
    "sg:city":"Orange",
    "sg:classifiers":[
        {
            "category":"Shopping",
            "subcategory":"Hobbies, Toys, & Games",
            "type":"Retail Goods"
        }
    ],
    "sg:phone":"+1 409 745 4241",
    "sg:postcode":"77632",
    "sg:province":"TX",
    "wof:name":"Peckerwood Sales",
    "wof:placetype":"venue"
},
  "geometry": {"coordinates":[-93.89893600000001,30.224898],"type":"Point"}
}