{
  "type": "Feature",
  "properties": {
    "iso:country":"US",
    "sg:address":"1602 E Frankford Rd Ofc",
    "sg:city":"Carrollton",
    "sg:classifiers":[
        {
            "category":"Real Estate",
            "subcategory":"Real Estate Operator",
            "type":"Services"
        }
    ],
    "sg:phone":"+1 972 245 2450",
    "sg:postcode":"75007",
    "sg:province":"TX",
    "sg:tags":[
        "apartment"
    ],
    "wof:name":"Tallows the",
    "wof:placetype":"venue"
},
  "geometry": {"coordinates":[-96.902901,32.998798],"type":"Point"}
}