{
  "type": "Feature",
  "properties": {
    "iso:country":"US",
    "sg:address":"5647 Castle Prince Dr",
    "sg:city":"San Antonio",
    "sg:classifiers":[
        {
            "category":"Building & Trades",
            "subcategory":"Construction",
            "type":"Services"
        }
    ],
    "sg:phone":"+1 210 590 1835",
    "sg:postcode":"78218",
    "sg:province":"TX",
    "sg:tags":[
        "house"
    ],
    "wof:name":"Modern Services",
    "wof:placetype":"venue"
},
  "geometry": {"coordinates":[-98.37692199999999,29.488873],"type":"Point"}
}