{
  "type": "Feature",
  "properties": {
    "iso:country":"US",
    "sg:address":"406 Hazel Ave",
    "sg:city":"Rockdale",
    "sg:classifiers":[
        {
            "category":"Manufacturing",
            "subcategory":"Motor Vehicles & Parts",
            "type":"Manufacturing & Wholesale Goods"
        }
    ],
    "sg:phone":"+1 512 446 2802",
    "sg:postcode":"76567",
    "sg:province":"TX",
    "sg:tags":[
        "trucking"
    ],
    "wof:name":"E & M Trucking",
    "wof:placetype":"venue"
},
  "geometry": {"coordinates":[-97.00762899999999,30.660231],"type":"Point"}
}