{
  "type": "Feature",
  "properties": {
    "iso:country":"US",
    "sg:address":"542 State Hwy 64",
    "sg:city":"Canton",
    "sg:classifiers":[
        {
            "category":"Shopping",
            "subcategory":"Used Merchandise",
            "type":"Retail Goods"
        }
    ],
    "sg:phone":"+1 903 567 0575",
    "sg:postcode":"75103",
    "sg:province":"TX",
    "wof:name":"Backroad Treasures",
    "wof:placetype":"venue"
},
  "geometry": {"coordinates":[-95.867042,32.557704],"type":"Point"}
}