{
  "type": "Feature",
  "properties": {
    "iso:country":"US",
    "sg:address":"2203 E Riviera Dr",
    "sg:city":"Cedar Park",
    "sg:classifiers":[
        {
            "category":"Professional",
            "subcategory":"Computer Services",
            "type":"Services"
        }
    ],
    "sg:phone":"+1 512 219 7060",
    "sg:postcode":"78613",
    "sg:province":"TX",
    "sg:tags":[
        "related"
    ],
    "wof:name":"Online Enterprises",
    "wof:placetype":"venue"
},
  "geometry": {"coordinates":[-97.81402300000001,30.481566],"type":"Point"}
}