{
  "type": "Feature",
  "properties": {
    "iso:country":"US",
    "sg:address":"2320 Hickory Dr",
    "sg:city":"Little Elm",
    "sg:classifiers":[
        {
            "category":"Professional",
            "subcategory":"Secretarial Services",
            "type":"Services"
        }
    ],
    "sg:phone":"+1 469 235 0359",
    "sg:postcode":"75068",
    "sg:province":"TX",
    "sg:tags":[
        "reporting"
    ],
    "wof:name":"Wornson Shareen",
    "wof:placetype":"venue"
},
  "geometry": {"coordinates":[-96.904753,33.172487],"type":"Point"}
}