{
  "type": "Feature",
  "properties": {
    "iso:country":"US",
    "sg:address":"2521 Broadway St",
    "sg:city":"Galveston",
    "sg:classifiers":[
        {
            "category":"Restaurant",
            "type":"Food & Drink"
        }
    ],
    "sg:menulink":"http://www.allmenus.com/tx/galveston/130643-subway/menu/",
    "sg:phone":"+1 409 762 8280",
    "sg:postcode":"77550",
    "sg:province":"TX",
    "sg:tags":[
        "american",
        "sandwich"
    ],
    "wof:name":"Subway",
    "wof:placetype":"venue"
},
  "geometry": {"coordinates":[-94.79512200000001,29.299169],"type":"Point"}
}