{
  "type": "Feature",
  "properties": {
    "iso:country":"US",
    "sg:address":"400 Inglewood Dr",
    "sg:city":"Socorro",
    "sg:classifiers":[
        {
            "category":"Shopping",
            "type":"Retail Goods"
        }
    ],
    "sg:phone":"+1 915 860 4505",
    "sg:postcode":"79927",
    "sg:province":"TX",
    "sg:tags":[
        "pet",
        "food",
        "supply"
    ],
    "wof:name":"United Valley Pet Food",
    "wof:placetype":"venue"
},
  "geometry": {"coordinates":[-106.297882,31.676669],"type":"Point"}
}