{
  "type": "Feature",
  "properties": {
    "iso:country":"US",
    "sg:address":"201 W Cleveland St Ste C",
    "sg:city":"Beeville",
    "sg:classifiers":[
        {
            "category":"Social Services",
            "type":"Services"
        }
    ],
    "sg:phone":"+1 361 362 0462",
    "sg:postcode":"78102",
    "sg:province":"TX",
    "wof:name":"Family Hlth Care Support Svcs",
    "wof:placetype":"venue"
},
  "geometry": {"coordinates":[-97.750778,28.40452],"type":"Point"}
}