{
  "type": "Feature",
  "properties": {
    "iso:country":"US",
    "sg:address":"314 N Main St",
    "sg:city":"Jasper",
    "sg:classifiers":[
        {
            "category":"Organizations",
            "subcategory":"Religious Organization",
            "type":"Services"
        }
    ],
    "sg:phone":"+1 409 384 2527",
    "sg:postcode":"75951",
    "sg:province":"TX",
    "sg:tags":[
        "churches-baptist"
    ],
    "wof:name":"Thee House Fbc",
    "wof:placetype":"venue"
},
  "geometry": {"coordinates":[-94.000618,30.923101],"type":"Point"}
}