{
  "type": "Feature",
  "properties": {
    "iso:country":"US",
    "sg:address":"8641 Old Bee Caves Rd",
    "sg:city":"Austin",
    "sg:classifiers":[
        {
            "category":"Autos & Motor Vehicles",
            "subcategory":"Auto Supplies",
            "type":"Retail Goods"
        }
    ],
    "sg:phone":"+1 512 821 9943",
    "sg:postcode":"78735",
    "sg:province":"TX",
    "sg:tags":[
        "trailer",
        "hitch"
    ],
    "wof:name":"B & H Custom Hitches Inc",
    "wof:placetype":"venue"
},
  "geometry": {"coordinates":[-97.89191,30.256323],"type":"Point"}
}