{
  "type": "Feature",
  "properties": {
    "iso:country":"US",
    "sg:address":"108 April Point Dr S",
    "sg:city":"Montgomery",
    "sg:classifiers":[
        {
            "category":"Health Services",
            "subcategory":"Optometrist",
            "type":"Services"
        }
    ],
    "sg:phone":"+1 936 539 3965",
    "sg:postcode":"77356",
    "sg:province":"TX",
    "wof:name":"Larsen Eye Care",
    "wof:placetype":"venue"
},
  "geometry": {"coordinates":[-95.60881500000001,30.375366],"type":"Point"}
}