{
  "type": "Feature",
  "properties": {
    "iso:country":"US",
    "sg:address":"1546 S Buffalo St",
    "sg:city":"Canton",
    "sg:classifiers":[
        {
            "category":"Personal",
            "type":"Services"
        }
    ],
    "sg:phone":"+1 903 567 7010",
    "sg:postcode":"75103",
    "sg:province":"TX",
    "wof:name":"Keep In Touch Massage Therapy",
    "wof:placetype":"venue"
},
  "geometry": {"coordinates":[-95.875353,32.540017],"type":"Point"}
}