{
  "type": "Feature",
  "properties": {
    "iso:country":"US",
    "sg:address":"2111 N Collins St",
    "sg:city":"Arlington",
    "sg:classifiers":[
        {
            "category":"Education",
            "subcategory":"Dance Studio",
            "type":"Public Place"
        }
    ],
    "sg:phone":"+1 817 274 7431",
    "sg:postcode":"76011",
    "sg:province":"TX",
    "sg:tags":[
        "instruction",
        "dancing"
    ],
    "wof:name":"Dance Invasion",
    "wof:placetype":"venue"
},
  "geometry": {"coordinates":[-97.09694,32.768945],"type":"Point"}
}