{
  "type": "Feature",
  "properties": {
    "iso:country":"US",
    "sg:address":"5507 Mountain Forest Dr",
    "sg:city":"Katy",
    "sg:classifiers":[
        {
            "category":"Building & Trades",
            "subcategory":"Construction",
            "type":"Services"
        }
    ],
    "sg:phone":"+1 281 345 2221",
    "sg:postcode":"77449",
    "sg:province":"TX",
    "sg:tags":[
        "house"
    ],
    "wof:name":"Westfield Sales Office",
    "wof:placetype":"venue"
},
  "geometry": {"coordinates":[-95.71966399999999,29.848713],"type":"Point"}
}