{
  "type": "Feature",
  "properties": {
    "iso:country":"US",
    "sg:address":"433 Co Rd 1056",
    "sg:city":"Pearsall",
    "sg:classifiers":[
        {
            "category":"Organizations",
            "subcategory":"Community Association",
            "type":"Services"
        }
    ],
    "sg:phone":"+1 830 334 4202",
    "sg:postcode":"78061",
    "sg:province":"TX",
    "sg:tags":[
        "club"
    ],
    "wof:name":"Pearsall Lions Club",
    "wof:placetype":"venue"
},
  "geometry": {"coordinates":[-99.09323500000001,28.918093],"type":"Point"}
}