{
  "type": "Feature",
  "properties": {
    "iso:country":"US",
    "sg:address":"300 W 6th St",
    "sg:city":"Borger",
    "sg:classifiers":[
        {
            "category":"Building & Trades",
            "subcategory":"Construction",
            "type":"Services"
        }
    ],
    "sg:phone":"+1 806 677 1708",
    "sg:postcode":"79007",
    "sg:province":"TX",
    "sg:tags":[
        "home",
        "builder"
    ],
    "wof:name":"Hutchcares Living At Home",
    "wof:placetype":"venue"
},
  "geometry": {"coordinates":[-101.39205699999999,35.671706],"type":"Point"}
}