{
  "type": "Feature",
  "properties": {
    "iso:country":"US",
    "sg:address":"2330 Hardwick St",
    "sg:city":"Dallas",
    "sg:classifiers":[
        {
            "category":"Freight",
            "type":"Transportation"
        }
    ],
    "sg:phone":"+1 214 741 9232",
    "sg:postcode":"75208",
    "sg:province":"TX",
    "sg:tags":[
        "operator",
        "local",
        "trucking"
    ],
    "wof:name":"A Garza Trucking",
    "wof:placetype":"venue"
},
  "geometry": {"coordinates":[-96.826564,32.772575],"type":"Point"}
}