{
  "type": "Feature",
  "properties": {
    "iso:country":"US",
    "sg:address":"2716 E 5th St",
    "sg:city":"Austin",
    "sg:classifiers":[
        {
            "category":"Utilities",
            "subcategory":"Telephone",
            "type":"Services"
        }
    ],
    "sg:phone":"+1 512 476 6777",
    "sg:postcode":"78702",
    "sg:province":"TX",
    "sg:tags":[
        "telecommunication"
    ],
    "sg:website":"www.mastec.com",
    "wof:name":"Mas Tec",
    "wof:placetype":"venue"
},
  "geometry": {"coordinates":[-97.713735,30.25754],"type":"Point"}
}