{
  "type": "Feature",
  "properties": {
    "iso:country":"US",
    "sg:address":"1931 Crepe Myrtle Dr",
    "sg:city":"Lancaster",
    "sg:classifiers":[
        {
            "category":"Personal",
            "subcategory":"Beauty Salon",
            "type":"Services"
        }
    ],
    "sg:phone":"+1 972 218 5199",
    "sg:postcode":"75146",
    "sg:province":"TX",
    "sg:tags":[
        "shop"
    ],
    "wof:name":"Headlines & Co",
    "wof:placetype":"venue"
},
  "geometry": {"coordinates":[-96.79296600000001,32.592873],"type":"Point"}
}