{
  "type": "Feature",
  "properties": {
    "iso:country":"US",
    "sg:address":"12711 East Fwy",
    "sg:city":"Houston",
    "sg:classifiers":[
        {
            "category":"Wholesale",
            "subcategory":"Durable Goods & Equipment",
            "type":"Manufacturing & Wholesale Goods"
        }
    ],
    "sg:phone":"+1 713 455 0296",
    "sg:postcode":"77015",
    "sg:province":"TX",
    "sg:tags":[
        "fire",
        "extinguisher"
    ],
    "sg:website":"www.a-1fire.com",
    "wof:name":"A 1 Fire Equipment Co Inc",
    "wof:placetype":"venue"
},
  "geometry": {"coordinates":[-95.209703,29.771321],"type":"Point"}
}