{
  "type": "Feature",
  "properties": {
    "iso:country":"US",
    "sg:address":"6150 Eldorado Pkwy",
    "sg:city":"Mc Kinney",
    "sg:classifiers":[
        {
            "category":"Professional",
            "subcategory":"Management & Consulting",
            "type":"Services"
        }
    ],
    "sg:phone":"+1 972 562 5444",
    "sg:postcode":"75070",
    "sg:province":"TX",
    "wof:name":"Lonestar Commisions",
    "wof:placetype":"venue"
},
  "geometry": {"coordinates":[-96.699658,33.174169],"type":"Point"}
}