{
  "type": "Feature",
  "properties": {
    "iso:country":"US",
    "sg:address":"904 Creekbend Dr",
    "sg:city":"Keller",
    "sg:classifiers":[
        {
            "category":"Professional",
            "type":"Services"
        }
    ],
    "sg:phone":"+1 817 581 9059",
    "sg:postcode":"76248",
    "sg:province":"TX",
    "wof:name":"David G Gonzales",
    "wof:placetype":"venue"
},
  "geometry": {"coordinates":[-97.230118,32.896814],"type":"Point"}
}