{
  "type": "Feature",
  "properties": {
    "iso:country":"US",
    "sg:address":"4515 Steffani Ln",
    "sg:city":"Houston",
    "sg:classifiers":[
        {
            "category":"Building & Trades",
            "subcategory":"Construction",
            "type":"Services"
        }
    ],
    "sg:phone":"+1 713 466 6737",
    "sg:postcode":"77041",
    "sg:province":"TX",
    "sg:tags":[
        "siding",
        "contractor"
    ],
    "wof:name":"Casco",
    "wof:placetype":"venue"
},
  "geometry": {"coordinates":[-95.546256,29.838058],"type":"Point"}
}