{
  "type": "Feature",
  "properties": {
    "iso:country":"US",
    "sg:address":"1505 Haddon St",
    "sg:city":"Houston",
    "sg:classifiers":[
        {
            "category":"Building & Trades",
            "subcategory":"Construction",
            "type":"Services"
        }
    ],
    "sg:phone":"+1 713 528 4196",
    "sg:postcode":"77006",
    "sg:province":"TX",
    "sg:tags":[
        "contractor"
    ],
    "sg:website":"www.tynessparks.com",
    "wof:name":"Tynes Sparks Building Corp",
    "wof:placetype":"venue"
},
  "geometry": {"coordinates":[-95.398903,29.751699],"type":"Point"}
}