{
  "type": "Feature",
  "properties": {
    "iso:country":"US",
    "sg:address":"1621 E Hwy 82",
    "sg:city":"Gainesville",
    "sg:classifiers":[
        {
            "category":"Organizations",
            "subcategory":"Religious Organization",
            "type":"Services"
        }
    ],
    "sg:phone":"+1 940 665 4748",
    "sg:postcode":"76240",
    "sg:province":"TX",
    "sg:tags":[
        "church"
    ],
    "wof:name":"Way The Truth ABD The Life",
    "wof:placetype":"venue"
},
  "geometry": {"coordinates":[-97.12785599999999,33.642279],"type":"Point"}
}