{
  "type": "Feature",
  "properties": {
    "iso:country":"US",
    "sg:address":"15820 Jersey Dr",
    "sg:city":"Houston",
    "sg:classifiers":[
        {
            "category":"Retail",
            "subcategory":"Auto Repair",
            "type":"Services"
        }
    ],
    "sg:phone":"+1 713 896 6288",
    "sg:postcode":"77040",
    "sg:province":"TX",
    "sg:tags":[
        "exhaust"
    ],
    "wof:name":"Meineke Discount Mufflers",
    "wof:placetype":"venue"
},
  "geometry": {"coordinates":[-95.560303,29.888396],"type":"Point"}
}