{
  "type": "Feature",
  "properties": {
    "iso:country":"US",
    "sg:address":"3922 Westheimer Rd",
    "sg:city":"Houston",
    "sg:classifiers":[
        {
            "category":"Personal",
            "type":"Services"
        }
    ],
    "sg:phone":"+1 713 871 9727",
    "sg:postcode":"77027",
    "sg:province":"TX",
    "sg:tags":[
        "wrapping",
        "gift"
    ],
    "wof:name":"Clowning Touch",
    "wof:placetype":"venue"
},
  "geometry": {"coordinates":[-95.44355299999999,29.741792],"type":"Point"}
}