{
  "type": "Feature",
  "properties": {
    "iso:country":"US",
    "sg:address":"2015 W Commerce St",
    "sg:city":"San Antonio",
    "sg:classifiers":[
        {
            "category":"Insurance",
            "subcategory":"Insurance Agent",
            "type":"Services"
        }
    ],
    "sg:phone":"+1 210 223 4139",
    "sg:postcode":"78207",
    "sg:province":"TX",
    "wof:name":"Aguilar Insurance Agency",
    "wof:placetype":"venue"
},
  "geometry": {"coordinates":[-98.517678,29.427367],"type":"Point"}
}