{
  "type": "Feature",
  "properties": {
    "iso:country":"US",
    "sg:address":"19465 McDonald St",
    "sg:city":"Lytle",
    "sg:classifiers":[
        {
            "category":"Restaurant",
            "type":"Food & Drink"
        }
    ],
    "sg:phone":"+1 830 772 3321",
    "sg:postcode":"78052",
    "sg:province":"TX",
    "sg:tags":[
        "parlor",
        "ice",
        "cream"
    ],
    "wof:name":"Dairy Queen",
    "wof:placetype":"venue"
},
  "geometry": {"coordinates":[-98.791529,29.235052],"type":"Point"}
}