{
  "type": "Feature",
  "properties": {
    "iso:country":"US",
    "sg:address":"1601 East St",
    "sg:city":"Texarkana",
    "sg:classifiers":[
        {
            "category":"Retail",
            "subcategory":"Auto Repair",
            "type":"Services"
        }
    ],
    "sg:phone":"+1 870 772 0742",
    "sg:postcode":"71854",
    "sg:province":"TX",
    "sg:tags":[
        "repairing",
        "automobile"
    ],
    "wof:name":"Ward's Four Wheel Drive",
    "wof:placetype":"venue"
},
  "geometry": {"coordinates":[-94.030345,33.405733],"type":"Point"}
}