{
  "type": "Feature",
  "properties": {
    "iso:country":"US",
    "sg:address":"11757 Katy Fwy Ste 1400",
    "sg:city":"Houston",
    "sg:classifiers":[
        {
            "category":"Manufacturing",
            "subcategory":"Petroleum Products",
            "type":"Manufacturing & Wholesale Goods"
        }
    ],
    "sg:phone":"+1 281 596 1644",
    "sg:postcode":"77079",
    "sg:province":"TX",
    "wof:name":"Sunoco Partners Butane Blending",
    "wof:placetype":"venue"
},
  "geometry": {"coordinates":[-95.59273899999999,29.784201],"type":"Point"}
}