{
  "type": "Feature",
  "properties": {
    "iso:country":"US",
    "sg:address":"13776 N Highway 183",
    "sg:city":"Austin",
    "sg:classifiers":[
        {
            "category":"Personal",
            "subcategory":"Nail Salon",
            "type":"Services"
        }
    ],
    "sg:phone":"+1 512 401 6193",
    "sg:postcode":"78750",
    "sg:province":"TX",
    "wof:name":"Sunny Nail & Spa",
    "wof:placetype":"venue"
},
  "geometry": {"coordinates":[-97.79472699999999,30.461501],"type":"Point"}
}