{
  "type": "Feature",
  "properties": {
    "iso:country":"US",
    "sg:address":"1506 Fairfield Dr",
    "sg:city":"Austin",
    "sg:classifiers":[
        {
            "category":"Shopping",
            "subcategory":"Books",
            "type":"Retail Goods"
        }
    ],
    "sg:phone":"+1 512 450 1597",
    "sg:postcode":"78757",
    "sg:province":"TX",
    "wof:name":"Space Age Comics",
    "wof:placetype":"venue"
},
  "geometry": {"coordinates":[-97.719162,30.361241],"type":"Point"}
}