{
  "type": "Feature",
  "properties": {
    "iso:country":"US",
    "sg:address":"6322 Costa Mesa Dr",
    "sg:city":"Houston",
    "sg:classifiers":[
        {
            "category":"Building & Trades",
            "subcategory":"Cleaning & Sanitation",
            "type":"Services"
        }
    ],
    "sg:phone":"+1 281 438 8359",
    "sg:postcode":"77053",
    "sg:province":"TX",
    "sg:tags":[
        "maintenance"
    ],
    "wof:name":"Phoenix Rizing",
    "wof:placetype":"venue"
},
  "geometry": {"coordinates":[-95.48084299999999,29.58969],"type":"Point"}
}