{
  "type": "Feature",
  "properties": {
    "iso:country":"US",
    "sg:address":"3140 FM 1960 W",
    "sg:city":"Houston",
    "sg:classifiers":[
        {
            "category":"Shopping",
            "subcategory":"Pharmacy",
            "type":"Retail Goods"
        }
    ],
    "sg:phone":"+1 281 880 1092",
    "sg:postcode":"77068",
    "sg:province":"TX",
    "wof:name":"CVS Pharmacy",
    "wof:placetype":"venue"
},
  "geometry": {"coordinates":[-95.47359,30.001812],"type":"Point"}
}