{
  "type": "Feature",
  "properties": {
    "iso:country":"US",
    "sg:address":"4800 Seawall Blvd",
    "sg:city":"Galveston",
    "sg:classifiers":[
        {
            "category":"Real Estate",
            "subcategory":"Real Estate Operator",
            "type":"Services"
        }
    ],
    "sg:phone":"+1 409 762 4800",
    "sg:postcode":"77551",
    "sg:province":"TX",
    "sg:tags":[
        "apartment"
    ],
    "wof:name":"Fort Crockett Apartments",
    "wof:placetype":"venue"
},
  "geometry": {"coordinates":[-94.81537899999999,29.272879],"type":"Point"}
}