{
  "type": "Feature",
  "properties": {
    "iso:country":"US",
    "sg:address":"1871 N Plano Rd",
    "sg:city":"Richardson",
    "sg:classifiers":[
        {
            "category":"Personal",
            "subcategory":"Nail Salon",
            "type":"Services"
        }
    ],
    "sg:phone":"+1 972 231 0205",
    "sg:postcode":"75081",
    "sg:province":"TX",
    "wof:name":"Alice's Nails",
    "wof:placetype":"venue"
},
  "geometry": {"coordinates":[-96.69994800000001,32.973971],"type":"Point"}
}