{
  "type": "Feature",
  "properties": {
    "iso:country":"US",
    "sg:address":"106 E Ovilla Rd",
    "sg:city":"Red Oak",
    "sg:classifiers":[
        {
            "category":"Health Services",
            "subcategory":"Doctor",
            "type":"Services"
        }
    ],
    "sg:phone":"+1 972 617 6660",
    "sg:postcode":"75154",
    "sg:province":"TX",
    "wof:name":"Typhair Sara MD",
    "wof:placetype":"venue"
},
  "geometry": {"coordinates":[-96.855904,32.531898],"type":"Point"}
}