{
  "type": "Feature",
  "properties": {
    "iso:country":"US",
    "sg:address":"1606 S Cooper St",
    "sg:city":"Arlington",
    "sg:classifiers":[
        {
            "category":"Food & Beverages",
            "subcategory":"Fruits & Vegetables",
            "type":"Retail Goods"
        }
    ],
    "sg:phone":"+1 817 276 8810",
    "sg:postcode":"76013",
    "sg:province":"TX",
    "wof:name":"Cooper Street Farmers Market",
    "wof:placetype":"venue"
},
  "geometry": {"coordinates":[-97.114744,32.716998],"type":"Point"}
}