{
  "type": "Feature",
  "properties": {
    "iso:country":"US",
    "sg:address":"2916 Jeanetta St",
    "sg:city":"Houston",
    "sg:classifiers":[
        {
            "category":"Restaurant",
            "type":"Food & Drink"
        }
    ],
    "sg:phone":"+1 713 266 6860",
    "sg:postcode":"77063",
    "sg:province":"TX",
    "sg:tags":[
        "barbeque"
    ],
    "sg:website":"www.blakesbarbq.com",
    "wof:name":"Blake's Barbecue and Burgers",
    "wof:placetype":"venue"
},
  "geometry": {"coordinates":[-95.52542200000001,29.733785],"type":"Point"}
}