{
  "type": "Feature",
  "properties": {
    "iso:country":"US",
    "sg:address":"3040 Post Oak Blvd",
    "sg:city":"Houston",
    "sg:classifiers":[
        {
            "category":"Insurance",
            "subcategory":"Life Insurance",
            "type":"Services"
        }
    ],
    "sg:phone":"+1 713 626 1930",
    "sg:postcode":"77056",
    "sg:province":"TX",
    "sg:tags":[
        "group",
        "health"
    ],
    "wof:name":"Massachusetts Mutl Lf Insur Co",
    "wof:placetype":"venue"
},
  "geometry": {"coordinates":[-95.46064,29.733805],"type":"Point"}
}