{
  "type": "Feature",
  "properties": {
    "iso:country":"US",
    "sg:address":"6020 W 33rd Ave",
    "sg:city":"Amarillo",
    "sg:classifiers":[
        {
            "category":"Personal",
            "subcategory":"Beauty Salon",
            "type":"Services"
        }
    ],
    "sg:phone":"+1 806 359 4771",
    "sg:postcode":"79106",
    "sg:province":"TX",
    "sg:tags":[
        "shop"
    ],
    "wof:name":"Kutting Krew",
    "wof:placetype":"venue"
},
  "geometry": {"coordinates":[-101.90415299999999,35.178416],"type":"Point"}
}