{
  "type": "Feature",
  "properties": {
    "iso:country":"US",
    "sg:address":"2614 Briargrove Ln",
    "sg:city":"San Angelo",
    "sg:classifiers":[
        {
            "category":"Farming",
            "subcategory":"Livestock Farm",
            "type":"Manufacturing & Wholesale Goods"
        }
    ],
    "sg:phone":"+1 325 949 9881",
    "sg:postcode":"76904",
    "sg:province":"TX",
    "sg:tags":[
        "beef",
        "feedlot",
        "cattle"
    ],
    "wof:name":"Jerry Stanford",
    "wof:placetype":"venue"
},
  "geometry": {"coordinates":[-100.479097,31.41233],"type":"Point"}
}