{
  "type": "Feature",
  "properties": {
    "iso:country":"US",
    "sg:address":"1901 N Ed Carey Dr",
    "sg:city":"Harlingen",
    "sg:classifiers":[
        {
            "category":"Health Services",
            "subcategory":"Doctor",
            "type":"Services"
        }
    ],
    "sg:phone":"+1 956 440 2800",
    "sg:postcode":"78550",
    "sg:province":"TX",
    "sg:tags":[
        "medical"
    ],
    "wof:name":"Lozano Diana H MD & John",
    "wof:placetype":"venue"
},
  "geometry": {"coordinates":[-97.710641,26.225529],"type":"Point"}
}