{
  "type": "Feature",
  "properties": {
    "iso:country":"US",
    "sg:address":"1706 Greenville Ave",
    "sg:city":"Dallas",
    "sg:classifiers":[
        {
            "category":"Building & Trades",
            "subcategory":"Locksmith",
            "type":"Services"
        }
    ],
    "sg:phone":"+1 214 824 5880",
    "sg:postcode":"75206",
    "sg:province":"TX",
    "sg:tags":[
        "key"
    ],
    "wof:name":"Key Service",
    "wof:placetype":"venue"
},
  "geometry": {"coordinates":[-96.77010300000001,32.811199],"type":"Point"}
}