{
  "type": "Feature",
  "properties": {
    "iso:country":"US",
    "sg:address":"4126 S Fitzhugh Ave",
    "sg:city":"Dallas",
    "sg:classifiers":[
        {
            "category":"Retail",
            "subcategory":"Auto Repair",
            "type":"Services"
        }
    ],
    "sg:phone":"+1 214 428 8801",
    "sg:postcode":"75210",
    "sg:province":"TX",
    "sg:tags":[
        "repairing",
        "automobile",
        "general"
    ],
    "wof:name":"Jackson Motor Company-Garage",
    "wof:placetype":"venue"
},
  "geometry": {"coordinates":[-96.752174,32.776319],"type":"Point"}
}