{
  "type": "Feature",
  "properties": {
    "iso:country":"US",
    "sg:address":"1100 Hidden Ridge",
    "sg:city":"Irving",
    "sg:classifiers":[
        {
            "category":"Real Estate",
            "subcategory":"Real Estate Operator",
            "type":"Services"
        }
    ],
    "sg:phone":"+1 972 714 3755",
    "sg:postcode":"75038",
    "sg:province":"TX",
    "sg:tags":[
        "building",
        "apartment"
    ],
    "wof:name":"Murphy Paggy",
    "wof:placetype":"venue"
},
  "geometry": {"coordinates":[-96.96317999999999,32.877034],"type":"Point"}
}