{
  "type": "Feature",
  "properties": {
    "iso:country":"US",
    "sg:address":"1800 1st St",
    "sg:city":"Palacios",
    "sg:classifiers":[
        {
            "category":"Place Of Worship",
            "subcategory":"Church",
            "type":"Public Place"
        },
        {
            "category":"Place Of Worship",
            "type":"Public Place"
        }
    ],
    "sg:phone":"+1 361 972 3675",
    "sg:postcode":"77465",
    "sg:province":"TX",
    "sg:tags":[
        "churches-interdenominational",
        "churches-various",
        "denomination"
    ],
    "wof:name":"Solid Rock Fellowship",
    "wof:placetype":"venue"
},
  "geometry": {"coordinates":[-96.210426,28.709042],"type":"Point"}
}