{
  "type": "Feature",
  "properties": {
    "iso:country":"US",
    "sg:address":"24183 Natural Bridge Caverns Rd",
    "sg:city":"San Antonio",
    "sg:classifiers":[
        {
            "category":"Shopping",
            "subcategory":"Gifts & Souvenirs",
            "type":"Retail Goods"
        }
    ],
    "sg:phone":"+1 210 651 9355",
    "sg:postcode":"78266",
    "sg:province":"TX",
    "wof:name":"Nells Unique Creations",
    "wof:placetype":"venue"
},
  "geometry": {"coordinates":[-98.314143,29.664216],"type":"Point"}
}