{
  "type": "Feature",
  "properties": {
    "iso:country":"US",
    "sg:address":"811 E Scott Ave",
    "sg:city":"Wichita Falls",
    "sg:classifiers":[
        {
            "category":"Professional",
            "type":"Services"
        }
    ],
    "sg:phone":"+1 940 723 5585",
    "sg:postcode":"76301",
    "sg:province":"TX",
    "sg:tags":[
        "consultant",
        "geological"
    ],
    "sg:website":"www.gunnoil.com",
    "wof:name":"Gunn Oil Co",
    "wof:placetype":"venue"
},
  "geometry": {"coordinates":[-98.476839,33.899418],"type":"Point"}
}