{
  "type": "Feature",
  "properties": {
    "iso:country":"US",
    "sg:address":"1023 E Marshall Ave",
    "sg:city":"Longview",
    "sg:classifiers":[
        {
            "category":"Organizations",
            "subcategory":"Community Association",
            "type":"Services"
        }
    ],
    "sg:phone":"+1 903 753 7461",
    "sg:postcode":"75601",
    "sg:province":"TX",
    "wof:name":"Foe 4125",
    "wof:placetype":"venue"
},
  "geometry": {"coordinates":[-94.72538400000001,32.503059],"type":"Point"}
}