{
  "type": "Feature",
  "properties": {
    "iso:country":"US",
    "sg:address":"12417 Micah Dr",
    "sg:city":"Waco",
    "sg:classifiers":[
        {
            "category":"Shopping",
            "subcategory":"Bicycles & Sporting Goods",
            "type":"Retail Goods"
        }
    ],
    "sg:phone":"+1 254 836 1112",
    "sg:postcode":"76708",
    "sg:province":"TX",
    "wof:name":"Cen Tex Gun Shop",
    "wof:placetype":"venue"
},
  "geometry": {"coordinates":[-97.280766,31.636508],"type":"Point"}
}