{
  "type": "Feature",
  "properties": {
    "iso:country":"US",
    "sg:address":"4624 State Hwy 31",
    "sg:city":"Tyler",
    "sg:classifiers":[
        {
            "category":"Manufacturing",
            "subcategory":"Buildings",
            "type":"Manufacturing & Wholesale Goods"
        }
    ],
    "sg:phone":"+1 903 593 6300",
    "sg:postcode":"75709",
    "sg:province":"TX",
    "sg:tags":[
        "prefab"
    ],
    "wof:name":"Patriot Homes West",
    "wof:placetype":"venue"
},
  "geometry": {"coordinates":[-95.359233,32.34306],"type":"Point"}
}