{
  "type": "Feature",
  "properties": {
    "iso:country":"US",
    "sg:address":"2303 Colorado Blvd",
    "sg:city":"Denton",
    "sg:classifiers":[
        {
            "category":"Home & Garden",
            "subcategory":"Carpets & Floor Coverings",
            "type":"Retail Goods"
        }
    ],
    "sg:phone":"+1 940 382 4340",
    "sg:postcode":"76205",
    "sg:province":"TX",
    "sg:tags":[
        "dealer",
        "rug"
    ],
    "wof:name":"Carpets Plus Inc",
    "wof:placetype":"venue"
},
  "geometry": {"coordinates":[-97.10617499999999,33.193831],"type":"Point"}
}