{
  "type": "Feature",
  "properties": {
    "iso:country":"US",
    "sg:address":"2209 N Dunlap Ave",
    "sg:city":"Mission",
    "sg:classifiers":[
        {
            "category":"Building & Trades",
            "subcategory":"Construction",
            "type":"Services"
        }
    ],
    "sg:phone":"+1 956 581 4745",
    "sg:postcode":"78572",
    "sg:province":"TX",
    "sg:tags":[
        "contractor"
    ],
    "wof:name":"R Salinas Construction",
    "wof:placetype":"venue"
},
  "geometry": {"coordinates":[-98.324977,26.228196],"type":"Point"}
}