{
  "type": "Feature",
  "properties": {
    "iso:country":"US",
    "sg:address":"10219 Holly Springs Dr",
    "sg:city":"Houston",
    "sg:classifiers":[
        {
            "category":"Shopping",
            "subcategory":"Pets & Pet Supplies",
            "type":"Retail Goods"
        }
    ],
    "sg:phone":"+1 713 952 5444",
    "sg:postcode":"77042",
    "sg:province":"TX",
    "sg:tags":[
        "product",
        "health",
        "animal"
    ],
    "wof:name":"Vetmart",
    "wof:placetype":"venue"
},
  "geometry": {"coordinates":[-95.55266399999999,29.754175],"type":"Point"}
}