{
  "type": "Feature",
  "properties": {
    "iso:country":"US",
    "sg:address":"500 N Lavaca Dr",
    "sg:city":"Moulton",
    "sg:classifiers":[
        {
            "category":"Organizations",
            "subcategory":"Community Association",
            "type":"Services"
        }
    ],
    "sg:phone":"+1 361 596 4811",
    "sg:postcode":"77975",
    "sg:province":"TX",
    "sg:tags":[
        "military"
    ],
    "wof:name":"American Legion",
    "wof:placetype":"venue"
},
  "geometry": {"coordinates":[-97.14367,29.579787],"type":"Point"}
}