{
  "type": "Feature",
  "properties": {
    "iso:country":"US",
    "sg:address":"1902 E Denman Ave",
    "sg:city":"Lufkin",
    "sg:classifiers":[
        {
            "category":"Restaurant",
            "type":"Food & Drink"
        }
    ],
    "sg:menulink":"http://www.allmenus.com/tx/lufkin/177639-jack-in-the-box/menu/",
    "sg:phone":"+1 936 634 2011",
    "sg:postcode":"75901",
    "sg:province":"TX",
    "sg:tags":[
        "burger",
        "american"
    ],
    "wof:name":"Jack in the Box",
    "wof:placetype":"venue"
},
  "geometry": {"coordinates":[-94.698329,31.318237],"type":"Point"}
}