{
  "type": "Feature",
  "properties": {
    "iso:country":"US",
    "sg:address":"3006 Creeks Edge Pkwy",
    "sg:city":"Austin",
    "sg:classifiers":[
        {
            "category":"Professional",
            "subcategory":"Advertising",
            "type":"Services"
        }
    ],
    "sg:phone":"+1 512 402 9937",
    "sg:postcode":"78733",
    "sg:province":"TX",
    "wof:name":"Media River Systems LLC",
    "wof:placetype":"venue"
},
  "geometry": {"coordinates":[-97.883702,30.291325],"type":"Point"}
}