{
  "type": "Feature",
  "properties": {
    "iso:country":"US",
    "sg:address":"100 W 3rd St",
    "sg:city":"Georgetown",
    "sg:classifiers":[
        {
            "category":"Health Services",
            "subcategory":"Doctor",
            "type":"Services"
        }
    ],
    "sg:phone":"+1 512 930 3280",
    "sg:postcode":"78626",
    "sg:province":"TX",
    "sg:tags":[
        "clinic"
    ],
    "wof:name":"Family Planning",
    "wof:placetype":"venue"
},
  "geometry": {"coordinates":[-97.678134,30.640787],"type":"Point"}
}