{
  "type": "Feature",
  "properties": {
    "iso:country":"US",
    "sg:address":"3330 Ella Blvd",
    "sg:city":"Houston",
    "sg:classifiers":[
        {
            "category":"Restaurant",
            "type":"Food & Drink"
        }
    ],
    "sg:phone":"+1 713 686 9920",
    "sg:postcode":"77018",
    "sg:province":"TX",
    "sg:tags":[
        "eating"
    ],
    "wof:name":"K F C",
    "wof:placetype":"venue"
},
  "geometry": {"coordinates":[-95.42932399999999,29.815625],"type":"Point"}
}