{
  "type": "Feature",
  "properties": {
    "iso:country":"US",
    "sg:address":"211 Old Authon Ln",
    "sg:city":"Weatherford",
    "sg:classifiers":[
        {
            "category":"Building & Trades",
            "subcategory":"Construction",
            "type":"Services"
        }
    ],
    "sg:phone":"+1 817 594 8077",
    "sg:postcode":"76088",
    "sg:province":"TX",
    "sg:tags":[
        "home",
        "builder"
    ],
    "wof:name":"Dee Sharp Construction",
    "wof:placetype":"venue"
},
  "geometry": {"coordinates":[-97.886107,32.832537],"type":"Point"}
}