{
  "type": "Feature",
  "properties": {
    "iso:country":"US",
    "sg:address":"Frankford Rd and Josey Ln",
    "sg:city":"Carrollton",
    "sg:classifiers":[
        {
            "category":"Education",
            "subcategory":"Special Training",
            "type":"Public Place"
        }
    ],
    "sg:phone":"+1 214 636 2811",
    "sg:postcode":"75007",
    "sg:province":"TX",
    "sg:tags":[
        "school",
        "specialty"
    ],
    "sg:website":"www.mysmarthandsdallas.com",
    "wof:name":"My Smart Hands Dallas",
    "wof:placetype":"venue"
},
  "geometry": {"coordinates":[-96.886619,33.000268],"type":"Point"}
}