{
  "type": "Feature",
  "properties": {
    "iso:country":"US",
    "sg:address":"4910 Wright Rd Ste 170",
    "sg:city":"Stafford",
    "sg:classifiers":[
        {
            "category":"Communications",
            "type":"Services"
        },
        {
            "category":"Shopping",
            "subcategory":"Computers & Home Electronics",
            "type":"Retail Goods"
        }
    ],
    "sg:phone":"+1 281 240 2100",
    "sg:postcode":"77477",
    "sg:province":"TX",
    "sg:tags":[
        "sound",
        "television",
        "system",
        "equipment",
        "radio",
        "store",
        "audio-visual"
    ],
    "sg:website":"http://www.nimbicsystems.com",
    "wof:name":"Nimbic Systems, Inc.",
    "wof:placetype":"venue"
},
  "geometry": {"coordinates":[-95.587495,29.630189],"type":"Point"}
}