{
  "type": "Feature",
  "properties": {
    "iso:country":"US",
    "sg:address":"3838 Oak Lawn Ave",
    "sg:city":"Dallas",
    "sg:classifiers":[
        {
            "category":"Real Estate",
            "subcategory":"Real Estate Operator",
            "type":"Services"
        }
    ],
    "sg:phone":"+1 214 521 4010",
    "sg:postcode":"75219",
    "sg:province":"TX",
    "sg:tags":[
        "shopping",
        "center",
        "operates"
    ],
    "wof:name":"Richardson Heights",
    "wof:placetype":"venue"
},
  "geometry": {"coordinates":[-96.80224200000001,32.815619],"type":"Point"}
}