{
  "type": "Feature",
  "properties": {
    "iso:country":"US",
    "sg:address":"2615 E Plum St",
    "sg:city":"Laredo",
    "sg:classifiers":[
        {
            "category":"Shopping",
            "type":"Retail Goods"
        }
    ],
    "sg:phone":"+1 956 724 3023",
    "sg:postcode":"78043",
    "sg:province":"TX",
    "sg:tags":[
        "merchandise"
    ],
    "wof:name":"J&I Sales",
    "wof:placetype":"venue"
},
  "geometry": {"coordinates":[-99.469149,27.524013],"type":"Point"}
}