{
  "type": "Feature",
  "properties": {
    "iso:country":"US",
    "sg:address":"705 Melwood Ave",
    "sg:city":"Brownwood",
    "sg:classifiers":[
        {
            "category":"Restaurant",
            "type":"Food & Drink"
        }
    ],
    "sg:phone":"+1 325 641 0708",
    "sg:postcode":"76801",
    "sg:province":"TX",
    "wof:name":"Melwood Place & Catering",
    "wof:placetype":"venue"
},
  "geometry": {"coordinates":[-98.98706900000001,31.720885],"type":"Point"}
}