{
  "type": "Feature",
  "properties": {
    "iso:country":"US",
    "sg:address":"1811 Junction Hwy",
    "sg:city":"Kerrville",
    "sg:classifiers":[
        {
            "category":"Building & Trades",
            "subcategory":"Construction",
            "type":"Services"
        }
    ],
    "sg:phone":"+1 830 895 5851",
    "sg:postcode":"78028",
    "sg:province":"TX",
    "sg:tags":[
        "excavation",
        "contractor"
    ],
    "wof:name":"Schwarz Construction Co",
    "wof:placetype":"venue"
},
  "geometry": {"coordinates":[-99.180131,30.066635],"type":"Point"}
}