{
  "type": "Feature",
  "properties": {
    "iso:country":"US",
    "sg:address":"1113 Wilson Dr",
    "sg:city":"Plano",
    "sg:classifiers":[
        {
            "category":"Wholesale",
            "subcategory":"Computers",
            "type":"Manufacturing & Wholesale Goods"
        }
    ],
    "sg:phone":"+1 972 599 1590",
    "sg:postcode":"75075",
    "sg:province":"TX",
    "sg:tags":[
        "new",
        "all",
        "selling",
        "accessory"
    ],
    "wof:name":"Compuplus Biz",
    "wof:placetype":"venue"
},
  "geometry": {"coordinates":[-96.739183,33.013403],"type":"Point"}
}