{
  "type": "Feature",
  "properties": {
    "iso:country":"US",
    "sg:address":"2324 Rock Island Rd",
    "sg:city":"Irving",
    "sg:classifiers":[
        {
            "category":"Personal",
            "subcategory":"Barber",
            "type":"Services"
        }
    ],
    "sg:phone":"+1 972 554 8188",
    "sg:postcode":"75060",
    "sg:province":"TX",
    "wof:name":"A Action Barber Shop",
    "wof:placetype":"venue"
},
  "geometry": {"coordinates":[-96.974924,32.815224],"type":"Point"}
}