{
  "type": "Feature",
  "properties": {
    "iso:country":"US",
    "sg:address":"20603 Apache Lake Dr",
    "sg:city":"Katy",
    "sg:classifiers":[
        {
            "category":"Professional",
            "subcategory":"Business Services",
            "type":"Services"
        }
    ],
    "sg:phone":"+1 281 492 6585",
    "sg:postcode":"77449",
    "sg:province":"TX",
    "wof:name":"Eco Enterprises",
    "wof:placetype":"venue"
},
  "geometry": {"coordinates":[-95.731177,29.81445],"type":"Point"}
}