{
  "type": "Feature",
  "properties": {
    "iso:country":"US",
    "sg:address":"1502 Pecan Crossing Dr",
    "sg:city":"Richmond",
    "sg:classifiers":[
        {
            "category":"Organizations",
            "subcategory":"Religious Organization",
            "type":"Services"
        }
    ],
    "sg:phone":"+1 281 238 5531",
    "sg:postcode":"77469",
    "sg:province":"TX",
    "wof:name":"Spirit of Life",
    "wof:placetype":"venue"
},
  "geometry": {"coordinates":[-95.727749,29.632982],"type":"Point"}
}