{
  "type": "Feature",
  "properties": {
    "iso:country":"US",
    "sg:address":"2812 S Marsalis Ave",
    "sg:city":"Dallas",
    "sg:classifiers":[
        {
            "category":"Home & Garden",
            "subcategory":"Furniture",
            "type":"Retail Goods"
        }
    ],
    "sg:phone":"+1 469 533 4369",
    "sg:postcode":"75216",
    "sg:province":"TX",
    "wof:name":"McGriffs Furniture",
    "wof:placetype":"venue"
},
  "geometry": {"coordinates":[-96.814493,32.711587],"type":"Point"}
}