{
  "type": "Feature",
  "properties": {
    "iso:country":"US",
    "sg:address":"222 S Galloway Ave",
    "sg:city":"Mesquite",
    "sg:classifiers":[
        {
            "category":"Retail",
            "subcategory":"Auto Repair",
            "type":"Services"
        }
    ],
    "sg:phone":"+1 972 329 0771",
    "sg:postcode":"75149",
    "sg:province":"TX",
    "sg:tags":[
        "repairing",
        "automobile",
        "supply"
    ],
    "wof:name":"Affordable Kar Kare",
    "wof:placetype":"venue"
},
  "geometry": {"coordinates":[-96.59929700000001,32.766102],"type":"Point"}
}