{
  "type": "Feature",
  "properties": {
    "iso:country":"US",
    "sg:address":"707 S Smith Ave",
    "sg:city":"Hebbronville",
    "sg:classifiers":[
        {
            "category":"Food & Beverages",
            "subcategory":"Meat & Fish",
            "type":"Retail Goods"
        },
        {
            "category":"Restaurant",
            "type":"Food & Drink"
        }
    ],
    "sg:phone":"+1 361 527 4330",
    "sg:postcode":"78361",
    "sg:province":"TX",
    "sg:tags":[
        "seafood",
        "eating"
    ],
    "wof:name":"Bay Net Seafood",
    "wof:placetype":"venue"
},
  "geometry": {"coordinates":[-98.678471,27.30079],"type":"Point"}
}