{
  "type": "Feature",
  "properties": {
    "iso:country":"US",
    "sg:address":"4510 S State Hwy 349",
    "sg:city":"Midland",
    "sg:classifiers":[
        {
            "category":"Manufacturing",
            "subcategory":"Tools & Machinery",
            "type":"Manufacturing & Wholesale Goods"
        }
    ],
    "sg:phone":"+1 432 682 8572",
    "sg:postcode":"79706",
    "sg:province":"TX",
    "sg:tags":[
        "compressor"
    ],
    "wof:name":"Midland Air Svc",
    "wof:placetype":"venue"
},
  "geometry": {"coordinates":[-102.064587,31.942922],"type":"Point"}
}