{
  "type": "Feature",
  "properties": {
    "iso:country":"US",
    "sg:address":"53 Waterlily Ct",
    "sg:city":"Lake Jackson",
    "sg:classifiers":[
        {
            "category":"Shopping",
            "type":"Retail Goods"
        }
    ],
    "sg:phone":"+1 979 265 0755",
    "sg:postcode":"77566",
    "sg:province":"TX",
    "sg:tags":[
        "album",
        "photo",
        "frame"
    ],
    "wof:name":"Jim Hemphill",
    "wof:placetype":"venue"
},
  "geometry": {"coordinates":[-95.423062,29.043486],"type":"Point"}
}