{
  "type": "Feature",
  "properties": {
    "iso:country":"US",
    "sg:address":"2550 W Fm 544",
    "sg:city":"Wylie",
    "sg:classifiers":[
        {
            "category":"Cinema",
            "subcategory":"Movie Rental",
            "type":"Entertainment"
        }
    ],
    "sg:phone":"+1 972 442 5645",
    "sg:postcode":"75098",
    "sg:province":"TX",
    "sg:tags":[
        "motion",
        "picture",
        "distributor",
        "film",
        "exchange"
    ],
    "wof:name":"Jame Winning Productions",
    "wof:placetype":"venue"
},
  "geometry": {"coordinates":[-96.57216,33.010928],"type":"Point"}
}