{
  "type": "Feature",
  "properties": {
    "iso:country":"US",
    "sg:address":"2802 Valley Way Dr",
    "sg:city":"Humble",
    "sg:classifiers":[
        {
            "category":"Real Estate",
            "subcategory":"Real Estate Agent",
            "type":"Services"
        }
    ],
    "sg:phone":"+1 281 852 8500",
    "sg:postcode":"77339",
    "sg:province":"TX",
    "wof:name":"Kings Lake Estates",
    "wof:placetype":"venue"
},
  "geometry": {"coordinates":[-95.196929,30.048422],"type":"Point"}
}