{
  "type": "Feature",
  "properties": {
    "iso:country":"US",
    "sg:address":"1605 E Expy 83",
    "sg:city":"Mission",
    "sg:classifiers":[
        {
            "category":"Social Services",
            "subcategory":"Job Training",
            "type":"Services"
        }
    ],
    "sg:phone":"+1 956 584 8980",
    "sg:postcode":"78572",
    "sg:province":"TX",
    "sg:tags":[
        "rehabilitation"
    ],
    "wof:name":"Stepping Stone Rehab Svc",
    "wof:placetype":"venue"
},
  "geometry": {"coordinates":[-98.303673,26.198288],"type":"Point"}
}