{
  "type": "Feature",
  "properties": {
    "iso:country":"US",
    "sg:address":"2616 Ellis Ct",
    "sg:city":"Plano",
    "sg:classifiers":[
        {
            "category":"Professional",
            "subcategory":"Business Services",
            "type":"Services"
        }
    ],
    "sg:phone":"+1 972 596 3371",
    "sg:postcode":"75075",
    "sg:province":"TX",
    "wof:name":"Active Solutions Rehabilitatio",
    "wof:placetype":"venue"
},
  "geometry": {"coordinates":[-96.76922999999999,33.034586],"type":"Point"}
}