{
  "type": "Feature",
  "properties": {
    "iso:country":"US",
    "sg:address":"17341 Louis Ln",
    "sg:city":"Porter",
    "sg:classifiers":[
        {
            "category":"Building & Trades",
            "subcategory":"Construction",
            "type":"Services"
        }
    ],
    "sg:phone":"+1 281 572 1011",
    "sg:postcode":"77365",
    "sg:province":"TX",
    "sg:tags":[
        "house"
    ],
    "wof:name":"Koehler Construction",
    "wof:placetype":"venue"
},
  "geometry": {"coordinates":[-95.30653599999999,30.154874],"type":"Point"}
}