{
  "type": "Feature",
  "properties": {
    "iso:country":"US",
    "sg:address":"14655 Northwest Fwy",
    "sg:city":"Houston",
    "sg:classifiers":[
        {
            "category":"Professional",
            "subcategory":"Employment Agencies",
            "type":"Services"
        }
    ],
    "sg:phone":"+1 713 681 2300",
    "sg:postcode":"77040",
    "sg:province":"TX",
    "sg:tags":[
        "opportunity"
    ],
    "wof:name":"Texstar Recruiters",
    "wof:placetype":"venue"
},
  "geometry": {"coordinates":[-95.541055,29.866594],"type":"Point"}
}