{
  "type": "Feature",
  "properties": {
    "iso:country":"US",
    "sg:address":"14152 Antonio Dr",
    "sg:city":"Helotes",
    "sg:classifiers":[
        {
            "category":"Restaurant",
            "type":"Food & Drink"
        }
    ],
    "sg:phone":"+1 210 930 4978",
    "sg:postcode":"78023",
    "sg:province":"TX",
    "sg:tags":[
        "caterer"
    ],
    "wof:name":"Savories Catering",
    "wof:placetype":"venue"
},
  "geometry": {"coordinates":[-98.694475,29.574398],"type":"Point"}
}