{
  "type": "Feature",
  "properties": {
    "iso:country":"US",
    "sg:address":"1000 N Church St",
    "sg:city":"Palestine",
    "sg:classifiers":[
        {
            "category":"Professional",
            "subcategory":"Lawyer & Legal Services",
            "type":"Services"
        }
    ],
    "sg:phone":"+1 903 723 6757",
    "sg:postcode":"75801",
    "sg:province":"TX",
    "sg:tags":[
        "attorney"
    ],
    "wof:name":"William M Curley PC",
    "wof:placetype":"venue"
},
  "geometry": {"coordinates":[-95.627026,31.770394],"type":"Point"}
}