{
  "type": "Feature",
  "properties": {
    "iso:country":"US",
    "sg:address":"342 S Temple St",
    "sg:city":"Goliad",
    "sg:classifiers":[
        {
            "category":"Personal",
            "subcategory":"Beauty Salon",
            "type":"Services"
        }
    ],
    "sg:phone":"+1 361 645 2006",
    "sg:postcode":"77963",
    "sg:province":"TX",
    "sg:tags":[
        "shop"
    ],
    "wof:name":"Hair By Sadie",
    "wof:placetype":"venue"
},
  "geometry": {"coordinates":[-97.383516,28.665302],"type":"Point"}
}