{
  "type": "Feature",
  "properties": {
    "iso:country":"US",
    "sg:address":"4405 Lilac Ln",
    "sg:city":"Victoria",
    "sg:classifiers":[
        {
            "category":"Professional",
            "subcategory":"Art Services",
            "type":"Services"
        }
    ],
    "sg:phone":"+1 361 576 9090",
    "sg:postcode":"77901",
    "sg:province":"TX",
    "sg:tags":[
        "graphic",
        "mfg",
        "specialty",
        "advert",
        "designer",
        "design"
    ],
    "wof:name":"Graphics Unlimited",
    "wof:placetype":"venue"
},
  "geometry": {"coordinates":[-96.998836,28.83545],"type":"Point"}
}