{
  "type": "Feature",
  "properties": {
    "iso:country":"US",
    "sg:address":"200 S John Redditt Dr",
    "sg:city":"Lufkin",
    "sg:classifiers":[
        {
            "category":"Health Services",
            "subcategory":"Doctor",
            "type":"Services"
        }
    ],
    "sg:phone":"+1 936 639 1110",
    "sg:postcode":"75904",
    "sg:province":"TX",
    "sg:tags":[
        "physician",
        "surgeon"
    ],
    "wof:name":"Allergy & Asthma Clinic",
    "wof:placetype":"venue"
},
  "geometry": {"coordinates":[-94.75860299999999,31.33156],"type":"Point"}
}