{
  "type": "Feature",
  "properties": {
    "iso:country":"US",
    "sg:address":"8219 Watchtower St",
    "sg:city":"San Antonio",
    "sg:classifiers":[
        {
            "category":"Real Estate",
            "subcategory":"Real Estate Agent",
            "type":"Services"
        }
    ],
    "sg:phone":"+1 210 497 0622",
    "sg:postcode":"78254",
    "sg:province":"TX",
    "sg:tags":[
        "management"
    ],
    "wof:name":"MGM Realty Svc",
    "wof:placetype":"venue"
},
  "geometry": {"coordinates":[-98.650115,29.52865],"type":"Point"}
}