{
  "type": "Feature",
  "properties": {
    "iso:country":"US",
    "sg:address":"120 River Park Dr",
    "sg:city":"Ingram",
    "sg:classifiers":[
        {
            "category":"Shopping",
            "subcategory":"Used Merchandise",
            "type":"Retail Goods"
        }
    ],
    "sg:phone":"+1 830 367 7819",
    "sg:postcode":"78025",
    "sg:province":"TX",
    "wof:name":"Collectible Edge",
    "wof:placetype":"venue"
},
  "geometry": {"coordinates":[-99.230086,30.071082],"type":"Point"}
}