{
  "type": "Feature",
  "properties": {
    "iso:country":"US",
    "sg:address":"4143 Galloway Dr",
    "sg:city":"Pearland",
    "sg:classifiers":[
        {
            "category":"Utilities",
            "subcategory":"Fuel Oil & Lpg",
            "type":"Services"
        }
    ],
    "sg:phone":"+1 281 489 6734",
    "sg:postcode":"77584",
    "sg:province":"TX",
    "sg:tags":[
        "equipment",
        "handling"
    ],
    "wof:name":"Rutex Equipment",
    "wof:placetype":"venue"
},
  "geometry": {"coordinates":[-95.352777,29.535673],"type":"Point"}
}