{
  "type": "Feature",
  "properties": {
    "iso:country":"US",
    "sg:address":"707 Purple Sage Trl",
    "sg:city":"Mesquite",
    "sg:classifiers":[
        {
            "category":"Education",
            "subcategory":"School",
            "type":"Public Place"
        }
    ],
    "sg:phone":"+1 972 882 7060",
    "sg:postcode":"75149",
    "sg:province":"TX",
    "sg:website":"www.mesquiteisd.org",
    "wof:name":"Mesquite Independent School District",
    "wof:placetype":"venue"
},
  "geometry": {"coordinates":[-96.579922,32.773381],"type":"Point"}
}