{
  "type": "Feature",
  "properties": {
    "iso:country":"US",
    "sg:address":"6222 Tanager St",
    "sg:city":"Houston",
    "sg:classifiers":[
        {
            "category":"Shopping",
            "subcategory":"Musical Instruments",
            "type":"Retail Goods"
        }
    ],
    "sg:phone":"+1 713 988 6292",
    "sg:postcode":"77074",
    "sg:province":"TX",
    "wof:name":"Space City Percussion",
    "wof:placetype":"venue"
},
  "geometry": {"coordinates":[-95.50238400000001,29.688333],"type":"Point"}
}