{
  "type": "Feature",
  "properties": {
    "iso:country":"US",
    "sg:address":"221 W MOORE AVE",
    "sg:city":"TERRELL",
    "sg:classifiers":[
        {
            "category":"Home & Garden",
            "subcategory":"Furniture",
            "type":"Retail Goods"
        },
        {
            "category":"Home & Garden",
            "subcategory":"Home Furnishings",
            "type":"Retail Goods"
        },
        {
            "category":"Home & Garden",
            "subcategory":"Household Appliances",
            "type":"Retail Goods"
        },
        {
            "category":"Home & Garden",
            "subcategory":"Carpets & Floor Coverings",
            "type":"Retail Goods"
        }
    ],
    "sg:phone":"+1 972 563 0597",
    "sg:postcode":"75160",
    "sg:province":"TX",
    "sg:tags":[
        "major",
        "set",
        "house",
        "bed",
        "mattress",
        "bedroom",
        "store"
    ],
    "sg:website":"http://www.traylorfurniture.com",
    "wof:name":"Traylor Furniture",
    "wof:placetype":"venue"
},
  "geometry": {"coordinates":[-96.27858500000001,32.736558],"type":"Point"}
}