{
  "type": "Feature",
  "properties": {
    "iso:country":"US",
    "sg:address":"8622 Irvington Blvd",
    "sg:city":"Houston",
    "sg:classifiers":[
        {
            "category":"Shopping",
            "subcategory":"Clothing, Apparel, & Fashions",
            "type":"Retail Goods"
        }
    ],
    "sg:phone":"+1 713 699 8339",
    "sg:postcode":"77022",
    "sg:province":"TX",
    "wof:name":"Gorditas Dona Tota",
    "wof:placetype":"venue"
},
  "geometry": {"coordinates":[-95.361486,29.838513],"type":"Point"}
}