{
  "type": "Feature",
  "properties": {
    "iso:country":"US",
    "sg:address":"5323 Ghost Hawk St",
    "sg:city":"San Antonio",
    "sg:classifiers":[
        {
            "category":"Retail",
            "subcategory":"Auto Repair",
            "type":"Services"
        }
    ],
    "sg:phone":"+1 210 623 5717",
    "sg:postcode":"78242",
    "sg:province":"TX",
    "sg:tags":[
        "automotive"
    ],
    "wof:name":"Camelot Towing",
    "wof:placetype":"venue"
},
  "geometry": {"coordinates":[-98.604591,29.339658],"type":"Point"}
}