{
  "type": "Feature",
  "properties": {
    "iso:country":"US",
    "sg:address":"305 S Main St",
    "sg:city":"Bridgeport",
    "sg:classifiers":[
        {
            "category":"Food & Beverages",
            "subcategory":"Liquor & Beverages",
            "type":"Retail Goods"
        }
    ],
    "sg:phone":"+1 940 683 4959",
    "sg:postcode":"76426",
    "sg:province":"TX",
    "sg:tags":[
        "beer",
        "ale",
        "store"
    ],
    "wof:name":"Twin Hills Store",
    "wof:placetype":"venue"
},
  "geometry": {"coordinates":[-97.82693500000001,33.203262],"type":"Point"}
}