{
  "type": "Feature",
  "properties": {
    "iso:country":"US",
    "sg:address":"415 Walker St",
    "sg:city":"Sealy",
    "sg:classifiers":[
        {
            "category":"Manufacturing",
            "subcategory":"Food",
            "type":"Manufacturing & Wholesale Goods"
        }
    ],
    "sg:phone":"+1 979 885 0458",
    "sg:postcode":"77474",
    "sg:province":"TX",
    "sg:tags":[
        "product",
        "mfg"
    ],
    "wof:name":"Mrs Bairds Bakeries",
    "wof:placetype":"venue"
},
  "geometry": {"coordinates":[-96.151717,29.78197],"type":"Point"}
}