{
  "type": "Feature",
  "properties": {
    "iso:country":"US",
    "sg:address":"606 Oriole Blvd",
    "sg:city":"Duncanville",
    "sg:classifiers":[
        {
            "category":"Professional",
            "type":"Services"
        }
    ],
    "sg:phone":"+1 972 298 3132",
    "sg:postcode":"75116",
    "sg:province":"TX",
    "sg:tags":[
        "establishment"
    ],
    "wof:name":"Willie Bean Smith PC",
    "wof:placetype":"venue"
},
  "geometry": {"coordinates":[-96.901436,32.659097],"type":"Point"}
}