{
  "type": "Feature",
  "properties": {
    "iso:country":"US",
    "sg:address":"14222 Lasater Rd",
    "sg:city":"Dallas",
    "sg:classifiers":[
        {
            "category":"Building & Trades",
            "subcategory":"Landscaping Services",
            "type":"Services"
        }
    ],
    "sg:phone":"+1 972 557 7393",
    "sg:postcode":"75253",
    "sg:province":"TX",
    "sg:tags":[
        "landscape",
        "contractor"
    ],
    "wof:name":"M & B Landscape",
    "wof:placetype":"venue"
},
  "geometry": {"coordinates":[-96.572284,32.7007],"type":"Point"}
}