{
  "type": "Feature",
  "properties": {
    "iso:country":"US",
    "sg:address":"813 Ave C",
    "sg:city":"Katy",
    "sg:classifiers":[
        {
            "category":"Real Estate",
            "subcategory":"Developer",
            "type":"Services"
        }
    ],
    "sg:phone":"+1 281 391 2347",
    "sg:postcode":"77493",
    "sg:province":"TX",
    "wof:name":"War Horse Development Corp",
    "wof:placetype":"venue"
},
  "geometry": {"coordinates":[-95.823379,29.786488],"type":"Point"}
}