{
  "type": "Feature",
  "properties": {
    "iso:country":"US",
    "sg:address":"121 S Bee St",
    "sg:city":"Mathis",
    "sg:classifiers":[
        {
            "category":"Government",
            "subcategory":"Post Office",
            "type":"Public Place"
        }
    ],
    "sg:phone":"+1 361 547 3061",
    "sg:postcode":"78368",
    "sg:province":"TX",
    "sg:tags":[
        "postal",
        "us"
    ],
    "wof:name":"US Post Office",
    "wof:placetype":"venue"
},
  "geometry": {"coordinates":[-97.827217,28.093199],"type":"Point"}
}