{
  "type": "Feature",
  "properties": {
    "iso:country":"US",
    "sg:address":"19055 Hufsmith Kohrville Rd",
    "sg:city":"Tomball",
    "sg:classifiers":[
        {
            "category":"Shopping",
            "type":"Retail Goods"
        }
    ],
    "sg:phone":"+1 281 351 9061",
    "sg:postcode":"77375",
    "sg:province":"TX",
    "sg:tags":[
        "merchandise"
    ],
    "wof:name":"Feather Valley Farm",
    "wof:placetype":"venue"
},
  "geometry": {"coordinates":[-95.591159,30.040963],"type":"Point"}
}