{
  "type": "Feature",
  "properties": {
    "iso:country":"US",
    "sg:address":"1108 Sun Ave",
    "sg:city":"Port Neches",
    "sg:classifiers":[
        {
            "category":"Building & Trades",
            "subcategory":"Electrical",
            "type":"Services"
        }
    ],
    "sg:phone":"+1 409 722 3319",
    "sg:postcode":"77651",
    "sg:province":"TX",
    "sg:tags":[
        "electric",
        "contractor"
    ],
    "wof:name":"Woodall Electric Co",
    "wof:placetype":"venue"
},
  "geometry": {"coordinates":[-93.96381599999999,29.983148],"type":"Point"}
}