{
  "type": "Feature",
  "properties": {
    "iso:country":"US",
    "sg:address":"1625 W Bedford St",
    "sg:city":"Dimmitt",
    "sg:classifiers":[
        {
            "category":"Shopping",
            "subcategory":"Clothing, Apparel, & Fashions",
            "type":"Retail Goods"
        }
    ],
    "sg:phone":"+1 806 647 3738",
    "sg:postcode":"79027",
    "sg:province":"TX",
    "sg:tags":[
        "family"
    ],
    "wof:name":"C G Collectables",
    "wof:placetype":"venue"
},
  "geometry": {"coordinates":[-102.337413,34.543598],"type":"Point"}
}