{
  "type": "Feature",
  "properties": {
    "iso:country":"US",
    "sg:address":"2104 W Holiday",
    "sg:city":"Rockwall",
    "sg:classifiers":[
        {
            "category":"Building & Trades",
            "subcategory":"Electrical",
            "type":"Services"
        }
    ],
    "sg:phone":"+1 972 722 1714",
    "sg:postcode":"75087",
    "sg:province":"TX",
    "sg:tags":[
        "electrical",
        "contractor"
    ],
    "wof:name":"John Junkin Inc",
    "wof:placetype":"venue"
},
  "geometry": {"coordinates":[-96.40088,32.936256],"type":"Point"}
}