{
  "type": "Feature",
  "properties": {
    "iso:country":"US",
    "sg:address":"2610 Lake Austin Blvd",
    "sg:city":"Austin",
    "sg:classifiers":[
        {
            "category":"Shopping",
            "subcategory":"Pharmacy",
            "type":"Retail Goods"
        }
    ],
    "sg:phone":"+1 512 322 0954",
    "sg:postcode":"78703",
    "sg:province":"TX",
    "wof:name":"CVS Pharmacy",
    "wof:placetype":"venue"
},
  "geometry": {"coordinates":[-97.7744,30.279538],"type":"Point"}
}