{
  "type": "Feature",
  "properties": {
    "iso:country":"US",
    "sg:address":"2440 Texas Pkwy Lbby",
    "sg:city":"Missouri City",
    "sg:classifiers":[
        {
            "category":"Banks & Credit Unions",
            "subcategory":"Bank",
            "type":"Services"
        }
    ],
    "sg:phone":"+1 281 261 6608",
    "sg:postcode":"77489",
    "sg:province":"TX",
    "wof:name":"Wells Fargo Bank Na",
    "wof:placetype":"venue"
},
  "geometry": {"coordinates":[-95.52660400000001,29.5921],"type":"Point"}
}