{
  "type": "Feature",
  "properties": {
    "iso:country":"US",
    "sg:address":"601 Shady Ln N",
    "sg:city":"Keller",
    "sg:classifiers":[
        {
            "category":"Personal",
            "subcategory":"Beauty Salon",
            "type":"Services"
        }
    ],
    "sg:phone":"+1 817 337 5394",
    "sg:postcode":"76248",
    "sg:province":"TX",
    "wof:name":"Sandi S Body Spa",
    "wof:placetype":"venue"
},
  "geometry": {"coordinates":[-97.246582,32.923939],"type":"Point"}
}