{
  "type": "Feature",
  "properties": {
    "iso:country":"US",
    "sg:address":"1010 N Nelson St",
    "sg:city":"Amarillo",
    "sg:classifiers":[
        {
            "category":"Shopping",
            "subcategory":"Books",
            "type":"Retail Goods"
        }
    ],
    "sg:phone":"+1 806 381 0268",
    "sg:postcode":"79107",
    "sg:province":"TX",
    "wof:name":"Sams 101 Sales Book Co",
    "wof:placetype":"venue"
},
  "geometry": {"coordinates":[-101.806005,35.225696],"type":"Point"}
}