{
  "type": "Feature",
  "properties": {
    "iso:country":"US",
    "sg:address":"7601 Main St",
    "sg:city":"Frisco",
    "sg:classifiers":[
        {
            "category":"Building & Trades",
            "subcategory":"Construction",
            "type":"Services"
        }
    ],
    "sg:phone":"+1 972 335 4028",
    "sg:postcode":"75034",
    "sg:province":"TX",
    "sg:tags":[
        "contractor"
    ],
    "wof:name":"C B I",
    "wof:placetype":"venue"
},
  "geometry": {"coordinates":[-96.81990399999999,33.149814],"type":"Point"}
}