{
  "type": "Feature",
  "properties": {
    "iso:country":"US",
    "sg:address":"26304 Jason Ave",
    "sg:city":"San Antonio",
    "sg:classifiers":[
        {
            "category":"Health Services",
            "subcategory":"Chiropractor",
            "type":"Services"
        }
    ],
    "sg:phone":"+1 210 698 5513",
    "sg:postcode":"78255",
    "sg:province":"TX",
    "wof:name":"Frederick DC Bigelow",
    "wof:placetype":"venue"
},
  "geometry": {"coordinates":[-98.650554,29.69182],"type":"Point"}
}