{
  "type": "Feature",
  "properties": {
    "iso:country":"US",
    "sg:address":"10766 Camellia Dr",
    "sg:city":"Dallas",
    "sg:classifiers":[
        {
            "category":"Professional",
            "subcategory":"Business Services",
            "type":"Services"
        }
    ],
    "sg:phone":"+1 214 674 5757",
    "sg:postcode":"75230",
    "sg:province":"TX",
    "wof:name":"Corson Decor",
    "wof:placetype":"venue"
},
  "geometry": {"coordinates":[-96.801382,32.893045],"type":"Point"}
}