{
  "type": "Feature",
  "properties": {
    "iso:country":"US",
    "sg:address":"22285 White Oak Dr",
    "sg:city":"Porter",
    "sg:classifiers":[
        {
            "category":"Building & Trades",
            "subcategory":"Plumbing",
            "type":"Services"
        }
    ],
    "sg:phone":"+1 281 354 3203",
    "sg:postcode":"77365",
    "sg:province":"TX",
    "sg:tags":[
        "contractor"
    ],
    "wof:name":"McMillan Plumbing Company Inc",
    "wof:placetype":"venue"
},
  "geometry": {"coordinates":[-95.25382500000001,30.118429],"type":"Point"}
}