{
  "type": "Feature",
  "properties": {
    "iso:country":"US",
    "sg:address":"5330 Myrtlewood St",
    "sg:city":"Houston",
    "sg:classifiers":[
        {
            "category":"Retail",
            "subcategory":"Repair Shop",
            "type":"Services"
        }
    ],
    "sg:phone":"+1 713 731 9025",
    "sg:postcode":"77033",
    "sg:province":"TX",
    "wof:name":"Kable",
    "wof:placetype":"venue"
},
  "geometry": {"coordinates":[-95.342044,29.666865],"type":"Point"}
}