{
  "type": "Feature",
  "properties": {
    "iso:country":"US",
    "sg:address":"414 E Ave A",
    "sg:city":"Killeen",
    "sg:classifiers":[
        {
            "category":"Real Estate",
            "subcategory":"Real Estate Operator",
            "type":"Services"
        }
    ],
    "sg:phone":"+1 254 628 1770",
    "sg:postcode":"76541",
    "sg:province":"TX",
    "wof:name":"Sand Bert Apartments",
    "wof:placetype":"venue"
},
  "geometry": {"coordinates":[-97.724735,31.12213],"type":"Point"}
}