{
  "type": "Feature",
  "properties": {
    "iso:country":"US",
    "sg:address":"4717 Westway Dr",
    "sg:city":"Corpus Christi",
    "sg:classifiers":[
        {
            "category":"Restaurant",
            "type":"Food & Drink"
        }
    ],
    "sg:phone":"+1 361 883 6611",
    "sg:postcode":"78408",
    "sg:province":"TX",
    "wof:name":"Fish Trackers Inc",
    "wof:placetype":"venue"
},
  "geometry": {"coordinates":[-97.45071799999999,27.792609],"type":"Point"}
}