{
  "type": "Feature",
  "properties": {
    "iso:country":"US",
    "sg:address":"850 S Lynchburg Rd",
    "sg:city":"Baytown",
    "sg:classifiers":[
        {
            "category":"Building & Trades",
            "subcategory":"Construction",
            "type":"Services"
        }
    ],
    "sg:phone":"+1 281 838 0003",
    "sg:postcode":"77520",
    "sg:province":"TX",
    "sg:tags":[
        "designer",
        "marine",
        "contractor"
    ],
    "wof:name":"Houston Marine Svc Personnel",
    "wof:placetype":"venue"
},
  "geometry": {"coordinates":[-95.068814,29.768902],"type":"Point"}
}