{
  "type": "Feature",
  "properties": {
    "iso:country":"US",
    "sg:address":"4091 Navarro Way",
    "sg:city":"Frisco",
    "sg:classifiers":[
        {
            "category":"Wholesale",
            "subcategory":"Non-durable Goods",
            "type":"Manufacturing & Wholesale Goods"
        }
    ],
    "sg:phone":"+1 972 668 0660",
    "sg:postcode":"75034",
    "sg:province":"TX",
    "wof:name":"Another Tyme",
    "wof:placetype":"venue"
},
  "geometry": {"coordinates":[-96.85348999999999,33.115611],"type":"Point"}
}