{
  "type": "Feature",
  "properties": {
    "iso:country":"US",
    "sg:address":"3499 Onion Shed Rd",
    "sg:city":"Anton",
    "sg:phone":"+1 806 997 7602",
    "sg:postcode":"79313",
    "sg:province":"TX",
    "sg:tags":[
        "farm",
        "cotton"
    ],
    "wof:name":"Earnest Coleman Inc",
    "wof:placetype":"venue"
},
  "geometry": {"coordinates":[-102.139195,33.718795],"type":"Point"}
}