{
  "type": "Feature",
  "properties": {
    "iso:country":"US",
    "sg:address":"9 Spencer Hwy",
    "sg:city":"South Houston",
    "sg:classifiers":[
        {
            "category":"Health Services",
            "subcategory":"Hospital",
            "type":"Services"
        }
    ],
    "sg:phone":"+1 713 941 9214",
    "sg:postcode":"77587",
    "sg:province":"TX",
    "sg:tags":[
        "specialty"
    ],
    "wof:name":"Southeast Recovery Inc",
    "wof:placetype":"venue"
},
  "geometry": {"coordinates":[-95.232146,29.664504],"type":"Point"}
}