{
  "type": "Feature",
  "properties": {
    "iso:country":"US",
    "sg:address":"310 W Brown St",
    "sg:city":"Wylie",
    "sg:classifiers":[
        {
            "category":"Insurance",
            "subcategory":"Insurance Agent",
            "type":"Services"
        }
    ],
    "sg:phone":"+1 972 442 6562",
    "sg:postcode":"75098",
    "sg:province":"TX",
    "wof:name":"Russell Davis Insurance",
    "wof:placetype":"venue"
},
  "geometry": {"coordinates":[-96.541669,33.017498],"type":"Point"}
}