{
  "type": "Feature",
  "properties": {
    "iso:country":"US",
    "sg:address":"6702 el Paso Ave",
    "sg:city":"Odessa",
    "sg:classifiers":[
        {
            "category":"Wholesale",
            "subcategory":"Machinery & Supplies",
            "type":"Manufacturing & Wholesale Goods"
        }
    ],
    "sg:phone":"+1 432 631 1507",
    "sg:postcode":"79762",
    "sg:province":"TX",
    "sg:tags":[
        "equipment",
        "industrial"
    ],
    "wof:name":"L & R Bit Co Inc",
    "wof:placetype":"venue"
},
  "geometry": {"coordinates":[-102.37928100000001,31.913757],"type":"Point"}
}