{
  "type": "Feature",
  "properties": {
    "iso:country":"US",
    "sg:address":"1751 Honey Brook Ln",
    "sg:city":"Prosper",
    "sg:classifiers":[
        {
            "category":"Professional",
            "subcategory":"Accounting & Tax Preparation",
            "type":"Services"
        }
    ],
    "sg:phone":"+1 972 346 3100",
    "sg:postcode":"75078",
    "sg:province":"TX",
    "wof:name":"Dianne Kerr CPA",
    "wof:placetype":"venue"
},
  "geometry": {"coordinates":[-96.747843,33.244342],"type":"Point"}
}