{
  "type": "Feature",
  "properties": {
    "iso:country":"US",
    "sg:address":"16522 Lost Quail Dr",
    "sg:city":"Missouri City",
    "sg:classifiers":[
        {
            "category":"Building & Trades",
            "subcategory":"Cleaning & Sanitation",
            "type":"Services"
        }
    ],
    "sg:phone":"+1 281 438 5059",
    "sg:postcode":"77489",
    "sg:province":"TX",
    "sg:tags":[
        "maintenance"
    ],
    "wof:name":"Superior Janitorial",
    "wof:placetype":"venue"
},
  "geometry": {"coordinates":[-95.517171,29.587286],"type":"Point"}
}