{
  "type": "Feature",
  "properties": {
    "iso:country":"US",
    "sg:address":"2400 W Park Row Dr",
    "sg:city":"Pantego",
    "sg:classifiers":[
        {
            "category":"Retail",
            "subcategory":"Repair Shop",
            "type":"Services"
        }
    ],
    "sg:phone":"+1 817 460 0551",
    "sg:postcode":"76013",
    "sg:province":"TX",
    "sg:tags":[
        "equipment",
        "conditioning",
        "air"
    ],
    "wof:name":"Texas Services Air Cond",
    "wof:placetype":"venue"
},
  "geometry": {"coordinates":[-97.147299,32.721259],"type":"Point"}
}