{
  "type": "Feature",
  "properties": {
    "iso:country":"US",
    "sg:address":"326 Givens Ave",
    "sg:city":"San Antonio",
    "sg:classifiers":[
        {
            "category":"Retail",
            "subcategory":"Repair Shop",
            "type":"Services"
        }
    ],
    "sg:phone":"+1 210 224 8739",
    "sg:postcode":"78204",
    "sg:province":"TX",
    "sg:tags":[
        "plumbing",
        "drain",
        "cleaning",
        "sewer"
    ],
    "wof:name":"B G Torres Plumbing",
    "wof:placetype":"venue"
},
  "geometry": {"coordinates":[-98.510299,29.399618],"type":"Point"}
}