{
  "type": "Feature",
  "properties": {
    "iso:country":"US",
    "sg:address":"2007 Texoma Pkwy",
    "sg:city":"Sherman",
    "sg:classifiers":[
        {
            "category":"Organizations",
            "subcategory":"Religious Organization",
            "type":"Services"
        }
    ],
    "sg:phone":"+1 903 892 1511",
    "sg:postcode":"75090",
    "sg:province":"TX",
    "wof:name":"Sherman-Mckinney District",
    "wof:placetype":"venue"
},
  "geometry": {"coordinates":[-96.601949,33.65826],"type":"Point"}
}