{
  "type": "Feature",
  "properties": {
    "iso:country":"US",
    "sg:address":"1720 Southmore Blvd",
    "sg:city":"Houston",
    "sg:classifiers":[
        {
            "category":"Social Services",
            "type":"Services"
        }
    ],
    "sg:phone":"+1 713 473 9990",
    "sg:postcode":"77004",
    "sg:province":"TX",
    "sg:tags":[
        "counseling"
    ],
    "wof:name":"Christian Counseling Ministres",
    "wof:placetype":"venue"
},
  "geometry": {"coordinates":[-95.380796,29.724446],"type":"Point"}
}