{
  "type": "Feature",
  "properties": {
    "iso:country":"US",
    "sg:address":"113 Meadow Ln",
    "sg:city":"Lake Dallas",
    "sg:classifiers":[
        {
            "category":"Farming",
            "subcategory":"Poultry Farm",
            "type":"Manufacturing & Wholesale Goods"
        }
    ],
    "sg:phone":"+1 940 321 4407",
    "sg:postcode":"75065",
    "sg:province":"TX",
    "sg:tags":[
        "egg"
    ],
    "wof:name":"Rodriguez Andy",
    "wof:placetype":"venue"
},
  "geometry": {"coordinates":[-97.008875,33.111699],"type":"Point"}
}