{
  "type": "Feature",
  "properties": {
    "iso:country":"US",
    "sg:address":"1129 Colorado Ln",
    "sg:city":"Arlington",
    "sg:classifiers":[
        {
            "category":"Manufacturing",
            "subcategory":"Metals",
            "type":"Manufacturing & Wholesale Goods"
        },
        {
            "category":"Shopping",
            "type":"Retail Goods"
        }
    ],
    "sg:phone":"+1 817 277 8636",
    "sg:postcode":"76015",
    "sg:province":"TX",
    "sg:tags":[
        "art",
        "mfg",
        "gallery",
        "architectural",
        "metalwork",
        "dealer"
    ],
    "wof:name":"Betzinger Metal Art Studio",
    "wof:placetype":"venue"
},
  "geometry": {"coordinates":[-97.122584,32.702103],"type":"Point"}
}