{
  "type": "Feature",
  "properties": {
    "iso:country":"US",
    "sg:address":"600 E Robinson Ave",
    "sg:city":"El Paso",
    "sg:classifiers":[
        {
            "category":"Shopping",
            "type":"Retail Goods"
        }
    ],
    "sg:phone":"+1 915 532 6801",
    "sg:postcode":"79902",
    "sg:province":"TX",
    "sg:tags":[
        "merchandise"
    ],
    "wof:name":"Steve Edwards",
    "wof:placetype":"venue"
},
  "geometry": {"coordinates":[-106.49827000000001,31.779002],"type":"Point"}
}