{
  "type": "Feature",
  "properties": {
    "iso:country":"US",
    "sg:address":"2777 N Stemmons Fwy",
    "sg:city":"Dallas",
    "sg:classifiers":[
        {
            "category":"Utilities",
            "subcategory":"Natural Gas",
            "type":"Services"
        }
    ],
    "sg:phone":"+1 214 640 6800",
    "sg:postcode":"75207",
    "sg:province":"TX",
    "sg:tags":[
        "transmission"
    ],
    "wof:name":"Lgne Natural Pipeline Company",
    "wof:placetype":"venue"
},
  "geometry": {"coordinates":[-96.930008,32.981446],"type":"Point"}
}