{
  "type": "Feature",
  "properties": {
    "iso:country":"US",
    "sg:address":"2316 Bridle Path",
    "sg:city":"Austin",
    "sg:classifiers":[
        {
            "category":"Professional",
            "subcategory":"Business Services",
            "type":"Services"
        }
    ],
    "sg:phone":"+1 512 432 5773",
    "sg:postcode":"78703",
    "sg:province":"TX",
    "sg:tags":[
        "consultant",
        "coach"
    ],
    "wof:name":"Matthew Geck Md Consulting",
    "wof:placetype":"venue"
},
  "geometry": {"coordinates":[-97.767132,30.289422],"type":"Point"}
}