{
  "type": "Feature",
  "properties": {
    "iso:country":"US",
    "sg:address":"116 Bowie Ln",
    "sg:city":"Hewitt",
    "sg:classifiers":[
        {
            "category":"Manufacturing",
            "subcategory":"Apparel",
            "type":"Manufacturing & Wholesale Goods"
        }
    ],
    "sg:phone":"+1 254 420 1561",
    "sg:postcode":"76643",
    "sg:province":"TX",
    "sg:tags":[
        "stitching",
        "pleating"
    ],
    "wof:name":"Sidney & Company",
    "wof:placetype":"venue"
},
  "geometry": {"coordinates":[-97.204801,31.462356],"type":"Point"}
}