{
  "type": "Feature",
  "properties": {
    "iso:country":"US",
    "sg:address":"1745 FM 126",
    "sg:city":"Nolan",
    "sg:classifiers":[
        {
            "category":"Government",
            "subcategory":"Post Office",
            "type":"Public Place"
        }
    ],
    "sg:phone":"+1 325 798 4361",
    "sg:postcode":"79520",
    "sg:province":"TX",
    "wof:name":"US Post Office",
    "wof:placetype":"venue"
},
  "geometry": {"coordinates":[-100.087253,32.766174],"type":"Point"}
}