{
  "type": "Feature",
  "properties": {
    "iso:country":"US",
    "sg:address":"8491 US Hwy 281",
    "sg:city":"Spring Branch",
    "sg:classifiers":[
        {
            "category":"Retail",
            "subcategory":"Repair Shop",
            "type":"Services"
        },
        {
            "category":"Recreation",
            "subcategory":"Marina",
            "type":"Entertainment"
        }
    ],
    "sg:phone":"+1 830 885 2495",
    "sg:postcode":"78070",
    "sg:province":"TX",
    "sg:tags":[
        "repairing",
        "boat"
    ],
    "wof:name":"Boat Masters",
    "wof:placetype":"venue"
},
  "geometry": {"coordinates":[-98.40723800000001,29.857013],"type":"Point"}
}