{
  "type": "Feature",
  "properties": {
    "iso:country":"US",
    "sg:address":"29711 Tanglewood St",
    "sg:city":"Magnolia",
    "sg:classifiers":[
        {
            "category":"Shopping",
            "type":"Retail Goods"
        }
    ],
    "sg:phone":"+1 281 356 9598",
    "sg:postcode":"77354",
    "sg:province":"TX",
    "sg:tags":[
        "merchandise"
    ],
    "wof:name":"Stamped Art Mania",
    "wof:placetype":"venue"
},
  "geometry": {"coordinates":[-95.626572,30.205548],"type":"Point"}
}