{
  "type": "Feature",
  "properties": {
    "iso:country":"US",
    "sg:address":"3603 32nd St",
    "sg:city":"Lubbock",
    "sg:classifiers":[
        {
            "category":"Professional",
            "subcategory":"Secretarial Services",
            "type":"Services"
        }
    ],
    "sg:phone":"+1 806 797 8165",
    "sg:postcode":"79410",
    "sg:province":"TX",
    "sg:tags":[
        "hearing",
        "reporter"
    ],
    "wof:name":"Judy E Barnes",
    "wof:placetype":"venue"
},
  "geometry": {"coordinates":[-101.89422500000001,33.565005],"type":"Point"}
}