{
  "type": "Feature",
  "properties": {
    "iso:country":"US",
    "sg:address":"113 S Tower Dr",
    "sg:city":"San Antonio",
    "sg:classifiers":[
        {
            "category":"Wholesale",
            "subcategory":"Machinery & Supplies",
            "type":"Manufacturing & Wholesale Goods"
        }
    ],
    "sg:phone":"+1 210 496 3335",
    "sg:postcode":"78232",
    "sg:province":"TX",
    "sg:tags":[
        "equipment",
        "transportation"
    ],
    "wof:name":"W G Henschen Co",
    "wof:placetype":"venue"
},
  "geometry": {"coordinates":[-98.482871,29.572134],"type":"Point"}
}