{
  "type": "Feature",
  "properties": {
    "iso:country":"US",
    "sg:address":"9119 Hwy 6 South Suite 230, Box 130",
    "sg:city":"Missouri City",
    "sg:classifiers":[
        {
            "category":"Professional",
            "subcategory":"Computer Services",
            "type":"Services"
        }
    ],
    "sg:phone":"+1 888 982 5432",
    "sg:postcode":"77459",
    "sg:province":"TX",
    "sg:tags":[
        "wireless",
        "cellular",
        "mobile",
        "billing",
        "bill-auditing",
        "telecom-expense-management",
        "telecom-bill-auditing",
        "wireless-bill-auditing",
        "mobile-market-data",
        "wireless-market-data",
        "wireless-market-research",
        "mobile-market-research"
    ],
    "sg:website":"http://www.myvalidas.com",
    "wof:name":"Validas",
    "wof:placetype":"venue"
},
  "geometry": {"coordinates":[-95.530597,29.529062],"type":"Point"}
}