{
  "type": "Feature",
  "properties": {
    "iso:country":"US",
    "sg:address":"610 Main St",
    "sg:city":"Sulphur Springs",
    "sg:classifiers":[
        {
            "category":"Retail",
            "subcategory":"Auto Repair",
            "type":"Services"
        },
        {
            "category":"Wholesale",
            "subcategory":"Auto Parts",
            "type":"Manufacturing & Wholesale Goods"
        }
    ],
    "sg:phone":"+1 903 885 9349",
    "sg:postcode":"75482",
    "sg:province":"TX",
    "sg:tags":[
        "shaft",
        "drive",
        "automotive",
        "welding"
    ],
    "wof:name":"City Muffler & Drive Shaft",
    "wof:placetype":"venue"
},
  "geometry": {"coordinates":[-95.60771800000001,33.135972],"type":"Point"}
}