{
  "type": "Feature",
  "properties": {
    "iso:country":"US",
    "sg:address":"1305 S Shepherd Dr # A",
    "sg:city":"Houston",
    "sg:classifiers":[
        {
            "category":"Personal",
            "subcategory":"Nail Salon",
            "type":"Services"
        }
    ],
    "sg:phone":"+1 713 529 5692",
    "sg:postcode":"77019",
    "sg:province":"TX",
    "sg:website":"www.avalonnail.com",
    "wof:name":"Avalon Nail Salon",
    "wof:placetype":"venue"
},
  "geometry": {"coordinates":[-95.4104,29.7549],"type":"Point"}
}