{
  "type": "Feature",
  "properties": {
    "iso:country":"US",
    "sg:address":"4017 S Jackson St",
    "sg:city":"Amarillo",
    "sg:classifiers":[
        {
            "category":"Shopping",
            "type":"Retail Goods"
        }
    ],
    "sg:phone":"+1 806 342 0100",
    "sg:postcode":"79110",
    "sg:province":"TX",
    "sg:tags":[
        "merchandise"
    ],
    "wof:name":"Jams Mini Mart",
    "wof:placetype":"venue"
},
  "geometry": {"coordinates":[-101.8455,35.171435],"type":"Point"}
}