{
  "type": "Feature",
  "properties": {
    "iso:country":"US",
    "sg:address":"4342 Gloster Rd",
    "sg:city":"Dallas",
    "sg:classifiers":[
        {
            "category":"Professional",
            "type":"Services"
        }
    ],
    "sg:phone":"+1 214 358 6840",
    "sg:postcode":"75220",
    "sg:province":"TX",
    "sg:tags":[
        "establishment"
    ],
    "wof:name":"Echange Management LLC",
    "wof:placetype":"venue"
},
  "geometry": {"coordinates":[-96.836625,32.868671],"type":"Point"}
}