{
  "type": "Feature",
  "properties": {
    "iso:country":"US",
    "sg:address":"2915 Downing St",
    "sg:city":"Pearland",
    "sg:classifiers":[
        {
            "category":"Professional",
            "type":"Services"
        }
    ],
    "sg:phone":"+1 281 997 2895",
    "sg:postcode":"77581",
    "sg:province":"TX",
    "wof:name":"Jam Services",
    "wof:placetype":"venue"
},
  "geometry": {"coordinates":[-95.259292,29.566435],"type":"Point"}
}