{
  "type": "Feature",
  "properties": {
    "iso:country":"US",
    "sg:address":"2806 Trail Dr",
    "sg:city":"Denison",
    "sg:classifiers":[
        {
            "category":"Personal",
            "subcategory":"Beauty Salon",
            "type":"Services"
        }
    ],
    "sg:phone":"+1 903 465 1091",
    "sg:postcode":"75020",
    "sg:province":"TX",
    "wof:name":"Gina's Salon",
    "wof:placetype":"venue"
},
  "geometry": {"coordinates":[-96.58273800000001,33.731267],"type":"Point"}
}