{
  "type": "Feature",
  "properties": {
    "iso:country":"US",
    "sg:address":"2737 N Longhorn Trl",
    "sg:city":"Pharr",
    "sg:classifiers":[
        {
            "category":"Organizations",
            "subcategory":"Religious Organization",
            "type":"Services"
        }
    ],
    "sg:phone":"+1 956 702 1050",
    "sg:postcode":"78577",
    "sg:province":"TX",
    "sg:tags":[
        "church"
    ],
    "wof:name":"Centro Cristiano Rey De Reyes",
    "wof:placetype":"venue"
},
  "geometry": {"coordinates":[-98.188734,26.219265],"type":"Point"}
}