{
  "type": "Feature",
  "properties": {
    "iso:country":"US",
    "sg:address":"1314 Beach Blvd",
    "sg:city":"Port Isabel",
    "sg:classifiers":[
        {
            "category":"Building & Trades",
            "subcategory":"Construction",
            "type":"Services"
        }
    ],
    "sg:phone":"+1 956 943 7031",
    "sg:postcode":"78578",
    "sg:province":"TX",
    "sg:tags":[
        "general",
        "contractor"
    ],
    "sg:website":"www.marenco.com",
    "wof:name":"Marenco Inc",
    "wof:placetype":"venue"
},
  "geometry": {"coordinates":[-97.295367,26.105718],"type":"Point"}
}