{
  "type": "Feature",
  "properties": {
    "iso:country":"US",
    "sg:address":"717 Greenville Rd",
    "sg:city":"Mc Kinney",
    "sg:classifiers":[
        {
            "category":"Health Services",
            "subcategory":"Doctor",
            "type":"Services"
        }
    ],
    "sg:phone":"+1 972 727 5771",
    "sg:postcode":"75069",
    "sg:province":"TX",
    "sg:tags":[
        "medical"
    ],
    "wof:name":"William R Merritt MD",
    "wof:placetype":"venue"
},
  "geometry": {"coordinates":[-96.610145,33.197298],"type":"Point"}
}