{
  "type": "Feature",
  "properties": {
    "iso:country":"US",
    "sg:address":"9894 Bissonnet St",
    "sg:city":"Houston",
    "sg:classifiers":[
        {
            "category":"Wholesale",
            "subcategory":"Metals & Minerals",
            "type":"Manufacturing & Wholesale Goods"
        }
    ],
    "sg:phone":"+1 713 977 5160",
    "sg:postcode":"77036",
    "sg:province":"TX",
    "sg:tags":[
        "chemical",
        "import",
        "export"
    ],
    "wof:name":"Unibar Corporation",
    "wof:placetype":"venue"
},
  "geometry": {"coordinates":[-95.55294600000001,29.675218],"type":"Point"}
}