{
  "type": "Feature",
  "properties": {
    "iso:country":"US",
    "sg:address":"641 Cupples Rd",
    "sg:city":"San Antonio",
    "sg:classifiers":[
        {
            "category":"Restaurant",
            "type":"Food & Drink"
        }
    ],
    "sg:phone":"+1 210 433 0488",
    "sg:postcode":"78237",
    "sg:province":"TX",
    "wof:name":"Cristina's Kitchen",
    "wof:placetype":"venue"
},
  "geometry": {"coordinates":[-98.548061,29.407237],"type":"Point"}
}