{
  "type": "Feature",
  "properties": {
    "iso:country":"US",
    "sg:address":"14280 Montana Ave",
    "sg:city":"El Paso",
    "sg:classifiers":[
        {
            "category":"Freight",
            "type":"Transportation"
        }
    ],
    "sg:phone":"+1 915 856 3666",
    "sg:postcode":"79938",
    "sg:province":"TX",
    "sg:tags":[
        "storage"
    ],
    "wof:name":"Transmaritime Inc",
    "wof:placetype":"venue"
},
  "geometry": {"coordinates":[-106.186166,31.817314],"type":"Point"}
}