{
  "type": "Feature",
  "properties": {
    "iso:country":"US",
    "sg:address":"3900 Preston Meadow Dr",
    "sg:city":"Plano",
    "sg:classifiers":[
        {
            "category":"Education",
            "subcategory":"School",
            "type":"Public Place"
        }
    ],
    "sg:phone":"+1 972 519 8828",
    "sg:postcode":"75093",
    "sg:province":"TX",
    "sg:tags":[
        "elementary"
    ],
    "wof:name":"Daffron Elementary School",
    "wof:placetype":"venue"
},
  "geometry": {"coordinates":[-96.78003099999999,33.04844],"type":"Point"}
}