{
  "type": "Feature",
  "properties": {
    "iso:country":"US",
    "sg:address":"302 Dove Creek",
    "sg:city":"Mc Kinney",
    "sg:classifiers":[
        {
            "category":"Shopping",
            "subcategory":"Used Merchandise",
            "type":"Retail Goods"
        }
    ],
    "sg:phone":"+1 972 276 5875",
    "sg:postcode":"75071",
    "sg:province":"TX",
    "wof:name":"M&J Antiques",
    "wof:placetype":"venue"
},
  "geometry": {"coordinates":[-96.564449,33.263958],"type":"Point"}
}