{
  "type": "Feature",
  "properties": {
    "iso:country":"US",
    "sg:address":"2429 Northcrest Dr",
    "sg:city":"Plano",
    "sg:classifiers":[
        {
            "category":"Arena",
            "subcategory":"Sports Club",
            "type":"Entertainment"
        }
    ],
    "sg:phone":"+1 972 423 0606",
    "sg:postcode":"75075",
    "sg:province":"TX",
    "wof:name":"Plano Destiny Softball Club",
    "wof:placetype":"venue"
},
  "geometry": {"coordinates":[-96.739079,33.00968],"type":"Point"}
}