{
  "type": "Feature",
  "properties": {
    "iso:country":"US",
    "sg:address":"1501 E Mockingbird Ln",
    "sg:city":"Victoria",
    "sg:classifiers":[
        {
            "category":"Building & Trades",
            "subcategory":"Landscaping Services",
            "type":"Services"
        }
    ],
    "sg:phone":"+1 361 573 2901",
    "sg:postcode":"77904",
    "sg:province":"TX",
    "wof:name":"Mortgages Direct",
    "wof:placetype":"venue"
},
  "geometry": {"coordinates":[-96.99129499999999,28.835884],"type":"Point"}
}