{
  "type": "Feature",
  "properties": {
    "iso:country":"US",
    "sg:address":"4766 Beechnut St",
    "sg:city":"Houston",
    "sg:classifiers":[
        {
            "category":"Shopping",
            "type":"Retail Goods"
        }
    ],
    "sg:phone":"+1 713 669 0117",
    "sg:postcode":"77096",
    "sg:province":"TX",
    "sg:tags":[
        "merchandise"
    ],
    "wof:name":"Beltone Hearing Aid",
    "wof:placetype":"venue"
},
  "geometry": {"coordinates":[-95.461055,29.689292],"type":"Point"}
}