{
  "type": "Feature",
  "properties": {
    "iso:country":"US",
    "sg:address":"325 N Prairie Ave Paul Ste. 4500",
    "sg:city":"Dallas",
    "sg:classifiers":[
        {
            "category":"Professional",
            "subcategory":"Lawyer & Legal Services",
            "type":"Services"
        }
    ],
    "sg:phone":"+1 214 580 2555",
    "sg:postcode":"75246",
    "sg:province":"TX",
    "sg:tags":[
        "attorney",
        "law",
        "personal",
        "practice",
        "commercial",
        "injury",
        "bankruptcy"
    ],
    "sg:website":"http://www.ghblawyers.com",
    "wof:name":"Gregory H Bevel - Attorney At Law",
    "wof:placetype":"venue"
},
  "geometry": {"coordinates":[-96.766136,32.795589],"type":"Point"}
}