{
  "type": "Feature",
  "properties": {
    "iso:country":"US",
    "sg:address":"4000 Whistler Dr",
    "sg:city":"Plano",
    "sg:classifiers":[
        {
            "category":"Autos & Motor Vehicles",
            "subcategory":"Automobile Sales",
            "type":"Retail Goods"
        }
    ],
    "sg:phone":"+1 469 522 0900",
    "sg:postcode":"75093",
    "sg:province":"TX",
    "wof:name":"Sanderson Sales & Marketing",
    "wof:placetype":"venue"
},
  "geometry": {"coordinates":[-96.770511,33.04844],"type":"Point"}
}