{
  "type": "Feature",
  "properties": {
    "iso:country":"US",
    "sg:address":"1380 River Rd",
    "sg:city":"San Marcos",
    "sg:classifiers":[
        {
            "category":"Real Estate",
            "subcategory":"Real Estate Agent",
            "type":"Services"
        }
    ],
    "sg:phone":"+1 512 754 6253",
    "sg:postcode":"78666",
    "sg:province":"TX",
    "wof:name":"Garza Real Estate",
    "wof:placetype":"venue"
},
  "geometry": {"coordinates":[-97.916821,29.877234],"type":"Point"}
}