{
  "type": "Feature",
  "properties": {
    "iso:country":"US",
    "sg:address":"3401 Montana Ave",
    "sg:city":"El Paso",
    "sg:classifiers":[
        {
            "category":"Shopping",
            "type":"Retail Goods"
        }
    ],
    "sg:phone":"+1 915 564 5923",
    "sg:postcode":"79903",
    "sg:province":"TX",
    "sg:tags":[
        "breast",
        "artificial"
    ],
    "wof:name":"Your Image Boutique Inc",
    "wof:placetype":"venue"
},
  "geometry": {"coordinates":[-106.45235099999999,31.783693],"type":"Point"}
}