{
  "type": "Feature",
  "properties": {
    "iso:country":"US",
    "sg:address":"4509 Kosarek Dr",
    "sg:city":"Corpus Christi",
    "sg:classifiers":[
        {
            "category":"Building & Trades",
            "subcategory":"Construction",
            "type":"Services"
        }
    ],
    "sg:phone":"+1 361 765 8178",
    "sg:postcode":"78415",
    "sg:province":"TX",
    "sg:tags":[
        "house"
    ],
    "wof:name":"Groundup Construction & Remode",
    "wof:placetype":"venue"
},
  "geometry": {"coordinates":[-97.403153,27.732868],"type":"Point"}
}