{
  "type": "Feature",
  "properties": {
    "iso:country":"US",
    "sg:address":"4685 College St",
    "sg:city":"Beaumont",
    "sg:classifiers":[
        {
            "category":"Professional",
            "subcategory":"Engineering",
            "type":"Services"
        }
    ],
    "sg:phone":"+1 409 813 1112",
    "sg:postcode":"77707",
    "sg:province":"TX",
    "sg:tags":[
        "engineer"
    ],
    "wof:name":"Eaton Cutler-Hammer",
    "wof:placetype":"venue"
},
  "geometry": {"coordinates":[-94.14542400000001,30.067936],"type":"Point"}
}