{
  "type": "Feature",
  "properties": {
    "iso:country":"US",
    "sg:address":"1352 W Main St",
    "sg:city":"Lewisville",
    "sg:classifiers":[
        {
            "category":"Home & Garden",
            "subcategory":"Carpets & Floor Coverings",
            "type":"Retail Goods"
        }
    ],
    "sg:phone":"+1 972 436 7077",
    "sg:postcode":"75067",
    "sg:province":"TX",
    "sg:tags":[
        "dealer",
        "rug"
    ],
    "wof:name":"Bruton's Carpet",
    "wof:placetype":"venue"
},
  "geometry": {"coordinates":[-97.031111,33.042086],"type":"Point"}
}