{
  "type": "Feature",
  "properties": {
    "iso:country":"US",
    "sg:address":"14625 FM 1485",
    "sg:city":"Conroe",
    "sg:classifiers":[
        {
            "category":"Cinema",
            "subcategory":"Movie Rental",
            "type":"Entertainment"
        }
    ],
    "sg:phone":"+1 281 689 5347",
    "sg:postcode":"77306",
    "sg:province":"TX",
    "sg:tags":[
        "leasing",
        "video",
        "disc",
        "tape"
    ],
    "wof:name":"Movies On The Go",
    "wof:placetype":"venue"
},
  "geometry": {"coordinates":[-95.299798,30.238111],"type":"Point"}
}