{
  "type": "Feature",
  "properties": {
    "iso:country":"US",
    "sg:address":"3110 W 27th Ave",
    "sg:city":"Amarillo",
    "sg:classifiers":[
        {
            "category":"Real Estate",
            "subcategory":"Real Estate Operator",
            "type":"Services"
        }
    ],
    "sg:phone":"+1 806 358 7491",
    "sg:postcode":"79109",
    "sg:province":"TX",
    "sg:tags":[
        "building",
        "apartment"
    ],
    "wof:name":"Colonial Arms Apartments",
    "wof:placetype":"venue"
},
  "geometry": {"coordinates":[-101.875041,35.183987],"type":"Point"}
}