{
  "type": "Feature",
  "properties": {
    "iso:country":"US",
    "sg:address":"112 Ravenwood St",
    "sg:city":"Henderson",
    "sg:classifiers":[
        {
            "category":"Travel",
            "subcategory":"Hotels & Motels",
            "type":"Entertainment"
        }
    ],
    "sg:phone":"+1 903 657 9447",
    "sg:postcode":"75654",
    "sg:province":"TX",
    "sg:tags":[
        "operation"
    ],
    "wof:name":"Turning Tides & Co Inc",
    "wof:placetype":"venue"
},
  "geometry": {"coordinates":[-94.827524,32.148187],"type":"Point"}
}