{
  "type": "Feature",
  "properties": {
    "iso:country":"US",
    "sg:address":"2434 Westpine Rd",
    "sg:city":"Beaumont",
    "sg:classifiers":[
        {
            "category":"Freight",
            "type":"Transportation"
        }
    ],
    "sg:phone":"+1 409 866 6200",
    "sg:postcode":"77713",
    "sg:province":"TX",
    "sg:tags":[
        "general"
    ],
    "wof:name":"Universal Whle",
    "wof:placetype":"venue"
},
  "geometry": {"coordinates":[-94.251165,30.049619],"type":"Point"}
}