{
  "type": "Feature",
  "properties": {
    "iso:country":"US",
    "sg:address":"525 N Locust St",
    "sg:city":"Denton",
    "sg:classifiers":[
        {
            "category":"Professional",
            "subcategory":"Lawyer & Legal Services",
            "type":"Services"
        }
    ],
    "sg:phone":"+1 940 565 9777",
    "sg:postcode":"76201",
    "sg:province":"TX",
    "sg:tags":[
        "attorney"
    ],
    "wof:name":"Russell Welch",
    "wof:placetype":"venue"
},
  "geometry": {"coordinates":[-97.13245000000001,33.218439],"type":"Point"}
}