{
  "type": "Feature",
  "properties": {
    "iso:country":"US",
    "sg:address":"2969 Nacogdoches Rd",
    "sg:city":"San Antonio",
    "sg:classifiers":[
        {
            "category":"Farming",
            "subcategory":"Livestock Farm",
            "type":"Manufacturing & Wholesale Goods"
        },
        {
            "category":"Banks & Credit Unions",
            "subcategory":"Investment Brokerage",
            "type":"Services"
        }
    ],
    "sg:phone":"+1 210 828 9289",
    "sg:postcode":"78217",
    "sg:province":"TX",
    "sg:tags":[
        "ranch",
        "gas",
        "oil",
        "lease"
    ],
    "wof:name":"Gates Mineral Company",
    "wof:placetype":"venue"
},
  "geometry": {"coordinates":[-98.43935399999999,29.526148],"type":"Point"}
}