{
  "type": "Feature",
  "properties": {
    "iso:country":"US",
    "sg:address":"9712 Summer Dr",
    "sg:city":"Frisco",
    "sg:classifiers":[
        {
            "category":"Professional",
            "subcategory":"Advertising",
            "type":"Services"
        }
    ],
    "sg:phone":"+1 972 712 4235",
    "sg:postcode":"75035",
    "sg:province":"TX",
    "sg:tags":[
        "distribution"
    ],
    "wof:name":"Wholesale Distributors",
    "wof:placetype":"venue"
},
  "geometry": {"coordinates":[-96.797363,33.132671],"type":"Point"}
}