{
  "type": "Feature",
  "properties": {
    "iso:country":"US",
    "sg:address":"1621 Willow",
    "sg:city":"Austin",
    "sg:classifiers":[
        {
            "category":"Building & Trades",
            "subcategory":"Landscaping Services",
            "type":"Services"
        }
    ],
    "sg:phone":"+1 512 480 8008",
    "sg:postcode":"78702",
    "sg:province":"TX",
    "sg:website":"d-crain.com/",
    "wof:name":"d-crain",
    "wof:placetype":"venue"
},
  "geometry": {"coordinates":[-97.72750600000001,30.256779],"type":"Point"}
}