{
  "type": "Feature",
  "properties": {
    "iso:country":"US",
    "sg:address":"2810 E I- 20",
    "sg:city":"Odessa",
    "sg:classifiers":[
        {
            "category":"Wholesale",
            "subcategory":"Machinery & Supplies",
            "type":"Manufacturing & Wholesale Goods"
        }
    ],
    "sg:phone":"+1 432 337 0444",
    "sg:postcode":"79701",
    "sg:province":"TX",
    "sg:tags":[
        "industrial"
    ],
    "wof:name":"Graco Operations Equipment Yar",
    "wof:placetype":"venue"
},
  "geometry": {"coordinates":[-102.020931,31.997177],"type":"Point"}
}