{
  "type": "Feature",
  "properties": {
    "iso:country":"US",
    "sg:address":"1500 Ullrich Ave",
    "sg:city":"Austin",
    "sg:classifiers":[
        {
            "category":"Manufacturing",
            "subcategory":"Signs",
            "type":"Manufacturing & Wholesale Goods"
        }
    ],
    "sg:phone":"+1 512 454 7423",
    "sg:postcode":"78756",
    "sg:province":"TX",
    "wof:name":"Austin Adver-Sign",
    "wof:placetype":"venue"
},
  "geometry": {"coordinates":[-97.7342,30.331146],"type":"Point"}
}