{
  "type": "Feature",
  "properties": {
    "iso:country":"US",
    "sg:address":"150 White St",
    "sg:city":"Longview",
    "sg:classifiers":[
        {
            "category":"Shopping",
            "subcategory":"Gifts & Souvenirs",
            "type":"Retail Goods"
        }
    ],
    "sg:phone":"+1 903 643 7955",
    "sg:postcode":"75604",
    "sg:province":"TX",
    "wof:name":"Ds Arts & Crafts & Gifts",
    "wof:placetype":"venue"
},
  "geometry": {"coordinates":[-94.898213,32.528144],"type":"Point"}
}