{
  "type": "Feature",
  "properties": {
    "iso:country":"US",
    "sg:address":"2230 High Point Cir",
    "sg:city":"Carrollton",
    "sg:classifiers":[
        {
            "category":"Banks & Credit Unions",
            "subcategory":"Financial Services",
            "type":"Services"
        }
    ],
    "sg:phone":"+1 972 306 1541",
    "sg:postcode":"75007",
    "sg:province":"TX",
    "sg:tags":[
        "company",
        "holding"
    ],
    "wof:name":"Munivalve Holdings LLC",
    "wof:placetype":"venue"
},
  "geometry": {"coordinates":[-96.85870799999999,33.021705],"type":"Point"}
}