{
  "type": "Feature",
  "properties": {
    "iso:country":"US",
    "sg:address":"32640 FM 3351",
    "sg:city":"Boerne",
    "sg:classifiers":[
        {
            "category":"Retail",
            "subcategory":"Veterinary Services",
            "type":"Services"
        }
    ],
    "sg:phone":"+1 830 336 3600",
    "sg:postcode":"78006",
    "sg:province":"TX",
    "wof:name":"David M Dutton",
    "wof:placetype":"venue"
},
  "geometry": {"coordinates":[-98.60141299999999,29.778464],"type":"Point"}
}