{
  "type": "Feature",
  "properties": {
    "iso:country":"US",
    "sg:address":"783 Johnson Dr",
    "sg:city":"Kerrville",
    "sg:classifiers":[
        {
            "category":"Building & Trades",
            "subcategory":"Construction",
            "type":"Services"
        }
    ],
    "sg:phone":"+1 830 634 2395",
    "sg:postcode":"78028",
    "sg:province":"TX",
    "sg:tags":[
        "excavation",
        "grading",
        "contractor"
    ],
    "wof:name":"Clint Reeves",
    "wof:placetype":"venue"
},
  "geometry": {"coordinates":[-99.08011399999999,29.979796],"type":"Point"}
}