{
  "type": "Feature",
  "properties": {
    "iso:country":"US",
    "sg:address":"3919 Crescent Dr",
    "sg:city":"Granbury",
    "sg:classifiers":[
        {
            "category":"Farming",
            "subcategory":"Farm & Veterinary Services",
            "type":"Manufacturing & Wholesale Goods"
        }
    ],
    "sg:phone":"+1 817 326 3616",
    "sg:postcode":"76049",
    "sg:province":"TX",
    "sg:tags":[
        "management"
    ],
    "wof:name":"Rim Ranch Rocky Management",
    "wof:placetype":"venue"
},
  "geometry": {"coordinates":[-97.683201,32.426359],"type":"Point"}
}