{
  "type": "Feature",
  "properties": {
    "iso:country":"US",
    "sg:address":"715 Culver St",
    "sg:city":"Commerce",
    "sg:classifiers":[
        {
            "category":"Health Services",
            "subcategory":"Dentist",
            "type":"Services"
        }
    ],
    "sg:phone":"+1 903 886 3081",
    "sg:postcode":"75428",
    "sg:province":"TX",
    "wof:name":"Cozart General Dentistry",
    "wof:placetype":"venue"
},
  "geometry": {"coordinates":[-95.891876,33.236008],"type":"Point"}
}