{
  "type": "Feature",
  "properties": {
    "iso:country":"US",
    "sg:address":"7952 Westheimer Rd",
    "sg:city":"Houston",
    "sg:classifiers":[
        {
            "category":"Restaurant",
            "type":"Food & Drink"
        }
    ],
    "sg:menulink":"http://www.allmenus.com/tx/houston/45253-lucky-seven-asian-cuisine/menu/",
    "sg:phone":"+1 713 780 3888",
    "sg:postcode":"77063",
    "sg:province":"TX",
    "sg:tags":[
        "asian",
        "chinese"
    ],
    "wof:name":"Lucky Seven Asian Cuisine",
    "wof:placetype":"venue"
},
  "geometry": {"coordinates":[-95.507462,29.73762],"type":"Point"}
}