{
  "type": "Feature",
  "properties": {
    "iso:country":"US",
    "sg:address":"1307 Austin Dr",
    "sg:city":"West Columbia",
    "sg:classifiers":[
        {
            "category":"Wholesale",
            "subcategory":"Electrical",
            "type":"Manufacturing & Wholesale Goods"
        }
    ],
    "sg:phone":"+1 979 345 2007",
    "sg:postcode":"77486",
    "sg:province":"TX",
    "sg:tags":[
        "equipment"
    ],
    "wof:name":"K & A Fire Safety",
    "wof:placetype":"venue"
},
  "geometry": {"coordinates":[-95.712682,29.1707],"type":"Point"}
}