{
  "type": "Feature",
  "properties": {
    "iso:country":"US",
    "sg:address":"3917 Forest Ln",
    "sg:city":"Garland",
    "sg:classifiers":[
        {
            "category":"Wholesale",
            "subcategory":"Machinery & Supplies",
            "type":"Manufacturing & Wholesale Goods"
        }
    ],
    "sg:phone":"+1 972 272 0457",
    "sg:postcode":"75042",
    "sg:province":"TX",
    "sg:tags":[
        "medical-cylinder",
        "bulk",
        "gas-industrial"
    ],
    "sg:website":"http://www.airgas.com",
    "wof:name":"Airgas",
    "wof:placetype":"venue"
},
  "geometry": {"coordinates":[-96.68975399999999,32.909231],"type":"Point"}
}