{
  "type": "Feature",
  "properties": {
    "iso:country":"US",
    "sg:address":"1250 Eldridge Pkwy",
    "sg:city":"Houston",
    "sg:phone":"+1 281 496 7600",
    "sg:postcode":"77077",
    "sg:province":"TX",
    "wof:name":"Petit Cafe",
    "wof:placetype":"venue"
},
  "geometry": {"coordinates":[-95.62535,29.765054],"type":"Point"}
}