{
  "type": "Feature",
  "properties": {
    "iso:country":"US",
    "sg:address":"2313 SW Military Dr",
    "sg:city":"San Antonio",
    "sg:classifiers":[
        {
            "category":"Shopping",
            "subcategory":"Department Store",
            "type":"Retail Goods"
        }
    ],
    "sg:phone":"+1 210 922 7155",
    "sg:postcode":"78224",
    "sg:province":"TX",
    "sg:tags":[
        "shop"
    ],
    "sg:website":"www.dollartree.com",
    "wof:name":"Dollar Tree",
    "wof:placetype":"venue"
},
  "geometry": {"coordinates":[-98.530789,29.35673],"type":"Point"}
}