{
  "type": "Feature",
  "properties": {
    "iso:country":"US",
    "sg:address":"5616 Scott Ct",
    "sg:city":"Joshua",
    "sg:classifiers":[
        {
            "category":"Shopping",
            "subcategory":"Used Merchandise",
            "type":"Retail Goods"
        }
    ],
    "sg:phone":"+1 817 558 6357",
    "sg:postcode":"76058",
    "sg:province":"TX",
    "sg:tags":[
        "store"
    ],
    "wof:name":"Booklady Bookstore",
    "wof:placetype":"venue"
},
  "geometry": {"coordinates":[-97.415205,32.459537],"type":"Point"}
}