{
  "type": "Feature",
  "properties": {
    "iso:country":"US",
    "sg:address":"844 FM 93 Spr",
    "sg:city":"Temple",
    "sg:classifiers":[
        {
            "category":"Building & Trades",
            "subcategory":"Construction",
            "type":"Services"
        }
    ],
    "sg:phone":"+1 254 773 1655",
    "sg:postcode":"76502",
    "sg:province":"TX",
    "sg:tags":[
        "home",
        "improvement"
    ],
    "wof:name":"Paul's Siding",
    "wof:placetype":"venue"
},
  "geometry": {"coordinates":[-97.350837,31.028995],"type":"Point"}
}