{
  "type": "Feature",
  "properties": {
    "iso:country":"US",
    "sg:address":"5728 Rittiman Plz",
    "sg:city":"San Antonio",
    "sg:classifiers":[
        {
            "category":"Retail",
            "subcategory":"Car Wash",
            "type":"Services"
        }
    ],
    "sg:phone":"+1 210 262 0977",
    "sg:postcode":"78218",
    "sg:province":"TX",
    "sg:tags":[
        "automobile",
        "detail",
        "clean"
    ],
    "wof:name":"Express Detail",
    "wof:placetype":"venue"
},
  "geometry": {"coordinates":[-98.40607199999999,29.481027],"type":"Point"}
}