{
  "type": "Feature",
  "properties": {
    "iso:country":"US",
    "sg:address":"9227 Reagan Meadow Ct",
    "sg:city":"Houston",
    "sg:classifiers":[
        {
            "category":"Professional",
            "subcategory":"Management & Consulting",
            "type":"Services"
        }
    ],
    "sg:phone":"+1 281 897 8475",
    "sg:postcode":"77064",
    "sg:province":"TX",
    "wof:name":"Dp Marketing Services LLC",
    "wof:placetype":"venue"
},
  "geometry": {"coordinates":[-95.55739199999999,29.932708],"type":"Point"}
}