{
  "type": "Feature",
  "properties": {
    "iso:country":"US",
    "sg:address":"3411 Robertson Rd",
    "sg:city":"Tyler",
    "sg:classifiers":[
        {
            "category":"Real Estate",
            "subcategory":"Real Estate Services",
            "type":"Services"
        },
        {
            "category":"Retail",
            "subcategory":"Laundry & Dry Cleaning",
            "type":"Services"
        },
        {
            "category":"Building & Trades",
            "subcategory":"Cleaning & Sanitation",
            "type":"Services"
        },
        {
            "category":"Home & Garden",
            "subcategory":"Carpets & Floor Coverings",
            "type":"Retail Goods"
        }
    ],
    "sg:phone":"+1 903 597 2381",
    "sg:postcode":"75701",
    "sg:province":"TX",
    "sg:tags":[
        "fire",
        "cleaner",
        "duct",
        "cleaners-water",
        "rug",
        "air",
        "water",
        "extraction",
        "restoration",
        "maintenance",
        "damage",
        "cleaners-interior"
    ],
    "sg:website":"http://www.steamatic.net",
    "wof:name":"Steamatic of East Texas",
    "wof:placetype":"venue"
},
  "geometry": {"coordinates":[-95.336923,32.332954],"type":"Point"}
}