{
  "type": "Feature",
  "properties": {
    "iso:country":"US",
    "sg:address":"3020 Stanley Ave",
    "sg:city":"Fort Worth",
    "sg:classifiers":[
        {
            "category":"Retail",
            "subcategory":"Laundry & Dry Cleaning",
            "type":"Services"
        }
    ],
    "sg:phone":"+1 817 926 4221",
    "sg:postcode":"76110",
    "sg:province":"TX",
    "sg:tags":[
        "personal",
        "mi"
    ],
    "wof:name":"Master Tailor",
    "wof:placetype":"venue"
},
  "geometry": {"coordinates":[-97.346068,32.706401],"type":"Point"}
}