{
  "type": "Feature",
  "properties": {
    "iso:country":"US",
    "sg:address":"3100 N Lamar Blvd",
    "sg:city":"Austin",
    "sg:classifiers":[
        {
            "category":"Building & Trades",
            "subcategory":"Locksmith",
            "type":"Services"
        }
    ],
    "sg:phone":"+1 512 623 1577",
    "sg:postcode":"78705",
    "sg:province":"TX",
    "sg:tags":[
        "lock"
    ],
    "wof:name":"Anytime Any Place Locksmith",
    "wof:placetype":"venue"
},
  "geometry": {"coordinates":[-97.746223,30.30027],"type":"Point"}
}