{
  "type": "Feature",
  "properties": {
    "iso:country":"US",
    "sg:address":"2775 Wilhurt Ave",
    "sg:city":"Dallas",
    "sg:classifiers":[
        {
            "category":"Health Services",
            "subcategory":"Doctor",
            "type":"Services"
        }
    ],
    "sg:phone":"+1 214 372 3123",
    "sg:postcode":"75216",
    "sg:province":"TX",
    "sg:tags":[
        "medical"
    ],
    "wof:name":"Alfred O Morgan",
    "wof:placetype":"venue"
},
  "geometry": {"coordinates":[-96.779111,32.70604],"type":"Point"}
}