{
  "type": "Feature",
  "properties": {
    "iso:country":"US",
    "sg:address":"4202 Primrose Dr",
    "sg:city":"Mc Kinney",
    "sg:classifiers":[
        {
            "category":"Shopping",
            "type":"Retail Goods"
        }
    ],
    "sg:phone":"+1 972 529 1483",
    "sg:postcode":"75070",
    "sg:province":"TX",
    "sg:tags":[
        "merchandise"
    ],
    "wof:name":"Fine Things",
    "wof:placetype":"venue"
},
  "geometry": {"coordinates":[-96.674262,33.166499],"type":"Point"}
}