{
  "type": "Feature",
  "properties": {
    "iso:country":"US",
    "sg:address":"15411 Vantage Pkwy W",
    "sg:city":"Houston",
    "sg:classifiers":[
        {
            "category":"Wholesale",
            "subcategory":"Office Equipment",
            "type":"Manufacturing & Wholesale Goods"
        },
        {
            "category":"Professional",
            "subcategory":"Printing & Photocopies",
            "type":"Services"
        },
        {
            "category":"Shopping",
            "subcategory":"Computers & Home Electronics",
            "type":"Retail Goods"
        }
    ],
    "sg:phone":"+1 281 227 0832",
    "sg:postcode":"77032",
    "sg:province":"TX",
    "sg:tags":[
        "scanning",
        "printer",
        "plotting",
        "supply"
    ],
    "wof:name":"KKP Business Solutions",
    "wof:placetype":"venue"
},
  "geometry": {"coordinates":[-95.36644699999999,29.943464],"type":"Point"}
}