{
  "type": "Feature",
  "properties": {
    "iso:country":"US",
    "sg:address":"700 Main St",
    "sg:city":"Fort Worth",
    "sg:classifiers":[
        {
            "category":"Travel",
            "subcategory":"Travel Agent",
            "type":"Entertainment"
        }
    ],
    "sg:phone":"+1 817 332 6811",
    "sg:postcode":"76102",
    "sg:province":"TX",
    "sg:tags":[
        "agency",
        "bureau"
    ],
    "wof:name":"Main Street Travel & Tours Inc",
    "wof:placetype":"venue"
},
  "geometry": {"coordinates":[-97.32990599999999,32.752673],"type":"Point"}
}