{
  "type": "Feature",
  "properties": {
    "iso:country":"US",
    "sg:address":"1608 Azurite Trl",
    "sg:city":"Plano",
    "sg:classifiers":[
        {
            "category":"Professional",
            "subcategory":"Management & Consulting",
            "type":"Services"
        }
    ],
    "sg:phone":"+1 972 424 1670",
    "sg:postcode":"75075",
    "sg:province":"TX",
    "sg:tags":[
        "marketing",
        "group",
        "interactive"
    ],
    "wof:name":"Performance Group LLC",
    "wof:placetype":"venue"
},
  "geometry": {"coordinates":[-96.73020699999999,33.040414],"type":"Point"}
}