{
  "type": "Feature",
  "properties": {
    "iso:country":"US",
    "sg:address":"217 E Jones St",
    "sg:city":"Dimmitt",
    "sg:classifiers":[
        {
            "category":"Government",
            "subcategory":"Office",
            "type":"Public Place"
        }
    ],
    "sg:phone":"+1 806 647 4492",
    "sg:postcode":"79027",
    "sg:province":"TX",
    "sg:tags":[
        "village"
    ],
    "wof:name":"Dimmitt City Maintenance",
    "wof:placetype":"venue"
},
  "geometry": {"coordinates":[-102.310907,34.549849],"type":"Point"}
}