{
  "type": "Feature",
  "properties": {
    "iso:country":"US",
    "sg:address":"2204 Timberloch Pl",
    "sg:city":"Spring",
    "sg:classifiers":[
        {
            "category":"Autos & Motor Vehicles",
            "subcategory":"Automobile Sales",
            "type":"Retail Goods"
        }
    ],
    "sg:phone":"+1 281 367 8844",
    "sg:postcode":"77380",
    "sg:province":"TX",
    "sg:tags":[
        "car",
        "dealer"
    ],
    "wof:name":"Joe Auto.Com Corporate Hq",
    "wof:placetype":"venue"
},
  "geometry": {"coordinates":[-95.460533,30.158591],"type":"Point"}
}