{
  "type": "Feature",
  "properties": {
    "iso:country":"US",
    "sg:address":"4500 E William Cannon Dr",
    "sg:city":"Austin",
    "sg:classifiers":[
        {
            "category":"Retail",
            "subcategory":"Auto Repair",
            "type":"Services"
        }
    ],
    "sg:phone":"+1 512 707 0668",
    "sg:postcode":"78744",
    "sg:province":"TX",
    "wof:name":"Custom Mechanics",
    "wof:placetype":"venue"
},
  "geometry": {"coordinates":[-97.754925,30.184321],"type":"Point"}
}