{
  "type": "Feature",
  "properties": {
    "iso:country":"US",
    "sg:address":"1132 W Panola St",
    "sg:city":"Carthage",
    "sg:classifiers":[
        {
            "category":"Autos & Motor Vehicles",
            "subcategory":"Automobile Sales",
            "type":"Retail Goods"
        }
    ],
    "sg:phone":"+1 903 693 8188",
    "sg:postcode":"75633",
    "sg:province":"TX",
    "sg:tags":[
        "used"
    ],
    "wof:name":"Pitts Auto Center",
    "wof:placetype":"venue"
},
  "geometry": {"coordinates":[-94.356264,32.158471],"type":"Point"}
}