{
  "type": "Feature",
  "properties": {
    "iso:country":"US",
    "sg:address":"6121 I- 35 Svc Rd N",
    "sg:city":"Austin",
    "sg:classifiers":[
        {
            "category":"Travel",
            "subcategory":"Hotels & Motels",
            "type":"Entertainment"
        }
    ],
    "sg:phone":"+1 512 323 5466",
    "sg:postcode":"78752",
    "sg:province":"TX",
    "sg:tags":[
        "operation",
        "drinking"
    ],
    "wof:name":"Hilton",
    "wof:placetype":"venue"
},
  "geometry": {"coordinates":[-97.705626,30.324907],"type":"Point"}
}