{
  "type": "Feature",
  "properties": {
    "iso:country":"US",
    "sg:address":"1407 Hitchin Ln",
    "sg:city":"Channelview",
    "sg:classifiers":[
        {
            "category":"Communications",
            "type":"Services"
        }
    ],
    "sg:phone":"+1 281 452 0078",
    "sg:postcode":"77530",
    "sg:province":"TX",
    "sg:tags":[
        "communication"
    ],
    "wof:name":"Endless Communications",
    "wof:placetype":"venue"
},
  "geometry": {"coordinates":[-95.139954,29.803383],"type":"Point"}
}