{
  "type": "Feature",
  "properties": {
    "iso:country":"US",
    "sg:address":"715 Lazy Ln",
    "sg:city":"Bryan",
    "sg:classifiers":[
        {
            "category":"Building & Trades",
            "subcategory":"Construction",
            "type":"Services"
        }
    ],
    "sg:phone":"+1 979 846 0393",
    "sg:postcode":"77802",
    "sg:province":"TX",
    "sg:tags":[
        "contractor",
        "con"
    ],
    "wof:name":"Franklin Siding & Construction",
    "wof:placetype":"venue"
},
  "geometry": {"coordinates":[-96.34563,30.639978],"type":"Point"}
}