{
  "type": "Feature",
  "properties": {
    "iso:country":"US",
    "sg:address":"912 State Hwy 25",
    "sg:city":"Electra",
    "sg:classifiers":[
        {
            "category":"Food & Beverages",
            "subcategory":"Groceries & Convenience Stores",
            "type":"Retail Goods"
        }
    ],
    "sg:phone":"+1 940 438 2985",
    "sg:postcode":"76360",
    "sg:province":"TX",
    "wof:name":"Judy Grocery",
    "wof:placetype":"venue"
},
  "geometry": {"coordinates":[-98.91765599999999,34.041301],"type":"Point"}
}