{
  "type": "Feature",
  "properties": {
    "iso:country":"US",
    "sg:address":"1803 Enterprise Ave",
    "sg:city":"League City",
    "sg:classifiers":[
        {
            "category":"Shopping",
            "subcategory":"Jewelry",
            "type":"Retail Goods"
        }
    ],
    "sg:phone":"+1 281 334 2581",
    "sg:postcode":"77573",
    "sg:province":"TX",
    "wof:name":"Gvo Custom Jewelry",
    "wof:placetype":"venue"
},
  "geometry": {"coordinates":[-95.066864,29.549566],"type":"Point"}
}