{
  "type": "Feature",
  "properties": {
    "iso:country":"US",
    "sg:address":"1711 Redondo Ave",
    "sg:city":"Odessa",
    "sg:classifiers":[
        {
            "category":"Real Estate",
            "subcategory":"Real Estate Operator",
            "type":"Services"
        }
    ],
    "sg:phone":"+1 432 381 0715",
    "sg:postcode":"79763",
    "sg:province":"TX",
    "sg:tags":[
        "mobile",
        "home",
        "community"
    ],
    "wof:name":"Western Star Mobile Home Ests",
    "wof:placetype":"venue"
},
  "geometry": {"coordinates":[-102.459661,31.837403],"type":"Point"}
}