{
  "type": "Feature",
  "properties": {
    "iso:country":"US",
    "sg:address":"8536 Glencrest Ln",
    "sg:city":"Dallas",
    "sg:classifiers":[
        {
            "category":"Wholesale",
            "subcategory":"Durable Goods & Equipment",
            "type":"Manufacturing & Wholesale Goods"
        }
    ],
    "sg:phone":"+1 214 350 1299",
    "sg:postcode":"75209",
    "sg:province":"TX",
    "sg:tags":[
        "representative",
        "manufacturer"
    ],
    "wof:name":"Procyon 2 Marketing",
    "wof:placetype":"venue"
},
  "geometry": {"coordinates":[-96.84536900000001,32.855236],"type":"Point"}
}