{
  "type": "Feature",
  "properties": {
    "iso:country":"US",
    "sg:address":"1330 Shores Cir",
    "sg:city":"Rockwall",
    "sg:classifiers":[
        {
            "category":"Banks & Credit Unions",
            "subcategory":"Investment Brokerage",
            "type":"Services"
        }
    ],
    "sg:phone":"+1 972 772 5545",
    "sg:postcode":"75087",
    "sg:province":"TX",
    "sg:tags":[
        "advisory"
    ],
    "wof:name":"Eavenson Harold & Assoc",
    "wof:placetype":"venue"
},
  "geometry": {"coordinates":[-96.47607600000001,32.954593],"type":"Point"}
}