{
  "type": "Feature",
  "properties": {
    "iso:country":"US",
    "sg:address":"9923 Kemp Forest Dr",
    "sg:city":"Houston",
    "sg:classifiers":[
        {
            "category":"Health Services",
            "subcategory":"Doctor",
            "type":"Services"
        }
    ],
    "sg:phone":"+1 713 996 9964",
    "sg:postcode":"77080",
    "sg:province":"TX",
    "wof:name":"Lege Dainey Ph D",
    "wof:placetype":"venue"
},
  "geometry": {"coordinates":[-95.538498,29.826799],"type":"Point"}
}