{
  "type": "Feature",
  "properties": {
    "iso:country":"US",
    "sg:address":"3002 E Pioneer Pkwy",
    "sg:city":"Arlington",
    "sg:classifiers":[
        {
            "category":"Restaurant",
            "type":"Food & Drink"
        }
    ],
    "sg:phone":"+1 817 633 1821",
    "sg:postcode":"76010",
    "sg:province":"TX",
    "wof:name":"Denny's",
    "wof:placetype":"venue"
},
  "geometry": {"coordinates":[-97.053563,32.712131],"type":"Point"}
}