{
  "type": "Feature",
  "properties": {
    "iso:country":"US",
    "sg:address":"101 E Rusk St",
    "sg:city":"Rockwall",
    "sg:classifiers":[
        {
            "category":"Government",
            "subcategory":"Office",
            "type":"Public Place"
        }
    ],
    "sg:phone":"+1 972 882 0290",
    "sg:postcode":"75087",
    "sg:province":"TX",
    "sg:tags":[
        "county",
        "taxation"
    ],
    "wof:name":"Rockwall County Treasurer",
    "wof:placetype":"venue"
},
  "geometry": {"coordinates":[-96.45946000000001,32.931058],"type":"Point"}
}