{
  "type": "Feature",
  "properties": {
    "iso:country":"US",
    "sg:address":"10331 Gulf Fwy",
    "sg:city":"Houston",
    "sg:classifiers":[
        {
            "category":"Retail",
            "subcategory":"Veterinary Services",
            "type":"Services"
        }
    ],
    "sg:phone":"+1 713 941 8460",
    "sg:postcode":"77034",
    "sg:province":"TX",
    "sg:tags":[
        "clinic",
        "emergency"
    ],
    "wof:name":"Animal Emrgncy Clnic Southeast",
    "wof:placetype":"venue"
},
  "geometry": {"coordinates":[-95.245797,29.644892],"type":"Point"}
}