{
  "type": "Feature",
  "properties": {
    "iso:country":"US",
    "sg:address":"918 S Fry Rd",
    "sg:city":"Katy",
    "sg:classifiers":[
        {
            "category":"Coffee & Tea",
            "type":"Food & Drink"
        },
        {
            "category":"Restaurant",
            "type":"Food & Drink"
        }
    ],
    "sg:phone":"+1 281 398 5255",
    "sg:postcode":"77450",
    "sg:province":"TX",
    "sg:tags":[
        "espresso"
    ],
    "wof:name":"Palios Pizza Cafe",
    "wof:placetype":"venue"
},
  "geometry": {"coordinates":[-95.746224,29.726131],"type":"Point"}
}