{
  "type": "Feature",
  "properties": {
    "iso:country":"US",
    "sg:address":"3900 North Fwy",
    "sg:city":"Houston",
    "sg:classifiers":[
        {
            "category":"Wholesale",
            "subcategory":"Office Equipment",
            "type":"Manufacturing & Wholesale Goods"
        }
    ],
    "sg:phone":"+1 713 590 8506",
    "sg:postcode":"77022",
    "sg:province":"TX",
    "sg:tags":[
        "machine",
        "mailing"
    ],
    "wof:name":"Franco Type Postalia Mailing",
    "wof:placetype":"venue"
},
  "geometry": {"coordinates":[-95.378559,29.821732],"type":"Point"}
}