{
  "type": "Feature",
  "properties": {
    "iso:country":"US",
    "sg:address":"610 S Mesa St",
    "sg:city":"El Paso",
    "sg:classifiers":[
        {
            "category":"Wholesale",
            "subcategory":"Poultry",
            "type":"Manufacturing & Wholesale Goods"
        }
    ],
    "sg:phone":"+1 915 532 7746",
    "sg:postcode":"79901",
    "sg:province":"TX",
    "wof:name":"Century 21 Casablanca Realty",
    "wof:placetype":"venue"
},
  "geometry": {"coordinates":[-106.48522800000001,31.753105],"type":"Point"}
}