{
  "type": "Feature",
  "properties": {
    "iso:country":"US",
    "sg:address":"6610 Deer Park Dr",
    "sg:city":"Amarillo",
    "sg:classifiers":[
        {
            "category":"Retail",
            "subcategory":"Repair Shop",
            "type":"Services"
        }
    ],
    "sg:phone":"+1 806 354 8684",
    "sg:postcode":"79124",
    "sg:province":"TX",
    "sg:tags":[
        "refinishing",
        "furniture"
    ],
    "wof:name":"Furniture Medic Inc",
    "wof:placetype":"venue"
},
  "geometry": {"coordinates":[-101.909706,35.215894],"type":"Point"}
}