{
  "type": "Feature",
  "properties": {
    "iso:country":"US",
    "sg:address":"4124 McKnight Rd",
    "sg:city":"Texarkana",
    "sg:classifiers":[
        {
            "category":"Social Services",
            "type":"Services"
        }
    ],
    "sg:phone":"+1 903 334 7261",
    "sg:postcode":"75503",
    "sg:province":"TX",
    "sg:tags":[
        "counselor",
        "marriage",
        "family"
    ],
    "wof:name":"Associated Family Therapists",
    "wof:placetype":"venue"
},
  "geometry": {"coordinates":[-94.10118799999999,33.464676],"type":"Point"}
}