{
  "type": "Feature",
  "properties": {
    "iso:country":"US",
    "sg:address":"11213 Rojas Dr",
    "sg:city":"El Paso",
    "sg:classifiers":[
        {
            "category":"Wholesale",
            "subcategory":"Auto Parts",
            "type":"Manufacturing & Wholesale Goods"
        }
    ],
    "sg:phone":"+1 915 593 8213",
    "sg:postcode":"79935",
    "sg:province":"TX",
    "sg:tags":[
        "equipment",
        "truck"
    ],
    "wof:name":"U-Joints Inc",
    "wof:placetype":"venue"
},
  "geometry": {"coordinates":[-106.328119,31.746756],"type":"Point"}
}