{
  "type": "Feature",
  "properties": {
    "iso:country":"US",
    "sg:address":"13359 N. Hwy 183, Ste. B406",
    "sg:city":"Austin",
    "sg:classifiers":[
        {
            "category":"Home & Garden",
            "subcategory":"Household Appliances",
            "type":"Retail Goods"
        },
        {
            "category":"Wholesale",
            "subcategory":"Machinery & Supplies",
            "type":"Manufacturing & Wholesale Goods"
        },
        {
            "category":"Retail",
            "subcategory":"Repair Shop",
            "type":"Services"
        }
    ],
    "sg:phone":"+1 512 377 6140",
    "sg:postcode":"78750",
    "sg:province":"TX",
    "sg:tags":[
        "major",
        "refinishing",
        "cleaners-household-dealers",
        "dryer",
        "part",
        "vacuum",
        "washer"
    ],
    "wof:name":"Austin Area Home Services",
    "wof:placetype":"venue"
},
  "geometry": {"coordinates":[-97.787796,30.444509],"type":"Point"}
}