{
  "type": "Feature",
  "properties": {
    "iso:country":"US",
    "sg:address":"123 E Baylor St",
    "sg:city":"San Antonio",
    "sg:classifiers":[
        {
            "category":"Building & Trades",
            "subcategory":"Construction",
            "type":"Services"
        }
    ],
    "sg:phone":"+1 210 227 6342",
    "sg:postcode":"78204",
    "sg:province":"TX",
    "sg:tags":[
        "hanging",
        "contractor"
    ],
    "wof:name":"Medina Painting Raymond",
    "wof:placetype":"venue"
},
  "geometry": {"coordinates":[-98.50323,29.398186],"type":"Point"}
}