{
  "type": "Feature",
  "properties": {
    "iso:country":"US",
    "sg:address":"1821 E FM 1187",
    "sg:city":"Aledo",
    "sg:classifiers":[
        {
            "category":"Shopping",
            "subcategory":"Hobbies, Toys, & Games",
            "type":"Retail Goods"
        }
    ],
    "sg:phone":"+1 817 441 9299",
    "sg:postcode":"76008",
    "sg:province":"TX",
    "wof:name":"Unique Etc",
    "wof:placetype":"venue"
},
  "geometry": {"coordinates":[-97.57820599999999,32.672313],"type":"Point"}
}