{
  "type": "Feature",
  "properties": {
    "iso:country":"US",
    "sg:address":"13430 Northwest Fwy",
    "sg:city":"Houston",
    "sg:classifiers":[
        {
            "category":"Professional",
            "subcategory":"Accounting & Tax Preparation",
            "type":"Services"
        }
    ],
    "sg:phone":"+1 409 935 5099",
    "sg:postcode":"77040",
    "sg:province":"TX",
    "sg:tags":[
        "accountant"
    ],
    "wof:name":"Jim Lehmberg & Co PC CPA",
    "wof:placetype":"venue"
},
  "geometry": {"coordinates":[-95.508957,29.851239],"type":"Point"}
}