{
  "type": "Feature",
  "properties": {
    "iso:country":"US",
    "sg:address":"18167 Brooknoll Dr",
    "sg:city":"Houston",
    "sg:classifiers":[
        {
            "category":"Professional",
            "subcategory":"Management & Consulting",
            "type":"Services"
        }
    ],
    "sg:phone":"+1 281 550 3560",
    "sg:postcode":"77084",
    "sg:province":"TX",
    "sg:tags":[
        "consultant",
        "educational"
    ],
    "wof:name":"C J Bibus Consulting",
    "wof:placetype":"venue"
},
  "geometry": {"coordinates":[-95.680533,29.852528],"type":"Point"}
}