{
  "type": "Feature",
  "properties": {
    "iso:country":"US",
    "sg:address":"1001 N 7th St",
    "sg:city":"Haskell",
    "sg:classifiers":[
        {
            "category":"Farming",
            "subcategory":"Livestock Farm",
            "type":"Manufacturing & Wholesale Goods"
        }
    ],
    "sg:phone":"+1 940 864 3290",
    "sg:postcode":"79521",
    "sg:province":"TX",
    "sg:tags":[
        "beef",
        "feedlot",
        "cattle"
    ],
    "wof:name":"Briscoe Cattle Exchange Co",
    "wof:placetype":"venue"
},
  "geometry": {"coordinates":[-99.740781,33.163213],"type":"Point"}
}