{
  "type": "Feature",
  "properties": {
    "iso:country":"US",
    "sg:address":"7002 Laughlin Dr",
    "sg:city":"Missouri City",
    "sg:classifiers":[
        {
            "category":"Sports & Exercise",
            "subcategory":"Sports Center",
            "type":"Entertainment"
        }
    ],
    "sg:phone":"+1 281 437 1930",
    "sg:postcode":"77489",
    "sg:province":"TX",
    "sg:tags":[
        "amateur",
        "team"
    ],
    "wof:name":"Briargate Community Improvement Association",
    "wof:placetype":"venue"
},
  "geometry": {"coordinates":[-95.489799,29.5961],"type":"Point"}
}