{
  "type": "Feature",
  "properties": {
    "iso:country":"US",
    "sg:address":"8414 Old McGregor Rd",
    "sg:city":"Waco",
    "sg:classifiers":[
        {
            "category":"Communications",
            "subcategory":"Film & Video Production",
            "type":"Services"
        },
        {
            "category":"Professional",
            "subcategory":"Management & Consulting",
            "type":"Services"
        }
    ],
    "sg:phone":"+1 254 776 5745",
    "sg:postcode":"76712",
    "sg:province":"TX",
    "sg:tags":[
        "motion",
        "marketing",
        "program"
    ],
    "wof:name":"Health Marketing Consultants",
    "wof:placetype":"venue"
},
  "geometry": {"coordinates":[-97.214778,31.497357],"type":"Point"}
}