{
  "type": "Feature",
  "properties": {
    "iso:country":"US",
    "sg:address":"1701 W Euless Blvd",
    "sg:city":"Euless",
    "sg:classifiers":[
        {
            "category":"Industrial Area",
            "type":"Public Place"
        }
    ],
    "sg:phone":"+1 817 571 6070",
    "sg:postcode":"76040",
    "sg:province":"TX",
    "sg:tags":[
        "development"
    ],
    "wof:name":"The Colfax Group",
    "wof:placetype":"venue"
},
  "geometry": {"coordinates":[-97.110283,32.824902],"type":"Point"}
}