{
  "type": "Feature",
  "properties": {
    "iso:country":"US",
    "sg:address":"11016 S Pipeline Rd",
    "sg:city":"Euless",
    "sg:classifiers":[
        {
            "category":"Building & Trades",
            "subcategory":"Construction",
            "type":"Services"
        }
    ],
    "sg:phone":"+1 817 835 0964",
    "sg:postcode":"76040",
    "sg:province":"TX",
    "sg:tags":[
        "contractor"
    ],
    "wof:name":"Erws Georgia LLC",
    "wof:placetype":"venue"
},
  "geometry": {"coordinates":[-97.1327,32.814637],"type":"Point"}
}