{
  "type": "Feature",
  "properties": {
    "iso:country":"US",
    "sg:address":"223 S Randell St",
    "sg:city":"Bronte",
    "sg:classifiers":[
        {
            "category":"Shopping",
            "subcategory":"Beauty & Cosmetics",
            "type":"Retail Goods"
        }
    ],
    "sg:phone":"+1 325 473 6008",
    "sg:postcode":"76933",
    "sg:province":"TX",
    "sg:tags":[
        "merchandise"
    ],
    "wof:name":"Riche Karen",
    "wof:placetype":"venue"
},
  "geometry": {"coordinates":[-100.28971199999999,31.885994],"type":"Point"}
}