{
  "type": "Feature",
  "properties": {
    "iso:country":"US",
    "sg:address":"138 W Lamar St",
    "sg:city":"Jasper",
    "sg:classifiers":[
        {
            "category":"Professional",
            "subcategory":"Management & Consulting",
            "type":"Services"
        }
    ],
    "sg:phone":"+1 409 489 0100",
    "sg:postcode":"75951",
    "sg:province":"TX",
    "wof:name":"N T Schofield Office",
    "wof:placetype":"venue"
},
  "geometry": {"coordinates":[-94.001068,30.921911],"type":"Point"}
}