{
  "type": "Feature",
  "properties": {
    "iso:country":"US",
    "sg:address":"312 W Sabine St",
    "sg:city":"Carthage",
    "sg:classifiers":[
        {
            "category":"Professional",
            "subcategory":"Business Services",
            "type":"Services"
        }
    ],
    "sg:phone":"+1 903 693 2206",
    "sg:postcode":"75633",
    "sg:province":"TX",
    "sg:tags":[
        "holding"
    ],
    "wof:name":"Excel Holding, Inc.",
    "wof:placetype":"venue"
},
  "geometry": {"coordinates":[-94.34042599999999,32.156295],"type":"Point"}
}