{
  "type": "Feature",
  "properties": {
    "iso:country":"US",
    "sg:address":"402 E Santa Rosa St",
    "sg:city":"Victoria",
    "sg:classifiers":[
        {
            "category":"Organizations",
            "subcategory":"Religious Organization",
            "type":"Services"
        }
    ],
    "sg:phone":"+1 361 573 4484",
    "sg:postcode":"77901",
    "sg:province":"TX",
    "sg:tags":[
        "church"
    ],
    "wof:name":"Nicea Presbyterian Church",
    "wof:placetype":"venue"
},
  "geometry": {"coordinates":[-97.00254200000001,28.797106],"type":"Point"}
}