{
  "type": "Feature",
  "properties": {
    "iso:country":"US",
    "sg:address":"2608 Bunker Hill",
    "sg:city":"Mc Kinney",
    "sg:classifiers":[
        {
            "category":"Professional",
            "subcategory":"Business Services",
            "type":"Services"
        }
    ],
    "sg:phone":"+1 972 542 1330",
    "sg:postcode":"75070",
    "sg:province":"TX",
    "wof:name":"Crow Partners GP Inc",
    "wof:placetype":"venue"
},
  "geometry": {"coordinates":[-96.649784,33.168041],"type":"Point"}
}