{
  "type": "Feature",
  "properties": {
    "iso:country":"US",
    "sg:address":"14559 Memorial Dr",
    "sg:city":"Houston",
    "sg:classifiers":[
        {
            "category":"Shopping",
            "subcategory":"Clothing, Apparel, & Fashions",
            "type":"Retail Goods"
        }
    ],
    "sg:phone":"+1 281 293 0437",
    "sg:postcode":"77079",
    "sg:province":"TX",
    "sg:tags":[
        "dressmaker"
    ],
    "wof:name":"Alterations-1",
    "wof:placetype":"venue"
},
  "geometry": {"coordinates":[-95.60468400000001,29.770051],"type":"Point"}
}