{
  "type": "Feature",
  "properties": {
    "iso:country":"US",
    "sg:address":"7550 Drouet St",
    "sg:city":"Houston",
    "sg:classifiers":[
        {
            "category":"Professional",
            "type":"Services"
        }
    ],
    "sg:phone":"+1 713 454 1356",
    "sg:postcode":"77061",
    "sg:province":"TX",
    "wof:name":"Williams Tresa",
    "wof:placetype":"venue"
},
  "geometry": {"coordinates":[-95.287193,29.666331],"type":"Point"}
}