{
  "type": "Feature",
  "properties": {
    "iso:country":"US",
    "sg:address":"701 Longspur Blvd W",
    "sg:city":"Austin",
    "sg:classifiers":[
        {
            "category":"Travel",
            "subcategory":"Travel Agent",
            "type":"Entertainment"
        }
    ],
    "sg:phone":"+1 512 821 3805",
    "sg:postcode":"78753",
    "sg:province":"TX",
    "sg:tags":[
        "agency"
    ],
    "wof:name":"Mandela Travel",
    "wof:placetype":"venue"
},
  "geometry": {"coordinates":[-97.69393100000001,30.367032],"type":"Point"}
}