{
  "type": "Feature",
  "properties": {
    "iso:country":"US",
    "sg:address":"4431 Mount Vernon St",
    "sg:city":"Houston",
    "sg:classifiers":[
        {
            "category":"Wholesale",
            "subcategory":"Books, Periodicals, & Newspapers",
            "type":"Manufacturing & Wholesale Goods"
        }
    ],
    "sg:phone":"+1 713 528 4395",
    "sg:postcode":"77006",
    "sg:province":"TX",
    "wof:name":"Scholars Book Co",
    "wof:placetype":"venue"
},
  "geometry": {"coordinates":[-95.393593,29.732964],"type":"Point"}
}