{
  "type": "Feature",
  "properties": {
    "iso:country":"US",
    "sg:address":"13523 Orchard Ridge Dr",
    "sg:city":"San Antonio",
    "sg:classifiers":[
        {
            "category":"Mining & Drilling",
            "type":"Manufacturing & Wholesale Goods"
        }
    ],
    "sg:phone":"+1 210 764 0955",
    "sg:postcode":"78231",
    "sg:province":"TX",
    "sg:tags":[
        "gas",
        "oil",
        "exploration"
    ],
    "wof:name":"Veritas Energy LLC",
    "wof:placetype":"venue"
},
  "geometry": {"coordinates":[-98.530935,29.56401],"type":"Point"}
}