{
  "type": "Feature",
  "properties": {
    "iso:country":"US",
    "sg:address":"13030 Northborough Dr",
    "sg:city":"Houston",
    "sg:classifiers":[
        {
            "category":"Social Services",
            "type":"Services"
        }
    ],
    "sg:phone":"+1 281 875 3893",
    "sg:postcode":"77067",
    "sg:province":"TX",
    "wof:name":"Shelise Day Care",
    "wof:placetype":"venue"
},
  "geometry": {"coordinates":[-95.423091,29.957071],"type":"Point"}
}