{
  "type": "Feature",
  "properties": {
    "iso:country":"US",
    "sg:address":"603 E Mesquite Ln",
    "sg:city":"Victoria",
    "sg:classifiers":[
        {
            "category":"Shopping",
            "subcategory":"Clothing, Apparel, & Fashions",
            "type":"Retail Goods"
        }
    ],
    "sg:phone":"+1 361 573 2878",
    "sg:postcode":"77901",
    "sg:province":"TX",
    "sg:tags":[
        "ready",
        "to",
        "wear",
        "accessory"
    ],
    "wof:name":"Antique Boutique",
    "wof:placetype":"venue"
},
  "geometry": {"coordinates":[-96.999526,28.824383],"type":"Point"}
}