{
  "type": "Feature",
  "properties": {
    "iso:country":"US",
    "sg:address":"2206 Ventnor Ct",
    "sg:city":"Arlington",
    "sg:classifiers":[
        {
            "category":"Building & Trades",
            "subcategory":"Construction",
            "type":"Services"
        }
    ],
    "sg:phone":"+1 817 261 4999",
    "sg:postcode":"76011",
    "sg:province":"TX",
    "sg:tags":[
        "contractor"
    ],
    "wof:name":"Texas Star Masonry",
    "wof:placetype":"venue"
},
  "geometry": {"coordinates":[-97.089232,32.771167],"type":"Point"}
}