{
  "type": "Feature",
  "properties": {
    "iso:country":"US",
    "sg:address":"6223 US Hwy 87",
    "sg:city":"San Antonio",
    "sg:classifiers":[
        {
            "category":"Building & Trades",
            "subcategory":"Construction",
            "type":"Services"
        }
    ],
    "sg:phone":"+1 210 532 7100",
    "sg:postcode":"78222",
    "sg:province":"TX",
    "sg:tags":[
        "roofing",
        "contractor"
    ],
    "wof:name":"Kelly Roofing Inc",
    "wof:placetype":"venue"
},
  "geometry": {"coordinates":[-98.365011,29.393763],"type":"Point"}
}