{
  "type": "Feature",
  "properties": {
    "iso:country":"US",
    "sg:address":"219 S Prairieville St",
    "sg:city":"Athens",
    "sg:classifiers":[
        {
            "category":"Personal",
            "subcategory":"Beauty Salon",
            "type":"Services"
        }
    ],
    "sg:phone":"+1 903 677 4247",
    "sg:postcode":"75751",
    "sg:province":"TX",
    "sg:tags":[
        "shop"
    ],
    "wof:name":"Agape Salon",
    "wof:placetype":"venue"
},
  "geometry": {"coordinates":[-95.85503799999999,32.201797],"type":"Point"}
}