{
  "type": "Feature",
  "properties": {
    "iso:country":"US",
    "sg:address":"15606 Shanghai St",
    "sg:city":"Houston",
    "sg:classifiers":[
        {
            "category":"Personal",
            "subcategory":"Barber",
            "type":"Services"
        }
    ],
    "sg:phone":"+1 713 896 1760",
    "sg:postcode":"77040",
    "sg:province":"TX",
    "sg:tags":[
        "shop"
    ],
    "wof:name":"His Hands Laser Engraving",
    "wof:placetype":"venue"
},
  "geometry": {"coordinates":[-95.556116,29.885134],"type":"Point"}
}