{
  "type": "Feature",
  "properties": {
    "iso:country":"US",
    "sg:address":"1508 Haskell St",
    "sg:city":"Wellington",
    "sg:phone":"+1 806 447 2831",
    "sg:postcode":"79095",
    "sg:province":"TX",
    "sg:tags":[
        "farm",
        "h",
        "wheat",
        "crop",
        "cotton"
    ],
    "wof:name":"Tank",
    "wof:placetype":"venue"
},
  "geometry": {"coordinates":[-100.222539,34.848964],"type":"Point"}
}