{
  "type": "Feature",
  "properties": {
    "iso:country":"US",
    "sg:address":"4737 Gretna St",
    "sg:city":"Dallas",
    "sg:classifiers":[
        {
            "category":"Manufacturing",
            "subcategory":"Printing",
            "type":"Manufacturing & Wholesale Goods"
        }
    ],
    "sg:phone":"+1 214 631 8581",
    "sg:postcode":"75207",
    "sg:province":"TX",
    "sg:tags":[
        "work"
    ],
    "wof:name":"Jmm Services",
    "wof:placetype":"venue"
},
  "geometry": {"coordinates":[-96.849228,32.802261],"type":"Point"}
}