{
  "type": "Feature",
  "properties": {
    "iso:country":"US",
    "sg:address":"1941 Taylor Rd",
    "sg:city":"Weatherford",
    "sg:classifiers":[
        {
            "category":"Professional",
            "subcategory":"Business Services",
            "type":"Services"
        }
    ],
    "sg:phone":"+1 817 613 9273",
    "sg:postcode":"76087",
    "sg:province":"TX",
    "wof:name":"Warrens Auctioneer",
    "wof:placetype":"venue"
},
  "geometry": {"coordinates":[-97.924418,32.641326],"type":"Point"}
}