{
  "type": "Feature",
  "properties": {
    "iso:country":"US",
    "sg:address":"6935 Tokalon Dr",
    "sg:city":"Dallas",
    "sg:classifiers":[
        {
            "category":"Insurance",
            "subcategory":"Insurance Agent",
            "type":"Services"
        }
    ],
    "sg:phone":"+1 214 319 6800",
    "sg:postcode":"75214",
    "sg:province":"TX",
    "wof:name":"Cavalier Insurance Agency LLC",
    "wof:placetype":"venue"
},
  "geometry": {"coordinates":[-96.73768800000001,32.819346],"type":"Point"}
}