{
  "type": "Feature",
  "properties": {
    "iso:country":"US",
    "sg:address":"1012 Micarta Dr",
    "sg:city":"Mesquite",
    "sg:classifiers":[
        {
            "category":"Home & Garden",
            "subcategory":"Building Materials",
            "type":"Retail Goods"
        }
    ],
    "sg:phone":"+1 972 222 3222",
    "sg:postcode":"75181",
    "sg:province":"TX",
    "wof:name":"Prism Glass",
    "wof:placetype":"venue"
},
  "geometry": {"coordinates":[-96.55710500000001,32.755571],"type":"Point"}
}