{
  "type": "Feature",
  "properties": {
    "iso:country":"US",
    "sg:address":"2810 E 3rd St",
    "sg:city":"Austin",
    "sg:classifiers":[
        {
            "category":"Organizations",
            "subcategory":"Religious Organization",
            "type":"Services"
        }
    ],
    "sg:phone":"+1 512 389 1093",
    "sg:postcode":"78702",
    "sg:province":"TX",
    "sg:tags":[
        "church"
    ],
    "wof:name":"El Sendero De LA Cruz",
    "wof:placetype":"venue"
},
  "geometry": {"coordinates":[-97.71100800000001,30.25458],"type":"Point"}
}