{
  "type": "Feature",
  "properties": {
    "iso:country":"US",
    "sg:address":"642 W Rhapsody Dr",
    "sg:city":"San Antonio",
    "sg:classifiers":[
        {
            "category":"Shopping",
            "subcategory":"Computers & Home Electronics",
            "type":"Retail Goods"
        }
    ],
    "sg:phone":"+1 210 341 7020",
    "sg:postcode":"78216",
    "sg:province":"TX",
    "sg:tags":[
        "system"
    ],
    "wof:name":"Acoustic Designs",
    "wof:placetype":"venue"
},
  "geometry": {"coordinates":[-98.50072,29.551498],"type":"Point"}
}