{
  "type": "Feature",
  "properties": {
    "iso:country":"US",
    "sg:address":"5623 Morningside Ave",
    "sg:city":"Dallas",
    "sg:classifiers":[
        {
            "category":"Professional",
            "type":"Services"
        }
    ],
    "sg:phone":"+1 214 823 4923",
    "sg:postcode":"75206",
    "sg:province":"TX",
    "wof:name":"James M Francis",
    "wof:placetype":"venue"
},
  "geometry": {"coordinates":[-96.77057600000001,32.829137],"type":"Point"}
}