{
  "type": "Feature",
  "properties": {
    "iso:country":"US",
    "sg:address":"600 State Hwy 6n Bus",
    "sg:city":"Marlin",
    "sg:classifiers":[
        {
            "category":"Shopping",
            "subcategory":"Department Store",
            "type":"Retail Goods"
        }
    ],
    "sg:phone":"+1 254 883 5556",
    "sg:postcode":"76661",
    "sg:province":"TX",
    "wof:name":"Wal-Mart",
    "wof:placetype":"venue"
},
  "geometry": {"coordinates":[-96.899351,31.302483],"type":"Point"}
}