{
  "type": "Feature",
  "properties": {
    "iso:country":"US",
    "sg:address":"15310 Appleridge Dr",
    "sg:city":"Missouri City",
    "sg:classifiers":[
        {
            "category":"Shopping",
            "subcategory":"Clothing, Apparel, & Fashions",
            "type":"Retail Goods"
        }
    ],
    "sg:phone":"+1 281 437 2835",
    "sg:postcode":"77489",
    "sg:province":"TX",
    "sg:tags":[
        "uniform"
    ],
    "wof:name":"Unique Uniforms Unlimited",
    "wof:placetype":"venue"
},
  "geometry": {"coordinates":[-95.499329,29.60362],"type":"Point"}
}