{
  "type": "Feature",
  "properties": {
    "iso:country":"US",
    "sg:address":"1204 N Meadow Ave",
    "sg:city":"Laredo",
    "sg:classifiers":[
        {
            "category":"Retail",
            "subcategory":"Laundry & Dry Cleaning",
            "type":"Services"
        }
    ],
    "sg:phone":"+1 956 723 6443",
    "sg:postcode":"78040",
    "sg:province":"TX",
    "sg:tags":[
        "cleaners"
    ],
    "wof:name":"Buford's Cleaning",
    "wof:placetype":"venue"
},
  "geometry": {"coordinates":[-99.480422,27.507464],"type":"Point"}
}