{
  "type": "Feature",
  "properties": {
    "iso:country":"US",
    "sg:address":"16340 FM 2920",
    "sg:city":"Tomball",
    "sg:classifiers":[
        {
            "category":"Building & Trades",
            "subcategory":"Construction",
            "type":"Services"
        }
    ],
    "sg:phone":"+1 281 655 0059",
    "sg:postcode":"77377",
    "sg:province":"TX",
    "sg:tags":[
        "swimming",
        "designer",
        "dealer",
        "pool",
        "contractor"
    ],
    "wof:name":"Backyard Oasis Inc",
    "wof:placetype":"venue"
},
  "geometry": {"coordinates":[-95.67301,30.079623],"type":"Point"}
}