{
  "type": "Feature",
  "properties": {
    "iso:country":"US",
    "sg:address":"11110 State Hwy 225",
    "sg:city":"La Porte",
    "sg:classifiers":[
        {
            "category":"Freight",
            "type":"Transportation"
        }
    ],
    "sg:phone":"+1 281 470 9598",
    "sg:postcode":"77571",
    "sg:province":"TX",
    "sg:tags":[
        "local",
        "except"
    ],
    "wof:name":"Ulysses Trucking Co Inc",
    "wof:placetype":"venue"
},
  "geometry": {"coordinates":[-95.064378,29.696078],"type":"Point"}
}