{
  "type": "Feature",
  "properties": {
    "iso:country":"US",
    "sg:address":"14114 Dallas Pkwy Ste 180",
    "sg:city":"Dallas",
    "sg:classifiers":[
        {
            "category":"Health Services",
            "subcategory":"Doctor",
            "type":"Services"
        }
    ],
    "sg:phone":"+1 972 720 9943",
    "sg:postcode":"75254",
    "sg:province":"TX",
    "wof:name":"Elite Healthcare & Rehabilitation",
    "wof:placetype":"venue"
},
  "geometry": {"coordinates":[-96.82157599999999,32.939901],"type":"Point"}
}