{
  "type": "Feature",
  "properties": {
    "iso:country":"US",
    "sg:address":"6120 Adirondack Trl",
    "sg:city":"Amarillo",
    "sg:classifiers":[
        {
            "category":"Building & Trades",
            "subcategory":"Construction",
            "type":"Services"
        }
    ],
    "sg:phone":"+1 806 351 0356",
    "sg:postcode":"79106",
    "sg:province":"TX",
    "sg:tags":[
        "contractor"
    ],
    "wof:name":"Kevin Jones Construction",
    "wof:placetype":"venue"
},
  "geometry": {"coordinates":[-101.90795199999999,35.185242],"type":"Point"}
}