{
  "type": "Feature",
  "properties": {
    "iso:country":"US",
    "sg:address":"4414 Clay St",
    "sg:city":"Houston",
    "sg:classifiers":[
        {
            "category":"Professional",
            "type":"Services"
        }
    ],
    "sg:phone":"+1 713 514 0904",
    "sg:postcode":"77023",
    "sg:province":"TX",
    "sg:tags":[
        "establishment"
    ],
    "wof:name":"Ngis",
    "wof:placetype":"venue"
},
  "geometry": {"coordinates":[-95.333597,29.737362],"type":"Point"}
}