{
  "type": "Feature",
  "properties": {
    "iso:country":"US",
    "sg:address":"9330 Wilson Rd",
    "sg:city":"Pilot Point",
    "sg:classifiers":[
        {
            "category":"Travel",
            "subcategory":"Hotels & Motels",
            "type":"Entertainment"
        }
    ],
    "sg:phone":"+1 940 686 5460",
    "sg:postcode":"76258",
    "sg:province":"TX",
    "sg:tags":[
        "breakfast",
        "accommodation",
        "bed"
    ],
    "wof:name":"Tlc Bed & Breakfast",
    "wof:placetype":"venue"
},
  "geometry": {"coordinates":[-96.971193,33.388643],"type":"Point"}
}