{
  "type": "Feature",
  "properties": {
    "iso:country":"US",
    "sg:address":"1705 Creek Bend Cir",
    "sg:city":"Round Rock",
    "sg:classifiers":[
        {
            "category":"Manufacturing",
            "subcategory":"Leather Goods",
            "type":"Manufacturing & Wholesale Goods"
        }
    ],
    "sg:phone":"+1 512 388 0347",
    "sg:postcode":"78681",
    "sg:province":"TX",
    "sg:tags":[
        "handbag",
        "purse"
    ],
    "wof:name":"Ann Sara Enterprises",
    "wof:placetype":"venue"
},
  "geometry": {"coordinates":[-97.715219,30.523366],"type":"Point"}
}