{
  "type": "Feature",
  "properties": {
    "iso:country":"US",
    "sg:address":"7319 Blythdale Dr",
    "sg:city":"Dallas",
    "sg:classifiers":[
        {
            "category":"Retail",
            "subcategory":"Laundry & Dry Cleaning",
            "type":"Services"
        }
    ],
    "sg:phone":"+1 972 931 5711",
    "sg:postcode":"75248",
    "sg:province":"TX",
    "wof:name":"Team Carpet Clean Inc",
    "wof:placetype":"venue"
},
  "geometry": {"coordinates":[-96.77968300000001,32.981726],"type":"Point"}
}