{
  "type": "Feature",
  "properties": {
    "iso:country":"US",
    "sg:address":"210 Bora Bora Dr",
    "sg:city":"Galveston",
    "sg:classifiers":[
        {
            "category":"Banks & Credit Unions",
            "subcategory":"Financial Services",
            "type":"Services"
        }
    ],
    "sg:phone":"+1 409 935 5497",
    "sg:postcode":"77554",
    "sg:province":"TX",
    "sg:tags":[
        "trust",
        "management"
    ],
    "wof:name":"Hayes Family Trust",
    "wof:placetype":"venue"
},
  "geometry": {"coordinates":[-94.91273099999999,29.295292],"type":"Point"}
}