{
  "type": "Feature",
  "properties": {
    "iso:country":"US",
    "sg:address":"106 Margarita Ave",
    "sg:city":"Del Rio",
    "sg:classifiers":[
        {
            "category":"Food & Beverages",
            "subcategory":"Groceries & Convenience Stores",
            "type":"Retail Goods"
        }
    ],
    "sg:phone":"+1 830 775 5154",
    "sg:postcode":"78840",
    "sg:province":"TX",
    "wof:name":"KWIK Pantry",
    "wof:placetype":"venue"
},
  "geometry": {"coordinates":[-100.88333,29.365349],"type":"Point"}
}