{
  "type": "Feature",
  "properties": {
    "iso:country":"US",
    "sg:address":"3133 Saba Ln",
    "sg:city":"Port Neches",
    "sg:classifiers":[
        {
            "category":"Health Services",
            "subcategory":"Doctor",
            "type":"Services"
        }
    ],
    "sg:phone":"+1 409 729 3668",
    "sg:postcode":"77651",
    "sg:province":"TX",
    "sg:tags":[
        "medical"
    ],
    "wof:name":"Bowling Richard G",
    "wof:placetype":"venue"
},
  "geometry": {"coordinates":[-93.955253,29.95324],"type":"Point"}
}