{
  "type": "Feature",
  "properties": {
    "iso:country":"US",
    "sg:address":"800 N Walnut St",
    "sg:city":"Roanoke",
    "sg:classifiers":[
        {
            "category":"Real Estate",
            "subcategory":"Real Estate Operator",
            "type":"Services"
        }
    ],
    "sg:phone":"+1 817 430 2211",
    "sg:postcode":"76262",
    "sg:province":"TX",
    "sg:tags":[
        "mobile",
        "home",
        "site",
        "community"
    ],
    "wof:name":"Greenhill Estates Mobile HM Pk",
    "wof:placetype":"venue"
},
  "geometry": {"coordinates":[-97.22360999999999,33.003928],"type":"Point"}
}