{
  "type": "Feature",
  "properties": {
    "iso:country":"US",
    "sg:address":"5138 E Frio Dr",
    "sg:city":"Dallas",
    "sg:classifiers":[
        {
            "category":"Professional",
            "type":"Services"
        }
    ],
    "sg:phone":"+1 214 371 3794",
    "sg:postcode":"75241",
    "sg:province":"TX",
    "wof:name":"Pico De Gallo Gourmet",
    "wof:placetype":"venue"
},
  "geometry": {"coordinates":[-96.794909,32.683144],"type":"Point"}
}