{
  "type": "Feature",
  "properties": {
    "iso:country":"US",
    "sg:address":"7345 Plumwood Dr",
    "sg:city":"Fort Worth",
    "sg:classifiers":[
        {
            "category":"Professional",
            "subcategory":"Business Services",
            "type":"Services"
        },
        {
            "category":"Recreation",
            "type":"Entertainment"
        }
    ],
    "sg:phone":"+1 817 428 9678",
    "sg:postcode":"76180",
    "sg:province":"TX",
    "sg:tags":[
        "instruction",
        "golf"
    ],
    "wof:name":"Prestige Golf Group",
    "wof:placetype":"venue"
},
  "geometry": {"coordinates":[-97.220191,32.881172],"type":"Point"}
}