{
  "type": "Feature",
  "properties": {
    "iso:country":"US",
    "sg:address":"10490 Brockwood Rd",
    "sg:city":"Dallas",
    "sg:classifiers":[
        {
            "category":"Wholesale",
            "subcategory":"Construction Materials",
            "type":"Manufacturing & Wholesale Goods"
        }
    ],
    "sg:phone":"+1 214 341 6500",
    "sg:postcode":"75238",
    "sg:province":"TX",
    "wof:name":"Mid Tex Specialty Supply",
    "wof:placetype":"venue"
},
  "geometry": {"coordinates":[-96.70602,32.890765],"type":"Point"}
}