{
  "type": "Feature",
  "properties": {
    "iso:country":"US",
    "sg:address":"4515 Tacoma St",
    "sg:city":"Dallas",
    "sg:classifiers":[
        {
            "category":"Professional",
            "type":"Services"
        }
    ],
    "sg:phone":"+1 214 371 5711",
    "sg:postcode":"75216",
    "sg:province":"TX",
    "wof:name":"Georgia N Bailey",
    "wof:placetype":"venue"
},
  "geometry": {"coordinates":[-96.773231,32.702807],"type":"Point"}
}