{
  "type": "Feature",
  "properties": {
    "iso:country":"US",
    "sg:address":"1766 FM 967",
    "sg:city":"Buda",
    "sg:classifiers":[
        {
            "category":"Professional",
            "subcategory":"Lawyer & Legal Services",
            "type":"Services"
        }
    ],
    "sg:phone":"+1 512 312 0904",
    "sg:postcode":"78610",
    "sg:province":"TX",
    "sg:tags":[
        "attorney"
    ],
    "wof:name":"Abigail C Klamert",
    "wof:placetype":"venue"
},
  "geometry": {"coordinates":[-97.849829,30.101075],"type":"Point"}
}