{
  "type": "Feature",
  "properties": {
    "iso:country":"US",
    "sg:address":"3812 Ash Ln",
    "sg:city":"Mc Kinney",
    "sg:classifiers":[
        {
            "category":"Shopping",
            "type":"Retail Goods"
        }
    ],
    "sg:phone":"+1 972 529 2772",
    "sg:postcode":"75070",
    "sg:province":"TX",
    "sg:tags":[
        "merchandise"
    ],
    "wof:name":"Michael Fine Caterer",
    "wof:placetype":"venue"
},
  "geometry": {"coordinates":[-96.681624,33.16445],"type":"Point"}
}