{
  "type": "Feature",
  "properties": {
    "iso:country":"US",
    "sg:address":"701 E Marshall Ave",
    "sg:city":"Longview",
    "sg:classifiers":[
        {
            "category":"Health Services",
            "subcategory":"Doctor",
            "type":"Services"
        }
    ],
    "sg:phone":"+1 903 315 2777",
    "sg:postcode":"75601",
    "sg:province":"TX",
    "sg:tags":[
        "medical"
    ],
    "wof:name":"Longview Family Practice",
    "wof:placetype":"venue"
},
  "geometry": {"coordinates":[-94.730181,32.501982],"type":"Point"}
}