{
  "type": "Feature",
  "properties": {
    "iso:country":"US",
    "sg:address":"303 Cooper St",
    "sg:city":"Lindale",
    "sg:classifiers":[
        {
            "category":"Building & Trades",
            "subcategory":"Construction",
            "type":"Services"
        }
    ],
    "sg:phone":"+1 903 882 5907",
    "sg:postcode":"75771",
    "sg:province":"TX",
    "sg:tags":[
        "painter"
    ],
    "wof:name":"Alpha-Omega",
    "wof:placetype":"venue"
},
  "geometry": {"coordinates":[-95.41094699999999,32.510392],"type":"Point"}
}