{
  "type": "Feature",
  "properties": {
    "iso:country":"US",
    "sg:address":"2600 Southwest Fwy",
    "sg:city":"Houston",
    "sg:classifiers":[
        {
            "category":"Professional",
            "subcategory":"Computer Services",
            "type":"Services"
        }
    ],
    "sg:phone":"+1 512 646 7873",
    "sg:postcode":"77098",
    "sg:province":"TX",
    "sg:tags":[
        "internet"
    ],
    "wof:name":"Everyone Internet",
    "wof:placetype":"venue"
},
  "geometry": {"coordinates":[-95.41891,29.730984],"type":"Point"}
}