{
  "type": "Feature",
  "properties": {
    "iso:country":"US",
    "sg:address":"1212 E Berry St",
    "sg:city":"Fort Worth",
    "sg:classifiers":[
        {
            "category":"Autos & Motor Vehicles",
            "subcategory":"Automobile Sales",
            "type":"Retail Goods"
        }
    ],
    "sg:phone":"+1 817 921 5344",
    "sg:postcode":"76110",
    "sg:province":"TX",
    "sg:tags":[
        "used"
    ],
    "wof:name":"Star Motors",
    "wof:placetype":"venue"
},
  "geometry": {"coordinates":[-97.311092,32.705868],"type":"Point"}
}