{
  "type": "Feature",
  "properties": {
    "iso:country":"US",
    "sg:address":"5960 W Northwest Hwy",
    "sg:city":"Dallas",
    "sg:classifiers":[
        {
            "category":"Shopping",
            "subcategory":"Mobile Phones",
            "type":"Retail Goods"
        }
    ],
    "sg:phone":"+1 214 368 8080",
    "sg:postcode":"75225",
    "sg:province":"TX",
    "sg:website":"www.texascellular.com",
    "wof:name":"Texas Cellular Communications",
    "wof:placetype":"venue"
},
  "geometry": {"coordinates":[-96.805689,32.865352],"type":"Point"}
}