{
  "type": "Feature",
  "properties": {
    "iso:country":"US",
    "sg:address":"5916 Maple Ln",
    "sg:city":"Rowlett",
    "sg:classifiers":[
        {
            "category":"Building & Trades",
            "subcategory":"Construction",
            "type":"Services"
        }
    ],
    "sg:phone":"+1 972 412 7262",
    "sg:postcode":"75089",
    "sg:province":"TX",
    "sg:tags":[
        "remodeling",
        "contractor"
    ],
    "wof:name":"A L King Construction",
    "wof:placetype":"venue"
},
  "geometry": {"coordinates":[-96.575262,32.912871],"type":"Point"}
}