{
  "type": "Feature",
  "properties": {
    "iso:country":"US",
    "sg:address":"16228 Huffmeister Rd",
    "sg:city":"Cypress",
    "sg:classifiers":[
        {
            "category":"Building & Trades",
            "subcategory":"Construction",
            "type":"Services"
        }
    ],
    "sg:phone":"+1 281 373 0423",
    "sg:postcode":"77429",
    "sg:province":"TX",
    "sg:tags":[
        "concrete",
        "contractor"
    ],
    "wof:name":"Creative Concrete Texture",
    "wof:placetype":"venue"
},
  "geometry": {"coordinates":[-95.66606899999999,29.987305],"type":"Point"}
}