{
  "type": "Feature",
  "properties": {
    "iso:country":"US",
    "sg:address":"1820 Harwood Ct",
    "sg:city":"Hurst",
    "sg:classifiers":[
        {
            "category":"Home & Garden",
            "subcategory":"Building Materials",
            "type":"Retail Goods"
        }
    ],
    "sg:phone":"+1 817 281 6799",
    "sg:postcode":"76054",
    "sg:province":"TX",
    "wof:name":"Cement Council of Texas",
    "wof:placetype":"venue"
},
  "geometry": {"coordinates":[-97.179654,32.847079],"type":"Point"}
}