{
  "type": "Feature",
  "properties": {
    "iso:country":"US",
    "sg:address":"1130 Cam la Costa",
    "sg:city":"Austin",
    "sg:classifiers":[
        {
            "category":"Recreation",
            "type":"Entertainment"
        }
    ],
    "sg:phone":"+1 512 453 6954",
    "sg:postcode":"78752",
    "sg:province":"TX",
    "sg:tags":[
        "parks"
    ],
    "wof:name":"Amer Park",
    "wof:placetype":"venue"
},
  "geometry": {"coordinates":[-97.695717,30.324397],"type":"Point"}
}