{
  "type": "Feature",
  "properties": {
    "iso:country":"US",
    "sg:address":"3109 Fountain View Dr",
    "sg:city":"Houston",
    "sg:classifiers":[
        {
            "category":"Restaurant",
            "type":"Food & Drink"
        }
    ],
    "sg:phone":"+1 713 868 9800",
    "sg:postcode":"77057",
    "sg:province":"TX",
    "sg:tags":[
        "specialty",
        "catering"
    ],
    "wof:name":"Savory Quisine",
    "wof:placetype":"venue"
},
  "geometry": {"coordinates":[-95.48416,29.732985],"type":"Point"}
}