{
  "type": "Feature",
  "properties": {
    "iso:country":"US",
    "sg:address":"1005 W University Dr",
    "sg:city":"Denton",
    "sg:classifiers":[
        {
            "category":"Professional",
            "subcategory":"Advertising",
            "type":"Services"
        }
    ],
    "sg:phone":"+1 940 566 1005",
    "sg:postcode":"76201",
    "sg:province":"TX",
    "wof:name":"American Classified",
    "wof:placetype":"venue"
},
  "geometry": {"coordinates":[-97.141958,33.229735],"type":"Point"}
}