{
  "type": "Feature",
  "properties": {
    "iso:country":"US",
    "sg:address":"2404 Rio Grande St",
    "sg:city":"Austin",
    "sg:classifiers":[
        {
            "category":"Insurance",
            "subcategory":"Insurance Agent",
            "type":"Services"
        }
    ],
    "sg:phone":"+1 512 477 6311",
    "sg:postcode":"78705",
    "sg:province":"TX",
    "sg:tags":[
        "appraisal",
        "real estate"
    ],
    "wof:name":"Paul Hornsby & Company",
    "wof:placetype":"venue"
},
  "geometry": {"coordinates":[-97.744692,30.288389],"type":"Point"}
}