{
  "type": "Feature",
  "properties": {
    "iso:country":"US",
    "sg:address":"11601 Audelia Rd",
    "sg:city":"Dallas",
    "sg:classifiers":[
        {
            "category":"Freight",
            "type":"Transportation"
        }
    ],
    "sg:phone":"+1 214 503 8389",
    "sg:postcode":"75243",
    "sg:province":"TX",
    "wof:name":"E&E Moving Inc",
    "wof:placetype":"venue"
},
  "geometry": {"coordinates":[-96.71792600000001,32.905886],"type":"Point"}
}