{
  "type": "Feature",
  "properties": {
    "iso:country":"US",
    "sg:address":"9430 Old Katy Rd",
    "sg:city":"Houston",
    "sg:classifiers":[
        {
            "category":"Real Estate",
            "subcategory":"Developer",
            "type":"Services"
        },
        {
            "category":"Real Estate",
            "subcategory":"Real Estate Agent",
            "type":"Services"
        }
    ],
    "sg:phone":"+1 713 789 2529",
    "sg:postcode":"77055",
    "sg:province":"TX",
    "sg:tags":[
        "development",
        "construction",
        "commercial"
    ],
    "wof:name":"Clay Development & Constructon",
    "wof:placetype":"venue"
},
  "geometry": {"coordinates":[-95.52179599999999,29.784852],"type":"Point"}
}