{
  "type": "Feature",
  "properties": {
    "iso:country":"US",
    "sg:address":"1816 N Midland Dr",
    "sg:city":"Midland",
    "sg:classifiers":[
        {
            "category":"Health Services",
            "subcategory":"Chiropractor",
            "type":"Services"
        }
    ],
    "sg:phone":"+1 432 699 5111",
    "sg:postcode":"79707",
    "sg:province":"TX",
    "sg:tags":[
        "help",
        "supply"
    ],
    "wof:name":"Emergy Clinic",
    "wof:placetype":"venue"
},
  "geometry": {"coordinates":[-102.13733000000001,32.003131],"type":"Point"}
}