{
  "type": "Feature",
  "properties": {
    "iso:country":"US",
    "sg:address":"City Park Rd",
    "sg:city":"Austin",
    "sg:classifiers":[
        {
            "category":"Park",
            "type":"Public Place"
        }
    ],
    "sg:phone":"+1 512 346 1831",
    "sg:postcode":"78798",
    "sg:province":"TX",
    "sg:website":"www.ci.austin.tx.us/parks/emmalo...",
    "wof:name":"Emma Long Park Trail",
    "wof:placetype":"venue"
},
  "geometry": {"coordinates":[-97.83305,30.35133],"type":"Point"}
}