{
  "type": "Feature",
  "properties": {
    "iso:country":"US",
    "sg:address":"3325 W Wadley Ave",
    "sg:city":"Midland",
    "sg:classifiers":[
        {
            "category":"Shopping",
            "subcategory":"Pharmacy",
            "type":"Retail Goods"
        }
    ],
    "sg:phone":"+1 432 697 1484",
    "sg:postcode":"79707",
    "sg:province":"TX",
    "wof:name":"Heb Pharmacy",
    "wof:placetype":"venue"
},
  "geometry": {"coordinates":[-102.125879,32.019527],"type":"Point"}
}