{
  "type": "Feature",
  "properties": {
    "iso:country":"US",
    "sg:address":"1201 Chicago Ave",
    "sg:city":"Mcallen",
    "sg:classifiers":[
        {
            "category":"Restaurant",
            "type":"Food & Drink"
        }
    ],
    "sg:phone":"+1 956 682 0097",
    "sg:postcode":"78501",
    "sg:province":"TX",
    "sg:tags":[
        "eating"
    ],
    "wof:name":"Salads & More",
    "wof:placetype":"venue"
},
  "geometry": {"coordinates":[-98.233773,26.201276],"type":"Point"}
}