{
  "type": "Feature",
  "properties": {
    "iso:country":"US",
    "sg:address":"7 Thornhill Oaks Dr",
    "sg:city":"Houston",
    "sg:classifiers":[
        {
            "category":"Health Services",
            "subcategory":"Chiropractor",
            "type":"Services"
        }
    ],
    "sg:phone":"+1 713 455 8031",
    "sg:postcode":"77015",
    "sg:province":"TX",
    "wof:name":"Tumino Chiropractic Clinic",
    "wof:placetype":"venue"
},
  "geometry": {"coordinates":[-95.20079800000001,29.799601],"type":"Point"}
}