{
  "type": "Feature",
  "properties": {
    "iso:country":"US",
    "sg:address":"4310 Pembrooke Pkwy N",
    "sg:city":"Colleyville",
    "sg:classifiers":[
        {
            "category":"Professional",
            "subcategory":"Management & Consulting",
            "type":"Services"
        }
    ],
    "sg:phone":"+1 214 454 7620",
    "sg:postcode":"76034",
    "sg:province":"TX",
    "sg:tags":[
        "business"
    ],
    "wof:name":"Neisus Consulting Investments",
    "wof:placetype":"venue"
},
  "geometry": {"coordinates":[-97.113013,32.872961],"type":"Point"}
}