{
  "type": "Feature",
  "properties": {
    "iso:country":"US",
    "sg:address":"5294 14th St",
    "sg:city":"Port Arthur",
    "sg:classifiers":[
        {
            "category":"Shopping",
            "subcategory":"Used Merchandise",
            "type":"Retail Goods"
        }
    ],
    "sg:phone":"+1 409 983 5578",
    "sg:postcode":"77642",
    "sg:province":"TX",
    "wof:name":"Frans",
    "wof:placetype":"venue"
},
  "geometry": {"coordinates":[-93.90470000000001,29.920686],"type":"Point"}
}