{
  "type": "Feature",
  "properties": {
    "iso:country":"US",
    "sg:address":"3406 Sabrina St",
    "sg:city":"Seguin",
    "sg:classifiers":[
        {
            "category":"Building & Trades",
            "subcategory":"Landscaping Services",
            "type":"Services"
        }
    ],
    "sg:phone":"+1 830 401 4037",
    "sg:postcode":"78155",
    "sg:province":"TX",
    "sg:tags":[
        "lawn",
        "maintenance"
    ],
    "wof:name":"Richardsons Quality Lawn",
    "wof:placetype":"venue"
},
  "geometry": {"coordinates":[-97.972252,29.612444],"type":"Point"}
}