{
  "type": "Feature",
  "properties": {
    "iso:country":"US",
    "sg:address":"1547 Hwy 71 W",
    "sg:city":"Bastrop",
    "sg:classifiers":[
        {
            "category":"Manufacturing",
            "subcategory":"Buildings",
            "type":"Manufacturing & Wholesale Goods"
        }
    ],
    "sg:phone":"+1 512 303 5599",
    "sg:postcode":"78602",
    "sg:province":"TX",
    "sg:tags":[
        "prefab"
    ],
    "wof:name":"Bluebonnet Homes",
    "wof:placetype":"venue"
},
  "geometry": {"coordinates":[-97.435885,30.124342],"type":"Point"}
}