{
  "type": "Feature",
  "properties": {
    "iso:country":"US",
    "sg:address":"3545 Gilmer Rd",
    "sg:city":"Longview",
    "sg:classifiers":[
        {
            "category":"Real Estate",
            "subcategory":"Real Estate Agent",
            "type":"Services"
        }
    ],
    "sg:phone":"+1 903 297 7800",
    "sg:postcode":"75604",
    "sg:province":"TX",
    "wof:name":"Murray Real Estate Investments",
    "wof:placetype":"venue"
},
  "geometry": {"coordinates":[-94.799454,32.550323],"type":"Point"}
}