{
  "type": "Feature",
  "properties": {
    "iso:country":"US",
    "sg:address":"17842 Dean Ct",
    "sg:city":"Conroe",
    "sg:classifiers":[
        {
            "category":"Shopping",
            "subcategory":"Clothing, Apparel, & Fashions",
            "type":"Retail Goods"
        }
    ],
    "sg:phone":"+1 281 429 0648",
    "sg:postcode":"77302",
    "sg:province":"TX",
    "wof:name":"Treasure Box",
    "wof:placetype":"venue"
},
  "geometry": {"coordinates":[-95.30047399999999,30.228306],"type":"Point"}
}