{
  "type": "Feature",
  "properties": {
    "iso:country":"US",
    "sg:address":"3027 Sesbania Dr",
    "sg:city":"Austin",
    "sg:classifiers":[
        {
            "category":"Real Estate",
            "subcategory":"Architect",
            "type":"Services"
        }
    ],
    "sg:phone":"+1 512 282 0693",
    "sg:postcode":"78748",
    "sg:province":"TX",
    "sg:tags":[
        "architectural"
    ],
    "wof:name":"Architecture TDC",
    "wof:placetype":"venue"
},
  "geometry": {"coordinates":[-97.85355300000001,30.164135],"type":"Point"}
}