{
  "type": "Feature",
  "properties": {
    "iso:country":"US",
    "sg:address":"23420 Cinco Ranch Blvd",
    "sg:city":"Katy",
    "sg:classifiers":[
        {
            "category":"Organizations",
            "subcategory":"Religious Organization",
            "type":"Services"
        }
    ],
    "sg:phone":"+1 281 646 1084",
    "sg:postcode":"77494",
    "sg:province":"TX",
    "sg:tags":[
        "church"
    ],
    "wof:name":"Fellowship Bible Church",
    "wof:placetype":"venue"
},
  "geometry": {"coordinates":[-95.77324900000001,29.733636],"type":"Point"}
}