{
  "type": "Feature",
  "properties": {
    "iso:country":"US",
    "sg:address":"918 Federal Rd",
    "sg:city":"Houston",
    "sg:classifiers":[
        {
            "category":"Organizations",
            "subcategory":"Community Association",
            "type":"Services"
        }
    ],
    "sg:phone":"+1 713 453 5371",
    "sg:postcode":"77015",
    "sg:province":"TX",
    "wof:name":"North Shore Lodge 1353 AF",
    "wof:placetype":"venue"
},
  "geometry": {"coordinates":[-95.215552,29.772801],"type":"Point"}
}