{
  "type": "Feature",
  "properties": {
    "iso:country":"US",
    "sg:address":"5905 Peden Rd",
    "sg:city":"Fort Worth",
    "sg:classifiers":[
        {
            "category":"Professional",
            "subcategory":"Management & Consulting",
            "type":"Services"
        }
    ],
    "sg:phone":"+1 817 236 8048",
    "sg:postcode":"76179",
    "sg:province":"TX",
    "sg:tags":[
        "business"
    ],
    "wof:name":"Heli Assist International",
    "wof:placetype":"venue"
},
  "geometry": {"coordinates":[-97.495008,32.941501],"type":"Point"}
}