{
  "type": "Feature",
  "properties": {
    "iso:country":"US",
    "sg:address":"2401 Leon St",
    "sg:city":"Austin",
    "sg:classifiers":[
        {
            "category":"Real Estate",
            "subcategory":"Real Estate Operator",
            "type":"Services"
        }
    ],
    "sg:postcode":"78705",
    "sg:province":"TX",
    "sg:tags":[
        "apartment"
    ],
    "wof:name":"Waterford Apartments",
    "wof:placetype":"venue"
},
  "geometry": {"coordinates":[-97.748971,30.288543],"type":"Point"}
}