{
  "type": "Feature",
  "properties": {
    "iso:country":"US",
    "sg:address":"531 Reunion Rd",
    "sg:city":"Desoto",
    "sg:classifiers":[
        {
            "category":"Organizations",
            "subcategory":"Religious Organization",
            "type":"Services"
        }
    ],
    "sg:phone":"+1 972 274 1055",
    "sg:postcode":"75115",
    "sg:province":"TX",
    "sg:tags":[
        "church"
    ],
    "wof:name":"True Vine Church-God In Christ",
    "wof:placetype":"venue"
},
  "geometry": {"coordinates":[-96.846745,32.58531],"type":"Point"}
}