{
  "type": "Feature",
  "properties": {
    "iso:country":"US",
    "sg:address":"907 S Stadium Rd",
    "sg:city":"Alice",
    "sg:classifiers":[
        {
            "category":"Mining & Drilling",
            "type":"Manufacturing & Wholesale Goods"
        }
    ],
    "sg:phone":"+1 361 668 0973",
    "sg:postcode":"78332",
    "sg:province":"TX",
    "sg:tags":[
        "field",
        "supply"
    ],
    "wof:name":"Hub City H Two S Monitoring",
    "wof:placetype":"venue"
},
  "geometry": {"coordinates":[-98.05320399999999,27.744992],"type":"Point"}
}