{
  "type": "Feature",
  "properties": {
    "iso:country":"US",
    "sg:address":"24002 Anchor Ranch Dr",
    "sg:city":"Hockley",
    "sg:classifiers":[
        {
            "category":"Professional",
            "type":"Services"
        }
    ],
    "sg:phone":"+1 281 373 0019",
    "sg:postcode":"77447",
    "sg:province":"TX",
    "sg:tags":[
        "information",
        "bureau"
    ],
    "wof:name":"Moe Services",
    "wof:placetype":"venue"
},
  "geometry": {"coordinates":[-95.79995700000001,30.015265],"type":"Point"}
}