{
  "type": "Feature",
  "properties": {
    "iso:country":"US",
    "sg:address":"1001 Paluxy Rd",
    "sg:city":"Granbury",
    "sg:classifiers":[
        {
            "category":"Health Services",
            "subcategory":"Optometrist",
            "type":"Services"
        }
    ],
    "sg:phone":"+1 817 579 0100",
    "sg:postcode":"76048",
    "sg:province":"TX",
    "wof:name":"Byrd Brenda OD",
    "wof:placetype":"venue"
},
  "geometry": {"coordinates":[-97.799126,32.434575],"type":"Point"}
}