{
  "type": "Feature",
  "properties": {
    "iso:country":"US",
    "sg:address":"828 E 19th St",
    "sg:city":"San Angelo",
    "sg:classifiers":[
        {
            "category":"Retail",
            "subcategory":"Auto Repair",
            "type":"Services"
        }
    ],
    "sg:phone":"+1 325 658 1636",
    "sg:postcode":"76903",
    "sg:province":"TX",
    "sg:tags":[
        "body",
        "automobile",
        "painting"
    ],
    "wof:name":"Blanco's Paint & Body Shop",
    "wof:placetype":"venue"
},
  "geometry": {"coordinates":[-100.436024,31.482099],"type":"Point"}
}