{
  "type": "Feature",
  "properties": {
    "iso:country":"US",
    "sg:address":"1255 W 15th St",
    "sg:city":"Plano",
    "sg:classifiers":[
        {
            "category":"Restaurant",
            "type":"Food & Drink"
        }
    ],
    "sg:phone":"+1 972 578 5052",
    "sg:postcode":"75075",
    "sg:province":"TX",
    "sg:tags":[
        "sandwich"
    ],
    "wof:name":"Pop's Sandwich Shop",
    "wof:placetype":"venue"
},
  "geometry": {"coordinates":[-96.718338,33.01944],"type":"Point"}
}