{
  "type": "Feature",
  "properties": {
    "iso:country":"US",
    "sg:address":"19411 Rio Villa Dr",
    "sg:city":"Houston",
    "sg:classifiers":[
        {
            "category":"Retail",
            "subcategory":"Repair Shop",
            "type":"Services"
        }
    ],
    "sg:phone":"+1 281 452 4783",
    "sg:postcode":"77049",
    "sg:province":"TX",
    "sg:tags":[
        "welding"
    ],
    "wof:name":"Malloy Welding",
    "wof:placetype":"venue"
},
  "geometry": {"coordinates":[-95.080409,29.828449],"type":"Point"}
}