{
  "type": "Feature",
  "properties": {
    "iso:country":"US",
    "sg:address":"8814 Brae Acres Rd",
    "sg:city":"Houston",
    "sg:classifiers":[
        {
            "category":"Professional",
            "subcategory":"Lawyer & Legal Services",
            "type":"Services"
        }
    ],
    "sg:phone":"+1 713 655 1300",
    "sg:postcode":"77074",
    "sg:province":"TX",
    "wof:name":"Salazar Baltazar Atty At Law",
    "wof:placetype":"venue"
},
  "geometry": {"coordinates":[-95.52240500000001,29.683199],"type":"Point"}
}