{
  "type": "Feature",
  "properties": {
    "iso:country":"US",
    "sg:address":"1 White Oak Ct",
    "sg:city":"Wichita Falls",
    "sg:classifiers":[
        {
            "category":"Manufacturing",
            "subcategory":"Wood Products",
            "type":"Manufacturing & Wholesale Goods"
        },
        {
            "category":"Shopping",
            "subcategory":"Gifts & Souvenirs",
            "type":"Retail Goods"
        }
    ],
    "sg:phone":"+1 940 692 5449",
    "sg:postcode":"76308",
    "sg:province":"TX",
    "sg:tags":[
        "shop",
        "stampings",
        "metal",
        "mfg"
    ],
    "wof:name":"Under The White Oak Tree",
    "wof:placetype":"venue"
},
  "geometry": {"coordinates":[-98.53472600000001,33.849869],"type":"Point"}
}