{
  "type": "Feature",
  "properties": {
    "iso:country":"US",
    "sg:address":"4500 Steiner Ranch Blvd",
    "sg:city":"Austin",
    "sg:classifiers":[
        {
            "category":"Professional",
            "subcategory":"Advertising",
            "type":"Services"
        }
    ],
    "sg:phone":"+1 512 266 1510",
    "sg:postcode":"78732",
    "sg:province":"TX",
    "sg:tags":[
        "agency"
    ],
    "wof:name":"Dog Trick Studio",
    "wof:placetype":"venue"
},
  "geometry": {"coordinates":[-97.870733,30.390023],"type":"Point"}
}