{
  "type": "Feature",
  "properties": {
    "iso:country":"US",
    "sg:address":"1227 E Pleasant Run Rd",
    "sg:city":"Dallas",
    "sg:classifiers":[
        {
            "category":"Banks & Credit Unions",
            "subcategory":"Bank",
            "type":"Services"
        }
    ],
    "sg:phone":"+1 972 228 2101",
    "sg:postcode":"75232",
    "sg:province":"TX",
    "wof:name":"Bank of America",
    "wof:placetype":"venue"
},
  "geometry": {"coordinates":[-96.678772,32.733196],"type":"Point"}
}