{
  "type": "Feature",
  "properties": {
    "iso:country":"US",
    "sg:address":"1501 N Amburn Rd",
    "sg:city":"Texas City",
    "sg:classifiers":[
        {
            "category":"Professional",
            "subcategory":"Lawyer & Legal Services",
            "type":"Services"
        }
    ],
    "sg:phone":"+1 409 945 0660",
    "sg:postcode":"77591",
    "sg:province":"TX",
    "sg:tags":[
        "attorney"
    ],
    "sg:website":"www.burwell-nebout.com",
    "wof:name":"Burwell Burwell & Nebout LLP",
    "wof:placetype":"venue"
},
  "geometry": {"coordinates":[-95.003438,29.398072],"type":"Point"}
}