{
  "type": "Feature",
  "properties": {
    "iso:country":"US",
    "sg:address":"480 W Interstate 30",
    "sg:city":"Garland",
    "sg:classifiers":[
        {
            "category":"Restaurant",
            "type":"Food & Drink"
        }
    ],
    "sg:phone":"+1 972 203 1527",
    "sg:postcode":"75043",
    "sg:province":"TX",
    "wof:name":"Williams Chicken",
    "wof:placetype":"venue"
},
  "geometry": {"coordinates":[-96.59339900000001,32.840698],"type":"Point"}
}