{
  "type": "Feature",
  "properties": {
    "iso:country":"US",
    "sg:address":"1827 Norfolk St",
    "sg:city":"Houston",
    "sg:classifiers":[
        {
            "category":"Professional",
            "subcategory":"Management & Consulting",
            "type":"Services"
        }
    ],
    "sg:phone":"+1 713 432 1881",
    "sg:postcode":"77098",
    "sg:province":"TX",
    "wof:name":"Decisioniong Resources",
    "wof:placetype":"venue"
},
  "geometry": {"coordinates":[-95.40642099999999,29.732529],"type":"Point"}
}