{
  "type": "Feature",
  "properties": {
    "iso:country":"US",
    "sg:address":"1123 Babcock Rd",
    "sg:city":"San Antonio",
    "sg:classifiers":[
        {
            "category":"Health Services",
            "subcategory":"Doctor",
            "type":"Services"
        }
    ],
    "sg:phone":"+1 210 697 7078",
    "sg:postcode":"78201",
    "sg:province":"TX",
    "wof:name":"Shannon Savagecerna DDS",
    "wof:placetype":"venue"
},
  "geometry": {"coordinates":[-98.558533,29.484363],"type":"Point"}
}