{
  "type": "Feature",
  "properties": {
    "iso:country":"US",
    "sg:address":"1435 S Main St",
    "sg:city":"Vidor",
    "sg:classifiers":[
        {
            "category":"Building & Trades",
            "subcategory":"Construction",
            "type":"Services"
        }
    ],
    "sg:phone":"+1 409 769 9111",
    "sg:postcode":"77662",
    "sg:province":"TX",
    "sg:tags":[
        "steel",
        "erectors"
    ],
    "wof:name":"A Ace Modular Bldg & Erectors",
    "wof:placetype":"venue"
},
  "geometry": {"coordinates":[-94.006908,30.108712],"type":"Point"}
}