{
  "type": "Feature",
  "properties": {
    "iso:country":"US",
    "sg:address":"342 Schmeltzer Ln",
    "sg:city":"San Antonio",
    "sg:classifiers":[
        {
            "category":"Building & Trades",
            "subcategory":"Plumbing",
            "type":"Services"
        }
    ],
    "sg:phone":"+1 210 344 9611",
    "sg:postcode":"78213",
    "sg:province":"TX",
    "sg:tags":[
        "contractor"
    ],
    "wof:name":"Haensel Air Conditioning & Htg",
    "wof:placetype":"venue"
},
  "geometry": {"coordinates":[-98.516296,29.498229],"type":"Point"}
}