{
  "type": "Feature",
  "properties": {
    "iso:country":"US",
    "sg:address":"3030 N Josey Ln Ste 126",
    "sg:city":"Carrollton",
    "sg:classifiers":[
        {
            "category":"Shopping",
            "subcategory":"Beauty & Cosmetics",
            "type":"Retail Goods"
        }
    ],
    "sg:phone":"+1 972 492 9404",
    "sg:postcode":"75007",
    "sg:province":"TX",
    "sg:tags":[
        "supply"
    ],
    "wof:name":"Queens Beauty Supply",
    "wof:placetype":"venue"
},
  "geometry": {"coordinates":[-96.88674899999999,32.997199],"type":"Point"}
}