{
  "type": "Feature",
  "properties": {
    "iso:country":"US",
    "sg:address":"618 N McColl Rd",
    "sg:city":"Mcallen",
    "sg:classifiers":[
        {
            "category":"Education",
            "subcategory":"Special Training",
            "type":"Public Place"
        }
    ],
    "sg:phone":"+1 956 687 2257",
    "sg:postcode":"78501",
    "sg:province":"TX",
    "sg:tags":[
        "school",
        "language"
    ],
    "wof:name":"CCLS Cultural Ctr-Language",
    "wof:placetype":"venue"
},
  "geometry": {"coordinates":[-98.211493,26.208375],"type":"Point"}
}