{
  "type": "Feature",
  "properties": {
    "iso:country":"US",
    "sg:address":"2308 Roberts Cir",
    "sg:city":"Arlington",
    "sg:classifiers":[
        {
            "category":"Professional",
            "subcategory":"Business Services",
            "type":"Services"
        }
    ],
    "sg:phone":"+1 817 469 6978",
    "sg:postcode":"76010",
    "sg:province":"TX",
    "wof:name":"Creative Works",
    "wof:placetype":"venue"
},
  "geometry": {"coordinates":[-97.066941,32.731304],"type":"Point"}
}