{
  "type": "Feature",
  "properties": {
    "iso:country":"US",
    "sg:address":"21947 Katy Fwy",
    "sg:city":"Katy",
    "sg:classifiers":[
        {
            "category":"Shopping",
            "type":"Retail Goods"
        }
    ],
    "sg:phone":"+1 281 398 1647",
    "sg:postcode":"77450",
    "sg:province":"TX",
    "sg:tags":[
        "glass",
        "merchandise",
        "mfg"
    ],
    "wof:name":"Patricias Folly",
    "wof:placetype":"venue"
},
  "geometry": {"coordinates":[-95.752909,29.783297],"type":"Point"}
}