{
  "type": "Feature",
  "properties": {
    "iso:country":"US",
    "sg:address":"20111 Co Rd 684B",
    "sg:city":"Sweeny",
    "sg:classifiers":[
        {
            "category":"Retail",
            "subcategory":"Repair Shop",
            "type":"Services"
        }
    ],
    "sg:phone":"+1 979 345 2894",
    "sg:postcode":"77480",
    "sg:province":"TX",
    "sg:tags":[
        "welding"
    ],
    "wof:name":"Montes Welding",
    "wof:placetype":"venue"
},
  "geometry": {"coordinates":[-95.677796,29.097815],"type":"Point"}
}