{
  "type": "Feature",
  "properties": {
    "iso:country":"US",
    "sg:address":"2601 Co Rd 180",
    "sg:city":"Brownwood",
    "sg:classifiers":[
        {
            "category":"Wholesale",
            "subcategory":"Sporting Goods",
            "type":"Manufacturing & Wholesale Goods"
        },
        {
            "category":"Recreation",
            "type":"Entertainment"
        }
    ],
    "sg:phone":"+1 325 649 0900",
    "sg:postcode":"76801",
    "sg:province":"TX",
    "sg:tags":[
        "ammunition"
    ],
    "wof:name":"Wayne's Range",
    "wof:placetype":"venue"
},
  "geometry": {"coordinates":[-99.032599,31.707469],"type":"Point"}
}