{
  "type": "Feature",
  "properties": {
    "iso:country":"US",
    "sg:address":"3924 W Park Ave",
    "sg:city":"Orange",
    "sg:classifiers":[
        {
            "category":"Building & Trades",
            "subcategory":"Pest Control",
            "type":"Services"
        }
    ],
    "sg:phone":"+1 409 886 2828",
    "sg:postcode":"77630",
    "sg:province":"TX",
    "wof:name":"Bill Clark Pest Control Inc",
    "wof:placetype":"venue"
},
  "geometry": {"coordinates":[-93.78012699999999,30.10998],"type":"Point"}
}