{
  "type": "Feature",
  "properties": {
    "iso:country":"US",
    "sg:address":"4310 Childress St",
    "sg:city":"Houston",
    "sg:classifiers":[
        {
            "category":"Arts & Performance",
            "subcategory":"Theater",
            "type":"Entertainment"
        }
    ],
    "sg:phone":"+1 713 664 7537",
    "sg:postcode":"77005",
    "sg:province":"TX",
    "sg:tags":[
        "group"
    ],
    "wof:name":"Celtic New Year",
    "wof:placetype":"venue"
},
  "geometry": {"coordinates":[-95.444991,29.726756],"type":"Point"}
}