{
  "type": "Feature",
  "properties": {
    "iso:country":"US",
    "sg:address":"133 Dylan Dr",
    "sg:city":"Prosper",
    "sg:classifiers":[
        {
            "category":"Manufacturing",
            "subcategory":"Signs",
            "type":"Manufacturing & Wholesale Goods"
        }
    ],
    "sg:phone":"+1 972 346 9111",
    "sg:postcode":"75078",
    "sg:province":"TX",
    "sg:tags":[
        "specialty",
        "mfg"
    ],
    "wof:name":"Texas Signs & Engraving",
    "wof:placetype":"venue"
},
  "geometry": {"coordinates":[-96.802328,33.260605],"type":"Point"}
}