{
  "type": "Feature",
  "properties": {
    "iso:country":"US",
    "sg:address":"3008 34th St",
    "sg:city":"Lubbock",
    "sg:classifiers":[
        {
            "category":"Health Services",
            "subcategory":"Doctor",
            "type":"Services"
        }
    ],
    "sg:phone":"+1 806 785 6677",
    "sg:postcode":"79410",
    "sg:province":"TX",
    "sg:tags":[
        "physician",
        "surgeon"
    ],
    "wof:name":"M Margee MD",
    "wof:placetype":"venue"
},
  "geometry": {"coordinates":[-101.881119,33.563341],"type":"Point"}
}