{
  "type": "Feature",
  "properties": {
    "iso:country":"US",
    "sg:address":"2890 Co Rd 4516",
    "sg:city":"Hondo",
    "sg:classifiers":[
        {
            "category":"Wholesale",
            "subcategory":"Construction Materials",
            "type":"Manufacturing & Wholesale Goods"
        }
    ],
    "sg:phone":"+1 830 741 8055",
    "sg:postcode":"78861",
    "sg:province":"TX",
    "wof:name":"K & R Gate Systems",
    "wof:placetype":"venue"
},
  "geometry": {"coordinates":[-98.96570199999999,29.370801],"type":"Point"}
}