{
  "type": "Feature",
  "properties": {
    "iso:country":"US",
    "sg:address":"5745 Christy Ln",
    "sg:city":"Haltom City",
    "sg:classifiers":[
        {
            "category":"Shopping",
            "type":"Retail Goods"
        }
    ],
    "sg:phone":"+1 817 605 3765",
    "sg:postcode":"76137",
    "sg:province":"TX",
    "sg:tags":[
        "miscellaneous",
        "store"
    ],
    "wof:name":"F W Creek Side",
    "wof:placetype":"venue"
},
  "geometry": {"coordinates":[-97.289428,32.850881],"type":"Point"}
}