{
  "type": "Feature",
  "properties": {
    "iso:country":"US",
    "sg:address":"11619 Palmsprings Dr",
    "sg:city":"Houston",
    "sg:classifiers":[
        {
            "category":"Building & Trades",
            "subcategory":"Construction",
            "type":"Services"
        }
    ],
    "sg:phone":"+1 713 943 1877",
    "sg:postcode":"77034",
    "sg:province":"TX",
    "sg:tags":[
        "concrete",
        "contractor"
    ],
    "wof:name":"Coast 2 Coast",
    "wof:placetype":"venue"
},
  "geometry": {"coordinates":[-95.217056,29.623255],"type":"Point"}
}