{
  "type": "Feature",
  "properties": {
    "iso:country":"US",
    "sg:address":"318 S 14th St",
    "sg:city":"Junction",
    "sg:classifiers":[
        {
            "category":"Shopping",
            "subcategory":"Florist",
            "type":"Retail Goods"
        }
    ],
    "sg:phone":"+1 325 446 2716",
    "sg:postcode":"76849",
    "sg:province":"TX",
    "wof:name":"Up My Alley Greenhouse",
    "wof:placetype":"venue"
},
  "geometry": {"coordinates":[-99.774224,30.485333],"type":"Point"}
}