{
  "type": "Feature",
  "properties": {
    "iso:country":"US",
    "sg:address":"2605 Freewood Dr",
    "sg:city":"Dallas",
    "sg:classifiers":[
        {
            "category":"Professional",
            "subcategory":"Computer Services",
            "type":"Services"
        }
    ],
    "sg:phone":"+1 214 352 7000",
    "sg:postcode":"75220",
    "sg:province":"TX",
    "sg:tags":[
        "repair"
    ],
    "sg:website":"www.bellagraniti.com",
    "wof:name":"Bella Graniti",
    "wof:placetype":"venue"
},
  "geometry": {"coordinates":[-96.889955,32.870647],"type":"Point"}
}