{
  "type": "Feature",
  "properties": {
    "iso:country":"US",
    "sg:address":"1814 Ward Ave",
    "sg:city":"San Angelo",
    "sg:classifiers":[
        {
            "category":"Real Estate",
            "subcategory":"Real Estate Agent",
            "type":"Services"
        }
    ],
    "sg:phone":"+1 325 653 1211",
    "sg:postcode":"76901",
    "sg:province":"TX",
    "wof:name":"Curry Realty Co",
    "wof:placetype":"venue"
},
  "geometry": {"coordinates":[-100.46173,31.454928],"type":"Point"}
}