{
  "type": "Feature",
  "properties": {
    "iso:country":"US",
    "sg:address":"12111 W Bellfort St",
    "sg:city":"Stafford",
    "sg:classifiers":[
        {
            "category":"Organizations",
            "subcategory":"Religious Organization",
            "type":"Services"
        }
    ],
    "sg:phone":"+1 281 498 5047",
    "sg:postcode":"77477",
    "sg:province":"TX",
    "sg:tags":[
        "church"
    ],
    "wof:name":"All Saints Lutheran Church",
    "wof:placetype":"venue"
},
  "geometry": {"coordinates":[-95.588741,29.657856],"type":"Point"}
}