{
  "type": "Feature",
  "properties": {
    "iso:country":"US",
    "sg:address":"203 Lakeridge Dr",
    "sg:city":"Dallas",
    "sg:classifiers":[
        {
            "category":"Professional",
            "subcategory":"Accounting & Tax Preparation",
            "type":"Services"
        }
    ],
    "sg:phone":"+1 214 575 9430",
    "sg:postcode":"75218",
    "sg:province":"TX",
    "wof:name":"Verucchi & Assoc PC",
    "wof:placetype":"venue"
},
  "geometry": {"coordinates":[-96.711489,32.859855],"type":"Point"}
}