{
  "type": "Feature",
  "properties": {
    "iso:country":"US",
    "sg:address":"2626 Cole Ave Ste 400",
    "sg:city":"Dallas",
    "sg:classifiers":[
        {
            "category":"Building & Trades",
            "subcategory":"Construction",
            "type":"Services"
        }
    ],
    "sg:phone":"+1 214 871 7550",
    "sg:postcode":"75204",
    "sg:province":"TX",
    "sg:tags":[
        "contractor"
    ],
    "wof:name":"McKee W & Associates",
    "wof:placetype":"venue"
},
  "geometry": {"coordinates":[-96.80500000000001,32.799599],"type":"Point"}
}