{
  "type": "Feature",
  "properties": {
    "iso:country":"US",
    "sg:address":"139 FM 1996",
    "sg:city":"Oglesby",
    "sg:classifiers":[
        {
            "category":"Real Estate",
            "subcategory":"Developer",
            "type":"Services"
        }
    ],
    "sg:phone":"+1 254 470 2317",
    "sg:postcode":"76561",
    "sg:province":"TX",
    "sg:tags":[
        "cemetery"
    ],
    "wof:name":"Post Oak Cemetery Assoc",
    "wof:placetype":"venue"
},
  "geometry": {"coordinates":[-97.508914,31.414167],"type":"Point"}
}