{
  "type": "Feature",
  "properties": {
    "iso:country":"US",
    "sg:address":"2501 Westridge",
    "sg:city":"Houston",
    "sg:classifiers":[
        {
            "category":"Real Estate",
            "subcategory":"Real Estate Operator",
            "type":"Services"
        }
    ],
    "sg:phone":"+1 713 667 6741",
    "sg:postcode":"77054",
    "sg:province":"TX",
    "sg:tags":[
        "building",
        "apartment"
    ],
    "wof:name":"L L Mangement",
    "wof:placetype":"venue"
},
  "geometry": {"coordinates":[-95.415952,29.682059],"type":"Point"}
}