{
  "type": "Feature",
  "properties": {
    "iso:country":"US",
    "sg:address":"5358 Montego Cove Dr",
    "sg:city":"Willis",
    "sg:classifiers":[
        {
            "category":"Wholesale",
            "subcategory":"Durable Goods & Equipment",
            "type":"Manufacturing & Wholesale Goods"
        }
    ],
    "sg:phone":"+1 936 856 3479",
    "sg:postcode":"77318",
    "sg:province":"TX",
    "sg:tags":[
        "professional"
    ],
    "wof:name":"Garner US Enterprises Inc",
    "wof:placetype":"venue"
},
  "geometry": {"coordinates":[-95.57333199999999,30.412397],"type":"Point"}
}