{
  "type": "Feature",
  "properties": {
    "iso:country":"US",
    "sg:address":"2008 Bosbury Dr",
    "sg:city":"Flower Mound",
    "sg:classifiers":[
        {
            "category":"Wholesale",
            "subcategory":"Machinery & Supplies",
            "type":"Manufacturing & Wholesale Goods"
        }
    ],
    "sg:phone":"+1 972 874 2755",
    "sg:postcode":"75028",
    "sg:province":"TX",
    "sg:tags":[
        "equipment",
        "industrial"
    ],
    "wof:name":"Idec Corp",
    "wof:placetype":"venue"
},
  "geometry": {"coordinates":[-97.03247,33.012139],"type":"Point"}
}