{
  "type": "Feature",
  "properties": {
    "iso:country":"US",
    "sg:address":"1802 W Tyler Ave",
    "sg:city":"Harlingen",
    "sg:classifiers":[
        {
            "category":"Restaurant",
            "type":"Food & Drink"
        }
    ],
    "sg:menulink":"http://www.allmenus.com/tx/harlingen-san-benito/70661-pizza-hut/menu/",
    "sg:phone":"+1 956 425 6520",
    "sg:postcode":"78550",
    "sg:province":"TX",
    "sg:tags":[
        "american",
        "pizza"
    ],
    "wof:name":"Pizza Hut",
    "wof:placetype":"venue"
},
  "geometry": {"coordinates":[-97.71517900000001,26.189489],"type":"Point"}
}