{
  "type": "Feature",
  "properties": {
    "iso:country":"US",
    "sg:address":"10370 Richmond Ave",
    "sg:city":"Houston",
    "sg:classifiers":[
        {
            "category":"Professional",
            "subcategory":"Computer Services",
            "type":"Services"
        }
    ],
    "sg:phone":"+1 713 977 1225",
    "sg:postcode":"77042",
    "sg:province":"TX",
    "sg:tags":[
        "consultant",
        "training",
        "software"
    ],
    "wof:name":"Aveva Inc",
    "wof:placetype":"venue"
},
  "geometry": {"coordinates":[-95.556764,29.727708],"type":"Point"}
}