{
  "type": "Feature",
  "properties": {
    "iso:country":"US",
    "sg:address":"1868 Nacogdoches Rd",
    "sg:city":"San Antonio",
    "sg:classifiers":[
        {
            "category":"Health Services",
            "subcategory":"Health Practitioner",
            "type":"Services"
        }
    ],
    "sg:phone":"+1 210 829 4876",
    "sg:postcode":"78209",
    "sg:province":"TX",
    "sg:tags":[
        "psychologist"
    ],
    "wof:name":"Shelley R Probber Psyd",
    "wof:placetype":"venue"
},
  "geometry": {"coordinates":[-98.458156,29.506318],"type":"Point"}
}