{
  "type": "Feature",
  "properties": {
    "iso:country":"US",
    "sg:address":"1005 Laswell Ln",
    "sg:city":"Bulverde",
    "sg:classifiers":[
        {
            "category":"Restaurant",
            "type":"Food & Drink"
        }
    ],
    "sg:phone":"+1 830 438 5681",
    "sg:postcode":"78163",
    "sg:province":"TX",
    "sg:tags":[
        "barbecue"
    ],
    "wof:name":"Rusty's Bar BQ",
    "wof:placetype":"venue"
},
  "geometry": {"coordinates":[-98.486501,29.80062],"type":"Point"}
}