{
  "type": "Feature",
  "properties": {
    "iso:country":"US",
    "sg:address":"6341 Juneau Rd",
    "sg:city":"Fort Worth",
    "sg:classifiers":[
        {
            "category":"Health Services",
            "subcategory":"Clinic",
            "type":"Services"
        }
    ],
    "sg:phone":"+1 817 737 2919",
    "sg:postcode":"76116",
    "sg:province":"TX",
    "sg:tags":[
        "retardation",
        "mental"
    ],
    "wof:name":"Juneau Residence",
    "wof:placetype":"venue"
},
  "geometry": {"coordinates":[-97.423699,32.746956],"type":"Point"}
}