{
  "type": "Feature",
  "properties": {
    "iso:country":"US",
    "sg:address":"1924 Smith Dr",
    "sg:city":"Plano",
    "sg:classifiers":[
        {
            "category":"Retail",
            "subcategory":"Repair Shop",
            "type":"Services"
        }
    ],
    "sg:phone":"+1 972 517 2881",
    "sg:postcode":"75023",
    "sg:province":"TX",
    "sg:tags":[
        "building",
        "maintenance"
    ],
    "wof:name":"Spenrath Cleaning",
    "wof:placetype":"venue"
},
  "geometry": {"coordinates":[-96.730621,33.069929],"type":"Point"}
}