{
  "type": "Feature",
  "properties": {
    "iso:country":"US",
    "sg:address":"312 S Mirick Ave",
    "sg:city":"Denison",
    "sg:classifiers":[
        {
            "category":"Personal",
            "subcategory":"Barber",
            "type":"Services"
        }
    ],
    "sg:phone":"+1 903 465 9869",
    "sg:postcode":"75020",
    "sg:province":"TX",
    "wof:name":"Davis Barber Shop",
    "wof:placetype":"venue"
},
  "geometry": {"coordinates":[-96.543127,33.752839],"type":"Point"}
}