{
  "type": "Feature",
  "properties": {
    "iso:country":"US",
    "sg:address":"2611 Revere Dr",
    "sg:city":"Pasadena",
    "sg:classifiers":[
        {
            "category":"Professional",
            "subcategory":"Business Services",
            "type":"Services"
        }
    ],
    "sg:phone":"+1 713 941 7921",
    "sg:postcode":"77502",
    "sg:province":"TX",
    "wof:name":"Gilded Acorn Custom Inter",
    "wof:placetype":"venue"
},
  "geometry": {"coordinates":[-95.22754399999999,29.671185],"type":"Point"}
}