{
  "type": "Feature",
  "properties": {
    "iso:country":"US",
    "sg:address":"808 Elizabeth Ave",
    "sg:city":"Rosenberg",
    "sg:classifiers":[
        {
            "category":"Utilities",
            "type":"Services"
        }
    ],
    "sg:phone":"+1 281 341 5642",
    "sg:postcode":"77471",
    "sg:province":"TX",
    "sg:tags":[
        "pond",
        "maintain",
        "lake"
    ],
    "wof:name":"Lake Sense",
    "wof:placetype":"venue"
},
  "geometry": {"coordinates":[-95.819101,29.538175],"type":"Point"}
}