{
  "type": "Feature",
  "properties": {
    "iso:country":"US",
    "sg:address":"320 Howard Langford Dr",
    "sg:city":"Uvalde",
    "sg:classifiers":[
        {
            "category":"Building & Trades",
            "subcategory":"Construction",
            "type":"Services"
        }
    ],
    "sg:phone":"+1 830 278 3375",
    "sg:postcode":"78801",
    "sg:province":"TX",
    "sg:tags":[
        "industrial",
        "painting",
        "contractors-commercial"
    ],
    "sg:website":"http://www.jmaircraftpainting.com",
    "wof:name":"Jim Miller Aircraft Painting Inc",
    "wof:placetype":"venue"
},
  "geometry": {"coordinates":[-99.748161,29.213892],"type":"Point"}
}