{
  "type": "Feature",
  "properties": {
    "iso:country":"US",
    "sg:address":"5732 Burnet Rd",
    "sg:city":"Austin",
    "sg:classifiers":[
        {
            "category":"Wholesale",
            "subcategory":"Stationery",
            "type":"Manufacturing & Wholesale Goods"
        }
    ],
    "sg:phone":"+1 512 451 9188",
    "sg:postcode":"78756",
    "sg:province":"TX",
    "sg:tags":[
        "supply"
    ],
    "wof:name":"Cartridge World",
    "wof:placetype":"venue"
},
  "geometry": {"coordinates":[-97.73993,30.334473],"type":"Point"}
}