{
  "type": "Feature",
  "properties": {
    "iso:country":"US",
    "sg:address":"11875 W Little York Rd",
    "sg:city":"Houston",
    "sg:classifiers":[
        {
            "category":"Professional",
            "type":"Services"
        }
    ],
    "sg:phone":"+1 713 849 0009",
    "sg:postcode":"77041",
    "sg:province":"TX",
    "sg:tags":[
        "establishment"
    ],
    "wof:name":"Kardo",
    "wof:placetype":"venue"
},
  "geometry": {"coordinates":[-95.586996,29.8668],"type":"Point"}
}