{
  "type": "Feature",
  "properties": {
    "iso:country":"US",
    "sg:address":"13711 Fairway Hedge",
    "sg:city":"San Antonio",
    "sg:classifiers":[
        {
            "category":"Education",
            "subcategory":"School",
            "type":"Public Place"
        }
    ],
    "sg:phone":"+1 210 656 4014",
    "sg:postcode":"78217",
    "sg:province":"TX",
    "wof:name":"Kipp Aspire Academy Inc",
    "wof:placetype":"venue"
},
  "geometry": {"coordinates":[-98.410382,29.566668],"type":"Point"}
}