{
  "type": "Feature",
  "properties": {
    "iso:country":"US",
    "sg:address":"11409 Scott St",
    "sg:city":"Houston",
    "sg:classifiers":[
        {
            "category":"Building & Trades",
            "subcategory":"Construction",
            "type":"Services"
        }
    ],
    "sg:phone":"+1 713 731 2800",
    "sg:postcode":"77047",
    "sg:province":"TX",
    "sg:tags":[
        "consultant"
    ],
    "wof:name":"South Acres Ranch Ltd",
    "wof:placetype":"venue"
},
  "geometry": {"coordinates":[-95.368088,29.60009],"type":"Point"}
}