{
  "type": "Feature",
  "properties": {
    "iso:country":"US",
    "sg:address":"2406 San Gabriel St",
    "sg:city":"Austin",
    "sg:classifiers":[
        {
            "category":"Shopping",
            "subcategory":"Pharmacy",
            "type":"Retail Goods"
        }
    ],
    "sg:phone":"+1 512 472 1424",
    "sg:postcode":"78705",
    "sg:province":"TX",
    "sg:tags":[
        "drugstore"
    ],
    "wof:name":"Nau Pharmacy",
    "wof:placetype":"venue"
},
  "geometry": {"coordinates":[-97.747597,30.2889],"type":"Point"}
}