{
  "type": "Feature",
  "properties": {
    "iso:country":"US",
    "sg:address":"16404 Malden Dr",
    "sg:city":"Pflugerville",
    "sg:classifiers":[
        {
            "category":"Building & Trades",
            "subcategory":"Cleaning & Sanitation",
            "type":"Services"
        }
    ],
    "sg:phone":"+1 512 989 5883",
    "sg:postcode":"78660",
    "sg:province":"TX",
    "sg:tags":[
        "maintenance"
    ],
    "wof:name":"Nicks Cleaning Services",
    "wof:placetype":"venue"
},
  "geometry": {"coordinates":[-97.643221,30.453901],"type":"Point"}
}