{
  "type": "Feature",
  "properties": {
    "iso:country":"US",
    "sg:address":"1391 S Hulgan Cir",
    "sg:city":"De Soto",
    "sg:classifiers":[
        {
            "category":"Organizations",
            "subcategory":"Religious Organization",
            "type":"Services"
        }
    ],
    "sg:phone":"+1 972 230 0564",
    "sg:postcode":"75115",
    "sg:province":"TX",
    "wof:name":"Saint Mark Family Development",
    "wof:placetype":"venue"
},
  "geometry": {"coordinates":[-96.896261,32.580022],"type":"Point"}
}