{
  "type": "Feature",
  "properties": {
    "iso:country":"US",
    "sg:address":"1615 Lakeville Dr",
    "sg:city":"Kingwood",
    "sg:classifiers":[
        {
            "category":"Building & Trades",
            "subcategory":"Construction",
            "type":"Services"
        }
    ],
    "sg:phone":"+1 281 359 5426",
    "sg:postcode":"77339",
    "sg:province":"TX",
    "sg:tags":[
        "general",
        "contractor"
    ],
    "wof:name":"Ellisor Constructors",
    "wof:placetype":"venue"
},
  "geometry": {"coordinates":[-95.22752800000001,30.052327],"type":"Point"}
}