{
  "type": "Feature",
  "properties": {
    "iso:country":"US",
    "sg:address":"900 Wiltshire Ave",
    "sg:city":"San Antonio",
    "sg:classifiers":[
        {
            "category":"Professional",
            "subcategory":"Management & Consulting",
            "type":"Services"
        }
    ],
    "sg:phone":"+1 210 824 7449",
    "sg:postcode":"78209",
    "sg:province":"TX",
    "sg:tags":[
        "consultant"
    ],
    "wof:name":"Spectra-Market Metrics",
    "wof:placetype":"venue"
},
  "geometry": {"coordinates":[-98.448989,29.482744],"type":"Point"}
}