{
  "type": "Feature",
  "properties": {
    "iso:country":"US",
    "sg:address":"921 E Main St",
    "sg:city":"Teague",
    "sg:classifiers":[
        {
            "category":"Professional",
            "type":"Services"
        }
    ],
    "sg:phone":"+1 254 739 3430",
    "sg:postcode":"75860",
    "sg:province":"TX",
    "wof:name":"Fast N Fair Inc",
    "wof:placetype":"venue"
},
  "geometry": {"coordinates":[-96.277807,31.626757],"type":"Point"}
}