{
  "type": "Feature",
  "properties": {
    "iso:country":"US",
    "sg:address":"6509 Winn Dr",
    "sg:city":"Fort Worth",
    "sg:classifiers":[
        {
            "category":"Professional",
            "type":"Services"
        }
    ],
    "sg:phone":"+1 817 551 1563",
    "sg:postcode":"76134",
    "sg:province":"TX",
    "wof:name":"Caracal Designs",
    "wof:placetype":"venue"
},
  "geometry": {"coordinates":[-97.340129,32.650363],"type":"Point"}
}