{
  "type": "Feature",
  "properties": {
    "iso:country":"US",
    "sg:address":"121 State Hwy 83",
    "sg:city":"Seminole",
    "sg:classifiers":[
        {
            "category":"Farming",
            "subcategory":"Livestock Farm",
            "type":"Manufacturing & Wholesale Goods"
        }
    ],
    "sg:phone":"+1 806 732 8611",
    "sg:postcode":"79323",
    "sg:province":"TX",
    "sg:tags":[
        "producer"
    ],
    "wof:name":"Shoestring Cattle Co",
    "wof:placetype":"venue"
},
  "geometry": {"coordinates":[-102.828204,32.964483],"type":"Point"}
}