{
  "type": "Feature",
  "properties": {
    "iso:country":"US",
    "sg:address":"1809 W Frontage Rd",
    "sg:city":"Van Horn",
    "sg:classifiers":[
        {
            "category":"Autos & Motor Vehicles",
            "subcategory":"Fuel & Gas Station",
            "type":"Retail Goods"
        }
    ],
    "sg:phone":"+1 432 283 2343",
    "sg:postcode":"79855",
    "sg:province":"TX",
    "sg:tags":[
        "plaza",
        "truck",
        "stops"
    ],
    "wof:name":"High Country Ventures Inc",
    "wof:placetype":"venue"
},
  "geometry": {"coordinates":[-104.855684,31.036239],"type":"Point"}
}