{
  "type": "Feature",
  "properties": {
    "iso:country":"US",
    "sg:address":"401 N Elm St",
    "sg:city":"Denton",
    "sg:classifiers":[
        {
            "category":"Professional",
            "subcategory":"Management & Consulting",
            "type":"Services"
        }
    ],
    "sg:phone":"+1 940 380 2436",
    "sg:postcode":"76201",
    "sg:province":"TX",
    "wof:name":"Hea Management Service",
    "wof:placetype":"venue"
},
  "geometry": {"coordinates":[-97.133724,33.21728],"type":"Point"}
}