{
  "type": "Feature",
  "properties": {
    "iso:country":"US",
    "sg:address":"513 N Cuernavaca Dr Apt A",
    "sg:city":"Austin",
    "sg:classifiers":[
        {
            "category":"Building & Trades",
            "subcategory":"Construction",
            "type":"Services"
        }
    ],
    "sg:phone":"+1 512 837 1666",
    "sg:postcode":"78733",
    "sg:province":"TX",
    "sg:tags":[
        "pool",
        "swimming"
    ],
    "wof:name":"Austin Water Designs",
    "wof:placetype":"venue"
},
  "geometry": {"coordinates":[-97.87085399999999,30.329522],"type":"Point"}
}