{
  "type": "Feature",
  "properties": {
    "iso:country":"US",
    "sg:address":"2415 Brookchase Dr",
    "sg:city":"Mesquite",
    "sg:classifiers":[
        {
            "category":"Travel",
            "subcategory":"Travel Agent",
            "type":"Entertainment"
        }
    ],
    "sg:phone":"+1 972 222 0365",
    "sg:postcode":"75181",
    "sg:province":"TX",
    "sg:tags":[
        "agency",
        "bureau"
    ],
    "wof:name":"Indus Travel",
    "wof:placetype":"venue"
},
  "geometry": {"coordinates":[-96.561511,32.752581],"type":"Point"}
}