{
  "type": "Feature",
  "properties": {
    "iso:country":"US",
    "sg:address":"8310 Precinct Line Rd",
    "sg:city":"Colleyville",
    "sg:classifiers":[
        {
            "category":"Building & Trades",
            "subcategory":"Plumbing",
            "type":"Services"
        }
    ],
    "sg:phone":"+1 817 577 5400",
    "sg:postcode":"76034",
    "sg:province":"TX",
    "sg:tags":[
        "contractor"
    ],
    "wof:name":"Dfw Plumbing Service",
    "wof:placetype":"venue"
},
  "geometry": {"coordinates":[-97.18653,32.905289],"type":"Point"}
}