{
  "type": "Feature",
  "properties": {
    "iso:country":"US",
    "sg:address":"8959 Westheimer Rd",
    "sg:city":"Houston",
    "sg:classifiers":[
        {
            "category":"Retail",
            "subcategory":"Laundry & Dry Cleaning",
            "type":"Services"
        }
    ],
    "sg:phone":"+1 713 789 9813",
    "sg:postcode":"77063",
    "sg:province":"TX",
    "wof:name":"Expert Cleaners",
    "wof:placetype":"venue"
},
  "geometry": {"coordinates":[-95.522899,29.737234],"type":"Point"}
}