{
  "type": "Feature",
  "properties": {
    "iso:country":"US",
    "sg:address":"1616 Blanco Rd",
    "sg:city":"San Antonio",
    "sg:classifiers":[
        {
            "category":"Education",
            "subcategory":"School",
            "type":"Public Place"
        }
    ],
    "sg:phone":"+1 210 733 8641",
    "sg:postcode":"78212",
    "sg:province":"TX",
    "sg:tags":[
        "elementary"
    ],
    "wof:name":"Agnes Cotton Elementary School",
    "wof:placetype":"venue"
},
  "geometry": {"coordinates":[-98.50780399999999,29.461359],"type":"Point"}
}