{
  "type": "Feature",
  "properties": {
    "iso:country":"US",
    "sg:address":"11723 Greenbay Dr",
    "sg:city":"Houston",
    "sg:classifiers":[
        {
            "category":"Shopping",
            "subcategory":"Florist",
            "type":"Retail Goods"
        }
    ],
    "sg:phone":"+1 713 467 6626",
    "sg:postcode":"77024",
    "sg:province":"TX",
    "wof:name":"Matsuen Bonsai",
    "wof:placetype":"venue"
},
  "geometry": {"coordinates":[-95.529134,29.762786],"type":"Point"}
}