{
  "type": "Feature",
  "properties": {
    "iso:country":"US",
    "sg:address":"140 W Camp Wisdom Rd",
    "sg:city":"Duncanville",
    "sg:classifiers":[
        {
            "category":"Personal",
            "subcategory":"Beauty Salon",
            "type":"Services"
        }
    ],
    "sg:phone":"+1 972 780 7100",
    "sg:postcode":"75116",
    "sg:province":"TX",
    "wof:name":"Beauty X",
    "wof:placetype":"venue"
},
  "geometry": {"coordinates":[-96.90736,32.661764],"type":"Point"}
}