{
  "type": "Feature",
  "properties": {
    "iso:country":"US",
    "sg:address":"1115 N 11th St",
    "sg:city":"Beaumont",
    "sg:classifiers":[
        {
            "category":"Retail",
            "subcategory":"Laundry & Dry Cleaning",
            "type":"Services"
        }
    ],
    "sg:phone":"+1 409 899 9779",
    "sg:postcode":"77702",
    "sg:province":"TX",
    "sg:tags":[
        "cleaner",
        "commercial"
    ],
    "wof:name":"A-1 Dry Cleaners",
    "wof:placetype":"venue"
},
  "geometry": {"coordinates":[-94.12993,30.091592],"type":"Point"}
}