{
  "type": "Feature",
  "properties": {
    "iso:country":"US",
    "sg:address":"12068 Co Rd 433",
    "sg:city":"Tyler",
    "sg:classifiers":[
        {
            "category":"Sports & Exercise",
            "subcategory":"Race Track",
            "type":"Entertainment"
        }
    ],
    "sg:phone":"+1 903 882 4215",
    "sg:postcode":"75704",
    "sg:province":"TX",
    "sg:tags":[
        "operation",
        "racing",
        "or"
    ],
    "wof:name":"Swan M X Park Inc",
    "wof:placetype":"venue"
},
  "geometry": {"coordinates":[-95.40374300000001,32.445658],"type":"Point"}
}