{
  "type": "Feature",
  "properties": {
    "iso:country":"US",
    "sg:address":"8217 Homewood Ln",
    "sg:city":"Houston",
    "sg:classifiers":[
        {
            "category":"Autos & Motor Vehicles",
            "subcategory":"Automobile Sales",
            "type":"Retail Goods"
        }
    ],
    "sg:phone":"+1 713 633 7327",
    "sg:postcode":"77028",
    "sg:province":"TX",
    "sg:tags":[
        "used"
    ],
    "wof:name":"Payless Car Sales",
    "wof:placetype":"venue"
},
  "geometry": {"coordinates":[-95.273652,29.842517],"type":"Point"}
}