{
  "type": "Feature",
  "properties": {
    "iso:country":"US",
    "sg:address":"6076 Maravillas River St",
    "sg:city":"Brownsville",
    "sg:classifiers":[
        {
            "category":"Manufacturing",
            "subcategory":"Tools & Machinery",
            "type":"Manufacturing & Wholesale Goods"
        }
    ],
    "sg:phone":"+1 956 350 0704",
    "sg:postcode":"78526",
    "sg:province":"TX",
    "sg:tags":[
        "steel"
    ],
    "wof:name":"Lamination Specialties",
    "wof:placetype":"venue"
},
  "geometry": {"coordinates":[-97.518552,25.995147],"type":"Point"}
}