{
  "type": "Feature",
  "properties": {
    "iso:country":"US",
    "sg:address":"9666 Scyene Rd",
    "sg:city":"Dallas",
    "sg:classifiers":[
        {
            "category":"Social Services",
            "subcategory":"Child Care",
            "type":"Services"
        }
    ],
    "sg:phone":"+1 214 664 9886",
    "sg:postcode":"75227",
    "sg:province":"TX",
    "wof:name":"God's Angels",
    "wof:placetype":"venue"
},
  "geometry": {"coordinates":[-96.656592,32.762655],"type":"Point"}
}