{
  "type": "Feature",
  "properties": {
    "iso:country":"US",
    "sg:address":"1204 N Mechanic St",
    "sg:city":"El Campo",
    "sg:classifiers":[
        {
            "category":"Personal",
            "subcategory":"Barber",
            "type":"Services"
        }
    ],
    "sg:phone":"+1 979 543 9131",
    "sg:postcode":"77437",
    "sg:province":"TX",
    "sg:tags":[
        "shop"
    ],
    "wof:name":"Andrews Style Shop",
    "wof:placetype":"venue"
},
  "geometry": {"coordinates":[-96.27636,29.204856],"type":"Point"}
}