{
  "type": "Feature",
  "properties": {
    "iso:country":"US",
    "sg:address":"1415 Hunter Ridge Ct",
    "sg:city":"Fresno",
    "sg:classifiers":[
        {
            "category":"Arts & Performance",
            "subcategory":"Theater",
            "type":"Entertainment"
        }
    ],
    "sg:phone":"+1 281 431 9934",
    "sg:postcode":"77545",
    "sg:province":"TX",
    "sg:tags":[
        "group"
    ],
    "wof:name":"Original Style Productions",
    "wof:placetype":"venue"
},
  "geometry": {"coordinates":[-95.472487,29.518791],"type":"Point"}
}