{
  "type": "Feature",
  "properties": {
    "iso:country":"US",
    "sg:address":"7006 Chiswick Dr",
    "sg:city":"Corpus Christi",
    "sg:classifiers":[
        {
            "category":"Professional",
            "subcategory":"Accounting & Tax Preparation",
            "type":"Services"
        }
    ],
    "sg:phone":"+1 361 980 1390",
    "sg:postcode":"78413",
    "sg:province":"TX",
    "sg:tags":[
        "return"
    ],
    "wof:name":"Levines Accounting & Income",
    "wof:placetype":"venue"
},
  "geometry": {"coordinates":[-97.399383,27.669135],"type":"Point"}
}