{
  "type": "Feature",
  "properties": {
    "iso:country":"US",
    "sg:address":"1008 Green Ave",
    "sg:city":"Orange",
    "sg:classifiers":[
        {
            "category":"Insurance",
            "subcategory":"Insurance Agent",
            "type":"Services"
        }
    ],
    "sg:phone":"+1 409 883 3567",
    "sg:postcode":"77630",
    "sg:province":"TX",
    "wof:name":"Orange Insurance",
    "wof:placetype":"venue"
},
  "geometry": {"coordinates":[-93.740009,30.093158],"type":"Point"}
}