{
  "type": "Feature",
  "properties": {
    "iso:country":"US",
    "sg:address":"4226 Bayglen Ct",
    "sg:city":"Houston",
    "sg:classifiers":[
        {
            "category":"Professional",
            "subcategory":"Management & Consulting",
            "type":"Services"
        }
    ],
    "sg:phone":"+1 281 444 2048",
    "sg:postcode":"77068",
    "sg:province":"TX",
    "sg:tags":[
        "fuel"
    ],
    "wof:name":"City & Town Management Svc",
    "wof:placetype":"venue"
},
  "geometry": {"coordinates":[-95.50322300000001,30.003294],"type":"Point"}
}