{
  "type": "Feature",
  "properties": {
    "iso:country":"US",
    "sg:address":"1519 Inverness Rd",
    "sg:city":"Mansfield",
    "sg:classifiers":[
        {
            "category":"Manufacturing",
            "subcategory":"Metals",
            "type":"Manufacturing & Wholesale Goods"
        }
    ],
    "sg:phone":"+1 817 473 2167",
    "sg:postcode":"76063",
    "sg:province":"TX",
    "sg:tags":[
        "barrels",
        "drum"
    ],
    "wof:name":"Ken Batson",
    "wof:placetype":"venue"
},
  "geometry": {"coordinates":[-97.12206500000001,32.591739],"type":"Point"}
}