{
  "type": "Feature",
  "properties": {
    "iso:country":"US",
    "sg:address":"213 Loma Vista Dr",
    "sg:city":"Kerrville",
    "sg:classifiers":[
        {
            "category":"Organizations",
            "subcategory":"Religious Organization",
            "type":"Services"
        }
    ],
    "sg:phone":"+1 830 896 4560",
    "sg:postcode":"78028",
    "sg:province":"TX",
    "sg:tags":[
        "church"
    ],
    "wof:name":"Uu Fellowship Of Kerrville",
    "wof:placetype":"venue"
},
  "geometry": {"coordinates":[-99.145335,30.030507],"type":"Point"}
}