{
  "type": "Feature",
  "properties": {
    "iso:country":"US",
    "sg:address":"4242 Woodcock Dr",
    "sg:city":"San Antonio",
    "sg:classifiers":[
        {
            "category":"Insurance",
            "subcategory":"Insurance Agent",
            "type":"Services"
        }
    ],
    "sg:phone":"+1 210 736 2448",
    "sg:postcode":"78228",
    "sg:province":"TX",
    "wof:name":"Allstate",
    "wof:placetype":"venue"
},
  "geometry": {"coordinates":[-98.570778,29.48723],"type":"Point"}
}