{
  "type": "Feature",
  "properties": {
    "iso:country":"US",
    "sg:address":"1500 Franklin Ave",
    "sg:city":"Waco",
    "sg:classifiers":[
        {
            "category":"Manufacturing",
            "subcategory":"Building Materials",
            "type":"Manufacturing & Wholesale Goods"
        }
    ],
    "sg:phone":"+1 254 752 6547",
    "sg:postcode":"76701",
    "sg:province":"TX",
    "sg:tags":[
        "cabinet"
    ],
    "wof:name":"C M Trautschold Co",
    "wof:placetype":"venue"
},
  "geometry": {"coordinates":[-97.140907,31.54711],"type":"Point"}
}