{
  "type": "Feature",
  "properties": {
    "iso:country":"US",
    "sg:address":"3414 NE 24th Ave",
    "sg:city":"Amarillo",
    "sg:classifiers":[
        {
            "category":"Insurance",
            "subcategory":"Insurance Agent",
            "type":"Services"
        }
    ],
    "sg:phone":"+1 806 381 9940",
    "sg:postcode":"79107",
    "sg:province":"TX",
    "wof:name":"Apex Insurance Co",
    "wof:placetype":"venue"
},
  "geometry": {"coordinates":[-101.797241,35.236295],"type":"Point"}
}