{
  "type": "Feature",
  "properties": {
    "iso:country":"US",
    "sg:address":"7217 Blimp Base Blvd",
    "sg:city":"Hitchcock",
    "sg:classifiers":[
        {
            "category":"Building & Trades",
            "subcategory":"Construction",
            "type":"Services"
        }
    ],
    "sg:phone":"+1 409 986 9193",
    "sg:postcode":"77563",
    "sg:province":"TX",
    "sg:tags":[
        "concrete",
        "contractor"
    ],
    "wof:name":"Burks Concrete Contrs Inc",
    "wof:placetype":"venue"
},
  "geometry": {"coordinates":[-95.04616,29.342584],"type":"Point"}
}