{
  "type": "Feature",
  "properties": {
    "iso:country":"US",
    "sg:address":"4222 S Alameda St",
    "sg:city":"Corpus Christi",
    "sg:classifiers":[
        {
            "category":"Personal",
            "subcategory":"Beauty Salon",
            "type":"Services"
        }
    ],
    "sg:phone":"+1 361 992 8941",
    "sg:postcode":"78412",
    "sg:province":"TX",
    "sg:tags":[
        "shop"
    ],
    "wof:name":"Hair Designers",
    "wof:placetype":"venue"
},
  "geometry": {"coordinates":[-97.372378,27.730714],"type":"Point"}
}