{
  "type": "Feature",
  "properties": {
    "iso:country":"US",
    "sg:address":"1321 Greenway Dr",
    "sg:city":"Irving",
    "sg:classifiers":[
        {
            "category":"Restaurant",
            "type":"Food & Drink"
        }
    ],
    "sg:phone":"+1 972 714 6298",
    "sg:postcode":"75038",
    "sg:province":"TX",
    "sg:tags":[
        "eating"
    ],
    "wof:name":"Eurest Dining Services 26179",
    "wof:placetype":"venue"
},
  "geometry": {"coordinates":[-96.96894399999999,32.889513],"type":"Point"}
}