{
  "type": "Feature",
  "properties": {
    "iso:country":"US",
    "sg:address":"255 N Franklin St",
    "sg:city":"La Grange",
    "sg:classifiers":[
        {
            "category":"Professional",
            "subcategory":"Management & Consulting",
            "type":"Services"
        }
    ],
    "sg:phone":"+1 979 968 6862",
    "sg:postcode":"78945",
    "sg:province":"TX",
    "sg:tags":[
        "business"
    ],
    "wof:name":"Mkl Consulting LLC",
    "wof:placetype":"venue"
},
  "geometry": {"coordinates":[-96.876546,29.907389],"type":"Point"}
}