{
  "type": "Feature",
  "properties": {
    "iso:country":"US",
    "sg:address":"5001 Wesley St",
    "sg:city":"Greenville",
    "sg:classifiers":[
        {
            "category":"Food & Beverages",
            "subcategory":"Groceries & Convenience Stores",
            "type":"Retail Goods"
        }
    ],
    "sg:phone":"+1 903 455 3772",
    "sg:postcode":"75402",
    "sg:province":"TX",
    "wof:name":"Quick Step",
    "wof:placetype":"venue"
},
  "geometry": {"coordinates":[-96.10917600000001,33.120321],"type":"Point"}
}