{
  "type": "Feature",
  "properties": {
    "iso:country":"US",
    "sg:address":"1004 Scotland Ave",
    "sg:city":"Azle",
    "sg:classifiers":[
        {
            "category":"Building & Trades",
            "subcategory":"Plumbing",
            "type":"Services"
        }
    ],
    "sg:phone":"+1 817 238 9109",
    "sg:postcode":"76020",
    "sg:province":"TX",
    "sg:tags":[
        "contractor"
    ],
    "wof:name":"Jons Little Plumbing",
    "wof:placetype":"venue"
},
  "geometry": {"coordinates":[-97.53524,32.874116],"type":"Point"}
}