{
  "type": "Feature",
  "properties": {
    "iso:country":"US",
    "sg:address":"911 W 2nd St",
    "sg:city":"Odessa",
    "sg:classifiers":[
        {
            "category":"Wholesale",
            "subcategory":"Petroleum",
            "type":"Manufacturing & Wholesale Goods"
        }
    ],
    "sg:phone":"+1 432 335 6260",
    "sg:postcode":"79763",
    "sg:province":"TX",
    "sg:tags":[
        "crude",
        "pipeline"
    ],
    "wof:name":"Chevron",
    "wof:placetype":"venue"
},
  "geometry": {"coordinates":[-102.37697900000001,31.840802],"type":"Point"}
}