{
  "type": "Feature",
  "properties": {
    "iso:country":"US",
    "sg:address":"9520 Highway 290 W Unit A",
    "sg:city":"Austin",
    "sg:classifiers":[
        {
            "category":"Retail",
            "subcategory":"Auto Repair",
            "type":"Services"
        }
    ],
    "sg:phone":"+1 512 301 2807",
    "sg:postcode":"78736",
    "sg:province":"TX",
    "wof:name":"Fastbrake",
    "wof:placetype":"venue"
},
  "geometry": {"coordinates":[-97.932862,30.230912],"type":"Point"}
}