{
  "type": "Feature",
  "properties": {
    "iso:country":"US",
    "sg:address":"2329 Magoffin Ave",
    "sg:city":"El Paso",
    "sg:classifiers":[
        {
            "category":"Professional",
            "subcategory":"Management & Consulting",
            "type":"Services"
        }
    ],
    "sg:phone":"+1 915 544 7711",
    "sg:postcode":"79901",
    "sg:province":"TX",
    "sg:tags":[
        "manufacture",
        "product",
        "wood",
        "way",
        "electronics",
        "r"
    ],
    "wof:name":"Security & Communications Intl",
    "wof:placetype":"venue"
},
  "geometry": {"coordinates":[-106.461612,31.771948],"type":"Point"}
}