{
  "type": "Feature",
  "properties": {
    "iso:country":"US",
    "sg:address":"6000 Randolph Blvd",
    "sg:city":"San Antonio",
    "sg:classifiers":[
        {
            "category":"Real Estate",
            "subcategory":"Real Estate Agent",
            "type":"Services"
        }
    ],
    "sg:phone":"+1 210 657 3500",
    "sg:postcode":"78233",
    "sg:province":"TX",
    "wof:name":"Reyes & Sansom",
    "wof:placetype":"venue"
},
  "geometry": {"coordinates":[-98.37388900000001,29.537225],"type":"Point"}
}