{
  "type": "Feature",
  "properties": {
    "iso:country":"US",
    "sg:address":"4367 Rittiman Rd",
    "sg:city":"San Antonio",
    "sg:classifiers":[
        {
            "category":"Manufacturing",
            "subcategory":"Apparel",
            "type":"Manufacturing & Wholesale Goods"
        }
    ],
    "sg:phone":"+1 210 646 0899",
    "sg:postcode":"78218",
    "sg:province":"TX",
    "sg:tags":[
        "sewing",
        "contractor"
    ],
    "wof:name":"S P Sewing",
    "wof:placetype":"venue"
},
  "geometry": {"coordinates":[-98.409054,29.48416],"type":"Point"}
}