{
  "type": "Feature",
  "properties": {
    "iso:country":"US",
    "sg:address":"8511 Starcrest Dr",
    "sg:city":"San Antonio",
    "sg:classifiers":[
        {
            "category":"Professional",
            "type":"Services"
        }
    ],
    "sg:phone":"+1 210 967 8450",
    "sg:postcode":"78217",
    "sg:province":"TX",
    "sg:tags":[
        "establishment"
    ],
    "wof:name":"A S Datacash",
    "wof:placetype":"venue"
},
  "geometry": {"coordinates":[-98.422915,29.519708],"type":"Point"}
}