{
  "type": "Feature",
  "properties": {
    "iso:country":"US",
    "sg:address":"14522 S Post Oak Rd Ste A",
    "sg:city":"Houston",
    "sg:classifiers":[
        {
            "category":"Shopping",
            "subcategory":"Shoes",
            "type":"Retail Goods"
        }
    ],
    "sg:phone":"+1 713 283 0485",
    "sg:postcode":"77045",
    "sg:province":"TX",
    "sg:tags":[
        "store"
    ],
    "wof:name":"Price Wise Shoes",
    "wof:placetype":"venue"
},
  "geometry": {"coordinates":[-95.46519000000001,29.616096],"type":"Point"}
}