{
  "type": "Feature",
  "properties": {
    "iso:country":"US",
    "sg:address":"3601 Nassau Ct",
    "sg:city":"Granbury",
    "sg:classifiers":[
        {
            "category":"Manufacturing",
            "subcategory":"Aerospace",
            "type":"Manufacturing & Wholesale Goods"
        }
    ],
    "sg:phone":"+1 817 326 6293",
    "sg:postcode":"76049",
    "sg:province":"TX",
    "sg:tags":[
        "manufacture",
        "propeller",
        "aircraft",
        "extension",
        "for"
    ],
    "wof:name":"Saber Manufacturing Inc",
    "wof:placetype":"venue"
},
  "geometry": {"coordinates":[-97.7135,32.417915],"type":"Point"}
}