{
  "type": "Feature",
  "properties": {
    "iso:country":"US",
    "sg:address":"1310 S College St",
    "sg:city":"Brady",
    "sg:classifiers":[
        {
            "category":"Restaurant",
            "type":"Food & Drink"
        }
    ],
    "sg:phone":"+1 325 597 3431",
    "sg:postcode":"76825",
    "sg:province":"TX",
    "sg:tags":[
        "eating"
    ],
    "wof:name":"Texas Corral Restaurant",
    "wof:placetype":"venue"
},
  "geometry": {"coordinates":[-99.33771,31.125305],"type":"Point"}
}