{
  "type": "Feature",
  "properties": {
    "iso:country":"US",
    "sg:address":"1110 N Hwy 175",
    "sg:city":"Seagoville",
    "sg:classifiers":[
        {
            "category":"Shopping",
            "type":"Retail Goods"
        }
    ],
    "sg:phone":"+1 972 287 7800",
    "sg:postcode":"75159",
    "sg:province":"TX",
    "sg:tags":[
        "merchandise"
    ],
    "wof:name":"Bankcard Depot",
    "wof:placetype":"venue"
},
  "geometry": {"coordinates":[-96.55313,32.653742],"type":"Point"}
}