{
  "type": "Feature",
  "properties": {
    "iso:country":"US",
    "sg:address":"910 Hall Ave",
    "sg:city":"Seabrook",
    "sg:classifiers":[
        {
            "category":"Shopping",
            "subcategory":"Used Merchandise",
            "type":"Retail Goods"
        }
    ],
    "sg:phone":"+1 281 474 9009",
    "sg:postcode":"77586",
    "sg:province":"TX",
    "wof:name":"Green Apple Antiques & Collect",
    "wof:placetype":"venue"
},
  "geometry": {"coordinates":[-95.022982,29.559674],"type":"Point"}
}