{
  "type": "Feature",
  "properties": {
    "iso:country":"US",
    "sg:address":"209 E Crosstimbers St",
    "sg:city":"Houston",
    "sg:classifiers":[
        {
            "category":"Health Services",
            "subcategory":"Doctor",
            "type":"Services"
        }
    ],
    "sg:phone":"+1 713 692 1344",
    "sg:postcode":"77022",
    "sg:province":"TX",
    "wof:name":"Universal Dental Clinic",
    "wof:placetype":"venue"
},
  "geometry": {"coordinates":[-95.37289,29.828465],"type":"Point"}
}