{
  "type": "Feature",
  "properties": {
    "iso:country":"US",
    "sg:address":"19208 Zetak Ln",
    "sg:city":"Crosby",
    "sg:classifiers":[
        {
            "category":"Professional",
            "type":"Services"
        }
    ],
    "sg:phone":"+1 281 328 1248",
    "sg:postcode":"77532",
    "sg:province":"TX",
    "wof:name":"Gillyball Inc",
    "wof:placetype":"venue"
},
  "geometry": {"coordinates":[-95.08832,29.955933],"type":"Point"}
}