{
  "type": "Feature",
  "properties": {
    "iso:country":"US",
    "sg:address":"14014 Barnhart Blvd",
    "sg:city":"Houston",
    "sg:classifiers":[
        {
            "category":"Banks & Credit Unions",
            "subcategory":"Financial Services",
            "type":"Services"
        }
    ],
    "sg:phone":"+1 281 293 7274",
    "sg:postcode":"77077",
    "sg:province":"TX",
    "sg:tags":[
        "company",
        "holding"
    ],
    "wof:name":"Rt Golden Inc",
    "wof:placetype":"venue"
},
  "geometry": {"coordinates":[-95.633396,29.751757],"type":"Point"}
}