{
  "type": "Feature",
  "properties": {
    "iso:country":"US",
    "sg:address":"404 Joanna Dr",
    "sg:city":"Hurst",
    "sg:classifiers":[
        {
            "category":"Professional",
            "type":"Services"
        }
    ],
    "sg:phone":"+1 817 282 6744",
    "sg:postcode":"76053",
    "sg:province":"TX",
    "wof:name":"Stalls & Spins Flying Ser",
    "wof:placetype":"venue"
},
  "geometry": {"coordinates":[-97.17724,32.826379],"type":"Point"}
}