{
  "type": "Feature",
  "properties": {
    "iso:country":"US",
    "sg:address":"11 Elm Ave",
    "sg:city":"Dumas",
    "sg:classifiers":[
        {
            "category":"Professional",
            "subcategory":"Accounting & Tax Preparation",
            "type":"Services"
        }
    ],
    "sg:phone":"+1 806 934 2084",
    "sg:postcode":"79029",
    "sg:province":"TX",
    "wof:name":"Working Overtime",
    "wof:placetype":"venue"
},
  "geometry": {"coordinates":[-101.967135,35.866346],"type":"Point"}
}