{
  "type": "Feature",
  "properties": {
    "iso:country":"US",
    "sg:address":"212 N Liberty St",
    "sg:city":"Montgomery",
    "sg:classifiers":[
        {
            "category":"Shopping",
            "subcategory":"Hobbies, Toys, & Games",
            "type":"Retail Goods"
        }
    ],
    "sg:phone":"+1 936 448 4285",
    "sg:postcode":"77356",
    "sg:province":"TX",
    "sg:tags":[
        "used"
    ],
    "wof:name":"Branding Iron Gifts and Antq",
    "wof:placetype":"venue"
},
  "geometry": {"coordinates":[-95.699198,30.399027],"type":"Point"}
}