{
  "type": "Feature",
  "properties": {
    "iso:country":"US",
    "sg:address":"109 Plum Cir",
    "sg:city":"Lake Jackson",
    "sg:classifiers":[
        {
            "category":"Professional",
            "subcategory":"Business Services",
            "type":"Services"
        }
    ],
    "sg:phone":"+1 979 480 9069",
    "sg:postcode":"77566",
    "sg:province":"TX",
    "wof:name":"Ce Enterprise",
    "wof:placetype":"venue"
},
  "geometry": {"coordinates":[-95.462779,29.040703],"type":"Point"}
}