{
  "type": "Feature",
  "properties": {
    "iso:country":"US",
    "sg:address":"403 Early Blvd",
    "sg:city":"Brownwood",
    "sg:classifiers":[
        {
            "category":"Retail",
            "subcategory":"Auto Repair",
            "type":"Services"
        }
    ],
    "sg:phone":"+1 325 643 1725",
    "sg:postcode":"76802",
    "sg:province":"TX",
    "sg:tags":[
        "repairing",
        "automobile"
    ],
    "wof:name":"Heard Brothers Automotive",
    "wof:placetype":"venue"
},
  "geometry": {"coordinates":[-98.95744999999999,31.737424],"type":"Point"}
}