{
  "type": "Feature",
  "properties": {
    "iso:country":"US",
    "sg:address":"6249 Gulfway Dr",
    "sg:city":"Groves",
    "sg:classifiers":[
        {
            "category":"Restaurant",
            "type":"Food & Drink"
        },
        {
            "category":"Food & Beverages",
            "subcategory":"Meat & Fish",
            "type":"Retail Goods"
        }
    ],
    "sg:phone":"+1 409 962 8300",
    "sg:postcode":"77619",
    "sg:province":"TX",
    "sg:tags":[
        "seafood",
        "market"
    ],
    "wof:name":"Willee's Crawfish Shack",
    "wof:placetype":"venue"
},
  "geometry": {"coordinates":[-93.89908200000001,29.933651],"type":"Point"}
}