{
  "type": "Feature",
  "properties": {
    "iso:country":"US",
    "sg:address":"1308 Placer Dr",
    "sg:city":"Allen",
    "sg:classifiers":[
        {
            "category":"Shopping",
            "subcategory":"Used Merchandise",
            "type":"Retail Goods"
        }
    ],
    "sg:phone":"+1 972 396 5260",
    "sg:postcode":"75013",
    "sg:province":"TX",
    "wof:name":"Deborah D Bush",
    "wof:placetype":"venue"
},
  "geometry": {"coordinates":[-96.702034,33.097989],"type":"Point"}
}