{
  "type": "Feature",
  "properties": {
    "iso:country":"US",
    "sg:address":"4914 64th St",
    "sg:city":"Lubbock",
    "sg:classifiers":[
        {
            "category":"Retail",
            "subcategory":"Repair Shop",
            "type":"Services"
        }
    ],
    "sg:phone":"+1 806 791 3151",
    "sg:postcode":"79414",
    "sg:province":"TX",
    "sg:tags":[
        "equipment",
        "conditioning",
        "air"
    ],
    "wof:name":"Service Air Inc",
    "wof:placetype":"venue"
},
  "geometry": {"coordinates":[-101.918261,33.536175],"type":"Point"}
}