{
  "type": "Feature",
  "properties": {
    "iso:country":"US",
    "sg:address":"318 Boomtown St",
    "sg:city":"Laredo",
    "sg:classifiers":[
        {
            "category":"Building & Trades",
            "subcategory":"Equipment Rental",
            "type":"Services"
        }
    ],
    "sg:phone":"+1 956 753 0994",
    "sg:postcode":"78043",
    "sg:province":"TX",
    "wof:name":"Tucan Lease Services",
    "wof:placetype":"venue"
},
  "geometry": {"coordinates":[-99.454643,27.494691],"type":"Point"}
}