{
  "type": "Feature",
  "properties": {
    "iso:country":"US",
    "sg:address":"9600 Co Rd 505",
    "sg:city":"Alvarado",
    "sg:classifiers":[
        {
            "category":"Building & Trades",
            "subcategory":"Construction",
            "type":"Services"
        }
    ],
    "sg:phone":"+1 817 783 6117",
    "sg:postcode":"76009",
    "sg:province":"TX",
    "sg:tags":[
        "carpentry",
        "contractor"
    ],
    "wof:name":"Meier Custom Work",
    "wof:placetype":"venue"
},
  "geometry": {"coordinates":[-97.155073,32.444153],"type":"Point"}
}