{
  "type": "Feature",
  "properties": {
    "iso:country":"US",
    "sg:address":"1445 S University Dr",
    "sg:city":"Fort Worth",
    "sg:classifiers":[
        {
            "category":"Real Estate",
            "subcategory":"Real Estate Agent",
            "type":"Services"
        }
    ],
    "sg:phone":"+1 817 921 8170",
    "sg:postcode":"76107",
    "sg:province":"TX",
    "sg:tags":[
        "development",
        "commercial",
        "management",
        "leasing"
    ],
    "wof:name":"Bradford Realty Services Inc",
    "wof:placetype":"venue"
},
  "geometry": {"coordinates":[-97.36142,32.731959],"type":"Point"}
}