{
  "type": "Feature",
  "properties": {
    "iso:country":"US",
    "sg:address":"802 Broadway St",
    "sg:city":"Galveston",
    "sg:classifiers":[
        {
            "category":"Retail",
            "subcategory":"Laundry & Dry Cleaning",
            "type":"Services"
        }
    ],
    "sg:phone":"+1 409 763 4264",
    "sg:postcode":"77550",
    "sg:province":"TX",
    "sg:tags":[
        "power"
    ],
    "wof:name":"Vans Laundry",
    "wof:placetype":"venue"
},
  "geometry": {"coordinates":[-94.77597799999999,29.304352],"type":"Point"}
}