{
  "type": "Feature",
  "properties": {
    "iso:country":"US",
    "sg:address":"12160 Richmond Ave",
    "sg:city":"Houston",
    "sg:classifiers":[
        {
            "category":"Recreation",
            "type":"Entertainment"
        }
    ],
    "sg:phone":"+1 281 293 7483",
    "sg:postcode":"77082",
    "sg:province":"TX",
    "sg:tags":[
        "range",
        "practice",
        "golf"
    ],
    "wof:name":"Golf Range On Richmond",
    "wof:placetype":"venue"
},
  "geometry": {"coordinates":[-95.594033,29.730657],"type":"Point"}
}