{
  "type": "Feature",
  "properties": {
    "iso:country":"US",
    "sg:address":"106 Abraham Ct",
    "sg:city":"El Paso",
    "sg:classifiers":[
        {
            "category":"Local Transit",
            "type":"Transportation"
        }
    ],
    "sg:phone":"+1 915 775 0306",
    "sg:postcode":"79915",
    "sg:province":"TX",
    "wof:name":"Drivers Logistics",
    "wof:placetype":"venue"
},
  "geometry": {"coordinates":[-106.395212,31.754086],"type":"Point"}
}