{
  "type": "Feature",
  "properties": {
    "iso:country":"US",
    "sg:address":"213 S Elm St",
    "sg:city":"Pearsall",
    "sg:classifiers":[
        {
            "category":"Wholesale",
            "subcategory":"Farm Supplies",
            "type":"Manufacturing & Wholesale Goods"
        }
    ],
    "sg:phone":"+1 830 334 3625",
    "sg:postcode":"78061",
    "sg:province":"TX",
    "sg:tags":[
        "peanut",
        "product"
    ],
    "wof:name":"Birdsong Peanuts",
    "wof:placetype":"venue"
},
  "geometry": {"coordinates":[-99.096576,28.891268],"type":"Point"}
}