{
  "type": "Feature",
  "properties": {
    "iso:country":"US",
    "sg:address":"207 Brook St",
    "sg:city":"Seguin",
    "sg:classifiers":[
        {
            "category":"Retail",
            "subcategory":"Auto Repair",
            "type":"Services"
        }
    ],
    "sg:phone":"+1 830 557 5541",
    "sg:postcode":"78155",
    "sg:province":"TX",
    "sg:tags":[
        "transmission",
        "automotive"
    ],
    "wof:name":"Repairs Unlimited",
    "wof:placetype":"venue"
},
  "geometry": {"coordinates":[-98.019576,29.557332],"type":"Point"}
}