{
  "type": "Feature",
  "properties": {
    "iso:country":"US",
    "sg:address":"9455 Kempwood Dr",
    "sg:city":"Houston",
    "sg:classifiers":[
        {
            "category":"Shopping",
            "subcategory":"Music",
            "type":"Retail Goods"
        }
    ],
    "sg:phone":"+1 713 460 4688",
    "sg:postcode":"77080",
    "sg:province":"TX",
    "sg:tags":[
        "video",
        "disc",
        "tape",
        "cassette"
    ],
    "wof:name":"Namvit Video",
    "wof:placetype":"venue"
},
  "geometry": {"coordinates":[-95.523843,29.821962],"type":"Point"}
}