{
  "type": "Feature",
  "properties": {
    "iso:country":"US",
    "sg:address":"2000 Cedar Dr",
    "sg:city":"La Marque",
    "sg:classifiers":[
        {
            "category":"Manufacturing",
            "subcategory":"Apparel",
            "type":"Manufacturing & Wholesale Goods"
        }
    ],
    "sg:phone":"+1 409 938 7228",
    "sg:postcode":"77568",
    "sg:province":"TX",
    "sg:tags":[
        "sewing",
        "contractor"
    ],
    "wof:name":"J's Sew & Sew",
    "wof:placetype":"venue"
},
  "geometry": {"coordinates":[-94.974239,29.368495],"type":"Point"}
}