{
  "type": "Feature",
  "properties": {
    "iso:country":"US",
    "sg:address":"9830 East Fwy",
    "sg:city":"Houston",
    "sg:classifiers":[
        {
            "category":"Manufacturing",
            "subcategory":"Chemicals & Compounds",
            "type":"Manufacturing & Wholesale Goods"
        }
    ],
    "sg:phone":"+1 281 578 1440",
    "sg:postcode":"77029",
    "sg:province":"TX",
    "sg:tags":[
        "pr",
        "inorganic",
        "industrial",
        "mfg"
    ],
    "wof:name":"Houston Plant",
    "wof:placetype":"venue"
},
  "geometry": {"coordinates":[-95.25126299999999,29.773325],"type":"Point"}
}