{
  "type": "Feature",
  "properties": {
    "iso:country":"US",
    "sg:address":"2204 Carson St",
    "sg:city":"Haltom City",
    "sg:classifiers":[
        {
            "category":"Building & Trades",
            "subcategory":"Construction",
            "type":"Services"
        }
    ],
    "sg:phone":"+1 682 647 1890",
    "sg:postcode":"76117",
    "sg:province":"TX",
    "sg:tags":[
        "masonry",
        "contractor"
    ],
    "wof:name":"Benchmark Masonry Supply",
    "wof:placetype":"venue"
},
  "geometry": {"coordinates":[-97.255776,32.791565],"type":"Point"}
}