{
  "type": "Feature",
  "properties": {
    "iso:country":"US",
    "sg:address":"7800 Banner Dr",
    "sg:city":"Dallas",
    "sg:classifiers":[
        {
            "category":"Manufacturing",
            "subcategory":"Electronics",
            "type":"Manufacturing & Wholesale Goods"
        }
    ],
    "sg:phone":"+1 972 917 1986",
    "sg:postcode":"75251",
    "sg:province":"TX",
    "sg:tags":[
        "electronic",
        "component",
        "mfg"
    ],
    "wof:name":"Texas Instruments",
    "wof:placetype":"venue"
},
  "geometry": {"coordinates":[-96.76921299999999,32.921222],"type":"Point"}
}