{
  "type": "Feature",
  "properties": {
    "iso:country":"US",
    "sg:address":"4201 N Dixie Blvd",
    "sg:city":"Odessa",
    "sg:classifiers":[
        {
            "category":"Food & Beverages",
            "subcategory":"Groceries & Convenience Stores",
            "type":"Retail Goods"
        }
    ],
    "sg:phone":"+1 432 366 0948",
    "sg:postcode":"79762",
    "sg:province":"TX",
    "sg:tags":[
        "grocer"
    ],
    "wof:name":"Lowe's",
    "wof:placetype":"venue"
},
  "geometry": {"coordinates":[-102.37409,31.8856],"type":"Point"}
}