{
  "type": "Feature",
  "properties": {
    "iso:country":"US",
    "sg:address":"711 Fort Worth St",
    "sg:city":"Jacksonville",
    "sg:classifiers":[
        {
            "category":"Education",
            "subcategory":"School",
            "type":"Public Place"
        }
    ],
    "sg:phone":"+1 903 586 5146",
    "sg:postcode":"75766",
    "sg:province":"TX",
    "wof:name":"East Side Elementary School",
    "wof:placetype":"venue"
},
  "geometry": {"coordinates":[-95.26120899999999,31.960778],"type":"Point"}
}