{
  "type": "Feature",
  "properties": {
    "iso:country":"US",
    "sg:address":"3216 Commander Dr",
    "sg:city":"Carrollton",
    "sg:classifiers":[
        {
            "category":"Shopping",
            "subcategory":"Mobile Phones",
            "type":"Retail Goods"
        }
    ],
    "sg:phone":"+1 972 960 1640",
    "sg:postcode":"75006",
    "sg:province":"TX",
    "wof:name":"Wireless America",
    "wof:placetype":"venue"
},
  "geometry": {"coordinates":[-96.849478,32.977321],"type":"Point"}
}