{
  "type": "Feature",
  "properties": {
    "iso:country":"US",
    "sg:address":"2775 Villa Creek Dr",
    "sg:city":"Dallas",
    "sg:classifiers":[
        {
            "category":"Professional",
            "subcategory":"Engineering",
            "type":"Services"
        }
    ],
    "sg:phone":"+1 972 484 3854",
    "sg:postcode":"75234",
    "sg:province":"TX",
    "wof:name":"Enercon Services Inc",
    "wof:placetype":"venue"
},
  "geometry": {"coordinates":[-96.884773,32.911868],"type":"Point"}
}