{
  "type": "Feature",
  "properties": {
    "iso:country":"US",
    "sg:address":"345 N Country Club Rd",
    "sg:city":"Garland",
    "sg:classifiers":[
        {
            "category":"Food & Beverages",
            "subcategory":"Groceries & Convenience Stores",
            "type":"Retail Goods"
        }
    ],
    "sg:phone":"+1 972 494 3292",
    "sg:postcode":"75040",
    "sg:province":"TX",
    "wof:name":"One Stop Food Mart",
    "wof:placetype":"venue"
},
  "geometry": {"coordinates":[-96.613899,32.914001],"type":"Point"}
}