{
  "type": "Feature",
  "properties": {
    "iso:country":"US",
    "sg:address":"4333 College Hills Blvd",
    "sg:city":"San Angelo",
    "sg:classifiers":[
        {
            "category":"Health Services",
            "subcategory":"Doctor",
            "type":"Services"
        }
    ],
    "sg:phone":"+1 325 944 2569",
    "sg:postcode":"76904",
    "sg:province":"TX",
    "wof:name":"Chris Henson DDS",
    "wof:placetype":"venue"
},
  "geometry": {"coordinates":[-100.485597,31.419396],"type":"Point"}
}