{
  "type": "Feature",
  "properties": {
    "iso:country":"US",
    "sg:address":"12160 Rojas Dr",
    "sg:city":"El Paso",
    "sg:classifiers":[
        {
            "category":"Manufacturing",
            "subcategory":"Electronics",
            "type":"Manufacturing & Wholesale Goods"
        }
    ],
    "sg:phone":"+1 915 860 3800",
    "sg:postcode":"79936",
    "sg:province":"TX",
    "sg:tags":[
        "equipment",
        "mfg",
        "home"
    ],
    "wof:name":"Zenith Electronics Corporation",
    "wof:placetype":"venue"
},
  "geometry": {"coordinates":[-106.292793,31.71703],"type":"Point"}
}