{
  "type": "Feature",
  "properties": {
    "iso:country":"US",
    "sg:address":"1105 31st St",
    "sg:city":"Galveston",
    "sg:classifiers":[
        {
            "category":"Retail",
            "subcategory":"Auto Repair",
            "type":"Services"
        }
    ],
    "sg:phone":"+1 409 765 4373",
    "sg:postcode":"77550",
    "sg:province":"TX",
    "sg:tags":[
        "repairing",
        "automobile"
    ],
    "wof:name":"Jerry's Garage",
    "wof:placetype":"venue"
},
  "geometry": {"coordinates":[-94.800828,29.296257],"type":"Point"}
}