{
  "type": "Feature",
  "properties": {
    "iso:country":"US",
    "sg:address":"20235 Prince Creek Dr",
    "sg:city":"Katy",
    "sg:classifiers":[
        {
            "category":"Government",
            "subcategory":"Office",
            "type":"Public Place"
        }
    ],
    "sg:phone":"+1 281 398 3198",
    "sg:postcode":"77450",
    "sg:province":"TX",
    "sg:tags":[
        "space"
    ],
    "wof:name":"Satellite Networks Intl",
    "wof:placetype":"venue"
},
  "geometry": {"coordinates":[-95.72346899999999,29.77009],"type":"Point"}
}