{
  "type": "Feature",
  "properties": {
    "iso:country":"US",
    "sg:address":"3938 Melbourne St",
    "sg:city":"Houston",
    "sg:classifiers":[
        {
            "category":"Organizations",
            "subcategory":"Religious Organization",
            "type":"Services"
        }
    ],
    "sg:phone":"+1 713 635 2000",
    "sg:postcode":"77026",
    "sg:province":"TX",
    "sg:tags":[
        "church"
    ],
    "wof:name":"Behtesda Baptist Church",
    "wof:placetype":"venue"
},
  "geometry": {"coordinates":[-95.332437,29.816764],"type":"Point"}
}