{
  "type": "Feature",
  "properties": {
    "iso:country":"US",
    "sg:address":"9133 Wallisville Rd",
    "sg:city":"Houston",
    "sg:classifiers":[
        {
            "category":"Wholesale",
            "subcategory":"Auto Parts",
            "type":"Manufacturing & Wholesale Goods"
        }
    ],
    "sg:phone":"+1 713 673 6400",
    "sg:postcode":"77029",
    "sg:province":"TX",
    "sg:tags":[
        "body",
        "mfg"
    ],
    "wof:name":"Southern Transport Parts",
    "wof:placetype":"venue"
},
  "geometry": {"coordinates":[-95.269256,29.791658],"type":"Point"}
}