{
  "type": "Feature",
  "properties": {
    "iso:country":"US",
    "sg:address":"2915 International Blvd",
    "sg:city":"Brownsville",
    "sg:classifiers":[
        {
            "category":"Restaurant",
            "type":"Food & Drink"
        }
    ],
    "sg:phone":"+1 956 542 9357",
    "sg:postcode":"78521",
    "sg:province":"TX",
    "sg:tags":[
        "eating"
    ],
    "wof:name":"Taqueria Seberia",
    "wof:placetype":"venue"
},
  "geometry": {"coordinates":[-97.47724700000001,25.909123],"type":"Point"}
}