{
  "type": "Feature",
  "properties": {
    "iso:country":"US",
    "sg:address":"2203 Timberloch Pl",
    "sg:city":"Spring",
    "sg:classifiers":[
        {
            "category":"Professional",
            "subcategory":"Management & Consulting",
            "type":"Services"
        }
    ],
    "sg:phone":"+1 281 292 1454",
    "sg:postcode":"77380",
    "sg:province":"TX",
    "sg:tags":[
        "business"
    ],
    "wof:name":"DCS Business Services",
    "wof:placetype":"venue"
},
  "geometry": {"coordinates":[-95.46060799999999,30.158441],"type":"Point"}
}