{
  "type": "Feature",
  "properties": {
    "iso:country":"US",
    "sg:address":"819 Lovett Blvd",
    "sg:city":"Houston",
    "sg:classifiers":[
        {
            "category":"Professional",
            "subcategory":"Lawyer & Legal Services",
            "type":"Services"
        }
    ],
    "sg:phone":"+1 713 629 5889",
    "sg:postcode":"77006",
    "sg:province":"TX",
    "wof:name":"Goldberg Edgar Atty",
    "wof:placetype":"venue"
},
  "geometry": {"coordinates":[-95.38919799999999,29.743299],"type":"Point"}
}