{
  "type": "Feature",
  "properties": {
    "iso:country":"US",
    "sg:address":"3313 S University Dr",
    "sg:city":"Fort Worth",
    "sg:classifiers":[
        {
            "category":"Professional",
            "subcategory":"Business Services",
            "type":"Services"
        }
    ],
    "sg:phone":"+1 817 735 8390",
    "sg:postcode":"76109",
    "sg:province":"TX",
    "sg:tags":[
        "plant",
        "design",
        "maintenance"
    ],
    "wof:name":"Richardson-Whitney & Assoc",
    "wof:placetype":"venue"
},
  "geometry": {"coordinates":[-97.360461,32.699779],"type":"Point"}
}