{
  "type": "Feature",
  "properties": {
    "iso:country":"US",
    "sg:address":"218 E Commanche St",
    "sg:city":"Fairfield",
    "sg:classifiers":[
        {
            "category":"Building & Trades",
            "subcategory":"Cleaning & Sanitation",
            "type":"Services"
        }
    ],
    "sg:phone":"+1 903 389 9683",
    "sg:postcode":"75840",
    "sg:province":"TX",
    "sg:tags":[
        "janitor"
    ],
    "wof:name":"SSC Svc Solutions",
    "wof:placetype":"venue"
},
  "geometry": {"coordinates":[-96.159166,31.727545],"type":"Point"}
}