{
  "type": "Feature",
  "properties": {
    "iso:country":"US",
    "sg:address":"910 N Date St",
    "sg:city":"Plainview",
    "sg:classifiers":[
        {
            "category":"Wholesale",
            "subcategory":"Machinery & Supplies",
            "type":"Manufacturing & Wholesale Goods"
        }
    ],
    "sg:phone":"+1 806 293 2538",
    "sg:postcode":"79072",
    "sg:province":"TX",
    "sg:tags":[
        "farm",
        "equipment"
    ],
    "sg:website":"www.edeere.com",
    "wof:name":"Ray Lee Equipment Co",
    "wof:placetype":"venue"
},
  "geometry": {"coordinates":[-101.69794400000001,34.19084],"type":"Point"}
}