{
  "type": "Feature",
  "properties": {
    "iso:country":"US",
    "sg:address":"7909 Mansfield Hwy",
    "sg:city":"Kennedale",
    "sg:classifiers":[
        {
            "category":"Autos & Motor Vehicles",
            "subcategory":"Auto Supplies",
            "type":"Retail Goods"
        },
        {
            "category":"Wholesale",
            "subcategory":"Auto Parts",
            "type":"Manufacturing & Wholesale Goods"
        }
    ],
    "sg:phone":"+1 817 572 1809",
    "sg:postcode":"76060",
    "sg:province":"TX",
    "sg:tags":[
        "automobile",
        "rebuilt",
        "rebuilt-wholesale",
        "supplies-used",
        "manufacturer"
    ],
    "wof:name":"Abs Chrysler Amc Inc",
    "wof:placetype":"venue"
},
  "geometry": {"coordinates":[-97.19036199999999,32.617345],"type":"Point"}
}