{
  "type": "Feature",
  "properties": {
    "iso:country":"US",
    "sg:address":"4067 Beltway Dr",
    "sg:city":"Addison",
    "sg:classifiers":[
        {
            "category":"Retail",
            "subcategory":"Laundry & Dry Cleaning",
            "type":"Services"
        }
    ],
    "sg:phone":"+1 972 980 9460",
    "sg:postcode":"75001",
    "sg:province":"TX",
    "sg:tags":[
        "cleaners",
        "rug",
        "carpet"
    ],
    "wof:name":"Ramos Carpet Cleaning",
    "wof:placetype":"venue"
},
  "geometry": {"coordinates":[-96.843599,32.951427],"type":"Point"}
}