{
  "type": "Feature",
  "properties": {
    "iso:country":"US",
    "sg:address":"6677 Gaston Ave",
    "sg:city":"Dallas",
    "sg:classifiers":[
        {
            "category":"Building & Trades",
            "subcategory":"Construction",
            "type":"Services"
        }
    ],
    "sg:phone":"+1 214 827 6318",
    "sg:postcode":"75214",
    "sg:province":"TX",
    "sg:tags":[
        "concrete",
        "contractor"
    ],
    "wof:name":"Titan Concrete Concepts L",
    "wof:placetype":"venue"
},
  "geometry": {"coordinates":[-96.74763799999999,32.816523],"type":"Point"}
}