{
  "type": "Feature",
  "properties": {
    "iso:country":"US",
    "sg:address":"3342 Baylor Camp Rd",
    "sg:city":"Crawford",
    "sg:classifiers":[
        {
            "category":"Shopping",
            "subcategory":"Party Supplies",
            "type":"Retail Goods"
        }
    ],
    "sg:phone":"+1 254 848 2232",
    "sg:postcode":"76638",
    "sg:province":"TX",
    "sg:tags":[
        "toilets-portable"
    ],
    "wof:name":"Taking Care Of Business",
    "wof:placetype":"venue"
},
  "geometry": {"coordinates":[-97.318629,31.606482],"type":"Point"}
}