{
  "type": "Feature",
  "properties": {
    "iso:country":"US",
    "sg:address":"4031 N 10th St",
    "sg:city":"Abilene",
    "sg:classifiers":[
        {
            "category":"Personal",
            "subcategory":"Beauty Salon",
            "type":"Services"
        }
    ],
    "sg:phone":"+1 325 232 7300",
    "sg:postcode":"79603",
    "sg:province":"TX",
    "wof:name":"Cynthia Marie Toornburg",
    "wof:placetype":"venue"
},
  "geometry": {"coordinates":[-99.77463400000001,32.461933],"type":"Point"}
}