{
  "type": "Feature",
  "properties": {
    "iso:country":"US",
    "sg:address":"4407 Bee Caves Rd",
    "sg:city":"Austin",
    "sg:classifiers":[
        {
            "category":"Building & Trades",
            "subcategory":"Construction",
            "type":"Services"
        }
    ],
    "sg:phone":"+1 512 328 8988",
    "sg:postcode":"78746",
    "sg:province":"TX",
    "sg:tags":[
        "home",
        "builder",
        "general",
        "contractor"
    ],
    "sg:website":"www.enfieldhomes.com",
    "wof:name":"Enfield Homes Ltd",
    "wof:placetype":"venue"
},
  "geometry": {"coordinates":[-97.810472,30.282824],"type":"Point"}
}