{
  "type": "Feature",
  "properties": {
    "iso:country":"US",
    "sg:address":"13525 Halifax St",
    "sg:city":"Houston",
    "sg:classifiers":[
        {
            "category":"Building & Trades",
            "subcategory":"Construction",
            "type":"Services"
        }
    ],
    "sg:phone":"+1 281 250 5134",
    "sg:postcode":"77015",
    "sg:province":"TX",
    "sg:tags":[
        "nonresidential"
    ],
    "wof:name":"Romeros Painting & Remodeling",
    "wof:placetype":"venue"
},
  "geometry": {"coordinates":[-95.183436,29.786197],"type":"Point"}
}