{
  "type": "Feature",
  "properties": {
    "iso:country":"US",
    "sg:address":"5015 S Acres Dr",
    "sg:city":"Houston",
    "sg:classifiers":[
        {
            "category":"Organizations",
            "subcategory":"Religious Organization",
            "type":"Services"
        }
    ],
    "sg:phone":"+1 713 733 9184",
    "sg:postcode":"77048",
    "sg:province":"TX",
    "sg:tags":[
        "church"
    ],
    "wof:name":"Charity Missionary Baptist Chr",
    "wof:placetype":"venue"
},
  "geometry": {"coordinates":[-95.349108,29.642369],"type":"Point"}
}