{
  "type": "Feature",
  "properties": {
    "iso:country":"US",
    "sg:address":"2725 Melrose Dr",
    "sg:city":"Plano",
    "sg:classifiers":[
        {
            "category":"Building & Trades",
            "subcategory":"Construction",
            "type":"Services"
        }
    ],
    "sg:phone":"+1 972 867 6090",
    "sg:postcode":"75075",
    "sg:province":"TX",
    "sg:tags":[
        "fence",
        "contractor"
    ],
    "wof:name":"Pool Barrier Of Dallas",
    "wof:placetype":"venue"
},
  "geometry": {"coordinates":[-96.74629,33.038718],"type":"Point"}
}