{
  "type": "Feature",
  "properties": {
    "iso:country":"US",
    "sg:address":"1229 Colorado Ln",
    "sg:city":"Arlington",
    "sg:classifiers":[
        {
            "category":"Autos & Motor Vehicles",
            "subcategory":"Automobile Sales",
            "type":"Retail Goods"
        }
    ],
    "sg:phone":"+1 817 303 2700",
    "sg:postcode":"76015",
    "sg:province":"TX",
    "wof:name":"Bay Motors",
    "wof:placetype":"venue"
},
  "geometry": {"coordinates":[-97.126273,32.702194],"type":"Point"}
}