{
  "type": "Feature",
  "properties": {
    "iso:country":"US",
    "sg:address":"1700 Ave F NW",
    "sg:city":"Childress",
    "sg:classifiers":[
        {
            "category":"Government",
            "subcategory":"Office",
            "type":"Public Place"
        }
    ],
    "sg:phone":"+1 940 937 2571",
    "sg:postcode":"79201",
    "sg:province":"TX",
    "sg:tags":[
        "dept",
        "transportation",
        "texas"
    ],
    "wof:name":"Transportation Texas Dept of",
    "wof:placetype":"venue"
},
  "geometry": {"coordinates":[-100.223658,34.433602],"type":"Point"}
}