{
  "type": "Feature",
  "properties": {
    "iso:country":"US",
    "sg:address":"1101 N Kilgore St",
    "sg:city":"Kilgore",
    "sg:classifiers":[
        {
            "category":"Banks & Credit Unions",
            "subcategory":"Investment Brokerage",
            "type":"Services"
        }
    ],
    "sg:phone":"+1 903 983 0228",
    "sg:postcode":"75662",
    "sg:province":"TX",
    "sg:tags":[
        "oil"
    ],
    "wof:name":"Brogoitti Investments Inc",
    "wof:placetype":"venue"
},
  "geometry": {"coordinates":[-94.866439,32.3909],"type":"Point"}
}