{
  "type": "Feature",
  "properties": {
    "iso:country":"US",
    "sg:address":"402 Roosevelt Ave",
    "sg:city":"San Antonio",
    "sg:classifiers":[
        {
            "category":"Organizations",
            "subcategory":"Religious Organization",
            "type":"Services"
        }
    ],
    "sg:phone":"+1 210 533 7789",
    "sg:postcode":"78210",
    "sg:province":"TX",
    "wof:name":"Faith Baptist Church",
    "wof:placetype":"venue"
},
  "geometry": {"coordinates":[-98.486256,29.399333],"type":"Point"}
}