{
  "type": "Feature",
  "properties": {
    "iso:country":"US",
    "sg:address":"105 Gay St",
    "sg:city":"Arlington",
    "sg:classifiers":[
        {
            "category":"Wholesale",
            "subcategory":"Electrical",
            "type":"Manufacturing & Wholesale Goods"
        }
    ],
    "sg:phone":"+1 817 261 7427",
    "sg:postcode":"76010",
    "sg:province":"TX",
    "sg:tags":[
        "fire",
        "equipment",
        "protection"
    ],
    "wof:name":"Kimbrough Fire Extinguisher",
    "wof:placetype":"venue"
},
  "geometry": {"coordinates":[-97.08761699999999,32.735528],"type":"Point"}
}