{
  "type": "Feature",
  "properties": {
    "iso:country":"US",
    "sg:address":"23182 Blanco Rd",
    "sg:city":"San Antonio",
    "sg:classifiers":[
        {
            "category":"Home & Garden",
            "subcategory":"Garden Supply",
            "type":"Retail Goods"
        }
    ],
    "sg:phone":"+1 210 490 5394",
    "sg:postcode":"78260",
    "sg:province":"TX",
    "sg:tags":[
        "sprinkler"
    ],
    "wof:name":"Moore Irrigation Svc",
    "wof:placetype":"venue"
},
  "geometry": {"coordinates":[-98.520129,29.665865],"type":"Point"}
}