{
  "type": "Feature",
  "properties": {
    "iso:country":"US",
    "sg:address":"3901 Hwy 190 W",
    "sg:city":"Livingston",
    "sg:classifiers":[
        {
            "category":"Home & Garden",
            "subcategory":"Building Materials",
            "type":"Retail Goods"
        }
    ],
    "sg:phone":"+1 936 967 8606",
    "sg:postcode":"77351",
    "sg:province":"TX",
    "sg:tags":[
        "glass",
        "window",
        "plate"
    ],
    "wof:name":"City Glass Etc",
    "wof:placetype":"venue"
},
  "geometry": {"coordinates":[-94.954481,30.712631],"type":"Point"}
}