{
  "type": "Feature",
  "properties": {
    "iso:country":"US",
    "sg:address":"3003 Live Oak St",
    "sg:city":"Dallas",
    "sg:classifiers":[
        {
            "category":"Organizations",
            "subcategory":"Professional Association",
            "type":"Services"
        }
    ],
    "sg:phone":"+1 214 827 7233",
    "sg:postcode":"75204",
    "sg:province":"TX",
    "sg:tags":[
        "trade"
    ],
    "wof:name":"Safe & Vault Technician Assn",
    "wof:placetype":"venue"
},
  "geometry": {"coordinates":[-96.78733099999999,32.790329],"type":"Point"}
}