{
  "type": "Feature",
  "properties": {
    "iso:country":"US",
    "sg:address":"5410 Nordling Rd",
    "sg:city":"Houston",
    "sg:classifiers":[
        {
            "category":"Personal",
            "subcategory":"Beauty Salon",
            "type":"Services"
        }
    ],
    "sg:phone":"+1 713 699 8523",
    "sg:postcode":"77076",
    "sg:province":"TX",
    "sg:tags":[
        "shop"
    ],
    "wof:name":"Elsa Beauty Salon",
    "wof:placetype":"venue"
},
  "geometry": {"coordinates":[-95.39076799999999,29.846689],"type":"Point"}
}