{
  "type": "Feature",
  "properties": {
    "iso:country":"US",
    "sg:address":"5409 Emerald Forest Dr",
    "sg:city":"Austin",
    "sg:classifiers":[
        {
            "category":"Real Estate",
            "subcategory":"Real Estate Agent",
            "type":"Services"
        }
    ],
    "sg:phone":"+1 512 326 4663",
    "sg:postcode":"78745",
    "sg:province":"TX",
    "wof:name":"Home Source Real Estate",
    "wof:placetype":"venue"
},
  "geometry": {"coordinates":[-97.786247,30.214547],"type":"Point"}
}