{
  "type": "Feature",
  "properties": {
    "iso:country":"US",
    "sg:address":"24830 Rock Bend Ln",
    "sg:city":"San Antonio",
    "sg:classifiers":[
        {
            "category":"Real Estate",
            "subcategory":"Real Estate Services",
            "type":"Services"
        }
    ],
    "sg:phone":"+1 210 341 2030",
    "sg:postcode":"78260",
    "sg:province":"TX",
    "sg:tags":[
        "home",
        "inspector"
    ],
    "sg:website":"www.king-inspections.com",
    "wof:name":"KING INSPECTIONS INC",
    "wof:placetype":"venue"
},
  "geometry": {"coordinates":[-98.506497,29.67158],"type":"Point"}
}