{
  "type": "Feature",
  "properties": {
    "iso:country":"US",
    "sg:address":"12104 Cherisse Dr",
    "sg:city":"Austin",
    "sg:classifiers":[
        {
            "category":"Building & Trades",
            "subcategory":"Construction",
            "type":"Services"
        }
    ],
    "sg:phone":"+1 512 301 0993",
    "sg:postcode":"78739",
    "sg:province":"TX",
    "sg:tags":[
        "contractor"
    ],
    "wof:name":"Newmark Homes Independence Park",
    "wof:placetype":"venue"
},
  "geometry": {"coordinates":[-97.92218,30.18643],"type":"Point"}
}