{
  "type": "Feature",
  "properties": {
    "iso:country":"US",
    "sg:address":"801 S Jefferson St",
    "sg:city":"Amarillo",
    "sg:classifiers":[
        {
            "category":"Building & Trades",
            "subcategory":"Construction",
            "type":"Services"
        }
    ],
    "sg:phone":"+1 806 374 4355",
    "sg:postcode":"79101",
    "sg:province":"AR",
    "sg:tags":[
        "carpentry",
        "contractor"
    ],
    "wof:name":"Distinctive Millworks",
    "wof:placetype":"venue"
},
  "geometry": {"coordinates":[-101.846386,35.205681],"type":"Point"}
}