{
  "type": "Feature",
  "properties": {
    "iso:country":"US",
    "sg:address":"11511 Sagecreek Dr",
    "sg:city":"Houston",
    "sg:classifiers":[
        {
            "category":"Manufacturing",
            "subcategory":"Motor Vehicles & Parts",
            "type":"Manufacturing & Wholesale Goods"
        }
    ],
    "sg:phone":"+1 281 484 2093",
    "sg:postcode":"77089",
    "sg:province":"TX",
    "sg:tags":[
        "mfg",
        "trimming"
    ],
    "wof:name":"Idea Grafica",
    "wof:placetype":"venue"
},
  "geometry": {"coordinates":[-95.20998,29.589844],"type":"Point"}
}