{
  "type": "Feature",
  "properties": {
    "iso:country":"US",
    "sg:address":"1115 Kirk Ave",
    "sg:city":"Austin",
    "sg:classifiers":[
        {
            "category":"Building & Trades",
            "subcategory":"Construction",
            "type":"Services"
        }
    ],
    "sg:phone":"+1 512 926 5232",
    "sg:postcode":"78702",
    "sg:province":"TX",
    "sg:tags":[
        "handyman"
    ],
    "wof:name":"Rgs General Repairs",
    "wof:placetype":"venue"
},
  "geometry": {"coordinates":[-97.69697600000001,30.265354],"type":"Point"}
}