{
  "type": "Feature",
  "properties": {
    "iso:country":"US",
    "sg:address":"120 Creekside Dr",
    "sg:city":"Boerne",
    "sg:classifiers":[
        {
            "category":"Building & Trades",
            "subcategory":"Construction",
            "type":"Services"
        }
    ],
    "sg:phone":"+1 830 249 8771",
    "sg:postcode":"78006",
    "sg:province":"TX",
    "sg:tags":[
        "house"
    ],
    "wof:name":"Robason Homes Inc",
    "wof:placetype":"venue"
},
  "geometry": {"coordinates":[-98.718316,29.798512],"type":"Point"}
}