{
  "type": "Feature",
  "properties": {
    "iso:country":"US",
    "sg:address":"4605 Columbia St",
    "sg:city":"Corpus Christi",
    "sg:classifiers":[
        {
            "category":"Organizations",
            "subcategory":"Religious Organization",
            "type":"Services"
        }
    ],
    "sg:phone":"+1 361 853 2842",
    "sg:postcode":"78416",
    "sg:province":"TX",
    "sg:tags":[
        "church"
    ],
    "wof:name":"Faith True Baptist Church",
    "wof:placetype":"venue"
},
  "geometry": {"coordinates":[-97.441228,27.75053],"type":"Point"}
}