{
  "type": "Feature",
  "properties": {
    "iso:country":"US",
    "sg:address":"6724 Davis Blvd",
    "sg:city":"North Richland Hills",
    "sg:classifiers":[
        {
            "category":"Restaurant",
            "type":"Food & Drink"
        }
    ],
    "sg:menulink":"http://www.allmenus.com/tx/northeast-tarrant/204287-sonic/menu/",
    "sg:phone":"+1 817 485 1221",
    "sg:postcode":"76180",
    "sg:province":"TX",
    "sg:tags":[
        "burger",
        "american"
    ],
    "wof:name":"Sonic",
    "wof:placetype":"venue"
},
  "geometry": {"coordinates":[-97.207837,32.869623],"type":"Point"}
}