{
  "type": "Feature",
  "properties": {
    "iso:country":"US",
    "sg:address":"2215 Investment Dr",
    "sg:city":"Pflugerville",
    "sg:classifiers":[
        {
            "category":"Personal",
            "type":"Services"
        }
    ],
    "sg:phone":"+1 512 834 8746",
    "sg:postcode":"78660",
    "sg:province":"TX",
    "sg:tags":[
        "local"
    ],
    "sg:website":"www.alphagraniteaustin.com",
    "wof:name":"Alpha Granite",
    "wof:placetype":"venue"
},
  "geometry": {"coordinates":[-97.629929,30.401041],"type":"Point"}
}