{
  "type": "Feature",
  "properties": {
    "iso:country":"US",
    "sg:address":"2908 Overdale Rd",
    "sg:city":"Austin",
    "sg:classifiers":[
        {
            "category":"Museum",
            "type":"Entertainment"
        }
    ],
    "sg:phone":"+1 512 928 3122",
    "sg:postcode":"78723",
    "sg:province":"TX",
    "wof:name":"Tejano Artist Music Museum",
    "wof:placetype":"venue"
},
  "geometry": {"coordinates":[-97.683031,30.302971],"type":"Point"}
}