{
  "type": "Feature",
  "properties": {
    "iso:country":"US",
    "sg:address":"104 Arboleda Cir",
    "sg:city":"Boerne",
    "sg:classifiers":[
        {
            "category":"Professional",
            "subcategory":"Detective & Security Services",
            "type":"Services"
        }
    ],
    "sg:phone":"+1 830 537 3364",
    "sg:postcode":"78006",
    "sg:province":"TX",
    "sg:tags":[
        "information",
        "bureau"
    ],
    "wof:name":"R R Services",
    "wof:placetype":"venue"
},
  "geometry": {"coordinates":[-98.82067000000001,29.783322],"type":"Point"}
}