{
  "type": "Feature",
  "properties": {
    "iso:country":"US",
    "sg:address":"301 US Hwy 84",
    "sg:city":"Coleman",
    "sg:classifiers":[
        {
            "category":"Shopping",
            "type":"Retail Goods"
        }
    ],
    "sg:phone":"+1 325 625 2254",
    "sg:postcode":"76834",
    "sg:province":"TX",
    "sg:tags":[
        "monument"
    ],
    "wof:name":"Mc Corkle Monument Co",
    "wof:placetype":"venue"
},
  "geometry": {"coordinates":[-99.42722999999999,31.829207],"type":"Point"}
}