{
  "type": "Feature",
  "properties": {
    "iso:country":"US",
    "sg:address":"11408 Ravenview Rd",
    "sg:city":"Dallas",
    "sg:classifiers":[
        {
            "category":"Shopping",
            "subcategory":"Antiques",
            "type":"Retail Goods"
        }
    ],
    "sg:phone":"+1 972 557 7606",
    "sg:postcode":"75253",
    "sg:province":"TX",
    "wof:name":"Country Cottage",
    "wof:placetype":"venue"
},
  "geometry": {"coordinates":[-96.627602,32.6903],"type":"Point"}
}