{
  "type": "Feature",
  "properties": {
    "iso:country":"US",
    "sg:address":"8632 Labron Ave",
    "sg:city":"Dallas",
    "sg:classifiers":[
        {
            "category":"Professional",
            "subcategory":"Management & Consulting",
            "type":"Services"
        }
    ],
    "sg:phone":"+1 214 956 9794",
    "sg:postcode":"75209",
    "sg:province":"TX",
    "sg:tags":[
        "retail",
        "direct",
        "sales"
    ],
    "wof:name":"Founders Fuel & Oil Corp",
    "wof:placetype":"venue"
},
  "geometry": {"coordinates":[-96.841707,32.858089],"type":"Point"}
}