{
  "type": "Feature",
  "properties": {
    "iso:country":"US",
    "sg:address":"1226 3 Forks Dr",
    "sg:city":"Katy",
    "sg:classifiers":[
        {
            "category":"Banks & Credit Unions",
            "subcategory":"Bank",
            "type":"Services"
        }
    ],
    "sg:phone":"+1 281 392 1612",
    "sg:postcode":"77450",
    "sg:province":"TX",
    "sg:tags":[
        "mortgage"
    ],
    "wof:name":"Diaz Mortgage Consultants",
    "wof:placetype":"venue"
},
  "geometry": {"coordinates":[-95.76915099999999,29.594703],"type":"Point"}
}