{
  "type": "Feature",
  "properties": {
    "iso:country":"US",
    "sg:address":"110 E Broadway St",
    "sg:city":"Del Rio",
    "sg:classifiers":[
        {
            "category":"Social Services",
            "type":"Services"
        }
    ],
    "sg:phone":"+1 830 768 2847",
    "sg:postcode":"78840",
    "sg:province":"TX",
    "sg:tags":[
        "organization",
        "welfare"
    ],
    "wof:name":"Crime Stoppers",
    "wof:placetype":"venue"
},
  "geometry": {"coordinates":[-100.898746,29.362078],"type":"Point"}
}