{
  "type": "Feature",
  "properties": {
    "iso:country":"US",
    "sg:address":"505 Forest Trce",
    "sg:city":"Rockwall",
    "sg:classifiers":[
        {
            "category":"Insurance",
            "subcategory":"Insurance Agent",
            "type":"Services"
        }
    ],
    "sg:phone":"+1 972 722 0341",
    "sg:postcode":"75087",
    "sg:province":"TX",
    "wof:name":"Allstate",
    "wof:placetype":"venue"
},
  "geometry": {"coordinates":[-96.467707,32.922282],"type":"Point"}
}