{
  "type": "Feature",
  "properties": {
    "iso:country":"US",
    "sg:address":"410 Bluebonnet Dr",
    "sg:city":"Tyler",
    "sg:classifiers":[
        {
            "category":"Real Estate",
            "subcategory":"Real Estate Operator",
            "type":"Services"
        }
    ],
    "sg:phone":"+1 903 595 2050",
    "sg:postcode":"75701",
    "sg:province":"TX",
    "sg:tags":[
        "building",
        "nonresidential"
    ],
    "wof:name":"Front Porch Properties LP",
    "wof:placetype":"venue"
},
  "geometry": {"coordinates":[-95.305633,32.317919],"type":"Point"}
}