{
  "type": "Feature",
  "properties": {
    "iso:country":"US",
    "sg:address":"414 Executive Center Blvd",
    "sg:city":"El Paso",
    "sg:classifiers":[
        {
            "category":"Insurance",
            "subcategory":"Insurance Agent",
            "type":"Services"
        }
    ],
    "sg:phone":"+1 915 532 1423",
    "sg:postcode":"79902",
    "sg:province":"TX",
    "wof:name":"State Farm Insurance",
    "wof:placetype":"venue"
},
  "geometry": {"coordinates":[-106.513435,31.795305],"type":"Point"}
}