{
  "type": "Feature",
  "properties": {
    "iso:country":"US",
    "sg:address":"1252 Security Dr",
    "sg:city":"Dallas",
    "sg:classifiers":[
        {
            "category":"Autos & Motor Vehicles",
            "subcategory":"Auto Supplies",
            "type":"Retail Goods"
        },
        {
            "category":"Manufacturing",
            "subcategory":"Glass & Minerals",
            "type":"Manufacturing & Wholesale Goods"
        }
    ],
    "sg:phone":"+1 214 631 4220",
    "sg:postcode":"75247",
    "sg:province":"TX",
    "sg:tags":[
        "window",
        "material",
        "coating",
        "tinting"
    ],
    "sg:website":"http://www.sun-gard.com",
    "wof:name":"Sun-Gard Mid-America",
    "wof:placetype":"venue"
},
  "geometry": {"coordinates":[-96.8535,32.805413],"type":"Point"}
}