{
  "type": "Feature",
  "properties": {
    "iso:country":"US",
    "sg:address":"7301 Bucknell Dr",
    "sg:city":"Austin",
    "sg:classifiers":[
        {
            "category":"Professional",
            "subcategory":"Management & Consulting",
            "type":"Services"
        }
    ],
    "sg:phone":"+1 512 926 6329",
    "sg:postcode":"78723",
    "sg:province":"TX",
    "sg:tags":[
        "marketing",
        "program"
    ],
    "wof:name":"MLC Hobbs & Assoc",
    "wof:placetype":"venue"
},
  "geometry": {"coordinates":[-97.673711,30.322569],"type":"Point"}
}