{
  "type": "Feature",
  "properties": {
    "iso:country":"US",
    "sg:address":"9670 Mesa Dr",
    "sg:city":"Houston",
    "sg:classifiers":[
        {
            "category":"Wholesale",
            "subcategory":"Electrical",
            "type":"Manufacturing & Wholesale Goods"
        }
    ],
    "sg:phone":"+1 713 631 5332",
    "sg:postcode":"77078",
    "sg:province":"TX",
    "sg:tags":[
        "electronic"
    ],
    "wof:name":"Mesa Video & Communications",
    "wof:placetype":"venue"
},
  "geometry": {"coordinates":[-95.262317,29.854214],"type":"Point"}
}