{
  "type": "Feature",
  "properties": {
    "iso:country":"US",
    "sg:address":"2238 Macarthur Dr",
    "sg:city":"Orange",
    "sg:classifiers":[
        {
            "category":"Home & Garden",
            "subcategory":"Home Furnishings",
            "type":"Retail Goods"
        },
        {
            "category":"Professional",
            "subcategory":"Art Services",
            "type":"Services"
        },
        {
            "category":"Home & Garden",
            "subcategory":"Carpets & Floor Coverings",
            "type":"Retail Goods"
        }
    ],
    "sg:phone":"+1 409 670 0235",
    "sg:postcode":"77630",
    "sg:province":"TX",
    "sg:tags":[
        "draperies",
        "designer",
        "rug",
        "window",
        "treatment",
        "interior",
        "curtain",
        "decorator"
    ],
    "wof:name":"Interior Design Studio",
    "wof:placetype":"venue"
},
  "geometry": {"coordinates":[-93.755605,30.0942],"type":"Point"}
}