{
  "type": "Feature",
  "properties": {
    "iso:country":"US",
    "sg:address":"8843 Grissom Rd",
    "sg:city":"San Antonio",
    "sg:classifiers":[
        {
            "category":"Health Services",
            "subcategory":"Doctor",
            "type":"Services"
        }
    ],
    "sg:phone":"+1 210 226 5685",
    "sg:postcode":"78251",
    "sg:province":"TX",
    "sg:tags":[
        "dentist"
    ],
    "wof:name":"Downtown Family Dental",
    "wof:placetype":"venue"
},
  "geometry": {"coordinates":[-98.658762,29.480283],"type":"Point"}
}