{
  "type": "Feature",
  "properties": {
    "iso:country":"US",
    "sg:address":"209 Belmont St",
    "sg:city":"Tomball",
    "sg:classifiers":[
        {
            "category":"Freight",
            "type":"Transportation"
        }
    ],
    "sg:phone":"+1 281 731 7687",
    "sg:postcode":"77375",
    "sg:province":"TX",
    "sg:tags":[
        "operator",
        "trucking"
    ],
    "wof:name":"Mustang Heavy Haul",
    "wof:placetype":"venue"
},
  "geometry": {"coordinates":[-95.61062,30.092339],"type":"Point"}
}