{
  "type": "Feature",
  "properties": {
    "iso:country":"US",
    "sg:address":"6100 Hirsch Rd",
    "sg:city":"Houston",
    "sg:classifiers":[
        {
            "category":"Organizations",
            "subcategory":"Religious Organization",
            "type":"Services"
        }
    ],
    "sg:phone":"+1 713 635 1397",
    "sg:postcode":"77026",
    "sg:province":"TX",
    "sg:tags":[
        "church"
    ],
    "wof:name":"New Loyalty Baptist Church",
    "wof:placetype":"venue"
},
  "geometry": {"coordinates":[-95.328716,29.816028],"type":"Point"}
}