{
  "type": "Feature",
  "properties": {
    "iso:country":"US",
    "sg:address":"110 W Hickory St",
    "sg:city":"Denton",
    "sg:classifiers":[
        {
            "category":"Government",
            "subcategory":"Office",
            "type":"Public Place"
        }
    ],
    "sg:phone":"+1 940 565 8670",
    "sg:postcode":"76201",
    "sg:province":"TX",
    "sg:tags":[
        "state",
        "inspection"
    ],
    "wof:name":"Alcoholic Beverage Commission",
    "wof:placetype":"venue"
},
  "geometry": {"coordinates":[-97.132548,33.214599],"type":"Point"}
}