{
  "type": "Feature",
  "properties": {
    "iso:country":"US",
    "sg:address":"111 Blacksmiths Dr",
    "sg:city":"Georgetown",
    "sg:classifiers":[
        {
            "category":"Health Services",
            "subcategory":"Doctor",
            "type":"Services"
        }
    ],
    "sg:phone":"+1 512 931 0965",
    "sg:postcode":"78633",
    "sg:province":"TX",
    "wof:name":"Kavieff Robert B DDS Msd",
    "wof:placetype":"venue"
},
  "geometry": {"coordinates":[-97.70986000000001,30.708554],"type":"Point"}
}