{
  "type": "Feature",
  "properties": {
    "iso:country":"US",
    "sg:address":"5439 Mersea Dr",
    "sg:city":"Katy",
    "sg:classifiers":[
        {
            "category":"Building & Trades",
            "subcategory":"Plumbing",
            "type":"Services"
        }
    ],
    "sg:phone":"+1 281 859 6293",
    "sg:postcode":"77449",
    "sg:province":"TX",
    "sg:tags":[
        "contractor",
        "mechanical"
    ],
    "wof:name":"A/C Mechanical Solutions",
    "wof:placetype":"venue"
},
  "geometry": {"coordinates":[-95.724136,29.85058],"type":"Point"}
}