{
  "type": "Feature",
  "properties": {
    "iso:country":"US",
    "sg:address":"700 State Hwy 323",
    "sg:city":"Tyler",
    "sg:classifiers":[
        {
            "category":"Home & Garden",
            "subcategory":"Furniture",
            "type":"Retail Goods"
        }
    ],
    "sg:phone":"+1 903 509 1444",
    "sg:postcode":"75701",
    "sg:province":"TX",
    "wof:name":"Sleep Masters Sleep Ctr",
    "wof:placetype":"venue"
},
  "geometry": {"coordinates":[-95.31155200000001,32.303499],"type":"Point"}
}