{
  "type": "Feature",
  "properties": {
    "iso:country":"US",
    "sg:address":"21600 State Hwy 71",
    "sg:city":"Spicewood",
    "sg:classifiers":[
        {
            "category":"Building & Trades",
            "subcategory":"Construction",
            "type":"Services"
        }
    ],
    "sg:phone":"+1 512 264 2741",
    "sg:postcode":"78669",
    "sg:province":"TX",
    "sg:tags":[
        "general",
        "contractor"
    ],
    "wof:name":"Safarick & Son",
    "wof:placetype":"venue"
},
  "geometry": {"coordinates":[-98.068941,30.359743],"type":"Point"}
}