{
  "type": "Feature",
  "properties": {
    "iso:country":"US",
    "sg:address":"4105 Westlake Dr",
    "sg:city":"Austin",
    "sg:classifiers":[
        {
            "category":"Shopping",
            "type":"Retail Goods"
        }
    ],
    "sg:phone":"+1 512 328 8100",
    "sg:postcode":"78746",
    "sg:province":"TX",
    "sg:tags":[
        "equipment",
        "telephone",
        "supply"
    ],
    "wof:name":"American Payphone Co",
    "wof:placetype":"venue"
},
  "geometry": {"coordinates":[-97.79412600000001,30.334336],"type":"Point"}
}