{
  "type": "Feature",
  "properties": {
    "iso:country":"US",
    "sg:address":"1305 S Hwy 285",
    "sg:city":"Fort Stockton",
    "sg:classifiers":[
        {
            "category":"Restaurant",
            "type":"Food & Drink"
        }
    ],
    "sg:phone":"+1 432 336 3243",
    "sg:postcode":"79735",
    "sg:province":"TX",
    "wof:name":"Atrium Club & Steakhouse",
    "wof:placetype":"venue"
},
  "geometry": {"coordinates":[-102.863812,30.868772],"type":"Point"}
}