{
  "type": "Feature",
  "properties": {
    "iso:country":"US",
    "sg:address":"1550 Champions Dr",
    "sg:city":"Rockwall",
    "sg:classifiers":[
        {
            "category":"Wholesale",
            "subcategory":"Furniture",
            "type":"Manufacturing & Wholesale Goods"
        }
    ],
    "sg:phone":"+1 972 771 9823",
    "sg:postcode":"75087",
    "sg:province":"TX",
    "wof:name":"Lakeside Distributing",
    "wof:placetype":"venue"
},
  "geometry": {"coordinates":[-96.478144,32.950058],"type":"Point"}
}