{
  "type": "Feature",
  "properties": {
    "iso:country":"US",
    "sg:address":"2001 Ross Ave Ste 1800",
    "sg:city":"Dallas",
    "sg:classifiers":[
        {
            "category":"Professional",
            "subcategory":"Accounting & Tax Preparation",
            "type":"Services"
        }
    ],
    "sg:phone":"+1 214 999 1400",
    "sg:postcode":"75201",
    "sg:province":"TX",
    "sg:tags":[
        "accountant"
    ],
    "wof:name":"Pricewaterhousecoopers Llp",
    "wof:placetype":"venue"
},
  "geometry": {"coordinates":[-96.79940000000001,32.7869],"type":"Point"}
}