{
  "type": "Feature",
  "properties": {
    "iso:country":"US",
    "sg:address":"3046 Lavon Dr Ste 136",
    "sg:city":"Garland",
    "sg:classifiers":[
        {
            "category":"Retail",
            "subcategory":"Veterinary Services",
            "type":"Services"
        }
    ],
    "sg:phone":"+1 972 530 3951",
    "sg:postcode":"75040",
    "sg:province":"TX",
    "sg:tags":[
        "veterinarian"
    ],
    "wof:name":"Pipes Charles R DVM",
    "wof:placetype":"venue"
},
  "geometry": {"coordinates":[-96.621498,32.943901],"type":"Point"}
}