{
  "type": "Feature",
  "properties": {
    "iso:country":"US",
    "sg:address":"15335 North Fwy",
    "sg:city":"Houston",
    "sg:classifiers":[
        {
            "category":"Restaurant",
            "type":"Food & Drink"
        }
    ],
    "sg:phone":"+1 281 873 4500",
    "sg:postcode":"77090",
    "sg:province":"TX",
    "sg:tags":[
        "eating"
    ],
    "wof:name":"Sudies Catfish House Inc",
    "wof:placetype":"venue"
},
  "geometry": {"coordinates":[-95.424036,29.988327],"type":"Point"}
}