{
  "type": "Feature",
  "properties": {
    "iso:country":"US",
    "sg:address":"216 E 14th St",
    "sg:city":"Houston",
    "sg:classifiers":[
        {
            "category":"Utilities",
            "subcategory":"Mobile Phone",
            "type":"Services"
        }
    ],
    "sg:phone":"+1 713 863 8605",
    "sg:postcode":"77008",
    "sg:province":"TX",
    "sg:tags":[
        "telephone",
        "cellular"
    ],
    "wof:name":"Cingular Wireless",
    "wof:placetype":"venue"
},
  "geometry": {"coordinates":[-95.395573,29.796181],"type":"Point"}
}