{
  "type": "Feature",
  "properties": {
    "iso:country":"US",
    "sg:address":"2418 N Kansas St",
    "sg:city":"El Paso",
    "sg:classifiers":[
        {
            "category":"Professional",
            "subcategory":"Computer Services",
            "type":"Services"
        }
    ],
    "sg:phone":"+1 915 532 1669",
    "sg:postcode":"79902",
    "sg:province":"TX",
    "sg:tags":[
        "home",
        "consulting",
        "page",
        "dev",
        "internet"
    ],
    "wof:name":"B C Design",
    "wof:placetype":"venue"
},
  "geometry": {"coordinates":[-106.500034,31.776549],"type":"Point"}
}