{
  "type": "Feature",
  "properties": {
    "iso:country":"US",
    "sg:address":"11111 S I H 35",
    "sg:city":"Austin",
    "sg:classifiers":[
        {
            "category":"Banks & Credit Unions",
            "subcategory":"Financial Services",
            "type":"Services"
        }
    ],
    "sg:phone":"+1 512 280 6571",
    "sg:postcode":"78747",
    "sg:province":"TX",
    "sg:tags":[
        "broker",
        "mortgage"
    ],
    "wof:name":"Onion Creek Mortgage",
    "wof:placetype":"venue"
},
  "geometry": {"coordinates":[-97.797096,30.136],"type":"Point"}
}