{
  "type": "Feature",
  "properties": {
    "iso:country":"US",
    "sg:address":"6933 Olson Ln",
    "sg:city":"Pasadena",
    "sg:classifiers":[
        {
            "category":"Manufacturing",
            "subcategory":"Metals",
            "type":"Manufacturing & Wholesale Goods"
        },
        {
            "category":"Manufacturing",
            "subcategory":"Tools & Machinery",
            "type":"Manufacturing & Wholesale Goods"
        }
    ],
    "sg:phone":"+1 281 998 0560",
    "sg:postcode":"77505",
    "sg:province":"TX",
    "sg:tags":[
        "valve",
        "mfg"
    ],
    "wof:name":"Handwheel's Inc",
    "wof:placetype":"venue"
},
  "geometry": {"coordinates":[-95.135434,29.658862],"type":"Point"}
}