{
  "type": "Feature",
  "properties": {
    "iso:country":"US",
    "sg:address":"1564 Co Rd 474",
    "sg:city":"Brownfield",
    "sg:classifiers":[
        {
            "category":"Wholesale",
            "subcategory":"Farm Supplies",
            "type":"Manufacturing & Wholesale Goods"
        }
    ],
    "sg:phone":"+1 806 637 1800",
    "sg:postcode":"79316",
    "sg:province":"TX",
    "sg:tags":[
        "peanut",
        "product"
    ],
    "wof:name":"Birdsong Peanuts",
    "wof:placetype":"venue"
},
  "geometry": {"coordinates":[-102.33521500000001,33.130542],"type":"Point"}
}