{
  "type": "Feature",
  "properties": {
    "iso:country":"US",
    "sg:address":"4901 Woodview Ave",
    "sg:city":"Austin",
    "sg:classifiers":[
        {
            "category":"Building & Trades",
            "subcategory":"Construction",
            "type":"Services"
        }
    ],
    "sg:phone":"+1 512 453 7510",
    "sg:postcode":"78756",
    "sg:province":"TX",
    "sg:tags":[
        "system",
        "contractor",
        "air conditioning"
    ],
    "wof:name":"Ac Solar",
    "wof:placetype":"venue"
},
  "geometry": {"coordinates":[-97.743683,30.322439],"type":"Point"}
}