{
  "type": "Feature",
  "properties": {
    "iso:country":"US",
    "sg:address":"4030 Sam Houston Ave",
    "sg:city":"Huntsville",
    "sg:classifiers":[
        {
            "category":"Real Estate",
            "subcategory":"Real Estate Agent",
            "type":"Services"
        }
    ],
    "sg:phone":"+1 936 291 1247",
    "sg:postcode":"77340",
    "sg:province":"TX",
    "sg:tags":[
        "management"
    ],
    "wof:name":"Over Site Management Co LLC",
    "wof:placetype":"venue"
},
  "geometry": {"coordinates":[-95.55006,30.707888],"type":"Point"}
}