{
  "type": "Feature",
  "properties": {
    "iso:country":"US",
    "sg:address":"9858 N Villa Dr",
    "sg:city":"Houston",
    "sg:classifiers":[
        {
            "category":"Organizations",
            "subcategory":"Religious Organization",
            "type":"Services"
        }
    ],
    "sg:phone":"+1 281 807 9851",
    "sg:postcode":"77064",
    "sg:province":"TX",
    "wof:name":"Children For Jesus Minist",
    "wof:placetype":"venue"
},
  "geometry": {"coordinates":[-95.56421,29.908007],"type":"Point"}
}