{
  "type": "Feature",
  "properties": {
    "iso:country":"US",
    "sg:address":"2719 Routh St",
    "sg:city":"Dallas",
    "sg:classifiers":[
        {
            "category":"Shopping",
            "subcategory":"Books",
            "type":"Retail Goods"
        }
    ],
    "sg:phone":"+1 214 871 2440",
    "sg:postcode":"75201",
    "sg:province":"TX",
    "sg:tags":[
        "dealer"
    ],
    "sg:website":"www.dallasinstitute.org",
    "wof:name":"Dallas Institute Of Humanities",
    "wof:placetype":"venue"
},
  "geometry": {"coordinates":[-96.803629,32.797843],"type":"Point"}
}