{
  "type": "Feature",
  "properties": {
    "iso:country":"US",
    "sg:address":"12 Staudt St",
    "sg:city":"Boerne",
    "sg:classifiers":[
        {
            "category":"Government",
            "subcategory":"Office",
            "type":"Public Place"
        }
    ],
    "sg:phone":"+1 830 249 3827",
    "sg:postcode":"78006",
    "sg:province":"TX",
    "sg:website":"www.co.kendall.tx.us",
    "wof:name":"Kendall County Road & Bridge",
    "wof:placetype":"venue"
},
  "geometry": {"coordinates":[-98.72264,29.805477],"type":"Point"}
}