{
  "type": "Feature",
  "properties": {
    "iso:country":"US",
    "sg:address":"120 Jay Jay Cove",
    "sg:city":"Kyle",
    "sg:classifiers":[
        {
            "category":"Building & Trades",
            "subcategory":"Plumbing",
            "type":"Services"
        }
    ],
    "sg:phone":"+1 512 268 7701",
    "sg:postcode":"78640",
    "sg:province":"TX",
    "sg:tags":[
        "contractor"
    ],
    "wof:name":"J Tek Plumbing & Services Ltd",
    "wof:placetype":"venue"
},
  "geometry": {"coordinates":[-97.901521,30.017944],"type":"Point"}
}