{
  "type": "Feature",
  "properties": {
    "iso:country":"US",
    "sg:address":"5700 Garrett Dr",
    "sg:city":"Plano",
    "sg:classifiers":[
        {
            "category":"Shopping",
            "type":"Retail Goods"
        }
    ],
    "sg:phone":"+1 972 608 0137",
    "sg:postcode":"75093",
    "sg:province":"TX",
    "sg:tags":[
        "cosmetic",
        "perfume"
    ],
    "wof:name":"Mary Kay Cosmetics",
    "wof:placetype":"venue"
},
  "geometry": {"coordinates":[-96.81841799999999,33.037528],"type":"Point"}
}