{
  "type": "Feature",
  "properties": {
    "iso:country":"US",
    "sg:address":"11615 Foxburo Dr",
    "sg:city":"Houston",
    "sg:classifiers":[
        {
            "category":"Professional",
            "subcategory":"Business Services",
            "type":"Services"
        }
    ],
    "sg:phone":"+1 713 819 5110",
    "sg:postcode":"77065",
    "sg:province":"TX",
    "sg:tags":[
        "drafting"
    ],
    "wof:name":"Details & Designs",
    "wof:placetype":"venue"
},
  "geometry": {"coordinates":[-95.59572300000001,29.936613],"type":"Point"}
}