{
  "type": "Feature",
  "properties": {
    "iso:country":"US",
    "sg:address":"2411 E Ann Arbor Ave",
    "sg:city":"Dallas",
    "sg:classifiers":[
        {
            "category":"Personal",
            "subcategory":"Beauty Salon",
            "type":"Services"
        }
    ],
    "sg:phone":"+1 214 371 3299",
    "sg:postcode":"75216",
    "sg:province":"TX",
    "wof:name":"Ivory's Beauty Salon",
    "wof:placetype":"venue"
},
  "geometry": {"coordinates":[-96.78199600000001,32.69951],"type":"Point"}
}