{
  "type": "Feature",
  "properties": {
    "iso:country":"US",
    "sg:address":"1310 Champions Dr",
    "sg:city":"Rockwall",
    "sg:classifiers":[
        {
            "category":"Building & Trades",
            "subcategory":"Construction",
            "type":"Services"
        }
    ],
    "sg:phone":"+1 972 772 8643",
    "sg:postcode":"75087",
    "sg:province":"TX",
    "sg:tags":[
        "hanging",
        "contractor"
    ],
    "wof:name":"Ray Painting Barry",
    "wof:placetype":"venue"
},
  "geometry": {"coordinates":[-96.473664,32.951429],"type":"Point"}
}