{
  "type": "Feature",
  "properties": {
    "iso:country":"US",
    "sg:address":"904 Hwy 35 S",
    "sg:city":"Rockport",
    "sg:classifiers":[
        {
            "category":"Shopping",
            "subcategory":"Department Store",
            "type":"Retail Goods"
        }
    ],
    "sg:phone":"+1 361 729 2476",
    "sg:postcode":"78382",
    "sg:province":"TX",
    "wof:name":"C L Petroleum",
    "wof:placetype":"venue"
},
  "geometry": {"coordinates":[-97.06143899999999,28.018012],"type":"Point"}
}