{
  "type": "Feature",
  "properties": {
    "iso:country":"US",
    "sg:address":"27 Kingwood Greens Dr",
    "sg:city":"Kingwood",
    "sg:classifiers":[
        {
            "category":"Real Estate",
            "subcategory":"Developer",
            "type":"Services"
        }
    ],
    "sg:phone":"+1 281 361 8590",
    "sg:postcode":"77339",
    "sg:province":"TX",
    "sg:tags":[
        "investing"
    ],
    "wof:name":"Gozepeda",
    "wof:placetype":"venue"
},
  "geometry": {"coordinates":[-95.17804099999999,30.032466],"type":"Point"}
}