{
  "type": "Feature",
  "properties": {
    "iso:country":"US",
    "sg:address":"2330 Greencrest Blvd",
    "sg:city":"Rockwall",
    "sg:classifiers":[
        {
            "category":"Restaurant",
            "type":"Food & Drink"
        }
    ],
    "sg:menulink":"http://www.allmenus.com/tx/northwest-rockwall/94455-dominos-pizza/menu/",
    "sg:phone":"+1 972 771 4092",
    "sg:postcode":"75087",
    "sg:province":"TX",
    "sg:tags":[
        "american",
        "wing",
        "pizza"
    ],
    "wof:name":"Domino's Pizza",
    "wof:placetype":"venue"
},
  "geometry": {"coordinates":[-96.460504,32.902597],"type":"Point"}
}