{
  "type": "Feature",
  "properties": {
    "iso:country":"US",
    "sg:address":"4407 W Commerce St",
    "sg:city":"San Antonio",
    "sg:classifiers":[
        {
            "category":"Retail",
            "subcategory":"Auto Repair",
            "type":"Services"
        }
    ],
    "sg:phone":"+1 210 432 1431",
    "sg:postcode":"78237",
    "sg:province":"TX",
    "sg:tags":[
        "general"
    ],
    "wof:name":"Kennedy Garage",
    "wof:placetype":"venue"
},
  "geometry": {"coordinates":[-98.548382,29.430306],"type":"Point"}
}