{
  "type": "Feature",
  "properties": {
    "iso:country":"US",
    "sg:address":"1107 Houston St",
    "sg:city":"Wellington",
    "sg:classifiers":[
        {
            "category":"Restaurant",
            "type":"Food & Drink"
        }
    ],
    "sg:phone":"+1 806 447 2941",
    "sg:postcode":"79095",
    "sg:province":"TX",
    "sg:tags":[
        "eating"
    ],
    "wof:name":"Mona's Cocina",
    "wof:placetype":"venue"
},
  "geometry": {"coordinates":[-100.204898,34.853076],"type":"Point"}
}