{
  "type": "Feature",
  "properties": {
    "iso:country":"US",
    "sg:address":"7894 State Hwy 6",
    "sg:city":"Waco",
    "sg:classifiers":[
        {
            "category":"Restaurant",
            "type":"Food & Drink"
        }
    ],
    "sg:phone":"+1 254 848 2446",
    "sg:postcode":"76712",
    "sg:province":"TX",
    "sg:tags":[
        "eating"
    ],
    "wof:name":"El Sombrero",
    "wof:placetype":"venue"
},
  "geometry": {"coordinates":[-97.288051,31.572543],"type":"Point"}
}