{
  "type": "Feature",
  "properties": {
    "iso:country":"US",
    "sg:address":"1935 Ave B",
    "sg:city":"Katy",
    "sg:classifiers":[
        {
            "category":"Building & Trades",
            "subcategory":"Cleaning & Sanitation",
            "type":"Services"
        }
    ],
    "sg:phone":"+1 281 391 7299",
    "sg:postcode":"77493",
    "sg:province":"TX",
    "sg:tags":[
        "maintenance"
    ],
    "wof:name":"Janitors Closet",
    "wof:placetype":"venue"
},
  "geometry": {"coordinates":[-95.822345,29.800228],"type":"Point"}
}