{
  "type": "Feature",
  "properties": {
    "iso:country":"US",
    "sg:address":"3528 Kimble Dr",
    "sg:city":"Plano",
    "sg:classifiers":[
        {
            "category":"Health Services",
            "subcategory":"Clinic",
            "type":"Services"
        }
    ],
    "sg:phone":"+1 972 377 7351",
    "sg:postcode":"75025",
    "sg:province":"TX",
    "sg:tags":[
        "specialty",
        "outpatient"
    ],
    "wof:name":"Funkensteins Lab",
    "wof:placetype":"venue"
},
  "geometry": {"coordinates":[-96.762061,33.10442],"type":"Point"}
}