{
  "type": "Feature",
  "properties": {
    "iso:country":"US",
    "sg:address":"8400 Marbach Rd",
    "sg:city":"San Antonio",
    "sg:classifiers":[
        {
            "category":"Shopping",
            "subcategory":"Jewelry",
            "type":"Retail Goods"
        }
    ],
    "sg:phone":"+1 210 674 1656",
    "sg:postcode":"78227",
    "sg:province":"TX",
    "sg:tags":[
        "jeweler"
    ],
    "wof:name":"National Jewelry",
    "wof:placetype":"venue"
},
  "geometry": {"coordinates":[-98.655513,29.417767],"type":"Point"}
}