{
  "type": "Feature",
  "properties": {
    "iso:country":"US",
    "sg:address":"8125 Phelan Blvd",
    "sg:city":"Beaumont",
    "sg:classifiers":[
        {
            "category":"Building & Trades",
            "subcategory":"Construction",
            "type":"Services"
        }
    ],
    "sg:phone":"+1 409 860 5333",
    "sg:postcode":"77706",
    "sg:province":"TX",
    "sg:tags":[
        "designer",
        "dealer",
        "pool",
        "swimming"
    ],
    "sg:website":"www.coastalpoolsinc.com",
    "wof:name":"Coastal Pools Inc",
    "wof:placetype":"venue"
},
  "geometry": {"coordinates":[-94.18577000000001,30.07574],"type":"Point"}
}