{
  "type": "Feature",
  "properties": {
    "iso:country":"US",
    "sg:address":"1729 Analog Dr",
    "sg:city":"Richardson",
    "sg:classifiers":[
        {
            "category":"Health Services",
            "subcategory":"Doctor",
            "type":"Services"
        }
    ],
    "sg:phone":"+1 972 437 0200",
    "sg:postcode":"75081",
    "sg:province":"TX",
    "sg:tags":[
        "surgeon",
        "oral"
    ],
    "wof:name":"Lee Christie DDS",
    "wof:placetype":"venue"
},
  "geometry": {"coordinates":[-96.701103,32.973],"type":"Point"}
}