{
  "type": "Feature",
  "properties": {
    "iso:country":"US",
    "sg:address":"1601 Crosswind Dr",
    "sg:city":"Bryan",
    "sg:classifiers":[
        {
            "category":"Manufacturing",
            "subcategory":"Tools & Machinery",
            "type":"Manufacturing & Wholesale Goods"
        }
    ],
    "sg:phone":"+1 979 778 8820",
    "sg:postcode":"77808",
    "sg:province":"TX",
    "sg:tags":[
        "machine",
        "shop"
    ],
    "wof:name":"J-Mar Machining",
    "wof:placetype":"venue"
},
  "geometry": {"coordinates":[-96.343548,30.726139],"type":"Point"}
}