{
  "type": "Feature",
  "properties": {
    "iso:country":"US",
    "sg:address":"223 S Ww White Rd",
    "sg:city":"San Antonio",
    "sg:classifiers":[
        {
            "category":"Professional",
            "type":"Services"
        }
    ],
    "sg:phone":"+1 210 333 9833",
    "sg:postcode":"78219",
    "sg:province":"TX",
    "wof:name":"Artic Winds",
    "wof:placetype":"venue"
},
  "geometry": {"coordinates":[-98.40555500000001,29.428174],"type":"Point"}
}