{
  "type": "Feature",
  "properties": {
    "iso:country":"US",
    "sg:address":"423 Bird House Hill Rd",
    "sg:city":"Schulenburg",
    "sg:classifiers":[
        {
            "category":"Farming",
            "subcategory":"Livestock Farm",
            "type":"Manufacturing & Wholesale Goods"
        }
    ],
    "sg:phone":"+1 979 561 5010",
    "sg:postcode":"78956",
    "sg:province":"TX",
    "sg:tags":[
        "beef",
        "feedlot",
        "cattle"
    ],
    "wof:name":"Banks Cattle Company",
    "wof:placetype":"venue"
},
  "geometry": {"coordinates":[-96.857017,29.691233],"type":"Point"}
}