{
  "type": "Feature",
  "properties": {
    "iso:country":"US",
    "sg:address":"1806 E Broadway St",
    "sg:city":"Sweetwater",
    "sg:classifiers":[
        {
            "category":"Professional",
            "subcategory":"Business Services",
            "type":"Services"
        }
    ],
    "sg:phone":"+1 325 235 9639",
    "sg:postcode":"79556",
    "sg:province":"TX",
    "sg:tags":[
        "auctioneer"
    ],
    "wof:name":"Kevin Hutson Auctioneers",
    "wof:placetype":"venue"
},
  "geometry": {"coordinates":[-100.38890000000001,32.479357],"type":"Point"}
}