{
  "type": "Feature",
  "properties": {
    "iso:country":"US",
    "sg:address":"1225 Mesquite Rd",
    "sg:city":"Cedar Park",
    "sg:classifiers":[
        {
            "category":"Professional",
            "subcategory":"Business Services",
            "type":"Services"
        }
    ],
    "sg:phone":"+1 512 844 2495",
    "sg:postcode":"78613",
    "sg:province":"TX",
    "wof:name":"Richter Deven Agency",
    "wof:placetype":"venue"
},
  "geometry": {"coordinates":[-97.826882,30.472258],"type":"Point"}
}