{
  "type": "Feature",
  "properties": {
    "iso:country":"US",
    "sg:address":"7979 Inwood Rd",
    "sg:city":"Dallas",
    "sg:classifiers":[
        {
            "category":"Personal",
            "subcategory":"Beauty Salon",
            "type":"Services"
        }
    ],
    "sg:phone":"+1 214 352 4818",
    "sg:postcode":"75209",
    "sg:province":"TX",
    "wof:name":"Gene Salon",
    "wof:placetype":"venue"
},
  "geometry": {"coordinates":[-96.821251,32.859503],"type":"Point"}
}