{
  "type": "Feature",
  "properties": {
    "iso:country":"US",
    "sg:address":"616 FM 1960 W",
    "sg:city":"Houston",
    "sg:classifiers":[
        {
            "category":"Professional",
            "subcategory":"Employment Agencies",
            "type":"Services"
        }
    ],
    "sg:phone":"+1 281 587 9926",
    "sg:postcode":"77090",
    "sg:province":"TX",
    "sg:tags":[
        "temporary",
        "help"
    ],
    "wof:name":"Manpower",
    "wof:placetype":"venue"
},
  "geometry": {"coordinates":[-95.437939,30.018519],"type":"Point"}
}