{
  "type": "Feature",
  "properties": {
    "iso:country":"US",
    "sg:address":"7717 Red Robin Ln",
    "sg:city":"Houston",
    "sg:classifiers":[
        {
            "category":"Retail",
            "subcategory":"Auto Repair",
            "type":"Services"
        }
    ],
    "sg:phone":"+1 713 991 6001",
    "sg:postcode":"77075",
    "sg:province":"TX",
    "sg:tags":[
        "muffler",
        "exhaust",
        "system"
    ],
    "wof:name":"Gholamreza Mardani Muffler",
    "wof:placetype":"venue"
},
  "geometry": {"coordinates":[-95.28257600000001,29.618942],"type":"Point"}
}