{
  "type": "Feature",
  "properties": {
    "iso:country":"US",
    "sg:address":"2502 N Mission Cir",
    "sg:city":"Friendswood",
    "sg:classifiers":[
        {
            "category":"Organizations",
            "subcategory":"Labor Organization",
            "type":"Services"
        }
    ],
    "sg:phone":"+1 281 648 6359",
    "sg:postcode":"77546",
    "sg:province":"TX",
    "wof:name":"Vds Managment Lc",
    "wof:placetype":"venue"
},
  "geometry": {"coordinates":[-95.213302,29.481742],"type":"Point"}
}