{
  "type": "Feature",
  "properties": {
    "iso:country":"US",
    "sg:address":"2011 W 21st St",
    "sg:city":"Plainview",
    "sg:classifiers":[
        {
            "category":"Shopping",
            "subcategory":"Hobbies, Toys, & Games",
            "type":"Retail Goods"
        }
    ],
    "sg:phone":"+1 806 293 8118",
    "sg:postcode":"79072",
    "sg:province":"TX",
    "wof:name":"Hembree Framing & Crafts",
    "wof:placetype":"venue"
},
  "geometry": {"coordinates":[-101.728381,34.202461],"type":"Point"}
}