{
  "type": "Feature",
  "properties": {
    "iso:country":"US",
    "sg:address":"601 Sterling St",
    "sg:city":"Borger",
    "sg:classifiers":[
        {
            "category":"Retail",
            "subcategory":"Auto Repair",
            "type":"Services"
        }
    ],
    "sg:phone":"+1 806 274 9418",
    "sg:postcode":"79007",
    "sg:province":"TX",
    "sg:tags":[
        "body",
        "automobile",
        "painting"
    ],
    "wof:name":"A-1 Paint & Body Shop",
    "wof:placetype":"venue"
},
  "geometry": {"coordinates":[-101.39881699999999,35.673166],"type":"Point"}
}