{
  "type": "Feature",
  "properties": {
    "iso:country":"US",
    "sg:address":"1936 Hinton Dr",
    "sg:city":"Irving",
    "sg:classifiers":[
        {
            "category":"Education",
            "subcategory":"School",
            "type":"Public Place"
        }
    ],
    "sg:phone":"+1 972 871 2738",
    "sg:postcode":"75061",
    "sg:province":"TX",
    "sg:tags":[
        "high",
        "middle",
        "elementary"
    ],
    "wof:name":"Heritage Crystal Claim",
    "wof:placetype":"venue"
},
  "geometry": {"coordinates":[-96.91825300000001,32.825534],"type":"Point"}
}