{
  "type": "Feature",
  "properties": {
    "iso:country":"US",
    "sg:address":"1331 Exchange Dr",
    "sg:city":"Richardson",
    "sg:classifiers":[
        {
            "category":"Home & Garden",
            "subcategory":"Home Furnishings",
            "type":"Retail Goods"
        }
    ],
    "sg:phone":"+1 214 357 2680",
    "sg:postcode":"75081",
    "sg:province":"TX",
    "sg:tags":[
        "house",
        "decor"
    ],
    "sg:website":"http://www.aromatrading.com",
    "wof:name":"Aroma Trading, Inc",
    "wof:placetype":"venue"
},
  "geometry": {"coordinates":[-96.707606,32.961101],"type":"Point"}
}