{
  "type": "Feature",
  "properties": {
    "iso:country":"US",
    "sg:address":"1910 Cranford Dr",
    "sg:city":"Garland",
    "sg:classifiers":[
        {
            "category":"Real Estate",
            "subcategory":"Real Estate Operator",
            "type":"Services"
        }
    ],
    "sg:phone":"+1 972 271 7424",
    "sg:postcode":"75041",
    "sg:province":"TX",
    "sg:tags":[
        "apartment"
    ],
    "wof:name":"Little Brook Apartments",
    "wof:placetype":"venue"
},
  "geometry": {"coordinates":[-96.65952299999999,32.877445],"type":"Point"}
}