{
  "type": "Feature",
  "properties": {
    "iso:country":"US",
    "sg:address":"1012 Sue Dr",
    "sg:city":"Kemah",
    "sg:classifiers":[
        {
            "category":"Retail",
            "subcategory":"Repair Shop",
            "type":"Services"
        }
    ],
    "sg:phone":"+1 281 808 5951",
    "sg:postcode":"77565",
    "sg:province":"TX",
    "wof:name":"Apache Marine",
    "wof:placetype":"venue"
},
  "geometry": {"coordinates":[-95.028685,29.52786],"type":"Point"}
}