{
  "type": "Feature",
  "properties": {
    "iso:country":"US",
    "sg:address":"6000 Teague Rd",
    "sg:city":"Houston",
    "sg:classifiers":[
        {
            "category":"Government",
            "subcategory":"Police Station",
            "type":"Public Place"
        }
    ],
    "sg:phone":"+1 713 744 0900",
    "sg:postcode":"77041",
    "sg:province":"TX",
    "sg:tags":[
        "department"
    ],
    "wof:name":"Police Dept-Northwest Patrol",
    "wof:placetype":"venue"
},
  "geometry": {"coordinates":[-95.540145,29.855159],"type":"Point"}
}