{
  "type": "Feature",
  "properties": {
    "iso:country":"US",
    "sg:address":"150 Center St",
    "sg:city":"Center Point",
    "sg:classifiers":[
        {
            "category":"Wholesale",
            "subcategory":"Vending Machines",
            "type":"Manufacturing & Wholesale Goods"
        }
    ],
    "sg:phone":"+1 830 634 7513",
    "sg:postcode":"78063",
    "sg:province":"TX",
    "sg:tags":[
        "operator"
    ],
    "wof:name":"Kardells Vending Machines",
    "wof:placetype":"venue"
},
  "geometry": {"coordinates":[-98.932441,29.605467],"type":"Point"}
}