{
  "type": "Feature",
  "properties": {
    "iso:country":"US",
    "sg:address":"19469 Hwy 35",
    "sg:city":"Alvin",
    "sg:classifiers":[
        {
            "category":"Autos & Motor Vehicles",
            "subcategory":"Automobile Sales",
            "type":"Retail Goods"
        }
    ],
    "sg:phone":"+1 281 993 5725",
    "sg:postcode":"77511",
    "sg:province":"TX",
    "sg:tags":[
        "used"
    ],
    "wof:name":"35 Discount Auto Sales",
    "wof:placetype":"venue"
},
  "geometry": {"coordinates":[-95.246548,29.493842],"type":"Point"}
}