{
  "type": "Feature",
  "properties": {
    "iso:country":"US",
    "sg:address":"12067 Kleinmeadow Dr",
    "sg:city":"Houston",
    "sg:classifiers":[
        {
            "category":"Professional",
            "type":"Services"
        }
    ],
    "sg:phone":"+1 281 440 8834",
    "sg:postcode":"77066",
    "sg:province":"TX",
    "wof:name":"Moms Treasures Inc",
    "wof:placetype":"venue"
},
  "geometry": {"coordinates":[-95.495481,29.952545],"type":"Point"}
}