{
  "type": "Feature",
  "properties": {
    "iso:country":"US",
    "sg:address":"625 Parker Sq",
    "sg:city":"Flower Mound",
    "sg:classifiers":[
        {
            "category":"Personal",
            "type":"Services"
        }
    ],
    "sg:phone":"+1 972 899 9911",
    "sg:postcode":"75028",
    "sg:province":"TX",
    "wof:name":"Color Me Mine",
    "wof:placetype":"venue"
},
  "geometry": {"coordinates":[-97.05069399999999,33.039168],"type":"Point"}
}