{
  "type": "Feature",
  "properties": {
    "iso:country":"US",
    "sg:address":"6595 Westgate Dr",
    "sg:city":"Beaumont",
    "sg:classifiers":[
        {
            "category":"Professional",
            "subcategory":"Engineering",
            "type":"Services"
        }
    ],
    "sg:phone":"+1 409 866 4904",
    "sg:postcode":"77706",
    "sg:province":"TX",
    "sg:tags":[
        "engineer"
    ],
    "wof:name":"R D Bryie & Assoc",
    "wof:placetype":"venue"
},
  "geometry": {"coordinates":[-94.17184399999999,30.087501],"type":"Point"}
}