{
  "type": "Feature",
  "properties": {
    "iso:country":"US",
    "sg:address":"1403 E Campbell Rd",
    "sg:city":"Richardson",
    "sg:classifiers":[
        {
            "category":"Personal",
            "subcategory":"Beauty Salon",
            "type":"Services"
        }
    ],
    "sg:phone":"+1 972 690 3434",
    "sg:postcode":"75081",
    "sg:province":"TX",
    "wof:name":"Debbie Daniels",
    "wof:placetype":"venue"
},
  "geometry": {"coordinates":[-96.69982899999999,32.974962],"type":"Point"}
}