{
  "type": "Feature",
  "properties": {
    "iso:country":"US",
    "sg:address":"1589 Clarksville St",
    "sg:city":"Paris",
    "sg:classifiers":[
        {
            "category":"Food & Beverages",
            "subcategory":"Bakery",
            "type":"Retail Goods"
        }
    ],
    "sg:phone":"+1 903 785 3415",
    "sg:postcode":"75460",
    "sg:province":"TX",
    "sg:tags":[
        "product",
        "eating",
        "doughnut",
        "mfg"
    ],
    "wof:name":"Southern Maid Donut Shop",
    "wof:placetype":"venue"
},
  "geometry": {"coordinates":[-95.53970200000001,33.657752],"type":"Point"}
}