{
  "type": "Feature",
  "properties": {
    "iso:country":"US",
    "sg:address":"4601 Whitehall Ct",
    "sg:city":"Mc Kinney",
    "sg:classifiers":[
        {
            "category":"Building & Trades",
            "subcategory":"Construction",
            "type":"Services"
        }
    ],
    "sg:phone":"+1 214 726 9100",
    "sg:postcode":"75070",
    "sg:province":"TX",
    "sg:tags":[
        "home",
        "builder"
    ],
    "wof:name":"Avery Edwards Custom Homes",
    "wof:placetype":"venue"
},
  "geometry": {"coordinates":[-96.67360600000001,33.15828],"type":"Point"}
}