{
  "type": "Feature",
  "properties": {
    "iso:country":"US",
    "sg:address":"17803 Birch Forest Ln",
    "sg:city":"Spring",
    "sg:classifiers":[
        {
            "category":"Professional",
            "subcategory":"Computer Services",
            "type":"Services"
        }
    ],
    "sg:phone":"+1 281 615 7459",
    "sg:postcode":"77379",
    "sg:province":"TX",
    "sg:tags":[
        "web",
        "design"
    ],
    "wof:name":"Tachycardia Solutions",
    "wof:placetype":"venue"
},
  "geometry": {"coordinates":[-95.547163,30.025527],"type":"Point"}
}