{
  "type": "Feature",
  "properties": {
    "iso:country":"US",
    "sg:address":"4500 Ratliff Ln",
    "sg:city":"Addison",
    "sg:classifiers":[
        {
            "category":"Building & Trades",
            "subcategory":"Construction",
            "type":"Services"
        }
    ],
    "sg:phone":"+1 972 713 7819",
    "sg:postcode":"75001",
    "sg:province":"TX",
    "sg:tags":[
        "contractor"
    ],
    "wof:name":"Moline Construction Mng",
    "wof:placetype":"venue"
},
  "geometry": {"coordinates":[-96.832184,32.970462],"type":"Point"}
}