{
  "type": "Feature",
  "properties": {
    "iso:country":"US",
    "sg:address":"317 Bell Plains Rd",
    "sg:city":"Tuscola",
    "sg:classifiers":[
        {
            "category":"Farming",
            "subcategory":"Livestock Farm",
            "type":"Manufacturing & Wholesale Goods"
        }
    ],
    "sg:phone":"+1 325 572 3582",
    "sg:postcode":"79562",
    "sg:province":"TX",
    "sg:tags":[
        "beef",
        "feedlot",
        "cattle"
    ],
    "wof:name":"H & H Ranch",
    "wof:placetype":"venue"
},
  "geometry": {"coordinates":[-99.766267,32.308155],"type":"Point"}
}