{
  "type": "Feature",
  "properties": {
    "iso:country":"US",
    "sg:address":"10745 Royal Forest Dr",
    "sg:city":"Conroe",
    "sg:classifiers":[
        {
            "category":"Building & Trades",
            "subcategory":"Landscaping Services",
            "type":"Services"
        }
    ],
    "sg:phone":"+1 936 890 9066",
    "sg:postcode":"77303",
    "sg:province":"TX",
    "wof:name":"Rainbow Lawn",
    "wof:placetype":"venue"
},
  "geometry": {"coordinates":[-95.40817,30.412755],"type":"Point"}
}