{
  "type": "Feature",
  "properties": {
    "iso:country":"US",
    "sg:address":"13915 Fondren Rd",
    "sg:city":"Missouri City",
    "sg:classifiers":[
        {
            "category":"Restaurant",
            "type":"Food & Drink"
        }
    ],
    "sg:menulink":"http://www.allmenus.com/tx/stafford-missouri-city/177664-jack-in-the-box/menu/",
    "sg:phone":"+1 281 438 1388",
    "sg:postcode":"77489",
    "sg:province":"TX",
    "sg:tags":[
        "burger",
        "american"
    ],
    "wof:name":"Jack in the Box",
    "wof:placetype":"venue"
},
  "geometry": {"coordinates":[-95.508059,29.619425],"type":"Point"}
}