{
  "type": "Feature",
  "properties": {
    "iso:country":"US",
    "sg:address":"13776 N US Hwy 183",
    "sg:city":"Austin",
    "sg:classifiers":[
        {
            "category":"Shopping",
            "subcategory":"Gifts & Souvenirs",
            "type":"Retail Goods"
        }
    ],
    "sg:phone":"+1 512 785 6294",
    "sg:postcode":"78750",
    "sg:province":"TX",
    "wof:name":"Fairy Collector",
    "wof:placetype":"venue"
},
  "geometry": {"coordinates":[-97.795748,30.464756],"type":"Point"}
}