{
  "type": "Feature",
  "properties": {
    "iso:country":"US",
    "sg:address":"5105 Junius St",
    "sg:city":"Dallas",
    "sg:classifiers":[
        {
            "category":"Mining & Drilling",
            "type":"Manufacturing & Wholesale Goods"
        }
    ],
    "sg:phone":"+1 214 887 0001",
    "sg:postcode":"75214",
    "sg:province":"TX",
    "sg:tags":[
        "development",
        "gas",
        "oil",
        "exploration"
    ],
    "wof:name":"Celestine Energy Inc",
    "wof:placetype":"venue"
},
  "geometry": {"coordinates":[-96.765747,32.801351],"type":"Point"}
}