{
  "type": "Feature",
  "properties": {
    "iso:country":"US",
    "sg:address":"19623 Vernier Woods Ln",
    "sg:city":"Spring",
    "sg:classifiers":[
        {
            "category":"Shopping",
            "subcategory":"Crafts & Fabrics",
            "type":"Retail Goods"
        }
    ],
    "sg:phone":"+1 281 370 2363",
    "sg:postcode":"77379",
    "sg:province":"TX",
    "sg:tags":[
        "sewing"
    ],
    "wof:name":"Merry Sew n Sew",
    "wof:placetype":"venue"
},
  "geometry": {"coordinates":[-95.503232,30.051214],"type":"Point"}
}