{
  "type": "Feature",
  "properties": {
    "iso:country":"US",
    "sg:address":"909 Pinafore Ln",
    "sg:city":"Houston",
    "sg:classifiers":[
        {
            "category":"Professional",
            "subcategory":"Business Services",
            "type":"Services"
        }
    ],
    "sg:phone":"+1 281 442 6500",
    "sg:postcode":"77039",
    "sg:province":"TX",
    "sg:tags":[
        "embroidery"
    ],
    "wof:name":"Extreme Embroidery",
    "wof:placetype":"venue"
},
  "geometry": {"coordinates":[-95.372153,29.922217],"type":"Point"}
}