{
  "type": "Feature",
  "properties": {
    "iso:country":"US",
    "sg:address":"3824 Walnut Dr",
    "sg:city":"Bedford",
    "sg:classifiers":[
        {
            "category":"Professional",
            "type":"Services"
        }
    ],
    "sg:phone":"+1 817 684 0435",
    "sg:postcode":"76021",
    "sg:province":"TX",
    "sg:tags":[
        "establishment"
    ],
    "wof:name":"Walnut House",
    "wof:placetype":"venue"
},
  "geometry": {"coordinates":[-97.10727199999999,32.847481],"type":"Point"}
}