{
  "type": "Feature",
  "properties": {
    "iso:country":"US",
    "sg:address":"6128 S Loop Fwy",
    "sg:city":"Houston",
    "sg:classifiers":[
        {
            "category":"Wholesale",
            "subcategory":"Machinery & Supplies",
            "type":"Manufacturing & Wholesale Goods"
        }
    ],
    "sg:phone":"+1 713 644 8889",
    "sg:postcode":"77087",
    "sg:province":"TX",
    "sg:tags":[
        "equipment",
        "parts",
        "tractor"
    ],
    "wof:name":"Letts Industries Inc",
    "wof:placetype":"venue"
},
  "geometry": {"coordinates":[-95.321268,29.693413],"type":"Point"}
}