{
  "type": "Feature",
  "properties": {
    "iso:country":"US",
    "sg:address":"14418 Industry Ave",
    "sg:city":"Laredo",
    "sg:classifiers":[
        {
            "category":"Professional",
            "subcategory":"Business Services",
            "type":"Services"
        }
    ],
    "sg:phone":"+1 956 796 9211",
    "sg:postcode":"78045",
    "sg:province":"TX",
    "wof:name":"Sla Enterprises Inc",
    "wof:placetype":"venue"
},
  "geometry": {"coordinates":[-99.53464700000001,27.625948],"type":"Point"}
}