{
  "type": "Feature",
  "properties": {
    "iso:country":"US",
    "sg:address":"413 S Main St",
    "sg:city":"Hallettsville",
    "sg:classifiers":[
        {
            "category":"Banks & Credit Unions",
            "subcategory":"Investment Brokerage",
            "type":"Services"
        }
    ],
    "sg:phone":"+1 361 798 1682",
    "sg:postcode":"77964",
    "sg:province":"TX",
    "sg:tags":[
        "security"
    ],
    "wof:name":"Crown Gas LLC",
    "wof:placetype":"venue"
},
  "geometry": {"coordinates":[-96.942176,29.440053],"type":"Point"}
}