{
  "type": "Feature",
  "properties": {
    "iso:country":"US",
    "sg:address":"1319 Bellaire Dr",
    "sg:city":"Grapevine",
    "sg:classifiers":[
        {
            "category":"Shopping",
            "subcategory":"Hobbies, Toys, & Games",
            "type":"Retail Goods"
        }
    ],
    "sg:phone":"+1 817 488 8023",
    "sg:postcode":"76051",
    "sg:province":"TX",
    "wof:name":"Unique Grafts",
    "wof:placetype":"venue"
},
  "geometry": {"coordinates":[-97.081746,32.926206],"type":"Point"}
}