{
  "type": "Feature",
  "properties": {
    "iso:country":"US",
    "sg:address":"4901 S Washington St",
    "sg:city":"Amarillo",
    "sg:classifiers":[
        {
            "category":"Organizations",
            "subcategory":"Community Association",
            "type":"Services"
        }
    ],
    "sg:phone":"+1 806 376 1959",
    "sg:postcode":"79110",
    "sg:province":"TX",
    "sg:tags":[
        "club"
    ],
    "wof:name":"Sparks",
    "wof:placetype":"venue"
},
  "geometry": {"coordinates":[-101.848382,35.157675],"type":"Point"}
}