{
  "type": "Feature",
  "properties": {
    "iso:country":"US",
    "sg:address":"10203 Oak Hollow Dr",
    "sg:city":"Austin",
    "sg:classifiers":[
        {
            "category":"Building & Trades",
            "subcategory":"Construction",
            "type":"Services"
        },
        {
            "category":"Home & Garden",
            "subcategory":"Furniture",
            "type":"Retail Goods"
        }
    ],
    "sg:phone":"+1 512 836 5275",
    "sg:postcode":"78758",
    "sg:province":"TX",
    "sg:tags":[
        "product",
        "designer",
        "mfg",
        "builder",
        "custom",
        "wood",
        "contractor"
    ],
    "sg:website":"http://www.masterpiecefurniture.com",
    "wof:name":"Masterpiece Furniture Creations",
    "wof:placetype":"venue"
},
  "geometry": {"coordinates":[-97.707323,30.378037],"type":"Point"}
}