{
  "type": "Feature",
  "properties": {
    "iso:country":"US",
    "sg:address":"3200 Bilglade Rd",
    "sg:city":"Fort Worth",
    "sg:classifiers":[
        {
            "category":"Organizations",
            "subcategory":"Religious Organization",
            "type":"Services"
        }
    ],
    "sg:phone":"+1 817 926 5281",
    "sg:postcode":"76133",
    "sg:province":"TX",
    "wof:name":"South Hills Christian Church",
    "wof:placetype":"venue"
},
  "geometry": {"coordinates":[-97.361458,32.677288],"type":"Point"}
}