{
  "type": "Feature",
  "properties": {
    "iso:country":"US",
    "sg:address":"1004 Candlewood Dr",
    "sg:city":"League City",
    "sg:classifiers":[
        {
            "category":"Professional",
            "type":"Services"
        }
    ],
    "sg:phone":"+1 281 316 2594",
    "sg:postcode":"77573",
    "sg:province":"TX",
    "wof:name":"Findinstock Co",
    "wof:placetype":"venue"
},
  "geometry": {"coordinates":[-95.14655,29.487213],"type":"Point"}
}