{
  "type": "Feature",
  "properties": {
    "iso:country":"US",
    "sg:address":"9742 US Hwy 79",
    "sg:city":"Bethany",
    "sg:classifiers":[
        {
            "category":"Organizations",
            "subcategory":"Religious Organization",
            "type":"Services"
        }
    ],
    "sg:phone":"+1 318 938 5221",
    "sg:postcode":"71007",
    "sg:province":"TX",
    "sg:tags":[
        "church"
    ],
    "wof:name":"Cornerstone Assembly-God Chr",
    "wof:placetype":"venue"
},
  "geometry": {"coordinates":[-94.029754,32.37845],"type":"Point"}
}