{
  "type": "Feature",
  "properties": {
    "iso:country":"US",
    "sg:address":"77 Ferry Dr",
    "sg:city":"Bridge City",
    "sg:classifiers":[
        {
            "category":"Shopping",
            "subcategory":"Bicycles & Sporting Goods",
            "type":"Retail Goods"
        }
    ],
    "sg:phone":"+1 409 735 5808",
    "sg:postcode":"77611",
    "sg:province":"TX",
    "sg:tags":[
        "sport"
    ],
    "wof:name":"Precision Archery",
    "wof:placetype":"venue"
},
  "geometry": {"coordinates":[-93.845889,30.022979],"type":"Point"}
}