{
  "type": "Feature",
  "properties": {
    "iso:country":"US",
    "sg:address":"1205 Hummingbird Cir",
    "sg:city":"Longview",
    "sg:classifiers":[
        {
            "category":"Manufacturing",
            "subcategory":"Printing",
            "type":"Manufacturing & Wholesale Goods"
        }
    ],
    "sg:phone":"+1 903 234 0636",
    "sg:postcode":"75601",
    "sg:province":"TX",
    "sg:tags":[
        "printer"
    ],
    "wof:name":"S & S Printing & Embroidery",
    "wof:placetype":"venue"
},
  "geometry": {"coordinates":[-94.704913,32.515049],"type":"Point"}
}