{
  "type": "Feature",
  "properties": {
    "iso:country":"US",
    "sg:address":"2203 Allen St",
    "sg:city":"Dallas",
    "sg:classifiers":[
        {
            "category":"Professional",
            "subcategory":"Business Services",
            "type":"Services"
        }
    ],
    "sg:phone":"+1 214 954 1079",
    "sg:postcode":"75204",
    "sg:province":"TX",
    "sg:tags":[
        "interior",
        "consultant",
        "design",
        "decorator"
    ],
    "wof:name":"Allen Street Interior Designs",
    "wof:placetype":"venue"
},
  "geometry": {"coordinates":[-96.797189,32.796539],"type":"Point"}
}