{
  "type": "Feature",
  "properties": {
    "iso:country":"US",
    "sg:address":"1625 Everman Pkwy",
    "sg:city":"Fort Worth",
    "sg:classifiers":[
        {
            "category":"Bars & Pubs",
            "type":"Food & Drink"
        }
    ],
    "sg:phone":"+1 817 551 6234",
    "sg:postcode":"76140",
    "sg:province":"TX",
    "sg:tags":[
        "drinking"
    ],
    "wof:name":"Gold Putter Lounge Inc",
    "wof:placetype":"venue"
},
  "geometry": {"coordinates":[-97.300085,32.626547],"type":"Point"}
}