{
  "type": "Feature",
  "properties": {
    "iso:country":"US",
    "sg:address":"3857 SW Loop 820",
    "sg:city":"Fort Worth",
    "sg:classifiers":[
        {
            "category":"Shopping",
            "subcategory":"Shoes",
            "type":"Retail Goods"
        }
    ],
    "sg:phone":"+1 817 292 0305",
    "sg:postcode":"76133",
    "sg:province":"TX",
    "wof:name":"Cooper's Shoe Store",
    "wof:placetype":"venue"
},
  "geometry": {"coordinates":[-97.376935,32.672655],"type":"Point"}
}