{
  "type": "Feature",
  "properties": {
    "iso:country":"US",
    "sg:address":"203 E Broadway St",
    "sg:city":"Jefferson",
    "sg:classifiers":[
        {
            "category":"Restaurant",
            "type":"Food & Drink"
        }
    ],
    "sg:phone":"+1 903 665 8415",
    "sg:postcode":"75657",
    "sg:province":"TX",
    "sg:tags":[
        "drinking",
        "eating",
        "operation"
    ],
    "wof:name":"Stillwater Inn",
    "wof:placetype":"venue"
},
  "geometry": {"coordinates":[-94.353797,32.761452],"type":"Point"}
}