{
  "type": "Feature",
  "properties": {
    "iso:country":"US",
    "sg:address":"522 Channel View Dr",
    "sg:city":"Port Aransas",
    "sg:classifiers":[
        {
            "category":"Manufacturing",
            "subcategory":"Printing",
            "type":"Manufacturing & Wholesale Goods"
        }
    ],
    "sg:phone":"+1 361 749 5855",
    "sg:postcode":"78373",
    "sg:province":"TX",
    "sg:tags":[
        "publisher"
    ],
    "wof:name":"Otten Publishing",
    "wof:placetype":"venue"
},
  "geometry": {"coordinates":[-97.05604700000001,27.838598],"type":"Point"}
}