{
  "type": "Feature",
  "properties": {
    "iso:country":"US",
    "sg:address":"6910 State Hwy 78",
    "sg:city":"Nevada",
    "sg:classifiers":[
        {
            "category":"Professional",
            "type":"Services"
        }
    ],
    "sg:phone":"+1 972 853 3272",
    "sg:postcode":"75173",
    "sg:province":"TX",
    "sg:tags":[
        "establishment"
    ],
    "wof:name":"Granny's L'Il Wonders",
    "wof:placetype":"venue"
},
  "geometry": {"coordinates":[-96.424234,33.066027],"type":"Point"}
}