{
  "type": "Feature",
  "properties": {
    "iso:country":"US",
    "sg:address":"116 E Front St",
    "sg:city":"Tyler",
    "sg:classifiers":[
        {
            "category":"Restaurant",
            "type":"Food & Drink"
        }
    ],
    "sg:phone":"+1 903 592 1630",
    "sg:postcode":"75702",
    "sg:province":"TX",
    "sg:tags":[
        "eating"
    ],
    "wof:name":"Lesommet LP",
    "wof:placetype":"venue"
},
  "geometry": {"coordinates":[-95.299683,32.346746],"type":"Point"}
}