{
  "type": "Feature",
  "properties": {
    "iso:country":"US",
    "sg:address":"2014 Lou Ellen Ln",
    "sg:city":"Houston",
    "sg:classifiers":[
        {
            "category":"Shopping",
            "subcategory":"Books",
            "type":"Retail Goods"
        }
    ],
    "sg:phone":"+1 713 688 2244",
    "sg:postcode":"77018",
    "sg:province":"TX",
    "sg:tags":[
        "bookstore"
    ],
    "sg:website":"www.richardsonsbooks.com",
    "wof:name":"Richardson's Books",
    "wof:placetype":"venue"
},
  "geometry": {"coordinates":[-95.435097,29.818501],"type":"Point"}
}