{
  "type": "Feature",
  "properties": {
    "iso:country":"US",
    "sg:address":"6601 Blanco Rd",
    "sg:city":"San Antonio",
    "sg:classifiers":[
        {
            "category":"Health Services",
            "subcategory":"Doctor",
            "type":"Services"
        }
    ],
    "sg:phone":"+1 210 979 8232",
    "sg:postcode":"78216",
    "sg:province":"TX",
    "sg:tags":[
        "dentist"
    ],
    "wof:name":"Ortho Video Diagnostic",
    "wof:placetype":"venue"
},
  "geometry": {"coordinates":[-98.50687600000001,29.515814],"type":"Point"}
}