{
  "type": "Feature",
  "properties": {
    "iso:country":"US",
    "sg:address":"1385 Co Rd 3440",
    "sg:city":"Hawkins",
    "sg:classifiers":[
        {
            "category":"Restaurant",
            "type":"Food & Drink"
        }
    ],
    "sg:phone":"+1 903 769 9580",
    "sg:postcode":"75765",
    "sg:province":"TX",
    "sg:tags":[
        "eating"
    ],
    "wof:name":"Captain Mikes Shipwreck Rest",
    "wof:placetype":"venue"
},
  "geometry": {"coordinates":[-95.25522599999999,32.615282],"type":"Point"}
}