{
  "type": "Feature",
  "properties": {
    "iso:country":"US",
    "sg:address":"132 Sayles Blvd",
    "sg:city":"Abilene",
    "sg:classifiers":[
        {
            "category":"Insurance",
            "subcategory":"Insurance Agent",
            "type":"Services"
        }
    ],
    "sg:phone":"+1 325 672 7741",
    "sg:postcode":"79605",
    "sg:province":"TX",
    "wof:name":"Voyles Beebe Eason Insurnace",
    "wof:placetype":"venue"
},
  "geometry": {"coordinates":[-99.748167,32.449083],"type":"Point"}
}