{
  "type": "Feature",
  "properties": {
    "iso:country":"US",
    "sg:address":"13418 Linden St",
    "sg:city":"Sugar Land",
    "sg:classifiers":[
        {
            "category":"Professional",
            "subcategory":"Business Services",
            "type":"Services"
        }
    ],
    "sg:phone":"+1 281 313 2010",
    "sg:postcode":"77478",
    "sg:province":"TX",
    "wof:name":"Southtex Solutions",
    "wof:placetype":"venue"
},
  "geometry": {"coordinates":[-95.6199,29.648503],"type":"Point"}
}