{
  "type": "Feature",
  "properties": {
    "iso:country":"US",
    "sg:address":"300 W Little York Rd",
    "sg:city":"Houston",
    "sg:classifiers":[
        {
            "category":"Building & Trades",
            "subcategory":"Equipment Rental",
            "type":"Services"
        }
    ],
    "sg:phone":"+1 713 699 8990",
    "sg:postcode":"77076",
    "sg:province":"TX",
    "wof:name":"Rent-A-Center",
    "wof:placetype":"venue"
},
  "geometry": {"coordinates":[-95.403599,29.869924],"type":"Point"}
}