{
  "type": "Feature",
  "properties": {
    "iso:country":"US",
    "sg:address":"12200 Ashley Circle Dr E",
    "sg:city":"Houston",
    "sg:classifiers":[
        {
            "category":"Organizations",
            "subcategory":"Professional Association",
            "type":"Services"
        },
        {
            "category":"Organizations",
            "subcategory":"Community Association",
            "type":"Services"
        }
    ],
    "sg:phone":"+1 713 779 6705",
    "sg:postcode":"77071",
    "sg:province":"TX",
    "wof:name":"Fondren Lakes Home Owners Assn",
    "wof:placetype":"venue"
},
  "geometry": {"coordinates":[-95.51965,29.644429],"type":"Point"}
}