{
  "type": "Feature",
  "properties": {
    "iso:country":"US",
    "sg:address":"8200 Sweetwater Ln",
    "sg:city":"Houston",
    "sg:classifiers":[
        {
            "category":"Freight",
            "type":"Transportation"
        }
    ],
    "sg:phone":"+1 281 261 5582",
    "sg:postcode":"77037",
    "sg:province":"TX",
    "sg:tags":[
        "operator",
        "local",
        "trucking"
    ],
    "wof:name":"United Parcel Service Cus",
    "wof:placetype":"venue"
},
  "geometry": {"coordinates":[-95.408444,29.882762],"type":"Point"}
}