{
  "type": "Feature",
  "properties": {
    "iso:country":"US",
    "sg:address":"2806 N Navarro St",
    "sg:city":"Victoria",
    "sg:classifiers":[
        {
            "category":"Restaurant",
            "type":"Food & Drink"
        }
    ],
    "sg:phone":"+1 361 578 2233",
    "sg:postcode":"77901",
    "sg:province":"TX",
    "wof:name":"Good To Last Bite",
    "wof:placetype":"venue"
},
  "geometry": {"coordinates":[-97.00052100000001,28.820553],"type":"Point"}
}