{
  "type": "Feature",
  "properties": {
    "iso:country":"US",
    "sg:address":"304 W 6th St",
    "sg:city":"Crane",
    "sg:classifiers":[
        {
            "category":"Real Estate",
            "subcategory":"Real Estate Services",
            "type":"Services"
        }
    ],
    "sg:phone":"+1 432 558 3112",
    "sg:postcode":"79731",
    "sg:province":"TX",
    "wof:name":"Crane County Abstract",
    "wof:placetype":"venue"
},
  "geometry": {"coordinates":[-102.352617,31.396877],"type":"Point"}
}