{
  "type": "Feature",
  "properties": {
    "iso:country":"US",
    "sg:address":"1308 S Hampton Rd",
    "sg:city":"Desoto",
    "sg:classifiers":[
        {
            "category":"Home & Garden",
            "subcategory":"Carpets & Floor Coverings",
            "type":"Retail Goods"
        }
    ],
    "sg:phone":"+1 972 223 2540",
    "sg:postcode":"75115",
    "sg:province":"TX",
    "sg:tags":[
        "flooring"
    ],
    "sg:website":"www.unitedlynncon.com",
    "wof:name":"United Lynn-Con Corp",
    "wof:placetype":"venue"
},
  "geometry": {"coordinates":[-96.85700199999999,32.566898],"type":"Point"}
}