{
  "type": "Feature",
  "properties": {
    "iso:country":"US",
    "sg:address":"1500 University Dr E",
    "sg:city":"College Station",
    "sg:classifiers":[
        {
            "category":"Professional",
            "type":"Services"
        }
    ],
    "sg:phone":"+1 979 846 2998",
    "sg:postcode":"77840",
    "sg:province":"TX",
    "sg:tags":[
        "establishment"
    ],
    "wof:name":"Associated Attorneys Title",
    "wof:placetype":"venue"
},
  "geometry": {"coordinates":[-96.318133,30.636998],"type":"Point"}
}