{
  "type": "Feature",
  "properties": {
    "iso:country":"US",
    "sg:address":"1319 Musser St",
    "sg:city":"Laredo",
    "sg:classifiers":[
        {
            "category":"Insurance",
            "subcategory":"Insurance Agent",
            "type":"Services"
        }
    ],
    "sg:phone":"+1 956 724 4767",
    "sg:postcode":"78040",
    "sg:province":"TX",
    "wof:name":"International Insurance Adm",
    "wof:placetype":"venue"
},
  "geometry": {"coordinates":[-99.48257099999999,27.514759],"type":"Point"}
}