{
  "type": "Feature",
  "properties": {
    "iso:country":"US",
    "sg:address":"2015 Ute Trl",
    "sg:city":"Dalhart",
    "sg:classifiers":[
        {
            "category":"Banks & Credit Unions",
            "subcategory":"Investment Brokerage",
            "type":"Services"
        }
    ],
    "sg:phone":"+1 806 249 6611",
    "sg:postcode":"79022",
    "sg:province":"TX",
    "wof:name":"Rigg Family",
    "wof:placetype":"venue"
},
  "geometry": {"coordinates":[-102.509686,36.043412],"type":"Point"}
}