{
  "type": "Feature",
  "properties": {
    "iso:country":"US",
    "sg:address":"9896 Bellaire Blvd Suite A",
    "sg:city":"Houston",
    "sg:classifiers":[
        {
            "category":"Restaurant",
            "type":"Food & Drink"
        }
    ],
    "sg:phone":"+1 713 773 1670",
    "sg:postcode":"77036",
    "sg:province":"TX",
    "sg:tags":[
        "chinese"
    ],
    "wof:name":"Chinese Sichaun",
    "wof:placetype":"venue"
},
  "geometry": {"coordinates":[-95.55494299999999,29.706927],"type":"Point"}
}