{
  "type": "Feature",
  "properties": {
    "iso:country":"US",
    "sg:address":"1745 Glencairn Ln",
    "sg:city":"Lewisville",
    "sg:classifiers":[
        {
            "category":"Professional",
            "subcategory":"Management & Consulting",
            "type":"Services"
        }
    ],
    "sg:phone":"+1 972 420 6913",
    "sg:postcode":"75067",
    "sg:province":"TX",
    "sg:tags":[
        "consultant",
        "lighting",
        "business"
    ],
    "wof:name":"Monte Mc Coy",
    "wof:placetype":"venue"
},
  "geometry": {"coordinates":[-97.041584,33.044693],"type":"Point"}
}