{
  "type": "Feature",
  "properties": {
    "iso:country":"US",
    "sg:address":"1422 Ave C",
    "sg:city":"Graham",
    "sg:classifiers":[
        {
            "category":"Recreation",
            "type":"Entertainment"
        }
    ],
    "sg:phone":"+1 940 549 1754",
    "sg:postcode":"76450",
    "sg:province":"TX",
    "sg:tags":[
        "sporting"
    ],
    "wof:name":"Brazos Valley Scuba",
    "wof:placetype":"venue"
},
  "geometry": {"coordinates":[-98.570808,33.115173],"type":"Point"}
}