{
  "type": "Feature",
  "properties": {
    "iso:country":"US",
    "sg:address":"701 C C Woodson Rd",
    "sg:city":"Brownwood",
    "sg:classifiers":[
        {
            "category":"Government",
            "subcategory":"Office",
            "type":"Public Place"
        }
    ],
    "sg:phone":"+1 325 646 0593",
    "sg:postcode":"76802",
    "sg:province":"TX",
    "wof:name":"Pecan Field Station",
    "wof:placetype":"venue"
},
  "geometry": {"coordinates":[-98.970232,31.729511],"type":"Point"}
}