{
  "type": "Feature",
  "properties": {
    "iso:country":"US",
    "sg:address":"102 S Main St",
    "sg:city":"Grapevine",
    "sg:classifiers":[
        {
            "category":"Food & Beverages",
            "subcategory":"Bakery",
            "type":"Retail Goods"
        }
    ],
    "sg:phone":"+1 817 421 1257",
    "sg:postcode":"76051",
    "sg:province":"TX",
    "sg:tags":[
        "doughnut"
    ],
    "wof:name":"Kountry Donuts",
    "wof:placetype":"venue"
},
  "geometry": {"coordinates":[-97.078428,32.939851],"type":"Point"}
}