{
  "type": "Feature",
  "properties": {
    "iso:country":"US",
    "sg:address":"2103 McClendon St",
    "sg:city":"Houston",
    "sg:classifiers":[
        {
            "category":"Home & Garden",
            "subcategory":"Home Furnishings",
            "type":"Retail Goods"
        }
    ],
    "sg:phone":"+1 713 668 7720",
    "sg:postcode":"77030",
    "sg:province":"TX",
    "wof:name":"Telina Armstrong Designs",
    "wof:placetype":"venue"
},
  "geometry": {"coordinates":[-95.41000699999999,29.708516],"type":"Point"}
}