{
  "type": "Feature",
  "properties": {
    "iso:country":"US",
    "sg:address":"2718 Band Rd",
    "sg:city":"Rosenberg",
    "sg:classifiers":[
        {
            "category":"Building & Trades",
            "subcategory":"Landscaping Services",
            "type":"Services"
        }
    ],
    "sg:phone":"+1 281 232 2524",
    "sg:postcode":"77471",
    "sg:province":"TX",
    "wof:name":"Total Lawn Care",
    "wof:placetype":"venue"
},
  "geometry": {"coordinates":[-95.82191,29.503912],"type":"Point"}
}