{
  "type": "Feature",
  "properties": {
    "iso:country":"US",
    "sg:address":"5726 N Dixie Blvd",
    "sg:city":"Odessa",
    "sg:classifiers":[
        {
            "category":"Shopping",
            "subcategory":"Jewelry",
            "type":"Retail Goods"
        },
        {
            "category":"Manufacturing",
            "subcategory":"Jewelry",
            "type":"Manufacturing & Wholesale Goods"
        },
        {
            "category":"Retail",
            "subcategory":"Repair Shop",
            "type":"Services"
        }
    ],
    "sg:phone":"+1 432 368 5702",
    "sg:postcode":"79762",
    "sg:province":"TX",
    "sg:tags":[
        "repairing",
        "stone",
        "designer",
        "clock",
        "jeweler",
        "precious",
        "semi-precious"
    ],
    "wof:name":"Kerr's Jewelry",
    "wof:placetype":"venue"
},
  "geometry": {"coordinates":[-102.37968100000001,31.900301],"type":"Point"}
}