{
  "type": "Feature",
  "properties": {
    "iso:country":"US",
    "sg:address":"16204 Loch Katrine Ln",
    "sg:city":"Houston",
    "sg:classifiers":[
        {
            "category":"Retail",
            "subcategory":"Laundry & Dry Cleaning",
            "type":"Services"
        }
    ],
    "sg:phone":"+1 281 463 9830",
    "sg:postcode":"77084",
    "sg:province":"TX",
    "sg:tags":[
        "drycleaning",
        "plant",
        "power"
    ],
    "wof:name":"One Hour S & H Cleaners",
    "wof:placetype":"venue"
},
  "geometry": {"coordinates":[-95.645782,29.84606],"type":"Point"}
}