{
  "type": "Feature",
  "properties": {
    "iso:country":"US",
    "sg:address":"3717 S Broadway Ave",
    "sg:city":"Tyler",
    "sg:classifiers":[
        {
            "category":"Shopping",
            "subcategory":"Used Merchandise",
            "type":"Retail Goods"
        }
    ],
    "sg:phone":"+1 903 939 8979",
    "sg:postcode":"75701",
    "sg:province":"TX",
    "wof:name":"Rose Second Hand",
    "wof:placetype":"venue"
},
  "geometry": {"coordinates":[-95.300737,32.307768],"type":"Point"}
}