{
  "type": "Feature",
  "properties": {
    "iso:country":"US",
    "sg:address":"6518 Co Rd 396",
    "sg:city":"Alvin",
    "sg:classifiers":[
        {
            "category":"Farming",
            "subcategory":"Nursery",
            "type":"Manufacturing & Wholesale Goods"
        },
        {
            "category":"Building & Trades",
            "subcategory":"Landscaping Services",
            "type":"Services"
        }
    ],
    "sg:phone":"+1 281 585 6639",
    "sg:postcode":"77511",
    "sg:province":"TX",
    "sg:tags":[
        "ornamental",
        "landscape",
        "contractor"
    ],
    "wof:name":"K & K Grass Farms",
    "wof:placetype":"venue"
},
  "geometry": {"coordinates":[-95.204567,29.361886],"type":"Point"}
}