{
  "type": "Feature",
  "properties": {
    "iso:country":"US",
    "sg:address":"353 Woodacre Cir",
    "sg:city":"Dallas",
    "sg:classifiers":[
        {
            "category":"Freight",
            "type":"Transportation"
        }
    ],
    "sg:phone":"+1 214 376 5548",
    "sg:postcode":"75241",
    "sg:province":"TX",
    "sg:tags":[
        "distance",
        "long",
        "trucking"
    ],
    "wof:name":"Woodberry Transportation",
    "wof:placetype":"venue"
},
  "geometry": {"coordinates":[-96.820128,32.682821],"type":"Point"}
}