{
  "type": "Feature",
  "properties": {
    "iso:country":"US",
    "sg:address":"3003 Blake St",
    "sg:city":"Corinth",
    "sg:classifiers":[
        {
            "category":"Building & Trades",
            "subcategory":"Construction",
            "type":"Services"
        }
    ],
    "sg:phone":"+1 940 498 1508",
    "sg:postcode":"76210",
    "sg:province":"TX",
    "sg:tags":[
        "wallcoverings-installation",
        "wallpaper",
        "painting",
        "contractor"
    ],
    "wof:name":"Todds Albert Painting Co",
    "wof:placetype":"venue"
},
  "geometry": {"coordinates":[-97.06285,33.140158],"type":"Point"}
}