{
  "type": "Feature",
  "properties": {
    "iso:country":"US",
    "sg:address":"3126 Franklin Ave",
    "sg:city":"Waco",
    "sg:classifiers":[
        {
            "category":"Home & Garden",
            "subcategory":"Carpets & Floor Coverings",
            "type":"Retail Goods"
        }
    ],
    "sg:phone":"+1 254 753 6600",
    "sg:postcode":"76710",
    "sg:province":"TX",
    "sg:tags":[
        "dealer",
        "rug"
    ],
    "wof:name":"Budget Carpet Cleaning",
    "wof:placetype":"venue"
},
  "geometry": {"coordinates":[-97.154707,31.534974],"type":"Point"}
}