{
  "type": "Feature",
  "properties": {
    "iso:country":"US",
    "sg:address":"5801 Preston Oaks Rd",
    "sg:city":"Dallas",
    "sg:classifiers":[
        {
            "category":"Professional",
            "type":"Services"
        }
    ],
    "sg:phone":"+1 972 386 7351",
    "sg:postcode":"75254",
    "sg:province":"TX",
    "sg:tags":[
        "establishment"
    ],
    "wof:name":"Madlock & Assoc",
    "wof:placetype":"venue"
},
  "geometry": {"coordinates":[-96.805998,32.942116],"type":"Point"}
}