{
  "type": "Feature",
  "properties": {
    "iso:country":"US",
    "sg:address":"18477 W Lake Houston Pkwy",
    "sg:city":"Humble",
    "sg:classifiers":[
        {
            "category":"Autos & Motor Vehicles",
            "subcategory":"Automobile Sales",
            "type":"Retail Goods"
        }
    ],
    "sg:phone":"+1 832 644 9260",
    "sg:postcode":"77346",
    "sg:province":"TX",
    "sg:tags":[
        "new",
        "car"
    ],
    "wof:name":"Gmc Way",
    "wof:placetype":"venue"
},
  "geometry": {"coordinates":[-95.161565,29.984915],"type":"Point"}
}