{
  "type": "Feature",
  "properties": {
    "iso:country":"US",
    "sg:address":"8920 Lawndale St Ste D",
    "sg:city":"Houston",
    "sg:classifiers":[
        {
            "category":"Professional",
            "subcategory":"Business Services",
            "type":"Services"
        }
    ],
    "sg:phone":"+1 713 921 3727",
    "sg:postcode":"77012",
    "sg:province":"TX",
    "sg:tags":[
        "delivery",
        "courier"
    ],
    "sg:website":"www.suzysexpress.com",
    "wof:name":"Suzy's Express Inc",
    "wof:placetype":"venue"
},
  "geometry": {"coordinates":[-95.268097,29.7146],"type":"Point"}
}