{
  "type": "Feature",
  "properties": {
    "iso:country":"US",
    "sg:address":"3184 Preston Rd",
    "sg:city":"Frisco",
    "sg:classifiers":[
        {
            "category":"Professional",
            "type":"Services"
        },
        {
            "category":"Real Estate",
            "subcategory":"Real Estate Agent",
            "type":"Services"
        }
    ],
    "sg:phone":"+1 469 234 2000",
    "sg:postcode":"75034",
    "sg:province":"TX",
    "wof:name":"Remax Premier IV",
    "wof:placetype":"venue"
},
  "geometry": {"coordinates":[-96.80585000000001,33.103839],"type":"Point"}
}