{
  "type": "Feature",
  "properties": {
    "iso:country":"US",
    "sg:address":"6791 State Hwy 6",
    "sg:city":"De Leon",
    "sg:classifiers":[
        {
            "category":"Insurance",
            "subcategory":"Insurance Agent",
            "type":"Services"
        }
    ],
    "sg:phone":"+1 254 893 4320",
    "sg:postcode":"76444",
    "sg:province":"TX",
    "wof:name":"Farmers Insurance",
    "wof:placetype":"venue"
},
  "geometry": {"coordinates":[-98.47538,32.100945],"type":"Point"}
}