{
  "type": "Feature",
  "properties": {
    "iso:country":"US",
    "sg:address":"4368 Seguin Rd",
    "sg:city":"San Antonio",
    "sg:classifiers":[
        {
            "category":"Wholesale",
            "subcategory":"Machinery & Supplies",
            "type":"Manufacturing & Wholesale Goods"
        }
    ],
    "sg:phone":"+1 210 226 2476",
    "sg:postcode":"78219",
    "sg:province":"TX",
    "sg:tags":[
        "janitor"
    ],
    "wof:name":"DADD Inc",
    "wof:placetype":"venue"
},
  "geometry": {"coordinates":[-98.410999,29.454853],"type":"Point"}
}