{
  "type": "Feature",
  "properties": {
    "iso:country":"US",
    "sg:address":"26014 Overlake Dr",
    "sg:city":"Spring",
    "sg:classifiers":[
        {
            "category":"Banks & Credit Unions",
            "subcategory":"Bank",
            "type":"Services"
        }
    ],
    "sg:phone":"+1 281 363 9006",
    "sg:postcode":"77380",
    "sg:province":"TX",
    "sg:tags":[
        "loan"
    ],
    "wof:name":"New Millennium Lending",
    "wof:placetype":"venue"
},
  "geometry": {"coordinates":[-95.45278999999999,30.137423],"type":"Point"}
}