{
  "type": "Feature",
  "properties": {
    "iso:country":"US",
    "sg:address":"1629 Post Rd",
    "sg:city":"San Marcos",
    "sg:classifiers":[
        {
            "category":"Real Estate",
            "subcategory":"Real Estate Operator",
            "type":"Services"
        }
    ],
    "sg:phone":"+1 512 353 6691",
    "sg:postcode":"78666",
    "sg:province":"TX",
    "sg:tags":[
        "apartment"
    ],
    "sg:website":"www.carlisleapts.com",
    "wof:name":"Post Road Place Apartments",
    "wof:placetype":"venue"
},
  "geometry": {"coordinates":[-97.918274,29.899689],"type":"Point"}
}