{
  "type": "Feature",
  "properties": {
    "iso:country":"US",
    "sg:address":"800 Rodeo Dr",
    "sg:city":"Colleyville",
    "sg:classifiers":[
        {
            "category":"Professional",
            "type":"Services"
        }
    ],
    "sg:phone":"+1 817 577 8458",
    "sg:postcode":"76034",
    "sg:province":"TX",
    "wof:name":"Triumvirate Productions",
    "wof:placetype":"venue"
},
  "geometry": {"coordinates":[-97.15472,32.869945],"type":"Point"}
}