{
  "type": "Feature",
  "properties": {
    "iso:country":"US",
    "sg:address":"3902 Columbus Dr",
    "sg:city":"Mc Kinney",
    "sg:classifiers":[
        {
            "category":"Banks & Credit Unions",
            "subcategory":"Bank",
            "type":"Services"
        }
    ],
    "sg:phone":"+1 972 562 4359",
    "sg:postcode":"75070",
    "sg:province":"TX",
    "sg:tags":[
        "mortgage"
    ],
    "wof:name":"Metro 1st Mortgage",
    "wof:placetype":"venue"
},
  "geometry": {"coordinates":[-96.673681,33.159158],"type":"Point"}
}