{
  "type": "Feature",
  "properties": {
    "iso:country":"US",
    "sg:address":"2250 E Loop 820",
    "sg:city":"Fort Worth",
    "sg:classifiers":[
        {
            "category":"Restaurant",
            "type":"Food & Drink"
        }
    ],
    "sg:menulink":"http://www.allmenus.com/tx/fort-worth/202339-mcdonalds/menu/",
    "sg:postcode":"76112",
    "sg:province":"TX",
    "sg:tags":[
        "burger",
        "american"
    ],
    "wof:name":"McDonald's",
    "wof:placetype":"venue"
},
  "geometry": {"coordinates":[-97.222826,32.746477],"type":"Point"}
}