{
  "type": "Feature",
  "properties": {
    "iso:country":"US",
    "sg:address":"8117 Preston Rd",
    "sg:city":"Dallas",
    "sg:classifiers":[
        {
            "category":"Banks & Credit Unions",
            "subcategory":"Bank",
            "type":"Services"
        }
    ],
    "sg:phone":"+1 214 346 0663",
    "sg:postcode":"75225",
    "sg:province":"TX",
    "sg:tags":[
        "loan",
        "real estate"
    ],
    "wof:name":"Wells Fargo Home Mortgage Inc",
    "wof:placetype":"venue"
},
  "geometry": {"coordinates":[-96.80414500000001,32.861154],"type":"Point"}
}