{
  "type": "Feature",
  "properties": {
    "iso:country":"US",
    "sg:address":"1702 Holly Creek Dr",
    "sg:city":"Tyler",
    "sg:classifiers":[
        {
            "category":"Shopping",
            "subcategory":"Computers & Home Electronics",
            "type":"Retail Goods"
        }
    ],
    "sg:phone":"+1 903 561 7096",
    "sg:postcode":"75703",
    "sg:province":"TX",
    "sg:tags":[
        "software"
    ],
    "sg:website":"www.docuchart.com",
    "wof:name":"Doc U Chart",
    "wof:placetype":"venue"
},
  "geometry": {"coordinates":[-95.32655,32.268654],"type":"Point"}
}