{
  "type": "Feature",
  "properties": {
    "iso:country":"US",
    "sg:address":"4637 Orange Grove Dr",
    "sg:city":"Houston",
    "sg:classifiers":[
        {
            "category":"Education",
            "subcategory":"Kindergarten",
            "type":"Public Place"
        }
    ],
    "sg:phone":"+1 281 449 7834",
    "sg:postcode":"77039",
    "sg:province":"TX",
    "sg:tags":[
        "school",
        "driving"
    ],
    "wof:name":"Class A Cdl Service",
    "wof:placetype":"venue"
},
  "geometry": {"coordinates":[-95.32399700000001,29.8943],"type":"Point"}
}