{
  "type": "Feature",
  "properties": {
    "iso:country":"US",
    "sg:address":"2401 Clark Blvd",
    "sg:city":"Laredo",
    "sg:classifiers":[
        {
            "category":"Education",
            "subcategory":"School",
            "type":"Public Place"
        }
    ],
    "sg:phone":"+1 956 795 4060",
    "sg:postcode":"78043",
    "sg:province":"TX",
    "wof:name":"M S Ryan Elementary School",
    "wof:placetype":"venue"
},
  "geometry": {"coordinates":[-99.47108900000001,27.51665],"type":"Point"}
}