{
  "type": "Feature",
  "properties": {
    "iso:country":"US",
    "sg:address":"1448 W Buckingham Rd",
    "sg:city":"Garland",
    "sg:classifiers":[
        {
            "category":"Building & Trades",
            "subcategory":"Construction",
            "type":"Services"
        }
    ],
    "sg:phone":"+1 972 485 9326",
    "sg:postcode":"75042",
    "sg:province":"TX",
    "sg:tags":[
        "residential"
    ],
    "wof:name":"H & R General Construction",
    "wof:placetype":"venue"
},
  "geometry": {"coordinates":[-96.650774,32.930517],"type":"Point"}
}