{
  "type": "Feature",
  "properties": {
    "iso:country":"US",
    "sg:address":"1735 Keller Springs Rd Ste 202",
    "sg:city":"Carrollton",
    "sg:classifiers":[
        {
            "category":"Community Center",
            "type":"Public Place"
        }
    ],
    "sg:phone":"+1 800 639 6773",
    "sg:postcode":"75006",
    "sg:province":"TX",
    "sg:tags":[
        "medical"
    ],
    "sg:website":"www.localstdtesting.com/15",
    "wof:name":"Local HIV / STD Testing",
    "wof:placetype":"venue"
},
  "geometry": {"coordinates":[-96.89389,32.972759],"type":"Point"}
}