{
  "type": "Feature",
  "properties": {
    "iso:country":"US",
    "sg:address":"1844 W Division St",
    "sg:city":"Arlington",
    "sg:classifiers":[
        {
            "category":"Autos & Motor Vehicles",
            "subcategory":"Automobile Sales",
            "type":"Retail Goods"
        }
    ],
    "sg:phone":"+1 817 794 5606",
    "sg:postcode":"76012",
    "sg:province":"TX",
    "wof:name":"Phase One Wholesale",
    "wof:placetype":"venue"
},
  "geometry": {"coordinates":[-97.137156,32.735783],"type":"Point"}
}