{
  "type": "Feature",
  "properties": {
    "iso:country":"US",
    "sg:address":"324 Cemetery Rd",
    "sg:city":"Angleton",
    "sg:classifiers":[
        {
            "category":"Real Estate",
            "subcategory":"Real Estate Operator",
            "type":"Services"
        }
    ],
    "sg:phone":"+1 979 849 0268",
    "sg:postcode":"77515",
    "sg:province":"TX",
    "sg:tags":[
        "mobile",
        "home",
        "site"
    ],
    "wof:name":"Southside Mobile Home Park",
    "wof:placetype":"venue"
},
  "geometry": {"coordinates":[-95.425712,29.150408],"type":"Point"}
}