{
  "type": "Feature",
  "properties": {
    "iso:country":"US",
    "sg:address":"11202 Beechnut St",
    "sg:city":"Houston",
    "sg:classifiers":[
        {
            "category":"Autos & Motor Vehicles",
            "subcategory":"Fuel & Gas Station",
            "type":"Retail Goods"
        }
    ],
    "sg:phone":"+1 281 351 3406",
    "sg:postcode":"77072",
    "sg:province":"TX",
    "sg:tags":[
        "station",
        "gasoline"
    ],
    "wof:name":"Texaco Boone",
    "wof:placetype":"venue"
},
  "geometry": {"coordinates":[-95.57536500000001,29.688115],"type":"Point"}
}