{
  "type": "Feature",
  "properties": {
    "iso:country":"US",
    "sg:address":"307 Laurel Dr",
    "sg:city":"Friendswood",
    "sg:classifiers":[
        {
            "category":"Personal",
            "subcategory":"Beauty Salon",
            "type":"Services"
        }
    ],
    "sg:phone":"+1 281 992 2116",
    "sg:postcode":"77546",
    "sg:province":"TX",
    "wof:name":"Essential Elegance Salon",
    "wof:placetype":"venue"
},
  "geometry": {"coordinates":[-95.203593,29.529022],"type":"Point"}
}