{
  "type": "Feature",
  "properties": {
    "iso:country":"US",
    "sg:address":"410 Main St",
    "sg:city":"Sulphur Springs",
    "sg:classifiers":[
        {
            "category":"Building & Trades",
            "subcategory":"Construction",
            "type":"Services"
        }
    ],
    "sg:phone":"+1 903 885 0051",
    "sg:postcode":"75482",
    "sg:province":"TX",
    "sg:tags":[
        "paving",
        "contractor"
    ],
    "wof:name":"A-1 Pavement Svc",
    "wof:placetype":"venue"
},
  "geometry": {"coordinates":[-95.604451,33.137158],"type":"Point"}
}