{
  "type": "Feature",
  "properties": {
    "iso:country":"US",
    "sg:address":"1611 Airport Commerce Dr",
    "sg:city":"Austin",
    "sg:classifiers":[
        {
            "category":"Travel",
            "subcategory":"Hotels & Motels",
            "type":"Entertainment"
        },
        {
            "category":"Retail",
            "subcategory":"Event Space",
            "type":"Services"
        }
    ],
    "sg:phone":"+1 877 660 8545",
    "sg:postcode":"78741",
    "sg:province":"TX",
    "sg:tags":[
        "facility",
        "banquet",
        "reception",
        "lodging",
        "corporate",
        "hall"
    ],
    "sg:website":"http://ad.doubleclick.net/clk;222817218;46581828;o?http://www.staybridge.com/redirect?path=hd&brandCode=sb&hotelCode=ausrs&_PMID=99601036&cm_mmc=mdpr-_-yellowpages-_-sb-_-ausrs",
    "wof:name":"Staybridge Suites Austin Airport",
    "wof:placetype":"venue"
},
  "geometry": {"coordinates":[-97.689407,30.22208],"type":"Point"}
}