{
  "type": "Feature",
  "properties": {
    "iso:country":"US",
    "sg:address":"7204 Staffordshire St",
    "sg:city":"Houston",
    "sg:classifiers":[
        {
            "category":"Professional",
            "subcategory":"Business Services",
            "type":"Services"
        }
    ],
    "sg:phone":"+1 713 795 5333",
    "sg:postcode":"77030",
    "sg:province":"TX",
    "sg:tags":[
        "consultant",
        "publishing"
    ],
    "wof:name":"Healthcare Journals, Inc.",
    "wof:placetype":"venue"
},
  "geometry": {"coordinates":[-95.394024,29.701823],"type":"Point"}
}