{
  "type": "Feature",
  "properties": {
    "iso:country":"US",
    "sg:address":"7615 Highmeadow Dr",
    "sg:city":"Houston",
    "sg:classifiers":[
        {
            "category":"Restaurant",
            "type":"Food & Drink"
        }
    ],
    "sg:phone":"+1 713 781 8096",
    "sg:postcode":"77063",
    "sg:province":"TX",
    "sg:tags":[
        "eating"
    ],
    "wof:name":"Creations I Chryshanthis",
    "wof:placetype":"venue"
},
  "geometry": {"coordinates":[-95.505573,29.73451],"type":"Point"}
}