{
  "type": "Feature",
  "properties": {
    "iso:country":"US",
    "sg:address":"512 N Walnut St",
    "sg:city":"Sherman",
    "sg:classifiers":[
        {
            "category":"Wholesale",
            "subcategory":"Medical Equipment & Supplies",
            "type":"Manufacturing & Wholesale Goods"
        }
    ],
    "sg:phone":"+1 903 893 7773",
    "sg:postcode":"75090",
    "sg:province":"TX",
    "sg:tags":[
        "x",
        "apparatus"
    ],
    "wof:name":"Roadrunner X Ray Inc",
    "wof:placetype":"venue"
},
  "geometry": {"coordinates":[-96.609433,33.640791],"type":"Point"}
}