{
  "type": "Feature",
  "properties": {
    "iso:country":"US",
    "sg:address":"1020 N Commerce St",
    "sg:city":"Baytown",
    "sg:classifiers":[
        {
            "category":"Building & Trades",
            "subcategory":"Plumbing",
            "type":"Services"
        }
    ],
    "sg:phone":"+1 281 427 4353",
    "sg:postcode":"77520",
    "sg:province":"TX",
    "sg:tags":[
        "contractor"
    ],
    "wof:name":"Cornejos Plumbing",
    "wof:placetype":"venue"
},
  "geometry": {"coordinates":[-94.964845,29.740619],"type":"Point"}
}