{
  "type": "Feature",
  "properties": {
    "iso:country":"US",
    "sg:address":"3103 Wilshire Ln",
    "sg:city":"Baytown",
    "sg:classifiers":[
        {
            "category":"Professional",
            "subcategory":"Management & Consulting",
            "type":"Services"
        }
    ],
    "sg:phone":"+1 281 427 9682",
    "sg:postcode":"77521",
    "sg:province":"TX",
    "sg:tags":[
        "business"
    ],
    "wof:name":"Heinlein Consulting LLC",
    "wof:placetype":"venue"
},
  "geometry": {"coordinates":[-94.930572,29.771776],"type":"Point"}
}