{
  "type": "Feature",
  "properties": {
    "iso:country":"US",
    "sg:address":"2822 Thorne Creek Ln",
    "sg:city":"Houston",
    "sg:classifiers":[
        {
            "category":"Shopping",
            "subcategory":"Gifts & Souvenirs",
            "type":"Retail Goods"
        }
    ],
    "sg:phone":"+1 281 359 3067",
    "sg:postcode":"77073",
    "sg:province":"TX",
    "wof:name":"Aarons Sports Cards",
    "wof:placetype":"venue"
},
  "geometry": {"coordinates":[-95.383207,30.008161],"type":"Point"}
}