{
  "type": "Feature",
  "properties": {
    "iso:country":"US",
    "sg:address":"8181 Ambassador Row",
    "sg:city":"Dallas",
    "sg:classifiers":[
        {
            "category":"Manufacturing",
            "subcategory":"Building Materials",
            "type":"Manufacturing & Wholesale Goods"
        }
    ],
    "sg:phone":"+1 214 630 0934",
    "sg:postcode":"75247",
    "sg:province":"TX",
    "sg:tags":[
        "window",
        "door",
        "storm"
    ],
    "sg:website":"http://www.donyoungwindows.com",
    "wof:name":"Don Young Company",
    "wof:placetype":"venue"
},
  "geometry": {"coordinates":[-96.878354,32.818933],"type":"Point"}
}