{
  "type": "Feature",
  "properties": {
    "iso:country":"US",
    "sg:address":"3618 W FM 2105",
    "sg:city":"San Angelo",
    "sg:classifiers":[
        {
            "category":"Restaurant",
            "type":"Food & Drink"
        }
    ],
    "sg:phone":"+1 325 653 4777",
    "sg:postcode":"76901",
    "sg:province":"TX",
    "sg:tags":[
        "cafe"
    ],
    "wof:name":"T J Cafe",
    "wof:placetype":"venue"
},
  "geometry": {"coordinates":[-100.482928,31.527191],"type":"Point"}
}