{
  "type": "Feature",
  "properties": {
    "iso:country":"US",
    "sg:address":"2721 Fall Creek Hwy",
    "sg:city":"Granbury",
    "sg:classifiers":[
        {
            "category":"Freight",
            "type":"Transportation"
        }
    ],
    "sg:phone":"+1 817 326 2664",
    "sg:postcode":"76049",
    "sg:province":"TX",
    "sg:tags":[
        "general"
    ],
    "wof:name":"Landmark Storage",
    "wof:placetype":"venue"
},
  "geometry": {"coordinates":[-97.687731,32.451857],"type":"Point"}
}