{
  "type": "Feature",
  "properties": {
    "iso:country":"US",
    "sg:address":"2301 N Collins St",
    "sg:city":"Arlington",
    "sg:classifiers":[
        {
            "category":"Recreation",
            "type":"Entertainment"
        }
    ],
    "sg:phone":"+1 817 461 1420",
    "sg:postcode":"76011",
    "sg:province":"TX",
    "wof:name":"Speeds Plus Inc",
    "wof:placetype":"venue"
},
  "geometry": {"coordinates":[-97.09707299999999,32.775335],"type":"Point"}
}