{
  "type": "Feature",
  "properties": {
    "iso:country":"US",
    "sg:address":"115 Lake Shore Dr",
    "sg:city":"Corpus Christi",
    "sg:classifiers":[
        {
            "category":"Real Estate",
            "subcategory":"Architect",
            "type":"Services"
        }
    ],
    "sg:phone":"+1 361 814 1271",
    "sg:postcode":"78413",
    "sg:province":"TX",
    "wof:name":"Larry Money",
    "wof:placetype":"venue"
},
  "geometry": {"coordinates":[-97.397784,27.694025],"type":"Point"}
}