{
  "type": "Feature",
  "properties": {
    "iso:country":"US",
    "sg:address":"1733 Curie Dr",
    "sg:city":"El Paso",
    "sg:classifiers":[
        {
            "category":"Health Services",
            "subcategory":"Health Practitioner",
            "type":"Services"
        }
    ],
    "sg:phone":"+1 915 533 4990",
    "sg:postcode":"79902",
    "sg:province":"TX",
    "sg:tags":[
        "audiologists"
    ],
    "wof:name":"Physicians Southwest Hearing",
    "wof:placetype":"venue"
},
  "geometry": {"coordinates":[-106.478269,31.779033],"type":"Point"}
}