{
  "type": "Feature",
  "properties": {
    "iso:country":"US",
    "sg:address":"575 N Valley Pkwy",
    "sg:city":"Lewisville",
    "sg:classifiers":[
        {
            "category":"Health Services",
            "subcategory":"Chiropractor",
            "type":"Services"
        }
    ],
    "sg:phone":"+1 972 219 0434",
    "sg:postcode":"75067",
    "sg:province":"TX",
    "sg:website":"www.byroadchiropractic.com",
    "wof:name":"Byroad Chiropractic Ctr",
    "wof:placetype":"venue"
},
  "geometry": {"coordinates":[-97.02070500000001,33.048722],"type":"Point"}
}