{
  "type": "Feature",
  "properties": {
    "iso:country":"US",
    "sg:address":"115 Lincoln Springs Rd",
    "sg:city":"Gladewater",
    "sg:classifiers":[
        {
            "category":"Wholesale",
            "subcategory":"Machinery & Supplies",
            "type":"Manufacturing & Wholesale Goods"
        }
    ],
    "sg:phone":"+1 903 844 2507",
    "sg:postcode":"75647",
    "sg:province":"TX",
    "wof:name":"Running M Trailers",
    "wof:placetype":"venue"
},
  "geometry": {"coordinates":[-94.98571,32.493793],"type":"Point"}
}