{
  "type": "Feature",
  "properties": {
    "iso:country":"US",
    "sg:address":"920 N Main St",
    "sg:city":"Paris",
    "sg:classifiers":[
        {
            "category":"Real Estate",
            "subcategory":"Surveying",
            "type":"Services"
        }
    ],
    "sg:phone":"+1 903 785 3399",
    "sg:postcode":"75460",
    "sg:province":"TX",
    "wof:name":"Nelson Surveying Co",
    "wof:placetype":"venue"
},
  "geometry": {"coordinates":[-95.55604099999999,33.670202],"type":"Point"}
}