{
  "type": "Feature",
  "properties": {
    "iso:country":"US",
    "sg:address":"3706 Laurel Ledge Ln",
    "sg:city":"Austin",
    "sg:classifiers":[
        {
            "category":"Manufacturing",
            "subcategory":"Tools & Machinery",
            "type":"Manufacturing & Wholesale Goods"
        }
    ],
    "sg:phone":"+1 512 458 8832",
    "sg:postcode":"78731",
    "sg:province":"TX",
    "sg:tags":[
        "field",
        "mfg"
    ],
    "wof:name":"Mm Jet Bit Inc",
    "wof:placetype":"venue"
},
  "geometry": {"coordinates":[-97.76123200000001,30.346895],"type":"Point"}
}