{
  "type": "Feature",
  "properties": {
    "iso:country":"US",
    "sg:address":"12413 Burlywood Trl",
    "sg:city":"Austin",
    "sg:classifiers":[
        {
            "category":"Building & Trades",
            "subcategory":"Cleaning & Sanitation",
            "type":"Services"
        }
    ],
    "sg:phone":"+1 512 329 0110",
    "sg:postcode":"78750",
    "sg:province":"TX",
    "sg:tags":[
        "polishing",
        "waxing",
        "floor"
    ],
    "wof:name":"Good Stuff Products",
    "wof:placetype":"venue"
},
  "geometry": {"coordinates":[-97.80608599999999,30.462159],"type":"Point"}
}