{
  "type": "Feature",
  "properties": {
    "iso:country":"US",
    "sg:address":"4567 Lake Shore Dr",
    "sg:city":"Waco",
    "sg:classifiers":[
        {
            "category":"Wholesale",
            "subcategory":"Durable Goods & Equipment",
            "type":"Manufacturing & Wholesale Goods"
        }
    ],
    "sg:phone":"+1 254 776 2060",
    "sg:postcode":"76710",
    "sg:province":"TX",
    "sg:tags":[
        "personal",
        "development",
        "leadership",
        "course"
    ],
    "wof:name":"LMI",
    "wof:placetype":"venue"
},
  "geometry": {"coordinates":[-97.19534899999999,31.561639],"type":"Point"}
}