{
  "type": "Feature",
  "properties": {
    "iso:country":"US",
    "sg:address":"407 13th St",
    "sg:city":"Abernathy",
    "sg:classifiers":[
        {
            "category":"Utilities",
            "subcategory":"Refuse",
            "type":"Services"
        }
    ],
    "sg:phone":"+1 806 298 2018",
    "sg:postcode":"79311",
    "sg:province":"TX",
    "sg:tags":[
        "system"
    ],
    "wof:name":"Triple C Sanitation Service",
    "wof:placetype":"venue"
},
  "geometry": {"coordinates":[-101.843132,33.83626],"type":"Point"}
}