{
  "type": "Feature",
  "properties": {
    "iso:country":"US",
    "sg:address":"1102 W Church St",
    "sg:city":"Grand Prairie",
    "sg:classifiers":[
        {
            "category":"Retail",
            "subcategory":"Auto Repair",
            "type":"Services"
        }
    ],
    "sg:phone":"+1 972 206 2108",
    "sg:postcode":"75050",
    "sg:province":"TX",
    "sg:tags":[
        "body"
    ],
    "wof:name":"J Auto Collision & Accessories",
    "wof:placetype":"venue"
},
  "geometry": {"coordinates":[-97.020995,32.746759],"type":"Point"}
}