{
  "type": "Feature",
  "properties": {
    "iso:country":"US",
    "sg:address":"215 Eldridge Dr",
    "sg:city":"Beaumont",
    "sg:classifiers":[
        {
            "category":"Shopping",
            "subcategory":"Hobbies, Toys, & Games",
            "type":"Retail Goods"
        }
    ],
    "sg:phone":"+1 409 866 6665",
    "sg:postcode":"77707",
    "sg:province":"TX",
    "wof:name":"Country Dreaming",
    "wof:placetype":"venue"
},
  "geometry": {"coordinates":[-94.18530199999999,30.072823],"type":"Point"}
}