{
  "type": "Feature",
  "properties": {
    "iso:country":"US",
    "sg:address":"3438 River Way",
    "sg:city":"San Antonio",
    "sg:classifiers":[
        {
            "category":"Professional",
            "type":"Services"
        }
    ],
    "sg:phone":"+1 210 690 8142",
    "sg:postcode":"78230",
    "sg:province":"TX",
    "wof:name":"David Moad",
    "wof:placetype":"venue"
},
  "geometry": {"coordinates":[-98.552802,29.546356],"type":"Point"}
}