{
  "type": "Feature",
  "properties": {
    "iso:country":"US",
    "sg:address":"900 Tony Lama St",
    "sg:city":"El Paso",
    "sg:classifiers":[
        {
            "category":"Retail",
            "subcategory":"Auto Repair",
            "type":"Services"
        }
    ],
    "sg:phone":"+1 915 590 6281",
    "sg:postcode":"79915",
    "sg:province":"TX",
    "sg:tags":[
        "transmission"
    ],
    "wof:name":"Quality Discount",
    "wof:placetype":"venue"
},
  "geometry": {"coordinates":[-106.375653,31.761751],"type":"Point"}
}