{
  "type": "Feature",
  "properties": {
    "iso:country":"US",
    "sg:address":"5906 Rocky Ridge Rd",
    "sg:city":"Dallas",
    "sg:classifiers":[
        {
            "category":"Arts & Performance",
            "subcategory":"Theater",
            "type":"Entertainment"
        }
    ],
    "sg:phone":"+1 214 374 1271",
    "sg:postcode":"75241",
    "sg:province":"TX",
    "sg:tags":[
        "theatrical"
    ],
    "wof:name":"K & O Sound Production",
    "wof:placetype":"venue"
},
  "geometry": {"coordinates":[-96.8192,32.675772],"type":"Point"}
}