{
  "type": "Feature",
  "properties": {
    "iso:country":"US",
    "sg:address":"751 Kilgore Dr",
    "sg:city":"Henderson",
    "sg:classifiers":[
        {
            "category":"Building & Trades",
            "subcategory":"Construction",
            "type":"Services"
        }
    ],
    "sg:phone":"+1 903 657 7149",
    "sg:postcode":"75652",
    "sg:province":"TX",
    "sg:tags":[
        "general",
        "contractor"
    ],
    "wof:name":"LCJ Construction Co",
    "wof:placetype":"venue"
},
  "geometry": {"coordinates":[-94.792333,32.177788],"type":"Point"}
}