{
  "type": "Feature",
  "properties": {
    "iso:country":"US",
    "sg:address":"42 N Deerfoot Cir",
    "sg:city":"Spring",
    "sg:classifiers":[
        {
            "category":"Shopping",
            "subcategory":"Hobbies, Toys, & Games",
            "type":"Retail Goods"
        }
    ],
    "sg:phone":"+1 281 367 5612",
    "sg:postcode":"77380",
    "sg:province":"TX",
    "wof:name":"Ilovetoysnet",
    "wof:placetype":"venue"
},
  "geometry": {"coordinates":[-95.45156799999999,30.155215],"type":"Point"}
}