{
  "type": "Feature",
  "properties": {
    "iso:country":"US",
    "sg:address":"1805 E 7th St",
    "sg:city":"Austin",
    "sg:classifiers":[
        {
            "category":"Arts & Performance",
            "subcategory":"Theater",
            "type":"Entertainment"
        }
    ],
    "sg:phone":"+1 512 478 9717",
    "sg:postcode":"78702",
    "sg:province":"TX",
    "sg:tags":[
        "dance",
        "performing"
    ],
    "sg:website":"www.aztlandance.com",
    "wof:name":"Aztlan Dance Company",
    "wof:placetype":"venue"
},
  "geometry": {"coordinates":[-97.722702,30.262899],"type":"Point"}
}