{
  "type": "Feature",
  "properties": {
    "iso:country":"US",
    "sg:address":"4212 Sherwood Ln",
    "sg:city":"Amarillo",
    "sg:classifiers":[
        {
            "category":"Professional",
            "subcategory":"Computer Services",
            "type":"Services"
        }
    ],
    "sg:phone":"+1 806 356 9519",
    "sg:postcode":"79110",
    "sg:province":"TX",
    "sg:tags":[
        "related"
    ],
    "wof:name":"Web Pagesights",
    "wof:placetype":"venue"
},
  "geometry": {"coordinates":[-101.885288,35.136551],"type":"Point"}
}