{
  "type": "Feature",
  "properties": {
    "iso:country":"US",
    "sg:address":"2709 Galvez Ave",
    "sg:city":"Fort Worth",
    "sg:classifiers":[
        {
            "category":"Manufacturing",
            "subcategory":"Chemicals & Compounds",
            "type":"Manufacturing & Wholesale Goods"
        }
    ],
    "sg:phone":"+1 817 335 1014",
    "sg:postcode":"76111",
    "sg:province":"TX",
    "sg:tags":[
        "preparation",
        "toilet",
        "mfg"
    ],
    "wof:name":"Fit Wright Dentures",
    "wof:placetype":"venue"
},
  "geometry": {"coordinates":[-97.306512,32.762347],"type":"Point"}
}