{
  "type": "Feature",
  "properties": {
    "iso:country":"US",
    "sg:address":"3301 Long Prairie Rd",
    "sg:city":"Flower Mound",
    "sg:classifiers":[
        {
            "category":"Personal",
            "type":"Services"
        }
    ],
    "sg:phone":"+1 972 724 9642",
    "sg:postcode":"75022",
    "sg:province":"TX",
    "sg:tags":[
        "consultant",
        "program",
        "health",
        "fitness"
    ],
    "wof:name":"Yoga Island",
    "wof:placetype":"venue"
},
  "geometry": {"coordinates":[-97.07083,33.030035],"type":"Point"}
}