{
  "type": "Feature",
  "properties": {
    "iso:country":"US",
    "sg:address":"319 Oklahoma St",
    "sg:city":"Laredo",
    "sg:classifiers":[
        {
            "category":"Manufacturing",
            "subcategory":"Signs",
            "type":"Manufacturing & Wholesale Goods"
        }
    ],
    "sg:phone":"+1 956 722 2468",
    "sg:postcode":"78041",
    "sg:province":"TX",
    "sg:tags":[
        "advertising",
        "specialty"
    ],
    "wof:name":"Dynamic Signs",
    "wof:placetype":"venue"
},
  "geometry": {"coordinates":[-99.483997,27.546799],"type":"Point"}
}