{
  "type": "Feature",
  "properties": {
    "iso:country":"US",
    "sg:address":"7747 Eckhert Rd",
    "sg:city":"San Antonio",
    "sg:classifiers":[
        {
            "category":"Personal",
            "subcategory":"Beauty Salon",
            "type":"Services"
        }
    ],
    "sg:phone":"+1 210 647 4247",
    "sg:postcode":"78240",
    "sg:province":"TX",
    "sg:tags":[
        "shop"
    ],
    "wof:name":"Mane Attitudes",
    "wof:placetype":"venue"
},
  "geometry": {"coordinates":[-98.62238600000001,29.513192],"type":"Point"}
}