{
  "type": "Feature",
  "properties": {
    "iso:country":"US",
    "sg:address":"930 W 2nd St",
    "sg:city":"Mercedes",
    "sg:classifiers":[
        {
            "category":"Cinema",
            "subcategory":"Movie Rental",
            "type":"Entertainment"
        }
    ],
    "sg:phone":"+1 956 565 2234",
    "sg:postcode":"78570",
    "sg:province":"TX",
    "sg:tags":[
        "video",
        "tape"
    ],
    "wof:name":"Top Video",
    "wof:placetype":"venue"
},
  "geometry": {"coordinates":[-97.919741,26.149827],"type":"Point"}
}