{
  "type": "Feature",
  "properties": {
    "iso:country":"US",
    "sg:address":"4103 Ocean Dr",
    "sg:city":"Corpus Christi",
    "sg:classifiers":[
        {
            "category":"Organizations",
            "subcategory":"Religious Organization",
            "type":"Services"
        }
    ],
    "sg:phone":"+1 361 854 2820",
    "sg:postcode":"78411",
    "sg:province":"TX",
    "wof:name":"Sisters Of The Adoration",
    "wof:placetype":"venue"
},
  "geometry": {"coordinates":[-97.370148,27.741603],"type":"Point"}
}