{
  "type": "Feature",
  "properties": {
    "iso:country":"US",
    "sg:address":"3417 Foothill Ter",
    "sg:city":"Austin",
    "sg:classifiers":[
        {
            "category":"Professional",
            "subcategory":"Management & Consulting",
            "type":"Services"
        }
    ],
    "sg:phone":"+1 512 453 3184",
    "sg:postcode":"78731",
    "sg:province":"TX",
    "sg:tags":[
        "fuel"
    ],
    "wof:name":"CBC Ranch Management",
    "wof:placetype":"venue"
},
  "geometry": {"coordinates":[-97.77109400000001,30.316757],"type":"Point"}
}