{
  "type": "Feature",
  "properties": {
    "iso:country":"US",
    "sg:address":"201 Locust St",
    "sg:city":"Winnsboro",
    "sg:classifiers":[
        {
            "category":"Government",
            "subcategory":"Post Office",
            "type":"Public Place"
        }
    ],
    "sg:phone":"+1 903 342 5594",
    "sg:postcode":"75494",
    "sg:province":"TX",
    "wof:name":"US Post Office",
    "wof:placetype":"venue"
},
  "geometry": {"coordinates":[-95.28865399999999,32.959021],"type":"Point"}
}