{
  "type": "Feature",
  "properties": {
    "iso:country":"US",
    "sg:address":"2016 Acton Hwy",
    "sg:city":"Granbury",
    "sg:classifiers":[
        {
            "category":"Organizations",
            "subcategory":"Religious Organization",
            "type":"Services"
        }
    ],
    "sg:phone":"+1 817 326 3573",
    "sg:postcode":"76049",
    "sg:province":"TX",
    "wof:name":"Seventh Day Adventist Church",
    "wof:placetype":"venue"
},
  "geometry": {"coordinates":[-97.74868600000001,32.441105],"type":"Point"}
}