{
  "type": "Feature",
  "properties": {
    "iso:country":"US",
    "sg:address":"3510 Greenhouse Rd",
    "sg:city":"Houston",
    "sg:classifiers":[
        {
            "category":"Wholesale",
            "subcategory":"Construction Materials",
            "type":"Manufacturing & Wholesale Goods"
        }
    ],
    "sg:phone":"+1 281 492 2558",
    "sg:postcode":"77084",
    "sg:province":"TX",
    "sg:tags":[
        "sand",
        "gravel"
    ],
    "wof:name":"G O Weiss Inc",
    "wof:placetype":"venue"
},
  "geometry": {"coordinates":[-95.70336,29.819594],"type":"Point"}
}