{
  "type": "Feature",
  "properties": {
    "iso:country":"US",
    "sg:address":"1518 Conrad Sauer Dr",
    "sg:city":"Houston",
    "sg:classifiers":[
        {
            "category":"Professional",
            "subcategory":"Printing & Photocopies",
            "type":"Services"
        }
    ],
    "sg:phone":"+1 713 863 0333",
    "sg:postcode":"77043",
    "sg:province":"TX",
    "sg:tags":[
        "photocopying"
    ],
    "wof:name":"Med-Foto Extra Duplicating Co",
    "wof:placetype":"venue"
},
  "geometry": {"coordinates":[-95.54917500000001,29.79765],"type":"Point"}
}