{
  "type": "Feature",
  "properties": {
    "iso:country":"US",
    "sg:address":"224 Investment Loop",
    "sg:city":"Hutto",
    "sg:classifiers":[
        {
            "category":"Manufacturing",
            "subcategory":"Retail Goods",
            "type":"Manufacturing & Wholesale Goods"
        }
    ],
    "sg:phone":"+1 512 759 6830",
    "sg:postcode":"78634",
    "sg:province":"TX",
    "sg:tags":[
        "manufacturer"
    ],
    "sg:website":"www.work-benches.com",
    "wof:name":"Above Board Mfg",
    "wof:placetype":"venue"
},
  "geometry": {"coordinates":[-97.584383,30.537378],"type":"Point"}
}