{
  "type": "Feature",
  "properties": {
    "iso:country":"US",
    "sg:address":"221 Landry Ct",
    "sg:city":"Irving",
    "sg:classifiers":[
        {
            "category":"Professional",
            "subcategory":"Management & Consulting",
            "type":"Services"
        }
    ],
    "sg:phone":"+1 972 831 0087",
    "sg:postcode":"75063",
    "sg:province":"TX",
    "sg:tags":[
        "business"
    ],
    "wof:name":"Jgp Consultants",
    "wof:placetype":"venue"
},
  "geometry": {"coordinates":[-96.943708,32.944208],"type":"Point"}
}