{
  "type": "Feature",
  "properties": {
    "iso:country":"US",
    "sg:address":"1110 Berry St",
    "sg:city":"Llano",
    "sg:classifiers":[
        {
            "category":"Social Services",
            "type":"Services"
        }
    ],
    "sg:phone":"+1 325 247 4662",
    "sg:postcode":"78643",
    "sg:province":"TX",
    "wof:name":"Llano Multi-Service Center",
    "wof:placetype":"venue"
},
  "geometry": {"coordinates":[-98.677137,30.747139],"type":"Point"}
}