{
  "type": "Feature",
  "properties": {
    "iso:country":"US",
    "sg:address":"114 Moody St",
    "sg:city":"Houston",
    "sg:classifiers":[
        {
            "category":"Shopping",
            "subcategory":"Hobbies, Toys, & Games",
            "type":"Retail Goods"
        }
    ],
    "sg:phone":"+1 325 347 6858",
    "sg:postcode":"77009",
    "sg:province":"TX",
    "sg:tags":[
        "craft",
        "supply"
    ],
    "wof:name":"Celebration Crafts",
    "wof:placetype":"venue"
},
  "geometry": {"coordinates":[-95.367639,29.80408],"type":"Point"}
}