{
  "type": "Feature",
  "properties": {
    "iso:country":"US",
    "sg:address":"4350 E Hwy 6",
    "sg:city":"Alvin",
    "sg:classifiers":[
        {
            "category":"Wholesale",
            "subcategory":"Auto Parts",
            "type":"Manufacturing & Wholesale Goods"
        }
    ],
    "sg:phone":"+1 281 331 3314",
    "sg:postcode":"77511",
    "sg:province":"TX",
    "sg:tags":[
        "automobile",
        "rebuilt"
    ],
    "wof:name":"Lee's Auto Parts",
    "wof:placetype":"venue"
},
  "geometry": {"coordinates":[-95.197467,29.409863],"type":"Point"}
}