{
  "type": "Feature",
  "properties": {
    "iso:country":"US",
    "sg:address":"7600 Burnet Rd Ste 515",
    "sg:city":"Austin",
    "sg:classifiers":[
        {
            "category":"Health Services",
            "subcategory":"Doctor",
            "type":"Services"
        }
    ],
    "sg:phone":"+1 512 358 0500",
    "sg:postcode":"78757",
    "sg:province":"TX",
    "sg:tags":[
        "medicine",
        "sport"
    ],
    "sg:website":"www.sportsandspineassociates.com",
    "wof:name":"Sports & Spine Associates",
    "wof:placetype":"venue"
},
  "geometry": {"coordinates":[-97.733997,30.353372],"type":"Point"}
}