{
  "type": "Feature",
  "properties": {
    "iso:country":"US",
    "sg:address":"1001 E Jackson Ave",
    "sg:city":"Mcallen",
    "sg:classifiers":[
        {
            "category":"Recreation",
            "type":"Entertainment"
        }
    ],
    "sg:phone":"+1 956 631 6171",
    "sg:postcode":"78501",
    "sg:province":"TX",
    "sg:tags":[
        "bingo",
        "game"
    ],
    "wof:name":"El Bingo Grande",
    "wof:placetype":"venue"
},
  "geometry": {"coordinates":[-98.21144099999999,26.191581],"type":"Point"}
}