{
  "type": "Feature",
  "properties": {
    "iso:country":"US",
    "sg:address":"1820 US Hwy 80",
    "sg:city":"Longview",
    "sg:classifiers":[
        {
            "category":"Freight",
            "type":"Transportation"
        }
    ],
    "sg:phone":"+1 903 297 5535",
    "sg:postcode":"75604",
    "sg:province":"TX",
    "sg:tags":[
        "dry",
        "bulk",
        "trucking"
    ],
    "wof:name":"Sun Co",
    "wof:placetype":"venue"
},
  "geometry": {"coordinates":[-94.776623,32.50522],"type":"Point"}
}