{
  "type": "Feature",
  "properties": {
    "iso:country":"US",
    "sg:address":"4408 Main St",
    "sg:city":"Dallas",
    "sg:classifiers":[
        {
            "category":"Autos & Motor Vehicles",
            "subcategory":"Automobile Sales",
            "type":"Retail Goods"
        }
    ],
    "sg:phone":"+1 214 824 5570",
    "sg:postcode":"75226",
    "sg:province":"TX",
    "sg:tags":[
        "car",
        "dealer"
    ],
    "wof:name":"Auto Buses Adame",
    "wof:placetype":"venue"
},
  "geometry": {"coordinates":[-96.769052,32.790046],"type":"Point"}
}