{
  "type": "Feature",
  "properties": {
    "iso:country":"US",
    "sg:address":"728 Ash St",
    "sg:city":"Burleson",
    "sg:classifiers":[
        {
            "category":"Building & Trades",
            "subcategory":"Electrical",
            "type":"Services"
        }
    ],
    "sg:phone":"+1 817 295 4752",
    "sg:postcode":"76028",
    "sg:province":"TX",
    "sg:tags":[
        "electrician"
    ],
    "wof:name":"Roper Electric",
    "wof:placetype":"venue"
},
  "geometry": {"coordinates":[-97.335297,32.530701],"type":"Point"}
}