{
  "type": "Feature",
  "properties": {
    "iso:country":"US",
    "sg:address":"1517 Texas Ave S",
    "sg:city":"College Station",
    "sg:classifiers":[
        {
            "category":"Shopping",
            "subcategory":"Discount & Variety Stores",
            "type":"Retail Goods"
        }
    ],
    "sg:phone":"+1 979 693 2420",
    "sg:postcode":"77840",
    "sg:province":"TX",
    "wof:name":"Dollar Tree",
    "wof:placetype":"venue"
},
  "geometry": {"coordinates":[-96.321697,30.617337],"type":"Point"}
}