{
  "type": "Feature",
  "properties": {
    "iso:country":"US",
    "sg:address":"209 N Edward Gray St",
    "sg:city":"San Marcos",
    "sg:classifiers":[
        {
            "category":"Retail",
            "subcategory":"Laundry & Dry Cleaning",
            "type":"Services"
        }
    ],
    "sg:phone":"+1 512 396 1242",
    "sg:postcode":"78666",
    "sg:province":"TX",
    "wof:name":"Jack Brown Cleaners",
    "wof:placetype":"venue"
},
  "geometry": {"coordinates":[-97.93908399999999,29.88443],"type":"Point"}
}