{
  "type": "Feature",
  "properties": {
    "iso:country":"US",
    "sg:address":"4235 Brandemere Way St",
    "sg:city":"Houston",
    "sg:classifiers":[
        {
            "category":"Professional",
            "subcategory":"Business Services",
            "type":"Services"
        }
    ],
    "sg:phone":"+1 281 440 9246",
    "sg:postcode":"77066",
    "sg:province":"TX",
    "wof:name":"Iniversal Safaris",
    "wof:placetype":"venue"
},
  "geometry": {"coordinates":[-95.491714,29.971264],"type":"Point"}
}