{
  "type": "Feature",
  "properties": {
    "iso:country":"US",
    "sg:address":"1005 N Sam Rayburn Fwy",
    "sg:city":"Sherman",
    "sg:classifiers":[
        {
            "category":"Retail",
            "subcategory":"Portrait Studio",
            "type":"Services"
        }
    ],
    "sg:phone":"+1 903 893 4882",
    "sg:postcode":"75090",
    "sg:province":"TX",
    "sg:tags":[
        "photographer"
    ],
    "wof:name":"ODEE'S Photography",
    "wof:placetype":"venue"
},
  "geometry": {"coordinates":[-96.612545,33.646319],"type":"Point"}
}