{
  "type": "Feature",
  "properties": {
    "iso:country":"US",
    "sg:address":"1213 Grant St",
    "sg:city":"Laredo",
    "sg:classifiers":[
        {
            "category":"Professional",
            "subcategory":"Engineering",
            "type":"Services"
        }
    ],
    "sg:phone":"+1 956 724 6885",
    "sg:postcode":"78040",
    "sg:province":"TX",
    "wof:name":"Sky Aviation Inc",
    "wof:placetype":"venue"
},
  "geometry": {"coordinates":[-99.508392,27.50276],"type":"Point"}
}