{
  "type": "Feature",
  "properties": {
    "iso:country":"US",
    "sg:address":"3502 Eldorado Trail",
    "sg:city":"Austin",
    "sg:classifiers":[
        {
            "category":"Real Estate",
            "subcategory":"Real Estate Services",
            "type":"Services"
        }
    ],
    "sg:phone":"+1 512 934 8789",
    "sg:postcode":"78739",
    "sg:province":"TX",
    "sg:tags":[
        "home",
        "inspector"
    ],
    "wof:name":"Phillips Property Inspections",
    "wof:placetype":"venue"
},
  "geometry": {"coordinates":[-97.864892,30.163322],"type":"Point"}
}