{
  "type": "Feature",
  "properties": {
    "iso:country":"US",
    "sg:address":"1705 Bonham Ave",
    "sg:city":"Odessa",
    "sg:classifiers":[
        {
            "category":"Insurance",
            "subcategory":"Insurance Agent",
            "type":"Services"
        }
    ],
    "sg:phone":"+1 432 362 6900",
    "sg:postcode":"79761",
    "sg:province":"TX",
    "wof:name":"Steve Leftwich Insurance Agcy",
    "wof:placetype":"venue"
},
  "geometry": {"coordinates":[-102.349889,31.870046],"type":"Point"}
}