{
  "type": "Feature",
  "properties": {
    "iso:country":"US",
    "sg:address":"12222 Cliffgate Dr",
    "sg:city":"Houston",
    "sg:classifiers":[
        {
            "category":"Building & Trades",
            "subcategory":"Construction",
            "type":"Services"
        }
    ],
    "sg:phone":"+1 713 392 6951",
    "sg:postcode":"77072",
    "sg:province":"TX",
    "sg:tags":[
        "house"
    ],
    "wof:name":"J A Contracting",
    "wof:placetype":"venue"
},
  "geometry": {"coordinates":[-95.59546899999999,29.685909],"type":"Point"}
}