{
  "type": "Feature",
  "properties": {
    "iso:country":"US",
    "sg:address":"400 S Oklahoma Ave",
    "sg:city":"Weslaco",
    "sg:classifiers":[
        {
            "category":"Education",
            "subcategory":"School",
            "type":"Public Place"
        }
    ],
    "sg:phone":"+1 956 969 6875",
    "sg:postcode":"78596",
    "sg:province":"TX",
    "wof:name":"Stephen F Austin Erly Child",
    "wof:placetype":"venue"
},
  "geometry": {"coordinates":[-97.994902,26.157718],"type":"Point"}
}