{
  "type": "Feature",
  "properties": {
    "iso:country":"US",
    "sg:address":"1601 Nandina Dr",
    "sg:city":"Arlington",
    "sg:classifiers":[
        {
            "category":"Professional",
            "subcategory":"Business Services",
            "type":"Services"
        }
    ],
    "sg:phone":"+1 817 784 9449",
    "sg:postcode":"76014",
    "sg:province":"TX",
    "sg:tags":[
        "auto",
        "transporter"
    ],
    "wof:name":"Back Door Xpress",
    "wof:placetype":"venue"
},
  "geometry": {"coordinates":[-97.08674499999999,32.682054],"type":"Point"}
}