{
  "type": "Feature",
  "properties": {
    "iso:country":"US",
    "sg:address":"13087 State Hwy 110",
    "sg:city":"Tyler",
    "sg:classifiers":[
        {
            "category":"Autos & Motor Vehicles",
            "subcategory":"Auto Supplies",
            "type":"Retail Goods"
        }
    ],
    "sg:phone":"+1 903 882 1885",
    "sg:postcode":"75704",
    "sg:province":"TX",
    "wof:name":"Ashtons Tire Barn",
    "wof:placetype":"venue"
},
  "geometry": {"coordinates":[-95.46909599999999,32.457344],"type":"Point"}
}