{
  "type": "Feature",
  "properties": {
    "iso:country":"US",
    "sg:address":"613 S Expressway 83",
    "sg:city":"Harlingen",
    "sg:classifiers":[
        {
            "category":"Shopping",
            "subcategory":"Florist",
            "type":"Retail Goods"
        },
        {
            "category":"Deli",
            "type":"Food & Drink"
        },
        {
            "category":"Food & Beverages",
            "subcategory":"Supermarket",
            "type":"Retail Goods"
        },
        {
            "category":"Shopping",
            "subcategory":"Pharmacy",
            "type":"Retail Goods"
        },
        {
            "category":"Bakery",
            "type":"Food & Drink"
        },
        {
            "category":"Food & Beverages",
            "subcategory":"Groceries & Convenience Stores",
            "type":"Retail Goods"
        }
    ],
    "sg:postcode":"78550",
    "sg:province":"TX",
    "sg:tags":[
        "wellness",
        "product",
        "health",
        "delicatessen",
        "super"
    ],
    "sg:website":"http://www.heb.com",
    "wof:name":"H-E-B",
    "wof:placetype":"venue"
},
  "geometry": {"coordinates":[-97.716926,26.18866],"type":"Point"}
}