{
  "type": "Feature",
  "properties": {
    "iso:country":"US",
    "sg:address":"4421 Jerri Ln",
    "sg:city":"Haltom City",
    "sg:classifiers":[
        {
            "category":"Organizations",
            "subcategory":"Religious Organization",
            "type":"Services"
        }
    ],
    "sg:phone":"+1 817 838 9914",
    "sg:postcode":"76117",
    "sg:province":"TX",
    "wof:name":"Cornerstone Full Gospel",
    "wof:placetype":"venue"
},
  "geometry": {"coordinates":[-97.28262100000001,32.817092],"type":"Point"}
}