{
  "type": "Feature",
  "properties": {
    "iso:country":"US",
    "sg:address":"2 N 5th St",
    "sg:city":"Temple",
    "sg:classifiers":[
        {
            "category":"Organizations",
            "subcategory":"Professional Association",
            "type":"Services"
        }
    ],
    "sg:phone":"+1 254 773 2105",
    "sg:postcode":"76501",
    "sg:province":"TX",
    "sg:tags":[
        "chambers",
        "commerce"
    ],
    "sg:website":"www.templetx.org",
    "wof:name":"Temple Chamber Of Commerce",
    "wof:placetype":"venue"
},
  "geometry": {"coordinates":[-97.343739,31.098454],"type":"Point"}
}