{
  "type": "Feature",
  "properties": {
    "iso:country":"US",
    "sg:address":"800 Pawnee Ave",
    "sg:city":"Rule",
    "sg:classifiers":[
        {
            "category":"Building & Trades",
            "subcategory":"Construction",
            "type":"Services"
        }
    ],
    "sg:phone":"+1 940 997 2147",
    "sg:postcode":"79547",
    "sg:province":"TX",
    "sg:tags":[
        "carpentry",
        "contractor"
    ],
    "wof:name":"Carreon Carpentry",
    "wof:placetype":"venue"
},
  "geometry": {"coordinates":[-99.89146,33.18163],"type":"Point"}
}