{
  "type": "Feature",
  "properties": {
    "iso:country":"US",
    "sg:address":"1110 Visa Rd",
    "sg:city":"El Paso",
    "sg:classifiers":[
        {
            "category":"Freight",
            "type":"Transportation"
        }
    ],
    "sg:phone":"+1 915 872 1009",
    "sg:postcode":"79927",
    "sg:province":"TX",
    "sg:tags":[
        "delivery"
    ],
    "wof:name":"Star Delivery Svc",
    "wof:placetype":"venue"
},
  "geometry": {"coordinates":[-106.236952,31.653654],"type":"Point"}
}