{
  "type": "Feature",
  "properties": {
    "iso:country":"US",
    "sg:address":"8721 5th St",
    "sg:city":"Frisco",
    "sg:classifiers":[
        {
            "category":"Real Estate",
            "subcategory":"Surveying",
            "type":"Services"
        }
    ],
    "sg:phone":"+1 214 387 8000",
    "sg:postcode":"75034",
    "sg:province":"TX",
    "wof:name":"Wier & Associates",
    "wof:placetype":"venue"
},
  "geometry": {"coordinates":[-96.824319,33.149355],"type":"Point"}
}