{
  "type": "Feature",
  "properties": {
    "iso:country":"US",
    "sg:address":"206 W 1st St",
    "sg:city":"Dumas",
    "sg:classifiers":[
        {
            "category":"Food & Beverages",
            "subcategory":"Bakery",
            "type":"Retail Goods"
        }
    ],
    "sg:phone":"+1 806 935 7178",
    "sg:postcode":"79029",
    "sg:province":"TX",
    "wof:name":"Sweets N Memories",
    "wof:placetype":"venue"
},
  "geometry": {"coordinates":[-101.97589499999999,35.865462],"type":"Point"}
}