{
  "type": "Feature",
  "properties": {
    "iso:country":"US",
    "sg:address":"3 Periwinkle Dr",
    "sg:city":"Wichita Falls",
    "sg:classifiers":[
        {
            "category":"Health Services",
            "subcategory":"Nursing And Care Facility",
            "type":"Services"
        }
    ],
    "sg:phone":"+1 940 696 2252",
    "sg:postcode":"76310",
    "sg:province":"TX",
    "wof:name":"C H Snowden LLC",
    "wof:placetype":"venue"
},
  "geometry": {"coordinates":[-98.575461,33.846248],"type":"Point"}
}