{
  "type": "Feature",
  "properties": {
    "iso:country":"US",
    "sg:address":"7901 Pat Booker Rd",
    "sg:city":"San Antonio",
    "sg:classifiers":[
        {
            "category":"Cinema",
            "subcategory":"Movie Theater",
            "type":"Entertainment"
        }
    ],
    "sg:phone":"+1 210 657 4480",
    "sg:postcode":"78233",
    "sg:province":"TX",
    "wof:name":"Live Oak 18",
    "wof:placetype":"venue"
},
  "geometry": {"coordinates":[-98.329449,29.561605],"type":"Point"}
}