{
  "type": "Feature",
  "properties": {
    "iso:country":"US",
    "sg:address":"5900 Westslope Dr",
    "sg:city":"Austin",
    "sg:classifiers":[
        {
            "category":"Professional",
            "subcategory":"Business Services",
            "type":"Services"
        }
    ],
    "sg:phone":"+1 512 454 8403",
    "sg:postcode":"78731",
    "sg:province":"TX",
    "wof:name":"Andrea Allen Interiors",
    "wof:placetype":"venue"
},
  "geometry": {"coordinates":[-97.782831,30.345538],"type":"Point"}
}