{
  "type": "Feature",
  "properties": {
    "iso:country":"US",
    "sg:address":"400 Center Ridge Dr",
    "sg:city":"Austin",
    "sg:classifiers":[
        {
            "category":"Education",
            "subcategory":"School",
            "type":"Public Place"
        }
    ],
    "sg:phone":"+1 512 989 5300",
    "sg:postcode":"78753",
    "sg:province":"TX",
    "sg:tags":[
        "k-",
        "private"
    ],
    "wof:name":"Pearson Educ Measurement",
    "wof:placetype":"venue"
},
  "geometry": {"coordinates":[-97.663467,30.414339],"type":"Point"}
}