{
  "type": "Feature",
  "properties": {
    "iso:country":"US",
    "sg:address":"1331 Cumberland St",
    "sg:city":"Vernon",
    "sg:classifiers":[
        {
            "category":"Wholesale",
            "subcategory":"Auto Parts",
            "type":"Manufacturing & Wholesale Goods"
        }
    ],
    "sg:phone":"+1 940 552 8080",
    "sg:postcode":"76384",
    "sg:province":"TX",
    "sg:tags":[
        "farm",
        "suppl",
        "supply"
    ],
    "wof:name":"Red River Ranch Supply",
    "wof:placetype":"venue"
},
  "geometry": {"coordinates":[-99.28330699999999,34.157154],"type":"Point"}
}