{
  "type": "Feature",
  "properties": {
    "iso:country":"US",
    "sg:address":"1408 Longhorn Trl",
    "sg:city":"Crowley",
    "sg:classifiers":[
        {
            "category":"Real Estate",
            "subcategory":"Real Estate Operator",
            "type":"Services"
        }
    ],
    "sg:phone":"+1 817 297 4776",
    "sg:postcode":"76036",
    "sg:province":"TX",
    "sg:tags":[
        "apartment"
    ],
    "wof:name":"St Charles Place Ltd",
    "wof:placetype":"venue"
},
  "geometry": {"coordinates":[-97.38069900000001,32.574799],"type":"Point"}
}