{
  "type": "Feature",
  "properties": {
    "iso:country":"US",
    "sg:address":"3400 S Georgia St",
    "sg:city":"Amarillo",
    "sg:classifiers":[
        {
            "category":"Food & Beverages",
            "subcategory":"Specialty",
            "type":"Retail Goods"
        },
        {
            "category":"Food & Beverages",
            "subcategory":"Groceries & Convenience Stores",
            "type":"Retail Goods"
        }
    ],
    "sg:phone":"+1 806 374 6386",
    "sg:postcode":"79109",
    "sg:province":"TX",
    "sg:tags":[
        "grocers-specialty"
    ],
    "wof:name":"Star Food Mart",
    "wof:placetype":"venue"
},
  "geometry": {"coordinates":[-101.866219,35.178371],"type":"Point"}
}