{
  "type": "Feature",
  "properties": {
    "iso:country":"US",
    "sg:address":"7 Dellforest Ct",
    "sg:city":"Spring",
    "sg:classifiers":[
        {
            "category":"Manufacturing",
            "subcategory":"Tools & Machinery",
            "type":"Manufacturing & Wholesale Goods"
        }
    ],
    "sg:phone":"+1 281 296 6333",
    "sg:postcode":"77381",
    "sg:province":"TX",
    "sg:tags":[
        "devices",
        "mfg"
    ],
    "wof:name":"Gastech Inc",
    "wof:placetype":"venue"
},
  "geometry": {"coordinates":[-95.499331,30.162788],"type":"Point"}
}