{
  "type": "Feature",
  "properties": {
    "iso:country":"US",
    "sg:address":"1417 N Park St",
    "sg:city":"Killeen",
    "sg:classifiers":[
        {
            "category":"Professional",
            "type":"Services"
        }
    ],
    "sg:phone":"+1 254 616 5005",
    "sg:postcode":"76541",
    "sg:province":"TX",
    "wof:name":"Merandas",
    "wof:placetype":"venue"
},
  "geometry": {"coordinates":[-97.728295,31.130519],"type":"Point"}
}