{
  "type": "Feature",
  "properties": {
    "iso:country":"US",
    "sg:address":"505 N Key Ave",
    "sg:city":"Lampasas",
    "sg:classifiers":[
        {
            "category":"Building & Trades",
            "subcategory":"Construction",
            "type":"Services"
        }
    ],
    "sg:phone":"+1 512 556 3602",
    "sg:postcode":"76550",
    "sg:province":"TX",
    "sg:tags":[
        "contracting",
        "remodeling",
        "roof"
    ],
    "wof:name":"Baxter Witcher",
    "wof:placetype":"venue"
},
  "geometry": {"coordinates":[-98.185323,31.071674],"type":"Point"}
}