{
  "type": "Feature",
  "properties": {
    "iso:country":"US",
    "sg:address":"403 E Blackjack St",
    "sg:city":"Dublin",
    "sg:classifiers":[
        {
            "category":"Museum",
            "type":"Entertainment"
        }
    ],
    "sg:phone":"+1 254 445 4210",
    "sg:postcode":"76446",
    "sg:province":"TX",
    "wof:name":"Dr Pepper Museum Studies",
    "wof:placetype":"venue"
},
  "geometry": {"coordinates":[-98.3379,32.08401],"type":"Point"}
}