{
  "type": "Feature",
  "properties": {
    "iso:country":"US",
    "sg:address":"730 Liberty Ave",
    "sg:city":"Beaumont",
    "sg:classifiers":[
        {
            "category":"Restaurant",
            "type":"Food & Drink"
        }
    ],
    "sg:phone":"+1 409 835 9652",
    "sg:postcode":"77701",
    "sg:province":"TX",
    "sg:tags":[
        "eating"
    ],
    "wof:name":"Quality Cafe",
    "wof:placetype":"venue"
},
  "geometry": {"coordinates":[-94.10146899999999,30.08416],"type":"Point"}
}