{
  "type": "Feature",
  "properties": {
    "iso:country":"US",
    "sg:address":"13 S Sherwood Dr",
    "sg:city":"Belton",
    "sg:classifiers":[
        {
            "category":"Professional",
            "type":"Services"
        }
    ],
    "sg:phone":"+1 254 780 2194",
    "sg:postcode":"76513",
    "sg:province":"TX",
    "wof:name":"Van R Savage",
    "wof:placetype":"venue"
},
  "geometry": {"coordinates":[-97.477065,31.153486],"type":"Point"}
}