{
  "type": "Feature",
  "properties": {
    "iso:country":"US",
    "sg:address":"319 W Hollywood Ave",
    "sg:city":"San Antonio",
    "sg:classifiers":[
        {
            "category":"Banks & Credit Unions",
            "subcategory":"Financial Services",
            "type":"Services"
        }
    ],
    "sg:phone":"+1 210 732 3867",
    "sg:postcode":"78212",
    "sg:province":"TX",
    "sg:tags":[
        "trust",
        "management"
    ],
    "wof:name":"Hardberger Partners Ltd",
    "wof:placetype":"venue"
},
  "geometry": {"coordinates":[-98.498992,29.464199],"type":"Point"}
}