{
  "type": "Feature",
  "properties": {
    "iso:country":"US",
    "sg:address":"4111 Gilmer Rd",
    "sg:city":"Longview",
    "sg:classifiers":[
        {
            "category":"Shopping",
            "subcategory":"Bicycles & Sporting Goods",
            "type":"Retail Goods"
        }
    ],
    "sg:phone":"+1 903 759 0638",
    "sg:postcode":"75604",
    "sg:province":"TX",
    "sg:website":"www.winchestersports.com",
    "wof:name":"Winchester's Sportsmans Outfit",
    "wof:placetype":"venue"
},
  "geometry": {"coordinates":[-94.800421,32.558038],"type":"Point"}
}