{
  "type": "Feature",
  "properties": {
    "iso:country":"US",
    "sg:address":"126 State St",
    "sg:city":"Winters",
    "sg:classifiers":[
        {
            "category":"Health Services",
            "subcategory":"Hospital",
            "type":"Services"
        }
    ],
    "sg:phone":"+1 325 754 5591",
    "sg:postcode":"79567",
    "sg:province":"TX",
    "sg:tags":[
        "mental"
    ],
    "wof:name":"West Texas Ctr For MHMR",
    "wof:placetype":"venue"
},
  "geometry": {"coordinates":[-99.963858,31.956927],"type":"Point"}
}