{
  "type": "Feature",
  "properties": {
    "iso:country":"US",
    "sg:address":"551 FM 148",
    "sg:city":"Terrell",
    "sg:classifiers":[
        {
            "category":"Retail",
            "subcategory":"Veterinary Services",
            "type":"Services"
        }
    ],
    "sg:phone":"+1 972 524 5300",
    "sg:postcode":"75160",
    "sg:province":"TX",
    "sg:tags":[
        "veterinarian"
    ],
    "wof:name":"Risinger Veterinary Hospital",
    "wof:placetype":"venue"
},
  "geometry": {"coordinates":[-96.314849,32.724738],"type":"Point"}
}