{
  "type": "Feature",
  "properties": {
    "iso:country":"US",
    "sg:address":"100 Glenborough Dr",
    "sg:city":"Houston",
    "sg:classifiers":[
        {
            "category":"Real Estate",
            "subcategory":"Real Estate Operator",
            "type":"Services"
        }
    ],
    "sg:phone":"+1 281 872 7177",
    "sg:postcode":"77067",
    "sg:province":"TX",
    "sg:tags":[
        "building",
        "nonresidential"
    ],
    "wof:name":"Equity Office",
    "wof:placetype":"venue"
},
  "geometry": {"coordinates":[-95.418419,29.950986],"type":"Point"}
}