{
  "type": "Feature",
  "properties": {
    "iso:country":"US",
    "sg:address":"709 W Pioneer Pkwy",
    "sg:city":"Grand Prairie",
    "sg:classifiers":[
        {
            "category":"Restaurant",
            "type":"Food & Drink"
        }
    ],
    "sg:phone":"+1 972 264 5200",
    "sg:postcode":"75051",
    "sg:province":"TX",
    "wof:name":"Pollo Salsa",
    "wof:placetype":"venue"
},
  "geometry": {"coordinates":[-97.01391,32.709573],"type":"Point"}
}