{
  "type": "Feature",
  "properties": {
    "iso:country":"US",
    "sg:address":"19062 FM 1485",
    "sg:city":"New Caney",
    "sg:classifiers":[
        {
            "category":"Wholesale",
            "subcategory":"Metals & Minerals",
            "type":"Manufacturing & Wholesale Goods"
        }
    ],
    "sg:phone":"+1 281 689 7941",
    "sg:postcode":"77357",
    "sg:province":"TX",
    "sg:tags":[
        "pipe"
    ],
    "wof:name":"Ok Pipe & Fittings Inc",
    "wof:placetype":"venue"
},
  "geometry": {"coordinates":[-95.238309,30.170795],"type":"Point"}
}