{
  "type": "Feature",
  "properties": {
    "iso:country":"US",
    "sg:address":"2311 Culpeper Dr",
    "sg:city":"Midland",
    "sg:classifiers":[
        {
            "category":"Arts & Performance",
            "subcategory":"Theater",
            "type":"Entertainment"
        }
    ],
    "sg:phone":"+1 432 570 4384",
    "sg:postcode":"79705",
    "sg:province":"TX",
    "wof:name":"Juggling For Success",
    "wof:placetype":"venue"
},
  "geometry": {"coordinates":[-102.112973,32.024493],"type":"Point"}
}