{
  "type": "Feature",
  "properties": {
    "iso:country":"US",
    "sg:address":"210 Aldine Bender Rd",
    "sg:city":"Houston",
    "sg:classifiers":[
        {
            "category":"Restaurant",
            "type":"Food & Drink"
        }
    ],
    "sg:phone":"+1 281 999 4149",
    "sg:postcode":"77060",
    "sg:province":"TX",
    "sg:tags":[
        "mexican"
    ],
    "wof:name":"El Asadero Mexican Restaurant",
    "wof:placetype":"venue"
},
  "geometry": {"coordinates":[-95.4011,29.9317],"type":"Point"}
}