{
  "type": "Feature",
  "properties": {
    "iso:country":"US",
    "sg:address":"14919 Stuebner Airline Rd",
    "sg:city":"Houston",
    "sg:classifiers":[
        {
            "category":"Manufacturing",
            "subcategory":"Printing",
            "type":"Manufacturing & Wholesale Goods"
        }
    ],
    "sg:phone":"+1 281 444 0001",
    "sg:postcode":"77069",
    "sg:province":"TX",
    "sg:tags":[
        "machine",
        "company",
        "bank",
        "teller"
    ],
    "wof:name":"Apple Press",
    "wof:placetype":"venue"
},
  "geometry": {"coordinates":[-95.50683100000001,29.999427],"type":"Point"}
}