{
  "type": "Feature",
  "properties": {
    "iso:country":"US",
    "sg:address":"4905 Great Divide Dr",
    "sg:city":"Austin",
    "sg:classifiers":[
        {
            "category":"Building & Trades",
            "subcategory":"Construction",
            "type":"Services"
        }
    ],
    "sg:phone":"+1 512 263 1062",
    "sg:postcode":"78738",
    "sg:province":"TX",
    "sg:tags":[
        "house",
        "nonresidential"
    ],
    "wof:name":"A&M Concept Builders LLC",
    "wof:placetype":"venue"
},
  "geometry": {"coordinates":[-97.95773699999999,30.304762],"type":"Point"}
}