{
  "type": "Feature",
  "properties": {
    "iso:country":"US",
    "sg:address":"3001 N Trade Days Blvd",
    "sg:city":"Canton",
    "sg:classifiers":[
        {
            "category":"Travel",
            "subcategory":"Hotels & Motels",
            "type":"Entertainment"
        }
    ],
    "sg:phone":"+1 903 567 0455",
    "sg:postcode":"75103",
    "sg:province":"TX",
    "wof:name":"Luxury Suites",
    "wof:placetype":"venue"
},
  "geometry": {"coordinates":[-95.854607,32.580444],"type":"Point"}
}