{
  "type": "Feature",
  "properties": {
    "iso:country":"US",
    "sg:address":"1105 Cheryl",
    "sg:city":"Whitehouse",
    "sg:classifiers":[
        {
            "category":"Education",
            "subcategory":"School",
            "type":"Public Place"
        }
    ],
    "sg:phone":"+1 903 839 6162",
    "sg:postcode":"75791",
    "sg:province":"TX",
    "wof:name":"Pinewood Schools Inc",
    "wof:placetype":"venue"
},
  "geometry": {"coordinates":[-95.209301,32.225771],"type":"Point"}
}