{
  "type": "Feature",
  "properties": {
    "iso:country":"US",
    "sg:address":"2315 Sherwood Way",
    "sg:city":"San Angelo",
    "sg:classifiers":[
        {
            "category":"Retail",
            "subcategory":"Auto Repair",
            "type":"Services"
        }
    ],
    "sg:phone":"+1 325 944 3412",
    "sg:postcode":"76901",
    "sg:province":"TX",
    "sg:tags":[
        "body"
    ],
    "wof:name":"Angelo Dent Removal",
    "wof:placetype":"venue"
},
  "geometry": {"coordinates":[-100.468194,31.451514],"type":"Point"}
}