{
  "type": "Feature",
  "properties": {
    "iso:country":"US",
    "sg:address":"1106 Amarillo St",
    "sg:city":"Plainview",
    "sg:classifiers":[
        {
            "category":"Building & Trades",
            "subcategory":"Landscaping Services",
            "type":"Services"
        }
    ],
    "sg:phone":"+1 806 296 0293",
    "sg:postcode":"79072",
    "sg:province":"TX",
    "sg:tags":[
        "landscape"
    ],
    "wof:name":"Melton Agriculture LLC",
    "wof:placetype":"venue"
},
  "geometry": {"coordinates":[-101.736891,34.193739],"type":"Point"}
}