{
  "type": "Feature",
  "properties": {
    "iso:country":"US",
    "sg:address":"3114 Redwood Shadows",
    "sg:city":"Houston",
    "sg:classifiers":[
        {
            "category":"Professional",
            "subcategory":"Management & Consulting",
            "type":"Services"
        }
    ],
    "sg:phone":"+1 281 578 3399",
    "sg:postcode":"77084",
    "sg:province":"TX",
    "wof:name":"Howlands International Inc",
    "wof:placetype":"venue"
},
  "geometry": {"coordinates":[-95.697237,29.813878],"type":"Point"}
}