{
  "type": "Feature",
  "properties": {
    "iso:country":"US",
    "sg:address":"2121 E Oltorf St",
    "sg:city":"Austin",
    "sg:classifiers":[
        {
            "category":"Professional",
            "type":"Services"
        }
    ],
    "sg:phone":"+1 512 442 6261",
    "sg:postcode":"78741",
    "sg:province":"TX",
    "sg:tags":[
        "establishment"
    ],
    "wof:name":"Courrier Works",
    "wof:placetype":"venue"
},
  "geometry": {"coordinates":[-97.732601,30.230492],"type":"Point"}
}