{
  "type": "Feature",
  "properties": {
    "iso:country":"US",
    "sg:address":"1231 Castroville Rd",
    "sg:city":"San Antonio",
    "sg:classifiers":[
        {
            "category":"Autos & Motor Vehicles",
            "subcategory":"Automobile Sales",
            "type":"Retail Goods"
        }
    ],
    "sg:phone":"+1 210 433 6323",
    "sg:postcode":"78237",
    "sg:province":"TX",
    "sg:tags":[
        "car",
        "used",
        "dealer"
    ],
    "wof:name":"L & S Auto Sales",
    "wof:placetype":"venue"
},
  "geometry": {"coordinates":[-98.55821,29.415721],"type":"Point"}
}