{
  "type": "Feature",
  "properties": {
    "iso:country":"US",
    "sg:address":"4100 FM 1960 Rd W",
    "sg:city":"Houston",
    "sg:classifiers":[
        {
            "category":"Restaurant",
            "type":"Food & Drink"
        }
    ],
    "sg:phone":"+1 281 586 2023",
    "sg:postcode":"77068",
    "sg:province":"TX",
    "sg:tags":[
        "japanese"
    ],
    "wof:name":"H B Japanese Steak House",
    "wof:placetype":"venue"
},
  "geometry": {"coordinates":[-95.457143,29.746889],"type":"Point"}
}