{
  "type": "Feature",
  "properties": {
    "iso:country":"US",
    "sg:address":"630 W Nasa Rd 1",
    "sg:city":"Webster",
    "sg:classifiers":[
        {
            "category":"Retail",
            "subcategory":"Auto Repair",
            "type":"Services"
        }
    ],
    "sg:phone":"+1 281 338 2201",
    "sg:postcode":"77598",
    "sg:province":"TX",
    "sg:tags":[
        "automotive"
    ],
    "wof:name":"Nas Car Lube",
    "wof:placetype":"venue"
},
  "geometry": {"coordinates":[-95.12304899999999,29.534298],"type":"Point"}
}