{
  "type": "Feature",
  "properties": {
    "iso:country":"US",
    "sg:address":"6400 Manchaca Rd",
    "sg:city":"Austin",
    "sg:classifiers":[
        {
            "category":"Insurance",
            "subcategory":"Insurance Agent",
            "type":"Services"
        },
        {
            "category":"Banks & Credit Unions",
            "subcategory":"Bank",
            "type":"Services"
        }
    ],
    "sg:phone":"+1 512 435 4545",
    "sg:postcode":"78745",
    "sg:province":"TX",
    "wof:name":"United Heritage Federal Cr Un",
    "wof:placetype":"venue"
},
  "geometry": {"coordinates":[-97.805863,30.207027],"type":"Point"}
}