{
  "type": "Feature",
  "properties": {
    "iso:country":"US",
    "sg:address":"776 Grant St",
    "sg:city":"Roma",
    "sg:classifiers":[
        {
            "category":"Communications",
            "type":"Services"
        }
    ],
    "sg:phone":"+1 956 849 3433",
    "sg:postcode":"78584",
    "sg:province":"TX",
    "sg:tags":[
        "communication"
    ],
    "wof:name":"B2b Communications",
    "wof:placetype":"venue"
},
  "geometry": {"coordinates":[-99.001372,26.401321],"type":"Point"}
}