{
  "type": "Feature",
  "properties": {
    "iso:country":"US",
    "sg:address":"11392 N Fm 148",
    "sg:city":"Terrell",
    "sg:classifiers":[
        {
            "category":"Autos & Motor Vehicles",
            "subcategory":"Automobile Sales",
            "type":"Retail Goods"
        }
    ],
    "sg:phone":"+1 972 563 4664",
    "sg:postcode":"75160",
    "sg:province":"TX",
    "sg:tags":[
        "car",
        "used"
    ],
    "wof:name":"Terrell Auto Depot Inc",
    "wof:placetype":"venue"
},
  "geometry": {"coordinates":[-96.328811,32.713707],"type":"Point"}
}