{
  "type": "Feature",
  "properties": {
    "iso:country":"US",
    "sg:address":"6420 Escondido Dr",
    "sg:city":"El Paso",
    "sg:classifiers":[
        {
            "category":"Insurance",
            "subcategory":"Insurance Agent",
            "type":"Services"
        }
    ],
    "sg:phone":"+1 915 845 5220",
    "sg:postcode":"79912",
    "sg:province":"TX",
    "wof:name":"Allstate Insurance",
    "wof:placetype":"venue"
},
  "geometry": {"coordinates":[-106.53550300000001,31.843519],"type":"Point"}
}