{
  "type": "Feature",
  "properties": {
    "iso:country":"US",
    "sg:address":"14838 Park Row",
    "sg:city":"Houston",
    "sg:classifiers":[
        {
            "category":"Personal",
            "subcategory":"Beauty Salon",
            "type":"Services"
        }
    ],
    "sg:phone":"+1 281 599 3070",
    "sg:postcode":"77084",
    "sg:province":"TX",
    "wof:name":"D & T Beauty Salon",
    "wof:placetype":"venue"
},
  "geometry": {"coordinates":[-95.645099,29.788046],"type":"Point"}
}