{
  "type": "Feature",
  "properties": {
    "iso:country":"US",
    "sg:address":"2971 Walnut Hill Ln",
    "sg:city":"Dallas",
    "sg:classifiers":[
        {
            "category":"Restaurant",
            "type":"Food & Drink"
        }
    ],
    "sg:phone":"+1 214 366 3443",
    "sg:postcode":"75229",
    "sg:province":"TX",
    "sg:tags":[
        "eating"
    ],
    "wof:name":"Tampico Comida Mexicana",
    "wof:placetype":"venue"
},
  "geometry": {"coordinates":[-96.878541,32.880991],"type":"Point"}
}