{
  "type": "Feature",
  "properties": {
    "iso:country":"US",
    "sg:address":"2063 N Town East Blvd",
    "sg:city":"Mesquite",
    "sg:classifiers":[
        {
            "category":"Home & Garden",
            "subcategory":"Furniture",
            "type":"Retail Goods"
        }
    ],
    "sg:phone":"+1 972 686 4066",
    "sg:postcode":"75150",
    "sg:province":"TX",
    "sg:tags":[
        "mattress"
    ],
    "wof:name":"Select Comfort Corp",
    "wof:placetype":"venue"
},
  "geometry": {"coordinates":[-96.634424,32.811276],"type":"Point"}
}