{
  "type": "Feature",
  "properties": {
    "iso:country":"US",
    "sg:address":"1426 Armadillo Dr",
    "sg:city":"Waco",
    "sg:classifiers":[
        {
            "category":"Retail",
            "subcategory":"Auto Repair",
            "type":"Services"
        }
    ],
    "sg:phone":"+1 254 666 7623",
    "sg:postcode":"76712",
    "sg:province":"TX",
    "sg:tags":[
        "automotive"
    ],
    "wof:name":"Halls Cen-Tex Wrecker Service",
    "wof:placetype":"venue"
},
  "geometry": {"coordinates":[-97.273833,31.451632],"type":"Point"}
}