{
  "type": "Feature",
  "properties": {
    "iso:country":"US",
    "sg:address":"3401 E 5th St",
    "sg:city":"Tyler",
    "sg:classifiers":[
        {
            "category":"Manufacturing",
            "subcategory":"Metals",
            "type":"Manufacturing & Wholesale Goods"
        }
    ],
    "sg:phone":"+1 903 566 0395",
    "sg:postcode":"75701",
    "sg:province":"TX",
    "sg:tags":[
        "ornamental",
        "work"
    ],
    "wof:name":"Nowlins Ornamental Iron Works",
    "wof:placetype":"venue"
},
  "geometry": {"coordinates":[-95.258455,32.332457],"type":"Point"}
}