{
  "type": "Feature",
  "properties": {
    "iso:country":"US",
    "sg:address":"1102 Barkley St",
    "sg:city":"Spearman",
    "sg:classifiers":[
        {
            "category":"Professional",
            "subcategory":"Computer Services",
            "type":"Services"
        }
    ],
    "sg:phone":"+1 806 659 2045",
    "sg:postcode":"79081",
    "sg:province":"TX",
    "sg:tags":[
        "internet"
    ],
    "wof:name":"Antden Online Svc",
    "wof:placetype":"venue"
},
  "geometry": {"coordinates":[-101.19456700000001,36.186247],"type":"Point"}
}