{
  "type": "Feature",
  "properties": {
    "iso:country":"US",
    "sg:address":"2027 N Jackson St",
    "sg:city":"Jacksonville",
    "sg:classifiers":[
        {
            "category":"Social Services",
            "type":"Services"
        }
    ],
    "sg:phone":"+1 903 586 4425",
    "sg:postcode":"75766",
    "sg:province":"TX",
    "sg:tags":[
        "counseling"
    ],
    "wof:name":"Center For Family Counseling",
    "wof:placetype":"venue"
},
  "geometry": {"coordinates":[-95.275724,32.00014],"type":"Point"}
}