{
  "type": "Feature",
  "properties": {
    "iso:country":"US",
    "sg:address":"19218 Wildoats Dr",
    "sg:city":"Katy",
    "sg:classifiers":[
        {
            "category":"Professional",
            "subcategory":"Printing & Photocopies",
            "type":"Services"
        }
    ],
    "sg:phone":"+1 281 398 3267",
    "sg:postcode":"77449",
    "sg:province":"TX",
    "sg:tags":[
        "photocopying"
    ],
    "wof:name":"State Copier Co",
    "wof:placetype":"venue"
},
  "geometry": {"coordinates":[-95.70551399999999,29.82133],"type":"Point"}
}