{
  "type": "Feature",
  "properties": {
    "iso:country":"US",
    "sg:address":"1205 Lake St",
    "sg:city":"Fort Worth",
    "sg:classifiers":[
        {
            "category":"Organizations",
            "subcategory":"Non-profit Organization",
            "type":"Services"
        }
    ],
    "sg:phone":"+1 817 870 9082",
    "sg:postcode":"76102",
    "sg:province":"TX",
    "wof:name":"Reach",
    "wof:placetype":"venue"
},
  "geometry": {"coordinates":[-97.338955,32.746073],"type":"Point"}
}