{
  "type": "Feature",
  "properties": {
    "iso:country":"US",
    "sg:address":"3003 S Loop W # 505",
    "sg:city":"Houston",
    "sg:classifiers":[
        {
            "category":"Health Services",
            "subcategory":"Doctor",
            "type":"Services"
        }
    ],
    "sg:phone":"+1 713 218 9443",
    "sg:postcode":"77054",
    "sg:province":"TX",
    "wof:name":"Andres H Keichian, MD PA",
    "wof:placetype":"venue"
},
  "geometry": {"coordinates":[-95.425324,29.676062],"type":"Point"}
}