{
  "type": "Feature",
  "properties": {
    "iso:country":"US",
    "sg:address":"2108 S Houston Rd",
    "sg:city":"Pasadena",
    "sg:classifiers":[
        {
            "category":"Building & Trades",
            "subcategory":"Construction",
            "type":"Services"
        }
    ],
    "sg:phone":"+1 713 473 2058",
    "sg:postcode":"77502",
    "sg:province":"TX",
    "sg:tags":[
        "remodeling",
        "pool",
        "swimming"
    ],
    "wof:name":"Arturos Pool Plaster Inc",
    "wof:placetype":"venue"
},
  "geometry": {"coordinates":[-95.22154999999999,29.681008],"type":"Point"}
}