{
  "type": "Feature",
  "properties": {
    "iso:country":"US",
    "sg:address":"1325 Whitlock Ln",
    "sg:city":"Carrollton",
    "sg:classifiers":[
        {
            "category":"Retail",
            "subcategory":"Auto Repair",
            "type":"Services"
        }
    ],
    "sg:phone":"+1 972 242 5454",
    "sg:postcode":"75006",
    "sg:province":"TX",
    "wof:name":"Whitlock Auto Kare & Sale",
    "wof:placetype":"venue"
},
  "geometry": {"coordinates":[-96.911962,32.968372],"type":"Point"}
}