{
  "type": "Feature",
  "properties": {
    "iso:country":"US",
    "sg:address":"538 Sawdust Rd",
    "sg:city":"Spring",
    "sg:classifiers":[
        {
            "category":"Shopping",
            "subcategory":"Gifts & Souvenirs",
            "type":"Retail Goods"
        }
    ],
    "sg:phone":"+1 281 681 1616",
    "sg:postcode":"77380",
    "sg:province":"TX",
    "wof:name":"Card Attack",
    "wof:placetype":"venue"
},
  "geometry": {"coordinates":[-95.451567,30.126772],"type":"Point"}
}