{
  "type": "Feature",
  "properties": {
    "iso:country":"US",
    "sg:address":"834 3rd St",
    "sg:city":"Rosenberg",
    "sg:classifiers":[
        {
            "category":"Real Estate",
            "subcategory":"Real Estate Agent",
            "type":"Services"
        }
    ],
    "sg:phone":"+1 281 342 3127",
    "sg:postcode":"77471",
    "sg:province":"TX",
    "wof:name":"Reese Real Estate",
    "wof:placetype":"venue"
},
  "geometry": {"coordinates":[-95.80680700000001,29.559948],"type":"Point"}
}