{
  "type": "Feature",
  "properties": {
    "iso:country":"US",
    "sg:address":"2801 Gateway Dr",
    "sg:city":"Irving",
    "sg:classifiers":[
        {
            "category":"Health Services",
            "subcategory":"Clinic",
            "type":"Services"
        }
    ],
    "sg:phone":"+1 972 870 4000",
    "sg:postcode":"75063",
    "sg:province":"TX",
    "sg:tags":[
        "agency",
        "welfare"
    ],
    "wof:name":"First Health",
    "wof:placetype":"venue"
},
  "geometry": {"coordinates":[-96.98507499999999,32.893485],"type":"Point"}
}