{
  "type": "Feature",
  "properties": {
    "iso:country":"US",
    "sg:address":"2810 Buffalo St",
    "sg:city":"Corpus Christi",
    "sg:classifiers":[
        {
            "category":"Professional",
            "subcategory":"Management & Consulting",
            "type":"Services"
        }
    ],
    "sg:phone":"+1 361 880 6705",
    "sg:postcode":"78408",
    "sg:province":"TX",
    "sg:tags":[
        "marketing",
        "program"
    ],
    "wof:name":"M E Marketing",
    "wof:placetype":"venue"
},
  "geometry": {"coordinates":[-97.424508,27.798823],"type":"Point"}
}