{
  "type": "Feature",
  "properties": {
    "iso:country":"US",
    "sg:address":"2104 Sadau Ct",
    "sg:city":"Denton",
    "sg:classifiers":[
        {
            "category":"Utilities",
            "subcategory":"Mobile Phone",
            "type":"Services"
        }
    ],
    "sg:phone":"+1 940 565 1366",
    "sg:postcode":"76210",
    "sg:province":"TX",
    "sg:tags":[
        "communications",
        "telephone",
        "cellular"
    ],
    "wof:name":"Southwestern Bell Mobile Syst",
    "wof:placetype":"venue"
},
  "geometry": {"coordinates":[-97.102064,33.189258],"type":"Point"}
}