{
  "type": "Feature",
  "properties": {
    "iso:country":"US",
    "sg:address":"703 Rock Harbor Dr",
    "sg:city":"Granbury",
    "sg:classifiers":[
        {
            "category":"Restaurant",
            "type":"Food & Drink"
        }
    ],
    "sg:phone":"+1 817 279 7544",
    "sg:postcode":"76048",
    "sg:province":"TX",
    "sg:tags":[
        "eating"
    ],
    "wof:name":"Take Two Med Trnscription Svcs",
    "wof:placetype":"venue"
},
  "geometry": {"coordinates":[-97.776982,32.414184],"type":"Point"}
}