{
  "type": "Feature",
  "properties": {
    "iso:country":"US",
    "sg:address":"2110 E Crosstimbers St",
    "sg:city":"Houston",
    "sg:classifiers":[
        {
            "category":"Organizations",
            "subcategory":"Religious Organization",
            "type":"Services"
        }
    ],
    "sg:phone":"+1 713 694 7410",
    "sg:postcode":"77093",
    "sg:province":"TX",
    "sg:tags":[
        "church"
    ],
    "wof:name":"Church Of The Living God",
    "wof:placetype":"venue"
},
  "geometry": {"coordinates":[-95.347443,29.828604],"type":"Point"}
}