{
  "type": "Feature",
  "properties": {
    "iso:country":"US",
    "sg:address":"12261 Veterans Memorial Dr",
    "sg:city":"Houston",
    "sg:classifiers":[
        {
            "category":"Autos & Motor Vehicles",
            "subcategory":"Auto Supplies",
            "type":"Retail Goods"
        }
    ],
    "sg:phone":"+1 281 440 8000",
    "sg:postcode":"77067",
    "sg:province":"TX",
    "sg:tags":[
        "shop",
        "tire"
    ],
    "wof:name":"Marin's Tire Shop",
    "wof:placetype":"venue"
},
  "geometry": {"coordinates":[-95.48114099999999,29.96503],"type":"Point"}
}