{
  "type": "Feature",
  "properties": {
    "iso:country":"US",
    "sg:address":"3470 Tigertown Rd",
    "sg:city":"Paris",
    "sg:classifiers":[
        {
            "category":"Building & Trades",
            "subcategory":"Cleaning & Sanitation",
            "type":"Services"
        }
    ],
    "sg:phone":"+1 903 784 2107",
    "sg:postcode":"75460",
    "sg:province":"TX",
    "sg:tags":[
        "maintenance"
    ],
    "wof:name":"Scotts Janitorial Service",
    "wof:placetype":"venue"
},
  "geometry": {"coordinates":[-95.607321,33.675308],"type":"Point"}
}