{
  "type": "Feature",
  "properties": {
    "iso:country":"US",
    "sg:address":"411 N Belknap St",
    "sg:city":"Stephenville",
    "sg:classifiers":[
        {
            "category":"Health Services",
            "subcategory":"Doctor",
            "type":"Services"
        },
        {
            "category":"Health Services",
            "subcategory":"Clinic",
            "type":"Services"
        },
        {
            "category":"Communications",
            "type":"Services"
        },
        {
            "category":"Health Services",
            "subcategory":"Hospital",
            "type":"Services"
        }
    ],
    "sg:phone":"+1 254 965 1500",
    "sg:postcode":"76401",
    "sg:province":"TX",
    "sg:tags":[
        "information",
        "speech-language",
        "referral",
        "family",
        "cancer",
        "cardiology",
        "gynecology",
        "practice",
        "surgeons",
        "physician",
        "pathologist",
        "orthopedics",
        "treatment",
        "medicine",
        "surgeon",
        "sport",
        "rehabilitation"
    ],
    "sg:website":"http://www.texashealth.org/landing.cfm?id=108",
    "wof:name":"Texas Health Harris Methodist Hospital Stephenville",
    "wof:placetype":"venue"
},
  "geometry": {"coordinates":[-98.204161,32.222174],"type":"Point"}
}