{
  "type": "Feature",
  "properties": {
    "iso:country":"US",
    "sg:address":"2920 W 5th Ave",
    "sg:city":"Amarillo",
    "sg:classifiers":[
        {
            "category":"Organizations",
            "subcategory":"Religious Organization",
            "type":"Services"
        }
    ],
    "sg:phone":"+1 806 372 4892",
    "sg:postcode":"79106",
    "sg:province":"TX",
    "sg:tags":[
        "church"
    ],
    "wof:name":"Christian Life Center Inc",
    "wof:placetype":"venue"
},
  "geometry": {"coordinates":[-101.869652,35.212288],"type":"Point"}
}