{
  "type": "Feature",
  "properties": {
    "iso:country":"US",
    "sg:address":"517 N Travis St",
    "sg:city":"Deer Park",
    "sg:classifiers":[
        {
            "category":"Building & Trades",
            "subcategory":"Cleaning & Sanitation",
            "type":"Services"
        }
    ],
    "sg:phone":"+1 281 478 6296",
    "sg:postcode":"77536",
    "sg:province":"TX",
    "sg:tags":[
        "maintenance"
    ],
    "wof:name":"We Be Maids",
    "wof:placetype":"venue"
},
  "geometry": {"coordinates":[-95.117887,29.666389],"type":"Point"}
}