{
  "type": "Feature",
  "properties": {
    "iso:country":"US",
    "sg:address":"19761 Turner Rd",
    "sg:city":"New Caney",
    "sg:classifiers":[
        {
            "category":"Building & Trades",
            "subcategory":"Landscaping Services",
            "type":"Services"
        }
    ],
    "sg:phone":"+1 281 399 0589",
    "sg:postcode":"77357",
    "sg:province":"TX",
    "sg:tags":[
        "landscape"
    ],
    "wof:name":"S & S Enterprises",
    "wof:placetype":"venue"
},
  "geometry": {"coordinates":[-95.226056,30.159332],"type":"Point"}
}