{
  "type": "Feature",
  "properties": {
    "iso:country":"US",
    "sg:address":"2704 Hillview Green Ln",
    "sg:city":"Austin",
    "sg:classifiers":[
        {
            "category":"Organizations",
            "subcategory":"Community Association",
            "type":"Services"
        }
    ],
    "sg:phone":"+1 512 474 4992",
    "sg:postcode":"78703",
    "sg:province":"TX",
    "wof:name":"Young Womens Alliance Fo",
    "wof:placetype":"venue"
},
  "geometry": {"coordinates":[-97.765614,30.302924],"type":"Point"}
}