{
  "type": "Feature",
  "properties": {
    "iso:country":"US",
    "sg:address":"10881 Bissonnet St",
    "sg:city":"Houston",
    "sg:classifiers":[
        {
            "category":"Banks & Credit Unions",
            "subcategory":"Bank",
            "type":"Services"
        }
    ],
    "sg:phone":"+1 281 933 7054",
    "sg:postcode":"77099",
    "sg:province":"TX",
    "sg:website":"http://www.amegybank.com",
    "wof:name":"Amegy Bank",
    "wof:placetype":"venue"
},
  "geometry": {"coordinates":[-95.569998,29.674119],"type":"Point"}
}