{
  "type": "Feature",
  "properties": {
    "iso:country":"US",
    "sg:address":"1458 Lawson",
    "sg:city":"Houston",
    "sg:classifiers":[
        {
            "category":"Arts & Performance",
            "subcategory":"Arts Center",
            "type":"Entertainment"
        }
    ],
    "sg:phone":"+1 713 928 5653",
    "sg:postcode":"77023",
    "sg:province":"TX",
    "sg:tags":[
        "performing"
    ],
    "sg:website":"www.namelesssound.org",
    "wof:name":"Nameless Sound",
    "wof:placetype":"venue"
},
  "geometry": {"coordinates":[-95.329255,29.72848],"type":"Point"}
}