{
  "type": "Feature",
  "properties": {
    "iso:country":"US",
    "sg:address":"10707 Corporate Dr",
    "sg:city":"Stafford",
    "sg:classifiers":[
        {
            "category":"Building & Trades",
            "subcategory":"Construction",
            "type":"Services"
        }
    ],
    "sg:phone":"+1 281 277 5588",
    "sg:postcode":"77477",
    "sg:province":"TX",
    "sg:tags":[
        "general",
        "contractor"
    ],
    "wof:name":"Kenro/Turner Construction",
    "wof:placetype":"venue"
},
  "geometry": {"coordinates":[-95.59413600000001,29.633153],"type":"Point"}
}