{
  "type": "Feature",
  "properties": {
    "iso:country":"US",
    "sg:address":"5011 Peebles Dr",
    "sg:city":"Houston",
    "sg:classifiers":[
        {
            "category":"Professional",
            "type":"Services"
        }
    ],
    "sg:phone":"+1 713 354 1334",
    "sg:postcode":"77084",
    "sg:province":"TX",
    "wof:name":"Mary Jo Hermann",
    "wof:placetype":"venue"
},
  "geometry": {"coordinates":[-95.66060299999999,29.849848],"type":"Point"}
}