{
  "type": "Feature",
  "properties": {
    "iso:country":"US",
    "sg:address":"2113 Stevenson Ln",
    "sg:city":"Flower Mound",
    "sg:classifiers":[
        {
            "category":"Professional",
            "subcategory":"Management & Consulting",
            "type":"Services"
        }
    ],
    "sg:phone":"+1 972 724 3432",
    "sg:postcode":"75028",
    "sg:province":"TX",
    "wof:name":"Demaso Inc",
    "wof:placetype":"venue"
},
  "geometry": {"coordinates":[-97.05947399999999,33.064891],"type":"Point"}
}