{
  "type": "Feature",
  "properties": {
    "iso:country":"US",
    "sg:address":"104 Chapman Cir",
    "sg:city":"Burkburnett",
    "sg:classifiers":[
        {
            "category":"Communications",
            "subcategory":"Film & Video Production",
            "type":"Services"
        }
    ],
    "sg:phone":"+1 940 569 1793",
    "sg:postcode":"76354",
    "sg:province":"TX",
    "sg:tags":[
        "motion"
    ],
    "wof:name":"Visual Concepts",
    "wof:placetype":"venue"
},
  "geometry": {"coordinates":[-98.58120700000001,34.076153],"type":"Point"}
}