{
  "type": "Feature",
  "properties": {
    "iso:country":"US",
    "sg:address":"920 Highway 287 N",
    "sg:city":"Mansfield",
    "sg:classifiers":[
        {
            "category":"Health Services",
            "subcategory":"Doctor",
            "type":"Services"
        }
    ],
    "sg:phone":"+1 817 473 7197",
    "sg:postcode":"76063",
    "sg:province":"TX",
    "sg:tags":[
        "physician",
        "surgeon"
    ],
    "wof:name":"Mansfield Medical Associates",
    "wof:placetype":"venue"
},
  "geometry": {"coordinates":[-97.130819,32.581169],"type":"Point"}
}