{
  "type": "Feature",
  "properties": {
    "iso:country":"US",
    "sg:address":"5932 Eastland St",
    "sg:city":"Fort Worth",
    "sg:classifiers":[
        {
            "category":"Organizations",
            "subcategory":"Religious Organization",
            "type":"Services"
        }
    ],
    "sg:phone":"+1 817 457 0147",
    "sg:postcode":"76119",
    "sg:province":"TX",
    "sg:tags":[
        "church"
    ],
    "wof:name":"Oakwood Baptist Church",
    "wof:placetype":"venue"
},
  "geometry": {"coordinates":[-97.229562,32.705696],"type":"Point"}
}