{
  "type": "Feature",
  "properties": {
    "iso:country":"US",
    "sg:address":"1208 W Jeannette",
    "sg:city":"Breckenridge",
    "sg:classifiers":[
        {
            "category":"Personal",
            "subcategory":"Beauty Salon",
            "type":"Services"
        }
    ],
    "sg:phone":"+1 254 559 8009",
    "sg:postcode":"76424",
    "sg:province":"TX",
    "sg:tags":[
        "shop"
    ],
    "wof:name":"Lavones Beauty Salon",
    "wof:placetype":"venue"
},
  "geometry": {"coordinates":[-98.918114,32.759122],"type":"Point"}
}