{
  "type": "Feature",
  "properties": {
    "iso:country":"US",
    "sg:address":"116 N Main St",
    "sg:city":"Belton",
    "sg:classifiers":[
        {
            "category":"Professional",
            "subcategory":"Lawyer & Legal Services",
            "type":"Services"
        }
    ],
    "sg:phone":"+1 254 939 3758",
    "sg:postcode":"76513",
    "sg:province":"TX",
    "sg:tags":[
        "attorney"
    ],
    "wof:name":"Ted L Potter Legal Office",
    "wof:placetype":"venue"
},
  "geometry": {"coordinates":[-97.463508,31.057253],"type":"Point"}
}