{
  "type": "Feature",
  "properties": {
    "iso:country":"US",
    "sg:address":"1225 International Blvd",
    "sg:city":"Brownsville",
    "sg:classifiers":[
        {
            "category":"Autos & Motor Vehicles",
            "subcategory":"Automobile Sales",
            "type":"Retail Goods"
        }
    ],
    "sg:phone":"+1 956 544 1931",
    "sg:postcode":"78520",
    "sg:province":"TX",
    "sg:tags":[
        "car",
        "used"
    ],
    "wof:name":"International Auto Sales",
    "wof:placetype":"venue"
},
  "geometry": {"coordinates":[-97.48887999999999,25.901475],"type":"Point"}
}