{
  "type": "Feature",
  "properties": {
    "iso:country":"US",
    "sg:address":"3310 Fm 967 Ste A104",
    "sg:city":"Buda",
    "sg:classifiers":[
        {
            "category":"Building & Trades",
            "subcategory":"Cleaning & Sanitation",
            "type":"Services"
        }
    ],
    "sg:phone":"+1 512 312 9569",
    "sg:postcode":"78610",
    "sg:province":"TX",
    "sg:tags":[
        "cleaning-industrial",
        "contractor"
    ],
    "wof:name":"Rebel Cleaners",
    "wof:placetype":"venue"
},
  "geometry": {"coordinates":[-97.87677600000001,30.096711],"type":"Point"}
}