{
  "type": "Feature",
  "properties": {
    "iso:country":"US",
    "sg:address":"14602 Compass St",
    "sg:city":"Corpus Christi",
    "sg:classifiers":[
        {
            "category":"Real Estate",
            "subcategory":"Real Estate Agent",
            "type":"Services"
        }
    ],
    "sg:phone":"+1 361 949 0649",
    "sg:postcode":"78418",
    "sg:province":"TX",
    "wof:name":"Sudhoff Properties",
    "wof:placetype":"venue"
},
  "geometry": {"coordinates":[-97.223135,27.617889],"type":"Point"}
}