{
  "type": "Feature",
  "properties": {
    "iso:country":"US",
    "sg:address":"702 S M St",
    "sg:city":"Harlingen",
    "sg:classifiers":[
        {
            "category":"Social Services",
            "subcategory":"Child Care",
            "type":"Services"
        }
    ],
    "sg:phone":"+1 956 412 0521",
    "sg:postcode":"78550",
    "sg:province":"TX",
    "wof:name":"Los Vecinos Headstart",
    "wof:placetype":"venue"
},
  "geometry": {"coordinates":[-97.710435,26.18593],"type":"Point"}
}