{
  "type": "Feature",
  "properties": {
    "iso:country":"US",
    "sg:address":"1905 Kramer Ln Ste B800",
    "sg:city":"Austin",
    "sg:classifiers":[
        {
            "category":"Shopping",
            "subcategory":"Stationery & Office Supplies",
            "type":"Retail Goods"
        }
    ],
    "sg:phone":"+1 512 997 2100",
    "sg:postcode":"78758",
    "sg:province":"TX",
    "sg:tags":[
        "equipment"
    ],
    "sg:website":"www.corporateexpress.com",
    "wof:name":"Corporate Express",
    "wof:placetype":"venue"
},
  "geometry": {"coordinates":[-97.71047,30.386192],"type":"Point"}
}