{
  "type": "Feature",
  "properties": {
    "iso:country":"US",
    "sg:address":"61 Huntsmans Horn Cir",
    "sg:city":"Spring",
    "sg:classifiers":[
        {
            "category":"Professional",
            "subcategory":"Business Services",
            "type":"Services"
        }
    ],
    "sg:phone":"+1 281 292 6421",
    "sg:postcode":"77380",
    "sg:province":"TX",
    "sg:tags":[
        "interior",
        "design"
    ],
    "wof:name":"Janet Melton Interiors",
    "wof:placetype":"venue"
},
  "geometry": {"coordinates":[-95.462683,30.149097],"type":"Point"}
}