{
  "type": "Feature",
  "properties": {
    "iso:country":"US",
    "sg:address":"545 Bear Ridge",
    "sg:city":"Keller",
    "sg:classifiers":[
        {
            "category":"Real Estate",
            "subcategory":"Real Estate Agent",
            "type":"Services"
        }
    ],
    "sg:phone":"+1 817 442 5443",
    "sg:postcode":"76248",
    "sg:province":"TX",
    "wof:name":"Dave Folsom Inc",
    "wof:placetype":"venue"
},
  "geometry": {"coordinates":[-97.223105,32.925298],"type":"Point"}
}