{
  "type": "Feature",
  "properties": {
    "iso:country":"US",
    "sg:address":"1200 S Dewey Ave",
    "sg:city":"Sherman",
    "sg:classifiers":[
        {
            "category":"Professional",
            "subcategory":"Employment Agencies",
            "type":"Services"
        }
    ],
    "sg:phone":"+1 903 891 4035",
    "sg:postcode":"75090",
    "sg:province":"TX",
    "sg:tags":[
        "help",
        "supply"
    ],
    "wof:name":"Sherman Municipal Airport",
    "wof:placetype":"venue"
},
  "geometry": {"coordinates":[-96.585426,33.628547],"type":"Point"}
}