{
  "type": "Feature",
  "properties": {
    "iso:country":"US",
    "sg:address":"3311 83rd St",
    "sg:city":"Lubbock",
    "sg:classifiers":[
        {
            "category":"Shopping",
            "type":"Retail Goods"
        }
    ],
    "sg:phone":"+1 806 796 0802",
    "sg:postcode":"79423",
    "sg:province":"TX",
    "sg:tags":[
        "pet",
        "shop"
    ],
    "wof:name":"Grooming Cottage",
    "wof:placetype":"venue"
},
  "geometry": {"coordinates":[-101.886318,33.51843],"type":"Point"}
}