{
  "type": "Feature",
  "properties": {
    "iso:country":"US",
    "sg:address":"105 E 30th St",
    "sg:city":"Mission",
    "sg:classifiers":[
        {
            "category":"Shopping",
            "subcategory":"Florist",
            "type":"Retail Goods"
        }
    ],
    "sg:phone":"+1 956 585 5021",
    "sg:postcode":"78574",
    "sg:province":"TX",
    "wof:name":"Fernwood Flowers & Gifts",
    "wof:placetype":"venue"
},
  "geometry": {"coordinates":[-98.317727,26.239131],"type":"Point"}
}