{
  "type": "Feature",
  "properties": {
    "iso:country":"US",
    "sg:address":"1003 Stanley St",
    "sg:city":"Denton",
    "sg:classifiers":[
        {
            "category":"Organizations",
            "subcategory":"Religious Organization",
            "type":"Services"
        }
    ],
    "sg:phone":"+1 940 898 0008",
    "sg:postcode":"76201",
    "sg:province":"TX",
    "sg:tags":[
        "church"
    ],
    "wof:name":"Living Stones Christian",
    "wof:placetype":"venue"
},
  "geometry": {"coordinates":[-97.159914,33.223881],"type":"Point"}
}