{
  "type": "Feature",
  "properties": {
    "iso:country":"US",
    "sg:address":"11711 Memorial Dr",
    "sg:city":"Houston",
    "sg:classifiers":[
        {
            "category":"Professional",
            "subcategory":"Business Services",
            "type":"Services"
        }
    ],
    "sg:phone":"+1 713 780 3439",
    "sg:postcode":"77024",
    "sg:province":"TX",
    "sg:tags":[
        "interior",
        "consultant",
        "design",
        "decorator",
        "architectural"
    ],
    "wof:name":"Blum Michael Interiors",
    "wof:placetype":"venue"
},
  "geometry": {"coordinates":[-95.526022,29.752041],"type":"Point"}
}