{
  "type": "Feature",
  "properties": {
    "iso:country":"US",
    "sg:address":"4131 Spicewood Springs Rd Ste P4",
    "sg:city":"Austin",
    "sg:classifiers":[
        {
            "category":"Banks & Credit Unions",
            "subcategory":"Investment Brokerage",
            "type":"Services"
        },
        {
            "category":"Banks & Credit Unions",
            "subcategory":"Financial Services",
            "type":"Services"
        }
    ],
    "sg:phone":"+1 512 349 2639",
    "sg:postcode":"78759",
    "sg:province":"TX",
    "sg:tags":[
        "investing",
        "advising"
    ],
    "sg:website":"ameripriseadvisors.com",
    "wof:name":"Ameriprise Financial Advisors",
    "wof:placetype":"venue"
},
  "geometry": {"coordinates":[-97.755588,30.369624],"type":"Point"}
}