{
  "type": "Feature",
  "properties": {
    "iso:country":"US",
    "sg:address":"1590 N Harvey Mitchell Pkwy",
    "sg:city":"Bryan",
    "sg:classifiers":[
        {
            "category":"Manufacturing",
            "subcategory":"Chemicals & Compounds",
            "type":"Manufacturing & Wholesale Goods"
        }
    ],
    "sg:phone":"+1 979 779 9399",
    "sg:postcode":"77803",
    "sg:province":"TX",
    "sg:tags":[
        "distribution",
        "janitorial",
        "supply"
    ],
    "wof:name":"Pro Star",
    "wof:placetype":"venue"
},
  "geometry": {"coordinates":[-96.407422,30.668046],"type":"Point"}
}