{
  "type": "Feature",
  "properties": {
    "iso:country":"US",
    "sg:address":"3200 S Lancaster Rd",
    "sg:city":"Dallas",
    "sg:classifiers":[
        {
            "category":"Professional",
            "subcategory":"Accounting & Tax Preparation",
            "type":"Services"
        }
    ],
    "sg:phone":"+1 214 376 8181",
    "sg:postcode":"75216",
    "sg:province":"TX",
    "sg:tags":[
        "return",
        "filing"
    ],
    "sg:website":"www.hrblock.com",
    "wof:name":"H & R Block Tax Svc",
    "wof:placetype":"venue"
},
  "geometry": {"coordinates":[-96.80210099999999,32.708349],"type":"Point"}
}