{
  "type": "Feature",
  "properties": {
    "iso:country":"US",
    "sg:address":"310 W Walnut St",
    "sg:city":"Celina",
    "sg:classifiers":[
        {
            "category":"Wholesale",
            "subcategory":"Construction Materials",
            "type":"Manufacturing & Wholesale Goods"
        }
    ],
    "sg:phone":"+1 972 382 4200",
    "sg:postcode":"75009",
    "sg:province":"TX",
    "sg:tags":[
        "fence"
    ],
    "wof:name":"Accent Fence Co",
    "wof:placetype":"venue"
},
  "geometry": {"coordinates":[-96.786456,33.323896],"type":"Point"}
}