{
  "type": "Feature",
  "properties": {
    "iso:country":"US",
    "sg:address":"203 Wiltshire Ave",
    "sg:city":"San Antonio",
    "sg:classifiers":[
        {
            "category":"Food & Beverages",
            "subcategory":"Groceries & Convenience Stores",
            "type":"Retail Goods"
        }
    ],
    "sg:phone":"+1 210 822 5323",
    "sg:postcode":"78209",
    "sg:province":"TX",
    "wof:name":"Supermarket Network",
    "wof:placetype":"venue"
},
  "geometry": {"coordinates":[-98.457517,29.476943],"type":"Point"}
}