{
  "type": "Feature",
  "properties": {
    "iso:country":"US",
    "sg:address":"5824 Misted Breeze Dr",
    "sg:city":"Plano",
    "sg:classifiers":[
        {
            "category":"Real Estate",
            "subcategory":"Real Estate Operator",
            "type":"Services"
        }
    ],
    "sg:phone":"+1 972 403 0833",
    "sg:postcode":"75093",
    "sg:province":"TX",
    "sg:tags":[
        "building",
        "nonresidential"
    ],
    "wof:name":"Slate Properties Inc",
    "wof:placetype":"venue"
},
  "geometry": {"coordinates":[-96.82088299999999,33.051653],"type":"Point"}
}