{
  "type": "Feature",
  "properties": {
    "iso:country":"US",
    "sg:address":"2911 McNiel Ave",
    "sg:city":"Wichita Falls",
    "sg:classifiers":[
        {
            "category":"Wholesale",
            "subcategory":"Sporting Goods",
            "type":"Manufacturing & Wholesale Goods"
        }
    ],
    "sg:phone":"+1 940 691 8391",
    "sg:postcode":"76309",
    "sg:province":"TX",
    "wof:name":"Booth Sales",
    "wof:placetype":"venue"
},
  "geometry": {"coordinates":[-98.549291,33.88254],"type":"Point"}
}