{
  "type": "Feature",
  "properties": {
    "iso:country":"US",
    "sg:address":"235 Sue Ln",
    "sg:city":"Mineola",
    "sg:classifiers":[
        {
            "category":"Home & Garden",
            "subcategory":"Building Materials",
            "type":"Retail Goods"
        }
    ],
    "sg:phone":"+1 903 569 4824",
    "sg:postcode":"75773",
    "sg:province":"TX",
    "sg:tags":[
        "wallpaper"
    ],
    "wof:name":"Wallpaper Fashions",
    "wof:placetype":"venue"
},
  "geometry": {"coordinates":[-95.479542,32.678028],"type":"Point"}
}