{
  "type": "Feature",
  "properties": {
    "iso:country":"US",
    "sg:address":"13708 Ann Pl",
    "sg:city":"Austin",
    "sg:classifiers":[
        {
            "category":"Wholesale",
            "subcategory":"Electrical",
            "type":"Manufacturing & Wholesale Goods"
        }
    ],
    "sg:phone":"+1 512 251 9594",
    "sg:postcode":"78728",
    "sg:province":"TX",
    "sg:tags":[
        "communication",
        "radio",
        "system"
    ],
    "sg:website":"www.cinema2wayradio.com",
    "wof:name":"Cinema 2 Way Radio Inc",
    "wof:placetype":"venue"
},
  "geometry": {"coordinates":[-97.67537900000001,30.426301],"type":"Point"}
}