{
  "type": "Feature",
  "properties": {
    "iso:country":"US",
    "sg:address":"2018 Mount Forest Dr",
    "sg:city":"Humble",
    "sg:classifiers":[
        {
            "category":"Organizations",
            "subcategory":"Professional Association",
            "type":"Services"
        }
    ],
    "sg:phone":"+1 281 441 1500",
    "sg:postcode":"77345",
    "sg:province":"TX",
    "sg:tags":[
        "business"
    ],
    "wof:name":"World Net Associates Inc",
    "wof:placetype":"venue"
},
  "geometry": {"coordinates":[-95.157517,30.049881],"type":"Point"}
}