{
  "type": "Feature",
  "properties": {
    "iso:country":"US",
    "sg:address":"8800 S Congress Ave",
    "sg:city":"Austin",
    "sg:classifiers":[
        {
            "category":"Professional",
            "type":"Services"
        },
        {
            "category":"Retail",
            "subcategory":"Auto Rental",
            "type":"Services"
        },
        {
            "category":"Building & Trades",
            "subcategory":"Equipment Rental",
            "type":"Services"
        },
        {
            "category":"Retail",
            "subcategory":"Storage",
            "type":"Services"
        },
        {
            "category":"Manufacturing",
            "subcategory":"Paper Products",
            "type":"Manufacturing & Wholesale Goods"
        }
    ],
    "sg:phone":"+1 866 205 7339",
    "sg:postcode":"78745",
    "sg:province":"TX",
    "sg:tags":[
        "renting",
        "moving-self",
        "fiber",
        "leasing",
        "material",
        "boxes-corrugated",
        "truck",
        "services-labor",
        "moving",
        "trailer"
    ],
    "sg:website":"http://www.pensketruckrental.com/personal_rental/?cid=Yptmlist",
    "wof:name":"Penske Truck Rental",
    "wof:placetype":"venue"
},
  "geometry": {"coordinates":[-97.786547,30.170531],"type":"Point"}
}