{
  "type": "Feature",
  "properties": {
    "iso:country":"US",
    "sg:address":"5627 Beechnut St",
    "sg:city":"Houston",
    "sg:classifiers":[
        {
            "category":"Personal",
            "subcategory":"Nail Salon",
            "type":"Services"
        }
    ],
    "sg:phone":"+1 713 777 4517",
    "sg:postcode":"77096",
    "sg:province":"TX",
    "wof:name":"Lee's Nails",
    "wof:placetype":"venue"
},
  "geometry": {"coordinates":[-95.489597,29.688686],"type":"Point"}
}