{
  "type": "Feature",
  "properties": {
    "iso:country":"US",
    "sg:address":"9749 US Hwy 283",
    "sg:city":"Vernon",
    "sg:classifiers":[
        {
            "category":"Wholesale",
            "subcategory":"Farm Supplies",
            "type":"Manufacturing & Wholesale Goods"
        }
    ],
    "sg:phone":"+1 940 552 7282",
    "sg:postcode":"76384",
    "sg:province":"TX",
    "sg:tags":[
        "grain",
        "livestock",
        "cash"
    ],
    "wof:name":"Schur Gt Farm",
    "wof:placetype":"venue"
},
  "geometry": {"coordinates":[-99.273911,34.184041],"type":"Point"}
}