{
  "type": "Feature",
  "properties": {
    "iso:country":"US",
    "sg:address":"446 N Manus Dr",
    "sg:city":"Dallas",
    "sg:classifiers":[
        {
            "category":"Building & Trades",
            "subcategory":"Electrical",
            "type":"Services"
        }
    ],
    "sg:phone":"+1 214 943 3192",
    "sg:postcode":"75224",
    "sg:province":"TX",
    "sg:tags":[
        "electrical",
        "contractor"
    ],
    "wof:name":"J R Electric",
    "wof:placetype":"venue"
},
  "geometry": {"coordinates":[-96.829628,32.732626],"type":"Point"}
}