{
  "type": "Feature",
  "properties": {
    "iso:country":"US",
    "sg:address":"9303 Winchester Rd",
    "sg:city":"Austin",
    "sg:classifiers":[
        {
            "category":"Professional",
            "subcategory":"Computer Services",
            "type":"Services"
        }
    ],
    "sg:phone":"+1 512 263 2488",
    "sg:postcode":"78733",
    "sg:province":"TX",
    "sg:tags":[
        "programing",
        "custom"
    ],
    "wof:name":"Transformation Technologies",
    "wof:placetype":"venue"
},
  "geometry": {"coordinates":[-97.860466,30.336197],"type":"Point"}
}