{
  "type": "Feature",
  "properties": {
    "iso:country":"US",
    "sg:address":"1705 N McKinney St",
    "sg:city":"Rice",
    "sg:classifiers":[
        {
            "category":"Wholesale",
            "subcategory":"Farm Supplies",
            "type":"Manufacturing & Wholesale Goods"
        }
    ],
    "sg:phone":"+1 903 326 6171",
    "sg:postcode":"75155",
    "sg:province":"TX",
    "wof:name":"County Line Feed & Supplies",
    "wof:placetype":"venue"
},
  "geometry": {"coordinates":[-96.505617,32.261991],"type":"Point"}
}