{
  "type": "Feature",
  "properties": {
    "iso:country":"US",
    "sg:address":"7505 E John Carpenter Fwy",
    "sg:city":"Dallas",
    "sg:classifiers":[
        {
            "category":"Professional",
            "subcategory":"Advertising",
            "type":"Services"
        }
    ],
    "sg:phone":"+1 214 224 1000",
    "sg:postcode":"75247",
    "sg:province":"TX",
    "sg:tags":[
        "marketing",
        "internet"
    ],
    "wof:name":"Internet University",
    "wof:placetype":"venue"
},
  "geometry": {"coordinates":[-96.870457,32.817171],"type":"Point"}
}