{
  "type": "Feature",
  "properties": {
    "iso:country":"US",
    "sg:address":"12508 Burlywood Trl",
    "sg:city":"Austin",
    "sg:classifiers":[
        {
            "category":"Shopping",
            "subcategory":"Used Merchandise",
            "type":"Retail Goods"
        }
    ],
    "sg:phone":"+1 512 250 9636",
    "sg:postcode":"78750",
    "sg:province":"TX",
    "wof:name":"Peddlepushers",
    "wof:placetype":"venue"
},
  "geometry": {"coordinates":[-97.806674,30.464385],"type":"Point"}
}