{
  "type": "Feature",
  "properties": {
    "iso:country":"US",
    "sg:address":"300 Fay St",
    "sg:city":"Vidor",
    "sg:classifiers":[
        {
            "category":"Manufacturing",
            "subcategory":"Metals",
            "type":"Manufacturing & Wholesale Goods"
        }
    ],
    "sg:phone":"+1 409 735 3114",
    "sg:postcode":"77662",
    "sg:province":"TX",
    "sg:tags":[
        "vessel"
    ],
    "sg:website":"www.hydro-extractors.com",
    "wof:name":"Allied Fabricating & Welding",
    "wof:placetype":"venue"
},
  "geometry": {"coordinates":[-94.090675,30.168753],"type":"Point"}
}