{
  "type": "Feature",
  "properties": {
    "iso:country":"US",
    "sg:address":"4204 Wilshire Pkwy Ste B",
    "sg:city":"Austin",
    "sg:classifiers":[
        {
            "category":"Professional",
            "type":"Services"
        }
    ],
    "sg:phone":"+1 512 553 5397",
    "sg:postcode":"78722",
    "sg:province":"TX",
    "sg:website":"www.keywordvalet.com",
    "wof:name":"KeywordValet SEM",
    "wof:placetype":"venue"
},
  "geometry": {"coordinates":[-97.71200899999999,30.297085],"type":"Point"}
}