{
  "type": "Feature",
  "properties": {
    "iso:country":"US",
    "sg:address":"10000 Research Boulevard",
    "sg:city":"Austin",
    "sg:classifiers":[
        {
            "category":"Home & Garden",
            "subcategory":"Furniture",
            "type":"Retail Goods"
        }
    ],
    "sg:phone":"+1 512 342 0614",
    "sg:postcode":"78759",
    "sg:province":"TX",
    "sg:tags":[
        "store"
    ],
    "sg:website":"www.restorationhardware.com/rh/i...",
    "wof:name":"Restoration Hardware",
    "wof:placetype":"venue"
},
  "geometry": {"coordinates":[-97.746863,30.392345],"type":"Point"}
}