{
  "type": "Feature",
  "properties": {
    "iso:country":"US",
    "sg:address":"1311 E Buckley St",
    "sg:city":"Brownfield",
    "sg:classifiers":[
        {
            "category":"Restaurant",
            "type":"Food & Drink"
        }
    ],
    "sg:phone":"+1 806 637 1528",
    "sg:postcode":"79316",
    "sg:province":"TX",
    "sg:tags":[
        "eating"
    ],
    "wof:name":"Riveras Sno Cone & Grill",
    "wof:placetype":"venue"
},
  "geometry": {"coordinates":[-102.25905400000001,33.175199],"type":"Point"}
}