{
  "type": "Feature",
  "properties": {
    "iso:country":"US",
    "sg:address":"100 Main St",
    "sg:city":"Rusk",
    "sg:classifiers":[
        {
            "category":"Restaurant",
            "type":"Food & Drink"
        }
    ],
    "sg:phone":"+1 903 683 6610",
    "sg:postcode":"75785",
    "sg:province":"TX",
    "sg:tags":[
        "eating"
    ],
    "wof:name":"Home Made Heaven",
    "wof:placetype":"venue"
},
  "geometry": {"coordinates":[-95.149187,31.786479],"type":"Point"}
}