{
  "type": "Feature",
  "properties": {
    "iso:country":"US",
    "sg:address":"35 Mott Ln",
    "sg:city":"Houston",
    "sg:classifiers":[
        {
            "category":"Professional",
            "type":"Services"
        }
    ],
    "sg:phone":"+1 713 952 2694",
    "sg:postcode":"77024",
    "sg:province":"TX",
    "wof:name":"Sham Usha R",
    "wof:placetype":"venue"
},
  "geometry": {"coordinates":[-95.520399,29.749241],"type":"Point"}
}