{
  "type": "Feature",
  "properties": {
    "iso:country":"US",
    "sg:address":"2908 Catalpa St",
    "sg:city":"Victoria",
    "sg:classifiers":[
        {
            "category":"Building & Trades",
            "subcategory":"Electrical",
            "type":"Services"
        }
    ],
    "sg:phone":"+1 361 580 2435",
    "sg:postcode":"77901",
    "sg:province":"TX",
    "sg:tags":[
        "electric",
        "contractor"
    ],
    "wof:name":"2 H Electrical Contractors",
    "wof:placetype":"venue"
},
  "geometry": {"coordinates":[-96.971936,28.815985],"type":"Point"}
}