{
  "type": "Feature",
  "properties": {
    "iso:country":"US",
    "sg:address":"803 Widener Ln",
    "sg:city":"Laredo",
    "sg:classifiers":[
        {
            "category":"Building & Trades",
            "subcategory":"Landscaping Services",
            "type":"Services"
        }
    ],
    "sg:phone":"+1 956 729 0525",
    "sg:postcode":"78041",
    "sg:province":"TX",
    "wof:name":"Arizona Contractor & Lawn",
    "wof:placetype":"venue"
},
  "geometry": {"coordinates":[-99.475005,27.569396],"type":"Point"}
}