{
  "type": "Feature",
  "properties": {
    "iso:country":"US",
    "sg:address":"505 High St",
    "sg:city":"Rogers",
    "sg:classifiers":[
        {
            "category":"Education",
            "subcategory":"School",
            "type":"Public Place"
        }
    ],
    "sg:phone":"+1 254 642 3647",
    "sg:postcode":"76569",
    "sg:province":"TX",
    "wof:name":"Rogers Independent School Dist",
    "wof:placetype":"venue"
},
  "geometry": {"coordinates":[-97.230531,30.929416],"type":"Point"}
}