{
  "type": "Feature",
  "properties": {
    "iso:country":"US",
    "sg:address":"5004 N Desert Blvd",
    "sg:city":"El Paso",
    "sg:classifiers":[
        {
            "category":"Restaurant",
            "type":"Food & Drink"
        }
    ],
    "sg:phone":"+1 915 585 8868",
    "sg:postcode":"79912",
    "sg:province":"TX",
    "sg:tags":[
        "hawaiian",
        "barbeque"
    ],
    "wof:name":"Aloha Hawaiian Barbecue",
    "wof:placetype":"venue"
},
  "geometry": {"coordinates":[-106.568845,31.839697],"type":"Point"}
}