{
  "type": "Feature",
  "properties": {
    "iso:country":"US",
    "sg:address":"306 Kennedy Ave",
    "sg:city":"San Antonio",
    "sg:classifiers":[
        {
            "category":"Professional",
            "subcategory":"Business Services",
            "type":"Services"
        }
    ],
    "sg:phone":"+1 210 824 3595",
    "sg:postcode":"78209",
    "sg:province":"TX",
    "wof:name":"Anchor Partners Ltd",
    "wof:placetype":"venue"
},
  "geometry": {"coordinates":[-98.466753,29.47777],"type":"Point"}
}