{
  "type": "Feature",
  "properties": {
    "iso:country":"US",
    "sg:address":"7410 Remcon Cir Ste C5",
    "sg:city":"El Paso",
    "sg:classifiers":[
        {
            "category":"Shopping",
            "subcategory":"Bicycles & Sporting Goods",
            "type":"Retail Goods"
        }
    ],
    "sg:phone":"+1 915 584 1944",
    "sg:postcode":"79912",
    "sg:province":"TX",
    "wof:name":"Fitness Superstore the",
    "wof:placetype":"venue"
},
  "geometry": {"coordinates":[-106.56099,31.836584],"type":"Point"}
}