{
  "type": "Feature",
  "properties": {
    "iso:country":"US",
    "sg:address":"1049 N 3rd St",
    "sg:city":"Abilene",
    "sg:classifiers":[
        {
            "category":"Professional",
            "type":"Services"
        }
    ],
    "sg:phone":"+1 325 670 0669",
    "sg:postcode":"79601",
    "sg:province":"TX",
    "sg:tags":[
        "establishment"
    ],
    "wof:name":"Ldds Worldcom",
    "wof:placetype":"venue"
},
  "geometry": {"coordinates":[-99.733576,32.451495],"type":"Point"}
}