{
  "type": "Feature",
  "properties": {
    "iso:country":"US",
    "sg:address":"531 Hubbard Dr",
    "sg:city":"Rockwall",
    "sg:classifiers":[
        {
            "category":"Retail",
            "subcategory":"Repair Shop",
            "type":"Services"
        }
    ],
    "sg:phone":"+1 972 772 8287",
    "sg:postcode":"75032",
    "sg:province":"TX",
    "wof:name":"Max Services",
    "wof:placetype":"venue"
},
  "geometry": {"coordinates":[-96.484543,32.828989],"type":"Point"}
}