{
  "type": "Feature",
  "properties": {
    "iso:country":"US",
    "sg:address":"1316 James St",
    "sg:city":"Sweetwater",
    "sg:classifiers":[
        {
            "category":"Shopping",
            "type":"Retail Goods"
        }
    ],
    "sg:phone":"+1 325 235 0768",
    "sg:postcode":"79556",
    "sg:province":"TX",
    "sg:tags":[
        "merchandise"
    ],
    "wof:name":"Jims Rock Shop",
    "wof:placetype":"venue"
},
  "geometry": {"coordinates":[-100.39450600000001,32.477519],"type":"Point"}
}