{
  "type": "Feature",
  "properties": {
    "iso:country":"US",
    "sg:address":"1006 Edgemont Ct",
    "sg:city":"Allen",
    "sg:classifiers":[
        {
            "category":"Wholesale",
            "subcategory":"Vending Machines",
            "type":"Manufacturing & Wholesale Goods"
        }
    ],
    "sg:phone":"+1 972 390 0250",
    "sg:postcode":"75013",
    "sg:province":"TX",
    "sg:tags":[
        "operator"
    ],
    "wof:name":"D Enterprises",
    "wof:placetype":"venue"
},
  "geometry": {"coordinates":[-96.68916400000001,33.097576],"type":"Point"}
}