{
  "type": "Feature",
  "properties": {
    "iso:country":"US",
    "sg:address":"227 N Main St",
    "sg:city":"San Angelo",
    "sg:classifiers":[
        {
            "category":"Professional",
            "subcategory":"Detective & Security Services",
            "type":"Services"
        },
        {
            "category":"Manufacturing",
            "subcategory":"Electronics",
            "type":"Manufacturing & Wholesale Goods"
        }
    ],
    "sg:phone":"+1 325 655 1611",
    "sg:postcode":"76903",
    "sg:province":"TX",
    "sg:tags":[
        "sound",
        "equipment",
        "electrical",
        "system",
        "contractor"
    ],
    "wof:name":"Kay Gee Inc",
    "wof:placetype":"venue"
},
  "geometry": {"coordinates":[-100.432159,31.468508],"type":"Point"}
}