{
  "type": "Feature",
  "properties": {
    "iso:country":"US",
    "sg:address":"2908 Verkin",
    "sg:city":"La Marque",
    "sg:classifiers":[
        {
            "category":"Wholesale",
            "subcategory":"Computers",
            "type":"Manufacturing & Wholesale Goods"
        }
    ],
    "sg:phone":"+1 409 933 0110",
    "sg:postcode":"77568",
    "sg:province":"TX",
    "wof:name":"Shilo Enterprises",
    "wof:placetype":"venue"
},
  "geometry": {"coordinates":[-94.987493,29.369792],"type":"Point"}
}