{
  "type": "Feature",
  "properties": {
    "iso:country":"US",
    "sg:address":"903 Nueces St",
    "sg:city":"Austin",
    "sg:classifiers":[
        {
            "category":"Professional",
            "type":"Services"
        }
    ],
    "sg:phone":"+1 512 480 8680",
    "sg:postcode":"78701",
    "sg:province":"TX",
    "wof:name":"Made From Nature",
    "wof:placetype":"venue"
},
  "geometry": {"coordinates":[-97.74697500000001,30.273342],"type":"Point"}
}