{
  "type": "Feature",
  "properties": {
    "iso:country":"US",
    "sg:address":"1704 Half Moon Dr",
    "sg:city":"Wharton",
    "sg:classifiers":[
        {
            "category":"Professional",
            "subcategory":"Management & Consulting",
            "type":"Services"
        }
    ],
    "sg:phone":"+1 979 532 5951",
    "sg:postcode":"77488",
    "sg:province":"TX",
    "sg:tags":[
        "agricultural",
        "consultant"
    ],
    "wof:name":"Ag Services Of Texas Inc",
    "wof:placetype":"venue"
},
  "geometry": {"coordinates":[-96.041842,29.294457],"type":"Point"}
}