{
  "type": "Feature",
  "properties": {
    "iso:country":"US",
    "sg:address":"1991 FM 1960 E",
    "sg:city":"Houston",
    "sg:classifiers":[
        {
            "category":"Restaurant",
            "type":"Food & Drink"
        }
    ],
    "sg:phone":"+1 281 251 4313",
    "sg:postcode":"77073",
    "sg:province":"TX",
    "sg:tags":[
        "eating"
    ],
    "wof:name":"Dominos Pizza",
    "wof:placetype":"venue"
},
  "geometry": {"coordinates":[-95.402886,30.027218],"type":"Point"}
}