{
  "type": "Feature",
  "properties": {
    "iso:country":"US",
    "sg:address":"4530 Coody Ln",
    "sg:city":"Corpus Christi",
    "sg:classifiers":[
        {
            "category":"Shopping",
            "subcategory":"Gifts & Souvenirs",
            "type":"Retail Goods"
        }
    ],
    "sg:phone":"+1 361 779 8159",
    "sg:postcode":"78413",
    "sg:province":"TX",
    "sg:tags":[
        "novelty"
    ],
    "wof:name":"J D Gear",
    "wof:placetype":"venue"
},
  "geometry": {"coordinates":[-97.404569,27.691493],"type":"Point"}
}