{
  "type": "Feature",
  "properties": {
    "iso:country":"US",
    "sg:address":"14400 Northwest Fwy",
    "sg:city":"Houston",
    "sg:classifiers":[
        {
            "category":"Social Services",
            "subcategory":"Child Care",
            "type":"Services"
        }
    ],
    "sg:phone":"+1 713 462 7751",
    "sg:postcode":"77040",
    "sg:province":"TX",
    "sg:tags":[
        "day"
    ],
    "wof:name":"Wee Care Daycare",
    "wof:placetype":"venue"
},
  "geometry": {"coordinates":[-95.534102,29.864504],"type":"Point"}
}