{
  "type": "Feature",
  "properties": {
    "iso:country":"US",
    "sg:address":"900 E University Dr",
    "sg:city":"Mckinney",
    "sg:classifiers":[
        {
            "category":"Professional",
            "type":"Services"
        }
    ],
    "sg:phone":"+1 972 542 5623",
    "sg:postcode":"75069",
    "sg:province":"TX",
    "sg:tags":[
        "establishment"
    ],
    "wof:name":"YTA",
    "wof:placetype":"venue"
},
  "geometry": {"coordinates":[-96.60561,33.207226],"type":"Point"}
}