{
  "type": "Feature",
  "properties": {
    "iso:country":"US",
    "sg:address":"805 Pauline Ave",
    "sg:city":"Pasadena",
    "sg:classifiers":[
        {
            "category":"Social Services",
            "subcategory":"Child Care",
            "type":"Services"
        }
    ],
    "sg:phone":"+1 713 472 3944",
    "sg:postcode":"77502",
    "sg:province":"TX",
    "wof:name":"Gloria Vasquez",
    "wof:placetype":"venue"
},
  "geometry": {"coordinates":[-95.202899,29.67762],"type":"Point"}
}