{
  "type": "Feature",
  "properties": {
    "iso:country":"US",
    "sg:address":"3017 Foxton Cove",
    "sg:city":"Austin",
    "sg:classifiers":[
        {
            "category":"Wholesale",
            "subcategory":"Vending Machines",
            "type":"Manufacturing & Wholesale Goods"
        }
    ],
    "sg:phone":"+1 512 280 7659",
    "sg:postcode":"78748",
    "sg:province":"TX",
    "wof:name":"Vending Solutions",
    "wof:placetype":"venue"
},
  "geometry": {"coordinates":[-97.84151799999999,30.17839],"type":"Point"}
}