{
  "type": "Feature",
  "properties": {
    "iso:country":"US",
    "sg:address":"201 Shant St",
    "sg:city":"Austin",
    "sg:classifiers":[
        {
            "category":"Structure",
            "subcategory":"Office Building",
            "type":"Public Place"
        }
    ],
    "sg:phone":"+1 512 292 1445",
    "sg:postcode":"78748",
    "sg:province":"TX",
    "sg:tags":[
        "park"
    ],
    "wof:name":"Gvm Commercial Properties Inc",
    "wof:placetype":"venue"
},
  "geometry": {"coordinates":[-97.792824,30.169161],"type":"Point"}
}