{
  "type": "Feature",
  "properties": {
    "iso:country":"US",
    "sg:address":"1416 Redmond St",
    "sg:city":"Houston",
    "sg:classifiers":[
        {
            "category":"Professional",
            "subcategory":"Computer Services",
            "type":"Services"
        }
    ],
    "sg:phone":"+1 713 455 6080",
    "sg:postcode":"77015",
    "sg:province":"TX",
    "sg:tags":[
        "programing",
        "custom"
    ],
    "wof:name":"K K Computer Svc",
    "wof:placetype":"venue"
},
  "geometry": {"coordinates":[-95.166231,29.768106],"type":"Point"}
}