{
  "type": "Feature",
  "properties": {
    "iso:country":"US",
    "sg:address":"223 S Broadway St",
    "sg:city":"Jewett",
    "sg:classifiers":[
        {
            "category":"Place Of Worship",
            "subcategory":"Church",
            "type":"Public Place"
        },
        {
            "category":"Place Of Worship",
            "type":"Public Place"
        }
    ],
    "sg:phone":"+1 903 626 4003",
    "sg:postcode":"75846",
    "sg:province":"TX",
    "sg:tags":[
        "churches-united",
        "methodist",
        "churches-methodist"
    ],
    "sg:website":"http://www.jewettumc.org",
    "wof:name":"Jewett United Methodist Church",
    "wof:placetype":"venue"
},
  "geometry": {"coordinates":[-96.145408,31.361656],"type":"Point"}
}