{
  "type": "Feature",
  "properties": {
    "iso:country":"US",
    "sg:address":"799 E Pike Blvd",
    "sg:city":"Weslaco",
    "sg:classifiers":[
        {
            "category":"Freight",
            "type":"Transportation"
        }
    ],
    "sg:phone":"+1 956 973 0090",
    "sg:postcode":"78596",
    "sg:province":"TX",
    "sg:tags":[
        "commercial",
        "storage",
        "special"
    ],
    "wof:name":"Affordable Attic Ltd",
    "wof:placetype":"venue"
},
  "geometry": {"coordinates":[-97.982817,26.170084],"type":"Point"}
}