{
  "type": "Feature",
  "properties": {
    "iso:country":"US",
    "sg:address":"1118 Smith",
    "sg:city":"Waller",
    "sg:classifiers":[
        {
            "category":"Home & Garden",
            "subcategory":"Household Appliances",
            "type":"Retail Goods"
        }
    ],
    "sg:phone":"+1 936 372 3639",
    "sg:postcode":"77484",
    "sg:province":"TX",
    "wof:name":"S & N Appliances",
    "wof:placetype":"venue"
},
  "geometry": {"coordinates":[-95.925726,30.057502],"type":"Point"}
}