{
  "type": "Feature",
  "properties": {
    "iso:country":"US",
    "sg:address":"5205 N O Connor Blvd",
    "sg:city":"Irving",
    "sg:classifiers":[
        {
            "category":"Professional",
            "subcategory":"Business Services",
            "type":"Services"
        }
    ],
    "sg:phone":"+1 972 831 5000",
    "sg:postcode":"75039",
    "sg:province":"TX",
    "wof:name":"Fairmont Leasing Corporation",
    "wof:placetype":"venue"
},
  "geometry": {"coordinates":[-96.94107099999999,32.869448],"type":"Point"}
}