{
  "type": "Feature",
  "properties": {
    "iso:country":"US",
    "sg:address":"2409 Strand St",
    "sg:city":"Galveston",
    "sg:classifiers":[
        {
            "category":"Travel",
            "subcategory":"Travel Agent",
            "type":"Entertainment"
        }
    ],
    "sg:phone":"+1 409 621 4771",
    "sg:postcode":"77550",
    "sg:province":"TX",
    "sg:tags":[
        "operator",
        "tour"
    ],
    "wof:name":"Galveston Duck Tour",
    "wof:placetype":"venue"
},
  "geometry": {"coordinates":[-94.796618,29.306482],"type":"Point"}
}