{
  "type": "Feature",
  "properties": {
    "iso:country":"US",
    "sg:address":"6898 Telephone Rd",
    "sg:city":"Houston",
    "sg:classifiers":[
        {
            "category":"Retail",
            "subcategory":"Auto Repair",
            "type":"Services"
        }
    ],
    "sg:phone":"+1 713 645 5917",
    "sg:postcode":"77061",
    "sg:province":"TX",
    "sg:tags":[
        "repairing",
        "automobile"
    ],
    "wof:name":"Dynasty Car Mart",
    "wof:placetype":"venue"
},
  "geometry": {"coordinates":[-95.288826,29.66108],"type":"Point"}
}