{
  "type": "Feature",
  "properties": {
    "iso:country":"US",
    "sg:address":"16650 Royal Mile Ln",
    "sg:city":"Houston",
    "sg:classifiers":[
        {
            "category":"Professional",
            "type":"Services"
        }
    ],
    "sg:phone":"+1 281 859 3285",
    "sg:postcode":"77084",
    "sg:province":"TX",
    "wof:name":"Zerimar",
    "wof:placetype":"venue"
},
  "geometry": {"coordinates":[-95.653997,29.845084],"type":"Point"}
}