{
  "type": "Feature",
  "properties": {
    "iso:country":"US",
    "sg:address":"111 Congress Ave",
    "sg:city":"Austin",
    "sg:classifiers":[
        {
            "category":"Professional",
            "subcategory":"Business Services",
            "type":"Services"
        }
    ],
    "sg:phone":"+1 512 637 0845",
    "sg:postcode":"78701",
    "sg:province":"TX",
    "sg:tags":[
        "consultant",
        "coach"
    ],
    "wof:name":"Spire Consulting Group",
    "wof:placetype":"venue"
},
  "geometry": {"coordinates":[-97.744326,30.26388],"type":"Point"}
}