{
  "type": "Feature",
  "properties": {
    "iso:country":"US",
    "sg:address":"179 W Main St",
    "sg:city":"Lewisville",
    "sg:classifiers":[
        {
            "category":"Home & Garden",
            "subcategory":"Home Furnishings",
            "type":"Retail Goods"
        }
    ],
    "sg:phone":"+1 972 436 6961",
    "sg:postcode":"75057",
    "sg:province":"TX",
    "sg:tags":[
        "cutlery"
    ],
    "wof:name":"Southern Knife Company",
    "wof:placetype":"venue"
},
  "geometry": {"coordinates":[-96.995891,33.046378],"type":"Point"}
}