{
  "type": "Feature",
  "properties": {
    "iso:country":"US",
    "sg:address":"400 Nolana St",
    "sg:city":"Mcallen",
    "sg:classifiers":[
        {
            "category":"Shopping",
            "subcategory":"Jewelry",
            "type":"Retail Goods"
        }
    ],
    "sg:phone":"+1 956 994 8711",
    "sg:postcode":"78504",
    "sg:province":"TX",
    "sg:tags":[
        "jeweler"
    ],
    "wof:name":"Sterling Avenue",
    "wof:placetype":"venue"
},
  "geometry": {"coordinates":[-98.219509,26.238719],"type":"Point"}
}