{
  "type": "Feature",
  "properties": {
    "iso:country":"US",
    "sg:address":"2090 Hwy 157 N",
    "sg:city":"Mansfield",
    "sg:classifiers":[
        {
            "category":"Shopping",
            "type":"Retail Goods"
        }
    ],
    "sg:phone":"+1 817 453 2043",
    "sg:postcode":"76063",
    "sg:province":"TX",
    "sg:tags":[
        "pet",
        "food",
        "supply"
    ],
    "wof:name":"Petorama",
    "wof:placetype":"venue"
},
  "geometry": {"coordinates":[-97.143095,32.607783],"type":"Point"}
}