{
  "type": "Feature",
  "properties": {
    "iso:country":"US",
    "sg:address":"84244 Main Ct",
    "sg:city":"Killeen",
    "sg:classifiers":[
        {
            "category":"Arts & Performance",
            "subcategory":"Theater",
            "type":"Entertainment"
        }
    ],
    "sg:phone":"+1 254 539 4178",
    "sg:postcode":"76544",
    "sg:province":"TX",
    "sg:tags":[
        "entertainer",
        "group"
    ],
    "wof:name":"Kathy Torres",
    "wof:placetype":"venue"
},
  "geometry": {"coordinates":[-97.824493,31.113616],"type":"Point"}
}