{
  "type": "Feature",
  "properties": {
    "iso:country":"US",
    "sg:address":"105 W Valencia Dr",
    "sg:city":"Amarillo",
    "sg:classifiers":[
        {
            "category":"Shopping",
            "subcategory":"Gifts & Souvenirs",
            "type":"Retail Goods"
        }
    ],
    "sg:phone":"+1 806 351 8300",
    "sg:postcode":"79118",
    "sg:province":"TX",
    "wof:name":"Railsbird Roost",
    "wof:placetype":"venue"
},
  "geometry": {"coordinates":[-101.839309,35.09801],"type":"Point"}
}