{
  "type": "Feature",
  "properties": {
    "iso:country":"US",
    "sg:address":"107 Eagle Lakes Dr",
    "sg:city":"Friendswood",
    "sg:classifiers":[
        {
            "category":"Professional",
            "subcategory":"Business Services",
            "type":"Services"
        },
        {
            "category":"Professional",
            "subcategory":"Management & Consulting",
            "type":"Services"
        }
    ],
    "sg:phone":"+1 281 648 5239",
    "sg:postcode":"77546",
    "sg:province":"TX",
    "sg:tags":[
        "break",
        "coffee",
        "supply"
    ],
    "wof:name":"S & B Espresso Express",
    "wof:placetype":"venue"
},
  "geometry": {"coordinates":[-95.186837,29.500873],"type":"Point"}
}