{
  "type": "Feature",
  "properties": {
    "iso:country":"US",
    "sg:address":"102 Owl Tree Trl",
    "sg:city":"Greenville",
    "sg:classifiers":[
        {
            "category":"Shopping",
            "subcategory":"Clothing, Apparel, & Fashions",
            "type":"Retail Goods"
        }
    ],
    "sg:phone":"+1 903 455 7257",
    "sg:postcode":"75402",
    "sg:province":"TX",
    "wof:name":"A Merry Heart",
    "wof:placetype":"venue"
},
  "geometry": {"coordinates":[-96.08314,33.113208],"type":"Point"}
}