{
  "type": "Feature",
  "properties": {
    "iso:country":"US",
    "sg:address":"525 International Pkwy # 501",
    "sg:city":"Richardson",
    "sg:classifiers":[
        {
            "category":"Manufacturing",
            "subcategory":"Buildings",
            "type":"Manufacturing & Wholesale Goods"
        },
        {
            "category":"Home & Garden",
            "subcategory":"Home Furnishings",
            "type":"Retail Goods"
        },
        {
            "category":"Home & Garden",
            "subcategory":"Building Materials",
            "type":"Retail Goods"
        },
        {
            "category":"Building & Trades",
            "subcategory":"Construction",
            "type":"Services"
        },
        {
            "category":"Manufacturing",
            "subcategory":"Building Materials",
            "type":"Manufacturing & Wholesale Goods"
        }
    ],
    "sg:phone":"+1 972 234 1413",
    "sg:postcode":"75081",
    "sg:province":"TX",
    "sg:tags":[
        "sunroom",
        "installation",
        "windows-repair",
        "solarium",
        "contractor",
        "window",
        "doors",
        "frames",
        "accessory",
        "builder",
        "replacement"
    ],
    "wof:name":"Window Expo Dfw",
    "wof:placetype":"venue"
},
  "geometry": {"coordinates":[-96.708742,32.956406],"type":"Point"}
}