{
  "type": "Feature",
  "properties": {
    "iso:country":"US",
    "sg:address":"5813 Preston Rd",
    "sg:city":"Plano",
    "sg:classifiers":[
        {
            "category":"Home & Garden",
            "subcategory":"Furniture",
            "type":"Retail Goods"
        }
    ],
    "sg:phone":"+1 972 781 1888",
    "sg:postcode":"75093",
    "sg:province":"TX",
    "wof:name":"Fitz and Floyd Inc",
    "wof:placetype":"venue"
},
  "geometry": {"coordinates":[-96.795035,33.055195],"type":"Point"}
}