{
  "type": "Feature",
  "properties": {
    "iso:country":"US",
    "sg:address":"603 West 13th Street Suite 1A-184",
    "sg:city":"Austin",
    "sg:classifiers":[
        {
            "category":"Professional",
            "type":"Services"
        }
    ],
    "sg:phone":"+1 512 583 4247",
    "sg:postcode":"78701",
    "sg:province":"TX",
    "sg:tags":[
        "planning",
        "event"
    ],
    "sg:website":"www.graymask.net",
    "wof:name":"Graymask",
    "wof:placetype":"venue"
},
  "geometry": {"coordinates":[-97.746295,30.27671],"type":"Point"}
}