{
  "type": "Feature",
  "properties": {
    "iso:country":"US",
    "sg:address":"312 E Pioneer Dr",
    "sg:city":"Irving",
    "sg:classifiers":[
        {
            "category":"Autos & Motor Vehicles",
            "subcategory":"Auto Supplies",
            "type":"Retail Goods"
        }
    ],
    "sg:phone":"+1 972 785 2828",
    "sg:postcode":"75061",
    "sg:province":"TX",
    "sg:tags":[
        "tire"
    ],
    "wof:name":"Cheap Tires",
    "wof:placetype":"venue"
},
  "geometry": {"coordinates":[-96.943046,32.817716],"type":"Point"}
}