{
  "type": "Feature",
  "properties": {
    "iso:country":"US",
    "sg:address":"425 N Main St",
    "sg:city":"Keller",
    "sg:classifiers":[
        {
            "category":"Shopping",
            "subcategory":"Stationery & Office Supplies",
            "type":"Retail Goods"
        }
    ],
    "sg:phone":"+1 817 431 9726",
    "sg:postcode":"76248",
    "sg:province":"TX",
    "wof:name":"Keller Office Supply",
    "wof:placetype":"venue"
},
  "geometry": {"coordinates":[-97.253445,32.939254],"type":"Point"}
}