{
  "type": "Feature",
  "properties": {
    "iso:country":"US",
    "sg:address":"12727 Villawood Ln",
    "sg:city":"Houston",
    "sg:classifiers":[
        {
            "category":"Retail",
            "subcategory":"Laundry & Dry Cleaning",
            "type":"Services"
        }
    ],
    "sg:phone":"+1 713 501 7214",
    "sg:postcode":"77072",
    "sg:province":"TX",
    "wof:name":"N and R Interest",
    "wof:placetype":"venue"
},
  "geometry": {"coordinates":[-95.60624199999999,29.693976],"type":"Point"}
}