{
  "type": "Feature",
  "properties": {
    "iso:country":"US",
    "sg:address":"31479 State Hwy 249",
    "sg:city":"Pinehurst",
    "sg:classifiers":[
        {
            "category":"Building & Trades",
            "subcategory":"Construction",
            "type":"Services"
        }
    ],
    "sg:phone":"+1 281 356 2326",
    "sg:postcode":"77362",
    "sg:province":"TX",
    "sg:tags":[
        "underground",
        "utility",
        "contractor"
    ],
    "wof:name":"Tm Construction Inc",
    "wof:placetype":"venue"
},
  "geometry": {"coordinates":[-95.649294,30.124109],"type":"Point"}
}