{
  "type": "Feature",
  "properties": {
    "iso:country":"US",
    "sg:address":"4007 James Casey St Ste C150",
    "sg:city":"Austin",
    "sg:classifiers":[
        {
            "category":"Health Services",
            "subcategory":"Doctor",
            "type":"Services"
        }
    ],
    "sg:phone":"+1 512 443 5988",
    "sg:postcode":"78745",
    "sg:province":"TX",
    "wof:name":"Northway Robert III MD",
    "wof:placetype":"venue"
},
  "geometry": {"coordinates":[-97.77324400000001,30.227238],"type":"Point"}
}