{
  "type": "Feature",
  "properties": {
    "iso:country":"US",
    "sg:address":"643 Feamster Dr",
    "sg:city":"Houston",
    "sg:classifiers":[
        {
            "category":"Shopping",
            "subcategory":"Gifts & Souvenirs",
            "type":"Retail Goods"
        }
    ],
    "sg:phone":"+1 713 697 8639",
    "sg:postcode":"77022",
    "sg:province":"TX",
    "wof:name":"Imani Gifts N More",
    "wof:placetype":"venue"
},
  "geometry": {"coordinates":[-95.388716,29.835635],"type":"Point"}
}