{
  "type": "Feature",
  "properties": {
    "iso:country":"US",
    "sg:address":"6451 Aldine Bender Rd",
    "sg:city":"Humble",
    "sg:classifiers":[
        {
            "category":"Manufacturing",
            "subcategory":"Glass & Minerals",
            "type":"Manufacturing & Wholesale Goods"
        }
    ],
    "sg:phone":"+1 281 441 2128",
    "sg:postcode":"77396",
    "sg:province":"TX",
    "sg:tags":[
        "ready",
        "concrete",
        "mfg"
    ],
    "wof:name":"T X I",
    "wof:placetype":"venue"
},
  "geometry": {"coordinates":[-95.29280199999999,29.930682],"type":"Point"}
}