{
  "type": "Feature",
  "properties": {
    "iso:country":"US",
    "sg:address":"4203 Bull Creek Rd",
    "sg:city":"Austin",
    "sg:classifiers":[
        {
            "category":"Government",
            "subcategory":"Office",
            "type":"Public Place"
        }
    ],
    "sg:phone":"+1 512 465 3674",
    "sg:postcode":"78731",
    "sg:province":"TX",
    "sg:tags":[
        "general"
    ],
    "wof:name":"Pavement Management Section",
    "wof:placetype":"venue"
},
  "geometry": {"coordinates":[-97.754453,30.316156],"type":"Point"}
}