{
  "type": "Feature",
  "properties": {
    "iso:country":"US",
    "sg:address":"7011 Pecan St",
    "sg:city":"Frisco",
    "sg:classifiers":[
        {
            "category":"Insurance",
            "subcategory":"Insurance Agent",
            "type":"Services"
        }
    ],
    "sg:phone":"+1 972 377 0924",
    "sg:postcode":"75034",
    "sg:province":"TX",
    "wof:name":"Farmers Insurance Group",
    "wof:placetype":"venue"
},
  "geometry": {"coordinates":[-96.823446,33.148291],"type":"Point"}
}