{
  "type": "Feature",
  "properties": {
    "iso:country":"US",
    "sg:address":"4 Canyon Creek Dr",
    "sg:city":"Wimberley",
    "sg:classifiers":[
        {
            "category":"Social Services",
            "type":"Services"
        }
    ],
    "sg:phone":"+1 512 847 5728",
    "sg:postcode":"78676",
    "sg:province":"TX",
    "wof:name":"Eeyore Counseling Services",
    "wof:placetype":"venue"
},
  "geometry": {"coordinates":[-98.107423,30.021533],"type":"Point"}
}