{
  "type": "Feature",
  "properties": {
    "iso:country":"US",
    "sg:address":"1118 W 6th St",
    "sg:city":"Austin",
    "sg:classifiers":[
        {
            "category":"Shopping",
            "type":"Retail Goods"
        }
    ],
    "sg:phone":"+1 512 472 1831",
    "sg:postcode":"78703",
    "sg:province":"TX",
    "sg:tags":[
        "art",
        "jewelry",
        "gallery"
    ],
    "wof:name":"Positive Images Art & Unique Gifts",
    "wof:placetype":"venue"
},
  "geometry": {"coordinates":[-97.756699,30.272699],"type":"Point"}
}