{
  "type": "Feature",
  "properties": {
    "iso:country":"US",
    "sg:address":"1162 Valley View Mall",
    "sg:city":"Dallas",
    "sg:classifiers":[
        {
            "category":"Shopping",
            "subcategory":"Gifts & Souvenirs",
            "type":"Retail Goods"
        }
    ],
    "sg:phone":"+1 972 774 1063",
    "sg:postcode":"75240",
    "sg:province":"TX",
    "wof:name":"Calendar Club LLC",
    "wof:placetype":"venue"
},
  "geometry": {"coordinates":[-96.80908700000001,32.926904],"type":"Point"}
}