{
  "type": "Feature",
  "properties": {
    "iso:country":"US",
    "sg:address":"3217 Timberview Dr",
    "sg:city":"Denton",
    "sg:classifiers":[
        {
            "category":"Building & Trades",
            "subcategory":"Construction",
            "type":"Services"
        }
    ],
    "sg:phone":"+1 940 321 3858",
    "sg:postcode":"76210",
    "sg:province":"TX",
    "sg:tags":[
        "residential"
    ],
    "wof:name":"B & L",
    "wof:placetype":"venue"
},
  "geometry": {"coordinates":[-97.052893,33.136951],"type":"Point"}
}