{
  "type": "Feature",
  "properties": {
    "iso:country":"US",
    "sg:address":"18803 Atasca South Dr",
    "sg:city":"Humble",
    "sg:classifiers":[
        {
            "category":"Place Of Worship",
            "subcategory":"Church",
            "type":"Public Place"
        },
        {
            "category":"Place Of Worship",
            "type":"Public Place"
        }
    ],
    "sg:phone":"+1 281 323 1219",
    "sg:postcode":"77346",
    "sg:province":"TX",
    "sg:tags":[
        "christ",
        "churches-community"
    ],
    "wof:name":"Never Ending Faith Community Church",
    "wof:placetype":"venue"
},
  "geometry": {"coordinates":[-95.17505,29.989972],"type":"Point"}
}