{
  "type": "Feature",
  "properties": {
    "iso:country":"US",
    "sg:address":"10763 Gulf Fwy",
    "sg:city":"Houston",
    "sg:classifiers":[
        {
            "category":"Professional",
            "subcategory":"Accounting & Tax Preparation",
            "type":"Services"
        }
    ],
    "sg:phone":"+1 713 944 9734",
    "sg:postcode":"77034",
    "sg:province":"TX",
    "sg:tags":[
        "return"
    ],
    "wof:name":"H & R Block",
    "wof:placetype":"venue"
},
  "geometry": {"coordinates":[-95.238395,29.63705],"type":"Point"}
}