{
  "type": "Feature",
  "properties": {
    "iso:country":"US",
    "sg:address":"3112 Timber Brook Dr",
    "sg:city":"Plano",
    "sg:classifiers":[
        {
            "category":"Home & Garden",
            "subcategory":"Building Materials",
            "type":"Retail Goods"
        }
    ],
    "sg:phone":"+1 972 509 7401",
    "sg:postcode":"75074",
    "sg:province":"TX",
    "wof:name":"Wallcraft Wallcoverings",
    "wof:placetype":"venue"
},
  "geometry": {"coordinates":[-96.67205300000001,33.067795],"type":"Point"}
}