{
  "type": "Feature",
  "properties": {
    "iso:country":"US",
    "sg:address":"225 Lonely Oaks Ln",
    "sg:city":"Killeen",
    "sg:classifiers":[
        {
            "category":"Insurance",
            "subcategory":"Insurance Agent",
            "type":"Services"
        }
    ],
    "sg:phone":"+1 254 526 9598",
    "sg:postcode":"76542",
    "sg:province":"TX",
    "sg:tags":[
        "preparation",
        "tax",
        "return"
    ],
    "wof:name":"Aquila Insurance",
    "wof:placetype":"venue"
},
  "geometry": {"coordinates":[-97.7379,31.05827],"type":"Point"}
}