{
  "type": "Feature",
  "properties": {
    "iso:country":"US",
    "sg:address":"11703 Wind Song Cove",
    "sg:city":"Austin",
    "sg:classifiers":[
        {
            "category":"Building & Trades",
            "subcategory":"Plumbing",
            "type":"Services"
        }
    ],
    "sg:phone":"+1 512 219 0707",
    "sg:postcode":"78750",
    "sg:province":"TX",
    "sg:tags":[
        "conditioning",
        "air",
        "system",
        "contractor"
    ],
    "wof:name":"Roger Brown Air Conditioning",
    "wof:placetype":"venue"
},
  "geometry": {"coordinates":[-97.816287,30.454041],"type":"Point"}
}