{
  "type": "Feature",
  "properties": {
    "iso:country":"US",
    "sg:address":"9069 Garland Rd",
    "sg:city":"Dallas",
    "sg:classifiers":[
        {
            "category":"Wholesale",
            "subcategory":"Auto Parts",
            "type":"Manufacturing & Wholesale Goods"
        }
    ],
    "sg:phone":"+1 214 324 8082",
    "sg:postcode":"75218",
    "sg:province":"TX",
    "sg:tags":[
        "supply"
    ],
    "wof:name":"NAPA Auto Parts",
    "wof:placetype":"venue"
},
  "geometry": {"coordinates":[-96.708832,32.828383],"type":"Point"}
}