{
  "type": "Feature",
  "properties": {
    "iso:country":"US",
    "sg:address":"2203 New Mill Ln",
    "sg:city":"Arlington",
    "sg:classifiers":[
        {
            "category":"Professional",
            "type":"Services"
        }
    ],
    "sg:phone":"+1 817 891 7614",
    "sg:postcode":"76012",
    "sg:province":"TX",
    "wof:name":"Netprogrammercom LLC",
    "wof:placetype":"venue"
},
  "geometry": {"coordinates":[-97.146434,32.753282],"type":"Point"}
}