{
  "type": "Feature",
  "properties": {
    "iso:country":"US",
    "sg:address":"421 Springfield Rd",
    "sg:city":"San Antonio",
    "sg:classifiers":[
        {
            "category":"Building & Trades",
            "subcategory":"Construction",
            "type":"Services"
        }
    ],
    "sg:phone":"+1 210 661 9133",
    "sg:postcode":"78219",
    "sg:province":"TX",
    "sg:tags":[
        "painting"
    ],
    "wof:name":"Harper Carroll Ltd",
    "wof:placetype":"venue"
},
  "geometry": {"coordinates":[-98.402635,29.446628],"type":"Point"}
}