{
  "type": "Feature",
  "properties": {
    "iso:country":"US",
    "sg:address":"1343 W 43rd St",
    "sg:city":"Houston",
    "sg:classifiers":[
        {
            "category":"Shopping",
            "subcategory":"Beauty & Cosmetics",
            "type":"Retail Goods"
        }
    ],
    "sg:phone":"+1 713 263 7440",
    "sg:postcode":"77018",
    "sg:province":"TX",
    "sg:tags":[
        "supply"
    ],
    "sg:website":"www.sallybeauty.com",
    "wof:name":"Sally Beauty Supply",
    "wof:placetype":"venue"
},
  "geometry": {"coordinates":[-95.433978,29.828087],"type":"Point"}
}