{
  "type": "Feature",
  "properties": {
    "iso:country":"US",
    "sg:address":"3465 Finley Rd",
    "sg:city":"Irving",
    "sg:classifiers":[
        {
            "category":"Social Services",
            "subcategory":"Child Care",
            "type":"Services"
        }
    ],
    "sg:phone":"+1 972 255 4961",
    "sg:postcode":"75062",
    "sg:province":"TX",
    "sg:tags":[
        "nursery",
        "day"
    ],
    "sg:website":"http://www.allisonsplayhouse.com",
    "wof:name":"Allison's Clubhouse-Gym",
    "wof:placetype":"venue"
},
  "geometry": {"coordinates":[-96.992735,32.85095],"type":"Point"}
}