{
  "type": "Feature",
  "properties": {
    "iso:country":"US",
    "sg:address":"210 E Jones St",
    "sg:city":"Sherman",
    "sg:classifiers":[
        {
            "category":"Organizations",
            "subcategory":"Religious Organization",
            "type":"Services"
        }
    ],
    "sg:phone":"+1 903 892 3015",
    "sg:postcode":"75090",
    "sg:province":"TX",
    "sg:tags":[
        "church"
    ],
    "wof:name":"Grace Tabernacle",
    "wof:placetype":"venue"
},
  "geometry": {"coordinates":[-96.606461,33.634996],"type":"Point"}
}