{
  "type": "Feature",
  "properties": {
    "iso:country":"US",
    "sg:address":"414 W Loop 281",
    "sg:city":"Longview",
    "sg:classifiers":[
        {
            "category":"Shopping",
            "type":"Retail Goods"
        }
    ],
    "sg:phone":"+1 903 238 8021",
    "sg:postcode":"75605",
    "sg:province":"TX",
    "sg:tags":[
        "merchandise"
    ],
    "wof:name":"East Texas Spa",
    "wof:placetype":"venue"
},
  "geometry": {"coordinates":[-94.75794999999999,32.540627],"type":"Point"}
}