{
  "type": "Feature",
  "properties": {
    "iso:country":"US",
    "sg:address":"155 N 3rd St",
    "sg:city":"Raymondville",
    "sg:classifiers":[
        {
            "category":"Professional",
            "subcategory":"Lawyer & Legal Services",
            "type":"Services"
        }
    ],
    "sg:phone":"+1 956 690 0239",
    "sg:postcode":"78580",
    "sg:province":"TX",
    "sg:tags":[
        "attorney",
        "practice"
    ],
    "wof:name":"Hinojosa Annette C Atty At Law",
    "wof:placetype":"venue"
},
  "geometry": {"coordinates":[-97.788269,26.482413],"type":"Point"}
}