{
  "type": "Feature",
  "properties": {
    "iso:country":"US",
    "sg:address":"616 Conrad Hilton Blvd",
    "sg:city":"Cisco",
    "sg:classifiers":[
        {
            "category":"Shopping",
            "subcategory":"Used Merchandise",
            "type":"Retail Goods"
        }
    ],
    "sg:phone":"+1 254 442 2209",
    "sg:postcode":"76437",
    "sg:province":"TX",
    "sg:tags":[
        "antique"
    ],
    "wof:name":"Men's Store",
    "wof:placetype":"venue"
},
  "geometry": {"coordinates":[-98.980378,32.389572],"type":"Point"}
}