{
  "type": "Feature",
  "properties": {
    "iso:country":"US",
    "sg:address":"1501 N Elm St",
    "sg:city":"Denton",
    "sg:classifiers":[
        {
            "category":"Health Services",
            "subcategory":"Health Practitioner",
            "type":"Services"
        },
        {
            "category":"Health Services",
            "subcategory":"Chiropractor",
            "type":"Services"
        }
    ],
    "sg:phone":"+1 940 484 8309",
    "sg:postcode":"76201",
    "sg:province":"TX",
    "sg:tags":[
        "gambling",
        "addiction-information",
        "treatment",
        "chiropractic"
    ],
    "wof:name":"Spinal Rehabilitation",
    "wof:placetype":"venue"
},
  "geometry": {"coordinates":[-97.133545,33.226898],"type":"Point"}
}