{
  "type": "Feature",
  "properties": {
    "iso:country":"US",
    "sg:address":"1822 Hillshire Dr",
    "sg:city":"Deer Park",
    "sg:classifiers":[
        {
            "category":"Banks & Credit Unions",
            "subcategory":"Bank",
            "type":"Services"
        }
    ],
    "sg:phone":"+1 281 930 1826",
    "sg:postcode":"77536",
    "sg:province":"TX",
    "sg:tags":[
        "depository",
        "banking"
    ],
    "wof:name":"American Coin Currency A",
    "wof:placetype":"venue"
},
  "geometry": {"coordinates":[-95.137196,29.677748],"type":"Point"}
}