{
  "type": "Feature",
  "properties": {
    "iso:country":"US",
    "sg:address":"2524 W Oak St",
    "sg:city":"Denton",
    "sg:classifiers":[
        {
            "category":"Professional",
            "subcategory":"Business Services",
            "type":"Services"
        }
    ],
    "sg:phone":"+1 817 504 3711",
    "sg:postcode":"76201",
    "sg:province":"TX",
    "wof:name":"Avason Group",
    "wof:placetype":"venue"
},
  "geometry": {"coordinates":[-97.16407599999999,33.215581],"type":"Point"}
}