{
  "type": "Feature",
  "properties": {
    "iso:country":"US",
    "sg:address":"1217 Ave G",
    "sg:city":"Lubbock",
    "sg:classifiers":[
        {
            "category":"Food & Beverages",
            "subcategory":"Bakery",
            "type":"Retail Goods"
        }
    ],
    "sg:phone":"+1 806 744 2685",
    "sg:postcode":"79401",
    "sg:province":"TX",
    "sg:tags":[
        "baker",
        "eating"
    ],
    "wof:name":"Jimenez Bakery and Resturant",
    "wof:placetype":"venue"
},
  "geometry": {"coordinates":[-101.843131,33.583694],"type":"Point"}
}