{
  "type": "Feature",
  "properties": {
    "iso:country":"US",
    "sg:address":"16536 Park Row Blvd",
    "sg:city":"Houston",
    "sg:classifiers":[
        {
            "category":"Deli",
            "type":"Food & Drink"
        },
        {
            "category":"Restaurant",
            "type":"Food & Drink"
        }
    ],
    "sg:menulink":"http://www.allmenus.com/tx/houston/43773-murphys-deli/menu/",
    "sg:phone":"+1 281 398 9559",
    "sg:postcode":"77084",
    "sg:province":"TX",
    "sg:tags":[
        "deli",
        "american"
    ],
    "wof:name":"Murphy's Deli",
    "wof:placetype":"venue"
},
  "geometry": {"coordinates":[-95.669488,29.78933],"type":"Point"}
}