{
  "type": "Feature",
  "properties": {
    "iso:country":"US",
    "sg:address":"9311 Zebulon Dr",
    "sg:city":"San Antonio",
    "sg:classifiers":[
        {
            "category":"Professional",
            "subcategory":"Computer Services",
            "type":"Services"
        }
    ],
    "sg:phone":"+1 210 696 3993",
    "sg:postcode":"78240",
    "sg:province":"TX",
    "sg:tags":[
        "datum"
    ],
    "wof:name":"General Data Processing",
    "wof:placetype":"venue"
},
  "geometry": {"coordinates":[-98.624308,29.5301],"type":"Point"}
}