{
  "type": "Feature",
  "properties": {
    "iso:country":"US",
    "sg:address":"2032 Switzerland Ave",
    "sg:city":"Plano",
    "sg:classifiers":[
        {
            "category":"Manufacturing",
            "subcategory":"Retail Goods",
            "type":"Manufacturing & Wholesale Goods"
        }
    ],
    "sg:phone":"+1 972 596 8315",
    "sg:postcode":"75025",
    "sg:province":"TX",
    "sg:tags":[
        "marking",
        "devices",
        "mfg"
    ],
    "wof:name":"Marjorie A Bode",
    "wof:placetype":"venue"
},
  "geometry": {"coordinates":[-96.734606,33.080878],"type":"Point"}
}