{
  "type": "Feature",
  "properties": {
    "iso:country":"US",
    "sg:address":"12900 Preston Rd Ste 1050",
    "sg:city":"Dallas",
    "sg:classifiers":[
        {
            "category":"Professional",
            "subcategory":"Lawyer & Legal Services",
            "type":"Services"
        }
    ],
    "sg:phone":"+1 972 239 9055",
    "sg:postcode":"75230",
    "sg:province":"TX",
    "wof:name":"Ungerman Arthur I",
    "wof:placetype":"venue"
},
  "geometry": {"coordinates":[-96.803398,32.924999],"type":"Point"}
}