{
  "type": "Feature",
  "properties": {
    "iso:country":"US",
    "sg:address":"1400 S Co Rd 1129",
    "sg:city":"Midland",
    "sg:classifiers":[
        {
            "category":"Shopping",
            "subcategory":"Gifts & Souvenirs",
            "type":"Retail Goods"
        }
    ],
    "sg:phone":"+1 432 684 4886",
    "sg:postcode":"79706",
    "sg:province":"TX",
    "wof:name":"Gift Tree",
    "wof:placetype":"venue"
},
  "geometry": {"coordinates":[-101.98027999999999,32.021486],"type":"Point"}
}