{
  "type": "Feature",
  "properties": {
    "iso:country":"US",
    "sg:address":"1215 Regents Park Ct",
    "sg:city":"De Soto",
    "sg:classifiers":[
        {
            "category":"Banks & Credit Unions",
            "subcategory":"Financial Services",
            "type":"Services"
        }
    ],
    "sg:phone":"+1 972 296 6696",
    "sg:postcode":"75115",
    "sg:province":"TX",
    "sg:tags":[
        "fund",
        "investment"
    ],
    "wof:name":"Kakarla Family Ltd Partnership",
    "wof:placetype":"venue"
},
  "geometry": {"coordinates":[-96.879316,32.612915],"type":"Point"}
}