{
  "type": "Feature",
  "properties": {
    "iso:country":"US",
    "sg:address":"1200 Lakeway Dr Ste 8",
    "sg:city":"Austin",
    "sg:classifiers":[
        {
            "category":"Health Services",
            "subcategory":"Doctor",
            "type":"Services"
        }
    ],
    "sg:phone":"+1 512 261 3999",
    "sg:postcode":"78734",
    "sg:province":"TX",
    "sg:tags":[
        "psychologist"
    ],
    "wof:name":"DeVere Ross E PhD",
    "wof:placetype":"venue"
},
  "geometry": {"coordinates":[-97.982592,30.36274],"type":"Point"}
}