{
  "type": "Feature",
  "properties": {
    "iso:country":"US",
    "sg:address":"6880 Telephone Rd",
    "sg:city":"Houston",
    "sg:classifiers":[
        {
            "category":"Building & Trades",
            "subcategory":"Construction",
            "type":"Services"
        }
    ],
    "sg:phone":"+1 713 644 4477",
    "sg:postcode":"77061",
    "sg:province":"TX",
    "sg:tags":[
        "general",
        "painter",
        "contractor"
    ],
    "wof:name":"K C Contractors",
    "wof:placetype":"venue"
},
  "geometry": {"coordinates":[-95.288893,29.660798],"type":"Point"}
}