{
  "type": "Feature",
  "properties": {
    "iso:country":"US",
    "sg:address":"485 Rolling Hills Pl",
    "sg:city":"Lancaster",
    "sg:classifiers":[
        {
            "category":"Real Estate",
            "subcategory":"Real Estate Operator",
            "type":"Services"
        }
    ],
    "sg:phone":"+1 972 274 2531",
    "sg:postcode":"75146",
    "sg:province":"TX",
    "sg:tags":[
        "building",
        "apartment"
    ],
    "wof:name":"Creekwood Pl Apartments Homes",
    "wof:placetype":"venue"
},
  "geometry": {"coordinates":[-96.81861000000001,32.600184],"type":"Point"}
}