{
  "type": "Feature",
  "properties": {
    "iso:country":"US",
    "sg:address":"1253 Round Table Dr",
    "sg:city":"Dallas",
    "sg:classifiers":[
        {
            "category":"Communications",
            "subcategory":"Television Station",
            "type":"Services"
        }
    ],
    "sg:phone":"+1 214 631 8004",
    "sg:postcode":"75247",
    "sg:province":"TX",
    "wof:name":"Dallas Community Television",
    "wof:placetype":"venue"
},
  "geometry": {"coordinates":[-96.884399,32.831799],"type":"Point"}
}