{
  "type": "Feature",
  "properties": {
    "iso:country":"US",
    "sg:address":"4110 US Hwy 67",
    "sg:city":"Midlothian",
    "sg:classifiers":[
        {
            "category":"Freight",
            "type":"Transportation"
        }
    ],
    "sg:phone":"+1 972 723 9664",
    "sg:postcode":"76065",
    "sg:province":"TX",
    "sg:tags":[
        "commercial",
        "storage"
    ],
    "wof:name":"C & L Self Storage",
    "wof:placetype":"venue"
},
  "geometry": {"coordinates":[-96.976956,32.529216],"type":"Point"}
}