{
  "type": "Feature",
  "properties": {
    "iso:country":"US",
    "sg:address":"701 Military Pkwy Ste 24",
    "sg:city":"Mesquite",
    "sg:classifiers":[
        {
            "category":"Professional",
            "subcategory":"Employment Agencies",
            "type":"Services"
        }
    ],
    "sg:phone":"+1 972 289 2225",
    "sg:postcode":"75149",
    "sg:province":"TX",
    "sg:website":"www.laborready.com",
    "wof:name":"Labor Ready",
    "wof:placetype":"venue"
},
  "geometry": {"coordinates":[-96.606734,32.76747],"type":"Point"}
}