{
  "type": "Feature",
  "properties": {
    "iso:country":"US",
    "sg:address":"7320 Foster Dr",
    "sg:city":"Fort Worth",
    "sg:classifiers":[
        {
            "category":"Professional",
            "type":"Services"
        }
    ],
    "sg:phone":"+1 817 238 8554",
    "sg:postcode":"76135",
    "sg:province":"TX",
    "wof:name":"L&L Framing",
    "wof:placetype":"venue"
},
  "geometry": {"coordinates":[-97.44443699999999,32.814619],"type":"Point"}
}