{
  "type": "Feature",
  "properties": {
    "iso:country":"US",
    "sg:address":"2212 S Riverside Dr",
    "sg:city":"Fort Worth",
    "sg:classifiers":[
        {
            "category":"Retail",
            "subcategory":"Auto Repair",
            "type":"Services"
        }
    ],
    "sg:phone":"+1 817 536 8646",
    "sg:postcode":"76104",
    "sg:province":"TX",
    "sg:tags":[
        "glass",
        "replacement"
    ],
    "wof:name":"Action Car & Truck Glass",
    "wof:placetype":"venue"
},
  "geometry": {"coordinates":[-97.304408,32.720892],"type":"Point"}
}