{
  "type": "Feature",
  "properties": {
    "iso:country":"US",
    "sg:address":"5044 Byers Ave",
    "sg:city":"Fort Worth",
    "sg:classifiers":[
        {
            "category":"Professional",
            "subcategory":"Lawyer & Legal Services",
            "type":"Services"
        }
    ],
    "sg:phone":"+1 817 732 6571",
    "sg:postcode":"76107",
    "sg:province":"TX",
    "wof:name":"Cole Gary Attorney At Law",
    "wof:placetype":"venue"
},
  "geometry": {"coordinates":[-97.39607100000001,32.738756],"type":"Point"}
}