{
  "type": "Feature",
  "properties": {
    "iso:country":"US",
    "sg:address":"14222 Kimberley Ln",
    "sg:city":"Houston",
    "sg:classifiers":[
        {
            "category":"Wholesale",
            "subcategory":"Office Equipment",
            "type":"Manufacturing & Wholesale Goods"
        }
    ],
    "sg:phone":"+1 281 493 5335",
    "sg:postcode":"77079",
    "sg:province":"TX",
    "wof:name":"A L Sabas Inc",
    "wof:placetype":"venue"
},
  "geometry": {"coordinates":[-95.595423,29.776448],"type":"Point"}
}