{
  "type": "Feature",
  "properties": {
    "iso:country":"US",
    "sg:address":"4251 Park Ln",
    "sg:city":"Dallas",
    "sg:classifiers":[
        {
            "category":"Education",
            "subcategory":"Special Training",
            "type":"Public Place"
        }
    ],
    "sg:phone":"+1 214 352 4646",
    "sg:postcode":"75220",
    "sg:province":"TX",
    "sg:tags":[
        "school",
        "language"
    ],
    "wof:name":"Dallas Goethe Ctr Inc",
    "wof:placetype":"venue"
},
  "geometry": {"coordinates":[-96.835781,32.874134],"type":"Point"}
}