{
  "type": "Feature",
  "properties": {
    "iso:country":"US",
    "sg:address":"1201 Fisher Dr",
    "sg:city":"Tyler",
    "sg:classifiers":[
        {
            "category":"Professional",
            "type":"Services"
        }
    ],
    "sg:phone":"+1 903 526 3405",
    "sg:postcode":"75701",
    "sg:province":"TX",
    "wof:name":"Reserve At Lake Tyler Dev Mktg",
    "wof:placetype":"venue"
},
  "geometry": {"coordinates":[-95.313312,32.316887],"type":"Point"}
}