{
  "type": "Feature",
  "properties": {
    "iso:country":"US",
    "sg:address":"1515 Grove Blvd A",
    "sg:city":"Austin",
    "sg:classifiers":[
        {
            "category":"Social Services",
            "type":"Services"
        }
    ],
    "sg:phone":"+1 512 267 7233",
    "sg:postcode":"78741",
    "sg:province":"TX",
    "sg:website":"http://www.austin-safeplace.org",
    "wof:name":"Safe Place",
    "wof:placetype":"venue"
},
  "geometry": {"coordinates":[-97.70625,30.231318],"type":"Point"}
}