{
  "type": "Feature",
  "properties": {
    "iso:country":"US",
    "sg:address":"10114 Burgoyne Rd",
    "sg:city":"Houston",
    "sg:classifiers":[
        {
            "category":"Recreation",
            "type":"Entertainment"
        }
    ],
    "sg:phone":"+1 281 597 1009",
    "sg:postcode":"77042",
    "sg:province":"TX",
    "wof:name":"West Hston Ata Blckbelt Acdemy",
    "wof:placetype":"venue"
},
  "geometry": {"coordinates":[-95.55305,29.741643],"type":"Point"}
}