{
  "type": "Feature",
  "properties": {
    "iso:country":"US",
    "sg:address":"1426 Fairmont Pkwy",
    "sg:city":"La Porte",
    "sg:classifiers":[
        {
            "category":"Personal",
            "subcategory":"Beauty Salon",
            "type":"Services"
        }
    ],
    "sg:phone":"+1 281 470 2211",
    "sg:postcode":"77571",
    "sg:province":"TX",
    "sg:tags":[
        "manicuring"
    ],
    "wof:name":"D L Nails",
    "wof:placetype":"venue"
},
  "geometry": {"coordinates":[-95.032956,29.652199],"type":"Point"}
}