{
  "type": "Feature",
  "properties": {
    "iso:country":"US",
    "sg:address":"9807 Radley Dr",
    "sg:city":"Sugar Land",
    "sg:classifiers":[
        {
            "category":"Shopping",
            "subcategory":"Computers & Home Electronics",
            "type":"Retail Goods"
        }
    ],
    "sg:phone":"+1 281 561 8063",
    "sg:postcode":"77478",
    "sg:province":"TX",
    "sg:tags":[
        "equipment",
        "dealer"
    ],
    "wof:name":"Sy",
    "wof:placetype":"venue"
},
  "geometry": {"coordinates":[-95.63901300000001,29.672144],"type":"Point"}
}