{
  "type": "Feature",
  "properties": {
    "iso:country":"US",
    "sg:address":"6701 Gulfway Dr",
    "sg:city":"Groves",
    "sg:classifiers":[
        {
            "category":"Retail",
            "subcategory":"Auto Repair",
            "type":"Services"
        }
    ],
    "sg:phone":"+1 409 962 6805",
    "sg:postcode":"77619",
    "sg:province":"TX",
    "sg:tags":[
        "automotive"
    ],
    "wof:name":"Dejean Automotive",
    "wof:placetype":"venue"
},
  "geometry": {"coordinates":[-93.894436,29.939124],"type":"Point"}
}