{
  "type": "Feature",
  "properties": {
    "iso:country":"US",
    "sg:address":"2201 S Lamar Blvd",
    "sg:city":"Austin",
    "sg:classifiers":[
        {
            "category":"Autos & Motor Vehicles",
            "subcategory":"Automobile Sales",
            "type":"Retail Goods"
        }
    ],
    "sg:phone":"+1 512 707 8282",
    "sg:postcode":"78704",
    "sg:province":"TX",
    "sg:tags":[
        "car",
        "dealer"
    ],
    "wof:name":"Down Under Auto Sales",
    "wof:placetype":"venue"
},
  "geometry": {"coordinates":[-97.77422799999999,30.247404],"type":"Point"}
}