{
  "type": "Feature",
  "properties": {
    "iso:country":"US",
    "sg:address":"1404 Harvest Hill Ln",
    "sg:city":"Arlington",
    "sg:classifiers":[
        {
            "category":"Professional",
            "type":"Services"
        }
    ],
    "sg:phone":"+1 817 795 7491",
    "sg:postcode":"76014",
    "sg:province":"TX",
    "wof:name":"Juan Reyna",
    "wof:placetype":"venue"
},
  "geometry": {"coordinates":[-97.086935,32.699891],"type":"Point"}
}