{
  "type": "Feature",
  "properties": {
    "iso:country":"US",
    "sg:address":"1408 Wedgewood Ct",
    "sg:city":"Southlake",
    "sg:classifiers":[
        {
            "category":"Professional",
            "subcategory":"Business Services",
            "type":"Services"
        }
    ],
    "sg:phone":"+1 817 416 6388",
    "sg:postcode":"76092",
    "sg:province":"TX",
    "wof:name":"C M P Meeting Services",
    "wof:placetype":"venue"
},
  "geometry": {"coordinates":[-97.17211500000001,32.938176],"type":"Point"}
}