{
  "type": "Feature",
  "properties": {
    "iso:country":"US",
    "sg:address":"14030 Fm 2920 Rd",
    "sg:city":"Tomball",
    "sg:classifiers":[
        {
            "category":"Restaurant",
            "type":"Food & Drink"
        }
    ],
    "sg:menulink":"http://www.allmenus.com/tx/northwest-harris/16186-pauls-pizza-shop/menu/",
    "sg:phone":"+1 281 290 8855",
    "sg:postcode":"77377",
    "sg:province":"TX",
    "sg:tags":[
        "american",
        "pizza"
    ],
    "wof:name":"Paul's Pizza Shop",
    "wof:placetype":"venue"
},
  "geometry": {"coordinates":[-95.633036,30.089437],"type":"Point"}
}