{
  "type": "Feature",
  "properties": {
    "iso:country":"US",
    "sg:address":"1520 4th St",
    "sg:city":"Graham",
    "sg:classifiers":[
        {
            "category":"Retail",
            "subcategory":"Auto Repair",
            "type":"Services"
        }
    ],
    "sg:phone":"+1 940 549 6130",
    "sg:postcode":"76450",
    "sg:province":"TX",
    "sg:tags":[
        "repairing",
        "automobile"
    ],
    "wof:name":"Robert Burk Shop",
    "wof:placetype":"venue"
},
  "geometry": {"coordinates":[-98.567466,33.108388],"type":"Point"}
}