{
  "type": "Feature",
  "properties": {
    "iso:country":"US",
    "sg:address":"867 Elm Valley Dr",
    "sg:city":"Bulverde",
    "sg:classifiers":[
        {
            "category":"Professional",
            "type":"Services"
        }
    ],
    "sg:phone":"+1 830 980 7268",
    "sg:postcode":"78163",
    "sg:province":"TX",
    "wof:name":"Fisher Aviation",
    "wof:placetype":"venue"
},
  "geometry": {"coordinates":[-98.436194,29.784955],"type":"Point"}
}