{
  "type": "Feature",
  "properties": {
    "iso:country":"US",
    "sg:address":"5529 Bentwood Dr",
    "sg:city":"San Angelo",
    "sg:classifiers":[
        {
            "category":"Personal",
            "subcategory":"Beauty Salon",
            "type":"Services"
        }
    ],
    "sg:phone":"+1 325 224 3105",
    "sg:postcode":"76904",
    "sg:province":"TX",
    "sg:tags":[
        "shop"
    ],
    "wof:name":"Phoenix Room",
    "wof:placetype":"venue"
},
  "geometry": {"coordinates":[-100.474407,31.401179],"type":"Point"}
}