{
  "type": "Feature",
  "properties": {
    "iso:country":"US",
    "sg:address":"5769 Cullen Blvd",
    "sg:city":"Houston",
    "sg:classifiers":[
        {
            "category":"Retail",
            "subcategory":"Auto Repair",
            "type":"Services"
        }
    ],
    "sg:phone":"+1 713 748 2821",
    "sg:postcode":"77021",
    "sg:province":"TX",
    "sg:tags":[
        "automotive"
    ],
    "wof:name":"Brake Check",
    "wof:placetype":"venue"
},
  "geometry": {"coordinates":[-95.34822200000001,29.703106],"type":"Point"}
}