{
  "type": "Feature",
  "properties": {
    "iso:country":"US",
    "sg:address":"302 McIntyre Ave",
    "sg:city":"Taft",
    "sg:classifiers":[
        {
            "category":"Organizations",
            "subcategory":"Religious Organization",
            "type":"Services"
        }
    ],
    "sg:phone":"+1 361 528 2131",
    "sg:postcode":"78390",
    "sg:province":"TX",
    "sg:tags":[
        "church"
    ],
    "wof:name":"First United Methodist Church",
    "wof:placetype":"venue"
},
  "geometry": {"coordinates":[-97.3927,27.979876],"type":"Point"}
}