{
  "type": "Feature",
  "properties": {
    "iso:country":"US",
    "sg:address":"6034 W Courtyard Dr",
    "sg:city":"Austin",
    "sg:classifiers":[
        {
            "category":"Travel",
            "subcategory":"Travel Agent",
            "type":"Entertainment"
        }
    ],
    "sg:phone":"+1 512 345 8020",
    "sg:postcode":"78730",
    "sg:province":"TX",
    "sg:tags":[
        "agency",
        "bureau"
    ],
    "wof:name":"Adelman Travel Group",
    "wof:placetype":"venue"
},
  "geometry": {"coordinates":[-97.797562,30.354328],"type":"Point"}
}