{
  "type": "Feature",
  "properties": {
    "iso:country":"US",
    "sg:address":"3806 Manchaca Rd",
    "sg:city":"Austin",
    "sg:classifiers":[
        {
            "category":"Social Services",
            "type":"Services"
        }
    ],
    "sg:phone":"+1 512 444 2377",
    "sg:postcode":"78704",
    "sg:province":"TX",
    "sg:tags":[
        "human"
    ],
    "wof:name":"Global Impact",
    "wof:placetype":"venue"
},
  "geometry": {"coordinates":[-97.78476499999999,30.235387],"type":"Point"}
}