{
  "type": "Feature",
  "properties": {
    "iso:country":"US",
    "sg:address":"905 Fort Worth Hwy",
    "sg:city":"Weatherford",
    "sg:classifiers":[
        {
            "category":"Autos & Motor Vehicles",
            "subcategory":"Auto Supplies",
            "type":"Retail Goods"
        }
    ],
    "sg:phone":"+1 817 598 0333",
    "sg:postcode":"76086",
    "sg:province":"TX",
    "sg:tags":[
        "automotive",
        "tire",
        "repair"
    ],
    "sg:website":"http://www.texastiresales.com",
    "wof:name":"Texas Tire Sales",
    "wof:placetype":"venue"
},
  "geometry": {"coordinates":[-97.784271,32.758709],"type":"Point"}
}