{
  "type": "Feature",
  "properties": {
    "iso:country":"US",
    "sg:address":"4210 Broadway",
    "sg:city":"San Antonio",
    "sg:classifiers":[
        {
            "category":"Restaurant",
            "type":"Food & Drink"
        }
    ],
    "sg:phone":"+1 210 822 3358",
    "sg:postcode":"78209",
    "sg:province":"TX",
    "wof:name":"Earl Abels Food To Go",
    "wof:placetype":"venue"
},
  "geometry": {"coordinates":[-98.46368200000001,29.465627],"type":"Point"}
}