{
  "type": "Feature",
  "properties": {
    "iso:country":"US",
    "sg:address":"11103 West Ave",
    "sg:city":"San Antonio",
    "sg:classifiers":[
        {
            "category":"Professional",
            "subcategory":"Management & Consulting",
            "type":"Services"
        }
    ],
    "sg:phone":"+1 210 524 6514",
    "sg:postcode":"78213",
    "sg:province":"TX",
    "sg:tags":[
        "hospital"
    ],
    "wof:name":"Visionary Properties Inc",
    "wof:placetype":"venue"
},
  "geometry": {"coordinates":[-98.514151,29.541298],"type":"Point"}
}