{
  "type": "Feature",
  "properties": {
    "iso:country":"US",
    "sg:address":"4006 Belt Line Rd",
    "sg:city":"Addison",
    "sg:classifiers":[
        {
            "category":"Real Estate",
            "subcategory":"Real Estate Agent",
            "type":"Services"
        }
    ],
    "sg:phone":"+1 972 233 1566",
    "sg:postcode":"75001",
    "sg:province":"TX",
    "wof:name":"Centerstone Management Corp",
    "wof:placetype":"venue"
},
  "geometry": {"coordinates":[-96.845394,32.954186],"type":"Point"}
}