{
  "type": "Feature",
  "properties": {
    "iso:country":"US",
    "sg:address":"1600 W Harrison Ave",
    "sg:city":"Harlingen",
    "sg:classifiers":[
        {
            "category":"Manufacturing",
            "subcategory":"Food",
            "type":"Manufacturing & Wholesale Goods"
        },
        {
            "category":"Wholesale",
            "subcategory":"Groceries",
            "type":"Manufacturing & Wholesale Goods"
        }
    ],
    "sg:phone":"+1 956 423 3120",
    "sg:postcode":"78550",
    "sg:province":"TX",
    "sg:tags":[
        "baker",
        "packaged",
        "product",
        "mfg"
    ],
    "wof:name":"Earthgrains Co",
    "wof:placetype":"venue"
},
  "geometry": {"coordinates":[-97.71396300000001,26.19062],"type":"Point"}
}