{
  "type": "Feature",
  "properties": {
    "iso:country":"US",
    "sg:address":"911 Dusky Rose Ln",
    "sg:city":"Pasadena",
    "sg:classifiers":[
        {
            "category":"Professional",
            "type":"Services"
        }
    ],
    "sg:phone":"+1 713 946 7021",
    "sg:postcode":"77502",
    "sg:province":"TX",
    "wof:name":"Plk Products",
    "wof:placetype":"venue"
},
  "geometry": {"coordinates":[-95.221397,29.673856],"type":"Point"}
}