{
  "type": "Feature",
  "properties": {
    "iso:country":"US",
    "sg:address":"210 E Pafford St",
    "sg:city":"Del Rio",
    "sg:classifiers":[
        {
            "category":"Building & Trades",
            "subcategory":"Construction",
            "type":"Services"
        }
    ],
    "sg:phone":"+1 830 775 5440",
    "sg:postcode":"78840",
    "sg:province":"TX",
    "sg:tags":[
        "housing",
        "contractor",
        "commercial",
        "general"
    ],
    "wof:name":"Hill Jack Construction Co",
    "wof:placetype":"venue"
},
  "geometry": {"coordinates":[-100.89662,29.355108],"type":"Point"}
}