{
  "type": "Feature",
  "properties": {
    "iso:country":"US",
    "sg:address":"13755 Riverview Dr",
    "sg:city":"Woodway",
    "sg:classifiers":[
        {
            "category":"Building & Trades",
            "subcategory":"Construction",
            "type":"Services"
        }
    ],
    "sg:phone":"+1 254 709 3752",
    "sg:postcode":"76712",
    "sg:province":"TX",
    "sg:tags":[
        "wallcoverings-installation",
        "wallpaper",
        "painting",
        "contractor"
    ],
    "wof:name":"Todd Brock Painting",
    "wof:placetype":"venue"
},
  "geometry": {"coordinates":[-97.24420600000001,31.492218],"type":"Point"}
}