{
  "type": "Feature",
  "properties": {
    "iso:country":"US",
    "sg:address":"6850 N Shiloh Rd",
    "sg:city":"Garland",
    "sg:classifiers":[
        {
            "category":"Restaurant",
            "type":"Food & Drink"
        }
    ],
    "sg:menulink":"http://www.allmenus.com/tx/northeast/139453-quiznos-sub/menu/",
    "sg:phone":"+1 972 675 0396",
    "sg:postcode":"75044",
    "sg:province":"TX",
    "sg:tags":[
        "wrap",
        "american",
        "sandwich"
    ],
    "wof:name":"Quiznos Sub",
    "wof:placetype":"venue"
},
  "geometry": {"coordinates":[-96.663972,32.97728],"type":"Point"}
}