{
  "type": "Feature",
  "properties": {
    "iso:country":"US",
    "sg:address":"1205 Richmond Ave",
    "sg:city":"Houston",
    "sg:classifiers":[
        {
            "category":"Bars & Pubs",
            "type":"Food & Drink"
        }
    ],
    "sg:phone":"+1 713 521 2224",
    "sg:postcode":"77006",
    "sg:province":"TX",
    "sg:tags":[
        "drinking"
    ],
    "wof:name":"Decades",
    "wof:placetype":"venue"
},
  "geometry": {"coordinates":[-95.394609,29.734381],"type":"Point"}
}