{
  "type": "Feature",
  "properties": {
    "iso:country":"US",
    "sg:address":"1401 Clay Ave",
    "sg:city":"Waco",
    "sg:classifiers":[
        {
            "category":"Retail",
            "subcategory":"Auto Repair",
            "type":"Services"
        }
    ],
    "sg:phone":"+1 254 753 6580",
    "sg:postcode":"76706",
    "sg:province":"TX",
    "sg:tags":[
        "body",
        "automobile",
        "painting"
    ],
    "wof:name":"Lorenzo's Body Shop",
    "wof:placetype":"venue"
},
  "geometry": {"coordinates":[-97.13594500000001,31.544869],"type":"Point"}
}