{
  "type": "Feature",
  "properties": {
    "iso:country":"US",
    "sg:address":"3811 Turtle Creek Blvd",
    "sg:city":"Dallas",
    "sg:classifiers":[
        {
            "category":"Health Services",
            "subcategory":"Chiropractor",
            "type":"Services"
        }
    ],
    "sg:phone":"+1 214 357 9119",
    "sg:postcode":"75219",
    "sg:province":"TX",
    "wof:name":"Center For the Healing Arts West",
    "wof:placetype":"venue"
},
  "geometry": {"coordinates":[-96.80059799999999,32.8134],"type":"Point"}
}