{
  "type": "Feature",
  "properties": {
    "iso:country":"US",
    "sg:address":"9631 Railton St",
    "sg:city":"Houston",
    "sg:classifiers":[
        {
            "category":"Wholesale",
            "subcategory":"Durable Goods & Equipment",
            "type":"Manufacturing & Wholesale Goods"
        }
    ],
    "sg:phone":"+1 713 690 6005",
    "sg:postcode":"77080",
    "sg:province":"TX",
    "sg:tags":[
        "fire",
        "extinguisher"
    ],
    "wof:name":"Alpha Fire Protection Inc",
    "wof:placetype":"venue"
},
  "geometry": {"coordinates":[-95.53091000000001,29.828266],"type":"Point"}
}