{
  "type": "Feature",
  "properties": {
    "iso:country":"US",
    "sg:address":"3301 Northland Drive Suite 320",
    "sg:city":"Austin",
    "sg:classifiers":[
        {
            "category":"Professional",
            "subcategory":"Computer Services",
            "type":"Services"
        }
    ],
    "sg:phone":"+1 512 450 5171",
    "sg:postcode":"78731",
    "sg:province":"TX",
    "sg:website":"http://bypasslane.com/",
    "wof:name":"Bypass Lane",
    "wof:placetype":"venue"
},
  "geometry": {"coordinates":[-97.75704899999999,30.337418],"type":"Point"}
}