{
  "type": "Feature",
  "properties": {
    "iso:country":"US",
    "sg:address":"9852 Dyer St",
    "sg:city":"El Paso",
    "sg:classifiers":[
        {
            "category":"Personal",
            "subcategory":"Beauty Salon",
            "type":"Services"
        }
    ],
    "sg:phone":"+1 915 751 7091",
    "sg:postcode":"79924",
    "sg:province":"TX",
    "sg:tags":[
        "shop"
    ],
    "wof:name":"California Concept Northland",
    "wof:placetype":"venue"
},
  "geometry": {"coordinates":[-106.411118,31.895321],"type":"Point"}
}