{
  "type": "Feature",
  "properties": {
    "iso:country":"US",
    "sg:address":"1007 Carpenter St",
    "sg:city":"Bridgeport",
    "sg:classifiers":[
        {
            "category":"Building & Trades",
            "subcategory":"Pest Control",
            "type":"Services"
        }
    ],
    "sg:phone":"+1 940 683 1996",
    "sg:postcode":"76426",
    "sg:province":"TX",
    "wof:name":"Bug Less Pest Control",
    "wof:placetype":"venue"
},
  "geometry": {"coordinates":[-97.75788799999999,33.21258],"type":"Point"}
}