{
  "type": "Feature",
  "properties": {
    "iso:country":"US",
    "sg:address":"3918 Fry Ave",
    "sg:city":"Tyler",
    "sg:classifiers":[
        {
            "category":"Farming",
            "subcategory":"Livestock Farm",
            "type":"Manufacturing & Wholesale Goods"
        }
    ],
    "sg:phone":"+1 903 839 6724",
    "sg:postcode":"75701",
    "sg:province":"TX",
    "sg:tags":[
        "beef",
        "feedlot",
        "cattle"
    ],
    "wof:name":"Everett Evans",
    "wof:placetype":"venue"
},
  "geometry": {"coordinates":[-95.29321899999999,32.305821],"type":"Point"}
}