{
  "type": "Feature",
  "properties": {
    "iso:country":"US",
    "sg:address":"200 W Taylor Ave",
    "sg:city":"Morton",
    "sg:classifiers":[
        {
            "category":"Government",
            "subcategory":"Office",
            "type":"Public Place"
        }
    ],
    "sg:phone":"+1 806 266 5067",
    "sg:postcode":"79346",
    "sg:province":"TX",
    "sg:tags":[
        "de",
        "community"
    ],
    "wof:name":"Wes-Tex RES Cnsrvtion Dev Area",
    "wof:placetype":"venue"
},
  "geometry": {"coordinates":[-102.761572,33.724295],"type":"Point"}
}