{
  "type": "Feature",
  "properties": {
    "iso:country":"US",
    "sg:address":"1605 Rock Prairie Rd",
    "sg:city":"College Station",
    "sg:classifiers":[
        {
            "category":"Health Services",
            "subcategory":"Doctor",
            "type":"Services"
        }
    ],
    "sg:phone":"+1 979 764 1474",
    "sg:postcode":"77845",
    "sg:province":"TX",
    "sg:tags":[
        "medical"
    ],
    "wof:name":"Michael E Crawford MD Facc",
    "wof:placetype":"venue"
},
  "geometry": {"coordinates":[-96.287239,30.583729],"type":"Point"}
}