{
  "type": "Feature",
  "properties": {
    "iso:country":"US",
    "sg:address":"233 Linda Dr",
    "sg:city":"Sulphur Springs",
    "sg:classifiers":[
        {
            "category":"Building & Trades",
            "subcategory":"Electrical",
            "type":"Services"
        }
    ],
    "sg:phone":"+1 903 438 2451",
    "sg:postcode":"75482",
    "sg:province":"TX",
    "sg:tags":[
        "electrical",
        "electric",
        "contractor"
    ],
    "wof:name":"Industrial Electric Service",
    "wof:placetype":"venue"
},
  "geometry": {"coordinates":[-95.598758,33.122047],"type":"Point"}
}