{
  "type": "Feature",
  "properties": {
    "iso:country":"US",
    "sg:address":"2201 W Ennis Ave",
    "sg:city":"Ennis",
    "sg:classifiers":[
        {
            "category":"Food & Beverages",
            "subcategory":"Groceries & Convenience Stores",
            "type":"Retail Goods"
        }
    ],
    "sg:phone":"+1 972 875 4206",
    "sg:postcode":"75119",
    "sg:province":"TX",
    "wof:name":"KWIK Pantry",
    "wof:placetype":"venue"
},
  "geometry": {"coordinates":[-96.647825,32.319854],"type":"Point"}
}