{
  "type": "Feature",
  "properties": {
    "iso:country":"US",
    "sg:address":"2413 Forest Ct",
    "sg:city":"Mckinney",
    "sg:classifiers":[
        {
            "category":"Real Estate",
            "subcategory":"Real Estate Operator",
            "type":"Services"
        }
    ],
    "sg:phone":"+1 972 542 7446",
    "sg:postcode":"75070",
    "sg:province":"TX",
    "sg:tags":[
        "building",
        "apartment",
        "property",
        "lessor"
    ],
    "wof:name":"Vpkk Ltd",
    "wof:placetype":"venue"
},
  "geometry": {"coordinates":[-96.64517600000001,33.176834],"type":"Point"}
}