{
  "type": "Feature",
  "properties": {
    "iso:country":"US",
    "sg:address":"6311 N O Connor Blvd",
    "sg:city":"Irving",
    "sg:classifiers":[
        {
            "category":"Professional",
            "subcategory":"Computer Services",
            "type":"Services"
        },
        {
            "category":"Manufacturing",
            "subcategory":"Printing",
            "type":"Manufacturing & Wholesale Goods"
        }
    ],
    "sg:phone":"+1 972 869 7664",
    "sg:postcode":"75039",
    "sg:province":"TX",
    "sg:tags":[
        "training",
        "multimedia",
        "based"
    ],
    "sg:website":"www.seri.com",
    "wof:name":"Ser Imaging Inc",
    "wof:placetype":"venue"
},
  "geometry": {"coordinates":[-96.937028,32.893078],"type":"Point"}
}