{
  "type": "Feature",
  "properties": {
    "iso:country":"US",
    "sg:address":"1706 E Lamar St",
    "sg:city":"Sherman",
    "sg:classifiers":[
        {
            "category":"Shopping",
            "subcategory":"Discount & Variety Stores",
            "type":"Retail Goods"
        }
    ],
    "sg:phone":"+1 903 893 9593",
    "sg:postcode":"75090",
    "sg:province":"TX",
    "wof:name":"Dollar General",
    "wof:placetype":"venue"
},
  "geometry": {"coordinates":[-96.589167,33.63977],"type":"Point"}
}