{
  "type": "Feature",
  "properties": {
    "iso:country":"US",
    "sg:address":"10819 Knollwood Dr",
    "sg:city":"Tyler",
    "sg:classifiers":[
        {
            "category":"Personal",
            "subcategory":"Beauty Salon",
            "type":"Services"
        }
    ],
    "sg:phone":"+1 903 939 3807",
    "sg:postcode":"75703",
    "sg:province":"TX",
    "sg:tags":[
        "shop"
    ],
    "wof:name":"An Affair To Remember",
    "wof:placetype":"venue"
},
  "geometry": {"coordinates":[-95.346746,32.259684],"type":"Point"}
}