{
  "type": "Feature",
  "properties": {
    "iso:country":"US",
    "sg:address":"6222 Anita St",
    "sg:city":"Dallas",
    "sg:classifiers":[
        {
            "category":"Professional",
            "type":"Services"
        }
    ],
    "sg:phone":"+1 214 824 5786",
    "sg:postcode":"75214",
    "sg:province":"TX",
    "wof:name":"Donna J Harris",
    "wof:placetype":"venue"
},
  "geometry": {"coordinates":[-96.755737,32.834557],"type":"Point"}
}