{
  "type": "Feature",
  "properties": {
    "iso:country":"US",
    "sg:address":"1125 Grand Ave",
    "sg:city":"Bacliff",
    "sg:classifiers":[
        {
            "category":"Professional",
            "type":"Services"
        }
    ],
    "sg:phone":"+1 281 559 2233",
    "sg:postcode":"77518",
    "sg:province":"TX",
    "sg:tags":[
        "establishment"
    ],
    "wof:name":"Damon Met West",
    "wof:placetype":"venue"
},
  "geometry": {"coordinates":[-94.99429600000001,29.499237],"type":"Point"}
}