{
  "type": "Feature",
  "properties": {
    "iso:country":"US",
    "sg:address":"107 E 5th St",
    "sg:city":"Rio Grande City",
    "sg:classifiers":[
        {
            "category":"Social Services",
            "type":"Services"
        }
    ],
    "sg:phone":"+1 956 487 5521",
    "sg:postcode":"78582",
    "sg:province":"TX",
    "sg:tags":[
        "probation"
    ],
    "wof:name":"Starr County Probation Office",
    "wof:placetype":"venue"
},
  "geometry": {"coordinates":[-98.819473,26.382467],"type":"Point"}
}