{
  "type": "Feature",
  "properties": {
    "iso:country":"US",
    "sg:address":"903 E Hwy 377",
    "sg:city":"Granbury",
    "sg:classifiers":[
        {
            "category":"Food & Beverages",
            "subcategory":"Groceries & Convenience Stores",
            "type":"Retail Goods"
        }
    ],
    "sg:phone":"+1 817 573 2397",
    "sg:postcode":"76048",
    "sg:province":"TX",
    "wof:name":"Tommys Food Store 25",
    "wof:placetype":"venue"
},
  "geometry": {"coordinates":[-97.777137,32.434403],"type":"Point"}
}