{
  "type": "Feature",
  "properties": {
    "iso:country":"US",
    "sg:address":"2505 FM 1462",
    "sg:city":"Alvin",
    "sg:classifiers":[
        {
            "category":"Retail",
            "subcategory":"Auto Repair",
            "type":"Services"
        }
    ],
    "sg:phone":"+1 281 331 6450",
    "sg:postcode":"77511",
    "sg:province":"TX",
    "sg:tags":[
        "automotive"
    ],
    "wof:name":"Winstons 24 Hour Wrecker Svc",
    "wof:placetype":"venue"
},
  "geometry": {"coordinates":[-95.266689,29.397642],"type":"Point"}
}