{
  "type": "Feature",
  "properties": {
    "iso:country":"US",
    "sg:address":"11706 Canemont St",
    "sg:city":"Houston",
    "sg:classifiers":[
        {
            "category":"Professional",
            "type":"Services"
        }
    ],
    "sg:phone":"+1 713 726 9885",
    "sg:postcode":"77035",
    "sg:province":"TX",
    "sg:tags":[
        "establishment"
    ],
    "wof:name":"HRD Inc",
    "wof:placetype":"venue"
},
  "geometry": {"coordinates":[-95.503162,29.634004],"type":"Point"}
}