{
  "type": "Feature",
  "properties": {
    "iso:country":"US",
    "sg:address":"2695 Villa Creek Dr",
    "sg:city":"Dallas",
    "sg:classifiers":[
        {
            "category":"Insurance",
            "subcategory":"Insurance Agent",
            "type":"Services"
        }
    ],
    "sg:phone":"+1 972 484 1991",
    "sg:postcode":"75234",
    "sg:province":"TX",
    "wof:name":"Health Plan USA",
    "wof:placetype":"venue"
},
  "geometry": {"coordinates":[-96.882645,32.91205],"type":"Point"}
}