{
  "type": "Feature",
  "properties": {
    "iso:country":"US",
    "sg:address":"1701 Rogers Rd",
    "sg:city":"Fort Worth",
    "sg:classifiers":[
        {
            "category":"Real Estate",
            "subcategory":"Real Estate Operator",
            "type":"Services"
        }
    ],
    "sg:phone":"+1 817 336 1111",
    "sg:postcode":"76107",
    "sg:province":"TX",
    "sg:tags":[
        "building",
        "apartment"
    ],
    "wof:name":"Park Garden Apts",
    "wof:placetype":"venue"
},
  "geometry": {"coordinates":[-97.364785,32.724537],"type":"Point"}
}