{
  "type": "Feature",
  "properties": {
    "iso:country":"US",
    "sg:address":"4311 S 31st St",
    "sg:city":"Temple",
    "sg:classifiers":[
        {
            "category":"Personal",
            "subcategory":"Tanning Parlor",
            "type":"Services"
        },
        {
            "category":"Personal",
            "type":"Services"
        }
    ],
    "sg:phone":"+1 254 899 8267",
    "sg:postcode":"76502",
    "sg:province":"TX",
    "sg:tags":[
        "salon"
    ],
    "wof:name":"Aloha Tan",
    "wof:placetype":"venue"
},
  "geometry": {"coordinates":[-97.373176,31.059282],"type":"Point"}
}