{
  "type": "Feature",
  "properties": {
    "iso:country":"US",
    "sg:address":"1201 Hidden Hill Cir",
    "sg:city":"Austin",
    "sg:classifiers":[
        {
            "category":"Building & Trades",
            "subcategory":"Construction",
            "type":"Services"
        }
    ],
    "sg:phone":"+1 512 444 4916",
    "sg:postcode":"78745",
    "sg:province":"TX",
    "sg:tags":[
        "house"
    ],
    "wof:name":"Precision Fence & Remodel",
    "wof:placetype":"venue"
},
  "geometry": {"coordinates":[-97.798301,30.198093],"type":"Point"}
}