{
  "type": "Feature",
  "properties": {
    "iso:country":"US",
    "sg:address":"4680 Reunion Dr",
    "sg:city":"Plano",
    "sg:classifiers":[
        {
            "category":"Farming",
            "subcategory":"Farm",
            "type":"Manufacturing & Wholesale Goods"
        }
    ],
    "sg:phone":"+1 972 618 1159",
    "sg:postcode":"75024",
    "sg:province":"TX",
    "sg:tags":[
        "crop",
        "general"
    ],
    "wof:name":"J & J Tree Farms Inc",
    "wof:placetype":"venue"
},
  "geometry": {"coordinates":[-96.791179,33.080252],"type":"Point"}
}