{
  "type": "Feature",
  "properties": {
    "iso:country":"US",
    "sg:address":"1106 S Paisano St",
    "sg:city":"Rockport",
    "sg:classifiers":[
        {
            "category":"Wholesale",
            "subcategory":"Machinery & Supplies",
            "type":"Manufacturing & Wholesale Goods"
        }
    ],
    "sg:phone":"+1 361 729 9806",
    "sg:postcode":"78382",
    "sg:province":"TX",
    "sg:tags":[
        "hardware",
        "industrial"
    ],
    "wof:name":"Burton Tool & Supply",
    "wof:placetype":"venue"
},
  "geometry": {"coordinates":[-97.05059900000001,28.038765],"type":"Point"}
}