{
  "type": "Feature",
  "properties": {
    "iso:country":"US",
    "sg:address":"923 S Kings Hwy",
    "sg:city":"Nash",
    "sg:classifiers":[
        {
            "category":"Manufacturing",
            "subcategory":"Food",
            "type":"Manufacturing & Wholesale Goods"
        }
    ],
    "sg:phone":"+1 903 832 7020",
    "sg:postcode":"75569",
    "sg:province":"TX",
    "sg:tags":[
        "mfg"
    ],
    "wof:name":"Candy Bouquet",
    "wof:placetype":"venue"
},
  "geometry": {"coordinates":[-94.13004599999999,33.431424],"type":"Point"}
}