{
  "type": "Feature",
  "properties": {
    "iso:country":"US",
    "sg:address":"6215 Tierwester St",
    "sg:city":"Houston",
    "sg:classifiers":[
        {
            "category":"Professional",
            "subcategory":"Business Services",
            "type":"Services"
        }
    ],
    "sg:phone":"+1 713 842 2982",
    "sg:postcode":"77021",
    "sg:province":"TX",
    "wof:name":"Nicaragua Express",
    "wof:placetype":"venue"
},
  "geometry": {"coordinates":[-95.36359400000001,29.705099],"type":"Point"}
}