{
  "type": "Feature",
  "properties": {
    "iso:country":"US",
    "sg:address":"732 E Ovilla Rd",
    "sg:city":"Red Oak",
    "sg:classifiers":[
        {
            "category":"Organizations",
            "subcategory":"Religious Organization",
            "type":"Services"
        }
    ],
    "sg:phone":"+1 972 617 2338",
    "sg:postcode":"75154",
    "sg:province":"TX",
    "sg:tags":[
        "church"
    ],
    "wof:name":"East Ridge Baptist Church",
    "wof:placetype":"venue"
},
  "geometry": {"coordinates":[-96.87036000000001,32.531882],"type":"Point"}
}