{
  "type": "Feature",
  "properties": {
    "iso:country":"US",
    "sg:address":"117 Magnolia Dr",
    "sg:city":"Ferris",
    "sg:classifiers":[
        {
            "category":"Banks & Credit Unions",
            "subcategory":"Investment Brokerage",
            "type":"Services"
        }
    ],
    "sg:phone":"+1 972 544 2525",
    "sg:postcode":"75125",
    "sg:province":"TX",
    "sg:tags":[
        "security"
    ],
    "wof:name":"Time Out Investments",
    "wof:placetype":"venue"
},
  "geometry": {"coordinates":[-96.655705,32.536002],"type":"Point"}
}