{
  "type": "Feature",
  "properties": {
    "iso:country":"US",
    "sg:address":"914 Grandview Ave",
    "sg:city":"Dallas",
    "sg:classifiers":[
        {
            "category":"Utilities",
            "subcategory":"Telephone",
            "type":"Services"
        }
    ],
    "sg:phone":"+1 214 824 2277",
    "sg:postcode":"75223",
    "sg:province":"TX",
    "sg:tags":[
        "communications"
    ],
    "wof:name":"Dallasartsrevuecom",
    "wof:placetype":"venue"
},
  "geometry": {"coordinates":[-96.74764500000001,32.798237],"type":"Point"}
}