{
  "type": "Feature",
  "properties": {
    "iso:country":"US",
    "sg:address":"20434 Drakewood Dr",
    "sg:city":"Katy",
    "sg:classifiers":[
        {
            "category":"Fast Food",
            "type":"Food & Drink"
        },
        {
            "category":"Restaurant",
            "type":"Food & Drink"
        }
    ],
    "sg:phone":"+1 281 578 0790",
    "sg:postcode":"77449",
    "sg:province":"TX",
    "sg:tags":[
        "hot",
        "hamburger",
        "dog"
    ],
    "wof:name":"Dogs 2717",
    "wof:placetype":"venue"
},
  "geometry": {"coordinates":[-95.72759600000001,29.826399],"type":"Point"}
}