{
  "type": "Feature",
  "properties": {
    "iso:country":"US",
    "sg:address":"7 Pizarro Ave",
    "sg:city":"Olmito",
    "sg:classifiers":[
        {
            "category":"Banks & Credit Unions",
            "subcategory":"Bank",
            "type":"Services"
        }
    ],
    "sg:phone":"+1 956 350 8860",
    "sg:postcode":"78575",
    "sg:province":"TX",
    "sg:tags":[
        "mortgage",
        "loan",
        "broker",
        "real estate"
    ],
    "wof:name":"American Home Mortgage",
    "wof:placetype":"venue"
},
  "geometry": {"coordinates":[-97.547904,26.040331],"type":"Point"}
}