{
  "type": "Feature",
  "properties": {
    "iso:country":"US",
    "sg:address":"989 Turpin Lake Rd",
    "sg:city":"Poolville",
    "sg:classifiers":[
        {
            "category":"Retail",
            "subcategory":"Animal Services",
            "type":"Services"
        }
    ],
    "sg:phone":"+1 817 594 7720",
    "sg:postcode":"76487",
    "sg:province":"TX",
    "sg:tags":[
        "farm",
        "raw",
        "product",
        "material"
    ],
    "wof:name":"Rudibaugh Training",
    "wof:placetype":"venue"
},
  "geometry": {"coordinates":[-97.887445,32.992349],"type":"Point"}
}