{
  "type": "Feature",
  "properties": {
    "iso:country":"US",
    "sg:address":"16102 Cutten Rd",
    "sg:city":"Houston",
    "sg:classifiers":[
        {
            "category":"Professional",
            "subcategory":"Management & Consulting",
            "type":"Services"
        }
    ],
    "sg:phone":"+1 713 655 9556",
    "sg:postcode":"77070",
    "sg:province":"TX",
    "wof:name":"Comtex",
    "wof:placetype":"venue"
},
  "geometry": {"coordinates":[-95.56956,30.004367],"type":"Point"}
}