{
  "type": "Feature",
  "properties": {
    "iso:country":"US",
    "sg:address":"2311 Cypress Pt E",
    "sg:city":"Austin",
    "sg:classifiers":[
        {
            "category":"Real Estate",
            "subcategory":"Real Estate Operator",
            "type":"Services"
        }
    ],
    "sg:phone":"+1 512 327 3885",
    "sg:postcode":"78746",
    "sg:province":"TX",
    "sg:tags":[
        "building",
        "apartment"
    ],
    "wof:name":"Pointsouth Apartments",
    "wof:placetype":"venue"
},
  "geometry": {"coordinates":[-97.84303800000001,30.278907],"type":"Point"}
}