{
  "type": "Feature",
  "properties": {
    "iso:country":"US",
    "sg:address":"2631 Willowbrook Rd",
    "sg:city":"Dallas",
    "sg:classifiers":[
        {
            "category":"Wholesale",
            "subcategory":"Metals & Minerals",
            "type":"Manufacturing & Wholesale Goods"
        }
    ],
    "sg:phone":"+1 214 352 1089",
    "sg:postcode":"75220",
    "sg:province":"TX",
    "sg:tags":[
        "pipe"
    ],
    "wof:name":"Pipe N Heads",
    "wof:placetype":"venue"
},
  "geometry": {"coordinates":[-96.881389,32.861631],"type":"Point"}
}