{
  "type": "Feature",
  "properties": {
    "iso:country":"US",
    "sg:address":"4715 Chapel Hill Rd",
    "sg:city":"Dallas",
    "sg:classifiers":[
        {
            "category":"Banks & Credit Unions",
            "subcategory":"Financial Services",
            "type":"Services"
        }
    ],
    "sg:phone":"+1 214 828 9922",
    "sg:postcode":"75214",
    "sg:province":"TX",
    "sg:tags":[
        "investor"
    ],
    "wof:name":"Chapel Hill Investments Ltd",
    "wof:placetype":"venue"
},
  "geometry": {"coordinates":[-96.73200199999999,32.847513],"type":"Point"}
}