{
  "type": "Feature",
  "properties": {
    "iso:country":"US",
    "sg:address":"2311 Cedar Springs Rd",
    "sg:city":"Dallas",
    "sg:classifiers":[
        {
            "category":"Professional",
            "subcategory":"Lawyer & Legal Services",
            "type":"Services"
        }
    ],
    "sg:phone":"+1 214 922 7560",
    "sg:postcode":"75201",
    "sg:province":"TX",
    "sg:tags":[
        "attorney"
    ],
    "wof:name":"Paul E Galvin Law Offices",
    "wof:placetype":"venue"
},
  "geometry": {"coordinates":[-96.805396,32.796184],"type":"Point"}
}