{
  "type": "Feature",
  "properties": {
    "iso:country":"US",
    "sg:address":"1225 Texas St",
    "sg:city":"Houston",
    "sg:classifiers":[
        {
            "category":"Social Services",
            "type":"Services"
        }
    ],
    "sg:phone":"+1 713 229 8319",
    "sg:postcode":"77002",
    "sg:province":"TX",
    "sg:tags":[
        "organization",
        "welfare"
    ],
    "wof:name":"Houston Compass Inc",
    "wof:placetype":"venue"
},
  "geometry": {"coordinates":[-95.360077,29.758597],"type":"Point"}
}