{
  "type": "Feature",
  "properties": {
    "iso:country":"US",
    "sg:address":"3301 Oakdale Ct",
    "sg:city":"Hurst",
    "sg:classifiers":[
        {
            "category":"Wholesale",
            "subcategory":"Groceries",
            "type":"Manufacturing & Wholesale Goods"
        }
    ],
    "sg:phone":"+1 817 656 3393",
    "sg:postcode":"76054",
    "sg:province":"TX",
    "wof:name":"Energy Man",
    "wof:placetype":"venue"
},
  "geometry": {"coordinates":[-97.18134499999999,32.880426],"type":"Point"}
}