{
  "type": "Feature",
  "properties": {
    "iso:country":"US",
    "sg:address":"14800 Landmark Blvd",
    "sg:city":"Dallas",
    "sg:classifiers":[
        {
            "category":"Professional",
            "subcategory":"Management & Consulting",
            "type":"Services"
        }
    ],
    "sg:phone":"+1 972 392 1788",
    "sg:postcode":"75254",
    "sg:province":"TX",
    "wof:name":"American Express",
    "wof:placetype":"venue"
},
  "geometry": {"coordinates":[-96.827975,32.950547],"type":"Point"}
}