{
  "type": "Feature",
  "properties": {
    "iso:country":"US",
    "sg:address":"100 Congress Ave",
    "sg:city":"Austin",
    "sg:classifiers":[
        {
            "category":"Real Estate",
            "subcategory":"Architect",
            "type":"Services"
        }
    ],
    "sg:phone":"+1 512 410 7398",
    "sg:postcode":"78701",
    "sg:province":"TX",
    "sg:tags":[
        "architects'",
        "specification",
        "builders'",
        "construction",
        "architectural"
    ],
    "wof:name":"Austin Software Architects",
    "wof:placetype":"venue"
},
  "geometry": {"coordinates":[-97.744347,30.263825],"type":"Point"}
}