{
  "type": "Feature",
  "properties": {
    "iso:country":"US",
    "sg:address":"151 Southwest Plz",
    "sg:city":"Arlington",
    "sg:classifiers":[
        {
            "category":"Wholesale",
            "subcategory":"Hardware",
            "type":"Manufacturing & Wholesale Goods"
        }
    ],
    "sg:phone":"+1 817 429 4411",
    "sg:postcode":"76016",
    "sg:province":"TX",
    "sg:tags":[
        "equipment",
        "energy",
        "solar"
    ],
    "wof:name":"Sunrise Solar",
    "wof:placetype":"venue"
},
  "geometry": {"coordinates":[-97.19879899999999,32.675612],"type":"Point"}
}