{
  "type": "Feature",
  "properties": {
    "iso:country":"US",
    "sg:address":"5318 Westerham",
    "sg:city":"Fulshear",
    "sg:classifiers":[
        {
            "category":"Real Estate",
            "subcategory":"Real Estate Agent",
            "type":"Services"
        }
    ],
    "sg:phone":"+1 281 346 0400",
    "sg:postcode":"77441",
    "sg:province":"TX",
    "wof:name":"Remi Properties",
    "wof:placetype":"venue"
},
  "geometry": {"coordinates":[-95.941677,29.67826],"type":"Point"}
}