{
  "type": "Feature",
  "properties": {
    "iso:country":"US",
    "sg:address":"4367 Springview Dr",
    "sg:city":"San Antonio",
    "sg:classifiers":[
        {
            "category":"Professional",
            "subcategory":"Business Services",
            "type":"Services"
        }
    ],
    "sg:phone":"+1 210 337 1880",
    "sg:postcode":"78222",
    "sg:province":"TX",
    "wof:name":"Sew True",
    "wof:placetype":"venue"
},
  "geometry": {"coordinates":[-98.410595,29.378841],"type":"Point"}
}