{
  "type": "Feature",
  "properties": {
    "iso:country":"US",
    "sg:address":"219 Billings St",
    "sg:city":"Arlington",
    "sg:classifiers":[
        {
            "category":"Professional",
            "type":"Services"
        }
    ],
    "sg:phone":"+1 817 633 2112",
    "sg:postcode":"76010",
    "sg:province":"TX",
    "wof:name":"Garrett Bros Inc",
    "wof:placetype":"venue"
},
  "geometry": {"coordinates":[-97.057159,32.734707],"type":"Point"}
}