{
  "type": "Feature",
  "properties": {
    "iso:country":"US",
    "sg:address":"3913 Rawlins St",
    "sg:city":"Dallas",
    "sg:classifiers":[
        {
            "category":"Building & Trades",
            "subcategory":"Cleaning & Sanitation",
            "type":"Services"
        }
    ],
    "sg:phone":"+1 214 404 5007",
    "sg:postcode":"75219",
    "sg:province":"TX",
    "sg:tags":[
        "home"
    ],
    "sg:website":"DallasCommercialCleaning.com",
    "wof:name":"Dallas Commercial Cleaning",
    "wof:placetype":"venue"
},
  "geometry": {"coordinates":[-96.808537,32.812098],"type":"Point"}
}