{
  "type": "Feature",
  "properties": {
    "iso:country":"US",
    "sg:address":"1111 Coker St",
    "sg:city":"Irving",
    "sg:classifiers":[
        {
            "category":"Restaurant",
            "type":"Food & Drink"
        }
    ],
    "sg:phone":"+1 972 258 1400",
    "sg:postcode":"75062",
    "sg:province":"TX",
    "wof:name":"Lunch Plus",
    "wof:placetype":"venue"
},
  "geometry": {"coordinates":[-96.959412,32.853601],"type":"Point"}
}