{
  "type": "Feature",
  "properties": {
    "iso:country":"US",
    "sg:address":"4010 Coryell Way",
    "sg:city":"Mesquite",
    "sg:classifiers":[
        {
            "category":"Education",
            "subcategory":"School",
            "type":"Public Place"
        }
    ],
    "sg:phone":"+1 972 290 4120",
    "sg:postcode":"75150",
    "sg:province":"TX",
    "sg:website":"www.mesquiteisd.org",
    "wof:name":"Mesquite Independent School District",
    "wof:placetype":"venue"
},
  "geometry": {"coordinates":[-96.62238600000001,32.81672],"type":"Point"}
}