{
  "type": "Feature",
  "properties": {
    "iso:country":"US",
    "sg:address":"18231 Openforest",
    "sg:city":"San Antonio",
    "sg:classifiers":[
        {
            "category":"Health Services",
            "subcategory":"Doctor",
            "type":"Services"
        }
    ],
    "sg:phone":"+1 210 499 5878",
    "sg:postcode":"78259",
    "sg:province":"TX",
    "sg:tags":[
        "anesthetist",
        "medical"
    ],
    "wof:name":"Bernatek Anesthesia Servi",
    "wof:placetype":"venue"
},
  "geometry": {"coordinates":[-98.429181,29.608956],"type":"Point"}
}