{
  "type": "Feature",
  "properties": {
    "iso:country":"US",
    "sg:address":"8128 Barclay St",
    "sg:city":"Dallas",
    "sg:classifiers":[
        {
            "category":"Real Estate",
            "subcategory":"Real Estate Agent",
            "type":"Services"
        },
        {
            "category":"Real Estate",
            "subcategory":"Real Estate Operator",
            "type":"Services"
        }
    ],
    "sg:phone":"+1 214 381 5193",
    "sg:postcode":"75227",
    "sg:province":"TX",
    "sg:tags":[
        "apartment"
    ],
    "wof:name":"Barclay Manor Apartments",
    "wof:placetype":"venue"
},
  "geometry": {"coordinates":[-96.680745,32.749942],"type":"Point"}
}