{
  "type": "Feature",
  "properties": {
    "iso:country":"US",
    "sg:address":"1629 N Town East Blvd",
    "sg:city":"Mesquite",
    "sg:classifiers":[
        {
            "category":"Shopping",
            "subcategory":"Department Store",
            "type":"Retail Goods"
        }
    ],
    "sg:phone":"+1 972 681 9071",
    "sg:postcode":"75150",
    "sg:province":"TX",
    "wof:name":"Target Stores",
    "wof:placetype":"venue"
},
  "geometry": {"coordinates":[-96.625198,32.810398],"type":"Point"}
}