{
  "type": "Feature",
  "properties": {
    "iso:country":"US",
    "sg:address":"8200 Wilcrest Dr",
    "sg:city":"Houston",
    "sg:classifiers":[
        {
            "category":"Personal",
            "subcategory":"Beauty Salon",
            "type":"Services"
        }
    ],
    "sg:phone":"+1 281 988 6743",
    "sg:postcode":"77072",
    "sg:province":"TX",
    "sg:tags":[
        "shop"
    ],
    "wof:name":"D & L Beauty Salon",
    "wof:placetype":"venue"
},
  "geometry": {"coordinates":[-95.570033,29.687568],"type":"Point"}
}