{
  "type": "Feature",
  "properties": {
    "iso:country":"US",
    "sg:address":"9786 Skillman St",
    "sg:city":"Dallas",
    "sg:classifiers":[
        {
            "category":"Health Services",
            "subcategory":"Clinic",
            "type":"Services"
        }
    ],
    "sg:phone":"+1 214 221 8181",
    "sg:postcode":"75243",
    "sg:province":"TX",
    "sg:tags":[
        "home"
    ],
    "sg:website":"www.guardianhealthsystems.com",
    "wof:name":"Guardian Health Systems",
    "wof:placetype":"venue"
},
  "geometry": {"coordinates":[-96.706868,32.908327],"type":"Point"}
}