{
  "type": "Feature",
  "properties": {
    "iso:country":"US",
    "sg:address":"3257 Bee Caves Rd",
    "sg:city":"Austin",
    "sg:classifiers":[
        {
            "category":"Restaurant",
            "type":"Food & Drink"
        },
        {
            "category":"Bakery",
            "type":"Food & Drink"
        },
        {
            "category":"Donuts",
            "subcategory":"None",
            "type":"Food & Drink"
        }
    ],
    "sg:phone":"+1 512 732 0000",
    "sg:postcode":"78746",
    "sg:province":"TX",
    "sg:tags":[
        "shop"
    ],
    "wof:name":"Howdy Donuts",
    "wof:placetype":"venue"
},
  "geometry": {"coordinates":[-97.800213,30.274241],"type":"Point"}
}