{
  "type": "Feature",
  "properties": {
    "iso:country":"US",
    "sg:address":"3365 Dixie Dr",
    "sg:city":"Houston",
    "sg:classifiers":[
        {
            "category":"Personal",
            "type":"Services"
        }
    ],
    "sg:phone":"+1 713 747 9192",
    "sg:postcode":"77021",
    "sg:province":"TX",
    "sg:tags":[
        "building",
        "operator",
        "nonresidential"
    ],
    "wof:name":"Dixie Warehouse Conference Cen",
    "wof:placetype":"venue"
},
  "geometry": {"coordinates":[-95.37230099999999,29.70518],"type":"Point"}
}