{
  "type": "Feature",
  "properties": {
    "iso:country":"US",
    "sg:address":"6341 Ashcroft Dr Ste 4A",
    "sg:city":"Houston",
    "sg:classifiers":[
        {
            "category":"Building & Trades",
            "subcategory":"Construction",
            "type":"Services"
        }
    ],
    "sg:phone":"+1 713 981 9054",
    "sg:postcode":"77081",
    "sg:province":"TX",
    "sg:tags":[
        "contractor"
    ],
    "sg:website":"www.kandpconst.com",
    "wof:name":"K & P Construction",
    "wof:placetype":"venue"
},
  "geometry": {"coordinates":[-95.49099699999999,29.712299],"type":"Point"}
}