{
  "type": "Feature",
  "properties": {
    "iso:country":"US",
    "sg:address":"6306 Pineview Rd",
    "sg:city":"Dallas",
    "sg:classifiers":[
        {
            "category":"Wholesale",
            "subcategory":"Chemicals & Plastics",
            "type":"Manufacturing & Wholesale Goods"
        }
    ],
    "sg:phone":"+1 972 701 8943",
    "sg:postcode":"75248",
    "sg:province":"TX",
    "sg:tags":[
        "electronic"
    ],
    "wof:name":"Silicones Unlimited Inc",
    "wof:placetype":"venue"
},
  "geometry": {"coordinates":[-96.795637,32.964391],"type":"Point"}
}