{
  "type": "Feature",
  "properties": {
    "iso:country":"US",
    "sg:address":"3314 S Alameda St",
    "sg:city":"Corpus Christi",
    "sg:classifiers":[
        {
            "category":"Health Services",
            "subcategory":"Health Practitioner",
            "type":"Services"
        }
    ],
    "sg:phone":"+1 361 852 8522",
    "sg:postcode":"78411",
    "sg:province":"TX",
    "sg:tags":[
        "merchandise"
    ],
    "wof:name":"Hear Again Hearing Aids",
    "wof:placetype":"venue"
},
  "geometry": {"coordinates":[-97.38707599999999,27.752644],"type":"Point"}
}