{
  "type": "Feature",
  "properties": {
    "iso:country":"US",
    "sg:address":"6721 Alder Dr",
    "sg:city":"Houston",
    "sg:classifiers":[
        {
            "category":"Retail",
            "subcategory":"Auto Repair",
            "type":"Services"
        }
    ],
    "sg:phone":"+1 713 664 7386",
    "sg:postcode":"77081",
    "sg:province":"TX",
    "sg:tags":[
        "body",
        "shop",
        "automotive"
    ],
    "wof:name":"Expert Auto Detail",
    "wof:placetype":"venue"
},
  "geometry": {"coordinates":[-95.480301,29.7066],"type":"Point"}
}