{
  "type": "Feature",
  "properties": {
    "iso:country":"US",
    "sg:address":"5911 E University Blvd",
    "sg:city":"Dallas",
    "sg:classifiers":[
        {
            "category":"Insurance",
            "subcategory":"Insurance Agent",
            "type":"Services"
        }
    ],
    "sg:phone":"+1 214 696 1039",
    "sg:postcode":"75206",
    "sg:province":"TX",
    "wof:name":"Bakweri Land Claims Commi",
    "wof:placetype":"venue"
},
  "geometry": {"coordinates":[-96.76446900000001,32.846132],"type":"Point"}
}