{
  "type": "Feature",
  "properties": {
    "iso:country":"US",
    "sg:address":"3840 FM 587",
    "sg:city":"De Leon",
    "sg:classifiers":[
        {
            "category":"Farming",
            "subcategory":"Livestock Farm",
            "type":"Manufacturing & Wholesale Goods"
        }
    ],
    "sg:phone":"+1 254 893 6269",
    "sg:postcode":"76444",
    "sg:province":"TX",
    "sg:tags":[
        "beef",
        "feedlot",
        "cattle"
    ],
    "wof:name":"Roger Pounds",
    "wof:placetype":"venue"
},
  "geometry": {"coordinates":[-98.67427499999999,32.104806],"type":"Point"}
}