{
  "type": "Feature",
  "properties": {
    "iso:country":"US",
    "sg:address":"8302 Preston Dr",
    "sg:city":"Pearland",
    "sg:classifiers":[
        {
            "category":"Wholesale",
            "subcategory":"Chemicals & Plastics",
            "type":"Manufacturing & Wholesale Goods"
        }
    ],
    "sg:phone":"+1 281 412 7799",
    "sg:postcode":"77584",
    "sg:province":"TX",
    "wof:name":"Nanette Richard-Jordan",
    "wof:placetype":"venue"
},
  "geometry": {"coordinates":[-95.34836900000001,29.550706],"type":"Point"}
}