{
  "type": "Feature",
  "properties": {
    "iso:country":"US",
    "sg:address":"17101 Vinland Dr",
    "sg:city":"Addison",
    "sg:classifiers":[
        {
            "category":"Travel",
            "subcategory":"Travel Agent",
            "type":"Entertainment"
        }
    ],
    "sg:phone":"+1 972 713 9444",
    "sg:postcode":"75001",
    "sg:province":"TX",
    "sg:tags":[
        "agency",
        "bureau"
    ],
    "wof:name":"In Travel",
    "wof:placetype":"venue"
},
  "geometry": {"coordinates":[-96.83622800000001,32.984615],"type":"Point"}
}