{
  "type": "Feature",
  "properties": {
    "iso:country":"US",
    "sg:address":"5701 Jade Ave",
    "sg:city":"Port Arthur",
    "sg:classifiers":[
        {
            "category":"Farming",
            "subcategory":"Farm",
            "type":"Manufacturing & Wholesale Goods"
        }
    ],
    "sg:phone":"+1 409 736 3150",
    "sg:postcode":"77640",
    "sg:province":"TX",
    "sg:tags":[
        "crop",
        "general"
    ],
    "wof:name":"Jack W Hemmenway",
    "wof:placetype":"venue"
},
  "geometry": {"coordinates":[-94.03164599999999,29.886269],"type":"Point"}
}