{
  "type": "Feature",
  "properties": {
    "iso:country":"US",
    "sg:address":"6073 Broadway St",
    "sg:city":"Pearland",
    "sg:classifiers":[
        {
            "category":"Retail",
            "subcategory":"Auto Repair",
            "type":"Services"
        }
    ],
    "sg:phone":"+1 281 997 8200",
    "sg:postcode":"77581",
    "sg:province":"TX",
    "sg:tags":[
        "transmission",
        "general"
    ],
    "wof:name":"Morrow's Transmissions",
    "wof:placetype":"venue"
},
  "geometry": {"coordinates":[-95.310732,29.559577],"type":"Point"}
}