{
  "type": "Feature",
  "properties": {
    "iso:country":"US",
    "sg:address":"9235 Westheimer Rd",
    "sg:city":"Houston",
    "sg:classifiers":[
        {
            "category":"Real Estate",
            "subcategory":"Real Estate Operator",
            "type":"Services"
        }
    ],
    "sg:phone":"+1 713 783 7990",
    "sg:postcode":"77063",
    "sg:province":"TX",
    "sg:tags":[
        "building",
        "apartment"
    ],
    "wof:name":"Westheimer Park Apartments",
    "wof:placetype":"venue"
},
  "geometry": {"coordinates":[-95.527038,29.737177],"type":"Point"}
}