{
  "type": "Feature",
  "properties": {
    "iso:country":"US",
    "sg:address":"1725 Altacrest Dr",
    "sg:city":"Grapevine",
    "sg:classifiers":[
        {
            "category":"Professional",
            "type":"Services"
        }
    ],
    "sg:phone":"+1 817 421 9885",
    "sg:postcode":"76051",
    "sg:province":"TX",
    "sg:tags":[
        "establishment"
    ],
    "wof:name":"AFP Technologies",
    "wof:placetype":"venue"
},
  "geometry": {"coordinates":[-97.090397,32.883081],"type":"Point"}
}