{
  "type": "Feature",
  "properties": {
    "iso:country":"US",
    "sg:address":"923 E Fm 455",
    "sg:city":"Anna",
    "sg:classifiers":[
        {
            "category":"Manufacturing",
            "subcategory":"Toys & Sporting Goods",
            "type":"Manufacturing & Wholesale Goods"
        },
        {
            "category":"Utilities",
            "subcategory":"Natural Gas",
            "type":"Services"
        }
    ],
    "sg:phone":"+1 972 924 3724",
    "sg:postcode":"75409",
    "sg:province":"TX",
    "sg:tags":[
        "fireworks-wholesale",
        "firework",
        "manufacturer"
    ],
    "wof:name":"Adams Fireworks",
    "wof:placetype":"venue"
},
  "geometry": {"coordinates":[-96.570712,33.34485],"type":"Point"}
}