{
  "type": "Feature",
  "properties": {
    "iso:country":"US",
    "sg:address":"10801 Truman St",
    "sg:city":"Amarillo",
    "sg:classifiers":[
        {
            "category":"Shopping",
            "subcategory":"Hobbies, Toys, & Games",
            "type":"Retail Goods"
        }
    ],
    "sg:phone":"+1 806 622 0737",
    "sg:postcode":"79118",
    "sg:province":"TX",
    "sg:tags":[
        "craft"
    ],
    "wof:name":"Kathy's Kountry Krafts",
    "wof:placetype":"venue"
},
  "geometry": {"coordinates":[-101.808274,35.100469],"type":"Point"}
}