{
  "type": "Feature",
  "properties": {
    "iso:country":"US",
    "sg:address":"127 Furr Dr",
    "sg:city":"San Antonio",
    "sg:classifiers":[
        {
            "category":"Building & Trades",
            "subcategory":"Construction",
            "type":"Services"
        }
    ],
    "sg:phone":"+1 210 669 2002",
    "sg:postcode":"78201",
    "sg:province":"TX",
    "sg:tags":[
        "demolition",
        "contractor"
    ],
    "wof:name":"Hansco",
    "wof:placetype":"venue"
},
  "geometry": {"coordinates":[-98.526618,29.463796],"type":"Point"}
}