{
  "type": "Feature",
  "properties": {
    "iso:country":"US",
    "sg:address":"809 Lamar St",
    "sg:city":"San Antonio",
    "sg:classifiers":[
        {
            "category":"Food & Beverages",
            "subcategory":"Meat & Fish",
            "type":"Retail Goods"
        }
    ],
    "sg:phone":"+1 210 222 9158",
    "sg:postcode":"78202",
    "sg:province":"TX",
    "wof:name":"Lackeys Retail Fish",
    "wof:placetype":"venue"
},
  "geometry": {"coordinates":[-98.467344,29.431516],"type":"Point"}
}