{
  "type": "Feature",
  "properties": {
    "iso:country":"US",
    "sg:address":"5914 Carver Ave",
    "sg:city":"Texas City",
    "sg:classifiers":[
        {
            "category":"Social Services",
            "subcategory":"Child Care",
            "type":"Services"
        }
    ],
    "sg:phone":"+1 409 938 4747",
    "sg:postcode":"77591",
    "sg:province":"TX",
    "wof:name":"Mainland Headstart",
    "wof:placetype":"venue"
},
  "geometry": {"coordinates":[-94.980744,29.383495],"type":"Point"}
}