{
  "type": "Feature",
  "properties": {
    "iso:country":"US",
    "sg:address":"9639 Hillcroft St",
    "sg:city":"Houston",
    "sg:classifiers":[
        {
            "category":"Professional",
            "subcategory":"Business Services",
            "type":"Services"
        }
    ],
    "sg:phone":"+1 713 726 1026",
    "sg:postcode":"77096",
    "sg:province":"TX",
    "wof:name":"Mailabox",
    "wof:placetype":"venue"
},
  "geometry": {"coordinates":[-95.49360799999999,29.676199],"type":"Point"}
}