{
  "type": "Feature",
  "properties": {
    "iso:country":"US",
    "sg:address":"130 Marina Dr",
    "sg:city":"Bullard",
    "sg:classifiers":[
        {
            "category":"Health Services",
            "subcategory":"Clinic",
            "type":"Services"
        }
    ],
    "sg:phone":"+1 903 825 2631",
    "sg:postcode":"75757",
    "sg:province":"TX",
    "wof:name":"Intl Health Care Technolo",
    "wof:placetype":"venue"
},
  "geometry": {"coordinates":[-95.441047,32.15376],"type":"Point"}
}