{
  "type": "Feature",
  "properties": {
    "iso:country":"US",
    "sg:address":"5228 89th St",
    "sg:city":"Lubbock",
    "sg:classifiers":[
        {
            "category":"Wholesale",
            "subcategory":"Chemicals & Plastics",
            "type":"Manufacturing & Wholesale Goods"
        }
    ],
    "sg:phone":"+1 806 798 7668",
    "sg:postcode":"79424",
    "sg:province":"TX",
    "wof:name":"Rebbco Chemicals",
    "wof:placetype":"venue"
},
  "geometry": {"coordinates":[-101.92486100000001,33.512789],"type":"Point"}
}