{
  "type": "Feature",
  "properties": {
    "iso:country":"US",
    "sg:address":"313 Main St",
    "sg:city":"Mc Kinney",
    "sg:classifiers":[
        {
            "category":"Wholesale",
            "subcategory":"Farm Supplies",
            "type":"Manufacturing & Wholesale Goods"
        }
    ],
    "sg:phone":"+1 972 542 9851",
    "sg:postcode":"75069",
    "sg:province":"TX",
    "sg:tags":[
        "fertilizer"
    ],
    "wof:name":"BBB Fertilizer Co",
    "wof:placetype":"venue"
},
  "geometry": {"coordinates":[-96.609548,33.199095],"type":"Point"}
}