{
  "type": "Feature",
  "properties": {
    "iso:country":"US",
    "sg:address":"4009 Banister Ln",
    "sg:city":"Austin",
    "sg:classifiers":[
        {
            "category":"Professional",
            "subcategory":"Research",
            "type":"Services"
        },
        {
            "category":"Shopping",
            "subcategory":"Pharmacy",
            "type":"Retail Goods"
        }
    ],
    "sg:phone":"+1 512 440 2973",
    "sg:postcode":"78704",
    "sg:province":"TX",
    "sg:tags":[
        "information",
        "medical",
        "drugstore"
    ],
    "wof:name":"Pharmaco",
    "wof:placetype":"venue"
},
  "geometry": {"coordinates":[-97.777939,30.229691],"type":"Point"}
}