{
  "type": "Feature",
  "properties": {
    "iso:country":"US",
    "sg:address":"30 Aldridge Ave",
    "sg:city":"Brownsville",
    "sg:classifiers":[
        {
            "category":"Restaurant",
            "type":"Food & Drink"
        }
    ],
    "sg:phone":"+1 956 504 1623",
    "sg:postcode":"78520",
    "sg:province":"TX",
    "sg:tags":[
        "eating"
    ],
    "wof:name":"Bettys Tortas Y Elotes",
    "wof:placetype":"venue"
},
  "geometry": {"coordinates":[-97.491919,25.922992],"type":"Point"}
}