{
  "type": "Feature",
  "properties": {
    "iso:country":"US",
    "sg:address":"7102 Stella St",
    "sg:city":"Murchison",
    "sg:classifiers":[
        {
            "category":"Farming",
            "subcategory":"Livestock Farm",
            "type":"Manufacturing & Wholesale Goods"
        }
    ],
    "sg:phone":"+1 903 469 3077",
    "sg:postcode":"75778",
    "sg:province":"TX",
    "sg:tags":[
        "beef",
        "feedlot",
        "cattle"
    ],
    "wof:name":"Praytor Farms Ltd",
    "wof:placetype":"venue"
},
  "geometry": {"coordinates":[-95.735688,32.280244],"type":"Point"}
}