{
  "type": "Feature",
  "properties": {
    "iso:country":"US",
    "sg:address":"730 Lipscomb Ave",
    "sg:city":"Dallas",
    "sg:classifiers":[
        {
            "category":"Professional",
            "subcategory":"Management & Consulting",
            "type":"Services"
        }
    ],
    "sg:phone":"+1 214 821 7962",
    "sg:postcode":"75214",
    "sg:province":"TX",
    "sg:tags":[
        "consultant",
        "business"
    ],
    "wof:name":"BC Group Intl",
    "wof:placetype":"venue"
},
  "geometry": {"coordinates":[-96.75603,32.810819],"type":"Point"}
}