{
  "type": "Feature",
  "properties": {
    "iso:country":"US",
    "sg:address":"20884 FM 2268",
    "sg:city":"Holland",
    "sg:classifiers":[
        {
            "category":"Shopping",
            "subcategory":"Hobbies, Toys, & Games",
            "type":"Retail Goods"
        }
    ],
    "sg:phone":"+1 254 657 2834",
    "sg:postcode":"76534",
    "sg:province":"TX",
    "wof:name":"Jennies Handmade Crafts",
    "wof:placetype":"venue"
},
  "geometry": {"coordinates":[-97.30192700000001,30.839606],"type":"Point"}
}