{
  "type": "Feature",
  "properties": {
    "iso:country":"US",
    "sg:address":"2335 Post Oak Blvd",
    "sg:city":"Houston",
    "sg:classifiers":[
        {
            "category":"Home & Garden",
            "subcategory":"Furniture",
            "type":"Retail Goods"
        }
    ],
    "sg:phone":"+1 713 439 0978",
    "sg:postcode":"77056",
    "sg:province":"TX",
    "wof:name":"Bombay Co",
    "wof:placetype":"venue"
},
  "geometry": {"coordinates":[-95.461152,29.743355],"type":"Point"}
}