{
  "type": "Feature",
  "properties": {
    "iso:country":"US",
    "sg:address":"1106 W Dittmar Road",
    "sg:city":"Austin",
    "sg:classifiers":[
        {
            "category":"Health Services",
            "subcategory":"Hospital",
            "type":"Services"
        }
    ],
    "sg:phone":"+1 512 444 4835",
    "sg:postcode":"78745",
    "sg:province":"TX",
    "wof:name":"Texas Neurorehab Center",
    "wof:placetype":"venue"
},
  "geometry": {"coordinates":[-97.80359900000001,30.185857],"type":"Point"}
}