{
  "type": "Feature",
  "properties": {
    "iso:country":"US",
    "sg:address":"501 W Main St",
    "sg:city":"Grand Prairie",
    "sg:classifiers":[
        {
            "category":"Restaurant",
            "type":"Food & Drink"
        }
    ],
    "sg:phone":"+1 972 264 4929",
    "sg:postcode":"75050",
    "sg:province":"TX",
    "sg:tags":[
        "eating"
    ],
    "wof:name":"Nina's Cafe",
    "wof:placetype":"venue"
},
  "geometry": {"coordinates":[-97.010429,32.744515],"type":"Point"}
}