{
  "type": "Feature",
  "properties": {
    "iso:country":"US",
    "sg:address":"1802 Balboa Dr",
    "sg:city":"Dallas",
    "sg:classifiers":[
        {
            "category":"Insurance",
            "subcategory":"Insurance Agent",
            "type":"Services"
        }
    ],
    "sg:phone":"+1 214 941 2886",
    "sg:postcode":"75224",
    "sg:province":"TX",
    "wof:name":"Oak Cliff Insurance",
    "wof:placetype":"venue"
},
  "geometry": {"coordinates":[-96.844055,32.727685],"type":"Point"}
}