{
  "type": "Feature",
  "properties": {
    "iso:country":"US",
    "sg:address":"1503 E 2nd St",
    "sg:city":"Odessa",
    "sg:classifiers":[
        {
            "category":"Bars & Pubs",
            "type":"Food & Drink"
        }
    ],
    "sg:phone":"+1 432 335 8420",
    "sg:postcode":"79761",
    "sg:province":"TX",
    "wof:name":"Yellow Rose",
    "wof:placetype":"venue"
},
  "geometry": {"coordinates":[-102.34887000000001,31.854776],"type":"Point"}
}