{
  "type": "Feature",
  "properties": {
    "iso:country":"US",
    "sg:address":"12400 W Highway 71",
    "sg:city":"Austin",
    "sg:classifiers":[
        {
            "category":"Shopping",
            "subcategory":"Beauty & Cosmetics",
            "type":"Retail Goods"
        }
    ],
    "sg:phone":"+1 512 263 0066",
    "sg:postcode":"78738",
    "sg:province":"TX",
    "sg:tags":[
        "supply"
    ],
    "sg:website":"www.beautyemporiumandsalon.com",
    "wof:name":"Beauty Emporium & Salon",
    "wof:placetype":"venue"
},
  "geometry": {"coordinates":[-97.934506,30.304107],"type":"Point"}
}