{
  "type": "Feature",
  "properties": {
    "iso:country":"US",
    "sg:address":"6604 Pheasant Run Rd",
    "sg:city":"Plano",
    "sg:classifiers":[
        {
            "category":"Professional",
            "type":"Services"
        }
    ],
    "sg:phone":"+1 972 618 2005",
    "sg:postcode":"75023",
    "sg:province":"TX",
    "wof:name":"ME & B Esigns",
    "wof:placetype":"venue"
},
  "geometry": {"coordinates":[-96.73904400000001,33.0648],"type":"Point"}
}