{
  "type": "Feature",
  "properties": {
    "iso:country":"US",
    "sg:address":"208 Summit Dr",
    "sg:city":"Kyle",
    "sg:classifiers":[
        {
            "category":"Building & Trades",
            "subcategory":"Construction",
            "type":"Services"
        }
    ],
    "sg:phone":"+1 512 295 4838",
    "sg:postcode":"78640",
    "sg:province":"TX",
    "sg:tags":[
        "concrete",
        "contractor"
    ],
    "wof:name":"Interiors Concrete Inc",
    "wof:placetype":"venue"
},
  "geometry": {"coordinates":[-97.809989,29.997557],"type":"Point"}
}