{
  "type": "Feature",
  "properties": {
    "iso:country":"US",
    "sg:address":"16214 Charolais Dr",
    "sg:city":"Cypress",
    "sg:classifiers":[
        {
            "category":"Building & Trades",
            "subcategory":"Plumbing",
            "type":"Services"
        }
    ],
    "sg:phone":"+1 281 373 1624",
    "sg:postcode":"77429",
    "sg:province":"TX",
    "sg:tags":[
        "contractor"
    ],
    "wof:name":"High Tech Htg & A Condition",
    "wof:placetype":"venue"
},
  "geometry": {"coordinates":[-95.67459599999999,29.989719],"type":"Point"}
}