{
  "type": "Feature",
  "properties": {
    "iso:country":"US",
    "sg:address":"5845 Jamar Rd",
    "sg:city":"Paris",
    "sg:classifiers":[
        {
            "category":"Building & Trades",
            "subcategory":"Plumbing",
            "type":"Services"
        }
    ],
    "sg:phone":"+1 903 785 5683",
    "sg:postcode":"75462",
    "sg:province":"TX",
    "sg:tags":[
        "plumbing",
        "contractor"
    ],
    "wof:name":"Alton Hess Plumbing",
    "wof:placetype":"venue"
},
  "geometry": {"coordinates":[-95.47384,33.665608],"type":"Point"}
}