{
  "type": "Feature",
  "properties": {
    "iso:country":"US",
    "sg:address":"178 E Mill St",
    "sg:city":"New Braunfels",
    "sg:classifiers":[
        {
            "category":"Government",
            "subcategory":"Office",
            "type":"Public Place"
        }
    ],
    "sg:phone":"+1 830 885 4975",
    "sg:postcode":"78130",
    "sg:province":"TX",
    "wof:name":"Comal County Appraisal Dist",
    "wof:placetype":"venue"
},
  "geometry": {"coordinates":[-98.124742,29.704678],"type":"Point"}
}