{
  "type": "Feature",
  "properties": {
    "iso:country":"US",
    "sg:address":"10907 Co Rd 160",
    "sg:city":"Boling",
    "sg:classifiers":[
        {
            "category":"Professional",
            "subcategory":"Business Services",
            "type":"Services"
        }
    ],
    "sg:phone":"+1 979 657 3526",
    "sg:postcode":"77420",
    "sg:province":"TX",
    "wof:name":"Marion Edwards Hodges",
    "wof:placetype":"venue"
},
  "geometry": {"coordinates":[-95.943043,29.315844],"type":"Point"}
}