{
  "type": "Feature",
  "properties": {
    "iso:country":"US",
    "sg:address":"1602 Oakbury Dr",
    "sg:city":"Missouri City",
    "sg:classifiers":[
        {
            "category":"Restaurant",
            "type":"Food & Drink"
        }
    ],
    "sg:phone":"+1 281 437 7455",
    "sg:postcode":"77489",
    "sg:province":"TX",
    "sg:tags":[
        "eating"
    ],
    "wof:name":"Jays Custom Catering",
    "wof:placetype":"venue"
},
  "geometry": {"coordinates":[-95.519497,29.605399],"type":"Point"}
}