{
  "type": "Feature",
  "properties": {
    "iso:country":"US",
    "sg:address":"16131 Champion Forest Dr",
    "sg:city":"Spring",
    "sg:classifiers":[
        {
            "category":"Retail",
            "subcategory":"Funeral Services",
            "type":"Services"
        }
    ],
    "sg:phone":"+1 281 320 2674",
    "sg:postcode":"77379",
    "sg:province":"TX",
    "wof:name":"Klein Fnrl Homes & Mem Parks",
    "wof:placetype":"venue"
},
  "geometry": {"coordinates":[-95.53355999999999,30.003918],"type":"Point"}
}