{
  "type": "Feature",
  "properties": {
    "iso:country":"US",
    "sg:address":"6501 Dalrock Rd",
    "sg:city":"Rowlett",
    "sg:classifiers":[
        {
            "category":"Food & Beverages",
            "subcategory":"Specialty",
            "type":"Retail Goods"
        }
    ],
    "sg:phone":"+1 972 412 5088",
    "sg:postcode":"75089",
    "sg:province":"TX",
    "wof:name":"GNC",
    "wof:placetype":"venue"
},
  "geometry": {"coordinates":[-96.51785,32.916041],"type":"Point"}
}