{
  "type": "Feature",
  "properties": {
    "iso:country":"US",
    "sg:address":"6404 Euston Dr",
    "sg:city":"Amarillo",
    "sg:classifiers":[
        {
            "category":"Shopping",
            "subcategory":"Computers & Home Electronics",
            "type":"Retail Goods"
        }
    ],
    "sg:phone":"+1 806 353 1280",
    "sg:postcode":"79109",
    "sg:province":"TX",
    "sg:tags":[
        "equipment",
        "electronic",
        "supply"
    ],
    "wof:name":"Husky International Elecs Inc",
    "wof:placetype":"venue"
},
  "geometry": {"coordinates":[-101.909734,35.141825],"type":"Point"}
}