{
  "type": "Feature",
  "properties": {
    "iso:country":"US",
    "sg:address":"929 N Padre Island Dr",
    "sg:city":"Corpus Christi",
    "sg:classifiers":[
        {
            "category":"Organizations",
            "subcategory":"Religious Organization",
            "type":"Services"
        }
    ],
    "sg:phone":"+1 361 299 1992",
    "sg:postcode":"78406",
    "sg:province":"TX",
    "sg:tags":[
        "church"
    ],
    "wof:name":"Worship Center-Corpus Christi",
    "wof:placetype":"venue"
},
  "geometry": {"coordinates":[-97.46971000000001,27.779071],"type":"Point"}
}