{
  "type": "Feature",
  "properties": {
    "iso:country":"US",
    "sg:address":"1212 E Arapaho Rd",
    "sg:city":"Richardson",
    "sg:classifiers":[
        {
            "category":"Professional",
            "subcategory":"Business Services",
            "type":"Services"
        }
    ],
    "sg:phone":"+1 972 664 0620",
    "sg:postcode":"75081",
    "sg:province":"TX",
    "sg:tags":[
        "holding"
    ],
    "sg:website":"http://www.stonecapital.com",
    "wof:name":"Stone Holdings",
    "wof:placetype":"venue"
},
  "geometry": {"coordinates":[-96.70511399999999,32.96059],"type":"Point"}
}