{
  "type": "Feature",
  "properties": {
    "iso:country":"US",
    "sg:address":"6649 Wickliff Trl",
    "sg:city":"Plano",
    "sg:classifiers":[
        {
            "category":"Manufacturing",
            "subcategory":"Retail Goods",
            "type":"Manufacturing & Wholesale Goods"
        },
        {
            "category":"Manufacturing",
            "subcategory":"Chemicals & Compounds",
            "type":"Manufacturing & Wholesale Goods"
        }
    ],
    "sg:phone":"+1 972 517 8259",
    "sg:postcode":"75023",
    "sg:province":"TX",
    "sg:tags":[
        "development",
        "product",
        "mfg",
        "design",
        "care",
        "manufacturer"
    ],
    "sg:website":"www.beautyhealthworks.com",
    "wof:name":"Beauty & Health Works Company",
    "wof:placetype":"venue"
},
  "geometry": {"coordinates":[-96.731742,33.065922],"type":"Point"}
}