{
  "type": "Feature",
  "properties": {
    "iso:country":"US",
    "sg:address":"1422 Taft Dr",
    "sg:city":"Deer Park",
    "sg:classifiers":[
        {
            "category":"Professional",
            "subcategory":"Business Services",
            "type":"Services"
        }
    ],
    "sg:phone":"+1 281 884 0400",
    "sg:postcode":"77536",
    "sg:province":"TX",
    "wof:name":"Affordable Answering Svc",
    "wof:placetype":"venue"
},
  "geometry": {"coordinates":[-95.108487,29.685932],"type":"Point"}
}