{
  "type": "Feature",
  "properties": {
    "iso:country":"US",
    "sg:address":"1101 State Hwy 114",
    "sg:city":"Southlake",
    "sg:classifiers":[
        {
            "category":"Retail",
            "subcategory":"Auto Rental",
            "type":"Services"
        }
    ],
    "sg:phone":"+1 817 421 0055",
    "sg:postcode":"76092",
    "sg:province":"TX",
    "sg:tags":[
        "passenger",
        "car"
    ],
    "wof:name":"Enterprise Leasing Company Dfw",
    "wof:placetype":"venue"
},
  "geometry": {"coordinates":[-97.134079,32.951051],"type":"Point"}
}