{
  "type": "Feature",
  "properties": {
    "iso:country":"US",
    "sg:address":"304 Bain Ct",
    "sg:city":"El Paso",
    "sg:classifiers":[
        {
            "category":"Manufacturing",
            "subcategory":"Apparel",
            "type":"Manufacturing & Wholesale Goods"
        }
    ],
    "sg:phone":"+1 915 852 2393",
    "sg:postcode":"79928",
    "sg:province":"TX",
    "sg:tags":[
        "clothing",
        "mfg"
    ],
    "wof:name":"24 7 Sewing Contractors",
    "wof:placetype":"venue"
},
  "geometry": {"coordinates":[-106.205393,31.691085],"type":"Point"}
}