{
  "type": "Feature",
  "properties": {
    "iso:country":"US",
    "sg:address":"110 E Main St",
    "sg:city":"Llano",
    "sg:classifiers":[
        {
            "category":"Shopping",
            "type":"Retail Goods"
        }
    ],
    "sg:phone":"+1 325 247 1903",
    "sg:postcode":"78643",
    "sg:province":"TX",
    "sg:tags":[
        "art",
        "gallery",
        "dealer"
    ],
    "wof:name":"Art On Main",
    "wof:placetype":"venue"
},
  "geometry": {"coordinates":[-98.67581199999999,30.75024],"type":"Point"}
}