{
  "type": "Feature",
  "properties": {
    "iso:country":"US",
    "sg:address":"5627 Aldine Bender Rd",
    "sg:city":"Houston",
    "sg:classifiers":[
        {
            "category":"Shopping",
            "subcategory":"Pharmacy",
            "type":"Retail Goods"
        }
    ],
    "sg:phone":"+1 281 227 1010",
    "sg:postcode":"77032",
    "sg:province":"TX",
    "sg:tags":[
        "drugstore"
    ],
    "wof:name":"Platinum Rx North Pharmacy",
    "wof:placetype":"venue"
},
  "geometry": {"coordinates":[-95.306089,29.930715],"type":"Point"}
}