{
  "type": "Feature",
  "properties": {
    "iso:country":"US",
    "sg:address":"166 Queenscliff Ct",
    "sg:city":"The Woodlands",
    "sg:classifiers":[
        {
            "category":"Building & Trades",
            "subcategory":"Construction",
            "type":"Services"
        }
    ],
    "sg:phone":"+1 281 356 1658",
    "sg:postcode":"77382",
    "sg:province":"TX",
    "sg:tags":[
        "home",
        "builder"
    ],
    "wof:name":"Emerald Homes",
    "wof:placetype":"venue"
},
  "geometry": {"coordinates":[-95.573081,30.184593],"type":"Point"}
}