{
  "type": "Feature",
  "properties": {
    "iso:country":"US",
    "sg:address":"16034 Rustic Sands Dr",
    "sg:city":"Houston",
    "sg:classifiers":[
        {
            "category":"Professional",
            "subcategory":"Management & Consulting",
            "type":"Services"
        }
    ],
    "sg:phone":"+1 281 855 0399",
    "sg:postcode":"77084",
    "sg:province":"TX",
    "wof:name":"Business News Today LLC",
    "wof:placetype":"venue"
},
  "geometry": {"coordinates":[-95.64283500000001,29.844062],"type":"Point"}
}