{
  "type": "Feature",
  "properties": {
    "iso:country":"US",
    "sg:address":"7505 Main St",
    "sg:city":"Houston",
    "sg:classifiers":[
        {
            "category":"Health Services",
            "subcategory":"Doctor",
            "type":"Services"
        }
    ],
    "sg:phone":"+1 713 790 1500",
    "sg:postcode":"77030",
    "sg:province":"TX",
    "sg:tags":[
        "medical",
        "center"
    ],
    "wof:name":"Texas Pain Consultants LLP",
    "wof:placetype":"venue"
},
  "geometry": {"coordinates":[-95.41114399999999,29.698466],"type":"Point"}
}