{
  "type": "Feature",
  "properties": {
    "iso:country":"US",
    "sg:address":"5646 Wood Climb St",
    "sg:city":"San Antonio",
    "sg:classifiers":[
        {
            "category":"Shopping",
            "type":"Retail Goods"
        }
    ],
    "sg:phone":"+1 210 654 7234",
    "sg:postcode":"78233",
    "sg:province":"TX",
    "sg:tags":[
        "merchandise"
    ],
    "wof:name":"William R Husser",
    "wof:placetype":"venue"
},
  "geometry": {"coordinates":[-98.37504199999999,29.566002],"type":"Point"}
}