{
  "type": "Feature",
  "properties": {
    "iso:country":"US",
    "sg:address":"10480 Montanio Dr",
    "sg:city":"New Braunfels",
    "sg:classifiers":[
        {
            "category":"Home & Garden",
            "subcategory":"Hardware",
            "type":"Retail Goods"
        }
    ],
    "sg:phone":"+1 830 606 2226",
    "sg:postcode":"78132",
    "sg:province":"TX",
    "wof:name":"Roberts Tool Co Inc",
    "wof:placetype":"venue"
},
  "geometry": {"coordinates":[-98.277378,29.676055],"type":"Point"}
}