{
  "type": "Feature",
  "properties": {
    "iso:country":"US",
    "sg:address":"257 Pasadena Town Sq Mll",
    "sg:city":"Pasadena",
    "sg:classifiers":[
        {
            "category":"Shopping",
            "subcategory":"Department Store",
            "type":"Retail Goods"
        }
    ],
    "sg:phone":"+1 713 472 2332",
    "sg:postcode":"77506",
    "sg:province":"TX",
    "sg:website":"www.pasadenatownsquare.com",
    "wof:name":"Pasadena Town Square",
    "wof:placetype":"venue"
},
  "geometry": {"coordinates":[-95.196404,29.6966],"type":"Point"}
}