{
  "type": "Feature",
  "properties": {
    "iso:country":"US",
    "sg:address":"5005 Commercial Park Dr",
    "sg:city":"Austin",
    "sg:classifiers":[
        {
            "category":"Food & Beverages",
            "subcategory":"Liquor & Beverages",
            "type":"Retail Goods"
        },
        {
            "category":"Ice Cream",
            "type":"Food & Drink"
        }
    ],
    "sg:phone":"+1 512 928 0080",
    "sg:postcode":"78724",
    "sg:province":"TX",
    "sg:tags":[
        "dry"
    ],
    "wof:name":"Flash Cubes Ice Service",
    "wof:placetype":"venue"
},
  "geometry": {"coordinates":[-97.654084,30.323136],"type":"Point"}
}