{
  "type": "Feature",
  "properties": {
    "iso:country":"US",
    "sg:address":"911 Talbot Ave",
    "sg:city":"Canutillo",
    "sg:classifiers":[
        {
            "category":"Restaurant",
            "type":"Food & Drink"
        }
    ],
    "sg:menulink":"http://www.allmenus.com/tx/el-paso-northwest/131008-subway/menu/",
    "sg:phone":"+1 915 877 3480",
    "sg:postcode":"79835",
    "sg:province":"TX",
    "sg:tags":[
        "american",
        "sandwich"
    ],
    "wof:name":"Subway",
    "wof:placetype":"venue"
},
  "geometry": {"coordinates":[-106.590141,31.908688],"type":"Point"}
}