{
  "type": "Feature",
  "properties": {
    "iso:country":"US",
    "sg:address":"5870 Westheimer Rd",
    "sg:city":"Houston",
    "sg:classifiers":[
        {
            "category":"Shopping",
            "subcategory":"Jewelry",
            "type":"Retail Goods"
        }
    ],
    "sg:phone":"+1 713 785 1595",
    "sg:postcode":"77057",
    "sg:province":"TX",
    "wof:name":"Argenta 001",
    "wof:placetype":"venue"
},
  "geometry": {"coordinates":[-95.48339799999999,29.738001],"type":"Point"}
}