{
  "type": "Feature",
  "properties": {
    "iso:country":"US",
    "sg:address":"210 Dogwood Trl",
    "sg:city":"Magnolia",
    "sg:classifiers":[
        {
            "category":"Building & Trades",
            "subcategory":"Electrical",
            "type":"Services"
        }
    ],
    "sg:phone":"+1 281 252 0711",
    "sg:postcode":"77354",
    "sg:province":"TX",
    "sg:tags":[
        "electrical"
    ],
    "wof:name":"Patriot Electrical Services",
    "wof:placetype":"venue"
},
  "geometry": {"coordinates":[-95.74334399999999,30.220083],"type":"Point"}
}