{
  "type": "Feature",
  "properties": {
    "iso:country":"US",
    "sg:address":"5902 Irvington Blvd",
    "sg:city":"Houston",
    "sg:classifiers":[
        {
            "category":"Personal",
            "subcategory":"Beauty Salon",
            "type":"Services"
        }
    ],
    "sg:phone":"+1 713 694 1772",
    "sg:postcode":"77009",
    "sg:province":"TX",
    "sg:tags":[
        "spa",
        "day"
    ],
    "wof:name":"Cynthelese Therapeutic Bdywrks",
    "wof:placetype":"venue"
},
  "geometry": {"coordinates":[-95.361166,29.813143],"type":"Point"}
}