{
  "type": "Feature",
  "properties": {
    "iso:country":"US",
    "sg:address":"107 Timber Ln",
    "sg:city":"Livingston",
    "sg:classifiers":[
        {
            "category":"Building & Trades",
            "subcategory":"Construction",
            "type":"Services"
        }
    ],
    "sg:phone":"+1 281 660 0441",
    "sg:postcode":"77331",
    "sg:province":"TX",
    "sg:tags":[
        "house"
    ],
    "wof:name":"R L Trucking & Const",
    "wof:placetype":"venue"
},
  "geometry": {"coordinates":[-95.11645300000001,30.632292],"type":"Point"}
}