{
  "type": "Feature",
  "properties": {
    "iso:country":"US",
    "sg:address":"11720 W Airport Blvd",
    "sg:city":"Stafford",
    "sg:classifiers":[
        {
            "category":"Professional",
            "subcategory":"Lawyer & Legal Services",
            "type":"Services"
        }
    ],
    "sg:phone":"+1 281 564 7900",
    "sg:postcode":"77477",
    "sg:province":"TX",
    "sg:tags":[
        "attorney",
        "plan"
    ],
    "wof:name":"Christopher Pham Law Group",
    "wof:placetype":"venue"
},
  "geometry": {"coordinates":[-95.581148,29.64762],"type":"Point"}
}