{
  "type": "Feature",
  "properties": {
    "iso:country":"US",
    "sg:address":"16206 Elm Dr",
    "sg:city":"Austin",
    "sg:classifiers":[
        {
            "category":"Building & Trades",
            "subcategory":"Construction",
            "type":"Services"
        }
    ],
    "sg:phone":"+1 512 266 3589",
    "sg:postcode":"78734",
    "sg:province":"TX",
    "sg:tags":[
        "plastering",
        "contractor"
    ],
    "wof:name":"Hunt Td Plastering",
    "wof:placetype":"venue"
},
  "geometry": {"coordinates":[-97.924347,30.427475],"type":"Point"}
}