{
  "type": "Feature",
  "properties": {
    "iso:country":"US",
    "sg:address":"1700 Country Club Dr",
    "sg:city":"Mansfield",
    "sg:classifiers":[
        {
            "category":"Health Services",
            "subcategory":"Doctor",
            "type":"Services"
        }
    ],
    "sg:phone":"+1 817 473 6227",
    "sg:postcode":"76063",
    "sg:province":"TX",
    "sg:tags":[
        "dentist"
    ],
    "wof:name":"Mansfield Dental Associates",
    "wof:placetype":"venue"
},
  "geometry": {"coordinates":[-97.10908999999999,32.593538],"type":"Point"}
}