{
  "type": "Feature",
  "properties": {
    "iso:country":"US",
    "sg:address":"1537 E Paisano Dr",
    "sg:city":"El Paso",
    "sg:classifiers":[
        {
            "category":"Personal",
            "subcategory":"Shoe Repair & Shine",
            "type":"Services"
        },
        {
            "category":"Wholesale",
            "subcategory":"Non-durable Goods",
            "type":"Manufacturing & Wholesale Goods"
        }
    ],
    "sg:phone":"+1 915 545 2667",
    "sg:postcode":"79901",
    "sg:province":"TX",
    "sg:tags":[
        "leather",
        "parlor"
    ],
    "wof:name":"Paisano Leather Co",
    "wof:placetype":"venue"
},
  "geometry": {"coordinates":[-106.473218,31.759812],"type":"Point"}
}