{
  "type": "Feature",
  "properties": {
    "iso:country":"US",
    "sg:address":"13015 Careywood Dr",
    "sg:city":"Sugar Land",
    "sg:classifiers":[
        {
            "category":"Wholesale",
            "subcategory":"Apparel",
            "type":"Manufacturing & Wholesale Goods"
        }
    ],
    "sg:phone":"+1 281 240 7732",
    "sg:postcode":"77478",
    "sg:province":"TX",
    "sg:tags":[
        "infant",
        "wear"
    ],
    "wof:name":"Brilliant Inc",
    "wof:placetype":"venue"
},
  "geometry": {"coordinates":[-95.61259200000001,29.648836],"type":"Point"}
}