{
  "type": "Feature",
  "properties": {
    "iso:country":"US",
    "sg:address":"750 Almeda-Genoa Rd",
    "sg:city":"Houston",
    "sg:classifiers":[
        {
            "category":"Manufacturing",
            "subcategory":"Furniture",
            "type":"Manufacturing & Wholesale Goods"
        }
    ],
    "sg:phone":"+1 713 688 0151",
    "sg:postcode":"77047",
    "sg:province":"TX",
    "sg:tags":[
        "metal",
        "industrial",
        "shelving",
        "mfg"
    ],
    "wof:name":"Dixie Shelving Company",
    "wof:placetype":"venue"
},
  "geometry": {"coordinates":[-95.41219700000001,29.613644],"type":"Point"}
}