{
  "type": "Feature",
  "properties": {
    "iso:country":"US",
    "sg:address":"3232 Halifax St",
    "sg:city":"Dallas",
    "sg:classifiers":[
        {
            "category":"Autos & Motor Vehicles",
            "subcategory":"Recreational Vehicle Sales",
            "type":"Retail Goods"
        },
        {
            "category":"Wholesale",
            "subcategory":"Auto Parts",
            "type":"Manufacturing & Wholesale Goods"
        }
    ],
    "sg:phone":"+1 214 637 2461",
    "sg:postcode":"75247",
    "sg:province":"TX",
    "sg:tags":[
        "trailer"
    ],
    "wof:name":"Dallas Axle & Hub Inc",
    "wof:placetype":"venue"
},
  "geometry": {"coordinates":[-96.87020200000001,32.811921],"type":"Point"}
}