{
  "type": "Feature",
  "properties": {
    "iso:country":"US",
    "sg:address":"4924 Ridgeside Dr",
    "sg:city":"Dallas",
    "sg:classifiers":[
        {
            "category":"Professional",
            "subcategory":"Management & Consulting",
            "type":"Services"
        }
    ],
    "sg:phone":"+1 972 897 4965",
    "sg:postcode":"75244",
    "sg:province":"TX",
    "sg:tags":[
        "consultant",
        "training"
    ],
    "wof:name":"Sandler Sales Institute",
    "wof:placetype":"venue"
},
  "geometry": {"coordinates":[-96.82195400000001,32.915086],"type":"Point"}
}