{
  "type": "Feature",
  "properties": {
    "iso:country":"US",
    "sg:address":"18 Purpletop Ct",
    "sg:city":"Spring",
    "sg:classifiers":[
        {
            "category":"Building & Trades",
            "subcategory":"Construction",
            "type":"Services"
        }
    ],
    "sg:phone":"+1 281 465 4557",
    "sg:postcode":"77381",
    "sg:province":"TX",
    "sg:tags":[
        "house"
    ],
    "wof:name":"Quality Home Services Inc",
    "wof:placetype":"venue"
},
  "geometry": {"coordinates":[-95.502702,30.152851],"type":"Point"}
}