{
  "type": "Feature",
  "properties": {
    "iso:country":"US",
    "sg:address":"3620 Cub St",
    "sg:city":"Corpus Christi",
    "sg:classifiers":[
        {
            "category":"Building & Trades",
            "subcategory":"Construction",
            "type":"Services"
        }
    ],
    "sg:phone":"+1 361 765 8545",
    "sg:postcode":"78405",
    "sg:province":"TX",
    "sg:tags":[
        "dry wall",
        "contractor"
    ],
    "wof:name":"Textures & More",
    "wof:placetype":"venue"
},
  "geometry": {"coordinates":[-97.43258,27.770373],"type":"Point"}
}