{
  "type": "Feature",
  "properties": {
    "iso:country":"US",
    "sg:address":"1451 Handley Dr",
    "sg:city":"Fort Worth",
    "sg:classifiers":[
        {
            "category":"Organizations",
            "subcategory":"Religious Organization",
            "type":"Services"
        }
    ],
    "sg:phone":"+1 817 451 3887",
    "sg:postcode":"76112",
    "sg:province":"TX",
    "sg:tags":[
        "church"
    ],
    "wof:name":"Brentwood Hills Primitive Bapt",
    "wof:placetype":"venue"
},
  "geometry": {"coordinates":[-97.212999,32.757686],"type":"Point"}
}