{
  "type": "Feature",
  "properties": {
    "iso:country":"US",
    "sg:address":"2703 Flintrock Cir",
    "sg:city":"Houston",
    "sg:classifiers":[
        {
            "category":"Building & Trades",
            "subcategory":"Construction",
            "type":"Services"
        }
    ],
    "sg:phone":"+1 832 215 6865",
    "sg:postcode":"77067",
    "sg:province":"TX",
    "sg:tags":[
        "contractor"
    ],
    "wof:name":"Wills Mobile & Pressure Wshg",
    "wof:placetype":"venue"
},
  "geometry": {"coordinates":[-95.465293,29.958382],"type":"Point"}
}