{
  "type": "Feature",
  "properties": {
    "iso:country":"US",
    "sg:address":"3200 N State Line Ave",
    "sg:city":"Texarkana",
    "sg:classifiers":[
        {
            "category":"Fast Food",
            "type":"Food & Drink"
        }
    ],
    "sg:phone":"+1 870 773 4943",
    "sg:postcode":"71854",
    "sg:province":"AR",
    "sg:tags":[
        "restaurant"
    ],
    "sg:website":"http://www.dixiediner.com",
    "wof:name":"Dixie Diner",
    "wof:placetype":"venue"
},
  "geometry": {"coordinates":[-94.043159,33.452942],"type":"Point"}
}