{
  "type": "Feature",
  "properties": {
    "iso:country":"US",
    "sg:address":"401 S 2nd St",
    "sg:city":"Lamesa",
    "sg:classifiers":[
        {
            "category":"Government",
            "subcategory":"Police Station",
            "type":"Public Place"
        }
    ],
    "sg:phone":"+1 806 872 7560",
    "sg:postcode":"79331",
    "sg:province":"TX",
    "sg:tags":[
        "protection"
    ],
    "wof:name":"Sheriffs Dept",
    "wof:placetype":"venue"
},
  "geometry": {"coordinates":[-101.951137,32.731124],"type":"Point"}
}