{
  "type": "Feature",
  "properties": {
    "iso:country":"US",
    "sg:address":"2218 Donegal Ct",
    "sg:city":"Deer Park",
    "sg:classifiers":[
        {
            "category":"Building & Trades",
            "subcategory":"Construction",
            "type":"Services"
        }
    ],
    "sg:phone":"+1 281 476 9094",
    "sg:postcode":"77536",
    "sg:province":"TX",
    "sg:tags":[
        "contractor"
    ],
    "wof:name":"Donnelly Dry Wall",
    "wof:placetype":"venue"
},
  "geometry": {"coordinates":[-95.12888599999999,29.691834],"type":"Point"}
}