{
  "type": "Feature",
  "properties": {
    "iso:country":"US",
    "sg:address":"724 S Garcia St",
    "sg:city":"Port Isabel",
    "sg:classifiers":[
        {
            "category":"Building & Trades",
            "subcategory":"Construction",
            "type":"Services"
        }
    ],
    "sg:phone":"+1 956 943 1893",
    "sg:postcode":"78578",
    "sg:province":"TX",
    "sg:tags":[
        "repairing",
        "remodeling",
        "contractor"
    ],
    "wof:name":"D & M Building Svc Inc",
    "wof:placetype":"venue"
},
  "geometry": {"coordinates":[-97.203378,26.073396],"type":"Point"}
}