{
  "type": "Feature",
  "properties": {
    "iso:country":"US",
    "sg:address":"11700 Deer Trl",
    "sg:city":"Amarillo",
    "sg:classifiers":[
        {
            "category":"Manufacturing",
            "subcategory":"Toys & Sporting Goods",
            "type":"Manufacturing & Wholesale Goods"
        }
    ],
    "sg:phone":"+1 806 335 1142",
    "sg:postcode":"79118",
    "sg:province":"TX",
    "sg:tags":[
        "mfg"
    ],
    "wof:name":"Texas Polocrosse",
    "wof:placetype":"venue"
},
  "geometry": {"coordinates":[-101.70379200000001,35.089652],"type":"Point"}
}