{
  "type": "Feature",
  "properties": {
    "iso:country":"US",
    "sg:address":"11102 West Ave",
    "sg:city":"San Antonio",
    "sg:classifiers":[
        {
            "category":"Real Estate",
            "subcategory":"Real Estate Agent",
            "type":"Services"
        }
    ],
    "sg:phone":"+1 210 340 6400",
    "sg:postcode":"78213",
    "sg:province":"TX",
    "wof:name":"Century 21",
    "wof:placetype":"venue"
},
  "geometry": {"coordinates":[-98.514039,29.541199],"type":"Point"}
}