{
  "type": "Feature",
  "properties": {
    "iso:country":"US",
    "sg:address":"303 S FM 1417",
    "sg:city":"Sherman",
    "sg:classifiers":[
        {
            "category":"Real Estate",
            "subcategory":"Real Estate Operator",
            "type":"Services"
        }
    ],
    "sg:phone":"+1 903 893 9551",
    "sg:postcode":"75092",
    "sg:province":"TX",
    "sg:tags":[
        "building",
        "apartment"
    ],
    "wof:name":"Lakewood Apartments",
    "wof:placetype":"venue"
},
  "geometry": {"coordinates":[-96.644997,33.623355],"type":"Point"}
}