{
  "type": "Feature",
  "properties": {
    "iso:country":"US",
    "sg:address":"409 Wildwood Ln",
    "sg:city":"Burleson",
    "sg:classifiers":[
        {
            "category":"Restaurant",
            "type":"Food & Drink"
        }
    ],
    "sg:phone":"+1 817 295 1571",
    "sg:postcode":"76028",
    "sg:province":"TX",
    "sg:tags":[
        "drinking",
        "eating"
    ],
    "wof:name":"Terrys",
    "wof:placetype":"venue"
},
  "geometry": {"coordinates":[-97.36296299999999,32.503212],"type":"Point"}
}