{
  "type": "Feature",
  "properties": {
    "iso:country":"US",
    "sg:address":"3615 Chatwood Dr",
    "sg:city":"Pearland",
    "sg:classifiers":[
        {
            "category":"Building & Trades",
            "subcategory":"Cleaning & Sanitation",
            "type":"Services"
        }
    ],
    "sg:phone":"+1 281 997 1219",
    "sg:postcode":"77584",
    "sg:province":"TX",
    "sg:tags":[
        "maintenance"
    ],
    "wof:name":"Slg Janitorial Services",
    "wof:placetype":"venue"
},
  "geometry": {"coordinates":[-95.36183,29.572982],"type":"Point"}
}