{
  "type": "Feature",
  "properties": {
    "iso:country":"US",
    "sg:address":"10528 Tanner Rd",
    "sg:city":"Houston",
    "sg:classifiers":[
        {
            "category":"Mining & Drilling",
            "type":"Manufacturing & Wholesale Goods"
        }
    ],
    "sg:phone":"+1 713 849 9600",
    "sg:postcode":"77041",
    "sg:province":"TX",
    "sg:tags":[
        "field",
        "oil"
    ],
    "wof:name":"Energy Fishing & Rental Svc",
    "wof:placetype":"venue"
},
  "geometry": {"coordinates":[-95.558654,29.850315],"type":"Point"}
}