{
  "type": "Feature",
  "properties": {
    "iso:country":"US",
    "sg:address":"1109 N Pruett St",
    "sg:city":"Baytown",
    "sg:classifiers":[
        {
            "category":"Real Estate",
            "subcategory":"Real Estate Agent",
            "type":"Services"
        }
    ],
    "sg:phone":"+1 281 428 2543",
    "sg:postcode":"77520",
    "sg:province":"TX",
    "wof:name":"G & J Properties",
    "wof:placetype":"venue"
},
  "geometry": {"coordinates":[-94.97149400000001,29.741632],"type":"Point"}
}