{
  "type": "Feature",
  "properties": {
    "iso:country":"US",
    "sg:address":"611 Paul St",
    "sg:city":"Rogers",
    "sg:classifiers":[
        {
            "category":"Real Estate",
            "subcategory":"Real Estate Operator",
            "type":"Services"
        }
    ],
    "sg:phone":"+1 254 642 3971",
    "sg:postcode":"76569",
    "sg:province":"TX",
    "sg:tags":[
        "building",
        "apartment"
    ],
    "wof:name":"Prairie Village Apartment LTD",
    "wof:placetype":"venue"
},
  "geometry": {"coordinates":[-97.22348700000001,30.9239],"type":"Point"}
}