{
  "type": "Feature",
  "properties": {
    "iso:country":"US",
    "sg:address":"310 N Washington St",
    "sg:city":"Beeville",
    "sg:classifiers":[
        {
            "category":"Health Services",
            "subcategory":"Optometrist",
            "type":"Services"
        }
    ],
    "sg:phone":"+1 361 358 3218",
    "sg:postcode":"78102",
    "sg:province":"TX",
    "wof:name":"Family Vision Assoc",
    "wof:placetype":"venue"
},
  "geometry": {"coordinates":[-97.750686,28.404488],"type":"Point"}
}