{
  "type": "Feature",
  "properties": {
    "iso:country":"US",
    "sg:address":"2594 Shell Rd Ste E",
    "sg:city":"Georgetown",
    "sg:classifiers":[
        {
            "category":"Utilities",
            "subcategory":"Water",
            "type":"Services"
        },
        {
            "category":"Recreation",
            "subcategory":"Water Park",
            "type":"Entertainment"
        },
        {
            "category":"Home & Garden",
            "subcategory":"Hardware",
            "type":"Retail Goods"
        },
        {
            "category":"Building & Trades",
            "subcategory":"Plumbing",
            "type":"Services"
        }
    ],
    "sg:phone":"+1 512 942 6161",
    "sg:postcode":"78628",
    "sg:province":"TX",
    "sg:tags":[
        "industrial",
        "filtration",
        "softening",
        "supply",
        "work",
        "supply-wholesale",
        "purification",
        "equipment",
        "conditioning",
        "supplies-commercial",
        "systems-equipment",
        "treatment"
    ],
    "wof:name":"Water Treatment Consultant",
    "wof:placetype":"venue"
},
  "geometry": {"coordinates":[-97.69092000000001,30.70824],"type":"Point"}
}