{
  "type": "Feature",
  "properties": {
    "iso:country":"US",
    "sg:address":"2109 Menton Dr",
    "sg:city":"Carrollton",
    "sg:classifiers":[
        {
            "category":"Freight",
            "type":"Transportation"
        }
    ],
    "sg:phone":"+1 972 417 7722",
    "sg:postcode":"75006",
    "sg:province":"TX",
    "wof:name":"American Logistics Group",
    "wof:placetype":"venue"
},
  "geometry": {"coordinates":[-96.883252,32.969713],"type":"Point"}
}