{
  "type": "Feature",
  "properties": {
    "iso:country":"US",
    "sg:address":"909 Salem Dr",
    "sg:city":"Corpus Christi",
    "sg:classifiers":[
        {
            "category":"Building & Trades",
            "subcategory":"Cleaning & Sanitation",
            "type":"Services"
        }
    ],
    "sg:phone":"+1 361 334 5268",
    "sg:postcode":"78412",
    "sg:province":"TX",
    "sg:tags":[
        "maintenance"
    ],
    "wof:name":"Phoenix Janitorial",
    "wof:placetype":"venue"
},
  "geometry": {"coordinates":[-97.36557000000001,27.715666],"type":"Point"}
}