{
  "type": "Feature",
  "properties": {
    "iso:country":"US",
    "sg:address":"4105 Ramsey Ave",
    "sg:city":"Austin",
    "sg:classifiers":[
        {
            "category":"Professional",
            "type":"Services"
        },
        {
            "category":"Professional",
            "subcategory":"Research",
            "type":"Services"
        }
    ],
    "sg:phone":"+1 512 477 6443",
    "sg:postcode":"78756",
    "sg:province":"TX",
    "sg:tags":[
        "archaeologist",
        "arranged",
        "outfitted",
        "expedition"
    ],
    "wof:name":"Primeira",
    "wof:placetype":"venue"
},
  "geometry": {"coordinates":[-97.746309,30.311653],"type":"Point"}
}