{
  "type": "Feature",
  "properties": {
    "iso:country":"US",
    "sg:address":"9531 Gold Hill Dr",
    "sg:city":"San Antonio",
    "sg:classifiers":[
        {
            "category":"Professional",
            "subcategory":"Business Services",
            "type":"Services"
        }
    ],
    "sg:phone":"+1 210 674 4806",
    "sg:postcode":"78245",
    "sg:province":"TX",
    "wof:name":"A & J Bargains Company",
    "wof:placetype":"venue"
},
  "geometry": {"coordinates":[-98.672066,29.428414],"type":"Point"}
}