{
  "type": "Feature",
  "properties": {
    "iso:country":"US",
    "sg:address":"2202 Emerald Oaks Ct",
    "sg:city":"Arlington",
    "sg:classifiers":[
        {
            "category":"Professional",
            "subcategory":"Accounting & Tax Preparation",
            "type":"Services"
        }
    ],
    "sg:phone":"+1 817 375 1111",
    "sg:postcode":"76017",
    "sg:province":"TX",
    "sg:tags":[
        "accountant"
    ],
    "wof:name":"Robert L Duke CPA",
    "wof:placetype":"venue"
},
  "geometry": {"coordinates":[-97.14359399999999,32.656217],"type":"Point"}
}