{
  "type": "Feature",
  "properties": {
    "iso:country":"US",
    "sg:address":"5501 Slide Rd",
    "sg:city":"Lubbock",
    "sg:classifiers":[
        {
            "category":"Restaurant",
            "type":"Food & Drink"
        }
    ],
    "sg:menulink":"http://www.allmenus.com/tx/lubbock/92935-fuddruckers/menu/",
    "sg:phone":"+1 806 687 3833",
    "sg:postcode":"79414",
    "sg:province":"TX",
    "sg:tags":[
        "burger",
        "american"
    ],
    "wof:name":"Fuddruckers",
    "wof:placetype":"venue"
},
  "geometry": {"coordinates":[-101.921773,33.543977],"type":"Point"}
}