{
  "type": "Feature",
  "properties": {
    "iso:country":"US",
    "sg:address":"3220 S Jupiter Rd",
    "sg:city":"Garland",
    "sg:classifiers":[
        {
            "category":"Building & Trades",
            "subcategory":"Equipment Rental",
            "type":"Services"
        }
    ],
    "sg:phone":"+1 972 864 1786",
    "sg:postcode":"75041",
    "sg:province":"TX",
    "wof:name":"United Rentals",
    "wof:placetype":"venue"
},
  "geometry": {"coordinates":[-96.68310099999999,32.877934],"type":"Point"}
}