{
  "type": "Feature",
  "properties": {
    "iso:country":"US",
    "sg:address":"2440 Parker Rd",
    "sg:city":"Wylie",
    "sg:classifiers":[
        {
            "category":"Manufacturing",
            "subcategory":"Buildings",
            "type":"Manufacturing & Wholesale Goods"
        }
    ],
    "sg:phone":"+1 972 442 2847",
    "sg:postcode":"75098",
    "sg:province":"TX",
    "sg:tags":[
        "home",
        "log",
        "cabin"
    ],
    "wof:name":"Air-Lock Log Co",
    "wof:placetype":"venue"
},
  "geometry": {"coordinates":[-96.54995700000001,33.05037],"type":"Point"}
}