{
  "type": "Feature",
  "properties": {
    "iso:country":"US",
    "sg:address":"28344 Aqueduct Ln",
    "sg:city":"Boerne",
    "sg:classifiers":[
        {
            "category":"Organizations",
            "subcategory":"Community Association",
            "type":"Services"
        }
    ],
    "sg:phone":"+1 210 698 1851",
    "sg:postcode":"78015",
    "sg:province":"TX",
    "wof:name":"Vanguard Institute Booster CLB",
    "wof:placetype":"venue"
},
  "geometry": {"coordinates":[-98.63348499999999,29.717325],"type":"Point"}
}