{
  "type": "Feature",
  "properties": {
    "iso:country":"US",
    "sg:address":"115 Rob Ln",
    "sg:city":"De Soto",
    "sg:classifiers":[
        {
            "category":"Professional",
            "type":"Services"
        }
    ],
    "sg:phone":"+1 972 223 7182",
    "sg:postcode":"75115",
    "sg:province":"TX",
    "wof:name":"Grapevine Car Service",
    "wof:placetype":"venue"
},
  "geometry": {"coordinates":[-96.860838,32.566147],"type":"Point"}
}