{
  "type": "Feature",
  "properties": {
    "iso:country":"US",
    "sg:address":"707 N Hwy 67",
    "sg:city":"Cedar Hill",
    "sg:classifiers":[
        {
            "category":"Shopping",
            "subcategory":"Musical Instruments",
            "type":"Retail Goods"
        }
    ],
    "sg:phone":"+1 214 330 0453",
    "sg:postcode":"75104",
    "sg:province":"TX",
    "sg:tags":[
        "piano"
    ],
    "sg:website":"www.brookmays.com",
    "wof:name":"Brook Mays Music Co",
    "wof:placetype":"venue"
},
  "geometry": {"coordinates":[-96.93432199999999,32.601712],"type":"Point"}
}