{
  "type": "Feature",
  "properties": {
    "iso:country":"US",
    "sg:address":"13839 Southwest Fwy",
    "sg:city":"Sugar Land",
    "sg:classifiers":[
        {
            "category":"Health Services",
            "subcategory":"Doctor",
            "type":"Services"
        }
    ],
    "sg:phone":"+1 281 242 5959",
    "sg:postcode":"77478",
    "sg:province":"TX",
    "wof:name":"Family Dentistry Of Fort Bend",
    "wof:placetype":"venue"
},
  "geometry": {"coordinates":[-95.600808,29.621843],"type":"Point"}
}