{
  "type": "Feature",
  "properties": {
    "iso:country":"US",
    "sg:address":"6404 Ashington Cir",
    "sg:city":"Plano",
    "sg:classifiers":[
        {
            "category":"Banks & Credit Unions",
            "subcategory":"Bank",
            "type":"Services"
        }
    ],
    "sg:phone":"+1 972 618 2414",
    "sg:postcode":"75023",
    "sg:province":"TX",
    "sg:tags":[
        "loan",
        "broker"
    ],
    "wof:name":"Eckert Enterprises Inc",
    "wof:placetype":"venue"
},
  "geometry": {"coordinates":[-96.75984200000001,33.059309],"type":"Point"}
}