{
  "type": "Feature",
  "properties": {
    "iso:country":"US",
    "sg:address":"33223 Forest West St",
    "sg:city":"Magnolia",
    "sg:classifiers":[
        {
            "category":"Professional",
            "subcategory":"Management & Consulting",
            "type":"Services"
        },
        {
            "category":"Building & Trades",
            "subcategory":"Construction",
            "type":"Services"
        }
    ],
    "sg:phone":"+1 281 252 3209",
    "sg:postcode":"77354",
    "sg:province":"TX",
    "sg:tags":[
        "railroad",
        "contractor"
    ],
    "wof:name":"Gulf Coast Rail Group Inc",
    "wof:placetype":"venue"
},
  "geometry": {"coordinates":[-95.58054,30.22829],"type":"Point"}
}