{
  "type": "Feature",
  "properties": {
    "iso:country":"US",
    "sg:address":"2105 Tradewinds Dr",
    "sg:city":"Missouri City",
    "sg:classifiers":[
        {
            "category":"Real Estate",
            "subcategory":"Real Estate Agent",
            "type":"Services"
        }
    ],
    "sg:phone":"+1 281 499 4392",
    "sg:postcode":"77459",
    "sg:province":"TX",
    "wof:name":"Trancapital Inc",
    "wof:placetype":"venue"
},
  "geometry": {"coordinates":[-95.57098499999999,29.588797],"type":"Point"}
}