{
  "type": "Feature",
  "properties": {
    "iso:country":"US",
    "sg:address":"902 Frostwood Dr",
    "sg:city":"Houston",
    "sg:classifiers":[
        {
            "category":"Health Services",
            "subcategory":"Doctor",
            "type":"Services"
        }
    ],
    "sg:phone":"+1 713 932 6565",
    "sg:postcode":"77024",
    "sg:province":"TX",
    "sg:tags":[
        "physician",
        "surgeon",
        "medical"
    ],
    "wof:name":"Robert W Koshman MD",
    "wof:placetype":"venue"
},
  "geometry": {"coordinates":[-95.547709,29.778615],"type":"Point"}
}