{
  "type": "Feature",
  "properties": {
    "iso:country":"US",
    "sg:address":"1646 NW Parkway St",
    "sg:city":"Azle",
    "sg:classifiers":[
        {
            "category":"Professional",
            "type":"Services"
        }
    ],
    "sg:phone":"+1 817 677 4886",
    "sg:postcode":"76020",
    "sg:province":"TX",
    "sg:tags":[
        "establishment"
    ],
    "wof:name":"Bailey Group",
    "wof:placetype":"venue"
},
  "geometry": {"coordinates":[-97.571985,32.907882],"type":"Point"}
}