{
  "type": "Feature",
  "properties": {
    "iso:country":"US",
    "sg:address":"4444 N Galloway Ave",
    "sg:city":"Mesquite",
    "sg:classifiers":[
        {
            "category":"Home & Garden",
            "subcategory":"Building Materials",
            "type":"Retail Goods"
        }
    ],
    "sg:phone":"+1 972 686 3823",
    "sg:postcode":"75150",
    "sg:province":"TX",
    "sg:tags":[
        "supply"
    ],
    "wof:name":"Lowe's Home Improvement Warehouse Store of",
    "wof:placetype":"venue"
},
  "geometry": {"coordinates":[-96.622704,32.824501],"type":"Point"}
}