{
  "type": "Feature",
  "properties": {
    "iso:country":"US",
    "sg:address":"121 N 21st St",
    "sg:city":"Mcallen",
    "sg:classifiers":[
        {
            "category":"Shopping",
            "subcategory":"Florist",
            "type":"Retail Goods"
        },
        {
            "category":"Manufacturing",
            "subcategory":"Watercraft",
            "type":"Manufacturing & Wholesale Goods"
        }
    ],
    "sg:phone":"+1 956 630 2717",
    "sg:postcode":"78501",
    "sg:province":"TX",
    "sg:website":"www.handcrafttexas.com",
    "wof:name":"Handcrafts",
    "wof:placetype":"venue"
},
  "geometry": {"coordinates":[-98.24169999999999,26.206427],"type":"Point"}
}