{
  "type": "Feature",
  "properties": {
    "iso:country":"US",
    "sg:address":"13502 Agarita Ln",
    "sg:city":"Houston",
    "sg:classifiers":[
        {
            "category":"Professional",
            "type":"Services"
        }
    ],
    "sg:phone":"+1 281 498 7138",
    "sg:postcode":"77083",
    "sg:province":"TX",
    "wof:name":"Hontex Co",
    "wof:placetype":"venue"
},
  "geometry": {"coordinates":[-95.621793,29.708195],"type":"Point"}
}