{
  "type": "Feature",
  "properties": {
    "iso:country":"US",
    "sg:address":"16918 N Derby Ave",
    "sg:city":"Gardendale",
    "sg:classifiers":[
        {
            "category":"Building & Trades",
            "subcategory":"Electrical",
            "type":"Services"
        }
    ],
    "sg:phone":"+1 432 563 4811",
    "sg:postcode":"79758",
    "sg:province":"TX",
    "sg:tags":[
        "industrial",
        "electrician",
        "contractors-commercial",
        "electric"
    ],
    "wof:name":"Fidel's Electrical Service",
    "wof:placetype":"venue"
},
  "geometry": {"coordinates":[-102.301571,32.050988],"type":"Point"}
}