{
  "type": "Feature",
  "properties": {
    "iso:country":"US",
    "sg:address":"12801 Midway Rd",
    "sg:city":"Dallas",
    "sg:classifiers":[
        {
            "category":"Banks & Credit Unions",
            "subcategory":"Bank",
            "type":"Services"
        }
    ],
    "sg:phone":"+1 972 247 2532",
    "sg:postcode":"75229",
    "sg:province":"TX",
    "sg:tags":[
        "cashing",
        "check"
    ],
    "wof:name":"Check 'n Go",
    "wof:placetype":"venue"
},
  "geometry": {"coordinates":[-96.838453,32.924585],"type":"Point"}
}