{
  "type": "Feature",
  "properties": {
    "iso:country":"US",
    "sg:address":"3605 State Hwy 107",
    "sg:city":"Edinburg",
    "sg:classifiers":[
        {
            "category":"Bars & Pubs",
            "type":"Food & Drink"
        }
    ],
    "sg:phone":"+1 956 289 8153",
    "sg:postcode":"78539",
    "sg:province":"TX",
    "sg:tags":[
        "lounge",
        "cocktail"
    ],
    "wof:name":"Chano's Lounge",
    "wof:placetype":"venue"
},
  "geometry": {"coordinates":[-98.185371,26.304792],"type":"Point"}
}