{
  "type": "Feature",
  "properties": {
    "iso:country":"US",
    "sg:address":"3344 Chimney Rock Rd",
    "sg:city":"Houston",
    "sg:classifiers":[
        {
            "category":"Food & Beverages",
            "subcategory":"Groceries & Convenience Stores",
            "type":"Retail Goods"
        }
    ],
    "sg:phone":"+1 713 783 6071",
    "sg:postcode":"77056",
    "sg:province":"TX",
    "wof:name":"Sunny's Food Store",
    "wof:placetype":"venue"
},
  "geometry": {"coordinates":[-95.476601,29.729099],"type":"Point"}
}