{
  "type": "Feature",
  "properties": {
    "iso:country":"US",
    "sg:address":"14000 S Post Oak Rd",
    "sg:city":"Houston",
    "sg:classifiers":[
        {
            "category":"Building & Trades",
            "subcategory":"Construction",
            "type":"Services"
        }
    ],
    "sg:phone":"+1 713 433 6026",
    "sg:postcode":"77045",
    "sg:province":"TX",
    "sg:tags":[
        "carpentry",
        "contractor"
    ],
    "wof:name":"Wood Crafters",
    "wof:placetype":"venue"
},
  "geometry": {"coordinates":[-95.465132,29.623993],"type":"Point"}
}