{
  "type": "Feature",
  "properties": {
    "iso:country":"US",
    "sg:address":"2412 Gulf Blvd",
    "sg:city":"S Padre Island",
    "sg:classifiers":[
        {
            "category":"Real Estate",
            "subcategory":"Real Estate Operator",
            "type":"Services"
        }
    ],
    "sg:phone":"+1 956 761 4315",
    "sg:postcode":"78597",
    "sg:province":"TX",
    "sg:tags":[
        "condominium"
    ],
    "wof:name":"Santa Barbara Condominium",
    "wof:placetype":"venue"
},
  "geometry": {"coordinates":[-97.164725,26.102776],"type":"Point"}
}