{
  "type": "Feature",
  "properties": {
    "iso:country":"US",
    "sg:address":"427 Savannah Springs Way",
    "sg:city":"Spring",
    "sg:classifiers":[
        {
            "category":"Professional",
            "subcategory":"Management & Consulting",
            "type":"Services"
        }
    ],
    "sg:phone":"+1 281 350 5353",
    "sg:postcode":"77373",
    "sg:province":"TX",
    "sg:tags":[
        "scheduling",
        "energy",
        "analysis"
    ],
    "wof:name":"Power Tex Energy Services LLC",
    "wof:placetype":"venue"
},
  "geometry": {"coordinates":[-95.427886,30.068543],"type":"Point"}
}