{
  "type": "Feature",
  "properties": {
    "iso:country":"US",
    "sg:address":"37450 I- 10 W",
    "sg:city":"Boerne",
    "sg:classifiers":[
        {
            "category":"Professional",
            "type":"Services"
        }
    ],
    "sg:phone":"+1 830 816 4360",
    "sg:postcode":"78006",
    "sg:province":"TX",
    "sg:tags":[
        "establishment"
    ],
    "wof:name":"RDS",
    "wof:placetype":"venue"
},
  "geometry": {"coordinates":[-98.75383600000001,29.804209],"type":"Point"}
}