{
  "type": "Feature",
  "properties": {
    "iso:country":"US",
    "sg:address":"8302 Grovecrest Dr",
    "sg:city":"Dallas",
    "sg:classifiers":[
        {
            "category":"Building & Trades",
            "subcategory":"Construction",
            "type":"Services"
        }
    ],
    "sg:phone":"+1 214 309 0739",
    "sg:postcode":"75217",
    "sg:province":"TX",
    "sg:tags":[
        "fence",
        "contractor"
    ],
    "wof:name":"B G Fence Co",
    "wof:placetype":"venue"
},
  "geometry": {"coordinates":[-96.674316,32.737348],"type":"Point"}
}