{
  "type": "Feature",
  "properties": {
    "iso:country":"US",
    "sg:address":"107 Brookside Dr",
    "sg:city":"Powell",
    "sg:classifiers":[
        {
            "category":"Building & Trades",
            "subcategory":"Landscaping Services",
            "type":"Services"
        }
    ],
    "sg:phone":"+1 903 345 2563",
    "sg:postcode":"75137",
    "sg:province":"TX",
    "sg:tags":[
        "farm",
        "pecan",
        "landscape",
        "contractor"
    ],
    "wof:name":"Green Tree Landscape",
    "wof:placetype":"venue"
},
  "geometry": {"coordinates":[-96.9061,32.635384],"type":"Point"}
}