{
  "type": "Feature",
  "properties": {
    "iso:country":"US",
    "sg:address":"1500 E Main St",
    "sg:city":"Itasca",
    "sg:phone":"+1 254 687 9987",
    "sg:postcode":"76055",
    "sg:province":"TX",
    "wof:name":"Diaz Tex Mex Restaurant",
    "wof:placetype":"venue"
},
  "geometry": {"coordinates":[-97.129868,32.170101],"type":"Point"}
}