{
  "type": "Feature",
  "properties": {
    "iso:country":"US",
    "sg:address":"215 State Hwy 243",
    "sg:city":"Canton",
    "sg:classifiers":[
        {
            "category":"Wholesale",
            "subcategory":"Auto Parts",
            "type":"Manufacturing & Wholesale Goods"
        }
    ],
    "sg:phone":"+1 903 567 4118",
    "sg:postcode":"75103",
    "sg:province":"TX",
    "sg:tags":[
        "supply"
    ],
    "wof:name":"Canton Auto Parts",
    "wof:placetype":"venue"
},
  "geometry": {"coordinates":[-95.86529299999999,32.544202],"type":"Point"}
}