{
  "type": "Feature",
  "properties": {
    "iso:country":"US",
    "sg:address":"6981 Agua Bravo Dr",
    "sg:city":"Brownsville",
    "sg:classifiers":[
        {
            "category":"Restaurant",
            "type":"Food & Drink"
        }
    ],
    "sg:phone":"+1 956 546 7770",
    "sg:postcode":"78526",
    "sg:province":"TX",
    "wof:name":"Flautas King",
    "wof:placetype":"venue"
},
  "geometry": {"coordinates":[-97.41546700000001,25.948636],"type":"Point"}
}