{
  "type": "Feature",
  "properties": {
    "iso:country":"US",
    "sg:address":"2006 Fair Oaks Cir",
    "sg:city":"Corinth",
    "sg:classifiers":[
        {
            "category":"Arts & Performance",
            "subcategory":"Dance",
            "type":"Entertainment"
        }
    ],
    "sg:phone":"+1 940 497 0695",
    "sg:postcode":"76210",
    "sg:province":"TX",
    "sg:tags":[
        "instruction",
        "dancing"
    ],
    "wof:name":"Spirit Unlimited",
    "wof:placetype":"venue"
},
  "geometry": {"coordinates":[-97.08008700000001,33.163225],"type":"Point"}
}