{
  "type": "Feature",
  "properties": {
    "iso:country":"US",
    "sg:address":"597 S Padre Island Dr",
    "sg:city":"Corpus Christi",
    "sg:classifiers":[
        {
            "category":"Food & Beverages",
            "subcategory":"Groceries & Convenience Stores",
            "type":"Retail Goods"
        }
    ],
    "sg:phone":"+1 361 289 7416",
    "sg:postcode":"78405",
    "sg:province":"TX",
    "wof:name":"Circle K",
    "wof:placetype":"venue"
},
  "geometry": {"coordinates":[-97.46195299999999,27.757492],"type":"Point"}
}