{
  "type": "Feature",
  "properties": {
    "iso:country":"US",
    "sg:address":"319 N Main Ave",
    "sg:city":"Denver City",
    "sg:classifiers":[
        {
            "category":"Professional",
            "subcategory":"Lawyer & Legal Services",
            "type":"Services"
        }
    ],
    "sg:phone":"+1 806 592 2129",
    "sg:postcode":"79323",
    "sg:province":"TX",
    "sg:tags":[
        "attorney"
    ],
    "wof:name":"New & New Attorneys",
    "wof:placetype":"venue"
},
  "geometry": {"coordinates":[-102.829306,32.967703],"type":"Point"}
}