{
  "type": "Feature",
  "properties": {
    "iso:country":"US",
    "sg:address":"901 Evergreen St",
    "sg:city":"Amarillo",
    "sg:classifiers":[
        {
            "category":"Personal",
            "type":"Services"
        }
    ],
    "sg:phone":"+1 806 383 7303",
    "sg:postcode":"79107",
    "sg:province":"TX",
    "wof:name":"Maintenance Etc",
    "wof:placetype":"venue"
},
  "geometry": {"coordinates":[-101.768843,35.226785],"type":"Point"}
}