{
  "type": "Feature",
  "properties": {
    "iso:country":"US",
    "sg:address":"5955 Alpha Rd",
    "sg:city":"Dallas",
    "sg:classifiers":[
        {
            "category":"Shopping",
            "subcategory":"Computers & Home Electronics",
            "type":"Retail Goods"
        }
    ],
    "sg:phone":"+1 972 458 7008",
    "sg:postcode":"75240",
    "sg:province":"TX",
    "wof:name":"Circuit City",
    "wof:placetype":"venue"
},
  "geometry": {"coordinates":[-96.80048600000001,32.933324],"type":"Point"}
}