{
  "type": "Feature",
  "properties": {
    "iso:country":"US",
    "sg:address":"101 Cardinal Dr",
    "sg:city":"Frankston",
    "sg:classifiers":[
        {
            "category":"Building & Trades",
            "subcategory":"Construction",
            "type":"Services"
        }
    ],
    "sg:phone":"+1 903 876 3407",
    "sg:postcode":"75763",
    "sg:province":"TX",
    "sg:tags":[
        "system",
        "contractor",
        "air conditioning"
    ],
    "wof:name":"Carr Air Conditioning",
    "wof:placetype":"venue"
},
  "geometry": {"coordinates":[-95.505989,32.047958],"type":"Point"}
}