{
  "type": "Feature",
  "properties": {
    "iso:country":"US",
    "sg:address":"8416 Forest Hills Blvd",
    "sg:city":"Dallas",
    "sg:classifiers":[
        {
            "category":"Professional",
            "subcategory":"Business Services",
            "type":"Services"
        }
    ],
    "sg:phone":"+1 214 319 7245",
    "sg:postcode":"75218",
    "sg:province":"TX",
    "wof:name":"Woods Laurie S Asid",
    "wof:placetype":"venue"
},
  "geometry": {"coordinates":[-96.713781,32.818368],"type":"Point"}
}