{
  "type": "Feature",
  "properties": {
    "iso:country":"US",
    "sg:address":"4610 S R L Thornton Fwy",
    "sg:city":"Dallas",
    "sg:classifiers":[
        {
            "category":"Travel",
            "subcategory":"Hotels & Motels",
            "type":"Entertainment"
        }
    ],
    "sg:phone":"+1 214 372 5924",
    "sg:postcode":"75224",
    "sg:province":"TX",
    "wof:name":"Motel 6",
    "wof:placetype":"venue"
},
  "geometry": {"coordinates":[-96.82451,32.688616],"type":"Point"}
}