{
  "type": "Feature",
  "properties": {
    "iso:country":"US",
    "sg:address":"6103 FM 1960 W",
    "sg:city":"Houston",
    "sg:classifiers":[
        {
            "category":"Personal",
            "subcategory":"Beauty Salon",
            "type":"Services"
        }
    ],
    "sg:phone":"+1 281 444 6864",
    "sg:postcode":"77069",
    "sg:province":"TX",
    "sg:tags":[
        "shop"
    ],
    "wof:name":"Doan's Diamond Nails",
    "wof:placetype":"venue"
},
  "geometry": {"coordinates":[-95.517928,29.977139],"type":"Point"}
}