{
  "type": "Feature",
  "properties": {
    "iso:country":"US",
    "sg:address":"300 Crescent Ct",
    "sg:city":"Dallas",
    "sg:classifiers":[
        {
            "category":"Airline",
            "type":"Transportation"
        }
    ],
    "sg:phone":"+1 214 661 3100",
    "sg:postcode":"75201",
    "sg:province":"TX",
    "sg:tags":[
        "charter",
        "flying"
    ],
    "wof:name":"Jjf Air Transport LLC",
    "wof:placetype":"venue"
},
  "geometry": {"coordinates":[-96.803898,32.794041],"type":"Point"}
}