{
  "type": "Feature",
  "properties": {
    "iso:country":"US",
    "sg:address":"1201 E End Blvd S",
    "sg:city":"Marshall",
    "sg:classifiers":[
        {
            "category":"Shopping",
            "type":"Retail Goods"
        }
    ],
    "sg:phone":"+1 903 927 2443",
    "sg:postcode":"75670",
    "sg:province":"TX",
    "sg:tags":[
        "merchandise",
        "motorcycle",
        "boat"
    ],
    "wof:name":"Lone Star Power Sports",
    "wof:placetype":"venue"
},
  "geometry": {"coordinates":[-94.35033,32.533915],"type":"Point"}
}