{
  "type": "Feature",
  "properties": {
    "iso:country":"US",
    "sg:address":"4400 Andrews Hwy Apt 712",
    "sg:city":"Midland",
    "sg:classifiers":[
        {
            "category":"Building & Trades",
            "subcategory":"Construction",
            "type":"Services"
        }
    ],
    "sg:phone":"+1 432 212 5672",
    "sg:postcode":"79703",
    "sg:province":"TX",
    "sg:tags":[
        "wallcoverings-installation",
        "wallpaper",
        "painting",
        "contractor"
    ],
    "wof:name":"Ronny Poole Painting",
    "wof:placetype":"venue"
},
  "geometry": {"coordinates":[-102.130585,32.003521],"type":"Point"}
}