{
  "type": "Feature",
  "properties": {
    "iso:country":"US",
    "sg:address":"1904 Aduanales Ln",
    "sg:city":"Laredo",
    "sg:classifiers":[
        {
            "category":"Manufacturing",
            "subcategory":"Retail Goods",
            "type":"Manufacturing & Wholesale Goods"
        }
    ],
    "sg:phone":"+1 956 725 1771",
    "sg:postcode":"78041",
    "sg:province":"TX",
    "sg:tags":[
        "mfg"
    ],
    "wof:name":"Anderson Brighton Co Inc",
    "wof:placetype":"venue"
},
  "geometry": {"coordinates":[-99.51522199999999,27.542684],"type":"Point"}
}