{
  "type": "Feature",
  "properties": {
    "iso:country":"US",
    "sg:address":"8275 SE 1020 Rd",
    "sg:city":"Corsicana",
    "sg:classifiers":[
        {
            "category":"Farming",
            "subcategory":"Livestock Farm",
            "type":"Manufacturing & Wholesale Goods"
        }
    ],
    "sg:phone":"+1 903 874 6873",
    "sg:postcode":"75110",
    "sg:province":"TX",
    "sg:tags":[
        "horse",
        "other",
        "equine"
    ],
    "wof:name":"Horizon Real Estate",
    "wof:placetype":"venue"
},
  "geometry": {"coordinates":[-96.408018,31.993035],"type":"Point"}
}