{
  "type": "Feature",
  "properties": {
    "iso:country":"US",
    "sg:address":"2100 Hampton Ct",
    "sg:city":"Carrollton",
    "sg:classifiers":[
        {
            "category":"Professional",
            "subcategory":"Business Services",
            "type":"Services"
        }
    ],
    "sg:phone":"+1 972 242 7083",
    "sg:postcode":"75006",
    "sg:province":"TX",
    "wof:name":"Jangle Group",
    "wof:placetype":"venue"
},
  "geometry": {"coordinates":[-96.89869299999999,32.968671],"type":"Point"}
}