{
  "type": "Feature",
  "properties": {
    "iso:country":"US",
    "sg:address":"735 Dulles Ave",
    "sg:city":"Stafford",
    "sg:classifiers":[
        {
            "category":"Professional",
            "type":"Services"
        }
    ],
    "sg:phone":"+1 281 499 6632",
    "sg:postcode":"77477",
    "sg:province":"TX",
    "sg:tags":[
        "establishment"
    ],
    "wof:name":"Houston Corporate Ofc At Vnngs",
    "wof:placetype":"venue"
},
  "geometry": {"coordinates":[-95.58246,29.619637],"type":"Point"}
}