{
  "type": "Feature",
  "properties": {
    "iso:country":"US",
    "sg:address":"231 W Lynwood Ave",
    "sg:city":"San Antonio",
    "sg:classifiers":[
        {
            "category":"Manufacturing",
            "subcategory":"Tools & Machinery",
            "type":"Manufacturing & Wholesale Goods"
        }
    ],
    "sg:phone":"+1 210 735 5371",
    "sg:postcode":"78212",
    "sg:province":"TX",
    "sg:tags":[
        "mfg",
        "ophthalmic"
    ],
    "wof:name":"Ophthalmic Diagnostic Tech",
    "wof:placetype":"venue"
},
  "geometry": {"coordinates":[-98.49690099999999,29.463176],"type":"Point"}
}