{
  "type": "Feature",
  "properties": {
    "iso:country":"US",
    "sg:address":"801 Beach Blvd",
    "sg:city":"Port Isabel",
    "sg:classifiers":[
        {
            "category":"Professional",
            "type":"Services"
        }
    ],
    "sg:phone":"+1 956 943 5159",
    "sg:postcode":"78578",
    "sg:province":"TX",
    "wof:name":"Paul Paulusma",
    "wof:placetype":"venue"
},
  "geometry": {"coordinates":[-97.29467099999999,26.105026],"type":"Point"}
}