{
  "type": "Feature",
  "properties": {
    "iso:country":"US",
    "sg:address":"6920 W Military Dr",
    "sg:city":"San Antonio",
    "sg:classifiers":[
        {
            "category":"Professional",
            "subcategory":"Accounting & Tax Preparation",
            "type":"Services"
        }
    ],
    "sg:phone":"+1 210 674 9000",
    "sg:postcode":"78227",
    "sg:province":"TX",
    "sg:tags":[
        "return",
        "filing"
    ],
    "wof:name":"R & M Rapid Refund Tax Ctr",
    "wof:placetype":"venue"
},
  "geometry": {"coordinates":[-98.62909000000001,29.406301],"type":"Point"}
}