{
  "type": "Feature",
  "properties": {
    "iso:country":"US",
    "sg:address":"549 Dickman Rd",
    "sg:city":"El Paso",
    "sg:classifiers":[
        {
            "category":"Health Services",
            "subcategory":"Doctor",
            "type":"Services"
        }
    ],
    "sg:phone":"+1 915 569 2421",
    "sg:postcode":"79906",
    "sg:province":"TX",
    "sg:tags":[
        "physician",
        "surgeon"
    ],
    "wof:name":"Rodney Del Valle MD",
    "wof:placetype":"venue"
},
  "geometry": {"coordinates":[-106.430812,31.798222],"type":"Point"}
}