{
  "type": "Feature",
  "properties": {
    "iso:country":"US",
    "sg:address":"9344 Jones Rd",
    "sg:city":"Houston",
    "sg:classifiers":[
        {
            "category":"Restaurant",
            "type":"Food & Drink"
        }
    ],
    "sg:menulink":"http://www.allmenus.com/tx/houston/139506-quiznos-sub/menu/",
    "sg:phone":"+1 281 894 0100",
    "sg:postcode":"77065",
    "sg:province":"TX",
    "sg:tags":[
        "wrap",
        "american",
        "sandwich"
    ],
    "wof:name":"Quiznos Sub",
    "wof:placetype":"venue"
},
  "geometry": {"coordinates":[-95.58456700000001,29.908654],"type":"Point"}
}