{
  "type": "Feature",
  "properties": {
    "iso:country":"US",
    "sg:address":"2500 Fondren Rd Ste 310",
    "sg:city":"Houston",
    "sg:classifiers":[
        {
            "category":"Health Services",
            "subcategory":"Doctor",
            "type":"Services"
        },
        {
            "category":"Health Services",
            "subcategory":"Clinic",
            "type":"Services"
        },
        {
            "category":"Health Services",
            "subcategory":"Podiatrist",
            "type":"Services"
        }
    ],
    "sg:phone":"+1 713 781 0019",
    "sg:postcode":"77063",
    "sg:province":"TX",
    "sg:tags":[
        "physician",
        "surgeons"
    ],
    "wof:name":"Nussbaum Meynard M DPM",
    "wof:placetype":"venue"
},
  "geometry": {"coordinates":[-95.52130099999999,29.7393],"type":"Point"}
}