{
  "type": "Feature",
  "properties": {
    "iso:country":"US",
    "sg:address":"5030 E University Blvd",
    "sg:city":"Odessa",
    "sg:classifiers":[
        {
            "category":"Professional",
            "subcategory":"Lawyer & Legal Services",
            "type":"Services"
        }
    ],
    "sg:phone":"+1 432 363 1300",
    "sg:postcode":"79762",
    "sg:province":"TX",
    "wof:name":"Durell Jay Atty",
    "wof:placetype":"venue"
},
  "geometry": {"coordinates":[-102.316672,31.882543],"type":"Point"}
}