{
  "type": "Feature",
  "properties": {
    "iso:country":"US",
    "sg:address":"101 N Greer Blvd",
    "sg:city":"Pittsburg",
    "sg:classifiers":[
        {
            "category":"Food & Beverages",
            "subcategory":"Groceries & Convenience Stores",
            "type":"Retail Goods"
        }
    ],
    "sg:phone":"+1 903 856 0630",
    "sg:postcode":"75686",
    "sg:province":"TX",
    "wof:name":"Corner Express",
    "wof:placetype":"venue"
},
  "geometry": {"coordinates":[-94.958635,32.999446],"type":"Point"}
}