{
  "type": "Feature",
  "properties": {
    "iso:country":"US",
    "sg:address":"220 W Oak St",
    "sg:city":"Palestine",
    "sg:classifiers":[
        {
            "category":"Shopping",
            "subcategory":"Optical Goods",
            "type":"Retail Goods"
        }
    ],
    "sg:phone":"+1 903 729 2020",
    "sg:postcode":"75801",
    "sg:province":"TX",
    "wof:name":"Eye 20/20 Optical",
    "wof:placetype":"venue"
},
  "geometry": {"coordinates":[-95.63264700000001,31.762543],"type":"Point"}
}