{
  "type": "Feature",
  "properties": {
    "iso:country":"US",
    "sg:address":"2304 White Oak Dr",
    "sg:city":"Houston",
    "sg:classifiers":[
        {
            "category":"Personal",
            "subcategory":"Barber",
            "type":"Services"
        }
    ],
    "sg:phone":"+1 713 861 7060",
    "sg:postcode":"77009",
    "sg:province":"TX",
    "sg:tags":[
        "shop"
    ],
    "wof:name":"Heights Barber Shop",
    "wof:placetype":"venue"
},
  "geometry": {"coordinates":[-95.382131,29.780021],"type":"Point"}
}