{
  "type": "Feature",
  "properties": {
    "iso:country":"US",
    "sg:address":"2103 Broadway St",
    "sg:city":"Houston",
    "sg:classifiers":[
        {
            "category":"Restaurant",
            "type":"Food & Drink"
        }
    ],
    "sg:phone":"+1 713 644 4855",
    "sg:postcode":"77012",
    "sg:province":"TX",
    "sg:tags":[
        "eating"
    ],
    "wof:name":"Ovantojitos Los Reyes",
    "wof:placetype":"venue"
},
  "geometry": {"coordinates":[-95.27801100000001,29.709058],"type":"Point"}
}