{
  "type": "Feature",
  "properties": {
    "iso:country":"US",
    "sg:address":"11020 Munn St",
    "sg:city":"Houston",
    "sg:classifiers":[
        {
            "category":"Building & Trades",
            "subcategory":"Construction",
            "type":"Services"
        }
    ],
    "sg:phone":"+1 713 451 0859",
    "sg:postcode":"77029",
    "sg:province":"TX",
    "sg:tags":[
        "contractor"
    ],
    "wof:name":"Lopez Paint Contractor",
    "wof:placetype":"venue"
},
  "geometry": {"coordinates":[-95.235026,29.76312],"type":"Point"}
}