{
  "type": "Feature",
  "properties": {
    "iso:country":"US",
    "sg:address":"1640 Doug Olson Dr",
    "sg:city":"El Paso",
    "sg:classifiers":[
        {
            "category":"Social Services",
            "subcategory":"Child Care",
            "type":"Services"
        }
    ],
    "sg:phone":"+1 915 855 0212",
    "sg:postcode":"79936",
    "sg:province":"TX",
    "wof:name":"Dinos Day Care",
    "wof:placetype":"venue"
},
  "geometry": {"coordinates":[-106.29665799999999,31.75155],"type":"Point"}
}