{
  "type": "Feature",
  "properties": {
    "iso:country":"US",
    "sg:address":"10109 Clarks Air Fld",
    "sg:city":"Justin",
    "sg:classifiers":[
        {
            "category":"Autos & Motor Vehicles",
            "subcategory":"Recreational Vehicle Sales",
            "type":"Retail Goods"
        }
    ],
    "sg:phone":"+1 940 648 2264",
    "sg:postcode":"76247",
    "sg:province":"TX",
    "sg:tags":[
        "aircraft"
    ],
    "sg:website":"http://www.clarksrvsales.com",
    "wof:name":"Clark's Aircraft & R V Sales",
    "wof:placetype":"venue"
},
  "geometry": {"coordinates":[-97.298914,33.13116],"type":"Point"}
}