{
  "type": "Feature",
  "properties": {
    "iso:country":"US",
    "sg:address":"5022 US Hwy 90 Alt",
    "sg:city":"Sugar Land",
    "sg:classifiers":[
        {
            "category":"Food & Beverages",
            "subcategory":"Specialty",
            "type":"Retail Goods"
        }
    ],
    "sg:phone":"+1 281 265 3285",
    "sg:postcode":"77478",
    "sg:province":"TX",
    "sg:tags":[
        "health",
        "diet"
    ],
    "wof:name":"Herbalife Distributor",
    "wof:placetype":"venue"
},
  "geometry": {"coordinates":[-95.68111500000001,29.60183],"type":"Point"}
}