{
  "type": "Feature",
  "properties": {
    "iso:country":"US",
    "sg:address":"1916 Baldwin St",
    "sg:city":"Houston",
    "sg:classifiers":[
        {
            "category":"Professional",
            "subcategory":"Lawyer & Legal Services",
            "type":"Services"
        }
    ],
    "sg:phone":"+1 713 652 2555",
    "sg:postcode":"77002",
    "sg:province":"TX",
    "sg:tags":[
        "attorney"
    ],
    "wof:name":"Lundeen & Dickinson Llp",
    "wof:placetype":"venue"
},
  "geometry": {"coordinates":[-95.376503,29.753799],"type":"Point"}
}