{
  "type": "Feature",
  "properties": {
    "iso:country":"US",
    "sg:address":"1322 S Main St",
    "sg:city":"Perryton",
    "sg:classifiers":[
        {
            "category":"Manufacturing",
            "subcategory":"Food",
            "type":"Manufacturing & Wholesale Goods"
        }
    ],
    "sg:phone":"+1 817 293 6230",
    "sg:postcode":"79070",
    "sg:province":"TX",
    "sg:tags":[
        "product",
        "mfg"
    ],
    "wof:name":"Mrs Bairds Bakeries",
    "wof:placetype":"venue"
},
  "geometry": {"coordinates":[-100.802708,36.387037],"type":"Point"}
}