{
  "type": "Feature",
  "properties": {
    "iso:country":"US",
    "sg:address":"4032 Glenwick Ln",
    "sg:city":"Dallas",
    "sg:classifiers":[
        {
            "category":"Banks & Credit Unions",
            "subcategory":"Financial Services",
            "type":"Services"
        }
    ],
    "sg:phone":"+1 214 522 0692",
    "sg:postcode":"75205",
    "sg:province":"TX",
    "sg:tags":[
        "trust",
        "investment",
        "real estate"
    ],
    "wof:name":"413 Thompson Company LLC",
    "wof:placetype":"venue"
},
  "geometry": {"coordinates":[-96.80366100000001,32.846869],"type":"Point"}
}