{
  "type": "Feature",
  "properties": {
    "iso:country":"US",
    "sg:address":"1316 S Cooper St",
    "sg:city":"Arlington",
    "sg:classifiers":[
        {
            "category":"Restaurant",
            "type":"Food & Drink"
        }
    ],
    "sg:menulink":"http://www.allmenus.com/tx/arlington/193259-taco-bell/menu/",
    "sg:postcode":"76013",
    "sg:province":"TX",
    "sg:tags":[
        "mexican"
    ],
    "wof:name":"Taco Bell",
    "wof:placetype":"venue"
},
  "geometry": {"coordinates":[-97.11503999999999,32.722997],"type":"Point"}
}