{
  "type": "Feature",
  "properties": {
    "iso:country":"US",
    "sg:address":"406 E Camp Wisdom Rd",
    "sg:city":"Duncanville",
    "sg:classifiers":[
        {
            "category":"Autos & Motor Vehicles",
            "subcategory":"Automobile Sales",
            "type":"Retail Goods"
        }
    ],
    "sg:phone":"+1 469 767 8431",
    "sg:postcode":"75116",
    "sg:province":"TX",
    "sg:tags":[
        "car",
        "dealer"
    ],
    "wof:name":"My My My Auto Sales",
    "wof:placetype":"venue"
},
  "geometry": {"coordinates":[-96.903238,32.661794],"type":"Point"}
}