{
  "type": "Feature",
  "properties": {
    "iso:country":"US",
    "sg:address":"3714 Altamesa Blvd",
    "sg:city":"Fort Worth",
    "sg:classifiers":[
        {
            "category":"Personal",
            "subcategory":"Beauty Salon",
            "type":"Services"
        }
    ],
    "sg:phone":"+1 817 294 9552",
    "sg:postcode":"76133",
    "sg:province":"TX",
    "sg:tags":[
        "shop"
    ],
    "wof:name":"Pro-Cuts",
    "wof:placetype":"venue"
},
  "geometry": {"coordinates":[-97.374545,32.650357],"type":"Point"}
}