{
  "type": "Feature",
  "properties": {
    "iso:country":"US",
    "sg:address":"1953 W Gramercy Pl",
    "sg:city":"San Antonio",
    "sg:classifiers":[
        {
            "category":"Wholesale",
            "subcategory":"Fruits & Vegetables",
            "type":"Manufacturing & Wholesale Goods"
        }
    ],
    "sg:phone":"+1 210 735 1205",
    "sg:postcode":"78201",
    "sg:province":"TX",
    "wof:name":"Pride Produce",
    "wof:placetype":"venue"
},
  "geometry": {"coordinates":[-98.528469,29.461868],"type":"Point"}
}