{
  "type": "Feature",
  "properties": {
    "iso:country":"US",
    "sg:address":"2122 S Olive St",
    "sg:city":"San Antonio",
    "sg:classifiers":[
        {
            "category":"Professional",
            "subcategory":"Management & Consulting",
            "type":"Services"
        }
    ],
    "sg:phone":"+1 210 534 2413",
    "sg:postcode":"78210",
    "sg:province":"TX",
    "sg:tags":[
        "cosmetic"
    ],
    "wof:name":"Elder Diane Marie D",
    "wof:placetype":"venue"
},
  "geometry": {"coordinates":[-98.471452,29.395431],"type":"Point"}
}