{
  "type": "Feature",
  "properties": {
    "iso:country":"US",
    "sg:address":"16350 R R 620",
    "sg:city":"Round Rock",
    "sg:classifiers":[
        {
            "category":"Retail",
            "subcategory":"Auto Repair",
            "type":"Services"
        }
    ],
    "sg:phone":"+1 512 246 1617",
    "sg:postcode":"78681",
    "sg:province":"TX",
    "sg:tags":[
        "repairing",
        "automobile",
        "automotive"
    ],
    "wof:name":"America's Service Station",
    "wof:placetype":"venue"
},
  "geometry": {"coordinates":[-97.72569900000001,30.493671],"type":"Point"}
}