{
  "type": "Feature",
  "properties": {
    "iso:country":"US",
    "sg:address":"4212 Lebanon",
    "sg:city":"Edinburg",
    "sg:classifiers":[
        {
            "category":"Banks & Credit Unions",
            "subcategory":"Investment Brokerage",
            "type":"Services"
        }
    ],
    "sg:phone":"+1 956 383 3187",
    "sg:postcode":"78539",
    "sg:province":"TX",
    "sg:tags":[
        "trust"
    ],
    "wof:name":"Leyendecker & Hunter",
    "wof:placetype":"venue"
},
  "geometry": {"coordinates":[-98.201336,26.282337],"type":"Point"}
}