{
  "type": "Feature",
  "properties": {
    "iso:country":"US",
    "sg:address":"1101 Melbourne Rd",
    "sg:city":"Hurst",
    "sg:classifiers":[
        {
            "category":"Shopping Center",
            "type":"Public Place"
        }
    ],
    "sg:phone":"+1 817 589 9603",
    "sg:postcode":"76053",
    "sg:province":"TX",
    "sg:tags":[
        "mall"
    ],
    "wof:name":"North East Mall Shopping Center",
    "wof:placetype":"venue"
},
  "geometry": {"coordinates":[-97.197304,32.82864],"type":"Point"}
}