{
  "type": "Feature",
  "properties": {
    "iso:country":"US",
    "sg:address":"4401 Speedway",
    "sg:city":"Austin",
    "sg:classifiers":[
        {
            "category":"Professional",
            "type":"Services"
        }
    ],
    "sg:phone":"+1 512 419 0279",
    "sg:postcode":"78751",
    "sg:province":"TX",
    "wof:name":"La Zahia",
    "wof:placetype":"venue"
},
  "geometry": {"coordinates":[-97.72838900000001,30.308633],"type":"Point"}
}