{
  "type": "Feature",
  "properties": {
    "iso:country":"US",
    "sg:address":"3424 Grimes Ranch Rd",
    "sg:city":"Austin",
    "sg:classifiers":[
        {
            "category":"Home & Garden",
            "subcategory":"Home Furnishings",
            "type":"Retail Goods"
        }
    ],
    "sg:phone":"+1 512 266 0030",
    "sg:postcode":"78732",
    "sg:province":"TX",
    "sg:tags":[
        "venetian",
        "blind"
    ],
    "wof:name":"WSA Inc",
    "wof:placetype":"venue"
},
  "geometry": {"coordinates":[-97.895374,30.370768],"type":"Point"}
}