{
  "type": "Feature",
  "properties": {
    "iso:country":"US",
    "sg:address":"1613 Jefferson St",
    "sg:city":"Plainview",
    "sg:classifiers":[
        {
            "category":"Social Services",
            "type":"Services"
        },
        {
            "category":"Place Of Worship",
            "subcategory":"Church",
            "type":"Public Place"
        },
        {
            "category":"Place Of Worship",
            "type":"Public Place"
        }
    ],
    "sg:phone":"+1 806 288 5964",
    "sg:postcode":"79072",
    "sg:province":"TX",
    "sg:tags":[
        "churches-interdenominational",
        "churches-various",
        "denomination"
    ],
    "sg:website":"http://www.salvationarmyusa.org",
    "wof:name":"Salvation Army Quarters",
    "wof:placetype":"venue"
},
  "geometry": {"coordinates":[-101.747039,34.19762],"type":"Point"}
}