{
  "type": "Feature",
  "properties": {
    "iso:country":"US",
    "sg:address":"363 N Briery Rd",
    "sg:city":"Irving",
    "sg:classifiers":[
        {
            "category":"Building & Trades",
            "subcategory":"Plumbing",
            "type":"Services"
        }
    ],
    "sg:phone":"+1 972 313 4500",
    "sg:postcode":"75061",
    "sg:province":"TX",
    "sg:tags":[
        "conditioning",
        "air",
        "system",
        "contractor"
    ],
    "wof:name":"American Air Customs Inc",
    "wof:placetype":"venue"
},
  "geometry": {"coordinates":[-96.989536,32.819077],"type":"Point"}
}