{
  "type": "Feature",
  "properties": {
    "iso:country":"US",
    "sg:address":"826 Starlight Dr",
    "sg:city":"Sherman",
    "sg:classifiers":[
        {
            "category":"Personal",
            "type":"Services"
        }
    ],
    "sg:phone":"+1 903 815 0386",
    "sg:postcode":"75090",
    "sg:province":"TX",
    "sg:tags":[
        "consultant",
        "planning",
        "wedding"
    ],
    "wof:name":"Affairs Of Heart",
    "wof:placetype":"venue"
},
  "geometry": {"coordinates":[-96.604541,33.66238],"type":"Point"}
}