{
  "type": "Feature",
  "properties": {
    "iso:country":"US",
    "sg:address":"1104 E Bell Ave",
    "sg:city":"Pharr",
    "sg:classifiers":[
        {
            "category":"Organizations",
            "subcategory":"Religious Organization",
            "type":"Services"
        }
    ],
    "sg:phone":"+1 956 781 4408",
    "sg:postcode":"78577",
    "sg:province":"TX",
    "wof:name":"Iglesia Apostolica",
    "wof:placetype":"venue"
},
  "geometry": {"coordinates":[-98.169527,26.197425],"type":"Point"}
}