{
  "type": "Feature",
  "properties": {
    "iso:country":"US",
    "sg:address":"414 Paredes Ave",
    "sg:city":"Brownsville",
    "sg:classifiers":[
        {
            "category":"Insurance",
            "subcategory":"Insurance Agent",
            "type":"Services"
        }
    ],
    "sg:phone":"+1 956 546 0081",
    "sg:postcode":"78521",
    "sg:province":"TX",
    "wof:name":"De Leon Insurance",
    "wof:placetype":"venue"
},
  "geometry": {"coordinates":[-97.49010800000001,25.9164],"type":"Point"}
}