{
  "type": "Feature",
  "properties": {
    "iso:country":"US",
    "sg:address":"6501 Trowbridge Dr",
    "sg:city":"El Paso",
    "sg:phone":"+1 915 779 6663",
    "sg:postcode":"79905",
    "sg:province":"TX",
    "sg:tags":[
        "bulk",
        "gas"
    ],
    "wof:name":"Praxair Inc",
    "wof:placetype":"venue"
},
  "geometry": {"coordinates":[-106.401765,31.770324],"type":"Point"}
}