{
  "type": "Feature",
  "properties": {
    "iso:country":"US",
    "sg:address":"2104 Bay Area Blvd",
    "sg:city":"Houston",
    "sg:classifiers":[
        {
            "category":"Food & Beverages",
            "subcategory":"Groceries & Convenience Stores",
            "type":"Retail Goods"
        }
    ],
    "sg:phone":"+1 281 280 8270",
    "sg:postcode":"77058",
    "sg:province":"TX",
    "wof:name":"Stop N Go",
    "wof:placetype":"venue"
},
  "geometry": {"coordinates":[-95.110944,29.56971],"type":"Point"}
}