{
  "type": "Feature",
  "properties": {
    "iso:country":"US",
    "sg:address":"14840 Venture Dr",
    "sg:city":"Farmers Branch",
    "sg:classifiers":[
        {
            "category":"Personal",
            "type":"Services"
        }
    ],
    "sg:phone":"+1 972 897 3123",
    "sg:postcode":"75234",
    "sg:province":"TX",
    "sg:tags":[
        "mover"
    ],
    "sg:website":"WWW.BELLAMOVERS.COM",
    "wof:name":"Bella Movers",
    "wof:placetype":"venue"
},
  "geometry": {"coordinates":[-96.85891599999999,32.951546],"type":"Point"}
}