{
  "type": "Feature",
  "properties": {
    "iso:country":"US",
    "sg:address":"3020 N Piedras St",
    "sg:city":"El Paso",
    "sg:classifiers":[
        {
            "category":"Wholesale",
            "subcategory":"Wine & Distilled Alcoholic Beverages",
            "type":"Manufacturing & Wholesale Goods"
        },
        {
            "category":"Wholesale",
            "subcategory":"Durable Goods & Equipment",
            "type":"Manufacturing & Wholesale Goods"
        }
    ],
    "sg:phone":"+1 915 562 0309",
    "sg:postcode":"79930",
    "sg:province":"TX",
    "sg:tags":[
        "importer"
    ],
    "wof:name":"B & B Import & Distribution Co",
    "wof:placetype":"venue"
},
  "geometry": {"coordinates":[-106.461296,31.803853],"type":"Point"}
}