{
  "type": "Feature",
  "properties": {
    "iso:country":"US",
    "sg:address":"6223 Cotton Field Ln",
    "sg:city":"Katy",
    "sg:classifiers":[
        {
            "category":"Manufacturing",
            "subcategory":"Wood Products",
            "type":"Manufacturing & Wholesale Goods"
        }
    ],
    "sg:phone":"+1 281 550 2789",
    "sg:postcode":"77449",
    "sg:province":"TX",
    "sg:tags":[
        "millwork-wholesale",
        "millwork",
        "manufacturer"
    ],
    "wof:name":"W W Woodworks Of Texas",
    "wof:placetype":"venue"
},
  "geometry": {"coordinates":[-95.702637,29.862074],"type":"Point"}
}