{
  "type": "Feature",
  "properties": {
    "iso:country":"US",
    "sg:address":"7743 Eckhert Rd",
    "sg:city":"San Antonio",
    "sg:classifiers":[
        {
            "category":"Retail",
            "subcategory":"Auto Rental",
            "type":"Services"
        }
    ],
    "sg:phone":"+1 210 684 8688",
    "sg:postcode":"78240",
    "sg:province":"TX",
    "sg:tags":[
        "renting",
        "truck",
        "leasing"
    ],
    "wof:name":"U-Haul Co",
    "wof:placetype":"venue"
},
  "geometry": {"coordinates":[-98.62477199999999,29.510531],"type":"Point"}
}