{
  "type": "Feature",
  "properties": {
    "iso:country":"US",
    "sg:address":"1413 N State Line Ave",
    "sg:city":"Texarkana",
    "sg:classifiers":[
        {
            "category":"Wholesale",
            "subcategory":"Machinery & Supplies",
            "type":"Manufacturing & Wholesale Goods"
        },
        {
            "category":"Wholesale",
            "subcategory":"Hardware",
            "type":"Manufacturing & Wholesale Goods"
        }
    ],
    "sg:phone":"+1 903 792 7719",
    "sg:postcode":"75501",
    "sg:province":"TX",
    "sg:tags":[
        "industrial"
    ],
    "wof:name":"Southern Fastening Systems LLC",
    "wof:placetype":"venue"
},
  "geometry": {"coordinates":[-94.043181,33.434544],"type":"Point"}
}