{
  "type": "Feature",
  "properties": {
    "iso:country":"US",
    "sg:address":"6533 Woodcreek Ln",
    "sg:city":"Fort Worth",
    "sg:classifiers":[
        {
            "category":"Manufacturing",
            "subcategory":"Printing",
            "type":"Manufacturing & Wholesale Goods"
        }
    ],
    "sg:phone":"+1 817 485 0741",
    "sg:postcode":"76180",
    "sg:province":"TX",
    "sg:tags":[
        "commercial"
    ],
    "wof:name":"Jefrey G Designs",
    "wof:placetype":"venue"
},
  "geometry": {"coordinates":[-97.243053,32.833683],"type":"Point"}
}