{
  "type": "Feature",
  "properties": {
    "iso:country":"US",
    "sg:address":"2621 Ridgepoint Dr",
    "sg:city":"Austin",
    "sg:classifiers":[
        {
            "category":"Wholesale",
            "subcategory":"Machinery & Supplies",
            "type":"Manufacturing & Wholesale Goods"
        }
    ],
    "sg:phone":"+1 512 680 2775",
    "sg:postcode":"78754",
    "sg:province":"TX",
    "sg:tags":[
        "industrial"
    ],
    "wof:name":"Metron Technology Corporation",
    "wof:placetype":"venue"
},
  "geometry": {"coordinates":[-97.669608,30.328209],"type":"Point"}
}