{
  "type": "Feature",
  "properties": {
    "iso:country":"US",
    "sg:address":"715 Austin St",
    "sg:city":"Liberty",
    "sg:classifiers":[
        {
            "category":"Education",
            "subcategory":"School",
            "type":"Public Place"
        }
    ],
    "sg:phone":"+1 936 336 8701",
    "sg:postcode":"77575",
    "sg:province":"TX",
    "wof:name":"Liberty County Co-Op",
    "wof:placetype":"venue"
},
  "geometry": {"coordinates":[-94.79969699999999,30.062941],"type":"Point"}
}