{
  "type": "Feature",
  "properties": {
    "iso:country":"US",
    "sg:address":"409 N Main St",
    "sg:city":"Cotulla",
    "sg:classifiers":[
        {
            "category":"Restaurant",
            "type":"Food & Drink"
        }
    ],
    "sg:phone":"+1 830 879 9040",
    "sg:postcode":"78014",
    "sg:province":"TX",
    "sg:tags":[
        "style",
        "family"
    ],
    "wof:name":"La Familia Restaurant",
    "wof:placetype":"venue"
},
  "geometry": {"coordinates":[-99.23556000000001,28.43908],"type":"Point"}
}