{
  "type": "Feature",
  "properties": {
    "iso:country":"US",
    "sg:address":"700 Olympic Plaza Cir",
    "sg:city":"Tyler",
    "sg:classifiers":[
        {
            "category":"Health Services",
            "subcategory":"Doctor",
            "type":"Services"
        }
    ],
    "sg:phone":"+1 903 596 3164",
    "sg:postcode":"75701",
    "sg:province":"TX",
    "sg:tags":[
        "physician",
        "family",
        "medical",
        "practice",
        "surgeons",
        "medicine"
    ],
    "wof:name":"Klouda Michael MD",
    "wof:placetype":"venue"
},
  "geometry": {"coordinates":[-95.29267900000001,32.337841],"type":"Point"}
}