{
  "type": "Feature",
  "properties": {
    "iso:country":"US",
    "sg:address":"601 Colchester Dr",
    "sg:city":"El Paso",
    "sg:classifiers":[
        {
            "category":"Manufacturing",
            "subcategory":"Metals",
            "type":"Manufacturing & Wholesale Goods"
        }
    ],
    "sg:phone":"+1 915 474 1949",
    "sg:postcode":"79912",
    "sg:province":"TX",
    "sg:tags":[
        "ornamental",
        "work"
    ],
    "wof:name":"Ken's Portable Welding",
    "wof:placetype":"venue"
},
  "geometry": {"coordinates":[-106.561213,31.853817],"type":"Point"}
}