{
  "type": "Feature",
  "properties": {
    "iso:country":"US",
    "sg:address":"1212 Hills Creek Dr",
    "sg:city":"Mc Kinney",
    "sg:classifiers":[
        {
            "category":"Professional",
            "type":"Services"
        }
    ],
    "sg:phone":"+1 972 540 1311",
    "sg:postcode":"75070",
    "sg:province":"TX",
    "wof:name":"BCI Bridgepoint Ltd",
    "wof:placetype":"venue"
},
  "geometry": {"coordinates":[-96.67886799999999,33.179047],"type":"Point"}
}