{
  "type": "Feature",
  "properties": {
    "iso:country":"US",
    "sg:address":"2600 Coatbridge Dr",
    "sg:city":"Austin",
    "sg:classifiers":[
        {
            "category":"Professional",
            "subcategory":"Business Services",
            "type":"Services"
        }
    ],
    "sg:phone":"+1 512 773 0383",
    "sg:postcode":"78745",
    "sg:province":"TX",
    "wof:name":"All In Good Time My Dear",
    "wof:placetype":"venue"
},
  "geometry": {"coordinates":[-97.80798799999999,30.216655],"type":"Point"}
}