{
  "type": "Feature",
  "properties": {
    "iso:country":"US",
    "sg:address":"2407 Burleson Ct",
    "sg:city":"Austin",
    "sg:classifiers":[
        {
            "category":"Retail",
            "subcategory":"Repair Shop",
            "type":"Services"
        }
    ],
    "sg:phone":"+1 512 462 2824",
    "sg:postcode":"78741",
    "sg:province":"TX",
    "wof:name":"Warp Visions",
    "wof:placetype":"venue"
},
  "geometry": {"coordinates":[-97.735366,30.228548],"type":"Point"}
}