{
  "type": "Feature",
  "properties": {
    "iso:country":"US",
    "sg:address":"1221 S Crockett St",
    "sg:city":"Sherman",
    "sg:classifiers":[
        {
            "category":"Retail",
            "subcategory":"Repair Shop",
            "type":"Services"
        }
    ],
    "sg:phone":"+1 903 892 3071",
    "sg:postcode":"75090",
    "sg:province":"TX",
    "sg:tags":[
        "clocks",
        "parts"
    ],
    "wof:name":"It's About Time",
    "wof:placetype":"venue"
},
  "geometry": {"coordinates":[-96.60684500000001,33.623316],"type":"Point"}
}