{
  "type": "Feature",
  "properties": {
    "iso:country":"US",
    "sg:address":"4510 Horizon Dr",
    "sg:city":"Garland",
    "sg:classifiers":[
        {
            "category":"Shopping",
            "subcategory":"Department Store",
            "type":"Retail Goods"
        },
        {
            "category":"Building & Trades",
            "subcategory":"Cleaning & Sanitation",
            "type":"Services"
        }
    ],
    "sg:phone":"+1 972 303 0608",
    "sg:postcode":"75043",
    "sg:province":"TX",
    "sg:tags":[
        "equipment",
        "cleaner",
        "supply",
        "house"
    ],
    "wof:name":"Lucky Enterprise",
    "wof:placetype":"venue"
},
  "geometry": {"coordinates":[-96.58834400000001,32.867695],"type":"Point"}
}