{
  "type": "Feature",
  "properties": {
    "iso:country":"US",
    "sg:address":"4508 Allendale Rd",
    "sg:city":"Wichita Falls",
    "sg:classifiers":[
        {
            "category":"Social Services",
            "subcategory":"Child Care",
            "type":"Services"
        }
    ],
    "sg:phone":"+1 940 692 8092",
    "sg:postcode":"76310",
    "sg:province":"TX",
    "sg:tags":[
        "day"
    ],
    "wof:name":"Sunshine Childrens Center",
    "wof:placetype":"venue"
},
  "geometry": {"coordinates":[-98.595972,33.865982],"type":"Point"}
}