{
  "type": "Feature",
  "properties": {
    "iso:country":"US",
    "sg:address":"4164 Meyerwood Dr",
    "sg:city":"Houston",
    "sg:classifiers":[
        {
            "category":"Professional",
            "subcategory":"Management & Consulting",
            "type":"Services"
        }
    ],
    "sg:phone":"+1 713 524 5980",
    "sg:postcode":"77025",
    "sg:province":"TX",
    "sg:tags":[
        "consultant",
        "business"
    ],
    "wof:name":"Loes & Assoc",
    "wof:placetype":"venue"
},
  "geometry": {"coordinates":[-95.44444300000001,29.680207],"type":"Point"}
}