{
  "type": "Feature",
  "properties": {
    "iso:country":"US",
    "sg:address":"16002 Wimberly Ln",
    "sg:city":"Rosharon",
    "sg:classifiers":[
        {
            "category":"Manufacturing",
            "subcategory":"Soap",
            "type":"Manufacturing & Wholesale Goods"
        }
    ],
    "sg:phone":"+1 281 595 9966",
    "sg:postcode":"77583",
    "sg:province":"TX",
    "sg:tags":[
        "detergent",
        "mfg"
    ],
    "wof:name":"Soapsmith The",
    "wof:placetype":"venue"
},
  "geometry": {"coordinates":[-95.40179000000001,29.355311],"type":"Point"}
}