{
  "type": "Feature",
  "properties": {
    "iso:country":"US",
    "sg:address":"2003 S Lamar Blvd",
    "sg:city":"Austin",
    "sg:classifiers":[
        {
            "category":"Health Services",
            "subcategory":"Doctor",
            "type":"Services"
        }
    ],
    "sg:phone":"+1 512 448 1927",
    "sg:postcode":"78704",
    "sg:province":"TX",
    "wof:name":"Jones Alison R MD",
    "wof:placetype":"venue"
},
  "geometry": {"coordinates":[-97.768942,30.248602],"type":"Point"}
}