{
  "type": "Feature",
  "properties": {
    "iso:country":"US",
    "sg:address":"11239 Stroud Dr",
    "sg:city":"Houston",
    "sg:classifiers":[
        {
            "category":"Building & Trades",
            "subcategory":"Construction",
            "type":"Services"
        }
    ],
    "sg:phone":"+1 281 561 9456",
    "sg:postcode":"77072",
    "sg:province":"TX",
    "sg:tags":[
        "contractor"
    ],
    "wof:name":"F & S Fence & Iron Works Co",
    "wof:placetype":"venue"
},
  "geometry": {"coordinates":[-95.57612899999999,29.699739],"type":"Point"}
}