{
  "type": "Feature",
  "properties": {
    "iso:country":"US",
    "sg:address":"5790 Frost St",
    "sg:city":"Beaumont",
    "sg:classifiers":[
        {
            "category":"Building & Trades",
            "subcategory":"Construction",
            "type":"Services"
        }
    ],
    "sg:phone":"+1 409 898 0650",
    "sg:postcode":"77706",
    "sg:province":"TX",
    "sg:tags":[
        "wallcoverings-installation",
        "wallpaper",
        "painting",
        "contractor"
    ],
    "wof:name":"Collier Richard",
    "wof:placetype":"venue"
},
  "geometry": {"coordinates":[-94.159854,30.088399],"type":"Point"}
}