{
  "type": "Feature",
  "properties": {
    "iso:country":"US",
    "sg:address":"1930 Fry Rd",
    "sg:city":"Houston",
    "sg:classifiers":[
        {
            "category":"Restaurant",
            "type":"Food & Drink"
        }
    ],
    "sg:menulink":"http://www.allmenus.com/tx/houston/70448-pizza-hut/menu/",
    "sg:phone":"+1 281 578 7461",
    "sg:postcode":"77084",
    "sg:province":"TX",
    "sg:tags":[
        "american",
        "pizza"
    ],
    "wof:name":"Pizza Hut",
    "wof:placetype":"venue"
},
  "geometry": {"coordinates":[-95.718608,29.794679],"type":"Point"}
}