{
  "type": "Feature",
  "properties": {
    "iso:country":"US",
    "sg:address":"9550 Forest Ln Ste 700",
    "sg:city":"Dallas",
    "sg:classifiers":[
        {
            "category":"Health Services",
            "subcategory":"Doctor",
            "type":"Services"
        }
    ],
    "sg:phone":"+1 214 348 5505",
    "sg:postcode":"75243",
    "sg:province":"TX",
    "sg:tags":[
        "surgeon",
        "oral"
    ],
    "wof:name":"Jones Mark B DDS",
    "wof:placetype":"venue"
},
  "geometry": {"coordinates":[-96.7286,32.9091],"type":"Point"}
}