{
  "type": "Feature",
  "properties": {
    "iso:country":"US",
    "sg:address":"922 14th St N",
    "sg:city":"Texas City",
    "sg:classifiers":[
        {
            "category":"Social Services",
            "type":"Services"
        }
    ],
    "sg:phone":"+1 409 948 4211",
    "sg:postcode":"77590",
    "sg:province":"TX",
    "sg:tags":[
        "organization",
        "welfare"
    ],
    "wof:name":"United Way",
    "wof:placetype":"venue"
},
  "geometry": {"coordinates":[-94.914731,29.394328],"type":"Point"}
}