{
  "type": "Feature",
  "properties": {
    "iso:country":"US",
    "sg:address":"401 E Texas Ave",
    "sg:city":"Midland",
    "sg:classifiers":[
        {
            "category":"Travel",
            "subcategory":"Hotels & Motels",
            "type":"Entertainment"
        }
    ],
    "sg:phone":"+1 432 682 9793",
    "sg:postcode":"79701",
    "sg:province":"TX",
    "wof:name":"Travel Inn Motel",
    "wof:placetype":"venue"
},
  "geometry": {"coordinates":[-102.07070899999999,31.9986],"type":"Point"}
}