{
  "type": "Feature",
  "properties": {
    "iso:country":"US",
    "sg:address":"212 E Chambers St",
    "sg:city":"Cleburne",
    "sg:classifiers":[
        {
            "category":"Education",
            "subcategory":"Special Training",
            "type":"Public Place"
        }
    ],
    "sg:phone":"+1 817 641 3187",
    "sg:postcode":"76031",
    "sg:province":"TX",
    "wof:name":"Kieschinck Learning Center",
    "wof:placetype":"venue"
},
  "geometry": {"coordinates":[-97.384046,32.347242],"type":"Point"}
}