{
  "type": "Feature",
  "properties": {
    "iso:country":"US",
    "sg:address":"610 Strickland Dr",
    "sg:city":"Orange",
    "sg:classifiers":[
        {
            "category":"Health Services",
            "subcategory":"Doctor",
            "type":"Services"
        }
    ],
    "sg:phone":"+1 409 883 5300",
    "sg:postcode":"77630",
    "sg:province":"TX",
    "sg:tags":[
        "medical"
    ],
    "wof:name":"Spine & Sports Medical Center",
    "wof:placetype":"venue"
},
  "geometry": {"coordinates":[-93.765548,30.097291],"type":"Point"}
}