{
  "type": "Feature",
  "properties": {
    "iso:country":"US",
    "sg:address":"8600 N Macarthur Blvd",
    "sg:city":"Irving",
    "sg:classifiers":[
        {
            "category":"Banks & Credit Unions",
            "subcategory":"Bank",
            "type":"Services"
        }
    ],
    "sg:phone":"+1 214 574 7575",
    "sg:postcode":"75063",
    "sg:province":"TX",
    "sg:tags":[
        "loan",
        "real estate"
    ],
    "wof:name":"Valley Ranch Mortgage",
    "wof:placetype":"venue"
},
  "geometry": {"coordinates":[-96.9552,32.92373],"type":"Point"}
}