{
  "type": "Feature",
  "properties": {
    "iso:country":"US",
    "sg:address":"3620 S New Braunfels Ave",
    "sg:city":"San Antonio",
    "sg:classifiers":[
        {
            "category":"Shopping",
            "subcategory":"Optical Goods",
            "type":"Retail Goods"
        }
    ],
    "sg:phone":"+1 210 534 5887",
    "sg:postcode":"78223",
    "sg:province":"TX",
    "wof:name":"Trinity Vision Ctr",
    "wof:placetype":"venue"
},
  "geometry": {"coordinates":[-98.461133,29.381762],"type":"Point"}
}