{
  "type": "Feature",
  "properties": {
    "iso:country":"US",
    "sg:address":"13716 Neutron Rd",
    "sg:city":"Dallas",
    "sg:classifiers":[
        {
            "category":"Shopping",
            "subcategory":"Antiques",
            "type":"Retail Goods"
        }
    ],
    "sg:phone":"+1 972 387 3723",
    "sg:postcode":"75244",
    "sg:province":"TX",
    "wof:name":"Dyna Strip of North Dallas Inc",
    "wof:placetype":"venue"
},
  "geometry": {"coordinates":[-96.834801,32.936298],"type":"Point"}
}