{
  "type": "Feature",
  "properties": {
    "iso:country":"US",
    "sg:address":"5620 Leven Ln",
    "sg:city":"Mckinney",
    "sg:classifiers":[
        {
            "category":"Structure",
            "subcategory":"Office Building",
            "type":"Public Place"
        }
    ],
    "sg:phone":"+1 469 855 6634",
    "sg:postcode":"75070",
    "sg:province":"TX",
    "sg:tags":[
        "park"
    ],
    "wof:name":"Judy Chan Rental Properties",
    "wof:placetype":"venue"
},
  "geometry": {"coordinates":[-96.688013,33.151738],"type":"Point"}
}