{
  "type": "Feature",
  "properties": {
    "iso:country":"US",
    "sg:address":"2029 N Cliffe",
    "sg:city":"Richardson",
    "sg:classifiers":[
        {
            "category":"Wholesale",
            "subcategory":"Vending Machines",
            "type":"Manufacturing & Wholesale Goods"
        }
    ],
    "sg:phone":"+1 972 530 9682",
    "sg:postcode":"75082",
    "sg:province":"TX",
    "sg:tags":[
        "operator"
    ],
    "wof:name":"Preferred Vending",
    "wof:placetype":"venue"
},
  "geometry": {"coordinates":[-96.683891,32.97788],"type":"Point"}
}