{
  "type": "Feature",
  "properties": {
    "iso:country":"US",
    "sg:address":"7267 Alameda Ave",
    "sg:city":"El Paso",
    "sg:classifiers":[
        {
            "category":"Autos & Motor Vehicles",
            "subcategory":"Automobile Sales",
            "type":"Retail Goods"
        }
    ],
    "sg:phone":"+1 915 772 3900",
    "sg:postcode":"79915",
    "sg:province":"TX",
    "sg:tags":[
        "car",
        "dealer"
    ],
    "wof:name":"EGS Auto Sales",
    "wof:placetype":"venue"
},
  "geometry": {"coordinates":[-106.385908,31.748617],"type":"Point"}
}