{
  "type": "Feature",
  "properties": {
    "iso:country":"US",
    "sg:address":"7920 San Felipe Blvd",
    "sg:city":"Austin",
    "sg:phone":"+1 866 403 1519",
    "sg:postcode":"78729",
    "sg:province":"TX",
    "sg:website":"http://local.ingenio.com/Listings/Details.aspx?NUM=a%3a10243152%3a13%3a4859924%3a14%3a0%3a7",
    "wof:name":"Martha's Vineyard",
    "wof:placetype":"venue"
},
  "geometry": {"coordinates":[-97.76871300000001,30.438211],"type":"Point"}
}