{
  "type": "Feature",
  "properties": {
    "iso:country":"US",
    "sg:address":"3712 Aspenwood Dr",
    "sg:city":"Bedford",
    "sg:classifiers":[
        {
            "category":"Real Estate",
            "subcategory":"Real Estate Services",
            "type":"Services"
        },
        {
            "category":"Real Estate",
            "subcategory":"Real Estate Agent",
            "type":"Services"
        }
    ],
    "sg:phone":"+1 817 832 6239",
    "sg:postcode":"76021",
    "sg:province":"TX",
    "sg:tags":[
        "buyer",
        "broker"
    ],
    "wof:name":"Rjg Inc",
    "wof:placetype":"venue"
},
  "geometry": {"coordinates":[-97.10853899999999,32.846256],"type":"Point"}
}