{
  "type": "Feature",
  "properties": {
    "iso:country":"US",
    "sg:address":"4755 Stoney Point Ct",
    "sg:city":"Sugar Land",
    "sg:classifiers":[
        {
            "category":"Shopping",
            "subcategory":"Gifts & Souvenirs",
            "type":"Retail Goods"
        }
    ],
    "sg:phone":"+1 281 565 1142",
    "sg:postcode":"77479",
    "sg:province":"TX",
    "wof:name":"Kristens Giftshop",
    "wof:placetype":"venue"
},
  "geometry": {"coordinates":[-95.68552699999999,29.600709],"type":"Point"}
}