{
  "type": "Feature",
  "properties": {
    "iso:country":"US",
    "sg:address":"1213 Lee St",
    "sg:city":"Goldthwaite",
    "sg:classifiers":[
        {
            "category":"Banks & Credit Unions",
            "subcategory":"Financial Services",
            "type":"Services"
        }
    ],
    "sg:phone":"+1 325 648 2459",
    "sg:postcode":"76844",
    "sg:province":"TX",
    "sg:tags":[
        "trust",
        "management"
    ],
    "wof:name":"Marks Doodles",
    "wof:placetype":"venue"
},
  "geometry": {"coordinates":[-98.57418800000001,31.451236],"type":"Point"}
}