{
  "type": "Feature",
  "properties": {
    "iso:country":"US",
    "sg:address":"330 S Blue Mound Rd",
    "sg:city":"Fort Worth",
    "sg:classifiers":[
        {
            "category":"Banks & Credit Unions",
            "subcategory":"Bank",
            "type":"Services"
        }
    ],
    "sg:phone":"+1 817 222 2288",
    "sg:postcode":"76131",
    "sg:province":"TX",
    "wof:name":"Member Preferred Federal CU",
    "wof:placetype":"venue"
},
  "geometry": {"coordinates":[-97.34312799999999,32.858545],"type":"Point"}
}