{
  "type": "Feature",
  "properties": {
    "iso:country":"US",
    "sg:address":"7038 Eckhert Rd",
    "sg:city":"San Antonio",
    "sg:classifiers":[
        {
            "category":"Health Services",
            "subcategory":"Doctor",
            "type":"Services"
        }
    ],
    "sg:phone":"+1 210 256 1971",
    "sg:postcode":"78238",
    "sg:province":"TX",
    "sg:tags":[
        "clinic"
    ],
    "wof:name":"First Choice Medical",
    "wof:placetype":"venue"
},
  "geometry": {"coordinates":[-98.634443,29.503294],"type":"Point"}
}