{
  "type": "Feature",
  "properties": {
    "iso:country":"US",
    "sg:address":"900 S 6th St",
    "sg:city":"Kingsville",
    "sg:classifiers":[
        {
            "category":"Wholesale",
            "subcategory":"Auto Parts",
            "type":"Manufacturing & Wholesale Goods"
        }
    ],
    "sg:phone":"+1 361 592 7847",
    "sg:postcode":"78363",
    "sg:province":"TX",
    "sg:tags":[
        "tire"
    ],
    "wof:name":"Vic's Tires",
    "wof:placetype":"venue"
},
  "geometry": {"coordinates":[-97.86753299999999,27.508637],"type":"Point"}
}