{
  "type": "Feature",
  "properties": {
    "iso:country":"US",
    "sg:address":"5824 Doniphan Dr",
    "sg:city":"El Paso",
    "sg:classifiers":[
        {
            "category":"Retail",
            "subcategory":"Event Space",
            "type":"Services"
        },
        {
            "category":"Communications",
            "type":"Services"
        }
    ],
    "sg:phone":"+1 915 584 8806",
    "sg:postcode":"79932",
    "sg:province":"TX",
    "sg:tags":[
        "recording",
        "rehearsal",
        "venue",
        "studio"
    ],
    "sg:website":"www.pennylanestudiosep.com",
    "wof:name":"Penny Lane Studios",
    "wof:placetype":"venue"
},
  "geometry": {"coordinates":[-106.589996,31.8687],"type":"Point"}
}