{
  "type": "Feature",
  "properties": {
    "iso:country":"US",
    "sg:address":"5205 Spruce St",
    "sg:city":"Bellaire",
    "sg:classifiers":[
        {
            "category":"Professional",
            "subcategory":"Art Services",
            "type":"Services"
        }
    ],
    "sg:phone":"+1 713 961 1323",
    "sg:postcode":"77401",
    "sg:province":"TX",
    "sg:tags":[
        "commercial",
        "design"
    ],
    "wof:name":"Strickland Mchael Design Group",
    "wof:placetype":"venue"
},
  "geometry": {"coordinates":[-95.472447,29.707805],"type":"Point"}
}