{
  "type": "Feature",
  "properties": {
    "iso:country":"US",
    "sg:address":"2601 Preston Rd",
    "sg:city":"Frisco",
    "sg:classifiers":[
        {
            "category":"Shopping",
            "subcategory":"Hobbies, Toys, & Games",
            "type":"Retail Goods"
        },
        {
            "category":"Shopping",
            "type":"Retail Goods"
        }
    ],
    "sg:phone":"+1 469 335 2899",
    "sg:postcode":"75034",
    "sg:province":"TX",
    "sg:tags":[
        "collectible",
        "sport",
        "card",
        "memorabilia"
    ],
    "wof:name":"Field Of Dreams",
    "wof:placetype":"venue"
},
  "geometry": {"coordinates":[-96.805817,33.100979],"type":"Point"}
}