{
  "type": "Feature",
  "properties": {
    "iso:country":"US",
    "sg:address":"2040 W Poplar St",
    "sg:city":"San Antonio",
    "sg:classifiers":[
        {
            "category":"Wholesale",
            "subcategory":"Drugs",
            "type":"Manufacturing & Wholesale Goods"
        }
    ],
    "sg:phone":"+1 210 732 7377",
    "sg:postcode":"78207",
    "sg:province":"TX",
    "wof:name":"Raf Mar Distributing",
    "wof:placetype":"venue"
},
  "geometry": {"coordinates":[-98.52463400000001,29.440559],"type":"Point"}
}