{
  "type": "Feature",
  "properties": {
    "iso:country":"US",
    "sg:address":"180 Davis Blvd",
    "sg:city":"Southlake",
    "sg:classifiers":[
        {
            "category":"Restaurant",
            "type":"Food & Drink"
        }
    ],
    "sg:menulink":"http://www.allmenus.com/tx/northeast-tarrant/204454-sonic/menu/",
    "sg:phone":"+1 817 482 1906",
    "sg:postcode":"76092",
    "sg:province":"TX",
    "sg:tags":[
        "burger",
        "american"
    ],
    "wof:name":"Sonic",
    "wof:placetype":"venue"
},
  "geometry": {"coordinates":[-97.18579200000001,32.935993],"type":"Point"}
}