{
  "type": "Feature",
  "properties": {
    "iso:country":"US",
    "sg:address":"4201 Main St",
    "sg:city":"Houston",
    "sg:classifiers":[
        {
            "category":"Personal",
            "subcategory":"Beauty Salon",
            "type":"Services"
        }
    ],
    "sg:phone":"+1 713 527 2343",
    "sg:postcode":"77002",
    "sg:province":"TX",
    "sg:tags":[
        "shop"
    ],
    "wof:name":"Premier Salon 22864",
    "wof:placetype":"venue"
},
  "geometry": {"coordinates":[-95.382976,29.734126],"type":"Point"}
}