{
  "type": "Feature",
  "properties": {
    "iso:country":"US",
    "sg:address":"112 E Park St",
    "sg:city":"Pharr",
    "sg:classifiers":[
        {
            "category":"Banks & Credit Unions",
            "subcategory":"Bank",
            "type":"Services"
        }
    ],
    "sg:phone":"+1 956 781 1131",
    "sg:postcode":"78577",
    "sg:province":"TX",
    "sg:tags":[
        "personal",
        "loan",
        "mortgage"
    ],
    "wof:name":"County Loan Company",
    "wof:placetype":"venue"
},
  "geometry": {"coordinates":[-98.18268399999999,26.193903],"type":"Point"}
}