{
  "type": "Feature",
  "properties": {
    "iso:country":"US",
    "sg:address":"1524 Babe Hiskey Ln",
    "sg:city":"El Paso",
    "sg:classifiers":[
        {
            "category":"Banks & Credit Unions",
            "subcategory":"Investment Brokerage",
            "type":"Services"
        }
    ],
    "sg:phone":"+1 915 590 8884",
    "sg:postcode":"79936",
    "sg:province":"TX",
    "sg:tags":[
        "advisory",
        "financial"
    ],
    "wof:name":"Vertex Financial Corp",
    "wof:placetype":"venue"
},
  "geometry": {"coordinates":[-106.310509,31.751952],"type":"Point"}
}