{
  "type": "Feature",
  "properties": {
    "iso:country":"US",
    "sg:address":"7526 Santa Fe Dr",
    "sg:city":"Houston",
    "sg:classifiers":[
        {
            "category":"Professional",
            "subcategory":"Business Services",
            "type":"Services"
        }
    ],
    "sg:phone":"+1 713 649 4650",
    "sg:postcode":"77061",
    "sg:province":"TX",
    "wof:name":"A Sherwood Morning",
    "wof:placetype":"venue"
},
  "geometry": {"coordinates":[-95.29503800000001,29.665364],"type":"Point"}
}