{
  "type": "Feature",
  "properties": {
    "iso:country":"US",
    "sg:address":"5641 Truitt St",
    "sg:city":"Lewisville",
    "sg:classifiers":[
        {
            "category":"Home & Garden",
            "subcategory":"Building Materials",
            "type":"Retail Goods"
        },
        {
            "category":"Building & Trades",
            "subcategory":"Construction",
            "type":"Services"
        }
    ],
    "sg:phone":"+1 972 625 9874",
    "sg:postcode":"75056",
    "sg:province":"TX",
    "sg:tags":[
        "fence",
        "contractor"
    ],
    "wof:name":"Alpha Fence Company",
    "wof:placetype":"venue"
},
  "geometry": {"coordinates":[-96.865646,33.10404],"type":"Point"}
}