{
  "type": "Feature",
  "properties": {
    "iso:country":"US",
    "sg:address":"5198 Ave H",
    "sg:city":"Rosenberg",
    "sg:classifiers":[
        {
            "category":"Food & Beverages",
            "subcategory":"Groceries & Convenience Stores",
            "type":"Retail Goods"
        }
    ],
    "sg:phone":"+1 713 789 0310",
    "sg:postcode":"77471",
    "sg:province":"TX",
    "wof:name":"Landmark",
    "wof:placetype":"venue"
},
  "geometry": {"coordinates":[-95.77660899999999,29.570698],"type":"Point"}
}