{
  "type": "Feature",
  "properties": {
    "iso:country":"US",
    "sg:address":"7003 Shepherds Glen",
    "sg:city":"Colleyville",
    "sg:classifiers":[
        {
            "category":"Professional",
            "subcategory":"Business Services",
            "type":"Services"
        }
    ],
    "sg:phone":"+1 817 442 5081",
    "sg:postcode":"76034",
    "sg:province":"TX",
    "wof:name":"Apex Solutions",
    "wof:placetype":"venue"
},
  "geometry": {"coordinates":[-97.14912099999999,32.909187],"type":"Point"}
}