{
  "type": "Feature",
  "properties": {
    "iso:country":"US",
    "sg:address":"1208 Cloudy Sky Ln",
    "sg:city":"Lewisville",
    "sg:classifiers":[
        {
            "category":"Professional",
            "type":"Services"
        }
    ],
    "sg:phone":"+1 972 315 0379",
    "sg:postcode":"75067",
    "sg:province":"TX",
    "wof:name":"Sarah & Susana Corp",
    "wof:placetype":"venue"
},
  "geometry": {"coordinates":[-97.02333900000001,33.018069],"type":"Point"}
}