{
  "type": "Feature",
  "properties": {
    "iso:country":"US",
    "sg:address":"228 NE Wilshire Blvd",
    "sg:city":"Burleson",
    "sg:classifiers":[
        {
            "category":"Insurance",
            "subcategory":"Insurance Agent",
            "type":"Services"
        }
    ],
    "sg:phone":"+1 817 295 7171",
    "sg:postcode":"76028",
    "sg:province":"TX",
    "wof:name":"Ted Whitley Insurance",
    "wof:placetype":"venue"
},
  "geometry": {"coordinates":[-97.324809,32.547177],"type":"Point"}
}