{
  "type": "Feature",
  "properties": {
    "iso:country":"US",
    "sg:address":"100 Hwy 332 W",
    "sg:city":"Lake Jackson",
    "sg:classifiers":[
        {
            "category":"Shopping",
            "subcategory":"Clothing, Apparel, & Fashions",
            "type":"Retail Goods"
        }
    ],
    "sg:phone":"+1 979 297 6120",
    "sg:postcode":"77566",
    "sg:province":"TX",
    "sg:tags":[
        "infant",
        "wear"
    ],
    "wof:name":"Children's Place",
    "wof:placetype":"venue"
},
  "geometry": {"coordinates":[-95.459092,29.04798],"type":"Point"}
}