{
  "type": "Feature",
  "properties": {
    "iso:country":"US",
    "sg:address":"2115 Teakwood Ln",
    "sg:city":"Plano",
    "sg:classifiers":[
        {
            "category":"Professional",
            "subcategory":"Engineering",
            "type":"Services"
        }
    ],
    "sg:phone":"+1 972 964 2161",
    "sg:postcode":"75075",
    "sg:province":"TX",
    "sg:tags":[
        "concrete",
        "structural",
        "contractor"
    ],
    "wof:name":"Smith Larry Engineering Inc",
    "wof:placetype":"venue"
},
  "geometry": {"coordinates":[-96.733542,33.037737],"type":"Point"}
}