{
  "type": "Feature",
  "properties": {
    "iso:country":"US",
    "sg:address":"5850 Town and Country Blvd",
    "sg:city":"Frisco",
    "sg:classifiers":[
        {
            "category":"Building & Trades",
            "subcategory":"Construction",
            "type":"Services"
        }
    ],
    "sg:phone":"+1 469 287 4500",
    "sg:postcode":"75034",
    "sg:province":"TX",
    "sg:tags":[
        "interior",
        "design"
    ],
    "wof:name":"Marketexpo",
    "wof:placetype":"venue"
},
  "geometry": {"coordinates":[-96.836046,33.023713],"type":"Point"}
}