{
  "type": "Feature",
  "properties": {
    "iso:country":"US",
    "sg:address":"177 Valruth Cir",
    "sg:city":"Kyle",
    "sg:classifiers":[
        {
            "category":"Professional",
            "subcategory":"Accounting & Tax Preparation",
            "type":"Services"
        }
    ],
    "sg:phone":"+1 512 268 5100",
    "sg:postcode":"78640",
    "sg:province":"TX",
    "sg:tags":[
        "bookkeeping",
        "billing"
    ],
    "wof:name":"Star Billing Services",
    "wof:placetype":"venue"
},
  "geometry": {"coordinates":[-97.84652800000001,29.960959],"type":"Point"}
}