{
  "type": "Feature",
  "properties": {
    "iso:country":"US",
    "sg:address":"204 S 6th Ave",
    "sg:city":"Mansfield",
    "sg:classifiers":[
        {
            "category":"Manufacturing",
            "subcategory":"Chemicals & Compounds",
            "type":"Manufacturing & Wholesale Goods"
        }
    ],
    "sg:phone":"+1 817 473 9964",
    "sg:postcode":"76063",
    "sg:province":"TX",
    "sg:tags":[
        "mfg"
    ],
    "wof:name":"Chemguard Inc",
    "wof:placetype":"venue"
},
  "geometry": {"coordinates":[-97.152331,32.550337],"type":"Point"}
}