{
  "type": "Feature",
  "properties": {
    "iso:country":"US",
    "sg:address":"2515 Oyster Loop Dr",
    "sg:city":"Sugar Land",
    "sg:classifiers":[
        {
            "category":"Banks & Credit Unions",
            "subcategory":"Financial Services",
            "type":"Services"
        }
    ],
    "sg:phone":"+1 281 491 3788",
    "sg:postcode":"77478",
    "sg:province":"TX",
    "sg:tags":[
        "real estate",
        "trust",
        "investor",
        "investment"
    ],
    "wof:name":"A & E Homebuyers  Inc",
    "wof:placetype":"venue"
},
  "geometry": {"coordinates":[-95.58915,29.588579],"type":"Point"}
}