{
  "type": "Feature",
  "properties": {
    "iso:country":"US",
    "sg:address":"251 Brunson Ln",
    "sg:city":"Wimberley",
    "sg:classifiers":[
        {
            "category":"Professional",
            "subcategory":"Lawyer & Legal Services",
            "type":"Services"
        }
    ],
    "sg:phone":"+1 512 847 8908",
    "sg:postcode":"78676",
    "sg:province":"TX",
    "wof:name":"Ideas At Large Inc",
    "wof:placetype":"venue"
},
  "geometry": {"coordinates":[-98.078338,30.062019],"type":"Point"}
}