{
  "type": "Feature",
  "properties": {
    "iso:country":"US",
    "sg:address":"1525 Turtle Creek Blvd",
    "sg:city":"Dallas",
    "sg:classifiers":[
        {
            "category":"Shopping",
            "type":"Retail Goods"
        }
    ],
    "sg:phone":"+1 214 748 1224",
    "sg:postcode":"75207",
    "sg:province":"TX",
    "sg:tags":[
        "picture",
        "frame",
        "merchandise"
    ],
    "wof:name":"Gallery Central",
    "wof:placetype":"venue"
},
  "geometry": {"coordinates":[-96.820944,32.797017],"type":"Point"}
}