{
  "type": "Feature",
  "properties": {
    "iso:country":"US",
    "sg:address":"7070 Rd C",
    "sg:city":"Corpus Christi",
    "sg:classifiers":[
        {
            "category":"Retail",
            "subcategory":"Animal Services",
            "type":"Services"
        }
    ],
    "sg:phone":"+1 361 991 0728",
    "sg:postcode":"78414",
    "sg:province":"TX",
    "sg:tags":[
        "training",
        "dog"
    ],
    "sg:website":"www.master-trainer.com",
    "wof:name":"Master Trainer Co",
    "wof:placetype":"venue"
},
  "geometry": {"coordinates":[-97.37142799999999,27.650899],"type":"Point"}
}