{
  "type": "Feature",
  "properties": {
    "iso:country":"US",
    "sg:address":"14005 N Hwy 183 Ste 1500",
    "sg:city":"Austin",
    "sg:classifiers":[
        {
            "category":"Retail",
            "subcategory":"Portrait Studio",
            "type":"Services"
        }
    ],
    "sg:postcode":"78717",
    "sg:province":"TX",
    "sg:tags":[
        "photography",
        "store"
    ],
    "sg:website":"portraitinnovations.com",
    "wof:name":"Portrait Innovations",
    "wof:placetype":"venue"
},
  "geometry": {"coordinates":[-97.79804,30.476149],"type":"Point"}
}