{
  "type": "Feature",
  "properties": {
    "iso:country":"US",
    "sg:address":"32823 Fm 2978 Rd",
    "sg:city":"Magnolia",
    "sg:classifiers":[
        {
            "category":"Personal",
            "subcategory":"Beauty Salon",
            "type":"Services"
        }
    ],
    "sg:phone":"+1 281 259 2411",
    "sg:postcode":"77354",
    "sg:province":"TX",
    "sg:tags":[
        "hair",
        "stylist"
    ],
    "wof:name":"Leslie's Hair Creations",
    "wof:placetype":"venue"
},
  "geometry": {"coordinates":[-95.56806400000001,30.216172],"type":"Point"}
}