{
  "type": "Feature",
  "properties": {
    "iso:country":"US",
    "sg:address":"4124 N 23rd St",
    "sg:city":"Mcallen",
    "sg:classifiers":[
        {
            "category":"Professional",
            "type":"Services"
        }
    ],
    "sg:phone":"+1 956 661 0599",
    "sg:postcode":"78504",
    "sg:province":"TX",
    "sg:tags":[
        "establishment"
    ],
    "wof:name":"M C Co LLC",
    "wof:placetype":"venue"
},
  "geometry": {"coordinates":[-98.238838,26.243374],"type":"Point"}
}