{
  "type": "Feature",
  "properties": {
    "iso:country":"US",
    "sg:address":"1100 N Velasco Blvd",
    "sg:city":"Freeport",
    "sg:classifiers":[
        {
            "category":"Real Estate",
            "subcategory":"Real Estate Agent",
            "type":"Services"
        }
    ],
    "sg:phone":"+1 979 265 2000",
    "sg:postcode":"77541",
    "sg:province":"TX",
    "sg:website":"www.coldwellbankerunited.com",
    "wof:name":"United Realtors",
    "wof:placetype":"venue"
},
  "geometry": {"coordinates":[-95.352628,28.964181],"type":"Point"}
}