{
  "type": "Feature",
  "properties": {
    "iso:country":"US",
    "sg:address":"1508 Harvey Rd",
    "sg:city":"College Station",
    "sg:classifiers":[
        {
            "category":"Utilities",
            "subcategory":"Telephone",
            "type":"Services"
        }
    ],
    "sg:phone":"+1 979 694 0586",
    "sg:postcode":"77840",
    "sg:province":"TX",
    "sg:tags":[
        "company"
    ],
    "wof:name":"A T & T Wireless Svc",
    "wof:placetype":"venue"
},
  "geometry": {"coordinates":[-96.30416200000001,30.627841],"type":"Point"}
}