{
  "type": "Feature",
  "properties": {
    "iso:country":"US",
    "sg:address":"2206 N Gordon St",
    "sg:city":"Alvin",
    "sg:classifiers":[
        {
            "category":"Professional",
            "subcategory":"Testing Lab",
            "type":"Services"
        }
    ],
    "sg:phone":"+1 281 331 8362",
    "sg:postcode":"77511",
    "sg:province":"TX",
    "sg:tags":[
        "metallurgist"
    ],
    "wof:name":"R D Evans Inc",
    "wof:placetype":"venue"
},
  "geometry": {"coordinates":[-95.244889,29.445522],"type":"Point"}
}