{
  "type": "Feature",
  "properties": {
    "iso:country":"US",
    "sg:address":"101 N Park St Charles",
    "sg:city":"Brenham",
    "sg:classifiers":[
        {
            "category":"Real Estate",
            "subcategory":"Real Estate Services",
            "type":"Services"
        },
        {
            "category":"Real Estate",
            "subcategory":"Real Estate Agent",
            "type":"Services"
        }
    ],
    "sg:phone":"+1 979 836 1002",
    "sg:postcode":"77833",
    "sg:province":"TX",
    "sg:tags":[
        "buyer",
        "broker"
    ],
    "sg:website":"http://www.kennedycountry.com",
    "wof:name":"Kennedy Country Properties",
    "wof:placetype":"venue"
},
  "geometry": {"coordinates":[-96.39810900000001,30.167351],"type":"Point"}
}