{
  "type": "Feature",
  "properties": {
    "iso:country":"US",
    "sg:address":"11704 Lemens Sugar Cove",
    "sg:city":"Austin",
    "sg:classifiers":[
        {
            "category":"Personal",
            "subcategory":"Beauty Salon",
            "type":"Services"
        }
    ],
    "sg:phone":"+1 512 336 0739",
    "sg:postcode":"78750",
    "sg:province":"TX",
    "sg:tags":[
        "shop"
    ],
    "wof:name":"Natural Beauty & Health LLC",
    "wof:placetype":"venue"
},
  "geometry": {"coordinates":[-97.78130899999999,30.436109],"type":"Point"}
}