{
  "type": "Feature",
  "properties": {
    "iso:country":"US",
    "sg:address":"951 W Pipeline Rd",
    "sg:city":"Hurst",
    "sg:classifiers":[
        {
            "category":"Real Estate",
            "subcategory":"Real Estate Agent",
            "type":"Services"
        },
        {
            "category":"Personal",
            "type":"Services"
        }
    ],
    "sg:phone":"+1 817 284 1717",
    "sg:postcode":"76053",
    "sg:province":"TX",
    "sg:tags":[
        "finding",
        "apartment",
        "rental"
    ],
    "wof:name":"All About Apartments",
    "wof:placetype":"venue"
},
  "geometry": {"coordinates":[-97.19274799999999,32.823654],"type":"Point"}
}