{
  "type": "Feature",
  "properties": {
    "iso:country":"US",
    "sg:address":"143 Wellwood St",
    "sg:city":"Corpus Christi",
    "sg:classifiers":[
        {
            "category":"Food & Beverages",
            "subcategory":"Specialty",
            "type":"Retail Goods"
        }
    ],
    "sg:phone":"+1 361 241 8460",
    "sg:postcode":"78410",
    "sg:province":"TX",
    "wof:name":"Better Health Naturally",
    "wof:placetype":"venue"
},
  "geometry": {"coordinates":[-97.572041,27.850545],"type":"Point"}
}