{
  "type": "Feature",
  "properties": {
    "iso:country":"US",
    "sg:address":"5306 Junius St",
    "sg:city":"Dallas",
    "sg:classifiers":[
        {
            "category":"Professional",
            "subcategory":"Lawyer & Legal Services",
            "type":"Services"
        }
    ],
    "sg:phone":"+1 214 824 5200",
    "sg:postcode":"75214",
    "sg:province":"TX",
    "wof:name":"Wootton Dale Atty",
    "wof:placetype":"venue"
},
  "geometry": {"coordinates":[-96.763802,32.802399],"type":"Point"}
}