{
  "type": "Feature",
  "properties": {
    "iso:country":"US",
    "sg:address":"307 S 5th St",
    "sg:city":"Alvarado",
    "sg:classifiers":[
        {
            "category":"Building & Trades",
            "subcategory":"Plumbing",
            "type":"Services"
        }
    ],
    "sg:phone":"+1 817 790 6155",
    "sg:postcode":"76009",
    "sg:province":"TX",
    "sg:tags":[
        "conditioning",
        "air",
        "system",
        "contractor"
    ],
    "wof:name":"Smith Air Conditioning & Htg",
    "wof:placetype":"venue"
},
  "geometry": {"coordinates":[-97.21053499999999,32.397995],"type":"Point"}
}