{
  "type": "Feature",
  "properties": {
    "iso:country":"US",
    "sg:address":"1114 Mill Run Dr",
    "sg:city":"Allen",
    "sg:classifiers":[
        {
            "category":"Retail",
            "subcategory":"Veterinary Services",
            "type":"Services"
        }
    ],
    "sg:phone":"+1 214 495 0631",
    "sg:postcode":"75002",
    "sg:province":"TX",
    "wof:name":"Feral Friends Animal Resc",
    "wof:placetype":"venue"
},
  "geometry": {"coordinates":[-96.647317,33.114443],"type":"Point"}
}