{
  "type": "Feature",
  "properties": {
    "iso:country":"US",
    "sg:address":"600 N Carrier Pkwy",
    "sg:city":"Grand Prairie",
    "sg:classifiers":[
        {
            "category":"Retail",
            "subcategory":"Car Wash",
            "type":"Services"
        }
    ],
    "sg:phone":"+1 972 262 3070",
    "sg:postcode":"75050",
    "sg:province":"TX",
    "sg:tags":[
        "polishing",
        "washing"
    ],
    "wof:name":"Supershine Car Wash",
    "wof:placetype":"venue"
},
  "geometry": {"coordinates":[-97.017009,32.747599],"type":"Point"}
}