{
  "type": "Feature",
  "properties": {
    "iso:country":"US",
    "sg:address":"3321 Cardinal Ln",
    "sg:city":"Irving",
    "sg:classifiers":[
        {
            "category":"Building & Trades",
            "subcategory":"Pest Control",
            "type":"Services"
        }
    ],
    "sg:phone":"+1 972 255 0447",
    "sg:postcode":"75062",
    "sg:province":"TX",
    "wof:name":"Amex Pest Control",
    "wof:placetype":"venue"
},
  "geometry": {"coordinates":[-96.994823,32.852456],"type":"Point"}
}