{
  "type": "Feature",
  "properties": {
    "iso:country":"US",
    "sg:address":"1301 Custer Rd",
    "sg:city":"Richardson",
    "sg:classifiers":[
        {
            "category":"Wholesale",
            "subcategory":"Computers",
            "type":"Manufacturing & Wholesale Goods"
        }
    ],
    "sg:phone":"+1 972 680 1566",
    "sg:postcode":"75080",
    "sg:province":"TX",
    "wof:name":"Spydercomm Inc",
    "wof:placetype":"venue"
},
  "geometry": {"coordinates":[-96.734303,32.967925],"type":"Point"}
}