{
  "type": "Feature",
  "properties": {
    "iso:country":"US",
    "sg:address":"12626 Woodforest Blvd",
    "sg:city":"Houston",
    "sg:classifiers":[
        {
            "category":"Health Services",
            "subcategory":"Dentist",
            "type":"Services"
        }
    ],
    "sg:phone":"+1 713 590 0999",
    "sg:postcode":"77015",
    "sg:province":"TX",
    "sg:tags":[
        "pediatric"
    ],
    "wof:name":"SUMMIT DENTAL CENTER",
    "wof:placetype":"venue"
},
  "geometry": {"coordinates":[-95.201268,29.791115],"type":"Point"}
}