{
  "type": "Feature",
  "properties": {
    "iso:country":"US",
    "sg:address":"5301 Campus Dr",
    "sg:city":"Fort Worth",
    "sg:classifiers":[
        {
            "category":"Education",
            "subcategory":"College",
            "type":"Public Place"
        }
    ],
    "sg:phone":"+1 817 515 8223",
    "sg:postcode":"76119",
    "sg:province":"TX",
    "sg:tags":[
        "academic",
        "school"
    ],
    "sg:website":"www.tccd.edu",
    "wof:name":"Tarrant County College",
    "wof:placetype":"venue"
},
  "geometry": {"coordinates":[-97.29354499999999,32.669846],"type":"Point"}
}