{
  "type": "Feature",
  "properties": {
    "iso:country":"US",
    "sg:address":"1705 Bench Mark Dr",
    "sg:city":"Austin",
    "sg:classifiers":[
        {
            "category":"Wholesale",
            "subcategory":"Electrical",
            "type":"Manufacturing & Wholesale Goods"
        }
    ],
    "sg:phone":"+1 512 252 1722",
    "sg:postcode":"78728",
    "sg:province":"TX",
    "sg:tags":[
        "equipment"
    ],
    "wof:name":"Nite Time Decor",
    "wof:placetype":"venue"
},
  "geometry": {"coordinates":[-97.678527,30.430853],"type":"Point"}
}