{
  "type": "Feature",
  "properties": {
    "iso:country":"US",
    "sg:address":"14915 Redbud Leaf Ln",
    "sg:city":"Cypress",
    "sg:classifiers":[
        {
            "category":"Retail",
            "subcategory":"Portrait Studio",
            "type":"Services"
        }
    ],
    "sg:phone":"+1 281 213 9499",
    "sg:postcode":"77433",
    "sg:province":"TX",
    "sg:tags":[
        "photographer"
    ],
    "wof:name":"Ivy's Garrden Photography",
    "wof:placetype":"venue"
},
  "geometry": {"coordinates":[-95.74721599999999,29.995549],"type":"Point"}
}