{
  "type": "Feature",
  "properties": {
    "iso:country":"US",
    "sg:address":"3410 65th Dr",
    "sg:city":"Lubbock",
    "sg:classifiers":[
        {
            "category":"Health Services",
            "subcategory":"Health Practitioner",
            "type":"Services"
        }
    ],
    "sg:phone":"+1 806 792 3823",
    "sg:postcode":"79413",
    "sg:province":"TX",
    "wof:name":"Luchsinger Pasha",
    "wof:placetype":"venue"
},
  "geometry": {"coordinates":[-101.889369,33.534463],"type":"Point"}
}