{
  "type": "Feature",
  "properties": {
    "iso:country":"US",
    "sg:address":"1506 Francis St",
    "sg:city":"Carrollton",
    "sg:classifiers":[
        {
            "category":"Building & Trades",
            "subcategory":"Landscaping Services",
            "type":"Services"
        }
    ],
    "sg:phone":"+1 972 323 4929",
    "sg:postcode":"75006",
    "sg:province":"TX",
    "sg:tags":[
        "designer",
        "landscape"
    ],
    "wof:name":"First Quality Property Svc",
    "wof:placetype":"venue"
},
  "geometry": {"coordinates":[-96.90028599999999,32.952204],"type":"Point"}
}