{
  "type": "Feature",
  "properties": {
    "iso:country":"US",
    "sg:address":"18111 Palisade Rock Ct",
    "sg:city":"Richmond",
    "sg:classifiers":[
        {
            "category":"Bakery",
            "type":"Food & Drink"
        }
    ],
    "sg:phone":"+1 281 762 2805",
    "sg:postcode":"77407",
    "sg:province":"TX",
    "sg:tags":[
        "cake",
        "pastry",
        "wedding"
    ],
    "wof:name":"Cake Sweet Cake",
    "wof:placetype":"venue"
},
  "geometry": {"coordinates":[-95.698109,29.68017],"type":"Point"}
}