{
  "type": "Feature",
  "properties": {
    "iso:country":"US",
    "sg:address":"902 NE Loop 289",
    "sg:city":"Lubbock",
    "sg:classifiers":[
        {
            "category":"Manufacturing",
            "subcategory":"Wood Products",
            "type":"Manufacturing & Wholesale Goods"
        },
        {
            "category":"Building & Trades",
            "subcategory":"Construction",
            "type":"Services"
        }
    ],
    "sg:phone":"+1 806 792 4864",
    "sg:postcode":"79403",
    "sg:province":"TX",
    "sg:tags":[
        "millwork-wholesale",
        "millwork",
        "maker",
        "manufacturer",
        "cabinet"
    ],
    "sg:website":"http://www.huntermillworks.com",
    "wof:name":"Hunter Millworks Inc",
    "wof:placetype":"venue"
},
  "geometry": {"coordinates":[-101.826075,33.616245],"type":"Point"}
}