{
  "type": "Feature",
  "properties": {
    "iso:country":"US",
    "sg:address":"439 Edgewood Dr",
    "sg:city":"Montgomery",
    "sg:classifiers":[
        {
            "category":"Retail",
            "subcategory":"Auto Repair",
            "type":"Services"
        }
    ],
    "sg:phone":"+1 936 597 5653",
    "sg:postcode":"77356",
    "sg:province":"TX",
    "sg:tags":[
        "automotive"
    ],
    "wof:name":"Puget Sound Lubes",
    "wof:placetype":"venue"
},
  "geometry": {"coordinates":[-95.615036,30.42308],"type":"Point"}
}