{
  "type": "Feature",
  "properties": {
    "iso:country":"US",
    "sg:address":"105 Brookhollow Dr",
    "sg:city":"Terrell",
    "sg:classifiers":[
        {
            "category":"Professional",
            "subcategory":"Advertising",
            "type":"Services"
        }
    ],
    "sg:phone":"+1 972 524 5870",
    "sg:postcode":"75160",
    "sg:province":"TX",
    "wof:name":"Stefco-Stephanie Crothers Advg",
    "wof:placetype":"venue"
},
  "geometry": {"coordinates":[-96.29118800000001,32.758521],"type":"Point"}
}