{
  "type": "Feature",
  "properties": {
    "iso:country":"US",
    "sg:address":"1822 Shadow Park St",
    "sg:city":"San Antonio",
    "sg:classifiers":[
        {
            "category":"Professional",
            "subcategory":"Art Services",
            "type":"Services"
        }
    ],
    "sg:phone":"+1 210 494 0446",
    "sg:postcode":"78232",
    "sg:province":"TX",
    "sg:tags":[
        "commercial",
        "design"
    ],
    "wof:name":"R O Gray",
    "wof:placetype":"venue"
},
  "geometry": {"coordinates":[-98.454964,29.567561],"type":"Point"}
}