{
  "type": "Feature",
  "properties": {
    "iso:country":"US",
    "sg:address":"1737 Knickerbocker Rd",
    "sg:city":"San Angelo",
    "sg:classifiers":[
        {
            "category":"Building & Trades",
            "subcategory":"Construction",
            "type":"Services"
        }
    ],
    "sg:phone":"+1 325 658 6627",
    "sg:postcode":"76904",
    "sg:province":"TX",
    "sg:tags":[
        "decorating",
        "painting",
        "contractor"
    ],
    "wof:name":"Counts Painting & Decorating",
    "wof:placetype":"venue"
},
  "geometry": {"coordinates":[-100.45605399999999,31.430774],"type":"Point"}
}