{
  "type": "Feature",
  "properties": {
    "iso:country":"US",
    "sg:address":"3025 Forest Ave",
    "sg:city":"Fort Worth",
    "sg:classifiers":[
        {
            "category":"Building & Trades",
            "subcategory":"Construction",
            "type":"Services"
        }
    ],
    "sg:phone":"+1 817 496 9888",
    "sg:postcode":"76112",
    "sg:province":"TX",
    "sg:tags":[
        "roofing",
        "contractor"
    ],
    "wof:name":"J & R Roofing Co",
    "wof:placetype":"venue"
},
  "geometry": {"coordinates":[-97.21889400000001,32.734772],"type":"Point"}
}