{
  "type": "Feature",
  "properties": {
    "iso:country":"US",
    "sg:address":"13003 Jones Maltsberger Rd",
    "sg:city":"San Antonio",
    "sg:classifiers":[
        {
            "category":"Retail",
            "subcategory":"Portrait Studio",
            "type":"Services"
        }
    ],
    "sg:phone":"+1 210 495 3686",
    "sg:postcode":"78247",
    "sg:province":"TX",
    "sg:tags":[
        "photographer"
    ],
    "wof:name":"Once Upon A Time Photography",
    "wof:placetype":"venue"
},
  "geometry": {"coordinates":[-98.45969700000001,29.560911],"type":"Point"}
}