{
  "type": "Feature",
  "properties": {
    "iso:country":"US",
    "sg:address":"5715 Sunup Dr",
    "sg:city":"San Antonio",
    "sg:classifiers":[
        {
            "category":"Professional",
            "subcategory":"Accounting & Tax Preparation",
            "type":"Services"
        }
    ],
    "sg:phone":"+1 210 293 0408",
    "sg:postcode":"78233",
    "sg:province":"TX",
    "sg:tags":[
        "bookkeeping",
        "general"
    ],
    "wof:name":"Altman Business Supplies",
    "wof:placetype":"venue"
},
  "geometry": {"coordinates":[-98.37291399999999,29.56913],"type":"Point"}
}