{
  "type": "Feature",
  "properties": {
    "iso:country":"US",
    "sg:address":"5203 W Cedar Bayou Lynchburg Rd",
    "sg:city":"Baytown",
    "sg:classifiers":[
        {
            "category":"Autos & Motor Vehicles",
            "subcategory":"Automobile Sales",
            "type":"Retail Goods"
        }
    ],
    "sg:phone":"+1 281 424 6094",
    "sg:postcode":"77521",
    "sg:province":"TX",
    "sg:tags":[
        "car",
        "dealer"
    ],
    "wof:name":"JSB Auto Sales",
    "wof:placetype":"venue"
},
  "geometry": {"coordinates":[-95.021382,29.7852],"type":"Point"}
}