{
  "type": "Feature",
  "properties": {
    "iso:country":"US",
    "sg:address":"203 N 4th St",
    "sg:city":"Robstown",
    "sg:classifiers":[
        {
            "category":"Professional",
            "type":"Services"
        }
    ],
    "sg:phone":"+1 361 387 2500",
    "sg:postcode":"78380",
    "sg:province":"TX",
    "sg:tags":[
        "establishment"
    ],
    "wof:name":"Mhc Of South Gulf Tx",
    "wof:placetype":"venue"
},
  "geometry": {"coordinates":[-97.664816,27.790607],"type":"Point"}
}