{
  "type": "Feature",
  "properties": {
    "iso:country":"US",
    "sg:address":"421 E Pioneer Dr",
    "sg:city":"Irving",
    "sg:classifiers":[
        {
            "category":"Wholesale",
            "subcategory":"Machinery & Supplies",
            "type":"Manufacturing & Wholesale Goods"
        },
        {
            "category":"Manufacturing",
            "subcategory":"Tools & Machinery",
            "type":"Manufacturing & Wholesale Goods"
        }
    ],
    "sg:phone":"+1 972 438 3377",
    "sg:postcode":"75061",
    "sg:province":"TX",
    "sg:tags":[
        "equipment",
        "industrial",
        "dairy",
        "contractor"
    ],
    "sg:website":"www.harvill-ind.com",
    "wof:name":"Harvill Industries Ltd",
    "wof:placetype":"venue"
},
  "geometry": {"coordinates":[-96.940579,32.817735],"type":"Point"}
}