{
  "type": "Feature",
  "properties": {
    "iso:country":"US",
    "sg:address":"819 W 61st St",
    "sg:city":"Odessa",
    "sg:classifiers":[
        {
            "category":"Shopping",
            "subcategory":"Gifts & Souvenirs",
            "type":"Retail Goods"
        }
    ],
    "sg:phone":"+1 432 362 4446",
    "sg:postcode":"79764",
    "sg:province":"TX",
    "sg:tags":[
        "shop",
        "beauty"
    ],
    "wof:name":"Country Cottage Hair Styling",
    "wof:placetype":"venue"
},
  "geometry": {"coordinates":[-102.400712,31.898918],"type":"Point"}
}