{
  "type": "Feature",
  "properties": {
    "iso:country":"US",
    "sg:address":"19518 Forest Fern Dr",
    "sg:city":"Humble",
    "sg:classifiers":[
        {
            "category":"Internet Cafe",
            "subcategory":"None",
            "type":"Food & Drink"
        }
    ],
    "sg:phone":"+1 281 812 0731",
    "sg:postcode":"77346",
    "sg:province":"TX",
    "sg:tags":[
        "product"
    ],
    "wof:name":"Atascosys",
    "wof:placetype":"venue"
},
  "geometry": {"coordinates":[-95.19251,30.004446],"type":"Point"}
}