{
  "type": "Feature",
  "properties": {
    "iso:country":"US",
    "sg:address":"3429 W Holcombe Blvd",
    "sg:city":"Houston",
    "sg:classifiers":[
        {
            "category":"Health Services",
            "subcategory":"Chiropractor",
            "type":"Services"
        }
    ],
    "sg:phone":"+1 713 661 3190",
    "sg:postcode":"77025",
    "sg:province":"TX",
    "sg:website":"www.doctorsspinaldecompressionce...",
    "wof:name":"Doctors Chiropractic Health & Rehab Center",
    "wof:placetype":"venue"
},
  "geometry": {"coordinates":[-95.43000000000001,29.7059],"type":"Point"}
}