{
  "type": "Feature",
  "properties": {
    "iso:country":"US",
    "sg:address":"8855 Mountain Ridge Cir",
    "sg:city":"Austin",
    "sg:classifiers":[
        {
            "category":"Shopping",
            "subcategory":"Musical Instruments",
            "type":"Retail Goods"
        }
    ],
    "sg:phone":"+1 512 335 6249",
    "sg:postcode":"78759",
    "sg:province":"TX",
    "sg:tags":[
        "guitar",
        "amplifier"
    ],
    "wof:name":"Delaine E Fedson",
    "wof:placetype":"venue"
},
  "geometry": {"coordinates":[-97.753069,30.385281],"type":"Point"}
}