{
  "type": "Feature",
  "properties": {
    "iso:country":"US",
    "sg:address":"4329 San Gabriel Dr",
    "sg:city":"Dallas",
    "sg:classifiers":[
        {
            "category":"Shopping",
            "subcategory":"Computers & Home Electronics",
            "type":"Retail Goods"
        }
    ],
    "sg:phone":"+1 214 358 0579",
    "sg:postcode":"75229",
    "sg:province":"TX",
    "wof:name":"Micro Marketing Co",
    "wof:placetype":"venue"
},
  "geometry": {"coordinates":[-96.83641299999999,32.899213],"type":"Point"}
}