{
  "type": "Feature",
  "properties": {
    "iso:country":"US",
    "sg:address":"509 E 3rd St",
    "sg:city":"Big Spring",
    "sg:classifiers":[
        {
            "category":"Building & Trades",
            "subcategory":"Construction",
            "type":"Services"
        }
    ],
    "sg:phone":"+1 432 264 6629",
    "sg:postcode":"79720",
    "sg:province":"TX",
    "sg:tags":[
        "roofing"
    ],
    "wof:name":"B&B Roofing & Construction",
    "wof:placetype":"venue"
},
  "geometry": {"coordinates":[-101.471355,32.254732],"type":"Point"}
}