{
  "type": "Feature",
  "properties": {
    "iso:country":"US",
    "sg:address":"2515 Parrott Ave",
    "sg:city":"Waco",
    "sg:classifiers":[
        {
            "category":"Insurance",
            "subcategory":"Insurance Agent",
            "type":"Services"
        }
    ],
    "sg:phone":"+1 254 753 5200",
    "sg:postcode":"76707",
    "sg:province":"TX",
    "wof:name":"Zucha Insurance Agency",
    "wof:placetype":"venue"
},
  "geometry": {"coordinates":[-97.164006,31.553511],"type":"Point"}
}