{
  "type": "Feature",
  "properties": {
    "iso:country":"US",
    "sg:address":"4600 S Medford Dr",
    "sg:city":"Lufkin",
    "sg:classifiers":[
        {
            "category":"Shopping",
            "subcategory":"Clothing, Apparel, & Fashions",
            "type":"Retail Goods"
        }
    ],
    "sg:phone":"+1 936 699 2566",
    "sg:postcode":"75901",
    "sg:province":"TX",
    "wof:name":"Gadzooks",
    "wof:placetype":"venue"
},
  "geometry": {"coordinates":[-94.725319,31.310554],"type":"Point"}
}