{
  "type": "Feature",
  "properties": {
    "iso:country":"US",
    "sg:address":"2808 Tommelson Creek Rd",
    "sg:city":"Brenham",
    "sg:classifiers":[
        {
            "category":"Real Estate",
            "subcategory":"Real Estate Operator",
            "type":"Services"
        }
    ],
    "sg:phone":"+1 979 836 8833",
    "sg:postcode":"77833",
    "sg:province":"TX",
    "sg:tags":[
        "building",
        "commercial"
    ],
    "wof:name":"Bassett Building",
    "wof:placetype":"venue"
},
  "geometry": {"coordinates":[-96.391543,30.22957],"type":"Point"}
}