{
  "type": "Feature",
  "properties": {
    "iso:country":"US",
    "sg:address":"106 E Young Ave",
    "sg:city":"Temple",
    "sg:classifiers":[
        {
            "category":"Professional",
            "subcategory":"Management & Consulting",
            "type":"Services"
        }
    ],
    "sg:phone":"+1 254 742 0135",
    "sg:postcode":"76501",
    "sg:province":"TX",
    "sg:tags":[
        "business"
    ],
    "wof:name":"Thompson Group",
    "wof:placetype":"venue"
},
  "geometry": {"coordinates":[-97.330941,31.120058],"type":"Point"}
}