{
  "type": "Feature",
  "properties": {
    "iso:country":"US",
    "sg:address":"311 S Industrial Blvd",
    "sg:city":"Euless",
    "sg:classifiers":[
        {
            "category":"Professional",
            "subcategory":"Computer Services",
            "type":"Services"
        }
    ],
    "sg:phone":"+1 817 571 1852",
    "sg:postcode":"76040",
    "sg:province":"TX",
    "sg:tags":[
        "datum"
    ],
    "wof:name":"True Tabernacle",
    "wof:placetype":"venue"
},
  "geometry": {"coordinates":[-97.09961,32.832116],"type":"Point"}
}