{
  "type": "Feature",
  "properties": {
    "iso:country":"US",
    "sg:address":"405 Evans Dr",
    "sg:city":"Euless",
    "sg:classifiers":[
        {
            "category":"Professional",
            "subcategory":"Management & Consulting",
            "type":"Services"
        }
    ],
    "sg:phone":"+1 817 540 6553",
    "sg:postcode":"76040",
    "sg:province":"TX",
    "sg:tags":[
        "business"
    ],
    "wof:name":"Wolff Enterprises",
    "wof:placetype":"venue"
},
  "geometry": {"coordinates":[-97.117508,32.83281],"type":"Point"}
}