{
  "type": "Feature",
  "properties": {
    "iso:country":"US",
    "sg:address":"607 Porpoise St",
    "sg:city":"Aransas Pass",
    "sg:classifiers":[
        {
            "category":"Real Estate",
            "subcategory":"Real Estate Operator",
            "type":"Services"
        }
    ],
    "sg:phone":"+1 361 758 1028",
    "sg:postcode":"78336",
    "sg:province":"TX",
    "sg:tags":[
        "building",
        "nonresidential"
    ],
    "wof:name":"E & R Properties Ltd",
    "wof:placetype":"venue"
},
  "geometry": {"coordinates":[-97.144272,27.899679],"type":"Point"}
}