{
  "type": "Feature",
  "properties": {
    "iso:country":"US",
    "sg:address":"219 Eastwood Ave Ste A",
    "sg:city":"Livingston",
    "sg:classifiers":[
        {
            "category":"Health Services",
            "subcategory":"Doctor",
            "type":"Services"
        }
    ],
    "sg:phone":"+1 936 685 7778",
    "sg:postcode":"77351",
    "sg:province":"TX",
    "sg:tags":[
        "physician",
        "family",
        "practice",
        "surgeons",
        "medicine"
    ],
    "wof:name":"Family Practice",
    "wof:placetype":"venue"
},
  "geometry": {"coordinates":[-94.92740000000001,30.709638],"type":"Point"}
}