{
  "type": "Feature",
  "properties": {
    "iso:country":"US",
    "sg:address":"3623 S Travis St",
    "sg:city":"Amarillo",
    "sg:classifiers":[
        {
            "category":"Professional",
            "type":"Services"
        }
    ],
    "sg:phone":"+1 806 358 4182",
    "sg:postcode":"79110",
    "sg:province":"TX",
    "wof:name":"Pjs Nascar & Collectible",
    "wof:placetype":"venue"
},
  "geometry": {"coordinates":[-101.85610699999999,35.172867],"type":"Point"}
}