{
  "type": "Feature",
  "properties": {
    "iso:country":"US",
    "sg:address":"8802 Dexter St",
    "sg:city":"Houston",
    "sg:classifiers":[
        {
            "category":"Professional",
            "subcategory":"Accounting & Tax Preparation",
            "type":"Services"
        }
    ],
    "sg:phone":"+1 713 941 7756",
    "sg:postcode":"77075",
    "sg:province":"TX",
    "sg:tags":[
        "return"
    ],
    "wof:name":"Benitez Income Tax Services",
    "wof:placetype":"venue"
},
  "geometry": {"coordinates":[-95.252836,29.640785],"type":"Point"}
}