{
  "type": "Feature",
  "properties": {
    "iso:country":"US",
    "sg:address":"60 Co Rd 367",
    "sg:city":"Anna",
    "sg:classifiers":[
        {
            "category":"Professional",
            "subcategory":"Business Services",
            "type":"Services"
        }
    ],
    "sg:phone":"+1 972 924 2765",
    "sg:postcode":"75409",
    "sg:province":"TX",
    "wof:name":"Audrey M Roberts",
    "wof:placetype":"venue"
},
  "geometry": {"coordinates":[-96.58813600000001,33.333875],"type":"Point"}
}