{
  "type": "Feature",
  "properties": {
    "iso:country":"US",
    "sg:address":"9802 Cane Creek Dr",
    "sg:city":"Houston",
    "sg:classifiers":[
        {
            "category":"Building & Trades",
            "subcategory":"Landscaping Services",
            "type":"Services"
        }
    ],
    "sg:phone":"+1 281 376 4107",
    "sg:postcode":"77070",
    "sg:province":"TX",
    "sg:tags":[
        "landscape"
    ],
    "wof:name":"Thailer Landscaping",
    "wof:placetype":"venue"
},
  "geometry": {"coordinates":[-95.57333,30.001054],"type":"Point"}
}