{
  "type": "Feature",
  "properties": {
    "iso:country":"US",
    "sg:address":"16990 Dallas Pkwy Ste 101",
    "sg:city":"Dallas",
    "sg:classifiers":[
        {
            "category":"Building & Trades",
            "subcategory":"Construction",
            "type":"Services"
        }
    ],
    "sg:phone":"+1 972 931 3450",
    "sg:postcode":"75248",
    "sg:province":"TX",
    "sg:tags":[
        "contractor"
    ],
    "wof:name":"Axxium Custom Homes",
    "wof:placetype":"venue"
},
  "geometry": {"coordinates":[-96.82849899999999,32.9814],"type":"Point"}
}