{
  "type": "Feature",
  "properties": {
    "iso:country":"US",
    "sg:address":"1704 Sharon Pl",
    "sg:city":"Cedar Park",
    "sg:classifiers":[
        {
            "category":"Wholesale",
            "subcategory":"Vending Machines",
            "type":"Manufacturing & Wholesale Goods"
        }
    ],
    "sg:phone":"+1 512 785 7139",
    "sg:postcode":"78613",
    "sg:province":"TX",
    "wof:name":"Java On The Job",
    "wof:placetype":"venue"
},
  "geometry": {"coordinates":[-97.837988,30.472593],"type":"Point"}
}