{
  "type": "Feature",
  "properties": {
    "iso:country":"US",
    "sg:address":"651 N US Highway 183",
    "sg:city":"Leander",
    "sg:classifiers":[
        {
            "category":"Wholesale",
            "subcategory":"Medical Equipment & Supplies",
            "type":"Manufacturing & Wholesale Goods"
        },
        {
            "category":"Food & Beverages",
            "subcategory":"Specialty",
            "type":"Retail Goods"
        },
        {
            "category":"Shopping",
            "subcategory":"Florist",
            "type":"Retail Goods"
        },
        {
            "category":"Food & Beverages",
            "subcategory":"Supermarket",
            "type":"Retail Goods"
        },
        {
            "category":"Shopping",
            "subcategory":"Pharmacy",
            "type":"Retail Goods"
        },
        {
            "category":"Food & Beverages",
            "subcategory":"Groceries & Convenience Stores",
            "type":"Retail Goods"
        }
    ],
    "sg:phone":"+1 512 528 7777",
    "sg:postcode":"78641",
    "sg:province":"TX",
    "sg:tags":[
        "product",
        "wellness",
        "vitamin",
        "supplement",
        "health",
        "aid",
        "super",
        "first"
    ],
    "sg:website":"http://www.heb.com/pharmacy/pharmacy-and-health.jsp",
    "wof:name":"H-E-B Pharmacy",
    "wof:placetype":"venue"
},
  "geometry": {"coordinates":[-97.879997,30.591935],"type":"Point"}
}