{
  "type": "Feature",
  "properties": {
    "iso:country":"US",
    "sg:address":"10595 W Sam Houston Pkwy S",
    "sg:city":"Houston",
    "sg:classifiers":[
        {
            "category":"Autos & Motor Vehicles",
            "subcategory":"Automobile Sales",
            "type":"Retail Goods"
        },
        {
            "category":"Autos & Motor Vehicles",
            "subcategory":"Auto Supplies",
            "type":"Retail Goods"
        },
        {
            "category":"Banks & Credit Unions",
            "subcategory":"Financial Services",
            "type":"Services"
        },
        {
            "category":"Retail",
            "subcategory":"Auto Repair",
            "type":"Services"
        }
    ],
    "sg:phone":"+1 877 544 9243",
    "sg:postcode":"77099",
    "sg:province":"TX",
    "sg:tags":[
        "used",
        "car",
        "loan",
        "accessory",
        "part",
        "new"
    ],
    "sg:website":"http://www.gillmanhondahouston.com",
    "wof:name":"Gillman Honda of Houston Southwest",
    "wof:placetype":"venue"
},
  "geometry": {"coordinates":[-95.55901799999999,29.664717],"type":"Point"}
}