{
  "type": "Feature",
  "properties": {
    "iso:country":"US",
    "sg:address":"14135 Stagecoach Rd",
    "sg:city":"Magnolia",
    "sg:classifiers":[
        {
            "category":"Manufacturing",
            "subcategory":"Furniture",
            "type":"Manufacturing & Wholesale Goods"
        }
    ],
    "sg:phone":"+1 281 356 6131",
    "sg:postcode":"77355",
    "sg:province":"TX",
    "sg:tags":[
        "household",
        "wood",
        "spec",
        "mfg"
    ],
    "wof:name":"Custom Wood Designs & Mfg",
    "wof:placetype":"venue"
},
  "geometry": {"coordinates":[-95.69938,30.138376],"type":"Point"}
}