{
  "type": "Feature",
  "properties": {
    "iso:country":"US",
    "sg:address":"1206 Cedar Hill Ave",
    "sg:city":"Dallas",
    "sg:classifiers":[
        {
            "category":"Building & Trades",
            "subcategory":"Construction",
            "type":"Services"
        }
    ],
    "sg:phone":"+1 214 739 8614",
    "sg:postcode":"75208",
    "sg:province":"TX",
    "sg:tags":[
        "repairing",
        "remodeling",
        "contractor"
    ],
    "wof:name":"A Approved Remodeling",
    "wof:placetype":"venue"
},
  "geometry": {"coordinates":[-96.830934,32.758004],"type":"Point"}
}