{
  "type": "Feature",
  "properties": {
    "iso:country":"US",
    "sg:address":"508 E San Antonio Ave",
    "sg:city":"Boerne",
    "sg:classifiers":[
        {
            "category":"Real Estate",
            "subcategory":"Real Estate Agent",
            "type":"Services"
        }
    ],
    "sg:phone":"+1 830 816 8181",
    "sg:postcode":"78006",
    "sg:province":"TX",
    "wof:name":"Reliance Property Group",
    "wof:placetype":"venue"
},
  "geometry": {"coordinates":[-98.726534,29.796186],"type":"Point"}
}