{
  "type": "Feature",
  "properties": {
    "iso:country":"US",
    "sg:address":"8834 N Capital of Texas Hwy",
    "sg:city":"Austin",
    "sg:classifiers":[
        {
            "category":"Professional",
            "subcategory":"Management & Consulting",
            "type":"Services"
        }
    ],
    "sg:phone":"+1 512 794 2917",
    "sg:postcode":"78759",
    "sg:province":"TX",
    "wof:name":"Adecco Tad Technical",
    "wof:placetype":"venue"
},
  "geometry": {"coordinates":[-97.760499,30.387971],"type":"Point"}
}