{
  "type": "Feature",
  "properties": {
    "iso:country":"US",
    "sg:address":"1502 Heights St",
    "sg:city":"Carrizo Springs",
    "sg:classifiers":[
        {
            "category":"Farming",
            "subcategory":"Farm & Veterinary Services",
            "type":"Manufacturing & Wholesale Goods"
        }
    ],
    "sg:phone":"+1 830 876 5595",
    "sg:postcode":"78834",
    "sg:province":"TX",
    "sg:tags":[
        "livestock"
    ],
    "wof:name":"4g Cattle Co",
    "wof:placetype":"venue"
},
  "geometry": {"coordinates":[-99.86212999999999,28.53449],"type":"Point"}
}