{
  "type": "Feature",
  "properties": {
    "iso:country":"US",
    "sg:address":"1720 Dryden Rd",
    "sg:city":"Houston",
    "sg:classifiers":[
        {
            "category":"Professional",
            "subcategory":"Business Services",
            "type":"Services"
        }
    ],
    "sg:phone":"+1 713 799 1999",
    "sg:postcode":"77030",
    "sg:province":"TX",
    "wof:name":"Medical Center Postal Express",
    "wof:placetype":"venue"
},
  "geometry": {"coordinates":[-95.400997,29.709901],"type":"Point"}
}