{
  "type": "Feature",
  "properties": {
    "iso:country":"US",
    "sg:address":"2313 N County Rd W",
    "sg:city":"Odessa",
    "sg:classifiers":[
        {
            "category":"Restaurant",
            "type":"Food & Drink"
        }
    ],
    "sg:menulink":"http://www.allmenus.com/tx/odessa/204292-sonic/menu/",
    "sg:phone":"+1 432 332 2363",
    "sg:postcode":"79763",
    "sg:province":"TX",
    "sg:tags":[
        "burger",
        "american"
    ],
    "wof:name":"Sonic",
    "wof:placetype":"venue"
},
  "geometry": {"coordinates":[-102.395213,31.859354],"type":"Point"}
}