{
  "type": "Feature",
  "properties": {
    "iso:country":"US",
    "sg:address":"2305 Mc Nay Dr",
    "sg:city":"Pasadena",
    "sg:classifiers":[
        {
            "category":"Retail",
            "subcategory":"Auto Repair",
            "type":"Services"
        }
    ],
    "sg:phone":"+1 713 477 5000",
    "sg:postcode":"77506",
    "sg:province":"TX",
    "sg:tags":[
        "automotive"
    ],
    "wof:name":"Pasadena Towing Service Inc",
    "wof:placetype":"venue"
},
  "geometry": {"coordinates":[-95.175995,29.699725],"type":"Point"}
}