{
  "type": "Feature",
  "properties": {
    "iso:country":"US",
    "sg:address":"608 Harvest Mountain Ct",
    "sg:city":"Allen",
    "sg:classifiers":[
        {
            "category":"Professional",
            "subcategory":"Management & Consulting",
            "type":"Services"
        }
    ],
    "sg:phone":"+1 972 727 3538",
    "sg:postcode":"75002",
    "sg:province":"TX",
    "sg:tags":[
        "business"
    ],
    "wof:name":"Help Desk Consultants",
    "wof:placetype":"venue"
},
  "geometry": {"coordinates":[-96.663078,33.090472],"type":"Point"}
}