{
  "type": "Feature",
  "properties": {
    "iso:country":"US",
    "sg:address":"2008 N Ware Rd",
    "sg:city":"Mcallen",
    "sg:classifiers":[
        {
            "category":"Organizations",
            "subcategory":"Membership Organization",
            "type":"Services"
        }
    ],
    "sg:phone":"+1 956 618 4180",
    "sg:postcode":"78501",
    "sg:province":"TX",
    "wof:name":"Islamic Society Of South Texas",
    "wof:placetype":"venue"
},
  "geometry": {"coordinates":[-98.25874899999999,26.223183],"type":"Point"}
}