{
  "type": "Feature",
  "properties": {
    "iso:country":"US",
    "sg:address":"127 S Crestwood Blvd",
    "sg:city":"De Soto",
    "sg:classifiers":[
        {
            "category":"Communications",
            "subcategory":"Film & Video Production",
            "type":"Services"
        }
    ],
    "sg:phone":"+1 972 230 0348",
    "sg:postcode":"75115",
    "sg:province":"TX",
    "sg:tags":[
        "motion"
    ],
    "wof:name":"Powell Productions",
    "wof:placetype":"venue"
},
  "geometry": {"coordinates":[-96.830955,32.587246],"type":"Point"}
}