{
  "type": "Feature",
  "properties": {
    "iso:country":"US",
    "sg:address":"3004 Aldine Bender Rd",
    "sg:city":"Houston",
    "sg:classifiers":[
        {
            "category":"Sports & Exercise",
            "subcategory":"Ski Resort",
            "type":"Entertainment"
        }
    ],
    "sg:phone":"+1 281 227 7918",
    "sg:postcode":"77032",
    "sg:province":"TX",
    "sg:tags":[
        "pipe",
        "fitting"
    ],
    "wof:name":"Edgen Murray",
    "wof:placetype":"venue"
},
  "geometry": {"coordinates":[-95.33897,29.930168],"type":"Point"}
}