{
  "type": "Feature",
  "properties": {
    "iso:country":"US",
    "sg:address":"3900 Teleport Blvd",
    "sg:city":"Irving",
    "sg:classifiers":[
        {
            "category":"Government",
            "subcategory":"Post Office",
            "type":"Public Place"
        }
    ],
    "sg:phone":"+1 972 831 1730",
    "sg:postcode":"75039",
    "sg:province":"TX",
    "wof:name":"US Post Office",
    "wof:placetype":"venue"
},
  "geometry": {"coordinates":[-96.926922,32.859379],"type":"Point"}
}