{
  "type": "Feature",
  "properties": {
    "iso:country":"US",
    "sg:address":"1001 Old Garner Rd",
    "sg:city":"Weatherford",
    "sg:classifiers":[
        {
            "category":"Autos & Motor Vehicles",
            "subcategory":"Auto Supplies",
            "type":"Retail Goods"
        },
        {
            "category":"Retail",
            "subcategory":"Auto Repair",
            "type":"Services"
        }
    ],
    "sg:phone":"+1 817 594 2414",
    "sg:postcode":"76088",
    "sg:province":"TX",
    "sg:tags":[
        "shop",
        "automobile",
        "part",
        "machine",
        "accessory"
    ],
    "wof:name":"Jay's Machine Shop",
    "wof:placetype":"venue"
},
  "geometry": {"coordinates":[-97.835644,32.775634],"type":"Point"}
}