{
  "type": "Feature",
  "properties": {
    "iso:country":"US",
    "sg:address":"3823 Bonnie View Rd",
    "sg:city":"Dallas",
    "sg:classifiers":[
        {
            "category":"Real Estate",
            "subcategory":"Real Estate Operator",
            "type":"Services"
        }
    ],
    "sg:phone":"+1 214 376 6020",
    "sg:postcode":"75216",
    "sg:province":"TX",
    "sg:tags":[
        "apartment"
    ],
    "wof:name":"Bonnieview Apartments",
    "wof:placetype":"venue"
},
  "geometry": {"coordinates":[-96.774874,32.712259],"type":"Point"}
}