{
  "type": "Feature",
  "properties": {
    "iso:country":"US",
    "sg:address":"1502 S Ave L",
    "sg:city":"Lamesa",
    "sg:classifiers":[
        {
            "category":"Building & Trades",
            "subcategory":"Construction",
            "type":"Services"
        }
    ],
    "sg:phone":"+1 806 872 3080",
    "sg:postcode":"79331",
    "sg:province":"TX",
    "sg:tags":[
        "house"
    ],
    "wof:name":"Victor E & Mary E Lentz",
    "wof:placetype":"venue"
},
  "geometry": {"coordinates":[-101.958701,32.716897],"type":"Point"}
}