{
  "type": "Feature",
  "properties": {
    "iso:country":"US",
    "sg:address":"5135 W. Alabama #5250A",
    "sg:city":"Houston",
    "sg:classifiers":[
        {
            "category":"Shopping",
            "subcategory":"Clothing, Apparel, & Fashions",
            "type":"Retail Goods"
        },
        {
            "category":"Personal",
            "type":"Services"
        }
    ],
    "sg:phone":"+1 713 572 9400",
    "sg:postcode":"77056",
    "sg:province":"TX",
    "sg:tags":[
        "accessory",
        "clothing",
        "women's"
    ],
    "sg:website":"www.apricotlanehouston.com",
    "wof:name":"Apricot Lane",
    "wof:placetype":"venue"
},
  "geometry": {"coordinates":[-95.464538,29.738029],"type":"Point"}
}