{
  "type": "Feature",
  "properties": {
    "iso:country":"US",
    "sg:address":"12717 Robert E Lee Rd",
    "sg:city":"Houston",
    "sg:classifiers":[
        {
            "category":"Food & Beverages",
            "subcategory":"Meat & Fish",
            "type":"Retail Goods"
        }
    ],
    "sg:phone":"+1 281 458 9504",
    "sg:postcode":"77044",
    "sg:province":"TX",
    "sg:tags":[
        "shop"
    ],
    "wof:name":"B & B Meat Company Inc",
    "wof:placetype":"venue"
},
  "geometry": {"coordinates":[-95.20500199999999,29.8426],"type":"Point"}
}