{
  "type": "Feature",
  "properties": {
    "iso:country":"US",
    "sg:address":"9403 Willowbridge Park Blvd",
    "sg:city":"Houston",
    "sg:classifiers":[
        {
            "category":"Shopping",
            "subcategory":"Clothing, Apparel, & Fashions",
            "type":"Retail Goods"
        }
    ],
    "sg:phone":"+1 281 894 2200",
    "sg:postcode":"77064",
    "sg:province":"TX",
    "sg:tags":[
        "children's",
        "clothing"
    ],
    "wof:name":"Alexandra & Austin",
    "wof:placetype":"venue"
},
  "geometry": {"coordinates":[-95.558953,29.90055],"type":"Point"}
}