{
  "type": "Feature",
  "properties": {
    "iso:country":"US",
    "sg:address":"117 E Lamar St",
    "sg:city":"Sherman",
    "sg:classifiers":[
        {
            "category":"Social Services",
            "type":"Services"
        }
    ],
    "sg:phone":"+1 903 892 8595",
    "sg:postcode":"75090",
    "sg:province":"TX",
    "sg:tags":[
        "organization",
        "welfare"
    ],
    "wof:name":"Crisis Center",
    "wof:placetype":"venue"
},
  "geometry": {"coordinates":[-96.608019,33.635859],"type":"Point"}
}