{
  "type": "Feature",
  "properties": {
    "iso:country":"US",
    "sg:address":"104 2nd St",
    "sg:city":"Freeport",
    "sg:classifiers":[
        {
            "category":"Restaurant",
            "type":"Food & Drink"
        }
    ],
    "sg:phone":"+1 979 373 9730",
    "sg:postcode":"77541",
    "sg:province":"TX",
    "wof:name":"Jetties",
    "wof:placetype":"venue"
},
  "geometry": {"coordinates":[-95.303909,28.938209],"type":"Point"}
}