{
  "type": "Feature",
  "properties": {
    "iso:country":"US",
    "sg:address":"350 N Sam Houston Pkwy E Ste 260",
    "sg:city":"Houston",
    "sg:classifiers":[
        {
            "category":"Building & Trades",
            "subcategory":"Construction",
            "type":"Services"
        }
    ],
    "sg:phone":"+1 281 820 9606",
    "sg:postcode":"77060",
    "sg:province":"TX",
    "sg:tags":[
        "contractor"
    ],
    "wof:name":"First Texas Homes Inc",
    "wof:placetype":"venue"
},
  "geometry": {"coordinates":[-95.40027499999999,29.939495],"type":"Point"}
}