{
  "type": "Feature",
  "properties": {
    "iso:country":"US",
    "sg:address":"105 Indian Creek Dr",
    "sg:city":"Comanche",
    "sg:classifiers":[
        {
            "category":"Home & Garden",
            "subcategory":"Building Materials",
            "type":"Retail Goods"
        }
    ],
    "sg:phone":"+1 325 356 1792",
    "sg:postcode":"76442",
    "sg:province":"TX",
    "sg:tags":[
        "glass",
        "leaded"
    ],
    "wof:name":"Custom Art Glass",
    "wof:placetype":"venue"
},
  "geometry": {"coordinates":[-98.622968,31.894581],"type":"Point"}
}