{
  "type": "Feature",
  "properties": {
    "iso:country":"US",
    "sg:address":"549 Prairie Dell St",
    "sg:city":"Lewisville",
    "sg:classifiers":[
        {
            "category":"Manufacturing",
            "subcategory":"Metals",
            "type":"Manufacturing & Wholesale Goods"
        }
    ],
    "sg:phone":"+1 972 436 9192",
    "sg:postcode":"75067",
    "sg:province":"TX",
    "sg:tags":[
        "work",
        "iron"
    ],
    "wof:name":"Daltex Metals",
    "wof:placetype":"venue"
},
  "geometry": {"coordinates":[-97.011329,33.043019],"type":"Point"}
}