{
  "type": "Feature",
  "properties": {
    "iso:country":"US",
    "sg:address":"2414 Arbor Pl",
    "sg:city":"San Antonio",
    "sg:classifiers":[
        {
            "category":"Organizations",
            "subcategory":"Religious Organization",
            "type":"Services"
        }
    ],
    "sg:phone":"+1 210 436 2146",
    "sg:postcode":"78228",
    "sg:province":"TX",
    "sg:tags":[
        "church"
    ],
    "wof:name":"Gilbert Hernandez Ministries",
    "wof:placetype":"venue"
},
  "geometry": {"coordinates":[-98.542573,29.438922],"type":"Point"}
}