{
  "type": "Feature",
  "properties": {
    "iso:country":"US",
    "sg:address":"131 N 5th St",
    "sg:city":"Krum",
    "sg:classifiers":[
        {
            "category":"Retail",
            "subcategory":"Portrait Studio",
            "type":"Services"
        }
    ],
    "sg:phone":"+1 940 482 6174",
    "sg:postcode":"76249",
    "sg:province":"TX",
    "sg:tags":[
        "photographer"
    ],
    "wof:name":"Alambar Photography",
    "wof:placetype":"venue"
},
  "geometry": {"coordinates":[-97.24333300000001,33.265398],"type":"Point"}
}