{
  "type": "Feature",
  "properties": {
    "iso:country":"US",
    "sg:address":"2904 Live Oak St",
    "sg:city":"Dallas",
    "sg:classifiers":[
        {
            "category":"Shopping",
            "subcategory":"Computers & Home Electronics",
            "type":"Retail Goods"
        }
    ],
    "sg:phone":"+1 214 442 1600",
    "sg:postcode":"75204",
    "sg:province":"TX",
    "sg:tags":[
        "television",
        "radio"
    ],
    "wof:name":"Foundation For Responsible TV",
    "wof:placetype":"venue"
},
  "geometry": {"coordinates":[-96.78683599999999,32.790611],"type":"Point"}
}