{
  "type": "Feature",
  "properties": {
    "iso:country":"US",
    "sg:address":"1901 Rodd Field Rd",
    "sg:city":"Corpus Christi",
    "sg:classifiers":[
        {
            "category":"Professional",
            "type":"Services"
        }
    ],
    "sg:phone":"+1 361 994 0216",
    "sg:postcode":"78412",
    "sg:province":"TX",
    "wof:name":"Designz By Fabulous",
    "wof:placetype":"venue"
},
  "geometry": {"coordinates":[-97.346496,27.685416],"type":"Point"}
}