{
  "type": "Feature",
  "properties": {
    "iso:country":"US",
    "sg:address":"907 Gardenia Ln",
    "sg:city":"Victoria",
    "sg:classifiers":[
        {
            "category":"Professional",
            "subcategory":"Management & Consulting",
            "type":"Services"
        }
    ],
    "sg:phone":"+1 361 576 2923",
    "sg:postcode":"77904",
    "sg:province":"TX",
    "sg:tags":[
        "retail",
        "direct",
        "sales"
    ],
    "wof:name":"Fun Parties",
    "wof:placetype":"venue"
},
  "geometry": {"coordinates":[-96.997743,28.840611],"type":"Point"}
}