{
  "type": "Feature",
  "properties": {
    "iso:country":"US",
    "sg:address":"3507 Mc Farlin Blvd",
    "sg:city":"Dallas",
    "sg:classifiers":[
        {
            "category":"Banks & Credit Unions",
            "subcategory":"Financial Services",
            "type":"Services"
        }
    ],
    "sg:phone":"+1 214 526 6118",
    "sg:postcode":"75205",
    "sg:province":"TX",
    "sg:tags":[
        "trust",
        "management"
    ],
    "wof:name":"Ruby Management Company",
    "wof:placetype":"venue"
},
  "geometry": {"coordinates":[-96.791038,32.843705],"type":"Point"}
}