{
  "type": "Feature",
  "properties": {
    "iso:country":"US",
    "sg:address":"1003 N Lynn St",
    "sg:city":"Gladewater",
    "sg:classifiers":[
        {
            "category":"Professional",
            "subcategory":"Computer Services",
            "type":"Services"
        }
    ],
    "sg:phone":"+1 903 806 8858",
    "sg:postcode":"75647",
    "sg:province":"TX",
    "sg:tags":[
        "graphic"
    ],
    "wof:name":"Hammerhead Web Design",
    "wof:placetype":"venue"
},
  "geometry": {"coordinates":[-94.926355,32.540001],"type":"Point"}
}