{
  "type": "Feature",
  "properties": {
    "iso:country":"US",
    "sg:address":"3527 Ponderosa Dr",
    "sg:city":"Grand Prairie",
    "sg:classifiers":[
        {
            "category":"Organizations",
            "subcategory":"Religious Organization",
            "type":"Services"
        }
    ],
    "sg:phone":"+1 972 660 8786",
    "sg:postcode":"75052",
    "sg:province":"TX",
    "wof:name":"Abundant Home Health LLC",
    "wof:placetype":"venue"
},
  "geometry": {"coordinates":[-97.03783199999999,32.685981],"type":"Point"}
}