{
  "type": "Feature",
  "properties": {
    "iso:country":"US",
    "sg:address":"2924 Findley Ave",
    "sg:city":"El Paso",
    "sg:classifiers":[
        {
            "category":"Building & Trades",
            "subcategory":"Construction",
            "type":"Services"
        }
    ],
    "sg:phone":"+1 915 751 2223",
    "sg:postcode":"79905",
    "sg:province":"TX",
    "wof:name":"Sevis Construction",
    "wof:placetype":"venue"
},
  "geometry": {"coordinates":[-106.460346,31.769274],"type":"Point"}
}