{
  "type": "Feature",
  "properties": {
    "iso:country":"US",
    "sg:address":"6919 Scyene Rd",
    "sg:city":"Dallas",
    "sg:classifiers":[
        {
            "category":"Personal",
            "subcategory":"Barber",
            "type":"Services"
        }
    ],
    "sg:phone":"+1 214 381 9626",
    "sg:postcode":"75227",
    "sg:province":"TX",
    "sg:tags":[
        "shop"
    ],
    "wof:name":"Fade",
    "wof:placetype":"venue"
},
  "geometry": {"coordinates":[-96.703198,32.763447],"type":"Point"}
}