{
  "type": "Feature",
  "properties": {
    "iso:country":"US",
    "sg:address":"912 S Stanton St",
    "sg:city":"El Paso",
    "sg:classifiers":[
        {
            "category":"Utilities",
            "subcategory":"Mobile Phone",
            "type":"Services"
        }
    ],
    "sg:phone":"+1 915 838 8885",
    "sg:postcode":"79901",
    "sg:province":"TX",
    "sg:tags":[
        "telephone",
        "cellular"
    ],
    "wof:name":"LA Pulga",
    "wof:placetype":"venue"
},
  "geometry": {"coordinates":[-106.483391,31.750725],"type":"Point"}
}