{
  "type": "Feature",
  "properties": {
    "iso:country":"US",
    "sg:address":"109 3rd Ave N",
    "sg:city":"Texas City",
    "sg:classifiers":[
        {
            "category":"Museum",
            "type":"Entertainment"
        },
        {
            "category":"Recreation",
            "type":"Entertainment"
        }
    ],
    "sg:phone":"+1 409 948 3805",
    "sg:postcode":"77590",
    "sg:province":"TX",
    "sg:tags":[
        "historical"
    ],
    "wof:name":"Davison House",
    "wof:placetype":"venue"
},
  "geometry": {"coordinates":[-94.896394,29.387056],"type":"Point"}
}