{
  "type": "Feature",
  "properties": {
    "iso:country":"US",
    "sg:address":"1500 W Airport Fwy",
    "sg:city":"Irving",
    "sg:classifiers":[
        {
            "category":"Utilities",
            "type":"Services"
        }
    ],
    "sg:phone":"+1 972 445 5555",
    "sg:postcode":"75062",
    "sg:province":"TX",
    "sg:tags":[
        "provider",
        "internet"
    ],
    "wof:name":"A T & T Broadband",
    "wof:placetype":"venue"
},
  "geometry": {"coordinates":[-96.964798,32.8368],"type":"Point"}
}