{
  "type": "Feature",
  "properties": {
    "iso:country":"US",
    "sg:address":"1302 N 2nd St",
    "sg:city":"Mcallen",
    "sg:classifiers":[
        {
            "category":"Retail",
            "subcategory":"Auto Repair",
            "type":"Services"
        }
    ],
    "sg:phone":"+1 956 581 0762",
    "sg:postcode":"78501",
    "sg:province":"TX",
    "sg:tags":[
        "recreational",
        "vehicle"
    ],
    "wof:name":"Juan Rivas Rv Repairs",
    "wof:placetype":"venue"
},
  "geometry": {"coordinates":[-98.218969,26.214802],"type":"Point"}
}