{
  "type": "Feature",
  "properties": {
    "iso:country":"US",
    "sg:address":"10215 Beechnut St",
    "sg:city":"Houston",
    "sg:classifiers":[
        {
            "category":"Real Estate",
            "subcategory":"Real Estate Operator",
            "type":"Services"
        }
    ],
    "sg:phone":"+1 281 495 7080",
    "sg:postcode":"77072",
    "sg:province":"TX",
    "sg:tags":[
        "building",
        "apartment"
    ],
    "wof:name":"Broadmoor Apartments The",
    "wof:placetype":"venue"
},
  "geometry": {"coordinates":[-95.558697,29.689536],"type":"Point"}
}