{
  "type": "Feature",
  "properties": {
    "iso:country":"US",
    "sg:address":"2135 Trishia Ln",
    "sg:city":"Red Oak",
    "sg:classifiers":[
        {
            "category":"Autos & Motor Vehicles",
            "subcategory":"Automobile Sales",
            "type":"Retail Goods"
        }
    ],
    "sg:phone":"+1 972 274 4498",
    "sg:postcode":"75154",
    "sg:province":"TX",
    "sg:tags":[
        "used"
    ],
    "wof:name":"Lazacks Used Auto Sales",
    "wof:placetype":"venue"
},
  "geometry": {"coordinates":[-96.852082,32.547648],"type":"Point"}
}