{
  "type": "Feature",
  "properties": {
    "iso:country":"US",
    "sg:address":"2220 Swallow Ln",
    "sg:city":"Lewisville",
    "sg:classifiers":[
        {
            "category":"Manufacturing",
            "subcategory":"Food",
            "type":"Manufacturing & Wholesale Goods"
        }
    ],
    "sg:phone":"+1 972 317 9011",
    "sg:postcode":"75077",
    "sg:province":"TX",
    "sg:tags":[
        "mfg",
        "potato"
    ],
    "wof:name":"Ye Old Honeycorn",
    "wof:placetype":"venue"
},
  "geometry": {"coordinates":[-97.032875,33.082383],"type":"Point"}
}