{
  "type": "Feature",
  "properties": {
    "iso:country":"US",
    "sg:address":"2410 US Hwy 77",
    "sg:city":"Harlingen",
    "sg:classifiers":[
        {
            "category":"Personal",
            "subcategory":"Beauty Salon",
            "type":"Services"
        }
    ],
    "sg:phone":"+1 956 412 9024",
    "sg:postcode":"78550",
    "sg:province":"TX",
    "sg:tags":[
        "shop"
    ],
    "wof:name":"Aleisah Beauty Salon",
    "wof:placetype":"venue"
},
  "geometry": {"coordinates":[-97.695865,26.169474],"type":"Point"}
}