{
  "type": "Feature",
  "properties": {
    "iso:country":"US",
    "sg:address":"1109 Bowie St",
    "sg:city":"Wellington",
    "sg:classifiers":[
        {
            "category":"Organizations",
            "subcategory":"Labor Organization",
            "type":"Services"
        }
    ],
    "sg:phone":"+1 806 447 5458",
    "sg:postcode":"79095",
    "sg:province":"TX",
    "wof:name":"Texas Farmers Union",
    "wof:placetype":"venue"
},
  "geometry": {"coordinates":[-100.216291,34.853087],"type":"Point"}
}