{
  "type": "Feature",
  "properties": {
    "iso:country":"US",
    "sg:address":"500 Cottonwood Pl",
    "sg:city":"Mc Kinney",
    "sg:classifiers":[
        {
            "category":"Professional",
            "type":"Services"
        }
    ],
    "sg:phone":"+1 972 562 1497",
    "sg:postcode":"75069",
    "sg:province":"TX",
    "wof:name":"Barr Barr & Associates",
    "wof:placetype":"venue"
},
  "geometry": {"coordinates":[-96.60941200000001,33.136968],"type":"Point"}
}