{
  "type": "Feature",
  "properties": {
    "iso:country":"US",
    "sg:address":"18723 W Cool Breeze Ln",
    "sg:city":"Montgomery",
    "sg:classifiers":[
        {
            "category":"Restaurant",
            "type":"Food & Drink"
        },
        {
            "category":"Ice Cream",
            "type":"Food & Drink"
        }
    ],
    "sg:phone":"+1 936 582 0352",
    "sg:postcode":"77356",
    "sg:province":"TX",
    "sg:tags":[
        "frozen",
        "dessert"
    ],
    "sg:website":"http://www.coldstonecreamery.com",
    "wof:name":"Cold Stone Creamery",
    "wof:placetype":"venue"
},
  "geometry": {"coordinates":[-95.654295,30.415151],"type":"Point"}
}