{
  "type": "Feature",
  "properties": {
    "iso:country":"US",
    "sg:address":"7134 Hwy 36",
    "sg:city":"Freeport",
    "sg:classifiers":[
        {
            "category":"Organizations",
            "subcategory":"Religious Organization",
            "type":"Services"
        }
    ],
    "sg:phone":"+1 979 233 4937",
    "sg:postcode":"77541",
    "sg:province":"TX",
    "wof:name":"Jones Creek Assembly Of God",
    "wof:placetype":"venue"
},
  "geometry": {"coordinates":[-95.456603,28.972625],"type":"Point"}
}