{
  "type": "Feature",
  "properties": {
    "iso:country":"US",
    "sg:address":"13418 Oak Hollow Dr",
    "sg:city":"Cypress",
    "sg:classifiers":[
        {
            "category":"Farming",
            "subcategory":"Farm & Veterinary Services",
            "type":"Manufacturing & Wholesale Goods"
        }
    ],
    "sg:phone":"+1 281 469 6571",
    "sg:postcode":"77429",
    "sg:province":"TX",
    "sg:tags":[
        "crop"
    ],
    "wof:name":"Imbc",
    "wof:placetype":"venue"
},
  "geometry": {"coordinates":[-95.594641,29.966725],"type":"Point"}
}