{
  "type": "Feature",
  "properties": {
    "iso:country":"US",
    "sg:address":"98 San Jacinto Blvd",
    "sg:city":"Austin",
    "sg:classifiers":[
        {
            "category":"Professional",
            "type":"Services"
        }
    ],
    "sg:phone":"+1 512 476 9363",
    "sg:postcode":"78701",
    "sg:province":"TX",
    "sg:tags":[
        "establishment"
    ],
    "wof:name":"Albert Reece Inc",
    "wof:placetype":"venue"
},
  "geometry": {"coordinates":[-97.742204,30.262407],"type":"Point"}
}