{
  "type": "Feature",
  "properties": {
    "iso:country":"US",
    "sg:address":"1216 Greenway Dr",
    "sg:city":"Mesquite",
    "sg:classifiers":[
        {
            "category":"Wholesale",
            "subcategory":"Farm Supplies",
            "type":"Manufacturing & Wholesale Goods"
        }
    ],
    "sg:phone":"+1 972 289 1880",
    "sg:postcode":"75149",
    "sg:province":"TX",
    "sg:tags":[
        "merchandise",
        "general"
    ],
    "wof:name":"Hartbar Equine Supply Co",
    "wof:placetype":"venue"
},
  "geometry": {"coordinates":[-96.588285,32.748961],"type":"Point"}
}