{
  "type": "Feature",
  "properties": {
    "iso:country":"US",
    "sg:address":"2501 Texas Ave S",
    "sg:city":"College Station",
    "sg:classifiers":[
        {
            "category":"Home & Garden",
            "subcategory":"Household Appliances",
            "type":"Retail Goods"
        }
    ],
    "sg:phone":"+1 979 695 9022",
    "sg:postcode":"77840",
    "sg:province":"TX",
    "wof:name":"Lacks Furniture Center",
    "wof:placetype":"venue"
},
  "geometry": {"coordinates":[-96.305503,30.604471],"type":"Point"}
}