{
  "type": "Feature",
  "properties": {
    "iso:country":"US",
    "sg:address":"494 Charleston Park",
    "sg:city":"Conroe",
    "sg:classifiers":[
        {
            "category":"Mining & Drilling",
            "type":"Manufacturing & Wholesale Goods"
        }
    ],
    "sg:phone":"+1 936 321 1811",
    "sg:postcode":"77302",
    "sg:province":"TX",
    "sg:tags":[
        "oil",
        "well"
    ],
    "wof:name":"Canova Royalty Company",
    "wof:placetype":"venue"
},
  "geometry": {"coordinates":[-95.447142,30.257923],"type":"Point"}
}