{
  "type": "Feature",
  "properties": {
    "iso:country":"US",
    "sg:address":"8070 Park Ln Ste 250",
    "sg:city":"Dallas",
    "sg:classifiers":[
        {
            "category":"Building & Trades",
            "subcategory":"Construction",
            "type":"Services"
        }
    ],
    "sg:phone":"+1 214 979 9050",
    "sg:postcode":"75231",
    "sg:province":"TX",
    "sg:tags":[
        "interior",
        "design"
    ],
    "wof:name":"Vivian-Nichols Associates Inc",
    "wof:placetype":"venue"
},
  "geometry": {"coordinates":[-96.767535,32.87192],"type":"Point"}
}