{
  "type": "Feature",
  "properties": {
    "iso:country":"US",
    "sg:address":"1504 N Greenville Ave",
    "sg:city":"Allen",
    "sg:classifiers":[
        {
            "category":"Insurance",
            "subcategory":"Insurance Agent",
            "type":"Services"
        }
    ],
    "sg:phone":"+1 972 678 3276",
    "sg:postcode":"75002",
    "sg:province":"TX",
    "wof:name":"State Farm Insurance",
    "wof:placetype":"venue"
},
  "geometry": {"coordinates":[-96.649512,33.121221],"type":"Point"}
}