{
  "type": "Feature",
  "properties": {
    "iso:country":"US",
    "sg:address":"1469 Huntsman St",
    "sg:city":"Orange",
    "sg:classifiers":[
        {
            "category":"Professional",
            "subcategory":"Accounting & Tax Preparation",
            "type":"Services"
        }
    ],
    "sg:phone":"+1 409 886 1714",
    "sg:postcode":"77632",
    "sg:province":"TX",
    "sg:tags":[
        "return",
        "filing"
    ],
    "wof:name":"Reliable Bookkeeping Services",
    "wof:placetype":"venue"
},
  "geometry": {"coordinates":[-93.76354499999999,30.156623],"type":"Point"}
}