{
  "type": "Feature",
  "properties": {
    "iso:country":"US",
    "sg:address":"6311 N O Connor Blvd",
    "sg:city":"Irving",
    "sg:classifiers":[
        {
            "category":"Utilities",
            "subcategory":"Telephone",
            "type":"Services"
        }
    ],
    "sg:phone":"+1 972 869 7646",
    "sg:postcode":"75039",
    "sg:province":"TX",
    "sg:tags":[
        "systems-wholesale",
        "equipment",
        "manufacturer"
    ],
    "wof:name":"Xel Communication",
    "wof:placetype":"venue"
},
  "geometry": {"coordinates":[-96.93777,32.894505],"type":"Point"}
}