{
  "type": "Feature",
  "properties": {
    "iso:country":"US",
    "sg:address":"Warehouse District 2nd St",
    "sg:city":"Austin",
    "sg:classifiers":[
        {
            "category":"Arts & Performance",
            "subcategory":"Art Gallery",
            "type":"Entertainment"
        }
    ],
    "sg:postcode":"78798",
    "sg:province":"TX",
    "wof:name":"Barkatecture",
    "wof:placetype":"venue"
},
  "geometry": {"coordinates":[-97.75651499999999,30.22306],"type":"Point"}
}