{
  "type": "Feature",
  "properties": {
    "iso:country":"US",
    "sg:address":"6 Hafer St",
    "sg:city":"Baytown",
    "sg:classifiers":[
        {
            "category":"Retail",
            "subcategory":"Repair Shop",
            "type":"Services"
        }
    ],
    "sg:phone":"+1 281 428 2723",
    "sg:postcode":"77520",
    "sg:province":"TX",
    "sg:tags":[
        "lock",
        "locksmith"
    ],
    "wof:name":"Brad's Wrecker Svc",
    "wof:placetype":"venue"
},
  "geometry": {"coordinates":[-94.961896,29.743639],"type":"Point"}
}