{
  "type": "Feature",
  "properties": {
    "iso:country":"US",
    "sg:address":"2338 Sandydale Ln",
    "sg:city":"Houston",
    "sg:classifiers":[
        {
            "category":"Wholesale",
            "subcategory":"Farm Supplies",
            "type":"Manufacturing & Wholesale Goods"
        }
    ],
    "sg:phone":"+1 281 449 9883",
    "sg:postcode":"77039",
    "sg:province":"TX",
    "wof:name":"Whiteacre Feed Inc",
    "wof:placetype":"venue"
},
  "geometry": {"coordinates":[-95.344782,29.906234],"type":"Point"}
}