{
  "type": "Feature",
  "properties": {
    "iso:country":"US",
    "sg:address":"2120 Crestmeadow St",
    "sg:city":"Denton",
    "sg:classifiers":[
        {
            "category":"Shopping",
            "subcategory":"Used Merchandise",
            "type":"Retail Goods"
        }
    ],
    "sg:phone":"+1 940 382 3383",
    "sg:postcode":"76207",
    "sg:province":"TX",
    "wof:name":"Red Shed Antiques",
    "wof:placetype":"venue"
},
  "geometry": {"coordinates":[-97.168036,33.236222],"type":"Point"}
}