{
  "type": "Feature",
  "properties": {
    "iso:country":"US",
    "sg:address":"203 Meador Ln",
    "sg:city":"Baytown",
    "sg:classifiers":[
        {
            "category":"Shopping",
            "subcategory":"Computers & Home Electronics",
            "type":"Retail Goods"
        }
    ],
    "sg:phone":"+1 281 424 1442",
    "sg:postcode":"77520",
    "sg:province":"TX",
    "sg:tags":[
        "system"
    ],
    "wof:name":"Innovative Home Concepts",
    "wof:placetype":"venue"
},
  "geometry": {"coordinates":[-95.03321099999999,29.771898],"type":"Point"}
}