{
  "type": "Feature",
  "properties": {
    "iso:country":"US",
    "sg:address":"2105 King St",
    "sg:city":"Greenville",
    "sg:classifiers":[
        {
            "category":"Shopping",
            "subcategory":"Clothing, Apparel, & Fashions",
            "type":"Retail Goods"
        }
    ],
    "sg:phone":"+1 903 454 0645",
    "sg:postcode":"75401",
    "sg:province":"TX",
    "sg:tags":[
        "apparel",
        "women's"
    ],
    "wof:name":"R&R Designs & Fashions",
    "wof:placetype":"venue"
},
  "geometry": {"coordinates":[-96.110929,33.142497],"type":"Point"}
}