{
  "type": "Feature",
  "properties": {
    "iso:country":"US",
    "sg:address":"12121 FM 306",
    "sg:city":"Canyon Lake",
    "sg:classifiers":[
        {
            "category":"Professional",
            "subcategory":"Advertising",
            "type":"Services"
        }
    ],
    "sg:phone":"+1 830 964 2728",
    "sg:postcode":"78133",
    "sg:province":"TX",
    "sg:tags":[
        "distribution"
    ],
    "wof:name":"Duke & Long Distr Co Inc",
    "wof:placetype":"venue"
},
  "geometry": {"coordinates":[-98.160493,29.862601],"type":"Point"}
}