{
  "type": "Feature",
  "properties": {
    "iso:country":"US",
    "sg:address":"1420 San Bernardo Ave",
    "sg:city":"Laredo",
    "sg:classifiers":[
        {
            "category":"Professional",
            "subcategory":"Lawyer & Legal Services",
            "type":"Services"
        }
    ],
    "sg:phone":"+1 956 726 1636",
    "sg:postcode":"78040",
    "sg:province":"TX",
    "wof:name":"Sergio Martinez Keko",
    "wof:placetype":"venue"
},
  "geometry": {"coordinates":[-99.504625,27.512276],"type":"Point"}
}