{
  "type": "Feature",
  "properties": {
    "iso:country":"US",
    "sg:address":"400 15th St",
    "sg:city":"Seagraves",
    "sg:classifiers":[
        {
            "category":"Education",
            "subcategory":"School",
            "type":"Public Place"
        }
    ],
    "sg:phone":"+1 806 387 2124",
    "sg:postcode":"79359",
    "sg:province":"TX",
    "sg:tags":[
        "k-",
        "private"
    ],
    "wof:name":"Seagraves Independent School District",
    "wof:placetype":"venue"
},
  "geometry": {"coordinates":[-102.571404,32.947361],"type":"Point"}
}