{
  "type": "Feature",
  "properties": {
    "iso:country":"US",
    "sg:address":"705 S Midkiff Rd",
    "sg:city":"Midland",
    "sg:classifiers":[
        {
            "category":"Utilities",
            "subcategory":"Refuse",
            "type":"Services"
        },
        {
            "category":"Utilities",
            "type":"Services"
        }
    ],
    "sg:phone":"+1 432 522 2424",
    "sg:postcode":"79701",
    "sg:province":"TX",
    "sg:tags":[
        "sanitary",
        "sanitation"
    ],
    "wof:name":"Fikes West Texas Inc",
    "wof:placetype":"venue"
},
  "geometry": {"coordinates":[-102.11299099999999,31.983013],"type":"Point"}
}