{
  "type": "Feature",
  "properties": {
    "iso:country":"US",
    "sg:address":"407 Garden Oaks Blvd",
    "sg:city":"Houston",
    "sg:classifiers":[
        {
            "category":"Retail",
            "subcategory":"Repair Shop",
            "type":"Services"
        }
    ],
    "sg:phone":"+1 713 694 3331",
    "sg:postcode":"77018",
    "sg:province":"TX",
    "sg:tags":[
        "equipment",
        "stereo"
    ],
    "wof:name":"JVC Svc & Engineering Co",
    "wof:placetype":"venue"
},
  "geometry": {"coordinates":[-95.405073,29.827046],"type":"Point"}
}