{
  "type": "Feature",
  "properties": {
    "iso:country":"US",
    "sg:address":"450 Elm St",
    "sg:city":"Graham",
    "sg:classifiers":[
        {
            "category":"Banks & Credit Unions",
            "subcategory":"Bank",
            "type":"Services"
        }
    ],
    "sg:phone":"+1 940 549 6207",
    "sg:postcode":"76450",
    "sg:province":"TX",
    "sg:tags":[
        "loan",
        "broker",
        "mortgage"
    ],
    "wof:name":"Allied Home Mrtg Capitl Corp",
    "wof:placetype":"venue"
},
  "geometry": {"coordinates":[-98.589613,33.108037],"type":"Point"}
}