{
  "type": "Feature",
  "properties": {
    "iso:country":"US",
    "sg:address":"2018 Chatsworth Rd",
    "sg:city":"Carrollton",
    "sg:classifiers":[
        {
            "category":"Shopping",
            "subcategory":"Clothing, Apparel, & Fashions",
            "type":"Retail Goods"
        }
    ],
    "sg:phone":"+1 972 492 2775",
    "sg:postcode":"75007",
    "sg:province":"TX",
    "wof:name":"Todays Products",
    "wof:placetype":"venue"
},
  "geometry": {"coordinates":[-96.875716,33.004303],"type":"Point"}
}