{
  "type": "Feature",
  "properties": {
    "iso:country":"US",
    "sg:address":"4325 N 23rd St",
    "sg:city":"Mcallen",
    "sg:classifiers":[
        {
            "category":"Professional",
            "subcategory":"Accounting & Tax Preparation",
            "type":"Services"
        }
    ],
    "sg:phone":"+1 956 994 9224",
    "sg:postcode":"78504",
    "sg:province":"TX",
    "sg:tags":[
        "bookkeeping",
        "billing"
    ],
    "wof:name":"All Stars",
    "wof:placetype":"venue"
},
  "geometry": {"coordinates":[-98.238804,26.244341],"type":"Point"}
}