{
  "type": "Feature",
  "properties": {
    "iso:country":"US",
    "sg:address":"3704 Yachtclub Dr",
    "sg:city":"Arlington",
    "sg:classifiers":[
        {
            "category":"Autos & Motor Vehicles",
            "subcategory":"Automobile Sales",
            "type":"Retail Goods"
        }
    ],
    "sg:phone":"+1 817 291 2708",
    "sg:postcode":"76016",
    "sg:province":"TX",
    "sg:tags":[
        "used"
    ],
    "wof:name":"Timeless Motor Cars Inc",
    "wof:placetype":"venue"
},
  "geometry": {"coordinates":[-97.21055200000001,32.688796],"type":"Point"}
}