{
  "type": "Feature",
  "properties": {
    "iso:country":"US",
    "sg:address":"17750 Highway 59 N",
    "sg:city":"Humble",
    "sg:classifiers":[
        {
            "category":"Real Estate",
            "subcategory":"Real Estate Services",
            "type":"Services"
        },
        {
            "category":"Real Estate",
            "subcategory":"Real Estate Operator",
            "type":"Services"
        }
    ],
    "sg:phone":"+1 281 446 8586",
    "sg:postcode":"77396",
    "sg:province":"TX",
    "sg:tags":[
        "apartment",
        "vacancy",
        "listing",
        "rental",
        "finder"
    ],
    "wof:name":"Deerbrook Forest Apartments",
    "wof:placetype":"venue"
},
  "geometry": {"coordinates":[-95.279006,29.976443],"type":"Point"}
}