{
  "type": "Feature",
  "properties": {
    "iso:country":"US",
    "sg:address":"30826 Sifton Dr",
    "sg:city":"Spring",
    "sg:classifiers":[
        {
            "category":"Real Estate",
            "subcategory":"Real Estate Agent",
            "type":"Services"
        }
    ],
    "sg:phone":"+1 281 292 2410",
    "sg:postcode":"77386",
    "sg:province":"TX",
    "wof:name":"Cliff Wren Realty",
    "wof:placetype":"venue"
},
  "geometry": {"coordinates":[-95.415668,30.13605],"type":"Point"}
}