{
  "type": "Feature",
  "properties": {
    "iso:country":"US",
    "sg:address":"6852 Alamo Downs Pkwy",
    "sg:city":"San Antonio",
    "sg:classifiers":[
        {
            "category":"Shopping",
            "subcategory":"Computers & Home Electronics",
            "type":"Retail Goods"
        }
    ],
    "sg:phone":"+1 210 521 3454",
    "sg:postcode":"78238",
    "sg:province":"TX",
    "sg:tags":[
        "software"
    ],
    "wof:name":"Sterling Software",
    "wof:placetype":"venue"
},
  "geometry": {"coordinates":[-98.620749,29.456082],"type":"Point"}
}