{
  "type": "Feature",
  "properties": {
    "iso:country":"US",
    "sg:address":"4780 Sweetwater Blvd",
    "sg:city":"Sugar Land",
    "sg:classifiers":[
        {
            "category":"Professional",
            "type":"Services"
        }
    ],
    "sg:phone":"+1 281 265 1800",
    "sg:postcode":"77479",
    "sg:province":"TX",
    "wof:name":"Audrey M Powell",
    "wof:placetype":"venue"
},
  "geometry": {"coordinates":[-95.63211099999999,29.586314],"type":"Point"}
}