{
  "type": "Feature",
  "properties": {
    "iso:country":"US",
    "sg:address":"3307 Cumberland Ave",
    "sg:city":"Wichita Falls",
    "sg:classifiers":[
        {
            "category":"Building & Trades",
            "subcategory":"Construction",
            "type":"Services"
        }
    ],
    "sg:phone":"+1 940 696 1873",
    "sg:postcode":"76309",
    "sg:province":"TX",
    "sg:tags":[
        "house",
        "nonresidential"
    ],
    "wof:name":"Gary Hart Construction",
    "wof:placetype":"venue"
},
  "geometry": {"coordinates":[-98.538484,33.889998],"type":"Point"}
}