{
  "type": "Feature",
  "properties": {
    "iso:country":"US",
    "sg:address":"3007 W Industrial Ave",
    "sg:city":"Midland",
    "sg:classifiers":[
        {
            "category":"Building & Trades",
            "subcategory":"Plumbing",
            "type":"Services"
        }
    ],
    "sg:phone":"+1 432 520 4322",
    "sg:postcode":"79701",
    "sg:province":"TX",
    "sg:tags":[
        "plumbing",
        "contractor"
    ],
    "wof:name":"Clayton Oldham Plumbing",
    "wof:placetype":"venue"
},
  "geometry": {"coordinates":[-102.10561300000001,31.979043],"type":"Point"}
}