{
  "type": "Feature",
  "properties": {
    "iso:country":"US",
    "sg:address":"16445 Addison Rd",
    "sg:city":"Addison",
    "sg:classifiers":[
        {
            "category":"Utilities",
            "subcategory":"Telephone",
            "type":"Services"
        },
        {
            "category":"Professional",
            "subcategory":"Computer Services",
            "type":"Services"
        }
    ],
    "sg:phone":"+1 972 930 8440",
    "sg:postcode":"75001",
    "sg:province":"TX",
    "sg:tags":[
        "communications",
        "internet"
    ],
    "wof:name":"Target Data",
    "wof:placetype":"venue"
},
  "geometry": {"coordinates":[-96.83034000000001,32.973816],"type":"Point"}
}