{
  "type": "Feature",
  "properties": {
    "iso:country":"US",
    "sg:address":"15657 Regian Dr",
    "sg:city":"Lindale",
    "sg:classifiers":[
        {
            "category":"Building & Trades",
            "subcategory":"Cleaning & Sanitation",
            "type":"Services"
        }
    ],
    "sg:phone":"+1 903 881 0224",
    "sg:postcode":"75771",
    "sg:province":"TX",
    "sg:tags":[
        "maintenance"
    ],
    "wof:name":"C&G Quality Cleaning Serv",
    "wof:placetype":"venue"
},
  "geometry": {"coordinates":[-95.42535599999999,32.494653],"type":"Point"}
}