{
  "type": "Feature",
  "properties": {
    "iso:country":"US",
    "sg:address":"1002 Country Lake Dr",
    "sg:city":"Richardson",
    "sg:classifiers":[
        {
            "category":"Professional",
            "subcategory":"Computer Services",
            "type":"Services"
        }
    ],
    "sg:phone":"+1 972 690 1909",
    "sg:postcode":"75006",
    "sg:province":"TX",
    "sg:tags":[
        "design",
        "system",
        "programing",
        "custom"
    ],
    "wof:name":"Florance & Assoc Consulting",
    "wof:placetype":"venue"
},
  "geometry": {"coordinates":[-96.857846,32.960182],"type":"Point"}
}