{
  "type": "Feature",
  "properties": {
    "iso:country":"US",
    "sg:address":"179 Dexter Dr",
    "sg:city":"San Antonio",
    "sg:classifiers":[
        {
            "category":"Shopping",
            "subcategory":"Musical Instruments",
            "type":"Retail Goods"
        }
    ],
    "sg:phone":"+1 210 436 2454",
    "sg:postcode":"78226",
    "sg:province":"TX",
    "wof:name":"Drumtalk Drums",
    "wof:placetype":"venue"
},
  "geometry": {"coordinates":[-98.559619,29.393867],"type":"Point"}
}