{
  "type": "Feature",
  "properties": {
    "iso:country":"US",
    "sg:address":"10004 Gulf Fwy",
    "sg:city":"Houston",
    "sg:classifiers":[
        {
            "category":"Shopping",
            "type":"Retail Goods"
        }
    ],
    "sg:phone":"+1 713 947 2027",
    "sg:postcode":"77034",
    "sg:province":"TX",
    "sg:tags":[
        "merchandise"
    ],
    "wof:name":"Global Choice Products In",
    "wof:placetype":"venue"
},
  "geometry": {"coordinates":[-95.24902,29.648104],"type":"Point"}
}