{
  "type": "Feature",
  "properties": {
    "iso:country":"US",
    "sg:address":"1709 Chaparral St",
    "sg:city":"Rockport",
    "sg:classifiers":[
        {
            "category":"Building & Trades",
            "subcategory":"Landscaping Services",
            "type":"Services"
        }
    ],
    "sg:phone":"+1 361 790 7895",
    "sg:postcode":"78382",
    "sg:province":"TX",
    "sg:tags":[
        "lawn",
        "maintenance",
        "grounds"
    ],
    "wof:name":"Exceptional Lawn & Garden Inc",
    "wof:placetype":"venue"
},
  "geometry": {"coordinates":[-97.05597,28.06594],"type":"Point"}
}