{
  "type": "Feature",
  "properties": {
    "iso:country":"US",
    "sg:address":"9800 Centre Pkwy Ste 860",
    "sg:city":"Houston",
    "sg:classifiers":[
        {
            "category":"Professional",
            "subcategory":"Lawyer & Legal Services",
            "type":"Services"
        }
    ],
    "sg:phone":"+1 713 270 4811",
    "sg:postcode":"77036",
    "sg:province":"TX",
    "wof:name":"Ellington Owen H Jr Atty",
    "wof:placetype":"venue"
},
  "geometry": {"coordinates":[-95.551102,29.673],"type":"Point"}
}