{
  "type": "Feature",
  "properties": {
    "iso:country":"US",
    "sg:address":"3606 Reagan St",
    "sg:city":"Houston",
    "sg:classifiers":[
        {
            "category":"Education",
            "subcategory":"Special Training",
            "type":"Public Place"
        }
    ],
    "sg:phone":"+1 713 864 4432",
    "sg:postcode":"77009",
    "sg:province":"TX",
    "sg:tags":[
        "tutoring"
    ],
    "wof:name":"Duplan Alice Claire Winslow",
    "wof:placetype":"venue"
},
  "geometry": {"coordinates":[-95.379293,29.79052],"type":"Point"}
}