{
  "type": "Feature",
  "properties": {
    "iso:country":"US",
    "sg:address":"16263 Rutley Cir",
    "sg:city":"Spring",
    "sg:classifiers":[
        {
            "category":"Retail",
            "subcategory":"Self-service Laundry",
            "type":"Services"
        }
    ],
    "sg:phone":"+1 281 370 5238",
    "sg:postcode":"77379",
    "sg:province":"TX",
    "sg:tags":[
        "laundries-self",
        "coin"
    ],
    "wof:name":"Laundry International",
    "wof:placetype":"venue"
},
  "geometry": {"coordinates":[-95.54360699999999,30.003947],"type":"Point"}
}