{
  "type": "Feature",
  "properties": {
    "iso:country":"US",
    "sg:address":"7300 Burnet Road",
    "sg:city":"Austin",
    "sg:classifiers":[
        {
            "category":"Home & Garden",
            "subcategory":"Furniture",
            "type":"Retail Goods"
        }
    ],
    "sg:phone":"+1 512 454 7365",
    "sg:postcode":"78757",
    "sg:province":"TX",
    "sg:tags":[
        "store"
    ],
    "wof:name":"The Sleep Shop",
    "wof:placetype":"venue"
},
  "geometry": {"coordinates":[-97.73509900000001,30.349035],"type":"Point"}
}