{
  "type": "Feature",
  "properties": {
    "iso:country":"US",
    "sg:address":"1111 Industrial Blvd",
    "sg:city":"Abilene",
    "sg:classifiers":[
        {
            "category":"Social Services",
            "type":"Services"
        }
    ],
    "sg:phone":"+1 325 691 2800",
    "sg:postcode":"79602",
    "sg:province":"TX",
    "wof:name":"Harmony Family Services Inc",
    "wof:placetype":"venue"
},
  "geometry": {"coordinates":[-99.737787,32.40123],"type":"Point"}
}