{
  "type": "Feature",
  "properties": {
    "iso:country":"US",
    "sg:address":"1401 Park St",
    "sg:city":"Laredo",
    "sg:classifiers":[
        {
            "category":"Professional",
            "type":"Services"
        }
    ],
    "sg:phone":"+1 956 718 2677",
    "sg:postcode":"78040",
    "sg:province":"TX",
    "wof:name":"Cubs & Tigers",
    "wof:placetype":"venue"
},
  "geometry": {"coordinates":[-99.51019100000001,27.517177],"type":"Point"}
}