{
  "type": "Feature",
  "properties": {
    "iso:country":"US",
    "sg:address":"2605 Twin Post Ct",
    "sg:city":"Irving",
    "sg:classifiers":[
        {
            "category":"Arts & Performance",
            "subcategory":"Theater",
            "type":"Entertainment"
        }
    ],
    "sg:phone":"+1 972 255 9356",
    "sg:postcode":"75062",
    "sg:province":"TX",
    "sg:tags":[
        "group"
    ],
    "wof:name":"Saxman Productions",
    "wof:placetype":"venue"
},
  "geometry": {"coordinates":[-96.955623,32.844154],"type":"Point"}
}