{
  "type": "Feature",
  "properties": {
    "iso:country":"US",
    "sg:address":"1919 Connorvale Rd",
    "sg:city":"Houston",
    "sg:classifiers":[
        {
            "category":"Building & Trades",
            "subcategory":"Construction",
            "type":"Services"
        }
    ],
    "sg:phone":"+1 281 442 7372",
    "sg:postcode":"77039",
    "sg:province":"TX",
    "sg:tags":[
        "preparation",
        "site",
        "contractor"
    ],
    "wof:name":"Americon Services Inc",
    "wof:placetype":"venue"
},
  "geometry": {"coordinates":[-95.356499,29.9097],"type":"Point"}
}