{
  "type": "Feature",
  "properties": {
    "iso:country":"US",
    "sg:address":"1200 Executive Dr E",
    "sg:city":"Richardson",
    "sg:classifiers":[
        {
            "category":"Shopping",
            "subcategory":"Computers & Home Electronics",
            "type":"Retail Goods"
        }
    ],
    "sg:phone":"+1 214 615 2302",
    "sg:postcode":"75081",
    "sg:province":"TX",
    "sg:tags":[
        "software"
    ],
    "wof:name":"Electronic Transaction Cnsltnt",
    "wof:placetype":"venue"
},
  "geometry": {"coordinates":[-96.710358,32.963034],"type":"Point"}
}