{
  "type": "Feature",
  "properties": {
    "iso:country":"US",
    "sg:address":"104 N Austin St",
    "sg:city":"Comanche",
    "sg:classifiers":[
        {
            "category":"Banks & Credit Unions",
            "subcategory":"Bank",
            "type":"Services"
        }
    ],
    "sg:phone":"+1 325 356 1616",
    "sg:postcode":"76442",
    "sg:province":"TX",
    "sg:tags":[
        "loan",
        "real estate"
    ],
    "wof:name":"Federal Land Bank Association",
    "wof:placetype":"venue"
},
  "geometry": {"coordinates":[-98.603797,31.898375],"type":"Point"}
}