{
  "type": "Feature",
  "properties": {
    "iso:country":"US",
    "sg:address":"8407 Battle Plains Dr",
    "sg:city":"Houston",
    "sg:classifiers":[
        {
            "category":"Food & Beverages",
            "subcategory":"Specialty",
            "type":"Retail Goods"
        }
    ],
    "sg:phone":"+1 713 466 8820",
    "sg:postcode":"77040",
    "sg:province":"TX",
    "wof:name":"Natures Health Solutions",
    "wof:placetype":"venue"
},
  "geometry": {"coordinates":[-95.52355300000001,29.882808],"type":"Point"}
}