{
  "type": "Feature",
  "properties": {
    "iso:country":"US",
    "sg:address":"6301 Gaston Ave",
    "sg:city":"Dallas",
    "sg:classifiers":[
        {
            "category":"Social Services",
            "type":"Services"
        }
    ],
    "sg:phone":"+1 214 821 8810",
    "sg:postcode":"75214",
    "sg:province":"TX",
    "wof:name":"The For Mothers Fathers",
    "wof:placetype":"venue"
},
  "geometry": {"coordinates":[-96.754621,32.812401],"type":"Point"}
}