{
  "type": "Feature",
  "properties": {
    "iso:country":"US",
    "sg:address":"3300 Chimney Rock Rd",
    "sg:city":"Houston",
    "sg:classifiers":[
        {
            "category":"Arts & Performance",
            "subcategory":"Arts Center",
            "type":"Entertainment"
        }
    ],
    "sg:phone":"+1 713 266 5982",
    "sg:postcode":"77056",
    "sg:province":"TX",
    "sg:tags":[
        "performing"
    ],
    "wof:name":"The Dance Place",
    "wof:placetype":"venue"
},
  "geometry": {"coordinates":[-95.476501,29.7302],"type":"Point"}
}