{
  "type": "Feature",
  "properties": {
    "iso:country":"US",
    "sg:address":"501 W California St",
    "sg:city":"Gainesville",
    "sg:classifiers":[
        {
            "category":"Restaurant",
            "type":"Food & Drink"
        }
    ],
    "sg:phone":"+1 940 668 0601",
    "sg:postcode":"76240",
    "sg:province":"TX",
    "sg:tags":[
        "eating"
    ],
    "wof:name":"Burger King",
    "wof:placetype":"venue"
},
  "geometry": {"coordinates":[-97.149017,33.624345],"type":"Point"}
}