{
  "type": "Feature",
  "properties": {
    "iso:country":"US",
    "sg:address":"3982 N Story Rd",
    "sg:city":"Irving",
    "sg:classifiers":[
        {
            "category":"Personal",
            "type":"Services"
        }
    ],
    "sg:phone":"+1 214 632 2276",
    "sg:postcode":"75038",
    "sg:province":"TX",
    "wof:name":"Two Brothers & A Hammer",
    "wof:placetype":"venue"
},
  "geometry": {"coordinates":[-96.97595699999999,32.860443],"type":"Point"}
}