{
  "type": "Feature",
  "properties": {
    "iso:country":"US",
    "sg:address":"1 State Hwy 16",
    "sg:city":"Helotes",
    "sg:classifiers":[
        {
            "category":"Building & Trades",
            "subcategory":"Electrical",
            "type":"Services"
        }
    ],
    "sg:phone":"+1 210 695 9242",
    "sg:postcode":"78023",
    "sg:province":"TX",
    "sg:tags":[
        "electric",
        "contractor"
    ],
    "wof:name":"Moore Lighting & Electrical",
    "wof:placetype":"venue"
},
  "geometry": {"coordinates":[-98.71064699999999,29.60655],"type":"Point"}
}