{
  "type": "Feature",
  "properties": {
    "iso:country":"US",
    "sg:address":"6123 Garth Rd",
    "sg:city":"Baytown",
    "sg:classifiers":[
        {
            "category":"Retail",
            "subcategory":"Funeral Services",
            "type":"Services"
        }
    ],
    "sg:phone":"+1 281 839 0700",
    "sg:postcode":"77521",
    "sg:province":"TX",
    "sg:tags":[
        "director"
    ],
    "wof:name":"L A Crespo Funeral Directors",
    "wof:placetype":"venue"
},
  "geometry": {"coordinates":[-94.980076,29.791328],"type":"Point"}
}