{
  "type": "Feature",
  "properties": {
    "iso:country":"US",
    "sg:address":"123 Rigdon St",
    "sg:city":"Borger",
    "sg:classifiers":[
        {
            "category":"Building & Trades",
            "subcategory":"Pest Control",
            "type":"Services"
        }
    ],
    "sg:phone":"+1 806 273 6113",
    "sg:postcode":"79007",
    "sg:province":"TX",
    "wof:name":"Bugs Burney Pest Control Co",
    "wof:placetype":"venue"
},
  "geometry": {"coordinates":[-101.37607300000001,35.655002],"type":"Point"}
}