{
  "type": "Feature",
  "properties": {
    "iso:country":"US",
    "sg:address":"3140 Commonwealth Dr",
    "sg:city":"Dallas",
    "sg:classifiers":[
        {
            "category":"Farming",
            "subcategory":"Vineyard",
            "type":"Manufacturing & Wholesale Goods"
        }
    ],
    "sg:phone":"+1 214 951 0700",
    "sg:postcode":"75247",
    "sg:province":"TX",
    "wof:name":"Vineyard Group",
    "wof:placetype":"venue"
},
  "geometry": {"coordinates":[-96.863866,32.809971],"type":"Point"}
}