{
  "type": "Feature",
  "properties": {
    "iso:country":"US",
    "sg:address":"3006 Ave G",
    "sg:city":"Hondo",
    "sg:classifiers":[
        {
            "category":"Local Transit",
            "type":"Transportation"
        }
    ],
    "sg:phone":"+1 830 426 5950",
    "sg:postcode":"78861",
    "sg:province":"TX",
    "sg:tags":[
        "passenger"
    ],
    "wof:name":"Community Ems Inc",
    "wof:placetype":"venue"
},
  "geometry": {"coordinates":[-99.135621,29.336812],"type":"Point"}
}