{
  "type": "Feature",
  "properties": {
    "iso:country":"US",
    "sg:address":"1116 W Parker Rd",
    "sg:city":"Plano",
    "sg:classifiers":[
        {
            "category":"Restaurant",
            "type":"Food & Drink"
        }
    ],
    "sg:phone":"+1 972 423 3434",
    "sg:postcode":"75075",
    "sg:province":"TX",
    "sg:tags":[
        "eating"
    ],
    "wof:name":"Jls Cajun Hut",
    "wof:placetype":"venue"
},
  "geometry": {"coordinates":[-96.717297,33.040835],"type":"Point"}
}