{
  "type": "Feature",
  "properties": {
    "iso:country":"US",
    "sg:address":"330 W Airport Fwy",
    "sg:city":"Irving",
    "sg:classifiers":[
        {
            "category":"Food & Beverages",
            "subcategory":"Meat & Fish",
            "type":"Retail Goods"
        }
    ],
    "sg:phone":"+1 972 554 6222",
    "sg:postcode":"75062",
    "sg:province":"TX",
    "wof:name":"Longhorn Sale",
    "wof:placetype":"venue"
},
  "geometry": {"coordinates":[-96.949275,32.83657],"type":"Point"}
}