{
  "type": "Feature",
  "properties": {
    "iso:country":"US",
    "sg:address":"4602 S Presa St",
    "sg:city":"San Antonio",
    "sg:classifiers":[
        {
            "category":"Restaurant",
            "type":"Food & Drink"
        }
    ],
    "sg:phone":"+1 210 531 3000",
    "sg:postcode":"78223",
    "sg:province":"TX",
    "sg:tags":[
        "parlor",
        "ice",
        "cream"
    ],
    "wof:name":"Good Humor Ice Cream",
    "wof:placetype":"venue"
},
  "geometry": {"coordinates":[-98.47526999999999,29.375521],"type":"Point"}
}