{
  "type": "Feature",
  "properties": {
    "iso:country":"US",
    "sg:address":"3818 Avenue H",
    "sg:city":"Rosenberg",
    "sg:classifiers":[
        {
            "category":"Autos & Motor Vehicles",
            "subcategory":"Auto Supplies",
            "type":"Retail Goods"
        },
        {
            "category":"Personal",
            "type":"Services"
        },
        {
            "category":"Retail",
            "subcategory":"Auto Repair",
            "type":"Services"
        }
    ],
    "sg:phone":"+1 281 344 0079",
    "sg:postcode":"77471",
    "sg:province":"TX",
    "sg:tags":[
        "body",
        "lettering",
        "automobile",
        "towing",
        "truck",
        "painting",
        "repairing"
    ],
    "wof:name":"Dan Wards Paint & Body Inc",
    "wof:placetype":"venue"
},
  "geometry": {"coordinates":[-95.788602,29.560092],"type":"Point"}
}