{
  "type": "Feature",
  "properties": {
    "iso:country":"US",
    "sg:address":"1502 E Airline Rd",
    "sg:city":"Victoria",
    "sg:classifiers":[
        {
            "category":"Bars & Pubs",
            "type":"Food & Drink"
        }
    ],
    "sg:phone":"+1 361 576 5945",
    "sg:postcode":"77901",
    "sg:province":"TX",
    "sg:tags":[
        "drinking"
    ],
    "wof:name":"Gilberts",
    "wof:placetype":"venue"
},
  "geometry": {"coordinates":[-96.990649,28.821236],"type":"Point"}
}