{
  "type": "Feature",
  "properties": {
    "iso:country":"US",
    "sg:address":"2626 E Front St",
    "sg:city":"Tyler",
    "sg:classifiers":[
        {
            "category":"Home & Garden",
            "subcategory":"Mobile Homes",
            "type":"Retail Goods"
        }
    ],
    "sg:phone":"+1 903 531 0379",
    "sg:postcode":"75702",
    "sg:province":"TX",
    "wof:name":"Universal Mobile Homes",
    "wof:placetype":"venue"
},
  "geometry": {"coordinates":[-95.268953,32.347515],"type":"Point"}
}