{
  "type": "Feature",
  "properties": {
    "iso:country":"US",
    "sg:address":"15308 Quinley Dr",
    "sg:city":"Austin",
    "sg:classifiers":[
        {
            "category":"Insurance",
            "subcategory":"Health Insurance",
            "type":"Services"
        }
    ],
    "sg:phone":"+1 512 215 8511",
    "sg:postcode":"78728",
    "sg:province":"TX",
    "sg:tags":[
        "maintenance"
    ],
    "wof:name":"Mcwhorter Technologies",
    "wof:placetype":"venue"
},
  "geometry": {"coordinates":[-97.687065,30.457441],"type":"Point"}
}