{
  "type": "Feature",
  "properties": {
    "iso:country":"US",
    "sg:address":"2636 Castanada Cir",
    "sg:city":"Fort Worth",
    "sg:classifiers":[
        {
            "category":"Insurance",
            "subcategory":"Insurance Agent",
            "type":"Services"
        }
    ],
    "sg:phone":"+1 817 429 7002",
    "sg:postcode":"76112",
    "sg:province":"TX",
    "wof:name":"P V Udeshi Financial Services",
    "wof:placetype":"venue"
},
  "geometry": {"coordinates":[-97.18373200000001,32.741008],"type":"Point"}
}