{
  "type": "Feature",
  "properties": {
    "iso:country":"US",
    "sg:address":"100 Co Rd 100",
    "sg:city":"Sweetwater",
    "sg:classifiers":[
        {
            "category":"Government",
            "subcategory":"Office",
            "type":"Public Place"
        }
    ],
    "sg:phone":"+1 325 235 3271",
    "sg:postcode":"79556",
    "sg:province":"TX",
    "sg:tags":[
        "county",
        "taxation"
    ],
    "wof:name":"Nolan County Tax Office",
    "wof:placetype":"venue"
},
  "geometry": {"coordinates":[-100.38189,32.391849],"type":"Point"}
}