{
  "type": "Feature",
  "properties": {
    "iso:country":"US",
    "sg:address":"1313 2nd St",
    "sg:city":"Floresville",
    "sg:classifiers":[
        {
            "category":"Shopping",
            "subcategory":"Hobbies, Toys, & Games",
            "type":"Retail Goods"
        }
    ],
    "sg:phone":"+1 830 393 1800",
    "sg:postcode":"78114",
    "sg:province":"TX",
    "wof:name":"Three Blind Mice",
    "wof:placetype":"venue"
},
  "geometry": {"coordinates":[-98.160258,29.133403],"type":"Point"}
}