{
  "type": "Feature",
  "properties": {
    "iso:country":"US",
    "sg:address":"18416 Kuykendahl Rd",
    "sg:city":"Spring",
    "sg:classifiers":[
        {
            "category":"Fast Food",
            "type":"Food & Drink"
        },
        {
            "category":"Restaurant",
            "type":"Food & Drink"
        }
    ],
    "sg:phone":"+1 281 350 0011",
    "sg:postcode":"77379",
    "sg:province":"TX",
    "sg:tags":[
        "take",
        "buffet",
        "pizza"
    ],
    "sg:website":"http://www.cicispizza.com",
    "wof:name":"CiCi's Pizza",
    "wof:placetype":"venue"
},
  "geometry": {"coordinates":[-95.48783,30.03935],"type":"Point"}
}