{
  "type": "Feature",
  "properties": {
    "iso:country":"US",
    "sg:address":"4100 Tanglewood Ln",
    "sg:city":"Odessa",
    "sg:classifiers":[
        {
            "category":"Manufacturing",
            "subcategory":"Toys & Sporting Goods",
            "type":"Manufacturing & Wholesale Goods"
        }
    ],
    "sg:phone":"+1 432 367 7110",
    "sg:postcode":"79762",
    "sg:province":"TX",
    "sg:tags":[
        "mfg"
    ],
    "wof:name":"Pennys Minis",
    "wof:placetype":"venue"
},
  "geometry": {"coordinates":[-102.34176600000001,31.89181],"type":"Point"}
}