{
  "type": "Feature",
  "properties": {
    "iso:country":"US",
    "sg:address":"322 Blueberry Ln",
    "sg:city":"Grand Prairie",
    "sg:classifiers":[
        {
            "category":"Freight",
            "type":"Transportation"
        }
    ],
    "sg:phone":"+1 972 262 1888",
    "sg:postcode":"75052",
    "sg:province":"TX",
    "sg:tags":[
        "delivery"
    ],
    "wof:name":"Texas Courier Svc",
    "wof:placetype":"venue"
},
  "geometry": {"coordinates":[-97.005145,32.7074],"type":"Point"}
}