{
  "type": "Feature",
  "properties": {
    "iso:country":"US",
    "sg:address":"12075 Denton Dr",
    "sg:city":"Dallas",
    "sg:classifiers":[
        {
            "category":"Manufacturing",
            "subcategory":"Tools & Machinery",
            "type":"Manufacturing & Wholesale Goods"
        },
        {
            "category":"Manufacturing",
            "subcategory":"Toys & Sporting Goods",
            "type":"Manufacturing & Wholesale Goods"
        }
    ],
    "sg:phone":"+1 972 241 9152",
    "sg:postcode":"75234",
    "sg:province":"TX",
    "sg:tags":[
        "engine",
        "supply",
        "mfg",
        "equipment",
        "electrical",
        "hobby",
        "model"
    ],
    "sg:website":"www.brisonaircraft.com",
    "wof:name":"Bison Aircraft",
    "wof:placetype":"venue"
},
  "geometry": {"coordinates":[-96.893477,32.911345],"type":"Point"}
}