{
  "type": "Feature",
  "properties": {
    "iso:country":"US",
    "sg:address":"2410 Ralph St",
    "sg:city":"Houston",
    "sg:classifiers":[
        {
            "category":"Retail",
            "subcategory":"Repair Shop",
            "type":"Services"
        }
    ],
    "sg:phone":"+1 713 528 6079",
    "sg:postcode":"77006",
    "sg:province":"TX",
    "wof:name":"Coverings An Upholstery",
    "wof:placetype":"venue"
},
  "geometry": {"coordinates":[-95.401357,29.743903],"type":"Point"}
}