{
  "type": "Feature",
  "properties": {
    "iso:country":"US",
    "sg:address":"2501 S W S Young Dr",
    "sg:city":"Killeen",
    "sg:classifiers":[
        {
            "category":"Shopping",
            "type":"Retail Goods"
        }
    ],
    "sg:phone":"+1 254 449 9140",
    "sg:postcode":"76542",
    "sg:province":"TX",
    "sg:tags":[
        "merchandise"
    ],
    "sg:website":"http://www.airandarmor.com",
    "wof:name":"Air & Armor",
    "wof:placetype":"venue"
},
  "geometry": {"coordinates":[-97.720296,31.089723],"type":"Point"}
}