{
  "type": "Feature",
  "properties": {
    "iso:country":"US",
    "sg:address":"903 W 9th St",
    "sg:city":"Houston",
    "sg:classifiers":[
        {
            "category":"Organizations",
            "subcategory":"Religious Organization",
            "type":"Services"
        }
    ],
    "sg:phone":"+1 713 862 6197",
    "sg:postcode":"77007",
    "sg:province":"TX",
    "sg:tags":[
        "church"
    ],
    "wof:name":"Jesucristo Es El Camino",
    "wof:placetype":"venue"
},
  "geometry": {"coordinates":[-95.406888,29.786934],"type":"Point"}
}