{
  "type": "Feature",
  "properties": {
    "iso:country":"US",
    "sg:address":"714 US Hwy 281",
    "sg:city":"Brownsville",
    "sg:classifiers":[
        {
            "category":"Restaurant",
            "type":"Food & Drink"
        }
    ],
    "sg:phone":"+1 956 546 0014",
    "sg:postcode":"78520",
    "sg:province":"TX",
    "wof:name":"Taqueria Y Antojito's Rico's",
    "wof:placetype":"venue"
},
  "geometry": {"coordinates":[-97.50899200000001,25.925547],"type":"Point"}
}