{
  "type": "Feature",
  "properties": {
    "iso:country":"US",
    "sg:address":"1403 Zora St",
    "sg:city":"Houston",
    "sg:classifiers":[
        {
            "category":"Building & Trades",
            "subcategory":"Landscaping Services",
            "type":"Services"
        }
    ],
    "sg:phone":"+1 713 681 3854",
    "sg:postcode":"77055",
    "sg:province":"TX",
    "wof:name":"Gus Landscaping",
    "wof:placetype":"venue"
},
  "geometry": {"coordinates":[-95.463559,29.797712],"type":"Point"}
}