{
  "type": "Feature",
  "properties": {
    "iso:country":"US",
    "sg:address":"8231 Gulfwood Ln",
    "sg:city":"Houston",
    "sg:classifiers":[
        {
            "category":"Organizations",
            "subcategory":"Religious Organization",
            "type":"Services"
        }
    ],
    "sg:phone":"+1 713 991 3841",
    "sg:postcode":"77075",
    "sg:province":"TX",
    "wof:name":"Awakening Ministries",
    "wof:placetype":"venue"
},
  "geometry": {"coordinates":[-95.27021000000001,29.60774],"type":"Point"}
}