{
  "type": "Feature",
  "properties": {
    "iso:country":"US",
    "sg:address":"9009 Glesby St",
    "sg:city":"Houston",
    "sg:classifiers":[
        {
            "category":"Manufacturing",
            "subcategory":"Rubber & Plastics",
            "type":"Manufacturing & Wholesale Goods"
        }
    ],
    "sg:phone":"+1 713 844 9700",
    "sg:postcode":"77029",
    "sg:province":"TX",
    "sg:tags":[
        "supply"
    ],
    "wof:name":"Goodall Rubber Co",
    "wof:placetype":"venue"
},
  "geometry": {"coordinates":[-95.267081,29.788559],"type":"Point"}
}