{
  "type": "Feature",
  "properties": {
    "iso:country":"US",
    "sg:address":"1516 John West Rd",
    "sg:city":"Dallas",
    "sg:classifiers":[
        {
            "category":"Retail",
            "subcategory":"Laundry & Dry Cleaning",
            "type":"Services"
        }
    ],
    "sg:phone":"+1 214 327 1984",
    "sg:postcode":"75228",
    "sg:province":"TX",
    "wof:name":"Bryant's One Hour Cleaners",
    "wof:placetype":"venue"
},
  "geometry": {"coordinates":[-96.690102,32.806801],"type":"Point"}
}