{
  "type": "Feature",
  "properties": {
    "iso:country":"US",
    "sg:address":"9413 Neils Thompson Road",
    "sg:city":"Austin",
    "sg:classifiers":[
        {
            "category":"Sports & Exercise",
            "subcategory":"Gym",
            "type":"Entertainment"
        }
    ],
    "sg:phone":"+1 512 665 6448",
    "sg:postcode":"78758",
    "sg:province":"TX",
    "sg:tags":[
        "trainer"
    ],
    "sg:website":"www.austinxfit.com",
    "wof:name":"Austin Executive Fitness",
    "wof:placetype":"venue"
},
  "geometry": {"coordinates":[-97.733216,30.382205],"type":"Point"}
}