{
  "type": "Feature",
  "properties": {
    "iso:country":"US",
    "sg:address":"5017 Conley Rd Ste A",
    "sg:city":"El Paso",
    "sg:classifiers":[
        {
            "category":"Health Services",
            "subcategory":"Doctor",
            "type":"Services"
        }
    ],
    "sg:phone":"+1 915 833 0303",
    "sg:postcode":"79932",
    "sg:province":"TX",
    "sg:tags":[
        "surgeon",
        "oral"
    ],
    "wof:name":"Henderson Robert E DDS",
    "wof:placetype":"venue"
},
  "geometry": {"coordinates":[-106.578003,31.841299],"type":"Point"}
}