{
  "type": "Feature",
  "properties": {
    "iso:country":"US",
    "sg:address":"11307 Forest Shower Rd",
    "sg:city":"San Antonio",
    "sg:classifiers":[
        {
            "category":"Social Services",
            "type":"Services"
        }
    ],
    "sg:phone":"+1 210 599 3053",
    "sg:postcode":"78233",
    "sg:province":"TX",
    "wof:name":"Woodcrest HM For Snior Ctizens",
    "wof:placetype":"venue"
},
  "geometry": {"coordinates":[-98.350707,29.542183],"type":"Point"}
}