{
  "type": "Feature",
  "properties": {
    "iso:country":"US",
    "sg:address":"806 Bomar St",
    "sg:city":"Houston",
    "sg:classifiers":[
        {
            "category":"Professional",
            "type":"Services"
        }
    ],
    "sg:phone":"+1 713 523 0986",
    "sg:postcode":"77006",
    "sg:province":"TX",
    "wof:name":"Desgin Concepts International",
    "wof:placetype":"venue"
},
  "geometry": {"coordinates":[-95.390439,29.751576],"type":"Point"}
}