{
  "type": "Feature",
  "properties": {
    "iso:country":"US",
    "sg:address":"1601 S 7th St",
    "sg:city":"Corsicana",
    "sg:classifiers":[
        {
            "category":"Retail",
            "subcategory":"Auto Repair",
            "type":"Services"
        }
    ],
    "sg:phone":"+1 903 874 2011",
    "sg:postcode":"75110",
    "sg:province":"TX",
    "sg:tags":[
        "automotive"
    ],
    "wof:name":"A 1 Towing & Recovery",
    "wof:placetype":"venue"
},
  "geometry": {"coordinates":[-96.45259799999999,32.084345],"type":"Point"}
}