{
  "type": "Feature",
  "properties": {
    "iso:country":"US",
    "sg:address":"20623 Wild Springs Dr",
    "sg:city":"San Antonio",
    "sg:classifiers":[
        {
            "category":"Shopping",
            "subcategory":"Clothing, Apparel, & Fashions",
            "type":"Retail Goods"
        }
    ],
    "sg:phone":"+1 210 497 7400",
    "sg:postcode":"78258",
    "sg:province":"TX",
    "wof:name":"Meltons Unlimted",
    "wof:placetype":"venue"
},
  "geometry": {"coordinates":[-98.458444,29.635661],"type":"Point"}
}