{
  "type": "Feature",
  "properties": {
    "iso:country":"US",
    "sg:address":"3619 Peggys Pl",
    "sg:city":"Tyler",
    "sg:classifiers":[
        {
            "category":"Health Services",
            "subcategory":"Doctor",
            "type":"Services"
        }
    ],
    "sg:phone":"+1 903 561 3619",
    "sg:postcode":"75701",
    "sg:province":"TX",
    "sg:tags":[
        "physician",
        "family",
        "practice",
        "surgeons",
        "medicine"
    ],
    "wof:name":"Brent R. Harris, M.D., P.A.",
    "wof:placetype":"venue"
},
  "geometry": {"coordinates":[-95.306862,32.308766],"type":"Point"}
}