{
  "type": "Feature",
  "properties": {
    "iso:country":"US",
    "sg:address":"5727 Westheimer Rd Ste G",
    "sg:city":"Houston",
    "sg:classifiers":[
        {
            "category":"Insurance",
            "subcategory":"Insurance Agent",
            "type":"Services"
        },
        {
            "category":"Insurance",
            "subcategory":"Hazard Insurance",
            "type":"Services"
        }
    ],
    "sg:phone":"+1 713 789 1080",
    "sg:postcode":"77057",
    "sg:province":"TX",
    "sg:tags":[
        "auto",
        "commercial",
        "business"
    ],
    "sg:website":"http://www.789auto.com",
    "wof:name":"Auto Insurance Discounters, Inc.",
    "wof:placetype":"venue"
},
  "geometry": {"coordinates":[-95.478105,29.737892],"type":"Point"}
}