{
  "type": "Feature",
  "properties": {
    "iso:country":"US",
    "sg:address":"11451 Jones Maltsberger Rd",
    "sg:city":"San Antonio",
    "sg:classifiers":[
        {
            "category":"Wholesale",
            "subcategory":"Machinery & Supplies",
            "type":"Manufacturing & Wholesale Goods"
        }
    ],
    "sg:phone":"+1 210 491 9521",
    "sg:postcode":"78216",
    "sg:province":"TX",
    "sg:tags":[
        "machine",
        "shredding",
        "paper"
    ],
    "sg:website":"www.texasshredder.com",
    "wof:name":"Texas Shredder Parts",
    "wof:placetype":"venue"
},
  "geometry": {"coordinates":[-98.476383,29.544328],"type":"Point"}
}