{
  "type": "Feature",
  "properties": {
    "iso:country":"US",
    "sg:address":"4700 SW Loop 820",
    "sg:city":"Fort Worth",
    "sg:classifiers":[
        {
            "category":"Restaurant",
            "type":"Food & Drink"
        }
    ],
    "sg:menulink":"http://www.allmenus.com/tx/fort-worth/14093-olive-garden-italian-restaurant/menu/",
    "sg:phone":"+1 817 377 8091",
    "sg:postcode":"76109",
    "sg:province":"TX",
    "sg:tags":[
        "italian"
    ],
    "wof:name":"Olive Garden Italian Restaurant",
    "wof:placetype":"venue"
},
  "geometry": {"coordinates":[-97.396152,32.682647],"type":"Point"}
}