{
  "type": "Feature",
  "properties": {
    "iso:country":"US",
    "sg:address":"1754 W Loop 281",
    "sg:city":"Longview",
    "sg:classifiers":[
        {
            "category":"Retail",
            "subcategory":"Photofinishing",
            "type":"Services"
        },
        {
            "category":"Shopping",
            "subcategory":"Pharmacy",
            "type":"Retail Goods"
        }
    ],
    "sg:phone":"+1 903 759 3816",
    "sg:postcode":"75604",
    "sg:province":"TX",
    "sg:tags":[
        "photo",
        "finishing",
        "first",
        "aid",
        "supply"
    ],
    "sg:website":"http://www.cvs.com",
    "wof:name":"CVS/pharmacy",
    "wof:placetype":"venue"
},
  "geometry": {"coordinates":[-94.782116,32.524999],"type":"Point"}
}