{
  "type": "Feature",
  "properties": {
    "iso:country":"US",
    "sg:address":"6202 Bellwood St",
    "sg:city":"San Antonio",
    "sg:classifiers":[
        {
            "category":"Shopping",
            "subcategory":"Hobbies, Toys, & Games",
            "type":"Retail Goods"
        }
    ],
    "sg:phone":"+1 210 699 6202",
    "sg:postcode":"78249",
    "sg:province":"TX",
    "wof:name":"R&S Ltd",
    "wof:placetype":"venue"
},
  "geometry": {"coordinates":[-98.60823600000001,29.55349],"type":"Point"}
}