{
  "type": "Feature",
  "properties": {
    "iso:country":"US",
    "sg:address":"9809 Fredericksburg Rd",
    "sg:city":"San Antonio",
    "sg:classifiers":[
        {
            "category":"Autos & Motor Vehicles",
            "subcategory":"Auto Supplies",
            "type":"Retail Goods"
        },
        {
            "category":"Wholesale",
            "subcategory":"Auto Parts",
            "type":"Manufacturing & Wholesale Goods"
        }
    ],
    "sg:phone":"+1 210 697 5863",
    "sg:postcode":"78240",
    "sg:province":"TX",
    "sg:tags":[
        "automobile"
    ],
    "wof:name":"Full Service Auto Parts Inc",
    "wof:placetype":"venue"
},
  "geometry": {"coordinates":[-98.578318,29.537327],"type":"Point"}
}