{
  "type": "Feature",
  "properties": {
    "iso:country":"US",
    "sg:address":"903 S McDonald St",
    "sg:city":"Mc Kinney",
    "sg:classifiers":[
        {
            "category":"Retail",
            "subcategory":"Auto Repair",
            "type":"Services"
        }
    ],
    "sg:phone":"+1 972 548 0551",
    "sg:postcode":"75069",
    "sg:province":"TX",
    "sg:tags":[
        "automobile",
        "top",
        "upholstery",
        "upholstering"
    ],
    "wof:name":"Arnold's Auto Upholstery",
    "wof:placetype":"venue"
},
  "geometry": {"coordinates":[-96.613373,33.188223],"type":"Point"}
}