{
  "type": "Feature",
  "properties": {
    "iso:country":"US",
    "sg:address":"3198 FM 521",
    "sg:city":"Brazoria",
    "sg:classifiers":[
        {
            "category":"Wholesale",
            "subcategory":"Construction Materials",
            "type":"Manufacturing & Wholesale Goods"
        }
    ],
    "sg:phone":"+1 979 798 7263",
    "sg:postcode":"77422",
    "sg:province":"TX",
    "wof:name":"Ellis Enterprises",
    "wof:placetype":"venue"
},
  "geometry": {"coordinates":[-95.584092,29.011675],"type":"Point"}
}