{
  "type": "Feature",
  "properties": {
    "iso:country":"US",
    "sg:address":"1545 W Mockingbird Ln Ste 5020",
    "sg:city":"Dallas",
    "sg:classifiers":[
        {
            "category":"Professional",
            "subcategory":"Lawyer & Legal Services",
            "type":"Services"
        }
    ],
    "sg:phone":"+1 903 232 1774",
    "sg:postcode":"75235",
    "sg:province":"TX",
    "wof:name":"Smith Gerald J",
    "wof:placetype":"venue"
},
  "geometry": {"coordinates":[-96.86057,32.822432],"type":"Point"}
}