{
  "type": "Feature",
  "properties": {
    "iso:country":"US",
    "sg:address":"1201 Shannon Ln",
    "sg:city":"Longview",
    "sg:classifiers":[
        {
            "category":"Professional",
            "subcategory":"Business Services",
            "type":"Services"
        }
    ],
    "sg:phone":"+1 903 297 3853",
    "sg:postcode":"75604",
    "sg:province":"TX",
    "wof:name":"Blsh Partners",
    "wof:placetype":"venue"
},
  "geometry": {"coordinates":[-94.765991,32.529534],"type":"Point"}
}