{
  "type": "Feature",
  "properties": {
    "iso:country":"US",
    "sg:address":"1204 Parkrow Pl",
    "sg:city":"Irving",
    "sg:classifiers":[
        {
            "category":"Real Estate",
            "subcategory":"Surveying",
            "type":"Services"
        }
    ],
    "sg:phone":"+1 972 313 0344",
    "sg:postcode":"75060",
    "sg:province":"TX",
    "wof:name":"Bailey Land Surveying",
    "wof:placetype":"venue"
},
  "geometry": {"coordinates":[-96.98074800000001,32.801625],"type":"Point"}
}