{
  "type": "Feature",
  "properties": {
    "iso:country":"US",
    "sg:address":"3803 Southwest Blvd",
    "sg:city":"Fort Worth",
    "sg:classifiers":[
        {
            "category":"Restaurant",
            "type":"Food & Drink"
        }
    ],
    "sg:phone":"+1 817 735 9988",
    "sg:postcode":"76116",
    "sg:province":"TX",
    "sg:tags":[
        "eating"
    ],
    "wof:name":"Mirandas Mexican Food",
    "wof:placetype":"venue"
},
  "geometry": {"coordinates":[-97.44157800000001,32.716447],"type":"Point"}
}