{
  "type": "Feature",
  "properties": {
    "iso:country":"US",
    "sg:address":"197 Floyd Wingo Dr",
    "sg:city":"Kilgore",
    "sg:classifiers":[
        {
            "category":"Professional",
            "subcategory":"Lawyer & Legal Services",
            "type":"Services"
        }
    ],
    "sg:phone":"+1 903 988 0609",
    "sg:postcode":"75662",
    "sg:province":"TX",
    "sg:tags":[
        "attorney",
        "criminal",
        "law"
    ],
    "wof:name":"Criminal Justice Center",
    "wof:placetype":"venue"
},
  "geometry": {"coordinates":[-94.845477,32.438959],"type":"Point"}
}