{
  "type": "Feature",
  "properties": {
    "iso:country":"US",
    "sg:address":"3557 E Highway 34",
    "sg:city":"Ennis",
    "sg:classifiers":[
        {
            "category":"Restaurant",
            "type":"Food & Drink"
        }
    ],
    "sg:phone":"+1 972 875 9918",
    "sg:postcode":"75119",
    "sg:province":"TX",
    "sg:tags":[
        "house",
        "steak",
        "barbecue"
    ],
    "wof:name":"Squeeze In Bbq",
    "wof:placetype":"venue"
},
  "geometry": {"coordinates":[-96.56780000000001,32.364357],"type":"Point"}
}