{
  "type": "Feature",
  "properties": {
    "iso:country":"US",
    "sg:address":"5434 Burnet Rd",
    "sg:city":"Austin",
    "sg:classifiers":[
        {
            "category":"Bars & Pubs",
            "type":"Food & Drink"
        }
    ],
    "sg:phone":"+1 512 458 1813",
    "sg:postcode":"78756",
    "sg:province":"TX",
    "sg:tags":[
        "drinking"
    ],
    "wof:name":"Little Longhorn Saloon",
    "wof:placetype":"venue"
},
  "geometry": {"coordinates":[-97.739951,30.329883],"type":"Point"}
}