{
  "type": "Feature",
  "properties": {
    "iso:country":"US",
    "sg:address":"3810 Harvey Rd",
    "sg:city":"College Station",
    "sg:classifiers":[
        {
            "category":"Manufacturing",
            "subcategory":"Signs",
            "type":"Manufacturing & Wholesale Goods"
        }
    ],
    "sg:phone":"+1 979 774 9191",
    "sg:postcode":"77845",
    "sg:province":"TX",
    "wof:name":"Price Traffic Products",
    "wof:placetype":"venue"
},
  "geometry": {"coordinates":[-96.288792,30.64402],"type":"Point"}
}