{
  "type": "Feature",
  "properties": {
    "iso:country":"US",
    "sg:address":"16708 San Luis Pass Rd",
    "sg:city":"Galveston",
    "sg:classifiers":[
        {
            "category":"Personal",
            "subcategory":"Tanning Parlor",
            "type":"Services"
        }
    ],
    "sg:phone":"+1 409 632 9200",
    "sg:postcode":"77554",
    "sg:province":"TX",
    "sg:tags":[
        "salon"
    ],
    "wof:name":"Jamaica Me Sweat",
    "wof:placetype":"venue"
},
  "geometry": {"coordinates":[-94.97276599999999,29.182989],"type":"Point"}
}