{
  "type": "Feature",
  "properties": {
    "iso:country":"US",
    "sg:address":"810 Hwy 3 N",
    "sg:city":"League City",
    "sg:classifiers":[
        {
            "category":"Autos & Motor Vehicles",
            "subcategory":"Automobile Sales",
            "type":"Retail Goods"
        }
    ],
    "sg:phone":"+1 281 316 3303",
    "sg:postcode":"77573",
    "sg:province":"TX",
    "wof:name":"Petes Auto Sales",
    "wof:placetype":"venue"
},
  "geometry": {"coordinates":[-95.099785,29.512607],"type":"Point"}
}