{
  "type": "Feature",
  "properties": {
    "iso:country":"US",
    "sg:address":"1525 Capital Dr",
    "sg:city":"Carrollton",
    "sg:classifiers":[
        {
            "category":"Professional",
            "subcategory":"Business Services",
            "type":"Services"
        }
    ],
    "sg:phone":"+1 972 446 1303",
    "sg:postcode":"75006",
    "sg:province":"TX",
    "sg:tags":[
        "program",
        "award"
    ],
    "wof:name":"Your Buying Network",
    "wof:placetype":"venue"
},
  "geometry": {"coordinates":[-96.919336,32.956557],"type":"Point"}
}