{
  "type": "Feature",
  "properties": {
    "iso:country":"US",
    "sg:address":"1107 Bert Dr",
    "sg:city":"Arlington",
    "sg:classifiers":[
        {
            "category":"Organizations",
            "subcategory":"Community Association",
            "type":"Services"
        }
    ],
    "sg:phone":"+1 817 461 7575",
    "sg:postcode":"76012",
    "sg:province":"TX",
    "sg:tags":[
        "real estate"
    ],
    "wof:name":"Wellington Realty",
    "wof:placetype":"venue"
},
  "geometry": {"coordinates":[-97.122799,32.773382],"type":"Point"}
}