{
  "type": "Feature",
  "properties": {
    "iso:country":"US",
    "sg:address":"5919 S Gessner Dr",
    "sg:city":"Houston",
    "sg:classifiers":[
        {
            "category":"Food & Beverages",
            "subcategory":"Groceries & Convenience Stores",
            "type":"Retail Goods"
        }
    ],
    "sg:phone":"+1 713 776 2706",
    "sg:postcode":"77036",
    "sg:province":"TX",
    "wof:name":"S Gessner Convenience Store",
    "wof:placetype":"venue"
},
  "geometry": {"coordinates":[-95.538696,29.715099],"type":"Point"}
}