{
  "type": "Feature",
  "properties": {
    "iso:country":"US",
    "sg:address":"2030 Woodland Valley Dr",
    "sg:city":"Humble",
    "sg:classifiers":[
        {
            "category":"Professional",
            "type":"Services"
        }
    ],
    "sg:phone":"+1 281 359 0011",
    "sg:postcode":"77339",
    "sg:province":"TX",
    "wof:name":"Cqtek",
    "wof:placetype":"venue"
},
  "geometry": {"coordinates":[-95.22335,30.035933],"type":"Point"}
}