{
  "type": "Feature",
  "properties": {
    "iso:country":"US",
    "sg:address":"2110 Forest Grove Estates Rd",
    "sg:city":"Allen",
    "sg:classifiers":[
        {
            "category":"Building & Trades",
            "subcategory":"Construction",
            "type":"Services"
        }
    ],
    "sg:phone":"+1 972 562 9038",
    "sg:postcode":"75002",
    "sg:province":"TX",
    "sg:tags":[
        "general",
        "contractor"
    ],
    "wof:name":"Hedgcoxe Construction Inc",
    "wof:placetype":"venue"
},
  "geometry": {"coordinates":[-96.61976,33.120424],"type":"Point"}
}