{
  "type": "Feature",
  "properties": {
    "iso:country":"US",
    "sg:address":"511 Co Rd 27",
    "sg:city":"Prosper",
    "sg:classifiers":[
        {
            "category":"Home & Garden",
            "subcategory":"Building Materials",
            "type":"Retail Goods"
        }
    ],
    "sg:phone":"+1 972 346 2701",
    "sg:postcode":"75078",
    "sg:province":"TX",
    "sg:tags":[
        "mixed",
        "concrete"
    ],
    "sg:website":"www.southernstar.com",
    "wof:name":"Southern Star",
    "wof:placetype":"venue"
},
  "geometry": {"coordinates":[-96.81970800000001,33.228151],"type":"Point"}
}