{
  "type": "Feature",
  "properties": {
    "iso:country":"US",
    "sg:address":"3500 Gaston Ave",
    "sg:city":"Dallas",
    "sg:classifiers":[
        {
            "category":"Education",
            "subcategory":"University",
            "type":"Public Place"
        },
        {
            "category":"Community Center",
            "type":"Public Place"
        }
    ],
    "sg:phone":"+1 214 820 3433",
    "sg:postcode":"75246",
    "sg:province":"TX",
    "sg:tags":[
        "medical",
        "college"
    ],
    "wof:name":"Sammons Cancer Ctr of Baylor University Medicl Ctr",
    "wof:placetype":"venue"
},
  "geometry": {"coordinates":[-96.78089900000001,32.790501],"type":"Point"}
}