{
  "type": "Feature",
  "properties": {
    "iso:country":"US",
    "sg:address":"4201 Bee Cave Rd Ste B210",
    "sg:city":"West Lake Hills",
    "sg:classifiers":[
        {
            "category":"Health Services",
            "subcategory":"Dentist",
            "type":"Services"
        }
    ],
    "sg:phone":"+1 512 328 0911",
    "sg:postcode":"78746",
    "sg:province":"TX",
    "sg:website":"www.davidabaker.net",
    "wof:name":"Family Dental Care - David A Baker, DDS",
    "wof:placetype":"venue"
},
  "geometry": {"coordinates":[-97.812382,30.284343],"type":"Point"}
}