{
  "type": "Feature",
  "properties": {
    "iso:country":"US",
    "sg:address":"8402 State Hwy 6",
    "sg:city":"Woodway",
    "sg:classifiers":[
        {
            "category":"Professional",
            "subcategory":"Business Services",
            "type":"Services"
        }
    ],
    "sg:phone":"+1 254 848 7377",
    "sg:postcode":"76712",
    "sg:province":"TX",
    "sg:tags":[
        "repossessing"
    ],
    "wof:name":"American Lenders Svc Co",
    "wof:placetype":"venue"
},
  "geometry": {"coordinates":[-97.30303000000001,31.580114],"type":"Point"}
}