{
  "type": "Feature",
  "properties": {
    "iso:country":"US",
    "sg:address":"690 E Lamar Blvd",
    "sg:city":"Arlington",
    "sg:classifiers":[
        {
            "category":"Insurance",
            "subcategory":"Insurance Agent",
            "type":"Services"
        }
    ],
    "sg:phone":"+1 817 633 4007",
    "sg:postcode":"76011",
    "sg:province":"TX",
    "sg:tags":[
        "broker"
    ],
    "wof:name":"USG Insurance Service Inc",
    "wof:placetype":"venue"
},
  "geometry": {"coordinates":[-97.104895,32.762818],"type":"Point"}
}