{
  "type": "Feature",
  "properties": {
    "iso:country":"US",
    "sg:address":"901 S Coit Rd",
    "sg:city":"Richardson",
    "sg:classifiers":[
        {
            "category":"Professional",
            "type":"Services"
        }
    ],
    "sg:phone":"+1 972 690 3426",
    "sg:postcode":"75080",
    "sg:province":"TX",
    "wof:name":"William Raddatz",
    "wof:placetype":"venue"
},
  "geometry": {"coordinates":[-96.76901599999999,32.943557],"type":"Point"}
}