{
  "type": "Feature",
  "properties": {
    "iso:country":"US",
    "sg:address":"1231 Greenway Dr Ste 100",
    "sg:city":"Irving",
    "sg:classifiers":[
        {
            "category":"Education",
            "subcategory":"Special Training",
            "type":"Public Place"
        }
    ],
    "sg:phone":"+1 972 580 3435",
    "sg:postcode":"75038",
    "sg:province":"TX",
    "sg:tags":[
        "school",
        "language"
    ],
    "wof:name":"Berlitz Language Centers",
    "wof:placetype":"venue"
},
  "geometry": {"coordinates":[-96.96639999999999,32.889599],"type":"Point"}
}