{
  "type": "Feature",
  "properties": {
    "iso:country":"US",
    "sg:address":"208 E Goliad Ave",
    "sg:city":"Crockett",
    "sg:classifiers":[
        {
            "category":"Professional",
            "type":"Services"
        }
    ],
    "sg:phone":"+1 936 545 2467",
    "sg:postcode":"75835",
    "sg:province":"TX",
    "sg:tags":[
        "restaurant"
    ],
    "wof:name":"Tchoupitoulas",
    "wof:placetype":"venue"
},
  "geometry": {"coordinates":[-95.459534,31.317626],"type":"Point"}
}