{
  "type": "Feature",
  "properties": {
    "iso:country":"US",
    "sg:address":"238 Castle Pne",
    "sg:city":"Kerrville",
    "sg:classifiers":[
        {
            "category":"Banks & Credit Unions",
            "subcategory":"Financial Services",
            "type":"Services"
        }
    ],
    "sg:phone":"+1 830 896 1469",
    "sg:postcode":"78028",
    "sg:province":"TX",
    "sg:tags":[
        "management",
        "investment"
    ],
    "wof:name":"Fred A Scaggs Investments",
    "wof:placetype":"venue"
},
  "geometry": {"coordinates":[-99.13916999999999,30.010175],"type":"Point"}
}