{
  "type": "Feature",
  "properties": {
    "iso:country":"US",
    "sg:address":"5715 Peek Rd",
    "sg:city":"Katy",
    "sg:classifiers":[
        {
            "category":"Organizations",
            "subcategory":"Religious Organization",
            "type":"Services"
        }
    ],
    "sg:phone":"+1 281 371 3900",
    "sg:postcode":"77449",
    "sg:province":"TX",
    "wof:name":"Tri County Baptist Church",
    "wof:placetype":"venue"
},
  "geometry": {"coordinates":[-95.77376099999999,29.854037],"type":"Point"}
}