{
  "type": "Feature",
  "properties": {
    "iso:country":"US",
    "sg:address":"255 SE 1900",
    "sg:city":"Andrews",
    "sg:classifiers":[
        {
            "category":"Restaurant",
            "type":"Food & Drink"
        }
    ],
    "sg:phone":"+1 432 523 6092",
    "sg:postcode":"79714",
    "sg:province":"TX",
    "sg:tags":[
        "eating"
    ],
    "wof:name":"Franks Beef Jerky",
    "wof:placetype":"venue"
},
  "geometry": {"coordinates":[-102.529467,32.29043],"type":"Point"}
}