{
  "type": "Feature",
  "properties": {
    "iso:country":"US",
    "sg:address":"49 Fernwood Dr",
    "sg:city":"Texarkana",
    "sg:classifiers":[
        {
            "category":"Building & Trades",
            "subcategory":"Construction",
            "type":"Services"
        }
    ],
    "sg:phone":"+1 903 831 3877",
    "sg:postcode":"75503",
    "sg:province":"TX",
    "sg:tags":[
        "residential"
    ],
    "wof:name":"Shadeco Inc",
    "wof:placetype":"venue"
},
  "geometry": {"coordinates":[-94.07223399999999,33.475003],"type":"Point"}
}