{
  "type": "Feature",
  "properties": {
    "iso:country":"US",
    "sg:address":"4400B N Fwy",
    "sg:city":"Houston",
    "sg:classifiers":[
        {
            "category":"Shopping",
            "subcategory":"Shoes",
            "type":"Retail Goods"
        }
    ],
    "sg:phone":"+1 713 699 4472",
    "sg:postcode":"77022",
    "sg:province":"TX",
    "sg:tags":[
        "store"
    ],
    "sg:website":"www.footlocker.com",
    "wof:name":"Foot Locker House of Hoops",
    "wof:placetype":"venue"
},
  "geometry": {"coordinates":[-95.294487,29.804038],"type":"Point"}
}