{
  "type": "Feature",
  "properties": {
    "iso:country":"US",
    "sg:address":"522 S Dumas Ave",
    "sg:city":"Dumas",
    "sg:classifiers":[
        {
            "category":"Shopping",
            "subcategory":"Luggage & Leather Goods",
            "type":"Retail Goods"
        }
    ],
    "sg:phone":"+1 806 934 9707",
    "sg:postcode":"79029",
    "sg:province":"TX",
    "wof:name":"El Vaquero",
    "wof:placetype":"venue"
},
  "geometry": {"coordinates":[-101.97334600000001,35.86071],"type":"Point"}
}