{
  "type": "Feature",
  "properties": {
    "iso:country":"US",
    "sg:address":"1308 Capital Ave",
    "sg:city":"Plano",
    "sg:classifiers":[
        {
            "category":"Wholesale",
            "subcategory":"Medical Equipment & Supplies",
            "type":"Manufacturing & Wholesale Goods"
        },
        {
            "category":"Shopping",
            "type":"Retail Goods"
        }
    ],
    "sg:phone":"+1 972 578 4831",
    "sg:postcode":"75074",
    "sg:province":"TX",
    "sg:tags":[
        "physician",
        "surgeon"
    ],
    "wof:name":"Affordable Medical Supplies",
    "wof:placetype":"venue"
},
  "geometry": {"coordinates":[-96.695768,33.011073],"type":"Point"}
}