{
  "type": "Feature",
  "properties": {
    "iso:country":"US",
    "sg:address":"222 N Washington St",
    "sg:city":"Seymour",
    "sg:classifiers":[
        {
            "category":"Insurance",
            "subcategory":"Insurance Agent",
            "type":"Services"
        }
    ],
    "sg:phone":"+1 940 889 5837",
    "sg:postcode":"76380",
    "sg:province":"TX",
    "wof:name":"Loving Insurance",
    "wof:placetype":"venue"
},
  "geometry": {"coordinates":[-99.261619,33.589825],"type":"Point"}
}