{
  "type": "Feature",
  "properties": {
    "iso:country":"US",
    "sg:address":"210 Main Ave",
    "sg:city":"Olton",
    "sg:classifiers":[
        {
            "category":"Banks & Credit Unions",
            "subcategory":"Bank",
            "type":"Services"
        }
    ],
    "sg:phone":"+1 806 285 2651",
    "sg:postcode":"79064",
    "sg:province":"TX",
    "sg:tags":[
        "loan"
    ],
    "wof:name":"Great Plains Ag Credit",
    "wof:placetype":"venue"
},
  "geometry": {"coordinates":[-102.13524200000001,34.187167],"type":"Point"}
}