{
  "type": "Feature",
  "properties": {
    "iso:country":"US",
    "sg:address":"4413 N Texas Ave",
    "sg:city":"Bryan",
    "sg:classifiers":[
        {
            "category":"Real Estate",
            "subcategory":"Real Estate Operator",
            "type":"Services"
        }
    ],
    "sg:phone":"+1 979 778 1287",
    "sg:postcode":"77803",
    "sg:province":"TX",
    "sg:tags":[
        "mobile",
        "home",
        "community"
    ],
    "wof:name":"Village Park North",
    "wof:placetype":"venue"
},
  "geometry": {"coordinates":[-96.39820899999999,30.707648],"type":"Point"}
}