{
  "type": "Feature",
  "properties": {
    "iso:country":"US",
    "sg:address":"717 N Harwood St",
    "sg:city":"Dallas",
    "sg:classifiers":[
        {
            "category":"Professional",
            "type":"Services"
        }
    ],
    "sg:phone":"+1 214 754 0393",
    "sg:postcode":"75201",
    "sg:province":"TX",
    "sg:tags":[
        "establishment"
    ],
    "wof:name":"STFI",
    "wof:placetype":"venue"
},
  "geometry": {"coordinates":[-96.79823399999999,32.785962],"type":"Point"}
}