{
  "type": "Feature",
  "properties": {
    "iso:country":"US",
    "sg:address":"12606 Crosby Lynchburg Rd",
    "sg:city":"Crosby",
    "sg:classifiers":[
        {
            "category":"Organizations",
            "subcategory":"Religious Organization",
            "type":"Services"
        }
    ],
    "sg:phone":"+1 281 328 4451",
    "sg:postcode":"77532",
    "sg:province":"TX",
    "wof:name":"St Martin De Porres Church Rectory",
    "wof:placetype":"venue"
},
  "geometry": {"coordinates":[-95.337694,29.874364],"type":"Point"}
}