{
  "type": "Feature",
  "properties": {
    "iso:country":"US",
    "sg:address":"3835 Beechwood Ln",
    "sg:city":"Dallas",
    "sg:classifiers":[
        {
            "category":"Professional",
            "subcategory":"Art Services",
            "type":"Services"
        }
    ],
    "sg:phone":"+1 214 352 0340",
    "sg:postcode":"75220",
    "sg:province":"TX",
    "sg:tags":[
        "commercial",
        "design"
    ],
    "wof:name":"Tunagraphix",
    "wof:placetype":"venue"
},
  "geometry": {"coordinates":[-96.85111499999999,32.876236],"type":"Point"}
}