{
  "type": "Feature",
  "properties": {
    "iso:country":"US",
    "sg:address":"13511 Westheimer Rd",
    "sg:city":"Houston",
    "sg:classifiers":[
        {
            "category":"Wholesale",
            "subcategory":"Electrical",
            "type":"Manufacturing & Wholesale Goods"
        }
    ],
    "sg:phone":"+1 281 556 6500",
    "sg:postcode":"77042",
    "sg:province":"TX",
    "sg:tags":[
        "lighting",
        "light",
        "fixture",
        "bulb"
    ],
    "wof:name":"The Light House",
    "wof:placetype":"venue"
},
  "geometry": {"coordinates":[-95.627398,29.7358],"type":"Point"}
}