{
  "type": "Feature",
  "properties": {
    "iso:country":"US",
    "sg:address":"2028 Sisterdale Rd",
    "sg:city":"Boerne",
    "sg:classifiers":[
        {
            "category":"Shopping",
            "subcategory":"Hobbies, Toys, & Games",
            "type":"Retail Goods"
        }
    ],
    "sg:phone":"+1 830 324 6548",
    "sg:postcode":"78006",
    "sg:province":"TX",
    "wof:name":"Cheryls Country Craft",
    "wof:placetype":"venue"
},
  "geometry": {"coordinates":[-98.738461,30.051319],"type":"Point"}
}