{
  "type": "Feature",
  "properties": {
    "iso:country":"US",
    "sg:address":"14065 Proton Rd",
    "sg:city":"Dallas",
    "sg:classifiers":[
        {
            "category":"Restaurant",
            "type":"Food & Drink"
        }
    ],
    "sg:phone":"+1 972 980 4630",
    "sg:postcode":"75244",
    "sg:province":"TX",
    "sg:tags":[
        "eating"
    ],
    "wof:name":"Transitions Group Inc",
    "wof:placetype":"venue"
},
  "geometry": {"coordinates":[-96.836821,32.942543],"type":"Point"}
}