{
  "type": "Feature",
  "properties": {
    "iso:country":"US",
    "sg:address":"700 Lavaca St",
    "sg:city":"Austin",
    "sg:classifiers":[
        {
            "category":"Professional",
            "subcategory":"Accounting & Tax Preparation",
            "type":"Services"
        },
        {
            "category":"Professional",
            "subcategory":"Lawyer & Legal Services",
            "type":"Services"
        }
    ],
    "sg:phone":"+1 512 322 0500",
    "sg:postcode":"78701",
    "sg:province":"TX",
    "sg:tags":[
        "divorce",
        "accountant",
        "law",
        "family"
    ],
    "wof:name":"Mitchell & Colmenero Llp",
    "wof:placetype":"venue"
},
  "geometry": {"coordinates":[-97.74490400000001,30.269699],"type":"Point"}
}