{
  "type": "Feature",
  "properties": {
    "iso:country":"US",
    "sg:address":"1002 S Key Ave",
    "sg:city":"Lampasas",
    "sg:classifiers":[
        {
            "category":"Health Services",
            "subcategory":"Doctor",
            "type":"Services"
        }
    ],
    "sg:phone":"+1 512 556 6444",
    "sg:postcode":"76550",
    "sg:province":"TX",
    "sg:tags":[
        "physician",
        "surgeon"
    ],
    "wof:name":"John T Higgins Md",
    "wof:placetype":"venue"
},
  "geometry": {"coordinates":[-98.180356,31.05972],"type":"Point"}
}