{
  "type": "Feature",
  "properties": {
    "iso:country":"US",
    "sg:address":"6306 Greenville Ave",
    "sg:city":"Dallas",
    "sg:classifiers":[
        {
            "category":"Shopping",
            "subcategory":"Computers & Home Electronics",
            "type":"Retail Goods"
        }
    ],
    "sg:phone":"+1 214 692 1106",
    "sg:postcode":"75206",
    "sg:province":"TX",
    "wof:name":"Car Toys TX Corporate",
    "wof:placetype":"venue"
},
  "geometry": {"coordinates":[-96.767454,32.862127],"type":"Point"}
}