{
  "type": "Feature",
  "properties": {
    "iso:country":"US",
    "sg:address":"1817 N Alexander St",
    "sg:city":"Sherman",
    "sg:classifiers":[
        {
            "category":"Manufacturing",
            "subcategory":"Buildings",
            "type":"Manufacturing & Wholesale Goods"
        },
        {
            "category":"Building & Trades",
            "subcategory":"Construction",
            "type":"Services"
        }
    ],
    "sg:phone":"+1 903 868 1243",
    "sg:postcode":"75092",
    "sg:province":"TX",
    "sg:tags":[
        "wallcoverings-installation",
        "builder",
        "wallpaper",
        "contractor",
        "home",
        "painting"
    ],
    "wof:name":"Terrell Construction",
    "wof:placetype":"venue"
},
  "geometry": {"coordinates":[-96.618796,33.653018],"type":"Point"}
}