{
  "type": "Feature",
  "properties": {
    "iso:country":"US",
    "sg:address":"8700 Burnet Road",
    "sg:city":"Austin",
    "sg:classifiers":[
        {
            "category":"Recreation",
            "subcategory":"Amusement Park",
            "type":"Entertainment"
        },
        {
            "category":"Shopping",
            "subcategory":"Hobbies, Toys, & Games",
            "type":"Retail Goods"
        },
        {
            "category":"Shopping",
            "subcategory":"Bicycles & Sporting Goods",
            "type":"Retail Goods"
        }
    ],
    "sg:phone":"+1 512 451 8353",
    "sg:postcode":"78757",
    "sg:province":"TX",
    "sg:tags":[
        "toy",
        "store"
    ],
    "sg:website":"www.atexfun.com",
    "wof:name":"A-Tex Family Fun Center",
    "wof:placetype":"venue"
},
  "geometry": {"coordinates":[-97.72714499999999,30.369734],"type":"Point"}
}