{
  "type": "Feature",
  "properties": {
    "iso:country":"US",
    "sg:address":"531 Harvest Glen Dr",
    "sg:city":"Richardson",
    "sg:classifiers":[
        {
            "category":"Wholesale",
            "subcategory":"Computers",
            "type":"Manufacturing & Wholesale Goods"
        }
    ],
    "sg:phone":"+1 972 458 2782",
    "sg:postcode":"75081",
    "sg:province":"TX",
    "wof:name":"Jade Computer Products Inc",
    "wof:placetype":"venue"
},
  "geometry": {"coordinates":[-96.725211,32.92866],"type":"Point"}
}