{
  "type": "Feature",
  "properties": {
    "iso:country":"US",
    "sg:address":"2710 N Josey Ln",
    "sg:city":"Carrollton",
    "sg:classifiers":[
        {
            "category":"Professional",
            "subcategory":"Employment Agencies",
            "type":"Services"
        }
    ],
    "sg:phone":"+1 972 466 4141",
    "sg:postcode":"75007",
    "sg:province":"TX",
    "sg:website":"www.abbastaffing.com",
    "wof:name":"Abba Staffing",
    "wof:placetype":"venue"
},
  "geometry": {"coordinates":[-96.88980100000001,32.990002],"type":"Point"}
}