{
  "type": "Feature",
  "properties": {
    "iso:country":"US",
    "sg:address":"418 Graham St",
    "sg:city":"Tuscola",
    "sg:classifiers":[
        {
            "category":"Government",
            "subcategory":"Office",
            "type":"Public Place"
        }
    ],
    "sg:phone":"+1 325 554 7766",
    "sg:postcode":"79562",
    "sg:province":"TX",
    "sg:tags":[
        "city"
    ],
    "wof:name":"Tuscola City Hall",
    "wof:placetype":"venue"
},
  "geometry": {"coordinates":[-99.79624200000001,32.2097],"type":"Point"}
}