{
  "type": "Feature",
  "properties": {
    "iso:country":"US",
    "sg:address":"400 Cedar Bayou Rd",
    "sg:city":"Baytown",
    "sg:classifiers":[
        {
            "category":"Organizations",
            "subcategory":"Religious Organization",
            "type":"Services"
        }
    ],
    "sg:phone":"+1 281 422 6644",
    "sg:postcode":"77520",
    "sg:province":"TX",
    "sg:tags":[
        "church"
    ],
    "sg:website":"www.cristoviene.org",
    "wof:name":"Iglesias Cristo Viene",
    "wof:placetype":"venue"
},
  "geometry": {"coordinates":[-94.963576,29.747692],"type":"Point"}
}