{
  "type": "Feature",
  "properties": {
    "iso:country":"US",
    "sg:address":"2112 Brentwood Dr",
    "sg:city":"Houston",
    "sg:classifiers":[
        {
            "category":"Professional",
            "type":"Services"
        }
    ],
    "sg:phone":"+1 713 522 6737",
    "sg:postcode":"77019",
    "sg:province":"TX",
    "sg:tags":[
        "consulting",
        "management"
    ],
    "wof:name":"Salvogroup Communications Inc",
    "wof:placetype":"venue"
},
  "geometry": {"coordinates":[-95.414615,29.753818],"type":"Point"}
}