{
  "type": "Feature",
  "properties": {
    "iso:country":"US",
    "sg:address":"3110 Meadway Dr",
    "sg:city":"Houston",
    "sg:classifiers":[
        {
            "category":"Wholesale",
            "subcategory":"Medical Equipment & Supplies",
            "type":"Manufacturing & Wholesale Goods"
        }
    ],
    "sg:phone":"+1 713 569 5915",
    "sg:postcode":"77082",
    "sg:province":"TX",
    "sg:tags":[
        "physician",
        "surgeon"
    ],
    "wof:name":"Medic Diagnostic Svc Intl",
    "wof:placetype":"venue"
},
  "geometry": {"coordinates":[-95.60999200000001,29.731151],"type":"Point"}
}