{
  "type": "Feature",
  "properties": {
    "iso:country":"US",
    "sg:address":"501 S Madison St",
    "sg:city":"Amarillo",
    "sg:classifiers":[
        {
            "category":"Manufacturing",
            "subcategory":"Tools & Machinery",
            "type":"Manufacturing & Wholesale Goods"
        }
    ],
    "sg:phone":"+1 806 374 2940",
    "sg:postcode":"79101",
    "sg:province":"AR",
    "sg:tags":[
        "machine",
        "shop"
    ],
    "wof:name":"AMI Machining",
    "wof:placetype":"venue"
},
  "geometry": {"coordinates":[-101.844475,35.208605],"type":"Point"}
}