{
  "type": "Feature",
  "properties": {
    "iso:country":"US",
    "sg:address":"3905 Marion St",
    "sg:city":"Corpus Christi",
    "sg:classifiers":[
        {
            "category":"Manufacturing",
            "subcategory":"Jewelry",
            "type":"Manufacturing & Wholesale Goods"
        }
    ],
    "sg:phone":"+1 361 855 6485",
    "sg:postcode":"78415",
    "sg:province":"TX",
    "sg:tags":[
        "precious",
        "metal",
        "mfg"
    ],
    "wof:name":"Designs By Lapointe",
    "wof:placetype":"venue"
},
  "geometry": {"coordinates":[-97.396798,27.727858],"type":"Point"}
}