{
  "type": "Feature",
  "properties": {
    "iso:country":"US",
    "sg:address":"513 S Commercial Ave",
    "sg:city":"Coleman",
    "sg:classifiers":[
        {
            "category":"Real Estate",
            "subcategory":"Real Estate Agent",
            "type":"Services"
        }
    ],
    "sg:phone":"+1 325 625 2988",
    "sg:postcode":"76834",
    "sg:province":"TX",
    "wof:name":"Ranch Realty Of Coleman",
    "wof:placetype":"venue"
},
  "geometry": {"coordinates":[-99.42299300000001,31.827097],"type":"Point"}
}