{
  "type": "Feature",
  "properties": {
    "iso:country":"US",
    "sg:address":"9202 Clearock Dr",
    "sg:city":"Austin",
    "sg:classifiers":[
        {
            "category":"Professional",
            "type":"Services"
        }
    ],
    "sg:phone":"+1 512 364 0969",
    "sg:postcode":"78750",
    "sg:province":"TX",
    "sg:website":"austinhydroax.com",
    "wof:name":"Hydroax Land Clearing",
    "wof:placetype":"venue"
},
  "geometry": {"coordinates":[-97.794025,30.445355],"type":"Point"}
}