{
  "type": "Feature",
  "properties": {
    "iso:country":"US",
    "sg:address":"101 N Ash St",
    "sg:city":"Pearsall",
    "sg:classifiers":[
        {
            "category":"Retail",
            "subcategory":"Repair Shop",
            "type":"Services"
        }
    ],
    "sg:phone":"+1 830 334 5599",
    "sg:postcode":"78061",
    "sg:province":"TX",
    "wof:name":"Johnnys T V Repair",
    "wof:placetype":"venue"
},
  "geometry": {"coordinates":[-99.09381500000001,28.892811],"type":"Point"}
}