{
  "type": "Feature",
  "properties": {
    "iso:country":"US",
    "sg:address":"1331 Edgewood Dr",
    "sg:city":"Graham",
    "sg:phone":"+1 940 549 0120",
    "sg:postcode":"76450",
    "sg:province":"TX",
    "sg:tags":[
        "distributor",
        "oil",
        "marketer"
    ],
    "wof:name":"K & S Petroleum Co",
    "wof:placetype":"venue"
},
  "geometry": {"coordinates":[-98.573387,33.100135],"type":"Point"}
}