{
  "type": "Feature",
  "properties": {
    "iso:country":"US",
    "sg:address":"10925 Estate Ln",
    "sg:city":"Dallas",
    "sg:classifiers":[
        {
            "category":"Professional",
            "subcategory":"Employment Agencies",
            "type":"Services"
        }
    ],
    "sg:phone":"+1 214 553 4508",
    "sg:postcode":"75238",
    "sg:province":"TX",
    "sg:tags":[
        "medical"
    ],
    "wof:name":"ATC Healthcare Svc",
    "wof:placetype":"venue"
},
  "geometry": {"coordinates":[-96.694945,32.882383],"type":"Point"}
}