{
  "type": "Feature",
  "properties": {
    "iso:country":"US",
    "sg:address":"5 Eureka Cir",
    "sg:city":"Wichita Falls",
    "sg:classifiers":[
        {
            "category":"Building & Trades",
            "subcategory":"Construction",
            "type":"Services"
        }
    ],
    "sg:phone":"+1 940 696 2243",
    "sg:postcode":"76308",
    "sg:province":"TX",
    "sg:tags":[
        "residential",
        "commercial",
        "family",
        "contractor"
    ],
    "wof:name":"Cage Construction & MGT Co",
    "wof:placetype":"venue"
},
  "geometry": {"coordinates":[-98.526338,33.869527],"type":"Point"}
}