{
  "type": "Feature",
  "properties": {
    "iso:country":"US",
    "sg:address":"3626 Cape Forest Dr",
    "sg:city":"Humble",
    "sg:classifiers":[
        {
            "category":"Professional",
            "subcategory":"Business Services",
            "type":"Services"
        }
    ],
    "sg:phone":"+1 281 361 8600",
    "sg:postcode":"77345",
    "sg:province":"TX",
    "sg:tags":[
        "interior",
        "consultant",
        "design",
        "decorator"
    ],
    "wof:name":"Interior Innovation By Evelyn",
    "wof:placetype":"venue"
},
  "geometry": {"coordinates":[-95.185675,30.057203],"type":"Point"}
}