{
  "type": "Feature",
  "properties": {
    "iso:country":"US",
    "sg:address":"10940 Katy Fwy",
    "sg:city":"Houston",
    "sg:classifiers":[
        {
            "category":"Arts & Performance",
            "subcategory":"Art Gallery",
            "type":"Entertainment"
        },
        {
            "category":"Farming",
            "subcategory":"Fish & Marine Products",
            "type":"Manufacturing & Wholesale Goods"
        },
        {
            "category":"Professional",
            "subcategory":"Art Services",
            "type":"Services"
        },
        {
            "category":"Manufacturing",
            "subcategory":"Wood Products",
            "type":"Manufacturing & Wholesale Goods"
        }
    ],
    "sg:phone":"+1 713 461 3244",
    "sg:postcode":"77043",
    "sg:province":"TX",
    "sg:tags":[
        "picture",
        "frame",
        "manufacturer",
        "frames-wholesale",
        "framing"
    ],
    "wof:name":"The Frame Gallery",
    "wof:placetype":"venue"
},
  "geometry": {"coordinates":[-95.57293300000001,29.784839],"type":"Point"}
}