{
  "type": "Feature",
  "properties": {
    "iso:country":"US",
    "sg:address":"1669 Peters San Felipe Rd",
    "sg:city":"Sealy",
    "sg:classifiers":[
        {
            "category":"Farming",
            "subcategory":"Livestock Farm",
            "type":"Manufacturing & Wholesale Goods"
        }
    ],
    "sg:phone":"+1 979 885 4678",
    "sg:postcode":"77474",
    "sg:province":"TX",
    "sg:tags":[
        "animal",
        "general"
    ],
    "wof:name":"Leroy & Pat Vornkahl",
    "wof:placetype":"venue"
},
  "geometry": {"coordinates":[-96.162629,29.849404],"type":"Point"}
}