{
  "type": "Feature",
  "properties": {
    "iso:country":"US",
    "sg:address":"6505 W Park Blvd Ste 322",
    "sg:city":"Plano",
    "sg:classifiers":[
        {
            "category":"Banks & Credit Unions",
            "subcategory":"Bank",
            "type":"Services"
        }
    ],
    "sg:phone":"+1 972 378 3500",
    "sg:postcode":"75093",
    "sg:province":"TX",
    "wof:name":"Stager Jeff Ins",
    "wof:placetype":"venue"
},
  "geometry": {"coordinates":[-96.840698,33.027302],"type":"Point"}
}