{
  "type": "Feature",
  "properties": {
    "iso:country":"US",
    "sg:address":"426 W 12th St",
    "sg:city":"Dallas",
    "sg:classifiers":[
        {
            "category":"Building & Trades",
            "subcategory":"Construction",
            "type":"Services"
        }
    ],
    "sg:phone":"+1 214 946 6500",
    "sg:postcode":"75208",
    "sg:province":"TX",
    "sg:tags":[
        "house"
    ],
    "wof:name":"Casas Modernas LLC",
    "wof:placetype":"venue"
},
  "geometry": {"coordinates":[-96.82975999999999,32.741193],"type":"Point"}
}