{
  "type": "Feature",
  "properties": {
    "iso:country":"US",
    "sg:address":"12421 Scarsdale Blvd",
    "sg:city":"Houston",
    "sg:classifiers":[
        {
            "category":"Communications",
            "type":"Services"
        }
    ],
    "sg:phone":"+1 713 464 9638",
    "sg:postcode":"77581",
    "sg:province":"TX",
    "sg:tags":[
        "carrier"
    ],
    "wof:name":"Kentel Communication Svc",
    "wof:placetype":"venue"
},
  "geometry": {"coordinates":[-95.20446800000001,29.592768],"type":"Point"}
}