{
  "type": "Feature",
  "properties": {
    "iso:country":"US",
    "sg:address":"912 W Tyler St",
    "sg:city":"Gilmer",
    "sg:classifiers":[
        {
            "category":"Real Estate",
            "subcategory":"Real Estate Agent",
            "type":"Services"
        }
    ],
    "sg:phone":"+1 903 843 9999",
    "sg:postcode":"75644",
    "sg:province":"TX",
    "wof:name":"Century 21",
    "wof:placetype":"venue"
},
  "geometry": {"coordinates":[-94.955392,32.728722],"type":"Point"}
}