{
  "type": "Feature",
  "properties": {
    "iso:country":"US",
    "sg:address":"34 Cedar Trails Dr",
    "sg:city":"Belton",
    "sg:classifiers":[
        {
            "category":"Real Estate",
            "subcategory":"Real Estate Agent",
            "type":"Services"
        }
    ],
    "sg:phone":"+1 254 780 1751",
    "sg:postcode":"76513",
    "sg:province":"TX",
    "wof:name":"Morgans Point Investments",
    "wof:placetype":"venue"
},
  "geometry": {"coordinates":[-97.46231,31.15025],"type":"Point"}
}