{
  "type": "Feature",
  "properties": {
    "iso:country":"US",
    "sg:address":"9005 Spicebrush Dr",
    "sg:city":"Austin",
    "sg:classifiers":[
        {
            "category":"Professional",
            "subcategory":"Computer Services",
            "type":"Services"
        }
    ],
    "sg:phone":"+1 512 342 1818",
    "sg:postcode":"78759",
    "sg:province":"TX",
    "sg:tags":[
        "cd-rom"
    ],
    "sg:website":"http://www.jwbsales.com",
    "wof:name":"Real Resolution Inc",
    "wof:placetype":"venue"
},
  "geometry": {"coordinates":[-97.772441,30.395549],"type":"Point"}
}