{
  "type": "Feature",
  "properties": {
    "iso:country":"US",
    "sg:address":"3605 Royalcrest Dr",
    "sg:city":"Fort Worth",
    "sg:classifiers":[
        {
            "category":"Building & Trades",
            "subcategory":"Cleaning & Sanitation",
            "type":"Services"
        }
    ],
    "sg:phone":"+1 817 563 6813",
    "sg:postcode":"76140",
    "sg:province":"TX",
    "sg:tags":[
        "maintenance"
    ],
    "wof:name":"R & R Floor Experts",
    "wof:placetype":"venue"
},
  "geometry": {"coordinates":[-97.264972,32.639923],"type":"Point"}
}