{
  "type": "Feature",
  "properties": {
    "iso:country":"US",
    "sg:address":"500 N Temple Dr",
    "sg:city":"Diboll",
    "sg:classifiers":[
        {
            "category":"Food & Beverages",
            "subcategory":"Groceries & Convenience Stores",
            "type":"Retail Goods"
        }
    ],
    "sg:phone":"+1 936 829 3000",
    "sg:postcode":"75941",
    "sg:province":"TX",
    "wof:name":"Joc-Stop 15",
    "wof:placetype":"venue"
},
  "geometry": {"coordinates":[-94.779613,31.194508],"type":"Point"}
}