{
  "type": "Feature",
  "properties": {
    "iso:country":"US",
    "sg:address":"516 Heights Blvd",
    "sg:city":"Houston",
    "sg:classifiers":[
        {
            "category":"Professional",
            "subcategory":"Lawyer & Legal Services",
            "type":"Services"
        }
    ],
    "sg:phone":"+1 713 222 2007",
    "sg:postcode":"77007",
    "sg:province":"TX",
    "wof:name":"Norris Cantu Llp",
    "wof:placetype":"venue"
},
  "geometry": {"coordinates":[-95.397206,29.779932],"type":"Point"}
}