{
  "type": "Feature",
  "properties": {
    "iso:country":"US",
    "sg:address":"2908 Laredo St",
    "sg:city":"Laredo",
    "sg:classifiers":[
        {
            "category":"Building & Trades",
            "subcategory":"Construction",
            "type":"Services"
        }
    ],
    "sg:phone":"+1 956 727 3225",
    "sg:postcode":"78043",
    "sg:province":"TX",
    "sg:tags":[
        "carpentry",
        "contractor"
    ],
    "wof:name":"Guillermo Mancha",
    "wof:placetype":"venue"
},
  "geometry": {"coordinates":[-99.46603500000001,27.507536],"type":"Point"}
}