{
  "type": "Feature",
  "properties": {
    "iso:country":"US",
    "sg:address":"8105 Fort Sumter Rd",
    "sg:city":"Austin",
    "sg:classifiers":[
        {
            "category":"Building & Trades",
            "subcategory":"Construction",
            "type":"Services"
        }
    ],
    "sg:phone":"+1 512 280 2353",
    "sg:postcode":"78745",
    "sg:province":"TX",
    "sg:tags":[
        "repairing",
        "house",
        "nonresidential",
        "remodeling",
        "contractor"
    ],
    "wof:name":"Austin Creative Builders Inc",
    "wof:placetype":"venue"
},
  "geometry": {"coordinates":[-97.82458200000001,30.194585],"type":"Point"}
}