{
  "type": "Feature",
  "properties": {
    "iso:country":"US",
    "sg:address":"2431 E Southeast Loop 323",
    "sg:city":"Tyler",
    "sg:classifiers":[
        {
            "category":"Food & Beverages",
            "subcategory":"Groceries & Convenience Stores",
            "type":"Retail Goods"
        }
    ],
    "sg:phone":"+1 903 566 1627",
    "sg:postcode":"75701",
    "sg:province":"TX",
    "wof:name":"Guru Dutt",
    "wof:placetype":"venue"
},
  "geometry": {"coordinates":[-95.27030000000001,32.312344],"type":"Point"}
}