{
  "type": "Feature",
  "properties": {
    "iso:country":"US",
    "sg:address":"620 N Coit Rd",
    "sg:city":"Richardson",
    "sg:classifiers":[
        {
            "category":"Health Services",
            "subcategory":"Doctor",
            "type":"Services"
        }
    ],
    "sg:phone":"+1 972 664 0676",
    "sg:postcode":"75080",
    "sg:province":"TX",
    "wof:name":"Estrada Pediatric Clinic",
    "wof:placetype":"venue"
},
  "geometry": {"coordinates":[-96.768636,32.957954],"type":"Point"}
}