{
  "type": "Feature",
  "properties": {
    "iso:country":"US",
    "sg:address":"843 Barbara Mae St",
    "sg:city":"Houston",
    "sg:classifiers":[
        {
            "category":"Building & Trades",
            "subcategory":"Plumbing",
            "type":"Services"
        }
    ],
    "sg:phone":"+1 713 453 7900",
    "sg:postcode":"77015",
    "sg:province":"TX",
    "sg:tags":[
        "plumbing",
        "contractor"
    ],
    "wof:name":"Anz Hydro-Tech Inc",
    "wof:placetype":"venue"
},
  "geometry": {"coordinates":[-95.16959300000001,29.780193],"type":"Point"}
}