{
  "type": "Feature",
  "properties": {
    "iso:country":"US",
    "sg:address":"3707 Doctors Dr",
    "sg:city":"Port Arthur",
    "sg:classifiers":[
        {
            "category":"Health Services",
            "subcategory":"Doctor",
            "type":"Services"
        }
    ],
    "sg:phone":"+1 409 983 2729",
    "sg:postcode":"77642",
    "sg:province":"TX",
    "sg:tags":[
        "medical"
    ],
    "wof:name":"Armando J Espiritu",
    "wof:placetype":"venue"
},
  "geometry": {"coordinates":[-93.94392499999999,29.914051],"type":"Point"}
}