{
  "type": "Feature",
  "properties": {
    "iso:country":"US",
    "sg:address":"1836 S Cooper St",
    "sg:city":"Arlington",
    "sg:classifiers":[
        {
            "category":"Personal",
            "subcategory":"Tattoo Parlor",
            "type":"Services"
        }
    ],
    "sg:phone":"+1 817 792 3623",
    "sg:postcode":"76013",
    "sg:province":"TX",
    "sg:tags":[
        "tattooing"
    ],
    "wof:name":"Tantilizing Tattoo",
    "wof:placetype":"venue"
},
  "geometry": {"coordinates":[-97.11473100000001,32.715612],"type":"Point"}
}