{
  "type": "Feature",
  "properties": {
    "iso:country":"US",
    "sg:address":"18551 Timber Forest Dr",
    "sg:city":"Humble",
    "sg:classifiers":[
        {
            "category":"Professional",
            "subcategory":"Employment Agencies",
            "type":"Services"
        }
    ],
    "sg:phone":"+1 832 601 5294",
    "sg:postcode":"77346",
    "sg:province":"TX",
    "wof:name":"Yos Consulting",
    "wof:placetype":"venue"
},
  "geometry": {"coordinates":[-95.19327699999999,29.99342],"type":"Point"}
}