{
  "type": "Feature",
  "properties": {
    "iso:country":"US",
    "sg:address":"3515 Double Lake Dr",
    "sg:city":"Missouri City",
    "sg:classifiers":[
        {
            "category":"Professional",
            "type":"Services"
        }
    ],
    "sg:phone":"+1 281 403 3929",
    "sg:postcode":"77459",
    "sg:province":"TX",
    "wof:name":"Blaze & Assoc",
    "wof:placetype":"venue"
},
  "geometry": {"coordinates":[-95.57929300000001,29.566559],"type":"Point"}
}