{
  "type": "Feature",
  "properties": {
    "iso:country":"US",
    "sg:address":"14060 Proton Rd",
    "sg:city":"Dallas",
    "sg:classifiers":[
        {
            "category":"Wholesale",
            "subcategory":"Electrical",
            "type":"Manufacturing & Wholesale Goods"
        }
    ],
    "sg:phone":"+1 972 371 2600",
    "sg:postcode":"75244",
    "sg:province":"TX",
    "sg:tags":[
        "equipment",
        "telecommunication"
    ],
    "wof:name":"Source Inc",
    "wof:placetype":"venue"
},
  "geometry": {"coordinates":[-96.836671,32.942371],"type":"Point"}
}