{
  "type": "Feature",
  "properties": {
    "iso:country":"US",
    "sg:address":"9203 Kirby Dr",
    "sg:city":"Houston",
    "sg:classifiers":[
        {
            "category":"Retail",
            "subcategory":"Repair Shop",
            "type":"Services"
        }
    ],
    "sg:phone":"+1 713 797 7800",
    "sg:postcode":"77054",
    "sg:province":"TX",
    "sg:tags":[
        "appliance",
        "household",
        "electrical"
    ],
    "wof:name":"Sears Roebuck and Co Inc",
    "wof:placetype":"venue"
},
  "geometry": {"coordinates":[-95.412243,29.671046],"type":"Point"}
}