{
  "type": "Feature",
  "properties": {
    "iso:country":"US",
    "sg:address":"1901 W William Cannon Dr",
    "sg:city":"Austin",
    "sg:classifiers":[
        {
            "category":"Shopping",
            "subcategory":"Florist",
            "type":"Retail Goods"
        }
    ],
    "sg:phone":"+1 512 444 8113",
    "sg:postcode":"78745",
    "sg:province":"TX",
    "wof:name":"Dolls & Bears Basket of",
    "wof:placetype":"venue"
},
  "geometry": {"coordinates":[-97.80439800000001,30.2022],"type":"Point"}
}