{
  "type": "Feature",
  "properties": {
    "iso:country":"US",
    "sg:address":"4414 50th St",
    "sg:city":"Lubbock",
    "sg:classifiers":[
        {
            "category":"Banks & Credit Unions",
            "subcategory":"Bank",
            "type":"Services"
        }
    ],
    "sg:phone":"+1 806 785 2357",
    "sg:postcode":"79414",
    "sg:province":"TX",
    "sg:tags":[
        "cashing",
        "check"
    ],
    "wof:name":"Money Place",
    "wof:placetype":"venue"
},
  "geometry": {"coordinates":[-101.90698399999999,33.54883],"type":"Point"}
}