{
  "type": "Feature",
  "properties": {
    "iso:country":"US",
    "sg:address":"9730 Town Park Dr",
    "sg:city":"Houston",
    "sg:classifiers":[
        {
            "category":"Manufacturing",
            "subcategory":"Printing",
            "type":"Manufacturing & Wholesale Goods"
        }
    ],
    "sg:phone":"+1 713 988 5140",
    "sg:postcode":"77036",
    "sg:province":"TX",
    "sg:tags":[
        "newspaper"
    ],
    "wof:name":"Asian Media Inc",
    "wof:placetype":"venue"
},
  "geometry": {"coordinates":[-95.55224699999999,29.711891],"type":"Point"}
}