{
  "type": "Feature",
  "properties": {
    "iso:country":"US",
    "sg:address":"2002 Morgan Ave",
    "sg:city":"Corpus Christi",
    "sg:classifiers":[
        {
            "category":"Food & Beverages",
            "subcategory":"Groceries & Convenience Stores",
            "type":"Retail Goods"
        }
    ],
    "sg:phone":"+1 361 881 8780",
    "sg:postcode":"78405",
    "sg:province":"TX",
    "wof:name":"Circle K",
    "wof:placetype":"venue"
},
  "geometry": {"coordinates":[-97.41236600000001,27.778213],"type":"Point"}
}