{
  "type": "Feature",
  "properties": {
    "iso:country":"US",
    "sg:address":"3201 N Sylvania Ave",
    "sg:city":"Fort Worth",
    "sg:classifiers":[
        {
            "category":"Home & Garden",
            "subcategory":"Building Materials",
            "type":"Retail Goods"
        }
    ],
    "sg:phone":"+1 817 831 3679",
    "sg:postcode":"76111",
    "sg:province":"TX",
    "sg:tags":[
        "center"
    ],
    "wof:name":"Home Depot",
    "wof:placetype":"venue"
},
  "geometry": {"coordinates":[-97.308408,32.807707],"type":"Point"}
}