{
  "type": "Feature",
  "properties": {
    "iso:country":"US",
    "sg:address":"29502 Country Place Rd",
    "sg:city":"Magnolia",
    "sg:classifiers":[
        {
            "category":"Professional",
            "subcategory":"Business Services",
            "type":"Services"
        }
    ],
    "sg:phone":"+1 281 356 3088",
    "sg:postcode":"77355",
    "sg:province":"TX",
    "wof:name":"Freddie Drake Enterprises",
    "wof:placetype":"venue"
},
  "geometry": {"coordinates":[-95.756614,30.17551],"type":"Point"}
}