{
  "type": "Feature",
  "properties": {
    "iso:country":"US",
    "sg:address":"606 N Edison St",
    "sg:city":"Fredericksburg",
    "sg:classifiers":[
        {
            "category":"Home & Garden",
            "subcategory":"Building Materials",
            "type":"Retail Goods"
        }
    ],
    "sg:phone":"+1 830 990 4800",
    "sg:postcode":"78624",
    "sg:province":"TX",
    "sg:tags":[
        "glass",
        "window",
        "plate"
    ],
    "wof:name":"Advantage Auto Glass",
    "wof:placetype":"venue"
},
  "geometry": {"coordinates":[-98.873696,30.285196],"type":"Point"}
}