{
  "type": "Feature",
  "properties": {
    "iso:country":"US",
    "sg:address":"1350 Manufacturing St",
    "sg:city":"Dallas",
    "sg:classifiers":[
        {
            "category":"Wholesale",
            "subcategory":"Electrical",
            "type":"Manufacturing & Wholesale Goods"
        }
    ],
    "sg:phone":"+1 214 742 3674",
    "sg:postcode":"75207",
    "sg:province":"TX",
    "sg:tags":[
        "equipment",
        "lighting",
        "system"
    ],
    "wof:name":"Energia",
    "wof:placetype":"venue"
},
  "geometry": {"coordinates":[-96.82977,32.797439],"type":"Point"}
}