{
  "type": "Feature",
  "properties": {
    "iso:country":"US",
    "sg:address":"305 N Corpus Christi St",
    "sg:city":"Rio Grande City",
    "sg:classifiers":[
        {
            "category":"Professional",
            "type":"Services"
        }
    ],
    "sg:phone":"+1 956 487 3528",
    "sg:postcode":"78582",
    "sg:province":"TX",
    "sg:tags":[
        "establishment"
    ],
    "wof:name":"Muscular Dystrophy Associati",
    "wof:placetype":"venue"
},
  "geometry": {"coordinates":[-98.818596,26.381166],"type":"Point"}
}