{
  "type": "Feature",
  "properties": {
    "iso:country":"US",
    "sg:address":"8303 Timberwilde St",
    "sg:city":"San Antonio",
    "sg:classifiers":[
        {
            "category":"Professional",
            "subcategory":"Computer Services",
            "type":"Services"
        }
    ],
    "sg:phone":"+1 210 684 0946",
    "sg:postcode":"78250",
    "sg:province":"TX",
    "sg:tags":[
        "related"
    ],
    "wof:name":"Structured Systems Engineering",
    "wof:placetype":"venue"
},
  "geometry": {"coordinates":[-98.64793299999999,29.495092],"type":"Point"}
}