{
  "type": "Feature",
  "properties": {
    "iso:country":"US",
    "sg:address":"8007 Brienne Dr",
    "sg:city":"Round Rock",
    "sg:classifiers":[
        {
            "category":"Building & Trades",
            "subcategory":"Construction",
            "type":"Services"
        }
    ],
    "sg:phone":"+1 512 759 1717",
    "sg:postcode":"78681",
    "sg:province":"TX",
    "sg:tags":[
        "residential"
    ],
    "wof:name":"Rex Patton Homes Inc",
    "wof:placetype":"venue"
},
  "geometry": {"coordinates":[-97.728978,30.502655],"type":"Point"}
}