{
  "type": "Feature",
  "properties": {
    "iso:country":"US",
    "sg:address":"1812 Payton Gin Rd",
    "sg:city":"Austin",
    "sg:classifiers":[
        {
            "category":"Utilities",
            "subcategory":"Mobile Phone",
            "type":"Services"
        },
        {
            "category":"Utilities",
            "subcategory":"Telephone",
            "type":"Services"
        },
        {
            "category":"Manufacturing",
            "subcategory":"Electronics",
            "type":"Manufacturing & Wholesale Goods"
        }
    ],
    "sg:phone":"+1 512 563 0122",
    "sg:postcode":"78758",
    "sg:province":"TX",
    "sg:tags":[
        "equipment",
        "telecommunications-equipment",
        "system",
        "cellular",
        "supply"
    ],
    "wof:name":"Discount Wireless",
    "wof:placetype":"venue"
},
  "geometry": {"coordinates":[-97.716638,30.36529],"type":"Point"}
}