{
  "type": "Feature",
  "properties": {
    "iso:country":"US",
    "sg:address":"1907 Macarthur Dr",
    "sg:city":"Orange",
    "sg:classifiers":[
        {
            "category":"Personal",
            "subcategory":"Beauty Salon",
            "type":"Services"
        }
    ],
    "sg:phone":"+1 409 833 3733",
    "sg:postcode":"77630",
    "sg:province":"TX",
    "sg:tags":[
        "hair",
        "consultant"
    ],
    "wof:name":"Free Style",
    "wof:placetype":"venue"
},
  "geometry": {"coordinates":[-93.748372,30.093314],"type":"Point"}
}