{
  "type": "Feature",
  "properties": {
    "iso:country":"US",
    "sg:address":"116 W Southmore Ave",
    "sg:city":"Pasadena",
    "sg:classifiers":[
        {
            "category":"Cinema",
            "subcategory":"Movie Rental",
            "type":"Entertainment"
        }
    ],
    "sg:phone":"+1 713 472 3656",
    "sg:postcode":"77502",
    "sg:province":"TX",
    "sg:tags":[
        "video",
        "tape",
        "store"
    ],
    "wof:name":"Blockbuster",
    "wof:placetype":"venue"
},
  "geometry": {"coordinates":[-95.21168400000001,29.690857],"type":"Point"}
}