{
  "type": "Feature",
  "properties": {
    "iso:country":"US",
    "sg:address":"729 Tamarack Dr",
    "sg:city":"New Braunfels",
    "sg:classifiers":[
        {
            "category":"Building & Trades",
            "subcategory":"Landscaping Services",
            "type":"Services"
        }
    ],
    "sg:phone":"+1 210 604 2361",
    "sg:postcode":"78133",
    "sg:province":"TX",
    "wof:name":"Cowboy Cutters",
    "wof:placetype":"venue"
},
  "geometry": {"coordinates":[-98.24232600000001,29.924241],"type":"Point"}
}