{
  "type": "Feature",
  "properties": {
    "iso:country":"US",
    "sg:address":"6220 Campbell Rd Ste 401",
    "sg:city":"Dallas",
    "sg:classifiers":[
        {
            "category":"Professional",
            "subcategory":"Lawyer & Legal Services",
            "type":"Services"
        }
    ],
    "sg:phone":"+1 972 503 6338",
    "sg:postcode":"75248",
    "sg:province":"TX",
    "sg:website":"www.carselaw.com",
    "wof:name":"Carse Law Firm",
    "wof:placetype":"venue"
},
  "geometry": {"coordinates":[-96.79938,32.979913],"type":"Point"}
}