{
  "type": "Feature",
  "properties": {
    "iso:country":"US",
    "sg:address":"3919 Fairmont Pkwy",
    "sg:city":"Pasadena",
    "sg:classifiers":[
        {
            "category":"Retail",
            "subcategory":"Auto Repair",
            "type":"Services"
        }
    ],
    "sg:phone":"+1 281 487 0870",
    "sg:postcode":"77504",
    "sg:province":"TX",
    "sg:tags":[
        "general"
    ],
    "wof:name":"Advantage Auto Air",
    "wof:placetype":"venue"
},
  "geometry": {"coordinates":[-95.189003,29.651491],"type":"Point"}
}