{
  "type": "Feature",
  "properties": {
    "iso:country":"US",
    "sg:address":"4523 Mowery Rd",
    "sg:city":"Houston",
    "sg:classifiers":[
        {
            "category":"Personal",
            "subcategory":"Barber",
            "type":"Services"
        }
    ],
    "sg:phone":"+1 713 731 2772",
    "sg:postcode":"77047",
    "sg:province":"TX",
    "sg:tags":[
        "shop"
    ],
    "wof:name":"Cloverland Barber Shop",
    "wof:placetype":"venue"
},
  "geometry": {"coordinates":[-95.356499,29.636299],"type":"Point"}
}