{
  "type": "Feature",
  "properties": {
    "iso:country":"US",
    "sg:address":"6004 Sun Vista Dr",
    "sg:city":"Austin",
    "sg:classifiers":[
        {
            "category":"Shopping",
            "subcategory":"Gifts & Souvenirs",
            "type":"Retail Goods"
        }
    ],
    "sg:phone":"+1 512 892 5256",
    "sg:postcode":"78749",
    "sg:province":"TX",
    "wof:name":"Two Cats In A Tub",
    "wof:placetype":"venue"
},
  "geometry": {"coordinates":[-97.847858,30.229497],"type":"Point"}
}