{
  "type": "Feature",
  "properties": {
    "iso:country":"US",
    "sg:address":"1465 S 11th St",
    "sg:city":"Slaton",
    "sg:classifiers":[
        {
            "category":"Freight",
            "type":"Transportation"
        }
    ],
    "sg:phone":"+1 806 828 5842",
    "sg:postcode":"79364",
    "sg:province":"TX",
    "sg:tags":[
        "without",
        "storage",
        "trucking"
    ],
    "wof:name":"Moreno Trucking",
    "wof:placetype":"venue"
},
  "geometry": {"coordinates":[-101.645433,33.424852],"type":"Point"}
}