{
  "type": "Feature",
  "properties": {
    "iso:country":"US",
    "sg:address":"3070 N Francis Ave",
    "sg:city":"Odessa",
    "sg:classifiers":[
        {
            "category":"Freight",
            "type":"Transportation"
        }
    ],
    "sg:phone":"+1 432 530 2592",
    "sg:postcode":"79764",
    "sg:province":"TX",
    "sg:tags":[
        "operator",
        "trucking"
    ],
    "wof:name":"Double T",
    "wof:placetype":"venue"
},
  "geometry": {"coordinates":[-102.434078,31.862959],"type":"Point"}
}