{
  "type": "Feature",
  "properties": {
    "iso:country":"US",
    "sg:address":"7039 Clayton Ave",
    "sg:city":"Dallas",
    "sg:classifiers":[
        {
            "category":"Building & Trades",
            "subcategory":"Construction",
            "type":"Services"
        }
    ],
    "sg:phone":"+1 214 328 6401",
    "sg:postcode":"75214",
    "sg:province":"TX",
    "sg:tags":[
        "contractor"
    ],
    "wof:name":"T & M Construction",
    "wof:placetype":"venue"
},
  "geometry": {"coordinates":[-96.737326,32.813786],"type":"Point"}
}