{
  "type": "Feature",
  "properties": {
    "iso:country":"US",
    "sg:address":"3008 Old Jacksboro Hwy",
    "sg:city":"Wichita Falls",
    "sg:classifiers":[
        {
            "category":"Shopping",
            "subcategory":"Used Merchandise",
            "type":"Retail Goods"
        }
    ],
    "sg:phone":"+1 940 723 7842",
    "sg:postcode":"76302",
    "sg:province":"TX",
    "sg:tags":[
        "pawnbroker"
    ],
    "wof:name":"City Jewelry & Loan Company",
    "wof:placetype":"venue"
},
  "geometry": {"coordinates":[-98.493037,33.882426],"type":"Point"}
}