{
  "type": "Feature",
  "properties": {
    "iso:country":"US",
    "sg:address":"216 W 6th St",
    "sg:city":"Ferris",
    "sg:classifiers":[
        {
            "category":"Manufacturing",
            "subcategory":"Printing",
            "type":"Manufacturing & Wholesale Goods"
        }
    ],
    "sg:phone":"+1 972 441 3286",
    "sg:postcode":"75125",
    "sg:province":"TX",
    "sg:tags":[
        "screen"
    ],
    "sg:website":"www.sandscreen.com",
    "wof:name":"Sandscreen Printing & Embrdry",
    "wof:placetype":"venue"
},
  "geometry": {"coordinates":[-96.665874,32.53379],"type":"Point"}
}