{
  "type": "Feature",
  "properties": {
    "iso:country":"US",
    "sg:address":"418 Coker Valley Dr",
    "sg:city":"Kennedale",
    "sg:classifiers":[
        {
            "category":"Professional",
            "type":"Services"
        }
    ],
    "sg:phone":"+1 817 561 9341",
    "sg:postcode":"76060",
    "sg:province":"TX",
    "wof:name":"Accu Paging Systems",
    "wof:placetype":"venue"
},
  "geometry": {"coordinates":[-97.19194400000001,32.642969],"type":"Point"}
}