{
  "type": "Feature",
  "properties": {
    "iso:country":"US",
    "sg:address":"2323 E Mulberry St",
    "sg:city":"Angleton",
    "sg:classifiers":[
        {
            "category":"Health Services",
            "subcategory":"Doctor",
            "type":"Services"
        }
    ],
    "sg:phone":"+1 979 849 2738",
    "sg:postcode":"77515",
    "sg:province":"TX",
    "sg:tags":[
        "physician",
        "surgeon",
        "medical"
    ],
    "wof:name":"Diagnostic Imaging Specialist",
    "wof:placetype":"venue"
},
  "geometry": {"coordinates":[-95.406662,29.187417],"type":"Point"}
}