{
  "type": "Feature",
  "properties": {
    "iso:country":"US",
    "sg:address":"8205 Ascot Pl",
    "sg:city":"Prosper",
    "sg:classifiers":[
        {
            "category":"Building & Trades",
            "subcategory":"Construction",
            "type":"Services"
        }
    ],
    "sg:phone":"+1 214 458 1604",
    "sg:postcode":"75078",
    "sg:province":"TX",
    "sg:tags":[
        "painter",
        "contractor"
    ],
    "wof:name":"Corner Stone PPI",
    "wof:placetype":"venue"
},
  "geometry": {"coordinates":[-96.768119,33.266695],"type":"Point"}
}