{
  "type": "Feature",
  "properties": {
    "iso:country":"US",
    "sg:address":"433 Flato Rd",
    "sg:city":"Corpus Christi",
    "sg:classifiers":[
        {
            "category":"Wholesale",
            "subcategory":"Machinery & Supplies",
            "type":"Manufacturing & Wholesale Goods"
        }
    ],
    "sg:phone":"+1 361 289 0727",
    "sg:postcode":"78405",
    "sg:province":"TX",
    "sg:tags":[
        "contractor"
    ],
    "wof:name":"J C Brown Inc",
    "wof:placetype":"venue"
},
  "geometry": {"coordinates":[-97.461224,27.78165],"type":"Point"}
}