{
  "type": "Feature",
  "properties": {
    "iso:country":"US",
    "sg:address":"216 N Ed Carey Dr",
    "sg:city":"Harlingen",
    "sg:classifiers":[
        {
            "category":"Shopping",
            "type":"Retail Goods"
        }
    ],
    "sg:phone":"+1 956 425 4011",
    "sg:postcode":"78550",
    "sg:province":"TX",
    "sg:tags":[
        "hearing",
        "equipment",
        "supply",
        "impaired"
    ],
    "wof:name":"New Sound Hearing Aid Ctr",
    "wof:placetype":"venue"
},
  "geometry": {"coordinates":[-97.66305800000001,26.196056],"type":"Point"}
}