{
  "type": "Feature",
  "properties": {
    "iso:country":"US",
    "sg:address":"5307 Gem Lake Rd",
    "sg:city":"Amarillo",
    "sg:classifiers":[
        {
            "category":"Real Estate",
            "subcategory":"Real Estate Operator",
            "type":"Services"
        }
    ],
    "sg:phone":"+1 806 355 2589",
    "sg:postcode":"79106",
    "sg:province":"TX",
    "sg:tags":[
        "building",
        "apartment"
    ],
    "wof:name":"Three Ponds Apartments",
    "wof:placetype":"venue"
},
  "geometry": {"coordinates":[-101.90057299999999,35.213299],"type":"Point"}
}