{
  "type": "Feature",
  "properties": {
    "iso:country":"US",
    "sg:address":"8115 Long Point Rd",
    "sg:city":"Houston",
    "sg:classifiers":[
        {
            "category":"Autos & Motor Vehicles",
            "subcategory":"Automobile Sales",
            "type":"Retail Goods"
        }
    ],
    "sg:phone":"+1 713 465 6600",
    "sg:postcode":"77055",
    "sg:province":"TX",
    "sg:tags":[
        "used"
    ],
    "wof:name":"Auto Union LTD",
    "wof:placetype":"venue"
},
  "geometry": {"coordinates":[-95.490447,29.802848],"type":"Point"}
}