{
  "type": "Feature",
  "properties": {
    "iso:country":"US",
    "sg:address":"12200 Madison Ln",
    "sg:city":"Justin",
    "sg:classifiers":[
        {
            "category":"Building & Trades",
            "subcategory":"Construction",
            "type":"Services"
        }
    ],
    "sg:phone":"+1 866 908 9765",
    "sg:postcode":"76247",
    "sg:province":"TX",
    "sg:tags":[
        "painting",
        "contractor"
    ],
    "wof:name":"Quality Painting",
    "wof:placetype":"venue"
},
  "geometry": {"coordinates":[-97.342493,33.158863],"type":"Point"}
}