{
  "type": "Feature",
  "properties": {
    "iso:country":"US",
    "sg:address":"626 Kelly Rd",
    "sg:city":"Magnolia",
    "sg:classifiers":[
        {
            "category":"Education",
            "subcategory":"Special Training",
            "type":"Public Place"
        }
    ],
    "sg:phone":"+1 281 356 9239",
    "sg:postcode":"77354",
    "sg:province":"TX",
    "sg:tags":[
        "program"
    ],
    "wof:name":"Mark Smith Training Svc",
    "wof:placetype":"venue"
},
  "geometry": {"coordinates":[-95.754347,30.21868],"type":"Point"}
}