{
  "type": "Feature",
  "properties": {
    "iso:country":"US",
    "sg:address":"1104 Morton Ave",
    "sg:city":"Dumas",
    "sg:classifiers":[
        {
            "category":"Professional",
            "type":"Services"
        }
    ],
    "sg:phone":"+1 806 935 9438",
    "sg:postcode":"79029",
    "sg:province":"TX",
    "wof:name":"Melissas Creations",
    "wof:placetype":"venue"
},
  "geometry": {"coordinates":[-101.960196,35.853846],"type":"Point"}
}