{
  "type": "Feature",
  "properties": {
    "iso:country":"US",
    "sg:address":"5959 Harry Hines Blvd",
    "sg:city":"Dallas",
    "sg:classifiers":[
        {
            "category":"Health Services",
            "subcategory":"Doctor",
            "type":"Services"
        }
    ],
    "sg:phone":"+1 214 879 8820",
    "sg:postcode":"75235",
    "sg:province":"TX",
    "sg:tags":[
        "physician",
        "surgeon"
    ],
    "wof:name":"Samuel Ngwu MD",
    "wof:placetype":"venue"
},
  "geometry": {"coordinates":[-96.844511,32.817765],"type":"Point"}
}