{
  "type": "Feature",
  "properties": {
    "iso:country":"US",
    "sg:address":"1529 Bryant St",
    "sg:city":"Irving",
    "sg:classifiers":[
        {
            "category":"Professional",
            "subcategory":"Computer Services",
            "type":"Services"
        }
    ],
    "sg:phone":"+1 972 871 7825",
    "sg:postcode":"75061",
    "sg:province":"TX",
    "sg:tags":[
        "related"
    ],
    "wof:name":"Dsw Technical",
    "wof:placetype":"venue"
},
  "geometry": {"coordinates":[-96.950114,32.831364],"type":"Point"}
}