{
  "type": "Feature",
  "properties": {
    "iso:country":"US",
    "sg:address":"4611 Sao Paulo St",
    "sg:city":"Pasadena",
    "sg:classifiers":[
        {
            "category":"Professional",
            "subcategory":"Business Services",
            "type":"Services"
        }
    ],
    "sg:phone":"+1 713 910 8830",
    "sg:postcode":"77504",
    "sg:province":"TX",
    "wof:name":"David Walker Agency",
    "wof:placetype":"venue"
},
  "geometry": {"coordinates":[-95.173162,29.654957],"type":"Point"}
}