{
  "type": "Feature",
  "properties": {
    "iso:country":"US",
    "sg:address":"6919 Scyene Rd",
    "sg:city":"Dallas",
    "sg:classifiers":[
        {
            "category":"Personal",
            "subcategory":"Beauty Salon",
            "type":"Services"
        }
    ],
    "sg:phone":"+1 214 484 6110",
    "sg:postcode":"75227",
    "sg:province":"TX",
    "sg:tags":[
        "hair"
    ],
    "wof:name":"Four J'S Barber Shop",
    "wof:placetype":"venue"
},
  "geometry": {"coordinates":[-96.701982,32.763663],"type":"Point"}
}