{
  "type": "Feature",
  "properties": {
    "iso:country":"US",
    "sg:address":"2012 W 43rd St",
    "sg:city":"Houston",
    "sg:classifiers":[
        {
            "category":"Food & Beverages",
            "subcategory":"Groceries & Convenience Stores",
            "type":"Retail Goods"
        }
    ],
    "sg:phone":"+1 713 682 3331",
    "sg:postcode":"77018",
    "sg:province":"TX",
    "wof:name":"43rd Food Store",
    "wof:placetype":"venue"
},
  "geometry": {"coordinates":[-95.447998,29.8326],"type":"Point"}
}