{
  "type": "Feature",
  "properties": {
    "iso:country":"US",
    "sg:address":"900 Main St",
    "sg:city":"Dallas",
    "sg:classifiers":[
        {
            "category":"Personal",
            "type":"Services"
        }
    ],
    "sg:phone":"+1 214 613 0047",
    "sg:postcode":"75202",
    "sg:province":"TX",
    "sg:tags":[
        "mover"
    ],
    "wof:name":"Movers Gaudie Dallas",
    "wof:placetype":"venue"
},
  "geometry": {"coordinates":[-96.803575,32.779331],"type":"Point"}
}