{
  "type": "Feature",
  "properties": {
    "iso:country":"US",
    "sg:address":"122 E McKinney St",
    "sg:city":"Denton",
    "sg:classifiers":[
        {
            "category":"Organizations",
            "subcategory":"Religious Organization",
            "type":"Services"
        }
    ],
    "sg:phone":"+1 940 591 1664",
    "sg:postcode":"76201",
    "sg:province":"TX",
    "wof:name":"Restoration Ministries",
    "wof:placetype":"venue"
},
  "geometry": {"coordinates":[-97.131925,33.216534],"type":"Point"}
}