{
  "type": "Feature",
  "properties": {
    "iso:country":"US",
    "sg:address":"920 N Main St",
    "sg:city":"Taylor",
    "sg:classifiers":[
        {
            "category":"Health Services",
            "subcategory":"Doctor",
            "type":"Services"
        }
    ],
    "sg:phone":"+1 512 352 5577",
    "sg:postcode":"76574",
    "sg:province":"TX",
    "sg:tags":[
        "dentist",
        "medical"
    ],
    "sg:website":"www.ezbraces.com",
    "wof:name":"Taylor Dental Assoc Inc",
    "wof:placetype":"venue"
},
  "geometry": {"coordinates":[-97.410178,30.576014],"type":"Point"}
}