{
  "type": "Feature",
  "properties": {
    "iso:country":"US",
    "sg:address":"10280 Forum West Dr",
    "sg:city":"Houston",
    "sg:classifiers":[
        {
            "category":"Retail",
            "subcategory":"Laundry & Dry Cleaning",
            "type":"Services"
        }
    ],
    "sg:phone":"+1 713 271 5481",
    "sg:postcode":"77036",
    "sg:province":"TX",
    "sg:tags":[
        "cleaners"
    ],
    "wof:name":"K R Cleaners",
    "wof:placetype":"venue"
},
  "geometry": {"coordinates":[-95.559062,29.667732],"type":"Point"}
}