{
  "type": "Feature",
  "properties": {
    "iso:country":"US",
    "sg:address":"3724 FM 1960 W",
    "sg:city":"Houston",
    "sg:classifiers":[
        {
            "category":"Professional",
            "subcategory":"Management & Consulting",
            "type":"Services"
        }
    ],
    "sg:phone":"+1 281 893 5946",
    "sg:postcode":"77068",
    "sg:province":"TX",
    "sg:tags":[
        "building",
        "lease"
    ],
    "wof:name":"Huang & Shu LP",
    "wof:placetype":"venue"
},
  "geometry": {"coordinates":[-95.480602,29.997762],"type":"Point"}
}