{
  "type": "Feature",
  "properties": {
    "iso:country":"US",
    "sg:address":"8731 Croteau Dr",
    "sg:city":"Houston",
    "sg:classifiers":[
        {
            "category":"Personal",
            "subcategory":"Beauty Salon",
            "type":"Services"
        }
    ],
    "sg:phone":"+1 281 458 7181",
    "sg:postcode":"77044",
    "sg:province":"TX",
    "wof:name":"Miss Brenda's",
    "wof:placetype":"venue"
},
  "geometry": {"coordinates":[-95.206872,29.853145],"type":"Point"}
}