{
  "type": "Feature",
  "properties": {
    "iso:country":"US",
    "sg:address":"449 Sandy Knoll Dr",
    "sg:city":"Coppell",
    "sg:classifiers":[
        {
            "category":"Professional",
            "type":"Services"
        }
    ],
    "sg:phone":"+1 972 462 7156",
    "sg:postcode":"75019",
    "sg:province":"TX",
    "wof:name":"Dl Promo Specialties",
    "wof:placetype":"venue"
},
  "geometry": {"coordinates":[-96.981387,32.969384],"type":"Point"}
}