{
  "type": "Feature",
  "properties": {
    "iso:country":"US",
    "sg:address":"822 Marimba Dr",
    "sg:city":"El Paso",
    "sg:classifiers":[
        {
            "category":"Real Estate",
            "subcategory":"Real Estate Agent",
            "type":"Services"
        },
        {
            "category":"Professional",
            "subcategory":"Accounting & Tax Preparation",
            "type":"Services"
        }
    ],
    "sg:phone":"+1 915 533 1000",
    "sg:postcode":"79912",
    "sg:province":"TX",
    "sg:tags":[
        "consultant"
    ],
    "wof:name":"Andresen & Company Inc",
    "wof:placetype":"venue"
},
  "geometry": {"coordinates":[-106.554807,31.82338],"type":"Point"}
}