{
  "type": "Feature",
  "properties": {
    "iso:country":"US",
    "sg:address":"2750 Briargrove Ln",
    "sg:city":"San Angelo",
    "sg:phone":"+1 325 224 0734",
    "sg:postcode":"76904",
    "sg:province":"TX",
    "sg:tags":[
        "farm",
        "wheat",
        "cotton"
    ],
    "wof:name":"Djdj Farms",
    "wof:placetype":"venue"
},
  "geometry": {"coordinates":[-100.482345,31.413559],"type":"Point"}
}