{
  "type": "Feature",
  "properties": {
    "iso:country":"US",
    "sg:address":"11215 Berkley Sq",
    "sg:city":"San Antonio",
    "sg:classifiers":[
        {
            "category":"Professional",
            "type":"Services"
        }
    ],
    "sg:phone":"+1 210 877 2791",
    "sg:postcode":"78249",
    "sg:province":"TX",
    "wof:name":"Fitzgerald Dora Education Cons",
    "wof:placetype":"venue"
},
  "geometry": {"coordinates":[-98.621208,29.546467],"type":"Point"}
}