{
  "type": "Feature",
  "properties": {
    "iso:country":"US",
    "sg:address":"500 N Akard St",
    "sg:city":"Dallas",
    "sg:classifiers":[
        {
            "category":"Personal",
            "subcategory":"Beauty Salon",
            "type":"Services"
        }
    ],
    "sg:phone":"+1 214 954 3008",
    "sg:postcode":"75201",
    "sg:province":"TX",
    "sg:tags":[
        "shop"
    ],
    "wof:name":"Lincoln Plaza Hair Design Inc",
    "wof:placetype":"venue"
},
  "geometry": {"coordinates":[-96.80073899999999,32.7847],"type":"Point"}
}