{
  "type": "Feature",
  "properties": {
    "iso:country":"US",
    "sg:address":"7612 W Hwy 71",
    "sg:city":"Austin",
    "sg:classifiers":[
        {
            "category":"Autos & Motor Vehicles",
            "subcategory":"Auto Supplies",
            "type":"Retail Goods"
        }
    ],
    "sg:phone":"+1 512 301 1001",
    "sg:postcode":"78735",
    "sg:province":"TX",
    "sg:tags":[
        "filter",
        "gas"
    ],
    "sg:website":"www.envirotex.com",
    "wof:name":"Enviro-Tex",
    "wof:placetype":"venue"
},
  "geometry": {"coordinates":[-97.88178600000001,30.24173],"type":"Point"}
}