{
  "type": "Feature",
  "properties": {
    "iso:country":"US",
    "sg:address":"315 Rosewood Ave",
    "sg:city":"Boerne",
    "sg:classifiers":[
        {
            "category":"Organizations",
            "subcategory":"Religious Organization",
            "type":"Services"
        }
    ],
    "sg:phone":"+1 830 816 1853",
    "sg:postcode":"78006",
    "sg:province":"TX",
    "sg:tags":[
        "church"
    ],
    "sg:website":"www.stjohnlutheran.com",
    "wof:name":"St John Lutheran Church",
    "wof:placetype":"venue"
},
  "geometry": {"coordinates":[-98.726687,29.793954],"type":"Point"}
}