{
  "type": "Feature",
  "properties": {
    "iso:country":"US",
    "sg:address":"7024 N 15th Ln",
    "sg:city":"Mcallen",
    "sg:classifiers":[
        {
            "category":"Building & Trades",
            "subcategory":"Construction",
            "type":"Services"
        }
    ],
    "sg:phone":"+1 956 279 2762",
    "sg:postcode":"78504",
    "sg:province":"TX",
    "sg:tags":[
        "contractor"
    ],
    "wof:name":"Kimberland Custom Siding",
    "wof:placetype":"venue"
},
  "geometry": {"coordinates":[-98.22585100000001,26.267631],"type":"Point"}
}