{
  "type": "Feature",
  "properties": {
    "iso:country":"US",
    "sg:address":"15502 Ripplestream St",
    "sg:city":"Houston",
    "sg:classifiers":[
        {
            "category":"Shopping",
            "subcategory":"Computers & Home Electronics",
            "type":"Retail Goods"
        }
    ],
    "sg:phone":"+1 281 440 4449",
    "sg:postcode":"77068",
    "sg:province":"TX",
    "sg:tags":[
        "equipment",
        "dealer"
    ],
    "wof:name":"Joey's Computers",
    "wof:placetype":"venue"
},
  "geometry": {"coordinates":[-95.496889,30.004061],"type":"Point"}
}