{
  "type": "Feature",
  "properties": {
    "iso:country":"US",
    "sg:address":"2128 Sidney Baker St",
    "sg:city":"Kerrville",
    "sg:classifiers":[
        {
            "category":"Restaurant",
            "type":"Food & Drink"
        }
    ],
    "sg:phone":"+1 830 792 5575",
    "sg:postcode":"78028",
    "sg:province":"TX",
    "sg:tags":[
        "eating"
    ],
    "wof:name":"McDonalds",
    "wof:placetype":"venue"
},
  "geometry": {"coordinates":[-99.11472500000001,30.067903],"type":"Point"}
}