{
  "type": "Feature",
  "properties": {
    "iso:country":"US",
    "sg:address":"5942 Brookside Rd",
    "sg:city":"Pearland",
    "sg:classifiers":[
        {
            "category":"Shopping",
            "subcategory":"Hobbies, Toys, & Games",
            "type":"Retail Goods"
        }
    ],
    "sg:phone":"+1 281 485 7600",
    "sg:postcode":"77581",
    "sg:province":"TX",
    "wof:name":"Country Bonnet",
    "wof:placetype":"venue"
},
  "geometry": {"coordinates":[-95.317348,29.587732],"type":"Point"}
}