{
  "type": "Feature",
  "properties": {
    "iso:country":"US",
    "sg:address":"500 W Main St",
    "sg:city":"Lewisville",
    "sg:classifiers":[
        {
            "category":"Health Services",
            "subcategory":"Doctor",
            "type":"Services"
        }
    ],
    "sg:phone":"+1 972 219 7203",
    "sg:postcode":"75057",
    "sg:province":"TX",
    "sg:tags":[
        "physician",
        "surgeon"
    ],
    "wof:name":"HCA Bio Medical Svc",
    "wof:placetype":"venue"
},
  "geometry": {"coordinates":[-97.005455,33.046326],"type":"Point"}
}