{
  "type": "Feature",
  "properties": {
    "iso:country":"US",
    "sg:address":"6314 Lewis Ln",
    "sg:city":"Rosharon",
    "sg:classifiers":[
        {
            "category":"Wholesale",
            "subcategory":"Sporting Goods",
            "type":"Manufacturing & Wholesale Goods"
        }
    ],
    "sg:phone":"+1 281 369 3222",
    "sg:postcode":"77583",
    "sg:province":"TX",
    "wof:name":"Skident Co",
    "wof:placetype":"venue"
},
  "geometry": {"coordinates":[-95.373717,29.388367],"type":"Point"}
}