{
  "type": "Feature",
  "properties": {
    "iso:country":"US",
    "sg:address":"1500 Village West Dr",
    "sg:city":"Austin",
    "sg:classifiers":[
        {
            "category":"Professional",
            "subcategory":"Business Services",
            "type":"Services"
        }
    ],
    "sg:phone":"+1 512 263 9307",
    "sg:postcode":"78733",
    "sg:province":"TX",
    "sg:tags":[
        "mail",
        "shipping"
    ],
    "wof:name":"Lake Hills Business & Communications Center",
    "wof:placetype":"venue"
},
  "geometry": {"coordinates":[-97.86521399999999,30.338149],"type":"Point"}
}