{
  "type": "Feature",
  "properties": {
    "iso:country":"US",
    "sg:address":"3219 Raging River Dr",
    "sg:city":"Austin",
    "sg:classifiers":[
        {
            "category":"Professional",
            "type":"Services"
        }
    ],
    "sg:phone":"+1 512 388 2378",
    "sg:postcode":"78728",
    "sg:province":"TX",
    "wof:name":"North Austin Caring Services I",
    "wof:placetype":"venue"
},
  "geometry": {"coordinates":[-97.68523399999999,30.450619],"type":"Point"}
}