{
  "type": "Feature",
  "properties": {
    "iso:country":"US",
    "sg:address":"443 Oakleaf Dr",
    "sg:city":"San Antonio",
    "sg:classifiers":[
        {
            "category":"Professional",
            "type":"Services"
        }
    ],
    "sg:phone":"+1 210 832 8393",
    "sg:postcode":"78209",
    "sg:province":"TX",
    "wof:name":"Right Horse Studio",
    "wof:placetype":"venue"
},
  "geometry": {"coordinates":[-98.44985800000001,29.504072],"type":"Point"}
}