{
  "type": "Feature",
  "properties": {
    "iso:country":"US",
    "sg:address":"1290 Rich Ln",
    "sg:city":"Buda",
    "sg:classifiers":[
        {
            "category":"Wholesale",
            "subcategory":"Non-durable Goods",
            "type":"Manufacturing & Wholesale Goods"
        }
    ],
    "sg:phone":"+1 512 312 0121",
    "sg:postcode":"78610",
    "sg:province":"TX",
    "wof:name":"First Continental Distrib",
    "wof:placetype":"venue"
},
  "geometry": {"coordinates":[-97.77302299999999,30.064237],"type":"Point"}
}