{
  "type": "Feature",
  "properties": {
    "iso:country":"US",
    "sg:address":"1143 Boston Ave",
    "sg:city":"Nederland",
    "sg:classifiers":[
        {
            "category":"Building & Trades",
            "subcategory":"Landscaping Services",
            "type":"Services"
        }
    ],
    "sg:phone":"+1 409 727 5455",
    "sg:postcode":"77627",
    "sg:province":"TX",
    "sg:tags":[
        "landscape",
        "contractor"
    ],
    "wof:name":"V P Tree Service Inc",
    "wof:placetype":"venue"
},
  "geometry": {"coordinates":[-93.990503,29.976581],"type":"Point"}
}