{
  "type": "Feature",
  "properties": {
    "iso:country":"US",
    "sg:address":"1603 S Zarzamora",
    "sg:city":"San Antonio",
    "sg:classifiers":[
        {
            "category":"Wholesale",
            "subcategory":"Fruits & Vegetables",
            "type":"Manufacturing & Wholesale Goods"
        }
    ],
    "sg:phone":"+1 210 431 0952",
    "sg:postcode":"78207",
    "sg:province":"TX",
    "wof:name":"Fernandez Produce Express Inc",
    "wof:placetype":"venue"
},
  "geometry": {"coordinates":[-98.529408,29.409679],"type":"Point"}
}