{
  "type": "Feature",
  "properties": {
    "iso:country":"US",
    "sg:address":"10563 Co Rd 316A",
    "sg:city":"Terrell",
    "sg:classifiers":[
        {
            "category":"Freight",
            "type":"Transportation"
        }
    ],
    "sg:phone":"+1 972 563 1687",
    "sg:postcode":"75161",
    "sg:province":"TX",
    "sg:tags":[
        "hauling"
    ],
    "wof:name":"Roberson Hauling",
    "wof:placetype":"venue"
},
  "geometry": {"coordinates":[-96.141592,32.708636],"type":"Point"}
}