{
  "type": "Feature",
  "properties": {
    "iso:country":"US",
    "sg:address":"723 Park Wind Dr",
    "sg:city":"Katy",
    "sg:classifiers":[
        {
            "category":"Professional",
            "subcategory":"Computer Services",
            "type":"Services"
        }
    ],
    "sg:phone":"+1 281 599 0320",
    "sg:postcode":"77450",
    "sg:province":"TX",
    "sg:tags":[
        "related"
    ],
    "wof:name":"Filtro-Comp",
    "wof:placetype":"venue"
},
  "geometry": {"coordinates":[-95.746359,29.771094],"type":"Point"}
}