{
  "type": "Feature",
  "properties": {
    "iso:country":"US",
    "sg:address":"9420 Research Blvd",
    "sg:city":"Austin",
    "sg:classifiers":[
        {
            "category":"Insurance",
            "subcategory":"Insurance Agent",
            "type":"Services"
        }
    ],
    "sg:phone":"+1 512 340 7950",
    "sg:postcode":"78759",
    "sg:province":"TX",
    "wof:name":"Broadspire SRCS Inc",
    "wof:placetype":"venue"
},
  "geometry": {"coordinates":[-97.74341,30.385055],"type":"Point"}
}