{
  "type": "Feature",
  "properties": {
    "iso:country":"US",
    "sg:address":"5019 McKinney Ave",
    "sg:city":"Dallas",
    "sg:classifiers":[
        {
            "category":"Professional",
            "subcategory":"Employment Agencies",
            "type":"Services"
        }
    ],
    "sg:phone":"+1 214 252 1558",
    "sg:postcode":"75205",
    "sg:province":"TX",
    "sg:tags":[
        "consultant",
        "search",
        "executive"
    ],
    "wof:name":"Global Professionals",
    "wof:placetype":"venue"
},
  "geometry": {"coordinates":[-96.784283,32.828119],"type":"Point"}
}