{
  "type": "Feature",
  "properties": {
    "iso:country":"US",
    "sg:address":"5775 Banks Rd",
    "sg:city":"Fort Worth",
    "sg:classifiers":[
        {
            "category":"Building & Trades",
            "subcategory":"Electrical",
            "type":"Services"
        }
    ],
    "sg:phone":"+1 817 478 6349",
    "sg:postcode":"76140",
    "sg:province":"TX",
    "sg:tags":[
        "electrical",
        "contractor"
    ],
    "wof:name":"John Williams Electric",
    "wof:placetype":"venue"
},
  "geometry": {"coordinates":[-97.25014,32.597087],"type":"Point"}
}