{
  "type": "Feature",
  "properties": {
    "iso:country":"US",
    "sg:address":"4400 S Washington St",
    "sg:city":"Amarillo",
    "sg:classifiers":[
        {
            "category":"Shopping",
            "type":"Retail Goods"
        }
    ],
    "sg:phone":"+1 806 355 7736",
    "sg:postcode":"79110",
    "sg:province":"TX",
    "sg:tags":[
        "pet",
        "shop",
        "supply"
    ],
    "wof:name":"Pitter Patter Pets",
    "wof:placetype":"venue"
},
  "geometry": {"coordinates":[-101.848534,35.164848],"type":"Point"}
}