{
  "type": "Feature",
  "properties": {
    "iso:country":"US",
    "sg:address":"6600 State Hwy 36 N",
    "sg:city":"Brenham",
    "sg:classifiers":[
        {
            "category":"Wholesale",
            "subcategory":"Machinery & Supplies",
            "type":"Manufacturing & Wholesale Goods"
        }
    ],
    "sg:phone":"+1 979 836 5027",
    "sg:postcode":"77833",
    "sg:province":"TX",
    "wof:name":"Schimdt Tractor Equipment",
    "wof:placetype":"venue"
},
  "geometry": {"coordinates":[-96.44423999999999,30.241707],"type":"Point"}
}