{
  "type": "Feature",
  "properties": {
    "iso:country":"US",
    "sg:address":"2110 W Eldorado Pkwy",
    "sg:city":"Mckinney",
    "sg:classifiers":[
        {
            "category":"Insurance",
            "subcategory":"Insurance Agent",
            "type":"Services"
        },
        {
            "category":"Insurance",
            "subcategory":"Hazard Insurance",
            "type":"Services"
        },
        {
            "category":"Insurance",
            "subcategory":"Title Insurance",
            "type":"Services"
        },
        {
            "category":"Insurance",
            "subcategory":"Life Insurance",
            "type":"Services"
        }
    ],
    "sg:phone":"+1 972 562 3133",
    "sg:postcode":"75070",
    "sg:province":"TX",
    "sg:tags":[
        "business",
        "auto",
        "commercial",
        "homeowner",
        "motorcycle",
        "renter"
    ],
    "wof:name":"Allstate Insurance Company - Fred Edwards",
    "wof:placetype":"venue"
},
  "geometry": {"coordinates":[-96.645607,33.17152],"type":"Point"}
}