{
  "type": "Feature",
  "properties": {
    "iso:country":"US",
    "sg:address":"908 2nd St",
    "sg:city":"Marble Falls",
    "sg:classifiers":[
        {
            "category":"Education",
            "subcategory":"Special Training",
            "type":"Public Place"
        }
    ],
    "sg:phone":"+1 830 693 8844",
    "sg:postcode":"78654",
    "sg:province":"TX",
    "sg:tags":[
        "instruction",
        "music"
    ],
    "wof:name":"Huntoon Music",
    "wof:placetype":"venue"
},
  "geometry": {"coordinates":[-98.27853399999999,30.571247],"type":"Point"}
}