{
  "type": "Feature",
  "properties": {
    "iso:country":"US",
    "sg:address":"5990 Lindenshire Ln",
    "sg:city":"Dallas",
    "sg:classifiers":[
        {
            "category":"Education",
            "subcategory":"School",
            "type":"Public Place"
        }
    ],
    "sg:phone":"+1 972 726 8742",
    "sg:postcode":"75230",
    "sg:province":"TX",
    "wof:name":"Magicmusiccom",
    "wof:placetype":"venue"
},
  "geometry": {"coordinates":[-96.804089,32.912092],"type":"Point"}
}