{
  "type": "Feature",
  "properties": {
    "iso:country":"US",
    "sg:address":"505 Parkside Dr",
    "sg:city":"Fort Worth",
    "sg:classifiers":[
        {
            "category":"Building & Trades",
            "subcategory":"Construction",
            "type":"Services"
        }
    ],
    "sg:phone":"+1 817 246 5641",
    "sg:postcode":"76108",
    "sg:province":"TX",
    "sg:tags":[
        "gate",
        "repair",
        "fence",
        "contractor"
    ],
    "wof:name":"Lynco Fence",
    "wof:placetype":"venue"
},
  "geometry": {"coordinates":[-97.470866,32.753],"type":"Point"}
}