{
  "type": "Feature",
  "properties": {
    "iso:country":"US",
    "sg:address":"979 Shady Oaks Dr",
    "sg:city":"Southlake",
    "sg:classifiers":[
        {
            "category":"Building & Trades",
            "subcategory":"Electrical",
            "type":"Services"
        }
    ],
    "sg:phone":"+1 817 481 6447",
    "sg:postcode":"76092",
    "sg:province":"TX",
    "sg:tags":[
        "electrician"
    ],
    "wof:name":"The Runyan Co",
    "wof:placetype":"venue"
},
  "geometry": {"coordinates":[-97.159685,32.95327],"type":"Point"}
}