{
  "type": "Feature",
  "properties": {
    "iso:country":"US",
    "sg:address":"509 Star Dust",
    "sg:city":"Crawford",
    "sg:classifiers":[
        {
            "category":"Education",
            "subcategory":"Junior College",
            "type":"Public Place"
        }
    ],
    "sg:phone":"+1 254 848 9994",
    "sg:postcode":"76638",
    "sg:province":"TX",
    "sg:tags":[
        "doll"
    ],
    "wof:name":"Wilde & Woolly Bears",
    "wof:placetype":"venue"
},
  "geometry": {"coordinates":[-97.330303,31.560741],"type":"Point"}
}