{
  "type": "Feature",
  "properties": {
    "iso:country":"US",
    "sg:address":"826 Office Park Cir",
    "sg:city":"Lewisville",
    "sg:classifiers":[
        {
            "category":"Manufacturing",
            "subcategory":"Tools & Machinery",
            "type":"Manufacturing & Wholesale Goods"
        }
    ],
    "sg:phone":"+1 972 353 4490",
    "sg:postcode":"75057",
    "sg:province":"TX",
    "sg:tags":[
        "measuring",
        "instrument",
        "electrical",
        "mfg"
    ],
    "wof:name":"ISI Technologies Inc",
    "wof:placetype":"venue"
},
  "geometry": {"coordinates":[-96.99798199999999,33.052105],"type":"Point"}
}