{
  "type": "Feature",
  "properties": {
    "iso:country":"US",
    "sg:address":"2205 US Hwy 77X Bus",
    "sg:city":"Harlingen",
    "sg:classifiers":[
        {
            "category":"Autos & Motor Vehicles",
            "subcategory":"Automobile Sales",
            "type":"Retail Goods"
        }
    ],
    "sg:phone":"+1 956 423 0316",
    "sg:postcode":"78550",
    "sg:province":"TX",
    "sg:tags":[
        "used"
    ],
    "wof:name":"Credit Used Cars Inc",
    "wof:placetype":"venue"
},
  "geometry": {"coordinates":[-97.70818300000001,26.213868],"type":"Point"}
}