{
  "type": "Feature",
  "properties": {
    "iso:country":"US",
    "sg:address":"3344 US Hwy 80 E",
    "sg:city":"Mesquite",
    "sg:classifiers":[
        {
            "category":"Utilities",
            "subcategory":"Telephone",
            "type":"Services"
        }
    ],
    "sg:phone":"+1 972 231 2185",
    "sg:postcode":"75149",
    "sg:province":"TX",
    "sg:tags":[
        "communication",
        "datum"
    ],
    "sg:website":"www.dataconninc.com",
    "wof:name":"Data Connection Inc",
    "wof:placetype":"venue"
},
  "geometry": {"coordinates":[-96.650639,32.791933],"type":"Point"}
}