{
  "type": "Feature",
  "properties": {
    "iso:country":"US",
    "sg:address":"2917 Pearl Ave",
    "sg:city":"Fort Worth",
    "sg:classifiers":[
        {
            "category":"Manufacturing",
            "subcategory":"Printing",
            "type":"Manufacturing & Wholesale Goods"
        }
    ],
    "sg:phone":"+1 817 626 1834",
    "sg:postcode":"76106",
    "sg:province":"TX",
    "sg:tags":[
        "newspaper"
    ],
    "wof:name":"Washington Daily",
    "wof:placetype":"venue"
},
  "geometry": {"coordinates":[-97.36212500000001,32.799268],"type":"Point"}
}