{
  "type": "Feature",
  "properties": {
    "iso:country":"US",
    "sg:address":"13539 Vargon St",
    "sg:city":"Dallas",
    "sg:classifiers":[
        {
            "category":"Professional",
            "subcategory":"Art Services",
            "type":"Services"
        }
    ],
    "sg:phone":"+1 972 437 0860",
    "sg:postcode":"75243",
    "sg:province":"TX",
    "sg:tags":[
        "commercial",
        "design"
    ],
    "wof:name":"Hotep Creations",
    "wof:placetype":"venue"
},
  "geometry": {"coordinates":[-96.74587099999999,32.931514],"type":"Point"}
}