{
  "type": "Feature",
  "properties": {
    "iso:country":"US",
    "sg:address":"102 S Bryan Rd",
    "sg:city":"Mission",
    "sg:classifiers":[
        {
            "category":"Government",
            "subcategory":"Office",
            "type":"Public Place"
        }
    ],
    "sg:phone":"+1 956 580 2531",
    "sg:postcode":"78572",
    "sg:province":"TX",
    "sg:tags":[
        "state",
        "resource"
    ],
    "wof:name":"Human Service Dept",
    "wof:placetype":"venue"
},
  "geometry": {"coordinates":[-98.311564,26.203791],"type":"Point"}
}