{
  "type": "Feature",
  "properties": {
    "iso:country":"US",
    "sg:address":"2406 Ashmont Dr",
    "sg:city":"Missouri City",
    "sg:classifiers":[
        {
            "category":"Professional",
            "type":"Services"
        }
    ],
    "sg:phone":"+1 281 438 0384",
    "sg:postcode":"77489",
    "sg:province":"TX",
    "wof:name":"Eagle Eye Protection Serv",
    "wof:placetype":"venue"
},
  "geometry": {"coordinates":[-95.540965,29.585507],"type":"Point"}
}