{
  "type": "Feature",
  "properties": {
    "iso:country":"US",
    "sg:address":"11 S Walnut Rd",
    "sg:city":"Belton",
    "sg:classifiers":[
        {
            "category":"Building & Trades",
            "subcategory":"Construction",
            "type":"Services"
        }
    ],
    "sg:phone":"+1 254 780 4581",
    "sg:postcode":"76513",
    "sg:province":"TX",
    "sg:tags":[
        "hanging",
        "contractor"
    ],
    "wof:name":"Schwertfeger Painting",
    "wof:placetype":"venue"
},
  "geometry": {"coordinates":[-97.44535399999999,31.159853],"type":"Point"}
}