{
  "type": "Feature",
  "properties": {
    "iso:country":"US",
    "sg:address":"3015 Earl St",
    "sg:city":"Houston",
    "sg:classifiers":[
        {
            "category":"Shopping",
            "subcategory":"Florist",
            "type":"Retail Goods"
        }
    ],
    "sg:phone":"+1 713 522 4748",
    "sg:postcode":"77098",
    "sg:province":"TX",
    "wof:name":"La Jardiniere",
    "wof:placetype":"venue"
},
  "geometry": {"coordinates":[-95.42289700000001,29.741199],"type":"Point"}
}