{
  "type": "Feature",
  "properties": {
    "iso:country":"US",
    "sg:address":"124 Grapevine Hwy",
    "sg:city":"Hurst",
    "sg:classifiers":[
        {
            "category":"Wholesale",
            "subcategory":"Hardware",
            "type":"Manufacturing & Wholesale Goods"
        }
    ],
    "sg:phone":"+1 817 428 1075",
    "sg:postcode":"76054",
    "sg:province":"TX",
    "wof:name":"Hardware & Fireplace Specialti",
    "wof:placetype":"venue"
},
  "geometry": {"coordinates":[-97.168441,32.870297],"type":"Point"}
}