{
  "type": "Feature",
  "properties": {
    "iso:country":"US",
    "sg:address":"1725 Brown St",
    "sg:city":"El Paso",
    "sg:classifiers":[
        {
            "category":"Health Services",
            "subcategory":"Doctor",
            "type":"Services"
        }
    ],
    "sg:phone":"+1 915 533 3486",
    "sg:postcode":"79902",
    "sg:province":"TX",
    "sg:tags":[
        "medical"
    ],
    "wof:name":"Pollet Randy J MD PA",
    "wof:placetype":"venue"
},
  "geometry": {"coordinates":[-106.486802,31.777043],"type":"Point"}
}