{
  "type": "Feature",
  "properties": {
    "iso:country":"US",
    "sg:address":"251 Horizon Blvd",
    "sg:city":"El Paso",
    "sg:classifiers":[
        {
            "category":"Restaurant",
            "type":"Food & Drink"
        }
    ],
    "sg:phone":"+1 915 860 1882",
    "sg:postcode":"79927",
    "sg:province":"TX",
    "sg:tags":[
        "eating"
    ],
    "wof:name":"Happy Boy's Salsitas",
    "wof:placetype":"venue"
},
  "geometry": {"coordinates":[-106.280446,31.648985],"type":"Point"}
}