{
  "type": "Feature",
  "properties": {
    "iso:country":"US",
    "sg:address":"9025 Forest Ln",
    "sg:city":"Dallas",
    "sg:classifiers":[
        {
            "category":"Shopping",
            "subcategory":"Mobile Phones",
            "type":"Retail Goods"
        }
    ],
    "sg:phone":"+1 972 231 2614",
    "sg:postcode":"75243",
    "sg:province":"TX",
    "sg:website":"www.radioshack.com",
    "wof:name":"Radioshack",
    "wof:placetype":"venue"
},
  "geometry": {"coordinates":[-96.727898,32.909302],"type":"Point"}
}