{
  "type": "Feature",
  "properties": {
    "iso:country":"US",
    "sg:address":"106 W Parsons St",
    "sg:city":"Manor",
    "sg:classifiers":[
        {
            "category":"Travel",
            "subcategory":"Hotels & Motels",
            "type":"Entertainment"
        }
    ],
    "sg:phone":"+1 512 272 8516",
    "sg:postcode":"78653",
    "sg:province":"TX",
    "wof:name":"Manor Inn Hotel",
    "wof:placetype":"venue"
},
  "geometry": {"coordinates":[-97.55779,30.341061],"type":"Point"}
}