{
  "type": "Feature",
  "properties": {
    "iso:country":"US",
    "sg:address":"140 Cedar Park",
    "sg:city":"San Marcos",
    "sg:classifiers":[
        {
            "category":"Personal",
            "subcategory":"Beauty Salon",
            "type":"Services"
        }
    ],
    "sg:phone":"+1 512 353 5676",
    "sg:postcode":"78666",
    "sg:province":"TX",
    "sg:tags":[
        "shop"
    ],
    "wof:name":"K Nails",
    "wof:placetype":"venue"
},
  "geometry": {"coordinates":[-97.983808,29.858769],"type":"Point"}
}