{
  "type": "Feature",
  "properties": {
    "iso:country":"US",
    "sg:address":"809 W 12th St Ste F",
    "sg:city":"Austin",
    "sg:classifiers":[
        {
            "category":"Professional",
            "subcategory":"Art Services",
            "type":"Services"
        }
    ],
    "sg:phone":"+1 512 797 4600",
    "sg:postcode":"78701",
    "sg:province":"TX",
    "sg:tags":[
        "graphic",
        "commercial",
        "designer",
        "artist"
    ],
    "wof:name":"Artifakt Digital",
    "wof:placetype":"venue"
},
  "geometry": {"coordinates":[-97.748558,30.27609],"type":"Point"}
}