{
  "type": "Feature",
  "properties": {
    "iso:country":"US",
    "sg:address":"811 Highway 35 S",
    "sg:city":"Rockport",
    "sg:classifiers":[
        {
            "category":"Real Estate",
            "subcategory":"Real Estate Operator",
            "type":"Services"
        }
    ],
    "sg:phone":"+1 806 763 5323",
    "sg:postcode":"78382",
    "sg:province":"TX",
    "sg:tags":[
        "apartment"
    ],
    "wof:name":"Rockport Housing Associates A Texas Limited Partnership",
    "wof:placetype":"venue"
},
  "geometry": {"coordinates":[-97.060452,28.020768],"type":"Point"}
}