{
  "type": "Feature",
  "properties": {
    "iso:country":"US",
    "sg:address":"6533 91st Pl",
    "sg:city":"Lubbock",
    "sg:classifiers":[
        {
            "category":"Professional",
            "subcategory":"Lawyer & Legal Services",
            "type":"Services"
        }
    ],
    "sg:phone":"+1 940 988 4357",
    "sg:postcode":"79424",
    "sg:province":"TX",
    "sg:tags":[
        "attorney",
        "practice"
    ],
    "wof:name":"Law Office Of Melissa Morgan P",
    "wof:placetype":"venue"
},
  "geometry": {"coordinates":[-101.95946600000001,33.510878],"type":"Point"}
}