{
  "type": "Feature",
  "properties": {
    "iso:country":"US",
    "sg:address":"8209 Kentwood Dr",
    "sg:city":"Fort Worth",
    "sg:classifiers":[
        {
            "category":"Insurance",
            "subcategory":"Insurance Agent",
            "type":"Services"
        }
    ],
    "sg:phone":"+1 817 498 2654",
    "sg:postcode":"76180",
    "sg:province":"TX",
    "wof:name":"Insurance Services",
    "wof:placetype":"venue"
},
  "geometry": {"coordinates":[-97.19326100000001,32.894116],"type":"Point"}
}