{
  "type": "Feature",
  "properties": {
    "iso:country":"US",
    "sg:address":"6412 N Navarro St",
    "sg:city":"Victoria",
    "sg:classifiers":[
        {
            "category":"Government",
            "subcategory":"Office",
            "type":"Public Place"
        }
    ],
    "sg:phone":"+1 361 573 4397",
    "sg:postcode":"77904",
    "sg:province":"TX",
    "sg:tags":[
        "armed",
        "force",
        "recruiting"
    ],
    "wof:name":"US Army Recruiting",
    "wof:placetype":"venue"
},
  "geometry": {"coordinates":[-96.996888,28.856179],"type":"Point"}
}