{
  "type": "Feature",
  "properties": {
    "iso:country":"US",
    "sg:address":"3141 Cliffoak Dr",
    "sg:city":"Dallas",
    "sg:classifiers":[
        {
            "category":"Shopping",
            "subcategory":"Hobbies, Toys, & Games",
            "type":"Retail Goods"
        }
    ],
    "sg:phone":"+1 214 376 6833",
    "sg:postcode":"75233",
    "sg:province":"TX",
    "wof:name":"Paiges Enterprise",
    "wof:placetype":"venue"
},
  "geometry": {"coordinates":[-96.87119,32.702902],"type":"Point"}
}