{
  "type": "Feature",
  "properties": {
    "iso:country":"US",
    "sg:address":"1580 W Main St",
    "sg:city":"Lancaster",
    "sg:classifiers":[
        {
            "category":"Retail",
            "subcategory":"Auto Repair",
            "type":"Services"
        }
    ],
    "sg:phone":"+1 972 227 4753",
    "sg:postcode":"75146",
    "sg:province":"TX",
    "wof:name":"Hussey Auto Small Engine",
    "wof:placetype":"venue"
},
  "geometry": {"coordinates":[-96.79052,32.582932],"type":"Point"}
}