{
  "type": "Feature",
  "properties": {
    "iso:country":"US",
    "sg:address":"529 Mountain Dr",
    "sg:city":"Kerrville",
    "sg:classifiers":[
        {
            "category":"Building & Trades",
            "subcategory":"Landscaping Services",
            "type":"Services"
        }
    ],
    "sg:phone":"+1 830 370 9201",
    "sg:postcode":"78028",
    "sg:province":"TX",
    "sg:tags":[
        "arborist",
        "tree"
    ],
    "wof:name":"John Goodman Tree Svc",
    "wof:placetype":"venue"
},
  "geometry": {"coordinates":[-99.179367,30.01693],"type":"Point"}
}