{
  "type": "Feature",
  "properties": {
    "iso:country":"US",
    "sg:address":"1608 Broadmoor Dr",
    "sg:city":"Austin",
    "sg:classifiers":[
        {
            "category":"Retail",
            "subcategory":"Repair Shop",
            "type":"Services"
        }
    ],
    "sg:phone":"+1 512 371 0301",
    "sg:postcode":"78723",
    "sg:province":"TX",
    "sg:tags":[
        "welding"
    ],
    "wof:name":"Cortinas Welding",
    "wof:placetype":"venue"
},
  "geometry": {"coordinates":[-97.69740299999999,30.306458],"type":"Point"}
}