{
  "type": "Feature",
  "properties": {
    "iso:country":"US",
    "sg:address":"2255 N Bonnie Brae St",
    "sg:city":"Denton",
    "sg:classifiers":[
        {
            "category":"Organizations",
            "subcategory":"Religious Organization",
            "type":"Services"
        }
    ],
    "sg:phone":"+1 940 565 1770",
    "sg:postcode":"76207",
    "sg:province":"TX",
    "sg:tags":[
        "church"
    ],
    "sg:website":"www.iccdenton.org",
    "wof:name":"Immaculate Conception Catholic",
    "wof:placetype":"venue"
},
  "geometry": {"coordinates":[-97.16086199999999,33.237545],"type":"Point"}
}