{
  "type": "Feature",
  "properties": {
    "iso:country":"US",
    "sg:address":"720 E US Hwy 83",
    "sg:city":"Mcallen",
    "sg:classifiers":[
        {
            "category":"Manufacturing",
            "subcategory":"Tools & Machinery",
            "type":"Manufacturing & Wholesale Goods"
        }
    ],
    "sg:phone":"+1 956 686 8311",
    "sg:postcode":"78501",
    "sg:province":"TX",
    "sg:tags":[
        "food",
        "product"
    ],
    "wof:name":"Fmc Corp",
    "wof:placetype":"venue"
},
  "geometry": {"coordinates":[-98.211814,26.199932],"type":"Point"}
}