{
  "type": "Feature",
  "properties": {
    "iso:country":"US",
    "sg:address":"10600 Ashmore Dr",
    "sg:city":"Fort Worth",
    "sg:classifiers":[
        {
            "category":"Government",
            "subcategory":"Office",
            "type":"Public Place"
        }
    ],
    "sg:phone":"+1 817 750 2316",
    "sg:postcode":"76131",
    "sg:province":"TX",
    "wof:name":"Total Erosion Services",
    "wof:placetype":"venue"
},
  "geometry": {"coordinates":[-97.37093,32.921329],"type":"Point"}
}