{
  "type": "Feature",
  "properties": {
    "iso:country":"US",
    "sg:address":"2215 86th St",
    "sg:city":"Lubbock",
    "sg:classifiers":[
        {
            "category":"Recreation",
            "type":"Entertainment"
        }
    ],
    "sg:phone":"+1 806 748 1993",
    "sg:postcode":"79423",
    "sg:province":"TX",
    "sg:tags":[
        "club",
        "membership"
    ],
    "wof:name":"Pedator Wrestling Club",
    "wof:placetype":"venue"
},
  "geometry": {"coordinates":[-101.86596,33.516511],"type":"Point"}
}