{
  "type": "Feature",
  "properties": {
    "iso:country":"US",
    "sg:address":"117 Main St",
    "sg:city":"Muleshoe",
    "sg:classifiers":[
        {
            "category":"Shopping",
            "subcategory":"Stationery & Office Supplies",
            "type":"Retail Goods"
        }
    ],
    "sg:phone":"+1 806 272 3113",
    "sg:postcode":"79347",
    "sg:province":"TX",
    "wof:name":"Williams Bros Office Supply",
    "wof:placetype":"venue"
},
  "geometry": {"coordinates":[-102.722882,34.225451],"type":"Point"}
}