{
  "type": "Feature",
  "properties": {
    "iso:country":"US",
    "sg:address":"4016 Ridglea Country Club Dr",
    "sg:city":"Fort Worth",
    "sg:classifiers":[
        {
            "category":"Professional",
            "subcategory":"Business Services",
            "type":"Services"
        }
    ],
    "sg:phone":"+1 817 732 2544",
    "sg:postcode":"76126",
    "sg:province":"TX",
    "wof:name":"Big Blue Pool Service",
    "wof:placetype":"venue"
},
  "geometry": {"coordinates":[-97.43146,32.693079],"type":"Point"}
}