{
  "type": "Feature",
  "properties": {
    "iso:country":"US",
    "sg:address":"8420 FM 14",
    "sg:city":"Tyler",
    "sg:classifiers":[
        {
            "category":"Autos & Motor Vehicles",
            "subcategory":"Automobile Sales",
            "type":"Retail Goods"
        }
    ],
    "sg:phone":"+1 903 592 1588",
    "sg:postcode":"75706",
    "sg:province":"TX",
    "sg:tags":[
        "car",
        "used",
        "dealer"
    ],
    "wof:name":"Sam's Auto Sales",
    "wof:placetype":"venue"
},
  "geometry": {"coordinates":[-95.28164200000001,32.399746],"type":"Point"}
}