{
  "type": "Feature",
  "properties": {
    "iso:country":"US",
    "sg:address":"1120 SW 3rd Ave",
    "sg:city":"Perryton",
    "sg:classifiers":[
        {
            "category":"Wholesale",
            "subcategory":"Stationery",
            "type":"Manufacturing & Wholesale Goods"
        }
    ],
    "sg:phone":"+1 806 435 2884",
    "sg:postcode":"79070",
    "sg:province":"TX",
    "sg:tags":[
        "supply"
    ],
    "wof:name":"J&T Enterprises",
    "wof:placetype":"venue"
},
  "geometry": {"coordinates":[-100.817211,36.397557],"type":"Point"}
}