{
  "type": "Feature",
  "properties": {
    "iso:country":"US",
    "sg:address":"6206 Merriwood Dr",
    "sg:city":"Austin",
    "sg:classifiers":[
        {
            "category":"Retail",
            "subcategory":"Repair Shop",
            "type":"Services"
        }
    ],
    "sg:phone":"+1 512 478 5728",
    "sg:postcode":"78745",
    "sg:province":"TX",
    "sg:tags":[
        "appliance"
    ],
    "wof:name":"Appliance Service Ctr",
    "wof:placetype":"venue"
},
  "geometry": {"coordinates":[-97.780647,30.200532],"type":"Point"}
}