{
  "type": "Feature",
  "properties": {
    "iso:country":"US",
    "sg:address":"702 Main St",
    "sg:city":"Houston",
    "sg:classifiers":[
        {
            "category":"Coffee & Tea",
            "type":"Food & Drink"
        },
        {
            "category":"Cafe",
            "type":"Food & Drink"
        },
        {
            "category":"Bakery",
            "type":"Food & Drink"
        }
    ],
    "sg:menulink":"http://www.allmenus.com/tx/houston/234075-nestle-toll-house-cafe/menu/",
    "sg:phone":"+1 713 229 0882",
    "sg:postcode":"77002",
    "sg:province":"TX",
    "sg:tags":[
        "american",
        "pastry"
    ],
    "wof:name":"Nestle Toll House Cafe",
    "wof:placetype":"venue"
},
  "geometry": {"coordinates":[-95.36326800000001,29.759169],"type":"Point"}
}