{
  "type": "Feature",
  "properties": {
    "iso:country":"US",
    "sg:address":"738 Oakland St",
    "sg:city":"Grand Prairie",
    "sg:classifiers":[
        {
            "category":"Freight",
            "type":"Transportation"
        }
    ],
    "sg:phone":"+1 972 263 1422",
    "sg:postcode":"75052",
    "sg:province":"TX",
    "sg:tags":[
        "trucking"
    ],
    "wof:name":"Vega Borrego Transport",
    "wof:placetype":"venue"
},
  "geometry": {"coordinates":[-97.01444600000001,32.68264],"type":"Point"}
}