{
  "type": "Feature",
  "properties": {
    "iso:country":"US",
    "sg:address":"804 W Main St",
    "sg:city":"Cuero",
    "sg:classifiers":[
        {
            "category":"Shopping",
            "subcategory":"Computers & Home Electronics",
            "type":"Retail Goods"
        }
    ],
    "sg:phone":"+1 361 275 9380",
    "sg:postcode":"77954",
    "sg:province":"TX",
    "sg:tags":[
        "electrical",
        "contractor"
    ],
    "wof:name":"Greg S Electric",
    "wof:placetype":"venue"
},
  "geometry": {"coordinates":[-97.298343,29.093095],"type":"Point"}
}