{
  "type": "Feature",
  "properties": {
    "iso:country":"US",
    "sg:address":"120 S Broadway Ave",
    "sg:city":"Tyler",
    "sg:classifiers":[
        {
            "category":"Professional",
            "subcategory":"Lawyer & Legal Services",
            "type":"Services"
        }
    ],
    "sg:phone":"+1 903 593 8040",
    "sg:postcode":"75702",
    "sg:province":"TX",
    "wof:name":"Ellis Curt Attorney At Law",
    "wof:placetype":"venue"
},
  "geometry": {"coordinates":[-95.300747,32.349879],"type":"Point"}
}