{
  "type": "Feature",
  "properties": {
    "iso:country":"US",
    "sg:address":"407 E Co Rd 138",
    "sg:city":"Midland",
    "sg:classifiers":[
        {
            "category":"Building & Trades",
            "subcategory":"Pest Control",
            "type":"Services"
        }
    ],
    "sg:phone":"+1 432 570 7378",
    "sg:postcode":"79706",
    "sg:province":"TX",
    "wof:name":"Bill Schneider's Pest Control",
    "wof:placetype":"venue"
},
  "geometry": {"coordinates":[-102.054411,31.932297],"type":"Point"}
}