{
  "type": "Feature",
  "properties": {
    "iso:country":"US",
    "sg:address":"1119 Singleton Blvd",
    "sg:city":"Dallas",
    "sg:classifiers":[
        {
            "category":"Real Estate",
            "subcategory":"Real Estate Services",
            "type":"Services"
        }
    ],
    "sg:phone":"+1 214 939 1119",
    "sg:postcode":"75212",
    "sg:province":"TX",
    "sg:tags":[
        "management",
        "property"
    ],
    "wof:name":"HMK LTD",
    "wof:placetype":"venue"
},
  "geometry": {"coordinates":[-96.839949,32.778667],"type":"Point"}
}