{
  "type": "Feature",
  "properties": {
    "iso:country":"US",
    "sg:address":"4412 18th St",
    "sg:city":"Lubbock",
    "sg:classifiers":[
        {
            "category":"Shopping",
            "subcategory":"Used Merchandise",
            "type":"Retail Goods"
        }
    ],
    "sg:phone":"+1 806 797 1297",
    "sg:postcode":"79416",
    "sg:province":"TX",
    "wof:name":"Marx Books",
    "wof:placetype":"venue"
},
  "geometry": {"coordinates":[-101.90705199999999,33.579417],"type":"Point"}
}