{
  "type": "Feature",
  "properties": {
    "iso:country":"US",
    "sg:address":"1119 Kiser Ln",
    "sg:city":"Marion",
    "sg:classifiers":[
        {
            "category":"Building & Trades",
            "subcategory":"Landscaping Services",
            "type":"Services"
        }
    ],
    "sg:phone":"+1 830 914 2485",
    "sg:postcode":"78124",
    "sg:province":"TX",
    "wof:name":"Darrens Stump and Tree Svcs",
    "wof:placetype":"venue"
},
  "geometry": {"coordinates":[-98.159873,29.572076],"type":"Point"}
}