{
  "type": "Feature",
  "properties": {
    "iso:country":"US",
    "sg:address":"7400 W Vickery Blvd",
    "sg:city":"Fort Worth",
    "sg:classifiers":[
        {
            "category":"Recreation",
            "type":"Entertainment"
        }
    ],
    "sg:phone":"+1 817 737 3829",
    "sg:postcode":"76116",
    "sg:province":"TX",
    "sg:tags":[
        "stable"
    ],
    "wof:name":"Ft Worth Horseshoe Club",
    "wof:placetype":"venue"
},
  "geometry": {"coordinates":[-97.440242,32.699301],"type":"Point"}
}