{
  "type": "Feature",
  "properties": {
    "iso:country":"US",
    "sg:address":"101 W Pearl St",
    "sg:city":"Granbury",
    "sg:classifiers":[
        {
            "category":"Professional",
            "subcategory":"Lawyer & Legal Services",
            "type":"Services"
        }
    ],
    "sg:phone":"+1 817 573 4000",
    "sg:postcode":"76048",
    "sg:province":"TX",
    "wof:name":"Doshier Association PC",
    "wof:placetype":"venue"
},
  "geometry": {"coordinates":[-97.787646,32.442208],"type":"Point"}
}