{
  "type": "Feature",
  "properties": {
    "iso:country":"US",
    "sg:address":"3109 Normandy Dr",
    "sg:city":"Mc Kinney",
    "sg:classifiers":[
        {
            "category":"Manufacturing",
            "subcategory":"Tools & Machinery",
            "type":"Manufacturing & Wholesale Goods"
        }
    ],
    "sg:phone":"+1 972 542 2002",
    "sg:postcode":"75070",
    "sg:province":"TX",
    "sg:tags":[
        "compressor",
        "mfg"
    ],
    "wof:name":"Fuelmaker Corp",
    "wof:placetype":"venue"
},
  "geometry": {"coordinates":[-96.65152399999999,33.168476],"type":"Point"}
}