{
  "type": "Feature",
  "properties": {
    "iso:country":"US",
    "sg:address":"4402 Chippendale Rd",
    "sg:city":"Brookshire",
    "sg:classifiers":[
        {
            "category":"Wholesale",
            "subcategory":"Electrical",
            "type":"Manufacturing & Wholesale Goods"
        }
    ],
    "sg:phone":"+1 281 346 2737",
    "sg:postcode":"77441",
    "sg:province":"TX",
    "sg:tags":[
        "supply",
        "sign"
    ],
    "wof:name":"Interactive Lighting Systems",
    "wof:placetype":"venue"
},
  "geometry": {"coordinates":[-95.948042,29.731958],"type":"Point"}
}