{
  "type": "Feature",
  "properties": {
    "iso:country":"US",
    "sg:address":"1734 N Greenville Ave",
    "sg:city":"Richardson",
    "sg:classifiers":[
        {
            "category":"Building & Trades",
            "subcategory":"Construction",
            "type":"Services"
        }
    ],
    "sg:phone":"+1 214 272 8885",
    "sg:postcode":"75081",
    "sg:province":"TX",
    "sg:tags":[
        "contractor"
    ],
    "wof:name":"Ramco",
    "wof:placetype":"venue"
},
  "geometry": {"coordinates":[-96.71543,32.97144],"type":"Point"}
}