{
  "type": "Feature",
  "properties": {
    "iso:country":"US",
    "sg:address":"449 Natalen St",
    "sg:city":"San Antonio",
    "sg:classifiers":[
        {
            "category":"Real Estate",
            "subcategory":"Real Estate Operator",
            "type":"Services"
        }
    ],
    "sg:phone":"+1 210 826 6110",
    "sg:postcode":"78209",
    "sg:province":"TX",
    "sg:tags":[
        "apartment"
    ],
    "wof:name":"Natalen Square Apartments",
    "wof:placetype":"venue"
},
  "geometry": {"coordinates":[-98.462146,29.455814],"type":"Point"}
}