{
  "type": "Feature",
  "properties": {
    "iso:country":"US",
    "sg:address":"8450 Cambridge St",
    "sg:city":"Houston",
    "sg:classifiers":[
        {
            "category":"Shopping",
            "subcategory":"Clothing, Apparel, & Fashions",
            "type":"Retail Goods"
        }
    ],
    "sg:phone":"+1 713 383 6462",
    "sg:postcode":"77054",
    "sg:province":"TX",
    "sg:tags":[
        "family"
    ],
    "wof:name":"Big Sister Lil Bro",
    "wof:placetype":"venue"
},
  "geometry": {"coordinates":[-95.39561399999999,29.683826],"type":"Point"}
}