{
  "type": "Feature",
  "properties": {
    "iso:country":"US",
    "sg:address":"633 E Ada St",
    "sg:city":"Miami",
    "sg:classifiers":[
        {
            "category":"Communications",
            "type":"Services"
        }
    ],
    "sg:phone":"+1 806 868 4001",
    "sg:postcode":"79059",
    "sg:province":"TX",
    "sg:tags":[
        "communication"
    ],
    "wof:name":"Harold Stone Communications",
    "wof:placetype":"venue"
},
  "geometry": {"coordinates":[-100.631338,35.694598],"type":"Point"}
}