{
  "type": "Feature",
  "properties": {
    "iso:country":"US",
    "sg:address":"3415 Katy Fwy",
    "sg:city":"Houston",
    "sg:classifiers":[
        {
            "category":"Shopping",
            "subcategory":"News",
            "type":"Retail Goods"
        }
    ],
    "sg:phone":"+1 713 869 7878",
    "sg:postcode":"77007",
    "sg:province":"TX",
    "wof:name":"Studemont Video",
    "wof:placetype":"venue"
},
  "geometry": {"coordinates":[-95.39409499999999,29.776111],"type":"Point"}
}