{
  "type": "Feature",
  "properties": {
    "iso:country":"US",
    "sg:address":"2515 Southwest Fwy",
    "sg:city":"Houston",
    "sg:classifiers":[
        {
            "category":"Restaurant",
            "type":"Food & Drink"
        }
    ],
    "sg:menulink":"http://www.allmenus.com/tx/houston/51291-ihop-restaurant/menu/",
    "sg:phone":"+1 713 520 9908",
    "sg:postcode":"77098",
    "sg:province":"TX",
    "sg:tags":[
        "american"
    ],
    "wof:name":"Ihop Restaurant",
    "wof:placetype":"venue"
},
  "geometry": {"coordinates":[-95.417343,29.730213],"type":"Point"}
}