{
  "type": "Feature",
  "properties": {
    "iso:country":"US",
    "sg:address":"1123 Summer Brook",
    "sg:city":"Sugar Land",
    "sg:classifiers":[
        {
            "category":"Professional",
            "type":"Services"
        }
    ],
    "sg:phone":"+1 281 343 8715",
    "sg:postcode":"77479",
    "sg:province":"TX",
    "wof:name":"Greatwood Womens Organiz",
    "wof:placetype":"venue"
},
  "geometry": {"coordinates":[-95.672939,29.542138],"type":"Point"}
}