{
  "type": "Feature",
  "properties": {
    "iso:country":"US",
    "sg:address":"601 Deerfoot Dr",
    "sg:city":"Round Rock",
    "sg:classifiers":[
        {
            "category":"Retail",
            "subcategory":"Portrait Studio",
            "type":"Services"
        }
    ],
    "sg:phone":"+1 512 218 1296",
    "sg:postcode":"78664",
    "sg:province":"TX",
    "sg:tags":[
        "photo"
    ],
    "wof:name":"Sweet Photography",
    "wof:placetype":"venue"
},
  "geometry": {"coordinates":[-97.67188400000001,30.507311],"type":"Point"}
}