{
  "type": "Feature",
  "properties": {
    "iso:country":"US",
    "sg:address":"9804 Lavera Dr",
    "sg:city":"Austin",
    "sg:classifiers":[
        {
            "category":"Professional",
            "subcategory":"Business Services",
            "type":"Services"
        }
    ],
    "sg:phone":"+1 512 918 0603",
    "sg:postcode":"78726",
    "sg:province":"TX",
    "wof:name":"Really Cool Stuff",
    "wof:placetype":"venue"
},
  "geometry": {"coordinates":[-97.830828,30.435054],"type":"Point"}
}