{
  "type": "Feature",
  "properties": {
    "iso:country":"US",
    "sg:address":"1207 Alcock St",
    "sg:city":"Pampa",
    "sg:classifiers":[
        {
            "category":"Retail",
            "subcategory":"Auto Repair",
            "type":"Services"
        }
    ],
    "sg:phone":"+1 806 688 0010",
    "sg:postcode":"79065",
    "sg:province":"TX",
    "sg:tags":[
        "glass",
        "replacement"
    ],
    "wof:name":"CGC Auto Glass",
    "wof:placetype":"venue"
},
  "geometry": {"coordinates":[-100.976293,35.533007],"type":"Point"}
}