{
  "type": "Feature",
  "properties": {
    "iso:country":"US",
    "sg:address":"3606 High Sierra Ln",
    "sg:city":"Houston",
    "sg:classifiers":[
        {
            "category":"Utilities",
            "subcategory":"Mobile Phone",
            "type":"Services"
        },
        {
            "category":"Shopping",
            "type":"Retail Goods"
        }
    ],
    "sg:phone":"+1 281 578 9775",
    "sg:postcode":"77084",
    "sg:province":"TX",
    "sg:tags":[
        "communication",
        "radiotelephone",
        "cellular",
        "telephone"
    ],
    "wof:name":"A K Wireless",
    "wof:placetype":"venue"
},
  "geometry": {"coordinates":[-95.691669,29.823903],"type":"Point"}
}