{
  "type": "Feature",
  "properties": {
    "iso:country":"US",
    "sg:address":"11666 Southlake Dr",
    "sg:city":"Houston",
    "sg:classifiers":[
        {
            "category":"Building & Trades",
            "subcategory":"Plumbing",
            "type":"Services"
        }
    ],
    "sg:phone":"+1 281 293 0509",
    "sg:postcode":"77077",
    "sg:province":"TX",
    "sg:tags":[
        "contractor"
    ],
    "wof:name":"Prince AC & Heating Inc",
    "wof:placetype":"venue"
},
  "geometry": {"coordinates":[-95.58451700000001,29.741451],"type":"Point"}
}