{
  "type": "Feature",
  "properties": {
    "iso:country":"US",
    "sg:address":"2038 Young St",
    "sg:city":"Grand Prairie",
    "sg:classifiers":[
        {
            "category":"Retail",
            "subcategory":"Auto Repair",
            "type":"Services"
        }
    ],
    "sg:phone":"+1 972 262 3192",
    "sg:postcode":"75050",
    "sg:province":"TX",
    "sg:tags":[
        "repairing",
        "automobile"
    ],
    "wof:name":"Ac Automotive",
    "wof:placetype":"venue"
},
  "geometry": {"coordinates":[-96.975601,32.746899],"type":"Point"}
}