{
  "type": "Feature",
  "properties": {
    "iso:country":"US",
    "sg:address":"1003 W Oak St",
    "sg:city":"Denton",
    "sg:classifiers":[
        {
            "category":"Building & Trades",
            "subcategory":"Construction",
            "type":"Services"
        }
    ],
    "sg:phone":"+1 940 387 5322",
    "sg:postcode":"76201",
    "sg:province":"TX",
    "sg:tags":[
        "home",
        "contractor",
        "general",
        "new"
    ],
    "wof:name":"Distinct Designs Construction",
    "wof:placetype":"venue"
},
  "geometry": {"coordinates":[-97.14319500000001,33.215597],"type":"Point"}
}