{
  "type": "Feature",
  "properties": {
    "iso:country":"US",
    "sg:address":"4820 S State Hwy 91",
    "sg:city":"Denison",
    "sg:classifiers":[
        {
            "category":"Recreation",
            "type":"Entertainment"
        }
    ],
    "sg:phone":"+1 903 465 4775",
    "sg:postcode":"75020",
    "sg:province":"TX",
    "sg:tags":[
        "parlor",
        "billiard"
    ],
    "wof:name":"Break Time",
    "wof:placetype":"venue"
},
  "geometry": {"coordinates":[-96.57131800000001,33.702024],"type":"Point"}
}