{
  "type": "Feature",
  "properties": {
    "iso:country":"US",
    "sg:address":"940 Keller Pkwy",
    "sg:city":"Keller",
    "sg:classifiers":[
        {
            "category":"Building & Trades",
            "subcategory":"Construction",
            "type":"Services"
        }
    ],
    "sg:phone":"+1 817 431 1143",
    "sg:postcode":"76248",
    "sg:province":"TX",
    "sg:tags":[
        "coping",
        "plastering",
        "tiling",
        "pool",
        "swimming"
    ],
    "wof:name":"Leslie Pool Mart Inc",
    "wof:placetype":"venue"
},
  "geometry": {"coordinates":[-97.232722,32.934287],"type":"Point"}
}