{
  "type": "Feature",
  "properties": {
    "iso:country":"US",
    "sg:address":"1414 E University Dr",
    "sg:city":"Edinburg",
    "sg:classifiers":[
        {
            "category":"Shopping",
            "subcategory":"Books",
            "type":"Retail Goods"
        }
    ],
    "sg:phone":"+1 956 287 7461",
    "sg:postcode":"78539",
    "sg:province":"TX",
    "sg:tags":[
        "bible"
    ],
    "wof:name":"Christian Supply",
    "wof:placetype":"venue"
},
  "geometry": {"coordinates":[-98.147807,26.299212],"type":"Point"}
}