{
  "type": "Feature",
  "properties": {
    "iso:country":"US",
    "sg:address":"5111 Royal Ln",
    "sg:city":"Dallas",
    "sg:classifiers":[
        {
            "category":"Professional",
            "subcategory":"Business Services",
            "type":"Services"
        }
    ],
    "sg:phone":"+1 214 369 7536",
    "sg:postcode":"75229",
    "sg:province":"TX",
    "sg:tags":[
        "auctioneer"
    ],
    "wof:name":"Walters & Assoc",
    "wof:placetype":"venue"
},
  "geometry": {"coordinates":[-96.812603,32.895014],"type":"Point"}
}