{
  "type": "Feature",
  "properties": {
    "iso:country":"US",
    "sg:address":"517 E Houston St",
    "sg:city":"Floydada",
    "sg:classifiers":[
        {
            "category":"Wholesale",
            "subcategory":"Farm Supplies",
            "type":"Manufacturing & Wholesale Goods"
        }
    ],
    "sg:phone":"+1 806 983 2233",
    "sg:postcode":"79235",
    "sg:province":"TX",
    "sg:tags":[
        "fertilizer"
    ],
    "wof:name":"Davis Farm Supply Inc",
    "wof:placetype":"venue"
},
  "geometry": {"coordinates":[-101.328373,33.978995],"type":"Point"}
}