{
  "type": "Feature",
  "properties": {
    "iso:country":"US",
    "sg:address":"1519 Rustic Trl",
    "sg:city":"Allen",
    "sg:classifiers":[
        {
            "category":"Home & Garden",
            "subcategory":"Building Materials",
            "type":"Retail Goods"
        }
    ],
    "sg:phone":"+1 972 396 9833",
    "sg:postcode":"75002",
    "sg:province":"TX",
    "wof:name":"D & S Overhead Door",
    "wof:placetype":"venue"
},
  "geometry": {"coordinates":[-96.63129000000001,33.110631],"type":"Point"}
}