{
  "type": "Feature",
  "properties": {
    "iso:country":"US",
    "sg:address":"2213 Fillmore St",
    "sg:city":"Wichita Falls",
    "sg:classifiers":[
        {
            "category":"Professional",
            "subcategory":"Detective & Security Services",
            "type":"Services"
        },
        {
            "category":"Wholesale",
            "subcategory":"Electrical",
            "type":"Manufacturing & Wholesale Goods"
        }
    ],
    "sg:phone":"+1 940 687 7233",
    "sg:postcode":"76309",
    "sg:province":"TX",
    "sg:tags":[
        "control",
        "system"
    ],
    "wof:name":"First Homeland Security",
    "wof:placetype":"venue"
},
  "geometry": {"coordinates":[-98.526005,33.890083],"type":"Point"}
}