{
  "type": "Feature",
  "properties": {
    "iso:country":"US",
    "sg:address":"2011 Little Elm Trail Ste 110",
    "sg:city":"Cedar Park",
    "sg:classifiers":[
        {
            "category":"Coffee & Tea",
            "type":"Food & Drink"
        }
    ],
    "sg:phone":"+1 512 506 9592",
    "sg:postcode":"78613",
    "sg:province":"TX",
    "wof:name":"Roaster's Coffee Haven",
    "wof:placetype":"venue"
},
  "geometry": {"coordinates":[-97.822581,30.509973],"type":"Point"}
}