{
  "type": "Feature",
  "properties": {
    "iso:country":"US",
    "sg:address":"2821 Salado Trl",
    "sg:city":"Fort Worth",
    "sg:classifiers":[
        {
            "category":"Professional",
            "subcategory":"Computer Services",
            "type":"Services"
        }
    ],
    "sg:phone":"+1 817 595 9291",
    "sg:postcode":"76118",
    "sg:province":"TX",
    "sg:tags":[
        "datum"
    ],
    "wof:name":"Specialty Baskets",
    "wof:placetype":"venue"
},
  "geometry": {"coordinates":[-97.19429,32.79809],"type":"Point"}
}