{
  "type": "Feature",
  "properties": {
    "iso:country":"US",
    "sg:address":"3111 Midwestern Pkwy",
    "sg:city":"Wichita Falls",
    "sg:classifiers":[
        {
            "category":"Bakery",
            "type":"Food & Drink"
        }
    ],
    "sg:menulink":"http://www.allmenus.com/tx/wichita-falls/231816-mrs-fields/menu/",
    "sg:phone":"+1 940 696 3111",
    "sg:postcode":"76308",
    "sg:province":"TX",
    "sg:tags":[
        "american",
        "pastry"
    ],
    "wof:name":"Mrs. Fields",
    "wof:placetype":"venue"
},
  "geometry": {"coordinates":[-98.53281800000001,33.870488],"type":"Point"}
}