{
  "type": "Feature",
  "properties": {
    "iso:country":"US",
    "sg:address":"4305 State Hwy 110",
    "sg:city":"Tyler",
    "sg:classifiers":[
        {
            "category":"Autos & Motor Vehicles",
            "subcategory":"Auto Supplies",
            "type":"Retail Goods"
        }
    ],
    "sg:phone":"+1 903 592 8971",
    "sg:postcode":"75704",
    "sg:province":"TX",
    "wof:name":"Hillard Truck Sales & Parts",
    "wof:placetype":"venue"
},
  "geometry": {"coordinates":[-95.360223,32.377325],"type":"Point"}
}