{
  "type": "Feature",
  "properties": {
    "iso:country":"US",
    "sg:address":"1519 Creekview Dr",
    "sg:city":"Keller",
    "sg:classifiers":[
        {
            "category":"Professional",
            "subcategory":"Business Services",
            "type":"Services"
        }
    ],
    "sg:phone":"+1 817 431 5559",
    "sg:postcode":"76248",
    "sg:province":"TX",
    "wof:name":"Gwb Enterprises Inc",
    "wof:placetype":"venue"
},
  "geometry": {"coordinates":[-97.218341,32.931178],"type":"Point"}
}