{
  "type": "Feature",
  "properties": {
    "iso:country":"US",
    "sg:address":"4900 Morris Ave",
    "sg:city":"Addison",
    "sg:classifiers":[
        {
            "category":"Professional",
            "subcategory":"Business Services",
            "type":"Services"
        }
    ],
    "sg:phone":"+1 972 934 0308",
    "sg:postcode":"75001",
    "sg:province":"TX",
    "wof:name":"Interior Dctg By Chris Neal",
    "wof:placetype":"venue"
},
  "geometry": {"coordinates":[-96.828745,32.962718],"type":"Point"}
}