{
  "type": "Feature",
  "properties": {
    "iso:country":"US",
    "sg:address":"2000 Inverness Dr",
    "sg:city":"Carrollton",
    "sg:classifiers":[
        {
            "category":"Building & Trades",
            "subcategory":"Construction",
            "type":"Services"
        }
    ],
    "sg:phone":"+1 972 245 8229",
    "sg:postcode":"75007",
    "sg:province":"TX",
    "sg:tags":[
        "contractor",
        "nonresidential"
    ],
    "wof:name":"Superior Remodeling",
    "wof:placetype":"venue"
},
  "geometry": {"coordinates":[-96.88601199999999,32.987105],"type":"Point"}
}