{
  "type": "Feature",
  "properties": {
    "iso:country":"US",
    "sg:address":"201 US Hwy 290 E",
    "sg:city":"Brenham",
    "sg:classifiers":[
        {
            "category":"Bars & Pubs",
            "type":"Food & Drink"
        }
    ],
    "sg:phone":"+1 979 836 2717",
    "sg:postcode":"77833",
    "sg:province":"TX",
    "wof:name":"Texas Tavern",
    "wof:placetype":"venue"
},
  "geometry": {"coordinates":[-96.392743,30.142846],"type":"Point"}
}