{
  "type": "Feature",
  "properties": {
    "iso:country":"US",
    "sg:address":"2005 Bandera Rd",
    "sg:city":"San Antonio",
    "sg:classifiers":[
        {
            "category":"Personal",
            "subcategory":"Beauty Salon",
            "type":"Services"
        }
    ],
    "sg:phone":"+1 210 647 0861",
    "sg:postcode":"78228",
    "sg:province":"TX",
    "wof:name":"Polished Perfection Hair",
    "wof:placetype":"venue"
},
  "geometry": {"coordinates":[-98.57885400000001,29.473325],"type":"Point"}
}