{
  "type": "Feature",
  "properties": {
    "iso:country":"US",
    "sg:address":"4410 Maybelle Ave",
    "sg:city":"Austin",
    "sg:classifiers":[
        {
            "category":"Professional",
            "type":"Services"
        }
    ],
    "sg:phone":"+1 512 374 9250",
    "sg:postcode":"78756",
    "sg:province":"TX",
    "wof:name":"Interior Exclamations",
    "wof:placetype":"venue"
},
  "geometry": {"coordinates":[-97.740707,30.31479],"type":"Point"}
}