{
  "type": "Feature",
  "properties": {
    "iso:country":"US",
    "sg:address":"4355 Sylvanfield Dr",
    "sg:city":"Houston",
    "sg:classifiers":[
        {
            "category":"Health Services",
            "subcategory":"Health Practitioner",
            "type":"Services"
        }
    ],
    "sg:phone":"+1 281 866 8746",
    "sg:postcode":"77014",
    "sg:province":"TX",
    "wof:name":"Highfield Krista",
    "wof:placetype":"venue"
},
  "geometry": {"coordinates":[-95.49042300000001,29.987447],"type":"Point"}
}