{
  "type": "Feature",
  "properties": {
    "iso:country":"US",
    "sg:address":"12210 Alameda Ave",
    "sg:city":"Clint",
    "sg:classifiers":[
        {
            "category":"Retail",
            "subcategory":"Auto Repair",
            "type":"Services"
        }
    ],
    "sg:phone":"+1 915 851 8663",
    "sg:postcode":"79836",
    "sg:province":"TX",
    "sg:tags":[
        "automotive"
    ],
    "wof:name":"Ultimate Wheel Alignment",
    "wof:placetype":"venue"
},
  "geometry": {"coordinates":[-106.24735,31.604016],"type":"Point"}
}