{
  "type": "Feature",
  "properties": {
    "iso:country":"US",
    "sg:address":"9224 King Arthur Dr",
    "sg:city":"Dallas",
    "sg:classifiers":[
        {
            "category":"Manufacturing",
            "subcategory":"Signs",
            "type":"Manufacturing & Wholesale Goods"
        }
    ],
    "sg:phone":"+1 817 715 3152",
    "sg:postcode":"75247",
    "sg:province":"TX",
    "sg:tags":[
        "advertising",
        "specialty"
    ],
    "wof:name":"Sign Remedy Inc",
    "wof:placetype":"venue"
},
  "geometry": {"coordinates":[-96.88203300000001,32.833104],"type":"Point"}
}