{
  "type": "Feature",
  "properties": {
    "iso:country":"US",
    "sg:address":"1109 Belle St",
    "sg:city":"Bedford",
    "sg:classifiers":[
        {
            "category":"Insurance",
            "subcategory":"Insurance Agent",
            "type":"Services"
        }
    ],
    "sg:phone":"+1 817 268 1452",
    "sg:postcode":"76022",
    "sg:province":"TX",
    "wof:name":"Dennis Donaghey Insurance",
    "wof:placetype":"venue"
},
  "geometry": {"coordinates":[-97.16333299999999,32.831179],"type":"Point"}
}