{
  "type": "Feature",
  "properties": {
    "iso:country":"US",
    "sg:address":"3511 Gayle St",
    "sg:city":"Victoria",
    "sg:classifiers":[
        {
            "category":"Building & Trades",
            "subcategory":"Landscaping Services",
            "type":"Services"
        }
    ],
    "sg:phone":"+1 361 576 6546",
    "sg:postcode":"77901",
    "sg:province":"TX",
    "wof:name":"Hector Lopez Lawncare",
    "wof:placetype":"venue"
},
  "geometry": {"coordinates":[-96.96672599999999,28.794507],"type":"Point"}
}