{
  "type": "Feature",
  "properties": {
    "iso:country":"US",
    "sg:address":"19300 Moorhead Rd",
    "sg:city":"Conroe",
    "sg:classifiers":[
        {
            "category":"Wholesale",
            "subcategory":"Construction Materials",
            "type":"Manufacturing & Wholesale Goods"
        }
    ],
    "sg:phone":"+1 281 572 1920",
    "sg:postcode":"77302",
    "sg:province":"TX",
    "wof:name":"Morris Sand & Gravel Inc",
    "wof:placetype":"venue"
},
  "geometry": {"coordinates":[-95.36845099999999,30.168028],"type":"Point"}
}