{
  "type": "Feature",
  "properties": {
    "iso:country":"US",
    "sg:address":"4104 Yellowstone Dr",
    "sg:city":"Pasadena",
    "sg:classifiers":[
        {
            "category":"Shopping",
            "type":"Retail Goods"
        }
    ],
    "sg:phone":"+1 281 998 9999",
    "sg:postcode":"77504",
    "sg:province":"TX",
    "sg:tags":[
        "equipment",
        "typewriter"
    ],
    "wof:name":"Brewington Business Machines Inc",
    "wof:placetype":"venue"
},
  "geometry": {"coordinates":[-95.18049600000001,29.6441],"type":"Point"}
}