{
  "type": "Feature",
  "properties": {
    "iso:country":"US",
    "sg:address":"4114 Willowbend Blvd",
    "sg:city":"Houston",
    "sg:classifiers":[
        {
            "category":"Wholesale",
            "subcategory":"Electrical",
            "type":"Manufacturing & Wholesale Goods"
        }
    ],
    "sg:phone":"+1 713 541 3474",
    "sg:postcode":"77025",
    "sg:province":"TX",
    "sg:tags":[
        "equipment"
    ],
    "wof:name":"South Texas Satellite",
    "wof:placetype":"venue"
},
  "geometry": {"coordinates":[-95.444012,29.664773],"type":"Point"}
}