{
  "type": "Feature",
  "properties": {
    "iso:country":"US",
    "sg:address":"1510 E Main St",
    "sg:city":"Alice",
    "sg:classifiers":[
        {
            "category":"Shopping",
            "subcategory":"Clothing, Apparel, & Fashions",
            "type":"Retail Goods"
        }
    ],
    "sg:phone":"+1 361 664 4389",
    "sg:postcode":"78332",
    "sg:province":"TX",
    "sg:tags":[
        "store"
    ],
    "wof:name":"Bealls",
    "wof:placetype":"venue"
},
  "geometry": {"coordinates":[-98.05636699999999,27.756544],"type":"Point"}
}