{
  "type": "Feature",
  "properties": {
    "iso:country":"US",
    "sg:address":"2450 S Shore Blvd",
    "sg:city":"League City",
    "sg:classifiers":[
        {
            "category":"Professional",
            "subcategory":"Computer Services",
            "type":"Services"
        }
    ],
    "sg:phone":"+1 281 535 1889",
    "sg:postcode":"77573",
    "sg:province":"TX",
    "sg:tags":[
        "scanning"
    ],
    "wof:name":"Advanced Digital Imaging",
    "wof:placetype":"venue"
},
  "geometry": {"coordinates":[-95.06472599999999,29.542258],"type":"Point"}
}