{
  "type": "Feature",
  "properties": {
    "iso:country":"US",
    "sg:address":"2211 N Fry Rd",
    "sg:city":"Katy",
    "sg:classifiers":[
        {
            "category":"Personal",
            "subcategory":"Beauty Salon",
            "type":"Services"
        }
    ],
    "sg:phone":"+1 281 492 2424",
    "sg:postcode":"77449",
    "sg:province":"TX",
    "sg:tags":[
        "shop"
    ],
    "wof:name":"Alkire's Hair Inc",
    "wof:placetype":"venue"
},
  "geometry": {"coordinates":[-95.719086,29.798448],"type":"Point"}
}