{
  "type": "Feature",
  "properties": {
    "iso:country":"US",
    "sg:address":"1708 Houston St.",
    "sg:city":"Austin",
    "sg:classifiers":[
        {
            "category":"Health Services",
            "subcategory":"Clinic",
            "type":"Services"
        },
        {
            "category":"Sports & Exercise",
            "subcategory":"Gym",
            "type":"Entertainment"
        }
    ],
    "sg:phone":"+1 512 628 0606",
    "sg:postcode":"78756",
    "sg:province":"TX",
    "sg:tags":[
        "equipment",
        "medical",
        "instruction",
        "pilate"
    ],
    "sg:website":"www.mindfulbodycenter.com/",
    "wof:name":"Mindful Body Center",
    "wof:placetype":"venue"
},
  "geometry": {"coordinates":[-97.738631,30.328334],"type":"Point"}
}