{
  "type": "Feature",
  "properties": {
    "iso:country":"US",
    "sg:address":"2105 W Ave M",
    "sg:city":"San Angelo",
    "sg:classifiers":[
        {
            "category":"Wholesale",
            "subcategory":"Office Equipment",
            "type":"Manufacturing & Wholesale Goods"
        },
        {
            "category":"Retail",
            "subcategory":"Laundry & Dry Cleaning",
            "type":"Services"
        }
    ],
    "sg:phone":"+1 325 949 7777",
    "sg:postcode":"76901",
    "sg:province":"TX",
    "sg:tags":[
        "carwash",
        "coin"
    ],
    "wof:name":"Wash Pot Cleaning Center",
    "wof:placetype":"venue"
},
  "geometry": {"coordinates":[-100.45941999999999,31.44347],"type":"Point"}
}