{
  "type": "Feature",
  "properties": {
    "iso:country":"US",
    "sg:address":"2606 Kidd Dr",
    "sg:city":"Arlington",
    "sg:classifiers":[
        {
            "category":"Wholesale",
            "subcategory":"Farm Supplies",
            "type":"Manufacturing & Wholesale Goods"
        }
    ],
    "sg:phone":"+1 817 461 6419",
    "sg:postcode":"76013",
    "sg:province":"TX",
    "sg:tags":[
        "livestock"
    ],
    "wof:name":"Kiblinger Farms",
    "wof:placetype":"venue"
},
  "geometry": {"coordinates":[-97.154207,32.718047],"type":"Point"}
}