{
  "type": "Feature",
  "properties": {
    "iso:country":"US",
    "sg:address":"1714 N Henderson Ave",
    "sg:city":"Dallas",
    "sg:classifiers":[
        {
            "category":"Health Services",
            "subcategory":"Health Practitioner",
            "type":"Services"
        }
    ],
    "sg:phone":"+1 214 826 2228",
    "sg:postcode":"75206",
    "sg:province":"TX",
    "sg:tags":[
        "therapy",
        "physical"
    ],
    "wof:name":"Shepherd Impact Care Inc",
    "wof:placetype":"venue"
},
  "geometry": {"coordinates":[-96.772499,32.809799],"type":"Point"}
}