{
  "type": "Feature",
  "properties": {
    "iso:country":"US",
    "sg:address":"800 W 8th St",
    "sg:city":"Plainview",
    "sg:classifiers":[
        {
            "category":"Professional",
            "type":"Services"
        }
    ],
    "sg:phone":"+1 806 291 8544",
    "sg:postcode":"79072",
    "sg:province":"TX",
    "wof:name":"MI Tierra",
    "wof:placetype":"venue"
},
  "geometry": {"coordinates":[-101.711778,34.188195],"type":"Point"}
}