{
  "type": "Feature",
  "properties": {
    "iso:country":"US",
    "sg:address":"15915 Katy Fwy",
    "sg:city":"Houston",
    "sg:classifiers":[
        {
            "category":"Health Services",
            "subcategory":"Nursing And Care Facility",
            "type":"Services"
        },
        {
            "category":"Social Services",
            "subcategory":"Job Training",
            "type":"Services"
        }
    ],
    "sg:phone":"+1 281 398 7900",
    "sg:postcode":"77094",
    "sg:province":"TX",
    "sg:tags":[
        "disabled",
        "clinic",
        "specialty",
        "developmentally",
        "outpatient"
    ],
    "sg:website":"www.ahslive.com",
    "wof:name":"American Habilition Service",
    "wof:placetype":"venue"
},
  "geometry": {"coordinates":[-95.66516300000001,29.784422],"type":"Point"}
}