{
  "type": "Feature",
  "properties": {
    "iso:country":"US",
    "sg:address":"7609 Danuers Ln",
    "sg:city":"Arlington",
    "sg:classifiers":[
        {
            "category":"Freight",
            "type":"Transportation"
        }
    ],
    "sg:phone":"+1 817 545 2520",
    "sg:postcode":"76002",
    "sg:province":"TX",
    "sg:tags":[
        "courier"
    ],
    "wof:name":"Wings Of Eagles Courier Svc",
    "wof:placetype":"venue"
},
  "geometry": {"coordinates":[-97.112756,32.620707],"type":"Point"}
}