{
  "type": "Feature",
  "properties": {
    "iso:country":"US",
    "sg:address":"1608 Woods Blvd",
    "sg:city":"Round Rock",
    "sg:classifiers":[
        {
            "category":"Building & Trades",
            "subcategory":"Cleaning & Sanitation",
            "type":"Services"
        }
    ],
    "sg:phone":"+1 512 388 6037",
    "sg:postcode":"78681",
    "sg:province":"TX",
    "sg:tags":[
        "maintenance"
    ],
    "wof:name":"A-A Powerwashing",
    "wof:placetype":"venue"
},
  "geometry": {"coordinates":[-97.703616,30.530578],"type":"Point"}
}