{
  "type": "Feature",
  "properties": {
    "iso:country":"US",
    "sg:address":"2010 Sybil Ln",
    "sg:city":"Tyler",
    "sg:classifiers":[
        {
            "category":"Insurance",
            "subcategory":"Insurance Agent",
            "type":"Services"
        }
    ],
    "sg:phone":"+1 903 939 2882",
    "sg:postcode":"75703",
    "sg:province":"TX",
    "wof:name":"CNA Insurance",
    "wof:placetype":"venue"
},
  "geometry": {"coordinates":[-95.277224,32.305292],"type":"Point"}
}