{
  "type": "Feature",
  "properties": {
    "iso:country":"US",
    "sg:address":"602 Amarillo St",
    "sg:city":"Abilene",
    "sg:classifiers":[
        {
            "category":"Retail",
            "subcategory":"Auto Rental",
            "type":"Services"
        }
    ],
    "sg:phone":"+1 325 673 0391",
    "sg:postcode":"79602",
    "sg:province":"TX",
    "sg:tags":[
        "renting",
        "truck",
        "leasing"
    ],
    "wof:name":"Esperanza Equipment LLC",
    "wof:placetype":"venue"
},
  "geometry": {"coordinates":[-99.746734,32.443018],"type":"Point"}
}