{
  "type": "Feature",
  "properties": {
    "iso:country":"US",
    "sg:address":"11505 FM 2410",
    "sg:city":"Belton",
    "sg:classifiers":[
        {
            "category":"Manufacturing",
            "subcategory":"Buildings",
            "type":"Manufacturing & Wholesale Goods"
        }
    ],
    "sg:phone":"+1 254 698 7320",
    "sg:postcode":"76513",
    "sg:province":"TX",
    "sg:tags":[
        "prefabricated",
        "wood",
        "mfg"
    ],
    "wof:name":"American Elite Homes",
    "wof:placetype":"venue"
},
  "geometry": {"coordinates":[-97.59983099999999,31.056048],"type":"Point"}
}