{
  "type": "Feature",
  "properties": {
    "iso:country":"US",
    "sg:address":"414 E Elizabeth St",
    "sg:city":"Brownsville",
    "sg:classifiers":[
        {
            "category":"Shopping",
            "type":"Retail Goods"
        }
    ],
    "sg:phone":"+1 956 548 2191",
    "sg:postcode":"78520",
    "sg:province":"TX",
    "sg:tags":[
        "merchandise"
    ],
    "wof:name":"Olmos Shop",
    "wof:placetype":"venue"
},
  "geometry": {"coordinates":[-97.503344,25.905835],"type":"Point"}
}