{
  "type": "Feature",
  "properties": {
    "iso:country":"US",
    "sg:address":"682 Coe Rd",
    "sg:city":"Cleveland",
    "sg:classifiers":[
        {
            "category":"Personal",
            "subcategory":"Beauty Salon",
            "type":"Services"
        }
    ],
    "sg:phone":"+1 281 432 0224",
    "sg:postcode":"77362",
    "sg:province":"TX",
    "wof:name":"Yaweh's Hair Design",
    "wof:placetype":"venue"
},
  "geometry": {"coordinates":[-95.678804,30.156637],"type":"Point"}
}