{
  "type": "Feature",
  "properties": {
    "iso:country":"US",
    "sg:address":"3649 Canyon Dr",
    "sg:city":"Amarillo",
    "sg:classifiers":[
        {
            "category":"Home & Garden",
            "subcategory":"Building Materials",
            "type":"Retail Goods"
        }
    ],
    "sg:phone":"+1 806 373 5654",
    "sg:postcode":"79110",
    "sg:province":"TX",
    "sg:tags":[
        "windows",
        "door",
        "storm"
    ],
    "wof:name":"All Seasons Patio & Storm Wndw",
    "wof:placetype":"venue"
},
  "geometry": {"coordinates":[-101.84601499999999,35.176409],"type":"Point"}
}