{
  "type": "Feature",
  "properties": {
    "iso:country":"US",
    "sg:address":"7040 N. Mesa",
    "sg:city":"El Paso",
    "sg:classifiers":[
        {
            "category":"Restaurant",
            "type":"Food & Drink"
        }
    ],
    "sg:phone":"+1 915 585 0202",
    "sg:postcode":"79912",
    "sg:province":"TX",
    "sg:tags":[
        "mexican"
    ],
    "wof:name":"Blue Pepper Mexican Grill",
    "wof:placetype":"venue"
},
  "geometry": {"coordinates":[-106.55273200000001,31.836881],"type":"Point"}
}