{
  "type": "Feature",
  "properties": {
    "iso:country":"US",
    "sg:address":"4444 Vista Rd",
    "sg:city":"Pasadena",
    "sg:classifiers":[
        {
            "category":"Place Of Worship",
            "subcategory":"Church",
            "type":"Public Place"
        }
    ],
    "sg:phone":"+1 713 944 0591",
    "sg:postcode":"77504",
    "sg:province":"TX",
    "sg:website":"www.lwogc.org",
    "wof:name":"Living Word of God Church",
    "wof:placetype":"venue"
},
  "geometry": {"coordinates":[-95.176385,29.657674],"type":"Point"}
}