{
  "type": "Feature",
  "properties": {
    "iso:country":"US",
    "sg:address":"6605 Greenfield Dr",
    "sg:city":"Arlington",
    "sg:classifiers":[
        {
            "category":"Professional",
            "subcategory":"Engineering",
            "type":"Services"
        }
    ],
    "sg:phone":"+1 817 561 5103",
    "sg:postcode":"76016",
    "sg:province":"TX",
    "wof:name":"Pittstop",
    "wof:placetype":"venue"
},
  "geometry": {"coordinates":[-97.21538,32.67358],"type":"Point"}
}