{
  "type": "Feature",
  "properties": {
    "iso:country":"US",
    "sg:address":"527 E County Line Rd",
    "sg:city":"Royse City",
    "sg:classifiers":[
        {
            "category":"Social Services",
            "subcategory":"Child Care",
            "type":"Services"
        }
    ],
    "sg:phone":"+1 972 636 2580",
    "sg:postcode":"75189",
    "sg:province":"TX",
    "wof:name":"Giggles & Grins",
    "wof:placetype":"venue"
},
  "geometry": {"coordinates":[-96.32659,32.981732],"type":"Point"}
}