{
  "type": "Feature",
  "properties": {
    "iso:country":"US",
    "sg:address":"2340 E Trinity Mills Rd Ste 118",
    "sg:city":"Carrollton",
    "sg:classifiers":[
        {
            "category":"Health Services",
            "subcategory":"Doctor",
            "type":"Services"
        },
        {
            "category":"Community Center",
            "type":"Public Place"
        }
    ],
    "sg:phone":"+1 972 247 1721",
    "sg:postcode":"75006",
    "sg:province":"TX",
    "sg:tags":[
        "medical"
    ],
    "wof:name":"Cardiovascular Consultants Of Texas",
    "wof:placetype":"venue"
},
  "geometry": {"coordinates":[-96.87479500000001,32.98497],"type":"Point"}
}