{
  "type": "Feature",
  "properties": {
    "iso:country":"US",
    "sg:address":"507 S 1st St",
    "sg:city":"Austin",
    "sg:classifiers":[
        {
            "category":"Travel",
            "subcategory":"Bed & Breakfast",
            "type":"Entertainment"
        }
    ],
    "sg:phone":"+1 512 326 0100",
    "sg:postcode":"78704",
    "sg:province":"TX",
    "sg:tags":[
        "inn"
    ],
    "wof:name":"Wellesley Inn & Suites",
    "wof:placetype":"venue"
},
  "geometry": {"coordinates":[-97.750134,30.258365],"type":"Point"}
}