{
  "type": "Feature",
  "properties": {
    "iso:country":"US",
    "sg:address":"70 Shearwater Pl",
    "sg:city":"Spring",
    "sg:classifiers":[
        {
            "category":"Professional",
            "subcategory":"Computer Services",
            "type":"Services"
        }
    ],
    "sg:phone":"+1 281 419 4461",
    "sg:postcode":"77381",
    "sg:province":"TX",
    "sg:tags":[
        "prepackaged",
        "publisher",
        "software",
        "developer"
    ],
    "wof:name":"Science Select",
    "wof:placetype":"venue"
},
  "geometry": {"coordinates":[-95.511269,30.184116],"type":"Point"}
}