{
  "type": "Feature",
  "properties": {
    "iso:country":"US",
    "sg:address":"1623 Main St",
    "sg:city":"Dallas",
    "sg:classifiers":[
        {
            "category":"Bars & Pubs",
            "subcategory":"Sports Bar",
            "type":"Food & Drink"
        },
        {
            "category":"Restaurant",
            "type":"Food & Drink"
        }
    ],
    "sg:phone":"+1 214 747 8226",
    "sg:postcode":"75201",
    "sg:province":"TX",
    "sg:tags":[
        "traditional",
        "american"
    ],
    "sg:website":"www.pressboxgrill.com",
    "wof:name":"Press Box Grill",
    "wof:placetype":"venue"
},
  "geometry": {"coordinates":[-96.797589,32.781378],"type":"Point"}
}