{
  "type": "Feature",
  "properties": {
    "iso:country":"US",
    "sg:address":"7012 Bittersweet Dr",
    "sg:city":"Fort Worth",
    "sg:classifiers":[
        {
            "category":"Building & Trades",
            "subcategory":"Cleaning & Sanitation",
            "type":"Services"
        }
    ],
    "sg:phone":"+1 817 429 2885",
    "sg:postcode":"76120",
    "sg:province":"TX",
    "sg:tags":[
        "maintenance"
    ],
    "wof:name":"Taylors Clean Sweep",
    "wof:placetype":"venue"
},
  "geometry": {"coordinates":[-97.20798600000001,32.764875],"type":"Point"}
}