{
  "type": "Feature",
  "properties": {
    "iso:country":"US",
    "sg:address":"1403 Essex Green",
    "sg:city":"College Station",
    "sg:classifiers":[
        {
            "category":"Food & Beverages",
            "subcategory":"Groceries & Convenience Stores",
            "type":"Retail Goods"
        }
    ],
    "sg:phone":"+1 979 693 6237",
    "sg:postcode":"77845",
    "sg:province":"TX",
    "wof:name":"G H N A Corp",
    "wof:placetype":"venue"
},
  "geometry": {"coordinates":[-96.276881,30.590267],"type":"Point"}
}