{
  "type": "Feature",
  "properties": {
    "iso:country":"US",
    "sg:address":"6223 Craigway Rd",
    "sg:city":"Spring",
    "sg:classifiers":[
        {
            "category":"Freight",
            "type":"Transportation"
        }
    ],
    "sg:phone":"+1 281 443 1700",
    "sg:postcode":"77389",
    "sg:province":"TX",
    "sg:tags":[
        "broker"
    ],
    "wof:name":"John W Cole and Associates",
    "wof:placetype":"venue"
},
  "geometry": {"coordinates":[-95.515196,30.103353],"type":"Point"}
}