{
  "type": "Feature",
  "properties": {
    "iso:country":"US",
    "sg:address":"1555 Lake Woodlands Dr",
    "sg:city":"The Woodlands",
    "sg:classifiers":[
        {
            "category":"Retail",
            "subcategory":"Auto Repair",
            "type":"Services"
        }
    ],
    "sg:phone":"+1 281 362 3028",
    "sg:postcode":"77380",
    "sg:province":"TX",
    "sg:tags":[
        "repairing",
        "automobile"
    ],
    "wof:name":"Sears Auto & Tire Ctr",
    "wof:placetype":"venue"
},
  "geometry": {"coordinates":[-95.460882,30.165964],"type":"Point"}
}