{
  "type": "Feature",
  "properties": {
    "iso:country":"US",
    "sg:address":"4602 52nd St",
    "sg:city":"Lubbock",
    "sg:classifiers":[
        {
            "category":"Personal",
            "subcategory":"Beauty Salon",
            "type":"Services"
        }
    ],
    "sg:phone":"+1 806 796 2217",
    "sg:postcode":"79414",
    "sg:province":"TX",
    "wof:name":"Innovations In Hair & Skin",
    "wof:placetype":"venue"
},
  "geometry": {"coordinates":[-101.913718,33.546933],"type":"Point"}
}