{
  "type": "Feature",
  "properties": {
    "iso:country":"US",
    "sg:address":"2522 McKinney Ave Ste 200",
    "sg:city":"Dallas",
    "sg:classifiers":[
        {
            "category":"Communications",
            "type":"Services"
        }
    ],
    "sg:phone":"+1 214 999 0301",
    "sg:postcode":"75201",
    "sg:province":"TX",
    "sg:tags":[
        "web",
        "design"
    ],
    "wof:name":"Quick Silver Interactive Group",
    "wof:placetype":"venue"
},
  "geometry": {"coordinates":[-96.802002,32.795502],"type":"Point"}
}