{
  "type": "Feature",
  "properties": {
    "iso:country":"US",
    "sg:address":"505 W 5th St",
    "sg:city":"Clifton",
    "sg:classifiers":[
        {
            "category":"Utilities",
            "subcategory":"Mobile Phone",
            "type":"Services"
        },
        {
            "category":"Manufacturing",
            "subcategory":"Electronics",
            "type":"Manufacturing & Wholesale Goods"
        }
    ],
    "sg:phone":"+1 254 675 3732",
    "sg:postcode":"76634",
    "sg:province":"TX",
    "sg:tags":[
        "communications",
        "satellite",
        "telephone",
        "cellular"
    ],
    "wof:name":"Cellular Concepts Etc",
    "wof:placetype":"venue"
},
  "geometry": {"coordinates":[-97.57608500000001,31.782773],"type":"Point"}
}