{
  "type": "Feature",
  "properties": {
    "iso:country":"US",
    "sg:address":"7014 Scott St",
    "sg:city":"Houston",
    "sg:classifiers":[
        {
            "category":"Personal",
            "subcategory":"Beauty Salon",
            "type":"Services"
        }
    ],
    "sg:phone":"+1 713 747 9353",
    "sg:postcode":"77021",
    "sg:province":"TX",
    "sg:tags":[
        "shop"
    ],
    "wof:name":"Glitzy Nails",
    "wof:placetype":"venue"
},
  "geometry": {"coordinates":[-95.363584,29.689037],"type":"Point"}
}