{
  "type": "Feature",
  "properties": {
    "iso:country":"US",
    "sg:address":"5323 11th St",
    "sg:city":"Katy",
    "sg:classifiers":[
        {
            "category":"Wholesale",
            "subcategory":"Stationery",
            "type":"Manufacturing & Wholesale Goods"
        }
    ],
    "sg:phone":"+1 281 391 7968",
    "sg:postcode":"77493",
    "sg:province":"TX",
    "sg:tags":[
        "supply"
    ],
    "wof:name":"KATY Business Forms & Labels",
    "wof:placetype":"venue"
},
  "geometry": {"coordinates":[-95.811988,29.79621],"type":"Point"}
}