{
  "type": "Feature",
  "properties": {
    "iso:country":"US",
    "sg:address":"904 Seco Rd",
    "sg:city":"Eagle Pass",
    "sg:classifiers":[
        {
            "category":"Building & Trades",
            "subcategory":"Plumbing",
            "type":"Services"
        }
    ],
    "sg:phone":"+1 830 773 4404",
    "sg:postcode":"78852",
    "sg:province":"TX",
    "sg:tags":[
        "conditioning",
        "air",
        "system",
        "contractor"
    ],
    "wof:name":"Mendoza's Air Cond & Heating",
    "wof:placetype":"venue"
},
  "geometry": {"coordinates":[-100.500254,28.746214],"type":"Point"}
}