{
  "type": "Feature",
  "properties": {
    "iso:country":"US",
    "sg:address":"1717 Creek Ridge Ct",
    "sg:city":"Irving",
    "sg:classifiers":[
        {
            "category":"Retail",
            "subcategory":"Funeral Services",
            "type":"Services"
        }
    ],
    "sg:phone":"+1 972 259 3423",
    "sg:postcode":"75060",
    "sg:province":"TX",
    "wof:name":"Stewart Lk Home Study Courses",
    "wof:placetype":"venue"
},
  "geometry": {"coordinates":[-96.953012,32.796313],"type":"Point"}
}