{
  "type": "Feature",
  "properties": {
    "iso:country":"US",
    "sg:address":"305 W Aimee St",
    "sg:city":"Forney",
    "sg:classifiers":[
        {
            "category":"Retail",
            "subcategory":"Auto Repair",
            "type":"Services"
        }
    ],
    "sg:phone":"+1 972 552 4646",
    "sg:postcode":"75126",
    "sg:province":"TX",
    "sg:tags":[
        "body",
        "automobile",
        "painting"
    ],
    "wof:name":"Blissett's Body Shop",
    "wof:placetype":"venue"
},
  "geometry": {"coordinates":[-96.47099,32.751552],"type":"Point"}
}