{
  "type": "Feature",
  "properties": {
    "iso:country":"US",
    "sg:address":"2402 Dunlavy St",
    "sg:city":"Houston",
    "sg:classifiers":[
        {
            "category":"Real Estate",
            "subcategory":"Architect",
            "type":"Services"
        }
    ],
    "sg:phone":"+1 713 524 2670",
    "sg:postcode":"77006",
    "sg:province":"TX",
    "wof:name":"The Terraces At Dunlavy",
    "wof:placetype":"venue"
},
  "geometry": {"coordinates":[-95.402237,29.744729],"type":"Point"}
}