{
  "type": "Feature",
  "properties": {
    "iso:country":"US",
    "sg:address":"10809 Garland Rd",
    "sg:city":"Dallas",
    "sg:classifiers":[
        {
            "category":"Manufacturing",
            "subcategory":"Printing",
            "type":"Manufacturing & Wholesale Goods"
        }
    ],
    "sg:phone":"+1 214 324 5285",
    "sg:postcode":"75218",
    "sg:province":"TX",
    "sg:tags":[
        "print",
        "newspaper",
        "medium"
    ],
    "wof:name":"White Rocker News the",
    "wof:placetype":"venue"
},
  "geometry": {"coordinates":[-96.688698,32.845001],"type":"Point"}
}