{
  "type": "Feature",
  "properties": {
    "iso:country":"US",
    "sg:address":"4714 Colleyville Blvd",
    "sg:city":"Colleyville",
    "sg:classifiers":[
        {
            "category":"Restaurant",
            "type":"Food & Drink"
        }
    ],
    "sg:phone":"+1 817 503 7888",
    "sg:postcode":"76034",
    "sg:province":"TX",
    "wof:name":"Pacific House Chinese Cuisine",
    "wof:placetype":"venue"
},
  "geometry": {"coordinates":[-97.156357,32.88026],"type":"Point"}
}