{
  "type": "Feature",
  "properties": {
    "iso:country":"US",
    "sg:address":"205 Benton Dr",
    "sg:city":"Allen",
    "sg:classifiers":[
        {
            "category":"Retail",
            "subcategory":"Portrait Studio",
            "type":"Services"
        }
    ],
    "sg:phone":"+1 214 495 0491",
    "sg:postcode":"75013",
    "sg:province":"TX",
    "sg:tags":[
        "photo"
    ],
    "wof:name":"Sharp Shooter Photography",
    "wof:placetype":"venue"
},
  "geometry": {"coordinates":[-96.68816200000001,33.102053],"type":"Point"}
}