{
  "type": "Feature",
  "properties": {
    "iso:country":"US",
    "sg:address":"1723 Milford St",
    "sg:city":"Houston",
    "sg:classifiers":[
        {
            "category":"Professional",
            "subcategory":"Management & Consulting",
            "type":"Services"
        }
    ],
    "sg:phone":"+1 713 520 0424",
    "sg:postcode":"77098",
    "sg:province":"TX",
    "sg:tags":[
        "business"
    ],
    "wof:name":"Change Makers Inc",
    "wof:placetype":"venue"
},
  "geometry": {"coordinates":[-95.403965,29.72867],"type":"Point"}
}