{
  "type": "Feature",
  "properties": {
    "iso:country":"US",
    "sg:address":"10121 Lake June Rd Ste 400",
    "sg:city":"Dallas",
    "sg:classifiers":[
        {
            "category":"Shopping",
            "subcategory":"Department Store",
            "type":"Retail Goods"
        }
    ],
    "sg:phone":"+1 972 288 3477",
    "sg:postcode":"75217",
    "sg:province":"TX",
    "sg:website":"www.familydollar.com",
    "wof:name":"Family Dollar",
    "wof:placetype":"venue"
},
  "geometry": {"coordinates":[-96.650136,32.734258],"type":"Point"}
}