{
  "type": "Feature",
  "properties": {
    "iso:country":"US",
    "sg:address":"12750 Merit Dr Ste 300",
    "sg:city":"Dallas",
    "sg:classifiers":[
        {
            "category":"Building & Trades",
            "subcategory":"Construction",
            "type":"Services"
        }
    ],
    "sg:phone":"+1 972 450 4100",
    "sg:postcode":"75251",
    "sg:province":"TX",
    "sg:tags":[
        "contractor"
    ],
    "wof:name":"Fluor Global Service",
    "wof:placetype":"venue"
},
  "geometry": {"coordinates":[-96.772102,32.9226],"type":"Point"}
}