{
  "type": "Feature",
  "properties": {
    "iso:country":"US",
    "sg:address":"3522 Gus Thomasson Rd",
    "sg:city":"Mesquite",
    "sg:classifiers":[
        {
            "category":"Insurance",
            "subcategory":"Insurance Agent",
            "type":"Services"
        }
    ],
    "sg:phone":"+1 972 270 4300",
    "sg:postcode":"75150",
    "sg:province":"TX",
    "wof:name":"A-Affordable Insurance",
    "wof:placetype":"venue"
},
  "geometry": {"coordinates":[-96.633813,32.807907],"type":"Point"}
}