{
  "type": "Feature",
  "properties": {
    "iso:country":"US",
    "sg:address":"225 Westview Ave",
    "sg:city":"Fort Worth",
    "sg:classifiers":[
        {
            "category":"Farming",
            "subcategory":"Livestock Farm",
            "type":"Manufacturing & Wholesale Goods"
        }
    ],
    "sg:phone":"+1 830 334 8888",
    "sg:postcode":"76107",
    "sg:province":"TX",
    "sg:tags":[
        "ranch"
    ],
    "wof:name":"Westview Ranch",
    "wof:placetype":"venue"
},
  "geometry": {"coordinates":[-97.378013,32.754357],"type":"Point"}
}