{
  "type": "Feature",
  "properties": {
    "iso:country":"US",
    "sg:address":"4343 N 1st St",
    "sg:city":"Abilene",
    "sg:classifiers":[
        {
            "category":"Autos & Motor Vehicles",
            "subcategory":"Automobile Sales",
            "type":"Retail Goods"
        }
    ],
    "sg:phone":"+1 325 677 0123",
    "sg:postcode":"79603",
    "sg:province":"TX",
    "sg:tags":[
        "car",
        "used",
        "dealer"
    ],
    "wof:name":"Gary Corpian Motor Co",
    "wof:placetype":"venue"
},
  "geometry": {"coordinates":[-99.779815,32.452883],"type":"Point"}
}