{
  "type": "Feature",
  "properties": {
    "iso:country":"US",
    "sg:address":"8808 Emnora Ln",
    "sg:city":"Houston",
    "sg:classifiers":[
        {
            "category":"Building & Trades",
            "subcategory":"Electrical",
            "type":"Services"
        }
    ],
    "sg:phone":"+1 713 935 9779",
    "sg:postcode":"77080",
    "sg:province":"TX",
    "sg:tags":[
        "installation"
    ],
    "wof:name":"Farley's Installation",
    "wof:placetype":"venue"
},
  "geometry": {"coordinates":[-95.513818,29.816],"type":"Point"}
}