{
  "type": "Feature",
  "properties": {
    "iso:country":"US",
    "sg:address":"55 Berry Rd",
    "sg:city":"Houston",
    "sg:classifiers":[
        {
            "category":"Food & Beverages",
            "subcategory":"Liquor & Beverages",
            "type":"Retail Goods"
        }
    ],
    "sg:phone":"+1 713 691 9204",
    "sg:postcode":"77022",
    "sg:province":"TX",
    "sg:tags":[
        "beer",
        "ale",
        "spirit",
        "wine"
    ],
    "wof:name":"Nick's Drive Inn",
    "wof:placetype":"venue"
},
  "geometry": {"coordinates":[-95.37960099999999,29.8374],"type":"Point"}
}