{
  "type": "Feature",
  "properties": {
    "iso:country":"US",
    "sg:address":"741 E FM 550",
    "sg:city":"Rockwall",
    "sg:classifiers":[
        {
            "category":"Building & Trades",
            "subcategory":"Construction",
            "type":"Services"
        }
    ],
    "sg:phone":"+1 972 771 4654",
    "sg:postcode":"75032",
    "sg:province":"TX",
    "sg:tags":[
        "hanging",
        "contractor"
    ],
    "wof:name":"Lopez Paint Contractor",
    "wof:placetype":"venue"
},
  "geometry": {"coordinates":[-96.372345,32.869204],"type":"Point"}
}