{
  "type": "Feature",
  "properties": {
    "iso:country":"US",
    "sg:address":"2911 Bel Air Dr",
    "sg:city":"Marshall",
    "sg:classifiers":[
        {
            "category":"Retail",
            "subcategory":"Auto Repair",
            "type":"Services"
        }
    ],
    "sg:phone":"+1 903 935 9688",
    "sg:postcode":"75672",
    "sg:province":"TX",
    "sg:tags":[
        "body",
        "painting",
        "repairing",
        "automobile"
    ],
    "wof:name":"Stokell's Auto & Marine Upholstery",
    "wof:placetype":"venue"
},
  "geometry": {"coordinates":[-94.375013,32.518917],"type":"Point"}
}