{
  "type": "Feature",
  "properties": {
    "iso:country":"US",
    "sg:address":"214 S Wall St",
    "sg:city":"Floydada",
    "sg:classifiers":[
        {
            "category":"Home & Garden",
            "subcategory":"Building Materials",
            "type":"Retail Goods"
        }
    ],
    "sg:phone":"+1 806 983 2140",
    "sg:postcode":"79235",
    "sg:province":"TX",
    "sg:tags":[
        "lumber"
    ],
    "wof:name":"Higginbotham Bartlett Co",
    "wof:placetype":"venue"
},
  "geometry": {"coordinates":[-101.33349800000001,33.984262],"type":"Point"}
}