{
  "type": "Feature",
  "properties": {
    "iso:country":"US",
    "sg:address":"18320 Hamilton Pool Rd",
    "sg:city":"Austin",
    "sg:classifiers":[
        {
            "category":"Farming",
            "subcategory":"Livestock Farm",
            "type":"Manufacturing & Wholesale Goods"
        },
        {
            "category":"Arena",
            "subcategory":"Horse Racetrack",
            "type":"Entertainment"
        }
    ],
    "sg:phone":"+1 512 264 2383",
    "sg:postcode":"78738",
    "sg:province":"TX",
    "sg:tags":[
        "breeder"
    ],
    "sg:website":"http://www.littlebuckarooranch.com",
    "wof:name":"Little Buckaroo Ranch",
    "wof:placetype":"venue"
},
  "geometry": {"coordinates":[-98.05802199999999,30.286715],"type":"Point"}
}