{
  "type": "Feature",
  "properties": {
    "iso:country":"US",
    "sg:address":"10513 FM 2166",
    "sg:city":"San Angelo",
    "sg:classifiers":[
        {
            "category":"Building & Trades",
            "subcategory":"Construction",
            "type":"Services"
        }
    ],
    "sg:phone":"+1 325 949 5609",
    "sg:postcode":"76904",
    "sg:province":"TX",
    "sg:tags":[
        "water",
        "well",
        "drilling"
    ],
    "wof:name":"Woehl Drilling",
    "wof:placetype":"venue"
},
  "geometry": {"coordinates":[-100.592367,31.352624],"type":"Point"}
}