{
  "type": "Feature",
  "properties": {
    "iso:country":"US",
    "sg:address":"100 E Quemada Ave",
    "sg:city":"San Diego",
    "sg:classifiers":[
        {
            "category":"Personal",
            "subcategory":"Beauty Salon",
            "type":"Services"
        }
    ],
    "sg:phone":"+1 361 279 7070",
    "sg:postcode":"78384",
    "sg:province":"TX",
    "sg:tags":[
        "shop"
    ],
    "wof:name":"Reflections Salon",
    "wof:placetype":"venue"
},
  "geometry": {"coordinates":[-98.242441,27.753622],"type":"Point"}
}