{
  "type": "Feature",
  "properties": {
    "iso:country":"US",
    "sg:address":"4125 Magnolia St",
    "sg:city":"Texarkana",
    "sg:classifiers":[
        {
            "category":"Social Services",
            "type":"Services"
        }
    ],
    "sg:phone":"+1 903 793 1377",
    "sg:postcode":"75503",
    "sg:province":"TX",
    "wof:name":"New Horizons",
    "wof:placetype":"venue"
},
  "geometry": {"coordinates":[-94.044234,33.45735],"type":"Point"}
}