{
  "type": "Feature",
  "properties": {
    "iso:country":"US",
    "sg:address":"1413 Forehand St",
    "sg:city":"Crockett",
    "sg:classifiers":[
        {
            "category":"Organizations",
            "subcategory":"Membership Organization",
            "type":"Services"
        }
    ],
    "sg:phone":"+1 936 544 8332",
    "sg:postcode":"75835",
    "sg:province":"TX",
    "wof:name":"Moore Frye Eckles Memorial",
    "wof:placetype":"venue"
},
  "geometry": {"coordinates":[-95.445581,31.306474],"type":"Point"}
}