{
  "type": "Feature",
  "properties": {
    "iso:country":"US",
    "sg:address":"9002 Ilona Ln",
    "sg:city":"Houston",
    "sg:classifiers":[
        {
            "category":"Museum",
            "subcategory":"Botanical Garden",
            "type":"Entertainment"
        },
        {
            "category":"Shopping",
            "type":"Retail Goods"
        }
    ],
    "sg:phone":"+1 713 665 3281",
    "sg:postcode":"77025",
    "sg:province":"TX",
    "sg:tags":[
        "aquarium"
    ],
    "wof:name":"Captive Aquatic Eco Systems",
    "wof:placetype":"venue"
},
  "geometry": {"coordinates":[-95.434236,29.684768],"type":"Point"}
}