{
  "type": "Feature",
  "properties": {
    "iso:country":"US",
    "sg:address":"5808 State Hwy 78",
    "sg:city":"Garland",
    "sg:classifiers":[
        {
            "category":"Food & Beverages",
            "subcategory":"Groceries & Convenience Stores",
            "type":"Retail Goods"
        }
    ],
    "sg:phone":"+1 972 530 8434",
    "sg:postcode":"75048",
    "sg:province":"TX",
    "wof:name":"Paul's Grocery",
    "wof:placetype":"venue"
},
  "geometry": {"coordinates":[-96.595792,32.9761],"type":"Point"}
}