{
  "type": "Feature",
  "properties": {
    "iso:country":"US",
    "sg:address":"1553 Sierra Bonita Dr",
    "sg:city":"El Paso",
    "sg:classifiers":[
        {
            "category":"Shopping",
            "subcategory":"Used Merchandise",
            "type":"Retail Goods"
        }
    ],
    "sg:phone":"+1 915 857 8978",
    "sg:postcode":"79936",
    "sg:province":"TX",
    "wof:name":"Adela Fierro-Guzman",
    "wof:placetype":"venue"
},
  "geometry": {"coordinates":[-106.29614599999999,31.743404],"type":"Point"}
}