{
  "type": "Feature",
  "properties": {
    "iso:country":"US",
    "sg:address":"7008 Lake Powell Dr",
    "sg:city":"Arlington",
    "sg:classifiers":[
        {
            "category":"Professional",
            "subcategory":"Business Services",
            "type":"Services"
        }
    ],
    "sg:phone":"+1 817 572 1045",
    "sg:postcode":"76016",
    "sg:province":"TX",
    "wof:name":"Leichner Design Jodi Group",
    "wof:placetype":"venue"
},
  "geometry": {"coordinates":[-97.220213,32.688139],"type":"Point"}
}