{
  "type": "Feature",
  "properties": {
    "iso:country":"US",
    "sg:address":"1514 NW 24th St",
    "sg:city":"San Antonio",
    "sg:classifiers":[
        {
            "category":"Building & Trades",
            "subcategory":"Construction",
            "type":"Services"
        }
    ],
    "sg:phone":"+1 210 733 3458",
    "sg:postcode":"78207",
    "sg:province":"TX",
    "sg:tags":[
        "residential",
        "commercial",
        "painting"
    ],
    "wof:name":"LP Painting & Contracting",
    "wof:placetype":"venue"
},
  "geometry": {"coordinates":[-98.540605,29.445312],"type":"Point"}
}