{
  "type": "Feature",
  "properties": {
    "iso:country":"US",
    "sg:address":"3003 Market St",
    "sg:city":"Laredo",
    "sg:classifiers":[
        {
            "category":"Food & Beverages",
            "subcategory":"Groceries & Convenience Stores",
            "type":"Retail Goods"
        }
    ],
    "sg:phone":"+1 956 722 1033",
    "sg:postcode":"78043",
    "sg:province":"TX",
    "wof:name":"Limon-Martinez Abel Gr Mkt",
    "wof:placetype":"venue"
},
  "geometry": {"coordinates":[-99.464962,27.50372],"type":"Point"}
}