{
  "type": "Feature",
  "properties": {
    "iso:country":"US",
    "sg:address":"317 Neill Ave",
    "sg:city":"Fort Worth",
    "sg:classifiers":[
        {
            "category":"Communications",
            "subcategory":"Film & Video Production",
            "type":"Services"
        }
    ],
    "sg:phone":"+1 817 568 2853",
    "sg:postcode":"76140",
    "sg:province":"TX",
    "sg:tags":[
        "motion"
    ],
    "wof:name":"Glory Productions",
    "wof:placetype":"venue"
},
  "geometry": {"coordinates":[-97.286964,32.627867],"type":"Point"}
}