{
  "type": "Feature",
  "properties": {
    "iso:country":"US",
    "sg:address":"16315 Ginger Run Way",
    "sg:city":"Sugar Land",
    "sg:classifiers":[
        {
            "category":"Professional",
            "subcategory":"Business Services",
            "type":"Services"
        }
    ],
    "sg:phone":"+1 281 277 3950",
    "sg:postcode":"77478",
    "sg:province":"TX",
    "wof:name":"Home Chek Inspections",
    "wof:placetype":"venue"
},
  "geometry": {"coordinates":[-95.671328,29.65148],"type":"Point"}
}