{
  "type": "Feature",
  "properties": {
    "iso:country":"US",
    "sg:address":"2127 Magoffin Ave",
    "sg:city":"El Paso",
    "sg:classifiers":[
        {
            "category":"Retail",
            "subcategory":"Auto Repair",
            "type":"Services"
        }
    ],
    "sg:phone":"+1 915 532 2794",
    "sg:postcode":"79901",
    "sg:province":"TX",
    "sg:tags":[
        "repairing",
        "automobile",
        "general"
    ],
    "wof:name":"Gonzalez Auto Repair Service",
    "wof:placetype":"venue"
},
  "geometry": {"coordinates":[-106.464286,31.770205],"type":"Point"}
}