{
  "type": "Feature",
  "properties": {
    "iso:country":"US",
    "sg:address":"6533 Dartbrook Dr",
    "sg:city":"Dallas",
    "sg:classifiers":[
        {
            "category":"Building & Trades",
            "subcategory":"Construction",
            "type":"Services"
        }
    ],
    "sg:phone":"+1 972 233 7120",
    "sg:postcode":"75254",
    "sg:province":"TX",
    "sg:tags":[
        "interior",
        "design"
    ],
    "wof:name":"Eaton Design I",
    "wof:placetype":"venue"
},
  "geometry": {"coordinates":[-96.793503,32.944698],"type":"Point"}
}