{
  "type": "Feature",
  "properties": {
    "iso:country":"US",
    "sg:address":"1105 State Hwy 276",
    "sg:city":"Rockwall",
    "sg:classifiers":[
        {
            "category":"Personal",
            "subcategory":"Beauty Salon",
            "type":"Services"
        }
    ],
    "sg:phone":"+1 469 698 8080",
    "sg:postcode":"75032",
    "sg:province":"TX",
    "wof:name":"Salon 276",
    "wof:placetype":"venue"
},
  "geometry": {"coordinates":[-96.44793300000001,32.907175],"type":"Point"}
}