{
  "type": "Feature",
  "properties": {
    "iso:country":"US",
    "sg:address":"1405 N Gary Ave",
    "sg:city":"Lubbock",
    "sg:classifiers":[
        {
            "category":"Manufacturing",
            "subcategory":"Glass & Minerals",
            "type":"Manufacturing & Wholesale Goods"
        }
    ],
    "sg:phone":"+1 806 765 7721",
    "sg:postcode":"79415",
    "sg:province":"TX",
    "sg:tags":[
        "ready"
    ],
    "sg:website":"www.southernstarconcrete.com",
    "wof:name":"Lubbock Building Products",
    "wof:placetype":"venue"
},
  "geometry": {"coordinates":[-101.883375,33.616232],"type":"Point"}
}