{
  "type": "Feature",
  "properties": {
    "iso:country":"US",
    "sg:address":"907 E Cedar St",
    "sg:city":"Angleton",
    "sg:classifiers":[
        {
            "category":"Professional",
            "subcategory":"Accounting & Tax Preparation",
            "type":"Services"
        }
    ],
    "sg:phone":"+1 979 849 7363",
    "sg:postcode":"77515",
    "sg:province":"TX",
    "sg:tags":[
        "return",
        "filing"
    ],
    "wof:name":"Adamson's Tax Svc",
    "wof:placetype":"venue"
},
  "geometry": {"coordinates":[-95.421541,29.170058],"type":"Point"}
}