{
  "type": "Feature",
  "properties": {
    "iso:country":"US",
    "sg:address":"1455 Buckingham Rd",
    "sg:city":"Richardson",
    "sg:classifiers":[
        {
            "category":"Shopping",
            "subcategory":"Discount & Variety Stores",
            "type":"Retail Goods"
        }
    ],
    "sg:phone":"+1 972 235 2047",
    "sg:postcode":"75081",
    "sg:province":"TX",
    "wof:name":"Dollar General",
    "wof:placetype":"venue"
},
  "geometry": {"coordinates":[-96.72410000000001,32.934844],"type":"Point"}
}