{
  "type": "Feature",
  "properties": {
    "iso:country":"US",
    "sg:address":"3202 Wentworth St",
    "sg:city":"Houston",
    "sg:classifiers":[
        {
            "category":"Professional",
            "subcategory":"Lawyer & Legal Services",
            "type":"Services"
        }
    ],
    "sg:phone":"+1 713 529 2636",
    "sg:postcode":"77004",
    "sg:province":"TX",
    "wof:name":"D Duckens Atty Law",
    "wof:placetype":"venue"
},
  "geometry": {"coordinates":[-95.36431899999999,29.719157],"type":"Point"}
}