{
  "type": "Feature",
  "properties": {
    "iso:country":"US",
    "sg:address":"3637 Mattox St",
    "sg:city":"El Paso",
    "sg:classifiers":[
        {
            "category":"Professional",
            "subcategory":"Management & Consulting",
            "type":"Services"
        }
    ],
    "sg:phone":"+1 915 778 9689",
    "sg:postcode":"79925",
    "sg:province":"TX",
    "wof:name":"Mc Donalds Restaurants",
    "wof:placetype":"venue"
},
  "geometry": {"coordinates":[-106.36765699999999,31.794696],"type":"Point"}
}