{
  "type": "Feature",
  "properties": {
    "iso:country":"US",
    "sg:address":"5700 Manchaca Rd",
    "sg:city":"Austin",
    "sg:classifiers":[
        {
            "category":"Place Of Worship",
            "subcategory":"Church",
            "type":"Public Place"
        },
        {
            "category":"Place Of Worship",
            "type":"Public Place"
        }
    ],
    "sg:phone":"+1 512 444 5550",
    "sg:postcode":"78745",
    "sg:province":"TX",
    "sg:tags":[
        "churches-charismatic",
        "churches-non-denominational"
    ],
    "sg:website":"http://www.whoc.org",
    "wof:name":"World Harvest Outreach Church",
    "wof:placetype":"venue"
},
  "geometry": {"coordinates":[-97.799789,30.214191],"type":"Point"}
}