{
  "type": "Feature",
  "properties": {
    "iso:country":"US",
    "sg:address":"12002 Jones Maltsberger Rd",
    "sg:city":"San Antonio",
    "sg:classifiers":[
        {
            "category":"Arena",
            "subcategory":"Sports Club",
            "type":"Entertainment"
        }
    ],
    "sg:phone":"+1 210 491 6100",
    "sg:postcode":"78216",
    "sg:province":"TX",
    "wof:name":"Athethic Dept",
    "wof:placetype":"venue"
},
  "geometry": {"coordinates":[-98.470287,29.550181],"type":"Point"}
}