{
  "type": "Feature",
  "properties": {
    "iso:country":"US",
    "sg:address":"3619 Brazos Ave",
    "sg:city":"Odessa",
    "sg:classifiers":[
        {
            "category":"Wholesale",
            "subcategory":"Machinery & Supplies",
            "type":"Manufacturing & Wholesale Goods"
        }
    ],
    "sg:phone":"+1 432 362 6688",
    "sg:postcode":"79764",
    "sg:province":"TX",
    "sg:tags":[
        "bearing",
        "seal"
    ],
    "wof:name":"K S Supplies Inc",
    "wof:placetype":"venue"
},
  "geometry": {"coordinates":[-102.402061,31.875042],"type":"Point"}
}