{
  "type": "Feature",
  "properties": {
    "iso:country":"US",
    "sg:address":"932 Acacia Ave",
    "sg:city":"Alamo",
    "sg:classifiers":[
        {
            "category":"Retail",
            "subcategory":"Repair Shop",
            "type":"Services"
        }
    ],
    "sg:phone":"+1 956 702 8920",
    "sg:postcode":"78516",
    "sg:province":"TX",
    "wof:name":"Upholstery Sanchez",
    "wof:placetype":"venue"
},
  "geometry": {"coordinates":[-98.120715,26.185046],"type":"Point"}
}