{
  "type": "Feature",
  "properties": {
    "iso:country":"US",
    "sg:address":"604 N Rio St",
    "sg:city":"Fort Stockton",
    "sg:classifiers":[
        {
            "category":"Building & Trades",
            "subcategory":"Landscaping Services",
            "type":"Services"
        }
    ],
    "sg:phone":"+1 432 336 6669",
    "sg:postcode":"79735",
    "sg:province":"TX",
    "sg:tags":[
        "tree"
    ],
    "wof:name":"Quality Tree & Lawn Care",
    "wof:placetype":"venue"
},
  "geometry": {"coordinates":[-102.89441100000001,30.890923],"type":"Point"}
}