{
  "type": "Feature",
  "properties": {
    "iso:country":"US",
    "sg:address":"265 S Clark Dr",
    "sg:city":"El Paso",
    "sg:classifiers":[
        {
            "category":"Building & Trades",
            "subcategory":"Electrical",
            "type":"Services"
        }
    ],
    "sg:phone":"+1 915 779 4610",
    "sg:postcode":"79905",
    "sg:province":"TX",
    "sg:tags":[
        "electrical",
        "contractor"
    ],
    "wof:name":"M One Electric",
    "wof:placetype":"venue"
},
  "geometry": {"coordinates":[-106.414215,31.762043],"type":"Point"}
}