{
  "type": "Feature",
  "properties": {
    "iso:country":"US",
    "sg:address":"11107 Briar Forest Dr",
    "sg:city":"Houston",
    "sg:classifiers":[
        {
            "category":"Retail",
            "subcategory":"Laundry & Dry Cleaning",
            "type":"Services"
        }
    ],
    "sg:phone":"+1 713 789 2775",
    "sg:postcode":"77042",
    "sg:province":"TX",
    "sg:tags":[
        "pickup",
        "station"
    ],
    "wof:name":"Dapper Dan Cleaners",
    "wof:placetype":"venue"
},
  "geometry": {"coordinates":[-95.572186,29.747875],"type":"Point"}
}