{
  "type": "Feature",
  "properties": {
    "iso:country":"US",
    "sg:address":"215 N Main St",
    "sg:city":"Corsicana",
    "sg:classifiers":[
        {
            "category":"Retail",
            "subcategory":"Laundry & Dry Cleaning",
            "type":"Services"
        }
    ],
    "sg:phone":"+1 903 874 4786",
    "sg:postcode":"75110",
    "sg:province":"TX",
    "sg:tags":[
        "cleaners",
        "linen",
        "supply"
    ],
    "wof:name":"Corsicana Laundry & Cleaners",
    "wof:placetype":"venue"
},
  "geometry": {"coordinates":[-96.46589299999999,32.09472],"type":"Point"}
}