{
  "type": "Feature",
  "properties": {
    "iso:country":"US",
    "sg:address":"5813 Gallant Fox Ln",
    "sg:city":"Plano",
    "sg:classifiers":[
        {
            "category":"Shopping",
            "subcategory":"Beauty & Cosmetics",
            "type":"Retail Goods"
        }
    ],
    "sg:phone":"+1 972 931 6007",
    "sg:postcode":"75093",
    "sg:province":"TX",
    "sg:tags":[
        "merchandise"
    ],
    "wof:name":"Merle T Waggoner Ranches",
    "wof:placetype":"venue"
},
  "geometry": {"coordinates":[-96.82258899999999,33.025601],"type":"Point"}
}