{
  "type": "Feature",
  "properties": {
    "iso:country":"US",
    "sg:address":"1111 Houston St",
    "sg:city":"Fort Worth",
    "sg:classifiers":[
        {
            "category":"Farming",
            "subcategory":"Livestock Farm",
            "type":"Manufacturing & Wholesale Goods"
        }
    ],
    "sg:phone":"+1 817 332 9141",
    "sg:postcode":"76102",
    "sg:province":"TX",
    "sg:tags":[
        "horse",
        "other",
        "equine"
    ],
    "wof:name":"Seagraves & Assoc",
    "wof:placetype":"venue"
},
  "geometry": {"coordinates":[-97.329319,32.750512],"type":"Point"}
}