{
  "type": "Feature",
  "properties": {
    "iso:country":"US",
    "sg:address":"1510 E 2nd St",
    "sg:city":"Odessa",
    "sg:classifiers":[
        {
            "category":"Autos & Motor Vehicles",
            "subcategory":"Automobile Sales",
            "type":"Retail Goods"
        }
    ],
    "sg:phone":"+1 432 580 9996",
    "sg:postcode":"79761",
    "sg:province":"TX",
    "sg:tags":[
        "car",
        "dealer"
    ],
    "sg:website":"www.westtexasnissan.com",
    "wof:name":"West Texas Nissan Of Odessa",
    "wof:placetype":"venue"
},
  "geometry": {"coordinates":[-102.34894,31.854602],"type":"Point"}
}