{
  "type": "Feature",
  "properties": {
    "iso:country":"US",
    "sg:address":"1330 Winding Trl",
    "sg:city":"Duncanville",
    "sg:classifiers":[
        {
            "category":"Professional",
            "type":"Services"
        }
    ],
    "sg:phone":"+1 972 298 7547",
    "sg:postcode":"75116",
    "sg:province":"TX",
    "wof:name":"Dessco",
    "wof:placetype":"venue"
},
  "geometry": {"coordinates":[-96.89626800000001,32.670613],"type":"Point"}
}