{
  "type": "Feature",
  "properties": {
    "iso:country":"US",
    "sg:address":"2570 Sweetgum Ln",
    "sg:city":"Beaumont",
    "sg:classifiers":[
        {
            "category":"Real Estate",
            "subcategory":"Real Estate Operator",
            "type":"Services"
        }
    ],
    "sg:phone":"+1 409 899 2591",
    "sg:postcode":"77703",
    "sg:province":"TX",
    "sg:tags":[
        "building",
        "apartment"
    ],
    "wof:name":"French Road Luxury Apartments",
    "wof:placetype":"venue"
},
  "geometry": {"coordinates":[-94.12881299999999,30.097581],"type":"Point"}
}