{
  "type": "Feature",
  "properties": {
    "iso:country":"US",
    "sg:address":"811 Alpha Dr",
    "sg:city":"Richardson",
    "sg:classifiers":[
        {
            "category":"Insurance",
            "subcategory":"Title Insurance",
            "type":"Services"
        },
        {
            "category":"Real Estate",
            "subcategory":"Real Estate Services",
            "type":"Services"
        }
    ],
    "sg:phone":"+1 972 437 5501",
    "sg:postcode":"75081",
    "sg:province":"TX",
    "sg:tags":[
        "company",
        "carrier",
        "abstract"
    ],
    "wof:name":"Standard Land Title Co LLC",
    "wof:placetype":"venue"
},
  "geometry": {"coordinates":[-96.71217900000001,32.957076],"type":"Point"}
}