{
  "type": "Feature",
  "properties": {
    "iso:country":"US",
    "sg:address":"688 W Main Ave",
    "sg:city":"Raymondville",
    "sg:classifiers":[
        {
            "category":"Place Of Worship",
            "subcategory":"Church",
            "type":"Public Place"
        },
        {
            "category":"Place Of Worship",
            "type":"Public Place"
        }
    ],
    "sg:phone":"+1 956 689 2633",
    "sg:postcode":"78580",
    "sg:province":"TX",
    "sg:tags":[
        "churches-baptist-general",
        "churches-baptist"
    ],
    "wof:name":"Iglesia Bautista Mexicana",
    "wof:placetype":"venue"
},
  "geometry": {"coordinates":[-97.790947,26.482871],"type":"Point"}
}