{
  "type": "Feature",
  "properties": {
    "iso:country":"US",
    "sg:address":"4408 Lakeside Dr",
    "sg:city":"Dallas",
    "sg:classifiers":[
        {
            "category":"Real Estate",
            "subcategory":"Real Estate Operator",
            "type":"Services"
        }
    ],
    "sg:phone":"+1 214 521 4408",
    "sg:postcode":"75205",
    "sg:province":"TX",
    "sg:tags":[
        "building",
        "nonresidential"
    ],
    "wof:name":"Lpg Properties Inc",
    "wof:placetype":"venue"
},
  "geometry": {"coordinates":[-96.800262,32.824722],"type":"Point"}
}