{
  "type": "Feature",
  "properties": {
    "iso:country":"US",
    "sg:address":"508 Graham Ln",
    "sg:city":"Wylie",
    "sg:classifiers":[
        {
            "category":"Home & Garden",
            "subcategory":"Garden Supply",
            "type":"Retail Goods"
        },
        {
            "category":"Manufacturing",
            "subcategory":"Paper Products",
            "type":"Manufacturing & Wholesale Goods"
        }
    ],
    "sg:phone":"+1 972 442 0123",
    "sg:postcode":"75098",
    "sg:province":"TX",
    "sg:tags":[
        "bamboo"
    ],
    "wof:name":"Arbolitos",
    "wof:placetype":"venue"
},
  "geometry": {"coordinates":[-96.54647,33.023058],"type":"Point"}
}