{
  "type": "Feature",
  "properties": {
    "iso:country":"US",
    "sg:address":"3501 N MacArthur Blvd Ste 400",
    "sg:city":"Irving",
    "sg:classifiers":[
        {
            "category":"Health Services",
            "subcategory":"Doctor",
            "type":"Services"
        }
    ],
    "sg:phone":"+1 972 253 4260",
    "sg:postcode":"75062",
    "sg:province":"TX",
    "sg:tags":[
        "practice",
        "family"
    ],
    "sg:website":"www.drfoodsensitivity.com",
    "wof:name":"MEDICAL & SURGICAL CLINIC OF IRVING",
    "wof:placetype":"venue"
},
  "geometry": {"coordinates":[-96.959273,32.852465],"type":"Point"}
}