{
  "type": "Feature",
  "properties": {
    "iso:country":"US",
    "sg:address":"123 Topeka Dr",
    "sg:city":"Waco",
    "sg:classifiers":[
        {
            "category":"Banks & Credit Unions",
            "subcategory":"Investment Brokerage",
            "type":"Services"
        }
    ],
    "sg:phone":"+1 254 776 5404",
    "sg:postcode":"76712",
    "sg:province":"TX",
    "sg:tags":[
        "advisory",
        "financial"
    ],
    "wof:name":"Preferred Retirement Options",
    "wof:placetype":"venue"
},
  "geometry": {"coordinates":[-97.20304,31.506702],"type":"Point"}
}