{
  "type": "Feature",
  "properties": {
    "iso:country":"US",
    "sg:address":"11500 Northwest Fwy Ste 490",
    "sg:city":"Houston",
    "sg:classifiers":[
        {
            "category":"Education",
            "subcategory":"School",
            "type":"Public Place"
        }
    ],
    "sg:phone":"+1 713 688 3649",
    "sg:postcode":"77092",
    "sg:province":"TX",
    "wof:name":"Miracle Educational Systems",
    "wof:placetype":"venue"
},
  "geometry": {"coordinates":[-95.47111,29.822398],"type":"Point"}
}