{
  "type": "Feature",
  "properties": {
    "iso:country":"US",
    "sg:address":"913 N 3rd St",
    "sg:city":"Longview",
    "sg:classifiers":[
        {
            "category":"Utilities",
            "subcategory":"Telephone",
            "type":"Services"
        }
    ],
    "sg:phone":"+1 903 234 8320",
    "sg:postcode":"75601",
    "sg:province":"TX",
    "sg:tags":[
        "telecommunication"
    ],
    "wof:name":"Alaniz Enterprises",
    "wof:placetype":"venue"
},
  "geometry": {"coordinates":[-94.732478,32.505907],"type":"Point"}
}