{
  "type": "Feature",
  "properties": {
    "iso:country":"US",
    "sg:address":"1528 Holt St",
    "sg:city":"Fort Worth",
    "sg:classifiers":[
        {
            "category":"Manufacturing",
            "subcategory":"Printing",
            "type":"Manufacturing & Wholesale Goods"
        }
    ],
    "sg:phone":"+1 817 450 4769",
    "sg:postcode":"76103",
    "sg:province":"TX",
    "sg:tags":[
        "publisher",
        "music"
    ],
    "wof:name":"Umg Records Inc",
    "wof:placetype":"venue"
},
  "geometry": {"coordinates":[-97.25156200000001,32.758234],"type":"Point"}
}