{
  "type": "Feature",
  "properties": {
    "iso:country":"US",
    "sg:address":"902 Singing Hills Dr",
    "sg:city":"Garland",
    "sg:classifiers":[
        {
            "category":"Wholesale",
            "subcategory":"Machinery & Supplies",
            "type":"Manufacturing & Wholesale Goods"
        }
    ],
    "sg:phone":"+1 972 414 6721",
    "sg:postcode":"75044",
    "sg:province":"TX",
    "sg:tags":[
        "equipment",
        "industrial"
    ],
    "wof:name":"Talk Light Inc",
    "wof:placetype":"venue"
},
  "geometry": {"coordinates":[-96.637933,32.971335],"type":"Point"}
}