{
  "type": "Feature",
  "properties": {
    "iso:country":"US",
    "sg:address":"2121 Larkspur Dr",
    "sg:city":"Carrollton",
    "sg:classifiers":[
        {
            "category":"Building & Trades",
            "subcategory":"Construction",
            "type":"Services"
        }
    ],
    "sg:phone":"+1 972 394 1927",
    "sg:postcode":"75010",
    "sg:province":"TX",
    "sg:tags":[
        "house"
    ],
    "wof:name":"Smith Home Repair",
    "wof:placetype":"venue"
},
  "geometry": {"coordinates":[-96.87321,33.026281],"type":"Point"}
}