{
  "type": "Feature",
  "properties": {
    "iso:country":"US",
    "sg:address":"7205 Louetta Rd",
    "sg:city":"Spring",
    "sg:classifiers":[
        {
            "category":"Building & Trades",
            "subcategory":"Landscaping Services",
            "type":"Services"
        }
    ],
    "sg:phone":"+1 281 370 4769",
    "sg:postcode":"77379",
    "sg:province":"TX",
    "sg:tags":[
        "work",
        "designer",
        "design",
        "landscape",
        "maintenance"
    ],
    "wof:name":"Colorful Environments Inc",
    "wof:placetype":"venue"
},
  "geometry": {"coordinates":[-95.522482,30.021601],"type":"Point"}
}