{
  "type": "Feature",
  "properties": {
    "iso:country":"US",
    "sg:address":"104 Ave C",
    "sg:city":"Gatesville",
    "sg:classifiers":[
        {
            "category":"Insurance",
            "subcategory":"Insurance Agent",
            "type":"Services"
        }
    ],
    "sg:phone":"+1 254 865 2698",
    "sg:postcode":"76528",
    "sg:province":"TX",
    "wof:name":"MSMMM Unlimited 33",
    "wof:placetype":"venue"
},
  "geometry": {"coordinates":[-97.772358,31.435081],"type":"Point"}
}