{
  "type": "Feature",
  "properties": {
    "iso:country":"US",
    "sg:address":"500 W William Cannon Dr",
    "sg:city":"Austin",
    "sg:classifiers":[
        {
            "category":"Restaurant",
            "type":"Food & Drink"
        }
    ],
    "sg:menulink":"http://www.allmenus.com/tx/austin/90904-wingstop/menu/",
    "sg:phone":"+1 512 416 9464",
    "sg:postcode":"78745",
    "sg:province":"TX",
    "sg:tags":[
        "american",
        "wing"
    ],
    "wof:name":"Wingstop",
    "wof:placetype":"venue"
},
  "geometry": {"coordinates":[-97.785105,30.196545],"type":"Point"}
}