{
  "type": "Feature",
  "properties": {
    "iso:country":"US",
    "sg:address":"2202 Sieber Dr",
    "sg:city":"Houston",
    "sg:classifiers":[
        {
            "category":"Professional",
            "subcategory":"Business Services",
            "type":"Services"
        }
    ],
    "sg:phone":"+1 713 946 5858",
    "sg:postcode":"77017",
    "sg:province":"TX",
    "wof:name":"Rick Zeplin Enterprises R",
    "wof:placetype":"venue"
},
  "geometry": {"coordinates":[-95.239206,29.675785],"type":"Point"}
}