{
  "type": "Feature",
  "properties": {
    "iso:country":"US",
    "sg:address":"4517 Rutland Ave",
    "sg:city":"Fort Worth",
    "sg:classifiers":[
        {
            "category":"Building & Trades",
            "subcategory":"Construction",
            "type":"Services"
        }
    ],
    "sg:phone":"+1 817 920 9669",
    "sg:postcode":"76133",
    "sg:province":"TX",
    "sg:tags":[
        "contractor"
    ],
    "wof:name":"N&S Acoustics",
    "wof:placetype":"venue"
},
  "geometry": {"coordinates":[-97.36169599999999,32.679888],"type":"Point"}
}