{
  "type": "Feature",
  "properties": {
    "iso:country":"US",
    "sg:address":"2121 Midlane St",
    "sg:city":"Houston",
    "sg:classifiers":[
        {
            "category":"Banks & Credit Unions",
            "subcategory":"Bank",
            "type":"Services"
        }
    ],
    "sg:phone":"+1 713 850 9008",
    "sg:postcode":"77027",
    "sg:province":"TX",
    "sg:tags":[
        "mortgage"
    ],
    "wof:name":"Lh Mortgage Financial Services",
    "wof:placetype":"venue"
},
  "geometry": {"coordinates":[-95.449685,29.744975],"type":"Point"}
}