{
  "type": "Feature",
  "properties": {
    "iso:country":"US",
    "sg:address":"5611 Comanche Dr",
    "sg:city":"Edinburg",
    "sg:classifiers":[
        {
            "category":"Retail",
            "subcategory":"Auto Repair",
            "type":"Services"
        }
    ],
    "sg:phone":"+1 956 787 9637",
    "sg:postcode":"78539",
    "sg:province":"TX",
    "sg:tags":[
        "general"
    ],
    "wof:name":"Martins Commercial Repair",
    "wof:placetype":"venue"
},
  "geometry": {"coordinates":[-98.14252500000001,26.243419],"type":"Point"}
}