{
  "type": "Feature",
  "properties": {
    "iso:country":"US",
    "sg:address":"926 Beau Dr",
    "sg:city":"Coppell",
    "sg:classifiers":[
        {
            "category":"Manufacturing",
            "subcategory":"Printing",
            "type":"Manufacturing & Wholesale Goods"
        }
    ],
    "sg:phone":"+1 972 393 9401",
    "sg:postcode":"75019",
    "sg:province":"TX",
    "sg:tags":[
        "publisher",
        "software"
    ],
    "wof:name":"Workflow Enterprises",
    "wof:placetype":"venue"
},
  "geometry": {"coordinates":[-96.96114,32.982844],"type":"Point"}
}