{
  "type": "Feature",
  "properties": {
    "iso:country":"US",
    "sg:address":"1430 Acton Ave",
    "sg:city":"Duncanville",
    "sg:classifiers":[
        {
            "category":"Insurance",
            "subcategory":"Insurance Agent",
            "type":"Services"
        }
    ],
    "sg:phone":"+1 972 298 4204",
    "sg:postcode":"75137",
    "sg:province":"TX",
    "sg:tags":[
        "fidelity",
        "surety",
        "bond"
    ],
    "wof:name":"Young Insurance",
    "wof:placetype":"venue"
},
  "geometry": {"coordinates":[-96.900886,32.634688],"type":"Point"}
}