{
  "type": "Feature",
  "properties": {
    "iso:country":"US",
    "sg:address":"25211 Grogans Mill Rd",
    "sg:city":"Spring",
    "sg:classifiers":[
        {
            "category":"Professional",
            "subcategory":"Management & Consulting",
            "type":"Services"
        }
    ],
    "sg:phone":"+1 281 298 6591",
    "sg:postcode":"77380",
    "sg:province":"TX",
    "wof:name":"Axiom Financial",
    "wof:placetype":"venue"
},
  "geometry": {"coordinates":[-95.45715,30.128972],"type":"Point"}
}