{
  "type": "Feature",
  "properties": {
    "iso:country":"US",
    "sg:address":"6502 Kury Ln",
    "sg:city":"Houston",
    "sg:classifiers":[
        {
            "category":"Restaurant",
            "type":"Food & Drink"
        }
    ],
    "sg:phone":"+1 713 868 3243",
    "sg:postcode":"77008",
    "sg:province":"TX",
    "sg:tags":[
        "caterer"
    ],
    "sg:website":"www.grandparentingmagazine.com",
    "wof:name":"Make My Lunch",
    "wof:placetype":"venue"
},
  "geometry": {"coordinates":[-95.43241500000001,29.797375],"type":"Point"}
}