{
  "type": "Feature",
  "properties": {
    "iso:country":"US",
    "sg:address":"5700 Granite Pkwy",
    "sg:city":"Plano",
    "sg:classifiers":[
        {
            "category":"Banks & Credit Unions",
            "subcategory":"Bank",
            "type":"Services"
        }
    ],
    "sg:phone":"+1 972 731 6711",
    "sg:postcode":"75024",
    "sg:province":"TX",
    "sg:tags":[
        "loan",
        "real estate"
    ],
    "wof:name":"Ambassador Mortgage",
    "wof:placetype":"venue"
},
  "geometry": {"coordinates":[-96.81727600000001,33.086931],"type":"Point"}
}