{
  "type": "Feature",
  "properties": {
    "iso:country":"US",
    "sg:address":"3315 Bush Dr",
    "sg:city":"Amarillo",
    "sg:classifiers":[
        {
            "category":"Banks & Credit Unions",
            "subcategory":"Investment Brokerage",
            "type":"Services"
        }
    ],
    "sg:phone":"+1 806 352 7705",
    "sg:postcode":"79106",
    "sg:province":"TX",
    "wof:name":"Morgan Financial Svc",
    "wof:placetype":"venue"
},
  "geometry": {"coordinates":[-101.909448,35.17803],"type":"Point"}
}