{
  "type": "Feature",
  "properties": {
    "iso:country":"US",
    "sg:address":"900 US Hwy 62",
    "sg:city":"Ralls",
    "sg:classifiers":[
        {
            "category":"Food & Beverages",
            "subcategory":"Groceries & Convenience Stores",
            "type":"Retail Goods"
        }
    ],
    "sg:phone":"+1 806 253 0118",
    "sg:postcode":"79316",
    "sg:province":"TX",
    "wof:name":"Ampride",
    "wof:placetype":"venue"
},
  "geometry": {"coordinates":[-102.274109,33.188099],"type":"Point"}
}