{
  "type": "Feature",
  "properties": {
    "iso:country":"US",
    "sg:address":"7003 Brittmoore Rd",
    "sg:city":"Houston",
    "sg:classifiers":[
        {
            "category":"Professional",
            "subcategory":"Business Services",
            "type":"Services"
        }
    ],
    "sg:phone":"+1 713 937 6060",
    "sg:postcode":"77041",
    "sg:province":"TX",
    "sg:tags":[
        "inspection"
    ],
    "wof:name":"Nelrod Co",
    "wof:placetype":"venue"
},
  "geometry": {"coordinates":[-95.569321,29.871145],"type":"Point"}
}