{
  "type": "Feature",
  "properties": {
    "iso:country":"US",
    "sg:address":"85 Artesian Way",
    "sg:city":"New Caney",
    "sg:classifiers":[
        {
            "category":"Professional",
            "subcategory":"Accounting & Tax Preparation",
            "type":"Services"
        }
    ],
    "sg:phone":"+1 281 399 2836",
    "sg:postcode":"77357",
    "sg:province":"TX",
    "sg:tags":[
        "billing"
    ],
    "wof:name":"Professional Billing Svc",
    "wof:placetype":"venue"
},
  "geometry": {"coordinates":[-95.162105,30.174591],"type":"Point"}
}