{
  "type": "Feature",
  "properties": {
    "iso:country":"US",
    "sg:address":"6808 Woodflame Ct",
    "sg:city":"San Antonio",
    "sg:classifiers":[
        {
            "category":"Building & Trades",
            "subcategory":"Pest Control",
            "type":"Services"
        }
    ],
    "sg:phone":"+1 210 673 7617",
    "sg:postcode":"78227",
    "sg:province":"TX",
    "wof:name":"J & E Pest Control",
    "wof:placetype":"venue"
},
  "geometry": {"coordinates":[-98.625567,29.423152],"type":"Point"}
}