{
  "type": "Feature",
  "properties": {
    "iso:country":"US",
    "sg:address":"2304 1st St",
    "sg:city":"Palacios",
    "sg:classifiers":[
        {
            "category":"Retail",
            "subcategory":"Auto Repair",
            "type":"Services"
        }
    ],
    "sg:phone":"+1 361 972 6394",
    "sg:postcode":"77465",
    "sg:province":"TX",
    "sg:tags":[
        "repairing",
        "automobile"
    ],
    "wof:name":"Correa Auto Repair",
    "wof:placetype":"venue"
},
  "geometry": {"coordinates":[-96.210189,28.726793],"type":"Point"}
}