{
  "type": "Feature",
  "properties": {
    "iso:country":"US",
    "sg:address":"1704 Holland",
    "sg:city":"Houston",
    "sg:classifiers":[
        {
            "category":"Recreation",
            "type":"Entertainment"
        }
    ],
    "sg:phone":"+1 713 453 5786",
    "sg:postcode":"77029",
    "sg:province":"TX",
    "sg:tags":[
        "track",
        "operation",
        "racing",
        "or"
    ],
    "wof:name":"Texas Canoe Racing Assoc",
    "wof:placetype":"venue"
},
  "geometry": {"coordinates":[-95.23371299999999,29.760322],"type":"Point"}
}