{
  "type": "Feature",
  "properties": {
    "iso:country":"US",
    "sg:address":"1308 Fannin St",
    "sg:city":"Columbus",
    "sg:classifiers":[
        {
            "category":"Communications",
            "type":"Services"
        }
    ],
    "sg:phone":"+1 979 732 2211",
    "sg:postcode":"78934",
    "sg:province":"TX",
    "wof:name":"Time Warner Communications",
    "wof:placetype":"venue"
},
  "geometry": {"coordinates":[-96.546919,29.704149],"type":"Point"}
}