{
  "type": "Feature",
  "properties": {
    "iso:country":"US",
    "sg:address":"410 E Main St",
    "sg:city":"Atlanta",
    "sg:classifiers":[
        {
            "category":"Professional",
            "subcategory":"Business Services",
            "type":"Services"
        },
        {
            "category":"Government",
            "subcategory":"Post Office",
            "type":"Public Place"
        }
    ],
    "sg:phone":"+1 903 799 6931",
    "sg:postcode":"75551",
    "sg:province":"TX",
    "sg:tags":[
        "mail",
        "receiving",
        "mailbox-rental",
        "shipping"
    ],
    "wof:name":"Mail Ma'am & More Inc",
    "wof:placetype":"venue"
},
  "geometry": {"coordinates":[-94.160881,33.112956],"type":"Point"}
}