{
  "type": "Feature",
  "properties": {
    "iso:country":"US",
    "sg:address":"42 E Concho Ave",
    "sg:city":"San Angelo",
    "sg:classifiers":[
        {
            "category":"Shopping",
            "subcategory":"Used Merchandise",
            "type":"Retail Goods"
        }
    ],
    "sg:phone":"+1 325 655 3962",
    "sg:postcode":"76903",
    "sg:province":"TX",
    "sg:tags":[
        "antique",
        "business"
    ],
    "wof:name":"Concho Confetti Antique Mall",
    "wof:placetype":"venue"
},
  "geometry": {"coordinates":[-100.43454199999999,31.460346],"type":"Point"}
}