{
  "type": "Feature",
  "properties": {
    "iso:country":"US",
    "sg:address":"1803 Knox St",
    "sg:city":"Uvalde",
    "sg:classifiers":[
        {
            "category":"Place Of Worship",
            "subcategory":"Church",
            "type":"Public Place"
        },
        {
            "category":"Place Of Worship",
            "type":"Public Place"
        }
    ],
    "sg:phone":"+1 830 278 2936",
    "sg:postcode":"78801",
    "sg:province":"TX",
    "sg:tags":[
        "churches-baptist-general",
        "churches-baptist"
    ],
    "wof:name":"Northside Baptist Church",
    "wof:placetype":"venue"
},
  "geometry": {"coordinates":[-99.795727,29.231498],"type":"Point"}
}