{
  "type": "Feature",
  "properties": {
    "iso:country":"US",
    "sg:address":"2415 Pittman St",
    "sg:city":"Dallas",
    "sg:classifiers":[
        {
            "category":"Retail",
            "subcategory":"Repair Shop",
            "type":"Services"
        }
    ],
    "sg:phone":"+1 214 748 5116",
    "sg:postcode":"75208",
    "sg:province":"TX",
    "sg:tags":[
        "industrial",
        "electrical",
        "machinery",
        "welding",
        "mfg"
    ],
    "wof:name":"Belz Machine Works",
    "wof:placetype":"venue"
},
  "geometry": {"coordinates":[-96.83111,32.774179],"type":"Point"}
}