{
  "type": "Feature",
  "properties": {
    "iso:country":"US",
    "sg:address":"13706 Barons Bridge Dr",
    "sg:city":"Houston",
    "sg:classifiers":[
        {
            "category":"Shopping",
            "subcategory":"Clothing, Apparel, & Fashions",
            "type":"Retail Goods"
        }
    ],
    "sg:phone":"+1 281 895 8826",
    "sg:postcode":"77069",
    "sg:province":"TX",
    "wof:name":"Linda Latest From",
    "wof:placetype":"venue"
},
  "geometry": {"coordinates":[-95.51978200000001,29.99109],"type":"Point"}
}