{
  "type": "Feature",
  "properties": {
    "iso:country":"US",
    "sg:address":"2623 Amherst Dr",
    "sg:city":"Wichita Falls",
    "sg:classifiers":[
        {
            "category":"Banks & Credit Unions",
            "subcategory":"Financial Services",
            "type":"Services"
        }
    ],
    "sg:phone":"+1 940 696 9212",
    "sg:postcode":"76308",
    "sg:province":"TX",
    "sg:tags":[
        "investor"
    ],
    "wof:name":"Kcalf LLC",
    "wof:placetype":"venue"
},
  "geometry": {"coordinates":[-98.53043,33.853407],"type":"Point"}
}