{
  "type": "Feature",
  "properties": {
    "iso:country":"US",
    "sg:address":"116 N Ballard Ave",
    "sg:city":"Wylie",
    "sg:classifiers":[
        {
            "category":"Shopping",
            "subcategory":"Jewelry",
            "type":"Retail Goods"
        }
    ],
    "sg:phone":"+1 972 442 4781",
    "sg:postcode":"75098",
    "sg:province":"TX",
    "sg:tags":[
        "jeweler"
    ],
    "wof:name":"Wylie Jewelry",
    "wof:placetype":"venue"
},
  "geometry": {"coordinates":[-96.538816,33.014249],"type":"Point"}
}