{
  "type": "Feature",
  "properties": {
    "iso:country":"US",
    "sg:address":"2227 Texas Ave",
    "sg:city":"Bridge City",
    "sg:classifiers":[
        {
            "category":"Restaurant",
            "type":"Food & Drink"
        }
    ],
    "sg:phone":"+1 409 735 5482",
    "sg:postcode":"77611",
    "sg:province":"TX",
    "sg:tags":[
        "barbecue"
    ],
    "wof:name":"Yellow Rose Bar-B-Q",
    "wof:placetype":"venue"
},
  "geometry": {"coordinates":[-93.827117,30.039276],"type":"Point"}
}