{
  "type": "Feature",
  "properties": {
    "iso:country":"US",
    "sg:address":"706 Arkansas St",
    "sg:city":"South Houston",
    "sg:classifiers":[
        {
            "category":"Shopping",
            "subcategory":"Beauty & Cosmetics",
            "type":"Retail Goods"
        }
    ],
    "sg:phone":"+1 713 944 5010",
    "sg:postcode":"77587",
    "sg:province":"TX",
    "sg:tags":[
        "merchandise"
    ],
    "wof:name":"Tonies Cosmetics",
    "wof:placetype":"venue"
},
  "geometry": {"coordinates":[-95.233086,29.654309],"type":"Point"}
}