{
  "type": "Feature",
  "properties": {
    "iso:country":"US",
    "sg:address":"4213 Todd Ln",
    "sg:city":"Austin",
    "sg:classifiers":[
        {
            "category":"Wholesale",
            "subcategory":"Electrical",
            "type":"Manufacturing & Wholesale Goods"
        }
    ],
    "sg:phone":"+1 512 441 0005",
    "sg:postcode":"78744",
    "sg:province":"TX",
    "sg:tags":[
        "equipment",
        "electric",
        "supply"
    ],
    "sg:website":"www.cdtexas.com",
    "wof:name":"Consolidated Electrical Distr",
    "wof:placetype":"venue"
},
  "geometry": {"coordinates":[-97.73897700000001,30.209342],"type":"Point"}
}