{
  "type": "Feature",
  "properties": {
    "iso:country":"US",
    "sg:address":"6633 Canyon Dr",
    "sg:city":"Amarillo",
    "sg:classifiers":[
        {
            "category":"Wholesale",
            "subcategory":"Medical Equipment & Supplies",
            "type":"Manufacturing & Wholesale Goods"
        },
        {
            "category":"Retail",
            "subcategory":"Repair Shop",
            "type":"Services"
        },
        {
            "category":"Shopping",
            "subcategory":"Pharmacy",
            "type":"Retail Goods"
        }
    ],
    "sg:phone":"+1 806 352 4140",
    "sg:postcode":"79110",
    "sg:province":"TX",
    "sg:tags":[
        "physician",
        "refinishing",
        "health",
        "home",
        "surgeon",
        "equipment-repairing",
        "care"
    ],
    "sg:website":"http://www.qualityo2.com",
    "wof:name":"Quality Respiratory Service and Repair",
    "wof:placetype":"venue"
},
  "geometry": {"coordinates":[-101.895174,35.136206],"type":"Point"}
}