{
  "type": "Feature",
  "properties": {
    "iso:country":"US",
    "sg:address":"9513 Burnet Rd Ste 203",
    "sg:city":"Austin",
    "sg:classifiers":[
        {
            "category":"Place Of Worship",
            "subcategory":"Church",
            "type":"Public Place"
        },
        {
            "category":"Place Of Worship",
            "type":"Public Place"
        }
    ],
    "sg:phone":"+1 512 647 7004",
    "sg:postcode":"78758",
    "sg:province":"TX",
    "sg:tags":[
        "churches-non-denominational"
    ],
    "wof:name":"Covenant Cathedral",
    "wof:placetype":"venue"
},
  "geometry": {"coordinates":[-97.725059,30.379222],"type":"Point"}
}