{
  "type": "Feature",
  "properties": {
    "iso:country":"US",
    "sg:address":"2315 Pheasant Creek Dr",
    "sg:city":"Sugar Land",
    "sg:classifiers":[
        {
            "category":"Professional",
            "subcategory":"Management & Consulting",
            "type":"Services"
        }
    ],
    "sg:phone":"+1 281 265 0628",
    "sg:postcode":"77478",
    "sg:province":"TX",
    "sg:tags":[
        "construction"
    ],
    "wof:name":"New Star Corp",
    "wof:placetype":"venue"
},
  "geometry": {"coordinates":[-95.66281600000001,29.640837],"type":"Point"}
}