{
  "type": "Feature",
  "properties": {
    "iso:country":"US",
    "sg:address":"315 Edgewood Ln",
    "sg:city":"Wake Village",
    "sg:classifiers":[
        {
            "category":"Building & Trades",
            "subcategory":"Plumbing",
            "type":"Services"
        }
    ],
    "sg:phone":"+1 903 832 8501",
    "sg:postcode":"75501",
    "sg:province":"TX",
    "sg:tags":[
        "conditioning",
        "air",
        "system",
        "contractor"
    ],
    "wof:name":"Bell Air Professional Svc",
    "wof:placetype":"venue"
},
  "geometry": {"coordinates":[-94.11877699999999,33.426595],"type":"Point"}
}