{
  "type": "Feature",
  "properties": {
    "iso:country":"US",
    "sg:address":"304 N Ballard Ave",
    "sg:city":"Wylie",
    "sg:classifiers":[
        {
            "category":"Shopping",
            "subcategory":"Jewelry",
            "type":"Retail Goods"
        }
    ],
    "sg:phone":"+1 972 578 2578",
    "sg:postcode":"75098",
    "sg:province":"TX",
    "sg:tags":[
        "designer"
    ],
    "wof:name":"Hart Mc Daniel Designs",
    "wof:placetype":"venue"
},
  "geometry": {"coordinates":[-96.538787,33.016324],"type":"Point"}
}