{
  "type": "Feature",
  "properties": {
    "iso:country":"US",
    "sg:address":"706 S Caddo St",
    "sg:city":"Cleburne",
    "sg:classifiers":[
        {
            "category":"Retail",
            "subcategory":"Auto Repair",
            "type":"Services"
        }
    ],
    "sg:phone":"+1 817 556 4600",
    "sg:postcode":"76031",
    "sg:province":"TX",
    "wof:name":"Jerry's Automotive Service",
    "wof:placetype":"venue"
},
  "geometry": {"coordinates":[-97.384426,32.342474],"type":"Point"}
}