{
  "type": "Feature",
  "properties": {
    "iso:country":"US",
    "sg:address":"231 E Belt Line Rd",
    "sg:city":"Desoto",
    "sg:classifiers":[
        {
            "category":"Professional",
            "type":"Services"
        },
        {
            "category":"Shopping",
            "type":"Retail Goods"
        }
    ],
    "sg:phone":"+1 972 230 2540",
    "sg:postcode":"75115",
    "sg:province":"TX",
    "sg:tags":[
        "carving",
        "product",
        "wood",
        "mfg"
    ],
    "wof:name":"Bavarian Wood Carving Studio",
    "wof:placetype":"venue"
},
  "geometry": {"coordinates":[-96.85543,32.58979],"type":"Point"}
}