{
  "type": "Feature",
  "properties": {
    "iso:country":"US",
    "sg:address":"4802 Old Spanish Trl",
    "sg:city":"Houston",
    "sg:classifiers":[
        {
            "category":"Banks & Credit Unions",
            "subcategory":"Bank",
            "type":"Services"
        }
    ],
    "sg:phone":"+1 713 440 9000",
    "sg:postcode":"77021",
    "sg:province":"TX",
    "sg:tags":[
        "loan"
    ],
    "wof:name":"Investor Lending Svc",
    "wof:placetype":"venue"
},
  "geometry": {"coordinates":[-95.34352699999999,29.706103],"type":"Point"}
}