{
  "type": "Feature",
  "properties": {
    "iso:country":"US",
    "sg:address":"3302 Old Alvin Rd",
    "sg:city":"Pearland",
    "sg:classifiers":[
        {
            "category":"Organizations",
            "subcategory":"Non-profit Organization",
            "type":"Services"
        }
    ],
    "sg:phone":"+1 281 997 2295",
    "sg:postcode":"77581",
    "sg:province":"TX",
    "sg:tags":[
        "disability"
    ],
    "wof:name":"Golden Rule Svc",
    "wof:placetype":"venue"
},
  "geometry": {"coordinates":[-95.277226,29.548306],"type":"Point"}
}