{
  "type": "Feature",
  "properties": {
    "iso:country":"US",
    "sg:address":"6145 Allendale Rd",
    "sg:city":"Houston",
    "sg:classifiers":[
        {
            "category":"Personal",
            "subcategory":"Beauty Salon",
            "type":"Services"
        }
    ],
    "sg:phone":"+1 713 473 1965",
    "sg:postcode":"77017",
    "sg:province":"TX",
    "sg:tags":[
        "nail",
        "shop"
    ],
    "wof:name":"Tk Nails",
    "wof:placetype":"venue"
},
  "geometry": {"coordinates":[-95.2304,29.6835],"type":"Point"}
}