{
  "type": "Feature",
  "properties": {
    "iso:country":"US",
    "sg:address":"9370 S Point Dr",
    "sg:city":"Houston",
    "sg:classifiers":[
        {
            "category":"Wholesale",
            "subcategory":"Machinery & Supplies",
            "type":"Manufacturing & Wholesale Goods"
        }
    ],
    "sg:phone":"+1 713 796 8800",
    "sg:postcode":"77054",
    "sg:province":"TX",
    "sg:tags":[
        "glass",
        "container",
        "metal",
        "bottle",
        "plastic"
    ],
    "wof:name":"Tricor Braun",
    "wof:placetype":"venue"
},
  "geometry": {"coordinates":[-95.41114,29.666617],"type":"Point"}
}