{
  "type": "Feature",
  "properties": {
    "iso:country":"US",
    "sg:address":"816 Stuckey Dr",
    "sg:city":"Longview",
    "sg:classifiers":[
        {
            "category":"Professional",
            "subcategory":"Art Services",
            "type":"Services"
        }
    ],
    "sg:phone":"+1 903 234 1448",
    "sg:postcode":"75601",
    "sg:province":"TX",
    "sg:tags":[
        "designer",
        "display",
        "producer"
    ],
    "wof:name":"K & E Darlin Designs",
    "wof:placetype":"venue"
},
  "geometry": {"coordinates":[-94.725454,32.500836],"type":"Point"}
}