{
  "type": "Feature",
  "properties": {
    "iso:country":"US",
    "sg:address":"9504 Topridge Dr",
    "sg:city":"Austin",
    "sg:classifiers":[
        {
            "category":"Building & Trades",
            "subcategory":"Cleaning & Sanitation",
            "type":"Services"
        }
    ],
    "sg:phone":"+1 512 258 0042",
    "sg:postcode":"78750",
    "sg:province":"TX",
    "sg:tags":[
        "window"
    ],
    "wof:name":"Artisan Window Cleaning",
    "wof:placetype":"venue"
},
  "geometry": {"coordinates":[-97.79766499999999,30.434389],"type":"Point"}
}