{
  "type": "Feature",
  "properties": {
    "iso:country":"US",
    "sg:address":"10960 Composite Dr",
    "sg:city":"Dallas",
    "sg:classifiers":[
        {
            "category":"Restaurant",
            "type":"Food & Drink"
        }
    ],
    "sg:phone":"+1 214 357 0279",
    "sg:postcode":"75220",
    "sg:province":"TX",
    "sg:tags":[
        "drinking",
        "eating"
    ],
    "wof:name":"Pauls Porterhouse Steak & Seafood",
    "wof:placetype":"venue"
},
  "geometry": {"coordinates":[-96.89589700000001,32.880299],"type":"Point"}
}