{
  "type": "Feature",
  "properties": {
    "iso:country":"US",
    "sg:address":"10405 Richard Cir",
    "sg:city":"Forney",
    "sg:classifiers":[
        {
            "category":"Building & Trades",
            "subcategory":"Construction",
            "type":"Services"
        }
    ],
    "sg:phone":"+1 972 564 9832",
    "sg:postcode":"75126",
    "sg:province":"TX",
    "sg:tags":[
        "contractor"
    ],
    "wof:name":"Bret Foster Roofing Inc",
    "wof:placetype":"venue"
},
  "geometry": {"coordinates":[-96.438959,32.718046],"type":"Point"}
}