{
  "type": "Feature",
  "properties": {
    "iso:country":"US",
    "sg:address":"4225 Redbud Ave",
    "sg:city":"Odessa",
    "sg:classifiers":[
        {
            "category":"Manufacturing",
            "subcategory":"Pet Food",
            "type":"Manufacturing & Wholesale Goods"
        }
    ],
    "sg:phone":"+1 432 366 0284",
    "sg:postcode":"79762",
    "sg:province":"TX",
    "sg:tags":[
        "hay"
    ],
    "wof:name":"Hay Magnet",
    "wof:placetype":"venue"
},
  "geometry": {"coordinates":[-102.35504,31.889592],"type":"Point"}
}