{
  "type": "Feature",
  "properties": {
    "iso:country":"US",
    "sg:address":"1115 Pecan Dr",
    "sg:city":"Weatherford",
    "sg:classifiers":[
        {
            "category":"Local Transit",
            "type":"Transportation"
        }
    ],
    "sg:phone":"+1 817 594 1196",
    "sg:postcode":"76086",
    "sg:province":"TX",
    "sg:tags":[
        "passenger"
    ],
    "wof:name":"Lifecare Emergency Medical Svc",
    "wof:placetype":"venue"
},
  "geometry": {"coordinates":[-97.784626,32.74738],"type":"Point"}
}