{
  "type": "Feature",
  "properties": {
    "iso:country":"US",
    "sg:address":"890 Regal Row",
    "sg:city":"Dallas",
    "sg:classifiers":[
        {
            "category":"Building & Trades",
            "subcategory":"Construction",
            "type":"Services"
        }
    ],
    "sg:phone":"+1 214 637 6555",
    "sg:postcode":"75247",
    "sg:province":"TX",
    "sg:tags":[
        "tile-contractors"
    ],
    "sg:website":"http://www.mundotile.com",
    "wof:name":"Mundo Tile",
    "wof:placetype":"venue"
},
  "geometry": {"coordinates":[-96.890328,32.823688],"type":"Point"}
}