{
  "type": "Feature",
  "properties": {
    "iso:country":"US",
    "sg:address":"11225 State Hwy 279",
    "sg:city":"Brownwood",
    "sg:classifiers":[
        {
            "category":"Professional",
            "type":"Services"
        }
    ],
    "sg:phone":"+1 325 641 9308",
    "sg:postcode":"76801",
    "sg:province":"TX",
    "wof:name":"Friends",
    "wof:placetype":"venue"
},
  "geometry": {"coordinates":[-99.120767,31.877603],"type":"Point"}
}