{
  "type": "Feature",
  "properties": {
    "iso:country":"US",
    "sg:address":"2411 Lily Ln",
    "sg:city":"Highlands",
    "sg:classifiers":[
        {
            "category":"Restaurant",
            "type":"Food & Drink"
        }
    ],
    "sg:phone":"+1 281 426 6016",
    "sg:postcode":"77562",
    "sg:province":"TX",
    "wof:name":"Cross Eyed Cookers",
    "wof:placetype":"venue"
},
  "geometry": {"coordinates":[-95.02420600000001,29.813984],"type":"Point"}
}