{
  "type": "Feature",
  "properties": {
    "iso:country":"US",
    "sg:address":"3407 NE 10th St",
    "sg:city":"Mineral Wells",
    "sg:classifiers":[
        {
            "category":"Wholesale",
            "subcategory":"Vending Machines",
            "type":"Manufacturing & Wholesale Goods"
        }
    ],
    "sg:phone":"+1 940 327 0822",
    "sg:postcode":"76067",
    "sg:province":"TX",
    "sg:tags":[
        "operator"
    ],
    "wof:name":"M&M Vending",
    "wof:placetype":"venue"
},
  "geometry": {"coordinates":[-98.086274,32.817058],"type":"Point"}
}