{
  "type": "Feature",
  "properties": {
    "iso:country":"US",
    "sg:address":"1413 W Mount Houston Rd",
    "sg:city":"Houston",
    "sg:classifiers":[
        {
            "category":"Retail",
            "subcategory":"Veterinary Services",
            "type":"Services"
        },
        {
            "category":"Retail",
            "subcategory":"Pet Boarding",
            "type":"Services"
        }
    ],
    "sg:phone":"+1 281 931 6237",
    "sg:postcode":"77038",
    "sg:province":"TX",
    "sg:tags":[
        "veterinarian",
        "boarding/pet",
        "sitting"
    ],
    "sg:website":"www.mthoustonanimalclinic.com",
    "wof:name":"Mt Houston Animal Clinic",
    "wof:placetype":"venue"
},
  "geometry": {"coordinates":[-95.425797,29.8979],"type":"Point"}
}