{
  "type": "Feature",
  "properties": {
    "iso:country":"US",
    "sg:address":"142 Gembler Rd",
    "sg:city":"San Antonio",
    "sg:classifiers":[
        {
            "category":"Manufacturing",
            "subcategory":"Tools & Machinery",
            "type":"Manufacturing & Wholesale Goods"
        }
    ],
    "sg:phone":"+1 210 476 7777",
    "sg:postcode":"78219",
    "sg:province":"TX",
    "sg:tags":[
        "construction"
    ],
    "wof:name":"Terex Utilities-South",
    "wof:placetype":"venue"
},
  "geometry": {"coordinates":[-98.430533,29.435465],"type":"Point"}
}