{
  "type": "Feature",
  "properties": {
    "iso:country":"US",
    "sg:address":"818 South Fwy",
    "sg:city":"Fort Worth",
    "sg:classifiers":[
        {
            "category":"Retail",
            "subcategory":"Auto Repair",
            "type":"Services"
        }
    ],
    "sg:phone":"+1 817 332 3443",
    "sg:postcode":"76104",
    "sg:province":"TX",
    "sg:tags":[
        "automotive"
    ],
    "wof:name":"Fort Worth Towing & Recovery",
    "wof:placetype":"venue"
},
  "geometry": {"coordinates":[-97.320892,32.736392],"type":"Point"}
}