{
  "type": "Feature",
  "properties": {
    "iso:country":"US",
    "sg:address":"2021 Ralph Janes Pl",
    "sg:city":"El Paso",
    "sg:classifiers":[
        {
            "category":"Personal",
            "type":"Services"
        }
    ],
    "sg:phone":"+1 915 857 1104",
    "sg:postcode":"79936",
    "sg:province":"TX",
    "sg:tags":[
        "therapist",
        "massage"
    ],
    "wof:name":"Ron Stone Massage Therapist",
    "wof:placetype":"venue"
},
  "geometry": {"coordinates":[-106.287209,31.770679],"type":"Point"}
}