{
  "type": "Feature",
  "properties": {
    "iso:country":"US",
    "sg:address":"903 N 7th St",
    "sg:city":"Sanger",
    "sg:classifiers":[
        {
            "category":"Building & Trades",
            "subcategory":"Plumbing",
            "type":"Services"
        }
    ],
    "sg:phone":"+1 940 458 4085",
    "sg:postcode":"76266",
    "sg:province":"TX",
    "sg:tags":[
        "contractor"
    ],
    "wof:name":"French Drainfields",
    "wof:placetype":"venue"
},
  "geometry": {"coordinates":[-97.17577900000001,33.36679],"type":"Point"}
}