{
  "type": "Feature",
  "properties": {
    "iso:country":"US",
    "sg:address":"4209 Whippoorwill Ln",
    "sg:city":"Plano",
    "sg:classifiers":[
        {
            "category":"Professional",
            "subcategory":"Management & Consulting",
            "type":"Services"
        }
    ],
    "sg:phone":"+1 972 758 1952",
    "sg:postcode":"75093",
    "sg:province":"TX",
    "sg:tags":[
        "business"
    ],
    "wof:name":"Isix Information Solutions",
    "wof:placetype":"venue"
},
  "geometry": {"coordinates":[-96.77496499999999,33.026316],"type":"Point"}
}