{
  "type": "Feature",
  "properties": {
    "iso:country":"US",
    "sg:address":"2265 63rd St",
    "sg:city":"Port Arthur",
    "sg:classifiers":[
        {
            "category":"Professional",
            "subcategory":"Management & Consulting",
            "type":"Services"
        }
    ],
    "sg:phone":"+1 409 736 1368",
    "sg:postcode":"77640",
    "sg:province":"TX",
    "sg:tags":[
        "consultant"
    ],
    "wof:name":"Applied Consultants Inc",
    "wof:placetype":"venue"
},
  "geometry": {"coordinates":[-94.013401,29.905018],"type":"Point"}
}