{
  "type": "Feature",
  "properties": {
    "iso:country":"US",
    "sg:address":"5353 N Fm 17",
    "sg:city":"Alba",
    "sg:phone":"+1 903 473 1701",
    "sg:postcode":"75410",
    "sg:province":"TX",
    "sg:website":"http://www.veronaitaliancafe.com",
    "wof:name":"Verona Italian Cafe",
    "wof:placetype":"venue"
},
  "geometry": {"coordinates":[-95.638627,32.879588],"type":"Point"}
}