{
  "type": "Feature",
  "properties": {
    "iso:country":"US",
    "sg:address":"428 N Winding Oaks Dr",
    "sg:city":"Wylie",
    "sg:classifiers":[
        {
            "category":"Home & Garden",
            "subcategory":"Home Furnishings",
            "type":"Retail Goods"
        }
    ],
    "sg:phone":"+1 972 429 1726",
    "sg:postcode":"75098",
    "sg:province":"TX",
    "sg:tags":[
        "equipment",
        "fireplace"
    ],
    "wof:name":"Glacier Flames",
    "wof:placetype":"venue"
},
  "geometry": {"coordinates":[-96.54441799999999,33.02216],"type":"Point"}
}