{
  "type": "Feature",
  "properties": {
    "iso:country":"US",
    "sg:address":"201 Wickdome Dr",
    "sg:city":"Willis",
    "sg:classifiers":[
        {
            "category":"Wholesale",
            "subcategory":"Home Furnishings",
            "type":"Manufacturing & Wholesale Goods"
        }
    ],
    "sg:phone":"+1 936 856 3807",
    "sg:postcode":"77378",
    "sg:province":"TX",
    "wof:name":"Sew B It",
    "wof:placetype":"venue"
},
  "geometry": {"coordinates":[-95.447895,30.411566],"type":"Point"}
}