{
  "type": "Feature",
  "properties": {
    "iso:country":"US",
    "sg:address":"704 Windsong Trl",
    "sg:city":"Austin",
    "sg:classifiers":[
        {
            "category":"Real Estate",
            "subcategory":"Real Estate Agent",
            "type":"Services"
        }
    ],
    "sg:phone":"+1 512 329 8863",
    "sg:postcode":"78746",
    "sg:province":"TX",
    "wof:name":"Ausbreck Holdings Inc",
    "wof:placetype":"venue"
},
  "geometry": {"coordinates":[-97.806527,30.300523],"type":"Point"}
}