{
  "type": "Feature",
  "properties": {
    "iso:country":"US",
    "sg:address":"10300 Jensen Dr",
    "sg:city":"Houston",
    "sg:classifiers":[
        {
            "category":"Retail",
            "subcategory":"Auto Repair",
            "type":"Services"
        }
    ],
    "sg:phone":"+1 713 697 6751",
    "sg:postcode":"77093",
    "sg:province":"TX",
    "sg:tags":[
        "trim"
    ],
    "wof:name":"Hicks Auto Trim",
    "wof:placetype":"venue"
},
  "geometry": {"coordinates":[-95.33549600000001,29.86058],"type":"Point"}
}