{
  "type": "Feature",
  "properties": {
    "iso:country":"US",
    "sg:address":"14500 E Cabana St",
    "sg:city":"Corpus Christi",
    "sg:classifiers":[
        {
            "category":"Real Estate",
            "subcategory":"Real Estate Operator",
            "type":"Services"
        }
    ],
    "sg:phone":"+1 361 949 7037",
    "sg:postcode":"78418",
    "sg:province":"TX",
    "sg:tags":[
        "condominium"
    ],
    "wof:name":"Mariner's Cay Marina Condos",
    "wof:placetype":"venue"
},
  "geometry": {"coordinates":[-97.224771,27.621231],"type":"Point"}
}