{
  "type": "Feature",
  "properties": {
    "iso:country":"US",
    "sg:address":"1 Signature Point Dr",
    "sg:city":"League City",
    "sg:classifiers":[
        {
            "category":"Professional",
            "type":"Services"
        }
    ],
    "sg:phone":"+1 281 316 6608",
    "sg:postcode":"77573",
    "sg:province":"TX",
    "wof:name":"American Music Co Op",
    "wof:placetype":"venue"
},
  "geometry": {"coordinates":[-95.074096,29.534913],"type":"Point"}
}