{
  "type": "Feature",
  "properties": {
    "iso:country":"US",
    "sg:address":"3815 Timms St",
    "sg:city":"Tyler",
    "sg:classifiers":[
        {
            "category":"Retail",
            "subcategory":"Auto Repair",
            "type":"Services"
        }
    ],
    "sg:phone":"+1 903 581 0030",
    "sg:postcode":"75701",
    "sg:province":"TX",
    "sg:tags":[
        "repairing",
        "automotive",
        "radiator",
        "automobile"
    ],
    "wof:name":"B & B Radiator & Condenser",
    "wof:placetype":"venue"
},
  "geometry": {"coordinates":[-95.330485,32.307017],"type":"Point"}
}