{
  "type": "Feature",
  "properties": {
    "iso:country":"US",
    "sg:address":"7432 Gateway Blvd E",
    "sg:city":"El Paso",
    "sg:classifiers":[
        {
            "category":"Personal",
            "subcategory":"Beauty Salon",
            "type":"Services"
        }
    ],
    "sg:phone":"+1 915 593 6161",
    "sg:postcode":"79915",
    "sg:province":"TX",
    "sg:tags":[
        "shop"
    ],
    "wof:name":"Keen Cuts",
    "wof:placetype":"venue"
},
  "geometry": {"coordinates":[-106.36613,31.765028],"type":"Point"}
}