{
  "type": "Feature",
  "properties": {
    "iso:country":"US",
    "sg:address":"4523 Stonebridge Dr",
    "sg:city":"Pearland",
    "sg:classifiers":[
        {
            "category":"Professional",
            "type":"Services"
        }
    ],
    "sg:phone":"+1 281 489 2220",
    "sg:postcode":"77584",
    "sg:province":"TX",
    "wof:name":"Scoopgrades",
    "wof:placetype":"venue"
},
  "geometry": {"coordinates":[-95.289469,29.542914],"type":"Point"}
}