{
  "type": "Feature",
  "properties": {
    "iso:country":"US",
    "sg:address":"4125 McCullough Ave",
    "sg:city":"San Antonio",
    "sg:classifiers":[
        {
            "category":"Health Services",
            "subcategory":"Doctor",
            "type":"Services"
        }
    ],
    "sg:phone":"+1 210 826 3372",
    "sg:postcode":"78212",
    "sg:province":"TX",
    "sg:tags":[
        "physician",
        "surgeon"
    ],
    "wof:name":"Anne Farrell MD",
    "wof:placetype":"venue"
},
  "geometry": {"coordinates":[-98.49181900000001,29.468676],"type":"Point"}
}