{
  "type": "Feature",
  "properties": {
    "iso:country":"US",
    "sg:address":"104 S Houston Ave",
    "sg:city":"Cameron",
    "sg:classifiers":[
        {
            "category":"Personal",
            "subcategory":"Barber",
            "type":"Services"
        }
    ],
    "sg:phone":"+1 254 697 3922",
    "sg:postcode":"76520",
    "sg:province":"TX",
    "wof:name":"Cameron Barber Shop & Salon",
    "wof:placetype":"venue"
},
  "geometry": {"coordinates":[-96.977373,30.850781],"type":"Point"}
}