{
  "type": "Feature",
  "properties": {
    "iso:country":"US",
    "sg:address":"8300 S I- 35",
    "sg:city":"Austin",
    "sg:classifiers":[
        {
            "category":"Local Transit",
            "type":"Transportation"
        }
    ],
    "sg:phone":"+1 512 282 5770",
    "sg:postcode":"78744",
    "sg:province":"TX",
    "sg:tags":[
        "bus",
        "charter"
    ],
    "wof:name":"National Express Corporation",
    "wof:placetype":"venue"
},
  "geometry": {"coordinates":[-97.77931700000001,30.176523],"type":"Point"}
}