{
  "type": "Feature",
  "properties": {
    "iso:country":"US",
    "sg:address":"205 E Mills Ave",
    "sg:city":"El Paso",
    "sg:classifiers":[
        {
            "category":"Banks & Credit Unions",
            "subcategory":"Bank",
            "type":"Services"
        }
    ],
    "sg:phone":"+1 915 532 1404",
    "sg:postcode":"79901",
    "sg:province":"TX",
    "sg:tags":[
        "small",
        "lender",
        "loan"
    ],
    "wof:name":"World Acceptance",
    "wof:placetype":"venue"
},
  "geometry": {"coordinates":[-106.48703500000001,31.76015],"type":"Point"}
}