{
  "type": "Feature",
  "properties": {
    "iso:country":"US",
    "sg:address":"5012 Jacksboro Hwy",
    "sg:city":"Fort Worth",
    "sg:classifiers":[
        {
            "category":"Autos & Motor Vehicles",
            "subcategory":"Automobile Sales",
            "type":"Retail Goods"
        }
    ],
    "sg:phone":"+1 817 624 0871",
    "sg:postcode":"76114",
    "sg:province":"TX",
    "sg:tags":[
        "used"
    ],
    "wof:name":"Richards Auto Sales Inc",
    "wof:placetype":"venue"
},
  "geometry": {"coordinates":[-97.398203,32.79602],"type":"Point"}
}