{
  "type": "Feature",
  "properties": {
    "iso:country":"US",
    "sg:address":"2706 Henderson Ave",
    "sg:city":"Odessa",
    "sg:classifiers":[
        {
            "category":"Professional",
            "subcategory":"Management & Consulting",
            "type":"Services"
        }
    ],
    "sg:phone":"+1 432 580 0910",
    "sg:postcode":"79764",
    "sg:province":"TX",
    "sg:tags":[
        "report",
        "construction"
    ],
    "wof:name":"Permian Basin Construction",
    "wof:placetype":"venue"
},
  "geometry": {"coordinates":[-102.38495399999999,31.868306],"type":"Point"}
}