{
  "type": "Feature",
  "properties": {
    "iso:country":"US",
    "sg:address":"1122 Colorado St",
    "sg:city":"Austin",
    "sg:classifiers":[
        {
            "category":"Restaurant",
            "type":"Food & Drink"
        }
    ],
    "sg:phone":"+1 512 320 7330",
    "sg:postcode":"78701",
    "sg:province":"TX",
    "sg:tags":[
        "eating"
    ],
    "wof:name":"McDonalds",
    "wof:placetype":"venue"
},
  "geometry": {"coordinates":[-97.742636,30.274136],"type":"Point"}
}