{
  "type": "Feature",
  "properties": {
    "iso:country":"US",
    "sg:address":"1110 W Wintergreen Rd",
    "sg:city":"Lancaster",
    "sg:classifiers":[
        {
            "category":"Real Estate",
            "subcategory":"Real Estate Operator",
            "type":"Services"
        }
    ],
    "sg:phone":"+1 972 224 3548",
    "sg:postcode":"75134",
    "sg:province":"TX",
    "sg:tags":[
        "building",
        "apartment"
    ],
    "wof:name":"Windsong Place Apts",
    "wof:placetype":"venue"
},
  "geometry": {"coordinates":[-96.785448,32.620501],"type":"Point"}
}