{
  "type": "Feature",
  "properties": {
    "iso:country":"US",
    "sg:address":"2102 Daniel Boone Dr",
    "sg:city":"San Antonio",
    "sg:classifiers":[
        {
            "category":"Shopping",
            "subcategory":"Used Merchandise",
            "type":"Retail Goods"
        }
    ],
    "sg:phone":"+1 210 680 3820",
    "sg:postcode":"78238",
    "sg:province":"TX",
    "wof:name":"Gonzalez Resale",
    "wof:placetype":"venue"
},
  "geometry": {"coordinates":[-98.60543800000001,29.457751],"type":"Point"}
}