{
  "type": "Feature",
  "properties": {
    "iso:country":"US",
    "sg:address":"215 Lake Shore Dr",
    "sg:city":"Seabrook",
    "sg:classifiers":[
        {
            "category":"Professional",
            "subcategory":"Business Services",
            "type":"Services"
        }
    ],
    "sg:phone":"+1 281 326 3299",
    "sg:postcode":"77586",
    "sg:province":"TX",
    "sg:tags":[
        "bus"
    ],
    "wof:name":"Inspectra Home Inspection Svc",
    "wof:placetype":"venue"
},
  "geometry": {"coordinates":[-95.05045800000001,29.569538],"type":"Point"}
}