{
  "type": "Feature",
  "properties": {
    "iso:country":"US",
    "sg:address":"3703 W Poplar St",
    "sg:city":"San Antonio",
    "sg:classifiers":[
        {
            "category":"Building & Trades",
            "subcategory":"Construction",
            "type":"Services"
        }
    ],
    "sg:phone":"+1 210 434 4524",
    "sg:postcode":"78228",
    "sg:province":"TX",
    "sg:tags":[
        "paving",
        "contractor"
    ],
    "wof:name":"Perez Paving",
    "wof:placetype":"venue"
},
  "geometry": {"coordinates":[-98.551149,29.443145],"type":"Point"}
}