{
  "type": "Feature",
  "properties": {
    "iso:country":"US",
    "sg:address":"13233 N Stemmons Fwy",
    "sg:city":"Dallas",
    "sg:classifiers":[
        {
            "category":"Restaurant",
            "type":"Food & Drink"
        }
    ],
    "sg:phone":"+1 972 484 8292",
    "sg:postcode":"75234",
    "sg:province":"TX",
    "wof:name":"Michael's Restaurant",
    "wof:placetype":"venue"
},
  "geometry": {"coordinates":[-96.90149700000001,32.922501],"type":"Point"}
}