{
  "type": "Feature",
  "properties": {
    "iso:country":"US",
    "sg:address":"2400 US Hwy 77X Bus",
    "sg:city":"San Benito",
    "sg:classifiers":[
        {
            "category":"Wholesale",
            "subcategory":"Vending Machines",
            "type":"Manufacturing & Wholesale Goods"
        }
    ],
    "sg:phone":"+1 956 361 1729",
    "sg:postcode":"78586",
    "sg:province":"TX",
    "wof:name":"Sugarloaf Of San Antonio",
    "wof:placetype":"venue"
},
  "geometry": {"coordinates":[-97.662215,26.16417],"type":"Point"}
}