{
  "type": "Feature",
  "properties": {
    "iso:country":"US",
    "sg:address":"101 Tascosa Rd",
    "sg:city":"Amarillo",
    "sg:classifiers":[
        {
            "category":"Restaurant",
            "type":"Food & Drink"
        }
    ],
    "sg:menulink":"http://www.allmenus.com/tx/amarillo/203663-sonic/menu/",
    "sg:phone":"+1 806 353 3637",
    "sg:postcode":"79124",
    "sg:province":"TX",
    "sg:tags":[
        "burger",
        "american"
    ],
    "wof:name":"Sonic",
    "wof:placetype":"venue"
},
  "geometry": {"coordinates":[-101.902562,35.213322],"type":"Point"}
}