{
  "type": "Feature",
  "properties": {
    "iso:country":"US",
    "sg:address":"2437 SE 14th St",
    "sg:city":"Grand Prairie",
    "sg:classifiers":[
        {
            "category":"Professional",
            "type":"Services"
        }
    ],
    "sg:phone":"+1 972 642 6354",
    "sg:postcode":"75051",
    "sg:province":"TX",
    "wof:name":"McK",
    "wof:placetype":"venue"
},
  "geometry": {"coordinates":[-96.98568899999999,32.70886],"type":"Point"}
}