{
  "type": "Feature",
  "properties": {
    "iso:country":"US",
    "sg:address":"215 N Main St",
    "sg:city":"Weatherford",
    "sg:classifiers":[
        {
            "category":"Professional",
            "subcategory":"Lawyer & Legal Services",
            "type":"Services"
        }
    ],
    "sg:phone":"+1 817 338 4854",
    "sg:postcode":"76086",
    "sg:province":"TX",
    "wof:name":"Susan Paquet Atty",
    "wof:placetype":"venue"
},
  "geometry": {"coordinates":[-97.79733899999999,32.761368],"type":"Point"}
}