{
  "type": "Feature",
  "properties": {
    "iso:country":"US",
    "sg:address":"100 Concho St",
    "sg:city":"San Marcos",
    "sg:classifiers":[
        {
            "category":"Organizations",
            "subcategory":"Religious Organization",
            "type":"Services"
        }
    ],
    "sg:phone":"+1 512 392 5925",
    "sg:postcode":"78666",
    "sg:province":"TX",
    "wof:name":"Catholic Student Center",
    "wof:placetype":"venue"
},
  "geometry": {"coordinates":[-97.94199399999999,29.886367],"type":"Point"}
}