{
  "type": "Feature",
  "properties": {
    "iso:country":"US",
    "sg:address":"14855 F A A Blvd",
    "sg:city":"Fort Worth",
    "sg:classifiers":[
        {
            "category":"Wholesale",
            "subcategory":"Machinery & Supplies",
            "type":"Manufacturing & Wholesale Goods"
        }
    ],
    "sg:phone":"+1 817 571 0900",
    "sg:postcode":"76155",
    "sg:province":"TX",
    "wof:name":"Kuboto Credit & Tractor",
    "wof:placetype":"venue"
},
  "geometry": {"coordinates":[-97.044521,32.833487],"type":"Point"}
}