{
  "type": "Feature",
  "properties": {
    "iso:country":"US",
    "sg:address":"4200 Marathon Boulevard Suite 310",
    "sg:city":"Austin",
    "sg:classifiers":[
        {
            "category":"Health Services",
            "subcategory":"Doctor",
            "type":"Services"
        }
    ],
    "sg:phone":"+1 512 420 9900",
    "sg:postcode":"78756",
    "sg:province":"TX",
    "sg:website":"www.sleepdoc.net",
    "wof:name":"Sleep Medicine Consultants",
    "wof:placetype":"venue"
},
  "geometry": {"coordinates":[-97.74108,30.310497],"type":"Point"}
}