{
  "type": "Feature",
  "properties": {
    "iso:country":"US",
    "sg:address":"158 Cascade Ct",
    "sg:city":"Center",
    "sg:classifiers":[
        {
            "category":"Government",
            "subcategory":"Office",
            "type":"Public Place"
        }
    ],
    "sg:phone":"+1 936 598 5557",
    "sg:postcode":"75901",
    "sg:province":"TX",
    "sg:tags":[
        "farm",
        "agency"
    ],
    "wof:name":"Farm Service Agency",
    "wof:placetype":"venue"
},
  "geometry": {"coordinates":[-94.727898,31.280127],"type":"Point"}
}