{
  "type": "Feature",
  "properties": {
    "iso:country":"US",
    "sg:address":"8406 Americas Cup",
    "sg:city":"Rowlett",
    "sg:classifiers":[
        {
            "category":"Manufacturing",
            "subcategory":"Electronics",
            "type":"Manufacturing & Wholesale Goods"
        }
    ],
    "sg:phone":"+1 469 246 2062",
    "sg:postcode":"75089",
    "sg:province":"TX",
    "sg:tags":[
        "lasers-manufacturers"
    ],
    "wof:name":"North Texas Laser",
    "wof:placetype":"venue"
},
  "geometry": {"coordinates":[-96.51747400000001,32.933899],"type":"Point"}
}