{
  "type": "Feature",
  "properties": {
    "iso:country":"US",
    "sg:address":"21502 Long Castle Dr",
    "sg:city":"Spring",
    "sg:classifiers":[
        {
            "category":"Recreation",
            "type":"Entertainment"
        }
    ],
    "sg:phone":"+1 281 353 6433",
    "sg:postcode":"77388",
    "sg:province":"TX",
    "wof:name":"New Life Services",
    "wof:placetype":"venue"
},
  "geometry": {"coordinates":[-95.460228,30.077939],"type":"Point"}
}