{
  "type": "Feature",
  "properties": {
    "iso:country":"US",
    "sg:address":"108 Delwood Dr",
    "sg:city":"Longview",
    "sg:classifiers":[
        {
            "category":"Retail",
            "subcategory":"Laundry & Dry Cleaning",
            "type":"Services"
        }
    ],
    "sg:phone":"+1 903 758 7750",
    "sg:postcode":"75605",
    "sg:province":"TX",
    "sg:tags":[
        "shop",
        "drycleaning",
        "plant",
        "barber"
    ],
    "wof:name":"Alpine Cleaners & Laundry",
    "wof:placetype":"venue"
},
  "geometry": {"coordinates":[-94.740909,32.527092],"type":"Point"}
}