{
  "type": "Feature",
  "properties": {
    "iso:country":"US",
    "sg:address":"223 E FM 1382",
    "sg:city":"Cedar Hill",
    "sg:classifiers":[
        {
            "category":"Shopping",
            "subcategory":"Gifts & Souvenirs",
            "type":"Retail Goods"
        }
    ],
    "sg:phone":"+1 972 299 5465",
    "sg:postcode":"75104",
    "sg:province":"TX",
    "wof:name":"Natashas Gifts",
    "wof:placetype":"venue"
},
  "geometry": {"coordinates":[-96.940681,32.596763],"type":"Point"}
}