{
  "type": "Feature",
  "properties": {
    "iso:country":"US",
    "sg:address":"2824 Balch Springs Rd",
    "sg:city":"Balch Springs",
    "sg:classifiers":[
        {
            "category":"Wholesale",
            "subcategory":"Vending Machines",
            "type":"Manufacturing & Wholesale Goods"
        }
    ],
    "sg:phone":"+1 972 286 6733",
    "sg:postcode":"75180",
    "sg:province":"TX",
    "wof:name":"M Ruth Thornell Vending",
    "wof:placetype":"venue"
},
  "geometry": {"coordinates":[-96.610648,32.728327],"type":"Point"}
}