{
  "type": "Feature",
  "properties": {
    "iso:country":"US",
    "sg:address":"15001 Cavalier Canyon Dr",
    "sg:city":"Austin",
    "sg:classifiers":[
        {
            "category":"Personal",
            "type":"Services"
        }
    ],
    "sg:phone":"+1 512 266 7600",
    "sg:postcode":"78734",
    "sg:province":"TX",
    "wof:name":"Feng Shui Places",
    "wof:placetype":"venue"
},
  "geometry": {"coordinates":[-97.94470099999999,30.367289],"type":"Point"}
}