{
  "type": "Feature",
  "properties": {
    "iso:country":"US",
    "sg:address":"7710 Lynn Ann St",
    "sg:city":"San Antonio",
    "sg:classifiers":[
        {
            "category":"Shopping",
            "subcategory":"Gifts & Souvenirs",
            "type":"Retail Goods"
        }
    ],
    "sg:phone":"+1 210 684 7825",
    "sg:postcode":"78240",
    "sg:province":"TX",
    "wof:name":"Perfect Gift of San Antonio",
    "wof:placetype":"venue"
},
  "geometry": {"coordinates":[-98.639965,29.53049],"type":"Point"}
}