{
  "type": "Feature",
  "properties": {
    "iso:country":"US",
    "sg:address":"1311 W Mount Houston Rd",
    "sg:city":"Houston",
    "sg:classifiers":[
        {
            "category":"Retail",
            "subcategory":"Auto Repair",
            "type":"Services"
        }
    ],
    "sg:phone":"+1 281 931 3055",
    "sg:postcode":"77038",
    "sg:province":"TX",
    "sg:tags":[
        "automobile",
        "inspection"
    ],
    "wof:name":"Maico Muffler Shop",
    "wof:placetype":"venue"
},
  "geometry": {"coordinates":[-95.42872699999999,29.89794],"type":"Point"}
}