{
  "type": "Feature",
  "properties": {
    "iso:country":"US",
    "sg:address":"4718 Leopard St",
    "sg:city":"Corpus Christi",
    "sg:classifiers":[
        {
            "category":"Restaurant",
            "type":"Food & Drink"
        }
    ],
    "sg:phone":"+1 361 881 9181",
    "sg:postcode":"78408",
    "sg:province":"TX",
    "sg:tags":[
        "eating"
    ],
    "wof:name":"Las Torres Cafe",
    "wof:placetype":"venue"
},
  "geometry": {"coordinates":[-97.446962,27.797257],"type":"Point"}
}