{
  "type": "Feature",
  "properties": {
    "iso:country":"US",
    "sg:address":"2638 S 14th St",
    "sg:city":"Abilene",
    "sg:classifiers":[
        {
            "category":"Personal",
            "type":"Services"
        }
    ],
    "sg:phone":"+1 325 691 0715",
    "sg:postcode":"79605",
    "sg:province":"TX",
    "wof:name":"Happy Dragon Tattooing",
    "wof:placetype":"venue"
},
  "geometry": {"coordinates":[-99.754469,32.432256],"type":"Point"}
}