{
  "type": "Feature",
  "properties": {
    "iso:country":"US",
    "sg:address":"4015 Cresthill Rd",
    "sg:city":"Dallas",
    "sg:classifiers":[
        {
            "category":"Manufacturing",
            "subcategory":"Toys & Sporting Goods",
            "type":"Manufacturing & Wholesale Goods"
        }
    ],
    "sg:phone":"+1 214 381 6349",
    "sg:postcode":"75227",
    "sg:province":"TX",
    "sg:tags":[
        "mfg"
    ],
    "wof:name":"American Sports Products",
    "wof:placetype":"venue"
},
  "geometry": {"coordinates":[-96.721211,32.782507],"type":"Point"}
}