{
  "type": "Feature",
  "properties": {
    "iso:country":"US",
    "sg:address":"990 Basse Rd E",
    "sg:city":"San Antonio",
    "sg:classifiers":[
        {
            "category":"Health Services",
            "subcategory":"Doctor",
            "type":"Services"
        }
    ],
    "sg:phone":"+1 210 822 8381",
    "sg:postcode":"78209",
    "sg:province":"TX",
    "sg:tags":[
        "dentist"
    ],
    "wof:name":"Alamo Heights Pediatric",
    "wof:placetype":"venue"
},
  "geometry": {"coordinates":[-98.469639,29.496723],"type":"Point"}
}