{
  "type": "Feature",
  "properties": {
    "iso:country":"US",
    "sg:address":"5250 Paredes Line Rd",
    "sg:city":"Brownsville",
    "sg:classifiers":[
        {
            "category":"Restaurant",
            "type":"Food & Drink"
        }
    ],
    "sg:phone":"+1 956 546 7417",
    "sg:postcode":"78526",
    "sg:province":"TX",
    "sg:tags":[
        "style",
        "mexican",
        "family"
    ],
    "wof:name":"Jr's Restaurant",
    "wof:placetype":"venue"
},
  "geometry": {"coordinates":[-97.484376,25.980376],"type":"Point"}
}