{
  "type": "Feature",
  "properties": {
    "iso:country":"US",
    "sg:address":"121 E Woodlawn Ave",
    "sg:city":"San Antonio",
    "sg:classifiers":[
        {
            "category":"Professional",
            "subcategory":"Credit Reporting & Collection",
            "type":"Services"
        }
    ],
    "sg:phone":"+1 210 735 4070",
    "sg:postcode":"78212",
    "sg:province":"TX",
    "sg:tags":[
        "agency"
    ],
    "wof:name":"Aleman & Aleman Enterprises",
    "wof:placetype":"venue"
},
  "geometry": {"coordinates":[-98.492189,29.45302],"type":"Point"}
}