{
  "type": "Feature",
  "properties": {
    "iso:country":"US",
    "sg:address":"4603 Nevada Path",
    "sg:city":"Austin",
    "sg:classifiers":[
        {
            "category":"Home & Garden",
            "subcategory":"Home Furnishings",
            "type":"Retail Goods"
        }
    ],
    "sg:phone":"+1 512 440 9000",
    "sg:postcode":"78745",
    "sg:province":"TX",
    "sg:tags":[
        "window",
        "covering"
    ],
    "wof:name":"WCI Window Covering",
    "wof:placetype":"venue"
},
  "geometry": {"coordinates":[-97.79386100000001,30.227241],"type":"Point"}
}