{
  "type": "Feature",
  "properties": {
    "iso:country":"US",
    "sg:address":"3900 Spring Valley Rd",
    "sg:city":"Addison",
    "sg:classifiers":[
        {
            "category":"Education",
            "subcategory":"School",
            "type":"Public Place"
        }
    ],
    "sg:phone":"+1 214 888 3191",
    "sg:postcode":"75001",
    "sg:province":"TX",
    "wof:name":"Dallas Independent School District",
    "wof:placetype":"venue"
},
  "geometry": {"coordinates":[-96.847516,32.939732],"type":"Point"}
}