{
  "type": "Feature",
  "properties": {
    "iso:country":"US",
    "sg:address":"710 W 5th St",
    "sg:city":"Plainview",
    "sg:classifiers":[
        {
            "category":"Organizations",
            "subcategory":"Professional Association",
            "type":"Services"
        }
    ],
    "sg:phone":"+1 806 296 7431",
    "sg:postcode":"79072",
    "sg:province":"TX",
    "sg:tags":[
        "business"
    ],
    "wof:name":"Plainview Chamber Of Commerce",
    "wof:placetype":"venue"
},
  "geometry": {"coordinates":[-101.710571,34.184503],"type":"Point"}
}