{
  "type": "Feature",
  "properties": {
    "iso:country":"US",
    "sg:address":"3402 Matador Dr",
    "sg:city":"Garland",
    "sg:classifiers":[
        {
            "category":"Manufacturing",
            "subcategory":"Jewelry",
            "type":"Manufacturing & Wholesale Goods"
        }
    ],
    "sg:phone":"+1 214 794 5292",
    "sg:postcode":"75042",
    "sg:province":"TX",
    "sg:tags":[
        "stone",
        "jewels-imitation"
    ],
    "wof:name":"Orion Original Jewelry",
    "wof:placetype":"venue"
},
  "geometry": {"coordinates":[-96.681614,32.9226],"type":"Point"}
}