{
  "type": "Feature",
  "properties": {
    "iso:country":"US",
    "sg:address":"2421 Texas Blvd",
    "sg:city":"Texarkana",
    "sg:classifiers":[
        {
            "category":"Personal",
            "subcategory":"Beauty Salon",
            "type":"Services"
        }
    ],
    "sg:phone":"+1 903 794 7919",
    "sg:postcode":"75503",
    "sg:province":"TX",
    "wof:name":"Lynn's Kuts Tans & Wrap",
    "wof:placetype":"venue"
},
  "geometry": {"coordinates":[-94.053197,33.440658],"type":"Point"}
}