{
  "type": "Feature",
  "properties": {
    "iso:country":"US",
    "sg:address":"1618 Future Dr",
    "sg:city":"Austin",
    "sg:classifiers":[
        {
            "category":"Wholesale",
            "subcategory":"Machinery & Supplies",
            "type":"Manufacturing & Wholesale Goods"
        }
    ],
    "sg:phone":"+1 512 928 8700",
    "sg:postcode":"78754",
    "sg:province":"TX",
    "sg:tags":[
        "truck"
    ],
    "sg:website":"www.toyotalift.com",
    "wof:name":"Toyota Lift",
    "wof:placetype":"venue"
},
  "geometry": {"coordinates":[-97.673795,30.343318],"type":"Point"}
}