{
  "type": "Feature",
  "properties": {
    "iso:country":"US",
    "sg:address":"911 N Raynor St",
    "sg:city":"El Paso",
    "sg:classifiers":[
        {
            "category":"Utilities",
            "subcategory":"Water",
            "type":"Services"
        }
    ],
    "sg:phone":"+1 915 565 1441",
    "sg:postcode":"79903",
    "sg:province":"TX",
    "sg:tags":[
        "company",
        "sewage"
    ],
    "wof:name":"El Paso City Government",
    "wof:placetype":"venue"
},
  "geometry": {"coordinates":[-106.459986,31.783639],"type":"Point"}
}