{
  "type": "Feature",
  "properties": {
    "iso:country":"US",
    "sg:address":"529 Loma Vis",
    "sg:city":"Rockwall",
    "sg:classifiers":[
        {
            "category":"Restaurant",
            "type":"Food & Drink"
        }
    ],
    "sg:phone":"+1 972 771 4171",
    "sg:postcode":"75032",
    "sg:province":"TX",
    "wof:name":"Sub-City Inc",
    "wof:placetype":"venue"
},
  "geometry": {"coordinates":[-96.467637,32.853387],"type":"Point"}
}