{
  "type": "Feature",
  "properties": {
    "iso:country":"US",
    "sg:address":"1807 W Berry St",
    "sg:city":"Fort Worth",
    "sg:classifiers":[
        {
            "category":"Banks & Credit Unions",
            "subcategory":"Bank",
            "type":"Services"
        }
    ],
    "sg:phone":"+1 817 924 3800",
    "sg:postcode":"76110",
    "sg:province":"TX",
    "sg:tags":[
        "other",
        "plan",
        "card"
    ],
    "wof:name":"Indigo International",
    "wof:placetype":"venue"
},
  "geometry": {"coordinates":[-97.347005,32.705966],"type":"Point"}
}