{
  "type": "Feature",
  "properties": {
    "iso:country":"US",
    "sg:address":"221 S Main St",
    "sg:city":"Victoria",
    "sg:classifiers":[
        {
            "category":"Personal",
            "subcategory":"Beauty Salon",
            "type":"Services"
        }
    ],
    "sg:phone":"+1 361 572 0914",
    "sg:postcode":"77901",
    "sg:province":"TX",
    "wof:name":"Total Image Salon",
    "wof:placetype":"venue"
},
  "geometry": {"coordinates":[-97.006809,28.797609],"type":"Point"}
}