{
  "type": "Feature",
  "properties": {
    "iso:country":"US",
    "sg:address":"8400 N Mo Pac Expressway",
    "sg:city":"Austin",
    "sg:classifiers":[
        {
            "category":"Professional",
            "subcategory":"Accounting & Tax Preparation",
            "type":"Services"
        }
    ],
    "sg:phone":"+1 512 340 0500",
    "sg:postcode":"78759",
    "sg:province":"TX",
    "sg:tags":[
        "accountant"
    ],
    "wof:name":"Coyner Roger E CPA Pllc",
    "wof:placetype":"venue"
},
  "geometry": {"coordinates":[-97.741485,30.371833],"type":"Point"}
}