{
  "type": "Feature",
  "properties": {
    "iso:country":"US",
    "sg:address":"23214 Sorters Rd",
    "sg:city":"Porter",
    "sg:classifiers":[
        {
            "category":"Autos & Motor Vehicles",
            "subcategory":"Automobile Sales",
            "type":"Retail Goods"
        }
    ],
    "sg:phone":"+1 281 354 3733",
    "sg:postcode":"77365",
    "sg:province":"TX",
    "sg:tags":[
        "used"
    ],
    "wof:name":"Jack Nicholson Auto Sales",
    "wof:placetype":"venue"
},
  "geometry": {"coordinates":[-95.264837,30.111728],"type":"Point"}
}