{
  "type": "Feature",
  "properties": {
    "iso:country":"US",
    "sg:address":"1001 S Eastman Rd",
    "sg:city":"Longview",
    "sg:classifiers":[
        {
            "category":"Real Estate",
            "subcategory":"Real Estate Agent",
            "type":"Services"
        }
    ],
    "sg:phone":"+1 903 234 9111",
    "sg:postcode":"75602",
    "sg:province":"TX",
    "wof:name":"J M Property Management Inc",
    "wof:placetype":"venue"
},
  "geometry": {"coordinates":[-94.707477,32.474435],"type":"Point"}
}