{
  "type": "Feature",
  "properties": {
    "iso:country":"US",
    "sg:address":"2005 E Oltorf St",
    "sg:city":"Austin",
    "sg:classifiers":[
        {
            "category":"Restaurant",
            "type":"Food & Drink"
        }
    ],
    "sg:phone":"+1 512 825 0212",
    "sg:postcode":"78741",
    "sg:province":"TX",
    "sg:tags":[
        "eating"
    ],
    "wof:name":"El Super Taco",
    "wof:placetype":"venue"
},
  "geometry": {"coordinates":[-97.731616,30.229926],"type":"Point"}
}