{
  "type": "Feature",
  "properties": {
    "iso:country":"US",
    "sg:address":"204 N Main St",
    "sg:city":"Riesel",
    "sg:classifiers":[
        {
            "category":"Personal",
            "subcategory":"Beauty Salon",
            "type":"Services"
        }
    ],
    "sg:phone":"+1 254 896 2425",
    "sg:postcode":"76682",
    "sg:province":"TX",
    "wof:name":"Jackie's Hair Care & Tanning",
    "wof:placetype":"venue"
},
  "geometry": {"coordinates":[-96.92555299999999,31.476217],"type":"Point"}
}