{
  "type": "Feature",
  "properties": {
    "iso:country":"US",
    "sg:address":"5803 Cayuga Dr",
    "sg:city":"San Antonio",
    "sg:classifiers":[
        {
            "category":"Health Services",
            "subcategory":"Doctor",
            "type":"Services"
        }
    ],
    "sg:phone":"+1 210 432 6736",
    "sg:postcode":"78228",
    "sg:province":"TX",
    "sg:tags":[
        "medical",
        "imaging"
    ],
    "wof:name":"Rainbow Medical Imaging",
    "wof:placetype":"venue"
},
  "geometry": {"coordinates":[-98.600587,29.459852],"type":"Point"}
}