{
  "type": "Feature",
  "properties": {
    "iso:country":"US",
    "sg:address":"3607 W Park Row Dr",
    "sg:city":"Arlington",
    "sg:classifiers":[
        {
            "category":"Insurance",
            "subcategory":"Insurance Agent",
            "type":"Services"
        }
    ],
    "sg:phone":"+1 817 261 1603",
    "sg:postcode":"76013",
    "sg:province":"TX",
    "sg:website":"www.insuringtexas.com",
    "wof:name":"Allstate Insurance",
    "wof:placetype":"venue"
},
  "geometry": {"coordinates":[-97.168588,32.721125],"type":"Point"}
}