{
  "type": "Feature",
  "properties": {
    "iso:country":"US",
    "sg:address":"509 N Harvey Mitchell Pkwy",
    "sg:city":"Bryan",
    "sg:classifiers":[
        {
            "category":"Restaurant",
            "type":"Food & Drink"
        }
    ],
    "sg:phone":"+1 979 775 0994",
    "sg:postcode":"77807",
    "sg:province":"TX",
    "sg:tags":[
        "eating"
    ],
    "wof:name":"Popeyes Chicken & Biscuits",
    "wof:placetype":"venue"
},
  "geometry": {"coordinates":[-96.37797399999999,30.633136],"type":"Point"}
}