{
  "type": "Feature",
  "properties": {
    "iso:country":"US",
    "sg:address":"2446 Rogers Loop",
    "sg:city":"San Antonio",
    "sg:classifiers":[
        {
            "category":"Building & Trades",
            "subcategory":"Construction",
            "type":"Services"
        }
    ],
    "sg:phone":"+1 210 492 2565",
    "sg:postcode":"78258",
    "sg:province":"TX",
    "sg:tags":[
        "designer"
    ],
    "wof:name":"Med By Design",
    "wof:placetype":"venue"
},
  "geometry": {"coordinates":[-98.53414600000001,29.611711],"type":"Point"}
}