{
  "type": "Feature",
  "properties": {
    "iso:country":"US",
    "sg:address":"2800 Stadium Dr",
    "sg:city":"Fort Worth",
    "sg:classifiers":[
        {
            "category":"Recreation",
            "type":"Entertainment"
        }
    ],
    "sg:phone":"+1 817 257 7529",
    "sg:postcode":"76109",
    "sg:province":"TX",
    "wof:name":"Tcu Recreational Sports",
    "wof:placetype":"venue"
},
  "geometry": {"coordinates":[-97.365432,32.711675],"type":"Point"}
}