{
  "type": "Feature",
  "properties": {
    "iso:country":"US",
    "sg:address":"3615 Waco St",
    "sg:city":"Texarkana",
    "sg:classifiers":[
        {
            "category":"Building & Trades",
            "subcategory":"Construction",
            "type":"Services"
        }
    ],
    "sg:phone":"+1 903 838 6851",
    "sg:postcode":"75501",
    "sg:province":"TX",
    "sg:tags":[
        "product",
        "asphalt"
    ],
    "wof:name":"Gibson Asphalt Construction",
    "wof:placetype":"venue"
},
  "geometry": {"coordinates":[-94.086527,33.41645],"type":"Point"}
}