{
  "type": "Feature",
  "properties": {
    "iso:country":"US",
    "sg:address":"402 University Dr E",
    "sg:city":"College Station",
    "sg:classifiers":[
        {
            "category":"Autos & Motor Vehicles",
            "subcategory":"Auto Supplies",
            "type":"Retail Goods"
        }
    ],
    "sg:phone":"+1 979 696 1721",
    "sg:postcode":"77840",
    "sg:province":"TX",
    "wof:name":"Carquest Auto Parts",
    "wof:placetype":"venue"
},
  "geometry": {"coordinates":[-96.331676,30.630629],"type":"Point"}
}