{
  "type": "Feature",
  "properties": {
    "iso:country":"US",
    "sg:address":"19606 Norfolk Dr",
    "sg:city":"Flint",
    "sg:classifiers":[
        {
            "category":"Government",
            "subcategory":"Fire Station",
            "type":"Public Place"
        }
    ],
    "sg:phone":"+1 903 894 6782",
    "sg:postcode":"75762",
    "sg:province":"TX",
    "sg:tags":[
        "relief",
        "disaster",
        "recovery"
    ],
    "wof:name":"B & V Carpet Service",
    "wof:placetype":"venue"
},
  "geometry": {"coordinates":[-95.337289,32.194479],"type":"Point"}
}