{
  "type": "Feature",
  "properties": {
    "iso:country":"US",
    "sg:address":"2002 E Central Texas Expy Ste. D",
    "sg:city":"Killeen",
    "sg:classifiers":[
        {
            "category":"Autos & Motor Vehicles",
            "subcategory":"Auto Supplies",
            "type":"Retail Goods"
        },
        {
            "category":"Retail",
            "subcategory":"Auto Repair",
            "type":"Services"
        }
    ],
    "sg:phone":"+1 254 526 6628",
    "sg:postcode":"76541",
    "sg:province":"TX",
    "sg:tags":[
        "repairing",
        "automotive",
        "part",
        "brake",
        "automobile",
        "tune",
        "service-equipment"
    ],
    "sg:website":"http://www.justbrakes.com",
    "wof:name":"Just Brakes - Brake Services",
    "wof:placetype":"venue"
},
  "geometry": {"coordinates":[-97.72213000000001,31.091206],"type":"Point"}
}