{
  "type": "Feature",
  "properties": {
    "iso:country":"US",
    "sg:address":"1613 High Crest Ct",
    "sg:city":"Irving",
    "sg:classifiers":[
        {
            "category":"Professional",
            "subcategory":"Accounting & Tax Preparation",
            "type":"Services"
        }
    ],
    "sg:phone":"+1 972 513 2244",
    "sg:postcode":"75061",
    "sg:province":"TX",
    "sg:tags":[
        "bookkeeping",
        "general"
    ],
    "wof:name":"Phyl's Bookkeeping",
    "wof:placetype":"venue"
},
  "geometry": {"coordinates":[-97.005906,32.830224],"type":"Point"}
}