{
  "type": "Feature",
  "properties": {
    "iso:country":"US",
    "sg:address":"2613 Wolflin Ave",
    "sg:city":"Amarillo",
    "sg:classifiers":[
        {
            "category":"Home & Garden",
            "subcategory":"Home Furnishings",
            "type":"Retail Goods"
        }
    ],
    "sg:phone":"+1 806 352 7848",
    "sg:postcode":"79109",
    "sg:province":"TX",
    "sg:tags":[
        "repair",
        "electrical"
    ],
    "wof:name":"House Of Shades & Lamp Repair",
    "wof:placetype":"venue"
},
  "geometry": {"coordinates":[-101.86427500000001,35.19274],"type":"Point"}
}