{
  "type": "Feature",
  "properties": {
    "iso:country":"US",
    "sg:address":"4706 Bryan Rd",
    "sg:city":"Odessa",
    "sg:classifiers":[
        {
            "category":"Building & Trades",
            "subcategory":"Construction",
            "type":"Services"
        }
    ],
    "sg:phone":"+1 432 550 5114",
    "sg:postcode":"79764",
    "sg:province":"TX",
    "sg:tags":[
        "home",
        "improvement"
    ],
    "wof:name":"Arrow Construction",
    "wof:placetype":"venue"
},
  "geometry": {"coordinates":[-102.413017,31.884377],"type":"Point"}
}