{
  "type": "Feature",
  "properties": {
    "iso:country":"US",
    "sg:address":"112 W Sinton St",
    "sg:city":"Sinton",
    "sg:classifiers":[
        {
            "category":"Personal",
            "subcategory":"Beauty Salon",
            "type":"Services"
        }
    ],
    "sg:phone":"+1 361 364 9231",
    "sg:postcode":"78387",
    "sg:province":"TX",
    "sg:tags":[
        "shop",
        "barber"
    ],
    "wof:name":"M G's Hair Designer",
    "wof:placetype":"venue"
},
  "geometry": {"coordinates":[-97.511522,28.036767],"type":"Point"}
}