{
  "type": "Feature",
  "properties": {
    "iso:country":"US",
    "sg:address":"5919 Saxon Dr",
    "sg:city":"Houston",
    "sg:classifiers":[
        {
            "category":"Retail",
            "subcategory":"Repair Shop",
            "type":"Services"
        }
    ],
    "sg:phone":"+1 713 680 3834",
    "sg:postcode":"77092",
    "sg:province":"TX",
    "sg:tags":[
        "equipment",
        "transportation"
    ],
    "wof:name":"Schulin Eqp & Accessory Co",
    "wof:placetype":"venue"
},
  "geometry": {"coordinates":[-95.477498,29.825714],"type":"Point"}
}