{
  "type": "Feature",
  "properties": {
    "iso:country":"US",
    "sg:address":"10022 Cedardale Dr",
    "sg:city":"Houston",
    "sg:classifiers":[
        {
            "category":"Shopping",
            "subcategory":"Beauty & Cosmetics",
            "type":"Retail Goods"
        }
    ],
    "sg:phone":"+1 713 827 1479",
    "sg:postcode":"77055",
    "sg:province":"TX",
    "sg:tags":[
        "merchandise"
    ],
    "wof:name":"Kay Nail Cosmetics",
    "wof:placetype":"venue"
},
  "geometry": {"coordinates":[-95.540813,29.790042],"type":"Point"}
}