{
  "type": "Feature",
  "properties": {
    "iso:country":"US",
    "sg:address":"12025 North Fwy",
    "sg:city":"Houston",
    "sg:classifiers":[
        {
            "category":"Professional",
            "subcategory":"Detective & Security Services",
            "type":"Services"
        }
    ],
    "sg:phone":"+1 832 232 5100",
    "sg:postcode":"77060",
    "sg:province":"TX",
    "sg:tags":[
        "car",
        "armored"
    ],
    "wof:name":"Loomis Fargo",
    "wof:placetype":"venue"
},
  "geometry": {"coordinates":[-95.413819,29.938602],"type":"Point"}
}