{
  "type": "Feature",
  "properties": {
    "iso:country":"US",
    "sg:address":"4107 Harvest Hill Rd",
    "sg:city":"Dallas",
    "sg:classifiers":[
        {
            "category":"Professional",
            "subcategory":"Business Services",
            "type":"Services"
        }
    ],
    "sg:phone":"+1 469 522 0405",
    "sg:postcode":"75244",
    "sg:province":"TX",
    "wof:name":"Hw Scott & Associates LLC",
    "wof:placetype":"venue"
},
  "geometry": {"coordinates":[-96.839175,32.921704],"type":"Point"}
}