{
  "type": "Feature",
  "properties": {
    "iso:country":"US",
    "sg:address":"5330 S Cooper St",
    "sg:city":"Arlington",
    "sg:classifiers":[
        {
            "category":"Food & Beverages",
            "subcategory":"Groceries & Convenience Stores",
            "type":"Retail Goods"
        }
    ],
    "sg:phone":"+1 817 472 9491",
    "sg:postcode":"76017",
    "sg:province":"TX",
    "wof:name":"Kroger",
    "wof:placetype":"venue"
},
  "geometry": {"coordinates":[-97.134429,32.661468],"type":"Point"}
}