{
  "type": "Feature",
  "properties": {
    "iso:country":"US",
    "sg:address":"412 E Pleasant Run Rd",
    "sg:city":"Desoto",
    "sg:classifiers":[
        {
            "category":"Health Services",
            "subcategory":"Doctor",
            "type":"Services"
        },
        {
            "category":"Health Services",
            "subcategory":"Clinic",
            "type":"Services"
        },
        {
            "category":"Health Services",
            "subcategory":"Dentist",
            "type":"Services"
        }
    ],
    "sg:phone":"+1 972 274 9300",
    "sg:postcode":"75115",
    "sg:province":"TX",
    "sg:tags":[
        "dentists-oral",
        "physician",
        "dentists-cosmetic",
        "maxillofacial",
        "dental",
        "surgeons",
        "dentistry",
        "surgery",
        "oral"
    ],
    "wof:name":"Lantern Dental Clinic",
    "wof:placetype":"venue"
},
  "geometry": {"coordinates":[-96.849628,32.604134],"type":"Point"}
}