{
  "type": "Feature",
  "properties": {
    "iso:country":"US",
    "sg:address":"3725 Fulton St",
    "sg:city":"Houston",
    "sg:classifiers":[
        {
            "category":"Recreation",
            "type":"Entertainment"
        }
    ],
    "sg:phone":"+1 713 692 6925",
    "sg:postcode":"77009",
    "sg:province":"TX",
    "sg:tags":[
        "hall",
        "auditorium"
    ],
    "wof:name":"Moody Community Ctr",
    "wof:placetype":"venue"
},
  "geometry": {"coordinates":[-95.36282300000001,29.793045],"type":"Point"}
}