{
  "type": "Feature",
  "properties": {
    "iso:country":"US",
    "sg:address":"10737 Kingspoint Rd",
    "sg:city":"Houston",
    "sg:classifiers":[
        {
            "category":"Cinema",
            "subcategory":"Movie Rental",
            "type":"Entertainment"
        }
    ],
    "sg:phone":"+1 713 944 8222",
    "sg:postcode":"77075",
    "sg:province":"TX",
    "sg:tags":[
        "leasing",
        "video",
        "disc",
        "tape"
    ],
    "wof:name":"Hoa Mai Videos",
    "wof:placetype":"venue"
},
  "geometry": {"coordinates":[-95.230113,29.61853],"type":"Point"}
}