{
  "type": "Feature",
  "properties": {
    "iso:country":"US",
    "sg:address":"8825 Fredericksburg Rd",
    "sg:city":"San Antonio",
    "sg:classifiers":[
        {
            "category":"Retail",
            "subcategory":"Auto Repair",
            "type":"Services"
        }
    ],
    "sg:phone":"+1 210 681 1100",
    "sg:postcode":"78240",
    "sg:province":"TX",
    "sg:tags":[
        "repairing",
        "automobile"
    ],
    "wof:name":"Leon Valley Automotive",
    "wof:placetype":"venue"
},
  "geometry": {"coordinates":[-98.57508,29.526048],"type":"Point"}
}