{
  "type": "Feature",
  "properties": {
    "iso:country":"US",
    "sg:address":"13750 N Eldridge Pkwy",
    "sg:city":"Cypress",
    "sg:classifiers":[
        {
            "category":"Restaurant",
            "type":"Food & Drink"
        }
    ],
    "sg:menulink":"http://www.allmenus.com/tx/northwest-harris/70449-pizza-hut/menu/",
    "sg:phone":"+1 281 257 6172",
    "sg:postcode":"77429",
    "sg:province":"TX",
    "sg:tags":[
        "american",
        "pizza"
    ],
    "wof:name":"Pizza Hut",
    "wof:placetype":"venue"
},
  "geometry": {"coordinates":[-95.610561,29.983322],"type":"Point"}
}