{
  "type": "Feature",
  "properties": {
    "iso:country":"US",
    "sg:address":"14501 Valentin Dr",
    "sg:city":"El Paso",
    "sg:classifiers":[
        {
            "category":"Building & Trades",
            "subcategory":"Landscaping Services",
            "type":"Services"
        }
    ],
    "sg:phone":"+1 915 852 3281",
    "sg:postcode":"79928",
    "sg:province":"TX",
    "sg:tags":[
        "lawn",
        "maintenance",
        "grounds"
    ],
    "wof:name":"Jesse's A-1 Landscaping Svc",
    "wof:placetype":"venue"
},
  "geometry": {"coordinates":[-106.18385600000001,31.666482],"type":"Point"}
}