{
  "type": "Feature",
  "properties": {
    "iso:country":"US",
    "sg:address":"1605 E 8th St",
    "sg:city":"Odessa",
    "sg:classifiers":[
        {
            "category":"Sports & Exercise",
            "subcategory":"Gym",
            "type":"Entertainment"
        }
    ],
    "sg:phone":"+1 432 582 0292",
    "sg:postcode":"79761",
    "sg:province":"TX",
    "sg:tags":[
        "club",
        "health",
        "studio",
        "gymnasium"
    ],
    "wof:name":"Curves For Women",
    "wof:placetype":"venue"
},
  "geometry": {"coordinates":[-102.351849,31.859785],"type":"Point"}
}