{
  "type": "Feature",
  "properties": {
    "iso:country":"US",
    "sg:address":"3052 N Belt Line Rd",
    "sg:city":"Sunnyvale",
    "sg:classifiers":[
        {
            "category":"Education",
            "subcategory":"School",
            "type":"Public Place"
        }
    ],
    "sg:phone":"+1 972 226 4941",
    "sg:postcode":"75182",
    "sg:province":"TX",
    "sg:website":"www.gracefellowship.net",
    "wof:name":"Grace Fellowship",
    "wof:placetype":"venue"
},
  "geometry": {"coordinates":[-96.595596,32.806702],"type":"Point"}
}