{
  "type": "Feature",
  "properties": {
    "iso:country":"US",
    "sg:address":"614 W 6th St",
    "sg:city":"Mc Gregor",
    "sg:classifiers":[
        {
            "category":"Organizations",
            "subcategory":"Religious Organization",
            "type":"Services"
        }
    ],
    "sg:phone":"+1 254 840 3422",
    "sg:postcode":"76657",
    "sg:province":"TX",
    "wof:name":"Church of Christ of McGregor",
    "wof:placetype":"venue"
},
  "geometry": {"coordinates":[-97.406719,31.435927],"type":"Point"}
}