{
  "type": "Feature",
  "properties": {
    "iso:country":"US",
    "sg:address":"3605 N Main St Ste 102",
    "sg:city":"Taylor",
    "sg:classifiers":[
        {
            "category":"Banks & Credit Unions",
            "subcategory":"Financial Services",
            "type":"Services"
        }
    ],
    "sg:phone":"+1 512 352 3351",
    "sg:postcode":"76574",
    "sg:province":"TX",
    "sg:tags":[
        "financing",
        "cashing",
        "money",
        "loan",
        "order",
        "payday",
        "check"
    ],
    "sg:website":"http://ad.doubleclick.net/clk;225053199;48888911;w?http://www.checkngo.com?source=yellowpages&cat=TLs&AfsCampaignId=642",
    "wof:name":"Check 'n Go",
    "wof:placetype":"venue"
},
  "geometry": {"coordinates":[-97.415434,30.598181],"type":"Point"}
}