{
  "type": "Feature",
  "properties": {
    "iso:country":"US",
    "sg:address":"10710 Scotland Well Dr",
    "sg:city":"Austin",
    "sg:classifiers":[
        {
            "category":"Building & Trades",
            "subcategory":"Construction",
            "type":"Services"
        }
    ],
    "sg:phone":"+1 512 335 0734",
    "sg:postcode":"78750",
    "sg:province":"TX",
    "sg:tags":[
        "carpentry",
        "contractor"
    ],
    "wof:name":"Charles H Crockett Jr",
    "wof:placetype":"venue"
},
  "geometry": {"coordinates":[-97.796004,30.429017],"type":"Point"}
}