{
  "type": "Feature",
  "properties": {
    "iso:country":"US",
    "sg:address":"998 Sidney Baker St S",
    "sg:city":"Kerrville",
    "sg:classifiers":[
        {
            "category":"Building & Trades",
            "subcategory":"Construction",
            "type":"Services"
        }
    ],
    "sg:phone":"+1 830 896 2000",
    "sg:postcode":"78028",
    "sg:province":"TX",
    "sg:tags":[
        "house"
    ],
    "wof:name":"Carroll Smith Homes",
    "wof:placetype":"venue"
},
  "geometry": {"coordinates":[-99.143924,30.034774],"type":"Point"}
}