{
  "type": "Feature",
  "properties": {
    "iso:country":"US",
    "sg:address":"2021 Goldsmith St",
    "sg:city":"Houston",
    "sg:classifiers":[
        {
            "category":"Professional",
            "subcategory":"Business Services",
            "type":"Services"
        }
    ],
    "sg:phone":"+1 713 520 0819",
    "sg:postcode":"77030",
    "sg:province":"TX",
    "wof:name":"Griffin Family Partnership",
    "wof:placetype":"venue"
},
  "geometry": {"coordinates":[-95.40707399999999,29.710171],"type":"Point"}
}