{
  "type": "Feature",
  "properties": {
    "iso:country":"US",
    "sg:address":"18218 Enchanted Rock Trl",
    "sg:city":"Humble",
    "sg:classifiers":[
        {
            "category":"Building & Trades",
            "subcategory":"Construction",
            "type":"Services"
        }
    ],
    "sg:phone":"+1 281 359 3208",
    "sg:postcode":"77346",
    "sg:province":"TX",
    "sg:tags":[
        "contractor"
    ],
    "wof:name":"Atex Roofing",
    "wof:placetype":"venue"
},
  "geometry": {"coordinates":[-95.185,29.984544],"type":"Point"}
}