{
  "type": "Feature",
  "properties": {
    "iso:country":"US",
    "sg:address":"9300 S I- 35",
    "sg:city":"Austin",
    "sg:classifiers":[
        {
            "category":"Building & Trades",
            "subcategory":"Construction",
            "type":"Services"
        }
    ],
    "sg:phone":"+1 512 282 9900",
    "sg:postcode":"78748",
    "sg:province":"TX",
    "sg:tags":[
        "tile",
        "dealer"
    ],
    "wof:name":"Image Tile & Carpet",
    "wof:placetype":"venue"
},
  "geometry": {"coordinates":[-97.789085,30.162181],"type":"Point"}
}