{
  "type": "Feature",
  "properties": {
    "iso:country":"US",
    "sg:address":"9809 Harwin Dr",
    "sg:city":"Houston",
    "sg:classifiers":[
        {
            "category":"Retail",
            "subcategory":"Repair Shop",
            "type":"Services"
        }
    ],
    "sg:phone":"+1 713 787 0797",
    "sg:postcode":"77036",
    "sg:province":"TX",
    "sg:tags":[
        "antique",
        "restoring"
    ],
    "wof:name":"Julio Antiques Reproducer",
    "wof:placetype":"venue"
},
  "geometry": {"coordinates":[-95.53659,29.717659],"type":"Point"}
}