{
  "type": "Feature",
  "properties": {
    "iso:country":"US",
    "sg:address":"9995 Monroe Dr",
    "sg:city":"Dallas",
    "sg:classifiers":[
        {
            "category":"Retail",
            "subcategory":"Portrait Studio",
            "type":"Services"
        }
    ],
    "sg:phone":"+1 214 350 1566",
    "sg:postcode":"75220",
    "sg:province":"TX",
    "sg:tags":[
        "photographer"
    ],
    "wof:name":"Production Studio",
    "wof:placetype":"venue"
},
  "geometry": {"coordinates":[-96.878338,32.879661],"type":"Point"}
}