{
  "type": "Feature",
  "properties": {
    "iso:country":"US",
    "sg:address":"2601 Preston Rd",
    "sg:city":"Frisco",
    "sg:classifiers":[
        {
            "category":"Health Services",
            "subcategory":"Optometrist",
            "type":"Services"
        },
        {
            "category":"Shopping",
            "subcategory":"Optical Goods",
            "type":"Retail Goods"
        }
    ],
    "sg:phone":"+1 972 731 8507",
    "sg:postcode":"75034",
    "sg:province":"TX",
    "sg:tags":[
        "eyeglass"
    ],
    "sg:website":"http://www.eyemasters.com",
    "wof:name":"EyeMasters",
    "wof:placetype":"venue"
},
  "geometry": {"coordinates":[-96.805817,33.100979],"type":"Point"}
}