{
  "type": "Feature",
  "properties": {
    "iso:country":"US",
    "sg:address":"1913 Justin Rd",
    "sg:city":"Flower Mound",
    "sg:classifiers":[
        {
            "category":"Restaurant",
            "type":"Food & Drink"
        }
    ],
    "sg:menulink":"http://www.allmenus.com/tx/lewisville/250216-empress-of-china/menu/",
    "sg:phone":"+1 972 691 1628",
    "sg:postcode":"75028",
    "sg:province":"TX",
    "sg:tags":[
        "asian",
        "chinese"
    ],
    "wof:name":"Empress Of China",
    "wof:placetype":"venue"
},
  "geometry": {"coordinates":[-97.055699,33.071323],"type":"Point"}
}