{
  "type": "Feature",
  "properties": {
    "iso:country":"US",
    "sg:address":"720 S Front St",
    "sg:city":"Bellville",
    "sg:classifiers":[
        {
            "category":"Food & Beverages",
            "subcategory":"Groceries & Convenience Stores",
            "type":"Retail Goods"
        }
    ],
    "sg:phone":"+1 409 790 6427",
    "sg:postcode":"77418",
    "sg:province":"TX",
    "sg:tags":[
        "grocer"
    ],
    "wof:name":"Brookshire Brothers 39",
    "wof:placetype":"venue"
},
  "geometry": {"coordinates":[-96.25176500000001,29.942464],"type":"Point"}
}