{
  "type": "Feature",
  "properties": {
    "iso:country":"US",
    "sg:address":"1911 N Chadbourne St",
    "sg:city":"San Angelo",
    "sg:classifiers":[
        {
            "category":"Building & Trades",
            "subcategory":"Construction",
            "type":"Services"
        }
    ],
    "sg:phone":"+1 325 655 4700",
    "sg:postcode":"76903",
    "sg:province":"TX",
    "sg:tags":[
        "carpentry",
        "contractor"
    ],
    "wof:name":"Dominguez Cabinets & Remodelin",
    "wof:placetype":"venue"
},
  "geometry": {"coordinates":[-100.44851199999999,31.480231],"type":"Point"}
}