{
  "type": "Feature",
  "properties": {
    "iso:country":"US",
    "sg:address":"2400 S Flores St",
    "sg:city":"San Antonio",
    "sg:classifiers":[
        {
            "category":"Retail",
            "subcategory":"Repair Shop",
            "type":"Services"
        }
    ],
    "sg:phone":"+1 210 226 3031",
    "sg:postcode":"78204",
    "sg:province":"TX",
    "sg:tags":[
        "upholsterer"
    ],
    "wof:name":"Sanitary Mattress & Upholstery",
    "wof:placetype":"venue"
},
  "geometry": {"coordinates":[-98.504471,29.399817],"type":"Point"}
}