{
  "type": "Feature",
  "properties": {
    "iso:country":"US",
    "sg:address":"1100 Lincoln Ave",
    "sg:city":"Robstown",
    "sg:classifiers":[
        {
            "category":"Real Estate",
            "subcategory":"Real Estate Agent",
            "type":"Services"
        }
    ],
    "sg:phone":"+1 361 387 3144",
    "sg:postcode":"78380",
    "sg:province":"TX",
    "wof:name":"Ruegg Realty",
    "wof:placetype":"venue"
},
  "geometry": {"coordinates":[-97.668414,27.776016],"type":"Point"}
}