{
  "type": "Feature",
  "properties": {
    "iso:country":"US",
    "sg:address":"707 Commerce St",
    "sg:city":"Euless",
    "sg:classifiers":[
        {
            "category":"Building & Trades",
            "subcategory":"Construction",
            "type":"Services"
        }
    ],
    "sg:phone":"+1 817 858 6788",
    "sg:postcode":"76040",
    "sg:province":"TX",
    "sg:tags":[
        "carpentry",
        "contractor"
    ],
    "wof:name":"Rafter Rats Inc",
    "wof:placetype":"venue"
},
  "geometry": {"coordinates":[-97.108958,32.827187],"type":"Point"}
}