{
  "type": "Feature",
  "properties": {
    "iso:country":"US",
    "sg:address":"4035 32nd St",
    "sg:city":"Port Arthur",
    "sg:classifiers":[
        {
            "category":"Building & Trades",
            "subcategory":"Plumbing",
            "type":"Services"
        }
    ],
    "sg:phone":"+1 409 982 6728",
    "sg:postcode":"77642",
    "sg:province":"TX",
    "sg:tags":[
        "electrical",
        "contractor"
    ],
    "wof:name":"Keys A C & Services",
    "wof:placetype":"venue"
},
  "geometry": {"coordinates":[-93.931788,29.9212],"type":"Point"}
}