{
  "type": "Feature",
  "properties": {
    "iso:country":"US",
    "sg:address":"2727 Westside Dr",
    "sg:city":"Pasadena",
    "sg:classifiers":[
        {
            "category":"Restaurant",
            "type":"Food & Drink"
        }
    ],
    "sg:phone":"+1 713 947 7310",
    "sg:postcode":"77502",
    "sg:province":"TX",
    "wof:name":"Hope Food Supply",
    "wof:placetype":"venue"
},
  "geometry": {"coordinates":[-95.207083,29.671927],"type":"Point"}
}