{
  "type": "Feature",
  "properties": {
    "iso:country":"US",
    "sg:address":"5834 Southlea St",
    "sg:city":"Houston",
    "sg:classifiers":[
        {
            "category":"Wholesale",
            "subcategory":"Vending Machines",
            "type":"Manufacturing & Wholesale Goods"
        }
    ],
    "sg:phone":"+1 713 645 3283",
    "sg:postcode":"77033",
    "sg:province":"TX",
    "sg:tags":[
        "operator"
    ],
    "wof:name":"Pg Vending & Supplies",
    "wof:placetype":"venue"
},
  "geometry": {"coordinates":[-95.33151599999999,29.685267],"type":"Point"}
}