{
  "type": "Feature",
  "properties": {
    "iso:country":"US",
    "sg:address":"7525 Calder Ave",
    "sg:city":"Beaumont",
    "sg:classifiers":[
        {
            "category":"Wholesale",
            "subcategory":"Machinery & Supplies",
            "type":"Manufacturing & Wholesale Goods"
        }
    ],
    "sg:phone":"+1 409 866 9700",
    "sg:postcode":"77706",
    "sg:province":"TX",
    "sg:tags":[
        "equipment",
        "establishment"
    ],
    "wof:name":"J Dons Beauty Supply",
    "wof:placetype":"venue"
},
  "geometry": {"coordinates":[-94.17952,30.074084],"type":"Point"}
}