{
  "type": "Feature",
  "properties": {
    "iso:country":"US",
    "sg:address":"1525 West Ave",
    "sg:city":"Waco",
    "sg:classifiers":[
        {
            "category":"Education",
            "subcategory":"School",
            "type":"Public Place"
        }
    ],
    "sg:phone":"+1 254 755 7844",
    "sg:postcode":"76707",
    "sg:province":"TX",
    "wof:name":"LA Rue's Learning Ctr",
    "wof:placetype":"venue"
},
  "geometry": {"coordinates":[-97.15060800000001,31.556939],"type":"Point"}
}