{
  "type": "Feature",
  "properties": {
    "iso:country":"US",
    "sg:address":"2738 Tidwell Rd",
    "sg:city":"Burke",
    "sg:classifiers":[
        {
            "category":"Banks & Credit Unions",
            "subcategory":"Financial Services",
            "type":"Services"
        }
    ],
    "sg:phone":"+1 936 829 4811",
    "sg:postcode":"75941",
    "sg:province":"TX",
    "sg:tags":[
        "information",
        "consumer"
    ],
    "sg:website":"http://www.abhomenet.com",
    "wof:name":"Absolute Home Networking",
    "wof:placetype":"venue"
},
  "geometry": {"coordinates":[-94.78039099999999,31.24138],"type":"Point"}
}