{
  "type": "Feature",
  "properties": {
    "iso:country":"US",
    "sg:address":"18901 Co Rd 620",
    "sg:city":"Venus",
    "sg:classifiers":[
        {
            "category":"Manufacturing",
            "subcategory":"Metals",
            "type":"Manufacturing & Wholesale Goods"
        }
    ],
    "sg:phone":"+1 972 366 3593",
    "sg:postcode":"76084",
    "sg:province":"TX",
    "sg:tags":[
        "fabricator",
        "sheet"
    ],
    "wof:name":"Venus Metal Works",
    "wof:placetype":"venue"
},
  "geometry": {"coordinates":[-97.097971,32.44687],"type":"Point"}
}