{
  "type": "Feature",
  "properties": {
    "iso:country":"US",
    "sg:address":"4995 State Hwy 16",
    "sg:city":"Bandera",
    "sg:classifiers":[
        {
            "category":"Utilities",
            "subcategory":"Natural Gas",
            "type":"Services"
        }
    ],
    "sg:phone":"+1 830 796 4329",
    "sg:postcode":"78003",
    "sg:province":"TX",
    "wof:name":"El Paso Field Services",
    "wof:placetype":"venue"
},
  "geometry": {"coordinates":[-99.144002,29.741704],"type":"Point"}
}