{
  "type": "Feature",
  "properties": {
    "iso:country":"US",
    "sg:address":"9157 Turrentine Dr",
    "sg:city":"El Paso",
    "sg:classifiers":[
        {
            "category":"Real Estate",
            "subcategory":"Real Estate Agent",
            "type":"Services"
        }
    ],
    "sg:phone":"+1 915 590 8534",
    "sg:postcode":"79925",
    "sg:province":"TX",
    "wof:name":"A Armendariz Realty Inc",
    "wof:placetype":"venue"
},
  "geometry": {"coordinates":[-106.36613800000001,31.779436],"type":"Point"}
}