{
  "type": "Feature",
  "properties": {
    "iso:country":"US",
    "sg:address":"2930 Gateway Blvd E",
    "sg:city":"El Paso",
    "sg:classifiers":[
        {
            "category":"Retail",
            "subcategory":"Auto Repair",
            "type":"Services"
        }
    ],
    "sg:phone":"+1 915 532 8041",
    "sg:postcode":"79905",
    "sg:province":"TX",
    "sg:tags":[
        "repairing",
        "automobile"
    ],
    "wof:name":"Piedras Auto",
    "wof:placetype":"venue"
},
  "geometry": {"coordinates":[-106.460362,31.777526],"type":"Point"}
}