{
  "type": "Feature",
  "properties": {
    "iso:country":"US",
    "sg:address":"146 W Saint Clair Dr",
    "sg:city":"Irving",
    "sg:classifiers":[
        {
            "category":"Local Transit",
            "type":"Transportation"
        }
    ],
    "sg:phone":"+1 972 253 7548",
    "sg:postcode":"75061",
    "sg:province":"TX",
    "sg:tags":[
        "passenger",
        "limousine"
    ],
    "wof:name":"60 Dollar Limo & Sedan Svc",
    "wof:placetype":"venue"
},
  "geometry": {"coordinates":[-96.962447,32.823074],"type":"Point"}
}