{
  "type": "Feature",
  "properties": {
    "iso:country":"US",
    "sg:address":"4336 State Hwy 36",
    "sg:city":"Rosenberg",
    "sg:classifiers":[
        {
            "category":"Health Services",
            "subcategory":"Clinic",
            "type":"Services"
        }
    ],
    "sg:phone":"+1 281 342 7233",
    "sg:postcode":"77471",
    "sg:province":"TX",
    "sg:tags":[
        "general",
        "local",
        "government"
    ],
    "wof:name":"Emergency Medical Services",
    "wof:placetype":"venue"
},
  "geometry": {"coordinates":[-95.808004,29.521214],"type":"Point"}
}