{
  "type": "Feature",
  "properties": {
    "iso:country":"US",
    "sg:address":"5750 Balcones Dr",
    "sg:city":"Austin",
    "sg:classifiers":[
        {
            "category":"Health Services",
            "subcategory":"Health Practitioner",
            "type":"Services"
        }
    ],
    "sg:phone":"+1 512 467 2663",
    "sg:postcode":"78731",
    "sg:province":"TX",
    "sg:tags":[
        "acupuncture",
        "medicine",
        "alternative"
    ],
    "wof:name":"Austin Healing Herbs",
    "wof:placetype":"venue"
},
  "geometry": {"coordinates":[-97.756353,30.338512],"type":"Point"}
}