{
  "type": "Feature",
  "properties": {
    "iso:country":"US",
    "sg:address":"10804 McAngus Rd",
    "sg:city":"Del Valle",
    "sg:classifiers":[
        {
            "category":"Freight",
            "type":"Transportation"
        }
    ],
    "sg:phone":"+1 512 773 8216",
    "sg:postcode":"78617",
    "sg:province":"TX",
    "sg:tags":[
        "operator",
        "local",
        "trucking"
    ],
    "wof:name":"Soliz Deliveries Inc",
    "wof:placetype":"venue"
},
  "geometry": {"coordinates":[-97.667652,30.152989],"type":"Point"}
}