{
  "type": "Feature",
  "properties": {
    "iso:country":"US",
    "sg:address":"1030 W Arkansas Ln",
    "sg:city":"Arlington",
    "sg:classifiers":[
        {
            "category":"Utilities",
            "subcategory":"Telephone",
            "type":"Services"
        }
    ],
    "sg:phone":"+1 817 265 2677",
    "sg:postcode":"76013",
    "sg:province":"TX",
    "sg:tags":[
        "communications",
        "radiotelephone",
        "communication"
    ],
    "wof:name":"Wireless 4u Cooper Store",
    "wof:placetype":"venue"
},
  "geometry": {"coordinates":[-97.118438,32.706451],"type":"Point"}
}