{
  "type": "Feature",
  "properties": {
    "iso:country":"US",
    "sg:address":"5304 Mabry Ct",
    "sg:city":"Austin",
    "sg:classifiers":[
        {
            "category":"Professional",
            "subcategory":"Art Services",
            "type":"Services"
        }
    ],
    "sg:phone":"+1 512 394 9400",
    "sg:postcode":"78749",
    "sg:province":"TX",
    "sg:tags":[
        "graphic",
        "design"
    ],
    "wof:name":"Imedia",
    "wof:placetype":"venue"
},
  "geometry": {"coordinates":[-97.86701100000001,30.204549],"type":"Point"}
}