{
  "type": "Feature",
  "properties": {
    "iso:country":"US",
    "sg:address":"404 Old Course Dr",
    "sg:city":"Friendswood",
    "sg:classifiers":[
        {
            "category":"Arena",
            "subcategory":"Sports Club",
            "type":"Entertainment"
        }
    ],
    "sg:phone":"+1 281 482 8581",
    "sg:postcode":"77546",
    "sg:province":"TX",
    "sg:tags":[
        "membership"
    ],
    "wof:name":"Friendswood Soccer Club",
    "wof:placetype":"venue"
},
  "geometry": {"coordinates":[-95.218671,29.488135],"type":"Point"}
}