{
  "type": "Feature",
  "properties": {
    "iso:country":"US",
    "sg:address":"2501 N Ave",
    "sg:city":"Plano",
    "sg:classifiers":[
        {
            "category":"Shopping",
            "subcategory":"Computers & Home Electronics",
            "type":"Retail Goods"
        }
    ],
    "sg:phone":"+1 972 423 2674",
    "sg:postcode":"75074",
    "sg:province":"TX",
    "wof:name":"West & Assoc",
    "wof:placetype":"venue"
},
  "geometry": {"coordinates":[-96.6949,33.032288],"type":"Point"}
}