{
  "type": "Feature",
  "properties": {
    "iso:country":"US",
    "sg:address":"3007 66th St",
    "sg:city":"Lubbock",
    "sg:classifiers":[
        {
            "category":"Professional",
            "type":"Services"
        }
    ],
    "sg:phone":"+1 806 795 9495",
    "sg:postcode":"79413",
    "sg:province":"TX",
    "wof:name":"Sylvias Home",
    "wof:placetype":"venue"
},
  "geometry": {"coordinates":[-101.883296,33.534178],"type":"Point"}
}