{
  "type": "Feature",
  "properties": {
    "iso:country":"US",
    "sg:address":"121 Oak Ave",
    "sg:city":"Sulphur Springs",
    "sg:classifiers":[
        {
            "category":"Building & Trades",
            "subcategory":"Construction",
            "type":"Services"
        }
    ],
    "sg:phone":"+1 903 438 1718",
    "sg:postcode":"75482",
    "sg:province":"TX",
    "sg:tags":[
        "contractor"
    ],
    "wof:name":"L & S Administrative Consultan",
    "wof:placetype":"venue"
},
  "geometry": {"coordinates":[-95.600328,33.13714],"type":"Point"}
}