{
  "type": "Feature",
  "properties": {
    "iso:country":"US",
    "sg:address":"10455 N Central Expy",
    "sg:city":"Dallas",
    "sg:classifiers":[
        {
            "category":"Shopping",
            "subcategory":"Beauty & Cosmetics",
            "type":"Retail Goods"
        }
    ],
    "sg:phone":"+1 214 361 7174",
    "sg:postcode":"75231",
    "sg:province":"TX",
    "sg:tags":[
        "merchandise"
    ],
    "wof:name":"Gigi Beauty Supllies",
    "wof:placetype":"venue"
},
  "geometry": {"coordinates":[-96.770321,32.88798],"type":"Point"}
}