{
  "type": "Feature",
  "properties": {
    "iso:country":"US",
    "sg:address":"1123 Boling Brook St",
    "sg:city":"San Antonio",
    "sg:classifiers":[
        {
            "category":"Professional",
            "type":"Services"
        }
    ],
    "sg:phone":"+1 210 673 0134",
    "sg:postcode":"78245",
    "sg:province":"TX",
    "sg:tags":[
        "establishment"
    ],
    "wof:name":"USDW",
    "wof:placetype":"venue"
},
  "geometry": {"coordinates":[-98.67246400000001,29.421739],"type":"Point"}
}