{
  "type": "Feature",
  "properties": {
    "iso:country":"US",
    "sg:address":"16602 Park Firth Dr",
    "sg:city":"Houston",
    "sg:classifiers":[
        {
            "category":"Real Estate",
            "subcategory":"Real Estate Agent",
            "type":"Services"
        }
    ],
    "sg:phone":"+1 281 855 7867",
    "sg:postcode":"77084",
    "sg:province":"TX",
    "wof:name":"Johnston Properties",
    "wof:placetype":"venue"
},
  "geometry": {"coordinates":[-95.651926,29.831897],"type":"Point"}
}