{
  "type": "Feature",
  "properties": {
    "iso:country":"US",
    "sg:address":"915 Cole Ave",
    "sg:city":"Rosenberg",
    "sg:classifiers":[
        {
            "category":"Real Estate",
            "subcategory":"Real Estate Operator",
            "type":"Services"
        }
    ],
    "sg:phone":"+1 281 238 4586",
    "sg:postcode":"77471",
    "sg:province":"TX",
    "sg:tags":[
        "building",
        "apartment"
    ],
    "wof:name":"Falcon Point APT",
    "wof:placetype":"venue"
},
  "geometry": {"coordinates":[-95.784649,29.560054],"type":"Point"}
}