{
  "type": "Feature",
  "properties": {
    "iso:country":"US",
    "sg:address":"2635 E Parkerville Rd",
    "sg:city":"Lancaster",
    "sg:classifiers":[
        {
            "category":"Retail",
            "subcategory":"Laundry & Dry Cleaning",
            "type":"Services"
        }
    ],
    "sg:phone":"+1 972 230 8457",
    "sg:postcode":"75146",
    "sg:province":"TX",
    "wof:name":"Assure Carpet Care",
    "wof:placetype":"venue"
},
  "geometry": {"coordinates":[-96.817573,32.575333],"type":"Point"}
}