{
  "type": "Feature",
  "properties": {
    "iso:country":"US",
    "sg:address":"860 Rayford Rd",
    "sg:city":"Spring",
    "sg:classifiers":[
        {
            "category":"Home & Garden",
            "subcategory":"Garden Supply",
            "type":"Retail Goods"
        }
    ],
    "sg:phone":"+1 281 363 2545",
    "sg:postcode":"77386",
    "sg:province":"TX",
    "sg:tags":[
        "farm"
    ],
    "wof:name":"Johnston Ventures Inc",
    "wof:placetype":"venue"
},
  "geometry": {"coordinates":[-95.43265599999999,30.127322],"type":"Point"}
}