{
  "type": "Feature",
  "properties": {
    "iso:country":"US",
    "sg:address":"1528 Tampico Dr",
    "sg:city":"Plano",
    "sg:classifiers":[
        {
            "category":"Manufacturing",
            "subcategory":"Retail Goods",
            "type":"Manufacturing & Wholesale Goods"
        }
    ],
    "sg:phone":"+1 972 867 5515",
    "sg:postcode":"75075",
    "sg:province":"TX",
    "sg:tags":[
        "product",
        "mfg"
    ],
    "wof:name":"Artcepts",
    "wof:placetype":"venue"
},
  "geometry": {"coordinates":[-96.72599200000001,33.036122],"type":"Point"}
}