{
  "type": "Feature",
  "properties": {
    "iso:country":"US",
    "sg:address":"10501 Whitestone Ranch Rd",
    "sg:city":"Benbrook",
    "sg:classifiers":[
        {
            "category":"Restaurant",
            "type":"Food & Drink"
        }
    ],
    "sg:phone":"+1 817 249 5223",
    "sg:postcode":"76126",
    "sg:province":"TX",
    "wof:name":"Trg Restaurants Corporation",
    "wof:placetype":"venue"
},
  "geometry": {"coordinates":[-97.491737,32.663448],"type":"Point"}
}