{
  "type": "Feature",
  "properties": {
    "iso:country":"US",
    "sg:address":"5510 Tin Top Hwy",
    "sg:city":"Granbury",
    "sg:classifiers":[
        {
            "category":"Insurance",
            "subcategory":"Health Insurance",
            "type":"Services"
        }
    ],
    "sg:phone":"+1 817 578 8877",
    "sg:postcode":"76048",
    "sg:province":"TX",
    "sg:tags":[
        "carrier"
    ],
    "wof:name":"Texas Health & Financial",
    "wof:placetype":"venue"
},
  "geometry": {"coordinates":[-97.848932,32.507876],"type":"Point"}
}