{
  "type": "Feature",
  "properties": {
    "iso:country":"US",
    "sg:address":"5507 McPherson Ave",
    "sg:city":"Laredo",
    "sg:classifiers":[
        {
            "category":"Restaurant",
            "type":"Food & Drink"
        }
    ],
    "sg:phone":"+1 956 722 1188",
    "sg:postcode":"78041",
    "sg:province":"TX",
    "wof:name":"Hanger 21",
    "wof:placetype":"venue"
},
  "geometry": {"coordinates":[-99.481347,27.551198],"type":"Point"}
}