{
  "type": "Feature",
  "properties": {
    "iso:country":"US",
    "sg:address":"4419 77th St",
    "sg:city":"Lubbock",
    "sg:classifiers":[
        {
            "category":"Professional",
            "subcategory":"Lawyer & Legal Services",
            "type":"Services"
        }
    ],
    "sg:phone":"+1 806 797 4398",
    "sg:postcode":"79424",
    "sg:province":"TX",
    "wof:name":"Covey Ranch LLC",
    "wof:placetype":"venue"
},
  "geometry": {"coordinates":[-101.90926399999999,33.524742],"type":"Point"}
}