{
  "type": "Feature",
  "properties": {
    "iso:country":"US",
    "sg:address":"7101 Harry Hines Blvd",
    "sg:city":"Dallas",
    "sg:classifiers":[
        {
            "category":"Restaurant",
            "type":"Food & Drink"
        }
    ],
    "sg:phone":"+1 214 678 9191",
    "sg:postcode":"75235",
    "sg:province":"TX",
    "sg:tags":[
        "mexican"
    ],
    "wof:name":"Taco Pronto",
    "wof:placetype":"venue"
},
  "geometry": {"coordinates":[-96.856003,32.826801],"type":"Point"}
}