{
  "type": "Feature",
  "properties": {
    "iso:country":"US",
    "sg:address":"207 Serenada Dr",
    "sg:city":"Georgetown",
    "sg:classifiers":[
        {
            "category":"Building & Trades",
            "subcategory":"Construction",
            "type":"Services"
        }
    ],
    "sg:phone":"+1 512 633 3197",
    "sg:postcode":"78628",
    "sg:province":"TX",
    "sg:tags":[
        "house"
    ],
    "wof:name":"Rostark Restoration Inc",
    "wof:placetype":"venue"
},
  "geometry": {"coordinates":[-97.69189299999999,30.67946],"type":"Point"}
}