{
  "type": "Feature",
  "properties": {
    "iso:country":"US",
    "sg:address":"4207 Colchester Ct",
    "sg:city":"College Station",
    "sg:classifiers":[
        {
            "category":"Building & Trades",
            "subcategory":"Construction",
            "type":"Services"
        }
    ],
    "sg:phone":"+1 979 690 8097",
    "sg:postcode":"77845",
    "sg:province":"TX",
    "sg:tags":[
        "nonresidential"
    ],
    "wof:name":"Cornerstone Homes",
    "wof:placetype":"venue"
},
  "geometry": {"coordinates":[-96.283563,30.54973],"type":"Point"}
}