{
  "type": "Feature",
  "properties": {
    "iso:country":"US",
    "sg:address":"1022 E 7th St",
    "sg:city":"Austin",
    "sg:classifiers":[
        {
            "category":"Building & Trades",
            "subcategory":"Landscaping Services",
            "type":"Services"
        }
    ],
    "sg:phone":"+1 512 472 4210",
    "sg:postcode":"78702",
    "sg:province":"TX",
    "wof:name":"Coachs Lawn Service",
    "wof:placetype":"venue"
},
  "geometry": {"coordinates":[-97.73035400000001,30.265511],"type":"Point"}
}