{
  "type": "Feature",
  "properties": {
    "iso:country":"US",
    "sg:address":"108 Deanna St",
    "sg:city":"Robinson",
    "sg:classifiers":[
        {
            "category":"Shopping",
            "subcategory":"Department Store",
            "type":"Retail Goods"
        }
    ],
    "sg:phone":"+1 254 662 6460",
    "sg:postcode":"76706",
    "sg:province":"TX",
    "sg:tags":[
        "shop"
    ],
    "wof:name":"Dollar General",
    "wof:placetype":"venue"
},
  "geometry": {"coordinates":[-97.12267300000001,31.474742],"type":"Point"}
}