{
  "type": "Feature",
  "properties": {
    "iso:country":"US",
    "sg:address":"3435 Greystone Drive Suite 101",
    "sg:city":"Austin",
    "sg:classifiers":[
        {
            "category":"Fast Food",
            "type":"Food & Drink"
        },
        {
            "category":"Restaurant",
            "type":"Food & Drink"
        },
        {
            "category":"Professional",
            "type":"Services"
        }
    ],
    "sg:phone":"+1 512 418 9444",
    "sg:postcode":"78731",
    "sg:province":"TX",
    "sg:tags":[
        "delivery",
        "take",
        "pizza"
    ],
    "sg:website":"www.pizzahut.com",
    "wof:name":"Pizza Hut",
    "wof:placetype":"venue"
},
  "geometry": {"coordinates":[-97.747654,30.35726],"type":"Point"}
}