{
  "type": "Feature",
  "properties": {
    "iso:country":"US",
    "sg:address":"139 Jack Rabbit Run",
    "sg:city":"Round Rock",
    "sg:classifiers":[
        {
            "category":"Home & Garden",
            "subcategory":"Home Furnishings",
            "type":"Retail Goods"
        }
    ],
    "sg:phone":"+1 512 238 6057",
    "sg:postcode":"78664",
    "sg:province":"TX",
    "sg:tags":[
        "venetian",
        "blind"
    ],
    "wof:name":"Your Blinds Rosie",
    "wof:placetype":"venue"
},
  "geometry": {"coordinates":[-97.61259099999999,30.50679],"type":"Point"}
}