{
  "type": "Feature",
  "properties": {
    "iso:country":"US",
    "sg:address":"4309 N 10th St",
    "sg:city":"Mcallen",
    "sg:classifiers":[
        {
            "category":"Education",
            "subcategory":"Special Training",
            "type":"Public Place"
        }
    ],
    "sg:phone":"+1 956 630 0928",
    "sg:postcode":"78504",
    "sg:province":"TX",
    "sg:tags":[
        "school",
        "massage"
    ],
    "wof:name":"School of Natural Therapy",
    "wof:placetype":"venue"
},
  "geometry": {"coordinates":[-98.223485,26.241934],"type":"Point"}
}