{
  "type": "Feature",
  "properties": {
    "iso:country":"US",
    "sg:address":"14011 Lund Carlson Rd",
    "sg:city":"Coupland",
    "sg:classifiers":[
        {
            "category":"Real Estate",
            "subcategory":"Real Estate Operator",
            "type":"Services"
        }
    ],
    "sg:phone":"+1 512 281 4129",
    "sg:postcode":"78615",
    "sg:province":"TX",
    "sg:tags":[
        "farm",
        "management",
        "property",
        "lessor"
    ],
    "wof:name":"Bradley Samuelson",
    "wof:placetype":"venue"
},
  "geometry": {"coordinates":[-97.451815,30.427745],"type":"Point"}
}