{
  "type": "Feature",
  "properties": {
    "iso:country":"US",
    "sg:address":"281 Benjiman St",
    "sg:city":"Denton",
    "sg:classifiers":[
        {
            "category":"Retail",
            "subcategory":"Auto Repair",
            "type":"Services"
        }
    ],
    "sg:phone":"+1 972 523 9807",
    "sg:postcode":"76207",
    "sg:province":"TX",
    "sg:tags":[
        "general"
    ],
    "wof:name":"Sandlin Mobile Auto Repair",
    "wof:placetype":"venue"
},
  "geometry": {"coordinates":[-97.138177,33.245194],"type":"Point"}
}