{
  "type": "Feature",
  "properties": {
    "iso:country":"US",
    "sg:address":"22115 Fincastle Dr",
    "sg:city":"Katy",
    "sg:classifiers":[
        {
            "category":"Shopping",
            "subcategory":"Used Merchandise",
            "type":"Retail Goods"
        }
    ],
    "sg:phone":"+1 281 693 7162",
    "sg:postcode":"77450",
    "sg:province":"TX",
    "wof:name":"Sass With Class",
    "wof:placetype":"venue"
},
  "geometry": {"coordinates":[-95.75502899999999,29.781304],"type":"Point"}
}