{
  "type": "Feature",
  "properties": {
    "iso:country":"US",
    "sg:address":"7425 Hollister St",
    "sg:city":"Houston",
    "sg:classifiers":[
        {
            "category":"Professional",
            "subcategory":"Computer Services",
            "type":"Services"
        }
    ],
    "sg:phone":"+1 713 937 9740",
    "sg:postcode":"77040",
    "sg:province":"TX",
    "sg:tags":[
        "related"
    ],
    "wof:name":"Raintree Network Services",
    "wof:placetype":"venue"
},
  "geometry": {"coordinates":[-95.50699299999999,29.87041],"type":"Point"}
}