{
  "type": "Feature",
  "properties": {
    "iso:country":"US",
    "sg:address":"3330 Montana Ave",
    "sg:city":"El Paso",
    "sg:classifiers":[
        {
            "category":"Professional",
            "subcategory":"Business Services",
            "type":"Services"
        }
    ],
    "sg:phone":"+1 915 562 6408",
    "sg:postcode":"79903",
    "sg:province":"TX",
    "wof:name":"Amigo Rmero Escritorio Publico",
    "wof:placetype":"venue"
},
  "geometry": {"coordinates":[-106.454257,31.783631],"type":"Point"}
}