{
  "type": "Feature",
  "properties": {
    "iso:country":"US",
    "sg:address":"7718 Medina Base Rd",
    "sg:city":"San Antonio",
    "sg:classifiers":[
        {
            "category":"Personal",
            "subcategory":"Beauty Salon",
            "type":"Services"
        }
    ],
    "sg:phone":"+1 210 675 3610",
    "sg:postcode":"78227",
    "sg:province":"TX",
    "sg:tags":[
        "shop"
    ],
    "wof:name":"Cindy's Hair Care",
    "wof:placetype":"venue"
},
  "geometry": {"coordinates":[-98.64601999999999,29.373764],"type":"Point"}
}