{
  "type": "Feature",
  "properties": {
    "iso:country":"US",
    "sg:address":"1155 Fort Worth Hwy",
    "sg:city":"Weatherford",
    "sg:classifiers":[
        {
            "category":"Autos & Motor Vehicles",
            "subcategory":"Automobile Sales",
            "type":"Retail Goods"
        }
    ],
    "sg:phone":"+1 817 341 3700",
    "sg:postcode":"76086",
    "sg:province":"TX",
    "sg:tags":[
        "car",
        "dealer"
    ],
    "wof:name":"Car Bucks",
    "wof:placetype":"venue"
},
  "geometry": {"coordinates":[-97.77707700000001,32.75879],"type":"Point"}
}