{
  "type": "Feature",
  "properties": {
    "iso:country":"US",
    "sg:address":"603 Blue Chalk Dr",
    "sg:city":"Cedar Hill",
    "sg:classifiers":[
        {
            "category":"Freight",
            "type":"Transportation"
        }
    ],
    "sg:phone":"+1 469 272 7975",
    "sg:postcode":"75104",
    "sg:province":"TX",
    "wof:name":"D and T Transportation",
    "wof:placetype":"venue"
},
  "geometry": {"coordinates":[-96.929047,32.59862],"type":"Point"}
}