{
  "type": "Feature",
  "properties": {
    "iso:country":"US",
    "sg:address":"9010 S Goliad Dr",
    "sg:city":"Pharr",
    "sg:classifiers":[
        {
            "category":"Wholesale",
            "subcategory":"Non-durable Goods",
            "type":"Manufacturing & Wholesale Goods"
        }
    ],
    "sg:phone":"+1 956 783 8822",
    "sg:postcode":"78577",
    "sg:province":"TX",
    "sg:tags":[
        "business"
    ],
    "wof:name":"Import Mex Export",
    "wof:placetype":"venue"
},
  "geometry": {"coordinates":[-98.202412,26.106635],"type":"Point"}
}