{
  "type": "Feature",
  "properties": {
    "iso:country":"US",
    "sg:address":"22811 Elkana Deane Ln",
    "sg:city":"Katy",
    "sg:classifiers":[
        {
            "category":"Professional",
            "type":"Services"
        }
    ],
    "sg:phone":"+1 281 347 3795",
    "sg:postcode":"77449",
    "sg:province":"TX",
    "wof:name":"Cdj Products",
    "wof:placetype":"venue"
},
  "geometry": {"coordinates":[-95.767709,29.806908],"type":"Point"}
}