{
  "type": "Feature",
  "properties": {
    "iso:country":"US",
    "sg:address":"2727 Bolton Boone Dr",
    "sg:city":"Desoto",
    "sg:classifiers":[
        {
            "category":"Health Services",
            "subcategory":"Doctor",
            "type":"Services"
        }
    ],
    "sg:phone":"+1 972 296 2505",
    "sg:postcode":"75115",
    "sg:province":"TX",
    "sg:tags":[
        "physician",
        "surgeon"
    ],
    "wof:name":"Edwin E Hitt & Assoc",
    "wof:placetype":"venue"
},
  "geometry": {"coordinates":[-96.878518,32.644544],"type":"Point"}
}