{
  "type": "Feature",
  "properties": {
    "iso:country":"US",
    "sg:address":"1626 Shepherd Ln",
    "sg:city":"Dallas",
    "sg:classifiers":[
        {
            "category":"Real Estate",
            "subcategory":"Real Estate Operator",
            "type":"Services"
        }
    ],
    "sg:phone":"+1 972 286 1453",
    "sg:postcode":"75253",
    "sg:province":"TX",
    "sg:tags":[
        "mobile",
        "home",
        "community"
    ],
    "wof:name":"Mark Village Inc A Texas Corp",
    "wof:placetype":"venue"
},
  "geometry": {"coordinates":[-96.61433700000001,32.693542],"type":"Point"}
}