{
  "type": "Feature",
  "properties": {
    "iso:country":"US",
    "sg:address":"230 E Ferguson Ave",
    "sg:city":"Pharr",
    "sg:classifiers":[
        {
            "category":"Personal",
            "subcategory":"Beauty Salon",
            "type":"Services"
        }
    ],
    "sg:phone":"+1 956 702 0599",
    "sg:postcode":"78577",
    "sg:province":"TX",
    "wof:name":"Kutter's Hair Salon",
    "wof:placetype":"venue"
},
  "geometry": {"coordinates":[-98.177924,26.211169],"type":"Point"}
}