{
  "type": "Feature",
  "properties": {
    "iso:country":"US",
    "sg:address":"2622 Reagan St",
    "sg:city":"Dallas",
    "sg:classifiers":[
        {
            "category":"Real Estate",
            "subcategory":"Real Estate Operator",
            "type":"Services"
        }
    ],
    "sg:phone":"+1 214 528 7799",
    "sg:postcode":"75219",
    "sg:province":"TX",
    "sg:tags":[
        "building",
        "apartment"
    ],
    "wof:name":"Reagan Plaza Apartments",
    "wof:placetype":"venue"
},
  "geometry": {"coordinates":[-96.81399500000001,32.807254],"type":"Point"}
}