{
  "type": "Feature",
  "properties": {
    "iso:country":"US",
    "sg:address":"533 Highfall Dr",
    "sg:city":"Dallas",
    "sg:classifiers":[
        {
            "category":"Health Services",
            "subcategory":"Clinic",
            "type":"Services"
        }
    ],
    "sg:phone":"+1 214 372 2054",
    "sg:postcode":"75232",
    "sg:province":"TX",
    "sg:tags":[
        "home",
        "care"
    ],
    "wof:name":"Gradys Home Care Inc",
    "wof:placetype":"venue"
},
  "geometry": {"coordinates":[-96.830292,32.662841],"type":"Point"}
}