{
  "type": "Feature",
  "properties": {
    "iso:country":"US",
    "sg:address":"232 Caribou Dr",
    "sg:city":"Spring Branch",
    "sg:classifiers":[
        {
            "category":"Professional",
            "subcategory":"Computer Services",
            "type":"Services"
        }
    ],
    "sg:phone":"+1 830 885 7395",
    "sg:postcode":"78070",
    "sg:province":"TX",
    "sg:tags":[
        "programing",
        "custom"
    ],
    "wof:name":"Eagle Computer Svcs",
    "wof:placetype":"venue"
},
  "geometry": {"coordinates":[-98.381281,29.946733],"type":"Point"}
}