{
  "type": "Feature",
  "properties": {
    "iso:country":"US",
    "sg:address":"21346 W Knox Dr",
    "sg:city":"Porter",
    "sg:classifiers":[
        {
            "category":"Real Estate",
            "subcategory":"Real Estate Operator",
            "type":"Services"
        }
    ],
    "sg:phone":"+1 281 577 6928",
    "sg:postcode":"77365",
    "sg:province":"TX",
    "sg:tags":[
        "mobile",
        "home",
        "site"
    ],
    "wof:name":"China Berry Lane Mobile HM Pk",
    "wof:placetype":"venue"
},
  "geometry": {"coordinates":[-95.24718300000001,30.078573],"type":"Point"}
}