{
  "type": "Feature",
  "properties": {
    "iso:country":"US",
    "sg:address":"1049 Gessner Dr",
    "sg:city":"Houston",
    "sg:classifiers":[
        {
            "category":"Shopping",
            "subcategory":"Jewelry",
            "type":"Retail Goods"
        }
    ],
    "sg:phone":"+1 713 984 0919",
    "sg:postcode":"77055",
    "sg:province":"TX",
    "sg:tags":[
        "jeweler"
    ],
    "wof:name":"Lee's Jewelry",
    "wof:placetype":"venue"
},
  "geometry": {"coordinates":[-95.544094,29.785934],"type":"Point"}
}