{
  "type": "Feature",
  "properties": {
    "iso:country":"US",
    "sg:address":"1100 Ramsay Dr",
    "sg:city":"Allen",
    "sg:classifiers":[
        {
            "category":"Wholesale",
            "subcategory":"Chemicals & Plastics",
            "type":"Manufacturing & Wholesale Goods"
        }
    ],
    "sg:phone":"+1 972 390 7700",
    "sg:postcode":"75002",
    "sg:province":"TX",
    "wof:name":"Top Line Tactics",
    "wof:placetype":"venue"
},
  "geometry": {"coordinates":[-96.574844,33.099244],"type":"Point"}
}