{
  "type": "Feature",
  "properties": {
    "iso:country":"US",
    "sg:address":"1620 E Belt Line Rd",
    "sg:city":"Carrollton",
    "sg:classifiers":[
        {
            "category":"Professional",
            "subcategory":"Lawyer & Legal Services",
            "type":"Services"
        }
    ],
    "sg:phone":"+1 972 242 8887",
    "sg:postcode":"75006",
    "sg:province":"TX",
    "wof:name":"Cantrell Garry atty",
    "wof:placetype":"venue"
},
  "geometry": {"coordinates":[-96.898027,32.953522],"type":"Point"}
}