{
  "type": "Feature",
  "properties": {
    "iso:country":"US",
    "sg:address":"9825 S Mason Rd Suite 280",
    "sg:city":"Richmond",
    "sg:classifiers":[
        {
            "category":"Banks & Credit Unions",
            "subcategory":"Investment Brokerage",
            "type":"Services"
        },
        {
            "category":"Banks & Credit Unions",
            "subcategory":"Bank",
            "type":"Services"
        },
        {
            "category":"Banks & Credit Unions",
            "subcategory":"Financial Services",
            "type":"Services"
        }
    ],
    "sg:phone":"+1 281 239 0888",
    "sg:postcode":"77406",
    "sg:province":"TX",
    "sg:tags":[
        "mutual",
        "retirement",
        "broker",
        "fund",
        "planning",
        "security",
        "bond",
        "stock"
    ],
    "sg:website":"http://www.edwardjones.com/en_US/fa/index.html&CIRN=517239",
    "wof:name":"Edward Jones - Financial Advisor: TREY WITTE III",
    "wof:placetype":"venue"
},
  "geometry": {"coordinates":[-95.736237,29.660063],"type":"Point"}
}