{
  "type": "Feature",
  "properties": {
    "iso:country":"US",
    "sg:address":"8603 Culebra Rd",
    "sg:city":"San Antonio",
    "sg:classifiers":[
        {
            "category":"Autos & Motor Vehicles",
            "subcategory":"Auto Supplies",
            "type":"Retail Goods"
        }
    ],
    "sg:phone":"+1 210 767 1407",
    "sg:postcode":"78251",
    "sg:province":"TX",
    "sg:tags":[
        "automobile",
        "parts"
    ],
    "sg:website":"www.advance.com",
    "wof:name":"Advance Auto Parts Inc",
    "wof:placetype":"venue"
},
  "geometry": {"coordinates":[-98.65274700000001,29.472913],"type":"Point"}
}