{
  "type": "Feature",
  "properties": {
    "iso:country":"US",
    "sg:address":"2242 US Hwy 83",
    "sg:city":"Crystal City",
    "sg:classifiers":[
        {
            "category":"Building & Trades",
            "subcategory":"Plumbing",
            "type":"Services"
        }
    ],
    "sg:phone":"+1 830 374 9000",
    "sg:postcode":"78839",
    "sg:province":"TX",
    "sg:tags":[
        "product",
        "management",
        "energy",
        "system"
    ],
    "wof:name":"Regency Energy",
    "wof:placetype":"venue"
},
  "geometry": {"coordinates":[-99.829382,28.695583],"type":"Point"}
}