{
  "type": "Feature",
  "properties": {
    "iso:country":"US",
    "sg:address":"12235 el Santo Way",
    "sg:city":"San Antonio",
    "sg:classifiers":[
        {
            "category":"Building & Trades",
            "subcategory":"Landscaping Services",
            "type":"Services"
        }
    ],
    "sg:phone":"+1 210 393 3366",
    "sg:postcode":"78233",
    "sg:province":"TX",
    "sg:tags":[
        "lawn",
        "maintenance",
        "grounds"
    ],
    "wof:name":"Done Right Lawn & Tree Svc",
    "wof:placetype":"venue"
},
  "geometry": {"coordinates":[-98.401827,29.55282],"type":"Point"}
}