{
  "type": "Feature",
  "properties": {
    "iso:country":"US",
    "sg:address":"10331 Broadway St",
    "sg:city":"Pearland",
    "sg:classifiers":[
        {
            "category":"Manufacturing",
            "subcategory":"Rubber & Plastics",
            "type":"Manufacturing & Wholesale Goods"
        },
        {
            "category":"Autos & Motor Vehicles",
            "subcategory":"Auto Supplies",
            "type":"Retail Goods"
        }
    ],
    "sg:phone":"+1 713 436 6045",
    "sg:postcode":"77584",
    "sg:province":"TX",
    "sg:tags":[
        "wheel",
        "tires-wholesale",
        "tire",
        "manufacturer"
    ],
    "sg:website":"http://www.discounttire.com/dtcs/home.do?utm_source=YellowPages&utm_medium=iyp&utm_campaign=YellowPagesIYPOrg",
    "wof:name":"Discount Tire",
    "wof:placetype":"venue"
},
  "geometry": {"coordinates":[-95.391243,29.555901],"type":"Point"}
}