{
  "type": "Feature",
  "properties": {
    "iso:country":"US",
    "sg:address":"301 W Parker Rd Ste 102",
    "sg:city":"Plano",
    "sg:classifiers":[
        {
            "category":"Shopping",
            "subcategory":"Clothing, Apparel, & Fashions",
            "type":"Retail Goods"
        },
        {
            "category":"Personal",
            "type":"Services"
        }
    ],
    "sg:phone":"+1 972 424 9049",
    "sg:postcode":"75023",
    "sg:province":"TX",
    "sg:tags":[
        "tailoring",
        "tailor",
        "alteration",
        "alterations-clothing",
        "wedding"
    ],
    "wof:name":"Le Tailor",
    "wof:placetype":"venue"
},
  "geometry": {"coordinates":[-96.707517,33.039472],"type":"Point"}
}