{
  "type": "Feature",
  "properties": {
    "iso:country":"US",
    "sg:address":"8757 Winedale Rd",
    "sg:city":"Burton",
    "sg:phone":"+1 979 278 3527",
    "sg:postcode":"77835",
    "sg:province":"TX",
    "sg:tags":[
        "farm",
        "corn"
    ],
    "wof:name":"Otto Bergmann",
    "wof:placetype":"venue"
},
  "geometry": {"coordinates":[-96.63012000000001,30.097077],"type":"Point"}
}