{
  "type": "Feature",
  "properties": {
    "iso:country":"US",
    "sg:address":"3507 Joshua Batton Cir",
    "sg:city":"San Antonio",
    "sg:classifiers":[
        {
            "category":"Wholesale",
            "subcategory":"Durable Goods & Equipment",
            "type":"Manufacturing & Wholesale Goods"
        }
    ],
    "sg:phone":"+1 210 967 9419",
    "sg:postcode":"78217",
    "sg:province":"TX",
    "wof:name":"Drill Tech Tool & Supply",
    "wof:placetype":"venue"
},
  "geometry": {"coordinates":[-98.436168,29.536471],"type":"Point"}
}