{
  "type": "Feature",
  "properties": {
    "iso:country":"US",
    "sg:address":"1526 Antoine Dr",
    "sg:city":"Houston",
    "sg:classifiers":[
        {
            "category":"Real Estate",
            "subcategory":"Real Estate Agent",
            "type":"Services"
        }
    ],
    "sg:phone":"+1 713 681 2081",
    "sg:postcode":"77055",
    "sg:province":"TX",
    "wof:name":"I Buy Ugly Houses",
    "wof:placetype":"venue"
},
  "geometry": {"coordinates":[-95.475668,29.798175],"type":"Point"}
}