{
  "type": "Feature",
  "properties": {
    "iso:country":"US",
    "sg:address":"209 Old Hewitt Rd",
    "sg:city":"Waco",
    "sg:classifiers":[
        {
            "category":"Banks & Credit Unions",
            "subcategory":"Investment Brokerage",
            "type":"Services"
        }
    ],
    "sg:phone":"+1 254 776 9330",
    "sg:postcode":"76712",
    "sg:province":"TX",
    "sg:tags":[
        "security"
    ],
    "wof:name":"Raymond James Financial Svc",
    "wof:placetype":"venue"
},
  "geometry": {"coordinates":[-97.211917,31.498671],"type":"Point"}
}