{
  "type": "Feature",
  "properties": {
    "iso:country":"US",
    "sg:address":"338 S Cedar Ridge Dr",
    "sg:city":"Duncanville",
    "sg:classifiers":[
        {
            "category":"Banks & Credit Unions",
            "subcategory":"Bank",
            "type":"Services"
        }
    ],
    "sg:phone":"+1 972 296 2265",
    "sg:postcode":"75116",
    "sg:province":"TX",
    "wof:name":"Oaks Bank & Trust Co",
    "wof:placetype":"venue"
},
  "geometry": {"coordinates":[-96.925499,32.6478],"type":"Point"}
}