{
  "type": "Feature",
  "properties": {
    "iso:country":"US",
    "sg:address":"240 N Hampton Rd",
    "sg:city":"Desoto",
    "sg:classifiers":[
        {
            "category":"Insurance",
            "subcategory":"Insurance Agent",
            "type":"Services"
        }
    ],
    "sg:phone":"+1 972 223 6828",
    "sg:postcode":"75115",
    "sg:province":"TX",
    "wof:name":"State Farm Insurance",
    "wof:placetype":"venue"
},
  "geometry": {"coordinates":[-96.856906,32.592338],"type":"Point"}
}