{
  "type": "Feature",
  "properties": {
    "iso:country":"US",
    "sg:address":"9702 Kings Link Cir",
    "sg:city":"Rowlett",
    "sg:classifiers":[
        {
            "category":"Building & Trades",
            "subcategory":"Construction",
            "type":"Services"
        }
    ],
    "sg:phone":"+1 972 412 2577",
    "sg:postcode":"75089",
    "sg:province":"TX",
    "sg:tags":[
        "house"
    ],
    "wof:name":"Triangle Construction Inc",
    "wof:placetype":"venue"
},
  "geometry": {"coordinates":[-96.53841799999999,32.944695],"type":"Point"}
}