{
  "type": "Feature",
  "properties": {
    "iso:country":"US",
    "sg:address":"207 Industrial Ct",
    "sg:city":"Wylie",
    "sg:classifiers":[
        {
            "category":"Wholesale",
            "subcategory":"Groceries",
            "type":"Manufacturing & Wholesale Goods"
        },
        {
            "category":"Wholesale",
            "subcategory":"Meat",
            "type":"Manufacturing & Wholesale Goods"
        }
    ],
    "sg:phone":"+1 972 442 5095",
    "sg:postcode":"75098",
    "sg:province":"TX",
    "sg:tags":[
        "facility",
        "food",
        "fruit",
        "vegetable",
        "fresh",
        "other"
    ],
    "wof:name":"Prime Kuts Distributing Inc",
    "wof:placetype":"venue"
},
  "geometry": {"coordinates":[-96.54304500000001,33.010737],"type":"Point"}
}