{
  "type": "Feature",
  "properties": {
    "iso:country":"US",
    "sg:address":"2905 Mangum Rd",
    "sg:city":"Houston",
    "sg:classifiers":[
        {
            "category":"Shopping",
            "subcategory":"Used Merchandise",
            "type":"Retail Goods"
        }
    ],
    "sg:phone":"+1 713 688 1680",
    "sg:postcode":"77092",
    "sg:province":"TX",
    "wof:name":"Christys Resale Shop",
    "wof:placetype":"venue"
},
  "geometry": {"coordinates":[-95.45938,29.815654],"type":"Point"}
}