{
  "type": "Feature",
  "properties": {
    "iso:country":"US",
    "sg:address":"808 3rd St",
    "sg:city":"Rosenberg",
    "sg:classifiers":[
        {
            "category":"Professional",
            "subcategory":"Management & Consulting",
            "type":"Services"
        },
        {
            "category":"Professional",
            "subcategory":"Accounting & Tax Preparation",
            "type":"Services"
        }
    ],
    "sg:phone":"+1 281 342 8611",
    "sg:postcode":"77471",
    "sg:province":"TX",
    "sg:tags":[
        "return",
        "filing"
    ],
    "wof:name":"Common Sense Financial Svcs",
    "wof:placetype":"venue"
},
  "geometry": {"coordinates":[-95.806815,29.56019],"type":"Point"}
}