{
  "type": "Feature",
  "properties": {
    "iso:country":"US",
    "sg:address":"915 Hwy 1131",
    "sg:city":"Vidor",
    "sg:classifiers":[
        {
            "category":"Food & Beverages",
            "subcategory":"Groceries & Convenience Stores",
            "type":"Retail Goods"
        }
    ],
    "sg:phone":"+1 409 786 2063",
    "sg:postcode":"77662",
    "sg:province":"TX",
    "wof:name":"Country Pantry",
    "wof:placetype":"venue"
},
  "geometry": {"coordinates":[-94.036238,30.192524],"type":"Point"}
}