{
  "type": "Feature",
  "properties": {
    "iso:country":"US",
    "sg:address":"605 N 3rd St",
    "sg:city":"Jarrell",
    "sg:classifiers":[
        {
            "category":"Retail",
            "subcategory":"Auto Repair",
            "type":"Services"
        }
    ],
    "sg:phone":"+1 512 746 5021",
    "sg:postcode":"76537",
    "sg:province":"TX",
    "sg:tags":[
        "transmission"
    ],
    "wof:name":"Richard's Transmission",
    "wof:placetype":"venue"
},
  "geometry": {"coordinates":[-97.609301,30.82802],"type":"Point"}
}