{
  "type": "Feature",
  "properties": {
    "iso:country":"US",
    "sg:address":"903 Bordeaux Dr",
    "sg:city":"Leander",
    "sg:classifiers":[
        {
            "category":"Education",
            "subcategory":"Special Training",
            "type":"Public Place"
        }
    ],
    "sg:phone":"+1 512 528 8793",
    "sg:postcode":"78641",
    "sg:province":"TX",
    "sg:tags":[
        "educational"
    ],
    "wof:name":"Michael Mazza Educational Services",
    "wof:placetype":"venue"
},
  "geometry": {"coordinates":[-97.83026599999999,30.554186],"type":"Point"}
}