{
  "type": "Feature",
  "properties": {
    "iso:country":"US",
    "sg:address":"100 Kiowa Dr W",
    "sg:city":"Gainesville",
    "sg:classifiers":[
        {
            "category":"Shopping",
            "subcategory":"Pharmacy",
            "type":"Retail Goods"
        }
    ],
    "sg:phone":"+1 940 668 7384",
    "sg:postcode":"76240",
    "sg:province":"TX",
    "wof:name":"Kiowa Pharmacy",
    "wof:placetype":"venue"
},
  "geometry": {"coordinates":[-97.01836400000001,33.560393],"type":"Point"}
}