{
  "type": "Feature",
  "properties": {
    "iso:country":"US",
    "sg:address":"5860 Ranchester Dr",
    "sg:city":"Houston",
    "sg:classifiers":[
        {
            "category":"Social Services",
            "subcategory":"Job Training",
            "type":"Services"
        }
    ],
    "sg:phone":"+1 713 271 4546",
    "sg:postcode":"77036",
    "sg:province":"TX",
    "sg:tags":[
        "rehabilitation"
    ],
    "wof:name":"JCDL Rehabilitation Ctr",
    "wof:placetype":"venue"
},
  "geometry": {"coordinates":[-95.54834099999999,29.715633],"type":"Point"}
}