{
  "type": "Feature",
  "properties": {
    "iso:country":"US",
    "sg:address":"2809 Santa Maria Ave",
    "sg:city":"Laredo",
    "sg:classifiers":[
        {
            "category":"Professional",
            "subcategory":"Detective & Security Services",
            "type":"Services"
        }
    ],
    "sg:phone":"+1 956 723 5009",
    "sg:postcode":"78040",
    "sg:province":"TX",
    "sg:tags":[
        "car",
        "guard",
        "patrol"
    ],
    "wof:name":"Lugo's Security Agency",
    "wof:placetype":"venue"
},
  "geometry": {"coordinates":[-99.51000999999999,27.52539],"type":"Point"}
}