{
  "type": "Feature",
  "properties": {
    "iso:country":"US",
    "sg:address":"6220 Dashwood Dr",
    "sg:city":"Houston",
    "sg:classifiers":[
        {
            "category":"Health Services",
            "subcategory":"Doctor",
            "type":"Services"
        }
    ],
    "sg:phone":"+1 713 771 8883",
    "sg:postcode":"77081",
    "sg:province":"TX",
    "sg:tags":[
        "dentist"
    ],
    "wof:name":"Good Shepherd Dental Clinic",
    "wof:placetype":"venue"
},
  "geometry": {"coordinates":[-95.491501,29.707399],"type":"Point"}
}