{
  "type": "Feature",
  "properties": {
    "iso:country":"US",
    "sg:address":"1141 N McCullough St",
    "sg:city":"San Benito",
    "sg:classifiers":[
        {
            "category":"Building & Trades",
            "subcategory":"Plumbing",
            "type":"Services"
        }
    ],
    "sg:phone":"+1 956 399 1359",
    "sg:postcode":"78586",
    "sg:province":"TX",
    "sg:tags":[
        "plumbing",
        "contractor"
    ],
    "wof:name":"Raymond's Plumbing & Repair",
    "wof:placetype":"venue"
},
  "geometry": {"coordinates":[-97.61609300000001,26.137536],"type":"Point"}
}