{
  "type": "Feature",
  "properties": {
    "iso:country":"US",
    "sg:address":"104 E 1st St",
    "sg:city":"Fort Stockton",
    "sg:classifiers":[
        {
            "category":"Banks & Credit Unions",
            "subcategory":"Investment Brokerage",
            "type":"Services"
        }
    ],
    "sg:phone":"+1 432 336 3611",
    "sg:postcode":"79735",
    "sg:province":"TX",
    "sg:tags":[
        "stock",
        "bond"
    ],
    "wof:name":"Edward Jones Co",
    "wof:placetype":"venue"
},
  "geometry": {"coordinates":[-102.879116,30.885351],"type":"Point"}
}