{
  "type": "Feature",
  "properties": {
    "iso:country":"US",
    "sg:address":"330 Southmore avenue",
    "sg:city":"Pasadena",
    "sg:classifiers":[
        {
            "category":"Fast Food",
            "type":"Food & Drink"
        },
        {
            "category":"Restaurant",
            "type":"Food & Drink"
        }
    ],
    "sg:phone":"+1 713 920 3330",
    "sg:postcode":"77502",
    "sg:province":"TX",
    "sg:tags":[
        "traditional",
        "american",
        "chicken",
        "wing"
    ],
    "wof:name":"Broadway Buffalo Wings",
    "wof:placetype":"venue"
},
  "geometry": {"coordinates":[-95.20820399999999,29.690807],"type":"Point"}
}