{
  "type": "Feature",
  "properties": {
    "iso:country":"US",
    "sg:address":"7198 Merchant Ave",
    "sg:city":"El Paso",
    "sg:classifiers":[
        {
            "category":"Freight",
            "type":"Transportation"
        }
    ],
    "sg:phone":"+1 915 881 9310",
    "sg:postcode":"79915",
    "sg:province":"TX",
    "sg:tags":[
        "delivery"
    ],
    "wof:name":"Consolidated Routing",
    "wof:placetype":"venue"
},
  "geometry": {"coordinates":[-106.380876,31.765452],"type":"Point"}
}