{
  "type": "Feature",
  "properties": {
    "iso:country":"US",
    "sg:address":"431 W Bedford Euless Rd",
    "sg:city":"Hurst",
    "sg:classifiers":[
        {
            "category":"Organizations",
            "subcategory":"Religious Organization",
            "type":"Services"
        }
    ],
    "sg:phone":"+1 817 285 1671",
    "sg:postcode":"76053",
    "sg:province":"TX",
    "sg:tags":[
        "church"
    ],
    "wof:name":"Christ Memorial Baptist Church",
    "wof:placetype":"venue"
},
  "geometry": {"coordinates":[-97.17475399999999,32.833874],"type":"Point"}
}