{
  "type": "Feature",
  "properties": {
    "iso:country":"US",
    "sg:address":"2443 Franklin Dr",
    "sg:city":"Mesquite",
    "sg:classifiers":[
        {
            "category":"Retail",
            "subcategory":"Auto Repair",
            "type":"Services"
        }
    ],
    "sg:phone":"+1 972 288 1475",
    "sg:postcode":"75150",
    "sg:province":"TX",
    "sg:tags":[
        "wrecker"
    ],
    "wof:name":"Mesquite Towing Svc",
    "wof:placetype":"venue"
},
  "geometry": {"coordinates":[-96.618414,32.797398],"type":"Point"}
}