{
  "type": "Feature",
  "properties": {
    "iso:country":"US",
    "sg:address":"11394 James Watt Dr",
    "sg:city":"El Paso",
    "sg:classifiers":[
        {
            "category":"Wholesale",
            "subcategory":"Construction Materials",
            "type":"Manufacturing & Wholesale Goods"
        }
    ],
    "sg:phone":"+1 915 593 0960",
    "sg:postcode":"79936",
    "sg:province":"TX",
    "sg:tags":[
        "steel",
        "locker",
        "industrial",
        "storage",
        "sh"
    ],
    "wof:name":"Vaughn Storage Systems Company",
    "wof:placetype":"venue"
},
  "geometry": {"coordinates":[-106.320087,31.74472],"type":"Point"}
}