{
  "type": "Feature",
  "properties": {
    "iso:country":"US",
    "sg:address":"106 Texas Ave",
    "sg:city":"San Marcos",
    "sg:classifiers":[
        {
            "category":"Building & Trades",
            "subcategory":"Construction",
            "type":"Services"
        }
    ],
    "sg:phone":"+1 512 754 7694",
    "sg:postcode":"78666",
    "sg:province":"TX",
    "sg:tags":[
        "contractor"
    ],
    "wof:name":"Celebrity Clrs Rstoration Svcs",
    "wof:placetype":"venue"
},
  "geometry": {"coordinates":[-97.953512,29.859535],"type":"Point"}
}