{
  "type": "Feature",
  "properties": {
    "iso:country":"US",
    "sg:address":"2804 Storey Ln",
    "sg:city":"Dallas",
    "sg:classifiers":[
        {
            "category":"Professional",
            "type":"Services"
        }
    ],
    "sg:phone":"+1 214 350 4545",
    "sg:postcode":"75220",
    "sg:province":"TX",
    "sg:tags":[
        "establishment"
    ],
    "wof:name":"Carter Vaughn",
    "wof:placetype":"venue"
},
  "geometry": {"coordinates":[-96.875241,32.861882],"type":"Point"}
}