{
  "type": "Feature",
  "properties": {
    "iso:country":"US",
    "sg:address":"2620 Summerhill Rd",
    "sg:city":"Texarkana",
    "sg:classifiers":[
        {
            "category":"Shopping",
            "type":"Retail Goods"
        }
    ],
    "sg:phone":"+1 903 792 1030",
    "sg:postcode":"75503",
    "sg:province":"TX",
    "sg:tags":[
        "home",
        "medical",
        "rental",
        "supply"
    ],
    "wof:name":"Tri-State HM Respiratory Care",
    "wof:placetype":"venue"
},
  "geometry": {"coordinates":[-94.06394,33.442071],"type":"Point"}
}