{
  "type": "Feature",
  "properties": {
    "iso:country":"US",
    "sg:address":"4205 Harvest Hill Rd",
    "sg:city":"Carrollton",
    "sg:classifiers":[
        {
            "category":"Building & Trades",
            "subcategory":"Construction",
            "type":"Services"
        }
    ],
    "sg:phone":"+1 972 446 0075",
    "sg:postcode":"75010",
    "sg:province":"TX",
    "sg:tags":[
        "system",
        "specialty",
        "heating",
        "contractor",
        "air conditioning"
    ],
    "wof:name":"D Bridges Service Company",
    "wof:placetype":"venue"
},
  "geometry": {"coordinates":[-96.871773,33.02533],"type":"Point"}
}