{
  "type": "Feature",
  "properties": {
    "iso:country":"US",
    "sg:address":"32 E Rivercrest Dr",
    "sg:city":"Houston",
    "sg:classifiers":[
        {
            "category":"Professional",
            "type":"Services"
        }
    ],
    "sg:phone":"+1 713 952 6491",
    "sg:postcode":"77042",
    "sg:province":"TX",
    "wof:name":"Herbert & Carol Zieben Fo",
    "wof:placetype":"venue"
},
  "geometry": {"coordinates":[-95.54207700000001,29.748863],"type":"Point"}
}