{
  "type": "Feature",
  "properties": {
    "iso:country":"US",
    "sg:address":"501 S Jupiter Rd",
    "sg:city":"Garland",
    "sg:classifiers":[
        {
            "category":"Education",
            "subcategory":"School",
            "type":"Public Place"
        }
    ],
    "sg:phone":"+1 972 485 4918",
    "sg:postcode":"75042",
    "sg:province":"TX",
    "wof:name":"Gisd Harris Hill",
    "wof:placetype":"venue"
},
  "geometry": {"coordinates":[-96.682999,32.909199],"type":"Point"}
}