{
  "type": "Feature",
  "properties": {
    "iso:country":"US",
    "sg:address":"2318 E Mitchell St",
    "sg:city":"Arlington",
    "sg:classifiers":[
        {
            "category":"Professional",
            "type":"Services"
        }
    ],
    "sg:phone":"+1 817 277 1293",
    "sg:postcode":"76010",
    "sg:province":"TX",
    "wof:name":"Lometa Cryer",
    "wof:placetype":"venue"
},
  "geometry": {"coordinates":[-97.06980900000001,32.724801],"type":"Point"}
}