{
  "type": "Feature",
  "properties": {
    "iso:country":"US",
    "sg:address":"8800 Shoal Creek Blvd",
    "sg:city":"Austin",
    "sg:classifiers":[
        {
            "category":"Wholesale",
            "subcategory":"Medical Equipment & Supplies",
            "type":"Manufacturing & Wholesale Goods"
        }
    ],
    "sg:phone":"+1 512 279 9900",
    "sg:postcode":"78757",
    "sg:province":"TX",
    "sg:tags":[
        "independent"
    ],
    "wof:name":"Medical Express Inc",
    "wof:placetype":"venue"
},
  "geometry": {"coordinates":[-97.73655100000001,30.373642],"type":"Point"}
}