{
  "type": "Feature",
  "properties": {
    "iso:country":"US",
    "sg:address":"822 W Mason St",
    "sg:city":"Mabank",
    "sg:classifiers":[
        {
            "category":"Education",
            "subcategory":"School",
            "type":"Public Place"
        }
    ],
    "sg:phone":"+1 903 887 9332",
    "sg:postcode":"75147",
    "sg:province":"TX",
    "wof:name":"Mabank High School",
    "wof:placetype":"venue"
},
  "geometry": {"coordinates":[-96.11363900000001,32.369286],"type":"Point"}
}