{
  "type": "Feature",
  "properties": {
    "iso:country":"US",
    "sg:address":"15401 Vantage Pkwy W",
    "sg:city":"Houston",
    "sg:classifiers":[
        {
            "category":"Manufacturing",
            "subcategory":"Electronics",
            "type":"Manufacturing & Wholesale Goods"
        }
    ],
    "sg:phone":"+1 281 442 2900",
    "sg:postcode":"77032",
    "sg:province":"TX",
    "wof:name":"Extel Llc",
    "wof:placetype":"venue"
},
  "geometry": {"coordinates":[-95.366294,29.941274],"type":"Point"}
}