{
  "type": "Feature",
  "properties": {
    "iso:country":"US",
    "sg:address":"2300 McKinney Ave",
    "sg:city":"Dallas",
    "sg:classifiers":[
        {
            "category":"Social Services",
            "type":"Services"
        }
    ],
    "sg:phone":"+1 214 871 6200",
    "sg:postcode":"75201",
    "sg:province":"TX",
    "wof:name":"American Red Cross",
    "wof:placetype":"venue"
},
  "geometry": {"coordinates":[-96.802575,32.79341],"type":"Point"}
}