{
  "type": "Feature",
  "properties": {
    "iso:country":"US",
    "sg:address":"4122 Ridgepoint Dr",
    "sg:city":"Pearland",
    "sg:classifiers":[
        {
            "category":"Retail",
            "subcategory":"Repair Shop",
            "type":"Services"
        }
    ],
    "sg:phone":"+1 281 489 4983",
    "sg:postcode":"77584",
    "sg:province":"TX",
    "sg:tags":[
        "air",
        "installation",
        "heating",
        "conditioning"
    ],
    "wof:name":"Healthy Indoor Systems",
    "wof:placetype":"venue"
},
  "geometry": {"coordinates":[-95.355217,29.535465],"type":"Point"}
}