{
  "type": "Feature",
  "properties": {
    "iso:country":"US",
    "sg:address":"322 Mohawk Rd",
    "sg:city":"Abilene",
    "sg:classifiers":[
        {
            "category":"Professional",
            "type":"Services"
        }
    ],
    "sg:phone":"+1 325 673 7618",
    "sg:postcode":"79601",
    "sg:province":"TX",
    "wof:name":"Jerry & Linda Davidson",
    "wof:placetype":"venue"
},
  "geometry": {"coordinates":[-99.690983,32.552953],"type":"Point"}
}