{
  "type": "Feature",
  "properties": {
    "iso:country":"US",
    "sg:address":"1520 Byron Nelson Pkwy",
    "sg:city":"Southlake",
    "sg:classifiers":[
        {
            "category":"Wholesale",
            "subcategory":"Drugs",
            "type":"Manufacturing & Wholesale Goods"
        }
    ],
    "sg:phone":"+1 817 251 9485",
    "sg:postcode":"76092",
    "sg:province":"TX",
    "sg:tags":[
        "pharmaceutical",
        "product"
    ],
    "wof:name":"Eli Lilly & Co",
    "wof:placetype":"venue"
},
  "geometry": {"coordinates":[-97.13359699999999,32.924346],"type":"Point"}
}