{
  "type": "Feature",
  "properties": {
    "iso:country":"US",
    "sg:address":"3833 Magnolia Ave",
    "sg:city":"Lubbock",
    "sg:classifiers":[
        {
            "category":"Building & Trades",
            "subcategory":"Construction",
            "type":"Services"
        }
    ],
    "sg:phone":"+1 806 765 9600",
    "sg:postcode":"79404",
    "sg:province":"TX",
    "sg:tags":[
        "contractor"
    ],
    "wof:name":"Norandex/Reynolds Dist Co",
    "wof:placetype":"venue"
},
  "geometry": {"coordinates":[-101.821592,33.558122],"type":"Point"}
}