{
  "type": "Feature",
  "properties": {
    "iso:country":"US",
    "sg:address":"1410 Avenue F NW",
    "sg:city":"Childress",
    "sg:classifiers":[
        {
            "category":"Travel",
            "subcategory":"Hotels & Motels",
            "type":"Entertainment"
        }
    ],
    "sg:phone":"+1 940 937 2506",
    "sg:postcode":"79201",
    "sg:province":"TX",
    "sg:tags":[
        "corporate",
        "lodging"
    ],
    "sg:website":"http://www.budgetinn.com",
    "wof:name":"Budget Inn",
    "wof:placetype":"venue"
},
  "geometry": {"coordinates":[-100.21920900000001,34.431931],"type":"Point"}
}