{
  "type": "Feature",
  "properties": {
    "iso:country":"US",
    "sg:address":"2702 Covington Dr",
    "sg:city":"Garland",
    "sg:classifiers":[
        {
            "category":"Education",
            "subcategory":"Special Training",
            "type":"Public Place"
        }
    ],
    "sg:phone":"+1 972 495 8758",
    "sg:postcode":"75040",
    "sg:province":"TX",
    "wof:name":"Iscc",
    "wof:placetype":"venue"
},
  "geometry": {"coordinates":[-96.609218,32.941164],"type":"Point"}
}