{
  "type": "Feature",
  "properties": {
    "iso:country":"US",
    "sg:address":"31103 Vickie Ln",
    "sg:city":"Magnolia",
    "sg:classifiers":[
        {
            "category":"Shopping",
            "subcategory":"Florist",
            "type":"Retail Goods"
        }
    ],
    "sg:phone":"+1 281 252 6011",
    "sg:postcode":"77354",
    "sg:province":"TX",
    "wof:name":"Floral Scentsations",
    "wof:placetype":"venue"
},
  "geometry": {"coordinates":[-95.608486,30.204525],"type":"Point"}
}