{
  "type": "Feature",
  "properties": {
    "iso:country":"US",
    "sg:address":"752 Co Rd 3324",
    "sg:city":"Pittsburg",
    "sg:classifiers":[
        {
            "category":"Building & Trades",
            "subcategory":"Construction",
            "type":"Services"
        }
    ],
    "sg:phone":"+1 903 856 7649",
    "sg:postcode":"75686",
    "sg:province":"TX",
    "sg:tags":[
        "contractor",
        "hanging"
    ],
    "wof:name":"Williams Roofing & Painting",
    "wof:placetype":"venue"
},
  "geometry": {"coordinates":[-95.044809,32.95215],"type":"Point"}
}