{
  "type": "Feature",
  "properties": {
    "iso:country":"US",
    "sg:address":"904 Hughes Ave",
    "sg:city":"Alice",
    "sg:classifiers":[
        {
            "category":"Professional",
            "subcategory":"Business Services",
            "type":"Services"
        }
    ],
    "sg:phone":"+1 361 664 5106",
    "sg:postcode":"78332",
    "sg:province":"TX",
    "wof:name":"Garcia Capital Partners LLC",
    "wof:placetype":"venue"
},
  "geometry": {"coordinates":[-98.06852600000001,27.725205],"type":"Point"}
}