{
  "type": "Feature",
  "properties": {
    "iso:country":"US",
    "sg:address":"816 Congress Ave Ste 1410",
    "sg:city":"Austin",
    "sg:classifiers":[
        {
            "category":"Professional",
            "subcategory":"Lawyer & Legal Services",
            "type":"Services"
        }
    ],
    "sg:phone":"+1 512 476 7771",
    "sg:postcode":"78701",
    "sg:province":"TX",
    "sg:website":"www.hotzerunkle.com",
    "wof:name":"Hotze Runkle PLLC",
    "wof:placetype":"venue"
},
  "geometry": {"coordinates":[-97.74220099999999,30.27013],"type":"Point"}
}