{
  "type": "Feature",
  "properties": {
    "iso:country":"US",
    "sg:address":"1814 Willow Rd",
    "sg:city":"Carrollton",
    "sg:classifiers":[
        {
            "category":"Retail",
            "subcategory":"Auto Repair",
            "type":"Services"
        }
    ],
    "sg:phone":"+1 972 242 7180",
    "sg:postcode":"75006",
    "sg:province":"TX",
    "sg:tags":[
        "body"
    ],
    "wof:name":"Ricks Paint & Body & High Per",
    "wof:placetype":"venue"
},
  "geometry": {"coordinates":[-96.90842600000001,32.965573],"type":"Point"}
}