{
  "type": "Feature",
  "properties": {
    "iso:country":"US",
    "sg:address":"2516 52nd St",
    "sg:city":"Dallas",
    "sg:classifiers":[
        {
            "category":"Shopping",
            "subcategory":"Clothing, Apparel, & Fashions",
            "type":"Retail Goods"
        }
    ],
    "sg:phone":"+1 214 371 6589",
    "sg:postcode":"75216",
    "sg:province":"TX",
    "wof:name":"Two Sisters Fashions",
    "wof:placetype":"venue"
},
  "geometry": {"coordinates":[-96.780569,32.693725],"type":"Point"}
}