{
  "type": "Feature",
  "properties": {
    "iso:country":"US",
    "sg:address":"574 Co Rd 1380",
    "sg:city":"Alvord",
    "sg:classifiers":[
        {
            "category":"Retail",
            "subcategory":"Auto Repair",
            "type":"Services"
        }
    ],
    "sg:phone":"+1 940 389 5432",
    "sg:postcode":"76225",
    "sg:province":"TX",
    "sg:tags":[
        "general"
    ],
    "wof:name":"Teds Auto & Truck Repair",
    "wof:placetype":"venue"
},
  "geometry": {"coordinates":[-97.68446,33.321398],"type":"Point"}
}