{
  "type": "Feature",
  "properties": {
    "iso:country":"US",
    "sg:address":"323 N Cedar St",
    "sg:city":"Kermit",
    "sg:classifiers":[
        {
            "category":"Organizations",
            "subcategory":"Religious Organization",
            "type":"Services"
        }
    ],
    "sg:phone":"+1 432 586 5641",
    "sg:postcode":"79745",
    "sg:province":"TX",
    "sg:tags":[
        "church"
    ],
    "wof:name":"Church Of God Of Prophecy",
    "wof:placetype":"venue"
},
  "geometry": {"coordinates":[-103.09325200000001,31.860799],"type":"Point"}
}