{
  "type": "Feature",
  "properties": {
    "iso:country":"US",
    "sg:address":"9525 Bissonnet St",
    "sg:city":"Houston",
    "sg:classifiers":[
        {
            "category":"Real Estate",
            "subcategory":"Real Estate Agent",
            "type":"Services"
        }
    ],
    "sg:phone":"+1 713 777 4267",
    "sg:postcode":"77036",
    "sg:province":"TX",
    "wof:name":"Hans-Christian Realty & Assoc",
    "wof:placetype":"venue"
},
  "geometry": {"coordinates":[-95.543111,29.675736],"type":"Point"}
}