{
  "type": "Feature",
  "properties": {
    "iso:country":"US",
    "sg:address":"12804 Seagoville Rd",
    "sg:city":"Mesquite",
    "sg:classifiers":[
        {
            "category":"Home & Garden",
            "subcategory":"Home Furnishings",
            "type":"Retail Goods"
        }
    ],
    "sg:phone":"+1 214 505 4526",
    "sg:postcode":"75180",
    "sg:province":"TX",
    "sg:tags":[
        "broom",
        "brush",
        "merchandise",
        "mfg"
    ],
    "sg:website":"http://www.janturner.com",
    "wof:name":"Fuller Brush Co Ind Distr",
    "wof:placetype":"venue"
},
  "geometry": {"coordinates":[-96.607933,32.704739],"type":"Point"}
}