{
  "type": "Feature",
  "properties": {
    "iso:country":"US",
    "sg:address":"10227 Inwood Dr",
    "sg:city":"Houston",
    "sg:classifiers":[
        {
            "category":"Organizations",
            "subcategory":"Non-profit Organization",
            "type":"Services"
        }
    ],
    "sg:phone":"+1 713 784 7883",
    "sg:postcode":"77042",
    "sg:province":"TX",
    "sg:tags":[
        "fund",
        "counselor",
        "raising"
    ],
    "wof:name":"Mc Cormick Group Intl Inc",
    "wof:placetype":"venue"
},
  "geometry": {"coordinates":[-95.55361499999999,29.745594],"type":"Point"}
}