{
  "type": "Feature",
  "properties": {
    "iso:country":"US",
    "sg:address":"12137 State Hwy 110",
    "sg:city":"Van",
    "sg:classifiers":[
        {
            "category":"Retail",
            "subcategory":"Auto Repair",
            "type":"Services"
        }
    ],
    "sg:phone":"+1 903 963 3334",
    "sg:postcode":"75790",
    "sg:province":"TX",
    "sg:tags":[
        "general"
    ],
    "wof:name":"A-1 Automotive",
    "wof:placetype":"venue"
},
  "geometry": {"coordinates":[-95.63740199999999,32.538976],"type":"Point"}
}