{
  "type": "Feature",
  "properties": {
    "iso:country":"US",
    "sg:address":"206 S Magnolia St",
    "sg:city":"Rockport",
    "sg:classifiers":[
        {
            "category":"Professional",
            "subcategory":"Business Services",
            "type":"Services"
        }
    ],
    "sg:phone":"+1 361 758 8043",
    "sg:postcode":"78382",
    "sg:province":"TX",
    "sg:tags":[
        "interior",
        "design"
    ],
    "wof:name":"PSI Designed Interiors",
    "wof:placetype":"venue"
},
  "geometry": {"coordinates":[-97.051464,28.023309],"type":"Point"}
}