{
  "type": "Feature",
  "properties": {
    "iso:country":"US",
    "sg:address":"140 Steele",
    "sg:city":"Kyle",
    "sg:classifiers":[
        {
            "category":"Professional",
            "subcategory":"Computer Services",
            "type":"Services"
        }
    ],
    "sg:phone":"+1 512 262 7250",
    "sg:postcode":"78640",
    "sg:province":"TX",
    "sg:tags":[
        "technical",
        "assistance",
        "support"
    ],
    "wof:name":"Books By Joe",
    "wof:placetype":"venue"
},
  "geometry": {"coordinates":[-97.877573,30.014974],"type":"Point"}
}