{
  "type": "Feature",
  "properties": {
    "iso:country":"US",
    "sg:address":"4335 Calder Ave",
    "sg:city":"Beaumont",
    "sg:classifiers":[
        {
            "category":"Shopping",
            "subcategory":"Gifts & Souvenirs",
            "type":"Retail Goods"
        }
    ],
    "sg:phone":"+1 409 658 3079",
    "sg:postcode":"77706",
    "sg:province":"TX",
    "sg:tags":[
        "shop",
        "cards",
        "book",
        "candle"
    ],
    "wof:name":"Tallulah's",
    "wof:placetype":"venue"
},
  "geometry": {"coordinates":[-94.149058,30.086259],"type":"Point"}
}