{
  "type": "Feature",
  "properties": {
    "iso:country":"US",
    "sg:address":"3609 Glacier Ln",
    "sg:city":"Garland",
    "sg:classifiers":[
        {
            "category":"Professional",
            "type":"Services"
        }
    ],
    "sg:phone":"+1 972 272 5002",
    "sg:postcode":"75042",
    "sg:province":"TX",
    "wof:name":"June E Cupples",
    "wof:placetype":"venue"
},
  "geometry": {"coordinates":[-96.685658,32.910829],"type":"Point"}
}