{
  "type": "Feature",
  "properties": {
    "iso:country":"US",
    "sg:address":"107 Ranch Rd 620 S",
    "sg:city":"Austin",
    "sg:classifiers":[
        {
            "category":"Home & Garden",
            "subcategory":"Carpets & Floor Coverings",
            "type":"Retail Goods"
        }
    ],
    "sg:phone":"+1 512 250 9135",
    "sg:postcode":"78734",
    "sg:province":"TX",
    "sg:tags":[
        "installs"
    ],
    "wof:name":"Imagine Floors of Austin",
    "wof:placetype":"venue"
},
  "geometry": {"coordinates":[-97.952327,30.363498],"type":"Point"}
}