{
  "type": "Feature",
  "properties": {
    "iso:country":"US",
    "sg:address":"1301 Wonderworld Dr",
    "sg:city":"San Marcos",
    "sg:classifiers":[
        {
            "category":"Health Services",
            "subcategory":"Doctor",
            "type":"Services"
        }
    ],
    "sg:phone":"+1 512 396 8565",
    "sg:postcode":"78666",
    "sg:province":"TX",
    "sg:tags":[
        "physician",
        "surgeon"
    ],
    "wof:name":"San Marcos Medical Imaging",
    "wof:placetype":"venue"
},
  "geometry": {"coordinates":[-97.94849499999999,29.852984],"type":"Point"}
}