{
  "type": "Feature",
  "properties": {
    "iso:country":"US",
    "sg:address":"7100 W New Boston Rd",
    "sg:city":"Texarkana",
    "sg:classifiers":[
        {
            "category":"Wholesale",
            "subcategory":"Vending Machines",
            "type":"Manufacturing & Wholesale Goods"
        }
    ],
    "sg:phone":"+1 903 831 6036",
    "sg:postcode":"75501",
    "sg:province":"TX",
    "sg:tags":[
        "operator"
    ],
    "wof:name":"Rocking B Productions",
    "wof:placetype":"venue"
},
  "geometry": {"coordinates":[-94.156155,33.445565],"type":"Point"}
}