{
  "type": "Feature",
  "properties": {
    "iso:country":"US",
    "sg:address":"399 W Campbell Rd Ste 102",
    "sg:city":"Richardson",
    "sg:classifiers":[
        {
            "category":"Health Services",
            "subcategory":"Doctor",
            "type":"Services"
        }
    ],
    "sg:phone":"+1 972 231 8883",
    "sg:postcode":"75080",
    "sg:province":"TX",
    "sg:tags":[
        "medicine",
        "internal"
    ],
    "sg:website":"www.lakewoodhillsinternalmedicin...",
    "wof:name":"Lakewood Hills Internal Medicine",
    "wof:placetype":"venue"
},
  "geometry": {"coordinates":[-96.724407,32.975227],"type":"Point"}
}