{
  "type": "Feature",
  "properties": {
    "iso:country":"US",
    "sg:address":"511 N High St",
    "sg:city":"Henderson",
    "sg:classifiers":[
        {
            "category":"Health Services",
            "subcategory":"Doctor",
            "type":"Services"
        }
    ],
    "sg:phone":"+1 903 657 7583",
    "sg:postcode":"75652",
    "sg:province":"TX",
    "sg:tags":[
        "clinic"
    ],
    "wof:name":"Trinity Clinic-Henderson",
    "wof:placetype":"venue"
},
  "geometry": {"coordinates":[-94.79669199999999,32.158091],"type":"Point"}
}