{
  "type": "Feature",
  "properties": {
    "iso:country":"US",
    "sg:address":"900 Market St E",
    "sg:city":"Honey Grove",
    "sg:classifiers":[
        {
            "category":"Organizations",
            "subcategory":"Community Association",
            "type":"Services"
        }
    ],
    "sg:phone":"+1 903 378 2669",
    "sg:postcode":"75446",
    "sg:province":"TX",
    "wof:name":"Masonic Lodge",
    "wof:placetype":"venue"
},
  "geometry": {"coordinates":[-95.904094,33.581865],"type":"Point"}
}