{
  "type": "Feature",
  "properties": {
    "iso:country":"US",
    "sg:address":"612 Nolana St",
    "sg:city":"Mcallen",
    "sg:classifiers":[
        {
            "category":"Professional",
            "subcategory":"Engineering",
            "type":"Services"
        }
    ],
    "sg:phone":"+1 956 687 7291",
    "sg:postcode":"78504",
    "sg:province":"TX",
    "sg:tags":[
        "civil",
        "consulting",
        "engineer"
    ],
    "wof:name":"Consulting Engineers Surveyors",
    "wof:placetype":"venue"
},
  "geometry": {"coordinates":[-98.221036,26.239002],"type":"Point"}
}