{
  "type": "Feature",
  "properties": {
    "iso:country":"US",
    "sg:address":"7540 Co Rd 331",
    "sg:city":"Abilene",
    "sg:classifiers":[
        {
            "category":"Professional",
            "type":"Services"
        }
    ],
    "sg:phone":"+1 325 537 9630",
    "sg:postcode":"79601",
    "sg:province":"TX",
    "wof:name":"Legacy Operations Inc",
    "wof:placetype":"venue"
},
  "geometry": {"coordinates":[-99.704437,32.681397],"type":"Point"}
}