{
  "type": "Feature",
  "properties": {
    "iso:country":"US",
    "sg:address":"3247 Karla Dr",
    "sg:city":"Mesquite",
    "sg:classifiers":[
        {
            "category":"Food & Beverages",
            "subcategory":"Groceries & Convenience Stores",
            "type":"Retail Goods"
        }
    ],
    "sg:phone":"+1 972 279 2701",
    "sg:postcode":"75150",
    "sg:province":"TX",
    "wof:name":"Save Time Food Mart Inc",
    "wof:placetype":"venue"
},
  "geometry": {"coordinates":[-96.648895,32.826127],"type":"Point"}
}