{
  "type": "Feature",
  "properties": {
    "iso:country":"US",
    "sg:address":"420 Bigelow St",
    "sg:city":"Aransas Pass",
    "sg:classifiers":[
        {
            "category":"Professional",
            "type":"Services"
        }
    ],
    "sg:phone":"+1 361 758 3232",
    "sg:postcode":"78336",
    "sg:province":"TX",
    "wof:name":"Barneys Place Inc",
    "wof:placetype":"venue"
},
  "geometry": {"coordinates":[-97.132035,27.910646],"type":"Point"}
}