{
  "type": "Feature",
  "properties": {
    "iso:country":"US",
    "sg:address":"1502 E Airline Rd",
    "sg:city":"Victoria",
    "sg:classifiers":[
        {
            "category":"Government",
            "subcategory":"Office",
            "type":"Public Place"
        }
    ],
    "sg:phone":"+1 361 575 2352",
    "sg:postcode":"77901",
    "sg:province":"TX",
    "sg:tags":[
        "administrative",
        "program",
        "health"
    ],
    "wof:name":"Blind Commission District 23",
    "wof:placetype":"venue"
},
  "geometry": {"coordinates":[-96.990649,28.821236],"type":"Point"}
}