{
  "type": "Feature",
  "properties": {
    "iso:country":"US",
    "sg:address":"3631 Callaghan Rd",
    "sg:city":"San Antonio",
    "sg:classifiers":[
        {
            "category":"Building & Trades",
            "subcategory":"Cleaning & Sanitation",
            "type":"Services"
        }
    ],
    "sg:phone":"+1 210 523 0490",
    "sg:postcode":"78228",
    "sg:province":"TX",
    "sg:tags":[
        "maintenance"
    ],
    "wof:name":"Jani King Phillip B River",
    "wof:placetype":"venue"
},
  "geometry": {"coordinates":[-98.602619,29.45629],"type":"Point"}
}