{
  "type": "Feature",
  "properties": {
    "iso:country":"US",
    "sg:address":"100 Methodist Encampment Rd",
    "sg:city":"Kerrville",
    "sg:classifiers":[
        {
            "category":"Real Estate",
            "subcategory":"Real Estate Operator",
            "type":"Services"
        }
    ],
    "sg:phone":"+1 830 895 4548",
    "sg:postcode":"78028",
    "sg:province":"TX",
    "sg:tags":[
        "apartment"
    ],
    "wof:name":"Spirit Property Management Llp",
    "wof:placetype":"venue"
},
  "geometry": {"coordinates":[-99.174751,30.064091],"type":"Point"}
}