{
  "type": "Feature",
  "properties": {
    "iso:country":"US",
    "sg:address":"2307 Balsam Dr",
    "sg:city":"Arlington",
    "sg:classifiers":[
        {
            "category":"Freight",
            "type":"Transportation"
        }
    ],
    "sg:phone":"+1 817 633 2277",
    "sg:postcode":"76006",
    "sg:province":"TX",
    "sg:tags":[
        "consultant"
    ],
    "wof:name":"Leap Logistics",
    "wof:placetype":"venue"
},
  "geometry": {"coordinates":[-97.06769300000001,32.771965],"type":"Point"}
}