{
  "type": "Feature",
  "properties": {
    "iso:country":"US",
    "sg:address":"2070 W Cardinal Dr",
    "sg:city":"Beaumont",
    "sg:classifiers":[
        {
            "category":"Building & Trades",
            "subcategory":"Construction",
            "type":"Services"
        }
    ],
    "sg:phone":"+1 409 842 5222",
    "sg:postcode":"77705",
    "sg:province":"TX",
    "sg:tags":[
        "concrete",
        "contractor"
    ],
    "wof:name":"Star Concrete Pumping",
    "wof:placetype":"venue"
},
  "geometry": {"coordinates":[-94.132498,30.043119],"type":"Point"}
}