{
  "type": "Feature",
  "properties": {
    "iso:country":"US",
    "sg:address":"510 Osage St",
    "sg:city":"Corpus Christi",
    "sg:classifiers":[
        {
            "category":"Sports & Exercise",
            "subcategory":"Golf",
            "type":"Entertainment"
        },
        {
            "category":"Social Services",
            "type":"Services"
        }
    ],
    "sg:phone":"+1 361 882 1561",
    "sg:postcode":"78405",
    "sg:province":"TX",
    "sg:tags":[
        "course",
        "senior",
        "public",
        "citizen"
    ],
    "wof:name":"Zavala Senior Center",
    "wof:placetype":"venue"
},
  "geometry": {"coordinates":[-97.42759100000001,27.778245],"type":"Point"}
}