{
  "type": "Feature",
  "properties": {
    "iso:country":"US",
    "sg:address":"2119 Nogalitos St",
    "sg:city":"San Antonio",
    "sg:classifiers":[
        {
            "category":"Shopping",
            "subcategory":"Used Merchandise",
            "type":"Retail Goods"
        }
    ],
    "sg:phone":"+1 210 532 4132",
    "sg:postcode":"78225",
    "sg:province":"TX",
    "wof:name":"Friendship Rlief Thrift Stores",
    "wof:placetype":"venue"
},
  "geometry": {"coordinates":[-98.51793600000001,29.393313],"type":"Point"}
}