{
  "type": "Feature",
  "properties": {
    "iso:country":"US",
    "sg:address":"210 E Corpus Christi St",
    "sg:city":"Beeville",
    "sg:classifiers":[
        {
            "category":"Government",
            "subcategory":"Office",
            "type":"Public Place"
        }
    ],
    "sg:phone":"+1 361 362 3281",
    "sg:postcode":"78102",
    "sg:province":"TX",
    "wof:name":"Extension Office",
    "wof:placetype":"venue"
},
  "geometry": {"coordinates":[-97.746168,28.402856],"type":"Point"}
}