{
  "type": "Feature",
  "properties": {
    "iso:country":"US",
    "sg:address":"12787 Point Dr",
    "sg:city":"Willis",
    "sg:classifiers":[
        {
            "category":"Insurance",
            "subcategory":"Insurance Agent",
            "type":"Services"
        }
    ],
    "sg:phone":"+1 936 890 7713",
    "sg:postcode":"77318",
    "sg:province":"TX",
    "wof:name":"Cunningham Insurance Agency",
    "wof:placetype":"venue"
},
  "geometry": {"coordinates":[-95.551872,30.458621],"type":"Point"}
}