{
  "type": "Feature",
  "properties": {
    "iso:country":"US",
    "sg:address":"6716 Camp Bowie Blvd",
    "sg:city":"Fort Worth",
    "sg:classifiers":[
        {
            "category":"Personal",
            "subcategory":"Beauty Salon",
            "type":"Services"
        }
    ],
    "sg:phone":"+1 817 735 8621",
    "sg:postcode":"76116",
    "sg:province":"TX",
    "sg:tags":[
        "shop"
    ],
    "wof:name":"Town West Beauty Salon",
    "wof:placetype":"venue"
},
  "geometry": {"coordinates":[-97.434197,32.72091],"type":"Point"}
}