{
  "type": "Feature",
  "properties": {
    "iso:country":"US",
    "sg:address":"1215 Epsilon St",
    "sg:city":"Pasadena",
    "sg:classifiers":[
        {
            "category":"Manufacturing",
            "subcategory":"Chemicals & Compounds",
            "type":"Manufacturing & Wholesale Goods"
        }
    ],
    "sg:phone":"+1 281 487 0239",
    "sg:postcode":"77504",
    "sg:province":"TX",
    "sg:tags":[
        "preparation",
        "mfg"
    ],
    "wof:name":"Sarvabhadra",
    "wof:placetype":"venue"
},
  "geometry": {"coordinates":[-95.186589,29.638372],"type":"Point"}
}