{
  "type": "Feature",
  "properties": {
    "iso:country":"US",
    "sg:address":"2601 State Hwy 114",
    "sg:city":"Southlake",
    "sg:classifiers":[
        {
            "category":"Shopping",
            "subcategory":"Discount & Variety Stores",
            "type":"Retail Goods"
        }
    ],
    "sg:phone":"+1 817 749 2804",
    "sg:postcode":"76092",
    "sg:province":"TX",
    "sg:tags":[
        "merchandise",
        "general"
    ],
    "wof:name":"Costco Wholesale Corporation",
    "wof:placetype":"venue"
},
  "geometry": {"coordinates":[-97.10990700000001,32.943133],"type":"Point"}
}