{
  "type": "Feature",
  "properties": {
    "iso:country":"US",
    "sg:address":"910 Travis St",
    "sg:city":"Houston",
    "sg:classifiers":[
        {
            "category":"Manufacturing",
            "subcategory":"Tools & Machinery",
            "type":"Manufacturing & Wholesale Goods"
        }
    ],
    "sg:phone":"+1 713 652 2010",
    "sg:postcode":"77002",
    "sg:province":"TX",
    "sg:tags":[
        "instrument",
        "mfg"
    ],
    "wof:name":"Kong Dr James",
    "wof:placetype":"venue"
},
  "geometry": {"coordinates":[-95.36581,29.757591],"type":"Point"}
}