{
  "type": "Feature",
  "properties": {
    "iso:country":"US",
    "sg:address":"1212 13th St",
    "sg:city":"Lubbock",
    "sg:classifiers":[
        {
            "category":"Shopping",
            "subcategory":"Stationery & Office Supplies",
            "type":"Retail Goods"
        }
    ],
    "sg:phone":"+1 806 749 5033",
    "sg:postcode":"79401",
    "sg:province":"TX",
    "sg:tags":[
        "business",
        "form"
    ],
    "wof:name":"Standard Register Company",
    "wof:placetype":"venue"
},
  "geometry": {"coordinates":[-101.848951,33.583607],"type":"Point"}
}