{
  "type": "Feature",
  "properties": {
    "iso:country":"US",
    "sg:address":"509 S Mason Rd",
    "sg:city":"Katy",
    "sg:classifiers":[
        {
            "category":"Restaurant",
            "type":"Food & Drink"
        }
    ],
    "sg:phone":"+1 281 492 0654",
    "sg:postcode":"77450",
    "sg:province":"TX",
    "sg:tags":[
        "barbecue",
        "american"
    ],
    "wof:name":"Wing's N More",
    "wof:placetype":"venue"
},
  "geometry": {"coordinates":[-95.75169099999999,29.776971],"type":"Point"}
}