{
  "type": "Feature",
  "properties": {
    "iso:country":"US",
    "sg:address":"6101 S Broadway Ave",
    "sg:city":"Tyler",
    "sg:classifiers":[
        {
            "category":"Banks & Credit Unions",
            "subcategory":"Bank",
            "type":"Services"
        }
    ],
    "sg:phone":"+1 903 534 6400",
    "sg:postcode":"75703",
    "sg:province":"TX",
    "sg:tags":[
        "national",
        "commercial"
    ],
    "wof:name":"Bank Of America",
    "wof:placetype":"venue"
},
  "geometry": {"coordinates":[-95.30507900000001,32.283494],"type":"Point"}
}