{
  "type": "Feature",
  "properties": {
    "iso:country":"US",
    "sg:address":"9412 McCombs St",
    "sg:city":"El Paso",
    "sg:classifiers":[
        {
            "category":"Retail",
            "subcategory":"Auto Repair",
            "type":"Services"
        }
    ],
    "sg:phone":"+1 915 755 9991",
    "sg:postcode":"79924",
    "sg:province":"TX",
    "sg:tags":[
        "repairing",
        "automobile"
    ],
    "wof:name":"Haaz Body Shop",
    "wof:placetype":"venue"
},
  "geometry": {"coordinates":[-106.406211,31.877871],"type":"Point"}
}