{
  "type": "Feature",
  "properties": {
    "iso:country":"US",
    "sg:address":"8828 N Stemmons Fwy",
    "sg:city":"Dallas",
    "sg:classifiers":[
        {
            "category":"Manufacturing",
            "subcategory":"Printing",
            "type":"Manufacturing & Wholesale Goods"
        }
    ],
    "sg:phone":"+1 214 630 8871",
    "sg:postcode":"75247",
    "sg:province":"TX",
    "sg:tags":[
        "printer"
    ],
    "wof:name":"Printing & Imaging Assn",
    "wof:placetype":"venue"
},
  "geometry": {"coordinates":[-96.874267,32.833563],"type":"Point"}
}