{
  "type": "Feature",
  "properties": {
    "iso:country":"US",
    "sg:address":"3807 Woodbrook Cir",
    "sg:city":"Austin",
    "sg:classifiers":[
        {
            "category":"Building & Trades",
            "subcategory":"Equipment Rental",
            "type":"Services"
        }
    ],
    "sg:phone":"+1 512 338 1018",
    "sg:postcode":"78759",
    "sg:province":"TX",
    "sg:tags":[
        "yard",
        "leasing",
        "store"
    ],
    "wof:name":"Mopac Leasing, Inc.",
    "wof:placetype":"venue"
},
  "geometry": {"coordinates":[-97.747947,30.374004],"type":"Point"}
}