{
  "type": "Feature",
  "properties": {
    "iso:country":"US",
    "sg:address":"6610 Harwin Dr",
    "sg:city":"Houston",
    "sg:classifiers":[
        {
            "category":"Health Services",
            "subcategory":"Hospital",
            "type":"Services"
        }
    ],
    "sg:phone":"+1 832 242 2273",
    "sg:postcode":"77036",
    "sg:province":"TX",
    "sg:tags":[
        "ambulance"
    ],
    "wof:name":"Victory Health Ambulance Services Inc",
    "wof:placetype":"venue"
},
  "geometry": {"coordinates":[-95.498283,29.719474],"type":"Point"}
}