{
  "type": "Feature",
  "properties": {
    "iso:country":"US",
    "sg:address":"26706 Eastwood Dr",
    "sg:city":"Spring",
    "sg:classifiers":[
        {
            "category":"Building & Trades",
            "subcategory":"Construction",
            "type":"Services"
        }
    ],
    "sg:phone":"+1 281 923 9987",
    "sg:postcode":"77386",
    "sg:province":"TX",
    "sg:tags":[
        "resurfacing",
        "floor",
        "laying",
        "refinishing",
        "contractor"
    ],
    "wof:name":"Lovett Hardwood Floors LLC",
    "wof:placetype":"venue"
},
  "geometry": {"coordinates":[-95.44335599999999,30.15377],"type":"Point"}
}