{
  "type": "Feature",
  "properties": {
    "iso:country":"US",
    "sg:address":"500 W Jefferson Blvd",
    "sg:city":"Dallas",
    "sg:classifiers":[
        {
            "category":"Shopping",
            "subcategory":"Pharmacy",
            "type":"Retail Goods"
        }
    ],
    "sg:phone":"+1 214 946 2152",
    "sg:postcode":"75208",
    "sg:province":"TX",
    "sg:tags":[
        "drugstore"
    ],
    "wof:name":"Raven's Nest Pharmacy",
    "wof:placetype":"venue"
},
  "geometry": {"coordinates":[-96.83049800000001,32.743198],"type":"Point"}
}