{
  "type": "Feature",
  "properties": {
    "iso:country":"US",
    "sg:address":"1904 Robbins Pl",
    "sg:city":"Austin",
    "sg:classifiers":[
        {
            "category":"Professional",
            "type":"Services"
        },
        {
            "category":"Professional",
            "subcategory":"Management & Consulting",
            "type":"Services"
        }
    ],
    "sg:phone":"+1 512 478 7226",
    "sg:postcode":"78705",
    "sg:province":"TX",
    "sg:tags":[
        "establishment",
        "business"
    ],
    "wof:name":"Hassler Suzanne Dramaturg",
    "wof:placetype":"venue"
},
  "geometry": {"coordinates":[-97.749397,30.28548],"type":"Point"}
}