{
  "type": "Feature",
  "properties": {
    "iso:country":"US",
    "sg:address":"1548 11th St",
    "sg:city":"Huntsville",
    "sg:classifiers":[
        {
            "category":"Personal",
            "subcategory":"Beauty Salon",
            "type":"Services"
        }
    ],
    "sg:phone":"+1 936 291 6776",
    "sg:postcode":"77320",
    "sg:province":"TX",
    "sg:tags":[
        "shop"
    ],
    "wof:name":"Crossley Brandie Salon",
    "wof:placetype":"venue"
},
  "geometry": {"coordinates":[-95.556181,30.723615],"type":"Point"}
}