{
  "type": "Feature",
  "properties": {
    "iso:country":"US",
    "sg:address":"5255 Beechnut St",
    "sg:city":"Houston",
    "sg:classifiers":[
        {
            "category":"Shopping",
            "subcategory":"Florist",
            "type":"Retail Goods"
        }
    ],
    "sg:phone":"+1 281 556 6009",
    "sg:postcode":"77096",
    "sg:province":"TX",
    "wof:name":"Elysian Fields Florist Inc",
    "wof:placetype":"venue"
},
  "geometry": {"coordinates":[-95.471846,29.689106],"type":"Point"}
}