{
  "type": "Feature",
  "properties": {
    "iso:country":"US",
    "sg:address":"17018 Turkey Point St",
    "sg:city":"San Antonio",
    "sg:classifiers":[
        {
            "category":"Real Estate",
            "subcategory":"Real Estate Agent",
            "type":"Services"
        }
    ],
    "sg:phone":"+1 210 499 1469",
    "sg:postcode":"78232",
    "sg:province":"TX",
    "sg:tags":[
        "inspection"
    ],
    "wof:name":"Carlson Home Inspection",
    "wof:placetype":"venue"
},
  "geometry": {"coordinates":[-98.441519,29.590882],"type":"Point"}
}