{
  "type": "Feature",
  "properties": {
    "iso:country":"US",
    "sg:address":"2888 S Richey St",
    "sg:city":"Houston",
    "sg:classifiers":[
        {
            "category":"Retail",
            "subcategory":"Auto Repair",
            "type":"Services"
        }
    ],
    "sg:phone":"+1 713 944 3372",
    "sg:postcode":"77017",
    "sg:province":"TX",
    "wof:name":"C D Automotive",
    "wof:placetype":"venue"
},
  "geometry": {"coordinates":[-95.231765,29.676961],"type":"Point"}
}