{
  "type": "Feature",
  "properties": {
    "iso:country":"US",
    "sg:address":"104 W 1st St",
    "sg:city":"Marfa",
    "sg:classifiers":[
        {
            "category":"Recreation",
            "type":"Entertainment"
        }
    ],
    "sg:phone":"+1 432 729 4201",
    "sg:postcode":"79843",
    "sg:province":"TX",
    "sg:tags":[
        "instruction",
        "yoga"
    ],
    "wof:name":"Yoga Marfa",
    "wof:placetype":"venue"
},
  "geometry": {"coordinates":[-104.02311,30.31658],"type":"Point"}
}