{
  "type": "Feature",
  "properties": {
    "iso:country":"US",
    "sg:address":"4914 Tamarisk St",
    "sg:city":"Bellaire",
    "sg:classifiers":[
        {
            "category":"Professional",
            "subcategory":"Research",
            "type":"Services"
        }
    ],
    "sg:phone":"+1 713 668 5844",
    "sg:postcode":"77401",
    "sg:province":"TX",
    "wof:name":"Christopher Machado",
    "wof:placetype":"venue"
},
  "geometry": {"coordinates":[-95.467771,29.716142],"type":"Point"}
}