{
  "type": "Feature",
  "properties": {
    "iso:country":"US",
    "sg:address":"10741 Reyes Canyons",
    "sg:city":"Helotes",
    "sg:classifiers":[
        {
            "category":"Real Estate",
            "subcategory":"Real Estate Agent",
            "type":"Services"
        }
    ],
    "sg:phone":"+1 210 695 5786",
    "sg:postcode":"78023",
    "sg:province":"TX",
    "wof:name":"Carey Properties Inc",
    "wof:placetype":"venue"
},
  "geometry": {"coordinates":[-98.704911,29.59103],"type":"Point"}
}