{
  "type": "Feature",
  "properties": {
    "iso:country":"US",
    "sg:address":"2404 Morrison Dr",
    "sg:city":"Big Spring",
    "sg:classifiers":[
        {
            "category":"Farming",
            "subcategory":"Farm",
            "type":"Manufacturing & Wholesale Goods"
        }
    ],
    "sg:phone":"+1 432 267 1764",
    "sg:postcode":"79720",
    "sg:province":"TX",
    "sg:tags":[
        "crop",
        "general"
    ],
    "wof:name":"A & B Farms Inc",
    "wof:placetype":"venue"
},
  "geometry": {"coordinates":[-101.441599,32.247166],"type":"Point"}
}