{
  "type": "Feature",
  "properties": {
    "iso:country":"US",
    "sg:address":"7511 Grapevine Hwy",
    "sg:city":"N Richland Hills",
    "sg:classifiers":[
        {
            "category":"Food & Beverages",
            "subcategory":"Groceries & Convenience Stores",
            "type":"Retail Goods"
        }
    ],
    "sg:phone":"+1 817 581 9544",
    "sg:postcode":"76180",
    "sg:province":"TX",
    "wof:name":"A & B Convenient Food Mart",
    "wof:placetype":"venue"
},
  "geometry": {"coordinates":[-97.22035700000001,32.829469],"type":"Point"}
}