{
  "type": "Feature",
  "properties": {
    "iso:country":"US",
    "sg:address":"4640 FM 1374",
    "sg:city":"Huntsville",
    "sg:classifiers":[
        {
            "category":"Mining & Drilling",
            "type":"Manufacturing & Wholesale Goods"
        }
    ],
    "sg:phone":"+1 936 291 7273",
    "sg:postcode":"77340",
    "sg:province":"TX",
    "sg:tags":[
        "mineral"
    ],
    "wof:name":"Rock Shop",
    "wof:placetype":"venue"
},
  "geometry": {"coordinates":[-95.499436,30.548336],"type":"Point"}
}