{
  "type": "Feature",
  "properties": {
    "iso:country":"US",
    "sg:address":"15325 Wallisville Rd",
    "sg:city":"Houston",
    "sg:classifiers":[
        {
            "category":"Restaurant",
            "type":"Food & Drink"
        }
    ],
    "sg:menulink":"http://www.allmenus.com/tx/houston/70551-pizza-hut/menu/",
    "sg:phone":"+1 281 458 7929",
    "sg:postcode":"77049",
    "sg:province":"TX",
    "sg:tags":[
        "american",
        "pizza"
    ],
    "wof:name":"Pizza Hut",
    "wof:placetype":"venue"
},
  "geometry": {"coordinates":[-95.166961,29.80823],"type":"Point"}
}