{
  "type": "Feature",
  "properties": {
    "iso:country":"US",
    "sg:address":"3916 Kemp Blvd",
    "sg:city":"Wichita Falls",
    "sg:classifiers":[
        {
            "category":"Personal",
            "subcategory":"Beauty Salon",
            "type":"Services"
        }
    ],
    "sg:phone":"+1 940 691 0066",
    "sg:postcode":"76308",
    "sg:province":"TX",
    "sg:tags":[
        "shop"
    ],
    "wof:name":"Crystal Nails",
    "wof:placetype":"venue"
},
  "geometry": {"coordinates":[-98.534623,33.87197],"type":"Point"}
}