{
  "type": "Feature",
  "properties": {
    "iso:country":"US",
    "sg:address":"142 S Dalton St",
    "sg:city":"Bartlett",
    "sg:classifiers":[
        {
            "category":"Wholesale",
            "subcategory":"Farm Supplies",
            "type":"Manufacturing & Wholesale Goods"
        }
    ],
    "sg:phone":"+1 254 527 4433",
    "sg:postcode":"76511",
    "sg:province":"TX",
    "sg:tags":[
        "fertilizer"
    ],
    "wof:name":"Steglich Feed & Farm Supply",
    "wof:placetype":"venue"
},
  "geometry": {"coordinates":[-97.426059,30.794519],"type":"Point"}
}