{
  "type": "Feature",
  "properties": {
    "iso:country":"US",
    "sg:address":"8070 Park Ln Ste 100",
    "sg:city":"Dallas",
    "sg:classifiers":[
        {
            "category":"Shopping Center",
            "type":"Public Place"
        }
    ],
    "sg:phone":"+1 214 369 0860",
    "sg:postcode":"75231",
    "sg:province":"TX",
    "wof:name":"The Shops at Park Lane",
    "wof:placetype":"venue"
},
  "geometry": {"coordinates":[-96.768576,32.87118],"type":"Point"}
}