{
  "type": "Feature",
  "properties": {
    "iso:country":"US",
    "sg:address":"1602 Lohmans Xing Rd",
    "sg:city":"Austin",
    "sg:classifiers":[
        {
            "category":"Health Services",
            "subcategory":"Podiatrist",
            "type":"Services"
        }
    ],
    "sg:phone":"+1 512 733 8600",
    "sg:postcode":"78734",
    "sg:province":"TX",
    "wof:name":"Foot Associates Of Central Tx",
    "wof:placetype":"venue"
},
  "geometry": {"coordinates":[-97.98100700000001,30.365794],"type":"Point"}
}