{
  "type": "Feature",
  "properties": {
    "iso:country":"US",
    "sg:address":"627 W George St",
    "sg:city":"Port Lavaca",
    "sg:classifiers":[
        {
            "category":"Social Services",
            "subcategory":"Child Care",
            "type":"Services"
        }
    ],
    "sg:phone":"+1 361 552 9787",
    "sg:postcode":"77979",
    "sg:province":"TX",
    "sg:tags":[
        "kindergarten",
        "academic",
        "school"
    ],
    "wof:name":"Victoria Head Start Child Dev",
    "wof:placetype":"venue"
},
  "geometry": {"coordinates":[-96.63298899999999,28.615356],"type":"Point"}
}