{
  "type": "Feature",
  "properties": {
    "iso:country":"US",
    "sg:address":"2921 S Cooper St",
    "sg:city":"Arlington",
    "sg:classifiers":[
        {
            "category":"Retail",
            "subcategory":"Auto Repair",
            "type":"Services"
        }
    ],
    "sg:phone":"+1 817 460 2453",
    "sg:postcode":"76015",
    "sg:province":"TX",
    "sg:tags":[
        "repairing",
        "automobile"
    ],
    "wof:name":"Ignition Pros",
    "wof:placetype":"venue"
},
  "geometry": {"coordinates":[-97.126329,32.694546],"type":"Point"}
}