{
  "type": "Feature",
  "properties": {
    "iso:country":"US",
    "sg:address":"4120 International Pkwy",
    "sg:city":"Carrollton",
    "sg:classifiers":[
        {
            "category":"Professional",
            "type":"Services"
        }
    ],
    "sg:phone":"+1 972 820 6648",
    "sg:postcode":"75007",
    "sg:province":"TX",
    "sg:tags":[
        "establishment"
    ],
    "wof:name":"HBW",
    "wof:placetype":"venue"
},
  "geometry": {"coordinates":[-96.847267,33.020491],"type":"Point"}
}