{
  "type": "Feature",
  "properties": {
    "iso:country":"US",
    "sg:address":"1912 Crepe Myrtle Dr",
    "sg:city":"Lancaster",
    "sg:classifiers":[
        {
            "category":"Organizations",
            "subcategory":"Religious Organization",
            "type":"Services"
        }
    ],
    "sg:phone":"+1 972 227 0396",
    "sg:postcode":"75146",
    "sg:province":"TX",
    "wof:name":"Progressive Revelation Church",
    "wof:placetype":"venue"
},
  "geometry": {"coordinates":[-96.792396,32.592728],"type":"Point"}
}