{
  "type": "Feature",
  "properties": {
    "iso:country":"US",
    "sg:address":"2306 Garden City Hwy",
    "sg:city":"Midland",
    "sg:classifiers":[
        {
            "category":"Wholesale",
            "subcategory":"Machinery & Supplies",
            "type":"Manufacturing & Wholesale Goods"
        }
    ],
    "sg:phone":"+1 432 684 4114",
    "sg:postcode":"79701",
    "sg:province":"TX",
    "sg:tags":[
        "field",
        "oil"
    ],
    "wof:name":"Adkins Supply Inc",
    "wof:placetype":"venue"
},
  "geometry": {"coordinates":[-102.046553,31.9849],"type":"Point"}
}