{
  "type": "Feature",
  "properties": {
    "iso:country":"US",
    "sg:address":"11652 Southwest Fwy",
    "sg:city":"Houston",
    "sg:classifiers":[
        {
            "category":"Personal",
            "subcategory":"Beauty Salon",
            "type":"Services"
        }
    ],
    "sg:phone":"+1 281 988 9120",
    "sg:postcode":"77031",
    "sg:province":"TX",
    "wof:name":"Beauty Switch Hair Salon",
    "wof:placetype":"venue"
},
  "geometry": {"coordinates":[-95.567601,29.651495],"type":"Point"}
}