{
  "type": "Feature",
  "properties": {
    "iso:country":"US",
    "sg:address":"5876 Co Rd 447",
    "sg:city":"Laneville",
    "sg:classifiers":[
        {
            "category":"Freight",
            "type":"Transportation"
        }
    ],
    "sg:phone":"+1 903 854 2483",
    "sg:postcode":"75667",
    "sg:province":"TX",
    "sg:tags":[
        "delivery"
    ],
    "wof:name":"BJDJ Svc",
    "wof:placetype":"venue"
},
  "geometry": {"coordinates":[-94.832689,32.046546],"type":"Point"}
}