{
  "type": "Feature",
  "properties": {
    "iso:country":"US",
    "sg:address":"630 N Hwy 67",
    "sg:city":"Cedar Hill",
    "sg:classifiers":[
        {
            "category":"Banks & Credit Unions",
            "subcategory":"Bank",
            "type":"Services"
        }
    ],
    "sg:phone":"+1 469 272 3800",
    "sg:postcode":"75104",
    "sg:province":"TX",
    "sg:tags":[
        "mortgage"
    ],
    "wof:name":"Amerinet Mortgage",
    "wof:placetype":"venue"
},
  "geometry": {"coordinates":[-96.932051,32.602771],"type":"Point"}
}