{
  "type": "Feature",
  "properties": {
    "iso:country":"US",
    "sg:address":"3508 50th St",
    "sg:city":"Lubbock",
    "sg:classifiers":[
        {
            "category":"Real Estate",
            "subcategory":"Real Estate Operator",
            "type":"Services"
        }
    ],
    "sg:phone":"+1 806 795 4427",
    "sg:postcode":"79413",
    "sg:province":"TX",
    "sg:tags":[
        "apartment"
    ],
    "wof:name":"Town Plaza Apartments",
    "wof:placetype":"venue"
},
  "geometry": {"coordinates":[-101.89193299999999,33.548831],"type":"Point"}
}