{
  "type": "Feature",
  "properties": {
    "iso:country":"US",
    "sg:address":"1220 Nantucket Dr",
    "sg:city":"Richardson",
    "sg:classifiers":[
        {
            "category":"Professional",
            "subcategory":"Detective & Security Services",
            "type":"Services"
        }
    ],
    "sg:phone":"+1 972 661 1243",
    "sg:postcode":"75080",
    "sg:province":"TX",
    "sg:tags":[
        "system"
    ],
    "wof:name":"Spear Security",
    "wof:placetype":"venue"
},
  "geometry": {"coordinates":[-96.74078900000001,32.967211],"type":"Point"}
}