{
  "type": "Feature",
  "properties": {
    "iso:country":"US",
    "sg:address":"10101 Harwin Dr",
    "sg:city":"Houston",
    "sg:classifiers":[
        {
            "category":"Professional",
            "subcategory":"Employment Agencies",
            "type":"Services"
        }
    ],
    "sg:phone":"+1 713 270 8383",
    "sg:postcode":"77036",
    "sg:province":"TX",
    "wof:name":"Acrux Staffing",
    "wof:placetype":"venue"
},
  "geometry": {"coordinates":[-95.540561,29.717727],"type":"Point"}
}