{
  "type": "Feature",
  "properties": {
    "iso:country":"US",
    "sg:address":"1325 S Creek",
    "sg:city":"Houston",
    "sg:classifiers":[
        {
            "category":"Wholesale",
            "subcategory":"Wine & Distilled Alcoholic Beverages",
            "type":"Manufacturing & Wholesale Goods"
        }
    ],
    "sg:phone":"+1 281 829 1114",
    "sg:postcode":"77084",
    "sg:province":"TX",
    "sg:tags":[
        "liquor"
    ],
    "sg:website":"www.mexcor.com",
    "wof:name":"Mexcor Liquor Importers & Dist",
    "wof:placetype":"venue"
},
  "geometry": {"coordinates":[-95.67661699999999,29.789219],"type":"Point"}
}