{
  "type": "Feature",
  "properties": {
    "iso:country":"US",
    "sg:address":"710 W Pipeline Rd",
    "sg:city":"Hurst",
    "sg:classifiers":[
        {
            "category":"Personal",
            "subcategory":"Beauty Salon",
            "type":"Services"
        }
    ],
    "sg:phone":"+1 817 282 6294",
    "sg:postcode":"76053",
    "sg:province":"TX",
    "sg:tags":[
        "shop"
    ],
    "wof:name":"Mary's Beauty Salon",
    "wof:placetype":"venue"
},
  "geometry": {"coordinates":[-97.186227,32.823724],"type":"Point"}
}