{
  "type": "Feature",
  "properties": {
    "iso:country":"US",
    "sg:address":"4109 Garrison Ave",
    "sg:city":"Fort Worth",
    "sg:classifiers":[
        {
            "category":"Wholesale",
            "subcategory":"Non-durable Goods",
            "type":"Manufacturing & Wholesale Goods"
        }
    ],
    "sg:phone":"+1 817 531 8478",
    "sg:postcode":"76119",
    "sg:province":"TX",
    "wof:name":"Shop & Save Wholesaler",
    "wof:placetype":"venue"
},
  "geometry": {"coordinates":[-97.261797,32.704304],"type":"Point"}
}