{
  "type": "Feature",
  "properties": {
    "iso:country":"US",
    "sg:address":"8080 Harwin Dr",
    "sg:city":"Houston",
    "sg:classifiers":[
        {
            "category":"Home & Garden",
            "subcategory":"Furniture",
            "type":"Retail Goods"
        }
    ],
    "sg:phone":"+1 832 242 0820",
    "sg:postcode":"77036",
    "sg:province":"TX",
    "sg:tags":[
        "bedding"
    ],
    "wof:name":"Blanket El Paraiso",
    "wof:placetype":"venue"
},
  "geometry": {"coordinates":[-95.526359,29.718009],"type":"Point"}
}