{
  "type": "Feature",
  "properties": {
    "iso:country":"US",
    "sg:address":"4402 Vance Jackson Rd",
    "sg:city":"San Antonio",
    "sg:classifiers":[
        {
            "category":"Insurance",
            "subcategory":"Hazard Insurance",
            "type":"Services"
        }
    ],
    "sg:phone":"+1 210 979 8104",
    "sg:postcode":"78230",
    "sg:province":"TX",
    "sg:tags":[
        "employee",
        "benefit",
        "compensation",
        "plan"
    ],
    "wof:name":"Benefit Plans Keystone",
    "wof:placetype":"venue"
},
  "geometry": {"coordinates":[-98.535053,29.518388],"type":"Point"}
}