{
  "type": "Feature",
  "properties": {
    "iso:country":"US",
    "sg:address":"207 Windy Hollow Ln",
    "sg:city":"Kyle",
    "sg:classifiers":[
        {
            "category":"Shopping",
            "subcategory":"Computers & Home Electronics",
            "type":"Retail Goods"
        }
    ],
    "sg:phone":"+1 512 268 5626",
    "sg:postcode":"78640",
    "sg:province":"TX",
    "sg:tags":[
        "equipment",
        "satellite",
        "system"
    ],
    "wof:name":"Cozmic Debris",
    "wof:placetype":"venue"
},
  "geometry": {"coordinates":[-97.807035,30.024674],"type":"Point"}
}