{
  "type": "Feature",
  "properties": {
    "iso:country":"US",
    "sg:address":"311 Ave F",
    "sg:city":"Hart",
    "sg:classifiers":[
        {
            "category":"Professional",
            "type":"Services"
        }
    ],
    "sg:phone":"+1 806 938 2322",
    "sg:postcode":"79043",
    "sg:province":"TX",
    "sg:tags":[
        "establishment"
    ],
    "wof:name":"Ruby's Beauty Shop",
    "wof:placetype":"venue"
},
  "geometry": {"coordinates":[-102.112448,34.386154],"type":"Point"}
}