{
  "type": "Feature",
  "properties": {
    "iso:country":"US",
    "sg:address":"7861 Creekview Dr",
    "sg:city":"Frisco",
    "sg:classifiers":[
        {
            "category":"Shopping",
            "type":"Retail Goods"
        }
    ],
    "sg:phone":"+1 972 335 0374",
    "sg:postcode":"75034",
    "sg:province":"TX",
    "sg:tags":[
        "merchandise"
    ],
    "wof:name":"Homeshoppingbazaar Co",
    "wof:placetype":"venue"
},
  "geometry": {"coordinates":[-96.815871,33.147507],"type":"Point"}
}