{
  "type": "Feature",
  "properties": {
    "iso:country":"US",
    "sg:address":"9223 Ponderosa Ln",
    "sg:city":"Houston",
    "sg:classifiers":[
        {
            "category":"Home & Garden",
            "subcategory":"Furniture",
            "type":"Retail Goods"
        },
        {
            "category":"Building & Trades",
            "subcategory":"Construction",
            "type":"Services"
        },
        {
            "category":"Manufacturing",
            "subcategory":"Building Materials",
            "type":"Manufacturing & Wholesale Goods"
        },
        {
            "category":"Wholesale",
            "subcategory":"Home Furnishings",
            "type":"Manufacturing & Wholesale Goods"
        }
    ],
    "sg:phone":"+1 713 271 0609",
    "sg:postcode":"77074",
    "sg:province":"TX",
    "sg:tags":[
        "industrial",
        "equipment-wholesale",
        "cabinetmakers-commercial",
        "kitchen",
        "equipment-household",
        "cabinet",
        "maker",
        "manufacturer"
    ],
    "sg:website":"http://www.maxscabinets.com",
    "wof:name":"Max Cabinets",
    "wof:placetype":"venue"
},
  "geometry": {"coordinates":[-95.53925,29.674902],"type":"Point"}
}