{
  "type": "Feature",
  "properties": {
    "iso:country":"US",
    "sg:address":"17451 Dallas Pkwy",
    "sg:city":"Dallas",
    "sg:classifiers":[
        {
            "category":"Professional",
            "subcategory":"Advertising",
            "type":"Services"
        },
        {
            "category":"Professional",
            "subcategory":"Business Services",
            "type":"Services"
        }
    ],
    "sg:phone":"+1 972 931 0042",
    "sg:postcode":"75287",
    "sg:province":"TX",
    "sg:tags":[
        "advertising-promotional",
        "product",
        "system",
        "form"
    ],
    "wof:name":"Safeguard Business System",
    "wof:placetype":"venue"
},
  "geometry": {"coordinates":[-96.828734,32.98816],"type":"Point"}
}