{
  "type": "Feature",
  "properties": {
    "iso:country":"US",
    "sg:address":"2205 W Lucas Rd",
    "sg:city":"Allen",
    "sg:classifiers":[
        {
            "category":"Farming",
            "subcategory":"Livestock Farm",
            "type":"Manufacturing & Wholesale Goods"
        }
    ],
    "sg:phone":"+1 972 727 5293",
    "sg:postcode":"75002",
    "sg:province":"TX",
    "sg:tags":[
        "feedlot",
        "grain",
        "cash",
        "beef",
        "cattle"
    ],
    "wof:name":"Four BS Delbeith",
    "wof:placetype":"venue"
},
  "geometry": {"coordinates":[-96.608091,33.085485],"type":"Point"}
}