{
  "type": "Feature",
  "properties": {
    "iso:country":"US",
    "sg:address":"425 Wildwood Ln",
    "sg:city":"Burleson",
    "sg:classifiers":[
        {
            "category":"Professional",
            "subcategory":"Business Services",
            "type":"Services"
        }
    ],
    "sg:phone":"+1 817 447 7718",
    "sg:postcode":"76028",
    "sg:province":"TX",
    "wof:name":"Novus Group Ltd Liability",
    "wof:placetype":"venue"
},
  "geometry": {"coordinates":[-97.361429,32.501844],"type":"Point"}
}