{
  "type": "Feature",
  "properties": {
    "iso:country":"US",
    "sg:address":"2518 Richmond Ave",
    "sg:city":"Houston",
    "sg:classifiers":[
        {
            "category":"Health Services",
            "subcategory":"Optometrist",
            "type":"Services"
        }
    ],
    "sg:phone":"+1 713 522 2522",
    "sg:postcode":"77098",
    "sg:province":"TX",
    "sg:tags":[
        "ophthalmologist"
    ],
    "wof:name":"Perfect Vision",
    "wof:placetype":"venue"
},
  "geometry": {"coordinates":[-95.41770200000001,29.734301],"type":"Point"}
}