{
  "type": "Feature",
  "properties": {
    "iso:country":"US",
    "sg:address":"8177 Indian Trl",
    "sg:city":"Sanger",
    "sg:classifiers":[
        {
            "category":"Retail",
            "subcategory":"Repair Shop",
            "type":"Services"
        }
    ],
    "sg:phone":"+1 940 482 6314",
    "sg:postcode":"76266",
    "sg:province":"TX",
    "sg:tags":[
        "lock",
        "locksmith"
    ],
    "wof:name":"Longhorn Locksmith",
    "wof:placetype":"venue"
},
  "geometry": {"coordinates":[-97.264523,33.319266],"type":"Point"}
}