{
  "type": "Feature",
  "properties": {
    "iso:country":"US",
    "sg:address":"5228 Pete Payan Dr",
    "sg:city":"El Paso",
    "sg:classifiers":[
        {
            "category":"Wholesale",
            "subcategory":"Hardware",
            "type":"Manufacturing & Wholesale Goods"
        }
    ],
    "sg:phone":"+1 915 726 3192",
    "sg:postcode":"79912",
    "sg:province":"TX",
    "sg:tags":[
        "heating",
        "supply"
    ],
    "wof:name":"Laser Industrial",
    "wof:placetype":"venue"
},
  "geometry": {"coordinates":[-106.529381,31.812044],"type":"Point"}
}