{
  "type": "Feature",
  "properties": {
    "iso:country":"US",
    "sg:address":"9715 Stella Link Rd",
    "sg:city":"Houston",
    "sg:classifiers":[
        {
            "category":"Food & Beverages",
            "subcategory":"Groceries & Convenience Stores",
            "type":"Retail Goods"
        }
    ],
    "sg:phone":"+1 713 661 9725",
    "sg:postcode":"77025",
    "sg:province":"TX",
    "wof:name":"Sunnys Food Store",
    "wof:placetype":"venue"
},
  "geometry": {"coordinates":[-95.439876,29.678244],"type":"Point"}
}