{
  "type": "Feature",
  "properties": {
    "iso:country":"US",
    "sg:address":"2635 E Ann Arbor Ave",
    "sg:city":"Dallas",
    "sg:classifiers":[
        {
            "category":"Place Of Worship",
            "subcategory":"Church",
            "type":"Public Place"
        },
        {
            "category":"Place Of Worship",
            "type":"Public Place"
        },
        {
            "category":"Place Of Worship",
            "subcategory":"Temple",
            "type":"Public Place"
        },
        {
            "category":"Organizations",
            "subcategory":"Religious Organization",
            "type":"Services"
        }
    ],
    "sg:phone":"+1 214 371 1777",
    "sg:postcode":"75216",
    "sg:province":"TX",
    "sg:tags":[
        "churches-interdenominational",
        "churches-various",
        "denomination"
    ],
    "wof:name":"Bible Temple Christian Center",
    "wof:placetype":"venue"
},
  "geometry": {"coordinates":[-96.77889999999999,32.701099],"type":"Point"}
}