{
  "type": "Feature",
  "properties": {
    "iso:country":"US",
    "sg:address":"610 S Sherman St",
    "sg:city":"Richardson",
    "sg:classifiers":[
        {
            "category":"Retail",
            "subcategory":"Auto Repair",
            "type":"Services"
        }
    ],
    "sg:phone":"+1 972 231 9292",
    "sg:postcode":"75081",
    "sg:province":"TX",
    "wof:name":"Day Custom Engine",
    "wof:placetype":"venue"
},
  "geometry": {"coordinates":[-96.73733199999999,32.9444],"type":"Point"}
}