{
  "type": "Feature",
  "properties": {
    "iso:country":"US",
    "sg:address":"1427 W 2nd Ave",
    "sg:city":"Corsicana",
    "sg:classifiers":[
        {
            "category":"Shopping",
            "subcategory":"Books",
            "type":"Retail Goods"
        }
    ],
    "sg:phone":"+1 903 875 1141",
    "sg:postcode":"75110",
    "sg:province":"TX",
    "wof:name":"Bookstack",
    "wof:placetype":"venue"
},
  "geometry": {"coordinates":[-96.480243,32.090102],"type":"Point"}
}