{
  "type": "Feature",
  "properties": {
    "iso:country":"US",
    "sg:address":"9405 Crownspoint Cir",
    "sg:city":"Austin",
    "sg:classifiers":[
        {
            "category":"Professional",
            "subcategory":"Secretarial Services",
            "type":"Services"
        }
    ],
    "sg:phone":"+1 512 282 1388",
    "sg:postcode":"78748",
    "sg:province":"TX",
    "sg:tags":[
        "reporting"
    ],
    "wof:name":"Oppenheimer Reporting Service",
    "wof:placetype":"venue"
},
  "geometry": {"coordinates":[-97.829217,30.181486],"type":"Point"}
}