{
  "type": "Feature",
  "properties": {
    "iso:country":"US",
    "sg:address":"5330 Winding Way Dr",
    "sg:city":"Houston",
    "sg:classifiers":[
        {
            "category":"Building & Trades",
            "subcategory":"Plumbing",
            "type":"Services"
        }
    ],
    "sg:phone":"+1 713 686 8270",
    "sg:postcode":"77091",
    "sg:province":"TX",
    "sg:tags":[
        "contractor"
    ],
    "wof:name":"Collins Joe Plumbing Services",
    "wof:placetype":"venue"
},
  "geometry": {"coordinates":[-95.465407,29.858119],"type":"Point"}
}