{
  "type": "Feature",
  "properties": {
    "iso:country":"US",
    "sg:address":"1402 Corinth St",
    "sg:city":"Dallas",
    "sg:classifiers":[
        {
            "category":"Retail",
            "subcategory":"Auto Repair",
            "type":"Services"
        }
    ],
    "sg:phone":"+1 972 317 6599",
    "sg:postcode":"75215",
    "sg:province":"TX",
    "sg:tags":[
        "glass",
        "replacement"
    ],
    "wof:name":"Accurate Auto Glass",
    "wof:placetype":"venue"
},
  "geometry": {"coordinates":[-96.78707199999999,32.766835],"type":"Point"}
}