{
  "type": "Feature",
  "properties": {
    "iso:country":"US",
    "sg:address":"415 S International Blvd",
    "sg:city":"Weslaco",
    "sg:classifiers":[
        {
            "category":"Banks & Credit Unions",
            "subcategory":"Investment Brokerage",
            "type":"Services"
        },
        {
            "category":"Professional",
            "subcategory":"Management & Consulting",
            "type":"Services"
        }
    ],
    "sg:phone":"+1 956 447 0517",
    "sg:postcode":"78596",
    "sg:province":"TX",
    "sg:tags":[
        "advisory",
        "financial"
    ],
    "wof:name":"Magellan Financial Group LLC",
    "wof:placetype":"venue"
},
  "geometry": {"coordinates":[-97.95826,26.153504],"type":"Point"}
}