{
  "type": "Feature",
  "properties": {
    "iso:country":"US",
    "sg:address":"2406 Wheeler St",
    "sg:city":"Houston",
    "sg:classifiers":[
        {
            "category":"Retail",
            "subcategory":"Veterinary Services",
            "type":"Services"
        }
    ],
    "sg:phone":"+1 713 528 6266",
    "sg:postcode":"77004",
    "sg:province":"TX",
    "sg:tags":[
        "hospital",
        "animal"
    ],
    "wof:name":"Dowling Animal Clinic",
    "wof:placetype":"venue"
},
  "geometry": {"coordinates":[-95.369344,29.725869],"type":"Point"}
}