{
  "type": "Feature",
  "properties": {
    "iso:country":"US",
    "sg:address":"2838 College Hills Blvd",
    "sg:city":"San Angelo",
    "sg:classifiers":[
        {
            "category":"Recreation",
            "type":"Entertainment"
        }
    ],
    "sg:phone":"+1 325 944 9683",
    "sg:postcode":"76904",
    "sg:province":"TX",
    "wof:name":"College Hills Driving Range",
    "wof:placetype":"venue"
},
  "geometry": {"coordinates":[-100.480419,31.434936],"type":"Point"}
}