{
  "type": "Feature",
  "properties": {
    "iso:country":"US",
    "sg:address":"1032 Pat Booker Rd",
    "sg:city":"Universal City",
    "sg:classifiers":[
        {
            "category":"Social Services",
            "subcategory":"Child Care",
            "type":"Services"
        }
    ],
    "sg:phone":"+1 210 658 5770",
    "sg:postcode":"78148",
    "sg:province":"TX",
    "sg:tags":[
        "school",
        "day"
    ],
    "wof:name":"Randolph Christian Academy",
    "wof:placetype":"venue"
},
  "geometry": {"coordinates":[-98.296336,29.550093],"type":"Point"}
}