{
  "type": "Feature",
  "properties": {
    "iso:country":"US",
    "sg:address":"10020 FM 1625",
    "sg:city":"Austin",
    "sg:classifiers":[
        {
            "category":"Building & Trades",
            "subcategory":"Construction",
            "type":"Services"
        }
    ],
    "sg:phone":"+1 512 293 7390",
    "sg:postcode":"78747",
    "sg:province":"TX",
    "sg:tags":[
        "house"
    ],
    "wof:name":"Yescas Sign Builders Inc",
    "wof:placetype":"venue"
},
  "geometry": {"coordinates":[-97.719668,30.113963],"type":"Point"}
}