{
  "type": "Feature",
  "properties": {
    "iso:country":"US",
    "sg:address":"25002 Arrow Glen",
    "sg:city":"San Antonio",
    "sg:classifiers":[
        {
            "category":"Professional",
            "type":"Services"
        }
    ],
    "sg:phone":"+1 210 497 4644",
    "sg:postcode":"78258",
    "sg:province":"TX",
    "wof:name":"Orient Expressions",
    "wof:placetype":"venue"
},
  "geometry": {"coordinates":[-98.49328300000001,29.641184],"type":"Point"}
}