{
  "type": "Feature",
  "properties": {
    "iso:country":"US",
    "sg:address":"2419 Luau St",
    "sg:city":"Mesquite",
    "sg:classifiers":[
        {
            "category":"Professional",
            "subcategory":"Management & Consulting",
            "type":"Services"
        }
    ],
    "sg:phone":"+1 972 270 6298",
    "sg:postcode":"75150",
    "sg:province":"TX",
    "wof:name":"Westerfield Marketing",
    "wof:placetype":"venue"
},
  "geometry": {"coordinates":[-96.65108600000001,32.799587],"type":"Point"}
}