{
  "type": "Feature",
  "properties": {
    "iso:country":"US",
    "sg:address":"2665 Freewood Dr",
    "sg:city":"Dallas",
    "sg:classifiers":[
        {
            "category":"Taxi",
            "type":"Transportation"
        }
    ],
    "sg:phone":"+1 214 350 4600",
    "sg:postcode":"75220",
    "sg:province":"TX",
    "sg:tags":[
        "taxicab"
    ],
    "wof:name":"Jet Taxi",
    "wof:placetype":"venue"
},
  "geometry": {"coordinates":[-96.885414,32.870584],"type":"Point"}
}