{
  "type": "Feature",
  "properties": {
    "iso:country":"US",
    "sg:address":"111 N Preston St",
    "sg:city":"Van Alstyne",
    "sg:classifiers":[
        {
            "category":"Retail",
            "subcategory":"Repair Shop",
            "type":"Services"
        }
    ],
    "sg:phone":"+1 903 482 2102",
    "sg:postcode":"75495",
    "sg:province":"TX",
    "sg:tags":[
        "repairing",
        "lawn",
        "mower"
    ],
    "wof:name":"Steve Hall Mower Repair",
    "wof:placetype":"venue"
},
  "geometry": {"coordinates":[-96.577285,33.424355],"type":"Point"}
}