{
  "type": "Feature",
  "properties": {
    "iso:country":"US",
    "sg:address":"26044 Old Fredericksburg Rd",
    "sg:city":"Boerne",
    "sg:classifiers":[
        {
            "category":"Personal",
            "subcategory":"Beauty Salon",
            "type":"Services"
        }
    ],
    "sg:phone":"+1 210 698 2079",
    "sg:postcode":"78015",
    "sg:province":"TX",
    "sg:tags":[
        "hair",
        "stylist"
    ],
    "wof:name":"Betty Friar Betts Designs",
    "wof:placetype":"venue"
},
  "geometry": {"coordinates":[-98.63871,29.685654],"type":"Point"}
}