{
  "type": "Feature",
  "properties": {
    "iso:country":"US",
    "sg:address":"11925 Loch Ness Dr",
    "sg:city":"Dallas",
    "sg:classifiers":[
        {
            "category":"Health Services",
            "subcategory":"Dentist",
            "type":"Services"
        }
    ],
    "sg:phone":"+1 214 341 4733",
    "sg:postcode":"75218",
    "sg:province":"TX",
    "wof:name":"Davis T Bob Dentist",
    "wof:placetype":"venue"
},
  "geometry": {"coordinates":[-96.689499,32.8592],"type":"Point"}
}