{
  "type": "Feature",
  "properties": {
    "iso:country":"US",
    "sg:address":"2609 Twin Oaks Dr",
    "sg:city":"Vernon",
    "sg:classifiers":[
        {
            "category":"Real Estate",
            "subcategory":"Real Estate Agent",
            "type":"Services"
        }
    ],
    "sg:phone":"+1 940 553 3200",
    "sg:postcode":"76384",
    "sg:province":"TX",
    "wof:name":"Holt Appraisal",
    "wof:placetype":"venue"
},
  "geometry": {"coordinates":[-99.310264,34.139779],"type":"Point"}
}