{
  "type": "Feature",
  "properties": {
    "iso:country":"US",
    "sg:address":"2033 Fm 609",
    "sg:city":"Flatonia",
    "sg:classifiers":[
        {
            "category":"Building & Trades",
            "subcategory":"Equipment Rental",
            "type":"Services"
        }
    ],
    "sg:phone":"+1 361 865 2142",
    "sg:postcode":"78941",
    "sg:province":"TX",
    "sg:tags":[
        "field",
        "oil"
    ],
    "wof:name":"Sellers' Pump & Supply",
    "wof:placetype":"venue"
},
  "geometry": {"coordinates":[-97.09228299999999,29.699836],"type":"Point"}
}