{
  "type": "Feature",
  "properties": {
    "iso:country":"US",
    "sg:address":"1975 Loop 431",
    "sg:city":"Quemado",
    "sg:classifiers":[
        {
            "category":"Health Services",
            "subcategory":"Doctor",
            "type":"Services"
        }
    ],
    "sg:phone":"+1 830 757 6761",
    "sg:postcode":"78852",
    "sg:province":"TX",
    "sg:tags":[
        "physician",
        "surgeon"
    ],
    "wof:name":"Ricardo Cigarroa MD",
    "wof:placetype":"venue"
},
  "geometry": {"coordinates":[-100.476626,28.722581],"type":"Point"}
}