{
  "type": "Feature",
  "properties": {
    "iso:country":"US",
    "sg:address":"149 Aunt Sadie Dr",
    "sg:city":"Vidor",
    "sg:classifiers":[
        {
            "category":"Shopping",
            "subcategory":"Jewelry",
            "type":"Retail Goods"
        }
    ],
    "sg:phone":"+1 409 783 9780",
    "sg:postcode":"77662",
    "sg:province":"TX",
    "wof:name":"Cryer Jewelry & Repair",
    "wof:placetype":"venue"
},
  "geometry": {"coordinates":[-94.01856600000001,30.229967],"type":"Point"}
}