{
  "type": "Feature",
  "properties": {
    "iso:country":"US",
    "sg:address":"2800 W Parker Rd",
    "sg:city":"Plano",
    "sg:classifiers":[
        {
            "category":"Professional",
            "subcategory":"Accounting & Tax Preparation",
            "type":"Services"
        }
    ],
    "sg:phone":"+1 972 519 0000",
    "sg:postcode":"75075",
    "sg:province":"TX",
    "sg:tags":[
        "accountant"
    ],
    "wof:name":"Lam Po & Xu",
    "wof:placetype":"venue"
},
  "geometry": {"coordinates":[-96.75023899999999,33.040965],"type":"Point"}
}