{
  "type": "Feature",
  "properties": {
    "iso:country":"US",
    "sg:address":"314 Willet Dr",
    "sg:city":"Buda",
    "sg:classifiers":[
        {
            "category":"Building & Trades",
            "subcategory":"Construction",
            "type":"Services"
        }
    ],
    "sg:phone":"+1 512 892 6073",
    "sg:postcode":"78610",
    "sg:province":"TX",
    "sg:tags":[
        "nonresidential"
    ],
    "wof:name":"Accent Deck Design",
    "wof:placetype":"venue"
},
  "geometry": {"coordinates":[-97.863885,30.111244],"type":"Point"}
}