{
  "type": "Feature",
  "properties": {
    "iso:country":"US",
    "sg:address":"908 W Main St",
    "sg:city":"La Porte",
    "sg:classifiers":[
        {
            "category":"Professional",
            "type":"Services"
        }
    ],
    "sg:phone":"+1 281 487 2800",
    "sg:postcode":"77571",
    "sg:province":"TX",
    "wof:name":"Great Blue Corp",
    "wof:placetype":"venue"
},
  "geometry": {"coordinates":[-95.02775200000001,29.665466],"type":"Point"}
}