{
  "type": "Feature",
  "properties": {
    "iso:country":"US",
    "sg:address":"13531 Grandmaster Piece Ln",
    "sg:city":"Houston",
    "sg:classifiers":[
        {
            "category":"Professional",
            "type":"Services"
        }
    ],
    "sg:phone":"+1 713 896 9504",
    "sg:postcode":"77041",
    "sg:province":"TX",
    "wof:name":"Cheatham Resources LLC",
    "wof:placetype":"venue"
},
  "geometry": {"coordinates":[-95.614785,29.851088],"type":"Point"}
}