{
  "type": "Feature",
  "properties": {
    "iso:country":"US",
    "sg:address":"402 W Cleveland St",
    "sg:city":"Cuero",
    "sg:classifiers":[
        {
            "category":"Retail",
            "subcategory":"Laundry & Dry Cleaning",
            "type":"Services"
        }
    ],
    "sg:phone":"+1 361 672 3733",
    "sg:postcode":"77954",
    "sg:province":"TX",
    "sg:tags":[
        "drycleaning",
        "plant"
    ],
    "wof:name":"Stampede Cleaners",
    "wof:placetype":"venue"
},
  "geometry": {"coordinates":[-97.289315,29.102463],"type":"Point"}
}