{
  "type": "Feature",
  "properties": {
    "iso:country":"US",
    "sg:address":"251 W Dallas Ave",
    "sg:city":"Cooper",
    "sg:classifiers":[
        {
            "category":"Professional",
            "type":"Services"
        }
    ],
    "sg:phone":"+1 903 395 0495",
    "sg:postcode":"75432",
    "sg:province":"TX",
    "sg:tags":[
        "establishment"
    ],
    "wof:name":"Burger Bar",
    "wof:placetype":"venue"
},
  "geometry": {"coordinates":[-95.69005799999999,33.373764],"type":"Point"}
}