{
  "type": "Feature",
  "properties": {
    "iso:country":"US",
    "sg:address":"205 Simpson Rd",
    "sg:city":"Victoria",
    "sg:classifiers":[
        {
            "category":"Building & Trades",
            "subcategory":"Landscaping Services",
            "type":"Services"
        },
        {
            "category":"Home & Garden",
            "subcategory":"Garden Supply",
            "type":"Retail Goods"
        },
        {
            "category":"Wholesale",
            "subcategory":"Machinery & Supplies",
            "type":"Manufacturing & Wholesale Goods"
        },
        {
            "category":"Professional",
            "subcategory":"Business Services",
            "type":"Services"
        },
        {
            "category":"Manufacturing",
            "subcategory":"Paper Products",
            "type":"Manufacturing & Wholesale Goods"
        }
    ],
    "sg:phone":"+1 361 573 0227",
    "sg:postcode":"77904",
    "sg:province":"TX",
    "sg:tags":[
        "lawn",
        "consultant",
        "irrigation",
        "system",
        "equipment",
        "maintenance",
        "bamboo",
        "contractor",
        "landscape"
    ],
    "wof:name":"Superior Sprinkler Systems",
    "wof:placetype":"venue"
},
  "geometry": {"coordinates":[-97.007403,28.872702],"type":"Point"}
}