{
  "type": "Feature",
  "properties": {
    "iso:country":"US",
    "sg:address":"1439 Saddle Rock Dr",
    "sg:city":"Houston",
    "sg:classifiers":[
        {
            "category":"Professional",
            "type":"Services"
        }
    ],
    "sg:phone":"+1 281 931 1051",
    "sg:postcode":"77088",
    "sg:province":"TX",
    "wof:name":"Ty Ro Specialty",
    "wof:placetype":"venue"
},
  "geometry": {"coordinates":[-95.426157,29.88972],"type":"Point"}
}