{
  "type": "Feature",
  "properties": {
    "iso:country":"US",
    "sg:address":"400 Burkburnett Rd",
    "sg:city":"Wichita Falls",
    "sg:classifiers":[
        {
            "category":"Bars & Pubs",
            "type":"Food & Drink"
        }
    ],
    "sg:phone":"+1 940 322 3744",
    "sg:postcode":"76306",
    "sg:province":"TX",
    "sg:tags":[
        "drinking"
    ],
    "wof:name":"Bubbalus",
    "wof:placetype":"venue"
},
  "geometry": {"coordinates":[-98.49670500000001,33.923814],"type":"Point"}
}