{
  "type": "Feature",
  "properties": {
    "iso:country":"US",
    "sg:address":"20737 FM 969",
    "sg:city":"Webberville",
    "sg:classifiers":[
        {
            "category":"Retail",
            "subcategory":"Auto Repair",
            "type":"Services"
        }
    ],
    "sg:phone":"+1 512 837 6735",
    "sg:postcode":"78621",
    "sg:province":"TX",
    "sg:tags":[
        "repairing",
        "automobile"
    ],
    "wof:name":"Austin Mobile Auto Repair",
    "wof:placetype":"venue"
},
  "geometry": {"coordinates":[-97.49111499999999,30.224904],"type":"Point"}
}