{
  "type": "Feature",
  "properties": {
    "iso:country":"US",
    "sg:address":"3903 McCullough Ave",
    "sg:city":"San Antonio",
    "sg:classifiers":[
        {
            "category":"Autos & Motor Vehicles",
            "subcategory":"Fuel & Gas Station",
            "type":"Retail Goods"
        }
    ],
    "sg:phone":"+1 210 805 0443",
    "sg:postcode":"78212",
    "sg:province":"TX",
    "sg:tags":[
        "repair",
        "station",
        "gasoline",
        "general"
    ],
    "wof:name":"Chevron",
    "wof:placetype":"venue"
},
  "geometry": {"coordinates":[-98.491865,29.467003],"type":"Point"}
}