{
  "type": "Feature",
  "properties": {
    "iso:country":"US",
    "sg:address":"950 Lakeshore Dr N",
    "sg:city":"Bandera",
    "sg:classifiers":[
        {
            "category":"Building & Trades",
            "subcategory":"Electrical",
            "type":"Services"
        }
    ],
    "sg:phone":"+1 830 460 7240",
    "sg:postcode":"78003",
    "sg:province":"TX",
    "sg:tags":[
        "electrical",
        "electric",
        "contractor"
    ],
    "wof:name":"Done Right Electric Inc",
    "wof:placetype":"venue"
},
  "geometry": {"coordinates":[-98.970505,29.639884],"type":"Point"}
}