{
  "type": "Feature",
  "properties": {
    "iso:country":"US",
    "sg:address":"10506 Permian Dr",
    "sg:city":"Sugar Land",
    "sg:classifiers":[
        {
            "category":"Shopping",
            "subcategory":"Computers & Home Electronics",
            "type":"Retail Goods"
        }
    ],
    "sg:phone":"+1 281 491 2088",
    "sg:postcode":"77478",
    "sg:province":"TX",
    "sg:tags":[
        "software"
    ],
    "wof:name":"Sutrasoft",
    "wof:placetype":"venue"
},
  "geometry": {"coordinates":[-95.63686199999999,29.663287],"type":"Point"}
}