{
  "type": "Feature",
  "properties": {
    "iso:country":"US",
    "sg:address":"411 NW 4th St",
    "sg:city":"Andrews",
    "sg:classifiers":[
        {
            "category":"Wholesale",
            "subcategory":"Farm Supplies",
            "type":"Manufacturing & Wholesale Goods"
        }
    ],
    "sg:phone":"+1 432 523 7128",
    "sg:postcode":"79714",
    "sg:province":"TX",
    "sg:tags":[
        "livestock"
    ],
    "wof:name":"Fisher Rodeo Cattle Co",
    "wof:placetype":"venue"
},
  "geometry": {"coordinates":[-102.552645,32.321583],"type":"Point"}
}