{
  "type": "Feature",
  "properties": {
    "iso:country":"US",
    "sg:address":"1417 W 7th Ave",
    "sg:city":"Corsicana",
    "sg:classifiers":[
        {
            "category":"Shopping",
            "subcategory":"Computers & Home Electronics",
            "type":"Retail Goods"
        }
    ],
    "sg:phone":"+1 903 872 9299",
    "sg:postcode":"75110",
    "sg:province":"TX",
    "sg:tags":[
        "equipment",
        "satellite",
        "system"
    ],
    "wof:name":"Miguel's Shop",
    "wof:placetype":"venue"
},
  "geometry": {"coordinates":[-96.47672300000001,32.085066],"type":"Point"}
}