{
  "type": "Feature",
  "properties": {
    "iso:country":"US",
    "sg:address":"205 Industrial Blvd",
    "sg:city":"Sugar Land",
    "sg:classifiers":[
        {
            "category":"Manufacturing",
            "subcategory":"Tools & Machinery",
            "type":"Manufacturing & Wholesale Goods"
        }
    ],
    "sg:phone":"+1 281 285 8500",
    "sg:postcode":"77478",
    "sg:province":"TX",
    "sg:tags":[
        "fluid",
        "devices",
        "mfg"
    ],
    "wof:name":"Schlumberger Technology Corp",
    "wof:placetype":"venue"
},
  "geometry": {"coordinates":[-95.605964,29.629246],"type":"Point"}
}