{
  "type": "Feature",
  "properties": {
    "iso:country":"US",
    "sg:address":"5100 Teague Rd",
    "sg:city":"Fort Worth",
    "sg:classifiers":[
        {
            "category":"Retail",
            "subcategory":"Auto Repair",
            "type":"Services"
        }
    ],
    "sg:phone":"+1 817 483 9906",
    "sg:postcode":"76140",
    "sg:province":"TX",
    "sg:tags":[
        "body",
        "automobile",
        "painting"
    ],
    "wof:name":"Dings & Pings",
    "wof:placetype":"venue"
},
  "geometry": {"coordinates":[-97.223131,32.607101],"type":"Point"}
}