{
  "type": "Feature",
  "properties": {
    "iso:country":"US",
    "sg:address":"710 W 9th St",
    "sg:city":"Freeport",
    "sg:classifiers":[
        {
            "category":"Organizations",
            "subcategory":"Community Association",
            "type":"Services"
        }
    ],
    "sg:phone":"+1 979 239 3233",
    "sg:postcode":"77541",
    "sg:province":"TX",
    "wof:name":"Knights of Columbus",
    "wof:placetype":"venue"
},
  "geometry": {"coordinates":[-95.356775,28.946055],"type":"Point"}
}