{
  "type": "Feature",
  "properties": {
    "iso:country":"US",
    "sg:address":"1010 Denver Ave",
    "sg:city":"Dalhart",
    "sg:classifiers":[
        {
            "category":"Shopping",
            "subcategory":"Jewelry",
            "type":"Retail Goods"
        }
    ],
    "sg:phone":"+1 806 244 4496",
    "sg:postcode":"79022",
    "sg:province":"TX",
    "wof:name":"K & A Accessories",
    "wof:placetype":"venue"
},
  "geometry": {"coordinates":[-102.521912,36.055509],"type":"Point"}
}