{
  "type": "Feature",
  "properties": {
    "iso:country":"US",
    "sg:address":"5006 Lakeland Cir",
    "sg:city":"Waco",
    "sg:classifiers":[
        {
            "category":"Professional",
            "subcategory":"Business Services",
            "type":"Services"
        }
    ],
    "sg:phone":"+1 254 776 7720",
    "sg:postcode":"76710",
    "sg:province":"TX",
    "sg:tags":[
        "interior",
        "commercial",
        "design"
    ],
    "wof:name":"Janet Pate Asid",
    "wof:placetype":"venue"
},
  "geometry": {"coordinates":[-97.19045699999999,31.537669],"type":"Point"}
}