{
  "type": "Feature",
  "properties": {
    "iso:country":"US",
    "sg:address":"714 1st St",
    "sg:city":"Marble Falls",
    "sg:classifiers":[
        {
            "category":"Personal",
            "type":"Services"
        }
    ],
    "sg:phone":"+1 830 693 1161",
    "sg:postcode":"78654",
    "sg:province":"TX",
    "sg:tags":[
        "therapist",
        "massage"
    ],
    "wof:name":"Cheryl Birck",
    "wof:placetype":"venue"
},
  "geometry": {"coordinates":[-98.27711600000001,30.569367],"type":"Point"}
}