{
  "type": "Feature",
  "properties": {
    "iso:country":"US",
    "sg:address":"2551 S Shore Blvd",
    "sg:city":"League City",
    "sg:classifiers":[
        {
            "category":"Autos & Motor Vehicles",
            "subcategory":"Boat Sales",
            "type":"Retail Goods"
        }
    ],
    "sg:phone":"+1 281 535 0900",
    "sg:postcode":"77573",
    "sg:province":"TX",
    "sg:tags":[
        "dealer",
        "sales"
    ],
    "sg:website":"www.gulfcoastyachtbroker.com",
    "wof:name":"Lauderdale Yacht Sales",
    "wof:placetype":"venue"
},
  "geometry": {"coordinates":[-95.06404000000001,29.541928],"type":"Point"}
}