{
  "type": "Feature",
  "properties": {
    "iso:country":"US",
    "sg:address":"850 Harvest Time Ln # 69",
    "sg:city":"Houston",
    "sg:classifiers":[
        {
            "category":"Recreation",
            "type":"Entertainment"
        }
    ],
    "sg:phone":"+1 281 755 0839",
    "sg:postcode":"77060",
    "sg:province":"TX",
    "sg:tags":[
        "entertainers-family",
        "business"
    ],
    "wof:name":"Camp Commerce Entertaintment",
    "wof:placetype":"venue"
},
  "geometry": {"coordinates":[-95.396393,29.953858],"type":"Point"}
}