{
  "type": "Feature",
  "properties": {
    "iso:country":"US",
    "sg:address":"1812 N Velasco St",
    "sg:city":"Angleton",
    "sg:classifiers":[
        {
            "category":"Personal",
            "subcategory":"Tanning Parlor",
            "type":"Services"
        }
    ],
    "sg:phone":"+1 979 864 4100",
    "sg:postcode":"77515",
    "sg:province":"TX",
    "sg:tags":[
        "salon"
    ],
    "wof:name":"Gulf Coast Tan",
    "wof:placetype":"venue"
},
  "geometry": {"coordinates":[-95.43395200000001,29.197271],"type":"Point"}
}