{
  "type": "Feature",
  "properties": {
    "iso:country":"US",
    "sg:address":"1105 Sheppard Ln",
    "sg:city":"Wylie",
    "sg:classifiers":[
        {
            "category":"Building & Trades",
            "subcategory":"Construction",
            "type":"Services"
        }
    ],
    "sg:phone":"+1 972 442 3749",
    "sg:postcode":"75098",
    "sg:province":"TX",
    "sg:tags":[
        "system",
        "specialty",
        "heating",
        "contractor",
        "air conditioning"
    ],
    "wof:name":"August Air Conditioning And Heating",
    "wof:placetype":"venue"
},
  "geometry": {"coordinates":[-96.515942,33.019269],"type":"Point"}
}