{
  "type": "Feature",
  "properties": {
    "iso:country":"US",
    "sg:address":"3905 Oak Lawn Ave Ste 110",
    "sg:city":"Dallas",
    "sg:classifiers":[
        {
            "category":"Freight",
            "type":"Transportation"
        },
        {
            "category":"Professional",
            "subcategory":"Printing & Photocopies",
            "type":"Services"
        }
    ],
    "sg:phone":"+1 214 522 3471",
    "sg:postcode":"75219",
    "sg:province":"TX",
    "sg:tags":[
        "shipping"
    ],
    "sg:website":"www.fedex.com",
    "wof:name":"FedEx Ship Center",
    "wof:placetype":"venue"
},
  "geometry": {"coordinates":[-96.802756,32.816578],"type":"Point"}
}