{
  "type": "Feature",
  "properties": {
    "iso:country":"US",
    "sg:address":"3309 Oxbow Trl",
    "sg:city":"Amarillo",
    "sg:classifiers":[
        {
            "category":"Professional",
            "subcategory":"Accounting & Tax Preparation",
            "type":"Services"
        }
    ],
    "sg:phone":"+1 806 359 0760",
    "sg:postcode":"79106",
    "sg:province":"TX",
    "wof:name":"Sage Financial Specialists",
    "wof:placetype":"venue"
},
  "geometry": {"coordinates":[-101.906306,35.176477],"type":"Point"}
}