{
  "type": "Feature",
  "properties": {
    "iso:country":"US",
    "sg:address":"706 W Koenig Ln",
    "sg:city":"Austin",
    "sg:classifiers":[
        {
            "category":"Manufacturing",
            "subcategory":"Printing",
            "type":"Manufacturing & Wholesale Goods"
        }
    ],
    "sg:phone":"+1 512 306 7252",
    "sg:postcode":"78756",
    "sg:province":"TX",
    "sg:tags":[
        "book"
    ],
    "wof:name":"Teachtech",
    "wof:placetype":"venue"
},
  "geometry": {"coordinates":[-97.72518100000001,30.324518],"type":"Point"}
}