{
  "type": "Feature",
  "properties": {
    "iso:country":"US",
    "sg:address":"7332 Alameda Ave",
    "sg:city":"El Paso",
    "sg:classifiers":[
        {
            "category":"Autos & Motor Vehicles",
            "subcategory":"Automobile Sales",
            "type":"Retail Goods"
        }
    ],
    "sg:phone":"+1 915 779 2889",
    "sg:postcode":"79915",
    "sg:province":"TX",
    "sg:tags":[
        "used"
    ],
    "wof:name":"Francia Motors",
    "wof:placetype":"venue"
},
  "geometry": {"coordinates":[-106.377449,31.741737],"type":"Point"}
}