{
  "type": "Feature",
  "properties": {
    "iso:country":"US",
    "sg:address":"3814 Highcliff Dr",
    "sg:city":"San Antonio",
    "sg:classifiers":[
        {
            "category":"Professional",
            "subcategory":"Management & Consulting",
            "type":"Services"
        }
    ],
    "sg:phone":"+1 210 946 1479",
    "sg:postcode":"78218",
    "sg:province":"TX",
    "sg:tags":[
        "consultant",
        "training"
    ],
    "wof:name":"Dameron Enterprises",
    "wof:placetype":"venue"
},
  "geometry": {"coordinates":[-98.420106,29.512031],"type":"Point"}
}