{
  "type": "Feature",
  "properties": {
    "iso:country":"US",
    "sg:address":"1330 Yale St",
    "sg:city":"Houston",
    "sg:classifiers":[
        {
            "category":"Communications",
            "subcategory":"Film & Video Production",
            "type":"Services"
        },
        {
            "category":"Professional",
            "subcategory":"Art Services",
            "type":"Services"
        }
    ],
    "sg:phone":"+1 832 380 4004",
    "sg:postcode":"77008",
    "sg:province":"TX",
    "sg:tags":[
        "photographer",
        "video/film"
    ],
    "sg:website":"steveleeweddings.com/",
    "wof:name":"Steve Lee Weddings",
    "wof:placetype":"venue"
},
  "geometry": {"coordinates":[-95.398741,29.795491],"type":"Point"}
}