{
  "type": "Feature",
  "properties": {
    "iso:country":"US",
    "sg:address":"133 Mimosa St",
    "sg:city":"Hereford",
    "sg:classifiers":[
        {
            "category":"Shopping",
            "subcategory":"Gifts & Souvenirs",
            "type":"Retail Goods"
        }
    ],
    "sg:phone":"+1 806 364 4056",
    "sg:postcode":"79045",
    "sg:province":"TX",
    "wof:name":"Precious Memories",
    "wof:placetype":"venue"
},
  "geometry": {"coordinates":[-102.425594,34.824873],"type":"Point"}
}