{
  "type": "Feature",
  "properties": {
    "iso:country":"US",
    "sg:address":"1450 N Post Oak Rd",
    "sg:city":"Houston",
    "sg:classifiers":[
        {
            "category":"Professional",
            "subcategory":"Computer Services",
            "type":"Services"
        }
    ],
    "sg:phone":"+1 713 956 9999",
    "sg:postcode":"77055",
    "sg:province":"TX",
    "sg:tags":[
        "repair"
    ],
    "wof:name":"IT Fire Control LLC",
    "wof:placetype":"venue"
},
  "geometry": {"coordinates":[-95.45700600000001,29.796467],"type":"Point"}
}