{
  "type": "Feature",
  "properties": {
    "iso:country":"US",
    "sg:address":"9157 Huebner Rd",
    "sg:city":"San Antonio",
    "sg:classifiers":[
        {
            "category":"Professional",
            "subcategory":"Research",
            "type":"Services"
        }
    ],
    "sg:phone":"+1 210 696 9706",
    "sg:postcode":"78240",
    "sg:province":"TX",
    "sg:tags":[
        "commercial",
        "physical"
    ],
    "wof:name":"Keystone Clinical Research",
    "wof:placetype":"venue"
},
  "geometry": {"coordinates":[-98.596689,29.527012],"type":"Point"}
}