{
  "type": "Feature",
  "properties": {
    "iso:country":"US",
    "sg:address":"804 S Terrell St",
    "sg:city":"Midland",
    "sg:classifiers":[
        {
            "category":"Wholesale",
            "subcategory":"Machinery & Supplies",
            "type":"Manufacturing & Wholesale Goods"
        },
        {
            "category":"Home & Garden",
            "subcategory":"Garden Supply",
            "type":"Retail Goods"
        }
    ],
    "sg:phone":"+1 432 683 6677",
    "sg:postcode":"79701",
    "sg:province":"TX",
    "sg:tags":[
        "engine",
        "equipment",
        "gene",
        "repair"
    ],
    "wof:name":"White's Industrial Engines",
    "wof:placetype":"venue"
},
  "geometry": {"coordinates":[-102.068076,31.989293],"type":"Point"}
}