{
  "type": "Feature",
  "properties": {
    "iso:country":"US",
    "sg:address":"15300 Westheimer Rd",
    "sg:city":"Houston",
    "sg:classifiers":[
        {
            "category":"Professional",
            "type":"Services"
        }
    ],
    "sg:phone":"+1 281 558 9351",
    "sg:postcode":"77077",
    "sg:province":"TX",
    "sg:tags":[
        "establishment"
    ],
    "wof:name":"Gulf Commerce Corp",
    "wof:placetype":"venue"
},
  "geometry": {"coordinates":[-95.655131,29.731473],"type":"Point"}
}