{
  "type": "Feature",
  "properties": {
    "iso:country":"US",
    "sg:address":"301 Ave H",
    "sg:city":"Ozona",
    "sg:classifiers":[
        {
            "category":"Shopping",
            "subcategory":"Jewelry",
            "type":"Retail Goods"
        }
    ],
    "sg:phone":"+1 915 392 3115",
    "sg:postcode":"76943",
    "sg:province":"TX",
    "wof:name":"Carlies After Hours",
    "wof:placetype":"venue"
},
  "geometry": {"coordinates":[-101.206137,30.717115],"type":"Point"}
}