{
  "type": "Feature",
  "properties": {
    "iso:country":"US",
    "sg:address":"5038 Airline Rd",
    "sg:city":"Dallas",
    "sg:classifiers":[
        {
            "category":"Professional",
            "type":"Services"
        }
    ],
    "sg:phone":"+1 214 528 8052",
    "sg:postcode":"75205",
    "sg:province":"TX",
    "wof:name":"Greg Pieroni",
    "wof:placetype":"venue"
},
  "geometry": {"coordinates":[-96.781494,32.832254],"type":"Point"}
}