{
  "type": "Feature",
  "properties": {
    "iso:country":"US",
    "sg:address":"5306 Almeda Road",
    "sg:city":"Houston",
    "sg:classifiers":[
        {
            "category":"Shopping",
            "subcategory":"Clothing, Apparel, & Fashions",
            "type":"Retail Goods"
        }
    ],
    "sg:phone":"+1 713 523 1608",
    "sg:postcode":"77004",
    "sg:province":"TX",
    "sg:website":"melodramaboutiqueonline.com/",
    "wof:name":"Melodrama",
    "wof:placetype":"venue"
},
  "geometry": {"coordinates":[-95.378984,29.722127],"type":"Point"}
}