{
  "type": "Feature",
  "properties": {
    "iso:country":"US",
    "sg:address":"6025 N Fry Rd",
    "sg:city":"Katy",
    "sg:classifiers":[
        {
            "category":"Restaurant",
            "type":"Food & Drink"
        }
    ],
    "sg:menulink":"http://www.allmenus.com/tx/houston/204147-sonic/menu/",
    "sg:postcode":"77449",
    "sg:province":"TX",
    "sg:tags":[
        "burger",
        "american"
    ],
    "wof:name":"Sonic",
    "wof:placetype":"venue"
},
  "geometry": {"coordinates":[-95.72009300000001,29.859372],"type":"Point"}
}