{
  "type": "Feature",
  "properties": {
    "iso:country":"US",
    "sg:address":"401 College St",
    "sg:city":"Ingram",
    "sg:classifiers":[
        {
            "category":"Retail",
            "subcategory":"Repair Shop",
            "type":"Services"
        }
    ],
    "sg:phone":"+1 830 367 7575",
    "sg:postcode":"78025",
    "sg:province":"TX",
    "sg:tags":[
        "scooter",
        "motorcycle",
        "motor"
    ],
    "wof:name":"Jacks Cycle Svc",
    "wof:placetype":"venue"
},
  "geometry": {"coordinates":[-99.24065400000001,30.07778],"type":"Point"}
}