{
  "type": "Feature",
  "properties": {
    "iso:country":"US",
    "sg:address":"18611 Woodbreeze Dr",
    "sg:city":"Humble",
    "sg:classifiers":[
        {
            "category":"Professional",
            "type":"Services"
        }
    ],
    "sg:phone":"+1 281 548 1624",
    "sg:postcode":"77346",
    "sg:province":"TX",
    "wof:name":"Terion Power Ltd Co",
    "wof:placetype":"venue"
},
  "geometry": {"coordinates":[-95.175555,29.988208],"type":"Point"}
}