{
  "type": "Feature",
  "properties": {
    "iso:country":"US",
    "sg:address":"3550 Timberglen Rd",
    "sg:city":"Dallas",
    "sg:classifiers":[
        {
            "category":"Shopping",
            "subcategory":"Used Merchandise",
            "type":"Retail Goods"
        }
    ],
    "sg:phone":"+1 214 943 4442",
    "sg:postcode":"75287",
    "sg:province":"TX",
    "wof:name":"Next To None Courier",
    "wof:placetype":"venue"
},
  "geometry": {"coordinates":[-96.860314,33.002465],"type":"Point"}
}