{
  "type": "Feature",
  "properties": {
    "iso:country":"US",
    "sg:address":"1101 SE 3rd St",
    "sg:city":"Mineral Wells",
    "sg:classifiers":[
        {
            "category":"Shopping",
            "subcategory":"Hobbies, Toys, & Games",
            "type":"Retail Goods"
        }
    ],
    "sg:phone":"+1 940 325 4665",
    "sg:postcode":"76067",
    "sg:province":"TX",
    "wof:name":"Barbaras Eggs",
    "wof:placetype":"venue"
},
  "geometry": {"coordinates":[-98.10419899999999,32.806973],"type":"Point"}
}