{
  "type": "Feature",
  "properties": {
    "iso:country":"US",
    "sg:address":"105 E Nakoma Dr",
    "sg:city":"San Antonio",
    "sg:classifiers":[
        {
            "category":"Manufacturing",
            "subcategory":"Motor Vehicles & Parts",
            "type":"Manufacturing & Wholesale Goods"
        }
    ],
    "sg:phone":"+1 210 349 7319",
    "sg:postcode":"78216",
    "sg:province":"TX",
    "sg:tags":[
        "equipment",
        "truck"
    ],
    "sg:website":"www.southtexasoutfitters.com",
    "wof:name":"South Texas Outfitters",
    "wof:placetype":"venue"
},
  "geometry": {"coordinates":[-98.493532,29.552133],"type":"Point"}
}