{
  "type": "Feature",
  "properties": {
    "iso:country":"US",
    "sg:address":"5115 Harrisburg Blvd",
    "sg:city":"Houston",
    "sg:classifiers":[
        {
            "category":"Social Services",
            "type":"Services"
        }
    ],
    "sg:phone":"+1 713 926 8771",
    "sg:postcode":"77011",
    "sg:province":"TX",
    "wof:name":"Houston Community Service Inc",
    "wof:placetype":"venue"
},
  "geometry": {"coordinates":[-95.324341,29.742552],"type":"Point"}
}