{
  "type": "Feature",
  "properties": {
    "iso:country":"US",
    "sg:address":"301 S Highway 87",
    "sg:city":"Dalhart",
    "sg:classifiers":[
        {
            "category":"Restaurant",
            "type":"Food & Drink"
        }
    ],
    "sg:menulink":"http://www.allmenus.com/tx/dalhart/70673-pizza-hut/menu/",
    "sg:phone":"+1 806 249 6536",
    "sg:postcode":"79022",
    "sg:province":"TX",
    "sg:tags":[
        "american",
        "pizza"
    ],
    "wof:name":"Pizza Hut",
    "wof:placetype":"venue"
},
  "geometry": {"coordinates":[-102.51818900000001,36.063247],"type":"Point"}
}