{
  "type": "Feature",
  "properties": {
    "iso:country":"US",
    "sg:address":"2600 S 1st St",
    "sg:city":"Temple",
    "sg:classifiers":[
        {
            "category":"Social Services",
            "subcategory":"Job Training",
            "type":"Services"
        }
    ],
    "sg:phone":"+1 254 298 8592",
    "sg:postcode":"76504",
    "sg:province":"TX",
    "sg:tags":[
        "vocational"
    ],
    "wof:name":"Bell County Business Alliance",
    "wof:placetype":"venue"
},
  "geometry": {"coordinates":[-97.350667,31.072682],"type":"Point"}
}