{
  "type": "Feature",
  "properties": {
    "iso:country":"US",
    "sg:address":"809 Cobb St",
    "sg:city":"Bridgeport",
    "sg:classifiers":[
        {
            "category":"Shopping",
            "subcategory":"Used Merchandise",
            "type":"Retail Goods"
        }
    ],
    "sg:phone":"+1 940 683 4043",
    "sg:postcode":"76426",
    "sg:province":"TX",
    "wof:name":"Grannys Antiques",
    "wof:placetype":"venue"
},
  "geometry": {"coordinates":[-97.758921,33.205689],"type":"Point"}
}