{
  "type": "Feature",
  "properties": {
    "iso:country":"US",
    "sg:address":"5233 Bridge St",
    "sg:city":"Fort Worth",
    "sg:classifiers":[
        {
            "category":"Communications",
            "subcategory":"Television Station",
            "type":"Services"
        }
    ],
    "sg:phone":"+1 817 451 1111",
    "sg:postcode":"76103",
    "sg:province":"TX",
    "sg:tags":[
        "broadcasting",
        "co"
    ],
    "wof:name":"KTVT",
    "wof:placetype":"venue"
},
  "geometry": {"coordinates":[-97.242861,32.760756],"type":"Point"}
}