{
  "type": "Feature",
  "properties": {
    "iso:country":"US",
    "sg:address":"5405 S Pleasant Valley Rd",
    "sg:city":"Austin",
    "sg:classifiers":[
        {
            "category":"Retail",
            "subcategory":"Self-service Laundry",
            "type":"Services"
        }
    ],
    "sg:phone":"+1 512 326 8092",
    "sg:postcode":"78744",
    "sg:province":"TX",
    "wof:name":"KWIK Wash Coin Laundries Inc",
    "wof:placetype":"venue"
},
  "geometry": {"coordinates":[-97.74450299999999,30.193577],"type":"Point"}
}