{
  "type": "Feature",
  "properties": {
    "iso:country":"US",
    "sg:address":"1117 Texas St",
    "sg:city":"Houston",
    "sg:classifiers":[
        {
            "category":"Arts & Performance",
            "subcategory":"Theater",
            "type":"Entertainment"
        }
    ],
    "sg:phone":"+1 713 224 5566",
    "sg:postcode":"77002",
    "sg:province":"TX",
    "sg:tags":[
        "entertainer",
        "performing",
        "business"
    ],
    "sg:website":"www.houstonchamberchoir.org/",
    "wof:name":"Houston Chamber Choir",
    "wof:placetype":"venue"
},
  "geometry": {"coordinates":[-95.361397,29.759399],"type":"Point"}
}