{
  "type": "Feature",
  "properties": {
    "iso:country":"US",
    "sg:address":"7500 Beechnut St",
    "sg:city":"Houston",
    "sg:classifiers":[
        {
            "category":"Health Services",
            "subcategory":"Doctor",
            "type":"Services"
        }
    ],
    "sg:phone":"+1 713 773 0454",
    "sg:postcode":"77074",
    "sg:province":"TX",
    "sg:tags":[
        "physician",
        "surgeon"
    ],
    "wof:name":"International Primary Care",
    "wof:placetype":"venue"
},
  "geometry": {"coordinates":[-95.518242,29.691081],"type":"Point"}
}