{
  "type": "Feature",
  "properties": {
    "iso:country":"US",
    "sg:address":"205 Dr Pepper Rd",
    "sg:city":"Stanton",
    "sg:phone":"+1 432 756 2401",
    "sg:postcode":"79782",
    "sg:province":"TX",
    "sg:tags":[
        "farm",
        "cotton"
    ],
    "wof:name":"Robert Quaid",
    "wof:placetype":"venue"
},
  "geometry": {"coordinates":[-101.805767,32.123951],"type":"Point"}
}