{
  "type": "Feature",
  "properties": {
    "iso:country":"US",
    "sg:address":"5230 de Zavala Rd",
    "sg:city":"San Antonio",
    "sg:classifiers":[
        {
            "category":"Airline",
            "type":"Transportation"
        }
    ],
    "sg:phone":"+1 210 696 5774",
    "sg:postcode":"78249",
    "sg:province":"TX",
    "sg:tags":[
        "cargo",
        "air"
    ],
    "wof:name":"Worldwide Express",
    "wof:placetype":"venue"
},
  "geometry": {"coordinates":[-98.586455,29.564768],"type":"Point"}
}