{
  "type": "Feature",
  "properties": {
    "iso:country":"US",
    "sg:address":"117 Cora St",
    "sg:city":"Center",
    "sg:classifiers":[
        {
            "category":"Place Of Worship",
            "subcategory":"Church",
            "type":"Public Place"
        },
        {
            "category":"Place Of Worship",
            "type":"Public Place"
        }
    ],
    "sg:phone":"+1 936 598 5605",
    "sg:postcode":"75935",
    "sg:province":"TX",
    "sg:tags":[
        "churches-baptist-general",
        "churches-baptist"
    ],
    "sg:website":"http://www.abc-usa.org",
    "wof:name":"First Bptst Ch Prayer Ministry",
    "wof:placetype":"venue"
},
  "geometry": {"coordinates":[-94.180243,31.795307],"type":"Point"}
}