{
  "type": "Feature",
  "properties": {
    "iso:country":"US",
    "sg:address":"9461 Lyndon B Johnson Fwy Suite 128",
    "sg:city":"Dallas",
    "sg:classifiers":[
        {
            "category":"Shopping",
            "subcategory":"Baby Store",
            "type":"Retail Goods"
        },
        {
            "category":"Professional",
            "type":"Services"
        },
        {
            "category":"Personal",
            "type":"Services"
        },
        {
            "category":"Social Services",
            "subcategory":"Child Care",
            "type":"Services"
        }
    ],
    "sg:phone":"+1 214 526 2772",
    "sg:postcode":"75243",
    "sg:province":"TX",
    "sg:tags":[
        "information",
        "abortion",
        "adoption",
        "pregnancy",
        "counseling",
        "alternative"
    ],
    "sg:website":"http://www.catholiccharitiesdallas.org/poverty",
    "wof:name":"Catholic Charities Professional Counseling",
    "wof:placetype":"venue"
},
  "geometry": {"coordinates":[-96.731801,32.909628],"type":"Point"}
}