{
  "type": "Feature",
  "properties": {
    "iso:country":"US",
    "sg:address":"135 W Ohio Ave",
    "sg:city":"Dallas",
    "sg:classifiers":[
        {
            "category":"Organizations",
            "subcategory":"Religious Organization",
            "type":"Services"
        }
    ],
    "sg:phone":"+1 214 943 4210",
    "sg:postcode":"75224",
    "sg:province":"TX",
    "wof:name":"Beckley Wynnewood Baptist",
    "wof:placetype":"venue"
},
  "geometry": {"coordinates":[-96.82414199999999,32.719571],"type":"Point"}
}