{
  "type": "Feature",
  "properties": {
    "iso:country":"US",
    "sg:address":"4109 College Ave",
    "sg:city":"Snyder",
    "sg:classifiers":[
        {
            "category":"Personal",
            "subcategory":"Beauty Salon",
            "type":"Services"
        }
    ],
    "sg:phone":"+1 325 573 0189",
    "sg:postcode":"79549",
    "sg:province":"TX",
    "wof:name":"Amazing Cuts",
    "wof:placetype":"venue"
},
  "geometry": {"coordinates":[-100.919201,32.689804],"type":"Point"}
}