{
  "type": "Feature",
  "properties": {
    "iso:country":"US",
    "sg:address":"816 W Lee St",
    "sg:city":"Pharr",
    "sg:classifiers":[
        {
            "category":"Retail",
            "subcategory":"Auto Repair",
            "type":"Services"
        }
    ],
    "sg:phone":"+1 956 781 1062",
    "sg:postcode":"78577",
    "sg:province":"TX",
    "sg:tags":[
        "transmission"
    ],
    "wof:name":"Jimmy's Automatic Trans",
    "wof:placetype":"venue"
},
  "geometry": {"coordinates":[-98.19293500000001,26.212397],"type":"Point"}
}