{
  "type": "Feature",
  "properties": {
    "iso:country":"US",
    "sg:address":"305 Sandy Corners Rd",
    "sg:city":"El Campo",
    "sg:classifiers":[
        {
            "category":"Shopping",
            "type":"Retail Goods"
        },
        {
            "category":"Health Services",
            "subcategory":"Doctor",
            "type":"Services"
        }
    ],
    "sg:phone":"+1 979 543 1590",
    "sg:postcode":"77437",
    "sg:province":"TX",
    "sg:tags":[
        "physician",
        "surgeon",
        "merchandise"
    ],
    "wof:name":"Palivela P Raju MD",
    "wof:placetype":"venue"
},
  "geometry": {"coordinates":[-96.289513,29.219105],"type":"Point"}
}