{
  "type": "Feature",
  "properties": {
    "iso:country":"US",
    "sg:address":"8101 Latigo Dr",
    "sg:city":"San Antonio",
    "sg:classifiers":[
        {
            "category":"Social Services",
            "subcategory":"Child Care",
            "type":"Services"
        }
    ],
    "sg:phone":"+1 210 678 2200",
    "sg:postcode":"78227",
    "sg:province":"TX",
    "wof:name":"Parent/Child Inc",
    "wof:placetype":"venue"
},
  "geometry": {"coordinates":[-98.648338,29.416074],"type":"Point"}
}