{
  "type": "Feature",
  "properties": {
    "iso:country":"US",
    "sg:address":"403 W Morin St",
    "sg:city":"Del Rio",
    "sg:classifiers":[
        {
            "category":"Retail",
            "subcategory":"Laundry & Dry Cleaning",
            "type":"Services"
        },
        {
            "category":"Shopping",
            "subcategory":"Clothing, Apparel, & Fashions",
            "type":"Retail Goods"
        }
    ],
    "sg:phone":"+1 830 774 4020",
    "sg:postcode":"78840",
    "sg:province":"TX",
    "sg:tags":[
        "alteration"
    ],
    "wof:name":"Juanita's Alterations",
    "wof:placetype":"venue"
},
  "geometry": {"coordinates":[-100.88272000000001,29.356317],"type":"Point"}
}