{
  "type": "Feature",
  "properties": {
    "iso:country":"US",
    "sg:address":"13923 Wadebridge Way",
    "sg:city":"Houston",
    "sg:classifiers":[
        {
            "category":"Building & Trades",
            "subcategory":"Equipment Rental",
            "type":"Services"
        }
    ],
    "sg:phone":"+1 713 451 3193",
    "sg:postcode":"77015",
    "sg:province":"TX",
    "wof:name":"Britt Kay Sales",
    "wof:placetype":"venue"
},
  "geometry": {"coordinates":[-95.173374,29.792765],"type":"Point"}
}