{
  "type": "Feature",
  "properties": {
    "iso:country":"US",
    "sg:address":"1500 Louisiana St",
    "sg:city":"Houston",
    "sg:classifiers":[
        {
            "category":"Banks & Credit Unions",
            "subcategory":"Investment Brokerage",
            "type":"Services"
        }
    ],
    "sg:phone":"+1 713 853 7926",
    "sg:postcode":"77002",
    "sg:province":"TX",
    "sg:tags":[
        "security",
        "investor"
    ],
    "wof:name":"UBS Warburg LLC",
    "wof:placetype":"venue"
},
  "geometry": {"coordinates":[-95.371056,29.754049],"type":"Point"}
}