{
  "type": "Feature",
  "properties": {
    "iso:country":"US",
    "sg:address":"500 Grandview Dr",
    "sg:city":"Corsicana",
    "sg:classifiers":[
        {
            "category":"Shopping",
            "type":"Retail Goods"
        }
    ],
    "sg:phone":"+1 903 874 1911",
    "sg:postcode":"75110",
    "sg:province":"TX",
    "sg:tags":[
        "coin",
        "dealer",
        "supply"
    ],
    "wof:name":"Sanders Trading Co",
    "wof:placetype":"venue"
},
  "geometry": {"coordinates":[-96.237871,31.983728],"type":"Point"}
}