{
  "type": "Feature",
  "properties": {
    "iso:country":"US",
    "sg:address":"15810 River Roads Dr",
    "sg:city":"Houston",
    "sg:classifiers":[
        {
            "category":"Professional",
            "subcategory":"Engineering",
            "type":"Services"
        }
    ],
    "sg:phone":"+1 281 679 7093",
    "sg:postcode":"77079",
    "sg:province":"TX",
    "sg:tags":[
        "engineer"
    ],
    "wof:name":"M J Engineering",
    "wof:placetype":"venue"
},
  "geometry": {"coordinates":[-95.639117,29.772931],"type":"Point"}
}