{
  "type": "Feature",
  "properties": {
    "iso:country":"US",
    "sg:address":"11312 Lyndon B Johnson Fwy",
    "sg:city":"Dallas",
    "sg:classifiers":[
        {
            "category":"Shopping",
            "subcategory":"Stationery & Office Supplies",
            "type":"Retail Goods"
        },
        {
            "category":"Shopping",
            "subcategory":"Gifts & Souvenirs",
            "type":"Retail Goods"
        }
    ],
    "sg:phone":"+1 214 503 8868",
    "sg:postcode":"75238",
    "sg:province":"TX",
    "sg:tags":[
        "shop",
        "store"
    ],
    "wof:name":"Condoms to Go",
    "wof:placetype":"venue"
},
  "geometry": {"coordinates":[-96.685827,32.876336],"type":"Point"}
}