{
  "type": "Feature",
  "properties": {
    "iso:country":"US",
    "sg:address":"2807 Cannongate Dr",
    "sg:city":"Arlington",
    "sg:classifiers":[
        {
            "category":"Retail",
            "subcategory":"Portrait Studio",
            "type":"Services"
        }
    ],
    "sg:phone":"+1 817 466 1212",
    "sg:postcode":"76015",
    "sg:province":"TX",
    "sg:tags":[
        "photographer"
    ],
    "wof:name":"Portraits By Michelle",
    "wof:placetype":"venue"
},
  "geometry": {"coordinates":[-97.135171,32.697149],"type":"Point"}
}