{
  "type": "Feature",
  "properties": {
    "iso:country":"US",
    "sg:address":"30 Lyerly St",
    "sg:city":"Houston",
    "sg:classifiers":[
        {
            "category":"Retail",
            "subcategory":"Repair Shop",
            "type":"Services"
        }
    ],
    "sg:phone":"+1 713 694 4315",
    "sg:postcode":"77022",
    "sg:province":"TX",
    "sg:tags":[
        "reupholstery",
        "furniture"
    ],
    "wof:name":"I & R Customs",
    "wof:placetype":"venue"
},
  "geometry": {"coordinates":[-95.381798,29.8346],"type":"Point"}
}