{
  "type": "Feature",
  "properties": {
    "iso:country":"US",
    "sg:address":"2047 Rigsby Ave",
    "sg:city":"San Antonio",
    "sg:classifiers":[
        {
            "category":"Autos & Motor Vehicles",
            "subcategory":"Automobile Sales",
            "type":"Retail Goods"
        }
    ],
    "sg:phone":"+1 210 333 2400",
    "sg:postcode":"78210",
    "sg:province":"TX",
    "sg:tags":[
        "used"
    ],
    "wof:name":"Clay Jackson Incorporated",
    "wof:placetype":"venue"
},
  "geometry": {"coordinates":[-98.429816,29.398143],"type":"Point"}
}