{
  "type": "Feature",
  "properties": {
    "iso:country":"US",
    "sg:address":"4150 S Danville Dr",
    "sg:city":"Abilene",
    "sg:classifiers":[
        {
            "category":"Food & Beverages",
            "subcategory":"Liquor & Beverages",
            "type":"Retail Goods"
        }
    ],
    "sg:phone":"+1 325 692 3993",
    "sg:postcode":"79605",
    "sg:province":"TX",
    "sg:tags":[
        "alcoholic"
    ],
    "wof:name":"Oasis Wines & Spirits",
    "wof:placetype":"venue"
},
  "geometry": {"coordinates":[-99.758836,32.402594],"type":"Point"}
}