{
  "type": "Feature",
  "properties": {
    "iso:country":"US",
    "sg:address":"491 E Princeton Dr",
    "sg:city":"Princeton",
    "sg:classifiers":[
        {
            "category":"Restaurant",
            "type":"Food & Drink"
        }
    ],
    "sg:menulink":"http://www.allmenus.com/tx/princeton/229101-golden-chick/menu/",
    "sg:phone":"+1 972 734 6943",
    "sg:postcode":"75407",
    "sg:province":"TX",
    "sg:tags":[
        "american"
    ],
    "wof:name":"Golden Chick",
    "wof:placetype":"venue"
},
  "geometry": {"coordinates":[-96.494175,33.173867],"type":"Point"}
}