{
  "type": "Feature",
  "properties": {
    "iso:country":"US",
    "sg:address":"1409 S Cherry Ln",
    "sg:city":"Fort Worth",
    "sg:classifiers":[
        {
            "category":"Autos & Motor Vehicles",
            "subcategory":"Fuel & Gas Station",
            "type":"Retail Goods"
        }
    ],
    "sg:phone":"+1 817 246 6265",
    "sg:postcode":"76108",
    "sg:province":"TX",
    "sg:tags":[
        "oil"
    ],
    "wof:name":"Conoco Mart 3",
    "wof:placetype":"venue"
},
  "geometry": {"coordinates":[-97.45168099999999,32.745456],"type":"Point"}
}