{
  "type": "Feature",
  "properties": {
    "iso:country":"US",
    "sg:address":"12502 Westerley Ln",
    "sg:city":"Houston",
    "sg:classifiers":[
        {
            "category":"Shopping",
            "subcategory":"Shoes",
            "type":"Retail Goods"
        }
    ],
    "sg:phone":"+1 281 497 0347",
    "sg:postcode":"77077",
    "sg:province":"TX",
    "wof:name":"AR Pipeline Consultants Inc",
    "wof:placetype":"venue"
},
  "geometry": {"coordinates":[-95.604246,29.760239],"type":"Point"}
}