{
  "type": "Feature",
  "properties": {
    "iso:country":"US",
    "sg:address":"601 Conrad Hilton Blvd",
    "sg:city":"Cisco",
    "sg:classifiers":[
        {
            "category":"Real Estate",
            "subcategory":"Real Estate Agent",
            "type":"Services"
        }
    ],
    "sg:phone":"+1 254 442 1880",
    "sg:postcode":"76437",
    "sg:province":"TX",
    "wof:name":"Ann Williams Real Estate",
    "wof:placetype":"venue"
},
  "geometry": {"coordinates":[-98.98038099999999,32.389738],"type":"Point"}
}