{
  "type": "Feature",
  "properties": {
    "iso:country":"US",
    "sg:address":"203 W B St",
    "sg:city":"La Porte",
    "sg:classifiers":[
        {
            "category":"Professional",
            "subcategory":"Engineering",
            "type":"Services"
        }
    ],
    "sg:phone":"+1 281 471 6131",
    "sg:postcode":"77571",
    "sg:province":"TX",
    "sg:tags":[
        "consulting",
        "management"
    ],
    "wof:name":"T C G Consulting Inc",
    "wof:placetype":"venue"
},
  "geometry": {"coordinates":[-95.02034,29.662768],"type":"Point"}
}