{
  "type": "Feature",
  "properties": {
    "iso:country":"US",
    "sg:address":"701 Highlander Blvd",
    "sg:city":"Arlington",
    "sg:classifiers":[
        {
            "category":"Real Estate",
            "subcategory":"Real Estate Services",
            "type":"Services"
        },
        {
            "category":"Banks & Credit Unions",
            "subcategory":"Financial Services",
            "type":"Services"
        }
    ],
    "sg:phone":"+1 817 557 0444",
    "sg:postcode":"76015",
    "sg:province":"TX",
    "sg:tags":[
        "loan",
        "processing"
    ],
    "wof:name":"Mccracken Mortgage",
    "wof:placetype":"venue"
},
  "geometry": {"coordinates":[-97.115067,32.68259],"type":"Point"}
}