{
  "type": "Feature",
  "properties": {
    "iso:country":"US",
    "sg:address":"101 Nob Hill Ln",
    "sg:city":"Red Oak",
    "sg:classifiers":[
        {
            "category":"Professional",
            "subcategory":"Business Services",
            "type":"Services"
        }
    ],
    "sg:phone":"+1 972 217 1840",
    "sg:postcode":"75154",
    "sg:province":"TX",
    "wof:name":"Dukes Enterprises",
    "wof:placetype":"venue"
},
  "geometry": {"coordinates":[-96.890198,32.5386],"type":"Point"}
}