{
  "type": "Feature",
  "properties": {
    "iso:country":"US",
    "sg:address":"5214 Inglewood Dr",
    "sg:city":"Pasadena",
    "sg:classifiers":[
        {
            "category":"Professional",
            "type":"Services"
        }
    ],
    "sg:phone":"+1 281 487 1746",
    "sg:postcode":"77505",
    "sg:province":"TX",
    "wof:name":"Rcs Interest",
    "wof:placetype":"venue"
},
  "geometry": {"coordinates":[-95.139002,29.63463],"type":"Point"}
}