{
  "type": "Feature",
  "properties": {
    "iso:country":"US",
    "sg:address":"132 W Batts St",
    "sg:city":"San Benito",
    "sg:classifiers":[
        {
            "category":"Health Services",
            "subcategory":"Podiatrist",
            "type":"Services"
        }
    ],
    "sg:phone":"+1 956 399 3338",
    "sg:postcode":"78586",
    "sg:province":"TX",
    "wof:name":"Foot Doctor The Inc",
    "wof:placetype":"venue"
},
  "geometry": {"coordinates":[-97.632378,26.132565],"type":"Point"}
}