{
  "type": "Feature",
  "properties": {
    "iso:country":"US",
    "sg:address":"4001 Broadway",
    "sg:city":"San Antonio",
    "sg:classifiers":[
        {
            "category":"Shopping",
            "subcategory":"Used Merchandise",
            "type":"Retail Goods"
        }
    ],
    "sg:phone":"+1 210 828 8032",
    "sg:postcode":"78209",
    "sg:province":"TX",
    "sg:tags":[
        "resale",
        "clothing",
        "store"
    ],
    "wof:name":"Baubles Beads Resale Boutiques",
    "wof:placetype":"venue"
},
  "geometry": {"coordinates":[-98.465087,29.46367],"type":"Point"}
}