{
  "type": "Feature",
  "properties": {
    "iso:country":"US",
    "sg:address":"1202 Sandhurst Ct",
    "sg:city":"Grapevine",
    "sg:classifiers":[
        {
            "category":"Professional",
            "subcategory":"Business Services",
            "type":"Services"
        }
    ],
    "sg:phone":"+1 817 488 4885",
    "sg:postcode":"76051",
    "sg:province":"TX",
    "wof:name":"Cerone Enterprises LLC",
    "wof:placetype":"venue"
},
  "geometry": {"coordinates":[-97.08924500000001,32.948376],"type":"Point"}
}