{
  "type": "Feature",
  "properties": {
    "iso:country":"US",
    "sg:address":"208 S 29th St",
    "sg:city":"Donna",
    "sg:classifiers":[
        {
            "category":"Shopping",
            "subcategory":"Discount & Variety Stores",
            "type":"Retail Goods"
        }
    ],
    "sg:phone":"+1 956 461 2812",
    "sg:postcode":"78537",
    "sg:province":"TX",
    "sg:tags":[
        "merchandise",
        "general"
    ],
    "wof:name":"Card Lady",
    "wof:placetype":"venue"
},
  "geometry": {"coordinates":[-98.034071,26.165853],"type":"Point"}
}