{
  "type": "Feature",
  "properties": {
    "iso:country":"US",
    "sg:address":"12968 Bissonnet St",
    "sg:city":"Houston",
    "sg:classifiers":[
        {
            "category":"Autos & Motor Vehicles",
            "subcategory":"Automobile Sales",
            "type":"Retail Goods"
        }
    ],
    "sg:phone":"+1 281 568 0606",
    "sg:postcode":"77099",
    "sg:province":"TX",
    "sg:tags":[
        "new",
        "used",
        "car"
    ],
    "wof:name":"Toyo Motors",
    "wof:placetype":"venue"
},
  "geometry": {"coordinates":[-95.60998499999999,29.680217],"type":"Point"}
}