{
  "type": "Feature",
  "properties": {
    "iso:country":"US",
    "sg:address":"161 Access Rd Ste I-20",
    "sg:city":"Kilgore",
    "sg:classifiers":[
        {
            "category":"Fast Food",
            "type":"Food & Drink"
        },
        {
            "category":"Restaurant",
            "type":"Food & Drink"
        }
    ],
    "sg:phone":"+1 903 984 8591",
    "sg:postcode":"75662",
    "sg:province":"TX",
    "sg:tags":[
        "dessert",
        "american",
        "take"
    ],
    "wof:name":"Dairy Queen",
    "wof:placetype":"venue"
},
  "geometry": {"coordinates":[-94.941271,32.434449],"type":"Point"}
}