{
  "type": "Feature",
  "properties": {
    "iso:country":"US",
    "sg:address":"3025 Matlock Rd",
    "sg:city":"Arlington",
    "sg:phone":"+1 800 714 2020",
    "sg:postcode":"76015",
    "sg:province":"TX",
    "sg:website":"http://www.lasiksurgery.com",
    "wof:name":"Kleiman/ Evangelista Eye Center",
    "wof:placetype":"venue"
},
  "geometry": {"coordinates":[-97.114769,32.69548],"type":"Point"}
}