{
  "type": "Feature",
  "properties": {
    "iso:country":"US",
    "sg:address":"14760 Memorial Dr",
    "sg:city":"Houston",
    "sg:classifiers":[
        {
            "category":"Professional",
            "type":"Services"
        }
    ],
    "sg:phone":"+1 281 493 0234",
    "sg:postcode":"77079",
    "sg:province":"TX",
    "wof:name":"Ginalo Worldwide Corp",
    "wof:placetype":"venue"
},
  "geometry": {"coordinates":[-95.610927,29.770861],"type":"Point"}
}