{
  "type": "Feature",
  "properties": {
    "iso:country":"US",
    "sg:address":"1813 Pine",
    "sg:city":"Liberty",
    "sg:classifiers":[
        {
            "category":"Building & Trades",
            "subcategory":"Electrical",
            "type":"Services"
        }
    ],
    "sg:phone":"+1 936 336 8469",
    "sg:postcode":"77575",
    "sg:province":"TX",
    "sg:tags":[
        "electrical",
        "contractor"
    ],
    "wof:name":"Liberty Alarms Inc",
    "wof:placetype":"venue"
},
  "geometry": {"coordinates":[-94.794674,30.075493],"type":"Point"}
}