{
  "type": "Feature",
  "properties": {
    "iso:country":"US",
    "sg:address":"105 Harborcrest Dr",
    "sg:city":"Seabrook",
    "sg:classifiers":[
        {
            "category":"Building & Trades",
            "subcategory":"Construction",
            "type":"Services"
        }
    ],
    "sg:phone":"+1 281 326 7336",
    "sg:postcode":"77586",
    "sg:province":"TX",
    "sg:tags":[
        "plant",
        "industrial"
    ],
    "wof:name":"Brambles Industrial Svcs Intl",
    "wof:placetype":"venue"
},
  "geometry": {"coordinates":[-95.050944,29.575091],"type":"Point"}
}