{
  "type": "Feature",
  "properties": {
    "iso:country":"US",
    "sg:address":"2001 State Hwy 137",
    "sg:city":"Stanton",
    "sg:classifiers":[
        {
            "category":"Organizations",
            "subcategory":"Religious Organization",
            "type":"Services"
        }
    ],
    "sg:phone":"+1 432 756 4546",
    "sg:postcode":"79782",
    "sg:province":"TX",
    "sg:tags":[
        "church"
    ],
    "wof:name":"Hosanna Christian Fellowship",
    "wof:placetype":"venue"
},
  "geometry": {"coordinates":[-101.807216,32.142479],"type":"Point"}
}