{
  "type": "Feature",
  "properties": {
    "iso:country":"US",
    "sg:address":"2004 Bert Ave",
    "sg:city":"Austin",
    "sg:classifiers":[
        {
            "category":"Education",
            "subcategory":"Preschool",
            "type":"Public Place"
        }
    ],
    "sg:phone":"+1 512 478 7775",
    "sg:postcode":"78704",
    "sg:province":"TX",
    "sg:tags":[
        "kindergarten"
    ],
    "wof:name":"Habibi's Hutch Preschool",
    "wof:placetype":"venue"
},
  "geometry": {"coordinates":[-97.786383,30.232888],"type":"Point"}
}