{
  "type": "Feature",
  "properties": {
    "iso:country":"US",
    "sg:address":"619 W Rhapsody Dr",
    "sg:city":"San Antonio",
    "sg:classifiers":[
        {
            "category":"Real Estate",
            "subcategory":"Real Estate Operator",
            "type":"Services"
        }
    ],
    "sg:phone":"+1 210 349 0404",
    "sg:postcode":"78216",
    "sg:province":"TX",
    "sg:tags":[
        "building",
        "property",
        "lessor",
        "nonresidential"
    ],
    "wof:name":"J D L V Properties",
    "wof:placetype":"venue"
},
  "geometry": {"coordinates":[-98.501216,29.552113],"type":"Point"}
}