{
  "type": "Feature",
  "properties": {
    "iso:country":"US",
    "sg:address":"100 S Main St",
    "sg:city":"Electra",
    "sg:classifiers":[
        {
            "category":"Banks & Credit Unions",
            "subcategory":"Bank",
            "type":"Services"
        }
    ],
    "sg:phone":"+1 940 495 2116",
    "sg:postcode":"76360",
    "sg:province":"TX",
    "sg:tags":[
        "state",
        "savings"
    ],
    "wof:name":"First American Bank Ssb",
    "wof:placetype":"venue"
},
  "geometry": {"coordinates":[-98.91897,34.029277],"type":"Point"}
}