{
  "type": "Feature",
  "properties": {
    "iso:country":"US",
    "sg:address":"173 Segovia Way",
    "sg:city":"Pflugerville",
    "sg:classifiers":[
        {
            "category":"Utilities",
            "subcategory":"Mobile Phone",
            "type":"Services"
        }
    ],
    "sg:phone":"+1 512 990 7466",
    "sg:postcode":"78660",
    "sg:province":"TX",
    "sg:tags":[
        "communication",
        "radiotelephone"
    ],
    "wof:name":"Centex Wireless",
    "wof:placetype":"venue"
},
  "geometry": {"coordinates":[-97.657139,30.418856],"type":"Point"}
}