{
  "type": "Feature",
  "properties": {
    "iso:country":"US",
    "sg:address":"2415 S Dairy Ashford St",
    "sg:city":"Houston",
    "sg:classifiers":[
        {
            "category":"Wholesale",
            "subcategory":"Machinery & Supplies",
            "type":"Manufacturing & Wholesale Goods"
        }
    ],
    "sg:phone":"+1 281 759 7483",
    "sg:postcode":"77077",
    "sg:province":"TX",
    "sg:tags":[
        "equipment",
        "establishment"
    ],
    "wof:name":"J W & Associates Professional",
    "wof:placetype":"venue"
},
  "geometry": {"coordinates":[-95.605835,29.739053],"type":"Point"}
}