{
  "type": "Feature",
  "properties": {
    "iso:country":"US",
    "sg:address":"2208 N Loop 250 W",
    "sg:city":"Midland",
    "sg:classifiers":[
        {
            "category":"Health Services",
            "subcategory":"Clinic",
            "type":"Services"
        }
    ],
    "sg:phone":"+1 432 522 1354",
    "sg:postcode":"79707",
    "sg:province":"TX",
    "sg:tags":[
        "specialty",
        "outpatient"
    ],
    "wof:name":"Alliance Care Of Texas",
    "wof:placetype":"venue"
},
  "geometry": {"coordinates":[-102.15432699999999,32.000973],"type":"Point"}
}