{
  "type": "Feature",
  "properties": {
    "iso:country":"US",
    "sg:address":"1716 Parkside Ave",
    "sg:city":"Irving",
    "sg:classifiers":[
        {
            "category":"Manufacturing",
            "subcategory":"Rubber & Plastics",
            "type":"Manufacturing & Wholesale Goods"
        }
    ],
    "sg:phone":"+1 972 254 2541",
    "sg:postcode":"75061",
    "sg:province":"TX",
    "sg:tags":[
        "injection",
        "molding"
    ],
    "wof:name":"C & G Plastics Inc",
    "wof:placetype":"venue"
},
  "geometry": {"coordinates":[-96.972528,32.816083],"type":"Point"}
}