{
  "type": "Feature",
  "properties": {
    "iso:country":"US",
    "sg:address":"820 W Brown St",
    "sg:city":"Pampa",
    "sg:classifiers":[
        {
            "category":"Retail",
            "subcategory":"Auto Repair",
            "type":"Services"
        }
    ],
    "sg:phone":"+1 806 665 9141",
    "sg:postcode":"79065",
    "sg:province":"TX",
    "sg:tags":[
        "body"
    ],
    "wof:name":"Pampa Body Shop",
    "wof:placetype":"venue"
},
  "geometry": {"coordinates":[-100.968569,35.527596],"type":"Point"}
}