{
  "type": "Feature",
  "properties": {
    "iso:country":"US",
    "sg:address":"105 E South St",
    "sg:city":"Uvalde",
    "sg:classifiers":[
        {
            "category":"Sports & Exercise",
            "subcategory":"Gym",
            "type":"Entertainment"
        }
    ],
    "sg:phone":"+1 830 591 1000",
    "sg:postcode":"78801",
    "sg:province":"TX",
    "sg:tags":[
        "fitness",
        "physical",
        "facility"
    ],
    "wof:name":"Fit For Life",
    "wof:placetype":"venue"
},
  "geometry": {"coordinates":[-99.785077,29.209089],"type":"Point"}
}