{
  "type": "Feature",
  "properties": {
    "iso:country":"US",
    "sg:address":"13835 Nacogdoches Rd",
    "sg:city":"San Antonio",
    "sg:classifiers":[
        {
            "category":"Restaurant",
            "type":"Food & Drink"
        }
    ],
    "sg:phone":"+1 210 651 1990",
    "sg:postcode":"78217",
    "sg:province":"TX",
    "wof:name":"Checkers Diner",
    "wof:placetype":"venue"
},
  "geometry": {"coordinates":[-98.38727,29.566449],"type":"Point"}
}