{
  "type": "Feature",
  "properties": {
    "iso:country":"US",
    "sg:address":"1001 US Hwy 77 Alt",
    "sg:city":"Yoakum",
    "sg:classifiers":[
        {
            "category":"Real Estate",
            "subcategory":"Developer",
            "type":"Services"
        }
    ],
    "sg:phone":"+1 361 293 9959",
    "sg:postcode":"77995",
    "sg:province":"TX",
    "sg:tags":[
        "cemetery"
    ],
    "wof:name":"Yoakum Restland Cemetery",
    "wof:placetype":"venue"
},
  "geometry": {"coordinates":[-97.14533,29.317631],"type":"Point"}
}