{
  "type": "Feature",
  "properties": {
    "iso:country":"US",
    "sg:address":"1015 N Broadway St",
    "sg:city":"La Porte",
    "sg:classifiers":[
        {
            "category":"Home & Garden",
            "subcategory":"Household Appliances",
            "type":"Retail Goods"
        }
    ],
    "sg:phone":"+1 281 471 5735",
    "sg:postcode":"77571",
    "sg:province":"TX",
    "wof:name":"Painted Pony & Quilts",
    "wof:placetype":"venue"
},
  "geometry": {"coordinates":[-95.019609,29.67726],"type":"Point"}
}