{
  "type": "Feature",
  "properties": {
    "iso:country":"US",
    "sg:address":"10427 Shadow Oaks Dr",
    "sg:city":"Houston",
    "sg:classifiers":[
        {
            "category":"Cinema",
            "subcategory":"Movie Rental",
            "type":"Entertainment"
        }
    ],
    "sg:phone":"+1 713 461 3454",
    "sg:postcode":"77043",
    "sg:province":"TX",
    "sg:tags":[
        "leasing",
        "video",
        "disc",
        "tape"
    ],
    "wof:name":"A Plus Video",
    "wof:placetype":"venue"
},
  "geometry": {"coordinates":[-95.55582200000001,29.793639],"type":"Point"}
}