{
  "type": "Feature",
  "properties": {
    "iso:country":"US",
    "sg:address":"5599 San Felipe St Ste 300",
    "sg:city":"Houston",
    "sg:classifiers":[
        {
            "category":"Wholesale",
            "subcategory":"Computers",
            "type":"Manufacturing & Wholesale Goods"
        },
        {
            "category":"Professional",
            "subcategory":"Computer Services",
            "type":"Services"
        }
    ],
    "sg:phone":"+1 713 513 3000",
    "sg:postcode":"77056",
    "sg:province":"TX",
    "sg:tags":[
        "repair"
    ],
    "wof:name":"Atos Origin",
    "wof:placetype":"venue"
},
  "geometry": {"coordinates":[-95.47444400000001,29.749902],"type":"Point"}
}