{
  "type": "Feature",
  "properties": {
    "iso:country":"US",
    "sg:address":"106 S Cedar Ridge Dr",
    "sg:city":"Duncanville",
    "sg:classifiers":[
        {
            "category":"Shopping",
            "subcategory":"Jewelry",
            "type":"Retail Goods"
        }
    ],
    "sg:phone":"+1 972 296 4319",
    "sg:postcode":"75116",
    "sg:province":"TX",
    "wof:name":"Milke's Mfg-Jewelers",
    "wof:placetype":"venue"
},
  "geometry": {"coordinates":[-96.925697,32.650101],"type":"Point"}
}