{
  "type": "Feature",
  "properties": {
    "iso:country":"US",
    "sg:address":"2003 US Hwy 380",
    "sg:city":"Bridgeport",
    "sg:classifiers":[
        {
            "category":"Home & Garden",
            "subcategory":"Mobile Homes",
            "type":"Retail Goods"
        }
    ],
    "sg:phone":"+1 940 683 2919",
    "sg:postcode":"76426",
    "sg:province":"TX",
    "wof:name":"J & J Mobile Homes Inc",
    "wof:placetype":"venue"
},
  "geometry": {"coordinates":[-97.744985,33.22236],"type":"Point"}
}