{
  "type": "Feature",
  "properties": {
    "iso:country":"US",
    "sg:address":"2307 Oakshire Cove",
    "sg:city":"Cedar Park",
    "sg:classifiers":[
        {
            "category":"Professional",
            "type":"Services"
        }
    ],
    "sg:phone":"+1 512 249 6654",
    "sg:postcode":"78613",
    "sg:province":"TX",
    "wof:name":"Brainworks",
    "wof:placetype":"venue"
},
  "geometry": {"coordinates":[-97.82752000000001,30.476203],"type":"Point"}
}