{
  "type": "Feature",
  "properties": {
    "iso:country":"US",
    "sg:address":"2104 Taft St",
    "sg:city":"Wichita Falls",
    "sg:classifiers":[
        {
            "category":"Home & Garden",
            "subcategory":"Furniture",
            "type":"Retail Goods"
        }
    ],
    "sg:phone":"+1 940 766 4433",
    "sg:postcode":"76309",
    "sg:province":"TX",
    "sg:tags":[
        "top",
        "counter"
    ],
    "wof:name":"Breegle Custom Countertops",
    "wof:placetype":"venue"
},
  "geometry": {"coordinates":[-98.518939,33.889901],"type":"Point"}
}