{
  "type": "Feature",
  "properties": {
    "iso:country":"US",
    "sg:address":"221 N 1st St",
    "sg:city":"Harlingen",
    "sg:classifiers":[
        {
            "category":"Retail",
            "subcategory":"Auto Repair",
            "type":"Services"
        }
    ],
    "sg:phone":"+1 956 425 4580",
    "sg:postcode":"78550",
    "sg:province":"TX",
    "sg:tags":[
        "exhaust"
    ],
    "wof:name":"Gutierrez Muffler Shop",
    "wof:placetype":"venue"
},
  "geometry": {"coordinates":[-97.695691,26.19464],"type":"Point"}
}