{
  "type": "Feature",
  "properties": {
    "iso:country":"US",
    "sg:address":"411 S 12th St",
    "sg:city":"Nederland",
    "sg:classifiers":[
        {
            "category":"Professional",
            "type":"Services"
        }
    ],
    "sg:phone":"+1 409 722 4036",
    "sg:postcode":"77627",
    "sg:province":"TX",
    "wof:name":"Boskoop Corp",
    "wof:placetype":"venue"
},
  "geometry": {"coordinates":[-93.985125,29.972],"type":"Point"}
}