{
  "type": "Feature",
  "properties": {
    "iso:country":"US",
    "sg:address":"6409 W University Blvd",
    "sg:city":"Odessa",
    "sg:classifiers":[
        {
            "category":"Retail",
            "subcategory":"Repair Shop",
            "type":"Services"
        }
    ],
    "sg:phone":"+1 432 530 0915",
    "sg:postcode":"79764",
    "sg:province":"TX",
    "sg:tags":[
        "appliance"
    ],
    "wof:name":"Basin Appliance Repair",
    "wof:placetype":"venue"
},
  "geometry": {"coordinates":[-102.455609,31.851449],"type":"Point"}
}