{
  "type": "Feature",
  "properties": {
    "iso:country":"US",
    "sg:address":"11601 Katy Fwy",
    "sg:city":"Houston",
    "sg:classifiers":[
        {
            "category":"Wholesale",
            "subcategory":"Electrical",
            "type":"Manufacturing & Wholesale Goods"
        }
    ],
    "sg:phone":"+1 281 293 8585",
    "sg:postcode":"77079",
    "sg:province":"TX",
    "sg:tags":[
        "equipment"
    ],
    "wof:name":"Airflow Systems",
    "wof:placetype":"venue"
},
  "geometry": {"coordinates":[-95.588188,29.78415],"type":"Point"}
}