{
  "type": "Feature",
  "properties": {
    "iso:country":"US",
    "sg:address":"111 Gum Springs Rd",
    "sg:city":"Longview",
    "sg:classifiers":[
        {
            "category":"Shopping",
            "subcategory":"Computers & Home Electronics",
            "type":"Retail Goods"
        }
    ],
    "sg:phone":"+1 903 660 3894",
    "sg:postcode":"75602",
    "sg:province":"TX",
    "sg:tags":[
        "radio",
        "television",
        "electronic",
        "store"
    ],
    "wof:name":"Larry D Myers",
    "wof:placetype":"venue"
},
  "geometry": {"coordinates":[-94.71370400000001,32.490898],"type":"Point"}
}