{
  "type": "Feature",
  "properties": {
    "iso:country":"US",
    "sg:address":"506 N Church St",
    "sg:city":"Decatur",
    "sg:classifiers":[
        {
            "category":"Retail",
            "subcategory":"Repair Shop",
            "type":"Services"
        }
    ],
    "sg:phone":"+1 940 627 2250",
    "sg:postcode":"76234",
    "sg:province":"TX",
    "wof:name":"Sturgeon Horseshoeing",
    "wof:placetype":"venue"
},
  "geometry": {"coordinates":[-97.585308,33.238094],"type":"Point"}
}