{
  "type": "Feature",
  "properties": {
    "iso:country":"US",
    "sg:address":"23014 Red River Dr",
    "sg:city":"Katy",
    "sg:classifiers":[
        {
            "category":"Building & Trades",
            "subcategory":"Construction",
            "type":"Services"
        },
        {
            "category":"Military Area",
            "subcategory":"Armory",
            "type":"Public Place"
        }
    ],
    "sg:phone":"+1 281 693 0795",
    "sg:postcode":"77450",
    "sg:province":"TX",
    "sg:tags":[
        "repair",
        "fence-sales",
        "fence",
        "contractor"
    ],
    "wof:name":"Martin Deck And Fence Company",
    "wof:placetype":"venue"
},
  "geometry": {"coordinates":[-95.77096400000001,29.77285],"type":"Point"}
}