{
  "type": "Feature",
  "properties": {
    "iso:country":"US",
    "sg:address":"1126 State Hwy 6",
    "sg:city":"Dublin",
    "sg:classifiers":[
        {
            "category":"Retail",
            "subcategory":"Repair Shop",
            "type":"Services"
        }
    ],
    "sg:phone":"+1 254 445 2701",
    "sg:postcode":"76446",
    "sg:province":"TX",
    "sg:tags":[
        "truck"
    ],
    "wof:name":"Ward's Repair",
    "wof:placetype":"venue"
},
  "geometry": {"coordinates":[-98.28454600000001,32.090143],"type":"Point"}
}