{
  "type": "Feature",
  "properties": {
    "iso:country":"US",
    "sg:address":"906 E 5th St",
    "sg:city":"Austin",
    "sg:classifiers":[
        {
            "category":"Professional",
            "type":"Services"
        },
        {
            "category":"Utilities",
            "subcategory":"Fuel Oil & Lpg",
            "type":"Services"
        }
    ],
    "sg:phone":"+1 512 493 0929",
    "sg:postcode":"78702",
    "sg:province":"TX",
    "sg:tags":[
        "development",
        "field",
        "exploration",
        "gas"
    ],
    "wof:name":"Travis Energy",
    "wof:placetype":"venue"
},
  "geometry": {"coordinates":[-97.73390000000001,30.264519],"type":"Point"}
}