{
  "type": "Feature",
  "properties": {
    "iso:country":"US",
    "sg:address":"1414 Post Office St",
    "sg:city":"Galveston",
    "sg:classifiers":[
        {
            "category":"Banks & Credit Unions",
            "subcategory":"Investment Brokerage",
            "type":"Services"
        }
    ],
    "sg:phone":"+1 409 765 9528",
    "sg:postcode":"77550",
    "sg:province":"TX",
    "wof:name":"Financial Advice Securities",
    "wof:placetype":"venue"
},
  "geometry": {"coordinates":[-94.783345,29.307187],"type":"Point"}
}