{
  "type": "Feature",
  "properties": {
    "iso:country":"US",
    "sg:address":"10660 Almeda-Genoa Rd",
    "sg:city":"Houston",
    "sg:classifiers":[
        {
            "category":"Home & Garden",
            "subcategory":"Household Appliances",
            "type":"Retail Goods"
        }
    ],
    "sg:phone":"+1 713 943 7002",
    "sg:postcode":"77034",
    "sg:province":"TX",
    "sg:tags":[
        "liquefied",
        "gas",
        "petroleum"
    ],
    "wof:name":"Roys Gas Grills",
    "wof:placetype":"venue"
},
  "geometry": {"coordinates":[-95.22297399999999,29.627699],"type":"Point"}
}