{
  "type": "Feature",
  "properties": {
    "iso:country":"US",
    "sg:address":"123 E Hidalgo Ave",
    "sg:city":"Raymondville",
    "sg:classifiers":[
        {
            "category":"Home & Garden",
            "subcategory":"Household Appliances",
            "type":"Retail Goods"
        }
    ],
    "sg:phone":"+1 956 689 3620",
    "sg:postcode":"78580",
    "sg:province":"TX",
    "sg:tags":[
        "rug",
        "carpet"
    ],
    "wof:name":"Ken's Furniture",
    "wof:placetype":"venue"
},
  "geometry": {"coordinates":[-97.782329,26.481895],"type":"Point"}
}