{
  "type": "Feature",
  "properties": {
    "iso:country":"US",
    "sg:address":"6170 Sherry Ln",
    "sg:city":"Dallas",
    "sg:classifiers":[
        {
            "category":"Health Services",
            "subcategory":"Doctor",
            "type":"Services"
        }
    ],
    "sg:phone":"+1 214 373 4233",
    "sg:postcode":"75225",
    "sg:province":"TX",
    "sg:tags":[
        "medical"
    ],
    "wof:name":"Glowing Skin",
    "wof:placetype":"venue"
},
  "geometry": {"coordinates":[-96.804551,32.862098],"type":"Point"}
}