{
  "type": "Feature",
  "properties": {
    "iso:country":"US",
    "sg:address":"5658 Bear Ln",
    "sg:city":"Corpus Christi",
    "sg:classifiers":[
        {
            "category":"Professional",
            "type":"Services"
        }
    ],
    "sg:phone":"+1 361 289 5881",
    "sg:postcode":"78405",
    "sg:province":"TX",
    "sg:tags":[
        "establishment"
    ],
    "wof:name":"Ryder Ate",
    "wof:placetype":"venue"
},
  "geometry": {"coordinates":[-97.474357,27.764132],"type":"Point"}
}