{
  "type": "Feature",
  "properties": {
    "iso:country":"US",
    "sg:address":"7509 Shortcake Ct",
    "sg:city":"Fort Worth",
    "sg:classifiers":[
        {
            "category":"Building & Trades",
            "subcategory":"Construction",
            "type":"Services"
        }
    ],
    "sg:phone":"+1 817 237 7531",
    "sg:postcode":"76135",
    "sg:province":"TX",
    "sg:tags":[
        "house"
    ],
    "wof:name":"Corbin George Construction Co",
    "wof:placetype":"venue"
},
  "geometry": {"coordinates":[-97.505835,32.85874],"type":"Point"}
}