{
  "type": "Feature",
  "properties": {
    "iso:country":"US",
    "sg:address":"11521 Ranch Rd 620 N",
    "sg:city":"Austin",
    "sg:classifiers":[
        {
            "category":"Insurance",
            "subcategory":"Insurance Agent",
            "type":"Services"
        }
    ],
    "sg:phone":"+1 512 996 0373",
    "sg:postcode":"78726",
    "sg:province":"TX",
    "wof:name":"Nationwide Insurance",
    "wof:placetype":"venue"
},
  "geometry": {"coordinates":[-97.828104,30.453294],"type":"Point"}
}