{
  "type": "Feature",
  "properties": {
    "iso:country":"US",
    "sg:address":"4122 Texas Blvd",
    "sg:city":"Texarkana",
    "sg:classifiers":[
        {
            "category":"Professional",
            "subcategory":"Lawyer & Legal Services",
            "type":"Services"
        }
    ],
    "sg:phone":"+1 903 794 1303",
    "sg:postcode":"75503",
    "sg:province":"TX",
    "sg:tags":[
        "attorney",
        "practice"
    ],
    "wof:name":"Young, Damon Attorney At Law",
    "wof:placetype":"venue"
},
  "geometry": {"coordinates":[-94.053034,33.456333],"type":"Point"}
}