{
  "type": "Feature",
  "properties": {
    "iso:country":"US",
    "sg:address":"1111 League Line Rd",
    "sg:city":"Conroe",
    "sg:classifiers":[
        {
            "category":"Shopping",
            "subcategory":"Luggage & Leather Goods",
            "type":"Retail Goods"
        }
    ],
    "sg:phone":"+1 936 788 5656",
    "sg:postcode":"77303",
    "sg:province":"TX",
    "wof:name":"Samsonite",
    "wof:placetype":"venue"
},
  "geometry": {"coordinates":[-95.47859699999999,30.365307],"type":"Point"}
}