{
  "type": "Feature",
  "properties": {
    "iso:country":"US",
    "sg:address":"1003 Alden Dr",
    "sg:city":"Cedar Hill",
    "sg:classifiers":[
        {
            "category":"Banks & Credit Unions",
            "subcategory":"Bank",
            "type":"Services"
        }
    ],
    "sg:phone":"+1 972 293 8131",
    "sg:postcode":"75104",
    "sg:province":"TX",
    "sg:tags":[
        "federal",
        "agency"
    ],
    "wof:name":"Import Plus",
    "wof:placetype":"venue"
},
  "geometry": {"coordinates":[-96.943185,32.571684],"type":"Point"}
}