{
  "type": "Feature",
  "properties": {
    "iso:country":"US",
    "sg:address":"16340 Park Ten Pl",
    "sg:city":"Houston",
    "sg:classifiers":[
        {
            "category":"Professional",
            "subcategory":"Engineering",
            "type":"Services"
        }
    ],
    "sg:phone":"+1 281 647 9696",
    "sg:postcode":"77084",
    "sg:province":"TX",
    "sg:tags":[
        "consulting",
        "oil",
        "gas",
        "engineer"
    ],
    "sg:website":"www.alliance-engineering.com",
    "wof:name":"Alliance Engineering Inc",
    "wof:placetype":"venue"
},
  "geometry": {"coordinates":[-95.66404900000001,29.786882],"type":"Point"}
}