{
  "type": "Feature",
  "properties": {
    "iso:country":"US",
    "sg:address":"1310 S Lamar Blvd",
    "sg:city":"Austin",
    "sg:classifiers":[
        {
            "category":"Manufacturing",
            "subcategory":"Rubber & Plastics",
            "type":"Manufacturing & Wholesale Goods"
        },
        {
            "category":"Professional",
            "subcategory":"Printing & Photocopies",
            "type":"Services"
        }
    ],
    "sg:phone":"+1 512 443 0818",
    "sg:postcode":"78704",
    "sg:province":"TX",
    "sg:tags":[
        "stamp"
    ],
    "sg:website":"http://www.abbeyprints.com",
    "wof:name":"Abbey Printing",
    "wof:placetype":"venue"
},
  "geometry": {"coordinates":[-97.76297599999999,30.253625],"type":"Point"}
}