{
  "type": "Feature",
  "properties": {
    "iso:country":"US",
    "sg:address":"23103 Fairvine Park Dr",
    "sg:city":"Katy",
    "sg:classifiers":[
        {
            "category":"Professional",
            "subcategory":"Engineering",
            "type":"Services"
        }
    ],
    "sg:phone":"+1 281 693 2067",
    "sg:postcode":"77494",
    "sg:province":"TX",
    "wof:name":"J P Hopko LLC",
    "wof:placetype":"venue"
},
  "geometry": {"coordinates":[-95.768485,29.749897],"type":"Point"}
}