{
  "type": "Feature",
  "properties": {
    "iso:country":"US",
    "sg:address":"1501 Shady Oaks Ln",
    "sg:city":"Fort Worth",
    "sg:classifiers":[
        {
            "category":"Banks & Credit Unions",
            "subcategory":"Investment Brokerage",
            "type":"Services"
        }
    ],
    "sg:phone":"+1 817 738 6702",
    "sg:postcode":"76107",
    "sg:province":"TX",
    "wof:name":"Aguilar Assoc Group",
    "wof:placetype":"venue"
},
  "geometry": {"coordinates":[-97.41870900000001,32.742585],"type":"Point"}
}