{
  "type": "Feature",
  "properties": {
    "iso:country":"US",
    "sg:address":"7415 Lake Whitney Dr",
    "sg:city":"Arlington",
    "sg:classifiers":[
        {
            "category":"Retail",
            "subcategory":"Laundry & Dry Cleaning",
            "type":"Services"
        }
    ],
    "sg:phone":"+1 817 468 8501",
    "sg:postcode":"76002",
    "sg:province":"TX",
    "wof:name":"Saving Carpet Cleaning",
    "wof:placetype":"venue"
},
  "geometry": {"coordinates":[-97.072103,32.628482],"type":"Point"}
}