{
  "type": "Feature",
  "properties": {
    "iso:country":"US",
    "sg:address":"11075 Harry Hines Blvd",
    "sg:city":"Dallas",
    "sg:classifiers":[
        {
            "category":"Restaurant",
            "type":"Food & Drink"
        }
    ],
    "sg:phone":"+1 972 241 2171",
    "sg:postcode":"75229",
    "sg:province":"TX",
    "sg:tags":[
        "mexican"
    ],
    "wof:name":"El Fenix Mexican Restaurants",
    "wof:placetype":"venue"
},
  "geometry": {"coordinates":[-96.88659699999999,32.883499],"type":"Point"}
}