{
  "type": "Feature",
  "properties": {
    "iso:country":"US",
    "sg:address":"511 Pratt Rd",
    "sg:city":"Red Oak",
    "sg:classifiers":[
        {
            "category":"Professional",
            "type":"Services"
        }
    ],
    "sg:phone":"+1 972 576 3638",
    "sg:postcode":"75154",
    "sg:province":"TX",
    "wof:name":"Divinia Inc",
    "wof:placetype":"venue"
},
  "geometry": {"coordinates":[-96.754119,32.509412],"type":"Point"}
}