{
  "type": "Feature",
  "properties": {
    "iso:country":"US",
    "sg:address":"611 Carpenter Ave",
    "sg:city":"Austin",
    "sg:classifiers":[
        {
            "category":"Professional",
            "type":"Services"
        }
    ],
    "sg:phone":"+1 512 836 5533",
    "sg:postcode":"78753",
    "sg:province":"TX",
    "sg:tags":[
        "communication"
    ],
    "wof:name":"GP Communications",
    "wof:placetype":"venue"
},
  "geometry": {"coordinates":[-97.698594,30.35761],"type":"Point"}
}