{
  "type": "Feature",
  "properties": {
    "iso:country":"US",
    "sg:address":"2313 Decatur Ave",
    "sg:city":"Fort Worth",
    "sg:classifiers":[
        {
            "category":"Retail",
            "subcategory":"Auto Repair",
            "type":"Services"
        }
    ],
    "sg:phone":"+1 817 740 1010",
    "sg:postcode":"76106",
    "sg:province":"TX",
    "sg:tags":[
        "truck"
    ],
    "wof:name":"Buck's Collision Ctr Inc",
    "wof:placetype":"venue"
},
  "geometry": {"coordinates":[-97.33737000000001,32.787738],"type":"Point"}
}