{
  "type": "Feature",
  "properties": {
    "iso:country":"US",
    "sg:address":"701 S Capital of Texas Hwy Ste E510",
    "sg:city":"West Lake Hills",
    "sg:classifiers":[
        {
            "category":"Food & Beverages",
            "subcategory":"Bakery",
            "type":"Retail Goods"
        }
    ],
    "sg:phone":"+1 512 306 8443",
    "sg:postcode":"78746",
    "sg:province":"TX",
    "sg:tags":[
        "sandwich"
    ],
    "sg:website":"www.quiznos.com",
    "wof:name":"Quiznos",
    "wof:placetype":"venue"
},
  "geometry": {"coordinates":[-97.828011,30.292225],"type":"Point"}
}