{
  "type": "Feature",
  "properties": {
    "iso:country":"US",
    "sg:address":"200 Fitness Ct",
    "sg:city":"Coppell",
    "sg:classifiers":[
        {
            "category":"Sports & Exercise",
            "subcategory":"Gym",
            "type":"Entertainment"
        }
    ],
    "sg:phone":"+1 972 471 2345",
    "sg:postcode":"75019",
    "sg:province":"TX",
    "sg:tags":[
        "fitness",
        "physical",
        "facility"
    ],
    "wof:name":"Everybody Fits",
    "wof:placetype":"venue"
},
  "geometry": {"coordinates":[-96.99572499999999,32.971674],"type":"Point"}
}