{
  "type": "Feature",
  "properties": {
    "iso:country":"US",
    "sg:address":"2111 Rose St",
    "sg:city":"Irving",
    "sg:classifiers":[
        {
            "category":"Retail",
            "subcategory":"Auto Rental",
            "type":"Services"
        }
    ],
    "sg:phone":"+1 972 438 3993",
    "sg:postcode":"75061",
    "sg:province":"TX",
    "sg:tags":[
        "car"
    ],
    "wof:name":"Enterprise Rent-A-Car",
    "wof:placetype":"venue"
},
  "geometry": {"coordinates":[-96.93800400000001,32.836102],"type":"Point"}
}