{
  "type": "Feature",
  "properties": {
    "iso:country":"US",
    "sg:address":"5206 Beacon Dr",
    "sg:city":"Austin",
    "sg:classifiers":[
        {
            "category":"Professional",
            "type":"Services"
        }
    ],
    "sg:phone":"+1 512 266 8226",
    "sg:postcode":"78734",
    "sg:province":"TX",
    "sg:tags":[
        "establishment"
    ],
    "wof:name":"OGM Corp",
    "wof:placetype":"venue"
},
  "geometry": {"coordinates":[-97.92464,30.412974],"type":"Point"}
}