{
  "type": "Feature",
  "properties": {
    "iso:country":"US",
    "sg:address":"7517 Arborside Dr",
    "sg:city":"Rowlett",
    "sg:classifiers":[
        {
            "category":"Professional",
            "subcategory":"Business Services",
            "type":"Services"
        }
    ],
    "sg:phone":"+1 972 475 2223",
    "sg:postcode":"75089",
    "sg:province":"TX",
    "wof:name":"Laura Drew Interiors",
    "wof:placetype":"venue"
},
  "geometry": {"coordinates":[-96.516718,32.924922],"type":"Point"}
}