{
  "type": "Feature",
  "properties": {
    "iso:country":"US",
    "sg:address":"2917 Oak Forest Dr",
    "sg:city":"Grapevine",
    "sg:classifiers":[
        {
            "category":"Professional",
            "subcategory":"Management & Consulting",
            "type":"Services"
        }
    ],
    "sg:phone":"+1 817 481 7939",
    "sg:postcode":"76051",
    "sg:province":"TX",
    "sg:tags":[
        "business"
    ],
    "wof:name":"Aritex Consultants Inc",
    "wof:placetype":"venue"
},
  "geometry": {"coordinates":[-97.11303100000001,32.910796],"type":"Point"}
}