{
  "type": "Feature",
  "properties": {
    "iso:country":"US",
    "sg:address":"814 May St",
    "sg:city":"Fort Worth",
    "sg:classifiers":[
        {
            "category":"Professional",
            "subcategory":"Business Services",
            "type":"Services"
        }
    ],
    "sg:phone":"+1 806 747 0257",
    "sg:postcode":"76104",
    "sg:province":"TX",
    "wof:name":"Ace Bond Co",
    "wof:placetype":"venue"
},
  "geometry": {"coordinates":[-97.329173,32.735694],"type":"Point"}
}