{
  "type": "Feature",
  "properties": {
    "iso:country":"US",
    "sg:address":"1005 Crestview St",
    "sg:city":"Round Rock",
    "sg:classifiers":[
        {
            "category":"Professional",
            "subcategory":"Computer Services",
            "type":"Services"
        }
    ],
    "sg:phone":"+1 512 626 7239",
    "sg:postcode":"78681",
    "sg:province":"TX",
    "sg:tags":[
        "datum"
    ],
    "wof:name":"Poetry Box",
    "wof:placetype":"venue"
},
  "geometry": {"coordinates":[-97.705414,30.501334],"type":"Point"}
}