{
  "type": "Feature",
  "properties": {
    "iso:country":"US",
    "sg:address":"10000 Emmett F Lowry Expy",
    "sg:city":"Texas City",
    "sg:classifiers":[
        {
            "category":"Shopping",
            "subcategory":"Clothing, Apparel, & Fashions",
            "type":"Retail Goods"
        }
    ],
    "sg:phone":"+1 409 986 8446",
    "sg:postcode":"77591",
    "sg:province":"TX",
    "wof:name":"Rave",
    "wof:placetype":"venue"
},
  "geometry": {"coordinates":[-95.02682799999999,29.403789],"type":"Point"}
}