{
  "type": "Feature",
  "properties": {
    "iso:country":"US",
    "sg:address":"8209 Claiborne St",
    "sg:city":"Houston",
    "sg:classifiers":[
        {
            "category":"Building & Trades",
            "subcategory":"Construction",
            "type":"Services"
        }
    ],
    "sg:phone":"+1 713 635 1617",
    "sg:postcode":"77078",
    "sg:province":"TX",
    "sg:tags":[
        "contractor"
    ],
    "wof:name":"Garcia Dry Wall Co",
    "wof:placetype":"venue"
},
  "geometry": {"coordinates":[-95.27598399999999,29.853568],"type":"Point"}
}