{
  "type": "Feature",
  "properties": {
    "iso:country":"US",
    "sg:address":"216 Livingston Rd",
    "sg:city":"Weatherford",
    "sg:classifiers":[
        {
            "category":"Wholesale",
            "subcategory":"Groceries",
            "type":"Manufacturing & Wholesale Goods"
        }
    ],
    "sg:phone":"+1 817 613 0654",
    "sg:postcode":"76087",
    "sg:province":"TX",
    "sg:tags":[
        "general"
    ],
    "wof:name":"J Tuley Distributors",
    "wof:placetype":"venue"
},
  "geometry": {"coordinates":[-97.828844,32.626427],"type":"Point"}
}