{
  "type": "Feature",
  "properties": {
    "iso:country":"US",
    "sg:address":"3103 Grand Ave",
    "sg:city":"Dallas",
    "sg:classifiers":[
        {
            "category":"Restaurant",
            "type":"Food & Drink"
        }
    ],
    "sg:phone":"+1 214 565 0310",
    "sg:postcode":"75215",
    "sg:province":"TX",
    "wof:name":"Lady Di's Restaurant",
    "wof:placetype":"venue"
},
  "geometry": {"coordinates":[-96.76817200000001,32.774867],"type":"Point"}
}