{
  "type": "Feature",
  "properties": {
    "iso:country":"US",
    "sg:address":"2128 Hwy 190 W",
    "sg:city":"Livingston",
    "sg:classifiers":[
        {
            "category":"Personal",
            "subcategory":"Beauty Salon",
            "type":"Services"
        }
    ],
    "sg:phone":"+1 936 327 3544",
    "sg:postcode":"77351",
    "sg:province":"TX",
    "wof:name":"His & Hers Hair Care",
    "wof:placetype":"venue"
},
  "geometry": {"coordinates":[-94.953309,30.712026],"type":"Point"}
}