{
  "type": "Feature",
  "properties": {
    "iso:country":"US",
    "sg:address":"8718 Stella Link Rd",
    "sg:city":"Houston",
    "sg:classifiers":[
        {
            "category":"Shopping",
            "subcategory":"Discount & Variety Stores",
            "type":"Retail Goods"
        }
    ],
    "sg:phone":"+1 713 661 7511",
    "sg:postcode":"77025",
    "sg:province":"TX",
    "wof:name":"K-Seven Mart Factory Outl Ctr",
    "wof:placetype":"venue"
},
  "geometry": {"coordinates":[-95.44011999999999,29.689034],"type":"Point"}
}