{
  "type": "Feature",
  "properties": {
    "iso:country":"US",
    "sg:address":"1105 Colquitt St",
    "sg:city":"Houston",
    "sg:classifiers":[
        {
            "category":"Professional",
            "subcategory":"Lawyer & Legal Services",
            "type":"Services"
        }
    ],
    "sg:phone":"+1 713 862 2700",
    "sg:postcode":"77006",
    "sg:province":"TX",
    "wof:name":"Steffler Bruce R Atty",
    "wof:placetype":"venue"
},
  "geometry": {"coordinates":[-95.392899,29.735201],"type":"Point"}
}