{
  "type": "Feature",
  "properties": {
    "iso:country":"US",
    "sg:address":"21302 Meadow Hill Dr",
    "sg:city":"Spring",
    "sg:classifiers":[
        {
            "category":"Social Services",
            "subcategory":"Child Care",
            "type":"Services"
        }
    ],
    "sg:phone":"+1 281 350 0567",
    "sg:postcode":"77388",
    "sg:province":"TX",
    "sg:tags":[
        "day"
    ],
    "wof:name":"Phillips Day Care",
    "wof:placetype":"venue"
},
  "geometry": {"coordinates":[-95.468991,30.073739],"type":"Point"}
}