{
  "type": "Feature",
  "properties": {
    "iso:country":"US",
    "sg:address":"1010 E 10th Street",
    "sg:city":"Austin",
    "sg:classifiers":[
        {
            "category":"Organizations",
            "subcategory":"Religious Organization",
            "type":"Services"
        }
    ],
    "sg:phone":"+1 512 479 0988",
    "sg:postcode":"78702",
    "sg:province":"TX",
    "wof:name":"Rebuild America Austin",
    "wof:placetype":"venue"
},
  "geometry": {"coordinates":[-97.730118,30.268418],"type":"Point"}
}