{
  "type": "Feature",
  "properties": {
    "iso:country":"US",
    "sg:address":"2001 E Cesar Chavez Street",
    "sg:city":"Austin",
    "sg:classifiers":[
        {
            "category":"Bars & Pubs",
            "subcategory":"Nightclub",
            "type":"Food & Drink"
        }
    ],
    "sg:phone":"+1 512 479 5925",
    "sg:postcode":"78702",
    "sg:province":"TX",
    "sg:tags":[
        "nightlife"
    ],
    "wof:name":"Club Calentano",
    "wof:placetype":"venue"
},
  "geometry": {"coordinates":[-97.723169,30.256722],"type":"Point"}
}