{
  "type": "Feature",
  "properties": {
    "iso:country":"US",
    "sg:address":"3312 Jones Ct",
    "sg:city":"Bedford",
    "sg:classifiers":[
        {
            "category":"Professional",
            "subcategory":"Management & Consulting",
            "type":"Services"
        }
    ],
    "sg:phone":"+1 817 540 4119",
    "sg:postcode":"76021",
    "sg:province":"TX",
    "sg:tags":[
        "business"
    ],
    "wof:name":"Shy Lion Inc",
    "wof:placetype":"venue"
},
  "geometry": {"coordinates":[-97.111971,32.86321],"type":"Point"}
}