{
  "type": "Feature",
  "properties": {
    "iso:country":"US",
    "sg:address":"118 N Garfield Ave",
    "sg:city":"Rotan",
    "sg:classifiers":[
        {
            "category":"Banks & Credit Unions",
            "subcategory":"Bank",
            "type":"Services"
        }
    ],
    "sg:phone":"+1 325 735 2224",
    "sg:postcode":"79546",
    "sg:province":"TX",
    "sg:tags":[
        "national"
    ],
    "wof:name":"First National Bank",
    "wof:placetype":"venue"
},
  "geometry": {"coordinates":[-100.467331,32.852639],"type":"Point"}
}