{
  "type": "Feature",
  "properties": {
    "iso:country":"US",
    "sg:address":"604 N Brownson St",
    "sg:city":"Victoria",
    "sg:classifiers":[
        {
            "category":"Building & Trades",
            "subcategory":"Plumbing",
            "type":"Services"
        }
    ],
    "sg:phone":"+1 361 578 3733",
    "sg:postcode":"77901",
    "sg:province":"TX",
    "sg:tags":[
        "conditioning",
        "air",
        "system",
        "contractor"
    ],
    "wof:name":"R & A Heating & Air Cond Co",
    "wof:placetype":"venue"
},
  "geometry": {"coordinates":[-96.988067,28.799041],"type":"Point"}
}