{
  "type": "Feature",
  "properties": {
    "iso:country":"US",
    "sg:address":"14531 Henry Rd",
    "sg:city":"Houston",
    "sg:classifiers":[
        {
            "category":"Retail",
            "subcategory":"Animal Services",
            "type":"Services"
        }
    ],
    "sg:phone":"+1 281 445 3481",
    "sg:postcode":"77060",
    "sg:province":"TX",
    "wof:name":"Lenor John Inc",
    "wof:placetype":"venue"
},
  "geometry": {"coordinates":[-95.38273,29.910026],"type":"Point"}
}