{
  "type": "Feature",
  "properties": {
    "iso:country":"US",
    "sg:address":"619 Jamboree Way",
    "sg:city":"Euless",
    "sg:classifiers":[
        {
            "category":"Banks & Credit Unions",
            "subcategory":"Financial Services",
            "type":"Services"
        }
    ],
    "sg:phone":"+1 817 685 2911",
    "sg:postcode":"76039",
    "sg:province":"TX",
    "sg:tags":[
        "investor"
    ],
    "wof:name":"Clark Kd Investments LLC",
    "wof:placetype":"venue"
},
  "geometry": {"coordinates":[-97.075051,32.878738],"type":"Point"}
}