{
  "type": "Feature",
  "properties": {
    "iso:country":"US",
    "sg:address":"111 N Ave D",
    "sg:city":"Burkburnett",
    "sg:classifiers":[
        {
            "category":"Professional",
            "subcategory":"Accounting & Tax Preparation",
            "type":"Services"
        }
    ],
    "sg:phone":"+1 940 569 2400",
    "sg:postcode":"76354",
    "sg:province":"TX",
    "sg:tags":[
        "accountant"
    ],
    "wof:name":"Kevin Scott Sparks CPA",
    "wof:placetype":"venue"
},
  "geometry": {"coordinates":[-98.569688,34.095117],"type":"Point"}
}