{
  "type": "Feature",
  "properties": {
    "iso:country":"US",
    "sg:address":"10025 Technology Blvd W",
    "sg:city":"Dallas",
    "sg:classifiers":[
        {
            "category":"Health Services",
            "subcategory":"Doctor",
            "type":"Services"
        }
    ],
    "sg:phone":"+1 214 350 7433",
    "sg:postcode":"75220",
    "sg:province":"TX",
    "sg:tags":[
        "orthopedist"
    ],
    "wof:name":"Stryker Orthopaedics",
    "wof:placetype":"venue"
},
  "geometry": {"coordinates":[-96.899197,32.86233],"type":"Point"}
}