{
  "type": "Feature",
  "properties": {
    "iso:country":"US",
    "sg:address":"2210 Belton Dr",
    "sg:city":"Arlington",
    "sg:classifiers":[
        {
            "category":"Home & Garden",
            "subcategory":"Furniture",
            "type":"Retail Goods"
        },
        {
            "category":"Organizations",
            "subcategory":"Professional Association",
            "type":"Services"
        }
    ],
    "sg:phone":"+1 817 419 6631",
    "sg:postcode":"76018",
    "sg:province":"TX",
    "wof:name":"Lzc and Associates",
    "wof:placetype":"venue"
},
  "geometry": {"coordinates":[-97.07187,32.651865],"type":"Point"}
}