{
  "type": "Feature",
  "properties": {
    "iso:country":"US",
    "sg:address":"4236 S Lamar Blvd",
    "sg:city":"Austin",
    "sg:classifiers":[
        {
            "category":"Restaurant",
            "type":"Food & Drink"
        }
    ],
    "sg:menulink":"http://www.allmenus.com/tx/austin/114933-chilis/menu/",
    "sg:phone":"+1 512 441 1899",
    "sg:postcode":"78704",
    "sg:province":"TX",
    "sg:tags":[
        "burger",
        "american",
        "sandwich",
        "tex-mex",
        "soup"
    ],
    "wof:name":"Chili's",
    "wof:placetype":"venue"
},
  "geometry": {"coordinates":[-97.79585,30.236077],"type":"Point"}
}