{
  "type": "Feature",
  "properties": {
    "iso:country":"US",
    "sg:address":"911 W Corsicana St",
    "sg:city":"Athens",
    "sg:classifiers":[
        {
            "category":"Retail",
            "subcategory":"Auto Repair",
            "type":"Services"
        },
        {
            "category":"Autos & Motor Vehicles",
            "subcategory":"Motorcycle Sales",
            "type":"Retail Goods"
        }
    ],
    "sg:phone":"+1 903 675 8778",
    "sg:postcode":"75751",
    "sg:province":"TX",
    "sg:tags":[
        "body"
    ],
    "wof:name":"Garys Paint & Body Shop",
    "wof:placetype":"venue"
},
  "geometry": {"coordinates":[-95.87396099999999,32.202745],"type":"Point"}
}