{
  "type": "Feature",
  "properties": {
    "iso:country":"US",
    "sg:address":"800 Williams St",
    "sg:city":"Marlin",
    "sg:classifiers":[
        {
            "category":"Manufacturing",
            "subcategory":"Food",
            "type":"Manufacturing & Wholesale Goods"
        }
    ],
    "sg:phone":"+1 254 883 2591",
    "sg:postcode":"76661",
    "sg:province":"TX",
    "sg:tags":[
        "frozen",
        "processor"
    ],
    "wof:name":"Jon-Lin Frozen Foods",
    "wof:placetype":"venue"
},
  "geometry": {"coordinates":[-96.899457,31.297372],"type":"Point"}
}