{
  "type": "Feature",
  "properties": {
    "iso:country":"US",
    "sg:address":"10603 Main St",
    "sg:city":"Houston",
    "sg:classifiers":[
        {
            "category":"Retail",
            "subcategory":"Auto Repair",
            "type":"Services"
        }
    ],
    "sg:phone":"+1 713 349 0277",
    "sg:postcode":"77025",
    "sg:province":"TX",
    "wof:name":"Objective Auto Service Plus",
    "wof:placetype":"venue"
},
  "geometry": {"coordinates":[-95.433296,29.67],"type":"Point"}
}