{
  "type": "Feature",
  "properties": {
    "iso:country":"US",
    "sg:address":"14810 Winding Waters Dr",
    "sg:city":"Cypress",
    "sg:classifiers":[
        {
            "category":"Organizations",
            "subcategory":"Religious Organization",
            "type":"Services"
        }
    ],
    "sg:phone":"+1 281 304 0039",
    "sg:postcode":"77429",
    "sg:province":"TX",
    "wof:name":"Potential Quotient Ministries",
    "wof:placetype":"venue"
},
  "geometry": {"coordinates":[-95.68191899999999,29.989208],"type":"Point"}
}