{
  "type": "Feature",
  "properties": {
    "iso:country":"US",
    "sg:address":"5721 Pearce St",
    "sg:city":"The Colony",
    "sg:classifiers":[
        {
            "category":"Building & Trades",
            "subcategory":"Landscaping Services",
            "type":"Services"
        }
    ],
    "sg:phone":"+1 972 624 5693",
    "sg:postcode":"75056",
    "sg:province":"TX",
    "sg:tags":[
        "landscape",
        "contractor"
    ],
    "wof:name":"Ramirez Lawn Svc",
    "wof:placetype":"venue"
},
  "geometry": {"coordinates":[-96.865285,33.094651],"type":"Point"}
}