{
  "type": "Feature",
  "properties": {
    "iso:country":"US",
    "sg:address":"5606 Summerhill Rd",
    "sg:city":"Texarkana",
    "sg:classifiers":[
        {
            "category":"Insurance",
            "subcategory":"Insurance Agent",
            "type":"Services"
        }
    ],
    "sg:phone":"+1 903 792 7610",
    "sg:postcode":"75503",
    "sg:province":"TX",
    "sg:website":"www.tcig.com",
    "wof:name":"Texarkana Consolidated Ins",
    "wof:placetype":"venue"
},
  "geometry": {"coordinates":[-94.070094,33.475093],"type":"Point"}
}