{
  "type": "Feature",
  "properties": {
    "iso:country":"US",
    "sg:address":"9904 Nocturne Cv",
    "sg:city":"Austin",
    "sg:classifiers":[
        {
            "category":"Shopping",
            "subcategory":"Hobbies, Toys, & Games",
            "type":"Retail Goods"
        }
    ],
    "sg:phone":"+1 512 310 1956",
    "sg:postcode":"78750",
    "sg:province":"TX",
    "sg:tags":[
        "video"
    ],
    "wof:name":"Eb Enterprises",
    "wof:placetype":"venue"
},
  "geometry": {"coordinates":[-97.800411,30.443025],"type":"Point"}
}