{
  "type": "Feature",
  "properties": {
    "iso:country":"US",
    "sg:address":"3446 Summerhill Rd",
    "sg:city":"Texarkana",
    "sg:classifiers":[
        {
            "category":"Personal",
            "type":"Services"
        }
    ],
    "sg:phone":"+1 903 794 0727",
    "sg:postcode":"75503",
    "sg:province":"TX",
    "sg:tags":[
        "therapist",
        "massage"
    ],
    "wof:name":"Massage Therapy By J Shelton",
    "wof:placetype":"venue"
},
  "geometry": {"coordinates":[-94.065015,33.453397],"type":"Point"}
}