{
  "type": "Feature",
  "properties": {
    "iso:country":"US",
    "sg:address":"3703 W Green Oaks Blvd",
    "sg:city":"Arlington",
    "sg:classifiers":[
        {
            "category":"Health Services",
            "subcategory":"Optometrist",
            "type":"Services"
        }
    ],
    "sg:phone":"+1 817 654 1999",
    "sg:postcode":"76016",
    "sg:province":"TX",
    "wof:name":"Melvin G Cleveland Od",
    "wof:placetype":"venue"
},
  "geometry": {"coordinates":[-97.191864,32.688652],"type":"Point"}
}