{
  "type": "Feature",
  "properties": {
    "iso:country":"US",
    "sg:address":"1035 Dairy Ashford St",
    "sg:city":"Houston",
    "sg:classifiers":[
        {
            "category":"Personal",
            "type":"Services"
        }
    ],
    "sg:phone":"+1 281 597 0901",
    "sg:postcode":"77079",
    "sg:province":"TX",
    "wof:name":"Adventure Locating",
    "wof:placetype":"venue"
},
  "geometry": {"coordinates":[-95.606466,29.77875],"type":"Point"}
}