{
  "type": "Feature",
  "properties": {
    "iso:country":"US",
    "sg:address":"2707 S Co Rd 1206",
    "sg:city":"Midland",
    "sg:classifiers":[
        {
            "category":"Building & Trades",
            "subcategory":"Construction",
            "type":"Services"
        }
    ],
    "sg:phone":"+1 432 520 6943",
    "sg:postcode":"79706",
    "sg:province":"TX",
    "sg:tags":[
        "roofing",
        "contractor"
    ],
    "wof:name":"Charles Terry Construction Co",
    "wof:placetype":"venue"
},
  "geometry": {"coordinates":[-102.098977,31.963315],"type":"Point"}
}