{
  "type": "Feature",
  "properties": {
    "iso:country":"US",
    "sg:address":"10504 Broadway St",
    "sg:city":"Pearland",
    "sg:classifiers":[
        {
            "category":"Restaurant",
            "type":"Food & Drink"
        },
        {
            "category":"Ice Cream",
            "type":"Food & Drink"
        }
    ],
    "sg:menulink":"http://www.allmenus.com/tx/alvin-pearland/242682-baskin-robbins/menu/",
    "sg:phone":"+1 713 436 5358",
    "sg:postcode":"77584",
    "sg:province":"TX",
    "sg:tags":[
        "american",
        "ice",
        "cream"
    ],
    "wof:name":"Baskin-Robbins",
    "wof:placetype":"venue"
},
  "geometry": {"coordinates":[-95.38333900000001,29.555962],"type":"Point"}
}