{
  "type": "Feature",
  "properties": {
    "iso:country":"US",
    "sg:address":"16969 Larkspur",
    "sg:city":"Conroe",
    "sg:classifiers":[
        {
            "category":"Education",
            "subcategory":"School",
            "type":"Public Place"
        }
    ],
    "sg:phone":"+1 936 273 3239",
    "sg:postcode":"77385",
    "sg:province":"TX",
    "wof:name":"PCAL",
    "wof:placetype":"venue"
},
  "geometry": {"coordinates":[-95.430937,30.211551],"type":"Point"}
}