{
  "type": "Feature",
  "properties": {
    "iso:country":"US",
    "sg:address":"23006 Hampton Forest Ln",
    "sg:city":"Spring",
    "sg:classifiers":[
        {
            "category":"Professional",
            "subcategory":"Management & Consulting",
            "type":"Services"
        }
    ],
    "sg:phone":"+1 281 379 1808",
    "sg:postcode":"77389",
    "sg:province":"TX",
    "sg:tags":[
        "retail",
        "direct",
        "sales"
    ],
    "wof:name":"Wishing Wells",
    "wof:placetype":"venue"
},
  "geometry": {"coordinates":[-95.50927,30.102482],"type":"Point"}
}