{
  "type": "Feature",
  "properties": {
    "iso:country":"US",
    "sg:address":"2647 Culebra Rd",
    "sg:city":"San Antonio",
    "sg:classifiers":[
        {
            "category":"Education",
            "subcategory":"Special Training",
            "type":"Public Place"
        }
    ],
    "sg:phone":"+1 210 432 2125",
    "sg:postcode":"78228",
    "sg:province":"TX",
    "sg:tags":[
        "instruction",
        "driving"
    ],
    "wof:name":"Texas Driving School",
    "wof:placetype":"venue"
},
  "geometry": {"coordinates":[-98.550837,29.447727],"type":"Point"}
}