{
  "type": "Feature",
  "properties": {
    "iso:country":"US",
    "sg:address":"2331 E 50th St",
    "sg:city":"Lubbock",
    "sg:classifiers":[
        {
            "category":"Recreation",
            "subcategory":"Picnic Area",
            "type":"Entertainment"
        }
    ],
    "sg:phone":"+1 806 762 1271",
    "sg:postcode":"79404",
    "sg:province":"TX",
    "sg:tags":[
        "farm",
        "repair",
        "equipment-parts"
    ],
    "wof:name":"Agri- Supply, Inc.",
    "wof:placetype":"venue"
},
  "geometry": {"coordinates":[-101.812416,33.548779],"type":"Point"}
}