{
  "type": "Feature",
  "properties": {
    "iso:country":"US",
    "sg:address":"5435 Cheena Dr",
    "sg:city":"Houston",
    "sg:classifiers":[
        {
            "category":"Health Services",
            "subcategory":"Clinic",
            "type":"Services"
        }
    ],
    "sg:phone":"+1 713 729 0977",
    "sg:postcode":"77096",
    "sg:province":"TX",
    "wof:name":"Acu Medical Inc",
    "wof:placetype":"venue"
},
  "geometry": {"coordinates":[-95.478877,29.668688],"type":"Point"}
}