{
  "type": "Feature",
  "properties": {
    "iso:country":"US",
    "sg:address":"3907 Windsor St",
    "sg:city":"Victoria",
    "sg:classifiers":[
        {
            "category":"Real Estate",
            "subcategory":"Real Estate Operator",
            "type":"Services"
        }
    ],
    "sg:phone":"+1 361 575 2189",
    "sg:postcode":"77901",
    "sg:province":"TX",
    "sg:tags":[
        "building",
        "apartment"
    ],
    "wof:name":"Blueridge Apartments",
    "wof:placetype":"venue"
},
  "geometry": {"coordinates":[-96.997079,28.83323],"type":"Point"}
}