{
  "type": "Feature",
  "properties": {
    "iso:country":"US",
    "sg:address":"6790 FM 3237",
    "sg:city":"Driftwood",
    "sg:classifiers":[
        {
            "category":"Farming",
            "subcategory":"Livestock Farm",
            "type":"Manufacturing & Wholesale Goods"
        }
    ],
    "sg:phone":"+1 512 847 1314",
    "sg:postcode":"78619",
    "sg:province":"TX",
    "sg:tags":[
        "beef",
        "feedlot",
        "cattle"
    ],
    "wof:name":"Dalton R Pape",
    "wof:placetype":"venue"
},
  "geometry": {"coordinates":[-98.026081,30.047996],"type":"Point"}
}