{
  "type": "Feature",
  "properties": {
    "iso:country":"US",
    "sg:address":"2308 Crest Park Dr",
    "sg:city":"Arlington",
    "sg:classifiers":[
        {
            "category":"Food & Beverages",
            "subcategory":"Bakery",
            "type":"Retail Goods"
        }
    ],
    "sg:phone":"+1 817 652 3289",
    "sg:postcode":"76006",
    "sg:province":"TX",
    "sg:tags":[
        "bagel"
    ],
    "wof:name":"Benny's Bagels",
    "wof:placetype":"venue"
},
  "geometry": {"coordinates":[-97.069329,32.779376],"type":"Point"}
}