{
  "type": "Feature",
  "properties": {
    "iso:country":"US",
    "sg:address":"26 Sunrise Dr",
    "sg:city":"Longview",
    "sg:classifiers":[
        {
            "category":"Shopping",
            "type":"Retail Goods"
        }
    ],
    "sg:phone":"+1 903 399 8304",
    "sg:postcode":"75605",
    "sg:province":"TX",
    "wof:name":"Darden Holdings",
    "wof:placetype":"venue"
},
  "geometry": {"coordinates":[-94.79600499999999,32.551159],"type":"Point"}
}