{
  "type": "Feature",
  "properties": {
    "iso:country":"US",
    "sg:address":"608 E Crestwood Dr",
    "sg:city":"Victoria",
    "sg:classifiers":[
        {
            "category":"Professional",
            "subcategory":"Business Services",
            "type":"Services"
        }
    ],
    "sg:phone":"+1 361 575 7486",
    "sg:postcode":"77901",
    "sg:province":"TX",
    "sg:tags":[
        "consultant",
        "petroleum"
    ],
    "wof:name":"Bagnall & Barber Petroleum Inc",
    "wof:placetype":"venue"
},
  "geometry": {"coordinates":[-96.99991900000001,28.828083],"type":"Point"}
}