{
  "type": "Feature",
  "properties": {
    "iso:country":"US",
    "sg:address":"10927 Ivyridge Rd",
    "sg:city":"Houston",
    "sg:classifiers":[
        {
            "category":"Professional",
            "subcategory":"Management & Consulting",
            "type":"Services"
        }
    ],
    "sg:phone":"+1 713 827 0509",
    "sg:postcode":"77043",
    "sg:province":"TX",
    "sg:tags":[
        "marketing",
        "consultant"
    ],
    "wof:name":"Innovative Marketing Solutions",
    "wof:placetype":"venue"
},
  "geometry": {"coordinates":[-95.572272,29.796347],"type":"Point"}
}