{
  "type": "Feature",
  "properties": {
    "iso:country":"US",
    "sg:address":"25661 I- 45",
    "sg:city":"The Woodlands",
    "sg:classifiers":[
        {
            "category":"Banks & Credit Unions",
            "subcategory":"Bank",
            "type":"Services"
        }
    ],
    "sg:phone":"+1 281 364 6691",
    "sg:postcode":"77380",
    "sg:province":"TX",
    "wof:name":"First Victoria",
    "wof:placetype":"venue"
},
  "geometry": {"coordinates":[-95.444703,30.131092],"type":"Point"}
}