{
  "type": "Feature",
  "properties": {
    "iso:country":"US",
    "sg:address":"8434 Gentlewood Ct",
    "sg:city":"Houston",
    "sg:classifiers":[
        {
            "category":"Arts & Performance",
            "subcategory":"Theater",
            "type":"Entertainment"
        }
    ],
    "sg:phone":"+1 281 550 5840",
    "sg:postcode":"77095",
    "sg:province":"TX",
    "sg:tags":[
        "television",
        "program",
        "producer"
    ],
    "wof:name":"Media Visions",
    "wof:placetype":"venue"
},
  "geometry": {"coordinates":[-95.65684400000001,29.905852],"type":"Point"}
}