{
  "type": "Feature",
  "properties": {
    "iso:country":"US",
    "sg:address":"1925 Ambler Ave",
    "sg:city":"Abilene",
    "sg:classifiers":[
        {
            "category":"Building & Trades",
            "subcategory":"Construction",
            "type":"Services"
        }
    ],
    "sg:phone":"+1 325 672 5415",
    "sg:postcode":"79603",
    "sg:province":"TX",
    "sg:tags":[
        "wallpaper"
    ],
    "wof:name":"Deanda's Painting",
    "wof:placetype":"venue"
},
  "geometry": {"coordinates":[-99.74366499999999,32.474341],"type":"Point"}
}