{
  "type": "Feature",
  "properties": {
    "iso:country":"US",
    "sg:address":"1937 Texas Pkwy",
    "sg:city":"Missouri City",
    "sg:classifiers":[
        {
            "category":"Shopping",
            "subcategory":"Mobile Phones",
            "type":"Retail Goods"
        }
    ],
    "sg:phone":"+1 281 403 1505",
    "sg:postcode":"77489",
    "sg:province":"TX",
    "wof:name":"Cricket",
    "wof:placetype":"venue"
},
  "geometry": {"coordinates":[-95.526652,29.599134],"type":"Point"}
}