{
  "type": "Feature",
  "properties": {
    "iso:country":"US",
    "sg:address":"20823 Highet Pl",
    "sg:city":"Tomball",
    "sg:classifiers":[
        {
            "category":"Shopping",
            "subcategory":"Used Merchandise",
            "type":"Retail Goods"
        }
    ],
    "sg:phone":"+1 281 290 9061",
    "sg:postcode":"77375",
    "sg:province":"TX",
    "wof:name":"Pennsylvania Station-Antiques",
    "wof:placetype":"venue"
},
  "geometry": {"coordinates":[-95.584243,30.067338],"type":"Point"}
}