{
  "type": "Feature",
  "properties": {
    "iso:country":"US",
    "sg:address":"1121 Wigwam",
    "sg:city":"Leander",
    "sg:classifiers":[
        {
            "category":"Building & Trades",
            "subcategory":"Construction",
            "type":"Services"
        }
    ],
    "sg:phone":"+1 512 335 0712",
    "sg:postcode":"78641",
    "sg:province":"TX",
    "sg:tags":[
        "painter"
    ],
    "wof:name":"Timberline Painting North",
    "wof:placetype":"venue"
},
  "geometry": {"coordinates":[-97.84880099999999,30.544701],"type":"Point"}
}