{
  "type": "Feature",
  "properties": {
    "iso:country":"US",
    "sg:address":"4801 Abbott Ave",
    "sg:city":"Dallas",
    "sg:classifiers":[
        {
            "category":"Restaurant",
            "type":"Food & Drink"
        }
    ],
    "sg:phone":"+1 214 526 6425",
    "sg:postcode":"75205",
    "sg:province":"TX",
    "sg:tags":[
        "eating"
    ],
    "wof:name":"Jill Bee",
    "wof:placetype":"venue"
},
  "geometry": {"coordinates":[-96.789025,32.827129],"type":"Point"}
}