{
  "type": "Feature",
  "properties": {
    "iso:country":"US",
    "sg:address":"2319 Oakside Dr",
    "sg:city":"Arlington",
    "sg:classifiers":[
        {
            "category":"Home & Garden",
            "subcategory":"Hardware",
            "type":"Retail Goods"
        }
    ],
    "sg:phone":"+1 817 496 4166",
    "sg:postcode":"76016",
    "sg:province":"TX",
    "wof:name":"Matco Tools",
    "wof:placetype":"venue"
},
  "geometry": {"coordinates":[-97.174724,32.70427],"type":"Point"}
}