{
  "type": "Feature",
  "properties": {
    "iso:country":"US",
    "sg:address":"11322 Toucan Ln",
    "sg:city":"Houston",
    "sg:classifiers":[
        {
            "category":"Professional",
            "type":"Services"
        }
    ],
    "sg:phone":"+1 281 893 2933",
    "sg:postcode":"77067",
    "sg:province":"TX",
    "wof:name":"Caring Arms of Love",
    "wof:placetype":"venue"
},
  "geometry": {"coordinates":[-95.45241799999999,29.948336],"type":"Point"}
}