{
  "type": "Feature",
  "properties": {
    "iso:country":"US",
    "sg:address":"14022 Walters Rd",
    "sg:city":"Houston",
    "sg:classifiers":[
        {
            "category":"Building & Trades",
            "subcategory":"Equipment Rental",
            "type":"Services"
        }
    ],
    "sg:phone":"+1 281 444 9656",
    "sg:postcode":"77014",
    "sg:province":"TX",
    "wof:name":"Casino Nite Rentals",
    "wof:placetype":"venue"
},
  "geometry": {"coordinates":[-95.47854700000001,29.98383],"type":"Point"}
}