{
  "type": "Feature",
  "properties": {
    "iso:country":"US",
    "sg:address":"1206 Bent Oaks Ct Ste 100",
    "sg:city":"Denton",
    "sg:classifiers":[
        {
            "category":"Transit Center",
            "subcategory":"Freight",
            "type":"Transportation"
        },
        {
            "category":"Freight",
            "type":"Transportation"
        }
    ],
    "sg:phone":"+1 940 565 5060",
    "sg:postcode":"76210",
    "sg:province":"TX",
    "sg:tags":[
        "local",
        "trucking-motor",
        "trucking"
    ],
    "wof:name":"Rsa Trucking",
    "wof:placetype":"venue"
},
  "geometry": {"coordinates":[-97.112858,33.172513],"type":"Point"}
}