{
  "type": "Feature",
  "properties": {
    "iso:country":"US",
    "sg:address":"1337 Crampton St",
    "sg:city":"Dallas",
    "sg:classifiers":[
        {
            "category":"Professional",
            "subcategory":"Art Services",
            "type":"Services"
        }
    ],
    "sg:phone":"+1 214 630 5160",
    "sg:postcode":"75207",
    "sg:province":"TX",
    "sg:tags":[
        "photographer"
    ],
    "sg:website":"www.johnsaxonphoto.com",
    "wof:name":"John Saxon Photography",
    "wof:placetype":"venue"
},
  "geometry": {"coordinates":[-96.838178,32.80218],"type":"Point"}
}