{
  "type": "Feature",
  "properties": {
    "iso:country":"US",
    "sg:address":"1531 Stone Trail Dr",
    "sg:city":"Sugar Land",
    "sg:classifiers":[
        {
            "category":"Manufacturing",
            "subcategory":"Petroleum Products",
            "type":"Manufacturing & Wholesale Goods"
        }
    ],
    "sg:phone":"+1 281 343 8008",
    "sg:postcode":"77479",
    "sg:province":"TX",
    "sg:tags":[
        "processing",
        "refiner",
        "blending"
    ],
    "wof:name":"Unigard Lubricants USA",
    "wof:placetype":"venue"
},
  "geometry": {"coordinates":[-95.68100800000001,29.551541],"type":"Point"}
}