{
  "type": "Feature",
  "properties": {
    "iso:country":"US",
    "sg:address":"1723 E Griffin Pkwy",
    "sg:city":"Mission",
    "sg:classifiers":[
        {
            "category":"Insurance",
            "subcategory":"Insurance Agent",
            "type":"Services"
        }
    ],
    "sg:phone":"+1 956 584 8600",
    "sg:postcode":"78572",
    "sg:province":"TX",
    "wof:name":"Valley Financial Mktg Group",
    "wof:placetype":"venue"
},
  "geometry": {"coordinates":[-98.294949,26.225818],"type":"Point"}
}