{
  "type": "Feature",
  "properties": {
    "iso:country":"US",
    "sg:address":"700 Glenoak Dr",
    "sg:city":"Corpus Christi",
    "sg:classifiers":[
        {
            "category":"Professional",
            "subcategory":"Business Services",
            "type":"Services"
        }
    ],
    "sg:phone":"+1 361 937 3928",
    "sg:postcode":"78418",
    "sg:province":"TX",
    "wof:name":"C & S Liquidations",
    "wof:placetype":"venue"
},
  "geometry": {"coordinates":[-97.301014,27.644537],"type":"Point"}
}