{
  "type": "Feature",
  "properties": {
    "iso:country":"US",
    "sg:address":"6300 Bridge Point Pkwy",
    "sg:city":"Austin",
    "sg:classifiers":[
        {
            "category":"Professional",
            "type":"Services"
        }
    ],
    "sg:phone":"+1 512 346 9023",
    "sg:postcode":"78730",
    "sg:province":"TX",
    "sg:tags":[
        "establishment"
    ],
    "wof:name":"Three Sixty Companies",
    "wof:placetype":"venue"
},
  "geometry": {"coordinates":[-97.800371,30.35412],"type":"Point"}
}