{
  "type": "Feature",
  "properties": {
    "iso:country":"US",
    "sg:address":"1445 Ross Ave",
    "sg:city":"Dallas",
    "sg:classifiers":[
        {
            "category":"Restaurant",
            "type":"Food & Drink"
        }
    ],
    "sg:phone":"+1 214 965 0055",
    "sg:postcode":"75202",
    "sg:province":"TX",
    "sg:tags":[
        "italian"
    ],
    "wof:name":"Samira Enterprise Inc",
    "wof:placetype":"venue"
},
  "geometry": {"coordinates":[-96.801788,32.784882],"type":"Point"}
}