{
  "type": "Feature",
  "properties": {
    "iso:country":"US",
    "sg:address":"8520 Sweetwater Ln",
    "sg:city":"Houston",
    "sg:classifiers":[
        {
            "category":"Building & Trades",
            "subcategory":"Construction",
            "type":"Services"
        }
    ],
    "sg:phone":"+1 281 260 9600",
    "sg:postcode":"77037",
    "sg:province":"TX",
    "sg:tags":[
        "contractor"
    ],
    "wof:name":"Demolition Materials LLC",
    "wof:placetype":"venue"
},
  "geometry": {"coordinates":[-95.40844800000001,29.883196],"type":"Point"}
}