{
  "type": "Feature",
  "properties": {
    "iso:country":"US",
    "sg:address":"3912 N McColl Rd",
    "sg:city":"Mcallen",
    "sg:classifiers":[
        {
            "category":"Manufacturing",
            "subcategory":"Petroleum Products",
            "type":"Manufacturing & Wholesale Goods"
        }
    ],
    "sg:phone":"+1 956 664 9588",
    "sg:postcode":"78501",
    "sg:province":"TX",
    "sg:tags":[
        "refiner"
    ],
    "wof:name":"Valley 1519",
    "wof:placetype":"venue"
},
  "geometry": {"coordinates":[-98.207289,26.233011],"type":"Point"}
}