{
  "type": "Feature",
  "properties": {
    "iso:country":"US",
    "sg:address":"4701 Boulder Dr",
    "sg:city":"Allen",
    "sg:classifiers":[
        {
            "category":"Professional",
            "subcategory":"Accounting & Tax Preparation",
            "type":"Services"
        }
    ],
    "sg:phone":"+1 972 424 6024",
    "sg:postcode":"75002",
    "sg:province":"TX",
    "wof:name":"Sherry J Martinez P C",
    "wof:placetype":"venue"
},
  "geometry": {"coordinates":[-96.64801,33.065544],"type":"Point"}
}