{
  "type": "Feature",
  "properties": {
    "iso:country":"US",
    "sg:address":"1335 E Whitestone Blvd #S-170",
    "sg:city":"Cedar Park",
    "sg:classifiers":[
        {
            "category":"Bakery",
            "type":"Food & Drink"
        }
    ],
    "sg:phone":"+1 512 986 7453",
    "sg:postcode":"78613",
    "sg:province":"TX",
    "sg:website":"www.nothingbundtcakes.com",
    "wof:name":"Nothing Bundt Cakes",
    "wof:placetype":"venue"
},
  "geometry": {"coordinates":[-97.815667,30.525929],"type":"Point"}
}