{
  "type": "Feature",
  "properties": {
    "iso:country":"US",
    "sg:address":"6434 Coachgate Dr",
    "sg:city":"Spring",
    "sg:classifiers":[
        {
            "category":"Autos & Motor Vehicles",
            "subcategory":"Auto Supplies",
            "type":"Retail Goods"
        }
    ],
    "sg:phone":"+1 281 209 0734",
    "sg:postcode":"77373",
    "sg:province":"TX",
    "wof:name":"ASJ Accessories",
    "wof:placetype":"venue"
},
  "geometry": {"coordinates":[-95.331396,30.04104],"type":"Point"}
}