{
  "type": "Feature",
  "properties": {
    "iso:country":"US",
    "sg:address":"105 E Main St",
    "sg:city":"Decatur",
    "sg:classifiers":[
        {
            "category":"Professional",
            "subcategory":"Business Services",
            "type":"Services"
        }
    ],
    "sg:phone":"+1 940 626 8000",
    "sg:postcode":"76234",
    "sg:province":"TX",
    "wof:name":"Pnr Enterprises",
    "wof:placetype":"venue"
},
  "geometry": {"coordinates":[-97.586314,33.234173],"type":"Point"}
}