{
  "type": "Feature",
  "properties": {
    "iso:country":"US",
    "sg:address":"201 W US Hwy 83",
    "sg:city":"Pharr",
    "sg:classifiers":[
        {
            "category":"Restaurant",
            "type":"Food & Drink"
        }
    ],
    "sg:phone":"+1 956 781 8827",
    "sg:postcode":"78577",
    "sg:province":"TX",
    "sg:tags":[
        "eating"
    ],
    "wof:name":"LA Rueda Restaurant",
    "wof:placetype":"venue"
},
  "geometry": {"coordinates":[-98.18454,26.206742],"type":"Point"}
}