{
  "type": "Feature",
  "properties": {
    "iso:country":"US",
    "sg:address":"2117 Sayles Blvd",
    "sg:city":"Abilene",
    "sg:classifiers":[
        {
            "category":"Restaurant",
            "type":"Food & Drink"
        }
    ],
    "sg:phone":"+1 325 670 0801",
    "sg:postcode":"79605",
    "sg:province":"TX",
    "sg:tags":[
        "eating"
    ],
    "wof:name":"Flossies Kitchen & Cater",
    "wof:placetype":"venue"
},
  "geometry": {"coordinates":[-99.74798699999999,32.422179],"type":"Point"}
}