{
  "type": "Feature",
  "properties": {
    "iso:country":"US",
    "sg:address":"837 S Wheeler St",
    "sg:city":"Jasper",
    "sg:classifiers":[
        {
            "category":"Insurance",
            "subcategory":"Insurance Agent",
            "type":"Services"
        }
    ],
    "sg:phone":"+1 409 384 4441",
    "sg:postcode":"75951",
    "sg:province":"TX",
    "wof:name":"AIG Sunamerica",
    "wof:placetype":"venue"
},
  "geometry": {"coordinates":[-93.99622599999999,30.912891],"type":"Point"}
}