{
  "type": "Feature",
  "properties": {
    "iso:country":"US",
    "sg:address":"764 W Commerce St",
    "sg:city":"Fairfield",
    "sg:classifiers":[
        {
            "category":"Health Services",
            "subcategory":"Doctor",
            "type":"Services"
        }
    ],
    "sg:phone":"+1 903 389 2181",
    "sg:postcode":"75840",
    "sg:province":"TX",
    "sg:tags":[
        "physician",
        "family",
        "practice",
        "surgeons",
        "medicine",
        "surgeon"
    ],
    "wof:name":"Keller John H MD",
    "wof:placetype":"venue"
},
  "geometry": {"coordinates":[-96.17104999999999,31.724826],"type":"Point"}
}