{
  "type": "Feature",
  "properties": {
    "iso:country":"US",
    "sg:address":"3802 Marquis Dr",
    "sg:city":"Garland",
    "sg:classifiers":[
        {
            "category":"Home & Garden",
            "subcategory":"Building Materials",
            "type":"Retail Goods"
        }
    ],
    "sg:phone":"+1 214 217 8460",
    "sg:postcode":"75042",
    "sg:province":"TX",
    "sg:tags":[
        "metal",
        "center"
    ],
    "wof:name":"Richardson Bros",
    "wof:placetype":"venue"
},
  "geometry": {"coordinates":[-96.68582600000001,32.901683],"type":"Point"}
}