{
  "type": "Feature",
  "properties": {
    "iso:country":"US",
    "sg:address":"12879 Josey Ln",
    "sg:city":"Dallas",
    "sg:classifiers":[
        {
            "category":"Health Services",
            "subcategory":"Clinic",
            "type":"Services"
        }
    ],
    "sg:phone":"+1 972 241 5442",
    "sg:postcode":"75234",
    "sg:province":"TX",
    "sg:tags":[
        "specialty",
        "outpatient"
    ],
    "wof:name":"Slaa",
    "wof:placetype":"venue"
},
  "geometry": {"coordinates":[-96.88182999999999,32.920557],"type":"Point"}
}