{
  "type": "Feature",
  "properties": {
    "iso:country":"US",
    "sg:address":"614 Green Hills Rd",
    "sg:city":"Duncanville",
    "sg:classifiers":[
        {
            "category":"Shopping",
            "type":"Retail Goods"
        }
    ],
    "sg:phone":"+1 972 780 1065",
    "sg:postcode":"75137",
    "sg:province":"TX",
    "sg:tags":[
        "merchandise"
    ],
    "wof:name":"Flight Path",
    "wof:placetype":"venue"
},
  "geometry": {"coordinates":[-96.938177,32.645627],"type":"Point"}
}