{
  "type": "Feature",
  "properties": {
    "iso:country":"US",
    "sg:address":"4270 Squaw Creek Dr",
    "sg:city":"Frisco",
    "sg:classifiers":[
        {
            "category":"Arts & Performance",
            "subcategory":"Theater",
            "type":"Entertainment"
        }
    ],
    "sg:phone":"+1 972 335 5391",
    "sg:postcode":"75035",
    "sg:province":"TX",
    "sg:tags":[
        "music"
    ],
    "wof:name":"Siren The Clown",
    "wof:placetype":"venue"
},
  "geometry": {"coordinates":[-96.77867500000001,33.112423],"type":"Point"}
}