{
  "type": "Feature",
  "properties": {
    "iso:country":"US",
    "sg:address":"2016 Rowe Loop",
    "sg:city":"Pflugerville",
    "sg:classifiers":[
        {
            "category":"Retail",
            "subcategory":"Animal Services",
            "type":"Services"
        }
    ],
    "sg:phone":"+1 512 990 2016",
    "sg:postcode":"78660",
    "sg:province":"TX",
    "wof:name":"Waggin Tails Dog Training",
    "wof:placetype":"venue"
},
  "geometry": {"coordinates":[-97.576442,30.485145],"type":"Point"}
}