{
  "type": "Feature",
  "properties": {
    "iso:country":"US",
    "sg:address":"2064 S Garland Ave",
    "sg:city":"Garland",
    "sg:classifiers":[
        {
            "category":"Retail",
            "subcategory":"Laundry & Dry Cleaning",
            "type":"Services"
        }
    ],
    "sg:phone":"+1 972 278 8039",
    "sg:postcode":"75041",
    "sg:province":"TX",
    "sg:tags":[
        "cleaner"
    ],
    "wof:name":"Tower Cleaners",
    "wof:placetype":"venue"
},
  "geometry": {"coordinates":[-96.650002,32.893101],"type":"Point"}
}