{
  "type": "Feature",
  "properties": {
    "iso:country":"US",
    "sg:address":"4635 Wild Indigo",
    "sg:city":"Houston",
    "sg:classifiers":[
        {
            "category":"Utilities",
            "subcategory":"Mobile Phone",
            "type":"Services"
        }
    ],
    "sg:phone":"+1 713 212 0102",
    "sg:postcode":"77027",
    "sg:province":"TX",
    "sg:tags":[
        "communication",
        "radiotelephone"
    ],
    "wof:name":"Road Inc",
    "wof:placetype":"venue"
},
  "geometry": {"coordinates":[-95.453318,29.728187],"type":"Point"}
}