{
  "type": "Feature",
  "properties": {
    "iso:country":"US",
    "sg:address":"5801 Ainez Dr",
    "sg:city":"Austin",
    "sg:classifiers":[
        {
            "category":"Government",
            "subcategory":"Police Station",
            "type":"Public Place"
        }
    ],
    "sg:phone":"+1 512 326 1463",
    "sg:postcode":"78744",
    "sg:province":"TX",
    "sg:tags":[
        "department"
    ],
    "wof:name":"Austin Neighborhood Police Ctr",
    "wof:placetype":"venue"
},
  "geometry": {"coordinates":[-97.738793,30.188761],"type":"Point"}
}