{
  "type": "Feature",
  "properties": {
    "iso:country":"US",
    "sg:address":"7555 Morley St",
    "sg:city":"Houston",
    "sg:classifiers":[
        {
            "category":"Building & Trades",
            "subcategory":"Construction",
            "type":"Services"
        }
    ],
    "sg:phone":"+1 713 641 2111",
    "sg:postcode":"77061",
    "sg:province":"TX",
    "sg:tags":[
        "repairing",
        "remodeling",
        "contractor"
    ],
    "wof:name":"HEA",
    "wof:placetype":"venue"
},
  "geometry": {"coordinates":[-95.288184,29.661164],"type":"Point"}
}