{
  "type": "Feature",
  "properties": {
    "iso:country":"US",
    "sg:address":"9227 Chimney Corner",
    "sg:city":"Dallas",
    "sg:classifiers":[
        {
            "category":"Arts & Performance",
            "subcategory":"Theater",
            "type":"Entertainment"
        }
    ],
    "sg:phone":"+1 214 575 9328",
    "sg:postcode":"75243",
    "sg:province":"TX",
    "sg:tags":[
        "group"
    ],
    "wof:name":"Beau Edmondson",
    "wof:placetype":"venue"
},
  "geometry": {"coordinates":[-96.73644,32.920145],"type":"Point"}
}