{
  "type": "Feature",
  "properties": {
    "iso:country":"US",
    "sg:address":"721 Lockhaven Dr",
    "sg:city":"Houston",
    "sg:classifiers":[
        {
            "category":"Education",
            "subcategory":"Special Training",
            "type":"Public Place"
        }
    ],
    "sg:phone":"+1 281 443 6262",
    "sg:postcode":"77073",
    "sg:province":"TX",
    "wof:name":"Business Office",
    "wof:placetype":"venue"
},
  "geometry": {"coordinates":[-95.412756,29.989961],"type":"Point"}
}