{
  "type": "Feature",
  "properties": {
    "iso:country":"US",
    "sg:address":"5926 FM 2100",
    "sg:city":"Crosby",
    "sg:classifiers":[
        {
            "category":"Autos & Motor Vehicles",
            "subcategory":"Fuel & Gas Station",
            "type":"Retail Goods"
        }
    ],
    "sg:phone":"+1 281 462 0224",
    "sg:postcode":"77532",
    "sg:province":"TX",
    "sg:tags":[
        "station",
        "gasoline"
    ],
    "wof:name":"Exxon Handi Plus",
    "wof:placetype":"venue"
},
  "geometry": {"coordinates":[-95.068793,29.910789],"type":"Point"}
}