{
  "type": "Feature",
  "properties": {
    "iso:country":"US",
    "sg:address":"4011 Briar Hollow St",
    "sg:city":"San Antonio",
    "sg:classifiers":[
        {
            "category":"Retail",
            "subcategory":"Repair Shop",
            "type":"Services"
        }
    ],
    "sg:phone":"+1 210 490 6619",
    "sg:postcode":"78247",
    "sg:province":"TX",
    "wof:name":"Hawbecker Repair Service",
    "wof:placetype":"venue"
},
  "geometry": {"coordinates":[-98.41183100000001,29.575703],"type":"Point"}
}