{
  "type": "Feature",
  "properties": {
    "iso:country":"US",
    "sg:address":"1415 State Hwy 36",
    "sg:city":"Sealy",
    "sg:classifiers":[
        {
            "category":"Mining & Drilling",
            "type":"Manufacturing & Wholesale Goods"
        }
    ],
    "sg:phone":"+1 979 885 6603",
    "sg:postcode":"77474",
    "sg:province":"TX",
    "sg:tags":[
        "field",
        "oil"
    ],
    "wof:name":"Brand X Perforators Inc",
    "wof:placetype":"venue"
},
  "geometry": {"coordinates":[-96.154763,29.770471],"type":"Point"}
}