{
  "type": "Feature",
  "properties": {
    "iso:country":"US",
    "sg:address":"907 N Coker Loop",
    "sg:city":"San Antonio",
    "sg:classifiers":[
        {
            "category":"Manufacturing",
            "subcategory":"Apparel",
            "type":"Manufacturing & Wholesale Goods"
        }
    ],
    "sg:phone":"+1 210 494 3421",
    "sg:postcode":"78216",
    "sg:province":"TX",
    "sg:tags":[
        "pad",
        "furniture"
    ],
    "wof:name":"Alamo Cotton Felt Co",
    "wof:placetype":"venue"
},
  "geometry": {"coordinates":[-98.481081,29.551541],"type":"Point"}
}