{
  "type": "Feature",
  "properties": {
    "iso:country":"US",
    "sg:address":"104 S Berkshire Ave",
    "sg:city":"Crosbyton",
    "sg:classifiers":[
        {
            "category":"Shopping",
            "subcategory":"Discount & Variety Stores",
            "type":"Retail Goods"
        }
    ],
    "sg:phone":"+1 806 675 9522",
    "sg:postcode":"79322",
    "sg:province":"TX",
    "sg:tags":[
        "merchandise",
        "general"
    ],
    "wof:name":"Bee Hive Sales",
    "wof:placetype":"venue"
},
  "geometry": {"coordinates":[-101.23942599999999,33.659945],"type":"Point"}
}