{
  "type": "Feature",
  "properties": {
    "iso:country":"US",
    "sg:address":"3399 Goehmann Ln",
    "sg:city":"Fredericksburg",
    "sg:classifiers":[
        {
            "category":"Building & Trades",
            "subcategory":"Construction",
            "type":"Services"
        },
        {
            "category":"Home & Garden",
            "subcategory":"Furniture",
            "type":"Retail Goods"
        }
    ],
    "sg:phone":"+1 830 997 8420",
    "sg:postcode":"78624",
    "sg:province":"TX",
    "sg:tags":[
        "cabinet",
        "maker",
        "custom"
    ],
    "wof:name":"Ronald's Cabinet Shop",
    "wof:placetype":"venue"
},
  "geometry": {"coordinates":[-98.84387099999999,30.261585],"type":"Point"}
}