{
  "type": "Feature",
  "properties": {
    "iso:country":"US",
    "sg:address":"310 N Ohio Ave",
    "sg:city":"Mercedes",
    "sg:classifiers":[
        {
            "category":"Communications",
            "subcategory":"Radio Station",
            "type":"Services"
        }
    ],
    "sg:phone":"+1 956 565 9678",
    "sg:postcode":"78570",
    "sg:province":"TX",
    "sg:tags":[
        "broadcast"
    ],
    "wof:name":"La Nueva Kbor Inc",
    "wof:placetype":"venue"
},
  "geometry": {"coordinates":[-97.912384,26.155599],"type":"Point"}
}