{
  "type": "Feature",
  "properties": {
    "iso:country":"US",
    "sg:address":"340 W Main St",
    "sg:city":"Azle",
    "sg:classifiers":[
        {
            "category":"Shopping",
            "subcategory":"Florist",
            "type":"Retail Goods"
        }
    ],
    "sg:phone":"+1 817 444 2661",
    "sg:postcode":"76020",
    "sg:province":"TX",
    "wof:name":"Sandy's Cozy Creations",
    "wof:placetype":"venue"
},
  "geometry": {"coordinates":[-97.546673,32.895805],"type":"Point"}
}