{
  "type": "Feature",
  "properties": {
    "iso:country":"US",
    "sg:address":"120 E North Loop Blvd",
    "sg:city":"Austin",
    "sg:classifiers":[
        {
            "category":"Food & Beverages",
            "subcategory":"Groceries & Convenience Stores",
            "type":"Retail Goods"
        }
    ],
    "sg:phone":"+1 512 458 5424",
    "sg:postcode":"78751",
    "sg:province":"TX",
    "wof:name":"North Loop Food Store",
    "wof:placetype":"venue"
},
  "geometry": {"coordinates":[-97.721298,30.3176],"type":"Point"}
}