{
  "type": "Feature",
  "properties": {
    "iso:country":"US",
    "sg:address":"3030 39th St",
    "sg:city":"Port Arthur",
    "sg:classifiers":[
        {
            "category":"Health Services",
            "subcategory":"Hospital",
            "type":"Services"
        }
    ],
    "sg:phone":"+1 409 985 0451",
    "sg:postcode":"77642",
    "sg:province":"TX",
    "sg:tags":[
        "general"
    ],
    "wof:name":"Tenet Cbo - Port Arthur",
    "wof:placetype":"venue"
},
  "geometry": {"coordinates":[-93.948894,29.914137],"type":"Point"}
}