{
  "type": "Feature",
  "properties": {
    "iso:country":"US",
    "sg:address":"3851 Airport Fwy",
    "sg:city":"Fort Worth",
    "sg:classifiers":[
        {
            "category":"Banks & Credit Unions",
            "subcategory":"Bank",
            "type":"Services"
        }
    ],
    "sg:phone":"+1 682 647 1374",
    "sg:postcode":"76111",
    "sg:province":"TX",
    "wof:name":"Woodforest National Bank",
    "wof:placetype":"venue"
},
  "geometry": {"coordinates":[-97.29266699999999,32.773151],"type":"Point"}
}