{
  "type": "Feature",
  "properties": {
    "iso:country":"US",
    "sg:address":"11243 Leo Ln",
    "sg:city":"Dallas",
    "sg:classifiers":[
        {
            "category":"Professional",
            "subcategory":"Detective & Security Services",
            "type":"Services"
        },
        {
            "category":"Organizations",
            "subcategory":"Professional Association",
            "type":"Services"
        }
    ],
    "sg:phone":"+1 214 350 0233",
    "sg:postcode":"75229",
    "sg:province":"TX",
    "sg:tags":[
        "information",
        "bureau",
        "representative",
        "agent",
        "manufacturers'"
    ],
    "wof:name":"Gulf Southwest Sales",
    "wof:placetype":"venue"
},
  "geometry": {"coordinates":[-96.88637,32.89332],"type":"Point"}
}