{
  "type": "Feature",
  "properties": {
    "iso:country":"US",
    "sg:address":"1221 Ashwood Dr",
    "sg:city":"Tyler",
    "sg:classifiers":[
        {
            "category":"Manufacturing",
            "subcategory":"Musical Instruments",
            "type":"Manufacturing & Wholesale Goods"
        }
    ],
    "sg:phone":"+1 903 561 0022",
    "sg:postcode":"75703",
    "sg:province":"TX",
    "sg:tags":[
        "mfg"
    ],
    "wof:name":"Tyler Tuning Service",
    "wof:placetype":"venue"
},
  "geometry": {"coordinates":[-95.287762,32.29],"type":"Point"}
}