{
  "type": "Feature",
  "properties": {
    "iso:country":"US",
    "sg:address":"15127 Chestnut Falls Dr",
    "sg:city":"Cypress",
    "sg:classifiers":[
        {
            "category":"Manufacturing",
            "subcategory":"Lumber",
            "type":"Manufacturing & Wholesale Goods"
        }
    ],
    "sg:phone":"+1 281 373 5858",
    "sg:postcode":"77433",
    "sg:province":"TX",
    "sg:tags":[
        "mill"
    ],
    "wof:name":"Texas Flavor Dust",
    "wof:placetype":"venue"
},
  "geometry": {"coordinates":[-95.73414099999999,29.992423],"type":"Point"}
}