{
  "type": "Feature",
  "properties": {
    "iso:country":"US",
    "sg:address":"337 Shady Ln",
    "sg:city":"Azle",
    "sg:classifiers":[
        {
            "category":"Building & Trades",
            "subcategory":"Construction",
            "type":"Services"
        }
    ],
    "sg:phone":"+1 817 478 2464",
    "sg:postcode":"76020",
    "sg:province":"TX",
    "sg:tags":[
        "general",
        "contractor"
    ],
    "wof:name":"Chaidez Construction Svc",
    "wof:placetype":"venue"
},
  "geometry": {"coordinates":[-97.53748400000001,32.895639],"type":"Point"}
}