{
  "type": "Feature",
  "properties": {
    "iso:country":"US",
    "sg:address":"211 W Lamar St",
    "sg:city":"Sherman",
    "sg:classifiers":[
        {
            "category":"Home & Garden",
            "subcategory":"Carpets & Floor Coverings",
            "type":"Retail Goods"
        }
    ],
    "sg:phone":"+1 903 893 2912",
    "sg:postcode":"75090",
    "sg:province":"TX",
    "sg:tags":[
        "dealer",
        "rug"
    ],
    "wof:name":"Childs Carpet Inc",
    "wof:placetype":"venue"
},
  "geometry": {"coordinates":[-96.61084700000001,33.635298],"type":"Point"}
}