{
  "type": "Feature",
  "properties": {
    "iso:country":"US",
    "sg:address":"103 Riverside Park",
    "sg:city":"Abilene",
    "sg:classifiers":[
        {
            "category":"Shopping",
            "subcategory":"Hobbies, Toys, & Games",
            "type":"Retail Goods"
        }
    ],
    "sg:phone":"+1 325 677 7324",
    "sg:postcode":"79605",
    "sg:province":"TX",
    "wof:name":"Louise Swim Gifts",
    "wof:placetype":"venue"
},
  "geometry": {"coordinates":[-99.768569,32.44843],"type":"Point"}
}