{
  "type": "Feature",
  "properties": {
    "iso:country":"US",
    "sg:address":"3214 Fall Creek Hwy",
    "sg:city":"Granbury",
    "sg:classifiers":[
        {
            "category":"Personal",
            "subcategory":"Beauty Salon",
            "type":"Services"
        }
    ],
    "sg:phone":"+1 817 910 4022",
    "sg:postcode":"76049",
    "sg:province":"TX",
    "wof:name":"Schoefield's Salon",
    "wof:placetype":"venue"
},
  "geometry": {"coordinates":[-97.689232,32.44521],"type":"Point"}
}