{
  "type": "Feature",
  "properties": {
    "iso:country":"US",
    "sg:address":"2425 K Ave",
    "sg:city":"Plano",
    "sg:classifiers":[
        {
            "category":"Restaurant",
            "type":"Food & Drink"
        },
        {
            "category":"Ice Cream",
            "type":"Food & Drink"
        }
    ],
    "sg:menulink":"http://www.allmenus.com/tx/plano/162448-dairy-queen/menu/",
    "sg:phone":"+1 972 423 4509",
    "sg:postcode":"75074",
    "sg:province":"TX",
    "sg:tags":[
        "burger",
        "american",
        "ice",
        "cream"
    ],
    "wof:name":"Dairy Queen",
    "wof:placetype":"venue"
},
  "geometry": {"coordinates":[-96.699371,33.030463],"type":"Point"}
}