{
  "type": "Feature",
  "properties": {
    "iso:country":"US",
    "sg:address":"600 E Beaumont Ave",
    "sg:city":"Cooper",
    "sg:classifiers":[
        {
            "category":"Professional",
            "subcategory":"Business Services",
            "type":"Services"
        }
    ],
    "sg:phone":"+1 903 395 4765",
    "sg:postcode":"75432",
    "sg:province":"TX",
    "wof:name":"Cotton Auction Barn",
    "wof:placetype":"venue"
},
  "geometry": {"coordinates":[-95.684338,33.366059],"type":"Point"}
}