{
  "type": "Feature",
  "properties": {
    "iso:country":"US",
    "sg:address":"15815 Fleetwood Oaks Dr",
    "sg:city":"Houston",
    "sg:classifiers":[
        {
            "category":"Shopping",
            "subcategory":"Gifts & Souvenirs",
            "type":"Retail Goods"
        }
    ],
    "sg:phone":"+1 281 493 2696",
    "sg:postcode":"77079",
    "sg:province":"TX",
    "wof:name":"Harold T Joseph Cards & Gifts",
    "wof:placetype":"venue"
},
  "geometry": {"coordinates":[-95.637655,29.777137],"type":"Point"}
}