{
  "type": "Feature",
  "properties": {
    "iso:country":"US",
    "sg:address":"3506 Cookstown Dr",
    "sg:city":"Austin",
    "sg:classifiers":[
        {
            "category":"Professional",
            "type":"Services"
        }
    ],
    "sg:phone":"+1 512 873 8165",
    "sg:postcode":"78759",
    "sg:province":"TX",
    "wof:name":"Ctc Services",
    "wof:placetype":"venue"
},
  "geometry": {"coordinates":[-97.715919,30.419907],"type":"Point"}
}