{
  "type": "Feature",
  "properties": {
    "iso:country":"US",
    "sg:address":"401 S Beckham Ave",
    "sg:city":"Tyler",
    "sg:classifiers":[
        {
            "category":"Food & Beverages",
            "subcategory":"Groceries & Convenience Stores",
            "type":"Retail Goods"
        }
    ],
    "sg:phone":"+1 903 592 3054",
    "sg:postcode":"75702",
    "sg:province":"TX",
    "wof:name":"Super Sak Stores",
    "wof:placetype":"venue"
},
  "geometry": {"coordinates":[-95.294296,32.346661],"type":"Point"}
}