{
  "type": "Feature",
  "properties": {
    "iso:country":"US",
    "sg:address":"4407 Hollister",
    "sg:city":"Houston",
    "sg:classifiers":[
        {
            "category":"Building & Trades",
            "subcategory":"Construction",
            "type":"Services"
        }
    ],
    "sg:phone":"+1 713 690 5501",
    "sg:postcode":"77040",
    "sg:province":"TX",
    "sg:tags":[
        "contractor"
    ],
    "wof:name":"N W Contractors Inc",
    "wof:placetype":"venue"
},
  "geometry": {"coordinates":[-95.506488,29.83924],"type":"Point"}
}