{
  "type": "Feature",
  "properties": {
    "iso:country":"US",
    "sg:address":"1528 Allen Dr",
    "sg:city":"Cedar Hill",
    "sg:classifiers":[
        {
            "category":"Banks & Credit Unions",
            "subcategory":"Investment Brokerage",
            "type":"Services"
        }
    ],
    "sg:phone":"+1 972 293 8340",
    "sg:postcode":"75104",
    "sg:province":"TX",
    "wof:name":"Gerald Andrews",
    "wof:placetype":"venue"
},
  "geometry": {"coordinates":[-96.94090199999999,32.621937],"type":"Point"}
}