{
  "type": "Feature",
  "properties": {
    "iso:country":"US",
    "sg:address":"1214 S Urbahn Ave",
    "sg:city":"Laredo",
    "sg:classifiers":[
        {
            "category":"Autos & Motor Vehicles",
            "subcategory":"Automobile Sales",
            "type":"Retail Goods"
        }
    ],
    "sg:phone":"+1 956 791 0164",
    "sg:postcode":"78043",
    "sg:province":"TX",
    "sg:tags":[
        "car",
        "dealer"
    ],
    "wof:name":"M & M Auto Sales",
    "wof:placetype":"venue"
},
  "geometry": {"coordinates":[-99.47577800000001,27.486043],"type":"Point"}
}