{
  "type": "Feature",
  "properties": {
    "iso:country":"US",
    "sg:address":"2221 Murphy Dr",
    "sg:city":"Bedford",
    "sg:classifiers":[
        {
            "category":"Professional",
            "subcategory":"Management & Consulting",
            "type":"Services"
        }
    ],
    "sg:phone":"+1 817 540 0993",
    "sg:postcode":"76021",
    "sg:province":"TX",
    "sg:tags":[
        "business"
    ],
    "wof:name":"Southern Consulting Group",
    "wof:placetype":"venue"
},
  "geometry": {"coordinates":[-97.12187299999999,32.841127],"type":"Point"}
}