{
  "type": "Feature",
  "properties": {
    "iso:country":"US",
    "sg:address":"163 Harmon Dr",
    "sg:city":"San Antonio",
    "sg:classifiers":[
        {
            "category":"Wholesale",
            "subcategory":"Medical Equipment & Supplies",
            "type":"Manufacturing & Wholesale Goods"
        }
    ],
    "sg:phone":"+1 210 820 3638",
    "sg:postcode":"78209",
    "sg:province":"TX",
    "wof:name":"American Precision Med Gas Co",
    "wof:placetype":"venue"
},
  "geometry": {"coordinates":[-98.45294199999999,29.491005],"type":"Point"}
}