{
  "type": "Feature",
  "properties": {
    "iso:country":"US",
    "sg:address":"1515 Cleburne St",
    "sg:city":"Houston",
    "sg:classifiers":[
        {
            "category":"Arts & Performance",
            "subcategory":"Theater",
            "type":"Entertainment"
        }
    ],
    "sg:phone":"+1 713 529 6508",
    "sg:postcode":"77004",
    "sg:province":"TX",
    "sg:tags":[
        "group"
    ],
    "wof:name":"Honey Harp",
    "wof:placetype":"venue"
},
  "geometry": {"coordinates":[-95.37633599999999,29.733043],"type":"Point"}
}