{
  "type": "Feature",
  "properties": {
    "iso:country":"US",
    "sg:address":"11500 Ranch Road 2222",
    "sg:city":"Austin",
    "sg:classifiers":[
        {
            "category":"Banks & Credit Unions",
            "subcategory":"Bank",
            "type":"Services"
        }
    ],
    "sg:phone":"+1 512 996 9555",
    "sg:postcode":"78730",
    "sg:province":"TX",
    "sg:website":"www.bankofamerica.com",
    "wof:name":"Bank of America",
    "wof:placetype":"venue"
},
  "geometry": {"coordinates":[-97.852755,30.402885],"type":"Point"}
}