{
  "type": "Feature",
  "properties": {
    "iso:country":"US",
    "sg:address":"247 Colonial Cir",
    "sg:city":"Athens",
    "sg:classifiers":[
        {
            "category":"Building & Trades",
            "subcategory":"Construction",
            "type":"Services"
        }
    ],
    "sg:phone":"+1 903 677 9420",
    "sg:postcode":"75751",
    "sg:province":"TX",
    "sg:tags":[
        "house",
        "contractor"
    ],
    "wof:name":"Purselley Construction Co",
    "wof:placetype":"venue"
},
  "geometry": {"coordinates":[-95.828529,32.193514],"type":"Point"}
}