{
  "type": "Feature",
  "properties": {
    "iso:country":"US",
    "sg:address":"201 N Cates St",
    "sg:city":"Decatur",
    "sg:classifiers":[
        {
            "category":"Food & Beverages",
            "subcategory":"Groceries & Convenience Stores",
            "type":"Retail Goods"
        }
    ],
    "sg:phone":"+1 940 627 3444",
    "sg:postcode":"76234",
    "sg:province":"TX",
    "sg:tags":[
        "station",
        "gasoline"
    ],
    "wof:name":"Allsups 7",
    "wof:placetype":"venue"
},
  "geometry": {"coordinates":[-97.583035,33.235396],"type":"Point"}
}