{
  "type": "Feature",
  "properties": {
    "iso:country":"US",
    "sg:address":"2815 Sachse Rd",
    "sg:city":"Wylie",
    "sg:classifiers":[
        {
            "category":"Freight",
            "type":"Transportation"
        }
    ],
    "sg:phone":"+1 972 442 2884",
    "sg:postcode":"75098",
    "sg:province":"TX",
    "sg:tags":[
        "operator",
        "local",
        "trucking"
    ],
    "wof:name":"Briseno Trucking",
    "wof:placetype":"venue"
},
  "geometry": {"coordinates":[-96.55584399999999,32.978546],"type":"Point"}
}