{
  "type": "Feature",
  "properties": {
    "iso:country":"US",
    "sg:address":"14930 el Miranda Dr",
    "sg:city":"Houston",
    "sg:classifiers":[
        {
            "category":"Professional",
            "type":"Services"
        }
    ],
    "sg:phone":"+1 281 550 4870",
    "sg:postcode":"77095",
    "sg:province":"TX",
    "wof:name":"Full Sail Royalty Co",
    "wof:placetype":"venue"
},
  "geometry": {"coordinates":[-95.633402,29.884716],"type":"Point"}
}