{
  "type": "Feature",
  "properties": {
    "iso:country":"US",
    "sg:address":"6107 Greenville Ave",
    "sg:city":"Dallas",
    "sg:classifiers":[
        {
            "category":"Restaurant",
            "type":"Food & Drink"
        }
    ],
    "sg:phone":"+1 214 361 9155",
    "sg:postcode":"75206",
    "sg:province":"TX",
    "sg:website":"www.schlotzskys.com",
    "wof:name":"Schlotzsky's Deli",
    "wof:placetype":"venue"
},
  "geometry": {"coordinates":[-96.768204,32.859699],"type":"Point"}
}