{
  "type": "Feature",
  "properties": {
    "iso:country":"US",
    "sg:address":"610 Victoria Dr",
    "sg:city":"Grand Prairie",
    "sg:classifiers":[
        {
            "category":"Arts & Performance",
            "subcategory":"Theater",
            "type":"Entertainment"
        }
    ],
    "sg:phone":"+1 972 237 9991",
    "sg:postcode":"75052",
    "sg:province":"TX",
    "sg:tags":[
        "theatrical"
    ],
    "wof:name":"Pcss",
    "wof:placetype":"venue"
},
  "geometry": {"coordinates":[-96.99479599999999,32.70707],"type":"Point"}
}