{
  "type": "Feature",
  "properties": {
    "iso:country":"US",
    "sg:address":"571 N Union Ave",
    "sg:city":"New Braunfels",
    "sg:classifiers":[
        {
            "category":"Health Services",
            "subcategory":"Doctor",
            "type":"Services"
        }
    ],
    "sg:phone":"+1 830 609 2040",
    "sg:postcode":"78130",
    "sg:province":"TX",
    "sg:tags":[
        "medical"
    ],
    "wof:name":"Neurology Management Services",
    "wof:placetype":"venue"
},
  "geometry": {"coordinates":[-98.12279700000001,29.714226],"type":"Point"}
}