{
  "type": "Feature",
  "properties": {
    "iso:country":"US",
    "sg:address":"1910 Hermitage Dr",
    "sg:city":"Round Rock",
    "sg:classifiers":[
        {
            "category":"Restaurant",
            "type":"Food & Drink"
        }
    ],
    "sg:phone":"+1 512 388 5307",
    "sg:postcode":"78681",
    "sg:province":"TX",
    "wof:name":"Cafe El Chef",
    "wof:placetype":"venue"
},
  "geometry": {"coordinates":[-97.706684,30.524289],"type":"Point"}
}