{
  "type": "Feature",
  "properties": {
    "iso:country":"US",
    "sg:address":"4605 Maher Ave",
    "sg:city":"Laredo",
    "sg:classifiers":[
        {
            "category":"Education",
            "subcategory":"Special Training",
            "type":"Public Place"
        }
    ],
    "sg:phone":"+1 956 724 1844",
    "sg:postcode":"78041",
    "sg:province":"TX",
    "sg:tags":[
        "educational"
    ],
    "wof:name":"Ser-Jobs For Progress In SW TX",
    "wof:placetype":"venue"
},
  "geometry": {"coordinates":[-99.472426,27.533739],"type":"Point"}
}