{
  "type": "Feature",
  "properties": {
    "iso:country":"US",
    "sg:address":"4901 Martin St",
    "sg:city":"Fort Worth",
    "sg:classifiers":[
        {
            "category":"Professional",
            "type":"Services"
        }
    ],
    "sg:phone":"+1 817 563 6060",
    "sg:postcode":"76119",
    "sg:province":"TX",
    "sg:tags":[
        "establishment"
    ],
    "wof:name":"RPS",
    "wof:placetype":"venue"
},
  "geometry": {"coordinates":[-97.244581,32.689022],"type":"Point"}
}