{
  "type": "Feature",
  "properties": {
    "iso:country":"US",
    "sg:address":"7303 Somerset Rd",
    "sg:city":"San Antonio",
    "sg:classifiers":[
        {
            "category":"Professional",
            "type":"Services"
        },
        {
            "category":"Retail",
            "subcategory":"Auto Repair",
            "type":"Services"
        }
    ],
    "sg:phone":"+1 210 927 1832",
    "sg:postcode":"78211",
    "sg:province":"TX",
    "sg:tags":[
        "shop",
        "automobile",
        "electric",
        "general"
    ],
    "wof:name":"Leal's Auto Electric",
    "wof:placetype":"venue"
},
  "geometry": {"coordinates":[-98.55329,29.35273],"type":"Point"}
}