{
  "type": "Feature",
  "properties": {
    "iso:country":"US",
    "sg:address":"2400 Wilson Pl",
    "sg:city":"Temple",
    "sg:classifiers":[
        {
            "category":"Education",
            "subcategory":"Special Training",
            "type":"Public Place"
        }
    ],
    "sg:phone":"+1 254 207 3579",
    "sg:postcode":"76504",
    "sg:province":"TX",
    "wof:name":"Wilson Arts International",
    "wof:placetype":"venue"
},
  "geometry": {"coordinates":[-97.370784,31.096162],"type":"Point"}
}