{
  "type": "Feature",
  "properties": {
    "iso:country":"US",
    "sg:address":"4001 Ave Los Presidentes",
    "sg:city":"Laredo",
    "sg:classifiers":[
        {
            "category":"Education",
            "subcategory":"School",
            "type":"Public Place"
        }
    ],
    "sg:phone":"+1 956 721 5600",
    "sg:postcode":"78046",
    "sg:province":"TX",
    "wof:name":"United S High Shcool",
    "wof:placetype":"venue"
},
  "geometry": {"coordinates":[-99.45154599999999,27.478982],"type":"Point"}
}