{
  "type": "Feature",
  "properties": {
    "iso:country":"US",
    "sg:address":"5111 W Harrow Dr",
    "sg:city":"Houston",
    "sg:classifiers":[
        {
            "category":"Professional",
            "subcategory":"Business Services",
            "type":"Services"
        }
    ],
    "sg:phone":"+1 281 550 4023",
    "sg:postcode":"77084",
    "sg:province":"TX",
    "wof:name":"Texas Millennium Group Inc",
    "wof:placetype":"venue"
},
  "geometry": {"coordinates":[-95.66467900000001,29.852389],"type":"Point"}
}