{
  "type": "Feature",
  "properties": {
    "iso:country":"US",
    "sg:address":"3605 Live Oak St",
    "sg:city":"Dallas",
    "sg:classifiers":[
        {
            "category":"Autos & Motor Vehicles",
            "subcategory":"Automobile Sales",
            "type":"Retail Goods"
        }
    ],
    "sg:phone":"+1 214 823 4900",
    "sg:postcode":"75204",
    "sg:province":"TX",
    "sg:tags":[
        "equipment",
        "aircraft",
        "parts",
        "supply"
    ],
    "wof:name":"Air Industries Intl LTD",
    "wof:placetype":"venue"
},
  "geometry": {"coordinates":[-96.78278899999999,32.794201],"type":"Point"}
}