{
  "type": "Feature",
  "properties": {
    "iso:country":"US",
    "sg:address":"10375 Richmond Ave Ste 1215",
    "sg:city":"Houston",
    "sg:classifiers":[
        {
            "category":"Professional",
            "subcategory":"Lawyer & Legal Services",
            "type":"Services"
        }
    ],
    "sg:phone":"+1 713 777 9799",
    "sg:postcode":"77042",
    "sg:province":"TX",
    "wof:name":"Williams & Overstreet PC",
    "wof:placetype":"venue"
},
  "geometry": {"coordinates":[-95.55590100000001,29.727501],"type":"Point"}
}