{
  "type": "Feature",
  "properties": {
    "iso:country":"US",
    "sg:address":"2619 Cornell St",
    "sg:city":"Lubbock",
    "sg:classifiers":[
        {
            "category":"Organizations",
            "subcategory":"Religious Organization",
            "type":"Services"
        }
    ],
    "sg:phone":"+1 806 744 9973",
    "sg:postcode":"79415",
    "sg:province":"TX",
    "wof:name":"Iglesia Mtdistia Unida Emanuel",
    "wof:placetype":"venue"
},
  "geometry": {"coordinates":[-101.871089,33.603086],"type":"Point"}
}