{
  "type": "Feature",
  "properties": {
    "iso:country":"US",
    "sg:address":"5815 W William Cannon Dr",
    "sg:city":"Austin",
    "sg:classifiers":[
        {
            "category":"Real Estate",
            "subcategory":"Real Estate Services",
            "type":"Services"
        }
    ],
    "sg:phone":"+1 512 394 9755",
    "sg:postcode":"78749",
    "sg:province":"TX",
    "sg:tags":[
        "company",
        "title"
    ],
    "wof:name":"Texas American Title Co",
    "wof:placetype":"venue"
},
  "geometry": {"coordinates":[-97.856916,30.225314],"type":"Point"}
}