{
  "type": "Feature",
  "properties": {
    "iso:country":"US",
    "sg:address":"103 Rebecca Ln",
    "sg:city":"Victoria",
    "sg:classifiers":[
        {
            "category":"Building & Trades",
            "subcategory":"Cleaning & Sanitation",
            "type":"Services"
        }
    ],
    "sg:phone":"+1 361 575 4683",
    "sg:postcode":"77901",
    "sg:province":"TX",
    "sg:tags":[
        "janitor"
    ],
    "wof:name":"Enviro-Tech Cleaning Solutions",
    "wof:placetype":"venue"
},
  "geometry": {"coordinates":[-96.97266,28.834316],"type":"Point"}
}