{
  "type": "Feature",
  "properties": {
    "iso:country":"US",
    "sg:address":"306 Amherst Ave",
    "sg:city":"Richardson",
    "sg:classifiers":[
        {
            "category":"Building & Trades",
            "subcategory":"Construction",
            "type":"Services"
        }
    ],
    "sg:phone":"+1 972 234 1515",
    "sg:postcode":"75081",
    "sg:province":"TX",
    "sg:tags":[
        "insulation",
        "heat",
        "contractor"
    ],
    "wof:name":"JLCO Inc",
    "wof:placetype":"venue"
},
  "geometry": {"coordinates":[-96.69309699999999,32.951307],"type":"Point"}
}