{
  "type": "Feature",
  "properties": {
    "iso:country":"US",
    "sg:address":"255 Basse Rd E",
    "sg:city":"San Antonio",
    "sg:classifiers":[
        {
            "category":"Home & Garden",
            "subcategory":"Furniture",
            "type":"Retail Goods"
        }
    ],
    "sg:phone":"+1 210 828 2953",
    "sg:postcode":"78209",
    "sg:province":"TX",
    "sg:tags":[
        "furnishing"
    ],
    "wof:name":"Restoration Hardware Inc",
    "wof:placetype":"venue"
},
  "geometry": {"coordinates":[-98.479388,29.495803],"type":"Point"}
}