{
  "type": "Feature",
  "properties": {
    "iso:country":"US",
    "sg:address":"3117 Motley Dr",
    "sg:city":"Mesquite",
    "sg:classifiers":[
        {
            "category":"Social Services",
            "subcategory":"Child Care",
            "type":"Services"
        },
        {
            "category":"Education",
            "subcategory":"Preschool",
            "type":"Public Place"
        },
        {
            "category":"Education",
            "subcategory":"School",
            "type":"Public Place"
        }
    ],
    "sg:phone":"+1 972 279 8042",
    "sg:postcode":"75150",
    "sg:province":"TX",
    "sg:tags":[
        "elementary",
        "day"
    ],
    "wof:name":"St Marks United Methodist Church",
    "wof:placetype":"venue"
},
  "geometry": {"coordinates":[-96.65010100000001,32.806],"type":"Point"}
}