{
  "type": "Feature",
  "properties": {
    "iso:country":"US",
    "sg:address":"12410 State Hwy 6",
    "sg:city":"Santa Fe",
    "sg:classifiers":[
        {
            "category":"Professional",
            "subcategory":"Research",
            "type":"Services"
        }
    ],
    "sg:phone":"+1 409 925 8080",
    "sg:postcode":"77510",
    "sg:province":"TX",
    "sg:tags":[
        "laboratory"
    ],
    "wof:name":"In Home Labs",
    "wof:placetype":"venue"
},
  "geometry": {"coordinates":[-95.090613,29.373164],"type":"Point"}
}