{
  "type": "Feature",
  "properties": {
    "iso:country":"US",
    "sg:address":"3720 Tanglewood Ln",
    "sg:city":"Odessa",
    "sg:classifiers":[
        {
            "category":"Mining & Drilling",
            "type":"Manufacturing & Wholesale Goods"
        }
    ],
    "sg:phone":"+1 432 550 4225",
    "sg:postcode":"79762",
    "sg:province":"TX",
    "sg:tags":[
        "field",
        "oil"
    ],
    "wof:name":"Pete Carter Co",
    "wof:placetype":"venue"
},
  "geometry": {"coordinates":[-102.33976699999999,31.885685],"type":"Point"}
}