{
  "type": "Feature",
  "properties": {
    "iso:country":"US",
    "sg:address":"3708 Texoma Pkwy",
    "sg:city":"Sherman",
    "sg:classifiers":[
        {
            "category":"Manufacturing",
            "subcategory":"Printing",
            "type":"Manufacturing & Wholesale Goods"
        }
    ],
    "sg:phone":"+1 903 868 4270",
    "sg:postcode":"75090",
    "sg:province":"TX",
    "sg:tags":[
        "commercial"
    ],
    "wof:name":"Parkway Graphics",
    "wof:placetype":"venue"
},
  "geometry": {"coordinates":[-96.58979600000001,33.675156],"type":"Point"}
}