{
  "type": "Feature",
  "properties": {
    "iso:country":"US",
    "sg:address":"7010 Baywater Dr",
    "sg:city":"San Antonio",
    "sg:classifiers":[
        {
            "category":"Organizations",
            "subcategory":"Religious Organization",
            "type":"Services"
        }
    ],
    "sg:phone":"+1 210 615 1945",
    "sg:postcode":"78229",
    "sg:province":"TX",
    "wof:name":"Spanish Baptist Missions",
    "wof:placetype":"venue"
},
  "geometry": {"coordinates":[-98.576899,29.498656],"type":"Point"}
}