{
  "type": "Feature",
  "properties": {
    "iso:country":"US",
    "sg:address":"3003 Bee Caves Rd",
    "sg:city":"Austin",
    "sg:classifiers":[
        {
            "category":"Health Services",
            "subcategory":"Doctor",
            "type":"Services"
        }
    ],
    "sg:phone":"+1 512 327 3773",
    "sg:postcode":"78746",
    "sg:province":"TX",
    "sg:tags":[
        "physician",
        "surgeon",
        "cosmetic",
        "surgery"
    ],
    "wof:name":"Austin Plastic Surgery Inst",
    "wof:placetype":"venue"
},
  "geometry": {"coordinates":[-97.795278,30.271525],"type":"Point"}
}