{
  "type": "Feature",
  "properties": {
    "iso:country":"US",
    "sg:address":"11700 E View Dr",
    "sg:city":"Amarillo",
    "sg:classifiers":[
        {
            "category":"Professional",
            "subcategory":"Lawyer & Legal Services",
            "type":"Services"
        }
    ],
    "sg:phone":"+1 806 352 0830",
    "sg:postcode":"79124",
    "sg:province":"TX",
    "sg:tags":[
        "divorce",
        "assistance"
    ],
    "wof:name":"Divorce Texas Style",
    "wof:placetype":"venue"
},
  "geometry": {"coordinates":[-101.97673500000001,35.254335],"type":"Point"}
}