{
  "type": "Feature",
  "properties": {
    "iso:country":"US",
    "sg:address":"6038 Lazy River Dr",
    "sg:city":"Dallas",
    "sg:classifiers":[
        {
            "category":"Banks & Credit Unions",
            "subcategory":"Financial Services",
            "type":"Services"
        }
    ],
    "sg:phone":"+1 214 371 6163",
    "sg:postcode":"75241",
    "sg:province":"TX",
    "sg:tags":[
        "investor"
    ],
    "wof:name":"New Link Investors",
    "wof:placetype":"venue"
},
  "geometry": {"coordinates":[-96.79340000000001,32.67583],"type":"Point"}
}