{
  "type": "Feature",
  "properties": {
    "iso:country":"US",
    "sg:address":"9807 North FM 620",
    "sg:city":"Austin",
    "sg:classifiers":[
        {
            "category":"Real Estate",
            "subcategory":"Real Estate Operator",
            "type":"Services"
        }
    ],
    "sg:phone":"+1 888 857 7548",
    "sg:postcode":"78726",
    "sg:province":"TX",
    "sg:tags":[
        "apartment"
    ],
    "wof:name":"Avendaro at Canyon Creek",
    "wof:placetype":"venue"
},
  "geometry": {"coordinates":[-97.606646,30.324251],"type":"Point"}
}