{
  "type": "Feature",
  "properties": {
    "iso:country":"US",
    "sg:address":"5033 Rosenthal Pkwy",
    "sg:city":"Lorena",
    "sg:classifiers":[
        {
            "category":"Professional",
            "subcategory":"Business Services",
            "type":"Services"
        }
    ],
    "sg:phone":"+1 254 881 7341",
    "sg:postcode":"76655",
    "sg:province":"TX",
    "sg:tags":[
        "consultant",
        "coach"
    ],
    "wof:name":"Excellence In Health",
    "wof:placetype":"venue"
},
  "geometry": {"coordinates":[-97.137253,31.40501],"type":"Point"}
}