{
  "type": "Feature",
  "properties": {
    "iso:country":"US",
    "sg:address":"100 N Main St",
    "sg:city":"Salado",
    "sg:classifiers":[
        {
            "category":"Shopping",
            "subcategory":"Clothing, Apparel, & Fashions",
            "type":"Retail Goods"
        }
    ],
    "sg:phone":"+1 254 947 3600",
    "sg:postcode":"76571",
    "sg:province":"TX",
    "wof:name":"Scarlett's At The Stagecoach",
    "wof:placetype":"venue"
},
  "geometry": {"coordinates":[-97.537013,30.946767],"type":"Point"}
}