{
  "type": "Feature",
  "properties": {
    "iso:country":"US",
    "sg:address":"6757 Arapaho Rd Ste 767",
    "sg:city":"Dallas",
    "sg:classifiers":[
        {
            "category":"Shopping",
            "subcategory":"Jewelry",
            "type":"Retail Goods"
        }
    ],
    "sg:phone":"+1 972 661 5790",
    "sg:postcode":"75248",
    "sg:province":"TX",
    "wof:name":"Hirschberg Enterprices Llc",
    "wof:placetype":"venue"
},
  "geometry": {"coordinates":[-96.791397,32.962502],"type":"Point"}
}