{
  "type": "Feature",
  "properties": {
    "iso:country":"US",
    "sg:address":"1217 Pilot Ln",
    "sg:city":"Galveston",
    "sg:classifiers":[
        {
            "category":"Professional",
            "subcategory":"Detective & Security Services",
            "type":"Services"
        }
    ],
    "sg:phone":"+1 409 502 7229",
    "sg:postcode":"77554",
    "sg:province":"TX",
    "sg:tags":[
        "information",
        "bureau"
    ],
    "wof:name":"Island Dj Service",
    "wof:placetype":"venue"
},
  "geometry": {"coordinates":[-94.877185,29.271784],"type":"Point"}
}