{
  "type": "Feature",
  "properties": {
    "iso:country":"US",
    "sg:address":"11514 Perrin Beitel Rd",
    "sg:city":"San Antonio",
    "sg:classifiers":[
        {
            "category":"Health Services",
            "subcategory":"Doctor",
            "type":"Services"
        }
    ],
    "sg:phone":"+1 210 590 0202",
    "sg:postcode":"78217",
    "sg:province":"TX",
    "sg:tags":[
        "clinic"
    ],
    "wof:name":"Planned Parenthood",
    "wof:placetype":"venue"
},
  "geometry": {"coordinates":[-98.410701,29.545308],"type":"Point"}
}