{
  "type": "Feature",
  "properties": {
    "iso:country":"US",
    "sg:address":"151 W Church St",
    "sg:city":"Lewisville",
    "sg:classifiers":[
        {
            "category":"Government",
            "subcategory":"Office",
            "type":"Public Place"
        }
    ],
    "sg:phone":"+1 972 219 3750",
    "sg:postcode":"75057",
    "sg:province":"TX",
    "sg:tags":[
        "city",
        "program",
        "adm"
    ],
    "sg:website":"www.cityoflewisville.com",
    "wof:name":"Lewisville City Economic Dev",
    "wof:placetype":"venue"
},
  "geometry": {"coordinates":[-96.99626499999999,33.047314],"type":"Point"}
}