{
  "type": "Feature",
  "properties": {
    "iso:country":"US",
    "sg:address":"1510 Canada St",
    "sg:city":"Jacksonville",
    "sg:classifiers":[
        {
            "category":"Professional",
            "subcategory":"Business Services",
            "type":"Services"
        }
    ],
    "sg:phone":"+1 903 586 8968",
    "sg:postcode":"75766",
    "sg:province":"TX",
    "wof:name":"Texas Artworks",
    "wof:placetype":"venue"
},
  "geometry": {"coordinates":[-95.242846,31.955734],"type":"Point"}
}