{
  "type": "Feature",
  "properties": {
    "iso:country":"US",
    "sg:address":"14648 Walters Rd",
    "sg:city":"Houston",
    "sg:classifiers":[
        {
            "category":"Organizations",
            "subcategory":"Religious Organization",
            "type":"Services"
        }
    ],
    "sg:phone":"+1 281 440 7560",
    "sg:postcode":"77068",
    "sg:province":"TX",
    "sg:tags":[
        "church"
    ],
    "wof:name":"Cornerstone Bible Fellowship",
    "wof:placetype":"venue"
},
  "geometry": {"coordinates":[-95.485896,29.995778],"type":"Point"}
}