{
  "type": "Feature",
  "properties": {
    "iso:country":"US",
    "sg:address":"3306 W Ranch Rd 1431",
    "sg:city":"Kingsland",
    "sg:classifiers":[
        {
            "category":"Personal",
            "type":"Services"
        }
    ],
    "sg:phone":"+1 325 388 6016",
    "sg:postcode":"78639",
    "sg:province":"TX",
    "sg:tags":[
        "therapist",
        "massage"
    ],
    "wof:name":"Willow Mist Massage Therapy",
    "wof:placetype":"venue"
},
  "geometry": {"coordinates":[-98.45704499999999,30.674755],"type":"Point"}
}