{
  "type": "Feature",
  "properties": {
    "iso:country":"US",
    "sg:address":"3443 W Campbell Rd Ste 900",
    "sg:city":"Garland",
    "sg:classifiers":[
        {
            "category":"Autos & Motor Vehicles",
            "subcategory":"Auto Supplies",
            "type":"Retail Goods"
        }
    ],
    "sg:phone":"+1 972 530 5322",
    "sg:postcode":"75044",
    "sg:province":"TX",
    "sg:tags":[
        "tire"
    ],
    "wof:name":"Firestone Tire & Service Centers",
    "wof:placetype":"venue"
},
  "geometry": {"coordinates":[-96.68180099999999,32.973301],"type":"Point"}
}