{
  "type": "Feature",
  "properties": {
    "iso:country":"US",
    "sg:address":"2303 N Bryant Blvd",
    "sg:city":"San Angelo",
    "sg:classifiers":[
        {
            "category":"Restaurant",
            "type":"Food & Drink"
        }
    ],
    "sg:menulink":"http://www.allmenus.com/tx/san-angelo/85978-little-caesars-pizza/menu/",
    "sg:phone":"+1 325 658 5808",
    "sg:postcode":"76903",
    "sg:province":"TX",
    "sg:tags":[
        "american",
        "pizza"
    ],
    "wof:name":"Little Caesar's Pizza",
    "wof:placetype":"venue"
},
  "geometry": {"coordinates":[-100.456571,31.480182],"type":"Point"}
}