{
  "type": "Feature",
  "properties": {
    "iso:country":"US",
    "sg:address":"8742 Westbrae Park Ln",
    "sg:city":"Houston",
    "sg:classifiers":[
        {
            "category":"Health Services",
            "subcategory":"Clinic",
            "type":"Services"
        }
    ],
    "sg:phone":"+1 713 779 0510",
    "sg:postcode":"77031",
    "sg:province":"TX",
    "wof:name":"Atrium Healthcare Services",
    "wof:placetype":"venue"
},
  "geometry": {"coordinates":[-95.53125799999999,29.662029],"type":"Point"}
}