{
  "type": "Feature",
  "properties": {
    "iso:country":"US",
    "sg:address":"1049 N 3rd St",
    "sg:city":"Abilene",
    "sg:classifiers":[
        {
            "category":"Manufacturing",
            "subcategory":"Buildings",
            "type":"Manufacturing & Wholesale Goods"
        },
        {
            "category":"Building & Trades",
            "subcategory":"Construction",
            "type":"Services"
        }
    ],
    "sg:phone":"+1 325 439 1232",
    "sg:postcode":"79601",
    "sg:province":"TX",
    "sg:tags":[
        "roofing",
        "industrial",
        "builder",
        "contractor",
        "contractors-commercial",
        "home"
    ],
    "wof:name":"Beasley Constr",
    "wof:placetype":"venue"
},
  "geometry": {"coordinates":[-99.73345,32.451529],"type":"Point"}
}