{
  "type": "Feature",
  "properties": {
    "iso:country":"US",
    "sg:address":"150 Dominion Park Dr",
    "sg:city":"Houston",
    "sg:classifiers":[
        {
            "category":"Shopping",
            "subcategory":"Bicycles & Sporting Goods",
            "type":"Retail Goods"
        }
    ],
    "sg:phone":"+1 281 874 9848",
    "sg:postcode":"77090",
    "sg:province":"TX",
    "wof:name":"Texas Scuba Academy",
    "wof:placetype":"venue"
},
  "geometry": {"coordinates":[-95.42289100000001,29.975137],"type":"Point"}
}