{
  "type": "Feature",
  "properties": {
    "iso:country":"US",
    "sg:address":"104 Lanark Dr",
    "sg:city":"San Antonio",
    "sg:classifiers":[
        {
            "category":"Restaurant",
            "type":"Food & Drink"
        }
    ],
    "sg:phone":"+1 210 653 8487",
    "sg:postcode":"78218",
    "sg:province":"TX",
    "wof:name":"LA Cascada Mex Res",
    "wof:placetype":"venue"
},
  "geometry": {"coordinates":[-98.415736,29.503236],"type":"Point"}
}