{
  "type": "Feature",
  "properties": {
    "iso:country":"US",
    "sg:address":"6368 Newport Ct",
    "sg:city":"Fort Worth",
    "sg:classifiers":[
        {
            "category":"Wholesale",
            "subcategory":"Auto Parts",
            "type":"Manufacturing & Wholesale Goods"
        }
    ],
    "sg:phone":"+1 817 731 0090",
    "sg:postcode":"76116",
    "sg:province":"TX",
    "sg:tags":[
        "equipment",
        "air",
        "condition",
        "automobile"
    ],
    "wof:name":"Automotive Solutions LLC",
    "wof:placetype":"venue"
},
  "geometry": {"coordinates":[-97.426152,32.751221],"type":"Point"}
}