{
  "type": "Feature",
  "properties": {
    "iso:country":"US",
    "sg:address":"3204 Skylane Dr",
    "sg:city":"Carrollton",
    "sg:classifiers":[
        {
            "category":"Wholesale",
            "subcategory":"Computers",
            "type":"Manufacturing & Wholesale Goods"
        }
    ],
    "sg:phone":"+1 972 248 4600",
    "sg:postcode":"75006",
    "sg:province":"TX",
    "wof:name":"Affordable Computer Prods Inc",
    "wof:placetype":"venue"
},
  "geometry": {"coordinates":[-96.843262,32.978321],"type":"Point"}
}