{
  "type": "Feature",
  "properties": {
    "iso:country":"US",
    "sg:address":"2701 W Berry St",
    "sg:city":"Fort Worth",
    "sg:classifiers":[
        {
            "category":"Organizations",
            "subcategory":"Religious Organization",
            "type":"Services"
        }
    ],
    "sg:phone":"+1 817 926 7711",
    "sg:postcode":"76109",
    "sg:province":"TX",
    "wof:name":"University Church Of Christ",
    "wof:placetype":"venue"
},
  "geometry": {"coordinates":[-97.356557,32.706117],"type":"Point"}
}