{
  "type": "Feature",
  "properties": {
    "iso:country":"US",
    "sg:address":"30080 US Hwy 281",
    "sg:city":"Bulverde",
    "sg:classifiers":[
        {
            "category":"Shopping",
            "subcategory":"Computers & Home Electronics",
            "type":"Retail Goods"
        }
    ],
    "sg:phone":"+1 830 438 8112",
    "sg:postcode":"78163",
    "sg:province":"TX",
    "sg:tags":[
        "software"
    ],
    "wof:name":"CTM Software Inc",
    "wof:placetype":"venue"
},
  "geometry": {"coordinates":[-98.43958000000001,29.733327],"type":"Point"}
}