{
  "type": "Feature",
  "properties": {
    "iso:country":"US",
    "sg:address":"1432 Waterside Dr",
    "sg:city":"Dallas",
    "sg:classifiers":[
        {
            "category":"Banks & Credit Unions",
            "subcategory":"Investment Brokerage",
            "type":"Services"
        }
    ],
    "sg:phone":"+1 214 521 0747",
    "sg:postcode":"75218",
    "sg:province":"TX",
    "sg:tags":[
        "advisory",
        "financial"
    ],
    "wof:name":"Roland Snipes",
    "wof:placetype":"venue"
},
  "geometry": {"coordinates":[-96.723675,32.810882],"type":"Point"}
}