{
  "type": "Feature",
  "properties": {
    "iso:country":"US",
    "sg:address":"2347 Village Way",
    "sg:city":"Dallas",
    "sg:classifiers":[
        {
            "category":"Building & Trades",
            "subcategory":"Cleaning & Sanitation",
            "type":"Services"
        }
    ],
    "sg:phone":"+1 214 376 1732",
    "sg:postcode":"75216",
    "sg:province":"TX",
    "sg:tags":[
        "maintenance"
    ],
    "wof:name":"Pinks Cleaning Service",
    "wof:placetype":"venue"
},
  "geometry": {"coordinates":[-96.790586,32.711617],"type":"Point"}
}