{
  "type": "Feature",
  "properties": {
    "iso:country":"US",
    "sg:address":"2650 Dumas Dr",
    "sg:city":"Amarillo",
    "sg:classifiers":[
        {
            "category":"Retail",
            "subcategory":"Funeral Services",
            "type":"Services"
        }
    ],
    "sg:phone":"+1 806 358 6577",
    "sg:postcode":"79107",
    "sg:province":"TX",
    "sg:tags":[
        "merchandise"
    ],
    "wof:name":"Best Price Caskets & Monuments",
    "wof:placetype":"venue"
},
  "geometry": {"coordinates":[-101.831782,35.242583],"type":"Point"}
}