{
  "type": "Feature",
  "properties": {
    "iso:country":"US",
    "sg:address":"5424 W Highway 290 Suite 200",
    "sg:city":"Austin",
    "sg:classifiers":[
        {
            "category":"Education",
            "subcategory":"University",
            "type":"Public Place"
        }
    ],
    "sg:phone":"+1 512 892 4270",
    "sg:postcode":"78735",
    "sg:province":"TX",
    "sg:tags":[
        "college"
    ],
    "wof:name":"Capitol City Trade And Technical Careers",
    "wof:placetype":"venue"
},
  "geometry": {"coordinates":[-97.839342,30.237088],"type":"Point"}
}