{
  "type": "Feature",
  "properties": {
    "iso:country":"US",
    "sg:address":"811 Central Expy",
    "sg:city":"Plano",
    "sg:classifiers":[
        {
            "category":"Shopping",
            "subcategory":"Shoes",
            "type":"Retail Goods"
        }
    ],
    "sg:phone":"+1 972 312 1695",
    "sg:postcode":"75075",
    "sg:province":"TX",
    "wof:name":"Bakers",
    "wof:placetype":"venue"
},
  "geometry": {"coordinates":[-96.70858800000001,33.010215],"type":"Point"}
}