{
  "type": "Feature",
  "properties": {
    "iso:country":"US",
    "sg:address":"1224 Fresno Dr",
    "sg:city":"San Antonio",
    "sg:classifiers":[
        {
            "category":"Bars & Pubs",
            "type":"Food & Drink"
        }
    ],
    "sg:phone":"+1 210 732 3286",
    "sg:postcode":"78201",
    "sg:province":"TX",
    "sg:tags":[
        "drinking"
    ],
    "wof:name":"Big Mo Fresno Bar",
    "wof:placetype":"venue"
},
  "geometry": {"coordinates":[-98.514656,29.474119],"type":"Point"}
}