{
  "type": "Feature",
  "properties": {
    "iso:country":"US",
    "sg:address":"2100 E Main St",
    "sg:city":"Eagle Pass",
    "sg:classifiers":[
        {
            "category":"Restaurant",
            "type":"Food & Drink"
        }
    ],
    "sg:menulink":"http://www.allmenus.com/tx/eagle-pass/229068-golden-chick/menu/",
    "sg:phone":"+1 830 757 4444",
    "sg:postcode":"78852",
    "sg:province":"TX",
    "sg:tags":[
        "american"
    ],
    "wof:name":"Golden Chick",
    "wof:placetype":"venue"
},
  "geometry": {"coordinates":[-100.48647200000001,28.708784],"type":"Point"}
}