{
  "type": "Feature",
  "properties": {
    "iso:country":"US",
    "sg:address":"111 S Bowen Rd",
    "sg:city":"Arlington",
    "sg:classifiers":[
        {
            "category":"Restaurant",
            "type":"Food & Drink"
        }
    ],
    "sg:phone":"+1 817 861 3263",
    "sg:postcode":"76012",
    "sg:province":"TX",
    "sg:tags":[
        "eating"
    ],
    "wof:name":"Ho Ho Kitchen Inc",
    "wof:placetype":"venue"
},
  "geometry": {"coordinates":[-97.149136,32.735945],"type":"Point"}
}