{
  "type": "Feature",
  "properties": {
    "iso:country":"US",
    "sg:address":"4509 Amy Ln",
    "sg:city":"Flower Mound",
    "sg:classifiers":[
        {
            "category":"Professional",
            "type":"Services"
        }
    ],
    "sg:phone":"+1 972 899 0649",
    "sg:postcode":"75028",
    "sg:province":"TX",
    "wof:name":"Brian Foust",
    "wof:placetype":"venue"
},
  "geometry": {"coordinates":[-97.080012,33.047908],"type":"Point"}
}