{
  "type": "Feature",
  "properties": {
    "iso:country":"US",
    "sg:address":"8907 S Gessner Dr",
    "sg:city":"Houston",
    "sg:classifiers":[
        {
            "category":"Retail",
            "subcategory":"Repair Shop",
            "type":"Services"
        }
    ],
    "sg:phone":"+1 713 772 8811",
    "sg:postcode":"77074",
    "sg:province":"TX",
    "sg:tags":[
        "key",
        "locksmith"
    ],
    "wof:name":"C & D Safe & Lock",
    "wof:placetype":"venue"
},
  "geometry": {"coordinates":[-95.52829699999999,29.684401],"type":"Point"}
}