{
  "type": "Feature",
  "properties": {
    "iso:country":"US",
    "sg:address":"145 Oyster Creek Dr",
    "sg:city":"Lake Jackson",
    "sg:classifiers":[
        {
            "category":"Food & Beverages",
            "subcategory":"Bakery",
            "type":"Retail Goods"
        }
    ],
    "sg:phone":"+1 979 297 9090",
    "sg:postcode":"77566",
    "sg:province":"TX",
    "sg:tags":[
        "baker"
    ],
    "wof:name":"Santa Margarita Bakery Shop",
    "wof:placetype":"venue"
},
  "geometry": {"coordinates":[-95.450909,29.045613],"type":"Point"}
}