{
  "type": "Feature",
  "properties": {
    "iso:country":"US",
    "sg:address":"220 S 25th Ave",
    "sg:city":"Edinburg",
    "sg:classifiers":[
        {
            "category":"Real Estate",
            "subcategory":"Real Estate Agent",
            "type":"Services"
        }
    ],
    "sg:phone":"+1 956 318 5119",
    "sg:postcode":"78539",
    "sg:province":"TX",
    "sg:tags":[
        "authorities",
        "housing"
    ],
    "wof:name":"Housing Authority City",
    "wof:placetype":"venue"
},
  "geometry": {"coordinates":[-98.146747,26.297237],"type":"Point"}
}