{
  "type": "Feature",
  "properties": {
    "iso:country":"US",
    "sg:address":"11869 N Profit Row",
    "sg:city":"Forney",
    "sg:classifiers":[
        {
            "category":"Manufacturing",
            "subcategory":"Retail Goods",
            "type":"Manufacturing & Wholesale Goods"
        },
        {
            "category":"Professional",
            "subcategory":"Business Services",
            "type":"Services"
        }
    ],
    "sg:phone":"+1 972 564 3167",
    "sg:postcode":"75126",
    "sg:province":"TX",
    "sg:tags":[
        "aerosol"
    ],
    "wof:name":"Southwest Aerosol Inc",
    "wof:placetype":"venue"
},
  "geometry": {"coordinates":[-96.439077,32.733458],"type":"Point"}
}