{
  "type": "Feature",
  "properties": {
    "iso:country":"US",
    "sg:address":"711 E Saint Elmo Rd",
    "sg:city":"Austin",
    "sg:classifiers":[
        {
            "category":"Retail",
            "subcategory":"Auto Repair",
            "type":"Services"
        }
    ],
    "sg:phone":"+1 512 440 1184",
    "sg:postcode":"78745",
    "sg:province":"TX",
    "sg:tags":[
        "transmission",
        "automotive"
    ],
    "wof:name":"Austin Trnsm Cltch Specialists",
    "wof:placetype":"venue"
},
  "geometry": {"coordinates":[-97.758251,30.215472],"type":"Point"}
}