{
  "type": "Feature",
  "properties": {
    "iso:country":"US",
    "sg:address":"5332 Marsh Dr",
    "sg:city":"The Colony",
    "sg:classifiers":[
        {
            "category":"Building & Trades",
            "subcategory":"Plumbing",
            "type":"Services"
        }
    ],
    "sg:phone":"+1 972 625 2571",
    "sg:postcode":"75056",
    "sg:province":"TX",
    "sg:tags":[
        "plumbing",
        "contractor"
    ],
    "wof:name":"Louis Pettiford & Assoc",
    "wof:placetype":"venue"
},
  "geometry": {"coordinates":[-96.878148,33.088211],"type":"Point"}
}