{
  "type": "Feature",
  "properties": {
    "iso:country":"US",
    "sg:address":"2970 Spruce Valley Ln",
    "sg:city":"Dallas",
    "sg:classifiers":[
        {
            "category":"Real Estate",
            "subcategory":"Real Estate Operator",
            "type":"Services"
        }
    ],
    "sg:phone":"+1 214 330 9686",
    "sg:postcode":"75233",
    "sg:province":"TX",
    "sg:tags":[
        "operation",
        "apartment"
    ],
    "wof:name":"Windsor Forest Apartments",
    "wof:placetype":"venue"
},
  "geometry": {"coordinates":[-96.87602800000001,32.713769],"type":"Point"}
}