{
  "type": "Feature",
  "properties": {
    "iso:country":"US",
    "sg:address":"2728 Oak Haven Dr",
    "sg:city":"San Marcos",
    "sg:classifiers":[
        {
            "category":"Professional",
            "subcategory":"Computer Services",
            "type":"Services"
        }
    ],
    "sg:phone":"+1 512 754 9567",
    "sg:postcode":"78666",
    "sg:province":"TX",
    "sg:tags":[
        "related"
    ],
    "wof:name":"Sdm Enterprises Inc",
    "wof:placetype":"venue"
},
  "geometry": {"coordinates":[-97.98179,29.864041],"type":"Point"}
}