{
  "type": "Feature",
  "properties": {
    "iso:country":"US",
    "sg:address":"11931 Wickchester Ln",
    "sg:city":"Houston",
    "sg:classifiers":[
        {
            "category":"Building & Trades",
            "subcategory":"Construction",
            "type":"Services"
        }
    ],
    "sg:phone":"+1 281 558 8006",
    "sg:postcode":"77043",
    "sg:province":"TX",
    "sg:tags":[
        "contractor",
        "paving",
        "asphalt",
        "sealcoating"
    ],
    "sg:website":"http://www.wrightasphalt.com",
    "wof:name":"Wright Asphalt Products Co.",
    "wof:placetype":"venue"
},
  "geometry": {"coordinates":[-95.595196,29.788394],"type":"Point"}
}