{
  "type": "Feature",
  "properties": {
    "iso:country":"US",
    "sg:address":"26831 Nelson Hill",
    "sg:city":"Boerne",
    "sg:classifiers":[
        {
            "category":"Building & Trades",
            "subcategory":"Construction",
            "type":"Services"
        }
    ],
    "sg:phone":"+1 210 698 0885",
    "sg:postcode":"78006",
    "sg:province":"TX",
    "sg:tags":[
        "nonresidential"
    ],
    "wof:name":"Amigo Building Corp",
    "wof:placetype":"venue"
},
  "geometry": {"coordinates":[-98.680983,29.699802],"type":"Point"}
}