{
  "type": "Feature",
  "properties": {
    "iso:country":"US",
    "sg:address":"311 E 3rd St",
    "sg:city":"Burkburnett",
    "sg:classifiers":[
        {
            "category":"Professional",
            "type":"Services"
        }
    ],
    "sg:phone":"+1 940 569 0203",
    "sg:postcode":"76354",
    "sg:province":"TX",
    "wof:name":"Upper West Side",
    "wof:placetype":"venue"
},
  "geometry": {"coordinates":[-98.57098000000001,34.097886],"type":"Point"}
}