{
  "type": "Feature",
  "properties": {
    "iso:country":"US",
    "sg:address":"2630 Parkway Dr",
    "sg:city":"Lubbock",
    "sg:classifiers":[
        {
            "category":"Banks & Credit Unions",
            "subcategory":"Bank",
            "type":"Services"
        }
    ],
    "sg:phone":"+1 806 744 4149",
    "sg:postcode":"79403",
    "sg:province":"TX",
    "sg:tags":[
        "commercial",
        "saving"
    ],
    "sg:website":"http://www.wellsfargo.com",
    "wof:name":"Wells Fargo Bank",
    "wof:placetype":"venue"
},
  "geometry": {"coordinates":[-101.80752699999999,33.59813],"type":"Point"}
}