{
  "type": "Feature",
  "properties": {
    "iso:country":"US",
    "sg:address":"10701 Timbergrove Ln",
    "sg:city":"Corpus Christi",
    "sg:classifiers":[
        {
            "category":"Shopping",
            "subcategory":"Used Merchandise",
            "type":"Retail Goods"
        }
    ],
    "sg:phone":"+1 361 241 2213",
    "sg:postcode":"78410",
    "sg:province":"TX",
    "wof:name":"101 Ranch Antiques",
    "wof:placetype":"venue"
},
  "geometry": {"coordinates":[-97.579275,27.844364],"type":"Point"}
}