{
  "type": "Feature",
  "properties": {
    "iso:country":"US",
    "sg:address":"108 Beachview Way",
    "sg:city":"Bridgeport",
    "sg:classifiers":[
        {
            "category":"Professional",
            "subcategory":"Business Services",
            "type":"Services"
        }
    ],
    "sg:phone":"+1 940 575 4812",
    "sg:postcode":"76426",
    "sg:province":"TX",
    "wof:name":"Top Shelf Sales",
    "wof:placetype":"venue"
},
  "geometry": {"coordinates":[-97.87065800000001,33.174651],"type":"Point"}
}