{
  "type": "Feature",
  "properties": {
    "iso:country":"US",
    "sg:address":"110 Robindale Cir",
    "sg:city":"Conroe",
    "sg:classifiers":[
        {
            "category":"Professional",
            "type":"Services"
        }
    ],
    "sg:phone":"+1 936 321 3314",
    "sg:postcode":"77384",
    "sg:province":"TX",
    "wof:name":"Rocks & Money",
    "wof:placetype":"venue"
},
  "geometry": {"coordinates":[-95.47372300000001,30.208956],"type":"Point"}
}