{
  "type": "Feature",
  "properties": {
    "iso:country":"US",
    "sg:address":"107 Larry Lee Dr",
    "sg:city":"Kerrville",
    "sg:classifiers":[
        {
            "category":"Professional",
            "subcategory":"Business Services",
            "type":"Services"
        }
    ],
    "sg:phone":"+1 830 257 5539",
    "sg:postcode":"78028",
    "sg:province":"TX",
    "wof:name":"Mk Interiors",
    "wof:placetype":"venue"
},
  "geometry": {"coordinates":[-99.13315799999999,30.013669],"type":"Point"}
}