{
  "type": "Feature",
  "properties": {
    "iso:country":"US",
    "sg:address":"1215 S Houston Ave",
    "sg:city":"Humble",
    "sg:classifiers":[
        {
            "category":"Manufacturing",
            "subcategory":"Wood Products",
            "type":"Manufacturing & Wholesale Goods"
        }
    ],
    "sg:phone":"+1 281 446 6644",
    "sg:postcode":"77338",
    "sg:province":"TX",
    "sg:tags":[
        "wire",
        "fabricated",
        "mfg"
    ],
    "wof:name":"MI-Lar Fence Co Inc",
    "wof:placetype":"venue"
},
  "geometry": {"coordinates":[-95.259922,29.983013],"type":"Point"}
}