{
  "type": "Feature",
  "properties": {
    "iso:country":"US",
    "sg:address":"1721 State Hwy 6",
    "sg:city":"Houston",
    "sg:classifiers":[
        {
            "category":"Freight",
            "type":"Transportation"
        }
    ],
    "sg:phone":"+1 281 556 6615",
    "sg:postcode":"77077",
    "sg:province":"TX",
    "sg:tags":[
        "leasing",
        "rental",
        "truck",
        "general"
    ],
    "wof:name":"A J P Storage & U-Haul",
    "wof:placetype":"venue"
},
  "geometry": {"coordinates":[-95.64452900000001,29.752543],"type":"Point"}
}