{
  "type": "Feature",
  "properties": {
    "iso:country":"US",
    "sg:address":"925 8th Ave",
    "sg:city":"Fort Worth",
    "sg:classifiers":[
        {
            "category":"Professional",
            "subcategory":"Lawyer & Legal Services",
            "type":"Services"
        }
    ],
    "sg:phone":"+1 817 332 2202",
    "sg:postcode":"76104",
    "sg:province":"TX",
    "sg:tags":[
        "attorney"
    ],
    "wof:name":"David W Wynne",
    "wof:placetype":"venue"
},
  "geometry": {"coordinates":[-97.343644,32.733788],"type":"Point"}
}