{
  "type": "Feature",
  "properties": {
    "iso:country":"US",
    "sg:address":"10810 Cliffton Forge Dr",
    "sg:city":"Houston",
    "sg:classifiers":[
        {
            "category":"Wholesale",
            "subcategory":"Jewelry",
            "type":"Manufacturing & Wholesale Goods"
        },
        {
            "category":"Shopping",
            "subcategory":"Crafts & Fabrics",
            "type":"Retail Goods"
        }
    ],
    "sg:phone":"+1 281 961 4572",
    "sg:postcode":"77065",
    "sg:province":"TX",
    "sg:tags":[
        "bead",
        "beads-wholesale",
        "manufacturer"
    ],
    "wof:name":"Baby's Beads",
    "wof:placetype":"venue"
},
  "geometry": {"coordinates":[-95.595583,29.931533],"type":"Point"}
}