{
  "type": "Feature",
  "properties": {
    "iso:country":"US",
    "sg:address":"2646 William D Tate Ave",
    "sg:city":"Grapevine",
    "sg:classifiers":[
        {
            "category":"Manufacturing",
            "subcategory":"Food",
            "type":"Manufacturing & Wholesale Goods"
        },
        {
            "category":"Food & Beverages",
            "subcategory":"Bakery",
            "type":"Retail Goods"
        }
    ],
    "sg:phone":"+1 817 421 9828",
    "sg:postcode":"76051",
    "sg:province":"TX",
    "sg:tags":[
        "product",
        "doughnut",
        "mfg"
    ],
    "wof:name":"David's Donuts",
    "wof:placetype":"venue"
},
  "geometry": {"coordinates":[-97.099929,32.910301],"type":"Point"}
}