{
  "type": "Feature",
  "properties": {
    "iso:country":"US",
    "sg:address":"321 Gross Rd",
    "sg:city":"Mesquite",
    "sg:classifiers":[
        {
            "category":"Shopping",
            "subcategory":"Bicycles & Sporting Goods",
            "type":"Retail Goods"
        }
    ],
    "sg:phone":"+1 972 285 6666",
    "sg:postcode":"75149",
    "sg:province":"TX",
    "sg:tags":[
        "athletic",
        "equipment",
        "sport",
        "team"
    ],
    "sg:website":"www.mesquitesports.com",
    "wof:name":"Mesquite Sports Center",
    "wof:placetype":"venue"
},
  "geometry": {"coordinates":[-96.614098,32.772202],"type":"Point"}
}