{
  "type": "Feature",
  "properties": {
    "iso:country":"US",
    "sg:address":"134 N Clack St",
    "sg:city":"Abilene",
    "sg:classifiers":[
        {
            "category":"Retail",
            "subcategory":"Auto Rental",
            "type":"Services"
        }
    ],
    "sg:phone":"+1 325 675 0888",
    "sg:postcode":"79603",
    "sg:province":"TX",
    "sg:tags":[
        "equipment",
        "medical",
        "leasing"
    ],
    "wof:name":"Bush Ramsey Motors",
    "wof:placetype":"venue"
},
  "geometry": {"coordinates":[-99.787319,32.454679],"type":"Point"}
}