{
  "type": "Feature",
  "properties": {
    "iso:country":"US",
    "sg:address":"509 Berryhill Dr",
    "sg:city":"Mansfield",
    "sg:classifiers":[
        {
            "category":"Health Services",
            "subcategory":"Health Practitioner",
            "type":"Services"
        }
    ],
    "sg:phone":"+1 817 473 7370",
    "sg:postcode":"76063",
    "sg:province":"TX",
    "wof:name":"Erika Loudermilk",
    "wof:placetype":"venue"
},
  "geometry": {"coordinates":[-97.13589399999999,32.556441],"type":"Point"}
}