{
  "type": "Feature",
  "properties": {
    "iso:country":"US",
    "sg:address":"611 E Marshall Ave",
    "sg:city":"Longview",
    "sg:classifiers":[
        {
            "category":"Banks & Credit Unions",
            "subcategory":"Bank",
            "type":"Services"
        }
    ],
    "sg:phone":"+1 903 758 9551",
    "sg:postcode":"75601",
    "sg:province":"TX",
    "sg:tags":[
        "depository",
        "banking"
    ],
    "wof:name":"Mr Payroll",
    "wof:placetype":"venue"
},
  "geometry": {"coordinates":[-94.73157999999999,32.501509],"type":"Point"}
}