{
  "type": "Feature",
  "properties": {
    "iso:country":"US",
    "sg:address":"2727 Premier St",
    "sg:city":"Fort Worth",
    "sg:classifiers":[
        {
            "category":"Manufacturing",
            "subcategory":"Metals",
            "type":"Manufacturing & Wholesale Goods"
        }
    ],
    "sg:phone":"+1 817 834 3310",
    "sg:postcode":"76111",
    "sg:province":"TX",
    "sg:tags":[
        "steel"
    ],
    "sg:website":"www.inwesco.com",
    "wof:name":"Inwesco",
    "wof:placetype":"venue"
},
  "geometry": {"coordinates":[-97.30881100000001,32.800499],"type":"Point"}
}