{
  "type": "Feature",
  "properties": {
    "iso:country":"US",
    "sg:address":"24814 Haverford Rd",
    "sg:city":"Spring",
    "sg:classifiers":[
        {
            "category":"Insurance",
            "subcategory":"Insurance Agent",
            "type":"Services"
        }
    ],
    "sg:phone":"+1 281 255 4844",
    "sg:postcode":"77389",
    "sg:province":"TX",
    "sg:tags":[
        "processing"
    ],
    "wof:name":"Business Administrators",
    "wof:placetype":"venue"
},
  "geometry": {"coordinates":[-95.512705,30.130693],"type":"Point"}
}