{
  "type": "Feature",
  "properties": {
    "iso:country":"US",
    "sg:address":"123 S Main St",
    "sg:city":"Georgetown",
    "sg:phone":"+1 512 863 0548",
    "sg:postcode":"78626",
    "sg:province":"TX",
    "sg:website":"http://www.rotorooter.com",
    "wof:name":"Roto-Rooter Plumbers",
    "wof:placetype":"venue"
},
  "geometry": {"coordinates":[-97.58684100000001,30.674943],"type":"Point"}
}