{
  "type": "Feature",
  "properties": {
    "iso:country":"US",
    "sg:address":"2007 Haymeadow",
    "sg:city":"Carrollton",
    "sg:classifiers":[
        {
            "category":"Professional",
            "type":"Services"
        }
    ],
    "sg:phone":"+1 972 236 1499",
    "sg:postcode":"75007",
    "sg:province":"TX",
    "wof:name":"Quistquest Services LLC",
    "wof:placetype":"venue"
},
  "geometry": {"coordinates":[-96.886945,32.992764],"type":"Point"}
}