{
  "type": "Feature",
  "properties": {
    "iso:country":"US",
    "sg:address":"4005 Co Rd 266",
    "sg:city":"Henderson",
    "sg:classifiers":[
        {
            "category":"Home & Garden",
            "subcategory":"Carpets & Floor Coverings",
            "type":"Retail Goods"
        }
    ],
    "sg:phone":"+1 903 836 2557",
    "sg:postcode":"75652",
    "sg:province":"TX",
    "sg:tags":[
        "contractor"
    ],
    "wof:name":"Runnels Carpets",
    "wof:placetype":"venue"
},
  "geometry": {"coordinates":[-94.70272300000001,32.198262],"type":"Point"}
}