{
  "type": "Feature",
  "properties": {
    "iso:country":"US",
    "sg:address":"5728 Marview Ln",
    "sg:city":"Dallas",
    "sg:classifiers":[
        {
            "category":"Professional",
            "subcategory":"Lawyer & Legal Services",
            "type":"Services"
        }
    ],
    "sg:phone":"+1 214 426 5876",
    "sg:postcode":"75227",
    "sg:province":"TX",
    "sg:tags":[
        "attorney"
    ],
    "wof:name":"Gene Gaines",
    "wof:placetype":"venue"
},
  "geometry": {"coordinates":[-96.701511,32.784514],"type":"Point"}
}