{
  "type": "Feature",
  "properties": {
    "iso:country":"US",
    "sg:address":"6121 Park Ln",
    "sg:city":"Dallas",
    "sg:classifiers":[
        {
            "category":"Utilities",
            "subcategory":"Mobile Phone",
            "type":"Services"
        }
    ],
    "sg:phone":"+1 972 202 2836",
    "sg:postcode":"75225",
    "sg:province":"TX",
    "sg:tags":[
        "telephone",
        "cellular"
    ],
    "wof:name":"Cingular Wireless",
    "wof:placetype":"venue"
},
  "geometry": {"coordinates":[-96.801453,32.873428],"type":"Point"}
}