{
  "type": "Feature",
  "properties": {
    "iso:country":"US",
    "sg:address":"2002 Clover Ln",
    "sg:city":"Cedar Park",
    "sg:classifiers":[
        {
            "category":"Building & Trades",
            "subcategory":"Electrical",
            "type":"Services"
        }
    ],
    "sg:phone":"+1 512 259 4313",
    "sg:postcode":"78613",
    "sg:province":"TX",
    "sg:tags":[
        "electrical",
        "contractor"
    ],
    "wof:name":"Fineline Communications",
    "wof:placetype":"venue"
},
  "geometry": {"coordinates":[-97.843284,30.534644],"type":"Point"}
}