{
  "type": "Feature",
  "properties": {
    "iso:country":"US",
    "sg:address":"6419 Larmanda St",
    "sg:city":"Dallas",
    "sg:classifiers":[
        {
            "category":"Communications",
            "subcategory":"Radio Station",
            "type":"Services"
        }
    ],
    "sg:phone":"+1 214 363 7588",
    "sg:postcode":"75231",
    "sg:province":"TX",
    "sg:tags":[
        "company",
        "broadcasting"
    ],
    "wof:name":"4everadio",
    "wof:placetype":"venue"
},
  "geometry": {"coordinates":[-96.744097,32.862524],"type":"Point"}
}