{
  "type": "Feature",
  "properties": {
    "iso:country":"US",
    "sg:address":"5151 Belt Line Rd",
    "sg:city":"Dallas",
    "sg:classifiers":[
        {
            "category":"Professional",
            "subcategory":"Business Services",
            "type":"Services"
        }
    ],
    "sg:phone":"+1 972 404 7584",
    "sg:postcode":"75254",
    "sg:province":"TX",
    "wof:name":"Ketchum Inc",
    "wof:placetype":"venue"
},
  "geometry": {"coordinates":[-96.81884700000001,32.954064],"type":"Point"}
}