{
  "type": "Feature",
  "properties": {
    "iso:country":"US",
    "sg:address":"4607 Modern Ln",
    "sg:city":"Laredo",
    "sg:classifiers":[
        {
            "category":"Freight",
            "type":"Transportation"
        }
    ],
    "sg:phone":"+1 956 723 0630",
    "sg:postcode":"78041",
    "sg:province":"TX",
    "wof:name":"Falcon Transfer Inc",
    "wof:placetype":"venue"
},
  "geometry": {"coordinates":[-99.513176,27.542935],"type":"Point"}
}