{
  "type": "Feature",
  "properties": {
    "iso:country":"US",
    "sg:address":"10506 Brentway Dr",
    "sg:city":"Houston",
    "sg:classifiers":[
        {
            "category":"Manufacturing",
            "subcategory":"Glass & Minerals",
            "type":"Manufacturing & Wholesale Goods"
        }
    ],
    "sg:phone":"+1 281 955 1269",
    "sg:postcode":"77070",
    "sg:province":"TX",
    "sg:tags":[
        "product",
        "nonmetallic",
        "mfg"
    ],
    "wof:name":"Pams Art & Collectables",
    "wof:placetype":"venue"
},
  "geometry": {"coordinates":[-95.580398,29.971658],"type":"Point"}
}