{
  "type": "Feature",
  "properties": {
    "iso:country":"US",
    "sg:address":"1982 S Austin Ave",
    "sg:city":"Georgetown",
    "sg:classifiers":[
        {
            "category":"Professional",
            "type":"Services"
        }
    ],
    "sg:phone":"+1 512 868 0713",
    "sg:postcode":"78626",
    "sg:province":"TX",
    "sg:tags":[
        "establishment"
    ],
    "wof:name":"Sw Enterprises",
    "wof:placetype":"venue"
},
  "geometry": {"coordinates":[-97.67845800000001,30.625908],"type":"Point"}
}