{
  "type": "Feature",
  "properties": {
    "iso:country":"US",
    "sg:address":"2299 E Mulberry St",
    "sg:city":"Angleton",
    "sg:classifiers":[
        {
            "category":"Food & Beverages",
            "subcategory":"Groceries & Convenience Stores",
            "type":"Retail Goods"
        }
    ],
    "sg:phone":"+1 979 864 3313",
    "sg:postcode":"77515",
    "sg:province":"TX",
    "wof:name":"Buc-Ees 13",
    "wof:placetype":"venue"
},
  "geometry": {"coordinates":[-95.410088,29.182086],"type":"Point"}
}