{
  "type": "Feature",
  "properties": {
    "iso:country":"US",
    "sg:address":"11301 I-45 N",
    "sg:city":"Houston",
    "sg:classifiers":[
        {
            "category":"Restaurant",
            "type":"Food & Drink"
        }
    ],
    "sg:phone":"+1 281 999 9928",
    "sg:postcode":"77037",
    "sg:province":"TX",
    "sg:tags":[
        "seafood"
    ],
    "wof:name":"Pappas",
    "wof:placetype":"venue"
},
  "geometry": {"coordinates":[-95.412481,29.891401],"type":"Point"}
}