{
  "type": "Feature",
  "properties": {
    "iso:country":"US",
    "sg:address":"11166 FM 521",
    "sg:city":"Rosharon",
    "sg:classifiers":[
        {
            "category":"Building & Trades",
            "subcategory":"Construction",
            "type":"Services"
        }
    ],
    "sg:phone":"+1 281 369 3280",
    "sg:postcode":"77583",
    "sg:province":"TX",
    "sg:tags":[
        "water",
        "well",
        "drilling"
    ],
    "wof:name":"Chaffin Water Well Servic",
    "wof:placetype":"venue"
},
  "geometry": {"coordinates":[-95.477909,29.4252],"type":"Point"}
}