{
  "type": "Feature",
  "properties": {
    "iso:country":"US",
    "sg:address":"2417 W Park Row Dr",
    "sg:city":"Arlington",
    "sg:classifiers":[
        {
            "category":"Restaurant",
            "type":"Food & Drink"
        }
    ],
    "sg:phone":"+1 817 548 1300",
    "sg:postcode":"76013",
    "sg:province":"TX",
    "sg:tags":[
        "florist",
        "eating"
    ],
    "wof:name":"Victors Bakery & Cafe Inc",
    "wof:placetype":"venue"
},
  "geometry": {"coordinates":[-97.147046,32.721406],"type":"Point"}
}