{
  "type": "Feature",
  "properties": {
    "iso:country":"US",
    "sg:address":"1321 State Hwy 1604",
    "sg:city":"San Antonio",
    "sg:classifiers":[
        {
            "category":"Shopping",
            "subcategory":"Shoes",
            "type":"Retail Goods"
        }
    ],
    "sg:phone":"+1 210 499 4772",
    "sg:postcode":"78232",
    "sg:province":"TX",
    "wof:name":"Payless Shoe Source",
    "wof:placetype":"venue"
},
  "geometry": {"coordinates":[-98.47059,29.609777],"type":"Point"}
}