{
  "type": "Feature",
  "properties": {
    "iso:country":"US",
    "sg:address":"1501 W Expy 83",
    "sg:city":"Mcallen",
    "sg:classifiers":[
        {
            "category":"Airline",
            "type":"Transportation"
        }
    ],
    "sg:phone":"+1 956 682 5513",
    "sg:postcode":"78501",
    "sg:province":"TX",
    "sg:tags":[
        "bus",
        "line",
        "courier",
        "intercity",
        "air"
    ],
    "wof:name":"McAllen Bus Depot",
    "wof:placetype":"venue"
},
  "geometry": {"coordinates":[-98.238928,26.190818],"type":"Point"}
}