{
  "type": "Feature",
  "properties": {
    "iso:country":"US",
    "sg:address":"3521 Northwest Pkwy",
    "sg:city":"Dallas",
    "sg:classifiers":[
        {
            "category":"Recreation",
            "type":"Entertainment"
        }
    ],
    "sg:phone":"+1 214 373 7475",
    "sg:postcode":"75225",
    "sg:province":"TX",
    "wof:name":"Fs Martial Arts",
    "wof:placetype":"venue"
},
  "geometry": {"coordinates":[-96.791511,32.865319],"type":"Point"}
}