{
  "type": "Feature",
  "properties": {
    "iso:country":"US",
    "sg:address":"11101 Burnet Rd",
    "sg:city":"Austin",
    "sg:classifiers":[
        {
            "category":"Shopping",
            "subcategory":"Department Store",
            "type":"Retail Goods"
        }
    ],
    "sg:phone":"+1 512 719 4141",
    "sg:postcode":"78758",
    "sg:province":"TX",
    "wof:name":"Detour Domain",
    "wof:placetype":"venue"
},
  "geometry": {"coordinates":[-97.72026200000001,30.395769],"type":"Point"}
}