{
  "type": "Feature",
  "properties": {
    "iso:country":"US",
    "sg:address":"2424 W Illinois Ave",
    "sg:city":"Dallas",
    "sg:classifiers":[
        {
            "category":"Donuts",
            "subcategory":"None",
            "type":"Food & Drink"
        }
    ],
    "sg:phone":"+1 214 467 4199",
    "sg:postcode":"75233",
    "sg:province":"TX",
    "wof:name":"Oak Cliff Donuts No 2",
    "wof:placetype":"venue"
},
  "geometry": {"coordinates":[-96.85749800000001,32.720299],"type":"Point"}
}