{
  "type": "Feature",
  "properties": {
    "iso:country":"US",
    "sg:address":"606 S Dumas Ave",
    "sg:city":"Dumas",
    "sg:classifiers":[
        {
            "category":"Personal",
            "subcategory":"Beauty Salon",
            "type":"Services"
        }
    ],
    "sg:phone":"+1 806 934 1411",
    "sg:postcode":"79029",
    "sg:province":"TX",
    "wof:name":"Merle Norman Cosmetics",
    "wof:placetype":"venue"
},
  "geometry": {"coordinates":[-101.973353,35.859803],"type":"Point"}
}