{
  "type": "Feature",
  "properties": {
    "iso:country":"US",
    "sg:address":"4111 Issacks Way",
    "sg:city":"Sugar Land",
    "sg:classifiers":[
        {
            "category":"Professional",
            "subcategory":"Business Services",
            "type":"Services"
        }
    ],
    "sg:phone":"+1 281 980 5296",
    "sg:postcode":"77479",
    "sg:province":"TX",
    "wof:name":"Janelle Interiors",
    "wof:placetype":"venue"
},
  "geometry": {"coordinates":[-95.593298,29.586042],"type":"Point"}
}