{
  "type": "Feature",
  "properties": {
    "iso:country":"US",
    "sg:address":"501 W Brown St",
    "sg:city":"Ennis",
    "sg:classifiers":[
        {
            "category":"Wholesale",
            "subcategory":"Machinery & Supplies",
            "type":"Manufacturing & Wholesale Goods"
        },
        {
            "category":"Personal",
            "subcategory":"Beauty Salon",
            "type":"Services"
        }
    ],
    "sg:phone":"+1 972 875 6441",
    "sg:postcode":"75119",
    "sg:province":"TX",
    "sg:tags":[
        "shop",
        "retail"
    ],
    "wof:name":"Sally's Beauty Shop",
    "wof:placetype":"venue"
},
  "geometry": {"coordinates":[-96.630298,32.325168],"type":"Point"}
}