{
  "type": "Feature",
  "properties": {
    "iso:country":"US",
    "sg:address":"704 Houston St",
    "sg:city":"Richmond",
    "sg:classifiers":[
        {
            "category":"Education",
            "subcategory":"School",
            "type":"Public Place"
        }
    ],
    "sg:phone":"+1 281 341 3322",
    "sg:postcode":"77469",
    "sg:province":"TX",
    "sg:website":"www.lcisd.org",
    "wof:name":"Jane Long Elementary School",
    "wof:placetype":"venue"
},
  "geometry": {"coordinates":[-95.76315200000001,29.579681],"type":"Point"}
}