{
  "type": "Feature",
  "properties": {
    "iso:country":"US",
    "sg:address":"8514 Peachtree St",
    "sg:city":"Houston",
    "sg:classifiers":[
        {
            "category":"Personal",
            "subcategory":"Beauty Salon",
            "type":"Services"
        }
    ],
    "sg:phone":"+1 713 635 4804",
    "sg:postcode":"77016",
    "sg:province":"TX",
    "sg:tags":[
        "shop",
        "clothing"
    ],
    "wof:name":"Hair & Fashions Unlimited Intl",
    "wof:placetype":"venue"
},
  "geometry": {"coordinates":[-95.31523900000001,29.840443],"type":"Point"}
}