{
  "type": "Feature",
  "properties": {
    "iso:country":"US",
    "sg:address":"423 S Monroe St",
    "sg:city":"Eagle Pass",
    "sg:classifiers":[
        {
            "category":"Freight",
            "type":"Transportation"
        },
        {
            "category":"Professional",
            "subcategory":"Management & Consulting",
            "type":"Services"
        }
    ],
    "sg:phone":"+1 830 757 1959",
    "sg:postcode":"78852",
    "sg:province":"TX",
    "sg:tags":[
        "warehouse",
        "product",
        "storage",
        "telephone",
        "self"
    ],
    "wof:name":"Hamar Enterprises Inc",
    "wof:placetype":"venue"
},
  "geometry": {"coordinates":[-100.500281,28.70195],"type":"Point"}
}