{
  "type": "Feature",
  "properties": {
    "iso:country":"US",
    "sg:address":"525 E Elm St",
    "sg:city":"Gainesville",
    "sg:classifiers":[
        {
            "category":"Education",
            "subcategory":"School",
            "type":"Public Place"
        }
    ],
    "sg:phone":"+1 940 668 1982",
    "sg:postcode":"76240",
    "sg:province":"TX",
    "wof:name":"Lindsay's School Fieldhouse",
    "wof:placetype":"venue"
},
  "geometry": {"coordinates":[-97.14084,33.625115],"type":"Point"}
}