{
  "type": "Feature",
  "properties": {
    "iso:country":"US",
    "sg:address":"10536 Sentinel St",
    "sg:city":"San Antonio",
    "sg:classifiers":[
        {
            "category":"Social Services",
            "type":"Services"
        }
    ],
    "sg:phone":"+1 210 654 3700",
    "sg:postcode":"78217",
    "sg:province":"TX",
    "sg:tags":[
        "instruction",
        "health",
        "care"
    ],
    "wof:name":"Healthcare Revenue Cycle",
    "wof:placetype":"venue"
},
  "geometry": {"coordinates":[-98.44437000000001,29.539825],"type":"Point"}
}