{
  "type": "Feature",
  "properties": {
    "iso:country":"US",
    "sg:address":"6610 Garth Rd",
    "sg:city":"Baytown",
    "sg:classifiers":[
        {
            "category":"Personal",
            "subcategory":"Nail Salon",
            "type":"Services"
        }
    ],
    "sg:phone":"+1 281 421 2266",
    "sg:postcode":"77521",
    "sg:province":"TX",
    "wof:name":"Elegant Nail",
    "wof:placetype":"venue"
},
  "geometry": {"coordinates":[-94.980766,29.797],"type":"Point"}
}