{
  "type": "Feature",
  "properties": {
    "iso:country":"US",
    "sg:address":"631 Leftwich St",
    "sg:city":"Mount Vernon",
    "sg:classifiers":[
        {
            "category":"Wholesale",
            "subcategory":"Non-durable Goods",
            "type":"Manufacturing & Wholesale Goods"
        }
    ],
    "sg:phone":"+1 903 537 2052",
    "sg:postcode":"75457",
    "sg:province":"TX",
    "wof:name":"Roach Associates",
    "wof:placetype":"venue"
},
  "geometry": {"coordinates":[-95.22322200000001,33.181428],"type":"Point"}
}