{
  "type": "Feature",
  "properties": {
    "iso:country":"US",
    "sg:address":"9523 Fairbanks N Houston Rd",
    "sg:city":"Houston",
    "sg:classifiers":[
        {
            "category":"Professional",
            "type":"Services"
        }
    ],
    "sg:phone":"+1 281 890 5328",
    "sg:postcode":"77064",
    "sg:province":"TX",
    "sg:tags":[
        "establishment"
    ],
    "wof:name":"Nci Fairbanks",
    "wof:placetype":"venue"
},
  "geometry": {"coordinates":[-95.52515699999999,29.919198],"type":"Point"}
}