{
  "type": "Feature",
  "properties": {
    "iso:country":"US",
    "sg:address":"1211 Country Place Dr",
    "sg:city":"Houston",
    "sg:classifiers":[
        {
            "category":"Organizations",
            "subcategory":"Professional Association",
            "type":"Services"
        },
        {
            "category":"Organizations",
            "subcategory":"Community Association",
            "type":"Services"
        }
    ],
    "sg:phone":"+1 281 497 7840",
    "sg:postcode":"77079",
    "sg:province":"TX",
    "sg:tags":[
        "membership"
    ],
    "wof:name":"Memorial Club Townhouses Assn",
    "wof:placetype":"venue"
},
  "geometry": {"coordinates":[-95.599324,29.781191],"type":"Point"}
}