{
  "type": "Feature",
  "properties": {
    "iso:country":"US",
    "sg:address":"3601 Easton Meadows Dr",
    "sg:city":"Garland",
    "sg:classifiers":[
        {
            "category":"Shopping",
            "subcategory":"Clothing, Apparel, & Fashions",
            "type":"Retail Goods"
        }
    ],
    "sg:phone":"+1 972 303 5603",
    "sg:postcode":"75043",
    "sg:province":"TX",
    "wof:name":"Seigles Signature Fashion",
    "wof:placetype":"venue"
},
  "geometry": {"coordinates":[-96.575282,32.852308],"type":"Point"}
}