{
  "type": "Feature",
  "properties": {
    "iso:country":"US",
    "sg:address":"2424 S Cockrell Hill Rd",
    "sg:city":"Dallas",
    "sg:classifiers":[
        {
            "category":"Restaurant",
            "type":"Food & Drink"
        }
    ],
    "sg:phone":"+1 214 337 0096",
    "sg:postcode":"75211",
    "sg:province":"TX",
    "sg:tags":[
        "drinking",
        "eating"
    ],
    "wof:name":"Cooper's Restaurant & Club",
    "wof:placetype":"venue"
},
  "geometry": {"coordinates":[-96.891502,32.719898],"type":"Point"}
}