{
  "type": "Feature",
  "properties": {
    "iso:country":"US",
    "sg:address":"841 Heinz Way",
    "sg:city":"Grand Prairie",
    "sg:classifiers":[
        {
            "category":"Insurance",
            "subcategory":"Insurance Agent",
            "type":"Services"
        }
    ],
    "sg:phone":"+1 972 606 9972",
    "sg:postcode":"75051",
    "sg:province":"TX",
    "wof:name":"Principle Mutal Life Insurance",
    "wof:placetype":"venue"
},
  "geometry": {"coordinates":[-97.04005600000001,32.734484],"type":"Point"}
}