{
  "type": "Feature",
  "properties": {
    "iso:country":"US",
    "sg:address":"8428 Ave P",
    "sg:city":"Lubbock",
    "sg:classifiers":[
        {
            "category":"Building & Trades",
            "subcategory":"Plumbing",
            "type":"Services"
        }
    ],
    "sg:phone":"+1 806 785 7666",
    "sg:postcode":"79423",
    "sg:province":"TX",
    "sg:tags":[
        "contractor"
    ],
    "wof:name":"Randall Carpenter Plumbing",
    "wof:placetype":"venue"
},
  "geometry": {"coordinates":[-101.85312999999999,33.517533],"type":"Point"}
}