{
  "type": "Feature",
  "properties": {
    "iso:country":"US",
    "sg:address":"905 E Los Ebanos Blvd",
    "sg:city":"Brownsville",
    "sg:classifiers":[
        {
            "category":"Professional",
            "type":"Services"
        }
    ],
    "sg:phone":"+1 956 504 1166",
    "sg:postcode":"78520",
    "sg:province":"TX",
    "wof:name":"Opportunity Y Brownsville",
    "wof:placetype":"venue"
},
  "geometry": {"coordinates":[-97.503759,25.932024],"type":"Point"}
}