{
  "type": "Feature",
  "properties": {
    "iso:country":"US",
    "sg:address":"9640 Clinton Dr",
    "sg:city":"Houston",
    "sg:classifiers":[
        {
            "category":"Government",
            "subcategory":"Office",
            "type":"Public Place"
        }
    ],
    "sg:phone":"+1 713 678 4573",
    "sg:postcode":"77029",
    "sg:province":"TX",
    "sg:tags":[
        "transportation"
    ],
    "wof:name":"Coast Guard Exchange System",
    "wof:placetype":"venue"
},
  "geometry": {"coordinates":[-95.25778200000001,29.733204],"type":"Point"}
}