{
  "type": "Feature",
  "properties": {
    "iso:country":"US",
    "sg:address":"2526 Quaker Dr",
    "sg:city":"Texas City",
    "sg:classifiers":[
        {
            "category":"Farming",
            "subcategory":"Livestock Farm",
            "type":"Manufacturing & Wholesale Goods"
        }
    ],
    "sg:phone":"+1 409 948 3572",
    "sg:postcode":"77590",
    "sg:province":"TX",
    "sg:tags":[
        "animal",
        "general"
    ],
    "wof:name":"Billups Ranch",
    "wof:placetype":"venue"
},
  "geometry": {"coordinates":[-94.928161,29.42119],"type":"Point"}
}