{
  "type": "Feature",
  "properties": {
    "iso:country":"US",
    "sg:address":"512 N Travis St",
    "sg:city":"Sherman",
    "sg:classifiers":[
        {
            "category":"Home & Garden",
            "subcategory":"Furniture",
            "type":"Retail Goods"
        }
    ],
    "sg:phone":"+1 903 891 0011",
    "sg:postcode":"75090",
    "sg:province":"TX",
    "sg:tags":[
        "wholesaler",
        "household",
        "retailer"
    ],
    "wof:name":"Hometown Wholesale Furn Clubs",
    "wof:placetype":"venue"
},
  "geometry": {"coordinates":[-96.61051500000001,33.640567],"type":"Point"}
}