{
  "type": "Feature",
  "properties": {
    "iso:country":"US",
    "sg:address":"4239 Holland Ave",
    "sg:city":"Dallas",
    "sg:classifiers":[
        {
            "category":"Professional",
            "type":"Services"
        }
    ],
    "sg:phone":"+1 214 599 9221",
    "sg:postcode":"75219",
    "sg:province":"TX",
    "wof:name":"Evol Real Estate of Texas LLC",
    "wof:placetype":"venue"
},
  "geometry": {"coordinates":[-96.80906899999999,32.817906],"type":"Point"}
}