{
  "type": "Feature",
  "properties": {
    "iso:country":"US",
    "sg:address":"525 S el Paso St",
    "sg:city":"El Paso",
    "sg:classifiers":[
        {
            "category":"Shopping",
            "subcategory":"Shoes",
            "type":"Retail Goods"
        }
    ],
    "sg:phone":"+1 325 351 6345",
    "sg:postcode":"79901",
    "sg:province":"TX",
    "wof:name":"Tennis Shoes Christian",
    "wof:placetype":"venue"
},
  "geometry": {"coordinates":[-106.487751,31.7536],"type":"Point"}
}