{
  "type": "Feature",
  "properties": {
    "iso:country":"US",
    "sg:address":"5908 Monterrey Dr",
    "sg:city":"Fort Worth",
    "sg:classifiers":[
        {
            "category":"Professional",
            "subcategory":"Management & Consulting",
            "type":"Services"
        }
    ],
    "sg:phone":"+1 817 457 8699",
    "sg:postcode":"76112",
    "sg:province":"TX",
    "sg:tags":[
        "business"
    ],
    "wof:name":"WJS Associates",
    "wof:placetype":"venue"
},
  "geometry": {"coordinates":[-97.229293,32.750988],"type":"Point"}
}