{
  "type": "Feature",
  "properties": {
    "iso:country":"US",
    "sg:address":"11460 Garland Rd",
    "sg:city":"Dallas",
    "sg:classifiers":[
        {
            "category":"Autos & Motor Vehicles",
            "subcategory":"Motorcycle Sales",
            "type":"Retail Goods"
        }
    ],
    "sg:phone":"+1 214 321 1929",
    "sg:postcode":"75218",
    "sg:province":"TX",
    "wof:name":"White Rock Custom",
    "wof:placetype":"venue"
},
  "geometry": {"coordinates":[-96.682019,32.850065],"type":"Point"}
}