{
  "type": "Feature",
  "properties": {
    "iso:country":"US",
    "sg:address":"7211 Upland Ave",
    "sg:city":"Lubbock",
    "sg:classifiers":[
        {
            "category":"Home & Garden",
            "subcategory":"Building Materials",
            "type":"Retail Goods"
        }
    ],
    "sg:phone":"+1 806 794 8860",
    "sg:postcode":"79424",
    "sg:province":"TX",
    "sg:tags":[
        "glass",
        "window",
        "plate"
    ],
    "wof:name":"Hardin Glass Svc",
    "wof:placetype":"venue"
},
  "geometry": {"coordinates":[-101.974328,33.528208],"type":"Point"}
}