{
  "type": "Feature",
  "properties": {
    "iso:country":"US",
    "sg:address":"22111 Gosling Rd",
    "sg:city":"Spring",
    "sg:classifiers":[
        {
            "category":"Shopping",
            "subcategory":"Gifts & Souvenirs",
            "type":"Retail Goods"
        }
    ],
    "sg:phone":"+1 281 288 6134",
    "sg:postcode":"77389",
    "sg:province":"TX",
    "sg:tags":[
        "balloon",
        "artist"
    ],
    "wof:name":"Booger Bears",
    "wof:placetype":"venue"
},
  "geometry": {"coordinates":[-95.50699899999999,30.084426],"type":"Point"}
}