{
  "type": "Feature",
  "properties": {
    "iso:country":"US",
    "sg:address":"1999 Kolfahl St",
    "sg:city":"Houston",
    "sg:classifiers":[
        {
            "category":"Wholesale",
            "subcategory":"Machinery & Supplies",
            "type":"Manufacturing & Wholesale Goods"
        }
    ],
    "sg:phone":"+1 713 923 2101",
    "sg:postcode":"77023",
    "sg:province":"TX",
    "sg:tags":[
        "valve"
    ],
    "sg:website":"www.eggelhof.com",
    "wof:name":"Eggelhof Inc",
    "wof:placetype":"venue"
},
  "geometry": {"coordinates":[-95.3258,29.722275],"type":"Point"}
}