{
  "type": "Feature",
  "properties": {
    "iso:country":"US",
    "sg:address":"7539 US Hwy 67",
    "sg:city":"Simms",
    "sg:classifiers":[
        {
            "category":"Government",
            "subcategory":"Post Office",
            "type":"Public Place"
        }
    ],
    "sg:phone":"+1 903 543 2768",
    "sg:postcode":"75501",
    "sg:province":"TX",
    "wof:name":"US Post Office",
    "wof:placetype":"venue"
},
  "geometry": {"coordinates":[-94.15769299999999,33.406146],"type":"Point"}
}