{
  "type": "Feature",
  "properties": {
    "iso:country":"US",
    "sg:address":"8181 Tezel Rd",
    "sg:city":"San Antonio",
    "sg:classifiers":[
        {
            "category":"Freight",
            "type":"Transportation"
        }
    ],
    "sg:phone":"+1 210 373 7700",
    "sg:postcode":"78250",
    "sg:province":"TX",
    "wof:name":"Integrating Moving Services",
    "wof:placetype":"venue"
},
  "geometry": {"coordinates":[-98.66242,29.517095],"type":"Point"}
}