{
  "type": "Feature",
  "properties": {
    "iso:country":"US",
    "sg:address":"23115 Dragon Rock Rd",
    "sg:city":"Elmendorf",
    "sg:classifiers":[
        {
            "category":"Professional",
            "subcategory":"Accounting & Tax Preparation",
            "type":"Services"
        }
    ],
    "sg:phone":"+1 210 621 0287",
    "sg:postcode":"78112",
    "sg:province":"TX",
    "sg:tags":[
        "return"
    ],
    "wof:name":"J Cox & Sons Co",
    "wof:placetype":"venue"
},
  "geometry": {"coordinates":[-98.41573699999999,29.177336],"type":"Point"}
}