{
  "type": "Feature",
  "properties": {
    "iso:country":"US",
    "sg:address":"805 E 32nd St",
    "sg:city":"Austin",
    "sg:classifiers":[
        {
            "category":"Health Services",
            "subcategory":"Doctor",
            "type":"Services"
        }
    ],
    "sg:phone":"+1 512 323 2452",
    "sg:postcode":"78705",
    "sg:province":"TX",
    "wof:name":"Silverthorn Andrew C MD",
    "wof:placetype":"venue"
},
  "geometry": {"coordinates":[-97.7286,30.2918],"type":"Point"}
}