{
  "type": "Feature",
  "properties": {
    "iso:country":"US",
    "sg:address":"3023 Deer Hollow Dr",
    "sg:city":"Mesquite",
    "sg:classifiers":[
        {
            "category":"Building & Trades",
            "subcategory":"Cleaning & Sanitation",
            "type":"Services"
        }
    ],
    "sg:phone":"+1 972 222 3710",
    "sg:postcode":"75181",
    "sg:province":"TX",
    "sg:tags":[
        "maintenance"
    ],
    "wof:name":"First Choice Janitorial",
    "wof:placetype":"venue"
},
  "geometry": {"coordinates":[-96.55551699999999,32.739303],"type":"Point"}
}