{
  "type": "Feature",
  "properties": {
    "iso:country":"US",
    "sg:address":"920 E Expy 83",
    "sg:city":"Mcallen",
    "sg:classifiers":[
        {
            "category":"Home & Garden",
            "subcategory":"Home Furnishings",
            "type":"Retail Goods"
        }
    ],
    "sg:phone":"+1 956 683 7461",
    "sg:postcode":"78503",
    "sg:province":"TX",
    "sg:tags":[
        "linen"
    ],
    "wof:name":"Anna's Linens",
    "wof:placetype":"venue"
},
  "geometry": {"coordinates":[-98.20968999999999,26.190805],"type":"Point"}
}