{
  "type": "Feature",
  "properties": {
    "iso:country":"US",
    "sg:address":"7215 Rancho Mission Dr",
    "sg:city":"Houston",
    "sg:classifiers":[
        {
            "category":"Sports & Exercise",
            "subcategory":"Bowling",
            "type":"Entertainment"
        }
    ],
    "sg:phone":"+1 281 933 7476",
    "sg:postcode":"77083",
    "sg:province":"TX",
    "sg:tags":[
        "center"
    ],
    "wof:name":"Super Bowl Catering & Flowers",
    "wof:placetype":"venue"
},
  "geometry": {"coordinates":[-95.645324,29.699265],"type":"Point"}
}