{
  "type": "Feature",
  "properties": {
    "iso:country":"US",
    "sg:address":"3004 N Closner Blvd",
    "sg:city":"Edinburg",
    "sg:classifiers":[
        {
            "category":"Health Services",
            "subcategory":"Clinic",
            "type":"Services"
        },
        {
            "category":"Health Services",
            "subcategory":"Health Practitioner",
            "type":"Services"
        }
    ],
    "sg:phone":"+1 956 383 0101",
    "sg:postcode":"78541",
    "sg:province":"TX",
    "sg:tags":[
        "information",
        "addiction-information",
        "alcoholism",
        "treatment",
        "gambling",
        "rehabilitation"
    ],
    "wof:name":"Total Care Rehab Center",
    "wof:placetype":"venue"
},
  "geometry": {"coordinates":[-98.157213,26.330908],"type":"Point"}
}