{
  "type": "Feature",
  "properties": {
    "iso:country":"US",
    "sg:address":"8440 State Hwy 242",
    "sg:city":"Conroe",
    "sg:classifiers":[
        {
            "category":"Building & Trades",
            "subcategory":"Plumbing",
            "type":"Services"
        }
    ],
    "sg:phone":"+1 936 321 2665",
    "sg:postcode":"77385",
    "sg:province":"TX",
    "sg:tags":[
        "conditioning",
        "air",
        "system",
        "contractor"
    ],
    "wof:name":"Coolair Air Conditioning & Htg",
    "wof:placetype":"venue"
},
  "geometry": {"coordinates":[-95.44645199999999,30.208239],"type":"Point"}
}