{
  "type": "Feature",
  "properties": {
    "iso:country":"US",
    "sg:address":"1645 Brittmoore Rd",
    "sg:city":"Houston",
    "sg:classifiers":[
        {
            "category":"Wholesale",
            "subcategory":"Farm Supplies",
            "type":"Manufacturing & Wholesale Goods"
        }
    ],
    "sg:phone":"+1 713 464 7070",
    "sg:postcode":"77043",
    "sg:province":"TX",
    "sg:tags":[
        "nursery"
    ],
    "wof:name":"Nutri Fern Products",
    "wof:placetype":"venue"
},
  "geometry": {"coordinates":[-95.569863,29.803967],"type":"Point"}
}