{
  "type": "Feature",
  "properties": {
    "iso:country":"US",
    "sg:address":"2417 S Stemmons Fwy",
    "sg:city":"Lewisville",
    "sg:classifiers":[
        {
            "category":"Shopping",
            "subcategory":"Gifts & Souvenirs",
            "type":"Retail Goods"
        }
    ],
    "sg:phone":"+1 972 459 3820",
    "sg:postcode":"75067",
    "sg:province":"TX",
    "sg:tags":[
        "shop"
    ],
    "wof:name":"Hallmark Creations",
    "wof:placetype":"venue"
},
  "geometry": {"coordinates":[-96.97117,33.005711],"type":"Point"}
}