{
  "type": "Feature",
  "properties": {
    "iso:country":"US",
    "sg:address":"1509 S 14th St",
    "sg:city":"Abilene",
    "sg:classifiers":[
        {
            "category":"Shopping",
            "subcategory":"Hobbies, Toys, & Games",
            "type":"Retail Goods"
        },
        {
            "category":"Shopping",
            "type":"Retail Goods"
        }
    ],
    "sg:phone":"+1 325 437 5407",
    "sg:postcode":"79602",
    "sg:province":"TX",
    "sg:tags":[
        "games-wholesale",
        "video",
        "merchandise",
        "supplies-wholesale",
        "manufacturer"
    ],
    "wof:name":"Manuels Nintendo Games and Collectables",
    "wof:placetype":"venue"
},
  "geometry": {"coordinates":[-99.740921,32.432098],"type":"Point"}
}