{
  "type": "Feature",
  "properties": {
    "iso:country":"US",
    "sg:address":"4905 Barclay Dr",
    "sg:city":"Tyler",
    "sg:classifiers":[
        {
            "category":"Recreation",
            "type":"Entertainment"
        }
    ],
    "sg:phone":"+1 903 561 7750",
    "sg:postcode":"75703",
    "sg:province":"TX",
    "sg:tags":[
        "device",
        "operator",
        "amusement"
    ],
    "wof:name":"Putt Putt Golf & Games",
    "wof:placetype":"venue"
},
  "geometry": {"coordinates":[-95.310529,32.295295],"type":"Point"}
}