{
  "type": "Feature",
  "properties": {
    "iso:country":"US",
    "sg:address":"12203 Midland Walk",
    "sg:city":"Austin",
    "sg:classifiers":[
        {
            "category":"Banks & Credit Unions",
            "subcategory":"Bank",
            "type":"Services"
        }
    ],
    "sg:phone":"+1 512 258 2057",
    "sg:postcode":"78727",
    "sg:province":"TX",
    "sg:tags":[
        "institution",
        "business"
    ],
    "wof:name":"Robert J Stroh Family Ltd",
    "wof:placetype":"venue"
},
  "geometry": {"coordinates":[-97.73651599999999,30.425158],"type":"Point"}
}