{
  "type": "Feature",
  "properties": {
    "iso:country":"US",
    "sg:address":"18207 Co Rd 127",
    "sg:city":"Pearland",
    "sg:classifiers":[
        {
            "category":"Professional",
            "type":"Services"
        }
    ],
    "sg:phone":"+1 281 996 9878",
    "sg:postcode":"77581",
    "sg:province":"TX",
    "wof:name":"Texas Bloomers",
    "wof:placetype":"venue"
},
  "geometry": {"coordinates":[-95.231649,29.519991],"type":"Point"}
}