{
  "type": "Feature",
  "properties": {
    "iso:country":"US",
    "sg:address":"7821 Santa Monica Ct",
    "sg:city":"El Paso",
    "sg:classifiers":[
        {
            "category":"Personal",
            "type":"Services"
        }
    ],
    "sg:phone":"+1 915 240 4053",
    "sg:postcode":"79915",
    "sg:province":"TX",
    "sg:tags":[
        "mobile",
        "home",
        "handyman",
        "repair"
    ],
    "wof:name":"Gloria & Associates",
    "wof:placetype":"venue"
},
  "geometry": {"coordinates":[-106.35243,31.745909],"type":"Point"}
}