{
  "type": "Feature",
  "properties": {
    "iso:country":"US",
    "sg:address":"2040 W Spring Creek Pkwy",
    "sg:city":"Plano",
    "sg:classifiers":[
        {
            "category":"Wholesale",
            "subcategory":"Sporting Goods",
            "type":"Manufacturing & Wholesale Goods"
        }
    ],
    "sg:phone":"+1 972 527 8062",
    "sg:postcode":"75023",
    "sg:province":"TX",
    "sg:tags":[
        "equipment",
        "exercise"
    ],
    "wof:name":"Fitness Clearinghouse Inc",
    "wof:placetype":"venue"
},
  "geometry": {"coordinates":[-96.729073,33.057719],"type":"Point"}
}