{
  "type": "Feature",
  "properties": {
    "iso:country":"US",
    "sg:address":"702 Forrest St",
    "sg:city":"Waco",
    "sg:classifiers":[
        {
            "category":"Wholesale",
            "subcategory":"Meat",
            "type":"Manufacturing & Wholesale Goods"
        }
    ],
    "sg:phone":"+1 254 752 2506",
    "sg:postcode":"76704",
    "sg:province":"TX",
    "wof:name":"H & B Packing Co",
    "wof:placetype":"venue"
},
  "geometry": {"coordinates":[-97.113646,31.566695],"type":"Point"}
}