{
  "type": "Feature",
  "properties": {
    "iso:country":"US",
    "sg:address":"2109 Exposition Blvd",
    "sg:city":"Austin",
    "sg:classifiers":[
        {
            "category":"Communications",
            "subcategory":"Film & Video Production",
            "type":"Services"
        }
    ],
    "sg:phone":"+1 512 342 7168",
    "sg:postcode":"78703",
    "sg:province":"TX",
    "sg:tags":[
        "motion"
    ],
    "wof:name":"Breathing Productions",
    "wof:placetype":"venue"
},
  "geometry": {"coordinates":[-97.769406,30.294555],"type":"Point"}
}