{
  "type": "Feature",
  "properties": {
    "iso:country":"US",
    "sg:address":"221 S Washington St",
    "sg:city":"Seymour",
    "sg:classifiers":[
        {
            "category":"Professional",
            "subcategory":"Accounting & Tax Preparation",
            "type":"Services"
        }
    ],
    "sg:phone":"+1 940 889 5133",
    "sg:postcode":"76380",
    "sg:province":"TX",
    "sg:tags":[
        "consultant"
    ],
    "wof:name":"Stavinoha Tax Svc",
    "wof:placetype":"venue"
},
  "geometry": {"coordinates":[-99.261545,33.586636],"type":"Point"}
}