{
  "type": "Feature",
  "properties": {
    "iso:country":"US",
    "sg:address":"5811 S 23rd St",
    "sg:city":"Mcallen",
    "sg:classifiers":[
        {
            "category":"Professional",
            "type":"Services"
        }
    ],
    "sg:phone":"+1 956 661 0733",
    "sg:postcode":"78503",
    "sg:province":"TX",
    "sg:tags":[
        "establishment"
    ],
    "wof:name":"Benny's Auto Mart",
    "wof:placetype":"venue"
},
  "geometry": {"coordinates":[-98.252769,26.155775],"type":"Point"}
}