{
  "type": "Feature",
  "properties": {
    "iso:country":"US",
    "sg:address":"110 W Norwood Ct",
    "sg:city":"San Antonio",
    "sg:classifiers":[
        {
            "category":"Building & Trades",
            "subcategory":"Landscaping Services",
            "type":"Services"
        }
    ],
    "sg:phone":"+1 210 826 3512",
    "sg:postcode":"78212",
    "sg:province":"TX",
    "sg:tags":[
        "landscape"
    ],
    "wof:name":"Good Guys Landscape & MAI",
    "wof:placetype":"venue"
},
  "geometry": {"coordinates":[-98.49538800000001,29.467859],"type":"Point"}
}