{
  "type": "Feature",
  "properties": {
    "iso:country":"US",
    "sg:address":"7400 Fannin St",
    "sg:city":"Houston",
    "sg:classifiers":[
        {
            "category":"Health Services",
            "subcategory":"Doctor",
            "type":"Services"
        }
    ],
    "sg:phone":"+1 713 790 1001",
    "sg:postcode":"77054",
    "sg:province":"TX",
    "wof:name":"Moon Jimmy J DDS & Barbara S",
    "wof:placetype":"venue"
},
  "geometry": {"coordinates":[-95.400808,29.695646],"type":"Point"}
}