{
  "type": "Feature",
  "properties": {
    "iso:country":"US",
    "sg:address":"5905 Cabrillo Dr",
    "sg:city":"El Paso",
    "sg:classifiers":[
        {
            "category":"Building & Trades",
            "subcategory":"Construction",
            "type":"Services"
        }
    ],
    "sg:phone":"+1 915 581 5824",
    "sg:postcode":"79912",
    "sg:province":"TX",
    "sg:tags":[
        "residential",
        "remodeling",
        "contractor"
    ],
    "wof:name":"A G Enterprises",
    "wof:placetype":"venue"
},
  "geometry": {"coordinates":[-106.539428,31.823892],"type":"Point"}
}