{
  "type": "Feature",
  "properties": {
    "iso:country":"US",
    "sg:address":"1324 Common St",
    "sg:city":"New Braunfels",
    "sg:classifiers":[
        {
            "category":"Shopping",
            "type":"Retail Goods"
        }
    ],
    "sg:phone":"+1 830 620 4327",
    "sg:postcode":"78130",
    "sg:province":"TX",
    "sg:tags":[
        "hearing",
        "equipment",
        "supply",
        "impaired"
    ],
    "wof:name":"Dottie Will's Advanced Hearing",
    "wof:placetype":"venue"
},
  "geometry": {"coordinates":[-98.100793,29.722151],"type":"Point"}
}