{
  "type": "Feature",
  "properties": {
    "iso:country":"US",
    "sg:address":"9501 N Navarro St",
    "sg:city":"Victoria",
    "sg:classifiers":[
        {
            "category":"Manufacturing",
            "subcategory":"Signs",
            "type":"Manufacturing & Wholesale Goods"
        }
    ],
    "sg:phone":"+1 361 573 4535",
    "sg:postcode":"77904",
    "sg:province":"TX",
    "sg:tags":[
        "advertising",
        "specialty"
    ],
    "wof:name":"Directional Design",
    "wof:placetype":"venue"
},
  "geometry": {"coordinates":[-96.995362,28.886187],"type":"Point"}
}