{
  "type": "Feature",
  "properties": {
    "iso:country":"US",
    "sg:address":"28105 State Hwy 249",
    "sg:city":"Tomball",
    "sg:classifiers":[
        {
            "category":"Building & Trades",
            "subcategory":"Pest Control",
            "type":"Services"
        }
    ],
    "sg:phone":"+1 281 351 8986",
    "sg:postcode":"77375",
    "sg:province":"TX",
    "sg:tags":[
        "spraying",
        "lawn",
        "structural"
    ],
    "wof:name":"Pro-Chem Pest Control Systems",
    "wof:placetype":"venue"
},
  "geometry": {"coordinates":[-95.630518,30.081889],"type":"Point"}
}