{
  "type": "Feature",
  "properties": {
    "iso:country":"US",
    "sg:address":"104 W Myrtle St",
    "sg:city":"Angleton",
    "sg:classifiers":[
        {
            "category":"Professional",
            "type":"Services"
        },
        {
            "category":"Professional",
            "subcategory":"Credit Reporting & Collection",
            "type":"Services"
        }
    ],
    "sg:phone":"+1 979 849 7022",
    "sg:postcode":"77515",
    "sg:province":"TX",
    "sg:tags":[
        "agency"
    ],
    "wof:name":"Processing Plus",
    "wof:placetype":"venue"
},
  "geometry": {"coordinates":[-95.431856,29.165569],"type":"Point"}
}