{
  "type": "Feature",
  "properties": {
    "iso:country":"US",
    "sg:address":"1808 N Cage Blvd",
    "sg:city":"Pharr",
    "sg:classifiers":[
        {
            "category":"Wholesale",
            "subcategory":"Electrical",
            "type":"Manufacturing & Wholesale Goods"
        }
    ],
    "sg:phone":"+1 956 787 1200",
    "sg:postcode":"78577",
    "sg:province":"TX",
    "wof:name":"Appliances Outlet",
    "wof:placetype":"venue"
},
  "geometry": {"coordinates":[-98.181494,26.210677],"type":"Point"}
}