{
  "type": "Feature",
  "properties": {
    "iso:country":"US",
    "sg:address":"10519 C F Hawn Fwy",
    "sg:city":"Dallas",
    "sg:classifiers":[
        {
            "category":"Autos & Motor Vehicles",
            "subcategory":"Automobile Sales",
            "type":"Retail Goods"
        }
    ],
    "sg:phone":"+1 972 557 5622",
    "sg:postcode":"75217",
    "sg:province":"TX",
    "sg:tags":[
        "car",
        "dealer"
    ],
    "wof:name":"Zaida's Auto Sales & Svc",
    "wof:placetype":"venue"
},
  "geometry": {"coordinates":[-96.639599,32.694715],"type":"Point"}
}