{
  "type": "Feature",
  "properties": {
    "iso:country":"US",
    "sg:address":"7305 Pegasus Dr",
    "sg:city":"Temple",
    "sg:classifiers":[
        {
            "category":"Building & Trades",
            "subcategory":"Electrical",
            "type":"Services"
        }
    ],
    "sg:phone":"+1 254 778 0050",
    "sg:postcode":"76501",
    "sg:province":"TX",
    "sg:tags":[
        "installation"
    ],
    "wof:name":"United Installation Inc",
    "wof:placetype":"venue"
},
  "geometry": {"coordinates":[-97.322006,31.167765],"type":"Point"}
}