{
  "type": "Feature",
  "properties": {
    "iso:country":"US",
    "sg:address":"2004 Travis Heights Blvd",
    "sg:city":"Austin",
    "sg:classifiers":[
        {
            "category":"Shopping",
            "subcategory":"Used Merchandise",
            "type":"Retail Goods"
        }
    ],
    "sg:phone":"+1 512 442 3466",
    "sg:postcode":"78704",
    "sg:province":"TX",
    "wof:name":"William Bradshaw",
    "wof:placetype":"venue"
},
  "geometry": {"coordinates":[-97.74440300000001,30.239583],"type":"Point"}
}