{
  "type": "Feature",
  "properties": {
    "iso:country":"US",
    "sg:address":"605 Masterson Pass",
    "sg:city":"Austin",
    "sg:classifiers":[
        {
            "category":"Professional",
            "type":"Services"
        }
    ],
    "sg:phone":"+1 512 651 5511",
    "sg:postcode":"78753",
    "sg:province":"TX",
    "sg:tags":[
        "establishment"
    ],
    "wof:name":"Family Eldercare",
    "wof:placetype":"venue"
},
  "geometry": {"coordinates":[-97.69241,30.371105],"type":"Point"}
}