{
  "type": "Feature",
  "properties": {
    "iso:country":"US",
    "sg:address":"4601 N Lamar Blvd Ste 105",
    "sg:city":"Austin",
    "sg:phone":"+1 512 892 6699",
    "sg:postcode":"78751",
    "sg:province":"TX",
    "wof:name":"Tien Jin Chinese Restaurant",
    "wof:placetype":"venue"
},
  "geometry": {"coordinates":[-97.731602,30.31748],"type":"Point"}
}