{
  "type": "Feature",
  "properties": {
    "iso:country":"US",
    "sg:address":"8391 Westview Dr",
    "sg:city":"Houston",
    "sg:classifiers":[
        {
            "category":"Health Services",
            "subcategory":"Doctor",
            "type":"Services"
        }
    ],
    "sg:phone":"+1 713 465 4300",
    "sg:postcode":"77055",
    "sg:province":"TX",
    "sg:tags":[
        "surgeon",
        "oral"
    ],
    "wof:name":"Robinson Allen J DDS",
    "wof:placetype":"venue"
},
  "geometry": {"coordinates":[-95.49490400000001,29.794701],"type":"Point"}
}