{
  "type": "Feature",
  "properties": {
    "iso:country":"US",
    "sg:address":"3401 Main St Ste A",
    "sg:city":"Dallas",
    "sg:classifiers":[
        {
            "category":"Personal",
            "subcategory":"Beauty Salon",
            "type":"Services"
        },
        {
            "category":"Personal",
            "subcategory":"Hair Removal",
            "type":"Services"
        }
    ],
    "sg:phone":"+1 214 554 7936",
    "sg:postcode":"75226",
    "sg:province":"TX",
    "sg:tags":[
        "wig",
        "piece",
        "weaving",
        "stylist"
    ],
    "sg:website":"http://www.braidlesshairextensions.com",
    "wof:name":"Braidless Hair Extensions By Jady",
    "wof:placetype":"venue"
},
  "geometry": {"coordinates":[-96.776093,32.785419],"type":"Point"}
}