{
  "type": "Feature",
  "properties": {
    "iso:country":"US",
    "sg:address":"9020 Creekwood Pass",
    "sg:city":"Spring Branch",
    "sg:classifiers":[
        {
            "category":"Professional",
            "subcategory":"Advertising",
            "type":"Services"
        }
    ],
    "sg:phone":"+1 830 885 5130",
    "sg:postcode":"78070",
    "sg:province":"TX",
    "sg:tags":[
        "counselor"
    ],
    "wof:name":"Ousset Agency Inc",
    "wof:placetype":"venue"
},
  "geometry": {"coordinates":[-98.370684,29.824788],"type":"Point"}
}