{
  "type": "Feature",
  "properties": {
    "iso:country":"US",
    "sg:address":"2034 Central Blvd",
    "sg:city":"Brownsville",
    "sg:classifiers":[
        {
            "category":"Restaurant",
            "type":"Food & Drink"
        }
    ],
    "sg:phone":"+1 956 504 2285",
    "sg:postcode":"78520",
    "sg:province":"TX",
    "sg:tags":[
        "eating"
    ],
    "wof:name":"Pitti's Pizza",
    "wof:placetype":"venue"
},
  "geometry": {"coordinates":[-97.510482,25.933454],"type":"Point"}
}