{
  "type": "Feature",
  "properties": {
    "iso:country":"US",
    "sg:address":"2000 N Midland Dr",
    "sg:city":"Midland",
    "sg:classifiers":[
        {
            "category":"Food & Beverages",
            "subcategory":"Bakery",
            "type":"Retail Goods"
        }
    ],
    "sg:phone":"+1 432 699 6536",
    "sg:postcode":"79707",
    "sg:province":"TX",
    "sg:tags":[
        "doughnut"
    ],
    "wof:name":"T & T Donuts",
    "wof:placetype":"venue"
},
  "geometry": {"coordinates":[-102.138351,32.006321],"type":"Point"}
}