{
  "type": "Feature",
  "properties": {
    "iso:country":"US",
    "sg:address":"3405 Coit Rd",
    "sg:city":"Plano",
    "sg:classifiers":[
        {
            "category":"Wholesale",
            "subcategory":"Stationery",
            "type":"Manufacturing & Wholesale Goods"
        }
    ],
    "sg:phone":"+1 972 398 6255",
    "sg:postcode":"75093",
    "sg:province":"TX",
    "sg:tags":[
        "box",
        "fiber"
    ],
    "wof:name":"Storage USA",
    "wof:placetype":"venue"
},
  "geometry": {"coordinates":[-96.770382,33.044184],"type":"Point"}
}