{
  "type": "Feature",
  "properties": {
    "iso:country":"US",
    "sg:address":"6300 W Parker Rd",
    "sg:city":"Plano",
    "sg:classifiers":[
        {
            "category":"Health Services",
            "subcategory":"Doctor",
            "type":"Services"
        }
    ],
    "sg:phone":"+1 214 691 1172",
    "sg:postcode":"75093",
    "sg:province":"TX",
    "sg:tags":[
        "dentist"
    ],
    "wof:name":"Carrie B Choate DDS",
    "wof:placetype":"venue"
},
  "geometry": {"coordinates":[-96.83747700000001,33.045061],"type":"Point"}
}