{
  "type": "Feature",
  "properties": {
    "iso:country":"US",
    "sg:address":"117 Heneretta Dr",
    "sg:city":"Hurst",
    "sg:classifiers":[
        {
            "category":"Building & Trades",
            "subcategory":"Construction",
            "type":"Services"
        }
    ],
    "sg:phone":"+1 817 706 6537",
    "sg:postcode":"76054",
    "sg:province":"TX",
    "sg:tags":[
        "contractor"
    ],
    "wof:name":"Bobby James Contracting",
    "wof:placetype":"venue"
},
  "geometry": {"coordinates":[-97.167849,32.873599],"type":"Point"}
}