{
  "type": "Feature",
  "properties": {
    "iso:country":"US",
    "sg:address":"11715 Meadow Place Ct",
    "sg:city":"Houston",
    "sg:classifiers":[
        {
            "category":"Professional",
            "type":"Services"
        }
    ],
    "sg:phone":"+1 713 779 6844",
    "sg:postcode":"77071",
    "sg:province":"TX",
    "wof:name":"Eakon Services",
    "wof:placetype":"venue"
},
  "geometry": {"coordinates":[-95.532391,29.650291],"type":"Point"}
}