{
  "type": "Feature",
  "properties": {
    "iso:country":"US",
    "sg:address":"5164 Buffalo Speedway",
    "sg:city":"Houston",
    "sg:classifiers":[
        {
            "category":"Education",
            "subcategory":"Special Training",
            "type":"Public Place"
        }
    ],
    "sg:phone":"+1 713 432 9700",
    "sg:postcode":"77005",
    "sg:province":"TX",
    "wof:name":"Rak One Partners Ltd",
    "wof:placetype":"venue"
},
  "geometry": {"coordinates":[-95.427987,29.72808],"type":"Point"}
}