{
  "type": "Feature",
  "properties": {
    "iso:country":"US",
    "sg:address":"2623 Lily St",
    "sg:city":"Pasadena",
    "sg:classifiers":[
        {
            "category":"Manufacturing",
            "subcategory":"Metals",
            "type":"Manufacturing & Wholesale Goods"
        }
    ],
    "sg:phone":"+1 281 487 1624",
    "sg:postcode":"77503",
    "sg:province":"TX",
    "sg:tags":[
        "product",
        "fabricated",
        "mfg"
    ],
    "wof:name":"Dph Enterprises",
    "wof:placetype":"venue"
},
  "geometry": {"coordinates":[-95.167106,29.672838],"type":"Point"}
}