{
  "type": "Feature",
  "properties": {
    "iso:country":"US",
    "sg:address":"4320 Avonshire Ln",
    "sg:city":"Plano",
    "sg:classifiers":[
        {
            "category":"Shopping",
            "subcategory":"Gifts & Souvenirs",
            "type":"Retail Goods"
        }
    ],
    "sg:phone":"+1 972 867 1383",
    "sg:postcode":"75093",
    "sg:province":"TX",
    "wof:name":"The Jones Alliance",
    "wof:placetype":"venue"
},
  "geometry": {"coordinates":[-96.777665,33.042438],"type":"Point"}
}