{
  "type": "Feature",
  "properties": {
    "iso:country":"US",
    "sg:address":"1006 Mo Pac Cir Ste 102",
    "sg:city":"Austin",
    "sg:classifiers":[
        {
            "category":"Social Services",
            "type":"Services"
        }
    ],
    "sg:phone":"+1 512 732 0033",
    "sg:postcode":"78746",
    "sg:province":"TX",
    "sg:tags":[
        "human"
    ],
    "wof:name":"Patient Privacy Rights Foundation",
    "wof:placetype":"venue"
},
  "geometry": {"coordinates":[-97.783817,30.266296],"type":"Point"}
}