{
  "type": "Feature",
  "properties": {
    "iso:country":"US",
    "sg:address":"3817 Alamo Ave",
    "sg:city":"Fort Worth",
    "sg:classifiers":[
        {
            "category":"Insurance",
            "subcategory":"Hazard Insurance",
            "type":"Services"
        }
    ],
    "sg:phone":"+1 817 731 2568",
    "sg:postcode":"76107",
    "sg:province":"TX",
    "sg:tags":[
        "fidelity",
        "bond"
    ],
    "sg:website":"www.txsurety.com",
    "wof:name":"Texas Contractors Surety",
    "wof:placetype":"venue"
},
  "geometry": {"coordinates":[-97.374436,32.731989],"type":"Point"}
}