{
  "type": "Feature",
  "properties": {
    "iso:country":"US",
    "sg:address":"10117 Leatherwood Dr",
    "sg:city":"Fort Worth",
    "sg:classifiers":[
        {
            "category":"Building & Trades",
            "subcategory":"Construction",
            "type":"Services"
        }
    ],
    "sg:phone":"+1 817 246 1431",
    "sg:postcode":"76108",
    "sg:province":"TX",
    "sg:tags":[
        "woodworker"
    ],
    "wof:name":"All Things Wood",
    "wof:placetype":"venue"
},
  "geometry": {"coordinates":[-97.49610199999999,32.763739],"type":"Point"}
}