{
  "type": "Feature",
  "properties": {
    "iso:country":"US",
    "sg:address":"10400 Westoffice Dr",
    "sg:city":"Houston",
    "sg:classifiers":[
        {
            "category":"Professional",
            "type":"Services"
        },
        {
            "category":"Building & Trades",
            "subcategory":"Construction",
            "type":"Services"
        }
    ],
    "sg:phone":"+1 281 493 9073",
    "sg:postcode":"77042",
    "sg:province":"TX",
    "sg:tags":[
        "establishment",
        "contractor"
    ],
    "wof:name":"Glastek Inc",
    "wof:placetype":"venue"
},
  "geometry": {"coordinates":[-95.550766,29.72062],"type":"Point"}
}