{
  "type": "Feature",
  "properties": {
    "iso:country":"US",
    "sg:address":"13000 Marsh Ln",
    "sg:city":"Dallas",
    "sg:classifiers":[
        {
            "category":"Organizations",
            "subcategory":"Religious Organization",
            "type":"Services"
        }
    ],
    "sg:phone":"+1 972 241 2006",
    "sg:postcode":"75234",
    "sg:province":"TX",
    "sg:tags":[
        "church"
    ],
    "sg:website":"www.brookhavenchurch.com",
    "wof:name":"Brookhaven Church",
    "wof:placetype":"venue"
},
  "geometry": {"coordinates":[-96.855885,32.922682],"type":"Point"}
}