{
  "type": "Feature",
  "properties": {
    "iso:country":"US",
    "sg:address":"1112 W Ave G",
    "sg:city":"Temple",
    "sg:classifiers":[
        {
            "category":"Freight",
            "type":"Transportation"
        }
    ],
    "sg:phone":"+1 254 718 1932",
    "sg:postcode":"76504",
    "sg:province":"TX",
    "sg:tags":[
        "general"
    ],
    "wof:name":"Hall Travis & Mary Entps",
    "wof:placetype":"venue"
},
  "geometry": {"coordinates":[-97.355521,31.092999],"type":"Point"}
}