{
  "type": "Feature",
  "properties": {
    "iso:country":"US",
    "sg:address":"1001 N 14th St",
    "sg:city":"Kingsville",
    "sg:classifiers":[
        {
            "category":"Restaurant",
            "type":"Food & Drink"
        }
    ],
    "sg:phone":"+1 361 592 6275",
    "sg:postcode":"78363",
    "sg:province":"TX",
    "wof:name":"Las Palmas Drive Thru",
    "wof:placetype":"venue"
},
  "geometry": {"coordinates":[-97.856139,27.526206],"type":"Point"}
}