{
  "type": "Feature",
  "properties": {
    "iso:country":"US",
    "sg:address":"300 Vaden Ave",
    "sg:city":"Fort Worth",
    "sg:classifiers":[
        {
            "category":"Building & Trades",
            "subcategory":"Construction",
            "type":"Services"
        }
    ],
    "sg:phone":"+1 817 568 1565",
    "sg:postcode":"76140",
    "sg:province":"TX",
    "sg:tags":[
        "nonresidential"
    ],
    "wof:name":"Am T Bros",
    "wof:placetype":"venue"
},
  "geometry": {"coordinates":[-97.28712899999999,32.627156],"type":"Point"}
}