{
  "type": "Feature",
  "properties": {
    "iso:country":"US",
    "sg:address":"14363 Torrey Chase Blvd",
    "sg:city":"Houston",
    "sg:classifiers":[
        {
            "category":"Health Services",
            "subcategory":"Health Practitioner",
            "type":"Services"
        }
    ],
    "sg:phone":"+1 281 880 9494",
    "sg:postcode":"77014",
    "sg:province":"TX",
    "wof:name":"Resolve Counseling Center",
    "wof:placetype":"venue"
},
  "geometry": {"coordinates":[-95.49136300000001,29.984766],"type":"Point"}
}