{
  "type": "Feature",
  "properties": {
    "iso:country":"US",
    "sg:address":"20530 Gulf Fwy",
    "sg:city":"Webster",
    "sg:classifiers":[
        {
            "category":"Building & Trades",
            "subcategory":"Construction",
            "type":"Services"
        }
    ],
    "sg:phone":"+1 281 332 1475",
    "sg:postcode":"77598",
    "sg:province":"TX",
    "sg:tags":[
        "floor",
        "laying",
        "contractor"
    ],
    "wof:name":"Mark Abbies",
    "wof:placetype":"venue"
},
  "geometry": {"coordinates":[-95.133786,29.531354],"type":"Point"}
}