{
  "type": "Feature",
  "properties": {
    "iso:country":"US",
    "sg:address":"1722 Sky Lark Ln",
    "sg:city":"Houston",
    "sg:classifiers":[
        {
            "category":"Professional",
            "subcategory":"Computer Services",
            "type":"Services"
        }
    ],
    "sg:phone":"+1 713 838 0038",
    "sg:postcode":"77056",
    "sg:province":"TX",
    "sg:tags":[
        "web",
        "consulting",
        "design",
        "page",
        "related"
    ],
    "wof:name":"Trinicom Communications LLC",
    "wof:placetype":"venue"
},
  "geometry": {"coordinates":[-95.463882,29.74906],"type":"Point"}
}