{
  "type": "Feature",
  "properties": {
    "iso:country":"US",
    "sg:address":"5930 Star Ln",
    "sg:city":"Houston",
    "sg:classifiers":[
        {
            "category":"Real Estate",
            "subcategory":"Real Estate Agent",
            "type":"Services"
        }
    ],
    "sg:phone":"+1 713 661 3008",
    "sg:postcode":"77057",
    "sg:province":"TX",
    "wof:name":"Avalon Media Partners",
    "wof:placetype":"venue"
},
  "geometry": {"coordinates":[-95.481964,29.727588],"type":"Point"}
}