{
  "type": "Feature",
  "properties": {
    "iso:country":"US",
    "sg:address":"17906 Fieldglen Dr",
    "sg:city":"Houston",
    "sg:classifiers":[
        {
            "category":"Manufacturing",
            "subcategory":"Musical Instruments",
            "type":"Manufacturing & Wholesale Goods"
        }
    ],
    "sg:phone":"+1 281 463 4436",
    "sg:postcode":"77084",
    "sg:province":"TX",
    "sg:tags":[
        "mfg"
    ],
    "wof:name":"Guitarz",
    "wof:placetype":"venue"
},
  "geometry": {"coordinates":[-95.681766,29.873708],"type":"Point"}
}