{
  "type": "Feature",
  "properties": {
    "iso:country":"US",
    "sg:address":"714 E I- 30",
    "sg:city":"Rockwall",
    "sg:classifiers":[
        {
            "category":"Food & Beverages",
            "subcategory":"Candy",
            "type":"Retail Goods"
        }
    ],
    "sg:phone":"+1 972 771 9603",
    "sg:postcode":"75043",
    "sg:province":"TX",
    "sg:tags":[
        "cookie",
        "arrangement"
    ],
    "wof:name":"Candy Dreams & More",
    "wof:placetype":"venue"
},
  "geometry": {"coordinates":[-96.564695,32.852667],"type":"Point"}
}