{
  "type": "Feature",
  "properties": {
    "iso:country":"US",
    "sg:address":"8810 Bevlyn Dr",
    "sg:city":"Houston",
    "sg:classifiers":[
        {
            "category":"Professional",
            "subcategory":"Computer Services",
            "type":"Services"
        }
    ],
    "sg:phone":"+1 713 661 6745",
    "sg:postcode":"77025",
    "sg:province":"TX",
    "sg:tags":[
        "datum"
    ],
    "wof:name":"Robin Kellogg Accounting Svcs",
    "wof:placetype":"venue"
},
  "geometry": {"coordinates":[-95.43045499999999,29.687574],"type":"Point"}
}