{
  "type": "Feature",
  "properties": {
    "iso:country":"US",
    "sg:address":"915 W 3rd St",
    "sg:city":"Pecos",
    "sg:classifiers":[
        {
            "category":"Food & Beverages",
            "subcategory":"Groceries & Convenience Stores",
            "type":"Retail Goods"
        }
    ],
    "sg:phone":"+1 432 445 1285",
    "sg:postcode":"79772",
    "sg:province":"TX",
    "wof:name":"KWIK Stop",
    "wof:placetype":"venue"
},
  "geometry": {"coordinates":[-103.50341899999999,31.422838],"type":"Point"}
}