{
  "type": "Feature",
  "properties": {
    "iso:country":"US",
    "sg:address":"417 S Cage Blvd",
    "sg:city":"Pharr",
    "sg:classifiers":[
        {
            "category":"Organizations",
            "subcategory":"Community Association",
            "type":"Services"
        }
    ],
    "sg:phone":"+1 956 787 7451",
    "sg:postcode":"78577",
    "sg:province":"TX",
    "sg:tags":[
        "military"
    ],
    "wof:name":"American Legion",
    "wof:placetype":"venue"
},
  "geometry": {"coordinates":[-98.18468300000001,26.190573],"type":"Point"}
}