{
  "type": "Feature",
  "properties": {
    "iso:country":"US",
    "sg:address":"5913 Volunteer Pl",
    "sg:city":"Rockwall",
    "sg:classifiers":[
        {
            "category":"Personal",
            "subcategory":"Beauty Salon",
            "type":"Services"
        }
    ],
    "sg:phone":"+1 972 771 6245",
    "sg:postcode":"75032",
    "sg:province":"TX",
    "sg:tags":[
        "shop"
    ],
    "wof:name":"Pinkies",
    "wof:placetype":"venue"
},
  "geometry": {"coordinates":[-96.47594700000001,32.878436],"type":"Point"}
}