{
  "type": "Feature",
  "properties": {
    "iso:country":"US",
    "sg:address":"517 Mill Creek Ct",
    "sg:city":"Azle",
    "sg:classifiers":[
        {
            "category":"Shopping",
            "subcategory":"Bicycles & Sporting Goods",
            "type":"Retail Goods"
        }
    ],
    "sg:phone":"+1 817 448 9311",
    "sg:postcode":"76020",
    "sg:province":"TX",
    "wof:name":"Brasch Enterprises",
    "wof:placetype":"venue"
},
  "geometry": {"coordinates":[-97.558942,32.850407],"type":"Point"}
}