{
  "type": "Feature",
  "properties": {
    "iso:country":"US",
    "sg:address":"7514 Centenary Dr",
    "sg:city":"Rowlett",
    "sg:classifiers":[
        {
            "category":"Manufacturing",
            "subcategory":"Printing",
            "type":"Manufacturing & Wholesale Goods"
        }
    ],
    "sg:phone":"+1 469 366 9423",
    "sg:postcode":"75089",
    "sg:province":"TX",
    "sg:tags":[
        "lithographic",
        "commercial"
    ],
    "wof:name":"Hall Printing & Promotional PR",
    "wof:placetype":"venue"
},
  "geometry": {"coordinates":[-96.527253,32.928523],"type":"Point"}
}