{
  "type": "Feature",
  "properties": {
    "iso:country":"US",
    "sg:address":"2820 Main St",
    "sg:city":"Dickinson",
    "sg:classifiers":[
        {
            "category":"Professional",
            "subcategory":"Engineering",
            "type":"Services"
        }
    ],
    "sg:phone":"+1 281 309 9100",
    "sg:postcode":"77539",
    "sg:province":"TX",
    "sg:tags":[
        "engineer"
    ],
    "sg:website":"www.jkcassociates.com",
    "wof:name":"JKC & Assoc Inc",
    "wof:placetype":"venue"
},
  "geometry": {"coordinates":[-95.049261,29.460817],"type":"Point"}
}