{
  "type": "Feature",
  "properties": {
    "iso:country":"US",
    "sg:address":"3601 Catclaw Dr",
    "sg:city":"Abilene",
    "sg:classifiers":[
        {
            "category":"Shopping",
            "subcategory":"Clothing, Apparel, & Fashions",
            "type":"Retail Goods"
        }
    ],
    "sg:phone":"+1 325 692 4230",
    "sg:postcode":"79606",
    "sg:province":"TX",
    "wof:name":"Old Navy",
    "wof:placetype":"venue"
},
  "geometry": {"coordinates":[-99.776858,32.40809],"type":"Point"}
}