{
  "type": "Feature",
  "properties": {
    "iso:country":"US",
    "sg:address":"1229 Industrial St",
    "sg:city":"New Braunfels",
    "sg:classifiers":[
        {
            "category":"Shopping",
            "type":"Retail Goods"
        }
    ],
    "sg:phone":"+1 830 620 8473",
    "sg:postcode":"78130",
    "sg:province":"TX",
    "sg:tags":[
        "mexican"
    ],
    "wof:name":"Guadalupe Import Co",
    "wof:placetype":"venue"
},
  "geometry": {"coordinates":[-98.097309,29.71615],"type":"Point"}
}