{
  "type": "Feature",
  "properties": {
    "iso:country":"US",
    "sg:address":"609 Rocky River Rd",
    "sg:city":"Austin",
    "sg:classifiers":[
        {
            "category":"Professional",
            "subcategory":"Computer Services",
            "type":"Services"
        }
    ],
    "sg:phone":"+1 512 478 7727",
    "sg:postcode":"78746",
    "sg:province":"TX",
    "sg:tags":[
        "prepackaged",
        "software"
    ],
    "wof:name":"Advanced Workflow Solutions",
    "wof:placetype":"venue"
},
  "geometry": {"coordinates":[-97.80027699999999,30.287369],"type":"Point"}
}