{
  "type": "Feature",
  "properties": {
    "iso:country":"US",
    "sg:address":"8240 Antoine Dr",
    "sg:city":"Houston",
    "sg:classifiers":[
        {
            "category":"Health Services",
            "subcategory":"Doctor",
            "type":"Services"
        }
    ],
    "sg:phone":"+1 281 999 6059",
    "sg:postcode":"77088",
    "sg:province":"TX",
    "sg:tags":[
        "physician",
        "surgeon"
    ],
    "wof:name":"Neonatal Circumcision Specs",
    "wof:placetype":"venue"
},
  "geometry": {"coordinates":[-95.474358,29.886744],"type":"Point"}
}