{
  "type": "Feature",
  "properties": {
    "iso:country":"US",
    "sg:address":"2705 W Cardinal Dr",
    "sg:city":"Beaumont",
    "sg:classifiers":[
        {
            "category":"Wholesale",
            "subcategory":"Petroleum",
            "type":"Manufacturing & Wholesale Goods"
        }
    ],
    "sg:phone":"+1 409 842 4422",
    "sg:postcode":"77705",
    "sg:province":"TX",
    "sg:tags":[
        "pipe",
        "line",
        "company"
    ],
    "wof:name":"Cypress Creek Pipeline",
    "wof:placetype":"venue"
},
  "geometry": {"coordinates":[-94.11151099999999,30.0373],"type":"Point"}
}