{
  "type": "Feature",
  "properties": {
    "iso:country":"US",
    "sg:address":"403 N Adams St",
    "sg:city":"Carthage",
    "sg:classifiers":[
        {
            "category":"Health Services",
            "subcategory":"Optometrist",
            "type":"Services"
        }
    ],
    "sg:phone":"+1 903 694 2300",
    "sg:postcode":"75633",
    "sg:province":"TX",
    "sg:tags":[
        "optical",
        "good"
    ],
    "wof:name":"Donald Eye Care",
    "wof:placetype":"venue"
},
  "geometry": {"coordinates":[-94.35178999999999,32.15988],"type":"Point"}
}