{
  "type": "Feature",
  "properties": {
    "iso:country":"US",
    "sg:address":"1100 Louisiana St",
    "sg:city":"Houston",
    "sg:classifiers":[
        {
            "category":"Restaurant",
            "type":"Food & Drink"
        }
    ],
    "sg:menulink":"http://www.allmenus.com/tx/houston/62620-subway/menu/",
    "sg:phone":"+1 713 751 8821",
    "sg:postcode":"77002",
    "sg:province":"TX",
    "sg:tags":[
        "american",
        "sandwich"
    ],
    "wof:name":"Subway",
    "wof:placetype":"venue"
},
  "geometry": {"coordinates":[-95.368185,29.757681],"type":"Point"}
}