{
  "type": "Feature",
  "properties": {
    "iso:country":"US",
    "sg:address":"13125 S Osage St",
    "sg:city":"Amarillo",
    "sg:classifiers":[
        {
            "category":"Autos & Motor Vehicles",
            "subcategory":"Automobile Sales",
            "type":"Retail Goods"
        }
    ],
    "sg:phone":"+1 806 622 2323",
    "sg:postcode":"79118",
    "sg:province":"TX",
    "sg:tags":[
        "car",
        "dealer"
    ],
    "wof:name":"J B's Auto",
    "wof:placetype":"venue"
},
  "geometry": {"coordinates":[-101.81283000000001,35.080495],"type":"Point"}
}