{
  "type": "Feature",
  "properties": {
    "iso:country":"US",
    "sg:address":"2021 W Governors Cir",
    "sg:city":"Houston",
    "sg:classifiers":[
        {
            "category":"Real Estate",
            "subcategory":"Real Estate Operator",
            "type":"Services"
        }
    ],
    "sg:phone":"+1 713 682 4454",
    "sg:postcode":"77092",
    "sg:province":"TX",
    "sg:tags":[
        "building",
        "parks"
    ],
    "wof:name":"Governors Circle Office Bldg",
    "wof:placetype":"venue"
},
  "geometry": {"coordinates":[-95.45111,29.806055],"type":"Point"}
}