{
  "type": "Feature",
  "properties": {
    "iso:country":"US",
    "sg:address":"2607 Underwood Ln",
    "sg:city":"Euless",
    "sg:classifiers":[
        {
            "category":"Retail",
            "subcategory":"Laundry & Dry Cleaning",
            "type":"Services"
        }
    ],
    "sg:phone":"+1 817 267 7115",
    "sg:postcode":"76039",
    "sg:province":"TX",
    "sg:tags":[
        "cleaners",
        "rug",
        "carpet"
    ],
    "wof:name":"Lone Star Carpet Cleaning Co",
    "wof:placetype":"venue"
},
  "geometry": {"coordinates":[-97.0895,32.875155],"type":"Point"}
}