{
  "type": "Feature",
  "properties": {
    "iso:country":"US",
    "sg:address":"1214 Park Meadow Dr",
    "sg:city":"Katy",
    "sg:classifiers":[
        {
            "category":"Professional",
            "subcategory":"Business Services",
            "type":"Services"
        }
    ],
    "sg:phone":"+1 281 646 9681",
    "sg:postcode":"77450",
    "sg:province":"TX",
    "wof:name":"Design By Carol",
    "wof:placetype":"venue"
},
  "geometry": {"coordinates":[-95.74319300000001,29.764205],"type":"Point"}
}