{
  "type": "Feature",
  "properties": {
    "iso:country":"US",
    "sg:address":"2911 Herring Ave",
    "sg:city":"Waco",
    "sg:classifiers":[
        {
            "category":"Health Services",
            "subcategory":"Medical Lab",
            "type":"Services"
        }
    ],
    "sg:phone":"+1 254 755 4420",
    "sg:postcode":"76708",
    "sg:province":"TX",
    "sg:tags":[
        "laboratory"
    ],
    "wof:name":"Clinical Pathology Labs Inc",
    "wof:placetype":"venue"
},
  "geometry": {"coordinates":[-97.17464200000001,31.56021],"type":"Point"}
}