{
  "type": "Feature",
  "properties": {
    "iso:country":"US",
    "sg:address":"1813 Hidalgo Blvd",
    "sg:city":"Zapata",
    "sg:classifiers":[
        {
            "category":"Restaurant",
            "type":"Food & Drink"
        }
    ],
    "sg:phone":"+1 956 765 3119",
    "sg:postcode":"78076",
    "sg:province":"TX",
    "wof:name":"El Arbolito",
    "wof:placetype":"venue"
},
  "geometry": {"coordinates":[-99.275141,26.913435],"type":"Point"}
}