{
  "type": "Feature",
  "properties": {
    "iso:country":"US",
    "sg:address":"525 Canyon Gap Rd",
    "sg:city":"Wimberley",
    "sg:classifiers":[
        {
            "category":"Education",
            "subcategory":"Special Training",
            "type":"Public Place"
        }
    ],
    "sg:phone":"+1 512 392 4942",
    "sg:postcode":"78676",
    "sg:province":"TX",
    "wof:name":"Lynn F Raska Maccc",
    "wof:placetype":"venue"
},
  "geometry": {"coordinates":[-98.06546299999999,29.950709],"type":"Point"}
}