{
  "type": "Feature",
  "properties": {
    "iso:country":"US",
    "sg:address":"9929 Westview",
    "sg:city":"Houston",
    "sg:classifiers":[
        {
            "category":"Retail",
            "subcategory":"Auto Repair",
            "type":"Services"
        }
    ],
    "sg:phone":"+1 713 468 1662",
    "sg:postcode":"77055",
    "sg:province":"TX",
    "wof:name":"Westview Automotive Repair",
    "wof:placetype":"venue"
},
  "geometry": {"coordinates":[-95.539519,29.790666],"type":"Point"}
}