{
  "type": "Feature",
  "properties": {
    "iso:country":"US",
    "sg:address":"2404 Drifting Leaf Dr",
    "sg:city":"Cedar Park",
    "sg:classifiers":[
        {
            "category":"Personal",
            "type":"Services"
        }
    ],
    "sg:phone":"+1 512 232 1592",
    "sg:postcode":"78613",
    "sg:province":"TX",
    "sg:tags":[
        "proposal",
        "grant"
    ],
    "wof:name":"Sierra  Rodrigo",
    "wof:placetype":"venue"
},
  "geometry": {"coordinates":[-97.849306,30.473309],"type":"Point"}
}