{
  "type": "Feature",
  "properties": {
    "iso:country":"US",
    "sg:address":"12141 Beamer Rd",
    "sg:city":"Houston",
    "sg:classifiers":[
        {
            "category":"Fast Food",
            "type":"Food & Drink"
        },
        {
            "category":"Restaurant",
            "type":"Food & Drink"
        },
        {
            "category":"Professional",
            "type":"Services"
        }
    ],
    "sg:phone":"+1 281 481 0563",
    "sg:postcode":"77089",
    "sg:province":"TX",
    "sg:tags":[
        "hamburger",
        "lunch",
        "mediterranean",
        "dog",
        "greek",
        "hot",
        "caterer",
        "brunch",
        "breakfast"
    ],
    "sg:website":"www.denosrestaurant.com/",
    "wof:name":"Deno's",
    "wof:placetype":"venue"
},
  "geometry": {"coordinates":[-95.220536,29.591386],"type":"Point"}
}