{
  "type": "Feature",
  "properties": {
    "iso:country":"US",
    "sg:address":"1229 E Pleasant Run Rd Suite 130",
    "sg:city":"Desoto",
    "sg:classifiers":[
        {
            "category":"Insurance",
            "subcategory":"Insurance Agent",
            "type":"Services"
        },
        {
            "category":"Insurance",
            "subcategory":"Hazard Insurance",
            "type":"Services"
        }
    ],
    "sg:phone":"+1 972 224 7182",
    "sg:postcode":"75115",
    "sg:province":"TX",
    "sg:tags":[
        "auto",
        "recreational",
        "motorcycle",
        "vehicle",
        "marine",
        "boat"
    ],
    "wof:name":"ROY WILLIS INSURANCE AGENCY",
    "wof:placetype":"venue"
},
  "geometry": {"coordinates":[-96.827108,32.604328],"type":"Point"}
}