{
  "type": "Feature",
  "properties": {
    "iso:country":"US",
    "sg:address":"684 Duke Rd",
    "sg:city":"San Antonio",
    "sg:classifiers":[
        {
            "category":"Wholesale",
            "subcategory":"Auto Parts",
            "type":"Manufacturing & Wholesale Goods"
        }
    ],
    "sg:phone":"+1 210 626 3765",
    "sg:postcode":"78264",
    "sg:province":"TX",
    "sg:tags":[
        "used"
    ],
    "wof:name":"Dukes Auto Salvage",
    "wof:placetype":"venue"
},
  "geometry": {"coordinates":[-98.512998,29.161685],"type":"Point"}
}