{
  "type": "Feature",
  "properties": {
    "iso:country":"US",
    "sg:address":"12207 Highway 6 Ste L",
    "sg:city":"Fresno",
    "sg:classifiers":[
        {
            "category":"Place Of Worship",
            "type":"Public Place"
        }
    ],
    "sg:phone":"+1 281 431 9929",
    "sg:postcode":"77545",
    "sg:province":"TX",
    "sg:tags":[
        "church"
    ],
    "wof:name":"Crossing Point Christian Church, Inc.",
    "wof:placetype":"venue"
},
  "geometry": {"coordinates":[-95.482146,29.518339],"type":"Point"}
}