{
  "type": "Feature",
  "properties": {
    "iso:country":"US",
    "sg:address":"331 W Main St",
    "sg:city":"Denison",
    "sg:classifiers":[
        {
            "category":"Banks & Credit Unions",
            "subcategory":"Bank",
            "type":"Services"
        }
    ],
    "sg:phone":"+1 903 465 7744",
    "sg:postcode":"75020",
    "sg:province":"TX",
    "wof:name":"Independent Bank",
    "wof:placetype":"venue"
},
  "geometry": {"coordinates":[-96.53953799999999,33.755517],"type":"Point"}
}