{
  "type": "Feature",
  "properties": {
    "iso:country":"US",
    "sg:address":"601 Mary Lake Dr",
    "sg:city":"Bryan",
    "sg:classifiers":[
        {
            "category":"Social Services",
            "type":"Services"
        }
    ],
    "sg:phone":"+1 979 260 7805",
    "sg:postcode":"77801",
    "sg:province":"TX",
    "wof:name":"Neuropsychiatric Clinic",
    "wof:placetype":"venue"
},
  "geometry": {"coordinates":[-96.34852600000001,30.639291],"type":"Point"}
}