{
  "type": "Feature",
  "properties": {
    "iso:country":"US",
    "sg:address":"7316 Cave Hollow Dr",
    "sg:city":"Austin",
    "sg:classifiers":[
        {
            "category":"Shopping",
            "subcategory":"Catalog Store",
            "type":"Retail Goods"
        }
    ],
    "sg:phone":"+1 512 255 4065",
    "sg:postcode":"78750",
    "sg:province":"TX",
    "sg:tags":[
        "merchandise",
        "general"
    ],
    "wof:name":"Utopian Living Inc",
    "wof:placetype":"venue"
},
  "geometry": {"coordinates":[-97.78950500000001,30.374809],"type":"Point"}
}