{
  "type": "Feature",
  "properties": {
    "iso:country":"US",
    "sg:address":"10303 S Gessner Dr",
    "sg:city":"Houston",
    "sg:classifiers":[
        {
            "category":"Food & Beverages",
            "subcategory":"Groceries & Convenience Stores",
            "type":"Retail Goods"
        }
    ],
    "sg:phone":"+1 713 271 3779",
    "sg:postcode":"77071",
    "sg:province":"TX",
    "wof:name":"Thrifty Food Service 2",
    "wof:placetype":"venue"
},
  "geometry": {"coordinates":[-95.527901,29.667299],"type":"Point"}
}