{
  "type": "Feature",
  "properties": {
    "iso:country":"US",
    "sg:address":"500 Carolina St",
    "sg:city":"San Antonio",
    "sg:classifiers":[
        {
            "category":"Retail",
            "subcategory":"Repair Shop",
            "type":"Services"
        }
    ],
    "sg:phone":"+1 210 736 1010",
    "sg:postcode":"78210",
    "sg:province":"TX",
    "sg:tags":[
        "refrigeration"
    ],
    "wof:name":"A1 Action Services Inc",
    "wof:placetype":"venue"
},
  "geometry": {"coordinates":[-98.477841,29.405466],"type":"Point"}
}