{
  "type": "Feature",
  "properties": {
    "iso:country":"US",
    "sg:address":"4268 Clark Rd",
    "sg:city":"Houston",
    "sg:classifiers":[
        {
            "category":"Manufacturing",
            "subcategory":"Building Materials",
            "type":"Manufacturing & Wholesale Goods"
        }
    ],
    "sg:phone":"+1 713 934 8320",
    "sg:postcode":"77040",
    "sg:province":"TX",
    "sg:tags":[
        "mfg"
    ],
    "wof:name":"Millinia Millworks",
    "wof:placetype":"venue"
},
  "geometry": {"coordinates":[-95.506243,29.836519],"type":"Point"}
}