{
  "type": "Feature",
  "properties": {
    "iso:country":"US",
    "sg:address":"482 Old San Antonio Rd",
    "sg:city":"Dale",
    "sg:classifiers":[
        {
            "category":"Shopping",
            "type":"Retail Goods"
        }
    ],
    "sg:phone":"+1 512 601 9010",
    "sg:postcode":"78616",
    "sg:province":"TX",
    "sg:tags":[
        "merchandise"
    ],
    "wof:name":"Texas Hardwood Pens",
    "wof:placetype":"venue"
},
  "geometry": {"coordinates":[-97.603252,30.02892],"type":"Point"}
}