{
  "type": "Feature",
  "properties": {
    "iso:country":"US",
    "sg:address":"8510 Concord Dr",
    "sg:city":"Rowlett",
    "sg:classifiers":[
        {
            "category":"Professional",
            "type":"Services"
        }
    ],
    "sg:phone":"+1 972 463 9558",
    "sg:postcode":"75089",
    "sg:province":"TX",
    "wof:name":"Kathy W Bucalos",
    "wof:placetype":"venue"
},
  "geometry": {"coordinates":[-96.519223,32.923432],"type":"Point"}
}