{
  "type": "Feature",
  "properties": {
    "iso:country":"US",
    "sg:address":"3404 S Main St",
    "sg:city":"Pearland",
    "sg:classifiers":[
        {
            "category":"Autos & Motor Vehicles",
            "subcategory":"Automobile Sales",
            "type":"Retail Goods"
        }
    ],
    "sg:phone":"+1 281 997 7707",
    "sg:postcode":"77581",
    "sg:province":"TX",
    "sg:tags":[
        "used"
    ],
    "wof:name":"Car Spot The Inc",
    "wof:placetype":"venue"
},
  "geometry": {"coordinates":[-95.27887200000001,29.549241],"type":"Point"}
}