{
  "type": "Feature",
  "properties": {
    "iso:country":"US",
    "sg:address":"129 Spring Grove Dr",
    "sg:city":"Waxahachie",
    "sg:classifiers":[
        {
            "category":"Manufacturing",
            "subcategory":"Buildings",
            "type":"Manufacturing & Wholesale Goods"
        }
    ],
    "sg:phone":"+1 972 923 2400",
    "sg:postcode":"75165",
    "sg:province":"TX",
    "sg:tags":[
        "home",
        "builder"
    ],
    "wof:name":"Texas Heritage Custom Homes Inc.",
    "wof:placetype":"venue"
},
  "geometry": {"coordinates":[-96.801867,32.421012],"type":"Point"}
}