{
  "type": "Feature",
  "properties": {
    "iso:country":"US",
    "sg:address":"6814 Gant Rd",
    "sg:city":"Houston",
    "sg:classifiers":[
        {
            "category":"Home & Garden",
            "subcategory":"Home Furnishings",
            "type":"Retail Goods"
        }
    ],
    "sg:phone":"+1 281 893 3825",
    "sg:postcode":"77066",
    "sg:province":"TX",
    "sg:tags":[
        "lighting",
        "fixture"
    ],
    "wof:name":"Harv's Electric",
    "wof:placetype":"venue"
},
  "geometry": {"coordinates":[-95.52148699999999,29.956722],"type":"Point"}
}