{
  "type": "Feature",
  "properties": {
    "iso:country":"US",
    "sg:address":"4602 Springhill Estates Dr",
    "sg:city":"Allen",
    "sg:classifiers":[
        {
            "category":"Building & Trades",
            "subcategory":"Construction",
            "type":"Services"
        }
    ],
    "sg:phone":"+1 972 467 3337",
    "sg:postcode":"75002",
    "sg:province":"TX",
    "sg:tags":[
        "house"
    ],
    "wof:name":"Eddie Summer Custom Homes LLC",
    "wof:placetype":"venue"
},
  "geometry": {"coordinates":[-96.6455,33.063968],"type":"Point"}
}