{
  "type": "Feature",
  "properties": {
    "iso:country":"US",
    "sg:address":"1008 Main St",
    "sg:city":"Junction",
    "sg:classifiers":[
        {
            "category":"Retail",
            "subcategory":"Auto Repair",
            "type":"Services"
        }
    ],
    "sg:phone":"+1 325 446 2042",
    "sg:postcode":"76849",
    "sg:province":"TX",
    "sg:tags":[
        "general"
    ],
    "wof:name":"Alexs Auto Service",
    "wof:placetype":"venue"
},
  "geometry": {"coordinates":[-99.771846,30.48937],"type":"Point"}
}