{
  "type": "Feature",
  "properties": {
    "iso:country":"US",
    "sg:address":"207 S Milam St",
    "sg:city":"Fredericksburg",
    "sg:classifiers":[
        {
            "category":"Food & Beverages",
            "subcategory":"Specialty",
            "type":"Retail Goods"
        }
    ],
    "sg:phone":"+1 830 238 4815",
    "sg:postcode":"78624",
    "sg:province":"TX",
    "wof:name":"K J Birck Enterprises Corp",
    "wof:placetype":"venue"
},
  "geometry": {"coordinates":[-98.878405,30.277598],"type":"Point"}
}