{
  "type": "Feature",
  "properties": {
    "iso:country":"US",
    "sg:address":"2103 Cullen Ave",
    "sg:city":"Austin",
    "sg:classifiers":[
        {
            "category":"Shopping",
            "type":"Retail Goods"
        }
    ],
    "sg:phone":"+1 512 452 0084",
    "sg:postcode":"78757",
    "sg:province":"TX",
    "sg:tags":[
        "merchandising"
    ],
    "wof:name":"Chaparral Studios",
    "wof:placetype":"venue"
},
  "geometry": {"coordinates":[-97.733925,30.345373],"type":"Point"}
}