{
  "type": "Feature",
  "properties": {
    "iso:country":"US",
    "sg:address":"17603 Pearland Sites Rd",
    "sg:city":"Pearland",
    "sg:classifiers":[
        {
            "category":"Food & Beverages",
            "subcategory":"Groceries & Convenience Stores",
            "type":"Retail Goods"
        }
    ],
    "sg:phone":"+1 281 489 0591",
    "sg:postcode":"77584",
    "sg:province":"TX",
    "sg:tags":[
        "grocer"
    ],
    "wof:name":"Gene's Country Store",
    "wof:placetype":"venue"
},
  "geometry": {"coordinates":[-95.288899,29.521021],"type":"Point"}
}