{
  "type": "Feature",
  "properties": {
    "iso:country":"US",
    "sg:address":"3423 S Peachtree Rd",
    "sg:city":"Mesquite",
    "sg:classifiers":[
        {
            "category":"Professional",
            "type":"Services"
        }
    ],
    "sg:phone":"+1 972 286 1346",
    "sg:postcode":"75180",
    "sg:province":"TX",
    "wof:name":"Azteca Document Service",
    "wof:placetype":"venue"
},
  "geometry": {"coordinates":[-96.631258,32.722895],"type":"Point"}
}