{
  "type": "Feature",
  "properties": {
    "iso:country":"US",
    "sg:address":"1201 N Arapahoe St",
    "sg:city":"Amarillo",
    "sg:classifiers":[
        {
            "category":"Retail",
            "subcategory":"Auto Repair",
            "type":"Services"
        }
    ],
    "sg:phone":"+1 806 372 9109",
    "sg:postcode":"79107",
    "sg:province":"TX",
    "sg:tags":[
        "repairing",
        "automobile"
    ],
    "wof:name":"Buchanan Repair & Machine",
    "wof:placetype":"venue"
},
  "geometry": {"coordinates":[-101.80709899999999,35.227216],"type":"Point"}
}