{
  "type": "Feature",
  "properties": {
    "iso:country":"US",
    "sg:address":"5515 South Loop E",
    "sg:city":"Houston",
    "sg:classifiers":[
        {
            "category":"Shopping",
            "subcategory":"Clothing, Apparel, & Fashions",
            "type":"Retail Goods"
        }
    ],
    "sg:phone":"+1 713 731 1334",
    "sg:postcode":"77033",
    "sg:province":"TX",
    "sg:tags":[
        "handbag"
    ],
    "wof:name":"Victoria's Style",
    "wof:placetype":"venue"
},
  "geometry": {"coordinates":[-95.336044,29.687521],"type":"Point"}
}