{
  "type": "Feature",
  "properties": {
    "iso:country":"US",
    "sg:address":"6901 Imperial Dr",
    "sg:city":"Waco",
    "sg:classifiers":[
        {
            "category":"Wholesale",
            "subcategory":"Machinery & Supplies",
            "type":"Manufacturing & Wholesale Goods"
        }
    ],
    "sg:phone":"+1 254 751 1415",
    "sg:postcode":"76712",
    "sg:province":"TX",
    "sg:tags":[
        "equipment",
        "industrial"
    ],
    "sg:website":"www.grainger.com",
    "wof:name":"Grainger Inc",
    "wof:placetype":"venue"
},
  "geometry": {"coordinates":[-97.193235,31.499019],"type":"Point"}
}