{
  "type": "Feature",
  "properties": {
    "iso:country":"US",
    "sg:address":"371 Co Rd 691",
    "sg:city":"Donie",
    "sg:classifiers":[
        {
            "category":"Professional",
            "type":"Services"
        }
    ],
    "sg:phone":"+1 254 359 4430",
    "sg:postcode":"75860",
    "sg:province":"TX",
    "sg:tags":[
        "establishment"
    ],
    "wof:name":"Wellhawk Inc",
    "wof:placetype":"venue"
},
  "geometry": {"coordinates":[-96.208491,31.545777],"type":"Point"}
}