{
  "type": "Feature",
  "properties": {
    "iso:country":"US",
    "sg:address":"99 Bitterwood Cir",
    "sg:city":"Spring",
    "sg:classifiers":[
        {
            "category":"Building & Trades",
            "subcategory":"Landscaping Services",
            "type":"Services"
        }
    ],
    "sg:phone":"+1 281 363 3608",
    "sg:postcode":"77381",
    "sg:province":"TX",
    "sg:tags":[
        "landscape"
    ],
    "wof:name":"V Mercado Designs",
    "wof:placetype":"venue"
},
  "geometry": {"coordinates":[-95.499995,30.148904],"type":"Point"}
}