{
  "type": "Feature",
  "properties": {
    "iso:country":"US",
    "sg:address":"9002 N Navarro St",
    "sg:city":"Victoria",
    "sg:classifiers":[
        {
            "category":"Personal",
            "subcategory":"Beauty Salon",
            "type":"Services"
        }
    ],
    "sg:phone":"+1 361 573 7771",
    "sg:postcode":"77904",
    "sg:province":"TX",
    "wof:name":"Smart Style Family Hair Salon",
    "wof:placetype":"venue"
},
  "geometry": {"coordinates":[-96.99706399999999,28.877373],"type":"Point"}
}