{
  "type": "Feature",
  "properties": {
    "iso:country":"US",
    "sg:address":"3925 Ridgeoak Way",
    "sg:city":"Dallas",
    "sg:classifiers":[
        {
            "category":"Building & Trades",
            "subcategory":"Construction",
            "type":"Services"
        }
    ],
    "sg:phone":"+1 972 243 6228",
    "sg:postcode":"75244",
    "sg:province":"TX",
    "sg:tags":[
        "painting",
        "contractor"
    ],
    "wof:name":"Perley Painting Co Inc",
    "wof:placetype":"venue"
},
  "geometry": {"coordinates":[-96.849086,32.922061],"type":"Point"}
}