{
  "type": "Feature",
  "properties": {
    "iso:country":"US",
    "sg:address":"5505 Almeda-Genoa Rd",
    "sg:city":"Houston",
    "sg:classifiers":[
        {
            "category":"Wholesale",
            "subcategory":"Metals & Minerals",
            "type":"Manufacturing & Wholesale Goods"
        }
    ],
    "sg:phone":"+1 713 991 6107",
    "sg:postcode":"77048",
    "sg:province":"TX",
    "sg:tags":[
        "pipe"
    ],
    "wof:name":"Brittex International Pipe",
    "wof:placetype":"venue"
},
  "geometry": {"coordinates":[-95.325238,29.621007],"type":"Point"}
}