{
  "type": "Feature",
  "properties": {
    "iso:country":"US",
    "sg:address":"15010 Park Creek Ct",
    "sg:city":"Houston",
    "sg:classifiers":[
        {
            "category":"Shopping",
            "subcategory":"Used Merchandise",
            "type":"Retail Goods"
        }
    ],
    "sg:phone":"+1 281 655 4662",
    "sg:postcode":"77070",
    "sg:province":"TX",
    "wof:name":"Main Street Mercantile",
    "wof:placetype":"venue"
},
  "geometry": {"coordinates":[-95.59679800000001,29.991878],"type":"Point"}
}