{
  "type": "Feature",
  "properties": {
    "iso:country":"US",
    "sg:address":"14110 Bluff Park Dr",
    "sg:city":"San Antonio",
    "sg:classifiers":[
        {
            "category":"Health Services",
            "subcategory":"Doctor",
            "type":"Services"
        }
    ],
    "sg:phone":"+1 210 403 3830",
    "sg:postcode":"78216",
    "sg:province":"TX",
    "sg:tags":[
        "medical"
    ],
    "wof:name":"Raul Vela",
    "wof:placetype":"venue"
},
  "geometry": {"coordinates":[-98.50061599999999,29.574253],"type":"Point"}
}