{
  "type": "Feature",
  "properties": {
    "iso:country":"US",
    "sg:address":"16920 Kuykendahl Rd",
    "sg:city":"Houston",
    "sg:classifiers":[
        {
            "category":"Autos & Motor Vehicles",
            "subcategory":"Auto Supplies",
            "type":"Retail Goods"
        }
    ],
    "sg:phone":"+1 281 866 0785",
    "sg:postcode":"77068",
    "sg:province":"TX",
    "sg:tags":[
        "automobile",
        "parts"
    ],
    "wof:name":"A Line Auto Parts",
    "wof:placetype":"venue"
},
  "geometry": {"coordinates":[-95.474429,30.022021],"type":"Point"}
}