{
  "type": "Feature",
  "properties": {
    "iso:country":"US",
    "sg:address":"2911 E Division St",
    "sg:city":"Arlington",
    "sg:classifiers":[
        {
            "category":"Shopping",
            "subcategory":"Bicycles & Sporting Goods",
            "type":"Retail Goods"
        }
    ],
    "sg:phone":"+1 817 649 7153",
    "sg:postcode":"76011",
    "sg:province":"TX",
    "wof:name":"Champs",
    "wof:placetype":"venue"
},
  "geometry": {"coordinates":[-97.057286,32.74189],"type":"Point"}
}