{
  "type": "Feature",
  "properties": {
    "iso:country":"US",
    "sg:address":"215 Meadow Lea Dr",
    "sg:city":"Houston",
    "sg:classifiers":[
        {
            "category":"Retail",
            "subcategory":"Auto Repair",
            "type":"Services"
        }
    ],
    "sg:phone":"+1 713 691 0611",
    "sg:postcode":"77022",
    "sg:province":"TX",
    "sg:tags":[
        "transmission"
    ],
    "wof:name":"Renes Transmission",
    "wof:placetype":"venue"
},
  "geometry": {"coordinates":[-95.37309999999999,29.835921],"type":"Point"}
}