{
  "type": "Feature",
  "properties": {
    "iso:country":"US",
    "sg:address":"7516 Wentwood Ct",
    "sg:city":"Fort Worth",
    "sg:classifiers":[
        {
            "category":"Professional",
            "subcategory":"Computer Services",
            "type":"Services"
        }
    ],
    "sg:phone":"+1 817 581 9896",
    "sg:postcode":"76180",
    "sg:province":"TX",
    "sg:tags":[
        "programing",
        "custom"
    ],
    "wof:name":"Pro Photo Copy",
    "wof:placetype":"venue"
},
  "geometry": {"coordinates":[-97.219227,32.875395],"type":"Point"}
}