{
  "type": "Feature",
  "properties": {
    "iso:country":"US",
    "sg:address":"1903 FM 718",
    "sg:city":"Aurora",
    "sg:classifiers":[
        {
            "category":"Manufacturing",
            "subcategory":"Metals",
            "type":"Manufacturing & Wholesale Goods"
        }
    ],
    "sg:phone":"+1 817 489 2264",
    "sg:postcode":"76052",
    "sg:province":"TX",
    "sg:tags":[
        "tube",
        "fabricating"
    ],
    "wof:name":"Tube Products Inc",
    "wof:placetype":"venue"
},
  "geometry": {"coordinates":[-97.401819,32.968811],"type":"Point"}
}