{
  "type": "Feature",
  "properties": {
    "iso:country":"US",
    "sg:address":"3209 Reagan Beth Ln",
    "sg:city":"Brenham",
    "sg:classifiers":[
        {
            "category":"Building & Trades",
            "subcategory":"Plumbing",
            "type":"Services"
        }
    ],
    "sg:phone":"+1 979 830 1581",
    "sg:postcode":"77833",
    "sg:province":"TX",
    "sg:tags":[
        "conditioning",
        "air",
        "system",
        "contractor"
    ],
    "wof:name":"Smittco AC & Heating",
    "wof:placetype":"venue"
},
  "geometry": {"coordinates":[-96.364418,30.221406],"type":"Point"}
}