{
  "type": "Feature",
  "properties": {
    "iso:country":"US",
    "sg:address":"3575 Far West Blvd",
    "sg:city":"Austin",
    "sg:phone":"+1 512 217 9556",
    "sg:postcode":"78731",
    "sg:province":"TX",
    "wof:name":"Best Picture Productions",
    "wof:placetype":"venue"
},
  "geometry": {"coordinates":[-97.75424700000001,30.353887],"type":"Point"}
}