{
  "type": "Feature",
  "properties": {
    "iso:country":"US",
    "sg:address":"1824 Ave M",
    "sg:city":"Rosenberg",
    "sg:classifiers":[
        {
            "category":"Food & Beverages",
            "subcategory":"Meat & Fish",
            "type":"Retail Goods"
        }
    ],
    "sg:phone":"+1 281 232 7902",
    "sg:postcode":"77471",
    "sg:province":"TX",
    "wof:name":"Kovasovic's Meat Market",
    "wof:placetype":"venue"
},
  "geometry": {"coordinates":[-95.808398,29.552652],"type":"Point"}
}