{
  "type": "Feature",
  "properties": {
    "iso:country":"US",
    "sg:address":"4023 Co Rd 421",
    "sg:city":"Waelder",
    "sg:classifiers":[
        {
            "category":"Farming",
            "subcategory":"Farm",
            "type":"Manufacturing & Wholesale Goods"
        }
    ],
    "sg:phone":"+1 830 540 4348",
    "sg:postcode":"78959",
    "sg:province":"TX",
    "sg:tags":[
        "crop",
        "general"
    ],
    "wof:name":"V Vaughan",
    "wof:placetype":"venue"
},
  "geometry": {"coordinates":[-97.33818599999999,29.61728],"type":"Point"}
}