{
  "type": "Feature",
  "properties": {
    "iso:country":"US",
    "sg:address":"2010 White Ln",
    "sg:city":"Haslet",
    "sg:classifiers":[
        {
            "category":"Shopping",
            "subcategory":"Gifts & Souvenirs",
            "type":"Retail Goods"
        }
    ],
    "sg:phone":"+1 817 439 3656",
    "sg:postcode":"76052",
    "sg:province":"TX",
    "wof:name":"Josies Quilt Design",
    "wof:placetype":"venue"
},
  "geometry": {"coordinates":[-97.344852,32.942822],"type":"Point"}
}