{
  "type": "Feature",
  "properties": {
    "iso:country":"US",
    "sg:address":"1322 State Hwy 16",
    "sg:city":"Graham",
    "sg:classifiers":[
        {
            "category":"Restaurant",
            "type":"Food & Drink"
        }
    ],
    "sg:phone":"+1 940 549 2200",
    "sg:postcode":"76450",
    "sg:province":"TX",
    "wof:name":"Chicken Express",
    "wof:placetype":"venue"
},
  "geometry": {"coordinates":[-98.57407600000001,33.121461],"type":"Point"}
}