{
  "type": "Feature",
  "properties": {
    "iso:country":"US",
    "sg:address":"1603 Idlewilde Dr",
    "sg:city":"Midland",
    "sg:classifiers":[
        {
            "category":"Education",
            "subcategory":"Dance Studio",
            "type":"Public Place"
        }
    ],
    "sg:phone":"+1 432 699 2190",
    "sg:postcode":"79703",
    "sg:province":"TX",
    "sg:tags":[
        "instruction",
        "dancing"
    ],
    "wof:name":"Absolute Dance",
    "wof:placetype":"venue"
},
  "geometry": {"coordinates":[-102.14813100000001,31.997683],"type":"Point"}
}