{
  "type": "Feature",
  "properties": {
    "iso:country":"US",
    "sg:address":"7017 Manor Dr",
    "sg:city":"Fort Worth",
    "sg:classifiers":[
        {
            "category":"Building & Trades",
            "subcategory":"Construction",
            "type":"Services"
        }
    ],
    "sg:phone":"+1 817 485 0501",
    "sg:postcode":"76180",
    "sg:province":"TX",
    "sg:tags":[
        "contractor"
    ],
    "wof:name":"Dilks & Foster Co",
    "wof:placetype":"venue"
},
  "geometry": {"coordinates":[-97.230484,32.826256],"type":"Point"}
}