{
  "type": "Feature",
  "properties": {
    "iso:country":"US",
    "sg:address":"4233 Mulberry Dr",
    "sg:city":"Belton",
    "sg:classifiers":[
        {
            "category":"Professional",
            "subcategory":"Business Services",
            "type":"Services"
        }
    ],
    "sg:phone":"+1 254 939 0644",
    "sg:postcode":"76513",
    "sg:province":"TX",
    "wof:name":"Leris Group",
    "wof:placetype":"venue"
},
  "geometry": {"coordinates":[-97.52297900000001,31.045674],"type":"Point"}
}