{
  "type": "Feature",
  "properties": {
    "iso:country":"US",
    "sg:address":"1809 Bay Shore Dr",
    "sg:city":"Rockport",
    "sg:classifiers":[
        {
            "category":"Real Estate",
            "subcategory":"Real Estate Agent",
            "type":"Services"
        }
    ],
    "sg:phone":"+1 361 729 2772",
    "sg:postcode":"78382",
    "sg:province":"TX",
    "wof:name":"Glenda Easley",
    "wof:placetype":"venue"
},
  "geometry": {"coordinates":[-97.02945099999999,28.04779],"type":"Point"}
}