{
  "type": "Feature",
  "properties": {
    "iso:country":"US",
    "sg:address":"1523 Azalea Bend",
    "sg:city":"Sugar Land",
    "sg:classifiers":[
        {
            "category":"Professional",
            "subcategory":"Management & Consulting",
            "type":"Services"
        }
    ],
    "sg:phone":"+1 281 937 1237",
    "sg:postcode":"77479",
    "sg:province":"TX",
    "wof:name":"3rd Management Inc",
    "wof:placetype":"venue"
},
  "geometry": {"coordinates":[-95.670298,29.547298],"type":"Point"}
}