{
  "type": "Feature",
  "properties": {
    "iso:country":"US",
    "sg:address":"4223 Bayliss St",
    "sg:city":"San Antonio",
    "sg:classifiers":[
        {
            "category":"Retail",
            "subcategory":"Repair Shop",
            "type":"Services"
        }
    ],
    "sg:phone":"+1 210 653 7040",
    "sg:postcode":"78233",
    "sg:province":"TX",
    "sg:tags":[
        "electrical"
    ],
    "wof:name":"Fan Man Moe",
    "wof:placetype":"venue"
},
  "geometry": {"coordinates":[-98.40518899999999,29.54065],"type":"Point"}
}