{
  "type": "Feature",
  "properties": {
    "iso:country":"US",
    "sg:address":"3930 S State Hwy 91",
    "sg:city":"Denison",
    "sg:classifiers":[
        {
            "category":"Wholesale",
            "subcategory":"Machinery & Supplies",
            "type":"Manufacturing & Wholesale Goods"
        }
    ],
    "sg:phone":"+1 903 465 3369",
    "sg:postcode":"75020",
    "sg:province":"TX",
    "sg:tags":[
        "equipment",
        "welding"
    ],
    "sg:website":"www.denisonoxygensupply.com",
    "wof:name":"Denison Oxygen Supply",
    "wof:placetype":"venue"
},
  "geometry": {"coordinates":[-96.563436,33.713623],"type":"Point"}
}