{
  "type": "Feature",
  "properties": {
    "iso:country":"US",
    "sg:address":"3568 Half Moon Dr",
    "sg:city":"Fort Worth",
    "sg:classifiers":[
        {
            "category":"Building & Trades",
            "subcategory":"Construction",
            "type":"Services"
        }
    ],
    "sg:phone":"+1 817 838 3143",
    "sg:postcode":"76111",
    "sg:province":"TX",
    "sg:tags":[
        "contractor"
    ],
    "wof:name":"Brandt Tile Service",
    "wof:placetype":"venue"
},
  "geometry": {"coordinates":[-97.295546,32.808682],"type":"Point"}
}