{
  "type": "Feature",
  "properties": {
    "iso:country":"US",
    "sg:address":"535 Colgate Dr",
    "sg:city":"Lancaster",
    "sg:classifiers":[
        {
            "category":"Retail",
            "subcategory":"Repair Shop",
            "type":"Services"
        }
    ],
    "sg:phone":"+1 972 227 2655",
    "sg:postcode":"75134",
    "sg:province":"TX",
    "sg:tags":[
        "electrical"
    ],
    "wof:name":"Practical Electronics Co",
    "wof:placetype":"venue"
},
  "geometry": {"coordinates":[-96.767354,32.612564],"type":"Point"}
}