{
  "type": "Feature",
  "properties": {
    "iso:country":"US",
    "sg:address":"3315 Ave H",
    "sg:city":"Nederland",
    "sg:classifiers":[
        {
            "category":"Real Estate",
            "subcategory":"Real Estate Operator",
            "type":"Services"
        }
    ],
    "sg:phone":"+1 409 722 7404",
    "sg:postcode":"77627",
    "sg:province":"TX",
    "sg:tags":[
        "building",
        "apartment"
    ],
    "wof:name":"LA Place Apartments",
    "wof:placetype":"venue"
},
  "geometry": {"coordinates":[-93.994394,29.95763],"type":"Point"}
}