{
  "type": "Feature",
  "properties": {
    "iso:country":"US",
    "sg:address":"1324 Oakwood Ct",
    "sg:city":"Flower Mound",
    "sg:classifiers":[
        {
            "category":"Professional",
            "subcategory":"Management & Consulting",
            "type":"Services"
        }
    ],
    "sg:phone":"+1 972 874 7887",
    "sg:postcode":"75028",
    "sg:province":"TX",
    "sg:tags":[
        "business"
    ],
    "wof:name":"Oakwood Alliance",
    "wof:placetype":"venue"
},
  "geometry": {"coordinates":[-97.04834,33.026384],"type":"Point"}
}