{
  "type": "Feature",
  "properties": {
    "iso:country":"US",
    "sg:address":"1541 E Pine St",
    "sg:city":"Jacksonville",
    "sg:classifiers":[
        {
            "category":"Professional",
            "type":"Services"
        }
    ],
    "sg:phone":"+1 903 586 5966",
    "sg:postcode":"75766",
    "sg:province":"TX",
    "sg:tags":[
        "establishment"
    ],
    "wof:name":"Cherokee County Juvenile Prbtn",
    "wof:placetype":"venue"
},
  "geometry": {"coordinates":[-95.256325,31.977621],"type":"Point"}
}