{
  "type": "Feature",
  "properties": {
    "iso:country":"US",
    "sg:address":"702 E Polk St",
    "sg:city":"Burnet",
    "sg:classifiers":[
        {
            "category":"Food & Beverages",
            "subcategory":"Groceries & Convenience Stores",
            "type":"Retail Goods"
        }
    ],
    "sg:phone":"+1 512 756 2936",
    "sg:postcode":"78611",
    "sg:province":"TX",
    "wof:name":"Miller's Food & Grocery",
    "wof:placetype":"venue"
},
  "geometry": {"coordinates":[-98.218276,30.760025],"type":"Point"}
}