{
  "type": "Feature",
  "properties": {
    "iso:country":"US",
    "sg:address":"4708 Byron Ave",
    "sg:city":"Dallas",
    "sg:classifiers":[
        {
            "category":"Travel",
            "subcategory":"Hotels & Motels",
            "type":"Entertainment"
        }
    ],
    "sg:phone":"+1 214 719 5153",
    "sg:postcode":"75205",
    "sg:province":"TX",
    "sg:tags":[
        "operation"
    ],
    "wof:name":"Winsor Ridge II Limited",
    "wof:placetype":"venue"
},
  "geometry": {"coordinates":[-96.79160299999999,32.827265],"type":"Point"}
}