{
  "type": "Feature",
  "properties": {
    "iso:country":"US",
    "sg:address":"272 Spanos Ranch Rd",
    "sg:city":"Crawford",
    "sg:classifiers":[
        {
            "category":"Professional",
            "type":"Services"
        }
    ],
    "sg:phone":"+1 254 486 0099",
    "sg:postcode":"76638",
    "sg:province":"TX",
    "sg:tags":[
        "establishment"
    ],
    "wof:name":"Spanos Cabin",
    "wof:placetype":"venue"
},
  "geometry": {"coordinates":[-97.504199,31.515623],"type":"Point"}
}