{
  "type": "Feature",
  "properties": {
    "iso:country":"US",
    "sg:address":"7327 Alameda Ave",
    "sg:city":"El Paso",
    "sg:classifiers":[
        {
            "category":"Restaurant",
            "type":"Food & Drink"
        }
    ],
    "sg:phone":"+1 915 772 6764",
    "sg:postcode":"79915",
    "sg:province":"TX",
    "sg:tags":[
        "eating"
    ],
    "wof:name":"Martha's Mexican Restaurant",
    "wof:placetype":"venue"
},
  "geometry": {"coordinates":[-106.38203,31.745573],"type":"Point"}
}