{
  "type": "Feature",
  "properties": {
    "iso:country":"US",
    "sg:address":"3000 Parkhaven Dr",
    "sg:city":"Flower Mound",
    "sg:classifiers":[
        {
            "category":"Professional",
            "subcategory":"Computer Services",
            "type":"Services"
        }
    ],
    "sg:phone":"+1 972 724 4421",
    "sg:postcode":"75022",
    "sg:province":"TX",
    "sg:tags":[
        "datum"
    ],
    "wof:name":"Rapboardcom LLC",
    "wof:placetype":"venue"
},
  "geometry": {"coordinates":[-97.080258,33.024859],"type":"Point"}
}