{
  "type": "Feature",
  "properties": {
    "iso:country":"US",
    "sg:address":"303 N Main St",
    "sg:city":"Keller",
    "sg:classifiers":[
        {
            "category":"Education",
            "subcategory":"Special Training",
            "type":"Public Place"
        }
    ],
    "sg:phone":"+1 940 648 2992",
    "sg:postcode":"76248",
    "sg:province":"TX",
    "wof:name":"4 J Defensive Driving",
    "wof:placetype":"venue"
},
  "geometry": {"coordinates":[-97.25351499999999,32.937504],"type":"Point"}
}