{
  "type": "Feature",
  "properties": {
    "iso:country":"US",
    "sg:address":"2814 Marlborough Dr",
    "sg:city":"San Antonio",
    "sg:classifiers":[
        {
            "category":"Health Services",
            "subcategory":"Doctor",
            "type":"Services"
        }
    ],
    "sg:phone":"+1 210 341 7253",
    "sg:postcode":"78230",
    "sg:province":"TX",
    "sg:tags":[
        "dentist"
    ],
    "wof:name":"Ronald R Morin DDS",
    "wof:placetype":"venue"
},
  "geometry": {"coordinates":[-98.541473,29.520168],"type":"Point"}
}