{
  "type": "Feature",
  "properties": {
    "iso:country":"US",
    "sg:address":"11802 Mesa Cir",
    "sg:city":"Corpus Christi",
    "sg:classifiers":[
        {
            "category":"Professional",
            "type":"Services"
        }
    ],
    "sg:phone":"+1 361 242 1011",
    "sg:postcode":"78410",
    "sg:province":"TX",
    "wof:name":"James Eley",
    "wof:placetype":"venue"
},
  "geometry": {"coordinates":[-97.598574,27.850845],"type":"Point"}
}