{
  "type": "Feature",
  "properties": {
    "iso:country":"US",
    "sg:address":"16306 Cumberland Trl",
    "sg:city":"Cypress",
    "sg:classifiers":[
        {
            "category":"Shopping",
            "subcategory":"Baby Store",
            "type":"Retail Goods"
        }
    ],
    "sg:phone":"+1 281 256 3949",
    "sg:postcode":"77433",
    "sg:province":"TX",
    "sg:tags":[
        "children's",
        "infant",
        "wear"
    ],
    "wof:name":"Sugarbean Baby & Me Accessorie",
    "wof:placetype":"venue"
},
  "geometry": {"coordinates":[-95.737261,30.01163],"type":"Point"}
}