{
  "type": "Feature",
  "properties": {
    "iso:country":"US",
    "sg:address":"3802 Dabney St",
    "sg:city":"Houston",
    "sg:classifiers":[
        {
            "category":"Professional",
            "type":"Services"
        }
    ],
    "sg:phone":"+1 713 671 9467",
    "sg:postcode":"77026",
    "sg:province":"TX",
    "wof:name":"Francks Place",
    "wof:placetype":"venue"
},
  "geometry": {"coordinates":[-95.310395,29.797031],"type":"Point"}
}