{
  "type": "Feature",
  "properties": {
    "iso:country":"US",
    "sg:address":"1810 Pilgrims Point Dr",
    "sg:city":"Friendswood",
    "sg:classifiers":[
        {
            "category":"Professional",
            "subcategory":"Computer Services",
            "type":"Services"
        }
    ],
    "sg:phone":"+1 281 996 0768",
    "sg:postcode":"77546",
    "sg:province":"TX",
    "sg:tags":[
        "datum"
    ],
    "wof:name":"Cyber One System",
    "wof:placetype":"venue"
},
  "geometry": {"coordinates":[-95.17110599999999,29.540748],"type":"Point"}
}