{
  "type": "Feature",
  "properties": {
    "iso:country":"US",
    "sg:address":"4011 Convict Hill Rd",
    "sg:city":"Austin",
    "sg:classifiers":[
        {
            "category":"Building & Trades",
            "subcategory":"Construction",
            "type":"Services"
        }
    ],
    "sg:phone":"+1 512 358 7100",
    "sg:postcode":"78749",
    "sg:province":"TX",
    "sg:tags":[
        "repairing",
        "remodeling",
        "contractor"
    ],
    "wof:name":"D M Remodeling",
    "wof:placetype":"venue"
},
  "geometry": {"coordinates":[-97.842484,30.215099],"type":"Point"}
}