{
  "type": "Feature",
  "properties": {
    "iso:country":"US",
    "sg:address":"809 Spring Lake Cir",
    "sg:city":"Garland",
    "sg:classifiers":[
        {
            "category":"Building & Trades",
            "subcategory":"Plumbing",
            "type":"Services"
        }
    ],
    "sg:phone":"+1 972 613 0214",
    "sg:postcode":"75043",
    "sg:province":"TX",
    "sg:tags":[
        "m",
        "contractor"
    ],
    "wof:name":"Sprinkler Specialists",
    "wof:placetype":"venue"
},
  "geometry": {"coordinates":[-96.63526899999999,32.85135],"type":"Point"}
}