{
  "type": "Feature",
  "properties": {
    "iso:country":"US",
    "sg:address":"8600 Crest Ridge Cir",
    "sg:city":"Austin",
    "sg:classifiers":[
        {
            "category":"Building & Trades",
            "subcategory":"Construction",
            "type":"Services"
        }
    ],
    "sg:phone":"+1 512 258 3992",
    "sg:postcode":"78750",
    "sg:province":"TX",
    "sg:tags":[
        "consultant",
        "management"
    ],
    "wof:name":"Buchanan Consulting & Assoc Inc",
    "wof:placetype":"venue"
},
  "geometry": {"coordinates":[-97.781914,30.436911],"type":"Point"}
}