{
  "type": "Feature",
  "properties": {
    "iso:country":"US",
    "sg:address":"4102 Caroline St",
    "sg:city":"Houston",
    "sg:classifiers":[
        {
            "category":"Professional",
            "type":"Services"
        }
    ],
    "sg:phone":"+1 713 520 7087",
    "sg:postcode":"77004",
    "sg:province":"TX",
    "sg:tags":[
        "establishment"
    ],
    "wof:name":"American Planning Institute",
    "wof:placetype":"venue"
},
  "geometry": {"coordinates":[-95.37953899999999,29.733794],"type":"Point"}
}