{
  "type": "Feature",
  "properties": {
    "iso:country":"US",
    "sg:address":"104 Bishop St",
    "sg:city":"Winters",
    "sg:classifiers":[
        {
            "category":"Social Services",
            "subcategory":"Child Care",
            "type":"Services"
        }
    ],
    "sg:phone":"+1 325 754 4748",
    "sg:postcode":"79567",
    "sg:province":"TX",
    "sg:tags":[
        "day"
    ],
    "wof:name":"Smiths Family Day Care Center",
    "wof:placetype":"venue"
},
  "geometry": {"coordinates":[-99.96177299999999,31.948096],"type":"Point"}
}