{
  "type": "Feature",
  "properties": {
    "iso:country":"US",
    "sg:address":"1330 Sequoia Ct",
    "sg:city":"De Soto",
    "sg:classifiers":[
        {
            "category":"Freight",
            "type":"Transportation"
        }
    ],
    "sg:phone":"+1 972 670 3168",
    "sg:postcode":"75115",
    "sg:province":"TX",
    "sg:tags":[
        "operator",
        "local",
        "trucking"
    ],
    "wof:name":"M&C Trucking",
    "wof:placetype":"venue"
},
  "geometry": {"coordinates":[-96.838589,32.614183],"type":"Point"}
}