{
  "type": "Feature",
  "properties": {
    "iso:country":"US",
    "sg:address":"14701 Saint Marys Ln",
    "sg:city":"Houston",
    "sg:classifiers":[
        {
            "category":"Building & Trades",
            "subcategory":"Construction",
            "type":"Services"
        }
    ],
    "sg:phone":"+1 281 870 5744",
    "sg:postcode":"77079",
    "sg:province":"TX",
    "sg:tags":[
        "contractor"
    ],
    "sg:website":"http://www.floatec.com",
    "wof:name":"Floatec",
    "wof:placetype":"venue"
},
  "geometry": {"coordinates":[-95.606537,29.78216],"type":"Point"}
}