{
  "type": "Feature",
  "properties": {
    "iso:country":"US",
    "sg:address":"811 W Butler St",
    "sg:city":"Gilmer",
    "sg:classifiers":[
        {
            "category":"Place Of Worship",
            "subcategory":"Church",
            "type":"Public Place"
        },
        {
            "category":"Place Of Worship",
            "type":"Public Place"
        }
    ],
    "sg:phone":"+1 903 680 2290",
    "sg:postcode":"75644",
    "sg:province":"TX",
    "sg:tags":[
        "churches-baptist-general",
        "churches-baptist"
    ],
    "sg:website":"http://www.gracebaptist.org",
    "wof:name":"White's Seamless Rain Gutters",
    "wof:placetype":"venue"
},
  "geometry": {"coordinates":[-94.95243499999999,32.726719],"type":"Point"}
}