{
  "type": "Feature",
  "properties": {
    "iso:country":"US",
    "sg:address":"182 S Willis St",
    "sg:city":"Abilene",
    "sg:classifiers":[
        {
            "category":"Wholesale",
            "subcategory":"Medical Equipment & Supplies",
            "type":"Manufacturing & Wholesale Goods"
        }
    ],
    "sg:phone":"+1 325 672 7030",
    "sg:postcode":"79605",
    "sg:province":"TX",
    "sg:tags":[
        "physician",
        "surgeon"
    ],
    "wof:name":"Lincare",
    "wof:placetype":"venue"
},
  "geometry": {"coordinates":[-99.76405699999999,32.450699],"type":"Point"}
}