{
  "type": "Feature",
  "properties": {
    "iso:country":"US",
    "sg:address":"103 N Goliad St",
    "sg:city":"Rockwall",
    "sg:classifiers":[
        {
            "category":"Insurance",
            "subcategory":"Hazard Insurance",
            "type":"Services"
        }
    ],
    "sg:phone":"+1 972 772 3383",
    "sg:postcode":"75087",
    "sg:province":"TX",
    "sg:tags":[
        "bond"
    ],
    "wof:name":"Best Price Bail Bonds",
    "wof:placetype":"venue"
},
  "geometry": {"coordinates":[-96.46040000000001,32.93175],"type":"Point"}
}