{
  "type": "Feature",
  "properties": {
    "iso:country":"US",
    "sg:address":"6393 Alameda Ave",
    "sg:city":"El Paso",
    "sg:classifiers":[
        {
            "category":"Autos & Motor Vehicles",
            "subcategory":"Automobile Sales",
            "type":"Retail Goods"
        }
    ],
    "sg:phone":"+1 915 778 9532",
    "sg:postcode":"79905",
    "sg:province":"TX",
    "sg:tags":[
        "used"
    ],
    "wof:name":"Texas Motor Co",
    "wof:placetype":"venue"
},
  "geometry": {"coordinates":[-106.409069,31.765045],"type":"Point"}
}