{
  "type": "Feature",
  "properties": {
    "iso:country":"US",
    "sg:address":"4700 W Guadalupe St",
    "sg:city":"Austin",
    "sg:classifiers":[
        {
            "category":"Restaurant",
            "type":"Food & Drink"
        }
    ],
    "sg:phone":"+1 512 323 9494",
    "sg:postcode":"78751",
    "sg:province":"TX",
    "sg:tags":[
        "traditional",
        "new",
        "american"
    ],
    "sg:website":"www.galaxycafeaustin.com",
    "wof:name":"Galaxy Cafe",
    "wof:placetype":"venue"
},
  "geometry": {"coordinates":[-97.732394,30.31509],"type":"Point"}
}