{
  "type": "Feature",
  "properties": {
    "iso:country":"US",
    "sg:address":"1109 Palomino Ln",
    "sg:city":"San Marcos",
    "sg:classifiers":[
        {
            "category":"Organizations",
            "subcategory":"Membership Organization",
            "type":"Services"
        }
    ],
    "sg:phone":"+1 512 396 5173",
    "sg:postcode":"78666",
    "sg:province":"TX",
    "wof:name":"Country Estates Homeowner Assn",
    "wof:placetype":"venue"
},
  "geometry": {"coordinates":[-97.97017200000001,29.913861],"type":"Point"}
}