{
  "type": "Feature",
  "properties": {
    "iso:country":"US",
    "sg:address":"2850 Allie Payne Rd",
    "sg:city":"Orange",
    "sg:classifiers":[
        {
            "category":"Building & Trades",
            "subcategory":"Construction",
            "type":"Services"
        }
    ],
    "sg:phone":"+1 409 886 0002",
    "sg:postcode":"77632",
    "sg:province":"TX",
    "sg:tags":[
        "home",
        "builder"
    ],
    "wof:name":"Southwest Homes",
    "wof:placetype":"venue"
},
  "geometry": {"coordinates":[-93.768305,30.141622],"type":"Point"}
}