{
  "type": "Feature",
  "properties": {
    "iso:country":"US",
    "sg:address":"1130 Basse Rd",
    "sg:city":"San Antonio",
    "sg:classifiers":[
        {
            "category":"Retail",
            "subcategory":"Repair Shop",
            "type":"Services"
        },
        {
            "category":"Building & Trades",
            "subcategory":"Plumbing",
            "type":"Services"
        }
    ],
    "sg:phone":"+1 210 734 7444",
    "sg:postcode":"78212",
    "sg:province":"TX",
    "sg:tags":[
        "plumbing",
        "water",
        "contractor",
        "heater"
    ],
    "wof:name":"All City Plumbing Repairs",
    "wof:placetype":"venue"
},
  "geometry": {"coordinates":[-98.502251,29.488082],"type":"Point"}
}