{
  "type": "Feature",
  "properties": {
    "iso:country":"US",
    "sg:address":"140 Regal Row",
    "sg:city":"Dallas",
    "sg:classifiers":[
        {
            "category":"Wholesale",
            "subcategory":"Electrical",
            "type":"Manufacturing & Wholesale Goods"
        }
    ],
    "sg:phone":"+1 214 630 9000",
    "sg:postcode":"75247",
    "sg:province":"TX",
    "sg:tags":[
        "equipment",
        "electric",
        "supply"
    ],
    "sg:website":"www.reynoldsonline.com",
    "wof:name":"Reynolds Co",
    "wof:placetype":"venue"
},
  "geometry": {"coordinates":[-96.900012,32.809962],"type":"Point"}
}