{
  "type": "Feature",
  "properties": {
    "iso:country":"US",
    "sg:address":"11300 Forest Sq",
    "sg:city":"Live Oak",
    "sg:classifiers":[
        {
            "category":"Building & Trades",
            "subcategory":"Construction",
            "type":"Services"
        }
    ],
    "sg:phone":"+1 210 657 6988",
    "sg:postcode":"78233",
    "sg:province":"TX",
    "sg:tags":[
        "tile",
        "dealer"
    ],
    "wof:name":"North American Tile & Stone",
    "wof:placetype":"venue"
},
  "geometry": {"coordinates":[-98.34297100000001,29.542881],"type":"Point"}
}