{
  "type": "Feature",
  "properties": {
    "iso:country":"US",
    "sg:address":"912 Walters Dr",
    "sg:city":"Cedar Hill",
    "sg:classifiers":[
        {
            "category":"Shopping",
            "subcategory":"Florist",
            "type":"Retail Goods"
        }
    ],
    "sg:phone":"+1 972 293 3740",
    "sg:postcode":"75104",
    "sg:province":"TX",
    "wof:name":"A Special Touch Stephanie",
    "wof:placetype":"venue"
},
  "geometry": {"coordinates":[-96.927679,32.585898],"type":"Point"}
}