{
  "type": "Feature",
  "properties": {
    "iso:country":"US",
    "sg:address":"5306 Wildwood Creek Way",
    "sg:city":"Spring",
    "sg:classifiers":[
        {
            "category":"Autos & Motor Vehicles",
            "subcategory":"Automobile Sales",
            "type":"Retail Goods"
        }
    ],
    "sg:phone":"+1 281 379 1500",
    "sg:postcode":"77379",
    "sg:province":"TX",
    "sg:tags":[
        "car",
        "used"
    ],
    "wof:name":"Cr Car Co",
    "wof:placetype":"venue"
},
  "geometry": {"coordinates":[-95.501609,30.045025],"type":"Point"}
}