{
  "type": "Feature",
  "properties": {
    "iso:country":"US",
    "sg:address":"3314 Garden Brook Dr",
    "sg:city":"Farmers Branch",
    "sg:classifiers":[
        {
            "category":"Insurance",
            "subcategory":"Hazard Insurance",
            "type":"Services"
        }
    ],
    "sg:phone":"+1 972 488 9408",
    "sg:postcode":"75234",
    "sg:province":"TX",
    "sg:tags":[
        "casualty"
    ],
    "wof:name":"Willtech Engineering",
    "wof:placetype":"venue"
},
  "geometry": {"coordinates":[-96.867813,32.950236],"type":"Point"}
}