{
  "type": "Feature",
  "properties": {
    "iso:country":"US",
    "sg:address":"2508 Hanover Ct",
    "sg:city":"Rowlett",
    "sg:classifiers":[
        {
            "category":"Arts & Performance",
            "subcategory":"Theater",
            "type":"Entertainment"
        }
    ],
    "sg:phone":"+1 972 588 8440",
    "sg:postcode":"75088",
    "sg:province":"TX",
    "sg:tags":[
        "live",
        "music"
    ],
    "wof:name":"Sound Advice DJ",
    "wof:placetype":"venue"
},
  "geometry": {"coordinates":[-96.577389,32.891077],"type":"Point"}
}