{
  "type": "Feature",
  "properties": {
    "iso:country":"US",
    "sg:address":"7502 Lake Superior Dr",
    "sg:city":"Corpus Christi",
    "sg:classifiers":[
        {
            "category":"Education",
            "subcategory":"Special Training",
            "type":"Public Place"
        }
    ],
    "sg:phone":"+1 361 852 0814",
    "sg:postcode":"78413",
    "sg:province":"TX",
    "wof:name":"CPR First",
    "wof:placetype":"venue"
},
  "geometry": {"coordinates":[-97.415992,27.677161],"type":"Point"}
}