{
  "type": "Feature",
  "properties": {
    "iso:country":"US",
    "sg:address":"4311 Shilling Way",
    "sg:city":"Dallas",
    "sg:classifiers":[
        {
            "category":"Professional",
            "subcategory":"Business Services",
            "type":"Services"
        }
    ],
    "sg:phone":"+1 214 467 2893",
    "sg:postcode":"75237",
    "sg:province":"TX",
    "sg:tags":[
        "convention",
        "meeting",
        "facility"
    ],
    "wof:name":"Dallas Show Svc",
    "wof:placetype":"venue"
},
  "geometry": {"coordinates":[-96.88850600000001,32.689661],"type":"Point"}
}