{
  "type": "Feature",
  "properties": {
    "iso:country":"US",
    "sg:address":"604 Orchard Street",
    "sg:city":"Cedar Park",
    "sg:classifiers":[
        {
            "category":"Building & Trades",
            "subcategory":"Construction",
            "type":"Services"
        }
    ],
    "sg:phone":"+1 512 260 8008",
    "sg:postcode":"78613",
    "sg:province":"TX",
    "sg:tags":[
        "handyman"
    ],
    "sg:website":"www.handymaams.com",
    "wof:name":"Handy Ma'ams",
    "wof:placetype":"venue"
},
  "geometry": {"coordinates":[-97.841849,30.532193],"type":"Point"}
}