{
  "type": "Feature",
  "properties": {
    "iso:country":"US",
    "sg:address":"200 Brisbane St",
    "sg:city":"Houston",
    "sg:classifiers":[
        {
            "category":"Transit Center",
            "subcategory":"Freight",
            "type":"Transportation"
        },
        {
            "category":"Retail",
            "subcategory":"Pet Boarding",
            "type":"Services"
        }
    ],
    "sg:phone":"+1 713 674 3544",
    "sg:postcode":"77061",
    "sg:province":"TX",
    "sg:tags":[
        "packing",
        "crating",
        "container"
    ],
    "wof:name":"Maritime Services Inc.",
    "wof:placetype":"venue"
},
  "geometry": {"coordinates":[-95.288979,29.63958],"type":"Point"}
}