{
  "type": "Feature",
  "properties": {
    "iso:country":"US",
    "sg:address":"2700 Pecan St W",
    "sg:city":"Pflugerville",
    "sg:classifiers":[
        {
            "category":"Building & Trades",
            "subcategory":"Cleaning & Sanitation",
            "type":"Services"
        }
    ],
    "sg:phone":"+1 512 251 5522",
    "sg:postcode":"78660",
    "sg:province":"TX",
    "sg:tags":[
        "maintenance"
    ],
    "wof:name":"Merry Maids",
    "wof:placetype":"venue"
},
  "geometry": {"coordinates":[-97.64698,30.44626],"type":"Point"}
}