{
  "type": "Feature",
  "properties": {
    "iso:country":"US",
    "sg:address":"1900 W 11th St",
    "sg:city":"Plainview",
    "sg:classifiers":[
        {
            "category":"Building & Trades",
            "subcategory":"Pest Control",
            "type":"Services"
        }
    ],
    "sg:phone":"+1 806 296 2830",
    "sg:postcode":"79072",
    "sg:province":"TX",
    "wof:name":"Omega Pest Management Co",
    "wof:placetype":"venue"
},
  "geometry": {"coordinates":[-101.72700399999999,34.191732],"type":"Point"}
}