{
  "type": "Feature",
  "properties": {
    "iso:country":"US",
    "sg:address":"116 Magendie St",
    "sg:city":"San Antonio",
    "sg:classifiers":[
        {
            "category":"Building & Trades",
            "subcategory":"Cleaning & Sanitation",
            "type":"Services"
        }
    ],
    "sg:phone":"+1 210 533 4153",
    "sg:postcode":"78210",
    "sg:province":"TX",
    "sg:tags":[
        "maintenance"
    ],
    "wof:name":"Blackwells Window Cleani",
    "wof:placetype":"venue"
},
  "geometry": {"coordinates":[-98.45137099999999,29.410768],"type":"Point"}
}