{
  "type": "Feature",
  "properties": {
    "iso:country":"US",
    "sg:address":"1560 Pendale Rd",
    "sg:city":"El Paso",
    "sg:classifiers":[
        {
            "category":"Restaurant",
            "type":"Food & Drink"
        }
    ],
    "sg:phone":"+1 915 594 9794",
    "sg:postcode":"79936",
    "sg:province":"TX",
    "wof:name":"LA Parilla",
    "wof:placetype":"venue"
},
  "geometry": {"coordinates":[-106.304267,31.742592],"type":"Point"}
}