{
  "type": "Feature",
  "properties": {
    "iso:country":"US",
    "sg:address":"4601 Cobbs Dr",
    "sg:city":"Waco",
    "sg:classifiers":[
        {
            "category":"Education",
            "subcategory":"School",
            "type":"Public Place"
        }
    ],
    "sg:phone":"+1 254 772 1910",
    "sg:postcode":"76710",
    "sg:province":"TX",
    "sg:tags":[
        "middle"
    ],
    "sg:website":"http://www.wacoisd.org/school.php?id=21",
    "wof:name":"Lake Air Middle School",
    "wof:placetype":"venue"
},
  "geometry": {"coordinates":[-97.192015,31.54607],"type":"Point"}
}