{
  "type": "Feature",
  "properties": {
    "iso:country":"US",
    "sg:address":"1625 Yellowstone Ave",
    "sg:city":"Lewisville",
    "sg:classifiers":[
        {
            "category":"Organizations",
            "subcategory":"Religious Organization",
            "type":"Services"
        }
    ],
    "sg:phone":"+1 972 966 8908",
    "sg:postcode":"75077",
    "sg:province":"TX",
    "wof:name":"First Resurrection Minist",
    "wof:placetype":"venue"
},
  "geometry": {"coordinates":[-97.03952,33.067401],"type":"Point"}
}