{
  "type": "Feature",
  "properties": {
    "iso:country":"US",
    "sg:address":"812 E 2nd St",
    "sg:city":"Colorado City",
    "sg:classifiers":[
        {
            "category":"Autos & Motor Vehicles",
            "subcategory":"Automobile Sales",
            "type":"Retail Goods"
        }
    ],
    "sg:phone":"+1 325 728 3888",
    "sg:postcode":"79512",
    "sg:province":"TX",
    "sg:tags":[
        "used"
    ],
    "wof:name":"Texas Motors",
    "wof:placetype":"venue"
},
  "geometry": {"coordinates":[-100.857259,32.387941],"type":"Point"}
}