{
  "type": "Feature",
  "properties": {
    "iso:country":"US",
    "sg:address":"422 S Zarzamora St",
    "sg:city":"San Antonio",
    "sg:classifiers":[
        {
            "category":"Restaurant",
            "type":"Food & Drink"
        }
    ],
    "sg:menulink":"http://www.allmenus.com/tx/san-antonio/204408-sonic/menu/",
    "sg:phone":"+1 210 431 0058",
    "sg:postcode":"78207",
    "sg:province":"TX",
    "sg:tags":[
        "burger",
        "american"
    ],
    "wof:name":"Sonic",
    "wof:placetype":"venue"
},
  "geometry": {"coordinates":[-98.527434,29.424414],"type":"Point"}
}