{
  "type": "Feature",
  "properties": {
    "iso:country":"US",
    "sg:address":"1900 E Elms Rd Ste A100",
    "sg:city":"Killeen",
    "sg:classifiers":[
        {
            "category":"Real Estate",
            "subcategory":"Real Estate Services",
            "type":"Services"
        },
        {
            "category":"Real Estate",
            "subcategory":"Real Estate Agent",
            "type":"Services"
        }
    ],
    "sg:phone":"+1 254 554 3342",
    "sg:postcode":"76542",
    "sg:province":"TX",
    "sg:tags":[
        "buyer",
        "broker"
    ],
    "wof:name":"Texas Heritage Real Estate",
    "wof:placetype":"venue"
},
  "geometry": {"coordinates":[-97.727234,31.078131],"type":"Point"}
}