{
  "type": "Feature",
  "properties": {
    "iso:country":"US",
    "sg:address":"11620 Goodnight Ln",
    "sg:city":"Dallas",
    "sg:classifiers":[
        {
            "category":"Airline",
            "type":"Transportation"
        }
    ],
    "sg:phone":"+1 972 484 5266",
    "sg:postcode":"75229",
    "sg:province":"TX",
    "sg:tags":[
        "courier",
        "air"
    ],
    "wof:name":"Sonic Air",
    "wof:placetype":"venue"
},
  "geometry": {"coordinates":[-96.902326,32.906506],"type":"Point"}
}