{
  "type": "Feature",
  "properties": {
    "iso:country":"US",
    "sg:address":"212 Harbor St",
    "sg:city":"Houston",
    "sg:classifiers":[
        {
            "category":"Freight",
            "type":"Transportation"
        }
    ],
    "sg:phone":"+1 713 673 3931",
    "sg:postcode":"77020",
    "sg:province":"TX",
    "sg:tags":[
        "local",
        "trucking"
    ],
    "wof:name":"Texas Commissary Inc",
    "wof:placetype":"venue"
},
  "geometry": {"coordinates":[-95.294988,29.785379],"type":"Point"}
}