{
  "type": "Feature",
  "properties": {
    "iso:country":"US",
    "sg:address":"727 Mary Lake Dr",
    "sg:city":"Bryan",
    "sg:classifiers":[
        {
            "category":"Social Services",
            "subcategory":"Child Care",
            "type":"Services"
        }
    ],
    "sg:phone":"+1 979 846 2752",
    "sg:postcode":"77802",
    "sg:province":"TX",
    "wof:name":"Jane's Little Pals Childrens",
    "wof:placetype":"venue"
},
  "geometry": {"coordinates":[-96.345737,30.641185],"type":"Point"}
}