{
  "type": "Feature",
  "properties": {
    "iso:country":"US",
    "sg:address":"5534 Crosswind Dr",
    "sg:city":"San Antonio",
    "sg:classifiers":[
        {
            "category":"Freight",
            "type":"Transportation"
        }
    ],
    "sg:phone":"+1 210 967 7352",
    "sg:postcode":"78239",
    "sg:province":"TX",
    "sg:tags":[
        "vehicle"
    ],
    "wof:name":"RELA Transport Inc",
    "wof:placetype":"venue"
},
  "geometry": {"coordinates":[-98.390083,29.516579],"type":"Point"}
}