{
  "type": "Feature",
  "properties": {
    "iso:country":"US",
    "sg:address":"6001 Stonington St",
    "sg:city":"Houston",
    "sg:classifiers":[
        {
            "category":"Food & Beverages",
            "subcategory":"Specialty",
            "type":"Retail Goods"
        }
    ],
    "sg:phone":"+1 713 690 1780",
    "sg:postcode":"77040",
    "sg:province":"TX",
    "wof:name":"Administration Office",
    "wof:placetype":"venue"
},
  "geometry": {"coordinates":[-95.532223,29.855912],"type":"Point"}
}