{
  "type": "Feature",
  "properties": {
    "iso:country":"US",
    "sg:address":"1106 Orchid St",
    "sg:city":"Houston",
    "sg:classifiers":[
        {
            "category":"Building & Trades",
            "subcategory":"Plumbing",
            "type":"Services"
        }
    ],
    "sg:phone":"+1 713 649 4669",
    "sg:postcode":"77017",
    "sg:province":"TX",
    "sg:tags":[
        "conditioning",
        "air",
        "system",
        "contractor"
    ],
    "wof:name":"Millco Appliance",
    "wof:placetype":"venue"
},
  "geometry": {"coordinates":[-95.243038,29.689261],"type":"Point"}
}