{
  "type": "Feature",
  "properties": {
    "iso:country":"US",
    "sg:address":"909 Adventure Ln",
    "sg:city":"Cedar Park",
    "sg:classifiers":[
        {
            "category":"Building & Trades",
            "subcategory":"Construction",
            "type":"Services"
        }
    ],
    "sg:phone":"+1 512 260 0303",
    "sg:postcode":"78613",
    "sg:province":"TX",
    "sg:tags":[
        "painter"
    ],
    "wof:name":"Covenant Contractors",
    "wof:placetype":"venue"
},
  "geometry": {"coordinates":[-97.78611600000001,30.511361],"type":"Point"}
}