{
  "type": "Feature",
  "properties": {
    "iso:country":"US",
    "sg:address":"1102 Bluebonnet Ave",
    "sg:city":"Odessa",
    "sg:classifiers":[
        {
            "category":"Personal",
            "subcategory":"Beauty Salon",
            "type":"Services"
        }
    ],
    "sg:phone":"+1 432 333 4691",
    "sg:postcode":"79761",
    "sg:province":"TX",
    "wof:name":"Hope's Beauty Salon",
    "wof:placetype":"venue"
},
  "geometry": {"coordinates":[-102.355486,31.837507],"type":"Point"}
}