{
  "type": "Feature",
  "properties": {
    "iso:country":"US",
    "sg:address":"12221 Merit Dr",
    "sg:city":"Dallas",
    "sg:classifiers":[
        {
            "category":"Health Services",
            "subcategory":"Doctor",
            "type":"Services"
        }
    ],
    "sg:phone":"+1 972 566 7822",
    "sg:postcode":"75251",
    "sg:province":"TX",
    "sg:tags":[
        "dentist"
    ],
    "wof:name":"Martin Weinberg DDS",
    "wof:placetype":"venue"
},
  "geometry": {"coordinates":[-96.772902,32.91766],"type":"Point"}
}