{
  "type": "Feature",
  "properties": {
    "iso:country":"US",
    "sg:address":"10300 Farrell Rd",
    "sg:city":"Willis",
    "sg:classifiers":[
        {
            "category":"Retail",
            "subcategory":"Repair Shop",
            "type":"Services"
        }
    ],
    "sg:phone":"+1 936 890 8111",
    "sg:postcode":"77378",
    "sg:province":"TX",
    "sg:tags":[
        "upholsterer"
    ],
    "wof:name":"J & C Svc Furn Restoration",
    "wof:placetype":"venue"
},
  "geometry": {"coordinates":[-95.441444,30.390615],"type":"Point"}
}