{
  "type": "Feature",
  "properties": {
    "iso:country":"US",
    "sg:address":"5511 Alameda Ave",
    "sg:city":"El Paso",
    "sg:classifiers":[
        {
            "category":"Professional",
            "subcategory":"Business Services",
            "type":"Services"
        }
    ],
    "sg:phone":"+1 915 778 6808",
    "sg:postcode":"79905",
    "sg:province":"TX",
    "wof:name":"Payment Agency",
    "wof:placetype":"venue"
},
  "geometry": {"coordinates":[-106.423722,31.768288],"type":"Point"}
}