{
  "type": "Feature",
  "properties": {
    "iso:country":"US",
    "sg:address":"1515 Flintwood Dr",
    "sg:city":"Richardson",
    "sg:classifiers":[
        {
            "category":"Manufacturing",
            "subcategory":"Electronics",
            "type":"Manufacturing & Wholesale Goods"
        }
    ],
    "sg:phone":"+1 972 644 2156",
    "sg:postcode":"75081",
    "sg:province":"TX",
    "sg:tags":[
        "equipment",
        "electronic",
        "supply"
    ],
    "wof:name":"Component Express Corp",
    "wof:placetype":"venue"
},
  "geometry": {"coordinates":[-96.69728499999999,32.935446],"type":"Point"}
}