{
  "type": "Feature",
  "properties": {
    "iso:country":"US",
    "sg:address":"10583 Long Branch Dr",
    "sg:city":"Conroe",
    "sg:classifiers":[
        {
            "category":"Freight",
            "type":"Transportation"
        }
    ],
    "sg:phone":"+1 936 890 0924",
    "sg:postcode":"77303",
    "sg:province":"TX",
    "sg:tags":[
        "operator",
        "trucking"
    ],
    "wof:name":"Kiwi & Yank Enterprises Inc",
    "wof:placetype":"venue"
},
  "geometry": {"coordinates":[-95.409617,30.394254],"type":"Point"}
}