{
  "type": "Feature",
  "properties": {
    "iso:country":"US",
    "sg:address":"14812 W State Highway 21",
    "sg:city":"Douglass",
    "sg:classifiers":[
        {
            "category":"Restaurant",
            "type":"Food & Drink"
        }
    ],
    "sg:phone":"+1 936 462 8600",
    "sg:postcode":"75943",
    "sg:province":"TX",
    "sg:tags":[
        "house",
        "steak",
        "barbecue"
    ],
    "wof:name":"Harlon's Bar B. Que",
    "wof:placetype":"venue"
},
  "geometry": {"coordinates":[-94.872957,31.671718],"type":"Point"}
}