{
  "type": "Feature",
  "properties": {
    "iso:country":"US",
    "sg:address":"502 Lake Air Dr",
    "sg:city":"Waco",
    "sg:classifiers":[
        {
            "category":"Personal",
            "type":"Services"
        }
    ],
    "sg:phone":"+1 254 741 1771",
    "sg:postcode":"76710",
    "sg:province":"TX",
    "wof:name":"Equator Tans",
    "wof:placetype":"venue"
},
  "geometry": {"coordinates":[-97.18682099999999,31.525778],"type":"Point"}
}