{
  "type": "Feature",
  "properties": {
    "iso:country":"US",
    "sg:address":"1325 N Central Ave",
    "sg:city":"Brownsville",
    "sg:classifiers":[
        {
            "category":"Freight",
            "type":"Transportation"
        }
    ],
    "sg:phone":"+1 956 838 1811",
    "sg:postcode":"78521",
    "sg:province":"TX",
    "sg:tags":[
        "broker",
        "customs"
    ],
    "wof:name":"J A Guerrero Us Customs Brkrs",
    "wof:placetype":"venue"
},
  "geometry": {"coordinates":[-97.446302,25.934675],"type":"Point"}
}