{
  "type": "Feature",
  "properties": {
    "iso:country":"US",
    "sg:address":"1721 Cantrell Blvd",
    "sg:city":"Conroe",
    "sg:classifiers":[
        {
            "category":"Building & Trades",
            "subcategory":"Construction",
            "type":"Services"
        }
    ],
    "sg:phone":"+1 936 441 2937",
    "sg:postcode":"77301",
    "sg:province":"TX",
    "sg:tags":[
        "water",
        "well",
        "drilling"
    ],
    "wof:name":"Drillers Vac Service Inc",
    "wof:placetype":"venue"
},
  "geometry": {"coordinates":[-95.43199799999999,30.309174],"type":"Point"}
}