{
  "type": "Feature",
  "properties": {
    "iso:country":"US",
    "sg:address":"200 Rivercrest Dr",
    "sg:city":"Fort Worth",
    "sg:classifiers":[
        {
            "category":"Professional",
            "subcategory":"Business Services",
            "type":"Services"
        }
    ],
    "sg:phone":"+1 817 429 1719",
    "sg:postcode":"76107",
    "sg:province":"TX",
    "wof:name":"Rabar Enterprises LLC",
    "wof:placetype":"venue"
},
  "geometry": {"coordinates":[-97.378642,32.757394],"type":"Point"}
}