{
  "type": "Feature",
  "properties": {
    "iso:country":"US",
    "sg:address":"302 Erie St",
    "sg:city":"Cleburne",
    "sg:classifiers":[
        {
            "category":"Home & Garden",
            "subcategory":"Garden Supply",
            "type":"Retail Goods"
        }
    ],
    "sg:phone":"+1 817 645 5872",
    "sg:postcode":"76031",
    "sg:province":"TX",
    "sg:tags":[
        "florist",
        "ornamental"
    ],
    "wof:name":"Myers Plant Co",
    "wof:placetype":"venue"
},
  "geometry": {"coordinates":[-97.38770599999999,32.367534],"type":"Point"}
}