{
  "type": "Feature",
  "properties": {
    "iso:country":"US",
    "sg:address":"10850 Co Rd 442",
    "sg:city":"Princeton",
    "sg:classifiers":[
        {
            "category":"Airport",
            "type":"Transportation"
        }
    ],
    "sg:phone":"+1 972 736 2857",
    "sg:postcode":"75407",
    "sg:province":"TX",
    "wof:name":"Turbo-Resins International",
    "wof:placetype":"venue"
},
  "geometry": {"coordinates":[-96.49359,33.091146],"type":"Point"}
}