{
  "type": "Feature",
  "properties": {
    "iso:country":"US",
    "sg:address":"17807 Abby Ln",
    "sg:city":"Spring",
    "sg:classifiers":[
        {
            "category":"Professional",
            "type":"Services"
        }
    ],
    "sg:phone":"+1 713 542 4143",
    "sg:postcode":"77379",
    "sg:province":"TX",
    "wof:name":"Aero Services Inc",
    "wof:placetype":"venue"
},
  "geometry": {"coordinates":[-95.546527,30.026277],"type":"Point"}
}