{
  "type": "Feature",
  "properties": {
    "iso:country":"US",
    "sg:address":"7 Dons Dr",
    "sg:city":"Mission",
    "sg:classifiers":[
        {
            "category":"Manufacturing",
            "subcategory":"Toys & Sporting Goods",
            "type":"Manufacturing & Wholesale Goods"
        }
    ],
    "sg:phone":"+1 956 581 9959",
    "sg:postcode":"78572",
    "sg:province":"TX",
    "sg:tags":[
        "doll"
    ],
    "wof:name":"Teach-A-Bodies Anatomical Dlls",
    "wof:placetype":"venue"
},
  "geometry": {"coordinates":[-98.30440900000001,26.219217],"type":"Point"}
}