{
  "type": "Feature",
  "properties": {
    "iso:country":"US",
    "sg:address":"1729 Front St",
    "sg:city":"Columbus",
    "sg:classifiers":[
        {
            "category":"Wholesale",
            "subcategory":"Non-durable Goods",
            "type":"Manufacturing & Wholesale Goods"
        }
    ],
    "sg:phone":"+1 979 732 3363",
    "sg:postcode":"78934",
    "sg:province":"TX",
    "wof:name":"Jerry Parker",
    "wof:placetype":"venue"
},
  "geometry": {"coordinates":[-96.53810300000001,29.699602],"type":"Point"}
}