{
  "type": "Feature",
  "properties": {
    "iso:country":"US",
    "sg:address":"92 Wilson Rd",
    "sg:city":"Humble",
    "sg:classifiers":[
        {
            "category":"Shopping",
            "subcategory":"Bicycles & Sporting Goods",
            "type":"Retail Goods"
        }
    ],
    "sg:phone":"+1 281 548 1688",
    "sg:postcode":"77338",
    "sg:province":"TX",
    "wof:name":"Wangs Martial Arts & Supplies",
    "wof:placetype":"venue"
},
  "geometry": {"coordinates":[-95.250186,29.999382],"type":"Point"}
}