{
  "type": "Feature",
  "properties": {
    "iso:country":"US",
    "sg:address":"4400 E Fm 1187",
    "sg:city":"Burleson",
    "sg:classifiers":[
        {
            "category":"Personal",
            "type":"Services"
        }
    ],
    "sg:phone":"+1 817 293 2214",
    "sg:postcode":"76028",
    "sg:province":"TX",
    "sg:tags":[
        "party",
        "planning",
        "event"
    ],
    "wof:name":"Auction Block the",
    "wof:placetype":"venue"
},
  "geometry": {"coordinates":[-97.266296,32.579498],"type":"Point"}
}