{
  "type": "Feature",
  "properties": {
    "iso:country":"US",
    "sg:address":"2711 S I H 35",
    "sg:city":"Austin",
    "sg:classifiers":[
        {
            "category":"Travel",
            "subcategory":"Hotels & Motels",
            "type":"Entertainment"
        }
    ],
    "sg:phone":"+1 512 462 9201",
    "sg:postcode":"78741",
    "sg:province":"TX",
    "wof:name":"Exel Inn of Austin South",
    "wof:placetype":"venue"
},
  "geometry": {"coordinates":[-97.743404,30.22892],"type":"Point"}
}