{
  "type": "Feature",
  "properties": {
    "iso:country":"US",
    "sg:address":"3060 Sycamore School Rd",
    "sg:city":"Fort Worth",
    "sg:classifiers":[
        {
            "category":"Health Services",
            "subcategory":"Doctor",
            "type":"Services"
        }
    ],
    "sg:phone":"+1 817 370 0268",
    "sg:postcode":"76133",
    "sg:province":"TX",
    "sg:tags":[
        "dentist"
    ],
    "wof:name":"Orthodonitc Ctr Of America",
    "wof:placetype":"venue"
},
  "geometry": {"coordinates":[-97.36443,32.634885],"type":"Point"}
}