{
  "type": "Feature",
  "properties": {
    "iso:country":"US",
    "sg:address":"312 W Expressway 83",
    "sg:city":"Weslaco",
    "sg:classifiers":[
        {
            "category":"Banks & Credit Unions",
            "subcategory":"Investment Brokerage",
            "type":"Services"
        }
    ],
    "sg:phone":"+1 956 969 8969",
    "sg:postcode":"78596",
    "sg:province":"TX",
    "sg:tags":[
        "advisory"
    ],
    "wof:name":"Triangular Investments",
    "wof:placetype":"venue"
},
  "geometry": {"coordinates":[-97.99529200000001,26.173249],"type":"Point"}
}