{
  "type": "Feature",
  "properties": {
    "iso:country":"US",
    "sg:address":"9903 Potranco Rd",
    "sg:city":"San Antonio",
    "sg:classifiers":[
        {
            "category":"Shopping",
            "subcategory":"Pharmacy",
            "type":"Retail Goods"
        }
    ],
    "sg:phone":"+1 210 268 7431",
    "sg:postcode":"78251",
    "sg:province":"TX",
    "wof:name":"Walgreens",
    "wof:placetype":"venue"
},
  "geometry": {"coordinates":[-98.68170499999999,29.437319],"type":"Point"}
}