{
  "type": "Feature",
  "properties": {
    "iso:country":"US",
    "sg:address":"508 Pierce St",
    "sg:city":"Lindale",
    "sg:classifiers":[
        {
            "category":"Health Services",
            "subcategory":"Clinic",
            "type":"Services"
        }
    ],
    "sg:phone":"+1 903 881 0275",
    "sg:postcode":"75771",
    "sg:province":"TX",
    "wof:name":"ADV Health Svc",
    "wof:placetype":"venue"
},
  "geometry": {"coordinates":[-95.40417600000001,32.510522],"type":"Point"}
}