{
  "type": "Feature",
  "properties": {
    "iso:country":"US",
    "sg:address":"8313 Novaro Dr",
    "sg:city":"Plano",
    "sg:classifiers":[
        {
            "category":"Professional",
            "subcategory":"Computer Services",
            "type":"Services"
        }
    ],
    "sg:phone":"+1 214 495 9815",
    "sg:postcode":"75025",
    "sg:province":"TX",
    "sg:tags":[
        "consulting",
        "system",
        "software"
    ],
    "wof:name":"Icon Systems Inc",
    "wof:placetype":"venue"
},
  "geometry": {"coordinates":[-96.744032,33.09074],"type":"Point"}
}