{
  "type": "Feature",
  "properties": {
    "iso:country":"US",
    "sg:address":"11511 N Garden St",
    "sg:city":"Houston",
    "sg:classifiers":[
        {
            "category":"Building & Trades",
            "subcategory":"Construction",
            "type":"Services"
        }
    ],
    "sg:phone":"+1 713 484 7040",
    "sg:postcode":"77071",
    "sg:province":"TX",
    "sg:tags":[
        "repair",
        "specialty",
        "systems-repairing",
        "system",
        "heating",
        "equipment",
        "contractor",
        "air conditioning"
    ],
    "sg:website":"http://www.losandesair.com",
    "wof:name":"Los Andes Air Systems",
    "wof:placetype":"venue"
},
  "geometry": {"coordinates":[-95.52240999999999,29.63332],"type":"Point"}
}