{
  "type": "Feature",
  "properties": {
    "iso:country":"US",
    "sg:address":"901 W 59th St",
    "sg:city":"Odessa",
    "sg:classifiers":[
        {
            "category":"Manufacturing",
            "subcategory":"Tools & Machinery",
            "type":"Manufacturing & Wholesale Goods"
        }
    ],
    "sg:phone":"+1 432 368 0835",
    "sg:postcode":"79764",
    "sg:province":"TX",
    "sg:tags":[
        "oil",
        "gas"
    ],
    "wof:name":"H C Howell Co",
    "wof:placetype":"venue"
},
  "geometry": {"coordinates":[-102.40667500000001,31.895577],"type":"Point"}
}