{
  "type": "Feature",
  "properties": {
    "iso:country":"US",
    "sg:address":"1801 Marketplace Dr",
    "sg:city":"Garland",
    "sg:classifiers":[
        {
            "category":"Juice Bar",
            "subcategory":"None",
            "type":"Food & Drink"
        },
        {
            "category":"Ice Cream",
            "type":"Food & Drink"
        }
    ],
    "sg:phone":"+1 972 279 6600",
    "sg:postcode":"75041",
    "sg:province":"TX",
    "sg:tags":[
        "smoothy",
        "frozen",
        "yogurt"
    ],
    "wof:name":"Palateria La Flor De Michoacan",
    "wof:placetype":"venue"
},
  "geometry": {"coordinates":[-96.65206499999999,32.862173],"type":"Point"}
}