{
  "type": "Feature",
  "properties": {
    "iso:country":"US",
    "sg:address":"3601 John Stockbauer Dr",
    "sg:city":"Victoria",
    "sg:classifiers":[
        {
            "category":"Food & Beverages",
            "subcategory":"Groceries & Convenience Stores",
            "type":"Retail Goods"
        }
    ],
    "sg:phone":"+1 361 575 7094",
    "sg:postcode":"77904",
    "sg:province":"TX",
    "wof:name":"Speedy Stop",
    "wof:placetype":"venue"
},
  "geometry": {"coordinates":[-96.94747599999999,28.818572],"type":"Point"}
}