{
  "type": "Feature",
  "properties": {
    "iso:country":"US",
    "sg:address":"113 W Kingsmill Ave",
    "sg:city":"Pampa",
    "sg:classifiers":[
        {
            "category":"Building & Trades",
            "subcategory":"Construction",
            "type":"Services"
        }
    ],
    "sg:phone":"+1 806 898 4409",
    "sg:postcode":"79065",
    "sg:province":"TX",
    "sg:tags":[
        "maker",
        "cabinet"
    ],
    "wof:name":"Giles Cabinet Shop",
    "wof:placetype":"venue"
},
  "geometry": {"coordinates":[-100.9622,35.536617],"type":"Point"}
}