{
  "type": "Feature",
  "properties": {
    "iso:country":"US",
    "sg:address":"1740 Continental Dr W",
    "sg:city":"Pleasanton",
    "sg:classifiers":[
        {
            "category":"Shopping",
            "subcategory":"Jewelry",
            "type":"Retail Goods"
        }
    ],
    "sg:phone":"+1 830 569 5113",
    "sg:postcode":"78064",
    "sg:province":"TX",
    "sg:tags":[
        "fine"
    ],
    "wof:name":"Wright Jewelers",
    "wof:placetype":"venue"
},
  "geometry": {"coordinates":[-98.508488,28.970395],"type":"Point"}
}