{
  "type": "Feature",
  "properties": {
    "iso:country":"US",
    "sg:address":"7510 Quail Run Dr",
    "sg:city":"San Antonio",
    "sg:classifiers":[
        {
            "category":"Professional",
            "type":"Services"
        }
    ],
    "sg:phone":"+1 210 822 6057",
    "sg:postcode":"78209",
    "sg:province":"TX",
    "wof:name":"Meeces Garden",
    "wof:placetype":"venue"
},
  "geometry": {"coordinates":[-98.438271,29.501809],"type":"Point"}
}