{
  "type": "Feature",
  "properties": {
    "iso:country":"US",
    "sg:address":"4290 Pepperhill Dr",
    "sg:city":"Montgomery",
    "sg:classifiers":[
        {
            "category":"Farming",
            "subcategory":"Livestock Farm",
            "type":"Manufacturing & Wholesale Goods"
        }
    ],
    "sg:phone":"+1 936 449 6521",
    "sg:postcode":"77316",
    "sg:province":"TX",
    "sg:tags":[
        "equine"
    ],
    "wof:name":"Pasos De Promesa",
    "wof:placetype":"venue"
},
  "geometry": {"coordinates":[-95.69107099999999,30.330101],"type":"Point"}
}