{
  "type": "Feature",
  "properties": {
    "iso:country":"US",
    "sg:address":"200 Bartlett Dr",
    "sg:city":"El Paso",
    "sg:classifiers":[
        {
            "category":"Building & Trades",
            "subcategory":"Construction",
            "type":"Services"
        }
    ],
    "sg:phone":"+1 915 585 3625",
    "sg:postcode":"79912",
    "sg:province":"TX",
    "sg:tags":[
        "contractor"
    ],
    "wof:name":"Orl",
    "wof:placetype":"venue"
},
  "geometry": {"coordinates":[-106.567001,31.8403],"type":"Point"}
}