{
  "type": "Feature",
  "properties": {
    "iso:country":"US",
    "sg:address":"3762 Up River Rd",
    "sg:city":"Corpus Christi",
    "sg:classifiers":[
        {
            "category":"Real Estate",
            "subcategory":"Real Estate Operator",
            "type":"Services"
        }
    ],
    "sg:phone":"+1 361 888 8586",
    "sg:postcode":"78408",
    "sg:province":"TX",
    "sg:tags":[
        "apartment"
    ],
    "wof:name":"Bay Bluff Apts",
    "wof:placetype":"venue"
},
  "geometry": {"coordinates":[-97.435165,27.797901],"type":"Point"}
}