{
  "type": "Feature",
  "properties": {
    "iso:country":"US",
    "sg:address":"13350 Dallas Pkwy",
    "sg:city":"Dallas",
    "sg:classifiers":[
        {
            "category":"Shopping",
            "subcategory":"Gifts & Souvenirs",
            "type":"Retail Goods"
        },
        {
            "category":"Shopping",
            "subcategory":"Clothing, Apparel, & Fashions",
            "type":"Retail Goods"
        }
    ],
    "sg:phone":"+1 972 404 0215",
    "sg:postcode":"75240",
    "sg:province":"TX",
    "sg:tags":[
        "sportswear"
    ],
    "wof:name":"Destination Dallas",
    "wof:placetype":"venue"
},
  "geometry": {"coordinates":[-96.821797,32.932724],"type":"Point"}
}