{
  "type": "Feature",
  "properties": {
    "iso:country":"US",
    "sg:address":"900 Ferndale Dr",
    "sg:city":"Round Rock",
    "sg:classifiers":[
        {
            "category":"Shopping",
            "subcategory":"Clothing, Apparel, & Fashions",
            "type":"Retail Goods"
        }
    ],
    "sg:phone":"+1 512 278 0371",
    "sg:postcode":"78664",
    "sg:province":"TX",
    "sg:tags":[
        "shop",
        "bridal"
    ],
    "wof:name":"Mendez Craft & Bridal",
    "wof:placetype":"venue"
},
  "geometry": {"coordinates":[-97.668902,30.498616],"type":"Point"}
}