{
  "type": "Feature",
  "properties": {
    "iso:country":"US",
    "sg:address":"8088 FM 2673",
    "sg:city":"Canyon Lake",
    "sg:classifiers":[
        {
            "category":"Food & Beverages",
            "subcategory":"Liquor & Beverages",
            "type":"Retail Goods"
        }
    ],
    "sg:phone":"+1 830 899 5626",
    "sg:postcode":"78133",
    "sg:province":"TX",
    "sg:tags":[
        "alcoholic"
    ],
    "wof:name":"Liquors At The Lake",
    "wof:placetype":"venue"
},
  "geometry": {"coordinates":[-98.25915999999999,29.840668],"type":"Point"}
}