{
  "type": "Feature",
  "properties": {
    "iso:country":"US",
    "sg:address":"201 Bryan Pl",
    "sg:city":"Cedar Hill",
    "sg:classifiers":[
        {
            "category":"Insurance",
            "subcategory":"Insurance Agent",
            "type":"Services"
        }
    ],
    "sg:phone":"+1 972 299 5355",
    "sg:postcode":"75104",
    "sg:province":"TX",
    "wof:name":"Haydin Group",
    "wof:placetype":"venue"
},
  "geometry": {"coordinates":[-96.951053,32.601633],"type":"Point"}
}