{
  "type": "Feature",
  "properties": {
    "iso:country":"US",
    "sg:address":"120 Houston St",
    "sg:city":"Angleton",
    "sg:classifiers":[
        {
            "category":"Professional",
            "type":"Services"
        }
    ],
    "sg:phone":"+1 979 849 5685",
    "sg:postcode":"77515",
    "sg:province":"TX",
    "wof:name":"Bock Machine",
    "wof:placetype":"venue"
},
  "geometry": {"coordinates":[-95.406727,29.179696],"type":"Point"}
}