{
  "type": "Feature",
  "properties": {
    "iso:country":"US",
    "sg:address":"1209 K Ave",
    "sg:city":"Plano",
    "sg:classifiers":[
        {
            "category":"Autos & Motor Vehicles",
            "subcategory":"Auto Supplies",
            "type":"Retail Goods"
        },
        {
            "category":"Retail",
            "subcategory":"Auto Repair",
            "type":"Services"
        }
    ],
    "sg:phone":"+1 972 881 1178",
    "sg:postcode":"75074",
    "sg:province":"TX",
    "sg:tags":[
        "recap",
        "retread",
        "tire"
    ],
    "wof:name":"Molina's Tire Service",
    "wof:placetype":"venue"
},
  "geometry": {"coordinates":[-96.69927199999999,33.01603],"type":"Point"}
}