{
  "type": "Feature",
  "properties": {
    "iso:country":"US",
    "sg:address":"11811 Avery Ln",
    "sg:city":"Mesquite",
    "sg:classifiers":[
        {
            "category":"Social Services",
            "subcategory":"Child Care",
            "type":"Services"
        }
    ],
    "sg:phone":"+1 972 289 0471",
    "sg:postcode":"75180",
    "sg:province":"TX",
    "sg:tags":[
        "day"
    ],
    "wof:name":"Deana Daycare",
    "wof:placetype":"venue"
},
  "geometry": {"coordinates":[-96.624838,32.739012],"type":"Point"}
}