{
  "type": "Feature",
  "properties": {
    "iso:country":"US",
    "sg:address":"1501 Arizona Ave",
    "sg:city":"El Paso",
    "sg:classifiers":[
        {
            "category":"Professional",
            "type":"Services"
        },
        {
            "category":"Personal",
            "type":"Services"
        }
    ],
    "sg:phone":"+1 915 577 9763",
    "sg:postcode":"79902",
    "sg:province":"TX",
    "sg:tags":[
        "therapist",
        "massage"
    ],
    "wof:name":"Alma Calderon",
    "wof:placetype":"venue"
},
  "geometry": {"coordinates":[-106.479157,31.77421],"type":"Point"}
}