{
  "type": "Feature",
  "properties": {
    "iso:country":"US",
    "sg:address":"2121 Washington Cir",
    "sg:city":"Arlington",
    "sg:classifiers":[
        {
            "category":"Real Estate",
            "subcategory":"Real Estate Operator",
            "type":"Services"
        }
    ],
    "sg:phone":"+1 817 274 2184",
    "sg:postcode":"76011",
    "sg:province":"TX",
    "sg:tags":[
        "apartment"
    ],
    "wof:name":"Woodstock Apartments-Arlington",
    "wof:placetype":"venue"
},
  "geometry": {"coordinates":[-97.10315199999999,32.769383],"type":"Point"}
}