{
  "type": "Feature",
  "properties": {
    "iso:country":"US",
    "sg:address":"2625 S Vernon Ave",
    "sg:city":"Dallas",
    "sg:classifiers":[
        {
            "category":"Professional",
            "subcategory":"Business Services",
            "type":"Services"
        }
    ],
    "sg:phone":"+1 214 946 2628",
    "sg:postcode":"75224",
    "sg:province":"TX",
    "wof:name":"Read J Sales Company",
    "wof:placetype":"venue"
},
  "geometry": {"coordinates":[-96.839005,32.718483],"type":"Point"}
}