{
  "type": "Feature",
  "properties": {
    "iso:country":"US",
    "sg:address":"907 Main St",
    "sg:city":"Buda",
    "sg:classifiers":[
        {
            "category":"Health Services",
            "subcategory":"Doctor",
            "type":"Services"
        }
    ],
    "sg:phone":"+1 512 295 2121",
    "sg:postcode":"78610",
    "sg:province":"TX",
    "sg:tags":[
        "physician",
        "family",
        "practice",
        "surgeons",
        "manipulative",
        "osteopathic",
        "treatment",
        "medicine",
        "surgeon"
    ],
    "wof:name":"Buda Family Practice",
    "wof:placetype":"venue"
},
  "geometry": {"coordinates":[-97.82335999999999,30.088525],"type":"Point"}
}