{
  "type": "Feature",
  "properties": {
    "iso:country":"US",
    "sg:address":"5946 Mount Houston Rd",
    "sg:city":"Houston",
    "sg:classifiers":[
        {
            "category":"Food & Beverages",
            "subcategory":"Specialty",
            "type":"Retail Goods"
        },
        {
            "category":"Food & Beverages",
            "subcategory":"Groceries & Convenience Stores",
            "type":"Retail Goods"
        }
    ],
    "sg:phone":"+1 281 227 0303",
    "sg:postcode":"77050",
    "sg:province":"TX",
    "sg:tags":[
        "grocers-specialty"
    ],
    "wof:name":"Nmart 410",
    "wof:placetype":"venue"
},
  "geometry": {"coordinates":[-95.301599,29.891098],"type":"Point"}
}