{
  "type": "Feature",
  "properties": {
    "iso:country":"US",
    "sg:address":"6400 Bowling Green St",
    "sg:city":"Houston",
    "sg:classifiers":[
        {
            "category":"Real Estate",
            "subcategory":"Real Estate Operator",
            "type":"Services"
        }
    ],
    "sg:phone":"+1 713 747 5400",
    "sg:postcode":"77021",
    "sg:province":"TX",
    "sg:tags":[
        "apartment"
    ],
    "wof:name":"Pear Grove Apartments",
    "wof:placetype":"venue"
},
  "geometry": {"coordinates":[-95.373527,29.704104],"type":"Point"}
}