{
  "type": "Feature",
  "properties": {
    "iso:country":"US",
    "sg:address":"603 N General Bruce Dr",
    "sg:city":"Temple",
    "sg:classifiers":[
        {
            "category":"Restaurant",
            "type":"Food & Drink"
        }
    ],
    "sg:menulink":"http://www.allmenus.com/tx/temple/70125-pizza-hut/menu/",
    "sg:phone":"+1 254 742 2222",
    "sg:postcode":"76504",
    "sg:province":"TX",
    "sg:tags":[
        "american",
        "pizza"
    ],
    "wof:name":"PIZZA HUT",
    "wof:placetype":"venue"
},
  "geometry": {"coordinates":[-97.35729499999999,31.107497],"type":"Point"}
}