{
  "type": "Feature",
  "properties": {
    "iso:country":"US",
    "sg:address":"201 Lamar St",
    "sg:city":"Sweetwater",
    "sg:classifiers":[
        {
            "category":"Travel",
            "subcategory":"Travel Agent",
            "type":"Entertainment"
        }
    ],
    "sg:phone":"+1 325 235 2742",
    "sg:postcode":"79556",
    "sg:province":"TX",
    "sg:tags":[
        "passenger",
        "transportation",
        "arrangement"
    ],
    "wof:name":"Greyhound Bus Line",
    "wof:placetype":"venue"
},
  "geometry": {"coordinates":[-100.40521099999999,32.468483],"type":"Point"}
}