{
  "type": "Feature",
  "properties": {
    "iso:country":"US",
    "sg:address":"3022 Canal Ave",
    "sg:city":"Nederland",
    "sg:classifiers":[
        {
            "category":"Professional",
            "type":"Services"
        }
    ],
    "sg:phone":"+1 409 727 5453",
    "sg:postcode":"77627",
    "sg:province":"TX",
    "wof:name":"Special Occassion Services",
    "wof:placetype":"venue"
},
  "geometry": {"coordinates":[-94.01483500000001,29.970426],"type":"Point"}
}