{
  "type": "Feature",
  "properties": {
    "iso:country":"US",
    "sg:address":"1295 Sandwood Ln",
    "sg:city":"Beaumont",
    "sg:classifiers":[
        {
            "category":"Personal",
            "subcategory":"Beauty Salon",
            "type":"Services"
        }
    ],
    "sg:phone":"+1 409 895 0941",
    "sg:postcode":"77706",
    "sg:province":"TX",
    "sg:tags":[
        "shop"
    ],
    "wof:name":"Event Media",
    "wof:placetype":"venue"
},
  "geometry": {"coordinates":[-94.142094,30.096145],"type":"Point"}
}