{
  "type": "Feature",
  "properties": {
    "iso:country":"US",
    "sg:address":"10 Alder Pl",
    "sg:city":"Spring",
    "sg:classifiers":[
        {
            "category":"Autos & Motor Vehicles",
            "subcategory":"Motorcycle Sales",
            "type":"Retail Goods"
        }
    ],
    "sg:phone":"+1 281 292 3224",
    "sg:postcode":"77380",
    "sg:province":"TX",
    "wof:name":"Sydne Cycles",
    "wof:placetype":"venue"
},
  "geometry": {"coordinates":[-95.461766,30.136059],"type":"Point"}
}