{
  "type": "Feature",
  "properties": {
    "iso:country":"US",
    "sg:address":"2120 Westheimer Rd",
    "sg:city":"Houston",
    "sg:classifiers":[
        {
            "category":"Education",
            "subcategory":"School",
            "type":"Public Place"
        }
    ],
    "sg:phone":"+1 713 526 3279",
    "sg:postcode":"77098",
    "sg:province":"TX",
    "wof:name":"St Anne Catholic Community",
    "wof:placetype":"venue"
},
  "geometry": {"coordinates":[-95.412308,29.742686],"type":"Point"}
}