{
  "type": "Feature",
  "properties": {
    "iso:country":"US",
    "sg:address":"320 Graystone Rd",
    "sg:city":"Burleson",
    "sg:classifiers":[
        {
            "category":"Shopping",
            "subcategory":"Gifts & Souvenirs",
            "type":"Retail Goods"
        }
    ],
    "sg:phone":"+1 817 426 4933",
    "sg:postcode":"76028",
    "sg:province":"TX",
    "wof:name":"Country Creations",
    "wof:placetype":"venue"
},
  "geometry": {"coordinates":[-97.24862899999999,32.510732],"type":"Point"}
}