{
  "type": "Feature",
  "properties": {
    "iso:country":"US",
    "sg:address":"831 W Sinton St",
    "sg:city":"Sinton",
    "sg:classifiers":[
        {
            "category":"Manufacturing",
            "subcategory":"Buildings",
            "type":"Manufacturing & Wholesale Goods"
        },
        {
            "category":"Building & Trades",
            "subcategory":"Construction",
            "type":"Services"
        }
    ],
    "sg:phone":"+1 361 437 7653",
    "sg:postcode":"78387",
    "sg:province":"TX",
    "sg:tags":[
        "home",
        "builder",
        "contractor"
    ],
    "wof:name":"Tobar Construction",
    "wof:placetype":"venue"
},
  "geometry": {"coordinates":[-97.52036099999999,28.036746],"type":"Point"}
}