{
  "type": "Feature",
  "properties": {
    "iso:country":"US",
    "sg:address":"4616 W Howard Ln Ste 650",
    "sg:city":"Austin",
    "sg:classifiers":[
        {
            "category":"Manufacturing",
            "subcategory":"Toys & Sporting Goods",
            "type":"Manufacturing & Wholesale Goods"
        },
        {
            "category":"Shopping",
            "subcategory":"Bicycles & Sporting Goods",
            "type":"Retail Goods"
        }
    ],
    "sg:phone":"+1 512 733 5300",
    "sg:postcode":"78728",
    "sg:province":"TX",
    "sg:tags":[
        "goods-wholesale",
        "manufacturer"
    ],
    "sg:website":"http://www.wwt.com",
    "wof:name":"Act Global Sports Technology Inc.",
    "wof:placetype":"venue"
},
  "geometry": {"coordinates":[-97.69458400000001,30.438675],"type":"Point"}
}