{
  "type": "Feature",
  "properties": {
    "iso:country":"US",
    "sg:address":"517 N R St",
    "sg:city":"Harlingen",
    "sg:classifiers":[
        {
            "category":"Personal",
            "subcategory":"Shoe Repair & Shine",
            "type":"Services"
        }
    ],
    "sg:phone":"+1 956 428 1699",
    "sg:postcode":"78550",
    "sg:province":"TX",
    "sg:tags":[
        "repairing",
        "boot"
    ],
    "wof:name":"Jorge's Shoe Shop",
    "wof:placetype":"venue"
},
  "geometry": {"coordinates":[-97.715919,26.198199],"type":"Point"}
}