{
  "type": "Feature",
  "properties": {
    "iso:country":"US",
    "sg:address":"1157 W Jeter Rd",
    "sg:city":"Argyle",
    "sg:classifiers":[
        {
            "category":"Farming",
            "subcategory":"Livestock Farm",
            "type":"Manufacturing & Wholesale Goods"
        }
    ],
    "sg:phone":"+1 940 464 3601",
    "sg:postcode":"76226",
    "sg:province":"TX",
    "sg:tags":[
        "animal",
        "general"
    ],
    "wof:name":"Furst Ranch",
    "wof:placetype":"venue"
},
  "geometry": {"coordinates":[-97.176925,33.081705],"type":"Point"}
}