{
  "type": "Feature",
  "properties": {
    "iso:country":"US",
    "sg:address":"433 E Hildebrand Ave",
    "sg:city":"San Antonio",
    "sg:classifiers":[
        {
            "category":"Retail",
            "subcategory":"Laundry & Dry Cleaning",
            "type":"Services"
        }
    ],
    "sg:phone":"+1 210 824 2120",
    "sg:postcode":"78212",
    "sg:province":"TX",
    "wof:name":"CC Fashions Inc",
    "wof:placetype":"venue"
},
  "geometry": {"coordinates":[-98.485435,29.466572],"type":"Point"}
}