{
  "type": "Feature",
  "properties": {
    "iso:country":"US",
    "sg:address":"3151 Halifax St",
    "sg:city":"Dallas",
    "sg:classifiers":[
        {
            "category":"Manufacturing",
            "subcategory":"Printing",
            "type":"Manufacturing & Wholesale Goods"
        }
    ],
    "sg:phone":"+1 214 819 9890",
    "sg:postcode":"75247",
    "sg:province":"TX",
    "sg:tags":[
        "printer"
    ],
    "wof:name":"National Printer Mgmt Group",
    "wof:placetype":"venue"
},
  "geometry": {"coordinates":[-96.864496,32.811963],"type":"Point"}
}