{
  "type": "Feature",
  "properties": {
    "iso:country":"US",
    "sg:address":"465 N Resler Dr",
    "sg:city":"El Paso",
    "sg:classifiers":[
        {
            "category":"Real Estate",
            "subcategory":"Developer",
            "type":"Services"
        }
    ],
    "sg:phone":"+1 915 584 0714",
    "sg:postcode":"79912",
    "sg:province":"TX",
    "wof:name":"John C Foster Development Corp",
    "wof:placetype":"venue"
},
  "geometry": {"coordinates":[-106.551338,31.845407],"type":"Point"}
}