{
  "type": "Feature",
  "properties": {
    "iso:country":"US",
    "sg:address":"3501 Shepherd Ln",
    "sg:city":"Balch Springs",
    "sg:classifiers":[
        {
            "category":"Organizations",
            "subcategory":"Professional Association",
            "type":"Services"
        }
    ],
    "sg:phone":"+1 972 913 5257",
    "sg:postcode":"75180",
    "sg:province":"TX",
    "wof:name":"Dallas County Sheriff's Assn",
    "wof:placetype":"venue"
},
  "geometry": {"coordinates":[-96.61412900000001,32.722079],"type":"Point"}
}