{
  "type": "Feature",
  "properties": {
    "iso:country":"US",
    "sg:address":"5555 N Lamar Blvd Ste C111",
    "sg:city":"Austin",
    "sg:classifiers":[
        {
            "category":"Banks & Credit Unions",
            "subcategory":"Financial Services",
            "type":"Services"
        }
    ],
    "sg:phone":"+1 512 837 5000",
    "sg:postcode":"78751",
    "sg:province":"TX",
    "sg:tags":[
        "broker",
        "mortgage"
    ],
    "wof:name":"C M J Lending",
    "wof:placetype":"venue"
},
  "geometry": {"coordinates":[-97.72782599999999,30.323222],"type":"Point"}
}