{
  "type": "Feature",
  "properties": {
    "iso:country":"US",
    "sg:address":"580 Flat Ct",
    "sg:city":"Waxahachie",
    "sg:classifiers":[
        {
            "category":"Building & Trades",
            "subcategory":"Cleaning & Sanitation",
            "type":"Services"
        }
    ],
    "sg:phone":"+1 972 435 1716",
    "sg:postcode":"75167",
    "sg:province":"TX",
    "sg:tags":[
        "maintenance"
    ],
    "wof:name":"All Pro Carpet & Wood Flooring",
    "wof:placetype":"venue"
},
  "geometry": {"coordinates":[-96.98119800000001,32.333064],"type":"Point"}
}