{
  "type": "Feature",
  "properties": {
    "iso:country":"US",
    "sg:address":"800 W Airport Fwy Ste 918",
    "sg:city":"Irving",
    "sg:classifiers":[
        {
            "category":"Professional",
            "subcategory":"Accounting & Tax Preparation",
            "type":"Services"
        }
    ],
    "sg:phone":"+1 972 579 9590",
    "sg:postcode":"75062",
    "sg:province":"TX",
    "sg:tags":[
        "accountant"
    ],
    "wof:name":"Brasch Bill CPA",
    "wof:placetype":"venue"
},
  "geometry": {"coordinates":[-96.96109800000001,32.837299],"type":"Point"}
}