{
  "type": "Feature",
  "properties": {
    "iso:country":"US",
    "sg:address":"1601 11th St",
    "sg:city":"Galena Park",
    "sg:classifiers":[
        {
            "category":"Education",
            "subcategory":"School",
            "type":"Public Place"
        }
    ],
    "sg:phone":"+1 713 670 9492",
    "sg:postcode":"77547",
    "sg:province":"TX",
    "wof:name":"Galena Park Independent School",
    "wof:placetype":"venue"
},
  "geometry": {"coordinates":[-95.237978,29.740484],"type":"Point"}
}