{
  "type": "Feature",
  "properties": {
    "iso:country":"US",
    "sg:address":"6550 Fannin St Ste 2403",
    "sg:city":"Houston",
    "sg:classifiers":[
        {
            "category":"Health Services",
            "subcategory":"Doctor",
            "type":"Services"
        }
    ],
    "sg:phone":"+1 713 790 6250",
    "sg:postcode":"77030",
    "sg:province":"TX",
    "wof:name":"Bloom Kim MD",
    "wof:placetype":"venue"
},
  "geometry": {"coordinates":[-95.400002,29.711201],"type":"Point"}
}