{
  "type": "Feature",
  "properties": {
    "iso:country":"US",
    "sg:address":"512 S Nebraska Ave",
    "sg:city":"Weslaco",
    "sg:classifiers":[
        {
            "category":"Professional",
            "subcategory":"Accounting & Tax Preparation",
            "type":"Services"
        }
    ],
    "sg:phone":"+1 956 782 7513",
    "sg:postcode":"78596",
    "sg:province":"TX",
    "sg:tags":[
        "bookkeeping",
        "general"
    ],
    "wof:name":"Cepeda Bookkeeping & Tax Svc",
    "wof:placetype":"venue"
},
  "geometry": {"coordinates":[-97.992723,26.156831],"type":"Point"}
}