{
  "type": "Feature",
  "properties": {
    "iso:country":"US",
    "sg:address":"306 McNee Dr",
    "sg:city":"Henderson",
    "sg:classifiers":[
        {
            "category":"Shopping",
            "subcategory":"Discount & Variety Stores",
            "type":"Retail Goods"
        }
    ],
    "sg:phone":"+1 903 657 6303",
    "sg:postcode":"75654",
    "sg:province":"TX",
    "sg:tags":[
        "merchandise",
        "general"
    ],
    "wof:name":"Morningstar Satellite",
    "wof:placetype":"venue"
},
  "geometry": {"coordinates":[-94.796308,32.145184],"type":"Point"}
}