{
  "type": "Feature",
  "properties": {
    "iso:country":"US",
    "sg:address":"6010 W Parmer Ln",
    "sg:city":"Austin",
    "sg:classifiers":[
        {
            "category":"Restaurant",
            "type":"Food & Drink"
        }
    ],
    "sg:menulink":"http://www.allmenus.com/tx/austin/202107-mcdonalds/menu/",
    "sg:postcode":"78727",
    "sg:province":"TX",
    "sg:tags":[
        "burger",
        "american"
    ],
    "wof:name":"McDonald's",
    "wof:placetype":"venue"
},
  "geometry": {"coordinates":[-97.741088,30.443381],"type":"Point"}
}