{
  "type": "Feature",
  "properties": {
    "iso:country":"US",
    "sg:address":"8215 FM 1488",
    "sg:city":"Magnolia",
    "sg:classifiers":[
        {
            "category":"Home & Garden",
            "subcategory":"Mobile Homes",
            "type":"Retail Goods"
        }
    ],
    "sg:phone":"+1 281 259 0099",
    "sg:postcode":"77384",
    "sg:province":"TX",
    "wof:name":"Millennium Mobile Homes Inc",
    "wof:placetype":"venue"
},
  "geometry": {"coordinates":[-95.513958,30.229226],"type":"Point"}
}