{
  "type": "Feature",
  "properties": {
    "iso:country":"US",
    "sg:address":"655 Martin Luther King Jr Dr",
    "sg:city":"Paris",
    "sg:classifiers":[
        {
            "category":"Education",
            "subcategory":"School",
            "type":"Public Place"
        }
    ],
    "sg:phone":"+1 903 737 7466",
    "sg:postcode":"75460",
    "sg:province":"TX",
    "wof:name":"Givens Elementary School",
    "wof:placetype":"venue"
},
  "geometry": {"coordinates":[-95.55045800000001,33.672754],"type":"Point"}
}