{
  "type": "Feature",
  "properties": {
    "iso:country":"US",
    "sg:address":"6701 Lakeshore Dr",
    "sg:city":"Dallas",
    "sg:classifiers":[
        {
            "category":"Manufacturing",
            "subcategory":"Retail Goods",
            "type":"Manufacturing & Wholesale Goods"
        }
    ],
    "sg:phone":"+1 214 827 3297",
    "sg:postcode":"75214",
    "sg:province":"TX",
    "sg:tags":[
        "product",
        "mfg"
    ],
    "wof:name":"Ralphanas",
    "wof:placetype":"venue"
},
  "geometry": {"coordinates":[-96.742711,32.820847],"type":"Point"}
}