{
  "type": "Feature",
  "properties": {
    "iso:country":"US",
    "sg:address":"6905 Mitchell Pkwy",
    "sg:city":"Arlington",
    "sg:classifiers":[
        {
            "category":"Building & Trades",
            "subcategory":"Construction",
            "type":"Services"
        }
    ],
    "sg:phone":"+1 817 417 9700",
    "sg:postcode":"76002",
    "sg:province":"TX",
    "sg:tags":[
        "utility",
        "contractor"
    ],
    "wof:name":"Area Excavation & Utility",
    "wof:placetype":"venue"
},
  "geometry": {"coordinates":[-97.07983400000001,32.627832],"type":"Point"}
}