{
  "type": "Feature",
  "properties": {
    "iso:country":"US",
    "sg:address":"404 Audrey St",
    "sg:city":"Whitehouse",
    "sg:classifiers":[
        {
            "category":"Health Services",
            "subcategory":"Clinic",
            "type":"Services"
        }
    ],
    "sg:phone":"+1 903 509 5719",
    "sg:postcode":"75791",
    "sg:province":"TX",
    "wof:name":"Ricky McFaddin",
    "wof:placetype":"venue"
},
  "geometry": {"coordinates":[-95.218588,32.231293],"type":"Point"}
}