{
  "type": "Feature",
  "properties": {
    "iso:country":"US",
    "sg:address":"14408 Maquila Loop",
    "sg:city":"Laredo",
    "sg:classifiers":[
        {
            "category":"Professional",
            "subcategory":"Computer Services",
            "type":"Services"
        }
    ],
    "sg:phone":"+1 956 727 3400",
    "sg:postcode":"78045",
    "sg:province":"TX",
    "sg:tags":[
        "consultant",
        "designer"
    ],
    "wof:name":"CAT Control Inc",
    "wof:placetype":"venue"
},
  "geometry": {"coordinates":[-99.530579,27.632084],"type":"Point"}
}