{
  "type": "Feature",
  "properties": {
    "iso:country":"US",
    "sg:address":"9034 Alameda Ave",
    "sg:city":"El Paso",
    "sg:classifiers":[
        {
            "category":"Retail",
            "subcategory":"Laundry & Dry Cleaning",
            "type":"Services"
        }
    ],
    "sg:phone":"+1 915 859 7021",
    "sg:postcode":"79907",
    "sg:province":"TX",
    "sg:tags":[
        "cleaners"
    ],
    "wof:name":"Paso Modern Cleaners",
    "wof:placetype":"venue"
},
  "geometry": {"coordinates":[-106.328563,31.692049],"type":"Point"}
}