{
  "type": "Feature",
  "properties": {
    "iso:country":"US",
    "sg:address":"300 Clarice St",
    "sg:city":"Grand Prairie",
    "sg:classifiers":[
        {
            "category":"Professional",
            "type":"Services"
        }
    ],
    "sg:phone":"+1 972 642 5607",
    "sg:postcode":"75051",
    "sg:province":"TX",
    "wof:name":"Nuga USA Inc",
    "wof:placetype":"venue"
},
  "geometry": {"coordinates":[-97.006896,32.73559],"type":"Point"}
}