{
  "type": "Feature",
  "properties": {
    "iso:country":"US",
    "sg:address":"6705 Levelland Rd",
    "sg:city":"Dallas",
    "sg:classifiers":[
        {
            "category":"Communications",
            "type":"Services"
        },
        {
            "category":"Professional",
            "subcategory":"Computer Services",
            "type":"Services"
        }
    ],
    "sg:phone":"+1 972 733 3390",
    "sg:postcode":"75252",
    "sg:province":"TX",
    "sg:tags":[
        "communication",
        "construction",
        "wiring"
    ],
    "sg:website":"www.nationwidenetwork.com",
    "wof:name":"Nationwide Network Tech",
    "wof:placetype":"venue"
},
  "geometry": {"coordinates":[-96.792666,32.98892],"type":"Point"}
}