{
  "type": "Feature",
  "properties": {
    "iso:country":"US",
    "sg:address":"7812 Tisdale Dr",
    "sg:city":"Austin",
    "sg:classifiers":[
        {
            "category":"Arts & Performance",
            "subcategory":"Arts Center",
            "type":"Entertainment"
        }
    ],
    "sg:phone":"+1 512 458 6087",
    "sg:postcode":"78757",
    "sg:province":"TX",
    "sg:tags":[
        "performing"
    ],
    "wof:name":"Odom Chester Ballroom & C-W Dance Instruction",
    "wof:placetype":"venue"
},
  "geometry": {"coordinates":[-97.7192,30.3505],"type":"Point"}
}