{
  "type": "Feature",
  "properties": {
    "iso:country":"US",
    "sg:address":"209 E Stadium St",
    "sg:city":"Kirbyville",
    "sg:classifiers":[
        {
            "category":"Organizations",
            "subcategory":"Community Association",
            "type":"Services"
        }
    ],
    "sg:phone":"+1 409 423 2115",
    "sg:postcode":"75956",
    "sg:province":"TX",
    "wof:name":"American Legion",
    "wof:placetype":"venue"
},
  "geometry": {"coordinates":[-93.89530499999999,30.648348],"type":"Point"}
}