{
  "type": "Feature",
  "properties": {
    "iso:country":"US",
    "sg:address":"8308 Sand Ridge Dr",
    "sg:city":"Plano",
    "sg:classifiers":[
        {
            "category":"Wholesale",
            "subcategory":"Toys & Hobbies",
            "type":"Manufacturing & Wholesale Goods"
        }
    ],
    "sg:phone":"+1 972 731 8667",
    "sg:postcode":"75025",
    "sg:province":"TX",
    "wof:name":"Puzzlepride",
    "wof:placetype":"venue"
},
  "geometry": {"coordinates":[-96.76008,33.09173],"type":"Point"}
}