{
  "type": "Feature",
  "properties": {
    "iso:country":"US",
    "sg:address":"7701 N Lamar Blvd",
    "sg:city":"Austin",
    "sg:classifiers":[
        {
            "category":"Health Services",
            "subcategory":"Clinic",
            "type":"Services"
        }
    ],
    "sg:phone":"+1 512 419 0003",
    "sg:postcode":"78752",
    "sg:province":"TX",
    "sg:tags":[
        "home"
    ],
    "wof:name":"Apicon Home Health Agcy Inc",
    "wof:placetype":"venue"
},
  "geometry": {"coordinates":[-97.712812,30.346504],"type":"Point"}
}