{
  "type": "Feature",
  "properties": {
    "iso:country":"US",
    "sg:address":"19511 Wied Rd",
    "sg:city":"Spring",
    "sg:classifiers":[
        {
            "category":"Manufacturing",
            "subcategory":"Metals",
            "type":"Manufacturing & Wholesale Goods"
        }
    ],
    "sg:phone":"+1 281 651 0200",
    "sg:postcode":"77388",
    "sg:province":"TX",
    "sg:tags":[
        "tubing"
    ],
    "sg:website":"http://www.coiltubingtechnology.com",
    "wof:name":"Coil Tubing Technology",
    "wof:placetype":"venue"
},
  "geometry": {"coordinates":[-95.47652100000001,30.0526],"type":"Point"}
}