{
  "type": "Feature",
  "properties": {
    "iso:country":"US",
    "sg:address":"715 E Whitney St",
    "sg:city":"Houston",
    "sg:classifiers":[
        {
            "category":"Professional",
            "subcategory":"Detective & Security Services",
            "type":"Services"
        }
    ],
    "sg:phone":"+1 713 692 2211",
    "sg:postcode":"77022",
    "sg:province":"TX",
    "sg:tags":[
        "system"
    ],
    "wof:name":"Superior Access Contrls Gates",
    "wof:placetype":"venue"
},
  "geometry": {"coordinates":[-95.388464,29.830761],"type":"Point"}
}