{
  "type": "Feature",
  "properties": {
    "iso:country":"US",
    "sg:address":"170 Cross Creek Rd",
    "sg:city":"Longview",
    "sg:classifiers":[
        {
            "category":"Building & Trades",
            "subcategory":"Construction",
            "type":"Services"
        }
    ],
    "sg:phone":"+1 903 660 3225",
    "sg:postcode":"75602",
    "sg:province":"TX",
    "sg:tags":[
        "contractor"
    ],
    "wof:name":"Harris Roofing Construction",
    "wof:placetype":"venue"
},
  "geometry": {"coordinates":[-94.61615399999999,32.46488],"type":"Point"}
}