{
  "type": "Feature",
  "properties": {
    "iso:country":"US",
    "sg:address":"2110 N Brazosport Blvd",
    "sg:city":"Freeport",
    "sg:classifiers":[
        {
            "category":"Freight",
            "type":"Transportation"
        }
    ],
    "sg:phone":"+1 979 239 1013",
    "sg:postcode":"77541",
    "sg:province":"TX",
    "sg:tags":[
        "general"
    ],
    "wof:name":"Area Mini Storage",
    "wof:placetype":"venue"
},
  "geometry": {"coordinates":[-95.376875,28.982791],"type":"Point"}
}