{
  "type": "Feature",
  "properties": {
    "iso:country":"US",
    "sg:address":"16610 N Dallas Pkwy #2200",
    "sg:city":"Dallas",
    "sg:classifiers":[
        {
            "category":"Professional",
            "subcategory":"Management & Consulting",
            "type":"Services"
        },
        {
            "category":"Professional",
            "subcategory":"Art Services",
            "type":"Services"
        },
        {
            "category":"Communications",
            "type":"Services"
        },
        {
            "category":"Professional",
            "subcategory":"Engineering",
            "type":"Services"
        }
    ],
    "sg:phone":"+1 214 694 2162",
    "sg:postcode":"75248",
    "sg:province":"TX",
    "sg:tags":[
        "web",
        "graphic",
        "consultant",
        "environmental",
        "ecological",
        "design",
        "engineer"
    ],
    "sg:website":"http://www.magiclogix.com",
    "wof:name":"Magic Logix",
    "wof:placetype":"venue"
},
  "geometry": {"coordinates":[-96.82170499999999,32.975098],"type":"Point"}
}