{
  "type": "Feature",
  "properties": {
    "iso:country":"US",
    "sg:address":"4222 Bobbitt Dr",
    "sg:city":"Dallas",
    "sg:classifiers":[
        {
            "category":"Professional",
            "subcategory":"Lawyer & Legal Services",
            "type":"Services"
        }
    ],
    "sg:phone":"+1 214 956 7447",
    "sg:postcode":"75229",
    "sg:province":"TX",
    "wof:name":"Hutchinson Clifton T Atty",
    "wof:placetype":"venue"
},
  "geometry": {"coordinates":[-96.837402,32.897202],"type":"Point"}
}