{
  "type": "Feature",
  "properties": {
    "iso:country":"US",
    "sg:address":"413 Baywood St",
    "sg:city":"La Porte",
    "sg:classifiers":[
        {
            "category":"Retail",
            "subcategory":"Repair Shop",
            "type":"Services"
        }
    ],
    "sg:phone":"+1 281 470 7478",
    "sg:postcode":"77571",
    "sg:province":"TX",
    "sg:tags":[
        "scooter",
        "motorcycle",
        "motor"
    ],
    "wof:name":"M G Cycleworks",
    "wof:placetype":"venue"
},
  "geometry": {"coordinates":[-95.01106900000001,29.61743],"type":"Point"}
}