{
  "type": "Feature",
  "properties": {
    "iso:country":"US",
    "sg:address":"1604 Bessie St",
    "sg:city":"Fort Worth",
    "sg:classifiers":[
        {
            "category":"Organizations",
            "subcategory":"Religious Organization",
            "type":"Services"
        }
    ],
    "sg:phone":"+1 817 293 7508",
    "sg:postcode":"76104",
    "sg:province":"TX",
    "wof:name":"New Beginning Holiness Church",
    "wof:placetype":"venue"
},
  "geometry": {"coordinates":[-97.304785,32.740129],"type":"Point"}
}