{
  "type": "Feature",
  "properties": {
    "iso:country":"US",
    "sg:address":"2626 S Padre Island Dr",
    "sg:city":"Corpus Christi",
    "sg:classifiers":[
        {
            "category":"Shopping",
            "type":"Retail Goods"
        }
    ],
    "sg:phone":"+1 361 225 0700",
    "sg:postcode":"78415",
    "sg:province":"TX",
    "sg:tags":[
        "fixture",
        "merchandise",
        "store"
    ],
    "wof:name":"Texas Store Fixtures-Supplies",
    "wof:placetype":"venue"
},
  "geometry": {"coordinates":[-97.420554,27.732705],"type":"Point"}
}