{
  "type": "Feature",
  "properties": {
    "iso:country":"US",
    "sg:address":"3701 W Alabama St Ste 353",
    "sg:city":"Houston",
    "sg:classifiers":[
        {
            "category":"Shopping",
            "subcategory":"Florist",
            "type":"Retail Goods"
        }
    ],
    "sg:phone":"+1 713 532 6100",
    "sg:postcode":"77027",
    "sg:province":"TX",
    "sg:website":"www.somethingspecialinflowers.com",
    "wof:name":"Something Special In Flowers",
    "wof:placetype":"venue"
},
  "geometry": {"coordinates":[-95.43661,29.738122],"type":"Point"}
}