{
  "type": "Feature",
  "properties": {
    "iso:country":"US",
    "sg:address":"706 Van Buren St",
    "sg:city":"Wichita Falls",
    "sg:classifiers":[
        {
            "category":"Social Services",
            "subcategory":"Child Care",
            "type":"Services"
        }
    ],
    "sg:phone":"+1 940 723 0116",
    "sg:postcode":"76301",
    "sg:province":"TX",
    "wof:name":"Jack & Jill Day Care Ctr",
    "wof:placetype":"venue"
},
  "geometry": {"coordinates":[-98.510384,33.905958],"type":"Point"}
}