{
  "type": "Feature",
  "properties": {
    "iso:country":"US",
    "sg:address":"1406 W Randol Mill Rd",
    "sg:city":"Arlington",
    "sg:classifiers":[
        {
            "category":"Health Services",
            "subcategory":"Chiropractor",
            "type":"Services"
        }
    ],
    "sg:phone":"+1 817 275 7288",
    "sg:postcode":"76012",
    "sg:province":"TX",
    "sg:tags":[
        "chiropractic"
    ],
    "wof:name":"Garlington Glen DC",
    "wof:placetype":"venue"
},
  "geometry": {"coordinates":[-97.12679300000001,32.750198],"type":"Point"}
}