{
  "type": "Feature",
  "properties": {
    "iso:country":"US",
    "sg:address":"1416 Chesterton Dr",
    "sg:city":"Richardson",
    "sg:classifiers":[
        {
            "category":"Professional",
            "subcategory":"Management & Consulting",
            "type":"Services"
        }
    ],
    "sg:phone":"+1 972 231 7725",
    "sg:postcode":"75080",
    "sg:province":"TX",
    "wof:name":"John A Green Company",
    "wof:placetype":"venue"
},
  "geometry": {"coordinates":[-96.765799,32.974835],"type":"Point"}
}