{
  "type": "Feature",
  "properties": {
    "iso:country":"US",
    "sg:address":"4130 Turnberry Cir",
    "sg:city":"Houston",
    "sg:classifiers":[
        {
            "category":"Professional",
            "type":"Services"
        }
    ],
    "sg:phone":"+1 713 787 1924",
    "sg:postcode":"77025",
    "sg:province":"TX",
    "wof:name":"Bill R Frazer",
    "wof:placetype":"venue"
},
  "geometry": {"coordinates":[-95.44415100000001,29.700677],"type":"Point"}
}