{
  "type": "Feature",
  "properties": {
    "iso:country":"US",
    "sg:address":"6711 Gleneagles Dr",
    "sg:city":"Pasadena",
    "sg:classifiers":[
        {
            "category":"Building & Trades",
            "subcategory":"Construction",
            "type":"Services"
        }
    ],
    "sg:phone":"+1 281 998 0384",
    "sg:postcode":"77505",
    "sg:province":"TX",
    "sg:tags":[
        "residential"
    ],
    "wof:name":"CMC Construction",
    "wof:placetype":"venue"
},
  "geometry": {"coordinates":[-95.135265,29.641697],"type":"Point"}
}