{
  "type": "Feature",
  "properties": {
    "iso:country":"US",
    "sg:address":"4101 James Casey St",
    "sg:city":"Austin",
    "sg:classifiers":[
        {
            "category":"Health Services",
            "subcategory":"Doctor",
            "type":"Services"
        }
    ],
    "sg:phone":"+1 512 447 6058",
    "sg:postcode":"78745",
    "sg:province":"TX",
    "sg:tags":[
        "medical",
        "hospital",
        "specialty"
    ],
    "wof:name":"South Austin Cancer Center",
    "wof:placetype":"venue"
},
  "geometry": {"coordinates":[-97.775719,30.222417],"type":"Point"}
}