{
  "type": "Feature",
  "properties": {
    "iso:country":"US",
    "sg:address":"7902 Matson St",
    "sg:city":"Houston",
    "sg:classifiers":[
        {
            "category":"Building & Trades",
            "subcategory":"Construction",
            "type":"Services"
        }
    ],
    "sg:phone":"+1 713 631 6500",
    "sg:postcode":"77078",
    "sg:province":"TX",
    "sg:tags":[
        "home",
        "builder"
    ],
    "wof:name":"Amenity Plus Homes Inc",
    "wof:placetype":"venue"
},
  "geometry": {"coordinates":[-95.281734,29.855387],"type":"Point"}
}