{
  "type": "Feature",
  "properties": {
    "iso:country":"US",
    "sg:address":"803 E Cherry St",
    "sg:city":"Duncanville",
    "sg:classifiers":[
        {
            "category":"Building & Trades",
            "subcategory":"Construction",
            "type":"Services"
        }
    ],
    "sg:phone":"+1 972 283 4929",
    "sg:postcode":"75116",
    "sg:province":"TX",
    "sg:tags":[
        "contractor"
    ],
    "wof:name":"R Lamkin and Associates",
    "wof:placetype":"venue"
},
  "geometry": {"coordinates":[-96.894507,32.653346],"type":"Point"}
}