{
  "type": "Feature",
  "properties": {
    "iso:country":"US",
    "sg:address":"712 Kurth Dr",
    "sg:city":"Lufkin",
    "sg:classifiers":[
        {
            "category":"Retail",
            "subcategory":"Car Wash",
            "type":"Services"
        }
    ],
    "sg:phone":"+1 936 634 2442",
    "sg:postcode":"75904",
    "sg:province":"TX",
    "sg:tags":[
        "polishing",
        "washing"
    ],
    "wof:name":"Nate's Detail",
    "wof:placetype":"venue"
},
  "geometry": {"coordinates":[-94.729011,31.355427],"type":"Point"}
}