{
  "type": "Feature",
  "properties": {
    "iso:country":"US",
    "sg:address":"7600 Burnet Rd Ste 380",
    "sg:city":"Austin",
    "sg:classifiers":[
        {
            "category":"Professional",
            "subcategory":"Employment Agencies",
            "type":"Services"
        }
    ],
    "sg:phone":"+1 512 302 3373",
    "sg:postcode":"78757",
    "sg:province":"TX",
    "wof:name":"H L Yoh Company",
    "wof:placetype":"venue"
},
  "geometry": {"coordinates":[-97.733002,30.3526],"type":"Point"}
}