{
  "type": "Feature",
  "properties": {
    "iso:country":"US",
    "sg:address":"1203 N Ave F",
    "sg:city":"Freeport",
    "sg:classifiers":[
        {
            "category":"Shopping",
            "subcategory":"Used Merchandise",
            "type":"Retail Goods"
        }
    ],
    "sg:phone":"+1 979 233 1219",
    "sg:postcode":"77541",
    "sg:province":"TX",
    "wof:name":"Kays Collectibles & Resales",
    "wof:placetype":"venue"
},
  "geometry": {"coordinates":[-95.370812,28.97048],"type":"Point"}
}