{
  "type": "Feature",
  "properties": {
    "iso:country":"US",
    "sg:address":"7681 Clarewood Dr",
    "sg:city":"Houston",
    "sg:classifiers":[
        {
            "category":"Personal",
            "type":"Services"
        }
    ],
    "sg:phone":"+1 713 271 5517",
    "sg:postcode":"77036",
    "sg:province":"TX",
    "sg:tags":[
        "sewing",
        "alteration"
    ],
    "wof:name":"Van Thanh Tailor Shop",
    "wof:placetype":"venue"
},
  "geometry": {"coordinates":[-95.521103,29.709299],"type":"Point"}
}