{
  "type": "Feature",
  "properties": {
    "iso:country":"US",
    "sg:address":"2209 E Mulberry St",
    "sg:city":"Angleton",
    "sg:classifiers":[
        {
            "category":"Travel",
            "subcategory":"Hotels & Motels",
            "type":"Entertainment"
        }
    ],
    "sg:phone":"+1 979 849 4402",
    "sg:postcode":"77515",
    "sg:province":"TX",
    "wof:name":"Longhorn Motel",
    "wof:placetype":"venue"
},
  "geometry": {"coordinates":[-95.410359,29.181748],"type":"Point"}
}