{
  "type": "Feature",
  "properties": {
    "iso:country":"US",
    "sg:address":"2615 Marietta Dr",
    "sg:city":"Dallas",
    "sg:classifiers":[
        {
            "category":"Building & Trades",
            "subcategory":"Cleaning & Sanitation",
            "type":"Services"
        }
    ],
    "sg:phone":"+1 972 406 3262",
    "sg:postcode":"75234",
    "sg:province":"TX",
    "sg:tags":[
        "maintenance"
    ],
    "wof:name":"White Dove Housekeeping",
    "wof:placetype":"venue"
},
  "geometry": {"coordinates":[-96.88787499999999,32.921197],"type":"Point"}
}