{
  "type": "Feature",
  "properties": {
    "iso:country":"US",
    "sg:address":"4331 Spectrum One",
    "sg:city":"San Antonio",
    "sg:classifiers":[
        {
            "category":"Travel",
            "subcategory":"Hotels & Motels",
            "type":"Entertainment"
        }
    ],
    "sg:phone":"+1 210 694 1229",
    "sg:postcode":"78230",
    "sg:province":"TX",
    "sg:tags":[
        "operations"
    ],
    "wof:name":"Studioplus 6083",
    "wof:placetype":"venue"
},
  "geometry": {"coordinates":[-98.566417,29.536586],"type":"Point"}
}