{
  "type": "Feature",
  "properties": {
    "iso:country":"US",
    "sg:address":"1255 N Main St",
    "sg:city":"Vidor",
    "sg:classifiers":[
        {
            "category":"Banks & Credit Unions",
            "subcategory":"Bank",
            "type":"Services"
        }
    ],
    "sg:phone":"+1 409 951 1667",
    "sg:postcode":"77662",
    "sg:province":"TX",
    "wof:name":"Hibernia National Bank",
    "wof:placetype":"venue"
},
  "geometry": {"coordinates":[-94.015764,30.141787],"type":"Point"}
}