{
  "type": "Feature",
  "properties": {
    "iso:country":"US",
    "sg:address":"2305 E 28th St",
    "sg:city":"Mission",
    "sg:classifiers":[
        {
            "category":"Banks & Credit Unions",
            "subcategory":"Financial Services",
            "type":"Services"
        }
    ],
    "sg:phone":"+1 956 580 1191",
    "sg:postcode":"78574",
    "sg:province":"TX",
    "sg:tags":[
        "investor"
    ],
    "wof:name":"Deringer Investments",
    "wof:placetype":"venue"
},
  "geometry": {"coordinates":[-98.28115,26.233393],"type":"Point"}
}