{
  "type": "Feature",
  "properties": {
    "iso:country":"US",
    "sg:address":"3355 Bee Caves Rd",
    "sg:city":"Austin",
    "sg:classifiers":[
        {
            "category":"Professional",
            "subcategory":"Research",
            "type":"Services"
        }
    ],
    "sg:phone":"+1 512 329 0031",
    "sg:postcode":"78746",
    "sg:province":"TX",
    "sg:tags":[
        "environmental",
        "ecological"
    ],
    "sg:website":"www.ecommcorporation.com",
    "wof:name":"Ecological Communication Corp",
    "wof:placetype":"venue"
},
  "geometry": {"coordinates":[-97.80255099999999,30.276041],"type":"Point"}
}