{
  "type": "Feature",
  "properties": {
    "iso:country":"US",
    "sg:address":"512 Milam Dr",
    "sg:city":"Euless",
    "sg:classifiers":[
        {
            "category":"Building & Trades",
            "subcategory":"Landscaping Services",
            "type":"Services"
        }
    ],
    "sg:phone":"+1 817 283 7563",
    "sg:postcode":"76039",
    "sg:province":"TX",
    "wof:name":"Hurley Landscape Management",
    "wof:placetype":"venue"
},
  "geometry": {"coordinates":[-97.08865,32.844095],"type":"Point"}
}