{
  "type": "Feature",
  "properties": {
    "iso:country":"US",
    "sg:address":"2916 Texas Blvd",
    "sg:city":"Texarkana",
    "sg:classifiers":[
        {
            "category":"Manufacturing",
            "subcategory":"Printing",
            "type":"Manufacturing & Wholesale Goods"
        }
    ],
    "sg:phone":"+1 903 792 3462",
    "sg:postcode":"75503",
    "sg:province":"TX",
    "sg:tags":[
        "commercial"
    ],
    "wof:name":"Alaska Printing Co",
    "wof:placetype":"venue"
},
  "geometry": {"coordinates":[-94.05299100000001,33.444852],"type":"Point"}
}