{
  "type": "Feature",
  "properties": {
    "iso:country":"US",
    "sg:address":"119 N Emberwood Dr",
    "sg:city":"Waco",
    "sg:classifiers":[
        {
            "category":"Professional",
            "type":"Services"
        }
    ],
    "sg:phone":"+1 254 662 5188",
    "sg:postcode":"76706",
    "sg:province":"TX",
    "wof:name":"Kerry B Kurtz",
    "wof:placetype":"venue"
},
  "geometry": {"coordinates":[-97.11517600000001,31.474602],"type":"Point"}
}