{
  "type": "Feature",
  "properties": {
    "iso:country":"US",
    "sg:address":"223 W 6th St",
    "sg:city":"Austin",
    "sg:classifiers":[
        {
            "category":"Real Estate",
            "subcategory":"Real Estate Services",
            "type":"Services"
        },
        {
            "category":"Structure",
            "subcategory":"Office Building",
            "type":"Public Place"
        }
    ],
    "sg:phone":"+1 512 501 2026",
    "sg:postcode":"78701",
    "sg:province":"TX",
    "sg:tags":[
        "space",
        "rental",
        "desk"
    ],
    "sg:website":"officespaceaustintx.com",
    "wof:name":"Office Space Austin TX",
    "wof:placetype":"venue"
},
  "geometry": {"coordinates":[-97.744693,30.268558],"type":"Point"}
}