{
  "type": "Feature",
  "properties": {
    "iso:country":"US",
    "sg:address":"4405 San Fernando Ln",
    "sg:city":"Mc Kinney",
    "sg:classifiers":[
        {
            "category":"Professional",
            "type":"Services"
        }
    ],
    "sg:phone":"+1 972 562 2419",
    "sg:postcode":"75070",
    "sg:province":"TX",
    "wof:name":"Wahakas Wares",
    "wof:placetype":"venue"
},
  "geometry": {"coordinates":[-96.669831,33.159615],"type":"Point"}
}