{
  "type": "Feature",
  "properties": {
    "iso:country":"US",
    "sg:address":"753 N Goode Rd",
    "sg:city":"Wilmer",
    "sg:classifiers":[
        {
            "category":"Restaurant",
            "type":"Food & Drink"
        }
    ],
    "sg:phone":"+1 972 441 3500",
    "sg:postcode":"75172",
    "sg:province":"TX",
    "sg:tags":[
        "eating"
    ],
    "wof:name":"Red Dog The",
    "wof:placetype":"venue"
},
  "geometry": {"coordinates":[-96.680559,32.599567],"type":"Point"}
}