{
  "type": "Feature",
  "properties": {
    "iso:country":"US",
    "sg:address":"23102 Harpergate Dr",
    "sg:city":"Spring",
    "sg:classifiers":[
        {
            "category":"Professional",
            "type":"Services"
        }
    ],
    "sg:phone":"+1 281 847 9322",
    "sg:postcode":"77373",
    "sg:province":"TX",
    "wof:name":"Nso Consutling Services",
    "wof:placetype":"venue"
},
  "geometry": {"coordinates":[-95.36337399999999,30.042057],"type":"Point"}
}