{
  "type": "Feature",
  "properties": {
    "iso:country":"US",
    "sg:address":"4801 Emmett F Lowry Expy",
    "sg:city":"Texas City",
    "sg:classifiers":[
        {
            "category":"Organizations",
            "subcategory":"Religious Organization",
            "type":"Services"
        }
    ],
    "sg:phone":"+1 409 935 7732",
    "sg:postcode":"77591",
    "sg:province":"TX",
    "sg:tags":[
        "church"
    ],
    "wof:name":"Church Of Christ-Mainland",
    "wof:placetype":"venue"
},
  "geometry": {"coordinates":[-94.969217,29.395318],"type":"Point"}
}