{
  "type": "Feature",
  "properties": {
    "iso:country":"US",
    "sg:address":"500 W Lookout Dr",
    "sg:city":"Richardson",
    "sg:classifiers":[
        {
            "category":"Professional",
            "type":"Services"
        }
    ],
    "sg:phone":"+1 214 239 9480",
    "sg:postcode":"75080",
    "sg:province":"TX",
    "sg:tags":[
        "establishment"
    ],
    "wof:name":"Dan Lee Assoc",
    "wof:placetype":"venue"
},
  "geometry": {"coordinates":[-96.727733,32.989508],"type":"Point"}
}