{
  "type": "Feature",
  "properties": {
    "iso:country":"US",
    "sg:address":"140 El Chanate Dr",
    "sg:city":"Canutillo",
    "sg:classifiers":[
        {
            "category":"Manufacturing",
            "subcategory":"Tools & Machinery",
            "type":"Manufacturing & Wholesale Goods"
        },
        {
            "category":"Manufacturing",
            "subcategory":"Building Materials",
            "type":"Manufacturing & Wholesale Goods"
        }
    ],
    "sg:phone":"+1 915 877 9106",
    "sg:postcode":"79835",
    "sg:province":"TX",
    "sg:tags":[
        "solid",
        "tools-electric",
        "maker",
        "surface",
        "die"
    ],
    "wof:name":"Doclan Of Texas",
    "wof:placetype":"venue"
},
  "geometry": {"coordinates":[-106.600555,31.923848],"type":"Point"}
}