{
  "type": "Feature",
  "properties": {
    "iso:country":"US",
    "sg:address":"2732 S Broadway Ave",
    "sg:city":"Tyler",
    "sg:classifiers":[
        {
            "category":"Health Services",
            "subcategory":"Optometrist",
            "type":"Services"
        }
    ],
    "sg:phone":"+1 903 597 9020",
    "sg:postcode":"75701",
    "sg:province":"TX",
    "wof:name":"Ronald N Smith OD",
    "wof:placetype":"venue"
},
  "geometry": {"coordinates":[-95.300707,32.316268],"type":"Point"}
}