{
  "type": "Feature",
  "properties": {
    "iso:country":"US",
    "sg:address":"12400 San Pedro Ave",
    "sg:city":"San Antonio",
    "sg:classifiers":[
        {
            "category":"Manufacturing",
            "subcategory":"Aerospace",
            "type":"Manufacturing & Wholesale Goods"
        }
    ],
    "sg:phone":"+1 210 495 7766",
    "sg:postcode":"78216",
    "sg:province":"TX",
    "sg:tags":[
        "aircraft"
    ],
    "wof:name":"Jaffe Group Inc",
    "wof:placetype":"venue"
},
  "geometry": {"coordinates":[-98.48589699999999,29.553576],"type":"Point"}
}