{
  "type": "Feature",
  "properties": {
    "iso:country":"US",
    "sg:address":"2828 Webb Chapel Exn",
    "sg:city":"Dallas",
    "sg:classifiers":[
        {
            "category":"Restaurant",
            "type":"Food & Drink"
        }
    ],
    "sg:phone":"+1 214 902 0313",
    "sg:postcode":"75220",
    "sg:province":"TX",
    "sg:tags":[
        "eating"
    ],
    "wof:name":"Lacondesa Restaurant & Marisqu",
    "wof:placetype":"venue"
},
  "geometry": {"coordinates":[-96.869913,32.857239],"type":"Point"}
}