{
  "type": "Feature",
  "properties": {
    "iso:country":"US",
    "sg:address":"104 Crescent St",
    "sg:city":"San Antonio",
    "sg:classifiers":[
        {
            "category":"Professional",
            "subcategory":"Employment Agencies",
            "type":"Services"
        }
    ],
    "sg:phone":"+1 210 829 8847",
    "sg:postcode":"78209",
    "sg:province":"TX",
    "sg:tags":[
        "help",
        "supply"
    ],
    "wof:name":"Deacon Medical Staffing Inc",
    "wof:placetype":"venue"
},
  "geometry": {"coordinates":[-98.471818,29.476591],"type":"Point"}
}