{
  "type": "Feature",
  "properties": {
    "iso:country":"US",
    "sg:address":"3400 Country Club Rd N",
    "sg:city":"Irving",
    "sg:classifiers":[
        {
            "category":"Social Services",
            "type":"Services"
        }
    ],
    "sg:phone":"+1 972 953 1366",
    "sg:postcode":"75062",
    "sg:province":"TX",
    "sg:tags":[
        "senior",
        "citizen"
    ],
    "wof:name":"Avalon Alzheimer's Care Home",
    "wof:placetype":"venue"
},
  "geometry": {"coordinates":[-96.97721199999999,32.852238],"type":"Point"}
}