{
  "type": "Feature",
  "properties": {
    "iso:country":"US",
    "sg:address":"2015 5th St",
    "sg:city":"Wichita Falls",
    "sg:classifiers":[
        {
            "category":"Freight",
            "type":"Transportation"
        }
    ],
    "sg:phone":"+1 940 720 3175",
    "sg:postcode":"76301",
    "sg:province":"TX",
    "sg:tags":[
        "general"
    ],
    "wof:name":"Warehouse",
    "wof:placetype":"venue"
},
  "geometry": {"coordinates":[-98.512119,33.909508],"type":"Point"}
}