{
  "type": "Feature",
  "properties": {
    "iso:country":"US",
    "sg:address":"430 S Mason Rd",
    "sg:city":"Katy",
    "sg:classifiers":[
        {
            "category":"Professional",
            "subcategory":"Printing & Photocopies",
            "type":"Services"
        }
    ],
    "sg:phone":"+1 281 395 0077",
    "sg:postcode":"77450",
    "sg:province":"TX",
    "sg:tags":[
        "photocopying",
        "lithographic",
        "commercial"
    ],
    "wof:name":"Kinkos",
    "wof:placetype":"venue"
},
  "geometry": {"coordinates":[-95.75187099999999,29.777913],"type":"Point"}
}