{
  "type": "Feature",
  "properties": {
    "iso:country":"US",
    "sg:address":"182 County Road 4679",
    "sg:city":"Boyd",
    "sg:classifiers":[
        {
            "category":"Insurance",
            "subcategory":"Hazard Insurance",
            "type":"Services"
        }
    ],
    "sg:phone":"+1 940 433 9931",
    "sg:postcode":"76023",
    "sg:province":"TX",
    "sg:tags":[
        "commercial",
        "business"
    ],
    "wof:name":"Alexander Insurance And Bonding",
    "wof:placetype":"venue"
},
  "geometry": {"coordinates":[-97.586215,33.062089],"type":"Point"}
}