{
  "type": "Feature",
  "properties": {
    "iso:country":"US",
    "sg:address":"3815 Antigua Dr",
    "sg:city":"Dallas",
    "sg:classifiers":[
        {
            "category":"Professional",
            "subcategory":"Management & Consulting",
            "type":"Services"
        }
    ],
    "sg:phone":"+1 972 484 2336",
    "sg:postcode":"75244",
    "sg:province":"TX",
    "sg:tags":[
        "s",
        "business",
        "furniture"
    ],
    "wof:name":"Schiska Joyce Designs",
    "wof:placetype":"venue"
},
  "geometry": {"coordinates":[-96.848327,32.919754],"type":"Point"}
}