{
  "type": "Feature",
  "properties": {
    "iso:country":"US",
    "sg:address":"1708 Lucas Ter",
    "sg:city":"Plano",
    "sg:classifiers":[
        {
            "category":"Professional",
            "subcategory":"Business Services",
            "type":"Services"
        }
    ],
    "sg:phone":"+1 972 578 9777",
    "sg:postcode":"75074",
    "sg:province":"TX",
    "sg:tags":[
        "pool",
        "swimming"
    ],
    "wof:name":"Ashley Pool & Spa Care",
    "wof:placetype":"venue"
},
  "geometry": {"coordinates":[-96.68907799999999,33.0373],"type":"Point"}
}