{
  "type": "Feature",
  "properties": {
    "iso:country":"US",
    "sg:address":"1200 W Highway 67",
    "sg:city":"Alvarado",
    "sg:classifiers":[
        {
            "category":"Restaurant",
            "type":"Food & Drink"
        }
    ],
    "sg:menulink":"http://www.allmenus.com/tx/alvarado/202932-mcdonalds/menu/",
    "sg:postcode":"76009",
    "sg:province":"TX",
    "sg:tags":[
        "burger",
        "american"
    ],
    "wof:name":"McDonald's",
    "wof:placetype":"venue"
},
  "geometry": {"coordinates":[-97.22562600000001,32.416355],"type":"Point"}
}