{
  "type": "Feature",
  "properties": {
    "iso:country":"US",
    "sg:address":"505 Barton Springs Rd Ste 1075",
    "sg:city":"Austin",
    "sg:classifiers":[
        {
            "category":"Real Estate",
            "subcategory":"Real Estate Services",
            "type":"Services"
        }
    ],
    "sg:phone":"+1 512 476 1700",
    "sg:postcode":"78704",
    "sg:province":"TX",
    "sg:tags":[
        "management",
        "property"
    ],
    "sg:website":"www.lpc.com",
    "wof:name":"Lincoln Property Co",
    "wof:placetype":"venue"
},
  "geometry": {"coordinates":[-97.749298,30.2584],"type":"Point"}
}