{
  "type": "Feature",
  "properties": {
    "iso:country":"US",
    "sg:address":"1560 South St",
    "sg:city":"Beaumont",
    "sg:classifiers":[
        {
            "category":"Building & Trades",
            "subcategory":"Plumbing",
            "type":"Services"
        }
    ],
    "sg:phone":"+1 409 832 4614",
    "sg:postcode":"77701",
    "sg:province":"TX",
    "sg:tags":[
        "sheet",
        "duct",
        "work",
        "metal",
        "air",
        "conditioning",
        "contractor"
    ],
    "wof:name":"S and L Sheet Metal & Services",
    "wof:placetype":"venue"
},
  "geometry": {"coordinates":[-94.11114999999999,30.082005],"type":"Point"}
}