{
  "type": "Feature",
  "properties": {
    "iso:country":"US",
    "sg:address":"8940 Alameda Ave",
    "sg:city":"El Paso",
    "sg:classifiers":[
        {
            "category":"Local Transit",
            "type":"Transportation"
        }
    ],
    "sg:phone":"+1 915 872 0908",
    "sg:postcode":"79907",
    "sg:province":"TX",
    "sg:tags":[
        "bus",
        "line"
    ],
    "wof:name":"Auto Buses Los Pisanos Inc",
    "wof:placetype":"venue"
},
  "geometry": {"coordinates":[-106.330675,31.692964],"type":"Point"}
}