{
  "type": "Feature",
  "properties": {
    "iso:country":"US",
    "sg:address":"1701 Oak Knoll Dr",
    "sg:city":"Colleyville",
    "sg:classifiers":[
        {
            "category":"Building & Trades",
            "subcategory":"Construction",
            "type":"Services"
        }
    ],
    "sg:phone":"+1 817 354 8780",
    "sg:postcode":"76034",
    "sg:province":"TX",
    "sg:tags":[
        "house"
    ],
    "wof:name":"Larry Gabel Remodeling",
    "wof:placetype":"venue"
},
  "geometry": {"coordinates":[-97.142019,32.874616],"type":"Point"}
}