{
  "type": "Feature",
  "properties": {
    "iso:country":"US",
    "sg:address":"15811 Tuckerton Rd",
    "sg:city":"Houston",
    "sg:classifiers":[
        {
            "category":"Retail",
            "subcategory":"Repair Shop",
            "type":"Services"
        }
    ],
    "sg:phone":"+1 713 681 5211",
    "sg:postcode":"77095",
    "sg:province":"TX",
    "sg:tags":[
        "equipment",
        "hydraulic"
    ],
    "wof:name":"Pneumatic & Hydraulic Company",
    "wof:placetype":"venue"
},
  "geometry": {"coordinates":[-95.645061,29.916395],"type":"Point"}
}