{
  "type": "Feature",
  "properties": {
    "iso:country":"US",
    "sg:address":"47 Viking St",
    "sg:city":"Port Lavaca",
    "sg:classifiers":[
        {
            "category":"Personal",
            "subcategory":"Barber",
            "type":"Services"
        }
    ],
    "sg:phone":"+1 361 552 5121",
    "sg:postcode":"77905",
    "sg:province":"TX",
    "sg:tags":[
        "shop"
    ],
    "wof:name":"Viking Barber Shop",
    "wof:placetype":"venue"
},
  "geometry": {"coordinates":[-96.91971700000001,28.829755],"type":"Point"}
}