{
  "type": "Feature",
  "properties": {
    "iso:country":"US",
    "sg:address":"7900 Lake June Rd",
    "sg:city":"Dallas",
    "sg:classifiers":[
        {
            "category":"Building & Trades",
            "subcategory":"Equipment Rental",
            "type":"Services"
        }
    ],
    "sg:phone":"+1 214 391 9678",
    "sg:postcode":"75217",
    "sg:province":"TX",
    "sg:tags":[
        "party",
        "supply"
    ],
    "wof:name":"Kelly's Party Rental",
    "wof:placetype":"venue"
},
  "geometry": {"coordinates":[-96.685996,32.734095],"type":"Point"}
}