{
  "type": "Feature",
  "properties": {
    "iso:country":"US",
    "sg:address":"2207 E Martin Luther King Jr Blvd",
    "sg:city":"Austin",
    "sg:classifiers":[
        {
            "category":"Organizations",
            "subcategory":"Non-profit Organization",
            "type":"Services"
        },
        {
            "category":"Health Services",
            "subcategory":"Hospital",
            "type":"Services"
        }
    ],
    "sg:phone":"+1 512 322 9234",
    "sg:postcode":"78702",
    "sg:province":"TX",
    "sg:tags":[
        "info",
        "specialty",
        "drug",
        "abuse",
        "treatment",
        "addiction"
    ],
    "sg:website":"www.na.org",
    "wof:name":"Miracles & Solutions",
    "wof:placetype":"venue"
},
  "geometry": {"coordinates":[-97.717311,30.280355],"type":"Point"}
}