{
  "type": "Feature",
  "properties": {
    "iso:country":"US",
    "sg:address":"1810 W FM 1462",
    "sg:city":"Rosharon",
    "sg:classifiers":[
        {
            "category":"Government",
            "subcategory":"Post Office",
            "type":"Public Place"
        }
    ],
    "sg:phone":"+1 281 369 2080",
    "sg:postcode":"77583",
    "sg:province":"TX",
    "wof:name":"United States Post Office",
    "wof:placetype":"venue"
},
  "geometry": {"coordinates":[-95.48921300000001,29.353313],"type":"Point"}
}