{
  "type": "Feature",
  "properties": {
    "iso:country":"US",
    "sg:address":"2925 Cliffridge Ln",
    "sg:city":"Fort Worth",
    "sg:classifiers":[
        {
            "category":"Professional",
            "subcategory":"Business Services",
            "type":"Services"
        }
    ],
    "sg:phone":"+1 817 244 5118",
    "sg:postcode":"76116",
    "sg:province":"TX",
    "wof:name":"Macrame By Louise",
    "wof:placetype":"venue"
},
  "geometry": {"coordinates":[-97.476393,32.733376],"type":"Point"}
}