{
  "type": "Feature",
  "properties": {
    "iso:country":"US",
    "sg:address":"103 Co Rd 3065",
    "sg:city":"Beckville",
    "sg:classifiers":[
        {
            "category":"Building & Trades",
            "subcategory":"Construction",
            "type":"Services"
        }
    ],
    "sg:phone":"+1 903 693 3595",
    "sg:postcode":"75631",
    "sg:province":"TX",
    "sg:tags":[
        "builder",
        "operative"
    ],
    "wof:name":"Hanna Contruction",
    "wof:placetype":"venue"
},
  "geometry": {"coordinates":[-94.342299,32.276754],"type":"Point"}
}