{
  "type": "Feature",
  "properties": {
    "iso:country":"US",
    "sg:address":"809 Jefferson Ave",
    "sg:city":"Waco",
    "sg:classifiers":[
        {
            "category":"Retail",
            "subcategory":"Auto Repair",
            "type":"Services"
        }
    ],
    "sg:phone":"+1 254 753 6791",
    "sg:postcode":"76701",
    "sg:province":"TX",
    "sg:tags":[
        "repairing",
        "automobile",
        "general"
    ],
    "wof:name":"Tip Automotive",
    "wof:placetype":"venue"
},
  "geometry": {"coordinates":[-97.138661,31.556599],"type":"Point"}
}