{
  "type": "Feature",
  "properties": {
    "iso:country":"US",
    "sg:address":"4721 Bryson Ln",
    "sg:city":"Midlothian",
    "sg:classifiers":[
        {
            "category":"Building & Trades",
            "subcategory":"Construction",
            "type":"Services"
        }
    ],
    "sg:phone":"+1 972 723 8525",
    "sg:postcode":"76065",
    "sg:province":"TX",
    "sg:tags":[
        "operations",
        "crane"
    ],
    "wof:name":"Byrum Crane & Sign Services",
    "wof:placetype":"venue"
},
  "geometry": {"coordinates":[-96.896106,32.528874],"type":"Point"}
}