{
  "type": "Feature",
  "properties": {
    "iso:country":"US",
    "sg:address":"1002 N Flores St",
    "sg:city":"San Antonio",
    "sg:classifiers":[
        {
            "category":"Insurance",
            "subcategory":"Insurance Agent",
            "type":"Services"
        }
    ],
    "sg:phone":"+1 210 615 1419",
    "sg:postcode":"78212",
    "sg:province":"TX",
    "sg:tags":[
        "adjuster"
    ],
    "wof:name":"Baggett Claim Svc",
    "wof:placetype":"venue"
},
  "geometry": {"coordinates":[-98.50059,29.435676],"type":"Point"}
}