{
  "type": "Feature",
  "properties": {
    "iso:country":"US",
    "sg:address":"720 Avocet Ave",
    "sg:city":"Mcallen",
    "sg:classifiers":[
        {
            "category":"Manufacturing",
            "subcategory":"Chemicals & Compounds",
            "type":"Manufacturing & Wholesale Goods"
        }
    ],
    "sg:phone":"+1 956 630 4410",
    "sg:postcode":"78504",
    "sg:province":"TX",
    "sg:tags":[
        "inorganic",
        "industrial",
        "mfg"
    ],
    "wof:name":"Dupont",
    "wof:placetype":"venue"
},
  "geometry": {"coordinates":[-98.219262,26.250305],"type":"Point"}
}