{
  "type": "Feature",
  "properties": {
    "iso:country":"US",
    "sg:address":"4010 Essex Ln",
    "sg:city":"Houston",
    "sg:classifiers":[
        {
            "category":"Shopping",
            "subcategory":"Clothing, Apparel, & Fashions",
            "type":"Retail Goods"
        }
    ],
    "sg:phone":"+1 713 960 1057",
    "sg:postcode":"77027",
    "sg:province":"TX",
    "wof:name":"Estelle M Lozmack",
    "wof:placetype":"venue"
},
  "geometry": {"coordinates":[-95.447315,29.739756],"type":"Point"}
}