{
  "type": "Feature",
  "properties": {
    "iso:country":"US",
    "sg:address":"911 E McDonald St",
    "sg:city":"Mineola",
    "sg:classifiers":[
        {
            "category":"Real Estate",
            "subcategory":"Developer",
            "type":"Services"
        }
    ],
    "sg:phone":"+1 903 569 6127",
    "sg:postcode":"75773",
    "sg:province":"TX",
    "wof:name":"Stewart Properties",
    "wof:placetype":"venue"
},
  "geometry": {"coordinates":[-95.476541,32.666744],"type":"Point"}
}