{
  "type": "Feature",
  "properties": {
    "iso:country":"US",
    "sg:address":"1707 Grey Fox Trl",
    "sg:city":"Killeen",
    "sg:classifiers":[
        {
            "category":"Shopping",
            "subcategory":"Jewelry",
            "type":"Retail Goods"
        },
        {
            "category":"Manufacturing",
            "subcategory":"Jewelry",
            "type":"Manufacturing & Wholesale Goods"
        }
    ],
    "sg:phone":"+1 254 953 4902",
    "sg:postcode":"76543",
    "sg:province":"TX",
    "sg:tags":[
        "designer",
        "jeweler"
    ],
    "wof:name":"Perry's Elegant Diamond Illusions",
    "wof:placetype":"venue"
},
  "geometry": {"coordinates":[-97.705282,31.093314],"type":"Point"}
}