{
  "type": "Feature",
  "properties": {
    "iso:country":"US",
    "sg:address":"3404 Richmond Rd",
    "sg:city":"Texarkana",
    "sg:classifiers":[
        {
            "category":"Banks & Credit Unions",
            "subcategory":"Bank",
            "type":"Services"
        },
        {
            "category":"Shopping",
            "subcategory":"Used Merchandise",
            "type":"Retail Goods"
        }
    ],
    "sg:phone":"+1 903 838 8906",
    "sg:postcode":"75503",
    "sg:province":"TX",
    "sg:tags":[
        "resale",
        "shop",
        "second",
        "hand"
    ],
    "sg:website":"http://www.nuff-said.com",
    "wof:name":"Musicians Buy Line",
    "wof:placetype":"venue"
},
  "geometry": {"coordinates":[-94.095167,33.466781],"type":"Point"}
}