{
  "type": "Feature",
  "properties": {
    "iso:country":"US",
    "sg:address":"5904 Cedar Ridge Dr",
    "sg:city":"Arlington",
    "sg:classifiers":[
        {
            "category":"Banks & Credit Unions",
            "subcategory":"Financial Services",
            "type":"Services"
        }
    ],
    "sg:phone":"+1 817 478 3912",
    "sg:postcode":"76017",
    "sg:province":"TX",
    "sg:tags":[
        "company",
        "holding"
    ],
    "wof:name":"Equivest Holdings LLC",
    "wof:placetype":"venue"
},
  "geometry": {"coordinates":[-97.181399,32.65028],"type":"Point"}
}