{
  "type": "Feature",
  "properties": {
    "iso:country":"US",
    "sg:address":"204 E Daggett Ave",
    "sg:city":"Fort Worth",
    "sg:classifiers":[
        {
            "category":"Manufacturing",
            "subcategory":"Metals",
            "type":"Manufacturing & Wholesale Goods"
        }
    ],
    "sg:phone":"+1 817 332 9922",
    "sg:postcode":"76104",
    "sg:province":"TX",
    "sg:tags":[
        "plating"
    ],
    "sg:website":"www.armoloyftworth.com",
    "wof:name":"Armoloy Co Of Fort Worth",
    "wof:placetype":"venue"
},
  "geometry": {"coordinates":[-97.323937,32.742427],"type":"Point"}
}