{
  "type": "Feature",
  "properties": {
    "iso:country":"US",
    "sg:address":"928 Runneburg Rd",
    "sg:city":"Crosby",
    "sg:classifiers":[
        {
            "category":"Professional",
            "type":"Services"
        }
    ],
    "sg:phone":"+1 281 328 2794",
    "sg:postcode":"77532",
    "sg:province":"TX",
    "wof:name":"Touch of Lace",
    "wof:placetype":"venue"
},
  "geometry": {"coordinates":[-95.058419,29.911728],"type":"Point"}
}