{
  "type": "Feature",
  "properties": {
    "iso:country":"US",
    "sg:address":"4142 La Place Dr",
    "sg:city":"Dallas",
    "sg:classifiers":[
        {
            "category":"Manufacturing",
            "subcategory":"Leather Goods",
            "type":"Manufacturing & Wholesale Goods"
        }
    ],
    "sg:phone":"+1 214 742 4861",
    "sg:postcode":"75220",
    "sg:province":"TX",
    "wof:name":"C-Warren & Associates",
    "wof:placetype":"venue"
},
  "geometry": {"coordinates":[-96.84147299999999,32.865379],"type":"Point"}
}