{
  "type": "Feature",
  "properties": {
    "iso:country":"US",
    "sg:address":"5807 Coldsworth Ct",
    "sg:city":"Arlington",
    "sg:classifiers":[
        {
            "category":"Professional",
            "type":"Services"
        }
    ],
    "sg:phone":"+1 817 472 8642",
    "sg:postcode":"76018",
    "sg:province":"TX",
    "wof:name":"Rana Corporation",
    "wof:placetype":"venue"
},
  "geometry": {"coordinates":[-97.100809,32.651102],"type":"Point"}
}