{
  "type": "Feature",
  "properties": {
    "iso:country":"US",
    "sg:address":"2102 Cobb Park Dr",
    "sg:city":"Fort Worth",
    "sg:classifiers":[
        {
            "category":"Government",
            "subcategory":"Office",
            "type":"Public Place"
        }
    ],
    "sg:phone":"+1 817 534 2764",
    "sg:postcode":"76105",
    "sg:province":"TX",
    "sg:tags":[
        "federal",
        "security"
    ],
    "wof:name":"US Army National Guard Recruit",
    "wof:placetype":"venue"
},
  "geometry": {"coordinates":[-97.293009,32.72441],"type":"Point"}
}