{
  "type": "Feature",
  "properties": {
    "iso:country":"US",
    "sg:address":"1730 Lawndale St",
    "sg:city":"Kingsville",
    "sg:classifiers":[
        {
            "category":"Professional",
            "subcategory":"Engineering",
            "type":"Services"
        }
    ],
    "sg:phone":"+1 361 595 7748",
    "sg:postcode":"78363",
    "sg:province":"TX",
    "wof:name":"Society of Mfg Engineers",
    "wof:placetype":"venue"
},
  "geometry": {"coordinates":[-97.853104,27.499899],"type":"Point"}
}