{
  "type": "Feature",
  "properties": {
    "iso:country":"US",
    "sg:address":"6501 N Beach St",
    "sg:city":"Fort Worth",
    "sg:classifiers":[
        {
            "category":"Health Services",
            "subcategory":"Doctor",
            "type":"Services"
        }
    ],
    "sg:phone":"+1 817 847 5304",
    "sg:postcode":"76137",
    "sg:province":"TX",
    "sg:tags":[
        "physician",
        "surgeon"
    ],
    "wof:name":"Cook Childrens Medical Ctr",
    "wof:placetype":"venue"
},
  "geometry": {"coordinates":[-97.290142,32.860527],"type":"Point"}
}