{
  "type": "Feature",
  "properties": {
    "iso:country":"US",
    "sg:address":"4801 Osborne Dr",
    "sg:city":"El Paso",
    "sg:classifiers":[
        {
            "category":"Government",
            "subcategory":"Police Station",
            "type":"Public Place"
        }
    ],
    "sg:phone":"+1 915 585 6000",
    "sg:postcode":"79922",
    "sg:province":"TX",
    "sg:tags":[
        "department"
    ],
    "wof:name":"El Paso Police Dept-Command",
    "wof:placetype":"venue"
},
  "geometry": {"coordinates":[-106.573032,31.838976],"type":"Point"}
}