{
  "type": "Feature",
  "properties": {
    "iso:country":"US",
    "sg:address":"2908 Commodore Dr",
    "sg:city":"Carrollton",
    "sg:classifiers":[
        {
            "category":"Manufacturing",
            "subcategory":"Printing",
            "type":"Manufacturing & Wholesale Goods"
        }
    ],
    "sg:phone":"+1 469 568 6000",
    "sg:postcode":"75007",
    "sg:province":"TX",
    "sg:tags":[
        "business",
        "system",
        "form",
        "promotional"
    ],
    "wof:name":"Standard Register Company",
    "wof:placetype":"venue"
},
  "geometry": {"coordinates":[-96.92829999999999,32.99406],"type":"Point"}
}