{
  "type": "Feature",
  "properties": {
    "iso:country":"US",
    "sg:address":"4164 Bus Park Dr",
    "sg:city":"Amarillo",
    "sg:classifiers":[
        {
            "category":"Personal",
            "type":"Services"
        }
    ],
    "sg:phone":"+1 806 463 3260",
    "sg:postcode":"79110",
    "sg:province":"TX",
    "sg:tags":[
        "therapist",
        "massage"
    ],
    "wof:name":"Awakening Spirit Massage",
    "wof:placetype":"venue"
},
  "geometry": {"coordinates":[-101.883376,35.143975],"type":"Point"}
}