{
  "type": "Feature",
  "properties": {
    "iso:country":"US",
    "sg:address":"8090 Kempwood Dr",
    "sg:city":"Houston",
    "sg:classifiers":[
        {
            "category":"Professional",
            "subcategory":"Management & Consulting",
            "type":"Services"
        }
    ],
    "sg:phone":"+1 713 464 8200",
    "sg:postcode":"77055",
    "sg:province":"TX",
    "sg:tags":[
        "operator",
        "local",
        "trucking"
    ],
    "wof:name":"Pioneer Contract Services",
    "wof:placetype":"venue"
},
  "geometry": {"coordinates":[-95.490937,29.817818],"type":"Point"}
}