{
  "type": "Feature",
  "properties": {
    "iso:country":"US",
    "sg:address":"3716 Jefferson Ave",
    "sg:city":"Texarkana",
    "sg:classifiers":[
        {
            "category":"Professional",
            "subcategory":"Engineering",
            "type":"Services"
        }
    ],
    "sg:phone":"+1 870 774 3204",
    "sg:postcode":"71854",
    "sg:province":"TX",
    "wof:name":"Spears Engineering Co",
    "wof:placetype":"venue"
},
  "geometry": {"coordinates":[-94.029117,33.459114],"type":"Point"}
}