{
  "type": "Feature",
  "properties": {
    "iso:country":"US",
    "sg:address":"7976 Glenway Dr",
    "sg:city":"Dallas",
    "sg:classifiers":[
        {
            "category":"Professional",
            "subcategory":"Management & Consulting",
            "type":"Services"
        }
    ],
    "sg:phone":"+1 972 283 2450",
    "sg:postcode":"75249",
    "sg:province":"TX",
    "wof:name":"Hjjventures LLC",
    "wof:placetype":"venue"
},
  "geometry": {"coordinates":[-96.964506,32.65403],"type":"Point"}
}