{
  "type": "Feature",
  "properties": {
    "iso:country":"US",
    "sg:address":"905 Blossomwood Ct",
    "sg:city":"Arlington",
    "sg:classifiers":[
        {
            "category":"Freight",
            "type":"Transportation"
        }
    ],
    "sg:phone":"+1 817 919 3753",
    "sg:postcode":"76017",
    "sg:province":"TX",
    "sg:tags":[
        "delivery",
        "arrangement"
    ],
    "wof:name":"Kemp's Express",
    "wof:placetype":"venue"
},
  "geometry": {"coordinates":[-97.122691,32.655793],"type":"Point"}
}