{
  "type": "Feature",
  "properties": {
    "iso:country":"US",
    "sg:address":"400 W Rusk St",
    "sg:city":"Jacksonville",
    "sg:classifiers":[
        {
            "category":"Government",
            "subcategory":"Post Office",
            "type":"Public Place"
        }
    ],
    "sg:phone":"+1 903 586 2011",
    "sg:postcode":"75766",
    "sg:province":"TX",
    "sg:tags":[
        "postal",
        "us"
    ],
    "wof:name":"US Post Office",
    "wof:placetype":"venue"
},
  "geometry": {"coordinates":[-95.276355,31.96116],"type":"Point"}
}