{
  "type": "Feature",
  "properties": {
    "iso:country":"US",
    "sg:address":"2818 S Country Club Rd",
    "sg:city":"Garland",
    "sg:classifiers":[
        {
            "category":"Health Services",
            "subcategory":"Doctor",
            "type":"Services"
        }
    ],
    "sg:phone":"+1 972 278 4701",
    "sg:postcode":"75043",
    "sg:province":"TX",
    "sg:website":"www.career-design.com",
    "wof:name":"Harkness Helen PHD",
    "wof:placetype":"venue"
},
  "geometry": {"coordinates":[-96.6073,32.882702],"type":"Point"}
}