{
  "type": "Feature",
  "properties": {
    "iso:country":"US",
    "sg:address":"2227 Winding Hollow Ln",
    "sg:city":"Katy",
    "sg:classifiers":[
        {
            "category":"Professional",
            "subcategory":"Computer Services",
            "type":"Services"
        }
    ],
    "sg:phone":"+1 281 599 3220",
    "sg:postcode":"77450",
    "sg:province":"TX",
    "sg:tags":[
        "related"
    ],
    "wof:name":"Solid Links",
    "wof:placetype":"venue"
},
  "geometry": {"coordinates":[-95.74391199999999,29.748593],"type":"Point"}
}