{
  "type": "Feature",
  "properties": {
    "iso:country":"US",
    "sg:address":"1327 Pegasus Dr",
    "sg:city":"Arlington",
    "sg:classifiers":[
        {
            "category":"Real Estate",
            "subcategory":"Real Estate Agent",
            "type":"Services"
        },
        {
            "category":"Professional",
            "subcategory":"Business Services",
            "type":"Services"
        }
    ],
    "sg:phone":"+1 817 446 0946",
    "sg:postcode":"76013",
    "sg:province":"TX",
    "sg:tags":[
        "inspection"
    ],
    "wof:name":"A Tech Home Inspections",
    "wof:placetype":"venue"
},
  "geometry": {"coordinates":[-97.178302,32.724796],"type":"Point"}
}