{
  "type": "Feature",
  "properties": {
    "iso:country":"US",
    "sg:address":"2207 Wildwood St",
    "sg:city":"Victoria",
    "sg:classifiers":[
        {
            "category":"Banks & Credit Unions",
            "subcategory":"Bank",
            "type":"Services"
        }
    ],
    "sg:phone":"+1 361 576 3168",
    "sg:postcode":"77901",
    "sg:province":"TX",
    "wof:name":"Victoria Teachers Federal CU",
    "wof:placetype":"venue"
},
  "geometry": {"coordinates":[-96.98134899999999,28.805043],"type":"Point"}
}