{
  "type": "Feature",
  "properties": {
    "iso:country":"US",
    "sg:address":"400 Intermodal Pkwy",
    "sg:city":"Fort Worth",
    "sg:classifiers":[
        {
            "category":"Professional",
            "subcategory":"Management & Consulting",
            "type":"Services"
        }
    ],
    "sg:phone":"+1 817 430 7820",
    "sg:postcode":"76177",
    "sg:province":"TX",
    "sg:tags":[
        "logistics"
    ],
    "wof:name":"Exel Logistics",
    "wof:placetype":"venue"
},
  "geometry": {"coordinates":[-97.33044099999999,32.988186],"type":"Point"}
}