{
  "type": "Feature",
  "properties": {
    "iso:country":"US",
    "sg:address":"804 W Villa Maria Rd",
    "sg:city":"Bryan",
    "sg:classifiers":[
        {
            "category":"Manufacturing",
            "subcategory":"Jewelry",
            "type":"Manufacturing & Wholesale Goods"
        }
    ],
    "sg:phone":"+1 979 775 4871",
    "sg:postcode":"77807",
    "sg:province":"TX",
    "wof:name":"Karat Patch",
    "wof:placetype":"venue"
},
  "geometry": {"coordinates":[-96.36734800000001,30.633652],"type":"Point"}
}