{
  "type": "Feature",
  "properties": {
    "iso:country":"US",
    "sg:address":"301 E Austin St",
    "sg:city":"Luling",
    "sg:classifiers":[
        {
            "category":"Recreation",
            "type":"Entertainment"
        }
    ],
    "sg:phone":"+1 830 875 9039",
    "sg:postcode":"78648",
    "sg:province":"TX",
    "sg:tags":[
        "parks"
    ],
    "wof:name":"Parks & Recreation Dept",
    "wof:placetype":"venue"
},
  "geometry": {"coordinates":[-97.652717,29.683771],"type":"Point"}
}