{
  "type": "Feature",
  "properties": {
    "iso:country":"US",
    "sg:address":"11209 Harvest Rd",
    "sg:city":"Mesquite",
    "sg:classifiers":[
        {
            "category":"Professional",
            "subcategory":"Computer Services",
            "type":"Services"
        }
    ],
    "sg:phone":"+1 972 557 2659",
    "sg:postcode":"75180",
    "sg:province":"TX",
    "sg:tags":[
        "programing",
        "custom"
    ],
    "wof:name":"Ecomp Systems",
    "wof:placetype":"venue"
},
  "geometry": {"coordinates":[-96.635634,32.708058],"type":"Point"}
}