{
  "type": "Feature",
  "properties": {
    "iso:country":"US",
    "sg:address":"1601 Monument Cir",
    "sg:city":"Plano",
    "sg:classifiers":[
        {
            "category":"Wholesale",
            "subcategory":"Electrical",
            "type":"Manufacturing & Wholesale Goods"
        }
    ],
    "sg:phone":"+1 972 380 9358",
    "sg:postcode":"75093",
    "sg:province":"TX",
    "sg:tags":[
        "equipment"
    ],
    "wof:name":"Citilites",
    "wof:placetype":"venue"
},
  "geometry": {"coordinates":[-96.800533,33.02193],"type":"Point"}
}