{
  "type": "Feature",
  "properties": {
    "iso:country":"US",
    "sg:address":"240 Cross Timbers Dr",
    "sg:city":"Lewisville",
    "sg:classifiers":[
        {
            "category":"Professional",
            "subcategory":"Management & Consulting",
            "type":"Services"
        }
    ],
    "sg:phone":"+1 817 491 3030",
    "sg:postcode":"75077",
    "sg:province":"TX",
    "sg:tags":[
        "merger",
        "consultant",
        "including",
        "business",
        "acquisition"
    ],
    "wof:name":"Corporate Dev Resources",
    "wof:placetype":"venue"
},
  "geometry": {"coordinates":[-97.111431,33.063404],"type":"Point"}
}