{
  "type": "Feature",
  "properties": {
    "iso:country":"US",
    "sg:address":"2000 Co Rd 152",
    "sg:city":"Brownwood",
    "sg:classifiers":[
        {
            "category":"Manufacturing",
            "subcategory":"Building Materials",
            "type":"Manufacturing & Wholesale Goods"
        }
    ],
    "sg:phone":"+1 325 752 0051",
    "sg:postcode":"76801",
    "sg:province":"TX",
    "sg:tags":[
        "mfg",
        "wood",
        "kitchen",
        "cabinet"
    ],
    "wof:name":"Quality Woodworking",
    "wof:placetype":"venue"
},
  "geometry": {"coordinates":[-99.06665599999999,31.754237],"type":"Point"}
}