{
  "type": "Feature",
  "properties": {
    "iso:country":"US",
    "sg:address":"1050 W Shady Grove Rd",
    "sg:city":"Irving",
    "sg:classifiers":[
        {
            "category":"Retail",
            "subcategory":"Portrait Studio",
            "type":"Services"
        },
        {
            "category":"Shopping",
            "subcategory":"Pharmacy",
            "type":"Retail Goods"
        }
    ],
    "sg:phone":"+1 972 253 8160",
    "sg:postcode":"75060",
    "sg:province":"TX",
    "sg:tags":[
        "photography",
        "drugstore",
        "store"
    ],
    "wof:name":"Walgreens the Pharmacy America Trusts",
    "wof:placetype":"venue"
},
  "geometry": {"coordinates":[-96.95819899999999,32.8013],"type":"Point"}
}