{
  "type": "Feature",
  "properties": {
    "iso:country":"US",
    "sg:address":"111 Congress Ave Fl 4",
    "sg:city":"Austin",
    "sg:classifiers":[
        {
            "category":"Real Estate",
            "subcategory":"Real Estate Services",
            "type":"Services"
        },
        {
            "category":"Banks & Credit Unions",
            "subcategory":"Financial Services",
            "type":"Services"
        }
    ],
    "sg:phone":"+1 512 391 3808",
    "sg:postcode":"78701",
    "sg:province":"TX",
    "sg:tags":[
        "loan",
        "processing"
    ],
    "wof:name":"Armstrong Mortgage Group",
    "wof:placetype":"venue"
},
  "geometry": {"coordinates":[-97.744326,30.26388],"type":"Point"}
}