{
  "type": "Feature",
  "properties": {
    "iso:country":"US",
    "sg:address":"3101 Joymeadow Dr",
    "sg:city":"Fort Worth",
    "sg:classifiers":[
        {
            "category":"Professional",
            "type":"Services"
        }
    ],
    "sg:phone":"+1 817 294 5303",
    "sg:postcode":"76123",
    "sg:province":"TX",
    "wof:name":"Ophthalmic Technical Services",
    "wof:placetype":"venue"
},
  "geometry": {"coordinates":[-97.36512399999999,32.633532],"type":"Point"}
}