{
  "type": "Feature",
  "properties": {
    "iso:country":"US",
    "sg:address":"3730 Westchase Dr",
    "sg:city":"Houston",
    "sg:classifiers":[
        {
            "category":"Manufacturing",
            "subcategory":"Textiles",
            "type":"Manufacturing & Wholesale Goods"
        }
    ],
    "sg:phone":"+1 713 266 8799",
    "sg:postcode":"77042",
    "sg:province":"TX",
    "sg:tags":[
        "fabric"
    ],
    "wof:name":"A Lakhany Intl Textile",
    "wof:placetype":"venue"
},
  "geometry": {"coordinates":[-95.551045,29.723029],"type":"Point"}
}