{
  "type": "Feature",
  "properties": {
    "iso:country":"US",
    "sg:address":"209 E Mulberry St",
    "sg:city":"Angleton",
    "sg:classifiers":[
        {
            "category":"Banks & Credit Unions",
            "subcategory":"Bank",
            "type":"Services"
        }
    ],
    "sg:phone":"+1 979 849 8571",
    "sg:postcode":"77515",
    "sg:province":"TX",
    "wof:name":"Wells Fargo Bank",
    "wof:placetype":"venue"
},
  "geometry": {"coordinates":[-95.429185,29.164578],"type":"Point"}
}