{
  "type": "Feature",
  "properties": {
    "iso:country":"US",
    "sg:address":"775 Voltaire Dr",
    "sg:city":"Plano",
    "sg:classifiers":[
        {
            "category":"Banks & Credit Unions",
            "subcategory":"Bank",
            "type":"Services"
        }
    ],
    "sg:phone":"+1 972 881 7743",
    "sg:postcode":"75023",
    "sg:province":"TX",
    "sg:tags":[
        "mortgage"
    ],
    "wof:name":"Rapid Mortgage Assoc",
    "wof:placetype":"venue"
},
  "geometry": {"coordinates":[-96.707897,33.045355],"type":"Point"}
}