{
  "type": "Feature",
  "properties": {
    "iso:country":"US",
    "sg:address":"3005 Glenda St",
    "sg:city":"Haltom City",
    "sg:classifiers":[
        {
            "category":"Shopping",
            "subcategory":"Department Store",
            "type":"Retail Goods"
        }
    ],
    "sg:phone":"+1 817 222 0446",
    "sg:postcode":"76117",
    "sg:province":"TX",
    "sg:tags":[
        "shop"
    ],
    "wof:name":"One Stop Bargain Shop",
    "wof:placetype":"venue"
},
  "geometry": {"coordinates":[-97.285783,32.798834],"type":"Point"}
}