{
  "type": "Feature",
  "properties": {
    "iso:country":"US",
    "sg:address":"2725 Faxon Dr",
    "sg:city":"Plano",
    "sg:classifiers":[
        {
            "category":"Arts & Performance",
            "subcategory":"Theater",
            "type":"Entertainment"
        }
    ],
    "sg:phone":"+1 972 727 1711",
    "sg:postcode":"75025",
    "sg:province":"TX",
    "sg:tags":[
        "group"
    ],
    "wof:name":"Nuevo Tejas Music",
    "wof:placetype":"venue"
},
  "geometry": {"coordinates":[-96.74399099999999,33.103478],"type":"Point"}
}