{
  "type": "Feature",
  "properties": {
    "iso:country":"US",
    "sg:address":"2805 E 22nd St",
    "sg:city":"Austin",
    "sg:classifiers":[
        {
            "category":"Food & Beverages",
            "subcategory":"Bakery",
            "type":"Retail Goods"
        }
    ],
    "sg:phone":"+1 512 499 8304",
    "sg:postcode":"78722",
    "sg:province":"TX",
    "sg:tags":[
        "cooky",
        "cracker"
    ],
    "wof:name":"Danos Cookies",
    "wof:placetype":"venue"
},
  "geometry": {"coordinates":[-97.71209,30.284063],"type":"Point"}
}