{
  "type": "Feature",
  "properties": {
    "iso:country":"US",
    "sg:address":"8200 Brookriver Dr",
    "sg:city":"Dallas",
    "sg:classifiers":[
        {
            "category":"Building & Trades",
            "subcategory":"Construction",
            "type":"Services"
        }
    ],
    "sg:phone":"+1 214 905 9720",
    "sg:postcode":"75247",
    "sg:province":"TX",
    "sg:tags":[
        "general",
        "contractor"
    ],
    "wof:name":"Sam Corp",
    "wof:placetype":"venue"
},
  "geometry": {"coordinates":[-96.868506,32.824266],"type":"Point"}
}