{
  "type": "Feature",
  "properties": {
    "iso:country":"US",
    "sg:address":"3206 College Ave",
    "sg:city":"Snyder",
    "sg:classifiers":[
        {
            "category":"Restaurant",
            "type":"Food & Drink"
        }
    ],
    "sg:phone":"+1 325 573 9253",
    "sg:postcode":"79549",
    "sg:province":"TX",
    "sg:tags":[
        "style",
        "mexican",
        "family"
    ],
    "wof:name":"Jaramillo's",
    "wof:placetype":"venue"
},
  "geometry": {"coordinates":[-100.91912499999999,32.709594],"type":"Point"}
}