{
  "type": "Feature",
  "properties": {
    "iso:country":"US",
    "sg:address":"200 Bower Rd",
    "sg:city":"Bridge City",
    "sg:classifiers":[
        {
            "category":"Recreation",
            "type":"Entertainment"
        }
    ],
    "sg:phone":"+1 409 697 1768",
    "sg:postcode":"77611",
    "sg:province":"TX",
    "sg:tags":[
        "charter",
        "boat"
    ],
    "wof:name":"T & D Marine Inc",
    "wof:placetype":"venue"
},
  "geometry": {"coordinates":[-93.82088400000001,30.040514],"type":"Point"}
}