{
  "type": "Feature",
  "properties": {
    "iso:country":"US",
    "sg:address":"770 E Warrior Trl",
    "sg:city":"Grand Prairie",
    "sg:classifiers":[
        {
            "category":"Organizations",
            "subcategory":"Religious Organization",
            "type":"Services"
        }
    ],
    "sg:phone":"+1 972 263 1554",
    "sg:postcode":"75052",
    "sg:province":"TX",
    "wof:name":"African Evangelical Baptist",
    "wof:placetype":"venue"
},
  "geometry": {"coordinates":[-96.99524099999999,32.698922],"type":"Point"}
}