{
  "type": "Feature",
  "properties": {
    "iso:country":"US",
    "sg:address":"455 Krams Creek Rd",
    "sg:city":"Seguin",
    "sg:classifiers":[
        {
            "category":"Professional",
            "subcategory":"Art Services",
            "type":"Services"
        }
    ],
    "sg:phone":"+1 830 372 3733",
    "sg:postcode":"78155",
    "sg:province":"TX",
    "sg:tags":[
        "commercial",
        "design"
    ],
    "wof:name":"Thome Typesetting",
    "wof:placetype":"venue"
},
  "geometry": {"coordinates":[-97.926132,29.521623],"type":"Point"}
}