{
  "type": "Feature",
  "properties": {
    "iso:country":"US",
    "sg:address":"1101 Ashford Dr",
    "sg:city":"San Angelo",
    "sg:classifiers":[
        {
            "category":"Utilities",
            "subcategory":"Cable",
            "type":"Services"
        }
    ],
    "sg:phone":"+1 325 481 0633",
    "sg:postcode":"76901",
    "sg:province":"TX",
    "sg:tags":[
        "television"
    ],
    "wof:name":"Television Enterprises Inc",
    "wof:placetype":"venue"
},
  "geometry": {"coordinates":[-100.513738,31.443646],"type":"Point"}
}