{
  "type": "Feature",
  "properties": {
    "iso:country":"US",
    "sg:address":"9230 Homeland Dr",
    "sg:city":"Houston",
    "sg:classifiers":[
        {
            "category":"Building & Trades",
            "subcategory":"Cleaning & Sanitation",
            "type":"Services"
        }
    ],
    "sg:phone":"+1 281 277 0070",
    "sg:postcode":"77083",
    "sg:province":"TX",
    "sg:tags":[
        "maintenance"
    ],
    "wof:name":"Cape Janitorial & Maid Svcs",
    "wof:placetype":"venue"
},
  "geometry": {"coordinates":[-95.624602,29.67972],"type":"Point"}
}