{
  "type": "Feature",
  "properties": {
    "iso:country":"US",
    "sg:address":"1101 Scott Ave",
    "sg:city":"Wichita Falls",
    "sg:classifiers":[
        {
            "category":"Professional",
            "subcategory":"Detective & Security Services",
            "type":"Services"
        }
    ],
    "sg:phone":"+1 940 761 2363",
    "sg:postcode":"76301",
    "sg:province":"TX",
    "sg:tags":[
        "investigator"
    ],
    "wof:name":"Joe Hall Investigations",
    "wof:placetype":"venue"
},
  "geometry": {"coordinates":[-98.48888599999999,33.908006],"type":"Point"}
}