{
  "type": "Feature",
  "properties": {
    "iso:country":"US",
    "sg:address":"3100 Wayfarer Rd",
    "sg:city":"Bedford",
    "sg:classifiers":[
        {
            "category":"Professional",
            "subcategory":"Business Services",
            "type":"Services"
        }
    ],
    "sg:phone":"+1 817 545 0301",
    "sg:postcode":"76021",
    "sg:province":"TX",
    "wof:name":"Creative Database Solutions",
    "wof:placetype":"venue"
},
  "geometry": {"coordinates":[-97.11760700000001,32.854465],"type":"Point"}
}