{
  "type": "Feature",
  "properties": {
    "iso:country":"US",
    "sg:address":"814 E Central Ave",
    "sg:city":"Belton",
    "sg:classifiers":[
        {
            "category":"Restaurant",
            "type":"Food & Drink"
        }
    ],
    "sg:phone":"+1 254 939 9006",
    "sg:postcode":"76513",
    "sg:province":"TX",
    "sg:tags":[
        "eating"
    ],
    "wof:name":"Sonic Drive-In",
    "wof:placetype":"venue"
},
  "geometry": {"coordinates":[-97.456152,31.05434],"type":"Point"}
}