{
  "type": "Feature",
  "properties": {
    "iso:country":"US",
    "sg:address":"16 Mariners Ln",
    "sg:city":"Kemah",
    "sg:classifiers":[
        {
            "category":"Professional",
            "type":"Services"
        }
    ],
    "sg:phone":"+1 281 334 5839",
    "sg:postcode":"77565",
    "sg:province":"TX",
    "wof:name":"Bittle Ltd Co",
    "wof:placetype":"venue"
},
  "geometry": {"coordinates":[-95.042006,29.548483],"type":"Point"}
}