{
  "type": "Feature",
  "properties": {
    "iso:country":"US",
    "sg:address":"10988 N State Hwy 78",
    "sg:city":"Ravenna",
    "sg:classifiers":[
        {
            "category":"Restaurant",
            "type":"Food & Drink"
        }
    ],
    "sg:phone":"+1 903 640 0625",
    "sg:postcode":"75476",
    "sg:province":"TX",
    "sg:tags":[
        "eating"
    ],
    "wof:name":"Kangaroo Corner",
    "wof:placetype":"venue"
},
  "geometry": {"coordinates":[-96.18810499999999,33.736349],"type":"Point"}
}