{
  "type": "Feature",
  "properties": {
    "iso:country":"US",
    "sg:address":"104 Loop 150",
    "sg:city":"Bastrop",
    "sg:classifiers":[
        {
            "category":"Government",
            "subcategory":"Office",
            "type":"Public Place"
        }
    ],
    "sg:phone":"+1 512 321 3982",
    "sg:postcode":"78602",
    "sg:province":"TX",
    "sg:tags":[
        "state",
        "program",
        "health"
    ],
    "wof:name":"Health Dept",
    "wof:placetype":"venue"
},
  "geometry": {"coordinates":[-97.328884,30.105589],"type":"Point"}
}