{
  "type": "Feature",
  "properties": {
    "iso:country":"US",
    "sg:address":"3418 Sakowitz St",
    "sg:city":"Houston",
    "sg:classifiers":[
        {
            "category":"Retail",
            "subcategory":"Auto Repair",
            "type":"Services"
        }
    ],
    "sg:phone":"+1 713 672 2397",
    "sg:postcode":"77026",
    "sg:province":"TX",
    "sg:tags":[
        "truck"
    ],
    "sg:website":"www.haplinc.com",
    "wof:name":"HAPL",
    "wof:placetype":"venue"
},
  "geometry": {"coordinates":[-95.313513,29.791599],"type":"Point"}
}