{
  "type": "Feature",
  "properties": {
    "iso:country":"US",
    "sg:address":"4005 Mesa Ridge Dr",
    "sg:city":"Fort Worth",
    "sg:classifiers":[
        {
            "category":"Shopping",
            "subcategory":"Clothing, Apparel, & Fashions",
            "type":"Retail Goods"
        }
    ],
    "sg:phone":"+1 817 847 9017",
    "sg:postcode":"76137",
    "sg:province":"TX",
    "wof:name":"Flights of Fancy Inc",
    "wof:placetype":"venue"
},
  "geometry": {"coordinates":[-97.297133,32.859945],"type":"Point"}
}