{
  "type": "Feature",
  "properties": {
    "iso:country":"US",
    "sg:address":"103 Balsam St",
    "sg:city":"Lake Jackson",
    "sg:classifiers":[
        {
            "category":"Real Estate",
            "subcategory":"Real Estate Agent",
            "type":"Services"
        }
    ],
    "sg:phone":"+1 979 297 2722",
    "sg:postcode":"77566",
    "sg:province":"TX",
    "wof:name":"Williams Kller Txas Golf Prpts",
    "wof:placetype":"venue"
},
  "geometry": {"coordinates":[-95.429872,29.016893],"type":"Point"}
}