{
  "type": "Feature",
  "properties": {
    "iso:country":"US",
    "sg:address":"229 Dowlen Rd",
    "sg:city":"Beaumont",
    "sg:classifiers":[
        {
            "category":"Insurance",
            "subcategory":"Insurance Agent",
            "type":"Services"
        },
        {
            "category":"Insurance",
            "subcategory":"Hazard Insurance",
            "type":"Services"
        },
        {
            "category":"Insurance",
            "subcategory":"Title Insurance",
            "type":"Services"
        },
        {
            "category":"Insurance",
            "subcategory":"Life Insurance",
            "type":"Services"
        }
    ],
    "sg:phone":"+1 409 866 6778",
    "sg:postcode":"77706",
    "sg:province":"TX",
    "sg:tags":[
        "auto",
        "flood",
        "homeowner"
    ],
    "sg:website":"http://www.farmersagent.com/grichmond",
    "wof:name":"George Richmond Agency",
    "wof:placetype":"venue"
},
  "geometry": {"coordinates":[-94.17227800000001,30.075023],"type":"Point"}
}