{
  "type": "Feature",
  "properties": {
    "iso:country":"US",
    "sg:address":"9310 Clay Rd",
    "sg:city":"Houston",
    "sg:classifiers":[
        {
            "category":"Restaurant",
            "type":"Food & Drink"
        }
    ],
    "sg:phone":"+1 713 462 6308",
    "sg:postcode":"77080",
    "sg:province":"TX",
    "wof:name":"Jack In the Box Restaurants",
    "wof:placetype":"venue"
},
  "geometry": {"coordinates":[-95.52220199999999,29.832701],"type":"Point"}
}