{
  "type": "Feature",
  "properties": {
    "iso:country":"US",
    "sg:address":"2013 Industrial Blvd",
    "sg:city":"Alice",
    "sg:classifiers":[
        {
            "category":"Retail",
            "subcategory":"Auto Repair",
            "type":"Services"
        }
    ],
    "sg:phone":"+1 361 664 0792",
    "sg:postcode":"78332",
    "sg:province":"TX",
    "sg:tags":[
        "body",
        "automobile",
        "painting"
    ],
    "wof:name":"Ray's Paint & Body Shop",
    "wof:placetype":"venue"
},
  "geometry": {"coordinates":[-98.07840400000001,27.770475],"type":"Point"}
}