{
  "type": "Feature",
  "properties": {
    "iso:country":"US",
    "sg:address":"211 E Main St",
    "sg:city":"Humble",
    "sg:classifiers":[
        {
            "category":"Personal",
            "subcategory":"Beauty Salon",
            "type":"Services"
        }
    ],
    "sg:phone":"+1 281 446 7586",
    "sg:postcode":"77338",
    "sg:province":"TX",
    "sg:tags":[
        "shop"
    ],
    "wof:name":"Before & After Hair Salon",
    "wof:placetype":"venue"
},
  "geometry": {"coordinates":[-95.263867,29.997817],"type":"Point"}
}