{
  "type": "Feature",
  "properties": {
    "iso:country":"US",
    "sg:address":"603 Baylor",
    "sg:city":"Austin",
    "sg:classifiers":[
        {
            "category":"Home & Garden",
            "subcategory":"Home Furnishings",
            "type":"Retail Goods"
        }
    ],
    "sg:phone":"+1 512 731 9924",
    "sg:postcode":"78703",
    "sg:province":"TX",
    "sg:tags":[
        "decor"
    ],
    "sg:website":"www.howlinteriors.com",
    "wof:name":"Howl Interiors",
    "wof:placetype":"venue"
},
  "geometry": {"coordinates":[-97.75471899999999,30.27228],"type":"Point"}
}