{
  "type": "Feature",
  "properties": {
    "iso:country":"US",
    "sg:address":"2401 Fresno Ave",
    "sg:city":"Mcallen",
    "sg:phone":"+1 956 682 9342",
    "sg:postcode":"78501",
    "sg:province":"TX",
    "sg:tags":[
        "equipment",
        "commercial"
    ],
    "wof:name":"Valdez Outdoor Equipment",
    "wof:placetype":"venue"
},
  "geometry": {"coordinates":[-98.248221,26.199886],"type":"Point"}
}