{
  "type": "Feature",
  "properties": {
    "iso:country":"US",
    "sg:address":"501 E Division St",
    "sg:city":"Arlington",
    "sg:classifiers":[
        {
            "category":"Bars & Pubs",
            "type":"Food & Drink"
        }
    ],
    "sg:phone":"+1 817 461 4499",
    "sg:postcode":"76011",
    "sg:province":"TX",
    "sg:tags":[
        "club",
        "drinking",
        "night"
    ],
    "wof:name":"John Henry's Inc",
    "wof:placetype":"venue"
},
  "geometry": {"coordinates":[-97.10136900000001,32.738924],"type":"Point"}
}