{
  "type": "Feature",
  "properties": {
    "iso:country":"US",
    "sg:address":"9002 Main St",
    "sg:city":"Needville",
    "sg:classifiers":[
        {
            "category":"Professional",
            "subcategory":"Lawyer & Legal Services",
            "type":"Services"
        }
    ],
    "sg:phone":"+1 979 793 6321",
    "sg:postcode":"77461",
    "sg:province":"TX",
    "sg:tags":[
        "attorney"
    ],
    "wof:name":"Marvin R Kanak",
    "wof:placetype":"venue"
},
  "geometry": {"coordinates":[-95.837889,29.39922],"type":"Point"}
}