{
  "type": "Feature",
  "properties": {
    "iso:country":"US",
    "sg:address":"775 Hamilton Dr",
    "sg:city":"Waco",
    "sg:classifiers":[
        {
            "category":"Professional",
            "type":"Services"
        }
    ],
    "sg:phone":"+1 254 829 2864",
    "sg:postcode":"76705",
    "sg:province":"TX",
    "wof:name":"Nicole",
    "wof:placetype":"venue"
},
  "geometry": {"coordinates":[-97.244513,31.711392],"type":"Point"}
}