{
  "type": "Feature",
  "properties": {
    "iso:country":"US",
    "sg:address":"8276 Alameda Ave",
    "sg:city":"El Paso",
    "sg:classifiers":[
        {
            "category":"Autos & Motor Vehicles",
            "subcategory":"Automobile Sales",
            "type":"Retail Goods"
        }
    ],
    "sg:phone":"+1 915 860 1097",
    "sg:postcode":"79907",
    "sg:province":"TX",
    "sg:tags":[
        "car",
        "dealer"
    ],
    "wof:name":"Silver Motors",
    "wof:placetype":"venue"
},
  "geometry": {"coordinates":[-106.351429,31.716998],"type":"Point"}
}