{
  "type": "Feature",
  "properties": {
    "iso:country":"US",
    "sg:address":"1807 W Main St",
    "sg:city":"Clarksville",
    "sg:classifiers":[
        {
            "category":"Real Estate",
            "subcategory":"Real Estate Operator",
            "type":"Services"
        }
    ],
    "sg:phone":"+1 903 427 2313",
    "sg:postcode":"75426",
    "sg:province":"TX",
    "sg:tags":[
        "apartment"
    ],
    "wof:name":"Parks Apartments",
    "wof:placetype":"venue"
},
  "geometry": {"coordinates":[-95.06616,33.610116],"type":"Point"}
}