{
  "type": "Feature",
  "properties": {
    "iso:country":"US",
    "sg:address":"200 W Expy 83",
    "sg:city":"Mcallen",
    "sg:classifiers":[
        {
            "category":"Travel",
            "subcategory":"Hotels & Motels",
            "type":"Entertainment"
        }
    ],
    "sg:phone":"+1 956 686 2471",
    "sg:postcode":"78501",
    "sg:province":"TX",
    "wof:name":"Holiday Inn",
    "wof:placetype":"venue"
},
  "geometry": {"coordinates":[-98.22403799999999,26.188675],"type":"Point"}
}