{
  "type": "Feature",
  "properties": {
    "iso:country":"US",
    "sg:address":"13522 Cedar Grove Dr",
    "sg:city":"Crosby",
    "sg:classifiers":[
        {
            "category":"Organizations",
            "subcategory":"Religious Organization",
            "type":"Services"
        }
    ],
    "sg:phone":"+1 713 631 7336",
    "sg:postcode":"77532",
    "sg:province":"TX",
    "wof:name":"Cedar Grv Frst Msnry Bptst CHR",
    "wof:placetype":"venue"
},
  "geometry": {"coordinates":[-95.041984,29.881467],"type":"Point"}
}