{
  "type": "Feature",
  "properties": {
    "iso:country":"US",
    "sg:address":"2506 Morning Glory Dr",
    "sg:city":"Richardson",
    "sg:classifiers":[
        {
            "category":"Professional",
            "type":"Services"
        }
    ],
    "sg:phone":"+1 972 729 5902",
    "sg:postcode":"75082",
    "sg:province":"TX",
    "wof:name":"Gelan International Corp",
    "wof:placetype":"venue"
},
  "geometry": {"coordinates":[-96.677173,32.996041],"type":"Point"}
}