{
  "type": "Feature",
  "properties": {
    "iso:country":"US",
    "sg:address":"3711 Pevetoe St",
    "sg:city":"Austin",
    "sg:classifiers":[
        {
            "category":"Professional",
            "subcategory":"Employment Agencies",
            "type":"Services"
        }
    ],
    "sg:phone":"+1 512 365 0367",
    "sg:postcode":"78725",
    "sg:province":"TX",
    "sg:tags":[
        "broker",
        "custom"
    ],
    "wof:name":"Hord International U.S. Customs House Brokers",
    "wof:placetype":"venue"
},
  "geometry": {"coordinates":[-97.586203,30.234996],"type":"Point"}
}