{
  "type": "Feature",
  "properties": {
    "iso:country":"US",
    "sg:address":"600 N O Connor Rd",
    "sg:city":"Irving",
    "sg:classifiers":[
        {
            "category":"Retail",
            "subcategory":"Auto Repair",
            "type":"Services"
        }
    ],
    "sg:phone":"+1 972 254 5458",
    "sg:postcode":"75061",
    "sg:province":"TX",
    "sg:tags":[
        "automobile",
        "lubrication"
    ],
    "wof:name":"KWIK Change Oil",
    "wof:placetype":"venue"
},
  "geometry": {"coordinates":[-96.949473,32.819386],"type":"Point"}
}