{
  "type": "Feature",
  "properties": {
    "iso:country":"US",
    "sg:address":"9230 Keough Rd",
    "sg:city":"Houston",
    "sg:classifiers":[
        {
            "category":"Wholesale",
            "subcategory":"Painting Supplies",
            "type":"Manufacturing & Wholesale Goods"
        },
        {
            "category":"Wholesale",
            "subcategory":"Auto Parts",
            "type":"Manufacturing & Wholesale Goods"
        }
    ],
    "sg:phone":"+1 713 896 8993",
    "sg:postcode":"77040",
    "sg:province":"TX",
    "sg:tags":[
        "body",
        "automotive",
        "paint",
        "shop",
        "automobile"
    ],
    "wof:name":"Northwest Auto Paint & Supply",
    "wof:placetype":"venue"
},
  "geometry": {"coordinates":[-95.540796,29.871082],"type":"Point"}
}