{
  "type": "Feature",
  "properties": {
    "iso:country":"US",
    "sg:address":"309 Mill St",
    "sg:city":"Del Rio",
    "sg:classifiers":[
        {
            "category":"Government",
            "subcategory":"Court House",
            "type":"Public Place"
        }
    ],
    "sg:phone":"+1 830 775 0505",
    "sg:postcode":"78840",
    "sg:province":"TX",
    "sg:tags":[
        "state",
        "counsel"
    ],
    "wof:name":"Texas District Attroney",
    "wof:placetype":"venue"
},
  "geometry": {"coordinates":[-100.893441,29.355556],"type":"Point"}
}