{
  "type": "Feature",
  "properties": {
    "iso:country":"US",
    "sg:address":"2517 Boardwalk St",
    "sg:city":"San Antonio",
    "sg:classifiers":[
        {
            "category":"Building & Trades",
            "subcategory":"Construction",
            "type":"Services"
        }
    ],
    "sg:phone":"+1 210 828 5255",
    "sg:postcode":"78217",
    "sg:province":"TX",
    "sg:tags":[
        "home",
        "siding",
        "contractor",
        "improvement"
    ],
    "sg:website":"www.southwestexteriors.com",
    "wof:name":"Southwest Exteriors",
    "wof:placetype":"venue"
},
  "geometry": {"coordinates":[-98.450532,29.533021],"type":"Point"}
}