{
  "type": "Feature",
  "properties": {
    "iso:country":"US",
    "sg:address":"3012 Fountainwood Dr",
    "sg:city":"Georgetown",
    "sg:classifiers":[
        {
            "category":"Professional",
            "subcategory":"Advertising",
            "type":"Services"
        }
    ],
    "sg:phone":"+1 512 869 2104",
    "sg:postcode":"78633",
    "sg:province":"TX",
    "sg:website":"www.onecoolproduct.com",
    "wof:name":"ONECOOLPRODUCT.COM",
    "wof:placetype":"venue"
},
  "geometry": {"coordinates":[-97.752476,30.69692],"type":"Point"}
}