{
  "type": "Feature",
  "properties": {
    "iso:country":"US",
    "sg:address":"3511 6th Ave",
    "sg:city":"Amarillo",
    "sg:classifiers":[
        {
            "category":"Shopping",
            "subcategory":"Used Merchandise",
            "type":"Retail Goods"
        }
    ],
    "sg:phone":"+1 806 373 1427",
    "sg:postcode":"79106",
    "sg:province":"TX",
    "wof:name":"Texas Ivy Unique Gifts",
    "wof:placetype":"venue"
},
  "geometry": {"coordinates":[-101.876794,35.211179],"type":"Point"}
}