{
  "type": "Feature",
  "properties": {
    "iso:country":"US",
    "sg:address":"3616 Mason Dr",
    "sg:city":"Plano",
    "sg:classifiers":[
        {
            "category":"Restaurant",
            "type":"Food & Drink"
        }
    ],
    "sg:phone":"+1 972 625 4002",
    "sg:postcode":"75025",
    "sg:province":"TX",
    "sg:tags":[
        "eating"
    ],
    "wof:name":"Egg Roll House",
    "wof:placetype":"venue"
},
  "geometry": {"coordinates":[-96.765039,33.103625],"type":"Point"}
}