{
  "type": "Feature",
  "properties": {
    "iso:country":"US",
    "sg:address":"109 W Main St",
    "sg:city":"Mesquite",
    "sg:classifiers":[
        {
            "category":"Building & Trades",
            "subcategory":"Electrical",
            "type":"Services"
        }
    ],
    "sg:phone":"+1 972 285 0791",
    "sg:postcode":"75149",
    "sg:province":"TX",
    "sg:tags":[
        "electric",
        "contractor"
    ],
    "wof:name":"Effectolite Contracting",
    "wof:placetype":"venue"
},
  "geometry": {"coordinates":[-96.600075,32.766967],"type":"Point"}
}