{
  "type": "Feature",
  "properties": {
    "iso:country":"US",
    "sg:address":"4347 W. Northwest Hwy. #120-116",
    "sg:city":"Dallas",
    "sg:classifiers":[
        {
            "category":"Sports & Exercise",
            "subcategory":"Sports Center",
            "type":"Entertainment"
        }
    ],
    "sg:phone":"+1 972 248 8867",
    "sg:postcode":"75220",
    "sg:province":"TX",
    "sg:tags":[
        "manager",
        "promoter"
    ],
    "sg:website":"http://www.quorumsports.com",
    "wof:name":"Quorum Sports Group",
    "wof:placetype":"venue"
},
  "geometry": {"coordinates":[-96.835527,32.863855],"type":"Point"}
}