{
  "type": "Feature",
  "properties": {
    "iso:country":"US",
    "sg:address":"5225 Hardway St",
    "sg:city":"Houston",
    "sg:classifiers":[
        {
            "category":"Organizations",
            "subcategory":"Religious Organization",
            "type":"Services"
        }
    ],
    "sg:phone":"+1 713 680 8761",
    "sg:postcode":"77092",
    "sg:province":"TX",
    "sg:tags":[
        "church"
    ],
    "wof:name":"Iglesia Hispana Pentecostal De",
    "wof:placetype":"venue"
},
  "geometry": {"coordinates":[-95.46855100000001,29.840243],"type":"Point"}
}