{
  "type": "Feature",
  "properties": {
    "iso:country":"US",
    "sg:address":"1025 N Stemmons Fwy",
    "sg:city":"Dallas",
    "sg:classifiers":[
        {
            "category":"Wholesale",
            "subcategory":"Furniture",
            "type":"Manufacturing & Wholesale Goods"
        }
    ],
    "sg:phone":"+1 214 742 5111",
    "sg:postcode":"75207",
    "sg:province":"TX",
    "wof:name":"Murrays Iron Works Inc",
    "wof:placetype":"venue"
},
  "geometry": {"coordinates":[-96.812665,32.786088],"type":"Point"}
}