{
  "type": "Feature",
  "properties": {
    "iso:country":"US",
    "sg:address":"801 S Hayden St",
    "sg:city":"Amarillo",
    "sg:classifiers":[
        {
            "category":"Building & Trades",
            "subcategory":"Plumbing",
            "type":"Services"
        }
    ],
    "sg:phone":"+1 806 373 3700",
    "sg:postcode":"79101",
    "sg:province":"AR",
    "sg:tags":[
        "conditioning",
        "air",
        "system",
        "contractor"
    ],
    "wof:name":"ROBERT Madden Inc",
    "wof:placetype":"venue"
},
  "geometry": {"coordinates":[-101.85076599999999,35.205998],"type":"Point"}
}