{
  "type": "Feature",
  "properties": {
    "iso:country":"US",
    "sg:address":"2800 Post Oak Blvd",
    "sg:city":"Houston",
    "sg:classifiers":[
        {
            "category":"Banks & Credit Unions",
            "subcategory":"Investment Brokerage",
            "type":"Services"
        }
    ],
    "sg:phone":"+1 713 993 0500",
    "sg:postcode":"77056",
    "sg:province":"TX",
    "sg:tags":[
        "investing"
    ],
    "wof:name":"Van Kampen-American Capital Marketing Inc",
    "wof:placetype":"venue"
},
  "geometry": {"coordinates":[-95.460899,29.7379],"type":"Point"}
}