{
  "type": "Feature",
  "properties": {
    "iso:country":"US",
    "sg:address":"200 Main St",
    "sg:city":"Kerrville",
    "sg:classifiers":[
        {
            "category":"Shopping",
            "subcategory":"Florist",
            "type":"Retail Goods"
        }
    ],
    "sg:phone":"+1 830 895 1965",
    "sg:postcode":"78028",
    "sg:province":"TX",
    "sg:tags":[
        "basket",
        "gift"
    ],
    "sg:website":"http://www.gloriasflowersandmore.com",
    "wof:name":"Gloria's Flowers & More",
    "wof:placetype":"venue"
},
  "geometry": {"coordinates":[-99.14582799999999,30.052031],"type":"Point"}
}