{
  "type": "Feature",
  "properties": {
    "iso:country":"US",
    "sg:address":"1901 Crockett Rd",
    "sg:city":"Palestine",
    "sg:classifiers":[
        {
            "category":"Personal",
            "subcategory":"Tanning Parlor",
            "type":"Services"
        },
        {
            "category":"Personal",
            "type":"Services"
        }
    ],
    "sg:phone":"+1 903 731 4621",
    "sg:postcode":"75801",
    "sg:province":"TX",
    "sg:tags":[
        "salon"
    ],
    "wof:name":"Island Tans",
    "wof:placetype":"venue"
},
  "geometry": {"coordinates":[-95.614172,31.740681],"type":"Point"}
}