{
  "type": "Feature",
  "properties": {
    "iso:country":"US",
    "sg:address":"901 College Pkwy",
    "sg:city":"Lewisville",
    "sg:classifiers":[
        {
            "category":"Organizations",
            "subcategory":"Religious Organization",
            "type":"Services"
        }
    ],
    "sg:phone":"+1 972 353 2518",
    "sg:postcode":"75077",
    "sg:province":"TX",
    "wof:name":"Lewisville Church Of Christ",
    "wof:placetype":"venue"
},
  "geometry": {"coordinates":[-97.01795,33.050889],"type":"Point"}
}