{
  "type": "Feature",
  "properties": {
    "iso:country":"US",
    "sg:address":"5000 Park Ln",
    "sg:city":"Dallas",
    "sg:classifiers":[
        {
            "category":"Restaurant",
            "type":"Food & Drink"
        }
    ],
    "sg:phone":"+1 972 732 6483",
    "sg:postcode":"75220",
    "sg:province":"TX",
    "sg:tags":[
        "eating"
    ],
    "wof:name":"LA Madeleine Cafe",
    "wof:placetype":"venue"
},
  "geometry": {"coordinates":[-96.821229,32.874049],"type":"Point"}
}