{
  "type": "Feature",
  "properties": {
    "iso:country":"US",
    "sg:address":"8400 Blanco Rd",
    "sg:city":"San Antonio",
    "sg:classifiers":[
        {
            "category":"Shopping",
            "subcategory":"News",
            "type":"Retail Goods"
        },
        {
            "category":"Manufacturing",
            "subcategory":"Printing",
            "type":"Manufacturing & Wholesale Goods"
        }
    ],
    "sg:phone":"+1 210 349 6667",
    "sg:postcode":"78216",
    "sg:province":"TX",
    "sg:tags":[
        "magazine",
        "periodical"
    ],
    "wof:name":"Our Kid's Magazine",
    "wof:placetype":"venue"
},
  "geometry": {"coordinates":[-98.50724599999999,29.543844],"type":"Point"}
}