{
  "type": "Feature",
  "properties": {
    "iso:country":"US",
    "sg:address":"2222 Southmore Ave Ste E",
    "sg:city":"Pasadena",
    "sg:classifiers":[
        {
            "category":"Restaurant",
            "type":"Food & Drink"
        }
    ],
    "sg:phone":"+1 713 475 9902",
    "sg:postcode":"77502",
    "sg:province":"TX",
    "wof:name":"Refresqueria Tamazula",
    "wof:placetype":"venue"
},
  "geometry": {"coordinates":[-95.18180099999999,29.6917],"type":"Point"}
}