{
  "type": "Feature",
  "properties": {
    "iso:country":"US",
    "sg:address":"5420 Gorman Rd",
    "sg:city":"Beaumont",
    "sg:classifiers":[
        {
            "category":"Manufacturing",
            "subcategory":"Tools & Machinery",
            "type":"Manufacturing & Wholesale Goods"
        }
    ],
    "sg:phone":"+1 409 840 5650",
    "sg:postcode":"77705",
    "sg:province":"TX",
    "sg:tags":[
        "machine",
        "shop"
    ],
    "sg:website":"www.tooltech.com",
    "wof:name":"Tool Tech Inc",
    "wof:placetype":"venue"
},
  "geometry": {"coordinates":[-94.098113,30.032834],"type":"Point"}
}