{
  "type": "Feature",
  "properties": {
    "iso:country":"US",
    "sg:address":"1508 Catamaran Ln",
    "sg:city":"Arlington",
    "sg:classifiers":[
        {
            "category":"Manufacturing",
            "subcategory":"Printing",
            "type":"Manufacturing & Wholesale Goods"
        }
    ],
    "sg:phone":"+1 817 860 5121",
    "sg:postcode":"76012",
    "sg:province":"TX",
    "sg:tags":[
        "publisher"
    ],
    "wof:name":"Interative Media Strategies",
    "wof:placetype":"venue"
},
  "geometry": {"coordinates":[-97.158632,32.756289],"type":"Point"}
}