{
  "type": "Feature",
  "properties": {
    "iso:country":"US",
    "sg:address":"4527 S State Hwy 91",
    "sg:city":"Denison",
    "sg:classifiers":[
        {
            "category":"Professional",
            "subcategory":"Business Services",
            "type":"Services"
        }
    ],
    "sg:phone":"+1 903 465 1777",
    "sg:postcode":"75020",
    "sg:province":"TX",
    "wof:name":"Indoor Market & Bazaar",
    "wof:placetype":"venue"
},
  "geometry": {"coordinates":[-96.566597,33.709354],"type":"Point"}
}