{
  "type": "Feature",
  "properties": {
    "iso:country":"US",
    "sg:address":"1801 Nottingham St",
    "sg:city":"Pasadena",
    "sg:classifiers":[
        {
            "category":"Freight",
            "type":"Transportation"
        }
    ],
    "sg:phone":"+1 713 472 1239",
    "sg:postcode":"77502",
    "sg:province":"TX",
    "sg:tags":[
        "local",
        "trucking"
    ],
    "wof:name":"Henry & Sons Trucking Service",
    "wof:placetype":"venue"
},
  "geometry": {"coordinates":[-95.20276,29.683757],"type":"Point"}
}