{
  "type": "Feature",
  "properties": {
    "iso:country":"US",
    "sg:address":"1708 Zuma Dr",
    "sg:city":"Arlington",
    "sg:classifiers":[
        {
            "category":"Professional",
            "type":"Services"
        }
    ],
    "sg:phone":"+1 817 469 6331",
    "sg:postcode":"76006",
    "sg:province":"TX",
    "wof:name":"Macs Career Corp",
    "wof:placetype":"venue"
},
  "geometry": {"coordinates":[-97.08475799999999,32.772025],"type":"Point"}
}