{
  "type": "Feature",
  "properties": {
    "iso:country":"US",
    "sg:address":"2600 Franklin Ave",
    "sg:city":"Waco",
    "sg:classifiers":[
        {
            "category":"Autos & Motor Vehicles",
            "subcategory":"Automobile Sales",
            "type":"Retail Goods"
        }
    ],
    "sg:phone":"+1 254 753 0710",
    "sg:postcode":"76710",
    "sg:province":"TX",
    "sg:tags":[
        "car",
        "used",
        "dealer"
    ],
    "wof:name":"Cen-Tex Motor Co Inc",
    "wof:placetype":"venue"
},
  "geometry": {"coordinates":[-97.15111400000001,31.538096],"type":"Point"}
}