{
  "type": "Feature",
  "properties": {
    "iso:country":"US",
    "sg:address":"5525 Henley St",
    "sg:city":"Santa Fe",
    "sg:classifiers":[
        {
            "category":"Building & Trades",
            "subcategory":"Construction",
            "type":"Services"
        }
    ],
    "sg:phone":"+1 281 337 6388",
    "sg:postcode":"77510",
    "sg:province":"TX",
    "sg:tags":[
        "hanging",
        "contractor"
    ],
    "wof:name":"Clear Lake Painting",
    "wof:placetype":"venue"
},
  "geometry": {"coordinates":[-95.103629,29.365279],"type":"Point"}
}