{
  "type": "Feature",
  "properties": {
    "iso:country":"US",
    "sg:address":"1214 N Post Oak Rd Ste 100",
    "sg:city":"Houston",
    "sg:classifiers":[
        {
            "category":"Health Services",
            "subcategory":"Chiropractor",
            "type":"Services"
        }
    ],
    "sg:phone":"+1 713 681 9100",
    "sg:postcode":"77055",
    "sg:province":"TX",
    "wof:name":"Nova Health Care Centers",
    "wof:placetype":"venue"
},
  "geometry": {"coordinates":[-95.454626,29.787769],"type":"Point"}
}