{
  "type": "Feature",
  "properties": {
    "iso:country":"US",
    "sg:address":"1004 N Louise St",
    "sg:city":"Atlanta",
    "sg:classifiers":[
        {
            "category":"Building & Trades",
            "subcategory":"Electrical",
            "type":"Services"
        }
    ],
    "sg:phone":"+1 903 796 1770",
    "sg:postcode":"75551",
    "sg:province":"TX",
    "sg:tags":[
        "industrial",
        "electrician",
        "contractors-commercial",
        "electric"
    ],
    "wof:name":"Dean's Electrical Service",
    "wof:placetype":"venue"
},
  "geometry": {"coordinates":[-94.1643,33.128992],"type":"Point"}
}