{
  "type": "Feature",
  "properties": {
    "iso:country":"US",
    "sg:address":"1414 New Boston Rd",
    "sg:city":"Texarkana",
    "sg:classifiers":[
        {
            "category":"Wholesale",
            "subcategory":"Office Equipment",
            "type":"Manufacturing & Wholesale Goods"
        }
    ],
    "sg:phone":"+1 903 793 3249",
    "sg:postcode":"75501",
    "sg:province":"TX",
    "sg:tags":[
        "machine",
        "duplicating",
        "copying"
    ],
    "wof:name":"Xerox Corp",
    "wof:placetype":"venue"
},
  "geometry": {"coordinates":[-94.058756,33.435112],"type":"Point"}
}