{
  "type": "Feature",
  "properties": {
    "iso:country":"US",
    "sg:address":"1106 8th Ave",
    "sg:city":"Canyon",
    "sg:classifiers":[
        {
            "category":"Professional",
            "subcategory":"Business Services",
            "type":"Services"
        }
    ],
    "sg:phone":"+1 806 655 6822",
    "sg:postcode":"79015",
    "sg:province":"TX",
    "wof:name":"Flatland Sales Co",
    "wof:placetype":"venue"
},
  "geometry": {"coordinates":[-101.933852,34.975652],"type":"Point"}
}