{
  "type": "Feature",
  "properties": {
    "iso:country":"US",
    "sg:address":"400 S I Rd",
    "sg:city":"Pharr",
    "sg:classifiers":[
        {
            "category":"Education",
            "subcategory":"School",
            "type":"Public Place"
        }
    ],
    "sg:phone":"+1 956 283 1700",
    "sg:postcode":"78577",
    "sg:province":"TX",
    "wof:name":"Vanguard Academy Charter Schl",
    "wof:placetype":"venue"
},
  "geometry": {"coordinates":[-98.16816300000001,26.189586],"type":"Point"}
}