{
  "type": "Feature",
  "properties": {
    "iso:country":"US",
    "sg:address":"1039 Lott Ave",
    "sg:city":"Austin",
    "sg:classifiers":[
        {
            "category":"Shopping",
            "subcategory":"Jewelry",
            "type":"Retail Goods"
        }
    ],
    "sg:phone":"+1 512 928 3163",
    "sg:postcode":"78721",
    "sg:province":"TX",
    "wof:name":"Naomis Gift & Jewelry",
    "wof:placetype":"venue"
},
  "geometry": {"coordinates":[-97.68214399999999,30.269929],"type":"Point"}
}