{
  "type": "Feature",
  "properties": {
    "iso:country":"US",
    "sg:address":"16008 N Evans Rd",
    "sg:city":"Schertz",
    "sg:classifiers":[
        {
            "category":"Professional",
            "subcategory":"Employment Agencies",
            "type":"Services"
        }
    ],
    "sg:phone":"+1 210 651 0667",
    "sg:postcode":"78154",
    "sg:province":"TX",
    "wof:name":"Yvonne Evans",
    "wof:placetype":"venue"
},
  "geometry": {"coordinates":[-98.30598000000001,29.584676],"type":"Point"}
}