{
  "type": "Feature",
  "properties": {
    "iso:country":"US",
    "sg:address":"312 W University Dr",
    "sg:city":"Mckinney",
    "sg:classifiers":[
        {
            "category":"Restaurant",
            "type":"Food & Drink"
        }
    ],
    "sg:menulink":"http://www.allmenus.com/tx/mckinney/204246-sonic/menu/",
    "sg:phone":"+1 972 562 7930",
    "sg:postcode":"75069",
    "sg:province":"TX",
    "sg:tags":[
        "burger",
        "american"
    ],
    "wof:name":"Sonic",
    "wof:placetype":"venue"
},
  "geometry": {"coordinates":[-96.619157,33.215285],"type":"Point"}
}