{
  "type": "Feature",
  "properties": {
    "iso:country":"US",
    "sg:address":"231 Oneoak Dr",
    "sg:city":"San Antonio",
    "sg:classifiers":[
        {
            "category":"Building & Trades",
            "subcategory":"Construction",
            "type":"Services"
        }
    ],
    "sg:phone":"+1 210 738 3781",
    "sg:postcode":"78228",
    "sg:province":"TX",
    "sg:tags":[
        "hanging",
        "contractor"
    ],
    "wof:name":"Reynolds Pro Painters",
    "wof:placetype":"venue"
},
  "geometry": {"coordinates":[-98.564938,29.484422],"type":"Point"}
}