{
  "type": "Feature",
  "properties": {
    "iso:country":"US",
    "sg:address":"1905 Towanda Dr",
    "sg:city":"Plano",
    "sg:classifiers":[
        {
            "category":"Professional",
            "type":"Services"
        }
    ],
    "sg:phone":"+1 972 424 9327",
    "sg:postcode":"75074",
    "sg:province":"TX",
    "wof:name":"Biggs 330000599231 Russell",
    "wof:placetype":"venue"
},
  "geometry": {"coordinates":[-96.685057,33.040545],"type":"Point"}
}