{
  "type": "Feature",
  "properties": {
    "iso:country":"US",
    "sg:address":"995 Bunker Hill Rd",
    "sg:city":"Houston",
    "sg:classifiers":[
        {
            "category":"Autos & Motor Vehicles",
            "subcategory":"Fuel & Gas Station",
            "type":"Retail Goods"
        }
    ],
    "sg:phone":"+1 713 932 6258",
    "sg:postcode":"77024",
    "sg:province":"TX",
    "sg:tags":[
        "station",
        "gasoline"
    ],
    "wof:name":"Texaco",
    "wof:placetype":"venue"
},
  "geometry": {"coordinates":[-95.53179900000001,29.781569],"type":"Point"}
}