{
  "type": "Feature",
  "properties": {
    "iso:country":"US",
    "sg:address":"4905 Commercial Park Dr",
    "sg:city":"Austin",
    "sg:classifiers":[
        {
            "category":"Retail",
            "subcategory":"Repair Shop",
            "type":"Services"
        }
    ],
    "sg:phone":"+1 512 926 8888",
    "sg:postcode":"78724",
    "sg:province":"TX",
    "wof:name":"American Hermedics",
    "wof:placetype":"venue"
},
  "geometry": {"coordinates":[-97.656593,30.324229],"type":"Point"}
}