{
  "type": "Feature",
  "properties": {
    "iso:country":"US",
    "sg:address":"4455 Alpha Rd",
    "sg:city":"Dallas",
    "sg:classifiers":[
        {
            "category":"Real Estate",
            "subcategory":"Real Estate Agent",
            "type":"Services"
        }
    ],
    "sg:phone":"+1 972 233 8888",
    "sg:postcode":"75244",
    "sg:province":"TX",
    "sg:tags":[
        "consultant"
    ],
    "wof:name":"RANDALL Gonzalez Co",
    "wof:placetype":"venue"
},
  "geometry": {"coordinates":[-96.832252,32.933148],"type":"Point"}
}