{
  "type": "Feature",
  "properties": {
    "iso:country":"US",
    "sg:address":"1204 E Corral Ave",
    "sg:city":"Kingsville",
    "sg:classifiers":[
        {
            "category":"Retail",
            "subcategory":"Repair Shop",
            "type":"Services"
        }
    ],
    "sg:phone":"+1 361 592 1405",
    "sg:postcode":"78363",
    "sg:province":"TX",
    "sg:tags":[
        "welding"
    ],
    "wof:name":"Joe's Welding & Leasing",
    "wof:placetype":"venue"
},
  "geometry": {"coordinates":[-97.851124,27.530781],"type":"Point"}
}