{
  "type": "Feature",
  "properties": {
    "iso:country":"US",
    "sg:address":"1417 Perry St",
    "sg:city":"Irving",
    "sg:classifiers":[
        {
            "category":"Freight",
            "type":"Transportation"
        }
    ],
    "sg:phone":"+1 972 445 8420",
    "sg:postcode":"75060",
    "sg:province":"TX",
    "wof:name":"Patterson Auto Transport",
    "wof:placetype":"venue"
},
  "geometry": {"coordinates":[-96.926586,32.813114],"type":"Point"}
}