{
  "type": "Feature",
  "properties": {
    "iso:country":"US",
    "sg:address":"4304 E Central Texas Expy",
    "sg:city":"Killeen",
    "sg:classifiers":[
        {
            "category":"Insurance",
            "subcategory":"Insurance Agent",
            "type":"Services"
        }
    ],
    "sg:phone":"+1 254 690 9220",
    "sg:postcode":"76543",
    "sg:province":"TX",
    "wof:name":"State Frm Insur Lnnie Rush Agt",
    "wof:placetype":"venue"
},
  "geometry": {"coordinates":[-97.698691,31.079789],"type":"Point"}
}