{
  "type": "Feature",
  "properties": {
    "iso:country":"US",
    "sg:address":"15402 Vantage Pkwy E",
    "sg:city":"Houston",
    "sg:classifiers":[
        {
            "category":"Home & Garden",
            "subcategory":"Furniture",
            "type":"Retail Goods"
        }
    ],
    "sg:phone":"+1 281 441 2324",
    "sg:postcode":"77032",
    "sg:province":"TX",
    "sg:tags":[
        "work",
        "cabinetry",
        "custom"
    ],
    "wof:name":"S K Cabinets",
    "wof:placetype":"venue"
},
  "geometry": {"coordinates":[-95.36647600000001,29.943337],"type":"Point"}
}