{
  "type": "Feature",
  "properties": {
    "iso:country":"US",
    "sg:address":"704 N Minter Ave",
    "sg:city":"Throckmorton",
    "sg:classifiers":[
        {
            "category":"Organizations",
            "subcategory":"Religious Organization",
            "type":"Services"
        }
    ],
    "sg:phone":"+1 940 849 0191",
    "sg:postcode":"76483",
    "sg:province":"TX",
    "wof:name":"Christian Center Church",
    "wof:placetype":"venue"
},
  "geometry": {"coordinates":[-99.177217,33.189086],"type":"Point"}
}