{
  "type": "Feature",
  "properties": {
    "iso:country":"US",
    "sg:address":"8201 Manderville Ln",
    "sg:city":"Dallas",
    "sg:classifiers":[
        {
            "category":"Shopping",
            "subcategory":"Used Merchandise",
            "type":"Retail Goods"
        }
    ],
    "sg:phone":"+1 214 503 9055",
    "sg:postcode":"75231",
    "sg:province":"TX",
    "wof:name":"Harris Liquidation",
    "wof:placetype":"venue"
},
  "geometry": {"coordinates":[-96.76526800000001,32.892178],"type":"Point"}
}