{
  "type": "Feature",
  "properties": {
    "iso:country":"US",
    "sg:address":"2924 Bill Owens Pkwy",
    "sg:city":"Longview",
    "sg:classifiers":[
        {
            "category":"Restaurant",
            "type":"Food & Drink"
        }
    ],
    "sg:phone":"+1 903 297 1111",
    "sg:postcode":"75605",
    "sg:province":"TX",
    "wof:name":"Pizza Hut",
    "wof:placetype":"venue"
},
  "geometry": {"coordinates":[-94.767657,32.536685],"type":"Point"}
}