{
  "type": "Feature",
  "properties": {
    "iso:country":"US",
    "sg:address":"1503 Gulf Pump Rd",
    "sg:city":"Crosby",
    "sg:classifiers":[
        {
            "category":"Manufacturing",
            "subcategory":"Metals",
            "type":"Manufacturing & Wholesale Goods"
        }
    ],
    "sg:phone":"+1 281 328 1641",
    "sg:postcode":"77532",
    "sg:province":"TX",
    "sg:tags":[
        "steel",
        "fabrication",
        "structural"
    ],
    "wof:name":"Marway Custom Fab Inc",
    "wof:placetype":"venue"
},
  "geometry": {"coordinates":[-95.084316,29.878464],"type":"Point"}
}