{
  "type": "Feature",
  "properties": {
    "iso:country":"US",
    "sg:address":"7015 Manor Way",
    "sg:city":"Humble",
    "sg:classifiers":[
        {
            "category":"Recreation",
            "type":"Entertainment"
        }
    ],
    "sg:phone":"+1 281 319 4444",
    "sg:postcode":"77396",
    "sg:province":"TX",
    "sg:tags":[
        "pool",
        "swimming"
    ],
    "wof:name":"Chances R",
    "wof:placetype":"venue"
},
  "geometry": {"coordinates":[-95.28492199999999,29.941436],"type":"Point"}
}