{
  "type": "Feature",
  "properties": {
    "iso:country":"US",
    "sg:address":"955 E Campbell Rd",
    "sg:city":"Richardson",
    "sg:classifiers":[
        {
            "category":"Restaurant",
            "type":"Food & Drink"
        }
    ],
    "sg:menulink":"http://www.allmenus.com/tx/northeast/139598-quiznos-sub/menu/",
    "sg:phone":"+1 972 690 8008",
    "sg:postcode":"75081",
    "sg:province":"TX",
    "sg:tags":[
        "wrap",
        "american",
        "sandwich"
    ],
    "wof:name":"Quiznos Sub",
    "wof:placetype":"venue"
},
  "geometry": {"coordinates":[-96.70884599999999,32.975905],"type":"Point"}
}