{
  "type": "Feature",
  "properties": {
    "iso:country":"US",
    "sg:address":"730 Wilken St",
    "sg:city":"Houston",
    "sg:classifiers":[
        {
            "category":"Professional",
            "subcategory":"Management & Consulting",
            "type":"Services"
        }
    ],
    "sg:phone":"+1 713 869 1167",
    "sg:postcode":"77008",
    "sg:province":"TX",
    "sg:tags":[
        "business"
    ],
    "wof:name":"Takoda Consulting Group",
    "wof:placetype":"venue"
},
  "geometry": {"coordinates":[-95.38988500000001,29.80131],"type":"Point"}
}