{
  "type": "Feature",
  "properties": {
    "iso:country":"US",
    "sg:address":"22078 E Knox Dr",
    "sg:city":"Porter",
    "sg:classifiers":[
        {
            "category":"Professional",
            "type":"Services"
        }
    ],
    "sg:phone":"+1 281 354 1656",
    "sg:postcode":"77365",
    "sg:province":"TX",
    "wof:name":"T & T Service",
    "wof:placetype":"venue"
},
  "geometry": {"coordinates":[-95.230592,30.078662],"type":"Point"}
}