{
  "type": "Feature",
  "properties": {
    "iso:country":"US",
    "sg:address":"2206 S Bonham St",
    "sg:city":"Amarillo",
    "sg:classifiers":[
        {
            "category":"Building & Trades",
            "subcategory":"Construction",
            "type":"Services"
        }
    ],
    "sg:phone":"+1 806 355 2980",
    "sg:postcode":"79109",
    "sg:province":"TX",
    "sg:tags":[
        "speculative",
        "remodeling",
        "builder"
    ],
    "wof:name":"Marvin F Winton Builders",
    "wof:placetype":"venue"
},
  "geometry": {"coordinates":[-101.859146,35.187515],"type":"Point"}
}