{
  "type": "Feature",
  "properties": {
    "iso:country":"US",
    "sg:address":"14405 Hurber Rd",
    "sg:city":"Dalhart",
    "sg:phone":"+1 806 362 4671",
    "sg:postcode":"79022",
    "sg:province":"TX",
    "sg:tags":[
        "farm",
        "grain",
        "cash"
    ],
    "wof:name":"Bill Sheets",
    "wof:placetype":"venue"
},
  "geometry": {"coordinates":[-102.860338,36.389648],"type":"Point"}
}