{
  "type": "Feature",
  "properties": {
    "iso:country":"US",
    "sg:address":"3415 Custer Rd",
    "sg:city":"Plano",
    "sg:classifiers":[
        {
            "category":"Real Estate",
            "subcategory":"Real Estate Agent",
            "type":"Services"
        }
    ],
    "sg:phone":"+1 972 596 5541",
    "sg:postcode":"75023",
    "sg:province":"TX",
    "wof:name":"North Point Realtors",
    "wof:placetype":"venue"
},
  "geometry": {"coordinates":[-96.73347699999999,33.042206],"type":"Point"}
}