{
  "type": "Feature",
  "properties": {
    "iso:country":"US",
    "sg:address":"3304 Troup Hwy",
    "sg:city":"Tyler",
    "sg:classifiers":[
        {
            "category":"Restaurant",
            "type":"Food & Drink"
        }
    ],
    "sg:phone":"+1 903 592 6771",
    "sg:postcode":"75701",
    "sg:province":"TX",
    "sg:website":"www.bennigans.com",
    "wof:name":"Bennigan's Grill & Tavern",
    "wof:placetype":"venue"
},
  "geometry": {"coordinates":[-95.275221,32.313272],"type":"Point"}
}