{
  "type": "Feature",
  "properties": {
    "iso:country":"US",
    "sg:address":"9703 Westward Drive",
    "sg:city":"Austin",
    "sg:classifiers":[
        {
            "category":"Building & Trades",
            "subcategory":"Plumbing",
            "type":"Services"
        }
    ],
    "sg:phone":"+1 512 263 5540",
    "sg:postcode":"78733",
    "sg:province":"TX",
    "wof:name":"The Magnum Plumbing Company",
    "wof:placetype":"venue"
},
  "geometry": {"coordinates":[-97.87178,30.328571],"type":"Point"}
}