{
  "type": "Feature",
  "properties": {
    "iso:country":"US",
    "sg:address":"1111 E Davis St",
    "sg:city":"Mesquite",
    "sg:classifiers":[
        {
            "category":"Professional",
            "type":"Services"
        },
        {
            "category":"Restaurant",
            "type":"Food & Drink"
        }
    ],
    "sg:menulink":"http://www.allmenus.com/tx/northeast/223708-chicken-express/menu/",
    "sg:phone":"+1 972 288 3400",
    "sg:postcode":"75149",
    "sg:province":"TX",
    "sg:tags":[
        "american"
    ],
    "wof:name":"Chicken Express",
    "wof:placetype":"venue"
},
  "geometry": {"coordinates":[-96.583916,32.76444],"type":"Point"}
}