{
  "type": "Feature",
  "properties": {
    "iso:country":"US",
    "sg:address":"2323 Timber Shadows Dr B",
    "sg:city":"Kingwood",
    "sg:classifiers":[
        {
            "category":"Health Services",
            "subcategory":"Doctor",
            "type":"Services"
        }
    ],
    "sg:phone":"+1 281 359 4858",
    "sg:postcode":"77339",
    "sg:province":"TX",
    "sg:tags":[
        "physician",
        "surgeon"
    ],
    "sg:website":"http://www.healthpartners.com",
    "wof:name":"Healthpartners, Inc.",
    "wof:placetype":"venue"
},
  "geometry": {"coordinates":[-95.23071400000001,30.050696],"type":"Point"}
}