{
  "type": "Feature",
  "properties": {
    "iso:country":"US",
    "sg:address":"400 Hurst St",
    "sg:city":"Center",
    "sg:classifiers":[
        {
            "category":"Place Of Worship",
            "subcategory":"Church",
            "type":"Public Place"
        },
        {
            "category":"Place Of Worship",
            "type":"Public Place"
        }
    ],
    "sg:phone":"+1 936 598 3785",
    "sg:postcode":"75935",
    "sg:province":"TX",
    "sg:tags":[
        "nazarene",
        "churches-church",
        "churches-nazarene"
    ],
    "wof:name":"Church of The Nazarene Parsonage",
    "wof:placetype":"venue"
},
  "geometry": {"coordinates":[-94.188698,31.79265],"type":"Point"}
}