{
  "type": "Feature",
  "properties": {
    "iso:country":"US",
    "sg:address":"109 Duluth Ln",
    "sg:city":"Brownsville",
    "sg:classifiers":[
        {
            "category":"Building & Trades",
            "subcategory":"Electrical",
            "type":"Services"
        }
    ],
    "sg:phone":"+1 956 542 6864",
    "sg:postcode":"78520",
    "sg:province":"TX",
    "sg:tags":[
        "electric",
        "contractor"
    ],
    "wof:name":"Salas Electric",
    "wof:placetype":"venue"
},
  "geometry": {"coordinates":[-97.51998,25.954348],"type":"Point"}
}