{
  "type": "Feature",
  "properties": {
    "iso:country":"US",
    "sg:address":"3443 McCart Ave",
    "sg:city":"Fort Worth",
    "sg:classifiers":[
        {
            "category":"Social Services",
            "subcategory":"Child Care",
            "type":"Services"
        }
    ],
    "sg:phone":"+1 817 927 0871",
    "sg:postcode":"76110",
    "sg:province":"TX",
    "sg:tags":[
        "kindergarten",
        "academic",
        "school",
        "day"
    ],
    "wof:name":"Dare Daisy School Inc",
    "wof:placetype":"venue"
},
  "geometry": {"coordinates":[-97.352887,32.700016],"type":"Point"}
}