{
  "type": "Feature",
  "properties": {
    "iso:country":"US",
    "sg:address":"10609 Pineview Ln",
    "sg:city":"Frisco",
    "sg:classifiers":[
        {
            "category":"Banks & Credit Unions",
            "subcategory":"Bank",
            "type":"Services"
        }
    ],
    "sg:phone":"+1 972 987 5087",
    "sg:postcode":"75035",
    "sg:province":"TX",
    "sg:tags":[
        "consultant",
        "loan",
        "government",
        "trade"
    ],
    "wof:name":"Charlie Reed SBA Ln Mktg Cnslt",
    "wof:placetype":"venue"
},
  "geometry": {"coordinates":[-96.787761,33.150676],"type":"Point"}
}