{
  "type": "Feature",
  "properties": {
    "iso:country":"US",
    "sg:address":"3701 McCart Ave",
    "sg:city":"Fort Worth",
    "sg:classifiers":[
        {
            "category":"Manufacturing",
            "subcategory":"Tools & Machinery",
            "type":"Manufacturing & Wholesale Goods"
        }
    ],
    "sg:phone":"+1 817 924 9561",
    "sg:postcode":"76110",
    "sg:province":"TX",
    "sg:tags":[
        "pattern",
        "industrial",
        "mfg"
    ],
    "wof:name":"Ferguson Woodcraft Inc",
    "wof:placetype":"venue"
},
  "geometry": {"coordinates":[-97.352986,32.694319],"type":"Point"}
}