{
  "type": "Feature",
  "properties": {
    "iso:country":"US",
    "sg:address":"216 S el Paso St",
    "sg:city":"El Paso",
    "sg:classifiers":[
        {
            "category":"Shopping",
            "subcategory":"Used Merchandise",
            "type":"Retail Goods"
        },
        {
            "category":"Wholesale",
            "subcategory":"Jewelry",
            "type":"Manufacturing & Wholesale Goods"
        }
    ],
    "sg:phone":"+1 915 533 3334",
    "sg:postcode":"79901",
    "sg:province":"TX",
    "sg:tags":[
        "platinum",
        "silver",
        "gold"
    ],
    "wof:name":"Dave's Loan Co",
    "wof:placetype":"venue"
},
  "geometry": {"coordinates":[-106.488615,31.756883],"type":"Point"}
}