{
  "type": "Feature",
  "properties": {
    "iso:country":"US",
    "sg:address":"8850 Jameel Rd",
    "sg:city":"Houston",
    "sg:classifiers":[
        {
            "category":"Wholesale",
            "subcategory":"Painting Supplies",
            "type":"Manufacturing & Wholesale Goods"
        }
    ],
    "sg:phone":"+1 713 688 5111",
    "sg:postcode":"77040",
    "sg:province":"TX",
    "sg:tags":[
        "paint"
    ],
    "sg:website":"www.sherwinwilliams.com",
    "wof:name":"Sherwin-Williams Paints",
    "wof:placetype":"venue"
},
  "geometry": {"coordinates":[-95.52762199999999,29.857542],"type":"Point"}
}