{
  "type": "Feature",
  "properties": {
    "iso:country":"US",
    "sg:address":"9751 Walnut St",
    "sg:city":"Dallas",
    "sg:classifiers":[
        {
            "category":"Restaurant",
            "type":"Food & Drink"
        }
    ],
    "sg:phone":"+1 214 575 3666",
    "sg:postcode":"75243",
    "sg:province":"TX",
    "sg:tags":[
        "shop",
        "coffee",
        "eating"
    ],
    "wof:name":"Cafe & Bida Hanh",
    "wof:placetype":"venue"
},
  "geometry": {"coordinates":[-96.72165200000001,32.924607],"type":"Point"}
}