{
  "type": "Feature",
  "properties": {
    "iso:country":"US",
    "sg:address":"10206 Telephone Rd",
    "sg:city":"Houston",
    "sg:classifiers":[
        {
            "category":"Professional",
            "subcategory":"Business Services",
            "type":"Services"
        }
    ],
    "sg:phone":"+1 713 991 3323",
    "sg:postcode":"77075",
    "sg:province":"TX",
    "wof:name":"IXE Dollar Express",
    "wof:placetype":"venue"
},
  "geometry": {"coordinates":[-95.28539600000001,29.620079],"type":"Point"}
}