{
  "type": "Feature",
  "properties": {
    "iso:country":"US",
    "sg:address":"8013 New Sulphur Springs Rd",
    "sg:city":"San Antonio",
    "sg:classifiers":[
        {
            "category":"Retail",
            "subcategory":"Animal Services",
            "type":"Services"
        }
    ],
    "sg:phone":"+1 210 648 9141",
    "sg:postcode":"78263",
    "sg:province":"TX",
    "wof:name":"Euro Dog Center",
    "wof:placetype":"venue"
},
  "geometry": {"coordinates":[-98.33635200000001,29.357503],"type":"Point"}
}