{
  "type": "Feature",
  "properties": {
    "iso:country":"US",
    "sg:address":"5310 E Belknap St",
    "sg:city":"Haltom City",
    "sg:classifiers":[
        {
            "category":"Travel",
            "subcategory":"Travel Agent",
            "type":"Entertainment"
        }
    ],
    "sg:phone":"+1 817 759 9663",
    "sg:postcode":"76117",
    "sg:province":"TX",
    "sg:tags":[
        "agency",
        "bureau"
    ],
    "wof:name":"A S Tours & Legal Svc",
    "wof:placetype":"venue"
},
  "geometry": {"coordinates":[-97.269445,32.796049],"type":"Point"}
}