{
  "type": "Feature",
  "properties": {
    "iso:country":"US",
    "sg:address":"2100 Ranch Rd 12",
    "sg:city":"San Marcos",
    "sg:classifiers":[
        {
            "category":"Food & Beverages",
            "subcategory":"Groceries & Convenience Stores",
            "type":"Retail Goods"
        }
    ],
    "sg:phone":"+1 512 396 3433",
    "sg:postcode":"78666",
    "sg:province":"TX",
    "wof:name":"Pac-N-Sac Drive In Grocery",
    "wof:placetype":"venue"
},
  "geometry": {"coordinates":[-97.973894,29.898923],"type":"Point"}
}