{
  "type": "Feature",
  "properties": {
    "iso:country":"US",
    "sg:address":"606 SE 4th St",
    "sg:city":"Seminole",
    "sg:classifiers":[
        {
            "category":"Building & Trades",
            "subcategory":"Construction",
            "type":"Services"
        }
    ],
    "sg:phone":"+1 432 758 9512",
    "sg:postcode":"79360",
    "sg:province":"TX",
    "sg:tags":[
        "painting",
        "commercial",
        "contractor"
    ],
    "wof:name":"Braun Construction",
    "wof:placetype":"venue"
},
  "geometry": {"coordinates":[-102.64102699999999,32.712107],"type":"Point"}
}