{
  "type": "Feature",
  "properties": {
    "iso:country":"US",
    "sg:address":"13485 Wetmore Rd",
    "sg:city":"San Antonio",
    "sg:classifiers":[
        {
            "category":"Shopping",
            "subcategory":"Gifts & Souvenirs",
            "type":"Retail Goods"
        }
    ],
    "sg:phone":"+1 210 490 8827",
    "sg:postcode":"78247",
    "sg:province":"TX",
    "wof:name":"Irish Cajun",
    "wof:placetype":"venue"
},
  "geometry": {"coordinates":[-98.42178199999999,29.561445],"type":"Point"}
}