{
  "type": "Feature",
  "properties": {
    "iso:country":"US",
    "sg:address":"607 Hill Ave",
    "sg:city":"New Braunfels",
    "sg:classifiers":[
        {
            "category":"Building & Trades",
            "subcategory":"Construction",
            "type":"Services"
        }
    ],
    "sg:phone":"+1 830 629 6471",
    "sg:postcode":"78130",
    "sg:province":"TX",
    "sg:tags":[
        "general",
        "contractor"
    ],
    "wof:name":"C W Builders",
    "wof:placetype":"venue"
},
  "geometry": {"coordinates":[-98.11934100000001,29.695926],"type":"Point"}
}