{
  "type": "Feature",
  "properties": {
    "iso:country":"US",
    "sg:address":"409 9th St",
    "sg:city":"Huntsville",
    "sg:classifiers":[
        {
            "category":"Organizations",
            "subcategory":"Religious Organization",
            "type":"Services"
        }
    ],
    "sg:phone":"+1 936 294 0215",
    "sg:postcode":"77320",
    "sg:province":"TX",
    "sg:tags":[
        "church"
    ],
    "wof:name":"Templo Crusto Rey",
    "wof:placetype":"venue"
},
  "geometry": {"coordinates":[-95.539495,30.726372],"type":"Point"}
}