{
  "type": "Feature",
  "properties": {
    "iso:country":"US",
    "sg:address":"3027 N Lamar Blvd",
    "sg:city":"Austin",
    "sg:classifiers":[
        {
            "category":"Personal",
            "subcategory":"Beauty Salon",
            "type":"Services"
        }
    ],
    "sg:phone":"+1 512 454 5225",
    "sg:postcode":"78705",
    "sg:province":"TX",
    "sg:tags":[
        "shop"
    ],
    "wof:name":"Steven Todd Hair Studio",
    "wof:placetype":"venue"
},
  "geometry": {"coordinates":[-97.74624,30.300048],"type":"Point"}
}