{
  "type": "Feature",
  "properties": {
    "iso:country":"US",
    "sg:address":"1710 Arvada Dr",
    "sg:city":"Richardson",
    "sg:classifiers":[
        {
            "category":"Shopping",
            "subcategory":"Hobbies, Toys, & Games",
            "type":"Retail Goods"
        }
    ],
    "sg:phone":"+1 972 644 1424",
    "sg:postcode":"75081",
    "sg:province":"TX",
    "sg:tags":[
        "basket"
    ],
    "wof:name":"Basket Creations By Donna",
    "wof:placetype":"venue"
},
  "geometry": {"coordinates":[-96.69240000000001,32.971416],"type":"Point"}
}