{
  "type": "Feature",
  "properties": {
    "iso:country":"US",
    "sg:address":"1206 Walnut St",
    "sg:city":"Texarkana",
    "sg:classifiers":[
        {
            "category":"Professional",
            "subcategory":"Business Services",
            "type":"Services"
        }
    ],
    "sg:phone":"+1 903 794 5033",
    "sg:postcode":"75501",
    "sg:province":"TX",
    "sg:tags":[
        "consultant",
        "coach"
    ],
    "wof:name":"Walnut House",
    "wof:placetype":"venue"
},
  "geometry": {"coordinates":[-94.045222,33.432084],"type":"Point"}
}