{
  "type": "Feature",
  "properties": {
    "iso:country":"US",
    "sg:address":"14777 Wunderlich Dr",
    "sg:city":"Houston",
    "sg:classifiers":[
        {
            "category":"Professional",
            "subcategory":"Accounting & Tax Preparation",
            "type":"Services"
        }
    ],
    "sg:phone":"+1 281 379 6921",
    "sg:postcode":"77069",
    "sg:province":"TX",
    "wof:name":"Richard Meredith Co In",
    "wof:placetype":"venue"
},
  "geometry": {"coordinates":[-95.511962,29.993349],"type":"Point"}
}