{
  "type": "Feature",
  "properties": {
    "iso:country":"US",
    "sg:address":"411 W Bernard Dr",
    "sg:city":"East Bernard",
    "sg:classifiers":[
        {
            "category":"Personal",
            "subcategory":"Beauty Salon",
            "type":"Services"
        }
    ],
    "sg:phone":"+1 979 335 7929",
    "sg:postcode":"77435",
    "sg:province":"TX",
    "sg:tags":[
        "shop"
    ],
    "wof:name":"Rejsek Scissor Shack",
    "wof:placetype":"venue"
},
  "geometry": {"coordinates":[-96.05887,29.534989],"type":"Point"}
}