{
  "type": "Feature",
  "properties": {
    "iso:country":"US",
    "sg:address":"245 E Sunset Dr",
    "sg:city":"Trinity",
    "sg:classifiers":[
        {
            "category":"Building & Trades",
            "subcategory":"Construction",
            "type":"Services"
        },
        {
            "category":"Home & Garden",
            "subcategory":"Mobile Homes",
            "type":"Retail Goods"
        }
    ],
    "sg:phone":"+1 936 594 5925",
    "sg:postcode":"75862",
    "sg:province":"TX",
    "sg:tags":[
        "manufactured",
        "housing-communities",
        "transporting"
    ],
    "wof:name":"Bogs Mobile Home Transport & S",
    "wof:placetype":"venue"
},
  "geometry": {"coordinates":[-95.29061400000001,30.910312],"type":"Point"}
}