{
  "type": "Feature",
  "properties": {
    "iso:country":"US",
    "sg:address":"14911 Trecastle Dr",
    "sg:city":"Channelview",
    "sg:classifiers":[
        {
            "category":"Professional",
            "subcategory":"Management & Consulting",
            "type":"Services"
        }
    ],
    "sg:phone":"+1 281 457 1238",
    "sg:postcode":"77530",
    "sg:province":"TX",
    "sg:tags":[
        "business"
    ],
    "wof:name":"Heartland Consulting",
    "wof:placetype":"venue"
},
  "geometry": {"coordinates":[-95.155562,29.795213],"type":"Point"}
}