{
  "type": "Feature",
  "properties": {
    "iso:country":"US",
    "sg:address":"19 Fosters Green Dr",
    "sg:city":"Sugar Land",
    "sg:classifiers":[
        {
            "category":"Farming",
            "subcategory":"Vineyard",
            "type":"Manufacturing & Wholesale Goods"
        }
    ],
    "sg:phone":"+1 281 565 5444",
    "sg:postcode":"77479",
    "sg:province":"TX",
    "sg:tags":[
        "beverage",
        "grape"
    ],
    "wof:name":"Live Oak Vinyard",
    "wof:placetype":"venue"
},
  "geometry": {"coordinates":[-95.671092,29.598728],"type":"Point"}
}