{
  "type": "Feature",
  "properties": {
    "iso:country":"US",
    "sg:address":"14 Cypress Ridge Ln",
    "sg:city":"Sugar Land",
    "sg:classifiers":[
        {
            "category":"Professional",
            "subcategory":"Management & Consulting",
            "type":"Services"
        }
    ],
    "sg:phone":"+1 281 980 5524",
    "sg:postcode":"77479",
    "sg:province":"TX",
    "sg:tags":[
        "personal",
        "company",
        "john",
        "holding",
        "for"
    ],
    "wof:name":"Jeh Management Co LLC",
    "wof:placetype":"venue"
},
  "geometry": {"coordinates":[-95.599059,29.567471],"type":"Point"}
}