{
  "type": "Feature",
  "properties": {
    "iso:country":"US",
    "sg:address":"3004 Medical Arts St",
    "sg:city":"Austin",
    "sg:classifiers":[
        {
            "category":"Health Services",
            "subcategory":"Health Practitioner",
            "type":"Services"
        }
    ],
    "sg:phone":"+1 214 542 3260",
    "sg:postcode":"78705",
    "sg:province":"TX",
    "sg:tags":[
        "acupuncture"
    ],
    "sg:website":"www.blackturtleacupuncture.com",
    "wof:name":"Jacob C Yo, LAc",
    "wof:placetype":"venue"
},
  "geometry": {"coordinates":[-97.728061,30.289894],"type":"Point"}
}