{
  "type": "Feature",
  "properties": {
    "iso:country":"US",
    "sg:address":"1037 S Beckley Ave",
    "sg:city":"Dallas",
    "sg:classifiers":[
        {
            "category":"Retail",
            "subcategory":"Auto Repair",
            "type":"Services"
        }
    ],
    "sg:phone":"+1 214 941 3860",
    "sg:postcode":"75203",
    "sg:province":"TX",
    "wof:name":"Chachos Auto Repair",
    "wof:placetype":"venue"
},
  "geometry": {"coordinates":[-96.822701,32.7356],"type":"Point"}
}