{
  "type": "Feature",
  "properties": {
    "iso:country":"US",
    "sg:address":"17401 Mines Rd",
    "sg:city":"Laredo",
    "sg:classifiers":[
        {
            "category":"Wholesale",
            "subcategory":"Petroleum",
            "type":"Manufacturing & Wholesale Goods"
        }
    ],
    "sg:phone":"+1 956 724 7191",
    "sg:postcode":"78045",
    "sg:province":"TX",
    "sg:tags":[
        "pipe",
        "line",
        "company"
    ],
    "sg:website":"www.duke-energy.com",
    "wof:name":"Duke Energy Field Svc",
    "wof:placetype":"venue"
},
  "geometry": {"coordinates":[-99.54818400000001,27.641538],"type":"Point"}
}