{
  "type": "Feature",
  "properties": {
    "iso:country":"US",
    "sg:address":"9715 Carnegie Ave",
    "sg:city":"El Paso",
    "sg:classifiers":[
        {
            "category":"Freight",
            "type":"Transportation"
        }
    ],
    "sg:phone":"+1 915 595 0174",
    "sg:postcode":"79925",
    "sg:province":"TX",
    "sg:tags":[
        "operator",
        "delivery",
        "local",
        "trucking"
    ],
    "wof:name":"Priority Delivery Svcs El Paso",
    "wof:placetype":"venue"
},
  "geometry": {"coordinates":[-106.355901,31.796458],"type":"Point"}
}