{
  "type": "Feature",
  "properties": {
    "iso:country":"US",
    "sg:address":"5206 Sioux Ln",
    "sg:city":"Austin",
    "sg:classifiers":[
        {
            "category":"Retail",
            "subcategory":"Repair Shop",
            "type":"Services"
        }
    ],
    "sg:phone":"+1 512 266 1835",
    "sg:postcode":"78734",
    "sg:province":"TX",
    "sg:tags":[
        "saws-sharpen"
    ],
    "wof:name":"Waynes Mobile Sharpening",
    "wof:placetype":"venue"
},
  "geometry": {"coordinates":[-97.921156,30.411848],"type":"Point"}
}