{
  "type": "Feature",
  "properties": {
    "iso:country":"US",
    "sg:address":"4100 Westheimer Rd Ste 113",
    "sg:city":"Houston",
    "sg:classifiers":[
        {
            "category":"Professional",
            "subcategory":"Employment Agencies",
            "type":"Services"
        }
    ],
    "sg:phone":"+1 713 961 1001",
    "sg:postcode":"77027",
    "sg:province":"TX",
    "wof:name":"Nurse Finders of Houston Inc",
    "wof:placetype":"venue"
},
  "geometry": {"coordinates":[-95.44789900000001,29.741699],"type":"Point"}
}