{
  "type": "Feature",
  "properties": {
    "iso:country":"US",
    "sg:address":"4401 Oak Brook Ct",
    "sg:city":"Arlington",
    "sg:classifiers":[
        {
            "category":"Shopping",
            "subcategory":"Jewelry",
            "type":"Retail Goods"
        }
    ],
    "sg:phone":"+1 817 572 2449",
    "sg:postcode":"76016",
    "sg:province":"TX",
    "sg:tags":[
        "jeweler"
    ],
    "wof:name":"Gems In The Snow",
    "wof:placetype":"venue"
},
  "geometry": {"coordinates":[-97.191323,32.676877],"type":"Point"}
}