{
  "type": "Feature",
  "properties": {
    "iso:country":"US",
    "sg:address":"424 Norma Dr",
    "sg:city":"Irving",
    "sg:classifiers":[
        {
            "category":"Banks & Credit Unions",
            "subcategory":"Financial Services",
            "type":"Services"
        }
    ],
    "sg:phone":"+1 972 790 2456",
    "sg:postcode":"75061",
    "sg:province":"TX",
    "sg:tags":[
        "trust",
        "management"
    ],
    "wof:name":"Ricker Family Trust",
    "wof:placetype":"venue"
},
  "geometry": {"coordinates":[-96.97259099999999,32.819591],"type":"Point"}
}