{
  "type": "Feature",
  "properties": {
    "iso:country":"US",
    "sg:address":"1815 N Collegiate Dr",
    "sg:city":"Paris",
    "sg:classifiers":[
        {
            "category":"Shopping",
            "subcategory":"Used Merchandise",
            "type":"Retail Goods"
        }
    ],
    "sg:phone":"+1 903 785 2377",
    "sg:postcode":"75462",
    "sg:province":"TX",
    "wof:name":"Bluebird Antiques",
    "wof:placetype":"venue"
},
  "geometry": {"coordinates":[-95.523262,33.677076],"type":"Point"}
}