{
  "type": "Feature",
  "properties": {
    "iso:country":"US",
    "sg:address":"2625 E Hwy 190",
    "sg:city":"Copperas Cove",
    "sg:classifiers":[
        {
            "category":"Restaurant",
            "type":"Food & Drink"
        }
    ],
    "sg:phone":"+1 254 542 2483",
    "sg:postcode":"76522",
    "sg:province":"TX",
    "wof:name":"Bush's Chicken",
    "wof:placetype":"venue"
},
  "geometry": {"coordinates":[-97.872029,31.120688],"type":"Point"}
}