{
  "type": "Feature",
  "properties": {
    "iso:country":"US",
    "sg:address":"164 Easter Ct",
    "sg:city":"Spring Branch",
    "sg:classifiers":[
        {
            "category":"Building & Trades",
            "subcategory":"Construction",
            "type":"Services"
        }
    ],
    "sg:phone":"+1 210 912 5062",
    "sg:postcode":"78070",
    "sg:province":"TX",
    "sg:tags":[
        "house"
    ],
    "wof:name":"Payne Builders",
    "wof:placetype":"venue"
},
  "geometry": {"coordinates":[-98.38861799999999,29.950954],"type":"Point"}
}