{
  "type": "Feature",
  "properties": {
    "iso:country":"US",
    "sg:address":"600 George Richey Rd",
    "sg:city":"Longview",
    "sg:classifiers":[
        {
            "category":"Organizations",
            "subcategory":"Religious Organization",
            "type":"Services"
        }
    ],
    "sg:phone":"+1 903 759 5552",
    "sg:postcode":"75604",
    "sg:province":"TX",
    "wof:name":"New Beginnings Baptist Church",
    "wof:placetype":"venue"
},
  "geometry": {"coordinates":[-94.81915100000001,32.565264],"type":"Point"}
}