{
  "type": "Feature",
  "properties": {
    "iso:country":"US",
    "sg:address":"8 E Greenway Plz",
    "sg:city":"Houston",
    "sg:classifiers":[
        {
            "category":"Utilities",
            "subcategory":"Fuel Oil & Lpg",
            "type":"Services"
        }
    ],
    "sg:phone":"+1 713 880 4343",
    "sg:postcode":"77046",
    "sg:province":"TX",
    "sg:tags":[
        "dealer"
    ],
    "wof:name":"Brazos Pipeline Co LLC",
    "wof:placetype":"venue"
},
  "geometry": {"coordinates":[-95.43172300000001,29.733372],"type":"Point"}
}