{
  "type": "Feature",
  "properties": {
    "iso:country":"US",
    "sg:address":"7832 Royal Ln",
    "sg:city":"Dallas",
    "sg:classifiers":[
        {
            "category":"Professional",
            "subcategory":"Art Services",
            "type":"Services"
        }
    ],
    "sg:phone":"+1 214 373 3200",
    "sg:postcode":"75230",
    "sg:province":"TX",
    "sg:tags":[
        "artist"
    ],
    "wof:name":"Slaton Creative Svc",
    "wof:placetype":"venue"
},
  "geometry": {"coordinates":[-96.771417,32.89837],"type":"Point"}
}