{
  "type": "Feature",
  "properties": {
    "iso:country":"US",
    "sg:address":"2507 Johnathan Way",
    "sg:city":"Leander",
    "sg:classifiers":[
        {
            "category":"Travel",
            "subcategory":"Travel Agent",
            "type":"Entertainment"
        }
    ],
    "sg:phone":"+1 512 528 0900",
    "sg:postcode":"78641",
    "sg:province":"TX",
    "sg:tags":[
        "agency"
    ],
    "wof:name":"Century Travel",
    "wof:placetype":"venue"
},
  "geometry": {"coordinates":[-97.829449,30.542175],"type":"Point"}
}