{
  "type": "Feature",
  "properties": {
    "iso:country":"US",
    "sg:address":"511 W Holland Ave",
    "sg:city":"Alpine",
    "sg:classifiers":[
        {
            "category":"Autos & Motor Vehicles",
            "subcategory":"Auto Supplies",
            "type":"Retail Goods"
        }
    ],
    "sg:phone":"+1 432 837 5835",
    "sg:postcode":"79830",
    "sg:province":"TX",
    "sg:tags":[
        "automobile",
        "parts"
    ],
    "wof:name":"Carquest Auto Parts",
    "wof:placetype":"venue"
},
  "geometry": {"coordinates":[-103.66531999999999,30.356351],"type":"Point"}
}