{
  "type": "Feature",
  "properties": {
    "iso:country":"US",
    "sg:address":"4265 San Felipe St Ste 650",
    "sg:city":"Houston",
    "sg:classifiers":[
        {
            "category":"Real Estate",
            "subcategory":"Real Estate Services",
            "type":"Services"
        }
    ],
    "sg:phone":"+1 713 621 3222",
    "sg:postcode":"77027",
    "sg:province":"TX",
    "sg:tags":[
        "management",
        "property"
    ],
    "wof:name":"Bms Management Inc",
    "wof:placetype":"venue"
},
  "geometry": {"coordinates":[-95.450203,29.746599],"type":"Point"}
}