{
  "type": "Feature",
  "properties": {
    "iso:country":"US",
    "sg:address":"1005 Long Meadow Dr",
    "sg:city":"Round Rock",
    "sg:classifiers":[
        {
            "category":"Freight",
            "type":"Transportation"
        }
    ],
    "sg:phone":"+1 512 238 7816",
    "sg:postcode":"78664",
    "sg:province":"TX",
    "sg:tags":[
        "trucking"
    ],
    "wof:name":"Storm Transport LLC",
    "wof:placetype":"venue"
},
  "geometry": {"coordinates":[-97.668581,30.527091],"type":"Point"}
}