{
  "type": "Feature",
  "properties": {
    "iso:country":"US",
    "sg:address":"197 Jeddo Rd",
    "sg:city":"Smithville",
    "sg:classifiers":[
        {
            "category":"Wholesale",
            "subcategory":"Petroleum",
            "type":"Manufacturing & Wholesale Goods"
        }
    ],
    "sg:phone":"+1 512 237 3649",
    "sg:postcode":"78953",
    "sg:province":"TX",
    "sg:tags":[
        "pipe",
        "line",
        "company"
    ],
    "wof:name":"Koch Pipeline Co",
    "wof:placetype":"venue"
},
  "geometry": {"coordinates":[-97.287702,29.926876],"type":"Point"}
}