{
  "type": "Feature",
  "properties": {
    "iso:country":"US",
    "sg:address":"1377 Co Rd 456",
    "sg:city":"Princeton",
    "sg:classifiers":[
        {
            "category":"Farming",
            "subcategory":"Livestock Farm",
            "type":"Manufacturing & Wholesale Goods"
        }
    ],
    "sg:phone":"+1 972 734 2203",
    "sg:postcode":"75407",
    "sg:province":"TX",
    "sg:tags":[
        "beef",
        "feedlot",
        "cattle"
    ],
    "wof:name":"Kalltex Consulting Co",
    "wof:placetype":"venue"
},
  "geometry": {"coordinates":[-96.476355,33.168713],"type":"Point"}
}