{
  "type": "Feature",
  "properties": {
    "iso:country":"US",
    "sg:address":"5525 Post Ridge Dr",
    "sg:city":"Fort Worth",
    "sg:classifiers":[
        {
            "category":"Building & Trades",
            "subcategory":"Construction",
            "type":"Services"
        }
    ],
    "sg:phone":"+1 817 572 1904",
    "sg:postcode":"76123",
    "sg:province":"TX",
    "sg:tags":[
        "home",
        "builder"
    ],
    "wof:name":"Mercedes Homes Inc",
    "wof:placetype":"venue"
},
  "geometry": {"coordinates":[-97.407858,32.636843],"type":"Point"}
}