{
  "type": "Feature",
  "properties": {
    "iso:country":"US",
    "sg:address":"3309 McKinney Ave",
    "sg:city":"Dallas",
    "sg:classifiers":[
        {
            "category":"Restaurant",
            "type":"Food & Drink"
        }
    ],
    "sg:phone":"+1 214 220 0510",
    "sg:postcode":"75204",
    "sg:province":"TX",
    "wof:name":"Primo's Bar & Grill",
    "wof:placetype":"venue"
},
  "geometry": {"coordinates":[-96.798457,32.805821],"type":"Point"}
}