{
  "type": "Feature",
  "properties": {
    "iso:country":"US",
    "sg:address":"2918 Dove Meadow Dr",
    "sg:city":"Garland",
    "sg:classifiers":[
        {
            "category":"Organizations",
            "subcategory":"Religious Organization",
            "type":"Services"
        }
    ],
    "sg:phone":"+1 972 226 4872",
    "sg:postcode":"75043",
    "sg:province":"TX",
    "wof:name":"Trinity River",
    "wof:placetype":"venue"
},
  "geometry": {"coordinates":[-96.584343,32.839319],"type":"Point"}
}