{
  "type": "Feature",
  "properties": {
    "iso:country":"US",
    "sg:address":"7 E Sunset Dr",
    "sg:city":"Orange",
    "sg:classifiers":[
        {
            "category":"Building & Trades",
            "subcategory":"Landscaping Services",
            "type":"Services"
        }
    ],
    "sg:phone":"+1 409 886 9916",
    "sg:postcode":"77630",
    "sg:province":"TX",
    "wof:name":"Wallaces Lawn Care & Service",
    "wof:placetype":"venue"
},
  "geometry": {"coordinates":[-93.745428,30.112319],"type":"Point"}
}