{
  "type": "Feature",
  "properties": {
    "iso:country":"US",
    "sg:address":"436 Young St",
    "sg:city":"Livingston",
    "sg:classifiers":[
        {
            "category":"Professional",
            "type":"Services"
        }
    ],
    "sg:phone":"+1 936 328 8998",
    "sg:postcode":"77351",
    "sg:province":"TX",
    "sg:tags":[
        "establishment"
    ],
    "wof:name":"Victorian Lady",
    "wof:placetype":"venue"
},
  "geometry": {"coordinates":[-94.926998,30.704494],"type":"Point"}
}