{
  "type": "Feature",
  "properties": {
    "iso:country":"US",
    "sg:address":"1701 State Hwy 6",
    "sg:city":"Houston",
    "sg:classifiers":[
        {
            "category":"Building & Trades",
            "subcategory":"Construction",
            "type":"Services"
        }
    ],
    "sg:phone":"+1 713 468 8827",
    "sg:postcode":"77077",
    "sg:province":"TX",
    "sg:tags":[
        "spa",
        "pool",
        "contractor"
    ],
    "wof:name":"Richards Ttal Bckyard Slutions",
    "wof:placetype":"venue"
},
  "geometry": {"coordinates":[-95.644519,29.754119],"type":"Point"}
}