{
  "type": "Feature",
  "properties": {
    "iso:country":"US",
    "sg:address":"501 W Viggie St",
    "sg:city":"Hebbronville",
    "sg:classifiers":[
        {
            "category":"Professional",
            "type":"Services"
        }
    ],
    "sg:phone":"+1 361 527 4479",
    "sg:postcode":"78361",
    "sg:province":"TX",
    "wof:name":"Angel J Soliz",
    "wof:placetype":"venue"
},
  "geometry": {"coordinates":[-98.68364,27.312928],"type":"Point"}
}