{
  "type": "Feature",
  "properties": {
    "iso:country":"US",
    "sg:address":"406 Caroline St",
    "sg:city":"Houston",
    "sg:classifiers":[
        {
            "category":"Government",
            "subcategory":"Office",
            "type":"Public Place"
        }
    ],
    "sg:phone":"+1 713 755 6621",
    "sg:postcode":"77002",
    "sg:province":"TX",
    "sg:website":"www.hctx.net",
    "wof:name":"Harris County Central Tech Ctr",
    "wof:placetype":"venue"
},
  "geometry": {"coordinates":[-95.359357,29.759262],"type":"Point"}
}