{
  "type": "Feature",
  "properties": {
    "iso:country":"US",
    "sg:address":"202 Young St",
    "sg:city":"Big Spring",
    "sg:classifiers":[
        {
            "category":"Retail",
            "subcategory":"Auto Repair",
            "type":"Services"
        }
    ],
    "sg:phone":"+1 432 267 3535",
    "sg:postcode":"79720",
    "sg:province":"TX",
    "sg:tags":[
        "general"
    ],
    "wof:name":"Auto Center",
    "wof:placetype":"venue"
},
  "geometry": {"coordinates":[-101.468525,32.256947],"type":"Point"}
}