{
  "type": "Feature",
  "properties": {
    "iso:country":"US",
    "sg:address":"10411 Belknap Rd",
    "sg:city":"Sugar Land",
    "sg:classifiers":[
        {
            "category":"Building & Trades",
            "subcategory":"Landscaping Services",
            "type":"Services"
        }
    ],
    "sg:phone":"+1 281 530 1622",
    "sg:postcode":"77478",
    "sg:province":"TX",
    "sg:tags":[
        "lawn",
        "gar",
        "contractor",
        "nursery",
        "landscape",
        "stock"
    ],
    "wof:name":"Gant's Plants",
    "wof:placetype":"venue"
},
  "geometry": {"coordinates":[-95.623188,29.665566],"type":"Point"}
}