{
  "type": "Feature",
  "properties": {
    "iso:country":"US",
    "sg:address":"4635 Princeton Ave",
    "sg:city":"Midland",
    "sg:classifiers":[
        {
            "category":"Autos & Motor Vehicles",
            "subcategory":"Automobile Sales",
            "type":"Retail Goods"
        }
    ],
    "sg:phone":"+1 432 694 0584",
    "sg:postcode":"79703",
    "sg:province":"TX",
    "sg:tags":[
        "car",
        "dealer"
    ],
    "wof:name":"Ranger Auto Sales",
    "wof:placetype":"venue"
},
  "geometry": {"coordinates":[-102.13843900000001,31.997818],"type":"Point"}
}