{
  "type": "Feature",
  "properties": {
    "iso:country":"US",
    "sg:address":"6226 Middle Fiskville Rd",
    "sg:city":"Austin",
    "sg:classifiers":[
        {
            "category":"Shopping",
            "subcategory":"Jewelry",
            "type":"Retail Goods"
        },
        {
            "category":"Shopping",
            "subcategory":"Crafts & Fabrics",
            "type":"Retail Goods"
        }
    ],
    "sg:phone":"+1 512 444 6655",
    "sg:postcode":"78752",
    "sg:province":"TX",
    "sg:tags":[
        "art"
    ],
    "sg:website":"bluegenieartbazaar.com",
    "wof:name":"Blue Genie Art Bazaar",
    "wof:placetype":"venue"
},
  "geometry": {"coordinates":[-97.708472,30.326147],"type":"Point"}
}