{
  "type": "Feature",
  "properties": {
    "iso:country":"US",
    "sg:address":"219 Main St",
    "sg:city":"Spring",
    "sg:classifiers":[
        {
            "category":"Shopping",
            "subcategory":"Gifts & Souvenirs",
            "type":"Retail Goods"
        }
    ],
    "sg:phone":"+1 281 528 9588",
    "sg:postcode":"77373",
    "sg:province":"TX",
    "wof:name":"Candles Southern & Gifts",
    "wof:placetype":"venue"
},
  "geometry": {"coordinates":[-95.41961499999999,30.079291],"type":"Point"}
}