{
  "type": "Feature",
  "properties": {
    "iso:country":"US",
    "sg:address":"5701 Martin Luther King Jr Blvd",
    "sg:city":"Houston",
    "sg:classifiers":[
        {
            "category":"Retail",
            "subcategory":"Veterinary Services",
            "type":"Services"
        }
    ],
    "sg:phone":"+1 713 643 2673",
    "sg:postcode":"77021",
    "sg:province":"TX",
    "sg:tags":[
        "veterinarian"
    ],
    "wof:name":"King Boulevard Animal Hospital Inc",
    "wof:placetype":"venue"
},
  "geometry": {"coordinates":[-95.33583400000001,29.698948],"type":"Point"}
}