{
  "type": "Feature",
  "properties": {
    "iso:country":"US",
    "sg:address":"505 Huntland Dr E",
    "sg:city":"Austin",
    "sg:classifiers":[
        {
            "category":"Professional",
            "subcategory":"Computer Services",
            "type":"Services"
        }
    ],
    "sg:phone":"+1 512 458 1112",
    "sg:postcode":"78752",
    "sg:province":"TX",
    "sg:tags":[
        "consultant",
        "designer"
    ],
    "sg:website":"www.austinnc.com",
    "wof:name":"Intercim",
    "wof:placetype":"venue"
},
  "geometry": {"coordinates":[-97.707796,30.330848],"type":"Point"}
}