{
  "type": "Feature",
  "properties": {
    "iso:country":"US",
    "sg:address":"1908 Rosharon Rd Ofc",
    "sg:city":"Alvin",
    "sg:classifiers":[
        {
            "category":"Real Estate",
            "subcategory":"Real Estate Services",
            "type":"Services"
        },
        {
            "category":"Real Estate",
            "subcategory":"Real Estate Operator",
            "type":"Services"
        }
    ],
    "sg:phone":"+1 281 388 1175",
    "sg:postcode":"77511",
    "sg:province":"TX",
    "sg:tags":[
        "vacancy",
        "apartment",
        "rental",
        "finder",
        "listing"
    ],
    "wof:name":"Quail Hollow Apts",
    "wof:placetype":"venue"
},
  "geometry": {"coordinates":[-95.26119199999999,29.402],"type":"Point"}
}