{
  "type": "Feature",
  "properties": {
    "iso:country":"US",
    "sg:address":"1000 W Main St",
    "sg:city":"Decatur",
    "sg:classifiers":[
        {
            "category":"Shopping",
            "subcategory":"Bicycles & Sporting Goods",
            "type":"Retail Goods"
        }
    ],
    "sg:phone":"+1 940 627 6412",
    "sg:postcode":"76234",
    "sg:province":"TX",
    "wof:name":"D P Sports",
    "wof:placetype":"venue"
},
  "geometry": {"coordinates":[-97.599614,33.234572],"type":"Point"}
}