{
  "type": "Feature",
  "properties": {
    "iso:country":"US",
    "sg:address":"8403 Cross Park Dr",
    "sg:city":"Austin",
    "sg:classifiers":[
        {
            "category":"Insurance",
            "subcategory":"Hazard Insurance",
            "type":"Services"
        }
    ],
    "sg:phone":"+1 512 491 7128",
    "sg:postcode":"78754",
    "sg:province":"TX",
    "sg:tags":[
        "sharing",
        "profit",
        "manage",
        "plan",
        "implement",
        "pension"
    ],
    "wof:name":"401 (k) Company",
    "wof:placetype":"venue"
},
  "geometry": {"coordinates":[-97.676576,30.339515],"type":"Point"}
}