{
  "type": "Feature",
  "properties": {
    "iso:country":"US",
    "sg:address":"3701 Hilton Dr",
    "sg:city":"Mesquite",
    "sg:classifiers":[
        {
            "category":"Organizations",
            "subcategory":"Religious Organization",
            "type":"Services"
        }
    ],
    "sg:phone":"+1 972 270 9786",
    "sg:postcode":"75150",
    "sg:province":"TX",
    "wof:name":"Perspective Ministries",
    "wof:placetype":"venue"
},
  "geometry": {"coordinates":[-96.655238,32.815639],"type":"Point"}
}