{
  "type": "Feature",
  "properties": {
    "iso:country":"US",
    "sg:address":"29206 Aberdeen Dr",
    "sg:city":"Magnolia",
    "sg:classifiers":[
        {
            "category":"Professional",
            "type":"Services"
        }
    ],
    "sg:phone":"+1 281 252 8260",
    "sg:postcode":"77354",
    "sg:province":"TX",
    "wof:name":"Apache Wells",
    "wof:placetype":"venue"
},
  "geometry": {"coordinates":[-95.62002099999999,30.18607],"type":"Point"}
}