{
  "type": "Feature",
  "properties": {
    "iso:country":"US",
    "sg:address":"17115 Aprilmont Dr",
    "sg:city":"Sugar Land",
    "sg:classifiers":[
        {
            "category":"Professional",
            "type":"Services"
        }
    ],
    "sg:phone":"+1 281 277 2711",
    "sg:postcode":"77478",
    "sg:province":"TX",
    "wof:name":"Tracy Layman",
    "wof:placetype":"venue"
},
  "geometry": {"coordinates":[-95.66407,29.638814],"type":"Point"}
}