{
  "type": "Feature",
  "properties": {
    "iso:country":"US",
    "sg:address":"3442 Rosedale St",
    "sg:city":"Houston",
    "sg:classifiers":[
        {
            "category":"Banks & Credit Unions",
            "subcategory":"Investment Brokerage",
            "type":"Services"
        }
    ],
    "sg:phone":"+1 713 521 7137",
    "sg:postcode":"77004",
    "sg:province":"TX",
    "sg:tags":[
        "advisory"
    ],
    "wof:name":"Gateway Financial Services",
    "wof:placetype":"venue"
},
  "geometry": {"coordinates":[-95.360686,29.716458],"type":"Point"}
}