{
  "type": "Feature",
  "properties": {
    "iso:country":"US",
    "sg:address":"13328 Country Oak Dr",
    "sg:city":"Willis",
    "sg:classifiers":[
        {
            "category":"Shopping",
            "subcategory":"Hobbies, Toys, & Games",
            "type":"Retail Goods"
        },
        {
            "category":"Shopping",
            "subcategory":"Crafts & Fabrics",
            "type":"Retail Goods"
        }
    ],
    "sg:phone":"+1 936 890 9491",
    "sg:postcode":"77318",
    "sg:province":"TX",
    "sg:tags":[
        "shop",
        "hobby",
        "model",
        "supplies-wholesale",
        "manufacturer"
    ],
    "wof:name":"Bob & Kat's Custom Home Furnishings",
    "wof:placetype":"venue"
},
  "geometry": {"coordinates":[-95.55681199999999,30.452361],"type":"Point"}
}