{
  "type": "Feature",
  "properties": {
    "iso:country":"US",
    "sg:address":"1501 Heritage Pkwy",
    "sg:city":"Mansfield",
    "sg:classifiers":[
        {
            "category":"Building & Trades",
            "subcategory":"Electrical",
            "type":"Services"
        }
    ],
    "sg:phone":"+1 817 477 4701",
    "sg:postcode":"76063",
    "sg:province":"TX",
    "sg:tags":[
        "electric",
        "contractor"
    ],
    "wof:name":"Cross Brothers Electric",
    "wof:placetype":"venue"
},
  "geometry": {"coordinates":[-97.11837800000001,32.553396],"type":"Point"}
}