{
  "type": "Feature",
  "properties": {
    "iso:country":"US",
    "sg:address":"1806 Sagebrush Trl",
    "sg:city":"Euless",
    "sg:classifiers":[
        {
            "category":"Home & Garden",
            "subcategory":"Home Furnishings",
            "type":"Retail Goods"
        }
    ],
    "sg:phone":"+1 817 283 9381",
    "sg:postcode":"76040",
    "sg:province":"TX",
    "sg:tags":[
        "venetian",
        "blind"
    ],
    "wof:name":"Moni's Custom Draperies",
    "wof:placetype":"venue"
},
  "geometry": {"coordinates":[-97.108271,32.829425],"type":"Point"}
}