{
  "type": "Feature",
  "properties": {
    "iso:country":"US",
    "sg:address":"1701 Webberwood Dr",
    "sg:city":"Elgin",
    "sg:classifiers":[
        {
            "category":"Freight",
            "type":"Transportation"
        }
    ],
    "sg:phone":"+1 512 276 1150",
    "sg:postcode":"78621",
    "sg:province":"TX",
    "sg:tags":[
        "special"
    ],
    "wof:name":"Irmas Mini Storage",
    "wof:placetype":"venue"
},
  "geometry": {"coordinates":[-97.490802,30.217235],"type":"Point"}
}