{
  "type": "Feature",
  "properties": {
    "iso:country":"US",
    "sg:address":"1110 Explorer St Suite A, Ste A",
    "sg:city":"Duncanville",
    "sg:classifiers":[
        {
            "category":"Autos & Motor Vehicles",
            "subcategory":"Auto Supplies",
            "type":"Retail Goods"
        },
        {
            "category":"Retail",
            "subcategory":"Auto Repair",
            "type":"Services"
        }
    ],
    "sg:phone":"+1 214 854 7314",
    "sg:postcode":"75137",
    "sg:province":"TX",
    "sg:tags":[
        "engines-rebuild",
        "body",
        "tire",
        "exchange",
        "transmission",
        "automobile",
        "engine",
        "rebuilding",
        "painting",
        "repairing"
    ],
    "wof:name":"Rios Tire & Mechanic Shop",
    "wof:placetype":"venue"
},
  "geometry": {"coordinates":[-96.92344,32.638534],"type":"Point"}
}