{
  "type": "Feature",
  "properties": {
    "iso:country":"US",
    "sg:address":"1825 Airline Rd",
    "sg:city":"Corpus Christi",
    "sg:classifiers":[
        {
            "category":"Building & Trades",
            "subcategory":"Construction",
            "type":"Services"
        }
    ],
    "sg:phone":"+1 361 991 0921",
    "sg:postcode":"78412",
    "sg:province":"TX",
    "sg:tags":[
        "house"
    ],
    "wof:name":"Crystal Claimer",
    "wof:placetype":"venue"
},
  "geometry": {"coordinates":[-97.363102,27.69997],"type":"Point"}
}