{
  "type": "Feature",
  "properties": {
    "iso:country":"US",
    "sg:address":"430 Ridgegate Pl",
    "sg:city":"Garland",
    "sg:classifiers":[
        {
            "category":"Recreation",
            "subcategory":"Arcade",
            "type":"Entertainment"
        }
    ],
    "sg:phone":"+1 972 495 7699",
    "sg:postcode":"75040",
    "sg:province":"TX",
    "sg:tags":[
        "device",
        "operator",
        "amusement"
    ],
    "wof:name":"Reel Deal Slot & Games",
    "wof:placetype":"venue"
},
  "geometry": {"coordinates":[-96.634061,32.943572],"type":"Point"}
}