{
  "type": "Feature",
  "properties": {
    "iso:country":"US",
    "sg:address":"7900 Fm 1826",
    "sg:city":"Austin",
    "sg:classifiers":[
        {
            "category":"Health Services",
            "subcategory":"Optometrist",
            "type":"Services"
        }
    ],
    "sg:phone":"+1 512 301 8558",
    "sg:postcode":"78737",
    "sg:province":"TX",
    "sg:tags":[
        "ophthalmologist"
    ],
    "sg:website":"www.premiereye.com",
    "wof:name":"Premier Eye Care PA",
    "wof:placetype":"venue"
},
  "geometry": {"coordinates":[-97.88829800000001,30.2292],"type":"Point"}
}