{
  "type": "Feature",
  "properties": {
    "iso:country":"US",
    "sg:address":"1808 Clay Ln",
    "sg:city":"Cedar Park",
    "sg:classifiers":[
        {
            "category":"Professional",
            "subcategory":"Art Services",
            "type":"Services"
        }
    ],
    "sg:phone":"+1 512 918 3853",
    "sg:postcode":"78613",
    "sg:province":"TX",
    "sg:tags":[
        "photographer"
    ],
    "wof:name":"Austin Empire",
    "wof:placetype":"venue"
},
  "geometry": {"coordinates":[-97.837114,30.470662],"type":"Point"}
}