{
  "type": "Feature",
  "properties": {
    "iso:country":"US",
    "sg:address":"9287 Richmond Ave",
    "sg:city":"Houston",
    "sg:classifiers":[
        {
            "category":"Restaurant",
            "type":"Food & Drink"
        }
    ],
    "sg:phone":"+1 713 784 2080",
    "sg:postcode":"77063",
    "sg:province":"TX",
    "wof:name":"Popeyes Famous Fried Chicken",
    "wof:placetype":"venue"
},
  "geometry": {"coordinates":[-95.52800000000001,29.7288],"type":"Point"}
}