{
  "type": "Feature",
  "properties": {
    "iso:country":"US",
    "sg:address":"104 W Main St",
    "sg:city":"Grandview",
    "sg:classifiers":[
        {
            "category":"Shopping",
            "subcategory":"Computers & Home Electronics",
            "type":"Retail Goods"
        }
    ],
    "sg:phone":"+1 817 866 3790",
    "sg:postcode":"76050",
    "sg:province":"TX",
    "wof:name":"Tlk Direct",
    "wof:placetype":"venue"
},
  "geometry": {"coordinates":[-97.18301599999999,32.271383],"type":"Point"}
}