{
  "type": "Feature",
  "properties": {
    "iso:country":"US",
    "sg:address":"801 Nolana St",
    "sg:city":"Mcallen",
    "sg:classifiers":[
        {
            "category":"Wholesale",
            "subcategory":"Machinery & Supplies",
            "type":"Manufacturing & Wholesale Goods"
        }
    ],
    "sg:phone":"+1 956 661 0505",
    "sg:postcode":"78504",
    "sg:province":"TX",
    "sg:tags":[
        "dock",
        "loading",
        "equipment"
    ],
    "wof:name":"Johnson Equipment Co",
    "wof:placetype":"venue"
},
  "geometry": {"coordinates":[-98.22386299999999,26.239321],"type":"Point"}
}