{
  "type": "Feature",
  "properties": {
    "iso:country":"US",
    "sg:address":"6411 Airline Dr",
    "sg:city":"Houston",
    "sg:classifiers":[
        {
            "category":"Manufacturing",
            "subcategory":"Signs",
            "type":"Manufacturing & Wholesale Goods"
        }
    ],
    "sg:phone":"+1 713 699 1121",
    "sg:postcode":"77076",
    "sg:province":"TX",
    "sg:tags":[
        "electrical",
        "mfg"
    ],
    "wof:name":"Atlas Sign Co",
    "wof:placetype":"venue"
},
  "geometry": {"coordinates":[-95.384753,29.858512],"type":"Point"}
}