{
  "type": "Feature",
  "properties": {
    "iso:country":"US",
    "sg:address":"518 N 15th St",
    "sg:city":"Corsicana",
    "sg:classifiers":[
        {
            "category":"Home & Garden",
            "subcategory":"Carpets & Floor Coverings",
            "type":"Retail Goods"
        }
    ],
    "sg:phone":"+1 903 872 6061",
    "sg:postcode":"75110",
    "sg:province":"TX",
    "sg:tags":[
        "rug"
    ],
    "wof:name":"Hometown Flooring",
    "wof:placetype":"venue"
},
  "geometry": {"coordinates":[-96.471664,32.094712],"type":"Point"}
}