{
  "type": "Feature",
  "properties": {
    "iso:country":"US",
    "sg:address":"2705 61st St",
    "sg:city":"Galveston",
    "sg:classifiers":[
        {
            "category":"Building & Trades",
            "subcategory":"Plumbing",
            "type":"Services"
        }
    ],
    "sg:phone":"+1 409 939 4319",
    "sg:postcode":"77551",
    "sg:province":"TX",
    "sg:tags":[
        "system",
        "septic"
    ],
    "wof:name":"Auzston Enterprises",
    "wof:placetype":"venue"
},
  "geometry": {"coordinates":[-94.829289,29.27229],"type":"Point"}
}