{
  "type": "Feature",
  "properties": {
    "iso:country":"US",
    "sg:address":"124 Austin Ave",
    "sg:city":"Lamesa",
    "sg:classifiers":[
        {
            "category":"Professional",
            "subcategory":"Accounting & Tax Preparation",
            "type":"Services"
        }
    ],
    "sg:phone":"+1 806 872 7845",
    "sg:postcode":"79331",
    "sg:province":"TX",
    "sg:tags":[
        "accountant"
    ],
    "wof:name":"Joe E Coffey CPA",
    "wof:placetype":"venue"
},
  "geometry": {"coordinates":[-101.953017,32.732672],"type":"Point"}
}