{
  "type": "Feature",
  "properties": {
    "iso:country":"US",
    "sg:address":"10901 Loma Portal Pl",
    "sg:city":"El Paso",
    "sg:classifiers":[
        {
            "category":"Professional",
            "type":"Services"
        }
    ],
    "sg:phone":"+1 915 822 8752",
    "sg:postcode":"79934",
    "sg:province":"TX",
    "wof:name":"Cruz Ibarra",
    "wof:placetype":"venue"
},
  "geometry": {"coordinates":[-106.43871799999999,31.929002],"type":"Point"}
}