{
  "type": "Feature",
  "properties": {
    "iso:country":"US",
    "sg:address":"1215 Centerville Rd",
    "sg:city":"Dallas",
    "sg:classifiers":[
        {
            "category":"Building & Trades",
            "subcategory":"Pest Control",
            "type":"Services"
        }
    ],
    "sg:phone":"+1 214 320 1020",
    "sg:postcode":"75218",
    "sg:province":"TX",
    "sg:tags":[
        "exterminating"
    ],
    "wof:name":"Sterling Pest Management Inc",
    "wof:placetype":"venue"
},
  "geometry": {"coordinates":[-96.68621,32.843096],"type":"Point"}
}