{
  "type": "Feature",
  "properties": {
    "iso:country":"US",
    "sg:address":"3306 Main St",
    "sg:city":"Rowlett",
    "sg:classifiers":[
        {
            "category":"Restaurant",
            "type":"Food & Drink"
        }
    ],
    "sg:phone":"+1 972 475 0335",
    "sg:postcode":"75088",
    "sg:province":"TX",
    "sg:tags":[
        "commissary",
        "contractor"
    ],
    "wof:name":"Correctional Food Svc",
    "wof:placetype":"venue"
},
  "geometry": {"coordinates":[-96.57086,32.902404],"type":"Point"}
}