{
  "type": "Feature",
  "properties": {
    "iso:country":"US",
    "sg:address":"4134 Sorrenson Dr",
    "sg:city":"Pearland",
    "sg:classifiers":[
        {
            "category":"Professional",
            "subcategory":"Business Services",
            "type":"Services"
        }
    ],
    "sg:phone":"+1 281 489 4731",
    "sg:postcode":"77584",
    "sg:province":"TX",
    "wof:name":"CVere Band",
    "wof:placetype":"venue"
},
  "geometry": {"coordinates":[-95.354202,29.538939],"type":"Point"}
}