{
  "type": "Feature",
  "properties": {
    "iso:country":"US",
    "sg:address":"15219 Ripplewind Ln",
    "sg:city":"Houston",
    "sg:classifiers":[
        {
            "category":"Manufacturing",
            "subcategory":"Chemicals & Compounds",
            "type":"Manufacturing & Wholesale Goods"
        }
    ],
    "sg:phone":"+1 281 397 9231",
    "sg:postcode":"77068",
    "sg:province":"TX",
    "sg:tags":[
        "industrial",
        "organic",
        "mfg"
    ],
    "wof:name":"Howell Laboratories Inc",
    "wof:placetype":"venue"
},
  "geometry": {"coordinates":[-95.488675,30.007035],"type":"Point"}
}