{
  "type": "Feature",
  "properties": {
    "iso:country":"US",
    "sg:address":"6121 W Park Blvd",
    "sg:city":"Plano",
    "sg:classifiers":[
        {
            "category":"Shopping",
            "subcategory":"Clothing, Apparel, & Fashions",
            "type":"Retail Goods"
        }
    ],
    "sg:phone":"+1 469 366 0144",
    "sg:postcode":"75093",
    "sg:province":"TX",
    "sg:tags":[
        "baby",
        "accessory"
    ],
    "wof:name":"Baby Market",
    "wof:placetype":"venue"
},
  "geometry": {"coordinates":[-96.831943,33.027758],"type":"Point"}
}