{
  "type": "Feature",
  "properties": {
    "iso:country":"US",
    "sg:address":"1002 NE Water St",
    "sg:city":"Victoria",
    "sg:classifiers":[
        {
            "category":"Building & Trades",
            "subcategory":"Electrical",
            "type":"Services"
        }
    ],
    "sg:phone":"+1 361 578 7155",
    "sg:postcode":"77901",
    "sg:province":"TX",
    "sg:tags":[
        "electrician"
    ],
    "wof:name":"Wolfshohl Jr, Vernon",
    "wof:placetype":"venue"
},
  "geometry": {"coordinates":[-97.000514,28.790544],"type":"Point"}
}