{
  "type": "Feature",
  "properties": {
    "iso:country":"US",
    "sg:address":"614 Highland Meadows Dr",
    "sg:city":"Lewisville",
    "sg:classifiers":[
        {
            "category":"Building & Trades",
            "subcategory":"Construction",
            "type":"Services"
        }
    ],
    "sg:phone":"+1 972 317 3870",
    "sg:postcode":"75077",
    "sg:province":"TX",
    "sg:tags":[
        "house"
    ],
    "wof:name":"Dw Construction Services",
    "wof:placetype":"venue"
},
  "geometry": {"coordinates":[-97.04908399999999,33.073995],"type":"Point"}
}