{
  "type": "Feature",
  "properties": {
    "iso:country":"US",
    "sg:address":"208 E Live Oak St",
    "sg:city":"Cuero",
    "sg:classifiers":[
        {
            "category":"Government",
            "subcategory":"Jail",
            "type":"Public Place"
        }
    ],
    "sg:phone":"+1 361 275 0034",
    "sg:postcode":"77954",
    "sg:province":"TX",
    "sg:tags":[
        "county",
        "govt",
        "institution"
    ],
    "wof:name":"De WITT County Jail",
    "wof:placetype":"venue"
},
  "geometry": {"coordinates":[-97.289051,29.092479],"type":"Point"}
}