{
  "type": "Feature",
  "properties": {
    "iso:country":"US",
    "sg:address":"7024 FM 1765",
    "sg:city":"Texas City",
    "sg:classifiers":[
        {
            "category":"Retail",
            "subcategory":"Car Wash",
            "type":"Services"
        },
        {
            "category":"Retail",
            "subcategory":"Auto Repair",
            "type":"Services"
        }
    ],
    "sg:phone":"+1 409 933 4680",
    "sg:postcode":"77591",
    "sg:province":"TX",
    "sg:tags":[
        "body",
        "automobile",
        "detail",
        "clean"
    ],
    "wof:name":"Cliff's Auto Care",
    "wof:placetype":"venue"
},
  "geometry": {"coordinates":[-94.989566,29.378709],"type":"Point"}
}