{
  "type": "Feature",
  "properties": {
    "iso:country":"US",
    "sg:address":"8500 Chapin Rd",
    "sg:city":"Fort Worth",
    "sg:classifiers":[
        {
            "category":"Organizations",
            "subcategory":"Religious Organization",
            "type":"Services"
        }
    ],
    "sg:phone":"+1 817 244 0216",
    "sg:postcode":"76116",
    "sg:province":"TX",
    "wof:name":"Western Hills Weeschool",
    "wof:placetype":"venue"
},
  "geometry": {"coordinates":[-97.46545500000001,32.716291],"type":"Point"}
}