{
  "type": "Feature",
  "properties": {
    "iso:country":"US",
    "sg:address":"7334 S Westmoreland Rd",
    "sg:city":"Dallas",
    "sg:classifiers":[
        {
            "category":"Government",
            "subcategory":"Office",
            "type":"Public Place"
        }
    ],
    "sg:phone":"+1 800 375 5283",
    "sg:postcode":"75237",
    "sg:province":"TX",
    "sg:tags":[
        "international",
        "affairs"
    ],
    "wof:name":"South Dllas Aplcat Support Ctr",
    "wof:placetype":"venue"
},
  "geometry": {"coordinates":[-96.88372699999999,32.657834],"type":"Point"}
}