{
  "type": "Feature",
  "properties": {
    "iso:country":"US",
    "sg:address":"22 Pegues Pl",
    "sg:city":"Longview",
    "sg:classifiers":[
        {
            "category":"Manufacturing",
            "subcategory":"Tools & Machinery",
            "type":"Manufacturing & Wholesale Goods"
        }
    ],
    "sg:phone":"+1 903 753 1955",
    "sg:postcode":"75601",
    "sg:province":"TX",
    "sg:tags":[
        "business"
    ],
    "wof:name":"Cave Family Partnership Ltd",
    "wof:placetype":"venue"
},
  "geometry": {"coordinates":[-94.737533,32.515637],"type":"Point"}
}