{
  "type": "Feature",
  "properties": {
    "iso:country":"US",
    "sg:address":"5142 Colter Way",
    "sg:city":"Dallas",
    "sg:classifiers":[
        {
            "category":"Professional",
            "subcategory":"Management & Consulting",
            "type":"Services"
        }
    ],
    "sg:phone":"+1 214 388 2762",
    "sg:postcode":"75227",
    "sg:province":"TX",
    "wof:name":"Conflict In Common",
    "wof:placetype":"venue"
},
  "geometry": {"coordinates":[-96.708901,32.788946],"type":"Point"}
}