{
  "type": "Feature",
  "properties": {
    "iso:country":"US",
    "sg:address":"17097 Pearce Ln",
    "sg:city":"Del Valle",
    "sg:classifiers":[
        {
            "category":"Food & Beverages",
            "subcategory":"Groceries & Convenience Stores",
            "type":"Retail Goods"
        }
    ],
    "sg:phone":"+1 512 247 9612",
    "sg:postcode":"78617",
    "sg:province":"TX",
    "wof:name":"Pearce Stop",
    "wof:placetype":"venue"
},
  "geometry": {"coordinates":[-97.568254,30.141691],"type":"Point"}
}