{
  "type": "Feature",
  "properties": {
    "iso:country":"US",
    "sg:address":"1301 N Collins St",
    "sg:city":"Arlington",
    "sg:classifiers":[
        {
            "category":"Banks & Credit Unions",
            "subcategory":"Bank",
            "type":"Services"
        }
    ],
    "sg:phone":"+1 817 276 8510",
    "sg:postcode":"76011",
    "sg:province":"TX",
    "sg:tags":[
        "cashing",
        "check"
    ],
    "wof:name":"Quik Cash",
    "wof:placetype":"venue"
},
  "geometry": {"coordinates":[-97.09716400000001,32.755558],"type":"Point"}
}