{
  "type": "Feature",
  "properties": {
    "iso:country":"US",
    "sg:address":"511 Cheyenne St",
    "sg:city":"Wheeler",
    "sg:classifiers":[
        {
            "category":"Building & Trades",
            "subcategory":"Plumbing",
            "type":"Services"
        }
    ],
    "sg:phone":"+1 806 826 5907",
    "sg:postcode":"79096",
    "sg:province":"TX",
    "sg:tags":[
        "plumbing",
        "contractor"
    ],
    "wof:name":"Wheeler Plumbing Co",
    "wof:placetype":"venue"
},
  "geometry": {"coordinates":[-100.279799,35.444092],"type":"Point"}
}