{
  "type": "Feature",
  "properties": {
    "iso:country":"US",
    "sg:address":"325 W Mockingbird Ln",
    "sg:city":"Dallas",
    "sg:classifiers":[
        {
            "category":"Retail",
            "subcategory":"Repair Shop",
            "type":"Services"
        }
    ],
    "sg:phone":"+1 214 879 9916",
    "sg:postcode":"75247",
    "sg:province":"TX",
    "sg:tags":[
        "equipment",
        "stereo"
    ],
    "wof:name":"Factory Service Ctr",
    "wof:placetype":"venue"
},
  "geometry": {"coordinates":[-96.87376999999999,32.803515],"type":"Point"}
}