{
  "type": "Feature",
  "properties": {
    "iso:country":"US",
    "sg:address":"6714 Glen Rock Dr",
    "sg:city":"Houston",
    "sg:classifiers":[
        {
            "category":"Wholesale",
            "subcategory":"Durable Goods & Equipment",
            "type":"Manufacturing & Wholesale Goods"
        }
    ],
    "sg:phone":"+1 713 640 2878",
    "sg:postcode":"77087",
    "sg:province":"TX",
    "sg:tags":[
        "importer"
    ],
    "wof:name":"H Williams & Co Imports",
    "wof:placetype":"venue"
},
  "geometry": {"coordinates":[-95.30661600000001,29.671614],"type":"Point"}
}