{
  "type": "Feature",
  "properties": {
    "iso:country":"US",
    "sg:address":"Toyota Center 1510 Polk St",
    "sg:city":"Houston",
    "sg:classifiers":[
        {
            "category":"Arena",
            "subcategory":"Sports Club",
            "type":"Entertainment"
        }
    ],
    "sg:phone":"+1 713 758 7529",
    "sg:postcode":"77002",
    "sg:province":"TX",
    "sg:tags":[
        "professional",
        "team"
    ],
    "sg:website":"www.rockets.com",
    "wof:name":"Houston Rockets",
    "wof:placetype":"venue"
},
  "geometry": {"coordinates":[-95.362313,29.752039],"type":"Point"}
}