{
  "type": "Feature",
  "properties": {
    "iso:country":"US",
    "sg:address":"10 Ellis Rd",
    "sg:city":"League City",
    "sg:classifiers":[
        {
            "category":"Shopping",
            "subcategory":"Jewelry",
            "type":"Retail Goods"
        }
    ],
    "sg:phone":"+1 281 554 5838",
    "sg:postcode":"77573",
    "sg:province":"TX",
    "wof:name":"Fays Jewelry & Accessori",
    "wof:placetype":"venue"
},
  "geometry": {"coordinates":[-95.146033,29.494933],"type":"Point"}
}