{
  "type": "Feature",
  "properties": {
    "iso:country":"US",
    "sg:address":"306 Fort Edward Dr",
    "sg:city":"Arlington",
    "sg:classifiers":[
        {
            "category":"Home & Garden",
            "subcategory":"Furniture",
            "type":"Retail Goods"
        }
    ],
    "sg:phone":"+1 817 466 2949",
    "sg:postcode":"76002",
    "sg:province":"TX",
    "sg:tags":[
        "store"
    ],
    "wof:name":"Ethan Enterprises",
    "wof:placetype":"venue"
},
  "geometry": {"coordinates":[-97.113023,32.610441],"type":"Point"}
}