{
  "type": "Feature",
  "properties": {
    "iso:country":"US",
    "sg:address":"210 S Ave C",
    "sg:city":"Humble",
    "sg:classifiers":[
        {
            "category":"Mining & Drilling",
            "type":"Manufacturing & Wholesale Goods"
        }
    ],
    "sg:phone":"+1 910 323 2689",
    "sg:postcode":"77338",
    "sg:province":"TX",
    "sg:tags":[
        "oil",
        "gas"
    ],
    "wof:name":"Ashton Operating Inc",
    "wof:placetype":"venue"
},
  "geometry": {"coordinates":[-95.26356800000001,29.995984],"type":"Point"}
}