{
  "type": "Feature",
  "properties": {
    "iso:country":"US",
    "sg:address":"1203 Main St",
    "sg:city":"Texarkana",
    "sg:classifiers":[
        {
            "category":"Retail",
            "subcategory":"Auto Repair",
            "type":"Services"
        }
    ],
    "sg:phone":"+1 903 791 0693",
    "sg:postcode":"75501",
    "sg:province":"TX",
    "sg:tags":[
        "repairing",
        "automobile"
    ],
    "wof:name":"Quest Diagnostics Inc",
    "wof:placetype":"venue"
},
  "geometry": {"coordinates":[-94.050112,33.430943],"type":"Point"}
}