{
  "type": "Feature",
  "properties": {
    "iso:country":"US",
    "sg:address":"106 Wildwood Ranch Rd",
    "sg:city":"Adkins",
    "sg:classifiers":[
        {
            "category":"Manufacturing",
            "subcategory":"Metals",
            "type":"Manufacturing & Wholesale Goods"
        }
    ],
    "sg:phone":"+1 210 355 4186",
    "sg:postcode":"78101",
    "sg:province":"TX",
    "wof:name":"Wright Metal Finishing",
    "wof:placetype":"venue"
},
  "geometry": {"coordinates":[-98.18569100000001,29.308759],"type":"Point"}
}