{
  "type": "Feature",
  "properties": {
    "iso:country":"US",
    "sg:address":"400 W 10th St",
    "sg:city":"Borger",
    "sg:classifiers":[
        {
            "category":"Retail",
            "subcategory":"Auto Repair",
            "type":"Services"
        }
    ],
    "sg:phone":"+1 806 273 2113",
    "sg:postcode":"79007",
    "sg:province":"TX",
    "sg:tags":[
        "repairing",
        "automobile"
    ],
    "wof:name":"D J's Automotive & Tire Shop",
    "wof:placetype":"venue"
},
  "geometry": {"coordinates":[-101.39310999999999,35.676791],"type":"Point"}
}