{
  "type": "Feature",
  "properties": {
    "iso:country":"US",
    "sg:address":"910 E Grauwyler Rd",
    "sg:city":"Irving",
    "sg:classifiers":[
        {
            "category":"Donuts",
            "subcategory":"None",
            "type":"Food & Drink"
        }
    ],
    "sg:phone":"+1 972 438 8200",
    "sg:postcode":"75061",
    "sg:province":"TX",
    "wof:name":"Donut Hut",
    "wof:placetype":"venue"
},
  "geometry": {"coordinates":[-96.934898,32.829498],"type":"Point"}
}