{
  "type": "Feature",
  "properties": {
    "iso:country":"US",
    "sg:address":"6911 Cypress Point Dr",
    "sg:city":"Houston",
    "sg:classifiers":[
        {
            "category":"Shopping",
            "subcategory":"Used Merchandise",
            "type":"Retail Goods"
        }
    ],
    "sg:phone":"+1 281 580 1625",
    "sg:postcode":"77069",
    "sg:province":"TX",
    "wof:name":"Three Friends Antiques",
    "wof:placetype":"venue"
},
  "geometry": {"coordinates":[-95.53654,29.975202],"type":"Point"}
}