{
  "type": "Feature",
  "properties": {
    "iso:country":"US",
    "sg:address":"9500 N Central Expy",
    "sg:city":"Dallas",
    "sg:classifiers":[
        {
            "category":"Shopping",
            "subcategory":"Hobbies, Toys, & Games",
            "type":"Retail Goods"
        }
    ],
    "sg:phone":"+1 214 363 3192",
    "sg:postcode":"75231",
    "sg:province":"TX",
    "wof:name":"Toys R Us",
    "wof:placetype":"venue"
},
  "geometry": {"coordinates":[-96.770779,32.877666],"type":"Point"}
}