{
  "type": "Feature",
  "properties": {
    "iso:country":"US",
    "sg:address":"4301 Sonora Dr",
    "sg:city":"Killeen",
    "sg:classifiers":[
        {
            "category":"Restaurant",
            "type":"Food & Drink"
        }
    ],
    "sg:phone":"+1 254 526 5860",
    "sg:postcode":"76549",
    "sg:province":"TX",
    "wof:name":"Pappa Charles",
    "wof:placetype":"venue"
},
  "geometry": {"coordinates":[-97.776543,31.088421],"type":"Point"}
}