{
  "type": "Feature",
  "properties": {
    "iso:country":"US",
    "sg:address":"2633 Royal Ln Ste 201",
    "sg:city":"Dallas",
    "sg:classifiers":[
        {
            "category":"Professional",
            "subcategory":"Lawyer & Legal Services",
            "type":"Services"
        }
    ],
    "sg:phone":"+1 972 247 8424",
    "sg:postcode":"75229",
    "sg:province":"TX",
    "wof:name":"Law & CPA Office",
    "wof:placetype":"venue"
},
  "geometry": {"coordinates":[-96.889351,32.895441],"type":"Point"}
}