{
  "type": "Feature",
  "properties": {
    "iso:country":"US",
    "sg:address":"2807 Sunset Ridge",
    "sg:city":"Mc Kinney",
    "sg:classifiers":[
        {
            "category":"Wholesale",
            "subcategory":"Machinery & Supplies",
            "type":"Manufacturing & Wholesale Goods"
        }
    ],
    "sg:phone":"+1 972 548 1380",
    "sg:postcode":"75070",
    "sg:province":"TX",
    "sg:tags":[
        "equipment",
        "industrial"
    ],
    "wof:name":"Farrow & Assoc Inc",
    "wof:placetype":"venue"
},
  "geometry": {"coordinates":[-96.65804,33.175551],"type":"Point"}
}