{
  "type": "Feature",
  "properties": {
    "iso:country":"US",
    "sg:address":"1607 San Jacinto Blvd",
    "sg:city":"Austin",
    "sg:classifiers":[
        {
            "category":"Organizations",
            "subcategory":"Community Association",
            "type":"Services"
        }
    ],
    "sg:phone":"+1 512 478 1411",
    "sg:postcode":"78701",
    "sg:province":"TX",
    "wof:name":"Saengerrunde Bowling Alley",
    "wof:placetype":"venue"
},
  "geometry": {"coordinates":[-97.73637100000001,30.278003],"type":"Point"}
}