{
  "type": "Feature",
  "properties": {
    "iso:country":"US",
    "sg:address":"503 Price Rd",
    "sg:city":"Victoria",
    "sg:classifiers":[
        {
            "category":"Building & Trades",
            "subcategory":"Construction",
            "type":"Services"
        }
    ],
    "sg:phone":"+1 361 575 0221",
    "sg:postcode":"77905",
    "sg:province":"TX",
    "sg:tags":[
        "house",
        "nonresidential"
    ],
    "wof:name":"Dreymala Construction Company",
    "wof:placetype":"venue"
},
  "geometry": {"coordinates":[-97.186291,28.854576],"type":"Point"}
}