{
  "type": "Feature",
  "properties": {
    "iso:country":"US",
    "sg:address":"9828 Great Hills Trail",
    "sg:city":"Austin",
    "sg:classifiers":[
        {
            "category":"Shopping",
            "subcategory":"Hobbies, Toys, & Games",
            "type":"Retail Goods"
        }
    ],
    "sg:phone":"+1 512 241 2885",
    "sg:postcode":"78759",
    "sg:province":"TX",
    "sg:tags":[
        "toy",
        "store"
    ],
    "sg:website":"www.lakeshorelearning.com",
    "wof:name":"Lakeshore Learning Materials",
    "wof:placetype":"venue"
},
  "geometry": {"coordinates":[-97.74845000000001,30.394255],"type":"Point"}
}