{
  "type": "Feature",
  "properties": {
    "iso:country":"US",
    "sg:address":"1529 39th St",
    "sg:city":"Galveston",
    "sg:classifiers":[
        {
            "category":"Health Services",
            "subcategory":"Podiatrist",
            "type":"Services"
        }
    ],
    "sg:phone":"+1 409 762 6433",
    "sg:postcode":"77550",
    "sg:province":"TX",
    "wof:name":"Associated Podiatrists",
    "wof:placetype":"venue"
},
  "geometry": {"coordinates":[-94.808655,29.289976],"type":"Point"}
}