{
  "type": "Feature",
  "properties": {
    "iso:country":"US",
    "sg:address":"8800 Katy Fwy Ste 104",
    "sg:city":"Houston",
    "sg:classifiers":[
        {
            "category":"Fast Food",
            "type":"Food & Drink"
        }
    ],
    "sg:phone":"+1 713 468 4111",
    "sg:postcode":"77024",
    "sg:province":"TX",
    "sg:tags":[
        "burger"
    ],
    "sg:website":"www.freewayburgersandgrill.com",
    "wof:name":"Freeway Burgers and Grill",
    "wof:placetype":"venue"
},
  "geometry": {"coordinates":[-95.506715,29.783477],"type":"Point"}
}