{
  "type": "Feature",
  "properties": {
    "iso:country":"US",
    "sg:address":"34660 Smithson Valley Rd",
    "sg:city":"Bulverde",
    "sg:classifiers":[
        {
            "category":"Building & Trades",
            "subcategory":"Plumbing",
            "type":"Services"
        }
    ],
    "sg:phone":"+1 830 885 6889",
    "sg:postcode":"78163",
    "sg:province":"TX",
    "sg:website":"www.triplecrossplumbing.com",
    "wof:name":"Triple Cross Plumbing & Utilities Limited",
    "wof:placetype":"venue"
},
  "geometry": {"coordinates":[-98.353996,29.796],"type":"Point"}
}