{
  "type": "Feature",
  "properties": {
    "iso:country":"US",
    "sg:address":"3211 Elizabeth Anne Ln",
    "sg:city":"Round Rock",
    "sg:classifiers":[
        {
            "category":"Professional",
            "type":"Services"
        }
    ],
    "sg:phone":"+1 512 218 0116",
    "sg:postcode":"78664",
    "sg:province":"TX",
    "sg:tags":[
        "arranging",
        "music",
        "composing"
    ],
    "wof:name":"Midian",
    "wof:placetype":"venue"
},
  "geometry": {"coordinates":[-97.624256,30.490617],"type":"Point"}
}