{
  "type": "Feature",
  "properties": {
    "iso:country":"US",
    "sg:address":"1811 Wall St",
    "sg:city":"Garland",
    "sg:classifiers":[
        {
            "category":"Building & Trades",
            "subcategory":"Plumbing",
            "type":"Services"
        }
    ],
    "sg:phone":"+1 972 278 0188",
    "sg:postcode":"75041",
    "sg:province":"TX",
    "sg:website":"www.johndeerelandscapes.com",
    "wof:name":"John Deere Landscapes",
    "wof:placetype":"venue"
},
  "geometry": {"coordinates":[-96.658001,32.874574],"type":"Point"}
}