{
  "type": "Feature",
  "properties": {
    "iso:country":"US",
    "sg:address":"411 Jordan Dr",
    "sg:city":"Laredo",
    "sg:classifiers":[
        {
            "category":"Professional",
            "subcategory":"Accounting & Tax Preparation",
            "type":"Services"
        }
    ],
    "sg:phone":"+1 956 723 7959",
    "sg:postcode":"78041",
    "sg:province":"TX",
    "wof:name":"3c Ranchwork Inc",
    "wof:placetype":"venue"
},
  "geometry": {"coordinates":[-99.48651,27.562408],"type":"Point"}
}