{
  "type": "Feature",
  "properties": {
    "iso:country":"US",
    "sg:address":"3722 Drew St",
    "sg:city":"Houston",
    "sg:classifiers":[
        {
            "category":"Food & Beverages",
            "subcategory":"Groceries & Convenience Stores",
            "type":"Retail Goods"
        }
    ],
    "sg:phone":"+1 713 748 0510",
    "sg:postcode":"77004",
    "sg:province":"TX",
    "wof:name":"Aurora Food Market",
    "wof:placetype":"venue"
},
  "geometry": {"coordinates":[-95.346199,29.7302],"type":"Point"}
}