{
  "type": "Feature",
  "properties": {
    "iso:country":"US",
    "sg:address":"300 W 6th St Ste 900",
    "sg:city":"Austin",
    "sg:classifiers":[
        {
            "category":"Utilities",
            "subcategory":"Electric",
            "type":"Services"
        }
    ],
    "sg:phone":"+1 512 691 6100",
    "sg:postcode":"78701",
    "sg:province":"TX",
    "sg:website":"http://www.greenmountain.com",
    "wof:name":"Begreen",
    "wof:placetype":"venue"
},
  "geometry": {"coordinates":[-97.745216,30.268749],"type":"Point"}
}