{
  "type": "Feature",
  "properties": {
    "iso:country":"US",
    "sg:address":"15210 State Hwy 3",
    "sg:city":"Webster",
    "sg:classifiers":[
        {
            "category":"Recreation",
            "type":"Entertainment"
        }
    ],
    "sg:phone":"+1 281 480 8441",
    "sg:postcode":"77598",
    "sg:province":"TX",
    "sg:tags":[
        "martial",
        "arts",
        "instruction"
    ],
    "wof:name":"Karate America",
    "wof:placetype":"venue"
},
  "geometry": {"coordinates":[-95.144852,29.566245],"type":"Point"}
}