{
  "type": "Feature",
  "properties": {
    "iso:country":"US",
    "sg:address":"13300 Hargrave Rd",
    "sg:city":"Houston",
    "sg:classifiers":[
        {
            "category":"Health Services",
            "subcategory":"Doctor",
            "type":"Services"
        }
    ],
    "sg:phone":"+1 281 890 1784",
    "sg:postcode":"77070",
    "sg:province":"TX",
    "sg:tags":[
        "physician",
        "surgeon"
    ],
    "wof:name":"1960 Eye Surgeons",
    "wof:placetype":"venue"
},
  "geometry": {"coordinates":[-95.55261,29.967893],"type":"Point"}
}