{
  "type": "Feature",
  "properties": {
    "iso:country":"US",
    "sg:address":"5400 Thomason Dr",
    "sg:city":"Midland",
    "sg:classifiers":[
        {
            "category":"Professional",
            "type":"Services"
        }
    ],
    "sg:phone":"+1 432 689 8099",
    "sg:postcode":"79703",
    "sg:province":"TX",
    "sg:tags":[
        "establishment"
    ],
    "wof:name":"Oasis Auto Wash",
    "wof:placetype":"venue"
},
  "geometry": {"coordinates":[-102.148155,31.981714],"type":"Point"}
}