{
  "type": "Feature",
  "properties": {
    "iso:country":"US",
    "sg:address":"4600 S Medford Dr",
    "sg:city":"Lufkin",
    "sg:classifiers":[
        {
            "category":"Shopping",
            "subcategory":"Jewelry",
            "type":"Retail Goods"
        }
    ],
    "sg:phone":"+1 936 634 9606",
    "sg:postcode":"75901",
    "sg:province":"TX",
    "sg:tags":[
        "jeweler"
    ],
    "sg:website":"www.friedmans.com",
    "wof:name":"Friedman's",
    "wof:placetype":"venue"
},
  "geometry": {"coordinates":[-94.725319,31.310554],"type":"Point"}
}