{
  "type": "Feature",
  "properties": {
    "iso:country":"US",
    "sg:address":"10723 Preston Rd",
    "sg:city":"Dallas",
    "sg:classifiers":[
        {
            "category":"Social Services",
            "subcategory":"Child Care",
            "type":"Services"
        },
        {
            "category":"Local Transit",
            "type":"Transportation"
        }
    ],
    "sg:phone":"+1 972 306 5562",
    "sg:postcode":"75230",
    "sg:province":"TX",
    "sg:tags":[
        "day",
        "public"
    ],
    "wof:name":"Going My Way",
    "wof:placetype":"venue"
},
  "geometry": {"coordinates":[-96.804163,32.893592],"type":"Point"}
}