{
  "type": "Feature",
  "properties": {
    "iso:country":"US",
    "sg:address":"1401 N 4th St",
    "sg:city":"Killeen",
    "sg:classifiers":[
        {
            "category":"Building & Trades",
            "subcategory":"Construction",
            "type":"Services"
        }
    ],
    "sg:phone":"+1 254 768 9062",
    "sg:postcode":"76541",
    "sg:province":"TX",
    "sg:tags":[
        "altering",
        "remodeling",
        "contractor"
    ],
    "wof:name":"J Aguilar Remodeling",
    "wof:placetype":"venue"
},
  "geometry": {"coordinates":[-97.72611999999999,31.129379],"type":"Point"}
}