{
  "type": "Feature",
  "properties": {
    "iso:country":"US",
    "sg:address":"2423 du Pont St",
    "sg:city":"Pasadena",
    "sg:classifiers":[
        {
            "category":"Retail",
            "subcategory":"Repair Shop",
            "type":"Services"
        }
    ],
    "sg:phone":"+1 281 487 0027",
    "sg:postcode":"77503",
    "sg:province":"TX",
    "sg:tags":[
        "refrigeration"
    ],
    "wof:name":"C&M Air Conditioning & Refrige",
    "wof:placetype":"venue"
},
  "geometry": {"coordinates":[-95.15322,29.676559],"type":"Point"}
}