{
  "type": "Feature",
  "properties": {
    "iso:country":"US",
    "sg:address":"3822 Cedar Gardens Dr",
    "sg:city":"Houston",
    "sg:classifiers":[
        {
            "category":"Manufacturing",
            "subcategory":"Tools & Machinery",
            "type":"Manufacturing & Wholesale Goods"
        }
    ],
    "sg:phone":"+1 281 531 1712",
    "sg:postcode":"77082",
    "sg:province":"TX",
    "sg:tags":[
        "computer",
        "storage",
        "devices"
    ],
    "wof:name":"Advanced Digital Information",
    "wof:placetype":"venue"
},
  "geometry": {"coordinates":[-95.654246,29.714775],"type":"Point"}
}