{
  "type": "Feature",
  "properties": {
    "iso:country":"US",
    "sg:address":"5328 Antoine Dr",
    "sg:city":"Houston",
    "sg:classifiers":[
        {
            "category":"Shopping",
            "subcategory":"Mobile Phones",
            "type":"Retail Goods"
        }
    ],
    "sg:phone":"+1 713 956 0001",
    "sg:postcode":"77091",
    "sg:province":"TX",
    "wof:name":"Continental Exchange Solution Inc",
    "wof:placetype":"venue"
},
  "geometry": {"coordinates":[-95.472921,29.8416],"type":"Point"}
}