{
  "type": "Feature",
  "properties": {
    "iso:country":"US",
    "sg:address":"5184 US Hwy 290",
    "sg:city":"Austin",
    "sg:classifiers":[
        {
            "category":"Building & Trades",
            "subcategory":"Construction",
            "type":"Services"
        }
    ],
    "sg:phone":"+1 512 892 6192",
    "sg:postcode":"78735",
    "sg:province":"TX",
    "sg:tags":[
        "painter"
    ],
    "wof:name":"Buride Inc",
    "wof:placetype":"venue"
},
  "geometry": {"coordinates":[-97.82955200000001,30.236313],"type":"Point"}
}