{
  "type": "Feature",
  "properties": {
    "iso:country":"US",
    "sg:address":"13831 Pkwy Manor Dr",
    "sg:city":"Willis",
    "sg:classifiers":[
        {
            "category":"Freight",
            "type":"Transportation"
        }
    ],
    "sg:phone":"+1 936 856 4762",
    "sg:postcode":"77318",
    "sg:province":"TX",
    "sg:tags":[
        "operator",
        "trucking"
    ],
    "wof:name":"J D Jones Trucking",
    "wof:placetype":"venue"
},
  "geometry": {"coordinates":[-95.565276,30.414413],"type":"Point"}
}