{
  "type": "Feature",
  "properties": {
    "iso:country":"US",
    "sg:address":"14673 Midway Rd Ste 236",
    "sg:city":"Addison",
    "sg:classifiers":[
        {
            "category":"Health Services",
            "subcategory":"Doctor",
            "type":"Services"
        }
    ],
    "sg:phone":"+1 972 404 8677",
    "sg:postcode":"75001",
    "sg:province":"TX",
    "sg:tags":[
        "psychiatrist"
    ],
    "wof:name":"Humphrey Irving L MD",
    "wof:placetype":"venue"
},
  "geometry": {"coordinates":[-96.840335,32.948554],"type":"Point"}
}