{
  "type": "Feature",
  "properties": {
    "iso:country":"US",
    "sg:address":"802 S Ash St",
    "sg:city":"Perryton",
    "sg:classifiers":[
        {
            "category":"Building & Trades",
            "subcategory":"Plumbing",
            "type":"Services"
        }
    ],
    "sg:phone":"+1 806 435 5080",
    "sg:postcode":"79070",
    "sg:province":"TX",
    "sg:tags":[
        "plumber",
        "contractor"
    ],
    "wof:name":"Bob Jay's of Perryton Inc",
    "wof:placetype":"venue"
},
  "geometry": {"coordinates":[-100.80130800000001,36.392228],"type":"Point"}
}