{
  "type": "Feature",
  "properties": {
    "iso:country":"US",
    "sg:address":"9523 Bonny Brg",
    "sg:city":"San Antonio",
    "sg:classifiers":[
        {
            "category":"Professional",
            "subcategory":"Accounting & Tax Preparation",
            "type":"Services"
        }
    ],
    "sg:phone":"+1 210 690 1660",
    "sg:postcode":"78240",
    "sg:province":"TX",
    "sg:tags":[
        "bookkeeping",
        "general"
    ],
    "wof:name":"Bob Martin CPA",
    "wof:placetype":"venue"
},
  "geometry": {"coordinates":[-98.607221,29.529282],"type":"Point"}
}