{
  "type": "Feature",
  "properties": {
    "iso:country":"US",
    "sg:address":"5000 W Slaughter Ln",
    "sg:city":"Austin",
    "sg:classifiers":[
        {
            "category":"Shopping",
            "subcategory":"Mobile Phones",
            "type":"Retail Goods"
        }
    ],
    "sg:phone":"+1 512 291 8700",
    "sg:postcode":"78749",
    "sg:province":"TX",
    "wof:name":"Austin Direct Connect",
    "wof:placetype":"venue"
},
  "geometry": {"coordinates":[-97.86326099999999,30.200015],"type":"Point"}
}