{
  "type": "Feature",
  "properties": {
    "iso:country":"US",
    "sg:address":"919 N Guadalupe St",
    "sg:city":"Seguin",
    "sg:classifiers":[
        {
            "category":"Social Services",
            "type":"Services"
        }
    ],
    "sg:phone":"+1 830 401 0717",
    "sg:postcode":"78155",
    "sg:province":"TX",
    "sg:tags":[
        "youth",
        "organization",
        "center"
    ],
    "wof:name":"Seguin Youth Svc",
    "wof:placetype":"venue"
},
  "geometry": {"coordinates":[-97.969548,29.57671],"type":"Point"}
}