{
  "type": "Feature",
  "properties": {
    "iso:country":"US",
    "sg:address":"103 N Main St",
    "sg:city":"Gladewater",
    "sg:classifiers":[
        {
            "category":"Shopping",
            "subcategory":"Used Merchandise",
            "type":"Retail Goods"
        }
    ],
    "sg:phone":"+1 903 845 6406",
    "sg:postcode":"75647",
    "sg:province":"TX",
    "wof:name":"Cottage Antique Mall",
    "wof:placetype":"venue"
},
  "geometry": {"coordinates":[-94.943619,32.535614],"type":"Point"}
}