{
  "type": "Feature",
  "properties": {
    "iso:country":"US",
    "sg:address":"17110 Costero Dr",
    "sg:city":"Houston",
    "sg:classifiers":[
        {
            "category":"Professional",
            "type":"Services"
        }
    ],
    "sg:phone":"+1 281 277 0971",
    "sg:postcode":"77083",
    "sg:province":"TX",
    "wof:name":"Solaron Communications",
    "wof:placetype":"venue"
},
  "geometry": {"coordinates":[-95.681628,29.689382],"type":"Point"}
}