{
  "type": "Feature",
  "properties": {
    "iso:country":"US",
    "sg:address":"5683 Eastex Fwy",
    "sg:city":"Beaumont",
    "sg:classifiers":[
        {
            "category":"Building & Trades",
            "subcategory":"Construction",
            "type":"Services"
        }
    ],
    "sg:phone":"+1 409 892 0992",
    "sg:postcode":"77706",
    "sg:province":"TX",
    "sg:tags":[
        "house"
    ],
    "wof:name":"Don Lafleur Homes & Const",
    "wof:placetype":"venue"
},
  "geometry": {"coordinates":[-94.155232,30.12511],"type":"Point"}
}