{
  "type": "Feature",
  "properties": {
    "iso:country":"US",
    "sg:address":"2603 Texas Blvd",
    "sg:city":"Texarkana",
    "sg:classifiers":[
        {
            "category":"Real Estate",
            "subcategory":"Real Estate Agent",
            "type":"Services"
        }
    ],
    "sg:phone":"+1 903 838 0706",
    "sg:postcode":"75503",
    "sg:province":"TX",
    "wof:name":"Re/Max",
    "wof:placetype":"venue"
},
  "geometry": {"coordinates":[-94.05317599999999,33.442293],"type":"Point"}
}