{
  "type": "Feature",
  "properties": {
    "iso:country":"US",
    "sg:address":"1301 E 29th St",
    "sg:city":"Bryan",
    "sg:classifiers":[
        {
            "category":"Shopping",
            "subcategory":"Bicycles & Sporting Goods",
            "type":"Retail Goods"
        }
    ],
    "sg:phone":"+1 979 775 7047",
    "sg:postcode":"77802",
    "sg:province":"TX",
    "wof:name":"Bullfrog Pest Control",
    "wof:placetype":"venue"
},
  "geometry": {"coordinates":[-96.360204,30.663618],"type":"Point"}
}