{
  "type": "Feature",
  "properties": {
    "iso:country":"US",
    "sg:address":"6004 W 34th St",
    "sg:city":"Houston",
    "sg:classifiers":[
        {
            "category":"Restaurant",
            "type":"Food & Drink"
        }
    ],
    "sg:phone":"+1 713 681 7701",
    "sg:postcode":"77092",
    "sg:province":"TX",
    "wof:name":"34 Street Restaurant",
    "wof:placetype":"venue"
},
  "geometry": {"coordinates":[-95.47730300000001,29.819401],"type":"Point"}
}