{
  "type": "Feature",
  "properties": {
    "iso:country":"US",
    "sg:address":"1120 E Hwy 190",
    "sg:city":"Copperas Cove",
    "sg:classifiers":[
        {
            "category":"Shopping",
            "subcategory":"Used Merchandise",
            "type":"Retail Goods"
        }
    ],
    "sg:phone":"+1 254 547 5900",
    "sg:postcode":"76522",
    "sg:province":"TX",
    "wof:name":"Action Pawn Shop 3",
    "wof:placetype":"venue"
},
  "geometry": {"coordinates":[-97.893075,31.119822],"type":"Point"}
}