{
  "type": "Feature",
  "properties": {
    "iso:country":"US",
    "sg:address":"500 S Dr E E Dunlap St",
    "sg:city":"San Diego",
    "sg:classifiers":[
        {
            "category":"Banks & Credit Unions",
            "subcategory":"Bank",
            "type":"Services"
        }
    ],
    "sg:phone":"+1 361 279 8181",
    "sg:postcode":"78384",
    "sg:province":"TX",
    "sg:tags":[
        "small",
        "lender",
        "loan",
        "financing"
    ],
    "wof:name":"Security Finance Corp",
    "wof:placetype":"venue"
},
  "geometry": {"coordinates":[-98.24012500000001,27.760344],"type":"Point"}
}