{
  "type": "Feature",
  "properties": {
    "iso:country":"US",
    "sg:address":"6286 32nd St",
    "sg:city":"Groves",
    "sg:classifiers":[
        {
            "category":"Social Services",
            "subcategory":"Child Care",
            "type":"Services"
        }
    ],
    "sg:phone":"+1 409 962 7636",
    "sg:postcode":"77619",
    "sg:province":"TX",
    "wof:name":"Red Apple Day Care",
    "wof:placetype":"venue"
},
  "geometry": {"coordinates":[-93.911849,29.942282],"type":"Point"}
}