{
  "type": "Feature",
  "properties": {
    "iso:country":"US",
    "sg:address":"2503 Big Horn Dr",
    "sg:city":"Austin",
    "sg:classifiers":[
        {
            "category":"Professional",
            "type":"Services"
        }
    ],
    "sg:phone":"+1 512 266 1014",
    "sg:postcode":"78734",
    "sg:province":"TX",
    "wof:name":"Terrie Gilbert Assoc",
    "wof:placetype":"venue"
},
  "geometry": {"coordinates":[-97.91587,30.372281],"type":"Point"}
}