{
  "type": "Feature",
  "properties": {
    "iso:country":"US",
    "sg:address":"2011 N Chadbourne St",
    "sg:city":"San Angelo",
    "sg:classifiers":[
        {
            "category":"Restaurant",
            "type":"Food & Drink"
        }
    ],
    "sg:phone":"+1 325 659 2600",
    "sg:postcode":"76903",
    "sg:province":"TX",
    "wof:name":"Hidalgo's HBS",
    "wof:placetype":"venue"
},
  "geometry": {"coordinates":[-100.449174,31.481247],"type":"Point"}
}