{
  "type": "Feature",
  "properties": {
    "iso:country":"US",
    "sg:address":"350 New York Ave",
    "sg:city":"New Braunfels",
    "sg:classifiers":[
        {
            "category":"Wholesale",
            "subcategory":"Machinery & Supplies",
            "type":"Manufacturing & Wholesale Goods"
        },
        {
            "category":"Building & Trades",
            "subcategory":"Cleaning & Sanitation",
            "type":"Services"
        }
    ],
    "sg:phone":"+1 830 624 7866",
    "sg:postcode":"78130",
    "sg:province":"TX",
    "sg:tags":[
        "equipment",
        "window",
        "establishment"
    ],
    "wof:name":"Clear Solutions Window Clean",
    "wof:placetype":"venue"
},
  "geometry": {"coordinates":[-98.143528,29.714032],"type":"Point"}
}