{
  "type": "Feature",
  "properties": {
    "iso:country":"US",
    "sg:address":"1020 E Hillside Rd",
    "sg:city":"Laredo",
    "sg:classifiers":[
        {
            "category":"Health Services",
            "subcategory":"Doctor",
            "type":"Services"
        }
    ],
    "sg:phone":"+1 956 727 7303",
    "sg:postcode":"78041",
    "sg:province":"TX",
    "sg:tags":[
        "physician",
        "surgeon"
    ],
    "wof:name":"Laredo Women's Ctr",
    "wof:placetype":"venue"
},
  "geometry": {"coordinates":[-99.48746199999999,27.545602],"type":"Point"}
}