{
  "type": "Feature",
  "properties": {
    "iso:country":"US",
    "sg:address":"1410 N Lee Trevino Dr",
    "sg:city":"El Paso",
    "sg:classifiers":[
        {
            "category":"Airline",
            "type":"Transportation"
        }
    ],
    "sg:phone":"+1 915 581 5550",
    "sg:postcode":"79936",
    "sg:province":"TX",
    "sg:tags":[
        "courier",
        "air"
    ],
    "wof:name":"Fedex",
    "wof:placetype":"venue"
},
  "geometry": {"coordinates":[-106.31947700000001,31.745774],"type":"Point"}
}