{
  "type": "Feature",
  "properties": {
    "iso:country":"US",
    "sg:address":"1511 Lakeside Enclave Dr",
    "sg:city":"Houston",
    "sg:classifiers":[
        {
            "category":"Building & Trades",
            "subcategory":"Equipment Rental",
            "type":"Services"
        }
    ],
    "sg:phone":"+1 281 556 0910",
    "sg:postcode":"77077",
    "sg:province":"TX",
    "wof:name":"Geek Rental",
    "wof:placetype":"venue"
},
  "geometry": {"coordinates":[-95.621443,29.752131],"type":"Point"}
}