{
  "type": "Feature",
  "properties": {
    "iso:country":"US",
    "sg:address":"11508 Sweetwater Trl",
    "sg:city":"Austin",
    "sg:classifiers":[
        {
            "category":"Professional",
            "subcategory":"Management & Consulting",
            "type":"Services"
        }
    ],
    "sg:phone":"+1 512 250 9871",
    "sg:postcode":"78750",
    "sg:province":"TX",
    "sg:tags":[
        "consultant",
        "business"
    ],
    "wof:name":"Thomas Love Associates",
    "wof:placetype":"venue"
},
  "geometry": {"coordinates":[-97.81863800000001,30.45188],"type":"Point"}
}