{
  "type": "Feature",
  "properties": {
    "iso:country":"US",
    "sg:address":"1610 Texas Ave",
    "sg:city":"San Antonio",
    "sg:classifiers":[
        {
            "category":"Restaurant",
            "type":"Food & Drink"
        }
    ],
    "sg:phone":"+1 210 735 5215",
    "sg:postcode":"78201",
    "sg:province":"TX",
    "sg:tags":[
        "mexican"
    ],
    "wof:name":"Castillo Del Lago",
    "wof:placetype":"venue"
},
  "geometry": {"coordinates":[-98.538652,29.449688],"type":"Point"}
}