{
  "type": "Feature",
  "properties": {
    "iso:country":"US",
    "sg:address":"2601 Preston Rd",
    "sg:city":"Frisco",
    "sg:classifiers":[
        {
            "category":"Shopping",
            "subcategory":"Jewelry",
            "type":"Retail Goods"
        }
    ],
    "sg:phone":"+1 972 731 0407",
    "sg:postcode":"75034",
    "sg:province":"TX",
    "sg:tags":[
        "jeweler"
    ],
    "sg:website":"www.helzberg.com",
    "wof:name":"Helzberg Diamonds",
    "wof:placetype":"venue"
},
  "geometry": {"coordinates":[-96.805673,33.099351],"type":"Point"}
}