{
  "type": "Feature",
  "properties": {
    "iso:country":"US",
    "sg:address":"221 E Upas Ave",
    "sg:city":"Mcallen",
    "sg:classifiers":[
        {
            "category":"Building & Trades",
            "subcategory":"Electrical",
            "type":"Services"
        }
    ],
    "sg:phone":"+1 956 668 8212",
    "sg:postcode":"78501",
    "sg:province":"TX",
    "sg:tags":[
        "booth",
        "equipment",
        "telephone",
        "pay"
    ],
    "wof:name":"Superior Payphones LTD",
    "wof:placetype":"venue"
},
  "geometry": {"coordinates":[-98.20962299999999,26.219494],"type":"Point"}
}