{
  "type": "Feature",
  "properties": {
    "iso:country":"US",
    "sg:address":"3301 Collard Rd",
    "sg:city":"Huntsville",
    "sg:classifiers":[
        {
            "category":"Banks & Credit Unions",
            "subcategory":"Investment Brokerage",
            "type":"Services"
        }
    ],
    "sg:phone":"+1 936 295 1066",
    "sg:postcode":"77340",
    "sg:province":"TX",
    "wof:name":"Molar Investments",
    "wof:placetype":"venue"
},
  "geometry": {"coordinates":[-95.552048,30.690906],"type":"Point"}
}