{
  "type": "Feature",
  "properties": {
    "iso:country":"US",
    "sg:address":"1621 E Iowa Rd",
    "sg:city":"Edinburg",
    "sg:classifiers":[
        {
            "category":"Autos & Motor Vehicles",
            "subcategory":"Recreational Vehicle Sales",
            "type":"Retail Goods"
        },
        {
            "category":"Building & Trades",
            "subcategory":"Equipment Rental",
            "type":"Services"
        },
        {
            "category":"Building & Trades",
            "subcategory":"Construction",
            "type":"Services"
        },
        {
            "category":"Manufacturing",
            "subcategory":"Building Materials",
            "type":"Manufacturing & Wholesale Goods"
        }
    ],
    "sg:phone":"+1 956 287 1700",
    "sg:postcode":"78542",
    "sg:province":"TX",
    "sg:tags":[
        "repairing",
        "oil",
        "leasing",
        "field",
        "automobile",
        "forklift",
        "cranes-mobile",
        "facilities-renting",
        "trucks-rental",
        "crane",
        "cranes-renting"
    ],
    "wof:name":"Tnt Crane & Rigging, Inc.",
    "wof:placetype":"venue"
},
  "geometry": {"coordinates":[-98.149413,26.281011],"type":"Point"}
}