{
  "type": "Feature",
  "properties": {
    "iso:country":"US",
    "sg:address":"10101 Fernstone Ln",
    "sg:city":"Houston",
    "sg:classifiers":[
        {
            "category":"Banks & Credit Unions",
            "subcategory":"Bank",
            "type":"Services"
        }
    ],
    "sg:phone":"+1 713 541 4439",
    "sg:postcode":"77070",
    "sg:province":"TX",
    "sg:tags":[
        "broker",
        "mortgage"
    ],
    "wof:name":"Fondren Financial Services",
    "wof:placetype":"venue"
},
  "geometry": {"coordinates":[-95.57186299999999,29.952344],"type":"Point"}
}