{
  "type": "Feature",
  "properties": {
    "iso:country":"US",
    "sg:address":"4024 S Lamar Blvd",
    "sg:city":"Austin",
    "sg:classifiers":[
        {
            "category":"Fast Food",
            "type":"Food & Drink"
        }
    ],
    "sg:phone":"+1 512 444 8202",
    "sg:postcode":"78704",
    "sg:province":"TX",
    "sg:tags":[
        "burger"
    ],
    "wof:name":"Fuddruckers",
    "wof:placetype":"venue"
},
  "geometry": {"coordinates":[-97.792,30.2369],"type":"Point"}
}