{
  "type": "Feature",
  "properties": {
    "iso:country":"US",
    "sg:address":"601 Stella St",
    "sg:city":"Baytown",
    "sg:classifiers":[
        {
            "category":"Building & Trades",
            "subcategory":"Construction",
            "type":"Services"
        }
    ],
    "sg:phone":"+1 281 427 2445",
    "sg:postcode":"77520",
    "sg:province":"TX",
    "sg:tags":[
        "contractor"
    ],
    "wof:name":"Sierra Brothers Roofing",
    "wof:placetype":"venue"
},
  "geometry": {"coordinates":[-94.97863,29.72578],"type":"Point"}
}