{
  "type": "Feature",
  "properties": {
    "iso:country":"US",
    "sg:address":"1 Medical Pkwy Ste 102",
    "sg:city":"Dallas",
    "sg:classifiers":[
        {
            "category":"Health Services",
            "subcategory":"Doctor",
            "type":"Services"
        }
    ],
    "sg:phone":"+1 972 247 2600",
    "sg:postcode":"75234",
    "sg:province":"TX",
    "wof:name":"Spiegel Mark K MD",
    "wof:placetype":"venue"
},
  "geometry": {"coordinates":[-96.87309999999999,32.915199],"type":"Point"}
}