{
  "type": "Feature",
  "properties": {
    "iso:country":"US",
    "sg:address":"3411 Armstrong St",
    "sg:city":"San Angelo",
    "sg:classifiers":[
        {
            "category":"Retail",
            "subcategory":"Repair Shop",
            "type":"Services"
        }
    ],
    "sg:phone":"+1 325 653 0897",
    "sg:postcode":"76903",
    "sg:province":"TX",
    "sg:tags":[
        "welding"
    ],
    "wof:name":"D Rays Welding",
    "wof:placetype":"venue"
},
  "geometry": {"coordinates":[-100.436756,31.495106],"type":"Point"}
}