{
  "type": "Feature",
  "properties": {
    "iso:country":"US",
    "sg:address":"607 Edwards Blvd",
    "sg:city":"Big Spring",
    "sg:classifiers":[
        {
            "category":"Professional",
            "subcategory":"Computer Services",
            "type":"Services"
        }
    ],
    "sg:phone":"+1 432 267 1011",
    "sg:postcode":"79720",
    "sg:province":"TX",
    "sg:tags":[
        "programing",
        "custom"
    ],
    "wof:name":"Bryant Enterprises",
    "wof:placetype":"venue"
},
  "geometry": {"coordinates":[-101.478786,32.234078],"type":"Point"}
}