{
  "type": "Feature",
  "properties": {
    "iso:country":"US",
    "sg:address":"5817 Colhurst St",
    "sg:city":"Dallas",
    "sg:classifiers":[
        {
            "category":"Shopping",
            "subcategory":"Jewelry",
            "type":"Retail Goods"
        }
    ],
    "sg:phone":"+1 214 692 8151",
    "sg:postcode":"75230",
    "sg:province":"TX",
    "sg:tags":[
        "jeweler"
    ],
    "wof:name":"Barry Martin",
    "wof:placetype":"venue"
},
  "geometry": {"coordinates":[-96.80699799999999,32.881195],"type":"Point"}
}