{
  "type": "Feature",
  "properties": {
    "iso:country":"US",
    "sg:address":"2405 Broadway St",
    "sg:city":"Lubbock",
    "sg:classifiers":[
        {
            "category":"Professional",
            "subcategory":"Lawyer & Legal Services",
            "type":"Services"
        }
    ],
    "sg:phone":"+1 806 747 4416",
    "sg:postcode":"79401",
    "sg:province":"TX",
    "wof:name":"Curry & Associates",
    "wof:placetype":"venue"
},
  "geometry": {"coordinates":[-101.870554,33.584369],"type":"Point"}
}