{
  "type": "Feature",
  "properties": {
    "iso:country":"US",
    "sg:address":"2205 N Lamar Blvd Apt 211",
    "sg:city":"Austin",
    "sg:classifiers":[
        {
            "category":"Professional",
            "subcategory":"Management & Consulting",
            "type":"Services"
        }
    ],
    "sg:phone":"+1 713 201 7592",
    "sg:postcode":"78705",
    "sg:province":"TX",
    "sg:tags":[
        "counselor",
        "relation",
        "public"
    ],
    "wof:name":"Adele Houghton Consulting",
    "wof:placetype":"venue"
},
  "geometry": {"coordinates":[-97.753212,30.286189],"type":"Point"}
}