{
  "type": "Feature",
  "properties": {
    "iso:country":"US",
    "sg:address":"3431 Alameda Ave",
    "sg:city":"El Paso",
    "sg:classifiers":[
        {
            "category":"Autos & Motor Vehicles",
            "subcategory":"Fuel & Gas Station",
            "type":"Retail Goods"
        }
    ],
    "sg:phone":"+1 915 544 2151",
    "sg:postcode":"79905",
    "sg:province":"TX",
    "sg:tags":[
        "convenience",
        "station"
    ],
    "wof:name":"Chevron",
    "wof:placetype":"venue"
},
  "geometry": {"coordinates":[-106.453554,31.773552],"type":"Point"}
}