{
  "type": "Feature",
  "properties": {
    "iso:country":"US",
    "sg:address":"3913 Arc St",
    "sg:city":"Houston",
    "sg:classifiers":[
        {
            "category":"Autos & Motor Vehicles",
            "subcategory":"Motorcycle Sales",
            "type":"Retail Goods"
        }
    ],
    "sg:phone":"+1 713 974 1908",
    "sg:postcode":"77063",
    "sg:province":"TX",
    "sg:website":"texoticmotorsports.com",
    "wof:name":"Texotic Motorsports",
    "wof:placetype":"venue"
},
  "geometry": {"coordinates":[-95.531066,29.721848],"type":"Point"}
}