{
  "type": "Feature",
  "properties": {
    "iso:country":"US",
    "sg:address":"7517 Duling Ln",
    "sg:city":"Amarillo",
    "sg:classifiers":[
        {
            "category":"Farming",
            "subcategory":"Livestock Farm",
            "type":"Manufacturing & Wholesale Goods"
        }
    ],
    "sg:phone":"+1 806 488 2446",
    "sg:postcode":"79110",
    "sg:province":"TX",
    "sg:tags":[
        "ranch"
    ],
    "wof:name":"Alton Wilson",
    "wof:placetype":"venue"
},
  "geometry": {"coordinates":[-101.88672,35.129822],"type":"Point"}
}