{
  "type": "Feature",
  "properties": {
    "iso:country":"US",
    "sg:address":"1040 N Bell Blvd",
    "sg:city":"Cedar Park",
    "sg:classifiers":[
        {
            "category":"Restaurant",
            "type":"Food & Drink"
        }
    ],
    "sg:menulink":"http://www.allmenus.com/tx/liberty-hill-cedar-park/176982-kfc---kentucky-fried-chicken/menu/",
    "sg:phone":"+1 512 259 0069",
    "sg:postcode":"78613",
    "sg:province":"TX",
    "sg:tags":[
        "american",
        "chicken"
    ],
    "wof:name":"KFC - Kentucky Fried Chicken",
    "wof:placetype":"venue"
},
  "geometry": {"coordinates":[-97.82996199999999,30.521587],"type":"Point"}
}