{
  "type": "Feature",
  "properties": {
    "iso:country":"US",
    "sg:address":"950 Sir Henry Dr",
    "sg:city":"Woodville",
    "sg:classifiers":[
        {
            "category":"Building & Trades",
            "subcategory":"Plumbing",
            "type":"Services"
        }
    ],
    "sg:phone":"+1 409 283 3072",
    "sg:postcode":"75979",
    "sg:province":"TX",
    "sg:tags":[
        "repair",
        "contractor"
    ],
    "wof:name":"D&D Plumbing",
    "wof:placetype":"venue"
},
  "geometry": {"coordinates":[-94.427863,30.680107],"type":"Point"}
}