{
  "type": "Feature",
  "properties": {
    "iso:country":"US",
    "sg:address":"1224 E Jackson Ave",
    "sg:city":"Mcallen",
    "sg:classifiers":[
        {
            "category":"Restaurant",
            "type":"Food & Drink"
        }
    ],
    "sg:menulink":"http://www.allmenus.com/tx/mcallen-pharr/10533-texas-roadhouse/menu/",
    "sg:phone":"+1 956 682 5400",
    "sg:postcode":"78503",
    "sg:province":"TX",
    "sg:tags":[
        "american",
        "steakhouse"
    ],
    "wof:name":"Texas Roadhouse",
    "wof:placetype":"venue"
},
  "geometry": {"coordinates":[-98.20836799999999,26.19107],"type":"Point"}
}