{
  "type": "Feature",
  "properties": {
    "iso:country":"US",
    "sg:address":"5124 82nd St",
    "sg:city":"Lubbock",
    "sg:classifiers":[
        {
            "category":"Insurance",
            "subcategory":"Insurance Agent",
            "type":"Services"
        }
    ],
    "sg:phone":"+1 806 798 8787",
    "sg:postcode":"79424",
    "sg:province":"TX",
    "wof:name":"Wayne Lawley",
    "wof:placetype":"venue"
},
  "geometry": {"coordinates":[-101.91884400000001,33.519796],"type":"Point"}
}