{
  "type": "Feature",
  "properties": {
    "iso:country":"US",
    "sg:address":"516 S Main St",
    "sg:city":"Mcallen",
    "sg:classifiers":[
        {
            "category":"Wholesale",
            "subcategory":"Plants",
            "type":"Manufacturing & Wholesale Goods"
        }
    ],
    "sg:phone":"+1 956 971 9998",
    "sg:postcode":"78501",
    "sg:province":"TX",
    "sg:tags":[
        "supply"
    ],
    "wof:name":"Flores Mia",
    "wof:placetype":"venue"
},
  "geometry": {"coordinates":[-98.235423,26.198743],"type":"Point"}
}