{
  "type": "Feature",
  "properties": {
    "iso:country":"US",
    "sg:address":"5302 E Belknap St",
    "sg:city":"Haltom City",
    "sg:classifiers":[
        {
            "category":"Insurance",
            "subcategory":"Insurance Agent",
            "type":"Services"
        }
    ],
    "sg:phone":"+1 817 838 0020",
    "sg:postcode":"76117",
    "sg:province":"TX",
    "wof:name":"Farmers Insurance Group",
    "wof:placetype":"venue"
},
  "geometry": {"coordinates":[-97.269392,32.796094],"type":"Point"}
}