{
  "type": "Feature",
  "properties": {
    "iso:country":"US",
    "sg:address":"3926 S Zarzamora",
    "sg:city":"San Antonio",
    "sg:classifiers":[
        {
            "category":"Retail",
            "subcategory":"Car Wash",
            "type":"Services"
        }
    ],
    "sg:phone":"+1 210 344 9631",
    "sg:postcode":"78225",
    "sg:province":"TX",
    "sg:tags":[
        "carwash"
    ],
    "wof:name":"Hura King Car Wash",
    "wof:placetype":"venue"
},
  "geometry": {"coordinates":[-98.533102,29.385642],"type":"Point"}
}