{
  "type": "Feature",
  "properties": {
    "iso:country":"US",
    "sg:address":"701 Plymouth Park",
    "sg:city":"Irving",
    "sg:classifiers":[
        {
            "category":"Shopping",
            "subcategory":"Computers & Home Electronics",
            "type":"Retail Goods"
        }
    ],
    "sg:phone":"+1 972 986 9071",
    "sg:postcode":"75061",
    "sg:province":"TX",
    "sg:tags":[
        "software"
    ],
    "wof:name":"Primesoft Technology Inc",
    "wof:placetype":"venue"
},
  "geometry": {"coordinates":[-96.976439,32.829862],"type":"Point"}
}