{
  "type": "Feature",
  "properties": {
    "iso:country":"US",
    "sg:address":"1102 Tenaha St",
    "sg:city":"Center",
    "sg:classifiers":[
        {
            "category":"Manufacturing",
            "subcategory":"Lumber",
            "type":"Manufacturing & Wholesale Goods"
        }
    ],
    "sg:phone":"+1 936 598 2192",
    "sg:postcode":"75935",
    "sg:province":"TX",
    "sg:tags":[
        "government"
    ],
    "wof:name":"Forest Service Ctr",
    "wof:placetype":"venue"
},
  "geometry": {"coordinates":[-94.193331,31.810666],"type":"Point"}
}