{
  "type": "Feature",
  "properties": {
    "iso:country":"US",
    "sg:address":"500 South Fwy",
    "sg:city":"Fort Worth",
    "sg:classifiers":[
        {
            "category":"Building & Trades",
            "subcategory":"Construction",
            "type":"Services"
        }
    ],
    "sg:phone":"+1 817 348 8208",
    "sg:postcode":"76104",
    "sg:province":"TX",
    "sg:tags":[
        "house"
    ],
    "wof:name":"Byron Court Construction",
    "wof:placetype":"venue"
},
  "geometry": {"coordinates":[-97.320871,32.738645],"type":"Point"}
}