{
  "type": "Feature",
  "properties": {
    "iso:country":"US",
    "sg:address":"223 W Quill Dr",
    "sg:city":"San Antonio",
    "sg:classifiers":[
        {
            "category":"Building & Trades",
            "subcategory":"Equipment Rental",
            "type":"Services"
        }
    ],
    "sg:phone":"+1 210 228 0777",
    "sg:postcode":"78228",
    "sg:province":"TX",
    "sg:tags":[
        "center"
    ],
    "wof:name":"Ace Rent-All Inc",
    "wof:placetype":"venue"
},
  "geometry": {"coordinates":[-98.571962,29.466367],"type":"Point"}
}