{
  "type": "Feature",
  "properties": {
    "iso:country":"US",
    "sg:address":"4308 Angus Dr",
    "sg:city":"Fort Worth",
    "sg:classifiers":[
        {
            "category":"Professional",
            "subcategory":"Management & Consulting",
            "type":"Services"
        }
    ],
    "sg:phone":"+1 817 731 3795",
    "sg:postcode":"76116",
    "sg:province":"TX",
    "sg:tags":[
        "business"
    ],
    "wof:name":"Collegiate Products Inc",
    "wof:placetype":"venue"
},
  "geometry": {"coordinates":[-97.430267,32.707892],"type":"Point"}
}