{
  "type": "Feature",
  "properties": {
    "iso:country":"US",
    "sg:address":"2368 Oates Dr",
    "sg:city":"Dallas",
    "sg:classifiers":[
        {
            "category":"Shopping",
            "subcategory":"Pawn Shop",
            "type":"Retail Goods"
        }
    ],
    "sg:phone":"+1 214 328 4635",
    "sg:postcode":"75228",
    "sg:province":"TX",
    "sg:tags":[
        "pawnbroker"
    ],
    "wof:name":"B J's Pawn Shop",
    "wof:placetype":"venue"
},
  "geometry": {"coordinates":[-96.675476,32.821433],"type":"Point"}
}