{
  "type": "Feature",
  "properties": {
    "iso:country":"US",
    "sg:address":"708 Knox St",
    "sg:city":"Houston",
    "sg:classifiers":[
        {
            "category":"Building & Trades",
            "subcategory":"Construction",
            "type":"Services"
        }
    ],
    "sg:phone":"+1 713 864 5385",
    "sg:postcode":"77007",
    "sg:province":"TX",
    "sg:tags":[
        "resurfacing",
        "laying",
        "refinishing",
        "floor"
    ],
    "wof:name":"M & M Wood Floors",
    "wof:placetype":"venue"
},
  "geometry": {"coordinates":[-95.420945,29.768065],"type":"Point"}
}