{
  "type": "Feature",
  "properties": {
    "iso:country":"US",
    "sg:address":"500 W 50th St",
    "sg:city":"Odessa",
    "sg:classifiers":[
        {
            "category":"Autos & Motor Vehicles",
            "subcategory":"Auto Supplies",
            "type":"Retail Goods"
        }
    ],
    "sg:phone":"+1 432 367 1555",
    "sg:postcode":"79764",
    "sg:province":"TX",
    "sg:tags":[
        "furniture"
    ],
    "wof:name":"C JS Auto & Salvage",
    "wof:placetype":"venue"
},
  "geometry": {"coordinates":[-102.395923,31.889322],"type":"Point"}
}