{
  "type": "Feature",
  "properties": {
    "iso:country":"US",
    "sg:address":"2213 Loop 256",
    "sg:city":"Palestine",
    "sg:classifiers":[
        {
            "category":"Shopping",
            "subcategory":"Hobbies, Toys, & Games",
            "type":"Retail Goods"
        }
    ],
    "sg:phone":"+1 903 723 5541",
    "sg:postcode":"75801",
    "sg:province":"TX",
    "sg:tags":[
        "supply"
    ],
    "wof:name":"Gamestop",
    "wof:placetype":"venue"
},
  "geometry": {"coordinates":[-95.612888,31.734358],"type":"Point"}
}