{
  "type": "Feature",
  "properties": {
    "iso:country":"US",
    "sg:address":"504 E Crestwood Dr",
    "sg:city":"Victoria",
    "sg:classifiers":[
        {
            "category":"Freight",
            "type":"Transportation"
        }
    ],
    "sg:phone":"+1 361 576 0100",
    "sg:postcode":"77901",
    "sg:province":"TX",
    "sg:tags":[
        "operator",
        "local",
        "trucking"
    ],
    "wof:name":"Crossroads Movers Inc",
    "wof:placetype":"venue"
},
  "geometry": {"coordinates":[-96.998935,28.828155],"type":"Point"}
}