{
  "type": "Feature",
  "properties": {
    "iso:country":"US",
    "sg:address":"4500 Shoal Creek Blvd",
    "sg:city":"Austin",
    "sg:classifiers":[
        {
            "category":"Real Estate",
            "subcategory":"Real Estate Agent",
            "type":"Services"
        }
    ],
    "sg:phone":"+1 512 454 5149",
    "sg:postcode":"78756",
    "sg:province":"TX",
    "wof:name":"Dorothy Wallace Realtors",
    "wof:placetype":"venue"
},
  "geometry": {"coordinates":[-97.745347,30.318699],"type":"Point"}
}