{
  "type": "Feature",
  "properties": {
    "iso:country":"US",
    "sg:address":"1001 E 15th St",
    "sg:city":"Plano",
    "sg:classifiers":[
        {
            "category":"Insurance",
            "subcategory":"Insurance Agent",
            "type":"Services"
        }
    ],
    "sg:phone":"+1 972 423 4546",
    "sg:postcode":"75074",
    "sg:province":"TX",
    "sg:tags":[
        "property",
        "broker",
        "casualty"
    ],
    "wof:name":"Schell A R & Son Agency",
    "wof:placetype":"venue"
},
  "geometry": {"coordinates":[-96.70083099999999,33.019658],"type":"Point"}
}