{
  "type": "Feature",
  "properties": {
    "iso:country":"US",
    "sg:address":"1775 Dickinson Ave",
    "sg:city":"Dickinson",
    "sg:classifiers":[
        {
            "category":"Home & Garden",
            "subcategory":"Building Materials",
            "type":"Retail Goods"
        }
    ],
    "sg:phone":"+1 281 534 9366",
    "sg:postcode":"77539",
    "sg:province":"TX",
    "sg:tags":[
        "glass",
        "window",
        "plate"
    ],
    "wof:name":"Coastal Glass & Mirror Inc",
    "wof:placetype":"venue"
},
  "geometry": {"coordinates":[-95.04718,29.484836],"type":"Point"}
}