{
  "type": "Feature",
  "properties": {
    "iso:country":"US",
    "sg:address":"1049 Eagle Dr",
    "sg:city":"De Soto",
    "sg:classifiers":[
        {
            "category":"Professional",
            "subcategory":"Research",
            "type":"Services"
        }
    ],
    "sg:phone":"+1 972 230 3632",
    "sg:postcode":"75115",
    "sg:province":"TX",
    "sg:tags":[
        "organization",
        "noncommercial"
    ],
    "wof:name":"Lawrence J Phillips Research",
    "wof:placetype":"venue"
},
  "geometry": {"coordinates":[-96.881811,32.585434],"type":"Point"}
}