{
  "type": "Feature",
  "properties": {
    "iso:country":"US",
    "sg:address":"3710 Cedar Street",
    "sg:city":"Austin",
    "sg:classifiers":[
        {
            "category":"Communications",
            "subcategory":"Newspaper",
            "type":"Services"
        }
    ],
    "sg:phone":"+1 512 451 7433",
    "sg:postcode":"78705",
    "sg:province":"TX",
    "sg:tags":[
        "print",
        "medium"
    ],
    "wof:name":"Senior Advocate Newspaper",
    "wof:placetype":"venue"
},
  "geometry": {"coordinates":[-97.734938,30.300719],"type":"Point"}
}