{
  "type": "Feature",
  "properties": {
    "iso:country":"US",
    "sg:address":"10910 Will Clayton Pkwy",
    "sg:city":"Humble",
    "sg:classifiers":[
        {
            "category":"Fast Food",
            "type":"Food & Drink"
        },
        {
            "category":"Restaurant",
            "type":"Food & Drink"
        }
    ],
    "sg:phone":"+1 281 852 0618",
    "sg:postcode":"77396",
    "sg:province":"TX",
    "sg:tags":[
        "chicken",
        "take"
    ],
    "sg:website":"http://www.churchschicken.com",
    "wof:name":"Church's Chicken",
    "wof:placetype":"venue"
},
  "geometry": {"coordinates":[-95.217491,29.979208],"type":"Point"}
}