{
  "type": "Feature",
  "properties": {
    "iso:country":"US",
    "sg:address":"310 Longview Dr",
    "sg:city":"Keller",
    "sg:classifiers":[
        {
            "category":"Wholesale",
            "subcategory":"Apparel",
            "type":"Manufacturing & Wholesale Goods"
        }
    ],
    "sg:phone":"+1 817 337 2734",
    "sg:postcode":"76248",
    "sg:province":"TX",
    "sg:tags":[
        "woman",
        "clothing"
    ],
    "wof:name":"Jim Carroll License Corp",
    "wof:placetype":"venue"
},
  "geometry": {"coordinates":[-97.21243200000001,32.930895],"type":"Point"}
}