{
  "type": "Feature",
  "properties": {
    "iso:country":"US",
    "sg:address":"1619 W 6th St",
    "sg:city":"Austin",
    "sg:classifiers":[
        {
            "category":"Health Services",
            "subcategory":"Chiropractor",
            "type":"Services"
        }
    ],
    "sg:phone":"+1 512 708 0421",
    "sg:postcode":"78703",
    "sg:province":"TX",
    "wof:name":"West End Chiropractic",
    "wof:placetype":"venue"
},
  "geometry": {"coordinates":[-97.764099,30.275499],"type":"Point"}
}