{
  "type": "Feature",
  "properties": {
    "iso:country":"US",
    "sg:address":"1602 Thibodeaux Dr",
    "sg:city":"Round Rock",
    "sg:classifiers":[
        {
            "category":"Professional",
            "type":"Services"
        }
    ],
    "sg:phone":"+1 512 773 4196",
    "sg:postcode":"78664",
    "sg:province":"TX",
    "wof:name":"Bella Tutti Designs",
    "wof:placetype":"venue"
},
  "geometry": {"coordinates":[-97.653516,30.4817],"type":"Point"}
}