{
  "type": "Feature",
  "properties": {
    "iso:country":"US",
    "sg:address":"104 Denver Blvd",
    "sg:city":"San Antonio",
    "sg:classifiers":[
        {
            "category":"Wholesale",
            "subcategory":"Medical Equipment & Supplies",
            "type":"Manufacturing & Wholesale Goods"
        }
    ],
    "sg:phone":"+1 210 532 5042",
    "sg:postcode":"78210",
    "sg:province":"TX",
    "wof:name":"First Aid Medical Suppiles",
    "wof:placetype":"venue"
},
  "geometry": {"coordinates":[-98.474784,29.404837],"type":"Point"}
}