{
  "type": "Feature",
  "properties": {
    "iso:country":"US",
    "sg:address":"2644 Avenue E",
    "sg:city":"Ingleside",
    "sg:classifiers":[
        {
            "category":"Building & Trades",
            "subcategory":"Landscaping Services",
            "type":"Services"
        }
    ],
    "sg:phone":"+1 832 721 4434",
    "sg:postcode":"78362",
    "sg:province":"TX",
    "sg:tags":[
        "landscape",
        "contractor"
    ],
    "wof:name":"Esquivel Landscaping",
    "wof:placetype":"venue"
},
  "geometry": {"coordinates":[-97.211274,27.873804],"type":"Point"}
}