{
  "type": "Feature",
  "properties": {
    "iso:country":"US",
    "sg:address":"1706 Glouchester Dr",
    "sg:city":"Garland",
    "sg:classifiers":[
        {
            "category":"Professional",
            "subcategory":"Engineering",
            "type":"Services"
        }
    ],
    "sg:phone":"+1 972 495 8154",
    "sg:postcode":"75044",
    "sg:province":"TX",
    "wof:name":"Hicks Industries",
    "wof:placetype":"venue"
},
  "geometry": {"coordinates":[-96.65604399999999,32.933853],"type":"Point"}
}