{
  "type": "Feature",
  "properties": {
    "iso:country":"US",
    "sg:address":"260 Passmore Ln",
    "sg:city":"Springtown",
    "sg:classifiers":[
        {
            "category":"Professional",
            "subcategory":"Art Services",
            "type":"Services"
        }
    ],
    "sg:phone":"+1 817 677 2028",
    "sg:postcode":"76082",
    "sg:province":"TX",
    "sg:tags":[
        "designer",
        "display",
        "producer"
    ],
    "wof:name":"Designs Ur Way",
    "wof:placetype":"venue"
},
  "geometry": {"coordinates":[-97.59706799999999,32.922511],"type":"Point"}
}