{
  "type": "Feature",
  "properties": {
    "iso:country":"US",
    "sg:address":"1104 S Ewing Ave",
    "sg:city":"Dallas",
    "sg:classifiers":[
        {
            "category":"Shopping",
            "subcategory":"Used Merchandise",
            "type":"Retail Goods"
        }
    ],
    "sg:phone":"+1 214 941 0921",
    "sg:postcode":"75216",
    "sg:province":"TX",
    "sg:tags":[
        "furniture"
    ],
    "wof:name":"Smith's Used Furniture & Appls",
    "wof:placetype":"venue"
},
  "geometry": {"coordinates":[-96.811373,32.735703],"type":"Point"}
}