{
  "type": "Feature",
  "properties": {
    "iso:country":"US",
    "sg:address":"2014 Commerce St",
    "sg:city":"Dallas",
    "sg:classifiers":[
        {
            "category":"Food & Beverages",
            "subcategory":"Groceries & Convenience Stores",
            "type":"Retail Goods"
        }
    ],
    "sg:phone":"+1 214 939 2699",
    "sg:postcode":"75201",
    "sg:province":"TX",
    "wof:name":"Pick N Go",
    "wof:placetype":"venue"
},
  "geometry": {"coordinates":[-96.792429,32.781211],"type":"Point"}
}