{
  "type": "Feature",
  "properties": {
    "iso:country":"US",
    "sg:address":"300 N Clark Dr",
    "sg:city":"El Paso",
    "sg:classifiers":[
        {
            "category":"Freight",
            "type":"Transportation"
        }
    ],
    "sg:phone":"+1 915 598 1101",
    "sg:postcode":"79905",
    "sg:province":"TX",
    "sg:tags":[
        "terminal",
        "trucking"
    ],
    "wof:name":"Wskt",
    "wof:placetype":"venue"
},
  "geometry": {"coordinates":[-106.4143,31.772098],"type":"Point"}
}