{
  "type": "Feature",
  "properties": {
    "iso:country":"US",
    "sg:address":"1001 Great Oaks Dr",
    "sg:city":"Round Rock",
    "sg:classifiers":[
        {
            "category":"Government",
            "subcategory":"Fire Station",
            "type":"Public Place"
        }
    ],
    "sg:phone":"+1 512 255 0100",
    "sg:postcode":"78681",
    "sg:province":"TX",
    "sg:tags":[
        "department"
    ],
    "sg:website":"www.sambassfd.com",
    "wof:name":"Sam Bass Volunteer Fire Dept",
    "wof:placetype":"venue"
},
  "geometry": {"coordinates":[-97.733693,30.517113],"type":"Point"}
}