{
  "type": "Feature",
  "properties": {
    "iso:country":"US",
    "sg:address":"15433 FM 2661",
    "sg:city":"Flint",
    "sg:classifiers":[
        {
            "category":"Personal",
            "subcategory":"Barber",
            "type":"Services"
        }
    ],
    "sg:phone":"+1 903 566 2577",
    "sg:postcode":"75762",
    "sg:province":"TX",
    "sg:tags":[
        "shop"
    ],
    "wof:name":"Jims Barber Shops",
    "wof:placetype":"venue"
},
  "geometry": {"coordinates":[-95.45147900000001,32.257074],"type":"Point"}
}