{
  "type": "Feature",
  "properties": {
    "iso:country":"US",
    "sg:address":"2501 Riverside Dr",
    "sg:city":"Houston",
    "sg:classifiers":[
        {
            "category":"Social Services",
            "subcategory":"Child Care",
            "type":"Services"
        }
    ],
    "sg:phone":"+1 713 847 8111",
    "sg:postcode":"77004",
    "sg:province":"TX",
    "sg:tags":[
        "day"
    ],
    "wof:name":"Learn A Lot Cognitive & Social",
    "wof:placetype":"venue"
},
  "geometry": {"coordinates":[-95.37777800000001,29.717256],"type":"Point"}
}