{
  "type": "Feature",
  "properties": {
    "iso:country":"US",
    "sg:address":"7960 Doniphan Dr",
    "sg:city":"Vinton",
    "sg:classifiers":[
        {
            "category":"Autos & Motor Vehicles",
            "subcategory":"Automobile Sales",
            "type":"Retail Goods"
        }
    ],
    "sg:phone":"+1 915 886 2776",
    "sg:postcode":"79821",
    "sg:province":"TX",
    "sg:tags":[
        "dealers-used",
        "car",
        "used",
        "cars-wholesale"
    ],
    "wof:name":"Ortega Motors",
    "wof:placetype":"venue"
},
  "geometry": {"coordinates":[-106.603478,31.955841],"type":"Point"}
}