{
  "type": "Feature",
  "properties": {
    "iso:country":"US",
    "sg:address":"3026 Crestbrook Bend Ln",
    "sg:city":"Katy",
    "sg:classifiers":[
        {
            "category":"Retail",
            "subcategory":"Auto Repair",
            "type":"Services"
        }
    ],
    "sg:phone":"+1 281 599 7414",
    "sg:postcode":"77449",
    "sg:province":"TX",
    "sg:tags":[
        "general"
    ],
    "wof:name":"Manuel Calderon Auto Rep",
    "wof:placetype":"venue"
},
  "geometry": {"coordinates":[-95.74586600000001,29.821251],"type":"Point"}
}