{
  "type": "Feature",
  "properties": {
    "iso:country":"US",
    "sg:address":"4090 Sauls Rd",
    "sg:city":"Aubrey",
    "sg:classifiers":[
        {
            "category":"Building & Trades",
            "subcategory":"Construction",
            "type":"Services"
        }
    ],
    "sg:phone":"+1 940 387 3633",
    "sg:postcode":"76227",
    "sg:province":"TX",
    "sg:tags":[
        "general",
        "contractor"
    ],
    "wof:name":"Wildwoods Custom Furniture",
    "wof:placetype":"venue"
},
  "geometry": {"coordinates":[-97.068313,33.290812],"type":"Point"}
}