{
  "type": "Feature",
  "properties": {
    "iso:country":"US",
    "sg:address":"203 Pine Manor Dr",
    "sg:city":"Conroe",
    "sg:classifiers":[
        {
            "category":"Manufacturing",
            "subcategory":"Printing",
            "type":"Manufacturing & Wholesale Goods"
        }
    ],
    "sg:phone":"+1 281 681 2682",
    "sg:postcode":"77385",
    "sg:province":"TX",
    "sg:tags":[
        "commercial"
    ],
    "wof:name":"A B Dick Company",
    "wof:placetype":"venue"
},
  "geometry": {"coordinates":[-95.444093,30.168287],"type":"Point"}
}