{
  "type": "Feature",
  "properties": {
    "iso:country":"US",
    "sg:address":"5001 Montana Ave",
    "sg:city":"El Paso",
    "sg:classifiers":[
        {
            "category":"Wholesale",
            "subcategory":"Office Equipment",
            "type":"Manufacturing & Wholesale Goods"
        }
    ],
    "sg:phone":"+1 915 562 6464",
    "sg:postcode":"79903",
    "sg:province":"TX",
    "sg:tags":[
        "machine",
        "mailing"
    ],
    "wof:name":"Mailing & Shipping Systems Inc",
    "wof:placetype":"venue"
},
  "geometry": {"coordinates":[-106.428301,31.783721],"type":"Point"}
}