{
  "type": "Feature",
  "properties": {
    "iso:country":"US",
    "sg:address":"4920 Cash Rd",
    "sg:city":"Dallas",
    "sg:classifiers":[
        {
            "category":"Wholesale",
            "subcategory":"Construction Materials",
            "type":"Manufacturing & Wholesale Goods"
        },
        {
            "category":"Home & Garden",
            "subcategory":"Building Materials",
            "type":"Retail Goods"
        }
    ],
    "sg:phone":"+1 214 688 7000",
    "sg:postcode":"75247",
    "sg:province":"TX",
    "sg:tags":[
        "insulation",
        "heat",
        "industrial",
        "supply"
    ],
    "sg:website":"www.generalinsulation.com",
    "wof:name":"General Insulation Co Inc",
    "wof:placetype":"venue"
},
  "geometry": {"coordinates":[-96.88224200000001,32.805552],"type":"Point"}
}