{
  "type": "Feature",
  "properties": {
    "iso:country":"US",
    "sg:address":"5705 Benefield Ave",
    "sg:city":"Odessa",
    "sg:classifiers":[
        {
            "category":"Retail",
            "subcategory":"Auto Repair",
            "type":"Services"
        }
    ],
    "sg:phone":"+1 432 550 5338",
    "sg:postcode":"79762",
    "sg:province":"TX",
    "sg:tags":[
        "body",
        "painting",
        "repairing",
        "automobile"
    ],
    "wof:name":"Leroys Body Shop",
    "wof:placetype":"venue"
},
  "geometry": {"coordinates":[-102.38068800000001,31.899785],"type":"Point"}
}