{
  "type": "Feature",
  "properties": {
    "iso:country":"US",
    "sg:address":"10257 Westward Dr",
    "sg:city":"Fort Worth",
    "sg:classifiers":[
        {
            "category":"Building & Trades",
            "subcategory":"Landscaping Services",
            "type":"Services"
        }
    ],
    "sg:phone":"+1 817 246 8009",
    "sg:postcode":"76108",
    "sg:province":"TX",
    "wof:name":"Zs Lawn Care",
    "wof:placetype":"venue"
},
  "geometry": {"coordinates":[-97.503758,32.75264],"type":"Point"}
}