{
  "type": "Feature",
  "properties": {
    "iso:country":"US",
    "sg:address":"513 S Kealy St",
    "sg:city":"Lewisville",
    "sg:classifiers":[
        {
            "category":"Building & Trades",
            "subcategory":"Landscaping Services",
            "type":"Services"
        }
    ],
    "sg:phone":"+1 972 420 7624",
    "sg:postcode":"75057",
    "sg:province":"TX",
    "sg:tags":[
        "landscape"
    ],
    "wof:name":"Miramontes Landscape",
    "wof:placetype":"venue"
},
  "geometry": {"coordinates":[-96.99290499999999,33.042135],"type":"Point"}
}