{
  "type": "Feature",
  "properties": {
    "iso:country":"US",
    "sg:address":"3101 Parkside Dr",
    "sg:city":"Plano",
    "sg:classifiers":[
        {
            "category":"Restaurant",
            "type":"Food & Drink"
        }
    ],
    "sg:phone":"+1 972 867 7609",
    "sg:postcode":"75075",
    "sg:province":"TX",
    "sg:tags":[
        "eating"
    ],
    "wof:name":"Step In Drive In",
    "wof:placetype":"venue"
},
  "geometry": {"coordinates":[-96.73868299999999,33.040492],"type":"Point"}
}