{
  "type": "Feature",
  "properties": {
    "iso:country":"US",
    "sg:address":"5864 Westheimer Rd",
    "sg:city":"Houston",
    "sg:classifiers":[
        {
            "category":"Personal",
            "subcategory":"Beauty Salon",
            "type":"Services"
        }
    ],
    "sg:phone":"+1 713 278 7090",
    "sg:postcode":"77057",
    "sg:province":"TX",
    "sg:tags":[
        "shop"
    ],
    "wof:name":"Paris Coiffure",
    "wof:placetype":"venue"
},
  "geometry": {"coordinates":[-95.483226,29.73782],"type":"Point"}
}