{
  "type": "Feature",
  "properties": {
    "iso:country":"US",
    "sg:address":"1741 N Galloway Ave",
    "sg:city":"Mesquite",
    "sg:classifiers":[
        {
            "category":"Food & Beverages",
            "subcategory":"Groceries & Convenience Stores",
            "type":"Retail Goods"
        }
    ],
    "sg:phone":"+1 972 329 6599",
    "sg:postcode":"75149",
    "sg:province":"TX",
    "wof:name":"Taj Mahal Asian Groceries",
    "wof:placetype":"venue"
},
  "geometry": {"coordinates":[-96.605904,32.786499],"type":"Point"}
}