{
  "type": "Feature",
  "properties": {
    "iso:country":"US",
    "sg:address":"2537 Mayhugh Ct",
    "sg:city":"Arlington",
    "sg:classifiers":[
        {
            "category":"Retail",
            "subcategory":"Car Wash",
            "type":"Services"
        }
    ],
    "sg:phone":"+1 817 461 2772",
    "sg:postcode":"76015",
    "sg:province":"TX",
    "sg:tags":[
        "truck",
        "cleaning"
    ],
    "sg:website":"www.fleetwash.com",
    "wof:name":"Fleetwash",
    "wof:placetype":"venue"
},
  "geometry": {"coordinates":[-97.125917,32.703327],"type":"Point"}
}