{
  "type": "Feature",
  "properties": {
    "iso:country":"US",
    "sg:address":"2309 Zapata St",
    "sg:city":"Freeport",
    "sg:classifiers":[
        {
            "category":"Building & Trades",
            "subcategory":"Equipment Rental",
            "type":"Services"
        },
        {
            "category":"Building & Trades",
            "subcategory":"Construction",
            "type":"Services"
        }
    ],
    "sg:phone":"+1 979 233 2841",
    "sg:postcode":"77541",
    "sg:province":"TX",
    "sg:tags":[
        "excavation",
        "contractors'",
        "contractor"
    ],
    "wof:name":"Brazos M & E Shop",
    "wof:placetype":"venue"
},
  "geometry": {"coordinates":[-95.371236,28.984647],"type":"Point"}
}