{
  "type": "Feature",
  "properties": {
    "iso:country":"US",
    "sg:address":"7515 Burleson Rd",
    "sg:city":"Austin",
    "sg:classifiers":[
        {
            "category":"Personal",
            "subcategory":"Beauty Salon",
            "type":"Services"
        }
    ],
    "sg:phone":"+1 512 385 2102",
    "sg:postcode":"78744",
    "sg:province":"TX",
    "sg:tags":[
        "shop"
    ],
    "wof:name":"Sis Style Salon",
    "wof:placetype":"venue"
},
  "geometry": {"coordinates":[-97.698364,30.192088],"type":"Point"}
}