{
  "type": "Feature",
  "properties": {
    "iso:country":"US",
    "sg:address":"1510 Greenlawn Blvd",
    "sg:city":"Round Rock",
    "sg:classifiers":[
        {
            "category":"Social Services",
            "subcategory":"Child Care",
            "type":"Services"
        }
    ],
    "sg:phone":"+1 512 388 1281",
    "sg:postcode":"78664",
    "sg:province":"TX",
    "wof:name":"LA Petite Academy",
    "wof:placetype":"venue"
},
  "geometry": {"coordinates":[-97.665307,30.496288],"type":"Point"}
}