{
  "type": "Feature",
  "properties": {
    "iso:country":"US",
    "sg:address":"7212 Mcneil Dr Ste 204",
    "sg:city":"Austin",
    "sg:classifiers":[
        {
            "category":"Health Services",
            "subcategory":"Doctor",
            "type":"Services"
        }
    ],
    "sg:phone":"+1 515 249 7598",
    "sg:postcode":"78729",
    "sg:province":"TX",
    "sg:tags":[
        "physician",
        "family",
        "practice",
        "surgeons",
        "medicine",
        "surgeon",
        "surgery-general"
    ],
    "wof:name":"1-800-Doctors",
    "wof:placetype":"venue"
},
  "geometry": {"coordinates":[-97.76541899999999,30.43574],"type":"Point"}
}