{
  "type": "Feature",
  "properties": {
    "iso:country":"US",
    "sg:address":"2212 Ranch Rd 12",
    "sg:city":"San Marcos",
    "sg:classifiers":[
        {
            "category":"Home & Garden",
            "subcategory":"Garden Supply",
            "type":"Retail Goods"
        }
    ],
    "sg:phone":"+1 512 754 0060",
    "sg:postcode":"78666",
    "sg:province":"TX",
    "wof:name":"Garden Ville Of San Marcos",
    "wof:placetype":"venue"
},
  "geometry": {"coordinates":[-97.988986,29.902459],"type":"Point"}
}