{
  "type": "Feature",
  "properties": {
    "iso:country":"US",
    "sg:address":"2104 Galloway Ave",
    "sg:city":"Mesquite",
    "sg:classifiers":[
        {
            "category":"Fast Food",
            "type":"Food & Drink"
        }
    ],
    "sg:phone":"+1 972 288 9653",
    "sg:postcode":"75150",
    "sg:province":"TX",
    "sg:website":"www.carlsjr.com/locations?restau...",
    "wof:name":"Carl's Jr",
    "wof:placetype":"venue"
},
  "geometry": {"coordinates":[-96.612037,32.793668],"type":"Point"}
}