{
  "type": "Feature",
  "properties": {
    "iso:country":"US",
    "sg:address":"515 N Ashland St",
    "sg:city":"Vidor",
    "sg:classifiers":[
        {
            "category":"Professional",
            "subcategory":"Business Services",
            "type":"Services"
        }
    ],
    "sg:phone":"+1 409 769 1158",
    "sg:postcode":"77662",
    "sg:province":"TX",
    "wof:name":"Southwinds Enterprises",
    "wof:placetype":"venue"
},
  "geometry": {"coordinates":[-93.968948,30.129899],"type":"Point"}
}