{
  "type": "Feature",
  "properties": {
    "iso:country":"US",
    "sg:address":"5560 Aspen St",
    "sg:city":"Bellaire",
    "sg:classifiers":[
        {
            "category":"Professional",
            "subcategory":"Art Services",
            "type":"Services"
        }
    ],
    "sg:phone":"+1 713 591 2284",
    "sg:postcode":"77401",
    "sg:province":"TX",
    "sg:tags":[
        "designer",
        "display",
        "producer"
    ],
    "wof:name":"Spice Paper Designs",
    "wof:placetype":"venue"
},
  "geometry": {"coordinates":[-95.479755,29.697257],"type":"Point"}
}