{
  "type": "Feature",
  "properties": {
    "iso:country":"US",
    "sg:address":"2321 Naomi St",
    "sg:city":"Houston",
    "sg:classifiers":[
        {
            "category":"Building & Trades",
            "subcategory":"Construction",
            "type":"Services"
        }
    ],
    "sg:phone":"+1 713 383 7237",
    "sg:postcode":"77054",
    "sg:province":"TX",
    "sg:tags":[
        "floor",
        "laying",
        "contractor"
    ],
    "wof:name":"Deluxe Carpet",
    "wof:placetype":"venue"
},
  "geometry": {"coordinates":[-95.393806,29.68244],"type":"Point"}
}