{
  "type": "Feature",
  "properties": {
    "iso:country":"US",
    "sg:address":"2301 Minimax Dr",
    "sg:city":"Houston",
    "sg:classifiers":[
        {
            "category":"Manufacturing",
            "subcategory":"Rubber & Plastics",
            "type":"Manufacturing & Wholesale Goods"
        }
    ],
    "sg:phone":"+1 713 864 3412",
    "sg:postcode":"77008",
    "sg:province":"TX",
    "sg:tags":[
        "distributor",
        "toy"
    ],
    "wof:name":"Funtastic",
    "wof:placetype":"venue"
},
  "geometry": {"coordinates":[-95.44266399999999,29.797631],"type":"Point"}
}