{
  "type": "Feature",
  "properties": {
    "iso:country":"US",
    "sg:address":"2030 E Oltorf St",
    "sg:city":"Austin",
    "sg:classifiers":[
        {
            "category":"Banks & Credit Unions",
            "subcategory":"Financial Services",
            "type":"Services"
        }
    ],
    "sg:phone":"+1 512 462 2009",
    "sg:postcode":"78741",
    "sg:province":"TX",
    "sg:tags":[
        "cashing",
        "check"
    ],
    "wof:name":"Mi Pueblito Market",
    "wof:placetype":"venue"
},
  "geometry": {"coordinates":[-97.733467,30.230883],"type":"Point"}
}