{
  "type": "Feature",
  "properties": {
    "iso:country":"US",
    "sg:address":"1048 Granite Ln",
    "sg:city":"De Soto",
    "sg:classifiers":[
        {
            "category":"Professional",
            "type":"Services"
        }
    ],
    "sg:phone":"+1 972 223 5497",
    "sg:postcode":"75115",
    "sg:province":"TX",
    "wof:name":"Clinton C Sterry",
    "wof:placetype":"venue"
},
  "geometry": {"coordinates":[-96.880539,32.588993],"type":"Point"}
}