{
  "type": "Feature",
  "properties": {
    "iso:country":"US",
    "sg:address":"809 N Locust St",
    "sg:city":"Denton",
    "sg:classifiers":[
        {
            "category":"Professional",
            "subcategory":"Management & Consulting",
            "type":"Services"
        }
    ],
    "sg:phone":"+1 940 591 0641",
    "sg:postcode":"76201",
    "sg:province":"TX",
    "sg:tags":[
        "retail",
        "store"
    ],
    "wof:name":"Myrna Brown Interiors",
    "wof:placetype":"venue"
},
  "geometry": {"coordinates":[-97.13238800000001,33.220956],"type":"Point"}
}