{
  "type": "Feature",
  "properties": {
    "iso:country":"US",
    "sg:address":"204 Centennial St",
    "sg:city":"Carmine",
    "sg:classifiers":[
        {
            "category":"Food & Beverages",
            "subcategory":"Groceries & Convenience Stores",
            "type":"Retail Goods"
        }
    ],
    "sg:phone":"+1 979 278 3242",
    "sg:postcode":"78932",
    "sg:province":"TX",
    "sg:tags":[
        "grocer"
    ],
    "wof:name":"Jacob's Store Inc",
    "wof:placetype":"venue"
},
  "geometry": {"coordinates":[-96.68666399999999,30.148483],"type":"Point"}
}