{
  "type": "Feature",
  "properties": {
    "iso:country":"US",
    "sg:address":"3105 Franklin Ave",
    "sg:city":"Waco",
    "sg:classifiers":[
        {
            "category":"Autos & Motor Vehicles",
            "subcategory":"Automobile Sales",
            "type":"Retail Goods"
        }
    ],
    "sg:phone":"+1 254 722 9907",
    "sg:postcode":"76710",
    "sg:province":"TX",
    "sg:tags":[
        "car",
        "dealer"
    ],
    "wof:name":"Powell Auto Sales",
    "wof:placetype":"venue"
},
  "geometry": {"coordinates":[-97.154991,31.534896],"type":"Point"}
}