{
  "type": "Feature",
  "properties": {
    "iso:country":"US",
    "sg:address":"802 S Austin St",
    "sg:city":"Comanche",
    "sg:classifiers":[
        {
            "category":"Farming",
            "subcategory":"Vineyard",
            "type":"Manufacturing & Wholesale Goods"
        }
    ],
    "sg:phone":"+1 325 356 9100",
    "sg:postcode":"76442",
    "sg:province":"TX",
    "sg:tags":[
        "grape"
    ],
    "wof:name":"Rockhouse Vineyards LLC",
    "wof:placetype":"venue"
},
  "geometry": {"coordinates":[-98.603776,31.890312],"type":"Point"}
}