{
  "type": "Feature",
  "properties": {
    "iso:country":"US",
    "sg:address":"1614 S Broadway St Ste 204",
    "sg:city":"Carrollton",
    "sg:classifiers":[
        {
            "category":"Building & Trades",
            "subcategory":"Plumbing",
            "type":"Services"
        }
    ],
    "sg:phone":"+1 972 245 1160",
    "sg:postcode":"75006",
    "sg:province":"TX",
    "wof:name":"All Plumbing",
    "wof:placetype":"venue"
},
  "geometry": {"coordinates":[-96.903397,32.947201],"type":"Point"}
}