{
  "type": "Feature",
  "properties": {
    "iso:country":"US",
    "sg:address":"5712 Redwood Dr S",
    "sg:city":"Fort Worth",
    "sg:classifiers":[
        {
            "category":"Professional",
            "type":"Services"
        }
    ],
    "sg:phone":"+1 817 483 7630",
    "sg:postcode":"76119",
    "sg:province":"TX",
    "wof:name":"Aguila Graciano Del",
    "wof:placetype":"venue"
},
  "geometry": {"coordinates":[-97.248711,32.671846],"type":"Point"}
}