{
  "type": "Feature",
  "properties": {
    "iso:country":"US",
    "sg:address":"1315 N Olive St",
    "sg:city":"San Antonio",
    "sg:classifiers":[
        {
            "category":"Manufacturing",
            "subcategory":"Retail Goods",
            "type":"Manufacturing & Wholesale Goods"
        }
    ],
    "sg:phone":"+1 210 662 0427",
    "sg:postcode":"78202",
    "sg:province":"TX",
    "sg:tags":[
        "assembly",
        "fabricating"
    ],
    "wof:name":"U S Products",
    "wof:placetype":"venue"
},
  "geometry": {"coordinates":[-98.471853,29.436624],"type":"Point"}
}