{
  "type": "Feature",
  "properties": {
    "iso:country":"US",
    "sg:address":"3508 E T C Jester Blvd",
    "sg:city":"Houston",
    "sg:classifiers":[
        {
            "category":"Shopping",
            "subcategory":"Computers & Home Electronics",
            "type":"Retail Goods"
        }
    ],
    "sg:phone":"+1 713 956 8887",
    "sg:postcode":"77018",
    "sg:province":"TX",
    "wof:name":"Hosier Services",
    "wof:placetype":"venue"
},
  "geometry": {"coordinates":[-95.444379,29.819751],"type":"Point"}
}