{
  "type": "Feature",
  "properties": {
    "iso:country":"US",
    "sg:address":"6750 Indian Lake Dr",
    "sg:city":"Missouri City",
    "sg:classifiers":[
        {
            "category":"Personal",
            "subcategory":"Beauty Salon",
            "type":"Services"
        }
    ],
    "sg:phone":"+1 281 440 9666",
    "sg:postcode":"77489",
    "sg:province":"TX",
    "sg:tags":[
        "shop"
    ],
    "wof:name":"Essences of Beauty Hair Salon",
    "wof:placetype":"venue"
},
  "geometry": {"coordinates":[-95.48871699999999,29.602234],"type":"Point"}
}