{
  "type": "Feature",
  "properties": {
    "iso:country":"US",
    "sg:address":"3328 Co Rd 245",
    "sg:city":"Brazoria",
    "sg:classifiers":[
        {
            "category":"Professional",
            "type":"Services"
        }
    ],
    "sg:phone":"+1 979 798 5975",
    "sg:postcode":"77422",
    "sg:province":"TX",
    "wof:name":"Preston W Alison",
    "wof:placetype":"venue"
},
  "geometry": {"coordinates":[-95.622342,29.072882],"type":"Point"}
}