{
  "type": "Feature",
  "properties": {
    "iso:country":"US",
    "sg:address":"1336 Glen Cove",
    "sg:city":"Southlake",
    "sg:classifiers":[
        {
            "category":"Building & Trades",
            "subcategory":"Construction",
            "type":"Services"
        }
    ],
    "sg:phone":"+1 817 481 7220",
    "sg:postcode":"76092",
    "sg:province":"TX",
    "sg:tags":[
        "concrete",
        "contractor"
    ],
    "wof:name":"Farrier Concrete Construction",
    "wof:placetype":"venue"
},
  "geometry": {"coordinates":[-97.176023,32.948058],"type":"Point"}
}