{
  "type": "Feature",
  "properties": {
    "iso:country":"US",
    "sg:address":"110 N 14th St",
    "sg:city":"Midlothian",
    "sg:classifiers":[
        {
            "category":"Real Estate",
            "subcategory":"Real Estate Operator",
            "type":"Services"
        }
    ],
    "sg:phone":"+1 972 775 8565",
    "sg:postcode":"76065",
    "sg:province":"TX",
    "sg:tags":[
        "building",
        "apartment"
    ],
    "wof:name":"Eastwood Apartments",
    "wof:placetype":"venue"
},
  "geometry": {"coordinates":[-96.98745700000001,32.483452],"type":"Point"}
}