{
  "type": "Feature",
  "properties": {
    "iso:country":"US",
    "sg:address":"110 W Sandy Lake Rd",
    "sg:city":"Coppell",
    "sg:classifiers":[
        {
            "category":"Retail",
            "subcategory":"Laundry & Dry Cleaning",
            "type":"Services"
        }
    ],
    "sg:phone":"+1 972 471 0245",
    "sg:postcode":"75019",
    "sg:province":"TX",
    "sg:tags":[
        "cleaners"
    ],
    "wof:name":"Comet Cleaners",
    "wof:placetype":"venue"
},
  "geometry": {"coordinates":[-96.9978,32.969588],"type":"Point"}
}