{
  "type": "Feature",
  "properties": {
    "iso:country":"US",
    "sg:address":"1816 7th St",
    "sg:city":"Bay City",
    "sg:classifiers":[
        {
            "category":"Insurance",
            "subcategory":"Hazard Insurance",
            "type":"Services"
        }
    ],
    "sg:phone":"+1 979 245 9633",
    "sg:postcode":"77414",
    "sg:province":"TX",
    "sg:tags":[
        "bond"
    ],
    "wof:name":"AAA Bonding Co",
    "wof:placetype":"venue"
},
  "geometry": {"coordinates":[-95.96775700000001,28.982981],"type":"Point"}
}