{
  "type": "Feature",
  "properties": {
    "iso:country":"US",
    "sg:address":"45 Misty Pond Dr",
    "sg:city":"Frisco",
    "sg:classifiers":[
        {
            "category":"Freight",
            "type":"Transportation"
        }
    ],
    "sg:phone":"+1 214 618 3535",
    "sg:postcode":"75034",
    "sg:province":"TX",
    "sg:tags":[
        "operator",
        "local",
        "trucking"
    ],
    "wof:name":"National Moving Co",
    "wof:placetype":"venue"
},
  "geometry": {"coordinates":[-96.811463,33.116536],"type":"Point"}
}