{
  "type": "Feature",
  "properties": {
    "iso:country":"US",
    "sg:address":"612 8th Ave",
    "sg:city":"Fort Worth",
    "sg:classifiers":[
        {
            "category":"Professional",
            "subcategory":"Lawyer & Legal Services",
            "type":"Services"
        }
    ],
    "sg:phone":"+1 817 850 4200",
    "sg:postcode":"76104",
    "sg:province":"TX",
    "wof:name":"Wright and Berry LLP",
    "wof:placetype":"venue"
},
  "geometry": {"coordinates":[-97.343744,32.737963],"type":"Point"}
}