{
  "type": "Feature",
  "properties": {
    "iso:country":"US",
    "sg:address":"1601 Broadway St",
    "sg:city":"Houston",
    "sg:classifiers":[
        {
            "category":"Education",
            "subcategory":"School",
            "type":"Public Place"
        }
    ],
    "sg:phone":"+1 713 928 7487",
    "sg:postcode":"77012",
    "sg:province":"TX",
    "sg:tags":[
        "high",
        "middle",
        "elementary"
    ],
    "wof:name":"Houston Independent School District",
    "wof:placetype":"venue"
},
  "geometry": {"coordinates":[-95.277872,29.710641],"type":"Point"}
}