{
  "type": "Feature",
  "properties": {
    "iso:country":"US",
    "sg:address":"13444 West Ave",
    "sg:city":"San Antonio",
    "sg:classifiers":[
        {
            "category":"Restaurant",
            "type":"Food & Drink"
        }
    ],
    "sg:menulink":"http://www.allmenus.com/tx/san-antonio/14602-magnolia-pancake-haus/menu/",
    "sg:phone":"+1 210 496 0828",
    "sg:postcode":"78216",
    "sg:province":"TX",
    "sg:tags":[
        "american"
    ],
    "wof:name":"Magnolia Pancake Haus",
    "wof:placetype":"venue"
},
  "geometry": {"coordinates":[-98.489862,29.565158],"type":"Point"}
}