{
  "type": "Feature",
  "properties": {
    "iso:country":"US",
    "sg:address":"4030 Neuches Ave",
    "sg:city":"Amarillo",
    "sg:classifiers":[
        {
            "category":"Building & Trades",
            "subcategory":"Landscaping Services",
            "type":"Services"
        }
    ],
    "sg:phone":"+1 806 372 6829",
    "sg:postcode":"79104",
    "sg:province":"TX",
    "wof:name":"Perez Lawn Service",
    "wof:placetype":"venue"
},
  "geometry": {"coordinates":[-101.78743799999999,35.212445],"type":"Point"}
}