{
  "type": "Feature",
  "properties": {
    "iso:country":"US",
    "sg:address":"1430 Centeno Ln",
    "sg:city":"Laredo",
    "sg:classifiers":[
        {
            "category":"Retail",
            "subcategory":"Auto Repair",
            "type":"Services"
        }
    ],
    "sg:phone":"+1 956 717 1050",
    "sg:postcode":"78046",
    "sg:province":"TX",
    "sg:tags":[
        "repairing",
        "automobile"
    ],
    "wof:name":"J & M Auto Tech",
    "wof:placetype":"venue"
},
  "geometry": {"coordinates":[-99.47796,27.365369],"type":"Point"}
}