{
  "type": "Feature",
  "properties": {
    "iso:country":"US",
    "sg:address":"1144 N Plano Rd",
    "sg:city":"Richardson",
    "sg:classifiers":[
        {
            "category":"Restaurant",
            "type":"Food & Drink"
        }
    ],
    "sg:phone":"+1 972 235 0594",
    "sg:postcode":"75081",
    "sg:province":"TX",
    "wof:name":"Gourmet Room",
    "wof:placetype":"venue"
},
  "geometry": {"coordinates":[-96.699868,32.96196],"type":"Point"}
}