{
  "type": "Feature",
  "properties": {
    "iso:country":"US",
    "sg:address":"8404 Sprague Rd",
    "sg:city":"Odessa",
    "sg:classifiers":[
        {
            "category":"Mining & Drilling",
            "type":"Manufacturing & Wholesale Goods"
        }
    ],
    "sg:phone":"+1 432 550 5342",
    "sg:postcode":"79764",
    "sg:province":"TX",
    "sg:tags":[
        "field"
    ],
    "wof:name":"Unical",
    "wof:placetype":"venue"
},
  "geometry": {"coordinates":[-102.433211,31.922315],"type":"Point"}
}