{
  "type": "Feature",
  "properties": {
    "iso:country":"US",
    "sg:address":"4931 Alice Ln",
    "sg:city":"Malakoff",
    "sg:classifiers":[
        {
            "category":"Building & Trades",
            "subcategory":"Construction",
            "type":"Services"
        }
    ],
    "sg:phone":"+1 903 489 3918",
    "sg:postcode":"75148",
    "sg:province":"TX",
    "sg:tags":[
        "house"
    ],
    "wof:name":"Eldon King Builder Inc",
    "wof:placetype":"venue"
},
  "geometry": {"coordinates":[-96.043904,32.215424],"type":"Point"}
}