{
  "type": "Feature",
  "properties": {
    "iso:country":"US",
    "sg:address":"1456 S Belt Line Rd",
    "sg:city":"Dallas",
    "sg:classifiers":[
        {
            "category":"Restaurant",
            "type":"Food & Drink"
        }
    ],
    "sg:phone":"+1 972 414 0168",
    "sg:postcode":"75253",
    "sg:province":"TX",
    "sg:tags":[
        "eating"
    ],
    "wof:name":"Bennys",
    "wof:placetype":"venue"
},
  "geometry": {"coordinates":[-96.59532400000001,32.682083],"type":"Point"}
}