{
  "type": "Feature",
  "properties": {
    "iso:country":"US",
    "sg:address":"426 Rolling Hills Trl",
    "sg:city":"Arlington",
    "sg:classifiers":[
        {
            "category":"Professional",
            "subcategory":"Management & Consulting",
            "type":"Services"
        }
    ],
    "sg:phone":"+1 817 274 1666",
    "sg:postcode":"76011",
    "sg:province":"TX",
    "wof:name":"Jaacs Inc",
    "wof:placetype":"venue"
},
  "geometry": {"coordinates":[-97.113736,32.773248],"type":"Point"}
}