{
  "type": "Feature",
  "properties": {
    "iso:country":"US",
    "sg:address":"205 Ange St",
    "sg:city":"El Paso",
    "sg:classifiers":[
        {
            "category":"Personal",
            "type":"Services"
        }
    ],
    "sg:phone":"+1 915 534 3959",
    "sg:postcode":"79901",
    "sg:province":"TX",
    "sg:tags":[
        "information",
        "document"
    ],
    "wof:name":"Mobile Shredders",
    "wof:placetype":"venue"
},
  "geometry": {"coordinates":[-106.480749,31.76352],"type":"Point"}
}