{
  "type": "Feature",
  "properties": {
    "iso:country":"US",
    "sg:address":"709 N Haskell Ave",
    "sg:city":"Dallas",
    "sg:classifiers":[
        {
            "category":"Shopping",
            "subcategory":"Discount & Variety Stores",
            "type":"Retail Goods"
        }
    ],
    "sg:phone":"+1 214 634 4900",
    "sg:postcode":"75246",
    "sg:province":"TX",
    "sg:tags":[
        "outlet"
    ],
    "wof:name":"MYBAG Handbag Outlet",
    "wof:placetype":"venue"
},
  "geometry": {"coordinates":[-96.776236,32.79311],"type":"Point"}
}