{
  "type": "Feature",
  "properties": {
    "iso:country":"US",
    "sg:address":"9203 State Hwy 6",
    "sg:city":"Houston",
    "sg:classifiers":[
        {
            "category":"Professional",
            "subcategory":"Business Services",
            "type":"Services"
        }
    ],
    "sg:phone":"+1 281 564 9400",
    "sg:postcode":"77083",
    "sg:province":"TX",
    "sg:tags":[
        "box",
        "mail"
    ],
    "wof:name":"Mailbox Depot",
    "wof:placetype":"venue"
},
  "geometry": {"coordinates":[-95.64340199999999,29.679036],"type":"Point"}
}