{
  "type": "Feature",
  "properties": {
    "iso:country":"US",
    "sg:address":"226 W Missouri St",
    "sg:city":"Floydada",
    "sg:classifiers":[
        {
            "category":"Government",
            "subcategory":"Post Office",
            "type":"Public Place"
        }
    ],
    "sg:phone":"+1 806 983 2410",
    "sg:postcode":"79235",
    "sg:province":"TX",
    "wof:name":"US Post Office",
    "wof:placetype":"venue"
},
  "geometry": {"coordinates":[-101.337608,33.985625],"type":"Point"}
}