{
  "type": "Feature",
  "properties": {
    "iso:country":"US",
    "sg:address":"3730 Eagle St",
    "sg:city":"Houston",
    "sg:classifiers":[
        {
            "category":"Professional",
            "type":"Services"
        }
    ],
    "sg:phone":"+1 713 747 4845",
    "sg:postcode":"77004",
    "sg:province":"TX",
    "wof:name":"Audacious Hats",
    "wof:placetype":"venue"
},
  "geometry": {"coordinates":[-95.353567,29.720836],"type":"Point"}
}