{
  "type": "Feature",
  "properties": {
    "iso:country":"US",
    "sg:address":"4633 S 14th St",
    "sg:city":"Abilene",
    "sg:classifiers":[
        {
            "category":"Real Estate",
            "subcategory":"Real Estate Agent",
            "type":"Services"
        }
    ],
    "sg:phone":"+1 325 698 5661",
    "sg:postcode":"79605",
    "sg:province":"TX",
    "wof:name":"Paj Investments",
    "wof:placetype":"venue"
},
  "geometry": {"coordinates":[-99.78383100000001,32.429013],"type":"Point"}
}