{
  "type": "Feature",
  "properties": {
    "iso:country":"US",
    "sg:address":"905 E 41st St",
    "sg:city":"Austin",
    "sg:classifiers":[
        {
            "category":"Retail",
            "subcategory":"Self-service Laundry",
            "type":"Services"
        }
    ],
    "sg:phone":"+1 512 302 9614",
    "sg:postcode":"78751",
    "sg:province":"TX",
    "wof:name":"KWIK-Wash Coin Laundries Inc",
    "wof:placetype":"venue"
},
  "geometry": {"coordinates":[-97.718227,30.297631],"type":"Point"}
}