{
  "type": "Feature",
  "properties": {
    "iso:country":"US",
    "sg:address":"3310 Northpark Dr",
    "sg:city":"Humble",
    "sg:classifiers":[
        {
            "category":"Freight",
            "type":"Transportation"
        }
    ],
    "sg:phone":"+1 713 942 2351",
    "sg:postcode":"77339",
    "sg:province":"TX",
    "sg:tags":[
        "special"
    ],
    "wof:name":"Shurgard Storage North Park",
    "wof:placetype":"venue"
},
  "geometry": {"coordinates":[-95.188599,30.067667],"type":"Point"}
}