{
  "type": "Feature",
  "properties": {
    "iso:country":"US",
    "sg:address":"76 Sugar Creek Pl",
    "sg:city":"Woodway",
    "sg:classifiers":[
        {
            "category":"Banks & Credit Unions",
            "subcategory":"Investment Brokerage",
            "type":"Services"
        }
    ],
    "sg:phone":"+1 254 772 5235",
    "sg:postcode":"76712",
    "sg:province":"TX",
    "sg:tags":[
        "trust"
    ],
    "wof:name":"Cynthia Marable",
    "wof:placetype":"venue"
},
  "geometry": {"coordinates":[-97.21865099999999,31.513835],"type":"Point"}
}