{
  "type": "Feature",
  "properties": {
    "iso:country":"US",
    "sg:address":"2801 E Arkansas Ln",
    "sg:city":"Arlington",
    "sg:classifiers":[
        {
            "category":"Retail",
            "subcategory":"Auto Repair",
            "type":"Services"
        }
    ],
    "sg:phone":"+1 817 649 3206",
    "sg:postcode":"76010",
    "sg:province":"TX",
    "sg:tags":[
        "automobile",
        "lubrication"
    ],
    "wof:name":"Destiny Oil Change & Lube",
    "wof:placetype":"venue"
},
  "geometry": {"coordinates":[-97.06112299999999,32.706049],"type":"Point"}
}