{
  "type": "Feature",
  "properties": {
    "iso:country":"US",
    "sg:address":"17752 Preston Rd",
    "sg:city":"Dallas",
    "sg:classifiers":[
        {
            "category":"Utilities",
            "subcategory":"Water",
            "type":"Services"
        }
    ],
    "sg:phone":"+1 972 380 4900",
    "sg:postcode":"75252",
    "sg:province":"TX",
    "sg:tags":[
        "pump",
        "well",
        "drilling",
        "contractor"
    ],
    "wof:name":"Jw Bosque Energy Inc",
    "wof:placetype":"venue"
},
  "geometry": {"coordinates":[-96.799396,32.994704],"type":"Point"}
}