{
  "type": "Feature",
  "properties": {
    "iso:country":"US",
    "sg:address":"4801 State Hwy 110",
    "sg:city":"Tyler",
    "sg:classifiers":[
        {
            "category":"Insurance",
            "subcategory":"Insurance Agent",
            "type":"Services"
        }
    ],
    "sg:phone":"+1 903 561 4263",
    "sg:postcode":"75704",
    "sg:province":"TX",
    "wof:name":"Ed Nolan Insurance",
    "wof:placetype":"venue"
},
  "geometry": {"coordinates":[-95.36139300000001,32.385159],"type":"Point"}
}