{
  "type": "Feature",
  "properties": {
    "iso:country":"US",
    "sg:address":"13010 N Hwy 183 Ste 218",
    "sg:city":"Austin",
    "sg:classifiers":[
        {
            "category":"Insurance",
            "subcategory":"Insurance Agent",
            "type":"Services"
        },
        {
            "category":"Insurance",
            "subcategory":"Hazard Insurance",
            "type":"Services"
        },
        {
            "category":"Insurance",
            "subcategory":"Title Insurance",
            "type":"Services"
        },
        {
            "category":"Insurance",
            "subcategory":"Life Insurance",
            "type":"Services"
        }
    ],
    "sg:phone":"+1 512 219 7411",
    "sg:postcode":"78750",
    "sg:province":"TX",
    "sg:tags":[
        "business",
        "auto",
        "commercial",
        "homeowner",
        "motorcycle",
        "renter"
    ],
    "sg:website":"www.allstateagencies.com/BlakeSi...",
    "wof:name":"Allstate Insurance - Blake Simpson Agency",
    "wof:placetype":"venue"
},
  "geometry": {"coordinates":[-97.777615,30.437531],"type":"Point"}
}