{
  "type": "Feature",
  "properties": {
    "iso:country":"US",
    "sg:address":"12319 Perthshire Rd",
    "sg:city":"Houston",
    "sg:classifiers":[
        {
            "category":"Home & Garden",
            "subcategory":"Home Furnishings",
            "type":"Retail Goods"
        }
    ],
    "sg:phone":"+1 713 468 6969",
    "sg:postcode":"77024",
    "sg:province":"TX",
    "sg:tags":[
        "bedding"
    ],
    "wof:name":"Fashions By Fran",
    "wof:placetype":"venue"
},
  "geometry": {"coordinates":[-95.544944,29.774347],"type":"Point"}
}