{
  "type": "Feature",
  "properties": {
    "iso:country":"US",
    "sg:address":"206 W Pleasant St",
    "sg:city":"Mt Pleasant",
    "sg:classifiers":[
        {
            "category":"Government",
            "subcategory":"Office",
            "type":"Public Place"
        }
    ],
    "sg:phone":"+1 903 572 1966",
    "sg:postcode":"75455",
    "sg:province":"TX",
    "sg:tags":[
        "state",
        "program"
    ],
    "wof:name":"Animal Health Commission",
    "wof:placetype":"venue"
},
  "geometry": {"coordinates":[-94.972351,33.143735],"type":"Point"}
}