{
  "type": "Feature",
  "properties": {
    "iso:country":"US",
    "sg:address":"4014 Walnut Pond Dr",
    "sg:city":"Houston",
    "sg:classifiers":[
        {
            "category":"Manufacturing",
            "subcategory":"Chemicals & Compounds",
            "type":"Manufacturing & Wholesale Goods"
        }
    ],
    "sg:phone":"+1 281 282 0022",
    "sg:postcode":"77059",
    "sg:province":"TX",
    "sg:tags":[
        "organic",
        "mfg",
        "surface",
        "plastic",
        "p",
        "agent",
        "active",
        "chem"
    ],
    "wof:name":"Croda Universal Inc",
    "wof:placetype":"venue"
},
  "geometry": {"coordinates":[-95.10507200000001,29.604354],"type":"Point"}
}