{
  "type": "Feature",
  "properties": {
    "iso:country":"US",
    "sg:address":"5222 Thunder Creek Rd",
    "sg:city":"Austin",
    "sg:classifiers":[
        {
            "category":"Professional",
            "subcategory":"Accounting & Tax Preparation",
            "type":"Services"
        }
    ],
    "sg:phone":"+1 512 346 6595",
    "sg:postcode":"78759",
    "sg:province":"TX",
    "sg:tags":[
        "return",
        "filing"
    ],
    "wof:name":"Austin Business Svc",
    "wof:placetype":"venue"
},
  "geometry": {"coordinates":[-97.745904,30.416882],"type":"Point"}
}