{
  "type": "Feature",
  "properties": {
    "iso:country":"US",
    "sg:address":"4213 S Co Rd 1300",
    "sg:city":"Odessa",
    "sg:classifiers":[
        {
            "category":"Freight",
            "type":"Transportation"
        }
    ],
    "sg:phone":"+1 432 563 8130",
    "sg:postcode":"79765",
    "sg:province":"TX",
    "sg:tags":[
        "trucking"
    ],
    "wof:name":"Accel Trucking",
    "wof:placetype":"venue"
},
  "geometry": {"coordinates":[-102.247649,31.900844],"type":"Point"}
}