{
  "type": "Feature",
  "properties": {
    "iso:country":"US",
    "sg:address":"2006 Greenfield Ln",
    "sg:city":"Allen",
    "sg:classifiers":[
        {
            "category":"Freight",
            "type":"Transportation"
        }
    ],
    "sg:phone":"+1 972 396 0413",
    "sg:postcode":"75013",
    "sg:province":"TX",
    "sg:tags":[
        "courier"
    ],
    "wof:name":"Siwel Courier Service",
    "wof:placetype":"venue"
},
  "geometry": {"coordinates":[-96.73023499999999,33.097826],"type":"Point"}
}