{
  "type": "Feature",
  "properties": {
    "iso:country":"US",
    "sg:address":"5300 San Dario Ave 440D",
    "sg:city":"Laredo",
    "sg:classifiers":[
        {
            "category":"Banks & Credit Unions",
            "subcategory":"Bank",
            "type":"Services"
        }
    ],
    "sg:phone":"+1 956 728 0063",
    "sg:postcode":"78041",
    "sg:province":"TX",
    "sg:tags":[
        "saving",
        "commercial"
    ],
    "sg:website":"http://www.ibc.com",
    "wof:name":"International Bank Commerce",
    "wof:placetype":"venue"
},
  "geometry": {"coordinates":[-99.502487,27.53193],"type":"Point"}
}