{
  "type": "Feature",
  "properties": {
    "iso:country":"US",
    "sg:address":"8805 N I H 35",
    "sg:city":"Austin",
    "sg:classifiers":[
        {
            "category":"Retail",
            "subcategory":"Auto Rental",
            "type":"Services"
        }
    ],
    "sg:phone":"+1 512 836 2225",
    "sg:postcode":"78753",
    "sg:province":"TX",
    "sg:tags":[
        "car"
    ],
    "sg:website":"www.enterprise.com",
    "wof:name":"Enterprise Rent-A-Car",
    "wof:placetype":"venue"
},
  "geometry": {"coordinates":[-97.692353,30.35058],"type":"Point"}
}