{
  "type": "Feature",
  "properties": {
    "iso:country":"US",
    "sg:address":"9122 Evening Primrose Path",
    "sg:city":"Austin",
    "sg:classifiers":[
        {
            "category":"Health Services",
            "subcategory":"Doctor",
            "type":"Services"
        }
    ],
    "sg:phone":"+1 512 401 8205",
    "sg:postcode":"78750",
    "sg:province":"TX",
    "sg:tags":[
        "medical"
    ],
    "wof:name":"Satyanarayana B RAO",
    "wof:placetype":"venue"
},
  "geometry": {"coordinates":[-97.794518,30.435711],"type":"Point"}
}