{
  "type": "Feature",
  "properties": {
    "iso:country":"US",
    "sg:address":"6016 Jupiter",
    "sg:city":"Temple",
    "sg:classifiers":[
        {
            "category":"Retail",
            "subcategory":"Repair Shop",
            "type":"Services"
        }
    ],
    "sg:phone":"+1 254 939 0944",
    "sg:postcode":"76502",
    "sg:province":"TX",
    "wof:name":"D & L Woodworks",
    "wof:placetype":"venue"
},
  "geometry": {"coordinates":[-97.41138100000001,31.102002],"type":"Point"}
}