{
  "type": "Feature",
  "properties": {
    "iso:country":"US",
    "sg:address":"810 Coe Rd",
    "sg:city":"Pinehurst",
    "sg:classifiers":[
        {
            "category":"Building & Trades",
            "subcategory":"Cleaning & Sanitation",
            "type":"Services"
        }
    ],
    "sg:phone":"+1 281 252 9992",
    "sg:postcode":"77362",
    "sg:province":"TX",
    "sg:tags":[
        "maintenance"
    ],
    "wof:name":"Lynnes Housekeeping Sevices",
    "wof:placetype":"venue"
},
  "geometry": {"coordinates":[-95.68052400000001,30.155554],"type":"Point"}
}