{
  "type": "Feature",
  "properties": {
    "iso:country":"US",
    "sg:address":"931 SW Military Dr",
    "sg:city":"San Antonio",
    "sg:classifiers":[
        {
            "category":"Shopping",
            "type":"Retail Goods"
        }
    ],
    "sg:phone":"+1 210 927 4175",
    "sg:postcode":"78221",
    "sg:province":"TX",
    "sg:tags":[
        "electronic",
        "cellular",
        "merchandise",
        "telephone"
    ],
    "wof:name":"One Call Communications",
    "wof:placetype":"venue"
},
  "geometry": {"coordinates":[-98.50695399999999,29.356757],"type":"Point"}
}