{
  "type": "Feature",
  "properties": {
    "iso:country":"US",
    "sg:address":"7193 Talley Rd",
    "sg:city":"San Antonio",
    "sg:classifiers":[
        {
            "category":"Home & Garden",
            "subcategory":"Building Materials",
            "type":"Retail Goods"
        }
    ],
    "sg:phone":"+1 210 573 8180",
    "sg:postcode":"78253",
    "sg:province":"TX",
    "wof:name":"Pro Glass",
    "wof:placetype":"venue"
},
  "geometry": {"coordinates":[-98.780249,29.504786],"type":"Point"}
}