{
  "type": "Feature",
  "properties": {
    "iso:country":"US",
    "sg:address":"335 Vincent St",
    "sg:city":"San Antonio",
    "sg:classifiers":[
        {
            "category":"Shopping",
            "subcategory":"Jewelry",
            "type":"Retail Goods"
        }
    ],
    "sg:phone":"+1 210 927 2665",
    "sg:postcode":"78211",
    "sg:province":"TX",
    "wof:name":"Jewelry Lady & More Malac",
    "wof:placetype":"venue"
},
  "geometry": {"coordinates":[-98.56043,29.32688],"type":"Point"}
}