{
  "type": "Feature",
  "properties": {
    "iso:country":"US",
    "sg:address":"515 E Goliad Ave",
    "sg:city":"Crockett",
    "sg:classifiers":[
        {
            "category":"Food & Beverages",
            "subcategory":"Bakery",
            "type":"Retail Goods"
        }
    ],
    "sg:phone":"+1 936 545 2874",
    "sg:postcode":"75835",
    "sg:province":"TX",
    "wof:name":"Beckys Bakery",
    "wof:placetype":"venue"
},
  "geometry": {"coordinates":[-95.456925,31.317612],"type":"Point"}
}