{
  "type": "Feature",
  "properties": {
    "iso:country":"US",
    "sg:address":"3004 Greenridge Dr",
    "sg:city":"Houston",
    "sg:classifiers":[
        {
            "category":"Retail",
            "subcategory":"Laundry & Dry Cleaning",
            "type":"Services"
        }
    ],
    "sg:phone":"+1 713 780 7240",
    "sg:postcode":"77057",
    "sg:province":"TX",
    "wof:name":"Greenridge Cleaners",
    "wof:placetype":"venue"
},
  "geometry": {"coordinates":[-95.48989899999999,29.7346],"type":"Point"}
}