{
  "type": "Feature",
  "properties": {
    "iso:country":"US",
    "sg:address":"8610 Shoal Creek Blvd",
    "sg:city":"Austin",
    "sg:classifiers":[
        {
            "category":"Government",
            "subcategory":"Jail",
            "type":"Public Place"
        }
    ],
    "sg:phone":"+1 512 406 7763",
    "sg:postcode":"78757",
    "sg:province":"TX",
    "sg:tags":[
        "section",
        "warrant"
    ],
    "wof:name":"Warrants Section",
    "wof:placetype":"venue"
},
  "geometry": {"coordinates":[-97.737054,30.372495],"type":"Point"}
}