{
  "type": "Feature",
  "properties": {
    "iso:country":"US",
    "sg:address":"1301 Schumac Ln",
    "sg:city":"Bedford",
    "sg:classifiers":[
        {
            "category":"Professional",
            "subcategory":"Management & Consulting",
            "type":"Services"
        }
    ],
    "sg:phone":"+1 817 283 3677",
    "sg:postcode":"76022",
    "sg:province":"TX",
    "wof:name":"Schriewer Family LP",
    "wof:placetype":"venue"
},
  "geometry": {"coordinates":[-97.14782099999999,32.830776],"type":"Point"}
}