{
  "type": "Feature",
  "properties": {
    "iso:country":"US",
    "sg:address":"1200 Old Decatur Rd",
    "sg:city":"Saginaw",
    "sg:classifiers":[
        {
            "category":"Bus Charters",
            "type":"Transportation"
        }
    ],
    "sg:phone":"+1 817 847 6537",
    "sg:postcode":"76179",
    "sg:province":"TX",
    "sg:tags":[
        "rental"
    ],
    "sg:website":"www.durhamschoolservices.com",
    "wof:name":"Durham Transportation",
    "wof:placetype":"venue"
},
  "geometry": {"coordinates":[-97.390665,32.874651],"type":"Point"}
}