{
  "type": "Feature",
  "properties": {
    "iso:country":"US",
    "sg:address":"2404 Castle Rock Rd",
    "sg:city":"Arlington",
    "sg:classifiers":[
        {
            "category":"Banks & Credit Unions",
            "subcategory":"Financial Services",
            "type":"Services"
        }
    ],
    "sg:phone":"+1 817 652 0045",
    "sg:postcode":"76006",
    "sg:province":"TX",
    "sg:tags":[
        "trust",
        "management"
    ],
    "wof:name":"Yale M Cason",
    "wof:placetype":"venue"
},
  "geometry": {"coordinates":[-97.066631,32.787381],"type":"Point"}
}