{
  "type": "Feature",
  "properties": {
    "iso:country":"US",
    "sg:address":"1177 W Loop S Ste 1200",
    "sg:city":"Houston",
    "sg:classifiers":[
        {
            "category":"Real Estate",
            "subcategory":"Real Estate Services",
            "type":"Services"
        },
        {
            "category":"Real Estate",
            "subcategory":"Real Estate Agent",
            "type":"Services"
        }
    ],
    "sg:phone":"+1 713 206 9140",
    "sg:postcode":"77027",
    "sg:province":"TX",
    "sg:website":"www.jasonzamora.com",
    "wof:name":"Jason Zamora - Heritage Texas Properties, Post Oak Park",
    "wof:placetype":"venue"
},
  "geometry": {"coordinates":[-95.45406,29.756961],"type":"Point"}
}