{
  "type": "Feature",
  "properties": {
    "iso:country":"US",
    "sg:address":"609 S Bliss Ave",
    "sg:city":"Dumas",
    "sg:classifiers":[
        {
            "category":"Professional",
            "subcategory":"Business Services",
            "type":"Services"
        },
        {
            "category":"Travel",
            "subcategory":"Travel Agent",
            "type":"Entertainment"
        }
    ],
    "sg:phone":"+1 806 935 6130",
    "sg:postcode":"79029",
    "sg:province":"TX",
    "sg:tags":[
        "agency",
        "bureau"
    ],
    "wof:name":"First Class Connection",
    "wof:placetype":"venue"
},
  "geometry": {"coordinates":[-101.971778,35.859774],"type":"Point"}
}