{
  "type": "Feature",
  "properties": {
    "iso:country":"US",
    "sg:address":"1200 E Berry St",
    "sg:city":"Fort Worth",
    "sg:classifiers":[
        {
            "category":"Autos & Motor Vehicles",
            "subcategory":"Auto Supplies",
            "type":"Retail Goods"
        }
    ],
    "sg:phone":"+1 817 921 4791",
    "sg:postcode":"76110",
    "sg:province":"TX",
    "sg:tags":[
        "equipment",
        "air",
        "conditioning",
        "automobile"
    ],
    "wof:name":"Daniel's Auto Air Conditioning",
    "wof:placetype":"venue"
},
  "geometry": {"coordinates":[-97.31247999999999,32.705945],"type":"Point"}
}