{
  "type": "Feature",
  "properties": {
    "iso:country":"US",
    "sg:address":"6001 Stonington St",
    "sg:city":"Houston",
    "sg:classifiers":[
        {
            "category":"Professional",
            "subcategory":"Accounting & Tax Preparation",
            "type":"Services"
        }
    ],
    "sg:phone":"+1 281 351 5622",
    "sg:postcode":"77040",
    "sg:province":"TX",
    "sg:tags":[
        "trust",
        "management"
    ],
    "wof:name":"Royce R Witte CPA",
    "wof:placetype":"venue"
},
  "geometry": {"coordinates":[-95.532223,29.855912],"type":"Point"}
}