{
  "type": "Feature",
  "properties": {
    "iso:country":"US",
    "sg:address":"6710 Windrock Rd",
    "sg:city":"Dallas",
    "sg:classifiers":[
        {
            "category":"Personal",
            "subcategory":"Beauty Salon",
            "type":"Services"
        }
    ],
    "sg:phone":"+1 972 407 9352",
    "sg:postcode":"75252",
    "sg:province":"TX",
    "sg:tags":[
        "shop"
    ],
    "wof:name":"Sports Clip",
    "wof:placetype":"venue"
},
  "geometry": {"coordinates":[-96.78465300000001,32.993777],"type":"Point"}
}