{
  "type": "Feature",
  "properties": {
    "iso:country":"US",
    "sg:address":"7609 Navarro Pl",
    "sg:city":"Austin",
    "sg:classifiers":[
        {
            "category":"Professional",
            "subcategory":"Business Services",
            "type":"Services"
        }
    ],
    "sg:phone":"+1 512 282 2648",
    "sg:postcode":"78749",
    "sg:province":"TX",
    "wof:name":"Tasbih Designs",
    "wof:placetype":"venue"
},
  "geometry": {"coordinates":[-97.849465,30.213377],"type":"Point"}
}