{
  "type": "Feature",
  "properties": {
    "iso:country":"US",
    "sg:address":"700 E 7th St",
    "sg:city":"Houston",
    "sg:classifiers":[
        {
            "category":"Shopping",
            "subcategory":"Catalog Store",
            "type":"Retail Goods"
        }
    ],
    "sg:phone":"+1 713 864 6226",
    "sg:postcode":"77007",
    "sg:province":"TX",
    "sg:tags":[
        "mail",
        "house"
    ],
    "wof:name":"Value Plus Catalog Sales",
    "wof:placetype":"venue"
},
  "geometry": {"coordinates":[-95.391001,29.783336],"type":"Point"}
}