{
  "type": "Feature",
  "properties": {
    "iso:country":"US",
    "sg:address":"501 Broadway",
    "sg:city":"San Antonio",
    "sg:classifiers":[
        {
            "category":"Communications",
            "subcategory":"Film & Video Production",
            "type":"Services"
        }
    ],
    "sg:phone":"+1 210 270 9000",
    "sg:postcode":"78215",
    "sg:province":"TX",
    "sg:tags":[
        "taping"
    ],
    "wof:name":"KLRN-TV",
    "wof:placetype":"venue"
},
  "geometry": {"coordinates":[-98.48434399999999,29.431144],"type":"Point"}
}