{
  "type": "Feature",
  "properties": {
    "iso:country":"US",
    "sg:address":"5116 58th St",
    "sg:city":"Lubbock",
    "sg:classifiers":[
        {
            "category":"Personal",
            "subcategory":"Beauty Salon",
            "type":"Services"
        }
    ],
    "sg:phone":"+1 806 797 6923",
    "sg:postcode":"79414",
    "sg:province":"TX",
    "sg:tags":[
        "shop",
        "manicuring"
    ],
    "wof:name":"Nail Tech",
    "wof:placetype":"venue"
},
  "geometry": {"coordinates":[-101.921322,33.54153],"type":"Point"}
}