{
  "type": "Feature",
  "properties": {
    "iso:country":"US",
    "sg:address":"4141 Spring Valley Rd",
    "sg:city":"Addison",
    "sg:classifiers":[
        {
            "category":"Education",
            "subcategory":"School",
            "type":"Public Place"
        }
    ],
    "sg:phone":"+1 972 628 5400",
    "sg:postcode":"75001",
    "sg:province":"TX",
    "sg:tags":[
        "organization",
        "religious"
    ],
    "wof:name":"Greenhill School",
    "wof:placetype":"venue"
},
  "geometry": {"coordinates":[-96.83979600000001,32.939927],"type":"Point"}
}