{
  "type": "Feature",
  "properties": {
    "iso:country":"US",
    "sg:address":"4315 Beechwood Ln",
    "sg:city":"Dallas",
    "sg:classifiers":[
        {
            "category":"Banks & Credit Unions",
            "subcategory":"Investment Brokerage",
            "type":"Services"
        }
    ],
    "sg:phone":"+1 214 352 3643",
    "sg:postcode":"75220",
    "sg:province":"TX",
    "sg:tags":[
        "advisory"
    ],
    "wof:name":"Lauragrace Corp",
    "wof:placetype":"venue"
},
  "geometry": {"coordinates":[-96.836451,32.875548],"type":"Point"}
}