{
  "type": "Feature",
  "properties": {
    "iso:country":"US",
    "sg:address":"1006 South 8th",
    "sg:city":"Austin",
    "sg:classifiers":[
        {
            "category":"Sports & Exercise",
            "subcategory":"Gym",
            "type":"Entertainment"
        }
    ],
    "sg:postcode":"78704",
    "sg:province":"TX",
    "sg:tags":[
        "yoga"
    ],
    "sg:website":"www.bodychoir.org",
    "wof:name":"Body Choir",
    "wof:placetype":"venue"
},
  "geometry": {"coordinates":[-97.760792,30.255578],"type":"Point"}
}