{
  "type": "Feature",
  "properties": {
    "iso:country":"US",
    "sg:address":"2708 Lark Cir",
    "sg:city":"Plano",
    "sg:classifiers":[
        {
            "category":"Real Estate",
            "subcategory":"Architect",
            "type":"Services"
        }
    ],
    "sg:phone":"+1 972 985 3833",
    "sg:postcode":"75075",
    "sg:province":"TX",
    "wof:name":"Chris Rador Inc",
    "wof:placetype":"venue"
},
  "geometry": {"coordinates":[-96.746178,33.036895],"type":"Point"}
}