{
  "type": "Feature",
  "properties": {
    "iso:country":"US",
    "sg:address":"106 E Corpus Christi St",
    "sg:city":"Beeville",
    "sg:classifiers":[
        {
            "category":"Professional",
            "type":"Services"
        }
    ],
    "sg:phone":"+1 361 358 4315",
    "sg:postcode":"78102",
    "sg:province":"TX",
    "wof:name":"Case Management Svc",
    "wof:placetype":"venue"
},
  "geometry": {"coordinates":[-97.747142,28.402415],"type":"Point"}
}