{
  "type": "Feature",
  "properties": {
    "iso:country":"US",
    "sg:address":"10838 Bravura Ln",
    "sg:city":"Dallas",
    "sg:classifiers":[
        {
            "category":"Social Services",
            "type":"Services"
        }
    ],
    "sg:phone":"+1 972 557 7256",
    "sg:postcode":"75217",
    "sg:province":"TX",
    "wof:name":"Real Life Athletic Association",
    "wof:placetype":"venue"
},
  "geometry": {"coordinates":[-96.64078600000001,32.729969],"type":"Point"}
}