{
  "type": "Feature",
  "properties": {
    "iso:country":"US",
    "sg:address":"3010 Lyndon B Johnson Fwy",
    "sg:city":"Dallas",
    "sg:phone":"+1 972 247 9250",
    "sg:postcode":"75234",
    "sg:province":"TX",
    "sg:website":"http://www.netatwork.com",
    "wof:name":"Structural Engenuity Inc",
    "wof:placetype":"venue"
},
  "geometry": {"coordinates":[-96.876684,32.911798],"type":"Point"}
}