{
  "type": "Feature",
  "properties": {
    "iso:country":"US",
    "sg:address":"4930 Washington Ave",
    "sg:city":"Houston",
    "sg:classifiers":[
        {
            "category":"Restaurant",
            "type":"Food & Drink"
        }
    ],
    "sg:phone":"+1 713 426 6609",
    "sg:postcode":"77007",
    "sg:province":"TX",
    "wof:name":"Subway Sandwiches & Salads",
    "wof:placetype":"venue"
},
  "geometry": {"coordinates":[-95.41130099999999,29.770599],"type":"Point"}
}