{
  "type": "Feature",
  "properties": {
    "iso:country":"US",
    "sg:address":"14512 Seminole Dr",
    "sg:city":"Balch Springs",
    "sg:classifiers":[
        {
            "category":"Retail",
            "subcategory":"Repair Shop",
            "type":"Services"
        }
    ],
    "sg:phone":"+1 214 403 8850",
    "sg:postcode":"75180",
    "sg:province":"TX",
    "sg:tags":[
        "television",
        "radio"
    ],
    "wof:name":"All Metroplex TV & Appliance",
    "wof:placetype":"venue"
},
  "geometry": {"coordinates":[-96.600205,32.706656],"type":"Point"}
}