{
  "type": "Feature",
  "properties": {
    "iso:country":"US",
    "sg:address":"1625 N 29 1/2 St",
    "sg:city":"Mcallen",
    "sg:classifiers":[
        {
            "category":"Building & Trades",
            "subcategory":"Plumbing",
            "type":"Services"
        }
    ],
    "sg:phone":"+1 956 534 3900",
    "sg:postcode":"78501",
    "sg:province":"TX",
    "sg:tags":[
        "plumber",
        "industrial",
        "contractors-commercial"
    ],
    "wof:name":"Bps Plumbing Service Dba",
    "wof:placetype":"venue"
},
  "geometry": {"coordinates":[-98.251431,26.222057],"type":"Point"}
}