{
  "type": "Feature",
  "properties": {
    "iso:country":"US",
    "sg:address":"4430 Centergate St",
    "sg:city":"San Antonio",
    "sg:classifiers":[
        {
            "category":"Manufacturing",
            "subcategory":"Motor Vehicles & Parts",
            "type":"Manufacturing & Wholesale Goods"
        }
    ],
    "sg:phone":"+1 210 590 8892",
    "sg:postcode":"78217",
    "sg:province":"TX",
    "sg:tags":[
        "screen",
        "printing",
        "embroidery"
    ],
    "wof:name":"Zubie Wear",
    "wof:placetype":"venue"
},
  "geometry": {"coordinates":[-98.40444599999999,29.520585],"type":"Point"}
}