{
  "type": "Feature",
  "properties": {
    "iso:country":"US",
    "sg:address":"901 E 10th Ave",
    "sg:city":"Corsicana",
    "sg:classifiers":[
        {
            "category":"Education",
            "subcategory":"School",
            "type":"Public Place"
        }
    ],
    "sg:phone":"+1 903 872 2988",
    "sg:postcode":"75110",
    "sg:province":"TX",
    "wof:name":"Dimensions Charter School",
    "wof:placetype":"venue"
},
  "geometry": {"coordinates":[-96.452905,32.093603],"type":"Point"}
}