{
  "type": "Feature",
  "properties": {
    "iso:country":"US",
    "sg:address":"17711 December Pine Ln",
    "sg:city":"Spring",
    "sg:classifiers":[
        {
            "category":"Building & Trades",
            "subcategory":"Construction",
            "type":"Services"
        }
    ],
    "sg:phone":"+1 281 370 2100",
    "sg:postcode":"77379",
    "sg:province":"TX",
    "sg:tags":[
        "house"
    ],
    "wof:name":"Atomic Painters & Remodelers",
    "wof:placetype":"venue"
},
  "geometry": {"coordinates":[-95.544539,30.024493],"type":"Point"}
}