{
  "type": "Feature",
  "properties": {
    "iso:country":"US",
    "sg:address":"4703 Ivanhoe St",
    "sg:city":"Houston",
    "sg:classifiers":[
        {
            "category":"Banks & Credit Unions",
            "subcategory":"Financial Services",
            "type":"Services"
        }
    ],
    "sg:phone":"+1 713 572 8040",
    "sg:postcode":"77027",
    "sg:province":"TX",
    "sg:tags":[
        "management",
        "open",
        "investment"
    ],
    "wof:name":"4730 Ivanhoe Partnership",
    "wof:placetype":"venue"
},
  "geometry": {"coordinates":[-95.455938,29.73957],"type":"Point"}
}