{
  "type": "Feature",
  "properties": {
    "iso:country":"US",
    "sg:address":"210 FM 247",
    "sg:city":"Huntsville",
    "sg:classifiers":[
        {
            "category":"Personal",
            "type":"Services"
        }
    ],
    "sg:phone":"+1 936 291 2259",
    "sg:postcode":"77320",
    "sg:province":"TX",
    "sg:tags":[
        "consultant",
        "wedding"
    ],
    "wof:name":"Mansion On Town Creek",
    "wof:placetype":"venue"
},
  "geometry": {"coordinates":[-95.55150500000001,30.734381],"type":"Point"}
}