{
  "type": "Feature",
  "properties": {
    "iso:country":"US",
    "sg:address":"10370 Richmond Ave",
    "sg:city":"Houston",
    "sg:classifiers":[
        {
            "category":"Professional",
            "type":"Services"
        }
    ],
    "sg:phone":"+1 713 458 5000",
    "sg:postcode":"77042",
    "sg:province":"TX",
    "sg:tags":[
        "establishment"
    ],
    "wof:name":"Experio Solutions",
    "wof:placetype":"venue"
},
  "geometry": {"coordinates":[-95.556764,29.727708],"type":"Point"}
}