{
  "type": "Feature",
  "properties": {
    "iso:country":"US",
    "sg:address":"1589 Flying Jib Dr",
    "sg:city":"Azle",
    "sg:classifiers":[
        {
            "category":"Building & Trades",
            "subcategory":"Construction",
            "type":"Services"
        }
    ],
    "sg:phone":"+1 817 270 3307",
    "sg:postcode":"76020",
    "sg:province":"TX",
    "sg:tags":[
        "painting",
        "contractor"
    ],
    "wof:name":"Tucker Enterprise Quixtar",
    "wof:placetype":"venue"
},
  "geometry": {"coordinates":[-97.520926,32.898032],"type":"Point"}
}