{
  "type": "Feature",
  "properties": {
    "iso:country":"US",
    "sg:address":"208 Murray Ln",
    "sg:city":"Richardson",
    "sg:classifiers":[
        {
            "category":"Professional",
            "subcategory":"Art Services",
            "type":"Services"
        }
    ],
    "sg:phone":"+1 972 238 0550",
    "sg:postcode":"75080",
    "sg:province":"TX",
    "sg:tags":[
        "commercial",
        "design"
    ],
    "wof:name":"Rankin Graphic Arts",
    "wof:placetype":"venue"
},
  "geometry": {"coordinates":[-96.75711800000001,32.949031],"type":"Point"}
}