{
  "type": "Feature",
  "properties": {
    "iso:country":"US",
    "sg:address":"8140 N MacArthur Blvd",
    "sg:city":"Irving",
    "sg:classifiers":[
        {
            "category":"Retail",
            "subcategory":"Laundry & Dry Cleaning",
            "type":"Services"
        }
    ],
    "sg:phone":"+1 972 506 9943",
    "sg:postcode":"75063",
    "sg:province":"TX",
    "wof:name":"Hackberry Cleaners",
    "wof:placetype":"venue"
},
  "geometry": {"coordinates":[-96.958265,32.920482],"type":"Point"}
}