{
  "type": "Feature",
  "properties": {
    "iso:country":"US",
    "sg:address":"6600 Columbine Way",
    "sg:city":"Plano",
    "sg:classifiers":[
        {
            "category":"Shopping",
            "subcategory":"Bicycles & Sporting Goods",
            "type":"Retail Goods"
        },
        {
            "category":"Organizations",
            "subcategory":"Membership Organization",
            "type":"Services"
        },
        {
            "category":"Sports & Exercise",
            "subcategory":"Golf",
            "type":"Entertainment"
        }
    ],
    "sg:phone":"+1 972 307 1620",
    "sg:postcode":"75093",
    "sg:province":"TX",
    "sg:tags":[
        "supply",
        "club",
        "instruction",
        "private",
        "equipment",
        "courses-private",
        "course"
    ],
    "wof:name":"Prestonwood Country Club",
    "wof:placetype":"venue"
},
  "geometry": {"coordinates":[-96.843727,33.039822],"type":"Point"}
}