{
  "type": "Feature",
  "properties": {
    "iso:country":"US",
    "sg:address":"8030 Aviation Pl",
    "sg:city":"Dallas",
    "sg:classifiers":[
        {
            "category":"Airport",
            "type":"Transportation"
        }
    ],
    "sg:phone":"+1 214 353 6700",
    "sg:postcode":"75235",
    "sg:province":"TX",
    "sg:tags":[
        "aviation",
        "management",
        "fleet"
    ],
    "wof:name":"GE",
    "wof:placetype":"venue"
},
  "geometry": {"coordinates":[-96.841148,32.838233],"type":"Point"}
}