{
  "type": "Feature",
  "properties": {
    "iso:country":"US",
    "sg:address":"95 White St",
    "sg:city":"Hartley",
    "sg:classifiers":[
        {
            "category":"Retail",
            "subcategory":"Repair Shop",
            "type":"Services"
        }
    ],
    "sg:phone":"+1 806 365 0093",
    "sg:postcode":"79044",
    "sg:province":"TX",
    "wof:name":"Hunter Long Shotting Supply",
    "wof:placetype":"venue"
},
  "geometry": {"coordinates":[-102.388927,35.890652],"type":"Point"}
}