{
  "type": "Feature",
  "properties": {
    "iso:country":"US",
    "sg:address":"6222 Yarwell Dr",
    "sg:city":"Houston",
    "sg:classifiers":[
        {
            "category":"Manufacturing",
            "subcategory":"Apparel",
            "type":"Manufacturing & Wholesale Goods"
        }
    ],
    "sg:phone":"+1 713 776 0902",
    "sg:postcode":"77096",
    "sg:province":"TX",
    "sg:tags":[
        "work",
        "clothing",
        "merchandise",
        "mfg"
    ],
    "wof:name":"M & M Lab Coats",
    "wof:placetype":"venue"
},
  "geometry": {"coordinates":[-95.500107,29.670219],"type":"Point"}
}