{
  "type": "Feature",
  "properties": {
    "iso:country":"US",
    "sg:address":"5780 W Pleasant Ridge Rd",
    "sg:city":"Arlington",
    "sg:classifiers":[
        {
            "category":"Retail",
            "subcategory":"Car Wash",
            "type":"Services"
        }
    ],
    "sg:phone":"+1 817 572 5935",
    "sg:postcode":"76016",
    "sg:province":"TX",
    "sg:tags":[
        "carwash",
        "automotive"
    ],
    "wof:name":"Colonial Car Wash & Lube Ctr",
    "wof:placetype":"venue"
},
  "geometry": {"coordinates":[-97.193766,32.681614],"type":"Point"}
}