{
  "type": "Feature",
  "properties": {
    "iso:country":"US",
    "sg:address":"17722 Woodlode Ln",
    "sg:city":"Spring",
    "sg:classifiers":[
        {
            "category":"Retail",
            "subcategory":"Auto Repair",
            "type":"Services"
        }
    ],
    "sg:phone":"+1 281 379 1165",
    "sg:postcode":"77379",
    "sg:province":"TX",
    "sg:tags":[
        "body",
        "automobile",
        "painting"
    ],
    "wof:name":"Hodges Auto Body",
    "wof:placetype":"venue"
},
  "geometry": {"coordinates":[-95.49771800000001,30.02143],"type":"Point"}
}