{
  "type": "Feature",
  "properties": {
    "iso:country":"US",
    "sg:address":"8353 Winkler Dr",
    "sg:city":"Houston",
    "sg:classifiers":[
        {
            "category":"Food & Beverages",
            "subcategory":"Groceries & Convenience Stores",
            "type":"Retail Goods"
        }
    ],
    "sg:phone":"+1 713 242 0970",
    "sg:postcode":"77017",
    "sg:province":"TX",
    "wof:name":"Winkler Food Mart",
    "wof:placetype":"venue"
},
  "geometry": {"coordinates":[-95.2677,29.6775],"type":"Point"}
}