{
  "type": "Feature",
  "properties": {
    "iso:country":"US",
    "sg:address":"206 San Pedro Ave",
    "sg:city":"San Antonio",
    "sg:classifiers":[
        {
            "category":"Health Services",
            "subcategory":"Medical Lab",
            "type":"Services"
        }
    ],
    "sg:phone":"+1 210 228 0183",
    "sg:postcode":"78205",
    "sg:province":"TX",
    "sg:tags":[
        "laboratory"
    ],
    "wof:name":"Lab Plus",
    "wof:placetype":"venue"
},
  "geometry": {"coordinates":[-98.49525,29.435005],"type":"Point"}
}