{
  "type": "Feature",
  "properties": {
    "iso:country":"US",
    "sg:address":"103 S Mechanic St",
    "sg:city":"El Campo",
    "sg:classifiers":[
        {
            "category":"Mining & Drilling",
            "type":"Manufacturing & Wholesale Goods"
        }
    ],
    "sg:phone":"+1 979 541 5454",
    "sg:postcode":"77437",
    "sg:province":"TX",
    "sg:tags":[
        "operator",
        "oil"
    ],
    "wof:name":"CJW Corp",
    "wof:placetype":"venue"
},
  "geometry": {"coordinates":[-96.26866699999999,29.195358],"type":"Point"}
}