{
  "type": "Feature",
  "properties": {
    "iso:country":"US",
    "sg:address":"7501 N Capital of Texas Hwy Ste A110",
    "sg:city":"Austin",
    "sg:classifiers":[
        {
            "category":"Banks & Credit Unions",
            "subcategory":"Bank",
            "type":"Services"
        },
        {
            "category":"Banks & Credit Unions",
            "subcategory":"Financial Services",
            "type":"Services"
        }
    ],
    "sg:phone":"+1 512 338 5600",
    "sg:postcode":"78731",
    "sg:province":"TX",
    "sg:tags":[
        "broker",
        "mortgage"
    ],
    "sg:website":"www.nationalcitymortgage.com",
    "wof:name":"National City Mortgage",
    "wof:placetype":"venue"
},
  "geometry": {"coordinates":[-97.78464200000001,30.372158],"type":"Point"}
}