{
  "type": "Feature",
  "properties": {
    "iso:country":"US",
    "sg:address":"108 NW 4th Ave",
    "sg:city":"Mineral Wells",
    "sg:classifiers":[
        {
            "category":"Organizations",
            "subcategory":"Religious Organization",
            "type":"Services"
        }
    ],
    "sg:phone":"+1 940 325 4789",
    "sg:postcode":"76067",
    "sg:province":"TX",
    "sg:tags":[
        "church"
    ],
    "wof:name":"Our Lady Of Lourdes Church",
    "wof:placetype":"venue"
},
  "geometry": {"coordinates":[-98.116252,32.809842],"type":"Point"}
}