{
  "type": "Feature",
  "properties": {
    "iso:country":"US",
    "sg:address":"112 Black Oak Dr",
    "sg:city":"Angleton",
    "sg:classifiers":[
        {
            "category":"Building & Trades",
            "subcategory":"Construction",
            "type":"Services"
        }
    ],
    "sg:phone":"+1 979 849 6178",
    "sg:postcode":"77515",
    "sg:province":"TX",
    "sg:tags":[
        "masonry",
        "contractor"
    ],
    "wof:name":"Grubbs Masonry",
    "wof:placetype":"venue"
},
  "geometry": {"coordinates":[-95.47487599999999,29.155197],"type":"Point"}
}