{
  "type": "Feature",
  "properties": {
    "iso:country":"US",
    "sg:address":"450 Airport Rd",
    "sg:city":"La Grange",
    "sg:classifiers":[
        {
            "category":"Autos & Motor Vehicles",
            "subcategory":"Fuel & Gas Station",
            "type":"Retail Goods"
        }
    ],
    "sg:phone":"+1 979 242 3958",
    "sg:postcode":"78945",
    "sg:province":"TX",
    "sg:tags":[
        "oil"
    ],
    "sg:website":"www.thomaspetro.com",
    "wof:name":"Thomas Petroleum Inc",
    "wof:placetype":"venue"
},
  "geometry": {"coordinates":[-96.94634000000001,29.909648],"type":"Point"}
}