{
  "type": "Feature",
  "properties": {
    "iso:country":"US",
    "sg:address":"800 5th Ave",
    "sg:city":"Fort Worth",
    "sg:classifiers":[
        {
            "category":"Health Services",
            "subcategory":"Doctor",
            "type":"Services"
        }
    ],
    "sg:phone":"+1 817 878 5410",
    "sg:postcode":"76104",
    "sg:province":"TX",
    "sg:tags":[
        "physician",
        "surgeon"
    ],
    "wof:name":"Breast Care",
    "wof:placetype":"venue"
},
  "geometry": {"coordinates":[-97.33851,32.735543],"type":"Point"}
}