{
  "type": "Feature",
  "properties": {
    "iso:country":"US",
    "sg:address":"3625 Wow Rd",
    "sg:city":"Corpus Christi",
    "sg:classifiers":[
        {
            "category":"Shopping",
            "subcategory":"Hobbies, Toys, & Games",
            "type":"Retail Goods"
        }
    ],
    "sg:phone":"+1 361 854 7744",
    "sg:postcode":"78413",
    "sg:province":"TX",
    "sg:tags":[
        "model",
        "supply"
    ],
    "wof:name":"Davis Dyno Tech",
    "wof:placetype":"venue"
},
  "geometry": {"coordinates":[-97.421791,27.698804],"type":"Point"}
}