{
  "type": "Feature",
  "properties": {
    "iso:country":"US",
    "sg:address":"4809 Forest Hill Cir",
    "sg:city":"Fort Worth",
    "sg:classifiers":[
        {
            "category":"Building & Trades",
            "subcategory":"Plumbing",
            "type":"Services"
        }
    ],
    "sg:phone":"+1 817 563 5100",
    "sg:postcode":"76140",
    "sg:province":"TX",
    "sg:tags":[
        "contractor"
    ],
    "wof:name":"Billy F Dorsey Plumbing Co",
    "wof:placetype":"venue"
},
  "geometry": {"coordinates":[-97.251479,32.66021],"type":"Point"}
}