{
  "type": "Feature",
  "properties": {
    "iso:country":"US",
    "sg:address":"955 Dairy Ashford St",
    "sg:city":"Houston",
    "sg:classifiers":[
        {
            "category":"Professional",
            "subcategory":"Accounting & Tax Preparation",
            "type":"Services"
        }
    ],
    "sg:phone":"+1 281 597 1300",
    "sg:postcode":"77079",
    "sg:province":"TX",
    "sg:tags":[
        "accountant"
    ],
    "wof:name":"Lester & Lester",
    "wof:placetype":"venue"
},
  "geometry": {"coordinates":[-95.606343,29.777392],"type":"Point"}
}