{
  "type": "Feature",
  "properties": {
    "iso:country":"US",
    "sg:address":"3410 Lindenwood Ave",
    "sg:city":"Dallas",
    "sg:classifiers":[
        {
            "category":"Professional",
            "subcategory":"Management & Consulting",
            "type":"Services"
        }
    ],
    "sg:phone":"+1 214 457 5679",
    "sg:postcode":"75205",
    "sg:province":"TX",
    "sg:tags":[
        "consultant",
        "business"
    ],
    "wof:name":"William Hall & Assoc",
    "wof:placetype":"venue"
},
  "geometry": {"coordinates":[-96.788938,32.82817],"type":"Point"}
}