{
  "type": "Feature",
  "properties": {
    "iso:country":"US",
    "sg:address":"222 W Houston St",
    "sg:city":"Sherman",
    "sg:classifiers":[
        {
            "category":"Wholesale",
            "subcategory":"Durable Goods & Equipment",
            "type":"Manufacturing & Wholesale Goods"
        }
    ],
    "sg:phone":"+1 903 891 3909",
    "sg:postcode":"75090",
    "sg:province":"TX",
    "wof:name":"Monterrey Mexican Imports",
    "wof:placetype":"venue"
},
  "geometry": {"coordinates":[-96.611485,33.636031],"type":"Point"}
}