{
  "type": "Feature",
  "properties": {
    "iso:country":"US",
    "sg:address":"210 Sam Houston Dr",
    "sg:city":"Victoria",
    "sg:classifiers":[
        {
            "category":"Health Services",
            "subcategory":"Health Practitioner",
            "type":"Services"
        }
    ],
    "sg:phone":"+1 361 572 0985",
    "sg:postcode":"77901",
    "sg:province":"TX",
    "wof:name":"Stephanie Elliott Mt",
    "wof:placetype":"venue"
},
  "geometry": {"coordinates":[-96.966306,28.815627],"type":"Point"}
}