{
  "type": "Feature",
  "properties": {
    "iso:country":"US",
    "sg:address":"3332 Park Lake Dr",
    "sg:city":"Fort Worth",
    "sg:classifiers":[
        {
            "category":"Professional",
            "type":"Services"
        }
    ],
    "sg:phone":"+1 817 292 9296",
    "sg:postcode":"76133",
    "sg:province":"TX",
    "wof:name":"Tpw Inc",
    "wof:placetype":"venue"
},
  "geometry": {"coordinates":[-97.364482,32.653625],"type":"Point"}
}