{
  "type": "Feature",
  "properties": {
    "iso:country":"US",
    "sg:address":"10110 Hardison Ln",
    "sg:city":"Houston",
    "sg:classifiers":[
        {
            "category":"Shopping",
            "type":"Retail Goods"
        },
        {
            "category":"Manufacturing",
            "subcategory":"Tools & Machinery",
            "type":"Manufacturing & Wholesale Goods"
        }
    ],
    "sg:phone":"+1 713 895 0844",
    "sg:postcode":"77041",
    "sg:province":"TX",
    "sg:tags":[
        "machine",
        "shop",
        "merchandise"
    ],
    "wof:name":"Valpo Machine Shop",
    "wof:placetype":"venue"
},
  "geometry": {"coordinates":[-95.542419,29.851535],"type":"Point"}
}