{
  "type": "Feature",
  "properties": {
    "iso:country":"US",
    "sg:address":"2023 Glade Rd",
    "sg:city":"Colleyville",
    "sg:classifiers":[
        {
            "category":"Shopping",
            "subcategory":"Gifts & Souvenirs",
            "type":"Retail Goods"
        }
    ],
    "sg:phone":"+1 817 421 9993",
    "sg:postcode":"76034",
    "sg:province":"TX",
    "sg:tags":[
        "shop"
    ],
    "sg:website":"www.hallmark.com",
    "wof:name":"Holly's Hallmark",
    "wof:placetype":"venue"
},
  "geometry": {"coordinates":[-97.135831,32.881788],"type":"Point"}
}