{
  "type": "Feature",
  "properties": {
    "iso:country":"US",
    "sg:address":"4013 Manchaca Rd",
    "sg:city":"Austin",
    "sg:classifiers":[
        {
            "category":"Shopping",
            "type":"Retail Goods"
        }
    ],
    "sg:phone":"+1 512 750 6906",
    "sg:postcode":"78704",
    "sg:province":"TX",
    "sg:tags":[
        "merchandise"
    ],
    "wof:name":"Carol Bourgeois",
    "wof:placetype":"venue"
},
  "geometry": {"coordinates":[-97.786102,30.233171],"type":"Point"}
}