{
  "type": "Feature",
  "properties": {
    "iso:country":"US",
    "sg:address":"1444 Oak Lawn Ave",
    "sg:city":"Dallas",
    "sg:classifiers":[
        {
            "category":"Professional",
            "subcategory":"Business Services",
            "type":"Services"
        }
    ],
    "sg:phone":"+1 214 741 7155",
    "sg:postcode":"75207",
    "sg:province":"TX",
    "sg:tags":[
        "interior",
        "design"
    ],
    "wof:name":"Interior Solutions Inc",
    "wof:placetype":"venue"
},
  "geometry": {"coordinates":[-96.82051,32.796034],"type":"Point"}
}