{
  "type": "Feature",
  "properties": {
    "iso:country":"US",
    "sg:address":"111 W 34th Ave",
    "sg:city":"Amarillo",
    "sg:classifiers":[
        {
            "category":"Wholesale",
            "subcategory":"Stationery",
            "type":"Manufacturing & Wholesale Goods"
        }
    ],
    "sg:phone":"+1 806 379 6018",
    "sg:postcode":"79109",
    "sg:province":"TX",
    "sg:tags":[
        "supply"
    ],
    "wof:name":"Forms In Time",
    "wof:placetype":"venue"
},
  "geometry": {"coordinates":[-101.842175,35.178311],"type":"Point"}
}