{
  "type": "Feature",
  "properties": {
    "iso:country":"US",
    "sg:address":"100 N Tenery St",
    "sg:city":"Gladewater",
    "sg:classifiers":[
        {
            "category":"Professional",
            "subcategory":"Business Services",
            "type":"Services"
        }
    ],
    "sg:phone":"+1 903 845 2018",
    "sg:postcode":"75647",
    "sg:province":"TX",
    "wof:name":"DEW Plans & Designs",
    "wof:placetype":"venue"
},
  "geometry": {"coordinates":[-94.946049,32.537098],"type":"Point"}
}