{
  "type": "Feature",
  "properties": {
    "iso:country":"US",
    "sg:address":"4004 Mansfield Hwy",
    "sg:city":"Fort Worth",
    "sg:classifiers":[
        {
            "category":"Autos & Motor Vehicles",
            "subcategory":"Automobile Sales",
            "type":"Retail Goods"
        }
    ],
    "sg:phone":"+1 817 534 3447",
    "sg:postcode":"76119",
    "sg:province":"TX",
    "sg:tags":[
        "used"
    ],
    "wof:name":"Quality Used Cars",
    "wof:placetype":"venue"
},
  "geometry": {"coordinates":[-97.267094,32.677287],"type":"Point"}
}