{
  "type": "Feature",
  "properties": {
    "iso:country":"US",
    "sg:address":"2926 Woodcreek Ln",
    "sg:city":"Houston",
    "sg:classifiers":[
        {
            "category":"Education",
            "subcategory":"Vocational School",
            "type":"Public Place"
        }
    ],
    "sg:phone":"+1 281 209 0837",
    "sg:postcode":"77073",
    "sg:province":"TX",
    "sg:tags":[
        "processing",
        "datum"
    ],
    "wof:name":"Technoversity LLC",
    "wof:placetype":"venue"
},
  "geometry": {"coordinates":[-95.377358,30.014835],"type":"Point"}
}