{
  "type": "Feature",
  "properties": {
    "iso:country":"US",
    "sg:address":"64 Highland Park Village",
    "sg:city":"Dallas",
    "sg:classifiers":[
        {
            "category":"Shopping",
            "subcategory":"Optical Goods",
            "type":"Retail Goods"
        }
    ],
    "sg:phone":"+1 214 522 0352",
    "sg:postcode":"75205",
    "sg:province":"TX",
    "wof:name":"Peepers Optical",
    "wof:placetype":"venue"
},
  "geometry": {"coordinates":[-96.806697,32.836318],"type":"Point"}
}