{
  "type": "Feature",
  "properties": {
    "iso:country":"US",
    "sg:address":"5918 W Courtyard Dr",
    "sg:city":"Austin",
    "sg:classifiers":[
        {
            "category":"Professional",
            "subcategory":"Computer Services",
            "type":"Services"
        }
    ],
    "sg:phone":"+1 512 276 2070",
    "sg:postcode":"78730",
    "sg:province":"TX",
    "sg:tags":[
        "cd-rom"
    ],
    "wof:name":"nFocus Software",
    "wof:placetype":"venue"
},
  "geometry": {"coordinates":[-97.795779,30.35273],"type":"Point"}
}