{
  "type": "Feature",
  "properties": {
    "iso:country":"US",
    "sg:address":"102 S Ector Dr",
    "sg:city":"Euless",
    "sg:classifiers":[
        {
            "category":"Food & Beverages",
            "subcategory":"Groceries & Convenience Stores",
            "type":"Retail Goods"
        }
    ],
    "sg:phone":"+1 817 545 6786",
    "sg:postcode":"76040",
    "sg:province":"TX",
    "sg:tags":[
        "motion",
        "picture",
        "video",
        "tape",
        "rental"
    ],
    "wof:name":"India Video & Grocery",
    "wof:placetype":"venue"
},
  "geometry": {"coordinates":[-97.09069100000001,32.834012],"type":"Point"}
}