{
  "type": "Feature",
  "properties": {
    "iso:country":"US",
    "sg:address":"1300 Cypress Dr",
    "sg:city":"Richardson",
    "sg:classifiers":[
        {
            "category":"Education",
            "subcategory":"School",
            "type":"Public Place"
        }
    ],
    "sg:phone":"+1 469 593 6400",
    "sg:postcode":"75080",
    "sg:province":"TX",
    "sg:tags":[
        "high",
        "middle",
        "elementary"
    ],
    "sg:website":"www.risd.org",
    "wof:name":"Schools",
    "wof:placetype":"venue"
},
  "geometry": {"coordinates":[-96.76230200000001,32.960967],"type":"Point"}
}