{
  "type": "Feature",
  "properties": {
    "iso:country":"US",
    "sg:address":"5331 N Macarthur Blvd # 20",
    "sg:city":"Irving",
    "sg:classifiers":[
        {
            "category":"Real Estate",
            "subcategory":"Real Estate Services",
            "type":"Services"
        },
        {
            "category":"Real Estate",
            "subcategory":"Real Estate Agent",
            "type":"Services"
        }
    ],
    "sg:phone":"+1 972 489 0824",
    "sg:postcode":"75038",
    "sg:province":"TX",
    "sg:tags":[
        "buyer",
        "broker"
    ],
    "wof:name":"Lance Blann Realtor",
    "wof:placetype":"venue"
},
  "geometry": {"coordinates":[-96.96393999999999,32.881448],"type":"Point"}
}