{
  "type": "Feature",
  "properties": {
    "iso:country":"US",
    "sg:address":"1101 Navasota St",
    "sg:city":"Austin",
    "sg:classifiers":[
        {
            "category":"Personal",
            "subcategory":"Barber",
            "type":"Services"
        }
    ],
    "sg:phone":"+1 512 320 8950",
    "sg:postcode":"78702",
    "sg:province":"TX",
    "sg:tags":[
        "shop"
    ],
    "wof:name":"Green Barber & Beauty Salon",
    "wof:placetype":"venue"
},
  "geometry": {"coordinates":[-97.727087,30.269226],"type":"Point"}
}