{
  "type": "Feature",
  "properties": {
    "iso:country":"US",
    "sg:address":"702 N Travis St",
    "sg:city":"Sherman",
    "sg:classifiers":[
        {
            "category":"Professional",
            "subcategory":"Business Services",
            "type":"Services"
        }
    ],
    "sg:phone":"+1 903 893 1233",
    "sg:postcode":"75090",
    "sg:province":"TX",
    "sg:tags":[
        "interior",
        "consultant",
        "design",
        "decorator"
    ],
    "wof:name":"Interiors Homestore",
    "wof:placetype":"venue"
},
  "geometry": {"coordinates":[-96.61162,33.644138],"type":"Point"}
}