{
  "type": "Feature",
  "properties": {
    "iso:country":"US",
    "sg:address":"413 Beckham St E",
    "sg:city":"Sulphur Springs",
    "sg:classifiers":[
        {
            "category":"Building & Trades",
            "subcategory":"Construction",
            "type":"Services"
        }
    ],
    "sg:phone":"+1 903 438 2991",
    "sg:postcode":"75482",
    "sg:province":"TX",
    "sg:tags":[
        "contractor"
    ],
    "wof:name":"Gray's Building",
    "wof:placetype":"venue"
},
  "geometry": {"coordinates":[-95.593177,33.13035],"type":"Point"}
}