{
  "type": "Feature",
  "properties": {
    "iso:country":"US",
    "sg:address":"280 US Hwy 380",
    "sg:city":"Jacksboro",
    "sg:classifiers":[
        {
            "category":"Social Services",
            "subcategory":"Child Care",
            "type":"Services"
        }
    ],
    "sg:phone":"+1 940 567 3583",
    "sg:postcode":"76458",
    "sg:province":"TX",
    "sg:tags":[
        "day"
    ],
    "wof:name":"Lisa Kinder",
    "wof:placetype":"venue"
},
  "geometry": {"coordinates":[-98.162567,33.218323],"type":"Point"}
}