{
  "type": "Feature",
  "properties": {
    "iso:country":"US",
    "sg:address":"1100 Summit Ave Ste 108",
    "sg:city":"Plano",
    "sg:classifiers":[
        {
            "category":"Building & Trades",
            "subcategory":"Construction",
            "type":"Services"
        }
    ],
    "sg:phone":"+1 972 509 2811",
    "sg:postcode":"75074",
    "sg:province":"TX",
    "sg:tags":[
        "contractor"
    ],
    "wof:name":"Petro-Jett LLC",
    "wof:placetype":"venue"
},
  "geometry": {"coordinates":[-96.699242,33.352885],"type":"Point"}
}