{
  "type": "Feature",
  "properties": {
    "iso:country":"US",
    "sg:address":"1016 Ritchey St",
    "sg:city":"Gainesville",
    "sg:classifiers":[
        {
            "category":"Health Services",
            "subcategory":"Hospital",
            "type":"Services"
        }
    ],
    "sg:phone":"+1 940 665 1751",
    "sg:postcode":"76240",
    "sg:province":"TX",
    "wof:name":"Gainesville Memorial Hospital",
    "wof:placetype":"venue"
},
  "geometry": {"coordinates":[-97.131248,33.635955],"type":"Point"}
}