{
  "type": "Feature",
  "properties": {
    "iso:country":"US",
    "sg:address":"3001 Sale St",
    "sg:city":"Dallas",
    "sg:classifiers":[
        {
            "category":"Professional",
            "type":"Services"
        }
    ],
    "sg:phone":"+1 214 252 9045",
    "sg:postcode":"75219",
    "sg:province":"TX",
    "sg:tags":[
        "establishment"
    ],
    "wof:name":"Parc Royale",
    "wof:placetype":"venue"
},
  "geometry": {"coordinates":[-96.80577099999999,32.806745],"type":"Point"}
}