{
  "type": "Feature",
  "properties": {
    "iso:country":"US",
    "sg:address":"11612 FM 2244",
    "sg:city":"Austin",
    "sg:classifiers":[
        {
            "category":"Building & Trades",
            "subcategory":"Landscaping Services",
            "type":"Services"
        }
    ],
    "sg:phone":"+1 512 693 4878",
    "sg:postcode":"78738",
    "sg:province":"TX",
    "wof:name":"Harvestree Arbor Care",
    "wof:placetype":"venue"
},
  "geometry": {"coordinates":[-97.895713,30.307468],"type":"Point"}
}