{
  "type": "Feature",
  "properties": {
    "iso:country":"US",
    "sg:address":"10520 Leedy Rd",
    "sg:city":"Manvel",
    "sg:classifiers":[
        {
            "category":"Building & Trades",
            "subcategory":"Landscaping Services",
            "type":"Services"
        }
    ],
    "sg:phone":"+1 281 331 7503",
    "sg:postcode":"77578",
    "sg:province":"TX",
    "wof:name":"Aaron Landscaping",
    "wof:placetype":"venue"
},
  "geometry": {"coordinates":[-95.37437199999999,29.423398],"type":"Point"}
}