{
  "type": "Feature",
  "properties": {
    "iso:country":"US",
    "sg:address":"2407 E Murphy St",
    "sg:city":"Odessa",
    "sg:classifiers":[
        {
            "category":"Mining & Drilling",
            "type":"Manufacturing & Wholesale Goods"
        }
    ],
    "sg:phone":"+1 432 580 5101",
    "sg:postcode":"79761",
    "sg:province":"TX",
    "sg:tags":[
        "well"
    ],
    "wof:name":"Key Energy Group",
    "wof:placetype":"venue"
},
  "geometry": {"coordinates":[-102.323633,31.8507],"type":"Point"}
}