{
  "type": "Feature",
  "properties": {
    "iso:country":"US",
    "sg:address":"10648 Mazoch Rd",
    "sg:city":"Weimar",
    "sg:classifiers":[
        {
            "category":"Building & Trades",
            "subcategory":"Landscaping Services",
            "type":"Services"
        }
    ],
    "sg:phone":"+1 979 263 5881",
    "sg:postcode":"78962",
    "sg:province":"TX",
    "sg:tags":[
        "tree"
    ],
    "wof:name":"Six J Ranch Tree Farm",
    "wof:placetype":"venue"
},
  "geometry": {"coordinates":[-96.81693799999999,29.762721],"type":"Point"}
}