{
  "type": "Feature",
  "properties": {
    "iso:country":"US",
    "sg:address":"6010 Shattuck Dr",
    "sg:city":"Garland",
    "sg:classifiers":[
        {
            "category":"Retail",
            "subcategory":"Repair Shop",
            "type":"Services"
        }
    ],
    "sg:phone":"+1 972 414 5000",
    "sg:postcode":"75044",
    "sg:province":"TX",
    "wof:name":"ASAP Locksmith",
    "wof:placetype":"venue"
},
  "geometry": {"coordinates":[-96.667368,32.969153],"type":"Point"}
}