{
  "type": "Feature",
  "properties": {
    "iso:country":"US",
    "sg:address":"5740 Forest Ln",
    "sg:city":"Dallas",
    "sg:classifiers":[
        {
            "category":"Wholesale",
            "subcategory":"Apparel",
            "type":"Manufacturing & Wholesale Goods"
        }
    ],
    "sg:phone":"+1 214 368 1692",
    "sg:postcode":"75230",
    "sg:province":"TX",
    "sg:tags":[
        "shoes-wholesale",
        "manufacturer"
    ],
    "wof:name":"Name Brand Shoes",
    "wof:placetype":"venue"
},
  "geometry": {"coordinates":[-96.809855,32.90942],"type":"Point"}
}