{
  "type": "Feature",
  "properties": {
    "iso:country":"US",
    "sg:address":"7860 San Jose Rd",
    "sg:city":"El Paso",
    "sg:classifiers":[
        {
            "category":"Wholesale",
            "subcategory":"Groceries",
            "type":"Manufacturing & Wholesale Goods"
        }
    ],
    "sg:phone":"+1 915 592 1075",
    "sg:postcode":"79915",
    "sg:province":"TX",
    "sg:tags":[
        "food",
        "product",
        "distributes",
        "mexican"
    ],
    "wof:name":"Albuquerque Tortilla Co",
    "wof:placetype":"venue"
},
  "geometry": {"coordinates":[-106.356796,31.732091],"type":"Point"}
}