{
  "type": "Feature",
  "properties": {
    "iso:country":"US",
    "sg:address":"6100 Preston Rd",
    "sg:city":"Frisco",
    "sg:classifiers":[
        {
            "category":"Health Services",
            "subcategory":"Doctor",
            "type":"Services"
        }
    ],
    "sg:phone":"+1 214 387 8181",
    "sg:postcode":"75034",
    "sg:province":"TX",
    "sg:tags":[
        "dentist"
    ],
    "wof:name":"Jason Miller DDS",
    "wof:placetype":"venue"
},
  "geometry": {"coordinates":[-96.80437999999999,33.133445],"type":"Point"}
}