{
  "type": "Feature",
  "properties": {
    "iso:country":"US",
    "sg:address":"2340 Sylvan Ave",
    "sg:city":"Dallas",
    "sg:classifiers":[
        {
            "category":"Freight",
            "type":"Transportation"
        }
    ],
    "sg:phone":"+1 214 752 4277",
    "sg:postcode":"75208",
    "sg:province":"TX",
    "sg:tags":[
        "trucking"
    ],
    "wof:name":"Mail Contractors Of America",
    "wof:placetype":"venue"
},
  "geometry": {"coordinates":[-96.83583,32.773619],"type":"Point"}
}