{
  "type": "Feature",
  "properties": {
    "iso:country":"US",
    "sg:address":"3209 Willowbrook St",
    "sg:city":"Waco",
    "sg:classifiers":[
        {
            "category":"Manufacturing",
            "subcategory":"Building Materials",
            "type":"Manufacturing & Wholesale Goods"
        }
    ],
    "sg:phone":"+1 254 756 5261",
    "sg:postcode":"76711",
    "sg:province":"TX",
    "sg:tags":[
        "mfg"
    ],
    "wof:name":"Carpenter S Son Woodcraft",
    "wof:placetype":"venue"
},
  "geometry": {"coordinates":[-97.15106400000001,31.529144],"type":"Point"}
}