{
  "type": "Feature",
  "properties": {
    "iso:country":"US",
    "sg:address":"2 Northpoint Dr",
    "sg:city":"Houston",
    "sg:classifiers":[
        {
            "category":"Professional",
            "subcategory":"Employment Agencies",
            "type":"Services"
        }
    ],
    "sg:phone":"+1 281 999 1886",
    "sg:postcode":"77060",
    "sg:province":"TX",
    "sg:tags":[
        "personnel",
        "computer",
        "programming",
        "placement"
    ],
    "wof:name":"SPS Group Inc",
    "wof:placetype":"venue"
},
  "geometry": {"coordinates":[-95.41031599999999,29.937928],"type":"Point"}
}