{
  "type": "Feature",
  "properties": {
    "iso:country":"US",
    "sg:address":"PO Box 540446",
    "sg:city":"Houston",
    "sg:classifiers":[
        {
            "category":"Professional",
            "subcategory":"Lawyer & Legal Services",
            "type":"Services"
        }
    ],
    "sg:phone":"+1 713 963 8998",
    "sg:postcode":"77254",
    "sg:province":"TX",
    "wof:name":"Lindsey-Salvato C A Atty",
    "wof:placetype":"venue"
},
  "geometry": {"coordinates":[-95.414703,29.682199],"type":"Point"}
}