{
  "type": "Feature",
  "properties": {
    "iso:country":"US",
    "sg:address":"1822 Banks Dr",
    "sg:city":"Weatherford",
    "sg:classifiers":[
        {
            "category":"Building & Trades",
            "subcategory":"Plumbing",
            "type":"Services"
        }
    ],
    "sg:phone":"+1 817 596 0060",
    "sg:postcode":"76087",
    "sg:province":"TX",
    "sg:tags":[
        "mechanical",
        "contractor"
    ],
    "wof:name":"Employee's Mechanical",
    "wof:placetype":"venue"
},
  "geometry": {"coordinates":[-97.744117,32.741179],"type":"Point"}
}