{
  "type": "Feature",
  "properties": {
    "iso:country":"US",
    "sg:address":"9011 John W Carpenter Fwy",
    "sg:city":"Dallas",
    "sg:classifiers":[
        {
            "category":"Health Services",
            "subcategory":"Clinic",
            "type":"Services"
        }
    ],
    "sg:phone":"+1 214 688 0330",
    "sg:postcode":"75247",
    "sg:province":"TX",
    "sg:tags":[
        "home",
        "care"
    ],
    "wof:name":"Intrepid USA Healthcare Svcs",
    "wof:placetype":"venue"
},
  "geometry": {"coordinates":[-96.883754,32.825469],"type":"Point"}
}