{
  "type": "Feature",
  "properties": {
    "iso:country":"US",
    "sg:address":"3908 Timberwood Ln",
    "sg:city":"Huntsville",
    "sg:classifiers":[
        {
            "category":"Wholesale",
            "subcategory":"Auto Parts",
            "type":"Manufacturing & Wholesale Goods"
        }
    ],
    "sg:phone":"+1 936 438 8877",
    "sg:postcode":"77340",
    "sg:province":"TX",
    "sg:tags":[
        "bus",
        "supply"
    ],
    "wof:name":"Buck's Wheel & Equipment Co",
    "wof:placetype":"venue"
},
  "geometry": {"coordinates":[-95.51969099999999,30.682886],"type":"Point"}
}