{
  "type": "Feature",
  "properties": {
    "iso:country":"US",
    "sg:address":"1560 West St",
    "sg:city":"Houston",
    "sg:classifiers":[
        {
            "category":"Professional",
            "subcategory":"Lawyer & Legal Services",
            "type":"Services"
        }
    ],
    "sg:phone":"+1 281 218 0008",
    "sg:postcode":"77026",
    "sg:province":"TX",
    "wof:name":"The Drake Law Firm",
    "wof:placetype":"venue"
},
  "geometry": {"coordinates":[-95.345596,29.775299],"type":"Point"}
}