{
  "type": "Feature",
  "properties": {
    "iso:country":"US",
    "sg:address":"14511 Quention Dr",
    "sg:city":"Houston",
    "sg:classifiers":[
        {
            "category":"Building & Trades",
            "subcategory":"Cleaning & Sanitation",
            "type":"Services"
        }
    ],
    "sg:phone":"+1 713 413 1671",
    "sg:postcode":"77045",
    "sg:province":"TX",
    "sg:tags":[
        "maintenance"
    ],
    "wof:name":"Seldow Concept Cleaning",
    "wof:placetype":"venue"
},
  "geometry": {"coordinates":[-95.440989,29.616199],"type":"Point"}
}