{
  "type": "Feature",
  "properties": {
    "iso:country":"US",
    "sg:address":"2044 W Oaklawn Rd",
    "sg:city":"Pleasanton",
    "sg:classifiers":[
        {
            "category":"Professional",
            "type":"Services"
        },
        {
            "category":"Mining & Drilling",
            "type":"Manufacturing & Wholesale Goods"
        }
    ],
    "sg:phone":"+1 830 569 8850",
    "sg:postcode":"78064",
    "sg:province":"TX",
    "sg:tags":[
        "field",
        "oil"
    ],
    "wof:name":"Gold Star Energy Services Inc",
    "wof:placetype":"venue"
},
  "geometry": {"coordinates":[-98.515677,28.938349],"type":"Point"}
}