{
  "type": "Feature",
  "properties": {
    "iso:country":"US",
    "sg:address":"7627 Rambler Rd",
    "sg:city":"Dallas",
    "sg:classifiers":[
        {
            "category":"Professional",
            "type":"Services"
        }
    ],
    "sg:phone":"+1 214 361 9532",
    "sg:postcode":"75231",
    "sg:province":"TX",
    "wof:name":"Art Reach Services LLC",
    "wof:placetype":"venue"
},
  "geometry": {"coordinates":[-96.762439,32.884788],"type":"Point"}
}