{
  "type": "Feature",
  "properties": {
    "iso:country":"US",
    "sg:address":"5011 McCullough Ave",
    "sg:city":"San Antonio",
    "sg:classifiers":[
        {
            "category":"Personal",
            "subcategory":"Beauty Salon",
            "type":"Services"
        }
    ],
    "sg:phone":"+1 210 805 0855",
    "sg:postcode":"78212",
    "sg:province":"TX",
    "sg:tags":[
        "shop"
    ],
    "wof:name":"Odilia's Hair Studio",
    "wof:placetype":"venue"
},
  "geometry": {"coordinates":[-98.491778,29.477885],"type":"Point"}
}