{
  "type": "Feature",
  "properties": {
    "iso:country":"US",
    "sg:address":"1007 Easy St",
    "sg:city":"Burkburnett",
    "sg:classifiers":[
        {
            "category":"Building & Trades",
            "subcategory":"Electrical",
            "type":"Services"
        }
    ],
    "sg:phone":"+1 940 569 1554",
    "sg:postcode":"76354",
    "sg:province":"TX",
    "sg:tags":[
        "electric",
        "contractor"
    ],
    "wof:name":"Cheney Electric",
    "wof:placetype":"venue"
},
  "geometry": {"coordinates":[-98.581324,34.082312],"type":"Point"}
}