{
  "type": "Feature",
  "properties": {
    "iso:country":"US",
    "sg:address":"918 Lakeview Dr S",
    "sg:city":"Marshall",
    "sg:classifiers":[
        {
            "category":"Building & Trades",
            "subcategory":"Electrical",
            "type":"Services"
        }
    ],
    "sg:phone":"+1 903 935 0205",
    "sg:postcode":"75672",
    "sg:province":"TX",
    "sg:tags":[
        "electrical",
        "contractor"
    ],
    "wof:name":"Caps Electric",
    "wof:placetype":"venue"
},
  "geometry": {"coordinates":[-94.380594,32.493668],"type":"Point"}
}