{
  "type": "Feature",
  "properties": {
    "iso:country":"US",
    "sg:address":"6560 Waterbury Dr",
    "sg:city":"Frisco",
    "sg:classifiers":[
        {
            "category":"Personal",
            "type":"Services"
        }
    ],
    "sg:phone":"+1 972 712 9758",
    "sg:postcode":"75035",
    "sg:province":"TX",
    "wof:name":"Execu Service",
    "wof:placetype":"venue"
},
  "geometry": {"coordinates":[-96.781723,33.132543],"type":"Point"}
}