{
  "type": "Feature",
  "properties": {
    "iso:country":"US",
    "sg:address":"2114 Holly Hill Ln",
    "sg:city":"Carrollton",
    "sg:classifiers":[
        {
            "category":"Wholesale",
            "subcategory":"Construction Materials",
            "type":"Manufacturing & Wholesale Goods"
        }
    ],
    "sg:phone":"+1 469 371 7890",
    "sg:postcode":"75007",
    "sg:province":"TX",
    "sg:tags":[
        "fence"
    ],
    "wof:name":"Kings Town",
    "wof:placetype":"venue"
},
  "geometry": {"coordinates":[-96.869804,33.014217],"type":"Point"}
}