{
  "type": "Feature",
  "properties": {
    "iso:country":"US",
    "sg:address":"1340 Enchanted Oaks Dr",
    "sg:city":"Driftwood",
    "sg:classifiers":[
        {
            "category":"Professional",
            "subcategory":"Business Services",
            "type":"Services"
        }
    ],
    "sg:phone":"+1 512 894 0479",
    "sg:postcode":"78619",
    "sg:province":"TX",
    "wof:name":"Whs Enterprises",
    "wof:placetype":"venue"
},
  "geometry": {"coordinates":[-98.012016,30.152622],"type":"Point"}
}