{
  "type": "Feature",
  "properties": {
    "iso:country":"US",
    "sg:address":"8227 Fredericksburg Rd",
    "sg:city":"San Antonio",
    "sg:classifiers":[
        {
            "category":"Health Services",
            "subcategory":"Health Practitioner",
            "type":"Services"
        }
    ],
    "sg:phone":"+1 210 616 0889",
    "sg:postcode":"78229",
    "sg:province":"TX",
    "sg:tags":[
        "audiologists"
    ],
    "sg:website":"www.hearingaidsforless.net",
    "wof:name":"HEARINGAIDSFORLESS.NET",
    "wof:placetype":"venue"
},
  "geometry": {"coordinates":[-98.57154,29.515398],"type":"Point"}
}