{
  "type": "Feature",
  "properties": {
    "iso:country":"US",
    "sg:address":"8709 Copano Dr",
    "sg:city":"Austin",
    "sg:classifiers":[
        {
            "category":"Professional",
            "subcategory":"Engineering",
            "type":"Services"
        }
    ],
    "sg:phone":"+1 512 280 8960",
    "sg:postcode":"78749",
    "sg:province":"TX",
    "sg:tags":[
        "research"
    ],
    "wof:name":"Amiya Research Corporation",
    "wof:placetype":"venue"
},
  "geometry": {"coordinates":[-97.855683,30.20296],"type":"Point"}
}