{
  "type": "Feature",
  "properties": {
    "iso:country":"US",
    "sg:address":"300 S Main St",
    "sg:city":"La Feria",
    "sg:classifiers":[
        {
            "category":"Shopping",
            "type":"Retail Goods"
        }
    ],
    "sg:phone":"+1 956 797 2421",
    "sg:postcode":"78559",
    "sg:province":"TX",
    "sg:tags":[
        "equipment",
        "irrigation",
        "system"
    ],
    "wof:name":"LA Feria Irrigation District",
    "wof:placetype":"venue"
},
  "geometry": {"coordinates":[-97.824023,26.155963],"type":"Point"}
}