{
  "type": "Feature",
  "properties": {
    "iso:country":"US",
    "sg:address":"1180 8th St",
    "sg:city":"La Feria",
    "sg:classifiers":[
        {
            "category":"Building & Trades",
            "subcategory":"Construction",
            "type":"Services"
        }
    ],
    "sg:phone":"+1 956 797 0381",
    "sg:postcode":"78550",
    "sg:province":"TX",
    "sg:tags":[
        "contractor"
    ],
    "wof:name":"Cable Network Construction",
    "wof:placetype":"venue"
},
  "geometry": {"coordinates":[-97.827028,26.163813],"type":"Point"}
}