{
  "type": "Feature",
  "properties": {
    "iso:country":"US",
    "sg:address":"2102 Martin Luther King Jr Blvd",
    "sg:city":"Killeen",
    "sg:classifiers":[
        {
            "category":"Government",
            "subcategory":"Office",
            "type":"Public Place"
        }
    ],
    "sg:phone":"+1 254 699 0191",
    "sg:postcode":"76543",
    "sg:province":"TX",
    "wof:name":"Texas Dept Of Transportation",
    "wof:placetype":"venue"
},
  "geometry": {"coordinates":[-97.69589499999999,31.089711],"type":"Point"}
}