{
  "type": "Feature",
  "properties": {
    "iso:country":"US",
    "sg:address":"2902 Amesbury Ct",
    "sg:city":"Carrollton",
    "sg:classifiers":[
        {
            "category":"Banks & Credit Unions",
            "subcategory":"Financial Services",
            "type":"Services"
        }
    ],
    "sg:phone":"+1 972 242 9119",
    "sg:postcode":"75007",
    "sg:province":"TX",
    "sg:tags":[
        "trust",
        "management"
    ],
    "wof:name":"McMullen Enterprise",
    "wof:placetype":"venue"
},
  "geometry": {"coordinates":[-96.88883,32.994113],"type":"Point"}
}