{
  "type": "Feature",
  "properties": {
    "iso:country":"US",
    "sg:address":"9355 Long Point Rd",
    "sg:city":"Houston",
    "sg:classifiers":[
        {
            "category":"Real Estate",
            "subcategory":"Real Estate Operator",
            "type":"Services"
        }
    ],
    "sg:phone":"+1 832 715 3587",
    "sg:postcode":"77055",
    "sg:province":"TX",
    "sg:tags":[
        "shopping",
        "center"
    ],
    "wof:name":"Korean Village Shopping Center",
    "wof:placetype":"venue"
},
  "geometry": {"coordinates":[-95.523338,29.798125],"type":"Point"}
}