{
  "type": "Feature",
  "properties": {
    "iso:country":"US",
    "sg:address":"4735 Highland Ave",
    "sg:city":"Beaumont",
    "sg:classifiers":[
        {
            "category":"Organizations",
            "subcategory":"Community Association",
            "type":"Services"
        }
    ],
    "sg:phone":"+1 409 835 2411",
    "sg:postcode":"77705",
    "sg:province":"TX",
    "sg:tags":[
        "fraternal"
    ],
    "wof:name":"Sigma Nu Fraternity",
    "wof:placetype":"venue"
},
  "geometry": {"coordinates":[-94.08526999999999,30.039214],"type":"Point"}
}