{
  "type": "Feature",
  "properties": {
    "iso:country":"US",
    "sg:address":"2704 Rio Grande St",
    "sg:city":"Austin",
    "sg:classifiers":[
        {
            "category":"Shopping",
            "subcategory":"Hobbies, Toys, & Games",
            "type":"Retail Goods"
        }
    ],
    "sg:phone":"+1 512 473 2256",
    "sg:postcode":"78705",
    "sg:province":"TX",
    "sg:tags":[
        "shop",
        "rock"
    ],
    "wof:name":"Natural Treasures",
    "wof:placetype":"venue"
},
  "geometry": {"coordinates":[-97.74435099999999,30.292],"type":"Point"}
}