{
  "type": "Feature",
  "properties": {
    "iso:country":"US",
    "sg:address":"10502 Long River Dr",
    "sg:city":"Sugar Land",
    "sg:classifiers":[
        {
            "category":"Freight",
            "type":"Transportation"
        }
    ],
    "sg:phone":"+1 281 242 1928",
    "sg:postcode":"77478",
    "sg:province":"TX",
    "sg:tags":[
        "operator",
        "local",
        "trucking"
    ],
    "wof:name":"Dans Discount Movers",
    "wof:placetype":"venue"
},
  "geometry": {"coordinates":[-95.636002,29.663237],"type":"Point"}
}