{
  "type": "Feature",
  "properties": {
    "iso:country":"US",
    "sg:address":"7300 Marywood Cir",
    "sg:city":"Austin",
    "sg:classifiers":[
        {
            "category":"Professional",
            "subcategory":"Secretarial Services",
            "type":"Services"
        }
    ],
    "sg:phone":"+1 512 458 4935",
    "sg:postcode":"78723",
    "sg:province":"TX",
    "sg:tags":[
        "reporting",
        "typing"
    ],
    "wof:name":"Chester's Typing",
    "wof:placetype":"venue"
},
  "geometry": {"coordinates":[-97.675701,30.320431],"type":"Point"}
}