{
  "type": "Feature",
  "properties": {
    "iso:country":"US",
    "sg:address":"845 Canyon Crest Dr",
    "sg:city":"Irving",
    "sg:classifiers":[
        {
            "category":"Travel",
            "subcategory":"Hotels & Motels",
            "type":"Entertainment"
        }
    ],
    "sg:phone":"+1 972 506 0203",
    "sg:postcode":"75063",
    "sg:province":"TX",
    "sg:tags":[
        "operation"
    ],
    "wof:name":"Resort Marketing Associates",
    "wof:placetype":"venue"
},
  "geometry": {"coordinates":[-96.95913,32.93608],"type":"Point"}
}