{
  "type": "Feature",
  "properties": {
    "iso:country":"US",
    "sg:address":"9009 Freeland St",
    "sg:city":"Houston",
    "sg:classifiers":[
        {
            "category":"Manufacturing",
            "subcategory":"Toys & Sporting Goods",
            "type":"Manufacturing & Wholesale Goods"
        }
    ],
    "sg:phone":"+1 713 947 9518",
    "sg:postcode":"77075",
    "sg:province":"TX",
    "sg:tags":[
        "house",
        "mfg",
        "mail"
    ],
    "wof:name":"Kapco Specialties",
    "wof:placetype":"venue"
},
  "geometry": {"coordinates":[-95.252872,29.639406],"type":"Point"}
}