{
  "type": "Feature",
  "properties": {
    "iso:country":"US",
    "sg:address":"1248 Pitchfork Rd",
    "sg:city":"Howe",
    "sg:classifiers":[
        {
            "category":"Farming",
            "subcategory":"Livestock Farm",
            "type":"Manufacturing & Wholesale Goods"
        }
    ],
    "sg:phone":"+1 903 813 6095",
    "sg:postcode":"75459",
    "sg:province":"TX",
    "sg:tags":[
        "ranch",
        "cattle"
    ],
    "wof:name":"Powell Farms",
    "wof:placetype":"venue"
},
  "geometry": {"coordinates":[-96.560597,33.486459],"type":"Point"}
}