{
  "type": "Feature",
  "properties": {
    "iso:country":"US",
    "sg:address":"3316 Bee Cave Road Suite C",
    "sg:city":"Austin",
    "sg:classifiers":[
        {
            "category":"Manufacturing",
            "subcategory":"Electronics",
            "type":"Manufacturing & Wholesale Goods"
        }
    ],
    "sg:phone":"+1 512 329 9400",
    "sg:postcode":"87846",
    "sg:province":"TX",
    "sg:website":"http://www.blacksand.com",
    "wof:name":"Black Sand Technologies",
    "wof:placetype":"venue"
},
  "geometry": {"coordinates":[-97.94971099999999,30.316487],"type":"Point"}
}