{
  "type": "Feature",
  "properties": {
    "iso:country":"US",
    "sg:address":"400 Briarwood Ct",
    "sg:city":"Coppell",
    "sg:classifiers":[
        {
            "category":"Professional",
            "subcategory":"Computer Services",
            "type":"Services"
        }
    ],
    "sg:phone":"+1 972 462 8009",
    "sg:postcode":"75019",
    "sg:province":"TX",
    "sg:tags":[
        "related"
    ],
    "wof:name":"Synergy Information Services",
    "wof:placetype":"venue"
},
  "geometry": {"coordinates":[-96.971828,32.975264],"type":"Point"}
}