{
  "type": "Feature",
  "properties": {
    "iso:country":"US",
    "sg:address":"900 Pat Booker Rd",
    "sg:city":"Universal City",
    "sg:classifiers":[
        {
            "category":"Restaurant",
            "type":"Food & Drink"
        }
    ],
    "sg:phone":"+1 210 566 2744",
    "sg:postcode":"78148",
    "sg:province":"TX",
    "sg:tags":[
        "eating"
    ],
    "wof:name":"Mary Jane's Cafe",
    "wof:placetype":"venue"
},
  "geometry": {"coordinates":[-98.294172,29.54949],"type":"Point"}
}