{
  "type": "Feature",
  "properties": {
    "iso:country":"US",
    "sg:address":"6 Oak Grove Cir",
    "sg:city":"Wichita Falls",
    "sg:classifiers":[
        {
            "category":"Professional",
            "type":"Services"
        }
    ],
    "sg:phone":"+1 940 691 6513",
    "sg:postcode":"76310",
    "sg:province":"TX",
    "wof:name":"Go Sha",
    "wof:placetype":"venue"
},
  "geometry": {"coordinates":[-98.567043,33.844803],"type":"Point"}
}