{
  "type": "Feature",
  "properties": {
    "iso:country":"US",
    "sg:address":"1051 N Pacific St",
    "sg:city":"Mineola",
    "sg:classifiers":[
        {
            "category":"Professional",
            "subcategory":"Accounting & Tax Preparation",
            "type":"Services"
        }
    ],
    "sg:phone":"+1 903 569 5011",
    "sg:postcode":"75773",
    "sg:province":"TX",
    "sg:tags":[
        "return"
    ],
    "wof:name":"National Tax Service",
    "wof:placetype":"venue"
},
  "geometry": {"coordinates":[-95.48544699999999,32.672264],"type":"Point"}
}