{
  "type": "Feature",
  "properties": {
    "iso:country":"US",
    "sg:address":"4024 Kirkmeadow Ln",
    "sg:city":"Dallas",
    "sg:classifiers":[
        {
            "category":"Professional",
            "type":"Services"
        }
    ],
    "sg:phone":"+1 972 931 8814",
    "sg:postcode":"75287",
    "sg:province":"TX",
    "wof:name":"Artistic Cllgrphy Design Group",
    "wof:placetype":"venue"
},
  "geometry": {"coordinates":[-96.840738,33.00433],"type":"Point"}
}