{
  "type": "Feature",
  "properties": {
    "iso:country":"US",
    "sg:address":"2705 Vine Ave",
    "sg:city":"Mcallen",
    "sg:classifiers":[
        {
            "category":"Wholesale",
            "subcategory":"Vending Machines",
            "type":"Manufacturing & Wholesale Goods"
        }
    ],
    "sg:phone":"+1 956 687 2031",
    "sg:postcode":"78501",
    "sg:province":"TX",
    "sg:tags":[
        "operator"
    ],
    "wof:name":"Valley Vending A General",
    "wof:placetype":"venue"
},
  "geometry": {"coordinates":[-98.25,26.226823],"type":"Point"}
}