{
  "type": "Feature",
  "properties": {
    "iso:country":"US",
    "sg:address":"2710 Sugar Line Ct",
    "sg:city":"Sugar Land",
    "sg:classifiers":[
        {
            "category":"Manufacturing",
            "subcategory":"Printing",
            "type":"Manufacturing & Wholesale Goods"
        }
    ],
    "sg:phone":"+1 281 980 8000",
    "sg:postcode":"77479",
    "sg:province":"TX",
    "sg:tags":[
        "publishing"
    ],
    "wof:name":"Jacee Publishing",
    "wof:placetype":"venue"
},
  "geometry": {"coordinates":[-95.611923,29.587705],"type":"Point"}
}