{
  "type": "Feature",
  "properties": {
    "iso:country":"US",
    "sg:address":"3010 Lyndon B Johnson Fwy",
    "sg:city":"Farmers Branch",
    "sg:classifiers":[
        {
            "category":"Banks & Credit Unions",
            "subcategory":"Bank",
            "type":"Services"
        }
    ],
    "sg:phone":"+1 972 243 8844",
    "sg:postcode":"75234",
    "sg:province":"TX",
    "sg:tags":[
        "loan",
        "real estate"
    ],
    "wof:name":"Available Mortgage Funding",
    "wof:placetype":"venue"
},
  "geometry": {"coordinates":[-96.87584,32.912336],"type":"Point"}
}