{
  "type": "Feature",
  "properties": {
    "iso:country":"US",
    "sg:address":"1210 Ralphcrest Dr",
    "sg:city":"Houston",
    "sg:classifiers":[
        {
            "category":"Wholesale",
            "subcategory":"Machinery & Supplies",
            "type":"Manufacturing & Wholesale Goods"
        }
    ],
    "sg:phone":"+1 281 449 1461",
    "sg:postcode":"77039",
    "sg:province":"TX",
    "sg:tags":[
        "industrial",
        "electrical",
        "surplus"
    ],
    "wof:name":"Bumpers Industrial Surplus",
    "wof:placetype":"venue"
},
  "geometry": {"coordinates":[-95.368701,29.931261],"type":"Point"}
}