{
  "type": "Feature",
  "properties": {
    "iso:country":"US",
    "sg:address":"310 N Beckham Ave",
    "sg:city":"Tyler",
    "sg:classifiers":[
        {
            "category":"Food & Beverages",
            "subcategory":"Groceries & Convenience Stores",
            "type":"Retail Goods"
        }
    ],
    "sg:phone":"+1 903 526 7700",
    "sg:postcode":"75702",
    "sg:province":"TX",
    "sg:tags":[
        "grocer"
    ],
    "wof:name":"LA Michoacana Meat Market",
    "wof:placetype":"venue"
},
  "geometry": {"coordinates":[-95.29482400000001,32.353515],"type":"Point"}
}