{
  "type": "Feature",
  "properties": {
    "iso:country":"US",
    "sg:address":"4410 S General Bruce Dr",
    "sg:city":"Temple",
    "sg:classifiers":[
        {
            "category":"Autos & Motor Vehicles",
            "subcategory":"Boat Sales",
            "type":"Retail Goods"
        }
    ],
    "sg:phone":"+1 254 773 9931",
    "sg:postcode":"76502",
    "sg:province":"TX",
    "sg:tags":[
        "repair",
        "marine"
    ],
    "wof:name":"Marine Outlet",
    "wof:placetype":"venue"
},
  "geometry": {"coordinates":[-97.396169,31.08816],"type":"Point"}
}