{
  "type": "Feature",
  "properties": {
    "iso:country":"US",
    "sg:address":"5001 Spring Valley Rd",
    "sg:city":"Dallas",
    "sg:classifiers":[
        {
            "category":"Insurance",
            "subcategory":"Health Insurance",
            "type":"Services"
        }
    ],
    "sg:phone":"+1 214 944 3451",
    "sg:postcode":"75244",
    "sg:province":"TX",
    "sg:tags":[
        "carrier"
    ],
    "wof:name":"Principal Life Insurance Co",
    "wof:placetype":"venue"
},
  "geometry": {"coordinates":[-96.825773,32.939597],"type":"Point"}
}