{
  "type": "Feature",
  "properties": {
    "iso:country":"US",
    "sg:address":"200 Ross St",
    "sg:city":"Bryan",
    "sg:classifiers":[
        {
            "category":"Wholesale",
            "subcategory":"Durable Goods & Equipment",
            "type":"Manufacturing & Wholesale Goods"
        }
    ],
    "sg:phone":"+1 979 779 0030",
    "sg:postcode":"77801",
    "sg:province":"TX",
    "wof:name":"American Fire & Safety Inc",
    "wof:placetype":"venue"
},
  "geometry": {"coordinates":[-96.367221,30.655158],"type":"Point"}
}