{
  "type": "Feature",
  "properties": {
    "iso:country":"US",
    "sg:address":"10607 Odyssey Ct",
    "sg:city":"Houston",
    "sg:classifiers":[
        {
            "category":"Social Services",
            "subcategory":"Child Care",
            "type":"Services"
        }
    ],
    "sg:phone":"+1 281 564 2108",
    "sg:postcode":"77099",
    "sg:province":"TX",
    "sg:tags":[
        "day"
    ],
    "wof:name":"Brishays Daycare Activity Ctr",
    "wof:placetype":"venue"
},
  "geometry": {"coordinates":[-95.58758400000001,29.664358],"type":"Point"}
}