{
  "type": "Feature",
  "properties": {
    "iso:country":"US",
    "sg:address":"616 N Red River St",
    "sg:city":"Mexia",
    "sg:classifiers":[
        {
            "category":"Education",
            "subcategory":"School",
            "type":"Public Place"
        }
    ],
    "sg:phone":"+1 254 562 5507",
    "sg:postcode":"76667",
    "sg:province":"TX",
    "wof:name":"Mexia Alternative School",
    "wof:placetype":"venue"
},
  "geometry": {"coordinates":[-96.476866,31.687676],"type":"Point"}
}