{
  "type": "Feature",
  "properties": {
    "iso:country":"US",
    "sg:address":"7676 Hillmont St Ste 325",
    "sg:city":"Houston",
    "sg:classifiers":[
        {
            "category":"Real Estate",
            "subcategory":"Architect",
            "type":"Services"
        }
    ],
    "sg:phone":"+1 713 996 7200",
    "sg:postcode":"77040",
    "sg:province":"TX",
    "wof:name":"Distefano santopetro Architects Inc",
    "wof:placetype":"venue"
},
  "geometry": {"coordinates":[-95.504679,29.843775],"type":"Point"}
}