{
  "type": "Feature",
  "properties": {
    "iso:country":"US",
    "sg:address":"703 N McCoy Blvd",
    "sg:city":"New Boston",
    "sg:classifiers":[
        {
            "category":"Travel",
            "subcategory":"Hotels & Motels",
            "type":"Entertainment"
        }
    ],
    "sg:phone":"+1 903 628 5561",
    "sg:postcode":"75570",
    "sg:province":"TX",
    "sg:tags":[
        "operation"
    ],
    "wof:name":"Bostonian Motor Inn Inc",
    "wof:placetype":"venue"
},
  "geometry": {"coordinates":[-94.409057,33.472133],"type":"Point"}
}