{
  "type": "Feature",
  "properties": {
    "iso:country":"US",
    "sg:address":"4215 Ted Trout Dr",
    "sg:city":"Lufkin",
    "sg:classifiers":[
        {
            "category":"Autos & Motor Vehicles",
            "subcategory":"Auto Supplies",
            "type":"Retail Goods"
        }
    ],
    "sg:phone":"+1 936 637 0126",
    "sg:postcode":"75904",
    "sg:province":"TX",
    "wof:name":"Hedgepath Tires",
    "wof:placetype":"venue"
},
  "geometry": {"coordinates":[-94.792339,31.325885],"type":"Point"}
}