{
  "type": "Feature",
  "properties": {
    "iso:country":"US",
    "sg:address":"6968 Alameda Ave",
    "sg:city":"El Paso",
    "sg:classifiers":[
        {
            "category":"Real Estate",
            "subcategory":"Real Estate Operator",
            "type":"Services"
        }
    ],
    "sg:phone":"+1 915 772 2023",
    "sg:postcode":"79915",
    "sg:province":"TX",
    "sg:tags":[
        "apartment"
    ],
    "wof:name":"Mission Apartments",
    "wof:placetype":"venue"
},
  "geometry": {"coordinates":[-106.399024,31.759261],"type":"Point"}
}