{
  "type": "Feature",
  "properties": {
    "iso:country":"US",
    "sg:address":"5492 Walzem Rd",
    "sg:city":"San Antonio",
    "sg:classifiers":[
        {
            "category":"Professional",
            "subcategory":"Advertising",
            "type":"Services"
        }
    ],
    "sg:phone":"+1 210 646 6245",
    "sg:postcode":"78218",
    "sg:province":"TX",
    "sg:tags":[
        "mailing",
        "shipping"
    ],
    "wof:name":"UPS Store",
    "wof:placetype":"venue"
},
  "geometry": {"coordinates":[-98.381348,29.510209],"type":"Point"}
}