{
  "type": "Feature",
  "properties": {
    "iso:country":"US",
    "sg:address":"6205 Lake June Pl",
    "sg:city":"Dallas",
    "sg:classifiers":[
        {
            "category":"Retail",
            "subcategory":"Repair Shop",
            "type":"Services"
        }
    ],
    "sg:phone":"+1 972 241 0753",
    "sg:postcode":"75217",
    "sg:province":"TX",
    "sg:tags":[
        "equipment",
        "scale"
    ],
    "wof:name":"Belmont Services Inc",
    "wof:placetype":"venue"
},
  "geometry": {"coordinates":[-96.715513,32.73439],"type":"Point"}
}