{
  "type": "Feature",
  "properties": {
    "iso:country":"US",
    "sg:address":"1000 E Anderson Ln",
    "sg:city":"Austin",
    "sg:classifiers":[
        {
            "category":"Banks & Credit Unions",
            "subcategory":"Bank",
            "type":"Services"
        }
    ],
    "sg:phone":"+1 512 873 1900",
    "sg:postcode":"78752",
    "sg:province":"TX",
    "wof:name":"First National Bank",
    "wof:placetype":"venue"
},
  "geometry": {"coordinates":[-97.693181,30.335977],"type":"Point"}
}