{
  "type": "Feature",
  "properties": {
    "iso:country":"US",
    "sg:address":"3801 22nd St",
    "sg:city":"Lubbock",
    "sg:classifiers":[
        {
            "category":"Wholesale",
            "subcategory":"Medical Equipment & Supplies",
            "type":"Manufacturing & Wholesale Goods"
        }
    ],
    "sg:phone":"+1 806 745 1063",
    "sg:postcode":"79410",
    "sg:province":"TX",
    "wof:name":"Area Wide Respiratory Care",
    "wof:placetype":"venue"
},
  "geometry": {"coordinates":[-101.89863,33.575022],"type":"Point"}
}