{
  "type": "Feature",
  "properties": {
    "iso:country":"US",
    "sg:address":"2321 Sherwood Way",
    "sg:city":"San Angelo",
    "sg:classifiers":[
        {
            "category":"Bars & Pubs",
            "type":"Food & Drink"
        }
    ],
    "sg:phone":"+1 325 949 7808",
    "sg:postcode":"76901",
    "sg:province":"TX",
    "wof:name":"Sherwood Lounge",
    "wof:placetype":"venue"
},
  "geometry": {"coordinates":[-100.468176,31.451525],"type":"Point"}
}