{
  "type": "Feature",
  "properties": {
    "iso:country":"US",
    "sg:address":"11740 Jollyville Rd",
    "sg:city":"Austin",
    "sg:classifiers":[
        {
            "category":"Professional",
            "subcategory":"Management & Consulting",
            "type":"Services"
        },
        {
            "category":"Education",
            "subcategory":"Special Training",
            "type":"Public Place"
        }
    ],
    "sg:phone":"+1 512 257 0577",
    "sg:postcode":"78759",
    "sg:province":"TX",
    "sg:tags":[
        "consultant",
        "educational",
        "tutoring"
    ],
    "wof:name":"Outrageous Mastery",
    "wof:placetype":"venue"
},
  "geometry": {"coordinates":[-97.75236700000001,30.419484],"type":"Point"}
}