{
  "type": "Feature",
  "properties": {
    "iso:country":"US",
    "sg:address":"831 S R L Thornton Fwy",
    "sg:city":"Dallas",
    "sg:classifiers":[
        {
            "category":"Building & Trades",
            "subcategory":"Construction",
            "type":"Services"
        }
    ],
    "sg:phone":"+1 866 241 6967",
    "sg:postcode":"75203",
    "sg:province":"TX",
    "sg:tags":[
        "roofing",
        "contractor"
    ],
    "wof:name":"American Eagle Restoration Roofing",
    "wof:placetype":"venue"
},
  "geometry": {"coordinates":[-96.81981500000001,32.74198],"type":"Point"}
}