{
  "type": "Feature",
  "properties": {
    "iso:country":"US",
    "sg:address":"11824 Jollyville Rd Ste 302",
    "sg:city":"Austin",
    "sg:classifiers":[
        {
            "category":"Professional",
            "subcategory":"Lawyer & Legal Services",
            "type":"Services"
        }
    ],
    "sg:phone":"+1 512 827 7548",
    "sg:postcode":"78759",
    "sg:province":"TX",
    "sg:tags":[
        "divorce",
        "law",
        "family"
    ],
    "wof:name":"Tray Gober",
    "wof:placetype":"venue"
},
  "geometry": {"coordinates":[-97.756074,30.422422],"type":"Point"}
}