{
  "type": "Feature",
  "properties": {
    "iso:country":"US",
    "sg:address":"5520 Evers Rd",
    "sg:city":"San Antonio",
    "sg:classifiers":[
        {
            "category":"Restaurant",
            "type":"Food & Drink"
        }
    ],
    "sg:phone":"+1 210 520 6800",
    "sg:postcode":"78238",
    "sg:province":"TX",
    "sg:tags":[
        "eating"
    ],
    "wof:name":"Thai Taste",
    "wof:placetype":"venue"
},
  "geometry": {"coordinates":[-98.596699,29.487785],"type":"Point"}
}