{
  "type": "Feature",
  "properties": {
    "iso:country":"US",
    "sg:address":"723 N Upper Broadway St",
    "sg:city":"Corpus Christi",
    "sg:classifiers":[
        {
            "category":"Government",
            "subcategory":"Office",
            "type":"Public Place"
        }
    ],
    "sg:phone":"+1 361 884 0903",
    "sg:postcode":"78401",
    "sg:province":"TX",
    "sg:tags":[
        "state",
        "program"
    ],
    "wof:name":"Moran-Gulf Shipping Agency",
    "wof:placetype":"venue"
},
  "geometry": {"coordinates":[-97.396366,27.798029],"type":"Point"}
}