{
  "type": "Feature",
  "properties": {
    "iso:country":"US",
    "sg:address":"4243 Co Rd 780",
    "sg:city":"Sweeny",
    "sg:classifiers":[
        {
            "category":"Freight",
            "type":"Transportation"
        }
    ],
    "sg:phone":"+1 979 647 4287",
    "sg:postcode":"77480",
    "sg:province":"TX",
    "sg:tags":[
        "operator",
        "local",
        "storage",
        "trucking"
    ],
    "wof:name":"Orchard Trucking",
    "wof:placetype":"venue"
},
  "geometry": {"coordinates":[-95.744158,29.111495],"type":"Point"}
}