{
  "type": "Feature",
  "properties": {
    "iso:country":"US",
    "sg:address":"3800 Anglin Dr",
    "sg:city":"Fort Worth",
    "sg:classifiers":[
        {
            "category":"Education",
            "subcategory":"School",
            "type":"Public Place"
        }
    ],
    "sg:phone":"+1 817 531 6390",
    "sg:postcode":"76119",
    "sg:province":"TX",
    "wof:name":"A M Pate Elementary School",
    "wof:placetype":"venue"
},
  "geometry": {"coordinates":[-97.252073,32.707353],"type":"Point"}
}