{
  "type": "Feature",
  "properties": {
    "iso:country":"US",
    "sg:address":"2826 Potosi Rd",
    "sg:city":"Abilene",
    "sg:classifiers":[
        {
            "category":"Organizations",
            "subcategory":"Religious Organization",
            "type":"Services"
        }
    ],
    "sg:phone":"+1 325 529 3227",
    "sg:postcode":"79602",
    "sg:province":"TX",
    "sg:tags":[
        "church"
    ],
    "wof:name":"Potosi Baptist Church",
    "wof:placetype":"venue"
},
  "geometry": {"coordinates":[-99.657026,32.334848],"type":"Point"}
}