{
  "type": "Feature",
  "properties": {
    "iso:country":"US",
    "sg:address":"1566 Sheffield Blvd",
    "sg:city":"Houston",
    "sg:classifiers":[
        {
            "category":"Retail",
            "subcategory":"Auto Repair",
            "type":"Services"
        }
    ],
    "sg:phone":"+1 713 451 3811",
    "sg:postcode":"77015",
    "sg:province":"TX",
    "sg:tags":[
        "automotive"
    ],
    "wof:name":"T C B Wrecker",
    "wof:placetype":"venue"
},
  "geometry": {"coordinates":[-95.2007,29.761055],"type":"Point"}
}