{
  "type": "Feature",
  "properties": {
    "iso:country":"US",
    "sg:address":"4900 Gladeview Dr",
    "sg:city":"Austin",
    "sg:classifiers":[
        {
            "category":"Bus Charters",
            "type":"Transportation"
        }
    ],
    "sg:phone":"+1 512 442 8300",
    "sg:postcode":"78745",
    "sg:province":"TX",
    "sg:tags":[
        "buses-charter",
        "rental"
    ],
    "wof:name":"Millennium Coaches",
    "wof:placetype":"venue"
},
  "geometry": {"coordinates":[-97.789942,30.220132],"type":"Point"}
}