{
  "type": "Feature",
  "properties": {
    "iso:country":"US",
    "sg:address":"3939 Fredericksburg Rd",
    "sg:city":"San Antonio",
    "sg:classifiers":[
        {
            "category":"Professional",
            "subcategory":"Business Services",
            "type":"Services"
        }
    ],
    "sg:phone":"+1 210 737 9558",
    "sg:postcode":"78201",
    "sg:province":"TX",
    "wof:name":"NRC Multi Business Associates",
    "wof:placetype":"venue"
},
  "geometry": {"coordinates":[-98.543971,29.482096],"type":"Point"}
}