{
  "type": "Feature",
  "properties": {
    "iso:country":"US",
    "sg:address":"7529 Canyon Dr",
    "sg:city":"Amarillo",
    "sg:classifiers":[
        {
            "category":"Retail",
            "subcategory":"Repair Shop",
            "type":"Services"
        },
        {
            "category":"Wholesale",
            "subcategory":"Photographic Equipment",
            "type":"Manufacturing & Wholesale Goods"
        }
    ],
    "sg:phone":"+1 806 351 0280",
    "sg:postcode":"79110",
    "sg:province":"TX",
    "sg:tags":[
        "stereo",
        "audio",
        "commercial"
    ],
    "wof:name":"Norris Audio Video Systems",
    "wof:placetype":"venue"
},
  "geometry": {"coordinates":[-101.89989199999999,35.130706],"type":"Point"}
}