{
  "type": "Feature",
  "properties": {
    "iso:country":"US",
    "sg:address":"2244 Old Mill Rd",
    "sg:city":"Carrollton",
    "sg:classifiers":[
        {
            "category":"Health Services",
            "subcategory":"Clinic",
            "type":"Services"
        },
        {
            "category":"Wholesale",
            "subcategory":"Wine & Distilled Alcoholic Beverages",
            "type":"Manufacturing & Wholesale Goods"
        }
    ],
    "sg:phone":"+1 972 416 0930",
    "sg:postcode":"75007",
    "sg:province":"TX",
    "sg:tags":[
        "information",
        "treatment",
        "alcoholism",
        "liquors-wholesale"
    ],
    "wof:name":"Friendly Liquor",
    "wof:placetype":"venue"
},
  "geometry": {"coordinates":[-96.873345,32.989788],"type":"Point"}
}