{
  "type": "Feature",
  "properties": {
    "iso:country":"US",
    "sg:address":"11901 Pavilion Boulevard",
    "sg:city":"Austin",
    "sg:classifiers":[
        {
            "category":"Travel",
            "subcategory":"Hotels & Motels",
            "type":"Entertainment"
        }
    ],
    "sg:phone":"+1 512 258 3556",
    "sg:postcode":"78759",
    "sg:province":"TX",
    "sg:website":"http://www.staystudio6.com",
    "wof:name":"Studio 6",
    "wof:placetype":"venue"
},
  "geometry": {"coordinates":[-97.755042,30.425221],"type":"Point"}
}