{
  "type": "Feature",
  "properties": {
    "iso:country":"US",
    "sg:address":"10501 South Dr",
    "sg:city":"Houston",
    "sg:classifiers":[
        {
            "category":"Insurance",
            "subcategory":"Insurance Agent",
            "type":"Services"
        }
    ],
    "sg:phone":"+1 281 564 0209",
    "sg:postcode":"77099",
    "sg:province":"TX",
    "wof:name":"Angels CNA",
    "wof:placetype":"venue"
},
  "geometry": {"coordinates":[-95.564527,29.667035],"type":"Point"}
}