{
  "type": "Feature",
  "properties": {
    "iso:country":"US",
    "sg:address":"1837 Van Buren Cir",
    "sg:city":"Arlington",
    "sg:classifiers":[
        {
            "category":"Professional",
            "subcategory":"Business Services",
            "type":"Services"
        }
    ],
    "sg:phone":"+1 817 459 3409",
    "sg:postcode":"76011",
    "sg:province":"TX",
    "wof:name":"Queen Solutions",
    "wof:placetype":"venue"
},
  "geometry": {"coordinates":[-97.109829,32.763161],"type":"Point"}
}