{
  "type": "Feature",
  "properties": {
    "iso:country":"US",
    "sg:address":"706 S McCarty Ave",
    "sg:city":"Eagle Lake",
    "sg:classifiers":[
        {
            "category":"Restaurant",
            "type":"Food & Drink"
        }
    ],
    "sg:phone":"+1 979 234 7274",
    "sg:postcode":"77434",
    "sg:province":"TX",
    "sg:tags":[
        "out"
    ],
    "wof:name":"C J's",
    "wof:placetype":"venue"
},
  "geometry": {"coordinates":[-96.339552,29.584685],"type":"Point"}
}