{
  "type": "Feature",
  "properties": {
    "iso:country":"US",
    "sg:address":"1305 Haskell St",
    "sg:city":"Wellington",
    "sg:classifiers":[
        {
            "category":"Real Estate",
            "subcategory":"Real Estate Operator",
            "type":"Services"
        }
    ],
    "sg:phone":"+1 806 447 5064",
    "sg:postcode":"79095",
    "sg:province":"TX",
    "sg:tags":[
        "apartment"
    ],
    "wof:name":"Xit Rental Incorportation",
    "wof:placetype":"venue"
},
  "geometry": {"coordinates":[-100.22252,34.851118],"type":"Point"}
}