{
  "type": "Feature",
  "properties": {
    "iso:country":"US",
    "sg:address":"1626 US Hwy 287R Bus",
    "sg:city":"Waxahachie",
    "sg:classifiers":[
        {
            "category":"Health Services",
            "subcategory":"Clinic",
            "type":"Services"
        }
    ],
    "sg:phone":"+1 972 935 9450",
    "sg:postcode":"75165",
    "sg:province":"TX",
    "sg:tags":[
        "home",
        "care"
    ],
    "wof:name":"Bethany Home Health",
    "wof:placetype":"venue"
},
  "geometry": {"coordinates":[-96.865359,32.399386],"type":"Point"}
}