{
  "type": "Feature",
  "properties": {
    "iso:country":"US",
    "sg:address":"611 James St",
    "sg:city":"Tomball",
    "sg:classifiers":[
        {
            "category":"Real Estate",
            "subcategory":"Real Estate Operator",
            "type":"Services"
        }
    ],
    "sg:phone":"+1 281 255 3646",
    "sg:postcode":"77375",
    "sg:province":"TX",
    "sg:tags":[
        "building",
        "apartment"
    ],
    "wof:name":"Tomball Sq APT",
    "wof:placetype":"venue"
},
  "geometry": {"coordinates":[-95.616895,30.091336],"type":"Point"}
}