{
  "type": "Feature",
  "properties": {
    "iso:country":"US",
    "sg:address":"900 S State St",
    "sg:city":"Bronte",
    "sg:classifiers":[
        {
            "category":"Social Services",
            "subcategory":"Job Training",
            "type":"Services"
        }
    ],
    "sg:phone":"+1 325 473 3621",
    "sg:postcode":"76933",
    "sg:province":"TX",
    "sg:tags":[
        "rehabilitation"
    ],
    "wof:name":"Bronte Health & Rehab Ctr",
    "wof:placetype":"venue"
},
  "geometry": {"coordinates":[-100.29253799999999,31.8796],"type":"Point"}
}