{
  "type": "Feature",
  "properties": {
    "iso:country":"US",
    "sg:address":"1801 Jb Jackson Jr Blvd",
    "sg:city":"Dallas",
    "sg:classifiers":[
        {
            "category":"Personal",
            "subcategory":"Barber",
            "type":"Services"
        }
    ],
    "sg:phone":"+1 214 428 3803",
    "sg:postcode":"75210",
    "sg:province":"TX",
    "wof:name":"A Geez Hair Care Center",
    "wof:placetype":"venue"
},
  "geometry": {"coordinates":[-96.760091,32.771825],"type":"Point"}
}