{
  "type": "Feature",
  "properties": {
    "iso:country":"US",
    "sg:address":"4619 Ross Ave",
    "sg:city":"Dallas",
    "sg:classifiers":[
        {
            "category":"Shopping",
            "subcategory":"Clothing, Apparel, & Fashions",
            "type":"Retail Goods"
        }
    ],
    "sg:phone":"+1 214 887 6657",
    "sg:postcode":"75204",
    "sg:province":"TX",
    "wof:name":"Harvey Enterprises",
    "wof:placetype":"venue"
},
  "geometry": {"coordinates":[-96.778752,32.804047],"type":"Point"}
}