{
  "type": "Feature",
  "properties": {
    "iso:country":"US",
    "sg:address":"8470 Gulf Fwy",
    "sg:city":"Houston",
    "sg:classifiers":[
        {
            "category":"Personal",
            "subcategory":"Barber",
            "type":"Services"
        }
    ],
    "sg:phone":"+1 713 649 7600",
    "sg:postcode":"77017",
    "sg:province":"TX",
    "wof:name":"Kutting Edge Barber Shop",
    "wof:placetype":"venue"
},
  "geometry": {"coordinates":[-95.264921,29.673343],"type":"Point"}
}