{
  "type": "Feature",
  "properties": {
    "iso:country":"US",
    "sg:address":"900 W State Highway 114",
    "sg:city":"Grapevine",
    "sg:phone":"+1 817 251 0255",
    "sg:postcode":"76051",
    "sg:province":"TX",
    "sg:website":"http://www.lamadeleine.com",
    "wof:name":"la Madeleine",
    "wof:placetype":"venue"
},
  "geometry": {"coordinates":[-97.086303,32.924791],"type":"Point"}
}