{
  "type": "Feature",
  "properties": {
    "iso:country":"US",
    "sg:address":"205 Valentine St",
    "sg:city":"Tyler",
    "sg:classifiers":[
        {
            "category":"Retail",
            "subcategory":"Auto Repair",
            "type":"Services"
        }
    ],
    "sg:phone":"+1 903 526 7573",
    "sg:postcode":"75702",
    "sg:province":"TX",
    "sg:tags":[
        "repairing",
        "automobile",
        "general"
    ],
    "wof:name":"Lollar's Garage",
    "wof:placetype":"venue"
},
  "geometry": {"coordinates":[-95.299421,32.359079],"type":"Point"}
}