{
  "type": "Feature",
  "properties": {
    "iso:country":"US",
    "sg:address":"421 E Main St",
    "sg:city":"Bellville",
    "sg:classifiers":[
        {
            "category":"Restaurant",
            "type":"Food & Drink"
        },
        {
            "category":"Ice Cream",
            "type":"Food & Drink"
        }
    ],
    "sg:menulink":"http://www.allmenus.com/tx/bellville/162099-dairy-queen/menu/",
    "sg:phone":"+1 979 865 3661",
    "sg:postcode":"77418",
    "sg:province":"TX",
    "sg:tags":[
        "burger",
        "american",
        "ice",
        "cream"
    ],
    "wof:name":"Dairy Queen",
    "wof:placetype":"venue"
},
  "geometry": {"coordinates":[-96.254116,29.949124],"type":"Point"}
}