{
  "type": "Feature",
  "properties": {
    "iso:country":"US",
    "sg:address":"144 Old US Hwy 90 W",
    "sg:city":"San Antonio",
    "sg:classifiers":[
        {
            "category":"Professional",
            "subcategory":"Accounting & Tax Preparation",
            "type":"Services"
        }
    ],
    "sg:phone":"+1 210 438 9954",
    "sg:postcode":"78237",
    "sg:province":"TX",
    "sg:tags":[
        "return",
        "filing"
    ],
    "wof:name":"Tax Busters",
    "wof:placetype":"venue"
},
  "geometry": {"coordinates":[-98.56164200000001,29.431183],"type":"Point"}
}