{
  "type": "Feature",
  "properties": {
    "iso:country":"US",
    "sg:address":"614 County Road 186 E",
    "sg:city":"Kilgore",
    "sg:classifiers":[
        {
            "category":"Building & Trades",
            "subcategory":"Landscaping Services",
            "type":"Services"
        }
    ],
    "sg:phone":"+1 903 984 0785",
    "sg:postcode":"75662",
    "sg:province":"TX",
    "sg:tags":[
        "tree"
    ],
    "wof:name":"Overman Tree Service",
    "wof:placetype":"venue"
},
  "geometry": {"coordinates":[-94.85575,32.35758],"type":"Point"}
}