{
  "type": "Feature",
  "properties": {
    "iso:country":"US",
    "sg:address":"5420 Highlands Dr",
    "sg:city":"Mc Kinney",
    "sg:classifiers":[
        {
            "category":"Building & Trades",
            "subcategory":"Landscaping Services",
            "type":"Services"
        }
    ],
    "sg:phone":"+1 214 908 1010",
    "sg:postcode":"75070",
    "sg:province":"TX",
    "sg:tags":[
        "landscape",
        "contractor"
    ],
    "wof:name":"Commercial Landscape Svc",
    "wof:placetype":"venue"
},
  "geometry": {"coordinates":[-96.68162,33.16378],"type":"Point"}
}