{
  "type": "Feature",
  "properties": {
    "iso:country":"US",
    "sg:address":"206 Heathbrook Ln",
    "sg:city":"Houston",
    "sg:classifiers":[
        {
            "category":"Professional",
            "type":"Services"
        }
    ],
    "sg:phone":"+1 281 599 8671",
    "sg:postcode":"77094",
    "sg:province":"TX",
    "wof:name":"L & M Numerical Services",
    "wof:placetype":"venue"
},
  "geometry": {"coordinates":[-95.70135399999999,29.78144],"type":"Point"}
}