{
  "type": "Feature",
  "properties": {
    "iso:country":"US",
    "sg:address":"3020 Simondale Dr",
    "sg:city":"Fort Worth",
    "sg:classifiers":[
        {
            "category":"Shopping",
            "subcategory":"Used Merchandise",
            "type":"Retail Goods"
        }
    ],
    "sg:phone":"+1 817 923 4994",
    "sg:postcode":"76109",
    "sg:province":"TX",
    "wof:name":"Something Special Antiques",
    "wof:placetype":"venue"
},
  "geometry": {"coordinates":[-97.372372,32.710141],"type":"Point"}
}