{
  "type": "Feature",
  "properties": {
    "iso:country":"US",
    "sg:address":"5817 Lindenshire Ln",
    "sg:city":"Dallas",
    "sg:classifiers":[
        {
            "category":"Real Estate",
            "subcategory":"Real Estate Agent",
            "type":"Services"
        }
    ],
    "sg:phone":"+1 972 387 0708",
    "sg:postcode":"75230",
    "sg:province":"TX",
    "sg:tags":[
        "investment"
    ],
    "wof:name":"Owr Investments Inc",
    "wof:placetype":"venue"
},
  "geometry": {"coordinates":[-96.809825,32.91272],"type":"Point"}
}