{
  "type": "Feature",
  "properties": {
    "iso:country":"US",
    "sg:address":"110 Erwin St",
    "sg:city":"Palestine",
    "sg:classifiers":[
        {
            "category":"Retail",
            "subcategory":"Repair Shop",
            "type":"Services"
        },
        {
            "category":"Professional",
            "subcategory":"Detective & Security Services",
            "type":"Services"
        }
    ],
    "sg:phone":"+1 903 727 2727",
    "sg:postcode":"75801",
    "sg:province":"TX",
    "sg:tags":[
        "skip",
        "tracing",
        "bail",
        "bond"
    ],
    "wof:name":"Ace Bailbonds",
    "wof:placetype":"venue"
},
  "geometry": {"coordinates":[-95.631733,31.764376],"type":"Point"}
}