{
  "type": "Feature",
  "properties": {
    "iso:country":"US",
    "sg:address":"221 N Main St",
    "sg:city":"Fort Stockton",
    "sg:classifiers":[
        {
            "category":"Banks & Credit Unions",
            "subcategory":"Financial Services",
            "type":"Services"
        }
    ],
    "sg:phone":"+1 432 336 8665",
    "sg:postcode":"79735",
    "sg:province":"TX",
    "sg:tags":[
        "investor"
    ],
    "wof:name":"Fiesta Investments Inc",
    "wof:placetype":"venue"
},
  "geometry": {"coordinates":[-102.87923000000001,30.88707],"type":"Point"}
}