{
  "type": "Feature",
  "properties": {
    "iso:country":"US",
    "sg:address":"2537 Cherry Blossom Ln",
    "sg:city":"Bedford",
    "sg:classifiers":[
        {
            "category":"Social Services",
            "type":"Services"
        }
    ],
    "sg:phone":"+1 817 799 0113",
    "sg:postcode":"76021",
    "sg:province":"TX",
    "sg:tags":[
        "organization",
        "welfare"
    ],
    "wof:name":"Unreached Peoples MIS",
    "wof:placetype":"venue"
},
  "geometry": {"coordinates":[-97.10924300000001,32.849347],"type":"Point"}
}