{
  "type": "Feature",
  "properties": {
    "iso:country":"US",
    "sg:address":"3826 Gable Grove Ln",
    "sg:city":"Katy",
    "sg:classifiers":[
        {
            "category":"Real Estate",
            "subcategory":"Real Estate Agent",
            "type":"Services"
        }
    ],
    "sg:phone":"+1 281 392 1969",
    "sg:postcode":"77494",
    "sg:province":"TX",
    "wof:name":"L R Realty & Associates",
    "wof:placetype":"venue"
},
  "geometry": {"coordinates":[-95.78397,29.723035],"type":"Point"}
}