{
  "type": "Feature",
  "properties": {
    "iso:country":"US",
    "sg:address":"617 Main St",
    "sg:city":"Junction",
    "sg:classifiers":[
        {
            "category":"Personal",
            "subcategory":"Beauty Salon",
            "type":"Services"
        }
    ],
    "sg:phone":"+1 325 446 2431",
    "sg:postcode":"76849",
    "sg:province":"TX",
    "wof:name":"Top Arts Beauty Shop",
    "wof:placetype":"venue"
},
  "geometry": {"coordinates":[-99.767325,30.489249],"type":"Point"}
}