{
  "type": "Feature",
  "properties": {
    "iso:country":"US",
    "sg:address":"2200 Jefferson St",
    "sg:city":"Houston",
    "sg:classifiers":[
        {
            "category":"Restaurant",
            "type":"Food & Drink"
        }
    ],
    "sg:phone":"+1 713 236 8868",
    "sg:postcode":"77003",
    "sg:province":"TX",
    "sg:tags":[
        "eating"
    ],
    "sg:website":"www.kimphung.com",
    "wof:name":"Kim Phung Restaurant",
    "wof:placetype":"venue"
},
  "geometry": {"coordinates":[-95.3592,29.744499],"type":"Point"}
}