{
  "type": "Feature",
  "properties": {
    "iso:country":"US",
    "sg:address":"22616 Loop 494",
    "sg:city":"Kingwood",
    "sg:classifiers":[
        {
            "category":"Real Estate",
            "subcategory":"Real Estate Services",
            "type":"Services"
        },
        {
            "category":"Real Estate",
            "subcategory":"Real Estate Agent",
            "type":"Services"
        }
    ],
    "sg:phone":"+1 281 359 5881",
    "sg:postcode":"77339",
    "sg:province":"TX",
    "sg:tags":[
        "buyer",
        "management",
        "broker"
    ],
    "wof:name":"Flags Real Estate",
    "wof:placetype":"venue"
},
  "geometry": {"coordinates":[-95.252095,30.039673],"type":"Point"}
}