{
  "type": "Feature",
  "properties": {
    "iso:country":"US",
    "sg:address":"2438 1st St",
    "sg:city":"Rosenberg",
    "sg:classifiers":[
        {
            "category":"Professional",
            "subcategory":"Credit Reporting & Collection",
            "type":"Services"
        }
    ],
    "sg:phone":"+1 832 595 8883",
    "sg:postcode":"77471",
    "sg:province":"TX",
    "sg:tags":[
        "agency"
    ],
    "wof:name":"Van Gundy May & Dean",
    "wof:placetype":"venue"
},
  "geometry": {"coordinates":[-95.808488,29.542302],"type":"Point"}
}