{
  "type": "Feature",
  "properties": {
    "iso:country":"US",
    "sg:address":"318 4th St",
    "sg:city":"Graham",
    "sg:classifiers":[
        {
            "category":"Retail",
            "subcategory":"Auto Repair",
            "type":"Services"
        }
    ],
    "sg:phone":"+1 940 549 3302",
    "sg:postcode":"76450",
    "sg:province":"TX",
    "sg:tags":[
        "repairing",
        "automobile",
        "radiator"
    ],
    "wof:name":"Golden's Radiator Shop",
    "wof:placetype":"venue"
},
  "geometry": {"coordinates":[-98.59437699999999,33.106989],"type":"Point"}
}