{
  "type": "Feature",
  "properties": {
    "iso:country":"US",
    "sg:address":"2419 Ellis St",
    "sg:city":"Dallas",
    "sg:classifiers":[
        {
            "category":"Wholesale",
            "subcategory":"Computers",
            "type":"Manufacturing & Wholesale Goods"
        }
    ],
    "sg:phone":"+1 214 459 0251",
    "sg:postcode":"75204",
    "sg:province":"TX",
    "wof:name":"Amerasiaenterprises Inc",
    "wof:placetype":"venue"
},
  "geometry": {"coordinates":[-96.796904,32.799489],"type":"Point"}
}