{
  "type": "Feature",
  "properties": {
    "iso:country":"US",
    "sg:address":"240 E Labadie Ave",
    "sg:city":"De Leon",
    "sg:classifiers":[
        {
            "category":"Retail",
            "subcategory":"Auto Repair",
            "type":"Services"
        }
    ],
    "sg:phone":"+1 254 893 2216",
    "sg:postcode":"76444",
    "sg:province":"TX",
    "sg:tags":[
        "body",
        "automobile",
        "painting"
    ],
    "wof:name":"Randy's Body Shop",
    "wof:placetype":"venue"
},
  "geometry": {"coordinates":[-98.53585,32.107689],"type":"Point"}
}