{
  "type": "Feature",
  "properties": {
    "iso:country":"US",
    "sg:address":"13018 Woodforest Blvd",
    "sg:city":"Houston",
    "sg:classifiers":[
        {
            "category":"Personal",
            "subcategory":"Beauty Salon",
            "type":"Services"
        }
    ],
    "sg:phone":"+1 713 453 1177",
    "sg:postcode":"77015",
    "sg:province":"TX",
    "sg:tags":[
        "hair"
    ],
    "wof:name":"Avalon Beauty Salon",
    "wof:placetype":"venue"
},
  "geometry": {"coordinates":[-95.194237,29.793617],"type":"Point"}
}