{
  "type": "Feature",
  "properties": {
    "iso:country":"US",
    "sg:address":"17635 Henderson Pass",
    "sg:city":"San Antonio",
    "sg:classifiers":[
        {
            "category":"Real Estate",
            "subcategory":"Real Estate Operator",
            "type":"Services"
        }
    ],
    "sg:phone":"+1 210 481 9500",
    "sg:postcode":"78232",
    "sg:province":"TX",
    "sg:tags":[
        "apartment"
    ],
    "wof:name":"Corporate Apartment Network",
    "wof:placetype":"venue"
},
  "geometry": {"coordinates":[-98.468475,29.602889],"type":"Point"}
}