{
  "type": "Feature",
  "properties": {
    "iso:country":"US",
    "sg:address":"6422 N Shepherd Dr",
    "sg:city":"Houston",
    "sg:classifiers":[
        {
            "category":"Autos & Motor Vehicles",
            "subcategory":"Automobile Sales",
            "type":"Retail Goods"
        }
    ],
    "sg:phone":"+1 713 694 7474",
    "sg:postcode":"77091",
    "sg:province":"TX",
    "sg:tags":[
        "car",
        "dealer"
    ],
    "wof:name":"Check In Auto",
    "wof:placetype":"venue"
},
  "geometry": {"coordinates":[-95.412469,29.857727],"type":"Point"}
}