{
  "type": "Feature",
  "properties": {
    "iso:country":"US",
    "sg:address":"1126 E Washington St",
    "sg:city":"Brownsville",
    "sg:classifiers":[
        {
            "category":"Restaurant",
            "type":"Food & Drink"
        }
    ],
    "sg:phone":"+1 956 544 2628",
    "sg:postcode":"78520",
    "sg:province":"TX",
    "sg:tags":[
        "eating"
    ],
    "wof:name":"Rupledge Hamburgers",
    "wof:placetype":"venue"
},
  "geometry": {"coordinates":[-97.497647,25.901834],"type":"Point"}
}