{
  "type": "Feature",
  "properties": {
    "iso:country":"US",
    "sg:address":"7711 Louis Pasteur Ct",
    "sg:city":"San Antonio",
    "sg:classifiers":[
        {
            "category":"Health Services",
            "subcategory":"Doctor",
            "type":"Services"
        }
    ],
    "sg:phone":"+1 210 692 3636",
    "sg:postcode":"78229",
    "sg:province":"TX",
    "sg:tags":[
        "medical"
    ],
    "wof:name":"Cavazos Bernard R Jr",
    "wof:placetype":"venue"
},
  "geometry": {"coordinates":[-98.566402,29.509691],"type":"Point"}
}