{
  "type": "Feature",
  "properties": {
    "iso:country":"US",
    "sg:address":"3300 Douglas Ave",
    "sg:city":"Dallas",
    "sg:classifiers":[
        {
            "category":"Health Services",
            "subcategory":"Dentist",
            "type":"Services"
        }
    ],
    "sg:phone":"+1 214 528 1587",
    "sg:postcode":"75219",
    "sg:province":"TX",
    "wof:name":"ABC Dental Center",
    "wof:placetype":"venue"
},
  "geometry": {"coordinates":[-96.812202,32.813999],"type":"Point"}
}