{
  "type": "Feature",
  "properties": {
    "iso:country":"US",
    "sg:address":"17202 US Hwy 59",
    "sg:city":"Humble",
    "sg:classifiers":[
        {
            "category":"Bars & Pubs",
            "type":"Food & Drink"
        }
    ],
    "sg:phone":"+1 281 446 1611",
    "sg:postcode":"77396",
    "sg:province":"TX",
    "sg:tags":[
        "drinking"
    ],
    "wof:name":"Urbies Lounge",
    "wof:placetype":"venue"
},
  "geometry": {"coordinates":[-95.282009,29.970143],"type":"Point"}
}