{
  "type": "Feature",
  "properties": {
    "iso:country":"US",
    "sg:address":"402 Old Gin Rd",
    "sg:city":"Ennis",
    "sg:classifiers":[
        {
            "category":"Building & Trades",
            "subcategory":"Construction",
            "type":"Services"
        }
    ],
    "sg:phone":"+1 972 846 9911",
    "sg:postcode":"75119",
    "sg:province":"TX",
    "sg:tags":[
        "contractor"
    ],
    "wof:name":"Z - Handyman",
    "wof:placetype":"venue"
},
  "geometry": {"coordinates":[-96.574068,32.461676],"type":"Point"}
}