{
  "type": "Feature",
  "properties": {
    "iso:country":"US",
    "sg:address":"200 Bear Creek Dr",
    "sg:city":"Euless",
    "sg:classifiers":[
        {
            "category":"Real Estate",
            "subcategory":"Real Estate Operator",
            "type":"Services"
        }
    ],
    "sg:phone":"+1 817 267 7666",
    "sg:postcode":"76039",
    "sg:province":"TX",
    "sg:tags":[
        "building",
        "apartment"
    ],
    "wof:name":"Wildwood APT",
    "wof:placetype":"venue"
},
  "geometry": {"coordinates":[-97.08474,32.872105],"type":"Point"}
}