{
  "type": "Feature",
  "properties": {
    "iso:country":"US",
    "sg:address":"1670 S Zarzamora",
    "sg:city":"San Antonio",
    "sg:classifiers":[
        {
            "category":"Autos & Motor Vehicles",
            "subcategory":"Auto Supplies",
            "type":"Retail Goods"
        }
    ],
    "sg:phone":"+1 210 226 2664",
    "sg:postcode":"78207",
    "sg:province":"TX",
    "sg:tags":[
        "parts"
    ],
    "wof:name":"Autozone",
    "wof:placetype":"venue"
},
  "geometry": {"coordinates":[-98.529312,29.4093],"type":"Point"}
}