{
  "type": "Feature",
  "properties": {
    "iso:country":"US",
    "sg:address":"8001 Ferndale Dr",
    "sg:city":"Fort Worth",
    "sg:classifiers":[
        {
            "category":"Professional",
            "subcategory":"Business Services",
            "type":"Services"
        }
    ],
    "sg:phone":"+1 817 244 1542",
    "sg:postcode":"76116",
    "sg:province":"TX",
    "wof:name":"Mfg Estimator",
    "wof:placetype":"venue"
},
  "geometry": {"coordinates":[-97.454228,32.713625],"type":"Point"}
}