{
  "type": "Feature",
  "properties": {
    "iso:country":"US",
    "sg:address":"3705 Vaucluse Dr",
    "sg:city":"Euless",
    "sg:classifiers":[
        {
            "category":"Building & Trades",
            "subcategory":"Landscaping Services",
            "type":"Services"
        }
    ],
    "sg:phone":"+1 817 684 9949",
    "sg:postcode":"76040",
    "sg:province":"TX",
    "sg:tags":[
        "lawn",
        "maintenance",
        "grounds"
    ],
    "wof:name":"Xxtreme Lawn Care Svc",
    "wof:placetype":"venue"
},
  "geometry": {"coordinates":[-97.072604,32.816882],"type":"Point"}
}