{
  "type": "Feature",
  "properties": {
    "iso:country":"US",
    "sg:address":"5123 Red River Dr",
    "sg:city":"Arlington",
    "sg:classifiers":[
        {
            "category":"Retail",
            "subcategory":"Photofinishing",
            "type":"Services"
        },
        {
            "category":"Professional",
            "subcategory":"Art Services",
            "type":"Services"
        },
        {
            "category":"Personal",
            "type":"Services"
        }
    ],
    "sg:phone":"+1 817 478 5905",
    "sg:postcode":"76017",
    "sg:province":"TX",
    "sg:tags":[
        "videography",
        "photo",
        "photography",
        "retouching",
        "restoration",
        "wedding"
    ],
    "sg:website":"http://www.lrphotos.com",
    "wof:name":"Larry Reynolds Photography",
    "wof:placetype":"venue"
},
  "geometry": {"coordinates":[-97.195852,32.664388],"type":"Point"}
}