{
  "type": "Feature",
  "properties": {
    "iso:country":"US",
    "sg:address":"2070 US Hwy 79",
    "sg:city":"Palestine",
    "sg:classifiers":[
        {
            "category":"Building & Trades",
            "subcategory":"Construction",
            "type":"Services"
        }
    ],
    "sg:phone":"+1 903 538 2505",
    "sg:postcode":"75801",
    "sg:province":"TX",
    "sg:tags":[
        "field",
        "oil",
        "contractor"
    ],
    "wof:name":"Peak USA Energy Svc",
    "wof:placetype":"venue"
},
  "geometry": {"coordinates":[-95.653465,31.746441],"type":"Point"}
}