{
  "type": "Feature",
  "properties": {
    "iso:country":"US",
    "sg:address":"13498 Alexander Rd",
    "sg:city":"Mesquite",
    "sg:classifiers":[
        {
            "category":"Restaurant",
            "type":"Food & Drink"
        }
    ],
    "sg:phone":"+1 972 286 0461",
    "sg:postcode":"75181",
    "sg:province":"TX",
    "sg:tags":[
        "eating"
    ],
    "wof:name":"Tmsu",
    "wof:placetype":"venue"
},
  "geometry": {"coordinates":[-96.5836,32.705405],"type":"Point"}
}