{
  "type": "Feature",
  "properties": {
    "iso:country":"US",
    "sg:address":"5533 Weslayan St",
    "sg:city":"Houston",
    "sg:classifiers":[
        {
            "category":"Personal",
            "subcategory":"Barber",
            "type":"Services"
        }
    ],
    "sg:phone":"+1 713 663 7474",
    "sg:postcode":"77005",
    "sg:province":"TX",
    "sg:tags":[
        "shop"
    ],
    "wof:name":"Supercuts",
    "wof:placetype":"venue"
},
  "geometry": {"coordinates":[-95.441255,29.724465],"type":"Point"}
}