{
  "type": "Feature",
  "properties": {
    "iso:country":"US",
    "sg:address":"11520 W Hwy 80 E",
    "sg:city":"Odessa",
    "sg:classifiers":[
        {
            "category":"Building & Trades",
            "subcategory":"Equipment Rental",
            "type":"Services"
        }
    ],
    "sg:phone":"+1 432 561 5105",
    "sg:postcode":"79765",
    "sg:province":"TX",
    "sg:tags":[
        "party",
        "supply"
    ],
    "wof:name":"Shack In The Back",
    "wof:placetype":"venue"
},
  "geometry": {"coordinates":[-102.23691700000001,31.912468],"type":"Point"}
}