{
  "type": "Feature",
  "properties": {
    "iso:country":"US",
    "sg:address":"1580 Champions Dr",
    "sg:city":"Rockwall",
    "sg:classifiers":[
        {
            "category":"Shopping",
            "subcategory":"Jewelry",
            "type":"Retail Goods"
        }
    ],
    "sg:phone":"+1 469 698 0480",
    "sg:postcode":"75087",
    "sg:province":"TX",
    "wof:name":"Suli",
    "wof:placetype":"venue"
},
  "geometry": {"coordinates":[-96.47878,32.949883],"type":"Point"}
}