{
  "type": "Feature",
  "properties": {
    "iso:country":"US",
    "sg:address":"3310 Noble Hollow Dr",
    "sg:city":"Sugar Land",
    "sg:classifiers":[
        {
            "category":"Shopping",
            "type":"Retail Goods"
        }
    ],
    "sg:phone":"+1 281 277 1778",
    "sg:postcode":"77478",
    "sg:province":"TX",
    "sg:tags":[
        "merchandise"
    ],
    "wof:name":"Budder International Entp",
    "wof:placetype":"venue"
},
  "geometry": {"coordinates":[-95.67834000000001,29.636908],"type":"Point"}
}