{
  "type": "Feature",
  "properties": {
    "iso:country":"US",
    "sg:address":"3715 Douglas Ave",
    "sg:city":"Dallas",
    "sg:classifiers":[
        {
            "category":"Professional",
            "type":"Services"
        }
    ],
    "sg:phone":"+1 214 559 2599",
    "sg:postcode":"75219",
    "sg:province":"TX",
    "sg:tags":[
        "establishment"
    ],
    "wof:name":"Michelle L Collins Inc",
    "wof:placetype":"venue"
},
  "geometry": {"coordinates":[-96.807874,32.817557],"type":"Point"}
}