{
  "type": "Feature",
  "properties": {
    "iso:country":"US",
    "sg:address":"110 S McKinney St",
    "sg:city":"Richardson",
    "sg:classifiers":[
        {
            "category":"Restaurant",
            "type":"Food & Drink"
        }
    ],
    "sg:phone":"+1 972 235 9191",
    "sg:postcode":"75081",
    "sg:province":"TX",
    "wof:name":"Del's Charcoal Burgers",
    "wof:placetype":"venue"
},
  "geometry": {"coordinates":[-96.731369,32.948083],"type":"Point"}
}