{
  "type": "Feature",
  "properties": {
    "iso:country":"US",
    "sg:address":"917 Cable St",
    "sg:city":"Conroe",
    "sg:classifiers":[
        {
            "category":"Banks & Credit Unions",
            "subcategory":"Bank",
            "type":"Services"
        }
    ],
    "sg:phone":"+1 936 441 3399",
    "sg:postcode":"77301",
    "sg:province":"TX",
    "sg:tags":[
        "loan",
        "real estate"
    ],
    "wof:name":"America's Mortgage Source",
    "wof:placetype":"venue"
},
  "geometry": {"coordinates":[-95.463786,30.314118],"type":"Point"}
}