{
  "type": "Feature",
  "properties": {
    "iso:country":"US",
    "sg:address":"7203 Burns Way",
    "sg:city":"San Antonio",
    "sg:classifiers":[
        {
            "category":"Professional",
            "subcategory":"Computer Services",
            "type":"Services"
        }
    ],
    "sg:phone":"+1 210 520 9828",
    "sg:postcode":"78250",
    "sg:province":"TX",
    "sg:tags":[
        "related"
    ],
    "wof:name":"RKB Compuservice",
    "wof:placetype":"venue"
},
  "geometry": {"coordinates":[-98.64538899999999,29.505402],"type":"Point"}
}