{
  "type": "Feature",
  "properties": {
    "iso:country":"US",
    "sg:address":"375 Municipal Dr",
    "sg:city":"Richardson",
    "sg:classifiers":[
        {
            "category":"Health Services",
            "subcategory":"Doctor",
            "type":"Services"
        }
    ],
    "sg:phone":"+1 972 231 6941",
    "sg:postcode":"75080",
    "sg:province":"TX",
    "sg:tags":[
        "dentist",
        "pediatric"
    ],
    "wof:name":"Morgan Robert E Dr DDS",
    "wof:placetype":"venue"
},
  "geometry": {"coordinates":[-96.725613,32.973416],"type":"Point"}
}