{
  "type": "Feature",
  "properties": {
    "iso:country":"US",
    "sg:address":"1702 Texas Ave S",
    "sg:city":"Bryan",
    "sg:classifiers":[
        {
            "category":"Social Services",
            "type":"Services"
        }
    ],
    "sg:phone":"+1 979 779 6379",
    "sg:postcode":"77802",
    "sg:province":"TX",
    "sg:tags":[
        "counseling",
        "senior",
        "citizen"
    ],
    "wof:name":"Elder Aid",
    "wof:placetype":"venue"
},
  "geometry": {"coordinates":[-96.363991,30.653289],"type":"Point"}
}