{
  "type": "Feature",
  "properties": {
    "iso:country":"US",
    "sg:address":"228 W 30th St",
    "sg:city":"Houston",
    "sg:classifiers":[
        {
            "category":"Organizations",
            "subcategory":"Membership Organization",
            "type":"Services"
        }
    ],
    "sg:phone":"+1 832 654 5769",
    "sg:postcode":"77018",
    "sg:province":"TX",
    "wof:name":"Lesbians Working Together LLC",
    "wof:placetype":"venue"
},
  "geometry": {"coordinates":[-95.403295,29.813932],"type":"Point"}
}