{
  "type": "Feature",
  "properties": {
    "iso:country":"US",
    "sg:address":"2714 Lufkin Ln",
    "sg:city":"Deer Park",
    "sg:classifiers":[
        {
            "category":"Professional",
            "type":"Services"
        }
    ],
    "sg:phone":"+1 281 476 5715",
    "sg:postcode":"77536",
    "sg:province":"TX",
    "wof:name":"Plan To Plant",
    "wof:placetype":"venue"
},
  "geometry": {"coordinates":[-95.133439,29.686263],"type":"Point"}
}