{
  "type": "Feature",
  "properties": {
    "iso:country":"US",
    "sg:address":"3316 Bee Caves Rd",
    "sg:city":"Austin",
    "sg:classifiers":[
        {
            "category":"Manufacturing",
            "subcategory":"Metals",
            "type":"Manufacturing & Wholesale Goods"
        }
    ],
    "sg:phone":"+1 512 327 5424",
    "sg:postcode":"78746",
    "sg:province":"TX",
    "sg:tags":[
        "metalwork",
        "sheet",
        "mfg"
    ],
    "wof:name":"Dwight Thompson",
    "wof:placetype":"venue"
},
  "geometry": {"coordinates":[-97.798485,30.273101],"type":"Point"}
}