{
  "type": "Feature",
  "properties": {
    "iso:country":"US",
    "sg:address":"1466 Grand Avenue Pkwy",
    "sg:city":"Pflugerville",
    "sg:classifiers":[
        {
            "category":"Restaurant",
            "type":"Food & Drink"
        }
    ],
    "sg:phone":"+1 512 989 0123",
    "sg:postcode":"78660",
    "sg:province":"TX",
    "sg:tags":[
        "eating"
    ],
    "wof:name":"Amigo's Bbq Grill",
    "wof:placetype":"venue"
},
  "geometry": {"coordinates":[-97.65351800000001,30.456325],"type":"Point"}
}