{
  "type": "Feature",
  "properties": {
    "iso:country":"US",
    "sg:address":"3003 W Holcombe Blvd",
    "sg:city":"Houston",
    "sg:classifiers":[
        {
            "category":"Cinema",
            "subcategory":"Movie Rental",
            "type":"Entertainment"
        }
    ],
    "sg:phone":"+1 713 349 8137",
    "sg:postcode":"77025",
    "sg:province":"TX",
    "sg:tags":[
        "game",
        "video"
    ],
    "wof:name":"Gamestop",
    "wof:placetype":"venue"
},
  "geometry": {"coordinates":[-95.42449999999999,29.705999],"type":"Point"}
}