{
  "type": "Feature",
  "properties": {
    "iso:country":"US",
    "sg:address":"2311 Preston Ave",
    "sg:city":"Pasadena",
    "sg:classifiers":[
        {
            "category":"Retail",
            "subcategory":"Auto Repair",
            "type":"Services"
        }
    ],
    "sg:phone":"+1 713 534 6304",
    "sg:postcode":"77503",
    "sg:province":"TX",
    "sg:tags":[
        "general"
    ],
    "wof:name":"C & D R V Sales & Service Inc",
    "wof:placetype":"venue"
},
  "geometry": {"coordinates":[-95.17247999999999,29.679107],"type":"Point"}
}