{
  "type": "Feature",
  "properties": {
    "iso:country":"US",
    "sg:address":"977 State Hwy 243",
    "sg:city":"Canton",
    "sg:classifiers":[
        {
            "category":"Organizations",
            "subcategory":"Religious Organization",
            "type":"Services"
        }
    ],
    "sg:phone":"+1 903 567 4959",
    "sg:postcode":"75103",
    "sg:province":"TX",
    "wof:name":"St Justin Episcopal Church",
    "wof:placetype":"venue"
},
  "geometry": {"coordinates":[-95.883454,32.543771],"type":"Point"}
}