{
  "type": "Feature",
  "properties": {
    "iso:country":"US",
    "sg:address":"8707 Beechnut St",
    "sg:city":"Houston",
    "sg:classifiers":[
        {
            "category":"Real Estate",
            "subcategory":"Real Estate Operator",
            "type":"Services"
        }
    ],
    "sg:phone":"+1 713 981 9448",
    "sg:postcode":"77036",
    "sg:province":"TX",
    "sg:tags":[
        "building",
        "apartment"
    ],
    "wof:name":"Brentwood Village APT S",
    "wof:placetype":"venue"
},
  "geometry": {"coordinates":[-95.542089,29.69053],"type":"Point"}
}