{
  "type": "Feature",
  "properties": {
    "iso:country":"US",
    "sg:address":"610 N Austin Rd",
    "sg:city":"Eagle Lake",
    "sg:classifiers":[
        {
            "category":"Health Services",
            "subcategory":"Doctor",
            "type":"Services"
        }
    ],
    "sg:phone":"+1 979 234 2551",
    "sg:postcode":"77434",
    "sg:province":"TX",
    "sg:tags":[
        "physician",
        "surgeon",
        "osteopathic"
    ],
    "wof:name":"Rice Medical Associates",
    "wof:placetype":"venue"
},
  "geometry": {"coordinates":[-96.337565,29.599445],"type":"Point"}
}