{
  "type": "Feature",
  "properties": {
    "iso:country":"US",
    "sg:address":"3032 Broadway St",
    "sg:city":"Houston",
    "sg:classifiers":[
        {
            "category":"Personal",
            "subcategory":"Beauty Salon",
            "type":"Services"
        }
    ],
    "sg:phone":"+1 713 643 4525",
    "sg:postcode":"77017",
    "sg:province":"TX",
    "sg:tags":[
        "shop"
    ],
    "wof:name":"Ludys Beauty Salon",
    "wof:placetype":"venue"
},
  "geometry": {"coordinates":[-95.277834,29.695866],"type":"Point"}
}