{
  "type": "Feature",
  "properties": {
    "iso:country":"US",
    "sg:address":"201 Prosperity Dr",
    "sg:city":"Mercedes",
    "sg:classifiers":[
        {
            "category":"Shopping",
            "type":"Retail Goods"
        }
    ],
    "sg:phone":"+1 956 825 7035",
    "sg:postcode":"78570",
    "sg:province":"TX",
    "sg:tags":[
        "merchandise"
    ],
    "wof:name":"Trophy Shop",
    "wof:placetype":"venue"
},
  "geometry": {"coordinates":[-97.90672000000001,26.136138],"type":"Point"}
}