{
  "type": "Feature",
  "properties": {
    "iso:country":"US",
    "sg:address":"200 Roberts St",
    "sg:city":"Crowley",
    "sg:classifiers":[
        {
            "category":"Shopping",
            "subcategory":"Discount & Variety Stores",
            "type":"Retail Goods"
        }
    ],
    "sg:phone":"+1 817 297 3136",
    "sg:postcode":"76036",
    "sg:province":"TX",
    "wof:name":"Dollar General",
    "wof:placetype":"venue"
},
  "geometry": {"coordinates":[-97.35512900000001,32.579136],"type":"Point"}
}