{
  "type": "Feature",
  "properties": {
    "iso:country":"US",
    "sg:address":"12402 Advance Dr",
    "sg:city":"Houston",
    "sg:classifiers":[
        {
            "category":"Wholesale",
            "subcategory":"Non-durable Goods",
            "type":"Manufacturing & Wholesale Goods"
        }
    ],
    "sg:phone":"+1 281 970 4090",
    "sg:postcode":"77065",
    "sg:province":"TX",
    "wof:name":"Mc Trading Post",
    "wof:placetype":"venue"
},
  "geometry": {"coordinates":[-95.610991,29.94494],"type":"Point"}
}