{
  "type": "Feature",
  "properties": {
    "iso:country":"US",
    "sg:address":"2200 McKenzie Ave",
    "sg:city":"Waco",
    "sg:classifiers":[
        {
            "category":"Building & Trades",
            "subcategory":"Construction",
            "type":"Services"
        }
    ],
    "sg:phone":"+1 254 755 8708",
    "sg:postcode":"76708",
    "sg:province":"TX",
    "sg:tags":[
        "house",
        "carpentry",
        "contractor"
    ],
    "wof:name":"Michael Husni",
    "wof:placetype":"venue"
},
  "geometry": {"coordinates":[-97.17012699999999,31.56777],"type":"Point"}
}