{
  "type": "Feature",
  "properties": {
    "iso:country":"US",
    "sg:address":"425 Green Meadow Dr",
    "sg:city":"Boyd",
    "sg:classifiers":[
        {
            "category":"Professional",
            "subcategory":"Detective & Security Services",
            "type":"Services"
        }
    ],
    "sg:phone":"+1 940 433 0134",
    "sg:postcode":"76023",
    "sg:province":"TX",
    "sg:tags":[
        "information",
        "bureau"
    ],
    "wof:name":"T.C. Flowback Services",
    "wof:placetype":"venue"
},
  "geometry": {"coordinates":[-97.570663,33.070736],"type":"Point"}
}