{
  "type": "Feature",
  "properties": {
    "iso:country":"US",
    "sg:address":"3397 US Hwy 380",
    "sg:city":"Greenville",
    "sg:classifiers":[
        {
            "category":"Professional",
            "subcategory":"Accounting & Tax Preparation",
            "type":"Services"
        },
        {
            "category":"Insurance",
            "subcategory":"Insurance Agent",
            "type":"Services"
        }
    ],
    "sg:phone":"+1 903 455 0874",
    "sg:postcode":"75401",
    "sg:province":"TX",
    "sg:tags":[
        "processing"
    ],
    "wof:name":"Lone Star Medical Billing",
    "wof:placetype":"venue"
},
  "geometry": {"coordinates":[-96.141986,33.132392],"type":"Point"}
}