{
  "type": "Feature",
  "properties": {
    "iso:country":"US",
    "sg:address":"5116 Bissonnet #453",
    "sg:city":"Bellaire",
    "sg:classifiers":[
        {
            "category":"Education",
            "subcategory":"Special Training",
            "type":"Public Place"
        }
    ],
    "sg:phone":"+1 713 665 4263",
    "sg:postcode":"77401",
    "sg:province":"TX",
    "sg:tags":[
        "school",
        "tutoring",
        "specialty"
    ],
    "sg:website":"www.stayingaheadofthegame.com",
    "wof:name":"Staying Ahead of the Game!, LLC",
    "wof:placetype":"venue"
},
  "geometry": {"coordinates":[-95.469173,29.706994],"type":"Point"}
}