{
  "type": "Feature",
  "properties": {
    "iso:country":"US",
    "sg:address":"9840 Harwin Dr",
    "sg:city":"Houston",
    "sg:classifiers":[
        {
            "category":"Shopping",
            "subcategory":"Shoes",
            "type":"Retail Goods"
        }
    ],
    "sg:phone":"+1 713 781 4644",
    "sg:postcode":"77036",
    "sg:province":"TX",
    "sg:tags":[
        "store"
    ],
    "wof:name":"All Bundy Shoes",
    "wof:placetype":"venue"
},
  "geometry": {"coordinates":[-95.53312699999999,29.717962],"type":"Point"}
}