{
  "type": "Feature",
  "properties": {
    "iso:country":"US",
    "sg:address":"5708 Highway 78",
    "sg:city":"Sachse",
    "sg:classifiers":[
        {
            "category":"Shopping",
            "subcategory":"Stationery & Office Supplies",
            "type":"Retail Goods"
        },
        {
            "category":"Retail",
            "subcategory":"Storage",
            "type":"Services"
        }
    ],
    "sg:phone":"+1 972 496 1030",
    "sg:postcode":"75048",
    "sg:province":"TX",
    "sg:tags":[
        "equipment",
        "self"
    ],
    "wof:name":"Staples Storage",
    "wof:placetype":"venue"
},
  "geometry": {"coordinates":[-96.597246,32.974627],"type":"Point"}
}