{
  "type": "Feature",
  "properties": {
    "iso:country":"US",
    "sg:address":"15241 Saddlewood Dr",
    "sg:city":"Conroe",
    "sg:classifiers":[
        {
            "category":"Building & Trades",
            "subcategory":"Construction",
            "type":"Services"
        }
    ],
    "sg:phone":"+1 936 273 6262",
    "sg:postcode":"77384",
    "sg:province":"TX",
    "sg:tags":[
        "house"
    ],
    "wof:name":"Jilco Services",
    "wof:placetype":"venue"
},
  "geometry": {"coordinates":[-95.53407799999999,30.231183],"type":"Point"}
}