{
  "type": "Feature",
  "properties": {
    "iso:country":"US",
    "sg:address":"6806 Isabelle Dr",
    "sg:city":"Austin",
    "sg:classifiers":[
        {
            "category":"Real Estate",
            "subcategory":"Real Estate Agent",
            "type":"Services"
        }
    ],
    "sg:phone":"+1 512 452 2639",
    "sg:postcode":"78752",
    "sg:province":"TX",
    "wof:name":"Greg Vallejo",
    "wof:placetype":"venue"
},
  "geometry": {"coordinates":[-97.713752,30.333469],"type":"Point"}
}