{
  "type": "Feature",
  "properties": {
    "iso:country":"US",
    "sg:address":"4515 Seton Center Pkwy",
    "sg:city":"Austin",
    "sg:classifiers":[
        {
            "category":"Health Services",
            "subcategory":"Doctor",
            "type":"Services"
        }
    ],
    "sg:phone":"+1 512 231 5500",
    "sg:postcode":"78759",
    "sg:province":"TX",
    "sg:tags":[
        "physician",
        "surgeon"
    ],
    "sg:website":"http://www.mediview.net",
    "wof:name":"Covenant Management Systems, Lp",
    "wof:placetype":"venue"
},
  "geometry": {"coordinates":[-97.742485,30.40041],"type":"Point"}
}