{
  "type": "Feature",
  "properties": {
    "iso:country":"US",
    "sg:address":"12670 Pensamiento Dr",
    "sg:city":"San Elizario",
    "sg:classifiers":[
        {
            "category":"Building & Trades",
            "subcategory":"Construction",
            "type":"Services"
        }
    ],
    "sg:phone":"+1 915 851 1366",
    "sg:postcode":"79849",
    "sg:province":"TX",
    "sg:tags":[
        "house"
    ],
    "wof:name":"E Mendoza Home Repair & A",
    "wof:placetype":"venue"
},
  "geometry": {"coordinates":[-106.279488,31.58845],"type":"Point"}
}