{
  "type": "Feature",
  "properties": {
    "iso:country":"US",
    "sg:address":"10402 Huntington Place Dr",
    "sg:city":"Houston",
    "sg:classifiers":[
        {
            "category":"Manufacturing",
            "subcategory":"Glass & Minerals",
            "type":"Manufacturing & Wholesale Goods"
        }
    ],
    "sg:phone":"+1 281 988 6049",
    "sg:postcode":"77099",
    "sg:province":"TX",
    "sg:tags":[
        "product",
        "mfg"
    ],
    "wof:name":"Pegasso Glass",
    "wof:placetype":"venue"
},
  "geometry": {"coordinates":[-95.60473399999999,29.667832],"type":"Point"}
}