{
  "type": "Feature",
  "properties": {
    "iso:country":"US",
    "sg:address":"116 Seminole Dr",
    "sg:city":"Roanoke",
    "sg:classifiers":[
        {
            "category":"Banks & Credit Unions",
            "subcategory":"Financial Services",
            "type":"Services"
        }
    ],
    "sg:phone":"+1 817 430 6288",
    "sg:postcode":"76262",
    "sg:province":"TX",
    "sg:tags":[
        "investor"
    ],
    "wof:name":"Ntbd Investments Inc",
    "wof:placetype":"venue"
},
  "geometry": {"coordinates":[-97.177573,32.994362],"type":"Point"}
}