{
  "type": "Feature",
  "properties": {
    "iso:country":"US",
    "sg:address":"3722 Irving Blvd",
    "sg:city":"Dallas",
    "sg:classifiers":[
        {
            "category":"Local Transit",
            "type":"Transportation"
        }
    ],
    "sg:phone":"+1 214 905 9270",
    "sg:postcode":"75247",
    "sg:province":"TX",
    "sg:tags":[
        "bus",
        "line"
    ],
    "wof:name":"International Harvester Co",
    "wof:placetype":"venue"
},
  "geometry": {"coordinates":[-96.880359,32.807992],"type":"Point"}
}