{
  "type": "Feature",
  "properties": {
    "iso:country":"US",
    "sg:address":"300 Bay Ave",
    "sg:city":"Kemah",
    "sg:classifiers":[
        {
            "category":"Autos & Motor Vehicles",
            "subcategory":"Boat Sales",
            "type":"Retail Goods"
        }
    ],
    "sg:phone":"+1 281 535 2628",
    "sg:postcode":"77565",
    "sg:province":"TX",
    "sg:tags":[
        "yacht",
        "broker"
    ],
    "wof:name":"Texas Sport Fishing Yacht",
    "wof:placetype":"venue"
},
  "geometry": {"coordinates":[-95.016881,29.545876],"type":"Point"}
}