{
  "type": "Feature",
  "properties": {
    "iso:country":"US",
    "sg:address":"705 Bunker Hill Dr",
    "sg:city":"Arlington",
    "sg:classifiers":[
        {
            "category":"Home & Garden",
            "subcategory":"Furniture",
            "type":"Retail Goods"
        }
    ],
    "sg:phone":"+1 817 461 1556",
    "sg:postcode":"76011",
    "sg:province":"TX",
    "sg:tags":[
        "store"
    ],
    "wof:name":"Kate Rose Collection",
    "wof:placetype":"venue"
},
  "geometry": {"coordinates":[-97.10392,32.772375],"type":"Point"}
}