{
  "type": "Feature",
  "properties": {
    "iso:country":"US",
    "sg:address":"9625 Webb Chapel Rd",
    "sg:city":"Dallas",
    "sg:classifiers":[
        {
            "category":"Banks & Credit Unions",
            "subcategory":"Bank",
            "type":"Services"
        }
    ],
    "sg:phone":"+1 214 357 3600",
    "sg:postcode":"75220",
    "sg:province":"TX",
    "sg:tags":[
        "money",
        "order"
    ],
    "wof:name":"Cliff's Check Cashing Store",
    "wof:placetype":"venue"
},
  "geometry": {"coordinates":[-96.861836,32.864155],"type":"Point"}
}