{
  "type": "Feature",
  "properties": {
    "iso:country":"US",
    "sg:address":"4111 Medical Parkway",
    "sg:city":"Austin",
    "sg:classifiers":[
        {
            "category":"Shopping",
            "subcategory":"Optician",
            "type":"Retail Goods"
        }
    ],
    "sg:phone":"+1 512 454 4808",
    "sg:postcode":"78756",
    "sg:province":"TX",
    "sg:tags":[
        "eyewear"
    ],
    "wof:name":"Leal Felix Optcn",
    "wof:placetype":"venue"
},
  "geometry": {"coordinates":[-97.74260200000001,30.310022],"type":"Point"}
}