{
  "type": "Feature",
  "properties": {
    "iso:country":"US",
    "sg:address":"10540 State Hwy 195",
    "sg:city":"Killeen",
    "sg:classifiers":[
        {
            "category":"Professional",
            "type":"Services"
        }
    ],
    "sg:phone":"+1 254 628 5023",
    "sg:postcode":"76542",
    "sg:province":"TX",
    "wof:name":"La Kozina",
    "wof:placetype":"venue"
},
  "geometry": {"coordinates":[-97.759381,31.035961],"type":"Point"}
}