{
  "type": "Feature",
  "properties": {
    "iso:country":"US",
    "sg:address":"2208 Cimarron Rd",
    "sg:city":"Mc Kinney",
    "sg:classifiers":[
        {
            "category":"Retail",
            "subcategory":"Auto Repair",
            "type":"Services"
        }
    ],
    "sg:phone":"+1 972 369 0493",
    "sg:postcode":"75070",
    "sg:province":"TX",
    "sg:tags":[
        "body"
    ],
    "wof:name":"Sanders Dent Service",
    "wof:placetype":"venue"
},
  "geometry": {"coordinates":[-96.684933,33.177875],"type":"Point"}
}