{
  "type": "Feature",
  "properties": {
    "iso:country":"US",
    "sg:address":"2727 S Loop 256",
    "sg:city":"Palestine",
    "sg:classifiers":[
        {
            "category":"Restaurant",
            "type":"Food & Drink"
        }
    ],
    "sg:menulink":"http://www.allmenus.com/tx/palestine/204304-sonic/menu/",
    "sg:phone":"+1 903 731 9172",
    "sg:postcode":"75801",
    "sg:province":"TX",
    "sg:tags":[
        "burger",
        "american"
    ],
    "wof:name":"Sonic",
    "wof:placetype":"venue"
},
  "geometry": {"coordinates":[-95.61850800000001,31.733722],"type":"Point"}
}