{
  "type": "Feature",
  "properties": {
    "iso:country":"US",
    "sg:address":"1212 Biscayne Dr",
    "sg:city":"Plano",
    "sg:classifiers":[
        {
            "category":"Farming",
            "subcategory":"Farm & Veterinary Services",
            "type":"Manufacturing & Wholesale Goods"
        }
    ],
    "sg:phone":"+1 972 596 4061",
    "sg:postcode":"75075",
    "sg:province":"TX",
    "sg:tags":[
        "livestock"
    ],
    "wof:name":"Gladewater Farms LLC",
    "wof:placetype":"venue"
},
  "geometry": {"coordinates":[-96.74848799999999,33.015634],"type":"Point"}
}