{
  "type": "Feature",
  "properties": {
    "iso:country":"US",
    "sg:address":"206 Martinek Ln",
    "sg:city":"Ennis",
    "sg:classifiers":[
        {
            "category":"Freight",
            "type":"Transportation"
        }
    ],
    "sg:phone":"+1 972 878 2300",
    "sg:postcode":"75152",
    "sg:province":"TX",
    "sg:tags":[
        "delivery"
    ],
    "wof:name":"Mike's Delivery Inc",
    "wof:placetype":"venue"
},
  "geometry": {"coordinates":[-96.634828,32.400333],"type":"Point"}
}