{
  "type": "Feature",
  "properties": {
    "iso:country":"US",
    "sg:address":"4115 Medical Dr",
    "sg:city":"San Antonio",
    "sg:classifiers":[
        {
            "category":"Wholesale",
            "subcategory":"Durable Goods & Equipment",
            "type":"Manufacturing & Wholesale Goods"
        }
    ],
    "sg:phone":"+1 210 614 3944",
    "sg:postcode":"78229",
    "sg:province":"TX",
    "sg:tags":[
        "importer"
    ],
    "wof:name":"A F Papers Inc",
    "wof:placetype":"venue"
},
  "geometry": {"coordinates":[-98.56860500000001,29.513208],"type":"Point"}
}