{
  "type": "Feature",
  "properties": {
    "iso:country":"US",
    "sg:address":"6114 Beaty Ave",
    "sg:city":"Odessa",
    "sg:classifiers":[
        {
            "category":"Manufacturing",
            "subcategory":"Petroleum Products",
            "type":"Manufacturing & Wholesale Goods"
        }
    ],
    "sg:phone":"+1 432 362 3943",
    "sg:postcode":"79764",
    "sg:province":"TX",
    "sg:tags":[
        "refiner"
    ],
    "wof:name":"Tjs Repair Service",
    "wof:placetype":"venue"
},
  "geometry": {"coordinates":[-102.40383300000001,31.899445],"type":"Point"}
}