{
  "type": "Feature",
  "properties": {
    "iso:country":"US",
    "sg:address":"235 NE Loop 820",
    "sg:city":"Hurst",
    "sg:classifiers":[
        {
            "category":"Professional",
            "subcategory":"Computer Services",
            "type":"Services"
        }
    ],
    "sg:phone":"+1 817 595 9457",
    "sg:postcode":"76053",
    "sg:province":"TX",
    "wof:name":"American Integration Inc",
    "wof:placetype":"venue"
},
  "geometry": {"coordinates":[-97.208609,32.812763],"type":"Point"}
}