{
  "type": "Feature",
  "properties": {
    "iso:country":"US",
    "sg:address":"9307 Harwin Dr Ste C",
    "sg:city":"Houston",
    "sg:classifiers":[
        {
            "category":"Retail",
            "subcategory":"Auto Repair",
            "type":"Services"
        }
    ],
    "sg:phone":"+1 713 789 1892",
    "sg:postcode":"77036",
    "sg:province":"TX",
    "wof:name":"Santana Auto Repair",
    "wof:placetype":"venue"
},
  "geometry": {"coordinates":[-95.526937,29.717783],"type":"Point"}
}