{
  "type": "Feature",
  "properties": {
    "iso:country":"US",
    "sg:address":"6363 N State Highway 161",
    "sg:city":"Irving",
    "sg:classifiers":[
        {
            "category":"Food & Beverages",
            "subcategory":"Liquor & Beverages",
            "type":"Retail Goods"
        }
    ],
    "sg:phone":"+1 214 492 0397",
    "sg:postcode":"75038",
    "sg:province":"TX",
    "sg:tags":[
        "beer",
        "spirit",
        "wine"
    ],
    "wof:name":"Schieffelin & Somerset Co",
    "wof:placetype":"venue"
},
  "geometry": {"coordinates":[-96.97580000000001,32.894402],"type":"Point"}
}