{
  "type": "Feature",
  "properties": {
    "iso:country":"US",
    "sg:address":"2419 Yale St",
    "sg:city":"Houston",
    "sg:classifiers":[
        {
            "category":"Wholesale",
            "subcategory":"Construction Materials",
            "type":"Manufacturing & Wholesale Goods"
        },
        {
            "category":"Home & Garden",
            "subcategory":"Building Materials",
            "type":"Retail Goods"
        }
    ],
    "sg:phone":"+1 713 862 6623",
    "sg:postcode":"77008",
    "sg:province":"TX",
    "sg:tags":[
        "hardware",
        "lumber"
    ],
    "wof:name":"Grogan Builders Supply",
    "wof:placetype":"venue"
},
  "geometry": {"coordinates":[-95.399401,29.808432],"type":"Point"}
}