{
  "type": "Feature",
  "properties": {
    "iso:country":"US",
    "sg:address":"833 Studewood St",
    "sg:city":"Houston",
    "sg:classifiers":[
        {
            "category":"Shopping",
            "subcategory":"Clothing, Apparel, & Fashions",
            "type":"Retail Goods"
        }
    ],
    "sg:phone":"+1 713 861 0301",
    "sg:postcode":"77007",
    "sg:province":"TX",
    "sg:tags":[
        "children's",
        "clothing"
    ],
    "wof:name":"Tulips & Tutus",
    "wof:placetype":"venue"
},
  "geometry": {"coordinates":[-95.387852,29.786871],"type":"Point"}
}