{
  "type": "Feature",
  "properties": {
    "iso:country":"US",
    "sg:address":"303 S Breckenridge Ave",
    "sg:city":"Breckenridge",
    "sg:classifiers":[
        {
            "category":"Restaurant",
            "type":"Food & Drink"
        }
    ],
    "sg:phone":"+1 254 559 9685",
    "sg:postcode":"76424",
    "sg:province":"TX",
    "sg:tags":[
        "house",
        "steak",
        "barbecue"
    ],
    "sg:website":"http://www.pitstopbar-b-q.com/",
    "wof:name":"Pit Stop Bar Bq",
    "wof:placetype":"venue"
},
  "geometry": {"coordinates":[-98.902573,32.753526],"type":"Point"}
}