{
  "type": "Feature",
  "properties": {
    "iso:country":"US",
    "sg:address":"9750 W Shore Dr",
    "sg:city":"Willis",
    "sg:classifiers":[
        {
            "category":"Shopping",
            "subcategory":"Crafts & Fabrics",
            "type":"Retail Goods"
        }
    ],
    "sg:phone":"+1 936 856 4609",
    "sg:postcode":"77318",
    "sg:province":"TX",
    "sg:tags":[
        "sewing"
    ],
    "wof:name":"Milford E Keene",
    "wof:placetype":"venue"
},
  "geometry": {"coordinates":[-95.55547300000001,30.384899],"type":"Point"}
}