{
  "type": "Feature",
  "properties": {
    "iso:country":"US",
    "sg:address":"507 S Garland Ave",
    "sg:city":"Garland",
    "sg:classifiers":[
        {
            "category":"Food & Beverages",
            "subcategory":"Groceries & Convenience Stores",
            "type":"Retail Goods"
        }
    ],
    "sg:phone":"+1 972 272 5562",
    "sg:postcode":"75040",
    "sg:province":"TX",
    "wof:name":"Hsiu Yu Corp",
    "wof:placetype":"venue"
},
  "geometry": {"coordinates":[-96.64847899999999,32.907706],"type":"Point"}
}