{
  "type": "Feature",
  "properties": {
    "iso:country":"US",
    "sg:address":"16790 Co Rd 43",
    "sg:city":"Tyler",
    "sg:classifiers":[
        {
            "category":"Farming",
            "subcategory":"Livestock Farm",
            "type":"Manufacturing & Wholesale Goods"
        }
    ],
    "sg:phone":"+1 903 593 3078",
    "sg:postcode":"75704",
    "sg:province":"TX",
    "sg:tags":[
        "beef",
        "feedlot",
        "cattle"
    ],
    "wof:name":"Griffith Farm",
    "wof:placetype":"venue"
},
  "geometry": {"coordinates":[-95.450379,32.405699],"type":"Point"}
}