{
  "type": "Feature",
  "properties": {
    "iso:country":"US",
    "sg:address":"801 W Wise St",
    "sg:city":"Bowie",
    "sg:classifiers":[
        {
            "category":"Food & Beverages",
            "subcategory":"Groceries & Convenience Stores",
            "type":"Retail Goods"
        }
    ],
    "sg:phone":"+1 940 872 2337",
    "sg:postcode":"76230",
    "sg:province":"TX",
    "wof:name":"Bowie Fina Mart",
    "wof:placetype":"venue"
},
  "geometry": {"coordinates":[-97.861136,33.567329],"type":"Point"}
}