{
  "type": "Feature",
  "properties": {
    "iso:country":"US",
    "sg:address":"1113 US Hwy 290 Bus",
    "sg:city":"Elgin",
    "sg:classifiers":[
        {
            "category":"Travel",
            "subcategory":"Hotels & Motels",
            "type":"Entertainment"
        }
    ],
    "sg:phone":"+1 512 285 4689",
    "sg:postcode":"78621",
    "sg:province":"TX",
    "sg:tags":[
        "operation"
    ],
    "wof:name":"Sunset Lodge",
    "wof:placetype":"venue"
},
  "geometry": {"coordinates":[-97.38226400000001,30.356199],"type":"Point"}
}