{
  "type": "Feature",
  "properties": {
    "iso:country":"US",
    "sg:address":"3515 Oak Gardens Dr",
    "sg:city":"Humble",
    "sg:classifiers":[
        {
            "category":"Building & Trades",
            "subcategory":"Landscaping Services",
            "type":"Services"
        }
    ],
    "sg:phone":"+1 281 359 7874",
    "sg:postcode":"77339",
    "sg:province":"TX",
    "wof:name":"Forest Tree Service",
    "wof:placetype":"venue"
},
  "geometry": {"coordinates":[-95.205618,30.060291],"type":"Point"}
}