{
  "type": "Feature",
  "properties": {
    "iso:country":"US",
    "sg:address":"15822 Bellis Ln",
    "sg:city":"Missouri City",
    "sg:classifiers":[
        {
            "category":"Professional",
            "type":"Services"
        }
    ],
    "sg:phone":"+1 281 835 1928",
    "sg:postcode":"77489",
    "sg:province":"TX",
    "wof:name":"Southwest Greater St Matt",
    "wof:placetype":"venue"
},
  "geometry": {"coordinates":[-95.48083200000001,29.596692],"type":"Point"}
}