{
  "type": "Feature",
  "properties": {
    "iso:country":"US",
    "sg:address":"1900 Macarthur Dr",
    "sg:city":"Orange",
    "sg:classifiers":[
        {
            "category":"Retail",
            "subcategory":"Repair Shop",
            "type":"Services"
        }
    ],
    "sg:phone":"+1 409 883 6159",
    "sg:postcode":"77630",
    "sg:province":"TX",
    "sg:tags":[
        "audio"
    ],
    "wof:name":"Don's VCR Repair",
    "wof:placetype":"venue"
},
  "geometry": {"coordinates":[-93.748311,30.093457],"type":"Point"}
}