{
  "type": "Feature",
  "properties": {
    "iso:country":"US",
    "sg:address":"9214 Bryce Ave",
    "sg:city":"Texas City",
    "sg:classifiers":[
        {
            "category":"Restaurant",
            "type":"Food & Drink"
        }
    ],
    "sg:phone":"+1 409 935 4037",
    "sg:postcode":"77591",
    "sg:province":"TX",
    "sg:tags":[
        "eating"
    ],
    "wof:name":"Palate Pleasers Catering",
    "wof:placetype":"venue"
},
  "geometry": {"coordinates":[-95.013076,29.387808],"type":"Point"}
}