{
  "type": "Feature",
  "properties": {
    "iso:country":"US",
    "sg:address":"2390 Central Blvd",
    "sg:city":"Brownsville",
    "sg:classifiers":[
        {
            "category":"Health Services",
            "subcategory":"Medical Lab",
            "type":"Services"
        }
    ],
    "sg:phone":"+1 210 822 7701",
    "sg:postcode":"78520",
    "sg:province":"TX",
    "sg:tags":[
        "specialty",
        "drug",
        "outpatient",
        "detection",
        "equipment",
        "clinic",
        "laboratory"
    ],
    "wof:name":"Analytical Group Inc",
    "wof:placetype":"venue"
},
  "geometry": {"coordinates":[-97.51018500000001,25.935839],"type":"Point"}
}