{
  "type": "Feature",
  "properties": {
    "iso:country":"US",
    "sg:address":"12519 Huffmeister Rd",
    "sg:city":"Cypress",
    "sg:classifiers":[
        {
            "category":"Insurance",
            "subcategory":"Insurance Agent",
            "type":"Services"
        }
    ],
    "sg:phone":"+1 281 807 4950",
    "sg:postcode":"77429",
    "sg:province":"TX",
    "wof:name":"Farmers Insurance",
    "wof:placetype":"venue"
},
  "geometry": {"coordinates":[-95.63097,29.956509],"type":"Point"}
}