{
  "type": "Feature",
  "properties": {
    "iso:country":"US",
    "sg:address":"2010 FM 2673",
    "sg:city":"Canyon Lake",
    "sg:classifiers":[
        {
            "category":"Social Services",
            "subcategory":"Child Care",
            "type":"Services"
        }
    ],
    "sg:phone":"+1 830 964 5430",
    "sg:postcode":"78133",
    "sg:province":"TX",
    "sg:tags":[
        "day"
    ],
    "wof:name":"Kid Junction",
    "wof:placetype":"venue"
},
  "geometry": {"coordinates":[-98.186269,29.843318],"type":"Point"}
}