{
  "type": "Feature",
  "properties": {
    "iso:country":"US",
    "sg:address":"13131 James Ln",
    "sg:city":"Stafford",
    "sg:classifiers":[
        {
            "category":"Building & Trades",
            "subcategory":"Landscaping Services",
            "type":"Services"
        }
    ],
    "sg:phone":"+1 281 499 2130",
    "sg:postcode":"77477",
    "sg:province":"TX",
    "wof:name":"As Tractor Service",
    "wof:placetype":"venue"
},
  "geometry": {"coordinates":[-95.54374199999999,29.630442],"type":"Point"}
}