{
  "type": "Feature",
  "properties": {
    "iso:country":"US",
    "sg:address":"634 Evergreen Ln",
    "sg:city":"New Braunfels",
    "sg:classifiers":[
        {
            "category":"Real Estate",
            "subcategory":"Developer",
            "type":"Services"
        }
    ],
    "sg:phone":"+1 830 629 4395",
    "sg:postcode":"78130",
    "sg:province":"TX",
    "wof:name":"Finke Development LLC",
    "wof:placetype":"venue"
},
  "geometry": {"coordinates":[-98.16080100000001,29.704977],"type":"Point"}
}