{
  "type": "Feature",
  "properties": {
    "iso:country":"US",
    "sg:address":"3617 Brown St",
    "sg:city":"Dallas",
    "sg:classifiers":[
        {
            "category":"Professional",
            "type":"Services"
        }
    ],
    "sg:phone":"+1 214 522 1730",
    "sg:postcode":"75219",
    "sg:province":"TX",
    "sg:tags":[
        "interior",
        "painting",
        "mural"
    ],
    "wof:name":"Trompe LOeil Interiors",
    "wof:placetype":"venue"
},
  "geometry": {"coordinates":[-96.81128200000001,32.805159],"type":"Point"}
}