{
  "type": "Feature",
  "properties": {
    "iso:country":"US",
    "sg:address":"200 Hart Rd",
    "sg:city":"Little Elm",
    "sg:classifiers":[
        {
            "category":"Professional",
            "subcategory":"Advertising",
            "type":"Services"
        }
    ],
    "sg:phone":"+1 972 294 1787",
    "sg:postcode":"75068",
    "sg:province":"TX",
    "sg:tags":[
        "agency"
    ],
    "wof:name":"Martx Advertising",
    "wof:placetype":"venue"
},
  "geometry": {"coordinates":[-96.92242,33.169286],"type":"Point"}
}