{
  "type": "Feature",
  "properties": {
    "iso:country":"US",
    "sg:address":"9600 Montrose Ct",
    "sg:city":"El Paso",
    "sg:classifiers":[
        {
            "category":"Food & Beverages",
            "subcategory":"Groceries & Convenience Stores",
            "type":"Retail Goods"
        }
    ],
    "sg:phone":"+1 915 598 2983",
    "sg:postcode":"79925",
    "sg:province":"TX",
    "wof:name":"Medina Benjamin Flea Mkt",
    "wof:placetype":"venue"
},
  "geometry": {"coordinates":[-106.35777,31.79309],"type":"Point"}
}