{
  "type": "Feature",
  "properties": {
    "iso:country":"US",
    "sg:address":"4422 E Overland Trl",
    "sg:city":"Abilene",
    "sg:classifiers":[
        {
            "category":"Retail",
            "subcategory":"Repair Shop",
            "type":"Services"
        },
        {
            "category":"Building & Trades",
            "subcategory":"Construction",
            "type":"Services"
        }
    ],
    "sg:phone":"+1 325 672 1490",
    "sg:postcode":"79601",
    "sg:province":"TX",
    "sg:tags":[
        "mobile",
        "home"
    ],
    "wof:name":"Trinity Mobile Home Services",
    "wof:placetype":"venue"
},
  "geometry": {"coordinates":[-99.65213199999999,32.443772],"type":"Point"}
}