{
  "type": "Feature",
  "properties": {
    "iso:country":"US",
    "sg:address":"4103 FM 2351 N",
    "sg:city":"Friendswood",
    "sg:classifiers":[
        {
            "category":"Building & Trades",
            "subcategory":"Construction",
            "type":"Services"
        }
    ],
    "sg:phone":"+1 281 482 6067",
    "sg:postcode":"77546",
    "sg:province":"TX",
    "sg:tags":[
        "general",
        "contractor"
    ],
    "wof:name":"JMV Inc",
    "wof:placetype":"venue"
},
  "geometry": {"coordinates":[-95.18156500000001,29.55606],"type":"Point"}
}