{
  "type": "Feature",
  "properties": {
    "iso:country":"US",
    "sg:address":"120 S Waco St",
    "sg:city":"Hillsboro",
    "sg:classifiers":[
        {
            "category":"Food & Beverages",
            "subcategory":"Groceries & Convenience Stores",
            "type":"Retail Goods"
        }
    ],
    "sg:phone":"+1 254 582 8468",
    "sg:postcode":"76645",
    "sg:province":"TX",
    "sg:tags":[
        "grocer"
    ],
    "wof:name":"Appletree Markets",
    "wof:placetype":"venue"
},
  "geometry": {"coordinates":[-97.130229,32.010217],"type":"Point"}
}