{
  "type": "Feature",
  "properties": {
    "iso:country":"US",
    "sg:address":"550 Westridge Dr",
    "sg:city":"Spring",
    "sg:classifiers":[
        {
            "category":"Building & Trades",
            "subcategory":"Landscaping Services",
            "type":"Services"
        }
    ],
    "sg:phone":"+1 281 367 9971",
    "sg:postcode":"77380",
    "sg:province":"TX",
    "sg:tags":[
        "landscape",
        "contractor"
    ],
    "wof:name":"Jam Enterprises Exterior Dsgn",
    "wof:placetype":"venue"
},
  "geometry": {"coordinates":[-95.45043200000001,30.120964],"type":"Point"}
}