{
  "type": "Feature",
  "properties": {
    "iso:country":"US",
    "sg:address":"18741 Stuebner Airline Rd",
    "sg:city":"Spring",
    "sg:classifiers":[
        {
            "category":"Shopping",
            "subcategory":"Clothing, Apparel, & Fashions",
            "type":"Retail Goods"
        },
        {
            "category":"Shopping",
            "subcategory":"Gifts & Souvenirs",
            "type":"Retail Goods"
        },
        {
            "category":"Shopping",
            "subcategory":"Crafts & Fabrics",
            "type":"Retail Goods"
        },
        {
            "category":"Professional",
            "subcategory":"Printing & Photocopies",
            "type":"Services"
        },
        {
            "category":"Professional",
            "subcategory":"Credit Reporting & Collection",
            "type":"Services"
        }
    ],
    "sg:phone":"+1 281 655 7300",
    "sg:postcode":"77379",
    "sg:province":"TX",
    "sg:tags":[
        "shop",
        "screen",
        "trophies",
        "t-shirt",
        "award",
        "embroidery",
        "medal",
        "plaque"
    ],
    "wof:name":"Absolute All Sports",
    "wof:placetype":"venue"
},
  "geometry": {"coordinates":[-95.538381,30.044657],"type":"Point"}
}