{
  "type": "Feature",
  "properties": {
    "iso:country":"US",
    "sg:address":"17926 State Hwy 3",
    "sg:city":"Webster",
    "sg:classifiers":[
        {
            "category":"Health Services",
            "subcategory":"Clinic",
            "type":"Services"
        }
    ],
    "sg:phone":"+1 281 554 9726",
    "sg:postcode":"77598",
    "sg:province":"TX",
    "sg:tags":[
        "specialty",
        "outpatient"
    ],
    "wof:name":"Up The Street Inc",
    "wof:placetype":"venue"
},
  "geometry": {"coordinates":[-95.11791700000001,29.537526],"type":"Point"}
}