{
  "type": "Feature",
  "properties": {
    "iso:country":"US",
    "sg:address":"2315 50th St",
    "sg:city":"Lubbock",
    "sg:classifiers":[
        {
            "category":"School Buses",
            "type":"Transportation"
        }
    ],
    "sg:phone":"+1 806 794 7525",
    "sg:postcode":"79412",
    "sg:province":"TX",
    "wof:name":"D R Solutions",
    "wof:placetype":"venue"
},
  "geometry": {"coordinates":[-101.870172,33.548655],"type":"Point"}
}