{
  "type": "Feature",
  "properties": {
    "iso:country":"US",
    "sg:address":"206 23rd St",
    "sg:city":"Lubbock",
    "sg:classifiers":[
        {
            "category":"Professional",
            "type":"Services"
        }
    ],
    "sg:phone":"+1 806 744 8799",
    "sg:postcode":"79404",
    "sg:province":"TX",
    "wof:name":"Holiday Theme Park Co",
    "wof:placetype":"venue"
},
  "geometry": {"coordinates":[-101.837141,33.57417],"type":"Point"}
}