{
  "type": "Feature",
  "properties": {
    "iso:country":"US",
    "sg:address":"457 Selkirk Dr",
    "sg:city":"Bay City",
    "sg:classifiers":[
        {
            "category":"Shopping",
            "type":"Retail Goods"
        }
    ],
    "sg:phone":"+1 979 863 7792",
    "sg:postcode":"77414",
    "sg:province":"TX",
    "sg:tags":[
        "merchandise"
    ],
    "wof:name":"Luvy M Bracken",
    "wof:placetype":"venue"
},
  "geometry": {"coordinates":[-95.996073,28.756264],"type":"Point"}
}