{
  "type": "Feature",
  "properties": {
    "iso:country":"US",
    "sg:address":"1614 Ave M",
    "sg:city":"Lubbock",
    "sg:classifiers":[
        {
            "category":"Professional",
            "subcategory":"Business Services",
            "type":"Services"
        }
    ],
    "sg:phone":"+1 806 763 0807",
    "sg:postcode":"79401",
    "sg:province":"TX",
    "sg:website":"www.micro-images.com",
    "wof:name":"Micro Images",
    "wof:placetype":"venue"
},
  "geometry": {"coordinates":[-101.850263,33.579972],"type":"Point"}
}