{
  "type": "Feature",
  "properties": {
    "iso:country":"US",
    "sg:address":"403 Winkler Dr",
    "sg:city":"Houston",
    "sg:classifiers":[
        {
            "category":"Restaurant",
            "type":"Food & Drink"
        }
    ],
    "sg:phone":"+1 713 644 8888",
    "sg:postcode":"77087",
    "sg:province":"TX",
    "sg:tags":[
        "chinese"
    ],
    "wof:name":"888 Restaurant",
    "wof:placetype":"venue"
},
  "geometry": {"coordinates":[-95.295401,29.70077],"type":"Point"}
}