{
  "type": "Feature",
  "properties": {
    "iso:country":"US",
    "sg:address":"107 S Main St",
    "sg:city":"Aubrey",
    "sg:classifiers":[
        {
            "category":"Government",
            "subcategory":"Office",
            "type":"Public Place"
        }
    ],
    "sg:phone":"+1 940 365 9343",
    "sg:postcode":"76227",
    "sg:province":"TX",
    "sg:tags":[
        "city",
        "council"
    ],
    "wof:name":"Aubrey City Hall",
    "wof:placetype":"venue"
},
  "geometry": {"coordinates":[-96.98629,33.3037],"type":"Point"}
}