{
  "type": "Feature",
  "properties": {
    "iso:country":"US",
    "sg:address":"3874 Plainview Rd",
    "sg:city":"Oglesby",
    "sg:classifiers":[
        {
            "category":"Farming",
            "subcategory":"Farm",
            "type":"Manufacturing & Wholesale Goods"
        }
    ],
    "sg:phone":"+1 254 840 3545",
    "sg:postcode":"76561",
    "sg:province":"TX",
    "sg:tags":[
        "crop",
        "general"
    ],
    "wof:name":"Troy Zacharias",
    "wof:placetype":"venue"
},
  "geometry": {"coordinates":[-97.48034199999999,31.45607],"type":"Point"}
}