{
  "type": "Feature",
  "properties": {
    "iso:country":"US",
    "sg:address":"1414 Brookside Dr",
    "sg:city":"Allen",
    "sg:classifiers":[
        {
            "category":"Manufacturing",
            "subcategory":"Chemicals & Compounds",
            "type":"Manufacturing & Wholesale Goods"
        }
    ],
    "sg:phone":"+1 972 727 1519",
    "sg:postcode":"75002",
    "sg:province":"TX",
    "sg:tags":[
        "preparation",
        "toilet",
        "mfg"
    ],
    "wof:name":"Making It Up As We Go Along",
    "wof:placetype":"venue"
},
  "geometry": {"coordinates":[-96.635306,33.107929],"type":"Point"}
}