{
  "type": "Feature",
  "properties": {
    "iso:country":"US",
    "sg:address":"11412 Reeder Rd",
    "sg:city":"Dallas",
    "sg:classifiers":[
        {
            "category":"Wholesale",
            "subcategory":"Hardware",
            "type":"Manufacturing & Wholesale Goods"
        }
    ],
    "sg:phone":"+1 972 241 9555",
    "sg:postcode":"75229",
    "sg:province":"TX",
    "sg:tags":[
        "tool"
    ],
    "wof:name":"Tools Depot",
    "wof:placetype":"venue"
},
  "geometry": {"coordinates":[-96.895814,32.900173],"type":"Point"}
}