{
  "type": "Feature",
  "properties": {
    "iso:country":"US",
    "sg:address":"16660 Dallas Pkwy",
    "sg:city":"Dallas",
    "sg:classifiers":[
        {
            "category":"Real Estate",
            "subcategory":"Real Estate Services",
            "type":"Services"
        }
    ],
    "sg:phone":"+1 972 788 0066",
    "sg:postcode":"75248",
    "sg:province":"TX",
    "wof:name":"McNeff Michael Real Estate",
    "wof:placetype":"venue"
},
  "geometry": {"coordinates":[-96.825996,32.977699],"type":"Point"}
}