{
  "type": "Feature",
  "properties": {
    "iso:country":"US",
    "sg:address":"5901 Coit Rd",
    "sg:city":"Plano",
    "sg:classifiers":[
        {
            "category":"Restaurant",
            "type":"Food & Drink"
        }
    ],
    "sg:menulink":"http://www.allmenus.com/tx/plano/240483-panda-express/menu/",
    "sg:phone":"+1 972 596 0107",
    "sg:postcode":"75093",
    "sg:province":"TX",
    "sg:tags":[
        "asian",
        "chinese"
    ],
    "wof:name":"Panda Express",
    "wof:placetype":"venue"
},
  "geometry": {"coordinates":[-96.770526,33.054958],"type":"Point"}
}