{
  "type": "Feature",
  "properties": {
    "iso:country":"US",
    "sg:address":"2038 Ward Pkwy",
    "sg:city":"Fort Worth",
    "sg:classifiers":[
        {
            "category":"Professional",
            "subcategory":"Business Services",
            "type":"Services"
        }
    ],
    "sg:phone":"+1 817 926 3333",
    "sg:postcode":"76110",
    "sg:province":"TX",
    "sg:tags":[
        "interior",
        "designer"
    ],
    "wof:name":"Inside Inc",
    "wof:placetype":"venue"
},
  "geometry": {"coordinates":[-97.350545,32.718049],"type":"Point"}
}