{
  "type": "Feature",
  "properties": {
    "iso:country":"US",
    "sg:address":"6100 Royalgate Dr",
    "sg:city":"San Antonio",
    "sg:classifiers":[
        {
            "category":"Education",
            "subcategory":"School",
            "type":"Public Place"
        }
    ],
    "sg:phone":"+1 210 645 3800",
    "sg:postcode":"78242",
    "sg:province":"TX",
    "wof:name":"Royalgate Elementary School",
    "wof:placetype":"venue"
},
  "geometry": {"coordinates":[-98.611312,29.371464],"type":"Point"}
}