{
  "type": "Feature",
  "properties": {
    "iso:country":"US",
    "sg:address":"3632 W 45th Ave",
    "sg:city":"Amarillo",
    "sg:classifiers":[
        {
            "category":"Freight",
            "type":"Transportation"
        }
    ],
    "sg:phone":"+1 806 373 4994",
    "sg:postcode":"79109",
    "sg:province":"TX",
    "sg:tags":[
        "commercial",
        "storage"
    ],
    "wof:name":"C & R Mini Storage",
    "wof:placetype":"venue"
},
  "geometry": {"coordinates":[-101.875373,35.163893],"type":"Point"}
}