{
  "type": "Feature",
  "properties": {
    "iso:country":"US",
    "sg:address":"9230 Research Boulevard",
    "sg:city":"Austin",
    "sg:classifiers":[
        {
            "category":"Building & Trades",
            "subcategory":"Construction",
            "type":"Services"
        }
    ],
    "sg:phone":"+1 512 323 2957",
    "sg:postcode":"78758",
    "sg:province":"TX",
    "sg:tags":[
        "interior",
        "design"
    ],
    "wof:name":"John-William Interiors",
    "wof:placetype":"venue"
},
  "geometry": {"coordinates":[-97.73532299999999,30.377454],"type":"Point"}
}