{
  "type": "Feature",
  "properties": {
    "iso:country":"US",
    "sg:address":"14060 Mint Trail Dr",
    "sg:city":"San Antonio",
    "sg:classifiers":[
        {
            "category":"Retail",
            "subcategory":"Veterinary Services",
            "type":"Services"
        }
    ],
    "sg:phone":"+1 210 545 7982",
    "sg:postcode":"78232",
    "sg:province":"TX",
    "wof:name":"Bovagen",
    "wof:placetype":"venue"
},
  "geometry": {"coordinates":[-98.49762200000001,29.583181],"type":"Point"}
}