{
  "type": "Feature",
  "properties": {
    "iso:country":"US",
    "sg:address":"1111 Commerce Dr",
    "sg:city":"Richardson",
    "sg:classifiers":[
        {
            "category":"Manufacturing",
            "subcategory":"Signs",
            "type":"Manufacturing & Wholesale Goods"
        }
    ],
    "sg:phone":"+1 972 235 2356",
    "sg:postcode":"75081",
    "sg:province":"TX",
    "sg:tags":[
        "textile",
        "specialty",
        "mfg"
    ],
    "wof:name":"Hightech Signs",
    "wof:placetype":"venue"
},
  "geometry": {"coordinates":[-96.705546,32.966013],"type":"Point"}
}