{
  "type": "Feature",
  "properties": {
    "iso:country":"US",
    "sg:address":"1202 Ave L",
    "sg:city":"Anson",
    "sg:classifiers":[
        {
            "category":"Mining & Drilling",
            "type":"Manufacturing & Wholesale Goods"
        }
    ],
    "sg:phone":"+1 325 823 3543",
    "sg:postcode":"79501",
    "sg:province":"TX",
    "sg:tags":[
        "crude",
        "production",
        "gas"
    ],
    "wof:name":"Hodges & Hodges",
    "wof:placetype":"venue"
},
  "geometry": {"coordinates":[-99.89926699999999,32.755984],"type":"Point"}
}