{
  "type": "Feature",
  "properties": {
    "iso:country":"US",
    "sg:address":"3643 Windlewood Dr",
    "sg:city":"Katy",
    "sg:classifiers":[
        {
            "category":"Home & Garden",
            "subcategory":"Furniture",
            "type":"Retail Goods"
        }
    ],
    "sg:phone":"+1 832 689 5084",
    "sg:postcode":"77449",
    "sg:province":"TX",
    "sg:tags":[
        "store"
    ],
    "sg:website":"http://www.tlynnsfurniture.com",
    "wof:name":"T Lynn's Furniture",
    "wof:placetype":"venue"
},
  "geometry": {"coordinates":[-95.727661,29.823642],"type":"Point"}
}