{
  "type": "Feature",
  "properties": {
    "iso:country":"US",
    "sg:address":"5134 Wood Creek Ln",
    "sg:city":"Garland",
    "sg:classifiers":[
        {
            "category":"Banks & Credit Unions",
            "subcategory":"Bank",
            "type":"Services"
        }
    ],
    "sg:phone":"+1 214 473 9481",
    "sg:postcode":"75044",
    "sg:province":"TX",
    "sg:tags":[
        "loan",
        "real estate"
    ],
    "wof:name":"Union Mortgage",
    "wof:placetype":"venue"
},
  "geometry": {"coordinates":[-96.637016,32.9656],"type":"Point"}
}