{
  "type": "Feature",
  "properties": {
    "iso:country":"US",
    "sg:address":"3109 Old Hickory Dr",
    "sg:city":"La Porte",
    "sg:classifiers":[
        {
            "category":"Shopping",
            "subcategory":"Jewelry",
            "type":"Retail Goods"
        }
    ],
    "sg:phone":"+1 281 471 7421",
    "sg:postcode":"77571",
    "sg:province":"TX",
    "wof:name":"Jancy Custom Jewelry",
    "wof:placetype":"venue"
},
  "geometry": {"coordinates":[-95.06725400000001,29.661322],"type":"Point"}
}