{
  "type": "Feature",
  "properties": {
    "iso:country":"US",
    "sg:address":"26170 FM 2090",
    "sg:city":"Splendora",
    "sg:classifiers":[
        {
            "category":"Social Services",
            "subcategory":"Child Care",
            "type":"Services"
        }
    ],
    "sg:phone":"+1 281 689 8687",
    "sg:postcode":"77372",
    "sg:province":"TX",
    "sg:tags":[
        "day"
    ],
    "wof:name":"Tot's-N-More",
    "wof:placetype":"venue"
},
  "geometry": {"coordinates":[-95.15504300000001,30.233183],"type":"Point"}
}