{
  "type": "Feature",
  "properties": {
    "iso:country":"US",
    "sg:address":"2329 E Missouri Ave",
    "sg:city":"El Paso",
    "sg:classifiers":[
        {
            "category":"Food & Beverages",
            "subcategory":"Groceries & Convenience Stores",
            "type":"Retail Goods"
        }
    ],
    "sg:phone":"+1 915 532 6111",
    "sg:postcode":"79903",
    "sg:province":"TX",
    "wof:name":"In-N-Out Convenience Store",
    "wof:placetype":"venue"
},
  "geometry": {"coordinates":[-106.466207,31.776985],"type":"Point"}
}