{
  "type": "Feature",
  "properties": {
    "iso:country":"US",
    "sg:address":"728 Bluebonnet Dr",
    "sg:city":"Hurst",
    "sg:classifiers":[
        {
            "category":"Building & Trades",
            "subcategory":"Construction",
            "type":"Services"
        }
    ],
    "sg:phone":"+1 817 875 7748",
    "sg:postcode":"76053",
    "sg:province":"TX",
    "sg:tags":[
        "tile",
        "dealer"
    ],
    "wof:name":"Layem Straight Tile",
    "wof:placetype":"venue"
},
  "geometry": {"coordinates":[-97.156645,32.81436],"type":"Point"}
}