{
  "type": "Feature",
  "properties": {
    "iso:country":"US",
    "sg:address":"139 Rouse St",
    "sg:city":"Houston",
    "sg:classifiers":[
        {
            "category":"Organizations",
            "subcategory":"Religious Organization",
            "type":"Services"
        }
    ],
    "sg:phone":"+1 713 462 0708",
    "sg:postcode":"77020",
    "sg:province":"TX",
    "wof:name":"First Untd Mthdst Krean Church",
    "wof:placetype":"venue"
},
  "geometry": {"coordinates":[-95.305187,29.785763],"type":"Point"}
}