{
  "type": "Feature",
  "properties": {
    "iso:country":"US",
    "sg:address":"2805 Rocky Ridge Dr",
    "sg:city":"El Paso",
    "sg:classifiers":[
        {
            "category":"Professional",
            "subcategory":"Management & Consulting",
            "type":"Services"
        }
    ],
    "sg:phone":"+1 915 757 7819",
    "sg:postcode":"79904",
    "sg:province":"TX",
    "sg:tags":[
        "consultant",
        "energy",
        "conservation"
    ],
    "wof:name":"Accu-Rate",
    "wof:placetype":"venue"
},
  "geometry": {"coordinates":[-106.467911,31.855403],"type":"Point"}
}