{
  "type": "Feature",
  "properties": {
    "iso:country":"US",
    "sg:address":"15010 Timberlea Dr",
    "sg:city":"Missouri City",
    "sg:classifiers":[
        {
            "category":"Freight",
            "type":"Transportation"
        }
    ],
    "sg:phone":"+1 281 416 2103",
    "sg:postcode":"77489",
    "sg:province":"TX",
    "wof:name":"Tc Transportation",
    "wof:placetype":"venue"
},
  "geometry": {"coordinates":[-95.493903,29.609392],"type":"Point"}
}