{
  "type": "Feature",
  "properties": {
    "iso:country":"US",
    "sg:address":"2602 Covington Dr",
    "sg:city":"Garland",
    "sg:classifiers":[
        {
            "category":"Retail",
            "subcategory":"Portrait Studio",
            "type":"Services"
        }
    ],
    "sg:phone":"+1 972 495 4569",
    "sg:postcode":"75040",
    "sg:province":"TX",
    "sg:tags":[
        "photo"
    ],
    "wof:name":"Ken Myers Photography",
    "wof:placetype":"venue"
},
  "geometry": {"coordinates":[-96.60813,32.941351],"type":"Point"}
}