{
  "type": "Feature",
  "properties": {
    "iso:country":"US",
    "sg:address":"3000 Bedford Rd",
    "sg:city":"Bedford",
    "sg:classifiers":[
        {
            "category":"Real Estate",
            "subcategory":"Real Estate Operator",
            "type":"Services"
        }
    ],
    "sg:phone":"+1 817 540 3988",
    "sg:postcode":"76021",
    "sg:province":"TX",
    "sg:tags":[
        "building",
        "apartment"
    ],
    "wof:name":"Copper Hill Apartments",
    "wof:placetype":"venue"
},
  "geometry": {"coordinates":[-97.108436,32.845174],"type":"Point"}
}