{
  "type": "Feature",
  "properties": {
    "iso:country":"US",
    "sg:address":"115 Walnut St",
    "sg:city":"Ranger",
    "sg:classifiers":[
        {
            "category":"Retail",
            "subcategory":"Repair Shop",
            "type":"Services"
        }
    ],
    "sg:phone":"+1 254 647 3466",
    "sg:postcode":"76470",
    "sg:province":"TX",
    "sg:tags":[
        "television",
        "radio"
    ],
    "wof:name":"Vinson Television",
    "wof:placetype":"venue"
},
  "geometry": {"coordinates":[-98.680181,32.471346],"type":"Point"}
}