{
  "type": "Feature",
  "properties": {
    "iso:country":"US",
    "sg:address":"2914 Forest Trl",
    "sg:city":"San Angelo",
    "sg:classifiers":[
        {
            "category":"Shopping",
            "subcategory":"Hobbies, Toys, & Games",
            "type":"Retail Goods"
        }
    ],
    "sg:phone":"+1 325 947 5312",
    "sg:postcode":"76904",
    "sg:province":"TX",
    "wof:name":"Country Cupboard",
    "wof:placetype":"venue"
},
  "geometry": {"coordinates":[-100.48467100000001,31.432592],"type":"Point"}
}