{
  "type": "Feature",
  "properties": {
    "iso:country":"US",
    "sg:address":"1105 Emerald Ct",
    "sg:city":"Colleyville",
    "sg:classifiers":[
        {
            "category":"Building & Trades",
            "subcategory":"Cleaning & Sanitation",
            "type":"Services"
        }
    ],
    "sg:phone":"+1 817 251 1764",
    "sg:postcode":"76034",
    "sg:province":"TX",
    "sg:tags":[
        "polishing",
        "waxing",
        "floor"
    ],
    "wof:name":"Floor Masters",
    "wof:placetype":"venue"
},
  "geometry": {"coordinates":[-97.151792,32.902018],"type":"Point"}
}