{
  "type": "Feature",
  "properties": {
    "iso:country":"US",
    "sg:address":"310 S Walton Walker Blvd",
    "sg:city":"Irving",
    "sg:classifiers":[
        {
            "category":"Autos & Motor Vehicles",
            "subcategory":"Automobile Sales",
            "type":"Retail Goods"
        }
    ],
    "sg:phone":"+1 972 871 8557",
    "sg:postcode":"75060",
    "sg:province":"TX",
    "sg:tags":[
        "truck"
    ],
    "sg:website":"www.dallastruckcenter.com",
    "wof:name":"Dallas Truck Ctr",
    "wof:placetype":"venue"
},
  "geometry": {"coordinates":[-96.92106099999999,32.810615],"type":"Point"}
}