{
  "type": "Feature",
  "properties": {
    "iso:country":"US",
    "sg:address":"807 28th St",
    "sg:city":"Orange",
    "sg:classifiers":[
        {
            "category":"Organizations",
            "subcategory":"Religious Organization",
            "type":"Services"
        }
    ],
    "sg:phone":"+1 409 882 9479",
    "sg:postcode":"77630",
    "sg:province":"TX",
    "wof:name":"Family Praise Center Church",
    "wof:placetype":"venue"
},
  "geometry": {"coordinates":[-93.76223899999999,30.099113],"type":"Point"}
}