{
  "type": "Feature",
  "properties": {
    "iso:country":"US",
    "sg:address":"229 Trl of the Flowers",
    "sg:city":"Georgetown",
    "sg:classifiers":[
        {
            "category":"Shopping",
            "subcategory":"Clothing, Apparel, & Fashions",
            "type":"Retail Goods"
        }
    ],
    "sg:phone":"+1 512 864 1708",
    "sg:postcode":"78633",
    "sg:province":"TX",
    "wof:name":"J L Designs",
    "wof:placetype":"venue"
},
  "geometry": {"coordinates":[-97.72786000000001,30.702136],"type":"Point"}
}