{
  "type": "Feature",
  "properties": {
    "iso:country":"US",
    "sg:address":"3800 Little York Rd",
    "sg:city":"Houston",
    "sg:classifiers":[
        {
            "category":"Shopping",
            "subcategory":"Clothing, Apparel, & Fashions",
            "type":"Retail Goods"
        }
    ],
    "sg:phone":"+1 713 695 7526",
    "sg:postcode":"77093",
    "sg:province":"TX",
    "sg:tags":[
        "accessory"
    ],
    "wof:name":"Julie's Fashion",
    "wof:placetype":"venue"
},
  "geometry": {"coordinates":[-95.3312,29.870701],"type":"Point"}
}