{
  "type": "Feature",
  "properties": {
    "iso:country":"US",
    "sg:address":"452 Century Ln",
    "sg:city":"Howe",
    "sg:classifiers":[
        {
            "category":"Building & Trades",
            "subcategory":"Construction",
            "type":"Services"
        }
    ],
    "sg:phone":"+1 903 532 1265",
    "sg:postcode":"75459",
    "sg:province":"TX",
    "sg:tags":[
        "general",
        "contractor"
    ],
    "wof:name":"Ron Davis Construction",
    "wof:placetype":"venue"
},
  "geometry": {"coordinates":[-96.639866,33.521731],"type":"Point"}
}