{
  "type": "Feature",
  "properties": {
    "iso:country":"US",
    "sg:address":"11200 Lakeline Mall Dr Lakeline Mall Food Court",
    "sg:city":"Cedar Park",
    "sg:classifiers":[
        {
            "category":"Juice Bar",
            "subcategory":"None",
            "type":"Food & Drink"
        }
    ],
    "sg:phone":"+1 512 257 8510",
    "sg:postcode":"78613",
    "sg:province":"TX",
    "sg:tags":[
        "smoothy"
    ],
    "wof:name":"Paradise Smoothies",
    "wof:placetype":"venue"
},
  "geometry": {"coordinates":[-97.803865,30.470308],"type":"Point"}
}