{
  "type": "Feature",
  "properties": {
    "iso:country":"US",
    "sg:address":"14635 FM 1485",
    "sg:city":"Conroe",
    "sg:classifiers":[
        {
            "category":"Professional",
            "subcategory":"Business Services",
            "type":"Services"
        }
    ],
    "sg:phone":"+1 281 399 1980",
    "sg:postcode":"77306",
    "sg:province":"TX",
    "sg:tags":[
        "water",
        "treatment"
    ],
    "wof:name":"Clearwater Systems Inc",
    "wof:placetype":"venue"
},
  "geometry": {"coordinates":[-95.299443,30.237885],"type":"Point"}
}