{
  "type": "Feature",
  "properties": {
    "iso:country":"US",
    "sg:address":"4303 Larkspur St",
    "sg:city":"Houston",
    "sg:classifiers":[
        {
            "category":"Bars & Pubs",
            "type":"Food & Drink"
        }
    ],
    "sg:phone":"+1 713 734 0025",
    "sg:postcode":"77051",
    "sg:province":"TX",
    "sg:tags":[
        "drinking"
    ],
    "wof:name":"Paramount Lounge",
    "wof:placetype":"venue"
},
  "geometry": {"coordinates":[-95.361923,29.661307],"type":"Point"}
}