{
  "type": "Feature",
  "properties": {
    "iso:country":"US",
    "sg:address":"409 Bessemer Ave",
    "sg:city":"Llano",
    "sg:classifiers":[
        {
            "category":"Shopping",
            "subcategory":"Bicycles & Sporting Goods",
            "type":"Retail Goods"
        }
    ],
    "sg:phone":"+1 325 247 2754",
    "sg:postcode":"78643",
    "sg:province":"TX",
    "sg:tags":[
        "saddlery",
        "harness"
    ],
    "wof:name":"Doug's Saddle Shop",
    "wof:placetype":"venue"
},
  "geometry": {"coordinates":[-98.675809,30.755197],"type":"Point"}
}