{
  "type": "Feature",
  "properties": {
    "iso:country":"US",
    "sg:address":"2706 Foreman St",
    "sg:city":"Dallas",
    "sg:classifiers":[
        {
            "category":"Health Services",
            "subcategory":"Doctor",
            "type":"Services"
        }
    ],
    "sg:phone":"+1 214 303 1888",
    "sg:postcode":"75210",
    "sg:province":"TX",
    "sg:tags":[
        "physician",
        "family"
    ],
    "sg:website":"www.lifespanmedicine.com",
    "wof:name":"Lifespan Medicine",
    "wof:placetype":"venue"
},
  "geometry": {"coordinates":[-96.744615,32.774953],"type":"Point"}
}