{
  "type": "Feature",
  "properties": {
    "iso:country":"US",
    "sg:address":"4006 W Plano Pkwy",
    "sg:city":"Plano",
    "sg:classifiers":[
        {
            "category":"Retail",
            "subcategory":"Auto Rental",
            "type":"Services"
        }
    ],
    "sg:phone":"+1 972 867 6792",
    "sg:postcode":"75093",
    "sg:province":"TX",
    "sg:tags":[
        "renting",
        "automobile"
    ],
    "wof:name":"Hertz Rent A Car",
    "wof:placetype":"venue"
},
  "geometry": {"coordinates":[-96.767268,33.009958],"type":"Point"}
}