{
  "type": "Feature",
  "properties": {
    "iso:country":"US",
    "sg:address":"10922 Ridgeview Dr",
    "sg:city":"Houston",
    "sg:classifiers":[
        {
            "category":"Organizations",
            "subcategory":"Religious Organization",
            "type":"Services"
        }
    ],
    "sg:phone":"+1 713 468 5337",
    "sg:postcode":"77043",
    "sg:province":"TX",
    "wof:name":"Northams The",
    "wof:placetype":"venue"
},
  "geometry": {"coordinates":[-95.572841,29.805476],"type":"Point"}
}