{
  "type": "Feature",
  "properties": {
    "iso:country":"US",
    "sg:address":"101 Vinson St",
    "sg:city":"Arlington",
    "sg:classifiers":[
        {
            "category":"Shopping",
            "subcategory":"Pharmacy",
            "type":"Retail Goods"
        }
    ],
    "sg:phone":"+1 817 860 6661",
    "sg:postcode":"76010",
    "sg:province":"TX",
    "sg:tags":[
        "aid",
        "first",
        "supply"
    ],
    "sg:website":"www.greenguard.com",
    "wof:name":"Green Guard",
    "wof:placetype":"venue"
},
  "geometry": {"coordinates":[-97.10011900000001,32.735563],"type":"Point"}
}