{
  "type": "Feature",
  "properties": {
    "iso:country":"US",
    "sg:address":"265 N Main St",
    "sg:city":"Boerne",
    "sg:classifiers":[
        {
            "category":"Building & Trades",
            "subcategory":"Construction",
            "type":"Services"
        }
    ],
    "sg:phone":"+1 830 248 1265",
    "sg:postcode":"78006",
    "sg:province":"TX",
    "sg:tags":[
        "general",
        "contractor"
    ],
    "wof:name":"Kyle Construction Co",
    "wof:placetype":"venue"
},
  "geometry": {"coordinates":[-98.732304,29.79497],"type":"Point"}
}