{
  "type": "Feature",
  "properties": {
    "iso:country":"US",
    "sg:address":"3656 Fairview Dr",
    "sg:city":"Denton",
    "sg:classifiers":[
        {
            "category":"Professional",
            "type":"Services"
        }
    ],
    "sg:phone":"+1 940 321 1784",
    "sg:postcode":"76210",
    "sg:province":"TX",
    "wof:name":"Cosby Service",
    "wof:placetype":"venue"
},
  "geometry": {"coordinates":[-97.05117,33.132849],"type":"Point"}
}