{
  "type": "Feature",
  "properties": {
    "iso:country":"US",
    "sg:address":"3510 N 1st St",
    "sg:city":"Abilene",
    "sg:classifiers":[
        {
            "category":"Professional",
            "subcategory":"Accounting & Tax Preparation",
            "type":"Services"
        }
    ],
    "sg:phone":"+1 866 871 1040",
    "sg:postcode":"79603",
    "sg:province":"TX",
    "sg:tags":[
        "return",
        "preparation-business"
    ],
    "sg:website":"http://www.libertytax.com/",
    "wof:name":"Liberty Tax Service",
    "wof:placetype":"venue"
},
  "geometry": {"coordinates":[-99.766488,32.452131],"type":"Point"}
}