{
  "type": "Feature",
  "properties": {
    "iso:country":"US",
    "sg:address":"1517 Lake Air Dr",
    "sg:city":"Waco",
    "sg:classifiers":[
        {
            "category":"Arts & Performance",
            "subcategory":"Theater",
            "type":"Entertainment"
        }
    ],
    "sg:phone":"+1 254 776 1591",
    "sg:postcode":"76710",
    "sg:province":"TX",
    "sg:tags":[
        "theatrical"
    ],
    "wof:name":"Waco Civic Theatre Inc",
    "wof:placetype":"venue"
},
  "geometry": {"coordinates":[-97.188568,31.537244],"type":"Point"}
}