{
  "type": "Feature",
  "properties": {
    "iso:country":"US",
    "sg:address":"5 Benton St",
    "sg:city":"Dayton",
    "sg:classifiers":[
        {
            "category":"Building & Trades",
            "subcategory":"Construction",
            "type":"Services"
        }
    ],
    "sg:phone":"+1 936 257 8094",
    "sg:postcode":"77535",
    "sg:province":"TX",
    "sg:tags":[
        "carpenter"
    ],
    "wof:name":"B & A Carpentry & Yard Svc",
    "wof:placetype":"venue"
},
  "geometry": {"coordinates":[-94.89321200000001,30.054957],"type":"Point"}
}