{
  "type": "Feature",
  "properties": {
    "iso:country":"US",
    "sg:address":"1250 Slocum St",
    "sg:city":"Dallas",
    "sg:classifiers":[
        {
            "category":"Wholesale",
            "subcategory":"Non-durable Goods",
            "type":"Manufacturing & Wholesale Goods"
        }
    ],
    "sg:phone":"+1 214 741 6141",
    "sg:postcode":"75207",
    "sg:province":"TX",
    "sg:tags":[
        "shop",
        "store",
        "gift",
        "furniture"
    ],
    "sg:website":"www.decorativecrafts.com",
    "wof:name":"Decorative Crafts Inc",
    "wof:placetype":"venue"
},
  "geometry": {"coordinates":[-96.815793,32.789916],"type":"Point"}
}