{
  "type": "Feature",
  "properties": {
    "iso:country":"US",
    "sg:address":"28 Blaschke Rd",
    "sg:city":"Comfort",
    "sg:classifiers":[
        {
            "category":"Manufacturing",
            "subcategory":"Leather Goods",
            "type":"Manufacturing & Wholesale Goods"
        }
    ],
    "sg:phone":"+1 830 995 4898",
    "sg:postcode":"78013",
    "sg:province":"TX",
    "sg:tags":[
        "equipment",
        "industrial",
        "mfg"
    ],
    "wof:name":"Silver Star Enterprises",
    "wof:placetype":"venue"
},
  "geometry": {"coordinates":[-98.836173,29.916788],"type":"Point"}
}