{
  "type": "Feature",
  "properties": {
    "iso:country":"US",
    "sg:address":"4745 Westheimer Rd",
    "sg:city":"Houston",
    "sg:classifiers":[
        {
            "category":"Personal",
            "type":"Services"
        }
    ],
    "sg:phone":"+1 713 772 7715",
    "sg:postcode":"77027",
    "sg:province":"TX",
    "wof:name":"Weighco of Southwest Inc",
    "wof:placetype":"venue"
},
  "geometry": {"coordinates":[-95.45692099999999,29.74105],"type":"Point"}
}