{
  "type": "Feature",
  "properties": {
    "iso:country":"US",
    "sg:address":"4202 Santiago St",
    "sg:city":"Austin",
    "sg:classifiers":[
        {
            "category":"Wholesale",
            "subcategory":"Medical Equipment & Supplies",
            "type":"Manufacturing & Wholesale Goods"
        },
        {
            "category":"Shopping",
            "subcategory":"Pharmacy",
            "type":"Retail Goods"
        }
    ],
    "sg:phone":"+1 512 448 4489",
    "sg:postcode":"78745",
    "sg:province":"TX",
    "sg:tags":[
        "home",
        "health",
        "care"
    ],
    "wof:name":"Texas Medical-Mobility Specialists",
    "wof:placetype":"venue"
},
  "geometry": {"coordinates":[-97.754633,30.215439],"type":"Point"}
}