{
  "type": "Feature",
  "properties": {
    "iso:country":"US",
    "sg:address":"5553 Harvest Hill Rd",
    "sg:city":"Dallas",
    "sg:classifiers":[
        {
            "category":"Building & Trades",
            "subcategory":"Construction",
            "type":"Services"
        }
    ],
    "sg:phone":"+1 972 816 1616",
    "sg:postcode":"75230",
    "sg:province":"TX",
    "sg:tags":[
        "painter"
    ],
    "wof:name":"Berkowitz & Son Painting",
    "wof:placetype":"venue"
},
  "geometry": {"coordinates":[-96.812145,32.922592],"type":"Point"}
}