{
  "type": "Feature",
  "properties": {
    "iso:country":"US",
    "sg:address":"1527 State Hwy 114L Bus",
    "sg:city":"Grapevine",
    "sg:classifiers":[
        {
            "category":"Professional",
            "subcategory":"Advertising",
            "type":"Services"
        }
    ],
    "sg:phone":"+1 817 301 3030",
    "sg:postcode":"76051",
    "sg:province":"TX",
    "sg:tags":[
        "mail",
        "direct"
    ],
    "wof:name":"UPS Store",
    "wof:placetype":"venue"
},
  "geometry": {"coordinates":[-97.094325,32.941048],"type":"Point"}
}