{
  "type": "Feature",
  "properties": {
    "iso:country":"US",
    "sg:address":"119 W 3rd St",
    "sg:city":"Sweetwater",
    "sg:classifiers":[
        {
            "category":"Home & Garden",
            "subcategory":"Furniture",
            "type":"Retail Goods"
        }
    ],
    "sg:phone":"+1 325 235 2170",
    "sg:postcode":"79556",
    "sg:province":"TX",
    "wof:name":"Nolan Furniture",
    "wof:placetype":"venue"
},
  "geometry": {"coordinates":[-100.40914100000001,32.470823],"type":"Point"}
}