{
  "type": "Feature",
  "properties": {
    "iso:country":"US",
    "sg:address":"13402 Agarita Ln",
    "sg:city":"Houston",
    "sg:classifiers":[
        {
            "category":"Wholesale",
            "subcategory":"Jewelry",
            "type":"Manufacturing & Wholesale Goods"
        }
    ],
    "sg:phone":"+1 281 530 9808",
    "sg:postcode":"77083",
    "sg:province":"TX",
    "sg:tags":[
        "stone"
    ],
    "wof:name":"Silver Intl Trading Co",
    "wof:placetype":"venue"
},
  "geometry": {"coordinates":[-95.620374,29.708211],"type":"Point"}
}