{
  "type": "Feature",
  "properties": {
    "iso:country":"US",
    "sg:address":"9030 North Fwy Ste 115",
    "sg:city":"Houston",
    "sg:classifiers":[
        {
            "category":"Education",
            "subcategory":"Kindergarten",
            "type":"Public Place"
        }
    ],
    "sg:phone":"+1 281 448 0430",
    "sg:postcode":"77037",
    "sg:province":"TX",
    "sg:tags":[
        "school",
        "driving"
    ],
    "wof:name":"Saenz Defensive Driving",
    "wof:placetype":"venue"
},
  "geometry": {"coordinates":[-95.410167,29.890105],"type":"Point"}
}