{
  "type": "Feature",
  "properties": {
    "iso:country":"US",
    "sg:address":"1220 N Texas Blvd",
    "sg:city":"Alice",
    "sg:classifiers":[
        {
            "category":"Food & Beverages",
            "subcategory":"Specialty",
            "type":"Retail Goods"
        }
    ],
    "sg:phone":"+1 361 396 0092",
    "sg:postcode":"78332",
    "sg:province":"TX",
    "sg:tags":[
        "health",
        "diet"
    ],
    "wof:name":"Vitamin Explorer",
    "wof:placetype":"venue"
},
  "geometry": {"coordinates":[-98.064724,27.761544],"type":"Point"}
}