{
  "type": "Feature",
  "properties": {
    "iso:country":"US",
    "sg:address":"2230 W Southlake Blvd",
    "sg:city":"Southlake",
    "sg:classifiers":[
        {
            "category":"Personal",
            "subcategory":"Barber",
            "type":"Services"
        }
    ],
    "sg:phone":"+1 817 431 3593",
    "sg:postcode":"76092",
    "sg:province":"TX",
    "sg:tags":[
        "shop"
    ],
    "wof:name":"Barber of Southlake",
    "wof:placetype":"venue"
},
  "geometry": {"coordinates":[-97.186167,32.937406],"type":"Point"}
}