{
  "type": "Feature",
  "properties": {
    "iso:country":"US",
    "sg:address":"1200 Lantana St",
    "sg:city":"Corpus Christi",
    "sg:classifiers":[
        {
            "category":"Education",
            "subcategory":"College",
            "type":"Public Place"
        }
    ],
    "sg:phone":"+1 361 289 9095",
    "sg:postcode":"78407",
    "sg:province":"TX",
    "sg:tags":[
        "undergraduate",
        "arts",
        "liberal",
        "institution",
        "higher"
    ],
    "wof:name":"Our Lady Of Corpus Christi",
    "wof:placetype":"venue"
},
  "geometry": {"coordinates":[-97.47150499999999,27.805586],"type":"Point"}
}