{
  "type": "Feature",
  "properties": {
    "iso:country":"US",
    "sg:address":"4301 Bissonnet St",
    "sg:city":"Bellaire",
    "sg:classifiers":[
        {
            "category":"Professional",
            "type":"Services"
        }
    ],
    "sg:phone":"+1 713 349 9894",
    "sg:postcode":"77401",
    "sg:province":"TX",
    "wof:name":"Lesile Anns",
    "wof:placetype":"venue"
},
  "geometry": {"coordinates":[-95.448527,29.717523],"type":"Point"}
}