{
  "type": "Feature",
  "properties": {
    "iso:country":"US",
    "sg:address":"10025 Lazy Oaks St",
    "sg:city":"Houston",
    "sg:classifiers":[
        {
            "category":"Professional",
            "subcategory":"Engineering",
            "type":"Services"
        }
    ],
    "sg:phone":"+1 713 935 0039",
    "sg:postcode":"77080",
    "sg:province":"TX",
    "sg:tags":[
        "consultant"
    ],
    "wof:name":"Mike Schrock Consulting",
    "wof:placetype":"venue"
},
  "geometry": {"coordinates":[-95.543809,29.799154],"type":"Point"}
}