{
  "type": "Feature",
  "properties": {
    "iso:country":"US",
    "sg:address":"1629 Montana Ave",
    "sg:city":"El Paso",
    "sg:classifiers":[
        {
            "category":"Home & Garden",
            "subcategory":"Furniture",
            "type":"Retail Goods"
        }
    ],
    "sg:phone":"+1 915 851 5173",
    "sg:postcode":"79902",
    "sg:province":"TX",
    "wof:name":"Carlos Vazquez",
    "wof:placetype":"venue"
},
  "geometry": {"coordinates":[-106.47672900000001,31.773555],"type":"Point"}
}