{
  "type": "Feature",
  "properties": {
    "iso:country":"US",
    "sg:address":"7400 Merton Minter",
    "sg:city":"San Antonio",
    "sg:classifiers":[
        {
            "category":"Organizations",
            "subcategory":"Non-profit Organization",
            "type":"Services"
        }
    ],
    "sg:phone":"+1 210 617 5285",
    "sg:postcode":"78284",
    "sg:province":"TX",
    "wof:name":"Biomedical Research Foundation",
    "wof:placetype":"venue"
},
  "geometry": {"coordinates":[-98.58056999999999,29.503345],"type":"Point"}
}