{
  "type": "Feature",
  "properties": {
    "iso:country":"US",
    "sg:address":"2620 Brickyard Rd",
    "sg:city":"Beaumont",
    "sg:classifiers":[
        {
            "category":"Organizations",
            "subcategory":"Labor Organization",
            "type":"Services"
        }
    ],
    "sg:phone":"+1 409 892 2361",
    "sg:postcode":"77703",
    "sg:province":"TX",
    "wof:name":"Sunny Inves",
    "wof:placetype":"venue"
},
  "geometry": {"coordinates":[-94.125242,30.10391],"type":"Point"}
}