{
  "type": "Feature",
  "properties": {
    "iso:country":"US",
    "sg:address":"475 Starlight Dr",
    "sg:city":"Ingleside",
    "sg:classifiers":[
        {
            "category":"Government",
            "subcategory":"Office",
            "type":"Public Place"
        }
    ],
    "sg:phone":"+1 361 776 5451",
    "sg:postcode":"78362",
    "sg:province":"TX",
    "sg:tags":[
        "village"
    ],
    "wof:name":"City Of Ingleside On Bay",
    "wof:placetype":"venue"
},
  "geometry": {"coordinates":[-97.220592,27.831269],"type":"Point"}
}