{
  "type": "Feature",
  "properties": {
    "iso:country":"US",
    "sg:address":"3302 Westwood Cir",
    "sg:city":"Rowlett",
    "sg:classifiers":[
        {
            "category":"Professional",
            "subcategory":"Management & Consulting",
            "type":"Services"
        }
    ],
    "sg:phone":"+1 972 412 2112",
    "sg:postcode":"75088",
    "sg:province":"TX",
    "wof:name":"All Custom",
    "wof:placetype":"venue"
},
  "geometry": {"coordinates":[-96.573038,32.893873],"type":"Point"}
}