{
  "type": "Feature",
  "properties": {
    "iso:country":"US",
    "sg:address":"405 N Gaston Dr",
    "sg:city":"Wylie",
    "sg:classifiers":[
        {
            "category":"Professional",
            "subcategory":"Detective & Security Services",
            "type":"Services"
        }
    ],
    "sg:phone":"+1 972 429 5191",
    "sg:postcode":"75098",
    "sg:province":"TX",
    "sg:tags":[
        "car"
    ],
    "wof:name":"Fpg Security & Assoc",
    "wof:placetype":"venue"
},
  "geometry": {"coordinates":[-96.54757499999999,33.022928],"type":"Point"}
}