{
  "type": "Feature",
  "properties": {
    "iso:country":"US",
    "sg:address":"9550 Homestead Rd",
    "sg:city":"Houston",
    "sg:classifiers":[
        {
            "category":"Food & Beverages",
            "subcategory":"Groceries & Convenience Stores",
            "type":"Retail Goods"
        }
    ],
    "sg:phone":"+1 713 631 6780",
    "sg:postcode":"77016",
    "sg:province":"TX",
    "wof:name":"Supervalu",
    "wof:placetype":"venue"
},
  "geometry": {"coordinates":[-95.301378,29.849719],"type":"Point"}
}