{
  "type": "Feature",
  "properties": {
    "iso:country":"US",
    "sg:address":"17417 Sleepy Hollow Dr",
    "sg:city":"Leander",
    "sg:classifiers":[
        {
            "category":"Professional",
            "type":"Services"
        }
    ],
    "sg:phone":"+1 512 267 9341",
    "sg:postcode":"78645",
    "sg:province":"TX",
    "wof:name":"Riley R Simon Family Part",
    "wof:placetype":"venue"
},
  "geometry": {"coordinates":[-97.95651700000001,30.412344],"type":"Point"}
}