{
  "type": "Feature",
  "properties": {
    "iso:country":"US",
    "sg:address":"2218 Burnside St",
    "sg:city":"Laredo",
    "sg:classifiers":[
        {
            "category":"Building & Trades",
            "subcategory":"Construction",
            "type":"Services"
        }
    ],
    "sg:phone":"+1 956 722 5681",
    "sg:postcode":"78040",
    "sg:province":"TX",
    "sg:tags":[
        "contractor"
    ],
    "wof:name":"L Ortiz Masonry",
    "wof:placetype":"venue"
},
  "geometry": {"coordinates":[-99.516137,27.529259],"type":"Point"}
}