{
  "type": "Feature",
  "properties": {
    "iso:country":"US",
    "sg:address":"514 N Van Buren St",
    "sg:city":"Henderson",
    "sg:classifiers":[
        {
            "category":"Organizations",
            "subcategory":"Non-profit Organization",
            "type":"Services"
        }
    ],
    "sg:phone":"+1 903 657 4227",
    "sg:postcode":"75652",
    "sg:province":"TX",
    "sg:tags":[
        "social"
    ],
    "wof:name":"Meals On Wheels of Palestine",
    "wof:placetype":"venue"
},
  "geometry": {"coordinates":[-94.804999,32.163823],"type":"Point"}
}