{
  "type": "Feature",
  "properties": {
    "iso:country":"US",
    "sg:address":"6933 Stonewall Rd",
    "sg:city":"Fort Worth",
    "sg:classifiers":[
        {
            "category":"Professional",
            "subcategory":"Art Services",
            "type":"Services"
        }
    ],
    "sg:phone":"+1 817 293 9105",
    "sg:postcode":"76140",
    "sg:province":"TX",
    "sg:tags":[
        "graphic",
        "designer"
    ],
    "wof:name":"Janet Benton Graphic Design",
    "wof:placetype":"venue"
},
  "geometry": {"coordinates":[-97.276597,32.653939],"type":"Point"}
}