{
  "type": "Feature",
  "properties": {
    "iso:country":"US",
    "sg:address":"2700 N Surrey Dr",
    "sg:city":"Carrollton",
    "sg:classifiers":[
        {
            "category":"Banks & Credit Unions",
            "subcategory":"Investment Brokerage",
            "type":"Services"
        }
    ],
    "sg:phone":"+1 972 417 0843",
    "sg:postcode":"75006",
    "sg:province":"TX",
    "sg:tags":[
        "tape",
        "video",
        "sale",
        "dvds-rental"
    ],
    "wof:name":"Moving Memories Video",
    "wof:placetype":"venue"
},
  "geometry": {"coordinates":[-96.862617,32.96743],"type":"Point"}
}