{
  "type": "Feature",
  "properties": {
    "iso:country":"US",
    "sg:address":"619 Wolf St",
    "sg:city":"Killeen",
    "sg:classifiers":[
        {
            "category":"Retail",
            "subcategory":"Auto Repair",
            "type":"Services"
        }
    ],
    "sg:phone":"+1 254 554 5077",
    "sg:postcode":"76541",
    "sg:province":"TX",
    "sg:tags":[
        "repairing",
        "automobile"
    ],
    "wof:name":"Oscar The Mechanic",
    "wof:placetype":"venue"
},
  "geometry": {"coordinates":[-97.736976,31.113771],"type":"Point"}
}