{
  "type": "Feature",
  "properties": {
    "iso:country":"US",
    "sg:address":"1740 Austin Hwy",
    "sg:city":"San Antonio",
    "sg:classifiers":[
        {
            "category":"Home & Garden",
            "subcategory":"Mobile Homes",
            "type":"Retail Goods"
        }
    ],
    "sg:phone":"+1 210 822 2273",
    "sg:postcode":"78218",
    "sg:province":"TX",
    "wof:name":"Mission Homes",
    "wof:placetype":"venue"
},
  "geometry": {"coordinates":[-98.428208,29.496183],"type":"Point"}
}