{
  "type": "Feature",
  "properties": {
    "iso:country":"US",
    "sg:address":"407 Spring Mill Dr",
    "sg:city":"Kerrville",
    "sg:classifiers":[
        {
            "category":"Building & Trades",
            "subcategory":"Construction",
            "type":"Services"
        }
    ],
    "sg:phone":"+1 830 896 3524",
    "sg:postcode":"78028",
    "sg:province":"TX",
    "wof:name":"Benchmark Design Build",
    "wof:placetype":"venue"
},
  "geometry": {"coordinates":[-99.133546,30.01251],"type":"Point"}
}