{
  "type": "Feature",
  "properties": {
    "iso:country":"US",
    "sg:address":"301 S Meadow Ave",
    "sg:city":"Odessa",
    "sg:classifiers":[
        {
            "category":"Wholesale",
            "subcategory":"Machinery & Supplies",
            "type":"Manufacturing & Wholesale Goods"
        }
    ],
    "sg:phone":"+1 432 582 2921",
    "sg:postcode":"79761",
    "sg:province":"TX",
    "sg:tags":[
        "contractor"
    ],
    "wof:name":"B J Independent",
    "wof:placetype":"venue"
},
  "geometry": {"coordinates":[-102.336286,31.848027],"type":"Point"}
}