{
  "type": "Feature",
  "properties": {
    "iso:country":"US",
    "sg:address":"769 Villa Vanessa Dr",
    "sg:city":"El Paso",
    "sg:classifiers":[
        {
            "category":"Professional",
            "subcategory":"Computer Services",
            "type":"Services"
        }
    ],
    "sg:phone":"+1 915 833 6163",
    "sg:postcode":"79912",
    "sg:province":"TX",
    "sg:tags":[
        "programing",
        "custom"
    ],
    "wof:name":"Akademos Latam Inc",
    "wof:placetype":"venue"
},
  "geometry": {"coordinates":[-106.552027,31.854496],"type":"Point"}
}