{
  "type": "Feature",
  "properties": {
    "iso:country":"US",
    "sg:address":"300 S Stemmons St",
    "sg:city":"Sanger",
    "sg:classifiers":[
        {
            "category":"Building & Trades",
            "subcategory":"Landscaping Services",
            "type":"Services"
        }
    ],
    "sg:phone":"+1 940 458 5674",
    "sg:postcode":"76266",
    "sg:province":"TX",
    "sg:tags":[
        "lawn",
        "designer",
        "stump",
        "consultant",
        "tree",
        "grinding",
        "contractor",
        "arborist",
        "removal",
        "landscape"
    ],
    "sg:website":"http://www.lovelacelandscape.com",
    "wof:name":"Lovelace Landscape & Tree Service",
    "wof:placetype":"venue"
},
  "geometry": {"coordinates":[-97.181877,33.3592],"type":"Point"}
}