{
  "type": "Feature",
  "properties": {
    "iso:country":"US",
    "sg:address":"1122 W Dallas St",
    "sg:city":"Conroe",
    "sg:classifiers":[
        {
            "category":"Freight",
            "type":"Transportation"
        }
    ],
    "sg:phone":"+1 281 367 0818",
    "sg:postcode":"77301",
    "sg:province":"TX",
    "sg:tags":[
        "operator",
        "local",
        "trucking"
    ],
    "wof:name":"Enforcer Trucking",
    "wof:placetype":"venue"
},
  "geometry": {"coordinates":[-95.468842,30.316211],"type":"Point"}
}