{
  "type": "Feature",
  "properties": {
    "iso:country":"US",
    "sg:address":"4624 Erie Dr",
    "sg:city":"Midland",
    "sg:classifiers":[
        {
            "category":"Professional",
            "subcategory":"Business Services",
            "type":"Services"
        }
    ],
    "sg:phone":"+1 432 520 4624",
    "sg:postcode":"79703",
    "sg:province":"TX",
    "wof:name":"Masters Design",
    "wof:placetype":"venue"
},
  "geometry": {"coordinates":[-102.13619799999999,31.978078],"type":"Point"}
}