{
  "type": "Feature",
  "properties": {
    "iso:country":"US",
    "sg:address":"407 S Main St",
    "sg:city":"Winnsboro",
    "sg:classifiers":[
        {
            "category":"Professional",
            "subcategory":"Business Services",
            "type":"Services"
        }
    ],
    "sg:phone":"+1 903 342 6051",
    "sg:postcode":"75494",
    "sg:province":"TX",
    "wof:name":"Oaklea Mansion Inc",
    "wof:placetype":"venue"
},
  "geometry": {"coordinates":[-95.291326,32.95442],"type":"Point"}
}