{
  "type": "Feature",
  "properties": {
    "iso:country":"US",
    "sg:address":"4907 Holly Tree Dr",
    "sg:city":"Dallas",
    "sg:classifiers":[
        {
            "category":"Professional",
            "subcategory":"Employment Agencies",
            "type":"Services"
        }
    ],
    "sg:phone":"+1 972 250 1740",
    "sg:postcode":"75287",
    "sg:province":"TX",
    "sg:tags":[
        "opportunity"
    ],
    "wof:name":"Drake Agency",
    "wof:placetype":"venue"
},
  "geometry": {"coordinates":[-96.82238099999999,32.99863],"type":"Point"}
}