{
  "type": "Feature",
  "properties": {
    "iso:country":"US",
    "sg:address":"6965 Commerce Ave",
    "sg:city":"El Paso",
    "sg:classifiers":[
        {
            "category":"Freight",
            "type":"Transportation"
        }
    ],
    "sg:phone":"+1 915 778 4271",
    "sg:postcode":"79915",
    "sg:province":"TX",
    "sg:tags":[
        "distance",
        "storage",
        "long",
        "moving",
        "mover",
        "local"
    ],
    "wof:name":"Allied Van Lines Agent",
    "wof:placetype":"venue"
},
  "geometry": {"coordinates":[-106.380892,31.771143],"type":"Point"}
}