{
  "type": "Feature",
  "properties": {
    "iso:country":"US",
    "sg:address":"506 Medical Center Blvd",
    "sg:city":"Conroe",
    "sg:classifiers":[
        {
            "category":"Health Services",
            "subcategory":"Doctor",
            "type":"Services"
        }
    ],
    "sg:phone":"+1 936 760 8525",
    "sg:postcode":"77304",
    "sg:province":"TX",
    "sg:tags":[
        "physician",
        "rheumatology",
        "arthritis",
        "surgeons",
        "surgeon"
    ],
    "wof:name":"Parke Frank Md",
    "wof:placetype":"venue"
},
  "geometry": {"coordinates":[-95.46627599999999,30.284454],"type":"Point"}
}