{
  "type": "Feature",
  "properties": {
    "iso:country":"US",
    "sg:address":"606 W Richards St",
    "sg:city":"Overton",
    "sg:classifiers":[
        {
            "category":"Professional",
            "subcategory":"Art Services",
            "type":"Services"
        }
    ],
    "sg:phone":"+1 903 283 1657",
    "sg:postcode":"75684",
    "sg:province":"TX",
    "sg:tags":[
        "designer",
        "display",
        "producer"
    ],
    "wof:name":"Cic Designs",
    "wof:placetype":"venue"
},
  "geometry": {"coordinates":[-94.98638200000001,32.27486],"type":"Point"}
}