{
  "type": "Feature",
  "properties": {
    "iso:country":"US",
    "sg:address":"517 Ave B",
    "sg:city":"Sinton",
    "sg:classifiers":[
        {
            "category":"Food & Beverages",
            "subcategory":"Groceries & Convenience Stores",
            "type":"Retail Goods"
        }
    ],
    "sg:phone":"+1 361 364 2107",
    "sg:postcode":"78387",
    "sg:province":"TX",
    "sg:tags":[
        "grocer"
    ],
    "wof:name":"Flores Grocery",
    "wof:placetype":"venue"
},
  "geometry": {"coordinates":[-97.50848000000001,28.03243],"type":"Point"}
}