{
  "type": "Feature",
  "properties": {
    "iso:country":"US",
    "sg:address":"1704 W Koenig Ln",
    "sg:city":"Austin",
    "sg:classifiers":[
        {
            "category":"Professional",
            "subcategory":"Computer Services",
            "type":"Services"
        }
    ],
    "sg:phone":"+1 512 450 1700",
    "sg:postcode":"78756",
    "sg:province":"TX",
    "sg:tags":[
        "repair"
    ],
    "sg:website":"www.austingeeks.com",
    "wof:name":"Computer Geeks",
    "wof:placetype":"venue"
},
  "geometry": {"coordinates":[-97.7351,30.332584],"type":"Point"}
}