{
  "type": "Feature",
  "properties": {
    "iso:country":"US",
    "sg:address":"907 E Rice St",
    "sg:city":"Falfurrias",
    "sg:classifiers":[
        {
            "category":"Building & Trades",
            "subcategory":"Electrical",
            "type":"Services"
        }
    ],
    "sg:phone":"+1 361 325 2308",
    "sg:postcode":"78355",
    "sg:province":"TX",
    "sg:tags":[
        "electric",
        "contractor"
    ],
    "wof:name":"Raul Guerra's Electric",
    "wof:placetype":"venue"
},
  "geometry": {"coordinates":[-98.13483600000001,27.225741],"type":"Point"}
}