{
  "type": "Feature",
  "properties": {
    "iso:country":"US",
    "sg:address":"923 New Dallas Hwy",
    "sg:city":"Waco",
    "sg:classifiers":[
        {
            "category":"Autos & Motor Vehicles",
            "subcategory":"Auto Supplies",
            "type":"Retail Goods"
        }
    ],
    "sg:phone":"+1 254 799 6848",
    "sg:postcode":"76705",
    "sg:province":"TX",
    "sg:tags":[
        "tire"
    ],
    "wof:name":"Alvarado's Tire Shop",
    "wof:placetype":"venue"
},
  "geometry": {"coordinates":[-97.11127999999999,31.603648],"type":"Point"}
}