{
  "type": "Feature",
  "properties": {
    "iso:country":"US",
    "sg:address":"1485 Calder Ave",
    "sg:city":"Beaumont",
    "sg:classifiers":[
        {
            "category":"Professional",
            "subcategory":"Business Services",
            "type":"Services"
        }
    ],
    "sg:phone":"+1 409 833 7007",
    "sg:postcode":"77701",
    "sg:province":"TX",
    "sg:tags":[
        "architectural"
    ],
    "wof:name":"James Steinmeyer Associates",
    "wof:placetype":"venue"
},
  "geometry": {"coordinates":[-94.10985700000001,30.085912],"type":"Point"}
}