{
  "type": "Feature",
  "properties": {
    "iso:country":"US",
    "sg:address":"512 Colgate Dr",
    "sg:city":"Allen",
    "sg:classifiers":[
        {
            "category":"Professional",
            "subcategory":"Business Services",
            "type":"Services"
        }
    ],
    "sg:phone":"+1 972 747 1096",
    "sg:postcode":"75013",
    "sg:province":"TX",
    "wof:name":"Long Colt Enterprises",
    "wof:placetype":"venue"
},
  "geometry": {"coordinates":[-96.708568,33.091715],"type":"Point"}
}