{
  "type": "Feature",
  "properties": {
    "iso:country":"US",
    "sg:address":"310 State Highway 78 N",
    "sg:city":"Farmersville",
    "sg:classifiers":[
        {
            "category":"Place Of Worship",
            "subcategory":"Church",
            "type":"Public Place"
        },
        {
            "category":"Place Of Worship",
            "type":"Public Place"
        }
    ],
    "sg:phone":"+1 972 784 6176",
    "sg:postcode":"75442",
    "sg:province":"TX",
    "sg:tags":[
        "testament",
        "churches-church",
        "christ",
        "christ-new"
    ],
    "wof:name":"Farmersville Church Of Ch",
    "wof:placetype":"venue"
},
  "geometry": {"coordinates":[-96.369355,33.165281],"type":"Point"}
}