{
  "type": "Feature",
  "properties": {
    "iso:country":"US",
    "sg:address":"1104 W Co Rd 114",
    "sg:city":"Midland",
    "sg:classifiers":[
        {
            "category":"Manufacturing",
            "subcategory":"Glass & Minerals",
            "type":"Manufacturing & Wholesale Goods"
        }
    ],
    "sg:phone":"+1 432 570 4030",
    "sg:postcode":"79706",
    "sg:province":"TX",
    "sg:tags":[
        "pipe",
        "drain"
    ],
    "wof:name":"Hayes Pipe & Equipment",
    "wof:placetype":"venue"
},
  "geometry": {"coordinates":[-102.07417100000001,31.96528],"type":"Point"}
}