{
  "type": "Feature",
  "properties": {
    "iso:country":"US",
    "sg:address":"9602 S Padre Island Dr",
    "sg:city":"Corpus Christi",
    "sg:classifiers":[
        {
            "category":"Food & Beverages",
            "subcategory":"Groceries & Convenience Stores",
            "type":"Retail Goods"
        }
    ],
    "sg:phone":"+1 361 939 9333",
    "sg:postcode":"78418",
    "sg:province":"TX",
    "wof:name":"Circle K",
    "wof:placetype":"venue"
},
  "geometry": {"coordinates":[-97.29611,27.675293],"type":"Point"}
}