{
  "type": "Feature",
  "properties": {
    "iso:country":"US",
    "sg:address":"4900 La Crosse Ave",
    "sg:city":"Austin",
    "sg:classifiers":[
        {
            "category":"Recreation",
            "type":"Entertainment"
        }
    ],
    "sg:postcode":"78739",
    "sg:province":"TX",
    "sg:tags":[
        "active",
        "life"
    ],
    "sg:website":"www.veloway.com",
    "wof:name":"Veloway",
    "wof:placetype":"venue"
},
  "geometry": {"coordinates":[-97.872506,30.190254],"type":"Point"}
}