{
  "type": "Feature",
  "properties": {
    "iso:country":"US",
    "sg:address":"12802 Noel Rd",
    "sg:city":"Dallas",
    "sg:classifiers":[
        {
            "category":"Building & Trades",
            "subcategory":"Cleaning & Sanitation",
            "type":"Services"
        }
    ],
    "sg:phone":"+1 972 490 3681",
    "sg:postcode":"75230",
    "sg:province":"TX",
    "sg:tags":[
        "maintenance"
    ],
    "wof:name":"AV Nice Cleaning Services",
    "wof:placetype":"venue"
},
  "geometry": {"coordinates":[-96.814966,32.922598],"type":"Point"}
}