{
  "type": "Feature",
  "properties": {
    "iso:country":"US",
    "sg:address":"3701 Decatur Ave",
    "sg:city":"Fort Worth",
    "sg:classifiers":[
        {
            "category":"Cinema",
            "subcategory":"Movie Rental",
            "type":"Entertainment"
        }
    ],
    "sg:phone":"+1 817 740 1110",
    "sg:postcode":"76106",
    "sg:province":"TX",
    "sg:tags":[
        "video",
        "tape"
    ],
    "wof:name":"Galaxy Video",
    "wof:placetype":"venue"
},
  "geometry": {"coordinates":[-97.339586,32.812137],"type":"Point"}
}