{
  "type": "Feature",
  "properties": {
    "iso:country":"US",
    "sg:address":"315 S Lockwood Dr",
    "sg:city":"Houston",
    "sg:classifiers":[
        {
            "category":"Personal",
            "subcategory":"Beauty Salon",
            "type":"Services"
        }
    ],
    "sg:phone":"+1 713 921 5528",
    "sg:postcode":"77011",
    "sg:province":"TX",
    "sg:tags":[
        "shop"
    ],
    "wof:name":"Peluqueria Tierra Caliente",
    "wof:placetype":"venue"
},
  "geometry": {"coordinates":[-95.328453,29.743645],"type":"Point"}
}