{
  "type": "Feature",
  "properties": {
    "iso:country":"US",
    "sg:address":"300 W Main St",
    "sg:city":"Hallsville",
    "sg:classifiers":[
        {
            "category":"Ice Cream",
            "type":"Food & Drink"
        }
    ],
    "sg:menulink":"http://www.allmenus.com/tx/hallsville/162269-dairy-queen/menu/",
    "sg:phone":"+1 903 668 2213",
    "sg:postcode":"75650",
    "sg:province":"TX",
    "sg:tags":[
        "burger",
        "american"
    ],
    "wof:name":"Dairy Queen",
    "wof:placetype":"venue"
},
  "geometry": {"coordinates":[-94.577309,32.504138],"type":"Point"}
}