{
  "type": "Feature",
  "properties": {
    "iso:country":"US",
    "sg:address":"614 W 31st St",
    "sg:city":"Austin",
    "sg:classifiers":[
        {
            "category":"Organizations",
            "subcategory":"Membership Organization",
            "type":"Services"
        }
    ],
    "sg:phone":"+1 512 450 1518",
    "sg:postcode":"78705",
    "sg:province":"TX",
    "wof:name":"Rosedale Foundation Inc",
    "wof:placetype":"venue"
},
  "geometry": {"coordinates":[-97.742626,30.298649],"type":"Point"}
}