{
  "type": "Feature",
  "properties": {
    "iso:country":"US",
    "sg:address":"2840 Keller Springs Rd Ste 1201",
    "sg:city":"Carrollton",
    "sg:classifiers":[
        {
            "category":"Health Services",
            "subcategory":"Health Practitioner",
            "type":"Services"
        }
    ],
    "sg:phone":"+1 972 416 5658",
    "sg:postcode":"75006",
    "sg:province":"TX",
    "sg:tags":[
        "acupuncture"
    ],
    "wof:name":"Acupuncture & Herb Clinic Of Pingping",
    "wof:placetype":"venue"
},
  "geometry": {"coordinates":[-96.856904,32.969962],"type":"Point"}
}