{
  "type": "Feature",
  "properties": {
    "iso:country":"US",
    "sg:address":"5510 Brittmoore Rd",
    "sg:city":"Houston",
    "sg:classifiers":[
        {
            "category":"Wholesale",
            "subcategory":"Machinery & Supplies",
            "type":"Manufacturing & Wholesale Goods"
        }
    ],
    "sg:phone":"+1 713 944 0319",
    "sg:postcode":"77041",
    "sg:province":"TX",
    "sg:tags":[
        "janitor"
    ],
    "wof:name":"Atex Wholesale Supply",
    "wof:placetype":"venue"
},
  "geometry": {"coordinates":[-95.57015,29.849165],"type":"Point"}
}