{
  "type": "Feature",
  "properties": {
    "iso:country":"US",
    "sg:address":"6801 McPherson Ave",
    "sg:city":"Laredo",
    "sg:classifiers":[
        {
            "category":"Shopping",
            "subcategory":"Optical Goods",
            "type":"Retail Goods"
        }
    ],
    "sg:phone":"+1 956 753 7373",
    "sg:postcode":"78041",
    "sg:province":"TX",
    "wof:name":"Flores Eye Care Clinic",
    "wof:placetype":"venue"
},
  "geometry": {"coordinates":[-99.473111,27.565398],"type":"Point"}
}