{
  "type": "Feature",
  "properties": {
    "iso:country":"US",
    "sg:address":"828 W Commerce St",
    "sg:city":"San Antonio",
    "sg:classifiers":[
        {
            "category":"Home & Garden",
            "subcategory":"Hardware",
            "type":"Retail Goods"
        }
    ],
    "sg:phone":"+1 210 222 9811",
    "sg:postcode":"78207",
    "sg:province":"TX",
    "wof:name":"Estrada True Value Hardware",
    "wof:placetype":"venue"
},
  "geometry": {"coordinates":[-98.503494,29.425956],"type":"Point"}
}