{
  "type": "Feature",
  "properties": {
    "iso:country":"US",
    "sg:address":"2013 N FM 1417",
    "sg:city":"Sherman",
    "sg:classifiers":[
        {
            "category":"Retail",
            "subcategory":"Veterinary Services",
            "type":"Services"
        }
    ],
    "sg:phone":"+1 903 893 0163",
    "sg:postcode":"75092",
    "sg:province":"TX",
    "wof:name":"Canyon Creek Pet Hospital",
    "wof:placetype":"venue"
},
  "geometry": {"coordinates":[-96.642274,33.654006],"type":"Point"}
}