{
  "type": "Feature",
  "properties": {
    "iso:country":"US",
    "sg:address":"5085 Westheimer Rd",
    "sg:city":"Houston",
    "sg:classifiers":[
        {
            "category":"Shopping",
            "subcategory":"Hobbies, Toys, & Games",
            "type":"Retail Goods"
        }
    ],
    "sg:phone":"+1 713 355 3388",
    "sg:postcode":"77056",
    "sg:province":"TX",
    "sg:tags":[
        "toy",
        "store"
    ],
    "wof:name":"Build-A-Bear Workshop",
    "wof:placetype":"venue"
},
  "geometry": {"coordinates":[-95.4636,29.740601],"type":"Point"}
}