{
  "type": "Feature",
  "properties": {
    "iso:country":"US",
    "sg:address":"24420 FM 1314",
    "sg:city":"Porter",
    "sg:classifiers":[
        {
            "category":"Shopping",
            "type":"Retail Goods"
        }
    ],
    "sg:phone":"+1 281 572 2881",
    "sg:postcode":"77365",
    "sg:province":"TX",
    "sg:tags":[
        "wedding",
        "supply"
    ],
    "wof:name":"Memory Maker Videos",
    "wof:placetype":"venue"
},
  "geometry": {"coordinates":[-95.24171,30.104532],"type":"Point"}
}