{
  "type": "Feature",
  "properties": {
    "iso:country":"US",
    "sg:address":"127 Creek Bend Blvd",
    "sg:city":"Nacogdoches",
    "sg:classifiers":[
        {
            "category":"Health Services",
            "subcategory":"Clinic",
            "type":"Services"
        }
    ],
    "sg:phone":"+1 936 560 4002",
    "sg:postcode":"75965",
    "sg:province":"TX",
    "wof:name":"Integrity Health Services",
    "wof:placetype":"venue"
},
  "geometry": {"coordinates":[-94.65562199999999,31.645976],"type":"Point"}
}