{
  "type": "Feature",
  "properties": {
    "iso:country":"US",
    "sg:address":"1000 Preston Rd",
    "sg:city":"Plano",
    "sg:classifiers":[
        {
            "category":"Home & Garden",
            "subcategory":"Garden Supply",
            "type":"Retail Goods"
        }
    ],
    "sg:phone":"+1 972 964 3084",
    "sg:postcode":"75093",
    "sg:province":"TX",
    "sg:tags":[
        "landscaping",
        "lawn",
        "nursery",
        "gardening",
        "nurseryman"
    ],
    "sg:website":"http://www.calloways.com",
    "wof:name":"Calloway's Nursery",
    "wof:placetype":"venue"
},
  "geometry": {"coordinates":[-96.795097,33.013302],"type":"Point"}
}