{
  "type": "Feature",
  "properties": {
    "iso:country":"US",
    "sg:address":"14522 S Post Oak Rd Ste A",
    "sg:city":"Houston",
    "sg:classifiers":[
        {
            "category":"Retail",
            "subcategory":"Laundry & Dry Cleaning",
            "type":"Services"
        }
    ],
    "sg:phone":"+1 713 413 3323",
    "sg:postcode":"77045",
    "sg:province":"TX",
    "wof:name":"B K Cleaners",
    "wof:placetype":"venue"
},
  "geometry": {"coordinates":[-95.465502,29.615869],"type":"Point"}
}