{
  "type": "Feature",
  "properties": {
    "iso:country":"US",
    "sg:address":"423 Birch Ln",
    "sg:city":"Richardson",
    "sg:classifiers":[
        {
            "category":"Professional",
            "subcategory":"Business Services",
            "type":"Services"
        }
    ],
    "sg:phone":"+1 972 437 0489",
    "sg:postcode":"75081",
    "sg:province":"TX",
    "wof:name":"Kema & Assoc",
    "wof:placetype":"venue"
},
  "geometry": {"coordinates":[-96.729107,32.931512],"type":"Point"}
}