{
  "type": "Feature",
  "properties": {
    "iso:country":"US",
    "sg:address":"2900 Cullen St",
    "sg:city":"Fort Worth",
    "sg:classifiers":[
        {
            "category":"Manufacturing",
            "subcategory":"Apparel",
            "type":"Manufacturing & Wholesale Goods"
        }
    ],
    "sg:phone":"+1 817 332 4493",
    "sg:postcode":"76107",
    "sg:province":"TX",
    "sg:tags":[
        "awning",
        "mfg",
        "tarpaulin",
        "tent"
    ],
    "wof:name":"Acme Tent & Awning Inc",
    "wof:placetype":"venue"
},
  "geometry": {"coordinates":[-97.360991,32.762012],"type":"Point"}
}