{
  "type": "Feature",
  "properties": {
    "iso:country":"US",
    "sg:address":"9000 Bellaire Blvd",
    "sg:city":"Houston",
    "sg:classifiers":[
        {
            "category":"Education",
            "subcategory":"School",
            "type":"Public Place"
        }
    ],
    "sg:phone":"+1 713 219 5400",
    "sg:postcode":"77036",
    "sg:province":"TX",
    "sg:tags":[
        "secondary"
    ],
    "sg:website":"www.st-agnes.org",
    "wof:name":"St Agnes Academy",
    "wof:placetype":"venue"
},
  "geometry": {"coordinates":[-95.542603,29.7052],"type":"Point"}
}