{
  "type": "Feature",
  "properties": {
    "iso:country":"US",
    "sg:address":"8178 Nelson Dr",
    "sg:city":"Dallas",
    "sg:classifiers":[
        {
            "category":"Organizations",
            "subcategory":"Religious Organization",
            "type":"Services"
        }
    ],
    "sg:phone":"+1 214 381 6607",
    "sg:postcode":"75227",
    "sg:province":"TX",
    "sg:tags":[
        "church"
    ],
    "wof:name":"St Philip The Apostle Church",
    "wof:placetype":"venue"
},
  "geometry": {"coordinates":[-96.680379,32.771035],"type":"Point"}
}