{
  "type": "Feature",
  "properties": {
    "iso:country":"US",
    "sg:address":"18502 Campers Crest Dr",
    "sg:city":"Humble",
    "sg:classifiers":[
        {
            "category":"Building & Trades",
            "subcategory":"Landscaping Services",
            "type":"Services"
        }
    ],
    "sg:phone":"+1 281 812 6377",
    "sg:postcode":"77346",
    "sg:province":"TX",
    "sg:tags":[
        "landscape"
    ],
    "wof:name":"Dees Landscape Design Service",
    "wof:placetype":"venue"
},
  "geometry": {"coordinates":[-95.153014,29.986059],"type":"Point"}
}