{
  "type": "Feature",
  "properties": {
    "iso:country":"US",
    "sg:address":"200 Shady Oaks Dr",
    "sg:city":"Liberty Hill",
    "sg:classifiers":[
        {
            "category":"Farming",
            "subcategory":"Livestock Farm",
            "type":"Manufacturing & Wholesale Goods"
        }
    ],
    "sg:phone":"+1 512 355 2345",
    "sg:postcode":"78616",
    "sg:province":"TX",
    "sg:tags":[
        "animal",
        "general"
    ],
    "wof:name":"Cadence Ranch",
    "wof:placetype":"venue"
},
  "geometry": {"coordinates":[-97.562202,30.029292],"type":"Point"}
}