{
  "type": "Feature",
  "properties": {
    "iso:country":"US",
    "sg:address":"15000 Bellaire Blvd",
    "sg:city":"Houston",
    "sg:classifiers":[
        {
            "category":"Food & Beverages",
            "subcategory":"Groceries & Convenience Stores",
            "type":"Retail Goods"
        },
        {
            "category":"Shopping",
            "type":"Retail Goods"
        }
    ],
    "sg:phone":"+1 281 988 9163",
    "sg:postcode":"77083",
    "sg:province":"TX",
    "sg:tags":[
        "mexican"
    ],
    "wof:name":"Carniceria Y Fruteria Morales",
    "wof:placetype":"venue"
},
  "geometry": {"coordinates":[-95.651971,29.701293],"type":"Point"}
}