{
  "type": "Feature",
  "properties": {
    "iso:country":"US",
    "sg:address":"133 E Crosstimbers St",
    "sg:city":"Houston",
    "sg:classifiers":[
        {
            "category":"Shopping",
            "subcategory":"Used Merchandise",
            "type":"Retail Goods"
        }
    ],
    "sg:phone":"+1 713 692 7011",
    "sg:postcode":"77022",
    "sg:province":"TX",
    "sg:tags":[
        "pawnbroker"
    ],
    "wof:name":"Cash America Pawn",
    "wof:placetype":"venue"
},
  "geometry": {"coordinates":[-95.376018,29.828322],"type":"Point"}
}