{
  "type": "Feature",
  "properties": {
    "iso:country":"US",
    "sg:address":"10310 McCombs St",
    "sg:city":"El Paso",
    "sg:classifiers":[
        {
            "category":"Building & Trades",
            "subcategory":"Construction",
            "type":"Services"
        }
    ],
    "sg:phone":"+1 915 821 1081",
    "sg:postcode":"79924",
    "sg:province":"TX",
    "sg:tags":[
        "carpentry",
        "contractor"
    ],
    "wof:name":"Gonzalez Carpentry",
    "wof:placetype":"venue"
},
  "geometry": {"coordinates":[-106.406893,31.912073],"type":"Point"}
}