{
  "type": "Feature",
  "properties": {
    "iso:country":"US",
    "sg:address":"2900 NE 6th Ave",
    "sg:city":"Amarillo",
    "sg:classifiers":[
        {
            "category":"Building & Trades",
            "subcategory":"Plumbing",
            "type":"Services"
        }
    ],
    "sg:phone":"+1 806 378 4187",
    "sg:postcode":"79107",
    "sg:province":"TX",
    "sg:tags":[
        "cooling",
        "tower"
    ],
    "wof:name":"Universal Utility Svc Co",
    "wof:placetype":"venue"
},
  "geometry": {"coordinates":[-101.801862,35.216882],"type":"Point"}
}