{
  "type": "Feature",
  "properties": {
    "iso:country":"US",
    "sg:address":"104 Warbonnet Trl",
    "sg:city":"Del Rio",
    "sg:classifiers":[
        {
            "category":"Shopping",
            "subcategory":"Gifts & Souvenirs",
            "type":"Retail Goods"
        }
    ],
    "sg:phone":"+1 830 768 1133",
    "sg:postcode":"78840",
    "sg:province":"TX",
    "wof:name":"Cjc Enterprises",
    "wof:placetype":"venue"
},
  "geometry": {"coordinates":[-100.92200800000001,29.406727],"type":"Point"}
}