{
  "type": "Feature",
  "properties": {
    "iso:country":"US",
    "sg:address":"617 Joyce Dr",
    "sg:city":"Garland",
    "sg:classifiers":[
        {
            "category":"Autos & Motor Vehicles",
            "subcategory":"Auto Supplies",
            "type":"Retail Goods"
        }
    ],
    "sg:phone":"+1 972 276 2076",
    "sg:postcode":"75040",
    "sg:province":"TX",
    "wof:name":"Barrows Mobile Tire Repa",
    "wof:placetype":"venue"
},
  "geometry": {"coordinates":[-96.638306,32.899794],"type":"Point"}
}