{
  "type": "Feature",
  "properties": {
    "iso:country":"US",
    "sg:address":"2301 Fountain View Dr",
    "sg:city":"Houston",
    "sg:classifiers":[
        {
            "category":"Retail",
            "subcategory":"Animal Services",
            "type":"Services"
        }
    ],
    "sg:phone":"+1 281 448 8551",
    "sg:postcode":"77057",
    "sg:province":"TX",
    "wof:name":"Airline Grooming & Pet Sups",
    "wof:placetype":"venue"
},
  "geometry": {"coordinates":[-95.485372,29.744755],"type":"Point"}
}