{
  "type": "Feature",
  "properties": {
    "iso:country":"US",
    "sg:address":"141 W Cotter Ave",
    "sg:city":"Port Aransas",
    "sg:classifiers":[
        {
            "category":"Manufacturing",
            "subcategory":"Printing",
            "type":"Manufacturing & Wholesale Goods"
        }
    ],
    "sg:phone":"+1 361 749 5131",
    "sg:postcode":"78373",
    "sg:province":"TX",
    "sg:tags":[
        "newspaper"
    ],
    "wof:name":"South Jetty Newspaper",
    "wof:placetype":"venue"
},
  "geometry": {"coordinates":[-97.062861,27.837786],"type":"Point"}
}