{
  "type": "Feature",
  "properties": {
    "iso:country":"US",
    "sg:address":"6500 Fm 2100 Rd",
    "sg:city":"Crosby",
    "sg:classifiers":[
        {
            "category":"Insurance",
            "subcategory":"Hazard Insurance",
            "type":"Services"
        }
    ],
    "sg:phone":"+1 281 328 3170",
    "sg:postcode":"77532",
    "sg:province":"TX",
    "sg:tags":[
        "commercial",
        "business"
    ],
    "wof:name":"Marek Ted Insurance Agency",
    "wof:placetype":"venue"
},
  "geometry": {"coordinates":[-95.070702,29.920214],"type":"Point"}
}