{
  "type": "Feature",
  "properties": {
    "iso:country":"US",
    "sg:address":"1725 Troup Hwy",
    "sg:city":"Tyler",
    "sg:classifiers":[
        {
            "category":"Retail",
            "subcategory":"Auto Repair",
            "type":"Services"
        }
    ],
    "sg:phone":"+1 903 592 2241",
    "sg:postcode":"75701",
    "sg:province":"TX",
    "sg:tags":[
        "station",
        "gasoline",
        "general"
    ],
    "wof:name":"Shell",
    "wof:placetype":"venue"
},
  "geometry": {"coordinates":[-95.27943399999999,32.31811],"type":"Point"}
}