{
  "type": "Feature",
  "properties": {
    "iso:country":"US",
    "sg:address":"603 W Pierce St",
    "sg:city":"San Saba",
    "sg:classifiers":[
        {
            "category":"Professional",
            "type":"Services"
        }
    ],
    "sg:phone":"+1 325 372 5309",
    "sg:postcode":"76877",
    "sg:province":"TX",
    "wof:name":"Oscar Saldivar",
    "wof:placetype":"venue"
},
  "geometry": {"coordinates":[-98.726427,31.20139],"type":"Point"}
}