{
  "type": "Feature",
  "properties": {
    "iso:country":"US",
    "sg:address":"5002 Center St",
    "sg:city":"Houston",
    "sg:classifiers":[
        {
            "category":"Insurance",
            "subcategory":"Life Insurance",
            "type":"Services"
        }
    ],
    "sg:phone":"+1 713 426 2299",
    "sg:postcode":"77007",
    "sg:province":"TX",
    "sg:tags":[
        "agency"
    ],
    "wof:name":"Royal & Sunalliance USA Inc",
    "wof:placetype":"venue"
},
  "geometry": {"coordinates":[-95.41248299999999,29.771243],"type":"Point"}
}