{
  "type": "Feature",
  "properties": {
    "iso:country":"US",
    "sg:address":"11914 Manzanita St",
    "sg:city":"San Antonio",
    "sg:classifiers":[
        {
            "category":"Shopping",
            "subcategory":"Catalog Store",
            "type":"Retail Goods"
        }
    ],
    "sg:phone":"+1 210 679 6145",
    "sg:postcode":"78245",
    "sg:province":"TX",
    "sg:tags":[
        "mail",
        "order"
    ],
    "wof:name":"Angel Place",
    "wof:placetype":"venue"
},
  "geometry": {"coordinates":[-98.727419,29.420589],"type":"Point"}
}