{
  "type": "Feature",
  "properties": {
    "iso:country":"US",
    "sg:address":"419 N Washington Ave",
    "sg:city":"Livingston",
    "sg:classifiers":[
        {
            "category":"Professional",
            "type":"Services"
        }
    ],
    "sg:phone":"+1 936 327 8211",
    "sg:postcode":"77351",
    "sg:province":"TX",
    "wof:name":"Detnet Inc",
    "wof:placetype":"venue"
},
  "geometry": {"coordinates":[-94.933086,30.711663],"type":"Point"}
}