{
  "type": "Feature",
  "properties": {
    "iso:country":"US",
    "sg:address":"16808 El Camino Real",
    "sg:city":"Houston",
    "sg:classifiers":[
        {
            "category":"Health Services",
            "subcategory":"Clinic",
            "type":"Services"
        }
    ],
    "sg:phone":"+1 281 488 0905",
    "sg:postcode":"77058",
    "sg:province":"TX",
    "sg:tags":[
        "information",
        "alcoholism",
        "treatment"
    ],
    "wof:name":"Into Action Recovery Center",
    "wof:placetype":"venue"
},
  "geometry": {"coordinates":[-95.120012,29.554472],"type":"Point"}
}