{
  "type": "Feature",
  "properties": {
    "iso:country":"US",
    "sg:address":"13602 Wheatbridge Dr",
    "sg:city":"Houston",
    "sg:classifiers":[
        {
            "category":"Professional",
            "type":"Services"
        }
    ],
    "sg:phone":"+1 713 937 4751",
    "sg:postcode":"77041",
    "sg:province":"TX",
    "wof:name":"Cindy Gamble",
    "wof:placetype":"venue"
},
  "geometry": {"coordinates":[-95.61672799999999,29.858762],"type":"Point"}
}