{
  "type": "Feature",
  "properties": {
    "iso:country":"US",
    "sg:address":"2401 University Blvd",
    "sg:city":"Houston",
    "sg:classifiers":[
        {
            "category":"Banks & Credit Unions",
            "subcategory":"Bank",
            "type":"Services"
        }
    ],
    "sg:phone":"+1 713 867 1111",
    "sg:postcode":"77005",
    "sg:province":"TX",
    "sg:website":"www.compassbank.com",
    "wof:name":"BBVA Compass",
    "wof:placetype":"venue"
},
  "geometry": {"coordinates":[-95.41489900000001,29.714932],"type":"Point"}
}