{
  "type": "Feature",
  "properties": {
    "iso:country":"US",
    "sg:address":"9809 Shadydale Ln",
    "sg:city":"Dallas",
    "sg:classifiers":[
        {
            "category":"Restaurant",
            "type":"Food & Drink"
        }
    ],
    "sg:phone":"+1 214 343 3258",
    "sg:postcode":"75238",
    "sg:province":"TX",
    "sg:tags":[
        "eating"
    ],
    "wof:name":"Catered Occasions",
    "wof:placetype":"venue"
},
  "geometry": {"coordinates":[-96.71605599999999,32.866979],"type":"Point"}
}