{
  "type": "Feature",
  "properties": {
    "iso:country":"US",
    "sg:address":"327 Park North Ln",
    "sg:city":"Keller",
    "sg:classifiers":[
        {
            "category":"Wholesale",
            "subcategory":"Hardware",
            "type":"Manufacturing & Wholesale Goods"
        }
    ],
    "sg:phone":"+1 817 431 5665",
    "sg:postcode":"76248",
    "sg:province":"TX",
    "sg:tags":[
        "equipment",
        "retail",
        "tank",
        "carbonic"
    ],
    "wof:name":"Carbonic Equipment Co",
    "wof:placetype":"venue"
},
  "geometry": {"coordinates":[-97.248625,32.928427],"type":"Point"}
}