{
  "type": "Feature",
  "properties": {
    "iso:country":"US",
    "sg:address":"4831 Fairmont Pkwy",
    "sg:city":"Pasadena",
    "sg:classifiers":[
        {
            "category":"Restaurant",
            "type":"Food & Drink"
        }
    ],
    "sg:phone":"+1 281 998 1605",
    "sg:postcode":"77505",
    "sg:province":"TX",
    "wof:name":"Whataburger Restaurants",
    "wof:placetype":"venue"
},
  "geometry": {"coordinates":[-95.170502,29.6499],"type":"Point"}
}