{
  "type": "Feature",
  "properties": {
    "iso:country":"US",
    "sg:address":"219 N Main St",
    "sg:city":"Weatherford",
    "sg:classifiers":[
        {
            "category":"Shopping",
            "subcategory":"Used Merchandise",
            "type":"Retail Goods"
        }
    ],
    "sg:phone":"+1 817 596 9151",
    "sg:postcode":"76086",
    "sg:province":"TX",
    "wof:name":"Saux Real Designs",
    "wof:placetype":"venue"
},
  "geometry": {"coordinates":[-97.79734000000001,32.761329],"type":"Point"}
}