{
  "type": "Feature",
  "properties": {
    "iso:country":"US",
    "sg:address":"5533 Dyer St",
    "sg:city":"Dallas",
    "sg:classifiers":[
        {
            "category":"Organizations",
            "subcategory":"Membership Organization",
            "type":"Services"
        }
    ],
    "sg:phone":"+1 214 363 0461",
    "sg:postcode":"75206",
    "sg:province":"TX",
    "wof:name":"Alateen Information Ctr",
    "wof:placetype":"venue"
},
  "geometry": {"coordinates":[-96.773737,32.843229],"type":"Point"}
}