{
  "type": "Feature",
  "properties": {
    "iso:country":"US",
    "sg:address":"2738 N Mesa St",
    "sg:city":"El Paso",
    "sg:classifiers":[
        {
            "category":"Building & Trades",
            "subcategory":"Construction",
            "type":"Services"
        }
    ],
    "sg:phone":"+1 915 845 0349",
    "sg:postcode":"79902",
    "sg:province":"TX",
    "sg:tags":[
        "general",
        "contractor"
    ],
    "wof:name":"V H Development",
    "wof:placetype":"venue"
},
  "geometry": {"coordinates":[-106.503528,31.777596],"type":"Point"}
}