{
  "type": "Feature",
  "properties": {
    "iso:country":"US",
    "sg:address":"2102 N 1st St",
    "sg:city":"Abilene",
    "sg:classifiers":[
        {
            "category":"Building & Trades",
            "subcategory":"Equipment Rental",
            "type":"Services"
        }
    ],
    "sg:phone":"+1 325 672 2242",
    "sg:postcode":"79603",
    "sg:province":"TX",
    "sg:tags":[
        "appliance"
    ],
    "wof:name":"Rent City Superstores",
    "wof:placetype":"venue"
},
  "geometry": {"coordinates":[-99.74918,32.450422],"type":"Point"}
}