{
  "type": "Feature",
  "properties": {
    "iso:country":"US",
    "sg:address":"1300 W Oaklawn Rd",
    "sg:city":"Pleasanton",
    "sg:classifiers":[
        {
            "category":"Retail",
            "subcategory":"Repair Shop",
            "type":"Services"
        }
    ],
    "sg:phone":"+1 830 569 5116",
    "sg:postcode":"78064",
    "sg:province":"TX",
    "sg:tags":[
        "electrical"
    ],
    "wof:name":"Marco Sew & Vac",
    "wof:placetype":"venue"
},
  "geometry": {"coordinates":[-98.49887099999999,28.950509],"type":"Point"}
}