{
  "type": "Feature",
  "properties": {
    "iso:country":"US",
    "sg:address":"507 Archwood Trail",
    "sg:city":"Houston",
    "sg:classifiers":[
        {
            "category":"Shopping",
            "type":"Retail Goods"
        }
    ],
    "sg:phone":"+1 713 568 1842",
    "sg:postcode":"77007",
    "sg:province":"TX",
    "sg:website":"www.indegoafrica.org",
    "wof:name":"Indego Africa",
    "wof:placetype":"venue"
},
  "geometry": {"coordinates":[-95.393925,29.765562],"type":"Point"}
}