{
  "type": "Feature",
  "properties": {
    "iso:country":"US",
    "sg:address":"6120 W by Northwest Blvd",
    "sg:city":"Houston",
    "sg:classifiers":[
        {
            "category":"Wholesale",
            "subcategory":"Hardware",
            "type":"Manufacturing & Wholesale Goods"
        }
    ],
    "sg:phone":"+1 713 939 0056",
    "sg:postcode":"77040",
    "sg:province":"TX",
    "sg:tags":[
        "fastener"
    ],
    "wof:name":"SFS Intec",
    "wof:placetype":"venue"
},
  "geometry": {"coordinates":[-95.535256,29.855708],"type":"Point"}
}