{
  "type": "Feature",
  "properties": {
    "iso:country":"US",
    "sg:address":"17940 Butte Creek Rd",
    "sg:city":"Houston",
    "sg:classifiers":[
        {
            "category":"Utilities",
            "subcategory":"Water",
            "type":"Services"
        }
    ],
    "sg:phone":"+1 281 440 9798",
    "sg:postcode":"77090",
    "sg:province":"TX",
    "sg:tags":[
        "district"
    ],
    "wof:name":"Ponders Rgnl Wst Wtr Trtmnt",
    "wof:placetype":"venue"
},
  "geometry": {"coordinates":[-95.46528499999999,30.024548],"type":"Point"}
}