{
  "type": "Feature",
  "properties": {
    "iso:country":"US",
    "sg:address":"1500 SW 5th St",
    "sg:city":"Seminole",
    "sg:classifiers":[
        {
            "category":"Place Of Worship",
            "subcategory":"Church",
            "type":"Public Place"
        },
        {
            "category":"Place Of Worship",
            "type":"Public Place"
        },
        {
            "category":"Organizations",
            "subcategory":"Religious Organization",
            "type":"Services"
        }
    ],
    "sg:phone":"+1 432 758 1151",
    "sg:postcode":"79360",
    "sg:province":"TX",
    "sg:tags":[
        "brother",
        "churches-mennonite"
    ],
    "wof:name":"Mennonite Evangelical Church",
    "wof:placetype":"venue"
},
  "geometry": {"coordinates":[-102.64991999999999,32.71136],"type":"Point"}
}