{
  "type": "Feature",
  "properties": {
    "iso:country":"US",
    "sg:address":"3319 Louisiana St",
    "sg:city":"Houston",
    "sg:classifiers":[
        {
            "category":"Shopping",
            "subcategory":"Antiques",
            "type":"Retail Goods"
        }
    ],
    "sg:phone":"+1 713 524 3080",
    "sg:postcode":"77006",
    "sg:province":"TX",
    "sg:website":"www.brawnerrestoration.com",
    "wof:name":"BRAWNER RESTORATION & CUSTOM LIGHTING WORKSHOP",
    "wof:placetype":"venue"
},
  "geometry": {"coordinates":[-95.38014800000001,29.7423],"type":"Point"}
}