{
  "type": "Feature",
  "properties": {
    "iso:country":"US",
    "sg:address":"36 W Plaza St",
    "sg:city":"Paris",
    "sg:classifiers":[
        {
            "category":"Insurance",
            "subcategory":"Insurance Agent",
            "type":"Services"
        }
    ],
    "sg:phone":"+1 903 784 4649",
    "sg:postcode":"75449",
    "sg:province":"TX",
    "wof:name":"Don Moffitt Insurance Agency",
    "wof:placetype":"venue"
},
  "geometry": {"coordinates":[-95.94739,33.425853],"type":"Point"}
}