{
  "type": "Feature",
  "properties": {
    "iso:country":"US",
    "sg:address":"10900 Stonelake Blvd Ste 250",
    "sg:city":"Austin",
    "sg:classifiers":[
        {
            "category":"Health Services",
            "subcategory":"Doctor",
            "type":"Services"
        }
    ],
    "sg:phone":"+1 512 795 5100",
    "sg:postcode":"78759",
    "sg:province":"TX",
    "wof:name":"Conrad Kirk",
    "wof:placetype":"venue"
},
  "geometry": {"coordinates":[-97.733141,30.398408],"type":"Point"}
}