{
  "type": "Feature",
  "properties": {
    "iso:country":"US",
    "sg:address":"4300 Ave G",
    "sg:city":"Austin",
    "sg:classifiers":[
        {
            "category":"Travel",
            "subcategory":"Hotels & Motels",
            "type":"Entertainment"
        },
        {
            "category":"Travel",
            "subcategory":"Bed & Breakfast",
            "type":"Entertainment"
        }
    ],
    "sg:phone":"+1 512 453 7696",
    "sg:postcode":"78751",
    "sg:province":"TX",
    "sg:website":"www.theadamshouse.com",
    "wof:name":"Adams House",
    "wof:placetype":"venue"
},
  "geometry": {"coordinates":[-97.727914,30.305543],"type":"Point"}
}