{
  "type": "Feature",
  "properties": {
    "iso:country":"US",
    "sg:address":"510 Water St",
    "sg:city":"Waxahachie",
    "sg:classifiers":[
        {
            "category":"Organizations",
            "subcategory":"Religious Organization",
            "type":"Services"
        }
    ],
    "sg:phone":"+1 972 937 7003",
    "sg:postcode":"75165",
    "sg:province":"TX",
    "sg:tags":[
        "clergy"
    ],
    "wof:name":"Fredom Center",
    "wof:placetype":"venue"
},
  "geometry": {"coordinates":[-96.85011299999999,32.387806],"type":"Point"}
}