{
  "type": "Feature",
  "properties": {
    "iso:country":"US",
    "sg:address":"2404 Ross Ave",
    "sg:city":"Dallas",
    "sg:classifiers":[
        {
            "category":"Sports & Exercise",
            "subcategory":"Gym",
            "type":"Entertainment"
        }
    ],
    "sg:phone":"+1 214 953 6200",
    "sg:postcode":"75201",
    "sg:province":"TX",
    "wof:name":"Blissworld Spa Reservations",
    "wof:placetype":"venue"
},
  "geometry": {"coordinates":[-96.79611,32.789336],"type":"Point"}
}