{
  "type": "Feature",
  "properties": {
    "iso:country":"US",
    "sg:address":"3550 State Hwy 279",
    "sg:city":"Brownwood",
    "sg:classifiers":[
        {
            "category":"Farming",
            "subcategory":"Livestock Farm",
            "type":"Manufacturing & Wholesale Goods"
        }
    ],
    "sg:phone":"+1 325 646 1398",
    "sg:postcode":"76801",
    "sg:province":"TX",
    "sg:tags":[
        "wheat",
        "beef",
        "feedlot",
        "cattle"
    ],
    "wof:name":"Thomason Wade and Sons",
    "wof:placetype":"venue"
},
  "geometry": {"coordinates":[-99.024067,31.758152],"type":"Point"}
}