{
  "type": "Feature",
  "properties": {
    "iso:country":"US",
    "sg:address":"603 Sancroft Ct",
    "sg:city":"Katy",
    "sg:classifiers":[
        {
            "category":"Building & Trades",
            "subcategory":"Landscaping Services",
            "type":"Services"
        }
    ],
    "sg:phone":"+1 281 578 0329",
    "sg:postcode":"77450",
    "sg:province":"TX",
    "sg:tags":[
        "landscape"
    ],
    "wof:name":"Paragon Industries",
    "wof:placetype":"venue"
},
  "geometry": {"coordinates":[-95.722455,29.778436],"type":"Point"}
}