{
  "type": "Feature",
  "properties": {
    "iso:country":"US",
    "sg:address":"600 Bent Tree Ct",
    "sg:city":"Irving",
    "sg:classifiers":[
        {
            "category":"Real Estate",
            "subcategory":"Developer",
            "type":"Services"
        }
    ],
    "sg:phone":"+1 972 254 6993",
    "sg:postcode":"75061",
    "sg:province":"TX",
    "sg:tags":[
        "cemetery"
    ],
    "wof:name":"Old Kit Cemetery Inc",
    "wof:placetype":"venue"
},
  "geometry": {"coordinates":[-96.960155,32.828276],"type":"Point"}
}