{
  "type": "Feature",
  "properties": {
    "iso:country":"US",
    "sg:address":"200 W Miller St",
    "sg:city":"Atlanta",
    "sg:classifiers":[
        {
            "category":"Professional",
            "type":"Services"
        }
    ],
    "sg:phone":"+1 903 796 5158",
    "sg:postcode":"75551",
    "sg:province":"TX",
    "wof:name":"Metro Tree Service",
    "wof:placetype":"venue"
},
  "geometry": {"coordinates":[-94.16861,33.117306],"type":"Point"}
}