{
  "type": "Feature",
  "properties": {
    "iso:country":"US",
    "sg:address":"101 Baldwin Blvd",
    "sg:city":"Corpus Christi",
    "sg:classifiers":[
        {
            "category":"Restaurant",
            "type":"Food & Drink"
        }
    ],
    "sg:phone":"+1 361 883 0192",
    "sg:postcode":"78404",
    "sg:province":"TX",
    "wof:name":"Aramark",
    "wof:placetype":"venue"
},
  "geometry": {"coordinates":[-97.40713100000001,27.767236],"type":"Point"}
}