{
  "type": "Feature",
  "properties": {
    "iso:country":"US",
    "sg:address":"2923 Cumbre Dr",
    "sg:city":"San Antonio",
    "sg:classifiers":[
        {
            "category":"Shopping",
            "subcategory":"Used Merchandise",
            "type":"Retail Goods"
        }
    ],
    "sg:phone":"+1 210 438 4325",
    "sg:postcode":"78237",
    "sg:province":"TX",
    "wof:name":"Juan Isarraraz",
    "wof:placetype":"venue"
},
  "geometry": {"coordinates":[-98.54939299999999,29.407275],"type":"Point"}
}