{
  "type": "Feature",
  "properties": {
    "iso:country":"US",
    "sg:address":"11035 Indian Trl",
    "sg:city":"Dallas",
    "sg:classifiers":[
        {
            "category":"Shopping",
            "subcategory":"Party Supplies",
            "type":"Retail Goods"
        }
    ],
    "sg:phone":"+1 972 247 8556",
    "sg:postcode":"75229",
    "sg:province":"TX",
    "sg:website":"www.alexandertent.com",
    "wof:name":"Alexander Tent Rentals Inc",
    "wof:placetype":"venue"
},
  "geometry": {"coordinates":[-96.883797,32.8993],"type":"Point"}
}