{
  "type": "Feature",
  "properties": {
    "iso:country":"US",
    "sg:address":"4122 Lavell Ave",
    "sg:city":"Wichita Falls",
    "sg:classifiers":[
        {
            "category":"Home & Garden",
            "subcategory":"Household Appliances",
            "type":"Retail Goods"
        }
    ],
    "sg:phone":"+1 940 691 1551",
    "sg:postcode":"76308",
    "sg:province":"TX",
    "wof:name":"Lawrence's Appliance Svc",
    "wof:placetype":"venue"
},
  "geometry": {"coordinates":[-98.55114,33.861046],"type":"Point"}
}