{
  "type": "Feature",
  "properties": {
    "iso:country":"US",
    "sg:address":"12810 Westbranch Ct",
    "sg:city":"Houston",
    "sg:classifiers":[
        {
            "category":"Health Services",
            "subcategory":"Clinic",
            "type":"Services"
        }
    ],
    "sg:phone":"+1 281 568 3532",
    "sg:postcode":"77072",
    "sg:province":"TX",
    "sg:tags":[
        "home"
    ],
    "wof:name":"Nay-Vel",
    "wof:placetype":"venue"
},
  "geometry": {"coordinates":[-95.608194,29.702033],"type":"Point"}
}