{
  "type": "Feature",
  "properties": {
    "iso:country":"US",
    "sg:address":"803 William St",
    "sg:city":"Houston",
    "sg:classifiers":[
        {
            "category":"Food & Beverages",
            "subcategory":"Candy",
            "type":"Retail Goods"
        }
    ],
    "sg:phone":"+1 713 227 0483",
    "sg:postcode":"77002",
    "sg:province":"TX",
    "wof:name":"Dawn N Fudge",
    "wof:placetype":"venue"
},
  "geometry": {"coordinates":[-95.35355199999999,29.768932],"type":"Point"}
}