{
  "type": "Feature",
  "properties": {
    "iso:country":"US",
    "sg:address":"13714 Camelot Centre Ct",
    "sg:city":"Houston",
    "sg:classifiers":[
        {
            "category":"Professional",
            "subcategory":"Lawyer & Legal Services",
            "type":"Services"
        }
    ],
    "sg:phone":"+1 281 580 5644",
    "sg:postcode":"77069",
    "sg:province":"TX",
    "wof:name":"Lynda F Burke",
    "wof:placetype":"venue"
},
  "geometry": {"coordinates":[-95.54047,29.975577],"type":"Point"}
}