{
  "type": "Feature",
  "properties": {
    "iso:country":"US",
    "sg:address":"200 E Pioneer Dr",
    "sg:city":"Irving",
    "sg:classifiers":[
        {
            "category":"Manufacturing",
            "subcategory":"Metals",
            "type":"Manufacturing & Wholesale Goods"
        }
    ],
    "sg:phone":"+1 972 790 7351",
    "sg:postcode":"75061",
    "sg:province":"TX",
    "sg:tags":[
        "duct",
        "connector",
        "sheet",
        "mfg"
    ],
    "wof:name":"Sheet Metal Connectors",
    "wof:placetype":"venue"
},
  "geometry": {"coordinates":[-96.94449299999999,32.818075],"type":"Point"}
}