{
  "type": "Feature",
  "properties": {
    "iso:country":"US",
    "sg:address":"504 6th St",
    "sg:city":"Comfort",
    "sg:classifiers":[
        {
            "category":"Restaurant",
            "type":"Food & Drink"
        }
    ],
    "sg:phone":"+1 830 995 4527",
    "sg:postcode":"78013",
    "sg:province":"TX",
    "sg:tags":[
        "cafe"
    ],
    "wof:name":"Little House Cafe",
    "wof:placetype":"venue"
},
  "geometry": {"coordinates":[-98.90894,29.969033],"type":"Point"}
}