{
  "type": "Feature",
  "properties": {
    "iso:country":"US",
    "sg:address":"4515 Manchaca Rd",
    "sg:city":"Austin",
    "sg:classifiers":[
        {
            "category":"Professional",
            "subcategory":"Research",
            "type":"Services"
        }
    ],
    "sg:phone":"+1 512 444 9400",
    "sg:postcode":"78745",
    "sg:province":"TX",
    "sg:tags":[
        "environmental",
        "ecological",
        "consultant"
    ],
    "wof:name":"Clean Environments, Inc.",
    "wof:placetype":"venue"
},
  "geometry": {"coordinates":[-97.790161,30.22706],"type":"Point"}
}