{
  "type": "Feature",
  "properties": {
    "iso:country":"US",
    "sg:address":"2516 Memphis Ave",
    "sg:city":"Nederland",
    "sg:classifiers":[
        {
            "category":"Professional",
            "subcategory":"Management & Consulting",
            "type":"Services"
        }
    ],
    "sg:phone":"+1 409 729 4200",
    "sg:postcode":"77627",
    "sg:province":"TX",
    "sg:tags":[
        "business"
    ],
    "wof:name":"Academic Achievement Center",
    "wof:placetype":"venue"
},
  "geometry": {"coordinates":[-94.00841800000001,29.972422],"type":"Point"}
}