{
  "type": "Feature",
  "properties": {
    "iso:country":"US",
    "sg:address":"10015 Cantertrot Dr",
    "sg:city":"Humble",
    "sg:classifiers":[
        {
            "category":"Farming",
            "subcategory":"Fish & Marine Products",
            "type":"Manufacturing & Wholesale Goods"
        },
        {
            "category":"Retail",
            "subcategory":"Repair Shop",
            "type":"Services"
        }
    ],
    "sg:phone":"+1 281 446 5642",
    "sg:postcode":"77338",
    "sg:province":"TX",
    "sg:tags":[
        "picture",
        "frame",
        "restoration",
        "framing"
    ],
    "wof:name":"Shadowhawk Antiques",
    "wof:placetype":"venue"
},
  "geometry": {"coordinates":[-95.270239,30.014887],"type":"Point"}
}