{
  "type": "Feature",
  "properties": {
    "iso:country":"US",
    "sg:address":"2100 Northland Dr",
    "sg:city":"Austin",
    "sg:classifiers":[
        {
            "category":"Professional",
            "subcategory":"Employment Agencies",
            "type":"Services"
        }
    ],
    "sg:phone":"+1 512 407 8989",
    "sg:postcode":"78756",
    "sg:province":"TX",
    "sg:tags":[
        "help",
        "supply"
    ],
    "wof:name":"Spherion Corporation",
    "wof:placetype":"venue"
},
  "geometry": {"coordinates":[-97.74160999999999,30.332818],"type":"Point"}
}