{
  "type": "Feature",
  "properties": {
    "iso:country":"US",
    "sg:address":"2009 Ranch Rd 620 N",
    "sg:city":"Lakeway",
    "sg:classifiers":[
        {
            "category":"Professional",
            "subcategory":"Computer Services",
            "type":"Services"
        }
    ],
    "sg:phone":"+1 512 266 3636",
    "sg:postcode":"78734",
    "sg:province":"TX",
    "sg:tags":[
        "repair"
    ],
    "wof:name":"Super Computers",
    "wof:placetype":"venue"
},
  "geometry": {"coordinates":[-97.94292900000001,30.382531],"type":"Point"}
}