{
  "type": "Feature",
  "properties": {
    "iso:country":"US",
    "sg:address":"409 4th St",
    "sg:city":"Markham",
    "sg:classifiers":[
        {
            "category":"Personal",
            "subcategory":"Beauty Salon",
            "type":"Services"
        }
    ],
    "sg:phone":"+1 979 843 5543",
    "sg:postcode":"77456",
    "sg:province":"TX",
    "wof:name":"Ann's Beauty Salon",
    "wof:placetype":"venue"
},
  "geometry": {"coordinates":[-96.068737,28.959157],"type":"Point"}
}