{
  "type": "Feature",
  "properties": {
    "iso:country":"US",
    "sg:address":"1307 Durbin Way",
    "sg:city":"San Antonio",
    "sg:classifiers":[
        {
            "category":"Organizations",
            "subcategory":"Religious Organization",
            "type":"Services"
        }
    ],
    "sg:phone":"+1 210 497 6640",
    "sg:postcode":"78258",
    "sg:province":"TX",
    "wof:name":"Divine Intention Ministries",
    "wof:placetype":"venue"
},
  "geometry": {"coordinates":[-98.516222,29.630657],"type":"Point"}
}