{
  "type": "Feature",
  "properties": {
    "iso:country":"US",
    "sg:address":"3300 Coulter St",
    "sg:city":"Amarillo",
    "sg:classifiers":[
        {
            "category":"Professional",
            "subcategory":"Business Services",
            "type":"Services"
        }
    ],
    "sg:phone":"+1 806 236 7038",
    "sg:postcode":"79106",
    "sg:province":"TX",
    "wof:name":"Rth Enterprises Inc",
    "wof:placetype":"venue"
},
  "geometry": {"coordinates":[-101.920278,35.176575],"type":"Point"}
}