{
  "type": "Feature",
  "properties": {
    "iso:country":"US",
    "sg:address":"8505 Broadway",
    "sg:city":"San Antonio",
    "sg:classifiers":[
        {
            "category":"Shopping",
            "subcategory":"Used Merchandise",
            "type":"Retail Goods"
        }
    ],
    "sg:phone":"+1 210 829 8824",
    "sg:postcode":"78217",
    "sg:province":"TX",
    "sg:tags":[
        "antique"
    ],
    "wof:name":"Luciane's Antiques Decorative",
    "wof:placetype":"venue"
},
  "geometry": {"coordinates":[-98.46330399999999,29.51806],"type":"Point"}
}