{
  "type": "Feature",
  "properties": {
    "iso:country":"US",
    "sg:address":"511 Nottingham Oaks Trl",
    "sg:city":"Houston",
    "sg:classifiers":[
        {
            "category":"Real Estate",
            "subcategory":"Real Estate Agent",
            "type":"Services"
        }
    ],
    "sg:phone":"+1 281 497 1487",
    "sg:postcode":"77079",
    "sg:province":"TX",
    "wof:name":"Ashford Professional",
    "wof:placetype":"venue"
},
  "geometry": {"coordinates":[-95.61344800000001,29.766386],"type":"Point"}
}