{
  "type": "Feature",
  "properties": {
    "iso:country":"US",
    "sg:address":"2311 W Alabama St",
    "sg:city":"Houston",
    "sg:classifiers":[
        {
            "category":"Personal",
            "subcategory":"Day Spa",
            "type":"Services"
        }
    ],
    "sg:phone":"+1 713 630 0772",
    "sg:postcode":"77098",
    "sg:province":"TX",
    "sg:website":"www.personadayspa.com",
    "wof:name":"Persona Day Spa",
    "wof:placetype":"venue"
},
  "geometry": {"coordinates":[-95.416028,29.738201],"type":"Point"}
}