{
  "type": "Feature",
  "properties": {
    "iso:country":"US",
    "sg:address":"501 S Friendswood Dr",
    "sg:city":"Friendswood",
    "sg:classifiers":[
        {
            "category":"Shopping",
            "subcategory":"Hobbies, Toys, & Games",
            "type":"Retail Goods"
        }
    ],
    "sg:phone":"+1 281 996 0596",
    "sg:postcode":"77546",
    "sg:province":"TX",
    "wof:name":"Rustic Woodworks",
    "wof:placetype":"venue"
},
  "geometry": {"coordinates":[-95.199969,29.528553],"type":"Point"}
}