{
  "type": "Feature",
  "properties": {
    "iso:country":"US",
    "sg:address":"3625 Bordeaux Ct",
    "sg:city":"Arlington",
    "sg:classifiers":[
        {
            "category":"Professional",
            "subcategory":"Advertising",
            "type":"Services"
        }
    ],
    "sg:phone":"+1 817 427 9300",
    "sg:postcode":"76016",
    "sg:province":"TX",
    "sg:tags":[
        "agency"
    ],
    "wof:name":"Emmanuel Kerr Kilsby",
    "wof:placetype":"venue"
},
  "geometry": {"coordinates":[-97.18292700000001,32.68842],"type":"Point"}
}