{
  "type": "Feature",
  "properties": {
    "iso:country":"US",
    "sg:address":"32880 I- 10 W",
    "sg:city":"Boerne",
    "sg:classifiers":[
        {
            "category":"Real Estate",
            "subcategory":"Real Estate Operator",
            "type":"Services"
        }
    ],
    "sg:phone":"+1 830 816 3305",
    "sg:postcode":"78006",
    "sg:province":"TX",
    "sg:tags":[
        "building",
        "nonresidential"
    ],
    "wof:name":"ABC Executive Suites",
    "wof:placetype":"venue"
},
  "geometry": {"coordinates":[-98.712017,29.760196],"type":"Point"}
}