{
  "type": "Feature",
  "properties": {
    "iso:country":"US",
    "sg:address":"2075 Maryland Dr",
    "sg:city":"Irving",
    "sg:classifiers":[
        {
            "category":"Building & Trades",
            "subcategory":"Construction",
            "type":"Services"
        }
    ],
    "sg:phone":"+1 972 721 9535",
    "sg:postcode":"75061",
    "sg:province":"TX",
    "sg:tags":[
        "contractor"
    ],
    "wof:name":"Wallco Retaining Walls",
    "wof:placetype":"venue"
},
  "geometry": {"coordinates":[-96.90771599999999,32.834578],"type":"Point"}
}