{
  "type": "Feature",
  "properties": {
    "iso:country":"US",
    "sg:address":"8824 Turnberry Ct",
    "sg:city":"Fort Worth",
    "sg:classifiers":[
        {
            "category":"Professional",
            "type":"Services"
        }
    ],
    "sg:phone":"+1 817 236 7244",
    "sg:postcode":"76179",
    "sg:province":"TX",
    "wof:name":"Javajox",
    "wof:placetype":"venue"
},
  "geometry": {"coordinates":[-97.43235799999999,32.876867],"type":"Point"}
}