{
  "type": "Feature",
  "properties": {
    "iso:country":"US",
    "sg:address":"3000 Princeton Dr",
    "sg:city":"Plano",
    "sg:classifiers":[
        {
            "category":"Education",
            "subcategory":"Special Training",
            "type":"Public Place"
        }
    ],
    "sg:phone":"+1 972 612 4463",
    "sg:postcode":"75075",
    "sg:province":"TX",
    "sg:tags":[
        "facility"
    ],
    "wof:name":"Gym 4 ME Inc",
    "wof:placetype":"venue"
},
  "geometry": {"coordinates":[-96.75080699999999,33.010332],"type":"Point"}
}