{
  "type": "Feature",
  "properties": {
    "iso:country":"US",
    "sg:address":"2074 Butternut St",
    "sg:city":"Abilene",
    "sg:classifiers":[
        {
            "category":"Bars & Pubs",
            "type":"Food & Drink"
        }
    ],
    "sg:phone":"+1 325 673 7151",
    "sg:postcode":"79602",
    "sg:province":"TX",
    "sg:tags":[
        "lounge",
        "cocktail"
    ],
    "wof:name":"Longhorn Bar",
    "wof:placetype":"venue"
},
  "geometry": {"coordinates":[-99.738719,32.424295],"type":"Point"}
}