{
  "type": "Feature",
  "properties": {
    "iso:country":"US",
    "sg:address":"211 NE Main St",
    "sg:city":"Ennis",
    "sg:classifiers":[
        {
            "category":"Home & Garden",
            "subcategory":"Furniture",
            "type":"Retail Goods"
        }
    ],
    "sg:phone":"+1 972 875 2831",
    "sg:postcode":"75119",
    "sg:province":"TX",
    "sg:tags":[
        "household"
    ],
    "wof:name":"Pollan Furniture Co Inc",
    "wof:placetype":"venue"
},
  "geometry": {"coordinates":[-96.627104,32.329016],"type":"Point"}
}