{
  "type": "Feature",
  "properties": {
    "iso:country":"US",
    "sg:address":"3401 Alice Ln",
    "sg:city":"Edinburg",
    "sg:classifiers":[
        {
            "category":"Building & Trades",
            "subcategory":"Construction",
            "type":"Services"
        }
    ],
    "sg:phone":"+1 956 383 5464",
    "sg:postcode":"78539",
    "sg:province":"TX",
    "sg:tags":[
        "heavy"
    ],
    "wof:name":"RB Earth Moving Inc",
    "wof:placetype":"venue"
},
  "geometry": {"coordinates":[-98.19837699999999,26.310614],"type":"Point"}
}