{
  "type": "Feature",
  "properties": {
    "iso:country":"US",
    "sg:address":"102 N Staples St",
    "sg:city":"Corpus Christi",
    "sg:classifiers":[
        {
            "category":"Professional",
            "subcategory":"Lawyer & Legal Services",
            "type":"Services"
        }
    ],
    "sg:phone":"+1 361 883 0911",
    "sg:postcode":"78401",
    "sg:province":"TX",
    "wof:name":"Bryan Walter Attny of Law",
    "wof:placetype":"venue"
},
  "geometry": {"coordinates":[-97.40269600000001,27.790839],"type":"Point"}
}