{
  "type": "Feature",
  "properties": {
    "iso:country":"US",
    "sg:address":"6175 Eastex Fwy",
    "sg:city":"Beaumont",
    "sg:classifiers":[
        {
            "category":"Shopping",
            "subcategory":"Department Store",
            "type":"Retail Goods"
        }
    ],
    "sg:phone":"+1 409 924 6700",
    "sg:postcode":"77706",
    "sg:province":"TX",
    "wof:name":"Foley's",
    "wof:placetype":"venue"
},
  "geometry": {"coordinates":[-94.15946,30.127265],"type":"Point"}
}