{
  "type": "Feature",
  "properties": {
    "iso:country":"US",
    "sg:address":"414 S Cage Blvd",
    "sg:city":"Pharr",
    "sg:classifiers":[
        {
            "category":"Professional",
            "subcategory":"Lawyer & Legal Services",
            "type":"Services"
        }
    ],
    "sg:phone":"+1 956 781 6203",
    "sg:postcode":"78577",
    "sg:province":"TX",
    "sg:tags":[
        "attorney"
    ],
    "wof:name":"Arturo Martinez",
    "wof:placetype":"venue"
},
  "geometry": {"coordinates":[-98.184834,26.190576],"type":"Point"}
}