{
  "type": "Feature",
  "properties": {
    "iso:country":"US",
    "sg:address":"2101 S I H 35",
    "sg:city":"Austin",
    "sg:classifiers":[
        {
            "category":"Building & Trades",
            "subcategory":"Construction",
            "type":"Services"
        }
    ],
    "sg:phone":"+1 512 442 4462",
    "sg:postcode":"78741",
    "sg:province":"TX",
    "sg:tags":[
        "contractor"
    ],
    "wof:name":"Gilbane",
    "wof:placetype":"venue"
},
  "geometry": {"coordinates":[-97.73907800000001,30.236521],"type":"Point"}
}