{
  "type": "Feature",
  "properties": {
    "iso:country":"US",
    "sg:address":"4209 S Industrial Dr",
    "sg:city":"Austin",
    "sg:classifiers":[
        {
            "category":"Manufacturing",
            "subcategory":"Tools & Machinery",
            "type":"Manufacturing & Wholesale Goods"
        },
        {
            "category":"Wholesale",
            "subcategory":"Electrical",
            "type":"Manufacturing & Wholesale Goods"
        }
    ],
    "sg:phone":"+1 512 448 1100",
    "sg:postcode":"78744",
    "sg:province":"TX",
    "sg:tags":[
        "equipment",
        "manufacturer",
        "supplies-wholesale",
        "electric",
        "supply"
    ],
    "wof:name":"Crawford Electric Supply Company",
    "wof:placetype":"venue"
},
  "geometry": {"coordinates":[-97.74361,30.210086],"type":"Point"}
}