{
  "type": "Feature",
  "properties": {
    "iso:country":"US",
    "sg:address":"8214 Cabot St",
    "sg:city":"Houston",
    "sg:classifiers":[
        {
            "category":"Retail",
            "subcategory":"Auto Repair",
            "type":"Services"
        }
    ],
    "sg:phone":"+1 713 631 9156",
    "sg:postcode":"77078",
    "sg:province":"TX",
    "sg:tags":[
        "automotive"
    ],
    "wof:name":"Greens Wrecker Service",
    "wof:placetype":"venue"
},
  "geometry": {"coordinates":[-95.27610799999999,29.854318],"type":"Point"}
}