{
  "type": "Feature",
  "properties": {
    "iso:country":"US",
    "sg:address":"507 Meadow Ln",
    "sg:city":"Arlington",
    "sg:classifiers":[
        {
            "category":"Professional",
            "subcategory":"Management & Consulting",
            "type":"Services"
        }
    ],
    "sg:phone":"+1 817 275 8571",
    "sg:postcode":"76010",
    "sg:province":"TX",
    "wof:name":"Bee Line Grass Management",
    "wof:placetype":"venue"
},
  "geometry": {"coordinates":[-97.099311,32.720088],"type":"Point"}
}