{
  "type": "Feature",
  "properties": {
    "iso:country":"US",
    "sg:address":"9434 Leopard St",
    "sg:city":"Corpus Christi",
    "sg:classifiers":[
        {
            "category":"Autos & Motor Vehicles",
            "subcategory":"Auto Supplies",
            "type":"Retail Goods"
        }
    ],
    "sg:phone":"+1 361 241 2351",
    "sg:postcode":"78410",
    "sg:province":"TX",
    "sg:tags":[
        "automobile",
        "parts"
    ],
    "wof:name":"Carquest Auto Parts 67",
    "wof:placetype":"venue"
},
  "geometry": {"coordinates":[-97.551805,27.827457],"type":"Point"}
}