{
  "type": "Feature",
  "properties": {
    "iso:country":"US",
    "sg:address":"3708 Broyles St",
    "sg:city":"Houston",
    "sg:classifiers":[
        {
            "category":"Manufacturing",
            "subcategory":"Textiles",
            "type":"Manufacturing & Wholesale Goods"
        }
    ],
    "sg:phone":"+1 713 675 1874",
    "sg:postcode":"77026",
    "sg:province":"TX",
    "sg:tags":[
        "mill",
        "knit",
        "outerwear"
    ],
    "wof:name":"Shas Personal Designs",
    "wof:placetype":"venue"
},
  "geometry": {"coordinates":[-95.327654,29.795137],"type":"Point"}
}