{
  "type": "Feature",
  "properties": {
    "iso:country":"US",
    "sg:address":"1012 Memorial Village Dr",
    "sg:city":"Houston",
    "sg:classifiers":[
        {
            "category":"Local Transit",
            "type":"Transportation"
        }
    ],
    "sg:phone":"+1 713 781 6777",
    "sg:postcode":"77024",
    "sg:province":"TX",
    "sg:tags":[
        "passenger"
    ],
    "wof:name":"Kidz Express",
    "wof:placetype":"venue"
},
  "geometry": {"coordinates":[-95.53317699999999,29.778875],"type":"Point"}
}