{
  "type": "Feature",
  "properties": {
    "iso:country":"US",
    "sg:address":"901 Ave D",
    "sg:city":"Ozona",
    "sg:classifiers":[
        {
            "category":"Organizations",
            "subcategory":"Religious Organization",
            "type":"Services"
        }
    ],
    "sg:phone":"+1 325 392 5555",
    "sg:postcode":"76943",
    "sg:province":"TX",
    "sg:tags":[
        "church"
    ],
    "wof:name":"First Baptist Church",
    "wof:placetype":"venue"
},
  "geometry": {"coordinates":[-101.200637,30.711579],"type":"Point"}
}