{
  "type": "Feature",
  "properties": {
    "iso:country":"US",
    "sg:address":"1311 Alpine Rd",
    "sg:city":"Longview",
    "sg:classifiers":[
        {
            "category":"Shopping",
            "subcategory":"Used Merchandise",
            "type":"Retail Goods"
        }
    ],
    "sg:phone":"+1 903 758 7592",
    "sg:postcode":"75601",
    "sg:province":"TX",
    "sg:tags":[
        "antique"
    ],
    "wof:name":"Blue Door Antiques",
    "wof:placetype":"venue"
},
  "geometry": {"coordinates":[-94.72113299999999,32.505193],"type":"Point"}
}