{
  "type": "Feature",
  "properties": {
    "iso:country":"US",
    "sg:address":"800 Lockwood Dr",
    "sg:city":"Houston",
    "sg:classifiers":[
        {
            "category":"Banks & Credit Unions",
            "subcategory":"Bank",
            "type":"Services"
        }
    ],
    "sg:phone":"+1 713 888 3400",
    "sg:postcode":"77020",
    "sg:province":"TX",
    "wof:name":"Comerica Bank",
    "wof:placetype":"venue"
},
  "geometry": {"coordinates":[-95.317802,29.7593],"type":"Point"}
}