{
  "type": "Feature",
  "properties": {
    "iso:country":"US",
    "sg:address":"4105 Tradewind St",
    "sg:city":"Amarillo",
    "sg:classifiers":[
        {
            "category":"Airport",
            "type":"Transportation"
        }
    ],
    "sg:phone":"+1 806 376 1008",
    "sg:postcode":"79118",
    "sg:province":"TX",
    "wof:name":"Tradewind Fbo",
    "wof:placetype":"venue"
},
  "geometry": {"coordinates":[-101.830759,35.1702],"type":"Point"}
}