{
  "type": "Feature",
  "properties": {
    "iso:country":"US",
    "sg:address":"306 S Bridge St",
    "sg:city":"Victoria",
    "sg:classifiers":[
        {
            "category":"Government",
            "subcategory":"Police Station",
            "type":"Public Place"
        }
    ],
    "sg:phone":"+1 361 572 2727",
    "sg:postcode":"77901",
    "sg:province":"TX",
    "sg:tags":[
        "department"
    ],
    "sg:website":"www.victoriatx.org",
    "wof:name":"Victoria City Police Dept",
    "wof:placetype":"venue"
},
  "geometry": {"coordinates":[-97.00800599999999,28.796879],"type":"Point"}
}