{
  "type": "Feature",
  "properties": {
    "iso:country":"US",
    "sg:address":"12626 Woodforest Blvd",
    "sg:city":"Houston",
    "sg:classifiers":[
        {
            "category":"Personal",
            "subcategory":"Nail Salon",
            "type":"Services"
        }
    ],
    "sg:phone":"+1 713 451 3800",
    "sg:postcode":"77015",
    "sg:province":"TX",
    "wof:name":"Pinkie Nails",
    "wof:placetype":"venue"
},
  "geometry": {"coordinates":[-95.201268,29.791115],"type":"Point"}
}