{
  "type": "Feature",
  "properties": {
    "iso:country":"US",
    "sg:address":"923 Ashland Ct",
    "sg:city":"Mansfield",
    "sg:classifiers":[
        {
            "category":"Professional",
            "subcategory":"Engineering",
            "type":"Services"
        }
    ],
    "sg:phone":"+1 817 477 1443",
    "sg:postcode":"76063",
    "sg:province":"TX",
    "sg:tags":[
        "consulting",
        "business"
    ],
    "wof:name":"Consolidated Consultants",
    "wof:placetype":"venue"
},
  "geometry": {"coordinates":[-97.110495,32.588639],"type":"Point"}
}