{
  "type": "Feature",
  "properties": {
    "iso:country":"US",
    "sg:address":"630 E 2nd St",
    "sg:city":"Mercedes",
    "sg:classifiers":[
        {
            "category":"Food & Beverages",
            "subcategory":"Groceries & Convenience Stores",
            "type":"Retail Goods"
        }
    ],
    "sg:phone":"+1 956 565 2342",
    "sg:postcode":"78570",
    "sg:province":"TX",
    "sg:tags":[
        "grocer"
    ],
    "wof:name":"Ten Ten Grocery",
    "wof:placetype":"venue"
},
  "geometry": {"coordinates":[-97.90378699999999,26.150759],"type":"Point"}
}