{
  "type": "Feature",
  "properties": {
    "iso:country":"US",
    "sg:address":"1202 Veterans Ave",
    "sg:city":"Copperas Cove",
    "sg:classifiers":[
        {
            "category":"Organizations",
            "subcategory":"Religious Organization",
            "type":"Services"
        }
    ],
    "sg:phone":"+1 254 547 3421",
    "sg:postcode":"76522",
    "sg:province":"TX",
    "sg:tags":[
        "church"
    ],
    "wof:name":"Fairview Community Church",
    "wof:placetype":"venue"
},
  "geometry": {"coordinates":[-97.915217,31.119107],"type":"Point"}
}