{
  "type": "Feature",
  "properties": {
    "iso:country":"US",
    "sg:address":"11308 Midmorning Dr",
    "sg:city":"Austin",
    "sg:classifiers":[
        {
            "category":"Real Estate",
            "subcategory":"Real Estate Operator",
            "type":"Services"
        }
    ],
    "sg:phone":"+1 512 288 2169",
    "sg:postcode":"78737",
    "sg:province":"TX",
    "sg:tags":[
        "building",
        "apartment"
    ],
    "wof:name":"Meadows At Danz Creek",
    "wof:placetype":"venue"
},
  "geometry": {"coordinates":[-97.931793,30.202486],"type":"Point"}
}