{
  "type": "Feature",
  "properties": {
    "iso:country":"US",
    "sg:address":"1917 Pantego Dr",
    "sg:city":"Fort Worth",
    "sg:classifiers":[
        {
            "category":"Building & Trades",
            "subcategory":"Construction",
            "type":"Services"
        }
    ],
    "sg:phone":"+1 817 568 0854",
    "sg:postcode":"76134",
    "sg:province":"TX",
    "sg:tags":[
        "painter"
    ],
    "wof:name":"Metroplex Painting",
    "wof:placetype":"venue"
},
  "geometry": {"coordinates":[-97.34692099999999,32.644409],"type":"Point"}
}