{
  "type": "Feature",
  "properties": {
    "iso:country":"US",
    "sg:address":"412 N 13th St",
    "sg:city":"Memphis",
    "sg:classifiers":[
        {
            "category":"Building & Trades",
            "subcategory":"Landscaping Services",
            "type":"Services"
        }
    ],
    "sg:phone":"+1 806 259 2591",
    "sg:postcode":"79245",
    "sg:province":"TX",
    "sg:tags":[
        "landscape"
    ],
    "wof:name":"Martin Torres",
    "wof:placetype":"venue"
},
  "geometry": {"coordinates":[-100.54582600000001,34.729297],"type":"Point"}
}