{
  "type": "Feature",
  "properties": {
    "iso:country":"US",
    "sg:address":"5300 San Dario Ave",
    "sg:city":"Laredo",
    "sg:classifiers":[
        {
            "category":"Restaurant",
            "type":"Food & Drink"
        }
    ],
    "sg:menulink":"http://www.allmenus.com/tx/laredo/15195-tony-romas/menu/",
    "sg:phone":"+1 956 722 7427",
    "sg:postcode":"78041",
    "sg:province":"TX",
    "sg:tags":[
        "seafood",
        "american"
    ],
    "wof:name":"Tony Romas",
    "wof:placetype":"venue"
},
  "geometry": {"coordinates":[-99.503096,27.547647],"type":"Point"}
}