{
  "type": "Feature",
  "properties": {
    "iso:country":"US",
    "sg:address":"3718 Big A Rd",
    "sg:city":"Rowlett",
    "sg:classifiers":[
        {
            "category":"Recreation",
            "type":"Entertainment"
        }
    ],
    "sg:phone":"+1 972 475 0435",
    "sg:postcode":"75089",
    "sg:province":"TX",
    "wof:name":"Body Boot Camp",
    "wof:placetype":"venue"
},
  "geometry": {"coordinates":[-96.557861,32.909482],"type":"Point"}
}