{
  "type": "Feature",
  "properties": {
    "iso:country":"US",
    "sg:address":"620 W Slaughter Ln",
    "sg:city":"Austin",
    "sg:classifiers":[
        {
            "category":"Autos & Motor Vehicles",
            "subcategory":"Automobile Sales",
            "type":"Retail Goods"
        },
        {
            "category":"Retail",
            "subcategory":"Auto Repair",
            "type":"Services"
        }
    ],
    "sg:phone":"+1 512 628 0500",
    "sg:postcode":"78748",
    "sg:province":"TX",
    "sg:tags":[
        "dealers-used",
        "car",
        "used",
        "cars-wholesale",
        "new"
    ],
    "sg:website":"www.samesrbm.com",
    "wof:name":"Sames Red Barn Motors",
    "wof:placetype":"venue"
},
  "geometry": {"coordinates":[-97.800786,30.17352],"type":"Point"}
}