{
  "type": "Feature",
  "properties": {
    "iso:country":"US",
    "sg:address":"5422 Heritage Cir",
    "sg:city":"Garland",
    "sg:classifiers":[
        {
            "category":"Professional",
            "type":"Services"
        }
    ],
    "sg:phone":"+1 972 495 1831",
    "sg:postcode":"75048",
    "sg:province":"TX",
    "wof:name":"Tomerce",
    "wof:placetype":"venue"
},
  "geometry": {"coordinates":[-96.571505,32.971375],"type":"Point"}
}