{
  "type": "Feature",
  "properties": {
    "iso:country":"US",
    "sg:address":"11403 Sagecreek Dr",
    "sg:city":"Houston",
    "sg:classifiers":[
        {
            "category":"Shopping",
            "subcategory":"Clothing, Apparel, & Fashions",
            "type":"Retail Goods"
        }
    ],
    "sg:phone":"+1 281 484 7638",
    "sg:postcode":"77089",
    "sg:province":"TX",
    "wof:name":"Top Bridal",
    "wof:placetype":"venue"
},
  "geometry": {"coordinates":[-95.215298,29.592737],"type":"Point"}
}