{
  "type": "Feature",
  "properties": {
    "iso:country":"US",
    "sg:address":"1201 E Main St",
    "sg:city":"Allen",
    "sg:classifiers":[
        {
            "category":"Education",
            "subcategory":"Library",
            "type":"Public Place"
        }
    ],
    "sg:phone":"+1 972 908 2508",
    "sg:postcode":"75002",
    "sg:province":"TX",
    "sg:tags":[
        "reading",
        "instruction"
    ],
    "sg:website":"http://www.kumon.com",
    "wof:name":"Kumon Math & Reading Center Of Allen-East",
    "wof:placetype":"venue"
},
  "geometry": {"coordinates":[-96.64147800000001,33.100313],"type":"Point"}
}