{
  "type": "Feature",
  "properties": {
    "iso:country":"US",
    "sg:address":"7510 Chelsea Pl",
    "sg:city":"Beaumont",
    "sg:classifiers":[
        {
            "category":"Building & Trades",
            "subcategory":"Cleaning & Sanitation",
            "type":"Services"
        }
    ],
    "sg:phone":"+1 409 893 5861",
    "sg:postcode":"77706",
    "sg:province":"TX",
    "sg:tags":[
        "maintenance"
    ],
    "wof:name":"Garys Home Maintenance",
    "wof:placetype":"venue"
},
  "geometry": {"coordinates":[-94.180198,30.076476],"type":"Point"}
}