{
  "type": "Feature",
  "properties": {
    "iso:country":"US",
    "sg:address":"2512 N Grandview Ave",
    "sg:city":"Odessa",
    "sg:classifiers":[
        {
            "category":"Professional",
            "subcategory":"Accounting & Tax Preparation",
            "type":"Services"
        }
    ],
    "sg:phone":"+1 432 362 7388",
    "sg:postcode":"79761",
    "sg:province":"TX",
    "sg:tags":[
        "return"
    ],
    "wof:name":"Xpress Cash",
    "wof:placetype":"venue"
},
  "geometry": {"coordinates":[-102.346802,31.874198],"type":"Point"}
}