{
  "type": "Feature",
  "properties": {
    "iso:country":"US",
    "sg:address":"6709 Levelland Rd",
    "sg:city":"Dallas",
    "sg:classifiers":[
        {
            "category":"Wholesale",
            "subcategory":"Hardware",
            "type":"Manufacturing & Wholesale Goods"
        }
    ],
    "sg:phone":"+1 972 248 0645",
    "sg:postcode":"75252",
    "sg:province":"TX",
    "sg:tags":[
        "builder",
        "accessory",
        "store",
        "kitchen"
    ],
    "sg:website":"www.dnbh.com",
    "wof:name":"Dallas North Builders Hardware",
    "wof:placetype":"venue"
},
  "geometry": {"coordinates":[-96.79270200000001,32.9883],"type":"Point"}
}