{
  "type": "Feature",
  "properties": {
    "iso:country":"US",
    "sg:address":"1583 American Plant Rd",
    "sg:city":"Waskom",
    "sg:classifiers":[
        {
            "category":"Freight",
            "type":"Transportation"
        }
    ],
    "sg:phone":"+1 903 687 2033",
    "sg:postcode":"75692",
    "sg:province":"TX",
    "sg:tags":[
        "operator",
        "trucking"
    ],
    "wof:name":"Futral Truck Lines Inc",
    "wof:placetype":"venue"
},
  "geometry": {"coordinates":[-94.111918,32.463597],"type":"Point"}
}