{
  "type": "Feature",
  "properties": {
    "iso:country":"US",
    "sg:address":"1700 Willow Creek Dr",
    "sg:city":"Austin",
    "sg:classifiers":[
        {
            "category":"Retail",
            "subcategory":"Car Wash",
            "type":"Services"
        }
    ],
    "sg:phone":"+1 512 916 4608",
    "sg:postcode":"78741",
    "sg:province":"TX",
    "sg:tags":[
        "carwash"
    ],
    "wof:name":"Willow Creek Car Wash",
    "wof:placetype":"venue"
},
  "geometry": {"coordinates":[-97.726997,30.236099],"type":"Point"}
}