{
  "type": "Feature",
  "properties": {
    "iso:country":"US",
    "sg:address":"13940 Bammel North Houston Rd",
    "sg:city":"Houston",
    "sg:classifiers":[
        {
            "category":"Building & Trades",
            "subcategory":"Cleaning & Sanitation",
            "type":"Services"
        }
    ],
    "sg:phone":"+1 281 440 4919",
    "sg:postcode":"77066",
    "sg:province":"TX",
    "sg:tags":[
        "maintenance"
    ],
    "wof:name":"C & S Building Maintance Svc",
    "wof:placetype":"venue"
},
  "geometry": {"coordinates":[-95.491986,29.978332],"type":"Point"}
}