{
  "type": "Feature",
  "properties": {
    "iso:country":"US",
    "sg:address":"2605 Shorecrest Dr",
    "sg:city":"Dallas",
    "sg:classifiers":[
        {
            "category":"Professional",
            "subcategory":"Engineering",
            "type":"Services"
        }
    ],
    "sg:phone":"+1 214 353 5000",
    "sg:postcode":"75235",
    "sg:province":"TX",
    "sg:tags":[
        "engineer"
    ],
    "wof:name":"Jacobs Engineering",
    "wof:placetype":"venue"
},
  "geometry": {"coordinates":[-96.862177,32.853215],"type":"Point"}
}