{
  "type": "Feature",
  "properties": {
    "iso:country":"US",
    "sg:address":"4410 Kemp Blvd",
    "sg:city":"Wichita Falls",
    "sg:classifiers":[
        {
            "category":"Utilities",
            "subcategory":"Mobile Phone",
            "type":"Services"
        }
    ],
    "sg:phone":"+1 940 696 1499",
    "sg:postcode":"76308",
    "sg:province":"TX",
    "sg:tags":[
        "telephone",
        "cellular"
    ],
    "wof:name":"First Impression Wireless",
    "wof:placetype":"venue"
},
  "geometry": {"coordinates":[-98.53607599999999,33.861916],"type":"Point"}
}