{
  "type": "Feature",
  "properties": {
    "iso:country":"US",
    "sg:address":"3838 Oak Lawn Ave",
    "sg:city":"Dallas",
    "sg:classifiers":[
        {
            "category":"Insurance",
            "subcategory":"Insurance Agent",
            "type":"Services"
        }
    ],
    "sg:phone":"+1 214 219 6610",
    "sg:postcode":"75219",
    "sg:province":"TX",
    "wof:name":"State Farm Insurance",
    "wof:placetype":"venue"
},
  "geometry": {"coordinates":[-96.80224200000001,32.815619],"type":"Point"}
}