{
  "type": "Feature",
  "properties": {
    "iso:country":"US",
    "sg:address":"6323 Ladera Dr",
    "sg:city":"Houston",
    "sg:classifiers":[
        {
            "category":"Retail",
            "subcategory":"Auto Repair",
            "type":"Services"
        }
    ],
    "sg:phone":"+1 281 561 6850",
    "sg:postcode":"77083",
    "sg:province":"TX",
    "sg:tags":[
        "general"
    ],
    "wof:name":"UNI Tech Automotive",
    "wof:placetype":"venue"
},
  "geometry": {"coordinates":[-95.647875,29.709903],"type":"Point"}
}