{
  "type": "Feature",
  "properties": {
    "iso:country":"US",
    "sg:address":"611 Lower Valley Ln",
    "sg:city":"Cibolo",
    "sg:classifiers":[
        {
            "category":"Building & Trades",
            "subcategory":"Construction",
            "type":"Services"
        }
    ],
    "sg:phone":"+1 210 658 6718",
    "sg:postcode":"78108",
    "sg:province":"TX",
    "sg:tags":[
        "house"
    ],
    "wof:name":"Dominguez Toerner",
    "wof:placetype":"venue"
},
  "geometry": {"coordinates":[-98.210747,29.528847],"type":"Point"}
}