{
  "type": "Feature",
  "properties": {
    "iso:country":"US",
    "sg:address":"2031 Dunstan Rd",
    "sg:city":"Houston",
    "sg:classifiers":[
        {
            "category":"Professional",
            "subcategory":"Lawyer & Legal Services",
            "type":"Services"
        }
    ],
    "sg:phone":"+1 713 520 5736",
    "sg:postcode":"77005",
    "sg:province":"TX",
    "wof:name":"Luby Ellen L Atty",
    "wof:placetype":"venue"
},
  "geometry": {"coordinates":[-95.407799,29.7209],"type":"Point"}
}