{
  "type": "Feature",
  "properties": {
    "iso:country":"US",
    "sg:address":"8357 FM 1459",
    "sg:city":"Sweeny",
    "sg:classifiers":[
        {
            "category":"Wholesale",
            "subcategory":"Farm Supplies",
            "type":"Manufacturing & Wholesale Goods"
        }
    ],
    "sg:phone":"+1 979 548 3944",
    "sg:postcode":"77480",
    "sg:province":"TX",
    "sg:tags":[
        "feed"
    ],
    "wof:name":"Bill's Supply & Feed",
    "wof:placetype":"venue"
},
  "geometry": {"coordinates":[-95.68913000000001,29.079315],"type":"Point"}
}