{
  "type": "Feature",
  "properties": {
    "iso:country":"US",
    "sg:address":"5521 Greenville Ave, Ste 109",
    "sg:city":"Dallas",
    "sg:classifiers":[
        {
            "category":"Food & Beverages",
            "subcategory":"Bakery",
            "type":"Retail Goods"
        }
    ],
    "sg:phone":"+1 214 692 6981",
    "sg:postcode":"75206",
    "sg:province":"TX",
    "sg:tags":[
        "sandwich"
    ],
    "wof:name":"Jersey Mike's Subs",
    "wof:placetype":"venue"
},
  "geometry": {"coordinates":[-96.769683,32.853912],"type":"Point"}
}