{
  "type": "Feature",
  "properties": {
    "iso:country":"US",
    "sg:address":"1400 Woodloch Forest Dr",
    "sg:city":"Spring",
    "sg:classifiers":[
        {
            "category":"Professional",
            "subcategory":"Lawyer & Legal Services",
            "type":"Services"
        }
    ],
    "sg:phone":"+1 832 381 3070",
    "sg:postcode":"77380",
    "sg:province":"TX",
    "sg:tags":[
        "attorney",
        "law",
        "transportation"
    ],
    "sg:website":"http://www.boltzlaw.com",
    "wof:name":"Boltz Law",
    "wof:placetype":"venue"
},
  "geometry": {"coordinates":[-95.455833,30.158421],"type":"Point"}
}