{
  "type": "Feature",
  "properties": {
    "iso:country":"US",
    "sg:address":"211 W Ford St",
    "sg:city":"Plainview",
    "sg:classifiers":[
        {
            "category":"Professional",
            "subcategory":"Business Services",
            "type":"Services"
        }
    ],
    "sg:phone":"+1 806 296 9789",
    "sg:postcode":"79065",
    "sg:province":"TX",
    "wof:name":"Jasper Wood Fire Extinguishers",
    "wof:placetype":"venue"
},
  "geometry": {"coordinates":[-100.957183,35.52703],"type":"Point"}
}