{
  "type": "Feature",
  "properties": {
    "iso:country":"US",
    "sg:address":"5640 Montana Ave",
    "sg:city":"El Paso",
    "sg:classifiers":[
        {
            "category":"Shopping",
            "subcategory":"Bicycles & Sporting Goods",
            "type":"Retail Goods"
        }
    ],
    "sg:phone":"+1 915 564 3732",
    "sg:postcode":"79925",
    "sg:province":"TX",
    "wof:name":"International Soccer",
    "wof:placetype":"venue"
},
  "geometry": {"coordinates":[-106.419661,31.78347],"type":"Point"}
}