{
  "type": "Feature",
  "properties": {
    "iso:country":"US",
    "sg:address":"5241 Mount Houston Rd",
    "sg:city":"Houston",
    "sg:classifiers":[
        {
            "category":"Education",
            "subcategory":"School",
            "type":"Public Place"
        }
    ],
    "sg:phone":"+1 281 985 6390",
    "sg:postcode":"77093",
    "sg:province":"TX",
    "sg:website":"www.aldine.k12.tx.us",
    "wof:name":"Aldine Independent School District",
    "wof:placetype":"venue"
},
  "geometry": {"coordinates":[-95.31549800000001,29.8911],"type":"Point"}
}