{
  "type": "Feature",
  "properties": {
    "iso:country":"US",
    "sg:address":"74 Hassell St",
    "sg:city":"San Angelo",
    "sg:classifiers":[
        {
            "category":"Shopping",
            "subcategory":"Catalog Store",
            "type":"Retail Goods"
        }
    ],
    "sg:phone":"+1 325 944 3375",
    "sg:postcode":"76901",
    "sg:province":"TX",
    "sg:tags":[
        "house",
        "mail"
    ],
    "wof:name":"Avon",
    "wof:placetype":"venue"
},
  "geometry": {"coordinates":[-100.47472999999999,31.447717],"type":"Point"}
}