{
  "type": "Feature",
  "properties": {
    "iso:country":"US",
    "sg:address":"16486 State Hwy 31",
    "sg:city":"Tyler",
    "sg:classifiers":[
        {
            "category":"Manufacturing",
            "subcategory":"Food",
            "type":"Manufacturing & Wholesale Goods"
        },
        {
            "category":"Wholesale",
            "subcategory":"Groceries",
            "type":"Manufacturing & Wholesale Goods"
        }
    ],
    "sg:phone":"+1 903 595 1375",
    "sg:postcode":"75709",
    "sg:province":"TX",
    "sg:tags":[
        "baker",
        "product",
        "mfg"
    ],
    "wof:name":"Bimbo Bakeries USA",
    "wof:placetype":"venue"
},
  "geometry": {"coordinates":[-95.443983,32.319291],"type":"Point"}
}