{
  "type": "Feature",
  "properties": {
    "iso:country":"US",
    "sg:address":"102 Shaver St",
    "sg:city":"Pasadena",
    "sg:classifiers":[
        {
            "category":"Communications",
            "subcategory":"Radio Station",
            "type":"Services"
        }
    ],
    "sg:phone":"+1 713 477 6318",
    "sg:postcode":"77506",
    "sg:province":"TX",
    "wof:name":"Pasadena Citizen Sports Line",
    "wof:placetype":"venue"
},
  "geometry": {"coordinates":[-95.211502,29.7124],"type":"Point"}
}