{
  "type": "Feature",
  "properties": {
    "iso:country":"US",
    "sg:address":"332 Leeward Cir",
    "sg:city":"Azle",
    "sg:classifiers":[
        {
            "category":"Manufacturing",
            "subcategory":"Tools & Machinery",
            "type":"Manufacturing & Wholesale Goods"
        }
    ],
    "sg:phone":"+1 817 270 2204",
    "sg:postcode":"76020",
    "sg:province":"TX",
    "sg:tags":[
        "industry",
        "mfg"
    ],
    "wof:name":"Adams Engineers & Equipment",
    "wof:placetype":"venue"
},
  "geometry": {"coordinates":[-97.51612799999999,32.897596],"type":"Point"}
}