{
  "type": "Feature",
  "properties": {
    "iso:country":"US",
    "sg:address":"5956 Sherry Ln",
    "sg:city":"Dallas",
    "sg:classifiers":[
        {
            "category":"Insurance",
            "subcategory":"Insurance Agent",
            "type":"Services"
        }
    ],
    "sg:phone":"+1 214 346 2954",
    "sg:postcode":"75225",
    "sg:province":"TX",
    "wof:name":"Farmers Insurance Group",
    "wof:placetype":"venue"
},
  "geometry": {"coordinates":[-96.810238,32.862216],"type":"Point"}
}