{
  "type": "Feature",
  "properties": {
    "iso:country":"US",
    "sg:address":"5732 Manchaca Rd",
    "sg:city":"Austin",
    "sg:classifiers":[
        {
            "category":"Personal",
            "subcategory":"Beauty Salon",
            "type":"Services"
        }
    ],
    "sg:phone":"+1 512 444 1510",
    "sg:postcode":"78745",
    "sg:province":"TX",
    "sg:tags":[
        "shop"
    ],
    "wof:name":"Anna Le",
    "wof:placetype":"venue"
},
  "geometry": {"coordinates":[-97.80066100000001,30.213879],"type":"Point"}
}