{
  "type": "Feature",
  "properties": {
    "iso:country":"US",
    "sg:address":"2910 Cherry Springs Dr",
    "sg:city":"Missouri City",
    "sg:classifiers":[
        {
            "category":"Restaurant",
            "type":"Food & Drink"
        }
    ],
    "sg:phone":"+1 281 438 9628",
    "sg:postcode":"77459",
    "sg:province":"TX",
    "sg:tags":[
        "eating"
    ],
    "wof:name":"Taqueria Zirandaro",
    "wof:placetype":"venue"
},
  "geometry": {"coordinates":[-95.52406499999999,29.577493],"type":"Point"}
}