{
  "type": "Feature",
  "properties": {
    "iso:country":"US",
    "sg:address":"104 SW 1200",
    "sg:city":"Andrews",
    "sg:classifiers":[
        {
            "category":"Building & Trades",
            "subcategory":"Construction",
            "type":"Services"
        },
        {
            "category":"Home & Garden",
            "subcategory":"Furniture",
            "type":"Retail Goods"
        }
    ],
    "sg:phone":"+1 432 524 6609",
    "sg:postcode":"79714",
    "sg:province":"TX",
    "sg:tags":[
        "house",
        "maker",
        "cabinet"
    ],
    "wof:name":"Superior Woodworks",
    "wof:placetype":"venue"
},
  "geometry": {"coordinates":[-102.54140599999999,32.30213],"type":"Point"}
}