{
  "type": "Feature",
  "properties": {
    "iso:country":"US",
    "sg:address":"1847 State Hwy 46",
    "sg:city":"New Braunfels",
    "sg:classifiers":[
        {
            "category":"Food & Beverages",
            "subcategory":"Liquor & Beverages",
            "type":"Retail Goods"
        }
    ],
    "sg:phone":"+1 830 608 9359",
    "sg:postcode":"78132",
    "sg:province":"TX",
    "sg:tags":[
        "alcoholic"
    ],
    "wof:name":"Burro Liquors",
    "wof:placetype":"venue"
},
  "geometry": {"coordinates":[-98.162381,29.718458],"type":"Point"}
}