{
  "type": "Feature",
  "properties": {
    "iso:country":"US",
    "sg:address":"25100 Pedernales Canyon Trl",
    "sg:city":"Spicewood",
    "sg:classifiers":[
        {
            "category":"Building & Trades",
            "subcategory":"Cleaning & Sanitation",
            "type":"Services"
        }
    ],
    "sg:phone":"+1 512 264 2579",
    "sg:postcode":"78669",
    "sg:province":"TX",
    "sg:tags":[
        "maintenance"
    ],
    "wof:name":"Austin Building Services",
    "wof:placetype":"venue"
},
  "geometry": {"coordinates":[-98.104677,30.393023],"type":"Point"}
}