{
  "type": "Feature",
  "properties": {
    "iso:country":"US",
    "sg:address":"112 Produce Row",
    "sg:city":"San Antonio",
    "sg:classifiers":[
        {
            "category":"Shopping",
            "subcategory":"Jewelry",
            "type":"Retail Goods"
        }
    ],
    "sg:phone":"+1 210 229 9014",
    "sg:postcode":"78207",
    "sg:province":"TX",
    "sg:tags":[
        "jeweler"
    ],
    "wof:name":"Viriana Jewelry & Craft",
    "wof:placetype":"venue"
},
  "geometry": {"coordinates":[-98.499116,29.425076],"type":"Point"}
}