{
  "type": "Feature",
  "properties": {
    "iso:country":"US",
    "sg:address":"2515 Canal Ave",
    "sg:city":"Nederland",
    "sg:classifiers":[
        {
            "category":"Organizations",
            "subcategory":"Religious Organization",
            "type":"Services"
        }
    ],
    "sg:phone":"+1 409 722 4701",
    "sg:postcode":"77627",
    "sg:province":"TX",
    "sg:tags":[
        "church"
    ],
    "sg:website":"www.calvarybaptistnederland.org",
    "wof:name":"Calvary Baptist Church",
    "wof:placetype":"venue"
},
  "geometry": {"coordinates":[-94.009838,29.975829],"type":"Point"}
}