{
  "type": "Feature",
  "properties": {
    "iso:country":"US",
    "sg:address":"1011 San Jacinto Blvd",
    "sg:city":"Austin",
    "sg:classifiers":[
        {
            "category":"Freight",
            "type":"Transportation"
        },
        {
            "category":"Shopping",
            "subcategory":"Shoes",
            "type":"Retail Goods"
        }
    ],
    "sg:phone":"+1 512 397 3801",
    "sg:postcode":"78701",
    "sg:province":"TX",
    "wof:name":"Jim Buster Transportation",
    "wof:placetype":"venue"
},
  "geometry": {"coordinates":[-97.73861100000001,30.271941],"type":"Point"}
}