{
  "type": "Feature",
  "properties": {
    "iso:country":"US",
    "sg:address":"104 S Lampasas St",
    "sg:city":"Round Rock",
    "sg:classifiers":[
        {
            "category":"Retail",
            "subcategory":"Auto Repair",
            "type":"Services"
        }
    ],
    "sg:phone":"+1 512 218 0722",
    "sg:postcode":"78664",
    "sg:province":"TX",
    "sg:tags":[
        "repairing",
        "automobile",
        "general",
        "automotive",
        "sup"
    ],
    "sg:website":"www.autocool.com",
    "wof:name":"A C Authority",
    "wof:placetype":"venue"
},
  "geometry": {"coordinates":[-97.67782,30.508804],"type":"Point"}
}