{
  "type": "Feature",
  "properties": {
    "iso:country":"US",
    "sg:address":"220 N Esplanade St",
    "sg:city":"Cuero",
    "sg:classifiers":[
        {
            "category":"Retail",
            "subcategory":"Auto Repair",
            "type":"Services"
        }
    ],
    "sg:phone":"+1 361 275 2387",
    "sg:postcode":"77954",
    "sg:province":"TX",
    "sg:tags":[
        "general",
        "supply"
    ],
    "wof:name":"Firestone",
    "wof:placetype":"venue"
},
  "geometry": {"coordinates":[-97.291004,29.091978],"type":"Point"}
}