{
  "type": "Feature",
  "properties": {
    "iso:country":"US",
    "sg:address":"10512 Huntington Rd",
    "sg:city":"Frisco",
    "sg:classifiers":[
        {
            "category":"Utilities",
            "subcategory":"Telephone",
            "type":"Services"
        }
    ],
    "sg:phone":"+1 972 377 9909",
    "sg:postcode":"75035",
    "sg:province":"TX",
    "sg:tags":[
        "development",
        "web",
        "hosting"
    ],
    "wof:name":"Stolid Networks",
    "wof:placetype":"venue"
},
  "geometry": {"coordinates":[-96.788736,33.14761],"type":"Point"}
}