{
  "type": "Feature",
  "properties": {
    "iso:country":"US",
    "sg:address":"3601 Encanto Dr",
    "sg:city":"Fort Worth",
    "sg:classifiers":[
        {
            "category":"Insurance",
            "subcategory":"Insurance Agent",
            "type":"Services"
        }
    ],
    "sg:phone":"+1 817 370 7400",
    "sg:postcode":"76109",
    "sg:province":"TX",
    "wof:name":"Quest Insurance Svc Inc",
    "wof:placetype":"venue"
},
  "geometry": {"coordinates":[-97.37921900000001,32.691874],"type":"Point"}
}