{
  "type": "Feature",
  "properties": {
    "iso:country":"US",
    "sg:address":"7954 Candle Green Ln",
    "sg:city":"Houston",
    "sg:classifiers":[
        {
            "category":"Professional",
            "subcategory":"Business Services",
            "type":"Services"
        }
    ],
    "sg:phone":"+1 713 721 0099",
    "sg:postcode":"77071",
    "sg:province":"TX",
    "wof:name":"Branch Expansion Services",
    "wof:placetype":"venue"
},
  "geometry": {"coordinates":[-95.517685,29.644867],"type":"Point"}
}