{
  "type": "Feature",
  "properties": {
    "iso:country":"US",
    "sg:address":"810 E Academy St",
    "sg:city":"Brenham",
    "sg:classifiers":[
        {
            "category":"Social Services",
            "subcategory":"Child Care",
            "type":"Services"
        }
    ],
    "sg:phone":"+1 979 830 0093",
    "sg:postcode":"77833",
    "sg:province":"TX",
    "wof:name":"Terrie Collins",
    "wof:placetype":"venue"
},
  "geometry": {"coordinates":[-96.39121799999999,30.172552],"type":"Point"}
}