{
  "type": "Feature",
  "properties": {
    "iso:country":"US",
    "sg:address":"202 Banks Dr",
    "sg:city":"Weatherford",
    "sg:classifiers":[
        {
            "category":"Building & Trades",
            "subcategory":"Construction",
            "type":"Services"
        }
    ],
    "sg:phone":"+1 817 599 9595",
    "sg:postcode":"76087",
    "sg:province":"TX",
    "sg:tags":[
        "house"
    ],
    "wof:name":"Montex Builders LLC",
    "wof:placetype":"venue"
},
  "geometry": {"coordinates":[-97.744142,32.738028],"type":"Point"}
}