{
  "type": "Feature",
  "properties": {
    "iso:country":"US",
    "sg:address":"301 NW Alpine Dr",
    "sg:city":"Plainview",
    "sg:classifiers":[
        {
            "category":"Professional",
            "type":"Services"
        }
    ],
    "sg:phone":"+1 806 292 6763",
    "sg:postcode":"79072",
    "sg:province":"TX",
    "wof:name":"Foodzone",
    "wof:placetype":"venue"
},
  "geometry": {"coordinates":[-101.70646600000001,34.169593],"type":"Point"}
}