{
  "type": "Feature",
  "properties": {
    "iso:country":"US",
    "sg:address":"115 E Main St",
    "sg:city":"La Porte",
    "sg:classifiers":[
        {
            "category":"Retail",
            "subcategory":"Auto Repair",
            "type":"Services"
        }
    ],
    "sg:phone":"+1 281 471 8439",
    "sg:postcode":"77571",
    "sg:province":"TX",
    "sg:tags":[
        "repairing",
        "automobile"
    ],
    "wof:name":"C & K Svc",
    "wof:placetype":"venue"
},
  "geometry": {"coordinates":[-95.018502,29.665947],"type":"Point"}
}