{
  "type": "Feature",
  "properties": {
    "iso:country":"US",
    "sg:address":"5409 95th St",
    "sg:city":"Lubbock",
    "sg:classifiers":[
        {
            "category":"Professional",
            "type":"Services"
        }
    ],
    "sg:phone":"+1 806 798 8862",
    "sg:postcode":"79424",
    "sg:province":"TX",
    "wof:name":"Ccr Metal Works",
    "wof:placetype":"venue"
},
  "geometry": {"coordinates":[-101.928359,33.507586],"type":"Point"}
}