{
  "type": "Feature",
  "properties": {
    "iso:country":"US",
    "sg:address":"1429 W Polk Ave",
    "sg:city":"Pharr",
    "sg:classifiers":[
        {
            "category":"Retail",
            "subcategory":"Repair Shop",
            "type":"Services"
        }
    ],
    "sg:phone":"+1 956 686 3352",
    "sg:postcode":"78577",
    "sg:province":"TX",
    "sg:tags":[
        "water",
        "equipment",
        "softening"
    ],
    "wof:name":"Aquatek Industries",
    "wof:placetype":"venue"
},
  "geometry": {"coordinates":[-98.20195099999999,26.207152],"type":"Point"}
}