{
  "type": "Feature",
  "properties": {
    "iso:country":"US",
    "sg:address":"3095 Bellaire Ranch Dr",
    "sg:city":"Fort Worth",
    "sg:classifiers":[
        {
            "category":"Professional",
            "subcategory":"Management & Consulting",
            "type":"Services"
        }
    ],
    "sg:phone":"+1 817 246 7064",
    "sg:postcode":"76109",
    "sg:province":"TX",
    "wof:name":"Piscitellis",
    "wof:placetype":"venue"
},
  "geometry": {"coordinates":[-97.39131399999999,32.705847],"type":"Point"}
}