{
  "type": "Feature",
  "properties": {
    "iso:country":"US",
    "sg:address":"4130 Briton Ct",
    "sg:city":"Grand Prairie",
    "sg:classifiers":[
        {
            "category":"Manufacturing",
            "subcategory":"Tools & Machinery",
            "type":"Manufacturing & Wholesale Goods"
        }
    ],
    "sg:phone":"+1 972 988 8164",
    "sg:postcode":"75052",
    "sg:province":"TX",
    "sg:tags":[
        "industry",
        "mfg"
    ],
    "wof:name":"Integrated Control Systems",
    "wof:placetype":"venue"
},
  "geometry": {"coordinates":[-97.04344399999999,32.668787],"type":"Point"}
}