{
  "type": "Feature",
  "properties": {
    "iso:country":"US",
    "sg:address":"3520 W Alabama St",
    "sg:city":"Houston",
    "sg:classifiers":[
        {
            "category":"Retail",
            "subcategory":"Auto Repair",
            "type":"Services"
        }
    ],
    "sg:phone":"+1 713 626 9320",
    "sg:postcode":"77027",
    "sg:province":"TX",
    "wof:name":"Swiss Garage",
    "wof:placetype":"venue"
},
  "geometry": {"coordinates":[-95.43409699999999,29.7384],"type":"Point"}
}