{
  "type": "Feature",
  "properties": {
    "iso:country":"US",
    "sg:address":"303 N Main St",
    "sg:city":"Belton",
    "sg:classifiers":[
        {
            "category":"Retail",
            "subcategory":"Car Wash",
            "type":"Services"
        }
    ],
    "sg:phone":"+1 254 933 0027",
    "sg:postcode":"76513",
    "sg:province":"TX",
    "sg:tags":[
        "automobile",
        "detail",
        "clean"
    ],
    "wof:name":"Thundershine",
    "wof:placetype":"venue"
},
  "geometry": {"coordinates":[-97.46262299999999,31.059186],"type":"Point"}
}