{
  "type": "Feature",
  "properties": {
    "iso:country":"US",
    "sg:address":"2703 Lasses Blvd",
    "sg:city":"San Antonio",
    "sg:classifiers":[
        {
            "category":"Food & Beverages",
            "subcategory":"Groceries & Convenience Stores",
            "type":"Retail Goods"
        }
    ],
    "sg:phone":"+1 210 333 4126",
    "sg:postcode":"78223",
    "sg:province":"TX",
    "wof:name":"Lasses Food Mart",
    "wof:placetype":"venue"
},
  "geometry": {"coordinates":[-98.446714,29.355738],"type":"Point"}
}