{
  "type": "Feature",
  "properties": {
    "iso:country":"US",
    "sg:address":"4532 Braeburn Dr",
    "sg:city":"Bellaire",
    "sg:classifiers":[
        {
            "category":"Health Services",
            "subcategory":"Clinic",
            "type":"Services"
        }
    ],
    "sg:phone":"+1 713 501 0226",
    "sg:postcode":"77401",
    "sg:province":"TX",
    "wof:name":"Pampassion Health",
    "wof:placetype":"venue"
},
  "geometry": {"coordinates":[-95.45411199999999,29.695938],"type":"Point"}
}