{
  "type": "Feature",
  "properties": {
    "iso:country":"US",
    "sg:address":"140 Patterson Ave",
    "sg:city":"San Antonio",
    "sg:classifiers":[
        {
            "category":"Professional",
            "subcategory":"Lawyer & Legal Services",
            "type":"Services"
        }
    ],
    "sg:phone":"+1 210 824 9890",
    "sg:postcode":"78209",
    "sg:province":"TX",
    "sg:tags":[
        "planning",
        "estate"
    ],
    "wof:name":"Executor's Helper",
    "wof:placetype":"venue"
},
  "geometry": {"coordinates":[-98.464591,29.471394],"type":"Point"}
}