{
  "type": "Feature",
  "properties": {
    "iso:country":"US",
    "sg:address":"401 Anderson St",
    "sg:city":"College Station",
    "sg:classifiers":[
        {
            "category":"Professional",
            "subcategory":"Research",
            "type":"Services"
        }
    ],
    "sg:phone":"+1 831 345 4782",
    "sg:postcode":"77840",
    "sg:province":"TX",
    "sg:tags":[
        "lab"
    ],
    "wof:name":"Tara A Kneeshaw",
    "wof:placetype":"venue"
},
  "geometry": {"coordinates":[-96.321736,30.609997],"type":"Point"}
}