{
  "type": "Feature",
  "properties": {
    "iso:country":"US",
    "sg:address":"701 Nannette St",
    "sg:city":"Fort Worth",
    "sg:classifiers":[
        {
            "category":"Building & Trades",
            "subcategory":"Plumbing",
            "type":"Services"
        }
    ],
    "sg:phone":"+1 817 732 6368",
    "sg:postcode":"76114",
    "sg:province":"TX",
    "sg:tags":[
        "contractor"
    ],
    "wof:name":"Backflow Management Inc S",
    "wof:placetype":"venue"
},
  "geometry": {"coordinates":[-97.414609,32.768766],"type":"Point"}
}