{
  "type": "Feature",
  "properties": {
    "iso:country":"US",
    "sg:address":"2807 Allen St Suite# 707",
    "sg:city":"Dallas",
    "sg:classifiers":[
        {
            "category":"Building & Trades",
            "subcategory":"Locksmith",
            "type":"Services"
        }
    ],
    "sg:phone":"+1 214 434 2643",
    "sg:postcode":"75204",
    "sg:province":"TX",
    "sg:tags":[
        "key"
    ],
    "sg:website":"www.adi-locksmith.com",
    "wof:name":"ADI Locksmith, Inc.",
    "wof:placetype":"venue"
},
  "geometry": {"coordinates":[-96.801295,32.800867],"type":"Point"}
}