{
  "type": "Feature",
  "properties": {
    "iso:country":"US",
    "sg:address":"13820 S Wayside Dr",
    "sg:city":"Houston",
    "sg:classifiers":[
        {
            "category":"Manufacturing",
            "subcategory":"Tools & Machinery",
            "type":"Manufacturing & Wholesale Goods"
        }
    ],
    "sg:phone":"+1 713 991 2454",
    "sg:postcode":"77048",
    "sg:province":"TX",
    "sg:tags":[
        "industrial",
        "mfg"
    ],
    "wof:name":"Olson Grinding Inc",
    "wof:placetype":"venue"
},
  "geometry": {"coordinates":[-95.317877,29.61158],"type":"Point"}
}