{
  "type": "Feature",
  "properties": {
    "iso:country":"US",
    "sg:address":"973 Melbourne Rd",
    "sg:city":"Hurst",
    "sg:classifiers":[
        {
            "category":"Manufacturing",
            "subcategory":"Jewelry",
            "type":"Manufacturing & Wholesale Goods"
        }
    ],
    "sg:phone":"+1 817 284 5602",
    "sg:postcode":"76053",
    "sg:province":"TX",
    "sg:tags":[
        "ware",
        "mfg"
    ],
    "wof:name":"Silver Creek Jewelers",
    "wof:placetype":"venue"
},
  "geometry": {"coordinates":[-97.19869,32.825365],"type":"Point"}
}