{
  "type": "Feature",
  "properties": {
    "iso:country":"US",
    "sg:address":"1032 Austin Hwy",
    "sg:city":"San Antonio",
    "sg:classifiers":[
        {
            "category":"Travel",
            "subcategory":"Hotels & Motels",
            "type":"Entertainment"
        }
    ],
    "sg:phone":"+1 210 826 9344",
    "sg:postcode":"78209",
    "sg:province":"TX",
    "sg:tags":[
        "operation"
    ],
    "wof:name":"Steele Motel Three",
    "wof:placetype":"venue"
},
  "geometry": {"coordinates":[-98.45132,29.485357],"type":"Point"}
}