{
  "type": "Feature",
  "properties": {
    "iso:country":"US",
    "sg:address":"3629 Mattox St",
    "sg:city":"El Paso",
    "sg:classifiers":[
        {
            "category":"Retail",
            "subcategory":"Repair Shop",
            "type":"Services"
        }
    ],
    "sg:phone":"+1 915 740 7788",
    "sg:postcode":"79925",
    "sg:province":"TX",
    "sg:tags":[
        "food",
        "equipment",
        "sales"
    ],
    "wof:name":"Dionix Enterprises",
    "wof:placetype":"venue"
},
  "geometry": {"coordinates":[-106.367763,31.794375],"type":"Point"}
}