{
  "type": "Feature",
  "properties": {
    "iso:country":"US",
    "sg:address":"5306 McCarty Ln",
    "sg:city":"Austin",
    "sg:classifiers":[
        {
            "category":"Building & Trades",
            "subcategory":"Landscaping Services",
            "type":"Services"
        }
    ],
    "sg:phone":"+1 512 892 1354",
    "sg:postcode":"78749",
    "sg:province":"TX",
    "sg:tags":[
        "lawn",
        "hwy",
        "mowing"
    ],
    "wof:name":"L L & N Contracting",
    "wof:placetype":"venue"
},
  "geometry": {"coordinates":[-97.851929,30.226359],"type":"Point"}
}