{
  "type": "Feature",
  "properties": {
    "iso:country":"US",
    "sg:address":"740 Meadowlark Cir",
    "sg:city":"Crowley",
    "sg:classifiers":[
        {
            "category":"Personal",
            "type":"Services"
        }
    ],
    "sg:phone":"+1 817 540 2344",
    "sg:postcode":"76036",
    "sg:province":"TX",
    "sg:tags":[
        "mover"
    ],
    "wof:name":"A 1 Lewis Moving",
    "wof:placetype":"venue"
},
  "geometry": {"coordinates":[-97.36827700000001,32.576512],"type":"Point"}
}