{
  "type": "Feature",
  "properties": {
    "iso:country":"US",
    "sg:address":"1043 W Bay Area Blvd",
    "sg:city":"Webster",
    "sg:classifiers":[
        {
            "category":"Autos & Motor Vehicles",
            "subcategory":"Fuel & Gas Station",
            "type":"Retail Goods"
        }
    ],
    "sg:phone":"+1 281 554 8832",
    "sg:postcode":"77598",
    "sg:province":"TX",
    "sg:tags":[
        "oil"
    ],
    "wof:name":"Chevron",
    "wof:placetype":"venue"
},
  "geometry": {"coordinates":[-95.13873,29.541904],"type":"Point"}
}