{
  "type": "Feature",
  "properties": {
    "iso:country":"US",
    "sg:address":"320 S Clark Rd",
    "sg:city":"Cedar Hill",
    "sg:classifiers":[
        {
            "category":"Personal",
            "subcategory":"Nail Salon",
            "type":"Services"
        }
    ],
    "sg:phone":"+1 469 272 0307",
    "sg:postcode":"75104",
    "sg:province":"TX",
    "wof:name":"U S Nails",
    "wof:placetype":"venue"
},
  "geometry": {"coordinates":[-96.94259599999999,32.585098],"type":"Point"}
}