{
  "type": "Feature",
  "properties": {
    "iso:country":"US",
    "sg:address":"800 W 38th St",
    "sg:city":"Austin",
    "sg:classifiers":[
        {
            "category":"Real Estate",
            "subcategory":"Real Estate Operator",
            "type":"Services"
        }
    ],
    "sg:phone":"+1 512 651 5700",
    "sg:postcode":"78705",
    "sg:province":"TX",
    "sg:tags":[
        "apartment"
    ],
    "sg:website":"http://local.ingenio.com/Listings/Details.aspx?NUM=a%3a10243054%3a13%3a4859924%3a14%3a0%3a7",
    "wof:name":"Gables At Central Park",
    "wof:placetype":"venue"
},
  "geometry": {"coordinates":[-97.74142999999999,30.304447],"type":"Point"}
}