{
  "type": "Feature",
  "properties": {
    "iso:country":"US",
    "sg:address":"201 E Pioneer Dr",
    "sg:city":"Irving",
    "sg:classifiers":[
        {
            "category":"Building & Trades",
            "subcategory":"Plumbing",
            "type":"Services"
        }
    ],
    "sg:phone":"+1 972 438 7612",
    "sg:postcode":"75061",
    "sg:province":"TX",
    "sg:tags":[
        "conditioning",
        "contractor",
        "system",
        "air"
    ],
    "wof:name":"Arnold S Service Inc",
    "wof:placetype":"venue"
},
  "geometry": {"coordinates":[-96.943788,32.818148],"type":"Point"}
}