{
  "type": "Feature",
  "properties": {
    "iso:country":"US",
    "sg:address":"7134 N Loop Dr",
    "sg:city":"El Paso",
    "sg:classifiers":[
        {
            "category":"Building & Trades",
            "subcategory":"Electrical",
            "type":"Services"
        }
    ],
    "sg:phone":"+1 915 771 8733",
    "sg:postcode":"79915",
    "sg:province":"TX",
    "sg:tags":[
        "electrical",
        "electric",
        "contractor"
    ],
    "wof:name":"International Electric",
    "wof:placetype":"venue"
},
  "geometry": {"coordinates":[-106.38208299999999,31.755086],"type":"Point"}
}