{
  "type": "Feature",
  "properties": {
    "iso:country":"US",
    "sg:address":"1601 S Morgan St",
    "sg:city":"Granbury",
    "sg:classifiers":[
        {
            "category":"Retail",
            "subcategory":"Repair Shop",
            "type":"Services"
        }
    ],
    "sg:phone":"+1 817 579 1656",
    "sg:postcode":"76048",
    "sg:province":"TX",
    "sg:tags":[
        "boat"
    ],
    "wof:name":"Tims Marine Service Inc",
    "wof:placetype":"venue"
},
  "geometry": {"coordinates":[-97.793308,32.427785],"type":"Point"}
}