{
  "type": "Feature",
  "properties": {
    "iso:country":"US",
    "sg:address":"24818 Spring Creek Dr",
    "sg:city":"Spring",
    "sg:classifiers":[
        {
            "category":"Shopping",
            "subcategory":"Gifts & Souvenirs",
            "type":"Retail Goods"
        }
    ],
    "sg:phone":"+1 281 321 3162",
    "sg:postcode":"77380",
    "sg:province":"TX",
    "sg:tags":[
        "basket",
        "parcel"
    ],
    "wof:name":"Mike's Gift Baskets",
    "wof:placetype":"venue"
},
  "geometry": {"coordinates":[-95.492436,30.12812],"type":"Point"}
}