{
  "type": "Feature",
  "properties": {
    "iso:country":"US",
    "sg:address":"8857 Gateway Blvd W",
    "sg:city":"El Paso",
    "sg:classifiers":[
        {
            "category":"Home & Garden",
            "subcategory":"Building Materials",
            "type":"Retail Goods"
        }
    ],
    "sg:phone":"+1 915 778 4127",
    "sg:postcode":"79935",
    "sg:province":"TX",
    "sg:tags":[
        "glass",
        "window",
        "plate"
    ],
    "wof:name":"R & E Gabldon Glass Inc",
    "wof:placetype":"venue"
},
  "geometry": {"coordinates":[-106.375676,31.771226],"type":"Point"}
}