{
  "type": "Feature",
  "properties": {
    "iso:country":"US",
    "sg:address":"3800 W Waco Dr",
    "sg:city":"Waco",
    "sg:classifiers":[
        {
            "category":"Insurance",
            "subcategory":"Hazard Insurance",
            "type":"Services"
        }
    ],
    "sg:phone":"+1 254 772 8866",
    "sg:postcode":"76710",
    "sg:province":"TX",
    "sg:tags":[
        "bond"
    ],
    "wof:name":"Gonzales Bail Bonds",
    "wof:placetype":"venue"
},
  "geometry": {"coordinates":[-97.16661999999999,31.531989],"type":"Point"}
}