{
  "type": "Feature",
  "properties": {
    "iso:country":"US",
    "sg:address":"908 E I- 30",
    "sg:city":"Garland",
    "sg:classifiers":[
        {
            "category":"Restaurant",
            "type":"Food & Drink"
        }
    ],
    "sg:phone":"+1 972 226 7788",
    "sg:postcode":"75043",
    "sg:province":"TX",
    "sg:tags":[
        "eating"
    ],
    "wof:name":"Dices Pizza & Sub Inc",
    "wof:placetype":"venue"
},
  "geometry": {"coordinates":[-96.551754,32.858097],"type":"Point"}
}