{
  "type": "Feature",
  "properties": {
    "iso:country":"US",
    "sg:address":"500 W Main St",
    "sg:city":"Baytown",
    "sg:classifiers":[
        {
            "category":"Organizations",
            "subcategory":"Religious Organization",
            "type":"Services"
        }
    ],
    "sg:phone":"+1 281 428 5745",
    "sg:postcode":"77520",
    "sg:province":"TX",
    "wof:name":"Iglesia Apospolica De La SE",
    "wof:placetype":"venue"
},
  "geometry": {"coordinates":[-94.976472,29.721203],"type":"Point"}
}