{
  "type": "Feature",
  "properties": {
    "iso:country":"US",
    "sg:address":"13401 Wigginsville Rd",
    "sg:city":"Conroe",
    "sg:classifiers":[
        {
            "category":"Social Services",
            "subcategory":"Child Care",
            "type":"Services"
        },
        {
            "category":"Education",
            "subcategory":"School",
            "type":"Public Place"
        }
    ],
    "sg:phone":"+1 936 231 2445",
    "sg:postcode":"77302",
    "sg:province":"TX",
    "wof:name":"Little Angels Academy",
    "wof:placetype":"venue"
},
  "geometry": {"coordinates":[-95.338284,30.257091],"type":"Point"}
}