{
  "type": "Feature",
  "properties": {
    "iso:country":"US",
    "sg:address":"907 SW Ave G",
    "sg:city":"Seminole",
    "sg:classifiers":[
        {
            "category":"Organizations",
            "subcategory":"Religious Organization",
            "type":"Services"
        }
    ],
    "sg:phone":"+1 432 758 3390",
    "sg:postcode":"79360",
    "sg:province":"TX",
    "wof:name":"Templo Nazareth",
    "wof:placetype":"venue"
},
  "geometry": {"coordinates":[-102.655321,32.711106],"type":"Point"}
}