{
  "type": "Feature",
  "properties": {
    "iso:country":"US",
    "sg:address":"1705 S Zarzamora",
    "sg:city":"San Antonio",
    "sg:classifiers":[
        {
            "category":"Restaurant",
            "type":"Food & Drink"
        }
    ],
    "sg:phone":"+1 210 226 9998",
    "sg:postcode":"78207",
    "sg:province":"TX",
    "wof:name":"Panchito's Restaurants",
    "wof:placetype":"venue"
},
  "geometry": {"coordinates":[-98.529628,29.407975],"type":"Point"}
}