{
  "type": "Feature",
  "properties": {
    "iso:country":"US",
    "sg:address":"510 Murphy Rd",
    "sg:city":"Stafford",
    "sg:classifiers":[
        {
            "category":"Autos & Motor Vehicles",
            "subcategory":"Auto Supplies",
            "type":"Retail Goods"
        }
    ],
    "sg:phone":"+1 281 499 6621",
    "sg:postcode":"77477",
    "sg:province":"TX",
    "sg:tags":[
        "tire"
    ],
    "wof:name":"Cannon Car Center",
    "wof:placetype":"venue"
},
  "geometry": {"coordinates":[-95.564555,29.612396],"type":"Point"}
}