{
  "type": "Feature",
  "properties": {
    "iso:country":"US",
    "sg:address":"5605 Nuckols Crossing Rd",
    "sg:city":"Austin",
    "sg:classifiers":[
        {
            "category":"Education",
            "subcategory":"School",
            "type":"Public Place"
        }
    ],
    "sg:phone":"+1 512 414 2556",
    "sg:postcode":"78744",
    "sg:province":"TX",
    "wof:name":"Widen Elementary School",
    "wof:placetype":"venue"
},
  "geometry": {"coordinates":[-97.740127,30.191158],"type":"Point"}
}