{
  "type": "Feature",
  "properties": {
    "iso:country":"US",
    "sg:address":"2225 E Southmore Ave",
    "sg:city":"Pasadena",
    "sg:classifiers":[
        {
            "category":"Autos & Motor Vehicles",
            "subcategory":"Automobile Sales",
            "type":"Retail Goods"
        }
    ],
    "sg:phone":"+1 713 472 0004",
    "sg:postcode":"77502",
    "sg:province":"TX",
    "sg:tags":[
        "used"
    ],
    "wof:name":"EZ Money",
    "wof:placetype":"venue"
},
  "geometry": {"coordinates":[-95.18119,29.691786],"type":"Point"}
}