{
  "type": "Feature",
  "properties": {
    "iso:country":"US",
    "sg:address":"13641 State Highway 249 Ste E",
    "sg:city":"Houston",
    "sg:classifiers":[
        {
            "category":"Personal",
            "subcategory":"Beauty Salon",
            "type":"Services"
        }
    ],
    "sg:phone":"+1 281 405 9638",
    "sg:postcode":"77086",
    "sg:province":"TX",
    "sg:tags":[
        "hair"
    ],
    "wof:name":"Vega's Beauty Salon",
    "wof:placetype":"venue"
},
  "geometry": {"coordinates":[-95.492507,29.918907],"type":"Point"}
}