{
  "type": "Feature",
  "properties": {
    "iso:country":"US",
    "sg:address":"411 S 14th St",
    "sg:city":"Gatesville",
    "sg:classifiers":[
        {
            "category":"Professional",
            "subcategory":"Computer Services",
            "type":"Services"
        }
    ],
    "sg:phone":"+1 254 865 7895",
    "sg:postcode":"76528",
    "sg:province":"TX",
    "sg:tags":[
        "repair"
    ],
    "wof:name":"Whizardies",
    "wof:placetype":"venue"
},
  "geometry": {"coordinates":[-97.74230799999999,31.432309],"type":"Point"}
}