{
  "type": "Feature",
  "properties": {
    "iso:country":"US",
    "sg:address":"644 W Mockingbird Ln",
    "sg:city":"Dallas",
    "sg:classifiers":[
        {
            "category":"Wholesale",
            "subcategory":"Machinery & Supplies",
            "type":"Manufacturing & Wholesale Goods"
        },
        {
            "category":"Manufacturing",
            "subcategory":"Metals",
            "type":"Manufacturing & Wholesale Goods"
        }
    ],
    "sg:phone":"+1 214 689 4673",
    "sg:postcode":"75247",
    "sg:province":"TX",
    "sg:tags":[
        "fitting",
        "hose",
        "coupling",
        "hydraulic",
        "tube"
    ],
    "wof:name":"G T Southwest Hose Inc",
    "wof:placetype":"venue"
},
  "geometry": {"coordinates":[-96.873597,32.811367],"type":"Point"}
}