{
  "type": "Feature",
  "properties": {
    "iso:country":"US",
    "sg:address":"119 Roadrunner Ln",
    "sg:city":"Buchanan Dam",
    "sg:classifiers":[
        {
            "category":"Wholesale",
            "subcategory":"Toys & Hobbies",
            "type":"Manufacturing & Wholesale Goods"
        }
    ],
    "sg:phone":"+1 512 793 6271",
    "sg:postcode":"78609",
    "sg:province":"TX",
    "sg:tags":[
        "wholesaler"
    ],
    "wof:name":"H & H Glove Co",
    "wof:placetype":"venue"
},
  "geometry": {"coordinates":[-98.387585,30.743158],"type":"Point"}
}