{
  "type": "Feature",
  "properties": {
    "iso:country":"US",
    "sg:address":"501 W Broadway St",
    "sg:city":"Winnsboro",
    "sg:classifiers":[
        {
            "category":"Wholesale",
            "subcategory":"Farm Supplies",
            "type":"Manufacturing & Wholesale Goods"
        }
    ],
    "sg:phone":"+1 903 885 6351",
    "sg:postcode":"75494",
    "sg:province":"TX",
    "sg:tags":[
        "feed"
    ],
    "wof:name":"W W Feeds",
    "wof:placetype":"venue"
},
  "geometry": {"coordinates":[-95.294466,32.958085],"type":"Point"}
}