{
  "type": "Feature",
  "properties": {
    "iso:country":"US",
    "sg:address":"4601 W Ennis Pkwy",
    "sg:city":"Ennis",
    "sg:classifiers":[
        {
            "category":"Professional",
            "type":"Services"
        }
    ],
    "sg:phone":"+1 972 878 0339",
    "sg:postcode":"75119",
    "sg:province":"TX",
    "wof:name":"Buyers Rep",
    "wof:placetype":"venue"
},
  "geometry": {"coordinates":[-96.686787,32.304498],"type":"Point"}
}