{
  "type": "Feature",
  "properties": {
    "iso:country":"US",
    "sg:address":"1717 Irving Blvd",
    "sg:city":"Dallas",
    "sg:classifiers":[
        {
            "category":"Wholesale",
            "subcategory":"Furniture",
            "type":"Manufacturing & Wholesale Goods"
        },
        {
            "category":"Manufacturing",
            "subcategory":"Furniture",
            "type":"Manufacturing & Wholesale Goods"
        },
        {
            "category":"Home & Garden",
            "subcategory":"Furniture",
            "type":"Retail Goods"
        }
    ],
    "sg:phone":"+1 214 757 9900",
    "sg:postcode":"75207",
    "sg:province":"TX",
    "sg:tags":[
        "equipment",
        "manufacturer",
        "store",
        "furniture-wholesale",
        "supply"
    ],
    "wof:name":"William Wesley CO",
    "wof:placetype":"venue"
},
  "geometry": {"coordinates":[-96.823767,32.792433],"type":"Point"}
}