{
  "type": "Feature",
  "properties": {
    "iso:country":"US",
    "sg:address":"414 Hohldale St",
    "sg:city":"Houston",
    "sg:classifiers":[
        {
            "category":"Professional",
            "type":"Services"
        }
    ],
    "sg:phone":"+1 713 697 3235",
    "sg:postcode":"77091",
    "sg:province":"TX",
    "sg:tags":[
        "establishment"
    ],
    "wof:name":"Michael Scott & Assoc",
    "wof:placetype":"venue"
},
  "geometry": {"coordinates":[-95.404961,29.841831],"type":"Point"}
}