{
  "type": "Feature",
  "properties": {
    "iso:country":"US",
    "sg:address":"2000 US Hwy 290 E",
    "sg:city":"Brenham",
    "sg:classifiers":[
        {
            "category":"Shopping",
            "type":"Retail Goods"
        }
    ],
    "sg:phone":"+1 979 836 0711",
    "sg:postcode":"77833",
    "sg:province":"TX",
    "sg:tags":[
        "merchandise"
    ],
    "wof:name":"Flag Store",
    "wof:placetype":"venue"
},
  "geometry": {"coordinates":[-96.36887299999999,30.142996],"type":"Point"}
}