{
  "type": "Feature",
  "properties": {
    "iso:country":"US",
    "sg:address":"2010 Harvest Run",
    "sg:city":"Garland",
    "sg:classifiers":[
        {
            "category":"Real Estate",
            "subcategory":"Real Estate Services",
            "type":"Services"
        },
        {
            "category":"Real Estate",
            "subcategory":"Real Estate Agent",
            "type":"Services"
        }
    ],
    "sg:phone":"+1 972 495 4888",
    "sg:postcode":"75040",
    "sg:province":"TX",
    "sg:tags":[
        "management"
    ],
    "wof:name":"Destin Management Real Estate",
    "wof:placetype":"venue"
},
  "geometry": {"coordinates":[-96.60574800000001,32.931609],"type":"Point"}
}