{
  "type": "Feature",
  "properties": {
    "iso:country":"US",
    "sg:address":"22090 White Oak Dr",
    "sg:city":"New Caney",
    "sg:classifiers":[
        {
            "category":"Retail",
            "subcategory":"Laundry & Dry Cleaning",
            "type":"Services"
        }
    ],
    "sg:phone":"+1 281 399 9407",
    "sg:postcode":"77357",
    "sg:province":"TX",
    "sg:tags":[
        "cleaners",
        "rug",
        "carpet"
    ],
    "wof:name":"Absolute Restoration Carpet",
    "wof:placetype":"venue"
},
  "geometry": {"coordinates":[-95.22747099999999,30.152088],"type":"Point"}
}