{
  "type": "Feature",
  "properties": {
    "iso:country":"US",
    "sg:address":"4310 Buffalo Gap Rd",
    "sg:city":"Abilene",
    "sg:classifiers":[
        {
            "category":"Shopping",
            "type":"Retail Goods"
        }
    ],
    "sg:phone":"+1 325 692 2466",
    "sg:postcode":"79606",
    "sg:province":"TX",
    "sg:tags":[
        "telephone",
        "cellular"
    ],
    "wof:name":"Digital Outfitters",
    "wof:placetype":"venue"
},
  "geometry": {"coordinates":[-99.759399,32.399097],"type":"Point"}
}