{
  "type": "Feature",
  "properties": {
    "iso:country":"US",
    "sg:address":"1712 Crown Pointe Blvd",
    "sg:city":"Mission",
    "sg:classifiers":[
        {
            "category":"Professional",
            "subcategory":"Business Services",
            "type":"Services"
        }
    ],
    "sg:phone":"+1 956 624 8679",
    "sg:postcode":"78572",
    "sg:province":"TX",
    "wof:name":"Claudias Interior Design",
    "wof:placetype":"venue"
},
  "geometry": {"coordinates":[-98.299131,26.219332],"type":"Point"}
}