{
  "type": "Feature",
  "properties": {
    "iso:country":"US",
    "sg:address":"9800 N Lamar Blvd Ste 280",
    "sg:city":"Austin",
    "sg:classifiers":[
        {
            "category":"Professional",
            "subcategory":"Accounting & Tax Preparation",
            "type":"Services"
        }
    ],
    "sg:phone":"+1 512 834 9624",
    "sg:postcode":"78753",
    "sg:province":"TX",
    "sg:tags":[
        "return",
        "preparation-business"
    ],
    "wof:name":"A Z Tax Service",
    "wof:placetype":"venue"
},
  "geometry": {"coordinates":[-97.694603,30.367399],"type":"Point"}
}