{
  "type": "Feature",
  "properties": {
    "iso:country":"US",
    "sg:address":"2626 McCullough Ave",
    "sg:city":"San Antonio",
    "sg:classifiers":[
        {
            "category":"Organizations",
            "subcategory":"Community Association",
            "type":"Services"
        }
    ],
    "sg:phone":"+1 210 732 4009",
    "sg:postcode":"78212",
    "sg:province":"TX",
    "sg:tags":[
        "environmental",
        "org"
    ],
    "wof:name":"Sur Tejas Corp",
    "wof:placetype":"venue"
},
  "geometry": {"coordinates":[-98.491731,29.454801],"type":"Point"}
}