{
  "type": "Feature",
  "properties": {
    "iso:country":"US",
    "sg:address":"1612 Waugh Dr",
    "sg:city":"Houston",
    "sg:classifiers":[
        {
            "category":"Recreation",
            "subcategory":"Dog Park",
            "type":"Entertainment"
        },
        {
            "category":"Shopping",
            "subcategory":"Pets & Pet Supplies",
            "type":"Retail Goods"
        },
        {
            "category":"Retail",
            "subcategory":"Animal Services",
            "type":"Services"
        }
    ],
    "sg:phone":"+1 832 217 7373",
    "sg:postcode":"77006",
    "sg:province":"TX",
    "sg:tags":[
        "exercising",
        "grooming",
        "training",
        "specialty",
        "sitting"
    ],
    "sg:website":"http://www.pawsandclawshouston.com/",
    "wof:name":"Paws and Claws",
    "wof:placetype":"venue"
},
  "geometry": {"coordinates":[-95.398033,29.753172],"type":"Point"}
}