{
  "type": "Feature",
  "properties": {
    "iso:country":"US",
    "sg:address":"2100 Irving Blvd",
    "sg:city":"Dallas",
    "sg:classifiers":[
        {
            "category":"Retail",
            "subcategory":"Repair Shop",
            "type":"Services"
        }
    ],
    "sg:phone":"+1 214 631 2255",
    "sg:postcode":"75207",
    "sg:province":"TX",
    "sg:tags":[
        "upholsterer"
    ],
    "sg:website":"www.aviamy.com",
    "wof:name":"Aviamy House Upholstery",
    "wof:placetype":"venue"
},
  "geometry": {"coordinates":[-96.83389699999999,32.795884],"type":"Point"}
}