{
  "type": "Feature",
  "properties": {
    "iso:country":"US",
    "sg:address":"821 Telephone Rd",
    "sg:city":"Houston",
    "sg:classifiers":[
        {
            "category":"Food & Beverages",
            "subcategory":"Liquor & Beverages",
            "type":"Retail Goods"
        }
    ],
    "sg:phone":"+1 713 921 6171",
    "sg:postcode":"77023",
    "sg:province":"TX",
    "sg:tags":[
        "beer",
        "spirit",
        "wine"
    ],
    "wof:name":"King Liquors No 2",
    "wof:placetype":"venue"
},
  "geometry": {"coordinates":[-95.328903,29.733801],"type":"Point"}
}