{
  "type": "Feature",
  "properties": {
    "iso:country":"US",
    "sg:address":"406 S College Dr",
    "sg:city":"Keene",
    "sg:classifiers":[
        {
            "category":"Professional",
            "subcategory":"Computer Services",
            "type":"Services"
        }
    ],
    "sg:phone":"+1 817 641 6128",
    "sg:postcode":"76059",
    "sg:province":"TX",
    "sg:tags":[
        "design",
        "integrated",
        "system"
    ],
    "wof:name":"Computer Trouble Shooters",
    "wof:placetype":"venue"
},
  "geometry": {"coordinates":[-97.326576,32.390849],"type":"Point"}
}