{
  "type": "Feature",
  "properties": {
    "iso:country":"US",
    "sg:address":"2408 Deer Horn Dr",
    "sg:city":"Plano",
    "sg:classifiers":[
        {
            "category":"Professional",
            "subcategory":"Business Services",
            "type":"Services"
        }
    ],
    "sg:phone":"+1 972 747 7901",
    "sg:postcode":"75025",
    "sg:province":"TX",
    "wof:name":"Services In Whitson Inspection",
    "wof:placetype":"venue"
},
  "geometry": {"coordinates":[-96.74004600000001,33.099422],"type":"Point"}
}