{
  "type": "Feature",
  "properties": {
    "iso:country":"US",
    "sg:address":"9241 Skillman St",
    "sg:city":"Dallas",
    "sg:classifiers":[
        {
            "category":"Restaurant",
            "type":"Food & Drink"
        }
    ],
    "sg:phone":"+1 214 343 0031",
    "sg:postcode":"75243",
    "sg:province":"TX",
    "sg:tags":[
        "eating"
    ],
    "wof:name":"Souper Salad 61",
    "wof:placetype":"venue"
},
  "geometry": {"coordinates":[-96.716505,32.90205],"type":"Point"}
}