{
  "type": "Feature",
  "properties": {
    "iso:country":"US",
    "sg:address":"2818 Peppermill Run St",
    "sg:city":"San Antonio",
    "sg:classifiers":[
        {
            "category":"Organizations",
            "subcategory":"Religious Organization",
            "type":"Services"
        }
    ],
    "sg:phone":"+1 210 764 8626",
    "sg:postcode":"78231",
    "sg:province":"TX",
    "sg:tags":[
        "monastery",
        "convent"
    ],
    "wof:name":"Community Chaminade",
    "wof:placetype":"venue"
},
  "geometry": {"coordinates":[-98.53506299999999,29.570963],"type":"Point"}
}