{
  "type": "Feature",
  "properties": {
    "iso:country":"US",
    "sg:address":"1504 2nd St",
    "sg:city":"Pleasanton",
    "sg:classifiers":[
        {
            "category":"Home & Garden",
            "subcategory":"Furniture",
            "type":"Retail Goods"
        }
    ],
    "sg:phone":"+1 830 569 3020",
    "sg:postcode":"78064",
    "sg:province":"TX",
    "wof:name":"American Furniture & Applncs",
    "wof:placetype":"venue"
},
  "geometry": {"coordinates":[-98.478819,28.973908],"type":"Point"}
}