{
  "type": "Feature",
  "properties": {
    "iso:country":"US",
    "sg:address":"17403 FM 529",
    "sg:city":"Houston",
    "sg:classifiers":[
        {
            "category":"Food & Beverages",
            "subcategory":"Groceries & Convenience Stores",
            "type":"Retail Goods"
        }
    ],
    "sg:phone":"+1 281 463 6295",
    "sg:postcode":"77095",
    "sg:province":"TX",
    "wof:name":"FM 529 Food Store",
    "wof:placetype":"venue"
},
  "geometry": {"coordinates":[-95.671053,29.878916],"type":"Point"}
}