{
  "type": "Feature",
  "properties": {
    "iso:country":"US",
    "sg:address":"203 Tapp St",
    "sg:city":"Pittsburg",
    "sg:classifiers":[
        {
            "category":"Government",
            "subcategory":"Police Station",
            "type":"Public Place"
        }
    ],
    "sg:phone":"+1 903 856 6651",
    "sg:postcode":"75686",
    "sg:province":"TX",
    "sg:tags":[
        "department",
        "protection"
    ],
    "wof:name":"Camp County Sheriff's Office",
    "wof:placetype":"venue"
},
  "geometry": {"coordinates":[-94.965671,32.996558],"type":"Point"}
}