{
  "type": "Feature",
  "properties": {
    "iso:country":"US",
    "sg:address":"523 Softwood Dr",
    "sg:city":"Duncanville",
    "sg:classifiers":[
        {
            "category":"Shopping",
            "subcategory":"Computers & Home Electronics",
            "type":"Retail Goods"
        }
    ],
    "sg:phone":"+1 972 298 8397",
    "sg:postcode":"75137",
    "sg:province":"TX",
    "sg:tags":[
        "related"
    ],
    "wof:name":"Wld Systems",
    "wof:placetype":"venue"
},
  "geometry": {"coordinates":[-96.921606,32.622922],"type":"Point"}
}