{
  "type": "Feature",
  "properties": {
    "iso:country":"US",
    "sg:address":"909 Dairy Ashford St",
    "sg:city":"Houston",
    "sg:classifiers":[
        {
            "category":"Real Estate",
            "subcategory":"Real Estate Operator",
            "type":"Services"
        }
    ],
    "sg:phone":"+1 281 496 1068",
    "sg:postcode":"77079",
    "sg:province":"TX",
    "sg:tags":[
        "building",
        "parks"
    ],
    "wof:name":"CCP Ashford Medical",
    "wof:placetype":"venue"
},
  "geometry": {"coordinates":[-95.606312,29.776321],"type":"Point"}
}