{
  "type": "Feature",
  "properties": {
    "iso:country":"US",
    "sg:address":"8515 S Hwy 35",
    "sg:city":"Liverpool",
    "sg:classifiers":[
        {
            "category":"Mining & Drilling",
            "type":"Manufacturing & Wholesale Goods"
        }
    ],
    "sg:phone":"+1 281 393 1451",
    "sg:postcode":"77577",
    "sg:province":"TX",
    "sg:tags":[
        "field",
        "oil"
    ],
    "wof:name":"Power Rig Rental Tool Co",
    "wof:placetype":"venue"
},
  "geometry": {"coordinates":[-95.296161,29.319325],"type":"Point"}
}