{
  "type": "Feature",
  "properties": {
    "iso:country":"US",
    "sg:address":"503 Hudgins St",
    "sg:city":"Smithville",
    "sg:classifiers":[
        {
            "category":"Manufacturing",
            "subcategory":"Metals",
            "type":"Manufacturing & Wholesale Goods"
        },
        {
            "category":"Manufacturing",
            "subcategory":"Jewelry",
            "type":"Manufacturing & Wholesale Goods"
        }
    ],
    "sg:phone":"+1 512 360 3026",
    "sg:postcode":"78957",
    "sg:province":"TX",
    "sg:tags":[
        "metals-precious",
        "jewelers-wholesale",
        "manufacturer"
    ],
    "wof:name":"Scattered Light Design",
    "wof:placetype":"venue"
},
  "geometry": {"coordinates":[-97.154707,30.008528],"type":"Point"}
}