{
  "type": "Feature",
  "properties": {
    "iso:country":"US",
    "sg:address":"110 W Louisiana Ave",
    "sg:city":"Midland",
    "sg:classifiers":[
        {
            "category":"Real Estate",
            "subcategory":"Real Estate Agent",
            "type":"Services"
        }
    ],
    "sg:phone":"+1 432 682 4424",
    "sg:postcode":"79701",
    "sg:province":"TX",
    "sg:tags":[
        "management"
    ],
    "wof:name":"Star Property Mgmt & Constr",
    "wof:placetype":"venue"
},
  "geometry": {"coordinates":[-102.075678,32.00383],"type":"Point"}
}