{
  "type": "Feature",
  "properties": {
    "iso:country":"US",
    "sg:address":"441 Walnut St",
    "sg:city":"Abilene",
    "sg:classifiers":[
        {
            "category":"Organizations",
            "subcategory":"Community Association",
            "type":"Services"
        }
    ],
    "sg:phone":"+1 325 677 1202",
    "sg:postcode":"79601",
    "sg:province":"TX",
    "wof:name":"Improved Order of Ted Men",
    "wof:placetype":"venue"
},
  "geometry": {"coordinates":[-99.73129299999999,32.45307],"type":"Point"}
}