{
  "type": "Feature",
  "properties": {
    "iso:country":"US",
    "sg:address":"3001 Dove Country Dr",
    "sg:city":"Stafford",
    "sg:classifiers":[
        {
            "category":"Building & Trades",
            "subcategory":"Construction",
            "type":"Services"
        }
    ],
    "sg:phone":"+1 832 665 1150",
    "sg:postcode":"77477",
    "sg:province":"TX",
    "sg:tags":[
        "system",
        "contractor",
        "air conditioning"
    ],
    "wof:name":"Alexander Air Ducts",
    "wof:placetype":"venue"
},
  "geometry": {"coordinates":[-95.562637,29.608259],"type":"Point"}
}