{
  "type": "Feature",
  "properties": {
    "iso:country":"US",
    "sg:address":"1506 Sunset Dr",
    "sg:city":"Marble Falls",
    "sg:classifiers":[
        {
            "category":"Building & Trades",
            "subcategory":"Cleaning & Sanitation",
            "type":"Services"
        }
    ],
    "sg:phone":"+1 830 693 9142",
    "sg:postcode":"78654",
    "sg:province":"TX",
    "sg:tags":[
        "janitor"
    ],
    "wof:name":"M R House Cleaning & Office",
    "wof:placetype":"venue"
},
  "geometry": {"coordinates":[-98.276882,30.59113],"type":"Point"}
}