{
  "type": "Feature",
  "properties": {
    "iso:country":"US",
    "sg:address":"310 N Columbia Dr",
    "sg:city":"West Columbia",
    "sg:classifiers":[
        {
            "category":"Professional",
            "subcategory":"Advertising",
            "type":"Services"
        }
    ],
    "sg:phone":"+1 979 345 6111",
    "sg:postcode":"77486",
    "sg:province":"TX",
    "sg:tags":[
        "outdoor"
    ],
    "wof:name":"Gulf Coast Signs",
    "wof:placetype":"venue"
},
  "geometry": {"coordinates":[-95.659381,29.149067],"type":"Point"}
}