{
  "type": "Feature",
  "properties": {
    "iso:country":"US",
    "sg:address":"3619 Wooded Creek Cir",
    "sg:city":"Arlington",
    "sg:classifiers":[
        {
            "category":"Banks & Credit Unions",
            "subcategory":"Financial Services",
            "type":"Services"
        }
    ],
    "sg:phone":"+1 817 794 0096",
    "sg:postcode":"76016",
    "sg:province":"TX",
    "sg:tags":[
        "investor"
    ],
    "wof:name":"Raw Genpair Inc",
    "wof:placetype":"venue"
},
  "geometry": {"coordinates":[-97.159021,32.691885],"type":"Point"}
}