{
  "type": "Feature",
  "properties": {
    "iso:country":"US",
    "sg:address":"610 3rd St",
    "sg:city":"Graham",
    "sg:classifiers":[
        {
            "category":"Restaurant",
            "type":"Food & Drink"
        }
    ],
    "sg:phone":"+1 940 549 7440",
    "sg:postcode":"76450",
    "sg:province":"TX",
    "wof:name":"Third Street Cafe",
    "wof:placetype":"venue"
},
  "geometry": {"coordinates":[-98.589415,33.105812],"type":"Point"}
}