{
  "type": "Feature",
  "properties": {
    "iso:country":"US",
    "sg:address":"1104 N Hwy 377",
    "sg:city":"Roanoke",
    "sg:classifiers":[
        {
            "category":"Food & Beverages",
            "subcategory":"Bakery",
            "type":"Retail Goods"
        }
    ],
    "sg:phone":"+1 817 961 0655",
    "sg:postcode":"76258",
    "sg:province":"TX",
    "sg:tags":[
        "product",
        "doughnut",
        "mfg"
    ],
    "wof:name":"Donut Paradise",
    "wof:placetype":"venue"
},
  "geometry": {"coordinates":[-96.93059100000001,33.433192],"type":"Point"}
}