{
  "type": "Feature",
  "properties": {
    "iso:country":"US",
    "sg:address":"3246 Bolton Gardens Dr",
    "sg:city":"Houston",
    "sg:classifiers":[
        {
            "category":"Building & Trades",
            "subcategory":"Cleaning & Sanitation",
            "type":"Services"
        }
    ],
    "sg:phone":"+1 281 880 9969",
    "sg:postcode":"77066",
    "sg:province":"TX",
    "sg:tags":[
        "maintenance"
    ],
    "wof:name":"Renards Maintenance Service",
    "wof:placetype":"venue"
},
  "geometry": {"coordinates":[-95.47237199999999,29.949494],"type":"Point"}
}