{
  "type": "Feature",
  "properties": {
    "iso:country":"US",
    "sg:address":"813 N Macarthur Blvd",
    "sg:city":"Irving",
    "sg:classifiers":[
        {
            "category":"Health Services",
            "subcategory":"Doctor",
            "type":"Services"
        }
    ],
    "sg:phone":"+1 972 253 0660",
    "sg:postcode":"75061",
    "sg:province":"TX",
    "sg:tags":[
        "dentist"
    ],
    "wof:name":"J R Gonzalez DDS",
    "wof:placetype":"venue"
},
  "geometry": {"coordinates":[-96.959022,32.822818],"type":"Point"}
}