{
  "type": "Feature",
  "properties": {
    "iso:country":"US",
    "sg:address":"2001 Sandalwood Ln",
    "sg:city":"Bryan",
    "sg:classifiers":[
        {
            "category":"Building & Trades",
            "subcategory":"Construction",
            "type":"Services"
        }
    ],
    "sg:phone":"+1 979 822 5329",
    "sg:postcode":"77807",
    "sg:province":"TX",
    "sg:tags":[
        "concrete",
        "contractor"
    ],
    "wof:name":"American Stone Works",
    "wof:placetype":"venue"
},
  "geometry": {"coordinates":[-96.37883600000001,30.629569],"type":"Point"}
}