{
  "type": "Feature",
  "properties": {
    "iso:country":"US",
    "sg:address":"4305 Roberts Ave",
    "sg:city":"Harlingen",
    "sg:classifiers":[
        {
            "category":"Building & Trades",
            "subcategory":"Construction",
            "type":"Services"
        }
    ],
    "sg:phone":"+1 956 423 6808",
    "sg:postcode":"78552",
    "sg:province":"TX",
    "sg:tags":[
        "house",
        "nonresidential"
    ],
    "wof:name":"Francisco Mata-Esquivel",
    "wof:placetype":"venue"
},
  "geometry": {"coordinates":[-97.742064,26.202038],"type":"Point"}
}