{
  "type": "Feature",
  "properties": {
    "iso:country":"US",
    "sg:address":"301 S 25 Mile Ave",
    "sg:city":"Hereford",
    "sg:classifiers":[
        {
            "category":"Wholesale",
            "subcategory":"Machinery & Supplies",
            "type":"Manufacturing & Wholesale Goods"
        }
    ],
    "sg:phone":"+1 806 364 6222",
    "sg:postcode":"79045",
    "sg:province":"TX",
    "sg:tags":[
        "equipment",
        "welding"
    ],
    "wof:name":"Hereford Welding Supply Inc",
    "wof:placetype":"venue"
},
  "geometry": {"coordinates":[-102.405751,34.813625],"type":"Point"}
}