{
  "type": "Feature",
  "properties": {
    "iso:country":"US",
    "sg:address":"3705 W Green Oaks Blvd",
    "sg:city":"Arlington",
    "sg:classifiers":[
        {
            "category":"Professional",
            "subcategory":"Lawyer & Legal Services",
            "type":"Services"
        }
    ],
    "sg:phone":"+1 817 457 9328",
    "sg:postcode":"76016",
    "sg:province":"TX",
    "sg:tags":[
        "living",
        "attorney",
        "estate",
        "planning",
        "trust",
        "probate"
    ],
    "wof:name":"Sweat, David R",
    "wof:placetype":"venue"
},
  "geometry": {"coordinates":[-97.19201,32.68865],"type":"Point"}
}