{
  "type": "Feature",
  "properties": {
    "iso:country":"US",
    "sg:address":"201 W Main St",
    "sg:city":"Arlington",
    "sg:classifiers":[
        {
            "category":"Museum",
            "type":"Entertainment"
        }
    ],
    "sg:phone":"+1 817 275 4600",
    "sg:postcode":"76010",
    "sg:province":"TX",
    "sg:tags":[
        "gallery"
    ],
    "wof:name":"Arlington Museum of Art Inc",
    "wof:placetype":"venue"
},
  "geometry": {"coordinates":[-97.10951799999999,32.736697],"type":"Point"}
}