{
  "type": "Feature",
  "properties": {
    "iso:country":"US",
    "sg:address":"210 S Bridge St",
    "sg:city":"Hidalgo",
    "sg:classifiers":[
        {
            "category":"Professional",
            "type":"Services"
        }
    ],
    "sg:phone":"+1 956 843 4722",
    "sg:postcode":"78557",
    "sg:province":"TX",
    "sg:tags":[
        "establishment"
    ],
    "wof:name":"Casa Cris",
    "wof:placetype":"venue"
},
  "geometry": {"coordinates":[-98.262333,26.104272],"type":"Point"}
}