{
  "type": "Feature",
  "properties": {
    "iso:country":"US",
    "sg:address":"5904 Bee Caves Rd",
    "sg:city":"Austin",
    "sg:classifiers":[
        {
            "category":"Insurance",
            "subcategory":"Insurance Agent",
            "type":"Services"
        }
    ],
    "sg:phone":"+1 512 327 2324",
    "sg:postcode":"78746",
    "sg:province":"TX",
    "wof:name":"Harold Davis & Associates",
    "wof:placetype":"venue"
},
  "geometry": {"coordinates":[-97.827099,30.29546],"type":"Point"}
}