{
  "type": "Feature",
  "properties": {
    "iso:country":"US",
    "sg:address":"814 Xavier Dr",
    "sg:city":"Arlington",
    "sg:classifiers":[
        {
            "category":"Building & Trades",
            "subcategory":"Plumbing",
            "type":"Services"
        }
    ],
    "sg:phone":"+1 817 557 1035",
    "sg:postcode":"76001",
    "sg:province":"TX",
    "sg:tags":[
        "conditioning",
        "air",
        "system",
        "contractor"
    ],
    "wof:name":"Accu-Air Air Conditioning",
    "wof:placetype":"venue"
},
  "geometry": {"coordinates":[-97.11832099999999,32.639469],"type":"Point"}
}