{
  "type": "Feature",
  "properties": {
    "iso:country":"US",
    "sg:address":"2501 Scripture St",
    "sg:city":"Denton",
    "sg:classifiers":[
        {
            "category":"Professional",
            "type":"Services"
        }
    ],
    "sg:phone":"+1 940 898 0944",
    "sg:postcode":"76201",
    "sg:province":"TX",
    "sg:tags":[
        "establishment"
    ],
    "wof:name":"Labcorp",
    "wof:placetype":"venue"
},
  "geometry": {"coordinates":[-97.163905,33.21896],"type":"Point"}
}