{
  "type": "Feature",
  "properties": {
    "iso:country":"US",
    "sg:address":"5909 Gaston Ave",
    "sg:city":"Dallas",
    "sg:classifiers":[
        {
            "category":"Real Estate",
            "subcategory":"Real Estate Operator",
            "type":"Services"
        }
    ],
    "sg:phone":"+1 214 824 3634",
    "sg:postcode":"75214",
    "sg:province":"TX",
    "sg:tags":[
        "apartment"
    ],
    "wof:name":"Bora Bora Apartments",
    "wof:placetype":"venue"
},
  "geometry": {"coordinates":[-96.75735,32.810149],"type":"Point"}
}