{
  "type": "Feature",
  "properties": {
    "iso:country":"US",
    "sg:address":"2106 109th St",
    "sg:city":"Lubbock",
    "sg:classifiers":[
        {
            "category":"Manufacturing",
            "subcategory":"Wood Products",
            "type":"Manufacturing & Wholesale Goods"
        }
    ],
    "sg:phone":"+1 806 745 2272",
    "sg:postcode":"79423",
    "sg:province":"TX",
    "wof:name":"Bob's Woodworks",
    "wof:placetype":"venue"
},
  "geometry": {"coordinates":[-101.861767,33.495335],"type":"Point"}
}