{
  "type": "Feature",
  "properties": {
    "iso:country":"US",
    "sg:address":"336 4th St",
    "sg:city":"Graham",
    "sg:classifiers":[
        {
            "category":"Shopping",
            "subcategory":"Used Merchandise",
            "type":"Retail Goods"
        }
    ],
    "sg:phone":"+1 940 549 0012",
    "sg:postcode":"76450",
    "sg:province":"TX",
    "sg:tags":[
        "antique"
    ],
    "wof:name":"Chantilly",
    "wof:placetype":"venue"
},
  "geometry": {"coordinates":[-98.594112,33.106988],"type":"Point"}
}