{
  "type": "Feature",
  "properties": {
    "iso:country":"US",
    "sg:address":"4416 Forest Bend Rd",
    "sg:city":"Dallas",
    "sg:classifiers":[
        {
            "category":"Professional",
            "subcategory":"Business Services",
            "type":"Services"
        }
    ],
    "sg:phone":"+1 972 490 4640",
    "sg:postcode":"75244",
    "sg:province":"TX",
    "wof:name":"Aleman Family Group LLC",
    "wof:placetype":"venue"
},
  "geometry": {"coordinates":[-96.82950099999999,32.923216],"type":"Point"}
}