{
  "type": "Feature",
  "properties": {
    "iso:country":"US",
    "sg:address":"1430 Arthur Rd",
    "sg:city":"Denison",
    "sg:classifiers":[
        {
            "category":"Building & Trades",
            "subcategory":"Construction",
            "type":"Services"
        }
    ],
    "sg:phone":"+1 903 465 6614",
    "sg:postcode":"75021",
    "sg:province":"TX",
    "sg:tags":[
        "contractor"
    ],
    "wof:name":"Webb Steel Homes",
    "wof:placetype":"venue"
},
  "geometry": {"coordinates":[-96.514433,33.712236],"type":"Point"}
}