{
  "type": "Feature",
  "properties": {
    "iso:country":"US",
    "sg:address":"13400 Perthshire St",
    "sg:city":"Austin",
    "sg:classifiers":[
        {
            "category":"Communications",
            "subcategory":"Film & Video Production",
            "type":"Services"
        }
    ],
    "sg:phone":"+1 512 249 0247",
    "sg:postcode":"78729",
    "sg:province":"TX",
    "sg:tags":[
        "motion"
    ],
    "wof:name":"Lip Slide Prdctons Incorported",
    "wof:placetype":"venue"
},
  "geometry": {"coordinates":[-97.779731,30.468718],"type":"Point"}
}