{
  "type": "Feature",
  "properties": {
    "iso:country":"US",
    "sg:address":"8614 Cullen Blvd",
    "sg:city":"Houston",
    "sg:classifiers":[
        {
            "category":"Autos & Motor Vehicles",
            "subcategory":"Automobile Sales",
            "type":"Retail Goods"
        }
    ],
    "sg:phone":"+1 713 734 3737",
    "sg:postcode":"77051",
    "sg:province":"TX",
    "sg:tags":[
        "car",
        "dealer"
    ],
    "wof:name":"Adventure Auto",
    "wof:placetype":"venue"
},
  "geometry": {"coordinates":[-95.35569099999999,29.667479],"type":"Point"}
}