{
  "type": "Feature",
  "properties": {
    "iso:country":"US",
    "sg:address":"2810 Schwald Rd",
    "sg:city":"Killeen",
    "sg:classifiers":[
        {
            "category":"Professional",
            "subcategory":"Art Services",
            "type":"Services"
        }
    ],
    "sg:phone":"+1 254 554 3754",
    "sg:postcode":"76543",
    "sg:province":"TX",
    "sg:tags":[
        "graphic",
        "commercial",
        "designer",
        "artist"
    ],
    "wof:name":"Rosalyn's Divine Images",
    "wof:placetype":"venue"
},
  "geometry": {"coordinates":[-97.690662,31.138344],"type":"Point"}
}