{
  "type": "Feature",
  "properties": {
    "iso:country":"US",
    "sg:address":"2722 Galveston Rd",
    "sg:city":"Houston",
    "sg:classifiers":[
        {
            "category":"Retail",
            "subcategory":"Auto Repair",
            "type":"Services"
        }
    ],
    "sg:phone":"+1 713 488 3100",
    "sg:postcode":"77017",
    "sg:province":"TX",
    "sg:tags":[
        "body"
    ],
    "wof:name":"Auto Center of Clear Lake",
    "wof:placetype":"venue"
},
  "geometry": {"coordinates":[-95.27060400000001,29.701459],"type":"Point"}
}