{
  "type": "Feature",
  "properties": {
    "iso:country":"US",
    "sg:address":"13515 N Stemmons Fwy",
    "sg:city":"Dallas",
    "sg:classifiers":[
        {
            "category":"Wholesale",
            "subcategory":"Medical Equipment & Supplies",
            "type":"Manufacturing & Wholesale Goods"
        },
        {
            "category":"Shopping",
            "subcategory":"Optical Goods",
            "type":"Retail Goods"
        }
    ],
    "sg:phone":"+1 972 241 4141",
    "sg:postcode":"75234",
    "sg:province":"TX",
    "sg:tags":[
        "eyeglass",
        "optometrists'"
    ],
    "sg:website":"http://www.crizal.com",
    "wof:name":"Duffens Optical",
    "wof:placetype":"venue"
},
  "geometry": {"coordinates":[-96.90150800000001,32.927548],"type":"Point"}
}