{
  "type": "Feature",
  "properties": {
    "iso:country":"US",
    "sg:address":"5222 Springlake Dr",
    "sg:city":"Garland",
    "sg:classifiers":[
        {
            "category":"Building & Trades",
            "subcategory":"Plumbing",
            "type":"Services"
        }
    ],
    "sg:phone":"+1 972 279 5188",
    "sg:postcode":"75043",
    "sg:province":"TX",
    "sg:tags":[
        "contractor"
    ],
    "wof:name":"Southwest Plumbing Co",
    "wof:placetype":"venue"
},
  "geometry": {"coordinates":[-96.63453,32.853037],"type":"Point"}
}