{
  "type": "Feature",
  "properties": {
    "iso:country":"US",
    "sg:address":"2502 Shaver St",
    "sg:city":"Pasadena",
    "sg:classifiers":[
        {
            "category":"Professional",
            "subcategory":"Advertising",
            "type":"Services"
        }
    ],
    "sg:phone":"+1 713 947 8144",
    "sg:postcode":"77502",
    "sg:province":"TX",
    "sg:tags":[
        "billboard",
        "leasing"
    ],
    "wof:name":"Mr Sign",
    "wof:placetype":"venue"
},
  "geometry": {"coordinates":[-95.208083,29.67419],"type":"Point"}
}