{
  "type": "Feature",
  "properties": {
    "iso:country":"US",
    "sg:address":"6112 Andrews Hwy",
    "sg:city":"Odessa",
    "sg:classifiers":[
        {
            "category":"Professional",
            "type":"Services"
        }
    ],
    "sg:phone":"+1 432 445 7801",
    "sg:postcode":"79762",
    "sg:province":"TX",
    "wof:name":"Yesterday Today & Tomorrow",
    "wof:placetype":"venue"
},
  "geometry": {"coordinates":[-102.391578,31.903288],"type":"Point"}
}