{
  "type": "Feature",
  "properties": {
    "iso:country":"US",
    "sg:address":"5105 Deerwood Park Dr",
    "sg:city":"Arlington",
    "sg:classifiers":[
        {
            "category":"Travel",
            "subcategory":"Travel Agent",
            "type":"Entertainment"
        }
    ],
    "sg:phone":"+1 817 465 1451",
    "sg:postcode":"76017",
    "sg:province":"TX",
    "sg:tags":[
        "agency"
    ],
    "wof:name":"Funtime Vacations",
    "wof:placetype":"venue"
},
  "geometry": {"coordinates":[-97.149028,32.664945],"type":"Point"}
}