{
  "type": "Feature",
  "properties": {
    "iso:country":"US",
    "sg:address":"2020 N Saint Marys St",
    "sg:city":"Beeville",
    "sg:classifiers":[
        {
            "category":"Restaurant",
            "type":"Food & Drink"
        }
    ],
    "sg:phone":"+1 361 354 5803",
    "sg:postcode":"78102",
    "sg:province":"TX",
    "sg:tags":[
        "mexican"
    ],
    "wof:name":"Taqueria Jalisco",
    "wof:placetype":"venue"
},
  "geometry": {"coordinates":[-97.75618299999999,28.419361],"type":"Point"}
}