{
  "type": "Feature",
  "properties": {
    "iso:country":"US",
    "sg:address":"309 Calhoun St",
    "sg:city":"Rockdale",
    "sg:classifiers":[
        {
            "category":"Professional",
            "type":"Services"
        }
    ],
    "sg:phone":"+1 512 446 2034",
    "sg:postcode":"76567",
    "sg:province":"TX",
    "sg:tags":[
        "establishment"
    ],
    "wof:name":"Brown Betz",
    "wof:placetype":"venue"
},
  "geometry": {"coordinates":[-97.027237,30.647053],"type":"Point"}
}