{
  "type": "Feature",
  "properties": {
    "iso:country":"US",
    "sg:address":"9950 Buxton St",
    "sg:city":"Houston",
    "sg:classifiers":[
        {
            "category":"Home & Garden",
            "subcategory":"Household Appliances",
            "type":"Retail Goods"
        },
        {
            "category":"Building & Trades",
            "subcategory":"Construction",
            "type":"Services"
        }
    ],
    "sg:phone":"+1 713 475 1471",
    "sg:postcode":"77017",
    "sg:province":"TX",
    "sg:tags":[
        "repair",
        "dishwashing",
        "system",
        "specialty",
        "machine",
        "heating",
        "contractor",
        "air conditioning"
    ],
    "wof:name":"Weather Venders Air Conditioning & Heating",
    "wof:placetype":"venue"
},
  "geometry": {"coordinates":[-95.245333,29.704296],"type":"Point"}
}