{
  "type": "Feature",
  "properties": {
    "iso:country":"US",
    "sg:address":"1400 Stagecoach Ranch Rd",
    "sg:city":"Dripping Springs",
    "sg:classifiers":[
        {
            "category":"Autos & Motor Vehicles",
            "subcategory":"Automobile Sales",
            "type":"Retail Goods"
        }
    ],
    "sg:phone":"+1 512 264 8347",
    "sg:postcode":"78620",
    "sg:province":"TX",
    "wof:name":"Corkys Honda Shop",
    "wof:placetype":"venue"
},
  "geometry": {"coordinates":[-98.133123,30.330032],"type":"Point"}
}