{
  "type": "Feature",
  "properties": {
    "iso:country":"US",
    "sg:address":"1828 W Winnipeg Ave",
    "sg:city":"San Antonio",
    "sg:classifiers":[
        {
            "category":"Professional",
            "type":"Services"
        }
    ],
    "sg:phone":"+1 210 924 1364",
    "sg:postcode":"78225",
    "sg:province":"TX",
    "wof:name":"Littlethings & Stuff",
    "wof:placetype":"venue"
},
  "geometry": {"coordinates":[-98.53738300000001,29.386576],"type":"Point"}
}