{
  "type": "Feature",
  "properties": {
    "iso:country":"US",
    "sg:address":"8951 Ruthby St",
    "sg:city":"Houston",
    "sg:classifiers":[
        {
            "category":"Social Services",
            "subcategory":"Job Training",
            "type":"Services"
        }
    ],
    "sg:phone":"+1 713 645 3536",
    "sg:postcode":"77061",
    "sg:province":"TX",
    "wof:name":"Southeast Rehabilitation Svc",
    "wof:placetype":"venue"
},
  "geometry": {"coordinates":[-95.269564,29.65928],"type":"Point"}
}