{
  "type": "Feature",
  "properties": {
    "iso:country":"US",
    "sg:address":"535 5th St",
    "sg:city":"Tuscola",
    "sg:classifiers":[
        {
            "category":"Health Services",
            "subcategory":"Doctor",
            "type":"Services"
        }
    ],
    "sg:phone":"+1 325 554 9377",
    "sg:postcode":"79562",
    "sg:province":"TX",
    "sg:tags":[
        "clinic"
    ],
    "wof:name":"Tuscola Medical Clinic",
    "wof:placetype":"venue"
},
  "geometry": {"coordinates":[-99.79730600000001,32.20848],"type":"Point"}
}