{
  "type": "Feature",
  "properties": {
    "iso:country":"US",
    "sg:address":"2469 Loop 337",
    "sg:city":"New Braunfels",
    "sg:classifiers":[
        {
            "category":"Retail",
            "subcategory":"Veterinary Services",
            "type":"Services"
        }
    ],
    "sg:phone":"+1 830 620 1100",
    "sg:postcode":"78130",
    "sg:province":"TX",
    "wof:name":"Countryside Veterinary Clinic",
    "wof:placetype":"venue"
},
  "geometry": {"coordinates":[-98.119288,29.729644],"type":"Point"}
}