{
  "type": "Feature",
  "properties": {
    "iso:country":"US",
    "sg:address":"2012 Bissonnet St",
    "sg:city":"Houston",
    "sg:classifiers":[
        {
            "category":"Health Services",
            "subcategory":"Clinic",
            "type":"Services"
        }
    ],
    "sg:phone":"+1 713 529 4588",
    "sg:postcode":"77005",
    "sg:province":"TX",
    "sg:tags":[
        "counseling",
        "mental"
    ],
    "wof:name":"Institute For Family Psychology",
    "wof:placetype":"venue"
},
  "geometry": {"coordinates":[-95.407402,29.7257],"type":"Point"}
}