{
  "type": "Feature",
  "properties": {
    "iso:country":"US",
    "sg:address":"6921 Charbonneau Rd",
    "sg:city":"Fort Worth",
    "sg:classifiers":[
        {
            "category":"Professional",
            "subcategory":"Management & Consulting",
            "type":"Services"
        }
    ],
    "sg:phone":"+1 817 237 9788",
    "sg:postcode":"76135",
    "sg:province":"TX",
    "sg:tags":[
        "business"
    ],
    "wof:name":"Cowboy Consultants Inc",
    "wof:placetype":"venue"
},
  "geometry": {"coordinates":[-97.438078,32.810196],"type":"Point"}
}