{
  "type": "Feature",
  "properties": {
    "iso:country":"US",
    "sg:address":"529 Cooper Ln",
    "sg:city":"Joshua",
    "sg:classifiers":[
        {
            "category":"Building & Trades",
            "subcategory":"Electrical",
            "type":"Services"
        }
    ],
    "sg:phone":"+1 817 774 3000",
    "sg:postcode":"76058",
    "sg:province":"TX",
    "sg:tags":[
        "electrical",
        "contractor"
    ],
    "wof:name":"Metro-Tex Electric",
    "wof:placetype":"venue"
},
  "geometry": {"coordinates":[-97.382119,32.453739],"type":"Point"}
}