{
  "type": "Feature",
  "properties": {
    "iso:country":"US",
    "sg:address":"8406 Leafdale Dr",
    "sg:city":"Humble",
    "sg:classifiers":[
        {
            "category":"Professional",
            "subcategory":"Business Services",
            "type":"Services"
        }
    ],
    "sg:phone":"+1 281 548 2813",
    "sg:postcode":"77338",
    "sg:province":"TX",
    "wof:name":"F S C Drafting Services",
    "wof:placetype":"venue"
},
  "geometry": {"coordinates":[-95.29665300000001,30.020393],"type":"Point"}
}