{
  "type": "Feature",
  "properties": {
    "iso:country":"US",
    "sg:address":"2703 Marshall St",
    "sg:city":"Fort Worth",
    "sg:classifiers":[
        {
            "category":"Retail",
            "subcategory":"Repair Shop",
            "type":"Services"
        }
    ],
    "sg:phone":"+1 817 834 6312",
    "sg:postcode":"76111",
    "sg:province":"TX",
    "sg:tags":[
        "related"
    ],
    "wof:name":"Longhorn Bevco & Supply",
    "wof:placetype":"venue"
},
  "geometry": {"coordinates":[-97.306777,32.77127],"type":"Point"}
}