{
  "type": "Feature",
  "properties": {
    "iso:country":"US",
    "sg:address":"121 E Edgewater Ter",
    "sg:city":"New Braunfels",
    "sg:classifiers":[
        {
            "category":"Building & Trades",
            "subcategory":"Landscaping Services",
            "type":"Services"
        }
    ],
    "sg:phone":"+1 830 625 1663",
    "sg:postcode":"78130",
    "sg:province":"TX",
    "sg:tags":[
        "landscape"
    ],
    "wof:name":"Horizon Landscaping",
    "wof:placetype":"venue"
},
  "geometry": {"coordinates":[-98.127668,29.720008],"type":"Point"}
}