{
  "type": "Feature",
  "properties": {
    "iso:country":"US",
    "sg:address":"2313 Hermosa Hills Ct",
    "sg:city":"Granbury",
    "sg:classifiers":[
        {
            "category":"Professional",
            "type":"Services"
        }
    ],
    "sg:phone":"+1 817 579 1990",
    "sg:postcode":"76048",
    "sg:province":"TX",
    "wof:name":"First & Lasting",
    "wof:placetype":"venue"
},
  "geometry": {"coordinates":[-97.73280699999999,32.365311],"type":"Point"}
}