{
  "type": "Feature",
  "properties": {
    "iso:country":"US",
    "sg:address":"1007 W Houston St",
    "sg:city":"Linden",
    "sg:classifiers":[
        {
            "category":"Food & Beverages",
            "subcategory":"Groceries & Convenience Stores",
            "type":"Retail Goods"
        }
    ],
    "sg:phone":"+1 903 756 5251",
    "sg:postcode":"75563",
    "sg:province":"TX",
    "sg:tags":[
        "grocer"
    ],
    "wof:name":"Berry's K-Zes",
    "wof:placetype":"venue"
},
  "geometry": {"coordinates":[-94.37617,33.011319],"type":"Point"}
}