{
  "type": "Feature",
  "properties": {
    "iso:country":"US",
    "sg:address":"1438 Crescent Dr",
    "sg:city":"Carrollton",
    "sg:classifiers":[
        {
            "category":"Building & Trades",
            "subcategory":"Construction",
            "type":"Services"
        }
    ],
    "sg:phone":"+1 972 242 8062",
    "sg:postcode":"75006",
    "sg:province":"TX",
    "sg:tags":[
        "good",
        "contractor"
    ],
    "wof:name":"Southwest Enclosures Systems",
    "wof:placetype":"venue"
},
  "geometry": {"coordinates":[-96.91740299999999,32.954655],"type":"Point"}
}