{
  "type": "Feature",
  "properties": {
    "iso:country":"US",
    "sg:address":"2800 Owen St",
    "sg:city":"Alvin",
    "sg:classifiers":[
        {
            "category":"Farming",
            "subcategory":"Livestock Farm",
            "type":"Manufacturing & Wholesale Goods"
        }
    ],
    "sg:phone":"+1 281 585 4665",
    "sg:postcode":"77511",
    "sg:province":"TX",
    "sg:tags":[
        "beef",
        "feedlot",
        "cattle"
    ],
    "wof:name":"Michael Wollam",
    "wof:placetype":"venue"
},
  "geometry": {"coordinates":[-95.275048,29.410541],"type":"Point"}
}