{
  "type": "Feature",
  "properties": {
    "iso:country":"US",
    "sg:address":"2521 Mollimar Dr",
    "sg:city":"Plano",
    "sg:classifiers":[
        {
            "category":"Food & Beverages",
            "subcategory":"Specialty",
            "type":"Retail Goods"
        }
    ],
    "sg:phone":"+1 972 596 0547",
    "sg:postcode":"75075",
    "sg:province":"TX",
    "sg:tags":[
        "juice",
        "health",
        "store",
        "bar"
    ],
    "wof:name":"Real Foods",
    "wof:placetype":"venue"
},
  "geometry": {"coordinates":[-96.741634,33.022576],"type":"Point"}
}