{
  "type": "Feature",
  "properties": {
    "iso:country":"US",
    "sg:address":"116 Historic Town Sq",
    "sg:city":"Lancaster",
    "sg:classifiers":[
        {
            "category":"Wholesale",
            "subcategory":"Computers",
            "type":"Manufacturing & Wholesale Goods"
        },
        {
            "category":"Professional",
            "subcategory":"Computer Services",
            "type":"Services"
        }
    ],
    "sg:phone":"+1 469 916 6624",
    "sg:postcode":"75146",
    "sg:province":"TX",
    "sg:tags":[
        "repair",
        "technical",
        "assistance",
        "equipment",
        "equipment-service",
        "support"
    ],
    "sg:website":"http://www.glts.com",
    "wof:name":"Glts, Inc",
    "wof:placetype":"venue"
},
  "geometry": {"coordinates":[-96.75601399999999,32.592083],"type":"Point"}
}