{
  "type": "Feature",
  "properties": {
    "iso:country":"US",
    "sg:address":"9265 Meadowglen Dr",
    "sg:city":"Dallas",
    "sg:classifiers":[
        {
            "category":"Mining & Drilling",
            "type":"Manufacturing & Wholesale Goods"
        }
    ],
    "sg:phone":"+1 214 348 3947",
    "sg:postcode":"75238",
    "sg:province":"TX",
    "sg:tags":[
        "exploration"
    ],
    "wof:name":"Harvest Consolidated Inc",
    "wof:placetype":"venue"
},
  "geometry": {"coordinates":[-96.724985,32.870662],"type":"Point"}
}