{
  "type": "Feature",
  "properties": {
    "iso:country":"US",
    "sg:address":"7206 Tokalon Dr",
    "sg:city":"Dallas",
    "sg:classifiers":[
        {
            "category":"Manufacturing",
            "subcategory":"Paper Products",
            "type":"Manufacturing & Wholesale Goods"
        },
        {
            "category":"Manufacturing",
            "subcategory":"Printing",
            "type":"Manufacturing & Wholesale Goods"
        }
    ],
    "sg:phone":"+1 214 939 1626",
    "sg:postcode":"75214",
    "sg:province":"TX",
    "sg:tags":[
        "stationery",
        "mfg",
        "book",
        "bo",
        "fiber"
    ],
    "wof:name":"Two Women Boxing Inc",
    "wof:placetype":"venue"
},
  "geometry": {"coordinates":[-96.731754,32.823509],"type":"Point"}
}