{
  "type": "Feature",
  "properties": {
    "iso:country":"US",
    "sg:address":"1911 Dove Ridge Trl",
    "sg:city":"Leander",
    "sg:classifiers":[
        {
            "category":"Professional",
            "subcategory":"Management & Consulting",
            "type":"Services"
        }
    ],
    "sg:phone":"+1 512 260 3519",
    "sg:postcode":"78641",
    "sg:province":"TX",
    "sg:tags":[
        "business"
    ],
    "wof:name":"Ruth A Mora Distributor",
    "wof:placetype":"venue"
},
  "geometry": {"coordinates":[-97.860159,30.546939],"type":"Point"}
}