{
  "type": "Feature",
  "properties": {
    "iso:country":"US",
    "sg:address":"109 Hill Top Cir",
    "sg:city":"Burleson",
    "sg:phone":"+1 817 295 2349",
    "sg:postcode":"76028",
    "sg:province":"TX",
    "sg:tags":[
        "product",
        "good",
        "petroleum",
        "mfg"
    ],
    "wof:name":"Hartman Enterprises",
    "wof:placetype":"venue"
},
  "geometry": {"coordinates":[-97.269683,32.551612],"type":"Point"}
}