{
  "type": "Feature",
  "properties": {
    "iso:country":"US",
    "sg:address":"912 W 8th St",
    "sg:city":"Dallas",
    "sg:classifiers":[
        {
            "category":"Restaurant",
            "type":"Food & Drink"
        }
    ],
    "sg:phone":"+1 214 941 2853",
    "sg:postcode":"75208",
    "sg:province":"TX",
    "sg:tags":[
        "eating"
    ],
    "wof:name":"4th Man Catering",
    "wof:placetype":"venue"
},
  "geometry": {"coordinates":[-96.839236,32.748009],"type":"Point"}
}