{
  "type": "Feature",
  "properties": {
    "iso:country":"US",
    "sg:address":"1531 W 18th St",
    "sg:city":"Houston",
    "sg:classifiers":[
        {
            "category":"Retail",
            "subcategory":"Laundry & Dry Cleaning",
            "type":"Services"
        }
    ],
    "sg:phone":"+1 713 861 5275",
    "sg:postcode":"77008",
    "sg:province":"TX",
    "wof:name":"Tip Top Cleaners",
    "wof:placetype":"venue"
},
  "geometry": {"coordinates":[-95.428299,29.8015],"type":"Point"}
}