{
  "type": "Feature",
  "properties": {
    "iso:country":"US",
    "sg:address":"700 W Hall Acres Rd",
    "sg:city":"Pharr",
    "sg:classifiers":[
        {
            "category":"Sports & Exercise",
            "subcategory":"Golf",
            "type":"Entertainment"
        }
    ],
    "sg:phone":"+1 956 702 2320",
    "sg:postcode":"78577",
    "sg:province":"TX",
    "sg:tags":[
        "course",
        "eating",
        "public"
    ],
    "wof:name":"Tierra Del Sol Golf Course",
    "wof:placetype":"venue"
},
  "geometry": {"coordinates":[-98.19595200000001,26.167381],"type":"Point"}
}