{
  "type": "Feature",
  "properties": {
    "iso:country":"US",
    "sg:address":"565 Whitfill Rd",
    "sg:city":"Ennis",
    "sg:classifiers":[
        {
            "category":"Restaurant",
            "type":"Food & Drink"
        }
    ],
    "sg:phone":"+1 972 351 1831",
    "sg:postcode":"75119",
    "sg:province":"TX",
    "sg:tags":[
        "house",
        "steak",
        "barbecue"
    ],
    "wof:name":"Alma Smokehouse Bbq",
    "wof:placetype":"venue"
},
  "geometry": {"coordinates":[-96.511579,32.283924],"type":"Point"}
}