{
  "type": "Feature",
  "properties": {
    "iso:country":"US",
    "sg:address":"213 Red River Dr",
    "sg:city":"Whitesboro",
    "sg:classifiers":[
        {
            "category":"Building & Trades",
            "subcategory":"Electrical",
            "type":"Services"
        }
    ],
    "sg:phone":"+1 903 815 5448",
    "sg:postcode":"76273",
    "sg:province":"TX",
    "sg:tags":[
        "electrician"
    ],
    "wof:name":"Best Electric",
    "wof:placetype":"venue"
},
  "geometry": {"coordinates":[-96.91024,33.667127],"type":"Point"}
}