{
  "type": "Feature",
  "properties": {
    "iso:country":"US",
    "sg:address":"714 W Jessamine St",
    "sg:city":"Fort Worth",
    "sg:classifiers":[
        {
            "category":"Bars & Pubs",
            "type":"Food & Drink"
        }
    ],
    "sg:phone":"+1 817 921 6341",
    "sg:postcode":"76110",
    "sg:province":"TX",
    "sg:tags":[
        "drinking"
    ],
    "wof:name":"Brenda's Place",
    "wof:placetype":"venue"
},
  "geometry": {"coordinates":[-97.332454,32.718256],"type":"Point"}
}