{
  "type": "Feature",
  "properties": {
    "iso:country":"US",
    "sg:address":"3415 Convent Ave",
    "sg:city":"Laredo",
    "sg:classifiers":[
        {
            "category":"Retail",
            "subcategory":"Auto Repair",
            "type":"Services"
        }
    ],
    "sg:phone":"+1 956 712 9674",
    "sg:postcode":"78040",
    "sg:province":"TX",
    "sg:tags":[
        "repairing",
        "automobile"
    ],
    "wof:name":"Sandy's Auto Repair",
    "wof:placetype":"venue"
},
  "geometry": {"coordinates":[-99.507143,27.530815],"type":"Point"}
}