{
  "type": "Feature",
  "properties": {
    "iso:country":"US",
    "sg:address":"2601 del Rio Dr",
    "sg:city":"Austin",
    "sg:classifiers":[
        {
            "category":"Shopping",
            "subcategory":"Bicycles & Sporting Goods",
            "type":"Retail Goods"
        }
    ],
    "sg:phone":"+1 512 327 4587",
    "sg:postcode":"78733",
    "sg:province":"TX",
    "wof:name":"Southern Star Skateboards",
    "wof:placetype":"venue"
},
  "geometry": {"coordinates":[-97.86259,30.350654],"type":"Point"}
}