{
  "type": "Feature",
  "properties": {
    "iso:country":"US",
    "sg:address":"3201 Robertson Rd",
    "sg:city":"Tyler",
    "sg:classifiers":[
        {
            "category":"Building & Trades",
            "subcategory":"Construction",
            "type":"Services"
        }
    ],
    "sg:phone":"+1 903 535 7921",
    "sg:postcode":"75701",
    "sg:province":"TX",
    "sg:tags":[
        "general",
        "contractor"
    ],
    "wof:name":"RPR Construction",
    "wof:placetype":"venue"
},
  "geometry": {"coordinates":[-95.334192,32.333062],"type":"Point"}
}