{
  "type": "Feature",
  "properties": {
    "iso:country":"US",
    "sg:address":"1109 Co Rd 701",
    "sg:city":"Cleburne",
    "sg:classifiers":[
        {
            "category":"Shopping",
            "subcategory":"Computers & Home Electronics",
            "type":"Retail Goods"
        }
    ],
    "sg:phone":"+1 817 845 1031",
    "sg:postcode":"76031",
    "sg:province":"TX",
    "wof:name":"M G T S Electronics",
    "wof:placetype":"venue"
},
  "geometry": {"coordinates":[-97.351752,32.398157],"type":"Point"}
}