{
  "type": "Feature",
  "properties": {
    "iso:country":"US",
    "sg:address":"320 S 8th St",
    "sg:city":"Skidmore",
    "sg:classifiers":[
        {
            "category":"Autos & Motor Vehicles",
            "subcategory":"Fuel & Gas Station",
            "type":"Retail Goods"
        }
    ],
    "sg:phone":"+1 361 287 3716",
    "sg:postcode":"78389",
    "sg:province":"TX",
    "sg:tags":[
        "oil"
    ],
    "wof:name":"Olivares Service Ctr",
    "wof:placetype":"venue"
},
  "geometry": {"coordinates":[-97.68513,28.251939],"type":"Point"}
}