{
  "type": "Feature",
  "properties": {
    "iso:country":"US",
    "sg:address":"6300 E Northwest Hwy",
    "sg:city":"Dallas",
    "sg:classifiers":[
        {
            "category":"Shopping",
            "subcategory":"Clothing, Apparel, & Fashions",
            "type":"Retail Goods"
        }
    ],
    "sg:phone":"+1 214 691 6635",
    "sg:postcode":"75231",
    "sg:province":"TX",
    "sg:website":"www.ashleystewart.com",
    "wof:name":"Ashley Stewart",
    "wof:placetype":"venue"
},
  "geometry": {"coordinates":[-96.75380199999999,32.859626],"type":"Point"}
}