{
  "type": "Feature",
  "properties": {
    "iso:country":"US",
    "sg:address":"201 Leveritts Loop",
    "sg:city":"Wimberley",
    "sg:classifiers":[
        {
            "category":"Local Transit",
            "type":"Transportation"
        }
    ],
    "sg:phone":"+1 512 847 0787",
    "sg:postcode":"78676",
    "sg:province":"TX",
    "sg:tags":[
        "passenger"
    ],
    "wof:name":"Champion Limousine Inc",
    "wof:placetype":"venue"
},
  "geometry": {"coordinates":[-98.10581500000001,29.993591],"type":"Point"}
}