{
  "type": "Feature",
  "properties": {
    "iso:country":"US",
    "sg:address":"111 W 6th St",
    "sg:city":"Plainview",
    "sg:classifiers":[
        {
            "category":"Government",
            "subcategory":"Office",
            "type":"Public Place"
        }
    ],
    "sg:phone":"+1 806 296 5217",
    "sg:postcode":"79072",
    "sg:province":"TX",
    "wof:name":"Special Projects",
    "wof:placetype":"venue"
},
  "geometry": {"coordinates":[-101.703254,34.185669],"type":"Point"}
}