{
  "type": "Feature",
  "properties": {
    "iso:country":"US",
    "sg:address":"2209 Guadalupe St",
    "sg:city":"San Antonio",
    "sg:classifiers":[
        {
            "category":"Bars & Pubs",
            "type":"Food & Drink"
        }
    ],
    "sg:phone":"+1 210 226 7807",
    "sg:postcode":"78207",
    "sg:province":"TX",
    "sg:tags":[
        "drinking"
    ],
    "wof:name":"J JS Tavern",
    "wof:placetype":"venue"
},
  "geometry": {"coordinates":[-98.525666,29.419476],"type":"Point"}
}