{
  "type": "Feature",
  "properties": {
    "iso:country":"US",
    "sg:address":"475 Kennon Cir",
    "sg:city":"Palo Pinto",
    "sg:classifiers":[
        {
            "category":"Professional",
            "type":"Services"
        }
    ],
    "sg:phone":"+1 940 769 3113",
    "sg:postcode":"76484",
    "sg:province":"TX",
    "wof:name":"Angelfire Pottery",
    "wof:placetype":"venue"
},
  "geometry": {"coordinates":[-98.30009099999999,32.657175],"type":"Point"}
}