{
  "type": "Feature",
  "properties": {
    "iso:country":"US",
    "sg:address":"5840 Lynbrook Dr",
    "sg:city":"Houston",
    "sg:classifiers":[
        {
            "category":"Professional",
            "subcategory":"Lawyer & Legal Services",
            "type":"Services"
        }
    ],
    "sg:phone":"+1 713 224 1700",
    "sg:postcode":"77057",
    "sg:province":"TX",
    "wof:name":"Knight & Franz Law Firm",
    "wof:placetype":"venue"
},
  "geometry": {"coordinates":[-95.48497500000001,29.755524],"type":"Point"}
}