{
  "type": "Feature",
  "properties": {
    "iso:country":"US",
    "sg:address":"2310 35th St",
    "sg:city":"Lubbock",
    "sg:classifiers":[
        {
            "category":"Personal",
            "type":"Services"
        }
    ],
    "sg:phone":"+1 806 793 3683",
    "sg:postcode":"79412",
    "sg:province":"TX",
    "wof:name":"Terry Russell",
    "wof:placetype":"venue"
},
  "geometry": {"coordinates":[-101.868073,33.562438],"type":"Point"}
}