{
  "type": "Feature",
  "properties": {
    "iso:country":"US",
    "sg:address":"7302 Misty Morning Dr",
    "sg:city":"Humble",
    "sg:classifiers":[
        {
            "category":"Wholesale",
            "subcategory":"Machinery & Supplies",
            "type":"Manufacturing & Wholesale Goods"
        }
    ],
    "sg:phone":"+1 281 812 3404",
    "sg:postcode":"77346",
    "sg:province":"TX",
    "sg:tags":[
        "equipment",
        "railroad"
    ],
    "wof:name":"Menard's Railroad Materials",
    "wof:placetype":"venue"
},
  "geometry": {"coordinates":[-95.165171,29.9952],"type":"Point"}
}