{
  "type": "Feature",
  "properties": {
    "iso:country":"US",
    "sg:address":"10641 Forest Ln",
    "sg:city":"Dallas",
    "sg:classifiers":[
        {
            "category":"Banks & Credit Unions",
            "subcategory":"Bank",
            "type":"Services"
        }
    ],
    "sg:phone":"+1 972 792 4240",
    "sg:postcode":"75243",
    "sg:province":"TX",
    "wof:name":"BB&T",
    "wof:placetype":"venue"
},
  "geometry": {"coordinates":[-96.701109,32.909292],"type":"Point"}
}