{
  "type": "Feature",
  "properties": {
    "iso:country":"US",
    "sg:address":"603 S 5th St",
    "sg:city":"Richmond",
    "sg:classifiers":[
        {
            "category":"Professional",
            "subcategory":"Lawyer & Legal Services",
            "type":"Services"
        }
    ],
    "sg:phone":"+1 713 626 7320",
    "sg:postcode":"77469",
    "sg:province":"TX",
    "wof:name":"George O Jacobs",
    "wof:placetype":"venue"
},
  "geometry": {"coordinates":[-95.761115,29.579597],"type":"Point"}
}