{
  "type": "Feature",
  "properties": {
    "iso:country":"US",
    "sg:address":"1201 Seward View Rd",
    "sg:city":"Leander",
    "sg:classifiers":[
        {
            "category":"Retail",
            "subcategory":"Auto Repair",
            "type":"Services"
        }
    ],
    "sg:phone":"+1 512 635 3421",
    "sg:postcode":"78641",
    "sg:province":"TX",
    "sg:tags":[
        "general"
    ],
    "wof:name":"Precision Auto Lab",
    "wof:placetype":"venue"
},
  "geometry": {"coordinates":[-97.895764,30.622335],"type":"Point"}
}