{
  "type": "Feature",
  "properties": {
    "iso:country":"US",
    "sg:address":"708 Texas St",
    "sg:city":"Liberty",
    "sg:classifiers":[
        {
            "category":"Shopping",
            "subcategory":"Pharmacy",
            "type":"Retail Goods"
        }
    ],
    "sg:phone":"+1 936 336 8074",
    "sg:postcode":"77575",
    "sg:province":"TX",
    "wof:name":"Faerie Apothecary",
    "wof:placetype":"venue"
},
  "geometry": {"coordinates":[-94.788352,30.063241],"type":"Point"}
}