{
  "type": "Feature",
  "properties": {
    "iso:country":"US",
    "sg:address":"1822 Keeler Ave",
    "sg:city":"Wichita Falls",
    "sg:classifiers":[
        {
            "category":"Retail",
            "subcategory":"Animal Services",
            "type":"Services"
        }
    ],
    "sg:phone":"+1 940 687 0402",
    "sg:postcode":"76301",
    "sg:province":"TX",
    "sg:tags":[
        "pet",
        "grooming",
        "washing"
    ],
    "wof:name":"Poochiez Pet Salon",
    "wof:placetype":"venue"
},
  "geometry": {"coordinates":[-98.507786,33.893051],"type":"Point"}
}