{
  "type": "Feature",
  "properties": {
    "iso:country":"US",
    "sg:address":"1002 Co Rd 499",
    "sg:city":"Harlingen",
    "sg:classifiers":[
        {
            "category":"Wholesale",
            "subcategory":"Electrical",
            "type":"Manufacturing & Wholesale Goods"
        }
    ],
    "sg:phone":"+1 956 423 6664",
    "sg:postcode":"78550",
    "sg:province":"TX",
    "sg:tags":[
        "equipment"
    ],
    "wof:name":"Light House",
    "wof:placetype":"venue"
},
  "geometry": {"coordinates":[-97.67676,26.16807],"type":"Point"}
}