{
  "type": "Feature",
  "properties": {
    "iso:country":"US",
    "sg:address":"121 N McCarty Ave",
    "sg:city":"Eagle Lake",
    "sg:classifiers":[
        {
            "category":"Personal",
            "type":"Services"
        }
    ],
    "sg:phone":"+1 979 234 2042",
    "sg:postcode":"77434",
    "sg:province":"TX",
    "sg:tags":[
        "wedding",
        "chapel"
    ],
    "wof:name":"Colorado County Justice-Peace",
    "wof:placetype":"venue"
},
  "geometry": {"coordinates":[-96.33396,29.589304],"type":"Point"}
}