{
  "type": "Feature",
  "properties": {
    "iso:country":"US",
    "sg:address":"13616 Tanglewood Dr",
    "sg:city":"Dallas",
    "sg:classifiers":[
        {
            "category":"Building & Trades",
            "subcategory":"Construction",
            "type":"Services"
        }
    ],
    "sg:phone":"+1 972 484 1301",
    "sg:postcode":"75234",
    "sg:province":"TX",
    "sg:tags":[
        "contractor"
    ],
    "wof:name":"Mainten Bertrand Brothers",
    "wof:placetype":"venue"
},
  "geometry": {"coordinates":[-96.856495,32.931199],"type":"Point"}
}