{
  "type": "Feature",
  "properties": {
    "iso:country":"US",
    "sg:address":"1333 Belt Line Rd",
    "sg:city":"Garland",
    "sg:classifiers":[
        {
            "category":"Organizations",
            "subcategory":"Religious Organization",
            "type":"Services"
        }
    ],
    "sg:phone":"+1 972 530 8555",
    "sg:postcode":"75040",
    "sg:province":"TX",
    "sg:tags":[
        "churches-lutheran"
    ],
    "sg:website":"www.gloriadeigarland.org",
    "wof:name":"Gloria Dei Lutheran Church",
    "wof:placetype":"venue"
},
  "geometry": {"coordinates":[-96.6465,32.945],"type":"Point"}
}