{
  "type": "Feature",
  "properties": {
    "iso:country":"US",
    "sg:address":"2413 Bertrand St",
    "sg:city":"Houston",
    "sg:classifiers":[
        {
            "category":"Building & Trades",
            "subcategory":"Construction",
            "type":"Services"
        }
    ],
    "sg:phone":"+1 281 987 1324",
    "sg:postcode":"77093",
    "sg:province":"TX",
    "sg:tags":[
        "contractor"
    ],
    "wof:name":"Sythetic & Stucco Designs",
    "wof:placetype":"venue"
},
  "geometry": {"coordinates":[-95.346029,29.886814],"type":"Point"}
}