{
  "type": "Feature",
  "properties": {
    "iso:country":"US",
    "sg:address":"2102 Tidwell Rd",
    "sg:city":"Houston",
    "sg:classifiers":[
        {
            "category":"Organizations",
            "subcategory":"Religious Organization",
            "type":"Services"
        }
    ],
    "sg:phone":"+1 713 692 6316",
    "sg:postcode":"77093",
    "sg:province":"TX",
    "wof:name":"North Central Baptist Church",
    "wof:placetype":"venue"
},
  "geometry": {"coordinates":[-95.351592,29.847967],"type":"Point"}
}