{
  "type": "Feature",
  "properties": {
    "iso:country":"US",
    "sg:address":"3208 Falls Dr",
    "sg:city":"Dallas",
    "sg:classifiers":[
        {
            "category":"Personal",
            "subcategory":"Beauty Salon",
            "type":"Services"
        }
    ],
    "sg:phone":"+1 214 330 2770",
    "sg:postcode":"75211",
    "sg:province":"TX",
    "sg:tags":[
        "nail",
        "shop"
    ],
    "wof:name":"A D Nails",
    "wof:placetype":"venue"
},
  "geometry": {"coordinates":[-96.873199,32.726501],"type":"Point"}
}