{
  "type": "Feature",
  "properties": {
    "iso:country":"US",
    "sg:address":"3941 Fondren Rd",
    "sg:city":"Houston",
    "sg:classifiers":[
        {
            "category":"Autos & Motor Vehicles",
            "subcategory":"Fuel & Gas Station",
            "type":"Retail Goods"
        }
    ],
    "sg:phone":"+1 713 785 9810",
    "sg:postcode":"77063",
    "sg:province":"TX",
    "wof:name":"Chevron Stations",
    "wof:placetype":"venue"
},
  "geometry": {"coordinates":[-95.520203,29.721901],"type":"Point"}
}