{
  "type": "Feature",
  "properties": {
    "iso:country":"US",
    "sg:address":"10106 Warrington Cove",
    "sg:city":"Austin",
    "sg:classifiers":[
        {
            "category":"Professional",
            "subcategory":"Computer Services",
            "type":"Services"
        }
    ],
    "sg:phone":"+1 512 837 8294",
    "sg:postcode":"78753",
    "sg:province":"TX",
    "sg:tags":[
        "programing",
        "custom"
    ],
    "wof:name":"Hellrung Business Solutions",
    "wof:placetype":"venue"
},
  "geometry": {"coordinates":[-97.673908,30.362052],"type":"Point"}
}