{
  "type": "Feature",
  "properties": {
    "iso:country":"US",
    "sg:address":"110 Sampson St",
    "sg:city":"Houston",
    "sg:classifiers":[
        {
            "category":"Manufacturing",
            "subcategory":"Tools & Machinery",
            "type":"Manufacturing & Wholesale Goods"
        }
    ],
    "sg:phone":"+1 713 222 1011",
    "sg:postcode":"77003",
    "sg:province":"TX",
    "sg:tags":[
        "measuring",
        "machinist",
        "cutting",
        "precision",
        "mfg"
    ],
    "wof:name":"Regal Cutting Tools",
    "wof:placetype":"venue"
},
  "geometry": {"coordinates":[-95.339026,29.751389],"type":"Point"}
}