{
  "type": "Feature",
  "properties": {
    "iso:country":"US",
    "sg:address":"3154 E 24th St",
    "sg:city":"Brownsville",
    "sg:classifiers":[
        {
            "category":"Shopping",
            "type":"Retail Goods"
        }
    ],
    "sg:phone":"+1 956 982 6823",
    "sg:postcode":"78521",
    "sg:province":"TX",
    "sg:tags":[
        "merchandise"
    ],
    "wof:name":"T S S Communications",
    "wof:placetype":"venue"
},
  "geometry": {"coordinates":[-97.46939999999999,25.907238],"type":"Point"}
}