{
  "type": "Feature",
  "properties": {
    "iso:country":"US",
    "sg:address":"1221 W 11th St",
    "sg:city":"Houston",
    "sg:classifiers":[
        {
            "category":"Restaurant",
            "type":"Food & Drink"
        }
    ],
    "sg:phone":"+1 713 426 2750",
    "sg:postcode":"77008",
    "sg:province":"TX",
    "sg:tags":[
        "fusion",
        "asian"
    ],
    "sg:website":"www.dragonbowlbistro.com",
    "wof:name":"Dragon Bowl Asian Bistro",
    "wof:placetype":"venue"
},
  "geometry": {"coordinates":[-95.409125,29.790519],"type":"Point"}
}