{
  "type": "Feature",
  "properties": {
    "iso:country":"US",
    "sg:address":"1408 E Main St",
    "sg:city":"Fredericksburg",
    "sg:classifiers":[
        {
            "category":"Restaurant",
            "type":"Food & Drink"
        }
    ],
    "sg:phone":"+1 830 997 9797",
    "sg:postcode":"78624",
    "sg:province":"TX",
    "sg:tags":[
        "eating"
    ],
    "wof:name":"Mr Gattis",
    "wof:placetype":"venue"
},
  "geometry": {"coordinates":[-98.854116,30.258913],"type":"Point"}
}