{
  "type": "Feature",
  "properties": {
    "iso:country":"US",
    "sg:address":"6315 Walnut Hill Ln",
    "sg:city":"Dallas",
    "sg:classifiers":[
        {
            "category":"Social Services",
            "subcategory":"Child Care",
            "type":"Services"
        }
    ],
    "sg:phone":"+1 214 363 4393",
    "sg:postcode":"75230",
    "sg:province":"TX",
    "sg:tags":[
        "day"
    ],
    "sg:website":"www.umc.org",
    "wof:name":"Preston Hollow United Methodist Church",
    "wof:placetype":"venue"
},
  "geometry": {"coordinates":[-96.797501,32.8801],"type":"Point"}
}