{
  "type": "Feature",
  "properties": {
    "iso:country":"US",
    "sg:address":"7906 Nimrod Trl",
    "sg:city":"Dallas",
    "sg:classifiers":[
        {
            "category":"Professional",
            "subcategory":"Management & Consulting",
            "type":"Services"
        }
    ],
    "sg:phone":"+1 214 349 8507",
    "sg:postcode":"75238",
    "sg:province":"TX",
    "wof:name":"Wylie Cat Communications",
    "wof:placetype":"venue"
},
  "geometry": {"coordinates":[-96.726747,32.867462],"type":"Point"}
}