{
  "type": "Feature",
  "properties": {
    "iso:country":"US",
    "sg:address":"599 Cool Water Dr",
    "sg:city":"Bastrop",
    "sg:classifiers":[
        {
            "category":"Travel",
            "subcategory":"Campground",
            "type":"Entertainment"
        }
    ],
    "sg:phone":"+1 512 581 0065",
    "sg:postcode":"78602",
    "sg:province":"TX",
    "sg:tags":[
        "camp"
    ],
    "wof:name":"Juvenile Boot Camp",
    "wof:placetype":"venue"
},
  "geometry": {"coordinates":[-97.301478,30.205622],"type":"Point"}
}