{
  "type": "Feature",
  "properties": {
    "iso:country":"US",
    "sg:address":"9736 Vinewood Dr",
    "sg:city":"Dallas",
    "sg:classifiers":[
        {
            "category":"Wholesale",
            "subcategory":"Jewelry",
            "type":"Manufacturing & Wholesale Goods"
        }
    ],
    "sg:phone":"+1 214 324 5912",
    "sg:postcode":"75228",
    "sg:province":"TX",
    "sg:tags":[
        "stone"
    ],
    "wof:name":"S Brooke",
    "wof:placetype":"venue"
},
  "geometry": {"coordinates":[-96.68825,32.822671],"type":"Point"}
}