{
  "type": "Feature",
  "properties": {
    "iso:country":"US",
    "sg:address":"5400 Fm 1640 Rd",
    "sg:city":"Richmond",
    "sg:classifiers":[
        {
            "category":"Restaurant",
            "type":"Food & Drink"
        }
    ],
    "sg:menulink":"http://www.allmenus.com/tx/rosenberg-richmond/157385-whataburger/menu/",
    "sg:phone":"+1 281 239 7161",
    "sg:postcode":"77469",
    "sg:province":"TX",
    "sg:tags":[
        "burger",
        "american"
    ],
    "wof:name":"Whataburger",
    "wof:placetype":"venue"
},
  "geometry": {"coordinates":[-95.76253199999999,29.569928],"type":"Point"}
}