{
  "type": "Feature",
  "properties": {
    "iso:country":"US",
    "sg:address":"4811 61st St",
    "sg:city":"Lubbock",
    "sg:classifiers":[
        {
            "category":"Shopping",
            "subcategory":"Gifts & Souvenirs",
            "type":"Retail Goods"
        }
    ],
    "sg:phone":"+1 806 797 5203",
    "sg:postcode":"79414",
    "sg:province":"TX",
    "wof:name":"Martha A Davis",
    "wof:placetype":"venue"
},
  "geometry": {"coordinates":[-101.91570400000001,33.53867],"type":"Point"}
}