{
  "type": "Feature",
  "properties": {
    "iso:country":"US",
    "sg:address":"18926 Wildrose Ln",
    "sg:city":"Tomball",
    "sg:classifiers":[
        {
            "category":"Health Services",
            "subcategory":"Doctor",
            "type":"Services"
        }
    ],
    "sg:phone":"+1 281 351 4909",
    "sg:postcode":"77377",
    "sg:province":"TX",
    "sg:tags":[
        "medicine",
        "physician",
        "practice",
        "surgeons",
        "family"
    ],
    "wof:name":"Cypress Medical Clinic",
    "wof:placetype":"venue"
},
  "geometry": {"coordinates":[-95.71688,30.084761],"type":"Point"}
}