{
  "type": "Feature",
  "properties": {
    "iso:country":"US",
    "sg:address":"5207 Brodie Lane Ste # 135",
    "sg:city":"Austin",
    "sg:classifiers":[
        {
            "category":"Personal",
            "type":"Services"
        }
    ],
    "sg:phone":"+1 512 891 0679",
    "sg:postcode":"78745",
    "sg:province":"TX",
    "sg:tags":[
        "shopping"
    ],
    "sg:website":"tmw.com",
    "wof:name":"Mens Warehouse",
    "wof:placetype":"venue"
},
  "geometry": {"coordinates":[-97.818585,30.231409],"type":"Point"}
}