{
  "type": "Feature",
  "properties": {
    "iso:country":"US",
    "sg:address":"8130 Westglen Dr Ste 100",
    "sg:city":"Houston",
    "sg:classifiers":[
        {
            "category":"Shopping",
            "subcategory":"Crafts & Fabrics",
            "type":"Retail Goods"
        },
        {
            "category":"Professional",
            "subcategory":"Art Services",
            "type":"Services"
        }
    ],
    "sg:phone":"+1 713 339 1373",
    "sg:postcode":"77063",
    "sg:province":"TX",
    "sg:tags":[
        "punching",
        "design",
        "embroidery"
    ],
    "sg:website":"http://www.diecastairplanes.com",
    "wof:name":"Wearable Etc",
    "wof:placetype":"venue"
},
  "geometry": {"coordinates":[-95.50798399999999,29.724747],"type":"Point"}
}