{
  "type": "Feature",
  "properties": {
    "iso:country":"US",
    "sg:address":"424 Mountainview Dr",
    "sg:city":"Hurst",
    "sg:classifiers":[
        {
            "category":"Organizations",
            "subcategory":"Religious Organization",
            "type":"Services"
        }
    ],
    "sg:phone":"+1 817 485 6864",
    "sg:postcode":"76054",
    "sg:province":"TX",
    "wof:name":"North Texas Biblical Studies",
    "wof:placetype":"venue"
},
  "geometry": {"coordinates":[-97.17681899999999,32.852796],"type":"Point"}
}