{
  "type": "Feature",
  "properties": {
    "iso:country":"US",
    "sg:address":"302 S Main St",
    "sg:city":"Boerne",
    "sg:classifiers":[
        {
            "category":"Shopping",
            "subcategory":"Clothing, Apparel, & Fashions",
            "type":"Retail Goods"
        }
    ],
    "sg:phone":"+1 830 249 5886",
    "sg:postcode":"78006",
    "sg:province":"TX",
    "wof:name":"Victorias Boutique",
    "wof:placetype":"venue"
},
  "geometry": {"coordinates":[-98.73061300000001,29.79147],"type":"Point"}
}