{
  "type": "Feature",
  "properties": {
    "iso:country":"US",
    "sg:address":"106 W 1st St",
    "sg:city":"Weatherford",
    "sg:classifiers":[
        {
            "category":"Retail",
            "subcategory":"Self-service Laundry",
            "type":"Services"
        }
    ],
    "sg:phone":"+1 817 599 8380",
    "sg:postcode":"76086",
    "sg:province":"TX",
    "sg:tags":[
        "coin",
        "power"
    ],
    "wof:name":"Edwards Laundry",
    "wof:placetype":"venue"
},
  "geometry": {"coordinates":[-97.797192,32.769759],"type":"Point"}
}