{
  "type": "Feature",
  "properties": {
    "iso:country":"US",
    "sg:address":"9819 Teasdale Ter",
    "sg:city":"Austin",
    "sg:classifiers":[
        {
            "category":"Professional",
            "type":"Services"
        }
    ],
    "sg:phone":"+1 512 834 2462",
    "sg:postcode":"78753",
    "sg:province":"TX",
    "wof:name":"Michael Zapata",
    "wof:placetype":"venue"
},
  "geometry": {"coordinates":[-97.67603699999999,30.358213],"type":"Point"}
}