{
  "type": "Feature",
  "properties": {
    "iso:country":"US",
    "sg:address":"505 Thornton Rd",
    "sg:city":"Houston",
    "sg:classifiers":[
        {
            "category":"Real Estate",
            "subcategory":"Real Estate Operator",
            "type":"Services"
        }
    ],
    "sg:phone":"+1 713 695 3455",
    "sg:postcode":"77018",
    "sg:province":"TX",
    "sg:tags":[
        "building",
        "apartment"
    ],
    "wof:name":"Las Palmas Apts",
    "wof:placetype":"venue"
},
  "geometry": {"coordinates":[-95.406503,29.832503],"type":"Point"}
}