{
  "type": "Feature",
  "properties": {
    "iso:country":"US",
    "sg:address":"1201 S Nebraska Ave",
    "sg:city":"San Juan",
    "sg:classifiers":[
        {
            "category":"Building & Trades",
            "subcategory":"Construction",
            "type":"Services"
        }
    ],
    "sg:phone":"+1 956 781 2922",
    "sg:postcode":"78589",
    "sg:province":"TX",
    "sg:tags":[
        "lift",
        "municipality",
        "for"
    ],
    "wof:name":"Stapleton Services & Mfg",
    "wof:placetype":"venue"
},
  "geometry": {"coordinates":[-98.157027,26.180647],"type":"Point"}
}