{
  "type": "Feature",
  "properties": {
    "iso:country":"US",
    "sg:address":"11008 River Plantation Dr",
    "sg:city":"Austin",
    "sg:classifiers":[
        {
            "category":"Arena",
            "subcategory":"Sports Club",
            "type":"Entertainment"
        }
    ],
    "sg:phone":"+1 512 422 5670",
    "sg:postcode":"78747",
    "sg:province":"TX",
    "wof:name":"Austins West End Volleyball",
    "wof:placetype":"venue"
},
  "geometry": {"coordinates":[-97.77989599999999,30.133834],"type":"Point"}
}