{
  "type": "Feature",
  "properties": {
    "iso:country":"US",
    "sg:address":"1031 W University Ave",
    "sg:city":"Georgetown",
    "sg:classifiers":[
        {
            "category":"Restaurant",
            "type":"Food & Drink"
        }
    ],
    "sg:menulink":"http://www.allmenus.com/tx/georgetown-round-rock/179299-chick-fil-a/menu/",
    "sg:phone":"+1 512 930 4884",
    "sg:postcode":"78628",
    "sg:province":"TX",
    "sg:tags":[
        "wrap",
        "soup",
        "american",
        "sandwich",
        "salad"
    ],
    "wof:name":"Chick-fil-A",
    "wof:placetype":"venue"
},
  "geometry": {"coordinates":[-97.693468,30.633026],"type":"Point"}
}