{
  "type": "Feature",
  "properties": {
    "iso:country":"US",
    "sg:address":"563 Silva St",
    "sg:city":"Seguin",
    "sg:classifiers":[
        {
            "category":"Farming",
            "subcategory":"Crops",
            "type":"Manufacturing & Wholesale Goods"
        }
    ],
    "sg:phone":"+1 830 379 8910",
    "sg:postcode":"78155",
    "sg:province":"TX",
    "sg:tags":[
        "farm"
    ],
    "wof:name":"McKnight Spray Co",
    "wof:placetype":"venue"
},
  "geometry": {"coordinates":[-97.97185399999999,29.581663],"type":"Point"}
}