{
  "type": "Feature",
  "properties": {
    "iso:country":"US",
    "sg:address":"315 W Oak St",
    "sg:city":"Sanderson",
    "sg:classifiers":[
        {
            "category":"Utilities",
            "subcategory":"Fuel Oil & Lpg",
            "type":"Services"
        }
    ],
    "sg:phone":"+1 432 345 2464",
    "sg:postcode":"79848",
    "sg:province":"TX",
    "sg:tags":[
        "gas",
        "butane"
    ],
    "wof:name":"Sanderson Propane",
    "wof:placetype":"venue"
},
  "geometry": {"coordinates":[-102.400627,30.142126],"type":"Point"}
}