{
  "type": "Feature",
  "properties": {
    "iso:country":"US",
    "sg:address":"713 E 2nd St",
    "sg:city":"Odessa",
    "sg:classifiers":[
        {
            "category":"Shopping",
            "type":"Retail Goods"
        }
    ],
    "sg:phone":"+1 432 332 3511",
    "sg:postcode":"79761",
    "sg:province":"TX",
    "sg:tags":[
        "product",
        "wood"
    ],
    "wof:name":"Wood Products",
    "wof:placetype":"venue"
},
  "geometry": {"coordinates":[-102.359359,31.850059],"type":"Point"}
}