{
  "type": "Feature",
  "properties": {
    "iso:country":"US",
    "sg:address":"1312 Ave H",
    "sg:city":"South Houston",
    "sg:classifiers":[
        {
            "category":"Freight",
            "type":"Transportation"
        }
    ],
    "sg:phone":"+1 713 910 1176",
    "sg:postcode":"77587",
    "sg:province":"TX",
    "wof:name":"Guzman Transports",
    "wof:placetype":"venue"
},
  "geometry": {"coordinates":[-95.213266,29.659414],"type":"Point"}
}