{
  "type": "Feature",
  "properties": {
    "iso:country":"US",
    "sg:address":"1804 W Hildebrand Ave",
    "sg:city":"San Antonio",
    "sg:classifiers":[
        {
            "category":"Manufacturing",
            "subcategory":"Signs",
            "type":"Manufacturing & Wholesale Goods"
        }
    ],
    "sg:phone":"+1 210 732 5888",
    "sg:postcode":"78201",
    "sg:province":"TX",
    "wof:name":"Sign Source",
    "wof:placetype":"venue"
},
  "geometry": {"coordinates":[-98.52596200000001,29.466414],"type":"Point"}
}