{
  "type": "Feature",
  "properties": {
    "iso:country":"US",
    "sg:address":"4415 West Ave",
    "sg:city":"San Antonio",
    "sg:classifiers":[
        {
            "category":"Autos & Motor Vehicles",
            "subcategory":"Fuel & Gas Station",
            "type":"Retail Goods"
        }
    ],
    "sg:phone":"+1 210 979 9134",
    "sg:postcode":"78213",
    "sg:province":"TX",
    "sg:tags":[
        "grocery",
        "gasoline"
    ],
    "wof:name":"Petro Pantry",
    "wof:placetype":"venue"
},
  "geometry": {"coordinates":[-98.526025,29.506295],"type":"Point"}
}