{
  "type": "Feature",
  "properties": {
    "iso:country":"US",
    "sg:address":"2377 N Stemmons Fwy",
    "sg:city":"Dallas",
    "sg:classifiers":[
        {
            "category":"Professional",
            "subcategory":"Business Services",
            "type":"Services"
        }
    ],
    "sg:phone":"+1 214 819 1800",
    "sg:postcode":"75207",
    "sg:province":"TX",
    "sg:tags":[
        "medical",
        "administration"
    ],
    "sg:website":"http://www.dallascounty.org",
    "wof:name":"Dallas County Health And Human Services",
    "wof:placetype":"venue"
},
  "geometry": {"coordinates":[-96.83535000000001,32.80378],"type":"Point"}
}