{
  "type": "Feature",
  "properties": {
    "iso:country":"US",
    "sg:address":"1617 Canyon Creek Dr",
    "sg:city":"Temple",
    "sg:classifiers":[
        {
            "category":"Professional",
            "type":"Services"
        }
    ],
    "sg:phone":"+1 254 742 1598",
    "sg:postcode":"76502",
    "sg:province":"TX",
    "sg:tags":[
        "establishment"
    ],
    "wof:name":"De Biaso D",
    "wof:placetype":"venue"
},
  "geometry": {"coordinates":[-97.374605,31.061815],"type":"Point"}
}