{
  "type": "Feature",
  "properties": {
    "iso:country":"US",
    "sg:address":"17520 Oak Mount Pl",
    "sg:city":"Dallas",
    "sg:classifiers":[
        {
            "category":"Shopping",
            "subcategory":"Jewelry",
            "type":"Retail Goods"
        }
    ],
    "sg:phone":"+1 214 505 4936",
    "sg:postcode":"75287",
    "sg:province":"TX",
    "sg:tags":[
        "jeweler"
    ],
    "wof:name":"Andrew Morgan Pearls",
    "wof:placetype":"venue"
},
  "geometry": {"coordinates":[-96.817542,32.991891],"type":"Point"}
}