{
  "type": "Feature",
  "properties": {
    "iso:country":"US",
    "sg:address":"1911 W Ben White Boulevard",
    "sg:city":"Austin",
    "sg:classifiers":[
        {
            "category":"Personal",
            "subcategory":"Shoe Repair & Shine",
            "type":"Services"
        }
    ],
    "sg:phone":"+1 512 440 8788",
    "sg:postcode":"78704",
    "sg:province":"TX",
    "wof:name":"Austin Shoe Hospital",
    "wof:placetype":"venue"
},
  "geometry": {"coordinates":[-97.787926,30.229227],"type":"Point"}
}