{
  "type": "Feature",
  "properties": {
    "iso:country":"US",
    "sg:address":"1416 Spring Cypress Rd",
    "sg:city":"Spring",
    "sg:classifiers":[
        {
            "category":"Professional",
            "subcategory":"Management & Consulting",
            "type":"Services"
        },
        {
            "category":"Shopping",
            "subcategory":"Crafts & Fabrics",
            "type":"Retail Goods"
        }
    ],
    "sg:phone":"+1 281 355 9820",
    "sg:postcode":"77373",
    "sg:province":"TX",
    "sg:tags":[
        "material",
        "quilting",
        "business",
        "supply"
    ],
    "wof:name":"Juliene's Quilts",
    "wof:placetype":"venue"
},
  "geometry": {"coordinates":[-95.43328700000001,30.075997],"type":"Point"}
}