{
  "type": "Feature",
  "properties": {
    "iso:country":"US",
    "sg:address":"1920 McPherson Ave",
    "sg:city":"Laredo",
    "sg:classifiers":[
        {
            "category":"Retail",
            "subcategory":"Laundry & Dry Cleaning",
            "type":"Services"
        }
    ],
    "sg:phone":"+1 956 718 3044",
    "sg:postcode":"78040",
    "sg:province":"TX",
    "sg:tags":[
        "cleaners",
        "rug",
        "carpet"
    ],
    "wof:name":"Royal Carpet & Upholstery",
    "wof:placetype":"venue"
},
  "geometry": {"coordinates":[-99.484562,27.513709],"type":"Point"}
}