{
  "type": "Feature",
  "properties": {
    "iso:country":"US",
    "sg:address":"3102 50th St",
    "sg:city":"Lubbock",
    "sg:classifiers":[
        {
            "category":"Building & Trades",
            "subcategory":"Construction",
            "type":"Services"
        }
    ],
    "sg:phone":"+1 806 796 2525",
    "sg:postcode":"79413",
    "sg:province":"TX",
    "sg:tags":[
        "roofing",
        "contractor"
    ],
    "wof:name":"Shield Exteriors",
    "wof:placetype":"venue"
},
  "geometry": {"coordinates":[-101.88339499999999,33.5488],"type":"Point"}
}