{
  "type": "Feature",
  "properties": {
    "iso:country":"US",
    "sg:address":"4403 Ganymede Dr",
    "sg:city":"Austin",
    "sg:classifiers":[
        {
            "category":"Arts & Performance",
            "subcategory":"Music",
            "type":"Entertainment"
        }
    ],
    "sg:phone":"+1 512 834 2126",
    "sg:postcode":"78727",
    "sg:province":"TX",
    "sg:tags":[
        "arranger",
        "composer"
    ],
    "wof:name":"Texasongwriter David Patr",
    "wof:placetype":"venue"
},
  "geometry": {"coordinates":[-97.72027199999999,30.425311],"type":"Point"}
}