{
  "type": "Feature",
  "properties": {
    "iso:country":"US",
    "sg:address":"2100 N Bell Blvd",
    "sg:city":"Cedar Park",
    "sg:classifiers":[
        {
            "category":"Freight",
            "type":"Transportation"
        }
    ],
    "sg:phone":"+1 512 259 2263",
    "sg:postcode":"78613",
    "sg:province":"TX",
    "sg:tags":[
        "commercial",
        "storage"
    ],
    "wof:name":"Storagemaster USA",
    "wof:placetype":"venue"
},
  "geometry": {"coordinates":[-97.83587900000001,30.534434],"type":"Point"}
}