{
  "type": "Feature",
  "properties": {
    "iso:country":"US",
    "sg:address":"5616 Lawndale St",
    "sg:city":"Houston",
    "sg:classifiers":[
        {
            "category":"Health Services",
            "subcategory":"Dentist",
            "type":"Services"
        }
    ],
    "sg:phone":"+1 713 921 2100",
    "sg:postcode":"77023",
    "sg:province":"TX",
    "wof:name":"Texas Dental Services C Diaz DDS & Associates",
    "wof:placetype":"venue"
},
  "geometry": {"coordinates":[-95.31735999999999,29.726443],"type":"Point"}
}