{
  "type": "Feature",
  "properties": {
    "iso:country":"US",
    "sg:address":"6606 Broken Stone St",
    "sg:city":"Houston",
    "sg:classifiers":[
        {
            "category":"Wholesale",
            "subcategory":"Durable Goods & Equipment",
            "type":"Manufacturing & Wholesale Goods"
        }
    ],
    "sg:phone":"+1 713 858 1930",
    "sg:postcode":"77084",
    "sg:province":"TX",
    "sg:tags":[
        "professional"
    ],
    "wof:name":"Cascade Systems Inc",
    "wof:placetype":"venue"
},
  "geometry": {"coordinates":[-95.66726300000001,29.872819],"type":"Point"}
}