{
  "type": "Feature",
  "properties": {
    "iso:country":"US",
    "sg:address":"815 S Flores St",
    "sg:city":"San Antonio",
    "sg:classifiers":[
        {
            "category":"Food & Beverages",
            "subcategory":"Specialty",
            "type":"Retail Goods"
        }
    ],
    "sg:phone":"+1 210 227 4821",
    "sg:postcode":"78204",
    "sg:province":"TX",
    "sg:tags":[
        "tea",
        "coffee"
    ],
    "wof:name":"Oonies",
    "wof:placetype":"venue"
},
  "geometry": {"coordinates":[-98.499027,29.4153],"type":"Point"}
}