{
  "type": "Feature",
  "properties": {
    "iso:country":"US",
    "sg:address":"2800 Decker Dr",
    "sg:city":"Baytown",
    "sg:classifiers":[
        {
            "category":"Building & Trades",
            "subcategory":"Equipment Rental",
            "type":"Services"
        },
        {
            "category":"Building & Trades",
            "subcategory":"Construction",
            "type":"Services"
        },
        {
            "category":"Home & Garden",
            "subcategory":"Carpets & Floor Coverings",
            "type":"Retail Goods"
        }
    ],
    "sg:phone":"+1 281 420 2894",
    "sg:postcode":"77520",
    "sg:province":"TX",
    "sg:tags":[
        "lift",
        "aerial",
        "scaffolding",
        "rigger",
        "contractors'"
    ],
    "wof:name":"Scaffolding Specialties",
    "wof:placetype":"venue"
},
  "geometry": {"coordinates":[-94.992604,29.754962],"type":"Point"}
}