{
  "type": "Feature",
  "properties": {
    "iso:country":"US",
    "sg:address":"7135 Southwest Fwy",
    "sg:city":"Houston",
    "sg:classifiers":[
        {
            "category":"Professional",
            "subcategory":"Business Services",
            "type":"Services"
        }
    ],
    "sg:phone":"+1 713 541 3800",
    "sg:postcode":"77074",
    "sg:province":"TX",
    "wof:name":"Miller Candida H",
    "wof:placetype":"venue"
},
  "geometry": {"coordinates":[-95.511593,29.70526],"type":"Point"}
}