{
  "type": "Feature",
  "properties": {
    "iso:country":"US",
    "sg:address":"2727 Fondren Rd",
    "sg:city":"Houston",
    "sg:classifiers":[
        {
            "category":"Shopping",
            "subcategory":"Musical Instruments",
            "type":"Retail Goods"
        }
    ],
    "sg:phone":"+1 713 266 3338",
    "sg:postcode":"77063",
    "sg:province":"TX",
    "wof:name":"Dixies Music World",
    "wof:placetype":"venue"
},
  "geometry": {"coordinates":[-95.521074,29.737136],"type":"Point"}
}