{
  "type": "Feature",
  "properties": {
    "iso:country":"US",
    "sg:address":"3838 W Miller Rd",
    "sg:city":"Garland",
    "sg:classifiers":[
        {
            "category":"Wholesale",
            "subcategory":"Auto Parts",
            "type":"Manufacturing & Wholesale Goods"
        }
    ],
    "sg:phone":"+1 214 349 1097",
    "sg:postcode":"75041",
    "sg:province":"TX",
    "sg:tags":[
        "grill",
        "gas",
        "accessory"
    ],
    "wof:name":"Grand Hall Usa Inc",
    "wof:placetype":"venue"
},
  "geometry": {"coordinates":[-96.689325,32.894485],"type":"Point"}
}