{
  "type": "Feature",
  "properties": {
    "iso:country":"US",
    "sg:address":"1405 Fox Ln",
    "sg:city":"Lockhart",
    "sg:classifiers":[
        {
            "category":"Shopping",
            "subcategory":"Hobbies, Toys, & Games",
            "type":"Retail Goods"
        }
    ],
    "sg:phone":"+1 512 376 5995",
    "sg:postcode":"78644",
    "sg:province":"TX",
    "wof:name":"C R Creations",
    "wof:placetype":"venue"
},
  "geometry": {"coordinates":[-97.567808,29.837486],"type":"Point"}
}