{
  "type": "Feature",
  "properties": {
    "iso:country":"US",
    "sg:address":"1601 N Texas Blvd",
    "sg:city":"Weslaco",
    "sg:classifiers":[
        {
            "category":"Personal",
            "subcategory":"Beauty Salon",
            "type":"Services"
        }
    ],
    "sg:phone":"+1 956 969 1118",
    "sg:postcode":"78596",
    "sg:province":"TX",
    "sg:tags":[
        "shop"
    ],
    "wof:name":"Hair By ME",
    "wof:placetype":"venue"
},
  "geometry": {"coordinates":[-97.99104699999999,26.176782],"type":"Point"}
}