{
  "type": "Feature",
  "properties": {
    "iso:country":"US",
    "sg:address":"431 NW 3rd St",
    "sg:city":"Premont",
    "sg:classifiers":[
        {
            "category":"Health Services",
            "subcategory":"Nursing And Care Facility",
            "type":"Services"
        }
    ],
    "sg:phone":"+1 361 348 3553",
    "sg:postcode":"78375",
    "sg:province":"TX",
    "sg:tags":[
        "home",
        "convalescent"
    ],
    "wof:name":"Premont Nursing Home Inc",
    "wof:placetype":"venue"
},
  "geometry": {"coordinates":[-98.12992800000001,27.363297],"type":"Point"}
}