{
  "type": "Feature",
  "properties": {
    "iso:country":"US",
    "sg:address":"8204 Bluebonnet Dr",
    "sg:city":"Amarillo",
    "sg:classifiers":[
        {
            "category":"Personal",
            "subcategory":"Beauty Salon",
            "type":"Services"
        }
    ],
    "sg:phone":"+1 806 381 1683",
    "sg:postcode":"79108",
    "sg:province":"TX",
    "sg:tags":[
        "shop"
    ],
    "wof:name":"Greens Salon The",
    "wof:placetype":"venue"
},
  "geometry": {"coordinates":[-101.826657,35.299084],"type":"Point"}
}