{
  "type": "Feature",
  "properties": {
    "iso:country":"US",
    "sg:address":"647 Prestonwood Dr",
    "sg:city":"Richardson",
    "sg:classifiers":[
        {
            "category":"Personal",
            "type":"Services"
        }
    ],
    "sg:phone":"+1 972 442 1762",
    "sg:postcode":"75081",
    "sg:province":"TX",
    "sg:tags":[
        "consultant",
        "wedding"
    ],
    "wof:name":"Creative Romance",
    "wof:placetype":"venue"
},
  "geometry": {"coordinates":[-96.74744,32.937088],"type":"Point"}
}