{
  "type": "Feature",
  "properties": {
    "iso:country":"US",
    "sg:address":"2206 Post Oak Ct",
    "sg:city":"Denton",
    "sg:classifiers":[
        {
            "category":"Real Estate",
            "subcategory":"Real Estate Agent",
            "type":"Services"
        }
    ],
    "sg:phone":"+1 940 498 0317",
    "sg:postcode":"76210",
    "sg:province":"TX",
    "wof:name":"Ean Inc",
    "wof:placetype":"venue"
},
  "geometry": {"coordinates":[-97.074951,33.160018],"type":"Point"}
}