{
  "type": "Feature",
  "properties": {
    "iso:country":"US",
    "sg:address":"12330 Southwest Fwy",
    "sg:city":"Stafford",
    "sg:classifiers":[
        {
            "category":"Restaurant",
            "type":"Food & Drink"
        }
    ],
    "sg:menulink":"http://www.allmenus.com/tx/sugar-land/15558-gringos/menu/",
    "sg:phone":"+1 281 980 7482",
    "sg:postcode":"77477",
    "sg:province":"TX",
    "sg:tags":[
        "mexican"
    ],
    "wof:name":"Gringo's",
    "wof:placetype":"venue"
},
  "geometry": {"coordinates":[-95.578577,29.643021],"type":"Point"}
}