{
  "type": "Feature",
  "properties": {
    "iso:country":"US",
    "sg:address":"117 Ward Rd",
    "sg:city":"Baytown",
    "sg:classifiers":[
        {
            "category":"Personal",
            "type":"Services"
        }
    ],
    "sg:phone":"+1 281 422 9302",
    "sg:postcode":"77520",
    "sg:province":"TX",
    "wof:name":"Training Studio",
    "wof:placetype":"venue"
},
  "geometry": {"coordinates":[-94.963359,29.74248],"type":"Point"}
}