{
  "type": "Feature",
  "properties": {
    "iso:country":"US",
    "sg:address":"2410 Hollowbrook Ln",
    "sg:city":"Conroe",
    "sg:classifiers":[
        {
            "category":"Professional",
            "type":"Services"
        }
    ],
    "sg:phone":"+1 936 321 1757",
    "sg:postcode":"77384",
    "sg:province":"TX",
    "wof:name":"Masters World Inc",
    "wof:placetype":"venue"
},
  "geometry": {"coordinates":[-95.503474,30.245712],"type":"Point"}
}