{
  "type": "Feature",
  "properties": {
    "iso:country":"US",
    "sg:address":"9711 Gatecrest Dr",
    "sg:city":"Dallas",
    "sg:classifiers":[
        {
            "category":"Shopping",
            "subcategory":"Discount & Variety Stores",
            "type":"Retail Goods"
        }
    ],
    "sg:phone":"+1 214 343 0696",
    "sg:postcode":"75238",
    "sg:province":"TX",
    "sg:tags":[
        "merchandise",
        "general"
    ],
    "wof:name":"AMA Goods LLC",
    "wof:placetype":"venue"
},
  "geometry": {"coordinates":[-96.719476,32.871647],"type":"Point"}
}