{
  "type": "Feature",
  "properties": {
    "iso:country":"US",
    "sg:address":"2201 Chamberlain St",
    "sg:city":"Houston",
    "sg:classifiers":[
        {
            "category":"Manufacturing",
            "subcategory":"Metals",
            "type":"Manufacturing & Wholesale Goods"
        }
    ],
    "sg:phone":"+1 281 449 4585",
    "sg:postcode":"77093",
    "sg:province":"TX",
    "sg:tags":[
        "trim",
        "mfg"
    ],
    "wof:name":"Metal Trim Fabricators Inc",
    "wof:placetype":"venue"
},
  "geometry": {"coordinates":[-95.350827,29.876935],"type":"Point"}
}