{
  "type": "Feature",
  "properties": {
    "iso:country":"US",
    "sg:address":"948 E Mulberry St",
    "sg:city":"Angleton",
    "sg:classifiers":[
        {
            "category":"Shopping",
            "subcategory":"Used Merchandise",
            "type":"Retail Goods"
        }
    ],
    "sg:phone":"+1 979 848 3708",
    "sg:postcode":"77515",
    "sg:province":"TX",
    "sg:tags":[
        "shop",
        "consignment"
    ],
    "wof:name":"Nikki's Resale & Boutique",
    "wof:placetype":"venue"
},
  "geometry": {"coordinates":[-95.420441,29.166577],"type":"Point"}
}