{
  "type": "Feature",
  "properties": {
    "iso:country":"US",
    "sg:address":"1217 S 7th St",
    "sg:city":"Corsicana",
    "sg:classifiers":[
        {
            "category":"Building & Trades",
            "subcategory":"Equipment Rental",
            "type":"Services"
        }
    ],
    "sg:phone":"+1 903 872 9290",
    "sg:postcode":"75110",
    "sg:province":"TX",
    "sg:tags":[
        "toilet"
    ],
    "wof:name":"R E Leaf Environmental Inc",
    "wof:placetype":"venue"
},
  "geometry": {"coordinates":[-96.45432099999999,32.086706],"type":"Point"}
}