{
  "type": "Feature",
  "properties": {
    "iso:country":"US",
    "sg:address":"329 Mack Holliman Dr",
    "sg:city":"Kerrville",
    "sg:classifiers":[
        {
            "category":"Organizations",
            "subcategory":"Professional Association",
            "type":"Services"
        }
    ],
    "sg:phone":"+1 512 495 9769",
    "sg:postcode":"78028",
    "sg:province":"TX",
    "sg:tags":[
        "business",
        "trade"
    ],
    "wof:name":"Automotive Service Assn Of Tx",
    "wof:placetype":"venue"
},
  "geometry": {"coordinates":[-99.12862800000001,30.009021],"type":"Point"}
}