{
  "type": "Feature",
  "properties": {
    "iso:country":"US",
    "sg:address":"14519 Kenny St",
    "sg:city":"Houston",
    "sg:classifiers":[
        {
            "category":"Communications",
            "type":"Services"
        }
    ],
    "sg:phone":"+1 713 451 9990",
    "sg:postcode":"77015",
    "sg:province":"TX",
    "wof:name":"Communications Cable Constr",
    "wof:placetype":"venue"
},
  "geometry": {"coordinates":[-95.164936,29.769845],"type":"Point"}
}