{
  "type": "Feature",
  "properties": {
    "iso:country":"US",
    "sg:address":"5411 Timber Vale St",
    "sg:city":"San Antonio",
    "sg:classifiers":[
        {
            "category":"Building & Trades",
            "subcategory":"Construction",
            "type":"Services"
        }
    ],
    "sg:phone":"+1 830 885 7159",
    "sg:postcode":"78250",
    "sg:province":"TX",
    "sg:tags":[
        "water",
        "well",
        "drilling"
    ],
    "wof:name":"Hopf Well Service",
    "wof:placetype":"venue"
},
  "geometry": {"coordinates":[-98.651146,29.494186],"type":"Point"}
}