{
  "type": "Feature",
  "properties": {
    "iso:country":"US",
    "sg:address":"1018 Sawdust Rd",
    "sg:city":"Spring",
    "sg:classifiers":[
        {
            "category":"Recreation",
            "type":"Entertainment"
        }
    ],
    "sg:phone":"+1 281 292 3397",
    "sg:postcode":"77380",
    "sg:province":"TX",
    "sg:tags":[
        "martial",
        "arts",
        "instruction"
    ],
    "wof:name":"Buke Ryu Karate Jutsu",
    "wof:placetype":"venue"
},
  "geometry": {"coordinates":[-95.46076100000001,30.126922],"type":"Point"}
}