{
  "type": "Feature",
  "properties": {
    "iso:country":"US",
    "sg:address":"4501 E Ben White Boulevard",
    "sg:city":"Austin",
    "sg:classifiers":[
        {
            "category":"Restaurant",
            "type":"Food & Drink"
        }
    ],
    "sg:phone":"+1 512 912 7511",
    "sg:postcode":"78741",
    "sg:province":"TX",
    "wof:name":"McDonald's",
    "wof:placetype":"venue"
},
  "geometry": {"coordinates":[-97.732821,30.214683],"type":"Point"}
}