{
  "type": "Feature",
  "properties": {
    "iso:country":"US",
    "sg:address":"309 N Grant Ave",
    "sg:city":"Odessa",
    "sg:classifiers":[
        {
            "category":"Insurance",
            "subcategory":"Insurance Agent",
            "type":"Services"
        }
    ],
    "sg:phone":"+1 432 337 5323",
    "sg:postcode":"79761",
    "sg:province":"TX",
    "wof:name":"Juan Luna Insurance",
    "wof:placetype":"venue"
},
  "geometry": {"coordinates":[-102.36895,31.847367],"type":"Point"}
}