{
  "type": "Feature",
  "properties": {
    "iso:country":"US",
    "sg:address":"12111 Brittmoore Park Dr",
    "sg:city":"Houston",
    "sg:classifiers":[
        {
            "category":"Manufacturing",
            "subcategory":"Metals",
            "type":"Manufacturing & Wholesale Goods"
        }
    ],
    "sg:phone":"+1 713 983 7253",
    "sg:postcode":"77041",
    "sg:province":"TX",
    "sg:tags":[
        "life",
        "fire",
        "sales",
        "protection",
        "design",
        "safety"
    ],
    "wof:name":"Advantage Interests Inc",
    "wof:placetype":"venue"
},
  "geometry": {"coordinates":[-95.58587,29.855403],"type":"Point"}
}