{
  "type": "Feature",
  "properties": {
    "iso:country":"US",
    "sg:address":"1300 W Peter Smith St",
    "sg:city":"Fort Worth",
    "sg:classifiers":[
        {
            "category":"Professional",
            "subcategory":"Research",
            "type":"Services"
        }
    ],
    "sg:phone":"+1 817 347 5400",
    "sg:postcode":"76104",
    "sg:province":"TX",
    "sg:tags":[
        "commercial",
        "physical"
    ],
    "wof:name":"R & D Department",
    "wof:placetype":"venue"
},
  "geometry": {"coordinates":[-97.34071900000001,32.74001],"type":"Point"}
}