{
  "type": "Feature",
  "properties": {
    "iso:country":"US",
    "sg:address":"233 Post Oak Rd",
    "sg:city":"Inez",
    "sg:classifiers":[
        {
            "category":"Building & Trades",
            "subcategory":"Construction",
            "type":"Services"
        }
    ],
    "sg:phone":"+1 361 576 2959",
    "sg:postcode":"77963",
    "sg:province":"TX",
    "sg:tags":[
        "house"
    ],
    "wof:name":"ORear Construction Inc",
    "wof:placetype":"venue"
},
  "geometry": {"coordinates":[-97.483245,28.773436],"type":"Point"}
}