{
  "type": "Feature",
  "properties": {
    "iso:country":"US",
    "sg:address":"9155 Dyer St",
    "sg:city":"El Paso",
    "sg:classifiers":[
        {
            "category":"Personal",
            "subcategory":"Beauty Salon",
            "type":"Services"
        },
        {
            "category":"Health Services",
            "subcategory":"Doctor",
            "type":"Services"
        }
    ],
    "sg:phone":"+1 915 755 6336",
    "sg:postcode":"79924",
    "sg:province":"TX",
    "sg:tags":[
        "medical"
    ],
    "wof:name":"Mystic Visions Hair Salon",
    "wof:placetype":"venue"
},
  "geometry": {"coordinates":[-106.427336,31.871247],"type":"Point"}
}