{
  "type": "Feature",
  "properties": {
    "iso:country":"US",
    "sg:address":"4440 W John Carpenter Fwy",
    "sg:city":"Irving",
    "sg:classifiers":[
        {
            "category":"Wholesale",
            "subcategory":"Photographic Equipment",
            "type":"Manufacturing & Wholesale Goods"
        },
        {
            "category":"Building & Trades",
            "subcategory":"Equipment Rental",
            "type":"Services"
        }
    ],
    "sg:phone":"+1 972 915 6977",
    "sg:postcode":"75063",
    "sg:province":"TX",
    "sg:tags":[
        "photo",
        "audio",
        "leasing"
    ],
    "wof:name":"Audio Visual Innovations Inc",
    "wof:placetype":"venue"
},
  "geometry": {"coordinates":[-97.0001,32.910083],"type":"Point"}
}