{
  "type": "Feature",
  "properties": {
    "iso:country":"US",
    "sg:address":"2750 S 8th St",
    "sg:city":"Beaumont",
    "sg:classifiers":[
        {
            "category":"Health Services",
            "subcategory":"Hospital",
            "type":"Services"
        },
        {
            "category":"Health Services",
            "subcategory":"Clinic",
            "type":"Services"
        }
    ],
    "sg:phone":"+1 409 839 1083",
    "sg:postcode":"77701",
    "sg:province":"TX",
    "sg:tags":[
        "mental",
        "outpatient",
        "specialty"
    ],
    "wof:name":"Community Psychiatric Center",
    "wof:placetype":"venue"
},
  "geometry": {"coordinates":[-94.124734,30.058471],"type":"Point"}
}