{
  "type": "Feature",
  "properties": {
    "iso:country":"US",
    "sg:address":"335 Holly St",
    "sg:city":"Maud",
    "sg:classifiers":[
        {
            "category":"Professional",
            "subcategory":"Art Services",
            "type":"Services"
        }
    ],
    "sg:phone":"+1 903 293 0296",
    "sg:postcode":"75567",
    "sg:province":"TX",
    "sg:tags":[
        "graphic",
        "designer"
    ],
    "wof:name":"Golden Wolf Productions",
    "wof:placetype":"venue"
},
  "geometry": {"coordinates":[-94.33886800000001,33.325858],"type":"Point"}
}