{
  "type": "Feature",
  "properties": {
    "iso:country":"US",
    "sg:address":"7418 Silver Lake Dr",
    "sg:city":"Rowlett",
    "sg:phone":"+1 972 771 6191",
    "sg:postcode":"75089",
    "sg:province":"TX",
    "sg:website":"http://www.effectivepestcontrol.com",
    "wof:name":"Effective Pest Control Lc",
    "wof:placetype":"venue"
},
  "geometry": {"coordinates":[-96.513853,32.924104],"type":"Point"}
}