{
  "type": "Feature",
  "properties": {
    "iso:country":"US",
    "sg:address":"4607 Green Acres Woods St",
    "sg:city":"San Antonio",
    "sg:classifiers":[
        {
            "category":"Professional",
            "subcategory":"Management & Consulting",
            "type":"Services"
        }
    ],
    "sg:phone":"+1 210 493 5104",
    "sg:postcode":"78249",
    "sg:province":"TX",
    "sg:tags":[
        "business"
    ],
    "wof:name":"Cates Consultants",
    "wof:placetype":"venue"
},
  "geometry": {"coordinates":[-98.574341,29.583808],"type":"Point"}
}