{
  "type": "Feature",
  "properties": {
    "iso:country":"US",
    "sg:address":"4102 Glenrose Dr",
    "sg:city":"Garland",
    "sg:classifiers":[
        {
            "category":"Building & Trades",
            "subcategory":"Construction",
            "type":"Services"
        }
    ],
    "sg:phone":"+1 972 272 0332",
    "sg:postcode":"75042",
    "sg:province":"TX",
    "sg:tags":[
        "roofing",
        "contractor"
    ],
    "wof:name":"L M Roofing",
    "wof:placetype":"venue"
},
  "geometry": {"coordinates":[-96.693753,32.929794],"type":"Point"}
}