{
  "type": "Feature",
  "properties": {
    "iso:country":"US",
    "sg:address":"5902 Sierra Madre",
    "sg:city":"Austin",
    "sg:classifiers":[
        {
            "category":"Wholesale",
            "subcategory":"Wine & Distilled Alcoholic Beverages",
            "type":"Manufacturing & Wholesale Goods"
        }
    ],
    "sg:phone":"+1 512 331 7597",
    "sg:postcode":"78759",
    "sg:province":"TX",
    "wof:name":"Ambassador Brands Inc",
    "wof:placetype":"venue"
},
  "geometry": {"coordinates":[-97.754836,30.419163],"type":"Point"}
}