{
  "type": "Feature",
  "properties": {
    "iso:country":"US",
    "sg:address":"1503 Laurel Dr",
    "sg:city":"Sugar Land",
    "sg:classifiers":[
        {
            "category":"Building & Trades",
            "subcategory":"Cleaning & Sanitation",
            "type":"Services"
        }
    ],
    "sg:phone":"+1 281 545 2442",
    "sg:postcode":"77479",
    "sg:province":"TX",
    "sg:tags":[
        "maintenance"
    ],
    "wof:name":"Emma Lozan Cleaning Services",
    "wof:placetype":"venue"
},
  "geometry": {"coordinates":[-95.691918,29.555188],"type":"Point"}
}