{
  "type": "Feature",
  "properties": {
    "iso:country":"US",
    "sg:address":"1813 W Pioneer Dr",
    "sg:city":"Irving",
    "sg:classifiers":[
        {
            "category":"Travel",
            "subcategory":"Travel Agent",
            "type":"Entertainment"
        }
    ],
    "sg:phone":"+1 972 790 4466",
    "sg:postcode":"75061",
    "sg:province":"TX",
    "sg:tags":[
        "agency"
    ],
    "wof:name":"Source 1 Travel",
    "wof:placetype":"venue"
},
  "geometry": {"coordinates":[-96.969286,32.822502],"type":"Point"}
}