{
  "type": "Feature",
  "properties": {
    "iso:country":"US",
    "sg:address":"2327 Morgan Ln",
    "sg:city":"Ingleside",
    "sg:classifiers":[
        {
            "category":"Professional",
            "subcategory":"Management & Consulting",
            "type":"Services"
        }
    ],
    "sg:phone":"+1 361 776 2912",
    "sg:postcode":"78362",
    "sg:province":"TX",
    "sg:tags":[
        "consultant",
        "safety"
    ],
    "wof:name":"Goodwin Safety Svc Inc",
    "wof:placetype":"venue"
},
  "geometry": {"coordinates":[-97.19768500000001,27.893363],"type":"Point"}
}