{
  "type": "Feature",
  "properties": {
    "iso:country":"US",
    "sg:address":"10720 Preston Rd Ste 1018",
    "sg:city":"Dallas",
    "sg:classifiers":[
        {
            "category":"Cinema",
            "subcategory":"Movie Rental",
            "type":"Entertainment"
        },
        {
            "category":"Shopping",
            "subcategory":"Music",
            "type":"Retail Goods"
        },
        {
            "category":"Shopping",
            "subcategory":"Books",
            "type":"Retail Goods"
        }
    ],
    "sg:phone":"+1 214 363 1977",
    "sg:postcode":"75230",
    "sg:province":"TX",
    "sg:tags":[
        "game",
        "bookstore",
        "video",
        "dvd's"
    ],
    "wof:name":"Borders Books Music & Cafe",
    "wof:placetype":"venue"
},
  "geometry": {"coordinates":[-96.803802,32.8927],"type":"Point"}
}