{
  "type": "Feature",
  "properties": {
    "iso:country":"US",
    "sg:address":"218 Seawall Blvd",
    "sg:city":"Galveston",
    "sg:classifiers":[
        {
            "category":"Professional",
            "type":"Services"
        }
    ],
    "sg:phone":"+1 409 766 7738",
    "sg:postcode":"77550",
    "sg:province":"TX",
    "wof:name":"Palam Annamalai",
    "wof:placetype":"venue"
},
  "geometry": {"coordinates":[-94.767218,29.311416],"type":"Point"}
}