{
  "type": "Feature",
  "properties": {
    "iso:country":"US",
    "sg:address":"1208 State Hwy 110",
    "sg:city":"Whitehouse",
    "sg:classifiers":[
        {
            "category":"Real Estate",
            "subcategory":"Real Estate Agent",
            "type":"Services"
        }
    ],
    "sg:phone":"+1 903 839 7000",
    "sg:postcode":"75791",
    "sg:province":"TX",
    "wof:name":"Gregory Real Estate and Proper",
    "wof:placetype":"venue"
},
  "geometry": {"coordinates":[-95.230272,32.240818],"type":"Point"}
}