{
  "type": "Feature",
  "properties": {
    "iso:country":"US",
    "sg:address":"13201 FM 812",
    "sg:city":"Del Valle",
    "sg:classifiers":[
        {
            "category":"Professional",
            "subcategory":"Research",
            "type":"Services"
        }
    ],
    "sg:phone":"+1 512 243 0821",
    "sg:postcode":"78617",
    "sg:province":"TX",
    "sg:tags":[
        "environmental",
        "ecological"
    ],
    "wof:name":"Allstate Environmental LTD",
    "wof:placetype":"venue"
},
  "geometry": {"coordinates":[-97.641953,30.12739],"type":"Point"}
}