{
  "type": "Feature",
  "properties": {
    "iso:country":"US",
    "sg:address":"15218 Holland Field Cir",
    "sg:city":"Houston",
    "sg:classifiers":[
        {
            "category":"Professional",
            "type":"Services"
        }
    ],
    "sg:phone":"+1 281 463 4450",
    "sg:postcode":"77095",
    "sg:province":"TX",
    "wof:name":"L Gibson",
    "wof:placetype":"venue"
},
  "geometry": {"coordinates":[-95.633002,29.91238],"type":"Point"}
}