{
  "type": "Feature",
  "properties": {
    "iso:country":"US",
    "sg:address":"2511 Sunray Ct",
    "sg:city":"Pearland",
    "sg:classifiers":[
        {
            "category":"Real Estate",
            "subcategory":"Real Estate Agent",
            "type":"Services"
        }
    ],
    "sg:phone":"+1 281 997 3365",
    "sg:postcode":"77584",
    "sg:province":"TX",
    "wof:name":"T & C Enterprises",
    "wof:placetype":"venue"
},
  "geometry": {"coordinates":[-95.363428,29.565078],"type":"Point"}
}