{
  "type": "Feature",
  "properties": {
    "iso:country":"US",
    "sg:address":"1050 Edgebrook Dr Ste 5",
    "sg:city":"Houston",
    "sg:classifiers":[
        {
            "category":"Building & Trades",
            "subcategory":"Locksmith",
            "type":"Services"
        }
    ],
    "sg:phone":"+1 713 941 5397",
    "sg:postcode":"77034",
    "sg:province":"TX",
    "sg:tags":[
        "key"
    ],
    "wof:name":"South Texas Safe & Lock",
    "wof:placetype":"venue"
},
  "geometry": {"coordinates":[-95.2388,29.643499],"type":"Point"}
}