{
  "type": "Feature",
  "properties": {
    "iso:country":"US",
    "sg:address":"1102 FM 1417",
    "sg:city":"Sherman",
    "sg:classifiers":[
        {
            "category":"Manufacturing",
            "subcategory":"Metals",
            "type":"Manufacturing & Wholesale Goods"
        }
    ],
    "sg:phone":"+1 903 891 9022",
    "sg:postcode":"75090",
    "sg:province":"TX",
    "sg:tags":[
        "machine",
        "parts"
    ],
    "sg:website":"www.clayprecision.com",
    "wof:name":"Clay Precision Inc",
    "wof:placetype":"venue"
},
  "geometry": {"coordinates":[-96.59114099999999,33.598299],"type":"Point"}
}