{
  "type": "Feature",
  "properties": {
    "iso:country":"US",
    "sg:address":"7426 Arbor Oaks Dr",
    "sg:city":"Dallas",
    "sg:classifiers":[
        {
            "category":"Utilities",
            "subcategory":"Telephone",
            "type":"Services"
        }
    ],
    "sg:phone":"+1 972 733 0931",
    "sg:postcode":"75248",
    "sg:province":"TX",
    "sg:tags":[
        "communications"
    ],
    "wof:name":"Milliken Group",
    "wof:placetype":"venue"
},
  "geometry": {"coordinates":[-96.781648,32.97563],"type":"Point"}
}