{
  "type": "Feature",
  "properties": {
    "iso:country":"US",
    "sg:address":"6505 Kiowa Ct",
    "sg:city":"Plano",
    "sg:classifiers":[
        {
            "category":"Professional",
            "subcategory":"Computer Services",
            "type":"Services"
        }
    ],
    "sg:phone":"+1 972 527 5401",
    "sg:postcode":"75023",
    "sg:province":"TX",
    "sg:tags":[
        "datum"
    ],
    "wof:name":"Unleash Net Inc",
    "wof:placetype":"venue"
},
  "geometry": {"coordinates":[-96.719795,33.061163],"type":"Point"}
}