{
  "type": "Feature",
  "properties": {
    "iso:country":"US",
    "sg:address":"1306 W Anderson Lane",
    "sg:city":"Austin",
    "sg:classifiers":[
        {
            "category":"Shopping",
            "subcategory":"Jewelry",
            "type":"Retail Goods"
        }
    ],
    "sg:phone":"+1 512 452 8461",
    "sg:postcode":"78757",
    "sg:province":"TX",
    "wof:name":"Bennett's Jewelry",
    "wof:placetype":"venue"
},
  "geometry": {"coordinates":[-97.719262,30.350703],"type":"Point"}
}