{
  "type": "Feature",
  "properties": {
    "iso:country":"US",
    "sg:address":"310 Parramatta Ln",
    "sg:city":"Houston",
    "sg:classifiers":[
        {
            "category":"Education",
            "subcategory":"School",
            "type":"Public Place"
        }
    ],
    "sg:phone":"+1 281 209 2911",
    "sg:postcode":"77073",
    "sg:province":"TX",
    "wof:name":"Al Mustafa Academy",
    "wof:placetype":"venue"
},
  "geometry": {"coordinates":[-95.421948,30.02863],"type":"Point"}
}