{
  "type": "Feature",
  "properties": {
    "iso:country":"US",
    "sg:address":"5720 New Territory Blvd",
    "sg:city":"Sugar Land",
    "sg:classifiers":[
        {
            "category":"Cinema",
            "subcategory":"Movie Rental",
            "type":"Entertainment"
        }
    ],
    "sg:phone":"+1 281 277 2080",
    "sg:postcode":"77479",
    "sg:province":"TX",
    "sg:tags":[
        "video",
        "tape"
    ],
    "wof:name":"Blockbuster",
    "wof:placetype":"venue"
},
  "geometry": {"coordinates":[-95.66144799999999,29.589586],"type":"Point"}
}