{
  "type": "Feature",
  "properties": {
    "iso:country":"US",
    "sg:address":"935 W Parker Rd",
    "sg:city":"Plano",
    "sg:classifiers":[
        {
            "category":"Restaurant",
            "type":"Food & Drink"
        }
    ],
    "sg:menulink":"http://www.allmenus.com/tx/plano/247461-austin-avenue/menu/",
    "sg:phone":"+1 972 422 8003",
    "sg:postcode":"75023",
    "sg:province":"TX",
    "sg:tags":[
        "american"
    ],
    "wof:name":"Austin Avenue",
    "wof:placetype":"venue"
},
  "geometry": {"coordinates":[-96.713393,33.041061],"type":"Point"}
}