{
  "type": "Feature",
  "properties": {
    "iso:country":"US",
    "sg:address":"2024 Fairfield Ct S",
    "sg:city":"League City",
    "sg:classifiers":[
        {
            "category":"Professional",
            "subcategory":"Management & Consulting",
            "type":"Services"
        }
    ],
    "sg:phone":"+1 281 338 1415",
    "sg:postcode":"77573",
    "sg:province":"TX",
    "sg:tags":[
        "business"
    ],
    "wof:name":"Lm King Sales Inc",
    "wof:placetype":"venue"
},
  "geometry": {"coordinates":[-95.11751099999999,29.496338],"type":"Point"}
}