{
  "type": "Feature",
  "properties": {
    "iso:country":"US",
    "sg:address":"12041 State Hwy 364",
    "sg:city":"Tyler",
    "sg:classifiers":[
        {
            "category":"Recreation",
            "type":"Entertainment"
        }
    ],
    "sg:phone":"+1 903 526 2151",
    "sg:postcode":"75709",
    "sg:province":"TX",
    "wof:name":"Classic Batting Cages",
    "wof:placetype":"venue"
},
  "geometry": {"coordinates":[-95.366714,32.310618],"type":"Point"}
}