{
  "type": "Feature",
  "properties": {
    "iso:country":"US",
    "sg:address":"6737 N Park Dr",
    "sg:city":"Fort Worth",
    "sg:classifiers":[
        {
            "category":"Real Estate",
            "subcategory":"Real Estate Agent",
            "type":"Services"
        }
    ],
    "sg:phone":"+1 817 788 2767",
    "sg:postcode":"76180",
    "sg:province":"TX",
    "wof:name":"M&B Aviation Appraisal",
    "wof:placetype":"venue"
},
  "geometry": {"coordinates":[-97.23531800000001,32.885475],"type":"Point"}
}