{
  "type": "Feature",
  "properties": {
    "iso:country":"US",
    "sg:address":"4316 Luella Ave",
    "sg:city":"Deer Park",
    "sg:classifiers":[
        {
            "category":"Organizations",
            "subcategory":"Religious Organization",
            "type":"Services"
        }
    ],
    "sg:phone":"+1 281 930 0856",
    "sg:postcode":"77536",
    "sg:province":"TX",
    "wof:name":"Primera Iglesia Bautista",
    "wof:placetype":"venue"
},
  "geometry": {"coordinates":[-95.113078,29.673331],"type":"Point"}
}