{
  "type": "Feature",
  "properties": {
    "iso:country":"US",
    "sg:address":"2248 N Main St",
    "sg:city":"Pearland",
    "sg:classifiers":[
        {
            "category":"Professional",
            "subcategory":"Business Services",
            "type":"Services"
        }
    ],
    "sg:phone":"+1 281 485 6624",
    "sg:postcode":"77581",
    "sg:province":"TX",
    "sg:tags":[
        "consulting",
        "design",
        "furnishing",
        "interior",
        "home",
        "retail"
    ],
    "wof:name":"Mitchell Designs",
    "wof:placetype":"venue"
},
  "geometry": {"coordinates":[-95.28615600000001,29.566273],"type":"Point"}
}