{
  "type": "Feature",
  "properties": {
    "iso:country":"US",
    "sg:address":"319 N Britain Rd Ste 101",
    "sg:city":"Irving",
    "sg:classifiers":[
        {
            "category":"Retail",
            "subcategory":"Auto Repair",
            "type":"Services"
        }
    ],
    "sg:phone":"+1 972 554 8842",
    "sg:postcode":"75061",
    "sg:province":"TX",
    "wof:name":"Irving Auto Repair",
    "wof:placetype":"venue"
},
  "geometry": {"coordinates":[-96.942497,32.816101],"type":"Point"}
}