{
  "type": "Feature",
  "properties": {
    "iso:country":"US",
    "sg:address":"433 Enke Rd",
    "sg:city":"Goliad",
    "sg:classifiers":[
        {
            "category":"Farming",
            "subcategory":"Livestock Farm",
            "type":"Manufacturing & Wholesale Goods"
        }
    ],
    "sg:phone":"+1 361 645 1991",
    "sg:postcode":"77963",
    "sg:province":"TX",
    "sg:tags":[
        "beef",
        "feedlot",
        "cattle"
    ],
    "wof:name":"Johnson Beefmaster Ranch",
    "wof:placetype":"venue"
},
  "geometry": {"coordinates":[-97.460847,28.800063],"type":"Point"}
}