{
  "type": "Feature",
  "properties": {
    "iso:country":"US",
    "sg:address":"810 Anchor St",
    "sg:city":"Madisonville",
    "sg:classifiers":[
        {
            "category":"Organizations",
            "subcategory":"Religious Organization",
            "type":"Services"
        }
    ],
    "sg:phone":"+1 936 348 2220",
    "sg:postcode":"77864",
    "sg:province":"TX",
    "sg:tags":[
        "church"
    ],
    "wof:name":"Kingdom Hall-Jehovah's Witness",
    "wof:placetype":"venue"
},
  "geometry": {"coordinates":[-95.904963,30.951487],"type":"Point"}
}