{
  "type": "Feature",
  "properties": {
    "iso:country":"US",
    "sg:address":"104 Pine Ridge Cir",
    "sg:city":"Sherman",
    "sg:classifiers":[
        {
            "category":"Shopping",
            "subcategory":"Computers & Home Electronics",
            "type":"Retail Goods"
        }
    ],
    "sg:phone":"+1 903 893 5575",
    "sg:postcode":"75092",
    "sg:province":"TX",
    "sg:tags":[
        "recorder",
        "time"
    ],
    "wof:name":"Red River Time Clock Co",
    "wof:placetype":"venue"
},
  "geometry": {"coordinates":[-96.683947,33.627268],"type":"Point"}
}