{
  "type": "Feature",
  "properties": {
    "iso:country":"US",
    "sg:address":"441 Railroad St",
    "sg:city":"Maxwell",
    "sg:classifiers":[
        {
            "category":"Manufacturing",
            "subcategory":"Building Materials",
            "type":"Manufacturing & Wholesale Goods"
        }
    ],
    "sg:phone":"+1 512 357 2773",
    "sg:postcode":"78656",
    "sg:province":"TX",
    "sg:tags":[
        "lumber",
        "truss"
    ],
    "wof:name":"National Truss",
    "wof:placetype":"venue"
},
  "geometry": {"coordinates":[-97.79040999999999,29.881207],"type":"Point"}
}