{
  "type": "Feature",
  "properties": {
    "iso:country":"US",
    "sg:address":"224 Summit Rd",
    "sg:city":"Mineral Wells",
    "sg:classifiers":[
        {
            "category":"Shopping",
            "subcategory":"Bicycles & Sporting Goods",
            "type":"Retail Goods"
        }
    ],
    "sg:phone":"+1 940 325 8540",
    "sg:postcode":"76067",
    "sg:province":"TX",
    "wof:name":"Larry Carstens",
    "wof:placetype":"venue"
},
  "geometry": {"coordinates":[-98.09173800000001,32.76976],"type":"Point"}
}