{
  "type": "Feature",
  "properties": {
    "iso:country":"US",
    "sg:address":"401 S 77 Sunshine Strip Ste D",
    "sg:city":"Harlingen",
    "sg:classifiers":[
        {
            "category":"Health Services",
            "subcategory":"Doctor",
            "type":"Services"
        },
        {
            "category":"Professional",
            "subcategory":"Testing Lab",
            "type":"Services"
        },
        {
            "category":"Health Services",
            "subcategory":"Medical Lab",
            "type":"Services"
        }
    ],
    "sg:phone":"+1 956 440 0700",
    "sg:postcode":"78550",
    "sg:province":"TX",
    "sg:tags":[
        "laboratories-pathological",
        "physician",
        "surgeons",
        "analytical",
        "laboratory",
        "pathology"
    ],
    "wof:name":"Clinical Pathology Laboratories Inc",
    "wof:placetype":"venue"
},
  "geometry": {"coordinates":[-97.68006099999999,26.195641],"type":"Point"}
}