{
  "type": "Feature",
  "properties": {
    "iso:country":"US",
    "sg:address":"6014 Homestead Rd",
    "sg:city":"Rosenberg",
    "sg:classifiers":[
        {
            "category":"Building & Trades",
            "subcategory":"Construction",
            "type":"Services"
        }
    ],
    "sg:phone":"+1 281 342 7648",
    "sg:postcode":"77471",
    "sg:province":"TX",
    "sg:tags":[
        "painter"
    ],
    "wof:name":"Lynn Pipkin Paint Co",
    "wof:placetype":"venue"
},
  "geometry": {"coordinates":[-95.768505,29.543726],"type":"Point"}
}