{
  "type": "Feature",
  "properties": {
    "iso:country":"US",
    "sg:address":"2501 W Parmer Ln Ste 900",
    "sg:city":"Austin",
    "sg:classifiers":[
        {
            "category":"Restaurant",
            "type":"Food & Drink"
        }
    ],
    "sg:phone":"+1 512 821 2307",
    "sg:postcode":"78727",
    "sg:province":"TX",
    "sg:tags":[
        "chinese"
    ],
    "sg:website":"www.pandaexpress.com",
    "wof:name":"Panda Express",
    "wof:placetype":"venue"
},
  "geometry": {"coordinates":[-97.70174799999999,30.41849],"type":"Point"}
}