{
  "type": "Feature",
  "properties": {
    "iso:country":"US",
    "sg:address":"29 Pinewood Cir",
    "sg:city":"Houston",
    "sg:classifiers":[
        {
            "category":"Professional",
            "subcategory":"Management & Consulting",
            "type":"Services"
        }
    ],
    "sg:phone":"+1 281 362 8161",
    "sg:postcode":"77024",
    "sg:province":"TX",
    "sg:tags":[
        "business"
    ],
    "wof:name":"Building Air Quality",
    "wof:placetype":"venue"
},
  "geometry": {"coordinates":[-95.500244,29.76551],"type":"Point"}
}