{
  "type": "Feature",
  "properties": {
    "iso:country":"US",
    "sg:address":"100 W Pflugerville Loop",
    "sg:city":"Pflugerville",
    "sg:classifiers":[
        {
            "category":"Building & Trades",
            "subcategory":"Construction",
            "type":"Services"
        }
    ],
    "sg:phone":"+1 512 252 2494",
    "sg:postcode":"78660",
    "sg:province":"TX",
    "sg:tags":[
        "fire",
        "restoration",
        "damage"
    ],
    "wof:name":"Signature Professional Clnng",
    "wof:placetype":"venue"
},
  "geometry": {"coordinates":[-97.625874,30.464274],"type":"Point"}
}