{
  "type": "Feature",
  "properties": {
    "iso:country":"US",
    "sg:address":"1330 W Taylor St",
    "sg:city":"Sherman",
    "sg:classifiers":[
        {
            "category":"Restaurant",
            "type":"Food & Drink"
        }
    ],
    "sg:phone":"+1 903 814 0007",
    "sg:postcode":"75092",
    "sg:province":"TX",
    "wof:name":"A R Enterprises",
    "wof:placetype":"venue"
},
  "geometry": {"coordinates":[-96.630805,33.651636],"type":"Point"}
}