{
  "type": "Feature",
  "properties": {
    "iso:country":"US",
    "sg:address":"1711 S Colorado St",
    "sg:city":"Lockhart",
    "sg:classifiers":[
        {
            "category":"Recreation",
            "type":"Entertainment"
        }
    ],
    "sg:phone":"+1 512 398 5425",
    "sg:postcode":"78644",
    "sg:province":"TX",
    "wof:name":"Champion Tae KWON Do",
    "wof:placetype":"venue"
},
  "geometry": {"coordinates":[-97.668626,29.863165],"type":"Point"}
}