{
  "type": "Feature",
  "properties": {
    "iso:country":"US",
    "sg:address":"5605 Bellaire Blvd",
    "sg:city":"Houston",
    "sg:classifiers":[
        {
            "category":"Fast Food",
            "type":"Food & Drink"
        }
    ],
    "sg:phone":"+1 713 395 0990",
    "sg:postcode":"77081",
    "sg:province":"TX",
    "sg:tags":[
        "chicken",
        "wing"
    ],
    "sg:website":"www.campero.com/index_eng_flash.php",
    "wof:name":"Pollo Campero",
    "wof:placetype":"venue"
},
  "geometry": {"coordinates":[-95.47869900000001,29.7054],"type":"Point"}
}