{
  "type": "Feature",
  "properties": {
    "iso:country":"US",
    "sg:address":"6221 N O Connor Blvd",
    "sg:city":"Irving",
    "sg:classifiers":[
        {
            "category":"Wholesale",
            "subcategory":"Motor Vehicles",
            "type":"Manufacturing & Wholesale Goods"
        }
    ],
    "sg:phone":"+1 972 869 2777",
    "sg:postcode":"75039",
    "sg:province":"TX",
    "sg:tags":[
        "automobile",
        "truck",
        "broker"
    ],
    "wof:name":"Redden Group/Mark Vii",
    "wof:placetype":"venue"
},
  "geometry": {"coordinates":[-96.935964,32.89077],"type":"Point"}
}