{
  "type": "Feature",
  "properties": {
    "iso:country":"US",
    "sg:address":"5723 Stewart Ave",
    "sg:city":"Galveston",
    "sg:classifiers":[
        {
            "category":"Wholesale",
            "subcategory":"Sporting Goods",
            "type":"Manufacturing & Wholesale Goods"
        }
    ],
    "sg:phone":"+1 409 744 9900",
    "sg:postcode":"77551",
    "sg:province":"TX",
    "sg:tags":[
        "equipment",
        "pool",
        "swimming"
    ],
    "wof:name":"Gautier Pools & Spas",
    "wof:placetype":"venue"
},
  "geometry": {"coordinates":[-94.83026700000001,29.283543],"type":"Point"}
}