{
  "type": "Feature",
  "properties": {
    "iso:country":"US",
    "sg:address":"4111 Herschel Ave",
    "sg:city":"Dallas",
    "sg:classifiers":[
        {
            "category":"Professional",
            "subcategory":"Management & Consulting",
            "type":"Services"
        }
    ],
    "sg:phone":"+1 214 443 9047",
    "sg:postcode":"75219",
    "sg:province":"TX",
    "wof:name":"Fas Construction Management In",
    "wof:placetype":"venue"
},
  "geometry": {"coordinates":[-96.804733,32.820767],"type":"Point"}
}