{
  "type": "Feature",
  "properties": {
    "iso:country":"US",
    "sg:address":"2133 Tampico Dr",
    "sg:city":"Carrollton",
    "sg:classifiers":[
        {
            "category":"Building & Trades",
            "subcategory":"Construction",
            "type":"Services"
        }
    ],
    "sg:phone":"+1 972 245 3420",
    "sg:postcode":"75006",
    "sg:province":"TX",
    "sg:tags":[
        "painter"
    ],
    "wof:name":"Migon's Finishes",
    "wof:placetype":"venue"
},
  "geometry": {"coordinates":[-96.88014099999999,32.982826],"type":"Point"}
}