{
  "type": "Feature",
  "properties": {
    "iso:country":"US",
    "sg:address":"6619 Lovington Dr",
    "sg:city":"Dallas",
    "sg:classifiers":[
        {
            "category":"Health Services",
            "subcategory":"Optometrist",
            "type":"Services"
        }
    ],
    "sg:phone":"+1 972 867 4324",
    "sg:postcode":"75252",
    "sg:province":"TX",
    "wof:name":"Sparks Jeryl L OD",
    "wof:placetype":"venue"
},
  "geometry": {"coordinates":[-96.789101,33.0033],"type":"Point"}
}