{
  "type": "Feature",
  "properties": {
    "iso:country":"US",
    "sg:address":"4978 Onion Rd",
    "sg:city":"Killeen",
    "sg:classifiers":[
        {
            "category":"Building & Trades",
            "subcategory":"Construction",
            "type":"Services"
        }
    ],
    "sg:phone":"+1 254 554 8565",
    "sg:postcode":"76542",
    "sg:province":"TX",
    "sg:tags":[
        "house"
    ],
    "wof:name":"Caesar Cobb",
    "wof:placetype":"venue"
},
  "geometry": {"coordinates":[-97.72265400000001,31.061321],"type":"Point"}
}