{
  "type": "Feature",
  "properties": {
    "iso:country":"US",
    "sg:address":"809 S Dallas St",
    "sg:city":"Ennis",
    "sg:classifiers":[
        {
            "category":"Retail",
            "subcategory":"Auto Repair",
            "type":"Services"
        }
    ],
    "sg:phone":"+1 972 875 2420",
    "sg:postcode":"75119",
    "sg:province":"TX",
    "sg:tags":[
        "tire"
    ],
    "wof:name":"Rudys Tires & Wheels",
    "wof:placetype":"venue"
},
  "geometry": {"coordinates":[-96.62373700000001,32.320923],"type":"Point"}
}