{
  "type": "Feature",
  "properties": {
    "iso:country":"US",
    "sg:address":"21738 Maple Bluff Dr",
    "sg:city":"Katy",
    "sg:classifiers":[
        {
            "category":"Building & Trades",
            "subcategory":"Landscaping Services",
            "type":"Services"
        }
    ],
    "sg:phone":"+1 281 859 4112",
    "sg:postcode":"77449",
    "sg:province":"TX",
    "wof:name":"Great American Lawn Care",
    "wof:placetype":"venue"
},
  "geometry": {"coordinates":[-95.730823,29.847086],"type":"Point"}
}