{
  "type": "Feature",
  "properties": {
    "iso:country":"US",
    "sg:address":"5223 1/2 Bellaire Blvd",
    "sg:city":"Bellaire",
    "sg:classifiers":[
        {
            "category":"Health Services",
            "subcategory":"Optometrist",
            "type":"Services"
        }
    ],
    "sg:phone":"+1 713 666 8636",
    "sg:postcode":"77401",
    "sg:province":"TX",
    "wof:name":"Days Optical",
    "wof:placetype":"venue"
},
  "geometry": {"coordinates":[-95.47075599999999,29.705559],"type":"Point"}
}