{
  "type": "Feature",
  "properties": {
    "iso:country":"US",
    "sg:address":"1823 Emerald Bay Dr",
    "sg:city":"Rockwall",
    "sg:classifiers":[
        {
            "category":"Shopping",
            "subcategory":"Catalog Store",
            "type":"Retail Goods"
        }
    ],
    "sg:phone":"+1 972 772 4326",
    "sg:postcode":"75087",
    "sg:province":"TX",
    "sg:tags":[
        "mail",
        "house"
    ],
    "wof:name":"Design Services",
    "wof:placetype":"venue"
},
  "geometry": {"coordinates":[-96.481314,32.941624],"type":"Point"}
}