{
  "type": "Feature",
  "properties": {
    "iso:country":"US",
    "sg:address":"210 E Duncan Ave",
    "sg:city":"Mertzon",
    "sg:classifiers":[
        {
            "category":"Food & Beverages",
            "subcategory":"Bakery",
            "type":"Retail Goods"
        }
    ],
    "sg:phone":"+1 325 632 2904",
    "sg:postcode":"76941",
    "sg:province":"TX",
    "wof:name":"Baker R US",
    "wof:placetype":"venue"
},
  "geometry": {"coordinates":[-100.816209,31.263088],"type":"Point"}
}