{
  "type": "Feature",
  "properties": {
    "iso:country":"US",
    "sg:address":"503 E 1st St",
    "sg:city":"Dumas",
    "sg:classifiers":[
        {
            "category":"Manufacturing",
            "subcategory":"Buildings",
            "type":"Manufacturing & Wholesale Goods"
        },
        {
            "category":"Building & Trades",
            "subcategory":"Construction",
            "type":"Services"
        }
    ],
    "sg:phone":"+1 806 935 6951",
    "sg:postcode":"79029",
    "sg:province":"TX",
    "sg:tags":[
        "home",
        "builder",
        "industrial",
        "contractors-commercial",
        "contractor"
    ],
    "wof:name":"Willis Construction",
    "wof:placetype":"venue"
},
  "geometry": {"coordinates":[-101.967067,35.865356],"type":"Point"}
}