{
  "type": "Feature",
  "properties": {
    "iso:country":"US",
    "sg:address":"440 Black Oak Ln",
    "sg:city":"Burleson",
    "sg:classifiers":[
        {
            "category":"Shopping",
            "subcategory":"Computers & Home Electronics",
            "type":"Retail Goods"
        }
    ],
    "sg:phone":"+1 817 426 2630",
    "sg:postcode":"76028",
    "sg:province":"TX",
    "sg:tags":[
        "equipment",
        "satellite",
        "system"
    ],
    "wof:name":"DSS Sales & Svc",
    "wof:placetype":"venue"
},
  "geometry": {"coordinates":[-97.299083,32.535004],"type":"Point"}
}