{
  "type": "Feature",
  "properties": {
    "iso:country":"US",
    "sg:address":"1043 Hickory Creek Rd",
    "sg:city":"Denton",
    "sg:classifiers":[
        {
            "category":"Fast Food",
            "type":"Food & Drink"
        },
        {
            "category":"Restaurant",
            "type":"Food & Drink"
        },
        {
            "category":"Professional",
            "type":"Services"
        }
    ],
    "sg:phone":"+1 940 321 1226",
    "sg:postcode":"76210",
    "sg:province":"TX",
    "sg:tags":[
        "delivery",
        "take",
        "pizza"
    ],
    "sg:website":"http://www.dominospizza.com",
    "wof:name":"Domino's Pizza",
    "wof:placetype":"venue"
},
  "geometry": {"coordinates":[-97.127049,33.147102],"type":"Point"}
}