{
  "type": "Feature",
  "properties": {
    "iso:country":"US",
    "sg:address":"531 E Parker Rd",
    "sg:city":"Houston",
    "sg:classifiers":[
        {
            "category":"Retail",
            "subcategory":"Self-service Laundry",
            "type":"Services"
        }
    ],
    "sg:phone":"+1 713 695 3233",
    "sg:postcode":"77076",
    "sg:province":"TX",
    "sg:tags":[
        "equipment"
    ],
    "wof:name":"Gracious Washatier",
    "wof:placetype":"venue"
},
  "geometry": {"coordinates":[-95.391699,29.859725],"type":"Point"}
}