{
  "type": "Feature",
  "properties": {
    "iso:country":"US",
    "sg:address":"330 Cantwell Ln",
    "sg:city":"Corpus Christi",
    "sg:classifiers":[
        {
            "category":"Wholesale",
            "subcategory":"Meat",
            "type":"Manufacturing & Wholesale Goods"
        }
    ],
    "sg:phone":"+1 361 882 1396",
    "sg:postcode":"78408",
    "sg:province":"TX",
    "wof:name":"L & D Meat Wholesale Co",
    "wof:placetype":"venue"
},
  "geometry": {"coordinates":[-97.451195,27.792704],"type":"Point"}
}