{
  "type": "Feature",
  "properties": {
    "iso:country":"US",
    "sg:address":"3003 Seevers Ave",
    "sg:city":"Dallas",
    "sg:classifiers":[
        {
            "category":"Organizations",
            "subcategory":"Religious Organization",
            "type":"Services"
        }
    ],
    "sg:phone":"+1 214 943 9933",
    "sg:postcode":"75216",
    "sg:province":"TX",
    "wof:name":"Agape Temple of Deliverance Church",
    "wof:placetype":"venue"
},
  "geometry": {"coordinates":[-96.821701,32.709099],"type":"Point"}
}