{
  "type": "Feature",
  "properties": {
    "iso:country":"US",
    "sg:address":"413 N 25 Mile Ave",
    "sg:city":"Hereford",
    "sg:classifiers":[
        {
            "category":"Autos & Motor Vehicles",
            "subcategory":"Automobile Sales",
            "type":"Retail Goods"
        }
    ],
    "sg:phone":"+1 806 364 3565",
    "sg:postcode":"79045",
    "sg:province":"TX",
    "sg:tags":[
        "used"
    ],
    "wof:name":"Marcum Motors Co",
    "wof:placetype":"venue"
},
  "geometry": {"coordinates":[-102.40551000000001,34.832674],"type":"Point"}
}