{
  "type": "Feature",
  "properties": {
    "iso:country":"US",
    "sg:address":"2013 Huldy St",
    "sg:city":"Houston",
    "sg:classifiers":[
        {
            "category":"Utilities",
            "subcategory":"Fuel Oil & Lpg",
            "type":"Services"
        }
    ],
    "sg:phone":"+1 713 527 0562",
    "sg:postcode":"77019",
    "sg:province":"TX",
    "sg:tags":[
        "consultant",
        "petroleum"
    ],
    "wof:name":"Petromation",
    "wof:placetype":"venue"
},
  "geometry": {"coordinates":[-95.40976499999999,29.747981],"type":"Point"}
}