{
  "type": "Feature",
  "properties": {
    "iso:country":"US",
    "sg:address":"410 N Guadalupe St",
    "sg:city":"Seguin",
    "sg:classifiers":[
        {
            "category":"Organizations",
            "subcategory":"Religious Organization",
            "type":"Services"
        }
    ],
    "sg:phone":"+1 830 379 9023",
    "sg:postcode":"78155",
    "sg:province":"TX",
    "sg:tags":[
        "church"
    ],
    "wof:name":"Refuge Church Of Christ",
    "wof:placetype":"venue"
},
  "geometry": {"coordinates":[-97.96955699999999,29.572377],"type":"Point"}
}