{
  "type": "Feature",
  "properties": {
    "iso:country":"US",
    "sg:address":"412 Buffalo St",
    "sg:city":"Gilmer",
    "sg:classifiers":[
        {
            "category":"Social Services",
            "type":"Services"
        }
    ],
    "sg:phone":"+1 903 843 1185",
    "sg:postcode":"75644",
    "sg:province":"TX",
    "wof:name":"James Idol",
    "wof:placetype":"venue"
},
  "geometry": {"coordinates":[-94.94861299999999,32.72985],"type":"Point"}
}