{
  "type": "Feature",
  "properties": {
    "iso:country":"US",
    "sg:address":"1613 Harvest Glen Dr",
    "sg:city":"Allen",
    "sg:classifiers":[
        {
            "category":"Arts & Performance",
            "subcategory":"Theater",
            "type":"Entertainment"
        }
    ],
    "sg:phone":"+1 972 549 0212",
    "sg:postcode":"75002",
    "sg:province":"TX",
    "sg:tags":[
        "group"
    ],
    "wof:name":"Gospel Messengers Inc",
    "wof:placetype":"venue"
},
  "geometry": {"coordinates":[-96.626614,33.120767],"type":"Point"}
}