{
  "type": "Feature",
  "properties": {
    "iso:country":"US",
    "sg:address":"3808 W Wall St",
    "sg:city":"Midland",
    "sg:classifiers":[
        {
            "category":"Travel",
            "subcategory":"Hotels & Motels",
            "type":"Entertainment"
        }
    ],
    "sg:phone":"+1 432 694 2576",
    "sg:postcode":"79703",
    "sg:province":"TX",
    "sg:tags":[
        "operation"
    ],
    "wof:name":"West Wind Motel Inc",
    "wof:placetype":"venue"
},
  "geometry": {"coordinates":[-102.116277,31.976273],"type":"Point"}
}