{
  "type": "Feature",
  "properties": {
    "iso:country":"US",
    "sg:address":"13103 High Star Dr",
    "sg:city":"Houston",
    "sg:classifiers":[
        {
            "category":"Retail",
            "subcategory":"Car Wash",
            "type":"Services"
        }
    ],
    "sg:phone":"+1 281 575 0806",
    "sg:postcode":"77072",
    "sg:province":"TX",
    "sg:tags":[
        "carwash"
    ],
    "wof:name":"Advanced Steel Detailing",
    "wof:placetype":"venue"
},
  "geometry": {"coordinates":[-95.6127,29.710555],"type":"Point"}
}