{
  "type": "Feature",
  "properties": {
    "iso:country":"US",
    "sg:address":"3201 Hulen St",
    "sg:city":"Fort Worth",
    "sg:classifiers":[
        {
            "category":"Real Estate",
            "subcategory":"Real Estate Agent",
            "type":"Services"
        }
    ],
    "sg:phone":"+1 817 731 3733",
    "sg:postcode":"76107",
    "sg:province":"TX",
    "wof:name":"Hotchkiss Family RE Ltd Par",
    "wof:placetype":"venue"
},
  "geometry": {"coordinates":[-97.38784699999999,32.728139],"type":"Point"}
}