{
  "type": "Feature",
  "properties": {
    "iso:country":"US",
    "sg:address":"4401 Brair Hollow Dr",
    "sg:city":"Plano",
    "sg:classifiers":[
        {
            "category":"Wholesale",
            "subcategory":"Computers",
            "type":"Manufacturing & Wholesale Goods"
        }
    ],
    "sg:phone":"+1 972 896 3000",
    "sg:postcode":"75093",
    "sg:province":"TX",
    "wof:name":"Sterling Technologies Inc",
    "wof:placetype":"venue"
},
  "geometry": {"coordinates":[-96.77955799999999,33.041323],"type":"Point"}
}