{
  "type": "Feature",
  "properties": {
    "iso:country":"US",
    "sg:address":"1718 College St",
    "sg:city":"Houston",
    "sg:classifiers":[
        {
            "category":"Retail",
            "subcategory":"Auto Repair",
            "type":"Services"
        }
    ],
    "sg:phone":"+1 713 943 1200",
    "sg:postcode":"77017",
    "sg:province":"TX",
    "sg:tags":[
        "transmission"
    ],
    "wof:name":"Kastl Transmissions",
    "wof:placetype":"venue"
},
  "geometry": {"coordinates":[-95.249467,29.653016],"type":"Point"}
}