{
  "type": "Feature",
  "properties": {
    "iso:country":"US",
    "sg:address":"4218 Winchester Ave",
    "sg:city":"Odessa",
    "sg:classifiers":[
        {
            "category":"Personal",
            "type":"Services"
        }
    ],
    "sg:phone":"+1 432 362 5945",
    "sg:postcode":"79762",
    "sg:province":"TX",
    "wof:name":"Dan The Handyman Can",
    "wof:placetype":"venue"
},
  "geometry": {"coordinates":[-102.362331,31.887304],"type":"Point"}
}