{
  "type": "Feature",
  "properties": {
    "iso:country":"US",
    "sg:address":"700 Durham Dr",
    "sg:city":"Houston",
    "sg:classifiers":[
        {
            "category":"Restaurant",
            "type":"Food & Drink"
        }
    ],
    "sg:phone":"+1 713 426 1171",
    "sg:postcode":"77007",
    "sg:province":"TX",
    "sg:tags":[
        "new",
        "american"
    ],
    "sg:website":"www.district7grill.com",
    "wof:name":"Table 7 Restaurant",
    "wof:placetype":"venue"
},
  "geometry": {"coordinates":[-95.410554,29.768258],"type":"Point"}
}