{
  "type": "Feature",
  "properties": {
    "iso:country":"US",
    "sg:address":"2735 Simondale Dr",
    "sg:city":"Fort Worth",
    "sg:classifiers":[
        {
            "category":"Professional",
            "subcategory":"Management & Consulting",
            "type":"Services"
        }
    ],
    "sg:phone":"+1 817 922 8900",
    "sg:postcode":"76109",
    "sg:province":"TX",
    "wof:name":"Charles M Brosseau",
    "wof:placetype":"venue"
},
  "geometry": {"coordinates":[-97.37231199999999,32.712685],"type":"Point"}
}