{
  "type": "Feature",
  "properties": {
    "iso:country":"US",
    "sg:address":"1900 Kenley St",
    "sg:city":"Fort Worth",
    "sg:classifiers":[
        {
            "category":"Building & Trades",
            "subcategory":"Cleaning & Sanitation",
            "type":"Services"
        }
    ],
    "sg:phone":"+1 817 732 2970",
    "sg:postcode":"76107",
    "sg:province":"TX",
    "sg:tags":[
        "ventilating",
        "system"
    ],
    "wof:name":"New Air Solutions",
    "wof:placetype":"venue"
},
  "geometry": {"coordinates":[-97.389456,32.74051],"type":"Point"}
}