{
  "type": "Feature",
  "properties": {
    "iso:country":"US",
    "sg:address":"8000 Bent Branch Dr",
    "sg:city":"Irving",
    "sg:classifiers":[
        {
            "category":"Professional",
            "subcategory":"Computer Services",
            "type":"Services"
        }
    ],
    "sg:phone":"+1 972 402 5000",
    "sg:postcode":"75063",
    "sg:province":"TX",
    "sg:tags":[
        "management",
        "facility"
    ],
    "wof:name":"IBM",
    "wof:placetype":"venue"
},
  "geometry": {"coordinates":[-96.98943,32.915576],"type":"Point"}
}