{
  "type": "Feature",
  "properties": {
    "iso:country":"US",
    "sg:address":"2233 N Prairie Creek Rd",
    "sg:city":"Dallas",
    "sg:classifiers":[
        {
            "category":"Professional",
            "type":"Services"
        }
    ],
    "sg:phone":"+1 214 388 4955",
    "sg:postcode":"75227",
    "sg:province":"TX",
    "sg:tags":[
        "establishment"
    ],
    "wof:name":"Gold & Jade House",
    "wof:placetype":"venue"
},
  "geometry": {"coordinates":[-96.66555,32.749771],"type":"Point"}
}