{
  "type": "Feature",
  "properties": {
    "iso:country":"US",
    "sg:address":"9501 Beechnut St",
    "sg:city":"Houston",
    "sg:classifiers":[
        {
            "category":"Professional",
            "type":"Services"
        }
    ],
    "sg:phone":"+1 713 988 2238",
    "sg:postcode":"77036",
    "sg:province":"TX",
    "wof:name":"Lilies & Brambles",
    "wof:placetype":"venue"
},
  "geometry": {"coordinates":[-95.548547,29.690467],"type":"Point"}
}