{
  "type": "Feature",
  "properties": {
    "iso:country":"US",
    "sg:address":"1909 US Hwy 281",
    "sg:city":"Marble Falls",
    "sg:classifiers":[
        {
            "category":"Retail",
            "subcategory":"Veterinary Services",
            "type":"Services"
        }
    ],
    "sg:phone":"+1 830 693 7561",
    "sg:postcode":"78654",
    "sg:province":"TX",
    "sg:tags":[
        "hospital",
        "animal"
    ],
    "wof:name":"Marble Falls Veterinary Clinic",
    "wof:placetype":"venue"
},
  "geometry": {"coordinates":[-98.286331,30.525034],"type":"Point"}
}