{
  "type": "Feature",
  "properties": {
    "iso:country":"US",
    "sg:address":"1003 S Elm St",
    "sg:city":"Ennis",
    "sg:classifiers":[
        {
            "category":"Building & Trades",
            "subcategory":"Construction",
            "type":"Services"
        }
    ],
    "sg:phone":"+1 972 878 4272",
    "sg:postcode":"75119",
    "sg:province":"TX",
    "sg:tags":[
        "house"
    ],
    "wof:name":"Kevin Berk Construction",
    "wof:placetype":"venue"
},
  "geometry": {"coordinates":[-96.612728,32.322796],"type":"Point"}
}