{
  "type": "Feature",
  "properties": {
    "iso:country":"US",
    "sg:address":"116 Austin Ave",
    "sg:city":"Lamesa",
    "sg:classifiers":[
        {
            "category":"Shopping",
            "subcategory":"Gifts & Souvenirs",
            "type":"Retail Goods"
        }
    ],
    "sg:phone":"+1 806 872 0835",
    "sg:postcode":"79331",
    "sg:province":"TX",
    "wof:name":"Peggy Barron Mi-Mis Attic",
    "wof:placetype":"venue"
},
  "geometry": {"coordinates":[-101.95303800000001,32.732758],"type":"Point"}
}