{
  "type": "Feature",
  "properties": {
    "iso:country":"US",
    "sg:address":"3309 Mulberry St",
    "sg:city":"Victoria",
    "sg:classifiers":[
        {
            "category":"Manufacturing",
            "subcategory":"Tools & Machinery",
            "type":"Manufacturing & Wholesale Goods"
        }
    ],
    "sg:phone":"+1 361 578 5209",
    "sg:postcode":"77901",
    "sg:province":"TX",
    "sg:tags":[
        "machine",
        "shop"
    ],
    "wof:name":"Pawlik Enterprises Inc",
    "wof:placetype":"venue"
},
  "geometry": {"coordinates":[-96.96872999999999,28.816459],"type":"Point"}
}