{
  "type": "Feature",
  "properties": {
    "iso:country":"US",
    "sg:address":"22814 Braken Manor Ln",
    "sg:city":"Katy",
    "sg:classifiers":[
        {
            "category":"Retail",
            "subcategory":"Portrait Studio",
            "type":"Services"
        }
    ],
    "sg:phone":"+1 281 347 3730",
    "sg:postcode":"77449",
    "sg:province":"TX",
    "sg:tags":[
        "photo"
    ],
    "wof:name":"Fahey Photos",
    "wof:placetype":"venue"
},
  "geometry": {"coordinates":[-95.766932,29.8098],"type":"Point"}
}