{
  "type": "Feature",
  "properties": {
    "iso:country":"US",
    "sg:address":"603 Rustic Ln",
    "sg:city":"Friendswood",
    "sg:classifiers":[
        {
            "category":"Professional",
            "subcategory":"Management & Consulting",
            "type":"Services"
        }
    ],
    "sg:phone":"+1 281 993 1644",
    "sg:postcode":"77546",
    "sg:province":"TX",
    "sg:tags":[
        "business"
    ],
    "wof:name":"4k Petroleum Services LLC",
    "wof:placetype":"venue"
},
  "geometry": {"coordinates":[-95.229641,29.533115],"type":"Point"}
}