{
  "type": "Feature",
  "properties": {
    "iso:country":"US",
    "sg:address":"917 N Hampton Rd Ste 231",
    "sg:city":"Desoto",
    "sg:classifiers":[
        {
            "category":"Personal",
            "subcategory":"Barber",
            "type":"Services"
        }
    ],
    "sg:phone":"+1 972 223 3104",
    "sg:postcode":"75115",
    "sg:province":"TX",
    "wof:name":"All Star Barber Shop",
    "wof:placetype":"venue"
},
  "geometry": {"coordinates":[-96.85808,32.605419],"type":"Point"}
}