{
  "type": "Feature",
  "properties": {
    "iso:country":"US",
    "sg:address":"259 Keim Rd",
    "sg:city":"Eddy",
    "sg:classifiers":[
        {
            "category":"Freight",
            "type":"Transportation"
        }
    ],
    "sg:phone":"+1 254 859 5795",
    "sg:postcode":"76524",
    "sg:province":"TX",
    "sg:tags":[
        "operator",
        "local",
        "trucking"
    ],
    "wof:name":"Ramon V Garza Trucking",
    "wof:placetype":"venue"
},
  "geometry": {"coordinates":[-97.287299,31.289355],"type":"Point"}
}