{
  "type": "Feature",
  "properties": {
    "iso:country":"US",
    "sg:address":"11006 Janet Lee Dr",
    "sg:city":"San Antonio",
    "sg:classifiers":[
        {
            "category":"Professional",
            "subcategory":"Management & Consulting",
            "type":"Services"
        }
    ],
    "sg:phone":"+1 210 344 9727",
    "sg:postcode":"78230",
    "sg:province":"TX",
    "sg:tags":[
        "business"
    ],
    "wof:name":"K & P Tutors",
    "wof:placetype":"venue"
},
  "geometry": {"coordinates":[-98.534885,29.540323],"type":"Point"}
}