{
  "type": "Feature",
  "properties": {
    "iso:country":"US",
    "sg:address":"801 W 38th St Suite 110",
    "sg:city":"Austin",
    "sg:phone":"+1 512 897 1233",
    "sg:postcode":"78705",
    "sg:province":"TX",
    "wof:name":"Compassionate Beans Espresso & Smoothie Bar",
    "wof:placetype":"venue"
},
  "geometry": {"coordinates":[-97.74176799999999,30.304569],"type":"Point"}
}