{
  "type": "Feature",
  "properties": {
    "iso:country":"US",
    "sg:address":"2703 Meadowview Dr",
    "sg:city":"Colleyville",
    "sg:classifiers":[
        {
            "category":"Shopping",
            "subcategory":"Stationery & Office Supplies",
            "type":"Retail Goods"
        }
    ],
    "sg:phone":"+1 817 235 5100",
    "sg:postcode":"76034",
    "sg:province":"TX",
    "sg:tags":[
        "envelope",
        "store"
    ],
    "wof:name":"Labels & More",
    "wof:placetype":"venue"
},
  "geometry": {"coordinates":[-97.125062,32.881069],"type":"Point"}
}