{
  "type": "Feature",
  "properties": {
    "iso:country":"US",
    "sg:address":"418 W Kilpatrick St",
    "sg:city":"Mineola",
    "sg:classifiers":[
        {
            "category":"Retail",
            "subcategory":"Laundry & Dry Cleaning",
            "type":"Services"
        }
    ],
    "sg:phone":"+1 903 530 8524",
    "sg:postcode":"75773",
    "sg:province":"TX",
    "wof:name":"Hydrocare Carpet Cleaning",
    "wof:placetype":"venue"
},
  "geometry": {"coordinates":[-95.49373,32.66535],"type":"Point"}
}