{
  "type": "Feature",
  "properties": {
    "iso:country":"US",
    "sg:address":"5722 Manchaca Road",
    "sg:city":"Austin",
    "sg:classifiers":[
        {
            "category":"Retail",
            "subcategory":"Pet Boarding",
            "type":"Services"
        }
    ],
    "sg:phone":"+1 512 448 2197",
    "sg:postcode":"78745",
    "sg:province":"TX",
    "sg:tags":[
        "boarding/pet",
        "sitting"
    ],
    "wof:name":"Cindy's Grooming",
    "wof:placetype":"venue"
},
  "geometry": {"coordinates":[-97.80024899999999,30.214161],"type":"Point"}
}