{
  "type": "Feature",
  "properties": {
    "iso:country":"US",
    "sg:address":"5914 W 34th St",
    "sg:city":"Houston",
    "sg:classifiers":[
        {
            "category":"Building & Trades",
            "subcategory":"Plumbing",
            "type":"Services"
        }
    ],
    "sg:phone":"+1 713 476 0949",
    "sg:postcode":"77092",
    "sg:province":"TX",
    "sg:tags":[
        "plumbing",
        "contractor"
    ],
    "wof:name":"A Best Plumbing",
    "wof:placetype":"venue"
},
  "geometry": {"coordinates":[-95.476063,29.819378],"type":"Point"}
}