{
  "type": "Feature",
  "properties": {
    "iso:country":"US",
    "sg:address":"500 N Chenango St",
    "sg:city":"Angleton",
    "sg:classifiers":[
        {
            "category":"Professional",
            "subcategory":"Business Services",
            "type":"Services"
        }
    ],
    "sg:phone":"+1 979 265 3272",
    "sg:postcode":"77515",
    "sg:province":"TX",
    "sg:tags":[
        "consultant",
        "coach"
    ],
    "wof:name":"Snow & Brooks Properties Clute Tx",
    "wof:placetype":"venue"
},
  "geometry": {"coordinates":[-95.430717,29.16865],"type":"Point"}
}