{
  "type": "Feature",
  "properties": {
    "iso:country":"US",
    "sg:address":"435 Murphy Rd",
    "sg:city":"Stafford",
    "sg:classifiers":[
        {
            "category":"Insurance",
            "subcategory":"Insurance Agent",
            "type":"Services"
        }
    ],
    "sg:phone":"+1 281 261 8200",
    "sg:postcode":"77477",
    "sg:province":"TX",
    "wof:name":"Abe Jacobs Insurance Agency",
    "wof:placetype":"venue"
},
  "geometry": {"coordinates":[-95.564526,29.615276],"type":"Point"}
}