{
  "type": "Feature",
  "properties": {
    "iso:country":"US",
    "sg:address":"16970 Dallas Pkwy Ste 601",
    "sg:city":"Dallas",
    "sg:classifiers":[
        {
            "category":"Banks & Credit Unions",
            "subcategory":"Investment Brokerage",
            "type":"Services"
        }
    ],
    "sg:phone":"+1 972 250 6550",
    "sg:postcode":"75248",
    "sg:province":"TX",
    "sg:tags":[
        "advisory"
    ],
    "wof:name":"Traci Ford Investments L C",
    "wof:placetype":"venue"
},
  "geometry": {"coordinates":[-96.827962,32.979489],"type":"Point"}
}