{
  "type": "Feature",
  "properties": {
    "iso:country":"US",
    "sg:address":"3197 Family Dr",
    "sg:city":"Fort Worth",
    "sg:classifiers":[
        {
            "category":"Building & Trades",
            "subcategory":"Plumbing",
            "type":"Services"
        }
    ],
    "sg:phone":"+1 817 238 0885",
    "sg:postcode":"76179",
    "sg:province":"TX",
    "sg:tags":[
        "septic"
    ],
    "wof:name":"Septic Tank Cleaning",
    "wof:placetype":"venue"
},
  "geometry": {"coordinates":[-97.43123300000001,32.983694],"type":"Point"}
}