{
  "type": "Feature",
  "properties": {
    "iso:country":"US",
    "sg:address":"306 State Hwy 37",
    "sg:city":"Mt Vernon",
    "sg:classifiers":[
        {
            "category":"Food & Beverages",
            "subcategory":"Groceries & Convenience Stores",
            "type":"Retail Goods"
        }
    ],
    "sg:phone":"+1 903 537 4989",
    "sg:postcode":"75457",
    "sg:province":"TX",
    "sg:tags":[
        "grocer"
    ],
    "wof:name":"Brookshire's",
    "wof:placetype":"venue"
},
  "geometry": {"coordinates":[-95.23364599999999,33.184939],"type":"Point"}
}