{
  "type": "Feature",
  "properties": {
    "iso:country":"US",
    "sg:address":"1002 Texan Trl",
    "sg:city":"Corpus Christi",
    "sg:classifiers":[
        {
            "category":"Education",
            "subcategory":"School",
            "type":"Public Place"
        }
    ],
    "sg:phone":"+1 361 806 5300",
    "sg:postcode":"78411",
    "sg:province":"TX",
    "wof:name":"Ray High School",
    "wof:placetype":"venue"
},
  "geometry": {"coordinates":[-97.394121,27.751614],"type":"Point"}
}