{
  "type": "Feature",
  "properties": {
    "iso:country":"US",
    "sg:address":"405 W Van Buren Ave",
    "sg:city":"Harlingen",
    "sg:classifiers":[
        {
            "category":"Real Estate",
            "subcategory":"Real Estate Agent",
            "type":"Services"
        }
    ],
    "sg:phone":"+1 956 428 9595",
    "sg:postcode":"78550",
    "sg:province":"TX",
    "wof:name":"Rio Grande Appraisals",
    "wof:placetype":"venue"
},
  "geometry": {"coordinates":[-97.699955,26.191628],"type":"Point"}
}