{
  "type": "Feature",
  "properties": {
    "iso:country":"US",
    "sg:address":"12843 Covey Ln",
    "sg:city":"Houston",
    "sg:classifiers":[
        {
            "category":"Food & Beverages",
            "subcategory":"Farmers Market",
            "type":"Retail Goods"
        }
    ],
    "sg:phone":"+1 281 564 8851",
    "sg:postcode":"77099",
    "sg:province":"TX",
    "sg:tags":[
        "operator",
        "oil"
    ],
    "sg:website":"http://www.mktechsolutions.com",
    "wof:name":"M K Tech Solutions Inc",
    "wof:placetype":"venue"
},
  "geometry": {"coordinates":[-95.609041,29.673799],"type":"Point"}
}