{
  "type": "Feature",
  "properties": {
    "iso:country":"US",
    "sg:address":"207 Dasher Dr",
    "sg:city":"Austin",
    "sg:classifiers":[
        {
            "category":"Health Services",
            "subcategory":"Nursing And Care Facility",
            "type":"Services"
        }
    ],
    "sg:phone":"+1 512 261 3908",
    "sg:postcode":"78734",
    "sg:province":"TX",
    "sg:tags":[
        "skilled"
    ],
    "wof:name":"Regency Terrace Nursing H",
    "wof:placetype":"venue"
},
  "geometry": {"coordinates":[-97.997331,30.363034],"type":"Point"}
}