{
  "type": "Feature",
  "properties": {
    "iso:country":"US",
    "sg:address":"502 S Summit Ave",
    "sg:city":"Fort Worth",
    "sg:classifiers":[
        {
            "category":"Autos & Motor Vehicles",
            "subcategory":"Automobile Sales",
            "type":"Retail Goods"
        }
    ],
    "sg:phone":"+1 817 665 6182",
    "sg:postcode":"76104",
    "sg:province":"TX",
    "sg:tags":[
        "equipment",
        "wrecker"
    ],
    "wof:name":"Hunter's 24 1/2 Hour Towing",
    "wof:placetype":"venue"
},
  "geometry": {"coordinates":[-97.342378,32.739377],"type":"Point"}
}