{
  "type": "Feature",
  "properties": {
    "iso:country":"US",
    "sg:address":"322 Enchanted Dr",
    "sg:city":"Mabank",
    "sg:classifiers":[
        {
            "category":"Real Estate",
            "subcategory":"Real Estate Agent",
            "type":"Services"
        }
    ],
    "sg:phone":"+1 903 880 7850",
    "sg:postcode":"75156",
    "sg:province":"TX",
    "wof:name":"Shelly Brown Realtor",
    "wof:placetype":"venue"
},
  "geometry": {"coordinates":[-96.108617,32.263603],"type":"Point"}
}