{
  "type": "Feature",
  "properties": {
    "iso:country":"US",
    "sg:address":"37 Windermere Ln",
    "sg:city":"Houston",
    "sg:classifiers":[
        {
            "category":"Banks & Credit Unions",
            "subcategory":"Financial Services",
            "type":"Services"
        }
    ],
    "sg:phone":"+1 713 336 7833",
    "sg:postcode":"77063",
    "sg:province":"TX",
    "sg:tags":[
        "trust",
        "management"
    ],
    "wof:name":"Capitol Peak Partnership",
    "wof:placetype":"venue"
},
  "geometry": {"coordinates":[-95.522818,29.746123],"type":"Point"}
}