{
  "type": "Feature",
  "properties": {
    "iso:country":"US",
    "sg:address":"3007 W Davis St",
    "sg:city":"Conroe",
    "sg:classifiers":[
        {
            "category":"Health Services",
            "subcategory":"Health Practitioner",
            "type":"Services"
        }
    ],
    "sg:phone":"+1 936 788 1010",
    "sg:postcode":"77304",
    "sg:province":"TX",
    "wof:name":"Lewis Stphnie Mssage Therapist",
    "wof:placetype":"venue"
},
  "geometry": {"coordinates":[-95.48178900000001,30.319229],"type":"Point"}
}