{
  "type": "Feature",
  "properties": {
    "iso:country":"US",
    "sg:address":"1235 Brittany Way",
    "sg:city":"Seagoville",
    "sg:classifiers":[
        {
            "category":"Retail",
            "subcategory":"Auto Repair",
            "type":"Services"
        }
    ],
    "sg:phone":"+1 972 287 8700",
    "sg:postcode":"75159",
    "sg:province":"TX",
    "sg:tags":[
        "general"
    ],
    "wof:name":"Diesel Doctors Twenty Four Hou",
    "wof:placetype":"venue"
},
  "geometry": {"coordinates":[-96.534459,32.661008],"type":"Point"}
}