{
  "type": "Feature",
  "properties": {
    "iso:country":"US",
    "sg:address":"103 W del Rio Ave",
    "sg:city":"Alpine",
    "sg:classifiers":[
        {
            "category":"Education",
            "subcategory":"School",
            "type":"Public Place"
        }
    ],
    "sg:phone":"+1 432 837 5377",
    "sg:postcode":"79830",
    "sg:province":"TX",
    "wof:name":"Alpine Montessori Elementary",
    "wof:placetype":"venue"
},
  "geometry": {"coordinates":[-103.66522999999999,30.366202],"type":"Point"}
}