{
  "type": "Feature",
  "properties": {
    "iso:country":"US",
    "sg:address":"227 S Waco St",
    "sg:city":"Hillsboro",
    "sg:classifiers":[
        {
            "category":"Retail",
            "subcategory":"Car Wash",
            "type":"Services"
        }
    ],
    "sg:phone":"+1 254 582 1122",
    "sg:postcode":"76645",
    "sg:province":"TX",
    "sg:tags":[
        "polishing",
        "washing"
    ],
    "wof:name":"Hometown Pride Car Care & Stge",
    "wof:placetype":"venue"
},
  "geometry": {"coordinates":[-97.13009700000001,32.007986],"type":"Point"}
}