{
  "type": "Feature",
  "properties": {
    "iso:country":"US",
    "sg:address":"7516 Chevy Chase Dr",
    "sg:city":"Houston",
    "sg:classifiers":[
        {
            "category":"Professional",
            "subcategory":"Business Services",
            "type":"Services"
        }
    ],
    "sg:phone":"+1 713 977 6333",
    "sg:postcode":"77063",
    "sg:province":"TX",
    "wof:name":"Best Bets Enterprises",
    "wof:placetype":"venue"
},
  "geometry": {"coordinates":[-95.50264,29.744773],"type":"Point"}
}