{
  "type": "Feature",
  "properties": {
    "iso:country":"US",
    "sg:address":"8903 Ave P",
    "sg:city":"Lubbock",
    "sg:classifiers":[
        {
            "category":"Wholesale",
            "subcategory":"Groceries",
            "type":"Manufacturing & Wholesale Goods"
        }
    ],
    "sg:phone":"+1 806 745 2470",
    "sg:postcode":"79423",
    "sg:province":"TX",
    "sg:tags":[
        "confectionery",
        "candy"
    ],
    "wof:name":"Simmco Brokerage",
    "wof:placetype":"venue"
},
  "geometry": {"coordinates":[-101.852982,33.513251],"type":"Point"}
}