{
  "type": "Feature",
  "properties": {
    "iso:country":"US",
    "sg:address":"405 W Main St",
    "sg:city":"Whitehouse",
    "sg:classifiers":[
        {
            "category":"Place Of Worship",
            "subcategory":"Church",
            "type":"Public Place"
        },
        {
            "category":"Place Of Worship",
            "type":"Public Place"
        }
    ],
    "sg:phone":"+1 903 839 2173",
    "sg:postcode":"75791",
    "sg:province":"TX",
    "sg:tags":[
        "churches-methodist"
    ],
    "wof:name":"Whitehouse United Methodist Church",
    "wof:placetype":"venue"
},
  "geometry": {"coordinates":[-95.232292,32.226749],"type":"Point"}
}