{
  "type": "Feature",
  "properties": {
    "iso:country":"US",
    "sg:address":"2132 Lattice Ct",
    "sg:city":"Plano",
    "sg:classifiers":[
        {
            "category":"Real Estate",
            "subcategory":"Real Estate Agent",
            "type":"Services"
        }
    ],
    "sg:phone":"+1 972 596 6393",
    "sg:postcode":"75075",
    "sg:province":"TX",
    "wof:name":"Martin Art Co",
    "wof:placetype":"venue"
},
  "geometry": {"coordinates":[-96.76331,33.029005],"type":"Point"}
}