{
  "type": "Feature",
  "properties": {
    "iso:country":"US",
    "sg:address":"12811 Greenwood Forest Dr",
    "sg:city":"Houston",
    "sg:classifiers":[
        {
            "category":"Real Estate",
            "subcategory":"Real Estate Operator",
            "type":"Services"
        }
    ],
    "sg:phone":"+1 281 440 7162",
    "sg:postcode":"77066",
    "sg:province":"TX",
    "sg:tags":[
        "apartment"
    ],
    "sg:website":"www.bhmanagement.com",
    "wof:name":"Champions Village",
    "wof:placetype":"venue"
},
  "geometry": {"coordinates":[-95.50526000000001,29.980726],"type":"Point"}
}