{
  "type": "Feature",
  "properties": {
    "iso:country":"US",
    "sg:address":"1011 31st St",
    "sg:city":"Galveston",
    "sg:classifiers":[
        {
            "category":"Organizations",
            "subcategory":"Religious Organization",
            "type":"Services"
        }
    ],
    "sg:phone":"+1 409 763 2621",
    "sg:postcode":"77550",
    "sg:province":"TX",
    "sg:tags":[
        "church"
    ],
    "wof:name":"Grace Church",
    "wof:placetype":"venue"
},
  "geometry": {"coordinates":[-94.800994,29.296758],"type":"Point"}
}