{
  "type": "Feature",
  "properties": {
    "iso:country":"US",
    "sg:address":"1400 S Main St",
    "sg:city":"Fort Worth",
    "sg:classifiers":[
        {
            "category":"Health Services",
            "subcategory":"Medical Lab",
            "type":"Services"
        }
    ],
    "sg:phone":"+1 817 332 9033",
    "sg:postcode":"76104",
    "sg:province":"TX",
    "sg:tags":[
        "laboratory"
    ],
    "wof:name":"Anatomical & Forensic Patholgy",
    "wof:placetype":"venue"
},
  "geometry": {"coordinates":[-97.32640600000001,32.728194],"type":"Point"}
}