{
  "type": "Feature",
  "properties": {
    "iso:country":"US",
    "sg:address":"816 S Florence St",
    "sg:city":"El Paso",
    "sg:classifiers":[
        {
            "category":"Organizations",
            "subcategory":"Religious Organization",
            "type":"Services"
        }
    ],
    "sg:phone":"+1 915 532 7109",
    "sg:postcode":"79901",
    "sg:province":"TX",
    "sg:tags":[
        "church"
    ],
    "wof:name":"Iglesia Bautista Del Centro",
    "wof:placetype":"venue"
},
  "geometry": {"coordinates":[-106.48060099999999,31.752385],"type":"Point"}
}