{
  "type": "Feature",
  "properties": {
    "iso:country":"US",
    "sg:address":"3632 S Congress Ave",
    "sg:city":"Austin",
    "sg:classifiers":[
        {
            "category":"Restaurant",
            "type":"Food & Drink"
        }
    ],
    "sg:phone":"+1 512 445 5922",
    "sg:postcode":"78704",
    "sg:province":"TX",
    "sg:tags":[
        "mexican"
    ],
    "wof:name":"Flacos Tacos Inc",
    "wof:placetype":"venue"
},
  "geometry": {"coordinates":[-97.76178,30.227225],"type":"Point"}
}