{
  "type": "Feature",
  "properties": {
    "iso:country":"US",
    "sg:address":"8701 Marys Creek Dr",
    "sg:city":"Benbrook",
    "sg:classifiers":[
        {
            "category":"Shopping",
            "subcategory":"Hobbies, Toys, & Games",
            "type":"Retail Goods"
        },
        {
            "category":"Shopping",
            "subcategory":"Crafts & Fabrics",
            "type":"Retail Goods"
        }
    ],
    "sg:phone":"+1 817 244 1547",
    "sg:postcode":"76116",
    "sg:province":"TX",
    "sg:tags":[
        "shop",
        "hobby",
        "model",
        "supplies-wholesale",
        "manufacturer"
    ],
    "wof:name":"Creations By Lois",
    "wof:placetype":"venue"
},
  "geometry": {"coordinates":[-97.46620900000001,32.707779],"type":"Point"}
}