{
  "type": "Feature",
  "properties": {
    "iso:country":"US",
    "sg:address":"2908 London Ct",
    "sg:city":"Pearland",
    "sg:classifiers":[
        {
            "category":"Home & Garden",
            "subcategory":"Home Furnishings",
            "type":"Retail Goods"
        }
    ],
    "sg:phone":"+1 281 997 9600",
    "sg:postcode":"77581",
    "sg:province":"TX",
    "wof:name":"Double K Blinds",
    "wof:placetype":"venue"
},
  "geometry": {"coordinates":[-95.26236,29.562645],"type":"Point"}
}