{
  "type": "Feature",
  "properties": {
    "iso:country":"US",
    "sg:address":"3612 Briarcliff Dr",
    "sg:city":"Plano",
    "sg:classifiers":[
        {
            "category":"Professional",
            "type":"Services"
        }
    ],
    "sg:phone":"+1 972 398 8234",
    "sg:postcode":"75025",
    "sg:province":"TX",
    "wof:name":"Ocean Cross LLC",
    "wof:placetype":"venue"
},
  "geometry": {"coordinates":[-96.76607300000001,33.084424],"type":"Point"}
}