{
  "type": "Feature",
  "properties": {
    "iso:country":"US",
    "sg:address":"520 S Twin City Hwy",
    "sg:city":"Nederland",
    "sg:classifiers":[
        {
            "category":"Health Services",
            "subcategory":"Doctor",
            "type":"Services"
        }
    ],
    "sg:phone":"+1 409 729 2266",
    "sg:postcode":"77627",
    "sg:province":"TX",
    "sg:tags":[
        "clinic"
    ],
    "wof:name":"Christopher Bell",
    "wof:placetype":"venue"
},
  "geometry": {"coordinates":[-93.98598800000001,29.973732],"type":"Point"}
}