{
  "type": "Feature",
  "properties": {
    "iso:country":"US",
    "sg:address":"3001 Provine Rd",
    "sg:city":"Mc Kinney",
    "sg:classifiers":[
        {
            "category":"Professional",
            "subcategory":"Business Services",
            "type":"Services"
        }
    ],
    "sg:phone":"+1 214 929 7017",
    "sg:postcode":"75070",
    "sg:province":"TX",
    "wof:name":"Grayce Sales Corp",
    "wof:placetype":"venue"
},
  "geometry": {"coordinates":[-96.665043,33.180057],"type":"Point"}
}