{
  "type": "Feature",
  "properties": {
    "iso:country":"US",
    "sg:address":"1805 Milam St",
    "sg:city":"Uvalde",
    "sg:classifiers":[
        {
            "category":"Autos & Motor Vehicles",
            "subcategory":"Auto Supplies",
            "type":"Retail Goods"
        }
    ],
    "sg:phone":"+1 830 278 1372",
    "sg:postcode":"78801",
    "sg:province":"TX",
    "sg:tags":[
        "transmission",
        "transmissions-other"
    ],
    "wof:name":"A-1 Transmission & General Repair",
    "wof:placetype":"venue"
},
  "geometry": {"coordinates":[-99.793402,29.231164],"type":"Point"}
}