{
  "type": "Feature",
  "properties": {
    "iso:country":"US",
    "sg:address":"6928 S R L Thornton Fwy",
    "sg:city":"Dallas",
    "sg:classifiers":[
        {
            "category":"Shopping",
            "subcategory":"Stationery & Office Supplies",
            "type":"Retail Goods"
        }
    ],
    "sg:phone":"+1 214 371 2355",
    "sg:postcode":"75232",
    "sg:province":"TX",
    "sg:tags":[
        "label"
    ],
    "sg:website":"http://www.reichassociates.com",
    "wof:name":"C & H Label Company Inc",
    "wof:placetype":"venue"
},
  "geometry": {"coordinates":[-96.822503,32.663722],"type":"Point"}
}