{
  "type": "Feature",
  "properties": {
    "iso:country":"US",
    "sg:address":"6715 Sherman St",
    "sg:city":"Houston",
    "sg:classifiers":[
        {
            "category":"Professional",
            "subcategory":"Art Services",
            "type":"Services"
        }
    ],
    "sg:phone":"+1 713 926 9339",
    "sg:postcode":"77011",
    "sg:province":"TX",
    "sg:tags":[
        "graphic",
        "commercial",
        "designer",
        "artist"
    ],
    "wof:name":"Homer S Visual Graphics",
    "wof:placetype":"venue"
},
  "geometry": {"coordinates":[-95.307164,29.73948],"type":"Point"}
}