{
  "type": "Feature",
  "properties": {
    "iso:country":"US",
    "sg:address":"2480 Times Blvd",
    "sg:city":"Houston",
    "sg:classifiers":[
        {
            "category":"Professional",
            "subcategory":"Lawyer & Legal Services",
            "type":"Services"
        }
    ],
    "sg:phone":"+1 713 524 6400",
    "sg:postcode":"77005",
    "sg:province":"TX",
    "sg:tags":[
        "attorney"
    ],
    "wof:name":"Barfield Virgil H Atty",
    "wof:placetype":"venue"
},
  "geometry": {"coordinates":[-95.41544500000001,29.716744],"type":"Point"}
}