{
  "type": "Feature",
  "properties": {
    "iso:country":"US",
    "sg:address":"2245 S Cooper St",
    "sg:city":"Arlington",
    "sg:classifiers":[
        {
            "category":"Personal",
            "subcategory":"Beauty Salon",
            "type":"Services"
        }
    ],
    "sg:phone":"+1 817 274 7009",
    "sg:postcode":"76013",
    "sg:province":"TX",
    "sg:tags":[
        "shop"
    ],
    "wof:name":"Linca Hair & Barber Salon",
    "wof:placetype":"venue"
},
  "geometry": {"coordinates":[-97.116376,32.707842],"type":"Point"}
}