{
  "type": "Feature",
  "properties": {
    "iso:country":"US",
    "sg:address":"2335 Hummingbird Trl",
    "sg:city":"Grapevine",
    "sg:classifiers":[
        {
            "category":"Professional",
            "subcategory":"Business Services",
            "type":"Services"
        }
    ],
    "sg:phone":"+1 817 424 2765",
    "sg:postcode":"76051",
    "sg:province":"TX",
    "wof:name":"United Payment Systems Inc",
    "wof:placetype":"venue"
},
  "geometry": {"coordinates":[-97.086018,32.964001],"type":"Point"}
}