{
  "type": "Feature",
  "properties": {
    "iso:country":"US",
    "sg:address":"7750 N MacArthur Blvd",
    "sg:city":"Irving",
    "sg:classifiers":[
        {
            "category":"Personal",
            "subcategory":"Nail Salon",
            "type":"Services"
        }
    ],
    "sg:phone":"+1 972 506 7070",
    "sg:postcode":"75063",
    "sg:province":"TX",
    "wof:name":"Hollywood Nail Spa",
    "wof:placetype":"venue"
},
  "geometry": {"coordinates":[-96.958416,32.91214],"type":"Point"}
}