{
  "type": "Feature",
  "properties": {
    "iso:country":"US",
    "sg:address":"4733 Don Dr",
    "sg:city":"Dallas",
    "sg:classifiers":[
        {
            "category":"Manufacturing",
            "subcategory":"Signs",
            "type":"Manufacturing & Wholesale Goods"
        }
    ],
    "sg:phone":"+1 214 634 0047",
    "sg:postcode":"75247",
    "sg:province":"TX",
    "sg:tags":[
        "specialty",
        "mfg"
    ],
    "wof:name":"Edwards & Patterson Signs",
    "wof:placetype":"venue"
},
  "geometry": {"coordinates":[-96.877404,32.805584],"type":"Point"}
}