{
  "type": "Feature",
  "properties": {
    "iso:country":"US",
    "sg:address":"104 Airport Rd",
    "sg:city":"Corpus Christi",
    "sg:classifiers":[
        {
            "category":"Freight",
            "type":"Transportation"
        }
    ],
    "sg:phone":"+1 361 879 0207",
    "sg:postcode":"78405",
    "sg:province":"TX",
    "sg:tags":[
        "operator",
        "trucking"
    ],
    "wof:name":"A P Trucking",
    "wof:placetype":"venue"
},
  "geometry": {"coordinates":[-97.43781,27.784289],"type":"Point"}
}