{
  "type": "Feature",
  "properties": {
    "iso:country":"US",
    "sg:address":"208 Mill Wood Ct",
    "sg:city":"Colleyville",
    "sg:classifiers":[
        {
            "category":"Organizations",
            "subcategory":"Non-profit Organization",
            "type":"Services"
        }
    ],
    "sg:phone":"+1 817 281 0162",
    "sg:postcode":"76034",
    "sg:province":"TX",
    "sg:tags":[
        "social"
    ],
    "wof:name":"Caring For Texans LLC",
    "wof:placetype":"venue"
},
  "geometry": {"coordinates":[-97.165226,32.877971],"type":"Point"}
}