{
  "type": "Feature",
  "properties": {
    "iso:country":"US",
    "sg:address":"3 Butterfield Trail Blvd",
    "sg:city":"El Paso",
    "sg:classifiers":[
        {
            "category":"Wholesale",
            "subcategory":"Meat",
            "type":"Manufacturing & Wholesale Goods"
        }
    ],
    "sg:phone":"+1 915 751 6632",
    "sg:postcode":"79906",
    "sg:province":"TX",
    "wof:name":"Peyton Meats",
    "wof:placetype":"venue"
},
  "geometry": {"coordinates":[-106.40358999999999,31.812857],"type":"Point"}
}