{
  "type": "Feature",
  "properties": {
    "iso:country":"US",
    "sg:address":"1331 N Lee Trevino Dr",
    "sg:city":"El Paso",
    "sg:classifiers":[
        {
            "category":"Shopping",
            "subcategory":"Clothing, Apparel, & Fashions",
            "type":"Retail Goods"
        }
    ],
    "sg:phone":"+1 915 595 1998",
    "sg:postcode":"79936",
    "sg:province":"TX",
    "wof:name":"Elodia Boutique & Bridal",
    "wof:placetype":"venue"
},
  "geometry": {"coordinates":[-106.32306699999999,31.741727],"type":"Point"}
}