{
  "type": "Feature",
  "properties": {
    "iso:country":"US",
    "sg:address":"2507 Texas Plume Rd",
    "sg:city":"Cedar Hill",
    "sg:classifiers":[
        {
            "category":"Professional",
            "subcategory":"Art Services",
            "type":"Services"
        }
    ],
    "sg:phone":"+1 972 291 8005",
    "sg:postcode":"75104",
    "sg:province":"TX",
    "sg:tags":[
        "photography",
        "commercial"
    ],
    "wof:name":"Burkey Studios",
    "wof:placetype":"venue"
},
  "geometry": {"coordinates":[-97.0001,32.556947],"type":"Point"}
}