{
  "type": "Feature",
  "properties": {
    "iso:country":"US",
    "sg:address":"9610 Triola Ln",
    "sg:city":"Houston",
    "sg:classifiers":[
        {
            "category":"Professional",
            "subcategory":"Management & Consulting",
            "type":"Services"
        }
    ],
    "sg:phone":"+1 713 974 1872",
    "sg:postcode":"77036",
    "sg:province":"TX",
    "wof:name":"Qmr",
    "wof:placetype":"venue"
},
  "geometry": {"coordinates":[-95.551343,29.698474],"type":"Point"}
}