{
  "type": "Feature",
  "properties": {
    "iso:country":"US",
    "sg:address":"200 Texas Longhorn Trl",
    "sg:city":"Dripping Springs",
    "sg:classifiers":[
        {
            "category":"Wholesale",
            "subcategory":"Medical Equipment & Supplies",
            "type":"Manufacturing & Wholesale Goods"
        }
    ],
    "sg:phone":"+1 512 858 1033",
    "sg:postcode":"78620",
    "sg:province":"TX",
    "wof:name":"Provident Care",
    "wof:placetype":"venue"
},
  "geometry": {"coordinates":[-98.164231,30.249574],"type":"Point"}
}