{
  "type": "Feature",
  "properties": {
    "iso:country":"US",
    "sg:address":"3618 Mount Vernon St",
    "sg:city":"Houston",
    "sg:classifiers":[
        {
            "category":"Shopping",
            "subcategory":"Clothing, Apparel, & Fashions",
            "type":"Retail Goods"
        }
    ],
    "sg:phone":"+1 713 942 0604",
    "sg:postcode":"77006",
    "sg:province":"TX",
    "wof:name":"Costumes & Dancewear Inc",
    "wof:placetype":"venue"
},
  "geometry": {"coordinates":[-95.393829,29.739756],"type":"Point"}
}