{
  "type": "Feature",
  "properties": {
    "iso:country":"US",
    "sg:address":"3902 Colorado St",
    "sg:city":"Texarkana",
    "sg:classifiers":[
        {
            "category":"Organizations",
            "subcategory":"Religious Organization",
            "type":"Services"
        }
    ],
    "sg:phone":"+1 903 794 9555",
    "sg:postcode":"75503",
    "sg:province":"TX",
    "sg:tags":[
        "church"
    ],
    "wof:name":"First United Methodist",
    "wof:placetype":"venue"
},
  "geometry": {"coordinates":[-94.06293599999999,33.454359],"type":"Point"}
}