{
  "type": "Feature",
  "properties": {
    "iso:country":"US",
    "sg:address":"438 Lazy Ln",
    "sg:city":"Montgomery",
    "sg:classifiers":[
        {
            "category":"Professional",
            "subcategory":"Computer Services",
            "type":"Services"
        }
    ],
    "sg:phone":"+1 936 448 6971",
    "sg:postcode":"77356",
    "sg:province":"TX",
    "sg:tags":[
        "datum"
    ],
    "wof:name":"Marick Enterprises",
    "wof:placetype":"venue"
},
  "geometry": {"coordinates":[-95.649727,30.382613],"type":"Point"}
}