{
  "type": "Feature",
  "properties": {
    "iso:country":"US",
    "sg:address":"2117 Ave I",
    "sg:city":"Rosenberg",
    "sg:classifiers":[
        {
            "category":"Shopping",
            "subcategory":"Photographic Equipment",
            "type":"Retail Goods"
        }
    ],
    "sg:phone":"+1 281 342 1360",
    "sg:postcode":"77471",
    "sg:province":"TX",
    "sg:tags":[
        "supply"
    ],
    "sg:website":"www.camerasunlimited.net",
    "wof:name":"Camera's Unlimited",
    "wof:placetype":"venue"
},
  "geometry": {"coordinates":[-95.805206,29.557329],"type":"Point"}
}