{
  "type": "Feature",
  "properties": {
    "iso:country":"US",
    "sg:address":"2142 Mistletoe Blvd",
    "sg:city":"Fort Worth",
    "sg:classifiers":[
        {
            "category":"Manufacturing",
            "subcategory":"Tools & Machinery",
            "type":"Manufacturing & Wholesale Goods"
        }
    ],
    "sg:phone":"+1 817 921 4818",
    "sg:postcode":"76110",
    "sg:province":"TX",
    "sg:tags":[
        "pattern",
        "industrial",
        "mfg"
    ],
    "wof:name":"Sids Pattern Shop Inc",
    "wof:placetype":"venue"
},
  "geometry": {"coordinates":[-97.349683,32.731598],"type":"Point"}
}