{
  "type": "Feature",
  "properties": {
    "iso:country":"US",
    "sg:address":"5746 Everhart Rd",
    "sg:city":"Corpus Christi",
    "sg:classifiers":[
        {
            "category":"Retail",
            "subcategory":"Auto Repair",
            "type":"Services"
        }
    ],
    "sg:phone":"+1 361 994 8515",
    "sg:postcode":"78413",
    "sg:province":"TX",
    "sg:tags":[
        "automobile",
        "used",
        "general"
    ],
    "wof:name":"Auto America",
    "wof:placetype":"venue"
},
  "geometry": {"coordinates":[-97.39014299999999,27.705365],"type":"Point"}
}