{
  "type": "Feature",
  "properties": {
    "iso:country":"US",
    "sg:address":"1100 Pueblo St",
    "sg:city":"Odessa",
    "sg:classifiers":[
        {
            "category":"Professional",
            "type":"Services"
        }
    ],
    "sg:phone":"+1 432 272 5282",
    "sg:postcode":"79761",
    "sg:province":"TX",
    "wof:name":"Elite Designs",
    "wof:placetype":"venue"
},
  "geometry": {"coordinates":[-102.33064400000001,31.868298],"type":"Point"}
}