{
  "type": "Feature",
  "properties": {
    "iso:country":"US",
    "sg:address":"111 N Victoria St",
    "sg:city":"San Diego",
    "sg:classifiers":[
        {
            "category":"Government",
            "subcategory":"Post Office",
            "type":"Public Place"
        }
    ],
    "sg:phone":"+1 361 279 3984",
    "sg:postcode":"78384",
    "sg:province":"TX",
    "sg:tags":[
        "postal",
        "us"
    ],
    "wof:name":"US Post Office",
    "wof:placetype":"venue"
},
  "geometry": {"coordinates":[-98.236605,27.76454],"type":"Point"}
}