{
  "type": "Feature",
  "properties": {
    "iso:country":"US",
    "sg:address":"632 W Carson St",
    "sg:city":"Bryan",
    "sg:classifiers":[
        {
            "category":"Retail",
            "subcategory":"Auto Rental",
            "type":"Services"
        }
    ],
    "sg:phone":"+1 979 779 5582",
    "sg:postcode":"77801",
    "sg:province":"TX",
    "sg:tags":[
        "truck"
    ],
    "wof:name":"Ryder",
    "wof:placetype":"venue"
},
  "geometry": {"coordinates":[-96.37191900000001,30.64516],"type":"Point"}
}