{
  "type": "Feature",
  "properties": {
    "iso:country":"US",
    "sg:address":"2355 N Stemmons Fwy",
    "sg:city":"Dallas",
    "sg:classifiers":[
        {
            "category":"Government",
            "subcategory":"Office",
            "type":"Public Place"
        }
    ],
    "sg:phone":"+1 214 302 4216",
    "sg:postcode":"75207",
    "sg:province":"TX",
    "sg:tags":[
        "state",
        "resource"
    ],
    "wof:name":"Child Care Licensing",
    "wof:placetype":"venue"
},
  "geometry": {"coordinates":[-96.83784,32.805006],"type":"Point"}
}