{
  "type": "Feature",
  "properties": {
    "iso:country":"US",
    "sg:address":"4307 Idalou Rd",
    "sg:city":"Lubbock",
    "sg:classifiers":[
        {
            "category":"Manufacturing",
            "subcategory":"Printing",
            "type":"Manufacturing & Wholesale Goods"
        }
    ],
    "sg:phone":"+1 806 744 8700",
    "sg:postcode":"79403",
    "sg:province":"TX",
    "sg:tags":[
        "screen"
    ],
    "wof:name":"Made To Order",
    "wof:placetype":"venue"
},
  "geometry": {"coordinates":[-101.780415,33.609435],"type":"Point"}
}