{
  "type": "Feature",
  "properties": {
    "iso:country":"US",
    "sg:address":"6261 State Hwy 123",
    "sg:city":"Stockdale",
    "sg:phone":"+1 830 745 2381",
    "sg:postcode":"78160",
    "sg:province":"TX",
    "sg:tags":[
        "farm",
        "field",
        "corn",
        "wheat",
        "crop"
    ],
    "wof:name":"Raymond Dyrzmala",
    "wof:placetype":"venue"
},
  "geometry": {"coordinates":[-97.945696,29.147433],"type":"Point"}
}