{
  "type": "Feature",
  "properties": {
    "iso:country":"US",
    "sg:address":"3100 Carlisle Suite 208",
    "sg:city":"Dallas",
    "sg:classifiers":[
        {
            "category":"Professional",
            "subcategory":"Computer Services",
            "type":"Services"
        }
    ],
    "sg:postcode":"75204",
    "sg:province":"TX",
    "sg:tags":[
        "keyringapp",
        "key-ring",
        "keyring",
        "loyalty-card-app",
        "mobestream"
    ],
    "sg:website":"http://www.keyringapp.com",
    "wof:name":"Mobestream Media",
    "wof:placetype":"venue"
},
  "geometry": {"coordinates":[-96.802532,32.803933],"type":"Point"}
}