{
  "type": "Feature",
  "properties": {
    "iso:country":"US",
    "sg:address":"1700 Cogdell Blvd",
    "sg:city":"Snyder",
    "sg:classifiers":[
        {
            "category":"Health Services",
            "subcategory":"Doctor",
            "type":"Services"
        }
    ],
    "sg:phone":"+1 325 574 7287",
    "sg:postcode":"79549",
    "sg:province":"TX",
    "sg:tags":[
        "medical"
    ],
    "wof:name":"David W Lamberts",
    "wof:placetype":"venue"
},
  "geometry": {"coordinates":[-100.91758799999999,32.688542],"type":"Point"}
}