{
  "type": "Feature",
  "properties": {
    "iso:country":"US",
    "sg:address":"6010 S. Westmoreland Rd",
    "sg:city":"Dallas",
    "sg:classifiers":[
        {
            "category":"Real Estate",
            "subcategory":"Real Estate Services",
            "type":"Services"
        },
        {
            "category":"Real Estate",
            "subcategory":"Real Estate Operator",
            "type":"Services"
        }
    ],
    "sg:phone":"+1 972 709 4400",
    "sg:postcode":"75237",
    "sg:province":"TX",
    "sg:tags":[
        "apartment"
    ],
    "sg:website":"www.woodsdallas.com",
    "wof:name":"The Woods Apartments",
    "wof:placetype":"venue"
},
  "geometry": {"coordinates":[-96.880571,32.673536],"type":"Point"}
}