{
  "type": "Feature",
  "properties": {
    "iso:country":"US",
    "sg:address":"1412 FM 1845 S",
    "sg:city":"Longview",
    "sg:classifiers":[
        {
            "category":"Health Services",
            "subcategory":"Clinic",
            "type":"Services"
        }
    ],
    "sg:phone":"+1 903 757 2242",
    "sg:postcode":"75603",
    "sg:province":"TX",
    "sg:tags":[
        "agency",
        "welfare"
    ],
    "wof:name":"Triumph Disposal Svc",
    "wof:placetype":"venue"
},
  "geometry": {"coordinates":[-94.763677,32.468888],"type":"Point"}
}