{
  "type": "Feature",
  "properties": {
    "iso:country":"US",
    "sg:address":"4826 Hwy 71 E",
    "sg:city":"Del Valle",
    "sg:classifiers":[
        {
            "category":"Personal",
            "type":"Services"
        }
    ],
    "sg:phone":"+1 512 247 2430",
    "sg:postcode":"78617",
    "sg:province":"TX",
    "wof:name":"L Bar Cattle Eqiupment Co LLC",
    "wof:placetype":"venue"
},
  "geometry": {"coordinates":[-97.57548199999999,30.189609],"type":"Point"}
}