{
  "type": "Feature",
  "properties": {
    "iso:country":"US",
    "sg:address":"11511 Pyreneese Dr",
    "sg:city":"Austin",
    "sg:classifiers":[
        {
            "category":"Real Estate",
            "subcategory":"Real Estate Agent",
            "type":"Services"
        }
    ],
    "sg:phone":"+1 512 346 0964",
    "sg:postcode":"78759",
    "sg:province":"TX",
    "wof:name":"Porter Properties Inc",
    "wof:placetype":"venue"
},
  "geometry": {"coordinates":[-97.740747,30.40969],"type":"Point"}
}