{
  "type": "Feature",
  "properties": {
    "iso:country":"US",
    "sg:address":"12800 Schleicher Trl",
    "sg:city":"Austin",
    "sg:classifiers":[
        {
            "category":"Health Services",
            "subcategory":"Clinic",
            "type":"Services"
        },
        {
            "category":"Health Services",
            "subcategory":"Medical Lab",
            "type":"Services"
        },
        {
            "category":"Health Services",
            "subcategory":"Dentist",
            "type":"Services"
        }
    ],
    "sg:phone":"+1 512 451 8595",
    "sg:postcode":"78732",
    "sg:province":"TX",
    "sg:tags":[
        "laboratories-medical",
        "dental",
        "imaging",
        "x-ray"
    ],
    "wof:name":"Austin Open MRI",
    "wof:placetype":"venue"
},
  "geometry": {"coordinates":[-97.89305899999999,30.38142],"type":"Point"}
}