{
  "type": "Feature",
  "properties": {
    "iso:country":"US",
    "sg:address":"2612 Throckmorton St",
    "sg:city":"Dallas",
    "sg:classifiers":[
        {
            "category":"Real Estate",
            "subcategory":"Real Estate Operator",
            "type":"Services"
        }
    ],
    "sg:phone":"+1 214 559 4119",
    "sg:postcode":"75219",
    "sg:province":"TX",
    "sg:tags":[
        "apartment"
    ],
    "wof:name":"Village Square Apartments",
    "wof:placetype":"venue"
},
  "geometry": {"coordinates":[-96.814746,32.80807],"type":"Point"}
}