{
  "type": "Feature",
  "properties": {
    "iso:country":"US",
    "sg:address":"5220 Caroline St",
    "sg:city":"Houston",
    "sg:classifiers":[
        {
            "category":"Professional",
            "subcategory":"Business Services",
            "type":"Services"
        }
    ],
    "sg:phone":"+1 713 524 5661",
    "sg:postcode":"77004",
    "sg:province":"TX",
    "wof:name":"Art & Artists Plus Inc",
    "wof:placetype":"venue"
},
  "geometry": {"coordinates":[-95.38536999999999,29.726444],"type":"Point"}
}