{
  "type": "Feature",
  "properties": {
    "iso:country":"US",
    "sg:address":"507 Oak Crest St",
    "sg:city":"Lake Dallas",
    "sg:classifiers":[
        {
            "category":"Building & Trades",
            "subcategory":"Construction",
            "type":"Services"
        }
    ],
    "sg:phone":"+1 940 321 1426",
    "sg:postcode":"75065",
    "sg:province":"TX",
    "sg:tags":[
        "house"
    ],
    "wof:name":"Fortune Construction",
    "wof:placetype":"venue"
},
  "geometry": {"coordinates":[-97.03398300000001,33.130829],"type":"Point"}
}