{
  "type": "Feature",
  "properties": {
    "iso:country":"US",
    "sg:address":"311 W Woodard St",
    "sg:city":"Denison",
    "sg:classifiers":[
        {
            "category":"Professional",
            "subcategory":"Research",
            "type":"Services"
        }
    ],
    "sg:phone":"+1 903 464 0883",
    "sg:postcode":"75020",
    "sg:province":"TX",
    "sg:tags":[
        "nonphysical",
        "commercial"
    ],
    "wof:name":"Denison Development Alliance",
    "wof:placetype":"venue"
},
  "geometry": {"coordinates":[-96.539798,33.7565],"type":"Point"}
}