{
  "type": "Feature",
  "properties": {
    "iso:country":"US",
    "sg:address":"330 T C Jester Blvd",
    "sg:city":"Houston",
    "sg:classifiers":[
        {
            "category":"Professional",
            "subcategory":"Lawyer & Legal Services",
            "type":"Services"
        }
    ],
    "sg:phone":"+1 713 652 0777",
    "sg:postcode":"77007",
    "sg:province":"TX",
    "sg:tags":[
        "attorney"
    ],
    "wof:name":"Deborah J Fritsche",
    "wof:placetype":"venue"
},
  "geometry": {"coordinates":[-95.417964,29.775937],"type":"Point"}
}