{
  "type": "Feature",
  "properties": {
    "iso:country":"US",
    "sg:address":"416 N Washington Ave",
    "sg:city":"Livingston",
    "sg:classifiers":[
        {
            "category":"Government",
            "subcategory":"Office",
            "type":"Public Place"
        }
    ],
    "sg:phone":"+1 936 327 6801",
    "sg:postcode":"77351",
    "sg:province":"TX",
    "sg:tags":[
        "policy",
        "parish",
        "government-county"
    ],
    "wof:name":"Polk County Tax Office",
    "wof:placetype":"venue"
},
  "geometry": {"coordinates":[-94.93300000000001,30.711126],"type":"Point"}
}