{
  "type": "Feature",
  "properties": {
    "iso:country":"US",
    "sg:address":"622 Richey St",
    "sg:city":"Pasadena",
    "sg:classifiers":[
        {
            "category":"Restaurant",
            "type":"Food & Drink"
        }
    ],
    "sg:phone":"+1 713 534 9900",
    "sg:postcode":"77506",
    "sg:province":"TX",
    "sg:tags":[
        "eating"
    ],
    "wof:name":"Refresqueria La Joya Ice Cream",
    "wof:placetype":"venue"
},
  "geometry": {"coordinates":[-95.219928,29.70321],"type":"Point"}
}