{
  "type": "Feature",
  "properties": {
    "iso:country":"US",
    "sg:address":"1431 Stagecoach Dr",
    "sg:city":"Richardson",
    "sg:classifiers":[
        {
            "category":"Professional",
            "subcategory":"Business Services",
            "type":"Services"
        }
    ],
    "sg:phone":"+1 972 680 1179",
    "sg:postcode":"75080",
    "sg:province":"TX",
    "wof:name":"Russian Ukrainian Translations",
    "wof:placetype":"venue"
},
  "geometry": {"coordinates":[-96.768068,32.947321],"type":"Point"}
}