{
  "type": "Feature",
  "properties": {
    "iso:country":"US",
    "sg:address":"4402 Storie Rd",
    "sg:city":"Arlington",
    "sg:classifiers":[
        {
            "category":"Personal",
            "subcategory":"Psychics & Astrologers",
            "type":"Services"
        }
    ],
    "sg:phone":"+1 817 478 7167",
    "sg:postcode":"76001",
    "sg:province":"TX",
    "sg:tags":[
        "medium"
    ],
    "wof:name":"Just Look Beyond",
    "wof:placetype":"venue"
},
  "geometry": {"coordinates":[-97.17673000000001,32.618243],"type":"Point"}
}