{
  "type": "Feature",
  "properties": {
    "iso:country":"US",
    "sg:address":"2100 W Trimmier Rd",
    "sg:city":"Killeen",
    "sg:classifiers":[
        {
            "category":"Banks & Credit Unions",
            "subcategory":"Investment Brokerage",
            "type":"Services"
        }
    ],
    "sg:phone":"+1 254 554 4426",
    "sg:postcode":"76541",
    "sg:province":"TX",
    "sg:tags":[
        "consultant",
        "planning",
        "financial"
    ],
    "wof:name":"Raymond James Financial Svc",
    "wof:placetype":"venue"
},
  "geometry": {"coordinates":[-97.73140600000001,31.097306],"type":"Point"}
}