{
  "type": "Feature",
  "properties": {
    "iso:country":"US",
    "sg:address":"6833 Snider Plaza",
    "sg:city":"Dallas",
    "sg:classifiers":[
        {
            "category":"Food & Beverages",
            "subcategory":"Specialty",
            "type":"Retail Goods"
        }
    ],
    "sg:phone":"+1 214 361 8600",
    "sg:postcode":"75205",
    "sg:province":"TX",
    "sg:website":"www.ediblearrangements.com",
    "wof:name":"Edible Arrangements",
    "wof:placetype":"venue"
},
  "geometry": {"coordinates":[-96.787986,32.849174],"type":"Point"}
}