{
  "type": "Feature",
  "properties": {
    "iso:country":"US",
    "sg:address":"5101 Ave H",
    "sg:city":"Rosenberg",
    "sg:classifiers":[
        {
            "category":"Manufacturing",
            "subcategory":"Metals",
            "type":"Manufacturing & Wholesale Goods"
        }
    ],
    "sg:phone":"+1 281 537 4050",
    "sg:postcode":"77471",
    "sg:province":"TX",
    "sg:tags":[
        "blast",
        "furnace",
        "works"
    ],
    "wof:name":"Emco Tool & Die",
    "wof:placetype":"venue"
},
  "geometry": {"coordinates":[-95.77367599999999,29.573978],"type":"Point"}
}