{
  "type": "Feature",
  "properties": {
    "iso:country":"US",
    "sg:address":"104 E Wallace St",
    "sg:city":"San Saba",
    "sg:classifiers":[
        {
            "category":"Professional",
            "type":"Services"
        }
    ],
    "sg:phone":"+1 325 372 3700",
    "sg:postcode":"76877",
    "sg:province":"TX",
    "sg:tags":[
        "establishment"
    ],
    "wof:name":"Global Payments",
    "wof:placetype":"venue"
},
  "geometry": {"coordinates":[-98.720061,31.195706],"type":"Point"}
}