{
  "type": "Feature",
  "properties": {
    "iso:country":"US",
    "sg:address":"1718 Allendale Dr",
    "sg:city":"Lufkin",
    "sg:classifiers":[
        {
            "category":"Building & Trades",
            "subcategory":"Construction",
            "type":"Services"
        }
    ],
    "sg:phone":"+1 936 632 4766",
    "sg:postcode":"75904",
    "sg:province":"TX",
    "sg:tags":[
        "special",
        "contractor"
    ],
    "wof:name":"Albert Walker Concrete",
    "wof:placetype":"venue"
},
  "geometry": {"coordinates":[-94.744533,31.315719],"type":"Point"}
}