{
  "type": "Feature",
  "properties": {
    "iso:country":"US",
    "sg:address":"3106 Hughes Rd",
    "sg:city":"Dickinson",
    "sg:classifiers":[
        {
            "category":"Shopping",
            "subcategory":"Used Merchandise",
            "type":"Retail Goods"
        }
    ],
    "sg:phone":"+1 281 337 0789",
    "sg:postcode":"77539",
    "sg:province":"TX",
    "wof:name":"Treasure Chest",
    "wof:placetype":"venue"
},
  "geometry": {"coordinates":[-95.03845099999999,29.453592],"type":"Point"}
}