{
  "type": "Feature",
  "properties": {
    "iso:country":"US",
    "sg:address":"2117 W Northwest Hwy",
    "sg:city":"Dallas",
    "sg:classifiers":[
        {
            "category":"Recreation",
            "subcategory":"Sailing Club",
            "type":"Entertainment"
        },
        {
            "category":"Shopping",
            "subcategory":"Adult",
            "type":"Retail Goods"
        }
    ],
    "sg:phone":"+1 972 869 3376",
    "sg:postcode":"75220",
    "sg:province":"TX",
    "sg:tags":[
        "gentlemen's"
    ],
    "sg:website":"dallasgentlemensclub.com/",
    "wof:name":"Dallas Gentlemans Club",
    "wof:placetype":"venue"
},
  "geometry": {"coordinates":[-96.904324,32.866326],"type":"Point"}
}