{
  "type": "Feature",
  "properties": {
    "iso:country":"US",
    "sg:address":"2712 Federal Ave",
    "sg:city":"El Paso",
    "sg:classifiers":[
        {
            "category":"Shopping",
            "subcategory":"Jewelry",
            "type":"Retail Goods"
        }
    ],
    "sg:phone":"+1 915 566 4956",
    "sg:postcode":"79930",
    "sg:province":"TX",
    "wof:name":"Anitas Jewelry & Gifts",
    "wof:placetype":"venue"
},
  "geometry": {"coordinates":[-106.462639,31.791293],"type":"Point"}
}