{
  "type": "Feature",
  "properties": {
    "iso:country":"US",
    "sg:address":"5322 W Bellfort St",
    "sg:city":"Houston",
    "sg:classifiers":[
        {
            "category":"Professional",
            "subcategory":"Lawyer & Legal Services",
            "type":"Services"
        }
    ],
    "sg:phone":"+1 713 723 6500",
    "sg:postcode":"77035",
    "sg:province":"TX",
    "sg:tags":[
        "attorney"
    ],
    "wof:name":"Michael S Holmes",
    "wof:placetype":"venue"
},
  "geometry": {"coordinates":[-95.475353,29.660255],"type":"Point"}
}