{
  "type": "Feature",
  "properties": {
    "iso:country":"US",
    "sg:address":"405 Londonderry Dr",
    "sg:city":"Waco",
    "sg:classifiers":[
        {
            "category":"Building & Trades",
            "subcategory":"Equipment Rental",
            "type":"Services"
        }
    ],
    "sg:phone":"+1 254 751 4990",
    "sg:postcode":"76712",
    "sg:province":"TX",
    "sg:tags":[
        "med",
        "leasing"
    ],
    "wof:name":"Providence Health Center Svc",
    "wof:placetype":"venue"
},
  "geometry": {"coordinates":[-97.199808,31.512834],"type":"Point"}
}