{
  "type": "Feature",
  "properties": {
    "iso:country":"US",
    "sg:address":"204 E 3rd St",
    "sg:city":"Bruni",
    "sg:classifiers":[
        {
            "category":"Government",
            "subcategory":"Post Office",
            "type":"Public Place"
        }
    ],
    "sg:phone":"+1 361 747 5495",
    "sg:postcode":"78332",
    "sg:province":"TX",
    "wof:name":"US Post Office",
    "wof:placetype":"venue"
},
  "geometry": {"coordinates":[-98.075542,27.753029],"type":"Point"}
}