{
  "type": "Feature",
  "properties": {
    "iso:country":"US",
    "sg:address":"3101 Surfside Blvd",
    "sg:city":"Corpus Christi",
    "sg:classifiers":[
        {
            "category":"Travel",
            "subcategory":"Hotels & Motels",
            "type":"Entertainment"
        }
    ],
    "sg:phone":"+1 361 887 1010",
    "sg:postcode":"78402",
    "sg:province":"TX",
    "sg:tags":[
        "operation"
    ],
    "wof:name":"Regency Inn",
    "wof:placetype":"venue"
},
  "geometry": {"coordinates":[-97.390614,27.819336],"type":"Point"}
}