{
  "type": "Feature",
  "properties": {
    "iso:country":"US",
    "sg:address":"5833 Armour Dr",
    "sg:city":"Houston",
    "sg:classifiers":[
        {
            "category":"Real Estate",
            "subcategory":"Real Estate Operator",
            "type":"Services"
        }
    ],
    "sg:phone":"+1 713 674 7573",
    "sg:postcode":"77020",
    "sg:province":"TX",
    "sg:tags":[
        "building",
        "nonresidential"
    ],
    "wof:name":"CM Chapman Properties LLC",
    "wof:placetype":"venue"
},
  "geometry": {"coordinates":[-95.304852,29.757855],"type":"Point"}
}