{
  "type": "Feature",
  "properties": {
    "iso:country":"US",
    "sg:address":"2150 W 18th St",
    "sg:city":"Houston",
    "sg:classifiers":[
        {
            "category":"Banks & Credit Unions",
            "subcategory":"Bank",
            "type":"Services"
        }
    ],
    "sg:phone":"+1 713 864 4663",
    "sg:postcode":"77008",
    "sg:province":"TX",
    "sg:tags":[
        "loan",
        "real estate"
    ],
    "wof:name":"Allied Home Mortgage Capital",
    "wof:placetype":"venue"
},
  "geometry": {"coordinates":[-95.43741900000001,29.801529],"type":"Point"}
}