{
  "type": "Feature",
  "properties": {
    "iso:country":"US",
    "sg:address":"1422 Harlin Dr",
    "sg:city":"Wylie",
    "sg:classifiers":[
        {
            "category":"Professional",
            "subcategory":"Computer Services",
            "type":"Services"
        }
    ],
    "sg:phone":"+1 972 442 2764",
    "sg:postcode":"75098",
    "sg:province":"TX",
    "sg:tags":[
        "datum"
    ],
    "wof:name":"Katek & Co Inc",
    "wof:placetype":"venue"
},
  "geometry": {"coordinates":[-96.54078699999999,33.034099],"type":"Point"}
}