{
  "type": "Feature",
  "properties": {
    "iso:country":"US",
    "sg:address":"10300 N Central Expy",
    "sg:city":"Dallas",
    "sg:classifiers":[
        {
            "category":"Insurance",
            "subcategory":"Insurance Agent",
            "type":"Services"
        }
    ],
    "sg:phone":"+1 214 891 0400",
    "sg:postcode":"75231",
    "sg:province":"TX",
    "wof:name":"William Miller Construction",
    "wof:placetype":"venue"
},
  "geometry": {"coordinates":[-96.76948299999999,32.887667],"type":"Point"}
}