{
  "type": "Feature",
  "properties": {
    "iso:country":"US",
    "sg:address":"2517 N Velasco St",
    "sg:city":"Angleton",
    "sg:classifiers":[
        {
            "category":"Restaurant",
            "type":"Food & Drink"
        }
    ],
    "sg:phone":"+1 979 849 9914",
    "sg:postcode":"77515",
    "sg:province":"TX",
    "wof:name":"Chili's Bar & Grill",
    "wof:placetype":"venue"
},
  "geometry": {"coordinates":[-95.43607299999999,29.206591],"type":"Point"}
}