{
  "type": "Feature",
  "properties": {
    "iso:country":"US",
    "sg:address":"3463 Magic Dr",
    "sg:city":"San Antonio",
    "sg:classifiers":[
        {
            "category":"Shopping",
            "subcategory":"Computers & Home Electronics",
            "type":"Retail Goods"
        }
    ],
    "sg:phone":"+1 210 344 0012",
    "sg:postcode":"78229",
    "sg:province":"TX",
    "sg:tags":[
        "management",
        "asset",
        "fixed"
    ],
    "wof:name":"Instant Data Technologies Inc",
    "wof:placetype":"venue"
},
  "geometry": {"coordinates":[-98.558194,29.50121],"type":"Point"}
}