{
  "type": "Feature",
  "properties": {
    "iso:country":"US",
    "sg:address":"80 Hearthwood Dr",
    "sg:city":"Coppell",
    "sg:classifiers":[
        {
            "category":"Real Estate",
            "subcategory":"Real Estate Operator",
            "type":"Services"
        }
    ],
    "sg:phone":"+1 972 393 7023",
    "sg:postcode":"75019",
    "sg:province":"TX",
    "sg:tags":[
        "building",
        "nonresidential"
    ],
    "wof:name":"Brockbank Village Shopping",
    "wof:placetype":"venue"
},
  "geometry": {"coordinates":[-96.99484099999999,32.963737],"type":"Point"}
}