{
  "type": "Feature",
  "properties": {
    "iso:country":"US",
    "sg:address":"420 Water St",
    "sg:city":"Kerrville",
    "sg:classifiers":[
        {
            "category":"Professional",
            "subcategory":"Accounting & Tax Preparation",
            "type":"Services"
        }
    ],
    "sg:phone":"+1 830 257 1040",
    "sg:postcode":"78028",
    "sg:province":"TX",
    "sg:tags":[
        "bookkeeping",
        "general"
    ],
    "wof:name":"Keep Your Sanity",
    "wof:placetype":"venue"
},
  "geometry": {"coordinates":[-99.144412,30.049379],"type":"Point"}
}