{
  "type": "Feature",
  "properties": {
    "iso:country":"US",
    "sg:address":"12929 Northwest Fwy",
    "sg:city":"Houston",
    "sg:classifiers":[
        {
            "category":"Travel",
            "subcategory":"Hotels & Motels",
            "type":"Entertainment"
        }
    ],
    "sg:phone":"+1 713 939 0800",
    "sg:postcode":"77040",
    "sg:province":"TX",
    "wof:name":"Red Roof Inns",
    "wof:placetype":"venue"
},
  "geometry": {"coordinates":[-95.496201,29.8431],"type":"Point"}
}