{
  "type": "Feature",
  "properties": {
    "iso:country":"US",
    "sg:address":"11200 Forest Shower Rd",
    "sg:city":"San Antonio",
    "sg:classifiers":[
        {
            "category":"Shopping",
            "subcategory":"Used Merchandise",
            "type":"Retail Goods"
        }
    ],
    "sg:phone":"+1 210 637 0644",
    "sg:postcode":"78233",
    "sg:province":"TX",
    "wof:name":"M S Elisa",
    "wof:placetype":"venue"
},
  "geometry": {"coordinates":[-98.35006799999999,29.541558],"type":"Point"}
}