{
  "type": "Feature",
  "properties": {
    "iso:country":"US",
    "sg:address":"6801 Carriage Ln",
    "sg:city":"Colleyville",
    "sg:classifiers":[
        {
            "category":"Professional",
            "type":"Services"
        }
    ],
    "sg:phone":"+1 817 251 5168",
    "sg:postcode":"76034",
    "sg:province":"TX",
    "wof:name":"Pack Man Energy Inc",
    "wof:placetype":"venue"
},
  "geometry": {"coordinates":[-97.13443700000001,32.906522],"type":"Point"}
}