{
  "type": "Feature",
  "properties": {
    "iso:country":"US",
    "sg:address":"2032 Orchid Ave A",
    "sg:city":"Mcallen",
    "sg:classifiers":[
        {
            "category":"Professional",
            "subcategory":"Art Services",
            "type":"Services"
        }
    ],
    "sg:phone":"+1 956 682 5077",
    "sg:postcode":"78504",
    "sg:province":"TX",
    "sg:tags":[
        "agent",
        "artist"
    ],
    "wof:name":"Vfr Specialties",
    "wof:placetype":"venue"
},
  "geometry": {"coordinates":[-98.234846,26.242465],"type":"Point"}
}