{
  "type": "Feature",
  "properties": {
    "iso:country":"US",
    "sg:address":"1718 S 23rd St",
    "sg:city":"Mcallen",
    "sg:classifiers":[
        {
            "category":"Retail",
            "subcategory":"Repair Shop",
            "type":"Services"
        }
    ],
    "sg:phone":"+1 956 618 5447",
    "sg:postcode":"78503",
    "sg:province":"TX",
    "sg:tags":[
        "related"
    ],
    "wof:name":"Martin's Commercial Repair",
    "wof:placetype":"venue"
},
  "geometry": {"coordinates":[-98.24777,26.190709],"type":"Point"}
}