{
  "type": "Feature",
  "properties": {
    "iso:country":"US",
    "sg:address":"3917 Coronado Dr",
    "sg:city":"Plano",
    "sg:classifiers":[
        {
            "category":"Building & Trades",
            "subcategory":"Landscaping Services",
            "type":"Services"
        }
    ],
    "sg:phone":"+1 972 516 4792",
    "sg:postcode":"75074",
    "sg:province":"TX",
    "sg:tags":[
        "lawn",
        "maintenance",
        "grounds"
    ],
    "wof:name":"Rodriguez Residential Lawn",
    "wof:placetype":"venue"
},
  "geometry": {"coordinates":[-96.65558799999999,33.01981],"type":"Point"}
}