{
  "type": "Feature",
  "properties": {
    "iso:country":"US",
    "sg:address":"1907 Preston Ave",
    "sg:city":"Pasadena",
    "sg:classifiers":[
        {
            "category":"Shopping",
            "subcategory":"Gifts & Souvenirs",
            "type":"Retail Goods"
        }
    ],
    "sg:phone":"+1 713 472 0895",
    "sg:postcode":"77503",
    "sg:province":"TX",
    "wof:name":"Pasadena Floral Center",
    "wof:placetype":"venue"
},
  "geometry": {"coordinates":[-95.17254,29.685369],"type":"Point"}
}