{
  "type": "Feature",
  "properties": {
    "iso:country":"US",
    "sg:address":"309 Airport Dr",
    "sg:city":"Tyler",
    "sg:classifiers":[
        {
            "category":"Airport",
            "type":"Transportation"
        }
    ],
    "sg:phone":"+1 903 526 3737",
    "sg:postcode":"75704",
    "sg:province":"TX",
    "sg:tags":[
        "aircraft",
        "storage"
    ],
    "wof:name":"Cox Hangar Pounds Airport",
    "wof:placetype":"venue"
},
  "geometry": {"coordinates":[-95.40138899999999,32.361165],"type":"Point"}
}