{
  "type": "Feature",
  "properties": {
    "iso:country":"US",
    "sg:address":"4527 Clawson Rd",
    "sg:city":"Austin",
    "sg:classifiers":[
        {
            "category":"Retail",
            "subcategory":"Repair Shop",
            "type":"Services"
        },
        {
            "category":"Home & Garden",
            "subcategory":"Building Materials",
            "type":"Retail Goods"
        },
        {
            "category":"Building & Trades",
            "subcategory":"Construction",
            "type":"Services"
        }
    ],
    "sg:phone":"+1 512 784 5970",
    "sg:postcode":"78745",
    "sg:province":"TX",
    "sg:tags":[
        "handyman",
        "improvement",
        "fix-it",
        "maintenance",
        "contractor",
        "painting"
    ],
    "sg:website":"http://www.APlusHandymenTX.com",
    "wof:name":"A Plus Handymen",
    "wof:placetype":"venue"
},
  "geometry": {"coordinates":[-97.78694900000001,30.224199],"type":"Point"}
}