{
  "type": "Feature",
  "properties": {
    "iso:country":"US",
    "sg:address":"13645 Fawn Trl",
    "sg:city":"Conroe",
    "sg:classifiers":[
        {
            "category":"Retail",
            "subcategory":"Repair Shop",
            "type":"Services"
        }
    ],
    "sg:phone":"+1 936 273 1314",
    "sg:postcode":"77302",
    "sg:province":"TX",
    "wof:name":"Lock Doctor",
    "wof:placetype":"venue"
},
  "geometry": {"coordinates":[-95.41833,30.256606],"type":"Point"}
}