{
  "type": "Feature",
  "properties": {
    "iso:country":"US",
    "sg:address":"6713 Telephone Rd",
    "sg:city":"Fort Worth",
    "sg:classifiers":[
        {
            "category":"Government",
            "subcategory":"Office",
            "type":"Public Place"
        }
    ],
    "sg:phone":"+1 817 238 4435",
    "sg:postcode":"76135",
    "sg:province":"TX",
    "sg:tags":[
        "county",
        "taxation"
    ],
    "wof:name":"Tarrant County Tax Assessor",
    "wof:placetype":"venue"
},
  "geometry": {"coordinates":[-97.43570699999999,32.81228],"type":"Point"}
}