{
  "type": "Feature",
  "properties": {
    "iso:country":"US",
    "sg:address":"3305 45th St",
    "sg:city":"Lubbock",
    "sg:classifiers":[
        {
            "category":"Building & Trades",
            "subcategory":"Construction",
            "type":"Services"
        }
    ],
    "sg:phone":"+1 806 799 0313",
    "sg:postcode":"79413",
    "sg:province":"TX",
    "sg:tags":[
        "concrete",
        "contractor"
    ],
    "wof:name":"Shannon Young General Contrs",
    "wof:placetype":"venue"
},
  "geometry": {"coordinates":[-101.88774600000001,33.553225],"type":"Point"}
}