{
  "type": "Feature",
  "properties": {
    "iso:country":"US",
    "sg:address":"3209 Lovers Ln",
    "sg:city":"Dallas",
    "sg:classifiers":[
        {
            "category":"Professional",
            "subcategory":"Computer Services",
            "type":"Services"
        }
    ],
    "sg:phone":"+1 214 725 5200",
    "sg:postcode":"75225",
    "sg:province":"TX",
    "sg:tags":[
        "datum"
    ],
    "wof:name":"Duck Foot Web Designs",
    "wof:placetype":"venue"
},
  "geometry": {"coordinates":[-96.784803,32.85105],"type":"Point"}
}