{
  "type": "Feature",
  "properties": {
    "iso:country":"US",
    "sg:address":"1532 Gessner Dr",
    "sg:city":"Houston",
    "sg:classifiers":[
        {
            "category":"Organizations",
            "subcategory":"Religious Organization",
            "type":"Services"
        }
    ],
    "sg:phone":"+1 713 932 6938",
    "sg:postcode":"77080",
    "sg:province":"TX",
    "wof:name":"Jesus Omar Perez",
    "wof:placetype":"venue"
},
  "geometry": {"coordinates":[-95.54469400000001,29.79778],"type":"Point"}
}