{
  "type": "Feature",
  "properties": {
    "iso:country":"US",
    "sg:address":"1927 Faithon P Lucas Sr Blvd",
    "sg:city":"Mesquite",
    "sg:classifiers":[
        {
            "category":"Food & Beverages",
            "subcategory":"Bakery",
            "type":"Retail Goods"
        }
    ],
    "sg:phone":"+1 972 222 8441",
    "sg:postcode":"75181",
    "sg:province":"TX",
    "sg:tags":[
        "doughnut"
    ],
    "wof:name":"Donut Palace",
    "wof:placetype":"venue"
},
  "geometry": {"coordinates":[-96.552983,32.743565],"type":"Point"}
}