{
  "type": "Feature",
  "properties": {
    "iso:country":"US",
    "sg:address":"107 Ave D",
    "sg:city":"Highlands",
    "sg:classifiers":[
        {
            "category":"Shopping",
            "subcategory":"Florist",
            "type":"Retail Goods"
        }
    ],
    "sg:phone":"+1 281 426 2504",
    "sg:postcode":"77562",
    "sg:province":"TX",
    "wof:name":"Bouquets By Mae",
    "wof:placetype":"venue"
},
  "geometry": {"coordinates":[-95.05716700000001,29.813429],"type":"Point"}
}