{
  "type": "Feature",
  "properties": {
    "iso:country":"US",
    "sg:address":"1300 N Washington St",
    "sg:city":"Pilot Point",
    "sg:classifiers":[
        {
            "category":"Education",
            "subcategory":"School",
            "type":"Public Place"
        }
    ],
    "sg:phone":"+1 940 686 2189",
    "sg:postcode":"76258",
    "sg:province":"TX",
    "wof:name":"Pilot Point High School",
    "wof:placetype":"venue"
},
  "geometry": {"coordinates":[-96.9474,33.41012],"type":"Point"}
}