{
  "type": "Feature",
  "properties": {
    "iso:country":"US",
    "sg:address":"1226 N Pacific St",
    "sg:city":"Mineola",
    "sg:classifiers":[
        {
            "category":"Restaurant",
            "type":"Food & Drink"
        }
    ],
    "sg:menulink":"http://www.allmenus.com/tx/mineola/130306-subway/menu/",
    "sg:phone":"+1 903 569 0116",
    "sg:postcode":"75773",
    "sg:province":"TX",
    "sg:tags":[
        "american",
        "sandwich"
    ],
    "wof:name":"Subway",
    "wof:placetype":"venue"
},
  "geometry": {"coordinates":[-95.483943,32.684571],"type":"Point"}
}