{
  "type": "Feature",
  "properties": {
    "iso:country":"US",
    "sg:address":"5633 Usher St",
    "sg:city":"Lewisville",
    "sg:classifiers":[
        {
            "category":"Wholesale",
            "subcategory":"Electrical",
            "type":"Manufacturing & Wholesale Goods"
        },
        {
            "category":"Professional",
            "subcategory":"Advertising",
            "type":"Services"
        }
    ],
    "sg:phone":"+1 972 370 0664",
    "sg:postcode":"75056",
    "sg:province":"TX",
    "sg:tags":[
        "distribution",
        "electronic"
    ],
    "wof:name":"Circuit Savers",
    "wof:placetype":"venue"
},
  "geometry": {"coordinates":[-96.863985,33.098902],"type":"Point"}
}