{
  "type": "Feature",
  "properties": {
    "iso:country":"US",
    "sg:address":"109 E Franklin St",
    "sg:city":"Waxahachie",
    "sg:classifiers":[
        {
            "category":"Building & Trades",
            "subcategory":"Construction",
            "type":"Services"
        }
    ],
    "sg:phone":"+1 972 938 7010",
    "sg:postcode":"75165",
    "sg:province":"TX",
    "sg:tags":[
        "restoration",
        "commercial",
        "contractor"
    ],
    "wof:name":"Talent Restoration & Water",
    "wof:placetype":"venue"
},
  "geometry": {"coordinates":[-96.84705099999999,32.384637],"type":"Point"}
}