{
  "type": "Feature",
  "properties": {
    "iso:country":"US",
    "sg:address":"307 Sunset Dr",
    "sg:city":"Round Rock",
    "sg:classifiers":[
        {
            "category":"Professional",
            "subcategory":"Engineering",
            "type":"Services"
        }
    ],
    "sg:phone":"+1 512 244 4279",
    "sg:postcode":"78664",
    "sg:province":"TX",
    "sg:tags":[
        "civil",
        "construction",
        "management",
        "engineer"
    ],
    "wof:name":"Corridor Engineering Co",
    "wof:placetype":"venue"
},
  "geometry": {"coordinates":[-97.68311799999999,30.51472],"type":"Point"}
}