{
  "type": "Feature",
  "properties": {
    "iso:country":"US",
    "sg:address":"6801 Preston Rd",
    "sg:city":"Dallas",
    "sg:classifiers":[
        {
            "category":"Retail",
            "subcategory":"Auto Repair",
            "type":"Services"
        }
    ],
    "sg:phone":"+1 214 252 9844",
    "sg:postcode":"75205",
    "sg:province":"TX",
    "sg:tags":[
        "automobile",
        "lubrication"
    ],
    "wof:name":"Vintage Lube Ctr",
    "wof:placetype":"venue"
},
  "geometry": {"coordinates":[-96.80425700000001,32.849215],"type":"Point"}
}