{
  "type": "Feature",
  "properties": {
    "iso:country":"US",
    "sg:address":"710 W 28th St",
    "sg:city":"Austin",
    "sg:classifiers":[
        {
            "category":"Organizations",
            "subcategory":"Community Association",
            "type":"Services"
        }
    ],
    "sg:phone":"+1 512 478 0205",
    "sg:postcode":"78705",
    "sg:province":"TX",
    "wof:name":"PI Lambda PHI",
    "wof:placetype":"venue"
},
  "geometry": {"coordinates":[-97.745079,30.29356],"type":"Point"}
}