{
  "type": "Feature",
  "properties": {
    "iso:country":"US",
    "sg:address":"7219 Longvine Dr",
    "sg:city":"Houston",
    "sg:classifiers":[
        {
            "category":"Shopping",
            "subcategory":"Computers & Home Electronics",
            "type":"Retail Goods"
        }
    ],
    "sg:phone":"+1 713 436 0861",
    "sg:postcode":"77072",
    "sg:province":"TX",
    "sg:tags":[
        "software"
    ],
    "sg:website":"www.nivert.com",
    "wof:name":"Nivert Technologies Inc",
    "wof:placetype":"venue"
},
  "geometry": {"coordinates":[-95.607337,29.698935],"type":"Point"}
}