{
  "type": "Feature",
  "properties": {
    "iso:country":"US",
    "sg:address":"9201 Fairbanks N Houston Rd",
    "sg:city":"Houston",
    "sg:classifiers":[
        {
            "category":"Wholesale",
            "subcategory":"Machinery & Supplies",
            "type":"Manufacturing & Wholesale Goods"
        }
    ],
    "sg:phone":"+1 281 807 1083",
    "sg:postcode":"77064",
    "sg:province":"TX",
    "sg:tags":[
        "equipment",
        "hydraulic"
    ],
    "wof:name":"DWS Hydraulics",
    "wof:placetype":"venue"
},
  "geometry": {"coordinates":[-95.52505499999999,29.914914],"type":"Point"}
}