{
  "type": "Feature",
  "properties": {
    "iso:country":"US",
    "sg:address":"251 N Harbin Dr Ste C",
    "sg:city":"Stephenville",
    "sg:classifiers":[
        {
            "category":"Health Services",
            "subcategory":"Chiropractor",
            "type":"Services"
        }
    ],
    "sg:phone":"+1 254 968 5075",
    "sg:postcode":"76401",
    "sg:province":"TX",
    "sg:tags":[
        "chiropractic"
    ],
    "wof:name":"Stephenville Chiropractic",
    "wof:placetype":"venue"
},
  "geometry": {"coordinates":[-98.223389,32.212096],"type":"Point"}
}