{
  "type": "Feature",
  "properties": {
    "iso:country":"US",
    "sg:address":"902 Frostwood Dr",
    "sg:city":"Houston",
    "sg:classifiers":[
        {
            "category":"Health Services",
            "subcategory":"Doctor",
            "type":"Services"
        }
    ],
    "sg:phone":"+1 713 984 9272",
    "sg:postcode":"77024",
    "sg:province":"TX",
    "sg:tags":[
        "physician",
        "surgeon",
        "surgeons",
        "surgery-general"
    ],
    "wof:name":"Northwest Houston Surgical Associates",
    "wof:placetype":"venue"
},
  "geometry": {"coordinates":[-95.54776699999999,29.779258],"type":"Point"}
}