{
  "type": "Feature",
  "properties": {
    "iso:country":"US",
    "sg:address":"5802 Windmier Ln",
    "sg:city":"Dallas",
    "sg:classifiers":[
        {
            "category":"Wholesale",
            "subcategory":"Durable Goods & Equipment",
            "type":"Manufacturing & Wholesale Goods"
        }
    ],
    "sg:phone":"+1 972 931 6722",
    "sg:postcode":"75252",
    "sg:province":"TX",
    "sg:tags":[
        "representative",
        "manufacturer"
    ],
    "wof:name":"Remark Inc",
    "wof:placetype":"venue"
},
  "geometry": {"coordinates":[-96.80553,32.998645],"type":"Point"}
}