{
  "type": "Feature",
  "properties": {
    "iso:country":"US",
    "sg:address":"4210 Durazno Ave",
    "sg:city":"El Paso",
    "sg:classifiers":[
        {
            "category":"Autos & Motor Vehicles",
            "subcategory":"Auto Supplies",
            "type":"Retail Goods"
        }
    ],
    "sg:phone":"+1 915 544 7304",
    "sg:postcode":"79905",
    "sg:province":"TX",
    "sg:tags":[
        "automobile",
        "parts"
    ],
    "wof:name":"GOT Supply",
    "wof:placetype":"venue"
},
  "geometry": {"coordinates":[-106.44084700000001,31.775877],"type":"Point"}
}