{
  "type": "Feature",
  "properties": {
    "iso:country":"US",
    "sg:address":"1101 E Main St",
    "sg:city":"Grand Prairie",
    "sg:classifiers":[
        {
            "category":"Insurance",
            "subcategory":"Insurance Agent",
            "type":"Services"
        }
    ],
    "sg:phone":"+1 972 263 6400",
    "sg:postcode":"75050",
    "sg:province":"TX",
    "wof:name":"Best-Rate Auto Insurance Inc",
    "wof:placetype":"venue"
},
  "geometry": {"coordinates":[-96.98747,32.747181],"type":"Point"}
}