{
  "type": "Feature",
  "properties": {
    "iso:country":"US",
    "sg:address":"1301 N Zaragoza Rd",
    "sg:city":"El Paso",
    "sg:classifiers":[
        {
            "category":"Autos & Motor Vehicles",
            "subcategory":"Automobile Sales",
            "type":"Retail Goods"
        }
    ],
    "sg:phone":"+1 915 633 9100",
    "sg:postcode":"79936",
    "sg:province":"TX",
    "sg:tags":[
        "car",
        "dealer"
    ],
    "wof:name":"Thrifty Auto Sales",
    "wof:placetype":"venue"
},
  "geometry": {"coordinates":[-106.30274799999999,31.725182],"type":"Point"}
}