{
  "type": "Feature",
  "properties": {
    "iso:country":"US",
    "sg:address":"204 Kent Ln",
    "sg:city":"Cedar Park",
    "sg:classifiers":[
        {
            "category":"Building & Trades",
            "subcategory":"Construction",
            "type":"Services"
        }
    ],
    "sg:phone":"+1 512 996 9884",
    "sg:postcode":"78613",
    "sg:province":"TX",
    "sg:tags":[
        "contractor"
    ],
    "wof:name":"Chasco Contracting",
    "wof:placetype":"venue"
},
  "geometry": {"coordinates":[-97.809111,30.495264],"type":"Point"}
}