{
  "type": "Feature",
  "properties": {
    "iso:country":"US",
    "sg:address":"14730 Treborway Dr",
    "sg:city":"Houston",
    "sg:classifiers":[
        {
            "category":"Professional",
            "subcategory":"Business Services",
            "type":"Services"
        }
    ],
    "sg:phone":"+1 281 583 7788",
    "sg:postcode":"77014",
    "sg:province":"TX",
    "wof:name":"Hexcorps Inc",
    "wof:placetype":"venue"
},
  "geometry": {"coordinates":[-95.48694500000001,29.988668],"type":"Point"}
}