{
  "type": "Feature",
  "properties": {
    "iso:country":"US",
    "sg:address":"210 Shannon Rd W",
    "sg:city":"Sulphur Springs",
    "sg:classifiers":[
        {
            "category":"Manufacturing",
            "subcategory":"Signs",
            "type":"Manufacturing & Wholesale Goods"
        },
        {
            "category":"Shopping",
            "type":"Retail Goods"
        }
    ],
    "sg:phone":"+1 903 438 9700",
    "sg:postcode":"75482",
    "sg:province":"TX",
    "sg:tags":[
        "merchandise"
    ],
    "wof:name":"Sign Express",
    "wof:placetype":"venue"
},
  "geometry": {"coordinates":[-95.600414,33.115851],"type":"Point"}
}