{
  "type": "Feature",
  "properties": {
    "iso:country":"US",
    "sg:address":"528 S Treadaway Blvd",
    "sg:city":"Abilene",
    "sg:classifiers":[
        {
            "category":"Building & Trades",
            "subcategory":"Construction",
            "type":"Services"
        }
    ],
    "sg:phone":"+1 325 691 1379",
    "sg:postcode":"79602",
    "sg:province":"TX",
    "sg:tags":[
        "home",
        "builder"
    ],
    "wof:name":"Malone Insulation Co",
    "wof:placetype":"venue"
},
  "geometry": {"coordinates":[-99.72784799999999,32.443712],"type":"Point"}
}