{
  "type": "Feature",
  "properties": {
    "iso:country":"US",
    "sg:address":"3131 Bell St",
    "sg:city":"Amarillo",
    "sg:classifiers":[
        {
            "category":"Wholesale",
            "subcategory":"Machinery & Supplies",
            "type":"Manufacturing & Wholesale Goods"
        }
    ],
    "sg:phone":"+1 806 355 4086",
    "sg:postcode":"79106",
    "sg:province":"TX",
    "sg:tags":[
        "equipment",
        "establishment"
    ],
    "wof:name":"Twin Distributing",
    "wof:placetype":"venue"
},
  "geometry": {"coordinates":[-101.902247,35.181258],"type":"Point"}
}