{
  "type": "Feature",
  "properties": {
    "iso:country":"US",
    "sg:address":"317 N 2nd St",
    "sg:city":"Temple",
    "sg:classifiers":[
        {
            "category":"Health Services",
            "subcategory":"Hospital",
            "type":"Services"
        },
        {
            "category":"Social Services",
            "type":"Services"
        }
    ],
    "sg:phone":"+1 254 791 0002",
    "sg:postcode":"76501",
    "sg:province":"TX",
    "sg:tags":[
        "individual",
        "mental",
        "family"
    ],
    "wof:name":"Children's Mental Health Svc",
    "wof:placetype":"venue"
},
  "geometry": {"coordinates":[-97.338729,31.100181],"type":"Point"}
}