{
  "type": "Feature",
  "properties": {
    "iso:country":"US",
    "sg:address":"8935 Knight Rd",
    "sg:city":"Houston",
    "sg:classifiers":[
        {
            "category":"Health Services",
            "subcategory":"Medical Lab",
            "type":"Services"
        }
    ],
    "sg:phone":"+1 713 795 4299",
    "sg:postcode":"77054",
    "sg:province":"TX",
    "sg:tags":[
        "laboratory"
    ],
    "wof:name":"Clinical Pathology Labs",
    "wof:placetype":"venue"
},
  "geometry": {"coordinates":[-95.399753,29.676376],"type":"Point"}
}