{
  "type": "Feature",
  "properties": {
    "iso:country":"US",
    "sg:address":"405 Jim Wright Fwy S",
    "sg:city":"White Settlement",
    "sg:classifiers":[
        {
            "category":"Real Estate",
            "subcategory":"Real Estate Agent",
            "type":"Services"
        }
    ],
    "sg:phone":"+1 817 246 1076",
    "sg:postcode":"76108",
    "sg:province":"TX",
    "sg:tags":[
        "management"
    ],
    "wof:name":"Havener Co",
    "wof:placetype":"venue"
},
  "geometry": {"coordinates":[-97.47816899999999,32.755853],"type":"Point"}
}