{
  "type": "Feature",
  "properties": {
    "iso:country":"US",
    "sg:address":"310 Terrace Dr",
    "sg:city":"Richardson",
    "sg:classifiers":[
        {
            "category":"Restaurant",
            "type":"Food & Drink"
        }
    ],
    "sg:phone":"+1 972 231 6371",
    "sg:postcode":"75081",
    "sg:province":"TX",
    "sg:tags":[
        "dim",
        "style",
        "chinese",
        "family",
        "sum",
        "asian",
        "pan"
    ],
    "sg:website":"http://www.maxines.com",
    "wof:name":"Maxine's Chinese Restaurant",
    "wof:placetype":"venue"
},
  "geometry": {"coordinates":[-96.728996,32.952],"type":"Point"}
}