{
  "type": "Feature",
  "properties": {
    "iso:country":"US",
    "sg:address":"3301 Santa Barbara St",
    "sg:city":"Laredo",
    "sg:classifiers":[
        {
            "category":"Manufacturing",
            "subcategory":"Food",
            "type":"Manufacturing & Wholesale Goods"
        }
    ],
    "sg:phone":"+1 956 723 4506",
    "sg:postcode":"78046",
    "sg:province":"TX",
    "sg:tags":[
        "corn",
        "chips",
        "potato"
    ],
    "wof:name":"Snack El Perico",
    "wof:placetype":"venue"
},
  "geometry": {"coordinates":[-99.461798,27.484599],"type":"Point"}
}