{
  "type": "Feature",
  "properties": {
    "iso:country":"US",
    "sg:address":"690 E Lamar Blvd",
    "sg:city":"Arlington",
    "sg:classifiers":[
        {
            "category":"Professional",
            "subcategory":"Employment Agencies",
            "type":"Services"
        }
    ],
    "sg:phone":"+1 817 860 6100",
    "sg:postcode":"76011",
    "sg:province":"TX",
    "sg:tags":[
        "help",
        "supply"
    ],
    "wof:name":"Remedy Intelligent Staffing",
    "wof:placetype":"venue"
},
  "geometry": {"coordinates":[-97.104895,32.762818],"type":"Point"}
}