{
  "type": "Feature",
  "properties": {
    "iso:country":"US",
    "sg:address":"3810 N Navarro St",
    "sg:city":"Victoria",
    "sg:classifiers":[
        {
            "category":"Fast Food",
            "type":"Food & Drink"
        },
        {
            "category":"Restaurant",
            "type":"Food & Drink"
        }
    ],
    "sg:phone":"+1 361 572 0876",
    "sg:postcode":"77901",
    "sg:province":"TX",
    "sg:tags":[
        "chicken",
        "take"
    ],
    "sg:website":"http://www.churchschicken.com",
    "wof:name":"Church's Chicken",
    "wof:placetype":"venue"
},
  "geometry": {"coordinates":[-97.001193,28.829962],"type":"Point"}
}