{
  "type": "Feature",
  "properties": {
    "iso:country":"US",
    "sg:address":"3307 Northland Dr",
    "sg:city":"Austin",
    "sg:classifiers":[
        {
            "category":"Health Services",
            "subcategory":"Doctor",
            "type":"Services"
        }
    ],
    "sg:phone":"+1 512 459 6000",
    "sg:postcode":"78731",
    "sg:province":"TX",
    "wof:name":"Withers George PhD",
    "wof:placetype":"venue"
},
  "geometry": {"coordinates":[-97.75630700000001,30.336745],"type":"Point"}
}