{
  "type": "Feature",
  "properties": {
    "iso:country":"US",
    "sg:address":"210 W Broad St",
    "sg:city":"Mineola",
    "sg:classifiers":[
        {
            "category":"Building & Trades",
            "subcategory":"Equipment Rental",
            "type":"Services"
        }
    ],
    "sg:phone":"+1 903 569 6213",
    "sg:postcode":"75773",
    "sg:province":"TX",
    "sg:tags":[
        "yard"
    ],
    "wof:name":"Rent-A-Center",
    "wof:placetype":"venue"
},
  "geometry": {"coordinates":[-95.491362,32.664015],"type":"Point"}
}