{
  "type": "Feature",
  "properties": {
    "iso:country":"US",
    "sg:address":"3621 Pottsboro Rd",
    "sg:city":"Denison",
    "sg:classifiers":[
        {
            "category":"Professional",
            "subcategory":"Advertising",
            "type":"Services"
        }
    ],
    "sg:phone":"+1 903 465 7447",
    "sg:postcode":"75020",
    "sg:province":"TX",
    "sg:tags":[
        "mailing",
        "shipping"
    ],
    "wof:name":"E Z Mail",
    "wof:placetype":"venue"
},
  "geometry": {"coordinates":[-96.58598000000001,33.763327],"type":"Point"}
}