{
  "type": "Feature",
  "properties": {
    "iso:country":"US",
    "sg:address":"2626 Westheimer Rd",
    "sg:city":"Houston",
    "sg:classifiers":[
        {
            "category":"Personal",
            "subcategory":"Barber",
            "type":"Services"
        }
    ],
    "sg:phone":"+1 713 523 6361",
    "sg:postcode":"77098",
    "sg:province":"TX",
    "sg:tags":[
        "shop"
    ],
    "wof:name":"Avalon Barber Shop",
    "wof:placetype":"venue"
},
  "geometry": {"coordinates":[-95.41909800000001,29.7423],"type":"Point"}
}