{
  "type": "Feature",
  "properties": {
    "iso:country":"US",
    "sg:address":"3500 Jefferson St",
    "sg:city":"Austin",
    "sg:classifiers":[
        {
            "category":"Social Services",
            "type":"Services"
        }
    ],
    "sg:phone":"+1 512 420 0046",
    "sg:postcode":"78731",
    "sg:province":"TX",
    "sg:tags":[
        "worker"
    ],
    "wof:name":"Michele Langmead Lcsw",
    "wof:placetype":"venue"
},
  "geometry": {"coordinates":[-97.750664,30.309185],"type":"Point"}
}