{
  "type": "Feature",
  "properties": {
    "iso:country":"US",
    "sg:address":"2305 N Big Spring St",
    "sg:city":"Midland",
    "sg:classifiers":[
        {
            "category":"Home & Garden",
            "subcategory":"Furniture",
            "type":"Retail Goods"
        }
    ],
    "sg:phone":"+1 432 682 7921",
    "sg:postcode":"79705",
    "sg:province":"TX",
    "wof:name":"Credit World",
    "wof:placetype":"venue"
},
  "geometry": {"coordinates":[-102.081053,32.021392],"type":"Point"}
}