{
  "type": "Feature",
  "properties": {
    "iso:country":"US",
    "sg:address":"8259 Endicott Ln",
    "sg:city":"Dallas",
    "sg:classifiers":[
        {
            "category":"Manufacturing",
            "subcategory":"Food",
            "type":"Manufacturing & Wholesale Goods"
        }
    ],
    "sg:phone":"+1 214 388 6054",
    "sg:postcode":"75227",
    "sg:province":"TX",
    "sg:tags":[
        "drink",
        "soft",
        "mfg"
    ],
    "wof:name":"Coca-Cola",
    "wof:placetype":"venue"
},
  "geometry": {"coordinates":[-96.67790100000001,32.781592],"type":"Point"}
}