{
  "type": "Feature",
  "properties": {
    "iso:country":"US",
    "sg:address":"3939 Belt Line Rd Ste 700",
    "sg:city":"Addison",
    "sg:classifiers":[
        {
            "category":"Banks & Credit Unions",
            "subcategory":"Financial Services",
            "type":"Services"
        }
    ],
    "sg:phone":"+1 214 432 0443",
    "sg:postcode":"75001",
    "sg:province":"TX",
    "sg:tags":[
        "broker",
        "mortgage"
    ],
    "sg:website":"www.petralending.com",
    "wof:name":"Petra Lending Group",
    "wof:placetype":"venue"
},
  "geometry": {"coordinates":[-96.848653,32.953467],"type":"Point"}
}