{
  "type": "Feature",
  "properties": {
    "iso:country":"US",
    "sg:address":"100 Scarborough Dr",
    "sg:city":"Conroe",
    "sg:classifiers":[
        {
            "category":"Shopping",
            "subcategory":"Discount & Variety Stores",
            "type":"Retail Goods"
        }
    ],
    "sg:phone":"+1 936 539 3500",
    "sg:postcode":"77304",
    "sg:province":"TX",
    "sg:tags":[
        "merchandise",
        "general"
    ],
    "wof:name":"Rivershire Home Sales",
    "wof:placetype":"venue"
},
  "geometry": {"coordinates":[-95.46628,30.292206],"type":"Point"}
}