{
  "type": "Feature",
  "properties": {
    "iso:country":"US",
    "sg:address":"931 Walnut St",
    "sg:city":"Columbus",
    "sg:classifiers":[
        {
            "category":"Home & Garden",
            "subcategory":"Building Materials",
            "type":"Retail Goods"
        }
    ],
    "sg:phone":"+1 979 732 6269",
    "sg:postcode":"78934",
    "sg:province":"TX",
    "sg:tags":[
        "glass",
        "window",
        "plate"
    ],
    "wof:name":"Windshield Xpress",
    "wof:placetype":"venue"
},
  "geometry": {"coordinates":[-96.57312899999999,29.704072],"type":"Point"}
}