{
  "type": "Feature",
  "properties": {
    "iso:country":"US",
    "sg:address":"715 US Hwy 79",
    "sg:city":"Milano",
    "sg:classifiers":[
        {
            "category":"Restaurant",
            "type":"Food & Drink"
        }
    ],
    "sg:phone":"+1 512 455 2921",
    "sg:postcode":"76556",
    "sg:province":"TX",
    "wof:name":"Bullock's Restaurant",
    "wof:placetype":"venue"
},
  "geometry": {"coordinates":[-96.853675,30.713748],"type":"Point"}
}