{
  "type": "Feature",
  "properties": {
    "iso:country":"US",
    "sg:address":"5075 Garth Rd",
    "sg:city":"Baytown",
    "sg:classifiers":[
        {
            "category":"Restaurant",
            "type":"Food & Drink"
        }
    ],
    "sg:phone":"+1 281 421 5988",
    "sg:postcode":"77521",
    "sg:province":"TX",
    "sg:tags":[
        "asian",
        "pan",
        "japanese"
    ],
    "wof:name":"Shogun Japanese Restaurant",
    "wof:placetype":"venue"
},
  "geometry": {"coordinates":[-94.97783099999999,29.779006],"type":"Point"}
}