{
  "type": "Feature",
  "properties": {
    "iso:country":"US",
    "sg:address":"2777 N Stemmons Fwy",
    "sg:city":"Dallas",
    "sg:classifiers":[
        {
            "category":"Professional",
            "subcategory":"Lawyer & Legal Services",
            "type":"Services"
        }
    ],
    "sg:phone":"+1 214 634 9100",
    "sg:postcode":"75207",
    "sg:province":"TX",
    "wof:name":"North East Center For Dispute",
    "wof:placetype":"venue"
},
  "geometry": {"coordinates":[-96.930008,32.981446],"type":"Point"}
}