{
  "type": "Feature",
  "properties": {
    "iso:country":"US",
    "sg:address":"131 FM 71",
    "sg:city":"Sulphur Bluff",
    "sg:classifiers":[
        {
            "category":"Government",
            "subcategory":"Post Office",
            "type":"Public Place"
        }
    ],
    "sg:phone":"+1 903 945 2975",
    "sg:postcode":"75487",
    "sg:province":"TX",
    "wof:name":"US Post Office",
    "wof:placetype":"venue"
},
  "geometry": {"coordinates":[-95.107045,33.359071],"type":"Point"}
}