{
  "type": "Feature",
  "properties": {
    "iso:country":"US",
    "sg:address":"16585 Blanco Rd",
    "sg:city":"San Antonio",
    "sg:classifiers":[
        {
            "category":"Professional",
            "subcategory":"Computer Services",
            "type":"Services"
        }
    ],
    "sg:phone":"+1 210 479 5600",
    "sg:postcode":"78232",
    "sg:province":"TX",
    "sg:tags":[
        "hardware",
        "software"
    ],
    "wof:name":"System Solutions of Texas",
    "wof:placetype":"venue"
},
  "geometry": {"coordinates":[-98.513699,29.589143],"type":"Point"}
}