{
  "type": "Feature",
  "properties": {
    "iso:country":"US",
    "sg:address":"1100 N Fielder Rd Suite 516",
    "sg:city":"Arlington",
    "sg:classifiers":[
        {
            "category":"Personal",
            "subcategory":"Massage",
            "type":"Services"
        },
        {
            "category":"Personal",
            "subcategory":"Beauty Salon",
            "type":"Services"
        },
        {
            "category":"Sports & Exercise",
            "subcategory":"Gym",
            "type":"Entertainment"
        },
        {
            "category":"Personal",
            "subcategory":"Day Spa",
            "type":"Services"
        },
        {
            "category":"Personal",
            "subcategory":"Nail Salon",
            "type":"Services"
        }
    ],
    "sg:phone":"+1 817 860 9400",
    "sg:postcode":"76012",
    "sg:province":"TX",
    "sg:tags":[
        "instruction",
        "yoga",
        "therapist"
    ],
    "sg:website":"http://beautyandbeyondpec.com",
    "wof:name":"Beauty and Beyond",
    "wof:placetype":"venue"
},
  "geometry": {"coordinates":[-97.131691,32.750221],"type":"Point"}
}