{
  "type": "Feature",
  "properties": {
    "iso:country":"US",
    "sg:address":"1917 Savannah Dr",
    "sg:city":"Mc Kinney",
    "sg:classifiers":[
        {
            "category":"Banks & Credit Unions",
            "subcategory":"Bank",
            "type":"Services"
        }
    ],
    "sg:phone":"+1 972 569 8621",
    "sg:postcode":"75070",
    "sg:province":"TX",
    "sg:tags":[
        "mortgage"
    ],
    "wof:name":"Executive Home Services",
    "wof:placetype":"venue"
},
  "geometry": {"coordinates":[-96.69767899999999,33.182813],"type":"Point"}
}