{
  "type": "Feature",
  "properties": {
    "iso:country":"US",
    "sg:address":"8501 Old Hickory Trl",
    "sg:city":"Dallas",
    "sg:classifiers":[
        {
            "category":"Real Estate",
            "subcategory":"Real Estate Operator",
            "type":"Services"
        }
    ],
    "sg:phone":"+1 214 774 0264",
    "sg:postcode":"75115",
    "sg:province":"TX",
    "sg:tags":[
        "apartment"
    ],
    "wof:name":"Providence At Thorntree",
    "wof:placetype":"venue"
},
  "geometry": {"coordinates":[-96.865494,32.640997],"type":"Point"}
}