{
  "type": "Feature",
  "properties": {
    "iso:country":"US",
    "sg:address":"10011 Denton Dr",
    "sg:city":"Dallas",
    "sg:classifiers":[
        {
            "category":"Bars & Pubs",
            "type":"Food & Drink"
        }
    ],
    "sg:phone":"+1 214 352 7400",
    "sg:postcode":"75220",
    "sg:province":"TX",
    "sg:tags":[
        "club",
        "night"
    ],
    "sg:website":"www.kaoba.com",
    "wof:name":"Kaoba Inc",
    "wof:placetype":"venue"
},
  "geometry": {"coordinates":[-96.877943,32.858371],"type":"Point"}
}