{
  "type": "Feature",
  "properties": {
    "iso:country":"US",
    "sg:address":"402 Estrella St",
    "sg:city":"Roma",
    "sg:classifiers":[
        {
            "category":"Shopping",
            "type":"Retail Goods"
        }
    ],
    "sg:phone":"+1 956 849 3672",
    "sg:postcode":"78584",
    "sg:province":"TX",
    "sg:tags":[
        "miscellaneous",
        "store"
    ],
    "wof:name":"UETA Of Texas Inc",
    "wof:placetype":"venue"
},
  "geometry": {"coordinates":[-99.016232,26.404131],"type":"Point"}
}