{
  "type": "Feature",
  "properties": {
    "iso:country":"US",
    "sg:address":"114 E 1st St",
    "sg:city":"Elgin",
    "sg:classifiers":[
        {
            "category":"Manufacturing",
            "subcategory":"Printing",
            "type":"Manufacturing & Wholesale Goods"
        }
    ],
    "sg:phone":"+1 512 285 3622",
    "sg:postcode":"78621",
    "sg:province":"TX",
    "sg:tags":[
        "printer",
        "commercial"
    ],
    "wof:name":"Powell's Printery",
    "wof:placetype":"venue"
},
  "geometry": {"coordinates":[-97.370212,30.348826],"type":"Point"}
}