{
  "type": "Feature",
  "properties": {
    "iso:country":"US",
    "sg:address":"12521 State Hwy 6",
    "sg:city":"Santa Fe",
    "sg:classifiers":[
        {
            "category":"Utilities",
            "subcategory":"Fuel Oil & Lpg",
            "type":"Services"
        }
    ],
    "sg:phone":"+1 409 927 8700",
    "sg:postcode":"77510",
    "sg:province":"TX",
    "sg:tags":[
        "liquefied",
        "gas",
        "petroleum"
    ],
    "wof:name":"Baygas Propane",
    "wof:placetype":"venue"
},
  "geometry": {"coordinates":[-95.093664,29.374139],"type":"Point"}
}