{
  "type": "Feature",
  "properties": {
    "iso:country":"US",
    "sg:address":"13510 Tutson Pl",
    "sg:city":"Houston",
    "sg:classifiers":[
        {
            "category":"Communications",
            "subcategory":"Radio Station",
            "type":"Services"
        }
    ],
    "sg:phone":"+1 713 721 1768",
    "sg:postcode":"77085",
    "sg:province":"TX",
    "sg:tags":[
        "educational"
    ],
    "wof:name":"Career Alternatives Inc",
    "wof:placetype":"venue"
},
  "geometry": {"coordinates":[-95.469336,29.628165],"type":"Point"}
}