{
  "type": "Feature",
  "properties": {
    "iso:country":"US",
    "sg:address":"500 N Texas St",
    "sg:city":"De Leon",
    "sg:classifiers":[
        {
            "category":"Retail",
            "subcategory":"Auto Repair",
            "type":"Services"
        }
    ],
    "sg:phone":"+1 254 893 6886",
    "sg:postcode":"76444",
    "sg:province":"TX",
    "sg:tags":[
        "body"
    ],
    "wof:name":"De Leon Motor Company",
    "wof:placetype":"venue"
},
  "geometry": {"coordinates":[-98.535912,32.114056],"type":"Point"}
}