{
  "type": "Feature",
  "properties": {
    "iso:country":"US",
    "sg:address":"5407 Creek Arbor Ct",
    "sg:city":"Dallas",
    "sg:classifiers":[
        {
            "category":"Banks & Credit Unions",
            "subcategory":"Financial Services",
            "type":"Services"
        }
    ],
    "sg:phone":"+1 972 931 5501",
    "sg:postcode":"75287",
    "sg:province":"TX",
    "sg:tags":[
        "investment",
        "private"
    ],
    "wof:name":"Gemoco Ltd",
    "wof:placetype":"venue"
},
  "geometry": {"coordinates":[-96.81389,32.995213],"type":"Point"}
}