{
  "type": "Feature",
  "properties": {
    "iso:country":"US",
    "sg:address":"157 W Cross St",
    "sg:city":"Muenster",
    "sg:classifiers":[
        {
            "category":"Building & Trades",
            "subcategory":"Construction",
            "type":"Services"
        }
    ],
    "sg:phone":"+1 940 759 4040",
    "sg:postcode":"76252",
    "sg:province":"TX",
    "sg:tags":[
        "general",
        "contractor"
    ],
    "wof:name":"Dangelmayr Construction Inc",
    "wof:placetype":"venue"
},
  "geometry": {"coordinates":[-97.37988799999999,33.646569],"type":"Point"}
}