{
  "type": "Feature",
  "properties": {
    "iso:country":"US",
    "sg:address":"2923 Hollinwell Dr",
    "sg:city":"Katy",
    "sg:classifiers":[
        {
            "category":"Organizations",
            "subcategory":"Religious Organization",
            "type":"Services"
        }
    ],
    "sg:phone":"+1 281 646 9646",
    "sg:postcode":"77450",
    "sg:province":"TX",
    "wof:name":"Spiritual Assembly of Bah",
    "wof:placetype":"venue"
},
  "geometry": {"coordinates":[-95.747767,29.740014],"type":"Point"}
}