{
  "type": "Feature",
  "properties": {
    "iso:country":"US",
    "sg:address":"2414 W 11th St",
    "sg:city":"Odessa",
    "sg:classifiers":[
        {
            "category":"Shopping",
            "subcategory":"Jewelry",
            "type":"Retail Goods"
        }
    ],
    "sg:phone":"+1 432 337 3623",
    "sg:postcode":"79763",
    "sg:province":"TX",
    "wof:name":"Leslies Jewelry",
    "wof:placetype":"venue"
},
  "geometry": {"coordinates":[-102.39855900000001,31.842797],"type":"Point"}
}