{
  "type": "Feature",
  "properties": {
    "iso:country":"US",
    "sg:address":"2031 Morning Dove St",
    "sg:city":"San Antonio",
    "sg:classifiers":[
        {
            "category":"Building & Trades",
            "subcategory":"Construction",
            "type":"Services"
        }
    ],
    "sg:phone":"+1 210 495 5671",
    "sg:postcode":"78232",
    "sg:province":"TX",
    "sg:tags":[
        "contractor"
    ],
    "wof:name":"Siding Masters",
    "wof:placetype":"venue"
},
  "geometry": {"coordinates":[-98.460454,29.567803],"type":"Point"}
}