{
  "type": "Feature",
  "properties": {
    "iso:country":"US",
    "sg:address":"1881 Sylvan Ave",
    "sg:city":"Dallas",
    "sg:classifiers":[
        {
            "category":"Professional",
            "subcategory":"Lawyer & Legal Services",
            "type":"Services"
        }
    ],
    "sg:phone":"+1 214 741 4421",
    "sg:postcode":"75208",
    "sg:province":"TX",
    "sg:tags":[
        "attorney"
    ],
    "wof:name":"Barela Dino Law Office",
    "wof:placetype":"venue"
},
  "geometry": {"coordinates":[-96.835814,32.76837],"type":"Point"}
}