{
  "type": "Feature",
  "properties": {
    "iso:country":"US",
    "sg:address":"412 Baylor Dr",
    "sg:city":"Arlington",
    "sg:classifiers":[
        {
            "category":"Health Services",
            "subcategory":"Clinic",
            "type":"Services"
        }
    ],
    "sg:phone":"+1 817 274 9212",
    "sg:postcode":"76010",
    "sg:province":"TX",
    "wof:name":"AMS Health Svc Schwab",
    "wof:placetype":"venue"
},
  "geometry": {"coordinates":[-97.110067,32.717534],"type":"Point"}
}