{
  "type": "Feature",
  "properties": {
    "iso:country":"US",
    "sg:address":"209 N Main St",
    "sg:city":"Weatherford",
    "sg:classifiers":[
        {
            "category":"Shopping",
            "subcategory":"Crafts & Fabrics",
            "type":"Retail Goods"
        }
    ],
    "sg:phone":"+1 817 594 5519",
    "sg:postcode":"76086",
    "sg:province":"TX",
    "sg:tags":[
        "sewing"
    ],
    "wof:name":"Stitches & Britches",
    "wof:placetype":"venue"
},
  "geometry": {"coordinates":[-97.79733899999999,32.761426],"type":"Point"}
}