{
  "type": "Feature",
  "properties": {
    "iso:country":"US",
    "sg:address":"6502 Southwest Fwy",
    "sg:city":"Houston",
    "sg:classifiers":[
        {
            "category":"Autos & Motor Vehicles",
            "subcategory":"Fuel & Gas Station",
            "type":"Retail Goods"
        }
    ],
    "sg:phone":"+1 713 782 1116",
    "sg:postcode":"77074",
    "sg:province":"TX",
    "sg:website":"p66conoco76.conocophillips.com",
    "wof:name":"Highway 59 Phillips 66",
    "wof:placetype":"venue"
},
  "geometry": {"coordinates":[-95.49990099999999,29.7167],"type":"Point"}
}