{
  "type": "Feature",
  "properties": {
    "iso:country":"US",
    "sg:address":"2517 Barrow St",
    "sg:city":"Abilene",
    "sg:classifiers":[
        {
            "category":"Retail",
            "subcategory":"Animal Services",
            "type":"Services"
        }
    ],
    "sg:phone":"+1 325 695 5373",
    "sg:postcode":"79605",
    "sg:province":"TX",
    "wof:name":"Lads & Lassies",
    "wof:placetype":"venue"
},
  "geometry": {"coordinates":[-99.75948200000001,32.41751],"type":"Point"}
}