{
  "type": "Feature",
  "properties": {
    "iso:country":"US",
    "sg:address":"7345 Estrid Trl",
    "sg:city":"San Antonio",
    "sg:classifiers":[
        {
            "category":"Shopping",
            "type":"Retail Goods"
        }
    ],
    "sg:phone":"+1 210 661 8943",
    "sg:postcode":"78244",
    "sg:province":"TX",
    "sg:tags":[
        "merchandise"
    ],
    "wof:name":"Stephanies Accessories",
    "wof:placetype":"venue"
},
  "geometry": {"coordinates":[-98.327884,29.500139],"type":"Point"}
}