{
  "type": "Feature",
  "properties": {
    "iso:country":"US",
    "sg:address":"12872 Adkins-St Hedwig Rd",
    "sg:city":"St Hedwig",
    "sg:classifiers":[
        {
            "category":"Farming",
            "subcategory":"Livestock Farm",
            "type":"Manufacturing & Wholesale Goods"
        },
        {
            "category":"Farming",
            "subcategory":"Farm & Veterinary Services",
            "type":"Manufacturing & Wholesale Goods"
        }
    ],
    "sg:phone":"+1 210 667 1478",
    "sg:postcode":"78152",
    "sg:province":"TX",
    "sg:tags":[
        "breeder",
        "animal"
    ],
    "wof:name":"Farris' Fancies",
    "wof:placetype":"venue"
},
  "geometry": {"coordinates":[-98.22361100000001,29.40924],"type":"Point"}
}