{
  "type": "Feature",
  "properties": {
    "iso:country":"US",
    "sg:address":"8013 John Ralston Rd",
    "sg:city":"Houston",
    "sg:classifiers":[
        {
            "category":"Restaurant",
            "type":"Food & Drink"
        }
    ],
    "sg:phone":"+1 281 459 6149",
    "sg:postcode":"77044",
    "sg:province":"TX",
    "sg:tags":[
        "eating"
    ],
    "wof:name":"Restaurant Chula Vista",
    "wof:placetype":"venue"
},
  "geometry": {"coordinates":[-95.227384,29.839858],"type":"Point"}
}