{
  "type": "Feature",
  "properties": {
    "iso:country":"US",
    "sg:address":"11484 FM 2868",
    "sg:city":"Flint",
    "sg:classifiers":[
        {
            "category":"Building & Trades",
            "subcategory":"Construction",
            "type":"Services"
        }
    ],
    "sg:phone":"+1 903 894 9393",
    "sg:postcode":"75762",
    "sg:province":"TX",
    "sg:tags":[
        "home",
        "builder"
    ],
    "wof:name":"Wayne Shay Builder",
    "wof:placetype":"venue"
},
  "geometry": {"coordinates":[-95.359469,32.202474],"type":"Point"}
}