{
  "type": "Feature",
  "properties": {
    "iso:country":"US",
    "sg:address":"18231 Arbor Oaks Cir",
    "sg:city":"New Caney",
    "sg:classifiers":[
        {
            "category":"Retail",
            "subcategory":"Portrait Studio",
            "type":"Services"
        }
    ],
    "sg:phone":"+1 281 429 1978",
    "sg:postcode":"77357",
    "sg:province":"TX",
    "sg:tags":[
        "photo",
        "photographer"
    ],
    "wof:name":"Fontz Photography",
    "wof:placetype":"venue"
},
  "geometry": {"coordinates":[-95.25452199999999,30.184863],"type":"Point"}
}