{
  "type": "Feature",
  "properties": {
    "iso:country":"US",
    "sg:address":"5040 W Plano Pkwy",
    "sg:city":"Plano",
    "sg:classifiers":[
        {
            "category":"Restaurant",
            "type":"Food & Drink"
        }
    ],
    "sg:menulink":"http://www.allmenus.com/tx/plano/50300-lubys/menu/",
    "sg:phone":"+1 972 732 8472",
    "sg:postcode":"75093",
    "sg:province":"TX",
    "sg:tags":[
        "new",
        "american"
    ],
    "wof:name":"Luby's",
    "wof:placetype":"venue"
},
  "geometry": {"coordinates":[-96.795788,33.016083],"type":"Point"}
}