{
  "type": "Feature",
  "properties": {
    "iso:country":"US",
    "sg:address":"3601 Cheyenne St",
    "sg:city":"Irving",
    "sg:classifiers":[
        {
            "category":"Education",
            "subcategory":"School",
            "type":"Public Place"
        }
    ],
    "sg:phone":"+1 972 261 2500",
    "sg:postcode":"75062",
    "sg:province":"TX",
    "wof:name":"Tom Haley Elementary School",
    "wof:placetype":"venue"
},
  "geometry": {"coordinates":[-97.001464,32.854873],"type":"Point"}
}