{
  "type": "Feature",
  "properties": {
    "iso:country":"US",
    "sg:address":"3909 Lost Oasis Hollow",
    "sg:city":"Austin",
    "sg:classifiers":[
        {
            "category":"Building & Trades",
            "subcategory":"Construction",
            "type":"Services"
        }
    ],
    "sg:phone":"+1 512 280 3972",
    "sg:postcode":"78739",
    "sg:province":"TX",
    "sg:tags":[
        "contractor"
    ],
    "wof:name":"American Bath Resurfacing",
    "wof:placetype":"venue"
},
  "geometry": {"coordinates":[-97.87358999999999,30.160696],"type":"Point"}
}