{
  "type": "Feature",
  "properties": {
    "iso:country":"US",
    "sg:address":"14403 Stuebner Airline Rd",
    "sg:city":"Houston",
    "sg:classifiers":[
        {
            "category":"Wholesale",
            "subcategory":"Farm Supplies",
            "type":"Manufacturing & Wholesale Goods"
        }
    ],
    "sg:phone":"+1 281 444 1010",
    "sg:postcode":"77069",
    "sg:province":"TX",
    "sg:tags":[
        "feed"
    ],
    "wof:name":"Hieden Feed & Supply",
    "wof:placetype":"venue"
},
  "geometry": {"coordinates":[-95.503908,29.99549],"type":"Point"}
}