{
  "type": "Feature",
  "properties": {
    "iso:country":"US",
    "sg:address":"4900 Green Oaks Dr",
    "sg:city":"Colleyville",
    "sg:classifiers":[
        {
            "category":"Health Services",
            "subcategory":"Doctor",
            "type":"Services"
        }
    ],
    "sg:phone":"+1 817 267 3574",
    "sg:postcode":"76034",
    "sg:province":"TX",
    "sg:tags":[
        "medical"
    ],
    "wof:name":"Dennis Arline Neil Fmly Ltd PA",
    "wof:placetype":"venue"
},
  "geometry": {"coordinates":[-97.120543,32.880074],"type":"Point"}
}