{
  "type": "Feature",
  "properties": {
    "iso:country":"US",
    "sg:address":"12414 Enchanted Path Dr",
    "sg:city":"Houston",
    "sg:classifiers":[
        {
            "category":"Professional",
            "subcategory":"Research",
            "type":"Services"
        }
    ],
    "sg:phone":"+1 281 459 1549",
    "sg:postcode":"77044",
    "sg:province":"TX",
    "sg:tags":[
        "commercial",
        "physical"
    ],
    "wof:name":"Innovative Research Services",
    "wof:placetype":"venue"
},
  "geometry": {"coordinates":[-95.21214500000001,29.853113],"type":"Point"}
}