{
  "type": "Feature",
  "properties": {
    "iso:country":"US",
    "sg:address":"6706 Gateridge Dr",
    "sg:city":"Dallas",
    "sg:classifiers":[
        {
            "category":"Professional",
            "subcategory":"Business Services",
            "type":"Services"
        }
    ],
    "sg:phone":"+1 972 788 2443",
    "sg:postcode":"75254",
    "sg:province":"TX",
    "wof:name":"Reeder Enterprises",
    "wof:placetype":"venue"
},
  "geometry": {"coordinates":[-96.78600900000001,32.945633],"type":"Point"}
}