{
  "type": "Feature",
  "properties": {
    "iso:country":"US",
    "sg:address":"815 N Minnesota Ave",
    "sg:city":"Brownsville",
    "sg:classifiers":[
        {
            "category":"Manufacturing",
            "subcategory":"Printing",
            "type":"Manufacturing & Wholesale Goods"
        }
    ],
    "sg:phone":"+1 956 831 3823",
    "sg:postcode":"78521",
    "sg:province":"TX",
    "sg:tags":[
        "printer"
    ],
    "wof:name":"Joe King Jr Commercial Printer",
    "wof:placetype":"venue"
},
  "geometry": {"coordinates":[-97.43157600000001,25.924958],"type":"Point"}
}