{
  "type": "Feature",
  "properties": {
    "iso:country":"US",
    "sg:address":"104 Odel Dr",
    "sg:city":"Weatherford",
    "sg:classifiers":[
        {
            "category":"Professional",
            "subcategory":"Engineering",
            "type":"Services"
        },
        {
            "category":"Retail",
            "subcategory":"Repair Shop",
            "type":"Services"
        },
        {
            "category":"Wholesale",
            "subcategory":"Machinery & Supplies",
            "type":"Manufacturing & Wholesale Goods"
        },
        {
            "category":"Building & Trades",
            "subcategory":"Construction",
            "type":"Services"
        }
    ],
    "sg:phone":"+1 817 599 4459",
    "sg:postcode":"76085",
    "sg:province":"TX",
    "sg:tags":[
        "specialty",
        "manufacturer",
        "system",
        "equipment-parts",
        "heating",
        "refrigeration",
        "air conditioning",
        "freezers-wholesale",
        "contractor",
        "freezers-repair",
        "refrigerator",
        "engineer"
    ],
    "sg:website":"http://mcbridemechanical.net",
    "wof:name":"T L & M Refridgeration",
    "wof:placetype":"venue"
},
  "geometry": {"coordinates":[-97.79768199999999,32.789847],"type":"Point"}
}