{
  "type": "Feature",
  "properties": {
    "iso:country":"US",
    "sg:address":"105 N Industrial Hwy",
    "sg:city":"Perryton",
    "sg:classifiers":[
        {
            "category":"Mining & Drilling",
            "type":"Manufacturing & Wholesale Goods"
        }
    ],
    "sg:phone":"+1 806 435 4034",
    "sg:postcode":"79070",
    "sg:province":"TX",
    "sg:tags":[
        "field",
        "oil"
    ],
    "wof:name":"National-Oilwell Varco",
    "wof:placetype":"venue"
},
  "geometry": {"coordinates":[-100.791681,36.401549],"type":"Point"}
}