{
  "type": "Feature",
  "properties": {
    "iso:country":"US",
    "sg:address":"417 N Bryan Belt Line Rd Suite A",
    "sg:city":"Mesquite",
    "sg:phone":"+1 972 285 8855",
    "sg:postcode":"75149",
    "sg:province":"TX",
    "wof:name":"Century 21 Larry Watson Realtor Inc",
    "wof:placetype":"venue"
},
  "geometry": {"coordinates":[-96.597076,32.769377],"type":"Point"}
}