{
  "type": "Feature",
  "properties": {
    "iso:country":"US",
    "sg:address":"1145 Ranch Valley Dr",
    "sg:city":"De Soto",
    "sg:classifiers":[
        {
            "category":"Health Services",
            "subcategory":"Clinic",
            "type":"Services"
        }
    ],
    "sg:phone":"+1 972 766 8827",
    "sg:postcode":"75115",
    "sg:province":"TX",
    "sg:tags":[
        "home",
        "care"
    ],
    "wof:name":"Ani Home Health Agency Ltd Co",
    "wof:placetype":"venue"
},
  "geometry": {"coordinates":[-96.82597699999999,32.612396],"type":"Point"}
}