{
  "type": "Feature",
  "properties": {
    "iso:country":"US",
    "sg:address":"3301 Cumberland Ave",
    "sg:city":"Wichita Falls",
    "sg:classifiers":[
        {
            "category":"Mining & Drilling",
            "type":"Manufacturing & Wholesale Goods"
        }
    ],
    "sg:phone":"+1 940 696 1631",
    "sg:postcode":"76309",
    "sg:province":"TX",
    "sg:tags":[
        "development",
        "gas",
        "oil",
        "exploration"
    ],
    "wof:name":"Seydell Operating Co",
    "wof:placetype":"venue"
},
  "geometry": {"coordinates":[-98.53865399999999,33.89],"type":"Point"}
}