{
  "type": "Feature",
  "properties": {
    "iso:country":"US",
    "sg:address":"106 Cardinal Ln",
    "sg:city":"Columbus",
    "sg:classifiers":[
        {
            "category":"Government",
            "subcategory":"Office",
            "type":"Public Place"
        }
    ],
    "sg:phone":"+1 979 732 8222",
    "sg:postcode":"78934",
    "sg:province":"TX",
    "wof:name":"Colorado County Appraisal",
    "wof:placetype":"venue"
},
  "geometry": {"coordinates":[-96.563894,29.705246],"type":"Point"}
}