{
  "type": "Feature",
  "properties": {
    "iso:country":"US",
    "sg:address":"601 Holliday St",
    "sg:city":"Wichita Falls",
    "sg:classifiers":[
        {
            "category":"Shopping",
            "type":"Retail Goods"
        }
    ],
    "sg:phone":"+1 940 723 8031",
    "sg:postcode":"76301",
    "sg:province":"TX",
    "sg:tags":[
        "merchandise"
    ],
    "wof:name":"Regal Enterprises",
    "wof:placetype":"venue"
},
  "geometry": {"coordinates":[-98.501885,33.907832],"type":"Point"}
}