{
  "type": "Feature",
  "properties": {
    "iso:country":"US",
    "sg:address":"1623 Martin Luther King Dr",
    "sg:city":"San Antonio",
    "sg:classifiers":[
        {
            "category":"Retail",
            "subcategory":"Car Wash",
            "type":"Services"
        }
    ],
    "sg:phone":"+1 210 533 4229",
    "sg:postcode":"78203",
    "sg:province":"TX",
    "sg:tags":[
        "polishing",
        "carwash",
        "washing"
    ],
    "wof:name":"Brighter Day Car Wash",
    "wof:placetype":"venue"
},
  "geometry": {"coordinates":[-98.45584100000001,29.413452],"type":"Point"}
}