{
  "type": "Feature",
  "properties": {
    "iso:country":"US",
    "sg:address":"109 S Elm St",
    "sg:city":"Waxahachie",
    "sg:classifiers":[
        {
            "category":"Wholesale",
            "subcategory":"Farm Supplies",
            "type":"Manufacturing & Wholesale Goods"
        },
        {
            "category":"Shopping",
            "type":"Retail Goods"
        }
    ],
    "sg:phone":"+1 972 937 8860",
    "sg:postcode":"75165",
    "sg:province":"TX",
    "sg:tags":[
        "feed",
        "merchandise"
    ],
    "wof:name":"Waxahachie Feed",
    "wof:placetype":"venue"
},
  "geometry": {"coordinates":[-96.849101,32.385671],"type":"Point"}
}