{
  "type": "Feature",
  "properties": {
    "iso:country":"US",
    "sg:address":"601 Illinois St",
    "sg:city":"South Houston",
    "sg:classifiers":[
        {
            "category":"Retail",
            "subcategory":"Repair Shop",
            "type":"Services"
        }
    ],
    "sg:phone":"+1 713 946 5813",
    "sg:postcode":"77587",
    "sg:province":"TX",
    "sg:tags":[
        "refrigeration"
    ],
    "wof:name":"Saenz Air Cond & Diesel Repair",
    "wof:placetype":"venue"
},
  "geometry": {"coordinates":[-95.23715799999999,29.660597],"type":"Point"}
}