{
  "type": "Feature",
  "properties": {
    "iso:country":"US",
    "sg:address":"1321 W Monahans St",
    "sg:city":"Odessa",
    "sg:classifiers":[
        {
            "category":"Organizations",
            "subcategory":"Religious Organization",
            "type":"Services"
        }
    ],
    "sg:phone":"+1 432 337 0241",
    "sg:postcode":"79763",
    "sg:province":"TX",
    "wof:name":"Saint Anthonys Ccd",
    "wof:placetype":"venue"
},
  "geometry": {"coordinates":[-102.379413,31.826347],"type":"Point"}
}