{
  "type": "Feature",
  "properties": {
    "iso:country":"US",
    "sg:address":"1658 Knoll Ridge Cir",
    "sg:city":"Denton",
    "sg:classifiers":[
        {
            "category":"Real Estate",
            "subcategory":"Real Estate Operator",
            "type":"Services"
        }
    ],
    "sg:phone":"+1 940 321 2370",
    "sg:postcode":"76210",
    "sg:province":"TX",
    "sg:tags":[
        "building",
        "nonresidential"
    ],
    "wof:name":"Jti Property",
    "wof:placetype":"venue"
},
  "geometry": {"coordinates":[-97.07446899999999,33.155988],"type":"Point"}
}