{
  "type": "Feature",
  "properties": {
    "iso:country":"US",
    "sg:address":"7925 FM 1960 W",
    "sg:city":"Houston",
    "sg:classifiers":[
        {
            "category":"Shopping",
            "subcategory":"Gifts & Souvenirs",
            "type":"Retail Goods"
        }
    ],
    "sg:phone":"+1 281 517 0523",
    "sg:postcode":"77070",
    "sg:province":"TX",
    "sg:tags":[
        "shop"
    ],
    "wof:name":"Gifts N Novelty",
    "wof:placetype":"venue"
},
  "geometry": {"coordinates":[-95.547201,29.961179],"type":"Point"}
}