{
  "type": "Feature",
  "properties": {
    "iso:country":"US",
    "sg:address":"700 Pecan St",
    "sg:city":"Burkburnett",
    "sg:classifiers":[
        {
            "category":"Professional",
            "subcategory":"Lawyer & Legal Services",
            "type":"Services"
        }
    ],
    "sg:phone":"+1 940 569 1006",
    "sg:postcode":"76354",
    "sg:province":"TX",
    "sg:tags":[
        "attorney",
        "practice"
    ],
    "wof:name":"Attorney At Law",
    "wof:placetype":"venue"
},
  "geometry": {"coordinates":[-98.567032,34.081924],"type":"Point"}
}