{
  "type": "Feature",
  "properties": {
    "iso:country":"US",
    "sg:address":"5306 Cambridge St",
    "sg:city":"Sugar Land",
    "sg:classifiers":[
        {
            "category":"Professional",
            "subcategory":"Management & Consulting",
            "type":"Services"
        }
    ],
    "sg:phone":"+1 713 914 3722",
    "sg:postcode":"77479",
    "sg:province":"TX",
    "wof:name":"Millard Tipton",
    "wof:placetype":"venue"
},
  "geometry": {"coordinates":[-95.61031199999999,29.553709],"type":"Point"}
}