{
  "type": "Feature",
  "properties": {
    "iso:country":"US",
    "sg:address":"1710 28th St",
    "sg:city":"Lubbock",
    "sg:classifiers":[
        {
            "category":"Organizations",
            "subcategory":"Non-profit Organization",
            "type":"Services"
        }
    ],
    "sg:phone":"+1 806 747 7543",
    "sg:postcode":"79411",
    "sg:province":"TX",
    "sg:tags":[
        "charity",
        "foundations-educational",
        "philanthropic",
        "research"
    ],
    "wof:name":"Charitable Spears Trust",
    "wof:placetype":"venue"
},
  "geometry": {"coordinates":[-101.855368,33.56913],"type":"Point"}
}