{
  "type": "Feature",
  "properties": {
    "iso:country":"US",
    "sg:address":"1063 Edgebrook Dr",
    "sg:city":"Houston",
    "sg:classifiers":[
        {
            "category":"Organizations",
            "subcategory":"Religious Organization",
            "type":"Services"
        }
    ],
    "sg:phone":"+1 713 946 7885",
    "sg:postcode":"77034",
    "sg:province":"TX",
    "wof:name":"Prince Pace Lthran Church Elca",
    "wof:placetype":"venue"
},
  "geometry": {"coordinates":[-95.238664,29.643539],"type":"Point"}
}