{
  "type": "Feature",
  "properties": {
    "iso:country":"US",
    "sg:address":"600 S Carver St",
    "sg:city":"Midland",
    "sg:classifiers":[
        {
            "category":"Government",
            "subcategory":"Office",
            "type":"Public Place"
        }
    ],
    "sg:phone":"+1 432 685 7278",
    "sg:postcode":"79701",
    "sg:province":"TX",
    "sg:tags":[
        "city",
        "program"
    ],
    "wof:name":"Midland Sanitation",
    "wof:placetype":"venue"
},
  "geometry": {"coordinates":[-102.057693,31.99288],"type":"Point"}
}