{
  "type": "Feature",
  "properties": {
    "iso:country":"US",
    "sg:address":"712 S 32nd St",
    "sg:city":"Temple",
    "sg:classifiers":[
        {
            "category":"Professional",
            "subcategory":"Management & Consulting",
            "type":"Services"
        },
        {
            "category":"Shopping",
            "subcategory":"Clothing, Apparel, & Fashions",
            "type":"Retail Goods"
        }
    ],
    "sg:phone":"+1 254 778 4829",
    "sg:postcode":"76501",
    "sg:province":"TX",
    "sg:tags":[
        "consultant"
    ],
    "wof:name":"Two Sisters Fashion Conslnts",
    "wof:placetype":"venue"
},
  "geometry": {"coordinates":[-97.327292,31.08388],"type":"Point"}
}