{
  "type": "Feature",
  "properties": {
    "iso:country":"US",
    "sg:address":"8502 Herts Rd",
    "sg:city":"Spring",
    "sg:classifiers":[
        {
            "category":"Professional",
            "type":"Services"
        }
    ],
    "sg:phone":"+1 281 655 5029",
    "sg:postcode":"77379",
    "sg:province":"TX",
    "wof:name":"Neltell Network",
    "wof:placetype":"venue"
},
  "geometry": {"coordinates":[-95.53773099999999,30.007161],"type":"Point"}
}