{
  "type": "Feature",
  "properties": {
    "iso:country":"US",
    "sg:address":"11014 Whiskey River Dr",
    "sg:city":"Austin",
    "sg:classifiers":[
        {
            "category":"Banks & Credit Unions",
            "subcategory":"Investment Brokerage",
            "type":"Services"
        }
    ],
    "sg:phone":"+1 512 292 3456",
    "sg:postcode":"78748",
    "sg:province":"TX",
    "wof:name":"DNV Investment Corp",
    "wof:placetype":"venue"
},
  "geometry": {"coordinates":[-97.850707,30.167835],"type":"Point"}
}