{
  "type": "Feature",
  "properties": {
    "iso:country":"US",
    "sg:address":"2203 San Antonio St",
    "sg:city":"Austin",
    "sg:classifiers":[
        {
            "category":"Place Of Worship",
            "type":"Public Place"
        },
        {
            "category":"Social Services",
            "subcategory":"Child Care",
            "type":"Services"
        }
    ],
    "sg:phone":"+1 512 476 5321",
    "sg:postcode":"78705",
    "sg:province":"TX",
    "sg:tags":[
        "nursery",
        "day",
        "church"
    ],
    "sg:website":"http://www.upcaustin.org",
    "wof:name":"Child Development Center",
    "wof:placetype":"venue"
},
  "geometry": {"coordinates":[-97.742864,30.2851],"type":"Point"}
}