{
  "type": "Feature",
  "properties": {
    "iso:country":"US",
    "sg:address":"617 W Moore Ave",
    "sg:city":"Terrell",
    "sg:classifiers":[
        {
            "category":"Professional",
            "subcategory":"Employment Agencies",
            "type":"Services"
        }
    ],
    "sg:phone":"+1 972 563 5862",
    "sg:postcode":"75160",
    "sg:province":"TX",
    "wof:name":"Instaff",
    "wof:placetype":"venue"
},
  "geometry": {"coordinates":[-96.28479299999999,32.737296],"type":"Point"}
}