{
  "type": "Feature",
  "properties": {
    "iso:country":"US",
    "sg:address":"5230 87th St",
    "sg:city":"Lubbock",
    "sg:classifiers":[
        {
            "category":"Building & Trades",
            "subcategory":"Construction",
            "type":"Services"
        }
    ],
    "sg:phone":"+1 806 797 3995",
    "sg:postcode":"79424",
    "sg:province":"TX",
    "sg:tags":[
        "hanging",
        "contractor"
    ],
    "wof:name":"Colormatch Paint Restoration",
    "wof:placetype":"venue"
},
  "geometry": {"coordinates":[-101.924893,33.514464],"type":"Point"}
}