{
  "type": "Feature",
  "properties": {
    "iso:country":"US",
    "sg:address":"2927 Fordham Rd",
    "sg:city":"Dallas",
    "sg:classifiers":[
        {
            "category":"Building & Trades",
            "subcategory":"Construction",
            "type":"Services"
        }
    ],
    "sg:phone":"+1 214 374 3287",
    "sg:postcode":"75216",
    "sg:province":"TX",
    "sg:tags":[
        "concrete",
        "contractor"
    ],
    "wof:name":"Curry Construction & Pnt Contg",
    "wof:placetype":"venue"
},
  "geometry": {"coordinates":[-96.775195,32.71002],"type":"Point"}
}