{
  "type": "Feature",
  "properties": {
    "iso:country":"US",
    "sg:address":"401 Bella Vista Dr",
    "sg:city":"Quinlan",
    "sg:classifiers":[
        {
            "category":"Banks & Credit Unions",
            "subcategory":"Bank",
            "type":"Services"
        }
    ],
    "sg:phone":"+1 817 999 8531",
    "sg:postcode":"75474",
    "sg:province":"TX",
    "sg:tags":[
        "broker",
        "mortgage"
    ],
    "wof:name":"Megamerica Mortgage",
    "wof:placetype":"venue"
},
  "geometry": {"coordinates":[-96.03207399999999,32.909649],"type":"Point"}
}