{
  "type": "Feature",
  "properties": {
    "iso:country":"US",
    "sg:address":"214 Glentower Dr",
    "sg:city":"San Antonio",
    "sg:classifiers":[
        {
            "category":"Banks & Credit Unions",
            "subcategory":"Investment Brokerage",
            "type":"Services"
        }
    ],
    "sg:phone":"+1 210 979 8801",
    "sg:postcode":"78213",
    "sg:province":"TX",
    "sg:tags":[
        "advisory",
        "financial"
    ],
    "wof:name":"Mazco Financial Inc",
    "wof:placetype":"venue"
},
  "geometry": {"coordinates":[-98.510381,29.5264],"type":"Point"}
}