{
  "type": "Feature",
  "properties": {
    "iso:country":"US",
    "sg:address":"2601 S Braeswood Blvd",
    "sg:city":"Houston",
    "sg:classifiers":[
        {
            "category":"Education",
            "subcategory":"Special Training",
            "type":"Public Place"
        }
    ],
    "sg:phone":"+1 713 218 8188",
    "sg:postcode":"77025",
    "sg:province":"TX",
    "sg:tags":[
        "professional",
        "consulting",
        "speaking"
    ],
    "wof:name":"Stroud Training Systems",
    "wof:placetype":"venue"
},
  "geometry": {"coordinates":[-95.41865799999999,29.696203],"type":"Point"}
}