{
  "type": "Feature",
  "properties": {
    "iso:country":"US",
    "sg:address":"2515 Coatbridge Dr",
    "sg:city":"Austin",
    "sg:classifiers":[
        {
            "category":"Health Services",
            "subcategory":"Doctor",
            "type":"Services"
        }
    ],
    "sg:phone":"+1 512 445 3436",
    "sg:postcode":"78745",
    "sg:province":"TX",
    "sg:tags":[
        "physician",
        "surgery",
        "surgeons",
        "oral"
    ],
    "wof:name":"Jay Harward",
    "wof:placetype":"venue"
},
  "geometry": {"coordinates":[-97.80569800000001,30.215447],"type":"Point"}
}