{
  "type": "Feature",
  "properties": {
    "iso:country":"US",
    "sg:address":"6850 Austin Center Blvd # 150",
    "sg:city":"Austin",
    "sg:classifiers":[
        {
            "category":"Real Estate",
            "subcategory":"Real Estate Services",
            "type":"Services"
        },
        {
            "category":"Real Estate",
            "subcategory":"Real Estate Agent",
            "type":"Services"
        }
    ],
    "sg:phone":"+1 512 476 4797",
    "sg:postcode":"78731",
    "sg:province":"TX",
    "sg:tags":[
        "buyer",
        "broker"
    ],
    "sg:website":"http://www.ausapts.com",
    "wof:name":"Dynastat Inc",
    "wof:placetype":"venue"
},
  "geometry": {"coordinates":[-97.75142700000001,30.351701],"type":"Point"}
}