{
  "type": "Feature",
  "properties": {
    "iso:country":"US",
    "sg:address":"4406 Stassen St",
    "sg:city":"Houston",
    "sg:classifiers":[
        {
            "category":"Bars & Pubs",
            "type":"Food & Drink"
        }
    ],
    "sg:phone":"+1 713 733 0947",
    "sg:postcode":"77051",
    "sg:province":"TX",
    "sg:tags":[
        "lounge",
        "cocktail"
    ],
    "wof:name":"Lounge Redslipper",
    "wof:placetype":"venue"
},
  "geometry": {"coordinates":[-95.361304,29.670832],"type":"Point"}
}