{
  "type": "Feature",
  "properties": {
    "iso:country":"US",
    "sg:address":"11168 Tenaha Ave",
    "sg:city":"El Paso",
    "sg:classifiers":[
        {
            "category":"Wholesale",
            "subcategory":"Electrical",
            "type":"Manufacturing & Wholesale Goods"
        }
    ],
    "sg:phone":"+1 915 629 0440",
    "sg:postcode":"79936",
    "sg:province":"TX",
    "sg:tags":[
        "electronic"
    ],
    "wof:name":"Digital Technology",
    "wof:placetype":"venue"
},
  "geometry": {"coordinates":[-106.31157399999999,31.795395],"type":"Point"}
}