{
  "type": "Feature",
  "properties": {
    "iso:country":"US",
    "sg:address":"332 N Main St",
    "sg:city":"Conroe",
    "sg:classifiers":[
        {
            "category":"Professional",
            "subcategory":"Lawyer & Legal Services",
            "type":"Services"
        }
    ],
    "sg:phone":"+1 936 494 1133",
    "sg:postcode":"77301",
    "sg:province":"TX",
    "sg:tags":[
        "attorney",
        "practice"
    ],
    "sg:website":"http://dwilawyermontgomerycountytexas.com",
    "wof:name":"Dishongh, Jeremy, Law Office Of",
    "wof:placetype":"venue"
},
  "geometry": {"coordinates":[-95.457069,30.311591],"type":"Point"}
}