{
  "type": "Feature",
  "properties": {
    "iso:country":"US",
    "sg:address":"2304 S Tourist Dr",
    "sg:city":"Edinburg",
    "sg:classifiers":[
        {
            "category":"Sports & Exercise",
            "subcategory":"Gym",
            "type":"Entertainment"
        }
    ],
    "sg:phone":"+1 956 380 6967",
    "sg:postcode":"78539",
    "sg:province":"TX",
    "sg:tags":[
        "club",
        "health",
        "studio",
        "gymnasium"
    ],
    "wof:name":"Boxing Gym",
    "wof:placetype":"venue"
},
  "geometry": {"coordinates":[-98.170126,26.276597],"type":"Point"}
}