{
  "type": "Feature",
  "properties": {
    "iso:country":"US",
    "sg:address":"2720 E Montgomery St",
    "sg:city":"Laredo",
    "sg:classifiers":[
        {
            "category":"Building & Trades",
            "subcategory":"Construction",
            "type":"Services"
        }
    ],
    "sg:phone":"+1 956 723 9063",
    "sg:postcode":"78043",
    "sg:province":"TX",
    "sg:tags":[
        "contractor"
    ],
    "wof:name":"Krystal Blue Pools Spas Texas",
    "wof:placetype":"venue"
},
  "geometry": {"coordinates":[-99.468188,27.527831],"type":"Point"}
}