{
  "type": "Feature",
  "properties": {
    "iso:country":"US",
    "sg:address":"11706 Playa Ct",
    "sg:city":"Houston",
    "sg:classifiers":[
        {
            "category":"Professional",
            "subcategory":"Secretarial Services",
            "type":"Services"
        }
    ],
    "sg:phone":"+1 281 484 0770",
    "sg:postcode":"77034",
    "sg:province":"TX",
    "sg:tags":[
        "convention",
        "reporting",
        "court",
        "reporters-court"
    ],
    "sg:website":"http://www.dvrproperties.com",
    "wof:name":"Ross Reporting Service",
    "wof:placetype":"venue"
},
  "geometry": {"coordinates":[-95.179688,29.598849],"type":"Point"}
}