{
  "type": "Feature",
  "properties": {
    "iso:country":"US",
    "sg:address":"430 W Beauregard Ave",
    "sg:city":"San Angelo",
    "sg:classifiers":[
        {
            "category":"Insurance",
            "subcategory":"Insurance Agent",
            "type":"Services"
        }
    ],
    "sg:phone":"+1 325 653 1448",
    "sg:postcode":"76903",
    "sg:province":"TX",
    "wof:name":"Zesch & Pickett Insurance",
    "wof:placetype":"venue"
},
  "geometry": {"coordinates":[-100.44528200000001,31.459984],"type":"Point"}
}