{
  "type": "Feature",
  "properties": {
    "iso:country":"US",
    "sg:address":"12935 Bamboo Forest Trl",
    "sg:city":"Houston",
    "sg:classifiers":[
        {
            "category":"Retail",
            "subcategory":"Auto Repair",
            "type":"Services"
        }
    ],
    "sg:phone":"+1 281 459 2266",
    "sg:postcode":"77044",
    "sg:province":"TX",
    "sg:tags":[
        "general"
    ],
    "wof:name":"Mikeys General Repair Rmdlg",
    "wof:placetype":"venue"
},
  "geometry": {"coordinates":[-95.20099999999999,29.849956],"type":"Point"}
}