{
  "type": "Feature",
  "properties": {
    "iso:country":"US",
    "sg:address":"4610 Drake Falls Ct",
    "sg:city":"Katy",
    "sg:classifiers":[
        {
            "category":"Professional",
            "subcategory":"Business Services",
            "type":"Services"
        }
    ],
    "sg:phone":"+1 281 646 7905",
    "sg:postcode":"77450",
    "sg:province":"TX",
    "wof:name":"Casual Elegance Design",
    "wof:placetype":"venue"
},
  "geometry": {"coordinates":[-95.752105,29.72402],"type":"Point"}
}