{
  "type": "Feature",
  "properties": {
    "iso:country":"US",
    "sg:address":"4701 Melrose Park Ct",
    "sg:city":"Colleyville",
    "sg:classifiers":[
        {
            "category":"Cinema",
            "subcategory":"Movie Rental",
            "type":"Entertainment"
        }
    ],
    "sg:phone":"+1 817 684 7544",
    "sg:postcode":"76034",
    "sg:province":"TX",
    "sg:tags":[
        "motion",
        "picture",
        "distributor",
        "film",
        "exchange"
    ],
    "wof:name":"Pigskin Productions",
    "wof:placetype":"venue"
},
  "geometry": {"coordinates":[-97.11773700000001,32.878208],"type":"Point"}
}