{
  "type": "Feature",
  "properties": {
    "iso:country":"US",
    "sg:address":"2203 W 7th St",
    "sg:city":"Odessa",
    "sg:classifiers":[
        {
            "category":"Organizations",
            "subcategory":"Religious Organization",
            "type":"Services"
        }
    ],
    "sg:phone":"+1 432 335 8388",
    "sg:postcode":"79763",
    "sg:province":"TX",
    "sg:tags":[
        "church"
    ],
    "wof:name":"Spanish Seventh-Day Adventist",
    "wof:placetype":"venue"
},
  "geometry": {"coordinates":[-102.39431999999999,31.839464],"type":"Point"}
}