{
  "type": "Feature",
  "properties": {
    "iso:country":"US",
    "sg:address":"308 W Church St",
    "sg:city":"Livingston",
    "sg:classifiers":[
        {
            "category":"Banks & Credit Unions",
            "subcategory":"Investment Brokerage",
            "type":"Services"
        },
        {
            "category":"Insurance",
            "subcategory":"Insurance Agent",
            "type":"Services"
        }
    ],
    "sg:phone":"+1 936 327 7789",
    "sg:postcode":"77351",
    "sg:province":"TX",
    "sg:tags":[
        "stock",
        "bond"
    ],
    "wof:name":"Church Street Financial Svcs",
    "wof:placetype":"venue"
},
  "geometry": {"coordinates":[-94.935007,30.711092],"type":"Point"}
}