{
  "type": "Feature",
  "properties": {
    "iso:country":"US",
    "sg:address":"409 Central Expy N",
    "sg:city":"Allen",
    "sg:classifiers":[
        {
            "category":"Personal",
            "subcategory":"Beauty Salon",
            "type":"Services"
        }
    ],
    "sg:phone":"+1 214 547 8660",
    "sg:postcode":"75013",
    "sg:province":"TX",
    "wof:name":"Nguyen Phuong Hair Salon",
    "wof:placetype":"venue"
},
  "geometry": {"coordinates":[-96.67517700000001,33.107484],"type":"Point"}
}