{
  "type": "Feature",
  "properties": {
    "iso:country":"US",
    "sg:address":"13276 Co Rd 474",
    "sg:city":"Lindale",
    "sg:classifiers":[
        {
            "category":"Retail",
            "subcategory":"Animal Services",
            "type":"Services"
        }
    ],
    "sg:phone":"+1 903 882 6515",
    "sg:postcode":"75771",
    "sg:province":"TX",
    "wof:name":"Pup-N-Suds",
    "wof:placetype":"venue"
},
  "geometry": {"coordinates":[-95.38694599999999,32.484359],"type":"Point"}
}