{
  "type": "Feature",
  "properties": {
    "iso:country":"US",
    "sg:address":"3710 Ave F",
    "sg:city":"Del Rio",
    "sg:classifiers":[
        {
            "category":"Restaurant",
            "type":"Food & Drink"
        }
    ],
    "sg:phone":"+1 830 774 2424",
    "sg:postcode":"78840",
    "sg:province":"TX",
    "sg:tags":[
        "eating"
    ],
    "wof:name":"Don Marcelinos Restaurant 4",
    "wof:placetype":"venue"
},
  "geometry": {"coordinates":[-100.904721,29.408554],"type":"Point"}
}