{
  "type": "Feature",
  "properties": {
    "iso:country":"US",
    "sg:address":"1211 Baylor St. Ste. 100",
    "sg:city":"Austin",
    "sg:classifiers":[
        {
            "category":"Personal",
            "subcategory":"Massage",
            "type":"Services"
        }
    ],
    "sg:phone":"+1 512 785 8301",
    "sg:postcode":"78703",
    "sg:province":"TX",
    "sg:website":"www.solaceaustin.com/",
    "wof:name":"Solace Massage Therapy",
    "wof:placetype":"venue"
},
  "geometry": {"coordinates":[-97.75179900000001,30.278007],"type":"Point"}
}