{
  "type": "Feature",
  "properties": {
    "iso:country":"US",
    "sg:address":"24 Country Oaks Dr",
    "sg:city":"Buda",
    "sg:classifiers":[
        {
            "category":"Farming",
            "subcategory":"Farm",
            "type":"Manufacturing & Wholesale Goods"
        }
    ],
    "sg:phone":"+1 512 312 1347",
    "sg:postcode":"78610",
    "sg:province":"TX",
    "wof:name":"Maureen A Courgeois Ranch",
    "wof:placetype":"venue"
},
  "geometry": {"coordinates":[-97.881354,30.115684],"type":"Point"}
}