{
  "type": "Feature",
  "properties": {
    "iso:country":"US",
    "sg:address":"1104 W Queen St",
    "sg:city":"Tyler",
    "sg:classifiers":[
        {
            "category":"Travel",
            "subcategory":"Hotels & Motels",
            "type":"Entertainment"
        }
    ],
    "sg:phone":"+1 903 593 4287",
    "sg:postcode":"75702",
    "sg:province":"TX",
    "wof:name":"Howard Johnson",
    "wof:placetype":"venue"
},
  "geometry": {"coordinates":[-95.313474,32.361476],"type":"Point"}
}