{
  "type": "Feature",
  "properties": {
    "iso:country":"US",
    "sg:address":"1100 Lamesa Hwy",
    "sg:city":"Big Spring",
    "sg:classifiers":[
        {
            "category":"Autos & Motor Vehicles",
            "subcategory":"Fuel & Gas Station",
            "type":"Retail Goods"
        }
    ],
    "sg:phone":"+1 432 267 7132",
    "sg:postcode":"79720",
    "sg:province":"TX",
    "sg:tags":[
        "grocery",
        "station",
        "gasoline"
    ],
    "wof:name":"Kates Fina",
    "wof:placetype":"venue"
},
  "geometry": {"coordinates":[-101.489846,32.262696],"type":"Point"}
}