{
  "type": "Feature",
  "properties": {
    "iso:country":"US",
    "sg:address":"6836 San Pedro Ave",
    "sg:city":"San Antonio",
    "sg:classifiers":[
        {
            "category":"Education",
            "subcategory":"Special Training",
            "type":"Public Place"
        }
    ],
    "sg:phone":"+1 210 240 0613",
    "sg:postcode":"78216",
    "sg:province":"TX",
    "sg:tags":[
        "instruction",
        "music"
    ],
    "wof:name":"San Antonio Guitar School",
    "wof:placetype":"venue"
},
  "geometry": {"coordinates":[-98.49918099999999,29.503466],"type":"Point"}
}