{
  "type": "Feature",
  "properties": {
    "iso:country":"US",
    "sg:address":"5606 Rabb Ridge Dr",
    "sg:city":"Richmond",
    "sg:classifiers":[
        {
            "category":"Building & Trades",
            "subcategory":"Electrical",
            "type":"Services"
        }
    ],
    "sg:phone":"+1 281 343 9500",
    "sg:postcode":"77469",
    "sg:province":"TX",
    "sg:tags":[
        "electric",
        "industrial",
        "contractors-commercial",
        "contractor"
    ],
    "wof:name":"Cook Electrical Improvements",
    "wof:placetype":"venue"
},
  "geometry": {"coordinates":[-95.70456,29.542387],"type":"Point"}
}