{
  "type": "Feature",
  "properties": {
    "iso:country":"US",
    "sg:address":"8277 Kirby Dr",
    "sg:city":"Houston",
    "sg:classifiers":[
        {
            "category":"Building & Trades",
            "subcategory":"Construction",
            "type":"Services"
        }
    ],
    "sg:phone":"+1 713 797 6112",
    "sg:postcode":"77054",
    "sg:province":"TX",
    "sg:tags":[
        "contractor"
    ],
    "wof:name":"Linbeck Construction",
    "wof:placetype":"venue"
},
  "geometry": {"coordinates":[-95.412508,29.691199],"type":"Point"}
}