{
  "type": "Feature",
  "properties": {
    "iso:country":"US",
    "sg:address":"10614 Slaughter Creek Dr",
    "sg:city":"Austin",
    "sg:classifiers":[
        {
            "category":"Communications",
            "subcategory":"Radio Station",
            "type":"Services"
        }
    ],
    "sg:phone":"+1 512 924 7779",
    "sg:postcode":"78748",
    "sg:province":"TX",
    "sg:tags":[
        "broadcast"
    ],
    "wof:name":"Texas Revolution",
    "wof:placetype":"venue"
},
  "geometry": {"coordinates":[-97.818995,30.156407],"type":"Point"}
}