{
  "type": "Feature",
  "properties": {
    "iso:country":"US",
    "sg:address":"300 S West Dr",
    "sg:city":"Leander",
    "sg:classifiers":[
        {
            "category":"Education",
            "subcategory":"School",
            "type":"Public Place"
        }
    ],
    "sg:phone":"+1 512 434 5003",
    "sg:postcode":"78641",
    "sg:province":"TX",
    "sg:website":"www.leanderisd.org",
    "wof:name":"Leo Center School",
    "wof:placetype":"venue"
},
  "geometry": {"coordinates":[-97.854742,30.575133],"type":"Point"}
}