{
  "type": "Feature",
  "properties": {
    "iso:country":"US",
    "sg:address":"401 Ssgt Macario Garcia Dr",
    "sg:city":"Houston",
    "sg:classifiers":[
        {
            "category":"Retail",
            "subcategory":"Funeral Services",
            "type":"Services"
        },
        {
            "category":"Cemetery",
            "type":"Public Place"
        }
    ],
    "sg:phone":"+1 713 921 3000",
    "sg:postcode":"77011",
    "sg:province":"TX",
    "sg:tags":[
        "director",
        "casket",
        "crematory"
    ],
    "sg:website":"http://www.santanafuneraldirectors.com",
    "wof:name":"Santana Funeral Directors",
    "wof:placetype":"venue"
},
  "geometry": {"coordinates":[-95.303459,29.73831],"type":"Point"}
}