{
  "type": "Feature",
  "properties": {
    "iso:country":"US",
    "sg:address":"508 Deerfoot Dr",
    "sg:city":"Round Rock",
    "sg:classifiers":[
        {
            "category":"Building & Trades",
            "subcategory":"Landscaping Services",
            "type":"Services"
        }
    ],
    "sg:phone":"+1 512 255 6469",
    "sg:postcode":"78664",
    "sg:province":"TX",
    "sg:tags":[
        "landscape"
    ],
    "wof:name":"Longhorn Landscaping",
    "wof:placetype":"venue"
},
  "geometry": {"coordinates":[-97.67370200000001,30.505717],"type":"Point"}
}