{
  "type": "Feature",
  "properties": {
    "iso:country":"US",
    "sg:address":"2314 Bagby St",
    "sg:city":"Houston",
    "sg:classifiers":[
        {
            "category":"Restaurant",
            "type":"Food & Drink"
        }
    ],
    "sg:menulink":"http://www.allmenus.com/tx/houston/62821-subway/menu/",
    "sg:phone":"+1 713 807 7977",
    "sg:postcode":"77006",
    "sg:province":"TX",
    "sg:tags":[
        "american",
        "sandwich"
    ],
    "wof:name":"Subway",
    "wof:placetype":"venue"
},
  "geometry": {"coordinates":[-95.377889,29.750196],"type":"Point"}
}