{
  "type": "Feature",
  "properties": {
    "iso:country":"US",
    "sg:address":"4201 Garth Rd",
    "sg:city":"Baytown",
    "sg:classifiers":[
        {
            "category":"Health Services",
            "subcategory":"Doctor",
            "type":"Services"
        }
    ],
    "sg:phone":"+1 281 420 2391",
    "sg:postcode":"77521",
    "sg:province":"TX",
    "sg:tags":[
        "physician",
        "surgeon"
    ],
    "wof:name":"Sarma S Challa MD",
    "wof:placetype":"venue"
},
  "geometry": {"coordinates":[-94.977592,29.767798],"type":"Point"}
}