{
  "type": "Feature",
  "properties": {
    "iso:country":"US",
    "sg:address":"1914 Elderleaf Dr",
    "sg:city":"Dallas",
    "sg:classifiers":[
        {
            "category":"Professional",
            "type":"Services"
        }
    ],
    "sg:phone":"+1 214 337 0196",
    "sg:postcode":"75232",
    "sg:province":"TX",
    "wof:name":"Original Works Of Faith",
    "wof:placetype":"venue"
},
  "geometry": {"coordinates":[-96.852465,32.66323],"type":"Point"}
}