{
  "type": "Feature",
  "properties": {
    "iso:country":"US",
    "sg:address":"115 N McCarty Ave",
    "sg:city":"Eagle Lake",
    "sg:classifiers":[
        {
            "category":"Shopping",
            "subcategory":"Gifts & Souvenirs",
            "type":"Retail Goods"
        }
    ],
    "sg:phone":"+1 979 234 7330",
    "sg:postcode":"77434",
    "sg:province":"TX",
    "wof:name":"C & KS Garden & Gift Shop",
    "wof:placetype":"venue"
},
  "geometry": {"coordinates":[-96.33392499999999,29.589335],"type":"Point"}
}