{
  "type": "Feature",
  "properties": {
    "iso:country":"US",
    "sg:address":"110 W Sandy Lake Rd",
    "sg:city":"Coppell",
    "sg:classifiers":[
        {
            "category":"Shopping",
            "type":"Retail Goods"
        }
    ],
    "sg:phone":"+1 972 304 1663",
    "sg:postcode":"75019",
    "sg:province":"TX",
    "sg:tags":[
        "equipment",
        "merchandise",
        "business",
        "pool",
        "swimming"
    ],
    "wof:name":"Leslies Swimming Pool Supplies",
    "wof:placetype":"venue"
},
  "geometry": {"coordinates":[-96.9978,32.969588],"type":"Point"}
}