{
  "type": "Feature",
  "properties": {
    "iso:country":"US",
    "sg:address":"5001 Spring Valley Rd Ste 1000W",
    "sg:city":"Dallas",
    "sg:classifiers":[
        {
            "category":"Professional",
            "subcategory":"Employment Agencies",
            "type":"Services"
        }
    ],
    "sg:phone":"+1 972 248 4422",
    "sg:postcode":"75244",
    "sg:province":"TX",
    "sg:website":"www.superiorhire.com",
    "wof:name":"Superior Search & Staffing",
    "wof:placetype":"venue"
},
  "geometry": {"coordinates":[-96.823667,32.939991],"type":"Point"}
}