{
  "type": "Feature",
  "properties": {
    "iso:country":"US",
    "sg:address":"701 Glade Rd",
    "sg:city":"Colleyville",
    "sg:classifiers":[
        {
            "category":"Retail",
            "subcategory":"Veterinary Services",
            "type":"Services"
        }
    ],
    "sg:phone":"+1 888 386 2616",
    "sg:postcode":"76034",
    "sg:province":"TX",
    "sg:tags":[
        "clinic",
        "veterinarian",
        "hospital"
    ],
    "sg:website":"http://local.ingenio.com/Listings/Details.aspx?NUM=a%3a9618042%3a13%3a4859924%3a14%3a0%3a7",
    "wof:name":"Colleyville Animal Clinic",
    "wof:placetype":"venue"
},
  "geometry": {"coordinates":[-97.158249,32.880959],"type":"Point"}
}