{
  "type": "Feature",
  "properties": {
    "iso:country":"US",
    "sg:address":"5004 Alameda Ave",
    "sg:city":"El Paso",
    "sg:classifiers":[
        {
            "category":"Health Services",
            "subcategory":"Hospital",
            "type":"Services"
        }
    ],
    "sg:phone":"+1 915 772 6555",
    "sg:postcode":"79905",
    "sg:province":"TX",
    "sg:tags":[
        "specialty"
    ],
    "wof:name":"El Paso Methadone Maintenance",
    "wof:placetype":"venue"
},
  "geometry": {"coordinates":[-106.430311,31.769389],"type":"Point"}
}