{
  "type": "Feature",
  "properties": {
    "iso:country":"US",
    "sg:address":"7619 Vinewood Ct",
    "sg:city":"San Antonio",
    "sg:classifiers":[
        {
            "category":"Professional",
            "subcategory":"Computer Services",
            "type":"Services"
        }
    ],
    "sg:phone":"+1 210 804 1010",
    "sg:postcode":"78209",
    "sg:province":"TX",
    "sg:tags":[
        "consultant",
        "designer"
    ],
    "sg:website":"www.thompsondata.com",
    "wof:name":"Thompson Consulting Group",
    "wof:placetype":"venue"
},
  "geometry": {"coordinates":[-98.464215,29.50522],"type":"Point"}
}