{
  "type": "Feature",
  "properties": {
    "iso:country":"US",
    "sg:address":"2100 Greenway Village Dr",
    "sg:city":"Katy",
    "sg:classifiers":[
        {
            "category":"Education",
            "subcategory":"School",
            "type":"Public Place"
        }
    ],
    "sg:phone":"+1 281 396 6450",
    "sg:postcode":"77494",
    "sg:province":"TX",
    "sg:website":"www.katyisd.org",
    "wof:name":"Fielder Elementary School",
    "wof:placetype":"venue"
},
  "geometry": {"coordinates":[-95.769803,29.751527],"type":"Point"}
}