{
  "type": "Feature",
  "properties": {
    "iso:country":"US",
    "sg:address":"7502 Shiner Ln",
    "sg:city":"Houston",
    "sg:classifiers":[
        {
            "category":"Professional",
            "subcategory":"Computer Services",
            "type":"Services"
        }
    ],
    "sg:phone":"+1 281 495 3826",
    "sg:postcode":"77072",
    "sg:province":"TX",
    "sg:tags":[
        "programing",
        "custom"
    ],
    "wof:name":"Joe Works",
    "wof:placetype":"venue"
},
  "geometry": {"coordinates":[-95.58893500000001,29.698994],"type":"Point"}
}