{
  "type": "Feature",
  "properties": {
    "iso:country":"US",
    "sg:address":"10969 Shady Trl Ste 105",
    "sg:city":"Dallas",
    "sg:classifiers":[
        {
            "category":"Manufacturing",
            "subcategory":"Toys & Sporting Goods",
            "type":"Manufacturing & Wholesale Goods"
        },
        {
            "category":"Shopping",
            "subcategory":"Bicycles & Sporting Goods",
            "type":"Retail Goods"
        }
    ],
    "sg:phone":"+1 214 352 7343",
    "sg:postcode":"75220",
    "sg:province":"TX",
    "sg:tags":[
        "goods-wholesale",
        "manufacturer"
    ],
    "wof:name":"Ader Sporting Goods Inc",
    "wof:placetype":"venue"
},
  "geometry": {"coordinates":[-96.890957,32.880213],"type":"Point"}
}