{
  "type": "Feature",
  "properties": {
    "iso:country":"US",
    "sg:address":"3315 Merrifield Ave",
    "sg:city":"Dallas",
    "sg:classifiers":[
        {
            "category":"Restaurant",
            "type":"Food & Drink"
        }
    ],
    "sg:phone":"+1 214 823 4600",
    "sg:postcode":"75223",
    "sg:province":"TX",
    "wof:name":"Two D's Chicken",
    "wof:placetype":"venue"
},
  "geometry": {"coordinates":[-96.738602,32.792301],"type":"Point"}
}