{
  "type": "Feature",
  "properties": {
    "iso:country":"US",
    "sg:address":"3950 Spencer Hwy",
    "sg:city":"Pasadena",
    "sg:classifiers":[
        {
            "category":"Cinema",
            "subcategory":"Movie Rental",
            "type":"Entertainment"
        }
    ],
    "sg:phone":"+1 713 946 7620",
    "sg:postcode":"77504",
    "sg:province":"TX",
    "sg:tags":[
        "game",
        "video"
    ],
    "wof:name":"Blockbuster Videos",
    "wof:placetype":"venue"
},
  "geometry": {"coordinates":[-95.18450199999999,29.665001],"type":"Point"}
}