{
  "type": "Feature",
  "properties": {
    "iso:country":"US",
    "sg:address":"19439 Cypress Bay Ct",
    "sg:city":"Katy",
    "sg:classifiers":[
        {
            "category":"Education",
            "subcategory":"Special Training",
            "type":"Public Place"
        }
    ],
    "sg:phone":"+1 281 345 2088",
    "sg:postcode":"77449",
    "sg:province":"TX",
    "sg:tags":[
        "instruction",
        "driving"
    ],
    "wof:name":"Benson Driving Education",
    "wof:placetype":"venue"
},
  "geometry": {"coordinates":[-95.710279,29.835796],"type":"Point"}
}