{
  "type": "Feature",
  "properties": {
    "iso:country":"US",
    "sg:address":"1250 W Mockingbird Ln",
    "sg:city":"Dallas",
    "sg:classifiers":[
        {
            "category":"Food & Beverages",
            "subcategory":"Bakery",
            "type":"Retail Goods"
        }
    ],
    "sg:phone":"+1 214 638 3354",
    "sg:postcode":"75247",
    "sg:province":"TX",
    "sg:tags":[
        "sandwich"
    ],
    "wof:name":"Murphy's Deli",
    "wof:placetype":"venue"
},
  "geometry": {"coordinates":[-96.86889600000001,32.819],"type":"Point"}
}