{
  "type": "Feature",
  "properties": {
    "iso:country":"US",
    "sg:address":"6550 Mapleridge St",
    "sg:city":"Houston",
    "sg:classifiers":[
        {
            "category":"Health Services",
            "subcategory":"Hospital",
            "type":"Services"
        }
    ],
    "sg:phone":"+1 832 778 8903",
    "sg:postcode":"77081",
    "sg:province":"TX",
    "wof:name":"Pss Partial Hospital Program",
    "wof:placetype":"venue"
},
  "geometry": {"coordinates":[-95.47429700000001,29.7097],"type":"Point"}
}