{
  "type": "Feature",
  "properties": {
    "iso:country":"US",
    "sg:address":"2100 SE Loop 820",
    "sg:city":"Fort Worth",
    "sg:classifiers":[
        {
            "category":"Shopping",
            "type":"Retail Goods"
        }
    ],
    "sg:phone":"+1 817 551 6500",
    "sg:postcode":"76140",
    "sg:province":"TX",
    "sg:tags":[
        "banner"
    ],
    "sg:website":"www.ebannersandsigns.com",
    "wof:name":"Reliant Signs",
    "wof:placetype":"venue"
},
  "geometry": {"coordinates":[-97.296289,32.666534],"type":"Point"}
}