{
  "type": "Feature",
  "properties": {
    "iso:country":"US",
    "sg:address":"9324 Stratford Way",
    "sg:city":"Dallas",
    "sg:classifiers":[
        {
            "category":"Professional",
            "subcategory":"Management & Consulting",
            "type":"Services"
        }
    ],
    "sg:phone":"+1 214 353 3911",
    "sg:postcode":"75220",
    "sg:province":"TX",
    "sg:tags":[
        "consultant",
        "search",
        "executive"
    ],
    "wof:name":"Schroeder, J Associates",
    "wof:placetype":"venue"
},
  "geometry": {"coordinates":[-96.843564,32.865099],"type":"Point"}
}