{
  "type": "Feature",
  "properties": {
    "iso:country":"US",
    "sg:address":"1307 Nederland Ave",
    "sg:city":"Nederland",
    "sg:classifiers":[
        {
            "category":"Building & Trades",
            "subcategory":"Landscaping Services",
            "type":"Services"
        }
    ],
    "sg:phone":"+1 409 724 1591",
    "sg:postcode":"77627",
    "sg:province":"TX",
    "wof:name":"Edwards Tree Trimming",
    "wof:placetype":"venue"
},
  "geometry": {"coordinates":[-93.990696,29.973008],"type":"Point"}
}