{
  "type": "Feature",
  "properties": {
    "iso:country":"US",
    "sg:address":"247 Savannah Dr",
    "sg:city":"San Antonio",
    "sg:classifiers":[
        {
            "category":"Building & Trades",
            "subcategory":"Cleaning & Sanitation",
            "type":"Services"
        }
    ],
    "sg:phone":"+1 210 341 5685",
    "sg:postcode":"78213",
    "sg:province":"TX",
    "sg:tags":[
        "maintenance"
    ],
    "wof:name":"Porfirio S Munoz Maintenance",
    "wof:placetype":"venue"
},
  "geometry": {"coordinates":[-98.53372899999999,29.500114],"type":"Point"}
}