{
  "type": "Feature",
  "properties": {
    "iso:country":"US",
    "sg:address":"601 Woodland West Dr",
    "sg:city":"Waco",
    "sg:classifiers":[
        {
            "category":"Restaurant",
            "type":"Food & Drink"
        }
    ],
    "sg:phone":"+1 254 741 9763",
    "sg:postcode":"76712",
    "sg:province":"TX",
    "sg:tags":[
        "eating"
    ],
    "wof:name":"Elliott Brothers Kettle Corn",
    "wof:placetype":"venue"
},
  "geometry": {"coordinates":[-97.21822,31.505914],"type":"Point"}
}