{
  "type": "Feature",
  "properties": {
    "iso:country":"US",
    "sg:address":"11901 Spring Hill Dr",
    "sg:city":"Austin",
    "sg:classifiers":[
        {
            "category":"Professional",
            "subcategory":"Business Services",
            "type":"Services"
        }
    ],
    "sg:phone":"+1 512 837 4245",
    "sg:postcode":"78753",
    "sg:province":"TX",
    "wof:name":"Beneficial Home Inspections",
    "wof:placetype":"venue"
},
  "geometry": {"coordinates":[-97.667903,30.385275],"type":"Point"}
}