{
  "type": "Feature",
  "properties": {
    "iso:country":"US",
    "sg:address":"9369 S US Hwy 277",
    "sg:city":"San Angelo",
    "sg:classifiers":[
        {
            "category":"Recreation",
            "type":"Entertainment"
        }
    ],
    "sg:phone":"+1 325 653 2525",
    "sg:postcode":"76904",
    "sg:province":"TX",
    "sg:tags":[
        "range",
        "pistol",
        "rifle"
    ],
    "wof:name":"Devil's Mountain Rifle Range",
    "wof:placetype":"venue"
},
  "geometry": {"coordinates":[-100.435801,31.349466],"type":"Point"}
}