{
  "type": "Feature",
  "properties": {
    "iso:country":"US",
    "sg:address":"4645 State Hwy 6",
    "sg:city":"Sugar Land",
    "sg:classifiers":[
        {
            "category":"Personal",
            "subcategory":"Beauty Salon",
            "type":"Services"
        }
    ],
    "sg:phone":"+1 281 494 8815",
    "sg:postcode":"77478",
    "sg:province":"TX",
    "sg:tags":[
        "shop"
    ],
    "wof:name":"Supercuts",
    "wof:placetype":"venue"
},
  "geometry": {"coordinates":[-95.58399199999999,29.581113],"type":"Point"}
}