{
  "type": "Feature",
  "properties": {
    "iso:country":"US",
    "sg:address":"13333 Blanco Rd",
    "sg:city":"San Antonio",
    "sg:classifiers":[
        {
            "category":"Banks & Credit Unions",
            "subcategory":"Bank",
            "type":"Services"
        }
    ],
    "sg:phone":"+1 210 493 4406",
    "sg:postcode":"78216",
    "sg:province":"TX",
    "sg:tags":[
        "mortgage"
    ],
    "wof:name":"Armstrong Mortgage",
    "wof:placetype":"venue"
},
  "geometry": {"coordinates":[-98.519901,29.567222],"type":"Point"}
}