{
  "type": "Feature",
  "properties": {
    "iso:country":"US",
    "sg:address":"136 Blackfoot Trl",
    "sg:city":"Gainesville",
    "sg:classifiers":[
        {
            "category":"Wholesale",
            "subcategory":"Non-durable Goods",
            "type":"Manufacturing & Wholesale Goods"
        },
        {
            "category":"Manufacturing",
            "subcategory":"Printing",
            "type":"Manufacturing & Wholesale Goods"
        }
    ],
    "sg:phone":"+1 940 665 0952",
    "sg:postcode":"76240",
    "sg:province":"TX",
    "sg:tags":[
        "printer"
    ],
    "wof:name":"Logo World",
    "wof:placetype":"venue"
},
  "geometry": {"coordinates":[-97.013988,33.578739],"type":"Point"}
}