{
  "type": "Feature",
  "properties": {
    "iso:country":"US",
    "sg:address":"1960 Loma Linda Ct",
    "sg:city":"Fort Worth",
    "sg:classifiers":[
        {
            "category":"Farming",
            "subcategory":"Livestock Farm",
            "type":"Manufacturing & Wholesale Goods"
        }
    ],
    "sg:phone":"+1 817 492 0769",
    "sg:postcode":"76112",
    "sg:province":"TX",
    "sg:tags":[
        "specialty",
        "animal"
    ],
    "wof:name":"Mariah Avaries",
    "wof:placetype":"venue"
},
  "geometry": {"coordinates":[-97.23618,32.74989],"type":"Point"}
}