{
  "type": "Feature",
  "properties": {
    "iso:country":"US",
    "sg:address":"1049 Dockal Rd",
    "sg:city":"New Ulm",
    "sg:classifiers":[
        {
            "category":"Social Services",
            "subcategory":"Job Training",
            "type":"Services"
        }
    ],
    "sg:phone":"+1 979 357 2607",
    "sg:postcode":"78950",
    "sg:province":"TX",
    "wof:name":"Micro Technology Training",
    "wof:placetype":"venue"
},
  "geometry": {"coordinates":[-96.567549,29.991157],"type":"Point"}
}