{
  "type": "Feature",
  "properties": {
    "iso:country":"US",
    "sg:address":"300 Devine St",
    "sg:city":"Groveton",
    "sg:classifiers":[
        {
            "category":"Real Estate",
            "subcategory":"Real Estate Operator",
            "type":"Services"
        }
    ],
    "sg:phone":"+1 936 642 1573",
    "sg:postcode":"75845",
    "sg:province":"TX",
    "sg:tags":[
        "apartment"
    ],
    "wof:name":"Groveton Community Council",
    "wof:placetype":"venue"
},
  "geometry": {"coordinates":[-95.12666299999999,31.053514],"type":"Point"}
}