{
  "type": "Feature",
  "properties": {
    "iso:country":"US",
    "sg:address":"321 Gloria St",
    "sg:city":"Keller",
    "sg:classifiers":[
        {
            "category":"Professional",
            "subcategory":"Computer Services",
            "type":"Services"
        }
    ],
    "sg:phone":"+1 817 431 9487",
    "sg:postcode":"76248",
    "sg:province":"TX",
    "sg:tags":[
        "design",
        "system"
    ],
    "wof:name":"Blu Bambu Interactive",
    "wof:placetype":"venue"
},
  "geometry": {"coordinates":[-97.238285,32.928996],"type":"Point"}
}