{
  "type": "Feature",
  "properties": {
    "iso:country":"US",
    "sg:address":"1405 N Park St",
    "sg:city":"Brenham",
    "sg:classifiers":[
        {
            "category":"Manufacturing",
            "subcategory":"Toys & Sporting Goods",
            "type":"Manufacturing & Wholesale Goods"
        }
    ],
    "sg:phone":"+1 979 830 5597",
    "sg:postcode":"77833",
    "sg:province":"TX",
    "sg:tags":[
        "mfg"
    ],
    "wof:name":"Cackle Blossums",
    "wof:placetype":"venue"
},
  "geometry": {"coordinates":[-96.40185,30.180859],"type":"Point"}
}