{
  "type": "Feature",
  "properties": {
    "iso:country":"US",
    "sg:address":"8759 Gray Fox Ct",
    "sg:city":"Fort Worth",
    "sg:classifiers":[
        {
            "category":"Building & Trades",
            "subcategory":"Construction",
            "type":"Services"
        }
    ],
    "sg:phone":"+1 817 361 7395",
    "sg:postcode":"76123",
    "sg:province":"TX",
    "sg:tags":[
        "hanging",
        "contractor"
    ],
    "wof:name":"Allen Painting & Remodeling",
    "wof:placetype":"venue"
},
  "geometry": {"coordinates":[-97.383607,32.612986],"type":"Point"}
}