{
  "type": "Feature",
  "properties": {
    "iso:country":"US",
    "sg:address":"108 Hunsley Hills Blvd",
    "sg:city":"Canyon",
    "sg:classifiers":[
        {
            "category":"Wholesale",
            "subcategory":"Machinery & Supplies",
            "type":"Manufacturing & Wholesale Goods"
        }
    ],
    "sg:phone":"+1 806 655 4506",
    "sg:postcode":"79015",
    "sg:province":"TX",
    "wof:name":"Tot Co Inc",
    "wof:placetype":"venue"
},
  "geometry": {"coordinates":[-101.93603299999999,34.995601],"type":"Point"}
}