{
  "type": "Feature",
  "properties": {
    "iso:country":"US",
    "sg:address":"580 Co Rd 271",
    "sg:city":"Riomedina",
    "sg:phone":"+1 830 538 2392",
    "sg:postcode":"78066",
    "sg:province":"TX",
    "sg:tags":[
        "farm",
        "corn",
        "grain",
        "cash"
    ],
    "wof:name":"Stein Sylvan Farm",
    "wof:placetype":"venue"
},
  "geometry": {"coordinates":[-98.89812000000001,29.404335],"type":"Point"}
}