{
  "type": "Feature",
  "properties": {
    "iso:country":"US",
    "sg:address":"717 Berry Rd",
    "sg:city":"Houston",
    "sg:classifiers":[
        {
            "category":"Retail",
            "subcategory":"Auto Repair",
            "type":"Services"
        }
    ],
    "sg:phone":"+1 713 695 2155",
    "sg:postcode":"77022",
    "sg:province":"TX",
    "wof:name":"Arturo's Garage",
    "wof:placetype":"venue"
},
  "geometry": {"coordinates":[-95.365898,29.8377],"type":"Point"}
}