{
  "type": "Feature",
  "properties": {
    "iso:country":"US",
    "sg:address":"2425 Paredes Line Rd",
    "sg:city":"Brownsville",
    "sg:classifiers":[
        {
            "category":"Restaurant",
            "type":"Food & Drink"
        }
    ],
    "sg:phone":"+1 956 547 9100",
    "sg:postcode":"78521",
    "sg:province":"TX",
    "wof:name":"El Pato Mexican Food",
    "wof:placetype":"venue"
},
  "geometry": {"coordinates":[-97.483307,25.993773],"type":"Point"}
}