{
  "type": "Feature",
  "properties": {
    "iso:country":"US",
    "sg:address":"1625 Pemelton Dr",
    "sg:city":"Abilene",
    "sg:classifiers":[
        {
            "category":"Retail",
            "subcategory":"Laundry & Dry Cleaning",
            "type":"Services"
        }
    ],
    "sg:phone":"+1 325 695 2111",
    "sg:postcode":"79601",
    "sg:province":"TX",
    "wof:name":"Chem-Dry",
    "wof:placetype":"venue"
},
  "geometry": {"coordinates":[-99.70191699999999,32.467906],"type":"Point"}
}