{
  "type": "Feature",
  "properties": {
    "iso:country":"US",
    "sg:address":"2521 S Presa St",
    "sg:city":"San Antonio",
    "sg:classifiers":[
        {
            "category":"Retail",
            "subcategory":"Auto Repair",
            "type":"Services"
        }
    ],
    "sg:phone":"+1 210 534 4440",
    "sg:postcode":"78210",
    "sg:province":"TX",
    "sg:tags":[
        "tire",
        "supply"
    ],
    "wof:name":"Rodriguez Tire Shop",
    "wof:placetype":"venue"
},
  "geometry": {"coordinates":[-98.48181200000001,29.396404],"type":"Point"}
}