{
  "type": "Feature",
  "properties": {
    "iso:country":"US",
    "sg:address":"1001 E Paisano Dr",
    "sg:city":"El Paso",
    "sg:classifiers":[
        {
            "category":"Autos & Motor Vehicles",
            "subcategory":"Automobile Sales",
            "type":"Retail Goods"
        }
    ],
    "sg:phone":"+1 915 545 5364",
    "sg:postcode":"79901",
    "sg:province":"TX",
    "sg:tags":[
        "used"
    ],
    "wof:name":"Super Motors",
    "wof:placetype":"venue"
},
  "geometry": {"coordinates":[-106.479123,31.757904],"type":"Point"}
}