{
  "type": "Feature",
  "properties": {
    "iso:country":"US",
    "sg:address":"210 N Thompson St",
    "sg:city":"Conroe",
    "sg:classifiers":[
        {
            "category":"Shopping",
            "subcategory":"Used Merchandise",
            "type":"Retail Goods"
        }
    ],
    "sg:phone":"+1 936 760 1566",
    "sg:postcode":"77301",
    "sg:province":"TX",
    "sg:tags":[
        "antique"
    ],
    "wof:name":"Conroe Antiques & Resale",
    "wof:placetype":"venue"
},
  "geometry": {"coordinates":[-95.458051,30.311203],"type":"Point"}
}