{
  "type": "Feature",
  "properties": {
    "iso:country":"US",
    "sg:address":"3451 Boston Ave",
    "sg:city":"Benbrook",
    "sg:classifiers":[
        {
            "category":"Shopping",
            "subcategory":"Catalog Store",
            "type":"Retail Goods"
        }
    ],
    "sg:phone":"+1 817 905 4343",
    "sg:postcode":"76116",
    "sg:province":"TX",
    "sg:tags":[
        "mail",
        "order"
    ],
    "wof:name":"Gift Store",
    "wof:placetype":"venue"
},
  "geometry": {"coordinates":[-97.454581,32.721926],"type":"Point"}
}