{
  "type": "Feature",
  "properties": {
    "iso:country":"US",
    "sg:address":"2540 Old Denton Rd",
    "sg:city":"Carrollton",
    "sg:classifiers":[
        {
            "category":"Wholesale",
            "subcategory":"Machinery & Supplies",
            "type":"Manufacturing & Wholesale Goods"
        }
    ],
    "sg:phone":"+1 972 242 1225",
    "sg:postcode":"75006",
    "sg:province":"TX",
    "sg:tags":[
        "equipment",
        "establishment"
    ],
    "wof:name":"Sally Beauty Supply",
    "wof:placetype":"venue"
},
  "geometry": {"coordinates":[-96.90974199999999,32.979344],"type":"Point"}
}