{
  "type": "Feature",
  "properties": {
    "iso:country":"US",
    "sg:address":"3927 Knollwood Dr",
    "sg:city":"Austin",
    "sg:classifiers":[
        {
            "category":"Professional",
            "subcategory":"Business Services",
            "type":"Services"
        }
    ],
    "sg:phone":"+1 512 349 2378",
    "sg:postcode":"78731",
    "sg:province":"TX",
    "wof:name":"Jforce Inc",
    "wof:placetype":"venue"
},
  "geometry": {"coordinates":[-97.766105,30.354189],"type":"Point"}
}