{
  "type": "Feature",
  "properties": {
    "iso:country":"US",
    "sg:address":"265 Cedar Sage Dr",
    "sg:city":"Garland",
    "sg:classifiers":[
        {
            "category":"Shopping",
            "subcategory":"Clothing, Apparel, & Fashions",
            "type":"Retail Goods"
        }
    ],
    "sg:phone":"+1 972 530 8337",
    "sg:postcode":"75040",
    "sg:province":"TX",
    "wof:name":"Spiritwear Embroidery",
    "wof:placetype":"venue"
},
  "geometry": {"coordinates":[-96.611903,32.953242],"type":"Point"}
}