{
  "type": "Feature",
  "properties": {
    "iso:country":"US",
    "sg:address":"13710 Barons Bridge Dr",
    "sg:city":"Houston",
    "sg:classifiers":[
        {
            "category":"Restaurant",
            "type":"Food & Drink"
        }
    ],
    "sg:phone":"+1 281 397 8832",
    "sg:postcode":"77069",
    "sg:province":"TX",
    "sg:tags":[
        "eating"
    ],
    "wof:name":"Graham Baker Catering Co",
    "wof:placetype":"venue"
},
  "geometry": {"coordinates":[-95.519764,29.991083],"type":"Point"}
}