{
  "type": "Feature",
  "properties": {
    "iso:country":"US",
    "sg:address":"451 Carey Ln",
    "sg:city":"Springtown",
    "sg:classifiers":[
        {
            "category":"Retail",
            "subcategory":"Repair Shop",
            "type":"Services"
        }
    ],
    "sg:phone":"+1 817 220 0296",
    "sg:postcode":"76082",
    "sg:province":"TX",
    "wof:name":"Rhino Door & Repair",
    "wof:placetype":"venue"
},
  "geometry": {"coordinates":[-97.808466,32.980728],"type":"Point"}
}