{
  "type": "Feature",
  "properties": {
    "iso:country":"US",
    "sg:address":"754 N Alamo Rd Ste B12",
    "sg:city":"Alamo",
    "sg:classifiers":[
        {
            "category":"Professional",
            "type":"Services"
        }
    ],
    "sg:phone":"+1 956 702 1288",
    "sg:postcode":"78516",
    "sg:province":"TX",
    "sg:tags":[
        "transportation"
    ],
    "wof:name":"Lone Star Produce & Freight Inc",
    "wof:placetype":"venue"
},
  "geometry": {"coordinates":[-98.121088,26.196153],"type":"Point"}
}