{
  "type": "Feature",
  "properties": {
    "iso:country":"US",
    "sg:address":"374 State Hwy 75",
    "sg:city":"Huntsville",
    "sg:classifiers":[
        {
            "category":"Organizations",
            "subcategory":"Community Association",
            "type":"Services"
        }
    ],
    "sg:phone":"+1 936 291 9922",
    "sg:postcode":"77320",
    "sg:province":"TX",
    "wof:name":"American Legion Inc Post 95",
    "wof:placetype":"venue"
},
  "geometry": {"coordinates":[-95.575874,30.735579],"type":"Point"}
}