{
  "type": "Feature",
  "properties": {
    "iso:country":"US",
    "sg:address":"13534 Heartside Pl",
    "sg:city":"Dallas",
    "sg:classifiers":[
        {
            "category":"Organizations",
            "subcategory":"Religious Organization",
            "type":"Services"
        }
    ],
    "sg:phone":"+1 972 484 3759",
    "sg:postcode":"75234",
    "sg:province":"TX",
    "sg:tags":[
        "church"
    ],
    "wof:name":"Dallas North Family Church",
    "wof:placetype":"venue"
},
  "geometry": {"coordinates":[-96.884868,32.930285],"type":"Point"}
}