{
  "type": "Feature",
  "properties": {
    "iso:country":"US",
    "sg:address":"3680 Dilido Rd",
    "sg:city":"Dallas",
    "sg:classifiers":[
        {
            "category":"Communications",
            "type":"Services"
        }
    ],
    "sg:phone":"+1 214 324 4069",
    "sg:postcode":"75228",
    "sg:province":"TX",
    "sg:tags":[
        "communication"
    ],
    "wof:name":"Oc Communications",
    "wof:placetype":"venue"
},
  "geometry": {"coordinates":[-96.68813400000001,32.798181],"type":"Point"}
}