{
  "type": "Feature",
  "properties": {
    "iso:country":"US",
    "sg:address":"603 Decatur St",
    "sg:city":"Bowie",
    "sg:classifiers":[
        {
            "category":"Government",
            "subcategory":"Office",
            "type":"Public Place"
        }
    ],
    "sg:phone":"+1 940 872 1496",
    "sg:postcode":"76230",
    "sg:province":"TX",
    "sg:tags":[
        "state",
        "program"
    ],
    "wof:name":"Public Safety-Drivers License",
    "wof:placetype":"venue"
},
  "geometry": {"coordinates":[-97.83926700000001,33.550083],"type":"Point"}
}