{
  "type": "Feature",
  "properties": {
    "iso:country":"US",
    "sg:address":"3203 W Davis St",
    "sg:city":"Dallas",
    "sg:classifiers":[
        {
            "category":"Education",
            "subcategory":"School",
            "type":"Public Place"
        }
    ],
    "sg:phone":"+1 469 248 4463",
    "sg:postcode":"75211",
    "sg:province":"TX",
    "wof:name":"Golden Rule Charter School Sunnyside",
    "wof:placetype":"venue"
},
  "geometry": {"coordinates":[-96.87281,32.749667],"type":"Point"}
}