{
  "type": "Feature",
  "properties": {
    "iso:country":"US",
    "sg:address":"8323 Tidwell Rd",
    "sg:city":"Houston",
    "sg:classifiers":[
        {
            "category":"Shopping",
            "subcategory":"Used Merchandise",
            "type":"Retail Goods"
        }
    ],
    "sg:phone":"+1 713 633 4997",
    "sg:postcode":"77028",
    "sg:province":"TX",
    "wof:name":"Sams Cottage",
    "wof:placetype":"venue"
},
  "geometry": {"coordinates":[-95.271896,29.850068],"type":"Point"}
}