{
  "type": "Feature",
  "properties": {
    "iso:country":"US",
    "sg:address":"2710 Lakeside",
    "sg:city":"Mc Kinney",
    "sg:classifiers":[
        {
            "category":"Organizations",
            "subcategory":"Membership Organization",
            "type":"Services"
        }
    ],
    "sg:phone":"+1 972 529 5217",
    "sg:postcode":"75070",
    "sg:province":"TX",
    "wof:name":"McKinney Area Newcomers S",
    "wof:placetype":"venue"
},
  "geometry": {"coordinates":[-96.649603,33.180615],"type":"Point"}
}