{
  "type": "Feature",
  "properties": {
    "iso:country":"US",
    "sg:address":"1052 County Road 147",
    "sg:city":"Alice",
    "sg:phone":"+1 361 668 1780",
    "sg:postcode":"78332",
    "sg:province":"TX",
    "wof:name":"Durbin's Air Conditioning & Heating Service",
    "wof:placetype":"venue"
},
  "geometry": {"coordinates":[-98.185198,27.720766],"type":"Point"}
}