{
  "type": "Feature",
  "properties": {
    "iso:country":"US",
    "sg:address":"9317 Esplanade Dr",
    "sg:city":"Dallas",
    "sg:classifiers":[
        {
            "category":"Professional",
            "subcategory":"Management & Consulting",
            "type":"Services"
        }
    ],
    "sg:phone":"+1 214 350 9508",
    "sg:postcode":"75220",
    "sg:province":"TX",
    "wof:name":"OSI",
    "wof:placetype":"venue"
},
  "geometry": {"coordinates":[-96.8413,32.865338],"type":"Point"}
}