{
  "type": "Feature",
  "properties": {
    "iso:country":"US",
    "sg:address":"10700 Richmond Ave Ste 100",
    "sg:city":"Houston",
    "sg:classifiers":[
        {
            "category":"Home & Garden",
            "subcategory":"Garden Supply",
            "type":"Retail Goods"
        },
        {
            "category":"Banks & Credit Unions",
            "subcategory":"Financial Services",
            "type":"Services"
        }
    ],
    "sg:phone":"+1 713 780 9001",
    "sg:postcode":"77042",
    "sg:province":"TX",
    "sg:tags":[
        "nursery",
        "gardening",
        "broker",
        "mortgage"
    ],
    "wof:name":"B & B Financial & Mortgage",
    "wof:placetype":"venue"
},
  "geometry": {"coordinates":[-95.56390399999999,29.7279],"type":"Point"}
}