{
  "type": "Feature",
  "properties": {
    "iso:country":"US",
    "sg:address":"6101 E Mockingbird Ln",
    "sg:city":"Dallas",
    "sg:classifiers":[
        {
            "category":"Retail",
            "subcategory":"Auto Repair",
            "type":"Services"
        }
    ],
    "sg:phone":"+1 214 823 9842",
    "sg:postcode":"75214",
    "sg:province":"TX",
    "sg:website":"www.mobil.com",
    "wof:name":"Mockingbird-Skillman Mobil Center",
    "wof:placetype":"venue"
},
  "geometry": {"coordinates":[-96.7612,32.8367],"type":"Point"}
}