{
  "type": "Feature",
  "properties": {
    "iso:country":"US",
    "sg:address":"3406 Ivanhoe Ln",
    "sg:city":"Garland",
    "sg:classifiers":[
        {
            "category":"Organizations",
            "subcategory":"Community Association",
            "type":"Services"
        }
    ],
    "sg:phone":"+1 972 530 7234",
    "sg:postcode":"75044",
    "sg:province":"TX",
    "wof:name":"Mission Retreat Inc",
    "wof:placetype":"venue"
},
  "geometry": {"coordinates":[-96.682175,32.964333],"type":"Point"}
}