{
  "type": "Feature",
  "properties": {
    "iso:country":"US",
    "sg:address":"7910 Westbank Ave",
    "sg:city":"Houston",
    "sg:classifiers":[
        {
            "category":"Manufacturing",
            "subcategory":"Tools & Machinery",
            "type":"Manufacturing & Wholesale Goods"
        }
    ],
    "sg:phone":"+1 713 466 1919",
    "sg:postcode":"77064",
    "sg:province":"TX",
    "sg:tags":[
        "farm",
        "automotive",
        "mfg",
        "repair"
    ],
    "wof:name":"Republic Trailer & Mfg",
    "wof:placetype":"venue"
},
  "geometry": {"coordinates":[-95.5179,29.901078],"type":"Point"}
}