{
  "type": "Feature",
  "properties": {
    "iso:country":"US",
    "sg:address":"13755 Main St",
    "sg:city":"Houston",
    "sg:classifiers":[
        {
            "category":"Education",
            "subcategory":"School",
            "type":"Public Place"
        }
    ],
    "sg:phone":"+1 713 726 2100",
    "sg:postcode":"77035",
    "sg:province":"TX",
    "sg:tags":[
        "high",
        "middle",
        "elementary"
    ],
    "wof:name":"Houston Independent School District",
    "wof:placetype":"venue"
},
  "geometry": {"coordinates":[-95.487409,29.638023],"type":"Point"}
}