{
  "type": "Feature",
  "properties": {
    "iso:country":"US",
    "sg:address":"10103 Wallisville Rd",
    "sg:city":"Houston",
    "sg:classifiers":[
        {
            "category":"Autos & Motor Vehicles",
            "subcategory":"Auto Supplies",
            "type":"Retail Goods"
        }
    ],
    "sg:phone":"+1 713 671 9078",
    "sg:postcode":"77013",
    "sg:province":"TX",
    "sg:tags":[
        "tire"
    ],
    "wof:name":"GTZ Tire Company & Truck Service",
    "wof:placetype":"venue"
},
  "geometry": {"coordinates":[-95.25112,29.794326],"type":"Point"}
}