{
  "type": "Feature",
  "properties": {
    "iso:country":"US",
    "sg:address":"11 Hanover Dr",
    "sg:city":"Midland",
    "sg:classifiers":[
        {
            "category":"Shopping",
            "subcategory":"Stationery & Office Supplies",
            "type":"Retail Goods"
        }
    ],
    "sg:phone":"+1 432 682 1505",
    "sg:postcode":"79705",
    "sg:province":"TX",
    "sg:tags":[
        "stationer"
    ],
    "wof:name":"Midland Secretariat",
    "wof:placetype":"venue"
},
  "geometry": {"coordinates":[-102.10530900000001,32.021827],"type":"Point"}
}