{
  "type": "Feature",
  "properties": {
    "iso:country":"US",
    "sg:address":"5875 Weber Rd",
    "sg:city":"Corpus Christi",
    "sg:classifiers":[
        {
            "category":"Banks & Credit Unions",
            "subcategory":"Bank",
            "type":"Services"
        }
    ],
    "sg:phone":"+1 361 855 2400",
    "sg:postcode":"78413",
    "sg:province":"TX",
    "wof:name":"Bank Of America",
    "wof:placetype":"venue"
},
  "geometry": {"coordinates":[-97.404971,27.711776],"type":"Point"}
}