{
  "type": "Feature",
  "properties": {
    "iso:country":"US",
    "sg:address":"2923 Elm St",
    "sg:city":"Dallas",
    "sg:classifiers":[
        {
            "category":"Professional",
            "subcategory":"Art Services",
            "type":"Services"
        }
    ],
    "sg:phone":"+1 214 939 2333",
    "sg:postcode":"75226",
    "sg:province":"TX",
    "sg:tags":[
        "photographer"
    ],
    "sg:website":"www.mcarterphoto.com",
    "wof:name":"Big Bang Inc",
    "wof:placetype":"venue"
},
  "geometry": {"coordinates":[-96.78128,32.785188],"type":"Point"}
}