{
  "type": "Feature",
  "properties": {
    "iso:country":"US",
    "sg:address":"908 Thackeray Ln",
    "sg:city":"Pflugerville",
    "sg:classifiers":[
        {
            "category":"Professional",
            "subcategory":"Art Services",
            "type":"Services"
        }
    ],
    "sg:phone":"+1 512 990 7802",
    "sg:postcode":"78660",
    "sg:province":"TX",
    "sg:tags":[
        "graphic",
        "designer"
    ],
    "wof:name":"Creativity Works",
    "wof:placetype":"venue"
},
  "geometry": {"coordinates":[-97.640101,30.460935],"type":"Point"}
}