{
  "type": "Feature",
  "properties": {
    "iso:country":"US",
    "sg:address":"200 E Park St",
    "sg:city":"Pharr",
    "sg:classifiers":[
        {
            "category":"Retail",
            "subcategory":"Self-service Laundry",
            "type":"Services"
        }
    ],
    "sg:phone":"+1 956 787 9203",
    "sg:postcode":"78577",
    "sg:province":"TX",
    "wof:name":"Parkway Coin Laundry",
    "wof:placetype":"venue"
},
  "geometry": {"coordinates":[-98.18123199999999,26.193728],"type":"Point"}
}