{
  "type": "Feature",
  "properties": {
    "iso:country":"US",
    "sg:address":"5114 Roundtable Dr",
    "sg:city":"San Antonio",
    "sg:classifiers":[
        {
            "category":"Recreation",
            "type":"Entertainment"
        }
    ],
    "sg:phone":"+1 210 656 1936",
    "sg:postcode":"78218",
    "sg:province":"TX",
    "wof:name":"Rhr",
    "wof:placetype":"venue"
},
  "geometry": {"coordinates":[-98.391378,29.505023],"type":"Point"}
}