{
  "type": "Feature",
  "properties": {
    "iso:country":"US",
    "sg:address":"2311 Little York Rd",
    "sg:city":"Houston",
    "sg:classifiers":[
        {
            "category":"Shopping",
            "type":"Retail Goods"
        }
    ],
    "sg:phone":"+1 713 694 8085",
    "sg:postcode":"77093",
    "sg:province":"TX",
    "sg:tags":[
        "merchandise"
    ],
    "wof:name":"My Cellular",
    "wof:placetype":"venue"
},
  "geometry": {"coordinates":[-95.350469,29.871069],"type":"Point"}
}