{
  "type": "Feature",
  "properties": {
    "iso:country":"US",
    "sg:address":"2918 Sun Valley St",
    "sg:city":"Irving",
    "sg:classifiers":[
        {
            "category":"Building & Trades",
            "subcategory":"Construction",
            "type":"Services"
        }
    ],
    "sg:phone":"+1 214 770 9300",
    "sg:postcode":"75062",
    "sg:province":"TX",
    "sg:tags":[
        "contractor"
    ],
    "wof:name":"Joe Hooper Enterprises",
    "wof:placetype":"venue"
},
  "geometry": {"coordinates":[-97.006047,32.847347],"type":"Point"}
}