{
  "type": "Feature",
  "properties": {
    "iso:country":"US",
    "sg:address":"408 N Kaufman St",
    "sg:city":"Ennis",
    "sg:classifiers":[
        {
            "category":"Autos & Motor Vehicles",
            "subcategory":"Auto Supplies",
            "type":"Retail Goods"
        },
        {
            "category":"Shopping",
            "subcategory":"Computers & Home Electronics",
            "type":"Retail Goods"
        }
    ],
    "sg:phone":"+1 972 875 1044",
    "sg:postcode":"75119",
    "sg:province":"TX",
    "sg:tags":[
        "automobile",
        "stereo",
        "radio"
    ],
    "wof:name":"Performance Car Audio Of Ennis",
    "wof:placetype":"venue"
},
  "geometry": {"coordinates":[-96.626031,32.331642],"type":"Point"}
}