{
  "type": "Feature",
  "properties": {
    "iso:country":"US",
    "sg:address":"908 Ferris Ave",
    "sg:city":"Waxahachie",
    "sg:classifiers":[
        {
            "category":"Restaurant",
            "type":"Food & Drink"
        }
    ],
    "sg:menulink":"http://www.allmenus.com/tx/waxahachie/131003-subway/menu/",
    "sg:phone":"+1 972 937 3330",
    "sg:postcode":"75165",
    "sg:province":"TX",
    "sg:tags":[
        "american",
        "sandwich"
    ],
    "wof:name":"Subway",
    "wof:placetype":"venue"
},
  "geometry": {"coordinates":[-96.845553,32.396065],"type":"Point"}
}