{
  "type": "Feature",
  "properties": {
    "iso:country":"US",
    "sg:address":"651 Cribbs Dr",
    "sg:city":"Coppell",
    "sg:classifiers":[
        {
            "category":"Building & Trades",
            "subcategory":"Plumbing",
            "type":"Services"
        }
    ],
    "sg:phone":"+1 972 462 0502",
    "sg:postcode":"75019",
    "sg:province":"TX",
    "sg:tags":[
        "contractor"
    ],
    "wof:name":"R C Mechanical Inc",
    "wof:placetype":"venue"
},
  "geometry": {"coordinates":[-96.97458399999999,32.982569],"type":"Point"}
}