{
  "type": "Feature",
  "properties": {
    "iso:country":"US",
    "sg:address":"12830 State Hwy 29",
    "sg:city":"Liberty Hill",
    "sg:classifiers":[
        {
            "category":"Building & Trades",
            "subcategory":"Construction",
            "type":"Services"
        }
    ],
    "sg:phone":"+1 512 515 6096",
    "sg:postcode":"78642",
    "sg:province":"TX",
    "sg:tags":[
        "house"
    ],
    "wof:name":"Payne Company",
    "wof:placetype":"venue"
},
  "geometry": {"coordinates":[-97.89490000000001,30.660327],"type":"Point"}
}