{
  "type": "Feature",
  "properties": {
    "iso:country":"US",
    "sg:address":"6203 Airline Dr",
    "sg:city":"Houston",
    "sg:classifiers":[
        {
            "category":"Autos & Motor Vehicles",
            "subcategory":"Automobile Sales",
            "type":"Retail Goods"
        }
    ],
    "sg:phone":"+1 713 697 7292",
    "sg:postcode":"77076",
    "sg:province":"TX",
    "sg:tags":[
        "car",
        "dealer"
    ],
    "wof:name":"Mi Raza Auto Sales",
    "wof:placetype":"venue"
},
  "geometry": {"coordinates":[-95.384715,29.855973],"type":"Point"}
}