{
  "type": "Feature",
  "properties": {
    "iso:country":"US",
    "sg:address":"4811 Pine St",
    "sg:city":"Seabrook",
    "sg:classifiers":[
        {
            "category":"Professional",
            "subcategory":"Business Services",
            "type":"Services"
        }
    ],
    "sg:phone":"+1 281 474 4299",
    "sg:postcode":"77586",
    "sg:province":"TX",
    "wof:name":"Disentey Balloons Design",
    "wof:placetype":"venue"
},
  "geometry": {"coordinates":[-94.995199,29.602482],"type":"Point"}
}