{
  "type": "Feature",
  "properties": {
    "iso:country":"US",
    "sg:address":"1008 Henderson St",
    "sg:city":"Houston",
    "sg:classifiers":[
        {
            "category":"Restaurant",
            "type":"Food & Drink"
        }
    ],
    "sg:phone":"+1 281 342 1511",
    "sg:postcode":"77007",
    "sg:province":"TX",
    "sg:tags":[
        "eating"
    ],
    "wof:name":"Papa Mex",
    "wof:placetype":"venue"
},
  "geometry": {"coordinates":[-95.37934799999999,29.768719],"type":"Point"}
}