{
  "type": "Feature",
  "properties": {
    "iso:country":"US",
    "sg:address":"340 W Tyler St",
    "sg:city":"Longview",
    "sg:classifiers":[
        {
            "category":"Mining & Drilling",
            "type":"Manufacturing & Wholesale Goods"
        },
        {
            "category":"Professional",
            "subcategory":"Management & Consulting",
            "type":"Services"
        },
        {
            "category":"Professional",
            "subcategory":"Engineering",
            "type":"Services"
        }
    ],
    "sg:phone":"+1 903 753 8200",
    "sg:postcode":"75601",
    "sg:province":"TX",
    "sg:tags":[
        "consultant",
        "ecological",
        "engineer",
        "geologist",
        "environmental"
    ],
    "wof:name":"Godsey & Associates",
    "wof:placetype":"venue"
},
  "geometry": {"coordinates":[-94.745499,32.497158],"type":"Point"}
}