{
  "type": "Feature",
  "properties": {
    "iso:country":"US",
    "sg:address":"6710 Lower Arrow Dr",
    "sg:city":"Houston",
    "sg:classifiers":[
        {
            "category":"Professional",
            "type":"Services"
        }
    ],
    "sg:phone":"+1 281 820 3524",
    "sg:postcode":"77086",
    "sg:province":"TX",
    "wof:name":"Gigante De San Luis Dj",
    "wof:placetype":"venue"
},
  "geometry": {"coordinates":[-95.489036,29.918534],"type":"Point"}
}