{
  "type": "Feature",
  "properties": {
    "iso:country":"US",
    "sg:address":"5847 San Felipe St",
    "sg:city":"Houston",
    "sg:classifiers":[
        {
            "category":"Professional",
            "subcategory":"Accounting & Tax Preparation",
            "type":"Services"
        },
        {
            "category":"Wholesale",
            "subcategory":"Office Equipment",
            "type":"Manufacturing & Wholesale Goods"
        }
    ],
    "sg:phone":"+1 713 621 8090",
    "sg:postcode":"77057",
    "sg:province":"TX",
    "sg:tags":[
        "return",
        "preparation-business",
        "accountants-certified",
        "supply",
        "machine",
        "bookkeeping",
        "public"
    ],
    "sg:website":"http://www.gddcpa.com",
    "wof:name":"Gainer, Donnelly, And Desroches",
    "wof:placetype":"venue"
},
  "geometry": {"coordinates":[-95.4825,29.749922],"type":"Point"}
}