{
  "type": "Feature",
  "properties": {
    "iso:country":"US",
    "sg:address":"14100 Trinity Blvd",
    "sg:city":"Fort Worth",
    "sg:classifiers":[
        {
            "category":"Restaurant",
            "type":"Food & Drink"
        }
    ],
    "sg:menulink":"http://www.allmenus.com/tx/fort-worth/177451-jack-in-the-box/menu/",
    "sg:phone":"+1 817 358 9517",
    "sg:postcode":"76155",
    "sg:province":"TX",
    "sg:tags":[
        "burger",
        "american"
    ],
    "wof:name":"Jack in the Box",
    "wof:placetype":"venue"
},
  "geometry": {"coordinates":[-97.060213,32.822236],"type":"Point"}
}