{
  "type": "Feature",
  "properties": {
    "iso:country":"US",
    "sg:address":"5312 Quad Ln",
    "sg:city":"Beaumont",
    "sg:classifiers":[
        {
            "category":"Restaurant",
            "type":"Food & Drink"
        }
    ],
    "sg:phone":"+1 409 842 9417",
    "sg:postcode":"77705",
    "sg:province":"TX",
    "sg:tags":[
        "eating"
    ],
    "wof:name":"Chill Zone Snow Cones",
    "wof:placetype":"venue"
},
  "geometry": {"coordinates":[-94.152203,30.036539],"type":"Point"}
}