{
  "type": "Feature",
  "properties": {
    "iso:country":"US",
    "sg:address":"12308 FM 3083",
    "sg:city":"Conroe",
    "sg:classifiers":[
        {
            "category":"Wholesale",
            "subcategory":"Machinery & Supplies",
            "type":"Manufacturing & Wholesale Goods"
        }
    ],
    "sg:phone":"+1 281 893 3320",
    "sg:postcode":"77301",
    "sg:province":"TX",
    "sg:tags":[
        "equipment",
        "industrial",
        "legal"
    ],
    "wof:name":"Wenzel Downhole Tools Inc",
    "wof:placetype":"venue"
},
  "geometry": {"coordinates":[-95.38760000000001,30.295795],"type":"Point"}
}