{
  "type": "Feature",
  "properties": {
    "iso:country":"US",
    "sg:address":"821 W 11th St",
    "sg:city":"Austin",
    "sg:phone":"+1 512 535 1081",
    "sg:postcode":"78701",
    "sg:province":"TX",
    "sg:website":"http://www.pq-law.com",
    "wof:name":"Law Office Of Paul Quinzi",
    "wof:placetype":"venue"
},
  "geometry": {"coordinates":[-97.75039700000001,30.275351],"type":"Point"}
}