{
  "type": "Feature",
  "properties": {
    "iso:country":"US",
    "sg:address":"718 Murphy Ln",
    "sg:city":"Pasadena",
    "sg:classifiers":[
        {
            "category":"Autos & Motor Vehicles",
            "subcategory":"Boat Sales",
            "type":"Retail Goods"
        }
    ],
    "sg:phone":"+1 713 944 2058",
    "sg:postcode":"77504",
    "sg:province":"TX",
    "sg:tags":[
        "equipment",
        "marine",
        "supply"
    ],
    "wof:name":"Merchant Marine Mechanics",
    "wof:placetype":"venue"
},
  "geometry": {"coordinates":[-95.201761,29.657955],"type":"Point"}
}