{
  "type": "Feature",
  "properties": {
    "iso:country":"US",
    "sg:address":"201 Cooper St",
    "sg:city":"Falls City",
    "sg:classifiers":[
        {
            "category":"Manufacturing",
            "subcategory":"Pet Food",
            "type":"Manufacturing & Wholesale Goods"
        }
    ],
    "sg:phone":"+1 830 254 3332",
    "sg:postcode":"78113",
    "sg:province":"TX",
    "sg:tags":[
        "feed"
    ],
    "wof:name":"Falls City Milling Co",
    "wof:placetype":"venue"
},
  "geometry": {"coordinates":[-98.01932499999999,28.982353],"type":"Point"}
}