{
  "type": "Feature",
  "properties": {
    "iso:country":"US",
    "sg:address":"1940 Highway 35 N",
    "sg:city":"Rockport",
    "sg:classifiers":[
        {
            "category":"Personal",
            "subcategory":"Beauty Salon",
            "type":"Services"
        }
    ],
    "sg:phone":"+1 361 729 5474",
    "sg:postcode":"78382",
    "sg:province":"TX",
    "wof:name":"Visiblecuts",
    "wof:placetype":"venue"
},
  "geometry": {"coordinates":[-97.042526,28.043133],"type":"Point"}
}