{
  "type": "Feature",
  "properties": {
    "iso:country":"US",
    "sg:address":"127 Jamar Dr",
    "sg:city":"Weatherford",
    "sg:classifiers":[
        {
            "category":"Professional",
            "subcategory":"Engineering",
            "type":"Services"
        }
    ],
    "sg:phone":"+1 864 907 3797",
    "sg:postcode":"76088",
    "sg:province":"TX",
    "sg:tags":[
        "consulting"
    ],
    "wof:name":"Kooling Solutions Inc",
    "wof:placetype":"venue"
},
  "geometry": {"coordinates":[-97.825333,32.866625],"type":"Point"}
}