{
  "type": "Feature",
  "properties": {
    "iso:country":"US",
    "sg:address":"500 S Garcia St",
    "sg:city":"Port Isabel",
    "sg:classifiers":[
        {
            "category":"Retail",
            "subcategory":"Repair Shop",
            "type":"Services"
        }
    ],
    "sg:phone":"+1 956 943 1613",
    "sg:postcode":"78578",
    "sg:province":"TX",
    "sg:tags":[
        "taxidermist"
    ],
    "wof:name":"Palermo Taxidermy",
    "wof:placetype":"venue"
},
  "geometry": {"coordinates":[-97.204556,26.075053],"type":"Point"}
}