{
  "type": "Feature",
  "properties": {
    "iso:country":"US",
    "sg:address":"817 N Travis St",
    "sg:city":"Liberty",
    "sg:classifiers":[
        {
            "category":"Health Services",
            "subcategory":"Doctor",
            "type":"Services"
        }
    ],
    "sg:phone":"+1 936 336 3322",
    "sg:postcode":"77575",
    "sg:province":"TX",
    "wof:name":"Stephen L Beyer DDS",
    "wof:placetype":"venue"
},
  "geometry": {"coordinates":[-94.797894,30.06384],"type":"Point"}
}