{
  "type": "Feature",
  "properties": {
    "iso:country":"US",
    "sg:address":"2018 Oak Trail Dr",
    "sg:city":"Rowlett",
    "sg:classifiers":[
        {
            "category":"Place Of Worship",
            "subcategory":"Church",
            "type":"Public Place"
        },
        {
            "category":"Place Of Worship",
            "type":"Public Place"
        }
    ],
    "sg:phone":"+1 972 741 0240",
    "sg:postcode":"75088",
    "sg:province":"TX",
    "sg:tags":[
        "churches-non-denominational"
    ],
    "wof:name":"David Eric Daniell",
    "wof:placetype":"venue"
},
  "geometry": {"coordinates":[-96.570183,32.881655],"type":"Point"}
}