{
  "type": "Feature",
  "properties": {
    "iso:country":"US",
    "sg:address":"2100 Reliance Pkwy",
    "sg:city":"Bedford",
    "sg:classifiers":[
        {
            "category":"Communications",
            "type":"Services"
        }
    ],
    "sg:phone":"+1 817 575 2300",
    "sg:postcode":"76021",
    "sg:province":"TX",
    "wof:name":"Tellabs Inc",
    "wof:placetype":"venue"
},
  "geometry": {"coordinates":[-97.107686,32.841213],"type":"Point"}
}