{
  "type": "Feature",
  "properties": {
    "iso:country":"US",
    "sg:address":"3401 N Shepherd Dr",
    "sg:city":"Houston",
    "sg:classifiers":[
        {
            "category":"Wholesale",
            "subcategory":"Durable Goods & Equipment",
            "type":"Manufacturing & Wholesale Goods"
        }
    ],
    "sg:phone":"+1 713 880 8091",
    "sg:postcode":"77018",
    "sg:province":"TX",
    "sg:tags":[
        "marker",
        "cemetery",
        "monument"
    ],
    "wof:name":"Rose Monument",
    "wof:placetype":"venue"
},
  "geometry": {"coordinates":[-95.41043500000001,29.818413],"type":"Point"}
}