{
  "type": "Feature",
  "properties": {
    "iso:country":"US",
    "sg:address":"2103 Danbury St",
    "sg:city":"San Antonio",
    "sg:classifiers":[
        {
            "category":"Utilities",
            "subcategory":"Telephone",
            "type":"Services"
        }
    ],
    "sg:phone":"+1 210 828 6797",
    "sg:postcode":"78217",
    "sg:province":"TX",
    "sg:tags":[
        "mobile",
        "cellular"
    ],
    "wof:name":"PCI",
    "wof:placetype":"venue"
},
  "geometry": {"coordinates":[-98.456473,29.524854],"type":"Point"}
}