{
  "type": "Feature",
  "properties": {
    "iso:country":"US",
    "sg:address":"2209 McDonell Ave",
    "sg:city":"Laredo",
    "sg:classifiers":[
        {
            "category":"Personal",
            "subcategory":"Beauty Salon",
            "type":"Services"
        }
    ],
    "sg:phone":"+1 956 725 9946",
    "sg:postcode":"78040",
    "sg:province":"TX",
    "sg:tags":[
        "shop"
    ],
    "wof:name":"Rono's Beauty Salon",
    "wof:placetype":"venue"
},
  "geometry": {"coordinates":[-99.496736,27.516667],"type":"Point"}
}