{
  "type": "Feature",
  "properties": {
    "iso:country":"US",
    "sg:address":"5580 Peterson Ln Ste 250",
    "sg:city":"Dallas",
    "sg:classifiers":[
        {
            "category":"Real Estate",
            "subcategory":"Real Estate Services",
            "type":"Services"
        }
    ],
    "sg:phone":"+1 972 991 4735",
    "sg:postcode":"75240",
    "sg:province":"TX",
    "wof:name":"Peterson Place Real Estate",
    "wof:placetype":"venue"
},
  "geometry": {"coordinates":[-96.81210299999999,32.930599],"type":"Point"}
}