{
  "type": "Feature",
  "properties": {
    "iso:country":"US",
    "sg:address":"14 Hampton Pl",
    "sg:city":"Spring",
    "sg:classifiers":[
        {
            "category":"Building & Trades",
            "subcategory":"Construction",
            "type":"Services"
        }
    ],
    "sg:phone":"+1 281 681 8778",
    "sg:postcode":"77381",
    "sg:province":"TX",
    "sg:tags":[
        "house"
    ],
    "wof:name":"H W D Woodlands",
    "wof:placetype":"venue"
},
  "geometry": {"coordinates":[-95.490521,30.161458],"type":"Point"}
}