{
  "type": "Feature",
  "properties": {
    "iso:country":"US",
    "sg:address":"50 Waugh Dr",
    "sg:city":"Houston",
    "sg:classifiers":[
        {
            "category":"Organizations",
            "subcategory":"Non-profit Organization",
            "type":"Services"
        }
    ],
    "sg:phone":"+1 713 685 2300",
    "sg:postcode":"77007",
    "sg:province":"TX",
    "sg:tags":[
        "service/non-profit",
        "community"
    ],
    "sg:website":"www.unitedwayhouston.org",
    "wof:name":"United Way of Greater Houston",
    "wof:placetype":"venue"
},
  "geometry": {"coordinates":[-95.398122,29.766873],"type":"Point"}
}