{
  "type": "Feature",
  "properties": {
    "iso:country":"US",
    "sg:address":"1909 Crouch Rd",
    "sg:city":"Dallas",
    "sg:classifiers":[
        {
            "category":"Recreation",
            "type":"Entertainment"
        }
    ],
    "sg:phone":"+1 214 670 7550",
    "sg:postcode":"75241",
    "sg:province":"TX",
    "sg:tags":[
        "center"
    ],
    "wof:name":"Singing Hills Recreation Ctr",
    "wof:placetype":"venue"
},
  "geometry": {"coordinates":[-96.784279,32.672402],"type":"Point"}
}