{
  "type": "Feature",
  "properties": {
    "iso:country":"US",
    "sg:address":"2911 Texas Ave S",
    "sg:city":"Bryan",
    "sg:classifiers":[
        {
            "category":"Health Services",
            "subcategory":"Doctor",
            "type":"Services"
        }
    ],
    "sg:phone":"+1 979 693 0656",
    "sg:postcode":"77802",
    "sg:province":"TX",
    "sg:tags":[
        "dentist"
    ],
    "wof:name":"Elms Orthodontics",
    "wof:placetype":"venue"
},
  "geometry": {"coordinates":[-96.35345,30.643729],"type":"Point"}
}