{
  "type": "Feature",
  "properties": {
    "iso:country":"US",
    "sg:address":"309 Orange St",
    "sg:city":"Cleveland",
    "sg:classifiers":[
        {
            "category":"Restaurant",
            "type":"Food & Drink"
        }
    ],
    "sg:phone":"+1 281 432 1566",
    "sg:postcode":"77327",
    "sg:province":"TX",
    "sg:tags":[
        "eating"
    ],
    "wof:name":"Lonestar Rolling Stop Lite",
    "wof:placetype":"venue"
},
  "geometry": {"coordinates":[-95.082525,30.360233],"type":"Point"}
}