{
  "type": "Feature",
  "properties": {
    "iso:country":"US",
    "sg:address":"207 W Juan Linn St",
    "sg:city":"Victoria",
    "sg:classifiers":[
        {
            "category":"Building & Trades",
            "subcategory":"Plumbing",
            "type":"Services"
        }
    ],
    "sg:phone":"+1 361 580 0046",
    "sg:postcode":"77901",
    "sg:province":"TX",
    "sg:tags":[
        "product",
        "management",
        "energy",
        "system"
    ],
    "wof:name":"O'Connor Energy",
    "wof:placetype":"venue"
},
  "geometry": {"coordinates":[-97.00869400000001,28.797926],"type":"Point"}
}