{
  "type": "Feature",
  "properties": {
    "iso:country":"US",
    "sg:address":"20624 Plaza Cir",
    "sg:city":"Crosby",
    "sg:classifiers":[
        {
            "category":"Building & Trades",
            "subcategory":"Cleaning & Sanitation",
            "type":"Services"
        }
    ],
    "sg:phone":"+1 281 328 6751",
    "sg:postcode":"77532",
    "sg:province":"TX",
    "sg:tags":[
        "maintenance"
    ],
    "wof:name":"Olympic Office Cleaning",
    "wof:placetype":"venue"
},
  "geometry": {"coordinates":[-95.000299,29.972999],"type":"Point"}
}