{
  "type": "Feature",
  "properties": {
    "iso:country":"US",
    "sg:address":"13101 Preston Rd",
    "sg:city":"Dallas",
    "sg:classifiers":[
        {
            "category":"Personal",
            "type":"Services"
        }
    ],
    "sg:phone":"+1 972 991 2553",
    "sg:postcode":"75240",
    "sg:province":"TX",
    "sg:tags":[
        "hair",
        "replacement"
    ],
    "sg:website":"www.masterpiece.com",
    "wof:name":"Masterpiece Of Hollywood",
    "wof:placetype":"venue"
},
  "geometry": {"coordinates":[-96.803556,32.927363],"type":"Point"}
}