{
  "type": "Feature",
  "properties": {
    "iso:country":"US",
    "sg:address":"506 E San Antonio St",
    "sg:city":"Victoria",
    "sg:classifiers":[
        {
            "category":"Health Services",
            "subcategory":"Doctor",
            "type":"Services"
        }
    ],
    "sg:phone":"+1 361 788 2549",
    "sg:postcode":"77901",
    "sg:province":"TX",
    "sg:tags":[
        "physician",
        "surgeon"
    ],
    "wof:name":"Lyster Hornish & Assoc",
    "wof:placetype":"venue"
},
  "geometry": {"coordinates":[-96.998417,28.807668],"type":"Point"}
}