{
  "type": "Feature",
  "properties": {
    "iso:country":"US",
    "sg:address":"2527 State Highway 361 D",
    "sg:city":"Ingleside",
    "sg:classifiers":[
        {
            "category":"Insurance",
            "subcategory":"Insurance Agent",
            "type":"Services"
        },
        {
            "category":"Insurance",
            "subcategory":"Hazard Insurance",
            "type":"Services"
        }
    ],
    "sg:phone":"+1 361 775 1271",
    "sg:postcode":"78362",
    "sg:province":"TX",
    "sg:tags":[
        "auto"
    ],
    "wof:name":"Michael Ladewig Agency, Inc.",
    "wof:placetype":"venue"
},
  "geometry": {"coordinates":[-97.207787,27.880629],"type":"Point"}
}