{
  "type": "Feature",
  "properties": {
    "iso:country":"US",
    "sg:address":"1412 S Voss Rd",
    "sg:city":"Houston",
    "sg:classifiers":[
        {
            "category":"Restaurant",
            "type":"Food & Drink"
        }
    ],
    "sg:menulink":"http://www.allmenus.com/tx/houston/48639-chipotle/menu/",
    "sg:phone":"+1 713 278 1310",
    "sg:postcode":"77057",
    "sg:province":"TX",
    "sg:tags":[
        "mexican"
    ],
    "wof:name":"Chipotle",
    "wof:placetype":"venue"
},
  "geometry": {"coordinates":[-95.50119599999999,29.752745],"type":"Point"}
}