{
  "type": "Feature",
  "properties": {
    "iso:country":"US",
    "sg:address":"1700 W Loop Fwy",
    "sg:city":"Houston",
    "sg:classifiers":[
        {
            "category":"Professional",
            "subcategory":"Engineering",
            "type":"Services"
        }
    ],
    "sg:phone":"+1 713 850 3400",
    "sg:postcode":"77056",
    "sg:province":"TX",
    "sg:tags":[
        "engineer"
    ],
    "sg:website":"www.gie.com",
    "wof:name":"Gulf Interstate Engineering",
    "wof:placetype":"venue"
},
  "geometry": {"coordinates":[-95.45638700000001,29.749736],"type":"Point"}
}