{
  "type": "Feature",
  "properties": {
    "iso:country":"US",
    "sg:address":"1807 US Hwy 281",
    "sg:city":"Marble Falls",
    "sg:classifiers":[
        {
            "category":"Utilities",
            "subcategory":"Mobile Phone",
            "type":"Services"
        }
    ],
    "sg:phone":"+1 830 798 0374",
    "sg:postcode":"78654",
    "sg:province":"TX",
    "sg:tags":[
        "communication",
        "telephone",
        "cellular",
        "radiotelephone"
    ],
    "wof:name":"Conquered Communications",
    "wof:placetype":"venue"
},
  "geometry": {"coordinates":[-98.286221,30.525277],"type":"Point"}
}