{
  "type": "Feature",
  "properties": {
    "iso:country":"US",
    "sg:address":"4800 Drexel Dr",
    "sg:city":"Dallas",
    "sg:classifiers":[
        {
            "category":"Professional",
            "subcategory":"Art Services",
            "type":"Services"
        }
    ],
    "sg:phone":"+1 214 528 8851",
    "sg:postcode":"75205",
    "sg:province":"TX",
    "sg:tags":[
        "commercial",
        "design"
    ],
    "wof:name":"Coquinas Designs",
    "wof:placetype":"venue"
},
  "geometry": {"coordinates":[-96.79510399999999,32.83088],"type":"Point"}
}