{
  "type": "Feature",
  "properties": {
    "iso:country":"US",
    "sg:address":"5122 Fredericksburg Rd",
    "sg:city":"San Antonio",
    "sg:classifiers":[
        {
            "category":"Real Estate",
            "subcategory":"Real Estate Agent",
            "type":"Services"
        }
    ],
    "sg:phone":"+1 210 348 8920",
    "sg:postcode":"78229",
    "sg:province":"TX",
    "sg:tags":[
        "finding",
        "apartment",
        "rental"
    ],
    "wof:name":"Hillcoat Properties Inc",
    "wof:placetype":"venue"
},
  "geometry": {"coordinates":[-98.56027400000001,29.502871],"type":"Point"}
}