{
  "type": "Feature",
  "properties": {
    "iso:country":"US",
    "sg:address":"6609 Kingswood Dr",
    "sg:city":"Fort Worth",
    "sg:classifiers":[
        {
            "category":"Shopping",
            "subcategory":"Computers & Home Electronics",
            "type":"Retail Goods"
        }
    ],
    "sg:phone":"+1 817 370 8177",
    "sg:postcode":"76133",
    "sg:province":"TX",
    "wof:name":"Ricks Parts 4 Pcs",
    "wof:placetype":"venue"
},
  "geometry": {"coordinates":[-97.39167399999999,32.649913],"type":"Point"}
}