{
  "type": "Feature",
  "properties": {
    "iso:country":"US",
    "sg:address":"2040 Willis Ln",
    "sg:city":"Keller",
    "sg:classifiers":[
        {
            "category":"Organizations",
            "subcategory":"Religious Organization",
            "type":"Services"
        }
    ],
    "sg:phone":"+1 817 431 8525",
    "sg:postcode":"76248",
    "sg:province":"TX",
    "sg:tags":[
        "church"
    ],
    "sg:website":"www.covenantlove.org",
    "wof:name":"Covenant Love Christian Ctr",
    "wof:placetype":"venue"
},
  "geometry": {"coordinates":[-97.24723299999999,32.909588],"type":"Point"}
}