{
  "type": "Feature",
  "properties": {
    "iso:country":"US",
    "sg:address":"6328 Broadway St",
    "sg:city":"Galveston",
    "sg:classifiers":[
        {
            "category":"Manufacturing",
            "subcategory":"Rubber & Plastics",
            "type":"Manufacturing & Wholesale Goods"
        },
        {
            "category":"Autos & Motor Vehicles",
            "subcategory":"Auto Supplies",
            "type":"Retail Goods"
        },
        {
            "category":"Retail",
            "subcategory":"Auto Repair",
            "type":"Services"
        }
    ],
    "sg:phone":"+1 409 744 1966",
    "sg:postcode":"77551",
    "sg:province":"TX",
    "sg:tags":[
        "wheel",
        "tires-wholesale",
        "tire",
        "retread",
        "balancing",
        "wheels-aligning",
        "recap",
        "brake",
        "manufacturer"
    ],
    "sg:website":"http://www.ntb.com",
    "wof:name":"NTB - National Tire & Battery",
    "wof:placetype":"venue"
},
  "geometry": {"coordinates":[-94.841663,29.288788],"type":"Point"}
}