{
  "type": "Feature",
  "properties": {
    "iso:country":"US",
    "sg:address":"2075 Kuehler Ave",
    "sg:city":"New Braunfels",
    "sg:classifiers":[
        {
            "category":"Building & Trades",
            "subcategory":"Construction",
            "type":"Services"
        }
    ],
    "sg:phone":"+1 830 609 2783",
    "sg:postcode":"78130",
    "sg:province":"TX",
    "sg:tags":[
        "nonresidential"
    ],
    "wof:name":"Krueger Construction",
    "wof:placetype":"venue"
},
  "geometry": {"coordinates":[-98.10894,29.693957],"type":"Point"}
}