{
  "type": "Feature",
  "properties": {
    "iso:country":"US",
    "sg:address":"1923 Gessner Dr",
    "sg:city":"Houston",
    "sg:classifiers":[
        {
            "category":"Banks & Credit Unions",
            "subcategory":"Financial Services",
            "type":"Services"
        }
    ],
    "sg:phone":"+1 713 461 7627",
    "sg:postcode":"77080",
    "sg:province":"TX",
    "sg:tags":[
        "loan",
        "financing"
    ],
    "wof:name":"World Acceptance",
    "wof:placetype":"venue"
},
  "geometry": {"coordinates":[-95.54524499999999,29.80655],"type":"Point"}
}