{
  "type": "Feature",
  "properties": {
    "iso:country":"US",
    "sg:address":"1033 US Hwy 69",
    "sg:city":"Jacksonville",
    "sg:classifiers":[
        {
            "category":"Autos & Motor Vehicles",
            "subcategory":"Automobile Sales",
            "type":"Retail Goods"
        }
    ],
    "sg:phone":"+1 903 586 3511",
    "sg:postcode":"75766",
    "sg:province":"TX",
    "sg:tags":[
        "car",
        "dealer"
    ],
    "wof:name":"Bacon Auto Country Inc",
    "wof:placetype":"venue"
},
  "geometry": {"coordinates":[-95.27355799999999,31.979554],"type":"Point"}
}