{
  "type": "Feature",
  "properties": {
    "iso:country":"US",
    "sg:address":"13215 Golden Valley Dr",
    "sg:city":"Cypress",
    "sg:classifiers":[
        {
            "category":"Professional",
            "type":"Services"
        }
    ],
    "sg:phone":"+1 281 374 9406",
    "sg:postcode":"77429",
    "sg:province":"TX",
    "wof:name":"Enron Transportaion",
    "wof:placetype":"venue"
},
  "geometry": {"coordinates":[-95.627217,29.996722],"type":"Point"}
}