{
  "type": "Feature",
  "properties": {
    "iso:country":"US",
    "sg:address":"5622 Evers Rd",
    "sg:city":"San Antonio",
    "sg:classifiers":[
        {
            "category":"Shopping",
            "subcategory":"Gifts & Souvenirs",
            "type":"Retail Goods"
        }
    ],
    "sg:phone":"+1 210 521 1170",
    "sg:postcode":"78238",
    "sg:province":"TX",
    "wof:name":"A Card",
    "wof:placetype":"venue"
},
  "geometry": {"coordinates":[-98.597689,29.488505],"type":"Point"}
}