{
  "type": "Feature",
  "properties": {
    "iso:country":"US",
    "sg:address":"3625 Whatley Dr",
    "sg:city":"Deer Park",
    "sg:classifiers":[
        {
            "category":"Retail",
            "subcategory":"Repair Shop",
            "type":"Services"
        }
    ],
    "sg:phone":"+1 713 302 3624",
    "sg:postcode":"77536",
    "sg:province":"TX",
    "wof:name":"Khl Impact",
    "wof:placetype":"venue"
},
  "geometry": {"coordinates":[-95.13889,29.678353],"type":"Point"}
}