{
  "type": "Feature",
  "properties": {
    "iso:country":"US",
    "sg:address":"6070 Black Oak Ln",
    "sg:city":"Fort Worth",
    "sg:classifiers":[
        {
            "category":"Building & Trades",
            "subcategory":"Landscaping Services",
            "type":"Services"
        }
    ],
    "sg:phone":"+1 817 737 7132",
    "sg:postcode":"76114",
    "sg:province":"TX",
    "wof:name":"Arthur P Henderson",
    "wof:placetype":"venue"
},
  "geometry": {"coordinates":[-97.41207300000001,32.773096],"type":"Point"}
}