{
  "type": "Feature",
  "properties": {
    "iso:country":"US",
    "sg:address":"3855 W Bay Cir",
    "sg:city":"Dallas",
    "sg:classifiers":[
        {
            "category":"Professional",
            "subcategory":"Management & Consulting",
            "type":"Services"
        }
    ],
    "sg:phone":"+1 214 828 6221",
    "sg:postcode":"75214",
    "sg:province":"TX",
    "wof:name":"H&N Management Inc",
    "wof:placetype":"venue"
},
  "geometry": {"coordinates":[-96.73319100000001,32.833484],"type":"Point"}
}