{
  "type": "Feature",
  "properties": {
    "iso:country":"US",
    "sg:address":"821 Clark Trl",
    "sg:city":"Grand Prairie",
    "sg:classifiers":[
        {
            "category":"Freight",
            "type":"Transportation"
        }
    ],
    "sg:phone":"+1 972 660 6107",
    "sg:postcode":"75052",
    "sg:province":"TX",
    "sg:tags":[
        "special"
    ],
    "wof:name":"R B V LLC",
    "wof:placetype":"venue"
},
  "geometry": {"coordinates":[-97.015057,32.652162],"type":"Point"}
}