{
  "type": "Feature",
  "properties": {
    "iso:country":"US",
    "sg:address":"1216 Military Dr",
    "sg:city":"San Marcos",
    "sg:classifiers":[
        {
            "category":"Autos & Motor Vehicles",
            "subcategory":"Boat Sales",
            "type":"Retail Goods"
        }
    ],
    "sg:phone":"+1 512 353 1854",
    "sg:postcode":"78666",
    "sg:province":"TX",
    "sg:tags":[
        "dealer",
        "sales"
    ],
    "wof:name":"Outboard Shop",
    "wof:placetype":"venue"
},
  "geometry": {"coordinates":[-97.899005,29.875067],"type":"Point"}
}