{
  "type": "Feature",
  "properties": {
    "iso:country":"US",
    "sg:address":"5416 Plaza Dr",
    "sg:city":"Texarkana",
    "sg:classifiers":[
        {
            "category":"Professional",
            "subcategory":"Lawyer & Legal Services",
            "type":"Services"
        }
    ],
    "sg:phone":"+1 903 831 5610",
    "sg:postcode":"75503",
    "sg:province":"TX",
    "sg:tags":[
        "attorney",
        "practice"
    ],
    "wof:name":"Condit Peek & Young Attorneys At Law",
    "wof:placetype":"venue"
},
  "geometry": {"coordinates":[-94.070953,33.472184],"type":"Point"}
}