{
  "type": "Feature",
  "properties": {
    "iso:country":"US",
    "sg:address":"607 Baylor St",
    "sg:city":"Austin",
    "sg:classifiers":[
        {
            "category":"Utilities",
            "subcategory":"Cable",
            "type":"Services"
        }
    ],
    "sg:phone":"+1 512 694 8898",
    "sg:postcode":"78703",
    "sg:province":"TX",
    "sg:tags":[
        "cable-non-electric",
        "wire"
    ],
    "wof:name":"Complete Cabling Service",
    "wof:placetype":"venue"
},
  "geometry": {"coordinates":[-97.754929,30.271993],"type":"Point"}
}