{
  "type": "Feature",
  "properties": {
    "iso:country":"US",
    "sg:address":"11000 Richmond Ave",
    "sg:city":"Houston",
    "sg:classifiers":[
        {
            "category":"Professional",
            "subcategory":"Management & Consulting",
            "type":"Services"
        },
        {
            "category":"Professional",
            "subcategory":"Computer Services",
            "type":"Services"
        }
    ],
    "sg:phone":"+1 713 260 8888",
    "sg:postcode":"77042",
    "sg:province":"TX",
    "sg:tags":[
        "control",
        "consultant",
        "system",
        "access",
        "security",
        "software"
    ],
    "sg:website":"www.commandsystems.com",
    "wof:name":"Integrated Command Systems Inc",
    "wof:placetype":"venue"
},
  "geometry": {"coordinates":[-95.569401,29.727834],"type":"Point"}
}