{
  "type": "Feature",
  "properties": {
    "iso:country":"US",
    "sg:address":"15510 Seahorse Dr",
    "sg:city":"Houston",
    "sg:classifiers":[
        {
            "category":"Shopping",
            "type":"Retail Goods"
        }
    ],
    "sg:phone":"+1 281 286 8730",
    "sg:postcode":"77062",
    "sg:province":"TX",
    "sg:tags":[
        "plumbing",
        "merchandise"
    ],
    "wof:name":"Do It Yourself Plumbing",
    "wof:placetype":"venue"
},
  "geometry": {"coordinates":[-95.123226,29.576392],"type":"Point"}
}