{
  "type": "Feature",
  "properties": {
    "iso:country":"US",
    "sg:address":"10497 Town and Country Way",
    "sg:city":"Houston",
    "sg:classifiers":[
        {
            "category":"Building & Trades",
            "subcategory":"Construction",
            "type":"Services"
        }
    ],
    "sg:phone":"+1 713 932 1226",
    "sg:postcode":"77024",
    "sg:province":"TX",
    "sg:tags":[
        "home",
        "builder",
        "contractor"
    ],
    "wof:name":"Commonhouse Company",
    "wof:placetype":"venue"
},
  "geometry": {"coordinates":[-95.555246,29.781337],"type":"Point"}
}