{
  "type": "Feature",
  "properties": {
    "iso:country":"US",
    "sg:address":"120 S Denton Tap Rd",
    "sg:city":"Coppell",
    "sg:classifiers":[
        {
            "category":"Health Services",
            "subcategory":"Doctor",
            "type":"Services"
        }
    ],
    "sg:phone":"+1 972 393 5559",
    "sg:postcode":"75019",
    "sg:province":"TX",
    "sg:tags":[
        "medical"
    ],
    "wof:name":"Cahan Nina",
    "wof:placetype":"venue"
},
  "geometry": {"coordinates":[-96.99365299999999,32.967655],"type":"Point"}
}