{
  "type": "Feature",
  "properties": {
    "iso:country":"US",
    "sg:address":"3909 Shady Valley Dr",
    "sg:city":"Arlington",
    "sg:classifiers":[
        {
            "category":"Professional",
            "subcategory":"Management & Consulting",
            "type":"Services"
        }
    ],
    "sg:phone":"+1 817 861 0683",
    "sg:postcode":"76013",
    "sg:province":"TX",
    "sg:tags":[
        "consultant",
        "business"
    ],
    "wof:name":"International Business Dev",
    "wof:placetype":"venue"
},
  "geometry": {"coordinates":[-97.166027,32.715911],"type":"Point"}
}