{
  "type": "Feature",
  "properties": {
    "iso:country":"US",
    "sg:address":"14630 Cadillac Dr",
    "sg:city":"San Antonio",
    "sg:classifiers":[
        {
            "category":"Professional",
            "subcategory":"Testing Lab",
            "type":"Services"
        }
    ],
    "sg:phone":"+1 210 764 1973",
    "sg:postcode":"78248",
    "sg:province":"TX",
    "sg:tags":[
        "laboratory"
    ],
    "wof:name":"Elias Shaer",
    "wof:placetype":"venue"
},
  "geometry": {"coordinates":[-98.521659,29.578302],"type":"Point"}
}