{
  "type": "Feature",
  "properties": {
    "iso:country":"US",
    "sg:address":"301 Junction Hwy",
    "sg:city":"Kerrville",
    "sg:classifiers":[
        {
            "category":"Professional",
            "subcategory":"Advertising",
            "type":"Services"
        }
    ],
    "sg:phone":"+1 830 896 1300",
    "sg:postcode":"78028",
    "sg:province":"TX",
    "sg:tags":[
        "counselor",
        "agency"
    ],
    "sg:website":"www.briscoehall.com",
    "wof:name":"Briscoe Hall Inc",
    "wof:placetype":"venue"
},
  "geometry": {"coordinates":[-99.15131599999999,30.054517],"type":"Point"}
}