{
  "type": "Feature",
  "properties": {
    "iso:country":"US",
    "sg:address":"7341 W Vickery Blvd",
    "sg:city":"Benbrook",
    "sg:classifiers":[
        {
            "category":"Retail",
            "subcategory":"Auto Repair",
            "type":"Services"
        }
    ],
    "sg:phone":"+1 817 763 8115",
    "sg:postcode":"76116",
    "sg:province":"TX",
    "sg:tags":[
        "repairing",
        "automobile"
    ],
    "wof:name":"Automotive Performance",
    "wof:placetype":"venue"
},
  "geometry": {"coordinates":[-97.441779,32.698465],"type":"Point"}
}