{
  "type": "Feature",
  "properties": {
    "iso:country":"US",
    "sg:address":"10701 North Fwy",
    "sg:city":"Houston",
    "sg:classifiers":[
        {
            "category":"Shopping",
            "subcategory":"Mobile Phones",
            "type":"Retail Goods"
        }
    ],
    "sg:phone":"+1 281 591 6555",
    "sg:postcode":"77037",
    "sg:province":"TX",
    "sg:website":"www.wireless.att.com",
    "wof:name":"AT&T",
    "wof:placetype":"venue"
},
  "geometry": {"coordinates":[-95.412947,29.921033],"type":"Point"}
}