{
  "type": "Feature",
  "properties": {
    "iso:country":"US",
    "sg:address":"6901 Corporate Dr Ste 202",
    "sg:city":"Houston",
    "sg:classifiers":[
        {
            "category":"Health Services",
            "subcategory":"Doctor",
            "type":"Services"
        }
    ],
    "sg:phone":"+1 713 779 9281",
    "sg:postcode":"77036",
    "sg:province":"TX",
    "sg:tags":[
        "surgeon",
        "oral"
    ],
    "wof:name":"Satitpunwaycha Punnee DDS",
    "wof:placetype":"venue"
},
  "geometry": {"coordinates":[-95.551399,29.7047],"type":"Point"}
}