{
  "type": "Feature",
  "properties": {
    "iso:country":"US",
    "sg:address":"6816 Slide Rd",
    "sg:city":"Lubbock",
    "sg:classifiers":[
        {
            "category":"Freight",
            "type":"Transportation"
        }
    ],
    "sg:phone":"+1 806 798 3823",
    "sg:postcode":"79424",
    "sg:province":"TX",
    "sg:tags":[
        "arrangement"
    ],
    "wof:name":"Circle Air",
    "wof:placetype":"venue"
},
  "geometry": {"coordinates":[-101.922455,33.532546],"type":"Point"}
}