{
  "type": "Feature",
  "properties": {
    "iso:country":"US",
    "sg:address":"1616 Bassett Ave",
    "sg:city":"El Paso",
    "sg:classifiers":[
        {
            "category":"Wholesale",
            "subcategory":"Furniture",
            "type":"Manufacturing & Wholesale Goods"
        }
    ],
    "sg:phone":"+1 915 544 8710",
    "sg:postcode":"79901",
    "sg:province":"TX",
    "sg:tags":[
        "including",
        "metal"
    ],
    "wof:name":"BUSINESS PRODUCTS & SERVICES",
    "wof:placetype":"venue"
},
  "geometry": {"coordinates":[-106.470767,31.767012],"type":"Point"}
}