{
  "type": "Feature",
  "properties": {
    "iso:country":"US",
    "sg:address":"1631 Harold St",
    "sg:city":"Houston",
    "sg:classifiers":[
        {
            "category":"Professional",
            "subcategory":"Business Services",
            "type":"Services"
        }
    ],
    "sg:phone":"+1 713 524 5546",
    "sg:postcode":"77006",
    "sg:province":"TX",
    "wof:name":"Usatel Inc",
    "wof:placetype":"venue"
},
  "geometry": {"coordinates":[-95.40131599999999,29.741151],"type":"Point"}
}