{
  "type": "Feature",
  "properties": {
    "iso:country":"US",
    "sg:address":"510 N Lakeview Dr",
    "sg:city":"Huffman",
    "sg:classifiers":[
        {
            "category":"Shopping",
            "subcategory":"Hobbies, Toys, & Games",
            "type":"Retail Goods"
        }
    ],
    "sg:phone":"+1 281 360 7076",
    "sg:postcode":"77356",
    "sg:province":"TX",
    "wof:name":"Thamestitchery",
    "wof:placetype":"venue"
},
  "geometry": {"coordinates":[-95.69059,30.322747],"type":"Point"}
}