{
  "type": "Feature",
  "properties": {
    "iso:country":"US",
    "sg:address":"121 Circle Way St",
    "sg:city":"Lake Jackson",
    "sg:classifiers":[
        {
            "category":"Social Services",
            "subcategory":"Child Care",
            "type":"Services"
        }
    ],
    "sg:phone":"+1 979 297 8999",
    "sg:postcode":"77566",
    "sg:province":"TX",
    "sg:tags":[
        "day"
    ],
    "wof:name":"An Apple A Day Care",
    "wof:placetype":"venue"
},
  "geometry": {"coordinates":[-95.448644,29.038607],"type":"Point"}
}