{
  "type": "Feature",
  "properties": {
    "iso:country":"US",
    "sg:address":"4236 Centergate St",
    "sg:city":"San Antonio",
    "sg:classifiers":[
        {
            "category":"Professional",
            "subcategory":"Art Services",
            "type":"Services"
        }
    ],
    "sg:phone":"+1 210 572 4323",
    "sg:postcode":"78217",
    "sg:province":"TX",
    "sg:tags":[
        "photographer"
    ],
    "wof:name":"Bob Wickley",
    "wof:placetype":"venue"
},
  "geometry": {"coordinates":[-98.409299,29.52044],"type":"Point"}
}