{
  "type": "Feature",
  "properties": {
    "iso:country":"US",
    "sg:address":"10542 Sandpiper Ln",
    "sg:city":"Dallas",
    "sg:classifiers":[
        {
            "category":"Building & Trades",
            "subcategory":"Construction",
            "type":"Services"
        }
    ],
    "sg:phone":"+1 214 343 0037",
    "sg:postcode":"75230",
    "sg:province":"TX",
    "sg:tags":[
        "hanging",
        "contractor"
    ],
    "wof:name":"Ladd Painting Co",
    "wof:placetype":"venue"
},
  "geometry": {"coordinates":[-96.77900099999999,32.891451],"type":"Point"}
}