{
  "type": "Feature",
  "properties": {
    "iso:country":"US",
    "sg:address":"8816 Westheimer Rd",
    "sg:city":"Houston",
    "sg:classifiers":[
        {
            "category":"Restaurant",
            "type":"Food & Drink"
        }
    ],
    "sg:menulink":"http://www.allmenus.com/tx/houston/26160-landrys-seafood-house/menu/",
    "sg:phone":"+1 713 975 7873",
    "sg:postcode":"77063",
    "sg:province":"TX",
    "sg:tags":[
        "seafood",
        "american"
    ],
    "wof:name":"Landry's Seafood House",
    "wof:placetype":"venue"
},
  "geometry": {"coordinates":[-95.519986,29.737473],"type":"Point"}
}