{
  "type": "Feature",
  "properties": {
    "iso:country":"US",
    "sg:address":"131 Taylor St",
    "sg:city":"Keller",
    "sg:classifiers":[
        {
            "category":"Shopping",
            "subcategory":"Hobbies, Toys, & Games",
            "type":"Retail Goods"
        },
        {
            "category":"Shopping",
            "subcategory":"Crafts & Fabrics",
            "type":"Retail Goods"
        }
    ],
    "sg:phone":"+1 817 431 1234",
    "sg:postcode":"76248",
    "sg:province":"TX",
    "sg:tags":[
        "sewing",
        "art",
        "merchandise",
        "supply"
    ],
    "wof:name":"Keepin' U In Stitches",
    "wof:placetype":"venue"
},
  "geometry": {"coordinates":[-97.25269900000001,32.933697],"type":"Point"}
}