{
  "type": "Feature",
  "properties": {
    "iso:country":"US",
    "sg:address":"2513 Warfield St",
    "sg:city":"Fort Worth",
    "sg:classifiers":[
        {
            "category":"Wholesale",
            "subcategory":"Electrical",
            "type":"Manufacturing & Wholesale Goods"
        }
    ],
    "sg:phone":"+1 817 625 4213",
    "sg:postcode":"76106",
    "sg:province":"TX",
    "sg:tags":[
        "high",
        "pressure",
        "washer"
    ],
    "wof:name":"Delco Cleaning Systems",
    "wof:placetype":"venue"
},
  "geometry": {"coordinates":[-97.32355,32.792037],"type":"Point"}
}