{
  "type": "Feature",
  "properties": {
    "iso:country":"US",
    "sg:address":"4815 Rollingwood Dr",
    "sg:city":"West Lake Hills",
    "sg:classifiers":[
        {
            "category":"Sports & Exercise",
            "subcategory":"Gym",
            "type":"Entertainment"
        }
    ],
    "sg:phone":"+1 512 327 6373",
    "sg:postcode":"78746",
    "sg:province":"TX",
    "wof:name":"Western Hills Athletic Club",
    "wof:placetype":"venue"
},
  "geometry": {"coordinates":[-97.792768,30.273696],"type":"Point"}
}