{
  "type": "Feature",
  "properties": {
    "iso:country":"US",
    "sg:address":"6234 War Lodge",
    "sg:city":"San Antonio",
    "sg:classifiers":[
        {
            "category":"Wholesale",
            "subcategory":"Jewelry",
            "type":"Manufacturing & Wholesale Goods"
        }
    ],
    "sg:phone":"+1 210 523 2057",
    "sg:postcode":"78238",
    "sg:province":"TX",
    "sg:tags":[
        "stone"
    ],
    "wof:name":"Wonders of Nature",
    "wof:placetype":"venue"
},
  "geometry": {"coordinates":[-98.608542,29.470574],"type":"Point"}
}