{
  "type": "Feature",
  "properties": {
    "iso:country":"US",
    "sg:address":"6757 Arapaho Rd",
    "sg:city":"Dallas",
    "sg:classifiers":[
        {
            "category":"Building & Trades",
            "subcategory":"Cleaning & Sanitation",
            "type":"Services"
        }
    ],
    "sg:phone":"+1 972 991 4114",
    "sg:postcode":"75248",
    "sg:province":"TX",
    "sg:tags":[
        "maintenance"
    ],
    "wof:name":"Crown Hill Building Services",
    "wof:placetype":"venue"
},
  "geometry": {"coordinates":[-96.792644,32.962783],"type":"Point"}
}