{
  "type": "Feature",
  "properties": {
    "iso:country":"US",
    "sg:address":"101 S Adams St",
    "sg:city":"Fredericksburg",
    "sg:classifiers":[
        {
            "category":"Shopping",
            "subcategory":"Clothing, Apparel, & Fashions",
            "type":"Retail Goods"
        }
    ],
    "sg:phone":"+1 830 997 8869",
    "sg:postcode":"78624",
    "sg:province":"TX",
    "sg:tags":[
        "t"
    ],
    "wof:name":"T Shirts Etcetera",
    "wof:placetype":"venue"
},
  "geometry": {"coordinates":[-98.872282,30.275101],"type":"Point"}
}