{
  "type": "Feature",
  "properties": {
    "iso:country":"US",
    "sg:address":"18207 FM 1472",
    "sg:city":"Laredo",
    "sg:classifiers":[
        {
            "category":"Autos & Motor Vehicles",
            "subcategory":"Auto Supplies",
            "type":"Retail Goods"
        }
    ],
    "sg:phone":"+1 956 717 2779",
    "sg:postcode":"78045",
    "sg:province":"TX",
    "wof:name":"J B Truck Parts",
    "wof:placetype":"venue"
},
  "geometry": {"coordinates":[-99.553468,27.643499],"type":"Point"}
}