{
  "type": "Feature",
  "properties": {
    "iso:country":"US",
    "sg:address":"5217 McKinney Ave",
    "sg:city":"Dallas",
    "sg:classifiers":[
        {
            "category":"Professional",
            "subcategory":"Advertising",
            "type":"Services"
        }
    ],
    "sg:phone":"+1 214 528 7600",
    "sg:postcode":"75205",
    "sg:province":"TX",
    "sg:tags":[
        "counselor"
    ],
    "sg:website":"www.naudburnett.com",
    "wof:name":"Genesis West",
    "wof:placetype":"venue"
},
  "geometry": {"coordinates":[-96.78352,32.829502],"type":"Point"}
}