{
  "type": "Feature",
  "properties": {
    "iso:country":"US",
    "sg:address":"5308 Elm St",
    "sg:city":"Houston",
    "sg:classifiers":[
        {
            "category":"Manufacturing",
            "subcategory":"Printing",
            "type":"Manufacturing & Wholesale Goods"
        }
    ],
    "sg:phone":"+1 713 666 4269",
    "sg:postcode":"77081",
    "sg:province":"TX",
    "sg:tags":[
        "publisher",
        "guide"
    ],
    "wof:name":"Medical Productions",
    "wof:placetype":"venue"
},
  "geometry": {"coordinates":[-95.472505,29.712988],"type":"Point"}
}