{
  "type": "Feature",
  "properties": {
    "iso:country":"US",
    "sg:address":"4220 Bull Creek Road",
    "sg:city":"Austin",
    "sg:classifiers":[
        {
            "category":"Health Services",
            "subcategory":"Doctor",
            "type":"Services"
        }
    ],
    "sg:phone":"+1 512 617 7500",
    "sg:postcode":"78731",
    "sg:province":"TX",
    "sg:tags":[
        "surgeon",
        "cosmetic"
    ],
    "sg:website":"www.meridiansurgery.com/",
    "wof:name":"Meridian Plastic Surgery Center",
    "wof:placetype":"venue"
},
  "geometry": {"coordinates":[-97.754127,30.315646],"type":"Point"}
}