{
  "type": "Feature",
  "properties": {
    "iso:country":"US",
    "sg:address":"1201 W University Dr",
    "sg:city":"Edinburg",
    "sg:classifiers":[
        {
            "category":"Government",
            "subcategory":"Office",
            "type":"Public Place"
        }
    ],
    "sg:phone":"+1 956 316 2619",
    "sg:postcode":"78539",
    "sg:province":"TX",
    "sg:tags":[
        "development",
        "minority",
        "business",
        "national",
        "for",
        "program"
    ],
    "wof:name":"South Texas Mboc",
    "wof:placetype":"venue"
},
  "geometry": {"coordinates":[-98.177267,26.30364],"type":"Point"}
}