{
  "type": "Feature",
  "properties": {
    "iso:country":"US",
    "sg:address":"122 Collin Ct",
    "sg:city":"Prosper",
    "sg:classifiers":[
        {
            "category":"Local Transit",
            "type":"Transportation"
        }
    ],
    "sg:phone":"+1 972 562 4480",
    "sg:postcode":"75078",
    "sg:province":"TX",
    "sg:tags":[
        "passenger"
    ],
    "wof:name":"Atp Limousine",
    "wof:placetype":"venue"
},
  "geometry": {"coordinates":[-96.735608,33.26081],"type":"Point"}
}