{
  "type": "Feature",
  "properties": {
    "iso:country":"US",
    "sg:address":"6514 Banta Dr",
    "sg:city":"Missouri City",
    "sg:classifiers":[
        {
            "category":"Building & Trades",
            "subcategory":"Construction",
            "type":"Services"
        }
    ],
    "sg:phone":"+1 713 787 9636",
    "sg:postcode":"77489",
    "sg:province":"TX",
    "sg:tags":[
        "painter"
    ],
    "wof:name":"Cuff Painting & Wallpapering",
    "wof:placetype":"venue"
},
  "geometry": {"coordinates":[-95.48004400000001,29.597288],"type":"Point"}
}