{
  "type": "Feature",
  "properties": {
    "iso:country":"US",
    "sg:address":"6707 Cindy Ln",
    "sg:city":"Houston",
    "sg:classifiers":[
        {
            "category":"Shopping",
            "subcategory":"Computers & Home Electronics",
            "type":"Retail Goods"
        }
    ],
    "sg:phone":"+1 713 861 2860",
    "sg:postcode":"77008",
    "sg:province":"TX",
    "sg:tags":[
        "software"
    ],
    "wof:name":"Iobar Inc",
    "wof:placetype":"venue"
},
  "geometry": {"coordinates":[-95.43786900000001,29.795425],"type":"Point"}
}