{
  "type": "Feature",
  "properties": {
    "iso:country":"US",
    "sg:address":"34 Lakeway Dr",
    "sg:city":"Rockwall",
    "sg:classifiers":[
        {
            "category":"Professional",
            "subcategory":"Business Services",
            "type":"Services"
        }
    ],
    "sg:phone":"+1 972 771 0053",
    "sg:postcode":"75032",
    "sg:province":"TX",
    "wof:name":"National Safty Systems Inc",
    "wof:placetype":"venue"
},
  "geometry": {"coordinates":[-96.478493,32.873771],"type":"Point"}
}