{
  "type": "Feature",
  "properties": {
    "iso:country":"US",
    "sg:address":"4667 Montana Ave",
    "sg:city":"El Paso",
    "sg:classifiers":[
        {
            "category":"Shopping",
            "subcategory":"Jewelry",
            "type":"Retail Goods"
        }
    ],
    "sg:phone":"+1 915 566 9281",
    "sg:postcode":"79903",
    "sg:province":"TX",
    "sg:tags":[
        "jeweler"
    ],
    "wof:name":"Henry Marmolejo Custom Jeweler",
    "wof:placetype":"venue"
},
  "geometry": {"coordinates":[-106.433515,31.783834],"type":"Point"}
}