{
  "type": "Feature",
  "properties": {
    "iso:country":"US",
    "sg:address":"9304 Forest Ln",
    "sg:city":"Dallas",
    "sg:classifiers":[
        {
            "category":"Real Estate",
            "subcategory":"Real Estate Agent",
            "type":"Services"
        }
    ],
    "sg:phone":"+1 214 349 2099",
    "sg:postcode":"75243",
    "sg:province":"TX",
    "wof:name":"Bob Browning Jr",
    "wof:placetype":"venue"
},
  "geometry": {"coordinates":[-96.740981,32.909169],"type":"Point"}
}