{
  "type": "Feature",
  "properties": {
    "iso:country":"US",
    "sg:address":"1014 Arroya Vista Dr",
    "sg:city":"San Antonio",
    "sg:classifiers":[
        {
            "category":"Real Estate",
            "subcategory":"Real Estate Operator",
            "type":"Services"
        }
    ],
    "sg:phone":"+1 210 366 3645",
    "sg:postcode":"78213",
    "sg:province":"TX",
    "sg:tags":[
        "building",
        "nonresidential"
    ],
    "wof:name":"Cerram Properties",
    "wof:placetype":"venue"
},
  "geometry": {"coordinates":[-98.51132,29.501643],"type":"Point"}
}