{
  "type": "Feature",
  "properties": {
    "iso:country":"US",
    "sg:address":"5350 W Highway 290",
    "sg:city":"Austin",
    "sg:classifiers":[
        {
            "category":"Autos & Motor Vehicles",
            "subcategory":"Automobile Sales",
            "type":"Retail Goods"
        }
    ],
    "sg:phone":"+1 512 892 2277",
    "sg:postcode":"78735",
    "sg:province":"TX",
    "sg:tags":[
        "dealers-used",
        "car",
        "used",
        "cars-wholesale",
        "new"
    ],
    "wof:name":"Qsi Auto Sales",
    "wof:placetype":"venue"
},
  "geometry": {"coordinates":[-97.838415,30.237087],"type":"Point"}
}