{
  "type": "Feature",
  "properties": {
    "iso:country":"US",
    "sg:address":"750 Duck Creek Way",
    "sg:city":"Mesquite",
    "sg:classifiers":[
        {
            "category":"Government",
            "subcategory":"Office",
            "type":"Public Place"
        }
    ],
    "sg:phone":"+1 972 203 4300",
    "sg:postcode":"75182",
    "sg:province":"TX",
    "sg:tags":[
        "village"
    ],
    "wof:name":"City Of Garland Duck Creek",
    "wof:placetype":"venue"
},
  "geometry": {"coordinates":[-96.535062,32.798552],"type":"Point"}
}