{
  "type": "Feature",
  "properties": {
    "iso:country":"US",
    "sg:address":"120 E Virginia St",
    "sg:city":"Mc Kinney",
    "sg:classifiers":[
        {
            "category":"Insurance",
            "subcategory":"Insurance Agent",
            "type":"Services"
        }
    ],
    "sg:phone":"+1 214 544 3438",
    "sg:postcode":"75069",
    "sg:province":"TX",
    "wof:name":"Mc Kinney Office & Retail",
    "wof:placetype":"venue"
},
  "geometry": {"coordinates":[-96.61572,33.197892],"type":"Point"}
}