{
  "type": "Feature",
  "properties": {
    "iso:country":"US",
    "sg:address":"9705 Burnet Rd",
    "sg:city":"Austin",
    "sg:classifiers":[
        {
            "category":"Insurance",
            "subcategory":"Insurance Agent",
            "type":"Services"
        }
    ],
    "sg:phone":"+1 512 339 1515",
    "sg:postcode":"78758",
    "sg:province":"TX",
    "wof:name":"Austin Insurance Group",
    "wof:placetype":"venue"
},
  "geometry": {"coordinates":[-97.72449400000001,30.38122],"type":"Point"}
}