{
  "type": "Feature",
  "properties": {
    "iso:country":"US",
    "sg:address":"520 Evergreen Dr",
    "sg:city":"Hurst",
    "sg:classifiers":[
        {
            "category":"Professional",
            "subcategory":"Business Services",
            "type":"Services"
        }
    ],
    "sg:phone":"+1 817 656 2287",
    "sg:postcode":"76054",
    "sg:province":"TX",
    "wof:name":"Levy & Assoc",
    "wof:placetype":"venue"
},
  "geometry": {"coordinates":[-97.17659399999999,32.875401],"type":"Point"}
}