{
  "type": "Feature",
  "properties": {
    "iso:country":"US",
    "sg:address":"13656 Victory Ln",
    "sg:city":"Tyler",
    "sg:classifiers":[
        {
            "category":"Restaurant",
            "type":"Food & Drink"
        }
    ],
    "sg:phone":"+1 903 581 2917",
    "sg:postcode":"75703",
    "sg:province":"TX",
    "wof:name":"Max Zea",
    "wof:placetype":"venue"
},
  "geometry": {"coordinates":[-95.39643700000001,32.240258],"type":"Point"}
}