{
  "type": "Feature",
  "properties": {
    "iso:country":"US",
    "sg:address":"903 S Main St",
    "sg:city":"Weatherford",
    "sg:classifiers":[
        {
            "category":"Shopping",
            "type":"Retail Goods"
        }
    ],
    "sg:phone":"+1 817 937 7708",
    "sg:postcode":"76086",
    "sg:province":"TX",
    "sg:tags":[
        "merchandise"
    ],
    "wof:name":"Spy Unlimited",
    "wof:placetype":"venue"
},
  "geometry": {"coordinates":[-97.797411,32.74994],"type":"Point"}
}