{
  "type": "Feature",
  "properties": {
    "iso:country":"US",
    "sg:address":"525 Surf St",
    "sg:city":"Lewisville",
    "sg:classifiers":[
        {
            "category":"Restaurant",
            "type":"Food & Drink"
        }
    ],
    "sg:menulink":"http://www.allmenus.com/tx/lewisville/104261-taco-cabana/menu/",
    "sg:phone":"+1 972 353 5575",
    "sg:postcode":"75067",
    "sg:province":"TX",
    "sg:tags":[
        "mexican"
    ],
    "wof:name":"Taco Cabana",
    "wof:placetype":"venue"
},
  "geometry": {"coordinates":[-97.01367500000001,33.044509],"type":"Point"}
}