{
  "type": "Feature",
  "properties": {
    "iso:country":"US",
    "sg:address":"120 Magnolia Trl",
    "sg:city":"Lumberton",
    "sg:classifiers":[
        {
            "category":"Wholesale",
            "subcategory":"Non-durable Goods",
            "type":"Manufacturing & Wholesale Goods"
        }
    ],
    "sg:phone":"+1 409 839 0255",
    "sg:postcode":"77657",
    "sg:province":"TX",
    "wof:name":"L A S Promotions",
    "wof:placetype":"venue"
},
  "geometry": {"coordinates":[-94.19645,30.282909],"type":"Point"}
}