{
  "type": "Feature",
  "properties": {
    "iso:country":"US",
    "sg:address":"323 NW 24th St",
    "sg:city":"San Antonio",
    "sg:classifiers":[
        {
            "category":"Health Services",
            "subcategory":"Doctor",
            "type":"Services"
        }
    ],
    "sg:phone":"+1 210 434 4321",
    "sg:postcode":"78207",
    "sg:province":"TX",
    "sg:tags":[
        "osteopathic"
    ],
    "wof:name":"Richard J Tamez Do",
    "wof:placetype":"venue"
},
  "geometry": {"coordinates":[-98.542312,29.432183],"type":"Point"}
}