{
  "type": "Feature",
  "properties": {
    "iso:country":"US",
    "sg:address":"10111 Pemcrest",
    "sg:city":"San Antonio",
    "sg:classifiers":[
        {
            "category":"Manufacturing",
            "subcategory":"Tools & Machinery",
            "type":"Manufacturing & Wholesale Goods"
        }
    ],
    "sg:phone":"+1 210 690 1016",
    "sg:postcode":"78240",
    "sg:province":"TX",
    "sg:tags":[
        "feeding",
        "handling",
        "raising",
        "cattle"
    ],
    "wof:name":"El Patron Ranch",
    "wof:placetype":"venue"
},
  "geometry": {"coordinates":[-98.616724,29.534735],"type":"Point"}
}