{
  "type": "Feature",
  "properties": {
    "iso:country":"US",
    "sg:address":"1201 E 10th Ave",
    "sg:city":"Amarillo",
    "sg:classifiers":[
        {
            "category":"Professional",
            "subcategory":"Accounting & Tax Preparation",
            "type":"Services"
        }
    ],
    "sg:phone":"+1 806 373 1040",
    "sg:postcode":"79102",
    "sg:province":"TX",
    "sg:tags":[
        "return",
        "filing"
    ],
    "wof:name":"Action Services",
    "wof:placetype":"venue"
},
  "geometry": {"coordinates":[-101.82271,35.20156],"type":"Point"}
}