{
  "type": "Feature",
  "properties": {
    "iso:country":"US",
    "sg:address":"1170 Bayou Ct",
    "sg:city":"Brownsville",
    "sg:classifiers":[
        {
            "category":"Autos & Motor Vehicles",
            "subcategory":"Boat Sales",
            "type":"Retail Goods"
        },
        {
            "category":"Marine",
            "type":"Transportation"
        }
    ],
    "sg:phone":"+1 956 831 7828",
    "sg:postcode":"78521",
    "sg:province":"TX",
    "sg:tags":[
        "equipment",
        "repair",
        "maintenance",
        "supply"
    ],
    "wof:name":"Zimco Marine, Inc",
    "wof:placetype":"venue"
},
  "geometry": {"coordinates":[-97.341362,25.976515],"type":"Point"}
}