{
  "type": "Feature",
  "properties": {
    "iso:country":"US",
    "sg:address":"509 Allison Ln",
    "sg:city":"Fort Worth",
    "sg:classifiers":[
        {
            "category":"Shopping",
            "subcategory":"Gifts & Souvenirs",
            "type":"Retail Goods"
        }
    ],
    "sg:phone":"+1 817 568 9923",
    "sg:postcode":"76140",
    "sg:province":"TX",
    "wof:name":"S&K Gift World",
    "wof:placetype":"venue"
},
  "geometry": {"coordinates":[-97.276095,32.626614],"type":"Point"}
}