{
  "type": "Feature",
  "properties": {
    "iso:country":"US",
    "sg:address":"114 Regency Dr",
    "sg:city":"Wylie",
    "sg:classifiers":[
        {
            "category":"Wholesale",
            "subcategory":"Home Furnishings",
            "type":"Manufacturing & Wholesale Goods"
        }
    ],
    "sg:phone":"+1 972 442 4357",
    "sg:postcode":"75098",
    "sg:province":"TX",
    "sg:tags":[
        "picture",
        "frame"
    ],
    "wof:name":"Bowon USA",
    "wof:placetype":"venue"
},
  "geometry": {"coordinates":[-96.585804,33.006853],"type":"Point"}
}