{
  "type": "Feature",
  "properties": {
    "iso:country":"US",
    "sg:address":"1900 5th Ave N",
    "sg:city":"Texas City",
    "sg:classifiers":[
        {
            "category":"Sports & Exercise",
            "subcategory":"Gym",
            "type":"Entertainment"
        }
    ],
    "sg:phone":"+1 409 643 5984",
    "sg:postcode":"77590",
    "sg:province":"TX",
    "sg:tags":[
        "club",
        "health",
        "studio",
        "gymnasium"
    ],
    "wof:name":"Lowry Physical Fitness Ctr",
    "wof:placetype":"venue"
},
  "geometry": {"coordinates":[-94.92349900000001,29.389215],"type":"Point"}
}