{
  "type": "Feature",
  "properties": {
    "iso:country":"US",
    "sg:address":"8140 E Houston Rd",
    "sg:city":"Houston",
    "sg:classifiers":[
        {
            "category":"Organizations",
            "subcategory":"Religious Organization",
            "type":"Services"
        }
    ],
    "sg:phone":"+1 713 631 0724",
    "sg:postcode":"77028",
    "sg:province":"TX",
    "sg:tags":[
        "church"
    ],
    "wof:name":"Iglesia De Dios",
    "wof:placetype":"venue"
},
  "geometry": {"coordinates":[-95.265502,29.836512],"type":"Point"}
}