{
  "type": "Feature",
  "properties": {
    "iso:country":"US",
    "sg:address":"110 Exposition Ave",
    "sg:city":"Dallas",
    "sg:classifiers":[
        {
            "category":"Professional",
            "subcategory":"Business Services",
            "type":"Services"
        }
    ],
    "sg:phone":"+1 214 821 6482",
    "sg:postcode":"75226",
    "sg:province":"TX",
    "sg:tags":[
        "decoration",
        "singing",
        "for",
        "special",
        "event"
    ],
    "wof:name":"Balloon City",
    "wof:placetype":"venue"
},
  "geometry": {"coordinates":[-96.77434700000001,32.785183],"type":"Point"}
}