{
  "type": "Feature",
  "properties": {
    "iso:country":"US",
    "sg:address":"7304 SW 34th Ave",
    "sg:city":"Amarillo",
    "sg:classifiers":[
        {
            "category":"Personal",
            "subcategory":"Nail Salon",
            "type":"Services"
        }
    ],
    "sg:phone":"+1 806 356 8752",
    "sg:postcode":"79121",
    "sg:province":"TX",
    "wof:name":"Ruby Nail I",
    "wof:placetype":"venue"
},
  "geometry": {"coordinates":[-101.92037000000001,35.176522],"type":"Point"}
}