{
  "type": "Feature",
  "properties": {
    "iso:country":"US",
    "sg:address":"6757 Arapaho Rd",
    "sg:city":"Dallas",
    "sg:classifiers":[
        {
            "category":"Professional",
            "subcategory":"Management & Consulting",
            "type":"Services"
        }
    ],
    "sg:phone":"+1 972 931 8422",
    "sg:postcode":"75248",
    "sg:province":"TX",
    "sg:tags":[
        "business"
    ],
    "wof:name":"Wayne C Hibbs Assoc",
    "wof:placetype":"venue"
},
  "geometry": {"coordinates":[-96.792644,32.962783],"type":"Point"}
}