{
  "type": "Feature",
  "properties": {
    "iso:country":"US",
    "sg:address":"15049 Valley Vw",
    "sg:city":"Forney",
    "sg:classifiers":[
        {
            "category":"Wholesale",
            "subcategory":"Machinery & Supplies",
            "type":"Manufacturing & Wholesale Goods"
        }
    ],
    "sg:phone":"+1 972 564 2503",
    "sg:postcode":"75126",
    "sg:province":"TX",
    "sg:tags":[
        "automobile",
        "rebuilt",
        "part",
        "supplies-used"
    ],
    "wof:name":"ReBuilders Specialities",
    "wof:placetype":"venue"
},
  "geometry": {"coordinates":[-96.450861,32.777425],"type":"Point"}
}