{
  "type": "Feature",
  "properties": {
    "iso:country":"US",
    "sg:address":"5005 Nacahuita Ln",
    "sg:city":"Brownsville",
    "sg:classifiers":[
        {
            "category":"Health Services",
            "subcategory":"Chiropractor",
            "type":"Services"
        }
    ],
    "sg:phone":"+1 956 440 8050",
    "sg:postcode":"78552",
    "sg:province":"TX",
    "wof:name":"Jemson Corp",
    "wof:placetype":"venue"
},
  "geometry": {"coordinates":[-97.753567,26.216032],"type":"Point"}
}