{
  "type": "Feature",
  "properties": {
    "iso:country":"US",
    "sg:address":"300 E Georgia Pacific Dr",
    "sg:city":"Daingerfield",
    "sg:classifiers":[
        {
            "category":"Personal",
            "subcategory":"Beauty Salon",
            "type":"Services"
        }
    ],
    "sg:phone":"+1 903 645 4809",
    "sg:postcode":"75638",
    "sg:province":"TX",
    "wof:name":"Purr-Fect Hair",
    "wof:placetype":"venue"
},
  "geometry": {"coordinates":[-94.71755400000001,33.03944],"type":"Point"}
}