{
  "type": "Feature",
  "properties": {
    "iso:country":"US",
    "sg:address":"6801 Patrick Ln",
    "sg:city":"Plano",
    "sg:classifiers":[
        {
            "category":"Professional",
            "subcategory":"Management & Consulting",
            "type":"Services"
        }
    ],
    "sg:phone":"+1 972 491 1471",
    "sg:postcode":"75024",
    "sg:province":"TX",
    "sg:tags":[
        "business"
    ],
    "wof:name":"Brent Bnton Assoc Cnslting LLC",
    "wof:placetype":"venue"
},
  "geometry": {"coordinates":[-96.784335,33.065245],"type":"Point"}
}