{
  "type": "Feature",
  "properties": {
    "iso:country":"US",
    "sg:address":"116 E Ellison St Ste A",
    "sg:city":"Burleson",
    "sg:classifiers":[
        {
            "category":"Personal",
            "subcategory":"Nail Salon",
            "type":"Services"
        }
    ],
    "sg:phone":"+1 817 447 0808",
    "sg:postcode":"76028",
    "sg:province":"TX",
    "wof:name":"Elan Hair and Nail Design",
    "wof:placetype":"venue"
},
  "geometry": {"coordinates":[-97.319397,32.542021],"type":"Point"}
}