{
  "type": "Feature",
  "properties": {
    "iso:country":"US",
    "sg:address":"943 E 10th St",
    "sg:city":"Brownsville",
    "sg:classifiers":[
        {
            "category":"Bars & Pubs",
            "type":"Food & Drink"
        }
    ],
    "sg:phone":"+1 956 542 1105",
    "sg:postcode":"78520",
    "sg:province":"TX",
    "sg:tags":[
        "club",
        "drinking",
        "night"
    ],
    "wof:name":"Southwinds Lounge",
    "wof:placetype":"venue"
},
  "geometry": {"coordinates":[-97.496364,25.905296],"type":"Point"}
}