{
  "type": "Feature",
  "properties": {
    "iso:country":"US",
    "sg:address":"2479 Deer Run",
    "sg:city":"Lewisville",
    "sg:classifiers":[
        {
            "category":"Food & Beverages",
            "subcategory":"Candy",
            "type":"Retail Goods"
        }
    ],
    "sg:phone":"+1 469 671 1063",
    "sg:postcode":"75067",
    "sg:province":"TX",
    "sg:tags":[
        "confectionery"
    ],
    "wof:name":"Cajun Country Candies",
    "wof:placetype":"venue"
},
  "geometry": {"coordinates":[-96.99786400000001,33.005219],"type":"Point"}
}