{
  "type": "Feature",
  "properties": {
    "iso:country":"US",
    "sg:address":"6034 W Courtyard Dr",
    "sg:city":"Austin",
    "sg:classifiers":[
        {
            "category":"Professional",
            "type":"Services"
        }
    ],
    "sg:phone":"+1 512 338 2124",
    "sg:postcode":"78730",
    "sg:province":"TX",
    "sg:tags":[
        "establishment"
    ],
    "wof:name":"Austin Vehicle Express",
    "wof:placetype":"venue"
},
  "geometry": {"coordinates":[-97.797562,30.354328],"type":"Point"}
}