{
  "type": "Feature",
  "properties": {
    "iso:country":"US",
    "sg:address":"4130 Sherwood Way",
    "sg:city":"San Angelo",
    "sg:classifiers":[
        {
            "category":"Building & Trades",
            "subcategory":"Plumbing",
            "type":"Services"
        }
    ],
    "sg:phone":"+1 325 947 3690",
    "sg:postcode":"76901",
    "sg:province":"TX",
    "sg:tags":[
        "system",
        "heating",
        "air",
        "conditioning",
        "contractor",
        "condition"
    ],
    "wof:name":"Huffman Heating & Air Cond",
    "wof:placetype":"venue"
},
  "geometry": {"coordinates":[-100.489351,31.440342],"type":"Point"}
}