{
  "type": "Feature",
  "properties": {
    "iso:country":"US",
    "sg:address":"1804 Chico Hwy",
    "sg:city":"Bridgeport",
    "sg:classifiers":[
        {
            "category":"Health Services",
            "subcategory":"Clinic",
            "type":"Services"
        },
        {
            "category":"Health Services",
            "subcategory":"Nursing And Care Facility",
            "type":"Services"
        },
        {
            "category":"Health Services",
            "subcategory":"Health Practitioner",
            "type":"Services"
        }
    ],
    "sg:phone":"+1 940 683 3300",
    "sg:postcode":"76426",
    "sg:province":"TX",
    "sg:tags":[
        "home",
        "eldercare-home",
        "welfare"
    ],
    "wof:name":"North Central Texas Hm. Health",
    "wof:placetype":"venue"
},
  "geometry": {"coordinates":[-97.76728,33.215312],"type":"Point"}
}