{
  "type": "Feature",
  "properties": {
    "iso:country":"US",
    "sg:address":"5226 I- 37",
    "sg:city":"Corpus Christi",
    "sg:classifiers":[
        {
            "category":"Home & Garden",
            "subcategory":"Garden Supply",
            "type":"Retail Goods"
        }
    ],
    "sg:phone":"+1 361 884 8275",
    "sg:postcode":"78407",
    "sg:province":"TX",
    "sg:tags":[
        "engine"
    ],
    "wof:name":"Waukesha-Pearce Industries Inc",
    "wof:placetype":"venue"
},
  "geometry": {"coordinates":[-97.45391100000001,27.804395],"type":"Point"}
}