{
  "type": "Feature",
  "properties": {
    "iso:country":"US",
    "sg:address":"609 Mossycup Oak Dr",
    "sg:city":"Plano",
    "sg:classifiers":[
        {
            "category":"Shopping",
            "subcategory":"Clothing, Apparel, & Fashions",
            "type":"Retail Goods"
        }
    ],
    "sg:phone":"+1 972 517 8049",
    "sg:postcode":"75025",
    "sg:province":"TX",
    "sg:tags":[
        "mfg"
    ],
    "wof:name":"Three Blind Mice",
    "wof:placetype":"venue"
},
  "geometry": {"coordinates":[-96.69838799999999,33.079094],"type":"Point"}
}