{
  "type": "Feature",
  "properties": {
    "iso:country":"US",
    "sg:address":"6006 Bihia Forest Dr",
    "sg:city":"Houston",
    "sg:classifiers":[
        {
            "category":"Real Estate",
            "subcategory":"Real Estate Agent",
            "type":"Services"
        }
    ],
    "sg:phone":"+1 281 931 4189",
    "sg:postcode":"77088",
    "sg:province":"TX",
    "wof:name":"Inwood Realty",
    "wof:placetype":"venue"
},
  "geometry": {"coordinates":[-95.47862499999999,29.88803],"type":"Point"}
}