{
  "type": "Feature",
  "properties": {
    "iso:country":"US",
    "sg:address":"201 2nd St",
    "sg:city":"Sealy",
    "sg:classifiers":[
        {
            "category":"Government",
            "subcategory":"Police Station",
            "type":"Public Place"
        }
    ],
    "sg:phone":"+1 979 885 2913",
    "sg:postcode":"77474",
    "sg:province":"TX",
    "sg:tags":[
        "protection"
    ],
    "wof:name":"Police Department",
    "wof:placetype":"venue"
},
  "geometry": {"coordinates":[-96.152674,29.782886],"type":"Point"}
}