{
  "type": "Feature",
  "properties": {
    "iso:country":"US",
    "sg:address":"6161 Savoy Dr",
    "sg:city":"Houston",
    "sg:classifiers":[
        {
            "category":"Real Estate",
            "subcategory":"Real Estate Services",
            "type":"Services"
        },
        {
            "category":"Real Estate",
            "subcategory":"Real Estate Agent",
            "type":"Services"
        }
    ],
    "sg:phone":"+1 713 952 5066",
    "sg:postcode":"77036",
    "sg:province":"TX",
    "sg:tags":[
        "buyer",
        "broker"
    ],
    "wof:name":"Ryland Enterprise",
    "wof:placetype":"venue"
},
  "geometry": {"coordinates":[-95.504454,29.715829],"type":"Point"}
}