{
  "type": "Feature",
  "properties": {
    "iso:country":"US",
    "sg:address":"3925 Fredericksburg Rd",
    "sg:city":"San Antonio",
    "sg:classifiers":[
        {
            "category":"Insurance",
            "subcategory":"Insurance Agent",
            "type":"Services"
        }
    ],
    "sg:phone":"+1 210 732 2874",
    "sg:postcode":"78201",
    "sg:province":"TX",
    "wof:name":"Michael Cicherski",
    "wof:placetype":"venue"
},
  "geometry": {"coordinates":[-98.544158,29.482311],"type":"Point"}
}