{
  "type": "Feature",
  "properties": {
    "iso:country":"US",
    "sg:address":"2150 N Josey Ln Ste 104",
    "sg:city":"Carrollton",
    "sg:classifiers":[
        {
            "category":"Personal",
            "subcategory":"Nail Salon",
            "type":"Services"
        }
    ],
    "sg:phone":"+1 972 446 2279",
    "sg:postcode":"75006",
    "sg:province":"TX",
    "wof:name":"Nail Time",
    "wof:placetype":"venue"
},
  "geometry": {"coordinates":[-96.8899,32.976299],"type":"Point"}
}