{
  "type": "Feature",
  "properties": {
    "iso:country":"US",
    "sg:address":"145 Moss Rose St",
    "sg:city":"Boerne",
    "sg:classifiers":[
        {
            "category":"Restaurant",
            "type":"Food & Drink"
        }
    ],
    "sg:phone":"+1 830 249 1030",
    "sg:postcode":"78006",
    "sg:province":"TX",
    "sg:tags":[
        "eating"
    ],
    "wof:name":"Old Macdonalds Collectib",
    "wof:placetype":"venue"
},
  "geometry": {"coordinates":[-98.716222,29.794489],"type":"Point"}
}