{
  "type": "Feature",
  "properties": {
    "iso:country":"US",
    "sg:address":"405 Irma Dr",
    "sg:city":"Austin",
    "sg:classifiers":[
        {
            "category":"Personal",
            "subcategory":"Barber",
            "type":"Services"
        }
    ],
    "sg:phone":"+1 512 453 3660",
    "sg:postcode":"78752",
    "sg:province":"TX",
    "sg:tags":[
        "shop"
    ],
    "wof:name":"Gaitans Barber Shop",
    "wof:placetype":"venue"
},
  "geometry": {"coordinates":[-97.718468,30.330765],"type":"Point"}
}