{
  "type": "Feature",
  "properties": {
    "iso:country":"US",
    "sg:address":"4004 Sam Houston Ave",
    "sg:city":"Huntsville",
    "sg:classifiers":[
        {
            "category":"Personal",
            "subcategory":"Beauty Salon",
            "type":"Services"
        }
    ],
    "sg:phone":"+1 936 291 3737",
    "sg:postcode":"77340",
    "sg:province":"TX",
    "sg:tags":[
        "hair"
    ],
    "wof:name":"Studio 2000",
    "wof:placetype":"venue"
},
  "geometry": {"coordinates":[-95.550132,30.707956],"type":"Point"}
}