{
  "type": "Feature",
  "properties": {
    "iso:country":"US",
    "sg:address":"5608 Plumtree Dr",
    "sg:city":"Dallas",
    "sg:classifiers":[
        {
            "category":"Professional",
            "subcategory":"Management & Consulting",
            "type":"Services"
        }
    ],
    "sg:phone":"+1 972 931 7622",
    "sg:postcode":"75252",
    "sg:province":"TX",
    "wof:name":"Kempgirls Family Partnersh",
    "wof:placetype":"venue"
},
  "geometry": {"coordinates":[-96.807526,32.995554],"type":"Point"}
}