{
  "type": "Feature",
  "properties": {
    "iso:country":"US",
    "sg:address":"11726 Crumpton Dr",
    "sg:city":"Mesquite",
    "sg:classifiers":[
        {
            "category":"Freight",
            "type":"Transportation"
        }
    ],
    "sg:phone":"+1 972 286 0718",
    "sg:postcode":"75180",
    "sg:province":"TX",
    "sg:tags":[
        "operator",
        "local",
        "trucking"
    ],
    "wof:name":"Delivery Specialist",
    "wof:placetype":"venue"
},
  "geometry": {"coordinates":[-96.623007,32.731746],"type":"Point"}
}