{
  "type": "Feature",
  "properties": {
    "iso:country":"US",
    "sg:address":"803 Apollo Dr",
    "sg:city":"Edna",
    "sg:classifiers":[
        {
            "category":"Professional",
            "type":"Services"
        }
    ],
    "sg:phone":"+1 361 782 8801",
    "sg:postcode":"77957",
    "sg:province":"TX",
    "wof:name":"Country Designs",
    "wof:placetype":"venue"
},
  "geometry": {"coordinates":[-96.650216,28.960388],"type":"Point"}
}