{
  "type": "Feature",
  "properties": {
    "iso:country":"US",
    "sg:address":"119 Senator St",
    "sg:city":"Texarkana",
    "sg:classifiers":[
        {
            "category":"Retail",
            "subcategory":"Auto Repair",
            "type":"Services"
        }
    ],
    "sg:phone":"+1 870 772 5674",
    "sg:postcode":"71854",
    "sg:province":"TX",
    "sg:tags":[
        "wrecker"
    ],
    "wof:name":"J & L Wrecker Svc",
    "wof:placetype":"venue"
},
  "geometry": {"coordinates":[-94.031668,33.428845],"type":"Point"}
}