{
  "type": "Feature",
  "properties": {
    "iso:country":"US",
    "sg:address":"Plaza 183 Shopping Center 13450 Research Blvd, Ste. 237B",
    "sg:city":"Austin",
    "sg:classifiers":[
        {
            "category":"Building & Trades",
            "subcategory":"Plumbing",
            "type":"Services"
        }
    ],
    "sg:phone":"+1 512 836 7200",
    "sg:postcode":"78750",
    "sg:province":"TX",
    "sg:website":"www.rebathoftraviscounty.com",
    "wof:name":"ReBath of Travis County",
    "wof:placetype":"venue"
},
  "geometry": {"coordinates":[-97.79065,30.447725],"type":"Point"}
}