{
  "type": "Feature",
  "properties": {
    "iso:country":"US",
    "sg:address":"4936 Overton Ridge Blvd",
    "sg:city":"Fort Worth",
    "sg:classifiers":[
        {
            "category":"Banks & Credit Unions",
            "subcategory":"Investment Brokerage",
            "type":"Services"
        }
    ],
    "sg:phone":"+1 817 346 8354",
    "sg:postcode":"76132",
    "sg:province":"TX",
    "sg:tags":[
        "stock",
        "bond"
    ],
    "wof:name":"Edward Jones Co",
    "wof:placetype":"venue"
},
  "geometry": {"coordinates":[-97.402226,32.676554],"type":"Point"}
}