{
  "type": "Feature",
  "properties": {
    "iso:country":"US",
    "sg:address":"328 Ripplewood Dr",
    "sg:city":"Mesquite",
    "sg:classifiers":[
        {
            "category":"Professional",
            "type":"Services"
        }
    ],
    "sg:phone":"+1 817 490 1126",
    "sg:postcode":"75150",
    "sg:province":"TX",
    "wof:name":"Portraits N' Things",
    "wof:placetype":"venue"
},
  "geometry": {"coordinates":[-96.599857,32.795298],"type":"Point"}
}