{
  "type": "Feature",
  "properties": {
    "iso:country":"US",
    "sg:address":"3200 Wilcrest Dr",
    "sg:city":"Houston",
    "sg:classifiers":[
        {
            "category":"Professional",
            "subcategory":"Employment Agencies",
            "type":"Services"
        }
    ],
    "sg:phone":"+1 713 975 7277",
    "sg:postcode":"77042",
    "sg:province":"TX",
    "sg:tags":[
        "opportunity"
    ],
    "wof:name":"Lofton Staffing Svc",
    "wof:placetype":"venue"
},
  "geometry": {"coordinates":[-95.57173,29.729019],"type":"Point"}
}