{
  "type": "Feature",
  "properties": {
    "iso:country":"US",
    "sg:address":"6800 W Gate Blvd",
    "sg:city":"Austin",
    "sg:classifiers":[
        {
            "category":"Restaurant",
            "type":"Food & Drink"
        }
    ],
    "sg:phone":"+1 512 416 9888",
    "sg:postcode":"78745",
    "sg:province":"TX",
    "wof:name":"C J Wong Restaurant",
    "wof:placetype":"venue"
},
  "geometry": {"coordinates":[-97.8154,30.207196],"type":"Point"}
}