{
  "type": "Feature",
  "properties": {
    "iso:country":"US",
    "sg:address":"4706 Wolverhampton Way",
    "sg:city":"Missouri City",
    "sg:classifiers":[
        {
            "category":"Autos & Motor Vehicles",
            "subcategory":"Fuel & Gas Station",
            "type":"Retail Goods"
        }
    ],
    "sg:phone":"+1 281 499 7799",
    "sg:postcode":"77459",
    "sg:province":"TX",
    "sg:tags":[
        "station",
        "gasoline"
    ],
    "wof:name":"Sima Enterprises LLC",
    "wof:placetype":"venue"
},
  "geometry": {"coordinates":[-95.580366,29.594792],"type":"Point"}
}