{
  "type": "Feature",
  "properties": {
    "iso:country":"US",
    "sg:address":"2909 S Hampton Rd",
    "sg:city":"Dallas",
    "sg:classifiers":[
        {
            "category":"Health Services",
            "subcategory":"Podiatrist",
            "type":"Services"
        }
    ],
    "sg:phone":"+1 214 337 8948",
    "sg:postcode":"75224",
    "sg:province":"TX",
    "wof:name":"Prigoff-Bowers LLP",
    "wof:placetype":"venue"
},
  "geometry": {"coordinates":[-96.857035,32.714353],"type":"Point"}
}