{
  "type": "Feature",
  "properties": {
    "iso:country":"US",
    "sg:address":"9401 Southwest Fwy",
    "sg:city":"Houston",
    "sg:classifiers":[
        {
            "category":"Real Estate",
            "subcategory":"Real Estate Agent",
            "type":"Services"
        }
    ],
    "sg:phone":"+1 713 777 7662",
    "sg:postcode":"77074",
    "sg:province":"TX",
    "sg:tags":[
        "management"
    ],
    "wof:name":"R S Property Management",
    "wof:placetype":"venue"
},
  "geometry": {"coordinates":[-95.537193,29.679805],"type":"Point"}
}