{
  "type": "Feature",
  "properties": {
    "iso:country":"US",
    "sg:address":"9513 Burnet Rd",
    "sg:city":"Austin",
    "sg:classifiers":[
        {
            "category":"Retail",
            "subcategory":"Laundry & Dry Cleaning",
            "type":"Services"
        }
    ],
    "sg:phone":"+1 512 459 3478",
    "sg:postcode":"78758",
    "sg:province":"TX",
    "sg:tags":[
        "cleaners",
        "rug",
        "carpet"
    ],
    "wof:name":"Certified Cleaning/Restoration",
    "wof:placetype":"venue"
},
  "geometry": {"coordinates":[-97.725127,30.378315],"type":"Point"}
}