{
  "type": "Feature",
  "properties": {
    "iso:country":"US",
    "sg:address":"13342 Peyton Dr",
    "sg:city":"Dallas",
    "sg:classifiers":[
        {
            "category":"Manufacturing",
            "subcategory":"Printing",
            "type":"Manufacturing & Wholesale Goods"
        }
    ],
    "sg:phone":"+1 972 702 0023",
    "sg:postcode":"75240",
    "sg:province":"TX",
    "sg:tags":[
        "book"
    ],
    "wof:name":"Perfect Shot The",
    "wof:placetype":"venue"
},
  "geometry": {"coordinates":[-96.78370099999999,32.930878],"type":"Point"}
}