{
  "type": "Feature",
  "properties": {
    "iso:country":"US",
    "sg:address":"4505 Ratliff Ln",
    "sg:city":"Addison",
    "sg:classifiers":[
        {
            "category":"Autos & Motor Vehicles",
            "subcategory":"Automobile Sales",
            "type":"Retail Goods"
        }
    ],
    "sg:phone":"+1 972 250 0725",
    "sg:postcode":"75001",
    "sg:province":"TX",
    "wof:name":"Auto Town Imports",
    "wof:placetype":"venue"
},
  "geometry": {"coordinates":[-96.832224,32.971256],"type":"Point"}
}