{
  "type": "Feature",
  "properties": {
    "iso:country":"US",
    "sg:address":"5445 La Sierra Dr Ste 209",
    "sg:city":"Dallas",
    "sg:classifiers":[
        {
            "category":"Health Services",
            "subcategory":"Doctor",
            "type":"Services"
        }
    ],
    "sg:phone":"+1 214 987 2398",
    "sg:postcode":"75231",
    "sg:province":"TX",
    "wof:name":"Cooper Kathryn MD",
    "wof:placetype":"venue"
},
  "geometry": {"coordinates":[-96.7677,32.884201],"type":"Point"}
}