{
  "type": "Feature",
  "properties": {
    "iso:country":"US",
    "sg:address":"1020 Clairmont Dr",
    "sg:city":"Orange",
    "sg:classifiers":[
        {
            "category":"Shopping",
            "subcategory":"Gifts & Souvenirs",
            "type":"Retail Goods"
        }
    ],
    "sg:phone":"+1 409 882 9228",
    "sg:postcode":"77630",
    "sg:province":"TX",
    "wof:name":"Jeffs Gifts Etc",
    "wof:placetype":"venue"
},
  "geometry": {"coordinates":[-93.740644,30.115272],"type":"Point"}
}