{
  "type": "Feature",
  "properties": {
    "iso:country":"US",
    "sg:address":"2113 Knickerbocker Rd",
    "sg:city":"San Angelo",
    "sg:classifiers":[
        {
            "category":"Banks & Credit Unions",
            "subcategory":"Investment Brokerage",
            "type":"Services"
        }
    ],
    "sg:phone":"+1 325 224 3333",
    "sg:postcode":"76904",
    "sg:province":"TX",
    "sg:tags":[
        "security",
        "management",
        "consulting"
    ],
    "wof:name":"A G Edwards & Sons Inc",
    "wof:placetype":"venue"
},
  "geometry": {"coordinates":[-100.459265,31.428451],"type":"Point"}
}