{
  "type": "Feature",
  "properties": {
    "iso:country":"US",
    "sg:address":"4800 Cash Rd",
    "sg:city":"Dallas",
    "sg:classifiers":[
        {
            "category":"Building & Trades",
            "subcategory":"Construction",
            "type":"Services"
        }
    ],
    "sg:phone":"+1 214 905 9950",
    "sg:postcode":"75247",
    "sg:province":"TX",
    "sg:tags":[
        "commercial"
    ],
    "wof:name":"TAs Commercial Con Cnstr LP",
    "wof:placetype":"venue"
},
  "geometry": {"coordinates":[-96.88227500000001,32.808075],"type":"Point"}
}