{
  "type": "Feature",
  "properties": {
    "iso:country":"US",
    "sg:address":"2445 Northwest Loop",
    "sg:city":"Stephenville",
    "sg:classifiers":[
        {
            "category":"Shopping",
            "subcategory":"Pharmacy",
            "type":"Retail Goods"
        }
    ],
    "sg:phone":"+1 254 968 7657",
    "sg:postcode":"76401",
    "sg:province":"TX",
    "sg:tags":[
        "equipment",
        "medical"
    ],
    "wof:name":"Tanglewood Medical Supplies",
    "wof:placetype":"venue"
},
  "geometry": {"coordinates":[-98.23757000000001,32.219714],"type":"Point"}
}