{
  "type": "Feature",
  "properties": {
    "iso:country":"US",
    "sg:address":"3602 Frankford Ave",
    "sg:city":"Lubbock",
    "sg:classifiers":[
        {
            "category":"Social Services",
            "subcategory":"Child Care",
            "type":"Services"
        }
    ],
    "sg:phone":"+1 806 792 4066",
    "sg:postcode":"79407",
    "sg:province":"TX",
    "sg:website":"www.kidstownlearningcenter.com",
    "wof:name":"Kid's Town Learning Ctr",
    "wof:placetype":"venue"
},
  "geometry": {"coordinates":[-101.93982800000001,33.559269],"type":"Point"}
}