{
  "type": "Feature",
  "properties": {
    "iso:country":"US",
    "sg:address":"8687 N. Central Expressway",
    "sg:city":"Dallas",
    "sg:classifiers":[
        {
            "category":"Shopping",
            "subcategory":"Hobbies, Toys, & Games",
            "type":"Retail Goods"
        }
    ],
    "sg:phone":"+1 214 750 6422",
    "sg:postcode":"75231",
    "sg:province":"TX",
    "sg:tags":[
        "toy",
        "store"
    ],
    "sg:website":"stores.lego.com/en-us/Dallas/Lan...",
    "wof:name":"The Lego Store",
    "wof:placetype":"venue"
},
  "geometry": {"coordinates":[-96.77325399999999,32.871604],"type":"Point"}
}