{
  "type": "Feature",
  "properties": {
    "iso:country":"US",
    "sg:address":"3015 Richmond Ave",
    "sg:city":"Houston",
    "sg:classifiers":[
        {
            "category":"Professional",
            "subcategory":"Art Services",
            "type":"Services"
        }
    ],
    "sg:phone":"+1 713 524 1739",
    "sg:postcode":"77098",
    "sg:province":"TX",
    "sg:tags":[
        "graphic",
        "designer"
    ],
    "wof:name":"Eight By Eight Design",
    "wof:placetype":"venue"
},
  "geometry": {"coordinates":[-95.42331,29.733957],"type":"Point"}
}