{
  "type": "Feature",
  "properties": {
    "iso:country":"US",
    "sg:address":"3645 Redbud Ave",
    "sg:city":"Odessa",
    "sg:classifiers":[
        {
            "category":"Building & Trades",
            "subcategory":"Plumbing",
            "type":"Services"
        }
    ],
    "sg:phone":"+1 432 272 5450",
    "sg:postcode":"79762",
    "sg:province":"TX",
    "sg:tags":[
        "plumber",
        "industrial",
        "contractors-commercial"
    ],
    "wof:name":"Lehman Plumbing",
    "wof:placetype":"venue"
},
  "geometry": {"coordinates":[-102.353683,31.885292],"type":"Point"}
}