{
  "type": "Feature",
  "properties": {
    "iso:country":"US",
    "sg:address":"204 S East St",
    "sg:city":"Arlington",
    "sg:classifiers":[
        {
            "category":"Professional",
            "subcategory":"Business Services",
            "type":"Services"
        }
    ],
    "sg:phone":"+1 817 461 7340",
    "sg:postcode":"76010",
    "sg:province":"TX",
    "sg:tags":[
        "recording",
        "studio"
    ],
    "wof:name":"Pineapple Recording Studio",
    "wof:placetype":"venue"
},
  "geometry": {"coordinates":[-97.103602,32.734827],"type":"Point"}
}