{
  "type": "Feature",
  "properties": {
    "iso:country":"US",
    "sg:address":"1506 N College St",
    "sg:city":"Mc Kinney",
    "sg:classifiers":[
        {
            "category":"Building & Trades",
            "subcategory":"Construction",
            "type":"Services"
        }
    ],
    "sg:phone":"+1 214 415 9274",
    "sg:postcode":"75069",
    "sg:province":"TX",
    "wof:name":"L&D Custom Finishes Inc",
    "wof:placetype":"venue"
},
  "geometry": {"coordinates":[-96.620338,33.211043],"type":"Point"}
}