{
  "type": "Feature",
  "properties": {
    "iso:country":"US",
    "sg:address":"9018 Lochgreen Ln",
    "sg:city":"Rowlett",
    "sg:classifiers":[
        {
            "category":"Insurance",
            "subcategory":"Insurance Agent",
            "type":"Services"
        }
    ],
    "sg:phone":"+1 972 278 0033",
    "sg:postcode":"75089",
    "sg:province":"TX",
    "wof:name":"Allstate",
    "wof:placetype":"venue"
},
  "geometry": {"coordinates":[-96.535477,32.939986],"type":"Point"}
}