{
  "type": "Feature",
  "properties": {
    "iso:country":"US",
    "sg:address":"34 Warwick",
    "sg:city":"Missouri City",
    "sg:classifiers":[
        {
            "category":"Professional",
            "type":"Services"
        }
    ],
    "sg:phone":"+1 281 403 0486",
    "sg:postcode":"77459",
    "sg:province":"TX",
    "wof:name":"Nubografix",
    "wof:placetype":"venue"
},
  "geometry": {"coordinates":[-95.560945,29.584393],"type":"Point"}
}