{
  "type": "Feature",
  "properties": {
    "iso:country":"US",
    "sg:address":"23746 Co Rd 508",
    "sg:city":"Harlingen",
    "sg:classifiers":[
        {
            "category":"Wholesale",
            "subcategory":"Groceries",
            "type":"Manufacturing & Wholesale Goods"
        },
        {
            "category":"Shopping",
            "subcategory":"Gifts & Souvenirs",
            "type":"Retail Goods"
        }
    ],
    "sg:phone":"+1 956 428 3963",
    "sg:postcode":"78550",
    "sg:province":"TX",
    "sg:tags":[
        "collectible",
        "confectionery"
    ],
    "wof:name":"Bees Precious Collectibles Not",
    "wof:placetype":"venue"
},
  "geometry": {"coordinates":[-97.63972200000001,26.247435],"type":"Point"}
}