{
  "type": "Feature",
  "properties": {
    "iso:country":"US",
    "sg:address":"1001 N Armstrong Ave",
    "sg:city":"Denison",
    "sg:classifiers":[
        {
            "category":"Health Services",
            "subcategory":"Nursing And Care Facility",
            "type":"Services"
        }
    ],
    "sg:phone":"+1 903 465 9670",
    "sg:postcode":"75020",
    "sg:province":"TX",
    "sg:tags":[
        "skilled"
    ],
    "wof:name":"Denison Health Center",
    "wof:placetype":"venue"
},
  "geometry": {"coordinates":[-96.546126,33.766283],"type":"Point"}
}