{
  "type": "Feature",
  "properties": {
    "iso:country":"US",
    "sg:address":"3673 Westcenter Dr",
    "sg:city":"Houston",
    "sg:classifiers":[
        {
            "category":"Banks & Credit Unions",
            "subcategory":"Bank",
            "type":"Services"
        }
    ],
    "sg:phone":"+1 713 974 0748",
    "sg:postcode":"77042",
    "sg:province":"TX",
    "sg:tags":[
        "mortgage",
        "loan",
        "broker",
        "real estate"
    ],
    "wof:name":"National Lending Corporation",
    "wof:placetype":"venue"
},
  "geometry": {"coordinates":[-95.55389,29.724365],"type":"Point"}
}