{
  "type": "Feature",
  "properties": {
    "iso:country":"US",
    "sg:address":"9735 Five Forks St",
    "sg:city":"San Antonio",
    "sg:classifiers":[
        {
            "category":"Building & Trades",
            "subcategory":"Construction",
            "type":"Services"
        }
    ],
    "sg:phone":"+1 210 674 5630",
    "sg:postcode":"78245",
    "sg:province":"TX",
    "sg:tags":[
        "home",
        "improvement",
        "contractor"
    ],
    "wof:name":"A V A Contractors",
    "wof:placetype":"venue"
},
  "geometry": {"coordinates":[-98.673733,29.414401],"type":"Point"}
}