{
  "type": "Feature",
  "properties": {
    "iso:country":"US",
    "sg:address":"3222 Clark Ave",
    "sg:city":"San Antonio",
    "sg:classifiers":[
        {
            "category":"Personal",
            "subcategory":"Beauty Salon",
            "type":"Services"
        }
    ],
    "sg:phone":"+1 210 532 7885",
    "sg:postcode":"78210",
    "sg:province":"TX",
    "wof:name":"Cindy's Beauty Shop",
    "wof:placetype":"venue"
},
  "geometry": {"coordinates":[-98.448252,29.384485],"type":"Point"}
}