{
  "type": "Feature",
  "properties": {
    "iso:country":"US",
    "sg:address":"17650 Northwest Fwy",
    "sg:city":"Houston",
    "sg:classifiers":[
        {
            "category":"Autos & Motor Vehicles",
            "subcategory":"Automobile Sales",
            "type":"Retail Goods"
        }
    ],
    "sg:phone":"+1 713 691 5555",
    "sg:postcode":"77065",
    "sg:province":"TX",
    "sg:tags":[
        "ha",
        "f",
        "used",
        "dealership",
        "deere",
        "john"
    ],
    "wof:name":"David Foster Auto Sales",
    "wof:placetype":"venue"
},
  "geometry": {"coordinates":[-95.584463,29.89066],"type":"Point"}
}