{
  "type": "Feature",
  "properties": {
    "iso:country":"US",
    "sg:address":"4723 Meadows Edge Ln",
    "sg:city":"Houston",
    "sg:classifiers":[
        {
            "category":"Wholesale",
            "subcategory":"Home Furnishings",
            "type":"Manufacturing & Wholesale Goods"
        }
    ],
    "sg:phone":"+1 281 855 9729",
    "sg:postcode":"77084",
    "sg:province":"TX",
    "wof:name":"Arts Afire",
    "wof:placetype":"venue"
},
  "geometry": {"coordinates":[-95.70034699999999,29.839132],"type":"Point"}
}