{
  "type": "Feature",
  "properties": {
    "iso:country":"US",
    "sg:address":"6555 Harbor Town Dr Apt 705",
    "sg:city":"Houston",
    "sg:classifiers":[
        {
            "category":"Restaurant",
            "type":"Food & Drink"
        }
    ],
    "sg:phone":"+1 903 753 3020",
    "sg:postcode":"77036",
    "sg:province":"TX",
    "wof:name":"Chen's Garden",
    "wof:placetype":"venue"
},
  "geometry": {"coordinates":[-95.527,29.709],"type":"Point"}
}