{
  "type": "Feature",
  "properties": {
    "iso:country":"US",
    "sg:address":"9815 Carnegie Dr",
    "sg:city":"Dallas",
    "sg:classifiers":[
        {
            "category":"Professional",
            "type":"Services"
        }
    ],
    "sg:phone":"+1 214 324 4017",
    "sg:postcode":"75228",
    "sg:province":"TX",
    "wof:name":"Novus Consumer Awareness",
    "wof:placetype":"venue"
},
  "geometry": {"coordinates":[-96.69069,32.831221],"type":"Point"}
}