{
  "type": "Feature",
  "properties": {
    "iso:country":"US",
    "sg:address":"730 S Cockrell Hill Rd",
    "sg:city":"Duncanville",
    "sg:classifiers":[
        {
            "category":"Wholesale",
            "subcategory":"Auto Parts",
            "type":"Manufacturing & Wholesale Goods"
        }
    ],
    "sg:phone":"+1 972 780 8712",
    "sg:postcode":"75137",
    "sg:province":"TX",
    "sg:tags":[
        "supply"
    ],
    "wof:name":"NAPA Auto Parts",
    "wof:placetype":"venue"
},
  "geometry": {"coordinates":[-96.891401,32.642379],"type":"Point"}
}