{
  "type": "Feature",
  "properties": {
    "iso:country":"US",
    "sg:address":"1280 Hawkins Blvd",
    "sg:city":"El Paso",
    "sg:classifiers":[
        {
            "category":"Professional",
            "subcategory":"Accounting & Tax Preparation",
            "type":"Services"
        }
    ],
    "sg:phone":"+1 915 593 1280",
    "sg:postcode":"79925",
    "sg:province":"TX",
    "sg:tags":[
        "firm"
    ],
    "wof:name":"Bixler & Company LLP",
    "wof:placetype":"venue"
},
  "geometry": {"coordinates":[-106.374427,31.775647],"type":"Point"}
}