{
  "type": "Feature",
  "properties": {
    "iso:country":"US",
    "sg:address":"105 E Expressway 83",
    "sg:city":"Pharr",
    "sg:classifiers":[
        {
            "category":"Social Services",
            "subcategory":"Adult Care",
            "type":"Services"
        }
    ],
    "sg:phone":"+1 956 783 1818",
    "sg:postcode":"78577",
    "sg:province":"TX",
    "sg:tags":[
        "centers-adult",
        "day"
    ],
    "wof:name":"Lahs Adult Daycare",
    "wof:placetype":"venue"
},
  "geometry": {"coordinates":[-98.18026399999999,26.206865],"type":"Point"}
}