{
  "type": "Feature",
  "properties": {
    "iso:country":"US",
    "sg:address":"2434 Lillian Miller Pkwy",
    "sg:city":"Denton",
    "sg:classifiers":[
        {
            "category":"Real Estate",
            "subcategory":"Real Estate Agent",
            "type":"Services"
        }
    ],
    "sg:phone":"+1 940 383 6683",
    "sg:postcode":"76205",
    "sg:province":"TX",
    "wof:name":"Mc Kissack Group Inc",
    "wof:placetype":"venue"
},
  "geometry": {"coordinates":[-97.10881500000001,33.185721],"type":"Point"}
}