{
  "type": "Feature",
  "properties": {
    "iso:country":"US",
    "sg:address":"800 W Highway 82",
    "sg:city":"Nocona",
    "sg:classifiers":[
        {
            "category":"Real Estate",
            "subcategory":"Real Estate Operator",
            "type":"Services"
        }
    ],
    "sg:phone":"+1 940 825 6006",
    "sg:postcode":"76255",
    "sg:province":"TX",
    "sg:tags":[
        "apartment"
    ],
    "wof:name":"Horizon Manor Carecenter",
    "wof:placetype":"venue"
},
  "geometry": {"coordinates":[-97.73468800000001,33.783875],"type":"Point"}
}