{
  "type": "Feature",
  "properties": {
    "iso:country":"US",
    "sg:address":"2006 45th St",
    "sg:city":"Galveston",
    "sg:classifiers":[
        {
            "category":"Health Services",
            "subcategory":"Chiropractor",
            "type":"Services"
        },
        {
            "category":"Health Services",
            "subcategory":"Doctor",
            "type":"Services"
        }
    ],
    "sg:phone":"+1 409 763 5900",
    "sg:postcode":"77550",
    "sg:province":"TX",
    "sg:tags":[
        "clinic"
    ],
    "wof:name":"Island Chiropractic",
    "wof:placetype":"venue"
},
  "geometry": {"coordinates":[-94.81402300000001,29.28431],"type":"Point"}
}