{
  "type": "Feature",
  "properties": {
    "iso:country":"US",
    "sg:address":"5509 China Berry Rd",
    "sg:city":"Austin",
    "sg:classifiers":[
        {
            "category":"Communications",
            "subcategory":"Film & Video Production",
            "type":"Services"
        }
    ],
    "sg:phone":"+1 512 442 3066",
    "sg:postcode":"78744",
    "sg:province":"TX",
    "sg:tags":[
        "motion"
    ],
    "wof:name":"Move Your Body Productions",
    "wof:placetype":"venue"
},
  "geometry": {"coordinates":[-97.735981,30.19244],"type":"Point"}
}