{
  "type": "Feature",
  "properties": {
    "iso:country":"US",
    "sg:address":"3411 Ashton Park Dr",
    "sg:city":"Houston",
    "sg:classifiers":[
        {
            "category":"Shopping",
            "subcategory":"Catalog Store",
            "type":"Retail Goods"
        }
    ],
    "sg:phone":"+1 281 556 5723",
    "sg:postcode":"77082",
    "sg:province":"TX",
    "sg:tags":[
        "hospitality",
        "furnishing"
    ],
    "wof:name":"Marbry Purchasing Intl Inc",
    "wof:placetype":"venue"
},
  "geometry": {"coordinates":[-95.607445,29.72535],"type":"Point"}
}