{
  "type": "Feature",
  "properties": {
    "iso:country":"US",
    "sg:address":"9010 Magnetic St",
    "sg:city":"El Paso",
    "sg:classifiers":[
        {
            "category":"Real Estate",
            "subcategory":"Real Estate Operator",
            "type":"Services"
        }
    ],
    "sg:phone":"+1 915 751 8531",
    "sg:postcode":"79904",
    "sg:province":"TX",
    "sg:tags":[
        "building",
        "apartment"
    ],
    "wof:name":"Canyon Hills Apartments",
    "wof:placetype":"venue"
},
  "geometry": {"coordinates":[-106.45347099999999,31.86937],"type":"Point"}
}