{
  "type": "Feature",
  "properties": {
    "iso:country":"US",
    "sg:address":"3410 Doug Dr",
    "sg:city":"Dallas",
    "sg:classifiers":[
        {
            "category":"Insurance",
            "subcategory":"Insurance Agent",
            "type":"Services"
        }
    ],
    "sg:phone":"+1 214 634 1750",
    "sg:postcode":"75247",
    "sg:province":"TX",
    "sg:tags":[
        "adjuster"
    ],
    "wof:name":"Invisible Fence-The Mtrplx",
    "wof:placetype":"venue"
},
  "geometry": {"coordinates":[-96.876188,32.803169],"type":"Point"}
}