{
  "type": "Feature",
  "properties": {
    "iso:country":"US",
    "sg:address":"15605 East Fwy",
    "sg:city":"Channelview",
    "sg:classifiers":[
        {
            "category":"Autos & Motor Vehicles",
            "subcategory":"Fuel & Gas Station",
            "type":"Retail Goods"
        },
        {
            "category":"Food & Beverages",
            "subcategory":"Groceries & Convenience Stores",
            "type":"Retail Goods"
        }
    ],
    "sg:phone":"+1 281 452 0864",
    "sg:postcode":"77530",
    "sg:province":"TX",
    "sg:website":"www.texaco.com",
    "wof:name":"Aneel's Texaco",
    "wof:placetype":"venue"
},
  "geometry": {"coordinates":[-95.12987800000001,29.777264],"type":"Point"}
}