{
  "type": "Feature",
  "properties": {
    "iso:country":"US",
    "sg:address":"2023 Babcock Rd",
    "sg:city":"San Antonio",
    "sg:classifiers":[
        {
            "category":"Food & Beverages",
            "subcategory":"Groceries & Convenience Stores",
            "type":"Retail Goods"
        }
    ],
    "sg:phone":"+1 210 691 2440",
    "sg:postcode":"78229",
    "sg:province":"TX",
    "sg:tags":[
        "station"
    ],
    "wof:name":"Diamond Shamrock",
    "wof:placetype":"venue"
},
  "geometry": {"coordinates":[-98.57754199999999,29.499437],"type":"Point"}
}