{
  "type": "Feature",
  "properties": {
    "iso:country":"US",
    "sg:address":"1300 Custer Rd",
    "sg:city":"Plano",
    "sg:classifiers":[
        {
            "category":"Home & Garden",
            "subcategory":"Building Materials",
            "type":"Retail Goods"
        }
    ],
    "sg:phone":"+1 972 221 9658",
    "sg:postcode":"75075",
    "sg:province":"TX",
    "wof:name":"Stenciled Interiors",
    "wof:placetype":"venue"
},
  "geometry": {"coordinates":[-96.73356800000001,33.017947],"type":"Point"}
}