{
  "type": "Feature",
  "properties": {
    "iso:country":"US",
    "sg:address":"9748 Westview Dr",
    "sg:city":"Houston",
    "sg:classifiers":[
        {
            "category":"Building & Trades",
            "subcategory":"Landscaping Services",
            "type":"Services"
        }
    ],
    "sg:phone":"+1 713 932 1859",
    "sg:postcode":"77055",
    "sg:province":"TX",
    "sg:tags":[
        "landscape"
    ],
    "wof:name":"No Limit Landscaping",
    "wof:placetype":"venue"
},
  "geometry": {"coordinates":[-95.53122999999999,29.792986],"type":"Point"}
}