{
  "type": "Feature",
  "properties": {
    "iso:country":"US",
    "sg:address":"6106 Jessamine St",
    "sg:city":"Houston",
    "sg:classifiers":[
        {
            "category":"Retail",
            "subcategory":"Auto Repair",
            "type":"Services"
        }
    ],
    "sg:phone":"+1 713 981 9300",
    "sg:postcode":"77081",
    "sg:province":"TX",
    "wof:name":"Auto Quick Fix",
    "wof:placetype":"venue"
},
  "geometry": {"coordinates":[-95.48886299999999,29.702009],"type":"Point"}
}