{
  "type": "Feature",
  "properties": {
    "iso:country":"US",
    "sg:address":"10206 Kirkwren Dr",
    "sg:city":"Houston",
    "sg:classifiers":[
        {
            "category":"Wholesale",
            "subcategory":"Non-durable Goods",
            "type":"Manufacturing & Wholesale Goods"
        }
    ],
    "sg:phone":"+1 281 484 1264",
    "sg:postcode":"77089",
    "sg:province":"TX",
    "wof:name":"Wang Supply International",
    "wof:placetype":"venue"
},
  "geometry": {"coordinates":[-95.244011,29.595079],"type":"Point"}
}