{
  "type": "Feature",
  "properties": {
    "iso:country":"US",
    "sg:address":"10575 Katy Fwy Ste 440",
    "sg:city":"Houston",
    "sg:classifiers":[
        {
            "category":"Communications",
            "type":"Services"
        }
    ],
    "sg:phone":"+1 713 468 1550",
    "sg:postcode":"77024",
    "sg:province":"TX",
    "sg:tags":[
        "translator",
        "interpreter"
    ],
    "wof:name":"Abroad",
    "wof:placetype":"venue"
},
  "geometry": {"coordinates":[-95.559483,29.783928],"type":"Point"}
}