{
  "type": "Feature",
  "properties": {
    "iso:country":"US",
    "sg:address":"7227 Antoine Dr",
    "sg:city":"Houston",
    "sg:classifiers":[
        {
            "category":"Food & Beverages",
            "subcategory":"Groceries & Convenience Stores",
            "type":"Retail Goods"
        }
    ],
    "sg:phone":"+1 281 447 2702",
    "sg:postcode":"77088",
    "sg:province":"TX",
    "wof:name":"Speedy Mart",
    "wof:placetype":"venue"
},
  "geometry": {"coordinates":[-95.473123,29.865922],"type":"Point"}
}