{
  "type": "Feature",
  "properties": {
    "iso:country":"US",
    "sg:address":"128 W Windemere St",
    "sg:city":"Leander",
    "sg:classifiers":[
        {
            "category":"Professional",
            "type":"Services"
        }
    ],
    "sg:phone":"+1 512 259 8623",
    "sg:postcode":"78641",
    "sg:province":"TX",
    "wof:name":"Susan Sidney",
    "wof:placetype":"venue"
},
  "geometry": {"coordinates":[-97.81546299999999,30.579163],"type":"Point"}
}