{
  "type": "Feature",
  "properties": {
    "iso:country":"US",
    "sg:address":"7701 I- 40 Bus",
    "sg:city":"Amarillo",
    "sg:classifiers":[
        {
            "category":"Shopping",
            "type":"Retail Goods"
        }
    ],
    "sg:phone":"+1 806 353 7033",
    "sg:postcode":"79107",
    "sg:province":"TX",
    "sg:tags":[
        "equipment",
        "merchandise"
    ],
    "wof:name":"AT&T",
    "wof:placetype":"venue"
},
  "geometry": {"coordinates":[-101.75842400000001,35.220636],"type":"Point"}
}