{
  "type": "Feature",
  "properties": {
    "iso:country":"US",
    "sg:address":"12123 Millstream Way",
    "sg:city":"Houston",
    "sg:classifiers":[
        {
            "category":"Professional",
            "subcategory":"Computer Services",
            "type":"Services"
        }
    ],
    "sg:phone":"+1 713 983 9913",
    "sg:postcode":"77041",
    "sg:province":"TX",
    "sg:tags":[
        "prepackaged",
        "software"
    ],
    "wof:name":"S & R Software LLC",
    "wof:placetype":"venue"
},
  "geometry": {"coordinates":[-95.591695,29.844543],"type":"Point"}
}