{
  "type": "Feature",
  "properties": {
    "iso:country":"US",
    "sg:address":"8467 Greylock Ct",
    "sg:city":"Fort Worth",
    "sg:classifiers":[
        {
            "category":"Restaurant",
            "type":"Food & Drink"
        }
    ],
    "sg:phone":"+1 817 788 9684",
    "sg:postcode":"76137",
    "sg:province":"TX",
    "sg:tags":[
        "eating"
    ],
    "wof:name":"Zak Group Inc",
    "wof:placetype":"venue"
},
  "geometry": {"coordinates":[-97.279827,32.892178],"type":"Point"}
}