{
  "type": "Feature",
  "properties": {
    "iso:country":"US",
    "sg:address":"11008 Fairwood Dr",
    "sg:city":"La Porte",
    "sg:classifiers":[
        {
            "category":"Professional",
            "subcategory":"Art Services",
            "type":"Services"
        }
    ],
    "sg:phone":"+1 281 471 3443",
    "sg:postcode":"77571",
    "sg:province":"TX",
    "sg:tags":[
        "commercial",
        "design"
    ],
    "wof:name":"Crystal Houston Graphics",
    "wof:placetype":"venue"
},
  "geometry": {"coordinates":[-95.05934000000001,29.663639],"type":"Point"}
}