{
  "type": "Feature",
  "properties": {
    "iso:country":"US",
    "sg:address":"2809 N Mechanic St",
    "sg:city":"El Campo",
    "sg:classifiers":[
        {
            "category":"Professional",
            "subcategory":"Lawyer & Legal Services",
            "type":"Services"
        }
    ],
    "sg:phone":"+1 979 578 0785",
    "sg:postcode":"77437",
    "sg:province":"TX",
    "sg:tags":[
        "plan"
    ],
    "wof:name":"Pre-Paid Legal Svc",
    "wof:placetype":"venue"
},
  "geometry": {"coordinates":[-96.296021,29.228994],"type":"Point"}
}