{
  "type": "Feature",
  "properties": {
    "iso:country":"US",
    "sg:address":"4431 Greystone Dr",
    "sg:city":"San Antonio",
    "sg:classifiers":[
        {
            "category":"Professional",
            "subcategory":"Detective & Security Services",
            "type":"Services"
        }
    ],
    "sg:phone":"+1 210 646 8070",
    "sg:postcode":"78233",
    "sg:province":"TX",
    "sg:tags":[
        "system"
    ],
    "wof:name":"C U Technologies",
    "wof:placetype":"venue"
},
  "geometry": {"coordinates":[-98.404247,29.543265],"type":"Point"}
}