{
  "type": "Feature",
  "properties": {
    "iso:country":"US",
    "sg:address":"3337 Kimberly Ln",
    "sg:city":"Grand Prairie",
    "sg:classifiers":[
        {
            "category":"Professional",
            "subcategory":"Management & Consulting",
            "type":"Services"
        }
    ],
    "sg:phone":"+1 972 602 1893",
    "sg:postcode":"75052",
    "sg:province":"TX",
    "wof:name":"Lassiter/Associate",
    "wof:placetype":"venue"
},
  "geometry": {"coordinates":[-97.049178,32.687498],"type":"Point"}
}