{
  "type": "Feature",
  "properties": {
    "iso:country":"US",
    "sg:address":"2360 Valwood Pkwy",
    "sg:city":"Dallas",
    "sg:classifiers":[
        {
            "category":"Food & Beverages",
            "subcategory":"Specialty",
            "type":"Retail Goods"
        },
        {
            "category":"Food & Beverages",
            "subcategory":"Groceries & Convenience Stores",
            "type":"Retail Goods"
        }
    ],
    "sg:phone":"+1 469 522 1717",
    "sg:postcode":"75234",
    "sg:province":"TX",
    "sg:tags":[
        "grocers-specialty"
    ],
    "wof:name":"Buddy S Food Mart",
    "wof:placetype":"venue"
},
  "geometry": {"coordinates":[-96.90147,32.938422],"type":"Point"}
}