{
  "type": "Feature",
  "properties": {
    "iso:country":"US",
    "sg:address":"514 Turner St",
    "sg:city":"Conroe",
    "sg:classifiers":[
        {
            "category":"Shopping",
            "subcategory":"Clothing, Apparel, & Fashions",
            "type":"Retail Goods"
        }
    ],
    "sg:phone":"+1 936 756 3529",
    "sg:postcode":"77301",
    "sg:province":"TX",
    "wof:name":"Leonor Fashions",
    "wof:placetype":"venue"
},
  "geometry": {"coordinates":[-95.451655,30.318355],"type":"Point"}
}