{
  "type": "Feature",
  "properties": {
    "iso:country":"US",
    "sg:address":"2220 Shadydale Dr",
    "sg:city":"Arlington",
    "sg:classifiers":[
        {
            "category":"Shopping",
            "type":"Retail Goods"
        }
    ],
    "sg:phone":"+1 817 794 0957",
    "sg:postcode":"76012",
    "sg:province":"TX",
    "sg:tags":[
        "merchandise"
    ],
    "wof:name":"Southwest Audio Designs/Instln",
    "wof:placetype":"venue"
},
  "geometry": {"coordinates":[-97.13518000000001,32.773024],"type":"Point"}
}