{
  "type": "Feature",
  "properties": {
    "iso:country":"US",
    "sg:address":"618 S 2nd St",
    "sg:city":"Corsicana",
    "sg:classifiers":[
        {
            "category":"Insurance",
            "subcategory":"Insurance Agent",
            "type":"Services"
        }
    ],
    "sg:phone":"+1 903 875 0400",
    "sg:postcode":"75110",
    "sg:province":"TX",
    "wof:name":"R Sterling Hyden Insurance",
    "wof:placetype":"venue"
},
  "geometry": {"coordinates":[-96.452887,32.093421],"type":"Point"}
}