{
  "type": "Feature",
  "properties": {
    "iso:country":"US",
    "sg:address":"600 S Lamar Blvd",
    "sg:city":"Austin",
    "sg:classifiers":[
        {
            "category":"Food Court",
            "type":"Food & Drink"
        },
        {
            "category":"Food & Beverages",
            "subcategory":"Meat & Fish",
            "type":"Retail Goods"
        }
    ],
    "sg:phone":"+1 512 761 3056",
    "sg:postcode":"78704",
    "sg:province":"TX",
    "sg:tags":[
        "hot",
        "stand",
        "dog"
    ],
    "wof:name":"That Hot Dog Stand",
    "wof:placetype":"venue"
},
  "geometry": {"coordinates":[-97.759019,30.259809],"type":"Point"}
}