{
  "type": "Feature",
  "properties": {
    "iso:country":"US",
    "sg:address":"9654 Spring Harvest Rd",
    "sg:city":"San Antonio",
    "sg:classifiers":[
        {
            "category":"Building & Trades",
            "subcategory":"Cleaning & Sanitation",
            "type":"Services"
        }
    ],
    "sg:phone":"+1 210 509 7671",
    "sg:postcode":"78254",
    "sg:province":"TX",
    "sg:tags":[
        "flue",
        "maintenance"
    ],
    "wof:name":"Alamo High Pressure Cleaning",
    "wof:placetype":"venue"
},
  "geometry": {"coordinates":[-98.673033,29.534619],"type":"Point"}
}