{
  "type": "Feature",
  "properties": {
    "iso:country":"US",
    "sg:address":"2309 Handley Ederville Rd",
    "sg:city":"Fort Worth",
    "sg:classifiers":[
        {
            "category":"Shopping",
            "subcategory":"News",
            "type":"Retail Goods"
        }
    ],
    "sg:phone":"+1 817 492 4551",
    "sg:postcode":"76118",
    "sg:province":"TX",
    "sg:tags":[
        "dealer"
    ],
    "wof:name":"Publishers Circulation",
    "wof:placetype":"venue"
},
  "geometry": {"coordinates":[-97.22057599999999,32.78133],"type":"Point"}
}