{
  "type": "Feature",
  "properties": {
    "iso:country":"US",
    "sg:address":"609 Castle Ridge Rd",
    "sg:city":"Austin",
    "sg:classifiers":[
        {
            "category":"Utilities",
            "subcategory":"Telephone",
            "type":"Services"
        }
    ],
    "sg:phone":"+1 512 327 4454",
    "sg:postcode":"78746",
    "sg:province":"TX",
    "sg:tags":[
        "communications"
    ],
    "wof:name":"Telephone Management",
    "wof:placetype":"venue"
},
  "geometry": {"coordinates":[-97.83044099999999,30.292942],"type":"Point"}
}