{
  "type": "Feature",
  "properties": {
    "iso:country":"US",
    "sg:address":"2427 7th St",
    "sg:city":"Lubbock",
    "sg:classifiers":[
        {
            "category":"Home & Garden",
            "subcategory":"Carpets & Floor Coverings",
            "type":"Retail Goods"
        }
    ],
    "sg:phone":"+1 806 744 4977",
    "sg:postcode":"79401",
    "sg:province":"TX",
    "sg:tags":[
        "laying",
        "contractor"
    ],
    "wof:name":"Bennies Carpet Service",
    "wof:placetype":"venue"
},
  "geometry": {"coordinates":[-101.87014000000001,33.589077],"type":"Point"}
}