{
  "type": "Feature",
  "properties": {
    "iso:country":"US",
    "sg:address":"5100 N Kings Hwy",
    "sg:city":"Texarkana",
    "sg:classifiers":[
        {
            "category":"Building & Trades",
            "subcategory":"Landscaping Services",
            "type":"Services"
        }
    ],
    "sg:phone":"+1 903 832 3996",
    "sg:postcode":"75503",
    "sg:province":"TX",
    "wof:name":"Asimos Lawn Care",
    "wof:placetype":"venue"
},
  "geometry": {"coordinates":[-94.14221499999999,33.469569],"type":"Point"}
}