{
  "type": "Feature",
  "properties": {
    "iso:country":"US",
    "sg:address":"7210 Elm St",
    "sg:city":"Frisco",
    "sg:classifiers":[
        {
            "category":"Food & Beverages",
            "subcategory":"Specialty",
            "type":"Retail Goods"
        }
    ],
    "sg:phone":"+1 972 712 8848",
    "sg:postcode":"75034",
    "sg:province":"TX",
    "sg:tags":[
        "gourmet",
        "shop"
    ],
    "wof:name":"Homemade Gourmet",
    "wof:placetype":"venue"
},
  "geometry": {"coordinates":[-96.821832,33.149167],"type":"Point"}
}