{
  "type": "Feature",
  "properties": {
    "iso:country":"US",
    "sg:address":"2511 Lolita Dr",
    "sg:city":"Dallas",
    "sg:classifiers":[
        {
            "category":"Building & Trades",
            "subcategory":"Construction",
            "type":"Services"
        }
    ],
    "sg:phone":"+1 214 381 3046",
    "sg:postcode":"75227",
    "sg:province":"TX",
    "sg:tags":[
        "handyman"
    ],
    "wof:name":"Gerardo Perette Svc",
    "wof:placetype":"venue"
},
  "geometry": {"coordinates":[-96.68011799999999,32.756106],"type":"Point"}
}