{
  "type": "Feature",
  "properties": {
    "iso:country":"US",
    "sg:address":"1507 Delano St",
    "sg:city":"Houston",
    "sg:classifiers":[
        {
            "category":"Organizations",
            "subcategory":"Religious Organization",
            "type":"Services"
        }
    ],
    "sg:phone":"+1 713 236 1015",
    "sg:postcode":"77003",
    "sg:province":"TX",
    "wof:name":"Pien Hou Temple",
    "wof:placetype":"venue"
},
  "geometry": {"coordinates":[-95.352699,29.743401],"type":"Point"}
}