{
  "type": "Feature",
  "properties": {
    "iso:country":"US",
    "sg:address":"14519 Misty Meadow Ln",
    "sg:city":"Houston",
    "sg:classifiers":[
        {
            "category":"Banks & Credit Unions",
            "subcategory":"Bank",
            "type":"Services"
        }
    ],
    "sg:phone":"+1 281 531 0886",
    "sg:postcode":"77079",
    "sg:province":"TX",
    "sg:tags":[
        "mortgage"
    ],
    "wof:name":"Loans By Design Mortgage Servi",
    "wof:placetype":"venue"
},
  "geometry": {"coordinates":[-95.599538,29.780152],"type":"Point"}
}