{
  "type": "Feature",
  "properties": {
    "iso:country":"US",
    "sg:address":"15906 Longneck Dr",
    "sg:city":"Magnolia",
    "sg:classifiers":[
        {
            "category":"Shopping",
            "type":"Retail Goods"
        }
    ],
    "sg:phone":"+1 281 356 6292",
    "sg:postcode":"77355",
    "sg:province":"TX",
    "sg:tags":[
        "merchandise"
    ],
    "wof:name":"Burkes Pet Supply",
    "wof:placetype":"venue"
},
  "geometry": {"coordinates":[-95.736667,30.124729],"type":"Point"}
}