{
  "type": "Feature",
  "properties": {
    "iso:country":"US",
    "sg:address":"1545 Goodyear Dr",
    "sg:city":"El Paso",
    "sg:classifiers":[
        {
            "category":"Wholesale",
            "subcategory":"Non-durable Goods",
            "type":"Manufacturing & Wholesale Goods"
        }
    ],
    "sg:phone":"+1 915 598 4977",
    "sg:postcode":"79936",
    "sg:province":"TX",
    "wof:name":"Istal Corp",
    "wof:placetype":"venue"
},
  "geometry": {"coordinates":[-106.31200200000001,31.743544],"type":"Point"}
}