{
  "type": "Feature",
  "properties": {
    "iso:country":"US",
    "sg:address":"1838 Cheshire Ln",
    "sg:city":"Houston",
    "sg:classifiers":[
        {
            "category":"Professional",
            "subcategory":"Management & Consulting",
            "type":"Services"
        }
    ],
    "sg:phone":"+1 713 688 1060",
    "sg:postcode":"77018",
    "sg:province":"TX",
    "sg:tags":[
        "counselor",
        "relation",
        "public"
    ],
    "wof:name":"Inter Ethnic Forum Of Houston",
    "wof:placetype":"venue"
},
  "geometry": {"coordinates":[-95.445289,29.829279],"type":"Point"}
}