{
  "type": "Feature",
  "properties": {
    "iso:country":"US",
    "sg:address":"4600 Rutherford Dr",
    "sg:city":"El Paso",
    "sg:classifiers":[
        {
            "category":"Recreation",
            "type":"Entertainment"
        }
    ],
    "sg:phone":"+1 915 541 4331",
    "sg:postcode":"79924",
    "sg:province":"TX",
    "sg:tags":[
        "parks"
    ],
    "wof:name":"Todd Ware Park",
    "wof:placetype":"venue"
},
  "geometry": {"coordinates":[-106.432237,31.876928],"type":"Point"}
}