{
  "type": "Feature",
  "properties": {
    "iso:country":"US",
    "sg:address":"16214 Koester St",
    "sg:city":"Houston",
    "sg:classifiers":[
        {
            "category":"Professional",
            "subcategory":"Computer Services",
            "type":"Services"
        }
    ],
    "sg:phone":"+1 713 937 6046",
    "sg:postcode":"77040",
    "sg:province":"TX",
    "sg:tags":[
        "product",
        "related",
        "mfg"
    ],
    "wof:name":"Grant Management",
    "wof:placetype":"venue"
},
  "geometry": {"coordinates":[-95.567134,29.893216],"type":"Point"}
}