{
  "type": "Feature",
  "properties": {
    "iso:country":"US",
    "sg:address":"1328 State Hwy 16",
    "sg:city":"Fredericksburg",
    "sg:classifiers":[
        {
            "category":"Health Services",
            "subcategory":"Clinic",
            "type":"Services"
        }
    ],
    "sg:phone":"+1 830 997 8023",
    "sg:postcode":"78624",
    "sg:province":"TX",
    "sg:tags":[
        "specialty",
        "outpatient"
    ],
    "wof:name":"Hill Country Cmnty Mhmr Ctr",
    "wof:placetype":"venue"
},
  "geometry": {"coordinates":[-98.89218700000001,30.254432],"type":"Point"}
}