{
  "type": "Feature",
  "properties": {
    "iso:country":"US",
    "sg:address":"824 Ash St",
    "sg:city":"Burleson",
    "sg:classifiers":[
        {
            "category":"Social Services",
            "subcategory":"Child Care",
            "type":"Services"
        }
    ],
    "sg:phone":"+1 817 447 6620",
    "sg:postcode":"76028",
    "sg:province":"TX",
    "sg:tags":[
        "day"
    ],
    "wof:name":"Carols Day Care",
    "wof:placetype":"venue"
},
  "geometry": {"coordinates":[-97.335869,32.530446],"type":"Point"}
}