{
  "type": "Feature",
  "properties": {
    "iso:country":"US",
    "sg:address":"1039 E 15th St",
    "sg:city":"Plano",
    "sg:classifiers":[
        {
            "category":"Education",
            "subcategory":"School",
            "type":"Public Place"
        }
    ],
    "sg:phone":"+1 972 423 7014",
    "sg:postcode":"75074",
    "sg:province":"TX",
    "wof:name":"North Texas Academy",
    "wof:placetype":"venue"
},
  "geometry": {"coordinates":[-96.699674,33.019766],"type":"Point"}
}