{
  "type": "Feature",
  "properties": {
    "iso:country":"US",
    "sg:address":"9950 Memorial Blvd",
    "sg:city":"Humble",
    "sg:classifiers":[
        {
            "category":"Professional",
            "type":"Services"
        }
    ],
    "sg:phone":"+1 281 540 5437",
    "sg:postcode":"77338",
    "sg:province":"TX",
    "wof:name":"Nelsoft Inc",
    "wof:placetype":"venue"
},
  "geometry": {"coordinates":[-95.27494799999999,29.994315],"type":"Point"}
}