{
  "type": "Feature",
  "properties": {
    "iso:country":"US",
    "sg:address":"5061 Westheimer Rd Ste 8020",
    "sg:city":"Houston",
    "sg:classifiers":[
        {
            "category":"Communications",
            "subcategory":"Newspaper",
            "type":"Services"
        },
        {
            "category":"Shopping",
            "subcategory":"Music",
            "type":"Retail Goods"
        },
        {
            "category":"Shopping",
            "subcategory":"Books",
            "type":"Retail Goods"
        }
    ],
    "sg:phone":"+1 713 960 0619",
    "sg:postcode":"77056",
    "sg:province":"TX",
    "sg:tags":[
        "magazine",
        "bookstore",
        "dvd's"
    ],
    "sg:website":"www.bordersstores.com",
    "wof:name":"Borders",
    "wof:placetype":"venue"
},
  "geometry": {"coordinates":[-95.462889,29.740662],"type":"Point"}
}