{
  "type": "Feature",
  "properties": {
    "iso:country":"US",
    "sg:address":"5080 Westheimer Rd",
    "sg:city":"Houston",
    "sg:classifiers":[
        {
            "category":"Shopping",
            "type":"Retail Goods"
        }
    ],
    "sg:phone":"+1 713 439 0198",
    "sg:postcode":"77056",
    "sg:province":"TX",
    "sg:tags":[
        "cards",
        "sport",
        "baseball",
        "memorabilia"
    ],
    "wof:name":"Field Of Dreams",
    "wof:placetype":"venue"
},
  "geometry": {"coordinates":[-95.462901,29.740777],"type":"Point"}
}