{
  "type": "Feature",
  "properties": {
    "iso:country":"US",
    "sg:address":"103 N Llano St",
    "sg:city":"Fredericksburg",
    "sg:classifiers":[
        {
            "category":"Health Services",
            "subcategory":"Doctor",
            "type":"Services"
        }
    ],
    "sg:phone":"+1 830 997 2550",
    "sg:postcode":"78624",
    "sg:province":"TX",
    "sg:tags":[
        "dentist"
    ],
    "wof:name":"David J Heinrich DDS",
    "wof:placetype":"venue"
},
  "geometry": {"coordinates":[-98.869507,30.274883],"type":"Point"}
}