{
  "type": "Feature",
  "properties": {
    "iso:country":"US",
    "sg:address":"317 Sesame Dr",
    "sg:city":"Mesquite",
    "sg:classifiers":[
        {
            "category":"Health Services",
            "subcategory":"Health Practitioner",
            "type":"Services"
        }
    ],
    "sg:phone":"+1 972 329 1993",
    "sg:postcode":"75149",
    "sg:province":"TX",
    "sg:tags":[
        "gambling",
        "addiction-information",
        "treatment"
    ],
    "wof:name":"Rehabworks Of Texas Inc",
    "wof:placetype":"venue"
},
  "geometry": {"coordinates":[-96.638091,32.770542],"type":"Point"}
}