{
  "type": "Feature",
  "properties": {
    "iso:country":"US",
    "sg:address":"5241 Hill Ridge Dr",
    "sg:city":"Fort Worth",
    "sg:classifiers":[
        {
            "category":"Building & Trades",
            "subcategory":"Construction",
            "type":"Services"
        }
    ],
    "sg:phone":"+1 817 238 0488",
    "sg:postcode":"76135",
    "sg:province":"TX",
    "sg:tags":[
        "house"
    ],
    "wof:name":"Constrction Prof Associatesinc",
    "wof:placetype":"venue"
},
  "geometry": {"coordinates":[-97.423693,32.828453],"type":"Point"}
}