{
  "type": "Feature",
  "properties": {
    "iso:country":"US",
    "sg:address":"945 Susan Dr",
    "sg:city":"Corpus Christi",
    "sg:classifiers":[
        {
            "category":"Professional",
            "subcategory":"Accounting & Tax Preparation",
            "type":"Services"
        }
    ],
    "sg:phone":"+1 361 993 7770",
    "sg:postcode":"78412",
    "sg:province":"TX",
    "wof:name":"Joann Wiedenhoeft",
    "wof:placetype":"venue"
},
  "geometry": {"coordinates":[-97.353669,27.709607],"type":"Point"}
}