{
  "type": "Feature",
  "properties": {
    "iso:country":"US",
    "sg:address":"8808-F Cullen Ln",
    "sg:city":"Austin",
    "sg:classifiers":[
        {
            "category":"Personal",
            "type":"Services"
        },
        {
            "category":"Retail",
            "subcategory":"Repair Shop",
            "type":"Services"
        },
        {
            "category":"Shopping",
            "subcategory":"Antiques",
            "type":"Retail Goods"
        }
    ],
    "sg:phone":"+1 512 282 1023",
    "sg:postcode":"78748",
    "sg:province":"TX",
    "sg:tags":[
        "home",
        "reupholstery",
        "furniture"
    ],
    "sg:website":"vmcupholstery.com",
    "wof:name":"VMC Upholstery",
    "wof:placetype":"venue"
},
  "geometry": {"coordinates":[-97.790873,30.171666],"type":"Point"}
}