{
  "type": "Feature",
  "properties": {
    "iso:country":"US",
    "sg:address":"3705 Vaucluse Dr",
    "sg:city":"Euless",
    "sg:classifiers":[
        {
            "category":"Professional",
            "subcategory":"Research",
            "type":"Services"
        }
    ],
    "sg:phone":"+1 817 684 4014",
    "sg:postcode":"76040",
    "sg:province":"TX",
    "sg:tags":[
        "commercial",
        "physical"
    ],
    "wof:name":"Neat Products",
    "wof:placetype":"venue"
},
  "geometry": {"coordinates":[-97.072604,32.816882],"type":"Point"}
}