{
  "type": "Feature",
  "properties": {
    "iso:country":"US",
    "sg:address":"3406 Rambling Pines Dr",
    "sg:city":"Kingwood",
    "sg:classifiers":[
        {
            "category":"Food & Beverages",
            "subcategory":"Groceries & Convenience Stores",
            "type":"Retail Goods"
        }
    ],
    "sg:phone":"+1 281 361 6770",
    "sg:postcode":"77345",
    "sg:province":"TX",
    "wof:name":"Cleveco Food Inc",
    "wof:placetype":"venue"
},
  "geometry": {"coordinates":[-95.16554600000001,30.063121],"type":"Point"}
}