{
  "type": "Feature",
  "properties": {
    "iso:country":"US",
    "sg:address":"3707 Hialeah Dr",
    "sg:city":"Arlington",
    "sg:classifiers":[
        {
            "category":"Manufacturing",
            "subcategory":"Chemicals & Compounds",
            "type":"Manufacturing & Wholesale Goods"
        }
    ],
    "sg:phone":"+1 817 465 8643",
    "sg:postcode":"76017",
    "sg:province":"TX",
    "sg:tags":[
        "product",
        "mfg"
    ],
    "wof:name":"World Spirit Unlimited",
    "wof:placetype":"venue"
},
  "geometry": {"coordinates":[-97.166071,32.665301],"type":"Point"}
}