{
  "type": "Feature",
  "properties": {
    "iso:country":"US",
    "sg:address":"6060 Long Dr",
    "sg:city":"Houston",
    "sg:classifiers":[
        {
            "category":"Food & Beverages",
            "subcategory":"Groceries & Convenience Stores",
            "type":"Retail Goods"
        }
    ],
    "sg:phone":"+1 713 641 1277",
    "sg:postcode":"77087",
    "sg:province":"TX",
    "wof:name":"Long Drive Food Mart",
    "wof:placetype":"venue"
},
  "geometry": {"coordinates":[-95.32089999999999,29.692801],"type":"Point"}
}