{
  "type": "Feature",
  "properties": {
    "iso:country":"US",
    "sg:address":"504 N Center St",
    "sg:city":"Sabinal",
    "sg:classifiers":[
        {
            "category":"Banks & Credit Unions",
            "subcategory":"Bank",
            "type":"Services"
        }
    ],
    "sg:phone":"+1 830 988 2465",
    "sg:postcode":"78881",
    "sg:province":"TX",
    "sg:tags":[
        "state"
    ],
    "wof:name":"First State Bank of Uvalde",
    "wof:placetype":"venue"
},
  "geometry": {"coordinates":[-99.467381,29.32246],"type":"Point"}
}