{
  "type": "Feature",
  "properties": {
    "iso:country":"US",
    "sg:address":"602 Red Bluff Rd",
    "sg:city":"Pasadena",
    "sg:classifiers":[
        {
            "category":"Wholesale",
            "subcategory":"Scrap",
            "type":"Manufacturing & Wholesale Goods"
        }
    ],
    "sg:phone":"+1 713 475 1200",
    "sg:postcode":"77506",
    "sg:province":"TX",
    "sg:tags":[
        "material"
    ],
    "wof:name":"San Jacinto Iron & Metal",
    "wof:placetype":"venue"
},
  "geometry": {"coordinates":[-95.203462,29.716832],"type":"Point"}
}