{
  "type": "Feature",
  "properties": {
    "iso:country":"US",
    "sg:address":"8505 Park Ln",
    "sg:city":"Tyler",
    "sg:classifiers":[
        {
            "category":"Shopping",
            "subcategory":"Crafts & Fabrics",
            "type":"Retail Goods"
        }
    ],
    "sg:phone":"+1 903 595 6960",
    "sg:postcode":"75708",
    "sg:province":"TX",
    "sg:tags":[
        "sewing"
    ],
    "wof:name":"Bbs",
    "wof:placetype":"venue"
},
  "geometry": {"coordinates":[-95.25044699999999,32.39293],"type":"Point"}
}