{
  "type": "Feature",
  "properties": {
    "iso:country":"US",
    "sg:address":"9900 Mearns Meadow Cove",
    "sg:city":"Austin",
    "sg:classifiers":[
        {
            "category":"Health Services",
            "subcategory":"Doctor",
            "type":"Services"
        }
    ],
    "sg:phone":"+1 512 836 2429",
    "sg:postcode":"78758",
    "sg:province":"TX",
    "wof:name":"Affordable Denatl Care Plus",
    "wof:placetype":"venue"
},
  "geometry": {"coordinates":[-97.703581,30.374126],"type":"Point"}
}