{
  "type": "Feature",
  "properties": {
    "iso:country":"US",
    "sg:address":"1613 Kingspoint Dr",
    "sg:city":"Carrollton",
    "sg:classifiers":[
        {
            "category":"Shopping",
            "subcategory":"Gifts & Souvenirs",
            "type":"Retail Goods"
        }
    ],
    "sg:phone":"+1 972 446 2777",
    "sg:postcode":"75007",
    "sg:province":"TX",
    "wof:name":"R Impex",
    "wof:placetype":"venue"
},
  "geometry": {"coordinates":[-96.900662,32.996068],"type":"Point"}
}