{
  "type": "Feature",
  "properties": {
    "iso:country":"US",
    "sg:address":"10176 Pooles Rd",
    "sg:city":"Montgomery",
    "sg:classifiers":[
        {
            "category":"Freight",
            "type":"Transportation"
        }
    ],
    "sg:phone":"+1 936 449 4756",
    "sg:postcode":"77356",
    "sg:province":"TX",
    "sg:tags":[
        "consultant"
    ],
    "wof:name":"Freight Tec",
    "wof:placetype":"venue"
},
  "geometry": {"coordinates":[-95.734469,30.393403],"type":"Point"}
}