{
  "type": "Feature",
  "properties": {
    "iso:country":"US",
    "sg:address":"2704 E 2nd St",
    "sg:city":"Austin",
    "sg:classifiers":[
        {
            "category":"Organizations",
            "subcategory":"Religious Organization",
            "type":"Services"
        }
    ],
    "sg:phone":"+1 512 322 0910",
    "sg:postcode":"78702",
    "sg:province":"TX",
    "sg:tags":[
        "church"
    ],
    "wof:name":"Centro Evangelico",
    "wof:placetype":"venue"
},
  "geometry": {"coordinates":[-97.713521,30.254457],"type":"Point"}
}