{
  "type": "Feature",
  "properties": {
    "iso:country":"US",
    "sg:address":"2133 Chicago Ave",
    "sg:city":"Mcallen",
    "sg:classifiers":[
        {
            "category":"Government",
            "subcategory":"Police Station",
            "type":"Public Place"
        }
    ],
    "sg:phone":"+1 956 972 7469",
    "sg:postcode":"78501",
    "sg:province":"TX",
    "sg:tags":[
        "department"
    ],
    "wof:name":"Mc Allen Community Policing",
    "wof:placetype":"venue"
},
  "geometry": {"coordinates":[-98.243251,26.202525],"type":"Point"}
}