{
  "type": "Feature",
  "properties": {
    "iso:country":"US",
    "sg:address":"3816 Orchid Ave",
    "sg:city":"Mcallen",
    "sg:classifiers":[
        {
            "category":"Place Of Worship",
            "subcategory":"Church",
            "type":"Public Place"
        },
        {
            "category":"Place Of Worship",
            "type":"Public Place"
        }
    ],
    "sg:phone":"+1 956 631 9028",
    "sg:postcode":"78504",
    "sg:province":"TX",
    "sg:tags":[
        "christ",
        "churches-community"
    ],
    "wof:name":"Valley Community Church",
    "wof:placetype":"venue"
},
  "geometry": {"coordinates":[-98.256271,26.244038],"type":"Point"}
}