{
  "type": "Feature",
  "properties": {
    "iso:country":"US",
    "sg:address":"2830 W Elm St",
    "sg:city":"Denison",
    "sg:classifiers":[
        {
            "category":"Building & Trades",
            "subcategory":"Construction",
            "type":"Services"
        }
    ],
    "sg:phone":"+1 903 465 5350",
    "sg:postcode":"75020",
    "sg:province":"TX",
    "sg:tags":[
        "residential",
        "contractor"
    ],
    "wof:name":"Anderson Construction",
    "wof:placetype":"venue"
},
  "geometry": {"coordinates":[-96.580843,33.765345],"type":"Point"}
}