{
  "type": "Feature",
  "properties": {
    "iso:country":"US",
    "sg:address":"207 W Hickory St",
    "sg:city":"Denton",
    "sg:classifiers":[
        {
            "category":"Health Services",
            "subcategory":"Doctor",
            "type":"Services"
        },
        {
            "category":"Health Services",
            "subcategory":"Clinic",
            "type":"Services"
        },
        {
            "category":"Social Services",
            "type":"Services"
        }
    ],
    "sg:phone":"+1 940 243 9367",
    "sg:postcode":"76201",
    "sg:province":"TX",
    "sg:tags":[
        "physician",
        "mental",
        "family",
        "information",
        "surgeons",
        "individual",
        "marriage",
        "child",
        "psychiatry",
        "surgeon",
        "counselor"
    ],
    "sg:website":"http://www.psychiatryandcounseling.com",
    "wof:name":"Psychiatry and Counseling",
    "wof:placetype":"venue"
},
  "geometry": {"coordinates":[-97.134153,33.214518],"type":"Point"}
}