{
  "type": "Feature",
  "properties": {
    "iso:country":"US",
    "sg:address":"2002 N Galloway Ave Ste E",
    "sg:city":"Mesquite",
    "sg:classifiers":[
        {
            "category":"Personal",
            "subcategory":"Tanning Parlor",
            "type":"Services"
        }
    ],
    "sg:phone":"+1 972 329 0005",
    "sg:postcode":"75149",
    "sg:province":"TX",
    "sg:website":"www.palmbeachtan.com",
    "wof:name":"Palm Beach Tan",
    "wof:placetype":"venue"
},
  "geometry": {"coordinates":[-96.610298,32.7906],"type":"Point"}
}