{
  "type": "Feature",
  "properties": {
    "iso:country":"US",
    "sg:address":"625 Albrook Dr",
    "sg:city":"Allen",
    "sg:classifiers":[
        {
            "category":"Organizations",
            "subcategory":"Religious Organization",
            "type":"Services"
        }
    ],
    "sg:phone":"+1 972 359 0059",
    "sg:postcode":"75002",
    "sg:province":"TX",
    "wof:name":"Bible Verse T-Shirts",
    "wof:placetype":"venue"
},
  "geometry": {"coordinates":[-96.66818499999999,33.073551],"type":"Point"}
}