{
  "type": "Feature",
  "properties": {
    "iso:country":"US",
    "sg:address":"7710 Colony St",
    "sg:city":"Houston",
    "sg:classifiers":[
        {
            "category":"Shopping",
            "type":"Retail Goods"
        }
    ],
    "sg:phone":"+1 713 981 0013",
    "sg:postcode":"77036",
    "sg:province":"TX",
    "sg:tags":[
        "merchandise"
    ],
    "wof:name":"Fur Feathers & Fins",
    "wof:placetype":"venue"
},
  "geometry": {"coordinates":[-95.548782,29.694277],"type":"Point"}
}