{
  "type": "Feature",
  "properties": {
    "iso:country":"US",
    "sg:address":"11615 Angus Rd",
    "sg:city":"Austin",
    "sg:classifiers":[
        {
            "category":"Professional",
            "subcategory":"Lawyer & Legal Services",
            "type":"Services"
        }
    ],
    "sg:phone":"+1 512 343 6262",
    "sg:postcode":"78759",
    "sg:province":"TX",
    "wof:name":"Blake K Jensen",
    "wof:placetype":"venue"
},
  "geometry": {"coordinates":[-97.743285,30.415609],"type":"Point"}
}