{
  "type": "Feature",
  "properties": {
    "iso:country":"US",
    "sg:address":"2603 Augusta Dr",
    "sg:city":"Houston",
    "sg:classifiers":[
        {
            "category":"Professional",
            "subcategory":"Lawyer & Legal Services",
            "type":"Services"
        }
    ],
    "sg:phone":"+1 713 520 9100",
    "sg:postcode":"77057",
    "sg:province":"TX",
    "sg:tags":[
        "attorney",
        "estate",
        "wills",
        "practice",
        "planning",
        "trust"
    ],
    "wof:name":"Simpson Stephen",
    "wof:placetype":"venue"
},
  "geometry": {"coordinates":[-95.48250299999999,29.739251],"type":"Point"}
}