{
  "type": "Feature",
  "properties": {
    "iso:country":"US",
    "sg:address":"2900 Atkinson Dr",
    "sg:city":"Lufkin",
    "sg:classifiers":[
        {
            "category":"Retail",
            "subcategory":"Repair Shop",
            "type":"Services"
        }
    ],
    "sg:phone":"+1 936 634 8505",
    "sg:postcode":"75901",
    "sg:province":"TX",
    "sg:tags":[
        "compressor",
        "air"
    ],
    "wof:name":"Thompson Air Compressor",
    "wof:placetype":"venue"
},
  "geometry": {"coordinates":[-94.687156,31.356002],"type":"Point"}
}