{
  "type": "Feature",
  "properties": {
    "iso:country":"US",
    "sg:address":"1560 Roberts Ave",
    "sg:city":"Beaumont",
    "sg:classifiers":[
        {
            "category":"Shopping",
            "type":"Retail Goods"
        }
    ],
    "sg:phone":"+1 409 833 4027",
    "sg:postcode":"77701",
    "sg:province":"TX",
    "sg:tags":[
        "merchandise"
    ],
    "wof:name":"North End Resale Shop",
    "wof:placetype":"venue"
},
  "geometry": {"coordinates":[-94.10018100000001,30.060138],"type":"Point"}
}