{
  "type": "Feature",
  "properties": {
    "iso:country":"US",
    "sg:address":"35 Crockett Dr",
    "sg:city":"Tulia",
    "sg:classifiers":[
        {
            "category":"Building & Trades",
            "subcategory":"Landscaping Services",
            "type":"Services"
        }
    ],
    "sg:phone":"+1 806 995 2526",
    "sg:postcode":"79088",
    "sg:province":"TX",
    "wof:name":"Tulia Lawn Care",
    "wof:placetype":"venue"
},
  "geometry": {"coordinates":[-101.760756,34.548939],"type":"Point"}
}