{
  "type": "Feature",
  "properties": {
    "iso:country":"US",
    "sg:address":"6922 Mobud Dr",
    "sg:city":"Houston",
    "sg:classifiers":[
        {
            "category":"Manufacturing",
            "subcategory":"Metals",
            "type":"Manufacturing & Wholesale Goods"
        },
        {
            "category":"Shopping",
            "type":"Retail Goods"
        }
    ],
    "sg:phone":"+1 713 777 0069",
    "sg:postcode":"77074",
    "sg:province":"TX",
    "sg:tags":[
        "trophy",
        "product",
        "mfg",
        "fabricated",
        "award",
        "medal"
    ],
    "wof:name":"Classic Crystal and Glass",
    "wof:placetype":"venue"
},
  "geometry": {"coordinates":[-95.508112,29.701333],"type":"Point"}
}