{
  "type": "Feature",
  "properties": {
    "iso:country":"US",
    "sg:address":"1425 Co Rd 180",
    "sg:city":"Cisco",
    "sg:classifiers":[
        {
            "category":"Retail",
            "subcategory":"Auto Repair",
            "type":"Services"
        }
    ],
    "sg:phone":"+1 254 442 1858",
    "sg:postcode":"76437",
    "sg:province":"TX",
    "sg:tags":[
        "automotive"
    ],
    "wof:name":"Justice Truck Service",
    "wof:placetype":"venue"
},
  "geometry": {"coordinates":[-98.928376,32.322755],"type":"Point"}
}