{
  "type": "Feature",
  "properties": {
    "iso:country":"US",
    "sg:address":"511 E John Carpenter Fwy",
    "sg:city":"Irving",
    "sg:classifiers":[
        {
            "category":"Professional",
            "subcategory":"Management & Consulting",
            "type":"Services"
        }
    ],
    "sg:phone":"+1 972 556 1660",
    "sg:postcode":"75062",
    "sg:province":"TX",
    "sg:tags":[
        "personnel",
        "consultant"
    ],
    "wof:name":"Thorn Network Inc",
    "wof:placetype":"venue"
},
  "geometry": {"coordinates":[-96.93262799999999,32.858483],"type":"Point"}
}