{
  "type": "Feature",
  "properties": {
    "iso:country":"US",
    "sg:address":"621 N Alamo St",
    "sg:city":"San Antonio",
    "sg:classifiers":[
        {
            "category":"Health Services",
            "subcategory":"Doctor",
            "type":"Services"
        }
    ],
    "sg:phone":"+1 210 227 5223",
    "sg:postcode":"78215",
    "sg:province":"TX",
    "sg:tags":[
        "physician",
        "surgeon"
    ],
    "wof:name":"Gregory L Lilly MD",
    "wof:placetype":"venue"
},
  "geometry": {"coordinates":[-98.48281900000001,29.431063],"type":"Point"}
}