{
  "type": "Feature",
  "properties": {
    "iso:country":"US",
    "sg:address":"1790 Millard St",
    "sg:city":"Plano",
    "sg:classifiers":[
        {
            "category":"Building & Trades",
            "subcategory":"Construction",
            "type":"Services"
        }
    ],
    "sg:phone":"+1 972 422 0374",
    "sg:postcode":"75074",
    "sg:province":"TX",
    "sg:tags":[
        "builder",
        "patio",
        "deck"
    ],
    "sg:website":"www.reeddeck.com",
    "wof:name":"Reed Fence & Deck Co",
    "wof:placetype":"venue"
},
  "geometry": {"coordinates":[-96.685182,33.016552],"type":"Point"}
}