{
  "type": "Feature",
  "properties": {
    "iso:country":"US",
    "sg:address":"6428 Ridglea Dr",
    "sg:city":"Fort Worth",
    "sg:classifiers":[
        {
            "category":"Wholesale",
            "subcategory":"Machinery & Supplies",
            "type":"Manufacturing & Wholesale Goods"
        },
        {
            "category":"Professional",
            "type":"Services"
        }
    ],
    "sg:phone":"+1 817 427 2060",
    "sg:postcode":"76148",
    "sg:province":"TX",
    "sg:tags":[
        "control",
        "equipment",
        "industrial",
        "establishment"
    ],
    "wof:name":"Westec Instruments Inc",
    "wof:placetype":"venue"
},
  "geometry": {"coordinates":[-97.245901,32.882848],"type":"Point"}
}