{
  "type": "Feature",
  "properties": {
    "iso:country":"US",
    "sg:address":"402 Hillcrest St",
    "sg:city":"Mansfield",
    "sg:classifiers":[
        {
            "category":"Retail",
            "subcategory":"Laundry & Dry Cleaning",
            "type":"Services"
        }
    ],
    "sg:phone":"+1 817 477 5351",
    "sg:postcode":"76063",
    "sg:province":"TX",
    "sg:tags":[
        "cleaners",
        "rug",
        "carpet"
    ],
    "wof:name":"Clean Paws Carpet Cleaning",
    "wof:placetype":"venue"
},
  "geometry": {"coordinates":[-97.129153,32.558195],"type":"Point"}
}