{
  "type": "Feature",
  "properties": {
    "iso:country":"US",
    "sg:address":"316 Main St",
    "sg:city":"Mont Belvieu",
    "sg:classifiers":[
        {
            "category":"Professional",
            "type":"Services"
        }
    ],
    "sg:phone":"+1 281 576 5147",
    "sg:postcode":"77545",
    "sg:province":"TX",
    "sg:tags":[
        "establishment"
    ],
    "wof:name":"Texas Brine Corp",
    "wof:placetype":"venue"
},
  "geometry": {"coordinates":[-95.444138,29.537677],"type":"Point"}
}