{
  "type": "Feature",
  "properties": {
    "iso:country":"US",
    "sg:address":"18351 Kuykendahl Rd",
    "sg:city":"Spring",
    "sg:classifiers":[
        {
            "category":"Building & Trades",
            "subcategory":"Plumbing",
            "type":"Services"
        }
    ],
    "sg:phone":"+1 281 924 9656",
    "sg:postcode":"77379",
    "sg:province":"TX",
    "sg:tags":[
        "contractor"
    ],
    "wof:name":"Mechanical Solutions",
    "wof:placetype":"venue"
},
  "geometry": {"coordinates":[-95.486923,30.037929],"type":"Point"}
}