{
  "type": "Feature",
  "properties": {
    "iso:country":"US",
    "sg:address":"102 S Lockwood Dr",
    "sg:city":"Houston",
    "sg:classifiers":[
        {
            "category":"Professional",
            "subcategory":"Lawyer & Legal Services",
            "type":"Services"
        }
    ],
    "sg:phone":"+1 713 522 3232",
    "sg:postcode":"77011",
    "sg:province":"TX",
    "wof:name":"Rodriguez & Associates",
    "wof:placetype":"venue"
},
  "geometry": {"coordinates":[-95.327499,29.7467],"type":"Point"}
}