{
  "type": "Feature",
  "properties": {
    "iso:country":"US",
    "sg:address":"1305 Airport Fwy",
    "sg:city":"Bedford",
    "sg:classifiers":[
        {
            "category":"Health Services",
            "subcategory":"Doctor",
            "type":"Services"
        }
    ],
    "sg:phone":"+1 817 267 6290",
    "sg:postcode":"76021",
    "sg:province":"TX",
    "sg:tags":[
        "medical"
    ],
    "wof:name":"Midcity Neurology",
    "wof:placetype":"venue"
},
  "geometry": {"coordinates":[-97.14227099999999,32.837317],"type":"Point"}
}