{
  "type": "Feature",
  "properties": {
    "iso:country":"US",
    "sg:address":"14801 Calaveras Dr",
    "sg:city":"Austin",
    "sg:classifiers":[
        {
            "category":"Professional",
            "subcategory":"Management & Consulting",
            "type":"Services"
        }
    ],
    "sg:phone":"+1 512 238 8780",
    "sg:postcode":"78717",
    "sg:province":"TX",
    "sg:tags":[
        "computer",
        "custom"
    ],
    "wof:name":"Weisz Choice",
    "wof:placetype":"venue"
},
  "geometry": {"coordinates":[-97.769936,30.489752],"type":"Point"}
}