{
  "type": "Feature",
  "properties": {
    "iso:country":"US",
    "sg:address":"2212 Arlington Downs Rd Ste 100",
    "sg:city":"Arlington",
    "sg:phone":"+1 817 640 8898",
    "sg:postcode":"76011",
    "sg:province":"TX",
    "sg:website":"http://www.royaldigitalimaging.com",
    "wof:name":"Royal Digital Imaging",
    "wof:placetype":"venue"
},
  "geometry": {"coordinates":[-97.071994,32.750333],"type":"Point"}
}