{
  "type": "Feature",
  "properties": {
    "iso:country":"US",
    "sg:address":"2544 Culebra Rd",
    "sg:city":"San Antonio",
    "sg:classifiers":[
        {
            "category":"Personal",
            "subcategory":"Beauty Salon",
            "type":"Services"
        }
    ],
    "sg:phone":"+1 210 438 1774",
    "sg:postcode":"78228",
    "sg:province":"TX",
    "sg:tags":[
        "manicuring"
    ],
    "wof:name":"Sylvia's Nails",
    "wof:placetype":"venue"
},
  "geometry": {"coordinates":[-98.547929,29.44747],"type":"Point"}
}