{
  "type": "Feature",
  "properties": {
    "iso:country":"US",
    "sg:address":"1606 Heather Glen Ct",
    "sg:city":"Richardson",
    "sg:classifiers":[
        {
            "category":"Home & Garden",
            "subcategory":"Home Furnishings",
            "type":"Retail Goods"
        }
    ],
    "sg:phone":"+1 972 644 5060",
    "sg:postcode":"75081",
    "sg:province":"TX",
    "wof:name":"John-Ping Lu",
    "wof:placetype":"venue"
},
  "geometry": {"coordinates":[-96.69810699999999,32.967951],"type":"Point"}
}