{
  "type": "Feature",
  "properties": {
    "iso:country":"US",
    "sg:address":"110 W Freddy Gonzalez Dr",
    "sg:city":"Edinburg",
    "sg:classifiers":[
        {
            "category":"Restaurant",
            "type":"Food & Drink"
        }
    ],
    "sg:phone":"+1 956 316 0185",
    "sg:postcode":"78539",
    "sg:province":"TX",
    "wof:name":"Diana's Mexican Cafe",
    "wof:placetype":"venue"
},
  "geometry": {"coordinates":[-98.166051,26.286982],"type":"Point"}
}