{
  "type": "Feature",
  "properties": {
    "iso:country":"US",
    "sg:address":"911 S Eastman Rd",
    "sg:city":"Longview",
    "sg:classifiers":[
        {
            "category":"Retail",
            "subcategory":"Auto Repair",
            "type":"Services"
        }
    ],
    "sg:phone":"+1 903 757 3158",
    "sg:postcode":"75602",
    "sg:province":"TX",
    "sg:tags":[
        "muffler",
        "exhaust",
        "system"
    ],
    "wof:name":"Alvarado Muffler & Co Inc",
    "wof:placetype":"venue"
},
  "geometry": {"coordinates":[-94.707447,32.480922],"type":"Point"}
}