{
  "type": "Feature",
  "properties": {
    "iso:country":"US",
    "sg:address":"5637 W Lovers Ln",
    "sg:city":"Dallas",
    "sg:classifiers":[
        {
            "category":"Shopping",
            "subcategory":"Gifts & Souvenirs",
            "type":"Retail Goods"
        }
    ],
    "sg:phone":"+1 214 350 8737",
    "sg:postcode":"75209",
    "sg:province":"TX",
    "sg:tags":[
        "antique",
        "repair"
    ],
    "wof:name":"New Asia Art Shop",
    "wof:placetype":"venue"
},
  "geometry": {"coordinates":[-96.81590300000001,32.851299],"type":"Point"}
}