{
  "type": "Feature",
  "properties": {
    "iso:country":"US",
    "sg:address":"7965 Co Rd 418",
    "sg:city":"Melissa",
    "sg:classifiers":[
        {
            "category":"Farming",
            "subcategory":"Livestock Farm",
            "type":"Manufacturing & Wholesale Goods"
        }
    ],
    "sg:phone":"+1 972 838 4136",
    "sg:postcode":"75454",
    "sg:province":"TX",
    "sg:tags":[
        "animal",
        "general"
    ],
    "wof:name":"Collin County Ranch",
    "wof:placetype":"venue"
},
  "geometry": {"coordinates":[-96.53894200000001,33.304951],"type":"Point"}
}