{
  "type": "Feature",
  "properties": {
    "iso:country":"US",
    "sg:address":"6859 Arapaho Rd",
    "sg:city":"Dallas",
    "sg:classifiers":[
        {
            "category":"Home & Garden",
            "subcategory":"Hardware",
            "type":"Retail Goods"
        }
    ],
    "sg:phone":"+1 972 408 7308",
    "sg:postcode":"75248",
    "sg:province":"TX",
    "wof:name":"Handyman Harware",
    "wof:placetype":"venue"
},
  "geometry": {"coordinates":[-96.790633,32.96233],"type":"Point"}
}