{
  "type": "Feature",
  "properties": {
    "iso:country":"US",
    "sg:address":"615 N Upper Broadway St",
    "sg:city":"Corpus Christi",
    "sg:classifiers":[
        {
            "category":"Professional",
            "subcategory":"Advertising",
            "type":"Services"
        }
    ],
    "sg:phone":"+1 361 885 0500",
    "sg:postcode":"78401",
    "sg:province":"TX",
    "wof:name":"Source",
    "wof:placetype":"venue"
},
  "geometry": {"coordinates":[-97.396393,27.79711],"type":"Point"}
}