{
  "type": "Feature",
  "properties": {
    "iso:country":"US",
    "sg:address":"4335 Alysheba Ln",
    "sg:city":"Friendswood",
    "sg:classifiers":[
        {
            "category":"Professional",
            "subcategory":"Business Services",
            "type":"Services"
        }
    ],
    "sg:phone":"+1 281 996 5565",
    "sg:postcode":"77546",
    "sg:province":"TX",
    "sg:tags":[
        "organizing",
        "services-household"
    ],
    "wof:name":"Contract Cash Management",
    "wof:placetype":"venue"
},
  "geometry": {"coordinates":[-95.174629,29.545041],"type":"Point"}
}