{
  "type": "Feature",
  "properties": {
    "iso:country":"US",
    "sg:address":"4703 Jacksboro Hwy",
    "sg:city":"Wichita Falls",
    "sg:classifiers":[
        {
            "category":"Mining & Drilling",
            "type":"Manufacturing & Wholesale Goods"
        }
    ],
    "sg:phone":"+1 940 766 0620",
    "sg:postcode":"76302",
    "sg:province":"TX",
    "sg:tags":[
        "field",
        "oil",
        "specialty"
    ],
    "wof:name":"Tumbleweed Specialties",
    "wof:placetype":"venue"
},
  "geometry": {"coordinates":[-98.494496,33.858726],"type":"Point"}
}