{
  "type": "Feature",
  "properties": {
    "iso:country":"US",
    "sg:address":"112 W Tarrant St",
    "sg:city":"Bowie",
    "sg:classifiers":[
        {
            "category":"Food & Beverages",
            "subcategory":"Specialty",
            "type":"Retail Goods"
        }
    ],
    "sg:phone":"+1 940 872 1399",
    "sg:postcode":"76230",
    "sg:province":"TX",
    "sg:tags":[
        "diet",
        "health",
        "salons-equipment",
        "beauty",
        "supply"
    ],
    "wof:name":"Betty's Health and Beauty",
    "wof:placetype":"venue"
},
  "geometry": {"coordinates":[-97.848555,33.560218],"type":"Point"}
}