{
  "type": "Feature",
  "properties": {
    "iso:country":"US",
    "sg:address":"5802 Briar St",
    "sg:city":"Amarillo",
    "sg:classifiers":[
        {
            "category":"Professional",
            "subcategory":"Management & Consulting",
            "type":"Services"
        }
    ],
    "sg:phone":"+1 806 353 1984",
    "sg:postcode":"79109",
    "sg:province":"TX",
    "wof:name":"Ncc & Assoc",
    "wof:placetype":"venue"
},
  "geometry": {"coordinates":[-101.896434,35.147519],"type":"Point"}
}