{
  "type": "Feature",
  "properties": {
    "iso:country":"US",
    "sg:address":"4200 Wynn Ln",
    "sg:city":"Mesquite",
    "sg:classifiers":[
        {
            "category":"Personal",
            "subcategory":"Beauty Salon",
            "type":"Services"
        }
    ],
    "sg:phone":"+1 972 286 6848",
    "sg:postcode":"75180",
    "sg:province":"TX",
    "wof:name":"'Flair's For You'",
    "wof:placetype":"venue"
},
  "geometry": {"coordinates":[-96.606461,32.713032],"type":"Point"}
}