{
  "type": "Feature",
  "properties": {
    "iso:country":"US",
    "sg:address":"1815 Nederland Ave",
    "sg:city":"Nederland",
    "sg:classifiers":[
        {
            "category":"Retail",
            "subcategory":"Auto Repair",
            "type":"Services"
        }
    ],
    "sg:phone":"+1 409 527 9984",
    "sg:postcode":"77627",
    "sg:province":"TX",
    "sg:tags":[
        "muffler",
        "exhaust",
        "brake",
        "system"
    ],
    "sg:website":"http://www.tomtracker.com/redirect.cfm?bID=4837&hID=111353",
    "wof:name":"Meineke Car Care Center",
    "wof:placetype":"venue"
},
  "geometry": {"coordinates":[-93.993696,29.96996],"type":"Point"}
}