{
  "type": "Feature",
  "properties": {
    "iso:country":"US",
    "sg:address":"32 Kenneth Dr",
    "sg:city":"Euless",
    "sg:classifiers":[
        {
            "category":"Social Services",
            "subcategory":"Child Care",
            "type":"Services"
        }
    ],
    "sg:phone":"+1 817 267 7182",
    "sg:postcode":"76040",
    "sg:province":"TX",
    "wof:name":"Glenda G Robinette",
    "wof:placetype":"venue"
},
  "geometry": {"coordinates":[-97.078186,32.823583],"type":"Point"}
}