{
  "type": "Feature",
  "properties": {
    "iso:country":"US",
    "sg:address":"6851 NE Loop 820 Suite 110",
    "sg:city":"North Richland Hills",
    "sg:classifiers":[
        {
            "category":"Professional",
            "subcategory":"Computer Services",
            "type":"Services"
        }
    ],
    "sg:phone":"+1 682 738 6867",
    "sg:postcode":"76180",
    "sg:province":"TX",
    "sg:website":"http://www.skeds.com",
    "wof:name":"SKEDS",
    "wof:placetype":"venue"
},
  "geometry": {"coordinates":[-97.231347,32.840098],"type":"Point"}
}