{
  "type": "Feature",
  "properties": {
    "iso:country":"US",
    "sg:address":"708 S Tennessee St",
    "sg:city":"Mckinney",
    "sg:classifiers":[
        {
            "category":"Health Services",
            "subcategory":"Doctor",
            "type":"Services"
        },
        {
            "category":"Health Services",
            "subcategory":"Clinic",
            "type":"Services"
        }
    ],
    "sg:phone":"+1 972 562 0660",
    "sg:postcode":"75069",
    "sg:province":"TX",
    "sg:tags":[
        "physician",
        "surgeon",
        "mental"
    ],
    "wof:name":"Community Support Program Csp",
    "wof:placetype":"venue"
},
  "geometry": {"coordinates":[-96.615624,33.191435],"type":"Point"}
}