{
  "type": "Feature",
  "properties": {
    "iso:country":"US",
    "sg:address":"1523 Ave P",
    "sg:city":"Huntsville",
    "sg:classifiers":[
        {
            "category":"Professional",
            "subcategory":"Management & Consulting",
            "type":"Services"
        }
    ],
    "sg:phone":"+1 936 577 0772",
    "sg:postcode":"77340",
    "sg:province":"TX",
    "wof:name":"K & H Marketing",
    "wof:placetype":"venue"
},
  "geometry": {"coordinates":[-95.557194,30.718156],"type":"Point"}
}