{
  "type": "Feature",
  "properties": {
    "iso:country":"US",
    "sg:address":"8292 Thaxton Rd",
    "sg:city":"Austin",
    "sg:classifiers":[
        {
            "category":"Professional",
            "subcategory":"Management & Consulting",
            "type":"Services"
        }
    ],
    "sg:phone":"+1 512 280 1483",
    "sg:postcode":"78747",
    "sg:province":"TX",
    "sg:tags":[
        "consultant",
        "educational"
    ],
    "wof:name":"Advanced Human Dev Concepts",
    "wof:placetype":"venue"
},
  "geometry": {"coordinates":[-97.73265499999999,30.151114],"type":"Point"}
}