{
  "type": "Feature",
  "properties": {
    "iso:country":"US",
    "sg:address":"113 Blue Star",
    "sg:city":"San Antonio",
    "sg:classifiers":[
        {
            "category":"Professional",
            "subcategory":"Computer Services",
            "type":"Services"
        }
    ],
    "sg:phone":"+1 210 224 7171",
    "sg:postcode":"78204",
    "sg:province":"TX",
    "sg:tags":[
        "attorney",
        "typing",
        "bureau",
        "for",
        "evidence"
    ],
    "wof:name":"Platen Company",
    "wof:placetype":"venue"
},
  "geometry": {"coordinates":[-98.495234,29.407705],"type":"Point"}
}