{
  "type": "Feature",
  "properties": {
    "iso:country":"US",
    "sg:address":"704 S Sam Rayburn Fwy",
    "sg:city":"Sherman",
    "sg:classifiers":[
        {
            "category":"Communications",
            "subcategory":"Radio Station",
            "type":"Services"
        }
    ],
    "sg:phone":"+1 903 870 0472",
    "sg:postcode":"75090",
    "sg:province":"TX",
    "sg:tags":[
        "company",
        "broadcasting"
    ],
    "wof:name":"KTBK Radio",
    "wof:placetype":"venue"
},
  "geometry": {"coordinates":[-96.614405,33.629375],"type":"Point"}
}