{
  "type": "Feature",
  "properties": {
    "iso:country":"US",
    "sg:address":"16555 Park Row",
    "sg:city":"Houston",
    "sg:classifiers":[
        {
            "category":"Shopping",
            "subcategory":"Department Store",
            "type":"Retail Goods"
        }
    ],
    "sg:phone":"+1 281 492 2400",
    "sg:postcode":"77084",
    "sg:province":"TX",
    "wof:name":"Sears Roebuck and Co Inc",
    "wof:placetype":"venue"
},
  "geometry": {"coordinates":[-95.66963800000001,29.789264],"type":"Point"}
}