{
  "type": "Feature",
  "properties": {
    "iso:country":"US",
    "sg:address":"7223 Wynnwood Ln",
    "sg:city":"Houston",
    "sg:classifiers":[
        {
            "category":"Professional",
            "subcategory":"Business Services",
            "type":"Services"
        }
    ],
    "sg:phone":"+1 713 861 0427",
    "sg:postcode":"77008",
    "sg:province":"TX",
    "wof:name":"Fulfillplus Inc",
    "wof:placetype":"venue"
},
  "geometry": {"coordinates":[-95.448627,29.793152],"type":"Point"}
}