{
  "type": "Feature",
  "properties": {
    "iso:country":"US",
    "sg:address":"10702 Stone Canyon Rd",
    "sg:city":"Dallas",
    "sg:classifiers":[
        {
            "category":"Shopping",
            "subcategory":"Bicycles & Sporting Goods",
            "type":"Retail Goods"
        }
    ],
    "sg:phone":"+1 214 691 1199",
    "sg:postcode":"75230",
    "sg:province":"TX",
    "wof:name":"Intertex Group",
    "wof:placetype":"venue"
},
  "geometry": {"coordinates":[-96.774154,32.893056],"type":"Point"}
}