{
  "type": "Feature",
  "properties": {
    "iso:country":"US",
    "sg:address":"12 Bayvilla Dr",
    "sg:city":"Baytown",
    "sg:classifiers":[
        {
            "category":"Real Estate",
            "subcategory":"Real Estate Agent",
            "type":"Services"
        }
    ],
    "sg:phone":"+1 281 838 3535",
    "sg:postcode":"77520",
    "sg:province":"TX",
    "sg:tags":[
        "industry",
        "mfg"
    ],
    "wof:name":"Michael K Loeb",
    "wof:placetype":"venue"
},
  "geometry": {"coordinates":[-95.02747599999999,29.742209],"type":"Point"}
}