{
  "type": "Feature",
  "properties": {
    "iso:country":"US",
    "sg:address":"7111 Bill Hughes Rd",
    "sg:city":"Austin",
    "sg:classifiers":[
        {
            "category":"Professional",
            "type":"Services"
        }
    ],
    "sg:phone":"+1 512 441 6239",
    "sg:postcode":"78745",
    "sg:province":"TX",
    "wof:name":"Forte Danial Writer",
    "wof:placetype":"venue"
},
  "geometry": {"coordinates":[-97.787857,30.191291],"type":"Point"}
}