{
  "type": "Feature",
  "properties": {
    "iso:country":"US",
    "sg:address":"734 S Timberland Dr",
    "sg:city":"Lufkin",
    "sg:classifiers":[
        {
            "category":"Food & Beverages",
            "subcategory":"Groceries & Convenience Stores",
            "type":"Retail Goods"
        }
    ],
    "sg:phone":"+1 936 639 5754",
    "sg:postcode":"75901",
    "sg:province":"TX",
    "sg:tags":[
        "grocer"
    ],
    "wof:name":"Save-A-Lot",
    "wof:placetype":"venue"
},
  "geometry": {"coordinates":[-94.723196,31.330274],"type":"Point"}
}