{
  "type": "Feature",
  "properties": {
    "iso:country":"US",
    "sg:address":"7505 W 7th St",
    "sg:city":"Texarkana",
    "sg:classifiers":[
        {
            "category":"Personal",
            "type":"Services"
        }
    ],
    "sg:phone":"+1 903 831 5125",
    "sg:postcode":"75501",
    "sg:province":"TX",
    "sg:tags":[
        "equipment"
    ],
    "wof:name":"Blessed Beginnings",
    "wof:placetype":"venue"
},
  "geometry": {"coordinates":[-94.156851,33.406664],"type":"Point"}
}