{
  "type": "Feature",
  "properties": {
    "iso:country":"US",
    "sg:address":"2505 N Stemmons Fwy",
    "sg:city":"Dallas",
    "sg:classifiers":[
        {
            "category":"Shopping",
            "subcategory":"Hobbies, Toys, & Games",
            "type":"Retail Goods"
        },
        {
            "category":"Shopping",
            "subcategory":"Thrift Store",
            "type":"Retail Goods"
        },
        {
            "category":"Manufacturing",
            "subcategory":"Building Materials",
            "type":"Manufacturing & Wholesale Goods"
        },
        {
            "category":"Shopping Center",
            "type":"Public Place"
        },
        {
            "category":"Home & Garden",
            "subcategory":"Carpets & Floor Coverings",
            "type":"Retail Goods"
        }
    ],
    "sg:phone":"+1 214 634 2505",
    "sg:postcode":"75207",
    "sg:province":"TX",
    "sg:tags":[
        "fixtures-used",
        "show",
        "garment",
        "fixture",
        "rack",
        "case",
        "mannequins-display",
        "display"
    ],
    "sg:website":"http://www.modernstore.com",
    "wof:name":"Modern Store Fixtures",
    "wof:placetype":"venue"
},
  "geometry": {"coordinates":[-96.83810099999999,32.805133],"type":"Point"}
}