{
  "type": "Feature",
  "properties": {
    "iso:country":"US",
    "sg:address":"5109 Ohio Garden Rd",
    "sg:city":"River Oaks",
    "sg:classifiers":[
        {
            "category":"Freight",
            "type":"Transportation"
        }
    ],
    "sg:phone":"+1 817 975 2575",
    "sg:postcode":"76114",
    "sg:province":"TX",
    "sg:tags":[
        "mover"
    ],
    "wof:name":"ABH Movers",
    "wof:placetype":"venue"
},
  "geometry": {"coordinates":[-97.399789,32.777092],"type":"Point"}
}