{
  "type": "Feature",
  "properties": {
    "iso:country":"US",
    "sg:address":"1839 Stella Ave",
    "sg:city":"Dallas",
    "sg:classifiers":[
        {
            "category":"Shopping",
            "subcategory":"Computers & Home Electronics",
            "type":"Retail Goods"
        }
    ],
    "sg:phone":"+1 214 878 1134",
    "sg:postcode":"75203",
    "sg:province":"TX",
    "sg:tags":[
        "hardware",
        "supply"
    ],
    "wof:name":"Deville Enterprises",
    "wof:placetype":"venue"
},
  "geometry": {"coordinates":[-96.79609000000001,32.730325],"type":"Point"}
}