{
  "type": "Feature",
  "properties": {
    "iso:country":"US",
    "sg:address":"1311 E Gentry Pkwy",
    "sg:city":"Tyler",
    "sg:classifiers":[
        {
            "category":"Retail",
            "subcategory":"Auto Repair",
            "type":"Services"
        }
    ],
    "sg:phone":"+1 903 526 5060",
    "sg:postcode":"75702",
    "sg:province":"TX",
    "sg:tags":[
        "repairing",
        "automobile"
    ],
    "wof:name":"Portillo's Auto Svc",
    "wof:placetype":"venue"
},
  "geometry": {"coordinates":[-95.29279200000001,32.360569],"type":"Point"}
}