{
  "type": "Feature",
  "properties": {
    "iso:country":"US",
    "sg:address":"219 Jordy Ln",
    "sg:city":"Dickinson",
    "sg:classifiers":[
        {
            "category":"Manufacturing",
            "subcategory":"Printing",
            "type":"Manufacturing & Wholesale Goods"
        }
    ],
    "sg:phone":"+1 281 614 0645",
    "sg:postcode":"77539",
    "sg:province":"TX",
    "sg:tags":[
        "lithographer",
        "commercial",
        "lithographic"
    ],
    "wof:name":"Pivotal Designs & Printing",
    "wof:placetype":"venue"
},
  "geometry": {"coordinates":[-95.02153800000001,29.472784],"type":"Point"}
}