{
  "type": "Feature",
  "properties": {
    "iso:country":"US",
    "sg:address":"5400 Lyndon B Johnson Fwy",
    "sg:city":"Dallas",
    "sg:classifiers":[
        {
            "category":"Banks & Credit Unions",
            "subcategory":"Investment Brokerage",
            "type":"Services"
        }
    ],
    "sg:phone":"+1 972 701 9106",
    "sg:postcode":"75240",
    "sg:province":"TX",
    "sg:tags":[
        "security",
        "exploration"
    ],
    "wof:name":"Texakoma Financial Inc",
    "wof:placetype":"venue"
},
  "geometry": {"coordinates":[-96.816131,32.925481],"type":"Point"}
}