{
  "type": "Feature",
  "properties": {
    "iso:country":"US",
    "sg:address":"7105 Tram Rd",
    "sg:city":"Beaumont",
    "sg:classifiers":[
        {
            "category":"Food & Beverages",
            "subcategory":"Groceries & Convenience Stores",
            "type":"Retail Goods"
        }
    ],
    "sg:phone":"+1 409 892 0898",
    "sg:postcode":"77713",
    "sg:province":"TX",
    "wof:name":"Tri Stop",
    "wof:placetype":"venue"
},
  "geometry": {"coordinates":[-94.18896700000001,30.171131],"type":"Point"}
}