{
  "type": "Feature",
  "properties": {
    "iso:country":"US",
    "sg:address":"11516 Gulf Fwy",
    "sg:city":"Houston",
    "sg:classifiers":[
        {
            "category":"Shopping",
            "subcategory":"Clothing, Apparel, & Fashions",
            "type":"Retail Goods"
        }
    ],
    "sg:phone":"+1 713 941 5100",
    "sg:postcode":"77034",
    "sg:province":"TX",
    "sg:tags":[
        "shop",
        "occasion",
        "bridal",
        "dress",
        "special"
    ],
    "wof:name":"Davids Bridal",
    "wof:placetype":"venue"
},
  "geometry": {"coordinates":[-95.21008999999999,29.610741],"type":"Point"}
}