{
  "type": "Feature",
  "properties": {
    "iso:country":"US",
    "sg:address":"2518 Sand Castle Ct",
    "sg:city":"Seabrook",
    "sg:classifiers":[
        {
            "category":"Local Transit",
            "type":"Transportation"
        }
    ],
    "sg:phone":"+1 281 291 0347",
    "sg:postcode":"77586",
    "sg:province":"TX",
    "sg:tags":[
        "passenger"
    ],
    "wof:name":"Covenant Limousine Servic",
    "wof:placetype":"venue"
},
  "geometry": {"coordinates":[-95.03134900000001,29.586519],"type":"Point"}
}