{
  "type": "Feature",
  "properties": {
    "iso:country":"US",
    "sg:address":"4603 Stanley Rd",
    "sg:city":"Texarkana",
    "sg:classifiers":[
        {
            "category":"Building & Trades",
            "subcategory":"Construction",
            "type":"Services"
        }
    ],
    "sg:phone":"+1 870 772 7360",
    "sg:postcode":"71854",
    "sg:province":"TX",
    "sg:tags":[
        "concrete",
        "contractor"
    ],
    "wof:name":"Asphalt Driveway Service",
    "wof:placetype":"venue"
},
  "geometry": {"coordinates":[-93.98120299999999,33.377134],"type":"Point"}
}