{
  "type": "Feature",
  "properties": {
    "iso:country":"US",
    "sg:address":"1200 Brittmoore Rd",
    "sg:city":"Houston",
    "sg:classifiers":[
        {
            "category":"Wholesale",
            "subcategory":"Furniture",
            "type":"Manufacturing & Wholesale Goods"
        }
    ],
    "sg:phone":"+1 713 461 3278",
    "sg:postcode":"77043",
    "sg:province":"TX",
    "sg:tags":[
        "recycling",
        "center"
    ],
    "sg:website":"http://www.avsecuritydestruction.com",
    "wof:name":"Av Security Destruction",
    "wof:placetype":"venue"
},
  "geometry": {"coordinates":[-95.569841,29.79152],"type":"Point"}
}