{
  "type": "Feature",
  "properties": {
    "iso:country":"US",
    "sg:address":"219 34th St",
    "sg:city":"Lubbock",
    "sg:classifiers":[
        {
            "category":"Freight",
            "type":"Transportation"
        }
    ],
    "sg:phone":"+1 806 687 0142",
    "sg:postcode":"79404",
    "sg:province":"TX",
    "sg:tags":[
        "delivery"
    ],
    "wof:name":"Marquis Messengers Southwest",
    "wof:placetype":"venue"
},
  "geometry": {"coordinates":[-101.83593500000001,33.563314],"type":"Point"}
}