{
  "type": "Feature",
  "properties": {
    "iso:country":"US",
    "sg:address":"200 S Weaver St",
    "sg:city":"Gainesville",
    "sg:classifiers":[
        {
            "category":"Education",
            "subcategory":"Library",
            "type":"Public Place"
        }
    ],
    "sg:phone":"+1 940 665 2401",
    "sg:postcode":"76240",
    "sg:province":"TX",
    "wof:name":"Cooke County Library",
    "wof:placetype":"venue"
},
  "geometry": {"coordinates":[-97.147921,33.623642],"type":"Point"}
}