{
  "type": "Feature",
  "properties": {
    "iso:country":"US",
    "sg:address":"205 S 26th St",
    "sg:city":"Waco",
    "sg:classifiers":[
        {
            "category":"Building & Trades",
            "subcategory":"Construction",
            "type":"Services"
        }
    ],
    "sg:phone":"+1 254 752 3696",
    "sg:postcode":"76710",
    "sg:province":"TX",
    "sg:tags":[
        "painting",
        "painter",
        "contractor"
    ],
    "wof:name":"Peters Painting Co Inc",
    "wof:placetype":"venue"
},
  "geometry": {"coordinates":[-97.149368,31.538135],"type":"Point"}
}