{
  "type": "Feature",
  "properties": {
    "iso:country":"US",
    "sg:address":"11110 Metric Blvd Ste A",
    "sg:city":"Austin",
    "sg:classifiers":[
        {
            "category":"Personal",
            "type":"Services"
        }
    ],
    "sg:phone":"+1 512 467 9927",
    "sg:postcode":"78758",
    "sg:province":"TX",
    "sg:tags":[
        "home",
        "local"
    ],
    "sg:website":"Broadviewsecurity.com",
    "wof:name":"Broadview Security",
    "wof:placetype":"venue"
},
  "geometry": {"coordinates":[-97.710142,30.391822],"type":"Point"}
}