{
  "type": "Feature",
  "properties": {
    "iso:country":"US",
    "sg:address":"5829 Secrest Dr",
    "sg:city":"Austin",
    "sg:classifiers":[
        {
            "category":"Professional",
            "type":"Services"
        }
    ],
    "sg:phone":"+1 512 377 1665",
    "sg:postcode":"78759",
    "sg:province":"TX",
    "sg:tags":[
        "establishment"
    ],
    "wof:name":"Techmate Inc",
    "wof:placetype":"venue"
},
  "geometry": {"coordinates":[-97.753226,30.420544],"type":"Point"}
}