{
  "type": "Feature",
  "properties": {
    "iso:country":"US",
    "sg:address":"4311 Harvest Hill Rd",
    "sg:city":"Carrollton",
    "sg:classifiers":[
        {
            "category":"Professional",
            "subcategory":"Accounting & Tax Preparation",
            "type":"Services"
        }
    ],
    "sg:phone":"+1 972 394 6748",
    "sg:postcode":"75010",
    "sg:province":"TX",
    "sg:tags":[
        "billing"
    ],
    "wof:name":"Total Medical Billing",
    "wof:placetype":"venue"
},
  "geometry": {"coordinates":[-96.868188,33.030329],"type":"Point"}
}