{
  "type": "Feature",
  "properties": {
    "iso:country":"US",
    "sg:address":"4790 Pittman Rd",
    "sg:city":"Adkins",
    "sg:classifiers":[
        {
            "category":"Manufacturing",
            "subcategory":"Tools & Machinery",
            "type":"Manufacturing & Wholesale Goods"
        }
    ],
    "sg:phone":"+1 210 649 2165",
    "sg:postcode":"78101",
    "sg:province":"TX",
    "sg:tags":[
        "building",
        "equipment",
        "construction"
    ],
    "wof:name":"Lloyd Kosub Company Inc",
    "wof:placetype":"venue"
},
  "geometry": {"coordinates":[-98.224386,29.373346],"type":"Point"}
}