{
  "type": "Feature",
  "properties": {
    "iso:country":"US",
    "sg:address":"5040 Cedar Creek Dr",
    "sg:city":"Houston",
    "sg:classifiers":[
        {
            "category":"Airline",
            "type":"Transportation"
        }
    ],
    "sg:phone":"+1 713 623 2544",
    "sg:postcode":"77056",
    "sg:province":"TX",
    "sg:tags":[
        "equipment",
        "courier",
        "air"
    ],
    "wof:name":"Russian Texas Shipping Corp",
    "wof:placetype":"venue"
},
  "geometry": {"coordinates":[-95.46336599999999,29.753116],"type":"Point"}
}