{
  "type": "Feature",
  "properties": {
    "iso:country":"US",
    "sg:address":"311 NW 11th St",
    "sg:city":"Seminole",
    "sg:classifiers":[
        {
            "category":"Retail",
            "subcategory":"Auto Repair",
            "type":"Services"
        }
    ],
    "sg:phone":"+1 432 758 8188",
    "sg:postcode":"79360",
    "sg:province":"NM",
    "sg:tags":[
        "automotive"
    ],
    "wof:name":"Pdq Lube & Car Wash",
    "wof:placetype":"venue"
},
  "geometry": {"coordinates":[-102.657174,32.724454],"type":"Point"}
}