{
  "type": "Feature",
  "properties": {
    "iso:country":"US",
    "sg:address":"21710 Forest Waters Cir",
    "sg:city":"San Antonio",
    "sg:classifiers":[
        {
            "category":"Personal",
            "type":"Services"
        }
    ],
    "sg:phone":"+1 210 651 5896",
    "sg:postcode":"78266",
    "sg:province":"TX",
    "wof:name":"USA Wedding Mall Inc",
    "wof:placetype":"venue"
},
  "geometry": {"coordinates":[-98.31588499999999,29.640176],"type":"Point"}
}