{
  "type": "Feature",
  "properties": {
    "iso:country":"US",
    "sg:address":"333 Stagecoach Trl",
    "sg:city":"San Marcos",
    "sg:classifiers":[
        {
            "category":"Education",
            "subcategory":"School",
            "type":"Public Place"
        }
    ],
    "sg:phone":"+1 512 393 6100",
    "sg:postcode":"78666",
    "sg:province":"TX",
    "wof:name":"Maria Hernandez School",
    "wof:placetype":"venue"
},
  "geometry": {"coordinates":[-97.967827,29.865748],"type":"Point"}
}