{
  "type": "Feature",
  "properties": {
    "iso:country":"US",
    "sg:address":"1414 N Elm St",
    "sg:city":"Denton",
    "sg:classifiers":[
        {
            "category":"Personal",
            "subcategory":"Beauty Salon",
            "type":"Services"
        }
    ],
    "sg:phone":"+1 940 898 1532",
    "sg:postcode":"76201",
    "sg:province":"TX",
    "sg:tags":[
        "shop"
    ],
    "wof:name":"Elm Solsn Unigue",
    "wof:placetype":"venue"
},
  "geometry": {"coordinates":[-97.133455,33.227681],"type":"Point"}
}