{
  "type": "Feature",
  "properties": {
    "iso:country":"US",
    "sg:address":"111 Congress Ave Ste 530",
    "sg:city":"Austin",
    "sg:classifiers":[
        {
            "category":"Real Estate",
            "subcategory":"Real Estate Services",
            "type":"Services"
        }
    ],
    "sg:phone":"+1 512 474 2664",
    "sg:postcode":"78701",
    "sg:province":"TX",
    "sg:tags":[
        "management",
        "property"
    ],
    "wof:name":"Greystar Management Services",
    "wof:placetype":"venue"
},
  "geometry": {"coordinates":[-97.744499,30.2635],"type":"Point"}
}