{
  "type": "Feature",
  "properties": {
    "iso:country":"US",
    "sg:address":"7301 W County Road 48",
    "sg:city":"Midland",
    "sg:classifiers":[
        {
            "category":"Farming",
            "subcategory":"Livestock Farm",
            "type":"Manufacturing & Wholesale Goods"
        },
        {
            "category":"Arena",
            "subcategory":"Horse Racetrack",
            "type":"Entertainment"
        }
    ],
    "sg:phone":"+1 432 689 4873",
    "sg:postcode":"79707",
    "sg:province":"TX",
    "sg:tags":[
        "breeder"
    ],
    "wof:name":"Shaody Horse Farm",
    "wof:placetype":"venue"
},
  "geometry": {"coordinates":[-102.19976800000001,32.034312],"type":"Point"}
}