{
  "type": "Feature",
  "properties": {
    "iso:country":"US",
    "sg:address":"116 Plum St",
    "sg:city":"Luling",
    "sg:classifiers":[
        {
            "category":"Professional",
            "subcategory":"Management & Consulting",
            "type":"Services"
        }
    ],
    "sg:phone":"+1 830 875 6757",
    "sg:postcode":"78648",
    "sg:province":"TX",
    "sg:tags":[
        "education"
    ],
    "wof:name":"George A Grantham",
    "wof:placetype":"venue"
},
  "geometry": {"coordinates":[-97.646158,29.672986],"type":"Point"}
}