{
  "type": "Feature",
  "properties": {
    "iso:country":"US",
    "sg:address":"6203 Lawford Ln",
    "sg:city":"Houston",
    "sg:classifiers":[
        {
            "category":"Home & Garden",
            "subcategory":"Building Materials",
            "type":"Retail Goods"
        },
        {
            "category":"Building & Trades",
            "subcategory":"Construction",
            "type":"Services"
        }
    ],
    "sg:phone":"+1 713 880 9933",
    "sg:postcode":"77040",
    "sg:province":"TX",
    "sg:tags":[
        "concrete",
        "foundation",
        "staining",
        "contractor"
    ],
    "wof:name":"Boswell Construction Co",
    "wof:placetype":"venue"
},
  "geometry": {"coordinates":[-95.53169,29.856398],"type":"Point"}
}