{
  "type": "Feature",
  "properties": {
    "iso:country":"US",
    "sg:address":"1175 Austin Rd",
    "sg:city":"Luling",
    "sg:classifiers":[
        {
            "category":"Mining & Drilling",
            "type":"Manufacturing & Wholesale Goods"
        }
    ],
    "sg:phone":"+1 830 875 2270",
    "sg:postcode":"78648",
    "sg:province":"TX",
    "sg:tags":[
        "oil",
        "well"
    ],
    "wof:name":"Jimchem Chemical Co",
    "wof:placetype":"venue"
},
  "geometry": {"coordinates":[-97.677069,29.690524],"type":"Point"}
}