{
  "type": "Feature",
  "properties": {
    "iso:country":"US",
    "sg:address":"7200 Military Dr",
    "sg:city":"Abilene",
    "sg:classifiers":[
        {
            "category":"Manufacturing",
            "subcategory":"Printing",
            "type":"Manufacturing & Wholesale Goods"
        }
    ],
    "sg:phone":"+1 325 692 0837",
    "sg:postcode":"79605",
    "sg:province":"TX",
    "sg:tags":[
        "book"
    ],
    "wof:name":"Dreams Texas Publishing",
    "wof:placetype":"venue"
},
  "geometry": {"coordinates":[-99.84585199999999,32.438891],"type":"Point"}
}