{
  "type": "Feature",
  "properties": {
    "iso:country":"US",
    "sg:address":"3418 W Holcombe Blvd",
    "sg:city":"Houston",
    "sg:classifiers":[
        {
            "category":"Autos & Motor Vehicles",
            "subcategory":"Automobile Sales",
            "type":"Retail Goods"
        }
    ],
    "sg:phone":"+1 713 669 8600",
    "sg:postcode":"77025",
    "sg:province":"TX",
    "sg:tags":[
        "tank",
        "trailer"
    ],
    "wof:name":"Jack Olsta Company",
    "wof:placetype":"venue"
},
  "geometry": {"coordinates":[-95.430026,29.706144],"type":"Point"}
}