{
  "type": "Feature",
  "properties": {
    "iso:country":"US",
    "sg:address":"3703 Cherry Ln",
    "sg:city":"Austin",
    "sg:classifiers":[
        {
            "category":"Professional",
            "type":"Services"
        }
    ],
    "sg:phone":"+1 512 478 2139",
    "sg:postcode":"78703",
    "sg:province":"TX",
    "wof:name":"William Roger Louis",
    "wof:placetype":"venue"
},
  "geometry": {"coordinates":[-97.78272,30.29803],"type":"Point"}
}