{
  "type": "Feature",
  "properties": {
    "iso:country":"US",
    "sg:address":"3827 N 10th St",
    "sg:city":"Mcallen",
    "sg:classifiers":[
        {
            "category":"Professional",
            "subcategory":"Lawyer & Legal Services",
            "type":"Services"
        }
    ],
    "sg:phone":"+1 956 687 2010",
    "sg:postcode":"78501",
    "sg:province":"TX",
    "wof:name":"McGee David Lee Law Offices PC",
    "wof:placetype":"venue"
},
  "geometry": {"coordinates":[-98.22412799999999,26.238148],"type":"Point"}
}