{
  "type": "Feature",
  "properties": {
    "iso:country":"US",
    "sg:address":"963 Wakefield Dr",
    "sg:city":"Houston",
    "sg:classifiers":[
        {
            "category":"Building & Trades",
            "subcategory":"Construction",
            "type":"Services"
        }
    ],
    "sg:phone":"+1 713 249 2785",
    "sg:postcode":"77018",
    "sg:province":"TX",
    "sg:tags":[
        "house"
    ],
    "wof:name":"Joyce Homes Inc",
    "wof:placetype":"venue"
},
  "geometry": {"coordinates":[-95.422269,29.821418],"type":"Point"}
}