{
  "type": "Feature",
  "properties": {
    "iso:country":"US",
    "sg:address":"3237 Sharpview Cir",
    "sg:city":"Dallas",
    "sg:classifiers":[
        {
            "category":"Professional",
            "subcategory":"Art Services",
            "type":"Services"
        }
    ],
    "sg:phone":"+1 214 321 9835",
    "sg:postcode":"75228",
    "sg:province":"TX",
    "sg:tags":[
        "graphic",
        "designer"
    ],
    "sg:website":"http://www.lottsofdesign.com",
    "wof:name":"Lotts Off Design",
    "wof:placetype":"venue"
},
  "geometry": {"coordinates":[-96.698295,32.796172],"type":"Point"}
}