{
  "type": "Feature",
  "properties": {
    "iso:country":"US",
    "sg:address":"204 N Houston St",
    "sg:city":"Granbury",
    "sg:classifiers":[
        {
            "category":"Wholesale",
            "subcategory":"Non-durable Goods",
            "type":"Manufacturing & Wholesale Goods"
        }
    ],
    "sg:phone":"+1 817 579 1865",
    "sg:postcode":"76048",
    "sg:province":"TX",
    "wof:name":"Art Cashe",
    "wof:placetype":"venue"
},
  "geometry": {"coordinates":[-97.78758000000001,32.444226],"type":"Point"}
}