{
  "type": "Feature",
  "properties": {
    "iso:country":"US",
    "sg:address":"703 Carrol Dr",
    "sg:city":"Laredo",
    "sg:classifiers":[
        {
            "category":"Insurance",
            "subcategory":"Hazard Insurance",
            "type":"Services"
        }
    ],
    "sg:phone":"+1 956 791 4748",
    "sg:postcode":"78045",
    "sg:province":"TX",
    "sg:tags":[
        "bond"
    ],
    "wof:name":"Gonzalez Bail Bonds",
    "wof:placetype":"venue"
},
  "geometry": {"coordinates":[-99.480289,27.583277],"type":"Point"}
}