{
  "type": "Feature",
  "properties": {
    "iso:country":"US",
    "sg:address":"10228 Panther Ridge Trl",
    "sg:city":"Dallas",
    "sg:classifiers":[
        {
            "category":"Professional",
            "type":"Services"
        }
    ],
    "sg:phone":"+1 972 644 9478",
    "sg:postcode":"75243",
    "sg:province":"TX",
    "wof:name":"Jimenez Marina B",
    "wof:placetype":"venue"
},
  "geometry": {"coordinates":[-96.706945,32.929201],"type":"Point"}
}