{
  "type": "Feature",
  "properties": {
    "iso:country":"US",
    "sg:address":"3512 Stone Creek Ln S",
    "sg:city":"Fort Worth",
    "sg:classifiers":[
        {
            "category":"Real Estate",
            "subcategory":"Real Estate Agent",
            "type":"Services"
        }
    ],
    "sg:phone":"+1 817 429 5966",
    "sg:postcode":"76137",
    "sg:province":"TX",
    "wof:name":"Jerry Lee Barton",
    "wof:placetype":"venue"
},
  "geometry": {"coordinates":[-97.30667200000001,32.860202],"type":"Point"}
}