{
  "type": "Feature",
  "properties": {
    "iso:country":"US",
    "sg:address":"2245 Highway 62 S",
    "sg:city":"Orange",
    "sg:classifiers":[
        {
            "category":"Travel",
            "subcategory":"Hotels & Motels",
            "type":"Entertainment"
        }
    ],
    "sg:phone":"+1 409 745 9393",
    "sg:postcode":"77630",
    "sg:province":"TX",
    "sg:tags":[
        "lodging"
    ],
    "sg:website":"http://www.sleepinn.com/hotel-orange-texas-TXB75",
    "wof:name":"Sleep Inn and Suites Orange",
    "wof:placetype":"venue"
},
  "geometry": {"coordinates":[-93.819965,30.096075],"type":"Point"}
}