{
  "type": "Feature",
  "properties": {
    "iso:country":"US",
    "sg:address":"4902 Lakeridge Dr",
    "sg:city":"Lubbock",
    "sg:classifiers":[
        {
            "category":"Insurance",
            "subcategory":"Hazard Insurance",
            "type":"Services"
        }
    ],
    "sg:phone":"+1 806 765 7264",
    "sg:postcode":"79424",
    "sg:province":"TX",
    "sg:tags":[
        "employee",
        "benefit",
        "compensation",
        "plan"
    ],
    "sg:website":"www.iabenefits.com",
    "wof:name":"Insurance Associates",
    "wof:placetype":"venue"
},
  "geometry": {"coordinates":[-101.917204,33.518336],"type":"Point"}
}