{
  "type": "Feature",
  "properties": {
    "iso:country":"US",
    "sg:address":"4323 S Hampton Rd",
    "sg:city":"Dallas",
    "sg:classifiers":[
        {
            "category":"Health Services",
            "subcategory":"Doctor",
            "type":"Services"
        }
    ],
    "sg:phone":"+1 214 330 7777",
    "sg:postcode":"75232",
    "sg:province":"TX",
    "wof:name":"Red Bird Emergency Center",
    "wof:placetype":"venue"
},
  "geometry": {"coordinates":[-96.857201,32.690701],"type":"Point"}
}