{
  "type": "Feature",
  "properties": {
    "iso:country":"US",
    "sg:address":"116 N Main Ave",
    "sg:city":"Big Lake",
    "sg:classifiers":[
        {
            "category":"Organizations",
            "subcategory":"Non-profit Organization",
            "type":"Services"
        },
        {
            "category":"Organizations",
            "subcategory":"Membership Organization",
            "type":"Services"
        }
    ],
    "sg:phone":"+1 325 884 9804",
    "sg:postcode":"76932",
    "sg:province":"TX",
    "sg:tags":[
        "charitable",
        "institution"
    ],
    "wof:name":"Friends For Hope Inc",
    "wof:placetype":"venue"
},
  "geometry": {"coordinates":[-101.461843,31.191378],"type":"Point"}
}