{
  "type": "Feature",
  "properties": {
    "iso:country":"US",
    "sg:address":"8912 Chancellor Row",
    "sg:city":"Dallas",
    "sg:classifiers":[
        {
            "category":"Shopping",
            "subcategory":"Stationery & Office Supplies",
            "type":"Retail Goods"
        }
    ],
    "sg:phone":"+1 214 631 4650",
    "sg:postcode":"75247",
    "sg:province":"TX",
    "sg:tags":[
        "equipment"
    ],
    "wof:name":"Team Office Partners Inc",
    "wof:placetype":"venue"
},
  "geometry": {"coordinates":[-96.887703,32.819401],"type":"Point"}
}