{
  "type": "Feature",
  "properties": {
    "iso:country":"US",
    "sg:address":"5330 Manchaca Rd",
    "sg:city":"Austin",
    "sg:classifiers":[
        {
            "category":"Organizations",
            "subcategory":"Professional Association",
            "type":"Services"
        }
    ],
    "sg:phone":"+1 512 892 3037",
    "sg:postcode":"78745",
    "sg:province":"TX",
    "sg:tags":[
        "sale"
    ],
    "wof:name":"Portraits By Curtis",
    "wof:placetype":"venue"
},
  "geometry": {"coordinates":[-97.7955,30.21842],"type":"Point"}
}