{
  "type": "Feature",
  "properties": {
    "iso:country":"US",
    "sg:address":"311 Augusta Dr",
    "sg:city":"Huntsville",
    "sg:classifiers":[
        {
            "category":"Professional",
            "subcategory":"Business Services",
            "type":"Services"
        }
    ],
    "sg:phone":"+1 936 295 1934",
    "sg:postcode":"77340",
    "sg:province":"TX",
    "wof:name":"Janmarco Inc",
    "wof:placetype":"venue"
},
  "geometry": {"coordinates":[-95.51752999999999,30.666867],"type":"Point"}
}