{
  "type": "Feature",
  "properties": {
    "iso:country":"US",
    "sg:address":"311 E Vickery Blvd",
    "sg:city":"Fort Worth",
    "sg:classifiers":[
        {
            "category":"Wholesale",
            "subcategory":"Hardware",
            "type":"Manufacturing & Wholesale Goods"
        }
    ],
    "sg:phone":"+1 817 336 0451",
    "sg:postcode":"76104",
    "sg:province":"TX",
    "sg:tags":[
        "air",
        "parts",
        "conditioning",
        "supply"
    ],
    "sg:website":"www.morsco.com",
    "wof:name":"Morrison Supply Co",
    "wof:placetype":"venue"
},
  "geometry": {"coordinates":[-97.32346800000001,32.743593],"type":"Point"}
}