{
  "type": "Feature",
  "properties": {
    "iso:country":"US",
    "sg:address":"673 Ridgewood Dr",
    "sg:city":"Port Neches",
    "sg:classifiers":[
        {
            "category":"Banks & Credit Unions",
            "subcategory":"Financial Services",
            "type":"Services"
        }
    ],
    "sg:phone":"+1 409 724 2046",
    "sg:postcode":"77651",
    "sg:province":"TX",
    "sg:tags":[
        "investor"
    ],
    "wof:name":"B&C Hometown Investments LLC",
    "wof:placetype":"venue"
},
  "geometry": {"coordinates":[-93.96617500000001,29.961169],"type":"Point"}
}