{
  "type": "Feature",
  "properties": {
    "iso:country":"US",
    "sg:address":"610 Middleway Rd",
    "sg:city":"Pflugerville",
    "sg:classifiers":[
        {
            "category":"Shopping",
            "subcategory":"Books",
            "type":"Retail Goods"
        }
    ],
    "sg:phone":"+1 512 799 6732",
    "sg:postcode":"78660",
    "sg:province":"TX",
    "wof:name":"A & Personalized Books Et",
    "wof:placetype":"venue"
},
  "geometry": {"coordinates":[-97.610074,30.42851],"type":"Point"}
}