{
  "type": "Feature",
  "properties": {
    "iso:country":"US",
    "sg:address":"554 Briarcliff Dr",
    "sg:city":"Garland",
    "sg:classifiers":[
        {
            "category":"Freight",
            "type":"Transportation"
        }
    ],
    "sg:phone":"+1 972 613 4405",
    "sg:postcode":"75043",
    "sg:province":"TX",
    "sg:tags":[
        "arrangement"
    ],
    "wof:name":"Special Transport Inc",
    "wof:placetype":"venue"
},
  "geometry": {"coordinates":[-96.610699,32.840882],"type":"Point"}
}