{
  "type": "Feature",
  "properties": {
    "iso:country":"US",
    "sg:address":"14713 Bulverde Rd",
    "sg:city":"San Antonio",
    "sg:classifiers":[
        {
            "category":"Professional",
            "type":"Services"
        }
    ],
    "sg:phone":"+1 210 495 8222",
    "sg:postcode":"78247",
    "sg:province":"TX",
    "wof:name":"Maverick Outdoor Media",
    "wof:placetype":"venue"
},
  "geometry": {"coordinates":[-98.41869,29.574979],"type":"Point"}
}