{
  "type": "Feature",
  "properties": {
    "iso:country":"US",
    "sg:address":"5130 Chromite St Apt P5",
    "sg:city":"El Paso",
    "sg:classifiers":[
        {
            "category":"Real Estate",
            "subcategory":"Real Estate Operator",
            "type":"Services"
        }
    ],
    "sg:phone":"+1 915 581 2089",
    "sg:postcode":"79932",
    "sg:province":"TX",
    "sg:tags":[
        "apartment"
    ],
    "wof:name":"El Pavon Apartments",
    "wof:placetype":"venue"
},
  "geometry": {"coordinates":[-106.581001,31.8465],"type":"Point"}
}