{
  "type": "Feature",
  "properties": {
    "iso:country":"US",
    "sg:address":"219 Alexander Ct",
    "sg:city":"Irving",
    "sg:classifiers":[
        {
            "category":"Manufacturing",
            "subcategory":"Building Materials",
            "type":"Manufacturing & Wholesale Goods"
        }
    ],
    "sg:phone":"+1 972 438 4363",
    "sg:postcode":"75061",
    "sg:province":"TX",
    "sg:tags":[
        "mfg"
    ],
    "wof:name":"Eagle Solar Screens",
    "wof:placetype":"venue"
},
  "geometry": {"coordinates":[-96.944149,32.826799],"type":"Point"}
}