{
  "type": "Feature",
  "properties": {
    "iso:country":"US",
    "sg:address":"603 E US Hwy 69",
    "sg:city":"Denison",
    "sg:classifiers":[
        {
            "category":"Health Services",
            "subcategory":"Nursing And Care Facility",
            "type":"Services"
        }
    ],
    "sg:phone":"+1 903 465 2438",
    "sg:postcode":"75021",
    "sg:province":"TX",
    "sg:tags":[
        "home",
        "convalescent"
    ],
    "wof:name":"Denison Manor",
    "wof:placetype":"venue"
},
  "geometry": {"coordinates":[-96.52633400000001,33.73748],"type":"Point"}
}