{
  "type": "Feature",
  "properties": {
    "iso:country":"US",
    "sg:address":"981 Redwing Dr",
    "sg:city":"Coppell",
    "sg:classifiers":[
        {
            "category":"Professional",
            "subcategory":"Business Services",
            "type":"Services"
        }
    ],
    "sg:phone":"+1 972 304 8840",
    "sg:postcode":"75019",
    "sg:province":"TX",
    "wof:name":"Louisiana Bay",
    "wof:placetype":"venue"
},
  "geometry": {"coordinates":[-96.962295,32.958794],"type":"Point"}
}