{
  "type": "Feature",
  "properties": {
    "iso:country":"US",
    "sg:address":"6203 Cheena Dr",
    "sg:city":"Houston",
    "sg:classifiers":[
        {
            "category":"Shopping",
            "subcategory":"Gifts & Souvenirs",
            "type":"Retail Goods"
        }
    ],
    "sg:phone":"+1 281 497 8162",
    "sg:postcode":"77096",
    "sg:province":"TX",
    "wof:name":"Confetti",
    "wof:placetype":"venue"
},
  "geometry": {"coordinates":[-95.50061599999999,29.66841],"type":"Point"}
}