{
  "type": "Feature",
  "properties": {
    "iso:country":"US",
    "sg:address":"4705 Cypress Ave",
    "sg:city":"Wichita Falls",
    "sg:classifiers":[
        {
            "category":"Building & Trades",
            "subcategory":"Construction",
            "type":"Services"
        }
    ],
    "sg:phone":"+1 940 691 2221",
    "sg:postcode":"76310",
    "sg:province":"TX",
    "sg:tags":[
        "foundation"
    ],
    "wof:name":"L & L Foundation & House Lvlng",
    "wof:placetype":"venue"
},
  "geometry": {"coordinates":[-98.56841799999999,33.856759],"type":"Point"}
}