{
  "type": "Feature",
  "properties": {
    "iso:country":"US",
    "sg:address":"914 Bray St",
    "sg:city":"Cedar Hill",
    "sg:classifiers":[
        {
            "category":"Home & Garden",
            "subcategory":"Furniture",
            "type":"Retail Goods"
        }
    ],
    "sg:phone":"+1 972 293 0877",
    "sg:postcode":"75104",
    "sg:province":"TX",
    "wof:name":"OBrien Family Furniture",
    "wof:placetype":"venue"
},
  "geometry": {"coordinates":[-96.928287,32.594544],"type":"Point"}
}