{
  "type": "Feature",
  "properties": {
    "iso:country":"US",
    "sg:address":"18005 Gregg Bluff Rd",
    "sg:city":"Leander",
    "sg:classifiers":[
        {
            "category":"Building & Trades",
            "subcategory":"Construction",
            "type":"Services"
        }
    ],
    "sg:phone":"+1 512 267 2908",
    "sg:postcode":"78645",
    "sg:province":"TX",
    "sg:tags":[
        "house"
    ],
    "wof:name":"Custom Craft Construction",
    "wof:placetype":"venue"
},
  "geometry": {"coordinates":[-97.923362,30.482978],"type":"Point"}
}