{
  "type": "Feature",
  "properties": {
    "iso:country":"US",
    "sg:address":"110 Old Boston Rd",
    "sg:city":"Texarkana",
    "sg:classifiers":[
        {
            "category":"Building & Trades",
            "subcategory":"Plumbing",
            "type":"Services"
        }
    ],
    "sg:phone":"+1 903 831 7068",
    "sg:postcode":"75501",
    "sg:province":"TX",
    "sg:tags":[
        "conditioning",
        "air",
        "system",
        "contractor"
    ],
    "wof:name":"Stuart's Heating & Air Cond",
    "wof:placetype":"venue"
},
  "geometry": {"coordinates":[-94.08091,33.44092],"type":"Point"}
}