{
  "type": "Feature",
  "properties": {
    "iso:country":"US",
    "sg:address":"2516 North St",
    "sg:city":"Nacogdoches",
    "sg:classifiers":[
        {
            "category":"Organizations",
            "subcategory":"Professional Association",
            "type":"Services"
        }
    ],
    "sg:phone":"+1 936 560 5533",
    "sg:postcode":"75965",
    "sg:province":"TX",
    "sg:tags":[
        "chambers",
        "commerce"
    ],
    "wof:name":"Nacogdoches Chamber-Commerce",
    "wof:placetype":"venue"
},
  "geometry": {"coordinates":[-94.652253,31.626484],"type":"Point"}
}