{
  "type": "Feature",
  "properties": {
    "iso:country":"US",
    "sg:address":"1005 Farmers Rd",
    "sg:city":"Brenham",
    "sg:classifiers":[
        {
            "category":"Wholesale",
            "subcategory":"Construction Materials",
            "type":"Manufacturing & Wholesale Goods"
        }
    ],
    "sg:phone":"+1 979 836 3178",
    "sg:postcode":"77833",
    "sg:province":"TX",
    "sg:tags":[
        "brick",
        "common",
        "face"
    ],
    "wof:name":"Rudloff Brick & Tile Sales Inc",
    "wof:placetype":"venue"
},
  "geometry": {"coordinates":[-96.42457,30.152164],"type":"Point"}
}