{
  "type": "Feature",
  "properties": {
    "iso:country":"US",
    "sg:address":"14518 Park Lake Ct",
    "sg:city":"Dallas",
    "sg:classifiers":[
        {
            "category":"Wholesale",
            "subcategory":"Machinery & Supplies",
            "type":"Manufacturing & Wholesale Goods"
        }
    ],
    "sg:phone":"+1 972 243 6653",
    "sg:postcode":"75234",
    "sg:province":"TX",
    "sg:tags":[
        "wholesaling",
        "parts",
        "aircraft",
        "manufacturer"
    ],
    "wof:name":"Marty Sidener Inc",
    "wof:placetype":"venue"
},
  "geometry": {"coordinates":[-96.85994700000001,32.947977],"type":"Point"}
}