{
  "type": "Feature",
  "properties": {
    "iso:country":"US",
    "sg:address":"3511 Campfield Ct",
    "sg:city":"Katy",
    "sg:classifiers":[
        {
            "category":"Social Services",
            "subcategory":"Child Care",
            "type":"Services"
        }
    ],
    "sg:phone":"+1 281 492 7208",
    "sg:postcode":"77449",
    "sg:province":"TX",
    "wof:name":"Kathleen Dufour",
    "wof:placetype":"venue"
},
  "geometry": {"coordinates":[-95.716858,29.823383],"type":"Point"}
}