{
  "type": "Feature",
  "properties": {
    "iso:country":"US",
    "sg:address":"7332 Antoine Dr",
    "sg:city":"Houston",
    "sg:classifiers":[
        {
            "category":"Shopping",
            "subcategory":"Used Merchandise",
            "type":"Retail Goods"
        }
    ],
    "sg:phone":"+1 281 405 8882",
    "sg:postcode":"77088",
    "sg:province":"TX",
    "sg:tags":[
        "antique"
    ],
    "wof:name":"Iris McNeer Antiques",
    "wof:placetype":"venue"
},
  "geometry": {"coordinates":[-95.47296,29.868346],"type":"Point"}
}