{
  "type": "Feature",
  "properties": {
    "iso:country":"US",
    "sg:address":"1910 E Pyron Ave",
    "sg:city":"San Antonio",
    "sg:classifiers":[
        {
            "category":"Manufacturing",
            "subcategory":"Jewelry",
            "type":"Manufacturing & Wholesale Goods"
        }
    ],
    "sg:phone":"+1 210 533 7778",
    "sg:postcode":"78223",
    "sg:province":"TX",
    "sg:tags":[
        "material",
        "mfg"
    ],
    "wof:name":"Texas Lapidaries",
    "wof:placetype":"venue"
},
  "geometry": {"coordinates":[-98.467573,29.356178],"type":"Point"}
}