{
  "type": "Feature",
  "properties": {
    "iso:country":"US",
    "sg:address":"419 Broadway St",
    "sg:city":"Dickinson",
    "sg:classifiers":[
        {
            "category":"Wholesale",
            "subcategory":"Machinery & Supplies",
            "type":"Manufacturing & Wholesale Goods"
        }
    ],
    "sg:phone":"+1 832 455 5106",
    "sg:postcode":"77539",
    "sg:province":"TX",
    "sg:tags":[
        "brokerage",
        "container",
        "shipping"
    ],
    "wof:name":"Coastal Container Company",
    "wof:placetype":"venue"
},
  "geometry": {"coordinates":[-94.916307,29.487278],"type":"Point"}
}