{
  "type": "Feature",
  "properties": {
    "iso:country":"US",
    "sg:address":"3401 Lockhaven Dr",
    "sg:city":"Kilgore",
    "sg:classifiers":[
        {
            "category":"Retail",
            "subcategory":"Portrait Studio",
            "type":"Services"
        }
    ],
    "sg:phone":"+1 903 983 3713",
    "sg:postcode":"75662",
    "sg:province":"TX",
    "sg:tags":[
        "photo"
    ],
    "wof:name":"Larrys Photography",
    "wof:placetype":"venue"
},
  "geometry": {"coordinates":[-94.841177,32.377646],"type":"Point"}
}