{
  "type": "Feature",
  "properties": {
    "iso:country":"US",
    "sg:address":"4541 Loop 322",
    "sg:city":"Abilene",
    "sg:classifiers":[
        {
            "category":"Recreation",
            "subcategory":"Miniature Golf",
            "type":"Entertainment"
        },
        {
            "category":"Sports & Exercise",
            "subcategory":"Bowling",
            "type":"Entertainment"
        },
        {
            "category":"Recreation",
            "subcategory":"Amusement Park",
            "type":"Entertainment"
        },
        {
            "category":"Sports & Exercise",
            "subcategory":"Sports Center",
            "type":"Entertainment"
        },
        {
            "category":"Recreation",
            "subcategory":"Picnic Area",
            "type":"Entertainment"
        },
        {
            "category":"Retail",
            "subcategory":"Event Space",
            "type":"Services"
        }
    ],
    "sg:phone":"+1 325 690 5555",
    "sg:postcode":"79602",
    "sg:province":"TX",
    "sg:tags":[
        "arcade",
        "facility",
        "ride",
        "hall",
        "equipment",
        "place",
        "reception",
        "banquet"
    ],
    "sg:website":"http://www.primetimeabilene.com",
    "wof:name":"Prime Time Family Entertainment Center",
    "wof:placetype":"venue"
},
  "geometry": {"coordinates":[-99.72110499999999,32.392169],"type":"Point"}
}