{
  "type": "Feature",
  "properties": {
    "iso:country":"US",
    "sg:address":"14439 Cypress Valley Dr",
    "sg:city":"Cypress",
    "sg:classifiers":[
        {
            "category":"Shopping",
            "subcategory":"Computers & Home Electronics",
            "type":"Retail Goods"
        }
    ],
    "sg:phone":"+1 281 379 6552",
    "sg:postcode":"77429",
    "sg:province":"TX",
    "sg:tags":[
        "equipment",
        "dealer"
    ],
    "wof:name":"Computing Concepts",
    "wof:placetype":"venue"
},
  "geometry": {"coordinates":[-95.639297,29.999175],"type":"Point"}
}