{
  "type": "Feature",
  "properties": {
    "iso:country":"US",
    "sg:address":"3434 Gulf Fwy",
    "sg:city":"Dickinson",
    "sg:classifiers":[
        {
            "category":"Utilities",
            "subcategory":"Mobile Phone",
            "type":"Services"
        }
    ],
    "sg:phone":"+1 281 534 6444",
    "sg:postcode":"77539",
    "sg:province":"TX",
    "sg:tags":[
        "telephone",
        "cellular"
    ],
    "wof:name":"Wireless Data Communications",
    "wof:placetype":"venue"
},
  "geometry": {"coordinates":[-95.078092,29.449754],"type":"Point"}
}