{
  "type": "Feature",
  "properties": {
    "iso:country":"US",
    "sg:address":"1701 Commerce St Ste 1A",
    "sg:city":"Houston",
    "sg:classifiers":[
        {
            "category":"Coffee & Tea",
            "type":"Food & Drink"
        }
    ],
    "sg:phone":"+1 713 222 9800",
    "sg:postcode":"77002",
    "sg:province":"TX",
    "sg:website":"www.lolacc.com",
    "wof:name":"Lola Savannah Coffee & Tea",
    "wof:placetype":"venue"
},
  "geometry": {"coordinates":[-95.35308499999999,29.760164],"type":"Point"}
}