{
  "type": "Feature",
  "properties": {
    "iso:country":"US",
    "sg:address":"6303 Commerce Dr",
    "sg:city":"Irving",
    "sg:classifiers":[
        {
            "category":"Real Estate",
            "subcategory":"Real Estate Services",
            "type":"Services"
        }
    ],
    "sg:phone":"+1 972 550 7510",
    "sg:postcode":"75063",
    "sg:province":"TX",
    "sg:tags":[
        "management",
        "property"
    ],
    "wof:name":"Gateway West",
    "wof:placetype":"venue"
},
  "geometry": {"coordinates":[-96.986817,32.896038],"type":"Point"}
}