{
  "type": "Feature",
  "properties": {
    "iso:country":"US",
    "sg:address":"716 Forest Bend Dr",
    "sg:city":"Plano",
    "sg:classifiers":[
        {
            "category":"Professional",
            "subcategory":"Business Services",
            "type":"Services"
        }
    ],
    "sg:phone":"+1 972 517 4561",
    "sg:postcode":"75025",
    "sg:province":"TX",
    "wof:name":"Agile Business Technologies",
    "wof:placetype":"venue"
},
  "geometry": {"coordinates":[-96.70305399999999,33.075317],"type":"Point"}
}