{
  "type": "Feature",
  "properties": {
    "iso:country":"US",
    "sg:address":"13534 Windhaven St",
    "sg:city":"Houston",
    "sg:classifiers":[
        {
            "category":"Arts & Performance",
            "subcategory":"Theater",
            "type":"Entertainment"
        }
    ],
    "sg:phone":"+1 281 458 7030",
    "sg:postcode":"77049",
    "sg:province":"TX",
    "sg:tags":[
        "group"
    ],
    "wof:name":"Mvp Entertainment & Studios",
    "wof:placetype":"venue"
},
  "geometry": {"coordinates":[-95.204099,29.822453],"type":"Point"}
}