{
  "type": "Feature",
  "properties": {
    "iso:country":"US",
    "sg:address":"2701 Ave I",
    "sg:city":"Hondo",
    "sg:classifiers":[
        {
            "category":"Farming",
            "subcategory":"Livestock Farm",
            "type":"Manufacturing & Wholesale Goods"
        }
    ],
    "sg:phone":"+1 830 426 2066",
    "sg:postcode":"78861",
    "sg:province":"TX",
    "sg:tags":[
        "beef",
        "feedlot",
        "cattle"
    ],
    "wof:name":"Bud Johnson Ranch",
    "wof:placetype":"venue"
},
  "geometry": {"coordinates":[-99.13757,29.340494],"type":"Point"}
}