{
  "type": "Feature",
  "properties": {
    "iso:country":"US",
    "sg:address":"3609 W 7th St",
    "sg:city":"Fort Worth",
    "sg:classifiers":[
        {
            "category":"Health Services",
            "subcategory":"Doctor",
            "type":"Services"
        }
    ],
    "sg:phone":"+1 817 731 4141",
    "sg:postcode":"76107",
    "sg:province":"TX",
    "sg:tags":[
        "medical"
    ],
    "wof:name":"Cohen Phillip E",
    "wof:placetype":"venue"
},
  "geometry": {"coordinates":[-97.37077499999999,32.751322],"type":"Point"}
}