{
  "type": "Feature",
  "properties": {
    "iso:country":"US",
    "sg:address":"802 Matamoros Dr",
    "sg:city":"Rosenberg",
    "sg:classifiers":[
        {
            "category":"Restaurant",
            "type":"Food & Drink"
        }
    ],
    "sg:phone":"+1 281 238 8595",
    "sg:postcode":"77471",
    "sg:province":"TX",
    "wof:name":"Jesusa A Delao And Elida Gamino",
    "wof:placetype":"venue"
},
  "geometry": {"coordinates":[-95.828509,29.546912],"type":"Point"}
}