{
  "type": "Feature",
  "properties": {
    "iso:country":"US",
    "sg:address":"308 E Main St",
    "sg:city":"Frankston",
    "sg:classifiers":[
        {
            "category":"Shopping",
            "subcategory":"Florist",
            "type":"Retail Goods"
        }
    ],
    "sg:phone":"+1 903 876 4177",
    "sg:postcode":"75763",
    "sg:province":"TX",
    "wof:name":"Four Seasons Flowers & Gift Sp",
    "wof:placetype":"venue"
},
  "geometry": {"coordinates":[-95.504424,32.050587],"type":"Point"}
}