{
  "type": "Feature",
  "properties": {
    "iso:country":"US",
    "sg:address":"12807 Britt Rd",
    "sg:city":"Pearland",
    "sg:classifiers":[
        {
            "category":"Wholesale",
            "subcategory":"Vending Machines",
            "type":"Manufacturing & Wholesale Goods"
        }
    ],
    "sg:phone":"+1 281 412 4110",
    "sg:postcode":"77581",
    "sg:province":"TX",
    "sg:tags":[
        "operator"
    ],
    "wof:name":"J Mas",
    "wof:placetype":"venue"
},
  "geometry": {"coordinates":[-95.310849,29.588635],"type":"Point"}
}