{
  "type": "Feature",
  "properties": {
    "iso:country":"US",
    "sg:address":"8787 Hammerly Blvd",
    "sg:city":"Houston",
    "sg:classifiers":[
        {
            "category":"Real Estate",
            "subcategory":"Real Estate Operator",
            "type":"Services"
        }
    ],
    "sg:phone":"+1 713 932 8126",
    "sg:postcode":"77080",
    "sg:province":"TX",
    "sg:tags":[
        "apartment"
    ],
    "wof:name":"Hammerly Walk",
    "wof:placetype":"venue"
},
  "geometry": {"coordinates":[-95.50912700000001,29.81099],"type":"Point"}
}