{
  "type": "Feature",
  "properties": {
    "iso:country":"US",
    "sg:address":"1201 Windsong Ln",
    "sg:city":"Longview",
    "sg:classifiers":[
        {
            "category":"Retail",
            "subcategory":"Auto Repair",
            "type":"Services"
        }
    ],
    "sg:phone":"+1 903 297 2909",
    "sg:postcode":"75604",
    "sg:province":"TX",
    "sg:tags":[
        "glass",
        "replacement"
    ],
    "wof:name":"Glass Fix",
    "wof:placetype":"venue"
},
  "geometry": {"coordinates":[-94.77246599999999,32.525615],"type":"Point"}
}