{
  "type": "Feature",
  "properties": {
    "iso:country":"US",
    "sg:address":"7004 Co Rd 417",
    "sg:city":"Beeville",
    "sg:classifiers":[
        {
            "category":"Shopping",
            "type":"Retail Goods"
        }
    ],
    "sg:phone":"+1 361 439 7288",
    "sg:postcode":"78102",
    "sg:province":"TX",
    "sg:tags":[
        "cosmetic",
        "perfume"
    ],
    "wof:name":"Nin's Perfume",
    "wof:placetype":"venue"
},
  "geometry": {"coordinates":[-97.607319,28.503708],"type":"Point"}
}