{
  "type": "Feature",
  "properties": {
    "iso:country":"US",
    "sg:address":"100 Kathi Ln",
    "sg:city":"Georgetown",
    "sg:classifiers":[
        {
            "category":"Shopping",
            "subcategory":"Music",
            "type":"Retail Goods"
        }
    ],
    "sg:phone":"+1 512 930 4565",
    "sg:postcode":"78628",
    "sg:province":"TX",
    "wof:name":"Bill Record",
    "wof:placetype":"venue"
},
  "geometry": {"coordinates":[-97.69674500000001,30.663781],"type":"Point"}
}