{
  "type": "Feature",
  "properties": {
    "iso:country":"US",
    "sg:address":"404 N McCoy Blvd",
    "sg:city":"New Boston",
    "sg:classifiers":[
        {
            "category":"Insurance",
            "subcategory":"Insurance Agent",
            "type":"Services"
        }
    ],
    "sg:phone":"+1 903 628 5581",
    "sg:postcode":"75570",
    "sg:province":"TX",
    "sg:website":"www.diversifiedinsurance.net",
    "wof:name":"Diversified Insurance Svc",
    "wof:placetype":"venue"
},
  "geometry": {"coordinates":[-94.408502,33.466362],"type":"Point"}
}