{
  "type": "Feature",
  "properties": {
    "iso:country":"US",
    "sg:address":"1724 Oak Tree Dr",
    "sg:city":"Houston",
    "sg:classifiers":[
        {
            "category":"Utilities",
            "subcategory":"Refuse",
            "type":"Services"
        }
    ],
    "sg:phone":"+1 713 461 4152",
    "sg:postcode":"77080",
    "sg:province":"TX",
    "sg:tags":[
        "waste",
        "container"
    ],
    "wof:name":"Compaction Services Inc",
    "wof:placetype":"venue"
},
  "geometry": {"coordinates":[-95.52668,29.803513],"type":"Point"}
}