{
  "type": "Feature",
  "properties": {
    "iso:country":"US",
    "sg:address":"1334 S Flores St",
    "sg:city":"San Antonio",
    "sg:classifiers":[
        {
            "category":"Wholesale",
            "subcategory":"Auto Parts",
            "type":"Manufacturing & Wholesale Goods"
        }
    ],
    "sg:phone":"+1 210 212 4810",
    "sg:postcode":"78204",
    "sg:province":"TX",
    "wof:name":"Allied Distributing",
    "wof:placetype":"venue"
},
  "geometry": {"coordinates":[-98.50087600000001,29.409988],"type":"Point"}
}