{
  "type": "Feature",
  "properties": {
    "iso:country":"US",
    "sg:address":"2015 E Red River St",
    "sg:city":"Victoria",
    "sg:classifiers":[
        {
            "category":"Personal",
            "subcategory":"Beauty Salon",
            "type":"Services"
        },
        {
            "category":"Personal",
            "subcategory":"Barber",
            "type":"Services"
        }
    ],
    "sg:phone":"+1 361 576 1239",
    "sg:postcode":"77901",
    "sg:province":"TX",
    "sg:tags":[
        "wig",
        "hair",
        "piece",
        "stylist"
    ],
    "wof:name":"Hair By Fred",
    "wof:placetype":"venue"
},
  "geometry": {"coordinates":[-96.984194,28.81403],"type":"Point"}
}