{
  "type": "Feature",
  "properties": {
    "iso:country":"US",
    "sg:address":"4682 E University Blvd",
    "sg:city":"Odessa",
    "sg:classifiers":[
        {
            "category":"Government",
            "subcategory":"Office",
            "type":"Public Place"
        }
    ],
    "sg:phone":"+1 432 367 9113",
    "sg:postcode":"79762",
    "sg:province":"TX",
    "sg:tags":[
        "state",
        "comptroller"
    ],
    "wof:name":"Comptroller Pub Accounts Texas",
    "wof:placetype":"venue"
},
  "geometry": {"coordinates":[-102.32338300000001,31.88084],"type":"Point"}
}