{
  "type": "Feature",
  "properties": {
    "iso:country":"US",
    "sg:address":"111 Ben Weeks Rd",
    "sg:city":"Lufkin",
    "sg:classifiers":[
        {
            "category":"Professional",
            "subcategory":"Computer Services",
            "type":"Services"
        }
    ],
    "sg:phone":"+1 936 829 2735",
    "sg:postcode":"75901",
    "sg:province":"TX",
    "sg:tags":[
        "on",
        "base",
        "datum",
        "retrieval",
        "information"
    ],
    "wof:name":"Hanna",
    "wof:placetype":"venue"
},
  "geometry": {"coordinates":[-94.66801100000001,31.183339],"type":"Point"}
}