{
  "type": "Feature",
  "properties": {
    "iso:country":"US",
    "sg:address":"3150 State Hwy 16",
    "sg:city":"Fredericksburg",
    "sg:classifiers":[
        {
            "category":"Organizations",
            "subcategory":"Religious Organization",
            "type":"Services"
        }
    ],
    "sg:phone":"+1 830 997 9707",
    "sg:postcode":"78624",
    "sg:province":"TX",
    "sg:tags":[
        "church"
    ],
    "wof:name":"Kager Baptist",
    "wof:placetype":"venue"
},
  "geometry": {"coordinates":[-98.82151399999999,30.304188],"type":"Point"}
}