{
  "type": "Feature",
  "properties": {
    "iso:country":"US",
    "sg:address":"3100 Independence Pkwy",
    "sg:city":"Plano",
    "sg:classifiers":[
        {
            "category":"Restaurant",
            "type":"Food & Drink"
        }
    ],
    "sg:menulink":"http://www.allmenus.com/tx/plano/44025-mac/menu/",
    "sg:phone":"+1 972 964 7025",
    "sg:postcode":"75075",
    "sg:province":"TX",
    "sg:tags":[
        "asian",
        "vietnamese"
    ],
    "wof:name":"Mac",
    "wof:placetype":"venue"
},
  "geometry": {"coordinates":[-96.75327,33.03766],"type":"Point"}
}