{
  "type": "Feature",
  "properties": {
    "iso:country":"US",
    "sg:address":"3563 Far West Blvd Ste 100",
    "sg:city":"Austin",
    "sg:classifiers":[
        {
            "category":"Food & Beverages",
            "subcategory":"Liquor & Beverages",
            "type":"Retail Goods"
        }
    ],
    "sg:phone":"+1 512 349 2828",
    "sg:postcode":"78731",
    "sg:province":"TX",
    "sg:tags":[
        "beer",
        "spirit",
        "wine"
    ],
    "wof:name":"Northwest Hills Liquor",
    "wof:placetype":"venue"
},
  "geometry": {"coordinates":[-97.75398300000001,30.353588],"type":"Point"}
}