{
  "type": "Feature",
  "properties": {
    "iso:country":"US",
    "sg:address":"2800 E Amarillo Blvd",
    "sg:city":"Amarillo",
    "sg:classifiers":[
        {
            "category":"Organizations",
            "subcategory":"Community Association",
            "type":"Services"
        }
    ],
    "sg:phone":"+1 806 383 0990",
    "sg:postcode":"79107",
    "sg:province":"TX",
    "sg:tags":[
        "club"
    ],
    "wof:name":"Copa Cabana",
    "wof:placetype":"venue"
},
  "geometry": {"coordinates":[-101.805943,35.221906],"type":"Point"}
}