{
  "type": "Feature",
  "properties": {
    "iso:country":"US",
    "sg:address":"1331 W Crawford St",
    "sg:city":"Denison",
    "sg:classifiers":[
        {
            "category":"Personal",
            "subcategory":"Beauty Salon",
            "type":"Services"
        }
    ],
    "sg:phone":"+1 903 464 0126",
    "sg:postcode":"75020",
    "sg:province":"TX",
    "wof:name":"Mia Bella Candes/Cyncy",
    "wof:placetype":"venue"
},
  "geometry": {"coordinates":[-96.554427,33.75409],"type":"Point"}
}