{
  "type": "Feature",
  "properties": {
    "iso:country":"US",
    "sg:address":"4455 Camp Bowie Blvd",
    "sg:city":"Fort Worth",
    "sg:classifiers":[
        {
            "category":"Autos & Motor Vehicles",
            "subcategory":"Automobile Sales",
            "type":"Retail Goods"
        }
    ],
    "sg:phone":"+1 817 737 6464",
    "sg:postcode":"76107",
    "sg:province":"TX",
    "wof:name":"Beaty Barry L",
    "wof:placetype":"venue"
},
  "geometry": {"coordinates":[-97.386256,32.740769],"type":"Point"}
}