{
  "type": "Feature",
  "properties": {
    "iso:country":"US",
    "sg:address":"288 Link Dr",
    "sg:city":"El Paso",
    "sg:classifiers":[
        {
            "category":"Food & Beverages",
            "subcategory":"Groceries & Convenience Stores",
            "type":"Retail Goods"
        }
    ],
    "sg:phone":"+1 915 858 7606",
    "sg:postcode":"79907",
    "sg:province":"TX",
    "wof:name":"Gomez Jose L Flea Mkt",
    "wof:placetype":"venue"
},
  "geometry": {"coordinates":[-106.328007,31.706708],"type":"Point"}
}