{
  "type": "Feature",
  "properties": {
    "iso:country":"US",
    "sg:address":"2407 Metz Pl",
    "sg:city":"Midland",
    "sg:classifiers":[
        {
            "category":"Professional",
            "subcategory":"Detective & Security Services",
            "type":"Services"
        }
    ],
    "sg:phone":"+1 432 631 7889",
    "sg:postcode":"79705",
    "sg:province":"TX",
    "sg:tags":[
        "investigator"
    ],
    "wof:name":"R & S Security & Investigation",
    "wof:placetype":"venue"
},
  "geometry": {"coordinates":[-102.114345,32.028721],"type":"Point"}
}