{
  "type": "Feature",
  "properties": {
    "iso:country":"US",
    "sg:address":"290 S Preston Rd",
    "sg:city":"Celina",
    "sg:classifiers":[
        {
            "category":"Banks & Credit Unions",
            "subcategory":"Bank",
            "type":"Services"
        }
    ],
    "sg:phone":"+1 972 382 2351",
    "sg:postcode":"75009",
    "sg:province":"TX",
    "sg:tags":[
        "saving",
        "commercial"
    ],
    "wof:name":"Independent Bank",
    "wof:placetype":"venue"
},
  "geometry": {"coordinates":[-96.77729100000001,33.3205],"type":"Point"}
}