{
  "type": "Feature",
  "properties": {
    "iso:country":"US",
    "sg:address":"112 S 1st St",
    "sg:city":"Harlingen",
    "sg:classifiers":[
        {
            "category":"Restaurant",
            "type":"Food & Drink"
        }
    ],
    "sg:phone":"+1 956 423 2992",
    "sg:postcode":"78550",
    "sg:province":"TX",
    "sg:tags":[
        "eating"
    ],
    "wof:name":"City Coffee Shop",
    "wof:placetype":"venue"
},
  "geometry": {"coordinates":[-97.69568700000001,26.191848],"type":"Point"}
}