{
  "type": "Feature",
  "properties": {
    "iso:country":"US",
    "sg:address":"8003 Gladstone St",
    "sg:city":"Houston",
    "sg:classifiers":[
        {
            "category":"Organizations",
            "subcategory":"Religious Organization",
            "type":"Services"
        }
    ],
    "sg:phone":"+1 713 734 0161",
    "sg:postcode":"77051",
    "sg:province":"TX",
    "wof:name":"Sunny Side Mssnary Bptst Chrch",
    "wof:placetype":"venue"
},
  "geometry": {"coordinates":[-95.36787,29.674469],"type":"Point"}
}