{
  "type": "Feature",
  "properties": {
    "iso:country":"US",
    "sg:address":"8001 Airline Dr",
    "sg:city":"Houston",
    "sg:classifiers":[
        {
            "category":"Shopping",
            "subcategory":"Bicycles & Sporting Goods",
            "type":"Retail Goods"
        }
    ],
    "sg:phone":"+1 281 447 0867",
    "sg:postcode":"77037",
    "sg:province":"TX",
    "wof:name":"Deportes Bravo",
    "wof:placetype":"venue"
},
  "geometry": {"coordinates":[-95.387398,29.8769],"type":"Point"}
}