{
  "type": "Feature",
  "properties": {
    "iso:country":"US",
    "sg:address":"9400 N Central Expy",
    "sg:city":"Dallas",
    "sg:classifiers":[
        {
            "category":"Banks & Credit Unions",
            "subcategory":"Financial Services",
            "type":"Services"
        },
        {
            "category":"Banks & Credit Unions",
            "subcategory":"Bank",
            "type":"Services"
        }
    ],
    "sg:phone":"+1 214 739 0170",
    "sg:postcode":"75231",
    "sg:province":"TX",
    "sg:tags":[
        "company",
        "premium",
        "insurance",
        "financing",
        "finance"
    ],
    "wof:name":"Premium Finance Holdings LLC",
    "wof:placetype":"venue"
},
  "geometry": {"coordinates":[-96.769576,32.878677],"type":"Point"}
}