{
  "type": "Feature",
  "properties": {
    "iso:country":"US",
    "sg:address":"3103 N Cardinal Rd",
    "sg:city":"Azle",
    "sg:classifiers":[
        {
            "category":"Shopping",
            "type":"Retail Goods"
        },
        {
            "category":"Organizations",
            "subcategory":"Non-profit Organization",
            "type":"Services"
        }
    ],
    "sg:phone":"+1 817 444 2252",
    "sg:postcode":"76020",
    "sg:province":"TX",
    "sg:tags":[
        "fund",
        "games",
        "raising",
        "merchandise",
        "supply"
    ],
    "wof:name":"Dreams Scholarship Foundation Inc",
    "wof:placetype":"venue"
},
  "geometry": {"coordinates":[-97.554061,32.984022],"type":"Point"}
}