{
  "type": "Feature",
  "properties": {
    "iso:country":"US",
    "sg:address":"691 N Santa Clara Rd",
    "sg:city":"Marion",
    "sg:classifiers":[
        {
            "category":"Manufacturing",
            "subcategory":"Toys & Sporting Goods",
            "type":"Manufacturing & Wholesale Goods"
        }
    ],
    "sg:phone":"+1 830 914 2677",
    "sg:postcode":"78124",
    "sg:province":"TX",
    "sg:tags":[
        "mfg"
    ],
    "wof:name":"Home Crafts",
    "wof:placetype":"venue"
},
  "geometry": {"coordinates":[-98.16466800000001,29.573754],"type":"Point"}
}