{
  "type": "Feature",
  "properties": {
    "iso:country":"US",
    "sg:address":"2350 Double Creek Dr",
    "sg:city":"Round Rock",
    "sg:classifiers":[
        {
            "category":"Professional",
            "subcategory":"Management & Consulting",
            "type":"Services"
        },
        {
            "category":"Manufacturing",
            "subcategory":"Chemicals & Compounds",
            "type":"Manufacturing & Wholesale Goods"
        }
    ],
    "sg:phone":"+1 512 310 9044",
    "sg:postcode":"78664",
    "sg:province":"TX",
    "sg:tags":[
        "development",
        "product",
        "mfg",
        "consultant",
        "research",
        "acid"
    ],
    "sg:website":"www.exfluor.com",
    "wof:name":"Exfluor Research Corporation",
    "wof:placetype":"venue"
},
  "geometry": {"coordinates":[-97.64336900000001,30.487747],"type":"Point"}
}