{
  "type": "Feature",
  "properties": {
    "iso:country":"US",
    "sg:address":"2801 6th Ave",
    "sg:city":"Fort Worth",
    "sg:classifiers":[
        {
            "category":"Professional",
            "subcategory":"Lawyer & Legal Services",
            "type":"Services"
        }
    ],
    "sg:phone":"+1 817 926 9499",
    "sg:postcode":"76110",
    "sg:province":"TX",
    "wof:name":"Lisa Ryan",
    "wof:placetype":"venue"
},
  "geometry": {"coordinates":[-97.340481,32.70959],"type":"Point"}
}