{
  "type": "Feature",
  "properties": {
    "iso:country":"US",
    "sg:address":"318 Meadowview Rd",
    "sg:city":"Longview",
    "sg:classifiers":[
        {
            "category":"Building & Trades",
            "subcategory":"Construction",
            "type":"Services"
        }
    ],
    "sg:phone":"+1 903 759 6424",
    "sg:postcode":"75604",
    "sg:province":"TX",
    "sg:tags":[
        "contractor"
    ],
    "wof:name":"Duvall Masonry Inc",
    "wof:placetype":"venue"
},
  "geometry": {"coordinates":[-94.83313,32.579048],"type":"Point"}
}