{
  "type": "Feature",
  "properties": {
    "iso:country":"US",
    "sg:address":"107 Cottonwood Dr",
    "sg:city":"Victoria",
    "sg:classifiers":[
        {
            "category":"Wholesale",
            "subcategory":"Furniture",
            "type":"Manufacturing & Wholesale Goods"
        }
    ],
    "sg:phone":"+1 361 573 7936",
    "sg:postcode":"77904",
    "sg:province":"TX",
    "wof:name":"Stockton Office Machines",
    "wof:placetype":"venue"
},
  "geometry": {"coordinates":[-97.07887100000001,28.89872],"type":"Point"}
}