{
  "type": "Feature",
  "properties": {
    "iso:country":"US",
    "sg:address":"805 W Lampasas St",
    "sg:city":"Ennis",
    "sg:classifiers":[
        {
            "category":"Health Services",
            "subcategory":"Doctor",
            "type":"Services"
        }
    ],
    "sg:phone":"+1 972 875 9494",
    "sg:postcode":"75119",
    "sg:province":"TX",
    "sg:tags":[
        "physician",
        "surgeon",
        "medical"
    ],
    "wof:name":"Norma Jean Fuelberth MD",
    "wof:placetype":"venue"
},
  "geometry": {"coordinates":[-96.630765,32.320249],"type":"Point"}
}