{
  "type": "Feature",
  "properties": {
    "iso:country":"US",
    "sg:address":"13919 Texarkana St",
    "sg:city":"Houston",
    "sg:classifiers":[
        {
            "category":"Real Estate",
            "subcategory":"Real Estate Services",
            "type":"Services"
        },
        {
            "category":"Real Estate",
            "subcategory":"Real Estate Agent",
            "type":"Services"
        }
    ],
    "sg:phone":"+1 713 637 7416",
    "sg:postcode":"77015",
    "sg:province":"TX",
    "sg:tags":[
        "management"
    ],
    "wof:name":"Sarisa Properties",
    "wof:placetype":"venue"
},
  "geometry": {"coordinates":[-95.17783900000001,29.785047],"type":"Point"}
}