{
  "type": "Feature",
  "properties": {
    "iso:country":"US",
    "sg:address":"805 S Great Southwest Pkwy",
    "sg:city":"Grand Prairie",
    "sg:classifiers":[
        {
            "category":"Shopping",
            "subcategory":"Hobbies, Toys, & Games",
            "type":"Retail Goods"
        }
    ],
    "sg:phone":"+1 972 660 7244",
    "sg:postcode":"75051",
    "sg:province":"TX",
    "sg:tags":[
        "bingo",
        "supply"
    ],
    "wof:name":"Bingo Resources",
    "wof:placetype":"venue"
},
  "geometry": {"coordinates":[-97.045976,32.731127],"type":"Point"}
}