{
  "type": "Feature",
  "properties": {
    "iso:country":"US",
    "sg:address":"504 S Denton Tap Rd",
    "sg:city":"Coppell",
    "sg:classifiers":[
        {
            "category":"Retail",
            "subcategory":"Veterinary Services",
            "type":"Services"
        }
    ],
    "sg:phone":"+1 972 462 1120",
    "sg:postcode":"75019",
    "sg:province":"TX",
    "sg:tags":[
        "pet",
        "for"
    ],
    "wof:name":"Stearman W C III Dvm",
    "wof:placetype":"venue"
},
  "geometry": {"coordinates":[-96.993494,32.958439],"type":"Point"}
}