{
  "type": "Feature",
  "properties": {
    "iso:country":"US",
    "sg:address":"6775 Wegner Rd",
    "sg:city":"New Braunfels",
    "sg:classifiers":[
        {
            "category":"Professional",
            "type":"Services"
        }
    ],
    "sg:phone":"+1 830 907 2174",
    "sg:postcode":"78132",
    "sg:province":"TX",
    "wof:name":"Dragon Fly",
    "wof:placetype":"venue"
},
  "geometry": {"coordinates":[-98.07131699999999,29.840982],"type":"Point"}
}