{
  "type": "Feature",
  "properties": {
    "iso:country":"US",
    "sg:address":"11863 Co Rd 3900",
    "sg:city":"Athens",
    "sg:classifiers":[
        {
            "category":"Shopping",
            "subcategory":"Used Merchandise",
            "type":"Retail Goods"
        }
    ],
    "sg:phone":"+1 903 677 9689",
    "sg:postcode":"75752",
    "sg:province":"TX",
    "wof:name":"Pawn Express",
    "wof:placetype":"venue"
},
  "geometry": {"coordinates":[-95.845805,32.322761],"type":"Point"}
}