{
  "type": "Feature",
  "properties": {
    "iso:country":"US",
    "sg:address":"9125 Viscount Row",
    "sg:city":"Dallas",
    "sg:classifiers":[
        {
            "category":"Manufacturing",
            "subcategory":"Motor Vehicles & Parts",
            "type":"Manufacturing & Wholesale Goods"
        },
        {
            "category":"Autos & Motor Vehicles",
            "subcategory":"Motorcycle Sales",
            "type":"Retail Goods"
        }
    ],
    "sg:phone":"+1 214 821 8607",
    "sg:postcode":"75247",
    "sg:province":"TX",
    "sg:tags":[
        "control",
        "electric"
    ],
    "sg:website":"http://www.standardcontrols.com",
    "wof:name":"Standard Controls, Inc.",
    "wof:placetype":"venue"
},
  "geometry": {"coordinates":[-96.895521,32.815604],"type":"Point"}
}