{
  "type": "Feature",
  "properties": {
    "iso:country":"US",
    "sg:address":"109 N Jack Kultgen Expy",
    "sg:city":"Waco",
    "sg:classifiers":[
        {
            "category":"Real Estate",
            "subcategory":"Real Estate Operator",
            "type":"Services"
        }
    ],
    "sg:phone":"+1 254 754 2230",
    "sg:postcode":"76704",
    "sg:province":"TX",
    "sg:tags":[
        "apartment"
    ],
    "wof:name":"Baylor Landing Apartments",
    "wof:placetype":"venue"
},
  "geometry": {"coordinates":[-97.118318,31.559965],"type":"Point"}
}