{
  "type": "Feature",
  "properties": {
    "iso:country":"US",
    "sg:address":"9317 Mc Neil Rd",
    "sg:city":"Austin",
    "sg:classifiers":[
        {
            "category":"Wholesale",
            "subcategory":"Construction Materials",
            "type":"Manufacturing & Wholesale Goods"
        }
    ],
    "sg:phone":"+1 512 836 3333",
    "sg:postcode":"78758",
    "sg:province":"TX",
    "wof:name":"Roofing Systems Sales",
    "wof:placetype":"venue"
},
  "geometry": {"coordinates":[-97.724526,30.376897],"type":"Point"}
}