{
  "type": "Feature",
  "properties": {
    "iso:country":"US",
    "sg:address":"6459 Woodstock Rd",
    "sg:city":"Fort Worth",
    "sg:classifiers":[
        {
            "category":"Professional",
            "subcategory":"Engineering",
            "type":"Services"
        }
    ],
    "sg:phone":"+1 817 874 7113",
    "sg:postcode":"76116",
    "sg:province":"TX",
    "wof:name":"K W S Structural Consultants",
    "wof:placetype":"venue"
},
  "geometry": {"coordinates":[-97.42448400000001,32.719248],"type":"Point"}
}