{
  "type": "Feature",
  "properties": {
    "iso:country":"US",
    "sg:address":"1309 W Adams Ave",
    "sg:city":"Temple",
    "sg:classifiers":[
        {
            "category":"Insurance",
            "subcategory":"Insurance Agent",
            "type":"Services"
        }
    ],
    "sg:phone":"+1 254 773 2226",
    "sg:postcode":"76504",
    "sg:province":"TX",
    "wof:name":"Ray Davis Insurance",
    "wof:placetype":"venue"
},
  "geometry": {"coordinates":[-97.354468,31.101354],"type":"Point"}
}