{
  "type": "Feature",
  "properties": {
    "iso:country":"US",
    "sg:address":"2210 Lynnbrook Dr Apt B",
    "sg:city":"Austin",
    "sg:classifiers":[
        {
            "category":"Retail",
            "subcategory":"Auto Repair",
            "type":"Services"
        }
    ],
    "sg:phone":"+1 512 292 3519",
    "sg:postcode":"78748",
    "sg:province":"TX",
    "sg:website":"http://www.stbautomotive.com",
    "wof:name":"Stb Automotive",
    "wof:placetype":"venue"
},
  "geometry": {"coordinates":[-97.834396,30.165899],"type":"Point"}
}