{
  "type": "Feature",
  "properties": {
    "iso:country":"US",
    "sg:address":"4706 Rustown Dr",
    "sg:city":"Austin",
    "sg:classifiers":[
        {
            "category":"Professional",
            "subcategory":"Computer Services",
            "type":"Services"
        }
    ],
    "sg:phone":"+1 512 336 1897",
    "sg:postcode":"78727",
    "sg:province":"TX",
    "sg:tags":[
        "related",
        "programing",
        "custom"
    ],
    "wof:name":"Duostar Consulting",
    "wof:placetype":"venue"
},
  "geometry": {"coordinates":[-97.732759,30.419231],"type":"Point"}
}