{
  "type": "Feature",
  "properties": {
    "iso:country":"US",
    "sg:address":"7729 Castillo Rd",
    "sg:city":"Fort Worth",
    "sg:classifiers":[
        {
            "category":"Freight",
            "type":"Transportation"
        }
    ],
    "sg:phone":"+1 817 429 3951",
    "sg:postcode":"76112",
    "sg:province":"TX",
    "sg:tags":[
        "trucking"
    ],
    "wof:name":"Michael Cartwright Trucking",
    "wof:placetype":"venue"
},
  "geometry": {"coordinates":[-97.185979,32.741941],"type":"Point"}
}