{
  "type": "Feature",
  "properties": {
    "iso:country":"US",
    "sg:address":"1746 N 3rd St",
    "sg:city":"Abilene",
    "sg:classifiers":[
        {
            "category":"Retail",
            "subcategory":"Animal Services",
            "type":"Services"
        }
    ],
    "sg:phone":"+1 325 677 5165",
    "sg:postcode":"79603",
    "sg:province":"TX",
    "sg:tags":[
        "pet",
        "boarding",
        "sitting"
    ],
    "wof:name":"Evelyn Guitars Boarding",
    "wof:placetype":"venue"
},
  "geometry": {"coordinates":[-99.741663,32.452707],"type":"Point"}
}