{
  "type": "Feature",
  "properties": {
    "iso:country":"US",
    "sg:address":"1019 Maltese Garden",
    "sg:city":"San Antonio",
    "sg:classifiers":[
        {
            "category":"Wholesale",
            "subcategory":"Electrical",
            "type":"Manufacturing & Wholesale Goods"
        }
    ],
    "sg:phone":"+1 210 491 0190",
    "sg:postcode":"78258",
    "sg:province":"TX",
    "sg:tags":[
        "equipment"
    ],
    "wof:name":"John C Zambrano",
    "wof:placetype":"venue"
},
  "geometry": {"coordinates":[-98.517743,29.656102],"type":"Point"}
}