{
  "type": "Feature",
  "properties": {
    "iso:country":"US",
    "sg:address":"13719 Omega Dr",
    "sg:city":"Dallas",
    "sg:classifiers":[
        {
            "category":"Freight",
            "type":"Transportation"
        }
    ],
    "sg:phone":"+1 972 661 9991",
    "sg:postcode":"75244",
    "sg:province":"TX",
    "sg:tags":[
        "food",
        "delivery"
    ],
    "wof:name":"Takeout Taxi Inc",
    "wof:placetype":"venue"
},
  "geometry": {"coordinates":[-96.833524,32.934697],"type":"Point"}
}