{
  "type": "Feature",
  "properties": {
    "iso:country":"US",
    "sg:address":"344 Broadway",
    "sg:city":"Winnie",
    "sg:classifiers":[
        {
            "category":"Home & Garden",
            "subcategory":"Furniture",
            "type":"Retail Goods"
        }
    ],
    "sg:phone":"+1 409 296 3737",
    "sg:postcode":"77665",
    "sg:province":"TX",
    "sg:tags":[
        "store"
    ],
    "wof:name":"Sherrie Anne's Home Furnishings",
    "wof:placetype":"venue"
},
  "geometry": {"coordinates":[-94.371073,29.820581],"type":"Point"}
}