{
  "type": "Feature",
  "properties": {
    "iso:country":"US",
    "sg:address":"33635 Ansley Rd",
    "sg:city":"Magnolia",
    "sg:classifiers":[
        {
            "category":"Shopping",
            "subcategory":"Computers & Home Electronics",
            "type":"Retail Goods"
        }
    ],
    "sg:phone":"+1 281 356 8121",
    "sg:postcode":"77355",
    "sg:province":"TX",
    "sg:tags":[
        "communications",
        "safety",
        "public",
        "including",
        "disaster"
    ],
    "wof:name":"Interconnect Telecom",
    "wof:placetype":"venue"
},
  "geometry": {"coordinates":[-95.681006,30.143083],"type":"Point"}
}