{
  "type": "Feature",
  "properties": {
    "iso:country":"US",
    "sg:address":"415 S International Blvd",
    "sg:city":"Weslaco",
    "sg:classifiers":[
        {
            "category":"Shopping",
            "subcategory":"Gifts & Souvenirs",
            "type":"Retail Goods"
        }
    ],
    "sg:phone":"+1 956 969 0889",
    "sg:postcode":"78596",
    "sg:province":"TX",
    "sg:tags":[
        "shop"
    ],
    "wof:name":"Klein Gray Trading Co",
    "wof:placetype":"venue"
},
  "geometry": {"coordinates":[-97.95826,26.153504],"type":"Point"}
}