{
  "type": "Feature",
  "properties": {
    "iso:country":"US",
    "sg:address":"3010 103rd St",
    "sg:city":"Lubbock",
    "sg:classifiers":[
        {
            "category":"Professional",
            "subcategory":"Employment Agencies",
            "type":"Services"
        }
    ],
    "sg:phone":"+1 806 745 5848",
    "sg:postcode":"79423",
    "sg:province":"TX",
    "wof:name":"John V Slyker Inc",
    "wof:placetype":"venue"
},
  "geometry": {"coordinates":[-101.87998,33.500676],"type":"Point"}
}