{
  "type": "Feature",
  "properties": {
    "iso:country":"US",
    "sg:address":"470 W Parker Rd",
    "sg:city":"Houston",
    "sg:classifiers":[
        {
            "category":"Food & Beverages",
            "subcategory":"Groceries & Convenience Stores",
            "type":"Retail Goods"
        }
    ],
    "sg:phone":"+1 713 884 8870",
    "sg:postcode":"77091",
    "sg:province":"TX",
    "wof:name":"Parker Food Mart",
    "wof:placetype":"venue"
},
  "geometry": {"coordinates":[-95.405602,29.8589],"type":"Point"}
}