{
  "type": "Feature",
  "properties": {
    "iso:country":"US",
    "sg:address":"7225 Scenic Brook Dr",
    "sg:city":"Austin",
    "sg:classifiers":[
        {
            "category":"Shopping",
            "subcategory":"Beauty & Cosmetics",
            "type":"Retail Goods"
        }
    ],
    "sg:phone":"+1 512 288 0993",
    "sg:postcode":"78736",
    "sg:province":"TX",
    "sg:tags":[
        "equipment",
        "perfume",
        "salons-equipment",
        "supply"
    ],
    "wof:name":"Mary Kay Cosmetics",
    "wof:placetype":"venue"
},
  "geometry": {"coordinates":[-97.890557,30.238676],"type":"Point"}
}