{
  "type": "Feature",
  "properties": {
    "iso:country":"US",
    "sg:address":"7188 Mykawa Rd",
    "sg:city":"Houston",
    "sg:classifiers":[
        {
            "category":"Wholesale",
            "subcategory":"Stationery",
            "type":"Manufacturing & Wholesale Goods"
        }
    ],
    "sg:phone":"+1 713 784 8688",
    "sg:postcode":"77033",
    "sg:province":"TX",
    "sg:tags":[
        "bag",
        "plastic"
    ],
    "wof:name":"Unistar Plastics",
    "wof:placetype":"venue"
},
  "geometry": {"coordinates":[-95.320716,29.674266],"type":"Point"}
}