{
  "type": "Feature",
  "properties": {
    "iso:country":"US",
    "sg:address":"1215 Industrial Blvd",
    "sg:city":"Plano",
    "sg:classifiers":[
        {
            "category":"Building & Trades",
            "subcategory":"Plumbing",
            "type":"Services"
        }
    ],
    "sg:phone":"+1 972 578 1085",
    "sg:postcode":"75074",
    "sg:province":"TX",
    "sg:tags":[
        "conditioning",
        "contractor",
        "system",
        "air"
    ],
    "wof:name":"Southgate Air Condg & Heating",
    "wof:placetype":"venue"
},
  "geometry": {"coordinates":[-96.684878,33.016417],"type":"Point"}
}