{
  "type": "Feature",
  "properties": {
    "iso:country":"US",
    "sg:address":"501 N Stratton St",
    "sg:city":"Seymour",
    "sg:classifiers":[
        {
            "category":"Professional",
            "subcategory":"Computer Services",
            "type":"Services"
        }
    ],
    "sg:phone":"+1 940 888 5726",
    "sg:postcode":"76380",
    "sg:province":"TX",
    "sg:tags":[
        "repair"
    ],
    "wof:name":"Master Data Computers",
    "wof:placetype":"venue"
},
  "geometry": {"coordinates":[-99.25662199999999,33.593181],"type":"Point"}
}