{
  "type": "Feature",
  "properties": {
    "iso:country":"US",
    "sg:address":"9529 Braeburn Glen Blvd",
    "sg:city":"Houston",
    "sg:classifiers":[
        {
            "category":"Education",
            "subcategory":"Dance Studio",
            "type":"Public Place"
        }
    ],
    "sg:phone":"+1 713 773 3110",
    "sg:postcode":"77074",
    "sg:province":"TX",
    "wof:name":"Redeemed Dance Co",
    "wof:placetype":"venue"
},
  "geometry": {"coordinates":[-95.532522,29.677177],"type":"Point"}
}