{
  "type": "Feature",
  "properties": {
    "iso:country":"US",
    "sg:address":"1662 San Pedro Ave",
    "sg:city":"San Antonio",
    "sg:classifiers":[
        {
            "category":"Shopping",
            "type":"Retail Goods"
        }
    ],
    "sg:phone":"+1 210 490 1790",
    "sg:postcode":"78212",
    "sg:province":"TX",
    "sg:tags":[
        "electronic",
        "merchandise"
    ],
    "wof:name":"Nextel",
    "wof:placetype":"venue"
},
  "geometry": {"coordinates":[-98.49927,29.449485],"type":"Point"}
}