{
  "type": "Feature",
  "properties": {
    "iso:country":"US",
    "sg:address":"1231 S Marlborough Ave",
    "sg:city":"Dallas",
    "sg:classifiers":[
        {
            "category":"Shopping",
            "subcategory":"Used Merchandise",
            "type":"Retail Goods"
        }
    ],
    "sg:phone":"+1 214 943 2284",
    "sg:postcode":"75208",
    "sg:province":"TX",
    "sg:tags":[
        "junk"
    ],
    "wof:name":"Roberts Lawn Svc",
    "wof:placetype":"venue"
},
  "geometry": {"coordinates":[-96.85176,32.732076],"type":"Point"}
}