{
  "type": "Feature",
  "properties": {
    "iso:country":"US",
    "sg:address":"1736 Carrington Dr",
    "sg:city":"Red Oak",
    "sg:classifiers":[
        {
            "category":"Freight",
            "type":"Transportation"
        }
    ],
    "sg:phone":"+1 972 230 8255",
    "sg:postcode":"75154",
    "sg:province":"TX",
    "sg:tags":[
        "trucking"
    ],
    "wof:name":"PDW Truckin",
    "wof:placetype":"venue"
},
  "geometry": {"coordinates":[-96.831659,32.558665],"type":"Point"}
}