{
  "type": "Feature",
  "properties": {
    "iso:country":"US",
    "sg:address":"402 S Washington St",
    "sg:city":"Kaufman",
    "sg:classifiers":[
        {
            "category":"Food & Beverages",
            "subcategory":"Specialty",
            "type":"Retail Goods"
        }
    ],
    "sg:phone":"+1 972 932 4220",
    "sg:postcode":"75142",
    "sg:province":"TX",
    "sg:tags":[
        "vitamin"
    ],
    "wof:name":"Karen's Vitamin Shoppe",
    "wof:placetype":"venue"
},
  "geometry": {"coordinates":[-96.309223,32.586507],"type":"Point"}
}