{
  "type": "Feature",
  "properties": {
    "iso:country":"US",
    "sg:address":"2538 Highwood Dr",
    "sg:city":"Dallas",
    "sg:classifiers":[
        {
            "category":"Real Estate",
            "subcategory":"Real Estate Agent",
            "type":"Services"
        }
    ],
    "sg:phone":"+1 214 328 3713",
    "sg:postcode":"75228",
    "sg:province":"TX",
    "wof:name":"Ridenour Realty Co",
    "wof:placetype":"venue"
},
  "geometry": {"coordinates":[-96.66875400000001,32.829375],"type":"Point"}
}