{
  "type": "Feature",
  "properties": {
    "iso:country":"US",
    "sg:address":"3001 34th St",
    "sg:city":"Lubbock",
    "sg:classifiers":[
        {
            "category":"Restaurant",
            "type":"Food & Drink"
        }
    ],
    "sg:phone":"+1 806 791 5813",
    "sg:postcode":"79410",
    "sg:province":"TX",
    "sg:tags":[
        "eating"
    ],
    "wof:name":"Burrito Tower",
    "wof:placetype":"venue"
},
  "geometry": {"coordinates":[-101.881265,33.563266],"type":"Point"}
}