{
  "type": "Feature",
  "properties": {
    "iso:country":"US",
    "sg:address":"315 Hickory St",
    "sg:city":"Lockhart",
    "sg:classifiers":[
        {
            "category":"Professional",
            "type":"Services"
        }
    ],
    "sg:phone":"+1 512 398 7374",
    "sg:postcode":"78644",
    "sg:province":"TX",
    "wof:name":"William P Christie III A Prof",
    "wof:placetype":"venue"
},
  "geometry": {"coordinates":[-97.667545,29.880753],"type":"Point"}
}