{
  "type": "Feature",
  "properties": {
    "iso:country":"US",
    "sg:address":"13215 Grantmoor Ln",
    "sg:city":"Houston",
    "sg:classifiers":[
        {
            "category":"Real Estate",
            "subcategory":"Surveying",
            "type":"Services"
        }
    ],
    "sg:phone":"+1 713 729 8767",
    "sg:postcode":"77045",
    "sg:province":"TX",
    "wof:name":"W Harry Padgett Surveyors",
    "wof:placetype":"venue"
},
  "geometry": {"coordinates":[-95.45327,29.635285],"type":"Point"}
}