{
  "type": "Feature",
  "properties": {
    "iso:country":"US",
    "sg:address":"1213 N Carrier Pkwy",
    "sg:city":"Grand Prairie",
    "sg:classifiers":[
        {
            "category":"Wholesale",
            "subcategory":"Chemicals & Plastics",
            "type":"Manufacturing & Wholesale Goods"
        }
    ],
    "sg:phone":"+1 972 602 3283",
    "sg:postcode":"75050",
    "sg:province":"TX",
    "sg:tags":[
        "resin"
    ],
    "wof:name":"Hanna Resin Distribution",
    "wof:placetype":"venue"
},
  "geometry": {"coordinates":[-97.019998,32.758147],"type":"Point"}
}