{
  "type": "Feature",
  "properties": {
    "iso:country":"US",
    "sg:address":"2807 E Park Row Dr",
    "sg:city":"Arlington",
    "sg:classifiers":[
        {
            "category":"Restaurant",
            "type":"Food & Drink"
        }
    ],
    "sg:phone":"+1 817 633 4243",
    "sg:postcode":"76010",
    "sg:province":"TX",
    "sg:tags":[
        "eating"
    ],
    "wof:name":"Pizza Joe Delivery",
    "wof:placetype":"venue"
},
  "geometry": {"coordinates":[-97.05727899999999,32.720796],"type":"Point"}
}