{
  "type": "Feature",
  "properties": {
    "iso:country":"US",
    "sg:address":"211 E Parkwood Ave",
    "sg:city":"Friendswood",
    "sg:classifiers":[
        {
            "category":"Travel",
            "subcategory":"Travel Agent",
            "type":"Entertainment"
        }
    ],
    "sg:phone":"+1 281 996 7800",
    "sg:postcode":"77546",
    "sg:province":"TX",
    "sg:tags":[
        "agency"
    ],
    "wof:name":"Ocean Connection",
    "wof:placetype":"venue"
},
  "geometry": {"coordinates":[-95.18713099999999,29.510613],"type":"Point"}
}