{
  "type": "Feature",
  "properties": {
    "iso:country":"US",
    "sg:address":"238 Heath Ln",
    "sg:city":"Jacksonville",
    "sg:classifiers":[
        {
            "category":"Professional",
            "subcategory":"Business Services",
            "type":"Services"
        }
    ],
    "sg:phone":"+1 903 589 3449",
    "sg:postcode":"75766",
    "sg:province":"TX",
    "wof:name":"Quality Wireless Solutions",
    "wof:placetype":"venue"
},
  "geometry": {"coordinates":[-95.274815,32.003574],"type":"Point"}
}