{
  "type": "Feature",
  "properties": {
    "iso:country":"US",
    "sg:address":"2918 W Walnut St",
    "sg:city":"Garland",
    "sg:classifiers":[
        {
            "category":"Freight",
            "type":"Transportation"
        }
    ],
    "sg:phone":"+1 972 276 1065",
    "sg:postcode":"75042",
    "sg:province":"TX",
    "sg:tags":[
        "operator",
        "local",
        "trucking"
    ],
    "wof:name":"Gallegos Trucking",
    "wof:placetype":"venue"
},
  "geometry": {"coordinates":[-96.67169,32.916467],"type":"Point"}
}