{
  "type": "Feature",
  "properties": {
    "iso:country":"US",
    "sg:address":"4700 Blaffer",
    "sg:city":"Houston",
    "sg:classifiers":[
        {
            "category":"Wholesale",
            "subcategory":"Durable Goods & Equipment",
            "type":"Manufacturing & Wholesale Goods"
        }
    ],
    "sg:phone":"+1 713 672 6276",
    "sg:postcode":"77026",
    "sg:province":"TX",
    "sg:tags":[
        "importer"
    ],
    "sg:website":"www.cdavisenterprises.com",
    "wof:name":"Davis C Enterprises Inc",
    "wof:placetype":"venue"
},
  "geometry": {"coordinates":[-95.305781,29.801656],"type":"Point"}
}