{
  "type": "Feature",
  "properties": {
    "iso:country":"US",
    "sg:address":"15522 Canterbury Forest Dr",
    "sg:city":"Tomball",
    "sg:classifiers":[
        {
            "category":"Professional",
            "subcategory":"Business Services",
            "type":"Services"
        }
    ],
    "sg:phone":"+1 281 374 7496",
    "sg:postcode":"77377",
    "sg:province":"TX",
    "wof:name":"Fastrack Ventures LLC",
    "wof:placetype":"venue"
},
  "geometry": {"coordinates":[-95.58935,30.002728],"type":"Point"}
}