{
  "type": "Feature",
  "properties": {
    "iso:country":"US",
    "sg:address":"8828 Research Blvd",
    "sg:city":"Austin",
    "sg:classifiers":[
        {
            "category":"Real Estate",
            "subcategory":"Real Estate Services",
            "type":"Services"
        },
        {
            "category":"Education",
            "subcategory":"University",
            "type":"Public Place"
        }
    ],
    "sg:phone":"+1 512 453 0900",
    "sg:postcode":"78758",
    "sg:province":"TX",
    "sg:tags":[
        "college"
    ],
    "sg:website":"www.austininstitute.com",
    "wof:name":"Austin Institute of Real Estate",
    "wof:placetype":"venue"
},
  "geometry": {"coordinates":[-97.718953,30.367485],"type":"Point"}
}