{
  "type": "Feature",
  "properties": {
    "iso:country":"US",
    "sg:address":"2906 Carver Dr",
    "sg:city":"Corpus Christi",
    "sg:classifiers":[
        {
            "category":"Organizations",
            "subcategory":"Religious Organization",
            "type":"Services"
        }
    ],
    "sg:phone":"+1 361 882 4781",
    "sg:postcode":"78405",
    "sg:province":"TX",
    "wof:name":"Calvary First Baptist Church",
    "wof:placetype":"venue"
},
  "geometry": {"coordinates":[-97.427522,27.771048],"type":"Point"}
}