{
  "type": "Feature",
  "properties": {
    "iso:country":"US",
    "sg:address":"1042 Humble Pl",
    "sg:city":"El Paso",
    "sg:classifiers":[
        {
            "category":"Freight",
            "type":"Transportation"
        }
    ],
    "sg:phone":"+1 915 772 5443",
    "sg:postcode":"79915",
    "sg:province":"TX",
    "sg:tags":[
        "trucking"
    ],
    "wof:name":"J R & Sons Trucking",
    "wof:placetype":"venue"
},
  "geometry": {"coordinates":[-106.38766200000001,31.775795],"type":"Point"}
}