{
  "type": "Feature",
  "properties": {
    "iso:country":"US",
    "sg:address":"6969 Market Ave",
    "sg:city":"El Paso",
    "sg:classifiers":[
        {
            "category":"Retail",
            "subcategory":"Auto Repair",
            "type":"Services"
        }
    ],
    "sg:phone":"+1 915 778 7888",
    "sg:postcode":"79915",
    "sg:province":"TX",
    "sg:tags":[
        "truck"
    ],
    "wof:name":"Chavez Jose Truck Svc",
    "wof:placetype":"venue"
},
  "geometry": {"coordinates":[-106.389009,31.770377],"type":"Point"}
}