{
  "type": "Feature",
  "properties": {
    "iso:country":"US",
    "sg:address":"3719 Ruby Dr",
    "sg:city":"Mesquite",
    "sg:classifiers":[
        {
            "category":"Professional",
            "subcategory":"Management & Consulting",
            "type":"Services"
        }
    ],
    "sg:phone":"+1 972 279 6934",
    "sg:postcode":"75150",
    "sg:province":"TX",
    "sg:tags":[
        "retail",
        "direct",
        "sales"
    ],
    "wof:name":"To Cherish",
    "wof:placetype":"venue"
},
  "geometry": {"coordinates":[-96.654928,32.814798],"type":"Point"}
}