{
  "type": "Feature",
  "properties": {
    "iso:country":"US",
    "sg:address":"5078 Warren Ln",
    "sg:city":"Orange",
    "sg:classifiers":[
        {
            "category":"Manufacturing",
            "subcategory":"Metals",
            "type":"Manufacturing & Wholesale Goods"
        }
    ],
    "sg:phone":"+1 409 735 4930",
    "sg:postcode":"77630",
    "sg:province":"TX",
    "sg:tags":[
        "mfg"
    ],
    "wof:name":"Home Treasures",
    "wof:placetype":"venue"
},
  "geometry": {"coordinates":[-93.89229,30.054962],"type":"Point"}
}