{
  "type": "Feature",
  "properties": {
    "iso:country":"US",
    "sg:address":"7149 Dairy Rd",
    "sg:city":"Miles",
    "sg:classifiers":[
        {
            "category":"Manufacturing",
            "subcategory":"Textiles",
            "type":"Manufacturing & Wholesale Goods"
        }
    ],
    "sg:phone":"+1 325 468 4121",
    "sg:postcode":"76861",
    "sg:province":"TX",
    "sg:tags":[
        "broker",
        "cotton"
    ],
    "wof:name":"Andy Schwertner",
    "wof:placetype":"venue"
},
  "geometry": {"coordinates":[-100.119872,31.541632],"type":"Point"}
}