{
  "type": "Feature",
  "properties": {
    "iso:country":"US",
    "sg:address":"2231 Quail Run Rd",
    "sg:city":"Arlington",
    "sg:phone":"+1 817 789 4949",
    "sg:postcode":"76014",
    "sg:province":"TX",
    "wof:name":"Arlington Security Systems-Protect Your Home",
    "wof:placetype":"venue"
},
  "geometry": {"coordinates":[-97.070984,32.685047],"type":"Point"}
}