{
  "type": "Feature",
  "properties": {
    "iso:country":"US",
    "sg:address":"180 State St",
    "sg:city":"Southlake",
    "sg:classifiers":[
        {
            "category":"Home & Garden",
            "subcategory":"Carpets & Floor Coverings",
            "type":"Retail Goods"
        }
    ],
    "sg:phone":"+1 817 481 4900",
    "sg:postcode":"76092",
    "sg:province":"TX",
    "sg:tags":[
        "dealer",
        "rug"
    ],
    "wof:name":"Luna Carpet & Blinds",
    "wof:placetype":"venue"
},
  "geometry": {"coordinates":[-97.13173,32.941881],"type":"Point"}
}