{
  "type": "Feature",
  "properties": {
    "iso:country":"US",
    "sg:address":"8122 Town Creek Dr",
    "sg:city":"Houston",
    "sg:classifiers":[
        {
            "category":"Wholesale",
            "subcategory":"Machinery & Supplies",
            "type":"Manufacturing & Wholesale Goods"
        }
    ],
    "sg:phone":"+1 281 855 2272",
    "sg:postcode":"77095",
    "sg:province":"TX",
    "sg:tags":[
        "bearing"
    ],
    "wof:name":"Global Bearing & Components",
    "wof:placetype":"venue"
},
  "geometry": {"coordinates":[-95.64142200000001,29.898259],"type":"Point"}
}