{
  "type": "Feature",
  "properties": {
    "iso:country":"US",
    "sg:address":"3611 Clinton Dr",
    "sg:city":"Houston",
    "sg:classifiers":[
        {
            "category":"Wholesale",
            "subcategory":"Machinery & Supplies",
            "type":"Manufacturing & Wholesale Goods"
        }
    ],
    "sg:phone":"+1 713 678 8080",
    "sg:postcode":"77020",
    "sg:province":"TX",
    "sg:tags":[
        "industrial"
    ],
    "wof:name":"Distributors Warehouse",
    "wof:placetype":"venue"
},
  "geometry": {"coordinates":[-95.33265299999999,29.765453],"type":"Point"}
}