{
  "type": "Feature",
  "properties": {
    "iso:country":"US",
    "sg:address":"3416 Hickory Tree Rd",
    "sg:city":"Balch Springs",
    "sg:classifiers":[
        {
            "category":"Wholesale",
            "subcategory":"Machinery & Supplies",
            "type":"Manufacturing & Wholesale Goods"
        },
        {
            "category":"Professional",
            "subcategory":"Art Services",
            "type":"Services"
        }
    ],
    "sg:phone":"+1 972 557 3796",
    "sg:postcode":"75180",
    "sg:province":"TX",
    "sg:tags":[
        "janitor",
        "design",
        "commercial"
    ],
    "wof:name":"Hill Custom Graphics",
    "wof:placetype":"venue"
},
  "geometry": {"coordinates":[-96.622562,32.723943],"type":"Point"}
}