{
  "type": "Feature",
  "properties": {
    "iso:country":"US",
    "sg:address":"611 Saddlebrook Dr",
    "sg:city":"Allen",
    "sg:classifiers":[
        {
            "category":"Building & Trades",
            "subcategory":"Landscaping Services",
            "type":"Services"
        }
    ],
    "sg:phone":"+1 972 359 9941",
    "sg:postcode":"75002",
    "sg:province":"TX",
    "wof:name":"Ticer Lawncare",
    "wof:placetype":"venue"
},
  "geometry": {"coordinates":[-96.599532,33.092771],"type":"Point"}
}