{
  "type": "Feature",
  "properties": {
    "iso:country":"US",
    "sg:address":"203 E Frank Ave",
    "sg:city":"Lufkin",
    "sg:classifiers":[
        {
            "category":"Retail",
            "subcategory":"Repair Shop",
            "type":"Services"
        }
    ],
    "sg:phone":"+1 936 637 2722",
    "sg:postcode":"75901",
    "sg:province":"TX",
    "sg:tags":[
        "watch",
        "jewelry",
        "clock"
    ],
    "wof:name":"B N Enterprises",
    "wof:placetype":"venue"
},
  "geometry": {"coordinates":[-94.72727999999999,31.339831],"type":"Point"}
}