{
  "type": "Feature",
  "properties": {
    "iso:country":"US",
    "sg:address":"8530 Alameda Ave",
    "sg:city":"El Paso",
    "sg:classifiers":[
        {
            "category":"Real Estate",
            "subcategory":"Real Estate Operator",
            "type":"Services"
        }
    ],
    "sg:phone":"+1 915 860 4832",
    "sg:postcode":"79907",
    "sg:province":"TX",
    "sg:tags":[
        "apartment"
    ],
    "wof:name":"Alameda Apartments",
    "wof:placetype":"venue"
},
  "geometry": {"coordinates":[-106.342961,31.704845],"type":"Point"}
}