{
  "type": "Feature",
  "properties": {
    "iso:country":"US",
    "sg:address":"827 E Highland Blvd",
    "sg:city":"San Antonio",
    "sg:classifiers":[
        {
            "category":"Shopping",
            "subcategory":"Used Merchandise",
            "type":"Retail Goods"
        }
    ],
    "sg:phone":"+1 210 533 7093",
    "sg:postcode":"78210",
    "sg:province":"TX",
    "wof:name":"Maria M Dawson",
    "wof:placetype":"venue"
},
  "geometry": {"coordinates":[-98.46646800000001,29.396363],"type":"Point"}
}