{
  "type": "Feature",
  "properties": {
    "iso:country":"US",
    "sg:address":"3412 North Fwy",
    "sg:city":"Houston",
    "sg:classifiers":[
        {
            "category":"Manufacturing",
            "subcategory":"Food",
            "type":"Manufacturing & Wholesale Goods"
        }
    ],
    "sg:phone":"+1 713 692 7213",
    "sg:postcode":"77009",
    "sg:province":"TX",
    "sg:tags":[
        "product",
        "manufacturer"
    ],
    "sg:website":"www.isaonline.net",
    "wof:name":"ISA",
    "wof:placetype":"venue"
},
  "geometry": {"coordinates":[-95.37510399999999,29.812921],"type":"Point"}
}