{
  "type": "Feature",
  "properties": {
    "iso:country":"US",
    "sg:address":"3601 Santa Maria Ave",
    "sg:city":"Laredo",
    "sg:classifiers":[
        {
            "category":"Recreation",
            "type":"Entertainment"
        }
    ],
    "sg:phone":"+1 956 712 2327",
    "sg:postcode":"78041",
    "sg:province":"TX",
    "sg:tags":[
        "park",
        "amusement"
    ],
    "wof:name":"Bear Karate Academy",
    "wof:placetype":"venue"
},
  "geometry": {"coordinates":[-99.510001,27.532802],"type":"Point"}
}