{
  "type": "Feature",
  "properties": {
    "iso:country":"US",
    "sg:address":"1440 Empire Central Dr",
    "sg:city":"Dallas",
    "sg:classifiers":[
        {
            "category":"Deli",
            "type":"Food & Drink"
        }
    ],
    "sg:phone":"+1 214 905 0955",
    "sg:postcode":"75247",
    "sg:province":"TX",
    "wof:name":"V P Empire Deli",
    "wof:placetype":"venue"
},
  "geometry": {"coordinates":[-96.870796,32.826801],"type":"Point"}
}