{
  "type": "Feature",
  "properties": {
    "iso:country":"US",
    "sg:address":"19539 FM 2767",
    "sg:city":"Winona",
    "sg:classifiers":[
        {
            "category":"Manufacturing",
            "subcategory":"Leather Goods",
            "type":"Manufacturing & Wholesale Goods"
        }
    ],
    "sg:phone":"+1 903 566 2028",
    "sg:postcode":"75792",
    "sg:province":"TX",
    "sg:tags":[
        "mfg"
    ],
    "wof:name":"R & R Collars",
    "wof:placetype":"venue"
},
  "geometry": {"coordinates":[-95.070525,32.390019],"type":"Point"}
}