{
  "type": "Feature",
  "properties": {
    "iso:country":"US",
    "sg:address":"3601 NE 24th Ave",
    "sg:city":"Amarillo",
    "sg:classifiers":[
        {
            "category":"Food & Beverages",
            "subcategory":"Groceries & Convenience Stores",
            "type":"Retail Goods"
        }
    ],
    "sg:phone":"+1 806 381 7754",
    "sg:postcode":"79107",
    "sg:province":"TX",
    "wof:name":"Toot'n Totum Food Stores",
    "wof:placetype":"venue"
},
  "geometry": {"coordinates":[-101.79310099999999,35.236377],"type":"Point"}
}