{
  "type": "Feature",
  "properties": {
    "iso:country":"US",
    "sg:address":"1006 Ainslee St",
    "sg:city":"Midland",
    "sg:classifiers":[
        {
            "category":"Shopping",
            "subcategory":"Florist",
            "type":"Retail Goods"
        }
    ],
    "sg:phone":"+1 432 682 1787",
    "sg:postcode":"79701",
    "sg:province":"TX",
    "wof:name":"Floral & Christmas Creations",
    "wof:placetype":"venue"
},
  "geometry": {"coordinates":[-102.10510499999999,32.003166],"type":"Point"}
}