{
  "type": "Feature",
  "properties": {
    "iso:country":"US",
    "sg:address":"1908 Fast Filly Ave",
    "sg:city":"Pflugerville",
    "sg:classifiers":[
        {
            "category":"Shopping",
            "subcategory":"Computers & Home Electronics",
            "type":"Retail Goods"
        }
    ],
    "sg:phone":"+1 512 251 6808",
    "sg:postcode":"78660",
    "sg:province":"TX",
    "sg:tags":[
        "publishing"
    ],
    "wof:name":"Cannon's Comfort & Expressions",
    "wof:placetype":"venue"
},
  "geometry": {"coordinates":[-97.57541500000001,30.491128],"type":"Point"}
}