{
  "type": "Feature",
  "properties": {
    "iso:country":"US",
    "sg:address":"22820 I- 45",
    "sg:city":"Spring",
    "sg:classifiers":[
        {
            "category":"Freight",
            "type":"Transportation"
        }
    ],
    "sg:phone":"+1 281 528 5131",
    "sg:postcode":"77373",
    "sg:province":"TX",
    "wof:name":"Caribou International Inc",
    "wof:placetype":"venue"
},
  "geometry": {"coordinates":[-95.43561699999999,30.099192],"type":"Point"}
}