{
  "type": "Feature",
  "properties": {
    "iso:country":"US",
    "sg:address":"15508 Golden Creek Rd",
    "sg:city":"Dallas",
    "sg:classifiers":[
        {
            "category":"Communications",
            "subcategory":"Film & Video Production",
            "type":"Services"
        }
    ],
    "sg:phone":"+1 972 490 5861",
    "sg:postcode":"75248",
    "sg:province":"TX",
    "sg:tags":[
        "motion"
    ],
    "wof:name":"Normstorm Productions",
    "wof:placetype":"venue"
},
  "geometry": {"coordinates":[-96.801951,32.960446],"type":"Point"}
}