{
  "type": "Feature",
  "properties": {
    "iso:country":"US",
    "sg:address":"2300 Seawall Blvd",
    "sg:city":"Galveston",
    "sg:classifiers":[
        {
            "category":"Travel",
            "subcategory":"Hotels & Motels",
            "type":"Entertainment"
        }
    ],
    "sg:phone":"+1 409 762 1166",
    "sg:postcode":"77550",
    "sg:province":"TX",
    "sg:tags":[
        "lodging"
    ],
    "sg:website":"http://www.ramada.com",
    "wof:name":"Four Points by Sheraton Galveston",
    "wof:placetype":"venue"
},
  "geometry": {"coordinates":[-94.788437,29.289801],"type":"Point"}
}