{
  "type": "Feature",
  "properties": {
    "iso:country":"US",
    "sg:address":"3194 Southmost Rd",
    "sg:city":"Brownsville",
    "sg:phone":"+1 956 544 3056",
    "sg:postcode":"78521",
    "sg:province":"TX",
    "wof:name":"Capistran Tortillas",
    "wof:placetype":"venue"
},
  "geometry": {"coordinates":[-97.459182,25.904707],"type":"Point"}
}