{
  "type": "Feature",
  "properties": {
    "iso:country":"US",
    "sg:address":"401 W Water St",
    "sg:city":"Kerrville",
    "sg:classifiers":[
        {
            "category":"Personal",
            "subcategory":"Beauty Salon",
            "type":"Services"
        }
    ],
    "sg:phone":"+1 830 895 2025",
    "sg:postcode":"78028",
    "sg:province":"TX",
    "sg:tags":[
        "shop"
    ],
    "wof:name":"Shabby To Chic",
    "wof:placetype":"venue"
},
  "geometry": {"coordinates":[-99.153069,30.056929],"type":"Point"}
}