{
  "type": "Feature",
  "properties": {
    "iso:country":"US",
    "sg:address":"1010 Bade St",
    "sg:city":"Houston",
    "sg:classifiers":[
        {
            "category":"Wholesale",
            "subcategory":"Apparel",
            "type":"Manufacturing & Wholesale Goods"
        },
        {
            "category":"Wholesale",
            "subcategory":"Non-durable Goods",
            "type":"Manufacturing & Wholesale Goods"
        }
    ],
    "sg:phone":"+1 713 464 3704",
    "sg:postcode":"77055",
    "sg:province":"TX",
    "sg:tags":[
        "fabric"
    ],
    "wof:name":"Anmerican Wholesale Supply",
    "wof:placetype":"venue"
},
  "geometry": {"coordinates":[-95.518049,29.786403],"type":"Point"}
}