{
  "type": "Feature",
  "properties": {
    "iso:country":"US",
    "sg:address":"1711 Patricia Dr",
    "sg:city":"San Antonio",
    "sg:classifiers":[
        {
            "category":"Home & Garden",
            "subcategory":"Building Materials",
            "type":"Retail Goods"
        }
    ],
    "sg:phone":"+1 210 698 6125",
    "sg:postcode":"78213",
    "sg:province":"TX",
    "sg:tags":[
        "trade",
        "contractor"
    ],
    "wof:name":"Sheerin Rountree Inc",
    "wof:placetype":"venue"
},
  "geometry": {"coordinates":[-98.520144,29.549896],"type":"Point"}
}