{
  "type": "Feature",
  "properties": {
    "iso:country":"US",
    "sg:address":"4016 Black Oak Dr",
    "sg:city":"Cleburne",
    "sg:classifiers":[
        {
            "category":"Professional",
            "subcategory":"Research",
            "type":"Services"
        }
    ],
    "sg:phone":"+1 817 690 3848",
    "sg:postcode":"76031",
    "sg:province":"TX",
    "wof:name":"Debra Isreal",
    "wof:placetype":"venue"
},
  "geometry": {"coordinates":[-97.298523,32.37692],"type":"Point"}
}