{
  "type": "Feature",
  "properties": {
    "iso:country":"US",
    "sg:address":"8525 Boat Club Rd",
    "sg:city":"Fort Worth",
    "sg:classifiers":[
        {
            "category":"Banks & Credit Unions",
            "subcategory":"Investment Brokerage",
            "type":"Services"
        }
    ],
    "sg:phone":"+1 817 236 5123",
    "sg:postcode":"76179",
    "sg:province":"TX",
    "sg:tags":[
        "security"
    ],
    "wof:name":"Edward Jones 13041",
    "wof:placetype":"venue"
},
  "geometry": {"coordinates":[-97.42585099999999,32.878468],"type":"Point"}
}