{
  "type": "Feature",
  "properties": {
    "iso:country":"US",
    "sg:address":"1013 W Pike Blvd",
    "sg:city":"Weslaco",
    "sg:classifiers":[
        {
            "category":"Professional",
            "subcategory":"Printing & Photocopies",
            "type":"Services"
        }
    ],
    "sg:phone":"+1 956 351 5780",
    "sg:postcode":"78596",
    "sg:province":"TX",
    "sg:tags":[
        "duplicating",
        "copying"
    ],
    "wof:name":"Copyrite",
    "wof:placetype":"venue"
},
  "geometry": {"coordinates":[-97.999036,26.169807],"type":"Point"}
}