{
  "type": "Feature",
  "properties": {
    "iso:country":"US",
    "sg:address":"208 N Patrick St",
    "sg:city":"Dublin",
    "sg:classifiers":[
        {
            "category":"Food & Beverages",
            "subcategory":"Groceries & Convenience Stores",
            "type":"Retail Goods"
        }
    ],
    "sg:phone":"+1 254 445 3229",
    "sg:postcode":"76446",
    "sg:province":"TX",
    "sg:tags":[
        "grocer"
    ],
    "wof:name":"David's Supermarket",
    "wof:placetype":"venue"
},
  "geometry": {"coordinates":[-98.34199,32.086663],"type":"Point"}
}