{
  "type": "Feature",
  "properties": {
    "iso:country":"US",
    "sg:address":"325 E Bell Ave",
    "sg:city":"Pharr",
    "sg:classifiers":[
        {
            "category":"Organizations",
            "subcategory":"Religious Organization",
            "type":"Services"
        }
    ],
    "sg:phone":"+1 956 702 8232",
    "sg:postcode":"78577",
    "sg:province":"TX",
    "wof:name":"Fellowship Bible Church",
    "wof:placetype":"venue"
},
  "geometry": {"coordinates":[-98.17928000000001,26.198912],"type":"Point"}
}