{
  "type": "Feature",
  "properties": {
    "iso:country":"US",
    "sg:address":"2665 Kirby Rd",
    "sg:city":"Aransas Pass",
    "sg:classifiers":[
        {
            "category":"Autos & Motor Vehicles",
            "subcategory":"Auto Supplies",
            "type":"Retail Goods"
        }
    ],
    "sg:phone":"+1 361 758 5827",
    "sg:postcode":"78336",
    "sg:province":"TX",
    "wof:name":"Chagos Used Tires",
    "wof:placetype":"venue"
},
  "geometry": {"coordinates":[-97.15464,27.937668],"type":"Point"}
}