{
  "type": "Feature",
  "properties": {
    "iso:country":"US",
    "sg:address":"402 W 3rd St",
    "sg:city":"Pecos",
    "sg:classifiers":[
        {
            "category":"Autos & Motor Vehicles",
            "subcategory":"Fuel & Gas Station",
            "type":"Retail Goods"
        }
    ],
    "sg:phone":"+1 432 445 5758",
    "sg:postcode":"79772",
    "sg:province":"TX",
    "sg:tags":[
        "oil"
    ],
    "wof:name":"Ham's Chevron KWIK Lupe Ctr",
    "wof:placetype":"venue"
},
  "geometry": {"coordinates":[-103.49833700000001,31.424439],"type":"Point"}
}