{
  "type": "Feature",
  "properties": {
    "iso:country":"US",
    "sg:address":"3008 Dawn Dr",
    "sg:city":"Georgetown",
    "sg:classifiers":[
        {
            "category":"Professional",
            "subcategory":"Lawyer & Legal Services",
            "type":"Services"
        }
    ],
    "sg:phone":"+1 512 931 2882",
    "sg:postcode":"78628",
    "sg:province":"TX",
    "sg:tags":[
        "attorney"
    ],
    "wof:name":"Johnson & Assoc",
    "wof:placetype":"venue"
},
  "geometry": {"coordinates":[-97.692108,30.665148],"type":"Point"}
}