{
  "type": "Feature",
  "properties": {
    "iso:country":"US",
    "sg:address":"3221 Lawnwood Dr",
    "sg:city":"Temple",
    "sg:classifiers":[
        {
            "category":"Professional",
            "type":"Services"
        }
    ],
    "sg:phone":"+1 254 721 2468",
    "sg:postcode":"76502",
    "sg:province":"TX",
    "sg:tags":[
        "establishment"
    ],
    "wof:name":"Compudoc",
    "wof:placetype":"venue"
},
  "geometry": {"coordinates":[-97.38586599999999,31.079871],"type":"Point"}
}