{
  "type": "Feature",
  "properties": {
    "iso:country":"US",
    "sg:address":"14310 Rolling Hills Ln",
    "sg:city":"Rosharon",
    "sg:classifiers":[
        {
            "category":"Marine",
            "type":"Transportation"
        }
    ],
    "sg:phone":"+1 281 431 4047",
    "sg:postcode":"77583",
    "sg:province":"TX",
    "sg:tags":[
        "salvage-marine"
    ],
    "wof:name":"Al Marine Surveyors Inc.",
    "wof:placetype":"venue"
},
  "geometry": {"coordinates":[-95.44371599999999,29.499406],"type":"Point"}
}