{
  "type": "Feature",
  "properties": {
    "iso:country":"US",
    "sg:address":"700 Louisiana St",
    "sg:city":"Houston",
    "sg:classifiers":[
        {
            "category":"Banks & Credit Unions",
            "subcategory":"Bank",
            "type":"Services"
        }
    ],
    "sg:phone":"+1 713 223 4610",
    "sg:postcode":"77002",
    "sg:province":"TX",
    "sg:tags":[
        "financial",
        "specialty"
    ],
    "wof:name":"Newport Glfcrse Conference Ctr",
    "wof:placetype":"venue"
},
  "geometry": {"coordinates":[-95.366355,29.760011],"type":"Point"}
}