{
  "type": "Feature",
  "properties": {
    "iso:country":"US",
    "sg:address":"1735 S Voss Rd",
    "sg:city":"Houston",
    "sg:classifiers":[
        {
            "category":"Shopping",
            "subcategory":"Clothing, Apparel, & Fashions",
            "type":"Retail Goods"
        }
    ],
    "sg:phone":"+1 713 782 0676",
    "sg:postcode":"77057",
    "sg:province":"TX",
    "sg:tags":[
        "item",
        "boutique"
    ],
    "wof:name":"Claire's Boutique",
    "wof:placetype":"venue"
},
  "geometry": {"coordinates":[-95.501025,29.750265],"type":"Point"}
}