{
  "type": "Feature",
  "properties": {
    "iso:country":"US",
    "sg:address":"1209 N I- 35",
    "sg:city":"Round Rock",
    "sg:classifiers":[
        {
            "category":"Professional",
            "subcategory":"Business Services",
            "type":"Services"
        }
    ],
    "sg:phone":"+1 512 341 7000",
    "sg:postcode":"78628",
    "sg:province":"TX",
    "sg:tags":[
        "equipment",
        "mfg",
        "communications"
    ],
    "wof:name":"Williamson Conference Center",
    "wof:placetype":"venue"
},
  "geometry": {"coordinates":[-97.674156,30.659142],"type":"Point"}
}