{
  "type": "Feature",
  "properties": {
    "iso:country":"US",
    "sg:address":"701 7th St",
    "sg:city":"Honey Grove",
    "sg:classifiers":[
        {
            "category":"Organizations",
            "subcategory":"Religious Organization",
            "type":"Services"
        }
    ],
    "sg:phone":"+1 903 378 2315",
    "sg:postcode":"75446",
    "sg:province":"TX",
    "sg:tags":[
        "church"
    ],
    "wof:name":"Mckenzie United Methodist Chur",
    "wof:placetype":"venue"
},
  "geometry": {"coordinates":[-95.90840900000001,33.585586],"type":"Point"}
}