{
  "type": "Feature",
  "properties": {
    "iso:country":"US",
    "sg:address":"4930 S Congress Ave Ste A",
    "sg:city":"Austin",
    "sg:classifiers":[
        {
            "category":"Manufacturing",
            "subcategory":"Food",
            "type":"Manufacturing & Wholesale Goods"
        },
        {
            "category":"Food & Beverages",
            "subcategory":"Specialty",
            "type":"Retail Goods"
        }
    ],
    "sg:phone":"+1 512 306 9911",
    "sg:postcode":"78745",
    "sg:province":"TX",
    "sg:tags":[
        "product",
        "products-wholesale",
        "vitamin",
        "diet",
        "supplement",
        "health",
        "manufacturer"
    ],
    "wof:name":"Kingsway",
    "wof:placetype":"venue"
},
  "geometry": {"coordinates":[-97.771317,30.211303],"type":"Point"}
}