{
  "type": "Feature",
  "properties": {
    "iso:country":"US",
    "sg:address":"102 E Old Bowman Rd",
    "sg:city":"Round Rock",
    "sg:classifiers":[
        {
            "category":"Insurance",
            "subcategory":"Insurance Agent",
            "type":"Services"
        }
    ],
    "sg:phone":"+1 512 255 1415",
    "sg:postcode":"78664",
    "sg:province":"TX",
    "wof:name":"American National Insurance Co",
    "wof:placetype":"venue"
},
  "geometry": {"coordinates":[-97.684507,30.523934],"type":"Point"}
}