{
  "type": "Feature",
  "properties": {
    "iso:country":"US",
    "sg:address":"1902 N Main St",
    "sg:city":"Del Rio",
    "sg:phone":"+1 830 778 2275",
    "sg:postcode":"78840",
    "sg:province":"TX",
    "sg:tags":[
        "farm",
        "corn"
    ],
    "wof:name":"Cornhuskers",
    "wof:placetype":"venue"
},
  "geometry": {"coordinates":[-100.910984,29.38107],"type":"Point"}
}