{
  "type": "Feature",
  "properties": {
    "iso:country":"US",
    "sg:address":"8280 Spring Valley Rd",
    "sg:city":"Dallas",
    "sg:classifiers":[
        {
            "category":"Retail",
            "subcategory":"Auto Repair",
            "type":"Services"
        }
    ],
    "sg:phone":"+1 972 918 0025",
    "sg:postcode":"75240",
    "sg:province":"TX",
    "sg:tags":[
        "automobile",
        "lubrication"
    ],
    "wof:name":"KWIK Kar Oil & Lube",
    "wof:placetype":"venue"
},
  "geometry": {"coordinates":[-96.763327,32.939756],"type":"Point"}
}