{
  "type": "Feature",
  "properties": {
    "iso:country":"US",
    "sg:address":"1515 W Donovan St",
    "sg:city":"Houston",
    "sg:classifiers":[
        {
            "category":"Professional",
            "subcategory":"Detective & Security Services",
            "type":"Services"
        }
    ],
    "sg:phone":"+1 713 681 5751",
    "sg:postcode":"77091",
    "sg:province":"TX",
    "sg:tags":[
        "information",
        "bureau"
    ],
    "wof:name":"K&S Pilot Car Service",
    "wof:placetype":"venue"
},
  "geometry": {"coordinates":[-95.435597,29.844022],"type":"Point"}
}