{
  "type": "Feature",
  "properties": {
    "iso:country":"US",
    "sg:address":"712 Co Rd 3300",
    "sg:city":"Lubbock",
    "sg:classifiers":[
        {
            "category":"Farming",
            "subcategory":"Farm",
            "type":"Manufacturing & Wholesale Goods"
        }
    ],
    "sg:phone":"+1 806 842 3545",
    "sg:postcode":"79403",
    "sg:province":"TX",
    "sg:tags":[
        "crop",
        "general"
    ],
    "wof:name":"August Patschke",
    "wof:placetype":"venue"
},
  "geometry": {"coordinates":[-101.674826,33.587791],"type":"Point"}
}