{
  "type": "Feature",
  "properties": {
    "iso:country":"US",
    "sg:address":"1348 State Hwy 123",
    "sg:city":"San Marcos",
    "sg:classifiers":[
        {
            "category":"Government",
            "subcategory":"Office",
            "type":"Public Place"
        }
    ],
    "sg:phone":"+1 512 353 8330",
    "sg:postcode":"78666",
    "sg:province":"TX",
    "sg:tags":[
        "state",
        "resource"
    ],
    "wof:name":"Human Service Dept-Food Stamp",
    "wof:placetype":"venue"
},
  "geometry": {"coordinates":[-97.939566,29.857405],"type":"Point"}
}