{
  "type": "Feature",
  "properties": {
    "iso:country":"US",
    "sg:address":"7700 Jones Maltsberger Rd",
    "sg:city":"San Antonio",
    "sg:classifiers":[
        {
            "category":"Retail",
            "subcategory":"Car Wash",
            "type":"Services"
        }
    ],
    "sg:phone":"+1 210 826 2301",
    "sg:postcode":"78216",
    "sg:province":"TX",
    "sg:tags":[
        "polishing",
        "washing"
    ],
    "wof:name":"Carwash",
    "wof:placetype":"venue"
},
  "geometry": {"coordinates":[-98.48170399999999,29.504244],"type":"Point"}
}