{
  "type": "Feature",
  "properties": {
    "iso:country":"US",
    "sg:address":"1552 E Springcrest Cir",
    "sg:city":"Lancaster",
    "sg:classifiers":[
        {
            "category":"Building & Trades",
            "subcategory":"Construction",
            "type":"Services"
        }
    ],
    "sg:phone":"+1 972 224 4869",
    "sg:postcode":"75134",
    "sg:province":"TX",
    "sg:tags":[
        "contractor"
    ],
    "wof:name":"Roberts Restoration",
    "wof:placetype":"venue"
},
  "geometry": {"coordinates":[-96.80258499999999,32.608041],"type":"Point"}
}