{
  "type": "Feature",
  "properties": {
    "iso:country":"US",
    "sg:address":"503 W Boyd Dr",
    "sg:city":"Allen",
    "sg:classifiers":[
        {
            "category":"Manufacturing",
            "subcategory":"Glass & Minerals",
            "type":"Manufacturing & Wholesale Goods"
        }
    ],
    "sg:phone":"+1 972 390 9116",
    "sg:postcode":"75013",
    "sg:province":"TX",
    "sg:tags":[
        "tile",
        "ceramic",
        "mfg"
    ],
    "wof:name":"Debra Ann White",
    "wof:placetype":"venue"
},
  "geometry": {"coordinates":[-96.67656700000001,33.104188],"type":"Point"}
}