{
  "type": "Feature",
  "properties": {
    "iso:country":"US",
    "sg:address":"1209 Main St",
    "sg:city":"Rusk",
    "sg:classifiers":[
        {
            "category":"Government",
            "subcategory":"Office",
            "type":"Public Place"
        }
    ],
    "sg:phone":"+1 903 683 4688",
    "sg:postcode":"75785",
    "sg:province":"TX",
    "sg:tags":[
        "county",
        "program",
        "health"
    ],
    "wof:name":"Cherokee County Health Unit",
    "wof:placetype":"venue"
},
  "geometry": {"coordinates":[-95.15045000000001,31.802868],"type":"Point"}
}