{
  "type": "Feature",
  "properties": {
    "iso:country":"US",
    "sg:address":"922 S Old Orchard Ln",
    "sg:city":"Lewisville",
    "sg:classifiers":[
        {
            "category":"Arts & Performance",
            "subcategory":"Theater",
            "type":"Entertainment"
        }
    ],
    "sg:phone":"+1 972 353 0761",
    "sg:postcode":"75067",
    "sg:province":"TX",
    "sg:tags":[
        "group"
    ],
    "wof:name":"World Wide Ave",
    "wof:placetype":"venue"
},
  "geometry": {"coordinates":[-97.02752,33.034779],"type":"Point"}
}