{
  "type": "Feature",
  "properties": {
    "iso:country":"US",
    "sg:address":"501 Texas Ave",
    "sg:city":"El Paso",
    "sg:classifiers":[
        {
            "category":"Banks & Credit Unions",
            "subcategory":"Financial Services",
            "type":"Services"
        }
    ],
    "sg:phone":"+1 915 532 0717",
    "sg:postcode":"79901",
    "sg:province":"TX",
    "sg:tags":[
        "company",
        "holding"
    ],
    "wof:name":"D Lamar Apartments",
    "wof:placetype":"venue"
},
  "geometry": {"coordinates":[-106.48376399999999,31.761018],"type":"Point"}
}