{
  "type": "Feature",
  "properties": {
    "iso:country":"US",
    "sg:address":"17545 FM 306",
    "sg:city":"New Braunfels",
    "sg:classifiers":[
        {
            "category":"Real Estate",
            "subcategory":"Real Estate Agent",
            "type":"Services"
        }
    ],
    "sg:phone":"+1 830 935 4355",
    "sg:postcode":"78133",
    "sg:province":"TX",
    "wof:name":"Hill Country Resort",
    "wof:placetype":"venue"
},
  "geometry": {"coordinates":[-98.21178,29.909993],"type":"Point"}
}