{
  "type": "Feature",
  "properties": {
    "iso:country":"US",
    "sg:address":"2250 Brown St",
    "sg:city":"Waxahachie",
    "sg:classifiers":[
        {
            "category":"Health Services",
            "subcategory":"Nursing And Care Facility",
            "type":"Services"
        }
    ],
    "sg:phone":"+1 972 937 2600",
    "sg:postcode":"75165",
    "sg:province":"TX",
    "wof:name":"Sterling House of Waxahachie",
    "wof:placetype":"venue"
},
  "geometry": {"coordinates":[-96.824251,32.416012],"type":"Point"}
}