{
  "type": "Feature",
  "properties": {
    "iso:country":"US",
    "sg:address":"1601 Reiser Ct",
    "sg:city":"Pearland",
    "sg:classifiers":[
        {
            "category":"Freight",
            "type":"Transportation"
        }
    ],
    "sg:phone":"+1 281 992 1675",
    "sg:postcode":"77581",
    "sg:province":"TX",
    "sg:tags":[
        "storage",
        "trucking",
        "sand",
        "without",
        "gravel",
        "local"
    ],
    "wof:name":"Ralph S Dorsett Trucking Inc",
    "wof:placetype":"venue"
},
  "geometry": {"coordinates":[-95.233255,29.538883],"type":"Point"}
}