{
  "type": "Feature",
  "properties": {
    "iso:country":"US",
    "sg:address":"2405 McFaddin Ave",
    "sg:city":"Beaumont",
    "sg:classifiers":[
        {
            "category":"Professional",
            "type":"Services"
        }
    ],
    "sg:phone":"+1 409 835 0659",
    "sg:postcode":"77702",
    "sg:province":"TX",
    "sg:tags":[
        "establishment"
    ],
    "wof:name":"Cranz Engravers Div Of Fr",
    "wof:placetype":"venue"
},
  "geometry": {"coordinates":[-94.124852,30.08664],"type":"Point"}
}