{
  "type": "Feature",
  "properties": {
    "iso:country":"US",
    "sg:address":"31119 Bulverde Hills Dr",
    "sg:city":"Bulverde",
    "sg:classifiers":[
        {
            "category":"Utilities",
            "subcategory":"Refuse",
            "type":"Services"
        }
    ],
    "sg:phone":"+1 830 980 2205",
    "sg:postcode":"78163",
    "sg:province":"TX",
    "sg:tags":[
        "disposal",
        "medical",
        "transport"
    ],
    "wof:name":"Medical Waste Removal",
    "wof:placetype":"venue"
},
  "geometry": {"coordinates":[-98.44278199999999,29.75562],"type":"Point"}
}