{
  "type": "Feature",
  "properties": {
    "iso:country":"US",
    "sg:address":"3510 NE 28th St",
    "sg:city":"Fort Worth",
    "sg:classifiers":[
        {
            "category":"Autos & Motor Vehicles",
            "subcategory":"Automobile Sales",
            "type":"Retail Goods"
        }
    ],
    "sg:phone":"+1 817 222 9559",
    "sg:postcode":"76111",
    "sg:province":"TX",
    "sg:tags":[
        "car",
        "dealer"
    ],
    "wof:name":"Ron Self Motor Co",
    "wof:placetype":"venue"
},
  "geometry": {"coordinates":[-97.296932,32.795041],"type":"Point"}
}