{
  "type": "Feature",
  "properties": {
    "iso:country":"US",
    "sg:address":"1520A E 6th St",
    "sg:city":"Weslaco",
    "sg:classifiers":[
        {
            "category":"Restaurant",
            "type":"Food & Drink"
        }
    ],
    "sg:phone":"+1 956 969 8052",
    "sg:postcode":"78596",
    "sg:province":"TX",
    "sg:tags":[
        "style",
        "family"
    ],
    "wof:name":"Restaurant Lagloria",
    "wof:placetype":"venue"
},
  "geometry": {"coordinates":[-97.976095,26.155623],"type":"Point"}
}