{
  "type": "Feature",
  "properties": {
    "iso:country":"US",
    "sg:address":"11711 Memorial Dr",
    "sg:city":"Houston",
    "sg:classifiers":[
        {
            "category":"Real Estate",
            "subcategory":"Real Estate Operator",
            "type":"Services"
        }
    ],
    "sg:phone":"+1 713 780 4936",
    "sg:postcode":"77024",
    "sg:province":"TX",
    "sg:tags":[
        "building",
        "apartment",
        "condominium"
    ],
    "wof:name":"Hudson Oaks Security",
    "wof:placetype":"venue"
},
  "geometry": {"coordinates":[-95.526022,29.752041],"type":"Point"}
}