{
  "type": "Feature",
  "properties": {
    "iso:country":"US",
    "sg:address":"1004 Mo Pac Cir Ste 201",
    "sg:city":"Austin",
    "sg:classifiers":[
        {
            "category":"Farming",
            "subcategory":"Farm",
            "type":"Manufacturing & Wholesale Goods"
        }
    ],
    "sg:phone":"+1 512 306 8300",
    "sg:postcode":"78746",
    "sg:province":"TX",
    "wof:name":"Behrens Phase E, Ltd.",
    "wof:placetype":"venue"
},
  "geometry": {"coordinates":[-97.783815,30.266294],"type":"Point"}
}