{
  "type": "Feature",
  "properties": {
    "iso:country":"US",
    "sg:address":"501 S Cage Blvd",
    "sg:city":"Pharr",
    "sg:classifiers":[
        {
            "category":"Travel",
            "subcategory":"Hotels & Motels",
            "type":"Entertainment"
        }
    ],
    "sg:phone":"+1 956 787 9958",
    "sg:postcode":"78577",
    "sg:province":"TX",
    "wof:name":"Sun Deck Motel",
    "wof:placetype":"venue"
},
  "geometry": {"coordinates":[-98.184946,26.189453],"type":"Point"}
}