{
  "type": "Feature",
  "properties": {
    "iso:country":"US",
    "sg:address":"727 Garcia St",
    "sg:city":"San Antonio",
    "sg:classifiers":[
        {
            "category":"Government",
            "subcategory":"Office",
            "type":"Public Place"
        }
    ],
    "sg:phone":"+1 210 472 6748",
    "sg:postcode":"78203",
    "sg:province":"TX",
    "sg:tags":[
        "farm",
        "agency"
    ],
    "wof:name":"Farm Service Agency",
    "wof:placetype":"venue"
},
  "geometry": {"coordinates":[-98.444492,29.41815],"type":"Point"}
}