{
  "type": "Feature",
  "properties": {
    "iso:country":"US",
    "sg:address":"4126 N Mesa St",
    "sg:city":"El Paso",
    "sg:classifiers":[
        {
            "category":"Shopping",
            "subcategory":"Gifts & Souvenirs",
            "type":"Retail Goods"
        }
    ],
    "sg:phone":"+1 915 543 9696",
    "sg:postcode":"79902",
    "sg:province":"TX",
    "sg:tags":[
        "collectible"
    ],
    "wof:name":"Beanie Planet",
    "wof:placetype":"venue"
},
  "geometry": {"coordinates":[-106.508413,31.792335],"type":"Point"}
}