{
  "type": "Feature",
  "properties": {
    "iso:country":"US",
    "sg:address":"1310 Sam Houston Dr",
    "sg:city":"Victoria",
    "sg:classifiers":[
        {
            "category":"Autos & Motor Vehicles",
            "subcategory":"Automobile Sales",
            "type":"Retail Goods"
        }
    ],
    "sg:phone":"+1 361 578 2444",
    "sg:postcode":"77901",
    "sg:province":"TX",
    "sg:tags":[
        "used"
    ],
    "wof:name":"Premier Auto Sales",
    "wof:placetype":"venue"
},
  "geometry": {"coordinates":[-96.978009,28.825927],"type":"Point"}
}