{
  "type": "Feature",
  "properties": {
    "iso:country":"US",
    "sg:address":"3530 Singleton Blvd",
    "sg:city":"Dallas",
    "sg:classifiers":[
        {
            "category":"Professional",
            "type":"Services"
        }
    ],
    "sg:phone":"+1 214 744 6229",
    "sg:postcode":"75212",
    "sg:province":"TX",
    "sg:tags":[
        "establishment"
    ],
    "wof:name":"Autobuses El Conejo",
    "wof:placetype":"venue"
},
  "geometry": {"coordinates":[-96.878225,32.778768],"type":"Point"}
}