{
  "type": "Feature",
  "properties": {
    "iso:country":"US",
    "sg:address":"1413 E 1st",
    "sg:city":"Hughes Springs",
    "sg:classifiers":[
        {
            "category":"Restaurant",
            "type":"Food & Drink"
        }
    ],
    "sg:menulink":"http://www.allmenus.com/tx/hughes-springs-avinger/130424-subway/menu/",
    "sg:phone":"+1 903 639 2576",
    "sg:postcode":"75656",
    "sg:province":"TX",
    "sg:tags":[
        "american",
        "sandwich"
    ],
    "wof:name":"Subway",
    "wof:placetype":"venue"
},
  "geometry": {"coordinates":[-94.612668,32.996728],"type":"Point"}
}