{
  "type": "Feature",
  "properties": {
    "iso:country":"US",
    "sg:address":"8235 Douglas Ave",
    "sg:city":"Dallas",
    "sg:classifiers":[
        {
            "category":"Mining & Drilling",
            "type":"Manufacturing & Wholesale Goods"
        }
    ],
    "sg:phone":"+1 214 265 1777",
    "sg:postcode":"75225",
    "sg:province":"TX",
    "sg:tags":[
        "development",
        "oil",
        "gas",
        "production",
        "exploration",
        "crude"
    ],
    "wof:name":"Mote Resources Inc",
    "wof:placetype":"venue"
},
  "geometry": {"coordinates":[-96.808756,32.863145],"type":"Point"}
}