{
  "type": "Feature",
  "properties": {
    "iso:country":"US",
    "sg:address":"9933 Consuela Dr",
    "sg:city":"Houston",
    "sg:classifiers":[
        {
            "category":"Building & Trades",
            "subcategory":"Construction",
            "type":"Services"
        }
    ],
    "sg:phone":"+1 713 777 8111",
    "sg:postcode":"77074",
    "sg:province":"TX",
    "sg:tags":[
        "contractor"
    ],
    "wof:name":"R W Wolfley Constructors",
    "wof:placetype":"venue"
},
  "geometry": {"coordinates":[-95.541377,29.671835],"type":"Point"}
}