{
  "type": "Feature",
  "properties": {
    "iso:country":"US",
    "sg:address":"508 50th St Unit D",
    "sg:city":"Lubbock",
    "sg:classifiers":[
        {
            "category":"Autos & Motor Vehicles",
            "subcategory":"Automobile Sales",
            "type":"Retail Goods"
        }
    ],
    "sg:phone":"+1 806 744 0596",
    "sg:postcode":"79404",
    "sg:province":"TX",
    "sg:tags":[
        "dealers-used",
        "car",
        "used",
        "cars-wholesale",
        "new"
    ],
    "wof:name":"Courtesy Auto Sales",
    "wof:placetype":"venue"
},
  "geometry": {"coordinates":[-101.840872,33.548816],"type":"Point"}
}