{
  "type": "Feature",
  "properties": {
    "iso:country":"US",
    "sg:address":"1026 Cheyenne Meadows Dr",
    "sg:city":"Katy",
    "sg:classifiers":[
        {
            "category":"Professional",
            "subcategory":"Computer Services",
            "type":"Services"
        }
    ],
    "sg:phone":"+1 281 389 4367",
    "sg:postcode":"77450",
    "sg:province":"TX",
    "sg:tags":[
        "related"
    ],
    "wof:name":"Allsop/Associates",
    "wof:placetype":"venue"
},
  "geometry": {"coordinates":[-95.766733,29.768228],"type":"Point"}
}