{
  "type": "Feature",
  "properties": {
    "iso:country":"US",
    "sg:address":"1313 W Calton Rd",
    "sg:city":"Laredo",
    "sg:classifiers":[
        {
            "category":"Utilities",
            "subcategory":"Telephone",
            "type":"Services"
        }
    ],
    "sg:phone":"+1 956 721 0600",
    "sg:postcode":"78041",
    "sg:province":"TX",
    "sg:tags":[
        "communications"
    ],
    "wof:name":"Road Runner High Speed Online",
    "wof:placetype":"venue"
},
  "geometry": {"coordinates":[-99.509601,27.54482],"type":"Point"}
}