{
  "type": "Feature",
  "properties": {
    "iso:country":"US",
    "sg:address":"107 S College Ave",
    "sg:city":"Cleveland",
    "sg:classifiers":[
        {
            "category":"Personal",
            "subcategory":"Barber",
            "type":"Services"
        }
    ],
    "sg:phone":"+1 281 592 1168",
    "sg:postcode":"77327",
    "sg:province":"TX",
    "sg:tags":[
        "shop"
    ],
    "wof:name":"Gary's Barber Shop",
    "wof:placetype":"venue"
},
  "geometry": {"coordinates":[-95.08771400000001,30.341466],"type":"Point"}
}