{
  "type": "Feature",
  "properties": {
    "iso:country":"US",
    "sg:address":"7901 Schrade Rd",
    "sg:city":"Rowlett",
    "sg:classifiers":[
        {
            "category":"Professional",
            "subcategory":"Art Services",
            "type":"Services"
        }
    ],
    "sg:phone":"+1 972 412 3503",
    "sg:postcode":"75088",
    "sg:province":"TX",
    "sg:tags":[
        "commercial",
        "design"
    ],
    "wof:name":"Bright Ideal",
    "wof:placetype":"venue"
},
  "geometry": {"coordinates":[-96.52189199999999,32.900045],"type":"Point"}
}