{
  "type": "Feature",
  "properties": {
    "iso:country":"US",
    "sg:address":"812 E Mansfield Hwy",
    "sg:city":"Kennedale",
    "sg:classifiers":[
        {
            "category":"Wholesale",
            "subcategory":"Machinery & Supplies",
            "type":"Manufacturing & Wholesale Goods"
        }
    ],
    "sg:phone":"+1 817 483 0700",
    "sg:postcode":"76060",
    "sg:province":"TX",
    "sg:tags":[
        "equipment",
        "industrial"
    ],
    "wof:name":"All Tools Supply Inc",
    "wof:placetype":"venue"
},
  "geometry": {"coordinates":[-97.21224100000001,32.637754],"type":"Point"}
}