{
  "type": "Feature",
  "properties": {
    "iso:country":"US",
    "sg:address":"202 Tuttle Rd",
    "sg:city":"San Antonio",
    "sg:classifiers":[
        {
            "category":"Banks & Credit Unions",
            "subcategory":"Financial Services",
            "type":"Services"
        }
    ],
    "sg:phone":"+1 210 822 6809",
    "sg:postcode":"78209",
    "sg:province":"TX",
    "sg:tags":[
        "investor"
    ],
    "wof:name":"Rachlar Investments Ltd",
    "wof:placetype":"venue"
},
  "geometry": {"coordinates":[-98.440529,29.473751],"type":"Point"}
}