{
  "type": "Feature",
  "properties": {
    "iso:country":"US",
    "sg:address":"4301 Versailles Ave",
    "sg:city":"Dallas",
    "sg:classifiers":[
        {
            "category":"Banks & Credit Unions",
            "subcategory":"Financial Services",
            "type":"Services"
        }
    ],
    "sg:phone":"+1 214 528 0064",
    "sg:postcode":"75205",
    "sg:province":"TX",
    "sg:tags":[
        "investment",
        "closed"
    ],
    "wof:name":"Lawson Asset Management",
    "wof:placetype":"venue"
},
  "geometry": {"coordinates":[-96.809871,32.831151],"type":"Point"}
}