{
  "type": "Feature",
  "properties": {
    "iso:country":"US",
    "sg:address":"1510 Pannell St",
    "sg:city":"Houston",
    "sg:classifiers":[
        {
            "category":"Organizations",
            "subcategory":"Religious Organization",
            "type":"Services"
        }
    ],
    "sg:phone":"+1 713 224 0052",
    "sg:postcode":"77020",
    "sg:province":"TX",
    "sg:tags":[
        "church"
    ],
    "wof:name":"Pleasant Hill Miss Bapt Chrch",
    "wof:placetype":"venue"
},
  "geometry": {"coordinates":[-95.331799,29.774807],"type":"Point"}
}