{
  "type": "Feature",
  "properties": {
    "iso:country":"US",
    "sg:address":"1109 Old Ocean Ave",
    "sg:city":"Sweeny",
    "sg:classifiers":[
        {
            "category":"Manufacturing",
            "subcategory":"Toys & Sporting Goods",
            "type":"Manufacturing & Wholesale Goods"
        }
    ],
    "sg:phone":"+1 979 548 1305",
    "sg:postcode":"77480",
    "sg:province":"TX",
    "sg:tags":[
        "mfg"
    ],
    "wof:name":"Lippylizzard Co",
    "wof:placetype":"venue"
},
  "geometry": {"coordinates":[-95.68918600000001,29.046483],"type":"Point"}
}