{
  "type": "Feature",
  "properties": {
    "iso:country":"US",
    "sg:address":"2811 Colonial Cir",
    "sg:city":"Mc Kinney",
    "sg:classifiers":[
        {
            "category":"Wholesale",
            "subcategory":"Electrical",
            "type":"Manufacturing & Wholesale Goods"
        }
    ],
    "sg:phone":"+1 972 562 8075",
    "sg:postcode":"75070",
    "sg:province":"TX",
    "sg:tags":[
        "electronic"
    ],
    "wof:name":"Peregrine Southwest Reps Inc",
    "wof:placetype":"venue"
},
  "geometry": {"coordinates":[-96.648318,33.17419],"type":"Point"}
}