{
  "type": "Feature",
  "properties": {
    "iso:country":"US",
    "sg:address":"1755 N Collins Blvd",
    "sg:city":"Richardson",
    "sg:classifiers":[
        {
            "category":"Professional",
            "subcategory":"Management & Consulting",
            "type":"Services"
        }
    ],
    "sg:phone":"+1 972 644 6886",
    "sg:postcode":"75080",
    "sg:province":"TX",
    "sg:tags":[
        "prepackaged",
        "business",
        "software"
    ],
    "wof:name":"Mobile Systems International",
    "wof:placetype":"venue"
},
  "geometry": {"coordinates":[-96.72380200000001,32.972659],"type":"Point"}
}