{
  "type": "Feature",
  "properties": {
    "iso:country":"US",
    "sg:address":"4234 Oak Arbor Dr",
    "sg:city":"Dallas",
    "sg:classifiers":[
        {
            "category":"Restaurant",
            "type":"Food & Drink"
        }
    ],
    "sg:phone":"+1 214 331 2685",
    "sg:postcode":"75233",
    "sg:province":"TX",
    "sg:tags":[
        "eating"
    ],
    "wof:name":"Lovies Kitchen",
    "wof:placetype":"venue"
},
  "geometry": {"coordinates":[-96.88367599999999,32.693265],"type":"Point"}
}