{
  "type": "Feature",
  "properties": {
    "iso:country":"US",
    "sg:address":"6407 Portuguese Bend Dr",
    "sg:city":"Missouri City",
    "sg:classifiers":[
        {
            "category":"Shopping",
            "type":"Retail Goods"
        }
    ],
    "sg:phone":"+1 281 208 2260",
    "sg:postcode":"77459",
    "sg:province":"TX",
    "sg:tags":[
        "merchandise"
    ],
    "wof:name":"Color Play",
    "wof:placetype":"venue"
},
  "geometry": {"coordinates":[-95.56505199999999,29.559288],"type":"Point"}
}