{
  "type": "Feature",
  "properties": {
    "iso:country":"US",
    "sg:address":"1908 Ascot Ln",
    "sg:city":"Cedar Park",
    "sg:classifiers":[
        {
            "category":"Professional",
            "subcategory":"Business Services",
            "type":"Services"
        }
    ],
    "sg:phone":"+1 512 554 1969",
    "sg:postcode":"78613",
    "sg:province":"TX",
    "sg:tags":[
        "notary"
    ],
    "wof:name":"Mobile Notary",
    "wof:placetype":"venue"
},
  "geometry": {"coordinates":[-97.84656,30.527995],"type":"Point"}
}