{
  "type": "Feature",
  "properties": {
    "iso:country":"US",
    "sg:address":"4162 Treadway Rd",
    "sg:city":"Beaumont",
    "sg:classifiers":[
        {
            "category":"Real Estate",
            "subcategory":"Real Estate Operator",
            "type":"Services"
        }
    ],
    "sg:phone":"+1 409 980 9789",
    "sg:postcode":"77706",
    "sg:province":"TX",
    "sg:tags":[
        "apartment"
    ],
    "wof:name":"Treadway Place Apartments",
    "wof:placetype":"venue"
},
  "geometry": {"coordinates":[-94.154116,30.115081],"type":"Point"}
}