{
  "type": "Feature",
  "properties": {
    "iso:country":"US",
    "sg:address":"1313 Iowa Dr",
    "sg:city":"Plano",
    "sg:classifiers":[
        {
            "category":"Professional",
            "subcategory":"Detective & Security Services",
            "type":"Services"
        }
    ],
    "sg:phone":"+1 972 267 8667",
    "sg:postcode":"75093",
    "sg:province":"TX",
    "sg:tags":[
        "guard",
        "patrol"
    ],
    "wof:name":"ISG Security Svc",
    "wof:placetype":"venue"
},
  "geometry": {"coordinates":[-96.78282400000001,33.017229],"type":"Point"}
}