{
  "type": "Feature",
  "properties": {
    "iso:country":"US",
    "sg:address":"5850 Belt Line Rd",
    "sg:city":"Dallas",
    "sg:classifiers":[
        {
            "category":"Communications",
            "type":"Services"
        }
    ],
    "sg:phone":"+1 972 661 5001",
    "sg:postcode":"75254",
    "sg:province":"TX",
    "sg:tags":[
        "communication"
    ],
    "wof:name":"Martel Communications Inc",
    "wof:placetype":"venue"
},
  "geometry": {"coordinates":[-96.808109,32.953943],"type":"Point"}
}