{
  "type": "Feature",
  "properties": {
    "iso:country":"US",
    "sg:address":"313 Ivy St",
    "sg:city":"Navasota",
    "sg:classifiers":[
        {
            "category":"Restaurant",
            "type":"Food & Drink"
        }
    ],
    "sg:phone":"+1 936 825 3880",
    "sg:postcode":"77868",
    "sg:province":"TX",
    "sg:tags":[
        "eating"
    ],
    "wof:name":"Margaritas Costna",
    "wof:placetype":"venue"
},
  "geometry": {"coordinates":[-96.073077,30.396986],"type":"Point"}
}