{
  "type": "Feature",
  "properties": {
    "iso:country":"US",
    "sg:address":"6536 Supply Row",
    "sg:city":"Houston",
    "sg:classifiers":[
        {
            "category":"Building & Trades",
            "subcategory":"Plumbing",
            "type":"Services"
        }
    ],
    "sg:phone":"+1 713 921 6565",
    "sg:postcode":"77011",
    "sg:province":"TX",
    "sg:tags":[
        "refrigeration",
        "contractor"
    ],
    "wof:name":"Atlantic Refrigeration Inc",
    "wof:placetype":"venue"
},
  "geometry": {"coordinates":[-95.312224,29.734464],"type":"Point"}
}