{
  "type": "Feature",
  "properties": {
    "iso:country":"US",
    "sg:address":"1935 E Centerville Rd",
    "sg:city":"Garland",
    "sg:classifiers":[
        {
            "category":"Education",
            "subcategory":"School",
            "type":"Public Place"
        }
    ],
    "sg:phone":"+1 214 703 3368",
    "sg:postcode":"75041",
    "sg:province":"TX",
    "sg:tags":[
        "k-",
        "private"
    ],
    "sg:website":"www.lakecitiesmontessori.com",
    "wof:name":"Lake Cities Montessori School LLC",
    "wof:placetype":"venue"
},
  "geometry": {"coordinates":[-96.60405299999999,32.892963],"type":"Point"}
}