{
  "type": "Feature",
  "properties": {
    "iso:country":"US",
    "sg:address":"810 N 3rd St",
    "sg:city":"Haskell",
    "sg:phone":"+1 940 864 3526",
    "sg:postcode":"79521",
    "sg:province":"TX",
    "sg:tags":[
        "farm",
        "grain",
        "wheat",
        "cash",
        "cotton"
    ],
    "wof:name":"Dunnam Farm",
    "wof:placetype":"venue"
},
  "geometry": {"coordinates":[-99.716313,33.159492],"type":"Point"}
}