{
  "type": "Feature",
  "properties": {
    "iso:country":"US",
    "sg:address":"17894 Co Rd 426",
    "sg:city":"Brazoria",
    "sg:classifiers":[
        {
            "category":"Shopping",
            "subcategory":"Florist",
            "type":"Retail Goods"
        }
    ],
    "sg:phone":"+1 979 798 1176",
    "sg:postcode":"77422",
    "sg:province":"TX",
    "wof:name":"Stems & Petals By Esther",
    "wof:placetype":"venue"
},
  "geometry": {"coordinates":[-95.674645,28.973141],"type":"Point"}
}