{
  "type": "Feature",
  "properties": {
    "iso:country":"US",
    "sg:address":"2820 Elm St",
    "sg:city":"Dallas",
    "sg:classifiers":[
        {
            "category":"Bars & Pubs",
            "type":"Food & Drink"
        }
    ],
    "sg:phone":"+1 214 747 7467",
    "sg:postcode":"75226",
    "sg:province":"TX",
    "sg:tags":[
        "drinking"
    ],
    "wof:name":"Pharmacy",
    "wof:placetype":"venue"
},
  "geometry": {"coordinates":[-96.78272699999999,32.784796],"type":"Point"}
}