{
  "type": "Feature",
  "properties": {
    "iso:country":"US",
    "sg:address":"2719 N Meadow Ave",
    "sg:city":"Laredo",
    "sg:classifiers":[
        {
            "category":"Wholesale",
            "subcategory":"Medical Equipment & Supplies",
            "type":"Manufacturing & Wholesale Goods"
        }
    ],
    "sg:phone":"+1 956 712 8170",
    "sg:postcode":"78040",
    "sg:province":"TX",
    "wof:name":"Aspin Health Systems Inc",
    "wof:placetype":"venue"
},
  "geometry": {"coordinates":[-99.48025,27.521184],"type":"Point"}
}