{
  "type": "Feature",
  "properties": {
    "iso:country":"US",
    "sg:address":"941 Liska Rd",
    "sg:city":"Ennis",
    "sg:classifiers":[
        {
            "category":"Building & Trades",
            "subcategory":"Cleaning & Sanitation",
            "type":"Services"
        }
    ],
    "sg:phone":"+1 972 878 0054",
    "sg:postcode":"75119",
    "sg:province":"TX",
    "sg:tags":[
        "maintenance"
    ],
    "wof:name":"Merritt Custodian Services",
    "wof:placetype":"venue"
},
  "geometry": {"coordinates":[-96.63454900000001,32.274245],"type":"Point"}
}