{
  "type": "Feature",
  "properties": {
    "iso:country":"US",
    "sg:address":"12501 Summerwood Dr",
    "sg:city":"Burleson",
    "sg:classifiers":[
        {
            "category":"Place Of Worship",
            "type":"Public Place"
        }
    ],
    "sg:phone":"+1 817 297 3949",
    "sg:postcode":"76028",
    "sg:province":"TX",
    "sg:tags":[
        "church"
    ],
    "wof:name":"The Living Connection",
    "wof:placetype":"venue"
},
  "geometry": {"coordinates":[-97.32663700000001,32.576012],"type":"Point"}
}