{
  "type": "Feature",
  "properties": {
    "iso:country":"US",
    "sg:address":"5815 W William Cannon Dr",
    "sg:city":"Austin",
    "sg:classifiers":[
        {
            "category":"Professional",
            "subcategory":"Research",
            "type":"Services"
        }
    ],
    "sg:phone":"+1 512 732 2444",
    "sg:postcode":"78749",
    "sg:province":"TX",
    "sg:tags":[
        "information",
        "medical"
    ],
    "wof:name":"Metaclin Research",
    "wof:placetype":"venue"
},
  "geometry": {"coordinates":[-97.86050899999999,30.227547],"type":"Point"}
}