{
  "type": "Feature",
  "properties": {
    "iso:country":"US",
    "sg:address":"101 E Dimmit St",
    "sg:city":"Crystal City",
    "sg:classifiers":[
        {
            "category":"Government",
            "subcategory":"Office",
            "type":"Public Place"
        }
    ],
    "sg:phone":"+1 830 374 3478",
    "sg:postcode":"78839",
    "sg:province":"TX",
    "sg:tags":[
        "city"
    ],
    "wof:name":"Crystal City City Hall",
    "wof:placetype":"venue"
},
  "geometry": {"coordinates":[-99.82802700000001,28.678708],"type":"Point"}
}