{
  "type": "Feature",
  "properties": {
    "iso:country":"US",
    "sg:address":"350 Stephenson Rd",
    "sg:city":"Vidor",
    "sg:classifiers":[
        {
            "category":"Retail",
            "subcategory":"Repair Shop",
            "type":"Services"
        }
    ],
    "sg:phone":"+1 409 783 0111",
    "sg:postcode":"77662",
    "sg:province":"TX",
    "sg:tags":[
        "taxidermist"
    ],
    "wof:name":"Bighorn Taxidermy",
    "wof:placetype":"venue"
},
  "geometry": {"coordinates":[-94.020712,30.22285],"type":"Point"}
}