{
  "type": "Feature",
  "properties": {
    "iso:country":"US",
    "sg:address":"4910 Rigsby Ave",
    "sg:city":"San Antonio",
    "sg:classifiers":[
        {
            "category":"Autos & Motor Vehicles",
            "subcategory":"Automobile Sales",
            "type":"Retail Goods"
        }
    ],
    "sg:phone":"+1 210 648 5181",
    "sg:postcode":"78222",
    "sg:province":"TX",
    "sg:tags":[
        "car",
        "dealer"
    ],
    "wof:name":"Trucks Etc",
    "wof:placetype":"venue"
},
  "geometry": {"coordinates":[-98.395347,29.398186],"type":"Point"}
}