{
  "type": "Feature",
  "properties": {
    "iso:country":"US",
    "sg:address":"1621 N Central Expy",
    "sg:city":"Richardson",
    "sg:classifiers":[
        {
            "category":"Home & Garden",
            "subcategory":"Home Furnishings",
            "type":"Retail Goods"
        },
        {
            "category":"Travel",
            "subcategory":"Travel Agent",
            "type":"Entertainment"
        }
    ],
    "sg:phone":"+1 972 690 3737",
    "sg:postcode":"75080",
    "sg:province":"TX",
    "sg:tags":[
        "agency",
        "bureau"
    ],
    "wof:name":"Casual Living 3",
    "wof:placetype":"venue"
},
  "geometry": {"coordinates":[-96.720705,32.96901],"type":"Point"}
}