{
  "type": "Feature",
  "properties": {
    "iso:country":"US",
    "sg:address":"2624 W William Cannon Dr",
    "sg:city":"Austin",
    "sg:classifiers":[
        {
            "category":"Professional",
            "subcategory":"Accounting & Tax Preparation",
            "type":"Services"
        },
        {
            "category":"Professional",
            "subcategory":"Business Services",
            "type":"Services"
        }
    ],
    "sg:phone":"+1 512 288 2011",
    "sg:postcode":"78745",
    "sg:province":"TX",
    "sg:tags":[
        "medical",
        "bookkeeping",
        "administration",
        "billing"
    ],
    "wof:name":"Complete Medical Management",
    "wof:placetype":"venue"
},
  "geometry": {"coordinates":[-97.815292,30.207239],"type":"Point"}
}