{
  "type": "Feature",
  "properties": {
    "iso:country":"US",
    "sg:address":"1811 Layton St",
    "sg:city":"Haltom City",
    "sg:classifiers":[
        {
            "category":"Autos & Motor Vehicles",
            "subcategory":"Auto Supplies",
            "type":"Retail Goods"
        }
    ],
    "sg:phone":"+1 817 838 6333",
    "sg:postcode":"76117",
    "sg:province":"TX",
    "sg:tags":[
        "automobile",
        "stereo",
        "radio"
    ],
    "wof:name":"Willie's Auto Elec Car Stereos",
    "wof:placetype":"venue"
},
  "geometry": {"coordinates":[-97.282414,32.787654],"type":"Point"}
}