{
  "type": "Feature",
  "properties": {
    "iso:country":"US",
    "sg:address":"203 W 20th St",
    "sg:city":"Mount Pleasant",
    "sg:classifiers":[
        {
            "category":"Health Services",
            "subcategory":"Doctor",
            "type":"Services"
        }
    ],
    "sg:phone":"+1 903 572 6618",
    "sg:postcode":"75455",
    "sg:province":"TX",
    "sg:tags":[
        "medical"
    ],
    "wof:name":"T F Williams MD",
    "wof:placetype":"venue"
},
  "geometry": {"coordinates":[-94.97196700000001,33.175189],"type":"Point"}
}