{
  "type": "Feature",
  "properties": {
    "iso:country":"US",
    "sg:address":"7901 Cameron Rd",
    "sg:city":"Austin",
    "sg:classifiers":[
        {
            "category":"Building & Trades",
            "subcategory":"Electrical",
            "type":"Services"
        }
    ],
    "sg:phone":"+1 512 977 9755",
    "sg:postcode":"78754",
    "sg:province":"TX",
    "sg:tags":[
        "electrician"
    ],
    "wof:name":"Genuine Clean",
    "wof:placetype":"venue"
},
  "geometry": {"coordinates":[-97.685203,30.334238],"type":"Point"}
}