{
  "type": "Feature",
  "properties": {
    "iso:country":"US",
    "sg:address":"8426 Winkler Dr",
    "sg:city":"Houston",
    "sg:classifiers":[
        {
            "category":"Building & Trades",
            "subcategory":"Construction",
            "type":"Services"
        }
    ],
    "sg:phone":"+1 713 644 0116",
    "sg:postcode":"77017",
    "sg:province":"TX",
    "sg:tags":[
        "utility",
        "contractor"
    ],
    "wof:name":"Colt Utilities Inc",
    "wof:placetype":"venue"
},
  "geometry": {"coordinates":[-95.265196,29.674983],"type":"Point"}
}