{
  "type": "Feature",
  "properties": {
    "iso:country":"US",
    "sg:address":"806 Belt Line Cove",
    "sg:city":"Richardson",
    "sg:classifiers":[
        {
            "category":"Professional",
            "subcategory":"Business Services",
            "type":"Services"
        }
    ],
    "sg:phone":"+1 972 479 0749",
    "sg:postcode":"75080",
    "sg:province":"TX",
    "wof:name":"Elite Integrated Solutions",
    "wof:placetype":"venue"
},
  "geometry": {"coordinates":[-96.750159,32.951292],"type":"Point"}
}