{
  "type": "Feature",
  "properties": {
    "iso:country":"US",
    "sg:address":"2929 Post Oak Blvd",
    "sg:city":"Houston",
    "sg:classifiers":[
        {
            "category":"Social Services",
            "subcategory":"Adult Care",
            "type":"Services"
        }
    ],
    "sg:phone":"+1 713 830 5024",
    "sg:postcode":"77056",
    "sg:province":"TX",
    "sg:tags":[
        "home",
        "residential"
    ],
    "wof:name":"Hampton Senior Living Network",
    "wof:placetype":"venue"
},
  "geometry": {"coordinates":[-95.460667,29.737928],"type":"Point"}
}