{
  "type": "Feature",
  "properties": {
    "iso:country":"US",
    "sg:address":"4102 Bellmead Dr",
    "sg:city":"Waco",
    "sg:classifiers":[
        {
            "category":"Shopping",
            "type":"Retail Goods"
        }
    ],
    "sg:phone":"+1 254 799 5450",
    "sg:postcode":"76705",
    "sg:province":"TX",
    "sg:tags":[
        "merchandise"
    ],
    "wof:name":"Wow 99 & Discount Tobacco",
    "wof:placetype":"venue"
},
  "geometry": {"coordinates":[-97.087829,31.600213],"type":"Point"}
}