{
  "type": "Feature",
  "properties": {
    "iso:country":"US",
    "sg:address":"2710 Central Fwy",
    "sg:city":"Wichita Falls",
    "sg:classifiers":[
        {
            "category":"Cinema",
            "subcategory":"Movie Rental",
            "type":"Entertainment"
        }
    ],
    "sg:phone":"+1 940 851 9990",
    "sg:postcode":"76306",
    "sg:province":"TX",
    "sg:tags":[
        "leasing",
        "video",
        "disc",
        "tape"
    ],
    "sg:website":"www.hollywoodvideo.com",
    "wof:name":"Hollywood Video",
    "wof:placetype":"venue"
},
  "geometry": {"coordinates":[-98.527002,33.952402],"type":"Point"}
}