{
  "type": "Feature",
  "properties": {
    "iso:country":"US",
    "sg:address":"7592 N General Bruce Dr",
    "sg:city":"Temple",
    "sg:phone":"+1 254 771 2244",
    "sg:postcode":"76501",
    "sg:province":"TX",
    "wof:name":"R & H Reefer & Trailer Repair",
    "wof:placetype":"venue"
},
  "geometry": {"coordinates":[-97.319214,31.167306],"type":"Point"}
}