{
  "type": "Feature",
  "properties": {
    "iso:country":"US",
    "sg:address":"126 Dixie Dr",
    "sg:city":"Clute",
    "sg:classifiers":[
        {
            "category":"Arts & Performance",
            "subcategory":"Arts Center",
            "type":"Entertainment"
        }
    ],
    "sg:phone":"+1 979 480 9311",
    "sg:postcode":"77531",
    "sg:province":"TX",
    "sg:tags":[
        "performing"
    ],
    "wof:name":"A Time To Dance",
    "wof:placetype":"venue"
},
  "geometry": {"coordinates":[-95.42035300000001,29.829643],"type":"Point"}
}