{
  "type": "Feature",
  "properties": {
    "iso:country":"US",
    "sg:address":"3235 5th St",
    "sg:city":"Port Arthur",
    "sg:classifiers":[
        {
            "category":"Wholesale",
            "subcategory":"Non-durable Goods",
            "type":"Manufacturing & Wholesale Goods"
        }
    ],
    "sg:phone":"+1 409 985 7544",
    "sg:postcode":"77642",
    "sg:province":"TX",
    "wof:name":"Trans National Distribution",
    "wof:placetype":"venue"
},
  "geometry": {"coordinates":[-93.914187,29.895445],"type":"Point"}
}