{
  "type": "Feature",
  "properties": {
    "iso:country":"US",
    "sg:address":"1428 35th St",
    "sg:city":"Galveston",
    "sg:classifiers":[
        {
            "category":"Food & Beverages",
            "subcategory":"Meat & Fish",
            "type":"Retail Goods"
        }
    ],
    "sg:phone":"+1 409 762 4510",
    "sg:postcode":"77550",
    "sg:province":"TX",
    "wof:name":"H & R Food Market",
    "wof:placetype":"venue"
},
  "geometry": {"coordinates":[-94.804224,29.292068],"type":"Point"}
}