{
  "type": "Feature",
  "properties": {
    "iso:country":"US",
    "sg:address":"311 S Rogers St",
    "sg:city":"Waxahachie",
    "sg:classifiers":[
        {
            "category":"Shopping",
            "subcategory":"Jewelry",
            "type":"Retail Goods"
        }
    ],
    "sg:phone":"+1 972 937 4381",
    "sg:postcode":"75165",
    "sg:province":"TX",
    "sg:tags":[
        "repair",
        "clock"
    ],
    "wof:name":"Maxwell Jewelry",
    "wof:placetype":"venue"
},
  "geometry": {"coordinates":[-96.84887000000001,32.384622],"type":"Point"}
}