{
  "type": "Feature",
  "properties": {
    "iso:country":"US",
    "sg:address":"500 E Rockport St",
    "sg:city":"Mathis",
    "sg:classifiers":[
        {
            "category":"Mining & Drilling",
            "type":"Manufacturing & Wholesale Goods"
        }
    ],
    "sg:phone":"+1 361 547 2304",
    "sg:postcode":"78368",
    "sg:province":"TX",
    "sg:tags":[
        "field",
        "oil",
        "well"
    ],
    "wof:name":"Sid Pollock",
    "wof:placetype":"venue"
},
  "geometry": {"coordinates":[-97.823837,28.09223],"type":"Point"}
}