{
  "type": "Feature",
  "properties": {
    "iso:country":"US",
    "sg:address":"1433 S 14th St",
    "sg:city":"Abilene",
    "sg:classifiers":[
        {
            "category":"Education",
            "subcategory":"Special Training",
            "type":"Public Place"
        }
    ],
    "sg:phone":"+1 325 677 0850",
    "sg:postcode":"79602",
    "sg:province":"TX",
    "sg:tags":[
        "instruction",
        "driving"
    ],
    "wof:name":"A Ok Driving School",
    "wof:placetype":"venue"
},
  "geometry": {"coordinates":[-99.740595,32.432011],"type":"Point"}
}