{
  "type": "Feature",
  "properties": {
    "iso:country":"US",
    "sg:address":"411 N Washington Ave Ste 5000",
    "sg:city":"Dallas",
    "sg:classifiers":[
        {
            "category":"Personal",
            "subcategory":"Hair Removal",
            "type":"Services"
        }
    ],
    "sg:phone":"+1 214 887 1577",
    "sg:postcode":"75246",
    "sg:province":"TX",
    "sg:tags":[
        "laser"
    ],
    "wof:name":"Renaissance Skin Care",
    "wof:placetype":"venue"
},
  "geometry": {"coordinates":[-96.775299,32.788502],"type":"Point"}
}