{
  "type": "Feature",
  "properties": {
    "iso:country":"US",
    "sg:address":"700 N Pearl St",
    "sg:city":"Dallas",
    "sg:classifiers":[
        {
            "category":"Building & Trades",
            "subcategory":"Construction",
            "type":"Services"
        }
    ],
    "sg:phone":"+1 214 261 5126",
    "sg:postcode":"75201",
    "sg:province":"TX",
    "sg:tags":[
        "mason",
        "masonry",
        "industrial",
        "contractors-commercial",
        "contractor"
    ],
    "wof:name":"Tech Central",
    "wof:placetype":"venue"
},
  "geometry": {"coordinates":[-96.795976,32.786723],"type":"Point"}
}