{
  "type": "Feature",
  "properties": {
    "iso:country":"US",
    "sg:address":"1314 N Industrial Blvd",
    "sg:city":"Dallas",
    "sg:classifiers":[
        {
            "category":"Shopping",
            "type":"Retail Goods"
        }
    ],
    "sg:phone":"+1 214 747 1900",
    "sg:postcode":"75207",
    "sg:province":"TX",
    "sg:tags":[
        "candle"
    ],
    "wof:name":"Candle Lady",
    "wof:placetype":"venue"
},
  "geometry": {"coordinates":[-96.820013,32.789805],"type":"Point"}
}