{
  "type": "Feature",
  "properties": {
    "iso:country":"US",
    "sg:address":"4735 Almond Ave",
    "sg:city":"Dallas",
    "sg:classifiers":[
        {
            "category":"Food & Beverages",
            "subcategory":"Liquor & Beverages",
            "type":"Retail Goods"
        }
    ],
    "sg:phone":"+1 214 631 2750",
    "sg:postcode":"75247",
    "sg:province":"TX",
    "sg:tags":[
        "alcoholic"
    ],
    "wof:name":"ABC Liquor License Bookkeeping",
    "wof:placetype":"venue"
},
  "geometry": {"coordinates":[-96.879378,32.805747],"type":"Point"}
}