{
  "type": "Feature",
  "properties": {
    "iso:country":"US",
    "sg:address":"2219 E Euless Blvd",
    "sg:city":"Euless",
    "sg:classifiers":[
        {
            "category":"Organizations",
            "subcategory":"Professional Association",
            "type":"Services"
        }
    ],
    "sg:phone":"+1 817 429 2323",
    "sg:postcode":"76040",
    "sg:province":"TX",
    "sg:tags":[
        "chambers",
        "commerce"
    ],
    "wof:name":"American Indian Chamber-Cmmrc",
    "wof:placetype":"venue"
},
  "geometry": {"coordinates":[-97.120132,32.821419],"type":"Point"}
}