{
  "type": "Feature",
  "properties": {
    "iso:country":"US",
    "sg:address":"2301 McDaniel Dr",
    "sg:city":"Carrollton",
    "sg:phone":"+1 972 241 1146",
    "sg:postcode":"75006",
    "sg:province":"TX",
    "sg:tags":[
        "equipment",
        "supply"
    ],
    "wof:name":"R W Smith & Co",
    "wof:placetype":"venue"
},
  "geometry": {"coordinates":[-96.921806,32.928523],"type":"Point"}
}