{
  "type": "Feature",
  "properties": {
    "iso:country":"US",
    "sg:address":"603 Grantham Rd",
    "sg:city":"Baytown",
    "sg:classifiers":[
        {
            "category":"Arts & Performance",
            "subcategory":"Theater",
            "type":"Entertainment"
        }
    ],
    "sg:phone":"+1 281 420 3007",
    "sg:postcode":"77521",
    "sg:province":"TX",
    "sg:tags":[
        "group"
    ],
    "wof:name":"Olufemi",
    "wof:placetype":"venue"
},
  "geometry": {"coordinates":[-94.972959,29.751662],"type":"Point"}
}