{
  "type": "Feature",
  "properties": {
    "iso:country":"US",
    "sg:address":"2516 Cedar Elm Ln",
    "sg:city":"Plano",
    "sg:classifiers":[
        {
            "category":"Building & Trades",
            "subcategory":"Landscaping Services",
            "type":"Services"
        }
    ],
    "sg:phone":"+1 972 867 2175",
    "sg:postcode":"75075",
    "sg:province":"TX",
    "sg:tags":[
        "lawn",
        "maintenance",
        "grounds"
    ],
    "wof:name":"Greentex",
    "wof:placetype":"venue"
},
  "geometry": {"coordinates":[-96.740611,33.027579],"type":"Point"}
}