{
  "type": "Feature",
  "properties": {
    "iso:country":"US",
    "sg:address":"4718 Hallmark Dr",
    "sg:city":"Houston",
    "sg:classifiers":[
        {
            "category":"Personal",
            "subcategory":"Beauty Salon",
            "type":"Services"
        }
    ],
    "sg:phone":"+1 713 622 0976",
    "sg:postcode":"77056",
    "sg:province":"TX",
    "sg:tags":[
        "shop"
    ],
    "wof:name":"Marys Hair Salon",
    "wof:placetype":"venue"
},
  "geometry": {"coordinates":[-95.456306,29.750301],"type":"Point"}
}