{
  "type": "Feature",
  "properties": {
    "iso:country":"US",
    "sg:address":"609 E Main St",
    "sg:city":"Arlington",
    "sg:classifiers":[
        {
            "category":"Shopping",
            "subcategory":"Clothing, Apparel, & Fashions",
            "type":"Retail Goods"
        }
    ],
    "sg:phone":"+1 817 303 1990",
    "sg:postcode":"76010",
    "sg:province":"TX",
    "wof:name":"Alluringly Yours",
    "wof:placetype":"venue"
},
  "geometry": {"coordinates":[-97.100803,32.736413],"type":"Point"}
}