{
  "type": "Feature",
  "properties": {
    "iso:country":"US",
    "sg:address":"108 Aspen Ln",
    "sg:city":"San Antonio",
    "sg:classifiers":[
        {
            "category":"Arena",
            "subcategory":"Sports Club",
            "type":"Entertainment"
        }
    ],
    "sg:phone":"+1 210 494 0751",
    "sg:postcode":"78232",
    "sg:province":"TX",
    "wof:name":"Baseball/Softball",
    "wof:placetype":"venue"
},
  "geometry": {"coordinates":[-98.482581,29.571668],"type":"Point"}
}