{
  "type": "Feature",
  "properties": {
    "iso:country":"US",
    "sg:address":"660 International Pkwy",
    "sg:city":"Richardson",
    "sg:classifiers":[
        {
            "category":"Professional",
            "subcategory":"Management & Consulting",
            "type":"Services"
        }
    ],
    "sg:phone":"+1 972 398 3585",
    "sg:postcode":"75081",
    "sg:province":"TX",
    "sg:tags":[
        "agricultural",
        "consultant"
    ],
    "wof:name":"AGC",
    "wof:placetype":"venue"
},
  "geometry": {"coordinates":[-96.708626,32.956135],"type":"Point"}
}