{
  "type": "Feature",
  "properties": {
    "iso:country":"US",
    "sg:address":"7034 Congressional Blvd",
    "sg:city":"San Antonio",
    "sg:classifiers":[
        {
            "category":"Wholesale",
            "subcategory":"Vending Machines",
            "type":"Manufacturing & Wholesale Goods"
        }
    ],
    "sg:phone":"+1 210 666 3910",
    "sg:postcode":"78244",
    "sg:province":"TX",
    "sg:tags":[
        "operator"
    ],
    "wof:name":"Hambys Snack Vending",
    "wof:placetype":"venue"
},
  "geometry": {"coordinates":[-98.343205,29.495416],"type":"Point"}
}