{
  "type": "Feature",
  "properties": {
    "iso:country":"US",
    "sg:address":"6000 Bryan Pkwy",
    "sg:city":"Dallas",
    "sg:classifiers":[
        {
            "category":"Professional",
            "subcategory":"Business Services",
            "type":"Services"
        }
    ],
    "sg:phone":"+1 214 821 2592",
    "sg:postcode":"75206",
    "sg:province":"TX",
    "wof:name":"Martin Purple Enterprises",
    "wof:placetype":"venue"
},
  "geometry": {"coordinates":[-96.76285300000001,32.809627],"type":"Point"}
}