{
  "type": "Feature",
  "properties": {
    "iso:country":"US",
    "sg:address":"1060 NE Green Oaks Blvd",
    "sg:city":"Arlington",
    "sg:classifiers":[
        {
            "category":"Banks & Credit Unions",
            "subcategory":"Bank",
            "type":"Services"
        }
    ],
    "sg:phone":"+1 817 468 3222",
    "sg:postcode":"76006",
    "sg:province":"TX",
    "sg:website":"www.arlingtonnationalbank.com",
    "wof:name":"Summit Bank Na",
    "wof:placetype":"venue"
},
  "geometry": {"coordinates":[-97.094572,32.784411],"type":"Point"}
}