{
  "type": "Feature",
  "properties": {
    "iso:country":"US",
    "sg:address":"418 N 5th St",
    "sg:city":"La Porte",
    "sg:classifiers":[
        {
            "category":"Building & Trades",
            "subcategory":"Landscaping Services",
            "type":"Services"
        }
    ],
    "sg:phone":"+1 281 470 1028",
    "sg:postcode":"77571",
    "sg:province":"TX",
    "wof:name":"Jacksons Trash Hlg Lawn Mntnan",
    "wof:placetype":"venue"
},
  "geometry": {"coordinates":[-95.024596,29.670273],"type":"Point"}
}