{
  "type": "Feature",
  "properties": {
    "iso:country":"US",
    "sg:address":"4503 Bridge St",
    "sg:city":"Fort Worth",
    "sg:classifiers":[
        {
            "category":"Organizations",
            "subcategory":"Religious Organization",
            "type":"Services"
        }
    ],
    "sg:phone":"+1 817 429 2920",
    "sg:postcode":"76103",
    "sg:province":"TX",
    "wof:name":"Catholic Renewal Ctr Of N Tx",
    "wof:placetype":"venue"
},
  "geometry": {"coordinates":[-97.258596,32.758975],"type":"Point"}
}