{
  "type": "Feature",
  "properties": {
    "iso:country":"US",
    "sg:address":"143 North St",
    "sg:city":"Brownsville",
    "sg:classifiers":[
        {
            "category":"Professional",
            "type":"Services"
        }
    ],
    "sg:phone":"+1 956 541 5771",
    "sg:postcode":"78521",
    "sg:province":"TX",
    "sg:tags":[
        "establishment"
    ],
    "wof:name":"Intermex Industrial Group",
    "wof:placetype":"venue"
},
  "geometry": {"coordinates":[-97.485544,25.922555],"type":"Point"}
}