{
  "type": "Feature",
  "properties": {
    "iso:country":"US",
    "sg:address":"13350 N Dallas Pkwy #2285",
    "sg:city":"Dallas",
    "sg:classifiers":[
        {
            "category":"Shopping",
            "subcategory":"Clothing, Apparel, & Fashions",
            "type":"Retail Goods"
        },
        {
            "category":"Sports & Exercise",
            "subcategory":"Bicycle Rental",
            "type":"Entertainment"
        },
        {
            "category":"Sports & Exercise",
            "subcategory":"Gym",
            "type":"Entertainment"
        }
    ],
    "sg:phone":"+1 972 385 2316",
    "sg:postcode":"75240",
    "sg:province":"TX",
    "sg:tags":[
        "yoga",
        "clothing",
        "wear",
        "women's"
    ],
    "sg:website":"www.lululemon.com",
    "wof:name":"lululemon athletica",
    "wof:placetype":"venue"
},
  "geometry": {"coordinates":[-96.819592,32.929958],"type":"Point"}
}