{
  "type": "Feature",
  "properties": {
    "iso:country":"US",
    "sg:address":"5150 Hogaboom Rd",
    "sg:city":"Port Arthur",
    "sg:classifiers":[
        {
            "category":"Wholesale",
            "subcategory":"Construction Materials",
            "type":"Manufacturing & Wholesale Goods"
        }
    ],
    "sg:phone":"+1 409 962 3801",
    "sg:postcode":"77642",
    "sg:province":"TX",
    "sg:tags":[
        "fence"
    ],
    "sg:website":"www.hindsfence.com",
    "wof:name":"Hinds Quality Fences Inc",
    "wof:placetype":"venue"
},
  "geometry": {"coordinates":[-93.94100299999999,29.945777],"type":"Point"}
}