{
  "type": "Feature",
  "properties": {
    "iso:country":"US",
    "sg:address":"1327 Glen Oaks Dr",
    "sg:city":"Conroe",
    "sg:classifiers":[
        {
            "category":"Building & Trades",
            "subcategory":"Construction",
            "type":"Services"
        }
    ],
    "sg:phone":"+1 281 682 1063",
    "sg:postcode":"77385",
    "sg:province":"TX",
    "sg:tags":[
        "porch",
        "enclosure",
        "patio",
        "deck"
    ],
    "wof:name":"Total Enclosures",
    "wof:placetype":"venue"
},
  "geometry": {"coordinates":[-95.43197499999999,30.19987],"type":"Point"}
}