{
  "type": "Feature",
  "properties": {
    "iso:country":"US",
    "sg:address":"1400 Jackson Keller Rd",
    "sg:city":"San Antonio",
    "sg:classifiers":[
        {
            "category":"Education",
            "subcategory":"School",
            "type":"Public Place"
        }
    ],
    "sg:phone":"+1 210 442 2505",
    "sg:postcode":"78213",
    "sg:province":"TX",
    "wof:name":"North East School Of The Arts",
    "wof:placetype":"venue"
},
  "geometry": {"coordinates":[-98.51429,29.507267],"type":"Point"}
}