{
  "type": "Feature",
  "properties": {
    "iso:country":"US",
    "sg:address":"9727 Hidden Brook",
    "sg:city":"San Antonio",
    "sg:classifiers":[
        {
            "category":"Shopping",
            "subcategory":"Catalog Store",
            "type":"Retail Goods"
        }
    ],
    "sg:phone":"+1 210 543 1557",
    "sg:postcode":"78250",
    "sg:province":"TX",
    "sg:tags":[
        "mail",
        "house"
    ],
    "wof:name":"Pebble Road",
    "wof:placetype":"venue"
},
  "geometry": {"coordinates":[-98.692725,29.493795],"type":"Point"}
}