{
  "type": "Feature",
  "properties": {
    "iso:country":"US",
    "sg:address":"18767 Forest Lane Cir",
    "sg:city":"New Caney",
    "sg:classifiers":[
        {
            "category":"Retail",
            "subcategory":"Auto Repair",
            "type":"Services"
        }
    ],
    "sg:phone":"+1 281 689 5558",
    "sg:postcode":"77357",
    "sg:province":"TX",
    "sg:tags":[
        "wrecker"
    ],
    "wof:name":"Lone Star Wrecker & Storage",
    "wof:placetype":"venue"
},
  "geometry": {"coordinates":[-95.240505,30.16552],"type":"Point"}
}