{
  "type": "Feature",
  "properties": {
    "iso:country":"US",
    "sg:address":"505 Hawthorne St",
    "sg:city":"Irving",
    "sg:classifiers":[
        {
            "category":"Building & Trades",
            "subcategory":"Plumbing",
            "type":"Services"
        }
    ],
    "sg:phone":"+1 972 253 5706",
    "sg:postcode":"75061",
    "sg:province":"TX",
    "sg:tags":[
        "contractor"
    ],
    "wof:name":"JERRELL'S PLUMBING",
    "wof:placetype":"venue"
},
  "geometry": {"coordinates":[-96.962244,32.818898],"type":"Point"}
}