{
  "type": "Feature",
  "properties": {
    "iso:country":"US",
    "sg:address":"1542 Nottingham Dr",
    "sg:city":"Kaufman",
    "sg:classifiers":[
        {
            "category":"Building & Trades",
            "subcategory":"Electrical",
            "type":"Services"
        }
    ],
    "sg:phone":"+1 972 962 7947",
    "sg:postcode":"75142",
    "sg:province":"TX",
    "sg:tags":[
        "electric",
        "contractor"
    ],
    "wof:name":"Bobby Shaw Electrical Inc",
    "wof:placetype":"venue"
},
  "geometry": {"coordinates":[-96.320515,32.558919],"type":"Point"}
}