{
  "type": "Feature",
  "properties": {
    "iso:country":"US",
    "sg:address":"4613 Creekmont Dr",
    "sg:city":"Houston",
    "sg:classifiers":[
        {
            "category":"Manufacturing",
            "subcategory":"Apparel",
            "type":"Manufacturing & Wholesale Goods"
        }
    ],
    "sg:phone":"+1 713 864 1550",
    "sg:postcode":"77091",
    "sg:province":"TX",
    "sg:tags":[
        "outerwear",
        "mfg"
    ],
    "wof:name":"Z Wear Inc",
    "wof:placetype":"venue"
},
  "geometry": {"coordinates":[-95.458482,29.842261],"type":"Point"}
}