{
  "type": "Feature",
  "properties": {
    "iso:country":"US",
    "sg:address":"201 Bedford Rd",
    "sg:city":"Bedford",
    "sg:classifiers":[
        {
            "category":"Retail",
            "subcategory":"Auto Repair",
            "type":"Services"
        }
    ],
    "sg:phone":"+1 817 282 0103",
    "sg:postcode":"76022",
    "sg:province":"TX",
    "sg:tags":[
        "shop",
        "automotive"
    ],
    "wof:name":"Super Lube",
    "wof:placetype":"venue"
},
  "geometry": {"coordinates":[-97.163675,32.83403],"type":"Point"}
}