{
  "type": "Feature",
  "properties": {
    "iso:country":"US",
    "sg:address":"14415 Briarcrest Dr",
    "sg:city":"Mesquite",
    "sg:classifiers":[
        {
            "category":"Personal",
            "subcategory":"Beauty Salon",
            "type":"Services"
        }
    ],
    "sg:phone":"+1 972 557 0333",
    "sg:postcode":"75180",
    "sg:province":"TX",
    "wof:name":"Bushwackers",
    "wof:placetype":"venue"
},
  "geometry": {"coordinates":[-96.595708,32.711769],"type":"Point"}
}