{
  "type": "Feature",
  "properties": {
    "iso:country":"US",
    "sg:address":"8774 Fox Meadow Way",
    "sg:city":"Fort Worth",
    "sg:classifiers":[
        {
            "category":"Real Estate",
            "subcategory":"Real Estate Agent",
            "type":"Services"
        }
    ],
    "sg:phone":"+1 817 370 7413",
    "sg:postcode":"76123",
    "sg:province":"TX",
    "wof:name":"Mary A Hanson Appraisals",
    "wof:placetype":"venue"
},
  "geometry": {"coordinates":[-97.378275,32.614653],"type":"Point"}
}