{
  "type": "Feature",
  "properties": {
    "iso:country":"US",
    "sg:address":"6111 Gladewell Dr",
    "sg:city":"Houston",
    "sg:classifiers":[
        {
            "category":"Social Services",
            "type":"Services"
        }
    ],
    "sg:phone":"+1 281 933 8737",
    "sg:postcode":"77072",
    "sg:province":"TX",
    "wof:name":"Texas Human Services Place",
    "wof:placetype":"venue"
},
  "geometry": {"coordinates":[-95.568094,29.714079],"type":"Point"}
}