{
  "type": "Feature",
  "properties": {
    "iso:country":"US",
    "sg:address":"1022 Pacific Ave",
    "sg:city":"Dallas",
    "sg:classifiers":[
        {
            "category":"Restaurant",
            "type":"Food & Drink"
        }
    ],
    "sg:phone":"+1 214 742 1891",
    "sg:postcode":"75202",
    "sg:province":"TX",
    "sg:tags":[
        "drinking",
        "eating"
    ],
    "wof:name":"Barbecue Etc",
    "wof:placetype":"venue"
},
  "geometry": {"coordinates":[-96.80404799999999,32.781062],"type":"Point"}
}