{
  "type": "Feature",
  "properties": {
    "iso:country":"US",
    "sg:address":"3714 Haven Pines Dr",
    "sg:city":"Humble",
    "sg:classifiers":[
        {
            "category":"Manufacturing",
            "subcategory":"Tools & Machinery",
            "type":"Manufacturing & Wholesale Goods"
        }
    ],
    "sg:phone":"+1 281 360 1802",
    "sg:postcode":"77345",
    "sg:province":"TX",
    "sg:tags":[
        "industrial",
        "mfg"
    ],
    "wof:name":"Sjiii Inc",
    "wof:placetype":"venue"
},
  "geometry": {"coordinates":[-95.18079400000001,30.065205],"type":"Point"}
}