{
  "type": "Feature",
  "properties": {
    "iso:country":"US",
    "sg:address":"17100 Timber Rd",
    "sg:city":"Troup",
    "sg:classifiers":[
        {
            "category":"Professional",
            "subcategory":"Business Services",
            "type":"Services"
        }
    ],
    "sg:phone":"+1 903 842 4011",
    "sg:postcode":"75789",
    "sg:province":"TX",
    "wof:name":"Matlocks Custom Draperies",
    "wof:placetype":"venue"
},
  "geometry": {"coordinates":[-95.12642200000001,32.185376],"type":"Point"}
}