{
  "type": "Feature",
  "properties": {
    "iso:country":"US",
    "sg:address":"9651 Bissonnet St Ste 201",
    "sg:city":"Houston",
    "sg:classifiers":[
        {
            "category":"Food & Beverages",
            "subcategory":"Meat & Fish",
            "type":"Retail Goods"
        }
    ],
    "sg:phone":"+1 713 771 6464",
    "sg:postcode":"77036",
    "sg:province":"TX",
    "sg:tags":[
        "shop"
    ],
    "wof:name":"Halal Meats Middle East",
    "wof:placetype":"venue"
},
  "geometry": {"coordinates":[-95.547302,29.6754],"type":"Point"}
}