{
  "type": "Feature",
  "properties": {
    "iso:country":"US",
    "sg:address":"5225 China Berry Dr",
    "sg:city":"Mc Kinney",
    "sg:classifiers":[
        {
            "category":"Building & Trades",
            "subcategory":"Landscaping Services",
            "type":"Services"
        }
    ],
    "sg:phone":"+1 972 529 1560",
    "sg:postcode":"75070",
    "sg:province":"TX",
    "wof:name":"Thomas Lawn Care",
    "wof:placetype":"venue"
},
  "geometry": {"coordinates":[-96.684439,33.161465],"type":"Point"}
}