{
  "type": "Feature",
  "properties": {
    "iso:country":"US",
    "sg:address":"10840 Burgess Rd",
    "sg:city":"Temple",
    "sg:classifiers":[
        {
            "category":"Shopping",
            "type":"Retail Goods"
        }
    ],
    "sg:phone":"+1 254 982 4474",
    "sg:postcode":"76501",
    "sg:province":"TX",
    "sg:tags":[
        "merchandise"
    ],
    "wof:name":"Don W Ross",
    "wof:placetype":"venue"
},
  "geometry": {"coordinates":[-97.328738,30.98062],"type":"Point"}
}