{
  "type": "Feature",
  "properties": {
    "iso:country":"US",
    "sg:address":"208 W Myrtle St",
    "sg:city":"Angleton",
    "sg:classifiers":[
        {
            "category":"Organizations",
            "subcategory":"Religious Organization",
            "type":"Services"
        }
    ],
    "sg:phone":"+1 979 848 1404",
    "sg:postcode":"77515",
    "sg:province":"TX",
    "wof:name":"Alpha & Omega Holiness Church",
    "wof:placetype":"venue"
},
  "geometry": {"coordinates":[-95.43337099999999,29.165402],"type":"Point"}
}