{
  "type": "Feature",
  "properties": {
    "iso:country":"US",
    "sg:address":"30 Schubach Dr",
    "sg:city":"Sugar Land",
    "sg:classifiers":[
        {
            "category":"Real Estate",
            "subcategory":"Real Estate Agent",
            "type":"Services"
        }
    ],
    "sg:phone":"+1 281 686 8896",
    "sg:postcode":"77479",
    "sg:province":"TX",
    "wof:name":"Long Tonint Plaza Apartments",
    "wof:placetype":"venue"
},
  "geometry": {"coordinates":[-95.672893,29.592229],"type":"Point"}
}