{
  "type": "Feature",
  "properties": {
    "iso:country":"US",
    "sg:address":"13280 Northwest Fwy #F301",
    "sg:city":"Houston",
    "sg:classifiers":[
        {
            "category":"Professional",
            "subcategory":"Engineering",
            "type":"Services"
        },
        {
            "category":"Home & Garden",
            "subcategory":"Building Materials",
            "type":"Retail Goods"
        },
        {
            "category":"Building & Trades",
            "subcategory":"Construction",
            "type":"Services"
        }
    ],
    "sg:phone":"+1 281 619 8846",
    "sg:postcode":"77092",
    "sg:province":"TX",
    "sg:tags":[
        "system",
        "specialty",
        "heating",
        "contractor",
        "equipment",
        "air conditioning"
    ],
    "sg:website":"http://find.trane.com/tcs-dealer-415110?utm_source=YP&utm_medium=banner&utm_campaign=TL",
    "wof:name":"Hi-Tech Mechanical Inc.",
    "wof:placetype":"venue"
},
  "geometry": {"coordinates":[-95.487976,29.837854],"type":"Point"}
}