{
  "type": "Feature",
  "properties": {
    "iso:country":"US",
    "sg:address":"2129 Wroxton Rd",
    "sg:city":"Houston",
    "sg:classifiers":[
        {
            "category":"Organizations",
            "subcategory":"Membership Organization",
            "type":"Services"
        }
    ],
    "sg:phone":"+1 713 523 0447",
    "sg:postcode":"77005",
    "sg:province":"TX",
    "wof:name":"Mackintosh Fndtion Hnry George",
    "wof:placetype":"venue"
},
  "geometry": {"coordinates":[-95.410044,29.724663],"type":"Point"}
}