{
  "type": "Feature",
  "properties": {
    "iso:country":"US",
    "sg:address":"3525 Rolling Green Dr",
    "sg:city":"Abilene",
    "sg:classifiers":[
        {
            "category":"Real Estate",
            "subcategory":"Real Estate Services",
            "type":"Services"
        },
        {
            "category":"Real Estate",
            "subcategory":"Real Estate Operator",
            "type":"Services"
        }
    ],
    "sg:phone":"+1 325 691 1470",
    "sg:postcode":"79606",
    "sg:province":"TX",
    "sg:tags":[
        "apartment",
        "condominium",
        "vacancy",
        "management",
        "listing",
        "rental",
        "finder"
    ],
    "wof:name":"Newport Village Apts.",
    "wof:placetype":"venue"
},
  "geometry": {"coordinates":[-99.76733,32.400211],"type":"Point"}
}