{
  "type": "Feature",
  "properties": {
    "iso:country":"US",
    "sg:address":"4524 Flo Ave",
    "sg:city":"Dallas",
    "sg:classifiers":[
        {
            "category":"Professional",
            "type":"Services"
        }
    ],
    "sg:phone":"+1 214 330 6994",
    "sg:postcode":"75211",
    "sg:province":"TX",
    "wof:name":"King Satellite Services Inc",
    "wof:placetype":"venue"
},
  "geometry": {"coordinates":[-96.897173,32.734074],"type":"Point"}
}