{
  "type": "Feature",
  "properties": {
    "iso:country":"US",
    "sg:address":"507 N 8th St",
    "sg:city":"Killeen",
    "sg:classifiers":[
        {
            "category":"Organizations",
            "subcategory":"Religious Organization",
            "type":"Services"
        }
    ],
    "sg:phone":"+1 254 634 6363",
    "sg:postcode":"76541",
    "sg:province":"TX",
    "sg:tags":[
        "child",
        "day",
        "care"
    ],
    "wof:name":"First United Methodist Church",
    "wof:placetype":"venue"
},
  "geometry": {"coordinates":[-97.72593999999999,31.122433],"type":"Point"}
}