{
  "type": "Feature",
  "properties": {
    "iso:country":"US",
    "sg:address":"777 Summit Run",
    "sg:city":"Lewisville",
    "sg:classifiers":[
        {
            "category":"Insurance",
            "subcategory":"Insurance Agent",
            "type":"Services"
        }
    ],
    "sg:phone":"+1 972 436 7154",
    "sg:postcode":"75077",
    "sg:province":"TX",
    "wof:name":"Onboard Marine Insurance Svcs",
    "wof:placetype":"venue"
},
  "geometry": {"coordinates":[-97.02306,33.053669],"type":"Point"}
}