{
  "type": "Feature",
  "properties": {
    "iso:country":"US",
    "sg:address":"5537 W Commerce St",
    "sg:city":"San Antonio",
    "sg:classifiers":[
        {
            "category":"Building & Trades",
            "subcategory":"Construction",
            "type":"Services"
        }
    ],
    "sg:phone":"+1 210 435 3316",
    "sg:postcode":"78237",
    "sg:province":"TX",
    "sg:tags":[
        "steel",
        "erectors"
    ],
    "wof:name":"G & L Welding & Erection Co",
    "wof:placetype":"venue"
},
  "geometry": {"coordinates":[-98.571212,29.432489],"type":"Point"}
}