{
  "type": "Feature",
  "properties": {
    "iso:country":"US",
    "sg:address":"1225 E North St",
    "sg:city":"Kilgore",
    "sg:classifiers":[
        {
            "category":"Building & Trades",
            "subcategory":"Construction",
            "type":"Services"
        }
    ],
    "sg:phone":"+1 903 983 2932",
    "sg:postcode":"75662",
    "sg:province":"TX",
    "sg:tags":[
        "general",
        "contractor"
    ],
    "wof:name":"Hita Corp",
    "wof:placetype":"venue"
},
  "geometry": {"coordinates":[-94.863634,32.382569],"type":"Point"}
}