{
  "type": "Feature",
  "properties": {
    "iso:country":"US",
    "sg:address":"4227 Deborah Kay",
    "sg:city":"Von Ormy",
    "sg:classifiers":[
        {
            "category":"Building & Trades",
            "subcategory":"Equipment Rental",
            "type":"Services"
        },
        {
            "category":"Personal",
            "type":"Services"
        }
    ],
    "sg:phone":"+1 210 624 2299",
    "sg:postcode":"78073",
    "sg:province":"TX",
    "sg:tags":[
        "party",
        "supply"
    ],
    "wof:name":"Apollo Moon Walks",
    "wof:placetype":"venue"
},
  "geometry": {"coordinates":[-98.583997,29.22767],"type":"Point"}
}