{
  "type": "Feature",
  "properties": {
    "iso:country":"US",
    "sg:address":"6460 Hiller St",
    "sg:city":"El Paso",
    "sg:classifiers":[
        {
            "category":"Government",
            "subcategory":"Court House",
            "type":"Public Place"
        }
    ],
    "sg:phone":"+1 915 772 1115",
    "sg:postcode":"79925",
    "sg:province":"TX",
    "sg:tags":[
        "enforcement",
        "support",
        "child"
    ],
    "wof:name":"Child Support Enforcement",
    "wof:placetype":"venue"
},
  "geometry": {"coordinates":[-106.403639,31.793438],"type":"Point"}
}