{
  "type": "Feature",
  "properties": {
    "iso:country":"US",
    "sg:address":"4804 Worth St",
    "sg:city":"Dallas",
    "sg:classifiers":[
        {
            "category":"Social Services",
            "type":"Services"
        }
    ],
    "sg:phone":"+1 214 828 2200",
    "sg:postcode":"75246",
    "sg:province":"TX",
    "sg:tags":[
        "youth",
        "organization",
        "center"
    ],
    "wof:name":"Boys & Girls Club Of Dallas",
    "wof:placetype":"venue"
},
  "geometry": {"coordinates":[-96.767538,32.798492],"type":"Point"}
}