{
  "type": "Feature",
  "properties": {
    "iso:country":"US",
    "sg:address":"29311 Fm 149",
    "sg:city":"Richards",
    "sg:classifiers":[
        {
            "category":"Winery",
            "type":"Food & Drink"
        },
        {
            "category":"Food & Beverages",
            "subcategory":"Liquor & Beverages",
            "type":"Retail Goods"
        },
        {
            "category":"Wholesale",
            "subcategory":"Wine & Distilled Alcoholic Beverages",
            "type":"Manufacturing & Wholesale Goods"
        }
    ],
    "sg:phone":"+1 936 851 2400",
    "sg:postcode":"77873",
    "sg:province":"TX",
    "sg:tags":[
        "broker"
    ],
    "wof:name":"Texas Star Winery",
    "wof:placetype":"venue"
},
  "geometry": {"coordinates":[-95.821862,30.544959],"type":"Point"}
}