{
  "type": "Feature",
  "properties": {
    "iso:country":"US",
    "sg:address":"1800 S Main St",
    "sg:city":"Mcallen",
    "sg:classifiers":[
        {
            "category":"Health Services",
            "subcategory":"Health Practitioner",
            "type":"Services"
        }
    ],
    "sg:phone":"+1 956 631 5196",
    "sg:postcode":"78503",
    "sg:province":"TX",
    "sg:tags":[
        "nurse",
        "registry"
    ],
    "wof:name":"Nursefinders",
    "wof:placetype":"venue"
},
  "geometry": {"coordinates":[-98.237217,26.187989],"type":"Point"}
}