{
  "type": "Feature",
  "properties": {
    "iso:country":"US",
    "sg:address":"2423 Whitewood Dr",
    "sg:city":"Dallas",
    "sg:classifiers":[
        {
            "category":"Shopping",
            "subcategory":"Jewelry",
            "type":"Retail Goods"
        }
    ],
    "sg:phone":"+1 214 330 2601",
    "sg:postcode":"75233",
    "sg:province":"TX",
    "wof:name":"Silver Star Jewelery & Accesso",
    "wof:placetype":"venue"
},
  "geometry": {"coordinates":[-96.8583,32.702771],"type":"Point"}
}