{
  "type": "Feature",
  "properties": {
    "iso:country":"US",
    "sg:address":"12150 Almeda Rd",
    "sg:city":"Houston",
    "sg:classifiers":[
        {
            "category":"Autos & Motor Vehicles",
            "subcategory":"Automobile Sales",
            "type":"Retail Goods"
        }
    ],
    "sg:phone":"+1 713 433 3334",
    "sg:postcode":"77045",
    "sg:province":"TX",
    "sg:tags":[
        "car",
        "dealer"
    ],
    "wof:name":"Allen Motors",
    "wof:placetype":"venue"
},
  "geometry": {"coordinates":[-95.41117199999999,29.634718],"type":"Point"}
}