{
  "type": "Feature",
  "properties": {
    "iso:country":"US",
    "sg:address":"5834 Vickery Blvd",
    "sg:city":"Dallas",
    "sg:classifiers":[
        {
            "category":"Professional",
            "type":"Services"
        }
    ],
    "sg:phone":"+1 214 826 3196",
    "sg:postcode":"75206",
    "sg:province":"TX",
    "wof:name":"Maxrack",
    "wof:placetype":"venue"
},
  "geometry": {"coordinates":[-96.766414,32.822856],"type":"Point"}
}