{
  "type": "Feature",
  "properties": {
    "iso:country":"US",
    "sg:address":"3328 Denton Hwy",
    "sg:city":"Fort Worth",
    "sg:classifiers":[
        {
            "category":"Restaurant",
            "type":"Food & Drink"
        }
    ],
    "sg:phone":"+1 682 647 0767",
    "sg:postcode":"76117",
    "sg:province":"TX",
    "wof:name":"Subway Sandwiches & Salads",
    "wof:placetype":"venue"
},
  "geometry": {"coordinates":[-97.264461,32.810745],"type":"Point"}
}