{
  "type": "Feature",
  "properties": {
    "iso:country":"US",
    "sg:address":"15307 Falcon Ridge Dr",
    "sg:city":"Humble",
    "sg:classifiers":[
        {
            "category":"Communications",
            "subcategory":"Radio Station",
            "type":"Services"
        }
    ],
    "sg:phone":"+1 281 441 3665",
    "sg:postcode":"77396",
    "sg:province":"TX",
    "sg:tags":[
        "broadcast"
    ],
    "wof:name":"Martin Broadcasting Inc",
    "wof:placetype":"venue"
},
  "geometry": {"coordinates":[-95.26718700000001,29.943452],"type":"Point"}
}