{
  "type": "Feature",
  "properties": {
    "iso:country":"US",
    "sg:address":"5221 Park Village Dr",
    "sg:city":"Houston",
    "sg:classifiers":[
        {
            "category":"Organizations",
            "subcategory":"Religious Organization",
            "type":"Services"
        }
    ],
    "sg:phone":"+1 713 733 1076",
    "sg:postcode":"77048",
    "sg:province":"TX",
    "wof:name":"Park Village Baptist Church",
    "wof:placetype":"venue"
},
  "geometry": {"coordinates":[-95.34323000000001,29.629159],"type":"Point"}
}