{
  "type": "Feature",
  "properties": {
    "iso:country":"US",
    "sg:address":"8603 Westheimer Rd",
    "sg:city":"Houston",
    "sg:classifiers":[
        {
            "category":"Home & Garden",
            "subcategory":"Garden Supply",
            "type":"Retail Goods"
        }
    ],
    "sg:phone":"+1 713 782 7757",
    "sg:postcode":"77063",
    "sg:province":"TX",
    "sg:tags":[
        "center"
    ],
    "sg:website":"www.brookwoodcommunity.org",
    "wof:name":"Brookwood Community",
    "wof:placetype":"venue"
},
  "geometry": {"coordinates":[-95.518317,29.737285],"type":"Point"}
}