{
  "type": "Feature",
  "properties": {
    "iso:country":"US",
    "sg:address":"700 W State Ave",
    "sg:city":"Pharr",
    "sg:classifiers":[
        {
            "category":"Food & Beverages",
            "subcategory":"Supermarket",
            "type":"Retail Goods"
        },
        {
            "category":"Food & Beverages",
            "subcategory":"Groceries & Convenience Stores",
            "type":"Retail Goods"
        }
    ],
    "sg:phone":"+1 956 787 3596",
    "sg:postcode":"78577",
    "sg:province":"TX",
    "sg:tags":[
        "super"
    ],
    "wof:name":"Cantu's Supermarket",
    "wof:placetype":"venue"
},
  "geometry": {"coordinates":[-98.19171900000001,26.197029],"type":"Point"}
}