{
  "type": "Feature",
  "properties": {
    "iso:country":"US",
    "sg:address":"420 Main St",
    "sg:city":"Brownwood",
    "sg:classifiers":[
        {
            "category":"Restaurant",
            "type":"Food & Drink"
        }
    ],
    "sg:phone":"+1 325 643 5953",
    "sg:postcode":"76801",
    "sg:province":"TX",
    "wof:name":"Peking Chinese Restaurant",
    "wof:placetype":"venue"
},
  "geometry": {"coordinates":[-98.983819,31.721102],"type":"Point"}
}