{
  "type": "Feature",
  "properties": {
    "iso:country":"US",
    "sg:address":"7404 Marsland Ln",
    "sg:city":"Arlington",
    "sg:classifiers":[
        {
            "category":"Home & Garden",
            "subcategory":"Garden Supply",
            "type":"Retail Goods"
        }
    ],
    "sg:phone":"+1 817 938 7315",
    "sg:postcode":"76001",
    "sg:province":"TX",
    "sg:tags":[
        "lawn",
        "mower"
    ],
    "wof:name":"Quick Mower Tunes",
    "wof:placetype":"venue"
},
  "geometry": {"coordinates":[-97.12023499999999,32.624826],"type":"Point"}
}