{
  "type": "Feature",
  "properties": {
    "iso:country":"US",
    "sg:address":"951 S Lillian",
    "sg:city":"Stephenville",
    "sg:classifiers":[
        {
            "category":"Personal",
            "subcategory":"Beauty Salon",
            "type":"Services"
        }
    ],
    "sg:phone":"+1 254 968 2111",
    "sg:postcode":"76401",
    "sg:province":"TX",
    "sg:tags":[
        "shop"
    ],
    "wof:name":"Stephenville Beauty College",
    "wof:placetype":"venue"
},
  "geometry": {"coordinates":[-98.210775,32.20527],"type":"Point"}
}