{
  "type": "Feature",
  "properties": {
    "iso:country":"US",
    "sg:address":"46 Allen Dr",
    "sg:city":"Huntsville",
    "sg:classifiers":[
        {
            "category":"Real Estate",
            "subcategory":"Real Estate Services",
            "type":"Services"
        },
        {
            "category":"Real Estate",
            "subcategory":"Real Estate Agent",
            "type":"Services"
        }
    ],
    "sg:phone":"+1 936 291 2796",
    "sg:postcode":"77320",
    "sg:province":"TX",
    "sg:tags":[
        "buyer",
        "broker"
    ],
    "wof:name":"Keys Real Estate",
    "wof:placetype":"venue"
},
  "geometry": {"coordinates":[-95.58255200000001,30.809643],"type":"Point"}
}