{
  "type": "Feature",
  "properties": {
    "iso:country":"US",
    "sg:address":"3118 San Jacinto St",
    "sg:city":"Houston",
    "sg:classifiers":[
        {
            "category":"Social Services",
            "type":"Services"
        }
    ],
    "sg:phone":"+1 713 524 1992",
    "sg:postcode":"77004",
    "sg:province":"TX",
    "wof:name":"3118 San Jacinto Houston S R O",
    "wof:placetype":"venue"
},
  "geometry": {"coordinates":[-95.37530700000001,29.740746],"type":"Point"}
}