{
  "type": "Feature",
  "properties": {
    "iso:country":"US",
    "sg:address":"220 W Morris St",
    "sg:city":"Yoakum",
    "sg:classifiers":[
        {
            "category":"Personal",
            "subcategory":"Beauty Salon",
            "type":"Services"
        }
    ],
    "sg:phone":"+1 361 293 7900",
    "sg:postcode":"77995",
    "sg:province":"TX",
    "wof:name":"Super Cut N Style",
    "wof:placetype":"venue"
},
  "geometry": {"coordinates":[-97.15228399999999,29.287764],"type":"Point"}
}