{
  "type": "Feature",
  "properties": {
    "iso:country":"US",
    "sg:address":"1213 Preston St",
    "sg:city":"Waco",
    "sg:classifiers":[
        {
            "category":"Farming",
            "subcategory":"Livestock Farm",
            "type":"Manufacturing & Wholesale Goods"
        }
    ],
    "sg:phone":"+1 254 235 1415",
    "sg:postcode":"76704",
    "sg:province":"TX",
    "sg:tags":[
        "breeder",
        "pit",
        "dog",
        "bull"
    ],
    "wof:name":"Golden Kings Kennel",
    "wof:placetype":"venue"
},
  "geometry": {"coordinates":[-97.133055,31.575092],"type":"Point"}
}