{
  "type": "Feature",
  "properties": {
    "iso:country":"US",
    "sg:address":"9320 FM 1472",
    "sg:city":"Laredo",
    "sg:classifiers":[
        {
            "category":"Professional",
            "subcategory":"Advertising",
            "type":"Services"
        }
    ],
    "sg:phone":"+1 956 753 5288",
    "sg:postcode":"78045",
    "sg:province":"TX",
    "sg:tags":[
        "mail",
        "direct"
    ],
    "wof:name":"Amistad Services LLC",
    "wof:placetype":"venue"
},
  "geometry": {"coordinates":[-99.51050600000001,27.586931],"type":"Point"}
}