{
  "type": "Feature",
  "properties": {
    "iso:country":"US",
    "sg:address":"11045 Indian Hill Rd",
    "sg:city":"Amarillo",
    "sg:classifiers":[
        {
            "category":"Professional",
            "type":"Services"
        }
    ],
    "sg:phone":"+1 806 359 1288",
    "sg:postcode":"79124",
    "sg:province":"TX",
    "wof:name":"Campbell Borger LP",
    "wof:placetype":"venue"
},
  "geometry": {"coordinates":[-101.971405,35.191417],"type":"Point"}
}