{
  "type": "Feature",
  "properties": {
    "iso:country":"US",
    "sg:address":"2365 Rice Blvd",
    "sg:city":"Houston",
    "sg:classifiers":[
        {
            "category":"Real Estate",
            "subcategory":"Real Estate Agent",
            "type":"Services"
        }
    ],
    "sg:phone":"+1 713 521 7699",
    "sg:postcode":"77005",
    "sg:province":"TX",
    "wof:name":"Rust Realty",
    "wof:placetype":"venue"
},
  "geometry": {"coordinates":[-95.414846,29.717399],"type":"Point"}
}