{
  "type": "Feature",
  "properties": {
    "iso:country":"US",
    "sg:address":"201 E Belknap St",
    "sg:city":"Fort Worth",
    "sg:classifiers":[
        {
            "category":"Professional",
            "subcategory":"Lawyer & Legal Services",
            "type":"Services"
        }
    ],
    "sg:phone":"+1 817 885 8687",
    "sg:postcode":"76102",
    "sg:province":"TX",
    "sg:tags":[
        "attorney"
    ],
    "wof:name":"Brenda Rotramble",
    "wof:placetype":"venue"
},
  "geometry": {"coordinates":[-97.33178100000001,32.758576],"type":"Point"}
}