{
  "type": "Feature",
  "properties": {
    "iso:country":"US",
    "sg:address":"927 E Main St",
    "sg:city":"Fairfield",
    "sg:classifiers":[
        {
            "category":"Shopping",
            "subcategory":"Gifts & Souvenirs",
            "type":"Retail Goods"
        }
    ],
    "sg:phone":"+1 903 389 7629",
    "sg:postcode":"75840",
    "sg:province":"TX",
    "sg:tags":[
        "shop"
    ],
    "wof:name":"Country Charm",
    "wof:placetype":"venue"
},
  "geometry": {"coordinates":[-96.14125199999999,31.730714],"type":"Point"}
}