{
  "type": "Feature",
  "properties": {
    "iso:country":"US",
    "sg:address":"9000 Cullen Blvd",
    "sg:city":"Houston",
    "sg:classifiers":[
        {
            "category":"Retail",
            "subcategory":"Auto Repair",
            "type":"Services"
        }
    ],
    "sg:phone":"+1 713 734 4766",
    "sg:postcode":"77051",
    "sg:province":"TX",
    "sg:tags":[
        "repairing",
        "automobile",
        "general"
    ],
    "wof:name":"Iron Mans Auto Repair Company",
    "wof:placetype":"venue"
},
  "geometry": {"coordinates":[-95.355527,29.659853],"type":"Point"}
}