{
  "type": "Feature",
  "properties": {
    "iso:country":"US",
    "sg:address":"1900 Preston Rd Ste 150",
    "sg:city":"Plano",
    "sg:classifiers":[
        {
            "category":"Shopping",
            "subcategory":"Clothing, Apparel, & Fashions",
            "type":"Retail Goods"
        }
    ],
    "sg:phone":"+1 972 867 5440",
    "sg:postcode":"75093",
    "sg:province":"TX",
    "sg:tags":[
        "accessory",
        "apparel",
        "handbag",
        "women's",
        "clothing",
        "sportswear"
    ],
    "sg:website":"www.talbots.com",
    "wof:name":"Talbots",
    "wof:placetype":"venue"
},
  "geometry": {"coordinates":[-96.794899,33.025799],"type":"Point"}
}