{
  "type": "Feature",
  "properties": {
    "iso:country":"US",
    "sg:address":"315 E Oak St",
    "sg:city":"Uvalde",
    "sg:classifiers":[
        {
            "category":"Freight",
            "type":"Transportation"
        }
    ],
    "sg:phone":"+1 830 278 6281",
    "sg:postcode":"78801",
    "sg:province":"TX",
    "sg:tags":[
        "trucking"
    ],
    "wof:name":"Southwestern Motor Transport",
    "wof:placetype":"venue"
},
  "geometry": {"coordinates":[-99.781954,29.214113],"type":"Point"}
}