{
  "type": "Feature",
  "properties": {
    "iso:country":"US",
    "sg:address":"1223 Darbytown Rd",
    "sg:city":"Grand Prairie",
    "sg:classifiers":[
        {
            "category":"Professional",
            "subcategory":"Business Services",
            "type":"Services"
        }
    ],
    "sg:phone":"+1 972 206 7722",
    "sg:postcode":"75052",
    "sg:province":"TX",
    "wof:name":"T Four Sales",
    "wof:placetype":"venue"
},
  "geometry": {"coordinates":[-97.022203,32.661081],"type":"Point"}
}