{
  "type": "Feature",
  "properties": {
    "iso:country":"US",
    "sg:address":"7430 Whitehall St",
    "sg:city":"Richland Hills",
    "sg:classifiers":[
        {
            "category":"Professional",
            "subcategory":"Computer Services",
            "type":"Services"
        }
    ],
    "sg:phone":"+1 817 595 9549",
    "sg:postcode":"76118",
    "sg:province":"TX",
    "sg:tags":[
        "planning",
        "disaster"
    ],
    "wof:name":"Arcus Data Security",
    "wof:placetype":"venue"
},
  "geometry": {"coordinates":[-97.219521,32.806599],"type":"Point"}
}