{
  "type": "Feature",
  "properties": {
    "iso:country":"US",
    "sg:address":"507 Towne Pl",
    "sg:city":"Duncanville",
    "sg:classifiers":[
        {
            "category":"Restaurant",
            "type":"Food & Drink"
        }
    ],
    "sg:phone":"+1 972 780 0765",
    "sg:postcode":"75116",
    "sg:province":"TX",
    "sg:tags":[
        "eating"
    ],
    "wof:name":"Brad & Ki Catering Srv",
    "wof:placetype":"venue"
},
  "geometry": {"coordinates":[-96.898045,32.647513],"type":"Point"}
}