{
  "type": "Feature",
  "properties": {
    "iso:country":"US",
    "sg:address":"3186 Merriman St",
    "sg:city":"Port Neches",
    "sg:classifiers":[
        {
            "category":"Health Services",
            "subcategory":"Doctor",
            "type":"Services"
        }
    ],
    "sg:phone":"+1 409 721 5361",
    "sg:postcode":"77651",
    "sg:province":"TX",
    "sg:tags":[
        "medical"
    ],
    "wof:name":"J J Shook",
    "wof:placetype":"venue"
},
  "geometry": {"coordinates":[-93.96870699999999,29.96234],"type":"Point"}
}