{
  "type": "Feature",
  "properties": {
    "iso:country":"US",
    "sg:address":"1613 M Pl",
    "sg:city":"Plano",
    "sg:classifiers":[
        {
            "category":"Home & Garden",
            "subcategory":"Garden Supply",
            "type":"Retail Goods"
        }
    ],
    "sg:phone":"+1 972 424 2020",
    "sg:postcode":"75074",
    "sg:province":"TX",
    "sg:tags":[
        "sprinkler"
    ],
    "wof:name":"Waterboy Sprinkler Co",
    "wof:placetype":"venue"
},
  "geometry": {"coordinates":[-96.69553399999999,33.023652],"type":"Point"}
}