{
  "type": "Feature",
  "properties": {
    "iso:country":"US",
    "sg:address":"908 E Live Oak St",
    "sg:city":"Lockhart",
    "sg:classifiers":[
        {
            "category":"Social Services",
            "subcategory":"Child Care",
            "type":"Services"
        }
    ],
    "sg:phone":"+1 512 398 2001",
    "sg:postcode":"78644",
    "sg:province":"TX",
    "wof:name":"God's Little Miracles",
    "wof:placetype":"venue"
},
  "geometry": {"coordinates":[-97.664098,29.88315],"type":"Point"}
}