{
  "type": "Feature",
  "properties": {
    "iso:country":"US",
    "sg:address":"1510 N Hampton Rd",
    "sg:city":"Dallas",
    "sg:classifiers":[
        {
            "category":"Health Services",
            "subcategory":"Health Practitioner",
            "type":"Services"
        }
    ],
    "sg:phone":"+1 972 228 9602",
    "sg:postcode":"75208",
    "sg:province":"TX",
    "sg:tags":[
        "psychotherapist"
    ],
    "wof:name":"Jennifer Bosma",
    "wof:placetype":"venue"
},
  "geometry": {"coordinates":[-96.856433,32.765694],"type":"Point"}
}