{
  "type": "Feature",
  "properties": {
    "iso:country":"US",
    "sg:address":"2901 Buffalo Gap Rd",
    "sg:city":"Abilene",
    "sg:classifiers":[
        {
            "category":"Building & Trades",
            "subcategory":"Electrical",
            "type":"Services"
        }
    ],
    "sg:phone":"+1 325 695 0061",
    "sg:postcode":"79605",
    "sg:province":"TX",
    "sg:tags":[
        "contractor"
    ],
    "wof:name":"Giddings Electric",
    "wof:placetype":"venue"
},
  "geometry": {"coordinates":[-99.752062,32.414043],"type":"Point"}
}