{
  "type": "Feature",
  "properties": {
    "iso:country":"US",
    "sg:address":"5104 Harrisburg Blvd",
    "sg:city":"Houston",
    "sg:classifiers":[
        {
            "category":"Professional",
            "subcategory":"Employment Agencies",
            "type":"Services"
        }
    ],
    "sg:phone":"+1 713 228 8848",
    "sg:postcode":"77011",
    "sg:province":"TX",
    "sg:website":"www.state.tx.us",
    "wof:name":"State of Texas",
    "wof:placetype":"venue"
},
  "geometry": {"coordinates":[-95.32449800000001,29.742367],"type":"Point"}
}