{
  "type": "Feature",
  "properties": {
    "iso:country":"US",
    "sg:address":"1204 11th St N",
    "sg:city":"Texas City",
    "sg:classifiers":[
        {
            "category":"Retail",
            "subcategory":"Auto Repair",
            "type":"Services"
        }
    ],
    "sg:phone":"+1 409 945 2650",
    "sg:postcode":"77590",
    "sg:province":"TX",
    "sg:tags":[
        "automotive"
    ],
    "wof:name":"Bobs Automotive AC Repr",
    "wof:placetype":"venue"
},
  "geometry": {"coordinates":[-94.909819,29.39476],"type":"Point"}
}