{
  "type": "Feature",
  "properties": {
    "iso:country":"US",
    "sg:address":"1902 Scarlett Ct",
    "sg:city":"Arlington",
    "sg:classifiers":[
        {
            "category":"Wholesale",
            "subcategory":"Toys & Hobbies",
            "type":"Manufacturing & Wholesale Goods"
        }
    ],
    "sg:phone":"+1 817 860 5008",
    "sg:postcode":"76012",
    "sg:province":"TX",
    "wof:name":"Miss Bettys Dolls",
    "wof:placetype":"venue"
},
  "geometry": {"coordinates":[-97.117384,32.766101],"type":"Point"}
}