{
  "type": "Feature",
  "properties": {
    "iso:country":"US",
    "sg:address":"4303 Everest Ln",
    "sg:city":"Austin",
    "sg:classifiers":[
        {
            "category":"Shopping",
            "subcategory":"Books",
            "type":"Retail Goods"
        }
    ],
    "sg:phone":"+1 512 926 1454",
    "sg:postcode":"78727",
    "sg:province":"TX",
    "sg:tags":[
        "dealers-used",
        "rare",
        "store"
    ],
    "wof:name":"Crazy Horse Books",
    "wof:placetype":"venue"
},
  "geometry": {"coordinates":[-97.72490500000001,30.419006],"type":"Point"}
}