{
  "type": "Feature",
  "properties": {
    "iso:country":"US",
    "sg:address":"4200 Research Forest Dr",
    "sg:city":"Spring",
    "sg:classifiers":[
        {
            "category":"Building & Trades",
            "subcategory":"Equipment Rental",
            "type":"Services"
        }
    ],
    "sg:phone":"+1 281 419 7851",
    "sg:postcode":"77381",
    "sg:province":"TX",
    "sg:tags":[
        "leasing"
    ],
    "wof:name":"Universal Leasing USA",
    "wof:placetype":"venue"
},
  "geometry": {"coordinates":[-95.49366000000001,30.194576],"type":"Point"}
}