{
  "type": "Feature",
  "properties": {
    "iso:country":"US",
    "sg:address":"112 Lazy Ln",
    "sg:city":"Lake Jackson",
    "sg:classifiers":[
        {
            "category":"Building & Trades",
            "subcategory":"Construction",
            "type":"Services"
        }
    ],
    "sg:phone":"+1 979 265 1443",
    "sg:postcode":"77566",
    "sg:province":"TX",
    "sg:tags":[
        "hanging",
        "contractor"
    ],
    "wof:name":"Blanchard Painting John C",
    "wof:placetype":"venue"
},
  "geometry": {"coordinates":[-95.42137200000001,29.050232],"type":"Point"}
}