{
  "type": "Feature",
  "properties": {
    "iso:country":"US",
    "sg:address":"1111 Hawkins Blvd",
    "sg:city":"El Paso",
    "sg:classifiers":[
        {
            "category":"Food & Beverages",
            "subcategory":"Specialty",
            "type":"Retail Goods"
        }
    ],
    "sg:phone":"+1 915 778 0001",
    "sg:postcode":"79925",
    "sg:province":"TX",
    "sg:tags":[
        "health",
        "diet"
    ],
    "wof:name":"Rainbow Natural Health Foods",
    "wof:placetype":"venue"
},
  "geometry": {"coordinates":[-106.377145,31.771776],"type":"Point"}
}