{
  "type": "Feature",
  "properties": {
    "iso:country":"US",
    "sg:address":"709 Bessemer Ave",
    "sg:city":"Llano",
    "sg:classifiers":[
        {
            "category":"Restaurant",
            "type":"Food & Drink"
        }
    ],
    "sg:phone":"+1 325 247 3955",
    "sg:postcode":"78643",
    "sg:province":"TX",
    "sg:tags":[
        "eating"
    ],
    "wof:name":"Nanny & Papas Tejas Taco",
    "wof:placetype":"venue"
},
  "geometry": {"coordinates":[-98.67528799999999,30.758396],"type":"Point"}
}