{
  "type": "Feature",
  "properties": {
    "iso:country":"US",
    "sg:address":"15125 Honeycomb Hollow",
    "sg:city":"Leander",
    "sg:classifiers":[
        {
            "category":"Organizations",
            "subcategory":"Religious Organization",
            "type":"Services"
        }
    ],
    "sg:phone":"+1 512 259 2767",
    "sg:postcode":"78641",
    "sg:province":"TX",
    "wof:name":"Honeycomb Hills Baptist Church",
    "wof:placetype":"venue"
},
  "geometry": {"coordinates":[-97.931461,30.575809],"type":"Point"}
}