{
  "type": "Feature",
  "properties": {
    "iso:country":"US",
    "sg:address":"1500 W 38th Street Suite 51",
    "sg:city":"Austin",
    "sg:classifiers":[
        {
            "category":"Health Services",
            "subcategory":"Dentist",
            "type":"Services"
        }
    ],
    "sg:phone":"+1 512 452 3223",
    "sg:postcode":"78731",
    "sg:province":"TX",
    "wof:name":"Widner J Steven DDS PA",
    "wof:placetype":"venue"
},
  "geometry": {"coordinates":[-97.748987,30.307947],"type":"Point"}
}