{
  "type": "Feature",
  "properties": {
    "iso:country":"US",
    "sg:address":"524 E 40th St",
    "sg:city":"Lubbock",
    "sg:classifiers":[
        {
            "category":"Health Services",
            "subcategory":"Nursing And Care Facility",
            "type":"Services"
        },
        {
            "category":"Social Services",
            "subcategory":"Adult Care",
            "type":"Services"
        }
    ],
    "sg:phone":"+1 806 747 5714",
    "sg:postcode":"79404",
    "sg:province":"TX",
    "sg:tags":[
        "personal",
        "living",
        "assisted",
        "home",
        "elder"
    ],
    "sg:website":"http://www.southernhomecareservices.com",
    "wof:name":"Alternative Business Services",
    "wof:placetype":"venue"
},
  "geometry": {"coordinates":[-101.831185,33.557883],"type":"Point"}
}