{
  "type": "Feature",
  "properties": {
    "iso:country":"US",
    "sg:address":"5315 Timber Creek Place Dr",
    "sg:city":"Houston",
    "sg:classifiers":[
        {
            "category":"Building & Trades",
            "subcategory":"Construction",
            "type":"Services"
        }
    ],
    "sg:phone":"+1 281 550 6140",
    "sg:postcode":"77084",
    "sg:province":"TX",
    "sg:tags":[
        "contractor"
    ],
    "wof:name":"Systematic Roofing",
    "wof:placetype":"venue"
},
  "geometry": {"coordinates":[-95.641295,29.852553],"type":"Point"}
}