{
  "type": "Feature",
  "properties": {
    "iso:country":"US",
    "sg:address":"136 NE Loop 564",
    "sg:city":"Mineola",
    "sg:classifiers":[
        {
            "category":"Shopping",
            "subcategory":"Department Store",
            "type":"Retail Goods"
        }
    ],
    "sg:phone":"+1 903 569 0670",
    "sg:postcode":"75773",
    "sg:province":"TX",
    "wof:name":"Wal-Mart Supercenter",
    "wof:placetype":"venue"
},
  "geometry": {"coordinates":[-95.48220499999999,32.687962],"type":"Point"}
}