{
  "type": "Feature",
  "properties": {
    "iso:country":"US",
    "sg:address":"6400 Midway Rd",
    "sg:city":"Fort Worth",
    "sg:classifiers":[
        {
            "category":"Wholesale",
            "subcategory":"Hardware",
            "type":"Manufacturing & Wholesale Goods"
        }
    ],
    "sg:phone":"+1 817 834 5337",
    "sg:postcode":"76117",
    "sg:province":"TX",
    "sg:tags":[
        "c"
    ],
    "wof:name":"Watsco Inc",
    "wof:placetype":"venue"
},
  "geometry": {"coordinates":[-97.24879799999999,32.794745],"type":"Point"}
}