{
  "type": "Feature",
  "properties": {
    "iso:country":"US",
    "sg:address":"4419 W Thunderwood Cir",
    "sg:city":"Fresno",
    "sg:classifiers":[
        {
            "category":"Personal",
            "subcategory":"Beauty Salon",
            "type":"Services"
        }
    ],
    "sg:phone":"+1 281 431 8846",
    "sg:postcode":"77545",
    "sg:province":"TX",
    "sg:tags":[
        "shop"
    ],
    "wof:name":"Mary Anns Boutique",
    "wof:placetype":"venue"
},
  "geometry": {"coordinates":[-95.482664,29.522999],"type":"Point"}
}