{
  "type": "Feature",
  "properties": {
    "iso:country":"US",
    "sg:address":"512 State Hwy 100",
    "sg:city":"Port Isabel",
    "sg:classifiers":[
        {
            "category":"Personal",
            "subcategory":"Beauty Salon",
            "type":"Services"
        }
    ],
    "sg:phone":"+1 956 943 5608",
    "sg:postcode":"78578",
    "sg:province":"TX",
    "wof:name":"Salon Espelos",
    "wof:placetype":"venue"
},
  "geometry": {"coordinates":[-97.20596500000001,26.078096],"type":"Point"}
}