{
  "type": "Feature",
  "properties": {
    "iso:country":"US",
    "sg:address":"510 Hopper Dr",
    "sg:city":"Corpus Christi",
    "sg:classifiers":[
        {
            "category":"Farming",
            "subcategory":"Fish & Marine Products",
            "type":"Manufacturing & Wholesale Goods"
        }
    ],
    "sg:phone":"+1 361 851 1962",
    "sg:postcode":"78411",
    "sg:province":"TX",
    "sg:tags":[
        "management"
    ],
    "wof:name":"Jim Atkins Outdoors",
    "wof:placetype":"venue"
},
  "geometry": {"coordinates":[-97.38373900000001,27.744602],"type":"Point"}
}