{
  "type": "Feature",
  "properties": {
    "iso:country":"US",
    "sg:address":"1901 John McCain Rd",
    "sg:city":"Colleyville",
    "sg:classifiers":[
        {
            "category":"Building & Trades",
            "subcategory":"Construction",
            "type":"Services"
        }
    ],
    "sg:phone":"+1 817 481 7164",
    "sg:postcode":"76034",
    "sg:province":"TX",
    "sg:tags":[
        "insulation",
        "heat",
        "contractor"
    ],
    "wof:name":"Maverick Drywall & Insulation",
    "wof:placetype":"venue"
},
  "geometry": {"coordinates":[-97.138884,32.911657],"type":"Point"}
}