{
  "type": "Feature",
  "properties": {
    "iso:country":"US",
    "sg:address":"535 Crosstimbers St",
    "sg:city":"Houston",
    "sg:classifiers":[
        {
            "category":"Personal",
            "subcategory":"Barber",
            "type":"Services"
        }
    ],
    "sg:phone":"+1 713 742 8689",
    "sg:postcode":"77022",
    "sg:province":"TX",
    "wof:name":"Distinguished Barber Shop",
    "wof:placetype":"venue"
},
  "geometry": {"coordinates":[-95.392259,29.828619],"type":"Point"}
}