{
  "type": "Feature",
  "properties": {
    "iso:country":"US",
    "sg:address":"3731 Cavalier Dr",
    "sg:city":"Garland",
    "sg:classifiers":[
        {
            "category":"Professional",
            "type":"Services"
        }
    ],
    "sg:phone":"+1 972 494 4770",
    "sg:postcode":"75042",
    "sg:province":"TX",
    "sg:tags":[
        "establishment"
    ],
    "wof:name":"Mac Source",
    "wof:placetype":"venue"
},
  "geometry": {"coordinates":[-96.68822,32.900393],"type":"Point"}
}