{
  "type": "Feature",
  "properties": {
    "iso:country":"US",
    "sg:address":"2925 Lyndon B Johnson Fwy",
    "sg:city":"Farmers Branch",
    "sg:classifiers":[
        {
            "category":"Shopping",
            "subcategory":"Computers & Home Electronics",
            "type":"Retail Goods"
        }
    ],
    "sg:phone":"+1 972 247 4889",
    "sg:postcode":"75234",
    "sg:province":"TX",
    "sg:tags":[
        "software"
    ],
    "wof:name":"Sevis Systems",
    "wof:placetype":"venue"
},
  "geometry": {"coordinates":[-96.878604,32.911956],"type":"Point"}
}