{
  "type": "Feature",
  "properties": {
    "iso:country":"US",
    "sg:address":"2875 Vinson Rd",
    "sg:city":"Wylie",
    "sg:classifiers":[
        {
            "category":"Building & Trades",
            "subcategory":"Construction",
            "type":"Services"
        }
    ],
    "sg:phone":"+1 972 475 1573",
    "sg:postcode":"75098",
    "sg:province":"TX",
    "sg:tags":[
        "concrete",
        "contractor"
    ],
    "wof:name":"Owen B Olson",
    "wof:placetype":"venue"
},
  "geometry": {"coordinates":[-96.523847,32.970547],"type":"Point"}
}