{
  "type": "Feature",
  "properties": {
    "iso:country":"US",
    "sg:address":"503 N Hampton Rd",
    "sg:city":"De Soto",
    "sg:classifiers":[
        {
            "category":"Social Services",
            "subcategory":"Child Care",
            "type":"Services"
        }
    ],
    "sg:phone":"+1 972 223 4400",
    "sg:postcode":"75115",
    "sg:province":"TX",
    "sg:tags":[
        "day"
    ],
    "wof:name":"Cabbage Patch Day Care",
    "wof:placetype":"venue"
},
  "geometry": {"coordinates":[-96.857106,32.596641],"type":"Point"}
}