{
  "type": "Feature",
  "properties": {
    "iso:country":"US",
    "sg:address":"7716 Glenview Dr",
    "sg:city":"Fort Worth",
    "sg:classifiers":[
        {
            "category":"Insurance",
            "subcategory":"Insurance Agent",
            "type":"Services"
        }
    ],
    "sg:phone":"+1 817 589 0006",
    "sg:postcode":"76180",
    "sg:province":"TX",
    "sg:tags":[
        "broker"
    ],
    "wof:name":"L Van Jones",
    "wof:placetype":"venue"
},
  "geometry": {"coordinates":[-97.214569,32.82378],"type":"Point"}
}