{
  "type": "Feature",
  "properties": {
    "iso:country":"US",
    "sg:address":"700 Main St",
    "sg:city":"Bedias",
    "sg:classifiers":[
        {
            "category":"Fast Food",
            "type":"Food & Drink"
        }
    ],
    "sg:phone":"+1 936 395 2537",
    "sg:postcode":"77831",
    "sg:province":"TX",
    "sg:tags":[
        "restaurant"
    ],
    "wof:name":"Cattlemans Express",
    "wof:placetype":"venue"
},
  "geometry": {"coordinates":[-95.958996,30.65207],"type":"Point"}
}