{
  "type": "Feature",
  "properties": {
    "iso:country":"US",
    "sg:address":"11520 N Central Expy",
    "sg:city":"Dallas",
    "sg:classifiers":[
        {
            "category":"Professional",
            "subcategory":"Engineering",
            "type":"Services"
        }
    ],
    "sg:phone":"+1 214 503 0030",
    "sg:postcode":"75243",
    "sg:province":"TX",
    "wof:name":"Rosenlund & Company Inc",
    "wof:placetype":"venue"
},
  "geometry": {"coordinates":[-96.768469,32.906543],"type":"Point"}
}