{
  "type": "Feature",
  "properties": {
    "iso:country":"US",
    "sg:address":"1101 Southmore Ave",
    "sg:city":"Pasadena",
    "sg:classifiers":[
        {
            "category":"Personal",
            "subcategory":"Beauty Salon",
            "type":"Services"
        }
    ],
    "sg:phone":"+1 713 472 4224",
    "sg:postcode":"77502",
    "sg:province":"TX",
    "sg:tags":[
        "shop"
    ],
    "wof:name":"Fashion Nails",
    "wof:placetype":"venue"
},
  "geometry": {"coordinates":[-95.20039800000001,29.690859],"type":"Point"}
}