{
  "type": "Feature",
  "properties": {
    "iso:country":"US",
    "sg:address":"600 Roosevelt Dr",
    "sg:city":"Seguin",
    "sg:classifiers":[
        {
            "category":"Restaurant",
            "type":"Food & Drink"
        }
    ],
    "sg:phone":"+1 830 379 1962",
    "sg:postcode":"78155",
    "sg:province":"TX",
    "wof:name":"Los Sombreros Mex Mex Restaurant",
    "wof:placetype":"venue"
},
  "geometry": {"coordinates":[-97.958038,29.590321],"type":"Point"}
}