{
  "type": "Feature",
  "properties": {
    "iso:country":"US",
    "sg:address":"1670 E Broad St",
    "sg:city":"Mansfield",
    "sg:classifiers":[
        {
            "category":"Health Services",
            "subcategory":"Doctor",
            "type":"Services"
        }
    ],
    "sg:phone":"+1 817 473 2228",
    "sg:postcode":"76063",
    "sg:province":"TX",
    "sg:tags":[
        "physician",
        "surgeon"
    ],
    "wof:name":"Podgurecki David",
    "wof:placetype":"venue"
},
  "geometry": {"coordinates":[-97.11434199999999,32.56916],"type":"Point"}
}