{
  "type": "Feature",
  "properties": {
    "iso:country":"US",
    "sg:address":"14237 N 3rd St",
    "sg:city":"Scurry",
    "sg:classifiers":[
        {
            "category":"Freight",
            "type":"Transportation"
        },
        {
            "category":"Building & Trades",
            "subcategory":"Construction",
            "type":"Services"
        }
    ],
    "sg:phone":"+1 903 498 3531",
    "sg:postcode":"75158",
    "sg:province":"TX",
    "sg:tags":[
        "mobile",
        "home",
        "contractor"
    ],
    "wof:name":"B-Line Mobile Home Movers",
    "wof:placetype":"venue"
},
  "geometry": {"coordinates":[-96.34236199999999,32.437977],"type":"Point"}
}