{
  "type": "Feature",
  "properties": {
    "iso:country":"US",
    "sg:address":"11100 Watt Cir",
    "sg:city":"San Antonio",
    "sg:classifiers":[
        {
            "category":"Manufacturing",
            "subcategory":"Food",
            "type":"Manufacturing & Wholesale Goods"
        }
    ],
    "sg:phone":"+1 210 655 2525",
    "sg:postcode":"78233",
    "sg:province":"TX",
    "sg:tags":[
        "flavor",
        "mfg"
    ],
    "wof:name":"ICEE Company",
    "wof:placetype":"venue"
},
  "geometry": {"coordinates":[-98.382007,29.5408],"type":"Point"}
}