{
  "type": "Feature",
  "properties": {
    "iso:country":"US",
    "sg:address":"118 Benchmark St",
    "sg:city":"Georgetown",
    "sg:classifiers":[
        {
            "category":"Building & Trades",
            "subcategory":"Electrical",
            "type":"Services"
        }
    ],
    "sg:phone":"+1 512 819 0413",
    "sg:postcode":"78626",
    "sg:province":"TX",
    "sg:tags":[
        "electrician"
    ],
    "wof:name":"Richards Electrical",
    "wof:placetype":"venue"
},
  "geometry": {"coordinates":[-97.666057,30.657661],"type":"Point"}
}