{
  "type": "Feature",
  "properties": {
    "iso:country":"US",
    "sg:address":"4139 Gardendale",
    "sg:city":"San Antonio",
    "sg:classifiers":[
        {
            "category":"Professional",
            "subcategory":"Computer Services",
            "type":"Services"
        }
    ],
    "sg:phone":"+1 210 341 2680",
    "sg:postcode":"78229",
    "sg:province":"TX",
    "sg:tags":[
        "datum",
        "storage",
        "verification"
    ],
    "wof:name":"Atc Erpean Registration Centre",
    "wof:placetype":"venue"
},
  "geometry": {"coordinates":[-98.568152,29.524112],"type":"Point"}
}