{
  "type": "Feature",
  "properties": {
    "iso:country":"US",
    "sg:address":"1507 Misty Cv",
    "sg:city":"Austin",
    "sg:classifiers":[
        {
            "category":"Building & Trades",
            "subcategory":"Construction",
            "type":"Services"
        }
    ],
    "sg:phone":"+1 512 339 2865",
    "sg:postcode":"78754",
    "sg:province":"TX",
    "sg:tags":[
        "consultant",
        "management"
    ],
    "wof:name":"C S Foxfire",
    "wof:placetype":"venue"
},
  "geometry": {"coordinates":[-97.664281,30.368124],"type":"Point"}
}