{
  "type": "Feature",
  "properties": {
    "iso:country":"US",
    "sg:address":"7817 Rockwood Ln 3rd Fl Ste 19",
    "sg:city":"Austin",
    "sg:classifiers":[
        {
            "category":"Personal",
            "subcategory":"Beauty Salon",
            "type":"Services"
        },
        {
            "category":"Personal",
            "subcategory":"Hair Removal",
            "type":"Services"
        }
    ],
    "sg:phone":"+1 512 695 6812",
    "sg:postcode":"78757",
    "sg:province":"TX",
    "sg:website":"www.salonsilvana.com/",
    "wof:name":"Salon Silvana - Hairlocs Hair Extensions",
    "wof:placetype":"venue"
},
  "geometry": {"coordinates":[-97.738175,30.358795],"type":"Point"}
}