{
  "type": "Feature",
  "properties": {
    "iso:country":"US",
    "sg:address":"8845 Highway 90 S",
    "sg:city":"Navasota",
    "sg:classifiers":[
        {
            "category":"Farming",
            "subcategory":"Livestock Farm",
            "type":"Manufacturing & Wholesale Goods"
        }
    ],
    "sg:phone":"+1 936 825 3294",
    "sg:postcode":"77868",
    "sg:province":"TX",
    "sg:tags":[
        "ranch"
    ],
    "wof:name":"Fred Thane",
    "wof:placetype":"venue"
},
  "geometry": {"coordinates":[-96.05763899999999,30.402432],"type":"Point"}
}