{
  "type": "Feature",
  "properties": {
    "iso:country":"US",
    "sg:address":"4223 Young St",
    "sg:city":"Pasadena",
    "sg:classifiers":[
        {
            "category":"Arts & Performance",
            "subcategory":"Dance",
            "type":"Entertainment"
        }
    ],
    "sg:phone":"+1 281 487 6539",
    "sg:postcode":"77504",
    "sg:province":"TX",
    "sg:tags":[
        "instruction",
        "dancing"
    ],
    "wof:name":"Mike's Dance World",
    "wof:placetype":"venue"
},
  "geometry": {"coordinates":[-95.194197,29.647307],"type":"Point"}
}