{
  "type": "Feature",
  "properties": {
    "iso:country":"US",
    "sg:address":"1304 1st St",
    "sg:city":"Seabrook",
    "sg:classifiers":[
        {
            "category":"Professional",
            "subcategory":"Business Services",
            "type":"Services"
        }
    ],
    "sg:phone":"+1 281 474 7968",
    "sg:postcode":"77586",
    "sg:province":"TX",
    "sg:tags":[
        "container",
        "inspection"
    ],
    "wof:name":"Silver Inspection Service Inc",
    "wof:placetype":"venue"
},
  "geometry": {"coordinates":[-95.021851,29.562212],"type":"Point"}
}