{
  "type": "Feature",
  "properties": {
    "iso:country":"US",
    "sg:address":"7801 N Lamar Boulevard Suite B174",
    "sg:city":"Austin",
    "sg:classifiers":[
        {
            "category":"Shopping",
            "subcategory":"Stationery & Office Supplies",
            "type":"Retail Goods"
        },
        {
            "category":"Banks & Credit Unions",
            "subcategory":"Investment Brokerage",
            "type":"Services"
        },
        {
            "category":"Manufacturing",
            "subcategory":"Paper Products",
            "type":"Manufacturing & Wholesale Goods"
        }
    ],
    "sg:phone":"+1 512 453 7650",
    "sg:postcode":"78752",
    "sg:province":"TX",
    "sg:tags":[
        "products-wholesale",
        "broker",
        "equipment",
        "representative",
        "converting",
        "mill",
        "manufacturer"
    ],
    "sg:website":"http://www.clampitt.com",
    "wof:name":"Fasclampitt",
    "wof:placetype":"venue"
},
  "geometry": {"coordinates":[-97.712874,30.346362],"type":"Point"}
}