{
  "type": "Feature",
  "properties": {
    "iso:country":"US",
    "sg:address":"4127 Idaho Ave",
    "sg:city":"Dallas",
    "sg:classifiers":[
        {
            "category":"Organizations",
            "subcategory":"Religious Organization",
            "type":"Services"
        }
    ],
    "sg:phone":"+1 214 374 3860",
    "sg:postcode":"75216",
    "sg:province":"TX",
    "sg:tags":[
        "church"
    ],
    "wof:name":"Living Testimony Baptist Chr",
    "wof:placetype":"venue"
},
  "geometry": {"coordinates":[-96.811846,32.695217],"type":"Point"}
}