{
  "type": "Feature",
  "properties": {
    "iso:country":"US",
    "sg:address":"6631 FM 1387",
    "sg:city":"Midlothian",
    "sg:classifiers":[
        {
            "category":"Education",
            "subcategory":"School",
            "type":"Public Place"
        }
    ],
    "sg:phone":"+1 972 775 2830",
    "sg:postcode":"75154",
    "sg:province":"TX",
    "wof:name":"Longbranch Elementary Sch",
    "wof:placetype":"venue"
},
  "geometry": {"coordinates":[-96.908064,32.486547],"type":"Point"}
}