{
  "type": "Feature",
  "properties": {
    "iso:country":"US",
    "sg:address":"2115 N 34th St",
    "sg:city":"Waco",
    "sg:classifiers":[
        {
            "category":"Health Services",
            "subcategory":"Doctor",
            "type":"Services"
        }
    ],
    "sg:phone":"+1 254 755 8577",
    "sg:postcode":"76708",
    "sg:province":"TX",
    "sg:tags":[
        "physician",
        "surgeon",
        "medical"
    ],
    "wof:name":"Rima Bishara Md",
    "wof:placetype":"venue"
},
  "geometry": {"coordinates":[-97.177261,31.553591],"type":"Point"}
}