{
  "type": "Feature",
  "properties": {
    "iso:country":"US",
    "sg:address":"2310 W 11th St",
    "sg:city":"Plainview",
    "sg:classifiers":[
        {
            "category":"Shopping",
            "subcategory":"Catalog Store",
            "type":"Retail Goods"
        }
    ],
    "sg:phone":"+1 806 296 6860",
    "sg:postcode":"79072",
    "sg:province":"TX",
    "sg:tags":[
        "mail",
        "house"
    ],
    "wof:name":"Cowboy Country Collectibles",
    "wof:placetype":"venue"
},
  "geometry": {"coordinates":[-101.730828,34.191748],"type":"Point"}
}