{
  "type": "Feature",
  "properties": {
    "iso:country":"US",
    "sg:address":"6715 Snider Plz",
    "sg:city":"Dallas",
    "sg:classifiers":[
        {
            "category":"Shopping",
            "subcategory":"Clothing, Apparel, & Fashions",
            "type":"Retail Goods"
        }
    ],
    "sg:phone":"+1 214 365 0801",
    "sg:postcode":"75205",
    "sg:province":"TX",
    "wof:name":"R & J Purse",
    "wof:placetype":"venue"
},
  "geometry": {"coordinates":[-96.787846,32.848359],"type":"Point"}
}