{
  "type": "Feature",
  "properties": {
    "iso:country":"US",
    "sg:address":"3409 Enterprise Dr Ste A",
    "sg:city":"Rowlett",
    "sg:classifiers":[
        {
            "category":"Professional",
            "subcategory":"Printing & Photocopies",
            "type":"Services"
        }
    ],
    "sg:phone":"+1 972 475 2045",
    "sg:postcode":"75088",
    "sg:province":"TX",
    "wof:name":"Brewer Printing/Flat Rate Printing & Promotions",
    "wof:placetype":"venue"
},
  "geometry": {"coordinates":[-96.57060199999999,32.905499],"type":"Point"}
}