{
  "type": "Feature",
  "properties": {
    "iso:country":"US",
    "sg:address":"4445 N Mesa St",
    "sg:city":"El Paso",
    "sg:classifiers":[
        {
            "category":"Restaurant",
            "type":"Food & Drink"
        }
    ],
    "sg:phone":"+1 915 544 8565",
    "sg:postcode":"79902",
    "sg:province":"TX",
    "wof:name":"Peter Piper Pizza",
    "wof:placetype":"venue"
},
  "geometry": {"coordinates":[-106.510876,31.799601],"type":"Point"}
}