{
  "type": "Feature",
  "properties": {
    "iso:country":"US",
    "sg:address":"12707 Queensbury Ln",
    "sg:city":"Houston",
    "sg:classifiers":[
        {
            "category":"Social Services",
            "subcategory":"Child Care",
            "type":"Services"
        }
    ],
    "sg:phone":"+1 713 827 7292",
    "sg:postcode":"77024",
    "sg:province":"TX",
    "sg:tags":[
        "nursery",
        "school",
        "toy",
        "book",
        "uniform"
    ],
    "wof:name":"Creme De La Creme",
    "wof:placetype":"venue"
},
  "geometry": {"coordinates":[-95.558177,29.778669],"type":"Point"}
}