{
  "type": "Feature",
  "properties": {
    "iso:country":"US",
    "sg:address":"6440 Rufe Snow Dr",
    "sg:city":"Fort Worth",
    "sg:classifiers":[
        {
            "category":"Restaurant",
            "type":"Food & Drink"
        }
    ],
    "sg:phone":"+1 817 577 0329",
    "sg:postcode":"76148",
    "sg:province":"TX",
    "sg:tags":[
        "eating"
    ],
    "sg:website":"www.burgerstreet.com",
    "wof:name":"Burger Street Inc",
    "wof:placetype":"venue"
},
  "geometry": {"coordinates":[-97.23800300000001,32.862321],"type":"Point"}
}