{
  "type": "Feature",
  "properties": {
    "iso:country":"US",
    "sg:address":"105 E Main St",
    "sg:city":"Bullard",
    "sg:classifiers":[
        {
            "category":"Deli",
            "type":"Food & Drink"
        },
        {
            "category":"Restaurant",
            "type":"Food & Drink"
        },
        {
            "category":"Food & Beverages",
            "subcategory":"Meat & Fish",
            "type":"Retail Goods"
        }
    ],
    "sg:phone":"+1 903 894 6263",
    "sg:postcode":"75757",
    "sg:province":"TX",
    "sg:tags":[
        "delicatessen",
        "market"
    ],
    "wof:name":"R A K's Meat Market & Deli",
    "wof:placetype":"venue"
},
  "geometry": {"coordinates":[-95.32110299999999,32.139705],"type":"Point"}
}