{
  "type": "Feature",
  "properties": {
    "iso:country":"US",
    "sg:address":"933 E Ave J",
    "sg:city":"Grand Prairie",
    "sg:classifiers":[
        {
            "category":"Building & Trades",
            "subcategory":"Construction",
            "type":"Services"
        }
    ],
    "sg:phone":"+1 972 641 2266",
    "sg:postcode":"75050",
    "sg:province":"TX",
    "sg:tags":[
        "general",
        "contractor"
    ],
    "wof:name":"Rayco Construction",
    "wof:placetype":"venue"
},
  "geometry": {"coordinates":[-97.05282200000001,32.766007],"type":"Point"}
}