{
  "type": "Feature",
  "properties": {
    "iso:country":"US",
    "sg:address":"1306 Burton Ave",
    "sg:city":"Orange",
    "sg:classifiers":[
        {
            "category":"Professional",
            "type":"Services"
        }
    ],
    "sg:phone":"+1 409 883 0054",
    "sg:postcode":"77630",
    "sg:province":"TX",
    "wof:name":"Charles",
    "wof:placetype":"venue"
},
  "geometry": {"coordinates":[-93.742766,30.1049],"type":"Point"}
}