{
  "type": "Feature",
  "properties": {
    "iso:country":"US",
    "sg:address":"501 S Staples St",
    "sg:city":"Corpus Christi",
    "sg:phone":"+1 361 904 0494",
    "sg:postcode":"78401",
    "sg:province":"TX",
    "sg:tags":[
        "equipment",
        "supply"
    ],
    "wof:name":"Discount Restaurant Supply",
    "wof:placetype":"venue"
},
  "geometry": {"coordinates":[-97.402214,27.786369],"type":"Point"}
}