{
  "type": "Feature",
  "properties": {
    "iso:country":"US",
    "sg:address":"610 Gibbins Ct",
    "sg:city":"Arlington",
    "sg:classifiers":[
        {
            "category":"Arts & Performance",
            "subcategory":"Theater",
            "type":"Entertainment"
        }
    ],
    "sg:phone":"+1 817 265 9432",
    "sg:postcode":"76011",
    "sg:province":"TX",
    "sg:tags":[
        "live",
        "music"
    ],
    "wof:name":"Black Pirate Productions",
    "wof:placetype":"venue"
},
  "geometry": {"coordinates":[-97.112278,32.755771],"type":"Point"}
}