{
  "type": "Feature",
  "properties": {
    "iso:country":"US",
    "sg:address":"6100 S 42nd St",
    "sg:city":"Mcallen",
    "sg:classifiers":[
        {
            "category":"Real Estate",
            "subcategory":"Real Estate Services",
            "type":"Services"
        },
        {
            "category":"Structure",
            "subcategory":"Office Building",
            "type":"Public Place"
        },
        {
            "category":"Real Estate",
            "subcategory":"Real Estate Agent",
            "type":"Services"
        }
    ],
    "sg:phone":"+1 956 971 9559",
    "sg:postcode":"78503",
    "sg:province":"TX",
    "sg:tags":[
        "management",
        "park"
    ],
    "wof:name":"Dur Properties",
    "wof:placetype":"venue"
},
  "geometry": {"coordinates":[-98.27607399999999,26.155158],"type":"Point"}
}