{
  "type": "Feature",
  "properties": {
    "iso:country":"US",
    "sg:address":"3410 82nd St",
    "sg:city":"Lubbock",
    "sg:classifiers":[
        {
            "category":"Personal",
            "subcategory":"Barber",
            "type":"Services"
        }
    ],
    "sg:phone":"+1 806 795 9201",
    "sg:postcode":"79423",
    "sg:province":"TX",
    "sg:tags":[
        "shop"
    ],
    "wof:name":"82nd St Barber & Style Shop",
    "wof:placetype":"venue"
},
  "geometry": {"coordinates":[-101.888553,33.519799],"type":"Point"}
}