{
  "type": "Feature",
  "properties": {
    "iso:country":"US",
    "sg:address":"21 Carriage Sq",
    "sg:city":"Waco",
    "sg:classifiers":[
        {
            "category":"Shopping",
            "subcategory":"Catalog Store",
            "type":"Retail Goods"
        }
    ],
    "sg:phone":"+1 254 753 7131",
    "sg:postcode":"76708",
    "sg:province":"TX",
    "sg:tags":[
        "house",
        "mail"
    ],
    "wof:name":"Suppliers Warehouse",
    "wof:placetype":"venue"
},
  "geometry": {"coordinates":[-97.18592,31.555849],"type":"Point"}
}