{
  "type": "Feature",
  "properties": {
    "iso:country":"US",
    "sg:address":"9412 W Montgomery Rd",
    "sg:city":"Houston",
    "sg:classifiers":[
        {
            "category":"Retail",
            "subcategory":"Car Wash",
            "type":"Services"
        }
    ],
    "sg:phone":"+1 281 445 6181",
    "sg:postcode":"77088",
    "sg:province":"TX",
    "sg:tags":[
        "automobile",
        "detail",
        "clean"
    ],
    "wof:name":"713 Auto Detailing",
    "wof:placetype":"venue"
},
  "geometry": {"coordinates":[-95.445789,29.87976],"type":"Point"}
}