{
  "type": "Feature",
  "properties": {
    "iso:country":"US",
    "sg:address":"825 S Crowley Rd",
    "sg:city":"Crowley",
    "sg:classifiers":[
        {
            "category":"Shopping",
            "subcategory":"Pharmacy",
            "type":"Retail Goods"
        }
    ],
    "sg:phone":"+1 817 297 3674",
    "sg:postcode":"76036",
    "sg:province":"TX",
    "sg:tags":[
        "drugstore"
    ],
    "sg:website":"www.cvs.com",
    "wof:name":"CVS pharmacy",
    "wof:placetype":"venue"
},
  "geometry": {"coordinates":[-97.352355,32.567212],"type":"Point"}
}