{
  "type": "Feature",
  "properties": {
    "iso:country":"US",
    "sg:address":"14100 Montfort Dr",
    "sg:city":"Dallas",
    "sg:classifiers":[
        {
            "category":"Arts & Performance",
            "subcategory":"Theater",
            "type":"Entertainment"
        }
    ],
    "sg:phone":"+1 972 239 2189",
    "sg:postcode":"75254",
    "sg:province":"TX",
    "sg:tags":[
        "group"
    ],
    "wof:name":"Choris Romance",
    "wof:placetype":"venue"
},
  "geometry": {"coordinates":[-96.814031,32.939541],"type":"Point"}
}