{
  "type": "Feature",
  "properties": {
    "iso:country":"US",
    "sg:address":"7336 Tanaqua Ln",
    "sg:city":"Austin",
    "sg:classifiers":[
        {
            "category":"Organizations",
            "subcategory":"Professional Association",
            "type":"Services"
        }
    ],
    "sg:phone":"+1 512 301 8705",
    "sg:postcode":"78739",
    "sg:province":"TX",
    "wof:name":"Tanaka, Hirofumi",
    "wof:placetype":"venue"
},
  "geometry": {"coordinates":[-97.904725,30.188456],"type":"Point"}
}