{
  "type": "Feature",
  "properties": {
    "iso:country":"US",
    "sg:address":"2801 Midwestern Pkwy",
    "sg:city":"Wichita Falls",
    "sg:classifiers":[
        {
            "category":"Restaurant",
            "type":"Food & Drink"
        }
    ],
    "sg:menulink":"http://www.allmenus.com/tx/wichita-falls/215478-atlanta-bread-company/menu/",
    "sg:phone":"+1 940 689 9098",
    "sg:postcode":"76308",
    "sg:province":"TX",
    "sg:tags":[
        "american"
    ],
    "wof:name":"Atlanta Bread Company",
    "wof:placetype":"venue"
},
  "geometry": {"coordinates":[-98.528716,33.870457],"type":"Point"}
}