{
  "type": "Feature",
  "properties": {
    "iso:country":"US",
    "sg:address":"107 N Main St",
    "sg:city":"Lockhart",
    "sg:classifiers":[
        {
            "category":"Shopping",
            "subcategory":"Gifts & Souvenirs",
            "type":"Retail Goods"
        }
    ],
    "sg:phone":"+1 512 376 3180",
    "sg:postcode":"78644",
    "sg:province":"TX",
    "wof:name":"Primerose & Fine Lace Tea",
    "wof:placetype":"venue"
},
  "geometry": {"coordinates":[-97.67265399999999,29.885526],"type":"Point"}
}