{
  "type": "Feature",
  "properties": {
    "iso:country":"US",
    "sg:address":"4601 S Flores St",
    "sg:city":"San Antonio",
    "sg:classifiers":[
        {
            "category":"Food & Beverages",
            "subcategory":"Meat & Fish",
            "type":"Retail Goods"
        }
    ],
    "sg:phone":"+1 210 977 8611",
    "sg:postcode":"78214",
    "sg:province":"TX",
    "wof:name":"Culebra Meat Market 12",
    "wof:placetype":"venue"
},
  "geometry": {"coordinates":[-98.50057700000001,29.379433],"type":"Point"}
}