{
  "type": "Feature",
  "properties": {
    "iso:country":"US",
    "sg:address":"17318 Pikes Peek Ct",
    "sg:city":"Tomball",
    "sg:classifiers":[
        {
            "category":"Professional",
            "type":"Services"
        }
    ],
    "sg:phone":"+1 281 655 1356",
    "sg:postcode":"77377",
    "sg:province":"TX",
    "wof:name":"Cross Line Christian Apparel I",
    "wof:placetype":"venue"
},
  "geometry": {"coordinates":[-95.607347,30.0167],"type":"Point"}
}