{
  "type": "Feature",
  "properties": {
    "iso:country":"US",
    "sg:address":"614 Cardinal Dr",
    "sg:city":"Red Oak",
    "sg:classifiers":[
        {
            "category":"Building & Trades",
            "subcategory":"Plumbing",
            "type":"Services"
        }
    ],
    "sg:phone":"+1 972 617 9099",
    "sg:postcode":"75154",
    "sg:province":"TX",
    "sg:tags":[
        "contractor"
    ],
    "wof:name":"Judd Co Plumbing",
    "wof:placetype":"venue"
},
  "geometry": {"coordinates":[-96.873169,32.526912],"type":"Point"}
}