{
  "type": "Feature",
  "properties": {
    "iso:country":"US",
    "sg:address":"809 Hurst St",
    "sg:city":"Center",
    "sg:classifiers":[
        {
            "category":"Autos & Motor Vehicles",
            "subcategory":"Automobile Sales",
            "type":"Retail Goods"
        }
    ],
    "sg:phone":"+1 936 591 9100",
    "sg:postcode":"75935",
    "sg:province":"TX",
    "sg:tags":[
        "dealers-used",
        "car",
        "used",
        "cars-wholesale"
    ],
    "wof:name":"Nintey-Six Equip.",
    "wof:placetype":"venue"
},
  "geometry": {"coordinates":[-94.191625,31.806183],"type":"Point"}
}