{
  "type": "Feature",
  "properties": {
    "iso:country":"US",
    "sg:address":"3319 Princeton Ave",
    "sg:city":"Dallas",
    "sg:classifiers":[
        {
            "category":"Professional",
            "type":"Services"
        }
    ],
    "sg:phone":"+1 214 520 7145",
    "sg:postcode":"75205",
    "sg:province":"TX",
    "wof:name":"Pulliam Clay Burnett",
    "wof:placetype":"venue"
},
  "geometry": {"coordinates":[-96.786812,32.831085],"type":"Point"}
}