{
  "type": "Feature",
  "properties": {
    "iso:country":"US",
    "sg:address":"3911 College Ave",
    "sg:city":"Snyder",
    "sg:classifiers":[
        {
            "category":"Food & Beverages",
            "subcategory":"Groceries & Convenience Stores",
            "type":"Retail Goods"
        }
    ],
    "sg:phone":"+1 325 573 8735",
    "sg:postcode":"79549",
    "sg:province":"TX",
    "wof:name":"Allsup's Convenience Store",
    "wof:placetype":"venue"
},
  "geometry": {"coordinates":[-100.919212,32.702764],"type":"Point"}
}