{
  "type": "Feature",
  "properties": {
    "iso:country":"US",
    "sg:address":"6714 Ellsworth Ave",
    "sg:city":"Dallas",
    "sg:classifiers":[
        {
            "category":"Freight",
            "type":"Transportation"
        },
        {
            "category":"Professional",
            "subcategory":"Management & Consulting",
            "type":"Services"
        }
    ],
    "sg:phone":"+1 214 823 9913",
    "sg:postcode":"75214",
    "sg:province":"TX",
    "sg:tags":[
        "business"
    ],
    "wof:name":"M & L Freight Svc",
    "wof:placetype":"venue"
},
  "geometry": {"coordinates":[-96.745508,32.833102],"type":"Point"}
}