{
  "type": "Feature",
  "properties": {
    "iso:country":"US",
    "sg:address":"3113 Fall Creek Hwy",
    "sg:city":"Granbury",
    "sg:classifiers":[
        {
            "category":"Personal",
            "subcategory":"Beauty Salon",
            "type":"Services"
        }
    ],
    "sg:phone":"+1 817 326 3806",
    "sg:postcode":"76049",
    "sg:province":"TX",
    "wof:name":"Eric Blaylock Harmony Day Spa",
    "wof:placetype":"venue"
},
  "geometry": {"coordinates":[-97.69004099999999,32.446609],"type":"Point"}
}