{
  "type": "Feature",
  "properties": {
    "iso:country":"US",
    "sg:address":"864 Lost Gold Rd",
    "sg:city":"Waco",
    "sg:classifiers":[
        {
            "category":"Real Estate",
            "subcategory":"Real Estate Agent",
            "type":"Services"
        }
    ],
    "sg:phone":"+1 254 749 2632",
    "sg:postcode":"76708",
    "sg:province":"TX",
    "wof:name":"Murray Lucy RE Apraisal",
    "wof:placetype":"venue"
},
  "geometry": {"coordinates":[-97.24815700000001,31.680956],"type":"Point"}
}