{
  "type": "Feature",
  "properties": {
    "iso:country":"US",
    "sg:address":"4001 Appian Way",
    "sg:city":"Arlington",
    "sg:classifiers":[
        {
            "category":"Manufacturing",
            "subcategory":"Jewelry",
            "type":"Manufacturing & Wholesale Goods"
        },
        {
            "category":"Shopping",
            "subcategory":"Crafts & Fabrics",
            "type":"Retail Goods"
        }
    ],
    "sg:phone":"+1 817 277 8282",
    "sg:postcode":"76013",
    "sg:province":"TX",
    "sg:tags":[
        "scrapbooking",
        "designer",
        "art",
        "supply"
    ],
    "sg:website":"http://www.first-impressions-designs.com",
    "wof:name":"First Impressions Designs",
    "wof:placetype":"venue"
},
  "geometry": {"coordinates":[-97.166573,32.708241],"type":"Point"}
}