{
  "type": "Feature",
  "properties": {
    "iso:country":"US",
    "sg:address":"906 Shady Grove Dr",
    "sg:city":"Granbury",
    "sg:classifiers":[
        {
            "category":"Retail",
            "subcategory":"Repair Shop",
            "type":"Services"
        }
    ],
    "sg:phone":"+1 817 326 8314",
    "sg:postcode":"76049",
    "sg:province":"TX",
    "wof:name":"Pw Enterprises",
    "wof:placetype":"venue"
},
  "geometry": {"coordinates":[-97.739345,32.442752],"type":"Point"}
}