{
  "type": "Feature",
  "properties": {
    "iso:country":"US",
    "sg:address":"5513 Pawn Ct",
    "sg:city":"Lake Dallas",
    "sg:classifiers":[
        {
            "category":"Professional",
            "type":"Services"
        }
    ],
    "sg:phone":"+1 940 497 0307",
    "sg:postcode":"75065",
    "sg:province":"TX",
    "wof:name":"Tricia Lowery",
    "wof:placetype":"venue"
},
  "geometry": {"coordinates":[-97.02689700000001,33.129218],"type":"Point"}
}