{
  "type": "Feature",
  "properties": {
    "iso:country":"US",
    "sg:address":"6402 Briarstone Ln",
    "sg:city":"Spring",
    "sg:classifiers":[
        {
            "category":"Professional",
            "type":"Services"
        }
    ],
    "sg:phone":"+1 281 374 7175",
    "sg:postcode":"77379",
    "sg:province":"TX",
    "wof:name":"Raymond H Jackson",
    "wof:placetype":"venue"
},
  "geometry": {"coordinates":[-95.517601,30.058098],"type":"Point"}
}