{
  "type": "Feature",
  "properties": {
    "iso:country":"US",
    "sg:address":"1415 Hollywood Ave",
    "sg:city":"Dallas",
    "sg:classifiers":[
        {
            "category":"Building & Trades",
            "subcategory":"Landscaping Services",
            "type":"Services"
        }
    ],
    "sg:phone":"+1 214 339 8603",
    "sg:postcode":"75208",
    "sg:province":"TX",
    "sg:tags":[
        "designer",
        "landscape"
    ],
    "wof:name":"Nature's Garden",
    "wof:placetype":"venue"
},
  "geometry": {"coordinates":[-96.855625,32.730597],"type":"Point"}
}