{
  "type": "Feature",
  "properties": {
    "iso:country":"US",
    "sg:address":"14 Crested Pines Ct",
    "sg:city":"Spring",
    "sg:classifiers":[
        {
            "category":"Home & Garden",
            "subcategory":"Home Furnishings",
            "type":"Retail Goods"
        }
    ],
    "sg:phone":"+1 281 367 1933",
    "sg:postcode":"77381",
    "sg:province":"TX",
    "wof:name":"Kimberlys Kollections",
    "wof:placetype":"venue"
},
  "geometry": {"coordinates":[-95.480313,30.17376],"type":"Point"}
}