{
  "type": "Feature",
  "properties": {
    "iso:country":"US",
    "sg:address":"815 N O Connor Rd",
    "sg:city":"Irving",
    "sg:classifiers":[
        {
            "category":"Shopping",
            "subcategory":"Pharmacy",
            "type":"Retail Goods"
        }
    ],
    "sg:phone":"+1 972 579 0511",
    "sg:postcode":"75061",
    "sg:province":"TX",
    "sg:tags":[
        "drugstore"
    ],
    "wof:name":"Gibson's Discount Pharmacy",
    "wof:placetype":"venue"
},
  "geometry": {"coordinates":[-96.949799,32.821999],"type":"Point"}
}