{
  "type": "Feature",
  "properties": {
    "iso:country":"US",
    "sg:address":"5600 Stuart Cir",
    "sg:city":"Austin",
    "sg:phone":"+1 512 385 9518",
    "sg:postcode":"78721",
    "sg:province":"TX",
    "wof:name":"Guzman Drywall",
    "wof:placetype":"venue"
},
  "geometry": {"coordinates":[-97.686081,30.26124],"type":"Point"}
}