{
  "type": "Feature",
  "properties": {
    "iso:country":"US",
    "sg:address":"822 Brunswick Dr",
    "sg:city":"Sugar Land",
    "sg:classifiers":[
        {
            "category":"Professional",
            "subcategory":"Business Services",
            "type":"Services"
        }
    ],
    "sg:phone":"+1 281 494 5461",
    "sg:postcode":"77478",
    "sg:province":"TX",
    "wof:name":"Beth Herring",
    "wof:placetype":"venue"
},
  "geometry": {"coordinates":[-95.58383000000001,29.614765],"type":"Point"}
}