{
  "type": "Feature",
  "properties": {
    "iso:country":"US",
    "sg:address":"4800 W 34th St",
    "sg:city":"Houston",
    "sg:classifiers":[
        {
            "category":"Building & Trades",
            "subcategory":"Electrical",
            "type":"Services"
        }
    ],
    "sg:phone":"+1 713 686 3456",
    "sg:postcode":"77092",
    "sg:province":"TX",
    "sg:tags":[
        "communications",
        "installation",
        "system"
    ],
    "wof:name":"Tvs Telephone Inc",
    "wof:placetype":"venue"
},
  "geometry": {"coordinates":[-95.461247,29.819669],"type":"Point"}
}