{
  "type": "Feature",
  "properties": {
    "iso:country":"US",
    "sg:address":"1551 N Walnut Ave",
    "sg:city":"New Braunfels",
    "sg:classifiers":[
        {
            "category":"Professional",
            "subcategory":"Business Services",
            "type":"Services"
        }
    ],
    "sg:phone":"+1 830 625 2278",
    "sg:postcode":"78130",
    "sg:province":"TX",
    "sg:tags":[
        "telemarketing"
    ],
    "wof:name":"Trade Publication Svc",
    "wof:placetype":"venue"
},
  "geometry": {"coordinates":[-98.155377,29.713508],"type":"Point"}
}