{
  "type": "Feature",
  "properties": {
    "iso:country":"US",
    "sg:address":"644 N Dixie Dr",
    "sg:city":"Lake Jackson",
    "sg:classifiers":[
        {
            "category":"Shopping",
            "subcategory":"Musical Instruments",
            "type":"Retail Goods"
        }
    ],
    "sg:phone":"+1 979 297 1278",
    "sg:postcode":"77566",
    "sg:province":"TX",
    "wof:name":"B & H Music Co",
    "wof:placetype":"venue"
},
  "geometry": {"coordinates":[-95.421975,29.03234],"type":"Point"}
}