{
  "type": "Feature",
  "properties": {
    "iso:country":"US",
    "sg:address":"2030 Gessner Dr",
    "sg:city":"Houston",
    "sg:classifiers":[
        {
            "category":"Restaurant",
            "type":"Food & Drink"
        }
    ],
    "sg:phone":"+1 713 465 3030",
    "sg:postcode":"77080",
    "sg:province":"TX",
    "sg:tags":[
        "pizza"
    ],
    "sg:website":"www.dominos.com",
    "wof:name":"Domino's Pizza",
    "wof:placetype":"venue"
},
  "geometry": {"coordinates":[-95.545097,29.8095],"type":"Point"}
}