{
  "type": "Feature",
  "properties": {
    "iso:country":"US",
    "sg:address":"2101 E St Elmo Rd",
    "sg:city":"Austin",
    "sg:classifiers":[
        {
            "category":"Professional",
            "subcategory":"Business Services",
            "type":"Services"
        }
    ],
    "sg:phone":"+1 512 275 9300",
    "sg:postcode":"78744",
    "sg:province":"TX",
    "wof:name":"Print Logics Inc",
    "wof:placetype":"venue"
},
  "geometry": {"coordinates":[-97.74763,30.210299],"type":"Point"}
}