{
  "type": "Feature",
  "properties": {
    "iso:country":"US",
    "sg:address":"5420 Lyndon B Johnson Fwy",
    "sg:city":"Dallas",
    "sg:classifiers":[
        {
            "category":"Professional",
            "subcategory":"Lawyer & Legal Services",
            "type":"Services"
        }
    ],
    "sg:phone":"+1 972 386 0158",
    "sg:postcode":"75240",
    "sg:province":"TX",
    "sg:tags":[
        "divorce",
        "law",
        "family"
    ],
    "wof:name":"CLI-TX",
    "wof:placetype":"venue"
},
  "geometry": {"coordinates":[-96.81586,32.925362],"type":"Point"}
}