{
  "type": "Feature",
  "properties": {
    "iso:country":"US",
    "sg:address":"4107 W 45th Ave",
    "sg:city":"Amarillo",
    "sg:classifiers":[
        {
            "category":"Shopping",
            "subcategory":"Clothing, Apparel, & Fashions",
            "type":"Retail Goods"
        }
    ],
    "sg:phone":"+1 806 353 0029",
    "sg:postcode":"79109",
    "sg:province":"TX",
    "sg:tags":[
        "family"
    ],
    "wof:name":"Exotica Wears",
    "wof:placetype":"venue"
},
  "geometry": {"coordinates":[-101.883819,35.163779],"type":"Point"}
}