{
  "type": "Feature",
  "properties": {
    "iso:country":"US",
    "sg:address":"1810 3rd St",
    "sg:city":"Lubbock",
    "sg:classifiers":[
        {
            "category":"Real Estate",
            "subcategory":"Real Estate Operator",
            "type":"Services"
        }
    ],
    "sg:phone":"+1 806 747 9464",
    "sg:postcode":"79415",
    "sg:province":"TX",
    "sg:tags":[
        "apartment"
    ],
    "wof:name":"Casa Orlando Apartments",
    "wof:placetype":"venue"
},
  "geometry": {"coordinates":[-101.85744699999999,33.594278],"type":"Point"}
}