{
  "type": "Feature",
  "properties": {
    "iso:country":"US",
    "sg:address":"146 Oak Wood Rd",
    "sg:city":"Kerrville",
    "sg:classifiers":[
        {
            "category":"Social Services",
            "type":"Services"
        }
    ],
    "sg:phone":"+1 830 895 4446",
    "sg:postcode":"78028",
    "sg:province":"TX",
    "sg:tags":[
        "counselor",
        "marriage",
        "family"
    ],
    "wof:name":"Texas Professional Recovery",
    "wof:placetype":"venue"
},
  "geometry": {"coordinates":[-99.11417899999999,29.967543],"type":"Point"}
}