{
  "type": "Feature",
  "properties": {
    "iso:country":"US",
    "sg:address":"1300 Cypress Trl",
    "sg:city":"Taylor",
    "sg:classifiers":[
        {
            "category":"Building & Trades",
            "subcategory":"Electrical",
            "type":"Services"
        }
    ],
    "sg:phone":"+1 512 365 5250",
    "sg:postcode":"76574",
    "sg:province":"TX",
    "sg:tags":[
        "electrical",
        "contractor"
    ],
    "wof:name":"AAA Electric Inc",
    "wof:placetype":"venue"
},
  "geometry": {"coordinates":[-97.430171,30.595357],"type":"Point"}
}