{
  "type": "Feature",
  "properties": {
    "iso:country":"US",
    "sg:address":"9275 Richmond Ave Ste 180",
    "sg:city":"Houston",
    "sg:classifiers":[
        {
            "category":"Education",
            "subcategory":"Vocational School",
            "type":"Public Place"
        },
        {
            "category":"Education",
            "subcategory":"University",
            "type":"Public Place"
        }
    ],
    "sg:phone":"+1 713 953 0262",
    "sg:postcode":"77063",
    "sg:province":"TX",
    "sg:tags":[
        "college",
        "cosmetology"
    ],
    "wof:name":"Texas Barber College",
    "wof:placetype":"venue"
},
  "geometry": {"coordinates":[-95.527603,29.728901],"type":"Point"}
}