{
  "type": "Feature",
  "properties": {
    "iso:country":"US",
    "sg:address":"4811 Big Falls Dr",
    "sg:city":"Humble",
    "sg:classifiers":[
        {
            "category":"Professional",
            "subcategory":"Business Services",
            "type":"Services"
        }
    ],
    "sg:phone":"+1 281 360 3183",
    "sg:postcode":"77345",
    "sg:province":"TX",
    "wof:name":"Wanguri Enterprises Inc",
    "wof:placetype":"venue"
},
  "geometry": {"coordinates":[-95.171908,30.048845],"type":"Point"}
}