{
  "type": "Feature",
  "properties": {
    "iso:country":"US",
    "sg:address":"1107 W Adams Ave",
    "sg:city":"Temple",
    "sg:classifiers":[
        {
            "category":"Manufacturing",
            "subcategory":"Glass & Minerals",
            "type":"Manufacturing & Wholesale Goods"
        },
        {
            "category":"Retail",
            "subcategory":"Auto Repair",
            "type":"Services"
        }
    ],
    "sg:phone":"+1 254 773 2642",
    "sg:postcode":"76504",
    "sg:province":"TX",
    "sg:tags":[
        "plate",
        "window",
        "windshield",
        "glass-auto"
    ],
    "sg:website":"http://www.wacoautoglasscenter.com",
    "wof:name":"Avenue Auto Glass Company",
    "wof:placetype":"venue"
},
  "geometry": {"coordinates":[-97.351669,31.100656],"type":"Point"}
}