{
  "type": "Feature",
  "properties": {
    "iso:country":"US",
    "sg:address":"2201 S I- 35 E",
    "sg:city":"Denton",
    "sg:classifiers":[
        {
            "category":"Real Estate",
            "subcategory":"Real Estate Operator",
            "type":"Services"
        },
        {
            "category":"Cinema",
            "subcategory":"Movie Theater",
            "type":"Entertainment"
        }
    ],
    "sg:phone":"+1 940 383 1130",
    "sg:postcode":"76205",
    "sg:province":"TX",
    "sg:tags":[
        "motion",
        "picture",
        "mall",
        "shopping",
        "center"
    ],
    "wof:name":"Golden Triangle Mall",
    "wof:placetype":"venue"
},
  "geometry": {"coordinates":[-97.10888,33.187669],"type":"Point"}
}