{
  "type": "Feature",
  "properties": {
    "iso:country":"US",
    "sg:address":"4560 W Highway 80 E",
    "sg:city":"Odessa",
    "sg:phone":"+1 432 381 2401",
    "sg:postcode":"79765",
    "sg:province":"TX",
    "sg:website":"http://www.citronsusedparts.com",
    "wof:name":"Citron's Used Auto Parts & Light Truck Parts",
    "wof:placetype":"venue"
},
  "geometry": {"coordinates":[-102.27619900000001,31.8921],"type":"Point"}
}