{
  "type": "Feature",
  "properties": {
    "iso:country":"US",
    "sg:address":"29702 Turner Rd",
    "sg:city":"Magnolia",
    "sg:classifiers":[
        {
            "category":"Professional",
            "subcategory":"Business Services",
            "type":"Services"
        }
    ],
    "sg:phone":"+1 281 356 1904",
    "sg:postcode":"77355",
    "sg:province":"TX",
    "wof:name":"Summit Commercial Kitchens",
    "wof:placetype":"venue"
},
  "geometry": {"coordinates":[-95.745312,30.178524],"type":"Point"}
}