{
  "type": "Feature",
  "properties": {
    "iso:country":"US",
    "sg:address":"111 N College St",
    "sg:city":"Georgetown",
    "sg:classifiers":[
        {
            "category":"Professional",
            "subcategory":"Computer Services",
            "type":"Services"
        }
    ],
    "sg:phone":"+1 512 930 3085",
    "sg:postcode":"78626",
    "sg:province":"TX",
    "sg:tags":[
        "internet"
    ],
    "wof:name":"Cox Communications",
    "wof:placetype":"venue"
},
  "geometry": {"coordinates":[-97.672157,30.64345],"type":"Point"}
}