{
  "type": "Feature",
  "properties": {
    "iso:country":"US",
    "sg:address":"1908 Ave F",
    "sg:city":"Del Rio",
    "sg:classifiers":[
        {
            "category":"Health Services",
            "subcategory":"Medical Lab",
            "type":"Services"
        }
    ],
    "sg:phone":"+1 830 768 0915",
    "sg:postcode":"78840",
    "sg:province":"TX",
    "sg:tags":[
        "laboratory",
        "clinical",
        "testing"
    ],
    "wof:name":"Quest Diagnostics",
    "wof:placetype":"venue"
},
  "geometry": {"coordinates":[-100.905514,29.383606],"type":"Point"}
}