{
  "type": "Feature",
  "properties": {
    "iso:country":"US",
    "sg:address":"400 Parr Ave",
    "sg:city":"Spicewood",
    "sg:classifiers":[
        {
            "category":"Building & Trades",
            "subcategory":"Construction",
            "type":"Services"
        }
    ],
    "sg:phone":"+1 830 693 8615",
    "sg:postcode":"78669",
    "sg:province":"TX",
    "sg:tags":[
        "concrete",
        "contractor"
    ],
    "wof:name":"Maxum Concrete Construction",
    "wof:placetype":"venue"
},
  "geometry": {"coordinates":[-98.202809,30.487152],"type":"Point"}
}