{
  "type": "Feature",
  "properties": {
    "iso:country":"US",
    "sg:address":"14700 FM 2100",
    "sg:city":"Crosby",
    "sg:classifiers":[
        {
            "category":"Banks & Credit Unions",
            "subcategory":"Bank",
            "type":"Services"
        }
    ],
    "sg:phone":"+1 281 867 1360",
    "sg:postcode":"77532",
    "sg:province":"TX",
    "sg:tags":[
        "state"
    ],
    "wof:name":"Compass Bank",
    "wof:placetype":"venue"
},
  "geometry": {"coordinates":[-95.06350399999999,29.900198],"type":"Point"}
}