{
  "type": "Feature",
  "properties": {
    "iso:country":"US",
    "sg:address":"3800 W Vickery Blvd",
    "sg:city":"Fort Worth",
    "sg:classifiers":[
        {
            "category":"Professional",
            "subcategory":"Business Services",
            "type":"Services"
        }
    ],
    "sg:phone":"+1 817 731 7500",
    "sg:postcode":"76107",
    "sg:province":"TX",
    "sg:tags":[
        "interior",
        "consultant",
        "design",
        "decorator"
    ],
    "sg:website":"www.tileartstudios.com",
    "wof:name":"Summit Tile & Granite Inc",
    "wof:placetype":"venue"
},
  "geometry": {"coordinates":[-97.372801,32.729962],"type":"Point"}
}