{
  "type": "Feature",
  "properties": {
    "iso:country":"US",
    "sg:address":"2424 Bay Area Blvd",
    "sg:city":"Houston",
    "sg:classifiers":[
        {
            "category":"Banks & Credit Unions",
            "subcategory":"Bank",
            "type":"Services"
        }
    ],
    "sg:phone":"+1 281 286 6800",
    "sg:postcode":"77058",
    "sg:province":"TX",
    "sg:tags":[
        "state",
        "commercial"
    ],
    "wof:name":"Comerica",
    "wof:placetype":"venue"
},
  "geometry": {"coordinates":[-95.108006,29.575118],"type":"Point"}
}