{
  "type": "Feature",
  "properties": {
    "iso:country":"US",
    "sg:address":"17006 Fenny Bridge Ln",
    "sg:city":"Spring",
    "sg:classifiers":[
        {
            "category":"Building & Trades",
            "subcategory":"Construction",
            "type":"Services"
        }
    ],
    "sg:phone":"+1 281 804 3108",
    "sg:postcode":"77379",
    "sg:province":"TX",
    "sg:tags":[
        "repairing",
        "remodeling",
        "contractor"
    ],
    "wof:name":"Creative Improvements LLC",
    "wof:placetype":"venue"
},
  "geometry": {"coordinates":[-95.557174,30.018392],"type":"Point"}
}