{
  "type": "Feature",
  "properties": {
    "iso:country":"US",
    "sg:address":"1701 Preston Rd",
    "sg:city":"Plano",
    "sg:classifiers":[
        {
            "category":"Shopping",
            "subcategory":"Clothing, Apparel, & Fashions",
            "type":"Retail Goods"
        }
    ],
    "sg:phone":"+1 972 735 1229",
    "sg:postcode":"75093",
    "sg:province":"TX",
    "sg:tags":[
        "wear",
        "merchandise",
        "furn"
    ],
    "wof:name":"Babies R Us",
    "wof:placetype":"venue"
},
  "geometry": {"coordinates":[-96.795141,33.024803],"type":"Point"}
}