{
  "type": "Feature",
  "properties": {
    "iso:country":"US",
    "sg:address":"905 Pleasanton Rd",
    "sg:city":"San Antonio",
    "sg:classifiers":[
        {
            "category":"Government",
            "subcategory":"Office",
            "type":"Public Place"
        }
    ],
    "sg:phone":"+1 210 924 6500",
    "sg:postcode":"78214",
    "sg:province":"TX",
    "sg:tags":[
        "state",
        "resource"
    ],
    "wof:name":"Texas Human Svc Dept",
    "wof:placetype":"venue"
},
  "geometry": {"coordinates":[-98.504344,29.374664],"type":"Point"}
}