{
  "type": "Feature",
  "properties": {
    "iso:country":"US",
    "sg:address":"403 N Guadalupe St",
    "sg:city":"San Marcos",
    "sg:classifiers":[
        {
            "category":"Food & Beverages",
            "subcategory":"Groceries & Convenience Stores",
            "type":"Retail Goods"
        }
    ],
    "sg:phone":"+1 512 396 4551",
    "sg:postcode":"78666",
    "sg:province":"TX",
    "wof:name":"7-Eleven",
    "wof:placetype":"venue"
},
  "geometry": {"coordinates":[-97.94191600000001,29.886359],"type":"Point"}
}