{
  "type": "Feature",
  "properties": {
    "iso:country":"US",
    "sg:address":"10510 Jody Ct",
    "sg:city":"Houston",
    "sg:classifiers":[
        {
            "category":"Professional",
            "subcategory":"Credit Reporting & Collection",
            "type":"Services"
        }
    ],
    "sg:phone":"+1 281 564 1252",
    "sg:postcode":"77099",
    "sg:province":"TX",
    "wof:name":"Anderson Blake Keller & Willia",
    "wof:placetype":"venue"
},
  "geometry": {"coordinates":[-95.61044,29.668494],"type":"Point"}
}