{
  "type": "Feature",
  "properties": {
    "iso:country":"US",
    "sg:address":"5713 Azle Ave",
    "sg:city":"Fort Worth",
    "sg:classifiers":[
        {
            "category":"Autos & Motor Vehicles",
            "subcategory":"Automobile Sales",
            "type":"Retail Goods"
        }
    ],
    "sg:phone":"+1 817 626 2411",
    "sg:postcode":"76114",
    "sg:province":"TX",
    "sg:tags":[
        "car",
        "dealer"
    ],
    "wof:name":"Texmex Motor Co",
    "wof:placetype":"venue"
},
  "geometry": {"coordinates":[-97.405383,32.81139],"type":"Point"}
}