{
  "type": "Feature",
  "properties": {
    "iso:country":"US",
    "sg:address":"915 State Hwy 323",
    "sg:city":"Tyler",
    "sg:classifiers":[
        {
            "category":"Travel",
            "subcategory":"Travel Agent",
            "type":"Entertainment"
        }
    ],
    "sg:phone":"+1 903 581 8111",
    "sg:postcode":"75701",
    "sg:province":"TX",
    "sg:tags":[
        "agency"
    ],
    "wof:name":"Travel Masters of Tyler",
    "wof:placetype":"venue"
},
  "geometry": {"coordinates":[-95.310992,32.303738],"type":"Point"}
}