{
  "type": "Feature",
  "properties": {
    "iso:country":"US",
    "sg:address":"715 San Mario Ct",
    "sg:city":"College Station",
    "sg:classifiers":[
        {
            "category":"Professional",
            "type":"Services"
        }
    ],
    "sg:phone":"+1 979 693 0148",
    "sg:postcode":"77845",
    "sg:province":"TX",
    "wof:name":"Warren Doyle",
    "wof:placetype":"venue"
},
  "geometry": {"coordinates":[-96.310491,30.584073],"type":"Point"}
}