{
  "type": "Feature",
  "properties": {
    "iso:country":"US",
    "sg:address":"3223 Smith St",
    "sg:city":"Houston",
    "sg:classifiers":[
        {
            "category":"Professional",
            "subcategory":"Lawyer & Legal Services",
            "type":"Services"
        }
    ],
    "sg:phone":"+1 713 529 2498",
    "sg:postcode":"77006",
    "sg:province":"TX",
    "sg:tags":[
        "attorney"
    ],
    "wof:name":"Daryl Moore",
    "wof:placetype":"venue"
},
  "geometry": {"coordinates":[-95.38087299999999,29.74311],"type":"Point"}
}