{
  "type": "Feature",
  "properties": {
    "iso:country":"US",
    "sg:address":"5240 FM 893",
    "sg:city":"Taft",
    "sg:phone":"+1 361 528 5474",
    "sg:postcode":"78390",
    "sg:province":"TX",
    "sg:tags":[
        "farm",
        "grain",
        "sorghum",
        "cotton"
    ],
    "wof:name":"Sam G Floerke Farms Inc",
    "wof:placetype":"venue"
},
  "geometry": {"coordinates":[-97.408225,27.947213],"type":"Point"}
}