{
  "type": "Feature",
  "properties": {
    "iso:country":"US",
    "sg:address":"305 W Main St",
    "sg:city":"Olney",
    "sg:classifiers":[
        {
            "category":"Health Services",
            "subcategory":"Doctor",
            "type":"Services"
        }
    ],
    "sg:phone":"+1 940 564 4470",
    "sg:postcode":"76374",
    "sg:province":"TX",
    "sg:tags":[
        "dentist"
    ],
    "wof:name":"Olney Family Dentistry",
    "wof:placetype":"venue"
},
  "geometry": {"coordinates":[-98.757291,33.370551],"type":"Point"}
}