{
  "type": "Feature",
  "properties": {
    "iso:country":"US",
    "sg:address":"1505 Southwest Pkwy",
    "sg:city":"Wichita Falls",
    "sg:classifiers":[
        {
            "category":"Recreation",
            "type":"Entertainment"
        }
    ],
    "sg:phone":"+1 940 767 0246",
    "sg:postcode":"76302",
    "sg:province":"TX",
    "wof:name":"Clicks Billiards",
    "wof:placetype":"venue"
},
  "geometry": {"coordinates":[-98.503987,33.854621],"type":"Point"}
}