{
  "type": "Feature",
  "properties": {
    "iso:country":"US",
    "sg:address":"3820 Old Spanish Trl",
    "sg:city":"Houston",
    "sg:classifiers":[
        {
            "category":"Restaurant",
            "type":"Food & Drink"
        }
    ],
    "sg:menulink":"http://www.allmenus.com/tx/houston/202500-mcdonalds/menu/",
    "sg:postcode":"77021",
    "sg:province":"TX",
    "sg:tags":[
        "burger",
        "american"
    ],
    "wof:name":"McDonald's",
    "wof:placetype":"venue"
},
  "geometry": {"coordinates":[-95.359892,29.701766],"type":"Point"}
}