{
  "type": "Feature",
  "properties": {
    "iso:country":"US",
    "sg:address":"2119 Miller Dr",
    "sg:city":"Tyler",
    "sg:classifiers":[
        {
            "category":"Building & Trades",
            "subcategory":"Construction",
            "type":"Services"
        }
    ],
    "sg:phone":"+1 903 593 8796",
    "sg:postcode":"75701",
    "sg:province":"TX",
    "sg:tags":[
        "industrial",
        "painting"
    ],
    "wof:name":"AC Special Services",
    "wof:placetype":"venue"
},
  "geometry": {"coordinates":[-95.273251,32.31761],"type":"Point"}
}