{
  "type": "Feature",
  "properties": {
    "iso:country":"US",
    "sg:address":"4107 Double Oak Ct",
    "sg:city":"Arlington",
    "sg:classifiers":[
        {
            "category":"Shopping",
            "subcategory":"Baby Store",
            "type":"Retail Goods"
        }
    ],
    "sg:phone":"+1 817 561 9127",
    "sg:postcode":"76001",
    "sg:province":"TX",
    "sg:tags":[
        "children's",
        "infant",
        "wear"
    ],
    "wof:name":"New & Used Kid Stuff",
    "wof:placetype":"venue"
},
  "geometry": {"coordinates":[-97.172202,32.637745],"type":"Point"}
}