{
  "type": "Feature",
  "properties": {
    "iso:country":"US",
    "sg:address":"1502 Old McDade Rd",
    "sg:city":"Elgin",
    "sg:classifiers":[
        {
            "category":"Retail",
            "subcategory":"Repair Shop",
            "type":"Services"
        }
    ],
    "sg:phone":"+1 512 281 3848",
    "sg:postcode":"78621",
    "sg:province":"TX",
    "sg:tags":[
        "welding"
    ],
    "wof:name":"Custom Welding Works",
    "wof:placetype":"venue"
},
  "geometry": {"coordinates":[-97.318074,30.324774],"type":"Point"}
}