{
  "type": "Feature",
  "properties": {
    "iso:country":"US",
    "sg:address":"1101 W Expy 83",
    "sg:city":"Mcallen",
    "sg:classifiers":[
        {
            "category":"Shopping",
            "subcategory":"Hobbies, Toys, & Games",
            "type":"Retail Goods"
        }
    ],
    "sg:phone":"+1 956 682 8697",
    "sg:postcode":"78503",
    "sg:province":"TX",
    "wof:name":"Toys R Us",
    "wof:placetype":"venue"
},
  "geometry": {"coordinates":[-98.236223,26.189664],"type":"Point"}
}