{
  "type": "Feature",
  "properties": {
    "iso:country":"US",
    "sg:address":"20515 I- 45",
    "sg:city":"Spring",
    "sg:classifiers":[
        {
            "category":"Home & Garden",
            "subcategory":"Mobile Homes",
            "type":"Retail Goods"
        }
    ],
    "sg:phone":"+1 281 355 0700",
    "sg:postcode":"77388",
    "sg:province":"TX",
    "wof:name":"Palm Harbor Village",
    "wof:placetype":"venue"
},
  "geometry": {"coordinates":[-95.43439100000001,30.063921],"type":"Point"}
}