{
  "type": "Feature",
  "properties": {
    "iso:country":"US",
    "sg:address":"7637 Long Point Rd",
    "sg:city":"Houston",
    "sg:classifiers":[
        {
            "category":"Autos & Motor Vehicles",
            "subcategory":"Auto Supplies",
            "type":"Retail Goods"
        }
    ],
    "sg:phone":"+1 832 332 5922",
    "sg:postcode":"77055",
    "sg:province":"TX",
    "sg:tags":[
        "glass"
    ],
    "wof:name":"VARGAS AUTO GLASS",
    "wof:placetype":"venue"
},
  "geometry": {"coordinates":[-95.48008400000001,29.80269],"type":"Point"}
}