{
  "type": "Feature",
  "properties": {
    "iso:country":"US",
    "sg:address":"5114 Gasmer Dr",
    "sg:city":"Houston",
    "sg:classifiers":[
        {
            "category":"Organizations",
            "subcategory":"Religious Organization",
            "type":"Services"
        }
    ],
    "sg:phone":"+1 713 283 8680",
    "sg:postcode":"77035",
    "sg:province":"TX",
    "wof:name":"Sharon Fellowship Church of Houston",
    "wof:placetype":"venue"
},
  "geometry": {"coordinates":[-95.46839900000001,29.6513],"type":"Point"}
}