{
  "type": "Feature",
  "properties": {
    "iso:country":"US",
    "sg:address":"308 S Garcia St",
    "sg:city":"Port Isabel",
    "sg:classifiers":[
        {
            "category":"Real Estate",
            "subcategory":"Real Estate Agent",
            "type":"Services"
        }
    ],
    "sg:phone":"+1 956 943 5950",
    "sg:postcode":"78578",
    "sg:province":"TX",
    "sg:tags":[
        "finding",
        "apartment",
        "rental"
    ],
    "wof:name":"Raven Corp",
    "wof:placetype":"venue"
},
  "geometry": {"coordinates":[-97.205685,26.076381],"type":"Point"}
}