{
  "type": "Feature",
  "properties": {
    "iso:country":"US",
    "sg:address":"319 N Prairieville St",
    "sg:city":"Athens",
    "sg:classifiers":[
        {
            "category":"Retail",
            "subcategory":"Auto Repair",
            "type":"Services"
        }
    ],
    "sg:phone":"+1 903 675 2214",
    "sg:postcode":"75751",
    "sg:province":"TX",
    "sg:tags":[
        "general"
    ],
    "wof:name":"Check Auto",
    "wof:placetype":"venue"
},
  "geometry": {"coordinates":[-95.85513,32.206427],"type":"Point"}
}