{
  "type": "Feature",
  "properties": {
    "iso:country":"US",
    "sg:address":"520 Sowell Ln",
    "sg:city":"Texarkana",
    "sg:classifiers":[
        {
            "category":"Government",
            "subcategory":"Office",
            "type":"Public Place"
        }
    ],
    "sg:phone":"+1 903 838 8574",
    "sg:postcode":"75501",
    "sg:province":"TX",
    "sg:tags":[
        "state",
        "program"
    ],
    "wof:name":"Transportation Dept",
    "wof:placetype":"venue"
},
  "geometry": {"coordinates":[-94.096284,33.443667],"type":"Point"}
}