{
  "type": "Feature",
  "properties": {
    "iso:country":"US",
    "sg:address":"2900 Ports O Call Ct",
    "sg:city":"Plano",
    "sg:classifiers":[
        {
            "category":"Social Services",
            "subcategory":"Adult Care",
            "type":"Services"
        }
    ],
    "sg:phone":"+1 972 867 4159",
    "sg:postcode":"75075",
    "sg:province":"TX",
    "sg:tags":[
        "home",
        "group"
    ],
    "wof:name":"Rescare",
    "wof:placetype":"venue"
},
  "geometry": {"coordinates":[-96.727498,33.03749],"type":"Point"}
}