{
  "type": "Feature",
  "properties": {
    "iso:country":"US",
    "sg:address":"1507 Waco Trce",
    "sg:city":"Harker Heights",
    "sg:classifiers":[
        {
            "category":"Manufacturing",
            "subcategory":"Toys & Sporting Goods",
            "type":"Manufacturing & Wholesale Goods"
        }
    ],
    "sg:phone":"+1 254 698 6996",
    "sg:postcode":"76548",
    "sg:province":"TX",
    "sg:tags":[
        "mfg"
    ],
    "wof:name":"Premier Woodcrafts",
    "wof:placetype":"venue"
},
  "geometry": {"coordinates":[-97.63729499999999,31.069041],"type":"Point"}
}