{
  "type": "Feature",
  "properties": {
    "iso:country":"US",
    "sg:address":"2206 Stafford Dr",
    "sg:city":"Arlington",
    "sg:classifiers":[
        {
            "category":"Professional",
            "subcategory":"Engineering",
            "type":"Services"
        }
    ],
    "sg:phone":"+1 817 460 6777",
    "sg:postcode":"76012",
    "sg:province":"TX",
    "sg:tags":[
        "consulting"
    ],
    "wof:name":"Femgineering",
    "wof:placetype":"venue"
},
  "geometry": {"coordinates":[-97.115391,32.771059],"type":"Point"}
}