{
  "type": "Feature",
  "properties": {
    "iso:country":"US",
    "sg:address":"533 N Alamo Rd",
    "sg:city":"Alamo",
    "sg:classifiers":[
        {
            "category":"Banks & Credit Unions",
            "subcategory":"Bank",
            "type":"Services"
        }
    ],
    "sg:phone":"+1 956 781 2471",
    "sg:postcode":"78541",
    "sg:province":"TX",
    "sg:website":"www.alamobank.com",
    "wof:name":"Alamo Bank Of Texas",
    "wof:placetype":"venue"
},
  "geometry": {"coordinates":[-98.10642900000001,26.292685],"type":"Point"}
}