{
  "type": "Feature",
  "properties": {
    "iso:country":"US",
    "sg:address":"5500 Greenville Ave",
    "sg:city":"Dallas",
    "sg:classifiers":[
        {
            "category":"Shopping",
            "subcategory":"Photographic Equipment",
            "type":"Retail Goods"
        }
    ],
    "sg:phone":"+1 214 691 3430",
    "sg:postcode":"75206",
    "sg:province":"TX",
    "sg:tags":[
        "camera",
        "film",
        "provides",
        "supply"
    ],
    "wof:name":"Wolf Camera and Video",
    "wof:placetype":"venue"
},
  "geometry": {"coordinates":[-96.76973700000001,32.85148],"type":"Point"}
}