{
  "type": "Feature",
  "properties": {
    "iso:country":"US",
    "sg:address":"3602 N Mccoll Rd",
    "sg:city":"Mcallen",
    "sg:classifiers":[
        {
            "category":"Health Services",
            "subcategory":"Medical Lab",
            "type":"Services"
        },
        {
            "category":"Insurance",
            "subcategory":"Hazard Insurance",
            "type":"Services"
        }
    ],
    "sg:phone":"+1 956 630 1169",
    "sg:postcode":"78501",
    "sg:province":"TX",
    "sg:tags":[
        "examination",
        "commercial",
        "business"
    ],
    "wof:name":"Imsi Exam One",
    "wof:placetype":"venue"
},
  "geometry": {"coordinates":[-98.20725899999999,26.233982],"type":"Point"}
}