{
  "type": "Feature",
  "properties": {
    "iso:country":"US",
    "sg:address":"1958 Co Rd Aa",
    "sg:city":"White Deer",
    "sg:classifiers":[
        {
            "category":"Farming",
            "subcategory":"Farm",
            "type":"Manufacturing & Wholesale Goods"
        }
    ],
    "sg:phone":"+1 806 883 6151",
    "sg:postcode":"79072",
    "sg:province":"TX",
    "wof:name":"Kotara Farms Inc",
    "wof:placetype":"venue"
},
  "geometry": {"coordinates":[-101.64432100000001,34.041597],"type":"Point"}
}