{
  "type": "Feature",
  "properties": {
    "iso:country":"US",
    "sg:address":"524 S Church St",
    "sg:city":"Paris",
    "sg:classifiers":[
        {
            "category":"Manufacturing",
            "subcategory":"Wood Products",
            "type":"Manufacturing & Wholesale Goods"
        }
    ],
    "sg:phone":"+1 903 784 3460",
    "sg:postcode":"75460",
    "sg:province":"TX",
    "sg:tags":[
        "preserving"
    ],
    "wof:name":"Preserving Historic Properties",
    "wof:placetype":"venue"
},
  "geometry": {"coordinates":[-95.554625,33.656883],"type":"Point"}
}