{
  "type": "Feature",
  "properties": {
    "iso:country":"US",
    "sg:address":"810 Lantana Ln",
    "sg:city":"Leander",
    "sg:classifiers":[
        {
            "category":"Professional",
            "type":"Services"
        }
    ],
    "sg:phone":"+1 512 528 1227",
    "sg:postcode":"78641",
    "sg:province":"TX",
    "wof:name":"Tessies Chores",
    "wof:placetype":"venue"
},
  "geometry": {"coordinates":[-97.861074,30.563071],"type":"Point"}
}