{
  "type": "Feature",
  "properties": {
    "iso:country":"US",
    "sg:address":"1401 S Ackard St",
    "sg:city":"Dallas",
    "sg:classifiers":[
        {
            "category":"Shopping",
            "subcategory":"Bicycles & Sporting Goods",
            "type":"Retail Goods"
        }
    ],
    "sg:phone":"+1 214 596 8420",
    "sg:postcode":"75205",
    "sg:province":"TX",
    "sg:tags":[
        "bike"
    ],
    "sg:website":"www.fleetwoodskitkat.com/",
    "wof:name":"Fleetwood's Kit Kat",
    "wof:placetype":"venue"
},
  "geometry": {"coordinates":[-96.784952,32.739682],"type":"Point"}
}