{
  "type": "Feature",
  "properties": {
    "iso:country":"US",
    "sg:address":"5625 E Rosedale St",
    "sg:city":"Fort Worth",
    "sg:classifiers":[
        {
            "category":"Shopping",
            "subcategory":"Stationery & Office Supplies",
            "type":"Retail Goods"
        }
    ],
    "sg:phone":"+1 817 654 1985",
    "sg:postcode":"76105",
    "sg:province":"TX",
    "sg:tags":[
        "equipment",
        "filing",
        "system"
    ],
    "wof:name":"ISC Labels & Equipment",
    "wof:placetype":"venue"
},
  "geometry": {"coordinates":[-97.234331,32.729898],"type":"Point"}
}