{
  "type": "Feature",
  "properties": {
    "iso:country":"US",
    "sg:address":"1405 S Main St",
    "sg:city":"Weatherford",
    "sg:classifiers":[
        {
            "category":"Retail",
            "subcategory":"Auto Repair",
            "type":"Services"
        }
    ],
    "sg:phone":"+1 817 598 0390",
    "sg:postcode":"76086",
    "sg:province":"TX",
    "sg:tags":[
        "automobile",
        "inspection",
        "automotive"
    ],
    "wof:name":"4 A Quicker Sticker",
    "wof:placetype":"venue"
},
  "geometry": {"coordinates":[-97.797567,32.742331],"type":"Point"}
}