{
  "type": "Feature",
  "properties": {
    "iso:country":"US",
    "sg:address":"1346 Westgreen Blvd",
    "sg:city":"Katy",
    "sg:classifiers":[
        {
            "category":"Professional",
            "subcategory":"Business Services",
            "type":"Services"
        }
    ],
    "sg:phone":"+1 281 492 6964",
    "sg:postcode":"77450",
    "sg:province":"TX",
    "wof:name":"Richeda Enterprises Inc",
    "wof:placetype":"venue"
},
  "geometry": {"coordinates":[-95.73496299999999,29.765191],"type":"Point"}
}