{
  "type": "Feature",
  "properties": {
    "iso:country":"US",
    "sg:address":"7202 Foxwick Ln",
    "sg:city":"Humble",
    "sg:classifiers":[
        {
            "category":"Professional",
            "type":"Services"
        }
    ],
    "sg:phone":"+1 281 446 1834",
    "sg:postcode":"77338",
    "sg:province":"TX",
    "wof:name":"Water Reclamation Inc",
    "wof:placetype":"venue"
},
  "geometry": {"coordinates":[-95.315651,30.012648],"type":"Point"}
}