{
  "type": "Feature",
  "properties": {
    "iso:country":"US",
    "sg:address":"140 Cypress Station Dr",
    "sg:city":"Houston",
    "sg:classifiers":[
        {
            "category":"Travel",
            "subcategory":"Travel Agent",
            "type":"Entertainment"
        }
    ],
    "sg:phone":"+1 281 586 6710",
    "sg:postcode":"77090",
    "sg:province":"TX",
    "sg:tags":[
        "agency"
    ],
    "wof:name":"American Express",
    "wof:placetype":"venue"
},
  "geometry": {"coordinates":[-95.430046,30.03268],"type":"Point"}
}