{
  "type": "Feature",
  "properties": {
    "iso:country":"US",
    "sg:address":"1327 Woodbrook Ln",
    "sg:city":"Southlake",
    "sg:classifiers":[
        {
            "category":"Freight",
            "type":"Transportation"
        }
    ],
    "sg:phone":"+1 817 691 8355",
    "sg:postcode":"76092",
    "sg:province":"TX",
    "sg:tags":[
        "operator",
        "local",
        "trucking"
    ],
    "wof:name":"Randy Eagan",
    "wof:placetype":"venue"
},
  "geometry": {"coordinates":[-97.173169,32.95471],"type":"Point"}
}