{
  "type": "Feature",
  "properties": {
    "iso:country":"US",
    "sg:address":"3102 FM 346 E",
    "sg:city":"Tyler",
    "sg:classifiers":[
        {
            "category":"Professional",
            "type":"Services"
        }
    ],
    "sg:phone":"+1 903 839 8778",
    "sg:postcode":"75703",
    "sg:province":"TX",
    "wof:name":"Edges Inc",
    "wof:placetype":"venue"
},
  "geometry": {"coordinates":[-95.294597,32.208894],"type":"Point"}
}