{
  "type": "Feature",
  "properties": {
    "iso:country":"US",
    "sg:address":"1020 Vermont St",
    "sg:city":"Wichita Falls",
    "sg:classifiers":[
        {
            "category":"Manufacturing",
            "subcategory":"Metals",
            "type":"Manufacturing & Wholesale Goods"
        }
    ],
    "sg:phone":"+1 940 322 9611",
    "sg:postcode":"76306",
    "sg:province":"TX",
    "wof:name":"Wichita Metal Products",
    "wof:placetype":"venue"
},
  "geometry": {"coordinates":[-98.511977,33.926242],"type":"Point"}
}