{
  "type": "Feature",
  "properties": {
    "iso:country":"US",
    "sg:address":"8502 Village Dr",
    "sg:city":"San Antonio",
    "sg:classifiers":[
        {
            "category":"Health Services",
            "subcategory":"Doctor",
            "type":"Services"
        }
    ],
    "sg:phone":"+1 210 653 7474",
    "sg:postcode":"78217",
    "sg:province":"TX",
    "sg:tags":[
        "dental",
        "dentist"
    ],
    "sg:website":"www.monarchdental.com",
    "wof:name":"Monarch Dental Associates Inc",
    "wof:placetype":"venue"
},
  "geometry": {"coordinates":[-98.427387,29.519511],"type":"Point"}
}