{
  "type": "Feature",
  "properties": {
    "iso:country":"US",
    "sg:address":"50 Cypress Ct",
    "sg:city":"Clute",
    "sg:classifiers":[
        {
            "category":"Real Estate",
            "subcategory":"Real Estate Agent",
            "type":"Services"
        }
    ],
    "sg:phone":"+1 979 266 8902",
    "sg:postcode":"77531",
    "sg:province":"TX",
    "wof:name":"Insync Real Estate Group Inc",
    "wof:placetype":"venue"
},
  "geometry": {"coordinates":[-95.40563,29.052608],"type":"Point"}
}