{
  "type": "Feature",
  "properties": {
    "iso:country":"US",
    "sg:address":"7656 Bellfort St",
    "sg:city":"Houston",
    "sg:classifiers":[
        {
            "category":"Restaurant",
            "type":"Food & Drink"
        }
    ],
    "sg:phone":"+1 713 640 1654",
    "sg:postcode":"77061",
    "sg:province":"TX",
    "sg:tags":[
        "chinese"
    ],
    "sg:website":"www.shan-hu.com/",
    "wof:name":"Shan Hu Chinese Restaurant",
    "wof:placetype":"venue"
},
  "geometry": {"coordinates":[-95.28209699999999,29.6721],"type":"Point"}
}