{
  "type": "Feature",
  "properties": {
    "iso:country":"US",
    "sg:address":"1301 E Collins Blvd",
    "sg:city":"Richardson",
    "sg:classifiers":[
        {
            "category":"Insurance",
            "subcategory":"Hazard Insurance",
            "type":"Services"
        }
    ],
    "sg:phone":"+1 214 570 6000",
    "sg:postcode":"75081",
    "sg:province":"TX",
    "wof:name":"Travelers Property Casualty Ins",
    "wof:placetype":"venue"
},
  "geometry": {"coordinates":[-96.70219400000001,32.967994],"type":"Point"}
}