{
  "type": "Feature",
  "properties": {
    "iso:country":"US",
    "sg:address":"10801 Spring Cypress Rd",
    "sg:city":"Houston",
    "sg:classifiers":[
        {
            "category":"Real Estate",
            "subcategory":"Real Estate Agent",
            "type":"Services"
        }
    ],
    "sg:phone":"+1 281 376 7595",
    "sg:postcode":"77070",
    "sg:province":"TX",
    "sg:tags":[
        "inspection"
    ],
    "wof:name":"Construction Analyst & Assoc",
    "wof:placetype":"venue"
},
  "geometry": {"coordinates":[-95.577533,30.01523],"type":"Point"}
}