{
  "type": "Feature",
  "properties": {
    "iso:country":"US",
    "sg:address":"11238 Jadestone Blvd",
    "sg:city":"San Antonio",
    "sg:classifiers":[
        {
            "category":"Professional",
            "subcategory":"Detective & Security Services",
            "type":"Services"
        }
    ],
    "sg:phone":"+1 210 561 0012",
    "sg:postcode":"78249",
    "sg:province":"TX",
    "sg:tags":[
        "car",
        "investigator"
    ],
    "wof:name":"Tony Cantu & Assoc",
    "wof:placetype":"venue"
},
  "geometry": {"coordinates":[-98.609728,29.546447],"type":"Point"}
}