{
  "type": "Feature",
  "properties": {
    "iso:country":"US",
    "sg:address":"10609 W Cleburne Rd",
    "sg:city":"Crowley",
    "sg:classifiers":[
        {
            "category":"Shopping",
            "subcategory":"Clothing, Apparel, & Fashions",
            "type":"Retail Goods"
        }
    ],
    "sg:phone":"+1 817 263 8240",
    "sg:postcode":"76036",
    "sg:province":"TX",
    "wof:name":"Bernies Boutique",
    "wof:placetype":"venue"
},
  "geometry": {"coordinates":[-97.410185,32.586935],"type":"Point"}
}