{
  "type": "Feature",
  "properties": {
    "iso:country":"US",
    "sg:address":"6041 Winsome Ln",
    "sg:city":"Houston",
    "sg:classifiers":[
        {
            "category":"Professional",
            "type":"Services"
        }
    ],
    "sg:phone":"+1 713 339 2752",
    "sg:postcode":"77057",
    "sg:province":"TX",
    "wof:name":"Cubed Element",
    "wof:placetype":"venue"
},
  "geometry": {"coordinates":[-95.48735600000001,29.7353],"type":"Point"}
}