{
  "type": "Feature",
  "properties": {
    "iso:country":"US",
    "sg:address":"16840 Barker Springs Rd",
    "sg:city":"Houston",
    "sg:classifiers":[
        {
            "category":"Professional",
            "subcategory":"Engineering",
            "type":"Services"
        },
        {
            "category":"Wholesale",
            "subcategory":"Electrical",
            "type":"Manufacturing & Wholesale Goods"
        }
    ],
    "sg:phone":"+1 281 398 1100",
    "sg:postcode":"77084",
    "sg:province":"TX",
    "sg:tags":[
        "process",
        "control",
        "industrial",
        "automation"
    ],
    "sg:website":"www.control-lab.com",
    "wof:name":"Intech Process Automation Inc",
    "wof:placetype":"venue"
},
  "geometry": {"coordinates":[-95.675325,29.785683],"type":"Point"}
}