{
  "type": "Feature",
  "properties": {
    "iso:country":"US",
    "sg:address":"5981 Temple Dr",
    "sg:city":"Plano",
    "sg:classifiers":[
        {
            "category":"Banks & Credit Unions",
            "subcategory":"Bank",
            "type":"Services"
        }
    ],
    "sg:phone":"+1 972 403 9484",
    "sg:postcode":"75093",
    "sg:province":"TX",
    "sg:tags":[
        "loan",
        "real estate"
    ],
    "wof:name":"Mira Vista Mortgage",
    "wof:placetype":"venue"
},
  "geometry": {"coordinates":[-96.82547700000001,33.037318],"type":"Point"}
}