{
  "type": "Feature",
  "properties": {
    "iso:country":"US",
    "sg:address":"5601 Brodie Ln",
    "sg:city":"Austin",
    "sg:classifiers":[
        {
            "category":"Personal",
            "subcategory":"Barber",
            "type":"Services"
        }
    ],
    "sg:phone":"+1 512 892 5550",
    "sg:postcode":"78745",
    "sg:province":"TX",
    "sg:website":"www.floydsbarbershops.com",
    "wof:name":"Floyd's 99 Barbershop",
    "wof:placetype":"venue"
},
  "geometry": {"coordinates":[-97.82151,30.226863],"type":"Point"}
}