{
  "type": "Feature",
  "properties": {
    "iso:country":"US",
    "sg:address":"1050 Co Rd 202",
    "sg:city":"Liberty Hill",
    "sg:classifiers":[
        {
            "category":"Farming",
            "subcategory":"Livestock Farm",
            "type":"Manufacturing & Wholesale Goods"
        }
    ],
    "sg:phone":"+1 512 515 6680",
    "sg:postcode":"78642",
    "sg:province":"TX",
    "sg:tags":[
        "ranch"
    ],
    "wof:name":"Stoney River Ranch",
    "wof:placetype":"venue"
},
  "geometry": {"coordinates":[-97.912313,30.736305],"type":"Point"}
}