{
  "type": "Feature",
  "properties": {
    "iso:country":"US",
    "sg:address":"6014 Caldwell St",
    "sg:city":"Waco",
    "sg:classifiers":[
        {
            "category":"Wholesale",
            "subcategory":"Painting Supplies",
            "type":"Manufacturing & Wholesale Goods"
        }
    ],
    "sg:phone":"+1 254 537 2404",
    "sg:postcode":"76710",
    "sg:province":"TX",
    "sg:tags":[
        "paint-wholesale",
        "manufacturer"
    ],
    "wof:name":"Simon Rodriguez Paint Com",
    "wof:placetype":"venue"
},
  "geometry": {"coordinates":[-97.202985,31.536713],"type":"Point"}
}