{
  "type": "Feature",
  "properties": {
    "iso:country":"US",
    "sg:address":"15707 Autumnbrook Dr",
    "sg:city":"Houston",
    "sg:classifiers":[
        {
            "category":"Retail",
            "subcategory":"Auto Repair",
            "type":"Services"
        }
    ],
    "sg:phone":"+1 281 444 4508",
    "sg:postcode":"77068",
    "sg:province":"TX",
    "sg:tags":[
        "automotive"
    ],
    "wof:name":"T F Stem & Co",
    "wof:placetype":"venue"
},
  "geometry": {"coordinates":[-95.495065,30.008751],"type":"Point"}
}