{
  "type": "Feature",
  "properties": {
    "iso:country":"US",
    "sg:address":"12920 Midway Rd",
    "sg:city":"Dallas",
    "sg:classifiers":[
        {
            "category":"Shopping",
            "subcategory":"Used Merchandise",
            "type":"Retail Goods"
        }
    ],
    "sg:phone":"+1 972 239 3711",
    "sg:postcode":"75244",
    "sg:province":"TX",
    "wof:name":"American Pawn Superstore",
    "wof:placetype":"venue"
},
  "geometry": {"coordinates":[-96.838622,32.925247],"type":"Point"}
}