{
  "type": "Feature",
  "properties": {
    "iso:country":"US",
    "sg:address":"25025 I- 45",
    "sg:city":"Spring",
    "sg:classifiers":[
        {
            "category":"Professional",
            "subcategory":"Lawyer & Legal Services",
            "type":"Services"
        }
    ],
    "sg:phone":"+1 281 364 7261",
    "sg:postcode":"77380",
    "sg:province":"TX",
    "wof:name":"Starzyk & Associates PC",
    "wof:placetype":"venue"
},
  "geometry": {"coordinates":[-95.443252,30.124603],"type":"Point"}
}