{
  "type": "Feature",
  "properties": {
    "iso:country":"US",
    "sg:address":"409 W Brookside Dr",
    "sg:city":"Bryan",
    "sg:classifiers":[
        {
            "category":"Retail",
            "subcategory":"Portrait Studio",
            "type":"Services"
        }
    ],
    "sg:phone":"+1 979 268 0387",
    "sg:postcode":"77801",
    "sg:province":"TX",
    "sg:tags":[
        "photo"
    ],
    "wof:name":"Templin Photography",
    "wof:placetype":"venue"
},
  "geometry": {"coordinates":[-96.354857,30.62794],"type":"Point"}
}