{
  "type": "Feature",
  "properties": {
    "iso:country":"US",
    "sg:address":"2817 Charter Oak Dr",
    "sg:city":"Plano",
    "sg:classifiers":[
        {
            "category":"Freight",
            "type":"Transportation"
        }
    ],
    "sg:phone":"+1 972 422 0913",
    "sg:postcode":"75074",
    "sg:province":"TX",
    "sg:tags":[
        "operator",
        "local",
        "trucking"
    ],
    "wof:name":"Hot Shots Delivery & Moving",
    "wof:placetype":"venue"
},
  "geometry": {"coordinates":[-96.676785,33.03821],"type":"Point"}
}