{
  "type": "Feature",
  "properties": {
    "iso:country":"US",
    "sg:address":"203 Hurst St",
    "sg:city":"Center",
    "sg:classifiers":[
        {
            "category":"Banks & Credit Unions",
            "subcategory":"Bank",
            "type":"Services"
        }
    ],
    "sg:phone":"+1 936 598 8212",
    "sg:postcode":"75935",
    "sg:province":"TX",
    "sg:tags":[
        "institution",
        "business"
    ],
    "wof:name":"Heritage Land Bank",
    "wof:placetype":"venue"
},
  "geometry": {"coordinates":[-94.18779000000001,31.791856],"type":"Point"}
}