{
  "type": "Feature",
  "properties": {
    "iso:country":"US",
    "sg:address":"121 N 2nd St",
    "sg:city":"Killeen",
    "sg:classifiers":[
        {
            "category":"Retail",
            "subcategory":"Animal Services",
            "type":"Services"
        }
    ],
    "sg:phone":"+1 254 526 3135",
    "sg:postcode":"76541",
    "sg:province":"TX",
    "wof:name":"Misty Winds All Breed Gr",
    "wof:placetype":"venue"
},
  "geometry": {"coordinates":[-97.730915,31.118483],"type":"Point"}
}