{
  "type": "Feature",
  "properties": {
    "iso:country":"US",
    "sg:address":"1715 E Lake Dr",
    "sg:city":"Weatherford",
    "sg:classifiers":[
        {
            "category":"Professional",
            "type":"Services"
        }
    ],
    "sg:phone":"+1 817 598 5914",
    "sg:postcode":"76087",
    "sg:province":"TX",
    "wof:name":"Danny & Tanet Deel",
    "wof:placetype":"venue"
},
  "geometry": {"coordinates":[-97.68570099999999,32.785643],"type":"Point"}
}