{
  "type": "Feature",
  "properties": {
    "iso:country":"US",
    "sg:address":"201 Connally St",
    "sg:city":"Sulphur Springs",
    "sg:classifiers":[
        {
            "category":"Banks & Credit Unions",
            "subcategory":"Bank",
            "type":"Services"
        }
    ],
    "sg:phone":"+1 903 885 7523",
    "sg:postcode":"75482",
    "sg:province":"TX",
    "sg:website":"www.bankatcnb.com",
    "wof:name":"City National Bank",
    "wof:placetype":"venue"
},
  "geometry": {"coordinates":[-95.602417,33.138366],"type":"Point"}
}