{
  "type": "Feature",
  "properties": {
    "iso:country":"US",
    "sg:address":"4026 Norfolk St",
    "sg:city":"Houston",
    "sg:classifiers":[
        {
            "category":"Professional",
            "type":"Services"
        }
    ],
    "sg:phone":"+1 713 660 6162",
    "sg:postcode":"77027",
    "sg:province":"TX",
    "wof:name":"I D Hub",
    "wof:placetype":"venue"
},
  "geometry": {"coordinates":[-95.443816,29.730755],"type":"Point"}
}