{
  "type": "Feature",
  "properties": {
    "iso:country":"US",
    "sg:address":"1900 Co Rd 2293",
    "sg:city":"Quinlan",
    "sg:classifiers":[
        {
            "category":"Organizations",
            "subcategory":"Religious Organization",
            "type":"Services"
        }
    ],
    "sg:phone":"+1 903 883 5264",
    "sg:postcode":"75474",
    "sg:province":"TX",
    "wof:name":"Literature Ministries Intl",
    "wof:placetype":"venue"
},
  "geometry": {"coordinates":[-96.172844,32.978831],"type":"Point"}
}