{
  "type": "Feature",
  "properties": {
    "iso:country":"US",
    "sg:address":"6700 Woodlands Pkwy",
    "sg:city":"Spring",
    "sg:classifiers":[
        {
            "category":"Organizations",
            "subcategory":"Community Association",
            "type":"Services"
        }
    ],
    "sg:phone":"+1 832 515 0120",
    "sg:postcode":"77382",
    "sg:province":"TX",
    "sg:tags":[
        "membership"
    ],
    "wof:name":"Transform Earth Foundation",
    "wof:placetype":"venue"
},
  "geometry": {"coordinates":[-95.54136,30.181866],"type":"Point"}
}