{
  "type": "Feature",
  "properties": {
    "iso:country":"US",
    "sg:address":"1101 W 1st St",
    "sg:city":"Hereford",
    "sg:classifiers":[
        {
            "category":"Retail",
            "subcategory":"Auto Repair",
            "type":"Services"
        }
    ],
    "sg:phone":"+1 806 364 7714",
    "sg:postcode":"79045",
    "sg:province":"TX",
    "sg:tags":[
        "truck"
    ],
    "wof:name":"Mechanical Techniques",
    "wof:placetype":"venue"
},
  "geometry": {"coordinates":[-102.410943,34.808699],"type":"Point"}
}