{
  "type": "Feature",
  "properties": {
    "iso:country":"US",
    "sg:address":"8630 Hemlock Hill Dr",
    "sg:city":"Houston",
    "sg:classifiers":[
        {
            "category":"Health Services",
            "subcategory":"Clinic",
            "type":"Services"
        }
    ],
    "sg:phone":"+1 281 564 5984",
    "sg:postcode":"77083",
    "sg:province":"TX",
    "wof:name":"Kina Medical & Equipment Suppl",
    "wof:placetype":"venue"
},
  "geometry": {"coordinates":[-95.62712399999999,29.684804],"type":"Point"}
}