{
  "type": "Feature",
  "properties": {
    "iso:country":"US",
    "sg:address":"6998 S Zarzamora",
    "sg:city":"San Antonio",
    "sg:classifiers":[
        {
            "category":"Banks & Credit Unions",
            "subcategory":"Bank",
            "type":"Services"
        }
    ],
    "sg:phone":"+1 210 923 3999",
    "sg:postcode":"78224",
    "sg:province":"TX",
    "sg:tags":[
        "depository",
        "banking"
    ],
    "wof:name":"ACE Cash Express",
    "wof:placetype":"venue"
},
  "geometry": {"coordinates":[-98.534037,29.357955],"type":"Point"}
}