{
  "type": "Feature",
  "properties": {
    "iso:country":"US",
    "sg:address":"901 SE 12th St",
    "sg:city":"Mineral Wells",
    "sg:classifiers":[
        {
            "category":"Professional",
            "subcategory":"Business Services",
            "type":"Services"
        }
    ],
    "sg:phone":"+1 940 325 0144",
    "sg:postcode":"76067",
    "sg:province":"TX",
    "wof:name":"Della Santibanez",
    "wof:placetype":"venue"
},
  "geometry": {"coordinates":[-98.106493,32.799271],"type":"Point"}
}