{
  "type": "Feature",
  "properties": {
    "iso:country":"US",
    "sg:address":"113 W Shandon Ave",
    "sg:city":"Midland",
    "sg:classifiers":[
        {
            "category":"Organizations",
            "subcategory":"Religious Organization",
            "type":"Services"
        }
    ],
    "sg:phone":"+1 432 684 4786",
    "sg:postcode":"79705",
    "sg:province":"TX",
    "wof:name":"Lee St Church Christ",
    "wof:placetype":"venue"
},
  "geometry": {"coordinates":[-102.083077,32.028301],"type":"Point"}
}