{
  "type": "Feature",
  "properties": {
    "iso:country":"US",
    "sg:address":"16404 San Pedro Ave",
    "sg:city":"San Antonio",
    "sg:classifiers":[
        {
            "category":"Travel",
            "subcategory":"Travel Agent",
            "type":"Entertainment"
        }
    ],
    "sg:phone":"+1 210 490 2400",
    "sg:postcode":"78232",
    "sg:province":"TX",
    "sg:tags":[
        "passenger",
        "agency",
        "transportation",
        "sea",
        "deep"
    ],
    "wof:name":"Aj Travel Inc",
    "wof:placetype":"venue"
},
  "geometry": {"coordinates":[-98.473344,29.5922],"type":"Point"}
}