{
  "type": "Feature",
  "properties": {
    "iso:country":"US",
    "sg:address":"1209 E Belknap St",
    "sg:city":"Fort Worth",
    "sg:classifiers":[
        {
            "category":"Professional",
            "subcategory":"Lawyer & Legal Services",
            "type":"Services"
        }
    ],
    "sg:phone":"+1 817 877 5995",
    "sg:postcode":"76102",
    "sg:province":"TX",
    "sg:tags":[
        "attorney"
    ],
    "wof:name":"Dale O'Neal",
    "wof:placetype":"venue"
},
  "geometry": {"coordinates":[-97.32454799999999,32.762126],"type":"Point"}
}