{
  "type": "Feature",
  "properties": {
    "iso:country":"US",
    "sg:address":"8400 Lamount Dr",
    "sg:city":"Amarillo",
    "sg:classifiers":[
        {
            "category":"Organizations",
            "subcategory":"Religious Organization",
            "type":"Services"
        }
    ],
    "sg:phone":"+1 806 353 5301",
    "sg:postcode":"79110",
    "sg:province":"TX",
    "wof:name":"Lamount Drive Baptist Church",
    "wof:placetype":"venue"
},
  "geometry": {"coordinates":[-101.89273900000001,35.120923],"type":"Point"}
}