{
  "type": "Feature",
  "properties": {
    "iso:country":"US",
    "sg:address":"518 Pecan Acres Ct",
    "sg:city":"Arlington",
    "sg:classifiers":[
        {
            "category":"Professional",
            "subcategory":"Computer Services",
            "type":"Services"
        }
    ],
    "sg:phone":"+1 817 654 5896",
    "sg:postcode":"76013",
    "sg:province":"TX",
    "wof:name":"P C Maintain",
    "wof:placetype":"venue"
},
  "geometry": {"coordinates":[-97.14300299999999,32.731214],"type":"Point"}
}