{
  "type": "Feature",
  "properties": {
    "iso:country":"US",
    "sg:address":"2535 Preston Ave",
    "sg:city":"Pasadena",
    "sg:classifiers":[
        {
            "category":"Building & Trades",
            "subcategory":"Construction",
            "type":"Services"
        }
    ],
    "sg:phone":"+1 281 487 3761",
    "sg:postcode":"77503",
    "sg:province":"TX",
    "sg:tags":[
        "installs",
        "tile",
        "floor",
        "covering"
    ],
    "wof:name":"Home Shade & Floor Covering",
    "wof:placetype":"venue"
},
  "geometry": {"coordinates":[-95.172326,29.673902],"type":"Point"}
}