{
  "type": "Feature",
  "properties": {
    "iso:country":"US",
    "sg:address":"2520 Stehle Rd",
    "sg:city":"Rosenberg",
    "sg:classifiers":[
        {
            "category":"Wholesale",
            "subcategory":"Hardware",
            "type":"Manufacturing & Wholesale Goods"
        }
    ],
    "sg:phone":"+1 281 341 0475",
    "sg:postcode":"77471",
    "sg:province":"TX",
    "wof:name":"Beechler Air Conditioning",
    "wof:placetype":"venue"
},
  "geometry": {"coordinates":[-95.841103,29.510887],"type":"Point"}
}