{
  "type": "Feature",
  "properties": {
    "iso:country":"US",
    "sg:address":"2815 Kings Crossing Dr",
    "sg:city":"Humble",
    "sg:classifiers":[
        {
            "category":"Professional",
            "type":"Services"
        }
    ],
    "sg:phone":"+1 281 361 5127",
    "sg:postcode":"77345",
    "sg:province":"TX",
    "sg:tags":[
        "establishment"
    ],
    "wof:name":"Community Access Management",
    "wof:placetype":"venue"
},
  "geometry": {"coordinates":[-95.18104200000001,30.045987],"type":"Point"}
}