{
  "type": "Feature",
  "properties": {
    "iso:country":"US",
    "sg:address":"21226 Park Run Dr",
    "sg:city":"Katy",
    "sg:classifiers":[
        {
            "category":"Building & Trades",
            "subcategory":"Construction",
            "type":"Services"
        }
    ],
    "sg:phone":"+1 281 599 7043",
    "sg:postcode":"77450",
    "sg:province":"TX",
    "sg:tags":[
        "floor",
        "laying",
        "contractor"
    ],
    "wof:name":"Advanced Hardwood Floors",
    "wof:placetype":"venue"
},
  "geometry": {"coordinates":[-95.735438,29.760478],"type":"Point"}
}