{
  "type": "Feature",
  "properties": {
    "iso:country":"US",
    "sg:address":"402 N Timberland Dr",
    "sg:city":"Lufkin",
    "sg:classifiers":[
        {
            "category":"Banks & Credit Unions",
            "subcategory":"Bank",
            "type":"Services"
        }
    ],
    "sg:phone":"+1 936 632 8666",
    "sg:postcode":"75901",
    "sg:province":"TX",
    "sg:tags":[
        "personal",
        "institution"
    ],
    "wof:name":"World Acceptance",
    "wof:placetype":"venue"
},
  "geometry": {"coordinates":[-94.71794199999999,31.34183],"type":"Point"}
}