{
  "type": "Feature",
  "properties": {
    "iso:country":"US",
    "sg:address":"1201 Main St",
    "sg:city":"Blanco",
    "sg:classifiers":[
        {
            "category":"Restaurant",
            "type":"Food & Drink"
        }
    ],
    "sg:phone":"+1 830 833 4645",
    "sg:postcode":"78606",
    "sg:province":"TX",
    "sg:tags":[
        "mexican"
    ],
    "wof:name":"Little Mexican Restaurant",
    "wof:placetype":"venue"
},
  "geometry": {"coordinates":[-98.41928900000001,30.10487],"type":"Point"}
}