{
  "type": "Feature",
  "properties": {
    "iso:country":"US",
    "sg:address":"1206 W 20th St",
    "sg:city":"Houston",
    "sg:classifiers":[
        {
            "category":"Bars & Pubs",
            "type":"Food & Drink"
        }
    ],
    "sg:phone":"+1 713 869 7000",
    "sg:postcode":"77008",
    "sg:province":"TX",
    "sg:tags":[
        "drinking",
        "diva"
    ],
    "wof:name":"Shady Tavern",
    "wof:placetype":"venue"
},
  "geometry": {"coordinates":[-95.420601,29.803801],"type":"Point"}
}