{
  "type": "Feature",
  "properties": {
    "iso:country":"US",
    "sg:address":"1506 Linda Ln",
    "sg:city":"Weatherford",
    "sg:classifiers":[
        {
            "category":"Wholesale",
            "subcategory":"Vending Machines",
            "type":"Manufacturing & Wholesale Goods"
        }
    ],
    "sg:phone":"+1 817 596 8546",
    "sg:postcode":"76087",
    "sg:province":"TX",
    "sg:tags":[
        "operator"
    ],
    "wof:name":"Better Vending",
    "wof:placetype":"venue"
},
  "geometry": {"coordinates":[-97.72757300000001,32.782385],"type":"Point"}
}