{
  "type": "Feature",
  "properties": {
    "iso:country":"US",
    "sg:address":"2105 SE 25th Ave",
    "sg:city":"Mineral Wells",
    "sg:classifiers":[
        {
            "category":"Social Services",
            "subcategory":"Child Care",
            "type":"Services"
        }
    ],
    "sg:phone":"+1 940 327 8840",
    "sg:postcode":"76067",
    "sg:province":"TX",
    "sg:tags":[
        "day"
    ],
    "wof:name":"Noahs Ark",
    "wof:placetype":"venue"
},
  "geometry": {"coordinates":[-98.088318,32.793706],"type":"Point"}
}