{
  "type": "Feature",
  "properties": {
    "iso:country":"US",
    "sg:address":"3601 Atlas Cove",
    "sg:city":"Austin",
    "sg:classifiers":[
        {
            "category":"Home & Garden",
            "subcategory":"Home Furnishings",
            "type":"Retail Goods"
        }
    ],
    "sg:phone":"+1 512 338 0737",
    "sg:postcode":"78730",
    "sg:province":"TX",
    "wof:name":"Coleen Brighton",
    "wof:placetype":"venue"
},
  "geometry": {"coordinates":[-97.860062,30.361749],"type":"Point"}
}