{
  "type": "Feature",
  "properties": {
    "iso:country":"US",
    "sg:address":"1109 E Seminary Dr",
    "sg:city":"Fort Worth",
    "sg:classifiers":[
        {
            "category":"Personal",
            "subcategory":"Beauty Salon",
            "type":"Services"
        }
    ],
    "sg:phone":"+1 817 923 1602",
    "sg:postcode":"76115",
    "sg:province":"TX",
    "sg:tags":[
        "shop"
    ],
    "wof:name":"G Hair Salon",
    "wof:placetype":"venue"
},
  "geometry": {"coordinates":[-97.31417399999999,32.68445],"type":"Point"}
}