{
  "type": "Feature",
  "properties": {
    "iso:country":"US",
    "sg:address":"1002 Small St",
    "sg:city":"Grand Prairie",
    "sg:classifiers":[
        {
            "category":"Professional",
            "subcategory":"Secretarial Services",
            "type":"Services"
        }
    ],
    "sg:phone":"+1 972 642 2727",
    "sg:postcode":"75050",
    "sg:province":"TX",
    "sg:tags":[
        "reporting"
    ],
    "wof:name":"Next Day Cash",
    "wof:placetype":"venue"
},
  "geometry": {"coordinates":[-96.991383,32.748845],"type":"Point"}
}