{
  "type": "Feature",
  "properties": {
    "iso:country":"US",
    "sg:address":"3808 N Shepherd Dr",
    "sg:city":"Houston",
    "sg:classifiers":[
        {
            "category":"Retail",
            "subcategory":"Laundry & Dry Cleaning",
            "type":"Services"
        }
    ],
    "sg:phone":"+1 713 692 2270",
    "sg:postcode":"77018",
    "sg:province":"TX",
    "wof:name":"Stan Cleaners",
    "wof:placetype":"venue"
},
  "geometry": {"coordinates":[-95.4104,29.821301],"type":"Point"}
}