{
  "type": "Feature",
  "properties": {
    "iso:country":"US",
    "sg:address":"2040 North Loop W Ste 102",
    "sg:city":"Houston",
    "sg:classifiers":[
        {
            "category":"Professional",
            "subcategory":"Lawyer & Legal Services",
            "type":"Services"
        }
    ],
    "sg:phone":"+1 713 880 8050",
    "sg:postcode":"77018",
    "sg:province":"TX",
    "wof:name":"Neville Michael T & Associates PC",
    "wof:placetype":"venue"
},
  "geometry": {"coordinates":[-95.436784,29.811279],"type":"Point"}
}