{
  "type": "Feature",
  "properties": {
    "iso:country":"US",
    "sg:address":"28541 Waterview Dr N",
    "sg:city":"Boerne",
    "sg:classifiers":[
        {
            "category":"Professional",
            "type":"Services"
        }
    ],
    "sg:phone":"+1 830 755 9049",
    "sg:postcode":"78006",
    "sg:province":"TX",
    "wof:name":"Hill Country Rv Service",
    "wof:placetype":"venue"
},
  "geometry": {"coordinates":[-98.672752,29.722056],"type":"Point"}
}