{
  "type": "Feature",
  "properties": {
    "iso:country":"US",
    "sg:address":"5729 Lebanon Rd",
    "sg:city":"Frisco",
    "sg:classifiers":[
        {
            "category":"Retail",
            "subcategory":"Car Wash",
            "type":"Services"
        }
    ],
    "sg:phone":"+1 214 549 3332",
    "sg:postcode":"75034",
    "sg:province":"TX",
    "wof:name":"Genter's Detailing, Inc.",
    "wof:placetype":"venue"
},
  "geometry": {"coordinates":[-96.83689099999999,33.116421],"type":"Point"}
}