{
  "type": "Feature",
  "properties": {
    "iso:country":"US",
    "sg:address":"1823 Fort View Rd",
    "sg:city":"Austin",
    "sg:classifiers":[
        {
            "category":"Social Services",
            "type":"Services"
        }
    ],
    "sg:phone":"+1 512 480 0205",
    "sg:postcode":"78704",
    "sg:province":"TX",
    "sg:tags":[
        "counselor",
        "marriage",
        "family"
    ],
    "wof:name":"Rio Grande Counseling Center",
    "wof:placetype":"venue"
},
  "geometry": {"coordinates":[-97.787502,30.230855],"type":"Point"}
}