{
  "type": "Feature",
  "properties": {
    "iso:country":"US",
    "sg:address":"1212 N Yarbrough Dr",
    "sg:city":"El Paso",
    "sg:classifiers":[
        {
            "category":"Restaurant",
            "type":"Food & Drink"
        },
        {
            "category":"Ice Cream",
            "type":"Food & Drink"
        }
    ],
    "sg:menulink":"http://www.allmenus.com/tx/el-paso/242689-baskin-robbins/menu/",
    "sg:phone":"+1 915 593 0831",
    "sg:postcode":"79925",
    "sg:province":"TX",
    "sg:tags":[
        "american",
        "ice",
        "cream"
    ],
    "wof:name":"Baskin-Robbins",
    "wof:placetype":"venue"
},
  "geometry": {"coordinates":[-106.341629,31.756878],"type":"Point"}
}