{
  "type": "Feature",
  "properties": {
    "iso:country":"US",
    "sg:address":"1846 Eastside Dr",
    "sg:city":"Wichita Falls",
    "sg:classifiers":[
        {
            "category":"Building & Trades",
            "subcategory":"Construction",
            "type":"Services"
        }
    ],
    "sg:phone":"+1 940 322 2504",
    "sg:postcode":"76301",
    "sg:province":"TX",
    "sg:tags":[
        "roofing",
        "contractor"
    ],
    "wof:name":"Menasco J Roofing Co",
    "wof:placetype":"venue"
},
  "geometry": {"coordinates":[-98.456532,33.902645],"type":"Point"}
}