{
  "type": "Feature",
  "properties": {
    "iso:country":"US",
    "sg:address":"5703 Glenmont Dr",
    "sg:city":"Houston",
    "sg:classifiers":[
        {
            "category":"Food & Beverages",
            "subcategory":"Groceries & Convenience Stores",
            "type":"Retail Goods"
        }
    ],
    "sg:phone":"+1 713 666 4296",
    "sg:postcode":"77081",
    "sg:province":"TX",
    "wof:name":"Super Mercado",
    "wof:placetype":"venue"
},
  "geometry": {"coordinates":[-95.48160900000001,29.720026],"type":"Point"}
}