{
  "type": "Feature",
  "properties": {
    "iso:country":"US",
    "sg:address":"1834 Ferguson Ln",
    "sg:city":"Austin",
    "sg:classifiers":[
        {
            "category":"Manufacturing",
            "subcategory":"Printing",
            "type":"Manufacturing & Wholesale Goods"
        }
    ],
    "sg:phone":"+1 512 451 3860",
    "sg:postcode":"78754",
    "sg:province":"TX",
    "sg:tags":[
        "printer"
    ],
    "wof:name":"Offset Press Svc",
    "wof:placetype":"venue"
},
  "geometry": {"coordinates":[-97.67147,30.344825],"type":"Point"}
}