{
  "type": "Feature",
  "properties": {
    "iso:country":"US",
    "sg:address":"10870 Alcott Dr",
    "sg:city":"Houston",
    "sg:classifiers":[
        {
            "category":"Wholesale",
            "subcategory":"Motor Vehicles",
            "type":"Manufacturing & Wholesale Goods"
        }
    ],
    "sg:phone":"+1 713 465 4606",
    "sg:postcode":"77043",
    "sg:province":"TX",
    "sg:tags":[
        "automobile"
    ],
    "wof:name":"Atlantic Motor Cars",
    "wof:placetype":"venue"
},
  "geometry": {"coordinates":[-95.568771,29.816171],"type":"Point"}
}