{
  "type": "Feature",
  "properties": {
    "iso:country":"US",
    "sg:address":"1008 E 6th Street",
    "sg:city":"Austin",
    "sg:classifiers":[
        {
            "category":"Real Estate",
            "subcategory":"Architect",
            "type":"Services"
        }
    ],
    "sg:phone":"+1 512 472 5572",
    "sg:postcode":"78702",
    "sg:province":"TX",
    "wof:name":"Kinney & Associates",
    "wof:placetype":"venue"
},
  "geometry": {"coordinates":[-97.732247,30.26488],"type":"Point"}
}