{
  "type": "Feature",
  "properties": {
    "iso:country":"US",
    "sg:address":"4950 N McColl Rd",
    "sg:city":"Mcallen",
    "sg:classifiers":[
        {
            "category":"Professional",
            "subcategory":"Management & Consulting",
            "type":"Services"
        }
    ],
    "sg:phone":"+1 956 683 0606",
    "sg:postcode":"78504",
    "sg:province":"TX",
    "wof:name":"Southwest Medical Partners",
    "wof:placetype":"venue"
},
  "geometry": {"coordinates":[-98.204688,26.248167],"type":"Point"}
}