{
  "type": "Feature",
  "properties": {
    "iso:country":"US",
    "sg:address":"1402 W North Loop Blvd",
    "sg:city":"Austin",
    "sg:classifiers":[
        {
            "category":"Social Services",
            "type":"Services"
        }
    ],
    "sg:phone":"+1 512 419 0649",
    "sg:postcode":"78756",
    "sg:province":"TX",
    "sg:tags":[
        "counselor",
        "marriage",
        "family"
    ],
    "wof:name":"Glenna Chappell",
    "wof:placetype":"venue"
},
  "geometry": {"coordinates":[-97.736994,30.324801],"type":"Point"}
}