{
  "type": "Feature",
  "properties": {
    "iso:country":"US",
    "sg:address":"20 Gus Garcia",
    "sg:city":"San Antonio",
    "sg:classifiers":[
        {
            "category":"Professional",
            "type":"Services"
        }
    ],
    "sg:phone":"+1 210 212 5787",
    "sg:postcode":"78207",
    "sg:province":"TX",
    "wof:name":"Sensational Candles",
    "wof:placetype":"venue"
},
  "geometry": {"coordinates":[-98.511484,29.416504],"type":"Point"}
}