{
  "type": "Feature",
  "properties": {
    "iso:country":"US",
    "sg:address":"1312 Flameleaf Dr",
    "sg:city":"Allen",
    "sg:classifiers":[
        {
            "category":"Professional",
            "subcategory":"Business Services",
            "type":"Services"
        }
    ],
    "sg:phone":"+1 972 727 5283",
    "sg:postcode":"75002",
    "sg:province":"TX",
    "wof:name":"Allen Commercial & Residential",
    "wof:placetype":"venue"
},
  "geometry": {"coordinates":[-96.636307,33.095942],"type":"Point"}
}