{
  "type": "Feature",
  "properties": {
    "iso:country":"US",
    "sg:address":"2919 Jackson Ave",
    "sg:city":"El Paso",
    "sg:classifiers":[
        {
            "category":"Home & Garden",
            "subcategory":"Home Furnishings",
            "type":"Retail Goods"
        }
    ],
    "sg:phone":"+1 915 565 6779",
    "sg:postcode":"79930",
    "sg:province":"TX",
    "sg:tags":[
        "utensil",
        "cooking"
    ],
    "wof:name":"Royal Gold Of Texas",
    "wof:placetype":"venue"
},
  "geometry": {"coordinates":[-106.46007,31.81061],"type":"Point"}
}