{
  "type": "Feature",
  "properties": {
    "iso:country":"US",
    "sg:address":"5235 Milwee St",
    "sg:city":"Houston",
    "sg:classifiers":[
        {
            "category":"Professional",
            "subcategory":"Advertising",
            "type":"Services"
        }
    ],
    "sg:phone":"+1 713 682 5211",
    "sg:postcode":"77092",
    "sg:province":"TX",
    "sg:tags":[
        "outdoor"
    ],
    "wof:name":"Outdoor Systems Advertising",
    "wof:placetype":"venue"
},
  "geometry": {"coordinates":[-95.46789099999999,29.822297],"type":"Point"}
}