{
  "type": "Feature",
  "properties": {
    "iso:country":"US",
    "sg:address":"10650 Strait Ln",
    "sg:city":"Dallas",
    "sg:classifiers":[
        {
            "category":"Health Services",
            "subcategory":"Doctor",
            "type":"Services"
        }
    ],
    "sg:phone":"+1 214 369 6613",
    "sg:postcode":"75229",
    "sg:province":"TX",
    "sg:tags":[
        "medical"
    ],
    "wof:name":"Callewart Family Ltd Part",
    "wof:placetype":"venue"
},
  "geometry": {"coordinates":[-96.824609,32.893796],"type":"Point"}
}