{
  "type": "Feature",
  "properties": {
    "iso:country":"US",
    "sg:address":"200 E Belt Line Rd",
    "sg:city":"Coppell",
    "sg:classifiers":[
        {
            "category":"Organizations",
            "subcategory":"Professional Association",
            "type":"Services"
        }
    ],
    "sg:phone":"+1 972 393 2829",
    "sg:postcode":"75019",
    "sg:province":"TX",
    "sg:tags":[
        "chambers",
        "commerce"
    ],
    "wof:name":"Coppell Chamber Of Commerce",
    "wof:placetype":"venue"
},
  "geometry": {"coordinates":[-96.97915999999999,32.953939],"type":"Point"}
}