{
  "type": "Feature",
  "properties": {
    "iso:country":"US",
    "sg:address":"9768 FM 949",
    "sg:city":"Cat Spring",
    "sg:classifiers":[
        {
            "category":"Building & Trades",
            "subcategory":"Plumbing",
            "type":"Services"
        }
    ],
    "sg:phone":"+1 979 865 8707",
    "sg:postcode":"78933",
    "sg:province":"TX",
    "sg:tags":[
        "contractor"
    ],
    "wof:name":"Brentwood Plumbing",
    "wof:placetype":"venue"
},
  "geometry": {"coordinates":[-96.32114300000001,29.855995],"type":"Point"}
}