{
  "type": "Feature",
  "properties": {
    "iso:country":"US",
    "sg:address":"1008 2nd St",
    "sg:city":"Pleasanton",
    "sg:classifiers":[
        {
            "category":"Shopping",
            "subcategory":"Clothing, Apparel, & Fashions",
            "type":"Retail Goods"
        }
    ],
    "sg:phone":"+1 830 281 8768",
    "sg:postcode":"78064",
    "sg:province":"TX",
    "sg:tags":[
        "alteration"
    ],
    "wof:name":"C & M Alterations",
    "wof:placetype":"venue"
},
  "geometry": {"coordinates":[-98.47883400000001,28.968845],"type":"Point"}
}