{
  "type": "Feature",
  "properties": {
    "iso:country":"US",
    "sg:address":"15711 Cameron Rd",
    "sg:city":"Pflugerville",
    "sg:classifiers":[
        {
            "category":"Government",
            "subcategory":"City Hall",
            "type":"Public Place"
        }
    ],
    "sg:phone":"+1 512 251 5622",
    "sg:postcode":"78660",
    "sg:province":"TX",
    "wof:name":"IESI",
    "wof:placetype":"venue"
},
  "geometry": {"coordinates":[-97.579652,30.411458],"type":"Point"}
}