{
  "type": "Feature",
  "properties": {
    "iso:country":"US",
    "sg:address":"170 S Hwy 67",
    "sg:city":"Cedar Hill",
    "sg:classifiers":[
        {
            "category":"Education",
            "subcategory":"School",
            "type":"Public Place"
        }
    ],
    "sg:phone":"+1 972 291 5205",
    "sg:postcode":"75104",
    "sg:province":"TX",
    "wof:name":"Cedar Hill Independent School",
    "wof:placetype":"venue"
},
  "geometry": {"coordinates":[-96.948736,32.58826],"type":"Point"}
}