{
  "type": "Feature",
  "properties": {
    "iso:country":"US",
    "sg:address":"817 Airline Rd",
    "sg:city":"Corpus Christi",
    "sg:classifiers":[
        {
            "category":"Professional",
            "subcategory":"Management & Consulting",
            "type":"Services"
        },
        {
            "category":"Mining & Drilling",
            "type":"Manufacturing & Wholesale Goods"
        }
    ],
    "sg:phone":"+1 361 906 9100",
    "sg:postcode":"78412",
    "sg:province":"TX",
    "sg:tags":[
        "consultant",
        "energy",
        "conservation"
    ],
    "wof:name":"Tiburon Resources Inc",
    "wof:placetype":"venue"
},
  "geometry": {"coordinates":[-97.36214699999999,27.719109],"type":"Point"}
}