{
  "type": "Feature",
  "properties": {
    "iso:country":"US",
    "sg:address":"5834 Sandy Valley St",
    "sg:city":"San Antonio",
    "sg:classifiers":[
        {
            "category":"Organizations",
            "subcategory":"Membership Organization",
            "type":"Services"
        }
    ],
    "sg:phone":"+1 210 675 4537",
    "sg:postcode":"78242",
    "sg:province":"TX",
    "wof:name":"Shavano Police Officers Assn",
    "wof:placetype":"venue"
},
  "geometry": {"coordinates":[-98.615484,29.357515],"type":"Point"}
}