{
  "type": "Feature",
  "properties": {
    "iso:country":"US",
    "sg:address":"32120 Co Rd 1847",
    "sg:city":"Los Fresnos",
    "sg:classifiers":[
        {
            "category":"Social Services",
            "type":"Services"
        }
    ],
    "sg:phone":"+1 956 233 5705",
    "sg:postcode":"78520",
    "sg:province":"TX",
    "sg:tags":[
        "organization",
        "welfare"
    ],
    "wof:name":"International Educational Svc",
    "wof:placetype":"venue"
},
  "geometry": {"coordinates":[-97.474423,26.093338],"type":"Point"}
}