{
  "type": "Feature",
  "properties": {
    "iso:country":"US",
    "sg:address":"3425 Wayside St",
    "sg:city":"El Paso",
    "sg:classifiers":[
        {
            "category":"Health Services",
            "subcategory":"Medical Lab",
            "type":"Services"
        }
    ],
    "sg:phone":"+1 915 592 0530",
    "sg:postcode":"79936",
    "sg:province":"TX",
    "sg:tags":[
        "laboratory",
        "dental"
    ],
    "wof:name":"Medina Dental Lab Csi",
    "wof:placetype":"venue"
},
  "geometry": {"coordinates":[-106.31979,31.793214],"type":"Point"}
}