{
  "type": "Feature",
  "properties": {
    "iso:country":"US",
    "sg:address":"7200 S Hampton Rd",
    "sg:city":"Dallas",
    "sg:classifiers":[
        {
            "category":"Organizations",
            "subcategory":"Religious Organization",
            "type":"Services"
        }
    ],
    "sg:phone":"+1 469 567 1934",
    "sg:postcode":"75232",
    "sg:province":"TX",
    "wof:name":"The Called Fellowship Baptist Church",
    "wof:placetype":"venue"
},
  "geometry": {"coordinates":[-96.85684500000001,32.660785],"type":"Point"}
}