{
  "type": "Feature",
  "properties": {
    "iso:country":"US",
    "sg:address":"4203 Woodcock Dr",
    "sg:city":"San Antonio",
    "sg:classifiers":[
        {
            "category":"Government",
            "subcategory":"Office",
            "type":"Public Place"
        }
    ],
    "sg:phone":"+1 210 731 1720",
    "sg:postcode":"78228",
    "sg:province":"TX",
    "sg:tags":[
        "state",
        "inspection"
    ],
    "sg:website":"www.tabc.state.tx.us",
    "wof:name":"Alcoholic Beverage Commission",
    "wof:placetype":"venue"
},
  "geometry": {"coordinates":[-98.570691,29.487846],"type":"Point"}
}