{
  "type": "Feature",
  "properties": {
    "iso:country":"US",
    "sg:address":"4502 Leopard St",
    "sg:city":"Corpus Christi",
    "sg:classifiers":[
        {
            "category":"Food & Beverages",
            "subcategory":"Groceries & Convenience Stores",
            "type":"Retail Goods"
        }
    ],
    "sg:phone":"+1 361 883 6822",
    "sg:postcode":"78408",
    "sg:province":"TX",
    "wof:name":"Circle K",
    "wof:placetype":"venue"
},
  "geometry": {"coordinates":[-97.444553,27.797218],"type":"Point"}
}