{
  "type": "Feature",
  "properties": {
    "iso:country":"US",
    "sg:address":"2410 Hunter Hill Dr",
    "sg:city":"Arlington",
    "sg:classifiers":[
        {
            "category":"Building & Trades",
            "subcategory":"Landscaping Services",
            "type":"Services"
        }
    ],
    "sg:phone":"+1 817 277 2314",
    "sg:postcode":"76012",
    "sg:province":"TX",
    "sg:tags":[
        "landscape",
        "contractor"
    ],
    "wof:name":"Burris Lawn & Landscape LLP",
    "wof:placetype":"venue"
},
  "geometry": {"coordinates":[-97.12606599999999,32.776206],"type":"Point"}
}