{
  "type": "Feature",
  "properties": {
    "iso:country":"US",
    "sg:address":"719 Sawdust Rd",
    "sg:city":"Spring",
    "sg:classifiers":[
        {
            "category":"Professional",
            "subcategory":"Accounting & Tax Preparation",
            "type":"Services"
        }
    ],
    "sg:phone":"+1 281 367 7086",
    "sg:postcode":"77380",
    "sg:province":"TX",
    "sg:tags":[
        "accountant",
        "return"
    ],
    "wof:name":"Complete Bookkeeping",
    "wof:placetype":"venue"
},
  "geometry": {"coordinates":[-95.456928,30.126695],"type":"Point"}
}