{
  "type": "Feature",
  "properties": {
    "iso:country":"US",
    "sg:address":"891 Crystal Farms Rd",
    "sg:city":"Tatum",
    "sg:classifiers":[
        {
            "category":"Building & Trades",
            "subcategory":"Construction",
            "type":"Services"
        }
    ],
    "sg:phone":"+1 903 947 2131",
    "sg:postcode":"75691",
    "sg:province":"TX",
    "sg:tags":[
        "painter"
    ],
    "wof:name":"Tuff Coat Powder Coating",
    "wof:placetype":"venue"
},
  "geometry": {"coordinates":[-94.529675,32.327361],"type":"Point"}
}