{
  "type": "Feature",
  "properties": {
    "iso:country":"US",
    "sg:address":"20707 Golden Hawthorne Ct",
    "sg:city":"Humble",
    "sg:classifiers":[
        {
            "category":"Professional",
            "subcategory":"Management & Consulting",
            "type":"Services"
        }
    ],
    "sg:phone":"+1 281 812 1660",
    "sg:postcode":"77346",
    "sg:province":"TX",
    "wof:name":"Communi K Ations",
    "wof:placetype":"venue"
},
  "geometry": {"coordinates":[-95.175815,30.013657],"type":"Point"}
}