{
  "type": "Feature",
  "properties": {
    "iso:country":"US",
    "sg:address":"2312 Nantucket Dr",
    "sg:city":"Houston",
    "sg:classifiers":[
        {
            "category":"Professional",
            "subcategory":"Business Services",
            "type":"Services"
        }
    ],
    "sg:phone":"+1 713 784 7408",
    "sg:postcode":"77057",
    "sg:province":"TX",
    "wof:name":"LAbbe & Associates Interiors",
    "wof:placetype":"venue"
},
  "geometry": {"coordinates":[-95.487376,29.744892],"type":"Point"}
}