{
  "type": "Feature",
  "properties": {
    "iso:country":"US",
    "sg:address":"7600 W Vickery Blvd",
    "sg:city":"Fort Worth",
    "sg:classifiers":[
        {
            "category":"Manufacturing",
            "subcategory":"Signs",
            "type":"Manufacturing & Wholesale Goods"
        }
    ],
    "sg:phone":"+1 817 377 2244",
    "sg:postcode":"76116",
    "sg:province":"TX",
    "wof:name":"B & B Signs",
    "wof:placetype":"venue"
},
  "geometry": {"coordinates":[-97.44374999999999,32.697251],"type":"Point"}
}