{
  "type": "Feature",
  "properties": {
    "iso:country":"US",
    "sg:address":"2829 56th St",
    "sg:city":"Dallas",
    "sg:classifiers":[
        {
            "category":"Shopping",
            "subcategory":"Gifts & Souvenirs",
            "type":"Retail Goods"
        }
    ],
    "sg:phone":"+1 214 375 0613",
    "sg:postcode":"75241",
    "sg:province":"TX",
    "sg:tags":[
        "shop"
    ],
    "wof:name":"Chapman Enterprises",
    "wof:placetype":"venue"
},
  "geometry": {"coordinates":[-96.773606,32.690321],"type":"Point"}
}