{
  "type": "Feature",
  "properties": {
    "iso:country":"US",
    "sg:address":"1331 Dominion Dr",
    "sg:city":"Katy",
    "sg:classifiers":[
        {
            "category":"Professional",
            "subcategory":"Management & Consulting",
            "type":"Services"
        }
    ],
    "sg:phone":"+1 281 492 0245",
    "sg:postcode":"77450",
    "sg:province":"TX",
    "sg:tags":[
        "business"
    ],
    "wof:name":"Boomers Consulting Inc",
    "wof:placetype":"venue"
},
  "geometry": {"coordinates":[-95.724456,29.766564],"type":"Point"}
}