{
  "type": "Feature",
  "properties": {
    "iso:country":"US",
    "sg:address":"1520 Ranch Rd 12",
    "sg:city":"San Marcos",
    "sg:classifiers":[
        {
            "category":"Personal",
            "type":"Services"
        }
    ],
    "sg:phone":"+1 512 396 8335",
    "sg:postcode":"78666",
    "sg:province":"TX",
    "wof:name":"Massage Pure Bliss",
    "wof:placetype":"venue"
},
  "geometry": {"coordinates":[-97.959727,29.894422],"type":"Point"}
}