{
  "type": "Feature",
  "properties": {
    "iso:country":"US",
    "sg:address":"202 S Main St",
    "sg:city":"Brazoria",
    "sg:classifiers":[
        {
            "category":"Government",
            "subcategory":"Office",
            "type":"Public Place"
        }
    ],
    "sg:phone":"+1 979 798 7441",
    "sg:postcode":"77422",
    "sg:province":"TX",
    "sg:tags":[
        "state",
        "inspection"
    ],
    "wof:name":"Texas Alcoholic Beverage",
    "wof:placetype":"venue"
},
  "geometry": {"coordinates":[-95.568926,29.044339],"type":"Point"}
}