{
  "type": "Feature",
  "properties": {
    "iso:country":"US",
    "sg:address":"323 Twisted Wood Dr",
    "sg:city":"San Antonio",
    "sg:classifiers":[
        {
            "category":"Banks & Credit Unions",
            "subcategory":"Financial Services",
            "type":"Services"
        }
    ],
    "sg:phone":"+1 210 270 4665",
    "sg:postcode":"78216",
    "sg:province":"TX",
    "sg:tags":[
        "investor"
    ],
    "wof:name":"Single Family Investments",
    "wof:placetype":"venue"
},
  "geometry": {"coordinates":[-98.491951,29.568075],"type":"Point"}
}