{
  "type": "Feature",
  "properties": {
    "iso:country":"US",
    "sg:address":"9502 Kempwood Dr",
    "sg:city":"Houston",
    "sg:classifiers":[
        {
            "category":"Autos & Motor Vehicles",
            "subcategory":"Fuel & Gas Station",
            "type":"Retail Goods"
        }
    ],
    "sg:phone":"+1 713 462 2350",
    "sg:postcode":"77080",
    "sg:province":"TX",
    "sg:tags":[
        "station"
    ],
    "wof:name":"CAM Kem",
    "wof:placetype":"venue"
},
  "geometry": {"coordinates":[-95.527072,29.822013],"type":"Point"}
}