{
  "type": "Feature",
  "properties": {
    "iso:country":"US",
    "sg:address":"5975 S Cooper St",
    "sg:city":"Arlington",
    "sg:classifiers":[
        {
            "category":"Personal",
            "subcategory":"Beauty Salon",
            "type":"Services"
        }
    ],
    "sg:phone":"+1 817 557 0575",
    "sg:postcode":"76017",
    "sg:province":"TX",
    "sg:tags":[
        "shop"
    ],
    "wof:name":"Fantastic Sams",
    "wof:placetype":"venue"
},
  "geometry": {"coordinates":[-97.13450400000001,32.650083],"type":"Point"}
}