{
  "type": "Feature",
  "properties": {
    "iso:country":"US",
    "sg:address":"8908 N Navarro St",
    "sg:city":"Victoria",
    "sg:classifiers":[
        {
            "category":"Restaurant",
            "type":"Food & Drink"
        }
    ],
    "sg:menulink":"http://www.allmenus.com/tx/victoria/157489-whataburger/menu/",
    "sg:phone":"+1 361 578 9858",
    "sg:postcode":"77904",
    "sg:province":"TX",
    "sg:tags":[
        "burger",
        "american"
    ],
    "wof:name":"Whataburger",
    "wof:placetype":"venue"
},
  "geometry": {"coordinates":[-96.997467,28.875541],"type":"Point"}
}