{
  "type": "Feature",
  "properties": {
    "iso:country":"US",
    "sg:address":"710 N Ave I",
    "sg:city":"Odessa",
    "sg:classifiers":[
        {
            "category":"Utilities",
            "subcategory":"Refuse",
            "type":"Services"
        }
    ],
    "sg:phone":"+1 432 385 0330",
    "sg:postcode":"79763",
    "sg:province":"TX",
    "sg:tags":[
        "system"
    ],
    "wof:name":"Corrales David Dumping Service",
    "wof:placetype":"venue"
},
  "geometry": {"coordinates":[-102.41763,31.833167],"type":"Point"}
}