{
  "type": "Feature",
  "properties": {
    "iso:country":"US",
    "sg:address":"2733 Stanford St",
    "sg:city":"Pasadena",
    "sg:classifiers":[
        {
            "category":"Building & Trades",
            "subcategory":"Construction",
            "type":"Services"
        }
    ],
    "sg:phone":"+1 713 935 2336",
    "sg:postcode":"77502",
    "sg:province":"TX",
    "sg:tags":[
        "roofing",
        "siding",
        "work"
    ],
    "wof:name":"Hill Roofing & Paving",
    "wof:placetype":"venue"
},
  "geometry": {"coordinates":[-95.17310000000001,29.681456],"type":"Point"}
}