{
  "type": "Feature",
  "properties": {
    "iso:country":"US",
    "sg:address":"601 W Cantu Rd",
    "sg:city":"Del Rio",
    "sg:classifiers":[
        {
            "category":"Insurance",
            "subcategory":"Insurance Agent",
            "type":"Services"
        }
    ],
    "sg:phone":"+1 830 775 9548",
    "sg:postcode":"78840",
    "sg:province":"TX",
    "wof:name":"Gerald Wilson Insurance",
    "wof:placetype":"venue"
},
  "geometry": {"coordinates":[-100.917593,29.385993],"type":"Point"}
}