{
  "type": "Feature",
  "properties": {
    "iso:country":"US",
    "sg:address":"4040 Hooper Dr",
    "sg:city":"Wichita Falls",
    "sg:classifiers":[
        {
            "category":"Shopping",
            "type":"Retail Goods"
        }
    ],
    "sg:phone":"+1 940 855 5003",
    "sg:postcode":"76306",
    "sg:province":"TX",
    "sg:tags":[
        "merchandise"
    ],
    "wof:name":"Fresh Air",
    "wof:placetype":"venue"
},
  "geometry": {"coordinates":[-98.525085,33.964267],"type":"Point"}
}