{
  "type": "Feature",
  "properties": {
    "iso:country":"US",
    "sg:address":"8706 Valencia Ave",
    "sg:city":"Lubbock",
    "sg:classifiers":[
        {
            "category":"Building & Trades",
            "subcategory":"Plumbing",
            "type":"Services"
        }
    ],
    "sg:phone":"+1 806 794 3760",
    "sg:postcode":"79424",
    "sg:province":"TX",
    "sg:tags":[
        "conditioning",
        "air",
        "system",
        "contractor"
    ],
    "wof:name":"Jack Adams Heating & Air Cond",
    "wof:placetype":"venue"
},
  "geometry": {"coordinates":[-101.978818,33.514031],"type":"Point"}
}