{
  "type": "Feature",
  "properties": {
    "iso:country":"US",
    "sg:address":"5393 Westheimer Rd",
    "sg:city":"Houston",
    "sg:classifiers":[
        {
            "category":"Shopping",
            "subcategory":"Used Merchandise",
            "type":"Retail Goods"
        }
    ],
    "sg:phone":"+1 713 960 9084",
    "sg:postcode":"77056",
    "sg:province":"TX",
    "sg:tags":[
        "antique"
    ],
    "sg:website":"www.themarketonline.com",
    "wof:name":"Market Uptown Collection",
    "wof:placetype":"venue"
},
  "geometry": {"coordinates":[-95.467142,29.740297],"type":"Point"}
}