{
  "type": "Feature",
  "properties": {
    "iso:country":"US",
    "sg:address":"103 N Main St",
    "sg:city":"Lumberton",
    "sg:classifiers":[
        {
            "category":"Restaurant",
            "type":"Food & Drink"
        }
    ],
    "sg:menulink":"http://www.allmenus.com/tx/chance-loeb/202862-mcdonalds/menu/",
    "sg:postcode":"77657",
    "sg:province":"TX",
    "sg:tags":[
        "burger",
        "american"
    ],
    "wof:name":"McDonald's",
    "wof:placetype":"venue"
},
  "geometry": {"coordinates":[-94.19823700000001,30.256138],"type":"Point"}
}