{
  "type": "Feature",
  "properties": {
    "iso:country":"US",
    "sg:address":"11425 Goodnight Ln",
    "sg:city":"Dallas",
    "sg:classifiers":[
        {
            "category":"Shopping",
            "subcategory":"Discount & Variety Stores",
            "type":"Retail Goods"
        }
    ],
    "sg:phone":"+1 972 620 7212",
    "sg:postcode":"75229",
    "sg:province":"TX",
    "sg:tags":[
        "merchandise",
        "general"
    ],
    "wof:name":"Sales & Marketing Inc",
    "wof:placetype":"venue"
},
  "geometry": {"coordinates":[-96.90217800000001,32.895999],"type":"Point"}
}