{
  "type": "Feature",
  "properties": {
    "iso:country":"US",
    "sg:address":"121 N 1st St",
    "sg:city":"Harlingen",
    "sg:classifiers":[
        {
            "category":"Home & Garden",
            "subcategory":"Furniture",
            "type":"Retail Goods"
        }
    ],
    "sg:phone":"+1 956 428 8677",
    "sg:postcode":"78550",
    "sg:province":"TX",
    "wof:name":"Apex Hotel Furniture Sales",
    "wof:placetype":"venue"
},
  "geometry": {"coordinates":[-97.69568700000001,26.19359],"type":"Point"}
}