{
  "type": "Feature",
  "properties": {
    "iso:country":"US",
    "sg:address":"411 Longview Dr",
    "sg:city":"Sugar Land",
    "sg:classifiers":[
        {
            "category":"Building & Trades",
            "subcategory":"Construction",
            "type":"Services"
        }
    ],
    "sg:phone":"+1 281 491 5389",
    "sg:postcode":"77478",
    "sg:province":"TX",
    "sg:tags":[
        "foundation"
    ],
    "wof:name":"Certified Foundation Spec",
    "wof:placetype":"venue"
},
  "geometry": {"coordinates":[-95.58794,29.621753],"type":"Point"}
}