{
  "type": "Feature",
  "properties": {
    "iso:country":"US",
    "sg:address":"1520 Rutherford Ln",
    "sg:city":"Austin",
    "sg:classifiers":[
        {
            "category":"Professional",
            "subcategory":"Computer Services",
            "type":"Services"
        }
    ],
    "sg:phone":"+1 512 491 7526",
    "sg:postcode":"78754",
    "sg:province":"TX",
    "sg:tags":[
        "isp",
        "provider",
        "internet"
    ],
    "wof:name":"COA DSL Line",
    "wof:placetype":"venue"
},
  "geometry": {"coordinates":[-97.68171,30.336546],"type":"Point"}
}