{
  "type": "Feature",
  "properties": {
    "iso:country":"US",
    "sg:address":"16840 Krug Rd",
    "sg:city":"Tomball",
    "sg:classifiers":[
        {
            "category":"Professional",
            "subcategory":"Management & Consulting",
            "type":"Services"
        }
    ],
    "sg:phone":"+1 281 357 5284",
    "sg:postcode":"77377",
    "sg:province":"TX",
    "sg:tags":[
        "public",
        "relations"
    ],
    "wof:name":"Logosmart",
    "wof:placetype":"venue"
},
  "geometry": {"coordinates":[-95.683894,30.099897],"type":"Point"}
}