{
  "type": "Feature",
  "properties": {
    "iso:country":"US",
    "sg:address":"808 Travis St",
    "sg:city":"Houston",
    "sg:classifiers":[
        {
            "category":"Mining & Drilling",
            "type":"Manufacturing & Wholesale Goods"
        }
    ],
    "sg:phone":"+1 713 223 5263",
    "sg:postcode":"77002",
    "sg:province":"TX",
    "sg:tags":[
        "development",
        "gas",
        "oil",
        "exploration"
    ],
    "wof:name":"Michael E Brennan & Assoc",
    "wof:placetype":"venue"
},
  "geometry": {"coordinates":[-95.365234,29.75833],"type":"Point"}
}