{
  "type": "Feature",
  "properties": {
    "iso:country":"US",
    "sg:address":"2013 Campbell Rd",
    "sg:city":"Houston",
    "sg:classifiers":[
        {
            "category":"Retail",
            "subcategory":"Auto Repair",
            "type":"Services"
        }
    ],
    "sg:phone":"+1 713 461 3000",
    "sg:postcode":"77080",
    "sg:province":"TX",
    "sg:tags":[
        "transmission"
    ],
    "wof:name":"Apollo Transmission",
    "wof:placetype":"venue"
},
  "geometry": {"coordinates":[-95.52573,29.807573],"type":"Point"}
}