{
  "type": "Feature",
  "properties": {
    "iso:country":"US",
    "sg:address":"2563 Trawood Dr",
    "sg:city":"El Paso",
    "sg:classifiers":[
        {
            "category":"Freight",
            "type":"Transportation"
        },
        {
            "category":"Airline",
            "type":"Transportation"
        }
    ],
    "sg:phone":"+1 915 593 1848",
    "sg:postcode":"79936",
    "sg:province":"TX",
    "sg:tags":[
        "carrier",
        "trucking"
    ],
    "wof:name":"Rocketline Carrier Service",
    "wof:placetype":"venue"
},
  "geometry": {"coordinates":[-106.313819,31.765216],"type":"Point"}
}