{
  "type": "Feature",
  "properties": {
    "iso:country":"US",
    "sg:address":"2001 Kirby Dr",
    "sg:city":"Houston",
    "sg:classifiers":[
        {
            "category":"Mining & Drilling",
            "type":"Manufacturing & Wholesale Goods"
        }
    ],
    "sg:phone":"+1 713 529 3729",
    "sg:postcode":"77019",
    "sg:province":"TX",
    "sg:tags":[
        "crude",
        "production",
        "gas"
    ],
    "wof:name":"Federal Royalty Partners Ltd",
    "wof:placetype":"venue"
},
  "geometry": {"coordinates":[-95.418825,29.747424],"type":"Point"}
}