{
  "type": "Feature",
  "properties": {
    "iso:country":"US",
    "sg:address":"1300 N Town East Blvd Ste 103",
    "sg:city":"Mesquite",
    "sg:classifiers":[
        {
            "category":"Shopping",
            "subcategory":"Jewelry",
            "type":"Retail Goods"
        }
    ],
    "sg:phone":"+1 972 613 3985",
    "sg:postcode":"75150",
    "sg:province":"TX",
    "wof:name":"Mesquite Gold & Silver",
    "wof:placetype":"venue"
},
  "geometry": {"coordinates":[-96.61900300000001,32.810699],"type":"Point"}
}