{
  "type": "Feature",
  "properties": {
    "iso:country":"US",
    "sg:address":"501 FM 3040",
    "sg:city":"Lewisville",
    "sg:classifiers":[
        {
            "category":"Restaurant",
            "type":"Food & Drink"
        }
    ],
    "sg:phone":"+1 972 315 0578",
    "sg:postcode":"75067",
    "sg:province":"TX",
    "sg:tags":[
        "eating"
    ],
    "wof:name":"McDonalds",
    "wof:placetype":"venue"
},
  "geometry": {"coordinates":[-97.00639700000001,33.0049],"type":"Point"}
}