{
  "type": "Feature",
  "properties": {
    "iso:country":"US",
    "sg:address":"210 S Industrial Blvd",
    "sg:city":"Euless",
    "sg:classifiers":[
        {
            "category":"Restaurant",
            "type":"Food & Drink"
        }
    ],
    "sg:phone":"+1 817 858 0507",
    "sg:postcode":"76040",
    "sg:province":"TX",
    "sg:tags":[
        "style",
        "american",
        "family"
    ],
    "wof:name":"Pockets Restaurant",
    "wof:placetype":"venue"
},
  "geometry": {"coordinates":[-97.09977000000001,32.835413],"type":"Point"}
}