{
  "type": "Feature",
  "properties": {
    "iso:country":"US",
    "sg:address":"1500 N Central Expy",
    "sg:city":"Mc Kinney",
    "sg:classifiers":[
        {
            "category":"Building & Trades",
            "subcategory":"Plumbing",
            "type":"Services"
        }
    ],
    "sg:phone":"+1 972 569 8800",
    "sg:postcode":"75070",
    "sg:province":"TX",
    "sg:tags":[
        "plumbing",
        "commercial",
        "contractor"
    ],
    "wof:name":"Lawton Group LLC",
    "wof:placetype":"venue"
},
  "geometry": {"coordinates":[-96.63690800000001,33.212545],"type":"Point"}
}