{
  "type": "Feature",
  "properties": {
    "iso:country":"US",
    "sg:address":"315 Morning Dove Dr",
    "sg:city":"Duncanville",
    "sg:classifiers":[
        {
            "category":"Professional",
            "type":"Services"
        }
    ],
    "sg:phone":"+1 972 780 1583",
    "sg:postcode":"75137",
    "sg:province":"TX",
    "wof:name":"Ynette's Correspondence Svc",
    "wof:placetype":"venue"
},
  "geometry": {"coordinates":[-96.91622599999999,32.639784],"type":"Point"}
}