{
  "type": "Feature",
  "properties": {
    "iso:country":"US",
    "sg:address":"11064 Hebron Rd",
    "sg:city":"Tyler",
    "sg:classifiers":[
        {
            "category":"Freight",
            "type":"Transportation"
        }
    ],
    "sg:phone":"+1 903 526 0553",
    "sg:postcode":"75708",
    "sg:province":"TX",
    "sg:tags":[
        "trucking"
    ],
    "wof:name":"Outlaw Auto Transport",
    "wof:placetype":"venue"
},
  "geometry": {"coordinates":[-95.22533799999999,32.374727],"type":"Point"}
}