{
  "type": "Feature",
  "properties": {
    "iso:country":"US",
    "sg:address":"2477 S Cockrell Hill Rd",
    "sg:city":"Dallas",
    "sg:classifiers":[
        {
            "category":"Food & Beverages",
            "subcategory":"Groceries & Convenience Stores",
            "type":"Retail Goods"
        }
    ],
    "sg:phone":"+1 214 339 6225",
    "sg:postcode":"75211",
    "sg:province":"TX",
    "wof:name":"Cost Plus Food Mart",
    "wof:placetype":"venue"
},
  "geometry": {"coordinates":[-96.891599,32.718941],"type":"Point"}
}