{
  "type": "Feature",
  "properties": {
    "iso:country":"US",
    "sg:address":"10617 Jefferson Chemical Rd",
    "sg:city":"Conroe",
    "sg:classifiers":[
        {
            "category":"Building & Trades",
            "subcategory":"Construction",
            "type":"Services"
        }
    ],
    "sg:phone":"+1 936 756 8011",
    "sg:postcode":"77301",
    "sg:province":"TX",
    "sg:tags":[
        "general",
        "contractor"
    ],
    "sg:website":"www.arbinc.com",
    "wof:name":"Arb Inc",
    "wof:placetype":"venue"
},
  "geometry": {"coordinates":[-95.38475800000001,30.295898],"type":"Point"}
}