{
  "type": "Feature",
  "properties": {
    "iso:country":"US",
    "sg:address":"4640 Ivanhoe St",
    "sg:city":"Houston",
    "sg:classifiers":[
        {
            "category":"Shopping",
            "subcategory":"Clothing, Apparel, & Fashions",
            "type":"Retail Goods"
        }
    ],
    "sg:phone":"+1 713 652 4124",
    "sg:postcode":"77027",
    "sg:province":"TX",
    "wof:name":"Akl Designs",
    "wof:placetype":"venue"
},
  "geometry": {"coordinates":[-95.45718100000001,29.739715],"type":"Point"}
}