{
  "type": "Feature",
  "properties": {
    "iso:country":"US",
    "sg:address":"4303 FM 2218",
    "sg:city":"Richmond",
    "sg:classifiers":[
        {
            "category":"Building & Trades",
            "subcategory":"Electrical",
            "type":"Services"
        }
    ],
    "sg:phone":"+1 281 232 2830",
    "sg:postcode":"77469",
    "sg:province":"TX",
    "sg:tags":[
        "electrical",
        "contractor"
    ],
    "wof:name":"Harris Electric Co",
    "wof:placetype":"venue"
},
  "geometry": {"coordinates":[-95.789535,29.514173],"type":"Point"}
}