{
  "type": "Feature",
  "properties": {
    "iso:country":"US",
    "sg:address":"3904 Peru Cir",
    "sg:city":"Pasadena",
    "sg:classifiers":[
        {
            "category":"Building & Trades",
            "subcategory":"Landscaping Services",
            "type":"Services"
        }
    ],
    "sg:phone":"+1 713 947 0321",
    "sg:postcode":"77504",
    "sg:province":"TX",
    "wof:name":"B & B Lawn Service",
    "wof:placetype":"venue"
},
  "geometry": {"coordinates":[-95.18447399999999,29.655462],"type":"Point"}
}