{
  "type": "Feature",
  "properties": {
    "iso:country":"US",
    "sg:address":"811 Molasses Rd",
    "sg:city":"Dale",
    "sg:classifiers":[
        {
            "category":"Farming",
            "subcategory":"Livestock Farm",
            "type":"Manufacturing & Wholesale Goods"
        }
    ],
    "sg:phone":"+1 512 398 6084",
    "sg:postcode":"78616",
    "sg:province":"TX",
    "sg:tags":[
        "equine"
    ],
    "wof:name":"Lazy Idh Paso Fino Ranch",
    "wof:placetype":"venue"
},
  "geometry": {"coordinates":[-97.518018,29.866406],"type":"Point"}
}