{
  "type": "Feature",
  "properties": {
    "iso:country":"US",
    "sg:address":"5231 Ivystone Ct",
    "sg:city":"Sugar Land",
    "sg:classifiers":[
        {
            "category":"Travel",
            "subcategory":"Travel Agent",
            "type":"Entertainment"
        }
    ],
    "sg:phone":"+1 281 265 0589",
    "sg:postcode":"77479",
    "sg:province":"TX",
    "sg:tags":[
        "passenger",
        "transportation",
        "arrangement"
    ],
    "wof:name":"Air India Sales Office",
    "wof:placetype":"venue"
},
  "geometry": {"coordinates":[-95.626251,29.559781],"type":"Point"}
}