{
  "type": "Feature",
  "properties": {
    "iso:country":"US",
    "sg:address":"3200 Montrose Blvd",
    "sg:city":"Houston",
    "sg:classifiers":[
        {
            "category":"Restaurant",
            "type":"Food & Drink"
        }
    ],
    "sg:menulink":"http://www.allmenus.com/tx/houston/51992-papa-johns-pizza/menu/",
    "sg:phone":"+1 713 874 1999",
    "sg:postcode":"77006",
    "sg:province":"TX",
    "sg:tags":[
        "american",
        "pizza"
    ],
    "wof:name":"Papa John's Pizza",
    "wof:placetype":"venue"
},
  "geometry": {"coordinates":[-95.391322,29.744555],"type":"Point"}
}