{
  "type": "Feature",
  "properties": {
    "iso:country":"US",
    "sg:address":"317 Omaha St",
    "sg:city":"Dalhart",
    "sg:classifiers":[
        {
            "category":"Home & Garden",
            "subcategory":"Building Materials",
            "type":"Retail Goods"
        }
    ],
    "sg:phone":"+1 806 244 5761",
    "sg:postcode":"79022",
    "sg:province":"TX",
    "sg:tags":[
        "trade",
        "contractor"
    ],
    "wof:name":"Eddies Welding & Fencing",
    "wof:placetype":"venue"
},
  "geometry": {"coordinates":[-102.527169,36.065389],"type":"Point"}
}