{
  "type": "Feature",
  "properties": {
    "iso:country":"US",
    "sg:address":"121 W 7th St",
    "sg:city":"Plainview",
    "sg:classifiers":[
        {
            "category":"Government",
            "subcategory":"Office",
            "type":"Public Place"
        }
    ],
    "sg:phone":"+1 806 296 1130",
    "sg:postcode":"79072",
    "sg:province":"TX",
    "sg:tags":[
        "village"
    ],
    "wof:name":"Plainview Finance Director",
    "wof:placetype":"venue"
},
  "geometry": {"coordinates":[-101.704065,34.186912],"type":"Point"}
}