{
  "type": "Feature",
  "properties": {
    "iso:country":"US",
    "sg:address":"4314 W Lovers Ln",
    "sg:city":"Dallas",
    "sg:classifiers":[
        {
            "category":"Health Services",
            "subcategory":"Clinic",
            "type":"Services"
        }
    ],
    "sg:phone":"+1 214 432 6624",
    "sg:postcode":"75209",
    "sg:province":"TX",
    "sg:tags":[
        "counseling",
        "mental"
    ],
    "sg:website":"hypnomark.com",
    "wof:name":"Good Vibes Hypnosis Dallas",
    "wof:placetype":"venue"
},
  "geometry": {"coordinates":[-96.835964,32.850962],"type":"Point"}
}