{
  "type": "Feature",
  "properties": {
    "iso:country":"US",
    "sg:address":"801 W Front St",
    "sg:city":"Alice",
    "sg:classifiers":[
        {
            "category":"Autos & Motor Vehicles",
            "subcategory":"Automobile Sales",
            "type":"Retail Goods"
        }
    ],
    "sg:phone":"+1 361 664 0411",
    "sg:postcode":"78332",
    "sg:province":"TX",
    "sg:tags":[
        "used"
    ],
    "wof:name":"R & J Motors",
    "wof:placetype":"venue"
},
  "geometry": {"coordinates":[-98.084808,27.746751],"type":"Point"}
}