{
  "type": "Feature",
  "properties": {
    "iso:country":"US",
    "sg:address":"9889 Bellaire Blvd Ste E209",
    "sg:city":"Houston",
    "sg:classifiers":[
        {
            "category":"Restaurant",
            "type":"Food & Drink"
        }
    ],
    "sg:phone":"+1 713 981 8838",
    "sg:postcode":"77036",
    "sg:province":"TX",
    "sg:tags":[
        "chinese"
    ],
    "wof:name":"Fu Fu Restaurant",
    "wof:placetype":"venue"
},
  "geometry": {"coordinates":[-95.553414,29.703436],"type":"Point"}
}