{
  "type": "Feature",
  "properties": {
    "iso:country":"US",
    "sg:address":"25003 Pitkin Rd",
    "sg:city":"Spring",
    "sg:classifiers":[
        {
            "category":"Health Services",
            "subcategory":"Doctor",
            "type":"Services"
        }
    ],
    "sg:phone":"+1 281 364 8326",
    "sg:postcode":"77386",
    "sg:province":"TX",
    "sg:tags":[
        "medical"
    ],
    "wof:name":"Team Pedorthics Inc",
    "wof:placetype":"venue"
},
  "geometry": {"coordinates":[-95.43928699999999,30.122193],"type":"Point"}
}