{
  "type": "Feature",
  "properties": {
    "iso:country":"US",
    "sg:address":"2417 Yonkers St",
    "sg:city":"Plainview",
    "sg:classifiers":[
        {
            "category":"Education",
            "subcategory":"School",
            "type":"Public Place"
        }
    ],
    "sg:phone":"+1 806 296 4184",
    "sg:postcode":"79072",
    "sg:province":"TX",
    "sg:website":"http://www.plainview.k12.tx.us",
    "wof:name":"Houston Middle & High School",
    "wof:placetype":"venue"
},
  "geometry": {"coordinates":[-101.734782,34.204847],"type":"Point"}
}