{
  "type": "Feature",
  "properties": {
    "iso:country":"US",
    "sg:address":"1001 E US Hwy 83",
    "sg:city":"Mcallen",
    "sg:classifiers":[
        {
            "category":"Shopping",
            "subcategory":"Discount & Variety Stores",
            "type":"Retail Goods"
        }
    ],
    "sg:phone":"+1 956 682 7637",
    "sg:postcode":"78501",
    "sg:province":"TX",
    "sg:tags":[
        "merchandise",
        "general"
    ],
    "wof:name":"Green Tree",
    "wof:placetype":"venue"
},
  "geometry": {"coordinates":[-98.210493,26.19985],"type":"Point"}
}