{
  "type": "Feature",
  "properties": {
    "iso:country":"US",
    "sg:address":"1710 Oak Ridge Dr",
    "sg:city":"Kemah",
    "sg:classifiers":[
        {
            "category":"Retail",
            "subcategory":"Photofinishing",
            "type":"Services"
        }
    ],
    "sg:phone":"+1 832 978 8971",
    "sg:postcode":"77565",
    "sg:province":"TX",
    "sg:tags":[
        "laboratory"
    ],
    "wof:name":"24 Hour Express",
    "wof:placetype":"venue"
},
  "geometry": {"coordinates":[-95.025701,29.531609],"type":"Point"}
}