{
  "type": "Feature",
  "properties": {
    "iso:country":"US",
    "sg:address":"11228 W Co Rd 127",
    "sg:city":"Odessa",
    "sg:classifiers":[
        {
            "category":"Manufacturing",
            "subcategory":"Tools & Machinery",
            "type":"Manufacturing & Wholesale Goods"
        }
    ],
    "sg:phone":"+1 432 563 2010",
    "sg:postcode":"79765",
    "sg:province":"TX",
    "sg:tags":[
        "machine",
        "shop"
    ],
    "wof:name":"Midco Machine",
    "wof:placetype":"venue"
},
  "geometry": {"coordinates":[-102.231544,31.910076],"type":"Point"}
}