{
  "type": "Feature",
  "properties": {
    "iso:country":"US",
    "sg:address":"7200 Wyoming Springs Dr 700",
    "sg:city":"Round Rock",
    "sg:classifiers":[
        {
            "category":"Health Services",
            "subcategory":"Doctor",
            "type":"Services"
        }
    ],
    "sg:phone":"+1 512 478 8116",
    "sg:postcode":"78681",
    "sg:province":"TX",
    "sg:website":"www.ctpomd.com/index.html",
    "wof:name":"Central Texas Pediatric Orthopedics",
    "wof:placetype":"venue"
},
  "geometry": {"coordinates":[-97.734594,30.564483],"type":"Point"}
}