{
  "type": "Feature",
  "properties": {
    "iso:country":"US",
    "sg:address":"2212 Rio Grande St",
    "sg:city":"Austin",
    "sg:classifiers":[
        {
            "category":"Communications",
            "subcategory":"Film & Video Production",
            "type":"Services"
        }
    ],
    "sg:phone":"+1 512 576 5560",
    "sg:postcode":"78705",
    "sg:province":"TX",
    "sg:tags":[
        "motion"
    ],
    "wof:name":"Shard Software",
    "wof:placetype":"venue"
},
  "geometry": {"coordinates":[-97.74478499999999,30.28669],"type":"Point"}
}