{
  "type": "Feature",
  "properties": {
    "iso:country":"US",
    "sg:address":"1165 S Stemmons Fwy",
    "sg:city":"Lewisville",
    "sg:classifiers":[
        {
            "category":"Home & Garden",
            "subcategory":"Furniture",
            "type":"Retail Goods"
        }
    ],
    "sg:phone":"+1 972 353 3333",
    "sg:postcode":"75067",
    "sg:province":"TX",
    "wof:name":"Furniture Basics",
    "wof:placetype":"venue"
},
  "geometry": {"coordinates":[-96.994373,33.030872],"type":"Point"}
}