{
  "type": "Feature",
  "properties": {
    "iso:country":"US",
    "sg:address":"308 Conroe St",
    "sg:city":"Longview",
    "sg:classifiers":[
        {
            "category":"Real Estate",
            "subcategory":"Real Estate Agent",
            "type":"Services"
        }
    ],
    "sg:phone":"+1 903 758 3346",
    "sg:postcode":"75604",
    "sg:province":"TX",
    "wof:name":"S & E Properties & Assoc",
    "wof:placetype":"venue"
},
  "geometry": {"coordinates":[-94.766194,32.492884],"type":"Point"}
}