{
  "type": "Feature",
  "properties": {
    "iso:country":"US",
    "sg:address":"1911 E Division St",
    "sg:city":"Arlington",
    "sg:classifiers":[
        {
            "category":"Autos & Motor Vehicles",
            "subcategory":"Automobile Sales",
            "type":"Retail Goods"
        }
    ],
    "sg:phone":"+1 817 462 8100",
    "sg:postcode":"76011",
    "sg:province":"TX",
    "sg:tags":[
        "truck"
    ],
    "wof:name":"Auto Nation Dodge Inc",
    "wof:placetype":"venue"
},
  "geometry": {"coordinates":[-97.076419,32.742753],"type":"Point"}
}