{
  "type": "Feature",
  "properties": {
    "iso:country":"US",
    "sg:address":"3660 Maplewood Ave",
    "sg:city":"Dallas",
    "sg:classifiers":[
        {
            "category":"Wholesale",
            "subcategory":"Groceries",
            "type":"Manufacturing & Wholesale Goods"
        }
    ],
    "sg:phone":"+1 214 526 2619",
    "sg:postcode":"75205",
    "sg:province":"TX",
    "sg:tags":[
        "confectionery",
        "candy"
    ],
    "wof:name":"Park Cities Praline Co",
    "wof:placetype":"venue"
},
  "geometry": {"coordinates":[-96.793921,32.835305],"type":"Point"}
}