{
  "type": "Feature",
  "properties": {
    "iso:country":"US",
    "sg:address":"12655 Woodforest Blvd Ste 855",
    "sg:city":"Houston",
    "sg:classifiers":[
        {
            "category":"Banks & Credit Unions",
            "subcategory":"Bank",
            "type":"Services"
        }
    ],
    "sg:phone":"+1 713 453 1010",
    "sg:postcode":"77015",
    "sg:province":"TX",
    "wof:name":"S P Trainmen Federal Credit Union",
    "wof:placetype":"venue"
},
  "geometry": {"coordinates":[-95.201103,29.7915],"type":"Point"}
}