{
  "type": "Feature",
  "properties": {
    "iso:country":"US",
    "sg:address":"4803 Keller Springs Rd",
    "sg:city":"Addison",
    "sg:classifiers":[
        {
            "category":"Real Estate",
            "subcategory":"Real Estate Agent",
            "type":"Services"
        }
    ],
    "sg:phone":"+1 972 248 1994",
    "sg:postcode":"75001",
    "sg:province":"TX",
    "wof:name":"Gateway Centre Leasing Office",
    "wof:placetype":"venue"
},
  "geometry": {"coordinates":[-96.827845,32.968718],"type":"Point"}
}