{
  "type": "Feature",
  "properties": {
    "iso:country":"US",
    "sg:address":"14601 Bellaire Blvd",
    "sg:city":"Houston",
    "sg:classifiers":[
        {
            "category":"Real Estate",
            "subcategory":"Real Estate Agent",
            "type":"Services"
        }
    ],
    "sg:phone":"+1 832 303 0954",
    "sg:postcode":"77083",
    "sg:province":"TX",
    "wof:name":"Atkins, Sonya - Houston's Choice Realty",
    "wof:placetype":"venue"
},
  "geometry": {"coordinates":[-95.64540100000001,29.703859],"type":"Point"}
}