{
  "type": "Feature",
  "properties": {
    "iso:country":"US",
    "sg:address":"15609 Ecorio Dr",
    "sg:city":"Austin",
    "sg:classifiers":[
        {
            "category":"Professional",
            "subcategory":"Management & Consulting",
            "type":"Services"
        }
    ],
    "sg:phone":"+1 512 255 1255",
    "sg:postcode":"78728",
    "sg:province":"TX",
    "sg:tags":[
        "consultant",
        "training"
    ],
    "sg:website":"www.jewellspeak.com",
    "wof:name":"JEWELLSPEAK.COM",
    "wof:placetype":"venue"
},
  "geometry": {"coordinates":[-97.685304,30.46146],"type":"Point"}
}