{
  "type": "Feature",
  "properties": {
    "iso:country":"US",
    "sg:address":"143 Kelly Rd",
    "sg:city":"Bastrop",
    "sg:classifiers":[
        {
            "category":"Professional",
            "subcategory":"Business Services",
            "type":"Services"
        }
    ],
    "sg:phone":"+1 512 303 3664",
    "sg:postcode":"78602",
    "sg:province":"TX",
    "wof:name":"Granite Events Mgmt Group",
    "wof:placetype":"venue"
},
  "geometry": {"coordinates":[-97.241936,30.158249],"type":"Point"}
}