{
  "type": "Feature",
  "properties": {
    "iso:country":"US",
    "sg:address":"2055 Lulach Ln",
    "sg:city":"Conroe",
    "sg:classifiers":[
        {
            "category":"Restaurant",
            "type":"Food & Drink"
        }
    ],
    "sg:phone":"+1 936 321 2478",
    "sg:postcode":"77301",
    "sg:province":"TX",
    "sg:tags":[
        "mexican"
    ],
    "wof:name":"7 Leguas Mexican Cafe &C",
    "wof:placetype":"venue"
},
  "geometry": {"coordinates":[-95.445637,30.273102],"type":"Point"}
}