{
  "type": "Feature",
  "properties": {
    "iso:country":"US",
    "sg:address":"12974 Bandera Rd",
    "sg:city":"Helotes",
    "sg:classifiers":[
        {
            "category":"Personal",
            "subcategory":"Beauty Salon",
            "type":"Services"
        },
        {
            "category":"Personal",
            "subcategory":"Barber",
            "type":"Services"
        }
    ],
    "sg:phone":"+1 210 695 3311",
    "sg:postcode":"78023",
    "sg:province":"TX",
    "sg:tags":[
        "shop"
    ],
    "wof:name":"Ella's Barber & Beauty Salon",
    "wof:placetype":"venue"
},
  "geometry": {"coordinates":[-98.686511,29.563776],"type":"Point"}
}