{
  "type": "Feature",
  "properties": {
    "iso:country":"US",
    "sg:address":"4320 Lula St",
    "sg:city":"Bellaire",
    "sg:classifiers":[
        {
            "category":"Banks & Credit Unions",
            "subcategory":"Financial Services",
            "type":"Services"
        }
    ],
    "sg:phone":"+1 713 661 9734",
    "sg:postcode":"77401",
    "sg:province":"TX",
    "sg:tags":[
        "trust",
        "investment",
        "real estate"
    ],
    "wof:name":"Pilot Financial Group LLC",
    "wof:placetype":"venue"
},
  "geometry": {"coordinates":[-95.44901299999999,29.700622],"type":"Point"}
}