{
  "type": "Feature",
  "properties": {
    "iso:country":"US",
    "sg:address":"6625 Colony Rd",
    "sg:city":"Tolar",
    "sg:classifiers":[
        {
            "category":"Recreation",
            "type":"Entertainment"
        }
    ],
    "sg:phone":"+1 254 835 4168",
    "sg:postcode":"76476",
    "sg:province":"TX",
    "sg:tags":[
        "operation"
    ],
    "wof:name":"Windmill Farm Bed & Breakfast",
    "wof:placetype":"venue"
},
  "geometry": {"coordinates":[-97.87319599999999,32.422308],"type":"Point"}
}