{
  "type": "Feature",
  "properties": {
    "iso:country":"US",
    "sg:address":"9603 Spring Dr",
    "sg:city":"Frisco",
    "sg:classifiers":[
        {
            "category":"Professional",
            "subcategory":"Management & Consulting",
            "type":"Services"
        }
    ],
    "sg:phone":"+1 972 377 2687",
    "sg:postcode":"75035",
    "sg:province":"TX",
    "sg:tags":[
        "fuel"
    ],
    "wof:name":"Network Management Solutions",
    "wof:placetype":"venue"
},
  "geometry": {"coordinates":[-96.798367,33.130972],"type":"Point"}
}