{
  "type": "Feature",
  "properties": {
    "iso:country":"US",
    "sg:address":"3101 N Pecos St",
    "sg:city":"Midland",
    "sg:classifiers":[
        {
            "category":"Professional",
            "subcategory":"Management & Consulting",
            "type":"Services"
        }
    ],
    "sg:phone":"+1 432 683 4348",
    "sg:postcode":"79705",
    "sg:province":"TX",
    "wof:name":"Van Eman C M",
    "wof:placetype":"venue"
},
  "geometry": {"coordinates":[-102.087532,32.026927],"type":"Point"}
}