{
  "type": "Feature",
  "properties": {
    "iso:country":"US",
    "sg:address":"2605 Mossvine Dr",
    "sg:city":"Carrollton",
    "sg:phone":"+1 972 307 1830",
    "sg:postcode":"75007",
    "sg:province":"TX",
    "sg:tags":[
        "farm",
        "grain",
        "cash"
    ],
    "wof:name":"Rocking M3 Family Partnership",
    "wof:placetype":"venue"
},
  "geometry": {"coordinates":[-96.848983,33.01413],"type":"Point"}
}