{
  "type": "Feature",
  "properties": {
    "iso:country":"US",
    "sg:address":"6001 Airport Blvd",
    "sg:city":"Austin",
    "sg:classifiers":[
        {
            "category":"Restaurant",
            "type":"Food & Drink"
        }
    ],
    "sg:phone":"+1 512 371 7231",
    "sg:postcode":"78752",
    "sg:province":"TX",
    "sg:tags":[
        "clothing",
        "store"
    ],
    "sg:website":"http://www.express.com",
    "wof:name":"Lotus Express of Highland",
    "wof:placetype":"venue"
},
  "geometry": {"coordinates":[-97.71575199999999,30.324221],"type":"Point"}
}