{
  "type": "Feature",
  "properties": {
    "iso:country":"US",
    "sg:address":"1105 Saint Williams Ave",
    "sg:city":"Round Rock",
    "sg:classifiers":[
        {
            "category":"Professional",
            "type":"Services"
        }
    ],
    "sg:phone":"+1 512 255 3558",
    "sg:postcode":"78681",
    "sg:province":"TX",
    "wof:name":"Subtrax",
    "wof:placetype":"venue"
},
  "geometry": {"coordinates":[-97.69097499999999,30.497906],"type":"Point"}
}