{
  "type": "Feature",
  "properties": {
    "iso:country":"US",
    "sg:address":"12835 Preston Rd",
    "sg:city":"Dallas",
    "sg:classifiers":[
        {
            "category":"Recreation",
            "type":"Entertainment"
        }
    ],
    "sg:phone":"+1 972 392 9642",
    "sg:postcode":"75230",
    "sg:province":"TX",
    "sg:tags":[
        "instruction",
        "yoga"
    ],
    "sg:website":"www.yfldallas.com",
    "wof:name":"Yoga For Life",
    "wof:placetype":"venue"
},
  "geometry": {"coordinates":[-96.803802,32.9235],"type":"Point"}
}