{
  "type": "Feature",
  "properties": {
    "iso:country":"US",
    "sg:address":"221 N Beckley Ave",
    "sg:city":"Desoto",
    "sg:classifiers":[
        {
            "category":"Home & Garden",
            "subcategory":"Building Materials",
            "type":"Retail Goods"
        }
    ],
    "sg:phone":"+1 972 230 3277",
    "sg:postcode":"75115",
    "sg:province":"TX",
    "sg:tags":[
        "door"
    ],
    "wof:name":"Calhoun's Garage Door Svc",
    "wof:placetype":"venue"
},
  "geometry": {"coordinates":[-96.82295499999999,32.591562],"type":"Point"}
}