{
  "type": "Feature",
  "properties": {
    "iso:country":"US",
    "sg:address":"500 DALLAS AT SMITH",
    "sg:city":"Spring",
    "sg:classifiers":[
        {
            "category":"Health Services",
            "subcategory":"Doctor",
            "type":"Services"
        },
        {
            "category":"Health Services",
            "subcategory":"Hospital",
            "type":"Services"
        },
        {
            "category":"Personal",
            "subcategory":"Shoe Repair & Shine",
            "type":"Services"
        }
    ],
    "sg:phone":"+1 713 739 7410",
    "sg:postcode":"77373",
    "sg:province":"TX",
    "sg:tags":[
        "physician",
        "surgeon"
    ],
    "sg:website":"http://www.houstonshoehospital.com",
    "wof:name":"Houston Shoe Hospital",
    "wof:placetype":"venue"
},
  "geometry": {"coordinates":[-95.407597,30.03991],"type":"Point"}
}