{
  "type": "Feature",
  "properties": {
    "iso:country":"US",
    "sg:address":"9103 Emmott Rd",
    "sg:city":"Houston",
    "sg:classifiers":[
        {
            "category":"Home & Garden",
            "subcategory":"Building Materials",
            "type":"Retail Goods"
        }
    ],
    "sg:phone":"+1 281 610 2349",
    "sg:postcode":"77040",
    "sg:province":"TX",
    "sg:tags":[
        "door"
    ],
    "wof:name":"Doorworks",
    "wof:placetype":"venue"
},
  "geometry": {"coordinates":[-95.536539,29.873797],"type":"Point"}
}