{
  "type": "Feature",
  "properties": {
    "iso:country":"US",
    "sg:address":"1338 W Lynwood Ave",
    "sg:city":"San Antonio",
    "sg:classifiers":[
        {
            "category":"Professional",
            "type":"Services"
        }
    ],
    "sg:phone":"+1 210 732 1678",
    "sg:postcode":"78201",
    "sg:province":"TX",
    "wof:name":"Living Images",
    "wof:placetype":"venue"
},
  "geometry": {"coordinates":[-98.518196,29.463192],"type":"Point"}
}