{
  "type": "Feature",
  "properties": {
    "iso:country":"US",
    "sg:address":"906 1st St",
    "sg:city":"Meadow",
    "sg:classifiers":[
        {
            "category":"Professional",
            "subcategory":"Lawyer & Legal Services",
            "type":"Services"
        }
    ],
    "sg:phone":"+1 806 539 2377",
    "sg:postcode":"79345",
    "sg:province":"TX",
    "sg:tags":[
        "federal",
        "attorney",
        "law",
        "administrative",
        "governmental"
    ],
    "wof:name":"City Of Meadow",
    "wof:placetype":"venue"
},
  "geometry": {"coordinates":[-102.20713600000001,33.337675],"type":"Point"}
}