{
  "type": "Feature",
  "properties": {
    "iso:country":"US",
    "sg:address":"3374 Pvt Rd 2213",
    "sg:city":"Greenville",
    "sg:classifiers":[
        {
            "category":"Manufacturing",
            "subcategory":"Tools & Machinery",
            "type":"Manufacturing & Wholesale Goods"
        }
    ],
    "sg:phone":"+1 903 527 9120",
    "sg:postcode":"75402",
    "sg:province":"TX",
    "sg:tags":[
        "machine",
        "mfg"
    ],
    "wof:name":"Southtek Cnc",
    "wof:placetype":"venue"
},
  "geometry": {"coordinates":[-96.161294,33.04282],"type":"Point"}
}