{
  "type": "Feature",
  "properties": {
    "iso:country":"US",
    "sg:address":"5222 de Zavala Rd",
    "sg:city":"San Antonio",
    "sg:classifiers":[
        {
            "category":"Food & Beverages",
            "subcategory":"Liquor & Beverages",
            "type":"Retail Goods"
        }
    ],
    "sg:phone":"+1 210 696 2731",
    "sg:postcode":"78249",
    "sg:province":"TX",
    "sg:tags":[
        "beer",
        "ale"
    ],
    "wof:name":"Western Beverages-San Antonio",
    "wof:placetype":"venue"
},
  "geometry": {"coordinates":[-98.586366,29.564806],"type":"Point"}
}