{
  "type": "Feature",
  "properties": {
    "iso:country":"US",
    "sg:address":"611 S Congress Avenue",
    "sg:city":"Austin",
    "sg:classifiers":[
        {
            "category":"Professional",
            "subcategory":"Accounting & Tax Preparation",
            "type":"Services"
        }
    ],
    "sg:phone":"+1 512 477 1011",
    "sg:postcode":"78704",
    "sg:province":"TX",
    "sg:tags":[
        "accountant"
    ],
    "wof:name":"Escobedo Armando CPA",
    "wof:placetype":"venue"
},
  "geometry": {"coordinates":[-97.747327,30.255952],"type":"Point"}
}