{
  "type": "Feature",
  "properties": {
    "iso:country":"US",
    "sg:address":"370 Nueces St",
    "sg:city":"Eagle Pass",
    "sg:classifiers":[
        {
            "category":"Building & Trades",
            "subcategory":"Plumbing",
            "type":"Services"
        }
    ],
    "sg:phone":"+1 830 773 0254",
    "sg:postcode":"78852",
    "sg:province":"TX",
    "sg:tags":[
        "conditioning",
        "air",
        "system",
        "contractor"
    ],
    "wof:name":"Prado's Air Conditioning & Htg",
    "wof:placetype":"venue"
},
  "geometry": {"coordinates":[-100.49651799999999,28.709177],"type":"Point"}
}