{
  "type": "Feature",
  "properties": {
    "iso:country":"US",
    "sg:address":"2201 Commerce St",
    "sg:city":"Marble Falls",
    "sg:classifiers":[
        {
            "category":"Freight",
            "type":"Transportation"
        }
    ],
    "sg:phone":"+1 830 693 1711",
    "sg:postcode":"78654",
    "sg:province":"TX",
    "sg:tags":[
        "storage"
    ],
    "wof:name":"Lakes & Hl Receiving Stge",
    "wof:placetype":"venue"
},
  "geometry": {"coordinates":[-98.27066499999999,30.592395],"type":"Point"}
}