{
  "type": "Feature",
  "properties": {
    "iso:country":"US",
    "sg:address":"16101 Market St",
    "sg:city":"Channelview",
    "sg:classifiers":[
        {
            "category":"Freight",
            "type":"Transportation"
        }
    ],
    "sg:phone":"+1 281 452 7103",
    "sg:postcode":"77530",
    "sg:province":"TX",
    "sg:tags":[
        "dry",
        "bulk",
        "trucking"
    ],
    "wof:name":"Mission Petroleum Carriers",
    "wof:placetype":"venue"
},
  "geometry": {"coordinates":[-95.117369,29.775066],"type":"Point"}
}