{
  "type": "Feature",
  "properties": {
    "iso:country":"US",
    "sg:address":"9124 Perrin Beitel Rd",
    "sg:city":"San Antonio",
    "sg:classifiers":[
        {
            "category":"Food & Beverages",
            "subcategory":"Liquor & Beverages",
            "type":"Retail Goods"
        }
    ],
    "sg:phone":"+1 210 653 7971",
    "sg:postcode":"78217",
    "sg:province":"TX",
    "sg:tags":[
        "alcoholic"
    ],
    "wof:name":"Picnic Foods 10",
    "wof:placetype":"venue"
},
  "geometry": {"coordinates":[-98.41091,29.52242],"type":"Point"}
}