{
  "type": "Feature",
  "properties": {
    "iso:country":"US",
    "sg:address":"1512 Alabama St",
    "sg:city":"Houston",
    "sg:classifiers":[
        {
            "category":"Professional",
            "subcategory":"Lawyer & Legal Services",
            "type":"Services"
        }
    ],
    "sg:phone":"+1 713 521 3600",
    "sg:postcode":"77004",
    "sg:province":"TX",
    "wof:name":"Keyser Deborah Atty",
    "wof:placetype":"venue"
},
  "geometry": {"coordinates":[-95.37509900000001,29.7348],"type":"Point"}
}