{
  "type": "Feature",
  "properties": {
    "iso:country":"US",
    "sg:address":"415 W Burleson St",
    "sg:city":"Marshall",
    "sg:classifiers":[
        {
            "category":"Social Services",
            "type":"Services"
        }
    ],
    "sg:phone":"+1 903 934 9499",
    "sg:postcode":"75670",
    "sg:province":"TX",
    "wof:name":"Special Hlth Rsurces E Texas Y",
    "wof:placetype":"venue"
},
  "geometry": {"coordinates":[-94.371196,32.547619],"type":"Point"}
}