{
  "type": "Feature",
  "properties": {
    "iso:country":"US",
    "sg:address":"12411 Donna Dr",
    "sg:city":"Houston",
    "sg:classifiers":[
        {
            "category":"Retail",
            "subcategory":"Repair Shop",
            "type":"Services"
        }
    ],
    "sg:phone":"+1 281 876 0430",
    "sg:postcode":"77067",
    "sg:province":"TX",
    "wof:name":"Greenspoint 2-Way Radio",
    "wof:placetype":"venue"
},
  "geometry": {"coordinates":[-95.428482,29.950932],"type":"Point"}
}