{
  "type": "Feature",
  "properties": {
    "iso:country":"US",
    "sg:address":"5250 Weber Rd",
    "sg:city":"Corpus Christi",
    "sg:classifiers":[
        {
            "category":"Health Services",
            "subcategory":"Doctor",
            "type":"Services"
        }
    ],
    "sg:phone":"+1 361 855 1521",
    "sg:postcode":"78411",
    "sg:province":"TX",
    "sg:tags":[
        "dentist"
    ],
    "wof:name":"Henry F Casillas Inc",
    "wof:placetype":"venue"
},
  "geometry": {"coordinates":[-97.400167,27.719026],"type":"Point"}
}