{
  "type": "Feature",
  "properties": {
    "iso:country":"US",
    "sg:address":"4001 Bellaire Blvd Ste D",
    "sg:city":"Houston",
    "sg:classifiers":[
        {
            "category":"Bakery",
            "type":"Food & Drink"
        }
    ],
    "sg:phone":"+1 713 839 1777",
    "sg:postcode":"77025",
    "sg:province":"TX",
    "wof:name":"Kolache Factory Store No 12",
    "wof:placetype":"venue"
},
  "geometry": {"coordinates":[-95.434303,29.688299],"type":"Point"}
}