{
  "type": "Feature",
  "properties": {
    "iso:country":"US",
    "sg:address":"6405 Rte 66",
    "sg:city":"Fort Worth",
    "sg:classifiers":[
        {
            "category":"Retail",
            "subcategory":"Portrait Studio",
            "type":"Services"
        }
    ],
    "sg:phone":"+1 817 428 6630",
    "sg:postcode":"76148",
    "sg:province":"TX",
    "sg:tags":[
        "photo"
    ],
    "wof:name":"Picture Perfect Portraits",
    "wof:placetype":"venue"
},
  "geometry": {"coordinates":[-97.241534,32.863559],"type":"Point"}
}