{
  "type": "Feature",
  "properties": {
    "iso:country":"US",
    "sg:address":"4051 Lyndon B Johnson Fwy",
    "sg:city":"Dallas",
    "sg:classifiers":[
        {
            "category":"Shopping",
            "subcategory":"Computers & Home Electronics",
            "type":"Retail Goods"
        }
    ],
    "sg:phone":"+1 972 484 3474",
    "sg:postcode":"75244",
    "sg:province":"TX",
    "wof:name":"Dish Network",
    "wof:placetype":"venue"
},
  "geometry": {"coordinates":[-96.847504,32.920502],"type":"Point"}
}