{
  "type": "Feature",
  "properties": {
    "iso:country":"US",
    "sg:address":"1031 Hot Wells Blvd",
    "sg:city":"San Antonio",
    "sg:classifiers":[
        {
            "category":"Manufacturing",
            "subcategory":"Food",
            "type":"Manufacturing & Wholesale Goods"
        }
    ],
    "sg:phone":"+1 210 333 2771",
    "sg:postcode":"78223",
    "sg:province":"TX",
    "sg:tags":[
        "mfg",
        "milk",
        "fluid"
    ],
    "wof:name":"Instantwhip-Texas Inc",
    "wof:placetype":"venue"
},
  "geometry": {"coordinates":[-98.444232,29.368785],"type":"Point"}
}