{
  "type": "Feature",
  "properties": {
    "iso:country":"US",
    "sg:address":"436 W. 2nd Street",
    "sg:city":"Austin",
    "sg:classifiers":[
        {
            "category":"Shopping",
            "subcategory":"Clothing, Apparel, & Fashions",
            "type":"Retail Goods"
        },
        {
            "category":"Arts & Performance",
            "subcategory":"Art Gallery",
            "type":"Entertainment"
        },
        {
            "category":"Shopping",
            "subcategory":"Crafts & Fabrics",
            "type":"Retail Goods"
        }
    ],
    "sg:phone":"+1 512 322 5241",
    "sg:postcode":"78701",
    "sg:province":"TX",
    "sg:tags":[
        "instruction",
        "consultant",
        "galleries",
        "women's",
        "clothing"
    ],
    "wof:name":"Gallery D",
    "wof:placetype":"venue"
},
  "geometry": {"coordinates":[-97.748538,30.265498],"type":"Point"}
}