{
  "type": "Feature",
  "properties": {
    "iso:country":"US",
    "sg:address":"5041 Grisham Dr",
    "sg:city":"Rowlett",
    "sg:classifiers":[
        {
            "category":"Autos & Motor Vehicles",
            "subcategory":"Automobile Sales",
            "type":"Retail Goods"
        }
    ],
    "sg:phone":"+1 214 707 8993",
    "sg:postcode":"75088",
    "sg:province":"TX",
    "sg:tags":[
        "a",
        "repair",
        "used",
        "general"
    ],
    "wof:name":"Stephen Mc Clung Auto Sales",
    "wof:placetype":"venue"
},
  "geometry": {"coordinates":[-96.582634,32.905998],"type":"Point"}
}