{
  "type": "Feature",
  "properties": {
    "iso:country":"US",
    "sg:address":"3104 Sam Houston Dr",
    "sg:city":"Victoria",
    "sg:classifiers":[
        {
            "category":"Real Estate",
            "subcategory":"Real Estate Operator",
            "type":"Services"
        }
    ],
    "sg:phone":"+1 361 578 2913",
    "sg:postcode":"77904",
    "sg:province":"TX",
    "sg:tags":[
        "building",
        "apartment"
    ],
    "wof:name":"Victorian Manor Apartments",
    "wof:placetype":"venue"
},
  "geometry": {"coordinates":[-96.99323099999999,28.83956],"type":"Point"}
}