{
  "type": "Feature",
  "properties": {
    "iso:country":"US",
    "sg:address":"22302 Goldstone Dr",
    "sg:city":"Katy",
    "sg:classifiers":[
        {
            "category":"Professional",
            "subcategory":"Business Services",
            "type":"Services"
        }
    ],
    "sg:phone":"+1 281 574 3819",
    "sg:postcode":"77450",
    "sg:province":"TX",
    "sg:tags":[
        "payphone"
    ],
    "wof:name":"Quicksilver Communications",
    "wof:placetype":"venue"
},
  "geometry": {"coordinates":[-95.75870500000001,29.780509],"type":"Point"}
}