{
  "type": "Feature",
  "properties": {
    "iso:country":"US",
    "sg:address":"4201 Ovalla Cove",
    "sg:city":"Austin",
    "sg:classifiers":[
        {
            "category":"Professional",
            "subcategory":"Art Services",
            "type":"Services"
        }
    ],
    "sg:phone":"+1 512 423 5010",
    "sg:postcode":"78749",
    "sg:province":"TX",
    "sg:tags":[
        "photographer"
    ],
    "sg:website":"www.tiffanytaglephotography.com",
    "wof:name":"Tiffany Tagle Photography",
    "wof:placetype":"venue"
},
  "geometry": {"coordinates":[-97.853711,30.197022],"type":"Point"}
}