{
  "type": "Feature",
  "properties": {
    "iso:country":"US",
    "sg:address":"6100 Granbury Hwy",
    "sg:city":"Weatherford",
    "sg:classifiers":[
        {
            "category":"Professional",
            "type":"Services"
        }
    ],
    "sg:phone":"+1 817 599 5855",
    "sg:postcode":"76087",
    "sg:province":"TX",
    "wof:name":"J&J Show Designs",
    "wof:placetype":"venue"
},
  "geometry": {"coordinates":[-97.770887,32.666581],"type":"Point"}
}