{
  "type": "Feature",
  "properties": {
    "iso:country":"US",
    "sg:address":"1517 Corpus Christi St",
    "sg:city":"Laredo",
    "sg:classifiers":[
        {
            "category":"Professional",
            "subcategory":"Accounting & Tax Preparation",
            "type":"Services"
        }
    ],
    "sg:phone":"+1 956 725 1102",
    "sg:postcode":"78040",
    "sg:province":"TX",
    "sg:tags":[
        "bookkeeping",
        "general"
    ],
    "wof:name":"Guevara Bookkeeping Svc",
    "wof:placetype":"venue"
},
  "geometry": {"coordinates":[-99.480507,27.508341],"type":"Point"}
}