{
  "type": "Feature",
  "properties": {
    "iso:country":"US",
    "sg:address":"5049 Addison Cir",
    "sg:city":"Addison",
    "sg:classifiers":[
        {
            "category":"Food & Beverages",
            "subcategory":"Groceries & Convenience Stores",
            "type":"Retail Goods"
        }
    ],
    "sg:phone":"+1 972 661 0461",
    "sg:postcode":"75001",
    "sg:province":"TX",
    "wof:name":"Addison Market",
    "wof:placetype":"venue"
},
  "geometry": {"coordinates":[-96.824247,32.962175],"type":"Point"}
}