{
  "type": "Feature",
  "properties": {
    "iso:country":"US",
    "sg:address":"169 S Guadalupe St",
    "sg:city":"San Marcos",
    "sg:classifiers":[
        {
            "category":"Professional",
            "type":"Services"
        },
        {
            "category":"Retail",
            "subcategory":"Auto Repair",
            "type":"Services"
        }
    ],
    "sg:phone":"+1 512 396 2038",
    "sg:postcode":"78666",
    "sg:province":"TX",
    "sg:tags":[
        "repairing",
        "automobile"
    ],
    "wof:name":"Klingemann American Car Care",
    "wof:placetype":"venue"
},
  "geometry": {"coordinates":[-97.940984,29.880752],"type":"Point"}
}