{
  "type": "Feature",
  "properties": {
    "iso:country":"US",
    "sg:address":"1817 Sandy Point Rd",
    "sg:city":"Bryan",
    "sg:classifiers":[
        {
            "category":"Local Transit",
            "type":"Transportation"
        }
    ],
    "sg:phone":"+1 979 823 1241",
    "sg:postcode":"77807",
    "sg:province":"TX",
    "sg:tags":[
        "passenger"
    ],
    "wof:name":"D R Limousine Service",
    "wof:placetype":"venue"
},
  "geometry": {"coordinates":[-96.395714,30.679869],"type":"Point"}
}