{
  "type": "Feature",
  "properties": {
    "iso:country":"US",
    "sg:address":"4 Bradenton Ct",
    "sg:city":"Austin",
    "sg:classifiers":[
        {
            "category":"Professional",
            "subcategory":"Management & Consulting",
            "type":"Services"
        }
    ],
    "sg:phone":"+1 512 608 6811",
    "sg:postcode":"78738",
    "sg:province":"TX",
    "wof:name":"Cmk Consulting Inc",
    "wof:placetype":"venue"
},
  "geometry": {"coordinates":[-97.985304,30.341018],"type":"Point"}
}