{
  "type": "Feature",
  "properties": {
    "iso:country":"US",
    "sg:address":"4501 Fm 1960 Rd W",
    "sg:city":"Houston",
    "sg:classifiers":[
        {
            "category":"Coffee & Tea",
            "type":"Food & Drink"
        }
    ],
    "sg:menulink":"http://www.allmenus.com/tx/northwest-harris/112902-starbucks-coffee/menu/",
    "sg:phone":"+1 281 587 8399",
    "sg:postcode":"77069",
    "sg:province":"TX",
    "sg:tags":[
        "american"
    ],
    "wof:name":"Starbucks Coffee",
    "wof:placetype":"venue"
},
  "geometry": {"coordinates":[-95.49894,29.985967],"type":"Point"}
}