{
  "type": "Feature",
  "properties": {
    "iso:country":"US",
    "sg:address":"3333 Winthrop Ave",
    "sg:city":"Fort Worth",
    "sg:classifiers":[
        {
            "category":"Organizations",
            "subcategory":"Religious Organization",
            "type":"Services"
        }
    ],
    "sg:phone":"+1 817 737 6689",
    "sg:postcode":"76116",
    "sg:province":"TX",
    "sg:tags":[
        "book"
    ],
    "wof:name":"Gillham Ministry",
    "wof:placetype":"venue"
},
  "geometry": {"coordinates":[-97.414337,32.727804],"type":"Point"}
}