{
  "type": "Feature",
  "properties": {
    "iso:country":"US",
    "sg:address":"2818 N Main St",
    "sg:city":"Liberty",
    "sg:classifiers":[
        {
            "category":"Wholesale",
            "subcategory":"Machinery & Supplies",
            "type":"Manufacturing & Wholesale Goods"
        }
    ],
    "sg:phone":"+1 936 336 1155",
    "sg:postcode":"77575",
    "sg:province":"TX",
    "sg:tags":[
        "trailer"
    ],
    "wof:name":"Ameri-Tech Building Systems",
    "wof:placetype":"venue"
},
  "geometry": {"coordinates":[-94.77941300000001,30.07604],"type":"Point"}
}