{
  "type": "Feature",
  "properties": {
    "iso:country":"US",
    "sg:address":"501 S 2nd Ave",
    "sg:city":"Dallas",
    "sg:classifiers":[
        {
            "category":"Shopping",
            "subcategory":"Florist",
            "type":"Retail Goods"
        }
    ],
    "sg:phone":"+1 214 887 1800",
    "sg:postcode":"75226",
    "sg:province":"TX",
    "wof:name":"A Stylish Soiree",
    "wof:placetype":"venue"
},
  "geometry": {"coordinates":[-96.772953,32.782393],"type":"Point"}
}