{
  "type": "Feature",
  "properties": {
    "iso:country":"US",
    "sg:address":"5030 E University Blvd",
    "sg:city":"Odessa",
    "sg:classifiers":[
        {
            "category":"Banks & Credit Unions",
            "subcategory":"Financial Services",
            "type":"Services"
        }
    ],
    "sg:phone":"+1 432 550 2320",
    "sg:postcode":"79762",
    "sg:province":"TX",
    "sg:tags":[
        "royalty",
        "oil"
    ],
    "wof:name":"Mac London Royalty Co",
    "wof:placetype":"venue"
},
  "geometry": {"coordinates":[-102.316672,31.882543],"type":"Point"}
}