{
  "type": "Feature",
  "properties": {
    "iso:country":"US",
    "sg:address":"1215 Stratford Pl",
    "sg:city":"Keller",
    "sg:classifiers":[
        {
            "category":"Professional",
            "subcategory":"Management & Consulting",
            "type":"Services"
        }
    ],
    "sg:phone":"+1 817 431 2889",
    "sg:postcode":"76248",
    "sg:province":"TX",
    "sg:tags":[
        "consultant",
        "business"
    ],
    "wof:name":"Panorama Consulting",
    "wof:placetype":"venue"
},
  "geometry": {"coordinates":[-97.227216,32.912814],"type":"Point"}
}