{
  "type": "Feature",
  "properties": {
    "iso:country":"US",
    "sg:address":"1402 Hospital Blvd",
    "sg:city":"Floresville",
    "sg:classifiers":[
        {
            "category":"Local Transit",
            "type":"Transportation"
        }
    ],
    "sg:phone":"+1 830 393 3120",
    "sg:postcode":"78114",
    "sg:province":"TX",
    "sg:tags":[
        "ambulance"
    ],
    "wof:name":"Wilson County Volunteer EMS",
    "wof:placetype":"venue"
},
  "geometry": {"coordinates":[-98.148552,29.132114],"type":"Point"}
}