{
  "type": "Feature",
  "properties": {
    "iso:country":"US",
    "sg:address":"7617 Parkwood Plaza Dr",
    "sg:city":"Fort Worth",
    "sg:classifiers":[
        {
            "category":"Communications",
            "subcategory":"Film & Video Production",
            "type":"Services"
        }
    ],
    "sg:phone":"+1 817 656 6015",
    "sg:postcode":"76137",
    "sg:province":"TX",
    "wof:name":"Cuales Produtions",
    "wof:placetype":"venue"
},
  "geometry": {"coordinates":[-97.26721000000001,32.879328],"type":"Point"}
}