{
  "type": "Feature",
  "properties": {
    "iso:country":"US",
    "sg:address":"4640 Mar St",
    "sg:city":"Brownsville",
    "sg:classifiers":[
        {
            "category":"Transit Center",
            "subcategory":"Freight",
            "type":"Transportation"
        }
    ],
    "sg:phone":"+1 956 831 0711",
    "sg:postcode":"78521",
    "sg:province":"TX",
    "sg:tags":[
        "container",
        "broker"
    ],
    "wof:name":"Mde Impex",
    "wof:placetype":"venue"
},
  "geometry": {"coordinates":[-97.443926,25.94134],"type":"Point"}
}