{
  "type": "Feature",
  "properties": {
    "iso:country":"US",
    "sg:address":"2525 Inwood Rd",
    "sg:city":"Dallas",
    "sg:classifiers":[
        {
            "category":"Retail",
            "subcategory":"Laundry & Dry Cleaning",
            "type":"Services"
        }
    ],
    "sg:phone":"+1 214 351 3341",
    "sg:postcode":"75235",
    "sg:province":"TX",
    "sg:tags":[
        "drycleaning",
        "plant"
    ],
    "wof:name":"Maplewood Cleaners",
    "wof:placetype":"venue"
},
  "geometry": {"coordinates":[-96.835668,32.822118],"type":"Point"}
}