{
  "type": "Feature",
  "properties": {
    "iso:country":"US",
    "sg:address":"9513 Kings Link Cir",
    "sg:city":"Rowlett",
    "sg:classifiers":[
        {
            "category":"Banks & Credit Unions",
            "subcategory":"Bank",
            "type":"Services"
        }
    ],
    "sg:phone":"+1 972 475 0974",
    "sg:postcode":"75089",
    "sg:province":"TX",
    "sg:tags":[
        "mortgage"
    ],
    "wof:name":"AAA Mortgage Processing",
    "wof:placetype":"venue"
},
  "geometry": {"coordinates":[-96.538166,32.944014],"type":"Point"}
}