{
  "type": "Feature",
  "properties": {
    "iso:country":"US",
    "sg:address":"4100 Duval Road",
    "sg:city":"Austin",
    "sg:classifiers":[
        {
            "category":"Health Services",
            "subcategory":"Hospital",
            "type":"Services"
        },
        {
            "category":"Personal",
            "subcategory":"Adult",
            "type":"Services"
        }
    ],
    "sg:phone":"+1 512 346 3224",
    "sg:postcode":"78759",
    "sg:province":"TX",
    "sg:tags":[
        "midwife"
    ],
    "wof:name":"Birthing Center",
    "wof:placetype":"venue"
},
  "geometry": {"coordinates":[-97.728312,30.411656],"type":"Point"}
}