{
  "type": "Feature",
  "properties": {
    "iso:country":"US",
    "sg:address":"520 Post Oak Blvd",
    "sg:city":"Houston",
    "sg:classifiers":[
        {
            "category":"Real Estate",
            "subcategory":"Real Estate Agent",
            "type":"Services"
        }
    ],
    "sg:phone":"+1 713 626 3930",
    "sg:postcode":"77027",
    "sg:province":"TX",
    "sg:tags":[
        "selling",
        "broker",
        "buying"
    ],
    "sg:website":"www.johndaugherty.com",
    "wof:name":"John Daugherty Realtors Inc",
    "wof:placetype":"venue"
},
  "geometry": {"coordinates":[-95.452017,29.753795],"type":"Point"}
}