{
  "type": "Feature",
  "properties": {
    "iso:country":"US",
    "sg:address":"715 Katy Rd",
    "sg:city":"Keller",
    "sg:classifiers":[
        {
            "category":"Building & Trades",
            "subcategory":"Construction",
            "type":"Services"
        }
    ],
    "sg:phone":"+1 817 379 4300",
    "sg:postcode":"76248",
    "sg:province":"TX",
    "sg:tags":[
        "contractor"
    ],
    "wof:name":"M & M Marketing",
    "wof:placetype":"venue"
},
  "geometry": {"coordinates":[-97.255351,32.942176],"type":"Point"}
}