{
  "type": "Feature",
  "properties": {
    "iso:country":"US",
    "sg:address":"3680 Co Rd 245",
    "sg:city":"Florence",
    "sg:classifiers":[
        {
            "category":"Farming",
            "subcategory":"Farm & Veterinary Services",
            "type":"Manufacturing & Wholesale Goods"
        }
    ],
    "sg:phone":"+1 254 793 3092",
    "sg:postcode":"76527",
    "sg:province":"TX",
    "sg:tags":[
        "livestock"
    ],
    "wof:name":"Berry Creek Ranch",
    "wof:placetype":"venue"
},
  "geometry": {"coordinates":[-97.78738,30.767477],"type":"Point"}
}