{
  "type": "Feature",
  "properties": {
    "iso:country":"US",
    "sg:address":"841 Sagebrush Dr",
    "sg:city":"Austin",
    "sg:classifiers":[
        {
            "category":"Building & Trades",
            "subcategory":"Landscaping Services",
            "type":"Services"
        }
    ],
    "sg:phone":"+1 512 837 7650",
    "sg:postcode":"78758",
    "sg:province":"TX",
    "sg:tags":[
        "landscape",
        "contractor"
    ],
    "wof:name":"Roving Gardner The",
    "wof:placetype":"venue"
},
  "geometry": {"coordinates":[-97.692741,30.374212],"type":"Point"}
}