{
  "type": "Feature",
  "properties": {
    "iso:country":"US",
    "sg:address":"9786 Hidden Brook",
    "sg:city":"San Antonio",
    "sg:classifiers":[
        {
            "category":"Building & Trades",
            "subcategory":"Cleaning & Sanitation",
            "type":"Services"
        }
    ],
    "sg:phone":"+1 210 521 0900",
    "sg:postcode":"78250",
    "sg:province":"TX",
    "sg:tags":[
        "maintenance"
    ],
    "wof:name":"Wise Choice Building Mntnc",
    "wof:placetype":"venue"
},
  "geometry": {"coordinates":[-98.694384,29.493664],"type":"Point"}
}