{
  "type": "Feature",
  "properties": {
    "iso:country":"US",
    "sg:address":"1722 Heights Blvd",
    "sg:city":"Houston",
    "sg:classifiers":[
        {
            "category":"Professional",
            "subcategory":"Lawyer & Legal Services",
            "type":"Services"
        }
    ],
    "sg:phone":"+1 713 650 6300",
    "sg:postcode":"77008",
    "sg:province":"TX",
    "wof:name":"Firm McLain Law",
    "wof:placetype":"venue"
},
  "geometry": {"coordinates":[-95.39782599999999,29.801713],"type":"Point"}
}