{
  "type": "Feature",
  "properties": {
    "iso:country":"US",
    "sg:address":"4027 Randall Ln",
    "sg:city":"Carrollton",
    "sg:classifiers":[
        {
            "category":"Professional",
            "subcategory":"Business Services",
            "type":"Services"
        }
    ],
    "sg:phone":"+1 972 939 0375",
    "sg:postcode":"75007",
    "sg:province":"TX",
    "wof:name":"Iley Financial Services",
    "wof:placetype":"venue"
},
  "geometry": {"coordinates":[-96.91026599999999,33.02162],"type":"Point"}
}