{
  "type": "Feature",
  "properties": {
    "iso:country":"US",
    "sg:address":"5807 Bus Park",
    "sg:city":"San Antonio",
    "sg:classifiers":[
        {
            "category":"Professional",
            "subcategory":"Business Services",
            "type":"Services"
        }
    ],
    "sg:phone":"+1 210 661 8800",
    "sg:postcode":"78218",
    "sg:province":"TX",
    "sg:tags":[
        "water",
        "treatment"
    ],
    "sg:website":"www.vrtx-technologies.com",
    "wof:name":"Vrtex Technologies",
    "wof:placetype":"venue"
},
  "geometry": {"coordinates":[-98.39346399999999,29.481549],"type":"Point"}
}