{
  "type": "Feature",
  "properties": {
    "iso:country":"US",
    "sg:address":"3200 Guadalupe St",
    "sg:city":"Austin",
    "sg:classifiers":[
        {
            "category":"Personal",
            "subcategory":"Beauty Salon",
            "type":"Services"
        },
        {
            "category":"Personal",
            "subcategory":"Barber",
            "type":"Services"
        }
    ],
    "sg:phone":"+1 512 467 9774",
    "sg:postcode":"78705",
    "sg:province":"TX",
    "sg:website":"http://www.zigzagsalon.com",
    "wof:name":"Zig Zag Salon",
    "wof:placetype":"venue"
},
  "geometry": {"coordinates":[-97.740494,30.29907],"type":"Point"}
}