{
  "type": "Feature",
  "properties": {
    "iso:country":"US",
    "sg:address":"4002 Belt Line Rd",
    "sg:city":"Addison",
    "sg:classifiers":[
        {
            "category":"Restaurant",
            "type":"Food & Drink"
        }
    ],
    "sg:phone":"+1 972 991 6867",
    "sg:postcode":"75001",
    "sg:province":"TX",
    "sg:tags":[
        "eating"
    ],
    "wof:name":"Restaurant Jasmine",
    "wof:placetype":"venue"
},
  "geometry": {"coordinates":[-96.845336,32.954199],"type":"Point"}
}