{
  "type": "Feature",
  "properties": {
    "iso:country":"US",
    "sg:address":"3231 Summerfield Dr",
    "sg:city":"Grapevine",
    "sg:classifiers":[
        {
            "category":"Organizations",
            "subcategory":"Membership Organization",
            "type":"Services"
        }
    ],
    "sg:phone":"+1 817 283 4987",
    "sg:postcode":"76051",
    "sg:province":"TX",
    "wof:name":"Shooting Stars Foundation Inc",
    "wof:placetype":"venue"
},
  "geometry": {"coordinates":[-97.119743,32.888154],"type":"Point"}
}