{
  "type": "Feature",
  "properties": {
    "iso:country":"US",
    "sg:address":"15009 Doria Dr",
    "sg:city":"Austin",
    "sg:classifiers":[
        {
            "category":"Real Estate",
            "subcategory":"Real Estate Agent",
            "type":"Services"
        }
    ],
    "sg:phone":"+1 512 310 0872",
    "sg:postcode":"78728",
    "sg:province":"TX",
    "wof:name":"Schmidt Building LLC",
    "wof:placetype":"venue"
},
  "geometry": {"coordinates":[-97.681997,30.44826],"type":"Point"}
}