{
  "type": "Feature",
  "properties": {
    "iso:country":"US",
    "sg:address":"8203 Bluff Springs Rd",
    "sg:city":"Austin",
    "sg:classifiers":[
        {
            "category":"Building & Trades",
            "subcategory":"Construction",
            "type":"Services"
        }
    ],
    "sg:phone":"+1 512 282 7581",
    "sg:postcode":"78744",
    "sg:province":"TX",
    "sg:tags":[
        "plastering",
        "contractor"
    ],
    "wof:name":"Ridgway Inc",
    "wof:placetype":"venue"
},
  "geometry": {"coordinates":[-97.76880300000001,30.16863],"type":"Point"}
}