{
  "type": "Feature",
  "properties": {
    "iso:country":"US",
    "sg:address":"11317 Alhambra Dr",
    "sg:city":"Austin",
    "sg:classifiers":[
        {
            "category":"Retail",
            "subcategory":"Repair Shop",
            "type":"Services"
        }
    ],
    "sg:phone":"+1 512 338 0085",
    "sg:postcode":"78759",
    "sg:province":"TX",
    "wof:name":"Specialty Time",
    "wof:placetype":"venue"
},
  "geometry": {"coordinates":[-97.738685,30.407424],"type":"Point"}
}