{
  "type": "Feature",
  "properties": {
    "iso:country":"US",
    "sg:address":"3495 Mccann Rd",
    "sg:city":"Longview",
    "sg:classifiers":[
        {
            "category":"Restaurant",
            "type":"Food & Drink"
        }
    ],
    "sg:phone":"+1 903 758 5678",
    "sg:postcode":"75605",
    "sg:province":"TX",
    "wof:name":"Asian Star",
    "wof:placetype":"venue"
},
  "geometry": {"coordinates":[-94.776535,32.575775],"type":"Point"}
}