{
  "type": "Feature",
  "properties": {
    "iso:country":"US",
    "sg:address":"3415 Cartwright Rd",
    "sg:city":"Missouri City",
    "sg:classifiers":[
        {
            "category":"Real Estate",
            "subcategory":"Real Estate Agent",
            "type":"Services"
        }
    ],
    "sg:phone":"+1 281 499 4571",
    "sg:postcode":"77459",
    "sg:province":"TX",
    "wof:name":"Prudential",
    "wof:placetype":"venue"
},
  "geometry": {"coordinates":[-95.55770099999999,29.582606],"type":"Point"}
}