{
  "type": "Feature",
  "properties": {
    "iso:country":"US",
    "sg:address":"51766 Comanche Cir",
    "sg:city":"Killeen",
    "sg:classifiers":[
        {
            "category":"Social Services",
            "subcategory":"Child Care",
            "type":"Services"
        }
    ],
    "sg:phone":"+1 254 501 4494",
    "sg:postcode":"76544",
    "sg:province":"TX",
    "sg:tags":[
        "family"
    ],
    "wof:name":"Galvans Learning Center",
    "wof:placetype":"venue"
},
  "geometry": {"coordinates":[-97.81288600000001,31.139894],"type":"Point"}
}