{
  "type": "Feature",
  "properties": {
    "iso:country":"US",
    "sg:address":"800 E Arapaho Rd",
    "sg:city":"Richardson",
    "sg:classifiers":[
        {
            "category":"Professional",
            "subcategory":"Employment Agencies",
            "type":"Services"
        }
    ],
    "sg:phone":"+1 972 480 8367",
    "sg:postcode":"75081",
    "sg:province":"TX",
    "wof:name":"Advanced Temporaries",
    "wof:placetype":"venue"
},
  "geometry": {"coordinates":[-96.71369900000001,32.960602],"type":"Point"}
}