{
  "type": "Feature",
  "properties": {
    "iso:country":"US",
    "sg:address":"1007 W Bow St",
    "sg:city":"Tyler",
    "sg:classifiers":[
        {
            "category":"Food & Beverages",
            "subcategory":"Groceries & Convenience Stores",
            "type":"Retail Goods"
        }
    ],
    "sg:phone":"+1 903 593 8280",
    "sg:postcode":"75702",
    "sg:province":"TX",
    "wof:name":"D & N Grocery",
    "wof:placetype":"venue"
},
  "geometry": {"coordinates":[-95.31226599999999,32.358413],"type":"Point"}
}