{
  "type": "Feature",
  "properties": {
    "iso:country":"US",
    "sg:address":"2306 Howard Ln",
    "sg:city":"Austin",
    "sg:classifiers":[
        {
            "category":"Building & Trades",
            "subcategory":"Construction",
            "type":"Services"
        },
        {
            "category":"Building & Trades",
            "subcategory":"Electrical",
            "type":"Services"
        },
        {
            "category":"Home & Garden",
            "subcategory":"Household Appliances",
            "type":"Retail Goods"
        },
        {
            "category":"Building & Trades",
            "subcategory":"Plumbing",
            "type":"Services"
        },
        {
            "category":"Home & Garden",
            "subcategory":"Building Materials",
            "type":"Retail Goods"
        },
        {
            "category":"Professional",
            "subcategory":"Engineering",
            "type":"Services"
        },
        {
            "category":"Utilities",
            "subcategory":"Sewage",
            "type":"Services"
        }
    ],
    "sg:phone":"+1 951 234 0780",
    "sg:postcode":"78728",
    "sg:province":"TX",
    "sg:tags":[
        "repair",
        "plumber",
        "industrial",
        "specialty",
        "pump",
        "consultant",
        "cleaning",
        "systems-repairing",
        "system",
        "contractor",
        "equipment",
        "furnaces-heating",
        "drain",
        "contractors-commercial",
        "heating",
        "plumbing-drain",
        "heat",
        "air conditioning",
        "sewer"
    ],
    "sg:website":"http://www.ars.com/ars/redirection.aspx?url=/home.aspx&product=A/C%20Service&partnerName=YellowPages.com&adName=YellPages-3823-ARS&promo=&utm_source=YellowPages&utm_medium=cpc&utm_content=YellowPages_TMP_ARS&utm_campaign=YellPages-3823-ARS",
    "wof:name":"ARS/Rescue Rooter of Austin",
    "wof:placetype":"venue"
},
  "geometry": {"coordinates":[-97.68751399999999,30.435298],"type":"Point"}
}