{
  "type": "Feature",
  "properties": {
    "iso:country":"US",
    "sg:address":"16 FM 1948 W",
    "sg:city":"Brenham",
    "sg:classifiers":[
        {
            "category":"Restaurant",
            "type":"Food & Drink"
        }
    ],
    "sg:phone":"+1 979 277 0720",
    "sg:postcode":"77833",
    "sg:province":"TX",
    "sg:tags":[
        "eating"
    ],
    "wof:name":"The Shack",
    "wof:placetype":"venue"
},
  "geometry": {"coordinates":[-96.505104,30.29809],"type":"Point"}
}