{
  "type": "Feature",
  "properties": {
    "iso:country":"US",
    "sg:address":"2908 Clovermeadow Dr",
    "sg:city":"Fort Worth",
    "sg:classifiers":[
        {
            "category":"Organizations",
            "subcategory":"Religious Organization",
            "type":"Services"
        }
    ],
    "sg:phone":"+1 817 346 3664",
    "sg:postcode":"76123",
    "sg:province":"TX",
    "wof:name":"Kenneth Gossett Etux Cath",
    "wof:placetype":"venue"
},
  "geometry": {"coordinates":[-97.363365,32.631805],"type":"Point"}
}