{
  "type": "Feature",
  "properties": {
    "iso:country":"US",
    "sg:address":"1010 Lamar St",
    "sg:city":"Houston",
    "sg:classifiers":[
        {
            "category":"Professional",
            "subcategory":"Lawyer & Legal Services",
            "type":"Services"
        }
    ],
    "sg:phone":"+1 713 522 6454",
    "sg:postcode":"77002",
    "sg:province":"TX",
    "sg:tags":[
        "attorney"
    ],
    "wof:name":"Carver L Henry & Assoc",
    "wof:placetype":"venue"
},
  "geometry": {"coordinates":[-95.36475799999999,29.755681],"type":"Point"}
}