{
  "type": "Feature",
  "properties": {
    "iso:country":"US",
    "sg:address":"7820 Summerglen Rd",
    "sg:city":"Fort Worth",
    "sg:classifiers":[
        {
            "category":"Professional",
            "subcategory":"Business Services",
            "type":"Services"
        }
    ],
    "sg:phone":"+1 817 294 2836",
    "sg:postcode":"76133",
    "sg:province":"TX",
    "wof:name":"Wolfes Inspection Service",
    "wof:placetype":"venue"
},
  "geometry": {"coordinates":[-97.38439099999999,32.629215],"type":"Point"}
}