{
  "type": "Feature",
  "properties": {
    "iso:country":"US",
    "sg:address":"2018 Menefee St",
    "sg:city":"Arlington",
    "sg:classifiers":[
        {
            "category":"Government",
            "subcategory":"Office",
            "type":"Public Place"
        }
    ],
    "sg:phone":"+1 817 277 2721",
    "sg:postcode":"76010",
    "sg:province":"TX",
    "sg:tags":[
        "sector",
        "regulation",
        "commercial"
    ],
    "wof:name":"R&P Specialties",
    "wof:placetype":"venue"
},
  "geometry": {"coordinates":[-97.078537,32.732909],"type":"Point"}
}