{
  "type": "Feature",
  "properties": {
    "iso:country":"US",
    "sg:address":"910 E Ave H",
    "sg:city":"Belton",
    "sg:classifiers":[
        {
            "category":"Building & Trades",
            "subcategory":"Electrical",
            "type":"Services"
        }
    ],
    "sg:phone":"+1 254 939 6686",
    "sg:postcode":"76513",
    "sg:province":"TX",
    "sg:tags":[
        "electric",
        "contractor"
    ],
    "wof:name":"Baird & Hunter Electric",
    "wof:placetype":"venue"
},
  "geometry": {"coordinates":[-97.45913299999999,31.047546],"type":"Point"}
}