{
  "type": "Feature",
  "properties": {
    "iso:country":"US",
    "sg:address":"3399 Peterson Rd S",
    "sg:city":"Iowa Park",
    "sg:classifiers":[
        {
            "category":"Manufacturing",
            "subcategory":"Food",
            "type":"Manufacturing & Wholesale Goods"
        },
        {
            "category":"Food & Beverages",
            "subcategory":"Liquor & Beverages",
            "type":"Retail Goods"
        }
    ],
    "sg:phone":"+1 940 855 1137",
    "sg:postcode":"76367",
    "sg:province":"TX",
    "sg:tags":[
        "winery",
        "alcoholic"
    ],
    "wof:name":"Wichita Falls Vineyards & Wine",
    "wof:placetype":"venue"
},
  "geometry": {"coordinates":[-98.629975,33.905735],"type":"Point"}
}