{
  "type": "Feature",
  "properties": {
    "iso:country":"US",
    "sg:address":"4527 E US Hwy 84",
    "sg:city":"Gatesville",
    "sg:classifiers":[
        {
            "category":"Personal",
            "type":"Services"
        }
    ],
    "sg:phone":"+1 254 865 9001",
    "sg:postcode":"76528",
    "sg:province":"TX",
    "wof:name":"Wedding Mansion",
    "wof:placetype":"venue"
},
  "geometry": {"coordinates":[-97.691524,31.42737],"type":"Point"}
}