{
  "type": "Feature",
  "properties": {
    "iso:country":"US",
    "sg:address":"8209 Burnet Rd",
    "sg:city":"Austin",
    "sg:classifiers":[
        {
            "category":"Real Estate",
            "subcategory":"Real Estate Agent",
            "type":"Services"
        }
    ],
    "sg:phone":"+1 512 467 9888",
    "sg:postcode":"78757",
    "sg:province":"TX",
    "wof:name":"Baizer Properties Innc",
    "wof:placetype":"venue"
},
  "geometry": {"coordinates":[-97.72960999999999,30.360251],"type":"Point"}
}