{
  "type": "Feature",
  "properties": {
    "iso:country":"US",
    "sg:address":"1 Sheldon Rd",
    "sg:city":"Channelview",
    "sg:classifiers":[
        {
            "category":"Organizations",
            "subcategory":"Religious Organization",
            "type":"Services"
        }
    ],
    "sg:phone":"+1 281 452 0700",
    "sg:postcode":"77530",
    "sg:province":"TX",
    "sg:tags":[
        "clergy"
    ],
    "wof:name":"Jerry M Horning",
    "wof:placetype":"venue"
},
  "geometry": {"coordinates":[-95.12390499999999,29.750614],"type":"Point"}
}