{
  "type": "Feature",
  "properties": {
    "iso:country":"US",
    "sg:address":"5601 Bryant Irvin Rd",
    "sg:city":"Fort Worth",
    "sg:classifiers":[
        {
            "category":"Building & Trades",
            "subcategory":"Construction",
            "type":"Services"
        }
    ],
    "sg:phone":"+1 817 346 2168",
    "sg:postcode":"76132",
    "sg:province":"TX",
    "sg:tags":[
        "general",
        "contractor"
    ],
    "wof:name":"Gamma Construction",
    "wof:placetype":"venue"
},
  "geometry": {"coordinates":[-97.419506,32.66892],"type":"Point"}
}