{
  "type": "Feature",
  "properties": {
    "iso:country":"US",
    "sg:address":"302 Variah St",
    "sg:city":"Palestine",
    "sg:classifiers":[
        {
            "category":"Building & Trades",
            "subcategory":"Construction",
            "type":"Services"
        }
    ],
    "sg:phone":"+1 903 723 5278",
    "sg:postcode":"75803",
    "sg:province":"TX",
    "sg:tags":[
        "house"
    ],
    "wof:name":"Mason Cemetery Improvement",
    "wof:placetype":"venue"
},
  "geometry": {"coordinates":[-95.650299,31.754284],"type":"Point"}
}