{
  "type": "Feature",
  "properties": {
    "iso:country":"US",
    "sg:address":"1714 Berkoff Dr",
    "sg:city":"Sugar Land",
    "sg:classifiers":[
        {
            "category":"Professional",
            "subcategory":"Accounting & Tax Preparation",
            "type":"Services"
        }
    ],
    "sg:phone":"+1 281 565 3751",
    "sg:postcode":"77479",
    "sg:province":"TX",
    "sg:tags":[
        "accountant"
    ],
    "wof:name":"Mani P Alapat",
    "wof:placetype":"venue"
},
  "geometry": {"coordinates":[-95.665012,29.585234],"type":"Point"}
}