{
  "type": "Feature",
  "properties": {
    "iso:country":"US",
    "sg:address":"716 Spring Hollow Dr",
    "sg:city":"Leander",
    "sg:classifiers":[
        {
            "category":"Retail",
            "subcategory":"Portrait Studio",
            "type":"Services"
        }
    ],
    "sg:phone":"+1 512 259 4503",
    "sg:postcode":"78641",
    "sg:province":"TX",
    "sg:tags":[
        "photo"
    ],
    "wof:name":"Action Youth Sports Photograph",
    "wof:placetype":"venue"
},
  "geometry": {"coordinates":[-97.838025,30.563755],"type":"Point"}
}