{
  "type": "Feature",
  "properties": {
    "iso:country":"US",
    "sg:address":"1408 9th St",
    "sg:city":"Dickinson",
    "sg:classifiers":[
        {
            "category":"Manufacturing",
            "subcategory":"Signs",
            "type":"Manufacturing & Wholesale Goods"
        }
    ],
    "sg:phone":"+1 281 339 6400",
    "sg:postcode":"77539",
    "sg:province":"TX",
    "sg:tags":[
        "specialty",
        "mfg"
    ],
    "wof:name":"Bay Area Signery",
    "wof:placetype":"venue"
},
  "geometry": {"coordinates":[-94.925692,29.473248],"type":"Point"}
}