{
  "type": "Feature",
  "properties": {
    "iso:country":"US",
    "sg:address":"3136 Routh St",
    "sg:city":"Dallas",
    "sg:classifiers":[
        {
            "category":"Professional",
            "subcategory":"Business Services",
            "type":"Services"
        }
    ],
    "sg:phone":"+1 214 754 9977",
    "sg:postcode":"75201",
    "sg:province":"TX",
    "sg:tags":[
        "embroidery"
    ],
    "sg:website":"www.gfinelogo.com",
    "wof:name":"GFINELOGO.COM",
    "wof:placetype":"venue"
},
  "geometry": {"coordinates":[-96.807334,32.801325],"type":"Point"}
}