{
  "type": "Feature",
  "properties": {
    "iso:country":"US",
    "sg:address":"3098 N Eastman Rd",
    "sg:city":"Longview",
    "sg:classifiers":[
        {
            "category":"Real Estate",
            "subcategory":"Developer",
            "type":"Services"
        }
    ],
    "sg:phone":"+1 903 663 4433",
    "sg:postcode":"75605",
    "sg:province":"TX",
    "wof:name":"Weber & Company",
    "wof:placetype":"venue"
},
  "geometry": {"coordinates":[-94.72307600000001,32.534585],"type":"Point"}
}