{
  "type": "Feature",
  "properties": {
    "iso:country":"US",
    "sg:address":"23780 Loop 494",
    "sg:city":"Porter",
    "sg:classifiers":[
        {
            "category":"Restaurant",
            "type":"Food & Drink"
        }
    ],
    "sg:menulink":"http://www.allmenus.com/tx/southeast-montgomery/94457-dominos-pizza/menu/",
    "sg:phone":"+1 281 354 1213",
    "sg:postcode":"77365",
    "sg:province":"TX",
    "sg:tags":[
        "american",
        "wing",
        "pizza"
    ],
    "wof:name":"Domino's Pizza",
    "wof:placetype":"venue"
},
  "geometry": {"coordinates":[-95.23018500000001,30.101559],"type":"Point"}
}