{
  "type": "Feature",
  "properties": {
    "iso:country":"US",
    "sg:address":"6201 Liberty Rd",
    "sg:city":"Houston",
    "sg:classifiers":[
        {
            "category":"Retail",
            "subcategory":"Repair Shop",
            "type":"Services"
        }
    ],
    "sg:phone":"+1 713 674 6475",
    "sg:postcode":"77026",
    "sg:province":"TX",
    "sg:tags":[
        "furniture"
    ],
    "wof:name":"Custom Furniture Shop",
    "wof:placetype":"venue"
},
  "geometry": {"coordinates":[-95.30649099999999,29.791915],"type":"Point"}
}