{
  "type": "Feature",
  "properties": {
    "iso:country":"US",
    "sg:address":"284 Co Rd 137",
    "sg:city":"Alice",
    "sg:classifiers":[
        {
            "category":"Building & Trades",
            "subcategory":"Construction",
            "type":"Services"
        }
    ],
    "sg:phone":"+1 361 664 0220",
    "sg:postcode":"78332",
    "sg:province":"TX",
    "sg:tags":[
        "roofing",
        "contractor"
    ],
    "wof:name":"Oscar's Roofing Inc",
    "wof:placetype":"venue"
},
  "geometry": {"coordinates":[-98.14619999999999,27.744297],"type":"Point"}
}