{
  "type": "Feature",
  "properties": {
    "iso:country":"US",
    "sg:address":"2951 Marina Bay Dr",
    "sg:city":"League City",
    "sg:classifiers":[
        {
            "category":"Professional",
            "subcategory":"Computer Services",
            "type":"Services"
        }
    ],
    "sg:phone":"+1 409 789 2336",
    "sg:postcode":"77573",
    "sg:province":"TX",
    "sg:tags":[
        "programming",
        "software"
    ],
    "wof:name":"Scientific Simulation Inc",
    "wof:placetype":"venue"
},
  "geometry": {"coordinates":[-95.064081,29.539925],"type":"Point"}
}