{
  "type": "Feature",
  "properties": {
    "iso:country":"US",
    "sg:address":"3545 Gilmer Rd",
    "sg:city":"Longview",
    "sg:classifiers":[
        {
            "category":"Building & Trades",
            "subcategory":"Construction",
            "type":"Services"
        }
    ],
    "sg:phone":"+1 903 297 0040",
    "sg:postcode":"75604",
    "sg:province":"TX",
    "sg:tags":[
        "house"
    ],
    "wof:name":"Prestige Builders",
    "wof:placetype":"venue"
},
  "geometry": {"coordinates":[-94.799454,32.550323],"type":"Point"}
}