{
  "type": "Feature",
  "properties": {
    "iso:country":"US",
    "sg:address":"5943 Crooked Post Rd",
    "sg:city":"Spring",
    "sg:classifiers":[
        {
            "category":"Building & Trades",
            "subcategory":"Electrical",
            "type":"Services"
        }
    ],
    "sg:phone":"+1 281 443 6569",
    "sg:postcode":"77373",
    "sg:province":"TX",
    "sg:tags":[
        "electrician",
        "contractor"
    ],
    "wof:name":"D & R Electrics",
    "wof:placetype":"venue"
},
  "geometry": {"coordinates":[-95.344618,30.051785],"type":"Point"}
}