{
  "type": "Feature",
  "properties": {
    "iso:country":"US",
    "sg:address":"1640 Sam Houston Pkwy",
    "sg:city":"Houston",
    "sg:classifiers":[
        {
            "category":"Manufacturing",
            "subcategory":"Printing",
            "type":"Manufacturing & Wholesale Goods"
        }
    ],
    "sg:phone":"+1 713 365 0506",
    "sg:postcode":"77015",
    "sg:province":"TX",
    "sg:tags":[
        "printer"
    ],
    "wof:name":"Imaging Systems Group",
    "wof:placetype":"venue"
},
  "geometry": {"coordinates":[-95.14560899999999,29.746252],"type":"Point"}
}