{
  "type": "Feature",
  "properties": {
    "iso:country":"US",
    "sg:address":"310 E Crawford St",
    "sg:city":"Palestine",
    "sg:classifiers":[
        {
            "category":"Recreation",
            "type":"Entertainment"
        }
    ],
    "sg:phone":"+1 903 727 2700",
    "sg:postcode":"75801",
    "sg:province":"TX",
    "sg:tags":[
        "club",
        "membership"
    ],
    "wof:name":"Shelton Hall",
    "wof:placetype":"venue"
},
  "geometry": {"coordinates":[-95.628373,31.764357],"type":"Point"}
}