{
  "type": "Feature",
  "properties": {
    "iso:country":"US",
    "sg:address":"1720 E Nasa Pkwy",
    "sg:city":"Houston",
    "sg:classifiers":[
        {
            "category":"Real Estate",
            "subcategory":"Real Estate Agent",
            "type":"Services"
        }
    ],
    "sg:phone":"+1 281 336 2243",
    "sg:postcode":"77058",
    "sg:province":"TX",
    "sg:tags":[
        "agency"
    ],
    "wof:name":"Re/Max",
    "wof:placetype":"venue"
},
  "geometry": {"coordinates":[-95.094386,29.549884],"type":"Point"}
}