{
  "type": "Feature",
  "properties": {
    "iso:country":"US",
    "sg:address":"313 Lakeview Dr",
    "sg:city":"Bridgeport",
    "sg:classifiers":[
        {
            "category":"Mining & Drilling",
            "type":"Manufacturing & Wholesale Goods"
        }
    ],
    "sg:phone":"+1 940 575 2391",
    "sg:postcode":"76426",
    "sg:province":"TX",
    "sg:tags":[
        "field"
    ],
    "wof:name":"Almar Production Co Inc",
    "wof:placetype":"venue"
},
  "geometry": {"coordinates":[-97.876566,33.169291],"type":"Point"}
}