{
  "type": "Feature",
  "properties": {
    "iso:country":"US",
    "sg:address":"12325 Hymeadow Dr",
    "sg:city":"Austin",
    "sg:classifiers":[
        {
            "category":"Shopping",
            "subcategory":"Computers & Home Electronics",
            "type":"Retail Goods"
        }
    ],
    "sg:phone":"+1 512 418 0231",
    "sg:postcode":"78750",
    "sg:province":"TX",
    "sg:tags":[
        "equipment",
        "electronic",
        "supply"
    ],
    "wof:name":"Edoc Technologies",
    "wof:placetype":"venue"
},
  "geometry": {"coordinates":[-97.797273,30.454167],"type":"Point"}
}