{
  "type": "Feature",
  "properties": {
    "iso:country":"US",
    "sg:address":"5519 W Hillside Dr",
    "sg:city":"Houston",
    "sg:classifiers":[
        {
            "category":"Autos & Motor Vehicles",
            "subcategory":"Auto Supplies",
            "type":"Retail Goods"
        }
    ],
    "sg:phone":"+1 281 219 2943",
    "sg:postcode":"77039",
    "sg:province":"TX",
    "wof:name":"Q Truck & Auto Parts LLC",
    "wof:placetype":"venue"
},
  "geometry": {"coordinates":[-95.306876,29.91492],"type":"Point"}
}