{
  "type": "Feature",
  "properties": {
    "iso:country":"US",
    "sg:address":"730 N. Post Oak Rd. Suite 201",
    "sg:city":"Houston",
    "sg:classifiers":[
        {
            "category":"Professional",
            "subcategory":"Lawyer & Legal Services",
            "type":"Services"
        }
    ],
    "sg:phone":"+1 713 956 9646",
    "sg:postcode":"77024",
    "sg:province":"TX",
    "sg:tags":[
        "personal",
        "injury"
    ],
    "wof:name":"Law Offices Of Rick McGuire-PI",
    "wof:placetype":"venue"
},
  "geometry": {"coordinates":[-95.456146,29.780817],"type":"Point"}
}