{
  "type": "Feature",
  "properties": {
    "iso:country":"US",
    "sg:address":"300 N 8th St",
    "sg:city":"Midlothian",
    "sg:classifiers":[
        {
            "category":"Professional",
            "subcategory":"Engineering",
            "type":"Services"
        },
        {
            "category":"Professional",
            "subcategory":"Research",
            "type":"Services"
        }
    ],
    "sg:phone":"+1 972 723 9509",
    "sg:postcode":"76065",
    "sg:province":"TX",
    "sg:tags":[
        "environmental",
        "ecological"
    ],
    "wof:name":"Compliance Partners Inc",
    "wof:placetype":"venue"
},
  "geometry": {"coordinates":[-96.994518,32.484287],"type":"Point"}
}