{
  "type": "Feature",
  "properties": {
    "iso:country":"US",
    "sg:address":"5031 Bayou Vista Dr",
    "sg:city":"Houston",
    "sg:classifiers":[
        {
            "category":"Professional",
            "subcategory":"Computer Services",
            "type":"Services"
        }
    ],
    "sg:phone":"+1 713 688 3727",
    "sg:postcode":"77091",
    "sg:province":"TX",
    "sg:tags":[
        "related"
    ],
    "wof:name":"Robert T Fleming Inc",
    "wof:placetype":"venue"
},
  "geometry": {"coordinates":[-95.46869700000001,29.848302],"type":"Point"}
}