{
  "type": "Feature",
  "properties": {
    "iso:country":"US",
    "sg:address":"5116 Timber Park Dr",
    "sg:city":"Flower Mound",
    "sg:classifiers":[
        {
            "category":"Real Estate",
            "subcategory":"Real Estate Agent",
            "type":"Services"
        }
    ],
    "sg:phone":"+1 972 724 0018",
    "sg:postcode":"75028",
    "sg:province":"TX",
    "wof:name":"Emilie Frantz & Associates",
    "wof:placetype":"venue"
},
  "geometry": {"coordinates":[-97.069638,33.05524],"type":"Point"}
}