{
  "type": "Feature",
  "properties": {
    "iso:country":"US",
    "sg:address":"131 E Candlestick Dr",
    "sg:city":"Lumberton",
    "sg:classifiers":[
        {
            "category":"Wholesale",
            "subcategory":"Groceries",
            "type":"Manufacturing & Wholesale Goods"
        }
    ],
    "sg:phone":"+1 409 755 2133",
    "sg:postcode":"77657",
    "sg:province":"TX",
    "sg:tags":[
        "food"
    ],
    "wof:name":"Guardian Angel Health Products",
    "wof:placetype":"venue"
},
  "geometry": {"coordinates":[-94.19738599999999,30.256121],"type":"Point"}
}