{
  "type": "Feature",
  "properties": {
    "iso:country":"US",
    "sg:address":"10200 Mc Kalla Pl",
    "sg:city":"Austin",
    "sg:classifiers":[
        {
            "category":"Freight",
            "type":"Transportation"
        }
    ],
    "sg:phone":"+1 512 339 3728",
    "sg:postcode":"78758",
    "sg:province":"TX",
    "sg:tags":[
        "cartage",
        "trucking"
    ],
    "sg:website":"www.firstair.com",
    "wof:name":"Bison Warehouse",
    "wof:placetype":"venue"
},
  "geometry": {"coordinates":[-97.720268,30.383139],"type":"Point"}
}