{
  "type": "Feature",
  "properties": {
    "iso:country":"US",
    "sg:address":"6023 Annapolis St",
    "sg:city":"Houston",
    "sg:classifiers":[
        {
            "category":"Health Services",
            "subcategory":"Doctor",
            "type":"Services"
        }
    ],
    "sg:phone":"+1 713 669 0290",
    "sg:postcode":"77005",
    "sg:province":"TX",
    "wof:name":"Schwartz Sidney DDS Inc",
    "wof:placetype":"venue"
},
  "geometry": {"coordinates":[-95.42078600000001,29.718573],"type":"Point"}
}