{
  "type": "Feature",
  "properties": {
    "iso:country":"US",
    "sg:address":"702 Lyons Ave",
    "sg:city":"Schulenburg",
    "sg:classifiers":[
        {
            "category":"Real Estate",
            "subcategory":"Real Estate Agent",
            "type":"Services"
        }
    ],
    "sg:phone":"+1 979 743 3017",
    "sg:postcode":"78956",
    "sg:province":"TX",
    "wof:name":"Town Square Realty",
    "wof:placetype":"venue"
},
  "geometry": {"coordinates":[-96.904782,29.680958],"type":"Point"}
}