{
  "type": "Feature",
  "properties": {
    "iso:country":"US",
    "sg:address":"17304 Preston Rd",
    "sg:city":"Dallas",
    "sg:classifiers":[
        {
            "category":"Shopping",
            "subcategory":"Jewelry",
            "type":"Retail Goods"
        }
    ],
    "sg:phone":"+1 972 407 1200",
    "sg:postcode":"75252",
    "sg:province":"TX",
    "wof:name":"Miles Goldberg Wholesale Jewelry Co",
    "wof:placetype":"venue"
},
  "geometry": {"coordinates":[-96.789101,33.002701],"type":"Point"}
}