{
  "type": "Feature",
  "properties": {
    "iso:country":"US",
    "sg:address":"12125 Bammel North Houston Rd",
    "sg:city":"Houston",
    "sg:classifiers":[
        {
            "category":"Autos & Motor Vehicles",
            "subcategory":"Auto Supplies",
            "type":"Retail Goods"
        },
        {
            "category":"Retail",
            "subcategory":"Auto Repair",
            "type":"Services"
        }
    ],
    "sg:phone":"+1 281 895 7500",
    "sg:postcode":"77066",
    "sg:province":"TX",
    "sg:tags":[
        "tire"
    ],
    "wof:name":"Champion Point Auto Center",
    "wof:placetype":"venue"
},
  "geometry": {"coordinates":[-95.498395,29.953611],"type":"Point"}
}