{
  "type": "Feature",
  "properties": {
    "iso:country":"US",
    "sg:address":"5510 Abrams Rd",
    "sg:city":"Dallas",
    "sg:classifiers":[
        {
            "category":"Health Services",
            "subcategory":"Doctor",
            "type":"Services"
        },
        {
            "category":"Health Services",
            "subcategory":"Dentist",
            "type":"Services"
        }
    ],
    "sg:phone":"+1 214 368 2080",
    "sg:postcode":"75214",
    "sg:province":"TX",
    "sg:tags":[
        "surgeon",
        "oral",
        "cosmetic"
    ],
    "sg:website":"www.75214dentist.com",
    "wof:name":"Steven B. Taylor, DDS",
    "wof:placetype":"venue"
},
  "geometry": {"coordinates":[-96.751643,32.853421],"type":"Point"}
}