{
  "type": "Feature",
  "properties": {
    "iso:country":"US",
    "sg:address":"305 Washington St",
    "sg:city":"Kerrville",
    "sg:classifiers":[
        {
            "category":"Arts & Performance",
            "subcategory":"Theater",
            "type":"Entertainment"
        }
    ],
    "sg:phone":"+1 830 896 9393",
    "sg:postcode":"78028",
    "sg:province":"TX",
    "sg:tags":[
        "theatrical"
    ],
    "wof:name":"Playhouse 2000",
    "wof:placetype":"venue"
},
  "geometry": {"coordinates":[-99.137292,30.046472],"type":"Point"}
}