{
  "type": "Feature",
  "properties": {
    "iso:country":"US",
    "sg:address":"7654 Ronnie Dr",
    "sg:city":"Dallas",
    "sg:classifiers":[
        {
            "category":"Retail",
            "subcategory":"Laundry & Dry Cleaning",
            "type":"Services"
        }
    ],
    "sg:phone":"+1 214 707 9072",
    "sg:postcode":"75252",
    "sg:province":"TX",
    "wof:name":"All American Maintenance",
    "wof:placetype":"venue"
},
  "geometry": {"coordinates":[-96.77639600000001,32.989611],"type":"Point"}
}