{
  "type": "Feature",
  "properties": {
    "iso:country":"US",
    "sg:address":"4420 Atlanta Dr",
    "sg:city":"Plano",
    "sg:classifiers":[
        {
            "category":"Banks & Credit Unions",
            "subcategory":"Investment Brokerage",
            "type":"Services"
        }
    ],
    "sg:phone":"+1 469 361 2210",
    "sg:postcode":"75093",
    "sg:province":"TX",
    "sg:tags":[
        "advisory"
    ],
    "wof:name":"Kocama Inc",
    "wof:placetype":"venue"
},
  "geometry": {"coordinates":[-96.779878,33.02624],"type":"Point"}
}