{
  "type": "Feature",
  "properties": {
    "iso:country":"US",
    "sg:address":"6515 Williams School Ct",
    "sg:city":"Needville",
    "sg:phone":"+1 979 793 6562",
    "sg:postcode":"77461",
    "sg:province":"TX",
    "sg:tags":[
        "farm",
        "grain",
        "cash"
    ],
    "wof:name":"R Ellerman",
    "wof:placetype":"venue"
},
  "geometry": {"coordinates":[-95.840779,29.431537],"type":"Point"}
}