{
  "type": "Feature",
  "properties": {
    "iso:country":"US",
    "sg:address":"8553 Ferguson Rd",
    "sg:city":"Dallas",
    "sg:classifiers":[
        {
            "category":"Personal",
            "subcategory":"Beauty Salon",
            "type":"Services"
        }
    ],
    "sg:phone":"+1 214 320 2100",
    "sg:postcode":"75228",
    "sg:province":"TX",
    "wof:name":"Unique X Pressions",
    "wof:placetype":"venue"
},
  "geometry": {"coordinates":[-96.701905,32.811679],"type":"Point"}
}