{
  "type": "Feature",
  "properties": {
    "iso:country":"US",
    "sg:address":"2130 Quincy St",
    "sg:city":"Dallas",
    "sg:classifiers":[
        {
            "category":"Professional",
            "type":"Services"
        }
    ],
    "sg:phone":"+1 972 910 9988",
    "sg:postcode":"75212",
    "sg:province":"TX",
    "sg:tags":[
        "establishment"
    ],
    "wof:name":"Post International Group Inc",
    "wof:placetype":"venue"
},
  "geometry": {"coordinates":[-96.918207,32.76875],"type":"Point"}
}