{
  "type": "Feature",
  "properties": {
    "iso:country":"US",
    "sg:address":"2786 Tallowood Dr",
    "sg:city":"League City",
    "sg:classifiers":[
        {
            "category":"Professional",
            "type":"Services"
        }
    ],
    "sg:phone":"+1 281 334 0346",
    "sg:postcode":"77573",
    "sg:province":"TX",
    "wof:name":"D&L Judgment Recovery Inc",
    "wof:placetype":"venue"
},
  "geometry": {"coordinates":[-95.05837699999999,29.523718],"type":"Point"}
}