{
  "type": "Feature",
  "properties": {
    "iso:country":"US",
    "sg:address":"5001 N Piedras St",
    "sg:city":"El Paso",
    "sg:classifiers":[
        {
            "category":"Health Services",
            "subcategory":"Doctor",
            "type":"Services"
        }
    ],
    "sg:phone":"+1 915 569 2288",
    "sg:postcode":"79930",
    "sg:province":"TX",
    "sg:tags":[
        "physician",
        "surgeon"
    ],
    "wof:name":"Veterans Administration",
    "wof:placetype":"venue"
},
  "geometry": {"coordinates":[-106.461489,31.822457],"type":"Point"}
}