{
  "type": "Feature",
  "properties": {
    "iso:country":"US",
    "sg:address":"2720 Safari Cir",
    "sg:city":"Plano",
    "sg:classifiers":[
        {
            "category":"Professional",
            "subcategory":"Business Services",
            "type":"Services"
        }
    ],
    "sg:phone":"+1 972 312 9561",
    "sg:postcode":"75025",
    "sg:province":"TX",
    "sg:tags":[
        "product",
        "mfg"
    ],
    "wof:name":"E Distributions",
    "wof:placetype":"venue"
},
  "geometry": {"coordinates":[-96.74621500000001,33.073856],"type":"Point"}
}