{
  "type": "Feature",
  "properties": {
    "iso:country":"US",
    "sg:address":"3101 Hobbs Rd",
    "sg:city":"Amarillo",
    "sg:classifiers":[
        {
            "category":"Professional",
            "subcategory":"Employment Agencies",
            "type":"Services"
        }
    ],
    "sg:phone":"+1 806 358 7300",
    "sg:postcode":"79109",
    "sg:province":"TX",
    "wof:name":"Nursecore Of Amarillo",
    "wof:placetype":"venue"
},
  "geometry": {"coordinates":[-101.88176,35.182049],"type":"Point"}
}