{
  "type": "Feature",
  "properties": {
    "iso:country":"US",
    "sg:address":"215 Mary Ave",
    "sg:city":"Waco",
    "sg:classifiers":[
        {
            "category":"Professional",
            "subcategory":"Lawyer & Legal Services",
            "type":"Services"
        }
    ],
    "sg:phone":"+1 254 753 4970",
    "sg:postcode":"76701",
    "sg:province":"TX",
    "sg:tags":[
        "attorney"
    ],
    "wof:name":"Fee Smith Sharp & Vitullo",
    "wof:placetype":"venue"
},
  "geometry": {"coordinates":[-97.127978,31.556959],"type":"Point"}
}