{
  "type": "Feature",
  "properties": {
    "iso:country":"US",
    "sg:address":"2815 Fruth St",
    "sg:city":"Austin",
    "sg:classifiers":[
        {
            "category":"Wholesale",
            "subcategory":"Sporting Goods",
            "type":"Manufacturing & Wholesale Goods"
        },
        {
            "category":"Shopping",
            "subcategory":"Bicycles & Sporting Goods",
            "type":"Retail Goods"
        }
    ],
    "sg:phone":"+1 512 472 9253",
    "sg:postcode":"78705",
    "sg:province":"TX",
    "sg:tags":[
        "security",
        "bike",
        "system",
        "rack"
    ],
    "wof:name":"Waterloo Cycles",
    "wof:placetype":"venue"
},
  "geometry": {"coordinates":[-97.742203,30.294399],"type":"Point"}
}