{
  "type": "Feature",
  "properties": {
    "iso:country":"US",
    "sg:address":"2306 E Main St",
    "sg:city":"Grand Prairie",
    "sg:classifiers":[
        {
            "category":"Autos & Motor Vehicles",
            "subcategory":"Automobile Sales",
            "type":"Retail Goods"
        }
    ],
    "sg:phone":"+1 972 266 0229",
    "sg:postcode":"75050",
    "sg:province":"TX",
    "sg:tags":[
        "car",
        "dealer"
    ],
    "wof:name":"Gomez Auto Sales & Repair",
    "wof:placetype":"venue"
},
  "geometry": {"coordinates":[-96.97080699999999,32.749447],"type":"Point"}
}