{
  "type": "Feature",
  "properties": {
    "iso:country":"US",
    "sg:address":"11450 Audelia Rd",
    "sg:city":"Dallas",
    "sg:classifiers":[
        {
            "category":"Building & Trades",
            "subcategory":"Plumbing",
            "type":"Services"
        }
    ],
    "sg:phone":"+1 214 503 9066",
    "sg:postcode":"75243",
    "sg:province":"TX",
    "sg:tags":[
        "product",
        "management",
        "energy",
        "system"
    ],
    "wof:name":"Commercial Energy Group",
    "wof:placetype":"venue"
},
  "geometry": {"coordinates":[-96.717201,32.90141],"type":"Point"}
}