{
  "type": "Feature",
  "properties": {
    "iso:country":"US",
    "sg:address":"815 Brazos St",
    "sg:city":"Austin",
    "sg:classifiers":[
        {
            "category":"Utilities",
            "subcategory":"Telephone",
            "type":"Services"
        }
    ],
    "sg:phone":"+1 512 479 0317",
    "sg:postcode":"78701",
    "sg:province":"TX",
    "sg:tags":[
        "communications"
    ],
    "wof:name":"Wifi Texascom Inc",
    "wof:placetype":"venue"
},
  "geometry": {"coordinates":[-97.740398,30.270313],"type":"Point"}
}