{
  "type": "Feature",
  "properties": {
    "iso:country":"US",
    "sg:address":"16001 Dallas Pkwy",
    "sg:city":"Addison",
    "sg:classifiers":[
        {
            "category":"Banks & Credit Unions",
            "subcategory":"Bank",
            "type":"Services"
        }
    ],
    "sg:phone":"+1 469 201 7025",
    "sg:postcode":"75001",
    "sg:province":"TX",
    "wof:name":"Bank of America",
    "wof:placetype":"venue"
},
  "geometry": {"coordinates":[-96.821928,32.967389],"type":"Point"}
}