{
  "type": "Feature",
  "properties": {
    "iso:country":"US",
    "sg:address":"201 West X Street",
    "sg:city":"Deer Park",
    "sg:classifiers":[
        {
            "category":"Travel",
            "subcategory":"Hotels & Motels",
            "type":"Entertainment"
        },
        {
            "category":"Retail",
            "subcategory":"Event Space",
            "type":"Services"
        }
    ],
    "sg:phone":"+1 281 479 9888",
    "sg:postcode":"77536",
    "sg:province":"TX",
    "sg:tags":[
        "venue"
    ],
    "sg:website":"www.holidayinnexpress.com",
    "wof:name":"Holiday Inn Express Hotel & Suites Deer Park",
    "wof:placetype":"venue"
},
  "geometry": {"coordinates":[-95.125146,29.695192],"type":"Point"}
}