{
  "type": "Feature",
  "properties": {
    "iso:country":"US",
    "sg:address":"7601 Clara Marie Cove",
    "sg:city":"Austin",
    "sg:classifiers":[
        {
            "category":"Building & Trades",
            "subcategory":"Cleaning & Sanitation",
            "type":"Services"
        }
    ],
    "sg:phone":"+1 512 426 5906",
    "sg:postcode":"78749",
    "sg:province":"TX",
    "sg:tags":[
        "maintenance"
    ],
    "wof:name":"Higher Hands",
    "wof:placetype":"venue"
},
  "geometry": {"coordinates":[-97.87796,30.226125],"type":"Point"}
}