{
  "type": "Feature",
  "properties": {
    "iso:country":"US",
    "sg:address":"619 S Staples St",
    "sg:city":"Corpus Christi",
    "sg:classifiers":[
        {
            "category":"Social Services",
            "subcategory":"Adult Care",
            "type":"Services"
        }
    ],
    "sg:phone":"+1 361 888 6232",
    "sg:postcode":"78401",
    "sg:province":"TX",
    "sg:tags":[
        "day"
    ],
    "wof:name":"National Adult Daycare Inc",
    "wof:placetype":"venue"
},
  "geometry": {"coordinates":[-97.40211600000001,27.784449],"type":"Point"}
}