{
  "type": "Feature",
  "properties": {
    "iso:country":"US",
    "sg:address":"3737 W Lake Houston Pkwy",
    "sg:city":"Humble",
    "sg:classifiers":[
        {
            "category":"Organizations",
            "subcategory":"Religious Organization",
            "type":"Services"
        }
    ],
    "sg:phone":"+1 281 360 8486",
    "sg:postcode":"77339",
    "sg:province":"TX",
    "wof:name":"Christs Church In Kingwood",
    "wof:placetype":"venue"
},
  "geometry": {"coordinates":[-95.18740699999999,30.064702],"type":"Point"}
}