{
  "type": "Feature",
  "properties": {
    "iso:country":"US",
    "sg:address":"5224 Co Rd 417",
    "sg:city":"Cleburne",
    "sg:classifiers":[
        {
            "category":"Retail",
            "subcategory":"Animal Services",
            "type":"Services"
        }
    ],
    "sg:phone":"+1 817 202 8335",
    "sg:postcode":"76031",
    "sg:province":"TX",
    "sg:tags":[
        "horse",
        "training"
    ],
    "wof:name":"2 J Ranch & Training Ctr",
    "wof:placetype":"venue"
},
  "geometry": {"coordinates":[-97.287493,32.320455],"type":"Point"}
}