{
  "type": "Feature",
  "properties": {
    "iso:country":"US",
    "sg:address":"2618 Century Ranch",
    "sg:city":"San Antonio",
    "sg:classifiers":[
        {
            "category":"Professional",
            "type":"Services"
        }
    ],
    "sg:phone":"+1 210 647 7943",
    "sg:postcode":"78251",
    "sg:province":"TX",
    "wof:name":"David Keeland",
    "wof:placetype":"venue"
},
  "geometry": {"coordinates":[-98.67726,29.46108],"type":"Point"}
}