{
  "type": "Feature",
  "properties": {
    "iso:country":"US",
    "sg:address":"685 N Harvey Mitchell Pkwy",
    "sg:city":"Bryan",
    "sg:classifiers":[
        {
            "category":"Professional",
            "subcategory":"Business Services",
            "type":"Services"
        }
    ],
    "sg:phone":"+1 979 823 1257",
    "sg:postcode":"77807",
    "sg:province":"TX",
    "wof:name":"Fedex",
    "wof:placetype":"venue"
},
  "geometry": {"coordinates":[-96.378516,30.634128],"type":"Point"}
}