{
  "type": "Feature",
  "properties": {
    "iso:country":"US",
    "sg:address":"101 N Ridgeway Dr",
    "sg:city":"Cleburne",
    "sg:classifiers":[
        {
            "category":"Professional",
            "type":"Services"
        }
    ],
    "sg:phone":"+1 817 556 2566",
    "sg:postcode":"76033",
    "sg:province":"TX",
    "wof:name":"Associated Permit Agents Inc",
    "wof:placetype":"venue"
},
  "geometry": {"coordinates":[-97.40842600000001,32.340412],"type":"Point"}
}