{
  "type": "Feature",
  "properties": {
    "iso:country":"US",
    "sg:address":"3131 McArdle Rd",
    "sg:city":"Corpus Christi",
    "sg:classifiers":[
        {
            "category":"Personal",
            "subcategory":"Beauty Salon",
            "type":"Services"
        },
        {
            "category":"Personal",
            "subcategory":"Barber",
            "type":"Services"
        }
    ],
    "sg:phone":"+1 361 852 3132",
    "sg:postcode":"78415",
    "sg:province":"TX",
    "sg:tags":[
        "shop"
    ],
    "wof:name":"Hair Exchange",
    "wof:placetype":"venue"
},
  "geometry": {"coordinates":[-97.411112,27.731909],"type":"Point"}
}