{
  "type": "Feature",
  "properties": {
    "iso:country":"US",
    "sg:address":"3201 Daniel Dr",
    "sg:city":"Arlington",
    "sg:classifiers":[
        {
            "category":"Organizations",
            "subcategory":"Religious Organization",
            "type":"Services"
        }
    ],
    "sg:phone":"+1 817 468 7522",
    "sg:postcode":"76014",
    "sg:province":"TX",
    "wof:name":"Glorious Mission Church O",
    "wof:placetype":"venue"
},
  "geometry": {"coordinates":[-97.09105599999999,32.694055],"type":"Point"}
}