{
  "type": "Feature",
  "properties": {
    "iso:country":"US",
    "sg:address":"504 S Pleasantview Dr",
    "sg:city":"Weslaco",
    "sg:classifiers":[
        {
            "category":"Wholesale",
            "subcategory":"Fruits & Vegetables",
            "type":"Manufacturing & Wholesale Goods"
        }
    ],
    "sg:phone":"+1 956 968 5251",
    "sg:postcode":"78596",
    "sg:province":"TX",
    "wof:name":"Texana Pickle Producers",
    "wof:placetype":"venue"
},
  "geometry": {"coordinates":[-97.96654100000001,26.157075],"type":"Point"}
}