{
  "type": "Feature",
  "properties": {
    "iso:country":"US",
    "sg:address":"28310 Margerstadt Rd",
    "sg:city":"Waller",
    "sg:classifiers":[
        {
            "category":"Wholesale",
            "subcategory":"Farm Supplies",
            "type":"Manufacturing & Wholesale Goods"
        }
    ],
    "sg:phone":"+1 936 372 2566",
    "sg:postcode":"77484",
    "sg:province":"TX",
    "sg:tags":[
        "livestock"
    ],
    "wof:name":"Roger Timmerman",
    "wof:placetype":"venue"
},
  "geometry": {"coordinates":[-95.865545,30.105375],"type":"Point"}
}