{
  "type": "Feature",
  "properties": {
    "iso:country":"US",
    "sg:address":"9155 Dyer St",
    "sg:city":"El Paso",
    "sg:classifiers":[
        {
            "category":"Restaurant",
            "type":"Food & Drink"
        }
    ],
    "sg:menulink":"http://www.allmenus.com/tx/el-paso/85853-little-caesars-pizza/menu/",
    "sg:phone":"+1 915 751 8801",
    "sg:postcode":"79924",
    "sg:province":"TX",
    "sg:tags":[
        "american",
        "pizza"
    ],
    "wof:name":"Little Caesar's Pizza",
    "wof:placetype":"venue"
},
  "geometry": {"coordinates":[-106.427384,31.872657],"type":"Point"}
}