{
  "type": "Feature",
  "properties": {
    "iso:country":"US",
    "sg:address":"913 N I- 35",
    "sg:city":"San Marcos",
    "sg:classifiers":[
        {
            "category":"Wholesale",
            "subcategory":"Durable Goods & Equipment",
            "type":"Manufacturing & Wholesale Goods"
        },
        {
            "category":"Shopping",
            "subcategory":"Gifts & Souvenirs",
            "type":"Retail Goods"
        }
    ],
    "sg:phone":"+1 512 878 1192",
    "sg:postcode":"78666",
    "sg:province":"TX",
    "sg:tags":[
        "party",
        "supply"
    ],
    "wof:name":"Penata Party Supply",
    "wof:placetype":"venue"
},
  "geometry": {"coordinates":[-97.926885,29.878014],"type":"Point"}
}