{
  "type": "Feature",
  "properties": {
    "iso:country":"US",
    "sg:address":"2907 Surrey Trail Ln",
    "sg:city":"Katy",
    "sg:classifiers":[
        {
            "category":"Professional",
            "subcategory":"Computer Services",
            "type":"Services"
        }
    ],
    "sg:phone":"+1 281 398 2726",
    "sg:postcode":"77450",
    "sg:province":"TX",
    "wof:name":"Burns Technical Services",
    "wof:placetype":"venue"
},
  "geometry": {"coordinates":[-95.73014999999999,29.739055],"type":"Point"}
}