{
  "type": "Feature",
  "properties": {
    "iso:country":"US",
    "sg:address":"3614 N Echo Trl",
    "sg:city":"Plano",
    "sg:classifiers":[
        {
            "category":"Professional",
            "type":"Services"
        }
    ],
    "sg:phone":"+1 972 867 6908",
    "sg:postcode":"75023",
    "sg:province":"TX",
    "wof:name":"Labstate",
    "wof:placetype":"venue"
},
  "geometry": {"coordinates":[-96.762405,33.042445],"type":"Point"}
}