{
  "type": "Feature",
  "properties": {
    "iso:country":"US",
    "sg:address":"92 Paradise Cove Rd",
    "sg:city":"Pottsboro",
    "sg:classifiers":[
        {
            "category":"Recreation",
            "subcategory":"Marina",
            "type":"Entertainment"
        }
    ],
    "sg:phone":"+1 903 786 7053",
    "sg:postcode":"75076",
    "sg:province":"TX",
    "sg:tags":[
        "storage",
        "boat"
    ],
    "wof:name":"Deutexland Inc",
    "wof:placetype":"venue"
},
  "geometry": {"coordinates":[-96.776302,33.797979],"type":"Point"}
}