{
  "type": "Feature",
  "properties": {
    "iso:country":"US",
    "sg:address":"3608 Jones St",
    "sg:city":"Texarkana",
    "sg:classifiers":[
        {
            "category":"Organizations",
            "subcategory":"Religious Organization",
            "type":"Services"
        }
    ],
    "sg:phone":"+1 903 793 7339",
    "sg:postcode":"75501",
    "sg:province":"TX",
    "sg:tags":[
        "church"
    ],
    "wof:name":"Grandview Church-God In Christ",
    "wof:placetype":"venue"
},
  "geometry": {"coordinates":[-94.084678,33.40397],"type":"Point"}
}