{
  "type": "Feature",
  "properties": {
    "iso:country":"US",
    "sg:address":"6051 Mimosa Ln",
    "sg:city":"Dallas",
    "sg:classifiers":[
        {
            "category":"Shopping",
            "subcategory":"Used Merchandise",
            "type":"Retail Goods"
        }
    ],
    "sg:phone":"+1 214 763 7575",
    "sg:postcode":"75230",
    "sg:province":"TX",
    "sg:tags":[
        "landscape"
    ],
    "wof:name":"Creative Gardens",
    "wof:placetype":"venue"
},
  "geometry": {"coordinates":[-96.800853,32.883351],"type":"Point"}
}