{
  "type": "Feature",
  "properties": {
    "iso:country":"US",
    "sg:address":"1414 S Lamar Blvd",
    "sg:city":"Austin",
    "sg:classifiers":[
        {
            "category":"Retail",
            "subcategory":"Auto Repair",
            "type":"Services"
        }
    ],
    "sg:phone":"+1 512 442 7525",
    "sg:postcode":"78704",
    "sg:province":"TX",
    "sg:tags":[
        "repairing",
        "automobile",
        "general"
    ],
    "wof:name":"South Lamar Automotive Service",
    "wof:placetype":"venue"
},
  "geometry": {"coordinates":[-97.7624,30.254745],"type":"Point"}
}