{
  "type": "Feature",
  "properties": {
    "iso:country":"US",
    "sg:address":"6005 Milwee St",
    "sg:city":"Houston",
    "sg:classifiers":[
        {
            "category":"Professional",
            "type":"Services"
        }
    ],
    "sg:phone":"+1 713 812 7072",
    "sg:postcode":"77092",
    "sg:province":"TX",
    "wof:name":"Topcoats USA",
    "wof:placetype":"venue"
},
  "geometry": {"coordinates":[-95.47614400000001,29.822143],"type":"Point"}
}