{
  "type": "Feature",
  "properties": {
    "iso:country":"US",
    "sg:address":"910 Paluxy Rd",
    "sg:city":"Granbury",
    "sg:classifiers":[
        {
            "category":"Organizations",
            "subcategory":"Religious Organization",
            "type":"Services"
        }
    ],
    "sg:phone":"+1 817 573 3405",
    "sg:postcode":"76048",
    "sg:province":"TX",
    "wof:name":"Southside Baptist Church SBC",
    "wof:placetype":"venue"
},
  "geometry": {"coordinates":[-97.797085,32.43573],"type":"Point"}
}