{
  "type": "Feature",
  "properties": {
    "iso:country":"US",
    "sg:address":"14110 Wallisville Rd",
    "sg:city":"Houston",
    "sg:classifiers":[
        {
            "category":"Sports & Exercise",
            "subcategory":"Sports Center",
            "type":"Entertainment"
        }
    ],
    "sg:phone":"+1 713 453 6527",
    "sg:postcode":"77049",
    "sg:province":"TX",
    "wof:name":"Sapphire Booster Club",
    "wof:placetype":"venue"
},
  "geometry": {"coordinates":[-95.199867,29.805901],"type":"Point"}
}