{
  "type": "Feature",
  "properties": {
    "iso:country":"US",
    "sg:address":"10402 Vrana Rd",
    "sg:city":"Houston",
    "sg:classifiers":[
        {
            "category":"Mining & Drilling",
            "type":"Manufacturing & Wholesale Goods"
        }
    ],
    "sg:phone":"+1 281 456 8401",
    "sg:postcode":"77049",
    "sg:province":"TX",
    "sg:tags":[
        "field",
        "oil"
    ],
    "wof:name":"Citisales Inc",
    "wof:placetype":"venue"
},
  "geometry": {"coordinates":[-95.124538,29.86669],"type":"Point"}
}