{
  "type": "Feature",
  "properties": {
    "iso:country":"US",
    "sg:address":"8300 Douglas Ave Ste 800",
    "sg:city":"Dallas",
    "sg:classifiers":[
        {
            "category":"Professional",
            "subcategory":"Lawyer & Legal Services",
            "type":"Services"
        }
    ],
    "sg:phone":"+1 214 706 9299",
    "sg:postcode":"75225",
    "sg:province":"TX",
    "wof:name":"Andrea K Stroller Atty",
    "wof:placetype":"venue"
},
  "geometry": {"coordinates":[-96.808403,32.863701],"type":"Point"}
}