{
  "type": "Feature",
  "properties": {
    "iso:country":"US",
    "sg:address":"10701 Kingwood Dr",
    "sg:city":"Corpus Christi",
    "sg:classifiers":[
        {
            "category":"Shopping",
            "subcategory":"Catalog Store",
            "type":"Retail Goods"
        }
    ],
    "sg:phone":"+1 361 241 5555",
    "sg:postcode":"78410",
    "sg:province":"TX",
    "sg:tags":[
        "mail",
        "house"
    ],
    "wof:name":"Cola Ectibles",
    "wof:placetype":"venue"
},
  "geometry": {"coordinates":[-97.58593500000001,27.836413],"type":"Point"}
}