{
  "type": "Feature",
  "properties": {
    "iso:country":"US",
    "sg:address":"4918 Rockford Ct",
    "sg:city":"Arlington",
    "sg:classifiers":[
        {
            "category":"Insurance",
            "subcategory":"Insurance Agent",
            "type":"Services"
        }
    ],
    "sg:phone":"+1 817 478 1543",
    "sg:postcode":"76017",
    "sg:province":"TX",
    "wof:name":"Bm Enterprises",
    "wof:placetype":"venue"
},
  "geometry": {"coordinates":[-97.186109,32.658371],"type":"Point"}
}