{
  "type": "Feature",
  "properties": {
    "iso:country":"US",
    "sg:address":"1407 Parkway Plaza Dr",
    "sg:city":"Houston",
    "sg:classifiers":[
        {
            "category":"Social Services",
            "subcategory":"Child Care",
            "type":"Services"
        },
        {
            "category":"Education",
            "subcategory":"Preschool",
            "type":"Public Place"
        }
    ],
    "sg:phone":"+1 281 531 1407",
    "sg:postcode":"77077",
    "sg:province":"TX",
    "sg:tags":[
        "kindergarten",
        "nursery",
        "day"
    ],
    "sg:website":"http://www.kindercare.com/our-centers/center-details/301476/?cid=YP_KC301476",
    "wof:name":"Brimhurst KinderCare",
    "wof:placetype":"venue"
},
  "geometry": {"coordinates":[-95.633191,29.763124],"type":"Point"}
}