{
  "type": "Feature",
  "properties": {
    "iso:country":"US",
    "sg:address":"7300 Jack Newell Blvd S",
    "sg:city":"Fort Worth",
    "sg:classifiers":[
        {
            "category":"Professional",
            "type":"Services"
        }
    ],
    "sg:phone":"+1 817 272 9588",
    "sg:postcode":"76118",
    "sg:province":"TX",
    "sg:tags":[
        "establishment"
    ],
    "wof:name":"UTA/Fort Worth Riverbend",
    "wof:placetype":"venue"
},
  "geometry": {"coordinates":[-97.226851,32.784754],"type":"Point"}
}