{
  "type": "Feature",
  "properties": {
    "iso:country":"US",
    "sg:address":"820 S Macarthur Blvd",
    "sg:city":"Coppell",
    "sg:classifiers":[
        {
            "category":"Shopping",
            "subcategory":"Stationery & Office Supplies",
            "type":"Retail Goods"
        }
    ],
    "sg:phone":"+1 972 304 4373",
    "sg:postcode":"75019",
    "sg:province":"TX",
    "sg:tags":[
        "stationer"
    ],
    "wof:name":"Petite Folie",
    "wof:placetype":"venue"
},
  "geometry": {"coordinates":[-96.95791699999999,32.953222],"type":"Point"}
}