{
  "type": "Feature",
  "properties": {
    "iso:country":"US",
    "sg:address":"607 Mason St",
    "sg:city":"Tomball",
    "sg:classifiers":[
        {
            "category":"Manufacturing",
            "subcategory":"Printing",
            "type":"Manufacturing & Wholesale Goods"
        }
    ],
    "sg:phone":"+1 281 516 0350",
    "sg:postcode":"77375",
    "sg:province":"TX",
    "sg:tags":[
        "publisher"
    ],
    "wof:name":"Doyle Publishing Co Inc",
    "wof:placetype":"venue"
},
  "geometry": {"coordinates":[-95.619833,30.096525],"type":"Point"}
}