{
  "type": "Feature",
  "properties": {
    "iso:country":"US",
    "sg:address":"1742 FM 126",
    "sg:city":"Nolan",
    "sg:classifiers":[
        {
            "category":"Recreation",
            "type":"Entertainment"
        }
    ],
    "sg:phone":"+1 325 798 3138",
    "sg:postcode":"79520",
    "sg:province":"TX",
    "sg:tags":[
        "center"
    ],
    "wof:name":"Nolan-Divide Community Ctr",
    "wof:placetype":"venue"
},
  "geometry": {"coordinates":[-100.087115,32.766241],"type":"Point"}
}