{
  "type": "Feature",
  "properties": {
    "iso:country":"US",
    "sg:address":"510 Billie Bess Ln",
    "sg:city":"Conroe",
    "sg:classifiers":[
        {
            "category":"Real Estate",
            "subcategory":"Real Estate Operator",
            "type":"Services"
        }
    ],
    "sg:phone":"+1 936 756 8168",
    "sg:postcode":"77301",
    "sg:province":"TX",
    "sg:tags":[
        "apartment"
    ],
    "wof:name":"Billy's Cove Apartments",
    "wof:placetype":"venue"
},
  "geometry": {"coordinates":[-95.462869,30.329397],"type":"Point"}
}