{
  "type": "Feature",
  "properties": {
    "iso:country":"US",
    "sg:address":"816 Main St",
    "sg:city":"Garland",
    "sg:classifiers":[
        {
            "category":"Utilities",
            "subcategory":"Mobile Phone",
            "type":"Services"
        }
    ],
    "sg:phone":"+1 972 494 4253",
    "sg:postcode":"75040",
    "sg:province":"TX",
    "sg:tags":[
        "provider",
        "telephone",
        "cellular",
        "internet"
    ],
    "sg:website":"www.sprint.com",
    "wof:name":"Sprint",
    "wof:placetype":"venue"
},
  "geometry": {"coordinates":[-96.64099899999999,32.9128],"type":"Point"}
}