{
  "type": "Feature",
  "properties": {
    "iso:country":"US",
    "sg:address":"910 E Main St",
    "sg:city":"Little River",
    "sg:classifiers":[
        {
            "category":"Real Estate",
            "subcategory":"Real Estate Operator",
            "type":"Services"
        }
    ],
    "sg:phone":"+1 254 982 4407",
    "sg:postcode":"76554",
    "sg:province":"TX",
    "sg:tags":[
        "property",
        "lessor"
    ],
    "wof:name":"Compton Rentals and Cnstr",
    "wof:placetype":"venue"
},
  "geometry": {"coordinates":[-97.341504,30.980498],"type":"Point"}
}