{
  "type": "Feature",
  "properties": {
    "iso:country":"US",
    "sg:address":"11450 James Watt Dr",
    "sg:city":"El Paso",
    "sg:classifiers":[
        {
            "category":"Shopping",
            "subcategory":"Computers & Home Electronics",
            "type":"Retail Goods"
        }
    ],
    "sg:phone":"+1 915 595 4390",
    "sg:postcode":"79936",
    "sg:province":"TX",
    "sg:tags":[
        "equipment",
        "dealer"
    ],
    "wof:name":"Daroc Computers",
    "wof:placetype":"venue"
},
  "geometry": {"coordinates":[-106.31547399999999,31.741568],"type":"Point"}
}