{
  "type": "Feature",
  "properties": {
    "iso:country":"US",
    "sg:address":"5415 Timber Beach St",
    "sg:city":"San Antonio",
    "sg:classifiers":[
        {
            "category":"Professional",
            "subcategory":"Research",
            "type":"Services"
        }
    ],
    "sg:phone":"+1 210 521 6484",
    "sg:postcode":"78250",
    "sg:province":"TX",
    "wof:name":"Applied Research & Technical",
    "wof:placetype":"venue"
},
  "geometry": {"coordinates":[-98.65609600000001,29.491956],"type":"Point"}
}