{
  "type": "Feature",
  "properties": {
    "iso:country":"US",
    "sg:address":"306 Meredith Dr",
    "sg:city":"San Antonio",
    "sg:classifiers":[
        {
            "category":"Building & Trades",
            "subcategory":"Construction",
            "type":"Services"
        }
    ],
    "sg:phone":"+1 210 732 3142",
    "sg:postcode":"78228",
    "sg:province":"TX",
    "sg:tags":[
        "nonresidential"
    ],
    "wof:name":"Economy Remodeling",
    "wof:placetype":"venue"
},
  "geometry": {"coordinates":[-98.546989,29.466324],"type":"Point"}
}