{
  "type": "Feature",
  "properties": {
    "iso:country":"US",
    "sg:address":"605 Woodard Ave",
    "sg:city":"Cleburne",
    "sg:classifiers":[
        {
            "category":"Freight",
            "type":"Transportation"
        }
    ],
    "sg:phone":"+1 817 641 1943",
    "sg:postcode":"76033",
    "sg:province":"TX",
    "sg:tags":[
        "operator",
        "local",
        "trucking"
    ],
    "wof:name":"Joe Warlick Inc",
    "wof:placetype":"venue"
},
  "geometry": {"coordinates":[-97.40751299999999,32.349719],"type":"Point"}
}