{
  "type": "Feature",
  "properties": {
    "iso:country":"US",
    "sg:address":"119 N Frances St",
    "sg:city":"Terrell",
    "sg:classifiers":[
        {
            "category":"Professional",
            "subcategory":"Lawyer & Legal Services",
            "type":"Services"
        }
    ],
    "sg:phone":"+1 972 551 0555",
    "sg:postcode":"75160",
    "sg:province":"TX",
    "sg:tags":[
        "attorney"
    ],
    "wof:name":"G Scott Odom Attorney",
    "wof:placetype":"venue"
},
  "geometry": {"coordinates":[-96.278278,32.737418],"type":"Point"}
}