{
  "type": "Feature",
  "properties": {
    "iso:country":"US",
    "sg:address":"121 W Rock Island Rd",
    "sg:city":"Grand Prairie",
    "sg:classifiers":[
        {
            "category":"Manufacturing",
            "subcategory":"Rubber & Plastics",
            "type":"Manufacturing & Wholesale Goods"
        }
    ],
    "sg:phone":"+1 972 790 9001",
    "sg:postcode":"75050",
    "sg:province":"TX",
    "sg:tags":[
        "producer"
    ],
    "wof:name":"Hagans Plastics Co",
    "wof:placetype":"venue"
},
  "geometry": {"coordinates":[-97.014124,32.815722],"type":"Point"}
}