{
  "type": "Feature",
  "properties": {
    "iso:country":"US",
    "sg:address":"318 S Stanton St",
    "sg:city":"El Paso",
    "sg:classifiers":[
        {
            "category":"Shopping",
            "subcategory":"Clothing, Apparel, & Fashions",
            "type":"Retail Goods"
        }
    ],
    "sg:phone":"+1 915 546 9355",
    "sg:postcode":"79901",
    "sg:province":"TX",
    "sg:tags":[
        "furnishing"
    ],
    "wof:name":"Rasputin Men's Wear",
    "wof:placetype":"venue"
},
  "geometry": {"coordinates":[-106.485079,31.755886],"type":"Point"}
}