{
  "type": "Feature",
  "properties": {
    "iso:country":"US",
    "sg:address":"3303 33rd St",
    "sg:city":"Lubbock",
    "sg:classifiers":[
        {
            "category":"Health Services",
            "subcategory":"Podiatrist",
            "type":"Services"
        }
    ],
    "sg:phone":"+1 806 797 2069",
    "sg:postcode":"79410",
    "sg:province":"TX",
    "wof:name":"Robert M Brodkin",
    "wof:placetype":"venue"
},
  "geometry": {"coordinates":[-101.88772400000001,33.564192],"type":"Point"}
}