{
  "type": "Feature",
  "properties": {
    "iso:country":"US",
    "sg:address":"3301 N Interstate 35E",
    "sg:city":"Carrollton",
    "sg:classifiers":[
        {
            "category":"Banks & Credit Unions",
            "subcategory":"Financial Services",
            "type":"Services"
        }
    ],
    "sg:phone":"+1 972 446 7757",
    "sg:postcode":"75007",
    "sg:province":"TX",
    "sg:tags":[
        "broker",
        "mortgage"
    ],
    "wof:name":"Universal Capital Mortgage",
    "wof:placetype":"venue"
},
  "geometry": {"coordinates":[-96.93229700000001,32.993999],"type":"Point"}
}