{
  "type": "Feature",
  "properties": {
    "iso:country":"US",
    "sg:address":"2519 E Hwy 190",
    "sg:city":"Copperas Cove",
    "sg:classifiers":[
        {
            "category":"Retail",
            "subcategory":"Car Wash",
            "type":"Services"
        }
    ],
    "sg:phone":"+1 254 518 0303",
    "sg:postcode":"76522",
    "sg:province":"TX",
    "sg:tags":[
        "carwash",
        "automobile",
        "detail",
        "clean"
    ],
    "wof:name":"Sudsy's Carwash",
    "wof:placetype":"venue"
},
  "geometry": {"coordinates":[-97.871899,31.120694],"type":"Point"}
}