{
  "type": "Feature",
  "properties": {
    "iso:country":"US",
    "sg:address":"3008 Shenandoah Dr",
    "sg:city":"Bedford",
    "sg:classifiers":[
        {
            "category":"Banks & Credit Unions",
            "subcategory":"Investment Brokerage",
            "type":"Services"
        },
        {
            "category":"Professional",
            "subcategory":"Management & Consulting",
            "type":"Services"
        }
    ],
    "sg:phone":"+1 817 577 3157",
    "sg:postcode":"76021",
    "sg:province":"TX",
    "sg:tags":[
        "merger",
        "acquisition"
    ],
    "wof:name":"Performance Acquisition Corp",
    "wof:placetype":"venue"
},
  "geometry": {"coordinates":[-97.167287,32.854678],"type":"Point"}
}