{
  "type": "Feature",
  "properties": {
    "iso:country":"US",
    "sg:address":"7901 Oakmont Blvd",
    "sg:city":"Fort Worth",
    "sg:classifiers":[
        {
            "category":"Social Services",
            "subcategory":"Child Care",
            "type":"Services"
        }
    ],
    "sg:phone":"+1 817 423 1515",
    "sg:postcode":"76132",
    "sg:province":"TX",
    "sg:website":"www.childrensworld.com",
    "wof:name":"Children's World Learning Ctr",
    "wof:placetype":"venue"
},
  "geometry": {"coordinates":[-97.42531700000001,32.667081],"type":"Point"}
}