{
  "type": "Feature",
  "properties": {
    "iso:country":"US",
    "sg:address":"201 N Walnut St",
    "sg:city":"Sherman",
    "sg:classifiers":[
        {
            "category":"Utilities",
            "subcategory":"Telephone",
            "type":"Services"
        }
    ],
    "sg:phone":"+1 903 870 5262",
    "sg:postcode":"75090",
    "sg:province":"TX",
    "sg:tags":[
        "switching",
        "center"
    ],
    "wof:name":"GTE Southwest Incorporated",
    "wof:placetype":"venue"
},
  "geometry": {"coordinates":[-96.60874,33.638798],"type":"Point"}
}