{
  "type": "Feature",
  "properties": {
    "iso:country":"US",
    "sg:address":"6130 S Padre Island Dr",
    "sg:city":"Corpus Christi",
    "sg:classifiers":[
        {
            "category":"Autos & Motor Vehicles",
            "subcategory":"Auto Supplies",
            "type":"Retail Goods"
        }
    ],
    "sg:phone":"+1 361 991 7511",
    "sg:postcode":"78412",
    "sg:province":"TX",
    "sg:tags":[
        "parts"
    ],
    "wof:name":"Southside Auto Supply",
    "wof:placetype":"venue"
},
  "geometry": {"coordinates":[-97.360071,27.703084],"type":"Point"}
}