{
  "type": "Feature",
  "properties": {
    "iso:country":"US",
    "sg:address":"4208 S General Bruce Dr",
    "sg:city":"Temple",
    "sg:classifiers":[
        {
            "category":"Wholesale",
            "subcategory":"Chemicals & Plastics",
            "type":"Manufacturing & Wholesale Goods"
        }
    ],
    "sg:phone":"+1 254 778 8701",
    "sg:postcode":"76502",
    "sg:province":"TX",
    "sg:tags":[
        "solvent"
    ],
    "sg:website":"www.temtexsolvents.com",
    "wof:name":"Tem-Tex Solvents Corporation",
    "wof:placetype":"venue"
},
  "geometry": {"coordinates":[-97.392989,31.089195],"type":"Point"}
}