{
  "type": "Feature",
  "properties": {
    "iso:country":"US",
    "sg:address":"4411 Colchester St",
    "sg:city":"Houston",
    "sg:classifiers":[
        {
            "category":"Professional",
            "type":"Services"
        }
    ],
    "sg:phone":"+1 713 686 5856",
    "sg:postcode":"77018",
    "sg:province":"TX",
    "sg:tags":[
        "store",
        "variety"
    ],
    "wof:name":"Busch Pottery",
    "wof:placetype":"venue"
},
  "geometry": {"coordinates":[-95.44634000000001,29.837929],"type":"Point"}
}