{
  "type": "Feature",
  "properties": {
    "iso:country":"US",
    "sg:address":"3460 W Walnut St",
    "sg:city":"Garland",
    "sg:classifiers":[
        {
            "category":"Communications",
            "type":"Services"
        }
    ],
    "sg:phone":"+1 972 494 0566",
    "sg:postcode":"75042",
    "sg:province":"TX",
    "sg:tags":[
        "communication"
    ],
    "wof:name":"Texas Communications",
    "wof:placetype":"venue"
},
  "geometry": {"coordinates":[-96.679333,32.916455],"type":"Point"}
}