{
  "type": "Feature",
  "properties": {
    "iso:country":"US",
    "sg:address":"105 Frankens St",
    "sg:city":"Diboll",
    "sg:classifiers":[
        {
            "category":"Organizations",
            "subcategory":"Religious Organization",
            "type":"Services"
        }
    ],
    "sg:phone":"+1 979 242 3727",
    "sg:postcode":"75941",
    "sg:province":"TX",
    "sg:tags":[
        "church"
    ],
    "wof:name":"Lighthouse United Pentecostal",
    "wof:placetype":"venue"
},
  "geometry": {"coordinates":[-94.77531999999999,31.182021],"type":"Point"}
}