{
  "type": "Feature",
  "properties": {
    "iso:country":"US",
    "sg:address":"148 E Little York Rd",
    "sg:city":"Houston",
    "sg:classifiers":[
        {
            "category":"Retail",
            "subcategory":"Event Space",
            "type":"Services"
        }
    ],
    "sg:phone":"+1 713 692 8759",
    "sg:postcode":"77076",
    "sg:province":"TX",
    "sg:tags":[
        "venue"
    ],
    "sg:website":"www.traditionpartyhall.com",
    "wof:name":"Tradition Party Hall Inc",
    "wof:placetype":"venue"
},
  "geometry": {"coordinates":[-95.398399,29.869699],"type":"Point"}
}