{
  "type": "Feature",
  "properties": {
    "iso:country":"US",
    "sg:address":"801 Oak Grove Rd",
    "sg:city":"San Marcos",
    "sg:classifiers":[
        {
            "category":"Professional",
            "subcategory":"Business Services",
            "type":"Services"
        }
    ],
    "sg:phone":"+1 512 805 2231",
    "sg:postcode":"78666",
    "sg:province":"TX",
    "sg:tags":[
        "installation",
        "custom"
    ],
    "wof:name":"Floors Etc",
    "wof:placetype":"venue"
},
  "geometry": {"coordinates":[-97.984619,29.985009],"type":"Point"}
}