{
  "type": "Feature",
  "properties": {
    "iso:country":"US",
    "sg:address":"217 W Veterans Memorial Blvd",
    "sg:city":"Killeen",
    "sg:classifiers":[
        {
            "category":"Local Transit",
            "type":"Transportation"
        }
    ],
    "sg:phone":"+1 254 680 3339",
    "sg:postcode":"76541",
    "sg:province":"TX",
    "sg:tags":[
        "passenger"
    ],
    "wof:name":"Discount Car Rental",
    "wof:placetype":"venue"
},
  "geometry": {"coordinates":[-97.73332000000001,31.118384],"type":"Point"}
}