{
  "type": "Feature",
  "properties": {
    "iso:country":"US",
    "sg:address":"403 Mill Rd",
    "sg:city":"Springtown",
    "sg:classifiers":[
        {
            "category":"Professional",
            "subcategory":"Art Services",
            "type":"Services"
        }
    ],
    "sg:phone":"+1 817 523 5143",
    "sg:postcode":"76082",
    "sg:province":"TX",
    "sg:tags":[
        "commercial",
        "design"
    ],
    "wof:name":"Bizzy Bee Graphics Inc",
    "wof:placetype":"venue"
},
  "geometry": {"coordinates":[-97.67481100000001,32.916464],"type":"Point"}
}