{
  "type": "Feature",
  "properties": {
    "iso:country":"US",
    "sg:address":"301 Beauty Ln",
    "sg:city":"Whitesboro",
    "sg:classifiers":[
        {
            "category":"Government",
            "subcategory":"Office",
            "type":"Public Place"
        }
    ],
    "sg:phone":"+1 903 564 3700",
    "sg:postcode":"76273",
    "sg:province":"TX",
    "sg:tags":[
        "housing",
        "program"
    ],
    "wof:name":"Whitesboro Housing Authority",
    "wof:placetype":"venue"
},
  "geometry": {"coordinates":[-96.89913799999999,33.659382],"type":"Point"}
}