{
  "type": "Feature",
  "properties": {
    "iso:country":"US",
    "sg:address":"8235 Almeda Genoa Rd",
    "sg:city":"Houston",
    "sg:classifiers":[
        {
            "category":"Manufacturing",
            "subcategory":"Electronics",
            "type":"Manufacturing & Wholesale Goods"
        },
        {
            "category":"Shopping",
            "subcategory":"Computers & Home Electronics",
            "type":"Retail Goods"
        },
        {
            "category":"Wholesale",
            "subcategory":"Computers",
            "type":"Manufacturing & Wholesale Goods"
        }
    ],
    "sg:phone":"+1 713 991 2471",
    "sg:postcode":"77075",
    "sg:province":"TX",
    "sg:tags":[
        "equipment",
        "printers-equipment",
        "printer",
        "supply"
    ],
    "wof:name":"Precise Laser",
    "wof:placetype":"venue"
},
  "geometry": {"coordinates":[-95.248169,29.6271],"type":"Point"}
}