{
  "type": "Feature",
  "properties": {
    "iso:country":"US",
    "sg:address":"114 Fairway Dr",
    "sg:city":"Olney",
    "sg:classifiers":[
        {
            "category":"Farming",
            "subcategory":"Farm",
            "type":"Manufacturing & Wholesale Goods"
        }
    ],
    "sg:phone":"+1 940 564 5761",
    "sg:postcode":"76374",
    "sg:province":"TX",
    "sg:tags":[
        "crop",
        "general"
    ],
    "wof:name":"Mathews Farms",
    "wof:placetype":"venue"
},
  "geometry": {"coordinates":[-98.753322,33.342476],"type":"Point"}
}