{
  "type": "Feature",
  "properties": {
    "iso:country":"US",
    "sg:address":"1108 Chestnut St",
    "sg:city":"Bastrop",
    "sg:classifiers":[
        {
            "category":"Insurance",
            "subcategory":"Insurance Agent",
            "type":"Services"
        }
    ],
    "sg:phone":"+1 512 303 9650",
    "sg:postcode":"78602",
    "sg:province":"TX",
    "wof:name":"Auto Insurance Svc",
    "wof:placetype":"venue"
},
  "geometry": {"coordinates":[-97.314981,30.110676],"type":"Point"}
}