{
  "type": "Feature",
  "properties": {
    "iso:country":"US",
    "sg:address":"2004 Spanish Trl",
    "sg:city":"Roanoke",
    "sg:classifiers":[
        {
            "category":"Professional",
            "type":"Services"
        }
    ],
    "sg:phone":"+1 817 379 0970",
    "sg:postcode":"76262",
    "sg:province":"TX",
    "wof:name":"Lance Happy Inc",
    "wof:placetype":"venue"
},
  "geometry": {"coordinates":[-97.202591,32.955516],"type":"Point"}
}