{
  "type": "Feature",
  "properties": {
    "iso:country":"US",
    "sg:address":"5209 Ledgestone Dr",
    "sg:city":"Fort Worth",
    "sg:classifiers":[
        {
            "category":"Professional",
            "subcategory":"Management & Consulting",
            "type":"Services"
        }
    ],
    "sg:phone":"+1 817 346 9733",
    "sg:postcode":"76132",
    "sg:province":"TX",
    "sg:tags":[
        "business"
    ],
    "wof:name":"Whitt Consulting Services",
    "wof:placetype":"venue"
},
  "geometry": {"coordinates":[-97.39775899999999,32.672732],"type":"Point"}
}