{
  "type": "Feature",
  "properties": {
    "iso:country":"US",
    "sg:address":"28225 Royal Ascot Dr",
    "sg:city":"Boerne",
    "sg:classifiers":[
        {
            "category":"Retail",
            "subcategory":"Auto Repair",
            "type":"Services"
        }
    ],
    "sg:phone":"+1 210 698 0820",
    "sg:postcode":"78015",
    "sg:province":"TX",
    "sg:tags":[
        "body",
        "automobile",
        "painting",
        "repairing"
    ],
    "wof:name":"Statewide Paint Inc",
    "wof:placetype":"venue"
},
  "geometry": {"coordinates":[-98.645191,29.719246],"type":"Point"}
}