{
  "type": "Feature",
  "properties": {
    "iso:country":"US",
    "sg:address":"927 Main St",
    "sg:city":"Sulphur Springs",
    "sg:classifiers":[
        {
            "category":"Retail",
            "subcategory":"Auto Repair",
            "type":"Services"
        }
    ],
    "sg:phone":"+1 903 885 7131",
    "sg:postcode":"75482",
    "sg:province":"TX",
    "sg:tags":[
        "body",
        "automobile",
        "painting"
    ],
    "wof:name":"J D Oxford Paint & Body",
    "wof:placetype":"venue"
},
  "geometry": {"coordinates":[-95.61335699999999,33.134227],"type":"Point"}
}