{
  "type": "Feature",
  "properties": {
    "iso:country":"US",
    "sg:address":"507 Airybrook Ln",
    "sg:city":"Houston",
    "sg:classifiers":[
        {
            "category":"Building & Trades",
            "subcategory":"Plumbing",
            "type":"Services"
        }
    ],
    "sg:phone":"+1 281 492 0088",
    "sg:postcode":"77094",
    "sg:province":"TX",
    "sg:tags":[
        "sprinklers-garden",
        "installation",
        "lawn",
        "contractor"
    ],
    "wof:name":"Five Star Sprinklers Inc",
    "wof:placetype":"venue"
},
  "geometry": {"coordinates":[-95.70574999999999,29.778431],"type":"Point"}
}