{
  "type": "Feature",
  "properties": {
    "iso:country":"US",
    "sg:address":"1111 Alta Loma Cir",
    "sg:city":"San Angelo",
    "sg:classifiers":[
        {
            "category":"Professional",
            "subcategory":"Business Services",
            "type":"Services"
        }
    ],
    "sg:phone":"+1 325 653 5959",
    "sg:postcode":"76901",
    "sg:province":"TX",
    "sg:tags":[
        "used",
        "merchandise"
    ],
    "wof:name":"Chelsea Shoppe",
    "wof:placetype":"venue"
},
  "geometry": {"coordinates":[-100.447213,31.449783],"type":"Point"}
}