{
  "type": "Feature",
  "properties": {
    "iso:country":"US",
    "sg:address":"1914 W Gray St Apt 207",
    "sg:city":"Houston",
    "sg:classifiers":[
        {
            "category":"Professional",
            "subcategory":"Lawyer & Legal Services",
            "type":"Services"
        }
    ],
    "sg:phone":"+1 713 526 6686",
    "sg:postcode":"77019",
    "sg:province":"TX",
    "wof:name":"Matt Freeman & Associates",
    "wof:placetype":"venue"
},
  "geometry": {"coordinates":[-95.40454,29.75325],"type":"Point"}
}