{
  "type": "Feature",
  "properties": {
    "iso:country":"US",
    "sg:address":"3007 Manor Green Blvd",
    "sg:city":"Euless",
    "sg:classifiers":[
        {
            "category":"Health Services",
            "subcategory":"Doctor",
            "type":"Services"
        }
    ],
    "sg:phone":"+1 817 685 0760",
    "sg:postcode":"76039",
    "sg:province":"TX",
    "sg:tags":[
        "physician",
        "surgeon"
    ],
    "wof:name":"Shams International Inc",
    "wof:placetype":"venue"
},
  "geometry": {"coordinates":[-97.08104400000001,32.879175],"type":"Point"}
}