{
  "type": "Feature",
  "properties": {
    "iso:country":"US",
    "sg:address":"116 E Front St",
    "sg:city":"Tyler",
    "sg:classifiers":[
        {
            "category":"Shopping",
            "subcategory":"Jewelry",
            "type":"Retail Goods"
        }
    ],
    "sg:phone":"+1 903 593 9800",
    "sg:postcode":"75702",
    "sg:province":"TX",
    "sg:tags":[
        "used",
        "merchandise"
    ],
    "wof:name":"Collection",
    "wof:placetype":"venue"
},
  "geometry": {"coordinates":[-95.299683,32.346746],"type":"Point"}
}