{
  "type": "Feature",
  "properties": {
    "iso:country":"US",
    "sg:address":"2425 N Central Expy",
    "sg:city":"Richardson",
    "sg:classifiers":[
        {
            "category":"Professional",
            "subcategory":"Employment Agencies",
            "type":"Services"
        }
    ],
    "sg:phone":"+1 972 480 8333",
    "sg:postcode":"75080",
    "sg:province":"TX",
    "sg:tags":[
        "help",
        "supply"
    ],
    "wof:name":"Technical Services",
    "wof:placetype":"venue"
},
  "geometry": {"coordinates":[-96.71180699999999,32.985738],"type":"Point"}
}