{
  "type": "Feature",
  "properties": {
    "iso:country":"US",
    "sg:address":"30502 Misty Meadow Dr",
    "sg:city":"Magnolia",
    "sg:classifiers":[
        {
            "category":"Food & Beverages",
            "subcategory":"Groceries & Convenience Stores",
            "type":"Retail Goods"
        }
    ],
    "sg:phone":"+1 281 356 2453",
    "sg:postcode":"77354",
    "sg:province":"TX",
    "sg:tags":[
        "station",
        "gas"
    ],
    "wof:name":"Track Side Grocery",
    "wof:placetype":"venue"
},
  "geometry": {"coordinates":[-95.710667,30.183756],"type":"Point"}
}