{
  "type": "Feature",
  "properties": {
    "iso:country":"US",
    "sg:address":"120 N Main Ave",
    "sg:city":"Denver City",
    "sg:classifiers":[
        {
            "category":"Organizations",
            "subcategory":"Professional Association",
            "type":"Services"
        }
    ],
    "sg:phone":"+1 806 592 5424",
    "sg:postcode":"79323",
    "sg:province":"TX",
    "sg:tags":[
        "business"
    ],
    "wof:name":"Chamber Cmmrce Vstor Infrmatio",
    "wof:placetype":"venue"
},
  "geometry": {"coordinates":[-102.82913499999999,32.965497],"type":"Point"}
}