{
  "type": "Feature",
  "properties": {
    "iso:country":"US",
    "sg:address":"836 N Cage Blvd",
    "sg:city":"Pharr",
    "sg:classifiers":[
        {
            "category":"Food & Beverages",
            "subcategory":"Groceries & Convenience Stores",
            "type":"Retail Goods"
        }
    ],
    "sg:phone":"+1 956 781 0667",
    "sg:postcode":"78577",
    "sg:province":"TX",
    "sg:tags":[
        "grocer"
    ],
    "wof:name":"M Rivas Food Store",
    "wof:placetype":"venue"
},
  "geometry": {"coordinates":[-98.18241399999999,26.204517],"type":"Point"}
}