{
  "type": "Feature",
  "properties": {
    "iso:country":"US",
    "sg:address":"2108 Huber Ave",
    "sg:city":"Borger",
    "sg:classifiers":[
        {
            "category":"Social Services",
            "type":"Services"
        }
    ],
    "sg:phone":"+1 806 274 3215",
    "sg:postcode":"79007",
    "sg:province":"TX",
    "wof:name":"A L F Therapon Counseling Cent",
    "wof:placetype":"venue"
},
  "geometry": {"coordinates":[-101.403248,35.646219],"type":"Point"}
}