{
  "type": "Feature",
  "properties": {
    "iso:country":"US",
    "sg:address":"908 Live Oak St",
    "sg:city":"Denton",
    "sg:classifiers":[
        {
            "category":"Building & Trades",
            "subcategory":"Construction",
            "type":"Services"
        }
    ],
    "sg:phone":"+1 940 387 7474",
    "sg:postcode":"79508",
    "sg:province":"TX",
    "sg:tags":[
        "tile",
        "dealer"
    ],
    "wof:name":"Joe Sherrill Ceramic Tile",
    "wof:placetype":"venue"
},
  "geometry": {"coordinates":[-99.831232,32.277621],"type":"Point"}
}