{
  "type": "Feature",
  "properties": {
    "iso:country":"US",
    "sg:address":"1000 Tesoro Ln",
    "sg:city":"Laredo",
    "sg:classifiers":[
        {
            "category":"Insurance",
            "subcategory":"Insurance Agent",
            "type":"Services"
        }
    ],
    "sg:phone":"+1 956 722 0551",
    "sg:postcode":"78040",
    "sg:province":"TX",
    "sg:tags":[
        "life",
        "health"
    ],
    "wof:name":"De Soto Realty",
    "wof:placetype":"venue"
},
  "geometry": {"coordinates":[-99.507285,27.545723],"type":"Point"}
}