{
  "type": "Feature",
  "properties": {
    "iso:country":"US",
    "sg:address":"515 E 2nd St",
    "sg:city":"Rio Grande City",
    "sg:classifiers":[
        {
            "category":"Real Estate",
            "subcategory":"Surveying",
            "type":"Services"
        }
    ],
    "sg:phone":"+1 956 487 8981",
    "sg:postcode":"78582",
    "sg:province":"TX",
    "sg:tags":[
        "surveyor"
    ],
    "wof:name":"Melden & Hunt Inc",
    "wof:placetype":"venue"
},
  "geometry": {"coordinates":[-98.81632,26.37873],"type":"Point"}
}