{
  "type": "Feature",
  "properties": {
    "iso:country":"US",
    "sg:address":"740 N Connally Dr",
    "sg:city":"Elm Mott",
    "sg:classifiers":[
        {
            "category":"Recreation",
            "type":"Entertainment"
        }
    ],
    "sg:phone":"+1 254 829 2675",
    "sg:postcode":"76640",
    "sg:province":"TX",
    "sg:tags":[
        "hall",
        "auditorium"
    ],
    "wof:name":"Geneva Hall",
    "wof:placetype":"venue"
},
  "geometry": {"coordinates":[-97.099744,31.674047],"type":"Point"}
}