{
  "type": "Feature",
  "properties": {
    "iso:country":"US",
    "sg:address":"1707 E 6th St",
    "sg:city":"Austin",
    "sg:classifiers":[
        {
            "category":"Restaurant",
            "type":"Food & Drink"
        }
    ],
    "sg:phone":"+1 512 391 6225",
    "sg:postcode":"78701",
    "sg:province":"TX",
    "sg:website":"www.grazeaustin.com",
    "wof:name":"Graze Catering",
    "wof:placetype":"venue"
},
  "geometry": {"coordinates":[-97.724345,30.26154],"type":"Point"}
}