{
  "type": "Feature",
  "properties": {
    "iso:country":"US",
    "sg:address":"5308 Bandera Rd",
    "sg:city":"San Antonio",
    "sg:classifiers":[
        {
            "category":"Retail",
            "subcategory":"Auto Repair",
            "type":"Services"
        }
    ],
    "sg:phone":"+1 210 684 1919",
    "sg:postcode":"78238",
    "sg:province":"TX",
    "sg:tags":[
        "automobile",
        "electric"
    ],
    "wof:name":"Alex's Automotive",
    "wof:placetype":"venue"
},
  "geometry": {"coordinates":[-98.59059000000001,29.478974],"type":"Point"}
}