{
  "type": "Feature",
  "properties": {
    "iso:country":"US",
    "sg:address":"4611 Feagan St",
    "sg:city":"Houston",
    "sg:classifiers":[
        {
            "category":"Building & Trades",
            "subcategory":"Landscaping Services",
            "type":"Services"
        }
    ],
    "sg:phone":"+1 713 869 2030",
    "sg:postcode":"77007",
    "sg:province":"TX",
    "wof:name":"Rolando Delgado Lawn Serv",
    "wof:placetype":"venue"
},
  "geometry": {"coordinates":[-95.40817199999999,29.76602],"type":"Point"}
}