{
  "type": "Feature",
  "properties": {
    "iso:country":"US",
    "sg:address":"1128 Wichita Ave",
    "sg:city":"Jacksboro",
    "sg:classifiers":[
        {
            "category":"Organizations",
            "subcategory":"Membership Organization",
            "type":"Services"
        }
    ],
    "sg:phone":"+1 940 567 2225",
    "sg:postcode":"76458",
    "sg:province":"TX",
    "wof:name":"Jack County Clothes Closet",
    "wof:placetype":"venue"
},
  "geometry": {"coordinates":[-98.17561600000001,33.223833],"type":"Point"}
}