{
  "type": "Feature",
  "properties": {
    "iso:country":"US",
    "sg:address":"1711 Potomac Drive",
    "sg:city":"Houston",
    "sg:classifiers":[
        {
            "category":"Personal",
            "type":"Services"
        }
    ],
    "sg:phone":"+1 713 492 5599",
    "sg:postcode":"77057",
    "sg:province":"TX",
    "sg:tags":[
        "mover"
    ],
    "sg:website":"www.copperwoodmoving.com/",
    "wof:name":"Copperwood Moving Company",
    "wof:placetype":"venue"
},
  "geometry": {"coordinates":[-95.48855,29.749518],"type":"Point"}
}