{
  "type": "Feature",
  "properties": {
    "iso:country":"US",
    "sg:address":"4322 Boynton Dr",
    "sg:city":"Houston",
    "sg:classifiers":[
        {
            "category":"Professional",
            "subcategory":"Management & Consulting",
            "type":"Services"
        }
    ],
    "sg:phone":"+1 713 413 2525",
    "sg:postcode":"77045",
    "sg:province":"TX",
    "sg:tags":[
        "marketing",
        "program"
    ],
    "wof:name":"Healthnet Inc",
    "wof:placetype":"venue"
},
  "geometry": {"coordinates":[-95.443578,29.62857],"type":"Point"}
}