{
  "type": "Feature",
  "properties": {
    "iso:country":"US",
    "sg:address":"122 N Ballard Ave",
    "sg:city":"Wylie",
    "sg:classifiers":[
        {
            "category":"Insurance",
            "subcategory":"Insurance Agent",
            "type":"Services"
        }
    ],
    "sg:phone":"+1 972 429 4948",
    "sg:postcode":"75098",
    "sg:province":"TX",
    "wof:name":"Bill Sinsabaugh Agency",
    "wof:placetype":"venue"
},
  "geometry": {"coordinates":[-96.538815,33.01432],"type":"Point"}
}