{
  "type": "Feature",
  "properties": {
    "iso:country":"US",
    "sg:address":"2411 N Texas Blvd",
    "sg:city":"Weslaco",
    "sg:classifiers":[
        {
            "category":"Government",
            "subcategory":"Office",
            "type":"Public Place"
        }
    ],
    "sg:phone":"+1 956 968 5457",
    "sg:postcode":"78596",
    "sg:province":"TX",
    "sg:tags":[
        "state",
        "resource"
    ],
    "wof:name":"Human Service Dept",
    "wof:placetype":"venue"
},
  "geometry": {"coordinates":[-97.991236,26.182388],"type":"Point"}
}