{
  "type": "Feature",
  "properties": {
    "iso:country":"US",
    "sg:address":"4742 Five Knolls Dr",
    "sg:city":"Friendswood",
    "sg:classifiers":[
        {
            "category":"Professional",
            "subcategory":"Detective & Security Services",
            "type":"Services"
        }
    ],
    "sg:phone":"+1 281 648 4606",
    "sg:postcode":"77546",
    "sg:province":"TX",
    "sg:tags":[
        "system"
    ],
    "wof:name":"All Safe",
    "wof:placetype":"venue"
},
  "geometry": {"coordinates":[-95.178561,29.540427],"type":"Point"}
}