{
  "type": "Feature",
  "properties": {
    "iso:country":"US",
    "sg:address":"1206 W 38th St",
    "sg:city":"Austin",
    "sg:classifiers":[
        {
            "category":"Shopping",
            "subcategory":"Jewelry",
            "type":"Retail Goods"
        }
    ],
    "sg:phone":"+1 512 458 8024",
    "sg:postcode":"78705",
    "sg:province":"TX",
    "wof:name":"Benchmark Designers Goldsmiths",
    "wof:placetype":"venue"
},
  "geometry": {"coordinates":[-97.744951,30.306106],"type":"Point"}
}