{
  "type": "Feature",
  "properties": {
    "iso:country":"US",
    "sg:address":"503 Windswept Dr",
    "sg:city":"Humble",
    "sg:classifiers":[
        {
            "category":"Shopping",
            "subcategory":"Jewelry",
            "type":"Retail Goods"
        }
    ],
    "sg:phone":"+1 281 548 1074",
    "sg:postcode":"77338",
    "sg:province":"TX",
    "wof:name":"Steka Enterprises",
    "wof:placetype":"venue"
},
  "geometry": {"coordinates":[-95.253591,29.990705],"type":"Point"}
}