{
  "type": "Feature",
  "properties": {
    "iso:country":"US",
    "sg:address":"6760 Abrams Rd",
    "sg:city":"Dallas",
    "sg:classifiers":[
        {
            "category":"Restaurant",
            "type":"Food & Drink"
        }
    ],
    "sg:menulink":"http://www.allmenus.com/tx/northeast/62525-subway/menu/",
    "sg:phone":"+1 214 553 9300",
    "sg:postcode":"75231",
    "sg:province":"TX",
    "sg:tags":[
        "american",
        "sandwich"
    ],
    "wof:name":"Subway",
    "wof:placetype":"venue"
},
  "geometry": {"coordinates":[-96.74287,32.867044],"type":"Point"}
}