{
  "type": "Feature",
  "properties": {
    "iso:country":"US",
    "sg:address":"1129 Maxwell St",
    "sg:city":"Buffalo Gap",
    "sg:classifiers":[
        {
            "category":"Retail",
            "subcategory":"Repair Shop",
            "type":"Services"
        }
    ],
    "sg:phone":"+1 325 672 3882",
    "sg:postcode":"79508",
    "sg:province":"TX",
    "wof:name":"Abilene Tub & Tile",
    "wof:placetype":"venue"
},
  "geometry": {"coordinates":[-99.82515100000001,32.272009],"type":"Point"}
}