{
  "type": "Feature",
  "properties": {
    "iso:country":"US",
    "sg:address":"1012 Ridgeview St",
    "sg:city":"Mesquite",
    "sg:classifiers":[
        {
            "category":"Restaurant",
            "type":"Food & Drink"
        }
    ],
    "sg:phone":"+1 972 329 0640",
    "sg:postcode":"75149",
    "sg:province":"TX",
    "sg:tags":[
        "eating"
    ],
    "wof:name":"Rodeos Home Cooking",
    "wof:placetype":"venue"
},
  "geometry": {"coordinates":[-96.62173199999999,32.781535],"type":"Point"}
}