{
  "type": "Feature",
  "properties": {
    "iso:country":"US",
    "sg:address":"14891 State Highway 205",
    "sg:city":"Terrell",
    "sg:classifiers":[
        {
            "category":"Transit Center",
            "subcategory":"Freight",
            "type":"Transportation"
        },
        {
            "category":"Autos & Motor Vehicles",
            "subcategory":"Recreational Vehicle Sales",
            "type":"Retail Goods"
        },
        {
            "category":"Building & Trades",
            "subcategory":"Construction",
            "type":"Services"
        },
        {
            "category":"Manufacturing",
            "subcategory":"Building Materials",
            "type":"Manufacturing & Wholesale Goods"
        }
    ],
    "sg:phone":"+1 972 563 8333",
    "sg:postcode":"75160",
    "sg:province":"TX",
    "sg:tags":[
        "repairing",
        "automobile",
        "cranes-mobile",
        "facilities-renting",
        "hoist",
        "crane"
    ],
    "sg:website":"http://www.fg-ind.com",
    "wof:name":"F & G Industries",
    "wof:placetype":"venue"
},
  "geometry": {"coordinates":[-96.34017900000001,32.802322],"type":"Point"}
}