{
  "type": "Feature",
  "properties": {
    "iso:country":"US",
    "sg:address":"901 Waterfall Way",
    "sg:city":"Richardson",
    "sg:classifiers":[
        {
            "category":"Building & Trades",
            "subcategory":"Cleaning & Sanitation",
            "type":"Services"
        }
    ],
    "sg:phone":"+1 972 437 4390",
    "sg:postcode":"75080",
    "sg:province":"TX",
    "sg:tags":[
        "janitor"
    ],
    "wof:name":"Angel Star Cleaning Svc Coml",
    "wof:placetype":"venue"
},
  "geometry": {"coordinates":[-96.764278,32.941773],"type":"Point"}
}