{
  "type": "Feature",
  "properties": {
    "iso:country":"US",
    "sg:address":"111 Idle Creek Ct",
    "sg:city":"Desoto",
    "sg:classifiers":[
        {
            "category":"Shopping",
            "subcategory":"Luggage & Leather Goods",
            "type":"Retail Goods"
        }
    ],
    "sg:phone":"+1 972 230 4980",
    "sg:postcode":"75115",
    "sg:province":"TX",
    "wof:name":"International Leather",
    "wof:placetype":"venue"
},
  "geometry": {"coordinates":[-96.83352600000001,32.591175],"type":"Point"}
}