{
  "type": "Feature",
  "properties": {
    "iso:country":"US",
    "sg:address":"11479 North Fwy",
    "sg:city":"Houston",
    "sg:classifiers":[
        {
            "category":"Bars & Pubs",
            "type":"Food & Drink"
        }
    ],
    "sg:phone":"+1 281 445 4171",
    "sg:postcode":"77060",
    "sg:province":"TX",
    "sg:tags":[
        "drinking",
        "restaurant"
    ],
    "wof:name":"Fiesta Michoacan",
    "wof:placetype":"venue"
},
  "geometry": {"coordinates":[-95.412498,29.9331],"type":"Point"}
}