{
  "type": "Feature",
  "properties": {
    "iso:country":"US",
    "sg:address":"29195 Old Fredericksburg Rd",
    "sg:city":"Fair Oaks Ranch",
    "sg:classifiers":[
        {
            "category":"Professional",
            "subcategory":"Business Services",
            "type":"Services"
        }
    ],
    "sg:phone":"+1 830 755 8446",
    "sg:postcode":"78015",
    "sg:province":"TX",
    "sg:tags":[
        "interior",
        "consultant",
        "design",
        "decorator"
    ],
    "wof:name":"Liza Pfeiffer Interiors",
    "wof:placetype":"venue"
},
  "geometry": {"coordinates":[-98.676559,29.738131],"type":"Point"}
}