{
  "type": "Feature",
  "properties": {
    "iso:country":"US",
    "sg:address":"212 Delby St",
    "sg:city":"Hutto",
    "sg:classifiers":[
        {
            "category":"Professional",
            "subcategory":"Management & Consulting",
            "type":"Services"
        },
        {
            "category":"Professional",
            "subcategory":"Research",
            "type":"Services"
        }
    ],
    "sg:phone":"+1 512 809 1468",
    "sg:postcode":"78634",
    "sg:province":"TX",
    "sg:tags":[
        "marketing",
        "economic",
        "market",
        "analysis",
        "consultant"
    ],
    "wof:name":"Total Market Solutions",
    "wof:placetype":"venue"
},
  "geometry": {"coordinates":[-97.550309,30.550584],"type":"Point"}
}