{
  "type": "Feature",
  "properties": {
    "iso:country":"US",
    "sg:address":"10401 Market St",
    "sg:city":"Houston",
    "sg:classifiers":[
        {
            "category":"Retail",
            "subcategory":"Auto Repair",
            "type":"Services"
        }
    ],
    "sg:phone":"+1 713 673 5599",
    "sg:postcode":"77029",
    "sg:province":"TX",
    "sg:tags":[
        "repairing",
        "automobile"
    ],
    "wof:name":"John's Garage",
    "wof:placetype":"venue"
},
  "geometry": {"coordinates":[-95.24469000000001,29.767536],"type":"Point"}
}