{
  "type": "Feature",
  "properties": {
    "iso:country":"US",
    "sg:address":"328 S Main St",
    "sg:city":"Conroe",
    "sg:classifiers":[
        {
            "category":"Shopping",
            "subcategory":"Computers & Home Electronics",
            "type":"Retail Goods"
        }
    ],
    "sg:phone":"+1 936 494 1424",
    "sg:postcode":"77301",
    "sg:province":"TX",
    "wof:name":"Conroe Car Audio",
    "wof:placetype":"venue"
},
  "geometry": {"coordinates":[-95.45706800000001,30.30459],"type":"Point"}
}