{
  "type": "Feature",
  "properties": {
    "iso:country":"US",
    "sg:address":"11037 Market St",
    "sg:city":"Houston",
    "sg:classifiers":[
        {
            "category":"Food & Beverages",
            "subcategory":"Groceries & Convenience Stores",
            "type":"Retail Goods"
        }
    ],
    "sg:phone":"+1 713 451 1666",
    "sg:postcode":"77029",
    "sg:province":"TX",
    "wof:name":"Alief Petroleum",
    "wof:placetype":"venue"
},
  "geometry": {"coordinates":[-95.235389,29.767712],"type":"Point"}
}