{
  "type": "Feature",
  "properties": {
    "iso:country":"US",
    "sg:address":"1544 FM 1960 W",
    "sg:city":"Houston",
    "sg:classifiers":[
        {
            "category":"Arts & Performance",
            "subcategory":"Theater",
            "type":"Entertainment"
        }
    ],
    "sg:phone":"+1 281 866 8659",
    "sg:postcode":"77090",
    "sg:province":"TX",
    "sg:tags":[
        "live",
        "music"
    ],
    "wof:name":"8668 Wedding Music Invitations",
    "wof:placetype":"venue"
},
  "geometry": {"coordinates":[-95.45183,30.013354],"type":"Point"}
}