{
  "type": "Feature",
  "properties": {
    "iso:country":"US",
    "sg:address":"8700 Norton St",
    "sg:city":"El Paso",
    "sg:classifiers":[
        {
            "category":"Real Estate",
            "subcategory":"Real Estate Operator",
            "type":"Services"
        }
    ],
    "sg:phone":"+1 915 591 4940",
    "sg:postcode":"79904",
    "sg:province":"TX",
    "sg:tags":[
        "building",
        "apartment"
    ],
    "wof:name":"Norton Manor Apartments",
    "wof:placetype":"venue"
},
  "geometry": {"coordinates":[-106.435743,31.862679],"type":"Point"}
}