{
  "type": "Feature",
  "properties": {
    "iso:country":"US",
    "sg:address":"3614 Deerbrook Ct",
    "sg:city":"Pearland",
    "sg:classifiers":[
        {
            "category":"Professional",
            "subcategory":"Business Services",
            "type":"Services"
        }
    ],
    "sg:phone":"+1 281 489 9384",
    "sg:postcode":"77584",
    "sg:province":"TX",
    "wof:name":"S&S Enterprises",
    "wof:placetype":"venue"
},
  "geometry": {"coordinates":[-95.358789,29.531101],"type":"Point"}
}