{
  "type": "Feature",
  "properties": {
    "iso:country":"US",
    "sg:address":"8201 Burnet Road",
    "sg:city":"Austin",
    "sg:classifiers":[
        {
            "category":"Home & Garden",
            "subcategory":"Furniture",
            "type":"Retail Goods"
        }
    ],
    "sg:phone":"+1 512 302 1617",
    "sg:postcode":"78757",
    "sg:province":"TX",
    "sg:tags":[
        "store"
    ],
    "wof:name":"Primitives Furniture & Accessories",
    "wof:placetype":"venue"
},
  "geometry": {"coordinates":[-97.729488,30.361735],"type":"Point"}
}