{
  "type": "Feature",
  "properties": {
    "iso:country":"US",
    "sg:address":"136 S Main St",
    "sg:city":"Farmersville",
    "sg:classifiers":[
        {
            "category":"Home & Garden",
            "subcategory":"Furniture",
            "type":"Retail Goods"
        }
    ],
    "sg:phone":"+1 972 782 6888",
    "sg:postcode":"75442",
    "sg:province":"TX",
    "wof:name":"May's Warehouse",
    "wof:placetype":"venue"
},
  "geometry": {"coordinates":[-96.36009199999999,33.162587],"type":"Point"}
}