{
  "type": "Feature",
  "properties": {
    "iso:country":"US",
    "sg:address":"12804 East Fwy",
    "sg:city":"Houston",
    "sg:classifiers":[
        {
            "category":"Professional",
            "subcategory":"Computer Services",
            "type":"Services"
        }
    ],
    "sg:phone":"+1 713 450 2500",
    "sg:postcode":"77015",
    "sg:province":"TX",
    "sg:tags":[
        "stereo",
        "installation"
    ],
    "wof:name":"Precision Car Audio",
    "wof:placetype":"venue"
},
  "geometry": {"coordinates":[-95.205806,29.770792],"type":"Point"}
}