{
  "type": "Feature",
  "properties": {
    "iso:country":"US",
    "sg:address":"229 Old Brock Rd",
    "sg:city":"Azle",
    "sg:classifiers":[
        {
            "category":"Building & Trades",
            "subcategory":"Construction",
            "type":"Services"
        }
    ],
    "sg:phone":"+1 817 341 3208",
    "sg:postcode":"76088",
    "sg:province":"TX",
    "sg:tags":[
        "residential"
    ],
    "wof:name":"Edniburgh Construction Inc",
    "wof:placetype":"venue"
},
  "geometry": {"coordinates":[-97.82108100000001,32.742153],"type":"Point"}
}