{
  "type": "Feature",
  "properties": {
    "iso:country":"US",
    "sg:address":"6335 Palo Pinto Ave",
    "sg:city":"Dallas",
    "sg:classifiers":[
        {
            "category":"Professional",
            "subcategory":"Accounting & Tax Preparation",
            "type":"Services"
        }
    ],
    "sg:phone":"+1 214 826 5777",
    "sg:postcode":"75214",
    "sg:province":"TX",
    "sg:tags":[
        "billing"
    ],
    "wof:name":"Reliant Medical Billing",
    "wof:placetype":"venue"
},
  "geometry": {"coordinates":[-96.753767,32.820139],"type":"Point"}
}