{
  "type": "Feature",
  "properties": {
    "iso:country":"US",
    "sg:address":"201 E 9th St",
    "sg:city":"Houston",
    "sg:classifiers":[
        {
            "category":"Place Of Worship",
            "subcategory":"Church",
            "type":"Public Place"
        },
        {
            "category":"Place Of Worship",
            "type":"Public Place"
        }
    ],
    "sg:phone":"+1 713 861 3102",
    "sg:postcode":"77007",
    "sg:province":"TX",
    "sg:tags":[
        "churches-baptist-general",
        "churches-baptist-southern",
        "churches-baptist"
    ],
    "sg:website":"http://www.fbcheights.org",
    "wof:name":"First Baptist Church Heights",
    "wof:placetype":"venue"
},
  "geometry": {"coordinates":[-95.39634700000001,29.78701],"type":"Point"}
}