{
  "type": "Feature",
  "properties": {
    "iso:country":"US",
    "sg:address":"4425 W Airport Fwy",
    "sg:city":"Irving",
    "sg:classifiers":[
        {
            "category":"Manufacturing",
            "subcategory":"Metals",
            "type":"Manufacturing & Wholesale Goods"
        },
        {
            "category":"Building & Trades",
            "subcategory":"Construction",
            "type":"Services"
        }
    ],
    "sg:phone":"+1 972 659 0828",
    "sg:postcode":"75062",
    "sg:province":"TX",
    "sg:tags":[
        "plate",
        "work",
        "fabricated",
        "culvert",
        "mfg"
    ],
    "wof:name":"Contech Construction Prods Inc",
    "wof:placetype":"venue"
},
  "geometry": {"coordinates":[-97.00924500000001,32.83794],"type":"Point"}
}