{
  "type": "Feature",
  "properties": {
    "iso:country":"US",
    "sg:address":"2804 State Highway 31 E",
    "sg:city":"Kilgore",
    "sg:classifiers":[
        {
            "category":"Retail",
            "subcategory":"Repair Shop",
            "type":"Services"
        },
        {
            "category":"Building & Trades",
            "subcategory":"Equipment Rental",
            "type":"Services"
        }
    ],
    "sg:phone":"+1 903 983 1033",
    "sg:postcode":"75662",
    "sg:province":"TX",
    "sg:tags":[
        "tools-renting",
        "saw"
    ],
    "wof:name":"Richardson Enterprises",
    "wof:placetype":"venue"
},
  "geometry": {"coordinates":[-94.85130700000001,32.408473],"type":"Point"}
}