{
  "type": "Feature",
  "properties": {
    "iso:country":"US",
    "sg:address":"4202 Greenwood Dr",
    "sg:city":"Corpus Christi",
    "sg:classifiers":[
        {
            "category":"Social Services",
            "type":"Services"
        }
    ],
    "sg:phone":"+1 361 854 2011",
    "sg:postcode":"78416",
    "sg:province":"TX",
    "sg:tags":[
        "agency",
        "adoption"
    ],
    "wof:name":"Texas Department Of Human Svc",
    "wof:placetype":"venue"
},
  "geometry": {"coordinates":[-97.43306,27.756264],"type":"Point"}
}