{
  "type": "Feature",
  "properties": {
    "iso:country":"US",
    "sg:address":"1642 S Buckner Blvd",
    "sg:city":"Dallas",
    "sg:classifiers":[
        {
            "category":"Shopping",
            "subcategory":"Party Supplies",
            "type":"Retail Goods"
        },
        {
            "category":"Shopping",
            "subcategory":"Gifts & Souvenirs",
            "type":"Retail Goods"
        }
    ],
    "sg:phone":"+1 214 391 1316",
    "sg:postcode":"75217",
    "sg:province":"TX",
    "sg:tags":[
        "shop"
    ],
    "wof:name":"Imelda's Gift Shop",
    "wof:placetype":"venue"
},
  "geometry": {"coordinates":[-96.68264600000001,32.740458],"type":"Point"}
}