{
  "type": "Feature",
  "properties": {
    "iso:country":"US",
    "sg:address":"417 Coronado Dr",
    "sg:city":"Grand Prairie",
    "sg:classifiers":[
        {
            "category":"Professional",
            "subcategory":"Business Services",
            "type":"Services"
        }
    ],
    "sg:phone":"+1 972 642 4170",
    "sg:postcode":"75052",
    "sg:province":"TX",
    "wof:name":"Lna Enterprise",
    "wof:placetype":"venue"
},
  "geometry": {"coordinates":[-97.002608,32.679041],"type":"Point"}
}