{
  "type": "Feature",
  "properties": {
    "iso:country":"US",
    "sg:address":"3727 W Kiest Blvd",
    "sg:city":"Dallas",
    "sg:classifiers":[
        {
            "category":"Organizations",
            "subcategory":"Religious Organization",
            "type":"Services"
        }
    ],
    "sg:phone":"+1 214 331 5459",
    "sg:postcode":"75233",
    "sg:province":"TX",
    "wof:name":"New Life Bible Fellowship",
    "wof:placetype":"venue"
},
  "geometry": {"coordinates":[-96.880954,32.705896],"type":"Point"}
}