{
  "type": "Feature",
  "properties": {
    "iso:country":"US",
    "sg:address":"1111 Louisiana St",
    "sg:city":"Houston",
    "sg:classifiers":[
        {
            "category":"Building & Trades",
            "subcategory":"Construction",
            "type":"Services"
        }
    ],
    "sg:phone":"+1 713 654 0948",
    "sg:postcode":"77002",
    "sg:province":"TX",
    "sg:tags":[
        "contractor"
    ],
    "wof:name":"Ka-Tex Constructors",
    "wof:placetype":"venue"
},
  "geometry": {"coordinates":[-95.368584,29.757065],"type":"Point"}
}