{
  "type": "Feature",
  "properties": {
    "iso:country":"US",
    "sg:address":"104 Austin St",
    "sg:city":"Balmorhea",
    "sg:classifiers":[
        {
            "category":"Utilities",
            "subcategory":"Water",
            "type":"Services"
        }
    ],
    "sg:phone":"+1 432 375 2238",
    "sg:postcode":"79718",
    "sg:province":"TX",
    "sg:tags":[
        "company",
        "sewage"
    ],
    "wof:name":"Reeves County Water",
    "wof:placetype":"venue"
},
  "geometry": {"coordinates":[-103.74066999999999,30.9866],"type":"Point"}
}