{
  "type": "Feature",
  "properties": {
    "iso:country":"US",
    "sg:address":"4701 N I H 35",
    "sg:city":"Austin",
    "sg:classifiers":[
        {
            "category":"Travel",
            "subcategory":"Hotels & Motels",
            "type":"Entertainment"
        }
    ],
    "sg:phone":"+1 512 448 0091",
    "sg:postcode":"78722",
    "sg:province":"TX",
    "sg:website":"www.redroof.com",
    "wof:name":"Red Roof Inn",
    "wof:placetype":"venue"
},
  "geometry": {"coordinates":[-97.712086,30.306207],"type":"Point"}
}