{
  "type": "Feature",
  "properties": {
    "iso:country":"US",
    "sg:address":"3808 Magnolia St",
    "sg:city":"Pearland",
    "sg:classifiers":[
        {
            "category":"Building & Trades",
            "subcategory":"Equipment Rental",
            "type":"Services"
        }
    ],
    "sg:phone":"+1 281 485 0500",
    "sg:postcode":"77584",
    "sg:province":"TX",
    "sg:tags":[
        "oil",
        "well",
        "supply"
    ],
    "wof:name":"Oil Field Rental Svc Co",
    "wof:placetype":"venue"
},
  "geometry": {"coordinates":[-95.280677,29.546483],"type":"Point"}
}