{
  "type": "Feature",
  "properties": {
    "iso:country":"US",
    "sg:address":"201 W 54th St",
    "sg:city":"Odessa",
    "sg:classifiers":[
        {
            "category":"Professional",
            "subcategory":"Management & Consulting",
            "type":"Services"
        }
    ],
    "sg:phone":"+1 432 367 9810",
    "sg:postcode":"79764",
    "sg:province":"TX",
    "sg:tags":[
        "consultant",
        "training"
    ],
    "wof:name":"Catesco",
    "wof:placetype":"venue"
},
  "geometry": {"coordinates":[-102.39197299999999,31.893784],"type":"Point"}
}