{
  "type": "Feature",
  "properties": {
    "iso:country":"US",
    "sg:address":"2200 Regency Dr",
    "sg:city":"Irving",
    "sg:classifiers":[
        {
            "category":"Wholesale",
            "subcategory":"Construction Materials",
            "type":"Manufacturing & Wholesale Goods"
        },
        {
            "category":"Wholesale",
            "subcategory":"Hardware",
            "type":"Manufacturing & Wholesale Goods"
        }
    ],
    "sg:phone":"+1 972 785 9900",
    "sg:postcode":"75062",
    "sg:province":"TX",
    "sg:tags":[
        "gas",
        "burner"
    ],
    "sg:website":"www.thorpeproducts.com",
    "wof:name":"Thorpe Products Co",
    "wof:placetype":"venue"
},
  "geometry": {"coordinates":[-96.89538899999999,32.83835],"type":"Point"}
}