{
  "type": "Feature",
  "properties": {
    "iso:country":"US",
    "sg:address":"11122 Javalin Trl",
    "sg:city":"Helotes",
    "sg:classifiers":[
        {
            "category":"Shopping",
            "subcategory":"Gifts & Souvenirs",
            "type":"Retail Goods"
        }
    ],
    "sg:phone":"+1 210 695 8228",
    "sg:postcode":"78023",
    "sg:province":"TX",
    "sg:tags":[
        "house",
        "online",
        "order",
        "mail"
    ],
    "wof:name":"Pacific Arts Of San Antonio",
    "wof:placetype":"venue"
},
  "geometry": {"coordinates":[-98.71035500000001,29.556921],"type":"Point"}
}