{
  "type": "Feature",
  "properties": {
    "iso:country":"US",
    "sg:address":"442 N Treadaway Blvd",
    "sg:city":"Abilene",
    "sg:classifiers":[
        {
            "category":"Organizations",
            "subcategory":"Religious Organization",
            "type":"Services"
        }
    ],
    "sg:phone":"+1 325 677 3197",
    "sg:postcode":"79601",
    "sg:province":"TX",
    "sg:tags":[
        "church"
    ],
    "wof:name":"Primera Baptist",
    "wof:placetype":"venue"
},
  "geometry": {"coordinates":[-99.726463,32.452721],"type":"Point"}
}