{
  "type": "Feature",
  "properties": {
    "iso:country":"US",
    "sg:address":"5409 Parkview Dr",
    "sg:city":"Fort Worth",
    "sg:classifiers":[
        {
            "category":"Professional",
            "subcategory":"Management & Consulting",
            "type":"Services"
        }
    ],
    "sg:phone":"+1 817 281 8590",
    "sg:postcode":"76148",
    "sg:province":"TX",
    "wof:name":"Turf Managment Systems",
    "wof:placetype":"venue"
},
  "geometry": {"coordinates":[-97.257386,32.844626],"type":"Point"}
}