{
  "type": "Feature",
  "properties": {
    "iso:country":"US",
    "sg:address":"407 Country Pl",
    "sg:city":"Colleyville",
    "sg:classifiers":[
        {
            "category":"Shopping",
            "subcategory":"Clothing, Apparel, & Fashions",
            "type":"Retail Goods"
        }
    ],
    "sg:phone":"+1 817 605 0006",
    "sg:postcode":"76034",
    "sg:province":"TX",
    "wof:name":"M3s Designs Ltd",
    "wof:placetype":"venue"
},
  "geometry": {"coordinates":[-97.175539,32.90015],"type":"Point"}
}