{
  "type": "Feature",
  "properties": {
    "iso:country":"US",
    "sg:address":"104 W Carrie Manor St",
    "sg:city":"Manor",
    "sg:classifiers":[
        {
            "category":"Social Services",
            "subcategory":"Child Care",
            "type":"Services"
        }
    ],
    "sg:phone":"+1 512 278 8844",
    "sg:postcode":"78653",
    "sg:province":"TX",
    "sg:tags":[
        "day"
    ],
    "wof:name":"Starting Gate",
    "wof:placetype":"venue"
},
  "geometry": {"coordinates":[-97.558127,30.339316],"type":"Point"}
}