{
  "type": "Feature",
  "properties": {
    "iso:country":"US",
    "sg:address":"1213 Wroxton Way",
    "sg:city":"Round Rock",
    "sg:classifiers":[
        {
            "category":"Wholesale",
            "subcategory":"Vending Machines",
            "type":"Manufacturing & Wholesale Goods"
        }
    ],
    "sg:phone":"+1 512 255 3105",
    "sg:postcode":"78664",
    "sg:province":"TX",
    "wof:name":"Revilla Vending",
    "wof:placetype":"venue"
},
  "geometry": {"coordinates":[-97.665926,30.520743],"type":"Point"}
}