{
  "type": "Feature",
  "properties": {
    "iso:country":"US",
    "sg:address":"3130 S Soncy Rd",
    "sg:city":"Amarillo",
    "sg:classifiers":[
        {
            "category":"Fast Food",
            "type":"Food & Drink"
        },
        {
            "category":"Restaurant",
            "type":"Food & Drink"
        },
        {
            "category":"Food & Beverages",
            "subcategory":"Groceries & Convenience Stores",
            "type":"Retail Goods"
        }
    ],
    "sg:phone":"+1 806 352 5811",
    "sg:postcode":"79124",
    "sg:province":"TX",
    "sg:tags":[
        "shop",
        "american",
        "sandwich",
        "take"
    ],
    "sg:website":"http://www.subway.com",
    "wof:name":"SUBWAY",
    "wof:placetype":"venue"
},
  "geometry": {"coordinates":[-101.938607,35.240767],"type":"Point"}
}