{
  "type": "Feature",
  "properties": {
    "iso:country":"US",
    "sg:address":"200 W Boyd Dr",
    "sg:city":"Allen",
    "sg:classifiers":[
        {
            "category":"Social Services",
            "subcategory":"Child Care",
            "type":"Services"
        }
    ],
    "sg:phone":"+1 972 390 9535",
    "sg:postcode":"75013",
    "sg:province":"TX",
    "sg:tags":[
        "kindergarten",
        "academic",
        "school"
    ],
    "wof:name":"Exclusively Three Four & Five",
    "wof:placetype":"venue"
},
  "geometry": {"coordinates":[-96.671736,33.104202],"type":"Point"}
}