{
  "type": "Feature",
  "properties": {
    "iso:country":"US",
    "sg:address":"320 Adams Dr",
    "sg:city":"Weatherford",
    "sg:classifiers":[
        {
            "category":"Fast Food",
            "type":"Food & Drink"
        },
        {
            "category":"Restaurant",
            "type":"Food & Drink"
        }
    ],
    "sg:phone":"+1 817 598 0432",
    "sg:postcode":"76086",
    "sg:province":"TX",
    "sg:tags":[
        "chicken",
        "style",
        "american",
        "family",
        "take"
    ],
    "sg:website":"http://www.buffalowildwings.com/",
    "wof:name":"Buffalo Wild Wings",
    "wof:placetype":"venue"
},
  "geometry": {"coordinates":[-97.78913900000001,32.731949],"type":"Point"}
}