{
  "type": "Feature",
  "properties": {
    "iso:country":"US",
    "sg:address":"2021 Saturn Rd Ste A",
    "sg:city":"Garland",
    "sg:classifiers":[
        {
            "category":"Place Of Worship",
            "subcategory":"Church",
            "type":"Public Place"
        },
        {
            "category":"Place Of Worship",
            "type":"Public Place"
        }
    ],
    "sg:phone":"+1 972 840 4914",
    "sg:postcode":"75041",
    "sg:province":"TX",
    "sg:tags":[
        "churches-pentecostal-independent",
        "churches-pentecostal"
    ],
    "wof:name":"Association Of Evangelical Ministries",
    "wof:placetype":"venue"
},
  "geometry": {"coordinates":[-96.648247,32.893671],"type":"Point"}
}