{
  "type": "Feature",
  "properties": {
    "iso:country":"US",
    "sg:address":"2114 Holliday Rd",
    "sg:city":"Wichita Falls",
    "sg:classifiers":[
        {
            "category":"Banks & Credit Unions",
            "subcategory":"Bank",
            "type":"Services"
        }
    ],
    "sg:phone":"+1 940 767 0550",
    "sg:postcode":"76301",
    "sg:province":"TX",
    "sg:tags":[
        "personal",
        "institution"
    ],
    "wof:name":"Faith City Loan Co",
    "wof:placetype":"venue"
},
  "geometry": {"coordinates":[-98.494421,33.893523],"type":"Point"}
}