{
  "type": "Feature",
  "properties": {
    "iso:country":"US",
    "sg:address":"1416 N Main St Ste 100",
    "sg:city":"Pearland",
    "sg:classifiers":[
        {
            "category":"Building & Trades",
            "subcategory":"Electrical",
            "type":"Services"
        }
    ],
    "sg:phone":"+1 281 485 6575",
    "sg:postcode":"77581",
    "sg:province":"TX",
    "sg:tags":[
        "electrician"
    ],
    "sg:website":"www.wescosystems.com",
    "wof:name":"Wesco System Inc",
    "wof:placetype":"venue"
},
  "geometry": {"coordinates":[-95.28649900000001,29.585199],"type":"Point"}
}