{
  "type": "Feature",
  "properties": {
    "iso:country":"US",
    "sg:address":"117 Peach St",
    "sg:city":"Seguin",
    "sg:classifiers":[
        {
            "category":"Personal",
            "subcategory":"Beauty Salon",
            "type":"Services"
        }
    ],
    "sg:phone":"+1 830 372 0881",
    "sg:postcode":"78155",
    "sg:province":"TX",
    "sg:tags":[
        "shop",
        "barber"
    ],
    "wof:name":"Professional Hair Salon",
    "wof:placetype":"venue"
},
  "geometry": {"coordinates":[-97.951144,29.569327],"type":"Point"}
}