{
  "type": "Feature",
  "properties": {
    "iso:country":"US",
    "sg:address":"609 W Harwood Rd",
    "sg:city":"Hurst",
    "sg:classifiers":[
        {
            "category":"Shopping",
            "subcategory":"Crafts & Fabrics",
            "type":"Retail Goods"
        }
    ],
    "sg:phone":"+1 817 581 7252",
    "sg:postcode":"76054",
    "sg:province":"TX",
    "sg:tags":[
        "sewing"
    ],
    "wof:name":"Jo-Ann Fabrics & Crafts",
    "wof:placetype":"venue"
},
  "geometry": {"coordinates":[-97.17857100000001,32.8473],"type":"Point"}
}