{
  "type": "Feature",
  "properties": {
    "iso:country":"US",
    "sg:address":"1358 Woodbrook Ln",
    "sg:city":"Southlake",
    "sg:classifiers":[
        {
            "category":"Professional",
            "subcategory":"Management & Consulting",
            "type":"Services"
        }
    ],
    "sg:phone":"+1 817 424 0851",
    "sg:postcode":"76092",
    "sg:province":"TX",
    "sg:tags":[
        "business"
    ],
    "wof:name":"T H Harden",
    "wof:placetype":"venue"
},
  "geometry": {"coordinates":[-97.176863,32.954168],"type":"Point"}
}