{
  "type": "Feature",
  "properties": {
    "iso:country":"US",
    "sg:address":"15330 Lyndon B Johnson Fwy",
    "sg:city":"Mesquite",
    "sg:classifiers":[
        {
            "category":"Building & Trades",
            "subcategory":"Cleaning & Sanitation",
            "type":"Services"
        }
    ],
    "sg:phone":"+1 972 270 7750",
    "sg:postcode":"75150",
    "sg:province":"TX",
    "sg:tags":[
        "carpet"
    ],
    "sg:website":"www.signaturecarpetcleaning.com",
    "wof:name":"Signature Carpet Cleaning",
    "wof:placetype":"venue"
},
  "geometry": {"coordinates":[-96.63332699999999,32.844373],"type":"Point"}
}