{
  "type": "Feature",
  "properties": {
    "iso:country":"US",
    "sg:address":"2001 Towne View Blvd",
    "sg:city":"Flower Mound",
    "sg:classifiers":[
        {
            "category":"Professional",
            "subcategory":"Computer Services",
            "type":"Services"
        }
    ],
    "sg:phone":"+1 214 334 9251",
    "sg:postcode":"75028",
    "sg:province":"TX",
    "sg:tags":[
        "consulting"
    ],
    "wof:name":"Technile LLC",
    "wof:placetype":"venue"
},
  "geometry": {"coordinates":[-97.067263,33.012085],"type":"Point"}
}