{
  "type": "Feature",
  "properties": {
    "iso:country":"US",
    "sg:address":"5053 S Colony Blvd",
    "sg:city":"Lewisville",
    "sg:classifiers":[
        {
            "category":"Building & Trades",
            "subcategory":"Landscaping Services",
            "type":"Services"
        }
    ],
    "sg:phone":"+1 972 740 7747",
    "sg:postcode":"75056",
    "sg:province":"TX",
    "wof:name":"Experience Lawn Care",
    "wof:placetype":"venue"
},
  "geometry": {"coordinates":[-96.88387,33.081982],"type":"Point"}
}