{
  "type": "Feature",
  "properties": {
    "iso:country":"US",
    "sg:address":"36 Wilson Rd",
    "sg:city":"Humble",
    "sg:classifiers":[
        {
            "category":"Health Services",
            "subcategory":"Chiropractor",
            "type":"Services"
        }
    ],
    "sg:phone":"+1 281 812 4325",
    "sg:postcode":"77338",
    "sg:province":"TX",
    "sg:tags":[
        "therapist",
        "physical"
    ],
    "sg:website":"http://atascahealth.com",
    "wof:name":"Atasca Health & Chiropractic",
    "wof:placetype":"venue"
},
  "geometry": {"coordinates":[-95.24992899999999,30.000528],"type":"Point"}
}