{
  "type": "Feature",
  "properties": {
    "iso:country":"US",
    "sg:address":"910 S Wharton St",
    "sg:city":"El Campo",
    "sg:classifiers":[
        {
            "category":"Building & Trades",
            "subcategory":"Construction",
            "type":"Services"
        }
    ],
    "sg:phone":"+1 979 543 7192",
    "sg:postcode":"77437",
    "sg:province":"TX",
    "sg:tags":[
        "contractor"
    ],
    "wof:name":"Ott Construction",
    "wof:placetype":"venue"
},
  "geometry": {"coordinates":[-96.261185,29.18993],"type":"Point"}
}