{
  "type": "Feature",
  "properties": {
    "iso:country":"US",
    "sg:address":"5214 Ponderosa Ln",
    "sg:city":"Corpus Christi",
    "sg:classifiers":[
        {
            "category":"Professional",
            "type":"Services"
        }
    ],
    "sg:phone":"+1 361 884 4935",
    "sg:postcode":"78415",
    "sg:province":"TX",
    "sg:tags":[
        "establishment"
    ],
    "wof:name":"Whitesands Operating LLC",
    "wof:placetype":"venue"
},
  "geometry": {"coordinates":[-97.411789,27.723022],"type":"Point"}
}