{
  "type": "Feature",
  "properties": {
    "iso:country":"US",
    "sg:address":"5989 N Mesa St",
    "sg:city":"El Paso",
    "sg:classifiers":[
        {
            "category":"Personal",
            "subcategory":"Beauty Salon",
            "type":"Services"
        }
    ],
    "sg:phone":"+1 915 584 2271",
    "sg:postcode":"79912",
    "sg:province":"TX",
    "wof:name":"Coronado Beauty Salon",
    "wof:placetype":"venue"
},
  "geometry": {"coordinates":[-106.529712,31.830037],"type":"Point"}
}