{
  "type": "Feature",
  "properties": {
    "iso:country":"US",
    "sg:address":"20811 Owl Creek Rd",
    "sg:city":"Gatesville",
    "sg:classifiers":[
        {
            "category":"Retail",
            "subcategory":"Repair Shop",
            "type":"Services"
        }
    ],
    "sg:phone":"+1 254 986 8400",
    "sg:postcode":"76528",
    "sg:province":"TX",
    "sg:tags":[
        "appliance",
        "electrical"
    ],
    "wof:name":"Day & Evening Appliance Repair",
    "wof:placetype":"venue"
},
  "geometry": {"coordinates":[-97.533085,31.237702],"type":"Point"}
}