{
  "type": "Feature",
  "properties": {
    "iso:country":"US",
    "sg:address":"4748 Old Bent Tree Ln",
    "sg:city":"Dallas",
    "sg:classifiers":[
        {
            "category":"Professional",
            "subcategory":"Advertising",
            "type":"Services"
        }
    ],
    "sg:phone":"+1 972 267 6677",
    "sg:postcode":"75287",
    "sg:province":"TX",
    "wof:name":"Information Design",
    "wof:placetype":"venue"
},
  "geometry": {"coordinates":[-96.82636100000001,32.99987],"type":"Point"}
}