{
  "type": "Feature",
  "properties": {
    "iso:country":"US",
    "sg:address":"2425 N Cooper St",
    "sg:city":"Arlington",
    "sg:classifiers":[
        {
            "category":"Professional",
            "subcategory":"Business Services",
            "type":"Services"
        }
    ],
    "sg:phone":"+1 817 261 9090",
    "sg:postcode":"76006",
    "sg:province":"TX",
    "wof:name":"Fire In Hole",
    "wof:placetype":"venue"
},
  "geometry": {"coordinates":[-97.114109,32.776588],"type":"Point"}
}