{
  "type": "Feature",
  "properties": {
    "iso:country":"US",
    "sg:address":"16250 Galveston Rd",
    "sg:city":"Webster",
    "sg:classifiers":[
        {
            "category":"Building & Trades",
            "subcategory":"Construction",
            "type":"Services"
        }
    ],
    "sg:phone":"+1 713 266 9116",
    "sg:postcode":"77598",
    "sg:province":"TX",
    "sg:tags":[
        "general",
        "contractor"
    ],
    "wof:name":"Multi Family Svc",
    "wof:placetype":"venue"
},
  "geometry": {"coordinates":[-95.135544,29.556497],"type":"Point"}
}