{
  "type": "Feature",
  "properties": {
    "iso:country":"US",
    "sg:address":"7733 Cypress Club Dr",
    "sg:city":"Fort Worth",
    "sg:classifiers":[
        {
            "category":"Professional",
            "subcategory":"Computer Services",
            "type":"Services"
        }
    ],
    "sg:phone":"+1 817 692 7318",
    "sg:postcode":"76137",
    "sg:province":"TX",
    "sg:tags":[
        "programing",
        "custom"
    ],
    "wof:name":"Eagles PC",
    "wof:placetype":"venue"
},
  "geometry": {"coordinates":[-97.26380899999999,32.883125],"type":"Point"}
}