{
  "type": "Feature",
  "properties": {
    "iso:country":"US",
    "sg:address":"5002 Graves Rd",
    "sg:city":"Alvin",
    "sg:classifiers":[
        {
            "category":"Shopping",
            "subcategory":"Gifts & Souvenirs",
            "type":"Retail Goods"
        }
    ],
    "sg:phone":"+1 409 925 5215",
    "sg:postcode":"77511",
    "sg:province":"TX",
    "sg:tags":[
        "shop"
    ],
    "wof:name":"Todays Gifts",
    "wof:placetype":"venue"
},
  "geometry": {"coordinates":[-95.16485299999999,29.379007],"type":"Point"}
}