{
  "type": "Feature",
  "properties": {
    "iso:country":"US",
    "sg:address":"23024 US Hwy 281",
    "sg:city":"San Benito",
    "sg:classifiers":[
        {
            "category":"Autos & Motor Vehicles",
            "subcategory":"Automobile Sales",
            "type":"Retail Goods"
        }
    ],
    "sg:phone":"+1 956 361 7909",
    "sg:postcode":"78586",
    "sg:province":"TX",
    "wof:name":"Silverado Truck Sales",
    "wof:placetype":"venue"
},
  "geometry": {"coordinates":[-97.64692599999999,26.030698],"type":"Point"}
}