{
  "type": "Feature",
  "properties": {
    "iso:country":"US",
    "sg:address":"415 Easy St",
    "sg:city":"Marlin",
    "sg:classifiers":[
        {
            "category":"Health Services",
            "subcategory":"Health Practitioner",
            "type":"Services"
        }
    ],
    "sg:phone":"+1 254 803 2346",
    "sg:postcode":"76661",
    "sg:province":"TX",
    "wof:name":"C & K Nurse Practioner Svcs",
    "wof:placetype":"venue"
},
  "geometry": {"coordinates":[-96.890242,31.311616],"type":"Point"}
}