{
  "type": "Feature",
  "properties": {
    "iso:country":"US",
    "sg:address":"7502 Morton St",
    "sg:city":"Dallas",
    "sg:classifiers":[
        {
            "category":"Professional",
            "subcategory":"Accounting & Tax Preparation",
            "type":"Services"
        }
    ],
    "sg:phone":"+1 469 330 9294",
    "sg:postcode":"75209",
    "sg:province":"TX",
    "sg:tags":[
        "auditing",
        "bookkeeping"
    ],
    "wof:name":"First Fruit Medical Ebs",
    "wof:placetype":"venue"
},
  "geometry": {"coordinates":[-96.823595,32.849377],"type":"Point"}
}