{
  "type": "Feature",
  "properties": {
    "iso:country":"US",
    "sg:address":"15902 Broad Oak Ct",
    "sg:city":"Tomball",
    "sg:classifiers":[
        {
            "category":"Professional",
            "subcategory":"Business Services",
            "type":"Services"
        }
    ],
    "sg:phone":"+1 281 351 2535",
    "sg:postcode":"77377",
    "sg:province":"TX",
    "wof:name":"Instep Technology",
    "wof:placetype":"venue"
},
  "geometry": {"coordinates":[-95.597084,30.006738],"type":"Point"}
}