{
  "type": "Feature",
  "properties": {
    "iso:country":"US",
    "sg:address":"21327 I- 45",
    "sg:city":"Spring",
    "sg:classifiers":[
        {
            "category":"Retail",
            "subcategory":"Car Wash",
            "type":"Services"
        }
    ],
    "sg:phone":"+1 281 288 1221",
    "sg:postcode":"77388",
    "sg:province":"TX",
    "sg:tags":[
        "automobile",
        "detail",
        "clean"
    ],
    "wof:name":"Dr Detail",
    "wof:placetype":"venue"
},
  "geometry": {"coordinates":[-95.435771,30.071494],"type":"Point"}
}