{
  "type": "Feature",
  "properties": {
    "iso:country":"US",
    "sg:address":"1220 Town East Blvd",
    "sg:city":"Mesquite",
    "sg:classifiers":[
        {
            "category":"Restaurant",
            "type":"Food & Drink"
        }
    ],
    "sg:phone":"+1 972 686 1700",
    "sg:postcode":"75150",
    "sg:province":"TX",
    "sg:tags":[
        "buffet",
        "pizza"
    ],
    "sg:website":"www.cicispizza.com/",
    "wof:name":"CiCi's Pizza",
    "wof:placetype":"venue"
},
  "geometry": {"coordinates":[-96.61290200000001,32.809436],"type":"Point"}
}