{
  "type": "Feature",
  "properties": {
    "iso:country":"US",
    "sg:address":"550 Benson Dr",
    "sg:city":"Kerrville",
    "sg:classifiers":[
        {
            "category":"Autos & Motor Vehicles",
            "subcategory":"Automobile Sales",
            "type":"Retail Goods"
        }
    ],
    "sg:phone":"+1 830 257 6121",
    "sg:postcode":"78028",
    "sg:province":"TX",
    "sg:tags":[
        "recreational"
    ],
    "wof:name":"Cecil Atkission Motors",
    "wof:placetype":"venue"
},
  "geometry": {"coordinates":[-99.11232800000001,30.071526],"type":"Point"}
}