{
  "type": "Feature",
  "properties": {
    "iso:country":"US",
    "sg:address":"1238 Woodhaven Blvd",
    "sg:city":"Fort Worth",
    "sg:classifiers":[
        {
            "category":"Recreation",
            "type":"Entertainment"
        }
    ],
    "sg:phone":"+1 817 547 5449",
    "sg:postcode":"76112",
    "sg:province":"TX",
    "sg:tags":[
        "instruction",
        "gymnastic"
    ],
    "wof:name":"Tumbleweed Gymnastics Inc",
    "wof:placetype":"venue"
},
  "geometry": {"coordinates":[-97.24048999999999,32.763091],"type":"Point"}
}