{
  "type": "Feature",
  "properties": {
    "iso:country":"US",
    "sg:address":"4117 Colleyville Blvd",
    "sg:city":"Colleyville",
    "sg:classifiers":[
        {
            "category":"Wholesale",
            "subcategory":"Office Equipment",
            "type":"Manufacturing & Wholesale Goods"
        }
    ],
    "sg:phone":"+1 817 281 8117",
    "sg:postcode":"76034",
    "sg:province":"TX",
    "wof:name":"Colleyville Copy Center",
    "wof:placetype":"venue"
},
  "geometry": {"coordinates":[-97.169167,32.869385],"type":"Point"}
}