{
  "type": "Feature",
  "properties": {
    "iso:country":"US",
    "sg:address":"5808 Speyside Dr",
    "sg:city":"Manor",
    "sg:classifiers":[
        {
            "category":"Community Center",
            "subcategory":"Youth",
            "type":"Public Place"
        }
    ],
    "sg:phone":"+1 512 278 9109",
    "sg:postcode":"78653",
    "sg:province":"TX",
    "wof:name":"Youth",
    "wof:placetype":"venue"
},
  "geometry": {"coordinates":[-97.613258,30.365764],"type":"Point"}
}