{
  "type": "Feature",
  "properties": {
    "iso:country":"US",
    "sg:address":"3832 Aspenwood Dr",
    "sg:city":"Bedford",
    "sg:classifiers":[
        {
            "category":"Personal",
            "type":"Services"
        }
    ],
    "sg:phone":"+1 817 571 4515",
    "sg:postcode":"76021",
    "sg:province":"TX",
    "wof:name":"Wraptique",
    "wof:placetype":"venue"
},
  "geometry": {"coordinates":[-97.108335,32.846564],"type":"Point"}
}