{
  "type": "Feature",
  "properties": {
    "iso:country":"US",
    "sg:address":"20140 Willow Glade Cir",
    "sg:city":"Pilot Point",
    "sg:classifiers":[
        {
            "category":"Communications",
            "type":"Services"
        }
    ],
    "sg:phone":"+1 940 686 5607",
    "sg:postcode":"76258",
    "sg:province":"TX",
    "sg:tags":[
        "communication"
    ],
    "wof:name":"Nortel Networks Inc",
    "wof:placetype":"venue"
},
  "geometry": {"coordinates":[-96.928342,33.41052],"type":"Point"}
}