{
  "type": "Feature",
  "properties": {
    "iso:country":"US",
    "sg:address":"414 E Hillmont Rd",
    "sg:city":"Odessa",
    "sg:classifiers":[
        {
            "category":"Airport",
            "type":"Transportation"
        }
    ],
    "sg:phone":"+1 432 368 0347",
    "sg:postcode":"79765",
    "sg:province":"TX",
    "sg:tags":[
        "aircraft",
        "maintenance"
    ],
    "wof:name":"Plane Action",
    "wof:placetype":"venue"
},
  "geometry": {"coordinates":[-102.391132,31.931334],"type":"Point"}
}