{
  "type": "Feature",
  "properties": {
    "iso:country":"US",
    "sg:address":"12957 Socorro Rd",
    "sg:city":"San Elizario",
    "sg:classifiers":[
        {
            "category":"Food & Beverages",
            "subcategory":"Liquor & Beverages",
            "type":"Retail Goods"
        }
    ],
    "sg:phone":"+1 915 851 5277",
    "sg:postcode":"79849",
    "sg:province":"TX",
    "sg:tags":[
        "beer",
        "ale"
    ],
    "wof:name":"Pete Wagons",
    "wof:placetype":"venue"
},
  "geometry": {"coordinates":[-106.26799200000001,31.580239],"type":"Point"}
}