{
  "type": "Feature",
  "properties": {
    "iso:country":"US",
    "sg:address":"824 Kentucky Ave",
    "sg:city":"San Antonio",
    "sg:classifiers":[
        {
            "category":"Social Services",
            "type":"Services"
        }
    ],
    "sg:phone":"+1 210 734 4893",
    "sg:postcode":"78201",
    "sg:province":"TX",
    "wof:name":"Little Flower Parrish",
    "wof:placetype":"venue"
},
  "geometry": {"coordinates":[-98.524333,29.446158],"type":"Point"}
}