{
  "type": "Feature",
  "properties": {
    "iso:country":"US",
    "sg:address":"12722 State Hwy 3",
    "sg:city":"Webster",
    "sg:classifiers":[
        {
            "category":"Wholesale",
            "subcategory":"Construction Materials",
            "type":"Manufacturing & Wholesale Goods"
        },
        {
            "category":"Shopping",
            "subcategory":"Hobbies, Toys, & Games",
            "type":"Retail Goods"
        }
    ],
    "sg:phone":"+1 281 280 0175",
    "sg:postcode":"77598",
    "sg:province":"TX",
    "sg:tags":[
        "product",
        "ceramic",
        "mfg"
    ],
    "wof:name":"M & T Ceramics",
    "wof:placetype":"venue"
},
  "geometry": {"coordinates":[-95.167267,29.590873],"type":"Point"}
}