{
  "type": "Feature",
  "properties": {
    "iso:country":"US",
    "sg:address":"13621 Ann Louise Rd",
    "sg:city":"Houston",
    "sg:classifiers":[
        {
            "category":"Travel",
            "subcategory":"Hotels & Motels",
            "type":"Entertainment"
        }
    ],
    "sg:phone":"+1 713 503 4394",
    "sg:postcode":"77086",
    "sg:province":"TX",
    "wof:name":"The King Room Addition",
    "wof:placetype":"venue"
},
  "geometry": {"coordinates":[-95.47054300000001,29.932241],"type":"Point"}
}