{
  "type": "Feature",
  "properties": {
    "iso:country":"US",
    "sg:address":"3016 Kimbo Rd",
    "sg:city":"Fort Worth",
    "sg:classifiers":[
        {
            "category":"Wholesale",
            "subcategory":"Construction Materials",
            "type":"Manufacturing & Wholesale Goods"
        }
    ],
    "sg:phone":"+1 817 838 2953",
    "sg:postcode":"76111",
    "sg:province":"TX",
    "wof:name":"Cowtown Septics",
    "wof:placetype":"venue"
},
  "geometry": {"coordinates":[-97.30645,32.796201],"type":"Point"}
}