{
  "type": "Feature",
  "properties": {
    "iso:country":"US",
    "sg:address":"8901 Market Street Rd",
    "sg:city":"Houston",
    "sg:classifiers":[
        {
            "category":"Autos & Motor Vehicles",
            "subcategory":"Auto Supplies",
            "type":"Retail Goods"
        }
    ],
    "sg:phone":"+1 832 200 1340",
    "sg:postcode":"77029",
    "sg:province":"TX",
    "sg:tags":[
        "tire"
    ],
    "wof:name":"Snider Tires",
    "wof:placetype":"venue"
},
  "geometry": {"coordinates":[-95.26478,29.769724],"type":"Point"}
}