{
  "type": "Feature",
  "properties": {
    "iso:country":"US",
    "sg:address":"4662 Lakeway Dr",
    "sg:city":"Brownsville",
    "sg:classifiers":[
        {
            "category":"Coffee & Tea",
            "type":"Food & Drink"
        },
        {
            "category":"Restaurant",
            "type":"Food & Drink"
        }
    ],
    "sg:phone":"+1 956 350 9121",
    "sg:postcode":"78520",
    "sg:province":"TX",
    "sg:tags":[
        "espresso"
    ],
    "wof:name":"Lotus Cafe At Boca Chica",
    "wof:placetype":"venue"
},
  "geometry": {"coordinates":[-97.535811,25.976713],"type":"Point"}
}