{
  "type": "Feature",
  "properties": {
    "iso:country":"US",
    "sg:address":"8863 Anderson Mill Rd",
    "sg:city":"Austin",
    "sg:classifiers":[
        {
            "category":"Shopping",
            "subcategory":"Computers & Home Electronics",
            "type":"Retail Goods"
        }
    ],
    "sg:phone":"+1 512 918 0100",
    "sg:postcode":"78729",
    "sg:province":"TX",
    "wof:name":"Discount Market",
    "wof:placetype":"venue"
},
  "geometry": {"coordinates":[-97.775982,30.4533],"type":"Point"}
}