{
  "type": "Feature",
  "properties": {
    "iso:country":"US",
    "sg:address":"1132 W Rusk St",
    "sg:city":"Jacksonville",
    "sg:classifiers":[
        {
            "category":"Building & Trades",
            "subcategory":"Pest Control",
            "type":"Services"
        }
    ],
    "sg:phone":"+1 903 586 5981",
    "sg:postcode":"75766",
    "sg:province":"TX",
    "wof:name":"Ant & Roach Specialists",
    "wof:placetype":"venue"
},
  "geometry": {"coordinates":[-95.28549099999999,31.959144],"type":"Point"}
}