{
  "type": "Feature",
  "properties": {
    "iso:country":"US",
    "sg:address":"7825 McCallum Blvd",
    "sg:city":"Dallas",
    "sg:classifiers":[
        {
            "category":"Utilities",
            "subcategory":"Telephone",
            "type":"Services"
        }
    ],
    "sg:phone":"+1 972 480 5876",
    "sg:postcode":"75252",
    "sg:province":"TX",
    "sg:tags":[
        "marketing",
        "internet"
    ],
    "wof:name":"E & J Enterprises",
    "wof:placetype":"venue"
},
  "geometry": {"coordinates":[-96.769621,32.988029],"type":"Point"}
}