{
  "type": "Feature",
  "properties": {
    "iso:country":"US",
    "sg:address":"402 Tarrow St",
    "sg:city":"College Station",
    "sg:classifiers":[
        {
            "category":"Health Services",
            "subcategory":"Doctor",
            "type":"Services"
        }
    ],
    "sg:phone":"+1 979 846 0082",
    "sg:postcode":"77840",
    "sg:province":"TX",
    "sg:tags":[
        "dentist"
    ],
    "wof:name":"Thomas H Davis DDS Inc",
    "wof:placetype":"venue"
},
  "geometry": {"coordinates":[-96.32883200000001,30.63586],"type":"Point"}
}