{
  "type": "Feature",
  "properties": {
    "iso:country":"US",
    "sg:address":"5416 S Hulen St",
    "sg:city":"Fort Worth",
    "sg:classifiers":[
        {
            "category":"Restaurant",
            "type":"Food & Drink"
        }
    ],
    "sg:phone":"+1 817 263 9597",
    "sg:postcode":"76132",
    "sg:province":"TX",
    "wof:name":"Papa John's Pizza",
    "wof:placetype":"venue"
},
  "geometry": {"coordinates":[-97.40010700000001,32.669845],"type":"Point"}
}