{
  "type": "Feature",
  "properties": {
    "iso:country":"US",
    "sg:address":"4511 Windy Gorge Dr",
    "sg:city":"Humble",
    "sg:classifiers":[
        {
            "category":"Utilities",
            "subcategory":"Telephone",
            "type":"Services"
        }
    ],
    "sg:phone":"+1 281 360 6661",
    "sg:postcode":"77345",
    "sg:province":"TX",
    "sg:tags":[
        "communications"
    ],
    "wof:name":"Aadast Co",
    "wof:placetype":"venue"
},
  "geometry": {"coordinates":[-95.17543999999999,30.078154],"type":"Point"}
}