{
  "type": "Feature",
  "properties": {
    "iso:country":"US",
    "sg:address":"8125 Rainbow Dr",
    "sg:city":"Rowlett",
    "sg:classifiers":[
        {
            "category":"Manufacturing",
            "subcategory":"Apparel",
            "type":"Manufacturing & Wholesale Goods"
        }
    ],
    "sg:phone":"+1 972 226 0468",
    "sg:postcode":"75089",
    "sg:province":"TX",
    "wof:name":"Sunny S Quilting",
    "wof:placetype":"venue"
},
  "geometry": {"coordinates":[-96.51712999999999,32.931753],"type":"Point"}
}