{
  "type": "Feature",
  "properties": {
    "iso:country":"US",
    "sg:address":"1323 Castle Hill Trl",
    "sg:city":"Humble",
    "sg:classifiers":[
        {
            "category":"Professional",
            "type":"Services"
        }
    ],
    "sg:phone":"+1 281 359 2229",
    "sg:postcode":"77339",
    "sg:province":"TX",
    "wof:name":"Ramblings",
    "wof:placetype":"venue"
},
  "geometry": {"coordinates":[-95.239195,30.046427],"type":"Point"}
}