{
  "type": "Feature",
  "properties": {
    "iso:country":"US",
    "sg:address":"1601 E Marshall Ave",
    "sg:city":"Longview",
    "sg:classifiers":[
        {
            "category":"Restaurant",
            "type":"Food & Drink"
        }
    ],
    "sg:phone":"+1 903 757 9466",
    "sg:postcode":"75601",
    "sg:province":"TX",
    "wof:name":"Dudley's Cajun Cafe",
    "wof:placetype":"venue"
},
  "geometry": {"coordinates":[-94.714356,32.504349],"type":"Point"}
}