{
  "type": "Feature",
  "properties": {
    "iso:country":"US",
    "sg:address":"502 Broadnax St",
    "sg:city":"Daingerfield",
    "sg:classifiers":[
        {
            "category":"Restaurant",
            "type":"Food & Drink"
        }
    ],
    "sg:phone":"+1 903 645 7986",
    "sg:postcode":"75638",
    "sg:province":"TX",
    "sg:tags":[
        "eating"
    ],
    "wof:name":"Kissin Ksins Kntry Knfctionary",
    "wof:placetype":"venue"
},
  "geometry": {"coordinates":[-94.725763,33.035967],"type":"Point"}
}