{
  "type": "Feature",
  "properties": {
    "iso:country":"US",
    "sg:address":"1516 E Expressway 83",
    "sg:city":"Mission",
    "sg:classifiers":[
        {
            "category":"Professional",
            "subcategory":"Lawyer & Legal Services",
            "type":"Services"
        }
    ],
    "sg:phone":"+1 956 585 9170",
    "sg:postcode":"78572",
    "sg:province":"TX",
    "sg:tags":[
        "attorney",
        "practice",
        "plan"
    ],
    "wof:name":"Law Office Of Daniel J Garcia",
    "wof:placetype":"venue"
},
  "geometry": {"coordinates":[-98.30979499999999,26.198407],"type":"Point"}
}