{
  "type": "Feature",
  "properties": {
    "iso:country":"US",
    "sg:address":"6322 Lakewood Pk",
    "sg:city":"San Antonio",
    "sg:classifiers":[
        {
            "category":"Health Services",
            "subcategory":"Health Practitioner",
            "type":"Services"
        }
    ],
    "sg:phone":"+1 210 657 3119",
    "sg:postcode":"78239",
    "sg:province":"TX",
    "sg:tags":[
        "psychologist"
    ],
    "wof:name":"Maiers Alan J Psyd",
    "wof:placetype":"venue"
},
  "geometry": {"coordinates":[-98.36605,29.51423],"type":"Point"}
}