{
  "type": "Feature",
  "properties": {
    "iso:country":"US",
    "sg:address":"2414 Whispering Cove Cir",
    "sg:city":"Garland",
    "sg:classifiers":[
        {
            "category":"Professional",
            "subcategory":"Business Services",
            "type":"Services"
        }
    ],
    "sg:phone":"+1 972 414 2866",
    "sg:postcode":"75044",
    "sg:province":"TX",
    "wof:name":"Ocean Fish Enterprise",
    "wof:placetype":"venue"
},
  "geometry": {"coordinates":[-96.664492,32.964737],"type":"Point"}
}