{
  "type": "Feature",
  "properties": {
    "iso:country":"US",
    "sg:address":"2115 Fulton St",
    "sg:city":"Houston",
    "sg:classifiers":[
        {
            "category":"Restaurant",
            "type":"Food & Drink"
        }
    ],
    "sg:phone":"+1 713 223 0519",
    "sg:postcode":"77009",
    "sg:province":"TX",
    "sg:tags":[
        "parlor",
        "ice",
        "cream"
    ],
    "wof:name":"Tropical Ice Cream",
    "wof:placetype":"venue"
},
  "geometry": {"coordinates":[-95.359432,29.780822],"type":"Point"}
}