{
  "type": "Feature",
  "properties": {
    "iso:country":"US",
    "sg:address":"1690 19th St SW",
    "sg:city":"Paris",
    "sg:classifiers":[
        {
            "category":"Autos & Motor Vehicles",
            "subcategory":"Automobile Sales",
            "type":"Retail Goods"
        }
    ],
    "sg:phone":"+1 903 785 8863",
    "sg:postcode":"75460",
    "sg:province":"TX",
    "sg:tags":[
        "truck"
    ],
    "wof:name":"Smallwood Jeff Trucks & Eqpt",
    "wof:placetype":"venue"
},
  "geometry": {"coordinates":[-95.582708,33.643301],"type":"Point"}
}