{
  "type": "Feature",
  "properties": {
    "iso:country":"US",
    "sg:address":"7316 Louetta Rd",
    "sg:city":"Spring",
    "sg:classifiers":[
        {
            "category":"Ice Cream",
            "type":"Food & Drink"
        }
    ],
    "sg:menulink":"http://www.allmenus.com/tx/northwest-harris/184404-cold-stone-creamery/menu/",
    "sg:phone":"+1 281 257 8007",
    "sg:postcode":"77379",
    "sg:province":"TX",
    "sg:tags":[
        "smoothy",
        "juice",
        "american"
    ],
    "wof:name":"Cold Stone Creamery",
    "wof:placetype":"venue"
},
  "geometry": {"coordinates":[-95.524159,30.020833],"type":"Point"}
}