{
  "type": "Feature",
  "properties": {
    "iso:country":"US",
    "sg:address":"109 S Crowley Rd",
    "sg:city":"Crowley",
    "sg:classifiers":[
        {
            "category":"Restaurant",
            "type":"Food & Drink"
        }
    ],
    "sg:phone":"+1 817 297 3888",
    "sg:postcode":"76036",
    "sg:province":"TX",
    "wof:name":"Subway Sandwich Shop",
    "wof:placetype":"venue"
},
  "geometry": {"coordinates":[-97.353104,32.577599],"type":"Point"}
}