{
  "type": "Feature",
  "properties": {
    "iso:country":"US",
    "sg:address":"653 Pin Oak Rd",
    "sg:city":"Katy",
    "sg:classifiers":[
        {
            "category":"Restaurant",
            "type":"Food & Drink"
        }
    ],
    "sg:phone":"+1 281 391 0605",
    "sg:postcode":"77494",
    "sg:province":"TX",
    "sg:tags":[
        "eating"
    ],
    "wof:name":"Tacos Y Tortas",
    "wof:placetype":"venue"
},
  "geometry": {"coordinates":[-95.820594,29.78367],"type":"Point"}
}