{
  "type": "Feature",
  "properties": {
    "iso:country":"US",
    "sg:address":"2200 N Bryan Rd",
    "sg:city":"Mission",
    "sg:classifiers":[
        {
            "category":"Professional",
            "type":"Services"
        }
    ],
    "sg:phone":"+1 956 581 3419",
    "sg:postcode":"78572",
    "sg:province":"TX",
    "sg:tags":[
        "establishment"
    ],
    "wof:name":"IBD Group",
    "wof:placetype":"venue"
},
  "geometry": {"coordinates":[-98.307654,26.225972],"type":"Point"}
}