{
  "type": "Feature",
  "properties": {
    "iso:country":"US",
    "sg:address":"605 Apollo Ct",
    "sg:city":"Granbury",
    "sg:classifiers":[
        {
            "category":"Building & Trades",
            "subcategory":"Pest Control",
            "type":"Services"
        }
    ],
    "sg:phone":"+1 817 573 2156",
    "sg:postcode":"76049",
    "sg:province":"TX",
    "wof:name":"Brownings Pest Control",
    "wof:placetype":"venue"
},
  "geometry": {"coordinates":[-97.778113,32.491864],"type":"Point"}
}