{
  "type": "Feature",
  "properties": {
    "iso:country":"US",
    "sg:address":"1800 E State Highway 114 Ste 102",
    "sg:city":"Southlake",
    "sg:classifiers":[
        {
            "category":"Home & Garden",
            "subcategory":"Kitchen Supply",
            "type":"Retail Goods"
        }
    ],
    "sg:phone":"+1 817 552 5500",
    "sg:postcode":"76092",
    "sg:province":"TX",
    "sg:tags":[
        "food",
        "equipment",
        "processing",
        "restaurant"
    ],
    "wof:name":"Equipment Preference Inc",
    "wof:placetype":"venue"
},
  "geometry": {"coordinates":[-97.127469,32.947027],"type":"Point"}
}