{
  "type": "Feature",
  "properties": {
    "iso:country":"US",
    "sg:address":"1505 31st St",
    "sg:city":"Hondo",
    "sg:classifiers":[
        {
            "category":"Travel",
            "subcategory":"Campground",
            "type":"Entertainment"
        }
    ],
    "sg:phone":"+1 830 426 2830",
    "sg:postcode":"78861",
    "sg:province":"TX",
    "sg:tags":[
        "camp"
    ],
    "wof:name":"Marc Zerr Ranch",
    "wof:placetype":"venue"
},
  "geometry": {"coordinates":[-99.146068,29.335865],"type":"Point"}
}