{
  "type": "Feature",
  "properties": {
    "iso:country":"US",
    "sg:address":"4832 Washington Blvd",
    "sg:city":"Beaumont",
    "sg:classifiers":[
        {
            "category":"Professional",
            "subcategory":"Testing Lab",
            "type":"Services"
        },
        {
            "category":"Professional",
            "subcategory":"Business Services",
            "type":"Services"
        }
    ],
    "sg:phone":"+1 409 840 9955",
    "sg:postcode":"77707",
    "sg:province":"TX",
    "sg:tags":[
        "x"
    ],
    "wof:name":"X Ray Inspections Inc",
    "wof:placetype":"venue"
},
  "geometry": {"coordinates":[-94.147937,30.055595],"type":"Point"}
}