{
  "type": "Feature",
  "properties": {
    "iso:country":"US",
    "sg:address":"4156 Brentwood Cir",
    "sg:city":"Grapevine",
    "sg:classifiers":[
        {
            "category":"Professional",
            "subcategory":"Management & Consulting",
            "type":"Services"
        }
    ],
    "sg:phone":"+1 817 695 7883",
    "sg:postcode":"76051",
    "sg:province":"TX",
    "sg:tags":[
        "business"
    ],
    "wof:name":"Richoz Consulting",
    "wof:placetype":"venue"
},
  "geometry": {"coordinates":[-97.119078,32.890099],"type":"Point"}
}