{
  "type": "Feature",
  "properties": {
    "iso:country":"US",
    "sg:address":"2014 Hwy 190 W",
    "sg:city":"Livingston",
    "sg:classifiers":[
        {
            "category":"Food & Beverages",
            "subcategory":"Groceries & Convenience Stores",
            "type":"Retail Goods"
        }
    ],
    "sg:phone":"+1 936 327 2808",
    "sg:postcode":"77351",
    "sg:province":"TX",
    "wof:name":"Partner's Gas & Convenience",
    "wof:placetype":"venue"
},
  "geometry": {"coordinates":[-94.953209,30.711962],"type":"Point"}
}