{
  "type": "Feature",
  "properties": {
    "iso:country":"US",
    "sg:address":"3122 Sherwood Way",
    "sg:city":"San Angelo",
    "sg:classifiers":[
        {
            "category":"Professional",
            "subcategory":"Business Services",
            "type":"Services"
        }
    ],
    "sg:phone":"+1 325 944 3400",
    "sg:postcode":"76901",
    "sg:province":"TX",
    "wof:name":"Airbrush Art By Rick",
    "wof:placetype":"venue"
},
  "geometry": {"coordinates":[-100.478683,31.44604],"type":"Point"}
}