{
  "type": "Feature",
  "properties": {
    "iso:country":"US",
    "sg:address":"5850 Gulf Fwy",
    "sg:city":"Houston",
    "sg:classifiers":[
        {
            "category":"Restaurant",
            "type":"Food & Drink"
        }
    ],
    "sg:phone":"+1 713 923 2188",
    "sg:postcode":"77023",
    "sg:province":"TX",
    "wof:name":"Jack In the Box Restaurants",
    "wof:placetype":"venue"
},
  "geometry": {"coordinates":[-95.316299,29.7152],"type":"Point"}
}