{
  "type": "Feature",
  "properties": {
    "iso:country":"US",
    "sg:address":"5080 Spectrum Dr Ste 105W",
    "sg:city":"Dallas",
    "sg:classifiers":[
        {
            "category":"Professional",
            "subcategory":"Accounting & Tax Preparation",
            "type":"Services"
        }
    ],
    "sg:phone":"+1 469 374 3150",
    "sg:postcode":"75001",
    "sg:province":"TX",
    "sg:tags":[
        "accountant"
    ],
    "sg:website":"www.gurianco.com",
    "wof:name":"Gurian PLLC CPA Firm",
    "wof:placetype":"venue"
},
  "geometry": {"coordinates":[-96.824505,32.956348],"type":"Point"}
}