{
  "type": "Feature",
  "properties": {
    "iso:country":"US",
    "sg:address":"1551 Lazy Spring Dr",
    "sg:city":"Missouri City",
    "sg:classifiers":[
        {
            "category":"Professional",
            "subcategory":"Computer Services",
            "type":"Services"
        }
    ],
    "sg:phone":"+1 281 633 2544",
    "sg:postcode":"77489",
    "sg:province":"TX",
    "sg:tags":[
        "consultant",
        "designer"
    ],
    "wof:name":"B B Consulting",
    "wof:placetype":"venue"
},
  "geometry": {"coordinates":[-95.525125,29.588755],"type":"Point"}
}