{
  "type": "Feature",
  "properties": {
    "iso:country":"US",
    "sg:address":"3090 Justin Rd",
    "sg:city":"Lewisville",
    "sg:classifiers":[
        {
            "category":"Personal",
            "subcategory":"Beauty Salon",
            "type":"Services"
        },
        {
            "category":"Personal",
            "subcategory":"Nail Salon",
            "type":"Services"
        }
    ],
    "sg:phone":"+1 972 317 8492",
    "sg:postcode":"75077",
    "sg:province":"TX",
    "wof:name":"Luxury Nail",
    "wof:placetype":"venue"
},
  "geometry": {"coordinates":[-97.075625,33.07381],"type":"Point"}
}