{
  "type": "Feature",
  "properties": {
    "iso:country":"US",
    "sg:address":"306 E Broad St",
    "sg:city":"Forney",
    "sg:classifiers":[
        {
            "category":"Retail",
            "subcategory":"Auto Repair",
            "type":"Services"
        }
    ],
    "sg:phone":"+1 972 564 5444",
    "sg:postcode":"75126",
    "sg:province":"TX",
    "sg:tags":[
        "wrecker"
    ],
    "wof:name":"Eastlake Towing Inc",
    "wof:placetype":"venue"
},
  "geometry": {"coordinates":[-96.468855,32.747696],"type":"Point"}
}