{
  "type": "Feature",
  "properties": {
    "iso:country":"US",
    "sg:address":"7519 Brian Clarke St",
    "sg:city":"San Antonio",
    "sg:classifiers":[
        {
            "category":"Professional",
            "subcategory":"Business Services",
            "type":"Services"
        }
    ],
    "sg:phone":"+1 210 684 2552",
    "sg:postcode":"78240",
    "sg:province":"TX",
    "wof:name":"Interior Plant Creations",
    "wof:placetype":"venue"
},
  "geometry": {"coordinates":[-98.635155,29.531524],"type":"Point"}
}