{
  "type": "Feature",
  "properties": {
    "iso:country":"US",
    "sg:address":"601 E Main St",
    "sg:city":"Rio Grande City",
    "sg:classifiers":[
        {
            "category":"Travel",
            "subcategory":"Hotels & Motels",
            "type":"Entertainment"
        }
    ],
    "sg:phone":"+1 956 487 5101",
    "sg:postcode":"78582",
    "sg:province":"TX",
    "wof:name":"LA Borde House",
    "wof:placetype":"venue"
},
  "geometry": {"coordinates":[-98.81586,26.377587],"type":"Point"}
}