{
  "type": "Feature",
  "properties": {
    "iso:country":"US",
    "sg:address":"606 Coyote Trl",
    "sg:city":"Alice",
    "sg:classifiers":[
        {
            "category":"Health Services",
            "subcategory":"Nursing And Care Facility",
            "type":"Services"
        }
    ],
    "sg:phone":"+1 361 664 5479",
    "sg:postcode":"78332",
    "sg:province":"TX",
    "sg:tags":[
        "skilled"
    ],
    "wof:name":"Retama Manor",
    "wof:placetype":"venue"
},
  "geometry": {"coordinates":[-98.05154400000001,27.756849],"type":"Point"}
}