{
  "type": "Feature",
  "properties": {
    "iso:country":"US",
    "sg:address":"1320 Co Rd 1143",
    "sg:city":"Tyler",
    "sg:classifiers":[
        {
            "category":"Education",
            "subcategory":"Special Training",
            "type":"Public Place"
        }
    ],
    "sg:phone":"+1 903 592 1291",
    "sg:postcode":"75704",
    "sg:province":"TX",
    "sg:tags":[
        "aircraft",
        "school"
    ],
    "wof:name":"Tyler Aviation Training",
    "wof:placetype":"venue"
},
  "geometry": {"coordinates":[-95.39089300000001,32.358234],"type":"Point"}
}