{
  "type": "Feature",
  "properties": {
    "iso:country":"US",
    "sg:address":"2117 Roosevelt Dr",
    "sg:city":"Pantego",
    "sg:classifiers":[
        {
            "category":"Social Services",
            "type":"Services"
        }
    ],
    "sg:phone":"+1 817 795 8066",
    "sg:postcode":"76013",
    "sg:province":"TX",
    "sg:tags":[
        "care",
        "center",
        "day"
    ],
    "wof:name":"Arlington Adult Day Health",
    "wof:placetype":"venue"
},
  "geometry": {"coordinates":[-97.155737,32.707005],"type":"Point"}
}