{
  "type": "Feature",
  "properties": {
    "iso:country":"US",
    "sg:address":"216 Crosstimber Dr",
    "sg:city":"Hurst",
    "sg:classifiers":[
        {
            "category":"Professional",
            "type":"Services"
        }
    ],
    "sg:phone":"+1 817 282 2824",
    "sg:postcode":"76053",
    "sg:province":"TX",
    "wof:name":"Pennington Ribon Co",
    "wof:placetype":"venue"
},
  "geometry": {"coordinates":[-97.179349,32.812901],"type":"Point"}
}