{
  "type": "Feature",
  "properties": {
    "iso:country":"US",
    "sg:address":"5265 Hawk Eye Dr",
    "sg:city":"Bulverde",
    "sg:classifiers":[
        {
            "category":"Professional",
            "type":"Services"
        }
    ],
    "sg:phone":"+1 830 438 8047",
    "sg:postcode":"78163",
    "sg:province":"TX",
    "wof:name":"Thomas H Dunn",
    "wof:placetype":"venue"
},
  "geometry": {"coordinates":[-98.383639,29.755349],"type":"Point"}
}