{
  "type": "Feature",
  "properties": {
    "iso:country":"US",
    "sg:address":"5117 Lockwood Dr",
    "sg:city":"Houston",
    "sg:classifiers":[
        {
            "category":"Organizations",
            "subcategory":"Religious Organization",
            "type":"Services"
        }
    ],
    "sg:phone":"+1 713 673 2827",
    "sg:postcode":"77026",
    "sg:province":"TX",
    "sg:tags":[
        "church"
    ],
    "wof:name":"Canaan Baptist Church",
    "wof:placetype":"venue"
},
  "geometry": {"coordinates":[-95.317148,29.807819],"type":"Point"}
}