{
  "type": "Feature",
  "properties": {
    "iso:country":"US",
    "sg:address":"5323 N Central Expy",
    "sg:city":"Dallas",
    "sg:classifiers":[
        {
            "category":"Retail",
            "subcategory":"Veterinary Services",
            "type":"Services"
        }
    ],
    "sg:phone":"+1 214 528 3360",
    "sg:postcode":"75205",
    "sg:province":"TX",
    "sg:tags":[
        "veterinarian"
    ],
    "wof:name":"Highland Park Animal Clinic",
    "wof:placetype":"venue"
},
  "geometry": {"coordinates":[-96.781502,32.8312],"type":"Point"}
}