{
  "type": "Feature",
  "properties": {
    "iso:country":"US",
    "sg:address":"3300 S 14th St",
    "sg:city":"Abilene",
    "sg:classifiers":[
        {
            "category":"Social Services",
            "type":"Services"
        }
    ],
    "sg:phone":"+1 325 677 3557",
    "sg:postcode":"79605",
    "sg:province":"TX",
    "sg:tags":[
        "youth",
        "organization",
        "center"
    ],
    "wof:name":"Junior Achievement",
    "wof:placetype":"venue"
},
  "geometry": {"coordinates":[-99.76613999999999,32.432268],"type":"Point"}
}