{
  "type": "Feature",
  "properties": {
    "iso:country":"US",
    "sg:address":"4720 Spring Cypress Rd",
    "sg:city":"Spring",
    "sg:classifiers":[
        {
            "category":"Restaurant",
            "type":"Food & Drink"
        }
    ],
    "sg:menulink":"http://www.allmenus.com/tx/northwest-harris/177780-jack-in-the-box/menu/",
    "sg:phone":"+1 281 374 0361",
    "sg:postcode":"77379",
    "sg:province":"TX",
    "sg:tags":[
        "burger",
        "american"
    ],
    "wof:name":"Jack in the Box",
    "wof:placetype":"venue"
},
  "geometry": {"coordinates":[-95.49363700000001,30.050503],"type":"Point"}
}