{
  "type": "Feature",
  "properties": {
    "iso:country":"US",
    "sg:address":"6464 E Northwest Hwy",
    "sg:city":"Dallas",
    "sg:classifiers":[
        {
            "category":"Bakery",
            "type":"Food & Drink"
        }
    ],
    "sg:phone":"+1 214 361 1622",
    "sg:postcode":"75214",
    "sg:province":"TX",
    "wof:name":"Ingram's Donut & Bakery",
    "wof:placetype":"venue"
},
  "geometry": {"coordinates":[-96.749337,32.856666],"type":"Point"}
}