{
  "type": "Feature",
  "properties": {
    "iso:country":"US",
    "sg:address":"10107 Glencarrie Ln",
    "sg:city":"Austin",
    "sg:classifiers":[
        {
            "category":"Manufacturing",
            "subcategory":"Apparel",
            "type":"Manufacturing & Wholesale Goods"
        }
    ],
    "sg:phone":"+1 512 335 7801",
    "sg:postcode":"78750",
    "sg:province":"TX",
    "sg:tags":[
        "mfg"
    ],
    "wof:name":"Byron Baird Apparel",
    "wof:placetype":"venue"
},
  "geometry": {"coordinates":[-97.810956,30.430766],"type":"Point"}
}