{
  "type": "Feature",
  "properties": {
    "iso:country":"US",
    "sg:address":"1250 Marvin Hancock Dr",
    "sg:city":"Jasper",
    "sg:classifiers":[
        {
            "category":"Health Services",
            "subcategory":"Doctor",
            "type":"Services"
        }
    ],
    "sg:phone":"+1 409 384 8990",
    "sg:postcode":"75951",
    "sg:province":"TX",
    "sg:tags":[
        "clinic"
    ],
    "wof:name":"Newton Family Clinic At Jasper",
    "wof:placetype":"venue"
},
  "geometry": {"coordinates":[-94.008351,30.908107],"type":"Point"}
}