{
  "type": "Feature",
  "properties": {
    "iso:country":"US",
    "sg:address":"2831 Eldorado Pkwy",
    "sg:city":"Frisco",
    "sg:classifiers":[
        {
            "category":"Personal",
            "subcategory":"Beauty Salon",
            "type":"Services"
        },
        {
            "category":"Personal",
            "subcategory":"Barber",
            "type":"Services"
        }
    ],
    "sg:phone":"+1 806 346 0942",
    "sg:postcode":"75034",
    "sg:province":"TX",
    "wof:name":"MD Caperton Japanese Straightening",
    "wof:placetype":"venue"
},
  "geometry": {"coordinates":[-96.86834,33.178276],"type":"Point"}
}