{
  "type": "Feature",
  "properties": {
    "iso:country":"US",
    "sg:address":"8206 Briarwood Ln",
    "sg:city":"Austin",
    "sg:classifiers":[
        {
            "category":"Real Estate",
            "subcategory":"Real Estate Services",
            "type":"Services"
        },
        {
            "category":"Banks & Credit Unions",
            "subcategory":"Financial Services",
            "type":"Services"
        }
    ],
    "sg:phone":"+1 512 453 5329",
    "sg:postcode":"78757",
    "sg:province":"TX",
    "sg:tags":[
        "loan",
        "processing",
        "broker",
        "mortgage"
    ],
    "sg:website":"www.imortgagetx.com",
    "wof:name":"Independent Mortgage",
    "wof:placetype":"venue"
},
  "geometry": {"coordinates":[-97.734053,30.365034],"type":"Point"}
}