{
  "type": "Feature",
  "properties": {
    "iso:country":"US",
    "sg:address":"800 Rosinante Rd",
    "sg:city":"El Paso",
    "sg:classifiers":[
        {
            "category":"Professional",
            "subcategory":"Engineering",
            "type":"Services"
        }
    ],
    "sg:phone":"+1 915 584 2020",
    "sg:postcode":"79922",
    "sg:province":"TX",
    "sg:tags":[
        "engineer"
    ],
    "wof:name":"Herrera Stafford & Assoc",
    "wof:placetype":"venue"
},
  "geometry": {"coordinates":[-106.597587,31.825127],"type":"Point"}
}