{
  "type": "Feature",
  "properties": {
    "iso:country":"US",
    "sg:address":"1689 Co Rd 2954",
    "sg:city":"Alba",
    "sg:classifiers":[
        {
            "category":"Retail",
            "subcategory":"Repair Shop",
            "type":"Services"
        }
    ],
    "sg:phone":"+1 903 765 2676",
    "sg:postcode":"75410",
    "sg:province":"TX",
    "wof:name":"Trussell Tractor Repair",
    "wof:placetype":"venue"
},
  "geometry": {"coordinates":[-95.615827,32.749623],"type":"Point"}
}