{
  "type": "Feature",
  "properties": {
    "iso:country":"US",
    "sg:address":"5811 Berkman Dr Ste 121",
    "sg:city":"Austin",
    "sg:classifiers":[
        {
            "category":"Shopping",
            "subcategory":"Optical Goods",
            "type":"Retail Goods"
        },
        {
            "category":"Shopping",
            "subcategory":"Optician",
            "type":"Retail Goods"
        },
        {
            "category":"Health Services",
            "subcategory":"Optometrist",
            "type":"Services"
        }
    ],
    "sg:phone":"+1 512 926 2400",
    "sg:postcode":"78723",
    "sg:province":"TX",
    "sg:tags":[
        "goods-wholesale",
        "eyewear",
        "manufacturer"
    ],
    "wof:name":"Ideal Optical",
    "wof:placetype":"venue"
},
  "geometry": {"coordinates":[-97.69361499999999,30.311953],"type":"Point"}
}