{
  "type": "Feature",
  "properties": {
    "iso:country":"US",
    "sg:address":"11418 Dennis Rd",
    "sg:city":"Dallas",
    "sg:classifiers":[
        {
            "category":"Travel",
            "subcategory":"Hotels & Motels",
            "type":"Entertainment"
        }
    ],
    "sg:phone":"+1 972 247 1358",
    "sg:postcode":"75229",
    "sg:province":"TX",
    "wof:name":"Villa Inn East Motel",
    "wof:placetype":"venue"
},
  "geometry": {"coordinates":[-96.88067100000001,32.90635],"type":"Point"}
}