{
  "type": "Feature",
  "properties": {
    "iso:country":"US",
    "sg:address":"308 Dugat Rd",
    "sg:city":"Dayton",
    "sg:classifiers":[
        {
            "category":"Home & Garden",
            "subcategory":"Building Materials",
            "type":"Retail Goods"
        }
    ],
    "sg:phone":"+1 936 258 5745",
    "sg:postcode":"77535",
    "sg:province":"TX",
    "sg:tags":[
        "glass",
        "window",
        "plate"
    ],
    "wof:name":"Windshield Doctor",
    "wof:placetype":"venue"
},
  "geometry": {"coordinates":[-94.85636700000001,29.99762],"type":"Point"}
}