{
  "type": "Feature",
  "properties": {
    "iso:country":"US",
    "sg:address":"215 Willard's Way",
    "sg:city":"Stafford",
    "sg:classifiers":[
        {
            "category":"Real Estate",
            "subcategory":"Real Estate Operator",
            "type":"Services"
        }
    ],
    "sg:phone":"+1 281 415 5573",
    "sg:postcode":"77477",
    "sg:province":"TX",
    "sg:tags":[
        "building",
        "nonresidential"
    ],
    "wof:name":"Dnp Investments LLC",
    "wof:placetype":"venue"
},
  "geometry": {"coordinates":[-95.568324,29.613172],"type":"Point"}
}