{
  "type": "Feature",
  "properties": {
    "iso:country":"US",
    "sg:address":"142 N Hwy 67",
    "sg:city":"Cedar Hill",
    "sg:classifiers":[
        {
            "category":"Autos & Motor Vehicles",
            "subcategory":"Auto Supplies",
            "type":"Retail Goods"
        }
    ],
    "sg:phone":"+1 972 291 3759",
    "sg:postcode":"75104",
    "sg:province":"TX",
    "sg:tags":[
        "tire"
    ],
    "wof:name":"Discount Tire Co Inc",
    "wof:placetype":"venue"
},
  "geometry": {"coordinates":[-96.944013,32.591077],"type":"Point"}
}