{
  "type": "Feature",
  "properties": {
    "iso:country":"US",
    "sg:address":"3411 Market Loop",
    "sg:city":"Temple",
    "sg:classifiers":[
        {
            "category":"Restaurant",
            "type":"Food & Drink"
        }
    ],
    "sg:menulink":"http://www.allmenus.com/tx/temple/139656-quiznos-sub/menu/",
    "sg:phone":"+1 254 773 7849",
    "sg:postcode":"76502",
    "sg:province":"TX",
    "sg:tags":[
        "wrap",
        "american",
        "sandwich"
    ],
    "wof:name":"Quiznos Sub",
    "wof:placetype":"venue"
},
  "geometry": {"coordinates":[-97.372766,31.071533],"type":"Point"}
}