{
  "type": "Feature",
  "properties": {
    "iso:country":"US",
    "sg:address":"5202 Tremper St",
    "sg:city":"Houston",
    "sg:classifiers":[
        {
            "category":"Building & Trades",
            "subcategory":"Construction",
            "type":"Services"
        }
    ],
    "sg:phone":"+1 713 675 2178",
    "sg:postcode":"77020",
    "sg:province":"TX",
    "sg:tags":[
        "residential",
        "commercial"
    ],
    "wof:name":"Rt Limited",
    "wof:placetype":"venue"
},
  "geometry": {"coordinates":[-95.318713,29.774676],"type":"Point"}
}