{
  "type": "Feature",
  "properties": {
    "iso:country":"US",
    "sg:address":"19103 Barry Ln",
    "sg:city":"Humble",
    "sg:classifiers":[
        {
            "category":"Building & Trades",
            "subcategory":"Construction",
            "type":"Services"
        }
    ],
    "sg:phone":"+1 281 451 5418",
    "sg:postcode":"77346",
    "sg:province":"TX",
    "sg:tags":[
        "roofing",
        "industrial",
        "contractors-commercial",
        "contractor"
    ],
    "wof:name":"Gulf Coast Restoration",
    "wof:placetype":"venue"
},
  "geometry": {"coordinates":[-95.182447,29.996677],"type":"Point"}
}