{
  "type": "Feature",
  "properties": {
    "iso:country":"US",
    "sg:address":"1520 Weiler Blvd",
    "sg:city":"Fort Worth",
    "sg:classifiers":[
        {
            "category":"Building & Trades",
            "subcategory":"Cleaning & Sanitation",
            "type":"Services"
        }
    ],
    "sg:phone":"+1 817 457 0576",
    "sg:postcode":"76112",
    "sg:province":"TX",
    "sg:tags":[
        "maintenance"
    ],
    "wof:name":"Windows By Russ",
    "wof:placetype":"venue"
},
  "geometry": {"coordinates":[-97.235437,32.756438],"type":"Point"}
}