{
  "type": "Feature",
  "properties": {
    "iso:country":"US",
    "sg:address":"445 Katie Ln",
    "sg:city":"Seguin",
    "sg:phone":"+1 830 372 2084",
    "sg:postcode":"78155",
    "sg:province":"TX",
    "sg:tags":[
        "farm",
        "field",
        "crop"
    ],
    "wof:name":"Lazy B Farms",
    "wof:placetype":"venue"
},
  "geometry": {"coordinates":[-98.046128,29.550701],"type":"Point"}
}