{
  "type": "Feature",
  "properties": {
    "iso:country":"US",
    "sg:address":"2531 Clara Ln",
    "sg:city":"San Antonio",
    "sg:classifiers":[
        {
            "category":"Real Estate",
            "subcategory":"Real Estate Operator",
            "type":"Services"
        }
    ],
    "sg:phone":"+1 210 340 0730",
    "sg:postcode":"78213",
    "sg:province":"TX",
    "sg:tags":[
        "apartment"
    ],
    "wof:name":"Vance Jackson Apartments",
    "wof:placetype":"venue"
},
  "geometry": {"coordinates":[-98.534485,29.494014],"type":"Point"}
}