{
  "type": "Feature",
  "properties": {
    "iso:country":"US",
    "sg:address":"105 US Hwy 90",
    "sg:city":"Marathon",
    "sg:classifiers":[
        {
            "category":"Shopping",
            "subcategory":"Books",
            "type":"Retail Goods"
        }
    ],
    "sg:phone":"+1 432 386 4249",
    "sg:postcode":"79843",
    "sg:province":"TX",
    "sg:tags":[
        "dealer"
    ],
    "wof:name":"Front Street Books",
    "wof:placetype":"venue"
},
  "geometry": {"coordinates":[-104.020628,30.309398],"type":"Point"}
}