{
  "type": "Feature",
  "properties": {
    "iso:country":"US",
    "sg:address":"201 N Main St",
    "sg:city":"Lockhart",
    "sg:classifiers":[
        {
            "category":"Government",
            "subcategory":"Office",
            "type":"Public Place"
        }
    ],
    "sg:phone":"+1 512 255 1720",
    "sg:postcode":"78644",
    "sg:province":"TX",
    "sg:tags":[
        "administrative",
        "program",
        "health"
    ],
    "wof:name":"Bluebnnet Trils Cmnty Mhmr Ctr",
    "wof:placetype":"venue"
},
  "geometry": {"coordinates":[-97.67276699999999,29.886467],"type":"Point"}
}