{
  "type": "Feature",
  "properties": {
    "iso:country":"US",
    "sg:address":"5114 Balcones Woods Drive",
    "sg:city":"Austin",
    "sg:classifiers":[
        {
            "category":"Health Services",
            "subcategory":"Dentist",
            "type":"Services"
        }
    ],
    "sg:phone":"+1 512 346 1900",
    "sg:postcode":"78759",
    "sg:province":"TX",
    "wof:name":"Archie Imperial DDS PC",
    "wof:placetype":"venue"
},
  "geometry": {"coordinates":[-97.74629299999999,30.407914],"type":"Point"}
}