{
  "type": "Feature",
  "properties": {
    "iso:country":"US",
    "sg:address":"510 Betsy Ross Dr",
    "sg:city":"Arlington",
    "sg:classifiers":[
        {
            "category":"Organizations",
            "subcategory":"Membership Organization",
            "type":"Services"
        }
    ],
    "sg:phone":"+1 817 784 8788",
    "sg:postcode":"76002",
    "sg:province":"TX",
    "wof:name":"No Speed Limit",
    "wof:placetype":"venue"
},
  "geometry": {"coordinates":[-97.10895600000001,32.641886],"type":"Point"}
}