{
  "type": "Feature",
  "properties": {
    "iso:country":"US",
    "sg:address":"761 Dairy Ashford St",
    "sg:city":"Houston",
    "sg:classifiers":[
        {
            "category":"Shopping",
            "subcategory":"Jewelry",
            "type":"Retail Goods"
        }
    ],
    "sg:phone":"+1 281 293 9021",
    "sg:postcode":"77079",
    "sg:province":"TX",
    "sg:tags":[
        "jeweler"
    ],
    "wof:name":"Arwa's Jewelry",
    "wof:placetype":"venue"
},
  "geometry": {"coordinates":[-95.606387,29.772247],"type":"Point"}
}