{
  "type": "Feature",
  "properties": {
    "iso:country":"US",
    "sg:address":"6501 Boulevard 26",
    "sg:city":"North Richland Hills",
    "sg:classifiers":[
        {
            "category":"Restaurant",
            "type":"Food & Drink"
        }
    ],
    "sg:menulink":"http://www.allmenus.com/tx/northeast-tarrant/177669-jack-in-the-box/menu/",
    "sg:phone":"+1 817 284 1301",
    "sg:postcode":"76180",
    "sg:province":"TX",
    "sg:tags":[
        "burger",
        "american"
    ],
    "wof:name":"Jack in the Box",
    "wof:placetype":"venue"
},
  "geometry": {"coordinates":[-97.24213,32.813067],"type":"Point"}
}