{
  "type": "Feature",
  "properties": {
    "iso:country":"US",
    "sg:address":"7503 Barberton Dr",
    "sg:city":"Houston",
    "sg:classifiers":[
        {
            "category":"Health Services",
            "subcategory":"Health Practitioner",
            "type":"Services"
        }
    ],
    "sg:phone":"+1 713 272 9266",
    "sg:postcode":"77036",
    "sg:province":"TX",
    "sg:tags":[
        "nurse"
    ],
    "wof:name":"Bellaire Lodge Personal Inc",
    "wof:placetype":"venue"
},
  "geometry": {"coordinates":[-95.522085,29.697546],"type":"Point"}
}