{
  "type": "Feature",
  "properties": {
    "iso:country":"US",
    "sg:address":"1808 Pace Bend Rd N",
    "sg:city":"Spicewood",
    "sg:classifiers":[
        {
            "category":"Shopping",
            "subcategory":"Bicycles & Sporting Goods",
            "type":"Retail Goods"
        }
    ],
    "sg:phone":"+1 512 264 2063",
    "sg:postcode":"78669",
    "sg:province":"TX",
    "wof:name":"Intelligent Golf Inc",
    "wof:placetype":"venue"
},
  "geometry": {"coordinates":[-98.047117,30.418961],"type":"Point"}
}