{
  "type": "Feature",
  "properties": {
    "iso:country":"US",
    "sg:address":"410 S Padre Island Dr",
    "sg:city":"Corpus Christi",
    "sg:classifiers":[
        {
            "category":"Professional",
            "subcategory":"Accounting & Tax Preparation",
            "type":"Services"
        }
    ],
    "sg:phone":"+1 361 289 5871",
    "sg:postcode":"78405",
    "sg:province":"TX",
    "sg:tags":[
        "accountant"
    ],
    "wof:name":"William H Cleavelin Jr CPA",
    "wof:placetype":"venue"
},
  "geometry": {"coordinates":[-97.462439,27.75823],"type":"Point"}
}