{
  "type": "Feature",
  "properties": {
    "iso:country":"US",
    "sg:address":"2709 S Padre Island Dr",
    "sg:city":"Corpus Christi",
    "sg:classifiers":[
        {
            "category":"Home & Garden",
            "subcategory":"Carpets & Floor Coverings",
            "type":"Retail Goods"
        }
    ],
    "sg:phone":"+1 361 853 1452",
    "sg:postcode":"78415",
    "sg:province":"TX",
    "sg:tags":[
        "dealer",
        "rug"
    ],
    "wof:name":"A Carpet World",
    "wof:placetype":"venue"
},
  "geometry": {"coordinates":[-97.42200099999999,27.732545],"type":"Point"}
}