{
  "type": "Feature",
  "properties": {
    "iso:country":"US",
    "sg:address":"123 SE Gardens Blvd",
    "sg:city":"Burleson",
    "sg:classifiers":[
        {
            "category":"Shopping",
            "subcategory":"Hobbies, Toys, & Games",
            "type":"Retail Goods"
        }
    ],
    "sg:phone":"+1 817 295 5945",
    "sg:postcode":"76028",
    "sg:province":"TX",
    "wof:name":"Lindas Country Crafts",
    "wof:placetype":"venue"
},
  "geometry": {"coordinates":[-97.334523,32.533268],"type":"Point"}
}