{
  "type": "Feature",
  "properties": {
    "iso:country":"US",
    "sg:address":"15401 Vantage Pkwy W",
    "sg:city":"Houston",
    "sg:classifiers":[
        {
            "category":"Building & Trades",
            "subcategory":"Equipment Rental",
            "type":"Services"
        }
    ],
    "sg:phone":"+1 281 590 3321",
    "sg:postcode":"77032",
    "sg:province":"TX",
    "sg:tags":[
        "home",
        "medical",
        "lease"
    ],
    "wof:name":"Aerocare Home Medical Inc",
    "wof:placetype":"venue"
},
  "geometry": {"coordinates":[-95.366294,29.941274],"type":"Point"}
}