{
  "type": "Feature",
  "properties": {
    "iso:country":"US",
    "sg:address":"185 Augusta Dr",
    "sg:city":"Wimberley",
    "sg:classifiers":[
        {
            "category":"Professional",
            "subcategory":"Management & Consulting",
            "type":"Services"
        }
    ],
    "sg:phone":"+1 512 847 0690",
    "sg:postcode":"78676",
    "sg:province":"TX",
    "sg:tags":[
        "consultant",
        "business"
    ],
    "wof:name":"Brendler Associates Inc",
    "wof:placetype":"venue"
},
  "geometry": {"coordinates":[-98.117937,30.034086],"type":"Point"}
}