{
  "type": "Feature",
  "properties": {
    "iso:country":"US",
    "sg:address":"2611 Worthington St",
    "sg:city":"Dallas",
    "sg:classifiers":[
        {
            "category":"Shopping",
            "type":"Retail Goods"
        }
    ],
    "sg:phone":"+1 972 218 5847",
    "sg:postcode":"75204",
    "sg:province":"TX",
    "sg:tags":[
        "hearing",
        "equipment",
        "supply",
        "impaired"
    ],
    "wof:name":"Texas Discount Hearing Aid",
    "wof:placetype":"venue"
},
  "geometry": {"coordinates":[-96.80179,32.798807],"type":"Point"}
}