{
  "type": "Feature",
  "properties": {
    "iso:country":"US",
    "sg:address":"4122 Jetty Terrace Cir",
    "sg:city":"Missouri City",
    "sg:classifiers":[
        {
            "category":"Professional",
            "subcategory":"Management & Consulting",
            "type":"Services"
        }
    ],
    "sg:phone":"+1 281 261 5913",
    "sg:postcode":"77459",
    "sg:province":"TX",
    "sg:tags":[
        "business"
    ],
    "wof:name":"Allen Grant Consulting",
    "wof:placetype":"venue"
},
  "geometry": {"coordinates":[-95.568562,29.593686],"type":"Point"}
}