{
  "type": "Feature",
  "properties": {
    "iso:country":"US",
    "sg:address":"1201 E Moore Rd",
    "sg:city":"Pharr",
    "sg:classifiers":[
        {
            "category":"Real Estate",
            "subcategory":"Real Estate Operator",
            "type":"Services"
        }
    ],
    "sg:phone":"+1 956 702 1291",
    "sg:postcode":"78577",
    "sg:province":"TX",
    "sg:tags":[
        "mobile",
        "home",
        "site",
        "community"
    ],
    "wof:name":"Buena Vista Estates",
    "wof:placetype":"venue"
},
  "geometry": {"coordinates":[-98.173593,26.171679],"type":"Point"}
}