{
  "type": "Feature",
  "properties": {
    "iso:country":"US",
    "sg:address":"1555 Merrimac Cir",
    "sg:city":"Fort Worth",
    "sg:classifiers":[
        {
            "category":"Health Services",
            "subcategory":"Clinic",
            "type":"Services"
        }
    ],
    "sg:phone":"+1 817 870 4949",
    "sg:postcode":"76107",
    "sg:province":"TX",
    "sg:tags":[
        "specialty",
        "outpatient"
    ],
    "wof:name":"Sports Thrapy Rhbilitaion Svcs",
    "wof:placetype":"venue"
},
  "geometry": {"coordinates":[-97.358767,32.729539],"type":"Point"}
}