{
  "type": "Feature",
  "properties": {
    "iso:country":"US",
    "sg:address":"2500 Highway 12",
    "sg:city":"Vidor",
    "sg:classifiers":[
        {
            "category":"Fast Food",
            "type":"Food & Drink"
        },
        {
            "category":"Restaurant",
            "type":"Food & Drink"
        }
    ],
    "sg:phone":"+1 409 769 1536",
    "sg:postcode":"77662",
    "sg:province":"TX",
    "wof:name":"Vidor Mdl Snack Bar",
    "wof:placetype":"venue"
},
  "geometry": {"coordinates":[-93.98429899999999,30.146258],"type":"Point"}
}