{
  "type": "Feature",
  "properties": {
    "iso:country":"US",
    "sg:address":"122 Gateway St",
    "sg:city":"Beaumont",
    "sg:classifiers":[
        {
            "category":"Shopping",
            "subcategory":"Shoes",
            "type":"Retail Goods"
        }
    ],
    "sg:phone":"+1 409 833 0363",
    "sg:postcode":"77701",
    "sg:province":"TX",
    "wof:name":"Norman's Men's Fashions",
    "wof:placetype":"venue"
},
  "geometry": {"coordinates":[-94.133866,30.071097],"type":"Point"}
}