{
  "type": "Feature",
  "properties": {
    "iso:country":"US",
    "sg:address":"504 Kemp Blvd",
    "sg:city":"Wichita Falls",
    "sg:classifiers":[
        {
            "category":"Health Services",
            "subcategory":"Hospital",
            "type":"Services"
        }
    ],
    "sg:phone":"+1 940 764 3290",
    "sg:postcode":"76301",
    "sg:province":"TX",
    "sg:tags":[
        "general"
    ],
    "wof:name":"Becky Young",
    "wof:placetype":"venue"
},
  "geometry": {"coordinates":[-98.51970799999999,33.905428],"type":"Point"}
}