{
  "type": "Feature",
  "properties": {
    "iso:country":"US",
    "sg:address":"241 W Live Oak St",
    "sg:city":"Jacksboro",
    "sg:classifiers":[
        {
            "category":"Organizations",
            "subcategory":"Religious Organization",
            "type":"Services"
        }
    ],
    "sg:phone":"+1 940 567 3735",
    "sg:postcode":"76458",
    "sg:province":"TX",
    "sg:tags":[
        "church"
    ],
    "sg:website":"www.jacksboroparish.org",
    "wof:name":"First Presbyterian Church",
    "wof:placetype":"venue"
},
  "geometry": {"coordinates":[-98.161767,33.222658],"type":"Point"}
}