{
  "type": "Feature",
  "properties": {
    "iso:country":"US",
    "sg:address":"3141 Skyway Cir S",
    "sg:city":"Irving",
    "sg:classifiers":[
        {
            "category":"Wholesale",
            "subcategory":"Durable Goods & Equipment",
            "type":"Manufacturing & Wholesale Goods"
        }
    ],
    "sg:phone":"+1 972 258 6953",
    "sg:postcode":"75038",
    "sg:province":"TX",
    "sg:tags":[
        "laboratory",
        "supply"
    ],
    "wof:name":"VWR Scientific Furniture",
    "wof:placetype":"venue"
},
  "geometry": {"coordinates":[-96.987898,32.869679],"type":"Point"}
}