{
  "type": "Feature",
  "properties": {
    "iso:country":"US",
    "sg:address":"1309 E Austin St",
    "sg:city":"Giddings",
    "sg:classifiers":[
        {
            "category":"Wholesale",
            "subcategory":"Machinery & Supplies",
            "type":"Manufacturing & Wholesale Goods"
        }
    ],
    "sg:phone":"+1 979 542 2259",
    "sg:postcode":"78942",
    "sg:province":"TX",
    "sg:tags":[
        "farm",
        "equipment"
    ],
    "wof:name":"Jaeger's Inc",
    "wof:placetype":"venue"
},
  "geometry": {"coordinates":[-96.92507000000001,30.180761],"type":"Point"}
}