{
  "type": "Feature",
  "properties": {
    "iso:country":"US",
    "sg:address":"2709 Lake Crest Dr",
    "sg:city":"Flower Mound",
    "sg:classifiers":[
        {
            "category":"Professional",
            "subcategory":"Business Services",
            "type":"Services"
        }
    ],
    "sg:phone":"+1 972 355 1883",
    "sg:postcode":"75022",
    "sg:province":"TX",
    "wof:name":"3dm Enterprises Inc",
    "wof:placetype":"venue"
},
  "geometry": {"coordinates":[-97.071918,33.005483],"type":"Point"}
}