{
  "type": "Feature",
  "properties": {
    "iso:country":"US",
    "sg:address":"690 Honeysuckle Ln",
    "sg:city":"Cedar Hill",
    "sg:classifiers":[
        {
            "category":"Recreation",
            "type":"Entertainment"
        }
    ],
    "sg:phone":"+1 469 556 6761",
    "sg:postcode":"75104",
    "sg:province":"TX",
    "wof:name":"Ricks Strike Zone",
    "wof:placetype":"venue"
},
  "geometry": {"coordinates":[-96.93195,32.608767],"type":"Point"}
}