{
  "type": "Feature",
  "properties": {
    "iso:country":"US",
    "sg:address":"6619 Chimney Rock Rd",
    "sg:city":"Houston",
    "sg:classifiers":[
        {
            "category":"Shopping",
            "subcategory":"Mobile Phones",
            "type":"Retail Goods"
        }
    ],
    "sg:phone":"+1 713 661 2226",
    "sg:postcode":"77081",
    "sg:province":"TX",
    "wof:name":"Mr Cellular N More 2",
    "wof:placetype":"venue"
},
  "geometry": {"coordinates":[-95.47608200000001,29.708383],"type":"Point"}
}