{
  "type": "Feature",
  "properties": {
    "iso:country":"US",
    "sg:address":"4438 Canyon Dr",
    "sg:city":"Amarillo",
    "sg:classifiers":[
        {
            "category":"Retail",
            "subcategory":"Auto Repair",
            "type":"Services"
        }
    ],
    "sg:phone":"+1 806 379 6941",
    "sg:postcode":"79109",
    "sg:province":"TX",
    "sg:tags":[
        "repairing",
        "automobile"
    ],
    "wof:name":"M F Automotive",
    "wof:placetype":"venue"
},
  "geometry": {"coordinates":[-101.870155,35.166655],"type":"Point"}
}