{
  "type": "Feature",
  "properties": {
    "iso:country":"US",
    "sg:address":"5906 Vandemere Dr",
    "sg:city":"Corpus Christi",
    "sg:classifiers":[
        {
            "category":"Shopping",
            "subcategory":"Beauty & Cosmetics",
            "type":"Retail Goods"
        }
    ],
    "sg:phone":"+1 361 992 7873",
    "sg:postcode":"78414",
    "sg:province":"TX",
    "sg:tags":[
        "merchandise"
    ],
    "wof:name":"Carol Martinez",
    "wof:placetype":"venue"
},
  "geometry": {"coordinates":[-97.373795,27.682183],"type":"Point"}
}