{
  "type": "Feature",
  "properties": {
    "iso:country":"US",
    "sg:address":"209 N Center St",
    "sg:city":"Grand Prairie",
    "sg:classifiers":[
        {
            "category":"Banks & Credit Unions",
            "subcategory":"Bank",
            "type":"Services"
        }
    ],
    "sg:phone":"+1 972 262 7935",
    "sg:postcode":"75050",
    "sg:province":"TX",
    "sg:tags":[
        "city",
        "government"
    ],
    "wof:name":"Grand Prairie Credit Union",
    "wof:placetype":"venue"
},
  "geometry": {"coordinates":[-97.003559,32.747602],"type":"Point"}
}