{
  "type": "Feature",
  "properties": {
    "iso:country":"US",
    "sg:address":"5827 Cliffbrier Dr",
    "sg:city":"San Antonio",
    "sg:classifiers":[
        {
            "category":"Building & Trades",
            "subcategory":"Construction",
            "type":"Services"
        }
    ],
    "sg:phone":"+1 210 520 5974",
    "sg:postcode":"78250",
    "sg:province":"TX",
    "sg:tags":[
        "home",
        "builder"
    ],
    "wof:name":"Kopplin Custom Homes Inc",
    "wof:placetype":"venue"
},
  "geometry": {"coordinates":[-98.68071999999999,29.494484],"type":"Point"}
}