{
  "type": "Feature",
  "properties": {
    "iso:country":"US",
    "sg:address":"705 E Arkansas Ave",
    "sg:city":"Sweetwater",
    "sg:classifiers":[
        {
            "category":"Personal",
            "subcategory":"Beauty Salon",
            "type":"Services"
        }
    ],
    "sg:phone":"+1 325 235 8005",
    "sg:postcode":"79556",
    "sg:province":"TX",
    "sg:tags":[
        "shop"
    ],
    "wof:name":"Elizabeths Beauty Salon",
    "wof:placetype":"venue"
},
  "geometry": {"coordinates":[-100.390635,32.46098],"type":"Point"}
}