{
  "type": "Feature",
  "properties": {
    "iso:country":"US",
    "sg:address":"9333 Research Boulevard",
    "sg:city":"Austin",
    "sg:classifiers":[
        {
            "category":"Health Services",
            "subcategory":"Optometrist",
            "type":"Services"
        },
        {
            "category":"Shopping",
            "subcategory":"Optician",
            "type":"Retail Goods"
        }
    ],
    "sg:phone":"+1 512 795 9399",
    "sg:postcode":"78759",
    "sg:province":"TX",
    "sg:tags":[
        "eyewear"
    ],
    "wof:name":"Pearle Vision",
    "wof:placetype":"venue"
},
  "geometry": {"coordinates":[-97.740663,30.382656],"type":"Point"}
}