{
  "type": "Feature",
  "properties": {
    "iso:country":"US",
    "sg:address":"1507 US Hwy 69",
    "sg:city":"Nederland",
    "sg:classifiers":[
        {
            "category":"Restaurant",
            "type":"Food & Drink"
        }
    ],
    "sg:phone":"+1 409 722 2323",
    "sg:postcode":"77627",
    "sg:province":"TX",
    "sg:tags":[
        "eating"
    ],
    "wof:name":"Schooner Restaurant Inc",
    "wof:placetype":"venue"
},
  "geometry": {"coordinates":[-94.01686599999999,29.963469],"type":"Point"}
}