{
  "type": "Feature",
  "properties": {
    "iso:country":"US",
    "sg:address":"520 W Broadway St",
    "sg:city":"Brownfield",
    "sg:classifiers":[
        {
            "category":"Food & Beverages",
            "subcategory":"Specialty",
            "type":"Retail Goods"
        }
    ],
    "sg:phone":"+1 806 637 2203",
    "sg:postcode":"79316",
    "sg:province":"TX",
    "sg:tags":[
        "water",
        "grocery",
        "company",
        "bulk",
        "dire",
        "merchandise"
    ],
    "wof:name":"Water Hole",
    "wof:placetype":"venue"
},
  "geometry": {"coordinates":[-102.28016700000001,33.177988],"type":"Point"}
}