{
  "type": "Feature",
  "properties": {
    "iso:country":"US",
    "sg:address":"1320 Airport Fwy",
    "sg:city":"Bedford",
    "sg:classifiers":[
        {
            "category":"Shopping",
            "subcategory":"Musical Instruments",
            "type":"Retail Goods"
        }
    ],
    "sg:phone":"+1 817 545 1103",
    "sg:postcode":"76022",
    "sg:province":"TX",
    "wof:name":"Mr E's Music Supercenters",
    "wof:placetype":"venue"
},
  "geometry": {"coordinates":[-97.145386,32.836715],"type":"Point"}
}