{
  "type": "Feature",
  "properties": {
    "iso:country":"US",
    "sg:address":"411 Lantana St",
    "sg:city":"Corpus Christi",
    "sg:classifiers":[
        {
            "category":"Utilities",
            "subcategory":"Telephone",
            "type":"Services"
        }
    ],
    "sg:phone":"+1 800 235 9800",
    "sg:postcode":"78408",
    "sg:province":"TX",
    "sg:tags":[
        "communication"
    ],
    "wof:name":"Southwestern Bell Telephone LP",
    "wof:placetype":"venue"
},
  "geometry": {"coordinates":[-97.47032900000001,27.794092],"type":"Point"}
}