{
  "type": "Feature",
  "properties": {
    "iso:country":"US",
    "sg:address":"9109 Dartbrook Dr",
    "sg:city":"San Antonio",
    "sg:classifiers":[
        {
            "category":"Real Estate",
            "subcategory":"Real Estate Operator",
            "type":"Services"
        }
    ],
    "sg:phone":"+1 210 696 0146",
    "sg:postcode":"78240",
    "sg:province":"TX",
    "sg:tags":[
        "apartment"
    ],
    "wof:name":"Cinnamon Creek Apartments",
    "wof:placetype":"venue"
},
  "geometry": {"coordinates":[-98.58007000000001,29.527199],"type":"Point"}
}