{
  "type": "Feature",
  "properties": {
    "iso:country":"US",
    "sg:address":"8143 Bruton Rd",
    "sg:city":"Dallas",
    "sg:classifiers":[
        {
            "category":"Food & Beverages",
            "subcategory":"Groceries & Convenience Stores",
            "type":"Retail Goods"
        }
    ],
    "sg:phone":"+1 214 275 6690",
    "sg:postcode":"75217",
    "sg:province":"TX",
    "wof:name":"E-Z Stop Food Store",
    "wof:placetype":"venue"
},
  "geometry": {"coordinates":[-96.68195900000001,32.74881],"type":"Point"}
}