{
  "type": "Feature",
  "properties": {
    "iso:country":"US",
    "sg:address":"149 Huntington Ct",
    "sg:city":"Rockwall",
    "sg:classifiers":[
        {
            "category":"Professional",
            "subcategory":"Business Services",
            "type":"Services"
        }
    ],
    "sg:phone":"+1 972 772 4191",
    "sg:postcode":"75032",
    "sg:province":"TX",
    "wof:name":"B Co Ventures Inc",
    "wof:placetype":"venue"
},
  "geometry": {"coordinates":[-96.472847,32.874919],"type":"Point"}
}