{
  "type": "Feature",
  "properties": {
    "iso:country":"US",
    "sg:address":"502 S Koenigheim St",
    "sg:city":"San Angelo",
    "sg:classifiers":[
        {
            "category":"Mining & Drilling",
            "type":"Manufacturing & Wholesale Goods"
        }
    ],
    "sg:phone":"+1 325 655 2166",
    "sg:postcode":"76903",
    "sg:province":"TX",
    "sg:tags":[
        "oil",
        "gas",
        "producer"
    ],
    "wof:name":"Parker & Parsley Petroleum",
    "wof:placetype":"venue"
},
  "geometry": {"coordinates":[-100.44045199999999,31.455321],"type":"Point"}
}