{
  "type": "Feature",
  "properties": {
    "iso:country":"US",
    "sg:address":"24419 Kuykendahl Rd",
    "sg:city":"Tomball",
    "sg:classifiers":[
        {
            "category":"Food & Beverages",
            "subcategory":"Groceries & Convenience Stores",
            "type":"Retail Goods"
        },
        {
            "category":"Autos & Motor Vehicles",
            "subcategory":"Fuel & Gas Station",
            "type":"Retail Goods"
        }
    ],
    "sg:phone":"+1 281 357 5956",
    "sg:postcode":"77375",
    "sg:province":"TX",
    "sg:tags":[
        "grocer",
        "station",
        "gasoline"
    ],
    "wof:name":"Chaudhry & Sons Inc",
    "wof:placetype":"venue"
},
  "geometry": {"coordinates":[-95.554517,30.117425],"type":"Point"}
}