{
  "type": "Feature",
  "properties": {
    "iso:country":"US",
    "sg:address":"8808 Huebner Rd",
    "sg:city":"San Antonio",
    "sg:classifiers":[
        {
            "category":"Insurance",
            "subcategory":"Insurance Agent",
            "type":"Services"
        }
    ],
    "sg:phone":"+1 210 691 0040",
    "sg:postcode":"78240",
    "sg:province":"TX",
    "wof:name":"Allstate Insurance",
    "wof:placetype":"venue"
},
  "geometry": {"coordinates":[-98.59890799999999,29.524576],"type":"Point"}
}