{
  "type": "Feature",
  "properties": {
    "iso:country":"US",
    "sg:address":"850 T C Jester Blvd",
    "sg:city":"Houston",
    "sg:classifiers":[
        {
            "category":"Retail",
            "subcategory":"Portrait Studio",
            "type":"Services"
        }
    ],
    "sg:phone":"+1 713 864 9481",
    "sg:postcode":"77008",
    "sg:province":"TX",
    "sg:tags":[
        "photographer",
        "photo"
    ],
    "wof:name":"Dick's Studio",
    "wof:placetype":"venue"
},
  "geometry": {"coordinates":[-95.416223,29.789664],"type":"Point"}
}