{
  "type": "Feature",
  "properties": {
    "iso:country":"US",
    "sg:address":"705 N Main St",
    "sg:city":"San Angelo",
    "sg:classifiers":[
        {
            "category":"Restaurant",
            "type":"Food & Drink"
        }
    ],
    "sg:phone":"+1 325 659 1286",
    "sg:postcode":"76903",
    "sg:province":"TX",
    "sg:tags":[
        "eating"
    ],
    "wof:name":"A&W Restaurant",
    "wof:placetype":"venue"
},
  "geometry": {"coordinates":[-100.432186,31.474913],"type":"Point"}
}