{
  "type": "Feature",
  "properties": {
    "iso:country":"US",
    "sg:address":"772 Lakewood Ct",
    "sg:city":"Lewisville",
    "sg:classifiers":[
        {
            "category":"Professional",
            "type":"Services"
        }
    ],
    "sg:phone":"+1 972 318 8987",
    "sg:postcode":"75077",
    "sg:province":"TX",
    "wof:name":"Aircraftsmen Inc",
    "wof:placetype":"venue"
},
  "geometry": {"coordinates":[-97.068698,33.090814],"type":"Point"}
}