{
  "type": "Feature",
  "properties": {
    "iso:country":"US",
    "sg:address":"803 Foxborough Ln",
    "sg:city":"Missouri City",
    "sg:classifiers":[
        {
            "category":"Professional",
            "subcategory":"Management & Consulting",
            "type":"Services"
        }
    ],
    "sg:phone":"+1 281 438 5156",
    "sg:postcode":"77489",
    "sg:province":"TX",
    "wof:name":"Construction Funds Management",
    "wof:placetype":"venue"
},
  "geometry": {"coordinates":[-95.51486,29.601607],"type":"Point"}
}