{
  "type": "Feature",
  "properties": {
    "iso:country":"US",
    "sg:address":"2555 Amherst St",
    "sg:city":"Houston",
    "sg:classifiers":[
        {
            "category":"Shopping",
            "subcategory":"Clothing, Apparel, & Fashions",
            "type":"Retail Goods"
        }
    ],
    "sg:phone":"+1 713 520 1184",
    "sg:postcode":"77005",
    "sg:province":"TX",
    "sg:tags":[
        "accessory",
        "clothing",
        "women's"
    ],
    "wof:name":"Hemline",
    "wof:placetype":"venue"
},
  "geometry": {"coordinates":[-95.417585,29.715722],"type":"Point"}
}