{
  "type": "Feature",
  "properties": {
    "iso:country":"US",
    "sg:address":"14002 Alderson St",
    "sg:city":"Houston",
    "sg:classifiers":[
        {
            "category":"Retail",
            "subcategory":"Auto Repair",
            "type":"Services"
        }
    ],
    "sg:phone":"+1 713 673 6303",
    "sg:postcode":"77015",
    "sg:province":"TX",
    "wof:name":"J & T Auto Service",
    "wof:placetype":"venue"
},
  "geometry": {"coordinates":[-95.175499,29.788],"type":"Point"}
}