{
  "type": "Feature",
  "properties": {
    "iso:country":"US",
    "sg:address":"3409 Viscount Dr",
    "sg:city":"Arlington",
    "sg:classifiers":[
        {
            "category":"Banks & Credit Unions",
            "subcategory":"Investment Brokerage",
            "type":"Services"
        }
    ],
    "sg:phone":"+1 817 429 6664",
    "sg:postcode":"76016",
    "sg:province":"TX",
    "sg:tags":[
        "advisory"
    ],
    "wof:name":"Hopper Investment Corp",
    "wof:placetype":"venue"
},
  "geometry": {"coordinates":[-97.17765799999999,32.692723],"type":"Point"}
}