{
  "type": "Feature",
  "properties": {
    "iso:country":"US",
    "sg:address":"201 S Cage Blvd",
    "sg:city":"Pharr",
    "sg:classifiers":[
        {
            "category":"Personal",
            "subcategory":"Beauty Salon",
            "type":"Services"
        }
    ],
    "sg:phone":"+1 956 783 0311",
    "sg:postcode":"78577",
    "sg:province":"TX",
    "wof:name":"Molly S Hair Care Salon",
    "wof:placetype":"venue"
},
  "geometry": {"coordinates":[-98.184242,26.19335],"type":"Point"}
}