{
  "type": "Feature",
  "properties": {
    "iso:country":"US",
    "sg:address":"501 S la Salle St",
    "sg:city":"Navasota",
    "sg:classifiers":[
        {
            "category":"Professional",
            "type":"Services"
        },
        {
            "category":"Restaurant",
            "type":"Food & Drink"
        },
        {
            "category":"Fast Food",
            "type":"Food & Drink"
        }
    ],
    "sg:phone":"+1 936 825 7273",
    "sg:postcode":"77868",
    "sg:province":"TX",
    "sg:tags":[
        "delivery",
        "take",
        "pizza"
    ],
    "sg:website":"http://www.pizzahut.com",
    "wof:name":"Pizza Hut",
    "wof:placetype":"venue"
},
  "geometry": {"coordinates":[-96.085616,30.384482],"type":"Point"}
}