{
  "type": "Feature",
  "properties": {
    "iso:country":"US",
    "sg:address":"10807 Ensbrook Dr",
    "sg:city":"Houston",
    "sg:classifiers":[
        {
            "category":"Building & Trades",
            "subcategory":"Construction",
            "type":"Services"
        }
    ],
    "sg:phone":"+1 281 879 0913",
    "sg:postcode":"77099",
    "sg:province":"TX",
    "sg:tags":[
        "handyman"
    ],
    "wof:name":"Dakota's Designs",
    "wof:placetype":"venue"
},
  "geometry": {"coordinates":[-95.572681,29.652714],"type":"Point"}
}