{
  "type": "Feature",
  "properties": {
    "iso:country":"US",
    "sg:address":"265 el Dorado Blvd",
    "sg:city":"Webster",
    "sg:classifiers":[
        {
            "category":"Real Estate",
            "subcategory":"Real Estate Operator",
            "type":"Services"
        }
    ],
    "sg:phone":"+1 281 480 3730",
    "sg:postcode":"77598",
    "sg:province":"TX",
    "sg:tags":[
        "building",
        "apartment"
    ],
    "wof:name":"Ranch El Dorado",
    "wof:placetype":"venue"
},
  "geometry": {"coordinates":[-95.148787,29.556707],"type":"Point"}
}