{
  "type": "Feature",
  "properties": {
    "iso:country":"US",
    "sg:address":"2019 W Northwest Hwy",
    "sg:city":"Dallas",
    "sg:classifiers":[
        {
            "category":"Restaurant",
            "type":"Food & Drink"
        }
    ],
    "sg:phone":"+1 972 869 3420",
    "sg:postcode":"75220",
    "sg:province":"TX",
    "sg:tags":[
        "eating"
    ],
    "wof:name":"I Love Egg Rolls",
    "wof:placetype":"venue"
},
  "geometry": {"coordinates":[-96.90685999999999,32.866809],"type":"Point"}
}