{
  "type": "Feature",
  "properties": {
    "iso:country":"US",
    "sg:address":"1109 Circle Ln",
    "sg:city":"Bedford",
    "sg:classifiers":[
        {
            "category":"Museum",
            "type":"Entertainment"
        }
    ],
    "sg:phone":"+1 817 581 1040",
    "sg:postcode":"76022",
    "sg:province":"TX",
    "sg:tags":[
        "organization",
        "arts",
        "information"
    ],
    "sg:website":"www.wpskimusic.com",
    "wof:name":"Winter Park Ski-Music Festival",
    "wof:placetype":"venue"
},
  "geometry": {"coordinates":[-97.150651,32.829352],"type":"Point"}
}