{
  "type": "Feature",
  "properties": {
    "iso:country":"US",
    "sg:address":"930 Marvin Hancock Dr",
    "sg:city":"Jasper",
    "sg:classifiers":[
        {
            "category":"Health Services",
            "subcategory":"Doctor",
            "type":"Services"
        }
    ],
    "sg:phone":"+1 409 384 4200",
    "sg:postcode":"75951",
    "sg:province":"TX",
    "sg:tags":[
        "medical"
    ],
    "wof:name":"Kidney Center Of Jasper",
    "wof:placetype":"venue"
},
  "geometry": {"coordinates":[-94.008015,30.911852],"type":"Point"}
}