{
  "type": "Feature",
  "properties": {
    "iso:country":"US",
    "sg:address":"7531 S Central Expy",
    "sg:city":"Dallas",
    "sg:classifiers":[
        {
            "category":"Autos & Motor Vehicles",
            "subcategory":"Auto Supplies",
            "type":"Retail Goods"
        }
    ],
    "sg:phone":"+1 214 374 3445",
    "sg:postcode":"75216",
    "sg:province":"TX",
    "wof:name":"Autowoox",
    "wof:placetype":"venue"
},
  "geometry": {"coordinates":[-96.756063,32.716373],"type":"Point"}
}