{
  "type": "Feature",
  "properties": {
    "iso:country":"US",
    "sg:address":"114 S Main St",
    "sg:city":"Perryton",
    "sg:classifiers":[
        {
            "category":"Shopping",
            "subcategory":"Clothing, Apparel, & Fashions",
            "type":"Retail Goods"
        }
    ],
    "sg:phone":"+1 806 435 4848",
    "sg:postcode":"79070",
    "sg:province":"TX",
    "wof:name":"Jackie's",
    "wof:placetype":"venue"
},
  "geometry": {"coordinates":[-100.80277700000001,36.399427],"type":"Point"}
}