{
  "type": "Feature",
  "properties": {
    "iso:country":"US",
    "sg:address":"7756 Northcross Dr",
    "sg:city":"Austin",
    "sg:classifiers":[
        {
            "category":"Professional",
            "subcategory":"Computer Services",
            "type":"Services"
        }
    ],
    "sg:phone":"+1 512 458 9923",
    "sg:postcode":"78757",
    "sg:province":"TX",
    "sg:tags":[
        "consultant",
        "designer",
        "datum",
        "system"
    ],
    "wof:name":"Sweetdate Concepts",
    "wof:placetype":"venue"
},
  "geometry": {"coordinates":[-97.73468699999999,30.352726],"type":"Point"}
}