{
  "type": "Feature",
  "properties": {
    "iso:country":"US",
    "sg:address":"6500 Co Rd 14",
    "sg:city":"Shamrock",
    "sg:classifiers":[
        {
            "category":"Manufacturing",
            "subcategory":"Tools & Machinery",
            "type":"Manufacturing & Wholesale Goods"
        }
    ],
    "sg:phone":"+1 806 256 2979",
    "sg:postcode":"79079",
    "sg:province":"TX",
    "sg:tags":[
        "farm",
        "mfg"
    ],
    "wof:name":"McMurtry Farm",
    "wof:placetype":"venue"
},
  "geometry": {"coordinates":[-100.289886,35.247783],"type":"Point"}
}