{
  "type": "Feature",
  "properties": {
    "iso:country":"US",
    "sg:address":"11565 State Hwy 6",
    "sg:city":"Sugar Land",
    "sg:classifiers":[
        {
            "category":"Autos & Motor Vehicles",
            "subcategory":"Fuel & Gas Station",
            "type":"Retail Goods"
        }
    ],
    "sg:phone":"+1 281 340 1515",
    "sg:postcode":"77478",
    "sg:province":"TX",
    "sg:tags":[
        "station",
        "gasoline",
        "oil"
    ],
    "wof:name":"Randall's Fuel Station",
    "wof:placetype":"venue"
},
  "geometry": {"coordinates":[-95.65130000000001,29.64731],"type":"Point"}
}