{
  "type": "Feature",
  "properties": {
    "iso:country":"US",
    "sg:address":"5710 4th St",
    "sg:city":"Lubbock",
    "sg:classifiers":[
        {
            "category":"Arts & Performance",
            "subcategory":"Theater",
            "type":"Entertainment"
        }
    ],
    "sg:phone":"+1 806 281 9322",
    "sg:postcode":"79416",
    "sg:province":"TX",
    "sg:tags":[
        "group"
    ],
    "wof:name":"Slim Opie Com",
    "wof:placetype":"venue"
},
  "geometry": {"coordinates":[-101.939322,33.592348],"type":"Point"}
}