{
  "type": "Feature",
  "properties": {
    "iso:country":"US",
    "sg:address":"4804 Holly St",
    "sg:city":"Bellaire",
    "sg:classifiers":[
        {
            "category":"Professional",
            "type":"Services"
        }
    ],
    "sg:phone":"+1 713 667 0108",
    "sg:postcode":"77401",
    "sg:province":"TX",
    "wof:name":"Ace Care",
    "wof:placetype":"venue"
},
  "geometry": {"coordinates":[-95.461392,29.693141],"type":"Point"}
}