{
  "type": "Feature",
  "properties": {
    "iso:country":"US",
    "sg:address":"2225 N Main St",
    "sg:city":"Vidor",
    "sg:classifiers":[
        {
            "category":"Personal",
            "subcategory":"Beauty Salon",
            "type":"Services"
        }
    ],
    "sg:phone":"+1 409 769 7576",
    "sg:postcode":"77662",
    "sg:province":"TX",
    "wof:name":"Sember's Salon",
    "wof:placetype":"venue"
},
  "geometry": {"coordinates":[-94.017117,30.158455],"type":"Point"}
}