{
  "type": "Feature",
  "properties": {
    "iso:country":"US",
    "sg:address":"3401 Custer Rd",
    "sg:city":"Plano",
    "sg:classifiers":[
        {
            "category":"Professional",
            "subcategory":"Computer Services",
            "type":"Services"
        }
    ],
    "sg:phone":"+1 972 985 7146",
    "sg:postcode":"75023",
    "sg:province":"TX",
    "sg:tags":[
        "consultant"
    ],
    "sg:website":"www.tcrnet.com",
    "wof:name":"Technical Consulting Resources",
    "wof:placetype":"venue"
},
  "geometry": {"coordinates":[-96.73347,33.043016],"type":"Point"}
}