{
  "type": "Feature",
  "properties": {
    "iso:country":"US",
    "sg:address":"11320 S Post Oak Rd Ste 212",
    "sg:city":"Houston",
    "sg:classifiers":[
        {
            "category":"Wholesale",
            "subcategory":"Home Furnishings",
            "type":"Manufacturing & Wholesale Goods"
        }
    ],
    "sg:phone":"+1 713 723 9719",
    "sg:postcode":"77035",
    "sg:province":"TX",
    "sg:tags":[
        "blind",
        "shade"
    ],
    "wof:name":"Houston Shutters",
    "wof:placetype":"venue"
},
  "geometry": {"coordinates":[-95.46399700000001,29.652399],"type":"Point"}
}