{
  "type": "Feature",
  "properties": {
    "iso:country":"US",
    "sg:address":"1907 Junction Hwy",
    "sg:city":"Kerrville",
    "sg:classifiers":[
        {
            "category":"Personal",
            "subcategory":"Beauty Salon",
            "type":"Services"
        }
    ],
    "sg:phone":"+1 830 895 2717",
    "sg:postcode":"78028",
    "sg:province":"TX",
    "sg:tags":[
        "shop",
        "manicuring"
    ],
    "wof:name":"Diane's Nails",
    "wof:placetype":"venue"
},
  "geometry": {"coordinates":[-99.191861,30.072436],"type":"Point"}
}