{
  "type": "Feature",
  "properties": {
    "iso:country":"US",
    "sg:address":"306 Co Rd 288",
    "sg:city":"Denton",
    "sg:classifiers":[
        {
            "category":"Government",
            "subcategory":"Office",
            "type":"Public Place"
        }
    ],
    "sg:phone":"+1 940 320 1813",
    "sg:postcode":"79536",
    "sg:province":"TX",
    "wof:name":"Denton County Planning",
    "wof:placetype":"venue"
},
  "geometry": {"coordinates":[-100.01083800000001,32.473475],"type":"Point"}
}