{
  "type": "Feature",
  "properties": {
    "iso:country":"US",
    "sg:address":"9859 S Kirkwood Rd",
    "sg:city":"Houston",
    "sg:classifiers":[
        {
            "category":"Health Services",
            "subcategory":"Clinic",
            "type":"Services"
        }
    ],
    "sg:phone":"+1 281 988 8897",
    "sg:postcode":"77099",
    "sg:province":"TX",
    "sg:tags":[
        "home"
    ],
    "wof:name":"Caring Proessional Hm Health",
    "wof:placetype":"venue"
},
  "geometry": {"coordinates":[-95.58798899999999,29.670908],"type":"Point"}
}