{
  "type": "Feature",
  "properties": {
    "iso:country":"US",
    "sg:address":"10003 Woodloch Forest Dr",
    "sg:city":"Spring",
    "sg:classifiers":[
        {
            "category":"Real Estate",
            "subcategory":"Real Estate Agent",
            "type":"Services"
        }
    ],
    "sg:phone":"+1 281 419 3095",
    "sg:postcode":"77380",
    "sg:province":"TX",
    "sg:tags":[
        "management"
    ],
    "wof:name":"Transwestern Commercial Svcs",
    "wof:placetype":"venue"
},
  "geometry": {"coordinates":[-95.455918,30.158545],"type":"Point"}
}