{
  "type": "Feature",
  "properties": {
    "iso:country":"US",
    "sg:address":"612 E Sandy Lake Rd",
    "sg:city":"Coppell",
    "sg:classifiers":[
        {
            "category":"Cinema",
            "subcategory":"Movie Rental",
            "type":"Entertainment"
        }
    ],
    "sg:phone":"+1 972 462 0250",
    "sg:postcode":"75019",
    "sg:province":"TX",
    "sg:tags":[
        "game",
        "video"
    ],
    "wof:name":"Family Video Store",
    "wof:placetype":"venue"
},
  "geometry": {"coordinates":[-96.97667800000001,32.969697],"type":"Point"}
}