{
  "type": "Feature",
  "properties": {
    "iso:country":"US",
    "sg:address":"10 Twin Lakes Ct",
    "sg:city":"Arlington",
    "sg:classifiers":[
        {
            "category":"Shopping",
            "subcategory":"Gifts & Souvenirs",
            "type":"Retail Goods"
        }
    ],
    "sg:phone":"+1 817 468 8575",
    "sg:postcode":"76016",
    "sg:province":"TX",
    "wof:name":"Chase Chicks",
    "wof:placetype":"venue"
},
  "geometry": {"coordinates":[-97.154372,32.684852],"type":"Point"}
}