{
  "type": "Feature",
  "properties": {
    "iso:country":"US",
    "sg:address":"8000 Rhoads Rd",
    "sg:city":"Aubrey",
    "sg:classifiers":[
        {
            "category":"Professional",
            "subcategory":"Computer Services",
            "type":"Services"
        }
    ],
    "sg:phone":"+1 940 365 3601",
    "sg:postcode":"76227",
    "sg:province":"TX",
    "sg:tags":[
        "related"
    ],
    "wof:name":"Team Technology Inc",
    "wof:placetype":"venue"
},
  "geometry": {"coordinates":[-97.03259,33.273108],"type":"Point"}
}