{
  "type": "Feature",
  "properties": {
    "iso:country":"US",
    "sg:address":"707 Cobblestone Ct",
    "sg:city":"Cedar Hill",
    "sg:classifiers":[
        {
            "category":"Manufacturing",
            "subcategory":"Tools & Machinery",
            "type":"Manufacturing & Wholesale Goods"
        }
    ],
    "sg:phone":"+1 972 293 9379",
    "sg:postcode":"75104",
    "sg:province":"TX",
    "sg:tags":[
        "mfg",
        "lithographic",
        "commercial",
        "trade",
        "p",
        "printing"
    ],
    "wof:name":"Global Direct USA",
    "wof:placetype":"venue"
},
  "geometry": {"coordinates":[-96.96101899999999,32.602641],"type":"Point"}
}