{
  "type": "Feature",
  "properties": {
    "iso:country":"US",
    "sg:address":"2385 S Stemmons Fwy",
    "sg:city":"Lewisville",
    "sg:classifiers":[
        {
            "category":"Autos & Motor Vehicles",
            "subcategory":"Auto Supplies",
            "type":"Retail Goods"
        }
    ],
    "sg:phone":"+1 972 315 3899",
    "sg:postcode":"75067",
    "sg:province":"TX",
    "sg:tags":[
        "tire"
    ],
    "sg:website":"www.discounttire.com/makeappt",
    "wof:name":"Discount Tire",
    "wof:placetype":"venue"
},
  "geometry": {"coordinates":[-96.974254,33.006583],"type":"Point"}
}