{
  "type": "Feature",
  "properties": {
    "iso:country":"US",
    "sg:address":"655 E Durango Blvd",
    "sg:city":"San Antonio",
    "sg:classifiers":[
        {
            "category":"Professional",
            "subcategory":"Secretarial Services",
            "type":"Services"
        }
    ],
    "sg:phone":"+1 210 271 0660",
    "sg:postcode":"78210",
    "sg:province":"TX",
    "sg:tags":[
        "reporting",
        "court"
    ],
    "wof:name":"Denver B Roden",
    "wof:placetype":"venue"
},
  "geometry": {"coordinates":[-98.487244,29.418421],"type":"Point"}
}