{
  "type": "Feature",
  "properties": {
    "iso:country":"US",
    "sg:address":"614 Cedar St",
    "sg:city":"Mercedes",
    "sg:classifiers":[
        {
            "category":"Building & Trades",
            "subcategory":"Electrical",
            "type":"Services"
        }
    ],
    "sg:phone":"+1 956 351 9292",
    "sg:postcode":"78570",
    "sg:province":"TX",
    "sg:tags":[
        "electrician"
    ],
    "wof:name":"Yg Electric",
    "wof:placetype":"venue"
},
  "geometry": {"coordinates":[-97.917817,26.15839],"type":"Point"}
}