{
  "type": "Feature",
  "properties": {
    "iso:country":"US",
    "sg:address":"4810 Beechnut St",
    "sg:city":"Houston",
    "sg:classifiers":[
        {
            "category":"Cinema",
            "subcategory":"Movie Rental",
            "type":"Entertainment"
        }
    ],
    "sg:phone":"+1 713 432 1959",
    "sg:postcode":"77096",
    "sg:province":"TX",
    "sg:tags":[
        "game",
        "video"
    ],
    "sg:website":"www.gamestop.com",
    "wof:name":"Game Stop",
    "wof:placetype":"venue"
},
  "geometry": {"coordinates":[-95.46169999999999,29.689301],"type":"Point"}
}