{
  "type": "Feature",
  "properties": {
    "iso:country":"US",
    "sg:address":"12300 Lake June Rd",
    "sg:city":"Mesquite",
    "sg:classifiers":[
        {
            "category":"Health Services",
            "subcategory":"Doctor",
            "type":"Services"
        }
    ],
    "sg:phone":"+1 972 913 0595",
    "sg:postcode":"75180",
    "sg:province":"TX",
    "wof:name":"Nguyen Dr & Associates",
    "wof:placetype":"venue"
},
  "geometry": {"coordinates":[-96.6157,32.733799],"type":"Point"}
}