{
  "type": "Feature",
  "properties": {
    "iso:country":"US",
    "sg:address":"23611 Mines Rd",
    "sg:city":"Laredo",
    "sg:classifiers":[
        {
            "category":"Autos & Motor Vehicles",
            "subcategory":"Automobile Sales",
            "type":"Retail Goods"
        }
    ],
    "sg:phone":"+1 956 723 5942",
    "sg:postcode":"78045",
    "sg:province":"TX",
    "sg:tags":[
        "truck"
    ],
    "wof:name":"Riley Truck & Equipment LLC",
    "wof:placetype":"venue"
},
  "geometry": {"coordinates":[-99.61424,27.653352],"type":"Point"}
}