{
  "type": "Feature",
  "properties": {
    "iso:country":"US",
    "sg:address":"11414 Mile Dr",
    "sg:city":"Houston",
    "sg:classifiers":[
        {
            "category":"Shopping",
            "subcategory":"Used Merchandise",
            "type":"Retail Goods"
        }
    ],
    "sg:phone":"+1 281 970 5048",
    "sg:postcode":"77065",
    "sg:province":"TX",
    "wof:name":"Rose Cabbage Antiques",
    "wof:placetype":"venue"
},
  "geometry": {"coordinates":[-95.592412,29.946155],"type":"Point"}
}