{
  "type": "Feature",
  "properties": {
    "iso:country":"US",
    "sg:address":"123 Blue Heron Dr Ste 101",
    "sg:city":"Montgomery",
    "sg:classifiers":[
        {
            "category":"Health Services",
            "subcategory":"Doctor",
            "type":"Services"
        }
    ],
    "sg:phone":"+1 936 448 6400",
    "sg:postcode":"77316",
    "sg:province":"TX",
    "sg:tags":[
        "medicine",
        "physician",
        "practice",
        "surgeons",
        "family"
    ],
    "wof:name":"Your Family Doctor",
    "wof:placetype":"venue"
},
  "geometry": {"coordinates":[-95.64302000000001,30.376596],"type":"Point"}
}