{
  "type": "Feature",
  "properties": {
    "iso:country":"US",
    "sg:address":"11515 Bellspring Dr",
    "sg:city":"Houston",
    "sg:classifiers":[
        {
            "category":"Building & Trades",
            "subcategory":"Landscaping Services",
            "type":"Services"
        }
    ],
    "sg:phone":"+1 281 495 4654",
    "sg:postcode":"77072",
    "sg:province":"TX",
    "wof:name":"Perez Family Landscaping",
    "wof:placetype":"venue"
},
  "geometry": {"coordinates":[-95.582156,29.713519],"type":"Point"}
}