{
  "type": "Feature",
  "properties": {
    "iso:country":"US",
    "sg:address":"1643 Lancaster Dr Ste 203",
    "sg:city":"Grapevine",
    "sg:classifiers":[
        {
            "category":"Health Services",
            "subcategory":"Doctor",
            "type":"Services"
        },
        {
            "category":"Health Services",
            "subcategory":"Clinic",
            "type":"Services"
        },
        {
            "category":"Community Center",
            "type":"Public Place"
        }
    ],
    "sg:phone":"+1 817 329 7670",
    "sg:postcode":"76051",
    "sg:province":"TX",
    "sg:tags":[
        "physician",
        "cardiology",
        "medical",
        "thoracic",
        "surgeons",
        "surgeon",
        "surgery",
        "surgery-general",
        "cardiovascular"
    ],
    "wof:name":"Cardiothoracic Surgery Associates Of North Texas Pa",
    "wof:placetype":"venue"
},
  "geometry": {"coordinates":[-97.09389400000001,32.932321],"type":"Point"}
}