{
  "type": "Feature",
  "properties": {
    "iso:country":"US",
    "sg:address":"321 Georgia St",
    "sg:city":"Odessa",
    "sg:classifiers":[
        {
            "category":"Wholesale",
            "subcategory":"Machinery & Supplies",
            "type":"Manufacturing & Wholesale Goods"
        }
    ],
    "sg:phone":"+1 432 550 0543",
    "sg:postcode":"79764",
    "sg:province":"TX",
    "sg:tags":[
        "field",
        "oil",
        "equipment"
    ],
    "wof:name":"Enertech Industries Inc",
    "wof:placetype":"venue"
},
  "geometry": {"coordinates":[-102.400311,31.912436],"type":"Point"}
}