{
  "type": "Feature",
  "properties": {
    "iso:country":"US",
    "sg:address":"2701 34th St",
    "sg:city":"Port Arthur",
    "sg:classifiers":[
        {
            "category":"Restaurant",
            "type":"Food & Drink"
        }
    ],
    "sg:phone":"+1 409 982 4296",
    "sg:postcode":"77640",
    "sg:province":"TX",
    "sg:tags":[
        "eating"
    ],
    "wof:name":"Fernees of Port Arthur",
    "wof:placetype":"venue"
},
  "geometry": {"coordinates":[-93.944934,29.909052],"type":"Point"}
}