{
  "type": "Feature",
  "properties": {
    "iso:country":"US",
    "sg:address":"1008 W Canty St",
    "sg:city":"Dallas",
    "sg:classifiers":[
        {
            "category":"Place Of Worship",
            "type":"Public Place"
        },
        {
            "category":"Place Of Worship",
            "subcategory":"Temple",
            "type":"Public Place"
        }
    ],
    "sg:phone":"+1 214 942 3008",
    "sg:postcode":"75208",
    "sg:province":"TX",
    "sg:tags":[
        "church"
    ],
    "wof:name":"Cliff Temple",
    "wof:placetype":"venue"
},
  "geometry": {"coordinates":[-96.839054,32.75237],"type":"Point"}
}