{
  "type": "Feature",
  "properties": {
    "iso:country":"US",
    "sg:address":"3614 Hwy 365",
    "sg:city":"Nederland",
    "sg:classifiers":[
        {
            "category":"Banks & Credit Unions",
            "subcategory":"Bank",
            "type":"Services"
        }
    ],
    "sg:phone":"+1 409 729 2939",
    "sg:postcode":"77627",
    "sg:province":"TX",
    "sg:tags":[
        "depository",
        "banking"
    ],
    "wof:name":"ACE Cash Express",
    "wof:placetype":"venue"
},
  "geometry": {"coordinates":[-93.99221,29.947669],"type":"Point"}
}