{
  "type": "Feature",
  "properties": {
    "iso:country":"US",
    "sg:address":"2510 S State Highway 36",
    "sg:city":"Gatesville",
    "sg:classifiers":[
        {
            "category":"Professional",
            "subcategory":"Advertising",
            "type":"Services"
        },
        {
            "category":"Manufacturing",
            "subcategory":"Signs",
            "type":"Manufacturing & Wholesale Goods"
        }
    ],
    "sg:phone":"+1 254 216 1461",
    "sg:postcode":"76528",
    "sg:province":"TX",
    "sg:tags":[
        "specialty"
    ],
    "wof:name":"Texas Custom Signs",
    "wof:placetype":"venue"
},
  "geometry": {"coordinates":[-97.727723,31.430915],"type":"Point"}
}