{
  "type": "Feature",
  "properties": {
    "iso:country":"US",
    "sg:address":"4210 Southpark Dr",
    "sg:city":"Amarillo",
    "sg:classifiers":[
        {
            "category":"Mining & Drilling",
            "type":"Manufacturing & Wholesale Goods"
        }
    ],
    "sg:phone":"+1 806 358 8793",
    "sg:postcode":"79109",
    "sg:province":"TX",
    "sg:tags":[
        "oil",
        "gas",
        "producer"
    ],
    "wof:name":"Water Resource Consultants",
    "wof:placetype":"venue"
},
  "geometry": {"coordinates":[-101.911339,35.164311],"type":"Point"}
}