{
  "type": "Feature",
  "properties": {
    "iso:country":"US",
    "sg:address":"1310 E 8th St",
    "sg:city":"Odessa",
    "sg:classifiers":[
        {
            "category":"Restaurant",
            "type":"Food & Drink"
        }
    ],
    "sg:phone":"+1 432 580 6648",
    "sg:postcode":"79761",
    "sg:province":"TX",
    "wof:name":"Rosa's Cafe & Tortilla Factory",
    "wof:placetype":"venue"
},
  "geometry": {"coordinates":[-102.35700900000001,31.858355],"type":"Point"}
}