{
  "type": "Feature",
  "properties": {
    "iso:country":"US",
    "sg:address":"2120 N Alexander Dr",
    "sg:city":"Baytown",
    "sg:classifiers":[
        {
            "category":"Fast Food",
            "type":"Food & Drink"
        },
        {
            "category":"Restaurant",
            "type":"Food & Drink"
        }
    ],
    "sg:phone":"+1 281 428 2573",
    "sg:postcode":"77520",
    "sg:province":"TX",
    "sg:tags":[
        "american",
        "take",
        "chicken"
    ],
    "sg:website":"http://www.popeyes.com",
    "wof:name":"Popeyes Chicken & Biscuits",
    "wof:placetype":"venue"
},
  "geometry": {"coordinates":[-94.950684,29.743732],"type":"Point"}
}