{
  "type": "Feature",
  "properties": {
    "iso:country":"US",
    "sg:address":"3020 Ridge Rd",
    "sg:city":"Rockwall",
    "sg:classifiers":[
        {
            "category":"Building & Trades",
            "subcategory":"Landscaping Services",
            "type":"Services"
        },
        {
            "category":"Community Center",
            "subcategory":"Senior",
            "type":"Public Place"
        },
        {
            "category":"Social Services",
            "subcategory":"Retirement Home",
            "type":"Services"
        },
        {
            "category":"Social Services",
            "subcategory":"Adult Care",
            "type":"Services"
        }
    ],
    "sg:phone":"+1 972 771 2800",
    "sg:postcode":"75032",
    "sg:province":"TX",
    "sg:tags":[
        "nurses-home",
        "nursing",
        "facility",
        "assisted",
        "convalescent",
        "homes-institutional",
        "citizen",
        "living",
        "aged"
    ],
    "sg:website":"http://www.scc-texas.com",
    "wof:name":"Summer Ridge Assisted Living & Retirement Community",
    "wof:placetype":"venue"
},
  "geometry": {"coordinates":[-96.473466,32.888109],"type":"Point"}
}