{
  "type": "Feature",
  "properties": {
    "iso:country":"US",
    "sg:address":"9968 Pack Saddle Trl",
    "sg:city":"Fort Worth",
    "sg:classifiers":[
        {
            "category":"Building & Trades",
            "subcategory":"Electrical",
            "type":"Services"
        }
    ],
    "sg:phone":"+1 817 367 7785",
    "sg:postcode":"76108",
    "sg:province":"TX",
    "sg:tags":[
        "installation"
    ],
    "wof:name":"J L Harp Svc",
    "wof:placetype":"venue"
},
  "geometry": {"coordinates":[-97.49368200000001,32.762132],"type":"Point"}
}