{
  "type": "Feature",
  "properties": {
    "iso:country":"US",
    "sg:address":"2045 Quail Run Rd",
    "sg:city":"Wylie",
    "sg:classifiers":[
        {
            "category":"Building & Trades",
            "subcategory":"Pest Control",
            "type":"Services"
        }
    ],
    "sg:phone":"+1 972 442 4443",
    "sg:postcode":"75098",
    "sg:province":"TX",
    "wof:name":"Roger's Pest Control",
    "wof:placetype":"venue"
},
  "geometry": {"coordinates":[-96.55511199999999,33.033523],"type":"Point"}
}