{
  "type": "Feature",
  "properties": {
    "iso:country":"US",
    "sg:address":"2401 E Missouri Ave",
    "sg:city":"El Paso",
    "sg:classifiers":[
        {
            "category":"Insurance",
            "subcategory":"Insurance Agent",
            "type":"Services"
        }
    ],
    "sg:phone":"+1 915 838 7529",
    "sg:postcode":"79903",
    "sg:province":"TX",
    "wof:name":"Palms Insurance Svc",
    "wof:placetype":"venue"
},
  "geometry": {"coordinates":[-106.465935,31.777085],"type":"Point"}
}