{
  "type": "Feature",
  "properties": {
    "iso:country":"US",
    "sg:address":"1813 Lucile Ave",
    "sg:city":"Wichita Falls",
    "sg:classifiers":[
        {
            "category":"Building & Trades",
            "subcategory":"Cleaning & Sanitation",
            "type":"Services"
        }
    ],
    "sg:phone":"+1 940 761 3408",
    "sg:postcode":"76301",
    "sg:province":"TX",
    "sg:tags":[
        "maintenance"
    ],
    "wof:name":"Golden Touch Window Cleaning",
    "wof:placetype":"venue"
},
  "geometry": {"coordinates":[-98.50624500000001,33.897941],"type":"Point"}
}