{
  "type": "Feature",
  "properties": {
    "iso:country":"US",
    "sg:address":"124 W Little York Rd",
    "sg:city":"Houston",
    "sg:classifiers":[
        {
            "category":"Real Estate",
            "subcategory":"Real Estate Services",
            "type":"Services"
        }
    ],
    "sg:phone":"+1 832 203 7319",
    "sg:postcode":"77076",
    "sg:province":"TX",
    "wof:name":"River Oaks Financial",
    "wof:placetype":"venue"
},
  "geometry": {"coordinates":[-95.399834,29.870083],"type":"Point"}
}