{
  "type": "Feature",
  "properties": {
    "iso:country":"US",
    "sg:address":"8716 N Mo Pac Expy",
    "sg:city":"Austin",
    "sg:classifiers":[
        {
            "category":"Banks & Credit Unions",
            "subcategory":"Financial Services",
            "type":"Services"
        }
    ],
    "sg:phone":"+1 512 342 9283",
    "sg:postcode":"78759",
    "sg:province":"TX",
    "sg:tags":[
        "broker",
        "mortgage"
    ],
    "sg:website":"www.tbimortgage.com",
    "wof:name":"TBI Mortgage",
    "wof:placetype":"venue"
},
  "geometry": {"coordinates":[-97.740146,30.375856],"type":"Point"}
}