{
  "type": "Feature",
  "properties": {
    "iso:country":"US",
    "sg:address":"3030 Towne Centre Dr",
    "sg:city":"Mesquite",
    "sg:classifiers":[
        {
            "category":"Health Services",
            "subcategory":"Health Practitioner",
            "type":"Services"
        }
    ],
    "sg:phone":"+1 972 681 8420",
    "sg:postcode":"75150",
    "sg:province":"TX",
    "sg:tags":[
        "home",
        "care"
    ],
    "sg:website":"www.agapehomehealth.com",
    "wof:name":"Agape Home Healthcare",
    "wof:placetype":"venue"
},
  "geometry": {"coordinates":[-96.62840300000001,32.8018],"type":"Point"}
}