{
  "type": "Feature",
  "properties": {
    "iso:country":"US",
    "sg:address":"10950 Highland Meadow Village",
    "sg:city":"Houston",
    "sg:classifiers":[
        {
            "category":"Social Services",
            "subcategory":"Child Care",
            "type":"Services"
        },
        {
            "category":"Education",
            "subcategory":"Preschool",
            "type":"Public Place"
        },
        {
            "category":"Education",
            "subcategory":"School",
            "type":"Public Place"
        }
    ],
    "sg:phone":"+1 281 412 5182",
    "sg:postcode":"77089",
    "sg:province":"TX",
    "sg:tags":[
        "high",
        "middle",
        "day",
        "elementary"
    ],
    "sg:website":"www.firstchristianacademy.org/",
    "wof:name":"First Christian Academy",
    "wof:placetype":"venue"
},
  "geometry": {"coordinates":[-95.215658,29.589721],"type":"Point"}
}