{
  "type": "Feature",
  "properties": {
    "iso:country":"US",
    "sg:address":"5683 Fairmont Pkwy",
    "sg:city":"Pasadena",
    "sg:classifiers":[
        {
            "category":"Shopping",
            "subcategory":"Shoes",
            "type":"Retail Goods"
        }
    ],
    "sg:phone":"+1 281 991 5251",
    "sg:postcode":"77505",
    "sg:province":"TX",
    "wof:name":"Shoe Zone Fairway Canter Inc",
    "wof:placetype":"venue"
},
  "geometry": {"coordinates":[-95.15422599999999,29.649995],"type":"Point"}
}