{
  "type": "Feature",
  "properties": {
    "iso:country":"US",
    "sg:address":"415 State Hwy 46 W",
    "sg:city":"Boerne",
    "sg:classifiers":[
        {
            "category":"Professional",
            "subcategory":"Business Services",
            "type":"Services"
        }
    ],
    "sg:phone":"+1 830 816 8102",
    "sg:postcode":"78006",
    "sg:province":"TX",
    "wof:name":"Benfield Group",
    "wof:placetype":"venue"
},
  "geometry": {"coordinates":[-98.79606,29.75754],"type":"Point"}
}