{
  "type": "Feature",
  "properties": {
    "iso:country":"US",
    "sg:address":"728 S Bois D Arc Ave",
    "sg:city":"Tyler",
    "sg:classifiers":[
        {
            "category":"Shopping",
            "type":"Retail Goods"
        }
    ],
    "sg:phone":"+1 903 593 4700",
    "sg:postcode":"75701",
    "sg:province":"TX",
    "sg:tags":[
        "art",
        "gallery",
        "dealer"
    ],
    "wof:name":"Marie Yvette Gallery",
    "wof:placetype":"venue"
},
  "geometry": {"coordinates":[-95.303229,32.341053],"type":"Point"}
}