{
  "type": "Feature",
  "properties": {
    "iso:country":"US",
    "sg:address":"510 Bering Dr Ste 300",
    "sg:city":"Houston",
    "sg:classifiers":[
        {
            "category":"Professional",
            "subcategory":"Accounting & Tax Preparation",
            "type":"Services"
        }
    ],
    "sg:phone":"+1 713 975 8558",
    "sg:postcode":"77057",
    "sg:province":"TX",
    "sg:tags":[
        "accountant"
    ],
    "wof:name":"Borchers Mary K CPA",
    "wof:placetype":"venue"
},
  "geometry": {"coordinates":[-95.4786,29.7651],"type":"Point"}
}