{
  "type": "Feature",
  "properties": {
    "iso:country":"US",
    "sg:address":"5911 Leisure Run Rd",
    "sg:city":"Austin",
    "sg:classifiers":[
        {
            "category":"Building & Trades",
            "subcategory":"Construction",
            "type":"Services"
        }
    ],
    "sg:phone":"+1 512 444 5487",
    "sg:postcode":"78745",
    "sg:province":"TX",
    "sg:tags":[
        "contractor"
    ],
    "wof:name":"Henrys Tile",
    "wof:placetype":"venue"
},
  "geometry": {"coordinates":[-97.784672,30.205043],"type":"Point"}
}