{
  "type": "Feature",
  "properties": {
    "iso:country":"US",
    "sg:address":"303 Kellett Ave",
    "sg:city":"Schulenburg",
    "sg:classifiers":[
        {
            "category":"Personal",
            "subcategory":"Barber",
            "type":"Services"
        }
    ],
    "sg:phone":"+1 979 743 6128",
    "sg:postcode":"78956",
    "sg:province":"TX",
    "sg:tags":[
        "shop"
    ],
    "wof:name":"Buster's Barber Shop",
    "wof:placetype":"venue"
},
  "geometry": {"coordinates":[-96.901985,29.684575],"type":"Point"}
}