{
  "type": "Feature",
  "properties": {
    "iso:country":"US",
    "sg:address":"4833 Saratoga Blvd",
    "sg:city":"Corpus Christi",
    "sg:classifiers":[
        {
            "category":"Professional",
            "subcategory":"Research",
            "type":"Services"
        }
    ],
    "sg:phone":"+1 361 334 1400",
    "sg:postcode":"78413",
    "sg:province":"TX",
    "sg:tags":[
        "environmental",
        "ecological"
    ],
    "wof:name":"Us Chemical Safety Svc",
    "wof:placetype":"venue"
},
  "geometry": {"coordinates":[-97.395556,27.691343],"type":"Point"}
}