{
  "type": "Feature",
  "properties": {
    "iso:country":"US",
    "sg:address":"924 Williamson Trl",
    "sg:city":"Amarillo",
    "sg:classifiers":[
        {
            "category":"Building & Trades",
            "subcategory":"Construction",
            "type":"Services"
        }
    ],
    "sg:phone":"+1 806 372 6330",
    "sg:postcode":"79118",
    "sg:province":"TX",
    "sg:tags":[
        "concrete",
        "contractor"
    ],
    "wof:name":"Concrete Floorstaining By Shan",
    "wof:placetype":"venue"
},
  "geometry": {"coordinates":[-101.82517300000001,35.161272],"type":"Point"}
}