{
  "type": "Feature",
  "properties": {
    "iso:country":"US",
    "sg:address":"3022 Rosemary Park Ln",
    "sg:city":"Houston",
    "sg:classifiers":[
        {
            "category":"Building & Trades",
            "subcategory":"Construction",
            "type":"Services"
        }
    ],
    "sg:phone":"+1 281 920 3569",
    "sg:postcode":"77082",
    "sg:province":"TX",
    "sg:tags":[
        "home",
        "builder"
    ],
    "wof:name":"David Powers Homes",
    "wof:placetype":"venue"
},
  "geometry": {"coordinates":[-95.587692,29.727956],"type":"Point"}
}