{
  "type": "Feature",
  "properties": {
    "iso:country":"US",
    "sg:address":"1121 Bedford Ct W",
    "sg:city":"Hurst",
    "sg:classifiers":[
        {
            "category":"Health Services",
            "subcategory":"Health Practitioner",
            "type":"Services"
        }
    ],
    "sg:phone":"+1 214 502 1356",
    "sg:postcode":"76053",
    "sg:province":"TX",
    "sg:tags":[
        "psychotherapist"
    ],
    "wof:name":"Healing Place",
    "wof:placetype":"venue"
},
  "geometry": {"coordinates":[-97.197042,32.829357],"type":"Point"}
}