{
  "type": "Feature",
  "properties": {
    "iso:country":"US",
    "sg:address":"6859 Arapaho Rd",
    "sg:city":"Dallas",
    "sg:classifiers":[
        {
            "category":"Retail",
            "subcategory":"Repair Shop",
            "type":"Services"
        }
    ],
    "sg:phone":"+1 214 291 9803",
    "sg:postcode":"75248",
    "sg:province":"TX",
    "wof:name":"24 Hour Emergency Locksmith",
    "wof:placetype":"venue"
},
  "geometry": {"coordinates":[-96.790633,32.96233],"type":"Point"}
}