{
  "type": "Feature",
  "properties": {
    "iso:country":"US",
    "sg:address":"929 Paradise Cove Rd",
    "sg:city":"Pottsboro",
    "sg:classifiers":[
        {
            "category":"Building & Trades",
            "subcategory":"Construction",
            "type":"Services"
        }
    ],
    "sg:phone":"+1 903 786 8684",
    "sg:postcode":"75076",
    "sg:province":"TX",
    "sg:tags":[
        "residential"
    ],
    "wof:name":"Interstate Mltfmily Contrs LLC",
    "wof:placetype":"venue"
},
  "geometry": {"coordinates":[-96.786327,33.789142],"type":"Point"}
}