{
  "type": "Feature",
  "properties": {
    "iso:country":"US",
    "sg:address":"13831 Northwest Fwy Ste 400",
    "sg:city":"Houston",
    "sg:classifiers":[
        {
            "category":"Banks & Credit Unions",
            "subcategory":"Bank",
            "type":"Services"
        },
        {
            "category":"Banks & Credit Unions",
            "subcategory":"Financial Services",
            "type":"Services"
        }
    ],
    "sg:phone":"+1 713 996 9838",
    "sg:postcode":"77040",
    "sg:province":"TX",
    "sg:tags":[
        "broker",
        "mortgage"
    ],
    "wof:name":"Mortgage Savings Of America",
    "wof:placetype":"venue"
},
  "geometry": {"coordinates":[-95.514816,29.85361],"type":"Point"}
}