{
  "type": "Feature",
  "properties": {
    "iso:country":"US",
    "sg:address":"2200 N Flores St",
    "sg:city":"San Antonio",
    "sg:classifiers":[
        {
            "category":"Recreation",
            "type":"Entertainment"
        }
    ],
    "sg:phone":"+1 210 732 5992",
    "sg:postcode":"78212",
    "sg:province":"TX",
    "sg:tags":[
        "pool",
        "swimming"
    ],
    "wof:name":"San Pedro Spring Swimming Pool",
    "wof:placetype":"venue"
},
  "geometry": {"coordinates":[-98.503818,29.448501],"type":"Point"}
}