{
  "type": "Feature",
  "properties": {
    "iso:country":"US",
    "sg:address":"2830 Calder Ave",
    "sg:city":"Beaumont",
    "sg:classifiers":[
        {
            "category":"Shopping",
            "subcategory":"Pharmacy",
            "type":"Retail Goods"
        }
    ],
    "sg:phone":"+1 409 899 7044",
    "sg:postcode":"77702",
    "sg:province":"TX",
    "wof:name":"St Elizabeth Room Control",
    "wof:placetype":"venue"
},
  "geometry": {"coordinates":[-94.130785,30.08568],"type":"Point"}
}