{
  "type": "Feature",
  "properties": {
    "iso:country":"US",
    "sg:address":"1902 E 7th St",
    "sg:city":"Brownsville",
    "sg:classifiers":[
        {
            "category":"Manufacturing",
            "subcategory":"Glass & Minerals",
            "type":"Manufacturing & Wholesale Goods"
        }
    ],
    "sg:phone":"+1 956 542 7575",
    "sg:postcode":"78520",
    "sg:province":"TX",
    "sg:tags":[
        "stone",
        "cut",
        "product"
    ],
    "wof:name":"Pinkerton Memorials",
    "wof:placetype":"venue"
},
  "geometry": {"coordinates":[-97.491303,25.913231],"type":"Point"}
}