{
  "type": "Feature",
  "properties": {
    "iso:country":"US",
    "sg:address":"821 S Greenville Ave",
    "sg:city":"Allen",
    "sg:classifiers":[
        {
            "category":"Organizations",
            "subcategory":"Religious Organization",
            "type":"Services"
        }
    ],
    "sg:phone":"+1 972 727 3191",
    "sg:postcode":"75002",
    "sg:province":"TX",
    "sg:tags":[
        "lutheran",
        "church"
    ],
    "wof:name":"Christ The Servant Lutheran",
    "wof:placetype":"venue"
},
  "geometry": {"coordinates":[-96.671409,33.086902],"type":"Point"}
}