{
  "type": "Feature",
  "properties": {
    "iso:country":"US",
    "sg:address":"4719 Taft Blvd",
    "sg:city":"Wichita Falls",
    "sg:classifiers":[
        {
            "category":"Professional",
            "subcategory":"Computer Services",
            "type":"Services"
        }
    ],
    "sg:phone":"+1 940 689 0200",
    "sg:postcode":"76308",
    "sg:province":"TX",
    "wof:name":"Computronix LLC",
    "wof:placetype":"venue"
},
  "geometry": {"coordinates":[-98.518598,33.860304],"type":"Point"}
}