{
  "type": "Feature",
  "properties": {
    "iso:country":"US",
    "sg:address":"14400 Midway Rd",
    "sg:city":"Dallas",
    "sg:classifiers":[
        {
            "category":"Education",
            "subcategory":"Library",
            "type":"Public Place"
        }
    ],
    "sg:phone":"+1 972 851 8000",
    "sg:postcode":"75244",
    "sg:province":"TX",
    "sg:tags":[
        "research"
    ],
    "wof:name":"Amigos Library Services",
    "wof:placetype":"venue"
},
  "geometry": {"coordinates":[-96.838804,32.947337],"type":"Point"}
}