{
  "type": "Feature",
  "properties": {
    "iso:country":"US",
    "sg:address":"830 Cherry St",
    "sg:city":"Uvalde",
    "sg:classifiers":[
        {
            "category":"Building & Trades",
            "subcategory":"Construction",
            "type":"Services"
        }
    ],
    "sg:phone":"+1 830 278 2809",
    "sg:postcode":"78801",
    "sg:province":"TX",
    "sg:tags":[
        "contractor"
    ],
    "wof:name":"T2 Welding",
    "wof:placetype":"venue"
},
  "geometry": {"coordinates":[-99.77412099999999,29.219228],"type":"Point"}
}