{
  "type": "Feature",
  "properties": {
    "iso:country":"US",
    "sg:address":"22811 I- 45",
    "sg:city":"Spring",
    "sg:classifiers":[
        {
            "category":"Building & Trades",
            "subcategory":"Pest Control",
            "type":"Services"
        }
    ],
    "sg:phone":"+1 281 353 4427",
    "sg:postcode":"77389",
    "sg:province":"TX",
    "wof:name":"Allied Exterminators",
    "wof:placetype":"venue"
},
  "geometry": {"coordinates":[-95.43590399999999,30.106635],"type":"Point"}
}