{
  "type": "Feature",
  "properties": {
    "iso:country":"US",
    "sg:address":"6829 Hillcrest Ave",
    "sg:city":"Dallas",
    "sg:classifiers":[
        {
            "category":"Banks & Credit Unions",
            "subcategory":"Bank",
            "type":"Services"
        }
    ],
    "sg:phone":"+1 214 378 3011",
    "sg:postcode":"75205",
    "sg:province":"TX",
    "sg:tags":[
        "saving",
        "commercial"
    ],
    "sg:website":"www.parkcitiesbank.com",
    "wof:name":"Park Cities Bank",
    "wof:placetype":"venue"
},
  "geometry": {"coordinates":[-96.787003,32.849201],"type":"Point"}
}