{
  "type": "Feature",
  "properties": {
    "iso:country":"US",
    "sg:address":"614 Cypress St",
    "sg:city":"Pittsburg",
    "sg:classifiers":[
        {
            "category":"Retail",
            "subcategory":"Auto Repair",
            "type":"Services"
        }
    ],
    "sg:phone":"+1 903 856 5409",
    "sg:postcode":"75686",
    "sg:province":"TX",
    "sg:tags":[
        "shop",
        "automotive",
        "general",
        "paint"
    ],
    "wof:name":"Allen Bodyshop",
    "wof:placetype":"venue"
},
  "geometry": {"coordinates":[-94.96663700000001,33.006911],"type":"Point"}
}