{
  "type": "Feature",
  "properties": {
    "iso:country":"US",
    "sg:address":"10023 Co Rd 6740",
    "sg:city":"Lubbock",
    "sg:classifiers":[
        {
            "category":"Wholesale",
            "subcategory":"Durable Goods & Equipment",
            "type":"Manufacturing & Wholesale Goods"
        }
    ],
    "sg:phone":"+1 806 885 1374",
    "sg:postcode":"79407",
    "sg:province":"TX",
    "wof:name":"Js Wholesale",
    "wof:placetype":"venue"
},
  "geometry": {"coordinates":[-102.043204,33.57062],"type":"Point"}
}