{
  "type": "Feature",
  "properties": {
    "iso:country":"US",
    "sg:address":"9721 S Coulter St",
    "sg:city":"Amarillo",
    "sg:classifiers":[
        {
            "category":"Recreation",
            "type":"Entertainment"
        }
    ],
    "sg:phone":"+1 806 351 0000",
    "sg:postcode":"79119",
    "sg:province":"TX",
    "sg:tags":[
        "skating",
        "rink"
    ],
    "wof:name":"Skate Plex",
    "wof:placetype":"venue"
},
  "geometry": {"coordinates":[-101.91965999999999,35.103812],"type":"Point"}
}