{
  "type": "Feature",
  "properties": {
    "iso:country":"US",
    "sg:address":"624 Denver Ave",
    "sg:city":"Dalhart",
    "sg:classifiers":[
        {
            "category":"Professional",
            "type":"Services"
        }
    ],
    "sg:phone":"+1 806 249 2133",
    "sg:postcode":"79022",
    "sg:province":"TX",
    "sg:tags":[
        "establishment"
    ],
    "wof:name":"Hartley Station",
    "wof:placetype":"venue"
},
  "geometry": {"coordinates":[-102.52198799999999,36.059593],"type":"Point"}
}