{
  "type": "Feature",
  "properties": {
    "iso:country":"US",
    "sg:address":"2469 Dalworth St",
    "sg:city":"Grand Prairie",
    "sg:classifiers":[
        {
            "category":"Bars & Pubs",
            "type":"Food & Drink"
        }
    ],
    "sg:menulink":"http://www.allmenus.com/tx/arlington/175995-dickeys-barbecue-pit/menu/",
    "sg:phone":"+1 972 641 9044",
    "sg:postcode":"75050",
    "sg:province":"TX",
    "sg:tags":[
        "barbecue",
        "american"
    ],
    "wof:name":"Dickey's Barbecue Pit",
    "wof:placetype":"venue"
},
  "geometry": {"coordinates":[-97.04203099999999,32.744375],"type":"Point"}
}