{
  "type": "Feature",
  "properties": {
    "iso:country":"US",
    "sg:address":"440 Benmar Dr",
    "sg:city":"Houston",
    "sg:classifiers":[
        {
            "category":"Organizations",
            "subcategory":"Non-profit Organization",
            "type":"Services"
        }
    ],
    "sg:phone":"+1 281 448 2387",
    "sg:postcode":"77060",
    "sg:province":"TX",
    "sg:tags":[
        "information",
        "alcoholism",
        "treatment"
    ],
    "wof:name":"Contemporary Teaching Videos",
    "wof:placetype":"venue"
},
  "geometry": {"coordinates":[-95.398763,29.943907],"type":"Point"}
}