{
  "type": "Feature",
  "properties": {
    "iso:country":"US",
    "sg:address":"2302 Field St",
    "sg:city":"San Angelo",
    "sg:classifiers":[
        {
            "category":"Retail",
            "subcategory":"Laundry & Dry Cleaning",
            "type":"Services"
        }
    ],
    "sg:phone":"+1 325 947 1617",
    "sg:postcode":"76901",
    "sg:province":"TX",
    "sg:tags":[
        "cleaners",
        "upholstery",
        "rug",
        "carpet"
    ],
    "wof:name":"Ken's Carpet Care",
    "wof:placetype":"venue"
},
  "geometry": {"coordinates":[-100.480756,31.471265],"type":"Point"}
}