{
  "type": "Feature",
  "properties": {
    "iso:country":"US",
    "sg:address":"2269 S Church St",
    "sg:city":"Paris",
    "sg:classifiers":[
        {
            "category":"Shopping",
            "subcategory":"Hobbies, Toys, & Games",
            "type":"Retail Goods"
        }
    ],
    "sg:phone":"+1 903 784 4579",
    "sg:postcode":"75460",
    "sg:province":"TX",
    "sg:tags":[
        "craft"
    ],
    "wof:name":"Lazy D Creations",
    "wof:placetype":"venue"
},
  "geometry": {"coordinates":[-95.55591099999999,33.63787],"type":"Point"}
}