{
  "type": "Feature",
  "properties": {
    "iso:country":"US",
    "sg:address":"501 W Jefferson Blvd",
    "sg:city":"Dallas",
    "sg:classifiers":[
        {
            "category":"Utilities",
            "subcategory":"Mobile Phone",
            "type":"Services"
        }
    ],
    "sg:phone":"+1 214 948 1202",
    "sg:postcode":"75208",
    "sg:province":"TX",
    "sg:tags":[
        "communication",
        "radiotelephone"
    ],
    "wof:name":"KWI Wireless",
    "wof:placetype":"venue"
},
  "geometry": {"coordinates":[-96.832123,32.743145],"type":"Point"}
}