{
  "type": "Feature",
  "properties": {
    "iso:country":"US",
    "sg:address":"15242 Shapiro Springs Ln",
    "sg:city":"Houston",
    "sg:classifiers":[
        {
            "category":"Building & Trades",
            "subcategory":"Construction",
            "type":"Services"
        }
    ],
    "sg:phone":"+1 281 463 0208",
    "sg:postcode":"77095",
    "sg:province":"TX",
    "sg:tags":[
        "house"
    ],
    "wof:name":"T K Builders Inc",
    "wof:placetype":"venue"
},
  "geometry": {"coordinates":[-95.632319,29.909986],"type":"Point"}
}