{
  "type": "Feature",
  "properties": {
    "iso:country":"US",
    "sg:address":"1311 Potter St",
    "sg:city":"Borger",
    "sg:classifiers":[
        {
            "category":"Wholesale",
            "subcategory":"Office Equipment",
            "type":"Manufacturing & Wholesale Goods"
        }
    ],
    "sg:phone":"+1 806 273 8506",
    "sg:postcode":"79007",
    "sg:province":"TX",
    "wof:name":"A1 Business Machines",
    "wof:placetype":"venue"
},
  "geometry": {"coordinates":[-101.392399,35.684104],"type":"Point"}
}