{
  "type": "Feature",
  "properties": {
    "iso:country":"US",
    "sg:address":"4112 Throckmorton St",
    "sg:city":"Dallas",
    "sg:classifiers":[
        {
            "category":"Organizations",
            "subcategory":"Religious Organization",
            "type":"Services"
        }
    ],
    "sg:phone":"+1 214 528 3741",
    "sg:postcode":"75219",
    "sg:province":"TX",
    "wof:name":"Saint Seraphim Estrn Orthdx Ch",
    "wof:placetype":"venue"
},
  "geometry": {"coordinates":[-96.804445,32.819561],"type":"Point"}
}