{
  "type": "Feature",
  "properties": {
    "iso:country":"US",
    "sg:address":"1633 Commercial Ave",
    "sg:city":"Anson",
    "sg:classifiers":[
        {
            "category":"Food & Beverages",
            "subcategory":"Groceries & Convenience Stores",
            "type":"Retail Goods"
        }
    ],
    "sg:phone":"+1 325 823 3722",
    "sg:postcode":"79501",
    "sg:province":"TX",
    "wof:name":"Allsup's Convenience Store",
    "wof:placetype":"venue"
},
  "geometry": {"coordinates":[-99.896722,32.752021],"type":"Point"}
}