{
  "type": "Feature",
  "properties": {
    "iso:country":"US",
    "sg:address":"629 Euclid St",
    "sg:city":"Houston",
    "sg:classifiers":[
        {
            "category":"Travel",
            "subcategory":"Travel Agent",
            "type":"Entertainment"
        }
    ],
    "sg:phone":"+1 713 266 8166",
    "sg:postcode":"77009",
    "sg:province":"TX",
    "sg:tags":[
        "agency"
    ],
    "wof:name":"Executive International Travel",
    "wof:placetype":"venue"
},
  "geometry": {"coordinates":[-95.37893200000001,29.785369],"type":"Point"}
}