{
  "type": "Feature",
  "properties": {
    "iso:country":"US",
    "sg:address":"5824 W Plano Pkwy",
    "sg:city":"Plano",
    "sg:classifiers":[
        {
            "category":"Health Services",
            "subcategory":"Dentist",
            "type":"Services"
        }
    ],
    "sg:phone":"+1 972 930 0940",
    "sg:postcode":"75093",
    "sg:province":"TX",
    "wof:name":"Dr David Gerkin & Dr Mary Carmen Esteso",
    "wof:placetype":"venue"
},
  "geometry": {"coordinates":[-96.81909899999999,33.016602],"type":"Point"}
}