{
  "type": "Feature",
  "properties": {
    "iso:country":"US",
    "sg:address":"4604 Hibiscus Valley Dr",
    "sg:city":"Austin",
    "sg:classifiers":[
        {
            "category":"Communications",
            "type":"Services"
        }
    ],
    "sg:phone":"+1 512 288 5572",
    "sg:postcode":"78739",
    "sg:province":"TX",
    "wof:name":"Mar-Key Media",
    "wof:placetype":"venue"
},
  "geometry": {"coordinates":[-97.865813,30.188342],"type":"Point"}
}