{
  "type": "Feature",
  "properties": {
    "iso:country":"US",
    "sg:address":"3506 State Hwy 6",
    "sg:city":"Sugar Land",
    "sg:classifiers":[
        {
            "category":"Restaurant",
            "type":"Food & Drink"
        }
    ],
    "sg:phone":"+1 281 980 6654",
    "sg:postcode":"77478",
    "sg:province":"TX",
    "sg:tags":[
        "parlor",
        "eating",
        "ice",
        "cream"
    ],
    "wof:name":"Yummies Catering",
    "wof:placetype":"venue"
},
  "geometry": {"coordinates":[-95.600632,29.590426],"type":"Point"}
}