{
  "type": "Feature",
  "properties": {
    "iso:country":"US",
    "sg:address":"5100 Westheimer Rd",
    "sg:city":"Houston",
    "sg:classifiers":[
        {
            "category":"Professional",
            "subcategory":"Lawyer & Legal Services",
            "type":"Services"
        }
    ],
    "sg:phone":"+1 713 629 9820",
    "sg:postcode":"77056",
    "sg:province":"TX",
    "wof:name":"Darcy Daniel J Atty",
    "wof:placetype":"venue"
},
  "geometry": {"coordinates":[-95.464203,29.740801],"type":"Point"}
}