{
  "type": "Feature",
  "properties": {
    "iso:country":"US",
    "sg:address":"10877 Rockwall Rd",
    "sg:city":"Dallas",
    "sg:classifiers":[
        {
            "category":"Building & Trades",
            "subcategory":"Construction",
            "type":"Services"
        }
    ],
    "sg:phone":"+1 214 253 2332",
    "sg:postcode":"75238",
    "sg:province":"TX",
    "sg:tags":[
        "contractor"
    ],
    "wof:name":"Metal Tech",
    "wof:placetype":"venue"
},
  "geometry": {"coordinates":[-96.707703,32.897315],"type":"Point"}
}