{
  "type": "Feature",
  "properties": {
    "iso:country":"US",
    "sg:address":"11461 Perrin Beitel Rd",
    "sg:city":"San Antonio",
    "sg:classifiers":[
        {
            "category":"Restaurant",
            "type":"Food & Drink"
        }
    ],
    "sg:phone":"+1 210 590 1492",
    "sg:postcode":"78217",
    "sg:province":"TX",
    "sg:tags":[
        "mexican"
    ],
    "wof:name":"Las Palapas Mexican Restaurant",
    "wof:placetype":"venue"
},
  "geometry": {"coordinates":[-98.411095,29.544144],"type":"Point"}
}