{
  "type": "Feature",
  "properties": {
    "iso:country":"US",
    "sg:address":"205 S Main St",
    "sg:city":"Bryan",
    "sg:phone":"+1 979 779 7337",
    "sg:postcode":"77803",
    "sg:province":"TX",
    "wof:name":"Los Nortenos Mexican Cafe",
    "wof:placetype":"venue"
},
  "geometry": {"coordinates":[-96.373581,30.672602],"type":"Point"}
}