{
  "type": "Feature",
  "properties": {
    "iso:country":"US",
    "sg:address":"2310 Fm 9 S",
    "sg:city":"Waskom",
    "sg:classifiers":[
        {
            "category":"Professional",
            "subcategory":"Detective & Security Services",
            "type":"Services"
        }
    ],
    "sg:phone":"+1 903 633 2244",
    "sg:postcode":"75692",
    "sg:province":"TX",
    "sg:tags":[
        "information",
        "bureau"
    ],
    "wof:name":"Industrial Waste Services",
    "wof:placetype":"venue"
},
  "geometry": {"coordinates":[-94.070517,32.44792],"type":"Point"}
}