{
  "type": "Feature",
  "properties": {
    "iso:country":"US",
    "sg:address":"509 W Crawford St",
    "sg:city":"Denison",
    "sg:classifiers":[
        {
            "category":"Retail",
            "subcategory":"Auto Rental",
            "type":"Services"
        }
    ],
    "sg:phone":"+1 903 891 0600",
    "sg:postcode":"75020",
    "sg:province":"TX",
    "sg:tags":[
        "renting",
        "leasing",
        "trailer"
    ],
    "wof:name":"Daniels Plant Food Inc",
    "wof:placetype":"venue"
},
  "geometry": {"coordinates":[-96.543043,33.753712],"type":"Point"}
}