{
  "type": "Feature",
  "properties": {
    "iso:country":"US",
    "sg:address":"1115 W Mayfield Rd",
    "sg:city":"Arlington",
    "sg:phone":"+1 817 467 6688",
    "sg:postcode":"76015",
    "sg:province":"TX",
    "wof:name":"Animal Health Care Center",
    "wof:placetype":"venue"
},
  "geometry": {"coordinates":[-97.124745,32.691312],"type":"Point"}
}