{
  "type": "Feature",
  "properties": {
    "iso:country":"US",
    "sg:address":"3505 Berry Rd",
    "sg:city":"Houston",
    "sg:classifiers":[
        {
            "category":"Health Services",
            "subcategory":"Clinic",
            "type":"Services"
        }
    ],
    "sg:phone":"+1 281 531 4461",
    "sg:postcode":"77093",
    "sg:province":"TX",
    "sg:tags":[
        "home"
    ],
    "wof:name":"West Houston HM Hlth Rehab Svc",
    "wof:placetype":"venue"
},
  "geometry": {"coordinates":[-95.335739,29.838515],"type":"Point"}
}