{
  "type": "Feature",
  "properties": {
    "iso:country":"US",
    "sg:address":"13330 Blanco Rd",
    "sg:city":"San Antonio",
    "sg:classifiers":[
        {
            "category":"Professional",
            "type":"Services"
        }
    ],
    "sg:phone":"+1 210 492 6746",
    "sg:postcode":"78216",
    "sg:province":"TX",
    "wof:name":"H Welsh",
    "wof:placetype":"venue"
},
  "geometry": {"coordinates":[-98.519718,29.567328],"type":"Point"}
}