{
  "type": "Feature",
  "properties": {
    "iso:country":"US",
    "sg:address":"170 Spring Pines Dr",
    "sg:city":"Spring",
    "sg:classifiers":[
        {
            "category":"Professional",
            "subcategory":"Business Services",
            "type":"Services"
        }
    ],
    "sg:phone":"+1 281 367 7251",
    "sg:postcode":"77386",
    "sg:province":"TX",
    "wof:name":"Bryan Business Solutions",
    "wof:placetype":"venue"
},
  "geometry": {"coordinates":[-95.44538799999999,30.145562],"type":"Point"}
}