{
  "type": "Feature",
  "properties": {
    "iso:country":"US",
    "sg:address":"703 S Highway 377",
    "sg:city":"Aubrey",
    "sg:classifiers":[
        {
            "category":"Community Center",
            "type":"Public Place"
        }
    ],
    "sg:phone":"+1 940 365 1770",
    "sg:postcode":"76227",
    "sg:province":"TX",
    "sg:tags":[
        "medical"
    ],
    "wof:name":"Springhill Medical & Aesthetics",
    "wof:placetype":"venue"
},
  "geometry": {"coordinates":[-96.98271099999999,33.298689],"type":"Point"}
}