{
  "type": "Feature",
  "properties": {
    "iso:country":"US",
    "sg:address":"10005 Fm 1960 Rd W",
    "sg:city":"Humble",
    "sg:classifiers":[
        {
            "category":"Restaurant",
            "type":"Food & Drink"
        }
    ],
    "sg:menulink":"http://www.allmenus.com/tx/houston/14686-pappasitos-cantina/menu/",
    "sg:phone":"+1 281 540 8664",
    "sg:postcode":"77338",
    "sg:province":"TX",
    "sg:tags":[
        "mexican"
    ],
    "wof:name":"Pappasito's Cantina",
    "wof:placetype":"venue"
},
  "geometry": {"coordinates":[-95.271755,30.001637],"type":"Point"}
}