{
  "type": "Feature",
  "properties": {
    "iso:country":"US",
    "sg:address":"5307 Ct of York",
    "sg:city":"Houston",
    "sg:classifiers":[
        {
            "category":"Professional",
            "type":"Services"
        }
    ],
    "sg:phone":"+1 281 537 0161",
    "sg:postcode":"77069",
    "sg:province":"TX",
    "wof:name":"Gus Camacho Inc",
    "wof:placetype":"venue"
},
  "geometry": {"coordinates":[-95.519347,29.994384],"type":"Point"}
}