{
  "type": "Feature",
  "properties": {
    "iso:country":"US",
    "sg:address":"20 Oakbrook Dr",
    "sg:city":"Lewisville",
    "sg:classifiers":[
        {
            "category":"Education",
            "subcategory":"Dance Studio",
            "type":"Public Place"
        }
    ],
    "sg:phone":"+1 214 513 7771",
    "sg:postcode":"75057",
    "sg:province":"TX",
    "sg:tags":[
        "instruction",
        "dancing"
    ],
    "wof:name":"Song N Dance",
    "wof:placetype":"venue"
},
  "geometry": {"coordinates":[-97.016947,33.081203],"type":"Point"}
}