{
  "type": "Feature",
  "properties": {
    "iso:country":"US",
    "sg:address":"446 Mid Cities Blvd",
    "sg:city":"Hurst",
    "sg:classifiers":[
        {
            "category":"Personal",
            "subcategory":"Beauty Salon",
            "type":"Services"
        }
    ],
    "sg:phone":"+1 817 514 8889",
    "sg:postcode":"76054",
    "sg:province":"TX",
    "wof:name":"Shelly Wade",
    "wof:placetype":"venue"
},
  "geometry": {"coordinates":[-97.173676,32.86733],"type":"Point"}
}