{
  "type": "Feature",
  "properties": {
    "iso:country":"US",
    "sg:address":"3419 Nottingham St",
    "sg:city":"Houston",
    "sg:classifiers":[
        {
            "category":"Health Services",
            "subcategory":"Hospital",
            "type":"Services"
        }
    ],
    "sg:phone":"+1 713 664 5772",
    "sg:postcode":"77005",
    "sg:province":"TX",
    "sg:tags":[
        "specialty"
    ],
    "wof:name":"Patrick G Grant P C",
    "wof:placetype":"venue"
},
  "geometry": {"coordinates":[-95.43100699999999,29.721834],"type":"Point"}
}