{
  "type": "Feature",
  "properties": {
    "iso:country":"US",
    "sg:address":"12151 Valliant St",
    "sg:city":"San Antonio",
    "sg:classifiers":[
        {
            "category":"Professional",
            "type":"Services"
        }
    ],
    "sg:phone":"+1 210 344 5642",
    "sg:postcode":"78216",
    "sg:province":"TX",
    "wof:name":"Bl LLC",
    "wof:placetype":"venue"
},
  "geometry": {"coordinates":[-98.497568,29.552015],"type":"Point"}
}