{
  "type": "Feature",
  "properties": {
    "iso:country":"US",
    "sg:address":"2928 Sharon St",
    "sg:city":"Dallas",
    "sg:classifiers":[
        {
            "category":"Personal",
            "subcategory":"Beauty Salon",
            "type":"Services"
        }
    ],
    "sg:phone":"+1 214 361 8510",
    "sg:postcode":"75211",
    "sg:province":"TX",
    "sg:tags":[
        "shop"
    ],
    "wof:name":"Beauty Salon",
    "wof:placetype":"venue"
},
  "geometry": {"coordinates":[-96.87163200000001,32.729705],"type":"Point"}
}