{
  "type": "Feature",
  "properties": {
    "iso:country":"US",
    "sg:address":"7108 76th St",
    "sg:city":"Lubbock",
    "sg:classifiers":[
        {
            "category":"Health Services",
            "subcategory":"Clinic",
            "type":"Services"
        }
    ],
    "sg:phone":"+1 806 798 8245",
    "sg:postcode":"79424",
    "sg:province":"TX",
    "wof:name":"Helm Medical Solutions",
    "wof:placetype":"venue"
},
  "geometry": {"coordinates":[-101.973229,33.525303],"type":"Point"}
}