{
  "type": "Feature",
  "properties": {
    "iso:country":"US",
    "sg:address":"1619 Summerfield Dr",
    "sg:city":"Edinburg",
    "sg:classifiers":[
        {
            "category":"Health Services",
            "subcategory":"Health Practitioner",
            "type":"Services"
        }
    ],
    "sg:phone":"+1 956 380 3838",
    "sg:postcode":"78539",
    "sg:province":"TX",
    "sg:tags":[
        "nurse",
        "registry"
    ],
    "wof:name":"Asap Nursing Svc",
    "wof:placetype":"venue"
},
  "geometry": {"coordinates":[-98.192605,26.287767],"type":"Point"}
}