{
  "type": "Feature",
  "properties": {
    "iso:country":"US",
    "sg:address":"16633 Dallas Pkwy",
    "sg:city":"Addison",
    "sg:classifiers":[
        {
            "category":"Real Estate",
            "subcategory":"Real Estate Services",
            "type":"Services"
        }
    ],
    "sg:phone":"+1 972 818 1810",
    "sg:postcode":"75001",
    "sg:province":"TX",
    "sg:tags":[
        "management",
        "property"
    ],
    "wof:name":"Transwestern Commercial Services",
    "wof:placetype":"venue"
},
  "geometry": {"coordinates":[-96.82857799999999,32.97928],"type":"Point"}
}