{
  "type": "Feature",
  "properties": {
    "iso:country":"US",
    "sg:address":"504 Medical Center Blvd",
    "sg:city":"Conroe",
    "sg:classifiers":[
        {
            "category":"Health Services",
            "subcategory":"Doctor",
            "type":"Services"
        }
    ],
    "sg:phone":"+1 936 539 7024",
    "sg:postcode":"77304",
    "sg:province":"TX",
    "sg:tags":[
        "radiology"
    ],
    "wof:name":"Conroe Network Radiology Assoc",
    "wof:placetype":"venue"
},
  "geometry": {"coordinates":[-95.465115,30.285897],"type":"Point"}
}