{
  "type": "Feature",
  "properties": {
    "iso:country":"US",
    "sg:address":"1823 Concho River Ct",
    "sg:city":"Sugar Land",
    "sg:classifiers":[
        {
            "category":"Professional",
            "subcategory":"Management & Consulting",
            "type":"Services"
        }
    ],
    "sg:phone":"+1 281 242 9505",
    "sg:postcode":"77478",
    "sg:province":"TX",
    "sg:tags":[
        "equipment",
        "energy",
        "oilfield"
    ],
    "wof:name":"Ashi Energy Services  LLC",
    "wof:placetype":"venue"
},
  "geometry": {"coordinates":[-95.585629,29.600436],"type":"Point"}
}