{
  "type": "Feature",
  "properties": {
    "iso:country":"US",
    "sg:address":"3231 Chesterfield Ln",
    "sg:city":"Stafford",
    "sg:classifiers":[
        {
            "category":"Restaurant",
            "type":"Food & Drink"
        }
    ],
    "sg:phone":"+1 281 494 2319",
    "sg:postcode":"77477",
    "sg:province":"TX",
    "sg:tags":[
        "eating"
    ],
    "wof:name":"Mu Shun Hsieh",
    "wof:placetype":"venue"
},
  "geometry": {"coordinates":[-95.58658,29.626441],"type":"Point"}
}