{
  "type": "Feature",
  "properties": {
    "iso:country":"US",
    "sg:address":"501 N Wichita St",
    "sg:city":"Electra",
    "sg:classifiers":[
        {
            "category":"Organizations",
            "subcategory":"Religious Organization",
            "type":"Services"
        }
    ],
    "sg:phone":"+1 940 495 2660",
    "sg:postcode":"76360",
    "sg:province":"TX",
    "sg:tags":[
        "church"
    ],
    "wof:name":"Crossroad Family Church",
    "wof:placetype":"venue"
},
  "geometry": {"coordinates":[-98.91768399999999,34.035223],"type":"Point"}
}