{
  "type": "Feature",
  "properties": {
    "iso:country":"US",
    "sg:address":"2121 San Jacinto St",
    "sg:city":"Dallas",
    "sg:classifiers":[
        {
            "category":"Food & Beverages",
            "subcategory":"Groceries & Convenience Stores",
            "type":"Retail Goods"
        }
    ],
    "sg:phone":"+1 214 754 1861",
    "sg:postcode":"75201",
    "sg:province":"TX",
    "wof:name":"Culinaire International",
    "wof:placetype":"venue"
},
  "geometry": {"coordinates":[-96.796982,32.787264],"type":"Point"}
}