{
  "type": "Feature",
  "properties": {
    "iso:country":"US",
    "sg:address":"6445 Gulfton St",
    "sg:city":"Houston",
    "sg:classifiers":[
        {
            "category":"Retail",
            "subcategory":"Auto Repair",
            "type":"Services"
        }
    ],
    "sg:phone":"+1 713 777 7267",
    "sg:postcode":"77081",
    "sg:province":"TX",
    "sg:tags":[
        "automotive"
    ],
    "wof:name":"Jiffy Lube",
    "wof:placetype":"venue"
},
  "geometry": {"coordinates":[-95.49539300000001,29.715941],"type":"Point"}
}