{
  "type": "Feature",
  "properties": {
    "iso:country":"US",
    "sg:address":"3013 S Cooper St",
    "sg:city":"Arlington",
    "sg:classifiers":[
        {
            "category":"Retail",
            "subcategory":"Auto Repair",
            "type":"Services"
        }
    ],
    "sg:phone":"+1 817 465 5016",
    "sg:postcode":"76015",
    "sg:province":"TX",
    "sg:tags":[
        "transmission",
        "general"
    ],
    "wof:name":"AAMCO Transmissions",
    "wof:placetype":"venue"
},
  "geometry": {"coordinates":[-97.125182,32.696019],"type":"Point"}
}