{
  "type": "Feature",
  "properties": {
    "iso:country":"US",
    "sg:address":"385 S Goliad St",
    "sg:city":"Rockwall",
    "sg:classifiers":[
        {
            "category":"Government",
            "subcategory":"Office",
            "type":"Public Place"
        }
    ],
    "sg:phone":"+1 972 771 7745",
    "sg:postcode":"75087",
    "sg:province":"TX",
    "sg:tags":[
        "city",
        "planning",
        "dev"
    ],
    "sg:website":"www.cityofrockwall.com",
    "wof:name":"Rockwall Planning & Zoning",
    "wof:placetype":"venue"
},
  "geometry": {"coordinates":[-96.460258,32.929258],"type":"Point"}
}