{
  "type": "Feature",
  "properties": {
    "iso:country":"US",
    "sg:address":"2800 W Northwest Hwy",
    "sg:city":"Dallas",
    "sg:classifiers":[
        {
            "category":"Banks & Credit Unions",
            "subcategory":"Bank",
            "type":"Services"
        }
    ],
    "sg:phone":"+1 214 357 9953",
    "sg:postcode":"75220",
    "sg:province":"TX",
    "sg:tags":[
        "cashing",
        "check"
    ],
    "wof:name":"Cliffs Check Cashing",
    "wof:placetype":"venue"
},
  "geometry": {"coordinates":[-96.87261700000001,32.857017],"type":"Point"}
}