{
  "type": "Feature",
  "properties": {
    "iso:country":"US",
    "sg:address":"4901 Joshua Dr",
    "sg:city":"Flower Mound",
    "sg:classifiers":[
        {
            "category":"Insurance",
            "subcategory":"Insurance Agent",
            "type":"Services"
        }
    ],
    "sg:phone":"+1 972 497 1600",
    "sg:postcode":"75028",
    "sg:province":"TX",
    "sg:tags":[
        "broker",
        "mortgage"
    ],
    "wof:name":"Acceptance Financial Inc",
    "wof:placetype":"venue"
},
  "geometry": {"coordinates":[-97.108431,33.053452],"type":"Point"}
}