{
  "type": "Feature",
  "properties": {
    "iso:country":"US",
    "sg:address":"5505 Polo Club Rd",
    "sg:city":"Midland",
    "sg:classifiers":[
        {
            "category":"Farming",
            "subcategory":"Farm",
            "type":"Manufacturing & Wholesale Goods"
        }
    ],
    "sg:phone":"+1 432 687 4061",
    "sg:postcode":"79705",
    "sg:province":"TX",
    "sg:tags":[
        "crop",
        "general"
    ],
    "wof:name":"Martex Farms",
    "wof:placetype":"venue"
},
  "geometry": {"coordinates":[-102.112031,32.048175],"type":"Point"}
}