{
  "type": "Feature",
  "properties": {
    "iso:country":"US",
    "sg:address":"411 Barrera St",
    "sg:city":"San Antonio",
    "sg:classifiers":[
        {
            "category":"Government",
            "subcategory":"Office",
            "type":"Public Place"
        }
    ],
    "sg:phone":"+1 210 212 7359",
    "sg:postcode":"78210",
    "sg:province":"TX",
    "sg:tags":[
        "village"
    ],
    "wof:name":"San Antonio Nutrition Sites",
    "wof:placetype":"venue"
},
  "geometry": {"coordinates":[-98.484351,29.413771],"type":"Point"}
}