{
  "type": "Feature",
  "properties": {
    "iso:country":"US",
    "sg:address":"602 Valentine Dr",
    "sg:city":"Longview",
    "sg:classifiers":[
        {
            "category":"Professional",
            "type":"Services"
        }
    ],
    "sg:phone":"+1 903 297 3541",
    "sg:postcode":"75604",
    "sg:province":"TX",
    "wof:name":"Brent Price",
    "wof:placetype":"venue"
},
  "geometry": {"coordinates":[-94.811562,32.48458],"type":"Point"}
}