{
  "type": "Feature",
  "properties": {
    "iso:country":"US",
    "sg:address":"2324 FM 1960 E",
    "sg:city":"Humble",
    "sg:classifiers":[
        {
            "category":"Recreation",
            "type":"Entertainment"
        }
    ],
    "sg:phone":"+1 281 446 2425",
    "sg:postcode":"77338",
    "sg:province":"TX",
    "sg:tags":[
        "range",
        "practice",
        "golf"
    ],
    "wof:name":"Browns Golf World Inc",
    "wof:placetype":"venue"
},
  "geometry": {"coordinates":[-95.390761,30.023449],"type":"Point"}
}