{
  "type": "Feature",
  "properties": {
    "iso:country":"US",
    "sg:address":"3766 Apollo Rd",
    "sg:city":"Corpus Christi",
    "sg:classifiers":[
        {
            "category":"Shopping",
            "type":"Retail Goods"
        }
    ],
    "sg:phone":"+1 361 853 4575",
    "sg:postcode":"78413",
    "sg:province":"TX",
    "sg:tags":[
        "equipment",
        "telephone",
        "supply"
    ],
    "wof:name":"Phoenix Tel Data",
    "wof:placetype":"venue"
},
  "geometry": {"coordinates":[-97.420768,27.696474],"type":"Point"}
}