{
  "type": "Feature",
  "properties": {
    "iso:country":"US",
    "sg:address":"1802 Henson St",
    "sg:city":"Abilene",
    "sg:classifiers":[
        {
            "category":"Mining & Drilling",
            "type":"Manufacturing & Wholesale Goods"
        }
    ],
    "sg:phone":"+1 325 673 0993",
    "sg:postcode":"79603",
    "sg:province":"TX",
    "sg:tags":[
        "oil",
        "well"
    ],
    "wof:name":"Ice Well Svc Inc",
    "wof:placetype":"venue"
},
  "geometry": {"coordinates":[-99.742116,32.50503],"type":"Point"}
}