{
  "type": "Feature",
  "properties": {
    "iso:country":"US",
    "sg:address":"10199 Slick Rock Trl",
    "sg:city":"Frisco",
    "sg:classifiers":[
        {
            "category":"Building & Trades",
            "subcategory":"Electrical",
            "type":"Services"
        }
    ],
    "sg:phone":"+1 972 712 6159",
    "sg:postcode":"75034",
    "sg:province":"TX",
    "sg:tags":[
        "electrical",
        "contractor"
    ],
    "wof:name":"Direct Home Systems",
    "wof:placetype":"venue"
},
  "geometry": {"coordinates":[-96.866815,33.161926],"type":"Point"}
}