{
  "type": "Feature",
  "properties": {
    "iso:country":"US",
    "sg:address":"5700 Miramar Ln",
    "sg:city":"Colleyville",
    "sg:classifiers":[
        {
            "category":"Banks & Credit Unions",
            "subcategory":"Financial Services",
            "type":"Services"
        }
    ],
    "sg:phone":"+1 817 540 4270",
    "sg:postcode":"76034",
    "sg:province":"TX",
    "sg:tags":[
        "investor"
    ],
    "wof:name":"Quaker Investment",
    "wof:placetype":"venue"
},
  "geometry": {"coordinates":[-97.13730200000001,32.890968],"type":"Point"}
}