{
  "type": "Feature",
  "properties": {
    "iso:country":"US",
    "sg:address":"1807 W Slaughter Ln",
    "sg:city":"Austin",
    "sg:classifiers":[
        {
            "category":"Retail",
            "subcategory":"Repair Shop",
            "type":"Services"
        }
    ],
    "sg:phone":"+1 512 282 5507",
    "sg:postcode":"78748",
    "sg:province":"TX",
    "wof:name":"Scientfic Instrumentation Svcs",
    "wof:placetype":"venue"
},
  "geometry": {"coordinates":[-97.822514,30.173632],"type":"Point"}
}