{
  "type": "Feature",
  "properties": {
    "iso:country":"US",
    "sg:address":"5802 Gardendale Dr",
    "sg:city":"Houston",
    "sg:classifiers":[
        {
            "category":"Building & Trades",
            "subcategory":"Equipment Rental",
            "type":"Services"
        }
    ],
    "sg:phone":"+1 713 682 5017",
    "sg:postcode":"77092",
    "sg:province":"TX",
    "sg:tags":[
        "hospital",
        "rent",
        "bed",
        "specialty"
    ],
    "wof:name":"Patient Care Systems Inc",
    "wof:placetype":"venue"
},
  "geometry": {"coordinates":[-95.480273,29.817126],"type":"Point"}
}