{
  "type": "Feature",
  "properties": {
    "iso:country":"US",
    "sg:address":"7309 Yamini Dr",
    "sg:city":"Dallas",
    "sg:classifiers":[
        {
            "category":"Recreation",
            "type":"Entertainment"
        }
    ],
    "sg:phone":"+1 214 890 7946",
    "sg:postcode":"75230",
    "sg:province":"TX",
    "sg:tags":[
        "instruction",
        "swimming"
    ],
    "wof:name":"Aquatots-Infant Aquatics",
    "wof:placetype":"venue"
},
  "geometry": {"coordinates":[-96.778407,32.902848],"type":"Point"}
}