{
  "type": "Feature",
  "properties": {
    "iso:country":"US",
    "sg:address":"1221 W Airport Fwy",
    "sg:city":"Irving",
    "sg:classifiers":[
        {
            "category":"Personal",
            "type":"Services"
        }
    ],
    "sg:phone":"+1 972 257 1866",
    "sg:postcode":"75062",
    "sg:province":"TX",
    "sg:tags":[
        "formal",
        "retail",
        "rental",
        "wear",
        "accessory"
    ],
    "wof:name":"A Formal Affair",
    "wof:placetype":"venue"
},
  "geometry": {"coordinates":[-96.96055800000001,32.837386],"type":"Point"}
}