{
  "type": "Feature",
  "properties": {
    "iso:country":"US",
    "sg:address":"301 W Expy 83",
    "sg:city":"Mcallen",
    "sg:classifiers":[
        {
            "category":"Health Services",
            "subcategory":"Doctor",
            "type":"Services"
        }
    ],
    "sg:phone":"+1 956 632 4599",
    "sg:postcode":"78503",
    "sg:province":"TX",
    "sg:tags":[
        "medical"
    ],
    "wof:name":"Perlas Marisa",
    "wof:placetype":"venue"
},
  "geometry": {"coordinates":[-98.226342,26.188201],"type":"Point"}
}