{
  "type": "Feature",
  "properties": {
    "iso:country":"US",
    "sg:address":"9009 Sautelle Ln",
    "sg:city":"Austin",
    "sg:classifiers":[
        {
            "category":"Real Estate",
            "subcategory":"Real Estate Services",
            "type":"Services"
        },
        {
            "category":"Real Estate",
            "subcategory":"Real Estate Agent",
            "type":"Services"
        }
    ],
    "sg:phone":"+1 512 282 8264",
    "sg:postcode":"78749",
    "sg:province":"TX",
    "sg:tags":[
        "buyer",
        "broker"
    ],
    "wof:name":"Differential X Real Estate",
    "wof:placetype":"venue"
},
  "geometry": {"coordinates":[-97.877838,30.208506],"type":"Point"}
}