{
  "type": "Feature",
  "properties": {
    "iso:country":"US",
    "sg:address":"404 Andrews Ave",
    "sg:city":"Dallas",
    "sg:classifiers":[
        {
            "category":"Wholesale",
            "subcategory":"Vending Machines",
            "type":"Manufacturing & Wholesale Goods"
        }
    ],
    "sg:phone":"+1 214 339 9758",
    "sg:postcode":"75211",
    "sg:province":"TX",
    "sg:tags":[
        "operator",
        "cashing",
        "check"
    ],
    "wof:name":"Jairo S Vending & Cashing Svc",
    "wof:placetype":"venue"
},
  "geometry": {"coordinates":[-96.88242700000001,32.740141],"type":"Point"}
}