{
  "type": "Feature",
  "properties": {
    "iso:country":"US",
    "sg:address":"645 S Rockdale St",
    "sg:city":"Lexington",
    "sg:classifiers":[
        {
            "category":"Retail",
            "subcategory":"Auto Repair",
            "type":"Services"
        }
    ],
    "sg:phone":"+1 979 773 2201",
    "sg:postcode":"78947",
    "sg:province":"TX",
    "sg:tags":[
        "repairing",
        "automobile"
    ],
    "wof:name":"Lexington Auto Repair",
    "wof:placetype":"venue"
},
  "geometry": {"coordinates":[-97.00366699999999,30.405988],"type":"Point"}
}