{
  "type": "Feature",
  "properties": {
    "iso:country":"US",
    "sg:address":"4220 Cobblers Ln",
    "sg:city":"Dallas",
    "sg:classifiers":[
        {
            "category":"Professional",
            "subcategory":"Management & Consulting",
            "type":"Services"
        }
    ],
    "sg:phone":"+1 972 248 8879",
    "sg:postcode":"75287",
    "sg:province":"TX",
    "sg:tags":[
        "consultant",
        "hospital"
    ],
    "wof:name":"National Health Care Review",
    "wof:placetype":"venue"
},
  "geometry": {"coordinates":[-96.836383,32.98975],"type":"Point"}
}