{
  "type": "Feature",
  "properties": {
    "iso:country":"US",
    "sg:address":"2707 Shelby Ave",
    "sg:city":"Dallas",
    "sg:classifiers":[
        {
            "category":"Personal",
            "subcategory":"Beauty Salon",
            "type":"Services"
        }
    ],
    "sg:phone":"+1 214 520 6399",
    "sg:postcode":"75219",
    "sg:province":"TX",
    "wof:name":"Shantalle Stressless Cuts",
    "wof:placetype":"venue"
},
  "geometry": {"coordinates":[-96.81193399999999,32.807773],"type":"Point"}
}