{
  "type": "Feature",
  "properties": {
    "iso:country":"US",
    "sg:address":"601 Golden Rd",
    "sg:city":"Tyler",
    "sg:classifiers":[
        {
            "category":"Health Services",
            "subcategory":"Nursing And Care Facility",
            "type":"Services"
        }
    ],
    "sg:phone":"+1 903 595 5641",
    "sg:postcode":"75701",
    "sg:province":"TX",
    "sg:tags":[
        "home",
        "rest"
    ],
    "wof:name":"William Booth Garden Apts",
    "wof:placetype":"venue"
},
  "geometry": {"coordinates":[-95.27273599999999,32.342779],"type":"Point"}
}