{
  "type": "Feature",
  "properties": {
    "iso:country":"US",
    "sg:address":"754 N Carroll Ave",
    "sg:city":"Southlake",
    "sg:classifiers":[
        {
            "category":"Health Services",
            "subcategory":"Doctor",
            "type":"Services"
        }
    ],
    "sg:phone":"+1 817 488 1150",
    "sg:postcode":"76092",
    "sg:province":"TX",
    "wof:name":"Czarnecki S Thomas DMD Ms",
    "wof:placetype":"venue"
},
  "geometry": {"coordinates":[-97.13416599999999,32.947847],"type":"Point"}
}