{
  "type": "Feature",
  "properties": {
    "iso:country":"US",
    "sg:address":"1210 S 12th St",
    "sg:city":"Harlingen",
    "sg:classifiers":[
        {
            "category":"Building & Trades",
            "subcategory":"Cleaning & Sanitation",
            "type":"Services"
        }
    ],
    "sg:phone":"+1 956 412 2501",
    "sg:postcode":"78550",
    "sg:province":"TX",
    "sg:tags":[
        "maintenance"
    ],
    "wof:name":"ABM Jntrial Srvcs-Northern Cal",
    "wof:placetype":"venue"
},
  "geometry": {"coordinates":[-97.68221,26.181445],"type":"Point"}
}