{
  "type": "Feature",
  "properties": {
    "iso:country":"US",
    "sg:address":"1327 3rd St",
    "sg:city":"Floresville",
    "sg:classifiers":[
        {
            "category":"Restaurant",
            "type":"Food & Drink"
        }
    ],
    "sg:phone":"+1 830 393 9896",
    "sg:postcode":"78114",
    "sg:province":"TX",
    "sg:tags":[
        "eating"
    ],
    "wof:name":"Tacqueria Guadalajara",
    "wof:placetype":"venue"
},
  "geometry": {"coordinates":[-98.15897099999999,29.134164],"type":"Point"}
}