{
  "type": "Feature",
  "properties": {
    "iso:country":"US",
    "sg:address":"1400 N Grant St",
    "sg:city":"Amarillo",
    "sg:classifiers":[
        {
            "category":"Education",
            "subcategory":"School",
            "type":"Public Place"
        }
    ],
    "sg:phone":"+1 806 381 7100",
    "sg:postcode":"79107",
    "sg:province":"TX",
    "wof:name":"Palo Duro High School",
    "wof:placetype":"venue"
},
  "geometry": {"coordinates":[-101.825115,35.229288],"type":"Point"}
}