{
  "type": "Feature",
  "properties": {
    "iso:country":"US",
    "sg:address":"480 S Highway 123 Byp",
    "sg:city":"Seguin",
    "sg:classifiers":[
        {
            "category":"Restaurant",
            "type":"Food & Drink"
        }
    ],
    "sg:menulink":"http://www.allmenus.com/tx/seguin/139638-quiznos-sub/menu/",
    "sg:phone":"+1 830 379 8278",
    "sg:postcode":"78155",
    "sg:province":"TX",
    "sg:tags":[
        "wrap",
        "american",
        "sandwich"
    ],
    "wof:name":"Quiznos Sub",
    "wof:placetype":"venue"
},
  "geometry": {"coordinates":[-97.94108300000001,29.566879],"type":"Point"}
}