{
  "type": "Feature",
  "properties": {
    "iso:country":"US",
    "sg:address":"7425 Davis Blvd",
    "sg:city":"Fort Worth",
    "sg:classifiers":[
        {
            "category":"Retail",
            "subcategory":"Auto Repair",
            "type":"Services"
        }
    ],
    "sg:phone":"+1 817 656 9100",
    "sg:postcode":"76180",
    "sg:province":"TX",
    "sg:tags":[
        "automobile",
        "lubrication"
    ],
    "wof:name":"KWIK Kar Lube & Tune",
    "wof:placetype":"venue"
},
  "geometry": {"coordinates":[-97.203558,32.883046],"type":"Point"}
}