{
  "type": "Feature",
  "properties": {
    "iso:country":"US",
    "sg:address":"998 Bellaire Blvd",
    "sg:city":"Lewisville",
    "sg:classifiers":[
        {
            "category":"Real Estate",
            "subcategory":"Real Estate Services",
            "type":"Services"
        },
        {
            "category":"Real Estate",
            "subcategory":"Real Estate Operator",
            "type":"Services"
        }
    ],
    "sg:phone":"+1 972 436 9233",
    "sg:postcode":"75067",
    "sg:province":"TX",
    "sg:tags":[
        "vacancy",
        "apartment",
        "rental",
        "finder",
        "listing"
    ],
    "sg:website":"http://www.udr.com",
    "wof:name":"Catalina At Bellaire",
    "wof:placetype":"venue"
},
  "geometry": {"coordinates":[-97.014313,33.027519],"type":"Point"}
}