{
  "type": "Feature",
  "properties": {
    "iso:country":"US",
    "sg:address":"16 Uvalde Rd",
    "sg:city":"Houston",
    "sg:classifiers":[
        {
            "category":"Government",
            "subcategory":"Office",
            "type":"Public Place"
        }
    ],
    "sg:phone":"+1 713 453 8528",
    "sg:postcode":"77015",
    "sg:province":"TX",
    "sg:tags":[
        "station",
        "recruiting"
    ],
    "wof:name":"Northshore Recruiting Station",
    "wof:placetype":"venue"
},
  "geometry": {"coordinates":[-95.182329,29.806079],"type":"Point"}
}