{
  "type": "Feature",
  "properties": {
    "iso:country":"US",
    "sg:address":"4031 N Star Dr",
    "sg:city":"Irving",
    "sg:classifiers":[
        {
            "category":"Real Estate",
            "subcategory":"Real Estate Operator",
            "type":"Services"
        }
    ],
    "sg:phone":"+1 972 659 1641",
    "sg:postcode":"75038",
    "sg:province":"TX",
    "sg:tags":[
        "building",
        "apartment"
    ],
    "wof:name":"Sable Pointe",
    "wof:placetype":"venue"
},
  "geometry": {"coordinates":[-97.007867,32.864175],"type":"Point"}
}