{
  "type": "Feature",
  "properties": {
    "iso:country":"US",
    "sg:address":"1808 Adina St",
    "sg:city":"Austin",
    "sg:classifiers":[
        {
            "category":"Freight",
            "type":"Transportation"
        }
    ],
    "sg:phone":"+1 512 873 7599",
    "sg:postcode":"78721",
    "sg:province":"TX",
    "sg:tags":[
        "operator",
        "local",
        "trucking"
    ],
    "wof:name":"J C Hall Trucking",
    "wof:placetype":"venue"
},
  "geometry": {"coordinates":[-97.679951,30.282457],"type":"Point"}
}