{
  "type": "Feature",
  "properties": {
    "iso:country":"US",
    "sg:address":"2555 Bay Area Blvd",
    "sg:city":"Houston",
    "sg:classifiers":[
        {
            "category":"Restaurant",
            "type":"Food & Drink"
        }
    ],
    "sg:menulink":"http://www.allmenus.com/tx/houston/16377-tommys/menu/",
    "sg:phone":"+1 281 480 2221",
    "sg:postcode":"77058",
    "sg:province":"TX",
    "sg:tags":[
        "american"
    ],
    "wof:name":"Tommy's",
    "wof:placetype":"venue"
},
  "geometry": {"coordinates":[-95.10759,29.576087],"type":"Point"}
}