{
  "type": "Feature",
  "properties": {
    "iso:country":"US",
    "sg:address":"10822 Peach Cir",
    "sg:city":"Forney",
    "sg:classifiers":[
        {
            "category":"Retail",
            "subcategory":"Repair Shop",
            "type":"Services"
        }
    ],
    "sg:phone":"+1 972 564 2139",
    "sg:postcode":"75126",
    "sg:province":"TX",
    "wof:name":"Maynor Equipment Company",
    "wof:placetype":"venue"
},
  "geometry": {"coordinates":[-96.487196,32.716874],"type":"Point"}
}