{
  "type": "Feature",
  "properties": {
    "iso:country":"US",
    "sg:address":"1450 FM 1978",
    "sg:city":"San Marcos",
    "sg:classifiers":[
        {
            "category":"Retail",
            "subcategory":"Repair Shop",
            "type":"Services"
        }
    ],
    "sg:phone":"+1 512 353 7015",
    "sg:postcode":"78666",
    "sg:province":"TX",
    "sg:tags":[
        "repairing",
        "lawn",
        "mower"
    ],
    "wof:name":"Bob KAT Small Engine Repair",
    "wof:placetype":"venue"
},
  "geometry": {"coordinates":[-97.898432,29.820247],"type":"Point"}
}