{
  "type": "Feature",
  "properties": {
    "iso:country":"US",
    "sg:address":"6497 Dawnridge Dr",
    "sg:city":"Houston",
    "sg:classifiers":[
        {
            "category":"Building & Trades",
            "subcategory":"Construction",
            "type":"Services"
        }
    ],
    "sg:phone":"+1 713 721 4079",
    "sg:postcode":"77035",
    "sg:province":"TX",
    "sg:tags":[
        "house",
        "nonresidential"
    ],
    "wof:name":"Re-Visions",
    "wof:placetype":"venue"
},
  "geometry": {"coordinates":[-95.504434,29.648984],"type":"Point"}
}