{
  "type": "Feature",
  "properties": {
    "iso:country":"US",
    "sg:address":"3626 50th St",
    "sg:city":"Lubbock",
    "sg:classifiers":[
        {
            "category":"Retail",
            "subcategory":"Laundry & Dry Cleaning",
            "type":"Services"
        }
    ],
    "sg:phone":"+1 806 791 4717",
    "sg:postcode":"79413",
    "sg:province":"TX",
    "sg:tags":[
        "cleaners"
    ],
    "wof:name":"Gristy's Dry Cleaning & Lndry",
    "wof:placetype":"venue"
},
  "geometry": {"coordinates":[-101.89281200000001,33.54876],"type":"Point"}
}