{
  "type": "Feature",
  "properties": {
    "iso:country":"US",
    "sg:address":"8551 Meadowbrook Dr",
    "sg:city":"Fort Worth",
    "sg:classifiers":[
        {
            "category":"Restaurant",
            "type":"Food & Drink"
        }
    ],
    "sg:phone":"+1 817 801 3321",
    "sg:postcode":"76120",
    "sg:province":"TX",
    "wof:name":"Chicken Express",
    "wof:placetype":"venue"
},
  "geometry": {"coordinates":[-97.166049,32.751982],"type":"Point"}
}