{
  "type": "Feature",
  "properties": {
    "iso:country":"US",
    "sg:address":"5517 76th St",
    "sg:city":"Lubbock",
    "sg:classifiers":[
        {
            "category":"Professional",
            "type":"Services"
        }
    ],
    "sg:phone":"+1 806 794 2971",
    "sg:postcode":"79424",
    "sg:province":"TX",
    "wof:name":"ML Steele Inc",
    "wof:placetype":"venue"
},
  "geometry": {"coordinates":[-101.93536,33.524784],"type":"Point"}
}