{
  "type": "Feature",
  "properties": {
    "iso:country":"US",
    "sg:address":"19922 Teller Blvd",
    "sg:city":"Spring",
    "sg:classifiers":[
        {
            "category":"Education",
            "subcategory":"School",
            "type":"Public Place"
        }
    ],
    "sg:phone":"+1 281 350 1185",
    "sg:postcode":"77388",
    "sg:province":"TX",
    "wof:name":"Houston Academy of Vocal A",
    "wof:placetype":"venue"
},
  "geometry": {"coordinates":[-95.446985,30.053649],"type":"Point"}
}