{
  "type": "Feature",
  "properties": {
    "iso:country":"US",
    "sg:address":"9210 Cameron Rd",
    "sg:city":"Austin",
    "sg:classifiers":[
        {
            "category":"Wholesale",
            "subcategory":"Machinery & Supplies",
            "type":"Manufacturing & Wholesale Goods"
        }
    ],
    "sg:phone":"+1 512 339 6007",
    "sg:postcode":"78754",
    "sg:province":"TX",
    "sg:tags":[
        "equipment",
        "establishment",
        "system",
        "vacuum"
    ],
    "wof:name":"Shimadyu Precision Instruments",
    "wof:placetype":"venue"
},
  "geometry": {"coordinates":[-97.67707900000001,30.347431],"type":"Point"}
}