{
  "type": "Feature",
  "properties": {
    "iso:country":"US",
    "sg:address":"5016 Briar Patch Ln",
    "sg:city":"Burleson",
    "sg:classifiers":[
        {
            "category":"Bakery",
            "type":"Food & Drink"
        }
    ],
    "sg:phone":"+1 817 295 9880",
    "sg:postcode":"76028",
    "sg:province":"TX",
    "wof:name":"Tammi's Tarts",
    "wof:placetype":"venue"
},
  "geometry": {"coordinates":[-97.234402,32.493877],"type":"Point"}
}