{
  "type": "Feature",
  "properties": {
    "iso:country":"US",
    "sg:address":"7007 Gulf Fwy",
    "sg:city":"Houston",
    "sg:classifiers":[
        {
            "category":"Professional",
            "subcategory":"Lawyer & Legal Services",
            "type":"Services"
        }
    ],
    "sg:phone":"+1 713 649 0219",
    "sg:postcode":"77087",
    "sg:province":"TX",
    "sg:tags":[
        "attorney"
    ],
    "wof:name":"Crivello Carlson Mentkowski S C",
    "wof:placetype":"venue"
},
  "geometry": {"coordinates":[-95.294659,29.70211],"type":"Point"}
}