{
  "type": "Feature",
  "properties": {
    "iso:country":"US",
    "sg:address":"6124 W Highway 290",
    "sg:city":"Austin",
    "sg:classifiers":[
        {
            "category":"Real Estate",
            "subcategory":"Real Estate Services",
            "type":"Services"
        }
    ],
    "sg:phone":"+1 512 899 9090",
    "sg:postcode":"78735",
    "sg:province":"TX",
    "sg:tags":[
        "management",
        "property"
    ],
    "wof:name":"Guardian 2000",
    "wof:placetype":"venue"
},
  "geometry": {"coordinates":[-97.855144,30.235718],"type":"Point"}
}