{
  "type": "Feature",
  "properties": {
    "iso:country":"US",
    "sg:address":"1181 Lytle Way Suite D",
    "sg:city":"Abilene",
    "sg:classifiers":[
        {
            "category":"Banks & Credit Unions",
            "subcategory":"Investment Brokerage",
            "type":"Services"
        },
        {
            "category":"Banks & Credit Unions",
            "subcategory":"Bank",
            "type":"Services"
        },
        {
            "category":"Banks & Credit Unions",
            "subcategory":"Financial Services",
            "type":"Services"
        }
    ],
    "sg:phone":"+1 325 455 0742",
    "sg:postcode":"79602",
    "sg:province":"TX",
    "sg:tags":[
        "advisory",
        "mutual",
        "retirement",
        "annuity",
        "broker",
        "fund",
        "planning",
        "plan",
        "consultant",
        "security",
        "bond",
        "insurance",
        "stock"
    ],
    "sg:website":"http://national.citysearch.com/profile/external/604311662/abilene_tx/edward_jones_shane_jennings.html?publisher=yellowpages&reference_id=1&placement=ypwebsitemip",
    "wof:name":"Edward Jones - SHANE JENNINGS",
    "wof:placetype":"venue"
},
  "geometry": {"coordinates":[-99.70585800000001,32.435155],"type":"Point"}
}