{
  "type": "Feature",
  "properties": {
    "iso:country":"US",
    "sg:address":"8103 Leader St",
    "sg:city":"Houston",
    "sg:classifiers":[
        {
            "category":"Professional",
            "subcategory":"Computer Services",
            "type":"Services"
        }
    ],
    "sg:phone":"+1 713 776 8039",
    "sg:postcode":"77036",
    "sg:province":"TX",
    "sg:tags":[
        "prepackaged",
        "software"
    ],
    "wof:name":"Friedrich Software Resour",
    "wof:placetype":"venue"
},
  "geometry": {"coordinates":[-95.53107300000001,29.703976],"type":"Point"}
}