{
  "type": "Feature",
  "properties": {
    "iso:country":"US",
    "sg:address":"6410 Sunset Trl",
    "sg:city":"Flower Mound",
    "sg:classifiers":[
        {
            "category":"Building & Trades",
            "subcategory":"Construction",
            "type":"Services"
        }
    ],
    "sg:phone":"+1 972 724 2766",
    "sg:postcode":"75022",
    "sg:province":"TX",
    "sg:tags":[
        "detached",
        "contractor",
        "general",
        "family",
        "custom"
    ],
    "wof:name":"Cortland Homes Inc",
    "wof:placetype":"venue"
},
  "geometry": {"coordinates":[-97.129656,33.028778],"type":"Point"}
}