{
  "type": "Feature",
  "properties": {
    "iso:country":"US",
    "sg:address":"112 Industrial Dr",
    "sg:city":"Forney",
    "sg:classifiers":[
        {
            "category":"Home & Garden",
            "subcategory":"Furniture",
            "type":"Retail Goods"
        }
    ],
    "sg:phone":"+1 972 564 2000",
    "sg:postcode":"75126",
    "sg:province":"TX",
    "sg:tags":[
        "top",
        "counter"
    ],
    "wof:name":"Star Counter Tops",
    "wof:placetype":"venue"
},
  "geometry": {"coordinates":[-96.454686,32.750967],"type":"Point"}
}