{
  "type": "Feature",
  "properties": {
    "iso:country":"US",
    "sg:address":"224 Richmond Ranch Rd",
    "sg:city":"Texarkana",
    "sg:classifiers":[
        {
            "category":"Shopping",
            "subcategory":"Optical Goods",
            "type":"Retail Goods"
        },
        {
            "category":"Health Services",
            "subcategory":"Optometrist",
            "type":"Services"
        },
        {
            "category":"Communications",
            "subcategory":"Television Station",
            "type":"Services"
        }
    ],
    "sg:phone":"+1 903 831 4022",
    "sg:postcode":"75503",
    "sg:province":"TX",
    "sg:tags":[
        "binoculars",
        "goods-wholesale",
        "telescope",
        "manufacturer"
    ],
    "sg:website":"http://www.eyedealeyecare.com",
    "wof:name":"Vision 4 Less 33",
    "wof:placetype":"venue"
},
  "geometry": {"coordinates":[-94.091936,33.456578],"type":"Point"}
}