{
  "type": "Feature",
  "properties": {
    "iso:country":"US",
    "sg:address":"13920 Josey Ln Ste 103",
    "sg:city":"Dallas",
    "sg:classifiers":[
        {
            "category":"Shopping",
            "subcategory":"Party Supplies",
            "type":"Retail Goods"
        }
    ],
    "sg:phone":"+1 972 620 9876",
    "sg:postcode":"75234",
    "sg:province":"TX",
    "wof:name":"Party's 2 Go",
    "wof:placetype":"venue"
},
  "geometry": {"coordinates":[-96.888397,32.933998],"type":"Point"}
}