{
  "type": "Feature",
  "properties": {
    "iso:country":"US",
    "sg:address":"5932 W Northwest Hwy",
    "sg:city":"Dallas",
    "sg:classifiers":[
        {
            "category":"Cinema",
            "subcategory":"Movie Theater",
            "type":"Entertainment"
        }
    ],
    "sg:phone":"+1 214 373 0909",
    "sg:postcode":"75225",
    "sg:province":"TX",
    "sg:website":"www.tfusa.com",
    "wof:name":"Ticket Finders USA Inc",
    "wof:placetype":"venue"
},
  "geometry": {"coordinates":[-96.807098,32.865398],"type":"Point"}
}