{
  "type": "Feature",
  "properties": {
    "iso:country":"US",
    "sg:address":"3112 Becky Ct",
    "sg:city":"Garland",
    "sg:classifiers":[
        {
            "category":"Building & Trades",
            "subcategory":"Construction",
            "type":"Services"
        }
    ],
    "sg:phone":"+1 972 495 7519",
    "sg:postcode":"75044",
    "sg:province":"TX",
    "sg:tags":[
        "residential"
    ],
    "wof:name":"McClure Construction",
    "wof:placetype":"venue"
},
  "geometry": {"coordinates":[-96.676377,32.980091],"type":"Point"}
}