{
  "type": "Feature",
  "properties": {
    "iso:country":"US",
    "sg:address":"1616 W Main St",
    "sg:city":"Houston",
    "sg:classifiers":[
        {
            "category":"Retail",
            "subcategory":"Portrait Studio",
            "type":"Services"
        }
    ],
    "sg:phone":"+1 713 661 2131",
    "sg:postcode":"77006",
    "sg:province":"TX",
    "sg:tags":[
        "photo"
    ],
    "wof:name":"Trish Strangmeyer Photography",
    "wof:placetype":"venue"
},
  "geometry": {"coordinates":[-95.401573,29.736136],"type":"Point"}
}