{
  "type": "Feature",
  "properties": {
    "iso:country":"US",
    "sg:address":"4477 Flamingo Ln",
    "sg:city":"Beaumont",
    "sg:classifiers":[
        {
            "category":"Personal",
            "type":"Services"
        }
    ],
    "sg:phone":"+1 409 842 9797",
    "sg:postcode":"77705",
    "sg:province":"TX",
    "wof:name":"Special Occasions",
    "wof:placetype":"venue"
},
  "geometry": {"coordinates":[-94.09952,30.043871],"type":"Point"}
}