{
  "type": "Feature",
  "properties": {
    "iso:country":"US",
    "sg:address":"16536 Co Rd 221",
    "sg:city":"Forney",
    "sg:classifiers":[
        {
            "category":"Professional",
            "subcategory":"Computer Services",
            "type":"Services"
        }
    ],
    "sg:phone":"+1 972 564 1645",
    "sg:postcode":"75126",
    "sg:province":"TX",
    "sg:tags":[
        "credit",
        "card"
    ],
    "wof:name":"Cocard Systems",
    "wof:placetype":"venue"
},
  "geometry": {"coordinates":[-96.417239,32.796006],"type":"Point"}
}