{
  "type": "Feature",
  "properties": {
    "iso:country":"US",
    "sg:address":"1 Heritage Trl",
    "sg:city":"Magnolia",
    "sg:classifiers":[
        {
            "category":"Farming",
            "subcategory":"Farm",
            "type":"Manufacturing & Wholesale Goods"
        }
    ],
    "sg:phone":"+1 281 356 5283",
    "sg:postcode":"77354",
    "sg:province":"TX",
    "wof:name":"Shadyside Farms Inc",
    "wof:placetype":"venue"
},
  "geometry": {"coordinates":[-95.67739899999999,30.227579],"type":"Point"}
}