{
  "type": "Feature",
  "properties": {
    "iso:country":"US",
    "sg:address":"15400 Knoll Trail Dr",
    "sg:city":"Dallas",
    "sg:classifiers":[
        {
            "category":"Real Estate",
            "subcategory":"Real Estate Agent",
            "type":"Services"
        }
    ],
    "sg:phone":"+1 972 755 6464",
    "sg:postcode":"75248",
    "sg:province":"TX",
    "sg:website":"www.self-store.net",
    "wof:name":"Darden Interests Inc",
    "wof:placetype":"venue"
},
  "geometry": {"coordinates":[-96.818856,32.962942],"type":"Point"}
}