{
  "type": "Feature",
  "properties": {
    "iso:country":"US",
    "sg:address":"801 W Kearney St",
    "sg:city":"Mesquite",
    "sg:classifiers":[
        {
            "category":"Insurance",
            "subcategory":"Insurance Agent",
            "type":"Services"
        }
    ],
    "sg:phone":"+1 972 285 0121",
    "sg:postcode":"75149",
    "sg:province":"TX",
    "wof:name":"Allstate",
    "wof:placetype":"venue"
},
  "geometry": {"coordinates":[-96.61107199999999,32.770767],"type":"Point"}
}