{
  "type": "Feature",
  "properties": {
    "iso:country":"US",
    "sg:address":"255 S Clover Dr",
    "sg:city":"Bridge City",
    "sg:classifiers":[
        {
            "category":"Building & Trades",
            "subcategory":"Landscaping Services",
            "type":"Services"
        }
    ],
    "sg:phone":"+1 409 735 9610",
    "sg:postcode":"77611",
    "sg:province":"TX",
    "wof:name":"Lawnmower Man Lawn Svc",
    "wof:placetype":"venue"
},
  "geometry": {"coordinates":[-93.83174699999999,30.030384],"type":"Point"}
}