{
  "type": "Feature",
  "properties": {
    "iso:country":"US",
    "sg:address":"9 Pin Oak Ct",
    "sg:city":"Roanoke",
    "sg:classifiers":[
        {
            "category":"Health Services",
            "subcategory":"Clinic",
            "type":"Services"
        }
    ],
    "sg:phone":"+1 817 430 2993",
    "sg:postcode":"76262",
    "sg:province":"TX",
    "sg:tags":[
        "welfare"
    ],
    "wof:name":"Home Medical Of American",
    "wof:placetype":"venue"
},
  "geometry": {"coordinates":[-97.167596,32.99101],"type":"Point"}
}