{
  "type": "Feature",
  "properties": {
    "iso:country":"US",
    "sg:address":"504 Howard Dr",
    "sg:city":"Lake Dallas",
    "sg:classifiers":[
        {
            "category":"Building & Trades",
            "subcategory":"Construction",
            "type":"Services"
        }
    ],
    "sg:phone":"+1 940 497 5848",
    "sg:postcode":"75065",
    "sg:province":"TX",
    "sg:tags":[
        "roofing",
        "contractor"
    ],
    "wof:name":"Tyree Roofing",
    "wof:placetype":"venue"
},
  "geometry": {"coordinates":[-97.02499,33.1291],"type":"Point"}
}