{
  "type": "Feature",
  "properties": {
    "iso:country":"US",
    "sg:address":"9333 San Pedro Dr",
    "sg:city":"El Paso",
    "sg:classifiers":[
        {
            "category":"Retail",
            "subcategory":"Repair Shop",
            "type":"Services"
        }
    ],
    "sg:phone":"+1 915 859 7556",
    "sg:postcode":"79907",
    "sg:province":"TX",
    "sg:tags":[
        "welding"
    ],
    "wof:name":"H B Welding & Fabricating",
    "wof:placetype":"venue"
},
  "geometry": {"coordinates":[-106.320885,31.68647],"type":"Point"}
}