{
  "type": "Feature",
  "properties": {
    "iso:country":"US",
    "sg:address":"5846 New Territory Blvd",
    "sg:city":"Sugar Land",
    "sg:classifiers":[
        {
            "category":"Organizations",
            "subcategory":"Political Organization",
            "type":"Services"
        }
    ],
    "sg:phone":"+1 281 491 5737",
    "sg:postcode":"77479",
    "sg:province":"TX",
    "wof:name":"Republican Party of Fort Bend",
    "wof:placetype":"venue"
},
  "geometry": {"coordinates":[-95.66200000000001,29.590056],"type":"Point"}
}