{
  "type": "Feature",
  "properties": {
    "iso:country":"US",
    "sg:address":"473 Upper Sisterdale Rd Fm",
    "sg:city":"Comfort",
    "sg:classifiers":[
        {
            "category":"Arts & Performance",
            "subcategory":"Art Gallery",
            "type":"Entertainment"
        }
    ],
    "sg:phone":"+1 830 995 3094",
    "sg:postcode":"78013",
    "sg:province":"TX",
    "sg:tags":[
        "fine",
        "artist"
    ],
    "wof:name":"Rex Foster Artist",
    "wof:placetype":"venue"
},
  "geometry": {"coordinates":[-98.75335,30.01718],"type":"Point"}
}