{
  "type": "Feature",
  "properties": {
    "iso:country":"US",
    "sg:address":"5934 Broadway St",
    "sg:city":"Galveston",
    "sg:classifiers":[
        {
            "category":"Health Services",
            "subcategory":"Doctor",
            "type":"Services"
        }
    ],
    "sg:phone":"+1 409 740 7744",
    "sg:postcode":"77551",
    "sg:province":"TX",
    "sg:tags":[
        "dentist"
    ],
    "wof:name":"Affordable Dental",
    "wof:placetype":"venue"
},
  "geometry": {"coordinates":[-94.833551,29.289287],"type":"Point"}
}