{
  "type": "Feature",
  "properties": {
    "iso:country":"US",
    "sg:address":"1221 UNIVERSITY AVE",
    "sg:city":"Lubbock",
    "sg:classifiers":[
        {
            "category":"Restaurant",
            "type":"Food & Drink"
        }
    ],
    "sg:menulink":"http://www.allmenus.com/tx/lubbock/283994-little-panda/menu/",
    "sg:phone":"+1 806 762 6548",
    "sg:postcode":"79401",
    "sg:province":"TX",
    "sg:tags":[
        "asian",
        "chinese"
    ],
    "wof:name":"Little Panda",
    "wof:placetype":"venue"
},
  "geometry": {"coordinates":[-101.870434,33.584188],"type":"Point"}
}