{
  "type": "Feature",
  "properties": {
    "iso:country":"US",
    "sg:address":"12269 Maggie Ln",
    "sg:city":"Willis",
    "sg:classifiers":[
        {
            "category":"Farming",
            "subcategory":"Livestock Farm",
            "type":"Manufacturing & Wholesale Goods"
        }
    ],
    "sg:phone":"+1 936 890 8970",
    "sg:postcode":"77318",
    "sg:province":"TX",
    "sg:tags":[
        "beef",
        "feedlot",
        "cattle"
    ],
    "wof:name":"Joe Worthy Ranches",
    "wof:placetype":"venue"
},
  "geometry": {"coordinates":[-95.55001799999999,30.411771],"type":"Point"}
}