{
  "type": "Feature",
  "properties": {
    "iso:country":"US",
    "sg:address":"1717 Saint James Pl",
    "sg:city":"Houston",
    "sg:classifiers":[
        {
            "category":"Professional",
            "subcategory":"Computer Services",
            "type":"Services"
        },
        {
            "category":"Professional",
            "subcategory":"Employment Agencies",
            "type":"Services"
        }
    ],
    "sg:phone":"+1 713 621 9220",
    "sg:postcode":"77056",
    "sg:province":"TX",
    "sg:tags":[
        "consultant",
        "designer",
        "programming"
    ],
    "sg:website":"www.ergos.com",
    "wof:name":"Ergos Technology Partners Inc",
    "wof:placetype":"venue"
},
  "geometry": {"coordinates":[-95.473045,29.747599],"type":"Point"}
}