{
  "type": "Feature",
  "properties": {
    "iso:country":"US",
    "sg:address":"4325 E Interstate 20 Svc Rd",
    "sg:city":"Willow Park",
    "sg:classifiers":[
        {
            "category":"Autos & Motor Vehicles",
            "subcategory":"Automobile Sales",
            "type":"Retail Goods"
        }
    ],
    "sg:phone":"+1 817 613 0007",
    "sg:postcode":"76087",
    "sg:province":"TX",
    "sg:tags":[
        "car",
        "dealer"
    ],
    "wof:name":"Wild Bill",
    "wof:placetype":"venue"
},
  "geometry": {"coordinates":[-97.6234,32.73158],"type":"Point"}
}