{
  "type": "Feature",
  "properties": {
    "iso:country":"US",
    "sg:address":"4211 Northaven Rd",
    "sg:city":"Dallas",
    "sg:classifiers":[
        {
            "category":"Government",
            "subcategory":"Fire Station",
            "type":"Public Place"
        }
    ],
    "sg:phone":"+1 214 670 4510",
    "sg:postcode":"75229",
    "sg:province":"TX",
    "sg:tags":[
        "protection"
    ],
    "wof:name":"Fire Station 2",
    "wof:placetype":"venue"
},
  "geometry": {"coordinates":[-96.83456700000001,32.902301],"type":"Point"}
}