{
  "type": "Feature",
  "properties": {
    "iso:country":"US",
    "sg:address":"12025 Shiloh Rd",
    "sg:city":"Dallas",
    "sg:classifiers":[
        {
            "category":"Government",
            "subcategory":"Court House",
            "type":"Public Place"
        }
    ],
    "sg:phone":"+1 214 320 3797",
    "sg:postcode":"75228",
    "sg:province":"TX",
    "sg:tags":[
        "enforcement",
        "child"
    ],
    "wof:name":"Child Support Enforcement",
    "wof:placetype":"venue"
},
  "geometry": {"coordinates":[-96.66591699999999,32.859785],"type":"Point"}
}