{
  "type": "Feature",
  "properties": {
    "iso:country":"US",
    "sg:address":"1609 W Magnolia Ave",
    "sg:city":"San Antonio",
    "sg:classifiers":[
        {
            "category":"Professional",
            "subcategory":"Business Services",
            "type":"Services"
        }
    ],
    "sg:phone":"+1 210 735 5724",
    "sg:postcode":"78201",
    "sg:province":"TX",
    "wof:name":"Alamo Broadband Solutions",
    "wof:placetype":"venue"
},
  "geometry": {"coordinates":[-98.523433,29.455995],"type":"Point"}
}