{
  "type": "Feature",
  "properties": {
    "iso:country":"US",
    "sg:address":"2725 W Pioneer Dr",
    "sg:city":"Irving",
    "sg:classifiers":[
        {
            "category":"Professional",
            "type":"Services"
        }
    ],
    "sg:phone":"+1 972 313 3490",
    "sg:postcode":"75061",
    "sg:province":"TX",
    "wof:name":"Harati Inc",
    "wof:placetype":"venue"
},
  "geometry": {"coordinates":[-96.982198,32.826446],"type":"Point"}
}