{
  "type": "Feature",
  "properties": {
    "iso:country":"US",
    "sg:address":"146 W Garza St",
    "sg:city":"Slaton",
    "sg:classifiers":[
        {
            "category":"Wholesale",
            "subcategory":"Durable Goods & Equipment",
            "type":"Manufacturing & Wholesale Goods"
        }
    ],
    "sg:phone":"+1 806 828 6636",
    "sg:postcode":"79364",
    "sg:province":"TX",
    "sg:tags":[
        "representative",
        "manufacturer"
    ],
    "wof:name":"Electra Sales Of West Texas",
    "wof:placetype":"venue"
},
  "geometry": {"coordinates":[-101.64336,33.437971],"type":"Point"}
}