{
  "type": "Feature",
  "properties": {
    "iso:country":"US",
    "sg:address":"7209 Glendora Ave",
    "sg:city":"Dallas",
    "sg:classifiers":[
        {
            "category":"Real Estate",
            "subcategory":"Real Estate Agent",
            "type":"Services"
        }
    ],
    "sg:phone":"+1 214 265 7227",
    "sg:postcode":"75230",
    "sg:province":"TX",
    "wof:name":"UAH Property Management",
    "wof:placetype":"venue"
},
  "geometry": {"coordinates":[-96.780402,32.885415],"type":"Point"}
}