{
  "type": "Feature",
  "properties": {
    "iso:country":"US",
    "sg:address":"3101 N Lee Trevino Dr",
    "sg:city":"El Paso",
    "sg:classifiers":[
        {
            "category":"Building & Trades",
            "subcategory":"Equipment Rental",
            "type":"Services"
        }
    ],
    "sg:phone":"+1 915 591 5858",
    "sg:postcode":"79936",
    "sg:province":"TX",
    "sg:tags":[
        "leasing",
        "furniture"
    ],
    "wof:name":"Aarons Sales & Lease Ownership",
    "wof:placetype":"venue"
},
  "geometry": {"coordinates":[-106.32326399999999,31.785192],"type":"Point"}
}