{
  "type": "Feature",
  "properties": {
    "iso:country":"US",
    "sg:address":"8527 Co Rd 271",
    "sg:city":"Terrell",
    "sg:classifiers":[
        {
            "category":"Wholesale",
            "subcategory":"Construction Materials",
            "type":"Manufacturing & Wholesale Goods"
        }
    ],
    "sg:phone":"+1 972 524 3618",
    "sg:postcode":"75160",
    "sg:province":"TX",
    "wof:name":"Danco Sand Co",
    "wof:placetype":"venue"
},
  "geometry": {"coordinates":[-96.354907,32.681761],"type":"Point"}
}