{
  "type": "Feature",
  "properties": {
    "iso:country":"US",
    "sg:address":"3913 Dartmouth St",
    "sg:city":"Garland",
    "sg:classifiers":[
        {
            "category":"Banks & Credit Unions",
            "subcategory":"Financial Services",
            "type":"Services"
        }
    ],
    "sg:phone":"+1 972 840 1949",
    "sg:postcode":"75043",
    "sg:province":"TX",
    "sg:tags":[
        "investor"
    ],
    "wof:name":"Millionaires Caucus Inc",
    "wof:placetype":"venue"
},
  "geometry": {"coordinates":[-96.62615099999999,32.870105],"type":"Point"}
}