{
  "type": "Feature",
  "properties": {
    "iso:country":"US",
    "sg:address":"11307 Jennifer Cir",
    "sg:city":"Sanger",
    "sg:classifiers":[
        {
            "category":"Donuts",
            "subcategory":"None",
            "type":"Food & Drink"
        }
    ],
    "sg:phone":"+1 940 458 2723",
    "sg:postcode":"76266",
    "sg:province":"TX",
    "sg:tags":[
        "shop"
    ],
    "wof:name":"Sip 'N Dip Donuts",
    "wof:placetype":"venue"
},
  "geometry": {"coordinates":[-97.187809,33.375375],"type":"Point"}
}