{
  "type": "Feature",
  "properties": {
    "iso:country":"US",
    "sg:address":"19720 US Hwy 281",
    "sg:city":"San Antonio",
    "sg:classifiers":[
        {
            "category":"Personal",
            "subcategory":"Beauty Salon",
            "type":"Services"
        }
    ],
    "sg:phone":"+1 210 626 2181",
    "sg:postcode":"78221",
    "sg:province":"TX",
    "wof:name":"Southwest Cafe",
    "wof:placetype":"venue"
},
  "geometry": {"coordinates":[-98.47659899999999,29.225467],"type":"Point"}
}