{
  "type": "Feature",
  "properties": {
    "iso:country":"US",
    "sg:address":"12605 N Gessner Dr",
    "sg:city":"Houston",
    "sg:classifiers":[
        {
            "category":"Restaurant",
            "type":"Food & Drink"
        }
    ],
    "sg:phone":"+1 832 912 1561",
    "sg:postcode":"77064",
    "sg:province":"TX",
    "sg:tags":[
        "eating"
    ],
    "wof:name":"Starbucks",
    "wof:placetype":"venue"
},
  "geometry": {"coordinates":[-95.543622,29.956062],"type":"Point"}
}