{
  "type": "Feature",
  "properties": {
    "iso:country":"US",
    "sg:address":"342 Texas Blvd",
    "sg:city":"Texarkana",
    "sg:classifiers":[
        {
            "category":"Freight",
            "type":"Transportation"
        }
    ],
    "sg:phone":"+1 903 223 9545",
    "sg:postcode":"75501",
    "sg:province":"TX",
    "sg:tags":[
        "storage"
    ],
    "wof:name":"Lindsey & Osborne Partnership",
    "wof:placetype":"venue"
},
  "geometry": {"coordinates":[-94.04595999999999,33.421942],"type":"Point"}
}