{
  "type": "Feature",
  "properties": {
    "iso:country":"US",
    "sg:address":"1452 Ryan Ct",
    "sg:city":"Grapevine",
    "sg:classifiers":[
        {
            "category":"Professional",
            "subcategory":"Business Services",
            "type":"Services"
        }
    ],
    "sg:phone":"+1 817 421 3320",
    "sg:postcode":"76051",
    "sg:province":"TX",
    "wof:name":"SGC Pool Service",
    "wof:placetype":"venue"
},
  "geometry": {"coordinates":[-97.094499,32.962461],"type":"Point"}
}