{
  "type": "Feature",
  "properties": {
    "iso:country":"US",
    "sg:address":"1604 Faulkner St",
    "sg:city":"Brenham",
    "sg:classifiers":[
        {
            "category":"Building & Trades",
            "subcategory":"Plumbing",
            "type":"Services"
        }
    ],
    "sg:phone":"+1 979 830 1513",
    "sg:postcode":"77833",
    "sg:province":"TX",
    "sg:tags":[
        "contractor"
    ],
    "wof:name":"Four Seasons HVAC",
    "wof:placetype":"venue"
},
  "geometry": {"coordinates":[-96.403944,30.152618],"type":"Point"}
}