{
  "type": "Feature",
  "properties": {
    "iso:country":"US",
    "sg:address":"305 E Harding Ave",
    "sg:city":"Morton",
    "sg:classifiers":[
        {
            "category":"Farming",
            "subcategory":"Farm",
            "type":"Manufacturing & Wholesale Goods"
        }
    ],
    "sg:phone":"+1 806 266 5987",
    "sg:postcode":"79346",
    "sg:province":"TX",
    "sg:tags":[
        "crop",
        "general"
    ],
    "wof:name":"Rusty Trull",
    "wof:placetype":"venue"
},
  "geometry": {"coordinates":[-102.755803,33.716345],"type":"Point"}
}