{
  "type": "Feature",
  "properties": {
    "iso:country":"US",
    "sg:address":"5915 S R L Thornton Fwy",
    "sg:city":"Dallas",
    "sg:classifiers":[
        {
            "category":"Autos & Motor Vehicles",
            "subcategory":"Auto Supplies",
            "type":"Retail Goods"
        }
    ],
    "sg:phone":"+1 214 376 2414",
    "sg:postcode":"75232",
    "sg:province":"TX",
    "sg:tags":[
        "lube",
        "oil"
    ],
    "wof:name":"Ghala Corporation",
    "wof:placetype":"venue"
},
  "geometry": {"coordinates":[-96.822945,32.675267],"type":"Point"}
}