{
  "type": "Feature",
  "properties": {
    "iso:country":"US",
    "sg:address":"9670 Co Rd 4221",
    "sg:city":"Frankston",
    "sg:classifiers":[
        {
            "category":"Organizations",
            "subcategory":"Religious Organization",
            "type":"Services"
        }
    ],
    "sg:phone":"+1 903 876 3270",
    "sg:postcode":"75763",
    "sg:province":"TX",
    "wof:name":"Pine Springs Baptist Church",
    "wof:placetype":"venue"
},
  "geometry": {"coordinates":[-95.50504100000001,32.112938],"type":"Point"}
}