{
  "type": "Feature",
  "properties": {
    "iso:country":"US",
    "sg:address":"12451 Kingsride Ln",
    "sg:city":"Houston",
    "sg:classifiers":[
        {
            "category":"Arts & Performance",
            "subcategory":"Theater",
            "type":"Entertainment"
        }
    ],
    "sg:phone":"+1 713 465 7222",
    "sg:postcode":"77024",
    "sg:province":"TX",
    "sg:tags":[
        "group"
    ],
    "wof:name":"Texas Po Boys",
    "wof:placetype":"venue"
},
  "geometry": {"coordinates":[-95.55027699999999,29.779461],"type":"Point"}
}