{
  "type": "Feature",
  "properties": {
    "iso:country":"US",
    "sg:address":"2474 Boca Chica Blvd",
    "sg:city":"Brownsville",
    "sg:classifiers":[
        {
            "category":"Insurance",
            "subcategory":"Insurance Agent",
            "type":"Services"
        }
    ],
    "sg:phone":"+1 956 504 0400",
    "sg:postcode":"78521",
    "sg:province":"TX",
    "wof:name":"Amco Insurance Agency",
    "wof:placetype":"venue"
},
  "geometry": {"coordinates":[-97.48317299999999,25.921645],"type":"Point"}
}