{
  "type": "Feature",
  "properties": {
    "iso:country":"US",
    "sg:address":"2850 Toccoa St",
    "sg:city":"Beaumont",
    "sg:classifiers":[
        {
            "category":"Insurance",
            "subcategory":"Hazard Insurance",
            "type":"Services"
        },
        {
            "category":"Insurance",
            "subcategory":"Health Insurance",
            "type":"Services"
        }
    ],
    "sg:phone":"+1 409 898 3446",
    "sg:postcode":"77703",
    "sg:province":"TX",
    "sg:tags":[
        "employee",
        "benefit",
        "commercial",
        "business"
    ],
    "sg:website":"http://www.ayerspatton.com",
    "wof:name":"Ayers Patton Insurance Services",
    "wof:placetype":"venue"
},
  "geometry": {"coordinates":[-94.131472,30.098375],"type":"Point"}
}