{
  "type": "Feature",
  "properties": {
    "iso:country":"US",
    "sg:address":"10140 Brimfield Dr",
    "sg:city":"Austin",
    "sg:classifiers":[
        {
            "category":"Professional",
            "subcategory":"Computer Services",
            "type":"Services"
        }
    ],
    "sg:phone":"+1 512 250 9709",
    "sg:postcode":"78726",
    "sg:province":"TX",
    "sg:tags":[
        "consultant",
        "designer"
    ],
    "wof:name":"AGR Assoc Inc",
    "wof:placetype":"venue"
},
  "geometry": {"coordinates":[-97.81788899999999,30.431272],"type":"Point"}
}