{
  "type": "Feature",
  "properties": {
    "iso:country":"US",
    "sg:address":"1434 N Central Expy",
    "sg:city":"Mc Kinney",
    "sg:classifiers":[
        {
            "category":"Personal",
            "subcategory":"Beauty Salon",
            "type":"Services"
        }
    ],
    "sg:phone":"+1 972 542 7342",
    "sg:postcode":"75070",
    "sg:province":"TX",
    "wof:name":"Tnt Designs",
    "wof:placetype":"venue"
},
  "geometry": {"coordinates":[-96.636616,33.213468],"type":"Point"}
}