{
  "type": "Feature",
  "properties": {
    "iso:country":"US",
    "sg:address":"739 S R L Thornton Fwy",
    "sg:city":"Dallas",
    "sg:classifiers":[
        {
            "category":"Building & Trades",
            "subcategory":"Construction",
            "type":"Services"
        }
    ],
    "sg:phone":"+1 214 942 0900",
    "sg:postcode":"75203",
    "sg:province":"TX",
    "sg:tags":[
        "home",
        "builder"
    ],
    "wof:name":"Simply Custom",
    "wof:placetype":"venue"
},
  "geometry": {"coordinates":[-96.81603200000001,32.744019],"type":"Point"}
}