{
  "type": "Feature",
  "properties": {
    "iso:country":"US",
    "sg:address":"1701 N Collins Blvd",
    "sg:city":"Richardson",
    "sg:classifiers":[
        {
            "category":"Health Services",
            "subcategory":"Clinic",
            "type":"Services"
        }
    ],
    "sg:phone":"+1 972 233 1725",
    "sg:postcode":"75080",
    "sg:province":"TX",
    "sg:tags":[
        "counseling",
        "mental"
    ],
    "wof:name":"Shirley Barga, MED, LTC, LMFT",
    "wof:placetype":"venue"
},
  "geometry": {"coordinates":[-96.72410499999999,32.972056],"type":"Point"}
}