{
  "type": "Feature",
  "properties": {
    "iso:country":"US",
    "sg:address":"2409 Teakwood Ln",
    "sg:city":"Plano",
    "sg:classifiers":[
        {
            "category":"Manufacturing",
            "subcategory":"Tools & Machinery",
            "type":"Manufacturing & Wholesale Goods"
        }
    ],
    "sg:phone":"+1 972 964 7866",
    "sg:postcode":"75075",
    "sg:province":"TX",
    "sg:tags":[
        "computer",
        "electronic",
        "mfg"
    ],
    "wof:name":"Paul Gaddy",
    "wof:placetype":"venue"
},
  "geometry": {"coordinates":[-96.742498,33.03693],"type":"Point"}
}