{
  "type": "Feature",
  "properties": {
    "iso:country":"US",
    "sg:address":"601 N Key Ave",
    "sg:city":"Lampasas",
    "sg:classifiers":[
        {
            "category":"Autos & Motor Vehicles",
            "subcategory":"Automobile Sales",
            "type":"Retail Goods"
        }
    ],
    "sg:phone":"+1 512 556 4880",
    "sg:postcode":"76550",
    "sg:province":"TX",
    "sg:tags":[
        "car",
        "dealer"
    ],
    "wof:name":"Benny Boyd Chrysler Dodge Jeep",
    "wof:placetype":"venue"
},
  "geometry": {"coordinates":[-98.186122,31.075885],"type":"Point"}
}