{
  "type": "Feature",
  "properties": {
    "iso:country":"US",
    "sg:address":"6413 High Lawn Ter",
    "sg:city":"Watauga",
    "sg:classifiers":[
        {
            "category":"Building & Trades",
            "subcategory":"Landscaping Services",
            "type":"Services"
        }
    ],
    "sg:phone":"+1 817 485 9708",
    "sg:postcode":"76148",
    "sg:province":"TX",
    "sg:tags":[
        "landscape",
        "contractor"
    ],
    "wof:name":"Heartland Landscape",
    "wof:placetype":"venue"
},
  "geometry": {"coordinates":[-97.24474499999999,32.889118],"type":"Point"}
}