{
  "type": "Feature",
  "properties": {
    "iso:country":"US",
    "sg:address":"530 Bedford Ct W",
    "sg:city":"Hurst",
    "sg:classifiers":[
        {
            "category":"Professional",
            "subcategory":"Employment Agencies",
            "type":"Services"
        }
    ],
    "sg:phone":"+1 817 268 3544",
    "sg:postcode":"76053",
    "sg:province":"TX",
    "sg:tags":[
        "help",
        "contractor"
    ],
    "wof:name":"Sterling Property Personnel",
    "wof:placetype":"venue"
},
  "geometry": {"coordinates":[-97.17723100000001,32.83057],"type":"Point"}
}