{
  "type": "Feature",
  "properties": {
    "iso:country":"US",
    "sg:address":"9525 Alta Mira Dr",
    "sg:city":"Dallas",
    "sg:classifiers":[
        {
            "category":"Building & Trades",
            "subcategory":"Landscaping Services",
            "type":"Services"
        }
    ],
    "sg:phone":"+1 214 324 5044",
    "sg:postcode":"75218",
    "sg:province":"TX",
    "sg:tags":[
        "landscape",
        "contractor"
    ],
    "wof:name":"A R Lawn Svc",
    "wof:placetype":"venue"
},
  "geometry": {"coordinates":[-96.696827,32.82539],"type":"Point"}
}