{
  "type": "Feature",
  "properties": {
    "iso:country":"US",
    "sg:address":"1354 Lakeview Dr",
    "sg:city":"Southlake",
    "sg:classifiers":[
        {
            "category":"Shopping",
            "subcategory":"Gifts & Souvenirs",
            "type":"Retail Goods"
        }
    ],
    "sg:phone":"+1 817 421 6612",
    "sg:postcode":"76092",
    "sg:province":"TX",
    "wof:name":"Ross Imports & Exports",
    "wof:placetype":"venue"
},
  "geometry": {"coordinates":[-97.18037099999999,32.955382],"type":"Point"}
}