{
  "type": "Feature",
  "properties": {
    "iso:country":"US",
    "sg:address":"7777 Fm 546",
    "sg:city":"Princeton",
    "sg:classifiers":[
        {
            "category":"Government",
            "subcategory":"Fire Station",
            "type":"Public Place"
        }
    ],
    "sg:phone":"+1 972 736 1310",
    "sg:postcode":"75407",
    "sg:province":"TX",
    "sg:tags":[
        "department",
        "protection"
    ],
    "sg:website":"http://www.branchfirerescue.org",
    "wof:name":"Branch Volunteer Fire Dept",
    "wof:placetype":"venue"
},
  "geometry": {"coordinates":[-96.50188799999999,33.102564],"type":"Point"}
}