{
  "type": "Feature",
  "properties": {
    "iso:country":"US",
    "sg:address":"1805 Florence Rd",
    "sg:city":"Killeen",
    "sg:classifiers":[
        {
            "category":"Personal",
            "subcategory":"Massage",
            "type":"Services"
        }
    ],
    "sg:phone":"+1 254 245 8145",
    "sg:postcode":"76541",
    "sg:province":"TX",
    "sg:tags":[
        "therapist"
    ],
    "sg:website":"http://www.gwilliamshealinghandsmt.com",
    "wof:name":"Healing Hands Massage Therapy",
    "wof:placetype":"venue"
},
  "geometry": {"coordinates":[-97.73855500000001,31.103342],"type":"Point"}
}