{
  "type": "Feature",
  "properties": {
    "iso:country":"US",
    "sg:address":"2112 Preston Ave",
    "sg:city":"Pasadena",
    "sg:classifiers":[
        {
            "category":"Professional",
            "subcategory":"Accounting & Tax Preparation",
            "type":"Services"
        }
    ],
    "sg:phone":"+1 713 477 8598",
    "sg:postcode":"77503",
    "sg:province":"TX",
    "sg:tags":[
        "return",
        "filing"
    ],
    "wof:name":"Fama Tax Svc",
    "wof:placetype":"venue"
},
  "geometry": {"coordinates":[-95.17252000000001,29.682246],"type":"Point"}
}