{
  "type": "Feature",
  "properties": {
    "iso:country":"US",
    "sg:address":"2844 W Woodlawn Ave",
    "sg:city":"San Antonio",
    "sg:classifiers":[
        {
            "category":"Banks & Credit Unions",
            "subcategory":"Bank",
            "type":"Services"
        }
    ],
    "sg:phone":"+1 210 734 7361",
    "sg:postcode":"78228",
    "sg:province":"TX",
    "wof:name":"South Trust Bank",
    "wof:placetype":"venue"
},
  "geometry": {"coordinates":[-98.54870699999999,29.456089],"type":"Point"}
}