{
  "type": "Feature",
  "properties": {
    "iso:country":"US",
    "sg:address":"3817 Cherokee Dr",
    "sg:city":"Bedford",
    "sg:classifiers":[
        {
            "category":"Autos & Motor Vehicles",
            "subcategory":"Auto Supplies",
            "type":"Retail Goods"
        }
    ],
    "sg:phone":"+1 817 540 3799",
    "sg:postcode":"76021",
    "sg:province":"TX",
    "wof:name":"New Comb Enterprises",
    "wof:placetype":"venue"
},
  "geometry": {"coordinates":[-97.102191,32.860744],"type":"Point"}
}