{
  "type": "Feature",
  "properties": {
    "iso:country":"US",
    "sg:address":"5622 Portal Dr",
    "sg:city":"Houston",
    "sg:classifiers":[
        {
            "category":"Banks & Credit Unions",
            "subcategory":"Investment Brokerage",
            "type":"Services"
        }
    ],
    "sg:phone":"+1 713 726 8881",
    "sg:postcode":"77096",
    "sg:province":"TX",
    "sg:tags":[
        "investing"
    ],
    "wof:name":"Cohen David R Cfp",
    "wof:placetype":"venue"
},
  "geometry": {"coordinates":[-95.485001,29.6614],"type":"Point"}
}