{
  "type": "Feature",
  "properties": {
    "iso:country":"US",
    "sg:address":"8000 Shoal Creek Blvd",
    "sg:city":"Austin",
    "sg:classifiers":[
        {
            "category":"Home & Garden",
            "subcategory":"Building Materials",
            "type":"Retail Goods"
        }
    ],
    "sg:phone":"+1 512 634 4330",
    "sg:postcode":"78757",
    "sg:province":"TX",
    "sg:tags":[
        "center"
    ],
    "wof:name":"Lowe's",
    "wof:placetype":"venue"
},
  "geometry": {"coordinates":[-97.739086,30.365325],"type":"Point"}
}