{
  "type": "Feature",
  "properties": {
    "iso:country":"US",
    "sg:address":"4616 Triangle Ave Apt 4102",
    "sg:city":"Austin",
    "sg:classifiers":[
        {
            "category":"Shopping",
            "subcategory":"Florist",
            "type":"Retail Goods"
        }
    ],
    "sg:phone":"+1 512 474 7719",
    "sg:postcode":"78751",
    "sg:province":"TX",
    "sg:website":"www.texasblooms.net",
    "wof:name":"A Texas Blooms",
    "wof:placetype":"venue"
},
  "geometry": {"coordinates":[-97.734892,30.30596],"type":"Point"}
}