{
  "type": "Feature",
  "properties": {
    "iso:country":"US",
    "sg:address":"1930 W William Cannon Dr",
    "sg:city":"Austin",
    "sg:classifiers":[
        {
            "category":"Restaurant",
            "type":"Food & Drink"
        }
    ],
    "sg:phone":"+1 512 444 1032",
    "sg:postcode":"78745",
    "sg:province":"TX",
    "sg:website":"www.billmillerbbq.com",
    "wof:name":"Bill Miller Bar-B-Q",
    "wof:placetype":"venue"
},
  "geometry": {"coordinates":[-97.804703,30.2026],"type":"Point"}
}