{
  "type": "Feature",
  "properties": {
    "iso:country":"US",
    "sg:address":"2430 14th St",
    "sg:city":"Plano",
    "sg:classifiers":[
        {
            "category":"Restaurant",
            "type":"Food & Drink"
        }
    ],
    "sg:phone":"+1 972 312 1200",
    "sg:postcode":"75074",
    "sg:province":"TX",
    "sg:tags":[
        "mexican"
    ],
    "wof:name":"El Pollo Regio",
    "wof:placetype":"venue"
},
  "geometry": {"coordinates":[-96.682725,33.017979],"type":"Point"}
}