{
  "type": "Feature",
  "properties": {
    "iso:country":"US",
    "sg:address":"3015 Berkshire Ln",
    "sg:city":"Denton",
    "sg:classifiers":[
        {
            "category":"Professional",
            "subcategory":"Accounting & Tax Preparation",
            "type":"Services"
        }
    ],
    "sg:phone":"+1 972 979 2086",
    "sg:postcode":"76210",
    "sg:province":"TX",
    "wof:name":"H Gene Brown & Assoc",
    "wof:placetype":"venue"
},
  "geometry": {"coordinates":[-97.062668,33.142581],"type":"Point"}
}