{
  "type": "Feature",
  "properties": {
    "iso:country":"US",
    "sg:address":"615 Hancock Ave",
    "sg:city":"Corpus Christi",
    "sg:classifiers":[
        {
            "category":"Retail",
            "subcategory":"Laundry & Dry Cleaning",
            "type":"Services"
        }
    ],
    "sg:phone":"+1 361 883 1281",
    "sg:postcode":"78404",
    "sg:province":"TX",
    "sg:tags":[
        "personal",
        "cleaners",
        "plant",
        "drycleaning"
    ],
    "wof:name":"Henry's Cleaners & Laundry",
    "wof:placetype":"venue"
},
  "geometry": {"coordinates":[-97.397375,27.782607],"type":"Point"}
}