{
  "type": "Feature",
  "properties": {
    "iso:country":"US",
    "sg:address":"517 N Lasalle St",
    "sg:city":"Navasota",
    "sg:classifiers":[
        {
            "category":"Personal",
            "type":"Services"
        }
    ],
    "sg:phone":"+1 936 825 1894",
    "sg:postcode":"77868",
    "sg:province":"TX",
    "wof:name":"High Maintenance Tanning",
    "wof:placetype":"venue"
},
  "geometry": {"coordinates":[-96.091837,30.392007],"type":"Point"}
}