{
  "type": "Feature",
  "properties": {
    "iso:country":"US",
    "sg:address":"5728 Leopard St",
    "sg:city":"Corpus Christi",
    "sg:classifiers":[
        {
            "category":"Building & Trades",
            "subcategory":"Landscaping Services",
            "type":"Services"
        }
    ],
    "sg:phone":"+1 361 289 1088",
    "sg:postcode":"78408",
    "sg:province":"TX",
    "sg:tags":[
        "landscape",
        "contractor"
    ],
    "wof:name":"Envirocare By Craig Smalley",
    "wof:placetype":"venue"
},
  "geometry": {"coordinates":[-97.473686,27.797738],"type":"Point"}
}