{
  "type": "Feature",
  "properties": {
    "iso:country":"US",
    "sg:address":"143 Bess St",
    "sg:city":"New Braunfels",
    "sg:classifiers":[
        {
            "category":"Restaurant",
            "type":"Food & Drink"
        }
    ],
    "sg:phone":"+1 830 629 1122",
    "sg:postcode":"78130",
    "sg:province":"TX",
    "sg:website":"www.whataburger.com",
    "wof:name":"Whataburger",
    "wof:placetype":"venue"
},
  "geometry": {"coordinates":[-98.050434,29.654422],"type":"Point"}
}