{
  "type": "Feature",
  "properties": {
    "iso:country":"US",
    "sg:address":"3800 Commerce St",
    "sg:city":"Dallas",
    "sg:classifiers":[
        {
            "category":"Arts & Performance",
            "subcategory":"Theater",
            "type":"Entertainment"
        }
    ],
    "sg:phone":"+1 214 754 4934",
    "sg:postcode":"75226",
    "sg:province":"TX",
    "sg:tags":[
        "television",
        "program",
        "producer"
    ],
    "wof:name":"Beaucoup Chapeaux",
    "wof:placetype":"venue"
},
  "geometry": {"coordinates":[-96.77109799999999,32.784298],"type":"Point"}
}