{
  "type": "Feature",
  "properties": {
    "iso:country":"US",
    "sg:address":"5505 Will Ruth Ave",
    "sg:city":"El Paso",
    "sg:classifiers":[
        {
            "category":"Social Services",
            "subcategory":"Child Care",
            "type":"Services"
        }
    ],
    "sg:phone":"+1 915 751 9487",
    "sg:postcode":"79924",
    "sg:province":"TX",
    "sg:tags":[
        "kindergarten",
        "academic",
        "school",
        "preschool",
        "elementary"
    ],
    "wof:name":"Northeast Children's Ed Ctr",
    "wof:placetype":"venue"
},
  "geometry": {"coordinates":[-106.414024,31.886153],"type":"Point"}
}