{
  "type": "Feature",
  "properties": {
    "iso:country":"US",
    "sg:address":"2951 Marina Bay Dr",
    "sg:city":"League City",
    "sg:classifiers":[
        {
            "category":"Real Estate",
            "subcategory":"Real Estate Operator",
            "type":"Services"
        }
    ],
    "sg:phone":"+1 281 291 7552",
    "sg:postcode":"77573",
    "sg:province":"TX",
    "sg:tags":[
        "property",
        "lessor"
    ],
    "wof:name":"Dorsey Properties",
    "wof:placetype":"venue"
},
  "geometry": {"coordinates":[-95.064081,29.539925],"type":"Point"}
}