{
  "type": "Feature",
  "properties": {
    "iso:country":"US",
    "sg:address":"8 Creekwood Cir",
    "sg:city":"Richardson",
    "sg:classifiers":[
        {
            "category":"Real Estate",
            "subcategory":"Real Estate Agent",
            "type":"Services"
        }
    ],
    "sg:phone":"+1 972 783 4619",
    "sg:postcode":"75080",
    "sg:province":"TX",
    "wof:name":"Yeargan Appraisal Group Inc",
    "wof:placetype":"venue"
},
  "geometry": {"coordinates":[-96.719362,32.982339],"type":"Point"}
}