{
  "type": "Feature",
  "properties": {
    "iso:country":"US",
    "sg:address":"4700 Pewter Ln",
    "sg:city":"Austin",
    "sg:classifiers":[
        {
            "category":"Personal",
            "subcategory":"Beauty Salon",
            "type":"Services"
        }
    ],
    "sg:phone":"+1 512 447 9570",
    "sg:postcode":"78744",
    "sg:province":"TX",
    "sg:tags":[
        "shop"
    ],
    "wof:name":"Naxi Hair Salon",
    "wof:placetype":"venue"
},
  "geometry": {"coordinates":[-97.74117699999999,30.198441],"type":"Point"}
}