{
  "type": "Feature",
  "properties": {
    "iso:country":"US",
    "sg:address":"507 E Lamar Blvd",
    "sg:city":"Arlington",
    "sg:classifiers":[
        {
            "category":"Professional",
            "subcategory":"Computer Services",
            "type":"Services"
        }
    ],
    "sg:phone":"+1 817 861 9347",
    "sg:postcode":"76011",
    "sg:province":"TX",
    "sg:tags":[
        "datum"
    ],
    "wof:name":"Rock Bottom",
    "wof:placetype":"venue"
},
  "geometry": {"coordinates":[-97.106391,32.762704],"type":"Point"}
}