{
  "type": "Feature",
  "properties": {
    "iso:country":"US",
    "sg:address":"700 E 11th St Ste 300",
    "sg:city":"Austin",
    "sg:classifiers":[
        {
            "category":"Social Services",
            "type":"Services"
        }
    ],
    "sg:phone":"+1 512 262 8215",
    "sg:postcode":"78701",
    "sg:province":"TX",
    "sg:tags":[
        "human"
    ],
    "wof:name":"Texas Round-Up",
    "wof:placetype":"venue"
},
  "geometry": {"coordinates":[-97.734337,30.27084],"type":"Point"}
}