{
  "type": "Feature",
  "properties": {
    "iso:country":"US",
    "sg:address":"2309 Versailles Ct",
    "sg:city":"Rockwall",
    "sg:classifiers":[
        {
            "category":"Mining & Drilling",
            "type":"Manufacturing & Wholesale Goods"
        }
    ],
    "sg:phone":"+1 972 771 6368",
    "sg:postcode":"75032",
    "sg:province":"TX",
    "sg:tags":[
        "field"
    ],
    "wof:name":"B R Technogy",
    "wof:placetype":"venue"
},
  "geometry": {"coordinates":[-96.476637,32.871253],"type":"Point"}
}