{
  "type": "Feature",
  "properties": {
    "iso:country":"US",
    "sg:address":"300 E Florida Ave",
    "sg:city":"Midland",
    "sg:classifiers":[
        {
            "category":"Shopping",
            "subcategory":"Clothing, Apparel, & Fashions",
            "type":"Retail Goods"
        }
    ],
    "sg:phone":"+1 432 620 8544",
    "sg:postcode":"79701",
    "sg:province":"TX",
    "sg:tags":[
        "item",
        "boutique"
    ],
    "wof:name":"LA Nueva Moda & More",
    "wof:placetype":"venue"
},
  "geometry": {"coordinates":[-102.070457,31.989207],"type":"Point"}
}