{
  "type": "Feature",
  "properties": {
    "iso:country":"US",
    "sg:address":"2201 College Ave",
    "sg:city":"Austin",
    "sg:classifiers":[
        {
            "category":"Restaurant",
            "type":"Food & Drink"
        }
    ],
    "sg:phone":"+1 512 443 4200",
    "sg:postcode":"78704",
    "sg:province":"TX",
    "sg:tags":[
        "eating",
        "italian"
    ],
    "sg:website":"www.treehousegrill.com",
    "wof:name":"Tree House Italian Grill",
    "wof:placetype":"venue"
},
  "geometry": {"coordinates":[-97.752602,30.241199],"type":"Point"}
}