{
  "type": "Feature",
  "properties": {
    "iso:country":"US",
    "sg:address":"114 Eastwood Dr",
    "sg:city":"San Antonio",
    "sg:classifiers":[
        {
            "category":"Building & Trades",
            "subcategory":"Plumbing",
            "type":"Services"
        }
    ],
    "sg:phone":"+1 210 333 5922",
    "sg:postcode":"78220",
    "sg:province":"TX",
    "sg:tags":[
        "conditioning",
        "contractor",
        "system",
        "air"
    ],
    "wof:name":"Green's Air Conditioning",
    "wof:placetype":"venue"
},
  "geometry": {"coordinates":[-98.410269,29.42388],"type":"Point"}
}