{
  "type": "Feature",
  "properties": {
    "iso:country":"US",
    "sg:address":"8708 S View Rd",
    "sg:city":"Austin",
    "sg:classifiers":[
        {
            "category":"Education",
            "subcategory":"Special Training",
            "type":"Public Place"
        }
    ],
    "sg:phone":"+1 512 288 6560",
    "sg:postcode":"78737",
    "sg:province":"TX",
    "wof:name":"Kairos Foundation The",
    "wof:placetype":"venue"
},
  "geometry": {"coordinates":[-97.910292,30.228489],"type":"Point"}
}