{
  "type": "Feature",
  "properties": {
    "iso:country":"US",
    "sg:address":"7900 Morley St",
    "sg:city":"Houston",
    "sg:classifiers":[
        {
            "category":"Freight",
            "type":"Transportation"
        }
    ],
    "sg:phone":"+1 713 649 5515",
    "sg:postcode":"77061",
    "sg:province":"TX",
    "sg:tags":[
        "operator",
        "local",
        "trucking"
    ],
    "wof:name":"Sandys Delivery",
    "wof:placetype":"venue"
},
  "geometry": {"coordinates":[-95.272419,29.661455],"type":"Point"}
}