{
  "type": "Feature",
  "properties": {
    "iso:country":"US",
    "sg:address":"902 S Airport Dr Ste 7",
    "sg:city":"Weslaco",
    "sg:classifiers":[
        {
            "category":"Community Center",
            "type":"Public Place"
        }
    ],
    "sg:phone":"+1 866 873 0879",
    "sg:postcode":"78596",
    "sg:province":"TX",
    "sg:tags":[
        "medical"
    ],
    "sg:website":"http://www.rapidstdtesting.com",
    "wof:name":"Rapid STD/HIV Testing",
    "wof:placetype":"venue"
},
  "geometry": {"coordinates":[-97.974422,26.151633],"type":"Point"}
}