{
  "type": "Feature",
  "properties": {
    "iso:country":"US",
    "sg:address":"6836 Megan Ln",
    "sg:city":"Fort Worth",
    "sg:classifiers":[
        {
            "category":"Shopping",
            "type":"Retail Goods"
        },
        {
            "category":"Professional",
            "subcategory":"Art Services",
            "type":"Services"
        }
    ],
    "sg:phone":"+1 817 656 9186",
    "sg:postcode":"76180",
    "sg:province":"TX",
    "sg:tags":[
        "commercial",
        "wedding",
        "design",
        "supply"
    ],
    "wof:name":"Design By Pretzel",
    "wof:placetype":"venue"
},
  "geometry": {"coordinates":[-97.23218900000001,32.868184],"type":"Point"}
}