{
  "type": "Feature",
  "properties": {
    "iso:country":"US",
    "sg:address":"2329 S Garland Ave",
    "sg:city":"Garland",
    "sg:classifiers":[
        {
            "category":"Professional",
            "type":"Services"
        }
    ],
    "sg:phone":"+1 972 840 9300",
    "sg:postcode":"75041",
    "sg:province":"TX",
    "wof:name":"Perception Motor Sports Lsg",
    "wof:placetype":"venue"
},
  "geometry": {"coordinates":[-96.652281,32.890214],"type":"Point"}
}