{
  "type": "Feature",
  "properties": {
    "iso:country":"US",
    "sg:address":"4912 Meadow Creek Dr",
    "sg:city":"Dallas",
    "sg:classifiers":[
        {
            "category":"Professional",
            "type":"Services"
        }
    ],
    "sg:phone":"+1 972 233 4374",
    "sg:postcode":"75248",
    "sg:province":"TX",
    "wof:name":"Scott J Chaffin",
    "wof:placetype":"venue"
},
  "geometry": {"coordinates":[-96.790164,32.970487],"type":"Point"}
}