{
  "type": "Feature",
  "properties": {
    "iso:country":"US",
    "sg:address":"4219 Edgar Park Ave",
    "sg:city":"El Paso",
    "sg:classifiers":[
        {
            "category":"Retail",
            "subcategory":"Repair Shop",
            "type":"Services"
        }
    ],
    "sg:phone":"+1 915 751 6167",
    "sg:postcode":"79904",
    "sg:province":"TX",
    "wof:name":"Angie & Sons Piano & Tune Up",
    "wof:placetype":"venue"
},
  "geometry": {"coordinates":[-106.441363,31.856409],"type":"Point"}
}