{
  "type": "Feature",
  "properties": {
    "iso:country":"US",
    "sg:address":"10976 Deer Creek Dr",
    "sg:city":"Tyler",
    "sg:classifiers":[
        {
            "category":"Professional",
            "type":"Services"
        }
    ],
    "sg:phone":"+1 903 566 5511",
    "sg:postcode":"75707",
    "sg:province":"TX",
    "wof:name":"Nikan LLC",
    "wof:placetype":"venue"
},
  "geometry": {"coordinates":[-95.180536,32.319821],"type":"Point"}
}