{
  "type": "Feature",
  "properties": {
    "iso:country":"US",
    "sg:address":"1106 E 42nd St",
    "sg:city":"Odessa",
    "sg:classifiers":[
        {
            "category":"Restaurant",
            "type":"Food & Drink"
        }
    ],
    "sg:menulink":"http://www.allmenus.com/tx/odessa/94310-dominos-pizza/menu/",
    "sg:phone":"+1 432 367 3030",
    "sg:postcode":"79762",
    "sg:province":"TX",
    "sg:tags":[
        "american",
        "wing",
        "pizza"
    ],
    "wof:name":"Domino's Pizza",
    "wof:placetype":"venue"
},
  "geometry": {"coordinates":[-102.37358999999999,31.884887],"type":"Point"}
}