{
  "type": "Feature",
  "properties": {
    "iso:country":"US",
    "sg:address":"608 E Hwy 377",
    "sg:city":"Granbury",
    "sg:classifiers":[
        {
            "category":"Professional",
            "subcategory":"Accounting & Tax Preparation",
            "type":"Services"
        }
    ],
    "sg:phone":"+1 817 279 7052",
    "sg:postcode":"76048",
    "sg:province":"TX",
    "wof:name":"Sue A Hull CPA",
    "wof:placetype":"venue"
},
  "geometry": {"coordinates":[-97.779083,32.434337],"type":"Point"}
}