{
  "type": "Feature",
  "properties": {
    "iso:country":"US",
    "sg:address":"3209 Channing Ln",
    "sg:city":"Bedford",
    "sg:classifiers":[
        {
            "category":"Local Transit",
            "type":"Transportation"
        }
    ],
    "sg:phone":"+1 817 540 9365",
    "sg:postcode":"76021",
    "sg:province":"TX",
    "sg:tags":[
        "limousine"
    ],
    "wof:name":"1 Hummer H2 Limousine",
    "wof:placetype":"venue"
},
  "geometry": {"coordinates":[-97.14406,32.857746],"type":"Point"}
}