{
  "type": "Feature",
  "properties": {
    "iso:country":"US",
    "sg:address":"3801 Westridge Ave",
    "sg:city":"Fort Worth",
    "sg:classifiers":[
        {
            "category":"Building & Trades",
            "subcategory":"Construction",
            "type":"Services"
        }
    ],
    "sg:phone":"+1 817 377 8614",
    "sg:postcode":"76116",
    "sg:province":"TX",
    "sg:tags":[
        "home",
        "builder"
    ],
    "wof:name":"Ridglea Place Townhome",
    "wof:placetype":"venue"
},
  "geometry": {"coordinates":[-97.41601,32.722226],"type":"Point"}
}