{
  "type": "Feature",
  "properties": {
    "iso:country":"US",
    "sg:address":"5940 Kroger Dr",
    "sg:city":"Keller",
    "sg:classifiers":[
        {
            "category":"Building & Trades",
            "subcategory":"Plumbing",
            "type":"Services"
        }
    ],
    "sg:phone":"+1 817 337 4442",
    "sg:postcode":"76248",
    "sg:province":"TX",
    "sg:tags":[
        "c",
        "air",
        "refrigeration",
        "ventilation",
        "heating"
    ],
    "wof:name":"Go Econo Air of Texas LLC",
    "wof:placetype":"venue"
},
  "geometry": {"coordinates":[-97.25975200000001,32.911334],"type":"Point"}
}