{
  "type": "Feature",
  "properties": {
    "iso:country":"US",
    "sg:address":"902 S Grandview Ave",
    "sg:city":"Odessa",
    "sg:classifiers":[
        {
            "category":"Retail",
            "subcategory":"Auto Repair",
            "type":"Services"
        }
    ],
    "sg:phone":"+1 432 332 4000",
    "sg:postcode":"79761",
    "sg:province":"TX",
    "sg:tags":[
        "automobile",
        "customizing"
    ],
    "wof:name":"M C Custom Hot Rods",
    "wof:placetype":"venue"
},
  "geometry": {"coordinates":[-102.34048300000001,31.843484],"type":"Point"}
}