{
  "type": "Feature",
  "properties": {
    "iso:country":"US",
    "sg:address":"3675 US Hwy 287",
    "sg:city":"Midlothian",
    "sg:classifiers":[
        {
            "category":"Wholesale",
            "subcategory":"Machinery & Supplies",
            "type":"Manufacturing & Wholesale Goods"
        }
    ],
    "sg:phone":"+1 972 723 3900",
    "sg:postcode":"76065",
    "sg:province":"TX",
    "sg:tags":[
        "propane",
        "equipment",
        "gas"
    ],
    "wof:name":"Midtex LP Gas",
    "wof:placetype":"venue"
},
  "geometry": {"coordinates":[-96.94442100000001,32.462002],"type":"Point"}
}