{
  "type": "Feature",
  "properties": {
    "iso:country":"US",
    "sg:address":"4209 W Walnut St",
    "sg:city":"Garland",
    "sg:classifiers":[
        {
            "category":"Professional",
            "type":"Services"
        }
    ],
    "sg:phone":"+1 972 205 0723",
    "sg:postcode":"75042",
    "sg:province":"TX",
    "wof:name":"Maria Coreas",
    "wof:placetype":"venue"
},
  "geometry": {"coordinates":[-96.69677900000001,32.91668],"type":"Point"}
}