{
  "type": "Feature",
  "properties": {
    "iso:country":"US",
    "sg:address":"2302 Blaine St",
    "sg:city":"Laredo",
    "sg:classifiers":[
        {
            "category":"Banks & Credit Unions",
            "subcategory":"Bank",
            "type":"Services"
        }
    ],
    "sg:phone":"+1 956 725 2525",
    "sg:postcode":"78043",
    "sg:province":"TX",
    "wof:name":"Commerce Bank",
    "wof:placetype":"venue"
},
  "geometry": {"coordinates":[-99.471574,27.490585],"type":"Point"}
}