{
  "type": "Feature",
  "properties": {
    "iso:country":"US",
    "sg:address":"2930 S 1st St",
    "sg:city":"Garland",
    "sg:classifiers":[
        {
            "category":"Shopping",
            "subcategory":"Mobile Phones",
            "type":"Retail Goods"
        }
    ],
    "sg:phone":"+1 972 864 2355",
    "sg:postcode":"75041",
    "sg:province":"TX",
    "wof:name":"Next Star Texas",
    "wof:placetype":"venue"
},
  "geometry": {"coordinates":[-96.630692,32.880591],"type":"Point"}
}