{
  "type": "Feature",
  "properties": {
    "iso:country":"US",
    "sg:address":"1 Erickson St",
    "sg:city":"Conroe",
    "sg:classifiers":[
        {
            "category":"Professional",
            "subcategory":"Art Services",
            "type":"Services"
        }
    ],
    "sg:phone":"+1 936 441 2920",
    "sg:postcode":"77301",
    "sg:province":"TX",
    "sg:tags":[
        "photography"
    ],
    "wof:name":"David Hopper Photography",
    "wof:placetype":"venue"
},
  "geometry": {"coordinates":[-95.45783,30.332182],"type":"Point"}
}