{
  "type": "Feature",
  "properties": {
    "iso:country":"US",
    "sg:address":"105 E Main St",
    "sg:city":"Palestine",
    "sg:classifiers":[
        {
            "category":"Health Services",
            "subcategory":"Doctor",
            "type":"Services"
        }
    ],
    "sg:phone":"+1 903 729 5140",
    "sg:postcode":"75801",
    "sg:province":"TX",
    "sg:tags":[
        "medical"
    ],
    "wof:name":"S Srivathanakul MD",
    "wof:placetype":"venue"
},
  "geometry": {"coordinates":[-95.63141299999999,31.762252],"type":"Point"}
}