{
  "type": "Feature",
  "properties": {
    "iso:country":"US",
    "sg:address":"1701 N College St",
    "sg:city":"Killeen",
    "sg:classifiers":[
        {
            "category":"Social Services",
            "subcategory":"Child Care",
            "type":"Services"
        }
    ],
    "sg:phone":"+1 254 554 6800",
    "sg:postcode":"76541",
    "sg:province":"TX",
    "wof:name":"Travan's Day Care",
    "wof:placetype":"venue"
},
  "geometry": {"coordinates":[-97.728623,31.132279],"type":"Point"}
}