{
  "type": "Feature",
  "properties": {
    "iso:country":"US",
    "sg:address":"700 US Hwy 259",
    "sg:city":"Kilgore",
    "sg:classifiers":[
        {
            "category":"Cinema",
            "subcategory":"Movie Rental",
            "type":"Entertainment"
        }
    ],
    "sg:phone":"+1 903 984 3835",
    "sg:postcode":"75662",
    "sg:province":"TX",
    "sg:tags":[
        "leasing",
        "video",
        "disc",
        "tape"
    ],
    "wof:name":"Movie Gallery",
    "wof:placetype":"venue"
},
  "geometry": {"coordinates":[-94.86764599999999,32.387302],"type":"Point"}
}