{
  "type": "Feature",
  "properties": {
    "iso:country":"US",
    "sg:address":"17530 Blake Manor Rd",
    "sg:city":"Manor",
    "sg:classifiers":[
        {
            "category":"Food & Beverages",
            "subcategory":"Groceries & Convenience Stores",
            "type":"Retail Goods"
        }
    ],
    "sg:phone":"+1 512 272 8388",
    "sg:postcode":"78653",
    "sg:province":"TX",
    "wof:name":"Blake Manor Food Mart",
    "wof:placetype":"venue"
},
  "geometry": {"coordinates":[-97.53903800000001,30.316184],"type":"Point"}
}