{
  "type": "Feature",
  "properties": {
    "iso:country":"US",
    "sg:address":"2503 4th Ave",
    "sg:city":"Amarillo",
    "sg:classifiers":[
        {
            "category":"Museum",
            "type":"Entertainment"
        }
    ],
    "sg:phone":"+1 806 651 2244",
    "sg:postcode":"79015",
    "sg:province":"TX",
    "sg:website":"www.panhandleplains.org",
    "wof:name":"Panhandle-Plains Historical Museum",
    "wof:placetype":"venue"
},
  "geometry": {"coordinates":[-101.91567000000001,34.979826],"type":"Point"}
}