{
  "type": "Feature",
  "properties": {
    "iso:country":"US",
    "sg:address":"4414 Hanover St",
    "sg:city":"Grand Prairie",
    "sg:classifiers":[
        {
            "category":"Shopping",
            "type":"Retail Goods"
        }
    ],
    "sg:phone":"+1 972 237 9220",
    "sg:postcode":"75052",
    "sg:province":"TX",
    "sg:tags":[
        "telephone",
        "cellular"
    ],
    "wof:name":"Novak Network",
    "wof:placetype":"venue"
},
  "geometry": {"coordinates":[-97.012933,32.664434],"type":"Point"}
}