{
  "type": "Feature",
  "properties": {
    "iso:country":"US",
    "sg:address":"202 Little Ranches Rd B",
    "sg:city":"Wimberley",
    "sg:classifiers":[
        {
            "category":"Building & Trades",
            "subcategory":"Construction",
            "type":"Services"
        }
    ],
    "sg:phone":"+1 512 847 3204",
    "sg:postcode":"78676",
    "sg:province":"TX",
    "sg:tags":[
        "siding",
        "contractor"
    ],
    "wof:name":"Nicols Siding Co",
    "wof:placetype":"venue"
},
  "geometry": {"coordinates":[-98.06205199999999,29.990133],"type":"Point"}
}