{
  "type": "Feature",
  "properties": {
    "iso:country":"US",
    "sg:address":"9021 Almeda-Genoa Rd",
    "sg:city":"Houston",
    "sg:classifiers":[
        {
            "category":"Retail",
            "subcategory":"Auto Repair",
            "type":"Services"
        }
    ],
    "sg:phone":"+1 713 991 0383",
    "sg:postcode":"77075",
    "sg:province":"TX",
    "sg:tags":[
        "repairing",
        "automobile",
        "general"
    ],
    "wof:name":"Balboa's Auto Repair",
    "wof:placetype":"venue"
},
  "geometry": {"coordinates":[-95.253314,29.627021],"type":"Point"}
}