{
  "type": "Feature",
  "properties": {
    "iso:country":"US",
    "sg:address":"18051 FM 1660",
    "sg:city":"Taylor",
    "sg:classifiers":[
        {
            "category":"Farming",
            "subcategory":"Farm & Veterinary Services",
            "type":"Manufacturing & Wholesale Goods"
        }
    ],
    "sg:phone":"+1 512 352 7444",
    "sg:postcode":"76574",
    "sg:province":"TX",
    "sg:tags":[
        "livestock"
    ],
    "wof:name":"Brushy Creek Custom Sires",
    "wof:placetype":"venue"
},
  "geometry": {"coordinates":[-97.41191999999999,30.473086],"type":"Point"}
}