{
  "type": "Feature",
  "properties": {
    "iso:country":"US",
    "sg:address":"3812 Fondren Rd",
    "sg:city":"Houston",
    "sg:classifiers":[
        {
            "category":"Personal",
            "subcategory":"Beauty Salon",
            "type":"Services"
        }
    ],
    "sg:phone":"+1 713 785 3832",
    "sg:postcode":"77063",
    "sg:province":"TX",
    "sg:tags":[
        "shop"
    ],
    "wof:name":"Delmis Beauty Salon",
    "wof:placetype":"venue"
},
  "geometry": {"coordinates":[-95.520601,29.723912],"type":"Point"}
}