{
  "type": "Feature",
  "properties": {
    "iso:country":"US",
    "sg:address":"807 W Moore Ave",
    "sg:city":"Terrell",
    "sg:classifiers":[
        {
            "category":"Restaurant",
            "type":"Food & Drink"
        }
    ],
    "sg:phone":"+1 972 524 6204",
    "sg:postcode":"75160",
    "sg:province":"TX",
    "sg:tags":[
        "out"
    ],
    "wof:name":"Yellow Rose Cafe",
    "wof:placetype":"venue"
},
  "geometry": {"coordinates":[-96.288651,32.737736],"type":"Point"}
}