{
  "type": "Feature",
  "properties": {
    "iso:country":"US",
    "sg:address":"5202 Kirby Dr",
    "sg:city":"Houston",
    "sg:classifiers":[
        {
            "category":"Banks & Credit Unions",
            "subcategory":"Bank",
            "type":"Services"
        }
    ],
    "sg:phone":"+1 713 807 0272",
    "sg:postcode":"77098",
    "sg:province":"TX",
    "sg:website":"www.wachovia.com",
    "wof:name":"Wachovia",
    "wof:placetype":"venue"
},
  "geometry": {"coordinates":[-95.418727,29.72634],"type":"Point"}
}