{
  "type": "Feature",
  "properties": {
    "iso:country":"US",
    "sg:address":"15710 Chimney Rock Rd",
    "sg:city":"Missouri City",
    "sg:classifiers":[
        {
            "category":"Social Services",
            "subcategory":"Child Care",
            "type":"Services"
        }
    ],
    "sg:phone":"+1 281 416 3700",
    "sg:postcode":"77489",
    "sg:province":"TX",
    "sg:tags":[
        "day"
    ],
    "wof:name":"First Learning Center",
    "wof:placetype":"venue"
},
  "geometry": {"coordinates":[-95.483299,29.599701],"type":"Point"}
}