{
  "type": "Feature",
  "properties": {
    "iso:country":"US",
    "sg:address":"2910 N Eastman Rd",
    "sg:city":"Longview",
    "sg:classifiers":[
        {
            "category":"Mining & Drilling",
            "type":"Manufacturing & Wholesale Goods"
        }
    ],
    "sg:phone":"+1 903 757 9399",
    "sg:postcode":"75605",
    "sg:province":"TX",
    "sg:tags":[
        "oil",
        "gas",
        "producer"
    ],
    "wof:name":"Thomas S Price",
    "wof:placetype":"venue"
},
  "geometry": {"coordinates":[-94.722025,32.532195],"type":"Point"}
}