{
  "type": "Feature",
  "properties": {
    "iso:country":"US",
    "sg:address":"2416 Fort Worth Hwy",
    "sg:city":"Weatherford",
    "sg:classifiers":[
        {
            "category":"Autos & Motor Vehicles",
            "subcategory":"Automobile Sales",
            "type":"Retail Goods"
        }
    ],
    "sg:phone":"+1 817 596 8072",
    "sg:postcode":"76087",
    "sg:province":"TX",
    "sg:tags":[
        "used",
        "car",
        "dealers-used",
        "new",
        "cars-wholesale"
    ],
    "wof:name":"Circle B Auto Sales",
    "wof:placetype":"venue"
},
  "geometry": {"coordinates":[-97.725168,32.756874],"type":"Point"}
}