{
  "type": "Feature",
  "properties": {
    "iso:country":"US",
    "sg:address":"3411 Hornbeam Dr",
    "sg:city":"Houston",
    "sg:classifiers":[
        {
            "category":"Organizations",
            "subcategory":"Religious Organization",
            "type":"Services"
        }
    ],
    "sg:phone":"+1 281 759 6667",
    "sg:postcode":"77082",
    "sg:province":"TX",
    "wof:name":"Hao Hoa Buddhist Church",
    "wof:placetype":"venue"
},
  "geometry": {"coordinates":[-95.650249,29.720401],"type":"Point"}
}