{
  "type": "Feature",
  "properties": {
    "iso:country":"US",
    "sg:address":"1705 N 1st St",
    "sg:city":"Kingsville",
    "sg:classifiers":[
        {
            "category":"Real Estate",
            "subcategory":"Real Estate Operator",
            "type":"Services"
        }
    ],
    "sg:phone":"+1 361 592 3121",
    "sg:postcode":"78363",
    "sg:province":"TX",
    "sg:tags":[
        "apartment"
    ],
    "wof:name":"Raintree Apartments",
    "wof:placetype":"venue"
},
  "geometry": {"coordinates":[-97.875203,27.532689],"type":"Point"}
}