{
  "type": "Feature",
  "properties": {
    "iso:country":"US",
    "sg:address":"611 N Yarbrough Dr",
    "sg:city":"El Paso",
    "sg:classifiers":[
        {
            "category":"Restaurant",
            "type":"Food & Drink"
        }
    ],
    "sg:phone":"+1 915 633 8173",
    "sg:postcode":"79915",
    "sg:province":"TX",
    "sg:tags":[
        "eating"
    ],
    "wof:name":"Aromas Catering",
    "wof:placetype":"venue"
},
  "geometry": {"coordinates":[-106.345986,31.74276],"type":"Point"}
}