{
  "type": "Feature",
  "properties": {
    "iso:country":"US",
    "sg:address":"220 N Broadway",
    "sg:city":"Dimmitt",
    "sg:classifiers":[
        {
            "category":"Professional",
            "subcategory":"Computer Services",
            "type":"Services"
        }
    ],
    "sg:phone":"+1 806 647 4841",
    "sg:postcode":"79027",
    "sg:province":"TX",
    "wof:name":"Computer Solutions",
    "wof:placetype":"venue"
},
  "geometry": {"coordinates":[-102.312291,34.552958],"type":"Point"}
}