{
  "type": "Feature",
  "properties": {
    "iso:country":"US",
    "sg:address":"4235 Commercial Ave",
    "sg:city":"San Antonio",
    "sg:classifiers":[
        {
            "category":"Food & Beverages",
            "subcategory":"Groceries & Convenience Stores",
            "type":"Retail Goods"
        }
    ],
    "sg:phone":"+1 210 924 2854",
    "sg:postcode":"78221",
    "sg:province":"TX",
    "wof:name":"Armandos Flea Mkt Sales",
    "wof:placetype":"venue"
},
  "geometry": {"coordinates":[-98.51627000000001,29.326325],"type":"Point"}
}