{
  "type": "Feature",
  "properties": {
    "iso:country":"US",
    "sg:address":"2205 SE 4th St",
    "sg:city":"Grand Prairie",
    "sg:classifiers":[
        {
            "category":"Education",
            "subcategory":"School",
            "type":"Public Place"
        }
    ],
    "sg:phone":"+1 972 264 8651",
    "sg:postcode":"75051",
    "sg:province":"TX",
    "wof:name":"Kennedy Middle School",
    "wof:placetype":"venue"
},
  "geometry": {"coordinates":[-97.001667,32.71043],"type":"Point"}
}