{
  "type": "Feature",
  "properties": {
    "iso:country":"US",
    "sg:address":"1711A E Frankford Rd",
    "sg:city":"Carrollton",
    "sg:classifiers":[
        {
            "category":"Retail",
            "subcategory":"Laundry & Dry Cleaning",
            "type":"Services"
        }
    ],
    "sg:phone":"+1 972 492 7286",
    "sg:postcode":"75007",
    "sg:province":"TX",
    "wof:name":"Stan's Comet Cleaners",
    "wof:placetype":"venue"
},
  "geometry": {"coordinates":[-96.89759100000001,32.998919],"type":"Point"}
}