{
  "type": "Feature",
  "properties": {
    "iso:country":"US",
    "sg:address":"8370 N Houston Rosslyn Rd",
    "sg:city":"Houston",
    "sg:classifiers":[
        {
            "category":"Bars & Pubs",
            "type":"Food & Drink"
        }
    ],
    "sg:phone":"+1 713 996 9877",
    "sg:postcode":"77088",
    "sg:province":"TX",
    "sg:tags":[
        "drinking"
    ],
    "wof:name":"LA Pantera Club & Sports Bar",
    "wof:placetype":"venue"
},
  "geometry": {"coordinates":[-95.487533,29.867106],"type":"Point"}
}