{
  "type": "Feature",
  "properties": {
    "iso:country":"US",
    "sg:address":"1106 N Richmond Rd",
    "sg:city":"Wharton",
    "sg:classifiers":[
        {
            "category":"Utilities",
            "subcategory":"Cable",
            "type":"Services"
        }
    ],
    "sg:phone":"+1 979 282 2121",
    "sg:postcode":"77488",
    "sg:province":"TX",
    "sg:tags":[
        "television"
    ],
    "wof:name":"Wireless One",
    "wof:placetype":"venue"
},
  "geometry": {"coordinates":[-96.099125,29.320204],"type":"Point"}
}