{
  "type": "Feature",
  "properties": {
    "iso:country":"US",
    "sg:address":"3205 Flintridge Ct",
    "sg:city":"Arlington",
    "sg:classifiers":[
        {
            "category":"Professional",
            "type":"Services"
        }
    ],
    "sg:phone":"+1 817 465 8870",
    "sg:postcode":"76017",
    "sg:province":"TX",
    "wof:name":"SPD Ent",
    "wof:placetype":"venue"
},
  "geometry": {"coordinates":[-97.15976999999999,32.666867],"type":"Point"}
}