{
  "type": "Feature",
  "properties": {
    "iso:country":"US",
    "sg:address":"14215 Coit Rd",
    "sg:city":"Dallas",
    "sg:classifiers":[
        {
            "category":"Personal",
            "subcategory":"Beauty Salon",
            "type":"Services"
        }
    ],
    "sg:phone":"+1 972 387 8504",
    "sg:postcode":"75254",
    "sg:province":"TX",
    "wof:name":"Supercuts",
    "wof:placetype":"venue"
},
  "geometry": {"coordinates":[-96.769019,32.937233],"type":"Point"}
}