{
  "type": "Feature",
  "properties": {
    "iso:country":"US",
    "sg:address":"11237 FM 14",
    "sg:city":"Tyler",
    "sg:classifiers":[
        {
            "category":"Retail",
            "subcategory":"Auto Repair",
            "type":"Services"
        }
    ],
    "sg:phone":"+1 903 593 2223",
    "sg:postcode":"75706",
    "sg:province":"TX",
    "sg:tags":[
        "repairing",
        "automobile"
    ],
    "wof:name":"Amazing Auto Works",
    "wof:placetype":"venue"
},
  "geometry": {"coordinates":[-95.280547,32.427496],"type":"Point"}
}