{
  "type": "Feature",
  "properties": {
    "iso:country":"US",
    "sg:address":"4001 Seville Dr",
    "sg:city":"Amarillo",
    "sg:classifiers":[
        {
            "category":"Insurance",
            "subcategory":"Insurance Agent",
            "type":"Services"
        }
    ],
    "sg:phone":"+1 806 353 0379",
    "sg:postcode":"79121",
    "sg:province":"TX",
    "wof:name":"Paul Holligan",
    "wof:placetype":"venue"
},
  "geometry": {"coordinates":[-101.92507999999999,35.167746],"type":"Point"}
}