{
  "type": "Feature",
  "properties": {
    "iso:country":"US",
    "sg:address":"5506 Fairmont Dr",
    "sg:city":"Rowlett",
    "sg:classifiers":[
        {
            "category":"Building & Trades",
            "subcategory":"Construction",
            "type":"Services"
        }
    ],
    "sg:phone":"+1 972 475 1755",
    "sg:postcode":"75088",
    "sg:province":"TX",
    "sg:tags":[
        "roofing",
        "contractor"
    ],
    "wof:name":"Alpha & Omega Roofing Co",
    "wof:placetype":"venue"
},
  "geometry": {"coordinates":[-96.511613,32.908945],"type":"Point"}
}