{
  "type": "Feature",
  "properties": {
    "iso:country":"US",
    "sg:address":"3930 Valley View Ln",
    "sg:city":"Irving",
    "sg:classifiers":[
        {
            "category":"Freight",
            "type":"Transportation"
        }
    ],
    "sg:phone":"+1 972 528 0186",
    "sg:postcode":"75062",
    "sg:province":"TX",
    "sg:tags":[
        "commercial",
        "household",
        "storage"
    ],
    "sg:website":"http://www.storagefront.com",
    "wof:name":"Pack & Stack Self Storage",
    "wof:placetype":"venue"
},
  "geometry": {"coordinates":[-97.021241,32.85548],"type":"Point"}
}