{
  "type": "Feature",
  "properties": {
    "iso:country":"US",
    "sg:address":"1207 W Church St",
    "sg:city":"Livingston",
    "sg:classifiers":[
        {
            "category":"Autos & Motor Vehicles",
            "subcategory":"Auto Supplies",
            "type":"Retail Goods"
        }
    ],
    "sg:phone":"+1 936 327 9880",
    "sg:postcode":"77351",
    "sg:province":"TX",
    "sg:tags":[
        "automobile",
        "parts"
    ],
    "sg:website":"www.oreillyauto.com",
    "wof:name":"O'Reilly Auto Parts",
    "wof:placetype":"venue"
},
  "geometry": {"coordinates":[-94.947115,30.710809],"type":"Point"}
}