{
  "type": "Feature",
  "properties": {
    "iso:country":"US",
    "sg:address":"30310 Charlie Ln",
    "sg:city":"Magnolia",
    "sg:classifiers":[
        {
            "category":"Building & Trades",
            "subcategory":"Landscaping Services",
            "type":"Services"
        },
        {
            "category":"Building & Trades",
            "subcategory":"Construction",
            "type":"Services"
        }
    ],
    "sg:phone":"+1 281 252 4727",
    "sg:postcode":"77355",
    "sg:province":"TX",
    "sg:tags":[
        "excavation",
        "landscape",
        "contractor"
    ],
    "wof:name":"Stuckey's Contract Service LP",
    "wof:placetype":"venue"
},
  "geometry": {"coordinates":[-95.741921,30.183237],"type":"Point"}
}