{
  "type": "Feature",
  "properties": {
    "iso:country":"US",
    "sg:address":"7801 N Lamar Blvd Svc Rd",
    "sg:city":"Austin",
    "sg:classifiers":[
        {
            "category":"Wholesale",
            "subcategory":"Electrical",
            "type":"Manufacturing & Wholesale Goods"
        }
    ],
    "sg:phone":"+1 512 371 0010",
    "sg:postcode":"78752",
    "sg:province":"TX",
    "sg:tags":[
        "industrial",
        "electronic"
    ],
    "wof:name":"G E A of Texas Inc",
    "wof:placetype":"venue"
},
  "geometry": {"coordinates":[-97.714338,30.344467],"type":"Point"}
}