{
  "type": "Feature",
  "properties": {
    "iso:country":"US",
    "sg:address":"5408 Duval St",
    "sg:city":"Austin",
    "sg:classifiers":[
        {
            "category":"Shopping",
            "type":"Retail Goods"
        }
    ],
    "sg:phone":"+1 512 452 2628",
    "sg:postcode":"78751",
    "sg:province":"TX",
    "sg:tags":[
        "merchandise"
    ],
    "wof:name":"R Davis Design",
    "wof:placetype":"venue"
},
  "geometry": {"coordinates":[-97.717215,30.318546],"type":"Point"}
}