{
  "type": "Feature",
  "properties": {
    "iso:country":"US",
    "sg:address":"2116 E Ledbetter Dr",
    "sg:city":"Dallas",
    "sg:classifiers":[
        {
            "category":"Fast Food",
            "type":"Food & Drink"
        },
        {
            "category":"Restaurant",
            "type":"Food & Drink"
        }
    ],
    "sg:phone":"+1 214 376 3337",
    "sg:postcode":"75216",
    "sg:province":"TX",
    "sg:tags":[
        "chicken",
        "wing",
        "pizza"
    ],
    "wof:name":"Wings Street",
    "wof:placetype":"venue"
},
  "geometry": {"coordinates":[-96.78822599999999,32.686466],"type":"Point"}
}