{
  "type": "Feature",
  "properties": {
    "iso:country":"US",
    "sg:address":"500 S Denton Tap Rd",
    "sg:city":"Coppell",
    "sg:classifiers":[
        {
            "category":"Real Estate",
            "subcategory":"Real Estate Agent",
            "type":"Services"
        }
    ],
    "sg:phone":"+1 972 393 9663",
    "sg:postcode":"75019",
    "sg:province":"TX",
    "wof:name":"Elaine Schauf",
    "wof:placetype":"venue"
},
  "geometry": {"coordinates":[-96.993493,32.95836],"type":"Point"}
}