{
  "type": "Feature",
  "properties": {
    "iso:country":"US",
    "sg:address":"300 W Walker St",
    "sg:city":"Breckenridge",
    "sg:classifiers":[
        {
            "category":"Autos & Motor Vehicles",
            "subcategory":"Automobile Sales",
            "type":"Retail Goods"
        }
    ],
    "sg:phone":"+1 254 559 2355",
    "sg:postcode":"76424",
    "sg:province":"TX",
    "sg:tags":[
        "car",
        "used"
    ],
    "wof:name":"Texas Longhorn Auto",
    "wof:placetype":"venue"
},
  "geometry": {"coordinates":[-98.883347,32.751942],"type":"Point"}
}