{
  "type": "Feature",
  "properties": {
    "iso:country":"US",
    "sg:address":"239 Greens Rd",
    "sg:city":"Houston",
    "sg:classifiers":[
        {
            "category":"Home & Garden",
            "subcategory":"Furniture",
            "type":"Retail Goods"
        }
    ],
    "sg:phone":"+1 713 221 4441",
    "sg:postcode":"77060",
    "sg:province":"TX",
    "sg:tags":[
        "mattress"
    ],
    "wof:name":"Finger Furniture Co",
    "wof:placetype":"venue"
},
  "geometry": {"coordinates":[-95.411674,29.950031],"type":"Point"}
}