{
  "type": "Feature",
  "properties": {
    "iso:country":"US",
    "sg:address":"5218 Silverberry Dr",
    "sg:city":"Corpus Christi",
    "sg:classifiers":[
        {
            "category":"Cinema",
            "subcategory":"Movie Theater",
            "type":"Entertainment"
        }
    ],
    "sg:phone":"+1 361 814 8518",
    "sg:postcode":"78416",
    "sg:province":"TX",
    "sg:tags":[
        "motion",
        "picture"
    ],
    "wof:name":"Cinemark Tinseltown Movies 16",
    "wof:placetype":"venue"
},
  "geometry": {"coordinates":[-97.43935399999999,27.740201],"type":"Point"}
}