{
  "type": "Feature",
  "properties": {
    "iso:country":"US",
    "sg:address":"1850 E Lowden St",
    "sg:city":"Abilene",
    "sg:classifiers":[
        {
            "category":"Social Services",
            "type":"Services"
        }
    ],
    "sg:phone":"+1 325 673 3346",
    "sg:postcode":"79601",
    "sg:province":"TX",
    "sg:tags":[
        "organization",
        "welfare"
    ],
    "wof:name":"Hill Resources Inc",
    "wof:placetype":"venue"
},
  "geometry": {"coordinates":[-99.692669,32.4818],"type":"Point"}
}