{
  "type": "Feature",
  "properties": {
    "iso:country":"US",
    "sg:address":"9323 Perrin Beitel Rd",
    "sg:city":"San Antonio",
    "sg:classifiers":[
        {
            "category":"Bars & Pubs",
            "type":"Food & Drink"
        }
    ],
    "sg:phone":"+1 210 650 5858",
    "sg:postcode":"78217",
    "sg:province":"TX",
    "sg:tags":[
        "drinking"
    ],
    "wof:name":"Kramersthe 5th Generation",
    "wof:placetype":"venue"
},
  "geometry": {"coordinates":[-98.411086,29.524564],"type":"Point"}
}