{
  "type": "Feature",
  "properties": {
    "iso:country":"US",
    "sg:address":"2410 Duhon Pl",
    "sg:city":"Seabrook",
    "sg:classifiers":[
        {
            "category":"Building & Trades",
            "subcategory":"Cleaning & Sanitation",
            "type":"Services"
        }
    ],
    "sg:phone":"+1 281 326 5418",
    "sg:postcode":"77586",
    "sg:province":"TX",
    "sg:tags":[
        "maintenance"
    ],
    "wof:name":"Admiral Window Cleaning",
    "wof:placetype":"venue"
},
  "geometry": {"coordinates":[-95.033676,29.572815],"type":"Point"}
}