{
  "type": "Feature",
  "properties": {
    "iso:country":"US",
    "sg:address":"2206 Jahan Trl",
    "sg:city":"Longview",
    "sg:classifiers":[
        {
            "category":"Shopping",
            "subcategory":"Used Merchandise",
            "type":"Retail Goods"
        }
    ],
    "sg:phone":"+1 903 297 7560",
    "sg:postcode":"75604",
    "sg:province":"TX",
    "sg:tags":[
        "book",
        "rare",
        "dealer"
    ],
    "sg:website":"www.booklocation.com",
    "wof:name":"Book Location",
    "wof:placetype":"venue"
},
  "geometry": {"coordinates":[-94.788659,32.526467],"type":"Point"}
}