{
  "type": "Feature",
  "properties": {
    "iso:country":"US",
    "sg:address":"107 Texas",
    "sg:city":"Temple",
    "sg:classifiers":[
        {
            "category":"Cinema",
            "subcategory":"Movie Rental",
            "type":"Entertainment"
        }
    ],
    "sg:phone":"+1 409 787 4707",
    "sg:postcode":"76501",
    "sg:province":"TX",
    "sg:tags":[
        "leasing",
        "video",
        "disc",
        "tape"
    ],
    "wof:name":"Showtime Videos",
    "wof:placetype":"venue"
},
  "geometry": {"coordinates":[-97.324348,31.114682],"type":"Point"}
}