{
  "type": "Feature",
  "properties": {
    "iso:country":"US",
    "sg:address":"8306 Forest Gate Dr",
    "sg:city":"Sugar Land",
    "sg:classifiers":[
        {
            "category":"Shopping",
            "subcategory":"Stationery & Office Supplies",
            "type":"Retail Goods"
        }
    ],
    "sg:phone":"+1 281 728 2684",
    "sg:postcode":"77479",
    "sg:province":"TX",
    "wof:name":"Southern Stationery",
    "wof:placetype":"venue"
},
  "geometry": {"coordinates":[-95.66894499999999,29.555475],"type":"Point"}
}