{
  "type": "Feature",
  "properties": {
    "iso:country":"US",
    "sg:address":"3907 Dyer St",
    "sg:city":"El Paso",
    "sg:classifiers":[
        {
            "category":"Restaurant",
            "type":"Food & Drink"
        }
    ],
    "sg:menulink":"http://www.allmenus.com/tx/el-paso/94537-dominos-pizza/menu/",
    "sg:phone":"+1 915 562 3500",
    "sg:postcode":"79930",
    "sg:province":"TX",
    "sg:tags":[
        "american",
        "wing",
        "pizza"
    ],
    "wof:name":"Domino's Pizza",
    "wof:placetype":"venue"
},
  "geometry": {"coordinates":[-106.44504499999999,31.811544],"type":"Point"}
}