{
  "type": "Feature",
  "properties": {
    "iso:country":"US",
    "sg:address":"1602 E Griffin Pkwy",
    "sg:city":"Mission",
    "sg:classifiers":[
        {
            "category":"Restaurant",
            "type":"Food & Drink"
        }
    ],
    "sg:phone":"+1 956 584 2249",
    "sg:postcode":"78572",
    "sg:province":"TX",
    "sg:tags":[
        "eating"
    ],
    "wof:name":"Quick Wok Restaurant",
    "wof:placetype":"venue"
},
  "geometry": {"coordinates":[-98.297213,26.225965],"type":"Point"}
}