{
  "type": "Feature",
  "properties": {
    "iso:country":"US",
    "sg:address":"4120 34th St",
    "sg:city":"Lubbock",
    "sg:classifiers":[
        {
            "category":"Shopping",
            "type":"Retail Goods"
        }
    ],
    "sg:phone":"+1 806 791 4770",
    "sg:postcode":"79410",
    "sg:province":"TX",
    "sg:tags":[
        "wedding",
        "supply"
    ],
    "wof:name":"Candlelight Wedding Rental",
    "wof:placetype":"venue"
},
  "geometry": {"coordinates":[-101.901432,33.563338],"type":"Point"}
}