{
  "type": "Feature",
  "properties": {
    "iso:country":"US",
    "sg:address":"212 W Irving Blvd",
    "sg:city":"Irving",
    "sg:classifiers":[
        {
            "category":"Manufacturing",
            "subcategory":"Food",
            "type":"Manufacturing & Wholesale Goods"
        },
        {
            "category":"Food & Beverages",
            "subcategory":"Specialty",
            "type":"Retail Goods"
        },
        {
            "category":"Food & Beverages",
            "subcategory":"Fruits & Vegetables",
            "type":"Retail Goods"
        }
    ],
    "sg:phone":"+1 972 259 3058",
    "sg:postcode":"75060",
    "sg:province":"TX",
    "sg:tags":[
        "product",
        "herb",
        "diet",
        "spices-wholesale",
        "health",
        "spice",
        "manufacturer"
    ],
    "wof:name":"The Herb Shoppe",
    "wof:placetype":"venue"
},
  "geometry": {"coordinates":[-96.94760100000001,32.81384],"type":"Point"}
}