{
  "type": "Feature",
  "properties": {
    "iso:country":"US",
    "sg:address":"620 E 2nd St",
    "sg:city":"Odessa",
    "sg:classifiers":[
        {
            "category":"Autos & Motor Vehicles",
            "subcategory":"Fuel & Gas Station",
            "type":"Retail Goods"
        }
    ],
    "sg:phone":"+1 432 337 0881",
    "sg:postcode":"79761",
    "sg:province":"TX",
    "sg:tags":[
        "station",
        "gasoline"
    ],
    "wof:name":"Ector Service Station",
    "wof:placetype":"venue"
},
  "geometry": {"coordinates":[-102.361445,31.848807],"type":"Point"}
}