{
  "type": "Feature",
  "properties": {
    "iso:country":"US",
    "sg:address":"1436 FM 1960 W",
    "sg:city":"Houston",
    "sg:classifiers":[
        {
            "category":"Shopping",
            "subcategory":"Clothing, Apparel, & Fashions",
            "type":"Retail Goods"
        }
    ],
    "sg:phone":"+1 281 440 7112",
    "sg:postcode":"77090",
    "sg:province":"TX",
    "sg:tags":[
        "wig",
        "toupee",
        "hairpiece"
    ],
    "wof:name":"D'Ann's Wig Salon",
    "wof:placetype":"venue"
},
  "geometry": {"coordinates":[-95.450799,30.014003],"type":"Point"}
}