{
  "type": "Feature",
  "properties": {
    "iso:country":"US",
    "sg:address":"940 E Henderson St",
    "sg:city":"Cleburne",
    "sg:classifiers":[
        {
            "category":"Shopping",
            "subcategory":"Discount & Variety Stores",
            "type":"Retail Goods"
        }
    ],
    "sg:phone":"+1 817 202 0603",
    "sg:postcode":"76031",
    "sg:province":"TX",
    "sg:tags":[
        "post",
        "trading"
    ],
    "wof:name":"Crows Trading Post",
    "wof:placetype":"venue"
},
  "geometry": {"coordinates":[-97.37399499999999,32.35085],"type":"Point"}
}