{
  "type": "Feature",
  "properties": {
    "iso:country":"US",
    "sg:address":"119 6th St",
    "sg:city":"Dickinson",
    "sg:classifiers":[
        {
            "category":"Retail",
            "subcategory":"Repair Shop",
            "type":"Services"
        }
    ],
    "sg:phone":"+1 281 339 2170",
    "sg:postcode":"77539",
    "sg:province":"TX",
    "wof:name":"Terrys Marine Service",
    "wof:placetype":"venue"
},
  "geometry": {"coordinates":[-94.915943,29.49501],"type":"Point"}
}