{
  "type": "Feature",
  "properties": {
    "iso:country":"US",
    "sg:address":"2114 26th St",
    "sg:city":"Lubbock",
    "sg:classifiers":[
        {
            "category":"Arts & Performance",
            "subcategory":"Theater",
            "type":"Entertainment"
        }
    ],
    "sg:phone":"+1 806 741 1369",
    "sg:postcode":"79411",
    "sg:province":"TX",
    "sg:tags":[
        "group"
    ],
    "wof:name":"Michael Newton",
    "wof:placetype":"venue"
},
  "geometry": {"coordinates":[-101.86273199999999,33.571083],"type":"Point"}
}