{
  "type": "Feature",
  "properties": {
    "iso:country":"US",
    "sg:address":"5533 US Hwy 277 S",
    "sg:city":"Abilene",
    "sg:classifiers":[
        {
            "category":"Insurance",
            "subcategory":"Insurance Agent",
            "type":"Services"
        }
    ],
    "sg:phone":"+1 325 691 5505",
    "sg:postcode":"79606",
    "sg:province":"TX",
    "wof:name":"Mike Barber Insurance",
    "wof:placetype":"venue"
},
  "geometry": {"coordinates":[-99.79441199999999,32.417753],"type":"Point"}
}