{
  "type": "Feature",
  "properties": {
    "iso:country":"US",
    "sg:address":"111 N 8th St",
    "sg:city":"Temple",
    "sg:classifiers":[
        {
            "category":"Building & Trades",
            "subcategory":"Landscaping Services",
            "type":"Services"
        }
    ],
    "sg:phone":"+1 254 791 0158",
    "sg:postcode":"76501",
    "sg:province":"TX",
    "wof:name":"Docs Lawn Care Service",
    "wof:placetype":"venue"
},
  "geometry": {"coordinates":[-97.33652600000001,31.097451],"type":"Point"}
}