{
  "type": "Feature",
  "properties": {
    "iso:country":"US",
    "sg:address":"23806 Brushy Trails St",
    "sg:city":"Hockley",
    "sg:classifiers":[
        {
            "category":"Wholesale",
            "subcategory":"Non-durable Goods",
            "type":"Manufacturing & Wholesale Goods"
        }
    ],
    "sg:phone":"+1 281 259 7772",
    "sg:postcode":"77447",
    "sg:province":"TX",
    "wof:name":"Moodwigs",
    "wof:placetype":"venue"
},
  "geometry": {"coordinates":[-95.787987,30.100621],"type":"Point"}
}