{
  "type": "Feature",
  "properties": {
    "iso:country":"US",
    "sg:address":"702 S Carter St",
    "sg:city":"Marshall",
    "sg:classifiers":[
        {
            "category":"Personal",
            "subcategory":"Beauty Salon",
            "type":"Services"
        }
    ],
    "sg:phone":"+1 903 923 8839",
    "sg:postcode":"75670",
    "sg:province":"TX",
    "sg:tags":[
        "shop"
    ],
    "wof:name":"Wilder's Beauty Salon",
    "wof:placetype":"venue"
},
  "geometry": {"coordinates":[-94.374031,32.538193],"type":"Point"}
}