{
  "type": "Feature",
  "properties": {
    "iso:country":"US",
    "sg:address":"8820 Bus Park Dr",
    "sg:city":"Austin",
    "sg:classifiers":[
        {
            "category":"Professional",
            "subcategory":"Accounting & Tax Preparation",
            "type":"Services"
        }
    ],
    "sg:phone":"+1 512 502 2454",
    "sg:postcode":"78759",
    "sg:province":"TX",
    "sg:tags":[
        "accountant"
    ],
    "wof:name":"Renee Clark CPA",
    "wof:placetype":"venue"
},
  "geometry": {"coordinates":[-97.741224,30.377803],"type":"Point"}
}