{
  "type": "Feature",
  "properties": {
    "iso:country":"US",
    "sg:address":"18179 Forest Cedars Dr",
    "sg:city":"Houston",
    "sg:classifiers":[
        {
            "category":"Building & Trades",
            "subcategory":"Construction",
            "type":"Services"
        }
    ],
    "sg:phone":"+1 281 859 1671",
    "sg:postcode":"77084",
    "sg:province":"TX",
    "sg:tags":[
        "hanging",
        "contractor"
    ],
    "wof:name":"P&R Painting Inc",
    "wof:placetype":"venue"
},
  "geometry": {"coordinates":[-95.68069800000001,29.857362],"type":"Point"}
}