{
  "type": "Feature",
  "properties": {
    "iso:country":"US",
    "sg:address":"805 Horizon Dr",
    "sg:city":"Plano",
    "sg:classifiers":[
        {
            "category":"Building & Trades",
            "subcategory":"Landscaping Services",
            "type":"Services"
        }
    ],
    "sg:phone":"+1 972 578 9483",
    "sg:postcode":"75094",
    "sg:province":"TX",
    "wof:name":"Texas Mow Time",
    "wof:placetype":"venue"
},
  "geometry": {"coordinates":[-96.60184700000001,32.994332],"type":"Point"}
}