{
  "type": "Feature",
  "properties": {
    "iso:country":"US",
    "sg:address":"13117 Green River Dr",
    "sg:city":"Houston",
    "sg:classifiers":[
        {
            "category":"Banks & Credit Unions",
            "subcategory":"Financial Services",
            "type":"Services"
        }
    ],
    "sg:phone":"+1 281 458 7020",
    "sg:postcode":"77044",
    "sg:province":"TX",
    "sg:tags":[
        "investor"
    ],
    "wof:name":"Mjf Investments LLC",
    "wof:placetype":"venue"
},
  "geometry": {"coordinates":[-95.197008,29.839671],"type":"Point"}
}