{
  "type": "Feature",
  "properties": {
    "iso:country":"US",
    "sg:address":"35 Muirfield Greens Ln",
    "sg:city":"Austin",
    "sg:classifiers":[
        {
            "category":"Wholesale",
            "subcategory":"Drugs",
            "type":"Manufacturing & Wholesale Goods"
        }
    ],
    "sg:phone":"+1 512 261 6982",
    "sg:postcode":"78738",
    "sg:province":"TX",
    "wof:name":"Liz Charbonnet",
    "wof:placetype":"venue"
},
  "geometry": {"coordinates":[-97.990859,30.35295],"type":"Point"}
}