{
  "type": "Feature",
  "properties": {
    "iso:country":"US",
    "sg:address":"300 Milam St Ste 130",
    "sg:city":"Houston",
    "sg:classifiers":[
        {
            "category":"Parking",
            "type":"Transportation"
        }
    ],
    "sg:phone":"+1 713 228 2088",
    "sg:postcode":"77002",
    "sg:province":"TX",
    "sg:website":"www.marketsquaregarage.com",
    "wof:name":"Market Square Garage",
    "wof:placetype":"venue"
},
  "geometry": {"coordinates":[-95.362583,29.763375],"type":"Point"}
}