{
  "type": "Feature",
  "properties": {
    "iso:country":"US",
    "sg:address":"17014 Tibet Rd",
    "sg:city":"Friendswood",
    "sg:classifiers":[
        {
            "category":"Shopping",
            "subcategory":"Computers & Home Electronics",
            "type":"Retail Goods"
        }
    ],
    "sg:phone":"+1 281 992 2760",
    "sg:postcode":"77546",
    "sg:province":"TX",
    "wof:name":"Roaming Air",
    "wof:placetype":"venue"
},
  "geometry": {"coordinates":[-95.175314,29.52674],"type":"Point"}
}