{
  "type": "Feature",
  "properties": {
    "iso:country":"US",
    "sg:address":"1009 W Main St",
    "sg:city":"Little River",
    "sg:classifiers":[
        {
            "category":"Professional",
            "type":"Services"
        }
    ],
    "sg:phone":"+1 254 982 4448",
    "sg:postcode":"76554",
    "sg:province":"TX",
    "sg:tags":[
        "establishment"
    ],
    "wof:name":"Centel",
    "wof:placetype":"venue"
},
  "geometry": {"coordinates":[-97.364491,30.988177],"type":"Point"}
}