{
  "type": "Feature",
  "properties": {
    "iso:country":"US",
    "sg:address":"416 W 9th St",
    "sg:city":"Mission",
    "sg:classifiers":[
        {
            "category":"Personal",
            "subcategory":"Beauty Salon",
            "type":"Services"
        }
    ],
    "sg:phone":"+1 956 585 8787",
    "sg:postcode":"78572",
    "sg:province":"TX",
    "wof:name":"Alicia's Magic Mirror",
    "wof:placetype":"venue"
},
  "geometry": {"coordinates":[-98.329063,26.21539],"type":"Point"}
}