{
  "type": "Feature",
  "properties": {
    "iso:country":"US",
    "sg:address":"6812 Ranch Road 620 N",
    "sg:city":"Austin",
    "sg:classifiers":[
        {
            "category":"Restaurant",
            "type":"Food & Drink"
        }
    ],
    "sg:menulink":"http://www.allmenus.com/tx/travis-northwest/14590-boat-house-grill/menu/",
    "sg:phone":"+1 512 249 5200",
    "sg:postcode":"78732",
    "sg:province":"TX",
    "sg:tags":[
        "american"
    ],
    "wof:name":"Boat House Grill",
    "wof:placetype":"venue"
},
  "geometry": {"coordinates":[-97.856331,30.399278],"type":"Point"}
}