{
  "type": "Feature",
  "properties": {
    "iso:country":"US",
    "sg:address":"18707 Long Trace Dr",
    "sg:city":"Humble",
    "sg:classifiers":[
        {
            "category":"Professional",
            "subcategory":"Business Services",
            "type":"Services"
        }
    ],
    "sg:phone":"+1 281 852 4533",
    "sg:postcode":"77346",
    "sg:province":"TX",
    "wof:name":"Ameritex Property Inspectors",
    "wof:placetype":"venue"
},
  "geometry": {"coordinates":[-95.168341,29.990037],"type":"Point"}
}