{
  "type": "Feature",
  "properties": {
    "iso:country":"US",
    "sg:address":"7513 Folkstone Dr",
    "sg:city":"Fort Worth",
    "sg:classifiers":[
        {
            "category":"Freight",
            "type":"Transportation"
        }
    ],
    "sg:phone":"+1 817 478 9566",
    "sg:postcode":"76140",
    "sg:province":"TX",
    "sg:tags":[
        "operator",
        "local",
        "trucking"
    ],
    "wof:name":"Julius Castle",
    "wof:placetype":"venue"
},
  "geometry": {"coordinates":[-97.26682,32.649468],"type":"Point"}
}