{
  "type": "Feature",
  "properties": {
    "iso:country":"US",
    "sg:address":"5434 Old US Hwy 90 W",
    "sg:city":"San Antonio",
    "sg:classifiers":[
        {
            "category":"Retail",
            "subcategory":"Auto Repair",
            "type":"Services"
        }
    ],
    "sg:phone":"+1 210 436 5990",
    "sg:postcode":"78227",
    "sg:province":"TX",
    "sg:tags":[
        "repairing",
        "tire"
    ],
    "wof:name":"A & A Tire Svc",
    "wof:placetype":"venue"
},
  "geometry": {"coordinates":[-98.599321,29.41536],"type":"Point"}
}