{
  "type": "Feature",
  "properties": {
    "iso:country":"US",
    "sg:address":"2843 Fernwood Ave",
    "sg:city":"Dallas",
    "sg:classifiers":[
        {
            "category":"Building & Trades",
            "subcategory":"Construction",
            "type":"Services"
        }
    ],
    "sg:phone":"+1 214 372 6243",
    "sg:postcode":"75216",
    "sg:province":"TX",
    "sg:tags":[
        "hanging",
        "contractor"
    ],
    "wof:name":"Fast Painting",
    "wof:placetype":"venue"
},
  "geometry": {"coordinates":[-96.808324,32.711867],"type":"Point"}
}