{
  "type": "Feature",
  "properties": {
    "iso:country":"US",
    "sg:address":"3680 College St",
    "sg:city":"Beaumont",
    "sg:classifiers":[
        {
            "category":"Wholesale",
            "subcategory":"Medical Equipment & Supplies",
            "type":"Manufacturing & Wholesale Goods"
        }
    ],
    "sg:phone":"+1 409 833 2300",
    "sg:postcode":"77701",
    "sg:province":"TX",
    "sg:tags":[
        "physician",
        "surgeon"
    ],
    "wof:name":"Liberty EMS",
    "wof:placetype":"venue"
},
  "geometry": {"coordinates":[-94.132411,30.068311],"type":"Point"}
}