{
  "type": "Feature",
  "properties": {
    "iso:country":"US",
    "sg:address":"2836 Walnut Hill Ln",
    "sg:city":"Dallas",
    "sg:classifiers":[
        {
            "category":"Shopping",
            "subcategory":"Optician",
            "type":"Retail Goods"
        }
    ],
    "sg:phone":"+1 214 358 4433",
    "sg:postcode":"75229",
    "sg:province":"TX",
    "sg:tags":[
        "eyewear"
    ],
    "wof:name":"C & H Contact Lens Inc",
    "wof:placetype":"venue"
},
  "geometry": {"coordinates":[-96.88249999999999,32.880798],"type":"Point"}
}