{
  "type": "Feature",
  "properties": {
    "iso:country":"US",
    "sg:address":"500 Cripple Creek Dr",
    "sg:city":"Euless",
    "sg:classifiers":[
        {
            "category":"Professional",
            "type":"Services"
        }
    ],
    "sg:phone":"+1 817 545 4951",
    "sg:postcode":"76039",
    "sg:province":"TX",
    "wof:name":"Ed Hickman",
    "wof:placetype":"venue"
},
  "geometry": {"coordinates":[-97.090521,32.864745],"type":"Point"}
}