{
  "type": "Feature",
  "properties": {
    "iso:country":"US",
    "sg:address":"901 S Mopac Expy Plaza One, Ste 300",
    "sg:city":"Austin",
    "sg:classifiers":[
        {
            "category":"Professional",
            "subcategory":"Lawyer & Legal Services",
            "type":"Services"
        }
    ],
    "sg:phone":"+1 866 413 2868",
    "sg:postcode":"78746",
    "sg:province":"TX",
    "sg:website":"www.sapiresearch.com",
    "wof:name":"Sapire Search Group",
    "wof:placetype":"venue"
},
  "geometry": {"coordinates":[-97.780478,30.26618],"type":"Point"}
}