{
  "type": "Feature",
  "properties": {
    "iso:country":"US",
    "sg:address":"412 Grassland Ln",
    "sg:city":"Georgetown",
    "sg:classifiers":[
        {
            "category":"Building & Trades",
            "subcategory":"Plumbing",
            "type":"Services"
        },
        {
            "category":"Building & Trades",
            "subcategory":"Cleaning & Sanitation",
            "type":"Services"
        }
    ],
    "sg:phone":"+1 866 909 9565",
    "sg:postcode":"78628",
    "sg:province":"TX",
    "sg:tags":[
        "cleaner",
        "plumber",
        "sewer",
        "plumbing-drain",
        "repairer"
    ],
    "wof:name":"Affordable Plus Plumbing",
    "wof:placetype":"venue"
},
  "geometry": {"coordinates":[-97.704363,30.650981],"type":"Point"}
}