{
  "type": "Feature",
  "properties": {
    "iso:country":"US",
    "sg:address":"4 W Main St",
    "sg:city":"Troy",
    "sg:classifiers":[
        {
            "category":"Food & Beverages",
            "subcategory":"Groceries & Convenience Stores",
            "type":"Retail Goods"
        }
    ],
    "sg:phone":"+1 254 938 2900",
    "sg:postcode":"76579",
    "sg:province":"TX",
    "wof:name":"E-Z Way",
    "wof:placetype":"venue"
},
  "geometry": {"coordinates":[-97.303793,31.207226],"type":"Point"}
}