{
  "type": "Feature",
  "properties": {
    "iso:country":"US",
    "sg:address":"1033 E Goode St",
    "sg:city":"Quitman",
    "sg:classifiers":[
        {
            "category":"Food & Beverages",
            "subcategory":"Bakery",
            "type":"Retail Goods"
        }
    ],
    "sg:phone":"+1 903 763 0434",
    "sg:postcode":"75783",
    "sg:province":"TX",
    "sg:tags":[
        "doughnut"
    ],
    "wof:name":"Donut Palace",
    "wof:placetype":"venue"
},
  "geometry": {"coordinates":[-95.434248,32.795882],"type":"Point"}
}