{
  "type": "Feature",
  "properties": {
    "iso:country":"US",
    "sg:address":"7212 Westover Rd",
    "sg:city":"Waco",
    "sg:classifiers":[
        {
            "category":"Professional",
            "subcategory":"Business Services",
            "type":"Services"
        }
    ],
    "sg:phone":"+1 254 776 4013",
    "sg:postcode":"76710",
    "sg:province":"TX",
    "wof:name":"Chase Enterprises",
    "wof:placetype":"venue"
},
  "geometry": {"coordinates":[-97.217085,31.529503],"type":"Point"}
}