{
  "type": "Feature",
  "properties": {
    "iso:country":"US",
    "sg:address":"3637 Timberglen Rd Suite 6111",
    "sg:city":"Dallas",
    "sg:classifiers":[
        {
            "category":"Shopping",
            "subcategory":"Computers & Home Electronics",
            "type":"Retail Goods"
        }
    ],
    "sg:phone":"+1 972 820 9098",
    "sg:postcode":"75287",
    "sg:province":"TX",
    "sg:tags":[
        "hardware",
        "supply"
    ],
    "wof:name":"Wise Buys- Usa .com,inc",
    "wof:placetype":"venue"
},
  "geometry": {"coordinates":[-96.851868,33.000221],"type":"Point"}
}