{
  "type": "Feature",
  "properties": {
    "iso:country":"US",
    "sg:address":"6975 Portwest Dr",
    "sg:city":"Houston",
    "sg:classifiers":[
        {
            "category":"Building & Trades",
            "subcategory":"Construction",
            "type":"Services"
        }
    ],
    "sg:phone":"+1 713 467 9840",
    "sg:postcode":"77024",
    "sg:province":"TX",
    "sg:tags":[
        "consultant"
    ],
    "wof:name":"Building Exterior Solutions",
    "wof:placetype":"venue"
},
  "geometry": {"coordinates":[-95.449989,29.781298],"type":"Point"}
}