{
  "type": "Feature",
  "properties": {
    "iso:country":"US",
    "sg:address":"192 Edmonson Ranch Rd",
    "sg:city":"Cedar Creek",
    "sg:classifiers":[
        {
            "category":"Shopping",
            "subcategory":"Used Merchandise",
            "type":"Retail Goods"
        }
    ],
    "sg:phone":"+1 512 308 9234",
    "sg:postcode":"78650",
    "sg:province":"TX",
    "wof:name":"Marthas Treasure Trove",
    "wof:placetype":"venue"
},
  "geometry": {"coordinates":[-97.199,30.305363],"type":"Point"}
}