{
  "type": "Feature",
  "properties": {
    "iso:country":"US",
    "sg:address":"2045 Salem St",
    "sg:city":"Irving",
    "sg:classifiers":[
        {
            "category":"Professional",
            "type":"Services"
        }
    ],
    "sg:phone":"+1 972 986 5336",
    "sg:postcode":"75061",
    "sg:province":"TX",
    "wof:name":"Pedro Soria Jr",
    "wof:placetype":"venue"
},
  "geometry": {"coordinates":[-96.97957700000001,32.83599],"type":"Point"}
}