{
  "type": "Feature",
  "properties": {
    "iso:country":"US",
    "sg:address":"711 Airway Dr",
    "sg:city":"Fort Worth",
    "sg:classifiers":[
        {
            "category":"Retail",
            "subcategory":"Auto Rental",
            "type":"Services"
        }
    ],
    "sg:phone":"+1 817 624 3650",
    "sg:postcode":"76106",
    "sg:province":"TX",
    "sg:tags":[
        "passenger",
        "leasing",
        "truck",
        "car",
        "mfg"
    ],
    "wof:name":"Fleet Body Equipment",
    "wof:placetype":"venue"
},
  "geometry": {"coordinates":[-97.34557599999999,32.831104],"type":"Point"}
}