{
  "type": "Feature",
  "properties": {
    "iso:country":"US",
    "sg:address":"300 N Hampton Rd",
    "sg:city":"Desoto",
    "sg:classifiers":[
        {
            "category":"Retail",
            "subcategory":"Auto Repair",
            "type":"Services"
        }
    ],
    "sg:phone":"+1 972 274 1044",
    "sg:postcode":"75115",
    "sg:province":"TX",
    "wof:name":"Rising Sun Automotive",
    "wof:placetype":"venue"
},
  "geometry": {"coordinates":[-96.856903,32.593399],"type":"Point"}
}