{
  "type": "Feature",
  "properties": {
    "iso:country":"US",
    "sg:address":"5421 E Grand Ave",
    "sg:city":"Dallas",
    "sg:classifiers":[
        {
            "category":"Autos & Motor Vehicles",
            "subcategory":"Automobile Sales",
            "type":"Retail Goods"
        }
    ],
    "sg:phone":"+1 214 275 9933",
    "sg:postcode":"75223",
    "sg:province":"TX",
    "sg:tags":[
        "used"
    ],
    "wof:name":"J & E Auto Wholesale",
    "wof:placetype":"venue"
},
  "geometry": {"coordinates":[-96.748428,32.792855],"type":"Point"}
}