{
  "type": "Feature",
  "properties": {
    "iso:country":"US",
    "sg:address":"28 W Hillside Pl",
    "sg:city":"Roanoke",
    "sg:classifiers":[
        {
            "category":"Professional",
            "type":"Services"
        }
    ],
    "sg:phone":"+1 817 430 0934",
    "sg:postcode":"76262",
    "sg:province":"TX",
    "wof:name":"Brierton Kompus Designs",
    "wof:placetype":"venue"
},
  "geometry": {"coordinates":[-97.177094,32.999724],"type":"Point"}
}