{
  "type": "Feature",
  "properties": {
    "iso:country":"US",
    "sg:address":"338 Shropshire Dr",
    "sg:city":"San Antonio",
    "sg:classifiers":[
        {
            "category":"Building & Trades",
            "subcategory":"Electrical",
            "type":"Services"
        }
    ],
    "sg:phone":"+1 210 829 7013",
    "sg:postcode":"78217",
    "sg:province":"TX",
    "sg:tags":[
        "electric",
        "contractor"
    ],
    "wof:name":"Elliott Enterprises",
    "wof:placetype":"venue"
},
  "geometry": {"coordinates":[-98.451302,29.522153],"type":"Point"}
}