{
  "type": "Feature",
  "properties": {
    "iso:country":"US",
    "sg:address":"5311 S Lamar St",
    "sg:city":"Dallas",
    "sg:classifiers":[
        {
            "category":"Wholesale",
            "subcategory":"Auto Parts",
            "type":"Manufacturing & Wholesale Goods"
        }
    ],
    "sg:phone":"+1 214 428 7727",
    "sg:postcode":"75215",
    "sg:province":"TX",
    "sg:tags":[
        "automobile",
        "rebuilt"
    ],
    "wof:name":"Greenleaf Dallas",
    "wof:placetype":"venue"
},
  "geometry": {"coordinates":[-96.759674,32.743725],"type":"Point"}
}