{
  "type": "Feature",
  "properties": {
    "iso:country":"US",
    "sg:address":"1514 US Hwy 281",
    "sg:city":"Marble Falls",
    "sg:classifiers":[
        {
            "category":"Insurance",
            "subcategory":"Hazard Insurance",
            "type":"Services"
        },
        {
            "category":"Insurance",
            "subcategory":"Insurance Agent",
            "type":"Services"
        }
    ],
    "sg:phone":"+1 830 693 6179",
    "sg:postcode":"78654",
    "sg:province":"TX",
    "sg:tags":[
        "casualty",
        "real estate"
    ],
    "wof:name":"Ida Mae Tunnell Insurance",
    "wof:placetype":"venue"
},
  "geometry": {"coordinates":[-98.285903,30.525976],"type":"Point"}
}