{
  "type": "Feature",
  "properties": {
    "iso:country":"US",
    "sg:address":"1821 W Anderson Ln",
    "sg:city":"Austin",
    "sg:classifiers":[
        {
            "category":"Health Services",
            "subcategory":"Clinic",
            "type":"Services"
        }
    ],
    "sg:phone":"+1 512 345 0631",
    "sg:postcode":"78757",
    "sg:province":"TX",
    "sg:tags":[
        "home",
        "care"
    ],
    "wof:name":"Touch of Class",
    "wof:placetype":"venue"
},
  "geometry": {"coordinates":[-97.72587300000001,30.353674],"type":"Point"}
}