{
  "type": "Feature",
  "properties": {
    "iso:country":"US",
    "sg:address":"2712 6th Ave",
    "sg:city":"Amarillo",
    "sg:classifiers":[
        {
            "category":"Wholesale",
            "subcategory":"Home Furnishings",
            "type":"Manufacturing & Wholesale Goods"
        }
    ],
    "sg:phone":"+1 806 373 6693",
    "sg:postcode":"79106",
    "sg:province":"TX",
    "wof:name":"Professional Drapery Wholesale",
    "wof:placetype":"venue"
},
  "geometry": {"coordinates":[-101.86735400000001,35.211371],"type":"Point"}
}