{
  "type": "Feature",
  "properties": {
    "iso:country":"US",
    "sg:address":"6255 Frisco Square Blvd",
    "sg:city":"Frisco",
    "sg:classifiers":[
        {
            "category":"Real Estate",
            "subcategory":"Real Estate Services",
            "type":"Services"
        },
        {
            "category":"Shopping Center",
            "type":"Public Place"
        }
    ],
    "sg:phone":"+1 972 668 5000",
    "sg:postcode":"75034",
    "sg:province":"TX",
    "sg:tags":[
        "mall",
        "management"
    ],
    "wof:name":"The Residences at Frisco Square",
    "wof:placetype":"venue"
},
  "geometry": {"coordinates":[-96.83415100000001,33.15054],"type":"Point"}
}