{
  "type": "Feature",
  "properties": {
    "iso:country":"US",
    "sg:address":"1355 Basse Rd",
    "sg:city":"San Antonio",
    "sg:classifiers":[
        {
            "category":"Building & Trades",
            "subcategory":"Construction",
            "type":"Services"
        }
    ],
    "sg:phone":"+1 210 341 5560",
    "sg:postcode":"78212",
    "sg:province":"TX",
    "sg:tags":[
        "house"
    ],
    "wof:name":"American Best Home Improvement",
    "wof:placetype":"venue"
},
  "geometry": {"coordinates":[-98.50689199999999,29.488236],"type":"Point"}
}