{
  "type": "Feature",
  "properties": {
    "iso:country":"US",
    "sg:address":"4800 Research Forest Dr",
    "sg:city":"Spring",
    "sg:classifiers":[
        {
            "category":"Real Estate",
            "subcategory":"Real Estate Agent",
            "type":"Services"
        }
    ],
    "sg:phone":"+1 214 571 1669",
    "sg:postcode":"77381",
    "sg:province":"TX",
    "wof:name":"First American RE Info Svcs",
    "wof:placetype":"venue"
},
  "geometry": {"coordinates":[-95.500945,30.195859],"type":"Point"}
}