{
  "type": "Feature",
  "properties": {
    "iso:country":"US",
    "sg:address":"1001 E Moore Ave",
    "sg:city":"Terrell",
    "sg:classifiers":[
        {
            "category":"Retail",
            "subcategory":"Auto Repair",
            "type":"Services"
        }
    ],
    "sg:phone":"+1 972 524 2744",
    "sg:postcode":"75160",
    "sg:province":"TX",
    "sg:tags":[
        "recreational",
        "vehicle"
    ],
    "wof:name":"Kaufman County Cycles & Atv's",
    "wof:placetype":"venue"
},
  "geometry": {"coordinates":[-96.26371399999999,32.734764],"type":"Point"}
}