{
  "type": "Feature",
  "properties": {
    "iso:country":"US",
    "sg:address":"4013 Clay Ave",
    "sg:city":"Fort Worth",
    "sg:classifiers":[
        {
            "category":"Wholesale",
            "subcategory":"Machinery & Supplies",
            "type":"Manufacturing & Wholesale Goods"
        },
        {
            "category":"Wholesale",
            "subcategory":"Electrical",
            "type":"Manufacturing & Wholesale Goods"
        }
    ],
    "sg:phone":"+1 817 605 9267",
    "sg:postcode":"76117",
    "sg:province":"TX",
    "sg:tags":[
        "industrial",
        "meter"
    ],
    "wof:name":"Primary Flow Products Inc",
    "wof:placetype":"venue"
},
  "geometry": {"coordinates":[-97.281982,32.829226],"type":"Point"}
}