{
  "type": "Feature",
  "properties": {
    "iso:country":"US",
    "sg:address":"15295 Runnymede St",
    "sg:city":"Conroe",
    "sg:classifiers":[
        {
            "category":"Building & Trades",
            "subcategory":"Construction",
            "type":"Services"
        }
    ],
    "sg:phone":"+1 936 273 5957",
    "sg:postcode":"77384",
    "sg:province":"TX",
    "sg:tags":[
        "house"
    ],
    "wof:name":"Whitakers Home Repair",
    "wof:placetype":"venue"
},
  "geometry": {"coordinates":[-95.54041599999999,30.237877],"type":"Point"}
}