{
  "type": "Feature",
  "properties": {
    "iso:country":"US",
    "sg:address":"5749 Cleveland Ave",
    "sg:city":"El Paso",
    "sg:classifiers":[
        {
            "category":"Retail",
            "subcategory":"Repair Shop",
            "type":"Services"
        }
    ],
    "sg:phone":"+1 915 855 1908",
    "sg:postcode":"79925",
    "sg:province":"TX",
    "sg:tags":[
        "watch",
        "jewelry",
        "clock"
    ],
    "wof:name":"Dunkin Donuts",
    "wof:placetype":"venue"
},
  "geometry": {"coordinates":[-106.419443,31.780469],"type":"Point"}
}