{
  "type": "Feature",
  "properties": {
    "iso:country":"US",
    "sg:address":"1006 11th St",
    "sg:city":"Huntsville",
    "sg:classifiers":[
        {
            "category":"Wholesale",
            "subcategory":"Painting Supplies",
            "type":"Manufacturing & Wholesale Goods"
        },
        {
            "category":"Retail",
            "subcategory":"Repair Shop",
            "type":"Services"
        },
        {
            "category":"Manufacturing",
            "subcategory":"Tools & Machinery",
            "type":"Manufacturing & Wholesale Goods"
        },
        {
            "category":"Home & Garden",
            "subcategory":"Hardware",
            "type":"Retail Goods"
        },
        {
            "category":"Home & Garden",
            "subcategory":"Building Materials",
            "type":"Retail Goods"
        },
        {
            "category":"Wholesale",
            "subcategory":"Hardware",
            "type":"Manufacturing & Wholesale Goods"
        },
        {
            "category":"Home & Garden",
            "subcategory":"Garden Supply",
            "type":"Retail Goods"
        }
    ],
    "sg:phone":"+1 936 295 7751",
    "sg:postcode":"77340",
    "sg:province":"TX",
    "sg:tags":[
        "renting",
        "lawn",
        "outdoor",
        "power",
        "equipment",
        "equipment-sales",
        "landscaping",
        "saw",
        "paint",
        "store"
    ],
    "sg:website":"http://www.stihldealer.net/default-dealer-042139.aspx",
    "wof:name":"Walker County Hardware, Inc.",
    "wof:placetype":"venue"
},
  "geometry": {"coordinates":[-95.549519,30.723779],"type":"Point"}
}