{
  "type": "Feature",
  "properties": {
    "iso:country":"US",
    "sg:address":"2302 W Ave N",
    "sg:city":"San Angelo",
    "sg:classifiers":[
        {
            "category":"Retail",
            "subcategory":"Auto Repair",
            "type":"Services"
        }
    ],
    "sg:phone":"+1 325 944 4918",
    "sg:postcode":"76904",
    "sg:province":"TX",
    "sg:tags":[
        "repairing",
        "automobile",
        "general"
    ],
    "wof:name":"Tony's Garage",
    "wof:placetype":"venue"
},
  "geometry": {"coordinates":[-100.460482,31.443127],"type":"Point"}
}