{
  "type": "Feature",
  "properties": {
    "iso:country":"US",
    "sg:address":"18850 S Memorial Dr",
    "sg:city":"Humble",
    "sg:classifiers":[
        {
            "category":"Health Services",
            "subcategory":"Doctor",
            "type":"Services"
        }
    ],
    "sg:phone":"+1 281 446 7900",
    "sg:postcode":"77338",
    "sg:province":"TX",
    "sg:tags":[
        "clinic"
    ],
    "sg:website":"www.manneye.com",
    "wof:name":"Mann Eye Institute",
    "wof:placetype":"venue"
},
  "geometry": {"coordinates":[-95.27582099999999,29.993472],"type":"Point"}
}