{
  "type": "Feature",
  "properties": {
    "iso:country":"US",
    "sg:address":"1300 N Sylvania Ave",
    "sg:city":"Fort Worth",
    "sg:classifiers":[
        {
            "category":"Food & Beverages",
            "subcategory":"Groceries & Convenience Stores",
            "type":"Retail Goods"
        }
    ],
    "sg:phone":"+1 817 831 8726",
    "sg:postcode":"76111",
    "sg:province":"TX",
    "wof:name":"E Z Shop",
    "wof:placetype":"venue"
},
  "geometry": {"coordinates":[-97.308576,32.781819],"type":"Point"}
}