{
  "type": "Feature",
  "properties": {
    "iso:country":"US",
    "sg:address":"10906 Allison Bend Ct",
    "sg:city":"Houston",
    "sg:classifiers":[
        {
            "category":"Professional",
            "type":"Services"
        }
    ],
    "sg:phone":"+1 281 580 8242",
    "sg:postcode":"77086",
    "sg:province":"TX",
    "wof:name":"Loop T Luus",
    "wof:placetype":"venue"
},
  "geometry": {"coordinates":[-95.502205,29.936467],"type":"Point"}
}