{
  "type": "Feature",
  "properties": {
    "iso:country":"US",
    "sg:address":"3164 Springfield Ave",
    "sg:city":"Lancaster",
    "sg:classifiers":[
        {
            "category":"Freight",
            "type":"Transportation"
        }
    ],
    "sg:phone":"+1 469 567 4799",
    "sg:postcode":"75134",
    "sg:province":"TX",
    "sg:tags":[
        "trucking"
    ],
    "wof:name":"Gemini Traffic Sales",
    "wof:placetype":"venue"
},
  "geometry": {"coordinates":[-96.818223,32.636859],"type":"Point"}
}