{
  "type": "Feature",
  "properties": {
    "iso:country":"US",
    "sg:address":"11139 N I H 35",
    "sg:city":"Austin",
    "sg:classifiers":[
        {
            "category":"Restaurant",
            "type":"Food & Drink"
        }
    ],
    "sg:phone":"+1 512 339 6577",
    "sg:postcode":"78753",
    "sg:province":"TX",
    "wof:name":"Quizno's Sub Braker",
    "wof:placetype":"venue"
},
  "geometry": {"coordinates":[-97.676698,30.375342],"type":"Point"}
}