{
  "type": "Feature",
  "properties": {
    "iso:country":"US",
    "sg:address":"12300 Ford Rd Ste 425",
    "sg:city":"Dallas",
    "sg:classifiers":[
        {
            "category":"Wholesale",
            "subcategory":"Medical Equipment & Supplies",
            "type":"Manufacturing & Wholesale Goods"
        }
    ],
    "sg:phone":"+1 972 931 1950",
    "sg:postcode":"75234",
    "sg:province":"TX",
    "sg:tags":[
        "surgical",
        "appliance"
    ],
    "wof:name":"Medex Surgical",
    "wof:placetype":"venue"
},
  "geometry": {"coordinates":[-96.89138800000001,32.914639],"type":"Point"}
}