{
  "type": "Feature",
  "properties": {
    "iso:country":"US",
    "sg:address":"971 E Sanford St",
    "sg:city":"Arlington",
    "sg:classifiers":[
        {
            "category":"Social Services",
            "type":"Services"
        }
    ],
    "sg:phone":"+1 817 861 9756",
    "sg:postcode":"76011",
    "sg:province":"TX",
    "wof:name":"Invisible Citizen",
    "wof:placetype":"venue"
},
  "geometry": {"coordinates":[-97.087559,32.74281],"type":"Point"}
}