{
  "type": "Feature",
  "properties": {
    "iso:country":"US",
    "sg:address":"37 Amethyst Cove",
    "sg:city":"Odessa",
    "sg:classifiers":[
        {
            "category":"Health Services",
            "subcategory":"Doctor",
            "type":"Services"
        }
    ],
    "sg:phone":"+1 432 550 2440",
    "sg:postcode":"79762",
    "sg:province":"TX",
    "sg:tags":[
        "medical"
    ],
    "wof:name":"Midessa Perfusion Service",
    "wof:placetype":"venue"
},
  "geometry": {"coordinates":[-102.304289,31.896019],"type":"Point"}
}