{
  "type": "Feature",
  "properties": {
    "iso:country":"US",
    "sg:address":"3701 W Northwest Hwy",
    "sg:city":"Dallas",
    "sg:classifiers":[
        {
            "category":"Shopping",
            "subcategory":"Department Store",
            "type":"Retail Goods"
        },
        {
            "category":"Shopping",
            "subcategory":"Clothing, Apparel, & Fashions",
            "type":"Retail Goods"
        }
    ],
    "sg:phone":"+1 214 350 5796",
    "sg:postcode":"75220",
    "sg:province":"TX",
    "sg:tags":[
        "family"
    ],
    "sg:website":"www.fallasparedes.com",
    "wof:name":"Fallas Paredes",
    "wof:placetype":"venue"
},
  "geometry": {"coordinates":[-96.85724399999999,32.860399],"type":"Point"}
}