{
  "type": "Feature",
  "properties": {
    "iso:country":"US",
    "sg:address":"6502 Alameda Ave",
    "sg:city":"El Paso",
    "sg:classifiers":[
        {
            "category":"Home & Garden",
            "subcategory":"Building Materials",
            "type":"Retail Goods"
        }
    ],
    "sg:phone":"+1 915 779 8160",
    "sg:postcode":"79905",
    "sg:province":"TX",
    "sg:tags":[
        "glass",
        "window",
        "plate"
    ],
    "wof:name":"Cuba Motor & Windshields",
    "wof:placetype":"venue"
},
  "geometry": {"coordinates":[-106.407207,31.764358],"type":"Point"}
}