{
  "type": "Feature",
  "properties": {
    "iso:country":"US",
    "sg:address":"5519 Lawndale St",
    "sg:city":"Houston",
    "sg:classifiers":[
        {
            "category":"Home & Garden",
            "subcategory":"Furniture",
            "type":"Retail Goods"
        }
    ],
    "sg:phone":"+1 713 928 6833",
    "sg:postcode":"77023",
    "sg:province":"TX",
    "wof:name":"Blanco Savers",
    "wof:placetype":"venue"
},
  "geometry": {"coordinates":[-95.319118,29.727206],"type":"Point"}
}