{
  "type": "Feature",
  "properties": {
    "iso:country":"US",
    "sg:address":"7331 Gaston Ave",
    "sg:city":"Dallas",
    "sg:classifiers":[
        {
            "category":"Cinema",
            "subcategory":"Movie Theater",
            "type":"Entertainment"
        }
    ],
    "sg:phone":"+1 214 324 5430",
    "sg:postcode":"75214",
    "sg:province":"TX",
    "wof:name":"Arena Theater",
    "wof:placetype":"venue"
},
  "geometry": {"coordinates":[-96.73070300000001,32.811994],"type":"Point"}
}