{
  "type": "Feature",
  "properties": {
    "iso:country":"US",
    "sg:address":"14902 Preston Rd",
    "sg:city":"Dallas",
    "sg:classifiers":[
        {
            "category":"Restaurant",
            "type":"Food & Drink"
        }
    ],
    "sg:phone":"+1 972 763 0615",
    "sg:postcode":"75254",
    "sg:province":"TX",
    "sg:tags":[
        "mexican"
    ],
    "wof:name":"Sona Rosa Mexican Restaurant",
    "wof:placetype":"venue"
},
  "geometry": {"coordinates":[-96.803596,32.9524],"type":"Point"}
}