{
  "type": "Feature",
  "properties": {
    "iso:country":"US",
    "sg:address":"4408 Spicewood Springs Rd",
    "sg:city":"Austin",
    "sg:classifiers":[
        {
            "category":"Professional",
            "subcategory":"Lawyer & Legal Services",
            "type":"Services"
        }
    ],
    "sg:phone":"+1 512 343 9141",
    "sg:postcode":"78759",
    "sg:province":"TX",
    "sg:tags":[
        "law"
    ],
    "wof:name":"Richey & Young PC",
    "wof:placetype":"venue"
},
  "geometry": {"coordinates":[-97.759264,30.374403],"type":"Point"}
}