{
  "type": "Feature",
  "properties": {
    "iso:country":"US",
    "sg:address":"2327 Park St",
    "sg:city":"Ennis",
    "sg:classifiers":[
        {
            "category":"Banks & Credit Unions",
            "subcategory":"Investment Brokerage",
            "type":"Services"
        }
    ],
    "sg:phone":"+1 972 878 9258",
    "sg:postcode":"75119",
    "sg:province":"TX",
    "sg:tags":[
        "advisory"
    ],
    "wof:name":"Jeffers Investments, Inc.",
    "wof:placetype":"venue"
},
  "geometry": {"coordinates":[-96.647859,32.342039],"type":"Point"}
}