{
  "type": "Feature",
  "properties": {
    "iso:country":"US",
    "sg:address":"8800 Lava Hill Rd",
    "sg:city":"Austin",
    "sg:classifiers":[
        {
            "category":"Home & Garden",
            "subcategory":"Building Materials",
            "type":"Retail Goods"
        },
        {
            "category":"Building & Trades",
            "subcategory":"Construction",
            "type":"Services"
        }
    ],
    "sg:phone":"+1 512 243 5256",
    "sg:postcode":"78744",
    "sg:province":"TX",
    "sg:tags":[
        "awning",
        "canopy",
        "canopies-repair"
    ],
    "wof:name":"Coolsun Awnings Inc",
    "wof:placetype":"venue"
},
  "geometry": {"coordinates":[-97.69666599999999,30.152693],"type":"Point"}
}