{
  "type": "Feature",
  "properties": {
    "iso:country":"US",
    "sg:address":"623 Blue Grass Dr",
    "sg:city":"Dallas",
    "sg:classifiers":[
        {
            "category":"Wholesale",
            "subcategory":"Construction Materials",
            "type":"Manufacturing & Wholesale Goods"
        }
    ],
    "sg:phone":"+1 214 337 0752",
    "sg:postcode":"75211",
    "sg:province":"TX",
    "wof:name":"H & E Trucking",
    "wof:placetype":"venue"
},
  "geometry": {"coordinates":[-96.92233400000001,32.739934],"type":"Point"}
}