{
  "type": "Feature",
  "properties": {
    "iso:country":"US",
    "sg:address":"9929 Warwana Rd",
    "sg:city":"Houston",
    "sg:classifiers":[
        {
            "category":"Professional",
            "type":"Services"
        }
    ],
    "sg:phone":"+1 713 984 2026",
    "sg:postcode":"77080",
    "sg:province":"TX",
    "sg:tags":[
        "establishment"
    ],
    "wof:name":"Madeline Sitzes & Assoc",
    "wof:placetype":"venue"
},
  "geometry": {"coordinates":[-95.538184,29.800858],"type":"Point"}
}