{
  "type": "Feature",
  "properties": {
    "iso:country":"US",
    "sg:address":"839 FM 467",
    "sg:city":"Seguin",
    "sg:classifiers":[
        {
            "category":"Bars & Pubs",
            "type":"Food & Drink"
        }
    ],
    "sg:phone":"+1 830 379 2995",
    "sg:postcode":"78155",
    "sg:province":"TX",
    "sg:tags":[
        "dance",
        "bar",
        "hall"
    ],
    "wof:name":"Country Cabaret",
    "wof:placetype":"venue"
},
  "geometry": {"coordinates":[-97.976985,29.534968],"type":"Point"}
}