{
  "type": "Feature",
  "properties": {
    "iso:country":"US",
    "sg:address":"5501 Tanglebriar Dr",
    "sg:city":"Dickinson",
    "sg:classifiers":[
        {
            "category":"Shopping",
            "subcategory":"Catalog Store",
            "type":"Retail Goods"
        }
    ],
    "sg:phone":"+1 281 534 4949",
    "sg:postcode":"77539",
    "sg:province":"TX",
    "sg:tags":[
        "on",
        "tool",
        "power",
        "accessory"
    ],
    "wof:name":"Dixon Industries",
    "wof:placetype":"venue"
},
  "geometry": {"coordinates":[-95.048543,29.447769],"type":"Point"}
}