{
  "type": "Feature",
  "properties": {
    "iso:country":"US",
    "sg:address":"1000 Post N Paddock St",
    "sg:city":"Grand Prairie",
    "sg:classifiers":[
        {
            "category":"Wholesale",
            "subcategory":"Machinery & Supplies",
            "type":"Manufacturing & Wholesale Goods"
        }
    ],
    "sg:phone":"+1 972 988 9000",
    "sg:postcode":"75050",
    "sg:province":"TX",
    "sg:tags":[
        "equipment",
        "lease",
        "material",
        "handling",
        "repair"
    ],
    "wof:name":"Shannon Corporate Services",
    "wof:placetype":"venue"
},
  "geometry": {"coordinates":[-97.048708,32.793285],"type":"Point"}
}