{
  "type": "Feature",
  "properties": {
    "iso:country":"US",
    "sg:address":"3002 US Hwy 77",
    "sg:city":"Rockdale",
    "sg:classifiers":[
        {
            "category":"Real Estate",
            "subcategory":"Real Estate Agent",
            "type":"Services"
        }
    ],
    "sg:phone":"+1 512 446 6165",
    "sg:postcode":"76520",
    "sg:province":"TX",
    "wof:name":"Richard Thrasher Real Estate",
    "wof:placetype":"venue"
},
  "geometry": {"coordinates":[-96.9735,30.875933],"type":"Point"}
}