{
  "type": "Feature",
  "properties": {
    "iso:country":"US",
    "sg:address":"2033 Sidney Baker St",
    "sg:city":"Kerrville",
    "sg:classifiers":[
        {
            "category":"Travel",
            "subcategory":"Hotels & Motels",
            "type":"Entertainment"
        }
    ],
    "sg:phone":"+1 830 257 4440",
    "sg:postcode":"78028",
    "sg:province":"TX",
    "sg:website":"www.hotelkerrville.com",
    "wof:name":"Y O Ranch Resort Hotel",
    "wof:placetype":"venue"
},
  "geometry": {"coordinates":[-99.118808,30.06545],"type":"Point"}
}