{
  "type": "Feature",
  "properties": {
    "iso:country":"US",
    "sg:address":"135 W Fm 243",
    "sg:city":"Bertram",
    "sg:classifiers":[
        {
            "category":"Professional",
            "subcategory":"Business Services",
            "type":"Services"
        },
        {
            "category":"Government",
            "subcategory":"Post Office",
            "type":"Public Place"
        }
    ],
    "sg:phone":"+1 512 355 2144",
    "sg:postcode":"78605",
    "sg:province":"TX",
    "sg:tags":[
        "mail",
        "shipping"
    ],
    "sg:website":"http://www.usps.gov",
    "wof:name":"USPS - United States Post Office",
    "wof:placetype":"venue"
},
  "geometry": {"coordinates":[-98.05893399999999,30.743922],"type":"Point"}
}