{
  "type": "Feature",
  "properties": {
    "iso:country":"US",
    "sg:address":"7062 Lakeview Haven Dr",
    "sg:city":"Houston",
    "sg:classifiers":[
        {
            "category":"Professional",
            "subcategory":"Business Services",
            "type":"Services"
        },
        {
            "category":"Professional",
            "subcategory":"Secretarial Services",
            "type":"Services"
        }
    ],
    "sg:phone":"+1 281 858 5454",
    "sg:postcode":"77095",
    "sg:province":"TX",
    "sg:tags":[
        "transcribing",
        "reporting",
        "disc"
    ],
    "wof:name":"Associate Transcription Servic",
    "wof:placetype":"venue"
},
  "geometry": {"coordinates":[-95.649804,29.880753],"type":"Point"}
}