{
  "type": "Feature",
  "properties": {
    "iso:country":"US",
    "sg:address":"15820 Addison Rd",
    "sg:city":"Addison",
    "sg:classifiers":[
        {
            "category":"Shopping",
            "subcategory":"Computers & Home Electronics",
            "type":"Retail Goods"
        }
    ],
    "sg:phone":"+1 512 336 3066",
    "sg:postcode":"75001",
    "sg:province":"TX",
    "sg:tags":[
        "software"
    ],
    "sg:website":"www.regencysystems.com",
    "wof:name":"S1 Corp",
    "wof:placetype":"venue"
},
  "geometry": {"coordinates":[-96.829774,32.965034],"type":"Point"}
}