{
  "type": "Feature",
  "properties": {
    "iso:country":"US",
    "sg:address":"103 W Hiram St",
    "sg:city":"Atlanta",
    "sg:classifiers":[
        {
            "category":"Professional",
            "subcategory":"Lawyer & Legal Services",
            "type":"Services"
        }
    ],
    "sg:phone":"+1 903 796 2801",
    "sg:postcode":"75551",
    "sg:province":"TX",
    "sg:tags":[
        "attorney",
        "practice",
        "plan"
    ],
    "wof:name":"Mays, Jeff W",
    "wof:placetype":"venue"
},
  "geometry": {"coordinates":[-94.16556199999999,33.115103],"type":"Point"}
}