{
  "type": "Feature",
  "properties": {
    "iso:country":"US",
    "sg:address":"3713 Honeysuckle Ave",
    "sg:city":"Fort Worth",
    "sg:classifiers":[
        {
            "category":"Building & Trades",
            "subcategory":"Landscaping Services",
            "type":"Services"
        }
    ],
    "sg:phone":"+1 817 838 8366",
    "sg:postcode":"76111",
    "sg:province":"TX",
    "sg:tags":[
        "landscape"
    ],
    "wof:name":"Environmental Enhancement",
    "wof:placetype":"venue"
},
  "geometry": {"coordinates":[-97.29382,32.784069],"type":"Point"}
}