{
  "type": "Feature",
  "properties": {
    "iso:country":"US",
    "sg:address":"27650 State Highway 249",
    "sg:city":"Tomball",
    "sg:classifiers":[
        {
            "category":"Health Services",
            "subcategory":"Optometrist",
            "type":"Services"
        }
    ],
    "sg:phone":"+1 281 357 5868",
    "sg:postcode":"77375",
    "sg:province":"TX",
    "wof:name":"Huynh, Misa Trang",
    "wof:placetype":"venue"
},
  "geometry": {"coordinates":[-95.628079,30.076281],"type":"Point"}
}