{
  "type": "Feature",
  "properties": {
    "iso:country":"US",
    "sg:address":"5327 Winding Way Dr",
    "sg:city":"Houston",
    "sg:classifiers":[
        {
            "category":"Professional",
            "subcategory":"Business Services",
            "type":"Services"
        }
    ],
    "sg:phone":"+1 713 956 5346",
    "sg:postcode":"77091",
    "sg:province":"TX",
    "wof:name":"J&D Moore Enterprises Inc",
    "wof:placetype":"venue"
},
  "geometry": {"coordinates":[-95.465559,29.858077],"type":"Point"}
}