{
  "type": "Feature",
  "properties": {
    "iso:country":"US",
    "sg:address":"1122 Millview Dr",
    "sg:city":"Arlington",
    "sg:classifiers":[
        {
            "category":"Real Estate",
            "subcategory":"Real Estate Operator",
            "type":"Services"
        }
    ],
    "sg:phone":"+1 817 792 3123",
    "sg:postcode":"76012",
    "sg:province":"TX",
    "sg:tags":[
        "property",
        "lessor"
    ],
    "wof:name":"Parkside Townhomes",
    "wof:placetype":"venue"
},
  "geometry": {"coordinates":[-97.13519100000001,32.751694],"type":"Point"}
}