{
  "type": "Feature",
  "properties": {
    "iso:country":"US",
    "sg:address":"400 E Levee St",
    "sg:city":"Brownsville",
    "sg:classifiers":[
        {
            "category":"Wholesale",
            "subcategory":"Non-durable Goods",
            "type":"Manufacturing & Wholesale Goods"
        }
    ],
    "sg:phone":"+1 956 982 1229",
    "sg:postcode":"78520",
    "sg:province":"TX",
    "wof:name":"Cano Pedroluis",
    "wof:placetype":"venue"
},
  "geometry": {"coordinates":[-97.503861,25.905158],"type":"Point"}
}