{
  "type": "Feature",
  "properties": {
    "iso:country":"US",
    "sg:address":"4102 Deepwoods Dr",
    "sg:city":"Austin",
    "sg:classifiers":[
        {
            "category":"Building & Trades",
            "subcategory":"Plumbing",
            "type":"Services"
        }
    ],
    "sg:phone":"+1 512 346 7141",
    "sg:postcode":"78731",
    "sg:province":"TX",
    "sg:tags":[
        "pipe",
        "inspection"
    ],
    "wof:name":"Greg A Guy",
    "wof:placetype":"venue"
},
  "geometry": {"coordinates":[-97.763907,30.364077],"type":"Point"}
}