{
  "type": "Feature",
  "properties": {
    "iso:country":"US",
    "sg:address":"4827 Keller Springs Rd",
    "sg:city":"Addison",
    "sg:classifiers":[
        {
            "category":"Shopping",
            "subcategory":"Gifts & Souvenirs",
            "type":"Retail Goods"
        }
    ],
    "sg:phone":"+1 972 250 9281",
    "sg:postcode":"75001",
    "sg:province":"TX",
    "wof:name":"Ceramic Expressions",
    "wof:placetype":"venue"
},
  "geometry": {"coordinates":[-96.828307,32.968721],"type":"Point"}
}