{
  "type": "Feature",
  "properties": {
    "iso:country":"US",
    "sg:address":"8786 Ferguson Rd",
    "sg:city":"Dallas",
    "sg:classifiers":[
        {
            "category":"Autos & Motor Vehicles",
            "subcategory":"Auto Supplies",
            "type":"Retail Goods"
        }
    ],
    "sg:phone":"+1 214 320 0019",
    "sg:postcode":"75228",
    "sg:province":"TX",
    "sg:tags":[
        "wheel",
        "cover"
    ],
    "wof:name":"Ministriespotter Wheel",
    "wof:placetype":"venue"
},
  "geometry": {"coordinates":[-96.699637,32.812487],"type":"Point"}
}