{
  "type": "Feature",
  "properties": {
    "iso:country":"US",
    "sg:address":"4134 Tasselwood Ln",
    "sg:city":"Houston",
    "sg:classifiers":[
        {
            "category":"Banks & Credit Unions",
            "subcategory":"Bank",
            "type":"Services"
        }
    ],
    "sg:phone":"+1 281 301 2017",
    "sg:postcode":"77014",
    "sg:province":"TX",
    "sg:tags":[
        "loan"
    ],
    "wof:name":"K T Lending",
    "wof:placetype":"venue"
},
  "geometry": {"coordinates":[-95.48556600000001,29.979871],"type":"Point"}
}