{
  "type": "Feature",
  "properties": {
    "iso:country":"US",
    "sg:address":"6817 Homestead Rd",
    "sg:city":"Houston",
    "sg:classifiers":[
        {
            "category":"Personal",
            "subcategory":"Beauty Salon",
            "type":"Services"
        }
    ],
    "sg:phone":"+1 713 635 6656",
    "sg:postcode":"77028",
    "sg:province":"TX",
    "sg:tags":[
        "shop"
    ],
    "wof:name":"Frank Braden",
    "wof:placetype":"venue"
},
  "geometry": {"coordinates":[-95.30203299999999,29.822656],"type":"Point"}
}