{
  "type": "Feature",
  "properties": {
    "iso:country":"US",
    "sg:address":"14319 Spyglen Ln",
    "sg:city":"Cypress",
    "sg:classifiers":[
        {
            "category":"Professional",
            "subcategory":"Business Services",
            "type":"Services"
        }
    ],
    "sg:phone":"+1 281 304 0216",
    "sg:postcode":"77429",
    "sg:province":"TX",
    "wof:name":"Karen R Patton",
    "wof:placetype":"venue"
},
  "geometry": {"coordinates":[-95.6401,29.980202],"type":"Point"}
}