{
  "type": "Feature",
  "properties": {
    "iso:country":"US",
    "sg:address":"1413 Robin Ave",
    "sg:city":"Katy",
    "sg:classifiers":[
        {
            "category":"Manufacturing",
            "subcategory":"Apparel",
            "type":"Manufacturing & Wholesale Goods"
        }
    ],
    "sg:phone":"+1 281 391 9852",
    "sg:postcode":"77493",
    "sg:province":"TX",
    "wof:name":"U-Name It Personalized Embroid",
    "wof:placetype":"venue"
},
  "geometry": {"coordinates":[-95.805316,29.791835],"type":"Point"}
}