{
  "type": "Feature",
  "properties": {
    "iso:country":"US",
    "sg:address":"805 S Columbia Dr",
    "sg:city":"West Columbia",
    "sg:classifiers":[
        {
            "category":"Professional",
            "type":"Services"
        }
    ],
    "sg:phone":"+1 979 345 3672",
    "sg:postcode":"77486",
    "sg:province":"TX",
    "wof:name":"Bos Yard Scape",
    "wof:placetype":"venue"
},
  "geometry": {"coordinates":[-95.652885,29.137533],"type":"Point"}
}