{
  "type": "Feature",
  "properties": {
    "iso:country":"US",
    "sg:address":"2928 Remond Dr",
    "sg:city":"Dallas",
    "sg:classifiers":[
        {
            "category":"Social Services",
            "subcategory":"Child Care",
            "type":"Services"
        }
    ],
    "sg:phone":"+1 214 333 9440",
    "sg:postcode":"75211",
    "sg:province":"TX",
    "sg:tags":[
        "day"
    ],
    "wof:name":"ABC Day School 2 Inc",
    "wof:placetype":"venue"
},
  "geometry": {"coordinates":[-96.8694,32.764198],"type":"Point"}
}