{
  "type": "Feature",
  "properties": {
    "iso:country":"US",
    "sg:address":"8657 Market Street Rd",
    "sg:city":"Houston",
    "sg:classifiers":[
        {
            "category":"Building & Trades",
            "subcategory":"Construction",
            "type":"Services"
        }
    ],
    "sg:phone":"+1 713 674 6310",
    "sg:postcode":"77029",
    "sg:province":"TX",
    "sg:tags":[
        "company"
    ],
    "wof:name":"A B Construction",
    "wof:placetype":"venue"
},
  "geometry": {"coordinates":[-95.269142,29.770117],"type":"Point"}
}