{
  "type": "Feature",
  "properties": {
    "iso:country":"US",
    "sg:address":"5416 71st St",
    "sg:city":"Lubbock",
    "sg:classifiers":[
        {
            "category":"Manufacturing",
            "subcategory":"Textiles",
            "type":"Manufacturing & Wholesale Goods"
        }
    ],
    "sg:phone":"+1 806 794 8672",
    "sg:postcode":"79424",
    "sg:province":"TX",
    "sg:tags":[
        "mill",
        "knit",
        "outerwear"
    ],
    "wof:name":"C & L TS",
    "wof:placetype":"venue"
},
  "geometry": {"coordinates":[-101.93000600000001,33.529155],"type":"Point"}
}