{
  "type": "Feature",
  "properties": {
    "iso:country":"US",
    "sg:address":"4121 Ballard Rd",
    "sg:city":"Robstown",
    "sg:classifiers":[
        {
            "category":"Insurance",
            "subcategory":"Insurance Agent",
            "type":"Services"
        }
    ],
    "sg:phone":"+1 361 767 8922",
    "sg:postcode":"78380",
    "sg:province":"TX",
    "sg:tags":[
        "processing"
    ],
    "wof:name":"Precision Claims Svc",
    "wof:placetype":"venue"
},
  "geometry": {"coordinates":[-97.681181,27.88323],"type":"Point"}
}