{
  "type": "Feature",
  "properties": {
    "iso:country":"US",
    "sg:address":"7655 De Moss Dr",
    "sg:city":"Houston",
    "sg:classifiers":[
        {
            "category":"Food & Beverages",
            "subcategory":"Groceries & Convenience Stores",
            "type":"Retail Goods"
        }
    ],
    "sg:phone":"+1 713 270 8889",
    "sg:postcode":"77036",
    "sg:province":"TX",
    "wof:name":"Sam Bo Supermarket",
    "wof:placetype":"venue"
},
  "geometry": {"coordinates":[-95.519997,29.7083],"type":"Point"}
}