{
  "type": "Feature",
  "properties": {
    "iso:country":"US",
    "sg:address":"4667 Wicklow Dr",
    "sg:city":"Frisco",
    "sg:classifiers":[
        {
            "category":"Professional",
            "subcategory":"Computer Services",
            "type":"Services"
        }
    ],
    "sg:phone":"+1 972 679 3870",
    "sg:postcode":"75034",
    "sg:province":"TX",
    "sg:tags":[
        "information",
        "technology"
    ],
    "wof:name":"Amko Technologies Inc",
    "wof:placetype":"venue"
},
  "geometry": {"coordinates":[-96.85204299999999,33.117376],"type":"Point"}
}