{
  "type": "Feature",
  "properties": {
    "iso:country":"US",
    "sg:address":"206 E Hamilton St",
    "sg:city":"Stamford",
    "sg:classifiers":[
        {
            "category":"Restaurant",
            "type":"Food & Drink"
        }
    ],
    "sg:phone":"+1 325 773 9047",
    "sg:postcode":"79553",
    "sg:province":"TX",
    "sg:tags":[
        "eating"
    ],
    "wof:name":"Griggs B B Q",
    "wof:placetype":"venue"
},
  "geometry": {"coordinates":[-99.80161,32.944025],"type":"Point"}
}