{
  "type": "Feature",
  "properties": {
    "iso:country":"US",
    "sg:address":"67 1/2 April Wind Dr S",
    "sg:city":"Montgomery",
    "sg:classifiers":[
        {
            "category":"Place Of Worship",
            "subcategory":"Church",
            "type":"Public Place"
        },
        {
            "category":"Place Of Worship",
            "type":"Public Place"
        }
    ],
    "sg:phone":"+1 936 588 2832",
    "sg:postcode":"77356",
    "sg:province":"TX",
    "sg:tags":[
        "churches-interdenominational",
        "churches-various",
        "denomination"
    ],
    "wof:name":"April Sound Church Inc",
    "wof:placetype":"venue"
},
  "geometry": {"coordinates":[-95.613777,30.36606],"type":"Point"}
}