{
  "type": "Feature",
  "properties": {
    "iso:country":"US",
    "sg:address":"3316 Scotch Moss Ln",
    "sg:city":"La Porte",
    "sg:classifiers":[
        {
            "category":"Professional",
            "subcategory":"Detective & Security Services",
            "type":"Services"
        }
    ],
    "sg:phone":"+1 281 542 9605",
    "sg:postcode":"77571",
    "sg:province":"TX",
    "sg:tags":[
        "system"
    ],
    "wof:name":"Sure Security Inc",
    "wof:placetype":"venue"
},
  "geometry": {"coordinates":[-95.10969,29.66014],"type":"Point"}
}