{
  "type": "Feature",
  "properties": {
    "iso:country":"US",
    "sg:address":"816 Preusser St",
    "sg:city":"San Angelo",
    "sg:classifiers":[
        {
            "category":"Building & Trades",
            "subcategory":"Cleaning & Sanitation",
            "type":"Services"
        }
    ],
    "sg:phone":"+1 325 653 3922",
    "sg:postcode":"76903",
    "sg:province":"TX",
    "sg:tags":[
        "janitor",
        "maintenance"
    ],
    "wof:name":"Heaven Scent Cleaning Services",
    "wof:placetype":"venue"
},
  "geometry": {"coordinates":[-100.423677,31.466648],"type":"Point"}
}