{
  "type": "Feature",
  "properties": {
    "iso:country":"US",
    "sg:address":"1601 S Shepherd Dr",
    "sg:city":"Houston",
    "sg:classifiers":[
        {
            "category":"Social Services",
            "subcategory":"Job Training",
            "type":"Services"
        }
    ],
    "sg:phone":"+1 713 526 5970",
    "sg:postcode":"77019",
    "sg:province":"TX",
    "sg:tags":[
        "career",
        "counseling",
        "vocational"
    ],
    "wof:name":"Future Trax",
    "wof:placetype":"venue"
},
  "geometry": {"coordinates":[-95.410623,29.750929],"type":"Point"}
}