{
  "type": "Feature",
  "properties": {
    "iso:country":"US",
    "sg:address":"1403 Chestnut Ave",
    "sg:city":"Midland",
    "sg:classifiers":[
        {
            "category":"Professional",
            "subcategory":"Business Services",
            "type":"Services"
        }
    ],
    "sg:phone":"+1 432 682 9614",
    "sg:postcode":"79701",
    "sg:province":"TX",
    "wof:name":"Rabbs Enterprises",
    "wof:placetype":"venue"
},
  "geometry": {"coordinates":[-102.060385,32.016674],"type":"Point"}
}