{
  "type": "Feature",
  "properties": {
    "iso:country":"US",
    "sg:address":"240 N Monroe St",
    "sg:city":"Eagle Pass",
    "sg:classifiers":[
        {
            "category":"Wholesale",
            "subcategory":"Machinery & Supplies",
            "type":"Manufacturing & Wholesale Goods"
        },
        {
            "category":"Home & Garden",
            "subcategory":"Garden Supply",
            "type":"Retail Goods"
        }
    ],
    "sg:phone":"+1 830 773 8207",
    "sg:postcode":"78852",
    "sg:province":"TX",
    "sg:tags":[
        "engine",
        "equipment",
        "industrial"
    ],
    "wof:name":"Cano's Small Engine Parts",
    "wof:placetype":"venue"
},
  "geometry": {"coordinates":[-100.500452,28.707682],"type":"Point"}
}