{
  "type": "Feature",
  "properties": {
    "iso:country":"US",
    "sg:address":"102 S Washington Ave",
    "sg:city":"Cleveland",
    "sg:classifiers":[
        {
            "category":"Food & Beverages",
            "subcategory":"Groceries & Convenience Stores",
            "type":"Retail Goods"
        }
    ],
    "sg:phone":"+1 281 592 7037",
    "sg:postcode":"77327",
    "sg:province":"TX",
    "wof:name":"Sunmart",
    "wof:placetype":"venue"
},
  "geometry": {"coordinates":[-95.089799,30.343008],"type":"Point"}
}