{
  "type": "Feature",
  "properties": {
    "iso:country":"US",
    "sg:address":"2905 Blue Ridge Dr",
    "sg:city":"Cedar Park",
    "sg:classifiers":[
        {
            "category":"Professional",
            "type":"Services"
        }
    ],
    "sg:phone":"+1 512 249 6890",
    "sg:postcode":"78613",
    "sg:province":"TX",
    "wof:name":"Jubilee Merchandise Co",
    "wof:placetype":"venue"
},
  "geometry": {"coordinates":[-97.814727,30.465391],"type":"Point"}
}