{
  "type": "Feature",
  "properties": {
    "iso:country":"US",
    "sg:address":"7319 Gore Dr",
    "sg:city":"Houston",
    "sg:classifiers":[
        {
            "category":"Travel",
            "subcategory":"Travel Agent",
            "type":"Entertainment"
        }
    ],
    "sg:phone":"+1 713 633 5785",
    "sg:postcode":"77016",
    "sg:province":"TX",
    "sg:tags":[
        "agency"
    ],
    "wof:name":"C G S Travel and Promotion",
    "wof:placetype":"venue"
},
  "geometry": {"coordinates":[-95.298197,29.862617],"type":"Point"}
}