{
  "type": "Feature",
  "properties": {
    "iso:country":"US",
    "sg:address":"2326 Lamonte Ln",
    "sg:city":"Houston",
    "sg:classifiers":[
        {
            "category":"Home & Garden",
            "subcategory":"Carpets & Floor Coverings",
            "type":"Retail Goods"
        }
    ],
    "sg:phone":"+1 713 682 1298",
    "sg:postcode":"77018",
    "sg:province":"TX",
    "wof:name":"Floor Revue Carpet Co",
    "wof:placetype":"venue"
},
  "geometry": {"coordinates":[-95.45188899999999,29.825712],"type":"Point"}
}