{
  "type": "Feature",
  "properties": {
    "iso:country":"US",
    "sg:address":"12410 W Bellfort Ave",
    "sg:city":"Houston",
    "sg:classifiers":[
        {
            "category":"Retail",
            "subcategory":"Auto Repair",
            "type":"Services"
        }
    ],
    "sg:phone":"+1 281 530 7632",
    "sg:postcode":"77099",
    "sg:province":"TX",
    "sg:tags":[
        "automotive"
    ],
    "wof:name":"Super Tech Auto Repair Inc",
    "wof:placetype":"venue"
},
  "geometry": {"coordinates":[-95.596675,29.660439],"type":"Point"}
}