{
  "type": "Feature",
  "properties": {
    "iso:country":"US",
    "sg:address":"1239 Gum Springs Rd",
    "sg:city":"Longview",
    "sg:classifiers":[
        {
            "category":"Freight",
            "type":"Transportation"
        }
    ],
    "sg:phone":"+1 903 758 9176",
    "sg:postcode":"75602",
    "sg:province":"TX",
    "sg:tags":[
        "hauling",
        "trucking"
    ],
    "wof:name":"Mc Crary Trucking Co",
    "wof:placetype":"venue"
},
  "geometry": {"coordinates":[-94.680241,32.459882],"type":"Point"}
}