{
  "type": "Feature",
  "properties": {
    "iso:country":"US",
    "sg:address":"3706 N Texas Ave",
    "sg:city":"Bryan",
    "sg:classifiers":[
        {
            "category":"Autos & Motor Vehicles",
            "subcategory":"Auto Supplies",
            "type":"Retail Goods"
        }
    ],
    "sg:phone":"+1 979 846 1139",
    "sg:postcode":"77803",
    "sg:province":"TX",
    "sg:tags":[
        "tire"
    ],
    "wof:name":"C & L Tire Svc Ctr",
    "wof:placetype":"venue"
},
  "geometry": {"coordinates":[-96.390469,30.701823],"type":"Point"}
}