{
  "type": "Feature",
  "properties": {
    "iso:country":"US",
    "sg:address":"332 6th St",
    "sg:city":"Port Aransas",
    "sg:classifiers":[
        {
            "category":"Recreation",
            "type":"Entertainment"
        }
    ],
    "sg:phone":"+1 361 749 5398",
    "sg:postcode":"78373",
    "sg:province":"TX",
    "wof:name":"Island Martial Arts & Fit",
    "wof:placetype":"venue"
},
  "geometry": {"coordinates":[-97.068709,27.833675],"type":"Point"}
}