{
  "type": "Feature",
  "properties": {
    "iso:country":"US",
    "sg:address":"2120 W Braker Ln",
    "sg:city":"Austin",
    "sg:classifiers":[
        {
            "category":"Manufacturing",
            "subcategory":"Tools & Machinery",
            "type":"Manufacturing & Wholesale Goods"
        }
    ],
    "sg:phone":"+1 512 451 3933",
    "sg:postcode":"78758",
    "sg:province":"TX",
    "sg:tags":[
        "control"
    ],
    "sg:website":"www.hydro-consystems.com",
    "wof:name":"Hydro-Con",
    "wof:placetype":"venue"
},
  "geometry": {"coordinates":[-97.71217900000001,30.392759],"type":"Point"}
}