{
  "type": "Feature",
  "properties": {
    "iso:country":"US",
    "sg:address":"4852 White Settlement Rd",
    "sg:city":"Fort Worth",
    "sg:classifiers":[
        {
            "category":"Manufacturing",
            "subcategory":"Printing",
            "type":"Manufacturing & Wholesale Goods"
        }
    ],
    "sg:phone":"+1 817 377 0711",
    "sg:postcode":"76114",
    "sg:province":"TX",
    "sg:tags":[
        "shop"
    ],
    "wof:name":"P D Q Fasprint Center",
    "wof:placetype":"venue"
},
  "geometry": {"coordinates":[-97.394547,32.760084],"type":"Point"}
}