{
  "type": "Feature",
  "properties": {
    "iso:country":"US",
    "sg:address":"6100 Long Prairie Rd",
    "sg:city":"Flower Mound",
    "sg:classifiers":[
        {
            "category":"Restaurant",
            "type":"Food & Drink"
        }
    ],
    "sg:menulink":"http://www.allmenus.com/tx/lewisville/250212-on-a-roll/menu/",
    "sg:phone":"+1 972 539 9110",
    "sg:postcode":"75028",
    "sg:province":"TX",
    "sg:tags":[
        "wrap",
        "american",
        "sandwich"
    ],
    "wof:name":"On A Roll",
    "wof:placetype":"venue"
},
  "geometry": {"coordinates":[-97.082448,33.069175],"type":"Point"}
}