{
  "type": "Feature",
  "properties": {
    "iso:country":"US",
    "sg:address":"125 Rooster Cogburn Ct",
    "sg:city":"Weatherford",
    "sg:classifiers":[
        {
            "category":"Restaurant",
            "type":"Food & Drink"
        }
    ],
    "sg:phone":"+1 817 599 9874",
    "sg:postcode":"76088",
    "sg:province":"TX",
    "sg:tags":[
        "chicken"
    ],
    "wof:name":"Golden Fried Chicken",
    "wof:placetype":"venue"
},
  "geometry": {"coordinates":[-97.85220099999999,32.782133],"type":"Point"}
}