{
  "type": "Feature",
  "properties": {
    "iso:country":"US",
    "sg:address":"3781 Woodridge Dr",
    "sg:city":"Abilene",
    "sg:classifiers":[
        {
            "category":"Health Services",
            "subcategory":"Chiropractor",
            "type":"Services"
        }
    ],
    "sg:phone":"+1 325 691 0690",
    "sg:postcode":"79605",
    "sg:province":"TX",
    "wof:name":"Abilene Family Chiropractic",
    "wof:placetype":"venue"
},
  "geometry": {"coordinates":[-99.77218999999999,32.433424],"type":"Point"}
}