{
  "type": "Feature",
  "properties": {
    "iso:country":"US",
    "sg:address":"3209 Avon Dr",
    "sg:city":"Arlington",
    "sg:classifiers":[
        {
            "category":"Shopping",
            "subcategory":"Discount & Variety Stores",
            "type":"Retail Goods"
        }
    ],
    "sg:phone":"+1 817 275 6493",
    "sg:postcode":"76015",
    "sg:province":"TX",
    "sg:tags":[
        "merchandise",
        "general"
    ],
    "wof:name":"Marsha W Bope",
    "wof:placetype":"venue"
},
  "geometry": {"coordinates":[-97.14860899999999,32.694382],"type":"Point"}
}