{
  "type": "Feature",
  "properties": {
    "iso:country":"US",
    "sg:address":"4500 Bissonnet St",
    "sg:city":"Bellaire",
    "sg:classifiers":[
        {
            "category":"Health Services",
            "subcategory":"Health Practitioner",
            "type":"Services"
        }
    ],
    "sg:phone":"+1 713 660 9988",
    "sg:postcode":"77401",
    "sg:province":"TX",
    "sg:tags":[
        "professional",
        "counselors-licensed"
    ],
    "wof:name":"Reichlin, Barbara",
    "wof:placetype":"venue"
},
  "geometry": {"coordinates":[-95.451431,29.71603],"type":"Point"}
}