{
  "type": "Feature",
  "properties": {
    "iso:country":"US",
    "sg:address":"204 Crescent Dr",
    "sg:city":"Littlefield",
    "sg:classifiers":[
        {
            "category":"Freight",
            "type":"Transportation"
        }
    ],
    "sg:phone":"+1 806 385 5371",
    "sg:postcode":"79339",
    "sg:province":"TX",
    "sg:tags":[
        "special"
    ],
    "wof:name":"Alamo Storage",
    "wof:placetype":"venue"
},
  "geometry": {"coordinates":[-102.33366599999999,33.909276],"type":"Point"}
}