{
  "type": "Feature",
  "properties": {
    "iso:country":"US",
    "sg:address":"806 W Dallas St",
    "sg:city":"Conroe",
    "sg:classifiers":[
        {
            "category":"Travel",
            "subcategory":"Travel Agent",
            "type":"Entertainment"
        }
    ],
    "sg:phone":"+1 936 539 1831",
    "sg:postcode":"77301",
    "sg:province":"TX",
    "sg:tags":[
        "agency",
        "bureau"
    ],
    "sg:website":"www.friendlytravel.com",
    "wof:name":"Friendly Travel Inc",
    "wof:placetype":"venue"
},
  "geometry": {"coordinates":[-95.46470600000001,30.319766],"type":"Point"}
}