{
  "type": "Feature",
  "properties": {
    "iso:country":"US",
    "sg:address":"2226 Michigan Ave",
    "sg:city":"Arlington",
    "sg:classifiers":[
        {
            "category":"Wholesale",
            "subcategory":"Furniture",
            "type":"Manufacturing & Wholesale Goods"
        },
        {
            "category":"Wholesale",
            "subcategory":"Durable Goods & Equipment",
            "type":"Manufacturing & Wholesale Goods"
        }
    ],
    "sg:phone":"+1 817 261 5224",
    "sg:postcode":"76013",
    "sg:province":"TX",
    "sg:tags":[
        "representative",
        "manufacturer"
    ],
    "wof:name":"Integrated Furniture Systems",
    "wof:placetype":"venue"
},
  "geometry": {"coordinates":[-97.157309,32.707741],"type":"Point"}
}