{
  "type": "Feature",
  "properties": {
    "iso:country":"US",
    "sg:address":"719 Water St",
    "sg:city":"Kerrville",
    "sg:classifiers":[
        {
            "category":"Restaurant",
            "type":"Food & Drink"
        }
    ],
    "sg:phone":"+1 830 895 4376",
    "sg:postcode":"78028",
    "sg:province":"TX",
    "sg:tags":[
        "eating"
    ],
    "wof:name":"Your Favorite hero",
    "wof:placetype":"venue"
},
  "geometry": {"coordinates":[-99.141549,30.046294],"type":"Point"}
}