{
  "type": "Feature",
  "properties": {
    "iso:country":"US",
    "sg:address":"4009 Oak Forest Dr",
    "sg:city":"Corpus Christi",
    "sg:classifiers":[
        {
            "category":"Building & Trades",
            "subcategory":"Landscaping Services",
            "type":"Services"
        }
    ],
    "sg:phone":"+1 361 855 9163",
    "sg:postcode":"78413",
    "sg:province":"TX",
    "wof:name":"Merts Mowing",
    "wof:placetype":"venue"
},
  "geometry": {"coordinates":[-97.41366600000001,27.696554],"type":"Point"}
}