{
  "type": "Feature",
  "properties": {
    "iso:country":"US",
    "sg:address":"1616 N Frazier St",
    "sg:city":"Conroe",
    "sg:classifiers":[
        {
            "category":"Personal",
            "subcategory":"Beauty Salon",
            "type":"Services"
        }
    ],
    "sg:phone":"+1 936 539 5669",
    "sg:postcode":"77301",
    "sg:province":"TX",
    "sg:tags":[
        "shop",
        "barber"
    ],
    "wof:name":"Hair Conductors",
    "wof:placetype":"venue"
},
  "geometry": {"coordinates":[-95.464924,30.326434],"type":"Point"}
}