{
  "type": "Feature",
  "properties": {
    "iso:country":"US",
    "sg:address":"425 Willow Bend Dr",
    "sg:city":"Murphy",
    "sg:classifiers":[
        {
            "category":"Health Services",
            "subcategory":"Clinic",
            "type":"Services"
        }
    ],
    "sg:phone":"+1 972 578 5067",
    "sg:postcode":"75094",
    "sg:province":"TX",
    "wof:name":"Complete Health Co",
    "wof:placetype":"venue"
},
  "geometry": {"coordinates":[-96.609123,33.002802],"type":"Point"}
}