{
  "type": "Feature",
  "properties": {
    "iso:country":"US",
    "sg:address":"4321 Jenning Ct",
    "sg:city":"Plano",
    "sg:classifiers":[
        {
            "category":"Professional",
            "type":"Services"
        },
        {
            "category":"Manufacturing",
            "subcategory":"Furniture",
            "type":"Manufacturing & Wholesale Goods"
        }
    ],
    "sg:phone":"+1 972 867 6551",
    "sg:postcode":"75093",
    "sg:province":"TX",
    "sg:tags":[
        "household",
        "wood",
        "establishment",
        "mfg"
    ],
    "sg:website":"www.chatsworth.com",
    "wof:name":"Chatsworth Products Inc",
    "wof:placetype":"venue"
},
  "geometry": {"coordinates":[-96.77892300000001,33.019781],"type":"Point"}
}