{
  "type": "Feature",
  "properties": {
    "iso:country":"US",
    "sg:address":"10915 Whisper Hollow",
    "sg:city":"San Antonio",
    "sg:classifiers":[
        {
            "category":"Arts & Performance",
            "subcategory":"Theater",
            "type":"Entertainment"
        }
    ],
    "sg:phone":"+1 210 493 2378",
    "sg:postcode":"78230",
    "sg:province":"TX",
    "sg:tags":[
        "band",
        "orchestra"
    ],
    "wof:name":"Cleartones",
    "wof:placetype":"venue"
},
  "geometry": {"coordinates":[-98.538803,29.541483],"type":"Point"}
}