{
  "type": "Feature",
  "properties": {
    "iso:country":"US",
    "sg:address":"7306 Trail Xing",
    "sg:city":"San Antonio",
    "sg:classifiers":[
        {
            "category":"Real Estate",
            "subcategory":"Real Estate Agent",
            "type":"Services"
        }
    ],
    "sg:phone":"+1 210 680 5845",
    "sg:postcode":"78250",
    "sg:province":"TX",
    "wof:name":"Daron Durham Real Estate Co",
    "wof:placetype":"venue"
},
  "geometry": {"coordinates":[-98.651634,29.507708],"type":"Point"}
}