{
  "type": "Feature",
  "properties": {
    "iso:country":"US",
    "sg:address":"4711 Lehigh St",
    "sg:city":"Lubbock",
    "sg:classifiers":[
        {
            "category":"Professional",
            "subcategory":"Computer Services",
            "type":"Services"
        }
    ],
    "sg:phone":"+1 806 747 8885",
    "sg:postcode":"79416",
    "sg:province":"TX",
    "sg:tags":[
        "prepackaged",
        "software"
    ],
    "wof:name":"Bee Zee Software",
    "wof:placetype":"venue"
},
  "geometry": {"coordinates":[-101.912972,33.612604],"type":"Point"}
}