{
  "type": "Feature",
  "properties": {
    "iso:country":"US",
    "sg:address":"6309 N O Connor Blvd",
    "sg:city":"Irving",
    "sg:classifiers":[
        {
            "category":"Professional",
            "subcategory":"Computer Services",
            "type":"Services"
        }
    ],
    "sg:phone":"+1 972 409 5940",
    "sg:postcode":"75039",
    "sg:province":"TX",
    "sg:tags":[
        "consultant",
        "designer"
    ],
    "wof:name":"Data Warehouse Specialists",
    "wof:placetype":"venue"
},
  "geometry": {"coordinates":[-96.937006,32.893013],"type":"Point"}
}