{
  "type": "Feature",
  "properties": {
    "iso:country":"US",
    "sg:address":"2707 Hibernia St",
    "sg:city":"Dallas",
    "sg:classifiers":[
        {
            "category":"Professional",
            "type":"Services"
        }
    ],
    "sg:phone":"+1 214 979 0403",
    "sg:postcode":"75204",
    "sg:province":"TX",
    "sg:tags":[
        "establishment"
    ],
    "wof:name":"FBN Inc",
    "wof:placetype":"venue"
},
  "geometry": {"coordinates":[-96.799779,32.797242],"type":"Point"}
}