{
  "type": "Feature",
  "properties": {
    "iso:country":"US",
    "sg:address":"10315 Mckalla Pl",
    "sg:city":"Austin",
    "sg:classifiers":[
        {
            "category":"Autos & Motor Vehicles",
            "subcategory":"Automobile Sales",
            "type":"Retail Goods"
        }
    ],
    "sg:phone":"+1 512 491 9299",
    "sg:postcode":"78758",
    "sg:province":"TX",
    "sg:tags":[
        "new",
        "car"
    ],
    "wof:name":"Beasley Roger Mazda",
    "wof:placetype":"venue"
},
  "geometry": {"coordinates":[-97.719796,30.38426],"type":"Point"}
}