{
  "type": "Feature",
  "properties": {
    "iso:country":"US",
    "sg:address":"1502 E Main St",
    "sg:city":"Grand Prairie",
    "sg:classifiers":[
        {
            "category":"Retail",
            "subcategory":"Repair Shop",
            "type":"Services"
        }
    ],
    "sg:phone":"+1 972 264 8791",
    "sg:postcode":"75050",
    "sg:province":"TX",
    "sg:tags":[
        "upholsterer"
    ],
    "wof:name":"East Main Street Upholstery",
    "wof:placetype":"venue"
},
  "geometry": {"coordinates":[-96.984888,32.747674],"type":"Point"}
}