{
  "type": "Feature",
  "properties": {
    "iso:country":"US",
    "sg:address":"111 E Ave D",
    "sg:city":"Muleshoe",
    "sg:classifiers":[
        {
            "category":"Government",
            "subcategory":"Office",
            "type":"Public Place"
        }
    ],
    "sg:phone":"+1 806 272 4538",
    "sg:postcode":"79347",
    "sg:province":"TX",
    "sg:tags":[
        "federal"
    ],
    "wof:name":"US Consolidated Farm Svc Agcy",
    "wof:placetype":"venue"
},
  "geometry": {"coordinates":[-102.725961,34.223734],"type":"Point"}
}