{
  "type": "Feature",
  "properties": {
    "iso:country":"US",
    "sg:address":"3307 Ave J",
    "sg:city":"Bay City",
    "sg:classifiers":[
        {
            "category":"Professional",
            "subcategory":"Computer Services",
            "type":"Services"
        }
    ],
    "sg:phone":"+1 979 245 2497",
    "sg:postcode":"77414",
    "sg:province":"TX",
    "sg:tags":[
        "programing",
        "custom"
    ],
    "wof:name":"Eisman Computer Consulting",
    "wof:placetype":"venue"
},
  "geometry": {"coordinates":[-95.96449,28.969533],"type":"Point"}
}