{
  "type": "Feature",
  "properties": {
    "iso:country":"US",
    "sg:address":"3801 William D Tate Ave",
    "sg:city":"Grapevine",
    "sg:classifiers":[
        {
            "category":"Professional",
            "subcategory":"Management & Consulting",
            "type":"Services"
        }
    ],
    "sg:phone":"+1 817 257 8054",
    "sg:postcode":"76051",
    "sg:province":"TX",
    "sg:tags":[
        "business"
    ],
    "wof:name":"Creative Pharmacy Solutions",
    "wof:placetype":"venue"
},
  "geometry": {"coordinates":[-97.098433,32.894255],"type":"Point"}
}