{
  "type": "Feature",
  "properties": {
    "iso:country":"US",
    "sg:address":"2924 Oak Lawn Ave",
    "sg:city":"Dallas",
    "sg:classifiers":[
        {
            "category":"Professional",
            "subcategory":"Printing & Photocopies",
            "type":"Services"
        }
    ],
    "sg:phone":"+1 214 220 0190",
    "sg:postcode":"75219",
    "sg:province":"TX",
    "sg:tags":[
        "blueprinting"
    ],
    "wof:name":"Merritt Reproduction Inc",
    "wof:placetype":"venue"
},
  "geometry": {"coordinates":[-96.809455,32.808082],"type":"Point"}
}