{
  "type": "Feature",
  "properties": {
    "iso:country":"US",
    "sg:address":"4901 W Plano Pkwy",
    "sg:city":"Plano",
    "sg:classifiers":[
        {
            "category":"Restaurant",
            "type":"Food & Drink"
        }
    ],
    "sg:menulink":"http://www.allmenus.com/tx/plano/35809-chipotle/menu/",
    "sg:phone":"+1 469 467 9900",
    "sg:postcode":"75093",
    "sg:province":"TX",
    "sg:tags":[
        "mexican"
    ],
    "wof:name":"Chipotle",
    "wof:placetype":"venue"
},
  "geometry": {"coordinates":[-96.792157,33.016398],"type":"Point"}
}