{
  "type": "Feature",
  "properties": {
    "iso:country":"US",
    "sg:address":"203 N Patrick St",
    "sg:city":"Dublin",
    "sg:classifiers":[
        {
            "category":"Health Services",
            "subcategory":"Clinic",
            "type":"Services"
        }
    ],
    "sg:phone":"+1 254 796 4701",
    "sg:postcode":"76446",
    "sg:province":"TX",
    "sg:tags":[
        "home",
        "care"
    ],
    "wof:name":"Stephens Health Care",
    "wof:placetype":"venue"
},
  "geometry": {"coordinates":[-98.34177099999999,32.086899],"type":"Point"}
}