{
  "type": "Feature",
  "properties": {
    "iso:country":"US",
    "sg:address":"9300 Malibu Ct",
    "sg:city":"Denton",
    "sg:classifiers":[
        {
            "category":"Professional",
            "subcategory":"Management & Consulting",
            "type":"Services"
        },
        {
            "category":"Professional",
            "subcategory":"Advertising",
            "type":"Services"
        }
    ],
    "sg:phone":"+1 940 246 0783",
    "sg:postcode":"76207",
    "sg:province":"TX",
    "sg:tags":[
        "marketing",
        "program",
        "consultant"
    ],
    "wof:name":"Fps Marketing",
    "wof:placetype":"venue"
},
  "geometry": {"coordinates":[-97.23438299999999,33.137829],"type":"Point"}
}