{
  "type": "Feature",
  "properties": {
    "iso:country":"US",
    "sg:address":"716 Rock St",
    "sg:city":"Georgetown",
    "sg:classifiers":[
        {
            "category":"Organizations",
            "subcategory":"Religious Organization",
            "type":"Services"
        }
    ],
    "sg:phone":"+1 512 869 0669",
    "sg:postcode":"78626",
    "sg:province":"TX",
    "wof:name":"Faith Place",
    "wof:placetype":"venue"
},
  "geometry": {"coordinates":[-97.67910500000001,30.637307],"type":"Point"}
}