{
  "type": "Feature",
  "properties": {
    "iso:country":"US",
    "sg:address":"2001 Copper St",
    "sg:city":"Garland",
    "sg:classifiers":[
        {
            "category":"Manufacturing",
            "subcategory":"Wood Products",
            "type":"Manufacturing & Wholesale Goods"
        },
        {
            "category":"Professional",
            "subcategory":"Art Services",
            "type":"Services"
        }
    ],
    "sg:phone":"+1 972 276 5685",
    "sg:postcode":"75042",
    "sg:province":"TX",
    "sg:tags":[
        "picture",
        "frame",
        "frames-wholesale",
        "manufacturer"
    ],
    "sg:website":"http://www.fpfmoulding.com",
    "wof:name":"F P F Moulding",
    "wof:placetype":"venue"
},
  "geometry": {"coordinates":[-96.659447,32.912189],"type":"Point"}
}