{
  "type": "Feature",
  "properties": {
    "iso:country":"US",
    "sg:address":"3107 Willowbrook Ct",
    "sg:city":"Garland",
    "sg:classifiers":[
        {
            "category":"Organizations",
            "subcategory":"Community Association",
            "type":"Services"
        }
    ],
    "sg:phone":"+1 972 495 2117",
    "sg:postcode":"75044",
    "sg:province":"TX",
    "sg:tags":[
        "homeowner"
    ],
    "wof:name":"Duck Creek Town Homes",
    "wof:placetype":"venue"
},
  "geometry": {"coordinates":[-96.676239,32.946101],"type":"Point"}
}