{
  "type": "Feature",
  "properties": {
    "iso:country":"US",
    "sg:address":"5103 Maher Ave",
    "sg:city":"Laredo",
    "sg:classifiers":[
        {
            "category":"Airline",
            "type":"Transportation"
        }
    ],
    "sg:phone":"+1 956 723 0737",
    "sg:postcode":"78041",
    "sg:province":"TX",
    "sg:tags":[
        "cargo",
        "air"
    ],
    "wof:name":"M & M Air Cargo & Delivery Svc",
    "wof:placetype":"venue"
},
  "geometry": {"coordinates":[-99.469756,27.539952],"type":"Point"}
}