{
  "type": "Feature",
  "properties": {
    "iso:country":"US",
    "sg:address":"9614 Dalecrest Dr",
    "sg:city":"Houston",
    "sg:classifiers":[
        {
            "category":"Professional",
            "subcategory":"Management & Consulting",
            "type":"Services"
        }
    ],
    "sg:phone":"+1 713 464 3206",
    "sg:postcode":"77080",
    "sg:province":"TX",
    "sg:tags":[
        "retail",
        "direct",
        "sales"
    ],
    "wof:name":"Century Mag Subscription Agcy",
    "wof:placetype":"venue"
},
  "geometry": {"coordinates":[-95.52664799999999,29.798218],"type":"Point"}
}