{
  "type": "Feature",
  "properties": {
    "iso:country":"US",
    "sg:address":"1113 Main St",
    "sg:city":"Commerce",
    "sg:classifiers":[
        {
            "category":"Restaurant",
            "type":"Food & Drink"
        }
    ],
    "sg:phone":"+1 903 886 2419",
    "sg:postcode":"75428",
    "sg:province":"TX",
    "wof:name":"Legendary Bar-B-Q",
    "wof:placetype":"venue"
},
  "geometry": {"coordinates":[-95.90042200000001,33.250717],"type":"Point"}
}