{
  "type": "Feature",
  "properties": {
    "iso:country":"US",
    "sg:address":"9440 Garland Rd Ste 138",
    "sg:city":"Dallas",
    "sg:classifiers":[
        {
            "category":"Education",
            "subcategory":"Special Training",
            "type":"Public Place"
        }
    ],
    "sg:phone":"+1 214 821 8383",
    "sg:postcode":"75218",
    "sg:province":"TX",
    "sg:tags":[
        "school",
        "art"
    ],
    "sg:website":"www.artisticgatherings.com",
    "wof:name":"Artistic Gatherings",
    "wof:placetype":"venue"
},
  "geometry": {"coordinates":[-96.702851,32.832963],"type":"Point"}
}