{
  "type": "Feature",
  "properties": {
    "iso:country":"US",
    "sg:address":"181 US Hwy 181",
    "sg:city":"Floresville",
    "sg:classifiers":[
        {
            "category":"Professional",
            "type":"Services"
        }
    ],
    "sg:phone":"+1 830 216 7450",
    "sg:postcode":"78114",
    "sg:province":"TX",
    "sg:tags":[
        "establishment"
    ],
    "wof:name":"Mike Lozano Arctic Cat",
    "wof:placetype":"venue"
},
  "geometry": {"coordinates":[-98.169991,29.156498],"type":"Point"}
}