{
  "type": "Feature",
  "properties": {
    "iso:country":"US",
    "sg:address":"202 W Louisiana St",
    "sg:city":"Mc Kinney",
    "sg:classifiers":[
        {
            "category":"Insurance",
            "subcategory":"Insurance Agent",
            "type":"Services"
        }
    ],
    "sg:phone":"+1 972 542 3877",
    "sg:postcode":"75069",
    "sg:province":"TX",
    "wof:name":"Colonial Supplemental Ins Co",
    "wof:placetype":"venue"
},
  "geometry": {"coordinates":[-96.61666200000001,33.19733],"type":"Point"}
}