{
  "type": "Feature",
  "properties": {
    "iso:country":"US",
    "sg:address":"14412 Bellaire Blvd",
    "sg:city":"Houston",
    "sg:classifiers":[
        {
            "category":"Retail",
            "subcategory":"Laundry & Dry Cleaning",
            "type":"Services"
        }
    ],
    "sg:phone":"+1 281 575 1820",
    "sg:postcode":"77083",
    "sg:province":"TX",
    "sg:tags":[
        "drycleaning"
    ],
    "wof:name":"Star Cleaners",
    "wof:placetype":"venue"
},
  "geometry": {"coordinates":[-95.640832,29.704067],"type":"Point"}
}