{
  "type": "Feature",
  "properties": {
    "iso:country":"US",
    "sg:address":"1209 Guildford St",
    "sg:city":"Garland",
    "sg:classifiers":[
        {
            "category":"Real Estate",
            "subcategory":"Real Estate Agent",
            "type":"Services"
        }
    ],
    "sg:phone":"+1 972 495 4524",
    "sg:postcode":"75040",
    "sg:province":"TX",
    "wof:name":"Triality Investments",
    "wof:placetype":"venue"
},
  "geometry": {"coordinates":[-96.646556,32.93739],"type":"Point"}
}