{
  "type": "Feature",
  "properties": {
    "iso:country":"US",
    "sg:address":"406 Elm St",
    "sg:city":"Graham",
    "sg:classifiers":[
        {
            "category":"Real Estate",
            "subcategory":"Real Estate Agent",
            "type":"Services"
        }
    ],
    "sg:phone":"+1 940 549 7500",
    "sg:postcode":"76450",
    "sg:province":"TX",
    "wof:name":"Gilmore Real Estate",
    "wof:placetype":"venue"
},
  "geometry": {"coordinates":[-98.589602,33.109409],"type":"Point"}
}