{
  "type": "Feature",
  "properties": {
    "iso:country":"US",
    "sg:address":"128 Golden Harvest",
    "sg:city":"Buchanan Dam",
    "sg:classifiers":[
        {
            "category":"Professional",
            "type":"Services"
        }
    ],
    "sg:phone":"+1 512 793 6436",
    "sg:postcode":"78609",
    "sg:province":"TX",
    "wof:name":"R & L Tanning",
    "wof:placetype":"venue"
},
  "geometry": {"coordinates":[-98.45695499999999,30.751576],"type":"Point"}
}