{
  "type": "Feature",
  "properties": {
    "iso:country":"US",
    "sg:address":"611 Live Oak Dr",
    "sg:city":"Stafford",
    "sg:classifiers":[
        {
            "category":"Shopping",
            "subcategory":"Clothing, Apparel, & Fashions",
            "type":"Retail Goods"
        }
    ],
    "sg:phone":"+1 281 403 9921",
    "sg:postcode":"77477",
    "sg:province":"TX",
    "sg:tags":[
        "shop",
        "bridal"
    ],
    "wof:name":"Connie's Bridal & More",
    "wof:placetype":"venue"
},
  "geometry": {"coordinates":[-95.55385,29.610306],"type":"Point"}
}