{
  "type": "Feature",
  "properties": {
    "iso:country":"US",
    "sg:address":"2844 Cynthia",
    "sg:city":"Palmer",
    "sg:classifiers":[
        {
            "category":"Retail",
            "subcategory":"Repair Shop",
            "type":"Services"
        }
    ],
    "sg:phone":"+1 972 842 2407",
    "sg:postcode":"75152",
    "sg:province":"TX",
    "sg:tags":[
        "welding"
    ],
    "wof:name":"R & R Welding",
    "wof:placetype":"venue"
},
  "geometry": {"coordinates":[-96.71361400000001,32.486699],"type":"Point"}
}