{
  "type": "Feature",
  "properties": {
    "iso:country":"US",
    "sg:address":"16479 Dallas Pkwy Ste 800",
    "sg:city":"Addison",
    "sg:classifiers":[
        {
            "category":"Professional",
            "subcategory":"Employment Agencies",
            "type":"Services"
        }
    ],
    "sg:phone":"+1 972 250 4504",
    "sg:postcode":"75001",
    "sg:province":"TX",
    "sg:tags":[
        "opportunity"
    ],
    "sg:website":"http://www.compupros.com",
    "wof:name":"Compupros, Ltd.",
    "wof:placetype":"venue"
},
  "geometry": {"coordinates":[-96.823666,32.975276],"type":"Point"}
}