{
  "type": "Feature",
  "properties": {
    "iso:country":"US",
    "sg:address":"6015 Pin Oak Pl",
    "sg:city":"Spring",
    "sg:classifiers":[
        {
            "category":"Recreation",
            "type":"Entertainment"
        }
    ],
    "sg:phone":"+1 281 320 7586",
    "sg:postcode":"77379",
    "sg:province":"TX",
    "wof:name":"Cloud 9 Rides",
    "wof:placetype":"venue"
},
  "geometry": {"coordinates":[-95.50760699999999,30.036897],"type":"Point"}
}