{
  "type": "Feature",
  "properties": {
    "iso:country":"US",
    "sg:address":"14905 Midway Rd",
    "sg:city":"Addison",
    "sg:classifiers":[
        {
            "category":"Restaurant",
            "type":"Food & Drink"
        }
    ],
    "sg:phone":"+1 972 233 0101",
    "sg:postcode":"75001",
    "sg:province":"TX",
    "sg:tags":[
        "eating"
    ],
    "wof:name":"Baja California",
    "wof:placetype":"venue"
},
  "geometry": {"coordinates":[-96.838973,32.951993],"type":"Point"}
}