{
  "type": "Feature",
  "properties": {
    "iso:country":"US",
    "sg:address":"401 Elm Ave",
    "sg:city":"Bryan",
    "sg:classifiers":[
        {
            "category":"Education",
            "subcategory":"School",
            "type":"Public Place"
        }
    ],
    "sg:phone":"+1 979 209 2960",
    "sg:postcode":"77801",
    "sg:province":"TX",
    "sg:tags":[
        "association"
    ],
    "wof:name":"Crockett Elementary School",
    "wof:placetype":"venue"
},
  "geometry": {"coordinates":[-96.352908,30.641696],"type":"Point"}
}