{
  "type": "Feature",
  "properties": {
    "iso:country":"US",
    "sg:address":"1202 W Co Rd 114",
    "sg:city":"Midland",
    "sg:classifiers":[
        {
            "category":"Building & Trades",
            "subcategory":"Construction",
            "type":"Services"
        }
    ],
    "sg:phone":"+1 432 570 7733",
    "sg:postcode":"79706",
    "sg:province":"TX",
    "sg:tags":[
        "contractor"
    ],
    "wof:name":"Design Services Construction",
    "wof:placetype":"venue"
},
  "geometry": {"coordinates":[-102.07619099999999,31.964814],"type":"Point"}
}