{
  "type": "Feature",
  "properties": {
    "iso:country":"US",
    "sg:address":"1024 Shadywood Dr",
    "sg:city":"Cedar Hill",
    "sg:classifiers":[
        {
            "category":"Real Estate",
            "subcategory":"Real Estate Operator",
            "type":"Services"
        }
    ],
    "sg:phone":"+1 972 299 9347",
    "sg:postcode":"75104",
    "sg:province":"TX",
    "sg:tags":[
        "building",
        "nonresidential"
    ],
    "wof:name":"Texas Providence Properties LL",
    "wof:placetype":"venue"
},
  "geometry": {"coordinates":[-96.92006000000001,32.583008],"type":"Point"}
}