{
  "type": "Feature",
  "properties": {
    "iso:country":"US",
    "sg:address":"11323 West Ave",
    "sg:city":"San Antonio",
    "sg:classifiers":[
        {
            "category":"Retail",
            "subcategory":"Repair Shop",
            "type":"Services"
        }
    ],
    "sg:phone":"+1 210 308 0663",
    "sg:postcode":"78213",
    "sg:province":"TX",
    "wof:name":"Rk Shooting Specialties",
    "wof:placetype":"venue"
},
  "geometry": {"coordinates":[-98.511869,29.543579],"type":"Point"}
}