{
  "type": "Feature",
  "properties": {
    "iso:country":"US",
    "sg:address":"5505 N Mesa St",
    "sg:city":"El Paso",
    "sg:classifiers":[
        {
            "category":"Insurance",
            "subcategory":"Insurance Agent",
            "type":"Services"
        }
    ],
    "sg:phone":"+1 915 587 8355",
    "sg:postcode":"79912",
    "sg:province":"TX",
    "wof:name":"Bill Tarpley Insurance",
    "wof:placetype":"venue"
},
  "geometry": {"coordinates":[-106.519386,31.821049],"type":"Point"}
}