{
  "type": "Feature",
  "properties": {
    "iso:country":"US",
    "sg:address":"128 E 2nd St",
    "sg:city":"Irving",
    "sg:classifiers":[
        {
            "category":"Shopping",
            "type":"Retail Goods"
        },
        {
            "category":"Wholesale",
            "subcategory":"Non-durable Goods",
            "type":"Manufacturing & Wholesale Goods"
        }
    ],
    "sg:phone":"+1 972 253 8656",
    "sg:postcode":"75060",
    "sg:province":"TX",
    "sg:tags":[
        "importer"
    ],
    "wof:name":"Cuila Import Export",
    "wof:placetype":"venue"
},
  "geometry": {"coordinates":[-96.94521899999999,32.812751],"type":"Point"}
}