{
  "type": "Feature",
  "properties": {
    "iso:country":"US",
    "sg:address":"3204 Dundee St",
    "sg:city":"El Paso",
    "sg:classifiers":[
        {
            "category":"Health Services",
            "subcategory":"Nursing And Care Facility",
            "type":"Services"
        }
    ],
    "sg:phone":"+1 915 591 3779",
    "sg:postcode":"79925",
    "sg:province":"TX",
    "sg:tags":[
        "intermediate"
    ],
    "wof:name":"A H S",
    "wof:placetype":"venue"
},
  "geometry": {"coordinates":[-106.35337699999999,31.788302],"type":"Point"}
}