{
  "type": "Feature",
  "properties": {
    "iso:country":"US",
    "sg:address":"902 S Ellis St",
    "sg:city":"Groesbeck",
    "sg:classifiers":[
        {
            "category":"Retail",
            "subcategory":"Veterinary Services",
            "type":"Services"
        }
    ],
    "sg:phone":"+1 254 729 5254",
    "sg:postcode":"76642",
    "sg:province":"TX",
    "sg:tags":[
        "hospital",
        "animal"
    ],
    "wof:name":"Groesbeck Veterinary Hospital",
    "wof:placetype":"venue"
},
  "geometry": {"coordinates":[-96.54006200000001,31.516421],"type":"Point"}
}