{
  "type": "Feature",
  "properties": {
    "iso:country":"US",
    "sg:address":"10135 W Co Rd 117",
    "sg:city":"Midland",
    "sg:classifiers":[
        {
            "category":"Building & Trades",
            "subcategory":"Electrical",
            "type":"Services"
        }
    ],
    "sg:phone":"+1 432 561 8886",
    "sg:postcode":"79706",
    "sg:province":"TX",
    "sg:tags":[
        "electric",
        "contractor"
    ],
    "wof:name":"Red Simpson Inc",
    "wof:placetype":"venue"
},
  "geometry": {"coordinates":[-102.217842,31.925178],"type":"Point"}
}