{
  "type": "Feature",
  "properties": {
    "iso:country":"US",
    "sg:address":"29639 FM 2978",
    "sg:city":"Magnolia",
    "sg:classifiers":[
        {
            "category":"Building & Trades",
            "subcategory":"Construction",
            "type":"Services"
        }
    ],
    "sg:phone":"+1 281 356 6700",
    "sg:postcode":"77354",
    "sg:province":"TX",
    "sg:tags":[
        "fabricator",
        "metal"
    ],
    "wof:name":"Enviroflex Design & Mfg",
    "wof:placetype":"venue"
},
  "geometry": {"coordinates":[-95.59365099999999,30.186761],"type":"Point"}
}