{
  "type": "Feature",
  "properties": {
    "iso:country":"US",
    "sg:address":"10306 Willowick Ln",
    "sg:city":"San Antonio",
    "sg:classifiers":[
        {
            "category":"Manufacturing",
            "subcategory":"Retail Goods",
            "type":"Manufacturing & Wholesale Goods"
        }
    ],
    "sg:phone":"+1 210 653 7791",
    "sg:postcode":"78217",
    "sg:province":"TX",
    "sg:tags":[
        "product",
        "mfg"
    ],
    "wof:name":"Bruce E Venable",
    "wof:placetype":"venue"
},
  "geometry": {"coordinates":[-98.44480799999999,29.530989],"type":"Point"}
}