{
  "type": "Feature",
  "properties": {
    "iso:country":"US",
    "sg:address":"80 Red River St",
    "sg:city":"Austin",
    "sg:classifiers":[
        {
            "category":"Education",
            "subcategory":"Special Training",
            "type":"Public Place"
        }
    ],
    "sg:phone":"+1 512 479 5004",
    "sg:postcode":"78701",
    "sg:province":"TX",
    "sg:tags":[
        "instruction",
        "music"
    ],
    "sg:website":"www.marcilynne.com",
    "wof:name":"Marci Lynne's Singing/Perfrmnc",
    "wof:placetype":"venue"
},
  "geometry": {"coordinates":[-97.739272,30.26062],"type":"Point"}
}