{
  "type": "Feature",
  "properties": {
    "iso:country":"US",
    "sg:address":"12822 Chiswick Rd",
    "sg:city":"Houston",
    "sg:classifiers":[
        {
            "category":"Building & Trades",
            "subcategory":"Plumbing",
            "type":"Services"
        }
    ],
    "sg:phone":"+1 713 413 4445",
    "sg:postcode":"77047",
    "sg:province":"TX",
    "sg:tags":[
        "contractor"
    ],
    "wof:name":"Peoples Air Conditioning and",
    "wof:placetype":"venue"
},
  "geometry": {"coordinates":[-95.404594,29.619967],"type":"Point"}
}