{
  "type": "Feature",
  "properties": {
    "iso:country":"US",
    "sg:address":"1935 Cordoba Dr",
    "sg:city":"Brownsville",
    "sg:classifiers":[
        {
            "category":"Health Services",
            "subcategory":"Clinic",
            "type":"Services"
        }
    ],
    "sg:phone":"+1 956 546 8037",
    "sg:postcode":"78521",
    "sg:province":"TX",
    "wof:name":"Amor Health Services",
    "wof:placetype":"venue"
},
  "geometry": {"coordinates":[-97.44113400000001,25.881719],"type":"Point"}
}