{
  "type": "Feature",
  "properties": {
    "iso:country":"US",
    "sg:address":"3001 NE 28th St",
    "sg:city":"Fort Worth",
    "sg:classifiers":[
        {
            "category":"Autos & Motor Vehicles",
            "subcategory":"Automobile Sales",
            "type":"Retail Goods"
        }
    ],
    "sg:phone":"+1 817 222 0711",
    "sg:postcode":"76111",
    "sg:province":"TX",
    "sg:tags":[
        "car",
        "dealer"
    ],
    "wof:name":"Madina Auto Sales",
    "wof:placetype":"venue"
},
  "geometry": {"coordinates":[-97.30265199999999,32.795206],"type":"Point"}
}