{
  "type": "Feature",
  "properties": {
    "iso:country":"US",
    "sg:address":"222 W Bedford Euless Rd",
    "sg:city":"Hurst",
    "sg:classifiers":[
        {
            "category":"Freight",
            "type":"Transportation"
        }
    ],
    "sg:phone":"+1 817 268 8833",
    "sg:postcode":"76053",
    "sg:province":"TX",
    "sg:tags":[
        "operator",
        "local",
        "trucking"
    ],
    "wof:name":"Main Delivery Service Inc",
    "wof:placetype":"venue"
},
  "geometry": {"coordinates":[-97.1725,32.834032],"type":"Point"}
}