{
  "type": "Feature",
  "properties": {
    "iso:country":"US",
    "sg:address":"801 E Ave B",
    "sg:city":"Robstown",
    "sg:classifiers":[
        {
            "category":"Personal",
            "subcategory":"Beauty Salon",
            "type":"Services"
        },
        {
            "category":"Personal",
            "subcategory":"Barber",
            "type":"Services"
        }
    ],
    "sg:phone":"+1 361 767 9334",
    "sg:postcode":"78380",
    "sg:province":"TX",
    "sg:tags":[
        "shop"
    ],
    "wof:name":"Yvonne's Family Hair Salon",
    "wof:placetype":"venue"
},
  "geometry": {"coordinates":[-97.65660800000001,27.789403],"type":"Point"}
}