{
  "type": "Feature",
  "properties": {
    "iso:country":"US",
    "sg:address":"3662 Westchase Dr",
    "sg:city":"Houston",
    "sg:classifiers":[
        {
            "category":"Banks & Credit Unions",
            "subcategory":"Investment Brokerage",
            "type":"Services"
        }
    ],
    "sg:phone":"+1 713 623 6456",
    "sg:postcode":"77042",
    "sg:province":"TX",
    "sg:tags":[
        "advisory",
        "financial"
    ],
    "wof:name":"Spinnaker Financial",
    "wof:placetype":"venue"
},
  "geometry": {"coordinates":[-95.55109,29.724088],"type":"Point"}
}