{
  "type": "Feature",
  "properties": {
    "iso:country":"US",
    "sg:address":"300 S Mill St",
    "sg:city":"Cleburne",
    "sg:classifiers":[
        {
            "category":"Retail",
            "subcategory":"Animal Services",
            "type":"Services"
        }
    ],
    "sg:phone":"+1 817 641 4821",
    "sg:postcode":"76033",
    "sg:province":"TX",
    "sg:tags":[
        "pet",
        "grooming",
        "washing"
    ],
    "wof:name":"Classie Lassie Dog Grooming",
    "wof:placetype":"venue"
},
  "geometry": {"coordinates":[-97.38674899999999,32.344484],"type":"Point"}
}