{
  "type": "Feature",
  "properties": {
    "iso:country":"US",
    "sg:address":"4818 Vicksburg St",
    "sg:city":"Dallas",
    "sg:classifiers":[
        {
            "category":"Restaurant",
            "type":"Food & Drink"
        }
    ],
    "sg:phone":"+1 214 343 1960",
    "sg:postcode":"75207",
    "sg:province":"TX",
    "sg:tags":[
        "parlor",
        "ice",
        "cream"
    ],
    "wof:name":"Ujuogo Ice Cream",
    "wof:placetype":"venue"
},
  "geometry": {"coordinates":[-96.850106,32.807084],"type":"Point"}
}