{
  "type": "Feature",
  "properties": {
    "iso:country":"US",
    "sg:address":"1705 N Town East Blvd",
    "sg:city":"Mesquite",
    "sg:classifiers":[
        {
            "category":"Shopping",
            "subcategory":"Gifts & Souvenirs",
            "type":"Retail Goods"
        },
        {
            "category":"Home & Garden",
            "subcategory":"Home Furnishings",
            "type":"Retail Goods"
        },
        {
            "category":"Building & Trades",
            "subcategory":"Construction",
            "type":"Services"
        }
    ],
    "sg:phone":"+1 972 270 0551",
    "sg:postcode":"75150",
    "sg:province":"TX",
    "sg:tags":[
        "shop",
        "house",
        "interior",
        "design"
    ],
    "sg:website":"http://www.kirklands.com",
    "wof:name":"Kirkland's",
    "wof:placetype":"venue"
},
  "geometry": {"coordinates":[-96.624021,32.810834],"type":"Point"}
}