{
  "type": "Feature",
  "properties": {
    "iso:country":"US",
    "sg:address":"12831 Kingsbridge Ln",
    "sg:city":"Houston",
    "sg:classifiers":[
        {
            "category":"Professional",
            "type":"Services"
        }
    ],
    "sg:phone":"+1 281 558 3049",
    "sg:postcode":"77077",
    "sg:province":"TX",
    "wof:name":"Jko Gp LLC",
    "wof:placetype":"venue"
},
  "geometry": {"coordinates":[-95.614654,29.760457],"type":"Point"}
}