{
  "type": "Feature",
  "properties": {
    "iso:country":"US",
    "sg:address":"99 Trophy Club Dr",
    "sg:city":"Roanoke",
    "sg:classifiers":[
        {
            "category":"Home & Garden",
            "subcategory":"Household Appliances",
            "type":"Retail Goods"
        }
    ],
    "sg:phone":"+1 817 430 5902",
    "sg:postcode":"76262",
    "sg:province":"TX",
    "wof:name":"Universal Compression",
    "wof:placetype":"venue"
},
  "geometry": {"coordinates":[-97.190083,32.994664],"type":"Point"}
}