{
  "type": "Feature",
  "properties": {
    "iso:country":"US",
    "sg:address":"2702 McKinney St",
    "sg:city":"Melissa",
    "sg:classifiers":[
        {
            "category":"Building & Trades",
            "subcategory":"Construction",
            "type":"Services"
        }
    ],
    "sg:phone":"+1 972 838 2700",
    "sg:postcode":"75454",
    "sg:province":"TX",
    "sg:tags":[
        "mfg",
        "kitchen",
        "cabinet",
        "wood",
        "contractor",
        "carpentry"
    ],
    "wof:name":"Daycor Enterprises Inc",
    "wof:placetype":"venue"
},
  "geometry": {"coordinates":[-96.574549,33.284669],"type":"Point"}
}