{
  "type": "Feature",
  "properties": {
    "iso:country":"US",
    "sg:address":"32635 US Hwy 281",
    "sg:city":"Bulverde",
    "sg:classifiers":[
        {
            "category":"Health Services",
            "subcategory":"Doctor",
            "type":"Services"
        }
    ],
    "sg:phone":"+1 830 980 6437",
    "sg:postcode":"78163",
    "sg:province":"TX",
    "sg:tags":[
        "clinic"
    ],
    "wof:name":"Family Clinic Of Bulverde",
    "wof:placetype":"venue"
},
  "geometry": {"coordinates":[-98.419135,29.797615],"type":"Point"}
}