{
  "type": "Feature",
  "properties": {
    "iso:country":"US",
    "sg:address":"2420 Zeppelin Dr",
    "sg:city":"Cedar Park",
    "sg:classifiers":[
        {
            "category":"Education",
            "subcategory":"School",
            "type":"Public Place"
        }
    ],
    "sg:phone":"+1 512 434 7176",
    "sg:postcode":"78613",
    "sg:province":"TX",
    "sg:tags":[
        "high",
        "middle",
        "elementary"
    ],
    "wof:name":"Leander Independent School District",
    "wof:placetype":"venue"
},
  "geometry": {"coordinates":[-97.849987,30.485162],"type":"Point"}
}