{
  "type": "Feature",
  "properties": {
    "iso:country":"US",
    "sg:address":"2929 Allen Parkway",
    "sg:city":"Houston",
    "sg:classifiers":[
        {
            "category":"Professional",
            "subcategory":"Computer Services",
            "type":"Services"
        }
    ],
    "sg:phone":"+1 800 956 6198",
    "sg:postcode":"77019",
    "sg:province":"TX",
    "sg:tags":[
        "cdp",
        "continuous-data-protection",
        "backup",
        "data-backup",
        "data-protection",
        "disaster-recovery",
        "backup-solution",
        "web-hosting",
        "hosting",
        "service",
        "recovery",
        "software"
    ],
    "sg:website":"http://www.r1soft.com/",
    "wof:name":"R1Soft",
    "wof:placetype":"venue"
},
  "geometry": {"coordinates":[-95.3969,29.761575],"type":"Point"}
}