{
  "type": "Feature",
  "properties": {
    "iso:country":"US",
    "sg:address":"3620 Country Vista Dr",
    "sg:city":"Burleson",
    "sg:classifiers":[
        {
            "category":"Building & Trades",
            "subcategory":"Electrical",
            "type":"Services"
        }
    ],
    "sg:phone":"+1 817 572 5544",
    "sg:postcode":"76028",
    "sg:province":"TX",
    "sg:tags":[
        "electrical",
        "contractor"
    ],
    "wof:name":"Bingham Electrical Surplus",
    "wof:placetype":"venue"
},
  "geometry": {"coordinates":[-97.25770799999999,32.548709],"type":"Point"}
}