{
  "type": "Feature",
  "properties": {
    "iso:country":"US",
    "sg:address":"9451 Cayo Blanco Ct",
    "sg:city":"Dallas",
    "sg:classifiers":[
        {
            "category":"Professional",
            "subcategory":"Art Services",
            "type":"Services"
        }
    ],
    "sg:phone":"+1 972 863 3923",
    "sg:postcode":"75217",
    "sg:province":"TX",
    "sg:tags":[
        "designer",
        "display",
        "producer"
    ],
    "wof:name":"Printex Design",
    "wof:placetype":"venue"
},
  "geometry": {"coordinates":[-96.66014199999999,32.685471],"type":"Point"}
}