{
  "type": "Feature",
  "properties": {
    "iso:country":"US",
    "sg:address":"9005 Mountain Ridge Dr Ste 100",
    "sg:city":"Austin",
    "sg:classifiers":[
        {
            "category":"Professional",
            "subcategory":"Engineering",
            "type":"Services"
        },
        {
            "category":"Professional",
            "subcategory":"Computer Services",
            "type":"Services"
        }
    ],
    "sg:phone":"+1 512 346 7743",
    "sg:postcode":"78759",
    "sg:province":"TX",
    "sg:tags":[
        "publisher",
        "designer",
        "engineer",
        "repair",
        "consultant",
        "system",
        "integration",
        "developer",
        "software"
    ],
    "sg:website":"www.spiceworks.com",
    "wof:name":"Spiceworks",
    "wof:placetype":"venue"
},
  "geometry": {"coordinates":[-97.752898,30.386497],"type":"Point"}
}