{
  "type": "Feature",
  "properties": {
    "iso:country":"US",
    "sg:address":"1303 W Dickinson Blvd",
    "sg:city":"Fort Stockton",
    "sg:classifiers":[
        {
            "category":"Cinema",
            "subcategory":"Movie Rental",
            "type":"Entertainment"
        }
    ],
    "sg:phone":"+1 432 336 8197",
    "sg:postcode":"79735",
    "sg:province":"TX",
    "sg:tags":[
        "video",
        "tape"
    ],
    "wof:name":"Showtyme Video",
    "wof:placetype":"venue"
},
  "geometry": {"coordinates":[-102.89328999999999,30.893854],"type":"Point"}
}