{
  "type": "Feature",
  "properties": {
    "iso:country":"US",
    "sg:address":"109 E Ogden St",
    "sg:city":"Del Rio",
    "sg:classifiers":[
        {
            "category":"Shopping",
            "subcategory":"Clothing, Apparel, & Fashions",
            "type":"Retail Goods"
        }
    ],
    "sg:phone":"+1 830 774 6000",
    "sg:postcode":"78840",
    "sg:province":"TX",
    "sg:tags":[
        "merchandise"
    ],
    "wof:name":"T-Shirts Et Cetera & Athc Sup",
    "wof:placetype":"venue"
},
  "geometry": {"coordinates":[-100.899728,29.363047],"type":"Point"}
}