{
  "type": "Feature",
  "properties": {
    "iso:country":"US",
    "sg:address":"1819 E Main St",
    "sg:city":"League City",
    "sg:classifiers":[
        {
            "category":"Professional",
            "subcategory":"Business Services",
            "type":"Services"
        }
    ],
    "sg:phone":"+1 281 332 0920",
    "sg:postcode":"77573",
    "sg:province":"TX",
    "sg:tags":[
        "interior",
        "consultant",
        "design",
        "decorator"
    ],
    "wof:name":"Interiors By Anniece",
    "wof:placetype":"venue"
},
  "geometry": {"coordinates":[-95.07888,29.519979],"type":"Point"}
}