{
  "type": "Feature",
  "properties": {
    "iso:country":"US",
    "sg:address":"2300 Lex Ave",
    "sg:city":"Tyler",
    "sg:classifiers":[
        {
            "category":"Building & Trades",
            "subcategory":"Construction",
            "type":"Services"
        }
    ],
    "sg:phone":"+1 903 363 3265",
    "sg:postcode":"75702",
    "sg:province":"TX",
    "sg:tags":[
        "wallcoverings-installation",
        "wallpaper",
        "painting",
        "contractor"
    ],
    "wof:name":"Munoz Painting",
    "wof:placetype":"venue"
},
  "geometry": {"coordinates":[-95.27555099999999,32.373176],"type":"Point"}
}