{
  "type": "Feature",
  "properties": {
    "iso:country":"US",
    "sg:address":"15918 Escher Rd",
    "sg:city":"Cypress",
    "sg:classifiers":[
        {
            "category":"Building & Trades",
            "subcategory":"Construction",
            "type":"Services"
        }
    ],
    "sg:phone":"+1 281 290 7265",
    "sg:postcode":"77433",
    "sg:province":"TX",
    "wof:name":"Elite Utility Services Inc",
    "wof:placetype":"venue"
},
  "geometry": {"coordinates":[-95.727147,30.007279],"type":"Point"}
}