{
  "type": "Feature",
  "properties": {
    "iso:country":"US",
    "sg:address":"205 del Roy Ln",
    "sg:city":"Longview",
    "sg:classifiers":[
        {
            "category":"Autos & Motor Vehicles",
            "subcategory":"Automobile Sales",
            "type":"Retail Goods"
        }
    ],
    "sg:phone":"+1 903 234 1864",
    "sg:postcode":"75604",
    "sg:province":"TX",
    "sg:tags":[
        "car",
        "dealer"
    ],
    "wof:name":"Pro Truck Auto Sales",
    "wof:placetype":"venue"
},
  "geometry": {"coordinates":[-94.760836,32.478248],"type":"Point"}
}