{
  "type": "Feature",
  "properties": {
    "iso:country":"US",
    "sg:address":"4417 Avenue S",
    "sg:city":"Galveston",
    "sg:classifiers":[
        {
            "category":"Retail",
            "subcategory":"Laundry & Dry Cleaning",
            "type":"Services"
        }
    ],
    "sg:phone":"+1 409 762 3738",
    "sg:postcode":"77550",
    "sg:province":"TX",
    "sg:tags":[
        "cleaners"
    ],
    "wof:name":"Lonestar Cleaners",
    "wof:placetype":"venue"
},
  "geometry": {"coordinates":[-94.81255,29.280284],"type":"Point"}
}