{
  "type": "Feature",
  "properties": {
    "iso:country":"US",
    "sg:address":"697 Metro Park Cir",
    "sg:city":"Lewisville",
    "sg:classifiers":[
        {
            "category":"Building & Trades",
            "subcategory":"Cleaning & Sanitation",
            "type":"Services"
        }
    ],
    "sg:phone":"+1 972 434 0101",
    "sg:postcode":"75057",
    "sg:province":"TX",
    "sg:tags":[
        "carpet"
    ],
    "wof:name":"Amigos Carpet Cleaning & Services Inc",
    "wof:placetype":"venue"
},
  "geometry": {"coordinates":[-96.983704,33.040298],"type":"Point"}
}