{
  "type": "Feature",
  "properties": {
    "iso:country":"US",
    "sg:address":"902 W Main St",
    "sg:city":"Brownfield",
    "sg:phone":"+1 806 637 4517",
    "sg:postcode":"79316",
    "sg:province":"TX",
    "sg:tags":[
        "gas"
    ],
    "wof:name":"Brownfield Farmer's Co-Op",
    "wof:placetype":"venue"
},
  "geometry": {"coordinates":[-102.285009,33.179078],"type":"Point"}
}