{
  "type": "Feature",
  "properties": {
    "iso:country":"US",
    "sg:address":"9931 Harwin Dr",
    "sg:city":"Houston",
    "sg:classifiers":[
        {
            "category":"Wholesale",
            "subcategory":"Tobacco Products",
            "type":"Manufacturing & Wholesale Goods"
        }
    ],
    "sg:phone":"+1 832 252 7808",
    "sg:postcode":"77036",
    "sg:province":"TX",
    "sg:tags":[
        "cigarette",
        "cigar",
        "dealer"
    ],
    "wof:name":"General Tobacco Wholesaler",
    "wof:placetype":"venue"
},
  "geometry": {"coordinates":[-95.53735,29.717649],"type":"Point"}
}