{
  "type": "Feature",
  "properties": {
    "iso:country":"US",
    "sg:address":"15247 Bedford Glen Dr",
    "sg:city":"Channelview",
    "sg:classifiers":[
        {
            "category":"Education",
            "subcategory":"School",
            "type":"Public Place"
        }
    ],
    "sg:phone":"+1 281 457 9769",
    "sg:postcode":"77530",
    "sg:province":"TX",
    "sg:tags":[
        "k-",
        "private"
    ],
    "wof:name":"Schools Latlsha",
    "wof:placetype":"venue"
},
  "geometry": {"coordinates":[-95.145009,29.802306],"type":"Point"}
}