{
  "type": "Feature",
  "properties": {
    "iso:country":"US",
    "sg:address":"6540 Richmond Dr",
    "sg:city":"Frisco",
    "sg:classifiers":[
        {
            "category":"Professional",
            "type":"Services"
        }
    ],
    "sg:phone":"+1 972 712 6228",
    "sg:postcode":"75035",
    "sg:province":"TX",
    "wof:name":"Innergy Wear",
    "wof:placetype":"venue"
},
  "geometry": {"coordinates":[-96.778477,33.132537],"type":"Point"}
}