{
  "type": "Feature",
  "properties": {
    "iso:country":"US",
    "sg:address":"14 Rosedale Brook Ct",
    "sg:city":"Spring",
    "sg:classifiers":[
        {
            "category":"Shopping",
            "subcategory":"Catalog Store",
            "type":"Retail Goods"
        }
    ],
    "sg:phone":"+1 713 880 9959",
    "sg:postcode":"77381",
    "sg:province":"TX",
    "sg:tags":[
        "house",
        "mail"
    ],
    "wof:name":"Remedial Music & Records",
    "wof:placetype":"venue"
},
  "geometry": {"coordinates":[-95.49451999999999,30.161415],"type":"Point"}
}