{
  "type": "Feature",
  "properties": {
    "iso:country":"US",
    "sg:address":"927 E Renfro St",
    "sg:city":"Burleson",
    "sg:classifiers":[
        {
            "category":"Building & Trades",
            "subcategory":"Electrical",
            "type":"Services"
        }
    ],
    "sg:phone":"+1 817 295 4307",
    "sg:postcode":"76028",
    "sg:province":"TX",
    "sg:tags":[
        "electrical",
        "contractor"
    ],
    "wof:name":"Blackmon Bunch Electric",
    "wof:placetype":"venue"
},
  "geometry": {"coordinates":[-97.299633,32.537213],"type":"Point"}
}