{
  "type": "Feature",
  "properties": {
    "iso:country":"US",
    "sg:address":"6334 N New Braunfels Ave",
    "sg:city":"San Antonio",
    "sg:classifiers":[
        {
            "category":"Shopping",
            "subcategory":"Clothing, Apparel, & Fashions",
            "type":"Retail Goods"
        }
    ],
    "sg:phone":"+1 210 824 0052",
    "sg:postcode":"78209",
    "sg:province":"TX",
    "sg:tags":[
        "maternity"
    ],
    "wof:name":"Mamacitas",
    "wof:placetype":"venue"
},
  "geometry": {"coordinates":[-98.459165,29.485702],"type":"Point"}
}