{
  "type": "Feature",
  "properties": {
    "iso:country":"US",
    "sg:address":"1950 N Stemmons Fwy",
    "sg:city":"Dallas",
    "sg:classifiers":[
        {
            "category":"Professional",
            "subcategory":"Employment Agencies",
            "type":"Services"
        }
    ],
    "sg:phone":"+1 214 800 4949",
    "sg:postcode":"75207",
    "sg:province":"TX",
    "wof:name":"Advanced Placement Team",
    "wof:placetype":"venue"
},
  "geometry": {"coordinates":[-96.825104,32.798199],"type":"Point"}
}