{
  "type": "Feature",
  "properties": {
    "iso:country":"US",
    "sg:address":"4801 Fairway Blvd",
    "sg:city":"Wichita Falls",
    "sg:classifiers":[
        {
            "category":"Retail",
            "subcategory":"Auto Repair",
            "type":"Services"
        }
    ],
    "sg:phone":"+1 940 691 5934",
    "sg:postcode":"76310",
    "sg:province":"TX",
    "sg:tags":[
        "transmission"
    ],
    "wof:name":"Quality Transmissions Inc",
    "wof:placetype":"venue"
},
  "geometry": {"coordinates":[-98.561166,33.853429],"type":"Point"}
}