{
  "type": "Feature",
  "properties": {
    "iso:country":"US",
    "sg:address":"9410 Hudson Bend Cir",
    "sg:city":"Houston",
    "sg:classifiers":[
        {
            "category":"Home & Garden",
            "subcategory":"Furniture",
            "type":"Retail Goods"
        }
    ],
    "sg:phone":"+1 281 861 8839",
    "sg:postcode":"77095",
    "sg:province":"TX",
    "wof:name":"Furniture By Loyce",
    "wof:placetype":"venue"
},
  "geometry": {"coordinates":[-95.639577,29.913585],"type":"Point"}
}