{
  "type": "Feature",
  "properties": {
    "iso:country":"US",
    "sg:address":"5117 Belaire Dr",
    "sg:city":"Midland",
    "sg:classifiers":[
        {
            "category":"Shopping",
            "subcategory":"Bicycles & Sporting Goods",
            "type":"Retail Goods"
        }
    ],
    "sg:phone":"+1 432 520 4055",
    "sg:postcode":"79703",
    "sg:province":"TX",
    "wof:name":"Michaels Rifles",
    "wof:placetype":"venue"
},
  "geometry": {"coordinates":[-102.14583399999999,31.986734],"type":"Point"}
}