{
  "type": "Feature",
  "properties": {
    "iso:country":"US",
    "sg:address":"401 N Central Expy",
    "sg:city":"Mc Kinney",
    "sg:classifiers":[
        {
            "category":"Professional",
            "subcategory":"Employment Agencies",
            "type":"Services"
        }
    ],
    "sg:phone":"+1 972 547 4040",
    "sg:postcode":"75070",
    "sg:province":"TX",
    "sg:tags":[
        "help",
        "supply"
    ],
    "wof:name":"Instaff",
    "wof:placetype":"venue"
},
  "geometry": {"coordinates":[-96.639154,33.201328],"type":"Point"}
}