{
  "type": "Feature",
  "properties": {
    "iso:country":"US",
    "sg:address":"1305 Tahoka Rd",
    "sg:city":"Brownfield",
    "sg:classifiers":[
        {
            "category":"Personal",
            "subcategory":"Beauty Salon",
            "type":"Services"
        }
    ],
    "sg:phone":"+1 806 637 3532",
    "sg:postcode":"79316",
    "sg:province":"TX",
    "sg:tags":[
        "shop"
    ],
    "wof:name":"Classic Hair & Nail Design",
    "wof:placetype":"venue"
},
  "geometry": {"coordinates":[-102.259275,33.181114],"type":"Point"}
}