{
  "type": "Feature",
  "properties": {
    "iso:country":"US",
    "sg:address":"3015 W 26th Ave",
    "sg:city":"Amarillo",
    "sg:classifiers":[
        {
            "category":"Autos & Motor Vehicles",
            "subcategory":"Auto Supplies",
            "type":"Retail Goods"
        }
    ],
    "sg:phone":"+1 806 356 8785",
    "sg:postcode":"79109",
    "sg:province":"TX",
    "sg:tags":[
        "automobile",
        "accessory"
    ],
    "sg:website":"www.fxmotorsports.com",
    "wof:name":"F/X Motor Sports",
    "wof:placetype":"venue"
},
  "geometry": {"coordinates":[-101.873316,35.185695],"type":"Point"}
}