{
  "type": "Feature",
  "properties": {
    "iso:country":"US",
    "sg:address":"6124 Ravenswood Dr",
    "sg:city":"Fort Worth",
    "sg:classifiers":[
        {
            "category":"Professional",
            "type":"Services"
        }
    ],
    "sg:phone":"+1 817 451 3960",
    "sg:postcode":"76112",
    "sg:province":"TX",
    "wof:name":"Oaklea LLC",
    "wof:placetype":"venue"
},
  "geometry": {"coordinates":[-97.226181,32.757749],"type":"Point"}
}