{
  "type": "Feature",
  "properties": {
    "iso:country":"US",
    "sg:address":"2405 W Arkansas Ln",
    "sg:city":"Arlington",
    "sg:classifiers":[
        {
            "category":"Building & Trades",
            "subcategory":"Construction",
            "type":"Services"
        }
    ],
    "sg:phone":"+1 817 801 9696",
    "sg:postcode":"76013",
    "sg:province":"TX",
    "sg:tags":[
        "contractor"
    ],
    "wof:name":"No Burn of Tarrant County",
    "wof:placetype":"venue"
},
  "geometry": {"coordinates":[-97.149083,32.706864],"type":"Point"}
}