{
  "type": "Feature",
  "properties": {
    "iso:country":"US",
    "sg:address":"201 S 2nd St",
    "sg:city":"Albany",
    "sg:classifiers":[
        {
            "category":"Organizations",
            "subcategory":"Non-profit Organization",
            "type":"Services"
        },
        {
            "category":"Museum",
            "type":"Entertainment"
        }
    ],
    "sg:phone":"+1 325 762 2269",
    "sg:postcode":"76430",
    "sg:province":"TX",
    "sg:tags":[
        "art"
    ],
    "wof:name":"Old Jail Art Center",
    "wof:placetype":"venue"
},
  "geometry": {"coordinates":[-99.29735100000001,32.723448],"type":"Point"}
}