{
  "type": "Feature",
  "properties": {
    "iso:country":"US",
    "sg:address":"903 W Davis St",
    "sg:city":"Conroe",
    "sg:classifiers":[
        {
            "category":"Shopping",
            "subcategory":"Florist",
            "type":"Retail Goods"
        }
    ],
    "sg:phone":"+1 936 756 5000",
    "sg:postcode":"77301",
    "sg:province":"TX",
    "sg:tags":[
        "shop"
    ],
    "wof:name":"Flowers Plus Inc",
    "wof:placetype":"venue"
},
  "geometry": {"coordinates":[-95.46911799999999,30.31379],"type":"Point"}
}