{
  "type": "Feature",
  "properties": {
    "iso:country":"US",
    "sg:address":"3306 Wiley Post Rd",
    "sg:city":"Carrollton",
    "sg:classifiers":[
        {
            "category":"Manufacturing",
            "subcategory":"Printing",
            "type":"Manufacturing & Wholesale Goods"
        }
    ],
    "sg:phone":"+1 972 701 6927",
    "sg:postcode":"75006",
    "sg:province":"TX",
    "sg:tags":[
        "lithographic",
        "commercial",
        "reproduction"
    ],
    "wof:name":"Tower Printing",
    "wof:placetype":"venue"
},
  "geometry": {"coordinates":[-96.844979,32.960447],"type":"Point"}
}