{
  "type": "Feature",
  "properties": {
    "iso:country":"US",
    "sg:address":"502 N Home St",
    "sg:city":"Corrigan",
    "sg:classifiers":[
        {
            "category":"Government",
            "subcategory":"Post Office",
            "type":"Public Place"
        }
    ],
    "sg:phone":"+1 936 398 4555",
    "sg:postcode":"75939",
    "sg:province":"TX",
    "wof:name":"US Post Office",
    "wof:placetype":"venue"
},
  "geometry": {"coordinates":[-94.825236,31.00353],"type":"Point"}
}