{
  "type": "Feature",
  "properties": {
    "iso:country":"US",
    "sg:address":"231 Greenway St",
    "sg:city":"Sunnyvale",
    "sg:classifiers":[
        {
            "category":"Health Services",
            "subcategory":"Doctor",
            "type":"Services"
        }
    ],
    "sg:phone":"+1 214 614 7307",
    "sg:postcode":"75182",
    "sg:province":"TX",
    "wof:name":"MD Firm Inc The",
    "wof:placetype":"venue"
},
  "geometry": {"coordinates":[-96.592082,32.82204],"type":"Point"}
}