{
  "type": "Feature",
  "properties": {
    "iso:country":"US",
    "sg:address":"1030 Pampa St",
    "sg:city":"Pasadena",
    "sg:classifiers":[
        {
            "category":"Manufacturing",
            "subcategory":"Wood Products",
            "type":"Manufacturing & Wholesale Goods"
        }
    ],
    "sg:phone":"+1 713 947 0749",
    "sg:postcode":"77504",
    "sg:province":"TX",
    "sg:tags":[
        "mfg"
    ],
    "wof:name":"Great Southern Woodworking",
    "wof:placetype":"venue"
},
  "geometry": {"coordinates":[-95.19992000000001,29.656411],"type":"Point"}
}