{
  "type": "Feature",
  "properties": {
    "iso:country":"US",
    "sg:address":"2720 Bataan St",
    "sg:city":"Dallas",
    "sg:classifiers":[
        {
            "category":"Wholesale",
            "subcategory":"Electrical",
            "type":"Manufacturing & Wholesale Goods"
        }
    ],
    "sg:phone":"+1 214 747 6119",
    "sg:postcode":"75212",
    "sg:province":"TX",
    "sg:tags":[
        "electric",
        "motor"
    ],
    "wof:name":"Metroplex Armature Works",
    "wof:placetype":"venue"
},
  "geometry": {"coordinates":[-96.83219800000001,32.776886],"type":"Point"}
}