{
  "type": "Feature",
  "properties": {
    "iso:country":"US",
    "sg:address":"2390 Dowlen Rd",
    "sg:city":"Beaumont",
    "sg:classifiers":[
        {
            "category":"Real Estate",
            "subcategory":"Real Estate Services",
            "type":"Services"
        }
    ],
    "sg:phone":"+1 409 866 8880",
    "sg:postcode":"77706",
    "sg:province":"TX",
    "sg:tags":[
        "home",
        "property",
        "issue",
        "for",
        "title"
    ],
    "wof:name":"Stewart Title Co",
    "wof:placetype":"venue"
},
  "geometry": {"coordinates":[-94.168244,30.103851],"type":"Point"}
}