{
  "type": "Feature",
  "properties": {
    "iso:country":"US",
    "sg:address":"201 Main St",
    "sg:city":"Kerrville",
    "sg:classifiers":[
        {
            "category":"Autos & Motor Vehicles",
            "subcategory":"Automobile Sales",
            "type":"Retail Goods"
        }
    ],
    "sg:phone":"+1 830 792 5115",
    "sg:postcode":"78028",
    "sg:province":"TX",
    "sg:tags":[
        "used"
    ],
    "wof:name":"Family Auto Sales",
    "wof:placetype":"venue"
},
  "geometry": {"coordinates":[-99.14581200000001,30.052041],"type":"Point"}
}