{
  "type": "Feature",
  "properties": {
    "iso:country":"US",
    "sg:address":"1016 Harrison St",
    "sg:city":"Kennedale",
    "sg:phone":"+1 817 516 0525",
    "sg:postcode":"76060",
    "sg:province":"TX",
    "sg:tags":[
        "wholesale",
        "commercial",
        "equipment"
    ],
    "wof:name":"Wrs Design",
    "wof:placetype":"venue"
},
  "geometry": {"coordinates":[-97.20636399999999,32.649875],"type":"Point"}
}