{
  "type": "Feature",
  "properties": {
    "iso:country":"US",
    "sg:address":"431 Savannah Springs Way",
    "sg:city":"Spring",
    "sg:classifiers":[
        {
            "category":"Professional",
            "subcategory":"Business Services",
            "type":"Services"
        }
    ],
    "sg:phone":"+1 281 528 8502",
    "sg:postcode":"77373",
    "sg:province":"TX",
    "wof:name":"Valaria Group",
    "wof:placetype":"venue"
},
  "geometry": {"coordinates":[-95.427823,30.068623],"type":"Point"}
}