{
  "type": "Feature",
  "properties": {
    "iso:country":"US",
    "sg:address":"3221 Fannin St",
    "sg:city":"Houston",
    "sg:classifiers":[
        {
            "category":"Health Services",
            "subcategory":"Doctor",
            "type":"Services"
        }
    ],
    "sg:phone":"+1 713 522 0212",
    "sg:postcode":"77004",
    "sg:province":"TX",
    "sg:tags":[
        "ophthalmologist",
        "medical"
    ],
    "wof:name":"Advanced Eyecare & Laser Center",
    "wof:placetype":"venue"
},
  "geometry": {"coordinates":[-95.37640399999999,29.740601],"type":"Point"}
}