{
  "type": "Feature",
  "properties": {
    "iso:country":"US",
    "sg:address":"2103 Lakeview Dr",
    "sg:city":"Amarillo",
    "sg:classifiers":[
        {
            "category":"Travel",
            "subcategory":"Hotels & Motels",
            "type":"Entertainment"
        }
    ],
    "sg:phone":"+1 806 352 8300",
    "sg:postcode":"79109",
    "sg:province":"TX",
    "sg:tags":[
        "operation"
    ],
    "wof:name":"Comfort Inn",
    "wof:placetype":"venue"
},
  "geometry": {"coordinates":[-101.874893,35.18915],"type":"Point"}
}