{
  "type": "Feature",
  "properties": {
    "iso:country":"US",
    "sg:address":"11166 Sam Snead Dr",
    "sg:city":"El Paso",
    "sg:classifiers":[
        {
            "category":"Autos & Motor Vehicles",
            "subcategory":"Automobile Sales",
            "type":"Retail Goods"
        }
    ],
    "sg:phone":"+1 915 781 0311",
    "sg:postcode":"79936",
    "sg:province":"TX",
    "sg:tags":[
        "car",
        "dealer"
    ],
    "wof:name":"York's Auto Sales & Cnsgnmnt",
    "wof:placetype":"venue"
},
  "geometry": {"coordinates":[-106.311313,31.776978],"type":"Point"}
}