{
  "type": "Feature",
  "properties": {
    "iso:country":"US",
    "sg:address":"8203 Jensen Dr",
    "sg:city":"Houston",
    "sg:classifiers":[
        {
            "category":"Organizations",
            "subcategory":"Religious Organization",
            "type":"Services"
        }
    ],
    "sg:phone":"+1 713 694 7341",
    "sg:postcode":"77093",
    "sg:province":"TX",
    "sg:tags":[
        "testament",
        "churches-church",
        "christ-new"
    ],
    "wof:name":"Church Of Christ",
    "wof:placetype":"venue"
},
  "geometry": {"coordinates":[-95.34271200000001,29.833971],"type":"Point"}
}