{
  "type": "Feature",
  "properties": {
    "iso:country":"US",
    "sg:address":"5309 Antoine Dr",
    "sg:city":"Houston",
    "sg:classifiers":[
        {
            "category":"Shopping",
            "subcategory":"Florist",
            "type":"Retail Goods"
        }
    ],
    "sg:phone":"+1 713 681 4611",
    "sg:postcode":"77091",
    "sg:province":"TX",
    "wof:name":"Benson's Flowers",
    "wof:placetype":"venue"
},
  "geometry": {"coordinates":[-95.47339599999999,29.841801],"type":"Point"}
}