{
  "type": "Feature",
  "properties": {
    "iso:country":"US",
    "sg:address":"122 Cottage Rd",
    "sg:city":"Carthage",
    "sg:classifiers":[
        {
            "category":"Shopping",
            "subcategory":"Discount & Variety Stores",
            "type":"Retail Goods"
        }
    ],
    "sg:phone":"+1 903 693 2944",
    "sg:postcode":"75633",
    "sg:province":"TX",
    "wof:name":"Dollar General",
    "wof:placetype":"venue"
},
  "geometry": {"coordinates":[-94.34130999999999,32.166086],"type":"Point"}
}