{
  "type": "Feature",
  "properties": {
    "iso:country":"US",
    "sg:address":"3125 Gamble Rd",
    "sg:city":"San Benito",
    "sg:classifiers":[
        {
            "category":"Food & Beverages",
            "subcategory":"Specialty",
            "type":"Retail Goods"
        }
    ],
    "sg:phone":"+1 956 399 0924",
    "sg:postcode":"78586",
    "sg:province":"TX",
    "sg:tags":[
        "gourmet",
        "shop"
    ],
    "sg:website":"www.serendipityofthevalley.com",
    "wof:name":"Serendipity Of The Valley",
    "wof:placetype":"venue"
},
  "geometry": {"coordinates":[-97.645678,26.100529],"type":"Point"}
}