{
  "type": "Feature",
  "properties": {
    "iso:country":"US",
    "sg:address":"513 Lamar St",
    "sg:city":"Sweetwater",
    "sg:classifiers":[
        {
            "category":"Place Of Worship",
            "subcategory":"Church",
            "type":"Public Place"
        },
        {
            "category":"Place Of Worship",
            "type":"Public Place"
        }
    ],
    "sg:phone":"+1 325 235 1779",
    "sg:postcode":"79556",
    "sg:province":"TX",
    "sg:tags":[
        "churches-baptist-general",
        "churches-baptist-southern",
        "churches-baptist"
    ],
    "wof:name":"Lamar Street Baptist Church",
    "wof:placetype":"venue"
},
  "geometry": {"coordinates":[-100.398788,32.451164],"type":"Point"}
}