{
  "type": "Feature",
  "properties": {
    "iso:country":"US",
    "sg:address":"547 Pleasant Oaks Dr",
    "sg:city":"Dallas",
    "sg:classifiers":[
        {
            "category":"Wholesale",
            "subcategory":"Vending Machines",
            "type":"Manufacturing & Wholesale Goods"
        }
    ],
    "sg:phone":"+1 972 557 5058",
    "sg:postcode":"75217",
    "sg:province":"TX",
    "sg:tags":[
        "merchandise"
    ],
    "wof:name":"Right Time Snacks",
    "wof:placetype":"venue"
},
  "geometry": {"coordinates":[-96.641535,32.720617],"type":"Point"}
}