{
  "type": "Feature",
  "properties": {
    "iso:country":"US",
    "sg:address":"1101 Southmore Ave",
    "sg:city":"Pasadena",
    "sg:classifiers":[
        {
            "category":"Sports & Exercise",
            "subcategory":"Gym",
            "type":"Entertainment"
        }
    ],
    "sg:phone":"+1 713 473 4600",
    "sg:postcode":"77502",
    "sg:province":"TX",
    "sg:tags":[
        "club",
        "health",
        "studio",
        "gymnasium"
    ],
    "wof:name":"Fitness Connection",
    "wof:placetype":"venue"
},
  "geometry": {"coordinates":[-95.20039800000001,29.690859],"type":"Point"}
}