{
  "type": "Feature",
  "properties": {
    "iso:country":"US",
    "sg:address":"1910 W Little York Rd",
    "sg:city":"Houston",
    "sg:classifiers":[
        {
            "category":"Education",
            "subcategory":"School",
            "type":"Public Place"
        }
    ],
    "sg:phone":"+1 713 878 0360",
    "sg:postcode":"77091",
    "sg:province":"TX",
    "wof:name":"Charles R Drew Middle Sch",
    "wof:placetype":"venue"
},
  "geometry": {"coordinates":[-95.44133100000001,29.863569],"type":"Point"}
}