{
  "type": "Feature",
  "properties": {
    "iso:country":"US",
    "sg:address":"4726 Broom St",
    "sg:city":"San Antonio",
    "sg:classifiers":[
        {
            "category":"Building & Trades",
            "subcategory":"Construction",
            "type":"Services"
        }
    ],
    "sg:phone":"+1 210 653 9107",
    "sg:postcode":"78217",
    "sg:province":"TX",
    "sg:tags":[
        "general",
        "contractor"
    ],
    "wof:name":"Architectural Habitat Inc",
    "wof:placetype":"venue"
},
  "geometry": {"coordinates":[-98.39695500000001,29.526756],"type":"Point"}
}