{
  "type": "Feature",
  "properties": {
    "iso:country":"US",
    "sg:address":"1306 S F St",
    "sg:city":"Harlingen",
    "sg:classifiers":[
        {
            "category":"Manufacturing",
            "subcategory":"Glass & Minerals",
            "type":"Manufacturing & Wholesale Goods"
        }
    ],
    "sg:phone":"+1 956 216 8070",
    "sg:postcode":"78550",
    "sg:province":"TX",
    "sg:tags":[
        "plate",
        "window",
        "glass-auto"
    ],
    "wof:name":"Marquez Glass",
    "wof:placetype":"venue"
},
  "geometry": {"coordinates":[-97.702133,26.180656],"type":"Point"}
}