{
  "type": "Feature",
  "properties": {
    "iso:country":"US",
    "sg:address":"1009 S Jackson St",
    "sg:city":"Jacksonville",
    "sg:classifiers":[
        {
            "category":"Farming",
            "subcategory":"Livestock Farm",
            "type":"Manufacturing & Wholesale Goods"
        }
    ],
    "sg:phone":"+1 903 589 8397",
    "sg:postcode":"75766",
    "sg:province":"TX",
    "sg:tags":[
        "ranch"
    ],
    "wof:name":"Piccolo Stivale Ranch LLC",
    "wof:placetype":"venue"
},
  "geometry": {"coordinates":[-95.266839,31.956421],"type":"Point"}
}