{
  "type": "Feature",
  "properties": {
    "iso:country":"US",
    "sg:address":"2100 N Stevens St",
    "sg:city":"El Paso",
    "sg:classifiers":[
        {
            "category":"Social Services",
            "type":"Services"
        }
    ],
    "sg:phone":"+1 915 562 7955",
    "sg:postcode":"79930",
    "sg:province":"TX",
    "sg:tags":[
        "intervention",
        "crisis",
        "center",
        "for",
        "child"
    ],
    "sg:website":"www.childcrisiselp.org",
    "wof:name":"Child Crisis Center of El Paso",
    "wof:placetype":"venue"
},
  "geometry": {"coordinates":[-106.449388,31.796392],"type":"Point"}
}