{
  "type": "Feature",
  "properties": {
    "iso:country":"US",
    "sg:address":"201 N 8th St",
    "sg:city":"Killeen",
    "sg:classifiers":[
        {
            "category":"Personal",
            "subcategory":"Beauty Salon",
            "type":"Services"
        }
    ],
    "sg:phone":"+1 254 526 8585",
    "sg:postcode":"76541",
    "sg:province":"TX",
    "sg:tags":[
        "shop"
    ],
    "wof:name":"Yong's Beauty Salon",
    "wof:placetype":"venue"
},
  "geometry": {"coordinates":[-97.72670599999999,31.119805],"type":"Point"}
}