{
  "type": "Feature",
  "properties": {
    "iso:country":"US",
    "sg:address":"510 N Sycamore St",
    "sg:city":"Palestine",
    "sg:classifiers":[
        {
            "category":"Real Estate",
            "subcategory":"Real Estate Agent",
            "type":"Services"
        }
    ],
    "sg:phone":"+1 903 729 1055",
    "sg:postcode":"75801",
    "sg:province":"TX",
    "wof:name":"Advantage Real Estate",
    "wof:placetype":"venue"
},
  "geometry": {"coordinates":[-95.631674,31.764311],"type":"Point"}
}