{
  "type": "Feature",
  "properties": {
    "iso:country":"US",
    "sg:address":"2890 Fannett Rd",
    "sg:city":"Beaumont",
    "sg:classifiers":[
        {
            "category":"Restaurant",
            "type":"Food & Drink"
        }
    ],
    "sg:phone":"+1 409 840 4844",
    "sg:postcode":"77705",
    "sg:province":"TX",
    "wof:name":"Soul Food Etc",
    "wof:placetype":"venue"
},
  "geometry": {"coordinates":[-94.11514699999999,30.055207],"type":"Point"}
}