{
  "type": "Feature",
  "properties": {
    "iso:country":"US",
    "sg:address":"709 Colony Ln",
    "sg:city":"Houston",
    "sg:classifiers":[
        {
            "category":"Shopping",
            "subcategory":"Music",
            "type":"Retail Goods"
        }
    ],
    "sg:phone":"+1 713 742 6248",
    "sg:postcode":"77076",
    "sg:province":"TX",
    "wof:name":"Rawside Records",
    "wof:placetype":"venue"
},
  "geometry": {"coordinates":[-95.38954099999999,29.853056],"type":"Point"}
}