{
  "type": "Feature",
  "properties": {
    "iso:country":"US",
    "sg:address":"1900 S College Ave",
    "sg:city":"Bryan",
    "sg:classifiers":[
        {
            "category":"Retail",
            "subcategory":"Auto Repair",
            "type":"Services"
        }
    ],
    "sg:phone":"+1 979 775 6708",
    "sg:postcode":"77801",
    "sg:province":"TX",
    "sg:tags":[
        "repairing",
        "automobile"
    ],
    "wof:name":"Pickups Plus",
    "wof:placetype":"venue"
},
  "geometry": {"coordinates":[-96.367195,30.651574],"type":"Point"}
}