{
  "type": "Feature",
  "properties": {
    "iso:country":"US",
    "sg:address":"7021 Quail Run",
    "sg:city":"Fort Worth",
    "sg:classifiers":[
        {
            "category":"Shopping",
            "subcategory":"Crafts & Fabrics",
            "type":"Retail Goods"
        }
    ],
    "sg:phone":"+1 817 485 5373",
    "sg:postcode":"76148",
    "sg:province":"TX",
    "sg:tags":[
        "sewing"
    ],
    "wof:name":"Cws World",
    "wof:placetype":"venue"
},
  "geometry": {"coordinates":[-97.253185,32.872181],"type":"Point"}
}