{
  "type": "Feature",
  "properties": {
    "iso:country":"US",
    "sg:address":"2044 Deerbrook Dr",
    "sg:city":"Tyler",
    "sg:classifiers":[
        {
            "category":"Professional",
            "subcategory":"Employment Agencies",
            "type":"Services"
        }
    ],
    "sg:phone":"+1 903 561 6241",
    "sg:postcode":"75703",
    "sg:province":"TX",
    "sg:tags":[
        "help",
        "contractor"
    ],
    "sg:website":"www.design-quest.com",
    "wof:name":"Design Quest Inc",
    "wof:placetype":"venue"
},
  "geometry": {"coordinates":[-95.277219,32.277365],"type":"Point"}
}