{
  "type": "Feature",
  "properties": {
    "iso:country":"US",
    "sg:address":"828 Steger Towne Rd",
    "sg:city":"Rockwall",
    "sg:classifiers":[
        {
            "category":"Professional",
            "subcategory":"Business Services",
            "type":"Services"
        }
    ],
    "sg:phone":"+1 972 772 7703",
    "sg:postcode":"75032",
    "sg:province":"TX",
    "wof:name":"Caribbean Copy",
    "wof:placetype":"venue"
},
  "geometry": {"coordinates":[-96.465487,32.892253],"type":"Point"}
}