{
  "type": "Feature",
  "properties": {
    "iso:country":"US",
    "sg:address":"8709 Bluegrass Dr",
    "sg:city":"Austin",
    "sg:classifiers":[
        {
            "category":"Professional",
            "subcategory":"Advertising",
            "type":"Services"
        }
    ],
    "sg:phone":"+1 512 346 8498",
    "sg:postcode":"78759",
    "sg:province":"TX",
    "sg:tags":[
        "distribution"
    ],
    "wof:name":"A J Assoc Intl Dist",
    "wof:placetype":"venue"
},
  "geometry": {"coordinates":[-97.768226,30.38786],"type":"Point"}
}