{
  "type": "Feature",
  "properties": {
    "iso:country":"US",
    "sg:address":"826 Westwood Dr",
    "sg:city":"Port Lavaca",
    "sg:classifiers":[
        {
            "category":"Shopping",
            "subcategory":"Bicycles & Sporting Goods",
            "type":"Retail Goods"
        }
    ],
    "sg:phone":"+1 361 552 0060",
    "sg:postcode":"77979",
    "sg:province":"TX",
    "wof:name":"Bay Gun Club Inc",
    "wof:placetype":"venue"
},
  "geometry": {"coordinates":[-96.638049,28.637842],"type":"Point"}
}