{
  "type": "Feature",
  "properties": {
    "iso:country":"US",
    "sg:address":"11302 Timber Tech Ave",
    "sg:city":"Tomball",
    "sg:classifiers":[
        {
            "category":"Manufacturing",
            "subcategory":"Signs",
            "type":"Manufacturing & Wholesale Goods"
        }
    ],
    "sg:phone":"+1 281 351 6598",
    "sg:postcode":"77375",
    "sg:province":"TX",
    "wof:name":"Leprechaun Graphics",
    "wof:placetype":"venue"
},
  "geometry": {"coordinates":[-95.60151399999999,30.033062],"type":"Point"}
}