{
  "type": "Feature",
  "properties": {
    "iso:country":"US",
    "sg:address":"1600 S 23rd St",
    "sg:city":"Mcallen",
    "sg:classifiers":[
        {
            "category":"Restaurant",
            "type":"Food & Drink"
        }
    ],
    "sg:menulink":"http://www.allmenus.com/tx/mcallen-pharr/130462-subway/menu/",
    "sg:phone":"+1 956 664 9086",
    "sg:postcode":"78503",
    "sg:province":"TX",
    "sg:tags":[
        "american",
        "sandwich"
    ],
    "wof:name":"Subway",
    "wof:placetype":"venue"
},
  "geometry": {"coordinates":[-98.24728500000001,26.193118],"type":"Point"}
}