{
  "type": "Feature",
  "properties": {
    "iso:country":"US",
    "sg:address":"2209 3rd St",
    "sg:city":"Port Neches",
    "sg:classifiers":[
        {
            "category":"Professional",
            "subcategory":"Business Services",
            "type":"Services"
        }
    ],
    "sg:phone":"+1 409 722 7797",
    "sg:postcode":"77651",
    "sg:province":"TX",
    "wof:name":"Queue Enterprises Inc",
    "wof:placetype":"venue"
},
  "geometry": {"coordinates":[-93.975477,29.98497],"type":"Point"}
}