{
  "type": "Feature",
  "properties": {
    "iso:country":"US",
    "sg:address":"4400 US Hwy 281",
    "sg:city":"Spring Branch",
    "sg:classifiers":[
        {
            "category":"Organizations",
            "subcategory":"Religious Organization",
            "type":"Services"
        }
    ],
    "sg:phone":"+1 830 980 4673",
    "sg:postcode":"78070",
    "sg:province":"TX",
    "wof:name":"Riverside Community Church",
    "wof:placetype":"venue"
},
  "geometry": {"coordinates":[-98.41741,29.803316],"type":"Point"}
}