{
  "type": "Feature",
  "properties": {
    "iso:country":"US",
    "sg:address":"1201 Western Cir",
    "sg:city":"Dimmitt",
    "sg:classifiers":[
        {
            "category":"Organizations",
            "subcategory":"Religious Organization",
            "type":"Services"
        }
    ],
    "sg:phone":"+1 806 647 3115",
    "sg:postcode":"79027",
    "sg:province":"TX",
    "wof:name":"Faith Baptist Church Dimmitt",
    "wof:placetype":"venue"
},
  "geometry": {"coordinates":[-102.330718,34.544419],"type":"Point"}
}