{
  "type": "Feature",
  "properties": {
    "iso:country":"US",
    "sg:address":"4505 Holmes Rd",
    "sg:city":"Richmond",
    "sg:classifiers":[
        {
            "category":"Professional",
            "subcategory":"Accounting & Tax Preparation",
            "type":"Services"
        }
    ],
    "sg:phone":"+1 281 342 4932",
    "sg:postcode":"77469",
    "sg:province":"TX",
    "sg:tags":[
        "consultant"
    ],
    "wof:name":"Hail EA Co",
    "wof:placetype":"venue"
},
  "geometry": {"coordinates":[-95.78630200000001,29.658481],"type":"Point"}
}