{
  "type": "Feature",
  "properties": {
    "iso:country":"US",
    "sg:address":"1130 Banks St",
    "sg:city":"Houston",
    "sg:classifiers":[
        {
            "category":"Restaurant",
            "type":"Food & Drink"
        }
    ],
    "sg:phone":"+1 713 874 0368",
    "sg:postcode":"77006",
    "sg:province":"TX",
    "sg:tags":[
        "eating"
    ],
    "wof:name":"Busy Lizzy Kitchen Design Co",
    "wof:placetype":"venue"
},
  "geometry": {"coordinates":[-95.393669,29.7302],"type":"Point"}
}