{
  "type": "Feature",
  "properties": {
    "iso:country":"US",
    "sg:address":"2904 Fulton St",
    "sg:city":"Houston",
    "sg:classifiers":[
        {
            "category":"Banks & Credit Unions",
            "subcategory":"Bank",
            "type":"Services"
        }
    ],
    "sg:phone":"+1 713 223 7700",
    "sg:postcode":"77009",
    "sg:province":"TX",
    "wof:name":"Horizon Capital Bank",
    "wof:placetype":"venue"
},
  "geometry": {"coordinates":[-95.360355,29.789727],"type":"Point"}
}