{
  "type": "Feature",
  "properties": {
    "iso:country":"US",
    "sg:address":"320 S Seymour Ave",
    "sg:city":"Laredo",
    "sg:classifiers":[
        {
            "category":"Retail",
            "subcategory":"Auto Repair",
            "type":"Services"
        }
    ],
    "sg:phone":"+1 956 723 6632",
    "sg:postcode":"78040",
    "sg:province":"TX",
    "sg:tags":[
        "general"
    ],
    "wof:name":"E & J Garage",
    "wof:placetype":"venue"
},
  "geometry": {"coordinates":[-99.48147,27.493926],"type":"Point"}
}