{
  "type": "Feature",
  "properties": {
    "iso:country":"US",
    "sg:address":"4006 Grovetree",
    "sg:city":"San Antonio",
    "sg:classifiers":[
        {
            "category":"Autos & Motor Vehicles",
            "subcategory":"Fuel & Gas Station",
            "type":"Retail Goods"
        }
    ],
    "sg:phone":"+1 210 403 2028",
    "sg:postcode":"78247",
    "sg:province":"TX",
    "sg:tags":[
        "station",
        "gasoline"
    ],
    "wof:name":"Shreehari Krupa Corp",
    "wof:placetype":"venue"
},
  "geometry": {"coordinates":[-98.43092799999999,29.561726],"type":"Point"}
}