{
  "type": "Feature",
  "properties": {
    "iso:country":"US",
    "sg:address":"311 W 5th St",
    "sg:city":"Breckenridge",
    "sg:classifiers":[
        {
            "category":"Building & Trades",
            "subcategory":"Plumbing",
            "type":"Services"
        }
    ],
    "sg:phone":"+1 254 559 5243",
    "sg:postcode":"76424",
    "sg:province":"TX",
    "sg:tags":[
        "plumbing",
        "contractor"
    ],
    "wof:name":"John's Plumbing",
    "wof:placetype":"venue"
},
  "geometry": {"coordinates":[-98.908107,32.763964],"type":"Point"}
}