{
  "type": "Feature",
  "properties": {
    "iso:country":"US",
    "sg:address":"1209 Iturbide St",
    "sg:city":"Laredo",
    "sg:classifiers":[
        {
            "category":"Wholesale",
            "subcategory":"Drugs",
            "type":"Manufacturing & Wholesale Goods"
        }
    ],
    "sg:phone":"+1 956 723 1101",
    "sg:postcode":"78040",
    "sg:province":"TX",
    "sg:tags":[
        "perfume"
    ],
    "wof:name":"Royal Perfumes Intl",
    "wof:placetype":"venue"
},
  "geometry": {"coordinates":[-99.50842900000001,27.503503],"type":"Point"}
}