{
  "type": "Feature",
  "properties": {
    "iso:country":"US",
    "sg:address":"1714 Quadrangle Dr",
    "sg:city":"Dallas",
    "sg:classifiers":[
        {
            "category":"Building & Trades",
            "subcategory":"Landscaping Services",
            "type":"Services"
        }
    ],
    "sg:phone":"+1 214 321 4905",
    "sg:postcode":"75228",
    "sg:province":"TX",
    "sg:tags":[
        "landscape"
    ],
    "wof:name":"Scott McElwain",
    "wof:placetype":"venue"
},
  "geometry": {"coordinates":[-96.69152800000001,32.827609],"type":"Point"}
}