{
  "type": "Feature",
  "properties": {
    "iso:country":"US",
    "sg:address":"2008 N Interstate 35E",
    "sg:city":"Carrollton",
    "sg:classifiers":[
        {
            "category":"Restaurant",
            "type":"Food & Drink"
        }
    ],
    "sg:phone":"+1 972 242 4300",
    "sg:postcode":"75006",
    "sg:province":"TX",
    "sg:tags":[
        "mexican"
    ],
    "wof:name":"El Paisa Cocina Mexicana",
    "wof:placetype":"venue"
},
  "geometry": {"coordinates":[-96.919034,32.969217],"type":"Point"}
}