{
  "type": "Feature",
  "properties": {
    "iso:country":"US",
    "sg:address":"6207 Danbury Ln",
    "sg:city":"Dallas",
    "sg:classifiers":[
        {
            "category":"Professional",
            "subcategory":"Management & Consulting",
            "type":"Services"
        }
    ],
    "sg:phone":"+1 214 692 5722",
    "sg:postcode":"75214",
    "sg:province":"TX",
    "sg:tags":[
        "consultant",
        "business"
    ],
    "wof:name":"AFL Consultants",
    "wof:placetype":"venue"
},
  "geometry": {"coordinates":[-96.75305400000001,32.847971],"type":"Point"}
}