{
  "type": "Feature",
  "properties": {
    "iso:country":"US",
    "sg:address":"5201 Harry Hines Blvd",
    "sg:city":"Dallas",
    "sg:classifiers":[
        {
            "category":"Health Services",
            "subcategory":"Hospital",
            "type":"Services"
        }
    ],
    "sg:phone":"+1 214 590 8000",
    "sg:postcode":"75235",
    "sg:province":"TX",
    "sg:tags":[
        "executive",
        "general"
    ],
    "sg:website":"www.parklandfoundation.org",
    "wof:name":"Parkland Health & Hospital Sys",
    "wof:placetype":"venue"
},
  "geometry": {"coordinates":[-96.83995899999999,32.813983],"type":"Point"}
}