{
  "type": "Feature",
  "properties": {
    "iso:country":"US",
    "sg:address":"611 E Main St",
    "sg:city":"Gatesville",
    "sg:classifiers":[
        {
            "category":"Professional",
            "type":"Services"
        }
    ],
    "sg:phone":"+1 254 865 7774",
    "sg:postcode":"76528",
    "sg:province":"TX",
    "sg:tags":[
        "establishment"
    ],
    "wof:name":"Main Street Market",
    "wof:placetype":"venue"
},
  "geometry": {"coordinates":[-97.75050299999999,31.435002],"type":"Point"}
}