{
  "type": "Feature",
  "properties": {
    "iso:country":"US",
    "sg:address":"2001 Bonnie Brae Ave",
    "sg:city":"Fort Worth",
    "sg:classifiers":[
        {
            "category":"Organizations",
            "subcategory":"Religious Organization",
            "type":"Services"
        }
    ],
    "sg:phone":"+1 817 831 1661",
    "sg:postcode":"76111",
    "sg:province":"TX",
    "sg:tags":[
        "church"
    ],
    "wof:name":"Oakhurst Presbyterian Church",
    "wof:placetype":"venue"
},
  "geometry": {"coordinates":[-97.29950599999999,32.78973],"type":"Point"}
}