{
  "type": "Feature",
  "properties": {
    "iso:country":"US",
    "sg:address":"5918 Lomo Alto Dr",
    "sg:city":"Dallas",
    "sg:classifiers":[
        {
            "category":"Professional",
            "subcategory":"Business Services",
            "type":"Services"
        }
    ],
    "sg:phone":"+1 214 521 2342",
    "sg:postcode":"75205",
    "sg:province":"TX",
    "wof:name":"Wjw Enterprises Inc",
    "wof:placetype":"venue"
},
  "geometry": {"coordinates":[-96.812921,32.839556],"type":"Point"}
}