{
  "type": "Feature",
  "properties": {
    "iso:country":"US",
    "sg:address":"1317 Garrett St",
    "sg:city":"Brenham",
    "sg:classifiers":[
        {
            "category":"Professional",
            "subcategory":"Art Services",
            "type":"Services"
        }
    ],
    "sg:phone":"+1 979 277 0650",
    "sg:postcode":"77833",
    "sg:province":"TX",
    "sg:tags":[
        "photography",
        "commercial"
    ],
    "wof:name":"Positive Image",
    "wof:placetype":"venue"
},
  "geometry": {"coordinates":[-96.385398,30.168621],"type":"Point"}
}