{
  "type": "Feature",
  "properties": {
    "iso:country":"US",
    "sg:address":"2200 Dennison St",
    "sg:city":"Dallas",
    "sg:classifiers":[
        {
            "category":"Education",
            "subcategory":"School",
            "type":"Public Place"
        }
    ],
    "sg:phone":"+1 972 502 2700",
    "sg:postcode":"75212",
    "sg:province":"TX",
    "wof:name":"Dallas Independent School District",
    "wof:placetype":"venue"
},
  "geometry": {"coordinates":[-96.858124,32.781982],"type":"Point"}
}