{
  "type": "Feature",
  "properties": {
    "iso:country":"US",
    "sg:address":"4418 S Washington St",
    "sg:city":"Amarillo",
    "sg:classifiers":[
        {
            "category":"Professional",
            "type":"Services"
        }
    ],
    "sg:phone":"+1 806 376 4741",
    "sg:postcode":"79110",
    "sg:province":"TX",
    "wof:name":"Clynn Carris Inc",
    "wof:placetype":"venue"
},
  "geometry": {"coordinates":[-101.84849699999999,35.164402],"type":"Point"}
}