{
  "type": "Feature",
  "properties": {
    "iso:country":"US",
    "sg:address":"7602 Susan Elaine St",
    "sg:city":"San Antonio",
    "sg:classifiers":[
        {
            "category":"Building & Trades",
            "subcategory":"Construction",
            "type":"Services"
        }
    ],
    "sg:phone":"+1 210 521 4197",
    "sg:postcode":"78240",
    "sg:province":"TX",
    "sg:tags":[
        "coping",
        "plastering",
        "tiling",
        "pool",
        "swimming"
    ],
    "wof:name":"Interpool Inc",
    "wof:placetype":"venue"
},
  "geometry": {"coordinates":[-98.637231,29.528675],"type":"Point"}
}