{
  "type": "Feature",
  "properties": {
    "iso:country":"US",
    "sg:address":"15206 Main St",
    "sg:city":"Lytle",
    "sg:classifiers":[
        {
            "category":"Autos & Motor Vehicles",
            "subcategory":"Fuel & Gas Station",
            "type":"Retail Goods"
        }
    ],
    "sg:phone":"+1 830 772 3551",
    "sg:postcode":"78052",
    "sg:province":"TX",
    "sg:tags":[
        "oil"
    ],
    "wof:name":"Chevron Food Mart",
    "wof:placetype":"venue"
},
  "geometry": {"coordinates":[-98.796988,29.232838],"type":"Point"}
}