{
  "type": "Feature",
  "properties": {
    "iso:country":"US",
    "sg:address":"4755 Eastex Fwy",
    "sg:city":"Beaumont",
    "sg:classifiers":[
        {
            "category":"Home & Garden",
            "subcategory":"Furniture",
            "type":"Retail Goods"
        }
    ],
    "sg:phone":"+1 409 898 2268",
    "sg:postcode":"77706",
    "sg:province":"TX",
    "wof:name":"Ethan Allen",
    "wof:placetype":"venue"
},
  "geometry": {"coordinates":[-94.14899800000001,30.120075],"type":"Point"}
}