{
  "type": "Feature",
  "properties": {
    "iso:country":"US",
    "sg:address":"907 N Ray St",
    "sg:city":"Alvarado",
    "sg:classifiers":[
        {
            "category":"Professional",
            "subcategory":"Business Services",
            "type":"Services"
        }
    ],
    "sg:phone":"+1 817 790 7795",
    "sg:postcode":"76009",
    "sg:province":"TX",
    "sg:tags":[
        "auctioneer"
    ],
    "wof:name":"Last Call Auction Co",
    "wof:placetype":"venue"
},
  "geometry": {"coordinates":[-97.213379,32.415029],"type":"Point"}
}