{
  "type": "Feature",
  "properties": {
    "iso:country":"US",
    "sg:address":"11920 Astoria Blvd",
    "sg:city":"Houston",
    "sg:classifiers":[
        {
            "category":"Health Services",
            "subcategory":"Doctor",
            "type":"Services"
        }
    ],
    "sg:phone":"+1 281 484 0900",
    "sg:postcode":"77089",
    "sg:province":"TX",
    "wof:name":"Tayyan Nawar MD",
    "wof:placetype":"venue"
},
  "geometry": {"coordinates":[-95.20715199999999,29.584939],"type":"Point"}
}