{
  "type": "Feature",
  "properties": {
    "iso:country":"US",
    "sg:address":"2510 Mills Branch Drive, Suite 160",
    "sg:city":"Kingwood",
    "sg:classifiers":[
        {
            "category":"Professional",
            "subcategory":"Computer Services",
            "type":"Services"
        }
    ],
    "sg:phone":"+1 281 360 4529",
    "sg:postcode":"77345",
    "sg:province":"TX",
    "sg:tags":[
        "gymnastics",
        "cheerleading",
        "dance",
        "tumbling",
        "karate",
        "parentchild-classes",
        "parents-survival-night"
    ],
    "sg:website":"http://www.tlgkingwoodtx.com",
    "wof:name":"The Little Gym of Kingwood",
    "wof:placetype":"venue"
},
  "geometry": {"coordinates":[-95.16892,30.070942],"type":"Point"}
}