{
  "type": "Feature",
  "properties": {
    "iso:country":"US",
    "sg:address":"9531 C F Hawn Fwy",
    "sg:city":"Dallas",
    "sg:classifiers":[
        {
            "category":"Retail",
            "subcategory":"Auto Repair",
            "type":"Services"
        }
    ],
    "sg:phone":"+1 214 391 8286",
    "sg:postcode":"75217",
    "sg:province":"TX",
    "sg:tags":[
        "automobile",
        "inspection"
    ],
    "wof:name":"St Augustine & Inspection",
    "wof:placetype":"venue"
},
  "geometry": {"coordinates":[-96.65884800000001,32.702255],"type":"Point"}
}