{
  "type": "Feature",
  "properties": {
    "iso:country":"US",
    "sg:address":"110 Royal St",
    "sg:city":"Bryan",
    "sg:classifiers":[
        {
            "category":"Social Services",
            "subcategory":"Child Care",
            "type":"Services"
        },
        {
            "category":"Education",
            "subcategory":"Preschool",
            "type":"Public Place"
        }
    ],
    "sg:phone":"+1 979 846 4503",
    "sg:postcode":"77801",
    "sg:province":"TX",
    "sg:tags":[
        "kindergarten",
        "nursery",
        "day"
    ],
    "sg:website":"http://www.kindercare.com/our-centers/center-details/300842/?cid=YP_KC300842",
    "wof:name":"Royal Street KinderCare",
    "wof:placetype":"venue"
},
  "geometry": {"coordinates":[-96.353061,30.633736],"type":"Point"}
}