{
  "type": "Feature",
  "properties": {
    "iso:country":"US",
    "sg:address":"309 Co Rd 461",
    "sg:city":"Eastland",
    "sg:classifiers":[
        {
            "category":"Professional",
            "type":"Services"
        },
        {
            "category":"Manufacturing",
            "subcategory":"Pet Food",
            "type":"Manufacturing & Wholesale Goods"
        }
    ],
    "sg:phone":"+1 254 629 8567",
    "sg:postcode":"76448",
    "sg:province":"TX",
    "sg:tags":[
        "feed",
        "mfg",
        "establishment",
        "prepared"
    ],
    "wof:name":"Champions Choice LLC",
    "wof:placetype":"venue"
},
  "geometry": {"coordinates":[-98.721453,32.390991],"type":"Point"}
}