{
  "type": "Feature",
  "properties": {
    "iso:country":"US",
    "sg:address":"7103 Valburn Dr",
    "sg:city":"Austin",
    "sg:classifiers":[
        {
            "category":"Communications",
            "subcategory":"Radio Station",
            "type":"Services"
        }
    ],
    "sg:phone":"+1 512 327 4034",
    "sg:postcode":"78731",
    "sg:province":"TX",
    "sg:tags":[
        "company",
        "broadcasting"
    ],
    "wof:name":"Thelese Co",
    "wof:placetype":"venue"
},
  "geometry": {"coordinates":[-97.781295,30.370034],"type":"Point"}
}