{
  "type": "Feature",
  "properties": {
    "iso:country":"US",
    "sg:address":"3318 Azle Ave",
    "sg:city":"Fort Worth",
    "sg:classifiers":[
        {
            "category":"Shopping",
            "subcategory":"Clothing, Apparel, & Fashions",
            "type":"Retail Goods"
        }
    ],
    "sg:phone":"+1 817 624 2575",
    "sg:postcode":"76106",
    "sg:province":"TX",
    "sg:tags":[
        "family"
    ],
    "wof:name":"Las 3 B B BS",
    "wof:placetype":"venue"
},
  "geometry": {"coordinates":[-97.388125,32.806208],"type":"Point"}
}