{
  "type": "Feature",
  "properties": {
    "iso:country":"US",
    "sg:address":"419 S Davis Dr",
    "sg:city":"Arlington",
    "sg:classifiers":[
        {
            "category":"Organizations",
            "subcategory":"Religious Organization",
            "type":"Services"
        }
    ],
    "sg:phone":"+1 817 261 8210",
    "sg:postcode":"76013",
    "sg:province":"TX",
    "wof:name":"CHI Alpha Cmpus Mnstry At Univ",
    "wof:placetype":"venue"
},
  "geometry": {"coordinates":[-97.123482,32.733601],"type":"Point"}
}