{
  "type": "Feature",
  "properties": {
    "iso:country":"US",
    "sg:address":"204 W Texas Ave",
    "sg:city":"Midland",
    "sg:classifiers":[
        {
            "category":"Mining & Drilling",
            "type":"Manufacturing & Wholesale Goods"
        }
    ],
    "sg:phone":"+1 432 684 9277",
    "sg:postcode":"79701",
    "sg:province":"TX",
    "sg:tags":[
        "oil",
        "gas",
        "producer"
    ],
    "wof:name":"Jbrock Oil",
    "wof:placetype":"venue"
},
  "geometry": {"coordinates":[-102.07681700000001,31.998585],"type":"Point"}
}