{
  "type": "Feature",
  "properties": {
    "iso:country":"US",
    "sg:address":"572 Harbor Cir",
    "sg:city":"Azle",
    "sg:classifiers":[
        {
            "category":"Professional",
            "subcategory":"Management & Consulting",
            "type":"Services"
        }
    ],
    "sg:phone":"+1 817 270 0099",
    "sg:postcode":"76020",
    "sg:province":"TX",
    "wof:name":"Arterburn & Assoc Inc",
    "wof:placetype":"venue"
},
  "geometry": {"coordinates":[-97.524308,32.903581],"type":"Point"}
}