{
  "type": "Feature",
  "properties": {
    "iso:country":"US",
    "sg:address":"2419 Corpus Christi St",
    "sg:city":"Laredo",
    "sg:classifiers":[
        {
            "category":"Shopping",
            "subcategory":"Florist",
            "type":"Retail Goods"
        }
    ],
    "sg:phone":"+1 956 791 5153",
    "sg:postcode":"78043",
    "sg:province":"TX",
    "wof:name":"EBM",
    "wof:placetype":"venue"
},
  "geometry": {"coordinates":[-99.471282,27.508313],"type":"Point"}
}