{
  "type": "Feature",
  "properties": {
    "iso:country":"US",
    "sg:address":"209 Odessa Dr",
    "sg:city":"Haslet",
    "sg:classifiers":[
        {
            "category":"Education",
            "subcategory":"Vocational School",
            "type":"Public Place"
        }
    ],
    "sg:phone":"+1 817 439 3807",
    "sg:postcode":"76052",
    "sg:province":"TX",
    "wof:name":"Manley Rob and Caron",
    "wof:placetype":"venue"
},
  "geometry": {"coordinates":[-97.34861600000001,32.960241],"type":"Point"}
}