{
  "type": "Feature",
  "properties": {
    "iso:country":"US",
    "sg:address":"1923 E 7th St",
    "sg:city":"Austin",
    "sg:classifiers":[
        {
            "category":"Health Services",
            "subcategory":"Dentist",
            "type":"Services"
        }
    ],
    "sg:phone":"+1 512 236 9300",
    "sg:postcode":"78702",
    "sg:province":"TX",
    "wof:name":"Access Dental",
    "wof:placetype":"venue"
},
  "geometry": {"coordinates":[-97.72161199999999,30.262311],"type":"Point"}
}