{
  "type": "Feature",
  "properties": {
    "iso:country":"US",
    "sg:address":"307 S Santa Rose Ave",
    "sg:city":"San Antonio",
    "sg:classifiers":[
        {
            "category":"Professional",
            "subcategory":"Lawyer & Legal Services",
            "type":"Services"
        }
    ],
    "sg:phone":"+1 210 224 6000",
    "sg:postcode":"78207",
    "sg:province":"TX",
    "sg:tags":[
        "attorney"
    ],
    "wof:name":"F Trey Fischer III",
    "wof:placetype":"venue"
},
  "geometry": {"coordinates":[-98.498622,29.421885],"type":"Point"}
}