{
  "type": "Feature",
  "properties": {
    "iso:country":"US",
    "sg:address":"939 Hawkins Blvd",
    "sg:city":"El Paso",
    "sg:classifiers":[
        {
            "category":"Wholesale",
            "subcategory":"Machinery & Supplies",
            "type":"Manufacturing & Wholesale Goods"
        }
    ],
    "sg:phone":"+1 915 772 0613",
    "sg:postcode":"79915",
    "sg:province":"TX",
    "sg:tags":[
        "construction",
        "equipment",
        "mining",
        "industrial"
    ],
    "wof:name":"Wwwinfosierraelpasocom",
    "wof:placetype":"venue"
},
  "geometry": {"coordinates":[-106.380833,31.763956],"type":"Point"}
}