{
  "type": "Feature",
  "properties": {
    "iso:country":"US",
    "sg:address":"3911 Kingsferry Dr",
    "sg:city":"Arlington",
    "sg:classifiers":[
        {
            "category":"Wholesale",
            "subcategory":"Computers",
            "type":"Manufacturing & Wholesale Goods"
        }
    ],
    "sg:phone":"+1 817 572 6565",
    "sg:postcode":"76016",
    "sg:province":"TX",
    "wof:name":"Software Systems Inc",
    "wof:placetype":"venue"
},
  "geometry": {"coordinates":[-97.212002,32.682141],"type":"Point"}
}