{
  "type": "Feature",
  "properties": {
    "iso:country":"US",
    "sg:address":"4119 McPherson Ave",
    "sg:city":"Laredo",
    "sg:classifiers":[
        {
            "category":"Retail",
            "subcategory":"Car Wash",
            "type":"Services"
        }
    ],
    "sg:phone":"+1 956 729 9358",
    "sg:postcode":"78041",
    "sg:province":"TX",
    "sg:tags":[
        "polishing",
        "washing"
    ],
    "wof:name":"G Beltrans Tire & Car Wash Svc",
    "wof:placetype":"venue"
},
  "geometry": {"coordinates":[-99.484353,27.534039],"type":"Point"}
}