{
  "type": "Feature",
  "properties": {
    "iso:country":"US",
    "sg:address":"2500 Wilcrest Dr Ste 107",
    "sg:city":"Houston",
    "sg:classifiers":[
        {
            "category":"Professional",
            "subcategory":"Lawyer & Legal Services",
            "type":"Services"
        }
    ],
    "sg:phone":"+1 713 680 9454",
    "sg:postcode":"77042",
    "sg:province":"TX",
    "sg:tags":[
        "divorce",
        "law",
        "family"
    ],
    "wof:name":"Hohenberger Robert",
    "wof:placetype":"venue"
},
  "geometry": {"coordinates":[-95.555397,29.74],"type":"Point"}
}