{
  "type": "Feature",
  "properties": {
    "iso:country":"US",
    "sg:address":"3508 N Navarro St",
    "sg:city":"Victoria",
    "sg:classifiers":[
        {
            "category":"Banks & Credit Unions",
            "subcategory":"Bank",
            "type":"Services"
        }
    ],
    "sg:phone":"+1 361 574 9037",
    "sg:postcode":"77901",
    "sg:province":"TX",
    "sg:tags":[
        "depository",
        "banking"
    ],
    "wof:name":"Mr Payroll of Victoria Check C",
    "wof:placetype":"venue"
},
  "geometry": {"coordinates":[-97.00094799999999,28.827867],"type":"Point"}
}