{
  "type": "Feature",
  "properties": {
    "iso:country":"US",
    "sg:address":"4822 N University Dr",
    "sg:city":"Nacogdoches",
    "sg:classifiers":[
        {
            "category":"Personal",
            "subcategory":"Beauty Salon",
            "type":"Services"
        }
    ],
    "sg:phone":"+1 936 564 4300",
    "sg:postcode":"75965",
    "sg:province":"TX",
    "sg:tags":[
        "shop"
    ],
    "wof:name":"Blades K S Haircare",
    "wof:placetype":"venue"
},
  "geometry": {"coordinates":[-94.63962600000001,31.641302],"type":"Point"}
}