{
  "type": "Feature",
  "properties": {
    "iso:country":"US",
    "sg:address":"31330 Bearing Star Ln",
    "sg:city":"Tomball",
    "sg:classifiers":[
        {
            "category":"Professional",
            "subcategory":"Business Services",
            "type":"Services"
        }
    ],
    "sg:phone":"+1 281 351 9959",
    "sg:postcode":"77375",
    "sg:province":"TX",
    "wof:name":"Leavell Enterprises",
    "wof:placetype":"venue"
},
  "geometry": {"coordinates":[-95.637687,30.116025],"type":"Point"}
}