{
  "type": "Feature",
  "properties": {
    "iso:country":"US",
    "sg:address":"215 Churchill Rd",
    "sg:city":"Fort Worth",
    "sg:classifiers":[
        {
            "category":"Education",
            "subcategory":"School",
            "type":"Public Place"
        }
    ],
    "sg:phone":"+1 817 252 2100",
    "sg:postcode":"76114",
    "sg:province":"TX",
    "sg:tags":[
        "high"
    ],
    "wof:name":"Castleberry High School",
    "wof:placetype":"venue"
},
  "geometry": {"coordinates":[-97.391313,32.762924],"type":"Point"}
}