{
  "type": "Feature",
  "properties": {
    "iso:country":"US",
    "sg:address":"1010 Mercury Dr",
    "sg:city":"Houston",
    "sg:classifiers":[
        {
            "category":"Building & Trades",
            "subcategory":"Construction",
            "type":"Services"
        }
    ],
    "sg:phone":"+1 713 675 4840",
    "sg:postcode":"77029",
    "sg:province":"TX",
    "sg:tags":[
        "steel",
        "erectors"
    ],
    "wof:name":"Eagle Erection Co",
    "wof:placetype":"venue"
},
  "geometry": {"coordinates":[-95.247631,29.77199],"type":"Point"}
}