{
  "type": "Feature",
  "properties": {
    "iso:country":"US",
    "sg:address":"6372 County Road 324",
    "sg:city":"Hawley",
    "sg:classifiers":[
        {
            "category":"Manufacturing",
            "subcategory":"Buildings",
            "type":"Manufacturing & Wholesale Goods"
        },
        {
            "category":"Building & Trades",
            "subcategory":"Construction",
            "type":"Services"
        }
    ],
    "sg:phone":"+1 325 537 9858",
    "sg:postcode":"79525",
    "sg:province":"TX",
    "sg:tags":[
        "home",
        "builder",
        "contractor"
    ],
    "wof:name":"Cando Construction",
    "wof:placetype":"venue"
},
  "geometry": {"coordinates":[-99.75809099999999,32.62629],"type":"Point"}
}