{
  "type": "Feature",
  "properties": {
    "iso:country":"US",
    "sg:address":"2520 NE Green Oaks Blvd",
    "sg:city":"Arlington",
    "sg:classifiers":[
        {
            "category":"Retail",
            "subcategory":"Laundry & Dry Cleaning",
            "type":"Services"
        }
    ],
    "sg:phone":"+1 817 652 2600",
    "sg:postcode":"76006",
    "sg:province":"TX",
    "sg:tags":[
        "drycleaning",
        "plant"
    ],
    "wof:name":"City Dry Clean Super Center",
    "wof:placetype":"venue"
},
  "geometry": {"coordinates":[-97.064407,32.784702],"type":"Point"}
}