{
  "type": "Feature",
  "properties": {
    "iso:country":"US",
    "sg:address":"555 Gellhorn Dr",
    "sg:city":"Houston",
    "sg:classifiers":[
        {
            "category":"Professional",
            "type":"Services"
        }
    ],
    "sg:phone":"+1 713 672 6577",
    "sg:postcode":"77029",
    "sg:province":"TX",
    "sg:tags":[
        "establishment"
    ],
    "wof:name":"Elder Parts & Equipment-Div",
    "wof:placetype":"venue"
},
  "geometry": {"coordinates":[-95.26732199999999,29.783691],"type":"Point"}
}