{
  "type": "Feature",
  "properties": {
    "iso:country":"US",
    "sg:address":"234 Palo Verde Dr",
    "sg:city":"Brownsville",
    "sg:classifiers":[
        {
            "category":"Real Estate",
            "subcategory":"Real Estate Agent",
            "type":"Services"
        }
    ],
    "sg:phone":"+1 956 504 5801",
    "sg:postcode":"78521",
    "sg:province":"TX",
    "sg:tags":[
        "inspection"
    ],
    "wof:name":"Tucker's Home Inspection Svc",
    "wof:placetype":"venue"
},
  "geometry": {"coordinates":[-97.482725,25.94358],"type":"Point"}
}