{
  "type": "Feature",
  "properties": {
    "iso:country":"US",
    "sg:address":"822 S Nebraska Ave",
    "sg:city":"Weslaco",
    "sg:classifiers":[
        {
            "category":"Building & Trades",
            "subcategory":"Construction",
            "type":"Services"
        }
    ],
    "sg:phone":"+1 956 969 4262",
    "sg:postcode":"78596",
    "sg:province":"TX",
    "sg:tags":[
        "general",
        "contractor"
    ],
    "wof:name":"A & M Construction",
    "wof:placetype":"venue"
},
  "geometry": {"coordinates":[-97.99260599999999,26.151372],"type":"Point"}
}