{
  "type": "Feature",
  "properties": {
    "iso:country":"US",
    "sg:address":"1100 Twin Oaks Dr",
    "sg:city":"Prosper",
    "sg:classifiers":[
        {
            "category":"Personal",
            "type":"Services"
        },
        {
            "category":"Professional",
            "subcategory":"Art Services",
            "type":"Services"
        }
    ],
    "sg:phone":"+1 972 347 1652",
    "sg:postcode":"75078",
    "sg:province":"TX",
    "sg:tags":[
        "photography",
        "videography",
        "wedding"
    ],
    "wof:name":"Bellon Photography",
    "wof:placetype":"venue"
},
  "geometry": {"coordinates":[-96.78302499999999,33.225463],"type":"Point"}
}