{
  "type": "Feature",
  "properties": {
    "iso:country":"US",
    "sg:address":"5717 Gerber Ter",
    "sg:city":"Plano",
    "sg:classifiers":[
        {
            "category":"Real Estate",
            "subcategory":"Real Estate Services",
            "type":"Services"
        },
        {
            "category":"Real Estate",
            "subcategory":"Real Estate Agent",
            "type":"Services"
        }
    ],
    "sg:phone":"+1 214 440 2397",
    "sg:postcode":"75094",
    "sg:province":"TX",
    "sg:tags":[
        "buyer",
        "broker"
    ],
    "wof:name":"Premise Realty",
    "wof:placetype":"venue"
},
  "geometry": {"coordinates":[-96.624292,33.009139],"type":"Point"}
}