{
  "type": "Feature",
  "properties": {
    "iso:country":"US",
    "sg:address":"5208 Firewood Dr",
    "sg:city":"Arlington",
    "sg:classifiers":[
        {
            "category":"Building & Trades",
            "subcategory":"Construction",
            "type":"Services"
        }
    ],
    "sg:phone":"+1 817 496 9163",
    "sg:postcode":"76016",
    "sg:province":"TX",
    "sg:tags":[
        "residential"
    ],
    "wof:name":"T & S Framing",
    "wof:placetype":"venue"
},
  "geometry": {"coordinates":[-97.188608,32.704773],"type":"Point"}
}