{
  "type": "Feature",
  "properties": {
    "iso:country":"US",
    "sg:address":"504 W Fairwinds St",
    "sg:city":"Hallettsville",
    "sg:classifiers":[
        {
            "category":"Restaurant",
            "type":"Food & Drink"
        }
    ],
    "sg:menulink":"http://www.allmenus.com/tx/hallettsville/68078-simple-simons-pizza/menu/",
    "sg:phone":"+1 361 798 1668",
    "sg:postcode":"77964",
    "sg:province":"TX",
    "sg:tags":[
        "american",
        "pizza"
    ],
    "wof:name":"Simple Simon's Pizza",
    "wof:placetype":"venue"
},
  "geometry": {"coordinates":[-96.96445199999999,29.435764],"type":"Point"}
}