{
  "type": "Feature",
  "properties": {
    "iso:country":"US",
    "sg:address":"208 Remington Dr",
    "sg:city":"Kilgore",
    "sg:classifiers":[
        {
            "category":"Retail",
            "subcategory":"Repair Shop",
            "type":"Services"
        }
    ],
    "sg:phone":"+1 903 983 2816",
    "sg:postcode":"75662",
    "sg:province":"TX",
    "sg:tags":[
        "welding"
    ],
    "wof:name":"Evans Welding Service",
    "wof:placetype":"venue"
},
  "geometry": {"coordinates":[-94.948049,32.415006],"type":"Point"}
}