{
  "type": "Feature",
  "properties": {
    "iso:country":"US",
    "sg:address":"1055 McNee Rd",
    "sg:city":"Houston",
    "sg:classifiers":[
        {
            "category":"Travel",
            "subcategory":"Hotels & Motels",
            "type":"Entertainment"
        }
    ],
    "sg:phone":"+1 713 668 1436",
    "sg:postcode":"77054",
    "sg:province":"TX",
    "wof:name":"Comfort Suites Inc",
    "wof:placetype":"venue"
},
  "geometry": {"coordinates":[-95.413803,29.692499],"type":"Point"}
}