{
  "type": "Feature",
  "properties": {
    "iso:country":"US",
    "sg:address":"4449 Bentley Dr",
    "sg:city":"Plano",
    "sg:classifiers":[
        {
            "category":"Professional",
            "type":"Services"
        }
    ],
    "sg:phone":"+1 972 612 7850",
    "sg:postcode":"75093",
    "sg:province":"TX",
    "wof:name":"Fast Home Buy LLC",
    "wof:placetype":"venue"
},
  "geometry": {"coordinates":[-96.77958700000001,33.045803],"type":"Point"}
}