{
  "type": "Feature",
  "properties": {
    "iso:country":"US",
    "sg:address":"4014 Elmwood Dr",
    "sg:city":"Pearland",
    "sg:classifiers":[
        {
            "category":"Real Estate",
            "subcategory":"Real Estate Agent",
            "type":"Services"
        }
    ],
    "sg:phone":"+1 281 692 9804",
    "sg:postcode":"77584",
    "sg:province":"TX",
    "wof:name":"Procyon Capital Corp",
    "wof:placetype":"venue"
},
  "geometry": {"coordinates":[-95.29327600000001,29.536196],"type":"Point"}
}