{
  "type": "Feature",
  "properties": {
    "iso:country":"US",
    "sg:address":"2213 S 45th St",
    "sg:city":"Temple",
    "sg:classifiers":[
        {
            "category":"Home & Garden",
            "subcategory":"Carpets & Floor Coverings",
            "type":"Retail Goods"
        }
    ],
    "sg:phone":"+1 254 771 3752",
    "sg:postcode":"76504",
    "sg:province":"TX",
    "sg:tags":[
        "material"
    ],
    "wof:name":"Lawler Carpet Service",
    "wof:placetype":"venue"
},
  "geometry": {"coordinates":[-97.37285799999999,31.081614],"type":"Point"}
}