{
  "type": "Feature",
  "properties": {
    "iso:country":"US",
    "sg:address":"621 Old London Ln",
    "sg:city":"Mesquite",
    "sg:classifiers":[
        {
            "category":"Organizations",
            "subcategory":"Religious Organization",
            "type":"Services"
        }
    ],
    "sg:phone":"+1 972 289 6227",
    "sg:postcode":"75149",
    "sg:province":"TX",
    "wof:name":"Christ Gospel Church",
    "wof:placetype":"venue"
},
  "geometry": {"coordinates":[-96.63878800000001,32.76106],"type":"Point"}
}