{
  "type": "Feature",
  "properties": {
    "iso:country":"US",
    "sg:address":"6025 Rocky Creek Rd",
    "sg:city":"La Grange",
    "sg:classifiers":[
        {
            "category":"Farming",
            "subcategory":"Livestock Farm",
            "type":"Manufacturing & Wholesale Goods"
        }
    ],
    "sg:phone":"+1 979 249 5155",
    "sg:postcode":"78945",
    "sg:province":"TX",
    "sg:tags":[
        "ranch"
    ],
    "wof:name":"Rocky Creek Ranch",
    "wof:placetype":"venue"
},
  "geometry": {"coordinates":[-96.805762,29.932734],"type":"Point"}
}