{
  "type": "Feature",
  "properties": {
    "iso:country":"US",
    "sg:address":"3100 Carlisle St",
    "sg:city":"Dallas",
    "sg:classifiers":[
        {
            "category":"Professional",
            "subcategory":"Management & Consulting",
            "type":"Services"
        }
    ],
    "sg:phone":"+1 214 303 1207",
    "sg:postcode":"75204",
    "sg:province":"TX",
    "sg:tags":[
        "information",
        "technology",
        "consultant"
    ],
    "wof:name":"D S L Group Inc",
    "wof:placetype":"venue"
},
  "geometry": {"coordinates":[-96.802532,32.803933],"type":"Point"}
}