{
  "type": "Feature",
  "properties": {
    "iso:country":"US",
    "sg:address":"5708 Mcpherson Rd Ste B",
    "sg:city":"Laredo",
    "sg:classifiers":[
        {
            "category":"Personal",
            "subcategory":"Beauty Salon",
            "type":"Services"
        }
    ],
    "sg:phone":"+1 956 712 8755",
    "sg:postcode":"78041",
    "sg:province":"TX",
    "sg:tags":[
        "hair",
        "stylist"
    ],
    "wof:name":"Hair Couture",
    "wof:placetype":"venue"
},
  "geometry": {"coordinates":[-99.48112999999999,27.552715],"type":"Point"}
}