{
  "type": "Feature",
  "properties": {
    "iso:country":"US",
    "sg:address":"112 E Market St",
    "sg:city":"Lockhart",
    "sg:classifiers":[
        {
            "category":"Professional",
            "subcategory":"Lawyer & Legal Services",
            "type":"Services"
        }
    ],
    "sg:phone":"+1 512 376 5318",
    "sg:postcode":"78644",
    "sg:province":"TX",
    "sg:tags":[
        "attorney"
    ],
    "wof:name":"Richard A Fielder Law Offices",
    "wof:placetype":"venue"
},
  "geometry": {"coordinates":[-97.671316,29.883925],"type":"Point"}
}