{
  "type": "Feature",
  "properties": {
    "iso:country":"US",
    "sg:address":"1818 N Padre Island Dr",
    "sg:city":"Corpus Christi",
    "sg:classifiers":[
        {
            "category":"Wholesale",
            "subcategory":"Metals & Minerals",
            "type":"Manufacturing & Wholesale Goods"
        }
    ],
    "sg:phone":"+1 361 289 8228",
    "sg:postcode":"78408",
    "sg:province":"TX",
    "sg:tags":[
        "pipe"
    ],
    "wof:name":"Epsco International Inc",
    "wof:placetype":"venue"
},
  "geometry": {"coordinates":[-97.467612,27.793559],"type":"Point"}
}