{
  "type": "Feature",
  "properties": {
    "iso:country":"US",
    "sg:address":"406 E Main St",
    "sg:city":"Clute",
    "sg:classifiers":[
        {
            "category":"Place Of Worship",
            "subcategory":"Church",
            "type":"Public Place"
        },
        {
            "category":"Place Of Worship",
            "type":"Public Place"
        }
    ],
    "sg:phone":"+1 979 265 2859",
    "sg:postcode":"77531",
    "sg:province":"TX",
    "sg:tags":[
        "churches-interdenominational",
        "churches-various",
        "denomination"
    ],
    "wof:name":"Iglesia La Fe",
    "wof:placetype":"venue"
},
  "geometry": {"coordinates":[-95.401409,29.023098],"type":"Point"}
}