{
  "type": "Feature",
  "properties": {
    "iso:country":"US",
    "sg:address":"19955 Katy Fwy",
    "sg:city":"Houston",
    "sg:classifiers":[
        {
            "category":"Shopping",
            "subcategory":"Department Store",
            "type":"Retail Goods"
        }
    ],
    "sg:phone":"+1 281 647 9191",
    "sg:postcode":"77094",
    "sg:province":"TX",
    "wof:name":"Target",
    "wof:placetype":"venue"
},
  "geometry": {"coordinates":[-95.716416,29.784185],"type":"Point"}
}