{
  "type": "Feature",
  "properties": {
    "iso:country":"US",
    "sg:address":"3305 Coit Rd",
    "sg:city":"Plano",
    "sg:classifiers":[
        {
            "category":"Retail",
            "subcategory":"Auto Repair",
            "type":"Services"
        }
    ],
    "sg:phone":"+1 972 867 3699",
    "sg:postcode":"75093",
    "sg:province":"TX",
    "sg:tags":[
        "automotive"
    ],
    "wof:name":"Texaco",
    "wof:placetype":"venue"
},
  "geometry": {"coordinates":[-96.77014,33.041538],"type":"Point"}
}