{
  "type": "Feature",
  "properties": {
    "iso:country":"US",
    "sg:address":"116 W 2nd St",
    "sg:city":"Shamrock",
    "sg:classifiers":[
        {
            "category":"Government",
            "subcategory":"Office",
            "type":"Public Place"
        }
    ],
    "sg:phone":"+1 806 256 3281",
    "sg:postcode":"79079",
    "sg:province":"TX",
    "sg:tags":[
        "city",
        "hall"
    ],
    "wof:name":"Business Office",
    "wof:placetype":"venue"
},
  "geometry": {"coordinates":[-100.25027900000001,35.2154],"type":"Point"}
}