{
  "type": "Feature",
  "properties": {
    "iso:country":"US",
    "sg:address":"6125 Sam Houston Pkwy",
    "sg:city":"Houston",
    "sg:classifiers":[
        {
            "category":"Banks & Credit Unions",
            "subcategory":"Bank",
            "type":"Services"
        }
    ],
    "sg:phone":"+1 713 896 9595",
    "sg:postcode":"77032",
    "sg:province":"TX",
    "sg:tags":[
        "loan",
        "real estate"
    ],
    "sg:website":"www.getmortgageloan.com",
    "wof:name":"Allied Home Mtg Capital Corp",
    "wof:placetype":"venue"
},
  "geometry": {"coordinates":[-95.29708100000001,29.940501],"type":"Point"}
}