{
  "type": "Feature",
  "properties": {
    "iso:country":"US",
    "sg:address":"6335 Skyline Dr",
    "sg:city":"Houston",
    "sg:classifiers":[
        {
            "category":"Retail",
            "subcategory":"Auto Repair",
            "type":"Services"
        }
    ],
    "sg:phone":"+1 713 266 5694",
    "sg:postcode":"77057",
    "sg:province":"TX",
    "sg:tags":[
        "automotive"
    ],
    "wof:name":"Bazarian Auto Service",
    "wof:placetype":"venue"
},
  "geometry": {"coordinates":[-95.49267999999999,29.728152],"type":"Point"}
}