{
  "type": "Feature",
  "properties": {
    "iso:country":"US",
    "sg:address":"2808 Cypress Point Dr",
    "sg:city":"Missouri City",
    "sg:classifiers":[
        {
            "category":"Restaurant",
            "type":"Food & Drink"
        }
    ],
    "sg:phone":"+1 281 261 5042",
    "sg:postcode":"77459",
    "sg:province":"TX",
    "sg:tags":[
        "security",
        "eating"
    ],
    "wof:name":"Chicken Foot Products",
    "wof:placetype":"venue"
},
  "geometry": {"coordinates":[-95.54349499999999,29.579727],"type":"Point"}
}