{
  "type": "Feature",
  "properties": {
    "iso:country":"US",
    "sg:address":"9206 Rod Rd",
    "sg:city":"Austin",
    "sg:classifiers":[
        {
            "category":"Shopping",
            "subcategory":"Pharmacy",
            "type":"Retail Goods"
        }
    ],
    "sg:phone":"+1 512 288 4118",
    "sg:postcode":"78736",
    "sg:province":"TX",
    "wof:name":"Southwest Alliance Pharma",
    "wof:placetype":"venue"
},
  "geometry": {"coordinates":[-97.932113,30.233261],"type":"Point"}
}