{
  "type": "Feature",
  "properties": {
    "iso:country":"US",
    "sg:address":"2511 Radcliffe Dr",
    "sg:city":"Sugar Land",
    "sg:classifiers":[
        {
            "category":"Professional",
            "type":"Services"
        }
    ],
    "sg:phone":"+1 281 277 2830",
    "sg:postcode":"77478",
    "sg:province":"TX",
    "wof:name":"Steve Newman Co Inc",
    "wof:placetype":"venue"
},
  "geometry": {"coordinates":[-95.665209,29.639799],"type":"Point"}
}