{
  "type": "Feature",
  "properties": {
    "iso:country":"US",
    "sg:address":"1017 S Cedar Hill Rd",
    "sg:city":"Cedar Hill",
    "sg:classifiers":[
        {
            "category":"Retail",
            "subcategory":"Auto Repair",
            "type":"Services"
        }
    ],
    "sg:phone":"+1 469 272 3222",
    "sg:postcode":"75104",
    "sg:province":"TX",
    "sg:tags":[
        "repairing",
        "automobile"
    ],
    "wof:name":"Classic Car Management",
    "wof:placetype":"venue"
},
  "geometry": {"coordinates":[-96.95953299999999,32.571879],"type":"Point"}
}