{
  "type": "Feature",
  "properties": {
    "iso:country":"US",
    "sg:address":"1212 Bay Area Blvd",
    "sg:city":"Austin",
    "sg:classifiers":[
        {
            "category":"Banks & Credit Unions",
            "subcategory":"Bank",
            "type":"Services"
        }
    ],
    "sg:phone":"+1 281 480 3214",
    "sg:postcode":"78767",
    "sg:province":"TX",
    "sg:website":"www.guarantybank.com",
    "wof:name":"Guaranty Bank",
    "wof:placetype":"venue"
},
  "geometry": {"coordinates":[-97.746696,30.2684],"type":"Point"}
}