{
  "type": "Feature",
  "properties": {
    "iso:country":"US",
    "sg:address":"3619 Brenda Ln",
    "sg:city":"Belton",
    "sg:classifiers":[
        {
            "category":"Shopping",
            "subcategory":"Gifts & Souvenirs",
            "type":"Retail Goods"
        }
    ],
    "sg:phone":"+1 254 933 2128",
    "sg:postcode":"76513",
    "sg:province":"TX",
    "wof:name":"Aunt Grannys",
    "wof:placetype":"venue"
},
  "geometry": {"coordinates":[-97.50698800000001,31.050212],"type":"Point"}
}