{
  "type": "Feature",
  "properties": {
    "iso:country":"US",
    "sg:address":"2613 Industrial Ln",
    "sg:city":"Garland",
    "sg:classifiers":[
        {
            "category":"Manufacturing",
            "subcategory":"Chemicals & Compounds",
            "type":"Manufacturing & Wholesale Goods"
        }
    ],
    "sg:phone":"+1 972 864 4809",
    "sg:postcode":"75041",
    "sg:province":"TX",
    "sg:tags":[
        "industrial",
        "gas",
        "mfg"
    ],
    "wof:name":"Air Products",
    "wof:placetype":"venue"
},
  "geometry": {"coordinates":[-96.675797,32.87916],"type":"Point"}
}