{
  "type": "Feature",
  "properties": {
    "iso:country":"US",
    "sg:address":"140 Guadalupe Plz",
    "sg:city":"Kerrville",
    "sg:classifiers":[
        {
            "category":"Building & Trades",
            "subcategory":"Construction",
            "type":"Services"
        }
    ],
    "sg:phone":"+1 830 257 2252",
    "sg:postcode":"78028",
    "sg:province":"TX",
    "sg:tags":[
        "supply",
        "wallcoverings-installation",
        "wallpaper",
        "painting",
        "contractor",
        "equipment",
        "drywall"
    ],
    "sg:website":"http://www.villapainting.net",
    "wof:name":"Villa Painting And Drywall",
    "wof:placetype":"venue"
},
  "geometry": {"coordinates":[-99.151375,30.050389],"type":"Point"}
}