{
  "type": "Feature",
  "properties": {
    "iso:country":"US",
    "sg:address":"8103 Broadway",
    "sg:city":"San Antonio",
    "sg:classifiers":[
        {
            "category":"Real Estate",
            "subcategory":"Real Estate Agent",
            "type":"Services"
        }
    ],
    "sg:phone":"+1 210 930 7007",
    "sg:postcode":"78209",
    "sg:province":"TX",
    "wof:name":"Michael Sauder Real Estate",
    "wof:placetype":"venue"
},
  "geometry": {"coordinates":[-98.466264,29.510761],"type":"Point"}
}