{
  "type": "Feature",
  "properties": {
    "iso:country":"US",
    "sg:address":"5318 Birchman Ave",
    "sg:city":"Fort Worth",
    "sg:classifiers":[
        {
            "category":"Insurance",
            "subcategory":"Insurance Agent",
            "type":"Services"
        }
    ],
    "sg:phone":"+1 817 737 7555",
    "sg:postcode":"76107",
    "sg:province":"TX",
    "wof:name":"Nicki Thomas All State",
    "wof:placetype":"venue"
},
  "geometry": {"coordinates":[-97.402365,32.735019],"type":"Point"}
}