{
  "type": "Feature",
  "properties": {
    "iso:country":"US",
    "sg:address":"8702 N Navarro St",
    "sg:city":"Victoria",
    "sg:classifiers":[
        {
            "category":"Fast Food",
            "type":"Food & Drink"
        },
        {
            "category":"Restaurant",
            "type":"Food & Drink"
        }
    ],
    "sg:phone":"+1 361 578 6938",
    "sg:postcode":"77904",
    "sg:province":"TX",
    "sg:tags":[
        "american",
        "take",
        "chicken"
    ],
    "sg:website":"http://www.popeyes.com",
    "wof:name":"Popeyes Chicken & Biscuits",
    "wof:placetype":"venue"
},
  "geometry": {"coordinates":[-96.997528,28.87464],"type":"Point"}
}