{
  "type": "Feature",
  "properties": {
    "iso:country":"US",
    "sg:address":"909 W Spring Creek Pkwy",
    "sg:city":"Plano",
    "sg:classifiers":[
        {
            "category":"Wholesale",
            "subcategory":"Painting Supplies",
            "type":"Manufacturing & Wholesale Goods"
        }
    ],
    "sg:phone":"+1 972 517 2226",
    "sg:postcode":"75023",
    "sg:province":"TX",
    "wof:name":"P P G Architectural Finishes",
    "wof:placetype":"venue"
},
  "geometry": {"coordinates":[-96.710729,33.056584],"type":"Point"}
}