{
  "type": "Feature",
  "properties": {
    "iso:country":"US",
    "sg:address":"508 W 14th Street",
    "sg:city":"Austin",
    "sg:classifiers":[
        {
            "category":"Professional",
            "subcategory":"Lawyer & Legal Services",
            "type":"Services"
        }
    ],
    "sg:phone":"+1 512 480 8693",
    "sg:postcode":"78701",
    "sg:province":"TX",
    "wof:name":"Keel Terry",
    "wof:placetype":"venue"
},
  "geometry": {"coordinates":[-97.744657,30.277429],"type":"Point"}
}