{
  "type": "Feature",
  "properties": {
    "iso:country":"US",
    "sg:address":"515 W Greens Rd",
    "sg:city":"Houston",
    "sg:classifiers":[
        {
            "category":"Professional",
            "subcategory":"Employment Agencies",
            "type":"Services"
        }
    ],
    "sg:phone":"+1 281 875 5600",
    "sg:postcode":"77067",
    "sg:province":"TX",
    "wof:name":"Venturi Staffing Partners",
    "wof:placetype":"venue"
},
  "geometry": {"coordinates":[-95.423875,29.948964],"type":"Point"}
}