{
  "type": "Feature",
  "properties": {
    "iso:country":"US",
    "sg:address":"6555 Eastex Fwy",
    "sg:city":"Beaumont",
    "sg:classifiers":[
        {
            "category":"Retail",
            "subcategory":"Auto Repair",
            "type":"Services"
        }
    ],
    "sg:phone":"+1 409 892 3531",
    "sg:postcode":"77706",
    "sg:province":"TX",
    "sg:tags":[
        "repairing",
        "automobile",
        "station",
        "gasoline",
        "general"
    ],
    "wof:name":"Covels Auto Service & Supply",
    "wof:placetype":"venue"
},
  "geometry": {"coordinates":[-94.16419,30.130274],"type":"Point"}
}