{
  "type": "Feature",
  "properties": {
    "iso:country":"US",
    "sg:address":"1700 Gazin St",
    "sg:city":"Houston",
    "sg:classifiers":[
        {
            "category":"Professional",
            "subcategory":"Engineering",
            "type":"Services"
        }
    ],
    "sg:phone":"+1 713 671 2233",
    "sg:postcode":"77020",
    "sg:province":"TX",
    "sg:tags":[
        "process",
        "fertilizer"
    ],
    "wof:name":"Vital-Cycle Inc",
    "wof:placetype":"venue"
},
  "geometry": {"coordinates":[-95.304113,29.757787],"type":"Point"}
}