{
  "type": "Feature",
  "properties": {
    "iso:country":"US",
    "sg:address":"2902 E Denman Ave",
    "sg:city":"Lufkin",
    "sg:classifiers":[
        {
            "category":"Wholesale",
            "subcategory":"Construction Materials",
            "type":"Manufacturing & Wholesale Goods"
        }
    ],
    "sg:phone":"+1 936 637 4920",
    "sg:postcode":"75901",
    "sg:province":"TX",
    "sg:tags":[
        "timberland",
        "company",
        "timber"
    ],
    "wof:name":"Preferred Timber",
    "wof:placetype":"venue"
},
  "geometry": {"coordinates":[-94.688699,31.313513],"type":"Point"}
}