{
  "type": "Feature",
  "properties": {
    "iso:country":"US",
    "sg:address":"2945 Thousand Oaks Dr",
    "sg:city":"San Antonio",
    "sg:classifiers":[
        {
            "category":"Shopping",
            "subcategory":"Gifts & Souvenirs",
            "type":"Retail Goods"
        }
    ],
    "sg:phone":"+1 210 402 3794",
    "sg:postcode":"78247",
    "sg:province":"TX",
    "sg:tags":[
        "shop"
    ],
    "wof:name":"Tuesday Morning",
    "wof:placetype":"venue"
},
  "geometry": {"coordinates":[-98.441489,29.578074],"type":"Point"}
}