{
  "type": "Feature",
  "properties": {
    "iso:country":"US",
    "sg:address":"514 Dogwood Ln",
    "sg:city":"Mount Pleasant",
    "sg:classifiers":[
        {
            "category":"Health Services",
            "subcategory":"Optometrist",
            "type":"Services"
        }
    ],
    "sg:phone":"+1 903 575 1011",
    "sg:postcode":"75455",
    "sg:province":"TX",
    "wof:name":"Mark J Glanzer Od",
    "wof:placetype":"venue"
},
  "geometry": {"coordinates":[-94.958777,33.14081],"type":"Point"}
}