{
  "type": "Feature",
  "properties": {
    "iso:country":"US",
    "sg:address":"2318 Walnut Ridge Dr",
    "sg:city":"Missouri City",
    "sg:classifiers":[
        {
            "category":"Social Services",
            "subcategory":"Adult Care",
            "type":"Services"
        }
    ],
    "sg:phone":"+1 281 499 4353",
    "sg:postcode":"77489",
    "sg:province":"TX",
    "sg:tags":[
        "home",
        "group"
    ],
    "wof:name":"Texana Mh & Mr Ctr",
    "wof:placetype":"venue"
},
  "geometry": {"coordinates":[-95.539705,29.58669],"type":"Point"}
}