{
  "type": "Feature",
  "properties": {
    "iso:country":"US",
    "sg:address":"6219 Crab Orchard",
    "sg:city":"San Antonio",
    "sg:classifiers":[
        {
            "category":"Shopping",
            "subcategory":"Hobbies, Toys, & Games",
            "type":"Retail Goods"
        }
    ],
    "sg:phone":"+1 210 520 9181",
    "sg:postcode":"78240",
    "sg:province":"TX",
    "sg:tags":[
        "model",
        "supply"
    ],
    "wof:name":"L G Graphics",
    "wof:placetype":"venue"
},
  "geometry": {"coordinates":[-98.603672,29.505686],"type":"Point"}
}