{
  "type": "Feature",
  "properties": {
    "iso:country":"US",
    "sg:address":"114 Robinson Rd",
    "sg:city":"Spring",
    "sg:classifiers":[
        {
            "category":"Health Services",
            "subcategory":"Doctor",
            "type":"Services"
        }
    ],
    "sg:phone":"+1 281 298 5000",
    "sg:postcode":"77320",
    "sg:province":"TX",
    "sg:tags":[
        "physician",
        "surgeon"
    ],
    "wof:name":"Stephen Kelly MD",
    "wof:placetype":"venue"
},
  "geometry": {"coordinates":[-95.501454,30.763074],"type":"Point"}
}