{
  "type": "Feature",
  "properties": {
    "iso:country":"US",
    "sg:address":"1158 Singing Hills Dr",
    "sg:city":"New Braunfels",
    "sg:classifiers":[
        {
            "category":"Shopping",
            "subcategory":"Hobbies, Toys, & Games",
            "type":"Retail Goods"
        }
    ],
    "sg:phone":"+1 830 899 4532",
    "sg:postcode":"78133",
    "sg:province":"TX",
    "sg:tags":[
        "craft"
    ],
    "wof:name":"Eagle and Turtle Art",
    "wof:placetype":"venue"
},
  "geometry": {"coordinates":[-98.27431,29.881387],"type":"Point"}
}