{
  "type": "Feature",
  "properties": {
    "iso:country":"US",
    "sg:address":"8008 Cedar Springs Rd",
    "sg:city":"Dallas",
    "sg:classifiers":[
        {
            "category":"Restaurant",
            "type":"Food & Drink"
        }
    ],
    "sg:phone":"+1 214 352 5668",
    "sg:postcode":"75235",
    "sg:province":"TX",
    "sg:website":"www.chilis.com",
    "wof:name":"Chili's Bar & Bites",
    "wof:placetype":"venue"
},
  "geometry": {"coordinates":[-96.84880099999999,32.843601],"type":"Point"}
}