{
  "type": "Feature",
  "properties": {
    "iso:country":"US",
    "sg:address":"6300 W Parker Rd",
    "sg:city":"Plano",
    "sg:classifiers":[
        {
            "category":"Professional",
            "subcategory":"Research",
            "type":"Services"
        }
    ],
    "sg:phone":"+1 972 378 0053",
    "sg:postcode":"75093",
    "sg:province":"TX",
    "sg:tags":[
        "laboratory"
    ],
    "wof:name":"Damon-Metwest Lab",
    "wof:placetype":"venue"
},
  "geometry": {"coordinates":[-96.83747700000001,33.045061],"type":"Point"}
}