{
  "type": "Feature",
  "properties": {
    "iso:country":"US",
    "sg:address":"1115 S 55th St",
    "sg:city":"Temple",
    "sg:classifiers":[
        {
            "category":"Retail",
            "subcategory":"Auto Repair",
            "type":"Services"
        }
    ],
    "sg:phone":"+1 254 771 1180",
    "sg:postcode":"76504",
    "sg:province":"TX",
    "sg:tags":[
        "body",
        "repairing",
        "customizing",
        "painting",
        "automobile"
    ],
    "wof:name":"Epperson Paint & Body Inc",
    "wof:placetype":"venue"
},
  "geometry": {"coordinates":[-97.37476100000001,31.09404],"type":"Point"}
}