{
  "type": "Feature",
  "properties": {
    "iso:country":"US",
    "sg:address":"307 Harrington Ln",
    "sg:city":"Euless",
    "sg:classifiers":[
        {
            "category":"Home & Garden",
            "subcategory":"Home Furnishings",
            "type":"Retail Goods"
        }
    ],
    "sg:phone":"+1 817 267 2880",
    "sg:postcode":"76039",
    "sg:province":"TX",
    "wof:name":"Total Interiors Ltd",
    "wof:placetype":"venue"
},
  "geometry": {"coordinates":[-97.078203,32.867784],"type":"Point"}
}