{
  "type": "Feature",
  "properties": {
    "iso:country":"US",
    "sg:address":"2555 Eldridge Rd",
    "sg:city":"Sugar Land",
    "sg:classifiers":[
        {
            "category":"Autos & Motor Vehicles",
            "subcategory":"Auto Supplies",
            "type":"Retail Goods"
        }
    ],
    "sg:phone":"+1 281 313 4252",
    "sg:postcode":"77478",
    "sg:province":"TX",
    "wof:name":"Booth Tech Inc",
    "wof:placetype":"venue"
},
  "geometry": {"coordinates":[-95.619103,29.652335],"type":"Point"}
}