{
  "type": "Feature",
  "properties": {
    "iso:country":"US",
    "sg:address":"5309 Walzem Rd",
    "sg:city":"San Antonio",
    "sg:classifiers":[
        {
            "category":"Manufacturing",
            "subcategory":"Printing",
            "type":"Manufacturing & Wholesale Goods"
        }
    ],
    "sg:phone":"+1 210 650 3459",
    "sg:postcode":"78218",
    "sg:province":"TX",
    "sg:tags":[
        "newspaper"
    ],
    "wof:name":"Satellite Network Medical",
    "wof:placetype":"venue"
},
  "geometry": {"coordinates":[-98.38181,29.51036],"type":"Point"}
}