{
  "type": "Feature",
  "properties": {
    "iso:country":"US",
    "sg:address":"8609 Lupton Ln",
    "sg:city":"Houston",
    "sg:classifiers":[
        {
            "category":"Professional",
            "subcategory":"Lawyer & Legal Services",
            "type":"Services"
        }
    ],
    "sg:phone":"+1 713 465 8820",
    "sg:postcode":"77055",
    "sg:province":"TX",
    "wof:name":"Lundgren Trial Consulting",
    "wof:placetype":"venue"
},
  "geometry": {"coordinates":[-95.503613,29.792803],"type":"Point"}
}