{
  "type": "Feature",
  "properties": {
    "iso:country":"US",
    "sg:address":"4150 Calder Ave",
    "sg:city":"Beaumont",
    "sg:classifiers":[
        {
            "category":"Insurance",
            "subcategory":"Insurance Agent",
            "type":"Services"
        }
    ],
    "sg:phone":"+1 409 924 8901",
    "sg:postcode":"77706",
    "sg:province":"TX",
    "wof:name":"Allstate",
    "wof:placetype":"venue"
},
  "geometry": {"coordinates":[-94.146646,30.085902],"type":"Point"}
}