{
  "type": "Feature",
  "properties": {
    "iso:country":"US",
    "sg:address":"3304 Meadow Creek Ln",
    "sg:city":"Garland",
    "sg:classifiers":[
        {
            "category":"Professional",
            "subcategory":"Management & Consulting",
            "type":"Services"
        }
    ],
    "sg:phone":"+1 972 495 9275",
    "sg:postcode":"75048",
    "sg:province":"TX",
    "sg:tags":[
        "business"
    ],
    "wof:name":"Rhines Technical Service LLC",
    "wof:placetype":"venue"
},
  "geometry": {"coordinates":[-96.592904,32.971457],"type":"Point"}
}