{
  "type": "Feature",
  "properties": {
    "iso:country":"US",
    "sg:address":"6518 Eastwood St",
    "sg:city":"Houston",
    "sg:classifiers":[
        {
            "category":"Manufacturing",
            "subcategory":"Tools & Machinery",
            "type":"Manufacturing & Wholesale Goods"
        }
    ],
    "sg:phone":"+1 713 747 3032",
    "sg:postcode":"77021",
    "sg:province":"TX",
    "sg:tags":[
        "machine",
        "shop"
    ],
    "wof:name":"Avco",
    "wof:placetype":"venue"
},
  "geometry": {"coordinates":[-95.353111,29.692847],"type":"Point"}
}