{
  "type": "Feature",
  "properties": {
    "iso:country":"US",
    "sg:address":"2227 W Briargate Dr",
    "sg:city":"Bryan",
    "sg:classifiers":[
        {
            "category":"Building & Trades",
            "subcategory":"Construction",
            "type":"Services"
        }
    ],
    "sg:phone":"+1 979 776 9709",
    "sg:postcode":"77802",
    "sg:province":"TX",
    "sg:tags":[
        "house"
    ],
    "wof:name":"Easterling Homes",
    "wof:placetype":"venue"
},
  "geometry": {"coordinates":[-96.340112,30.668795],"type":"Point"}
}