{
  "type": "Feature",
  "properties": {
    "iso:country":"US",
    "sg:address":"27910 State Highway 249",
    "sg:city":"Tomball",
    "sg:classifiers":[
        {
            "category":"Insurance",
            "subcategory":"Insurance Agent",
            "type":"Services"
        },
        {
            "category":"Insurance",
            "subcategory":"Hazard Insurance",
            "type":"Services"
        }
    ],
    "sg:phone":"+1 281 547 3644",
    "sg:postcode":"77375",
    "sg:province":"TX",
    "sg:tags":[
        "auto",
        "motorcycle"
    ],
    "sg:website":"http://www.firstacceptancecorp.com/Locations.aspx",
    "wof:name":"Acceptance Auto Insurance- Tomball",
    "wof:placetype":"venue"
},
  "geometry": {"coordinates":[-95.629716,30.079943],"type":"Point"}
}