{
  "type": "Feature",
  "properties": {
    "iso:country":"US",
    "sg:address":"109 S Melton Dr",
    "sg:city":"Malakoff",
    "sg:classifiers":[
        {
            "category":"Government",
            "subcategory":"City Hall",
            "type":"Public Place"
        },
        {
            "category":"Government",
            "subcategory":"Office",
            "type":"Public Place"
        }
    ],
    "sg:phone":"+1 903 489 0521",
    "sg:postcode":"75148",
    "sg:province":"TX",
    "sg:tags":[
        "town",
        "township",
        "planner",
        "government-city",
        "village"
    ],
    "wof:name":"City of Malakoff",
    "wof:placetype":"venue"
},
  "geometry": {"coordinates":[-96.01413100000001,32.170485],"type":"Point"}
}