{
  "type": "Feature",
  "properties": {
    "iso:country":"US",
    "sg:address":"7239 Park Ln",
    "sg:city":"Dallas",
    "sg:classifiers":[
        {
            "category":"Professional",
            "subcategory":"Management & Consulting",
            "type":"Services"
        }
    ],
    "sg:phone":"+1 214 361 1231",
    "sg:postcode":"75225",
    "sg:province":"TX",
    "sg:tags":[
        "consultant",
        "business"
    ],
    "wof:name":"Time2",
    "wof:placetype":"venue"
},
  "geometry": {"coordinates":[-96.780423,32.872714],"type":"Point"}
}