{
  "type": "Feature",
  "properties": {
    "iso:country":"US",
    "sg:address":"1025 Nogalitos St",
    "sg:city":"San Antonio",
    "sg:classifiers":[
        {
            "category":"Bars & Pubs",
            "type":"Food & Drink"
        }
    ],
    "sg:phone":"+1 210 227 5130",
    "sg:postcode":"78204",
    "sg:province":"TX",
    "sg:tags":[
        "drinking"
    ],
    "wof:name":"Cool Arrows",
    "wof:placetype":"venue"
},
  "geometry": {"coordinates":[-98.51009999999999,29.402338],"type":"Point"}
}