{
  "type": "Feature",
  "properties": {
    "iso:country":"US",
    "sg:address":"808 Brook Ave",
    "sg:city":"Wichita Falls",
    "sg:classifiers":[
        {
            "category":"Health Services",
            "subcategory":"Doctor",
            "type":"Services"
        }
    ],
    "sg:phone":"+1 940 761 4116",
    "sg:postcode":"76301",
    "sg:province":"TX",
    "sg:tags":[
        "physician"
    ],
    "wof:name":"Paul L Bice",
    "wof:placetype":"venue"
},
  "geometry": {"coordinates":[-98.50373,33.903902],"type":"Point"}
}