{
  "type": "Feature",
  "properties": {
    "iso:country":"US",
    "sg:address":"8643 Darrington Dr",
    "sg:city":"Dallas",
    "sg:classifiers":[
        {
            "category":"Organizations",
            "subcategory":"Community Association",
            "type":"Services"
        }
    ],
    "sg:phone":"+1 972 298 3227",
    "sg:postcode":"75249",
    "sg:province":"TX",
    "wof:name":"Daybreak Community Service",
    "wof:placetype":"venue"
},
  "geometry": {"coordinates":[-96.94959299999999,32.658798],"type":"Point"}
}