{
  "type": "Feature",
  "properties": {
    "iso:country":"US",
    "sg:address":"303 Jackson Hill St",
    "sg:city":"Houston",
    "sg:classifiers":[
        {
            "category":"Social Services",
            "type":"Services"
        }
    ],
    "sg:phone":"+1 713 914 0556",
    "sg:postcode":"77007",
    "sg:province":"TX",
    "sg:tags":[
        "therapy",
        "lecturing"
    ],
    "wof:name":"Center For Recovering Families",
    "wof:placetype":"venue"
},
  "geometry": {"coordinates":[-95.401826,29.763342],"type":"Point"}
}