{
  "type": "Feature",
  "properties": {
    "iso:country":"US",
    "sg:address":"1508 C St",
    "sg:city":"Floresville",
    "sg:classifiers":[
        {
            "category":"Organizations",
            "subcategory":"Membership Organization",
            "type":"Services"
        }
    ],
    "sg:phone":"+1 830 393 3395",
    "sg:postcode":"78114",
    "sg:province":"TX",
    "wof:name":"Texas Through Time Living Hist",
    "wof:placetype":"venue"
},
  "geometry": {"coordinates":[-98.15234700000001,29.138023],"type":"Point"}
}