{
  "type": "Feature",
  "properties": {
    "iso:country":"US",
    "sg:address":"9201 Dyer St",
    "sg:city":"El Paso",
    "sg:classifiers":[
        {
            "category":"Health Services",
            "subcategory":"Doctor",
            "type":"Services"
        }
    ],
    "sg:phone":"+1 915 757 9854",
    "sg:postcode":"79924",
    "sg:province":"TX",
    "sg:tags":[
        "clinic"
    ],
    "wof:name":"Northeast Clinic",
    "wof:placetype":"venue"
},
  "geometry": {"coordinates":[-106.42458999999999,31.875404],"type":"Point"}
}