{
  "type": "Feature",
  "properties": {
    "iso:country":"US",
    "sg:address":"3131 Bulverde Rd",
    "sg:city":"Bulverde",
    "sg:classifiers":[
        {
            "category":"Banks & Credit Unions",
            "subcategory":"Bank",
            "type":"Services"
        }
    ],
    "sg:phone":"+1 830 438 4848",
    "sg:postcode":"78163",
    "sg:province":"TX",
    "wof:name":"Security State Bank & Trust",
    "wof:placetype":"venue"
},
  "geometry": {"coordinates":[-98.43711999999999,29.742809],"type":"Point"}
}