{
  "type": "Feature",
  "properties": {
    "iso:country":"US",
    "sg:address":"900 W 38th Street Suite 350",
    "sg:city":"Austin",
    "sg:classifiers":[
        {
            "category":"Health Services",
            "subcategory":"Doctor",
            "type":"Services"
        }
    ],
    "sg:phone":"+1 512 458 2600",
    "sg:postcode":"78705",
    "sg:province":"TX",
    "wof:name":"Cain Robert M MD",
    "wof:placetype":"venue"
},
  "geometry": {"coordinates":[-97.742249,30.304833],"type":"Point"}
}