{
  "type": "Feature",
  "properties": {
    "iso:country":"US",
    "sg:address":"3956 Bluebonnet Dr",
    "sg:city":"Stafford",
    "sg:classifiers":[
        {
            "category":"Health Services",
            "subcategory":"Health Practitioner",
            "type":"Services"
        }
    ],
    "sg:phone":"+1 281 494 5141",
    "sg:postcode":"77477",
    "sg:province":"TX",
    "sg:tags":[
        "therapist",
        "physical"
    ],
    "wof:name":"Complete Medical & Rehab",
    "wof:placetype":"venue"
},
  "geometry": {"coordinates":[-95.56873299999999,29.635973],"type":"Point"}
}