{
  "type": "Feature",
  "properties": {
    "iso:country":"US",
    "sg:address":"4025 State Hwy 6",
    "sg:city":"Houston",
    "sg:classifiers":[
        {
            "category":"Food & Beverages",
            "subcategory":"Bakery",
            "type":"Retail Goods"
        }
    ],
    "sg:phone":"+1 281 859 7822",
    "sg:postcode":"77084",
    "sg:province":"TX",
    "sg:tags":[
        "doughnut"
    ],
    "wof:name":"Champion Donuts & Kolaches",
    "wof:placetype":"venue"
},
  "geometry": {"coordinates":[-95.645567,29.831438],"type":"Point"}
}