{
  "type": "Feature",
  "properties": {
    "iso:country":"US",
    "sg:address":"8015 Glenview Dr",
    "sg:city":"Fort Worth",
    "sg:classifiers":[
        {
            "category":"Professional",
            "subcategory":"Computer Services",
            "type":"Services"
        }
    ],
    "sg:phone":"+1 817 280 0494",
    "sg:postcode":"76180",
    "sg:province":"TX",
    "sg:tags":[
        "consultant",
        "designer"
    ],
    "sg:website":"www.abacinc.com",
    "wof:name":"Abaci Inc",
    "wof:placetype":"venue"
},
  "geometry": {"coordinates":[-97.20746800000001,32.823578],"type":"Point"}
}