{
  "type": "Feature",
  "properties": {
    "iso:country":"US",
    "sg:address":"2032 Ave F",
    "sg:city":"Bay City",
    "sg:classifiers":[
        {
            "category":"Personal",
            "subcategory":"Beauty Salon",
            "type":"Services"
        }
    ],
    "sg:phone":"+1 979 245 0102",
    "sg:postcode":"77414",
    "sg:province":"TX",
    "sg:tags":[
        "manicuring"
    ],
    "wof:name":"K Nails Too",
    "wof:placetype":"venue"
},
  "geometry": {"coordinates":[-95.97013099999999,28.98372],"type":"Point"}
}