{
  "type": "Feature",
  "properties": {
    "iso:country":"US",
    "sg:address":"1971 E State Hwy 31",
    "sg:city":"Corsicana",
    "sg:classifiers":[
        {
            "category":"Autos & Motor Vehicles",
            "subcategory":"Automobile Sales",
            "type":"Retail Goods"
        }
    ],
    "sg:phone":"+1 903 874 6548",
    "sg:postcode":"75110",
    "sg:province":"TX",
    "sg:tags":[
        "car",
        "dealer"
    ],
    "wof:name":"Berry Chrysler-Dodge-Jeep",
    "wof:placetype":"venue"
},
  "geometry": {"coordinates":[-96.444197,32.098573],"type":"Point"}
}