{
  "type": "Feature",
  "properties": {
    "iso:country":"US",
    "sg:address":"5271 34th St",
    "sg:city":"Lubbock",
    "sg:classifiers":[
        {
            "category":"Wholesale",
            "subcategory":"Home Furnishings",
            "type":"Manufacturing & Wholesale Goods"
        }
    ],
    "sg:phone":"+1 806 791 2774",
    "sg:postcode":"79407",
    "sg:province":"TX",
    "wof:name":"Polter Company",
    "wof:placetype":"venue"
},
  "geometry": {"coordinates":[-101.92518200000001,33.563363],"type":"Point"}
}