{
  "type": "Feature",
  "properties": {
    "iso:country":"US",
    "sg:address":"11618 Barrow",
    "sg:city":"San Antonio",
    "sg:classifiers":[
        {
            "category":"Retail",
            "subcategory":"Repair Shop",
            "type":"Services"
        }
    ],
    "sg:phone":"+1 210 732 3300",
    "sg:postcode":"78253",
    "sg:province":"TX",
    "sg:tags":[
        "bathtub",
        "sink",
        "refinishing"
    ],
    "wof:name":"San Antonio Stone",
    "wof:placetype":"venue"
},
  "geometry": {"coordinates":[-98.718131,29.445579],"type":"Point"}
}