{
  "type": "Feature",
  "properties": {
    "iso:country":"US",
    "sg:address":"5305 Trinity Blvd",
    "sg:city":"Snyder",
    "sg:classifiers":[
        {
            "category":"Health Services",
            "subcategory":"Clinic",
            "type":"Services"
        }
    ],
    "sg:phone":"+1 325 574 6874",
    "sg:postcode":"79549",
    "sg:province":"TX",
    "sg:tags":[
        "home",
        "care"
    ],
    "wof:name":"Interim Services",
    "wof:placetype":"venue"
},
  "geometry": {"coordinates":[-100.918533,32.688809],"type":"Point"}
}