{
  "type": "Feature",
  "properties": {
    "iso:country":"US",
    "sg:address":"1008 Clinton Dr",
    "sg:city":"Plano",
    "sg:classifiers":[
        {
            "category":"Professional",
            "subcategory":"Engineering",
            "type":"Services"
        }
    ],
    "sg:phone":"+1 972 509 7094",
    "sg:postcode":"75075",
    "sg:province":"TX",
    "sg:tags":[
        "aircraft",
        "maintenance"
    ],
    "sg:website":"http://www.zeusaircraftparts.vpweb.com",
    "wof:name":"Zeus Aircraft Parts",
    "wof:placetype":"venue"
},
  "geometry": {"coordinates":[-96.71489699999999,33.035278],"type":"Point"}
}