{
  "type": "Feature",
  "properties": {
    "iso:country":"US",
    "sg:address":"1201 Elm St",
    "sg:city":"Dallas",
    "sg:classifiers":[
        {
            "category":"Restaurant",
            "type":"Food & Drink"
        }
    ],
    "sg:menulink":"http://www.allmenus.com/tx/northeast/179269-chick-fil-a/menu/",
    "sg:phone":"+1 214 748 4520",
    "sg:postcode":"75270",
    "sg:province":"TX",
    "sg:tags":[
        "wrap",
        "soup",
        "american",
        "sandwich",
        "salad"
    ],
    "wof:name":"Chick-fil-A",
    "wof:placetype":"venue"
},
  "geometry": {"coordinates":[-96.80203299999999,32.781277],"type":"Point"}
}