{
  "type": "Feature",
  "properties": {
    "iso:country":"US",
    "sg:address":"10449 Yorkford Dr",
    "sg:city":"Dallas",
    "sg:classifiers":[
        {
            "category":"Manufacturing",
            "subcategory":"Aerospace",
            "type":"Manufacturing & Wholesale Goods"
        }
    ],
    "sg:phone":"+1 214 341 1131",
    "sg:postcode":"75238",
    "sg:province":"TX",
    "sg:tags":[
        "aircraft",
        "component"
    ],
    "wof:name":"Bell South Wireless Data",
    "wof:placetype":"venue"
},
  "geometry": {"coordinates":[-96.704517,32.884602],"type":"Point"}
}