{
  "type": "Feature",
  "properties": {
    "iso:country":"US",
    "sg:address":"103 Wedgewood Ave",
    "sg:city":"Hitchcock",
    "sg:classifiers":[
        {
            "category":"Retail",
            "subcategory":"Repair Shop",
            "type":"Services"
        }
    ],
    "sg:phone":"+1 409 762 6714",
    "sg:postcode":"77563",
    "sg:province":"TX",
    "sg:tags":[
        "lock",
        "locksmith"
    ],
    "wof:name":"Able Keys",
    "wof:placetype":"venue"
},
  "geometry": {"coordinates":[-95.01781699999999,29.354788],"type":"Point"}
}