{
  "type": "Feature",
  "properties": {
    "iso:country":"US",
    "sg:address":"1517 Wexford Dr",
    "sg:city":"Deer Park",
    "sg:classifiers":[
        {
            "category":"Professional",
            "subcategory":"Business Services",
            "type":"Services"
        }
    ],
    "sg:phone":"+1 281 479 4341",
    "sg:postcode":"77536",
    "sg:province":"TX",
    "wof:name":"Premier Design",
    "wof:placetype":"venue"
},
  "geometry": {"coordinates":[-95.13711000000001,29.693614],"type":"Point"}
}