{
  "type": "Feature",
  "properties": {
    "iso:country":"US",
    "sg:address":"502 Texas St",
    "sg:city":"Copperas Cove",
    "sg:classifiers":[
        {
            "category":"Wholesale",
            "subcategory":"Machinery & Supplies",
            "type":"Manufacturing & Wholesale Goods"
        }
    ],
    "sg:phone":"+1 254 542 7607",
    "sg:postcode":"76522",
    "sg:province":"TX",
    "sg:tags":[
        "janitor"
    ],
    "wof:name":"Polaris Marketing",
    "wof:placetype":"venue"
},
  "geometry": {"coordinates":[-97.89024000000001,31.13216],"type":"Point"}
}