{
  "type": "Feature",
  "properties": {
    "iso:country":"US",
    "sg:address":"28510 Lochlevan Ct",
    "sg:city":"Huffman",
    "sg:classifiers":[
        {
            "category":"Professional",
            "subcategory":"Business Services",
            "type":"Services"
        }
    ],
    "sg:phone":"+1 281 324 4960",
    "sg:postcode":"77336",
    "sg:province":"TX",
    "wof:name":"Advanced A&G Solutions",
    "wof:placetype":"venue"
},
  "geometry": {"coordinates":[-95.09887500000001,30.073131],"type":"Point"}
}