{
  "type": "Feature",
  "properties": {
    "iso:country":"US",
    "sg:address":"720 N Commerce St",
    "sg:city":"Port Lavaca",
    "sg:classifiers":[
        {
            "category":"Retail",
            "subcategory":"Repair Shop",
            "type":"Services"
        }
    ],
    "sg:phone":"+1 361 552 5322",
    "sg:postcode":"77979",
    "sg:province":"TX",
    "sg:tags":[
        "house",
        "construction"
    ],
    "wof:name":"Services Unlimited",
    "wof:placetype":"venue"
},
  "geometry": {"coordinates":[-96.630675,28.624038],"type":"Point"}
}