{
  "type": "Feature",
  "properties": {
    "iso:country":"US",
    "sg:address":"828 Ball St",
    "sg:city":"Galveston",
    "sg:classifiers":[
        {
            "category":"Professional",
            "subcategory":"Business Services",
            "type":"Services"
        }
    ],
    "sg:phone":"+1 409 765 8506",
    "sg:postcode":"77550",
    "sg:province":"TX",
    "wof:name":"Designs By Petty Kash",
    "wof:placetype":"venue"
},
  "geometry": {"coordinates":[-94.77546599999999,29.30642],"type":"Point"}
}