{
  "type": "Feature",
  "properties": {
    "iso:country":"US",
    "sg:address":"1266 Santa Fe Trl",
    "sg:city":"Tyler",
    "sg:classifiers":[
        {
            "category":"Professional",
            "type":"Services"
        }
    ],
    "sg:phone":"+1 903 871 0057",
    "sg:postcode":"75703",
    "sg:province":"TX",
    "sg:tags":[
        "agent",
        "real estate"
    ],
    "wof:name":"Jerry Frampton",
    "wof:placetype":"venue"
},
  "geometry": {"coordinates":[-95.289073,32.24595],"type":"Point"}
}