{
  "type": "Feature",
  "properties": {
    "iso:country":"US",
    "sg:address":"16607 Jones Maltsberger Rd",
    "sg:city":"San Antonio",
    "sg:classifiers":[
        {
            "category":"Building & Trades",
            "subcategory":"Plumbing",
            "type":"Services"
        }
    ],
    "sg:phone":"+1 210 494 2570",
    "sg:postcode":"78247",
    "sg:province":"TX",
    "sg:tags":[
        "plumbing",
        "repair",
        "hardware",
        "work",
        "appliance"
    ],
    "wof:name":"Barts Plumbing",
    "wof:placetype":"venue"
},
  "geometry": {"coordinates":[-98.437085,29.593716],"type":"Point"}
}