{
  "type": "Feature",
  "properties": {
    "iso:country":"US",
    "sg:address":"4218 Cambridge Dr",
    "sg:city":"Corpus Christi",
    "sg:classifiers":[
        {
            "category":"Shopping",
            "subcategory":"Florist",
            "type":"Retail Goods"
        }
    ],
    "sg:phone":"+1 361 851 9778",
    "sg:postcode":"78415",
    "sg:province":"TX",
    "wof:name":"B's Flower Shop",
    "wof:placetype":"venue"
},
  "geometry": {"coordinates":[-97.41310199999999,27.743673],"type":"Point"}
}