{
  "type": "Feature",
  "properties": {
    "iso:country":"US",
    "sg:address":"12901 South Fwy",
    "sg:city":"Burleson",
    "sg:phone":"+1 817 295 1091",
    "sg:postcode":"76028",
    "sg:province":"TX",
    "sg:tags":[
        "distributor",
        "oil",
        "marketer"
    ],
    "wof:name":"Gene Harris Petroleum Inc",
    "wof:placetype":"venue"
},
  "geometry": {"coordinates":[-97.31835100000001,32.569921],"type":"Point"}
}