{
  "type": "Feature",
  "properties": {
    "iso:country":"US",
    "sg:address":"703 W Coke Rd",
    "sg:city":"Winnsboro",
    "sg:classifiers":[
        {
            "category":"Professional",
            "type":"Services"
        }
    ],
    "sg:phone":"+1 903 342 6970",
    "sg:postcode":"75494",
    "sg:province":"TX",
    "wof:name":"ND Simons Co",
    "wof:placetype":"venue"
},
  "geometry": {"coordinates":[-95.30493300000001,32.948021],"type":"Point"}
}