{
  "type": "Feature",
  "properties": {
    "iso:country":"US",
    "sg:address":"320 E Griffin Pkwy",
    "sg:city":"Mission",
    "sg:classifiers":[
        {
            "category":"Real Estate",
            "subcategory":"Real Estate Operator",
            "type":"Services"
        }
    ],
    "sg:phone":"+1 956 581 3111",
    "sg:postcode":"78572",
    "sg:province":"TX",
    "sg:tags":[
        "building",
        "apartment"
    ],
    "wof:name":"Mission Village Apts",
    "wof:placetype":"venue"
},
  "geometry": {"coordinates":[-98.321493,26.229334],"type":"Point"}
}