{
  "type": "Feature",
  "properties": {
    "iso:country":"US",
    "sg:address":"3301 Sherman St",
    "sg:city":"Houston",
    "sg:phone":"+1 713 227 2493",
    "sg:postcode":"77003",
    "sg:province":"TX",
    "sg:tags":[
        "product",
        "petroleum"
    ],
    "wof:name":"Direct Supply",
    "wof:placetype":"venue"
},
  "geometry": {"coordinates":[-95.339568,29.750581],"type":"Point"}
}