{
  "type": "Feature",
  "properties": {
    "iso:country":"US",
    "sg:address":"1609 E Griffin Pkwy",
    "sg:city":"Mission",
    "sg:classifiers":[
        {
            "category":"Professional",
            "subcategory":"Business Services",
            "type":"Services"
        }
    ],
    "sg:phone":"+1 956 519 7178",
    "sg:postcode":"78572",
    "sg:province":"TX",
    "sg:tags":[
        "box",
        "mail"
    ],
    "wof:name":"A A Mail",
    "wof:placetype":"venue"
},
  "geometry": {"coordinates":[-98.29732,26.226133],"type":"Point"}
}