{
  "type": "Feature",
  "properties": {
    "iso:country":"US",
    "sg:address":"427 W Twohig Ave",
    "sg:city":"San Angelo",
    "sg:classifiers":[
        {
            "category":"Organizations",
            "subcategory":"Membership Organization",
            "type":"Services"
        }
    ],
    "sg:phone":"+1 325 949 1255",
    "sg:postcode":"76903",
    "sg:province":"TX",
    "wof:name":"San Angelo Old Town Cnservancy",
    "wof:placetype":"venue"
},
  "geometry": {"coordinates":[-100.444767,31.458515],"type":"Point"}
}