{
  "type": "Feature",
  "properties": {
    "iso:country":"US",
    "sg:address":"101 State Hwy 114",
    "sg:city":"Grapevine",
    "sg:classifiers":[
        {
            "category":"Autos & Motor Vehicles",
            "subcategory":"Fuel & Gas Station",
            "type":"Retail Goods"
        }
    ],
    "sg:phone":"+1 817 421 0422",
    "sg:postcode":"76092",
    "sg:province":"TX",
    "sg:tags":[
        "oil"
    ],
    "wof:name":"Chevron Stations Inc",
    "wof:placetype":"venue"
},
  "geometry": {"coordinates":[-97.15096200000001,32.961194],"type":"Point"}
}