{
  "type": "Feature",
  "properties": {
    "iso:country":"US",
    "sg:address":"1701 N Hampton Rd",
    "sg:city":"Desoto",
    "sg:classifiers":[
        {
            "category":"Retail",
            "subcategory":"Portrait Studio",
            "type":"Services"
        }
    ],
    "sg:phone":"+1 972 572 4334",
    "sg:postcode":"75115",
    "sg:province":"TX",
    "sg:tags":[
        "photographer",
        "photo"
    ],
    "wof:name":"Just Sports Photography",
    "wof:placetype":"venue"
},
  "geometry": {"coordinates":[-96.85694100000001,32.624127],"type":"Point"}
}