{
  "type": "Feature",
  "properties": {
    "iso:country":"US",
    "sg:address":"2401 30th Ave N",
    "sg:city":"Texas City",
    "sg:classifiers":[
        {
            "category":"Building & Trades",
            "subcategory":"Landscaping Services",
            "type":"Services"
        }
    ],
    "sg:phone":"+1 832 256 7928",
    "sg:postcode":"77590",
    "sg:province":"TX",
    "wof:name":"Demers Landscaping",
    "wof:placetype":"venue"
},
  "geometry": {"coordinates":[-94.93070299999999,29.411669],"type":"Point"}
}