{
  "type": "Feature",
  "properties": {
    "iso:country":"US",
    "sg:address":"4645 Hwy 6",
    "sg:city":"Sugar Land",
    "sg:classifiers":[
        {
            "category":"Coffee & Tea",
            "type":"Food & Drink"
        }
    ],
    "sg:menulink":"http://www.allmenus.com/tx/sugar-land/59514-anthonys-house/menu/",
    "sg:phone":"+1 281 491 0098",
    "sg:postcode":"77478",
    "sg:province":"TX",
    "sg:tags":[
        "american"
    ],
    "wof:name":"Anthony's House",
    "wof:placetype":"venue"
},
  "geometry": {"coordinates":[-95.58398800000001,29.581456],"type":"Point"}
}