{
  "type": "Feature",
  "properties": {
    "iso:country":"US",
    "sg:address":"9662 Meadowvale Dr",
    "sg:city":"Houston",
    "sg:classifiers":[
        {
            "category":"Professional",
            "subcategory":"Management & Consulting",
            "type":"Services"
        }
    ],
    "sg:phone":"+1 713 781 2347",
    "sg:postcode":"77063",
    "sg:province":"TX",
    "sg:tags":[
        "consultant",
        "business"
    ],
    "wof:name":"Alberto Zanrrina Castillo",
    "wof:placetype":"venue"
},
  "geometry": {"coordinates":[-95.536592,29.727277],"type":"Point"}
}