{
  "type": "Feature",
  "properties": {
    "iso:country":"US",
    "sg:address":"108 Lantana Hollow",
    "sg:city":"Boerne",
    "sg:classifiers":[
        {
            "category":"Manufacturing",
            "subcategory":"Textiles",
            "type":"Manufacturing & Wholesale Goods"
        }
    ],
    "sg:phone":"+1 830 336 4151",
    "sg:postcode":"78006",
    "sg:province":"TX",
    "sg:tags":[
        "underwear",
        "knit",
        "mill"
    ],
    "wof:name":"Texas Star Classics Inc",
    "wof:placetype":"venue"
},
  "geometry": {"coordinates":[-98.582178,29.829972],"type":"Point"}
}