{
  "type": "Feature",
  "properties": {
    "iso:country":"US",
    "sg:address":"900 E 30th St Ste 107 Suite 204",
    "sg:city":"Austin",
    "sg:classifiers":[
        {
            "category":"Health Services",
            "subcategory":"Doctor",
            "type":"Services"
        }
    ],
    "sg:phone":"+1 512 452 1521",
    "sg:postcode":"78705",
    "sg:province":"TX",
    "wof:name":"Sorin Robert",
    "wof:placetype":"venue"
},
  "geometry": {"coordinates":[-97.726795,30.288855],"type":"Point"}
}