{
  "type": "Feature",
  "properties": {
    "iso:country":"US",
    "sg:address":"11600 Big John St",
    "sg:city":"Houston",
    "sg:classifiers":[
        {
            "category":"Organizations",
            "subcategory":"Religious Organization",
            "type":"Services"
        }
    ],
    "sg:phone":"+1 281 847 9770",
    "sg:postcode":"77038",
    "sg:province":"TX",
    "wof:name":"Prophets Chmbers Crtive Church",
    "wof:placetype":"venue"
},
  "geometry": {"coordinates":[-95.452777,29.89914],"type":"Point"}
}