{
  "type": "Feature",
  "properties": {
    "iso:country":"US",
    "sg:address":"1720 S Cooper St",
    "sg:city":"Arlington",
    "sg:classifiers":[
        {
            "category":"Professional",
            "subcategory":"Printing & Photocopies",
            "type":"Services"
        }
    ],
    "sg:phone":"+1 817 265 1217",
    "sg:postcode":"76013",
    "sg:province":"TX",
    "sg:tags":[
        "photocopying",
        "duplicating",
        "copying"
    ],
    "wof:name":"Eagle Business Center",
    "wof:placetype":"venue"
},
  "geometry": {"coordinates":[-97.114805,32.718131],"type":"Point"}
}