{
  "type": "Feature",
  "properties": {
    "iso:country":"US",
    "sg:address":"1054 Beechcraft Ave",
    "sg:city":"Corpus Christi",
    "sg:classifiers":[
        {
            "category":"Manufacturing",
            "subcategory":"Jewelry",
            "type":"Manufacturing & Wholesale Goods"
        }
    ],
    "sg:phone":"+1 361 879 0145",
    "sg:postcode":"78405",
    "sg:province":"TX",
    "sg:tags":[
        "precious",
        "metal",
        "mfg"
    ],
    "wof:name":"Romona P Lomas",
    "wof:placetype":"venue"
},
  "geometry": {"coordinates":[-97.43237999999999,27.766862],"type":"Point"}
}