{
  "type": "Feature",
  "properties": {
    "iso:country":"US",
    "sg:address":"7663 Guilbeau Rd",
    "sg:city":"San Antonio",
    "sg:classifiers":[
        {
            "category":"Restaurant",
            "type":"Food & Drink"
        }
    ],
    "sg:menulink":"http://www.allmenus.com/tx/san-antonio/202211-mcdonalds/menu/",
    "sg:postcode":"78250",
    "sg:province":"TX",
    "sg:tags":[
        "burger",
        "american"
    ],
    "wof:name":"McDonald's",
    "wof:placetype":"venue"
},
  "geometry": {"coordinates":[-98.63847800000001,29.519535],"type":"Point"}
}