{
  "type": "Feature",
  "properties": {
    "iso:country":"US",
    "sg:address":"3611 Gulf Fwy",
    "sg:city":"Houston",
    "sg:classifiers":[
        {
            "category":"Retail",
            "subcategory":"Auto Rental",
            "type":"Services"
        }
    ],
    "sg:phone":"+1 713 493 6557",
    "sg:postcode":"77003",
    "sg:province":"TX",
    "sg:tags":[
        "car"
    ],
    "wof:name":"Enterprise Rent-A-Car",
    "wof:placetype":"venue"
},
  "geometry": {"coordinates":[-95.34580200000001,29.735001],"type":"Point"}
}