{
  "type": "Feature",
  "properties": {
    "iso:country":"US",
    "sg:address":"4600 W Guadalupe St Blg B, Ste 5",
    "sg:city":"Austin",
    "sg:classifiers":[
        {
            "category":"Restaurant",
            "type":"Food & Drink"
        }
    ],
    "sg:phone":"+1 512 452 0300",
    "sg:postcode":"78751",
    "sg:province":"TX",
    "sg:tags":[
        "mexican"
    ],
    "sg:website":"sagomodernmexican.com",
    "wof:name":"Sago",
    "wof:placetype":"venue"
},
  "geometry": {"coordinates":[-97.731697,30.312914],"type":"Point"}
}