{
  "type": "Feature",
  "properties": {
    "iso:country":"US",
    "sg:address":"2353 S Collins St",
    "sg:city":"Arlington",
    "sg:classifiers":[
        {
            "category":"Professional",
            "subcategory":"Engineering",
            "type":"Services"
        },
        {
            "category":"Professional",
            "subcategory":"Business Services",
            "type":"Services"
        }
    ],
    "sg:phone":"+1 817 277 2433",
    "sg:postcode":"76014",
    "sg:province":"TX",
    "sg:tags":[
        "drafting"
    ],
    "wof:name":"Agee Steel & Detailing",
    "wof:placetype":"venue"
},
  "geometry": {"coordinates":[-97.097471,32.704291],"type":"Point"}
}