{
  "type": "Feature",
  "properties": {
    "iso:country":"US",
    "sg:address":"1602 E Van Buren Ave",
    "sg:city":"Harlingen",
    "sg:classifiers":[
        {
            "category":"Building & Trades",
            "subcategory":"Construction",
            "type":"Services"
        }
    ],
    "sg:phone":"+1 956 428 6123",
    "sg:postcode":"78550",
    "sg:province":"TX",
    "sg:tags":[
        "nonresidential"
    ],
    "wof:name":"Formost Construction",
    "wof:placetype":"venue"
},
  "geometry": {"coordinates":[-97.67875100000001,26.191612],"type":"Point"}
}