{
  "type": "Feature",
  "properties": {
    "iso:country":"US",
    "sg:address":"9633 W Ferris Branch Blvd",
    "sg:city":"Dallas",
    "sg:classifiers":[
        {
            "category":"Personal",
            "subcategory":"Beauty Salon",
            "type":"Services"
        }
    ],
    "sg:phone":"+1 214 341 0406",
    "sg:postcode":"75243",
    "sg:province":"TX",
    "sg:tags":[
        "shop"
    ],
    "wof:name":"A Nu Look Salon",
    "wof:placetype":"venue"
},
  "geometry": {"coordinates":[-96.72682,32.904305],"type":"Point"}
}