{
  "type": "Feature",
  "properties": {
    "iso:country":"US",
    "sg:address":"2922 N Bend Dr",
    "sg:city":"Dallas",
    "sg:classifiers":[
        {
            "category":"Professional",
            "type":"Services"
        }
    ],
    "sg:phone":"+1 972 406 9840",
    "sg:postcode":"75229",
    "sg:province":"TX",
    "wof:name":"Mark A Reynolds",
    "wof:placetype":"venue"
},
  "geometry": {"coordinates":[-96.880151,32.907967],"type":"Point"}
}