{
  "type": "Feature",
  "properties": {
    "iso:country":"US",
    "sg:address":"6006 Fairdale Ln",
    "sg:city":"Houston",
    "sg:classifiers":[
        {
            "category":"Professional",
            "subcategory":"Management & Consulting",
            "type":"Services"
        }
    ],
    "sg:phone":"+1 713 977 1118",
    "sg:postcode":"77057",
    "sg:province":"TX",
    "sg:tags":[
        "equipment",
        "construction"
    ],
    "wof:name":"Swiss Builders",
    "wof:placetype":"venue"
},
  "geometry": {"coordinates":[-95.48432699999999,29.733127],"type":"Point"}
}