{
  "type": "Feature",
  "properties": {
    "iso:country":"US",
    "sg:address":"8991 Grissom Rd",
    "sg:city":"San Antonio",
    "sg:classifiers":[
        {
            "category":"Autos & Motor Vehicles",
            "subcategory":"Automobile Sales",
            "type":"Retail Goods"
        }
    ],
    "sg:phone":"+1 210 256 8788",
    "sg:postcode":"78251",
    "sg:province":"TX",
    "sg:tags":[
        "used"
    ],
    "wof:name":"J D Mustangs",
    "wof:placetype":"venue"
},
  "geometry": {"coordinates":[-98.660929,29.481719],"type":"Point"}
}