{
  "type": "Feature",
  "properties": {
    "iso:country":"US",
    "sg:address":"3402 Hwy 21 E",
    "sg:city":"Bryan",
    "sg:classifiers":[
        {
            "category":"Food & Beverages",
            "subcategory":"Groceries & Convenience Stores",
            "type":"Retail Goods"
        }
    ],
    "sg:phone":"+1 979 778 0564",
    "sg:postcode":"77808",
    "sg:province":"TX",
    "wof:name":"Express Mart",
    "wof:placetype":"venue"
},
  "geometry": {"coordinates":[-96.35469000000001,30.700573],"type":"Point"}
}