{
  "type": "Feature",
  "properties": {
    "iso:country":"US",
    "sg:address":"2812 Umar Ave",
    "sg:city":"Mcallen",
    "sg:classifiers":[
        {
            "category":"Retail",
            "subcategory":"Portrait Studio",
            "type":"Services"
        }
    ],
    "sg:phone":"+1 956 607 9369",
    "sg:postcode":"78504",
    "sg:province":"TX",
    "sg:tags":[
        "photographer"
    ],
    "wof:name":"Reflection Video Production",
    "wof:placetype":"venue"
},
  "geometry": {"coordinates":[-98.24265200000001,26.270889],"type":"Point"}
}