{
  "type": "Feature",
  "properties": {
    "iso:country":"US",
    "sg:address":"309 Ridgewood Rd",
    "sg:city":"Fort Worth",
    "sg:classifiers":[
        {
            "category":"Manufacturing",
            "subcategory":"Retail Goods",
            "type":"Manufacturing & Wholesale Goods"
        }
    ],
    "sg:phone":"+1 817 740 9292",
    "sg:postcode":"76107",
    "sg:province":"TX",
    "sg:tags":[
        "product",
        "mfg"
    ],
    "wof:name":"Planet Zolon",
    "wof:placetype":"venue"
},
  "geometry": {"coordinates":[-97.37556499999999,32.765463],"type":"Point"}
}