{
  "type": "Feature",
  "properties": {
    "iso:country":"US",
    "sg:address":"16350 Park Ten Pl",
    "sg:city":"Houston",
    "sg:classifiers":[
        {
            "category":"Building & Trades",
            "subcategory":"Pest Control",
            "type":"Services"
        }
    ],
    "sg:phone":"+1 281 578 3839",
    "sg:postcode":"77084",
    "sg:province":"TX",
    "wof:name":"Four Seasons Pest Control",
    "wof:placetype":"venue"
},
  "geometry": {"coordinates":[-95.66392399999999,29.786889],"type":"Point"}
}