{
  "type": "Feature",
  "properties": {
    "iso:country":"US",
    "sg:address":"10115 Cottonwood Canyon Dr",
    "sg:city":"Houston",
    "sg:phone":"+1 281 213 4939",
    "sg:postcode":"77095",
    "sg:province":"TX",
    "sg:website":"http://www.naturesownpestcontrol.org",
    "wof:name":"Nature's Own Pest and Lawn Services",
    "wof:placetype":"venue"
},
  "geometry": {"coordinates":[-95.682288,29.921535],"type":"Point"}
}