{
  "type": "Feature",
  "properties": {
    "iso:country":"US",
    "sg:address":"3035 Broadway Blvd",
    "sg:city":"Garland",
    "sg:classifiers":[
        {
            "category":"Building & Trades",
            "subcategory":"Equipment Rental",
            "type":"Services"
        }
    ],
    "sg:phone":"+1 972 840 0067",
    "sg:postcode":"75041",
    "sg:province":"TX",
    "sg:tags":[
        "yard"
    ],
    "wof:name":"Rent-A-Center",
    "wof:placetype":"venue"
},
  "geometry": {"coordinates":[-96.62208,32.879262],"type":"Point"}
}