{
  "type": "Feature",
  "properties": {
    "iso:country":"US",
    "sg:address":"501 E Kent St",
    "sg:city":"Lubbock",
    "sg:classifiers":[
        {
            "category":"Wholesale",
            "subcategory":"Apparel",
            "type":"Manufacturing & Wholesale Goods"
        }
    ],
    "sg:phone":"+1 806 747 8716",
    "sg:postcode":"79403",
    "sg:province":"TX",
    "sg:tags":[
        "clothing"
    ],
    "wof:name":"Western Glove Company",
    "wof:placetype":"venue"
},
  "geometry": {"coordinates":[-101.82739599999999,33.635884],"type":"Point"}
}