{
  "type": "Feature",
  "properties": {
    "iso:country":"US",
    "sg:address":"15 Louisiana Cv",
    "sg:city":"Odessa",
    "sg:classifiers":[
        {
            "category":"Professional",
            "subcategory":"Accounting & Tax Preparation",
            "type":"Services"
        }
    ],
    "sg:phone":"+1 432 362 3915",
    "sg:postcode":"79762",
    "sg:province":"TX",
    "sg:tags":[
        "return",
        "preparation-business"
    ],
    "wof:name":"Meador Tax Service",
    "wof:placetype":"venue"
},
  "geometry": {"coordinates":[-102.346513,31.901702],"type":"Point"}
}