{
  "type": "Feature",
  "properties": {
    "iso:country":"US",
    "sg:address":"5 US Hwy 83",
    "sg:city":"Mission",
    "sg:classifiers":[
        {
            "category":"Utilities",
            "subcategory":"Electric",
            "type":"Services"
        }
    ],
    "sg:phone":"+1 956 585 3751",
    "sg:postcode":"78572",
    "sg:province":"TX",
    "sg:tags":[
        "company",
        "electrical"
    ],
    "wof:name":"AEP Texas Central Company",
    "wof:placetype":"venue"
},
  "geometry": {"coordinates":[-98.38346,26.23488],"type":"Point"}
}