{
  "type": "Feature",
  "properties": {
    "iso:country":"US",
    "sg:address":"3501 New Boston Rd",
    "sg:city":"Texarkana",
    "sg:classifiers":[
        {
            "category":"Professional",
            "subcategory":"Detective & Security Services",
            "type":"Services"
        }
    ],
    "sg:phone":"+1 903 838 1538",
    "sg:postcode":"75501",
    "sg:province":"TX",
    "sg:tags":[
        "investigator"
    ],
    "wof:name":"Ronny Sharp Investigating Svc",
    "wof:placetype":"venue"
},
  "geometry": {"coordinates":[-94.09350999999999,33.442937],"type":"Point"}
}