{
  "type": "Feature",
  "properties": {
    "iso:country":"US",
    "sg:address":"8128 Fredericksburg Rd",
    "sg:city":"San Antonio",
    "sg:classifiers":[
        {
            "category":"Shopping",
            "subcategory":"Clothing, Apparel, & Fashions",
            "type":"Retail Goods"
        }
    ],
    "sg:phone":"+1 210 733 7100",
    "sg:postcode":"78229",
    "sg:province":"TX",
    "sg:tags":[
        "uniform"
    ],
    "wof:name":"Medix Discount Uniforms",
    "wof:placetype":"venue"
},
  "geometry": {"coordinates":[-98.57217300000001,29.516889],"type":"Point"}
}