{
  "type": "Feature",
  "properties": {
    "iso:country":"US",
    "sg:address":"1651 US Hwy 380",
    "sg:city":"Decatur",
    "sg:classifiers":[
        {
            "category":"Communications",
            "subcategory":"Film & Video Production",
            "type":"Services"
        }
    ],
    "sg:phone":"+1 940 626 4938",
    "sg:postcode":"76234",
    "sg:province":"TX",
    "sg:tags":[
        "motion"
    ],
    "wof:name":"Winchester Production Co",
    "wof:placetype":"venue"
},
  "geometry": {"coordinates":[-97.60890000000001,33.234562],"type":"Point"}
}