{
  "type": "Feature",
  "properties": {
    "iso:country":"US",
    "sg:address":"705 Riddels Rd",
    "sg:city":"Sherman",
    "sg:classifiers":[
        {
            "category":"Building & Trades",
            "subcategory":"Construction",
            "type":"Services"
        }
    ],
    "sg:phone":"+1 903 892 8253",
    "sg:postcode":"75092",
    "sg:province":"TX",
    "sg:tags":[
        "house"
    ],
    "wof:name":"Walker Construction",
    "wof:placetype":"venue"
},
  "geometry": {"coordinates":[-96.671147,33.613633],"type":"Point"}
}