{
  "type": "Feature",
  "properties": {
    "iso:country":"US",
    "sg:address":"224 Red Poppy Trl",
    "sg:city":"Georgetown",
    "sg:classifiers":[
        {
            "category":"Building & Trades",
            "subcategory":"Landscaping Services",
            "type":"Services"
        }
    ],
    "sg:phone":"+1 512 869 2406",
    "sg:postcode":"78633",
    "sg:province":"TX",
    "sg:tags":[
        "tree"
    ],
    "wof:name":"Williams Don",
    "wof:placetype":"venue"
},
  "geometry": {"coordinates":[-97.734425,30.697656],"type":"Point"}
}