{
  "type": "Feature",
  "properties": {
    "iso:country":"US",
    "sg:address":"508 W Shady Dr",
    "sg:city":"Kerrville",
    "sg:classifiers":[
        {
            "category":"Professional",
            "type":"Services"
        }
    ],
    "sg:phone":"+1 830 257 8878",
    "sg:postcode":"78028",
    "sg:province":"TX",
    "wof:name":"Ray Crooks",
    "wof:placetype":"venue"
},
  "geometry": {"coordinates":[-99.154678,30.052495],"type":"Point"}
}