{
  "type": "Feature",
  "properties": {
    "iso:country":"US",
    "sg:address":"1906 E Lancaster Ave",
    "sg:city":"Fort Worth",
    "sg:classifiers":[
        {
            "category":"Autos & Motor Vehicles",
            "subcategory":"Automobile Sales",
            "type":"Retail Goods"
        }
    ],
    "sg:phone":"+1 817 885 8279",
    "sg:postcode":"76103",
    "sg:province":"TX",
    "sg:tags":[
        "car",
        "dealer"
    ],
    "wof:name":"RKG & Assoc",
    "wof:placetype":"venue"
},
  "geometry": {"coordinates":[-97.299128,32.745931],"type":"Point"}
}