{
  "type": "Feature",
  "properties": {
    "iso:country":"US",
    "sg:address":"950 W Live Oak St",
    "sg:city":"Austin",
    "sg:classifiers":[
        {
            "category":"Shopping",
            "subcategory":"Antiques",
            "type":"Retail Goods"
        }
    ],
    "sg:phone":"+1 512 328 1797",
    "sg:postcode":"78704",
    "sg:province":"TX",
    "wof:name":"Leonard Oneill Antiques",
    "wof:placetype":"venue"
},
  "geometry": {"coordinates":[-97.762683,30.246058],"type":"Point"}
}