{
  "type": "Feature",
  "properties": {
    "iso:country":"US",
    "sg:address":"1010 College St",
    "sg:city":"Bastrop",
    "sg:classifiers":[
        {
            "category":"Professional",
            "type":"Services"
        }
    ],
    "sg:phone":"+1 512 308 9160",
    "sg:postcode":"78602",
    "sg:province":"TX",
    "sg:tags":[
        "establishment"
    ],
    "wof:name":"Clicks",
    "wof:placetype":"venue"
},
  "geometry": {"coordinates":[-97.31608199999999,30.105271],"type":"Point"}
}