{
  "type": "Feature",
  "properties": {
    "iso:country":"US",
    "sg:address":"611 N Temple Dr Ste A",
    "sg:city":"Diboll",
    "sg:classifiers":[
        {
            "category":"Wholesale",
            "subcategory":"Farm Supplies",
            "type":"Manufacturing & Wholesale Goods"
        },
        {
            "category":"Home & Garden",
            "subcategory":"Garden Supply",
            "type":"Retail Goods"
        },
        {
            "category":"Shopping",
            "subcategory":"Pets & Pet Supplies",
            "type":"Retail Goods"
        }
    ],
    "sg:phone":"+1 936 829 4040",
    "sg:postcode":"75941",
    "sg:province":"TX",
    "sg:tags":[
        "feed",
        "feed-wholesale",
        "equipment",
        "supplement",
        "landscaping",
        "concentrate",
        "manufacturer"
    ],
    "sg:website":"http://www.poulands.com",
    "wof:name":"Pouland's The Everything Store",
    "wof:placetype":"venue"
},
  "geometry": {"coordinates":[-94.781271,31.190667],"type":"Point"}
}