{
  "type": "Feature",
  "properties": {
    "iso:country":"US",
    "sg:address":"5301 Azle Hwy",
    "sg:city":"Weatherford",
    "sg:classifiers":[
        {
            "category":"Farming",
            "subcategory":"Livestock Farm",
            "type":"Manufacturing & Wholesale Goods"
        }
    ],
    "sg:phone":"+1 817 599 7068",
    "sg:postcode":"76085",
    "sg:province":"TX",
    "sg:tags":[
        "general"
    ],
    "wof:name":"Keene & Shelley Wright",
    "wof:placetype":"venue"
},
  "geometry": {"coordinates":[-97.67116300000001,32.822201],"type":"Point"}
}