{
  "type": "Feature",
  "properties": {
    "iso:country":"US",
    "sg:address":"4606 Centerview Dr",
    "sg:city":"San Antonio",
    "sg:classifiers":[
        {
            "category":"Professional",
            "subcategory":"Engineering",
            "type":"Services"
        },
        {
            "category":"Real Estate",
            "subcategory":"Surveying",
            "type":"Services"
        }
    ],
    "sg:phone":"+1 210 736 2646",
    "sg:postcode":"78228",
    "sg:province":"TX",
    "sg:tags":[
        "civil",
        "surveyor",
        "land"
    ],
    "wof:name":"South Texas Engineering Inc",
    "wof:placetype":"venue"
},
  "geometry": {"coordinates":[-98.574206,29.487956],"type":"Point"}
}