{
  "type": "Feature",
  "properties": {
    "iso:country":"US",
    "sg:address":"2405 Main St",
    "sg:city":"Houston",
    "sg:classifiers":[
        {
            "category":"Insurance",
            "subcategory":"Insurance Agent",
            "type":"Services"
        }
    ],
    "sg:phone":"+1 713 788 2131",
    "sg:postcode":"77002",
    "sg:province":"TX",
    "wof:name":"Texas Serenity Counseling Svcs",
    "wof:placetype":"venue"
},
  "geometry": {"coordinates":[-95.373524,29.745988],"type":"Point"}
}