{
  "type": "Feature",
  "properties": {
    "iso:country":"US",
    "sg:address":"4436 Jeff Davis St",
    "sg:city":"Marshall",
    "sg:classifiers":[
        {
            "category":"Manufacturing",
            "subcategory":"Retail Goods",
            "type":"Manufacturing & Wholesale Goods"
        }
    ],
    "sg:phone":"+1 903 927 2238",
    "sg:postcode":"75672",
    "sg:province":"TX",
    "sg:tags":[
        "product",
        "mfg"
    ],
    "wof:name":"Specialty Equipment Companies",
    "wof:placetype":"venue"
},
  "geometry": {"coordinates":[-94.315107,32.547068],"type":"Point"}
}