{
  "type": "Feature",
  "properties": {
    "iso:country":"US",
    "sg:address":"1006 West Ave",
    "sg:city":"San Antonio",
    "sg:classifiers":[
        {
            "category":"Building & Trades",
            "subcategory":"Construction",
            "type":"Services"
        }
    ],
    "sg:phone":"+1 210 736 1595",
    "sg:postcode":"78201",
    "sg:province":"TX",
    "sg:tags":[
        "roofing",
        "contractor"
    ],
    "wof:name":"Pro Star Roofing",
    "wof:placetype":"venue"
},
  "geometry": {"coordinates":[-98.52601,29.472],"type":"Point"}
}