{
  "type": "Feature",
  "properties": {
    "iso:country":"US",
    "sg:address":"6339 Kenwood Ave",
    "sg:city":"Dallas",
    "sg:classifiers":[
        {
            "category":"Professional",
            "subcategory":"Lawyer & Legal Services",
            "type":"Services"
        }
    ],
    "sg:phone":"+1 214 691 9000",
    "sg:postcode":"75214",
    "sg:province":"TX",
    "wof:name":"Law Office Of Edward Wayne Malouf",
    "wof:placetype":"venue"
},
  "geometry": {"coordinates":[-96.754259,32.833031],"type":"Point"}
}