{
  "type": "Feature",
  "properties": {
    "iso:country":"US",
    "sg:address":"3047 Pine St",
    "sg:city":"Abilene",
    "sg:classifiers":[
        {
            "category":"Freight",
            "type":"Transportation"
        }
    ],
    "sg:phone":"+1 325 670 9845",
    "sg:postcode":"79601",
    "sg:province":"TX",
    "sg:tags":[
        "mover"
    ],
    "wof:name":"County Moving Of Abilene",
    "wof:placetype":"venue"
},
  "geometry": {"coordinates":[-99.73112,32.487233],"type":"Point"}
}