{
  "type": "Feature",
  "properties": {
    "iso:country":"US",
    "sg:address":"408 Elm St",
    "sg:city":"Graham",
    "sg:classifiers":[
        {
            "category":"Professional",
            "type":"Services"
        }
    ],
    "sg:phone":"+1 940 549 6929",
    "sg:postcode":"76450",
    "sg:province":"TX",
    "sg:tags":[
        "consultant",
        "geological"
    ],
    "wof:name":"Kirk Morgan Geologist",
    "wof:placetype":"venue"
},
  "geometry": {"coordinates":[-98.589602,33.109346],"type":"Point"}
}