{
  "type": "Feature",
  "properties": {
    "iso:country":"US",
    "sg:address":"634 Lexington Ave",
    "sg:city":"Abilene",
    "sg:classifiers":[
        {
            "category":"Real Estate",
            "subcategory":"Real Estate Services",
            "type":"Services"
        },
        {
            "category":"Building & Trades",
            "subcategory":"Cleaning & Sanitation",
            "type":"Services"
        }
    ],
    "sg:phone":"+1 325 692 8444",
    "sg:postcode":"79605",
    "sg:province":"TX",
    "sg:tags":[
        "janitorial",
        "maintenance",
        "cleaners-interior"
    ],
    "sg:website":"http://www.dewaynerobertson.com",
    "wof:name":"Abilene Building Care",
    "wof:placetype":"venue"
},
  "geometry": {"coordinates":[-99.774286,32.44422],"type":"Point"}
}