{
  "type": "Feature",
  "properties": {
    "iso:country":"US",
    "sg:address":"5806 Cornell St",
    "sg:city":"Lubbock",
    "sg:classifiers":[
        {
            "category":"Social Services",
            "subcategory":"Child Care",
            "type":"Services"
        }
    ],
    "sg:phone":"+1 806 797 5560",
    "sg:postcode":"79416",
    "sg:province":"TX",
    "sg:tags":[
        "day"
    ],
    "wof:name":"Teachers of Kindergarten",
    "wof:placetype":"venue"
},
  "geometry": {"coordinates":[-101.94157800000001,33.602546],"type":"Point"}
}