{
  "type": "Feature",
  "properties": {
    "iso:country":"US",
    "sg:address":"403 S Walcott St",
    "sg:city":"Jefferson",
    "sg:classifiers":[
        {
            "category":"Restaurant",
            "type":"Food & Drink"
        },
        {
            "category":"Ice Cream",
            "type":"Food & Drink"
        }
    ],
    "sg:menulink":"http://www.allmenus.com/tx/marion-east/162318-dairy-queen/menu/",
    "sg:phone":"+1 903 665 3682",
    "sg:postcode":"75657",
    "sg:province":"TX",
    "sg:tags":[
        "burger",
        "american",
        "ice",
        "cream"
    ],
    "wof:name":"Dairy Queen",
    "wof:placetype":"venue"
},
  "geometry": {"coordinates":[-94.35495299999999,32.758319],"type":"Point"}
}