{
  "type": "Feature",
  "properties": {
    "iso:country":"US",
    "sg:address":"4727 Lexington Blvd",
    "sg:city":"Missouri City",
    "sg:classifiers":[
        {
            "category":"Health Services",
            "subcategory":"Doctor",
            "type":"Services"
        }
    ],
    "sg:phone":"+1 281 403 3595",
    "sg:postcode":"77459",
    "sg:province":"TX",
    "wof:name":"Yehdo & Assoc",
    "wof:placetype":"venue"
},
  "geometry": {"coordinates":[-95.579222,29.600859],"type":"Point"}
}