{
  "type": "Feature",
  "properties": {
    "iso:country":"US",
    "sg:address":"215 N Kaufman St",
    "sg:city":"Seagoville",
    "sg:classifiers":[
        {
            "category":"Professional",
            "subcategory":"Accounting & Tax Preparation",
            "type":"Services"
        }
    ],
    "sg:phone":"+1 972 287 9500",
    "sg:postcode":"75159",
    "sg:province":"TX",
    "sg:tags":[
        "return",
        "filing"
    ],
    "wof:name":"Jackson Hewitt Tax Svc",
    "wof:placetype":"venue"
},
  "geometry": {"coordinates":[-96.540317,32.640404],"type":"Point"}
}