{
  "type": "Feature",
  "properties": {
    "iso:country":"US",
    "sg:address":"2535 Rand Morgan Rd",
    "sg:city":"Corpus Christi",
    "sg:classifiers":[
        {
            "category":"Professional",
            "subcategory":"Business Services",
            "type":"Services"
        }
    ],
    "sg:phone":"+1 361 241 0605",
    "sg:postcode":"78410",
    "sg:province":"TX",
    "wof:name":"Inspection Services",
    "wof:placetype":"venue"
},
  "geometry": {"coordinates":[-97.54776,27.825965],"type":"Point"}
}