{
  "type": "Feature",
  "properties": {
    "iso:country":"US",
    "sg:address":"10905 Timberoak Dr",
    "sg:city":"Houston",
    "sg:classifiers":[
        {
            "category":"Professional",
            "subcategory":"Business Services",
            "type":"Services"
        }
    ],
    "sg:phone":"+1 713 464 8922",
    "sg:postcode":"77043",
    "sg:province":"TX",
    "wof:name":"Erosion Control Solutions",
    "wof:placetype":"venue"
},
  "geometry": {"coordinates":[-95.57444,29.801818],"type":"Point"}
}