{
  "type": "Feature",
  "properties": {
    "iso:country":"US",
    "sg:address":"5550 SW H K Dodgen Loop",
    "sg:city":"Temple",
    "sg:classifiers":[
        {
            "category":"Banks & Credit Unions",
            "subcategory":"Financial Services",
            "type":"Services"
        }
    ],
    "sg:phone":"+1 254 771 5550",
    "sg:postcode":"76504",
    "sg:province":"TX",
    "sg:tags":[
        "company",
        "holding"
    ],
    "sg:website":"www.fsbcentex.com",
    "wof:name":"Central Community Corp",
    "wof:placetype":"venue"
},
  "geometry": {"coordinates":[-97.391702,31.105231],"type":"Point"}
}