{
  "type": "Feature",
  "properties": {
    "iso:country":"US",
    "sg:address":"1112 Lawrence St",
    "sg:city":"Rosenberg",
    "sg:classifiers":[
        {
            "category":"Shopping",
            "type":"Retail Goods"
        }
    ],
    "sg:phone":"+1 281 762 9555",
    "sg:postcode":"77471",
    "sg:province":"TX",
    "sg:tags":[
        "product",
        "wood"
    ],
    "wof:name":"United Pacific Forest Products",
    "wof:placetype":"venue"
},
  "geometry": {"coordinates":[-95.789917,29.557596],"type":"Point"}
}