{
  "type": "Feature",
  "properties": {
    "iso:country":"US",
    "sg:address":"4601 Hudson Bend Rd",
    "sg:city":"Austin",
    "sg:classifiers":[
        {
            "category":"Manufacturing",
            "subcategory":"Metals",
            "type":"Manufacturing & Wholesale Goods"
        },
        {
            "category":"Manufacturing",
            "subcategory":"Building Materials",
            "type":"Manufacturing & Wholesale Goods"
        }
    ],
    "sg:phone":"+1 512 334 9788",
    "sg:postcode":"78734",
    "sg:province":"TX",
    "sg:tags":[
        "steel",
        "sheet",
        "work",
        "warehouse",
        "distributor",
        "mill"
    ],
    "wof:name":"Steel Rayne",
    "wof:placetype":"venue"
},
  "geometry": {"coordinates":[-97.926551,30.407323],"type":"Point"}
}