{
  "type": "Feature",
  "properties": {
    "iso:country":"US",
    "sg:address":"103 Old State Hwy 27",
    "sg:city":"Ingram",
    "sg:classifiers":[
        {
            "category":"Food & Beverages",
            "subcategory":"Groceries & Convenience Stores",
            "type":"Retail Goods"
        }
    ],
    "sg:phone":"+1 830 367 4838",
    "sg:postcode":"78028",
    "sg:province":"TX",
    "wof:name":"Neu Mart",
    "wof:placetype":"venue"
},
  "geometry": {"coordinates":[-99.22169599999999,30.068296],"type":"Point"}
}