{
  "type": "Feature",
  "properties": {
    "iso:country":"US",
    "sg:address":"1701 50th St",
    "sg:city":"Lubbock",
    "sg:classifiers":[
        {
            "category":"Restaurant",
            "type":"Food & Drink"
        }
    ],
    "sg:phone":"+1 806 744 7475",
    "sg:postcode":"79412",
    "sg:province":"TX",
    "wof:name":"Henry D's Cafe & Grill",
    "wof:placetype":"venue"
},
  "geometry": {"coordinates":[-101.857418,33.54873],"type":"Point"}
}