{
  "type": "Feature",
  "properties": {
    "iso:country":"US",
    "sg:address":"6207 Stratmor Ct",
    "sg:city":"Spring",
    "sg:classifiers":[
        {
            "category":"Manufacturing",
            "subcategory":"Rubber & Plastics",
            "type":"Manufacturing & Wholesale Goods"
        }
    ],
    "sg:phone":"+1 281 655 9970",
    "sg:postcode":"77389",
    "sg:province":"TX",
    "sg:tags":[
        "product",
        "fabricated",
        "mfg"
    ],
    "wof:name":"Timco Rubber Products Inc",
    "wof:placetype":"venue"
},
  "geometry": {"coordinates":[-95.518152,30.116577],"type":"Point"}
}