{
  "type": "Feature",
  "properties": {
    "iso:country":"US",
    "sg:address":"1004 W Bluff St",
    "sg:city":"Woodville",
    "sg:classifiers":[
        {
            "category":"Retail",
            "subcategory":"Portrait Studio",
            "type":"Services"
        }
    ],
    "sg:phone":"+1 409 283 5919",
    "sg:postcode":"75979",
    "sg:province":"TX",
    "sg:tags":[
        "photo"
    ],
    "wof:name":"Dogwood Productions",
    "wof:placetype":"venue"
},
  "geometry": {"coordinates":[-94.427646,30.775219],"type":"Point"}
}