{
  "type": "Feature",
  "properties": {
    "iso:country":"US",
    "sg:address":"1515 S Capital of Texas Hwy",
    "sg:city":"Austin",
    "sg:classifiers":[
        {
            "category":"Professional",
            "subcategory":"Accounting & Tax Preparation",
            "type":"Services"
        }
    ],
    "sg:phone":"+1 512 264 3006",
    "sg:postcode":"78746",
    "sg:province":"TX",
    "wof:name":"Tilson Stephen",
    "wof:placetype":"venue"
},
  "geometry": {"coordinates":[-97.81903800000001,30.277352],"type":"Point"}
}