{
  "type": "Feature",
  "properties": {
    "iso:country":"US",
    "sg:address":"505 Hickory Hwy",
    "sg:city":"Devine",
    "sg:classifiers":[
        {
            "category":"Shopping",
            "subcategory":"Clothing, Apparel, & Fashions",
            "type":"Retail Goods"
        }
    ],
    "sg:phone":"+1 830 665 9764",
    "sg:postcode":"78016",
    "sg:province":"TX",
    "wof:name":"Abadabs",
    "wof:placetype":"venue"
},
  "geometry": {"coordinates":[-98.905597,29.157116],"type":"Point"}
}