{
  "type": "Feature",
  "properties": {
    "iso:country":"US",
    "sg:address":"12484 Abrams Rd",
    "sg:city":"Dallas",
    "sg:classifiers":[
        {
            "category":"Professional",
            "subcategory":"Computer Services",
            "type":"Services"
        }
    ],
    "sg:phone":"+1 972 235 1940",
    "sg:postcode":"75243",
    "sg:province":"TX",
    "sg:tags":[
        "consultant",
        "designer"
    ],
    "wof:name":"Spectrum Consulting",
    "wof:placetype":"venue"
},
  "geometry": {"coordinates":[-96.735451,32.91783],"type":"Point"}
}