{
  "type": "Feature",
  "properties": {
    "iso:country":"US",
    "sg:address":"201 S Moseley Ln",
    "sg:city":"Alpine",
    "sg:classifiers":[
        {
            "category":"Real Estate",
            "subcategory":"Real Estate Operator",
            "type":"Services"
        }
    ],
    "sg:phone":"+1 432 837 5583",
    "sg:postcode":"79830",
    "sg:province":"TX",
    "sg:tags":[
        "property",
        "lessor"
    ],
    "wof:name":"Fort Davis Estates Inc",
    "wof:placetype":"venue"
},
  "geometry": {"coordinates":[-103.686491,30.345141],"type":"Point"}
}