{
  "type": "Feature",
  "properties": {
    "iso:country":"US",
    "sg:address":"641 N Cherry Ln",
    "sg:city":"Fort Worth",
    "sg:classifiers":[
        {
            "category":"Organizations",
            "subcategory":"Labor Organization",
            "type":"Services"
        }
    ],
    "sg:phone":"+1 817 246 4981",
    "sg:postcode":"76108",
    "sg:province":"TX",
    "wof:name":"Office & Prof Employes Intl Un",
    "wof:placetype":"venue"
},
  "geometry": {"coordinates":[-97.451036,32.764893],"type":"Point"}
}