{
  "type": "Feature",
  "properties": {
    "iso:country":"US",
    "sg:address":"15202 Claypool St",
    "sg:city":"Houston",
    "sg:classifiers":[
        {
            "category":"Retail",
            "subcategory":"Portrait Studio",
            "type":"Services"
        }
    ],
    "sg:phone":"+1 713 385 8125",
    "sg:postcode":"77032",
    "sg:province":"TX",
    "sg:tags":[
        "photo"
    ],
    "wof:name":"Jonahs Fashion Kids Photograp",
    "wof:placetype":"venue"
},
  "geometry": {"coordinates":[-95.369128,29.937523],"type":"Point"}
}