{
  "type": "Feature",
  "properties": {
    "iso:country":"US",
    "sg:address":"13607 Carlton Oaks",
    "sg:city":"San Antonio",
    "sg:classifiers":[
        {
            "category":"Professional",
            "subcategory":"Business Services",
            "type":"Services"
        }
    ],
    "sg:phone":"+1 210 496 9489",
    "sg:postcode":"78232",
    "sg:province":"TX",
    "wof:name":"Carol Coleman Straub",
    "wof:placetype":"venue"
},
  "geometry": {"coordinates":[-98.45874999999999,29.56738],"type":"Point"}
}