{
  "type": "Feature",
  "properties": {
    "iso:country":"US",
    "sg:address":"2539 Judson Rd",
    "sg:city":"Longview",
    "sg:classifiers":[
        {
            "category":"Home & Garden",
            "subcategory":"Furniture",
            "type":"Retail Goods"
        }
    ],
    "sg:phone":"+1 903 234 9588",
    "sg:postcode":"75605",
    "sg:province":"TX",
    "wof:name":"America's Finest Furniture",
    "wof:placetype":"venue"
},
  "geometry": {"coordinates":[-94.745429,32.539624],"type":"Point"}
}