{
  "type": "Feature",
  "properties": {
    "iso:country":"US",
    "sg:address":"5944 W Parker Rd",
    "sg:city":"Plano",
    "sg:classifiers":[
        {
            "category":"Farming",
            "subcategory":"Livestock Farm",
            "type":"Manufacturing & Wholesale Goods"
        },
        {
            "category":"Health Services",
            "subcategory":"Doctor",
            "type":"Services"
        }
    ],
    "sg:phone":"+1 972 943 5944",
    "sg:postcode":"75093",
    "sg:province":"TX",
    "sg:tags":[
        "dentist",
        "animal",
        "general"
    ],
    "wof:name":"Star Ranch Dental Spa",
    "wof:placetype":"venue"
},
  "geometry": {"coordinates":[-96.825821,33.045182],"type":"Point"}
}