{
  "type": "Feature",
  "properties": {
    "iso:country":"US",
    "sg:address":"5763 Ray Ellison Blvd",
    "sg:city":"San Antonio",
    "sg:classifiers":[
        {
            "category":"Organizations",
            "subcategory":"Community Association",
            "type":"Services"
        }
    ],
    "sg:phone":"+1 210 673 2132",
    "sg:postcode":"78242",
    "sg:province":"TX",
    "wof:name":"Knights Of Columbus",
    "wof:placetype":"venue"
},
  "geometry": {"coordinates":[-98.621298,29.357086],"type":"Point"}
}