{
  "type": "Feature",
  "properties": {
    "iso:country":"US",
    "sg:address":"575 Dawson Rd",
    "sg:city":"Seagoville",
    "sg:classifiers":[
        {
            "category":"Freight",
            "type":"Transportation"
        }
    ],
    "sg:phone":"+1 972 476 2840",
    "sg:postcode":"75159",
    "sg:province":"TX",
    "sg:tags":[
        "operator",
        "local",
        "trucking"
    ],
    "wof:name":"Ballantine Trucking",
    "wof:placetype":"venue"
},
  "geometry": {"coordinates":[-96.504544,32.549016],"type":"Point"}
}