{
  "type": "Feature",
  "properties": {
    "iso:country":"US",
    "sg:address":"3006 Bee Caves Rd Ste C250",
    "sg:city":"Austin",
    "sg:classifiers":[
        {
            "category":"Professional",
            "type":"Services"
        },
        {
            "category":"Personal",
            "type":"Services"
        }
    ],
    "sg:phone":"+1 512 236 0264",
    "sg:postcode":"78746",
    "sg:province":"TX",
    "sg:tags":[
        "party",
        "planning",
        "event"
    ],
    "sg:website":"www.clinkevents.com",
    "wof:name":"CLINK",
    "wof:placetype":"venue"
},
  "geometry": {"coordinates":[-97.793066,30.27145],"type":"Point"}
}