{
  "type": "Feature",
  "properties": {
    "iso:country":"US",
    "sg:address":"7107 W Highway 71 Suite E19",
    "sg:city":"Austin",
    "sg:classifiers":[
        {
            "category":"Banks & Credit Unions",
            "subcategory":"Investment Brokerage",
            "type":"Services"
        },
        {
            "category":"Shopping",
            "subcategory":"Computers & Home Electronics",
            "type":"Retail Goods"
        }
    ],
    "sg:phone":"+1 512 301 3494",
    "sg:postcode":"78735",
    "sg:province":"TX",
    "sg:tags":[
        "dvd",
        "tape",
        "video",
        "sale",
        "dvds-rental"
    ],
    "sg:website":"http://www.blockbuster.com",
    "wof:name":"Blockbuster Video",
    "wof:placetype":"venue"
},
  "geometry": {"coordinates":[-97.876884,30.235376],"type":"Point"}
}