{
  "type": "Feature",
  "properties": {
    "iso:country":"US",
    "sg:address":"19410 Haystream Dr",
    "sg:city":"Katy",
    "sg:classifiers":[
        {
            "category":"Wholesale",
            "subcategory":"Groceries",
            "type":"Manufacturing & Wholesale Goods"
        }
    ],
    "sg:phone":"+1 281 398 0730",
    "sg:postcode":"77449",
    "sg:province":"TX",
    "wof:name":"Rosettes Baskets & Bags",
    "wof:placetype":"venue"
},
  "geometry": {"coordinates":[-95.708054,29.818774],"type":"Point"}
}