{
  "type": "Feature",
  "properties": {
    "iso:country":"US",
    "sg:address":"4812 Almeda Rd",
    "sg:city":"Houston",
    "sg:classifiers":[
        {
            "category":"Education",
            "subcategory":"Dance Studio",
            "type":"Public Place"
        }
    ],
    "sg:phone":"+1 713 874 0460",
    "sg:postcode":"77004",
    "sg:province":"TX",
    "wof:name":"Candy Lady Ballroom",
    "wof:placetype":"venue"
},
  "geometry": {"coordinates":[-95.37750200000001,29.726772],"type":"Point"}
}