{
  "type": "Feature",
  "properties": {
    "iso:country":"US",
    "sg:address":"4613 W Orem Dr",
    "sg:city":"Houston",
    "sg:classifiers":[
        {
            "category":"Health Services",
            "subcategory":"Dentist",
            "type":"Services"
        }
    ],
    "sg:phone":"+1 713 433 4344",
    "sg:postcode":"77045",
    "sg:province":"TX",
    "sg:website":"www.westoremdental.com",
    "wof:name":"West Orem Dental Center",
    "wof:placetype":"venue"
},
  "geometry": {"coordinates":[-95.448196,29.6273],"type":"Point"}
}