{
  "type": "Feature",
  "properties": {
    "iso:country":"US",
    "sg:address":"6005 Troon Cir",
    "sg:city":"Garland",
    "sg:classifiers":[
        {
            "category":"Professional",
            "type":"Services"
        }
    ],
    "sg:phone":"+1 972 530 5883",
    "sg:postcode":"75044",
    "sg:province":"TX",
    "wof:name":"John A Rohr",
    "wof:placetype":"venue"
},
  "geometry": {"coordinates":[-96.63499899999999,32.969217],"type":"Point"}
}