{
  "type": "Feature",
  "properties": {
    "iso:country":"US",
    "sg:address":"618 Nas Dr",
    "sg:city":"Corpus Christi",
    "sg:classifiers":[
        {
            "category":"Personal",
            "subcategory":"Barber",
            "type":"Services"
        }
    ],
    "sg:phone":"+1 361 937 2470",
    "sg:postcode":"78418",
    "sg:province":"TX",
    "sg:tags":[
        "shop"
    ],
    "wof:name":"Mingo's Barber Shop",
    "wof:placetype":"venue"
},
  "geometry": {"coordinates":[-97.279512,27.673317],"type":"Point"}
}