{
  "type": "Feature",
  "properties": {
    "iso:country":"US",
    "sg:address":"511 2nd Ave",
    "sg:city":"Mineola",
    "sg:classifiers":[
        {
            "category":"Organizations",
            "subcategory":"Religious Organization",
            "type":"Services"
        }
    ],
    "sg:phone":"+1 903 569 5537",
    "sg:postcode":"75773",
    "sg:province":"TX",
    "wof:name":"Primera Asamblea De Dios",
    "wof:placetype":"venue"
},
  "geometry": {"coordinates":[-95.49051300000001,32.667908],"type":"Point"}
}