{
  "type": "Feature",
  "properties": {
    "iso:country":"US",
    "sg:address":"3056 Northpark Dr",
    "sg:city":"Humble",
    "sg:classifiers":[
        {
            "category":"Shopping",
            "subcategory":"Books",
            "type":"Retail Goods"
        }
    ],
    "sg:phone":"+1 281 360 8166",
    "sg:postcode":"77339",
    "sg:province":"TX",
    "wof:name":"Bolton Bookstore",
    "wof:placetype":"venue"
},
  "geometry": {"coordinates":[-95.201171,30.068474],"type":"Point"}
}