{
  "type": "Feature",
  "properties": {
    "iso:country":"US",
    "sg:address":"7902 Parkglen",
    "sg:city":"Houston",
    "sg:classifiers":[
        {
            "category":"Building & Trades",
            "subcategory":"Landscaping Services",
            "type":"Services"
        }
    ],
    "sg:phone":"+1 281 459 3616",
    "sg:postcode":"77049",
    "sg:province":"TX",
    "wof:name":"Betheas Best Lawn Service",
    "wof:placetype":"venue"
},
  "geometry": {"coordinates":[-95.18921899999999,29.839135],"type":"Point"}
}