{
  "type": "Feature",
  "properties": {
    "iso:country":"US",
    "sg:address":"1268 Co Rd 348",
    "sg:city":"Brazoria",
    "sg:classifiers":[
        {
            "category":"Shopping",
            "subcategory":"Clothing, Apparel, & Fashions",
            "type":"Retail Goods"
        }
    ],
    "sg:phone":"+1 979 798 0792",
    "sg:postcode":"77422",
    "sg:province":"TX",
    "wof:name":"Royal Fashion & More",
    "wof:placetype":"venue"
},
  "geometry": {"coordinates":[-95.59328600000001,29.067997],"type":"Point"}
}