{
  "type": "Feature",
  "properties": {
    "iso:country":"US",
    "sg:address":"1900 Justo Penn St",
    "sg:city":"Laredo",
    "sg:classifiers":[
        {
            "category":"Freight",
            "type":"Transportation"
        }
    ],
    "sg:phone":"+1 956 725 5658",
    "sg:postcode":"78041",
    "sg:province":"TX",
    "sg:tags":[
        "arrangement"
    ],
    "wof:name":"MCA Forwarding",
    "wof:placetype":"venue"
},
  "geometry": {"coordinates":[-99.513879,27.547666],"type":"Point"}
}