{
  "type": "Feature",
  "properties": {
    "iso:country":"US",
    "sg:address":"4200 Rock Prairie Rd",
    "sg:city":"College Station",
    "sg:classifiers":[
        {
            "category":"Restaurant",
            "type":"Food & Drink"
        }
    ],
    "sg:phone":"+1 979 690 7000",
    "sg:postcode":"77845",
    "sg:province":"TX",
    "sg:tags":[
        "eating"
    ],
    "wof:name":"Simply Delicious",
    "wof:placetype":"venue"
},
  "geometry": {"coordinates":[-96.269578,30.5851],"type":"Point"}
}