{
  "type": "Feature",
  "properties": {
    "iso:country":"US",
    "sg:address":"2000 Whisper Wood Rd",
    "sg:city":"Harker Heights",
    "sg:classifiers":[
        {
            "category":"Shopping",
            "subcategory":"Gifts & Souvenirs",
            "type":"Retail Goods"
        }
    ],
    "sg:phone":"+1 254 698 7141",
    "sg:postcode":"76548",
    "sg:province":"TX",
    "wof:name":"Greek Shop",
    "wof:placetype":"venue"
},
  "geometry": {"coordinates":[-97.647751,31.065592],"type":"Point"}
}