{
  "type": "Feature",
  "properties": {
    "iso:country":"US",
    "sg:address":"1403 Tripp Rd",
    "sg:city":"Mesquite",
    "sg:classifiers":[
        {
            "category":"Retail",
            "subcategory":"Storage",
            "type":"Services"
        }
    ],
    "sg:phone":"+1 972 289 0469",
    "sg:postcode":"75150",
    "sg:province":"TX",
    "sg:tags":[
        "self"
    ],
    "wof:name":"Lone Star Self Storage",
    "wof:placetype":"venue"
},
  "geometry": {"coordinates":[-96.616798,32.794701],"type":"Point"}
}