{
  "type": "Feature",
  "properties": {
    "iso:country":"US",
    "sg:address":"5919 Richard Carlton Blvd",
    "sg:city":"Austin",
    "sg:classifiers":[
        {
            "category":"Manufacturing",
            "subcategory":"Electronics",
            "type":"Manufacturing & Wholesale Goods"
        }
    ],
    "sg:phone":"+1 512 331 7269",
    "sg:postcode":"78727",
    "sg:province":"TX",
    "sg:tags":[
        "apparatus",
        "mfg"
    ],
    "wof:name":"D G Telecom",
    "wof:placetype":"venue"
},
  "geometry": {"coordinates":[-97.742119,30.440324],"type":"Point"}
}