{
  "type": "Feature",
  "properties": {
    "iso:country":"US",
    "sg:address":"123 Eagle Point Rd",
    "sg:city":"Van Alstyne",
    "sg:classifiers":[
        {
            "category":"Building & Trades",
            "subcategory":"Construction",
            "type":"Services"
        }
    ],
    "sg:phone":"+1 903 482 5382",
    "sg:postcode":"75495",
    "sg:province":"TX",
    "sg:tags":[
        "new",
        "medical",
        "commercial"
    ],
    "wof:name":"J M Cooley Co Inc",
    "wof:placetype":"venue"
},
  "geometry": {"coordinates":[-96.610443,33.421631],"type":"Point"}
}