{
  "type": "Feature",
  "properties": {
    "iso:country":"US",
    "sg:address":"100 N Old Betsy Rd",
    "sg:city":"Keene",
    "sg:classifiers":[
        {
            "category":"Insurance",
            "subcategory":"Insurance Agent",
            "type":"Services"
        }
    ],
    "sg:phone":"+1 817 645 7272",
    "sg:postcode":"76059",
    "sg:province":"TX",
    "wof:name":"Harold Burton Agency",
    "wof:placetype":"venue"
},
  "geometry": {"coordinates":[-97.33065499999999,32.398092],"type":"Point"}
}