{
  "type": "Feature",
  "properties": {
    "iso:country":"US",
    "sg:address":"10484 W Cleburne Rd",
    "sg:city":"Crowley",
    "sg:classifiers":[
        {
            "category":"Recreation",
            "type":"Entertainment"
        }
    ],
    "sg:phone":"+1 817 297 1396",
    "sg:postcode":"76036",
    "sg:province":"TX",
    "wof:name":"Stony Meadows",
    "wof:placetype":"venue"
},
  "geometry": {"coordinates":[-97.40424400000001,32.587092],"type":"Point"}
}