{
  "type": "Feature",
  "properties": {
    "iso:country":"US",
    "sg:address":"1597 W Main St",
    "sg:city":"Lewisville",
    "sg:classifiers":[
        {
            "category":"Autos & Motor Vehicles",
            "subcategory":"Fuel & Gas Station",
            "type":"Retail Goods"
        }
    ],
    "sg:phone":"+1 972 221 9951",
    "sg:postcode":"75067",
    "sg:province":"TX",
    "sg:tags":[
        "oil"
    ],
    "wof:name":"Shell",
    "wof:placetype":"venue"
},
  "geometry": {"coordinates":[-97.035831,33.04244],"type":"Point"}
}