{
  "type": "Feature",
  "properties": {
    "iso:country":"US",
    "sg:address":"2610 Charter Oak Dr",
    "sg:city":"Temple",
    "sg:classifiers":[
        {
            "category":"Building & Trades",
            "subcategory":"Construction",
            "type":"Services"
        }
    ],
    "sg:phone":"+1 254 778 8096",
    "sg:postcode":"76502",
    "sg:province":"TX",
    "sg:tags":[
        "sandblasting",
        "contractor"
    ],
    "sg:website":"www.texblast.com",
    "wof:name":"Tex-Blast Sandblasting Company",
    "wof:placetype":"venue"
},
  "geometry": {"coordinates":[-97.413078,31.08217],"type":"Point"}
}