{
  "type": "Feature",
  "properties": {
    "iso:country":"US",
    "sg:address":"2100 Kramer Ln",
    "sg:city":"Austin",
    "sg:classifiers":[
        {
            "category":"Health Services",
            "subcategory":"Health Practitioner",
            "type":"Services"
        }
    ],
    "sg:phone":"+1 512 373 0959",
    "sg:postcode":"78758",
    "sg:province":"TX",
    "sg:tags":[
        "psychologist"
    ],
    "wof:name":"Common Sense Approach",
    "wof:placetype":"venue"
},
  "geometry": {"coordinates":[-97.713095,30.390099],"type":"Point"}
}