{
  "type": "Feature",
  "properties": {
    "iso:country":"US",
    "sg:address":"2617 Shalimar Dr",
    "sg:city":"Garland",
    "sg:classifiers":[
        {
            "category":"Building & Trades",
            "subcategory":"Construction",
            "type":"Services"
        }
    ],
    "sg:phone":"+1 972 414 3890",
    "sg:postcode":"75040",
    "sg:province":"TX",
    "sg:tags":[
        "general",
        "remodeling",
        "contractor"
    ],
    "wof:name":"Great Wstn Exterior Renovation",
    "wof:placetype":"venue"
},
  "geometry": {"coordinates":[-96.609955,32.937473],"type":"Point"}
}