{
  "type": "Feature",
  "properties": {
    "iso:country":"US",
    "sg:address":"1231 Alma St",
    "sg:city":"Tomball",
    "sg:classifiers":[
        {
            "category":"Restaurant",
            "type":"Food & Drink"
        }
    ],
    "sg:phone":"+1 281 255 2636",
    "sg:postcode":"77375",
    "sg:province":"TX",
    "sg:tags":[
        "eating"
    ],
    "wof:name":"Los Pinos Mexican Restaurant",
    "wof:placetype":"venue"
},
  "geometry": {"coordinates":[-95.62808800000001,30.090291],"type":"Point"}
}