{
  "type": "Feature",
  "properties": {
    "iso:country":"US",
    "sg:address":"7530 Park North Dr",
    "sg:city":"Beaumont",
    "sg:classifiers":[
        {
            "category":"Home & Garden",
            "subcategory":"Hardware",
            "type":"Retail Goods"
        }
    ],
    "sg:phone":"+1 409 892 1377",
    "sg:postcode":"77708",
    "sg:province":"TX",
    "wof:name":"Eastex Tools Inc",
    "wof:placetype":"venue"
},
  "geometry": {"coordinates":[-94.172881,30.147548],"type":"Point"}
}