{
  "type": "Feature",
  "properties": {
    "iso:country":"US",
    "sg:address":"1689 W Northwest Hwy",
    "sg:city":"Grapevine",
    "sg:classifiers":[
        {
            "category":"Wholesale",
            "subcategory":"Durable Goods & Equipment",
            "type":"Manufacturing & Wholesale Goods"
        }
    ],
    "sg:phone":"+1 817 251 8072",
    "sg:postcode":"76051",
    "sg:province":"TX",
    "sg:tags":[
        "exporter"
    ],
    "wof:name":"Carlos Galvan",
    "wof:placetype":"venue"
},
  "geometry": {"coordinates":[-97.092393,32.941031],"type":"Point"}
}