{
  "type": "Feature",
  "properties": {
    "iso:country":"US",
    "sg:address":"5807 Lookout Mountain Dr",
    "sg:city":"Austin",
    "sg:classifiers":[
        {
            "category":"Professional",
            "subcategory":"Management & Consulting",
            "type":"Services"
        }
    ],
    "sg:phone":"+1 512 323 9421",
    "sg:postcode":"78731",
    "sg:province":"TX",
    "wof:name":"Creativity Coaching",
    "wof:placetype":"venue"
},
  "geometry": {"coordinates":[-97.78152900000001,30.345307],"type":"Point"}
}