{
  "type": "Feature",
  "properties": {
    "iso:country":"US",
    "sg:address":"1505 W 44th St",
    "sg:city":"Austin",
    "sg:classifiers":[
        {
            "category":"Professional",
            "subcategory":"Lawyer & Legal Services",
            "type":"Services"
        }
    ],
    "sg:phone":"+1 512 476 7200",
    "sg:postcode":"78756",
    "sg:province":"TX",
    "sg:tags":[
        "information",
        "attorney",
        "referral",
        "plan"
    ],
    "wof:name":"Waterloo Litigation Support",
    "wof:placetype":"venue"
},
  "geometry": {"coordinates":[-97.743399,30.314438],"type":"Point"}
}