{
  "type": "Feature",
  "properties": {
    "iso:country":"US",
    "sg:address":"3131 Story Rd W",
    "sg:city":"Irving",
    "sg:classifiers":[
        {
            "category":"Manufacturing",
            "subcategory":"Aerospace",
            "type":"Manufacturing & Wholesale Goods"
        }
    ],
    "sg:phone":"+1 972 659 2600",
    "sg:postcode":"75038",
    "sg:province":"TX",
    "sg:tags":[
        "engine",
        "aircraft",
        "parts"
    ],
    "wof:name":"BAE Systems",
    "wof:placetype":"venue"
},
  "geometry": {"coordinates":[-96.987897,32.871466],"type":"Point"}
}