{
  "type": "Feature",
  "properties": {
    "iso:country":"US",
    "sg:address":"810 S Church St",
    "sg:city":"Georgetown",
    "sg:classifiers":[
        {
            "category":"Manufacturing",
            "subcategory":"Printing",
            "type":"Manufacturing & Wholesale Goods"
        }
    ],
    "sg:phone":"+1 512 863 7762",
    "sg:postcode":"78626",
    "sg:province":"TX",
    "sg:tags":[
        "publisher"
    ],
    "sg:website":"www.eurekah.com",
    "wof:name":"Landes Bioscience Inc",
    "wof:placetype":"venue"
},
  "geometry": {"coordinates":[-97.67611599999999,30.636525],"type":"Point"}
}