{
  "type": "Feature",
  "properties": {
    "iso:country":"US",
    "sg:address":"701 Calvin Dr",
    "sg:city":"Garland",
    "sg:classifiers":[
        {
            "category":"Building & Trades",
            "subcategory":"Construction",
            "type":"Services"
        }
    ],
    "sg:phone":"+1 972 271 9481",
    "sg:postcode":"75041",
    "sg:province":"TX",
    "sg:tags":[
        "concrete",
        "contractor"
    ],
    "wof:name":"Juan R Mojano",
    "wof:placetype":"venue"
},
  "geometry": {"coordinates":[-96.62217,32.885377],"type":"Point"}
}