{
  "type": "Feature",
  "properties": {
    "iso:country":"US",
    "sg:address":"804 Montclair Dr",
    "sg:city":"El Paso",
    "sg:classifiers":[
        {
            "category":"Professional",
            "subcategory":"Accounting & Tax Preparation",
            "type":"Services"
        }
    ],
    "sg:phone":"+1 915 584 1295",
    "sg:postcode":"79932",
    "sg:province":"TX",
    "sg:tags":[
        "return",
        "filing"
    ],
    "wof:name":"Fineline Accounting Svc",
    "wof:placetype":"venue"
},
  "geometry": {"coordinates":[-106.60231,31.854612],"type":"Point"}
}