{
  "type": "Feature",
  "properties": {
    "iso:country":"US",
    "sg:address":"712 San Antonio St",
    "sg:city":"Mason",
    "sg:classifiers":[
        {
            "category":"Retail",
            "subcategory":"Laundry & Dry Cleaning",
            "type":"Services"
        }
    ],
    "sg:phone":"+1 325 347 5265",
    "sg:postcode":"76856",
    "sg:province":"TX",
    "sg:tags":[
        "cleaners"
    ],
    "wof:name":"Cowboy Cleaners",
    "wof:placetype":"venue"
},
  "geometry": {"coordinates":[-99.219185,30.739962],"type":"Point"}
}