{
  "type": "Feature",
  "properties": {
    "iso:country":"US",
    "sg:address":"5965 Rosedale Dr",
    "sg:city":"Beaumont",
    "sg:classifiers":[
        {
            "category":"Social Services",
            "subcategory":"Child Care",
            "type":"Services"
        }
    ],
    "sg:phone":"+1 409 898 7292",
    "sg:postcode":"77706",
    "sg:province":"TX",
    "sg:tags":[
        "day"
    ],
    "wof:name":"Agapeland Learning Tree",
    "wof:placetype":"venue"
},
  "geometry": {"coordinates":[-94.16767,30.132582],"type":"Point"}
}