{
  "type": "Feature",
  "properties": {
    "iso:country":"US",
    "sg:address":"2017 Copper St",
    "sg:city":"Garland",
    "sg:classifiers":[
        {
            "category":"Manufacturing",
            "subcategory":"Apparel",
            "type":"Manufacturing & Wholesale Goods"
        }
    ],
    "sg:phone":"+1 972 272 9810",
    "sg:postcode":"75042",
    "sg:province":"TX",
    "sg:tags":[
        "dress",
        "mfg"
    ],
    "wof:name":"S Y Lee Inc",
    "wof:placetype":"venue"
},
  "geometry": {"coordinates":[-96.65883100000001,32.912263],"type":"Point"}
}