{
  "type": "Feature",
  "properties": {
    "iso:country":"US",
    "sg:address":"1100 107th St",
    "sg:city":"Arlington",
    "sg:classifiers":[
        {
            "category":"Building & Trades",
            "subcategory":"Construction",
            "type":"Services"
        }
    ],
    "sg:phone":"+1 817 640 3303",
    "sg:postcode":"76011",
    "sg:province":"TX",
    "sg:tags":[
        "contractor"
    ],
    "wof:name":"Roofing By Hollings Inc",
    "wof:placetype":"venue"
},
  "geometry": {"coordinates":[-97.05794299999999,32.764291],"type":"Point"}
}