{
  "type": "Feature",
  "properties": {
    "iso:country":"US",
    "sg:address":"2320 10th St",
    "sg:city":"Port Arthur",
    "sg:classifiers":[
        {
            "category":"Social Services",
            "subcategory":"Child Care",
            "type":"Services"
        }
    ],
    "sg:phone":"+1 409 985 5175",
    "sg:postcode":"77640",
    "sg:province":"TX",
    "sg:tags":[
        "day"
    ],
    "wof:name":"All My Angels Child Care",
    "wof:placetype":"venue"
},
  "geometry": {"coordinates":[-93.92624499999999,29.890194],"type":"Point"}
}