{
  "type": "Feature",
  "properties": {
    "iso:country":"US",
    "sg:address":"3706 Texas Ave S",
    "sg:city":"Bryan",
    "sg:classifiers":[
        {
            "category":"Retail",
            "subcategory":"Auto Repair",
            "type":"Services"
        }
    ],
    "sg:phone":"+1 979 846 1139",
    "sg:postcode":"77802",
    "sg:province":"TX",
    "sg:tags":[
        "general",
        "supply"
    ],
    "wof:name":"C & L Tire & Service Center",
    "wof:placetype":"venue"
},
  "geometry": {"coordinates":[-96.346428,30.637498],"type":"Point"}
}