{
  "type": "Feature",
  "properties": {
    "iso:country":"US",
    "sg:address":"642 Cantwell Ln",
    "sg:city":"Corpus Christi",
    "sg:classifiers":[
        {
            "category":"Building & Trades",
            "subcategory":"Construction",
            "type":"Services"
        }
    ],
    "sg:phone":"+1 361 887 2168",
    "sg:postcode":"78408",
    "sg:province":"TX",
    "sg:tags":[
        "house"
    ],
    "wof:name":"Jewel Home Builders Inc",
    "wof:placetype":"venue"
},
  "geometry": {"coordinates":[-97.44917599999999,27.795953],"type":"Point"}
}