{
  "type": "Feature",
  "properties": {
    "iso:country":"US",
    "sg:address":"209 E South St",
    "sg:city":"Alvin",
    "sg:classifiers":[
        {
            "category":"Professional",
            "subcategory":"Printing & Photocopies",
            "type":"Services"
        },
        {
            "category":"Manufacturing",
            "subcategory":"Paper Products",
            "type":"Manufacturing & Wholesale Goods"
        }
    ],
    "sg:phone":"+1 281 331 4105",
    "sg:postcode":"77511",
    "sg:province":"TX",
    "sg:tags":[
        "bookbinder",
        "services-commercial",
        "duplicating",
        "copying"
    ],
    "sg:website":"http://www.greeninkprintinginc.com",
    "wof:name":"Green Ink Printing",
    "wof:placetype":"venue"
},
  "geometry": {"coordinates":[-95.241632,29.40927],"type":"Point"}
}