{
  "type": "Feature",
  "properties": {
    "iso:country":"US",
    "sg:address":"1502 W 6th St",
    "sg:city":"Austin",
    "sg:classifiers":[
        {
            "category":"Personal",
            "subcategory":"Skin Care",
            "type":"Services"
        }
    ],
    "sg:phone":"+1 512 482 8338",
    "sg:postcode":"78703",
    "sg:province":"TX",
    "sg:website":"www.cheekyskin.com",
    "wof:name":"Cheeky Skin",
    "wof:placetype":"venue"
},
  "geometry": {"coordinates":[-97.761718,30.274682],"type":"Point"}
}