{
  "type": "Feature",
  "properties": {
    "iso:country":"US",
    "sg:address":"502 W 30th St",
    "sg:city":"Austin",
    "sg:classifiers":[
        {
            "category":"Real Estate",
            "subcategory":"Real Estate Services",
            "type":"Services"
        }
    ],
    "sg:phone":"+1 512 478 1000",
    "sg:postcode":"78705",
    "sg:province":"TX",
    "sg:website":"www.avignonrealty.com",
    "wof:name":"Avignon Realty",
    "wof:placetype":"venue"
},
  "geometry": {"coordinates":[-97.741387,30.296374],"type":"Point"}
}