{
  "type": "Feature",
  "properties": {
    "iso:country":"US",
    "sg:address":"2240 Texas Pkwy",
    "sg:city":"Missouri City",
    "sg:classifiers":[
        {
            "category":"Cinema",
            "subcategory":"Movie Rental",
            "type":"Entertainment"
        }
    ],
    "sg:phone":"+1 281 261 0960",
    "sg:postcode":"77489",
    "sg:province":"TX",
    "sg:tags":[
        "leasing",
        "video",
        "disc",
        "tape"
    ],
    "sg:website":"www.blockbuster.com",
    "wof:name":"Blockbuster Video",
    "wof:placetype":"venue"
},
  "geometry": {"coordinates":[-95.526794,29.595374],"type":"Point"}
}