{
  "type": "Feature",
  "properties": {
    "iso:country":"US",
    "sg:address":"20900 Derby Day Ave",
    "sg:city":"Pflugerville",
    "sg:classifiers":[
        {
            "category":"Manufacturing",
            "subcategory":"Tools & Machinery",
            "type":"Manufacturing & Wholesale Goods"
        }
    ],
    "sg:phone":"+1 512 252 9030",
    "sg:postcode":"78660",
    "sg:province":"TX",
    "sg:tags":[
        "computer",
        "storage",
        "devices"
    ],
    "wof:name":"Advanced Digital Information",
    "wof:placetype":"venue"
},
  "geometry": {"coordinates":[-97.576459,30.493347],"type":"Point"}
}