{
  "type": "Feature",
  "properties": {
    "iso:country":"US",
    "sg:address":"3928 Duck Creek Rd",
    "sg:city":"Sanger",
    "sg:classifiers":[
        {
            "category":"Manufacturing",
            "subcategory":"Glass & Minerals",
            "type":"Manufacturing & Wholesale Goods"
        }
    ],
    "sg:phone":"+1 940 458 3213",
    "sg:postcode":"76266",
    "sg:province":"TX",
    "sg:tags":[
        "ready",
        "concrete",
        "mfg"
    ],
    "wof:name":"James C Ready",
    "wof:placetype":"venue"
},
  "geometry": {"coordinates":[-97.191931,33.356859],"type":"Point"}
}