{
  "type": "Feature",
  "properties": {
    "iso:country":"US",
    "sg:address":"20105 Mashburn St",
    "sg:city":"Pflugerville",
    "sg:classifiers":[
        {
            "category":"Building & Trades",
            "subcategory":"Construction",
            "type":"Services"
        }
    ],
    "sg:phone":"+1 512 251 3536",
    "sg:postcode":"78660",
    "sg:province":"TX",
    "sg:tags":[
        "business",
        "contractor"
    ],
    "wof:name":"Austin Plastering Inc",
    "wof:placetype":"venue"
},
  "geometry": {"coordinates":[-97.58214,30.482819],"type":"Point"}
}