{
  "type": "Feature",
  "properties": {
    "iso:country":"US",
    "sg:address":"900 Jackson St",
    "sg:city":"Dallas",
    "sg:classifiers":[
        {
            "category":"Professional",
            "subcategory":"Lawyer & Legal Services",
            "type":"Services"
        }
    ],
    "sg:phone":"+1 214 712 9566",
    "sg:postcode":"75202",
    "sg:province":"TX",
    "wof:name":"Whitehurst Mary Evelyn atty",
    "wof:placetype":"venue"
},
  "geometry": {"coordinates":[-96.80344700000001,32.778061],"type":"Point"}
}