{
  "type": "Feature",
  "properties": {
    "iso:country":"US",
    "sg:address":"17317 el Camino Real",
    "sg:city":"Houston",
    "sg:classifiers":[
        {
            "category":"Wholesale",
            "subcategory":"Non-durable Goods",
            "type":"Manufacturing & Wholesale Goods"
        }
    ],
    "sg:phone":"+1 281 286 7553",
    "sg:postcode":"77062",
    "sg:province":"TX",
    "sg:tags":[
        "advertising",
        "specialty"
    ],
    "wof:name":"Houston Embroidery Works",
    "wof:placetype":"venue"
},
  "geometry": {"coordinates":[-95.11405499999999,29.551353],"type":"Point"}
}