{
  "type": "Feature",
  "properties": {
    "iso:country":"US",
    "sg:address":"2909 San Gabriel Ct",
    "sg:city":"Fort Worth",
    "sg:classifiers":[
        {
            "category":"Real Estate",
            "subcategory":"Real Estate Agent",
            "type":"Services"
        }
    ],
    "sg:phone":"+1 817 595 2616",
    "sg:postcode":"76118",
    "sg:province":"TX",
    "wof:name":"Case Dee Ann Etvir Gerald",
    "wof:placetype":"venue"
},
  "geometry": {"coordinates":[-97.19236100000001,32.801932],"type":"Point"}
}