{
  "type": "Feature",
  "properties": {
    "iso:country":"US",
    "sg:address":"5930 W Park Blvd",
    "sg:city":"Plano",
    "sg:classifiers":[
        {
            "category":"Sports & Exercise",
            "subcategory":"Gym",
            "type":"Entertainment"
        }
    ],
    "sg:phone":"+1 972 248 2777",
    "sg:postcode":"75093",
    "sg:province":"TX",
    "sg:tags":[
        "facility",
        "club",
        "gymnasium",
        "health",
        "fitness",
        "studio",
        "physical"
    ],
    "sg:website":"www.fitness-evolution.com",
    "wof:name":"Fitness Evolution",
    "wof:placetype":"venue"
},
  "geometry": {"coordinates":[-96.827212,33.027795],"type":"Point"}
}