{
  "type": "Feature",
  "properties": {
    "iso:country":"US",
    "sg:address":"6688 N Central Expy",
    "sg:city":"Dallas",
    "sg:classifiers":[
        {
            "category":"Professional",
            "subcategory":"Lawyer & Legal Services",
            "type":"Services"
        }
    ],
    "sg:phone":"+1 214 373 7788",
    "sg:postcode":"75206",
    "sg:province":"TX",
    "wof:name":"Barker Calvin A Jr",
    "wof:placetype":"venue"
},
  "geometry": {"coordinates":[-96.772102,32.8479],"type":"Point"}
}