{
  "type": "Feature",
  "properties": {
    "iso:country":"US",
    "sg:address":"2505 E Pearl St",
    "sg:city":"Odessa",
    "sg:classifiers":[
        {
            "category":"Manufacturing",
            "subcategory":"Tools & Machinery",
            "type":"Manufacturing & Wholesale Goods"
        }
    ],
    "sg:phone":"+1 432 333 9544",
    "sg:postcode":"79761",
    "sg:province":"TX",
    "sg:tags":[
        "control",
        "industrial",
        "relay"
    ],
    "wof:name":"Tectrol Inc",
    "wof:placetype":"venue"
},
  "geometry": {"coordinates":[-102.331051,31.86074],"type":"Point"}
}