{
  "type": "Feature",
  "properties": {
    "iso:country":"US",
    "sg:address":"4020 82nd St",
    "sg:city":"Lubbock",
    "sg:classifiers":[
        {
            "category":"Restaurant",
            "type":"Food & Drink"
        }
    ],
    "sg:menulink":"http://www.allmenus.com/tx/lubbock/165969-arbys/menu/",
    "sg:phone":"+1 806 797 9200",
    "sg:postcode":"79423",
    "sg:province":"TX",
    "sg:tags":[
        "burger",
        "american"
    ],
    "wof:name":"Arby's",
    "wof:placetype":"venue"
},
  "geometry": {"coordinates":[-101.900989,33.520141],"type":"Point"}
}