{
  "type": "Feature",
  "properties": {
    "iso:country":"US",
    "sg:address":"2700 Clearmeadow St",
    "sg:city":"Bedford",
    "sg:classifiers":[
        {
            "category":"Professional",
            "subcategory":"Business Services",
            "type":"Services"
        }
    ],
    "sg:phone":"+1 817 685 8621",
    "sg:postcode":"76021",
    "sg:province":"TX",
    "wof:name":"Fioravanti Co Inc",
    "wof:placetype":"venue"
},
  "geometry": {"coordinates":[-97.135001,32.850068],"type":"Point"}
}