{
  "type": "Feature",
  "properties": {
    "iso:country":"US",
    "sg:address":"11500 Metric Blvd Ste 420",
    "sg:city":"Austin",
    "sg:classifiers":[
        {
            "category":"Shopping",
            "subcategory":"Stationery & Office Supplies",
            "type":"Retail Goods"
        },
        {
            "category":"Wholesale",
            "subcategory":"Office Equipment",
            "type":"Manufacturing & Wholesale Goods"
        },
        {
            "category":"Manufacturing",
            "subcategory":"Motor Vehicles & Parts",
            "type":"Manufacturing & Wholesale Goods"
        },
        {
            "category":"Professional",
            "subcategory":"Computer Services",
            "type":"Services"
        }
    ],
    "sg:phone":"+1 512 834 9981",
    "sg:postcode":"78758",
    "sg:province":"TX",
    "sg:tags":[
        "repair",
        "fax",
        "register",
        "autographic",
        "machine",
        "equipment-service",
        "furniture"
    ],
    "wof:name":"Zeno Imaging",
    "wof:placetype":"venue"
},
  "geometry": {"coordinates":[-97.707317,30.393971],"type":"Point"}
}