{
  "type": "Feature",
  "properties": {
    "iso:country":"US",
    "sg:address":"1059 Lovers Ln",
    "sg:city":"Bastrop",
    "sg:classifiers":[
        {
            "category":"Recreation",
            "type":"Entertainment"
        }
    ],
    "sg:phone":"+1 512 303 2333",
    "sg:postcode":"78602",
    "sg:province":"TX",
    "sg:tags":[
        "amusement"
    ],
    "wof:name":"Ginnie's Baton Twirling",
    "wof:placetype":"venue"
},
  "geometry": {"coordinates":[-97.32799900000001,30.089827],"type":"Point"}
}