{
  "type": "Feature",
  "properties": {
    "iso:country":"US",
    "sg:address":"8653 Village of Fondren Dr",
    "sg:city":"Houston",
    "sg:classifiers":[
        {
            "category":"Retail",
            "subcategory":"Repair Shop",
            "type":"Services"
        }
    ],
    "sg:phone":"+1 713 541 3750",
    "sg:postcode":"77071",
    "sg:province":"TX",
    "sg:tags":[
        "tractor"
    ],
    "wof:name":"Ground Service/The Grasscutter",
    "wof:placetype":"venue"
},
  "geometry": {"coordinates":[-95.530145,29.6381],"type":"Point"}
}