{
  "type": "Feature",
  "properties": {
    "iso:country":"US",
    "sg:address":"1701 Paxton Dr",
    "sg:city":"Carrollton",
    "sg:classifiers":[
        {
            "category":"Communications",
            "subcategory":"Film & Video Production",
            "type":"Services"
        }
    ],
    "sg:phone":"+1 972 939 2866",
    "sg:postcode":"75007",
    "sg:province":"TX",
    "sg:tags":[
        "audio"
    ],
    "sg:website":"www.oncuestaging.com",
    "wof:name":"On Cue Staging",
    "wof:placetype":"venue"
},
  "geometry": {"coordinates":[-96.89169,33.00566],"type":"Point"}
}