{
  "type": "Feature",
  "properties": {
    "iso:country":"US",
    "sg:address":"515 S Saint Marys St",
    "sg:city":"San Antonio",
    "sg:classifiers":[
        {
            "category":"Insurance",
            "subcategory":"Insurance Agent",
            "type":"Services"
        }
    ],
    "sg:phone":"+1 210 226 9261",
    "sg:postcode":"78205",
    "sg:province":"TX",
    "sg:website":"www.texashermannsons.org",
    "wof:name":"Grand Lodge Hermann Sons",
    "wof:placetype":"venue"
},
  "geometry": {"coordinates":[-98.491044,29.420029],"type":"Point"}
}