{
  "type": "Feature",
  "properties": {
    "iso:country":"US",
    "sg:address":"633 Everhart Rd",
    "sg:city":"Corpus Christi",
    "sg:classifiers":[
        {
            "category":"Health Services",
            "subcategory":"Clinic",
            "type":"Services"
        }
    ],
    "sg:phone":"+1 361 980 1711",
    "sg:postcode":"78411",
    "sg:province":"TX",
    "wof:name":"Harbor Perfusion Inc",
    "wof:placetype":"venue"
},
  "geometry": {"coordinates":[-97.375224,27.729033],"type":"Point"}
}