{
  "type": "Feature",
  "properties": {
    "iso:country":"US",
    "sg:address":"5043 Cedar Springs Rd",
    "sg:city":"Dallas",
    "sg:classifiers":[
        {
            "category":"Professional",
            "type":"Services"
        }
    ],
    "sg:phone":"+1 214 559 0038",
    "sg:postcode":"75235",
    "sg:province":"TX",
    "wof:name":"Garden Accents",
    "wof:placetype":"venue"
},
  "geometry": {"coordinates":[-96.82301699999999,32.820881],"type":"Point"}
}