{
  "type": "Feature",
  "properties": {
    "iso:country":"US",
    "sg:address":"14513 Amy Francis St",
    "sg:city":"Austin",
    "sg:classifiers":[
        {
            "category":"Professional",
            "subcategory":"Business Services",
            "type":"Services"
        },
        {
            "category":"Shopping",
            "subcategory":"Gifts & Souvenirs",
            "type":"Retail Goods"
        }
    ],
    "sg:phone":"+1 512 276 9258",
    "sg:postcode":"78725",
    "sg:province":"TX",
    "sg:tags":[
        "party",
        "supply"
    ],
    "wof:name":"Jumpinjohns Bouncies Moonwalk",
    "wof:placetype":"venue"
},
  "geometry": {"coordinates":[-97.58989800000001,30.231422],"type":"Point"}
}