{
  "type": "Feature",
  "properties": {
    "iso:country":"US",
    "sg:address":"6075 Dooley Dr",
    "sg:city":"Lewisville",
    "sg:classifiers":[
        {
            "category":"Recreation",
            "type":"Entertainment"
        }
    ],
    "sg:phone":"+1 972 489 6483",
    "sg:postcode":"75056",
    "sg:province":"TX",
    "wof:name":"Comselect",
    "wof:placetype":"venue"
},
  "geometry": {"coordinates":[-96.857292,33.10584],"type":"Point"}
}