{
  "type": "Feature",
  "properties": {
    "iso:country":"US",
    "sg:address":"811 N Main St",
    "sg:city":"Highlands",
    "sg:classifiers":[
        {
            "category":"Retail",
            "subcategory":"Repair Shop",
            "type":"Services"
        }
    ],
    "sg:phone":"+1 281 426 8498",
    "sg:postcode":"77562",
    "sg:province":"TX",
    "wof:name":"Control Company",
    "wof:placetype":"venue"
},
  "geometry": {"coordinates":[-95.057399,29.826631],"type":"Point"}
}