{
  "type": "Feature",
  "properties": {
    "iso:country":"US",
    "sg:address":"2620 Willowbrook Rd",
    "sg:city":"Dallas",
    "sg:classifiers":[
        {
            "category":"Home & Garden",
            "subcategory":"Home Furnishings",
            "type":"Retail Goods"
        },
        {
            "category":"Manufacturing",
            "subcategory":"Glass & Minerals",
            "type":"Manufacturing & Wholesale Goods"
        },
        {
            "category":"Manufacturing",
            "subcategory":"Building Materials",
            "type":"Manufacturing & Wholesale Goods"
        }
    ],
    "sg:phone":"+1 214 306 6110",
    "sg:postcode":"75220",
    "sg:province":"TX",
    "sg:tags":[
        "ornamental",
        "door",
        "plate",
        "glass-auto",
        "shower",
        "window",
        "carved",
        "mirror",
        "glass-beveled",
        "etched",
        "repair",
        "enclosure",
        "replacement"
    ],
    "sg:website":"http://www.inwoodglass.com",
    "wof:name":"Inwood Glass & Mirror",
    "wof:placetype":"venue"
},
  "geometry": {"coordinates":[-96.884478,32.861581],"type":"Point"}
}