{
  "type": "Feature",
  "properties": {
    "iso:country":"US",
    "sg:address":"405 Slide Rd",
    "sg:city":"Lubbock",
    "sg:classifiers":[
        {
            "category":"Professional",
            "subcategory":"Employment Agencies",
            "type":"Services"
        }
    ],
    "sg:phone":"+1 806 783 8740",
    "sg:postcode":"79416",
    "sg:province":"TX",
    "sg:tags":[
        "opportunity"
    ],
    "wof:name":"Adecco",
    "wof:placetype":"venue"
},
  "geometry": {"coordinates":[-101.922364,33.590647],"type":"Point"}
}