{
  "type": "Feature",
  "properties": {
    "iso:country":"US",
    "sg:address":"410 W Orange Ave",
    "sg:city":"Orange Grove",
    "sg:classifiers":[
        {
            "category":"Retail",
            "subcategory":"Photofinishing",
            "type":"Services"
        }
    ],
    "sg:phone":"+1 361 384 0810",
    "sg:postcode":"78372",
    "sg:province":"TX",
    "sg:tags":[
        "photo",
        "processing",
        "digital"
    ],
    "wof:name":"Sister's Photo Pntng & Plsrs",
    "wof:placetype":"venue"
},
  "geometry": {"coordinates":[-97.93973099999999,27.958343],"type":"Point"}
}