{
  "type": "Feature",
  "properties": {
    "iso:country":"US",
    "sg:address":"3404 Rankin St",
    "sg:city":"Dallas",
    "sg:classifiers":[
        {
            "category":"Shopping",
            "subcategory":"Clothing, Apparel, & Fashions",
            "type":"Retail Goods"
        }
    ],
    "sg:phone":"+1 214 750 1202",
    "sg:postcode":"75205",
    "sg:province":"TX",
    "sg:tags":[
        "alteration"
    ],
    "wof:name":"O K Alterations",
    "wof:placetype":"venue"
},
  "geometry": {"coordinates":[-96.78689199999999,32.849345],"type":"Point"}
}