{
  "type": "Feature",
  "properties": {
    "iso:country":"US",
    "sg:address":"5944 Luther Ln",
    "sg:city":"Dallas",
    "sg:classifiers":[
        {
            "category":"Professional",
            "subcategory":"Accounting & Tax Preparation",
            "type":"Services"
        }
    ],
    "sg:phone":"+1 214 692 5878",
    "sg:postcode":"75225",
    "sg:province":"TX",
    "sg:tags":[
        "accountant"
    ],
    "wof:name":"Masters Albert PC",
    "wof:placetype":"venue"
},
  "geometry": {"coordinates":[-96.810204,32.863602],"type":"Point"}
}