{
  "type": "Feature",
  "properties": {
    "iso:country":"US",
    "sg:address":"11612 Chimney Rock Rd",
    "sg:city":"Houston",
    "sg:classifiers":[
        {
            "category":"Retail",
            "subcategory":"Auto Repair",
            "type":"Services"
        }
    ],
    "sg:phone":"+1 713 723 8994",
    "sg:postcode":"77035",
    "sg:province":"TX",
    "wof:name":"Angel Car Care",
    "wof:placetype":"venue"
},
  "geometry": {"coordinates":[-95.480598,29.6535],"type":"Point"}
}