{
  "type": "Feature",
  "properties": {
    "iso:country":"US",
    "sg:address":"800 E Central Pkwy",
    "sg:city":"Plano",
    "sg:classifiers":[
        {
            "category":"Real Estate",
            "subcategory":"Architect",
            "type":"Services"
        }
    ],
    "sg:phone":"+1 972 423 4500",
    "sg:postcode":"75074",
    "sg:province":"TX",
    "sg:tags":[
        "home",
        "planning",
        "design"
    ],
    "wof:name":"Korel Home Designs",
    "wof:placetype":"venue"
},
  "geometry": {"coordinates":[-96.70512600000001,33.028064],"type":"Point"}
}