{
  "type": "Feature",
  "properties": {
    "iso:country":"US",
    "sg:address":"2325 Live Oak Cir",
    "sg:city":"Granbury",
    "sg:classifiers":[
        {
            "category":"Real Estate",
            "subcategory":"Real Estate Operator",
            "type":"Services"
        }
    ],
    "sg:phone":"+1 817 579 8965",
    "sg:postcode":"76048",
    "sg:province":"TX",
    "sg:tags":[
        "property",
        "lessor"
    ],
    "wof:name":"Couch Realty",
    "wof:placetype":"venue"
},
  "geometry": {"coordinates":[-97.790164,32.474009],"type":"Point"}
}