{
  "type": "Feature",
  "properties": {
    "iso:country":"US",
    "sg:address":"117 Ward Rd",
    "sg:city":"Baytown",
    "sg:classifiers":[
        {
            "category":"Shopping",
            "subcategory":"Crafts & Fabrics",
            "type":"Retail Goods"
        }
    ],
    "sg:phone":"+1 281 422 4341",
    "sg:postcode":"77520",
    "sg:province":"TX",
    "sg:tags":[
        "sewing"
    ],
    "wof:name":"Rocking Chair",
    "wof:placetype":"venue"
},
  "geometry": {"coordinates":[-94.963359,29.74248],"type":"Point"}
}