{
  "type": "Feature",
  "properties": {
    "iso:country":"US",
    "sg:address":"1111 Frankford Rd W",
    "sg:city":"Carrollton",
    "sg:classifiers":[
        {
            "category":"Banks & Credit Unions",
            "subcategory":"Bank",
            "type":"Services"
        }
    ],
    "sg:phone":"+1 972 820 7343",
    "sg:postcode":"75007",
    "sg:province":"TX",
    "sg:tags":[
        "loan",
        "real estate"
    ],
    "wof:name":"First Wholesale Mortgage",
    "wof:placetype":"venue"
},
  "geometry": {"coordinates":[-96.91241599999999,32.997639],"type":"Point"}
}