{
  "type": "Feature",
  "properties": {
    "iso:country":"US",
    "sg:address":"602 Santa Maria St",
    "sg:city":"Sugar Land",
    "sg:classifiers":[
        {
            "category":"Real Estate",
            "subcategory":"Real Estate Agent",
            "type":"Services"
        }
    ],
    "sg:phone":"+1 281 494 0727",
    "sg:postcode":"77478",
    "sg:province":"TX",
    "wof:name":"Janet G Schenck",
    "wof:placetype":"venue"
},
  "geometry": {"coordinates":[-95.624718,29.617866],"type":"Point"}
}