{
  "type": "Feature",
  "properties": {
    "iso:country":"US",
    "sg:address":"1241 Post Oak Trl",
    "sg:city":"Grapevine",
    "sg:classifiers":[
        {
            "category":"Building & Trades",
            "subcategory":"Electrical",
            "type":"Services"
        },
        {
            "category":"Wholesale",
            "subcategory":"Electrical",
            "type":"Manufacturing & Wholesale Goods"
        }
    ],
    "sg:phone":"+1 817 481 5033",
    "sg:postcode":"76092",
    "sg:province":"TX",
    "sg:tags":[
        "control",
        "security",
        "system",
        "contractor"
    ],
    "wof:name":"All Safe & Sound",
    "wof:placetype":"venue"
},
  "geometry": {"coordinates":[-97.170857,32.959561],"type":"Point"}
}