{
  "type": "Feature",
  "properties": {
    "iso:country":"US",
    "sg:address":"510 Lake View Dr",
    "sg:city":"Montgomery",
    "sg:classifiers":[
        {
            "category":"Building & Trades",
            "subcategory":"Construction",
            "type":"Services"
        }
    ],
    "sg:phone":"+1 936 582 6549",
    "sg:postcode":"77356",
    "sg:province":"TX",
    "sg:tags":[
        "carpentry",
        "contractor"
    ],
    "wof:name":"GM Carpentry Inc",
    "wof:placetype":"venue"
},
  "geometry": {"coordinates":[-95.640379,30.382926],"type":"Point"}
}