{
  "type": "Feature",
  "properties": {
    "iso:country":"US",
    "sg:address":"1915 E 12th St",
    "sg:city":"Austin",
    "sg:classifiers":[
        {
            "category":"Personal",
            "subcategory":"Barber",
            "type":"Services"
        }
    ],
    "sg:phone":"+1 512 472 0302",
    "sg:postcode":"78702",
    "sg:province":"TX",
    "sg:tags":[
        "shop"
    ],
    "sg:website":"www.marshallsonline.com",
    "wof:name":"Marshall's Barber Shop",
    "wof:placetype":"venue"
},
  "geometry": {"coordinates":[-97.71929900000001,30.274],"type":"Point"}
}