{
  "type": "Feature",
  "properties": {
    "iso:country":"US",
    "sg:address":"2727 Medill St",
    "sg:city":"Dallas",
    "sg:classifiers":[
        {
            "category":"Building & Trades",
            "subcategory":"Plumbing",
            "type":"Services"
        }
    ],
    "sg:phone":"+1 214 421 4525",
    "sg:postcode":"75215",
    "sg:province":"TX",
    "sg:tags":[
        "contractor"
    ],
    "wof:name":"Wayne Repair Air Condition",
    "wof:placetype":"venue"
},
  "geometry": {"coordinates":[-96.76553199999999,32.773762],"type":"Point"}
}