{
  "type": "Feature",
  "properties": {
    "iso:country":"US",
    "sg:address":"1036 S Fort Hood St",
    "sg:city":"Killeen",
    "sg:classifiers":[
        {
            "category":"Travel",
            "subcategory":"Travel Agent",
            "type":"Entertainment"
        }
    ],
    "sg:phone":"+1 254 634 3171",
    "sg:postcode":"76541",
    "sg:province":"TX",
    "sg:tags":[
        "agency",
        "bureau"
    ],
    "wof:name":"Great Escapes Travel Svc",
    "wof:placetype":"venue"
},
  "geometry": {"coordinates":[-97.74615900000001,31.112525],"type":"Point"}
}