{
  "type": "Feature",
  "properties": {
    "iso:country":"US",
    "sg:address":"3 Crescent Pl",
    "sg:city":"Lubbock",
    "sg:classifiers":[
        {
            "category":"Real Estate",
            "subcategory":"Architect",
            "type":"Services"
        }
    ],
    "sg:phone":"+1 806 799 6649",
    "sg:postcode":"79416",
    "sg:province":"TX",
    "sg:tags":[
        "architectural"
    ],
    "wof:name":"Powell Raymond D",
    "wof:placetype":"venue"
},
  "geometry": {"coordinates":[-101.92156199999999,33.593223],"type":"Point"}
}