{
  "type": "Feature",
  "properties": {
    "iso:country":"US",
    "sg:address":"200 Berkshire Ln",
    "sg:city":"Fort Worth",
    "sg:classifiers":[
        {
            "category":"Professional",
            "subcategory":"Engineering",
            "type":"Services"
        }
    ],
    "sg:phone":"+1 817 706 2526",
    "sg:postcode":"76134",
    "sg:province":"TX",
    "wof:name":"Mzr Enterprises",
    "wof:placetype":"venue"
},
  "geometry": {"coordinates":[-97.327012,32.646724],"type":"Point"}
}