{
  "type": "Feature",
  "properties": {
    "iso:country":"US",
    "sg:address":"2410 S 4th St",
    "sg:city":"Beaumont",
    "sg:classifiers":[
        {
            "category":"Autos & Motor Vehicles",
            "subcategory":"Automobile Sales",
            "type":"Retail Goods"
        }
    ],
    "sg:phone":"+1 409 838 9077",
    "sg:postcode":"77701",
    "sg:province":"TX",
    "sg:tags":[
        "car",
        "dealer"
    ],
    "wof:name":"Fourth Street Used Auto Sales",
    "wof:placetype":"venue"
},
  "geometry": {"coordinates":[-94.115728,30.063527],"type":"Point"}
}