{
  "type": "Feature",
  "properties": {
    "iso:country":"US",
    "sg:address":"915 Century Plaza Dr",
    "sg:city":"Houston",
    "sg:classifiers":[
        {
            "category":"Home & Garden",
            "subcategory":"Building Materials",
            "type":"Retail Goods"
        }
    ],
    "sg:phone":"+1 281 209 9942",
    "sg:postcode":"77073",
    "sg:province":"TX",
    "sg:tags":[
        "center"
    ],
    "wof:name":"Fleetwood Home Ctr",
    "wof:placetype":"venue"
},
  "geometry": {"coordinates":[-95.40839800000001,29.986669],"type":"Point"}
}