{
  "type": "Feature",
  "properties": {
    "iso:country":"US",
    "sg:address":"340 Dallas St",
    "sg:city":"Houston",
    "sg:phone":"+1 713 652 0700",
    "sg:postcode":"77002",
    "sg:province":"TX",
    "sg:website":"http://www.thedowntownclub.com",
    "wof:name":"Downtown Club",
    "wof:placetype":"venue"
},
  "geometry": {"coordinates":[-95.372561,29.757832],"type":"Point"}
}