{
  "type": "Feature",
  "properties": {
    "iso:country":"US",
    "sg:address":"3404 Westhaven Dr",
    "sg:city":"Amarillo",
    "sg:classifiers":[
        {
            "category":"Food & Beverages",
            "subcategory":"Meat & Fish",
            "type":"Retail Goods"
        }
    ],
    "sg:phone":"+1 806 353 4267",
    "sg:postcode":"79109",
    "sg:province":"TX",
    "wof:name":"Texas Country Hams",
    "wof:placetype":"venue"
},
  "geometry": {"coordinates":[-101.877467,35.180459],"type":"Point"}
}