{
  "type": "Feature",
  "properties": {
    "iso:country":"US",
    "sg:address":"3101 Bee Caves Rd",
    "sg:city":"Austin",
    "sg:classifiers":[
        {
            "category":"Professional",
            "subcategory":"Lawyer & Legal Services",
            "type":"Services"
        }
    ],
    "sg:phone":"+1 512 634 1980",
    "sg:postcode":"78746",
    "sg:province":"TX",
    "sg:tags":[
        "information",
        "attorney",
        "referral"
    ],
    "sg:website":"http://www.esquiresolutions.com/Deposition-Solutions/",
    "wof:name":"Esquire Deposition Svc",
    "wof:placetype":"venue"
},
  "geometry": {"coordinates":[-97.796623,30.2717],"type":"Point"}
}