{
  "type": "Feature",
  "properties": {
    "iso:country":"US",
    "sg:address":"728 E 12th St",
    "sg:city":"Littlefield",
    "sg:classifiers":[
        {
            "category":"Home & Garden",
            "subcategory":"Garden Supply",
            "type":"Retail Goods"
        }
    ],
    "sg:phone":"+1 806 385 3870",
    "sg:postcode":"79339",
    "sg:province":"TX",
    "sg:tags":[
        "center"
    ],
    "wof:name":"Macha Garden & Supply",
    "wof:placetype":"venue"
},
  "geometry": {"coordinates":[-102.327575,33.915304],"type":"Point"}
}