{
  "type": "Feature",
  "properties": {
    "iso:country":"US",
    "sg:address":"400 E Pecan Blvd",
    "sg:city":"Mcallen",
    "sg:classifiers":[
        {
            "category":"Home & Garden",
            "subcategory":"Building Materials",
            "type":"Retail Goods"
        }
    ],
    "sg:phone":"+1 956 682 2892",
    "sg:postcode":"78501",
    "sg:province":"TX",
    "wof:name":"Glass Doctor",
    "wof:placetype":"venue"
},
  "geometry": {"coordinates":[-98.211664,26.215732],"type":"Point"}
}