{
  "type": "Feature",
  "properties": {
    "iso:country":"US",
    "sg:address":"5409 N Jim Miller Rd",
    "sg:city":"Dallas",
    "sg:classifiers":[
        {
            "category":"Education",
            "subcategory":"Special Training",
            "type":"Public Place"
        }
    ],
    "sg:phone":"+1 214 320 2573",
    "sg:postcode":"75227",
    "sg:province":"TX",
    "wof:name":"Danneker Med Creer Trining Ctr",
    "wof:placetype":"venue"
},
  "geometry": {"coordinates":[-96.70020599999999,32.789375],"type":"Point"}
}