{
  "type": "Feature",
  "properties": {
    "iso:country":"US",
    "sg:address":"7325 Paul Calle Dr",
    "sg:city":"Plano",
    "sg:classifiers":[
        {
            "category":"Education",
            "subcategory":"Special Training",
            "type":"Public Place"
        },
        {
            "category":"Education",
            "subcategory":"Vocational School",
            "type":"Public Place"
        }
    ],
    "sg:phone":"+1 972 618 1880",
    "sg:postcode":"75025",
    "sg:province":"TX",
    "sg:tags":[
        "technical",
        "educational",
        "industrial",
        "business",
        "trade"
    ],
    "sg:website":"http://www.the-sales-company.com",
    "wof:name":"Mrazek Sales Co",
    "wof:placetype":"venue"
},
  "geometry": {"coordinates":[-96.75950899999999,33.076694],"type":"Point"}
}