{
  "type": "Feature",
  "properties": {
    "iso:country":"US",
    "sg:address":"1614 Highway 59 N",
    "sg:city":"Bowie",
    "sg:classifiers":[
        {
            "category":"Wholesale",
            "subcategory":"Hardware",
            "type":"Manufacturing & Wholesale Goods"
        },
        {
            "category":"Home & Garden",
            "subcategory":"Garden Supply",
            "type":"Retail Goods"
        },
        {
            "category":"Retail",
            "subcategory":"Repair Shop",
            "type":"Services"
        }
    ],
    "sg:phone":"+1 940 872 2322",
    "sg:postcode":"76230",
    "sg:province":"TX",
    "sg:tags":[
        "renting",
        "lawn",
        "outdoor",
        "power",
        "landscaping",
        "equipment-sales",
        "equipment",
        "saw"
    ],
    "sg:website":"http://www.stihldealer.net/default-dealer-001043.aspx",
    "wof:name":"White's Magneto & Supply",
    "wof:placetype":"venue"
},
  "geometry": {"coordinates":[-97.830231,33.56871],"type":"Point"}
}