{
  "type": "Feature",
  "properties": {
    "iso:country":"US",
    "sg:address":"329 Oaks Trl",
    "sg:city":"Garland",
    "sg:classifiers":[
        {
            "category":"Shopping",
            "subcategory":"Computers & Home Electronics",
            "type":"Retail Goods"
        },
        {
            "category":"Professional",
            "subcategory":"Computer Services",
            "type":"Services"
        }
    ],
    "sg:phone":"+1 972 203 3400",
    "sg:postcode":"75043",
    "sg:province":"TX",
    "sg:tags":[
        "equipment",
        "dealer",
        "related"
    ],
    "sg:website":"www.psullivanco.com",
    "wof:name":"C M C Network Solutions",
    "wof:placetype":"venue"
},
  "geometry": {"coordinates":[-96.571596,32.847905],"type":"Point"}
}