{
  "type": "Feature",
  "properties": {
    "iso:country":"US",
    "sg:address":"2728 Culebra Rd",
    "sg:city":"San Antonio",
    "sg:classifiers":[
        {
            "category":"Autos & Motor Vehicles",
            "subcategory":"Automobile Sales",
            "type":"Retail Goods"
        }
    ],
    "sg:phone":"+1 210 436 9650",
    "sg:postcode":"78228",
    "sg:province":"TX",
    "sg:tags":[
        "car",
        "dealer"
    ],
    "wof:name":"Texas State Auto",
    "wof:placetype":"venue"
},
  "geometry": {"coordinates":[-98.55306,29.447796],"type":"Point"}
}