{
  "type": "Feature",
  "properties": {
    "iso:country":"US",
    "sg:address":"13355 Noel Rd",
    "sg:city":"Dallas",
    "sg:classifiers":[
        {
            "category":"Professional",
            "subcategory":"Lawyer & Legal Services",
            "type":"Services"
        }
    ],
    "sg:phone":"+1 972 702 7035",
    "sg:postcode":"75240",
    "sg:province":"TX",
    "wof:name":"Asset Prtction Legal Group LLP",
    "wof:placetype":"venue"
},
  "geometry": {"coordinates":[-96.81811999999999,32.929623],"type":"Point"}
}