{
  "type": "Feature",
  "properties": {
    "iso:country":"US",
    "sg:address":"7424 FM 1488",
    "sg:city":"Magnolia",
    "sg:classifiers":[
        {
            "category":"Real Estate",
            "subcategory":"Surveying",
            "type":"Services"
        }
    ],
    "sg:phone":"+1 281 356 6908",
    "sg:postcode":"77384",
    "sg:province":"TX",
    "sg:tags":[
        "surveyor"
    ],
    "wof:name":"Geomatics",
    "wof:placetype":"venue"
},
  "geometry": {"coordinates":[-95.50680199999999,30.230388],"type":"Point"}
}