{
  "type": "Feature",
  "properties": {
    "iso:country":"US",
    "sg:address":"341 Yorktown Blvd",
    "sg:city":"Corpus Christi",
    "sg:classifiers":[
        {
            "category":"Food & Beverages",
            "subcategory":"Groceries & Convenience Stores",
            "type":"Retail Goods"
        }
    ],
    "sg:phone":"+1 361 939 9506",
    "sg:postcode":"78418",
    "sg:province":"TX",
    "wof:name":"Bayside Grocery",
    "wof:placetype":"venue"
},
  "geometry": {"coordinates":[-97.3053,27.621459],"type":"Point"}
}