{
  "type": "Feature",
  "properties": {
    "iso:country":"US",
    "sg:address":"300 Hurst St",
    "sg:city":"Center",
    "sg:classifiers":[
        {
            "category":"Wholesale",
            "subcategory":"Medical Equipment & Supplies",
            "type":"Manufacturing & Wholesale Goods"
        },
        {
            "category":"Health Services",
            "subcategory":"Hospital",
            "type":"Services"
        },
        {
            "category":"Shopping",
            "subcategory":"Pharmacy",
            "type":"Retail Goods"
        }
    ],
    "sg:phone":"+1 936 590 4464",
    "sg:postcode":"75935",
    "sg:province":"TX",
    "sg:tags":[
        "home",
        "oxygen",
        "care"
    ],
    "wof:name":"Gaddy's Medical Equipment & Supplies",
    "wof:placetype":"venue"
},
  "geometry": {"coordinates":[-94.187721,31.791941],"type":"Point"}
}