{
  "type": "Feature",
  "properties": {
    "iso:country":"US",
    "sg:address":"1901 S Westmoreland Rd",
    "sg:city":"Red Oak",
    "sg:classifiers":[
        {
            "category":"Professional",
            "type":"Services"
        }
    ],
    "sg:phone":"+1 972 230 7728",
    "sg:postcode":"75154",
    "sg:province":"TX",
    "wof:name":"RTW Drives & Control",
    "wof:placetype":"venue"
},
  "geometry": {"coordinates":[-96.87409599999999,32.558894],"type":"Point"}
}