{
  "type": "Feature",
  "properties": {
    "iso:country":"US",
    "sg:address":"783 Antoine Dr",
    "sg:city":"Plano",
    "sg:classifiers":[
        {
            "category":"Professional",
            "subcategory":"Business Services",
            "type":"Services"
        }
    ],
    "sg:phone":"+1 972 424 8169",
    "sg:postcode":"75023",
    "sg:province":"TX",
    "sg:tags":[
        "holding"
    ],
    "wof:name":"Gatwin Holdings",
    "wof:placetype":"venue"
},
  "geometry": {"coordinates":[-96.708771,33.046139],"type":"Point"}
}