{
  "type": "Feature",
  "properties": {
    "iso:country":"US",
    "sg:address":"4426 Brookston St",
    "sg:city":"Houston",
    "sg:classifiers":[
        {
            "category":"Bars & Pubs",
            "type":"Food & Drink"
        }
    ],
    "sg:phone":"+1 713 726 8550",
    "sg:postcode":"77045",
    "sg:province":"TX",
    "sg:tags":[
        "drinking",
        "nightlife"
    ],
    "wof:name":"Club L J",
    "wof:placetype":"venue"
},
  "geometry": {"coordinates":[-95.445198,29.6366],"type":"Point"}
}