{
  "type": "Feature",
  "properties": {
    "iso:country":"US",
    "sg:address":"7911 Ferguson Rd",
    "sg:city":"Dallas",
    "sg:classifiers":[
        {
            "category":"Shopping",
            "subcategory":"Computers & Home Electronics",
            "type":"Retail Goods"
        }
    ],
    "sg:phone":"+1 214 324 1132",
    "sg:postcode":"75228",
    "sg:province":"TX",
    "wof:name":"Tuell Freeman Speaker Repair Service",
    "wof:placetype":"venue"
},
  "geometry": {"coordinates":[-96.7145,32.801601],"type":"Point"}
}