{
  "type": "Feature",
  "properties": {
    "iso:country":"US",
    "sg:address":"3705 Ranch Road 620 N",
    "sg:city":"Austin",
    "sg:classifiers":[
        {
            "category":"Food & Beverages",
            "subcategory":"Liquor & Beverages",
            "type":"Retail Goods"
        },
        {
            "category":"Wholesale",
            "subcategory":"Wine & Distilled Alcoholic Beverages",
            "type":"Manufacturing & Wholesale Goods"
        }
    ],
    "sg:phone":"+1 512 266 4640",
    "sg:postcode":"78734",
    "sg:province":"TX",
    "sg:tags":[
        "broker",
        "store"
    ],
    "wof:name":"Cool Beer & Wine",
    "wof:placetype":"venue"
},
  "geometry": {"coordinates":[-97.92728099999999,30.397399],"type":"Point"}
}