{
  "type": "Feature",
  "properties": {
    "iso:country":"US",
    "sg:address":"24950 Spring Ridge Dr",
    "sg:city":"Spring",
    "sg:classifiers":[
        {
            "category":"Real Estate",
            "subcategory":"Real Estate Agent",
            "type":"Services"
        }
    ],
    "sg:phone":"+1 281 362 8220",
    "sg:postcode":"77386",
    "sg:province":"TX",
    "wof:name":"American Appraisal Associates",
    "wof:placetype":"venue"
},
  "geometry": {"coordinates":[-95.43831299999999,30.125447],"type":"Point"}
}