{
  "type": "Feature",
  "properties": {
    "iso:country":"US",
    "sg:address":"207 N 3rd St",
    "sg:city":"Kingsville",
    "sg:classifiers":[
        {
            "category":"Education",
            "subcategory":"School",
            "type":"Public Place"
        }
    ],
    "sg:phone":"+1 361 592 3387",
    "sg:postcode":"78363",
    "sg:province":"TX",
    "wof:name":"Isd Receiving",
    "wof:placetype":"venue"
},
  "geometry": {"coordinates":[-97.87206500000001,27.517741],"type":"Point"}
}