{
  "type": "Feature",
  "properties": {
    "iso:country":"US",
    "sg:address":"400 S Zang Blvd",
    "sg:city":"Dallas",
    "sg:classifiers":[
        {
            "category":"Shopping",
            "subcategory":"News",
            "type":"Retail Goods"
        },
        {
            "category":"Professional",
            "type":"Services"
        }
    ],
    "sg:phone":"+1 214 948 7690",
    "sg:postcode":"75208",
    "sg:province":"TX",
    "sg:tags":[
        "food",
        "concession",
        "beverage",
        "establishment",
        "gift"
    ],
    "wof:name":"Accommodations Inc",
    "wof:placetype":"venue"
},
  "geometry": {"coordinates":[-96.824637,32.741327],"type":"Point"}
}