{
  "type": "Feature",
  "properties": {
    "iso:country":"US",
    "sg:address":"708 Pennsylvania Ave",
    "sg:city":"Fort Worth",
    "sg:classifiers":[
        {
            "category":"Shopping",
            "subcategory":"Pharmacy",
            "type":"Retail Goods"
        }
    ],
    "sg:phone":"+1 817 877 3677",
    "sg:postcode":"76104",
    "sg:province":"TX",
    "sg:tags":[
        "drugstore"
    ],
    "wof:name":"Halls Pharmacy Incorporated",
    "wof:placetype":"venue"
},
  "geometry": {"coordinates":[-97.332587,32.738532],"type":"Point"}
}