{
  "type": "Feature",
  "properties": {
    "iso:country":"US",
    "sg:address":"5601 Brodie Ln",
    "sg:city":"Sunset Valley",
    "sg:classifiers":[
        {
            "category":"Professional",
            "type":"Services"
        }
    ],
    "sg:phone":"+1 512 892 7921",
    "sg:postcode":"78745",
    "sg:province":"TX",
    "sg:tags":[
        "establishment"
    ],
    "wof:name":"Oldnavy",
    "wof:placetype":"venue"
},
  "geometry": {"coordinates":[-97.821442,30.227695],"type":"Point"}
}