{
  "type": "Feature",
  "properties": {
    "iso:country":"US",
    "sg:address":"309 N Wall St",
    "sg:city":"Iowa Park",
    "sg:classifiers":[
        {
            "category":"Shopping",
            "subcategory":"Florist",
            "type":"Retail Goods"
        }
    ],
    "sg:phone":"+1 940 592 2493",
    "sg:postcode":"76367",
    "sg:province":"TX",
    "wof:name":"Sincerely Yours",
    "wof:placetype":"venue"
},
  "geometry": {"coordinates":[-98.667823,33.953166],"type":"Point"}
}