{
  "type": "Feature",
  "properties": {
    "iso:country":"US",
    "sg:address":"401 Molly Dr",
    "sg:city":"Caldwell",
    "sg:classifiers":[
        {
            "category":"Real Estate",
            "subcategory":"Real Estate Operator",
            "type":"Services"
        }
    ],
    "sg:phone":"+1 979 567 7712",
    "sg:postcode":"77836",
    "sg:province":"TX",
    "sg:tags":[
        "building",
        "apartment"
    ],
    "wof:name":"Stone Street Retirement LTD",
    "wof:placetype":"venue"
},
  "geometry": {"coordinates":[-96.70249200000001,30.54036],"type":"Point"}
}