{
  "type": "Feature",
  "properties": {
    "iso:country":"US",
    "sg:address":"16324 Stuebner Airline Rd",
    "sg:city":"Spring",
    "sg:classifiers":[
        {
            "category":"Shopping",
            "subcategory":"Baby Store",
            "type":"Retail Goods"
        },
        {
            "category":"Shopping",
            "subcategory":"Gifts & Souvenirs",
            "type":"Retail Goods"
        },
        {
            "category":"Shopping",
            "type":"Retail Goods"
        },
        {
            "category":"Manufacturing",
            "subcategory":"Pottery",
            "type":"Manufacturing & Wholesale Goods"
        }
    ],
    "sg:phone":"+1 281 257 5944",
    "sg:postcode":"77379",
    "sg:province":"TX",
    "sg:tags":[
        "shop",
        "infant",
        "item",
        "products-decorative",
        "boutique",
        "ceramic",
        "children's",
        "wear",
        "basket"
    ],
    "sg:website":"http://www.NeighborhoodHodgePodge.com",
    "wof:name":"Neighborhood Hodge Podge",
    "wof:placetype":"venue"
},
  "geometry": {"coordinates":[-95.518365,30.01546],"type":"Point"}
}