{
  "type": "Feature",
  "properties": {
    "iso:country":"US",
    "sg:address":"10401 Airline Dr",
    "sg:city":"Houston",
    "sg:classifiers":[
        {
            "category":"Retail",
            "subcategory":"Auto Repair",
            "type":"Services"
        }
    ],
    "sg:phone":"+1 281 260 8838",
    "sg:postcode":"77037",
    "sg:province":"TX",
    "wof:name":"West Road Auto Care",
    "wof:placetype":"venue"
},
  "geometry": {"coordinates":[-95.401901,29.906099],"type":"Point"}
}