{
  "type": "Feature",
  "properties": {
    "iso:country":"US",
    "sg:address":"2205 Toulouse Dr",
    "sg:city":"Austin",
    "sg:classifiers":[
        {
            "category":"Social Services",
            "subcategory":"Job Training",
            "type":"Services"
        }
    ],
    "sg:phone":"+1 512 280 3508",
    "sg:postcode":"78748",
    "sg:province":"TX",
    "sg:tags":[
        "consultant"
    ],
    "wof:name":"Fame Training",
    "wof:placetype":"venue"
},
  "geometry": {"coordinates":[-97.82312,30.18025],"type":"Point"}
}