{
  "type": "Feature",
  "properties": {
    "iso:country":"US",
    "sg:address":"121 Pine St",
    "sg:city":"Ranger",
    "sg:classifiers":[
        {
            "category":"Retail",
            "subcategory":"Auto Repair",
            "type":"Services"
        }
    ],
    "sg:phone":"+1 254 647 1726",
    "sg:postcode":"76470",
    "sg:province":"TX",
    "sg:tags":[
        "general"
    ],
    "wof:name":"D L Crawford Garage",
    "wof:placetype":"venue"
},
  "geometry": {"coordinates":[-98.681225,32.469484],"type":"Point"}
}