{
  "type": "Feature",
  "properties": {
    "iso:country":"US",
    "sg:address":"712 Stonecreek Cir",
    "sg:city":"Friendswood",
    "sg:classifiers":[
        {
            "category":"Professional",
            "subcategory":"Management & Consulting",
            "type":"Services"
        }
    ],
    "sg:phone":"+1 281 648 3888",
    "sg:postcode":"77546",
    "sg:province":"TX",
    "sg:tags":[
        "personnel",
        "consultant"
    ],
    "wof:name":"Protek Sales",
    "wof:placetype":"venue"
},
  "geometry": {"coordinates":[-95.18907299999999,29.499007],"type":"Point"}
}