{
  "type": "Feature",
  "properties": {
    "iso:country":"US",
    "sg:address":"1319 Oakhurst Dr",
    "sg:city":"Southlake",
    "sg:classifiers":[
        {
            "category":"Real Estate",
            "subcategory":"Real Estate Operator",
            "type":"Services"
        }
    ],
    "sg:phone":"+1 817 481 5830",
    "sg:postcode":"76092",
    "sg:province":"TX",
    "sg:tags":[
        "building",
        "nonresidential"
    ],
    "wof:name":"Oakhurst Properties LLC",
    "wof:placetype":"venue"
},
  "geometry": {"coordinates":[-97.173744,32.925303],"type":"Point"}
}