{
  "type": "Feature",
  "properties": {
    "iso:country":"US",
    "sg:address":"25122 Burrard St",
    "sg:city":"Spring",
    "sg:classifiers":[
        {
            "category":"Real Estate",
            "subcategory":"Real Estate Agent",
            "type":"Services"
        }
    ],
    "sg:phone":"+1 281 350 8024",
    "sg:postcode":"77373",
    "sg:province":"TX",
    "wof:name":"Realty Executives",
    "wof:placetype":"venue"
},
  "geometry": {"coordinates":[-95.39099,30.075895],"type":"Point"}
}