{
  "type": "Feature",
  "properties": {
    "iso:country":"US",
    "sg:address":"5858 S Padre Island Dr",
    "sg:city":"Corpus Christi",
    "sg:classifiers":[
        {
            "category":"Shopping",
            "subcategory":"Shoes",
            "type":"Retail Goods"
        }
    ],
    "sg:phone":"+1 361 993 9194",
    "sg:postcode":"78412",
    "sg:province":"TX",
    "wof:name":"Payless Shoe Source",
    "wof:placetype":"venue"
},
  "geometry": {"coordinates":[-97.36633,27.706193],"type":"Point"}
}