{
  "type": "Feature",
  "properties": {
    "iso:country":"US",
    "sg:address":"50 Briar Hollow Ln",
    "sg:city":"Houston",
    "sg:classifiers":[
        {
            "category":"Health Services",
            "subcategory":"Clinic",
            "type":"Services"
        }
    ],
    "sg:phone":"+1 713 623 0837",
    "sg:postcode":"77027",
    "sg:province":"TX",
    "sg:tags":[
        "counseling",
        "mental"
    ],
    "wof:name":"Aronson Harvey B Lmsw-Acp/Lmft",
    "wof:placetype":"venue"
},
  "geometry": {"coordinates":[-95.45056,29.754575],"type":"Point"}
}