{
  "type": "Feature",
  "properties": {
    "iso:country":"US",
    "sg:address":"2614 W Braker Ln",
    "sg:city":"Austin",
    "sg:classifiers":[
        {
            "category":"Restaurant",
            "type":"Food & Drink"
        }
    ],
    "sg:phone":"+1 512 339 0600",
    "sg:postcode":"78758",
    "sg:province":"TX",
    "sg:website":"www.tacobell.com",
    "wof:name":"Taco Bell",
    "wof:placetype":"venue"
},
  "geometry": {"coordinates":[-97.721188,30.391131],"type":"Point"}
}