{
  "type": "Feature",
  "properties": {
    "iso:country":"US",
    "sg:address":"15802 Webelos St",
    "sg:city":"Friendswood",
    "sg:classifiers":[
        {
            "category":"Professional",
            "subcategory":"Computer Services",
            "type":"Services"
        }
    ],
    "sg:phone":"+1 832 881 6041",
    "sg:postcode":"77546",
    "sg:province":"TX",
    "sg:tags":[
        "publisher",
        "developer",
        "software"
    ],
    "wof:name":"Reynolds Ecm Inc",
    "wof:placetype":"venue"
},
  "geometry": {"coordinates":[-95.18004000000001,29.546667],"type":"Point"}
}