{
  "type": "Feature",
  "properties": {
    "iso:country":"US",
    "sg:address":"4965 Littlewood Dr",
    "sg:city":"Beaumont",
    "sg:classifiers":[
        {
            "category":"Professional",
            "subcategory":"Management & Consulting",
            "type":"Services"
        }
    ],
    "sg:phone":"+1 409 898 1685",
    "sg:postcode":"77706",
    "sg:province":"TX",
    "wof:name":"Loufo Management LLC",
    "wof:placetype":"venue"
},
  "geometry": {"coordinates":[-94.15586500000001,30.11079],"type":"Point"}
}