{
  "type": "Feature",
  "properties": {
    "iso:country":"US",
    "sg:address":"6212 Fair Rd",
    "sg:city":"Kaufman",
    "sg:classifiers":[
        {
            "category":"Building & Trades",
            "subcategory":"Landscaping Services",
            "type":"Services"
        }
    ],
    "sg:phone":"+1 972 962 3123",
    "sg:postcode":"75142",
    "sg:province":"TX",
    "wof:name":"Bestway Lawn Service",
    "wof:placetype":"venue"
},
  "geometry": {"coordinates":[-96.288994,32.548178],"type":"Point"}
}