{
  "type": "Feature",
  "properties": {
    "iso:country":"US",
    "sg:address":"307 University Dr",
    "sg:city":"College Station",
    "sg:classifiers":[
        {
            "category":"Restaurant",
            "type":"Food & Drink"
        }
    ],
    "sg:phone":"+1 979 846 2322",
    "sg:postcode":"77840",
    "sg:province":"TX",
    "sg:website":"www.dixiechicken.com",
    "wof:name":"Dixie Chicken",
    "wof:placetype":"venue"
},
  "geometry": {"coordinates":[-96.34546899999999,30.618304],"type":"Point"}
}