{
  "type": "Feature",
  "properties": {
    "iso:country":"US",
    "sg:address":"2500 WEST FREEWAY SUITE 300",
    "sg:city":"Denton",
    "sg:classifiers":[
        {
            "category":"Health Services",
            "subcategory":"Clinic",
            "type":"Services"
        },
        {
            "category":"Health Services",
            "subcategory":"Health Practitioner",
            "type":"Services"
        }
    ],
    "sg:phone":"+1 817 423 4400",
    "sg:postcode":"76201",
    "sg:province":"TX",
    "sg:tags":[
        "information",
        "therapist",
        "therapy",
        "treatment",
        "alcoholism",
        "physical"
    ],
    "wof:name":"Legacy Heart Care",
    "wof:placetype":"venue"
},
  "geometry": {"coordinates":[-97.150856,33.21291],"type":"Point"}
}