{
  "type": "Feature",
  "properties": {
    "iso:country":"US",
    "sg:address":"605 Highland Ave",
    "sg:city":"Austin",
    "sg:classifiers":[
        {
            "category":"Travel",
            "subcategory":"Travel Agent",
            "type":"Entertainment"
        }
    ],
    "sg:phone":"+1 512 478 2179",
    "sg:postcode":"78703",
    "sg:province":"TX",
    "sg:tags":[
        "operator",
        "tour"
    ],
    "wof:name":"Pro Tour Services",
    "wof:placetype":"venue"
},
  "geometry": {"coordinates":[-97.76149599999999,30.274383],"type":"Point"}
}