{
  "type": "Feature",
  "properties": {
    "iso:country":"US",
    "sg:address":"240 Holly St",
    "sg:city":"Alba",
    "sg:classifiers":[
        {
            "category":"Government",
            "subcategory":"Post Office",
            "type":"Public Place"
        }
    ],
    "sg:phone":"+1 903 765 2390",
    "sg:postcode":"75410",
    "sg:province":"TX",
    "sg:tags":[
        "postal",
        "us"
    ],
    "wof:name":"Alba Main Post Office",
    "wof:placetype":"venue"
},
  "geometry": {"coordinates":[-95.632301,32.792983],"type":"Point"}
}