{
  "type": "Feature",
  "properties": {
    "iso:country":"US",
    "sg:address":"1500 Harvey Rd",
    "sg:city":"College Station",
    "sg:classifiers":[
        {
            "category":"Ice Cream",
            "type":"Food & Drink"
        }
    ],
    "sg:menulink":"http://www.allmenus.com/tx/bryan-college-station/226819-dippin-dots/menu/",
    "sg:phone":"+1 979 695 2806",
    "sg:postcode":"77840",
    "sg:province":"TX",
    "sg:tags":[
        "american"
    ],
    "wof:name":"Dippin' Dots",
    "wof:placetype":"venue"
},
  "geometry": {"coordinates":[-96.304919,30.627401],"type":"Point"}
}