{
  "type": "Feature",
  "properties": {
    "iso:country":"US",
    "sg:address":"3201 Oak Lawn Ave",
    "sg:city":"Dallas",
    "sg:classifiers":[
        {
            "category":"Banks & Credit Unions",
            "subcategory":"Investment Brokerage",
            "type":"Services"
        }
    ],
    "sg:phone":"+1 214 560 2275",
    "sg:postcode":"75219",
    "sg:province":"TX",
    "wof:name":"Phoenix Strategy Investments",
    "wof:placetype":"venue"
},
  "geometry": {"coordinates":[-96.80835399999999,32.809663],"type":"Point"}
}