{
  "type": "Feature",
  "properties": {
    "iso:country":"US",
    "sg:address":"6405 N Beach St",
    "sg:city":"Fort Worth",
    "sg:classifiers":[
        {
            "category":"Restaurant",
            "type":"Food & Drink"
        }
    ],
    "sg:phone":"+1 817 232 2938",
    "sg:postcode":"76137",
    "sg:province":"TX",
    "sg:tags":[
        "eating"
    ],
    "wof:name":"2 P W Inc",
    "wof:placetype":"venue"
},
  "geometry": {"coordinates":[-97.290147,32.860935],"type":"Point"}
}