{
  "type": "Feature",
  "properties": {
    "iso:country":"US",
    "sg:address":"9555 W Sam Houston Pkwy S",
    "sg:city":"Houston",
    "sg:classifiers":[
        {
            "category":"Insurance",
            "subcategory":"Hazard Insurance",
            "type":"Services"
        }
    ],
    "sg:phone":"+1 713 219 1200",
    "sg:postcode":"77099",
    "sg:province":"TX",
    "wof:name":"Zenith Administrators",
    "wof:placetype":"venue"
},
  "geometry": {"coordinates":[-95.559196,29.6786],"type":"Point"}
}