{
  "type": "Feature",
  "properties": {
    "iso:country":"US",
    "sg:address":"2303 Weatherby Dr",
    "sg:city":"Mesquite",
    "sg:classifiers":[
        {
            "category":"Home & Garden",
            "subcategory":"Home Furnishings",
            "type":"Retail Goods"
        }
    ],
    "sg:phone":"+1 972 222 0037",
    "sg:postcode":"75181",
    "sg:province":"TX",
    "sg:tags":[
        "venetian",
        "blind",
        "window",
        "covering"
    ],
    "wof:name":"Rainbow Shutters Inc",
    "wof:placetype":"venue"
},
  "geometry": {"coordinates":[-96.564307,32.754132],"type":"Point"}
}