{
  "type": "Feature",
  "properties": {
    "iso:country":"US",
    "sg:address":"1806 W Irving Blvd",
    "sg:city":"Irving",
    "sg:classifiers":[
        {
            "category":"Manufacturing",
            "subcategory":"Printing",
            "type":"Manufacturing & Wholesale Goods"
        }
    ],
    "sg:phone":"+1 972 254 2288",
    "sg:postcode":"75061",
    "sg:province":"TX",
    "sg:tags":[
        "newspaper"
    ],
    "wof:name":"Thrifty Nickel Want Ads",
    "wof:placetype":"venue"
},
  "geometry": {"coordinates":[-96.96691199999999,32.824132],"type":"Point"}
}