{
  "type": "Feature",
  "properties": {
    "iso:country":"US",
    "sg:address":"812 Guam St",
    "sg:city":"Texarkana",
    "sg:classifiers":[
        {
            "category":"Building & Trades",
            "subcategory":"Construction",
            "type":"Services"
        }
    ],
    "sg:phone":"+1 903 838 8001",
    "sg:postcode":"75501",
    "sg:province":"TX",
    "sg:tags":[
        "concrete",
        "contractor"
    ],
    "wof:name":"House Leveler",
    "wof:placetype":"venue"
},
  "geometry": {"coordinates":[-94.10048399999999,33.426835],"type":"Point"}
}