{
  "type": "Feature",
  "properties": {
    "iso:country":"US",
    "sg:address":"2625 Green Oak Dr",
    "sg:city":"Carrollton",
    "sg:classifiers":[
        {
            "category":"Shopping",
            "type":"Retail Goods"
        }
    ],
    "sg:phone":"+1 972 862 9585",
    "sg:postcode":"75010",
    "sg:province":"TX",
    "sg:tags":[
        "merchandise"
    ],
    "wof:name":"Novel Tea Shoppe",
    "wof:placetype":"venue"
},
  "geometry": {"coordinates":[-96.858835,33.030976],"type":"Point"}
}