{
  "type": "Feature",
  "properties": {
    "iso:country":"US",
    "sg:address":"224 Ridgecrest Dr",
    "sg:city":"Hurst",
    "sg:classifiers":[
        {
            "category":"Shopping",
            "subcategory":"Gifts & Souvenirs",
            "type":"Retail Goods"
        }
    ],
    "sg:phone":"+1 817 282 4820",
    "sg:postcode":"76053",
    "sg:province":"TX",
    "wof:name":"Carlson Gifts",
    "wof:placetype":"venue"
},
  "geometry": {"coordinates":[-97.181164,32.81249],"type":"Point"}
}