{
  "type": "Feature",
  "properties": {
    "iso:country":"US",
    "sg:address":"10911 Petal St",
    "sg:city":"Dallas",
    "sg:classifiers":[
        {
            "category":"Insurance",
            "subcategory":"Insurance Agent",
            "type":"Services"
        }
    ],
    "sg:phone":"+1 214 503 0146",
    "sg:postcode":"75238",
    "sg:province":"TX",
    "wof:name":"Winterstone Financial Ltd",
    "wof:placetype":"venue"
},
  "geometry": {"coordinates":[-96.691513,32.883404],"type":"Point"}
}