{
  "type": "Feature",
  "properties": {
    "iso:country":"US",
    "sg:address":"3631 Spencer Hwy",
    "sg:city":"Pasadena",
    "sg:phone":"+1 281 922 8266",
    "sg:postcode":"77504",
    "sg:province":"TX",
    "sg:tags":[
        "leather"
    ],
    "wof:name":"Darque Tan",
    "wof:placetype":"venue"
},
  "geometry": {"coordinates":[-95.18930400000001,29.665049],"type":"Point"}
}