{
  "type": "Feature",
  "properties": {
    "iso:country":"US",
    "sg:address":"1340 S 5th St",
    "sg:city":"Midlothian",
    "sg:classifiers":[
        {
            "category":"Shopping",
            "subcategory":"Discount & Variety Stores",
            "type":"Retail Goods"
        }
    ],
    "sg:phone":"+1 972 723 7970",
    "sg:postcode":"76065",
    "sg:province":"TX",
    "sg:tags":[
        "merchandising",
        "merchandise"
    ],
    "wof:name":"Konea",
    "wof:placetype":"venue"
},
  "geometry": {"coordinates":[-96.998482,32.471545],"type":"Point"}
}