{
  "type": "Feature",
  "properties": {
    "iso:country":"US",
    "sg:address":"9234 Woodlyn Rd",
    "sg:city":"Houston",
    "sg:classifiers":[
        {
            "category":"Freight",
            "type":"Transportation"
        }
    ],
    "sg:phone":"+1 713 631 9182",
    "sg:postcode":"77078",
    "sg:province":"TX",
    "sg:tags":[
        "operator",
        "trucking"
    ],
    "wof:name":"Roberts T&F Enterprises",
    "wof:placetype":"venue"
},
  "geometry": {"coordinates":[-95.250681,29.840613],"type":"Point"}
}