{
  "type": "Feature",
  "properties": {
    "iso:country":"US",
    "sg:address":"1215 S 10th St",
    "sg:city":"Raymondville",
    "sg:classifiers":[
        {
            "category":"Insurance",
            "subcategory":"Hazard Insurance",
            "type":"Services"
        }
    ],
    "sg:phone":"+1 956 689 2961",
    "sg:postcode":"78580",
    "sg:province":"TX",
    "sg:tags":[
        "carrier",
        "surety"
    ],
    "wof:name":"Zaley Management Co LLC",
    "wof:placetype":"venue"
},
  "geometry": {"coordinates":[-97.77873200000001,26.471353],"type":"Point"}
}