{
  "type": "Feature",
  "properties": {
    "iso:country":"US",
    "sg:address":"8524 Davis Blvd",
    "sg:city":"N Richland Hills",
    "sg:classifiers":[
        {
            "category":"Banks & Credit Unions",
            "subcategory":"Bank",
            "type":"Services"
        }
    ],
    "sg:phone":"+1 817 788 5104",
    "sg:postcode":"76180",
    "sg:province":"TX",
    "wof:name":"Washington Mutual",
    "wof:placetype":"venue"
},
  "geometry": {"coordinates":[-97.18885299999999,32.910097],"type":"Point"}
}