{
  "type": "Feature",
  "properties": {
    "iso:country":"US",
    "sg:address":"1209 E 12th St",
    "sg:city":"Austin",
    "sg:classifiers":[
        {
            "category":"Shopping",
            "type":"Retail Goods"
        }
    ],
    "sg:phone":"+1 512 474 6056",
    "sg:postcode":"78702",
    "sg:province":"TX",
    "sg:tags":[
        "art",
        "gallery",
        "dealer"
    ],
    "wof:name":"Niendorff Art Gallery",
    "wof:placetype":"venue"
},
  "geometry": {"coordinates":[-97.72657,30.272648],"type":"Point"}
}