{
  "type": "Feature",
  "properties": {
    "iso:country":"US",
    "sg:address":"3300 Parker Ln",
    "sg:city":"Austin",
    "sg:classifiers":[
        {
            "category":"Organizations",
            "subcategory":"Professional Association",
            "type":"Services"
        }
    ],
    "sg:phone":"+1 512 848 3395",
    "sg:postcode":"78741",
    "sg:province":"TX",
    "sg:tags":[
        "agency",
        "bureau",
        "entertainment"
    ],
    "wof:name":"Micrich Entertainment, Inc",
    "wof:placetype":"venue"
},
  "geometry": {"coordinates":[-97.742248,30.221094],"type":"Point"}
}