{
  "type": "Feature",
  "properties": {
    "iso:country":"US",
    "sg:address":"3413 Sherrye Dr",
    "sg:city":"Plano",
    "sg:classifiers":[
        {
            "category":"Education",
            "subcategory":"Vocational School",
            "type":"Public Place"
        }
    ],
    "sg:phone":"+1 972 423 3623",
    "sg:postcode":"75074",
    "sg:province":"TX",
    "sg:tags":[
        "training",
        "computer"
    ],
    "wof:name":"Dianna Hanson",
    "wof:placetype":"venue"
},
  "geometry": {"coordinates":[-96.66700400000001,33.025934],"type":"Point"}
}