{
  "type": "Feature",
  "properties": {
    "iso:country":"US",
    "sg:address":"3315 Maxwell Dr",
    "sg:city":"Midland",
    "sg:classifiers":[
        {
            "category":"Banks & Credit Unions",
            "subcategory":"Investment Brokerage",
            "type":"Services"
        }
    ],
    "sg:phone":"+1 432 697 4054",
    "sg:postcode":"79707",
    "sg:province":"TX",
    "sg:tags":[
        "security"
    ],
    "wof:name":"TCO Investment Club",
    "wof:placetype":"venue"
},
  "geometry": {"coordinates":[-102.126918,32.019887],"type":"Point"}
}