{
  "type": "Feature",
  "properties": {
    "iso:country":"US",
    "sg:address":"1 White Pillars Ln",
    "sg:city":"Houston",
    "sg:classifiers":[
        {
            "category":"Professional",
            "type":"Services"
        }
    ],
    "sg:phone":"+1 713 468 4202",
    "sg:postcode":"77024",
    "sg:province":"TX",
    "wof:name":"R Davis & Gloria J James",
    "wof:placetype":"venue"
},
  "geometry": {"coordinates":[-95.517381,29.7736],"type":"Point"}
}