{
  "type": "Feature",
  "properties": {
    "iso:country":"US",
    "sg:address":"3430 Old Denton Rd",
    "sg:city":"Carrollton",
    "sg:classifiers":[
        {
            "category":"Retail",
            "subcategory":"Laundry & Dry Cleaning",
            "type":"Services"
        }
    ],
    "sg:phone":"+1 972 394 4082",
    "sg:postcode":"75007",
    "sg:province":"TX",
    "wof:name":"Molinars Carpet Care",
    "wof:placetype":"venue"
},
  "geometry": {"coordinates":[-96.909803,33.005905],"type":"Point"}
}