{
  "type": "Feature",
  "properties": {
    "iso:country":"US",
    "sg:address":"118 E Live Oak St",
    "sg:city":"Dublin",
    "sg:classifiers":[
        {
            "category":"Real Estate",
            "subcategory":"Real Estate Agent",
            "type":"Services"
        }
    ],
    "sg:phone":"+1 254 445 2517",
    "sg:postcode":"76446",
    "sg:province":"TX",
    "wof:name":"KB Nichols Management Inc",
    "wof:placetype":"venue"
},
  "geometry": {"coordinates":[-98.34195699999999,32.086073],"type":"Point"}
}