{
  "type": "Feature",
  "properties": {
    "iso:country":"US",
    "sg:address":"Saigon Mall 3212 N Jupiter Rd",
    "sg:city":"Garland",
    "sg:classifiers":[
        {
            "category":"Restaurant",
            "type":"Food & Drink"
        }
    ],
    "sg:postcode":"75044",
    "sg:province":"TX",
    "sg:tags":[
        "vietnamese"
    ],
    "wof:name":"Pho Que Huong",
    "wof:placetype":"venue"
},
  "geometry": {"coordinates":[-96.681387,32.947222],"type":"Point"}
}