{
  "type": "Feature",
  "properties": {
    "iso:country":"US",
    "sg:address":"8963 Silver Spruce Rd",
    "sg:city":"Gilmer",
    "sg:classifiers":[
        {
            "category":"Building & Trades",
            "subcategory":"Construction",
            "type":"Services"
        }
    ],
    "sg:phone":"+1 903 734 7687",
    "sg:postcode":"75645",
    "sg:province":"TX",
    "sg:tags":[
        "house"
    ],
    "wof:name":"Herndon Construction",
    "wof:placetype":"venue"
},
  "geometry": {"coordinates":[-94.941036,32.613024],"type":"Point"}
}