{
  "type": "Feature",
  "properties": {
    "iso:country":"US",
    "sg:address":"9222 Wilcrest Dr",
    "sg:city":"Houston",
    "sg:classifiers":[
        {
            "category":"Organizations",
            "subcategory":"Religious Organization",
            "type":"Services"
        }
    ],
    "sg:phone":"+1 281 530 0120",
    "sg:postcode":"77099",
    "sg:province":"TX",
    "wof:name":"Mount Olive Church of God",
    "wof:placetype":"venue"
},
  "geometry": {"coordinates":[-95.570714,29.677885],"type":"Point"}
}