{
  "type": "Feature",
  "properties": {
    "iso:country":"US",
    "sg:address":"2802 NW 22nd St",
    "sg:city":"Fort Worth",
    "sg:classifiers":[
        {
            "category":"Building & Trades",
            "subcategory":"Construction",
            "type":"Services"
        }
    ],
    "sg:phone":"+1 817 626 0003",
    "sg:postcode":"76106",
    "sg:province":"TX",
    "sg:tags":[
        "concrete",
        "contractor"
    ],
    "wof:name":"Mariano C Barron Concrete",
    "wof:placetype":"venue"
},
  "geometry": {"coordinates":[-97.384753,32.79653],"type":"Point"}
}