{
  "type": "Feature",
  "properties": {
    "iso:country":"US",
    "sg:address":"767 Shady Tree Ct",
    "sg:city":"Burleson",
    "sg:classifiers":[
        {
            "category":"Government",
            "subcategory":"Office",
            "type":"Public Place"
        }
    ],
    "sg:phone":"+1 817 426 6921",
    "sg:postcode":"76028",
    "sg:province":"TX",
    "wof:name":"Steven Lee Mahan",
    "wof:placetype":"venue"
},
  "geometry": {"coordinates":[-97.298299,32.525937],"type":"Point"}
}