{
  "type": "Feature",
  "properties": {
    "iso:country":"US",
    "sg:address":"12313 Bend Creek Ln",
    "sg:city":"Pearland",
    "sg:classifiers":[
        {
            "category":"Professional",
            "subcategory":"Employment Agencies",
            "type":"Services"
        }
    ],
    "sg:phone":"+1 832 816 5800",
    "sg:postcode":"77584",
    "sg:province":"TX",
    "sg:tags":[
        "opportunity",
        "contractor"
    ],
    "wof:name":"Lane Staffing, Inc.",
    "wof:placetype":"venue"
},
  "geometry": {"coordinates":[-95.411101,29.561935],"type":"Point"}
}