{
  "type": "Feature",
  "properties": {
    "iso:country":"US",
    "sg:address":"3621 Carson St",
    "sg:city":"Amarillo",
    "sg:classifiers":[
        {
            "category":"Organizations",
            "subcategory":"Membership Organization",
            "type":"Services"
        }
    ],
    "sg:phone":"+1 806 355 1415",
    "sg:postcode":"79109",
    "sg:province":"TX",
    "wof:name":"Reserve Officers Assn Texas",
    "wof:placetype":"venue"
},
  "geometry": {"coordinates":[-101.881804,35.173313],"type":"Point"}
}