{
  "type": "Feature",
  "properties": {
    "iso:country":"US",
    "sg:address":"716 Ridgemont Ln",
    "sg:city":"Gonzales",
    "sg:classifiers":[
        {
            "category":"Building & Trades",
            "subcategory":"Construction",
            "type":"Services"
        }
    ],
    "sg:phone":"+1 830 672 2332",
    "sg:postcode":"78629",
    "sg:province":"TX",
    "sg:tags":[
        "house"
    ],
    "wof:name":"E Almaraz General Contracing",
    "wof:placetype":"venue"
},
  "geometry": {"coordinates":[-97.457008,29.517954],"type":"Point"}
}