{
  "type": "Feature",
  "properties": {
    "iso:country":"US",
    "sg:address":"1811 Garden City Hwy",
    "sg:city":"Midland",
    "sg:classifiers":[
        {
            "category":"Mining & Drilling",
            "type":"Manufacturing & Wholesale Goods"
        }
    ],
    "sg:phone":"+1 432 570 7440",
    "sg:postcode":"79701",
    "sg:province":"TX",
    "sg:tags":[
        "field",
        "oil",
        "well"
    ],
    "sg:website":"www.keyenergy.com",
    "wof:name":"Key Fishing & Rental Tools",
    "wof:placetype":"venue"
},
  "geometry": {"coordinates":[-102.055915,31.98782],"type":"Point"}
}