{
  "type": "Feature",
  "properties": {
    "iso:country":"US",
    "sg:address":"2105 Silber Rd",
    "sg:city":"Houston",
    "sg:classifiers":[
        {
            "category":"Professional",
            "subcategory":"Business Services",
            "type":"Services"
        },
        {
            "category":"Professional",
            "subcategory":"Management & Consulting",
            "type":"Services"
        }
    ],
    "sg:phone":"+1 713 682 3000",
    "sg:postcode":"77055",
    "sg:province":"TX",
    "sg:tags":[
        "water",
        "purification",
        "treatment",
        "system"
    ],
    "sg:website":"www.mirexsolutions.com",
    "wof:name":"Mirex Aquapure Solutions",
    "wof:placetype":"venue"
},
  "geometry": {"coordinates":[-95.467997,29.805779],"type":"Point"}
}