{
  "type": "Feature",
  "properties": {
    "iso:country":"US",
    "sg:address":"804 Medical Cir",
    "sg:city":"Longview",
    "sg:classifiers":[
        {
            "category":"Health Services",
            "subcategory":"Doctor",
            "type":"Services"
        }
    ],
    "sg:phone":"+1 903 619 0322",
    "sg:postcode":"75605",
    "sg:province":"TX",
    "sg:tags":[
        "physician",
        "surgeon"
    ],
    "wof:name":"Stephen Somerville MD Pa",
    "wof:placetype":"venue"
},
  "geometry": {"coordinates":[-94.731672,32.534015],"type":"Point"}
}