{
  "type": "Feature",
  "properties": {
    "iso:country":"US",
    "sg:address":"5375 W Richey Rd",
    "sg:city":"Houston",
    "sg:classifiers":[
        {
            "category":"Food & Beverages",
            "subcategory":"Liquor & Beverages",
            "type":"Retail Goods"
        }
    ],
    "sg:phone":"+1 281 444 5884",
    "sg:postcode":"77066",
    "sg:province":"TX",
    "sg:tags":[
        "alcoholic"
    ],
    "wof:name":"Time Savers Discount Liquor",
    "wof:placetype":"venue"
},
  "geometry": {"coordinates":[-95.50059899999999,29.960116],"type":"Point"}
}