{
  "type": "Feature",
  "properties": {
    "iso:country":"US",
    "sg:address":"18914 Windsor Wood",
    "sg:city":"San Antonio",
    "sg:classifiers":[
        {
            "category":"Banks & Credit Unions",
            "subcategory":"Financial Services",
            "type":"Services"
        }
    ],
    "sg:phone":"+1 210 479 3826",
    "sg:postcode":"78258",
    "sg:province":"TX",
    "sg:tags":[
        "company",
        "holding"
    ],
    "wof:name":"Sundance Holdings LLC",
    "wof:placetype":"venue"
},
  "geometry": {"coordinates":[-98.514056,29.616475],"type":"Point"}
}