{
  "type": "Feature",
  "properties": {
    "iso:country":"US",
    "sg:address":"553 Highland Dr",
    "sg:city":"Bandera",
    "sg:classifiers":[
        {
            "category":"Health Services",
            "subcategory":"Health Practitioner",
            "type":"Services"
        }
    ],
    "sg:phone":"+1 830 796 9250",
    "sg:postcode":"78003",
    "sg:province":"TX",
    "sg:tags":[
        "nutritionist"
    ],
    "wof:name":"Nutrition 4U",
    "wof:placetype":"venue"
},
  "geometry": {"coordinates":[-99.142123,29.747432],"type":"Point"}
}