{
  "type": "Feature",
  "properties": {
    "iso:country":"US",
    "sg:address":"915 Ruby St",
    "sg:city":"Nacogdoches",
    "sg:classifiers":[
        {
            "category":"Building & Trades",
            "subcategory":"Plumbing",
            "type":"Services"
        }
    ],
    "sg:phone":"+1 936 560 1616",
    "sg:postcode":"75961",
    "sg:province":"TX",
    "sg:tags":[
        "plumbing",
        "contractor"
    ],
    "wof:name":"Kinney's Plumbing",
    "wof:placetype":"venue"
},
  "geometry": {"coordinates":[-94.657144,31.61145],"type":"Point"}
}