{
  "type": "Feature",
  "properties": {
    "iso:country":"US",
    "sg:address":"27239 Hill and Dale Ave",
    "sg:city":"Splendora",
    "sg:classifiers":[
        {
            "category":"Professional",
            "subcategory":"Business Services",
            "type":"Services"
        }
    ],
    "sg:phone":"+1 281 399 3960",
    "sg:postcode":"77372",
    "sg:province":"TX",
    "wof:name":"Linan Enterprises",
    "wof:placetype":"venue"
},
  "geometry": {"coordinates":[-95.151512,30.20514],"type":"Point"}
}