{
  "type": "Feature",
  "properties": {
    "iso:country":"US",
    "sg:address":"2207 Payton Colony Rd",
    "sg:city":"Blanco",
    "sg:classifiers":[
        {
            "category":"Farming",
            "subcategory":"Livestock Farm",
            "type":"Manufacturing & Wholesale Goods"
        }
    ],
    "sg:phone":"+1 830 833 5870",
    "sg:postcode":"78606",
    "sg:province":"TX",
    "sg:tags":[
        "animal",
        "general"
    ],
    "wof:name":"High Country Ranches Property",
    "wof:placetype":"venue"
},
  "geometry": {"coordinates":[-98.31127499999999,30.139398],"type":"Point"}
}