{
  "type": "Feature",
  "properties": {
    "iso:country":"US",
    "sg:address":"8310 Southwestern Blvd",
    "sg:city":"Dallas",
    "sg:classifiers":[
        {
            "category":"Sports & Exercise",
            "subcategory":"Tennis Court",
            "type":"Entertainment"
        }
    ],
    "sg:phone":"+1 214 772 1900",
    "sg:postcode":"75206",
    "sg:province":"TX",
    "wof:name":"Village Pro Shop",
    "wof:placetype":"venue"
},
  "geometry": {"coordinates":[-96.76460299999999,32.860401],"type":"Point"}
}