{
  "type": "Feature",
  "properties": {
    "iso:country":"US",
    "sg:address":"815 S College Ave",
    "sg:city":"Tyler",
    "sg:classifiers":[
        {
            "category":"Professional",
            "subcategory":"Accounting & Tax Preparation",
            "type":"Services"
        },
        {
            "category":"Banks & Credit Unions",
            "subcategory":"Investment Brokerage",
            "type":"Services"
        }
    ],
    "sg:phone":"+1 903 597 8206",
    "sg:postcode":"75701",
    "sg:province":"TX",
    "sg:tags":[
        "billing"
    ],
    "wof:name":"Gene E Wright Inc",
    "wof:placetype":"venue"
},
  "geometry": {"coordinates":[-95.302773,32.340622],"type":"Point"}
}