{
  "type": "Feature",
  "properties": {
    "iso:country":"US",
    "sg:address":"290 Co Rd 386",
    "sg:city":"San Antonio",
    "sg:classifiers":[
        {
            "category":"Real Estate",
            "subcategory":"Real Estate Operator",
            "type":"Services"
        }
    ],
    "sg:phone":"+1 210 931 3710",
    "sg:postcode":"78253",
    "sg:province":"TX",
    "sg:tags":[
        "building",
        "nonresidential"
    ],
    "wof:name":"Jth Properties",
    "wof:placetype":"venue"
},
  "geometry": {"coordinates":[-98.82524600000001,29.43946],"type":"Point"}
}