{
  "type": "Feature",
  "properties": {
    "iso:country":"US",
    "sg:address":"18593 Fm 1431",
    "sg:city":"Jonestown",
    "sg:classifiers":[
        {
            "category":"Park",
            "type":"Public Place"
        }
    ],
    "sg:phone":"+1 512 267 5550",
    "sg:postcode":"78645",
    "sg:province":"TX",
    "wof:name":"Texas Recreation & Park Society",
    "wof:placetype":"venue"
},
  "geometry": {"coordinates":[-97.92289700000001,30.4981],"type":"Point"}
}