{
  "type": "Feature",
  "properties": {
    "iso:country":"US",
    "sg:address":"23033 Aldine Westfield Rd",
    "sg:city":"Spring",
    "sg:classifiers":[
        {
            "category":"Retail",
            "subcategory":"Laundry & Dry Cleaning",
            "type":"Services"
        }
    ],
    "sg:phone":"+1 281 528 5540",
    "sg:postcode":"77373",
    "sg:province":"TX",
    "sg:tags":[
        "garment",
        "agent"
    ],
    "wof:name":"Spring Cleaners",
    "wof:placetype":"venue"
},
  "geometry": {"coordinates":[-95.38569200000001,30.046156],"type":"Point"}
}