{
  "type": "Feature",
  "properties": {
    "iso:country":"US",
    "sg:address":"5613 Adams Ave",
    "sg:city":"Austin",
    "sg:classifiers":[
        {
            "category":"Shopping",
            "subcategory":"Computers & Home Electronics",
            "type":"Retail Goods"
        },
        {
            "category":"Professional",
            "subcategory":"Computer Services",
            "type":"Services"
        }
    ],
    "sg:phone":"+1 512 459 4357",
    "sg:postcode":"78756",
    "sg:province":"TX",
    "sg:tags":[
        "repair",
        "recovery",
        "supply",
        "technical",
        "assistance",
        "system",
        "hardware",
        "network",
        "security-systems",
        "design",
        "equipment-service",
        "data",
        "support",
        "software"
    ],
    "wof:name":"Balcones PC",
    "wof:placetype":"venue"
},
  "geometry": {"coordinates":[-97.73991599999999,30.330074],"type":"Point"}
}