{
  "type": "Feature",
  "properties": {
    "iso:country":"US",
    "sg:address":"5709 Woodmont Ct",
    "sg:city":"Plano",
    "sg:classifiers":[
        {
            "category":"Professional",
            "subcategory":"Business Services",
            "type":"Services"
        }
    ],
    "sg:phone":"+1 972 398 2395",
    "sg:postcode":"75093",
    "sg:province":"TX",
    "wof:name":"Cindy Lukeheart Interiors",
    "wof:placetype":"venue"
},
  "geometry": {"coordinates":[-96.819695,33.034824],"type":"Point"}
}