{
  "type": "Feature",
  "properties": {
    "iso:country":"US",
    "sg:address":"2821 Andrews Hwy",
    "sg:city":"Odessa",
    "sg:classifiers":[
        {
            "category":"Building & Trades",
            "subcategory":"Equipment Rental",
            "type":"Services"
        }
    ],
    "sg:phone":"+1 432 332 3281",
    "sg:postcode":"79762",
    "sg:province":"TX",
    "sg:tags":[
        "leasing",
        "furniture"
    ],
    "wof:name":"Credit World",
    "wof:placetype":"venue"
},
  "geometry": {"coordinates":[-102.38123400000001,31.870705],"type":"Point"}
}