{
  "type": "Feature",
  "properties": {
    "iso:country":"US",
    "sg:address":"12502 Exchange Dr",
    "sg:city":"Stafford",
    "sg:classifiers":[
        {
            "category":"Home & Garden",
            "subcategory":"Building Materials",
            "type":"Retail Goods"
        }
    ],
    "sg:phone":"+1 281 240 5335",
    "sg:postcode":"77477",
    "sg:province":"TX",
    "sg:tags":[
        "equipment",
        "electric",
        "supply"
    ],
    "sg:website":"www.hitecups.com",
    "wof:name":"Hitec Inc",
    "wof:placetype":"venue"
},
  "geometry": {"coordinates":[-95.593039,29.635179],"type":"Point"}
}