{
  "type": "Feature",
  "properties": {
    "iso:country":"US",
    "sg:address":"6410 Fannin St Ste 200",
    "sg:city":"Houston",
    "sg:classifiers":[
        {
            "category":"Health Services",
            "subcategory":"Doctor",
            "type":"Services"
        }
    ],
    "sg:phone":"+1 713 796 8357",
    "sg:postcode":"77030",
    "sg:province":"TX",
    "sg:tags":[
        "obstetrician",
        "gynecologist"
    ],
    "sg:website":"obgynofhouston.com",
    "wof:name":"OB/Gyn Of Houston",
    "wof:placetype":"venue"
},
  "geometry": {"coordinates":[-95.39788799999999,29.714407],"type":"Point"}
}