{
  "type": "Feature",
  "properties": {
    "iso:country":"US",
    "sg:address":"1 Treasure Hill Rd",
    "sg:city":"Texarkana",
    "sg:classifiers":[
        {
            "category":"Professional",
            "type":"Services"
        }
    ],
    "sg:phone":"+1 903 794 7730",
    "sg:postcode":"75503",
    "sg:province":"TX",
    "wof:name":"Personally Yours",
    "wof:placetype":"venue"
},
  "geometry": {"coordinates":[-94.04851600000001,33.495494],"type":"Point"}
}