{
  "type": "Feature",
  "properties": {
    "iso:country":"US",
    "sg:address":"2200 Panther Trl",
    "sg:city":"Austin",
    "sg:classifiers":[
        {
            "category":"Shopping",
            "subcategory":"Computers & Home Electronics",
            "type":"Retail Goods"
        }
    ],
    "sg:phone":"+1 512 472 1221",
    "sg:postcode":"78704",
    "sg:province":"TX",
    "sg:tags":[
        "software"
    ],
    "wof:name":"Guidance Software",
    "wof:placetype":"venue"
},
  "geometry": {"coordinates":[-97.78856500000001,30.238104],"type":"Point"}
}