{
  "type": "Feature",
  "properties": {
    "iso:country":"US",
    "sg:address":"3036 Albans Rd",
    "sg:city":"Houston",
    "sg:classifiers":[
        {
            "category":"Shopping",
            "subcategory":"Clothing, Apparel, & Fashions",
            "type":"Retail Goods"
        }
    ],
    "sg:phone":"+1 713 668 2576",
    "sg:postcode":"77005",
    "sg:province":"TX",
    "wof:name":"Feahaus",
    "wof:placetype":"venue"
},
  "geometry": {"coordinates":[-95.427291,29.723915],"type":"Point"}
}