{
  "type": "Feature",
  "properties": {
    "iso:country":"US",
    "sg:address":"1 Riverway Ste 1850",
    "sg:city":"Houston",
    "sg:classifiers":[
        {
            "category":"Professional",
            "subcategory":"Lawyer & Legal Services",
            "type":"Services"
        }
    ],
    "sg:phone":"+1 713 961 8028",
    "sg:postcode":"77056",
    "sg:province":"TX",
    "wof:name":"Associates Grundy &",
    "wof:placetype":"venue"
},
  "geometry": {"coordinates":[-95.46332099999999,29.761253],"type":"Point"}
}