{
  "type": "Feature",
  "properties": {
    "iso:country":"US",
    "sg:address":"6604 Frankford Ave",
    "sg:city":"Lubbock",
    "sg:classifiers":[
        {
            "category":"Banks & Credit Unions",
            "subcategory":"Bank",
            "type":"Services"
        }
    ],
    "sg:phone":"+1 806 798 5800",
    "sg:postcode":"79424",
    "sg:province":"TX",
    "sg:tags":[
        "commercial"
    ],
    "sg:website":"www.firstunited.net",
    "wof:name":"First United Bank SWB",
    "wof:placetype":"venue"
},
  "geometry": {"coordinates":[-101.93979,33.534205],"type":"Point"}
}