{
  "type": "Feature",
  "properties": {
    "iso:country":"US",
    "sg:address":"2505 Robinson Dr",
    "sg:city":"Waco",
    "sg:classifiers":[
        {
            "category":"Restaurant",
            "type":"Food & Drink"
        }
    ],
    "sg:phone":"+1 254 662 3359",
    "sg:postcode":"76706",
    "sg:province":"TX",
    "sg:tags":[
        "mexican"
    ],
    "wof:name":"Taqueria El Crucero",
    "wof:placetype":"venue"
},
  "geometry": {"coordinates":[-97.13054700000001,31.518886],"type":"Point"}
}