{
  "type": "Feature",
  "properties": {
    "iso:country":"US",
    "sg:address":"6506 Knottingham Dr",
    "sg:city":"Arlington",
    "sg:classifiers":[
        {
            "category":"Professional",
            "subcategory":"Lawyer & Legal Services",
            "type":"Services"
        }
    ],
    "sg:phone":"+1 817 467 1340",
    "sg:postcode":"76001",
    "sg:province":"TX",
    "sg:tags":[
        "paralegal"
    ],
    "wof:name":"Jolly's Paralegal Svcs",
    "wof:placetype":"venue"
},
  "geometry": {"coordinates":[-97.115932,32.638907],"type":"Point"}
}