{
  "type": "Feature",
  "properties": {
    "iso:country":"US",
    "sg:address":"403 W Tyler St",
    "sg:city":"Gilmer",
    "sg:classifiers":[
        {
            "category":"Professional",
            "subcategory":"Lawyer & Legal Services",
            "type":"Services"
        }
    ],
    "sg:phone":"+1 903 843 5678",
    "sg:postcode":"75644",
    "sg:province":"TX",
    "sg:tags":[
        "attorney",
        "practice"
    ],
    "sg:website":"http://www.teftellerlaw.com",
    "wof:name":"Law Offices Todd Tefteller",
    "wof:placetype":"venue"
},
  "geometry": {"coordinates":[-94.94766300000001,32.728745],"type":"Point"}
}