{
  "type": "Feature",
  "properties": {
    "iso:country":"US",
    "sg:address":"13016 Hughes Ln",
    "sg:city":"Dallas",
    "sg:classifiers":[
        {
            "category":"Real Estate",
            "subcategory":"Real Estate Agent",
            "type":"Services"
        }
    ],
    "sg:phone":"+1 972 503 7060",
    "sg:postcode":"75240",
    "sg:province":"TX",
    "wof:name":"Wanda Baker Real Estate",
    "wof:placetype":"venue"
},
  "geometry": {"coordinates":[-96.797127,32.925933],"type":"Point"}
}