{
  "type": "Feature",
  "properties": {
    "iso:country":"US",
    "sg:address":"192 S Vail St",
    "sg:city":"La Grange",
    "sg:classifiers":[
        {
            "category":"Education",
            "subcategory":"School",
            "type":"Public Place"
        }
    ],
    "sg:phone":"+1 979 968 4700",
    "sg:postcode":"78945",
    "sg:province":"TX",
    "wof:name":"LA Grange Intermediate School",
    "wof:placetype":"venue"
},
  "geometry": {"coordinates":[-96.869145,29.908037],"type":"Point"}
}