{
  "type": "Feature",
  "properties": {
    "iso:country":"US",
    "sg:address":"5314 Arapaho Rd",
    "sg:city":"Dallas",
    "sg:classifiers":[
        {
            "category":"Professional",
            "type":"Services"
        }
    ],
    "sg:phone":"+1 972 702 1711",
    "sg:postcode":"75248",
    "sg:province":"TX",
    "sg:tags":[
        "establishment"
    ],
    "wof:name":"Anson & Corley Co",
    "wof:placetype":"venue"
},
  "geometry": {"coordinates":[-96.816457,32.960947],"type":"Point"}
}