{
  "type": "Feature",
  "properties": {
    "iso:country":"US",
    "sg:address":"201 Highway 332 W",
    "sg:city":"Lake Jackson",
    "sg:classifiers":[
        {
            "category":"Shopping",
            "subcategory":"Beauty & Cosmetics",
            "type":"Retail Goods"
        }
    ],
    "sg:phone":"+1 979 299 3328",
    "sg:postcode":"77566",
    "sg:province":"TX",
    "sg:tags":[
        "supply"
    ],
    "sg:website":"www.sallybeauty.com",
    "wof:name":"Sally Beauty Supply",
    "wof:placetype":"venue"
},
  "geometry": {"coordinates":[-95.46525200000001,29.842684],"type":"Point"}
}