{
  "type": "Feature",
  "properties": {
    "iso:country":"US",
    "sg:address":"13752 Northwest Fwy",
    "sg:city":"Houston",
    "sg:classifiers":[
        {
            "category":"Shopping",
            "subcategory":"Discount & Variety Stores",
            "type":"Retail Goods"
        }
    ],
    "sg:phone":"+1 713 996 8100",
    "sg:postcode":"77040",
    "sg:province":"TX",
    "sg:tags":[
        "merchandise",
        "general"
    ],
    "wof:name":"Northwest Dollar Land LLC",
    "wof:placetype":"venue"
},
  "geometry": {"coordinates":[-95.512658,29.85342],"type":"Point"}
}