{
  "type": "Feature",
  "properties": {
    "iso:country":"US",
    "sg:address":"618 W 8th Ave",
    "sg:city":"Amarillo",
    "sg:classifiers":[
        {
            "category":"Personal",
            "subcategory":"Beauty Salon",
            "type":"Services"
        }
    ],
    "sg:phone":"+1 806 350 7780",
    "sg:postcode":"79101",
    "sg:province":"AR",
    "wof:name":"Salon Downtown 618",
    "wof:placetype":"venue"
},
  "geometry": {"coordinates":[-101.84467600000001,35.206588],"type":"Point"}
}