{
  "type": "Feature",
  "properties": {
    "iso:country":"US",
    "sg:address":"1615 Redway Ln",
    "sg:city":"Houston",
    "sg:classifiers":[
        {
            "category":"Manufacturing",
            "subcategory":"Glass & Minerals",
            "type":"Manufacturing & Wholesale Goods"
        }
    ],
    "sg:phone":"+1 281 286 1522",
    "sg:postcode":"77062",
    "sg:province":"TX",
    "sg:tags":[
        "mfg"
    ],
    "wof:name":"Contempo Art",
    "wof:placetype":"venue"
},
  "geometry": {"coordinates":[-95.12018,29.567877],"type":"Point"}
}