{
  "type": "Feature",
  "properties": {
    "iso:country":"US",
    "sg:address":"921 Main St",
    "sg:city":"Houston",
    "sg:classifiers":[
        {
            "category":"Parking",
            "type":"Transportation"
        }
    ],
    "sg:phone":"+1 713 650 6216",
    "sg:postcode":"77002",
    "sg:province":"TX",
    "wof:name":"Usaa Realty Company",
    "wof:placetype":"venue"
},
  "geometry": {"coordinates":[-95.364403,29.7575],"type":"Point"}
}