{
  "type": "Feature",
  "properties": {
    "iso:country":"US",
    "sg:address":"2550 Midway Rd",
    "sg:city":"Carrollton",
    "sg:classifiers":[
        {
            "category":"Professional",
            "subcategory":"Accounting & Tax Preparation",
            "type":"Services"
        }
    ],
    "sg:phone":"+1 972 250 2023",
    "sg:postcode":"75006",
    "sg:province":"TX",
    "sg:tags":[
        "billing"
    ],
    "wof:name":"Diversified Reimbursement Syst",
    "wof:placetype":"venue"
},
  "geometry": {"coordinates":[-96.842077,32.984009],"type":"Point"}
}