{
  "type": "Feature",
  "properties": {
    "iso:country":"US",
    "sg:address":"16227 Peach Bough Ln",
    "sg:city":"Houston",
    "sg:classifiers":[
        {
            "category":"Professional",
            "subcategory":"Art Services",
            "type":"Services"
        }
    ],
    "sg:phone":"+1 281 859 3645",
    "sg:postcode":"77095",
    "sg:province":"TX",
    "sg:tags":[
        "commercial",
        "design"
    ],
    "wof:name":"Holsome Publishing",
    "wof:placetype":"venue"
},
  "geometry": {"coordinates":[-95.65219500000001,29.891061],"type":"Point"}
}