{
  "type": "Feature",
  "properties": {
    "iso:country":"US",
    "sg:address":"2069 Hwy 1187",
    "sg:city":"Mansfield",
    "sg:classifiers":[
        {
            "category":"Manufacturing",
            "subcategory":"Tools & Machinery",
            "type":"Manufacturing & Wholesale Goods"
        }
    ],
    "sg:phone":"+1 817 473 8181",
    "sg:postcode":"76063",
    "sg:province":"TX",
    "sg:tags":[
        "machine",
        "shop"
    ],
    "wof:name":"Metro Gear",
    "wof:placetype":"venue"
},
  "geometry": {"coordinates":[-97.17643099999999,32.583766],"type":"Point"}
}