{
  "type": "Feature",
  "properties": {
    "iso:country":"US",
    "sg:address":"9208 N Royal Ln",
    "sg:city":"Irving",
    "sg:classifiers":[
        {
            "category":"Building & Trades",
            "subcategory":"Construction",
            "type":"Services"
        }
    ],
    "sg:phone":"+1 972 929 6440",
    "sg:postcode":"75063",
    "sg:province":"TX",
    "sg:tags":[
        "house"
    ],
    "wof:name":"Firesafe Homes",
    "wof:placetype":"venue"
},
  "geometry": {"coordinates":[-97.019791,32.931899],"type":"Point"}
}