{
  "type": "Feature",
  "properties": {
    "iso:country":"US",
    "sg:address":"5717 Creekridge Dr",
    "sg:city":"Arlington",
    "sg:classifiers":[
        {
            "category":"Professional",
            "type":"Services"
        }
    ],
    "sg:phone":"+1 817 467 9976",
    "sg:postcode":"76018",
    "sg:province":"TX",
    "wof:name":"Payson McCune",
    "wof:placetype":"venue"
},
  "geometry": {"coordinates":[-97.08604699999999,32.650275],"type":"Point"}
}