{
  "type": "Feature",
  "properties": {
    "iso:country":"US",
    "sg:address":"5065 Wagon Wheel Ave",
    "sg:city":"Abilene",
    "sg:classifiers":[
        {
            "category":"Wholesale",
            "subcategory":"Machinery & Supplies",
            "type":"Manufacturing & Wholesale Goods"
        }
    ],
    "sg:phone":"+1 325 698 8334",
    "sg:postcode":"79606",
    "sg:province":"TX",
    "sg:tags":[
        "industrial"
    ],
    "wof:name":"Grainger",
    "wof:placetype":"venue"
},
  "geometry": {"coordinates":[-99.78849099999999,32.359153],"type":"Point"}
}