{
  "type": "Feature",
  "properties": {
    "iso:country":"US",
    "sg:address":"16726 Town Glade Dr",
    "sg:city":"Cypress",
    "sg:classifiers":[
        {
            "category":"Retail",
            "subcategory":"Portrait Studio",
            "type":"Services"
        }
    ],
    "sg:phone":"+1 281 304 4255",
    "sg:postcode":"77429",
    "sg:province":"TX",
    "sg:tags":[
        "photo"
    ],
    "wof:name":"Proshots Photography & Digital",
    "wof:placetype":"venue"
},
  "geometry": {"coordinates":[-95.676333,29.980137],"type":"Point"}
}