{
  "type": "Feature",
  "properties": {
    "iso:country":"US",
    "sg:address":"3626 Airport Blvd",
    "sg:city":"Houston",
    "sg:classifiers":[
        {
            "category":"Wholesale",
            "subcategory":"Scrap",
            "type":"Manufacturing & Wholesale Goods"
        }
    ],
    "sg:phone":"+1 713 734 4901",
    "sg:postcode":"77051",
    "sg:province":"TX",
    "sg:tags":[
        "auto",
        "material",
        "parts",
        "used"
    ],
    "wof:name":"Airport & Smith Wrecking Yard",
    "wof:placetype":"venue"
},
  "geometry": {"coordinates":[-95.367436,29.645144],"type":"Point"}
}