{
  "type": "Feature",
  "properties": {
    "iso:country":"US",
    "sg:address":"6990 Killarney",
    "sg:city":"Beaumont",
    "sg:classifiers":[
        {
            "category":"Professional",
            "subcategory":"Business Services",
            "type":"Services"
        }
    ],
    "sg:phone":"+1 409 866 5656",
    "sg:postcode":"77706",
    "sg:province":"TX",
    "wof:name":"Broussard Inspections",
    "wof:placetype":"venue"
},
  "geometry": {"coordinates":[-94.184049,30.086233],"type":"Point"}
}