{
  "type": "Feature",
  "properties": {
    "iso:country":"US",
    "sg:address":"4828 Lp Central Dr",
    "sg:city":"Houston",
    "sg:classifiers":[
        {
            "category":"Organizations",
            "subcategory":"Membership Organization",
            "type":"Services"
        }
    ],
    "sg:phone":"+1 281 538 2666",
    "sg:postcode":"77081",
    "sg:province":"TX",
    "wof:name":"Rose Compass Community Assn",
    "wof:placetype":"venue"
},
  "geometry": {"coordinates":[-95.457227,29.724582],"type":"Point"}
}