{
  "type": "Feature",
  "properties": {
    "iso:country":"US",
    "sg:address":"2701 North Blvd",
    "sg:city":"Houston",
    "sg:classifiers":[
        {
            "category":"Real Estate",
            "subcategory":"Real Estate Operator",
            "type":"Services"
        }
    ],
    "sg:phone":"+1 713 524 3730",
    "sg:postcode":"77098",
    "sg:province":"TX",
    "sg:tags":[
        "apartment"
    ],
    "wof:name":"North Boulevard Apartments",
    "wof:placetype":"venue"
},
  "geometry": {"coordinates":[-95.41974399999999,29.727573],"type":"Point"}
}