{
  "type": "Feature",
  "properties": {
    "iso:country":"US",
    "sg:address":"3440 Independence Blvd",
    "sg:city":"Missouri City",
    "sg:classifiers":[
        {
            "category":"Education",
            "subcategory":"School",
            "type":"Public Place"
        }
    ],
    "sg:phone":"+1 281 634 9410",
    "sg:postcode":"77489",
    "sg:province":"TX",
    "sg:tags":[
        "elementary"
    ],
    "wof:name":"Fort Bend ISD Elementary School",
    "wof:placetype":"venue"
},
  "geometry": {"coordinates":[-95.534857,29.593118],"type":"Point"}
}