{
  "type": "Feature",
  "properties": {
    "iso:country":"US",
    "sg:address":"3333 Fannin St",
    "sg:city":"Houston",
    "sg:classifiers":[
        {
            "category":"Banks & Credit Unions",
            "subcategory":"Financial Services",
            "type":"Services"
        }
    ],
    "sg:phone":"+1 713 528 7100",
    "sg:postcode":"77004",
    "sg:province":"TX",
    "sg:tags":[
        "broker",
        "mortgage"
    ],
    "wof:name":"Premier",
    "wof:placetype":"venue"
},
  "geometry": {"coordinates":[-95.37674800000001,29.74011],"type":"Point"}
}