{
  "type": "Feature",
  "properties": {
    "iso:country":"US",
    "sg:address":"36 Lwsc Rd",
    "sg:city":"Sherman",
    "sg:classifiers":[
        {
            "category":"Utilities",
            "subcategory":"Water",
            "type":"Services"
        }
    ],
    "sg:phone":"+1 903 892 9084",
    "sg:postcode":"75090",
    "sg:province":"TX",
    "sg:tags":[
        "company-utility",
        "supply"
    ],
    "wof:name":"Luella Water Supplies Inc",
    "wof:placetype":"venue"
},
  "geometry": {"coordinates":[-96.54928,33.569486],"type":"Point"}
}