{
  "type": "Feature",
  "properties": {
    "iso:country":"US",
    "sg:address":"9673 Marbach Rd",
    "sg:city":"San Antonio",
    "sg:classifiers":[
        {
            "category":"Health Services",
            "subcategory":"Doctor",
            "type":"Services"
        }
    ],
    "sg:phone":"+1 210 675 8390",
    "sg:postcode":"78245",
    "sg:province":"TX",
    "sg:tags":[
        "physician",
        "surgeon",
        "medical"
    ],
    "wof:name":"Heritage Medical Clinic Inc",
    "wof:placetype":"venue"
},
  "geometry": {"coordinates":[-98.676045,29.417912],"type":"Point"}
}