{
  "type": "Feature",
  "properties": {
    "iso:country":"US",
    "sg:address":"2260 State Hwy 154",
    "sg:city":"Gilmer",
    "sg:classifiers":[
        {
            "category":"Professional",
            "subcategory":"Business Services",
            "type":"Services"
        }
    ],
    "sg:phone":"+1 903 797 2557",
    "sg:postcode":"75645",
    "sg:province":"TX",
    "sg:tags":[
        "appraiser"
    ],
    "wof:name":"Player Appraisers",
    "wof:placetype":"venue"
},
  "geometry": {"coordinates":[-94.90803200000001,32.721087],"type":"Point"}
}