{
  "type": "Feature",
  "properties": {
    "iso:country":"US",
    "sg:address":"2418 Runneburg Rd",
    "sg:city":"Crosby",
    "sg:phone":"+1 281 328 2802",
    "sg:postcode":"77532",
    "sg:province":"TX",
    "sg:tags":[
        "farm",
        "field",
        "crop"
    ],
    "wof:name":"Kenneth Fielder",
    "wof:placetype":"venue"
},
  "geometry": {"coordinates":[-95.028217,29.911349],"type":"Point"}
}