{
  "type": "Feature",
  "properties": {
    "iso:country":"US",
    "sg:address":"1133 N Shoreline Blvd",
    "sg:city":"Corpus Christi",
    "sg:classifiers":[
        {
            "category":"Professional",
            "subcategory":"Management & Consulting",
            "type":"Services"
        }
    ],
    "sg:phone":"+1 361 881 8484",
    "sg:postcode":"78401",
    "sg:province":"TX",
    "sg:tags":[
        "consultant",
        "security",
        "system"
    ],
    "wof:name":"Security Consultants Group",
    "wof:placetype":"venue"
},
  "geometry": {"coordinates":[-97.392,27.802137],"type":"Point"}
}