{
  "type": "Feature",
  "properties": {
    "iso:country":"US",
    "sg:address":"1702 Amazon Dr",
    "sg:city":"Corpus Christi",
    "sg:classifiers":[
        {
            "category":"Professional",
            "subcategory":"Business Services",
            "type":"Services"
        }
    ],
    "sg:phone":"+1 361 992 2173",
    "sg:postcode":"78412",
    "sg:province":"TX",
    "wof:name":"M E Bean",
    "wof:placetype":"venue"
},
  "geometry": {"coordinates":[-97.349729,27.689846],"type":"Point"}
}