{
  "type": "Feature",
  "properties": {
    "iso:country":"US",
    "sg:address":"721 S Mesa St",
    "sg:city":"El Paso",
    "sg:classifiers":[
        {
            "category":"Government",
            "subcategory":"Office",
            "type":"Public Place"
        }
    ],
    "sg:phone":"+1 915 534 2533",
    "sg:postcode":"79901",
    "sg:province":"TX",
    "sg:tags":[
        "city",
        "program",
        "health"
    ],
    "wof:name":"Henderson Health Clinic",
    "wof:placetype":"venue"
},
  "geometry": {"coordinates":[-106.48512599999999,31.752281],"type":"Point"}
}