{
  "type": "Feature",
  "properties": {
    "iso:country":"US",
    "sg:address":"13221 NW Military Hwy",
    "sg:city":"San Antonio",
    "sg:classifiers":[
        {
            "category":"Health Services",
            "subcategory":"Doctor",
            "type":"Services"
        }
    ],
    "sg:phone":"+1 210 492 5668",
    "sg:postcode":"78231",
    "sg:province":"TX",
    "sg:tags":[
        "dentist"
    ],
    "wof:name":"Jon P Oefinger DDS",
    "wof:placetype":"venue"
},
  "geometry": {"coordinates":[-98.539186,29.565758],"type":"Point"}
}