{
  "type": "Feature",
  "properties": {
    "iso:country":"US",
    "sg:address":"13532 Co Rd 4122",
    "sg:city":"Lindale",
    "sg:classifiers":[
        {
            "category":"Building & Trades",
            "subcategory":"Construction",
            "type":"Services"
        }
    ],
    "sg:phone":"+1 903 882 1102",
    "sg:postcode":"75771",
    "sg:province":"TX",
    "sg:tags":[
        "elevator"
    ],
    "wof:name":"Tex-Chec Overhead Crane Svc",
    "wof:placetype":"venue"
},
  "geometry": {"coordinates":[-95.38965899999999,32.565818],"type":"Point"}
}