{
  "type": "Feature",
  "properties": {
    "iso:country":"US",
    "sg:address":"5246 Blanco Rd",
    "sg:city":"San Antonio",
    "sg:classifiers":[
        {
            "category":"Professional",
            "type":"Services"
        }
    ],
    "sg:phone":"+1 210 341 0966",
    "sg:postcode":"78216",
    "sg:province":"TX",
    "sg:tags":[
        "establishment"
    ],
    "wof:name":"Roseland Bingo",
    "wof:placetype":"venue"
},
  "geometry": {"coordinates":[-98.50774199999999,29.498535],"type":"Point"}
}