{
  "type": "Feature",
  "properties": {
    "iso:country":"US",
    "sg:address":"100 N Walnut Creek Dr",
    "sg:city":"Mansfield",
    "sg:classifiers":[
        {
            "category":"Professional",
            "subcategory":"Management & Consulting",
            "type":"Services"
        }
    ],
    "sg:phone":"+1 817 453 0045",
    "sg:postcode":"76063",
    "sg:province":"TX",
    "sg:tags":[
        "environmental"
    ],
    "wof:name":"Rio Vista Environmental Svc",
    "wof:placetype":"venue"
},
  "geometry": {"coordinates":[-97.134992,32.56369],"type":"Point"}
}