{
  "type": "Feature",
  "properties": {
    "iso:country":"US",
    "sg:address":"5206 Mckinney Ave",
    "sg:city":"Dallas",
    "sg:classifiers":[
        {
            "category":"Health Services",
            "subcategory":"Hospital",
            "type":"Services"
        },
        {
            "category":"Health Services",
            "subcategory":"Health Practitioner",
            "type":"Services"
        }
    ],
    "sg:phone":"+1 214 521 8483",
    "sg:postcode":"75205",
    "sg:province":"TX",
    "sg:tags":[
        "holistic",
        "sleep",
        "treatment",
        "disorders-information"
    ],
    "wof:name":"From My Garden",
    "wof:placetype":"venue"
},
  "geometry": {"coordinates":[-96.78343599999999,32.829677],"type":"Point"}
}