{
  "type": "Feature",
  "properties": {
    "iso:country":"US",
    "sg:address":"816 Clover Park Dr",
    "sg:city":"Arlington",
    "sg:classifiers":[
        {
            "category":"Health Services",
            "subcategory":"Clinic",
            "type":"Services"
        }
    ],
    "sg:phone":"+1 817 548 9353",
    "sg:postcode":"76013",
    "sg:province":"TX",
    "sg:tags":[
        "retardation",
        "home",
        "group",
        "mental"
    ],
    "wof:name":"Clover Park Residence",
    "wof:placetype":"venue"
},
  "geometry": {"coordinates":[-97.14312,32.724389],"type":"Point"}
}