{
  "type": "Feature",
  "properties": {
    "iso:country":"US",
    "sg:address":"5200 Roundrock Trl",
    "sg:city":"Plano",
    "sg:classifiers":[
        {
            "category":"Professional",
            "subcategory":"Business Services",
            "type":"Services"
        }
    ],
    "sg:phone":"+1 972 519 9508",
    "sg:postcode":"75023",
    "sg:province":"TX",
    "sg:tags":[
        "transcribing",
        "disc"
    ],
    "wof:name":"Medproserve",
    "wof:placetype":"venue"
},
  "geometry": {"coordinates":[-96.74485900000001,33.053084],"type":"Point"}
}