{
  "type": "Feature",
  "properties": {
    "iso:country":"US",
    "sg:address":"303 Central Ave",
    "sg:city":"Sonora",
    "sg:classifiers":[
        {
            "category":"Professional",
            "type":"Services"
        }
    ],
    "sg:phone":"+1 325 387 9607",
    "sg:postcode":"76950",
    "sg:province":"TX",
    "wof:name":"Zare",
    "wof:placetype":"venue"
},
  "geometry": {"coordinates":[-100.648523,30.556889],"type":"Point"}
}