{
  "type": "Feature",
  "properties": {
    "iso:country":"US",
    "sg:address":"128 Grape St",
    "sg:city":"Abilene",
    "sg:classifiers":[
        {
            "category":"Professional",
            "subcategory":"Accounting & Tax Preparation",
            "type":"Services"
        }
    ],
    "sg:phone":"+1 325 672 4405",
    "sg:postcode":"79601",
    "sg:province":"TX",
    "sg:tags":[
        "return",
        "filing"
    ],
    "wof:name":"Profit Income Tax",
    "wof:placetype":"venue"
},
  "geometry": {"coordinates":[-99.741675,32.450768],"type":"Point"}
}