{
  "type": "Feature",
  "properties": {
    "iso:country":"US",
    "sg:address":"4506 Medinah Pl",
    "sg:city":"Bellaire",
    "sg:classifiers":[
        {
            "category":"Personal",
            "type":"Services"
        }
    ],
    "sg:phone":"+1 713 665 0073",
    "sg:postcode":"77401",
    "sg:province":"TX",
    "wof:name":"Title By Marti",
    "wof:placetype":"venue"
},
  "geometry": {"coordinates":[-95.45181100000001,29.717228],"type":"Point"}
}