{
  "type": "Feature",
  "properties": {
    "iso:country":"US",
    "sg:address":"7650 S Will Rogers Blvd",
    "sg:city":"Fort Worth",
    "sg:classifiers":[
        {
            "category":"Wholesale",
            "subcategory":"Groceries",
            "type":"Manufacturing & Wholesale Goods"
        }
    ],
    "sg:phone":"+1 817 654 3663",
    "sg:postcode":"76140",
    "sg:province":"TX",
    "sg:tags":[
        "food",
        "broker"
    ],
    "wof:name":"Ben E Keith Co",
    "wof:placetype":"venue"
},
  "geometry": {"coordinates":[-97.31295299999999,32.638751],"type":"Point"}
}