{
  "type": "Feature",
  "properties": {
    "iso:country":"US",
    "sg:address":"5012 Hopper Rd",
    "sg:city":"Houston",
    "sg:classifiers":[
        {
            "category":"Retail",
            "subcategory":"Auto Repair",
            "type":"Services"
        }
    ],
    "sg:phone":"+1 281 442 5325",
    "sg:postcode":"77093",
    "sg:province":"TX",
    "sg:tags":[
        "repairing",
        "automobile"
    ],
    "wof:name":"Hopper Road Auto Repair",
    "wof:placetype":"venue"
},
  "geometry": {"coordinates":[-95.315952,29.879381],"type":"Point"}
}