{
  "type": "Feature",
  "properties": {
    "iso:country":"US",
    "sg:address":"3500 Alameda Ave",
    "sg:city":"El Paso",
    "sg:classifiers":[
        {
            "category":"Manufacturing",
            "subcategory":"Tools & Machinery",
            "type":"Manufacturing & Wholesale Goods"
        }
    ],
    "sg:phone":"+1 915 542 3863",
    "sg:postcode":"79905",
    "sg:province":"TX",
    "sg:tags":[
        "pump"
    ],
    "wof:name":"Texas Water Pump Mfrs",
    "wof:placetype":"venue"
},
  "geometry": {"coordinates":[-106.450924,31.773335],"type":"Point"}
}