{
  "type": "Feature",
  "properties": {
    "iso:country":"US",
    "sg:address":"6905 Lake Jackson Dr",
    "sg:city":"Arlington",
    "sg:classifiers":[
        {
            "category":"Professional",
            "subcategory":"Business Services",
            "type":"Services"
        }
    ],
    "sg:phone":"+1 817 468 8190",
    "sg:postcode":"76002",
    "sg:province":"TX",
    "wof:name":"Olide Enterprise Service",
    "wof:placetype":"venue"
},
  "geometry": {"coordinates":[-97.079365,32.629487],"type":"Point"}
}