{
  "type": "Feature",
  "properties": {
    "iso:country":"US",
    "sg:address":"2114 W Commerce St",
    "sg:city":"San Antonio",
    "sg:classifiers":[
        {
            "category":"Home & Garden",
            "subcategory":"Building Materials",
            "type":"Retail Goods"
        }
    ],
    "sg:phone":"+1 210 227 4798",
    "sg:postcode":"78207",
    "sg:province":"TX",
    "wof:name":"Marco Paint Supply",
    "wof:placetype":"venue"
},
  "geometry": {"coordinates":[-98.518807,29.427316],"type":"Point"}
}