{
  "type": "Feature",
  "properties": {
    "iso:country":"US",
    "sg:address":"1027 Oaklands Dr",
    "sg:city":"Round Rock",
    "sg:classifiers":[
        {
            "category":"Restaurant",
            "type":"Food & Drink"
        }
    ],
    "sg:phone":"+1 512 341 8368",
    "sg:postcode":"78681",
    "sg:province":"TX",
    "sg:tags":[
        "eating"
    ],
    "wof:name":"Chef Du Jour",
    "wof:placetype":"venue"
},
  "geometry": {"coordinates":[-97.715915,30.518251],"type":"Point"}
}