{
  "type": "Feature",
  "properties": {
    "iso:country":"US",
    "sg:address":"2704 Colonial Cir",
    "sg:city":"Mc Kinney",
    "sg:classifiers":[
        {
            "category":"Professional",
            "subcategory":"Management & Consulting",
            "type":"Services"
        }
    ],
    "sg:phone":"+1 972 548 0487",
    "sg:postcode":"75070",
    "sg:province":"TX",
    "wof:name":"Creative Solutions Plus",
    "wof:placetype":"venue"
},
  "geometry": {"coordinates":[-96.650235,33.174341],"type":"Point"}
}