{
  "type": "Feature",
  "properties": {
    "iso:country":"US",
    "sg:address":"1335 Edenderry Ln",
    "sg:city":"Missouri City",
    "sg:classifiers":[
        {
            "category":"Wholesale",
            "subcategory":"Durable Goods & Equipment",
            "type":"Manufacturing & Wholesale Goods"
        }
    ],
    "sg:phone":"+1 281 499 8729",
    "sg:postcode":"77459",
    "sg:province":"TX",
    "wof:name":"Mamtech Supply Co",
    "wof:placetype":"venue"
},
  "geometry": {"coordinates":[-95.575405,29.599871],"type":"Point"}
}