{
  "type": "Feature",
  "properties": {
    "iso:country":"US",
    "sg:address":"1021 N Main St",
    "sg:city":"Pearland",
    "sg:classifiers":[
        {
            "category":"Building & Trades",
            "subcategory":"Construction",
            "type":"Services"
        }
    ],
    "sg:phone":"+1 281 485 2791",
    "sg:postcode":"77581",
    "sg:province":"TX",
    "sg:tags":[
        "contractor"
    ],
    "wof:name":"Bell Bottom Foundation Co",
    "wof:placetype":"venue"
},
  "geometry": {"coordinates":[-95.28649900000001,29.594999],"type":"Point"}
}