{
  "type": "Feature",
  "properties": {
    "iso:country":"US",
    "sg:address":"1641 Co Rd 266",
    "sg:city":"Mc Kinney",
    "sg:classifiers":[
        {
            "category":"Building & Trades",
            "subcategory":"Construction",
            "type":"Services"
        }
    ],
    "sg:phone":"+1 214 544 1640",
    "sg:postcode":"75069",
    "sg:province":"TX",
    "sg:tags":[
        "home",
        "builder"
    ],
    "wof:name":"Us Homes",
    "wof:placetype":"venue"
},
  "geometry": {"coordinates":[-96.58611999999999,33.135134],"type":"Point"}
}