{
  "type": "Feature",
  "properties": {
    "iso:country":"US",
    "sg:address":"3400 S Western St",
    "sg:city":"Amarillo",
    "sg:classifiers":[
        {
            "category":"Food & Beverages",
            "subcategory":"Groceries & Convenience Stores",
            "type":"Retail Goods"
        }
    ],
    "sg:phone":"+1 806 356 9866",
    "sg:postcode":"79109",
    "sg:province":"TX",
    "sg:tags":[
        "grocer"
    ],
    "wof:name":"Pak-A-Sak",
    "wof:placetype":"venue"
},
  "geometry": {"coordinates":[-101.883957,35.175501],"type":"Point"}
}