{
  "type": "Feature",
  "properties": {
    "iso:country":"US",
    "sg:address":"10244 FM 1346",
    "sg:city":"Adkins",
    "sg:classifiers":[
        {
            "category":"Education",
            "subcategory":"Special Training",
            "type":"Public Place"
        }
    ],
    "sg:phone":"+1 210 667 9714",
    "sg:postcode":"78101",
    "sg:province":"TX",
    "sg:tags":[
        "aircraft",
        "school"
    ],
    "wof:name":"Adkins Flite Ctr Inc",
    "wof:placetype":"venue"
},
  "geometry": {"coordinates":[-98.295056,29.421429],"type":"Point"}
}