{
  "type": "Feature",
  "properties": {
    "iso:country":"US",
    "sg:address":"8123 Comanche Pass",
    "sg:city":"Converse",
    "sg:classifiers":[
        {
            "category":"Professional",
            "type":"Services"
        }
    ],
    "sg:phone":"+1 210 659 3758",
    "sg:postcode":"78109",
    "sg:province":"TX",
    "wof:name":"Wings Remote Aerial Svc",
    "wof:placetype":"venue"
},
  "geometry": {"coordinates":[-98.329341,29.528042],"type":"Point"}
}