{
  "type": "Feature",
  "properties": {
    "iso:country":"US",
    "sg:address":"2002 Bevington Oaks Cir",
    "sg:city":"Katy",
    "sg:classifiers":[
        {
            "category":"Wholesale",
            "subcategory":"Machinery & Supplies",
            "type":"Manufacturing & Wholesale Goods"
        }
    ],
    "sg:phone":"+1 281 599 9992",
    "sg:postcode":"77450",
    "sg:province":"TX",
    "sg:tags":[
        "spare",
        "equipment",
        "industrial",
        "pa",
        "electric"
    ],
    "wof:name":"Klp International Inc",
    "wof:placetype":"venue"
},
  "geometry": {"coordinates":[-95.749291,29.752409],"type":"Point"}
}