{
  "type": "Feature",
  "properties": {
    "iso:country":"US",
    "sg:address":"4103 Brisbane St",
    "sg:city":"Houston",
    "sg:classifiers":[
        {
            "category":"Professional",
            "subcategory":"Business Services",
            "type":"Services"
        },
        {
            "category":"Organizations",
            "subcategory":"Membership Organization",
            "type":"Services"
        }
    ],
    "sg:phone":"+1 713 738 8016",
    "sg:postcode":"77047",
    "sg:province":"TX",
    "sg:tags":[
        "environmental",
        "product",
        "conservation",
        "ecological"
    ],
    "wof:name":"Nature Heritage Society",
    "wof:placetype":"venue"
},
  "geometry": {"coordinates":[-95.36320600000001,29.63776],"type":"Point"}
}