{
  "type": "Feature",
  "properties": {
    "iso:country":"US",
    "sg:address":"6806 New York St",
    "sg:city":"Houston",
    "sg:classifiers":[
        {
            "category":"Bars & Pubs",
            "type":"Food & Drink"
        }
    ],
    "sg:phone":"+1 713 748 1452",
    "sg:postcode":"77021",
    "sg:province":"TX",
    "sg:tags":[
        "club",
        "night"
    ],
    "wof:name":"Dillard Van's Lounge",
    "wof:placetype":"venue"
},
  "geometry": {"coordinates":[-95.352599,29.687753],"type":"Point"}
}