{
  "type": "Feature",
  "properties": {
    "iso:country":"US",
    "sg:address":"133 Glen Haven Dr",
    "sg:city":"Azle",
    "sg:classifiers":[
        {
            "category":"Building & Trades",
            "subcategory":"Plumbing",
            "type":"Services"
        }
    ],
    "sg:phone":"+1 817 237 6925",
    "sg:postcode":"76020",
    "sg:province":"TX",
    "sg:tags":[
        "plumbing",
        "contractor"
    ],
    "wof:name":"Moonlighting Master Plumber",
    "wof:placetype":"venue"
},
  "geometry": {"coordinates":[-97.53094900000001,32.879533],"type":"Point"}
}