{
  "type": "Feature",
  "properties": {
    "iso:country":"US",
    "sg:address":"5635 Alpha Rd",
    "sg:city":"Dallas",
    "sg:classifiers":[
        {
            "category":"Restaurant",
            "type":"Food & Drink"
        }
    ],
    "sg:phone":"+1 972 960 7691",
    "sg:postcode":"75240",
    "sg:province":"TX",
    "sg:tags":[
        "eating"
    ],
    "wof:name":"Alpha Chinese Restaurant",
    "wof:placetype":"venue"
},
  "geometry": {"coordinates":[-96.8095,32.932951],"type":"Point"}
}