{
  "type": "Feature",
  "properties": {
    "iso:country":"US",
    "sg:address":"7000 Braes Blvd",
    "sg:city":"Houston",
    "sg:classifiers":[
        {
            "category":"Education",
            "subcategory":"School",
            "type":"Public Place"
        }
    ],
    "sg:phone":"+1 713 295 5240",
    "sg:postcode":"77025",
    "sg:province":"TX",
    "sg:tags":[
        "high",
        "middle",
        "elementary"
    ],
    "wof:name":"Houston Independent School District",
    "wof:placetype":"venue"
},
  "geometry": {"coordinates":[-95.437307,29.702809],"type":"Point"}
}