{
  "type": "Feature",
  "properties": {
    "iso:country":"US",
    "sg:address":"3605 NE Loop 286",
    "sg:city":"Paris",
    "sg:classifiers":[
        {
            "category":"Banks & Credit Unions",
            "subcategory":"Bank",
            "type":"Services"
        }
    ],
    "sg:phone":"+1 903 784 6658",
    "sg:postcode":"75460",
    "sg:province":"TX",
    "sg:tags":[
        "mortgage"
    ],
    "wof:name":"Curtis Mortgage",
    "wof:placetype":"venue"
},
  "geometry": {"coordinates":[-95.510463,33.664913],"type":"Point"}
}