{
  "type": "Feature",
  "properties": {
    "iso:country":"US",
    "sg:address":"1525 4th St",
    "sg:city":"Graham",
    "sg:classifiers":[
        {
            "category":"Shopping",
            "subcategory":"Used Merchandise",
            "type":"Retail Goods"
        }
    ],
    "sg:phone":"+1 940 549 6054",
    "sg:postcode":"76450",
    "sg:province":"TX",
    "wof:name":"Hidden Treasure",
    "wof:placetype":"venue"
},
  "geometry": {"coordinates":[-98.567593,33.108485],"type":"Point"}
}