{
  "type": "Feature",
  "properties": {
    "iso:country":"US",
    "sg:address":"219 Kelly Brook Ln",
    "sg:city":"Weatherford",
    "sg:classifiers":[
        {
            "category":"Building & Trades",
            "subcategory":"Cleaning & Sanitation",
            "type":"Services"
        }
    ],
    "sg:phone":"+1 817 594 9866",
    "sg:postcode":"76087",
    "sg:province":"TX",
    "sg:tags":[
        "maintenance"
    ],
    "wof:name":"Parker County Chimney Sweep",
    "wof:placetype":"venue"
},
  "geometry": {"coordinates":[-97.780359,32.678236],"type":"Point"}
}