{
  "type": "Feature",
  "properties": {
    "iso:country":"US",
    "sg:address":"130 Col Etheredge Blvd",
    "sg:city":"Huntsville",
    "sg:classifiers":[
        {
            "category":"Restaurant",
            "type":"Food & Drink"
        }
    ],
    "sg:menulink":"http://www.allmenus.com/tx/huntsville/93976-schlotzskys/menu/",
    "sg:phone":"+1 936 293 1900",
    "sg:postcode":"77340",
    "sg:province":"TX",
    "sg:tags":[
        "wrap",
        "american",
        "sandwich",
        "pizza"
    ],
    "wof:name":"Schlotzsky's",
    "wof:placetype":"venue"
},
  "geometry": {"coordinates":[-95.57653000000001,30.714127],"type":"Point"}
}