{
  "type": "Feature",
  "properties": {
    "iso:country":"US",
    "sg:address":"2605 US Hwy 59",
    "sg:city":"Lufkin",
    "sg:classifiers":[
        {
            "category":"Professional",
            "type":"Services"
        }
    ],
    "sg:phone":"+1 936 633 7480",
    "sg:postcode":"75901",
    "sg:province":"TX",
    "sg:tags":[
        "establishment"
    ],
    "wof:name":"Angelina Transition",
    "wof:placetype":"venue"
},
  "geometry": {"coordinates":[-94.728424,31.294549],"type":"Point"}
}