{
  "type": "Feature",
  "properties": {
    "iso:country":"US",
    "sg:address":"751 W Main St",
    "sg:city":"Lewisville",
    "sg:classifiers":[
        {
            "category":"Utilities",
            "subcategory":"Mobile Phone",
            "type":"Services"
        }
    ],
    "sg:phone":"+1 214 222 8026",
    "sg:postcode":"75067",
    "sg:province":"TX",
    "sg:tags":[
        "telephone",
        "cellular"
    ],
    "wof:name":"Radio Shack",
    "wof:placetype":"venue"
},
  "geometry": {"coordinates":[-97.011151,33.046273],"type":"Point"}
}