{
  "type": "Feature",
  "properties": {
    "iso:country":"US",
    "sg:address":"7642 Presidio Sands",
    "sg:city":"Boerne",
    "sg:classifiers":[
        {
            "category":"Professional",
            "subcategory":"Lawyer & Legal Services",
            "type":"Services"
        }
    ],
    "sg:phone":"+1 210 698 9189",
    "sg:postcode":"78015",
    "sg:province":"TX",
    "sg:tags":[
        "attorney",
        "practice"
    ],
    "wof:name":"Taylor Kohm Attorney At Law Pc",
    "wof:placetype":"venue"
},
  "geometry": {"coordinates":[-98.635626,29.683782],"type":"Point"}
}