{
  "type": "Feature",
  "properties": {
    "iso:country":"US",
    "sg:address":"1025 China St",
    "sg:city":"Abilene",
    "sg:classifiers":[
        {
            "category":"Manufacturing",
            "subcategory":"Pet Food",
            "type":"Manufacturing & Wholesale Goods"
        }
    ],
    "sg:phone":"+1 325 672 3271",
    "sg:postcode":"79602",
    "sg:province":"TX",
    "sg:tags":[
        "feed",
        "plant"
    ],
    "wof:name":"Cargill Incorporated",
    "wof:placetype":"venue"
},
  "geometry": {"coordinates":[-99.727307,32.437202],"type":"Point"}
}