{
  "type": "Feature",
  "properties": {
    "iso:country":"US",
    "sg:address":"515 Spr 100",
    "sg:city":"Kerrville",
    "sg:classifiers":[
        {
            "category":"Organizations",
            "subcategory":"Membership Organization",
            "type":"Services"
        }
    ],
    "sg:phone":"+1 830 257 4500",
    "sg:postcode":"78028",
    "sg:province":"TX",
    "sg:tags":[
        "society",
        "humane"
    ],
    "wof:name":"Freeman Fritts Amimal Shelter",
    "wof:placetype":"venue"
},
  "geometry": {"coordinates":[-99.107253,30.0307],"type":"Point"}
}