{
  "type": "Feature",
  "properties": {
    "iso:country":"US",
    "sg:address":"1102 Howard Dr",
    "sg:city":"Deer Park",
    "sg:classifiers":[
        {
            "category":"Personal",
            "type":"Services"
        }
    ],
    "sg:phone":"+1 281 817 5804",
    "sg:postcode":"77536",
    "sg:province":"TX",
    "sg:tags":[
        "mover"
    ],
    "wof:name":"Deer Park Moving",
    "wof:placetype":"venue"
},
  "geometry": {"coordinates":[-95.132766,29.707055],"type":"Point"}
}