{
  "type": "Feature",
  "properties": {
    "iso:country":"US",
    "sg:address":"514 Shadberry Dr",
    "sg:city":"Magnolia",
    "sg:classifiers":[
        {
            "category":"Retail",
            "subcategory":"Auto Repair",
            "type":"Services"
        }
    ],
    "sg:phone":"+1 936 271 0857",
    "sg:postcode":"77354",
    "sg:province":"TX",
    "sg:tags":[
        "automotive"
    ],
    "wof:name":"Dolbee Towing & Recovery",
    "wof:placetype":"venue"
},
  "geometry": {"coordinates":[-95.549836,30.236206],"type":"Point"}
}