{
  "type": "Feature",
  "properties": {
    "iso:country":"US",
    "sg:address":"15416 Esther Dr",
    "sg:city":"Conroe",
    "sg:classifiers":[
        {
            "category":"Retail",
            "subcategory":"Auto Repair",
            "type":"Services"
        }
    ],
    "sg:phone":"+1 936 321 0107",
    "sg:postcode":"77384",
    "sg:province":"TX",
    "sg:tags":[
        "body"
    ],
    "wof:name":"Supercar Restoration & Repair",
    "wof:placetype":"venue"
},
  "geometry": {"coordinates":[-95.514601,30.235268],"type":"Point"}
}