{
  "type": "Feature",
  "properties": {
    "iso:country":"US",
    "sg:address":"2106 W Gentry Pkwy",
    "sg:city":"Tyler",
    "sg:classifiers":[
        {
            "category":"Insurance",
            "subcategory":"Insurance Agent",
            "type":"Services"
        }
    ],
    "sg:phone":"+1 903 595 2886",
    "sg:postcode":"75702",
    "sg:province":"TX",
    "wof:name":"Nationwide",
    "wof:placetype":"venue"
},
  "geometry": {"coordinates":[-95.32380499999999,32.365338],"type":"Point"}
}