{
  "type": "Feature",
  "properties": {
    "iso:country":"US",
    "sg:address":"915 S Jupiter Rd",
    "sg:city":"Garland",
    "sg:classifiers":[
        {
            "category":"Manufacturing",
            "subcategory":"Tools & Machinery",
            "type":"Manufacturing & Wholesale Goods"
        }
    ],
    "sg:phone":"+1 972 272 6631",
    "sg:postcode":"75042",
    "sg:province":"TX",
    "sg:tags":[
        "computer",
        "storage",
        "enclosure",
        "devices"
    ],
    "wof:name":"Rackmount Solutions Ltd",
    "wof:placetype":"venue"
},
  "geometry": {"coordinates":[-96.683126,32.90184],"type":"Point"}
}