{
  "type": "Feature",
  "properties": {
    "iso:country":"US",
    "sg:address":"3001 58th St",
    "sg:city":"Lubbock",
    "sg:classifiers":[
        {
            "category":"Building & Trades",
            "subcategory":"Landscaping Services",
            "type":"Services"
        }
    ],
    "sg:phone":"+1 806 791 2016",
    "sg:postcode":"79413",
    "sg:province":"TX",
    "wof:name":"Ultra-Care",
    "wof:placetype":"venue"
},
  "geometry": {"coordinates":[-101.880279,33.541243],"type":"Point"}
}