{
  "type": "Feature",
  "properties": {
    "iso:country":"US",
    "sg:address":"7826 Galleon Field Ln",
    "sg:city":"Cypress",
    "sg:classifiers":[
        {
            "category":"Wholesale",
            "subcategory":"Non-durable Goods",
            "type":"Manufacturing & Wholesale Goods"
        }
    ],
    "sg:phone":"+1 281 304 2694",
    "sg:postcode":"77433",
    "sg:province":"TX",
    "sg:tags":[
        "dry",
        "goods-wholesale"
    ],
    "wof:name":"Ivey Kadeen",
    "wof:placetype":"venue"
},
  "geometry": {"coordinates":[-95.706884,29.890359],"type":"Point"}
}