{
  "type": "Feature",
  "properties": {
    "iso:country":"US",
    "sg:address":"211 Latham St",
    "sg:city":"Houston",
    "sg:classifiers":[
        {
            "category":"Professional",
            "type":"Services"
        }
    ],
    "sg:phone":"+1 713 921 1319",
    "sg:postcode":"77011",
    "sg:province":"TX",
    "wof:name":"Rh Frame Body & Mechanic",
    "wof:placetype":"venue"
},
  "geometry": {"coordinates":[-95.31944799999999,29.741074],"type":"Point"}
}