{
  "type": "Feature",
  "properties": {
    "iso:country":"US",
    "sg:address":"419 N Carroll Blvd",
    "sg:city":"Denton",
    "sg:classifiers":[
        {
            "category":"Professional",
            "subcategory":"Accounting & Tax Preparation",
            "type":"Services"
        }
    ],
    "sg:phone":"+1 940 387 6174",
    "sg:postcode":"76201",
    "sg:province":"TX",
    "sg:tags":[
        "accountant"
    ],
    "wof:name":"Leroy Howe & Co",
    "wof:placetype":"venue"
},
  "geometry": {"coordinates":[-97.137326,33.218049],"type":"Point"}
}