{
  "type": "Feature",
  "properties": {
    "iso:country":"US",
    "sg:address":"200 E Mildred Ln",
    "sg:city":"Fort Worth",
    "sg:classifiers":[
        {
            "category":"Organizations",
            "subcategory":"Religious Organization",
            "type":"Services"
        }
    ],
    "sg:phone":"+1 817 249 9393",
    "sg:postcode":"76126",
    "sg:province":"TX",
    "sg:tags":[
        "church"
    ],
    "wof:name":"Korean Central Church",
    "wof:placetype":"venue"
},
  "geometry": {"coordinates":[-97.465203,32.67084],"type":"Point"}
}