{
  "type": "Feature",
  "properties": {
    "iso:country":"US",
    "sg:address":"14819 Irene",
    "sg:city":"Houston",
    "sg:classifiers":[
        {
            "category":"Wholesale",
            "subcategory":"Farm Supplies",
            "type":"Manufacturing & Wholesale Goods"
        }
    ],
    "sg:phone":"+1 713 729 9099",
    "sg:postcode":"77085",
    "sg:province":"TX",
    "wof:name":"Drop Dead Pest & Bee Control",
    "wof:placetype":"venue"
},
  "geometry": {"coordinates":[-95.50985,29.627583],"type":"Point"}
}