{
  "type": "Feature",
  "properties": {
    "iso:country":"US",
    "sg:address":"1600 E Elizabeth St",
    "sg:city":"Brownsville",
    "sg:classifiers":[
        {
            "category":"Organizations",
            "subcategory":"Professional Association",
            "type":"Services"
        }
    ],
    "sg:phone":"+1 956 542 4341",
    "sg:postcode":"78520",
    "sg:province":"TX",
    "sg:tags":[
        "chambers",
        "executive",
        "business",
        "commerce"
    ],
    "sg:website":"www.brownsvillechamber.com",
    "wof:name":"Brownsville Chamber of Commrce",
    "wof:placetype":"venue"
},
  "geometry": {"coordinates":[-97.494489,25.898006],"type":"Point"}
}