{
  "type": "Feature",
  "properties": {
    "iso:country":"US",
    "sg:address":"2301 State Hwy 46",
    "sg:city":"Seguin",
    "sg:classifiers":[
        {
            "category":"Building & Trades",
            "subcategory":"Construction",
            "type":"Services"
        }
    ],
    "sg:phone":"+1 830 386 2980",
    "sg:postcode":"78155",
    "sg:province":"TX",
    "wof:name":"Centex Manufactured Housing",
    "wof:placetype":"venue"
},
  "geometry": {"coordinates":[-97.988978,29.54561],"type":"Point"}
}