{
  "type": "Feature",
  "properties": {
    "iso:country":"US",
    "sg:address":"5631 Dyer St",
    "sg:city":"El Paso",
    "sg:classifiers":[
        {
            "category":"Shopping",
            "type":"Retail Goods"
        },
        {
            "category":"Wholesale",
            "subcategory":"Electrical",
            "type":"Manufacturing & Wholesale Goods"
        }
    ],
    "sg:phone":"+1 915 564 5226",
    "sg:postcode":"79904",
    "sg:province":"TX",
    "sg:tags":[
        "radio",
        "pager",
        "telephone"
    ],
    "wof:name":"King's Telephone Plus",
    "wof:placetype":"venue"
},
  "geometry": {"coordinates":[-106.44516400000001,31.829036],"type":"Point"}
}