{
  "type": "Feature",
  "properties": {
    "iso:country":"US",
    "sg:address":"109 N Oak St",
    "sg:city":"Roanoke",
    "sg:classifiers":[
        {
            "category":"Home & Garden",
            "subcategory":"Furniture",
            "type":"Retail Goods"
        }
    ],
    "sg:phone":"+1 682 831 9619",
    "sg:postcode":"76262",
    "sg:province":"TX",
    "wof:name":"Andrews Home Furnishing",
    "wof:placetype":"venue"
},
  "geometry": {"coordinates":[-97.22925600000001,32.998794],"type":"Point"}
}