{
  "type": "Feature",
  "properties": {
    "iso:country":"US",
    "sg:address":"2626 Indian Trail Dr",
    "sg:city":"Missouri City",
    "sg:classifiers":[
        {
            "category":"Professional",
            "subcategory":"Computer Services",
            "type":"Services"
        }
    ],
    "sg:phone":"+1 281 835 1264",
    "sg:postcode":"77489",
    "sg:province":"TX",
    "wof:name":"Hudson Technologies",
    "wof:placetype":"venue"
},
  "geometry": {"coordinates":[-95.52311400000001,29.589046],"type":"Point"}
}