{
  "type": "Feature",
  "properties": {
    "iso:country":"US",
    "sg:address":"601 N FM 1417",
    "sg:city":"Sherman",
    "sg:classifiers":[
        {
            "category":"Organizations",
            "subcategory":"Religious Organization",
            "type":"Services"
        }
    ],
    "sg:phone":"+1 903 893 2643",
    "sg:postcode":"75092",
    "sg:province":"TX",
    "wof:name":"Sherman Chruch of The Nazarene",
    "wof:placetype":"venue"
},
  "geometry": {"coordinates":[-96.64077899999999,33.642776],"type":"Point"}
}