{
  "type": "Feature",
  "properties": {
    "iso:country":"US",
    "sg:address":"3301 Lotus Ln",
    "sg:city":"Lufkin",
    "sg:classifiers":[
        {
            "category":"Professional",
            "subcategory":"Management & Consulting",
            "type":"Services"
        }
    ],
    "sg:phone":"+1 936 637 7029",
    "sg:postcode":"75904",
    "sg:province":"TX",
    "wof:name":"Hill Management & Accessories",
    "wof:placetype":"venue"
},
  "geometry": {"coordinates":[-94.75821500000001,31.348459],"type":"Point"}
}