{
  "type": "Feature",
  "properties": {
    "iso:country":"US",
    "sg:address":"5809 Sweetbriar Dr",
    "sg:city":"Richardson",
    "sg:classifiers":[
        {
            "category":"Banks & Credit Unions",
            "subcategory":"Financial Services",
            "type":"Services"
        }
    ],
    "sg:phone":"+1 972 437 5005",
    "sg:postcode":"75082",
    "sg:province":"TX",
    "sg:tags":[
        "company",
        "bank",
        "holding"
    ],
    "wof:name":"Dennis R Lye",
    "wof:placetype":"venue"
},
  "geometry": {"coordinates":[-96.614741,32.98707],"type":"Point"}
}