{
  "type": "Feature",
  "properties": {
    "iso:country":"US",
    "sg:address":"2340 E. Trinity Mills Rd Ste 225",
    "sg:city":"Carrollton",
    "sg:classifiers":[
        {
            "category":"Health Services",
            "subcategory":"Chiropractor",
            "type":"Services"
        }
    ],
    "sg:phone":"+1 469 546 0325",
    "sg:postcode":"75006",
    "sg:province":"TX",
    "sg:website":"www.serenitychiro.net",
    "wof:name":"Serenity Chiropractic & Family Wellness Center",
    "wof:placetype":"venue"
},
  "geometry": {"coordinates":[-96.87464799999999,32.984577],"type":"Point"}
}