{
  "type": "Feature",
  "properties": {
    "iso:country":"US",
    "sg:address":"3020 Marina Bay Dr",
    "sg:city":"League City",
    "sg:classifiers":[
        {
            "category":"Restaurant",
            "type":"Food & Drink"
        }
    ],
    "sg:phone":"+1 281 535 4776",
    "sg:postcode":"77573",
    "sg:province":"TX",
    "sg:tags":[
        "eating"
    ],
    "wof:name":"San Lrnzo Mxcan Rstrnt Cantina",
    "wof:placetype":"venue"
},
  "geometry": {"coordinates":[-95.061688,29.541758],"type":"Point"}
}