{
  "type": "Feature",
  "properties": {
    "iso:country":"US",
    "sg:address":"407 S Adams St",
    "sg:city":"Fredericksburg",
    "sg:classifiers":[
        {
            "category":"Utilities",
            "subcategory":"Telephone",
            "type":"Services"
        },
        {
            "category":"Manufacturing",
            "subcategory":"Electronics",
            "type":"Manufacturing & Wholesale Goods"
        },
        {
            "category":"Communications",
            "type":"Services"
        }
    ],
    "sg:phone":"+1 830 997 2860",
    "sg:postcode":"78624",
    "sg:province":"TX",
    "sg:tags":[
        "equipment",
        "telecommunications-equipment",
        "system",
        "supply"
    ],
    "wof:name":"Pocket Communications",
    "wof:placetype":"venue"
},
  "geometry": {"coordinates":[-98.869758,30.277895],"type":"Point"}
}