{
  "type": "Feature",
  "properties": {
    "iso:country":"US",
    "sg:address":"3330 Audley St",
    "sg:city":"Houston",
    "sg:classifiers":[
        {
            "category":"Retail",
            "subcategory":"Portrait Studio",
            "type":"Services"
        },
        {
            "category":"Professional",
            "subcategory":"Art Services",
            "type":"Services"
        }
    ],
    "sg:phone":"+1 713 520 9044",
    "sg:postcode":"77098",
    "sg:province":"TX",
    "sg:tags":[
        "photographer",
        "photo"
    ],
    "wof:name":"David Bray Photography",
    "wof:placetype":"venue"
},
  "geometry": {"coordinates":[-95.42637000000001,29.735049],"type":"Point"}
}