{
  "type": "Feature",
  "properties": {
    "iso:country":"US",
    "sg:address":"7707 Heathrow Ln",
    "sg:city":"Spring",
    "sg:classifiers":[
        {
            "category":"Manufacturing",
            "subcategory":"Printing",
            "type":"Manufacturing & Wholesale Goods"
        }
    ],
    "sg:phone":"+1 281 370 8358",
    "sg:postcode":"77379",
    "sg:province":"TX",
    "sg:tags":[
        "cards",
        "greeting",
        "mfg"
    ],
    "wof:name":"Diane M Larubbio",
    "wof:placetype":"venue"
},
  "geometry": {"coordinates":[-95.524832,30.009915],"type":"Point"}
}