{
  "type": "Feature",
  "properties": {
    "iso:country":"US",
    "sg:address":"13599 N Lamar Dr",
    "sg:city":"Laredo",
    "sg:classifiers":[
        {
            "category":"Professional",
            "subcategory":"Management & Consulting",
            "type":"Services"
        }
    ],
    "sg:phone":"+1 956 712 8274",
    "sg:postcode":"78045",
    "sg:province":"TX",
    "sg:tags":[
        "international",
        "consultant"
    ],
    "wof:name":"Integrated Trade Systems Inc",
    "wof:placetype":"venue"
},
  "geometry": {"coordinates":[-99.520546,27.617582],"type":"Point"}
}