{
  "type": "Feature",
  "properties": {
    "iso:country":"US",
    "sg:address":"226 Nolan St",
    "sg:city":"San Antonio",
    "sg:classifiers":[
        {
            "category":"Social Services",
            "type":"Services"
        }
    ],
    "sg:phone":"+1 210 226 2291",
    "sg:postcode":"78202",
    "sg:province":"TX",
    "sg:tags":[
        "organization",
        "welfare"
    ],
    "sg:website":"www.salvationarmysatx.org",
    "wof:name":"Salvation Army",
    "wof:placetype":"venue"
},
  "geometry": {"coordinates":[-98.479372,29.427543],"type":"Point"}
}