{
  "type": "Feature",
  "properties": {
    "iso:country":"US",
    "sg:address":"3615 Tower Dr",
    "sg:city":"Amarillo",
    "sg:classifiers":[
        {
            "category":"Autos & Motor Vehicles",
            "subcategory":"Automobile Sales",
            "type":"Retail Goods"
        }
    ],
    "sg:phone":"+1 806 374 8153",
    "sg:postcode":"79104",
    "sg:province":"TX",
    "sg:tags":[
        "car",
        "dealer"
    ],
    "wof:name":"Car Lot",
    "wof:placetype":"venue"
},
  "geometry": {"coordinates":[-101.79501500000001,35.193888],"type":"Point"}
}