{
  "type": "Feature",
  "properties": {
    "iso:country":"US",
    "sg:address":"19654 Airport Pkwy",
    "sg:city":"Conroe",
    "sg:classifiers":[
        {
            "category":"Organizations",
            "subcategory":"Non-profit Organization",
            "type":"Services"
        }
    ],
    "sg:phone":"+1 936 788 2446",
    "sg:postcode":"77303",
    "sg:province":"TX",
    "wof:name":"Friendship Gardens",
    "wof:placetype":"venue"
},
  "geometry": {"coordinates":[-95.435019,30.347628],"type":"Point"}
}