{
  "type": "Feature",
  "properties": {
    "iso:country":"US",
    "sg:address":"1001 Waugh Dr",
    "sg:city":"Houston",
    "sg:classifiers":[
        {
            "category":"Shopping",
            "subcategory":"Pharmacy",
            "type":"Retail Goods"
        }
    ],
    "sg:phone":"+1 713 807 7859",
    "sg:postcode":"77019",
    "sg:province":"TX",
    "sg:tags":[
        "drugstore"
    ],
    "sg:website":"www.cvs.com",
    "wof:name":"CVS Pharmacy",
    "wof:placetype":"venue"
},
  "geometry": {"coordinates":[-95.398117,29.757325],"type":"Point"}
}