{
  "type": "Feature",
  "properties": {
    "iso:country":"US",
    "sg:address":"2914 E Yandell Dr",
    "sg:city":"El Paso",
    "sg:classifiers":[
        {
            "category":"Personal",
            "subcategory":"Beauty Salon",
            "type":"Services"
        }
    ],
    "sg:phone":"+1 915 566 0420",
    "sg:postcode":"79903",
    "sg:province":"TX",
    "sg:tags":[
        "manicuring"
    ],
    "wof:name":"Casuals",
    "wof:placetype":"venue"
},
  "geometry": {"coordinates":[-106.46011300000001,31.781635],"type":"Point"}
}