{
  "type": "Feature",
  "properties": {
    "iso:country":"US",
    "sg:address":"490 State Hwy 36",
    "sg:city":"Caldwell",
    "sg:classifiers":[
        {
            "category":"Real Estate",
            "subcategory":"Real Estate Operator",
            "type":"Services"
        }
    ],
    "sg:phone":"+1 979 567 7124",
    "sg:postcode":"77836",
    "sg:province":"TX",
    "sg:tags":[
        "apartment"
    ],
    "wof:name":"Burleson Heights Apartments",
    "wof:placetype":"venue"
},
  "geometry": {"coordinates":[-96.693467,30.537228],"type":"Point"}
}