{
  "type": "Feature",
  "properties": {
    "iso:country":"US",
    "sg:address":"3300 Wilbarger St",
    "sg:city":"Vernon",
    "sg:classifiers":[
        {
            "category":"Wholesale",
            "subcategory":"Farm Supplies",
            "type":"Manufacturing & Wholesale Goods"
        }
    ],
    "sg:phone":"+1 940 552 6253",
    "sg:postcode":"76384",
    "sg:province":"TX",
    "sg:tags":[
        "buyer",
        "cotton"
    ],
    "wof:name":"W B Dunavant Cotton Co",
    "wof:placetype":"venue"
},
  "geometry": {"coordinates":[-99.30085699999999,34.152545],"type":"Point"}
}