{
  "type": "Feature",
  "properties": {
    "iso:country":"US",
    "sg:address":"1016 Miranda Dr",
    "sg:city":"Mesquite",
    "sg:classifiers":[
        {
            "category":"Health Services",
            "subcategory":"Dentist",
            "type":"Services"
        }
    ],
    "sg:phone":"+1 972 285 0712",
    "sg:postcode":"75149",
    "sg:province":"TX",
    "wof:name":"Todd Brown",
    "wof:placetype":"venue"
},
  "geometry": {"coordinates":[-96.588616,32.753043],"type":"Point"}
}