{
  "type": "Feature",
  "properties": {
    "iso:country":"US",
    "sg:address":"112 Medina St",
    "sg:city":"Austin",
    "sg:classifiers":[
        {
            "category":"Organizations",
            "subcategory":"Religious Organization",
            "type":"Services"
        }
    ],
    "sg:phone":"+1 512 478 2802",
    "sg:postcode":"78702",
    "sg:province":"TX",
    "wof:name":"Primera Iglsia Bautista Austin",
    "wof:placetype":"venue"
},
  "geometry": {"coordinates":[-97.733299,30.261072],"type":"Point"}
}