{
  "type": "Feature",
  "properties": {
    "iso:country":"US",
    "sg:address":"1156 Fairway Dr W",
    "sg:city":"Lindale",
    "sg:classifiers":[
        {
            "category":"Professional",
            "subcategory":"Management & Consulting",
            "type":"Services"
        }
    ],
    "sg:phone":"+1 903 882 8910",
    "sg:postcode":"75771",
    "sg:province":"TX",
    "wof:name":"Andy Hickman",
    "wof:placetype":"venue"
},
  "geometry": {"coordinates":[-95.465791,32.478285],"type":"Point"}
}