{
  "type": "Feature",
  "properties": {
    "iso:country":"US",
    "sg:address":"575 Anchor St",
    "sg:city":"Beaumont",
    "sg:classifiers":[
        {
            "category":"Organizations",
            "subcategory":"Religious Organization",
            "type":"Services"
        }
    ],
    "sg:phone":"+1 409 838 0614",
    "sg:postcode":"77705",
    "sg:province":"TX",
    "sg:tags":[
        "church"
    ],
    "wof:name":"Church Of Christ",
    "wof:placetype":"venue"
},
  "geometry": {"coordinates":[-94.085882,30.044608],"type":"Point"}
}