{
  "type": "Feature",
  "properties": {
    "iso:country":"US",
    "sg:address":"1802 9th St",
    "sg:city":"Bridgeport",
    "sg:classifiers":[
        {
            "category":"Utilities",
            "subcategory":"Refuse",
            "type":"Services"
        }
    ],
    "sg:phone":"+1 940 683 5425",
    "sg:postcode":"76426",
    "sg:province":"TX",
    "sg:tags":[
        "truck",
        "dump"
    ],
    "wof:name":"Danny Shinn Trucking",
    "wof:placetype":"venue"
},
  "geometry": {"coordinates":[-97.758827,33.21751],"type":"Point"}
}