{
  "type": "Feature",
  "properties": {
    "iso:country":"US",
    "sg:address":"129 Heritage Row",
    "sg:city":"Marlin",
    "sg:classifiers":[
        {
            "category":"Professional",
            "subcategory":"Accounting & Tax Preparation",
            "type":"Services"
        }
    ],
    "sg:phone":"+1 254 883 5910",
    "sg:postcode":"76661",
    "sg:province":"TX",
    "sg:tags":[
        "return"
    ],
    "wof:name":"H & R Block",
    "wof:placetype":"venue"
},
  "geometry": {"coordinates":[-96.896619,31.309047],"type":"Point"}
}