{
  "type": "Feature",
  "properties": {
    "iso:country":"US",
    "sg:address":"1511 S Ewing Ave",
    "sg:city":"Dallas",
    "sg:classifiers":[
        {
            "category":"Personal",
            "subcategory":"Beauty Salon",
            "type":"Services"
        }
    ],
    "sg:phone":"+1 214 942 1541",
    "sg:postcode":"75216",
    "sg:province":"TX",
    "sg:tags":[
        "school",
        "cosmetology"
    ],
    "sg:website":"www.velmabs.com",
    "wof:name":"Velma B's Beauty Academy",
    "wof:placetype":"venue"
},
  "geometry": {"coordinates":[-96.811302,32.729198],"type":"Point"}
}