{
  "type": "Feature",
  "properties": {
    "iso:country":"US",
    "sg:address":"1151 Uptown Park Blvd Ste 1",
    "sg:city":"Houston",
    "sg:classifiers":[
        {
            "category":"Restaurant",
            "type":"Food & Drink"
        }
    ],
    "sg:phone":"+1 713 840 7900",
    "sg:postcode":"77056",
    "sg:province":"TX",
    "sg:tags":[
        "traditional",
        "seafood",
        "american"
    ],
    "sg:website":"mccormickandschmicks.com",
    "wof:name":"McCormick & Schmick's Seafood Restaurant",
    "wof:placetype":"venue"
},
  "geometry": {"coordinates":[-95.45764699999999,29.755734],"type":"Point"}
}