{
  "type": "Feature",
  "properties": {
    "iso:country":"US",
    "sg:address":"400 Fuller-Wiser Rd",
    "sg:city":"Euless",
    "sg:classifiers":[
        {
            "category":"Manufacturing",
            "subcategory":"Printing",
            "type":"Manufacturing & Wholesale Goods"
        }
    ],
    "sg:phone":"+1 817 540 4666",
    "sg:postcode":"76039",
    "sg:province":"TX",
    "sg:tags":[
        "newspaper"
    ],
    "wof:name":"Dfw People",
    "wof:placetype":"venue"
},
  "geometry": {"coordinates":[-97.072397,32.844376],"type":"Point"}
}