{
  "type": "Feature",
  "properties": {
    "iso:country":"US",
    "sg:address":"488 Windwood Ln",
    "sg:city":"Bells",
    "sg:classifiers":[
        {
            "category":"Farming",
            "subcategory":"Farm",
            "type":"Manufacturing & Wholesale Goods"
        }
    ],
    "sg:phone":"+1 903 364 5390",
    "sg:postcode":"75414",
    "sg:province":"TX",
    "wof:name":"Windwood Farms",
    "wof:placetype":"venue"
},
  "geometry": {"coordinates":[-96.39946,33.56942],"type":"Point"}
}