{
  "type": "Feature",
  "properties": {
    "iso:country":"US",
    "sg:address":"601 N College Ave",
    "sg:city":"Van Alstyne",
    "sg:classifiers":[
        {
            "category":"Real Estate",
            "subcategory":"Real Estate Operator",
            "type":"Services"
        }
    ],
    "sg:phone":"+1 903 482 6714",
    "sg:postcode":"75495",
    "sg:province":"TX",
    "sg:tags":[
        "apartment"
    ],
    "wof:name":"Windscape Apartments",
    "wof:placetype":"venue"
},
  "geometry": {"coordinates":[-96.584194,33.426812],"type":"Point"}
}