{
  "type": "Feature",
  "properties": {
    "iso:country":"US",
    "sg:address":"1000 N Grama St",
    "sg:city":"El Paso",
    "sg:classifiers":[
        {
            "category":"Education",
            "subcategory":"School",
            "type":"Public Place"
        }
    ],
    "sg:phone":"+1 915 231 2620",
    "sg:postcode":"79903",
    "sg:province":"TX",
    "wof:name":"Alta Vista School",
    "wof:placetype":"venue"
},
  "geometry": {"coordinates":[-106.452343,31.78471],"type":"Point"}
}