{
  "type": "Feature",
  "properties": {
    "iso:country":"US",
    "sg:address":"2100 W Northwest Hwy",
    "sg:city":"Grapevine",
    "sg:classifiers":[
        {
            "category":"Restaurant",
            "type":"Food & Drink"
        }
    ],
    "sg:menulink":"http://www.allmenus.com/tx/northeast-tarrant/249967-asian-top-restaurant/menu/",
    "sg:phone":"+1 817 251 1860",
    "sg:postcode":"76051",
    "sg:province":"TX",
    "sg:tags":[
        "japanese",
        "asian"
    ],
    "wof:name":"Asian Top Restaurant",
    "wof:placetype":"venue"
},
  "geometry": {"coordinates":[-97.099917,32.943055],"type":"Point"}
}