{
  "type": "Feature",
  "properties": {
    "iso:country":"US",
    "sg:address":"3100 Richmond Ave",
    "sg:city":"Houston",
    "sg:classifiers":[
        {
            "category":"Banks & Credit Unions",
            "subcategory":"Bank",
            "type":"Services"
        }
    ],
    "sg:phone":"+1 713 586 6635",
    "sg:postcode":"77098",
    "sg:province":"TX",
    "sg:tags":[
        "loan",
        "real estate"
    ],
    "wof:name":"First Alliance Mortgage",
    "wof:placetype":"venue"
},
  "geometry": {"coordinates":[-95.426272,29.734002],"type":"Point"}
}