{
  "type": "Feature",
  "properties": {
    "iso:country":"US",
    "sg:address":"1005 W Jefferson Blvd",
    "sg:city":"Dallas",
    "sg:classifiers":[
        {
            "category":"Banks & Credit Unions",
            "subcategory":"Bank",
            "type":"Services"
        }
    ],
    "sg:phone":"+1 214 942 6464",
    "sg:postcode":"75208",
    "sg:province":"TX",
    "sg:tags":[
        "consultant",
        "financing",
        "insurance",
        "analyst"
    ],
    "wof:name":"Longhorn Acceptance",
    "wof:placetype":"venue"
},
  "geometry": {"coordinates":[-96.83970600000001,32.743176],"type":"Point"}
}