{
  "type": "Feature",
  "properties": {
    "iso:country":"US",
    "sg:address":"10750 Barker Cypress Rd",
    "sg:city":"Cypress",
    "sg:classifiers":[
        {
            "category":"Restaurant",
            "type":"Food & Drink"
        }
    ],
    "sg:phone":"+1 281 373 5559",
    "sg:postcode":"77433",
    "sg:province":"TX",
    "wof:name":"League Play Grill",
    "wof:placetype":"venue"
},
  "geometry": {"coordinates":[-95.68288699999999,29.93314],"type":"Point"}
}