{
  "type": "Feature",
  "properties": {
    "iso:country":"US",
    "sg:address":"1914 Suntide Rd",
    "sg:city":"Corpus Christi",
    "sg:classifiers":[
        {
            "category":"Wholesale",
            "subcategory":"Metals & Minerals",
            "type":"Manufacturing & Wholesale Goods"
        }
    ],
    "sg:phone":"+1 361 289 7191",
    "sg:postcode":"78409",
    "sg:province":"TX",
    "sg:tags":[
        "steel",
        "warehouse"
    ],
    "wof:name":"Tejas Metals",
    "wof:placetype":"venue"
},
  "geometry": {"coordinates":[-97.520135,27.817605],"type":"Point"}
}