{
  "type": "Feature",
  "properties": {
    "iso:country":"US",
    "sg:address":"680 SW Military Dr",
    "sg:city":"San Antonio",
    "sg:classifiers":[
        {
            "category":"Real Estate",
            "subcategory":"Real Estate Agent",
            "type":"Services"
        }
    ],
    "sg:phone":"+1 210 928 2577",
    "sg:postcode":"78221",
    "sg:province":"TX",
    "sg:tags":[
        "management"
    ],
    "wof:name":"Fairman & Assoc",
    "wof:placetype":"venue"
},
  "geometry": {"coordinates":[-98.50382,29.356765],"type":"Point"}
}