{
  "type": "Feature",
  "properties": {
    "iso:country":"US",
    "sg:address":"5555 de Zavala Rd",
    "sg:city":"San Antonio",
    "sg:classifiers":[
        {
            "category":"Banks & Credit Unions",
            "subcategory":"Bank",
            "type":"Services"
        }
    ],
    "sg:phone":"+1 210 691 5355",
    "sg:postcode":"78249",
    "sg:province":"TX",
    "sg:tags":[
        "national",
        "commercial"
    ],
    "wof:name":"Woodforest National Bank",
    "wof:placetype":"venue"
},
  "geometry": {"coordinates":[-98.591528,29.563186],"type":"Point"}
}