{
  "type": "Feature",
  "properties": {
    "iso:country":"US",
    "sg:address":"7119 San Pedro Ave",
    "sg:city":"San Antonio",
    "sg:classifiers":[
        {
            "category":"Shopping",
            "subcategory":"Computers & Home Electronics",
            "type":"Retail Goods"
        }
    ],
    "sg:phone":"+1 210 341 3391",
    "sg:postcode":"78216",
    "sg:province":"TX",
    "wof:name":"Radio Shack",
    "wof:placetype":"venue"
},
  "geometry": {"coordinates":[-98.499347,29.511512],"type":"Point"}
}