{
  "type": "Feature",
  "properties": {
    "iso:country":"US",
    "sg:address":"229 E University Blvd",
    "sg:city":"Odessa",
    "sg:classifiers":[
        {
            "category":"Retail",
            "subcategory":"Repair Shop",
            "type":"Services"
        }
    ],
    "sg:phone":"+1 432 580 6010",
    "sg:postcode":"79762",
    "sg:province":"TX",
    "sg:tags":[
        "appliance",
        "household",
        "electrical"
    ],
    "wof:name":"House Of Vacuum Cleaners",
    "wof:placetype":"venue"
},
  "geometry": {"coordinates":[-102.37949,31.868542],"type":"Point"}
}