{
  "type": "Feature",
  "properties": {
    "iso:country":"US",
    "sg:address":"6909 Forbess Dr",
    "sg:city":"Brownwood",
    "sg:classifiers":[
        {
            "category":"Wholesale",
            "subcategory":"Books, Periodicals, & Newspapers",
            "type":"Manufacturing & Wholesale Goods"
        }
    ],
    "sg:phone":"+1 325 784 8180",
    "sg:postcode":"76801",
    "sg:province":"TX",
    "sg:tags":[
        "publisher",
        "book"
    ],
    "wof:name":"Eagle Press",
    "wof:placetype":"venue"
},
  "geometry": {"coordinates":[-99.094651,31.820589],"type":"Point"}
}