{
  "type": "Feature",
  "properties": {
    "iso:country":"US",
    "sg:address":"340 Arrowhead St",
    "sg:city":"Fort Worth",
    "sg:classifiers":[
        {
            "category":"Professional",
            "subcategory":"Management & Consulting",
            "type":"Services"
        }
    ],
    "sg:phone":"+1 817 448 8447",
    "sg:postcode":"76108",
    "sg:province":"TX",
    "wof:name":"Morris Jerry Construction Svcs",
    "wof:placetype":"venue"
},
  "geometry": {"coordinates":[-97.554147,32.78016],"type":"Point"}
}