{
  "type": "Feature",
  "properties": {
    "iso:country":"US",
    "sg:address":"1407 Roberts Ave",
    "sg:city":"Cleburne",
    "sg:classifiers":[
        {
            "category":"Freight",
            "type":"Transportation"
        }
    ],
    "sg:phone":"+1 817 517 7184",
    "sg:postcode":"76033",
    "sg:province":"TX",
    "sg:tags":[
        "truck",
        "driver"
    ],
    "wof:name":"Bennie L Jewett",
    "wof:placetype":"venue"
},
  "geometry": {"coordinates":[-97.412404,32.357371],"type":"Point"}
}