{
  "type": "Feature",
  "properties": {
    "iso:country":"US",
    "sg:address":"117 S Sylvania Ave",
    "sg:city":"Fort Worth",
    "sg:classifiers":[
        {
            "category":"Shopping",
            "type":"Retail Goods"
        }
    ],
    "sg:phone":"+1 800 281 6792",
    "sg:postcode":"76111",
    "sg:province":"TX",
    "sg:tags":[
        "merchandise"
    ],
    "wof:name":"Jump For Fun Inc",
    "wof:placetype":"venue"
},
  "geometry": {"coordinates":[-97.308886,32.764447],"type":"Point"}
}