{
  "type": "Feature",
  "properties": {
    "iso:country":"US",
    "sg:address":"723 N Brazosport Blvd",
    "sg:city":"Freeport",
    "sg:classifiers":[
        {
            "category":"Professional",
            "type":"Services"
        },
        {
            "category":"Retail",
            "subcategory":"Auto Repair",
            "type":"Services"
        }
    ],
    "sg:phone":"+1 979 230 9117",
    "sg:postcode":"77541",
    "sg:province":"TX",
    "sg:tags":[
        "repairing",
        "automobile"
    ],
    "wof:name":"Facundo's Mechanic",
    "wof:placetype":"venue"
},
  "geometry": {"coordinates":[-95.37219399999999,28.966751],"type":"Point"}
}