{
  "type": "Feature",
  "properties": {
    "iso:country":"US",
    "sg:address":"5221 N O Connor Blvd",
    "sg:city":"Irving",
    "sg:classifiers":[
        {
            "category":"Real Estate",
            "subcategory":"Real Estate Services",
            "type":"Services"
        },
        {
            "category":"Real Estate",
            "subcategory":"Real Estate Agent",
            "type":"Services"
        }
    ],
    "sg:phone":"+1 972 501 0178",
    "sg:postcode":"75039",
    "sg:province":"TX",
    "sg:tags":[
        "buyer",
        "broker"
    ],
    "wof:name":"TIAA Realty Inc.",
    "wof:placetype":"venue"
},
  "geometry": {"coordinates":[-96.93966500000001,32.870004],"type":"Point"}
}