{
  "type": "Feature",
  "properties": {
    "iso:country":"US",
    "sg:address":"310 University Dr E",
    "sg:city":"College Station",
    "sg:classifiers":[
        {
            "category":"Real Estate",
            "subcategory":"Real Estate Agent",
            "type":"Services"
        }
    ],
    "sg:phone":"+1 979 696 6600",
    "sg:postcode":"77840",
    "sg:province":"TX",
    "wof:name":"Southern Realty & Financial Co",
    "wof:placetype":"venue"
},
  "geometry": {"coordinates":[-96.33228800000001,30.63007],"type":"Point"}
}