{
  "type": "Feature",
  "properties": {
    "iso:country":"US",
    "sg:address":"1415 N Hughes St",
    "sg:city":"Amarillo",
    "sg:classifiers":[
        {
            "category":"Personal",
            "subcategory":"Beauty Salon",
            "type":"Services"
        }
    ],
    "sg:phone":"+1 806 374 6881",
    "sg:postcode":"79107",
    "sg:province":"TX",
    "wof:name":"Golden Comb Beauty Shop",
    "wof:placetype":"venue"
},
  "geometry": {"coordinates":[-101.847103,35.228402],"type":"Point"}
}