{
  "type": "Feature",
  "properties": {
    "iso:country":"US",
    "sg:address":"2143 Barnard Rd",
    "sg:city":"Brownsville",
    "sg:classifiers":[
        {
            "category":"Building & Trades",
            "subcategory":"Construction",
            "type":"Services"
        }
    ],
    "sg:phone":"+1 956 548 0805",
    "sg:postcode":"78520",
    "sg:province":"TX",
    "sg:tags":[
        "house",
        "builder",
        "home"
    ],
    "wof:name":"Benson Builders Inc",
    "wof:placetype":"venue"
},
  "geometry": {"coordinates":[-97.503489,25.933821],"type":"Point"}
}