{
  "type": "Feature",
  "properties": {
    "iso:country":"US",
    "sg:address":"1101 Main St",
    "sg:city":"Garland",
    "sg:classifiers":[
        {
            "category":"Shopping",
            "subcategory":"Clothing, Apparel, & Fashions",
            "type":"Retail Goods"
        },
        {
            "category":"Professional",
            "subcategory":"Advertising",
            "type":"Services"
        },
        {
            "category":"Professional",
            "subcategory":"Printing & Photocopies",
            "type":"Services"
        },
        {
            "category":"Manufacturing",
            "subcategory":"Signs",
            "type":"Manufacturing & Wholesale Goods"
        }
    ],
    "sg:phone":"+1 972 487 6960",
    "sg:postcode":"75040",
    "sg:province":"TX",
    "sg:tags":[
        "t-shirt",
        "screen",
        "hanger",
        "signs-erectors",
        "specialty"
    ],
    "sg:website":"http://www.actiontshirts.com",
    "wof:name":"Action Signs & Banners",
    "wof:placetype":"venue"
},
  "geometry": {"coordinates":[-96.643433,32.91272],"type":"Point"}
}