{
  "type": "Feature",
  "properties": {
    "iso:country":"US",
    "sg:address":"3406 Tanglewilde St",
    "sg:city":"Houston",
    "sg:classifiers":[
        {
            "category":"Shopping",
            "subcategory":"Clothing, Apparel, & Fashions",
            "type":"Retail Goods"
        }
    ],
    "sg:phone":"+1 713 952 4335",
    "sg:postcode":"77063",
    "sg:province":"TX",
    "wof:name":"Triune Golf Inc",
    "wof:placetype":"venue"
},
  "geometry": {"coordinates":[-95.53513599999999,29.726343],"type":"Point"}
}