{
  "type": "Feature",
  "properties": {
    "iso:country":"US",
    "sg:address":"12585 Whittington Dr",
    "sg:city":"Houston",
    "sg:classifiers":[
        {
            "category":"Personal",
            "subcategory":"Beauty Salon",
            "type":"Services"
        }
    ],
    "sg:phone":"+1 281 679 7886",
    "sg:postcode":"77077",
    "sg:province":"TX",
    "sg:tags":[
        "shop"
    ],
    "wof:name":"Sony Nail",
    "wof:placetype":"venue"
},
  "geometry": {"coordinates":[-95.602947,29.746193],"type":"Point"}
}