{
  "type": "Feature",
  "properties": {
    "iso:country":"US",
    "sg:address":"2938 Valley View Ln",
    "sg:city":"Dallas",
    "sg:classifiers":[
        {
            "category":"Retail",
            "subcategory":"Portrait Studio",
            "type":"Services"
        }
    ],
    "sg:phone":"+1 972 241 6644",
    "sg:postcode":"75234",
    "sg:province":"TX",
    "sg:tags":[
        "photographer",
        "travel",
        "agency",
        "photo"
    ],
    "wof:name":"Passports & Visas Inc",
    "wof:placetype":"venue"
},
  "geometry": {"coordinates":[-96.88002899999999,32.924418],"type":"Point"}
}