{
  "type": "Feature",
  "properties": {
    "iso:country":"US",
    "sg:address":"18381 Co Rd 2171",
    "sg:city":"Whitehouse",
    "sg:classifiers":[
        {
            "category":"Home & Garden",
            "subcategory":"Furniture",
            "type":"Retail Goods"
        }
    ],
    "sg:phone":"+1 903 839 2085",
    "sg:postcode":"75791",
    "sg:province":"TX",
    "sg:tags":[
        "cabinet"
    ],
    "wof:name":"C & C Construction",
    "wof:placetype":"venue"
},
  "geometry": {"coordinates":[-95.22878900000001,32.213169],"type":"Point"}
}