{
  "type": "Feature",
  "properties": {
    "iso:country":"US",
    "sg:address":"2921 Lackland Rd",
    "sg:city":"Fort Worth",
    "sg:classifiers":[
        {
            "category":"Health Services",
            "subcategory":"Doctor",
            "type":"Services"
        }
    ],
    "sg:phone":"+1 817 732 2821",
    "sg:postcode":"76116",
    "sg:province":"TX",
    "sg:tags":[
        "dentist"
    ],
    "wof:name":"Eugene M Kouri DDS",
    "wof:placetype":"venue"
},
  "geometry": {"coordinates":[-97.434527,32.733263],"type":"Point"}
}