{
  "type": "Feature",
  "properties": {
    "iso:country":"US",
    "sg:address":"1300 W Lindsey St",
    "sg:city":"Breckenridge",
    "sg:classifiers":[
        {
            "category":"Building & Trades",
            "subcategory":"Construction",
            "type":"Services"
        }
    ],
    "sg:phone":"+1 254 559 1305",
    "sg:postcode":"76424",
    "sg:province":"TX",
    "sg:tags":[
        "foundation"
    ],
    "wof:name":"Buckaroo Foundation Repair",
    "wof:placetype":"venue"
},
  "geometry": {"coordinates":[-98.92117399999999,32.758297],"type":"Point"}
}