{
  "type": "Feature",
  "properties": {
    "iso:country":"US",
    "sg:address":"6501 Dalrock Rd Ste 124",
    "sg:city":"Rowlett",
    "sg:classifiers":[
        {
            "category":"Personal",
            "subcategory":"Nail Salon",
            "type":"Services"
        }
    ],
    "sg:phone":"+1 972 463 2757",
    "sg:postcode":"75089",
    "sg:province":"TX",
    "wof:name":"Rowlett Nails",
    "wof:placetype":"venue"
},
  "geometry": {"coordinates":[-96.517982,32.918381],"type":"Point"}
}