{
  "type": "Feature",
  "properties": {
    "iso:country":"US",
    "sg:address":"3425 Thousand Oaks Dr",
    "sg:city":"San Antonio",
    "sg:classifiers":[
        {
            "category":"Freight",
            "type":"Transportation"
        }
    ],
    "sg:phone":"+1 210 495 5550",
    "sg:postcode":"78232",
    "sg:province":"TX",
    "sg:tags":[
        "commercial",
        "storage"
    ],
    "wof:name":"Security Self Storage",
    "wof:placetype":"venue"
},
  "geometry": {"coordinates":[-98.432536,29.569727],"type":"Point"}
}