{
  "type": "Feature",
  "properties": {
    "iso:country":"US",
    "sg:address":"300 E Expy 83",
    "sg:city":"Pharr",
    "sg:classifiers":[
        {
            "category":"Recreation",
            "type":"Entertainment"
        }
    ],
    "sg:phone":"+1 956 787 3187",
    "sg:postcode":"78577",
    "sg:province":"TX",
    "sg:tags":[
        "bingo",
        "game"
    ],
    "wof:name":"Triple City Bingo",
    "wof:placetype":"venue"
},
  "geometry": {"coordinates":[-98.179822,26.206022],"type":"Point"}
}