{
  "type": "Feature",
  "properties": {
    "iso:country":"US",
    "sg:address":"14800 Webb Chapel Rd",
    "sg:city":"Dallas",
    "sg:classifiers":[
        {
            "category":"Health Services",
            "subcategory":"Dentist",
            "type":"Services"
        }
    ],
    "sg:phone":"+1 972 620 8280",
    "sg:postcode":"75234",
    "sg:province":"TX",
    "sg:tags":[
        "product",
        "dentists-cosmetic",
        "dental",
        "teeth",
        "clinic",
        "whitening",
        "dentistry",
        "dentists-orthodontists"
    ],
    "sg:website":"http://www.alfadental.com",
    "wof:name":"Alfa Dental",
    "wof:placetype":"venue"
},
  "geometry": {"coordinates":[-96.873199,32.912279],"type":"Point"}
}