{
  "type": "Feature",
  "properties": {
    "iso:country":"US",
    "sg:address":"50 Southridge Dr",
    "sg:city":"Canyon",
    "sg:classifiers":[
        {
            "category":"Real Estate",
            "subcategory":"Real Estate Operator",
            "type":"Services"
        }
    ],
    "sg:phone":"+1 806 655 9611",
    "sg:postcode":"79015",
    "sg:province":"TX",
    "sg:tags":[
        "building",
        "apartment"
    ],
    "wof:name":"Canyon Creek Apartments",
    "wof:placetype":"venue"
},
  "geometry": {"coordinates":[-101.932502,34.986923],"type":"Point"}
}