{
  "type": "Feature",
  "properties": {
    "iso:country":"US",
    "sg:address":"111 E North Loop Blvd",
    "sg:city":"Austin",
    "sg:classifiers":[
        {
            "category":"Restaurant",
            "type":"Food & Drink"
        }
    ],
    "sg:menulink":"http://www.allmenus.com/tx/austin/282894-pharas-mediterranean-cuisine/menu/",
    "sg:phone":"+1 512 632 7067",
    "sg:postcode":"78751",
    "sg:province":"TX",
    "sg:tags":[
        "mediterranean"
    ],
    "wof:name":"Phara's Mediterranean Cuisine",
    "wof:placetype":"venue"
},
  "geometry": {"coordinates":[-97.721963,30.317465],"type":"Point"}
}