{
  "type": "Feature",
  "properties": {
    "iso:country":"US",
    "sg:address":"223 S Nueces St",
    "sg:city":"George West",
    "sg:classifiers":[
        {
            "category":"Bars & Pubs",
            "type":"Food & Drink"
        }
    ],
    "sg:phone":"+1 361 449 1092",
    "sg:postcode":"78022",
    "sg:province":"TX",
    "wof:name":"Pete's Red Barn",
    "wof:placetype":"venue"
},
  "geometry": {"coordinates":[-98.11410100000001,28.321409],"type":"Point"}
}