{
  "type": "Feature",
  "properties": {
    "iso:country":"US",
    "sg:address":"10732 W Bellfort St",
    "sg:city":"Houston",
    "sg:classifiers":[
        {
            "category":"Shopping",
            "type":"Retail Goods"
        }
    ],
    "sg:phone":"+1 281 933 7387",
    "sg:postcode":"77099",
    "sg:province":"TX",
    "sg:tags":[
        "merchandise"
    ],
    "wof:name":"Discount Tropical Fish",
    "wof:placetype":"venue"
},
  "geometry": {"coordinates":[-95.56795700000001,29.654612],"type":"Point"}
}