{
  "type": "Feature",
  "properties": {
    "iso:country":"US",
    "sg:address":"6943 N Dallas Pkwy",
    "sg:city":"Plano",
    "sg:classifiers":[
        {
            "category":"Professional",
            "subcategory":"Business Services",
            "type":"Services"
        }
    ],
    "sg:phone":"+1 972 378 3896",
    "sg:postcode":"75024",
    "sg:province":"TX",
    "wof:name":"Express Yourself Etc",
    "wof:placetype":"venue"
},
  "geometry": {"coordinates":[-96.823954,33.07358],"type":"Point"}
}