{
  "type": "Feature",
  "properties": {
    "iso:country":"US",
    "sg:address":"12500 Memorial Dr",
    "sg:city":"Houston",
    "sg:classifiers":[
        {
            "category":"Coffee & Tea",
            "type":"Food & Drink"
        }
    ],
    "sg:menulink":"http://www.allmenus.com/tx/houston/112947-starbucks-coffee/menu/",
    "sg:phone":"+1 713 647 9824",
    "sg:postcode":"77024",
    "sg:province":"TX",
    "sg:tags":[
        "american"
    ],
    "wof:name":"Starbucks Coffee",
    "wof:placetype":"venue"
},
  "geometry": {"coordinates":[-95.55147100000001,29.766842],"type":"Point"}
}