{
  "type": "Feature",
  "properties": {
    "iso:country":"US",
    "sg:address":"2000 W Gentry Pkwy",
    "sg:city":"Tyler",
    "sg:classifiers":[
        {
            "category":"Organizations",
            "subcategory":"Professional Association",
            "type":"Services"
        }
    ],
    "sg:phone":"+1 903 593 6026",
    "sg:postcode":"75702",
    "sg:province":"TX",
    "sg:tags":[
        "chambers",
        "commerce"
    ],
    "wof:name":"Tyler Metropolitan",
    "wof:placetype":"venue"
},
  "geometry": {"coordinates":[-95.322478,32.364534],"type":"Point"}
}