{
  "type": "Feature",
  "properties": {
    "iso:country":"US",
    "sg:address":"2310 W Lane Dr",
    "sg:city":"Houston",
    "sg:classifiers":[
        {
            "category":"Professional",
            "subcategory":"Lawyer & Legal Services",
            "type":"Services"
        }
    ],
    "sg:phone":"+1 713 888 0500",
    "sg:postcode":"77027",
    "sg:province":"TX",
    "wof:name":"Hernden Tricia Attorney At Law",
    "wof:placetype":"venue"
},
  "geometry": {"coordinates":[-95.451103,29.7439],"type":"Point"}
}