{
  "type": "Feature",
  "properties": {
    "iso:country":"US",
    "sg:address":"10605 Birmingham Dr",
    "sg:city":"Frisco",
    "sg:classifiers":[
        {
            "category":"Real Estate",
            "subcategory":"Real Estate Agent",
            "type":"Services"
        }
    ],
    "sg:phone":"+1 972 335 3033",
    "sg:postcode":"75035",
    "sg:province":"TX",
    "wof:name":"Callaway Property Management",
    "wof:placetype":"venue"
},
  "geometry": {"coordinates":[-96.785832,33.126973],"type":"Point"}
}