{
  "type": "Feature",
  "properties": {
    "iso:country":"US",
    "sg:address":"1608 W 23rd St",
    "sg:city":"Houston",
    "sg:classifiers":[
        {
            "category":"Manufacturing",
            "subcategory":"Wood Products",
            "type":"Manufacturing & Wholesale Goods"
        }
    ],
    "sg:phone":"+1 713 426 0019",
    "sg:postcode":"77008",
    "sg:province":"TX",
    "sg:tags":[
        "mfg"
    ],
    "wof:name":"Texas Woodworking",
    "wof:placetype":"venue"
},
  "geometry": {"coordinates":[-95.427606,29.806589],"type":"Point"}
}