{
  "type": "Feature",
  "properties": {
    "iso:country":"US",
    "sg:address":"1200 Hospital Dr",
    "sg:city":"Angleton",
    "sg:classifiers":[
        {
            "category":"Manufacturing",
            "subcategory":"Printing",
            "type":"Manufacturing & Wholesale Goods"
        }
    ],
    "sg:phone":"+1 979 549 9555",
    "sg:postcode":"77515",
    "sg:province":"TX",
    "sg:tags":[
        "newspaper"
    ],
    "wof:name":"Houston Chronicle",
    "wof:placetype":"venue"
},
  "geometry": {"coordinates":[-95.41918699999999,29.184925],"type":"Point"}
}