{
  "type": "Feature",
  "properties": {
    "iso:country":"US",
    "sg:address":"1110 I- 35 Svc Rd",
    "sg:city":"Round Rock",
    "sg:classifiers":[
        {
            "category":"Personal",
            "type":"Services"
        }
    ],
    "sg:phone":"+1 512 733 9180",
    "sg:postcode":"78681",
    "sg:province":"TX",
    "sg:tags":[
        "therapist",
        "business",
        "massage"
    ],
    "wof:name":"Stress Express",
    "wof:placetype":"venue"
},
  "geometry": {"coordinates":[-97.68129500000001,30.498186],"type":"Point"}
}