{
  "type": "Feature",
  "properties": {
    "iso:country":"US",
    "sg:address":"16147 Spinnaker Dr",
    "sg:city":"Crosby",
    "sg:classifiers":[
        {
            "category":"Professional",
            "subcategory":"Business Services",
            "type":"Services"
        }
    ],
    "sg:phone":"+1 281 328 4128",
    "sg:postcode":"77532",
    "sg:province":"TX",
    "wof:name":"Lakeside Ventures",
    "wof:placetype":"venue"
},
  "geometry": {"coordinates":[-95.08287300000001,29.917614],"type":"Point"}
}