{
  "type": "Feature",
  "properties": {
    "iso:country":"US",
    "sg:address":"520 Castile Ave",
    "sg:city":"El Paso",
    "sg:classifiers":[
        {
            "category":"Professional",
            "type":"Services"
        }
    ],
    "sg:phone":"+1 915 833 1894",
    "sg:postcode":"79912",
    "sg:province":"TX",
    "sg:tags":[
        "establishment"
    ],
    "wof:name":"Laura's Production",
    "wof:placetype":"venue"
},
  "geometry": {"coordinates":[-106.543239,31.829169],"type":"Point"}
}