{
  "type": "Feature",
  "properties": {
    "iso:country":"US",
    "sg:address":"302 W 8th St",
    "sg:city":"Houston",
    "sg:classifiers":[
        {
            "category":"Organizations",
            "subcategory":"Religious Organization",
            "type":"Services"
        }
    ],
    "sg:phone":"+1 713 864 9782",
    "sg:postcode":"77007",
    "sg:province":"TX",
    "sg:tags":[
        "church"
    ],
    "wof:name":"Jones Chapel A M E Church",
    "wof:placetype":"venue"
},
  "geometry": {"coordinates":[-95.40104599999999,29.785036],"type":"Point"}
}