{
  "type": "Feature",
  "properties": {
    "iso:country":"US",
    "sg:address":"4544 Sunbelt Dr",
    "sg:city":"Addison",
    "sg:classifiers":[
        {
            "category":"Communications",
            "subcategory":"News Services",
            "type":"Services"
        }
    ],
    "sg:phone":"+1 214 378 1441",
    "sg:postcode":"75001",
    "sg:province":"TX",
    "wof:name":"Sunbelt News Network",
    "wof:placetype":"venue"
},
  "geometry": {"coordinates":[-96.833517,32.977046],"type":"Point"}
}