{
  "type": "Feature",
  "properties": {
    "iso:country":"US",
    "sg:address":"4821 Cain Dr",
    "sg:city":"Corpus Christi",
    "sg:classifiers":[
        {
            "category":"Retail",
            "subcategory":"Repair Shop",
            "type":"Services"
        }
    ],
    "sg:phone":"+1 361 991 6464",
    "sg:postcode":"78411",
    "sg:province":"TX",
    "sg:tags":[
        "water",
        "heater"
    ],
    "wof:name":"R C Plumbing & Drain Svc",
    "wof:placetype":"venue"
},
  "geometry": {"coordinates":[-97.385981,27.705218],"type":"Point"}
}