{
  "type": "Feature",
  "properties": {
    "iso:country":"US",
    "sg:address":"6101 43rd St",
    "sg:city":"Lubbock",
    "sg:classifiers":[
        {
            "category":"Wholesale",
            "subcategory":"Stationery",
            "type":"Manufacturing & Wholesale Goods"
        }
    ],
    "sg:phone":"+1 806 797 0003",
    "sg:postcode":"79407",
    "sg:province":"TX",
    "sg:tags":[
        "school",
        "supply"
    ],
    "wof:name":"Teacher Heaven Inc",
    "wof:placetype":"venue"
},
  "geometry": {"coordinates":[-101.949681,33.556108],"type":"Point"}
}