{
  "type": "Feature",
  "properties": {
    "iso:country":"US",
    "sg:address":"10435 Westedge Dr",
    "sg:city":"Sugar Land",
    "sg:classifiers":[
        {
            "category":"Social Services",
            "subcategory":"Child Care",
            "type":"Services"
        }
    ],
    "sg:phone":"+1 281 242 7179",
    "sg:postcode":"77478",
    "sg:province":"TX",
    "sg:tags":[
        "day"
    ],
    "wof:name":"Nancy Gale Schoditsch",
    "wof:placetype":"venue"
},
  "geometry": {"coordinates":[-95.63500999999999,29.663149],"type":"Point"}
}