{
  "type": "Feature",
  "properties": {
    "iso:country":"US",
    "sg:address":"2935 Elm St",
    "sg:city":"Dallas",
    "sg:classifiers":[
        {
            "category":"Restaurant",
            "type":"Food & Drink"
        }
    ],
    "sg:phone":"+1 214 744 6262",
    "sg:postcode":"75226",
    "sg:province":"TX",
    "sg:tags":[
        "italian"
    ],
    "wof:name":"Mama Mia Pizza & Pasta",
    "wof:placetype":"venue"
},
  "geometry": {"coordinates":[-96.781125,32.785419],"type":"Point"}
}