{
  "type": "Feature",
  "properties": {
    "iso:country":"US",
    "sg:address":"934 Sierra Shadows Dr",
    "sg:city":"Katy",
    "sg:classifiers":[
        {
            "category":"Wholesale",
            "subcategory":"Vending Machines",
            "type":"Manufacturing & Wholesale Goods"
        }
    ],
    "sg:phone":"+1 281 693 1410",
    "sg:postcode":"77450",
    "sg:province":"TX",
    "sg:tags":[
        "operator"
    ],
    "wof:name":"Melissa's College Vending Co",
    "wof:placetype":"venue"
},
  "geometry": {"coordinates":[-95.75478699999999,29.767388],"type":"Point"}
}