{
  "type": "Feature",
  "properties": {
    "iso:country":"US",
    "sg:address":"4215 Belclaire Ave",
    "sg:city":"Dallas",
    "sg:classifiers":[
        {
            "category":"Professional",
            "subcategory":"Business Services",
            "type":"Services"
        }
    ],
    "sg:phone":"+1 214 526 5216",
    "sg:postcode":"75205",
    "sg:province":"TX",
    "wof:name":"Beth V Ewing Designs",
    "wof:placetype":"venue"
},
  "geometry": {"coordinates":[-96.80666100000001,32.830124],"type":"Point"}
}