{
  "type": "Feature",
  "properties": {
    "iso:country":"US",
    "sg:address":"408 E Griffin Pkwy",
    "sg:city":"Mission",
    "sg:classifiers":[
        {
            "category":"Building & Trades",
            "subcategory":"Construction",
            "type":"Services"
        }
    ],
    "sg:phone":"+1 956 585 3388",
    "sg:postcode":"78572",
    "sg:province":"TX",
    "sg:tags":[
        "nonresidential"
    ],
    "wof:name":"Andis Construction",
    "wof:placetype":"venue"
},
  "geometry": {"coordinates":[-98.32073099999999,26.22929],"type":"Point"}
}