{
  "type": "Feature",
  "properties": {
    "iso:country":"US",
    "sg:address":"5506 Plumtree Dr",
    "sg:city":"San Antonio",
    "sg:classifiers":[
        {
            "category":"Professional",
            "type":"Services"
        }
    ],
    "sg:phone":"+1 210 673 2691",
    "sg:postcode":"78242",
    "sg:province":"TX",
    "wof:name":"Leticia F Duarte",
    "wof:placetype":"venue"
},
  "geometry": {"coordinates":[-98.602541,29.366961],"type":"Point"}
}