{
  "type": "Feature",
  "properties": {
    "iso:country":"US",
    "sg:address":"901 S Main St",
    "sg:city":"Fort Worth",
    "sg:classifiers":[
        {
            "category":"Professional",
            "subcategory":"Advertising",
            "type":"Services"
        }
    ],
    "sg:phone":"+1 817 332 1040",
    "sg:postcode":"76104",
    "sg:province":"TX",
    "sg:tags":[
        "counselor",
        "agency"
    ],
    "wof:name":"Main Station Advertising Inc",
    "wof:placetype":"venue"
},
  "geometry": {"coordinates":[-97.325873,32.734263],"type":"Point"}
}