{
  "type": "Feature",
  "properties": {
    "iso:country":"US",
    "sg:address":"330 S 5th St",
    "sg:city":"La Porte",
    "sg:classifiers":[
        {
            "category":"Shopping",
            "subcategory":"Hobbies, Toys, & Games",
            "type":"Retail Goods"
        }
    ],
    "sg:phone":"+1 281 471 1209",
    "sg:postcode":"77571",
    "sg:province":"TX",
    "wof:name":"Lucille H Singleton",
    "wof:placetype":"venue"
},
  "geometry": {"coordinates":[-95.024564,29.6624],"type":"Point"}
}