{
  "type": "Feature",
  "properties": {
    "iso:country":"US",
    "sg:address":"420 S Gaston St",
    "sg:city":"Crane",
    "sg:classifiers":[
        {
            "category":"Manufacturing",
            "subcategory":"Textiles",
            "type":"Manufacturing & Wholesale Goods"
        },
        {
            "category":"Manufacturing",
            "subcategory":"Apparel",
            "type":"Manufacturing & Wholesale Goods"
        }
    ],
    "sg:phone":"+1 432 558 3222",
    "sg:postcode":"79731",
    "sg:province":"TX",
    "sg:tags":[
        "c",
        "sheet",
        "fabric",
        "mfg",
        "canvas",
        "related",
        "product",
        "mill",
        "metalwork",
        "cotton"
    ],
    "wof:name":"Rig Canvas Co Inc",
    "wof:placetype":"venue"
},
  "geometry": {"coordinates":[-102.350883,31.39913],"type":"Point"}
}