{
  "type": "Feature",
  "properties": {
    "iso:country":"US",
    "sg:address":"410 Alamo St",
    "sg:city":"Hidalgo",
    "sg:classifiers":[
        {
            "category":"Personal",
            "subcategory":"Beauty Salon",
            "type":"Services"
        }
    ],
    "sg:phone":"+1 956 843 7240",
    "sg:postcode":"78557",
    "sg:province":"TX",
    "sg:tags":[
        "shop"
    ],
    "wof:name":"Secret Garden Beauty Salon",
    "wof:placetype":"venue"
},
  "geometry": {"coordinates":[-98.228881,26.104554],"type":"Point"}
}