{
  "type": "Feature",
  "properties": {
    "iso:country":"US",
    "sg:address":"7324 Marlborough Dr W",
    "sg:city":"Fort Worth",
    "sg:classifiers":[
        {
            "category":"Shopping",
            "subcategory":"Clothing, Apparel, & Fashions",
            "type":"Retail Goods"
        }
    ],
    "sg:phone":"+1 817 551 6206",
    "sg:postcode":"76134",
    "sg:province":"TX",
    "wof:name":"Gibsons Resale",
    "wof:placetype":"venue"
},
  "geometry": {"coordinates":[-97.34157999999999,32.639873],"type":"Point"}
}