{
  "type": "Feature",
  "properties": {
    "iso:country":"US",
    "sg:address":"4610 Morelos Rd",
    "sg:city":"Baytown",
    "sg:classifiers":[
        {
            "category":"Manufacturing",
            "subcategory":"Tools & Machinery",
            "type":"Manufacturing & Wholesale Goods"
        }
    ],
    "sg:phone":"+1 281 424 6648",
    "sg:postcode":"77521",
    "sg:province":"TX",
    "sg:tags":[
        "industrial",
        "tank",
        "cleaning"
    ],
    "wof:name":"Mtz Hydro-Blast",
    "wof:placetype":"venue"
},
  "geometry": {"coordinates":[-95.008217,29.794064],"type":"Point"}
}