{
  "type": "Feature",
  "properties": {
    "iso:country":"US",
    "sg:address":"129 Center St",
    "sg:city":"Whitesboro",
    "sg:classifiers":[
        {
            "category":"Organizations",
            "subcategory":"Religious Organization",
            "type":"Services"
        }
    ],
    "sg:phone":"+1 903 564 4636",
    "sg:postcode":"76273",
    "sg:province":"TX",
    "sg:tags":[
        "church"
    ],
    "wof:name":"First Bapt Church Youth Phone",
    "wof:placetype":"venue"
},
  "geometry": {"coordinates":[-96.905401,33.65771],"type":"Point"}
}