{
  "type": "Feature",
  "properties": {
    "iso:country":"US",
    "sg:address":"5020 Old Seguin Rd",
    "sg:city":"San Antonio",
    "sg:classifiers":[
        {
            "category":"Freight",
            "type":"Transportation"
        }
    ],
    "sg:phone":"+1 209 403 7368",
    "sg:postcode":"78219",
    "sg:province":"TX",
    "sg:tags":[
        "operator",
        "local",
        "trucking"
    ],
    "wof:name":"Jesus Aguinaga",
    "wof:placetype":"venue"
},
  "geometry": {"coordinates":[-98.39249100000001,29.465833],"type":"Point"}
}