{
  "type": "Feature",
  "properties": {
    "iso:country":"US",
    "sg:address":"1521 S Sam Rayburn Fwy",
    "sg:city":"Sherman",
    "sg:classifiers":[
        {
            "category":"Food & Beverages",
            "subcategory":"Candy",
            "type":"Retail Goods"
        }
    ],
    "sg:phone":"+1 903 813 4176",
    "sg:postcode":"75090",
    "sg:province":"TX",
    "sg:tags":[
        "confectionery"
    ],
    "wof:name":"Buford's Fun & Nut Co",
    "wof:placetype":"venue"
},
  "geometry": {"coordinates":[-96.610159,33.618708],"type":"Point"}
}