{
  "type": "Feature",
  "properties": {
    "iso:country":"US",
    "sg:address":"248 Trinity Pl",
    "sg:city":"El Paso",
    "sg:classifiers":[
        {
            "category":"Building & Trades",
            "subcategory":"Construction",
            "type":"Services"
        }
    ],
    "sg:phone":"+1 915 772 6883",
    "sg:postcode":"79905",
    "sg:province":"TX",
    "sg:tags":[
        "tile",
        "dealer"
    ],
    "wof:name":"Armando Rojero Ceramic Tile",
    "wof:placetype":"venue"
},
  "geometry": {"coordinates":[-106.41488200000001,31.761687],"type":"Point"}
}