{
  "type": "Feature",
  "properties": {
    "iso:country":"US",
    "sg:address":"1012 Forest Ave",
    "sg:city":"Tyler",
    "sg:classifiers":[
        {
            "category":"Professional",
            "subcategory":"Lawyer & Legal Services",
            "type":"Services"
        }
    ],
    "sg:phone":"+1 903 595 5000",
    "sg:postcode":"75702",
    "sg:province":"TX",
    "sg:tags":[
        "firm",
        "law"
    ],
    "wof:name":"Weathers and Weathers",
    "wof:placetype":"venue"
},
  "geometry": {"coordinates":[-95.321276,32.361634],"type":"Point"}
}