{
  "type": "Feature",
  "properties": {
    "iso:country":"US",
    "sg:address":"1822 N Main St",
    "sg:city":"Cleburne",
    "sg:classifiers":[
        {
            "category":"Building & Trades",
            "subcategory":"Equipment Rental",
            "type":"Services"
        }
    ],
    "sg:phone":"+1 817 641 0408",
    "sg:postcode":"76033",
    "sg:province":"TX",
    "sg:tags":[
        "yard"
    ],
    "wof:name":"ABS Rentals",
    "wof:placetype":"venue"
},
  "geometry": {"coordinates":[-97.395949,32.369465],"type":"Point"}
}