{
  "type": "Feature",
  "properties": {
    "iso:country":"US",
    "sg:address":"2208 Pessara St",
    "sg:city":"La Marque",
    "sg:classifiers":[
        {
            "category":"Building & Trades",
            "subcategory":"Landscaping Services",
            "type":"Services"
        }
    ],
    "sg:phone":"+1 409 938 0506",
    "sg:postcode":"77568",
    "sg:province":"TX",
    "wof:name":"O M Lawn Care",
    "wof:placetype":"venue"
},
  "geometry": {"coordinates":[-94.975977,29.359041],"type":"Point"}
}