{
  "type": "Feature",
  "properties": {
    "iso:country":"US",
    "sg:address":"3424 Sorrento Dr",
    "sg:city":"Mesquite",
    "sg:classifiers":[
        {
            "category":"Travel",
            "subcategory":"Hotels & Motels",
            "type":"Entertainment"
        }
    ],
    "sg:phone":"+1 972 682 0400",
    "sg:postcode":"75150",
    "sg:province":"TX",
    "wof:name":"Microtel Inns & Suites",
    "wof:placetype":"venue"
},
  "geometry": {"coordinates":[-96.653904,32.808192],"type":"Point"}
}