{
  "type": "Feature",
  "properties": {
    "iso:country":"US",
    "sg:address":"5 Mystic Ct",
    "sg:city":"Mansfield",
    "sg:classifiers":[
        {
            "category":"Real Estate",
            "subcategory":"Real Estate Agent",
            "type":"Services"
        }
    ],
    "sg:phone":"+1 817 477 9496",
    "sg:postcode":"76063",
    "sg:province":"TX",
    "sg:tags":[
        "information",
        "referral"
    ],
    "wof:name":"Goombays Getaway",
    "wof:placetype":"venue"
},
  "geometry": {"coordinates":[-97.073122,32.554519],"type":"Point"}
}