{
  "type": "Feature",
  "properties": {
    "iso:country":"US",
    "sg:address":"706 US Hwy 69",
    "sg:city":"Rusk",
    "sg:classifiers":[
        {
            "category":"Retail",
            "subcategory":"Auto Repair",
            "type":"Services"
        }
    ],
    "sg:phone":"+1 903 683 3131",
    "sg:postcode":"75785",
    "sg:province":"TX",
    "sg:tags":[
        "repairing",
        "automobile"
    ],
    "wof:name":"G & G Auto Repair",
    "wof:placetype":"venue"
},
  "geometry": {"coordinates":[-95.147705,31.801903],"type":"Point"}
}