{
  "type": "Feature",
  "properties": {
    "iso:country":"US",
    "sg:address":"212 James Dr",
    "sg:city":"Rockwall",
    "sg:classifiers":[
        {
            "category":"Organizations",
            "subcategory":"Labor Organization",
            "type":"Services"
        }
    ],
    "sg:phone":"+1 972 771 6424",
    "sg:postcode":"75032",
    "sg:province":"TX",
    "wof:name":"Dallas Soc For Bnrgetc Therapy",
    "wof:placetype":"venue"
},
  "geometry": {"coordinates":[-96.50079599999999,32.82844],"type":"Point"}
}