{
  "type": "Feature",
  "properties": {
    "iso:country":"US",
    "sg:address":"8711 State Hwy 136",
    "sg:city":"Amarillo",
    "sg:classifiers":[
        {
            "category":"Building & Trades",
            "subcategory":"Plumbing",
            "type":"Services"
        }
    ],
    "sg:phone":"+1 806 335 2769",
    "sg:postcode":"79108",
    "sg:province":"TX",
    "sg:tags":[
        "tank",
        "septic"
    ],
    "wof:name":"Boyd's Backhoe Svc",
    "wof:placetype":"venue"
},
  "geometry": {"coordinates":[-101.692381,35.300033],"type":"Point"}
}