{
  "type": "Feature",
  "properties": {
    "iso:country":"US",
    "sg:address":"1221 Crampton St",
    "sg:city":"Dallas",
    "sg:classifiers":[
        {
            "category":"Home & Garden",
            "subcategory":"Furniture",
            "type":"Retail Goods"
        }
    ],
    "sg:phone":"+1 972 241 0600",
    "sg:postcode":"75207",
    "sg:province":"TX",
    "sg:tags":[
        "store"
    ],
    "wof:name":"Orion Furniture Express",
    "wof:placetype":"venue"
},
  "geometry": {"coordinates":[-96.84030199999999,32.7994],"type":"Point"}
}