{
  "type": "Feature",
  "properties": {
    "iso:country":"US",
    "sg:address":"215 Robin Hill Ln",
    "sg:city":"Duncanville",
    "sg:classifiers":[
        {
            "category":"Professional",
            "subcategory":"Management & Consulting",
            "type":"Services"
        }
    ],
    "sg:phone":"+1 972 709 6788",
    "sg:postcode":"75137",
    "sg:province":"TX",
    "sg:tags":[
        "relations",
        "computer",
        "public",
        "related"
    ],
    "wof:name":"Pro Comp Sales Company Inc",
    "wof:placetype":"venue"
},
  "geometry": {"coordinates":[-96.915784,32.635627],"type":"Point"}
}