{
  "type": "Feature",
  "properties": {
    "iso:country":"US",
    "sg:address":"1311 N Main St",
    "sg:city":"Mcallen",
    "sg:classifiers":[
        {
            "category":"Food & Beverages",
            "subcategory":"Bakery",
            "type":"Retail Goods"
        }
    ],
    "sg:phone":"+1 956 668 7437",
    "sg:postcode":"78501",
    "sg:province":"TX",
    "wof:name":"Sweet N Tasty",
    "wof:placetype":"venue"
},
  "geometry": {"coordinates":[-98.23230599999999,26.216694],"type":"Point"}
}