{
  "type": "Feature",
  "properties": {
    "iso:country":"US",
    "sg:address":"2421 W Interstate 20 State Rte",
    "sg:city":"Odessa",
    "sg:classifiers":[
        {
            "category":"Retail",
            "subcategory":"Auto Repair",
            "type":"Services"
        }
    ],
    "sg:phone":"+1 432 333 4133",
    "sg:postcode":"79766",
    "sg:province":"TX",
    "sg:tags":[
        "glass",
        "replacement"
    ],
    "wof:name":"Champion Auto Glass",
    "wof:placetype":"venue"
},
  "geometry": {"coordinates":[-102.388279,31.816734],"type":"Point"}
}