{
  "type": "Feature",
  "properties": {
    "iso:country":"US",
    "sg:address":"2315 Harris Ln",
    "sg:city":"Fort Worth",
    "sg:classifiers":[
        {
            "category":"Wholesale",
            "subcategory":"Construction Materials",
            "type":"Manufacturing & Wholesale Goods"
        }
    ],
    "sg:phone":"+1 817 831 2104",
    "sg:postcode":"76117",
    "sg:province":"TX",
    "sg:tags":[
        "fence"
    ],
    "wof:name":"Kustom Fence",
    "wof:placetype":"venue"
},
  "geometry": {"coordinates":[-97.27846099999999,32.791258],"type":"Point"}
}