{
  "type": "Feature",
  "properties": {
    "iso:country":"US",
    "sg:address":"2117 Franklin Dr",
    "sg:city":"Arlington",
    "sg:classifiers":[
        {
            "category":"Wholesale",
            "subcategory":"Stationery",
            "type":"Manufacturing & Wholesale Goods"
        }
    ],
    "sg:phone":"+1 817 625 5201",
    "sg:postcode":"76011",
    "sg:province":"TX",
    "sg:tags":[
        "product",
        "paper"
    ],
    "wof:name":"Olmsted-KIRK Paper Co",
    "wof:placetype":"venue"
},
  "geometry": {"coordinates":[-97.10886600000001,32.771165],"type":"Point"}
}