{
  "type": "Feature",
  "properties": {
    "iso:country":"US",
    "sg:address":"613 Louisiana St",
    "sg:city":"South Houston",
    "sg:classifiers":[
        {
            "category":"Building & Trades",
            "subcategory":"Construction",
            "type":"Services"
        }
    ],
    "sg:phone":"+1 713 946 6614",
    "sg:postcode":"77587",
    "sg:province":"TX",
    "sg:tags":[
        "fabricator",
        "metal"
    ],
    "sg:website":"www.gulfexinc.com",
    "wof:name":"Gulfex Inc",
    "wof:placetype":"venue"
},
  "geometry": {"coordinates":[-95.244309,29.668478],"type":"Point"}
}