{
  "type": "Feature",
  "properties": {
    "iso:country":"US",
    "sg:address":"3800 E 42nd St",
    "sg:city":"Odessa",
    "sg:classifiers":[
        {
            "category":"Wholesale",
            "subcategory":"Auto Parts",
            "type":"Manufacturing & Wholesale Goods"
        }
    ],
    "sg:phone":"+1 432 367 7255",
    "sg:postcode":"79762",
    "sg:province":"TX",
    "wof:name":"Direct Tyres",
    "wof:placetype":"venue"
},
  "geometry": {"coordinates":[-102.34176600000001,31.89181],"type":"Point"}
}