{
  "type": "Feature",
  "properties": {
    "iso:country":"US",
    "sg:address":"2800 Lometa Dr",
    "sg:city":"Amarillo",
    "sg:classifiers":[
        {
            "category":"Real Estate",
            "subcategory":"Real Estate Operator",
            "type":"Services"
        }
    ],
    "sg:phone":"+1 806 355 8061",
    "sg:postcode":"79109",
    "sg:province":"TX",
    "sg:tags":[
        "building",
        "apartment"
    ],
    "wof:name":"Lexington Apartments The",
    "wof:placetype":"venue"
},
  "geometry": {"coordinates":[-101.879643,35.185006],"type":"Point"}
}