{
  "type": "Feature",
  "properties": {
    "iso:country":"US",
    "sg:address":"114 Oak Grove",
    "sg:city":"Dale",
    "sg:classifiers":[
        {
            "category":"Building & Trades",
            "subcategory":"Construction",
            "type":"Services"
        }
    ],
    "sg:phone":"+1 512 243 3701",
    "sg:postcode":"78616",
    "sg:province":"TX",
    "sg:tags":[
        "carpentry",
        "contractor"
    ],
    "wof:name":"Bishop Custom Trim",
    "wof:placetype":"venue"
},
  "geometry": {"coordinates":[-97.597599,30.067224],"type":"Point"}
}