{
  "type": "Feature",
  "properties": {
    "iso:country":"US",
    "sg:address":"7118 Hand Rd",
    "sg:city":"Richmond",
    "sg:classifiers":[
        {
            "category":"Insurance",
            "subcategory":"Insurance Agent",
            "type":"Services"
        }
    ],
    "sg:phone":"+1 281 232 6931",
    "sg:postcode":"77469",
    "sg:province":"TX",
    "sg:tags":[
        "agency"
    ],
    "wof:name":"Thieleman Insurance",
    "wof:placetype":"venue"
},
  "geometry": {"coordinates":[-95.765676,29.476426],"type":"Point"}
}