{
  "type": "Feature",
  "properties": {
    "iso:country":"US",
    "sg:address":"4620 Dyer St",
    "sg:city":"El Paso",
    "sg:classifiers":[
        {
            "category":"Bars & Pubs",
            "type":"Food & Drink"
        }
    ],
    "sg:phone":"+1 915 564 4007",
    "sg:postcode":"79930",
    "sg:province":"TX",
    "sg:tags":[
        "club",
        "night"
    ],
    "wof:name":"Shark Bar & Nightclub",
    "wof:placetype":"venue"
},
  "geometry": {"coordinates":[-106.44458299999999,31.818026],"type":"Point"}
}