{
  "type": "Feature",
  "properties": {
    "iso:country":"US",
    "sg:address":"3959 Ridgeoak Way",
    "sg:city":"Dallas",
    "sg:classifiers":[
        {
            "category":"Health Services",
            "subcategory":"Nursing And Care Facility",
            "type":"Services"
        }
    ],
    "sg:phone":"+1 972 241 7148",
    "sg:postcode":"75244",
    "sg:province":"TX",
    "wof:name":"Volunteer America",
    "wof:placetype":"venue"
},
  "geometry": {"coordinates":[-96.849807,32.921666],"type":"Point"}
}