{
  "type": "Feature",
  "properties": {
    "iso:country":"US",
    "sg:address":"1216 Lausanne Ave",
    "sg:city":"Dallas",
    "sg:classifiers":[
        {
            "category":"Professional",
            "subcategory":"Business Services",
            "type":"Services"
        }
    ],
    "sg:phone":"+1 214 946 8549",
    "sg:postcode":"75208",
    "sg:province":"TX",
    "wof:name":"Brobus Technologies",
    "wof:placetype":"venue"
},
  "geometry": {"coordinates":[-96.844807,32.761097],"type":"Point"}
}