{
  "type": "Feature",
  "properties": {
    "iso:country":"US",
    "sg:address":"235 W Main St",
    "sg:city":"Fredericksburg",
    "sg:classifiers":[
        {
            "category":"Banks & Credit Unions",
            "subcategory":"Investment Brokerage",
            "type":"Services"
        }
    ],
    "sg:phone":"+1 830 997 7403",
    "sg:postcode":"78624",
    "sg:province":"TX",
    "wof:name":"Cimarron Investment Advisors",
    "wof:placetype":"venue"
},
  "geometry": {"coordinates":[-98.87519500000001,30.277138],"type":"Point"}
}