{
  "type": "Feature",
  "properties": {
    "iso:country":"US",
    "sg:address":"2069 Southgate Blvd",
    "sg:city":"Houston",
    "sg:classifiers":[
        {
            "category":"Professional",
            "subcategory":"Business Services",
            "type":"Services"
        }
    ],
    "sg:phone":"+1 713 668 2305",
    "sg:postcode":"77030",
    "sg:province":"TX",
    "wof:name":"Doddlebug Design",
    "wof:placetype":"venue"
},
  "geometry": {"coordinates":[-95.404988,29.709296],"type":"Point"}
}