{
  "type": "Feature",
  "properties": {
    "iso:country":"US",
    "sg:address":"9198 Old Katy Rd",
    "sg:city":"Houston",
    "sg:classifiers":[
        {
            "category":"Shopping",
            "subcategory":"Crafts & Fabrics",
            "type":"Retail Goods"
        }
    ],
    "sg:phone":"+1 713 464 8653",
    "sg:postcode":"77055",
    "sg:province":"TX",
    "sg:tags":[
        "sewing"
    ],
    "wof:name":"Calico Corners",
    "wof:placetype":"venue"
},
  "geometry": {"coordinates":[-95.515925,29.784754],"type":"Point"}
}