{
  "type": "Feature",
  "properties": {
    "iso:country":"US",
    "sg:address":"181 W Harwood Rd",
    "sg:city":"Hurst",
    "sg:classifiers":[
        {
            "category":"Food & Beverages",
            "subcategory":"Candy",
            "type":"Retail Goods"
        }
    ],
    "sg:phone":"+1 817 282 9400",
    "sg:postcode":"76054",
    "sg:province":"TX",
    "sg:tags":[
        "confectionery"
    ],
    "wof:name":"Hot Chocolate LTD Co",
    "wof:placetype":"venue"
},
  "geometry": {"coordinates":[-97.171789,32.849365],"type":"Point"}
}