{
  "type": "Feature",
  "properties": {
    "iso:country":"US",
    "sg:address":"308 Casa Dr",
    "sg:city":"Copperas Cove",
    "sg:classifiers":[
        {
            "category":"Personal",
            "subcategory":"Beauty Salon",
            "type":"Services"
        }
    ],
    "sg:phone":"+1 254 547 7459",
    "sg:postcode":"76522",
    "sg:province":"TX",
    "wof:name":"Kimberly's Hair Salon",
    "wof:placetype":"venue"
},
  "geometry": {"coordinates":[-97.912925,31.112491],"type":"Point"}
}