{
  "type": "Feature",
  "properties": {
    "iso:country":"US",
    "sg:address":"9003 Main St",
    "sg:city":"Needville",
    "sg:classifiers":[
        {
            "category":"Shopping",
            "subcategory":"Pharmacy",
            "type":"Retail Goods"
        }
    ],
    "sg:phone":"+1 979 793 4252",
    "sg:postcode":"77461",
    "sg:province":"TX",
    "wof:name":"City Drug Store",
    "wof:placetype":"venue"
},
  "geometry": {"coordinates":[-95.83778599999999,29.399329],"type":"Point"}
}