{
  "type": "Feature",
  "properties": {
    "iso:country":"US",
    "sg:address":"3818 Fuqua St",
    "sg:city":"Houston",
    "sg:classifiers":[
        {
            "category":"Bars & Pubs",
            "type":"Food & Drink"
        }
    ],
    "sg:phone":"+1 713 733 8130",
    "sg:postcode":"77047",
    "sg:province":"TX",
    "sg:tags":[
        "drinking"
    ],
    "wof:name":"Hop Os",
    "wof:placetype":"venue"
},
  "geometry": {"coordinates":[-95.360392,29.612137],"type":"Point"}
}