{
  "type": "Feature",
  "properties": {
    "iso:country":"US",
    "sg:address":"705 Plumbago Dr",
    "sg:city":"Pflugerville",
    "sg:classifiers":[
        {
            "category":"Manufacturing",
            "subcategory":"Apparel",
            "type":"Manufacturing & Wholesale Goods"
        }
    ],
    "sg:phone":"+1 512 252 0550",
    "sg:postcode":"78660",
    "sg:province":"TX",
    "sg:tags":[
        "household",
        "furnishing",
        "mfg"
    ],
    "wof:name":"Dawns Decorative Crafts",
    "wof:placetype":"venue"
},
  "geometry": {"coordinates":[-97.6027,30.438311],"type":"Point"}
}