{
  "type": "Feature",
  "properties": {
    "iso:country":"US",
    "sg:address":"1004 Creekbend Cove",
    "sg:city":"Pflugerville",
    "sg:classifiers":[
        {
            "category":"Building & Trades",
            "subcategory":"Construction",
            "type":"Services"
        }
    ],
    "sg:phone":"+1 512 251 2002",
    "sg:postcode":"78660",
    "sg:province":"TX",
    "sg:tags":[
        "hanging",
        "contractor"
    ],
    "wof:name":"Lone Star Wallcovering",
    "wof:placetype":"venue"
},
  "geometry": {"coordinates":[-97.61875000000001,30.447576],"type":"Point"}
}