{
  "type": "Feature",
  "properties": {
    "iso:country":"US",
    "sg:address":"306 W 61st St",
    "sg:city":"Odessa",
    "sg:classifiers":[
        {
            "category":"Manufacturing",
            "subcategory":"Tools & Machinery",
            "type":"Manufacturing & Wholesale Goods"
        }
    ],
    "sg:phone":"+1 432 367 0008",
    "sg:postcode":"79764",
    "sg:province":"TX",
    "sg:tags":[
        "machine",
        "shop"
    ],
    "wof:name":"Bear's Machine & Mfg Co",
    "wof:placetype":"venue"
},
  "geometry": {"coordinates":[-102.396208,31.900103],"type":"Point"}
}