{
  "type": "Feature",
  "properties": {
    "iso:country":"US",
    "sg:address":"5601 Sears St",
    "sg:city":"Dallas",
    "sg:classifiers":[
        {
            "category":"Food & Beverages",
            "subcategory":"Specialty",
            "type":"Retail Goods"
        }
    ],
    "sg:phone":"+1 214 370 3038",
    "sg:postcode":"75206",
    "sg:province":"TX",
    "sg:tags":[
        "gourmet",
        "shop"
    ],
    "wof:name":"Jacki's Gourmet",
    "wof:placetype":"venue"
},
  "geometry": {"coordinates":[-96.77019300000001,32.814569],"type":"Point"}
}