{
  "type": "Feature",
  "properties": {
    "iso:country":"US",
    "sg:address":"1285 Joe Battle Blvd",
    "sg:city":"El Paso",
    "sg:classifiers":[
        {
            "category":"Utilities",
            "subcategory":"Cable",
            "type":"Services"
        }
    ],
    "sg:phone":"+1 915 298 5900",
    "sg:postcode":"79936",
    "sg:province":"TX",
    "sg:tags":[
        "broadcast",
        "equipment",
        "satellite",
        "television",
        "direct"
    ],
    "wof:name":"Echostar Communications Corp",
    "wof:placetype":"venue"
},
  "geometry": {"coordinates":[-106.28879999999999,31.697556],"type":"Point"}
}