{
  "type": "Feature",
  "properties": {
    "iso:country":"US",
    "sg:address":"2400 Beaumont Ave",
    "sg:city":"Liberty",
    "sg:classifiers":[
        {
            "category":"Government",
            "subcategory":"Jail",
            "type":"Public Place"
        }
    ],
    "sg:phone":"+1 936 334 1884",
    "sg:postcode":"77575",
    "sg:province":"TX",
    "sg:tags":[
        "correctional",
        "institution"
    ],
    "wof:name":"Aramark",
    "wof:placetype":"venue"
},
  "geometry": {"coordinates":[-94.78970099999999,30.05939],"type":"Point"}
}