{
  "type": "Feature",
  "properties": {
    "iso:country":"US",
    "sg:address":"4000 FM 1788 S",
    "sg:city":"Midland",
    "sg:classifiers":[
        {
            "category":"Autos & Motor Vehicles",
            "subcategory":"Auto Supplies",
            "type":"Retail Goods"
        }
    ],
    "sg:phone":"+1 432 563 1981",
    "sg:postcode":"79706",
    "sg:province":"TX",
    "sg:tags":[
        "automobile",
        "parts"
    ],
    "wof:name":"Western Auto",
    "wof:placetype":"venue"
},
  "geometry": {"coordinates":[-102.216758,31.915443],"type":"Point"}
}