{
  "type": "Feature",
  "properties": {
    "iso:country":"US",
    "sg:address":"3020 6th Ave",
    "sg:city":"Fort Worth",
    "sg:classifiers":[
        {
            "category":"Education",
            "subcategory":"Special Training",
            "type":"Public Place"
        }
    ],
    "sg:phone":"+1 817 924 2144",
    "sg:postcode":"76110",
    "sg:province":"TX",
    "sg:tags":[
        "organization",
        "membership",
        "mi"
    ],
    "wof:name":"James Jims Athletic Massage E",
    "wof:placetype":"venue"
},
  "geometry": {"coordinates":[-97.340614,32.707098],"type":"Point"}
}