{
  "type": "Feature",
  "properties": {
    "iso:country":"US",
    "sg:address":"1857 Bingle Rd",
    "sg:city":"Houston",
    "sg:classifiers":[
        {
            "category":"Professional",
            "subcategory":"Computer Services",
            "type":"Services"
        }
    ],
    "sg:phone":"+1 713 270 1231",
    "sg:postcode":"77055",
    "sg:province":"TX",
    "sg:tags":[
        "repair"
    ],
    "wof:name":"Windows Support",
    "wof:placetype":"venue"
},
  "geometry": {"coordinates":[-95.501108,29.805336],"type":"Point"}
}