{
  "type": "Feature",
  "properties": {
    "iso:country":"US",
    "sg:address":"1621 Spicewood Dr",
    "sg:city":"Corpus Christi",
    "sg:classifiers":[
        {
            "category":"Shopping",
            "subcategory":"Hobbies, Toys, & Games",
            "type":"Retail Goods"
        }
    ],
    "sg:phone":"+1 361 991 3641",
    "sg:postcode":"78412",
    "sg:province":"TX",
    "wof:name":"Bee It Crafts",
    "wof:placetype":"venue"
},
  "geometry": {"coordinates":[-97.359622,27.6998],"type":"Point"}
}