{
  "type": "Feature",
  "properties": {
    "iso:country":"US",
    "sg:address":"6015 Callaghan Rd",
    "sg:city":"San Antonio",
    "sg:classifiers":[
        {
            "category":"Professional",
            "subcategory":"Art Services",
            "type":"Services"
        }
    ],
    "sg:phone":"+1 210 223 4357",
    "sg:postcode":"78228",
    "sg:province":"TX",
    "sg:tags":[
        "graphic",
        "designer"
    ],
    "wof:name":"Visuals Business Solutions",
    "wof:placetype":"venue"
},
  "geometry": {"coordinates":[-98.576213,29.487573],"type":"Point"}
}