{
  "type": "Feature",
  "properties": {
    "iso:country":"US",
    "sg:address":"633 W 13th St",
    "sg:city":"Austin",
    "sg:classifiers":[
        {
            "category":"Building & Trades",
            "subcategory":"Locksmith",
            "type":"Services"
        }
    ],
    "sg:phone":"+1 800 556 5582",
    "sg:postcode":"78701",
    "sg:province":"TX",
    "sg:tags":[
        "lock"
    ],
    "wof:name":"Team Locksmith",
    "wof:placetype":"venue"
},
  "geometry": {"coordinates":[-97.745943,30.276651],"type":"Point"}
}