{
  "type": "Feature",
  "properties": {
    "iso:country":"US",
    "sg:address":"315 E Church St",
    "sg:city":"Livingston",
    "sg:classifiers":[
        {
            "category":"Home & Garden",
            "subcategory":"Furniture",
            "type":"Retail Goods"
        }
    ],
    "sg:phone":"+1 936 327 8180",
    "sg:postcode":"77351",
    "sg:province":"TX",
    "sg:tags":[
        "store"
    ],
    "wof:name":"Second Chance",
    "wof:placetype":"venue"
},
  "geometry": {"coordinates":[-94.930997,30.710932],"type":"Point"}
}