{
  "type": "Feature",
  "properties": {
    "iso:country":"US",
    "sg:address":"1130 Hollywood Ave",
    "sg:city":"Dallas",
    "sg:classifiers":[
        {
            "category":"Manufacturing",
            "subcategory":"Tools & Machinery",
            "type":"Manufacturing & Wholesale Goods"
        }
    ],
    "sg:phone":"+1 214 942 7247",
    "sg:postcode":"75208",
    "sg:province":"TX",
    "sg:tags":[
        "lamp",
        "electric",
        "mfg"
    ],
    "wof:name":"Outta Bounds Studio",
    "wof:placetype":"venue"
},
  "geometry": {"coordinates":[-96.85542100000001,32.733728],"type":"Point"}
}