{
  "type": "Feature",
  "properties": {
    "iso:country":"US",
    "sg:address":"1110 Chamberlain St",
    "sg:city":"Irving",
    "sg:classifiers":[
        {
            "category":"Organizations",
            "subcategory":"Non-profit Organization",
            "type":"Services"
        }
    ],
    "sg:phone":"+1 972 554 8766",
    "sg:postcode":"75060",
    "sg:province":"TX",
    "sg:tags":[
        "social"
    ],
    "wof:name":"Rocio Home Painting",
    "wof:placetype":"venue"
},
  "geometry": {"coordinates":[-96.932158,32.802469],"type":"Point"}
}