{
  "type": "Feature",
  "properties": {
    "iso:country":"US",
    "sg:address":"2750 McCree Rd",
    "sg:city":"Garland",
    "sg:classifiers":[
        {
            "category":"Shopping",
            "type":"Retail Goods"
        },
        {
            "category":"Building & Trades",
            "subcategory":"Construction",
            "type":"Services"
        }
    ],
    "sg:phone":"+1 972 271 2441",
    "sg:postcode":"75041",
    "sg:province":"TX",
    "sg:tags":[
        "designer",
        "material",
        "merchandise",
        "dealer",
        "pool",
        "swimming"
    ],
    "sg:website":"www.morganusa.com",
    "wof:name":"Morgan Buildings & Spas Inc",
    "wof:placetype":"venue"
},
  "geometry": {"coordinates":[-96.671432,32.871456],"type":"Point"}
}