{
  "type": "Feature",
  "properties": {
    "iso:country":"US",
    "sg:address":"721 Hempel Dr",
    "sg:city":"Copperas Cove",
    "sg:classifiers":[
        {
            "category":"Building & Trades",
            "subcategory":"Construction",
            "type":"Services"
        }
    ],
    "sg:phone":"+1 254 542 1606",
    "sg:postcode":"76522",
    "sg:province":"TX",
    "sg:tags":[
        "excavating",
        "contractor"
    ],
    "wof:name":"Donald Hempel Construction",
    "wof:placetype":"venue"
},
  "geometry": {"coordinates":[-97.905507,31.19003],"type":"Point"}
}