{
  "type": "Feature",
  "properties": {
    "iso:country":"US",
    "sg:address":"5951 Ingram Rd",
    "sg:city":"San Antonio",
    "sg:classifiers":[
        {
            "category":"Banks & Credit Unions",
            "subcategory":"Bank",
            "type":"Services"
        }
    ],
    "sg:phone":"+1 210 436 8986",
    "sg:postcode":"78228",
    "sg:province":"TX",
    "sg:tags":[
        "depository",
        "banking"
    ],
    "wof:name":"ACE Cash Express",
    "wof:placetype":"venue"
},
  "geometry": {"coordinates":[-98.60001800000001,29.465908],"type":"Point"}
}