{
  "type": "Feature",
  "properties": {
    "iso:country":"US",
    "sg:address":"412 E Grand Ave",
    "sg:city":"Marshall",
    "sg:classifiers":[
        {
            "category":"Banks & Credit Unions",
            "subcategory":"Bank",
            "type":"Services"
        }
    ],
    "sg:phone":"+1 903 693 2257",
    "sg:postcode":"75670",
    "sg:province":"TX",
    "wof:name":"Gurantee Federal Bank",
    "wof:placetype":"venue"
},
  "geometry": {"coordinates":[-94.364234,32.548467],"type":"Point"}
}