{
  "type": "Feature",
  "properties": {
    "iso:country":"US",
    "sg:address":"914 Frost St",
    "sg:city":"Rosenberg",
    "sg:classifiers":[
        {
            "category":"Social Services",
            "type":"Services"
        }
    ],
    "sg:phone":"+1 281 344 9911",
    "sg:postcode":"77471",
    "sg:province":"TX",
    "sg:tags":[
        "care",
        "center",
        "day"
    ],
    "wof:name":"Caring People",
    "wof:placetype":"venue"
},
  "geometry": {"coordinates":[-95.815724,29.55896],"type":"Point"}
}