{
  "type": "Feature",
  "properties": {
    "iso:country":"US",
    "sg:address":"821 Blue Jay Ln",
    "sg:city":"Coppell",
    "sg:classifiers":[
        {
            "category":"Professional",
            "type":"Services"
        }
    ],
    "sg:phone":"+1 972 393 3646",
    "sg:postcode":"75019",
    "sg:province":"TX",
    "wof:name":"Qualisoft Corp",
    "wof:placetype":"venue"
},
  "geometry": {"coordinates":[-96.965502,32.958725],"type":"Point"}
}