{
  "type": "Feature",
  "properties": {
    "iso:country":"US",
    "sg:address":"1315 Kimberly Dr",
    "sg:city":"Laredo",
    "sg:classifiers":[
        {
            "category":"Building & Trades",
            "subcategory":"Landscaping Services",
            "type":"Services"
        }
    ],
    "sg:phone":"+1 956 725 8709",
    "sg:postcode":"78045",
    "sg:province":"TX",
    "sg:tags":[
        "lawn",
        "maintenance",
        "grounds"
    ],
    "wof:name":"Lawn Maintenance & General Svc",
    "wof:placetype":"venue"
},
  "geometry": {"coordinates":[-99.466538,27.590541],"type":"Point"}
}