{
  "type": "Feature",
  "properties": {
    "iso:country":"US",
    "sg:address":"7801 N Lamar Blvd",
    "sg:city":"Austin",
    "sg:classifiers":[
        {
            "category":"Professional",
            "subcategory":"Printing & Photocopies",
            "type":"Services"
        },
        {
            "category":"Wholesale",
            "subcategory":"Books, Periodicals, & Newspapers",
            "type":"Manufacturing & Wholesale Goods"
        }
    ],
    "sg:phone":"+1 512 451 2679",
    "sg:postcode":"78752",
    "sg:province":"TX",
    "sg:tags":[
        "publisher",
        "duplicating",
        "copying",
        "lithographer"
    ],
    "sg:website":"http://www.allegranetwork.com",
    "wof:name":"Allegra Print & Imaging",
    "wof:placetype":"venue"
},
  "geometry": {"coordinates":[-97.71328800000001,30.345833],"type":"Point"}
}