{
  "type": "Feature",
  "properties": {
    "iso:country":"US",
    "sg:address":"901 N Oak Ave",
    "sg:city":"Mineral Wells",
    "sg:classifiers":[
        {
            "category":"Organizations",
            "subcategory":"Religious Organization",
            "type":"Services"
        }
    ],
    "sg:phone":"+1 940 325 6274",
    "sg:postcode":"76067",
    "sg:province":"TX",
    "sg:tags":[
        "church"
    ],
    "sg:website":"www.northoakchurch.org",
    "wof:name":"Church Of Christ North Oak",
    "wof:placetype":"venue"
},
  "geometry": {"coordinates":[-98.11290200000001,32.816012],"type":"Point"}
}