{
  "type": "Feature",
  "properties": {
    "iso:country":"US",
    "sg:address":"22307 Webb St",
    "sg:city":"Hockley",
    "sg:classifiers":[
        {
            "category":"Building & Trades",
            "subcategory":"Construction",
            "type":"Services"
        }
    ],
    "sg:phone":"+1 281 357 1780",
    "sg:postcode":"77447",
    "sg:province":"TX",
    "sg:tags":[
        "house"
    ],
    "wof:name":"Lonnie Burrow Construction",
    "wof:placetype":"venue"
},
  "geometry": {"coordinates":[-95.76911800000001,30.043756],"type":"Point"}
}