{
  "type": "Feature",
  "properties": {
    "iso:country":"US",
    "sg:address":"1661 S Fitzhugh Ave",
    "sg:city":"Dallas",
    "sg:classifiers":[
        {
            "category":"Retail",
            "subcategory":"Auto Repair",
            "type":"Services"
        }
    ],
    "sg:phone":"+1 214 826 2772",
    "sg:postcode":"75223",
    "sg:province":"TX",
    "sg:tags":[
        "body",
        "shop"
    ],
    "wof:name":"Infiniti Paint & Body",
    "wof:placetype":"venue"
},
  "geometry": {"coordinates":[-96.7491,32.782501],"type":"Point"}
}