{
  "type": "Feature",
  "properties": {
    "iso:country":"US",
    "sg:address":"5221 Wren Ave",
    "sg:city":"El Paso",
    "sg:classifiers":[
        {
            "category":"Autos & Motor Vehicles",
            "subcategory":"Fuel & Gas Station",
            "type":"Retail Goods"
        }
    ],
    "sg:phone":"+1 915 755 2243",
    "sg:postcode":"79924",
    "sg:province":"TX",
    "sg:tags":[
        "oil"
    ],
    "wof:name":"Northgate Service Station",
    "wof:placetype":"venue"
},
  "geometry": {"coordinates":[-106.418458,31.877584],"type":"Point"}
}