{
  "type": "Feature",
  "properties": {
    "iso:country":"US",
    "sg:address":"2100 E Griffin Pkwy",
    "sg:city":"Mission",
    "sg:classifiers":[
        {
            "category":"Restaurant",
            "type":"Food & Drink"
        }
    ],
    "sg:phone":"+1 956 580 2880",
    "sg:postcode":"78572",
    "sg:province":"TX",
    "sg:tags":[
        "eating"
    ],
    "wof:name":"Hotties Grill & Bar",
    "wof:placetype":"venue"
},
  "geometry": {"coordinates":[-98.28748899999999,26.224708],"type":"Point"}
}