{
  "type": "Feature",
  "properties": {
    "iso:country":"US",
    "sg:address":"1717 Joyce St",
    "sg:city":"Arlington",
    "sg:classifiers":[
        {
            "category":"Professional",
            "subcategory":"Research",
            "type":"Services"
        }
    ],
    "sg:phone":"+1 817 861 0219",
    "sg:postcode":"76010",
    "sg:province":"TX",
    "wof:name":"Nan's Archives Research",
    "wof:placetype":"venue"
},
  "geometry": {"coordinates":[-97.085769,32.731327],"type":"Point"}
}