{
  "type": "Feature",
  "properties": {
    "iso:country":"US",
    "sg:address":"8709 Linden Rd",
    "sg:city":"Del Valle",
    "sg:classifiers":[
        {
            "category":"Building & Trades",
            "subcategory":"Construction",
            "type":"Services"
        }
    ],
    "sg:phone":"+1 512 247 7868",
    "sg:postcode":"78617",
    "sg:province":"TX",
    "sg:tags":[
        "concrete",
        "contractor"
    ],
    "wof:name":"Azteca Concrete Co Inc",
    "wof:placetype":"venue"
},
  "geometry": {"coordinates":[-97.59625200000001,30.127597],"type":"Point"}
}