{
  "type": "Feature",
  "properties": {
    "iso:country":"US",
    "sg:address":"6460 Hiller St",
    "sg:city":"El Paso",
    "sg:classifiers":[
        {
            "category":"Education",
            "subcategory":"Vocational School",
            "type":"Public Place"
        }
    ],
    "sg:phone":"+1 915 779 0900",
    "sg:postcode":"79925",
    "sg:province":"TX",
    "wof:name":"IBC",
    "wof:placetype":"venue"
},
  "geometry": {"coordinates":[-106.403639,31.793438],"type":"Point"}
}