{
  "type": "Feature",
  "properties": {
    "iso:country":"US",
    "sg:address":"1123 Goodnight Trl",
    "sg:city":"Houston",
    "sg:classifiers":[
        {
            "category":"Home & Garden",
            "subcategory":"Building Materials",
            "type":"Retail Goods"
        }
    ],
    "sg:phone":"+1 281 443 8436",
    "sg:postcode":"77060",
    "sg:province":"TX",
    "sg:tags":[
        "mixed",
        "concrete"
    ],
    "wof:name":"Hanson Ready Mix",
    "wof:placetype":"venue"
},
  "geometry": {"coordinates":[-95.388398,29.961021],"type":"Point"}
}