{
  "type": "Feature",
  "properties": {
    "iso:country":"US",
    "sg:address":"203 N Gray St",
    "sg:city":"Caldwell",
    "sg:phone":"+1 979 567 6270",
    "sg:postcode":"77836",
    "sg:province":"TX",
    "wof:name":"Caldwell Middle School",
    "wof:placetype":"venue"
},
  "geometry": {"coordinates":[-96.699725,30.528384],"type":"Point"}
}