{
  "type": "Feature",
  "properties": {
    "iso:country":"US",
    "sg:address":"5905 High Meadow St",
    "sg:city":"League City",
    "sg:classifiers":[
        {
            "category":"Manufacturing",
            "subcategory":"Tools & Machinery",
            "type":"Manufacturing & Wholesale Goods"
        }
    ],
    "sg:phone":"+1 281 332 7392",
    "sg:postcode":"77573",
    "sg:province":"TX",
    "sg:tags":[
        "metalworking",
        "mfg"
    ],
    "wof:name":"Nelson Machinery",
    "wof:placetype":"venue"
},
  "geometry": {"coordinates":[-95.153254,29.482952],"type":"Point"}
}