{
  "type": "Feature",
  "properties": {
    "iso:country":"US",
    "sg:address":"2633 Aero Dr",
    "sg:city":"Grand Prairie",
    "sg:classifiers":[
        {
            "category":"Wholesale",
            "subcategory":"Vending Machines",
            "type":"Manufacturing & Wholesale Goods"
        }
    ],
    "sg:phone":"+1 972 988 8363",
    "sg:postcode":"75052",
    "sg:province":"TX",
    "sg:tags":[
        "operator"
    ],
    "wof:name":"Vend America Metro",
    "wof:placetype":"venue"
},
  "geometry": {"coordinates":[-97.055746,32.704354],"type":"Point"}
}