{
  "type": "Feature",
  "properties": {
    "iso:country":"US",
    "sg:address":"1612 Hutton Dr",
    "sg:city":"Carrollton",
    "sg:classifiers":[
        {
            "category":"Manufacturing",
            "subcategory":"Tools & Machinery",
            "type":"Manufacturing & Wholesale Goods"
        }
    ],
    "sg:phone":"+1 972 236 2400",
    "sg:postcode":"75006",
    "sg:province":"TX",
    "sg:tags":[
        "dock",
        "loading",
        "equipment"
    ],
    "sg:website":"www.sercocompany.com",
    "wof:name":"SPX Dock Products",
    "wof:placetype":"venue"
},
  "geometry": {"coordinates":[-96.91660299999999,32.942367],"type":"Point"}
}