{
  "type": "Feature",
  "properties": {
    "iso:country":"US",
    "sg:address":"1416 Wagonwheel Ct",
    "sg:city":"Irving",
    "sg:classifiers":[
        {
            "category":"Health Services",
            "subcategory":"Hospital",
            "type":"Services"
        }
    ],
    "sg:phone":"+1 469 442 8350",
    "sg:postcode":"75061",
    "sg:province":"TX",
    "wof:name":"Parkland Health And Hospital System",
    "wof:placetype":"venue"
},
  "geometry": {"coordinates":[-97.005025,32.828134],"type":"Point"}
}