{
  "type": "Feature",
  "properties": {
    "iso:country":"US",
    "sg:address":"3353 Knickerbocker Rd",
    "sg:city":"San Angelo",
    "sg:classifiers":[
        {
            "category":"Health Services",
            "subcategory":"Chiropractor",
            "type":"Services"
        }
    ],
    "sg:phone":"+1 325 224 4120",
    "sg:postcode":"76904",
    "sg:province":"TX",
    "wof:name":"Power Family Chiropractic P C",
    "wof:placetype":"venue"
},
  "geometry": {"coordinates":[-100.468153,31.421603],"type":"Point"}
}