{
  "type": "Feature",
  "properties": {
    "iso:country":"US",
    "sg:address":"951 W Bitters Rd",
    "sg:city":"San Antonio",
    "sg:classifiers":[
        {
            "category":"Home & Garden",
            "subcategory":"Garden Supply",
            "type":"Retail Goods"
        }
    ],
    "sg:phone":"+1 210 545 7246",
    "sg:postcode":"78216",
    "sg:province":"TX",
    "sg:tags":[
        "sprinkler"
    ],
    "wof:name":"Pro Irrigation & Repair",
    "wof:placetype":"venue"
},
  "geometry": {"coordinates":[-98.506141,29.581389],"type":"Point"}
}