{
  "type": "Feature",
  "properties": {
    "iso:country":"US",
    "sg:address":"408 N 4th St",
    "sg:city":"Killeen",
    "sg:classifiers":[
        {
            "category":"Organizations",
            "subcategory":"Religious Organization",
            "type":"Services"
        }
    ],
    "sg:phone":"+1 254 200 2633",
    "sg:postcode":"76541",
    "sg:province":"TX",
    "sg:tags":[
        "church"
    ],
    "wof:name":"Harvest Ministries Sow",
    "wof:placetype":"venue"
},
  "geometry": {"coordinates":[-97.728424,31.12205],"type":"Point"}
}