{
  "type": "Feature",
  "properties": {
    "iso:country":"US",
    "sg:address":"14506 Smith Rd",
    "sg:city":"Humble",
    "sg:classifiers":[
        {
            "category":"Professional",
            "type":"Services"
        }
    ],
    "sg:phone":"+1 281 441 8149",
    "sg:postcode":"77396",
    "sg:province":"TX",
    "sg:tags":[
        "establishment"
    ],
    "wof:name":"Industrial Tx Corp",
    "wof:placetype":"venue"
},
  "geometry": {"coordinates":[-95.287406,29.925781],"type":"Point"}
}