{
  "type": "Feature",
  "properties": {
    "iso:country":"US",
    "sg:address":"101 East Ave",
    "sg:city":"Wellington",
    "sg:classifiers":[
        {
            "category":"Organizations",
            "subcategory":"Religious Organization",
            "type":"Services"
        }
    ],
    "sg:phone":"+1 806 447 5802",
    "sg:postcode":"79095",
    "sg:province":"TX",
    "sg:tags":[
        "churches-baptist"
    ],
    "wof:name":"Faith Baptist Church Study",
    "wof:placetype":"venue"
},
  "geometry": {"coordinates":[-100.21305099999999,34.86356],"type":"Point"}
}