{
  "type": "Feature",
  "properties": {
    "iso:country":"US",
    "sg:address":"1120 N Pacific St",
    "sg:city":"Mineola",
    "sg:classifiers":[
        {
            "category":"Professional",
            "type":"Services"
        }
    ],
    "sg:phone":"+1 903 592 8400",
    "sg:postcode":"75773",
    "sg:province":"TX",
    "wof:name":"East Texas Bayou Services LLC",
    "wof:placetype":"venue"
},
  "geometry": {"coordinates":[-95.484921,32.674249],"type":"Point"}
}