{
  "type": "Feature",
  "properties": {
    "iso:country":"US",
    "sg:address":"1237 Co Rd 343",
    "sg:city":"Gonzales",
    "sg:classifiers":[
        {
            "category":"Farming",
            "subcategory":"Poultry Farm",
            "type":"Manufacturing & Wholesale Goods"
        }
    ],
    "sg:phone":"+1 830 672 3007",
    "sg:postcode":"78629",
    "sg:province":"TX",
    "sg:tags":[
        "egg",
        "beef",
        "feedlot",
        "cattle"
    ],
    "wof:name":"Bill Glass Farm",
    "wof:placetype":"venue"
},
  "geometry": {"coordinates":[-97.394621,29.481408],"type":"Point"}
}