{
  "type": "Feature",
  "properties": {
    "iso:country":"US",
    "sg:address":"1135 Cresthaven Dr",
    "sg:city":"Lancaster",
    "sg:classifiers":[
        {
            "category":"Building & Trades",
            "subcategory":"Electrical",
            "type":"Services"
        }
    ],
    "sg:phone":"+1 972 218 9447",
    "sg:postcode":"75134",
    "sg:province":"TX",
    "sg:tags":[
        "electrician"
    ],
    "wof:name":"Rickeys Electric",
    "wof:placetype":"venue"
},
  "geometry": {"coordinates":[-96.77853,32.623277],"type":"Point"}
}