{
  "type": "Feature",
  "properties": {
    "iso:country":"US",
    "sg:address":"5421 Cavalcade St",
    "sg:city":"Houston",
    "sg:classifiers":[
        {
            "category":"Travel",
            "subcategory":"Hotels & Motels",
            "type":"Entertainment"
        }
    ],
    "sg:phone":"+1 713 673 1200",
    "sg:postcode":"77026",
    "sg:province":"TX",
    "wof:name":"Travelers Inn",
    "wof:placetype":"venue"
},
  "geometry": {"coordinates":[-95.315719,29.800637],"type":"Point"}
}