{
  "type": "Feature",
  "properties": {
    "iso:country":"US",
    "sg:address":"14623 Sequoia Bend Blvd",
    "sg:city":"Houston",
    "sg:classifiers":[
        {
            "category":"Retail",
            "subcategory":"Laundry & Dry Cleaning",
            "type":"Services"
        }
    ],
    "sg:phone":"+1 281 227 5907",
    "sg:postcode":"77032",
    "sg:province":"TX",
    "wof:name":"Lucky 7 Cleaners",
    "wof:placetype":"venue"
},
  "geometry": {"coordinates":[-95.31489999999999,29.930027],"type":"Point"}
}