{
  "type": "Feature",
  "properties": {
    "iso:country":"US",
    "sg:address":"2008 San Simeon Dr",
    "sg:city":"Mesquite",
    "sg:classifiers":[
        {
            "category":"Professional",
            "type":"Services"
        }
    ],
    "sg:phone":"+1 972 726 0569",
    "sg:postcode":"75181",
    "sg:province":"TX",
    "wof:name":"Your Logo On Tshirt Etc",
    "wof:placetype":"venue"
},
  "geometry": {"coordinates":[-96.572036,32.743643],"type":"Point"}
}