{
  "type": "Feature",
  "properties": {
    "iso:country":"US",
    "sg:address":"9310 Bellaire Blvd",
    "sg:city":"Houston",
    "sg:classifiers":[
        {
            "category":"Restaurant",
            "type":"Food & Drink"
        }
    ],
    "sg:menulink":"http://www.allmenus.com/tx/houston/40769-one-dragon-restaurant/menu/",
    "sg:phone":"+1 713 995 6545",
    "sg:postcode":"77036",
    "sg:province":"TX",
    "sg:tags":[
        "asian",
        "chinese"
    ],
    "wof:name":"One Dragon Restaurant",
    "wof:placetype":"venue"
},
  "geometry": {"coordinates":[-95.546983,29.705014],"type":"Point"}
}