{
  "type": "Feature",
  "properties": {
    "iso:country":"US",
    "sg:address":"751 Canyon Dr",
    "sg:city":"Coppell",
    "sg:classifiers":[
        {
            "category":"Recreation",
            "type":"Entertainment"
        }
    ],
    "sg:phone":"+1 972 304 1656",
    "sg:postcode":"75019",
    "sg:province":"TX",
    "sg:tags":[
        "guide"
    ],
    "wof:name":"Amazon Tours Inc",
    "wof:placetype":"venue"
},
  "geometry": {"coordinates":[-97.01758599999999,32.982093],"type":"Point"}
}