{
  "type": "Feature",
  "properties": {
    "iso:country":"US",
    "sg:address":"516 Brian Dr",
    "sg:city":"Kerrville",
    "sg:classifiers":[
        {
            "category":"Real Estate",
            "subcategory":"Real Estate Operator",
            "type":"Services"
        }
    ],
    "sg:phone":"+1 830 896 3255",
    "sg:postcode":"78028",
    "sg:province":"TX",
    "sg:tags":[
        "apartment"
    ],
    "wof:name":"Northridge Village Duplexes",
    "wof:placetype":"venue"
},
  "geometry": {"coordinates":[-99.11994300000001,30.067133],"type":"Point"}
}