{
  "type": "Feature",
  "properties": {
    "iso:country":"US",
    "sg:address":"1101 Stillwell Ridge",
    "sg:city":"Cedar Park",
    "sg:classifiers":[
        {
            "category":"Building & Trades",
            "subcategory":"Plumbing",
            "type":"Services"
        }
    ],
    "sg:phone":"+1 512 257 2653",
    "sg:postcode":"78613",
    "sg:province":"TX",
    "sg:tags":[
        "conditioning",
        "air",
        "system",
        "contractor"
    ],
    "wof:name":"Air Control Mechanical",
    "wof:placetype":"venue"
},
  "geometry": {"coordinates":[-97.84642599999999,30.485967],"type":"Point"}
}