{
  "type": "Feature",
  "properties": {
    "iso:country":"US",
    "sg:address":"506 N Broad St",
    "sg:city":"Lampasas",
    "sg:classifiers":[
        {
            "category":"Organizations",
            "subcategory":"Religious Organization",
            "type":"Services"
        }
    ],
    "sg:phone":"+1 512 556 5851",
    "sg:postcode":"76550",
    "sg:province":"TX",
    "sg:tags":[
        "church"
    ],
    "wof:name":"Church Of Christ",
    "wof:placetype":"venue"
},
  "geometry": {"coordinates":[-98.18758200000001,31.071002],"type":"Point"}
}