{
  "type": "Feature",
  "properties": {
    "iso:country":"US",
    "sg:address":"6638 Reed Rd",
    "sg:city":"Houston",
    "sg:classifiers":[
        {
            "category":"Building & Trades",
            "subcategory":"Construction",
            "type":"Services"
        }
    ],
    "sg:phone":"+1 713 641 2511",
    "sg:postcode":"77087",
    "sg:province":"TX",
    "sg:tags":[
        "house"
    ],
    "wof:name":"ABB & I",
    "wof:placetype":"venue"
},
  "geometry": {"coordinates":[-95.309657,29.660639],"type":"Point"}
}