{
  "type": "Feature",
  "properties": {
    "iso:country":"US",
    "sg:address":"10517 S Post Oak Rd",
    "sg:city":"Houston",
    "sg:classifiers":[
        {
            "category":"Restaurant",
            "type":"Food & Drink"
        },
        {
            "category":"Donuts",
            "subcategory":"None",
            "type":"Food & Drink"
        }
    ],
    "sg:phone":"+1 713 728 9366",
    "sg:postcode":"77035",
    "sg:province":"TX",
    "sg:tags":[
        "shop"
    ],
    "wof:name":"Shipley DO-Nut Shops",
    "wof:placetype":"venue"
},
  "geometry": {"coordinates":[-95.462898,29.667101],"type":"Point"}
}