{
  "type": "Feature",
  "properties": {
    "iso:country":"US",
    "sg:address":"6321 Commerce St",
    "sg:city":"Wallis",
    "sg:classifiers":[
        {
            "category":"Shopping",
            "subcategory":"Used Merchandise",
            "type":"Retail Goods"
        }
    ],
    "sg:phone":"+1 979 478 6193",
    "sg:postcode":"77485",
    "sg:province":"TX",
    "wof:name":"Country Rose",
    "wof:placetype":"venue"
},
  "geometry": {"coordinates":[-96.060514,29.629331],"type":"Point"}
}