{
  "type": "Feature",
  "properties": {
    "iso:country":"US",
    "sg:address":"3010 Leopard St",
    "sg:city":"Corpus Christi",
    "sg:classifiers":[
        {
            "category":"Retail",
            "subcategory":"Auto Repair",
            "type":"Services"
        }
    ],
    "sg:phone":"+1 361 881 8200",
    "sg:postcode":"78408",
    "sg:province":"TX",
    "sg:tags":[
        "transmission"
    ],
    "wof:name":"AAMCO Transmissions",
    "wof:placetype":"venue"
},
  "geometry": {"coordinates":[-97.424058,27.796775],"type":"Point"}
}