{
  "type": "Feature",
  "properties": {
    "iso:country":"US",
    "sg:address":"101 W Hillside Rd",
    "sg:city":"Laredo",
    "sg:classifiers":[
        {
            "category":"Personal",
            "subcategory":"Beauty Salon",
            "type":"Services"
        }
    ],
    "sg:phone":"+1 956 728 1560",
    "sg:postcode":"78041",
    "sg:province":"TX",
    "sg:tags":[
        "shop"
    ],
    "wof:name":"Grisell's Beauty Salon & Spa",
    "wof:placetype":"venue"
},
  "geometry": {"coordinates":[-99.496443,27.546867],"type":"Point"}
}