{
  "type": "Feature",
  "properties": {
    "iso:country":"US",
    "sg:address":"747 Shepherd Dr",
    "sg:city":"Houston",
    "sg:classifiers":[
        {
            "category":"Airline",
            "type":"Transportation"
        }
    ],
    "sg:phone":"+1 713 869 7575",
    "sg:postcode":"77007",
    "sg:province":"TX",
    "sg:tags":[
        "courier",
        "air"
    ],
    "sg:website":"www.hotshot.to",
    "wof:name":"Airport Delivery Svc",
    "wof:placetype":"venue"
},
  "geometry": {"coordinates":[-95.40951099999999,29.768638],"type":"Point"}
}