{
  "type": "Feature",
  "properties": {
    "iso:country":"US",
    "sg:address":"1901 E State Highway 356",
    "sg:city":"Irving",
    "sg:classifiers":[
        {
            "category":"Insurance",
            "subcategory":"Hazard Insurance",
            "type":"Services"
        }
    ],
    "sg:phone":"+1 972 554 8800",
    "sg:postcode":"75060",
    "sg:province":"TX",
    "wof:name":"A-Affordable Insurance Agency",
    "wof:placetype":"venue"
},
  "geometry": {"coordinates":[-96.921097,32.809601],"type":"Point"}
}