{
  "type": "Feature",
  "properties": {
    "iso:country":"US",
    "sg:address":"805 Acacia Ave",
    "sg:city":"Alamo",
    "sg:classifiers":[
        {
            "category":"Organizations",
            "subcategory":"Community Association",
            "type":"Services"
        }
    ],
    "sg:phone":"+1 956 787 9253",
    "sg:postcode":"78516",
    "sg:province":"TX",
    "sg:tags":[
        "club"
    ],
    "wof:name":"El Tenampa Club",
    "wof:placetype":"venue"
},
  "geometry": {"coordinates":[-98.11895699999999,26.184739],"type":"Point"}
}