{
  "type": "Feature",
  "properties": {
    "iso:country":"US",
    "sg:address":"341 Buena Vista Rd",
    "sg:city":"Royse City",
    "sg:classifiers":[
        {
            "category":"Building & Trades",
            "subcategory":"Electrical",
            "type":"Services"
        }
    ],
    "sg:phone":"+1 956 233 1540",
    "sg:postcode":"75189",
    "sg:province":"TX",
    "sg:tags":[
        "electric",
        "contractor"
    ],
    "wof:name":"Reliable Electric INSURANCE",
    "wof:placetype":"venue"
},
  "geometry": {"coordinates":[-96.304615,32.863532],"type":"Point"}
}