{
  "type": "Feature",
  "properties": {
    "iso:country":"US",
    "sg:address":"4610 S Coulter St",
    "sg:city":"Amarillo",
    "sg:classifiers":[
        {
            "category":"Shopping",
            "subcategory":"Department Store",
            "type":"Retail Goods"
        }
    ],
    "sg:phone":"+1 806 354 9300",
    "sg:postcode":"79119",
    "sg:province":"TX",
    "sg:tags":[
        "grocery"
    ],
    "wof:name":"Wal-Mart",
    "wof:placetype":"venue"
},
  "geometry": {"coordinates":[-101.920078,35.153546],"type":"Point"}
}