{
  "type": "Feature",
  "properties": {
    "iso:country":"US",
    "sg:address":"1005 Main St",
    "sg:city":"Bastrop",
    "sg:classifiers":[
        {
            "category":"Health Services",
            "subcategory":"Clinic",
            "type":"Services"
        }
    ],
    "sg:phone":"+1 512 303 7567",
    "sg:postcode":"78602",
    "sg:province":"TX",
    "sg:tags":[
        "home"
    ],
    "wof:name":"Blue Bonnett CBA Div",
    "wof:placetype":"venue"
},
  "geometry": {"coordinates":[-97.319957,30.11159],"type":"Point"}
}