{
  "type": "Feature",
  "properties": {
    "iso:country":"US",
    "sg:address":"9629 Hillcroft St",
    "sg:city":"Houston",
    "sg:classifiers":[
        {
            "category":"Food & Beverages",
            "subcategory":"Ethnic Foods",
            "type":"Retail Goods"
        }
    ],
    "sg:phone":"+1 713 665 1177",
    "sg:postcode":"77096",
    "sg:province":"TX",
    "wof:name":"Russian General Store",
    "wof:placetype":"venue"
},
  "geometry": {"coordinates":[-95.493301,29.6747],"type":"Point"}
}