{
  "type": "Feature",
  "properties": {
    "iso:country":"US",
    "sg:address":"2050 Crooked Lane Blvd",
    "sg:city":"Southlake",
    "sg:classifiers":[
        {
            "category":"Home & Garden",
            "subcategory":"Building Materials",
            "type":"Retail Goods"
        }
    ],
    "sg:phone":"+1 817 488 8151",
    "sg:postcode":"76092",
    "sg:province":"TX",
    "sg:tags":[
        "installs",
        "overhead",
        "door"
    ],
    "wof:name":"Beech's Overhead Door Inc",
    "wof:placetype":"venue"
},
  "geometry": {"coordinates":[-97.11515300000001,32.932102],"type":"Point"}
}