{
  "type": "Feature",
  "properties": {
    "iso:country":"US",
    "sg:address":"1924 S 33rd St",
    "sg:city":"Mcallen",
    "sg:classifiers":[
        {
            "category":"Building & Trades",
            "subcategory":"Construction",
            "type":"Services"
        }
    ],
    "sg:phone":"+1 956 533 3227",
    "sg:postcode":"78503",
    "sg:province":"TX",
    "sg:tags":[
        "home",
        "family"
    ],
    "wof:name":"Tremor Construction Inc",
    "wof:placetype":"venue"
},
  "geometry": {"coordinates":[-98.26034,26.191063],"type":"Point"}
}