{
  "type": "Feature",
  "properties": {
    "iso:country":"US",
    "sg:address":"243 Boca Chica Blvd",
    "sg:city":"Brownsville",
    "sg:classifiers":[
        {
            "category":"Restaurant",
            "type":"Food & Drink"
        }
    ],
    "sg:phone":"+1 956 546 8918",
    "sg:postcode":"78520",
    "sg:province":"TX",
    "sg:tags":[
        "eating"
    ],
    "wof:name":"Jerrys Grill",
    "wof:placetype":"venue"
},
  "geometry": {"coordinates":[-97.518102,25.926589],"type":"Point"}
}