{
  "type": "Feature",
  "properties": {
    "iso:country":"US",
    "sg:address":"705 W Indiana Ave",
    "sg:city":"Midland",
    "sg:classifiers":[
        {
            "category":"Real Estate",
            "subcategory":"Real Estate Agent",
            "type":"Services"
        }
    ],
    "sg:phone":"+1 432 683 1381",
    "sg:postcode":"79701",
    "sg:province":"TX",
    "wof:name":"Tyson Properties",
    "wof:placetype":"venue"
},
  "geometry": {"coordinates":[-102.08108900000001,31.995212],"type":"Point"}
}