{
  "type": "Feature",
  "properties": {
    "iso:country":"US",
    "sg:address":"6530 Broken Stone St",
    "sg:city":"Houston",
    "sg:classifiers":[
        {
            "category":"Professional",
            "type":"Services"
        }
    ],
    "sg:phone":"+1 281 859 2402",
    "sg:postcode":"77084",
    "sg:province":"TX",
    "wof:name":"Now Specialties Inc",
    "wof:placetype":"venue"
},
  "geometry": {"coordinates":[-95.66727,29.871339],"type":"Point"}
}