{
  "type": "Feature",
  "properties": {
    "iso:country":"US",
    "sg:address":"1010 W Rundberg Ln",
    "sg:city":"Austin",
    "sg:classifiers":[
        {
            "category":"Professional",
            "subcategory":"Business Services",
            "type":"Services"
        }
    ],
    "sg:phone":"+1 512 832 1826",
    "sg:postcode":"78758",
    "sg:province":"TX",
    "wof:name":"Auctions Plus",
    "wof:placetype":"venue"
},
  "geometry": {"coordinates":[-97.70161400000001,30.365412],"type":"Point"}
}