{
  "type": "Feature",
  "properties": {
    "iso:country":"US",
    "sg:address":"3300 E Walnut St",
    "sg:city":"Pearland",
    "sg:classifiers":[
        {
            "category":"Health Services",
            "subcategory":"Doctor",
            "type":"Services"
        }
    ],
    "sg:phone":"+1 281 485 7005",
    "sg:postcode":"77581",
    "sg:province":"TX",
    "sg:tags":[
        "dentist"
    ],
    "wof:name":"Pearland Dental Clinic",
    "wof:placetype":"venue"
},
  "geometry": {"coordinates":[-95.27396400000001,29.56017],"type":"Point"}
}