{
  "type": "Feature",
  "properties": {
    "iso:country":"US",
    "sg:address":"1501 E Elms Rd",
    "sg:city":"Killeen",
    "sg:classifiers":[
        {
            "category":"Shopping",
            "subcategory":"Department Store",
            "type":"Retail Goods"
        }
    ],
    "sg:phone":"+1 254 554 8321",
    "sg:postcode":"76542",
    "sg:province":"TX",
    "wof:name":"Dollar General",
    "wof:placetype":"venue"
},
  "geometry": {"coordinates":[-97.734995,31.080338],"type":"Point"}
}