{
  "type": "Feature",
  "properties": {
    "iso:country":"US",
    "sg:address":"20823 N Highway 36",
    "sg:city":"Brazoria",
    "sg:classifiers":[
        {
            "category":"Professional",
            "subcategory":"Detective & Security Services",
            "type":"Services"
        }
    ],
    "sg:phone":"+1 979 798 0412",
    "sg:postcode":"77422",
    "sg:province":"TX",
    "sg:tags":[
        "information",
        "bureau"
    ],
    "wof:name":"Kmac Specialty Services Inc",
    "wof:placetype":"venue"
},
  "geometry": {"coordinates":[-95.603086,29.07649],"type":"Point"}
}