{
  "type": "Feature",
  "properties": {
    "iso:country":"US",
    "sg:address":"1512 N Gladiator Blvd",
    "sg:city":"Roma",
    "sg:classifiers":[
        {
            "category":"Building & Trades",
            "subcategory":"Cleaning & Sanitation",
            "type":"Services"
        }
    ],
    "sg:phone":"+1 956 849 3064",
    "sg:postcode":"78584",
    "sg:province":"TX",
    "sg:tags":[
        "janitorial"
    ],
    "wof:name":"Gonzalez Liliana",
    "wof:placetype":"venue"
},
  "geometry": {"coordinates":[-99.01442400000001,26.415235],"type":"Point"}
}