{
  "type": "Feature",
  "properties": {
    "iso:country":"US",
    "sg:address":"717 Jewell Dr",
    "sg:city":"Waco",
    "sg:classifiers":[
        {
            "category":"Professional",
            "subcategory":"Advertising",
            "type":"Services"
        }
    ],
    "sg:phone":"+1 254 776 4600",
    "sg:postcode":"76712",
    "sg:province":"TX",
    "sg:website":"www.dynamicdesignsinc.com",
    "wof:name":"Dynamic Designs Inc",
    "wof:placetype":"venue"
},
  "geometry": {"coordinates":[-97.1952,31.501842],"type":"Point"}
}