{
  "type": "Feature",
  "properties": {
    "iso:country":"US",
    "sg:address":"9297 Wahrenberger Rd",
    "sg:city":"Conroe",
    "sg:classifiers":[
        {
            "category":"Building & Trades",
            "subcategory":"Construction",
            "type":"Services"
        }
    ],
    "sg:phone":"+1 936 441 7774",
    "sg:postcode":"77304",
    "sg:province":"TX",
    "sg:tags":[
        "contractor"
    ],
    "wof:name":"Beck Ford Construction Inc",
    "wof:placetype":"venue"
},
  "geometry": {"coordinates":[-95.53441100000001,30.31525],"type":"Point"}
}