{
  "type": "Feature",
  "properties": {
    "iso:country":"US",
    "sg:address":"3998 State Hwy 6 S",
    "sg:city":"College Station",
    "sg:classifiers":[
        {
            "category":"Autos & Motor Vehicles",
            "subcategory":"Fuel & Gas Station",
            "type":"Retail Goods"
        }
    ],
    "sg:phone":"+1 979 696 1124",
    "sg:postcode":"77845",
    "sg:province":"TX",
    "sg:tags":[
        "oil"
    ],
    "wof:name":"Exxon",
    "wof:placetype":"venue"
},
  "geometry": {"coordinates":[-96.28635199999999,30.585241],"type":"Point"}
}