{
  "type": "Feature",
  "properties": {
    "iso:country":"US",
    "sg:address":"330 Kayton Ave",
    "sg:city":"San Antonio",
    "sg:classifiers":[
        {
            "category":"Communications",
            "type":"Services"
        }
    ],
    "sg:phone":"+1 210 599 7354",
    "sg:postcode":"78210",
    "sg:province":"TX",
    "sg:tags":[
        "communication"
    ],
    "wof:name":"Mayatel Communications",
    "wof:placetype":"venue"
},
  "geometry": {"coordinates":[-98.46828600000001,29.397339],"type":"Point"}
}