{
  "type": "Feature",
  "properties": {
    "iso:country":"US",
    "sg:address":"522 Long Shadows Cir",
    "sg:city":"Spring",
    "sg:classifiers":[
        {
            "category":"Wholesale",
            "subcategory":"Auto Parts",
            "type":"Manufacturing & Wholesale Goods"
        }
    ],
    "sg:phone":"+1 281 350 0023",
    "sg:postcode":"77388",
    "sg:province":"TX",
    "wof:name":"Has Distributing",
    "wof:placetype":"venue"
},
  "geometry": {"coordinates":[-95.445651,30.049088],"type":"Point"}
}