{
  "type": "Feature",
  "properties": {
    "iso:country":"US",
    "sg:address":"5405 T C Jester Blvd",
    "sg:city":"Houston",
    "sg:classifiers":[
        {
            "category":"Food & Beverages",
            "subcategory":"Liquor & Beverages",
            "type":"Retail Goods"
        }
    ],
    "sg:phone":"+1 713 688 3411",
    "sg:postcode":"77091",
    "sg:province":"TX",
    "sg:tags":[
        "beer",
        "spirit",
        "wine"
    ],
    "wof:name":"H&H Liquor Store",
    "wof:placetype":"venue"
},
  "geometry": {"coordinates":[-95.458415,29.84347],"type":"Point"}
}