{
  "type": "Feature",
  "properties": {
    "iso:country":"US",
    "sg:address":"940 Kessler Pkwy",
    "sg:city":"Dallas",
    "sg:classifiers":[
        {
            "category":"Farming",
            "subcategory":"Nursery",
            "type":"Manufacturing & Wholesale Goods"
        }
    ],
    "sg:phone":"+1 214 942 9422",
    "sg:postcode":"75208",
    "sg:province":"TX",
    "sg:tags":[
        "ornamental"
    ],
    "wof:name":"Kessler Park Nursery",
    "wof:placetype":"venue"
},
  "geometry": {"coordinates":[-96.829571,32.763126],"type":"Point"}
}