{
  "type": "Feature",
  "properties": {
    "iso:country":"US",
    "sg:address":"6800 Mc Neil Dr",
    "sg:city":"Austin",
    "sg:classifiers":[
        {
            "category":"Real Estate",
            "subcategory":"Real Estate Agent",
            "type":"Services"
        }
    ],
    "sg:phone":"+1 512 257 4000",
    "sg:postcode":"78729",
    "sg:province":"TX",
    "sg:tags":[
        "property"
    ],
    "wof:name":"Stone Creek Apartments",
    "wof:placetype":"venue"
},
  "geometry": {"coordinates":[-97.755781,30.438955],"type":"Point"}
}