{
  "type": "Feature",
  "properties": {
    "iso:country":"US",
    "sg:address":"3520 Gator Ct",
    "sg:city":"Brownsville",
    "sg:classifiers":[
        {
            "category":"Retail",
            "subcategory":"Repair Shop",
            "type":"Services"
        }
    ],
    "sg:phone":"+1 956 831 3612",
    "sg:postcode":"78521",
    "sg:province":"TX",
    "sg:tags":[
        "boat"
    ],
    "wof:name":"Clpa Boat Maintence",
    "wof:placetype":"venue"
},
  "geometry": {"coordinates":[-97.336628,25.975717],"type":"Point"}
}