{
  "type": "Feature",
  "properties": {
    "iso:country":"US",
    "sg:address":"511 Lake Rd",
    "sg:city":"Belton",
    "sg:classifiers":[
        {
            "category":"Personal",
            "type":"Services"
        }
    ],
    "sg:phone":"+1 254 939 6399",
    "sg:postcode":"76513",
    "sg:province":"TX",
    "sg:tags":[
        "control",
        "weight"
    ],
    "wof:name":"Nutritional Weight Loss Ctr",
    "wof:placetype":"venue"
},
  "geometry": {"coordinates":[-97.46078199999999,31.084822],"type":"Point"}
}