{
  "type": "Feature",
  "properties": {
    "iso:country":"US",
    "sg:address":"1825 Co Rd 511",
    "sg:city":"Brownsville",
    "sg:classifiers":[
        {
            "category":"Utilities",
            "subcategory":"Electric",
            "type":"Services"
        }
    ],
    "sg:phone":"+1 956 831 2427",
    "sg:postcode":"78521",
    "sg:province":"TX",
    "sg:tags":[
        "company"
    ],
    "wof:name":"Magic Valley Electric Co-Op",
    "wof:placetype":"venue"
},
  "geometry": {"coordinates":[-97.40725500000001,25.935785],"type":"Point"}
}