{
  "type": "Feature",
  "properties": {
    "iso:country":"US",
    "sg:address":"1313 Quail Cir",
    "sg:city":"Killeen",
    "sg:classifiers":[
        {
            "category":"Arts & Performance",
            "subcategory":"Theater",
            "type":"Entertainment"
        },
        {
            "category":"Professional",
            "type":"Services"
        }
    ],
    "sg:phone":"+1 254 680 3335",
    "sg:postcode":"76549",
    "sg:province":"TX",
    "sg:tags":[
        "bureau"
    ],
    "wof:name":"Jenny Entertainment",
    "wof:placetype":"venue"
},
  "geometry": {"coordinates":[-97.76515999999999,31.10664],"type":"Point"}
}