{
  "type": "Feature",
  "properties": {
    "iso:country":"US",
    "sg:address":"915 Dragon St",
    "sg:city":"Dallas",
    "sg:classifiers":[
        {
            "category":"Shopping",
            "type":"Retail Goods"
        }
    ],
    "sg:phone":"+1 214 747 8018",
    "sg:postcode":"75207",
    "sg:province":"TX",
    "sg:tags":[
        "equipment",
        "telephone",
        "supply"
    ],
    "wof:name":"Eagle Network Svc Inc",
    "wof:placetype":"venue"
},
  "geometry": {"coordinates":[-96.81620100000001,32.786455],"type":"Point"}
}