{
  "type": "Feature",
  "properties": {
    "iso:country":"US",
    "sg:address":"301 Wentz St",
    "sg:city":"San Benito",
    "sg:classifiers":[
        {
            "category":"Social Services",
            "subcategory":"Child Care",
            "type":"Services"
        }
    ],
    "sg:phone":"+1 956 361 7148",
    "sg:postcode":"78586",
    "sg:province":"TX",
    "sg:tags":[
        "kindergarten",
        "academic",
        "school"
    ],
    "wof:name":"Lagallina Head Start",
    "wof:placetype":"venue"
},
  "geometry": {"coordinates":[-97.64226499999999,26.125183],"type":"Point"}
}