{
  "type": "Feature",
  "properties": {
    "iso:country":"US",
    "sg:address":"5335 Indigo St",
    "sg:city":"Houston",
    "sg:classifiers":[
        {
            "category":"Professional",
            "type":"Services"
        }
    ],
    "sg:phone":"+1 713 665 5746",
    "sg:postcode":"77096",
    "sg:province":"TX",
    "wof:name":"Indigo Bight Co",
    "wof:placetype":"venue"
},
  "geometry": {"coordinates":[-95.478651,29.686549],"type":"Point"}
}