{
  "type": "Feature",
  "properties": {
    "iso:country":"US",
    "sg:address":"9605 Carnegie Ave",
    "sg:city":"El Paso",
    "sg:classifiers":[
        {
            "category":"Organizations",
            "subcategory":"Labor Organization",
            "type":"Services"
        }
    ],
    "sg:phone":"+1 915 591 9427",
    "sg:postcode":"79925",
    "sg:province":"TX",
    "wof:name":"Movers Service Agency Inc",
    "wof:placetype":"venue"
},
  "geometry": {"coordinates":[-106.357046,31.796319],"type":"Point"}
}