{
  "type": "Feature",
  "properties": {
    "iso:country":"US",
    "sg:address":"5615 Preston Fairways Dr",
    "sg:city":"Dallas",
    "sg:classifiers":[
        {
            "category":"Shopping",
            "type":"Retail Goods"
        }
    ],
    "sg:phone":"+1 972 407 0332",
    "sg:postcode":"75252",
    "sg:province":"TX",
    "sg:tags":[
        "printing",
        "commercial",
        "merchandise"
    ],
    "wof:name":"Party Art Inc",
    "wof:placetype":"venue"
},
  "geometry": {"coordinates":[-96.80855,32.989855],"type":"Point"}
}