{
  "type": "Feature",
  "properties": {
    "iso:country":"US",
    "sg:address":"7685 Canyon Dr",
    "sg:city":"Amarillo",
    "sg:classifiers":[
        {
            "category":"Building & Trades",
            "subcategory":"Construction",
            "type":"Services"
        }
    ],
    "sg:phone":"+1 806 356 9677",
    "sg:postcode":"79110",
    "sg:province":"TX",
    "sg:tags":[
        "contractor"
    ],
    "wof:name":"Response Roofing Inc",
    "wof:placetype":"venue"
},
  "geometry": {"coordinates":[-101.900458,35.129967],"type":"Point"}
}