{
  "type": "Feature",
  "properties": {
    "iso:country":"US",
    "sg:address":"901 Tennessee Ave",
    "sg:city":"Dalhart",
    "sg:classifiers":[
        {
            "category":"Real Estate",
            "subcategory":"Real Estate Operator",
            "type":"Services"
        }
    ],
    "sg:phone":"+1 806 249 0103",
    "sg:postcode":"79022",
    "sg:province":"TX",
    "sg:tags":[
        "apartment"
    ],
    "wof:name":"Thunderbird Apts",
    "wof:placetype":"venue"
},
  "geometry": {"coordinates":[-102.51358,36.057369],"type":"Point"}
}