{
  "type": "Feature",
  "properties": {
    "iso:country":"US",
    "sg:address":"17697 Abd Rd",
    "sg:city":"Harlingen",
    "sg:classifiers":[
        {
            "category":"Building & Trades",
            "subcategory":"Construction",
            "type":"Services"
        }
    ],
    "sg:phone":"+1 956 423 5250",
    "sg:postcode":"78552",
    "sg:province":"TX",
    "sg:tags":[
        "concrete",
        "product",
        "asphalt",
        "contractor"
    ],
    "wof:name":"Rio Grande Construction Inc",
    "wof:placetype":"venue"
},
  "geometry": {"coordinates":[-97.734227,26.134397],"type":"Point"}
}