{
  "type": "Feature",
  "properties": {
    "iso:country":"US",
    "sg:address":"13801 Diplomat Dr",
    "sg:city":"Dallas",
    "sg:classifiers":[
        {
            "category":"Professional",
            "subcategory":"Business Services",
            "type":"Services"
        }
    ],
    "sg:phone":"+1 214 459 9977",
    "sg:postcode":"75234",
    "sg:province":"TX",
    "sg:tags":[
        "wireless",
        "repair",
        "system"
    ],
    "wof:name":"RMS Logistics LP",
    "wof:placetype":"venue"
},
  "geometry": {"coordinates":[-96.90672499999999,32.936512],"type":"Point"}
}