{
  "type": "Feature",
  "properties": {
    "iso:country":"US",
    "sg:address":"306 Cottonwood St",
    "sg:city":"Brenham",
    "sg:classifiers":[
        {
            "category":"Organizations",
            "subcategory":"Religious Organization",
            "type":"Services"
        }
    ],
    "sg:phone":"+1 979 836 6140",
    "sg:postcode":"77833",
    "sg:province":"TX",
    "sg:tags":[
        "church"
    ],
    "wof:name":"First Christian Church",
    "wof:placetype":"venue"
},
  "geometry": {"coordinates":[-96.39584600000001,30.170089],"type":"Point"}
}