{
  "type": "Feature",
  "properties": {
    "iso:country":"US",
    "sg:address":"6060 Victory Dr",
    "sg:city":"Houston",
    "sg:classifiers":[
        {
            "category":"Insurance",
            "subcategory":"Insurance Agent",
            "type":"Services"
        }
    ],
    "sg:phone":"+1 281 448 5255",
    "sg:postcode":"77088",
    "sg:province":"TX",
    "wof:name":"Harvey J Stavinoha Jr Insuranc",
    "wof:placetype":"venue"
},
  "geometry": {"coordinates":[-95.479443,29.865677],"type":"Point"}
}