{
  "type": "Feature",
  "properties": {
    "iso:country":"US",
    "sg:address":"6615 Cypress Point Dr",
    "sg:city":"Houston",
    "sg:classifiers":[
        {
            "category":"Professional",
            "subcategory":"Engineering",
            "type":"Services"
        }
    ],
    "sg:phone":"+1 832 249 9758",
    "sg:postcode":"77069",
    "sg:province":"TX",
    "wof:name":"Bioform Engineering Inc",
    "wof:placetype":"venue"
},
  "geometry": {"coordinates":[-95.532068,29.977512],"type":"Point"}
}