{
  "type": "Feature",
  "properties": {
    "iso:country":"US",
    "sg:address":"2301 Forest Ln",
    "sg:city":"Garland",
    "sg:classifiers":[
        {
            "category":"Health Services",
            "subcategory":"Health Practitioner",
            "type":"Services"
        }
    ],
    "sg:phone":"+1 972 272 0688",
    "sg:postcode":"75042",
    "sg:province":"TX",
    "sg:tags":[
        "therapy",
        "physical"
    ],
    "wof:name":"Advanced Orthopedic Services",
    "wof:placetype":"venue"
},
  "geometry": {"coordinates":[-96.659679,32.909177],"type":"Point"}
}