{
  "type": "Feature",
  "properties": {
    "iso:country":"US",
    "sg:address":"306 Grand Central Blvd",
    "sg:city":"Laredo",
    "sg:classifiers":[
        {
            "category":"Shopping",
            "subcategory":"Computers & Home Electronics",
            "type":"Retail Goods"
        }
    ],
    "sg:phone":"+1 956 728 7462",
    "sg:postcode":"78045",
    "sg:province":"TX",
    "wof:name":"Sima Computers",
    "wof:placetype":"venue"
},
  "geometry": {"coordinates":[-99.489266,27.60752],"type":"Point"}
}