{
  "type": "Feature",
  "properties": {
    "iso:country":"US",
    "sg:address":"2570 Eldorado Pkwy",
    "sg:city":"Mc Kinney",
    "sg:classifiers":[
        {
            "category":"Real Estate",
            "subcategory":"Real Estate Agent",
            "type":"Services"
        }
    ],
    "sg:phone":"+1 972 529 2910",
    "sg:postcode":"75070",
    "sg:province":"TX",
    "wof:name":"Keller Williams Realty",
    "wof:placetype":"venue"
},
  "geometry": {"coordinates":[-96.646246,33.171202],"type":"Point"}
}