{
  "type": "Feature",
  "properties": {
    "iso:country":"US",
    "sg:address":"2601 N Mesa St",
    "sg:city":"El Paso",
    "sg:classifiers":[
        {
            "category":"Professional",
            "subcategory":"Printing & Photocopies",
            "type":"Services"
        }
    ],
    "sg:phone":"+1 915 541 7072",
    "sg:postcode":"79902",
    "sg:province":"TX",
    "wof:name":"D & H Copy Services Inc",
    "wof:placetype":"venue"
},
  "geometry": {"coordinates":[-106.50313300000001,31.776957],"type":"Point"}
}