{
  "type": "Feature",
  "properties": {
    "iso:country":"US",
    "sg:address":"8802 Royalwood Dr",
    "sg:city":"Austin",
    "sg:classifiers":[
        {
            "category":"Retail",
            "subcategory":"Portrait Studio",
            "type":"Services"
        }
    ],
    "sg:phone":"+1 512 335 4277",
    "sg:postcode":"78750",
    "sg:province":"TX",
    "sg:tags":[
        "photo"
    ],
    "wof:name":"Donna Moore Photography",
    "wof:placetype":"venue"
},
  "geometry": {"coordinates":[-97.786581,30.433308],"type":"Point"}
}