{
  "type": "Feature",
  "properties": {
    "iso:country":"US",
    "sg:address":"10925 Preston Trail Dr",
    "sg:city":"Austin",
    "sg:classifiers":[
        {
            "category":"Insurance",
            "subcategory":"Insurance Agent",
            "type":"Services"
        }
    ],
    "sg:phone":"+1 512 280 1611",
    "sg:postcode":"78747",
    "sg:province":"TX",
    "wof:name":"James R Tague & Assoc",
    "wof:placetype":"venue"
},
  "geometry": {"coordinates":[-97.78957699999999,30.137174],"type":"Point"}
}