{
  "type": "Feature",
  "properties": {
    "iso:country":"US",
    "sg:address":"3811 Rutledge St",
    "sg:city":"Fort Worth",
    "sg:classifiers":[
        {
            "category":"Real Estate",
            "subcategory":"Real Estate Agent",
            "type":"Services"
        }
    ],
    "sg:phone":"+1 817 735 1191",
    "sg:postcode":"76107",
    "sg:province":"TX",
    "wof:name":"Witherspoon Services Co",
    "wof:placetype":"venue"
},
  "geometry": {"coordinates":[-97.372773,32.729389],"type":"Point"}
}