{
  "type": "Feature",
  "properties": {
    "iso:country":"US",
    "sg:address":"2801 N A St",
    "sg:city":"Midland",
    "sg:classifiers":[
        {
            "category":"Health Services",
            "subcategory":"Nursing And Care Facility",
            "type":"Services"
        }
    ],
    "sg:phone":"+1 432 682 6253",
    "sg:postcode":"79705",
    "sg:province":"TX",
    "sg:tags":[
        "intermediate"
    ],
    "wof:name":"Midland Assn For Rtrded Ctzens",
    "wof:placetype":"venue"
},
  "geometry": {"coordinates":[-102.09115,32.025211],"type":"Point"}
}