{
  "type": "Feature",
  "properties": {
    "iso:country":"US",
    "sg:address":"4730 S Padre Island Dr",
    "sg:city":"Corpus Christi",
    "sg:classifiers":[
        {
            "category":"Shopping",
            "subcategory":"Bicycles & Sporting Goods",
            "type":"Retail Goods"
        }
    ],
    "sg:phone":"+1 361 814 4378",
    "sg:postcode":"78411",
    "sg:province":"TX",
    "sg:tags":[
        "equipment",
        "exercise"
    ],
    "sg:website":"www.hestfitness.com",
    "wof:name":"HEST Fitness Products",
    "wof:placetype":"venue"
},
  "geometry": {"coordinates":[-97.38446,27.71523],"type":"Point"}
}