{
  "type": "Feature",
  "properties": {
    "iso:country":"US",
    "sg:address":"22522 Old Church Ln",
    "sg:city":"Katy",
    "sg:phone":"+1 281 347 6294",
    "sg:postcode":"77449",
    "sg:province":"TX",
    "sg:tags":[
        "equipment",
        "station"
    ],
    "wof:name":"B K Gas Pump Svc",
    "wof:placetype":"venue"
},
  "geometry": {"coordinates":[-95.763768,29.815604],"type":"Point"}
}