{
  "type": "Feature",
  "properties": {
    "iso:country":"US",
    "sg:address":"1105 Champions Dr",
    "sg:city":"Lufkin",
    "sg:classifiers":[
        {
            "category":"Real Estate",
            "subcategory":"Real Estate Agent",
            "type":"Services"
        }
    ],
    "sg:phone":"+1 936 637 1221",
    "sg:postcode":"75901",
    "sg:province":"TX",
    "sg:tags":[
        "agency",
        "rental"
    ],
    "wof:name":"Lucky Rentals",
    "wof:placetype":"venue"
},
  "geometry": {"coordinates":[-94.720189,31.280434],"type":"Point"}
}