{
  "type": "Feature",
  "properties": {
    "iso:country":"US",
    "sg:address":"2308 N Ben Wilson St",
    "sg:city":"Victoria",
    "sg:classifiers":[
        {
            "category":"Building & Trades",
            "subcategory":"Construction",
            "type":"Services"
        }
    ],
    "sg:phone":"+1 361 570 8156",
    "sg:postcode":"77901",
    "sg:province":"TX",
    "sg:tags":[
        "contractor"
    ],
    "wof:name":"Leita Fence Co",
    "wof:placetype":"venue"
},
  "geometry": {"coordinates":[-96.974277,28.811957],"type":"Point"}
}