{
  "type": "Feature",
  "properties": {
    "iso:country":"US",
    "sg:address":"5331 Beverlyhill St",
    "sg:city":"Houston",
    "sg:classifiers":[
        {
            "category":"Professional",
            "subcategory":"Business Services",
            "type":"Services"
        }
    ],
    "sg:phone":"+1 713 961 4136",
    "sg:postcode":"77056",
    "sg:province":"TX",
    "wof:name":"Pcs Solution",
    "wof:placetype":"venue"
},
  "geometry": {"coordinates":[-95.470252,29.730062],"type":"Point"}
}