{
  "type": "Feature",
  "properties": {
    "iso:country":"US",
    "sg:address":"8339 C E King Pkwy",
    "sg:city":"Houston",
    "sg:classifiers":[
        {
            "category":"Manufacturing",
            "subcategory":"Metals",
            "type":"Manufacturing & Wholesale Goods"
        },
        {
            "category":"Wholesale",
            "subcategory":"Electrical",
            "type":"Manufacturing & Wholesale Goods"
        }
    ],
    "sg:phone":"+1 281 459 1667",
    "sg:postcode":"77044",
    "sg:province":"TX",
    "sg:tags":[
        "burglar",
        "mfg",
        "resistant",
        "equipment",
        "architectural",
        "metalwork"
    ],
    "wof:name":"Beautiful Burglar Alarms",
    "wof:placetype":"venue"
},
  "geometry": {"coordinates":[-95.214136,29.845164],"type":"Point"}
}