{
  "type": "Feature",
  "properties": {
    "iso:country":"US",
    "sg:address":"612 S Highway 385",
    "sg:city":"Dimmitt",
    "sg:classifiers":[
        {
            "category":"Restaurant",
            "type":"Food & Drink"
        }
    ],
    "sg:phone":"+1 806 647 2406",
    "sg:postcode":"79027",
    "sg:province":"TX",
    "sg:tags":[
        "asian",
        "chinese",
        "pan"
    ],
    "wof:name":"Somboune's Thai Chinese",
    "wof:placetype":"venue"
},
  "geometry": {"coordinates":[-102.309442,34.544579],"type":"Point"}
}