{
  "type": "Feature",
  "properties": {
    "iso:country":"US",
    "sg:address":"7622 Jackwood St",
    "sg:city":"Houston",
    "sg:classifiers":[
        {
            "category":"Restaurant",
            "type":"Food & Drink"
        }
    ],
    "sg:phone":"+1 713 774 0441",
    "sg:postcode":"77074",
    "sg:province":"TX",
    "sg:tags":[
        "eating"
    ],
    "wof:name":"Taqueria Express",
    "wof:placetype":"venue"
},
  "geometry": {"coordinates":[-95.52099800000001,29.685377],"type":"Point"}
}