{
  "type": "Feature",
  "properties": {
    "iso:country":"US",
    "sg:address":"9914 Derecho Dr",
    "sg:city":"Austin",
    "sg:classifiers":[
        {
            "category":"Personal",
            "subcategory":"Beauty Salon",
            "type":"Services"
        }
    ],
    "sg:phone":"+1 512 301 9370",
    "sg:postcode":"78737",
    "sg:province":"TX",
    "sg:tags":[
        "shop"
    ],
    "wof:name":"Mary Anns Favorite Thing",
    "wof:placetype":"venue"
},
  "geometry": {"coordinates":[-97.937534,30.218215],"type":"Point"}
}