{
  "type": "Feature",
  "properties": {
    "iso:country":"US",
    "sg:address":"9913 Bruton Rd",
    "sg:city":"Dallas",
    "sg:classifiers":[
        {
            "category":"Professional",
            "type":"Services"
        }
    ],
    "sg:phone":"+1 214 664 9110",
    "sg:postcode":"75217",
    "sg:province":"TX",
    "wof:name":"Wilson Laquitha",
    "wof:placetype":"venue"
},
  "geometry": {"coordinates":[-96.650599,32.748655],"type":"Point"}
}