{
  "type": "Feature",
  "properties": {
    "iso:country":"US",
    "sg:address":"200 W Dallas Ave",
    "sg:city":"Cooper",
    "sg:classifiers":[
        {
            "category":"Government",
            "subcategory":"Office",
            "type":"Public Place"
        }
    ],
    "sg:phone":"+1 903 395 4417",
    "sg:postcode":"75432",
    "sg:province":"TX",
    "wof:name":"Delta County Extension Agents",
    "wof:placetype":"venue"
},
  "geometry": {"coordinates":[-95.69040099999999,33.373844],"type":"Point"}
}