{
  "type": "Feature",
  "properties": {
    "iso:country":"US",
    "sg:address":"527 Houston School Rd",
    "sg:city":"Red Oak",
    "sg:classifiers":[
        {
            "category":"Building & Trades",
            "subcategory":"Construction",
            "type":"Services"
        }
    ],
    "sg:phone":"+1 972 230 6665",
    "sg:postcode":"75154",
    "sg:province":"TX",
    "sg:tags":[
        "contractor"
    ],
    "wof:name":"Deans Welding Services",
    "wof:placetype":"venue"
},
  "geometry": {"coordinates":[-96.805364,32.543253],"type":"Point"}
}