{
  "type": "Feature",
  "properties": {
    "iso:country":"US",
    "sg:address":"3511 Ave A",
    "sg:city":"Snyder",
    "sg:classifiers":[
        {
            "category":"Professional",
            "subcategory":"Business Services",
            "type":"Services"
        }
    ],
    "sg:phone":"+1 325 573 3267",
    "sg:postcode":"79549",
    "sg:province":"TX",
    "sg:tags":[
        "inspection"
    ],
    "wof:name":"Don's Inspection Svc",
    "wof:placetype":"venue"
},
  "geometry": {"coordinates":[-100.893355,32.707024],"type":"Point"}
}