{
  "type": "Feature",
  "properties": {
    "iso:country":"US",
    "sg:address":"7102 Deep Forest Dr",
    "sg:city":"Houston",
    "sg:classifiers":[
        {
            "category":"Real Estate",
            "subcategory":"Architect",
            "type":"Services"
        }
    ],
    "sg:phone":"+1 281 448 7218",
    "sg:postcode":"77088",
    "sg:province":"TX",
    "sg:tags":[
        "consultant",
        "design",
        "architectural"
    ],
    "wof:name":"Teklab",
    "wof:placetype":"venue"
},
  "geometry": {"coordinates":[-95.475572,29.865744],"type":"Point"}
}