{
  "type": "Feature",
  "properties": {
    "iso:country":"US",
    "sg:address":"425 Industrial Dr E",
    "sg:city":"Sulphur Springs",
    "sg:classifiers":[
        {
            "category":"Restaurant",
            "type":"Food & Drink"
        }
    ],
    "sg:phone":"+1 903 885 7746",
    "sg:postcode":"75482",
    "sg:province":"TX",
    "sg:tags":[
        "eating"
    ],
    "wof:name":"KFC",
    "wof:placetype":"venue"
},
  "geometry": {"coordinates":[-95.586468,33.119784],"type":"Point"}
}