{
  "type": "Feature",
  "properties": {
    "iso:country":"US",
    "sg:address":"8111 LBJ Fwy Ste 1150",
    "sg:city":"Dallas",
    "sg:classifiers":[
        {
            "category":"Banks & Credit Unions",
            "subcategory":"Financial Services",
            "type":"Services"
        }
    ],
    "sg:phone":"+1 866 430 3437",
    "sg:postcode":"75241",
    "sg:province":"TX",
    "sg:website":"www.fhfinancialservice.com",
    "wof:name":"FH Financial Service",
    "wof:placetype":"venue"
},
  "geometry": {"coordinates":[-96.76636000000001,32.925415],"type":"Point"}
}