{
  "type": "Feature",
  "properties": {
    "iso:country":"US",
    "sg:address":"12593 Research Blvd",
    "sg:city":"Austin",
    "sg:classifiers":[
        {
            "category":"Social Services",
            "type":"Services"
        }
    ],
    "sg:phone":"+1 512 249 0123",
    "sg:postcode":"78759",
    "sg:province":"TX",
    "sg:tags":[
        "counselor",
        "marriage",
        "family"
    ],
    "wof:name":"Jamie R Oliver",
    "wof:placetype":"venue"
},
  "geometry": {"coordinates":[-97.760964,30.430544],"type":"Point"}
}