{
  "type": "Feature",
  "properties": {
    "iso:country":"US",
    "sg:address":"6000 Stonewall St",
    "sg:city":"Greenville",
    "sg:classifiers":[
        {
            "category":"Education",
            "subcategory":"School",
            "type":"Public Place"
        }
    ],
    "sg:phone":"+1 903 457 2676",
    "sg:postcode":"75402",
    "sg:province":"TX",
    "sg:tags":[
        "elementary"
    ],
    "sg:website":"http://www.greenvilleisd.com",
    "wof:name":"Bowie Elementary School",
    "wof:placetype":"venue"
},
  "geometry": {"coordinates":[-96.107491,33.109859],"type":"Point"}
}