{
  "type": "Feature",
  "properties": {
    "iso:country":"US",
    "sg:address":"6370 N Eldridge Pkwy",
    "sg:city":"Houston",
    "sg:classifiers":[
        {
            "category":"Shopping",
            "type":"Retail Goods"
        }
    ],
    "sg:phone":"+1 281 859 5822",
    "sg:postcode":"77041",
    "sg:province":"TX",
    "sg:tags":[
        "candle"
    ],
    "wof:name":"Burning Desires",
    "wof:placetype":"venue"
},
  "geometry": {"coordinates":[-95.60807200000001,29.862596],"type":"Point"}
}