{
  "type": "Feature",
  "properties": {
    "iso:country":"US",
    "sg:address":"123 Southbridge St",
    "sg:city":"San Antonio",
    "sg:classifiers":[
        {
            "category":"Personal",
            "type":"Services"
        }
    ],
    "sg:phone":"+1 210 344 7623",
    "sg:postcode":"78216",
    "sg:province":"TX",
    "sg:tags":[
        "salon",
        "tanning"
    ],
    "wof:name":"Tan Your Hide",
    "wof:placetype":"venue"
},
  "geometry": {"coordinates":[-98.49988,29.515413],"type":"Point"}
}