{
  "type": "Feature",
  "properties": {
    "iso:country":"US",
    "sg:address":"18167 Glenledi Dr",
    "sg:city":"Houston",
    "sg:classifiers":[
        {
            "category":"Restaurant",
            "type":"Food & Drink"
        }
    ],
    "sg:phone":"+1 281 861 8226",
    "sg:postcode":"77084",
    "sg:province":"TX",
    "wof:name":"Hay Caramba",
    "wof:placetype":"venue"
},
  "geometry": {"coordinates":[-95.67914,29.856285],"type":"Point"}
}