{
  "type": "Feature",
  "properties": {
    "iso:country":"US",
    "sg:address":"550 Valley Ridge Blvd",
    "sg:city":"Lewisville",
    "sg:classifiers":[
        {
            "category":"Building & Trades",
            "subcategory":"Construction",
            "type":"Services"
        }
    ],
    "sg:phone":"+1 972 219 2446",
    "sg:postcode":"75057",
    "sg:province":"TX",
    "sg:tags":[
        "fiber",
        "optics"
    ],
    "wof:name":"Vikimatic Sales Inc",
    "wof:placetype":"venue"
},
  "geometry": {"coordinates":[-97.00673,33.056984],"type":"Point"}
}