{
  "type": "Feature",
  "properties": {
    "iso:country":"US",
    "sg:address":"3706 Sun Valley Dr",
    "sg:city":"Houston",
    "sg:classifiers":[
        {
            "category":"Health Services",
            "subcategory":"Dentist",
            "type":"Services"
        }
    ],
    "sg:phone":"+1 713 666 7961",
    "sg:postcode":"77025",
    "sg:province":"TX",
    "wof:name":"Willie Joseph R Dntst",
    "wof:placetype":"venue"
},
  "geometry": {"coordinates":[-95.43710299999999,29.683201],"type":"Point"}
}