{
  "type": "Feature",
  "properties": {
    "iso:country":"US",
    "sg:address":"5009 Woodville Ln",
    "sg:city":"Pearland",
    "sg:classifiers":[
        {
            "category":"Professional",
            "subcategory":"Business Services",
            "type":"Services"
        }
    ],
    "sg:phone":"+1 281 485 7553",
    "sg:postcode":"77584",
    "sg:province":"TX",
    "wof:name":"Edwards Training & Consulting",
    "wof:placetype":"venue"
},
  "geometry": {"coordinates":[-95.30089599999999,29.553944],"type":"Point"}
}