{
  "type": "Feature",
  "properties": {
    "iso:country":"US",
    "sg:address":"416 State Hwy 19",
    "sg:city":"Trinity",
    "sg:classifiers":[
        {
            "category":"Shopping",
            "subcategory":"Computers & Home Electronics",
            "type":"Retail Goods"
        }
    ],
    "sg:phone":"+1 936 594 6679",
    "sg:postcode":"75862",
    "sg:province":"TX",
    "sg:tags":[
        "antenna"
    ],
    "wof:name":"Custom Satellite",
    "wof:placetype":"venue"
},
  "geometry": {"coordinates":[-95.381878,30.957015],"type":"Point"}
}