{
  "type": "Feature",
  "properties": {
    "iso:country":"US",
    "sg:address":"5400 Rustic Trl",
    "sg:city":"Kaufman",
    "sg:classifiers":[
        {
            "category":"Manufacturing",
            "subcategory":"Metals",
            "type":"Manufacturing & Wholesale Goods"
        }
    ],
    "sg:phone":"+1 972 932 6790",
    "sg:postcode":"75142",
    "sg:province":"TX",
    "sg:tags":[
        "mfg",
        "forging"
    ],
    "wof:name":"Ron Atchison",
    "wof:placetype":"venue"
},
  "geometry": {"coordinates":[-96.27274300000001,32.563798],"type":"Point"}
}