{
  "type": "Feature",
  "properties": {
    "iso:country":"US",
    "sg:address":"300 N Green St",
    "sg:city":"Longview",
    "sg:classifiers":[
        {
            "category":"Professional",
            "subcategory":"Management & Consulting",
            "type":"Services"
        }
    ],
    "sg:phone":"+1 903 753 3388",
    "sg:postcode":"75601",
    "sg:province":"TX",
    "sg:tags":[
        "fuel"
    ],
    "wof:name":"Sixty-Six Management",
    "wof:placetype":"venue"
},
  "geometry": {"coordinates":[-94.73622400000001,32.496482],"type":"Point"}
}