{
  "type": "Feature",
  "properties": {
    "iso:country":"US",
    "sg:address":"210 E Broadway St",
    "sg:city":"Andrews",
    "sg:classifiers":[
        {
            "category":"Professional",
            "subcategory":"Advertising",
            "type":"Services"
        }
    ],
    "sg:phone":"+1 432 523 2085",
    "sg:postcode":"79714",
    "sg:province":"TX",
    "sg:tags":[
        "representative"
    ],
    "wof:name":"Andrews County News",
    "wof:placetype":"venue"
},
  "geometry": {"coordinates":[-102.54524000000001,32.318968],"type":"Point"}
}