{
  "type": "Feature",
  "properties": {
    "iso:country":"US",
    "sg:address":"13135 Dairy Ashford Rd",
    "sg:city":"Sugar Land",
    "sg:classifiers":[
        {
            "category":"Health Services",
            "subcategory":"Health Practitioner",
            "type":"Services"
        }
    ],
    "sg:phone":"+1 281 313 6363",
    "sg:postcode":"77478",
    "sg:province":"TX",
    "sg:tags":[
        "nurse",
        "registry"
    ],
    "wof:name":"Interim Healthcare",
    "wof:placetype":"venue"
},
  "geometry": {"coordinates":[-95.597705,29.628592],"type":"Point"}
}