{
  "type": "Feature",
  "properties": {
    "iso:country":"US",
    "sg:address":"9 Village Way",
    "sg:city":"Roanoke",
    "sg:classifiers":[
        {
            "category":"Professional",
            "type":"Services"
        }
    ],
    "sg:phone":"+1 817 430 4655",
    "sg:postcode":"76262",
    "sg:province":"TX",
    "wof:name":"Medical Air Svc",
    "wof:placetype":"venue"
},
  "geometry": {"coordinates":[-97.180305,32.993922],"type":"Point"}
}