{
  "type": "Feature",
  "properties": {
    "iso:country":"US",
    "sg:address":"1628 Ardath Ave",
    "sg:city":"Wichita Falls",
    "sg:classifiers":[
        {
            "category":"Building & Trades",
            "subcategory":"Construction",
            "type":"Services"
        }
    ],
    "sg:phone":"+1 940 642 8884",
    "sg:postcode":"76301",
    "sg:province":"TX",
    "sg:tags":[
        "house"
    ],
    "wof:name":"Kozmozaic Designs",
    "wof:placetype":"venue"
},
  "geometry": {"coordinates":[-98.500491,33.89018],"type":"Point"}
}