{
  "type": "Feature",
  "properties": {
    "iso:country":"US",
    "sg:address":"2625 N Josey Ln",
    "sg:city":"Carrollton",
    "sg:classifiers":[
        {
            "category":"Banks & Credit Unions",
            "subcategory":"Bank",
            "type":"Services"
        }
    ],
    "sg:phone":"+1 972 446 3618",
    "sg:postcode":"75007",
    "sg:province":"TX",
    "wof:name":"Comerica Bank",
    "wof:placetype":"venue"
},
  "geometry": {"coordinates":[-96.891048,32.986971],"type":"Point"}
}