{
  "type": "Feature",
  "properties": {
    "iso:country":"US",
    "sg:address":"434 Texas St",
    "sg:city":"South Houston",
    "sg:classifiers":[
        {
            "category":"Building & Trades",
            "subcategory":"Plumbing",
            "type":"Services"
        }
    ],
    "sg:phone":"+1 713 947 0399",
    "sg:postcode":"77587",
    "sg:province":"TX",
    "sg:tags":[
        "contractor"
    ],
    "wof:name":"AC Service",
    "wof:placetype":"venue"
},
  "geometry": {"coordinates":[-95.229798,29.660187],"type":"Point"}
}