{
  "type": "Feature",
  "properties": {
    "iso:country":"US",
    "sg:address":"5201 Wolf Ln",
    "sg:city":"Del Valle",
    "sg:classifiers":[
        {
            "category":"Retail",
            "subcategory":"Auto Repair",
            "type":"Services"
        }
    ],
    "sg:phone":"+1 512 247 9962",
    "sg:postcode":"78617",
    "sg:province":"TX",
    "sg:tags":[
        "body",
        "automobile",
        "painting"
    ],
    "wof:name":"J & V Body Shop",
    "wof:placetype":"venue"
},
  "geometry": {"coordinates":[-97.544383,30.177193],"type":"Point"}
}