{
  "type": "Feature",
  "properties": {
    "iso:country":"US",
    "sg:address":"4925 63rd St",
    "sg:city":"Lubbock",
    "sg:classifiers":[
        {
            "category":"Shopping",
            "subcategory":"Books",
            "type":"Retail Goods"
        }
    ],
    "sg:phone":"+1 806 793 0696",
    "sg:postcode":"79414",
    "sg:province":"TX",
    "wof:name":"Elmcreek Ranche Books",
    "wof:placetype":"venue"
},
  "geometry": {"coordinates":[-101.91923,33.536888],"type":"Point"}
}