{
  "type": "Feature",
  "properties": {
    "iso:country":"US",
    "sg:address":"11634 Taos Ln",
    "sg:city":"Houston",
    "sg:classifiers":[
        {
            "category":"Professional",
            "subcategory":"Detective & Security Services",
            "type":"Services"
        }
    ],
    "sg:phone":"+1 281 370 5882",
    "sg:postcode":"77070",
    "sg:province":"TX",
    "sg:tags":[
        "car",
        "investigator"
    ],
    "wof:name":"Dan H North & Associates",
    "wof:placetype":"venue"
},
  "geometry": {"coordinates":[-95.597719,29.976907],"type":"Point"}
}