{
  "type": "Feature",
  "properties": {
    "iso:country":"US",
    "sg:address":"623 W Main St",
    "sg:city":"Arlington",
    "sg:classifiers":[
        {
            "category":"Banks & Credit Unions",
            "subcategory":"Financial Services",
            "type":"Services"
        }
    ],
    "sg:phone":"+1 817 469 9420",
    "sg:postcode":"76010",
    "sg:province":"TX",
    "sg:tags":[
        "investor"
    ],
    "wof:name":"City Investors Group Inc",
    "wof:placetype":"venue"
},
  "geometry": {"coordinates":[-97.11256299999999,32.736874],"type":"Point"}
}