{
  "type": "Feature",
  "properties": {
    "iso:country":"US",
    "sg:address":"557 Myra St",
    "sg:city":"El Paso",
    "sg:classifiers":[
        {
            "category":"Building & Trades",
            "subcategory":"Construction",
            "type":"Services"
        }
    ],
    "sg:phone":"+1 915 591 3937",
    "sg:postcode":"79915",
    "sg:province":"TX",
    "sg:tags":[
        "contractor"
    ],
    "wof:name":"Valley Roofing Inc",
    "wof:placetype":"venue"
},
  "geometry": {"coordinates":[-106.353807,31.737926],"type":"Point"}
}