{
  "type": "Feature",
  "properties": {
    "iso:country":"US",
    "sg:address":"4318 Centergate St",
    "sg:city":"San Antonio",
    "sg:classifiers":[
        {
            "category":"Wholesale",
            "subcategory":"Electrical",
            "type":"Manufacturing & Wholesale Goods"
        }
    ],
    "sg:phone":"+1 210 657 4110",
    "sg:postcode":"78217",
    "sg:province":"TX",
    "sg:tags":[
        "equipment",
        "electronic"
    ],
    "wof:name":"HISCO",
    "wof:placetype":"venue"
},
  "geometry": {"coordinates":[-98.407448,29.520533],"type":"Point"}
}