{
  "type": "Feature",
  "properties": {
    "iso:country":"US",
    "sg:address":"7616 Jamie Renee Ln",
    "sg:city":"Fort Worth",
    "sg:classifiers":[
        {
            "category":"Professional",
            "subcategory":"Business Services",
            "type":"Services"
        }
    ],
    "sg:phone":"+1 817 581 1157",
    "sg:postcode":"76180",
    "sg:province":"TX",
    "wof:name":"Van Scoit Group LLC",
    "wof:placetype":"venue"
},
  "geometry": {"coordinates":[-97.218827,32.866623],"type":"Point"}
}