{
  "type": "Feature",
  "properties": {
    "iso:country":"US",
    "sg:address":"7275 Creekside Dr",
    "sg:city":"Austin",
    "sg:classifiers":[
        {
            "category":"Professional",
            "subcategory":"Business Services",
            "type":"Services"
        }
    ],
    "sg:phone":"+1 512 454 6422",
    "sg:postcode":"78752",
    "sg:province":"TX",
    "wof:name":"Kim Dunkerley-Offor",
    "wof:placetype":"venue"
},
  "geometry": {"coordinates":[-97.68455299999999,30.324209],"type":"Point"}
}