{
  "type": "Feature",
  "properties": {
    "iso:country":"US",
    "sg:address":"7600 Whitley Rd",
    "sg:city":"Watauga",
    "sg:classifiers":[
        {
            "category":"Education",
            "subcategory":"School",
            "type":"Public Place"
        }
    ],
    "sg:phone":"+1 817 281 9542",
    "sg:postcode":"76148",
    "sg:province":"TX",
    "sg:website":"www.kellerisd.net",
    "wof:name":"Whitley Road Elementary School",
    "wof:placetype":"venue"
},
  "geometry": {"coordinates":[-97.25485500000001,32.881468],"type":"Point"}
}