{
  "type": "Feature",
  "properties": {
    "iso:country":"US",
    "sg:address":"1611 S I- 35 E",
    "sg:city":"Carrollton",
    "sg:classifiers":[
        {
            "category":"Professional",
            "subcategory":"Computer Services",
            "type":"Services"
        }
    ],
    "sg:phone":"+1 972 466 4629",
    "sg:postcode":"75006",
    "sg:province":"TX",
    "sg:tags":[
        "design",
        "integrated",
        "system"
    ],
    "wof:name":"Ecoglo LLC",
    "wof:placetype":"venue"
},
  "geometry": {"coordinates":[-96.904866,32.946065],"type":"Point"}
}