{
  "type": "Feature",
  "properties": {
    "iso:country":"US",
    "sg:address":"27 Hickory Hollow Pl",
    "sg:city":"Spring",
    "sg:classifiers":[
        {
            "category":"Professional",
            "type":"Services"
        }
    ],
    "sg:phone":"+1 281 363 9374",
    "sg:postcode":"77381",
    "sg:province":"TX",
    "wof:name":"Creative Writing",
    "wof:placetype":"venue"
},
  "geometry": {"coordinates":[-95.51375,30.161433],"type":"Point"}
}