{
  "type": "Feature",
  "properties": {
    "iso:country":"US",
    "sg:address":"13526 Rockshire Dr",
    "sg:city":"Houston",
    "sg:classifiers":[
        {
            "category":"Building & Trades",
            "subcategory":"Construction",
            "type":"Services"
        }
    ],
    "sg:phone":"+1 281 449 4522",
    "sg:postcode":"77039",
    "sg:province":"TX",
    "sg:tags":[
        "contractor"
    ],
    "wof:name":"Gng Rodz Contracting",
    "wof:placetype":"venue"
},
  "geometry": {"coordinates":[-95.341747,29.910972],"type":"Point"}
}