{
  "type": "Feature",
  "properties": {
    "iso:country":"US",
    "sg:address":"527 Holfords Prairie Rd",
    "sg:city":"Lewisville",
    "sg:classifiers":[
        {
            "category":"Freight",
            "type":"Transportation"
        }
    ],
    "sg:phone":"+1 972 492 8568",
    "sg:postcode":"75056",
    "sg:province":"TX",
    "sg:tags":[
        "general"
    ],
    "wof:name":"Raymond Myers",
    "wof:placetype":"venue"
},
  "geometry": {"coordinates":[-96.93639899999999,33.043268],"type":"Point"}
}