{
  "type": "Feature",
  "properties": {
    "iso:country":"US",
    "sg:address":"1857 Leroy Bonse Dr",
    "sg:city":"El Paso",
    "sg:classifiers":[
        {
            "category":"Social Services",
            "subcategory":"Child Care",
            "type":"Services"
        }
    ],
    "sg:phone":"+1 915 855 2318",
    "sg:postcode":"79936",
    "sg:province":"TX",
    "sg:tags":[
        "day"
    ],
    "wof:name":"Paolas Day Care",
    "wof:placetype":"venue"
},
  "geometry": {"coordinates":[-106.290857,31.766616],"type":"Point"}
}