{
  "type": "Feature",
  "properties": {
    "iso:country":"US",
    "sg:address":"1200 Summit Ave",
    "sg:city":"Fort Worth",
    "sg:classifiers":[
        {
            "category":"Real Estate",
            "subcategory":"Architect",
            "type":"Services"
        }
    ],
    "sg:phone":"+1 817 336 9010",
    "sg:postcode":"76102",
    "sg:province":"TX",
    "sg:tags":[
        "architectural"
    ],
    "wof:name":"Nader Design Group",
    "wof:placetype":"venue"
},
  "geometry": {"coordinates":[-97.34162999999999,32.746035],"type":"Point"}
}