{
  "type": "Feature",
  "properties": {
    "iso:country":"US",
    "sg:address":"113 Rio Bravo St",
    "sg:city":"San Antonio",
    "sg:classifiers":[
        {
            "category":"Insurance",
            "subcategory":"Insurance Agent",
            "type":"Services"
        }
    ],
    "sg:phone":"+1 210 494 3357",
    "sg:postcode":"78232",
    "sg:province":"TX",
    "wof:name":"Norman C Thomas",
    "wof:placetype":"venue"
},
  "geometry": {"coordinates":[-98.47019299999999,29.581095],"type":"Point"}
}