{
  "type": "Feature",
  "properties": {
    "iso:country":"US",
    "sg:address":"1298 Ross Ln",
    "sg:city":"Boyd",
    "sg:classifiers":[
        {
            "category":"Retail",
            "subcategory":"Animal Services",
            "type":"Services"
        }
    ],
    "sg:phone":"+1 817 691 3768",
    "sg:postcode":"76082",
    "sg:province":"TX",
    "sg:tags":[
        "training",
        "dog"
    ],
    "wof:name":"Crooked Oak Kennels",
    "wof:placetype":"venue"
},
  "geometry": {"coordinates":[-97.60212799999999,33.008789],"type":"Point"}
}