{
  "type": "Feature",
  "properties": {
    "iso:country":"US",
    "sg:address":"3995 S 4th St",
    "sg:city":"Beaumont",
    "sg:classifiers":[
        {
            "category":"Retail",
            "subcategory":"Car Wash",
            "type":"Services"
        }
    ],
    "sg:phone":"+1 409 840 6244",
    "sg:postcode":"77705",
    "sg:province":"TX",
    "sg:tags":[
        "polishing",
        "washing"
    ],
    "wof:name":"Lincoln's Car Wash",
    "wof:placetype":"venue"
},
  "geometry": {"coordinates":[-94.11529899999999,30.04808],"type":"Point"}
}