{
  "type": "Feature",
  "properties": {
    "iso:country":"US",
    "sg:address":"106 E Market St",
    "sg:city":"Lockhart",
    "sg:classifiers":[
        {
            "category":"Shopping",
            "subcategory":"Used Merchandise",
            "type":"Retail Goods"
        }
    ],
    "sg:phone":"+1 512 620 0307",
    "sg:postcode":"78644",
    "sg:province":"TX",
    "sg:tags":[
        "shop",
        "consignment"
    ],
    "wof:name":"Raelynn's",
    "wof:placetype":"venue"
},
  "geometry": {"coordinates":[-97.671263,29.883934],"type":"Point"}
}