{
  "type": "Feature",
  "properties": {
    "iso:country":"US",
    "sg:address":"612 Prestonwood Cir",
    "sg:city":"Tyler",
    "sg:classifiers":[
        {
            "category":"Health Services",
            "subcategory":"Clinic",
            "type":"Services"
        },
        {
            "category":"Health Services",
            "subcategory":"Nursing And Care Facility",
            "type":"Services"
        },
        {
            "category":"Health Services",
            "subcategory":"Health Practitioner",
            "type":"Services"
        }
    ],
    "sg:phone":"+1 903 504 5145",
    "sg:postcode":"75703",
    "sg:province":"TX",
    "sg:tags":[
        "home",
        "eldercare-home",
        "welfare"
    ],
    "wof:name":"Humility Home Health Care",
    "wof:placetype":"venue"
},
  "geometry": {"coordinates":[-95.315819,32.268669],"type":"Point"}
}