{
  "type": "Feature",
  "properties": {
    "iso:country":"US",
    "sg:address":"11625 Pellicano Dr",
    "sg:city":"El Paso",
    "sg:classifiers":[
        {
            "category":"Health Services",
            "subcategory":"Clinic",
            "type":"Services"
        }
    ],
    "sg:phone":"+1 915 591 0900",
    "sg:postcode":"79936",
    "sg:province":"TX",
    "sg:tags":[
        "home"
    ],
    "wof:name":"Southwest Home Health",
    "wof:placetype":"venue"
},
  "geometry": {"coordinates":[-106.301379,31.744439],"type":"Point"}
}