{
  "type": "Feature",
  "properties": {
    "iso:country":"US",
    "sg:address":"501 School House Rd",
    "sg:city":"Haslet",
    "sg:classifiers":[
        {
            "category":"Education",
            "subcategory":"School",
            "type":"Public Place"
        }
    ],
    "sg:phone":"+1 817 439 3231",
    "sg:postcode":"76052",
    "sg:province":"TX",
    "wof:name":"Haslet Elementary School",
    "wof:placetype":"venue"
},
  "geometry": {"coordinates":[-97.349335,32.970108],"type":"Point"}
}