{
  "type": "Feature",
  "properties": {
    "iso:country":"US",
    "sg:address":"4825 San Jacinto St",
    "sg:city":"Houston",
    "sg:classifiers":[
        {
            "category":"Wholesale",
            "subcategory":"Durable Goods & Equipment",
            "type":"Manufacturing & Wholesale Goods"
        }
    ],
    "sg:phone":"+1 713 524 8236",
    "sg:postcode":"77004",
    "sg:province":"TX",
    "sg:tags":[
        "theatrical",
        "costume",
        "supply"
    ],
    "sg:website":"http://www.southern-importers.com",
    "wof:name":"Southern Importers & Exporters",
    "wof:placetype":"venue"
},
  "geometry": {"coordinates":[-95.383698,29.7299],"type":"Point"}
}