{
  "type": "Feature",
  "properties": {
    "iso:country":"US",
    "sg:address":"2 S Briar Hollow Ln",
    "sg:city":"Houston",
    "sg:classifiers":[
        {
            "category":"Professional",
            "type":"Services"
        }
    ],
    "sg:phone":"+1 713 355 6118",
    "sg:postcode":"77027",
    "sg:province":"TX",
    "wof:name":"Interests L Chaney L",
    "wof:placetype":"venue"
},
  "geometry": {"coordinates":[-95.448663,29.751178],"type":"Point"}
}