{
  "type": "Feature",
  "properties": {
    "iso:country":"US",
    "sg:address":"2813 Country Club Dr",
    "sg:city":"Pearland",
    "sg:classifiers":[
        {
            "category":"Banks & Credit Unions",
            "subcategory":"Bank",
            "type":"Services"
        }
    ],
    "sg:phone":"+1 281 294 9911",
    "sg:postcode":"77581",
    "sg:province":"TX",
    "sg:tags":[
        "loan",
        "real estate"
    ],
    "wof:name":"Brownstone Mortgage Co",
    "wof:placetype":"venue"
},
  "geometry": {"coordinates":[-95.24620400000001,29.562711],"type":"Point"}
}