{
  "type": "Feature",
  "properties": {
    "iso:country":"US",
    "sg:address":"6128 N Martin Luther King Ave",
    "sg:city":"Hitchcock",
    "sg:classifiers":[
        {
            "category":"Shopping",
            "subcategory":"Clothing, Apparel, & Fashions",
            "type":"Retail Goods"
        }
    ],
    "sg:phone":"+1 409 986 6822",
    "sg:postcode":"77563",
    "sg:province":"TX",
    "wof:name":"Drmt Smith & Assoc",
    "wof:placetype":"venue"
},
  "geometry": {"coordinates":[-94.992152,29.338982],"type":"Point"}
}