{
  "type": "Feature",
  "properties": {
    "iso:country":"US",
    "sg:address":"402 Main St",
    "sg:city":"Odem",
    "sg:classifiers":[
        {
            "category":"Social Services",
            "subcategory":"Child Care",
            "type":"Services"
        }
    ],
    "sg:phone":"+1 361 368 3068",
    "sg:postcode":"78370",
    "sg:province":"TX",
    "wof:name":"Cinderellas Child Group Day",
    "wof:placetype":"venue"
},
  "geometry": {"coordinates":[-97.58438099999999,27.951721],"type":"Point"}
}