{
  "type": "Feature",
  "properties": {
    "iso:country":"US",
    "sg:address":"10821 Bissonnet St",
    "sg:city":"Houston",
    "sg:classifiers":[
        {
            "category":"Insurance",
            "subcategory":"Insurance Agent",
            "type":"Services"
        }
    ],
    "sg:phone":"+1 281 879 5858",
    "sg:postcode":"77099",
    "sg:province":"TX",
    "wof:name":"Insurance Claims Assistants",
    "wof:placetype":"venue"
},
  "geometry": {"coordinates":[-95.568907,29.674213],"type":"Point"}
}