{
  "type": "Feature",
  "properties": {
    "iso:country":"US",
    "sg:address":"1241 Gazania Dr",
    "sg:city":"Pflugerville",
    "sg:classifiers":[
        {
            "category":"Retail",
            "subcategory":"Repair Shop",
            "type":"Services"
        }
    ],
    "sg:phone":"+1 512 252 8173",
    "sg:postcode":"78660",
    "sg:province":"TX",
    "wof:name":"Had Thatcom",
    "wof:placetype":"venue"
},
  "geometry": {"coordinates":[-97.630725,30.458033],"type":"Point"}
}