{
  "type": "Feature",
  "properties": {
    "iso:country":"US",
    "sg:address":"518 Wellington Pt",
    "sg:city":"Houston",
    "sg:classifiers":[
        {
            "category":"Insurance",
            "subcategory":"Insurance Agent",
            "type":"Services"
        }
    ],
    "sg:phone":"+1 281 398 0767",
    "sg:postcode":"77094",
    "sg:province":"TX",
    "wof:name":"Health Insurance Solutions",
    "wof:placetype":"venue"
},
  "geometry": {"coordinates":[-95.705962,29.776535],"type":"Point"}
}