{
  "type": "Feature",
  "properties": {
    "iso:country":"US",
    "sg:address":"2102 W Avenue D",
    "sg:city":"Temple",
    "sg:classifiers":[
        {
            "category":"Retail",
            "subcategory":"Laundry & Dry Cleaning",
            "type":"Services"
        }
    ],
    "sg:phone":"+1 254 771 3402",
    "sg:postcode":"76504",
    "sg:province":"TX",
    "sg:tags":[
        "cleaner",
        "rug",
        "carpet"
    ],
    "sg:website":"http://www.dynacleanps.com",
    "wof:name":"Dynaclean",
    "wof:placetype":"venue"
},
  "geometry": {"coordinates":[-97.36480899999999,31.098802],"type":"Point"}
}