{
  "type": "Feature",
  "properties": {
    "iso:country":"US",
    "sg:address":"310 N University Dr",
    "sg:city":"Nacogdoches",
    "sg:classifiers":[
        {
            "category":"Personal",
            "subcategory":"Beauty Salon",
            "type":"Services"
        }
    ],
    "sg:phone":"+1 936 569 8083",
    "sg:postcode":"75961",
    "sg:province":"TX",
    "sg:tags":[
        "shop"
    ],
    "wof:name":"Head To Toe Salon",
    "wof:placetype":"venue"
},
  "geometry": {"coordinates":[-94.64633600000001,31.601544],"type":"Point"}
}