{
  "type": "Feature",
  "properties": {
    "iso:country":"US",
    "sg:address":"3715 Mohawk St",
    "sg:city":"Bryan",
    "sg:classifiers":[
        {
            "category":"Sports & Exercise",
            "subcategory":"Golf",
            "type":"Entertainment"
        }
    ],
    "sg:phone":"+1 979 776 0300",
    "sg:postcode":"77802",
    "sg:province":"TX",
    "sg:tags":[
        "course"
    ],
    "wof:name":"Bryan Driving Range",
    "wof:placetype":"venue"
},
  "geometry": {"coordinates":[-96.325858,30.672777],"type":"Point"}
}