{
  "type": "Feature",
  "properties": {
    "iso:country":"US",
    "sg:address":"623 New Laredo Hwy",
    "sg:city":"San Antonio",
    "sg:classifiers":[
        {
            "category":"Professional",
            "type":"Services"
        },
        {
            "category":"Manufacturing",
            "subcategory":"Food",
            "type":"Manufacturing & Wholesale Goods"
        }
    ],
    "sg:phone":"+1 210 922 8411",
    "sg:postcode":"78211",
    "sg:province":"TX",
    "sg:tags":[
        "company",
        "establishment"
    ],
    "wof:name":"El Rancho Tortilla Inc",
    "wof:placetype":"venue"
},
  "geometry": {"coordinates":[-98.549172,29.365684],"type":"Point"}
}