{
  "type": "Feature",
  "properties": {
    "iso:country":"US",
    "sg:address":"14621 State Hwy 249",
    "sg:city":"Houston",
    "sg:classifiers":[
        {
            "category":"Autos & Motor Vehicles",
            "subcategory":"Automobile Sales",
            "type":"Retail Goods"
        }
    ],
    "sg:phone":"+1 281 537 1555",
    "sg:postcode":"77086",
    "sg:province":"TX",
    "sg:tags":[
        "used"
    ],
    "wof:name":"Z Auto Place",
    "wof:placetype":"venue"
},
  "geometry": {"coordinates":[-95.501294,29.925346],"type":"Point"}
}