{
  "type": "Feature",
  "properties": {
    "iso:country":"US",
    "sg:address":"3331 State Hwy 146",
    "sg:city":"Bacliff",
    "sg:classifiers":[
        {
            "category":"Manufacturing",
            "subcategory":"Tools & Machinery",
            "type":"Manufacturing & Wholesale Goods"
        }
    ],
    "sg:phone":"+1 281 339 2660",
    "sg:postcode":"77518",
    "sg:province":"TX",
    "wof:name":"Centrifuge Services Intl",
    "wof:placetype":"venue"
},
  "geometry": {"coordinates":[-95.00416300000001,29.514258],"type":"Point"}
}