{
  "type": "Feature",
  "properties": {
    "iso:country":"US",
    "sg:address":"107 W Cibolo Dr",
    "sg:city":"Boerne",
    "sg:classifiers":[
        {
            "category":"Personal",
            "subcategory":"Beauty Salon",
            "type":"Services"
        }
    ],
    "sg:phone":"+1 830 249 2606",
    "sg:postcode":"78006",
    "sg:province":"TX",
    "sg:tags":[
        "shop"
    ],
    "wof:name":"Arlie's Beauty Shop",
    "wof:placetype":"venue"
},
  "geometry": {"coordinates":[-98.736591,29.793098],"type":"Point"}
}