{
  "type": "Feature",
  "properties": {
    "iso:country":"US",
    "sg:address":"3011 Grand Ave",
    "sg:city":"Liberty",
    "sg:classifiers":[
        {
            "category":"Restaurant",
            "type":"Food & Drink"
        }
    ],
    "sg:phone":"+1 936 336 1143",
    "sg:postcode":"77575",
    "sg:province":"TX",
    "sg:tags":[
        "eating"
    ],
    "wof:name":"Conquest Investments Inc",
    "wof:placetype":"venue"
},
  "geometry": {"coordinates":[-94.783278,30.063365],"type":"Point"}
}