{
  "type": "Feature",
  "properties": {
    "iso:country":"US",
    "sg:address":"4616 Triangle Ave Ste 403",
    "sg:city":"Austin",
    "sg:classifiers":[
        {
            "category":"Autos & Motor Vehicles",
            "subcategory":"Motorcycle Sales",
            "type":"Retail Goods"
        },
        {
            "category":"Food & Beverages",
            "subcategory":"Groceries & Convenience Stores",
            "type":"Retail Goods"
        }
    ],
    "sg:phone":"+1 512 608 4090",
    "sg:postcode":"78751",
    "sg:province":"TX",
    "sg:website":"www.electricavenuescooters.com",
    "wof:name":"Electric Avenue Scooters + Market",
    "wof:placetype":"venue"
},
  "geometry": {"coordinates":[-97.734184,30.31402],"type":"Point"}
}