{
  "type": "Feature",
  "properties": {
    "iso:country":"US",
    "sg:address":"3125 Matlock Rd",
    "sg:city":"Arlington",
    "sg:classifiers":[
        {
            "category":"Health Services",
            "subcategory":"Doctor",
            "type":"Services"
        }
    ],
    "sg:phone":"+1 817 468 5400",
    "sg:postcode":"76015",
    "sg:province":"TX",
    "sg:tags":[
        "dentist"
    ],
    "wof:name":"John V Shroyer DDS PA",
    "wof:placetype":"venue"
},
  "geometry": {"coordinates":[-97.114964,32.693086],"type":"Point"}
}