{
  "type": "Feature",
  "properties": {
    "iso:country":"US",
    "sg:address":"5902 N Shepherd Dr",
    "sg:city":"Houston",
    "sg:classifiers":[
        {
            "category":"Home & Garden",
            "subcategory":"Household Appliances",
            "type":"Retail Goods"
        }
    ],
    "sg:phone":"+1 713 697 1447",
    "sg:postcode":"77091",
    "sg:province":"TX",
    "wof:name":"D Leon Appliance",
    "wof:placetype":"venue"
},
  "geometry": {"coordinates":[-95.411885,29.851324],"type":"Point"}
}