{
  "type": "Feature",
  "properties": {
    "iso:country":"US",
    "sg:address":"525 Grant Pl",
    "sg:city":"Corpus Christi",
    "sg:phone":"+1 361 854 7550",
    "sg:postcode":"78411",
    "sg:province":"TX",
    "sg:tags":[
        "product",
        "petroleum"
    ],
    "wof:name":"Sk Production",
    "wof:placetype":"venue"
},
  "geometry": {"coordinates":[-97.382797,27.740682],"type":"Point"}
}