{
  "type": "Feature",
  "properties": {
    "iso:country":"US",
    "sg:address":"7700 Cat Hollow Dr Ste 205",
    "sg:city":"Round Rock",
    "sg:classifiers":[
        {
            "category":"Health Services",
            "subcategory":"Doctor",
            "type":"Services"
        }
    ],
    "sg:phone":"+1 512 218 4900",
    "sg:postcode":"78681",
    "sg:province":"TX",
    "wof:name":"Matsubara Atsushi",
    "wof:placetype":"venue"
},
  "geometry": {"coordinates":[-97.725976,30.496474],"type":"Point"}
}