{
  "type": "Feature",
  "properties": {
    "iso:country":"US",
    "sg:address":"5301 E McKinney St",
    "sg:city":"Denton",
    "sg:classifiers":[
        {
            "category":"Sports & Exercise",
            "subcategory":"Golf",
            "type":"Entertainment"
        }
    ],
    "sg:phone":"+1 940 243 4566",
    "sg:postcode":"76208",
    "sg:province":"TX",
    "sg:tags":[
        "course",
        "public"
    ],
    "wof:name":"Changing Course Foundation",
    "wof:placetype":"venue"
},
  "geometry": {"coordinates":[-97.074519,33.207538],"type":"Point"}
}