{
  "type": "Feature",
  "properties": {
    "iso:country":"US",
    "sg:address":"1200 Rosewood Ln",
    "sg:city":"Allen",
    "sg:classifiers":[
        {
            "category":"Professional",
            "type":"Services"
        }
    ],
    "sg:phone":"+1 972 396 0314",
    "sg:postcode":"75002",
    "sg:province":"TX",
    "wof:name":"Justines Designs & Inter",
    "wof:placetype":"venue"
},
  "geometry": {"coordinates":[-96.660082,33.077773],"type":"Point"}
}