{
  "type": "Feature",
  "properties": {
    "iso:country":"US",
    "sg:address":"2244 E State Hwy 176",
    "sg:city":"Andrews",
    "sg:classifiers":[
        {
            "category":"Professional",
            "type":"Services"
        }
    ],
    "sg:phone":"+1 432 523 7842",
    "sg:postcode":"79714",
    "sg:province":"TX",
    "sg:tags":[
        "establishment"
    ],
    "wof:name":"K & D Roustabout",
    "wof:placetype":"venue"
},
  "geometry": {"coordinates":[-102.50105600000001,32.325298],"type":"Point"}
}