{
  "type": "Feature",
  "properties": {
    "iso:country":"US",
    "sg:address":"3818 Irving Mall",
    "sg:city":"Irving",
    "sg:classifiers":[
        {
            "category":"Shopping",
            "subcategory":"Hobbies, Toys, & Games",
            "type":"Retail Goods"
        }
    ],
    "sg:phone":"+1 972 570 5251",
    "sg:postcode":"75062",
    "sg:province":"TX",
    "sg:tags":[
        "store"
    ],
    "wof:name":"Kb Toys",
    "wof:placetype":"venue"
},
  "geometry": {"coordinates":[-96.993622,32.840772],"type":"Point"}
}