{
  "type": "Feature",
  "properties": {
    "iso:country":"US",
    "sg:address":"2402 Texas Ave",
    "sg:city":"El Paso",
    "sg:classifiers":[
        {
            "category":"Manufacturing",
            "subcategory":"Leather Goods",
            "type":"Manufacturing & Wholesale Goods"
        }
    ],
    "sg:phone":"+1 915 533 8732",
    "sg:postcode":"79901",
    "sg:province":"TX",
    "wof:name":"Aztec Importers Inc",
    "wof:placetype":"venue"
},
  "geometry": {"coordinates":[-106.46218,31.774744],"type":"Point"}
}