{
  "type": "Feature",
  "properties": {
    "iso:country":"US",
    "sg:address":"4646 Perrin Creek Pump",
    "sg:city":"San Antonio",
    "sg:classifiers":[
        {
            "category":"Wholesale",
            "subcategory":"Medical Equipment & Supplies",
            "type":"Manufacturing & Wholesale Goods"
        }
    ],
    "sg:phone":"+1 210 655 2160",
    "sg:postcode":"78217",
    "sg:province":"TX",
    "wof:name":"Sourceone Healthcare Tech",
    "wof:placetype":"venue"
},
  "geometry": {"coordinates":[-98.39997700000001,29.52299],"type":"Point"}
}