{
  "type": "Feature",
  "properties": {
    "iso:country":"US",
    "sg:address":"918 Lehman St",
    "sg:city":"Houston",
    "sg:classifiers":[
        {
            "category":"Building & Trades",
            "subcategory":"Landscaping Services",
            "type":"Services"
        }
    ],
    "sg:phone":"+1 713 694 9876",
    "sg:postcode":"77018",
    "sg:province":"TX",
    "sg:tags":[
        "landscape",
        "contractor"
    ],
    "wof:name":"Marco's Lawn & Landscaping",
    "wof:placetype":"venue"
},
  "geometry": {"coordinates":[-95.419275,29.838752],"type":"Point"}
}