{
  "type": "Feature",
  "properties": {
    "iso:country":"US",
    "sg:address":"4426 Blossom St",
    "sg:city":"Houston",
    "sg:classifiers":[
        {
            "category":"Utilities",
            "subcategory":"Telephone",
            "type":"Services"
        }
    ],
    "sg:phone":"+1 713 864 5744",
    "sg:postcode":"77007",
    "sg:province":"TX",
    "sg:tags":[
        "communications"
    ],
    "wof:name":"Diginix",
    "wof:placetype":"venue"
},
  "geometry": {"coordinates":[-95.405781,29.767666],"type":"Point"}
}