{
  "type": "Feature",
  "properties": {
    "iso:country":"US",
    "sg:address":"14414 Moorfield Dr",
    "sg:city":"Houston",
    "sg:classifiers":[
        {
            "category":"Restaurant",
            "type":"Food & Drink"
        }
    ],
    "sg:phone":"+1 281 498 0485",
    "sg:postcode":"77083",
    "sg:province":"TX",
    "sg:tags":[
        "eating"
    ],
    "wof:name":"Cocina Decolima Inc",
    "wof:placetype":"venue"
},
  "geometry": {"coordinates":[-95.63858999999999,29.676338],"type":"Point"}
}