{
  "type": "Feature",
  "properties": {
    "iso:country":"US",
    "sg:address":"504 E June Ave",
    "sg:city":"Alpine",
    "sg:classifiers":[
        {
            "category":"Professional",
            "subcategory":"Accounting & Tax Preparation",
            "type":"Services"
        }
    ],
    "sg:phone":"+1 432 837 5240",
    "sg:postcode":"79830",
    "sg:province":"TX",
    "wof:name":"Cobb Bookkeeping",
    "wof:placetype":"venue"
},
  "geometry": {"coordinates":[-103.661709,30.375239],"type":"Point"}
}