{
  "type": "Feature",
  "properties": {
    "iso:country":"US",
    "sg:address":"2517 Hackberry Creek",
    "sg:city":"Mesquite",
    "sg:classifiers":[
        {
            "category":"Wholesale",
            "subcategory":"Vending Machines",
            "type":"Manufacturing & Wholesale Goods"
        }
    ],
    "sg:phone":"+1 972 222 9593",
    "sg:postcode":"75181",
    "sg:province":"TX",
    "sg:tags":[
        "operator"
    ],
    "wof:name":"Terry Vending",
    "wof:placetype":"venue"
},
  "geometry": {"coordinates":[-96.55896,32.75214],"type":"Point"}
}