{
  "type": "Feature",
  "properties": {
    "iso:country":"US",
    "sg:address":"4750 Frank Luke Dr",
    "sg:city":"Addison",
    "sg:classifiers":[
        {
            "category":"Mining & Drilling",
            "type":"Manufacturing & Wholesale Goods"
        }
    ],
    "sg:phone":"+1 972 931 3075",
    "sg:postcode":"75001",
    "sg:province":"TX",
    "sg:tags":[
        "oil",
        "gas",
        "producer"
    ],
    "wof:name":"Gopher Oil Co",
    "wof:placetype":"venue"
},
  "geometry": {"coordinates":[-96.83188800000001,32.973078],"type":"Point"}
}