{
  "type": "Feature",
  "properties": {
    "iso:country":"US",
    "sg:address":"10614 Sabo Rd",
    "sg:city":"Houston",
    "sg:classifiers":[
        {
            "category":"Social Services",
            "subcategory":"Child Care",
            "type":"Services"
        },
        {
            "category":"Education",
            "subcategory":"Preschool",
            "type":"Public Place"
        },
        {
            "category":"Education",
            "subcategory":"School",
            "type":"Public Place"
        }
    ],
    "sg:phone":"+1 713 941 6400",
    "sg:postcode":"77089",
    "sg:province":"TX",
    "sg:tags":[
        "elementary",
        "day"
    ],
    "wof:name":"Greenhouse Learning Center the",
    "wof:placetype":"venue"
},
  "geometry": {"coordinates":[-95.2276,29.6164],"type":"Point"}
}