{
  "type": "Feature",
  "properties": {
    "iso:country":"US",
    "sg:address":"1301 31st St N",
    "sg:city":"Texas City",
    "sg:classifiers":[
        {
            "category":"Restaurant",
            "type":"Food & Drink"
        }
    ],
    "sg:phone":"+1 409 945 6151",
    "sg:postcode":"77590",
    "sg:province":"TX",
    "sg:tags":[
        "seafood"
    ],
    "wof:name":"Reef Seafood House",
    "wof:placetype":"venue"
},
  "geometry": {"coordinates":[-94.940692,29.395504],"type":"Point"}
}