{
  "type": "Feature",
  "properties": {
    "iso:country":"US",
    "sg:address":"1301 Travis St",
    "sg:city":"Houston",
    "sg:classifiers":[
        {
            "category":"Banks & Credit Unions",
            "subcategory":"Bank",
            "type":"Services"
        }
    ],
    "sg:phone":"+1 713 751 0500",
    "sg:postcode":"77002",
    "sg:province":"TX",
    "sg:tags":[
        "commercial"
    ],
    "wof:name":"Credit Lyonnais",
    "wof:placetype":"venue"
},
  "geometry": {"coordinates":[-95.36816399999999,29.7545],"type":"Point"}
}