{
  "type": "Feature",
  "properties": {
    "iso:country":"US",
    "sg:address":"604 Green Meadows Ln",
    "sg:city":"Red Oak",
    "sg:classifiers":[
        {
            "category":"Shopping",
            "subcategory":"Crafts & Fabrics",
            "type":"Retail Goods"
        }
    ],
    "sg:phone":"+1 972 217 3471",
    "sg:postcode":"75154",
    "sg:province":"TX",
    "sg:tags":[
        "sewing"
    ],
    "wof:name":"Stitched With Love",
    "wof:placetype":"venue"
},
  "geometry": {"coordinates":[-96.900285,32.540332],"type":"Point"}
}