{
  "type": "Feature",
  "properties": {
    "iso:country":"US",
    "sg:address":"10963 Scarsdale Blvd",
    "sg:city":"Houston",
    "sg:classifiers":[
        {
            "category":"Shopping",
            "subcategory":"Antiques",
            "type":"Retail Goods"
        }
    ],
    "sg:phone":"+1 281 484 2017",
    "sg:postcode":"77089",
    "sg:province":"TX",
    "wof:name":"B & M Clock Repair",
    "wof:placetype":"venue"
},
  "geometry": {"coordinates":[-95.211502,29.5868],"type":"Point"}
}