{
  "type": "Feature",
  "properties": {
    "iso:country":"US",
    "sg:address":"7310 Doniphan Dr",
    "sg:city":"Canutillo",
    "sg:classifiers":[
        {
            "category":"Building & Trades",
            "subcategory":"Construction",
            "type":"Services"
        }
    ],
    "sg:phone":"+1 915 877 5407",
    "sg:postcode":"79835",
    "sg:province":"TX",
    "sg:tags":[
        "house"
    ],
    "wof:name":"Smithco Construction",
    "wof:placetype":"venue"
},
  "geometry": {"coordinates":[-106.601714,31.926164],"type":"Point"}
}