{
  "type": "Feature",
  "properties": {
    "iso:country":"US",
    "sg:address":"3921 Arbor Glen Way",
    "sg:city":"Austin",
    "sg:classifiers":[
        {
            "category":"Banks & Credit Unions",
            "subcategory":"Financial Services",
            "type":"Services"
        }
    ],
    "sg:phone":"+1 512 346 8808",
    "sg:postcode":"78731",
    "sg:province":"TX",
    "sg:tags":[
        "investor"
    ],
    "wof:name":"Woods General Investments LLC",
    "wof:placetype":"venue"
},
  "geometry": {"coordinates":[-97.755915,30.366657],"type":"Point"}
}