{
  "type": "Feature",
  "properties": {
    "iso:country":"US",
    "sg:address":"1 Mann Rd",
    "sg:city":"Forney",
    "sg:classifiers":[
        {
            "category":"Farming",
            "subcategory":"Livestock Farm",
            "type":"Manufacturing & Wholesale Goods"
        }
    ],
    "sg:phone":"+1 972 524 8852",
    "sg:postcode":"75126",
    "sg:province":"TX",
    "sg:tags":[
        "beef",
        "feedlot",
        "cattle"
    ],
    "wof:name":"Onemann Ranch",
    "wof:placetype":"venue"
},
  "geometry": {"coordinates":[-96.389538,32.802676],"type":"Point"}
}