{
  "type": "Feature",
  "properties": {
    "iso:country":"US",
    "sg:address":"23874 State Loop 494",
    "sg:city":"Porter",
    "sg:classifiers":[
        {
            "category":"Personal",
            "subcategory":"Beauty Salon",
            "type":"Services"
        }
    ],
    "sg:phone":"+1 281 354 8196",
    "sg:postcode":"77365",
    "sg:province":"TX",
    "sg:tags":[
        "shop"
    ],
    "wof:name":"Hair Port The",
    "wof:placetype":"venue"
},
  "geometry": {"coordinates":[-95.23043,30.100379],"type":"Point"}
}