{
  "type": "Feature",
  "properties": {
    "iso:country":"US",
    "sg:address":"3658 Bethel Rd",
    "sg:city":"Weatherford",
    "sg:classifiers":[
        {
            "category":"Farming",
            "subcategory":"Livestock Farm",
            "type":"Manufacturing & Wholesale Goods"
        }
    ],
    "sg:phone":"+1 817 598 0217",
    "sg:postcode":"76087",
    "sg:province":"TX",
    "sg:tags":[
        "beef",
        "feedlot",
        "animal",
        "cattle"
    ],
    "wof:name":"Bar H Ranch",
    "wof:placetype":"venue"
},
  "geometry": {"coordinates":[-97.831101,32.675119],"type":"Point"}
}