{
  "type": "Feature",
  "properties": {
    "iso:country":"US",
    "sg:address":"2601 Valley View Dr",
    "sg:city":"Denton",
    "sg:classifiers":[
        {
            "category":"Retail",
            "subcategory":"Repair Shop",
            "type":"Services"
        }
    ],
    "sg:phone":"+1 940 321 3734",
    "sg:postcode":"76210",
    "sg:province":"TX",
    "sg:tags":[
        "electrical",
        "merchandise"
    ],
    "wof:name":"A JS Electronics",
    "wof:placetype":"venue"
},
  "geometry": {"coordinates":[-97.068247,33.147195],"type":"Point"}
}