{
  "type": "Feature",
  "properties": {
    "iso:country":"US",
    "sg:address":"2014 Pleasanton Rd",
    "sg:city":"San Antonio",
    "sg:classifiers":[
        {
            "category":"Banks & Credit Unions",
            "subcategory":"Bank",
            "type":"Services"
        }
    ],
    "sg:phone":"+1 210 924 9051",
    "sg:postcode":"78221",
    "sg:province":"TX",
    "sg:tags":[
        "loan"
    ],
    "wof:name":"Security Finance Corp",
    "wof:placetype":"venue"
},
  "geometry": {"coordinates":[-98.503788,29.36096],"type":"Point"}
}