{
  "type": "Feature",
  "properties": {
    "iso:country":"US",
    "sg:address":"3248 Towerwood Dr",
    "sg:city":"Farmers Branch",
    "sg:classifiers":[
        {
            "category":"Wholesale",
            "subcategory":"Machinery & Supplies",
            "type":"Manufacturing & Wholesale Goods"
        }
    ],
    "sg:phone":"+1 972 247 8075",
    "sg:postcode":"75234",
    "sg:province":"TX",
    "sg:tags":[
        "industrial",
        "miscellaneous"
    ],
    "wof:name":"South Central Claridge",
    "wof:placetype":"venue"
},
  "geometry": {"coordinates":[-96.86646399999999,32.951458],"type":"Point"}
}