{
  "type": "Feature",
  "properties": {
    "iso:country":"US",
    "sg:address":"5704 Kelly Ct",
    "sg:city":"Fort Worth",
    "sg:classifiers":[
        {
            "category":"Professional",
            "subcategory":"Engineering",
            "type":"Services"
        }
    ],
    "sg:phone":"+1 817 313 3999",
    "sg:postcode":"76137",
    "sg:province":"TX",
    "wof:name":"Prisc Systems Inc",
    "wof:placetype":"venue"
},
  "geometry": {"coordinates":[-97.286424,32.849711],"type":"Point"}
}