{
  "type": "Feature",
  "properties": {
    "iso:country":"US",
    "sg:address":"404 SE 2nd St",
    "sg:city":"Seminole",
    "sg:classifiers":[
        {
            "category":"Shopping",
            "type":"Retail Goods"
        },
        {
            "category":"Shopping",
            "subcategory":"Beauty & Cosmetics",
            "type":"Retail Goods"
        }
    ],
    "sg:phone":"+1 432 758 2288",
    "sg:postcode":"79360",
    "sg:province":"TX",
    "sg:tags":[
        "merchandise",
        "perfume"
    ],
    "wof:name":"Heavenly Scents n Lotion",
    "wof:placetype":"venue"
},
  "geometry": {"coordinates":[-102.643861,32.715563],"type":"Point"}
}