{
  "type": "Feature",
  "properties": {
    "iso:country":"US",
    "sg:address":"5427 S Hulen St",
    "sg:city":"Fort Worth",
    "sg:classifiers":[
        {
            "category":"Shopping",
            "subcategory":"Computers & Home Electronics",
            "type":"Retail Goods"
        }
    ],
    "sg:phone":"+1 817 370 7170",
    "sg:postcode":"76132",
    "sg:province":"TX",
    "wof:name":"Gamestop 546",
    "wof:placetype":"venue"
},
  "geometry": {"coordinates":[-97.399947,32.669995],"type":"Point"}
}