{
  "type": "Feature",
  "properties": {
    "iso:country":"US",
    "sg:address":"4802 Cranbrook Dr E",
    "sg:city":"Colleyville",
    "sg:classifiers":[
        {
            "category":"Education",
            "subcategory":"Special Training",
            "type":"Public Place"
        }
    ],
    "sg:phone":"+1 817 540 6499",
    "sg:postcode":"76034",
    "sg:province":"TX",
    "wof:name":"Parents Coalition of Tex",
    "wof:placetype":"venue"
},
  "geometry": {"coordinates":[-97.137514,32.880817],"type":"Point"}
}