{
  "type": "Feature",
  "properties": {
    "iso:country":"US",
    "sg:address":"15510 River Bend",
    "sg:city":"San Antonio",
    "sg:classifiers":[
        {
            "category":"Wholesale",
            "subcategory":"Electrical",
            "type":"Manufacturing & Wholesale Goods"
        }
    ],
    "sg:phone":"+1 210 402 0605",
    "sg:postcode":"78247",
    "sg:province":"TX",
    "sg:tags":[
        "equipment"
    ],
    "wof:name":"Dielmann JW Inc",
    "wof:placetype":"venue"
},
  "geometry": {"coordinates":[-98.42762999999999,29.583342],"type":"Point"}
}