{
  "type": "Feature",
  "properties": {
    "iso:country":"US",
    "sg:address":"3509 Harvey St",
    "sg:city":"Mcallen",
    "sg:classifiers":[
        {
            "category":"Professional",
            "subcategory":"Art Services",
            "type":"Services"
        }
    ],
    "sg:phone":"+1 956 682 1168",
    "sg:postcode":"78501",
    "sg:province":"TX",
    "sg:tags":[
        "commercial",
        "design"
    ],
    "wof:name":"Ad Mart Specialty Advertising",
    "wof:placetype":"venue"
},
  "geometry": {"coordinates":[-98.25554700000001,26.232161],"type":"Point"}
}