{
  "type": "Feature",
  "properties": {
    "iso:country":"US",
    "sg:address":"2110 S Main St",
    "sg:city":"Vidor",
    "sg:classifiers":[
        {
            "category":"Organizations",
            "subcategory":"Community Association",
            "type":"Services"
        }
    ],
    "sg:phone":"+1 409 768 1482",
    "sg:postcode":"77662",
    "sg:province":"TX",
    "sg:tags":[
        "military"
    ],
    "wof:name":"Veterans Of Foreign Wars",
    "wof:placetype":"venue"
},
  "geometry": {"coordinates":[-94.00673399999999,30.102237],"type":"Point"}
}