{
  "type": "Feature",
  "properties": {
    "iso:country":"US",
    "sg:address":"5510 S I H 35",
    "sg:city":"Austin",
    "sg:classifiers":[
        {
            "category":"Health Services",
            "subcategory":"Optometrist",
            "type":"Services"
        }
    ],
    "sg:phone":"+1 512 693 2020",
    "sg:postcode":"78745",
    "sg:province":"TX",
    "wof:name":"Reed Optometry",
    "wof:placetype":"venue"
},
  "geometry": {"coordinates":[-97.76317400000001,30.200388],"type":"Point"}
}