{
  "type": "Feature",
  "properties": {
    "iso:country":"US",
    "sg:address":"8140 Esters Blvd",
    "sg:city":"Irving",
    "sg:classifiers":[
        {
            "category":"Restaurant",
            "type":"Food & Drink"
        }
    ],
    "sg:menulink":"http://www.allmenus.com/tx/southwest/11727-dennys/menu/",
    "sg:phone":"+1 972 929 4282",
    "sg:postcode":"75063",
    "sg:province":"TX",
    "sg:tags":[
        "american",
        "diner"
    ],
    "wof:name":"Denny's",
    "wof:placetype":"venue"
},
  "geometry": {"coordinates":[-97.007907,32.918303],"type":"Point"}
}