{
  "type": "Feature",
  "properties": {
    "iso:country":"US",
    "sg:address":"1600 S 6th St",
    "sg:city":"Kingsville",
    "sg:classifiers":[
        {
            "category":"Shopping",
            "subcategory":"Hobbies, Toys, & Games",
            "type":"Retail Goods"
        }
    ],
    "sg:phone":"+1 361 592 4003",
    "sg:postcode":"78363",
    "sg:province":"TX",
    "sg:tags":[
        "model",
        "supply"
    ],
    "wof:name":"Guidry's Hobbies",
    "wof:placetype":"venue"
},
  "geometry": {"coordinates":[-97.867805,27.501866],"type":"Point"}
}