{
  "type": "Feature",
  "properties": {
    "iso:country":"US",
    "sg:address":"5805 Lake Hubbard Pkwy",
    "sg:city":"Garland",
    "sg:classifiers":[
        {
            "category":"Professional",
            "subcategory":"Detective & Security Services",
            "type":"Services"
        }
    ],
    "sg:phone":"+1 972 226 4774",
    "sg:postcode":"75043",
    "sg:province":"TX",
    "sg:tags":[
        "guard",
        "patrol"
    ],
    "wof:name":"Hartford Security",
    "wof:placetype":"venue"
},
  "geometry": {"coordinates":[-96.546013,32.858521],"type":"Point"}
}