{
  "type": "Feature",
  "properties": {
    "iso:country":"US",
    "sg:address":"8731 Shoal Creek Blvd",
    "sg:city":"Austin",
    "sg:classifiers":[
        {
            "category":"Professional",
            "subcategory":"Lawyer & Legal Services",
            "type":"Services"
        }
    ],
    "sg:phone":"+1 512 217 2873",
    "sg:postcode":"78757",
    "sg:province":"TX",
    "sg:tags":[
        "attorney"
    ],
    "wof:name":"Elizabeth Cohen",
    "wof:placetype":"venue"
},
  "geometry": {"coordinates":[-97.735859,30.374624],"type":"Point"}
}