{
  "type": "Feature",
  "properties": {
    "iso:country":"US",
    "sg:address":"2601 Pine St",
    "sg:city":"Galveston",
    "sg:classifiers":[
        {
            "category":"Shopping",
            "subcategory":"Bicycles & Sporting Goods",
            "type":"Retail Goods"
        }
    ],
    "sg:phone":"+1 409 740 3241",
    "sg:postcode":"77551",
    "sg:province":"TX",
    "wof:name":"A Js Guns",
    "wof:placetype":"venue"
},
  "geometry": {"coordinates":[-94.840751,29.265109],"type":"Point"}
}