{
  "type": "Feature",
  "properties": {
    "iso:country":"US",
    "sg:address":"6500 Greenville Ave Ste 760",
    "sg:city":"Dallas",
    "sg:classifiers":[
        {
            "category":"Wholesale",
            "subcategory":"Medical Equipment & Supplies",
            "type":"Manufacturing & Wholesale Goods"
        },
        {
            "category":"Health Services",
            "subcategory":"Clinic",
            "type":"Services"
        },
        {
            "category":"Health Services",
            "subcategory":"Medical Lab",
            "type":"Services"
        },
        {
            "category":"Health Services",
            "subcategory":"Hospital",
            "type":"Services"
        },
        {
            "category":"Health Services",
            "subcategory":"Doctor",
            "type":"Services"
        },
        {
            "category":"Building & Trades",
            "subcategory":"Equipment Rental",
            "type":"Services"
        }
    ],
    "sg:phone":"+1 214 363 6611",
    "sg:postcode":"75206",
    "sg:province":"TX",
    "sg:tags":[
        "supplies-renting",
        "cardiologist",
        "outpatient",
        "imaging"
    ],
    "wof:name":"Cardiovascular On-Call Specialists Inc",
    "wof:placetype":"venue"
},
  "geometry": {"coordinates":[-96.767098,32.864084],"type":"Point"}
}