{
  "type": "Feature",
  "properties": {
    "iso:country":"US",
    "sg:address":"11695 Twin Deer Rd",
    "sg:city":"Conroe",
    "sg:classifiers":[
        {
            "category":"Professional",
            "subcategory":"Advertising",
            "type":"Services"
        }
    ],
    "sg:phone":"+1 281 465 9261",
    "sg:postcode":"77385",
    "sg:province":"TX",
    "wof:name":"Showpro",
    "wof:placetype":"venue"
},
  "geometry": {"coordinates":[-95.40350599999999,30.178691],"type":"Point"}
}