{
  "type": "Feature",
  "properties": {
    "iso:country":"US",
    "sg:address":"1928 N Conway Ave",
    "sg:city":"Mission",
    "sg:classifiers":[
        {
            "category":"Banks & Credit Unions",
            "subcategory":"Financial Services",
            "type":"Services"
        }
    ],
    "sg:phone":"+1 956 519 8009",
    "sg:postcode":"78572",
    "sg:province":"TX",
    "sg:tags":[
        "loan",
        "plan"
    ],
    "wof:name":"Tiempo Loans",
    "wof:placetype":"venue"
},
  "geometry": {"coordinates":[-98.32409699999999,26.225468],"type":"Point"}
}