{
  "type": "Feature",
  "properties": {
    "iso:country":"US",
    "sg:address":"3618 Nichols Ave",
    "sg:city":"Bay City",
    "sg:classifiers":[
        {
            "category":"Home & Garden",
            "subcategory":"Building Materials",
            "type":"Retail Goods"
        }
    ],
    "sg:phone":"+1 979 244 4851",
    "sg:postcode":"77414",
    "sg:province":"TX",
    "sg:tags":[
        "glass",
        "window",
        "plate"
    ],
    "sg:website":"www.cmautoglass.com",
    "wof:name":"C M Auto Glass",
    "wof:placetype":"venue"
},
  "geometry": {"coordinates":[-95.95302700000001,28.969395],"type":"Point"}
}