{
  "type": "Feature",
  "properties": {
    "iso:country":"US",
    "sg:address":"3629 Saratoga Pl",
    "sg:city":"Schertz",
    "sg:classifiers":[
        {
            "category":"Education",
            "subcategory":"Special Training",
            "type":"Public Place"
        }
    ],
    "sg:phone":"+1 210 566 6574",
    "sg:postcode":"78154",
    "sg:province":"TX",
    "wof:name":"Roadworthy Driving Academy",
    "wof:placetype":"venue"
},
  "geometry": {"coordinates":[-98.280636,29.582962],"type":"Point"}
}