{
  "type": "Feature",
  "properties": {
    "iso:country":"US",
    "sg:address":"2501 Biggs Dr",
    "sg:city":"Austin",
    "sg:classifiers":[
        {
            "category":"Retail",
            "subcategory":"Animal Services",
            "type":"Services"
        }
    ],
    "sg:phone":"+1 512 441 3890",
    "sg:postcode":"78741",
    "sg:province":"TX",
    "sg:tags":[
        "breeder",
        "labrador",
        "retriever"
    ],
    "wof:name":"Charisma Labradors",
    "wof:placetype":"venue"
},
  "geometry": {"coordinates":[-97.73786200000001,30.22882],"type":"Point"}
}