{
  "type": "Feature",
  "properties": {
    "iso:country":"US",
    "sg:address":"308 Robin Hood Dr",
    "sg:city":"Irving",
    "sg:classifiers":[
        {
            "category":"Personal",
            "subcategory":"Beauty Salon",
            "type":"Services"
        }
    ],
    "sg:phone":"+1 972 790 2333",
    "sg:postcode":"75061",
    "sg:province":"TX",
    "sg:tags":[
        "shop"
    ],
    "wof:name":"Skin Care By Laimi",
    "wof:placetype":"venue"
},
  "geometry": {"coordinates":[-96.981115,32.81959],"type":"Point"}
}