{
  "type": "Feature",
  "properties": {
    "iso:country":"US",
    "sg:address":"17480 W Grand Pkwy S",
    "sg:city":"Sugar Land",
    "sg:classifiers":[
        {
            "category":"Restaurant",
            "type":"Food & Drink"
        }
    ],
    "sg:menulink":"http://www.allmenus.com/tx/rosenberg-richmond/157467-whataburger/menu/",
    "sg:phone":"+1 281 232 5546",
    "sg:postcode":"77479",
    "sg:province":"TX",
    "sg:tags":[
        "burger",
        "american"
    ],
    "wof:name":"Whataburger",
    "wof:placetype":"venue"
},
  "geometry": {"coordinates":[-95.687652,29.563701],"type":"Point"}
}