{
  "type": "Feature",
  "properties": {
    "iso:country":"US",
    "sg:address":"417 E 11th St",
    "sg:city":"Brownsville",
    "sg:classifiers":[
        {
            "category":"Bars & Pubs",
            "type":"Food & Drink"
        }
    ],
    "sg:phone":"+1 956 542 9912",
    "sg:postcode":"78520",
    "sg:province":"TX",
    "sg:tags":[
        "drinking"
    ],
    "wof:name":"Barrell Lounge",
    "wof:placetype":"venue"
},
  "geometry": {"coordinates":[-97.49907399999999,25.901736],"type":"Point"}
}