{
  "type": "Feature",
  "properties": {
    "iso:country":"US",
    "sg:address":"5950 River Oaks Blvd",
    "sg:city":"Fort Worth",
    "sg:classifiers":[
        {
            "category":"Shopping",
            "subcategory":"Clothing, Apparel, & Fashions",
            "type":"Retail Goods"
        }
    ],
    "sg:phone":"+1 817 738 0087",
    "sg:postcode":"76114",
    "sg:province":"TX",
    "sg:tags":[
        "alteration"
    ],
    "wof:name":"Charlies Tailor Shop & Clng",
    "wof:placetype":"venue"
},
  "geometry": {"coordinates":[-97.40818299999999,32.766002],"type":"Point"}
}