{
  "type": "Feature",
  "properties": {
    "iso:country":"US",
    "sg:address":"14115 Gray Wing St",
    "sg:city":"San Antonio",
    "sg:classifiers":[
        {
            "category":"Home & Garden",
            "subcategory":"Building Materials",
            "type":"Retail Goods"
        }
    ],
    "sg:phone":"+1 210 492 3005",
    "sg:postcode":"78231",
    "sg:province":"TX",
    "sg:tags":[
        "glass",
        "leaded"
    ],
    "wof:name":"D K Young Co",
    "wof:placetype":"venue"
},
  "geometry": {"coordinates":[-98.53854699999999,29.5699],"type":"Point"}
}