{
  "type": "Feature",
  "properties": {
    "iso:country":"US",
    "sg:address":"12525 Texaco Rd",
    "sg:city":"Houston",
    "sg:classifiers":[
        {
            "category":"Retail",
            "subcategory":"Auto Repair",
            "type":"Services"
        }
    ],
    "sg:phone":"+1 713 451 3571",
    "sg:postcode":"77013",
    "sg:province":"TX",
    "sg:tags":[
        "truck"
    ],
    "wof:name":"D & S Diesel",
    "wof:placetype":"venue"
},
  "geometry": {"coordinates":[-95.217724,29.799752],"type":"Point"}
}