{
  "type": "Feature",
  "properties": {
    "iso:country":"US",
    "sg:address":"909 W 7th St",
    "sg:city":"Justin",
    "sg:classifiers":[
        {
            "category":"Real Estate",
            "subcategory":"Real Estate Services",
            "type":"Services"
        },
        {
            "category":"Real Estate",
            "subcategory":"Real Estate Operator",
            "type":"Services"
        }
    ],
    "sg:phone":"+1 940 648 3296",
    "sg:postcode":"76247",
    "sg:province":"TX",
    "sg:tags":[
        "vacancy",
        "apartment",
        "rental",
        "finder",
        "listing"
    ],
    "wof:name":"Luety Ave Apt",
    "wof:placetype":"venue"
},
  "geometry": {"coordinates":[-97.30520799999999,33.090561],"type":"Point"}
}