{
  "type": "Feature",
  "properties": {
    "iso:country":"US",
    "sg:address":"2409 Co Rd 7130",
    "sg:city":"Lubbock",
    "sg:classifiers":[
        {
            "category":"Recreation",
            "type":"Entertainment"
        }
    ],
    "sg:phone":"+1 806 745 4070",
    "sg:postcode":"79404",
    "sg:province":"TX",
    "wof:name":"LA Carreta Pool Hall",
    "wof:placetype":"venue"
},
  "geometry": {"coordinates":[-101.816875,33.514267],"type":"Point"}
}