{
  "type": "Feature",
  "properties": {
    "iso:country":"US",
    "sg:address":"1409 24th St",
    "sg:city":"Lubbock",
    "sg:classifiers":[
        {
            "category":"Social Services",
            "subcategory":"Adult Care",
            "type":"Services"
        }
    ],
    "sg:phone":"+1 806 749 3640",
    "sg:postcode":"79411",
    "sg:province":"TX",
    "sg:tags":[
        "residential"
    ],
    "wof:name":"Imani House",
    "wof:placetype":"venue"
},
  "geometry": {"coordinates":[-101.85086800000001,33.573168],"type":"Point"}
}