{
  "type": "Feature",
  "properties": {
    "iso:country":"US",
    "sg:address":"7453 Las Colinas Blvd",
    "sg:city":"Irving",
    "sg:classifiers":[
        {
            "category":"Health Services",
            "subcategory":"Hospital",
            "type":"Services"
        },
        {
            "category":"Social Services",
            "subcategory":"Child Care",
            "type":"Services"
        }
    ],
    "sg:phone":"+1 972 444 0884",
    "sg:postcode":"75063",
    "sg:province":"TX",
    "sg:tags":[
        "day"
    ],
    "wof:name":"Our Children's House",
    "wof:placetype":"venue"
},
  "geometry": {"coordinates":[-96.954376,32.909346],"type":"Point"}
}