{
  "type": "Feature",
  "properties": {
    "iso:country":"US",
    "sg:address":"1219 Jacoby Ln",
    "sg:city":"Aransas Pass",
    "sg:classifiers":[
        {
            "category":"Wholesale",
            "subcategory":"Home Furnishings",
            "type":"Manufacturing & Wholesale Goods"
        }
    ],
    "sg:phone":"+1 361 758 8627",
    "sg:postcode":"78336",
    "sg:province":"TX",
    "wof:name":"Prissy Patch",
    "wof:placetype":"venue"
},
  "geometry": {"coordinates":[-97.145493,27.938244],"type":"Point"}
}