{
  "type": "Feature",
  "properties": {
    "iso:country":"US",
    "sg:address":"6380 Phelan Blvd",
    "sg:city":"Beaumont",
    "sg:classifiers":[
        {
            "category":"Restaurant",
            "type":"Food & Drink"
        }
    ],
    "sg:menulink":"http://www.allmenus.com/tx/beaumont/202144-mcdonalds/menu/",
    "sg:postcode":"77706",
    "sg:province":"TX",
    "sg:tags":[
        "burger",
        "american"
    ],
    "wof:name":"McDonald's",
    "wof:placetype":"venue"
},
  "geometry": {"coordinates":[-94.163301,30.080514],"type":"Point"}
}