{
  "type": "Feature",
  "properties": {
    "iso:country":"US",
    "sg:address":"400 Trice St",
    "sg:city":"Claude",
    "sg:classifiers":[
        {
            "category":"Organizations",
            "subcategory":"Religious Organization",
            "type":"Services"
        }
    ],
    "sg:phone":"+1 806 226 2061",
    "sg:postcode":"79019",
    "sg:province":"TX",
    "sg:tags":[
        "place",
        "worship",
        "church"
    ],
    "sg:website":"http://www.umc.org",
    "wof:name":"United Methodist Church",
    "wof:placetype":"venue"
},
  "geometry": {"coordinates":[-101.36086299999999,35.10714],"type":"Point"}
}