{
  "type": "Feature",
  "properties": {
    "iso:country":"US",
    "sg:address":"1324 E 10th St",
    "sg:city":"Colorado City",
    "sg:classifiers":[
        {
            "category":"Real Estate",
            "subcategory":"Real Estate Operator",
            "type":"Services"
        }
    ],
    "sg:phone":"+1 325 728 2347",
    "sg:postcode":"79512",
    "sg:province":"TX",
    "sg:tags":[
        "apartment"
    ],
    "wof:name":"Colorado City Seniors Apts",
    "wof:placetype":"venue"
},
  "geometry": {"coordinates":[-100.845584,32.402436],"type":"Point"}
}