{
  "type": "Feature",
  "properties": {
    "iso:country":"US",
    "sg:address":"302 Almeda-Genoa Rd",
    "sg:city":"Houston",
    "sg:classifiers":[
        {
            "category":"Building & Trades",
            "subcategory":"Cleaning & Sanitation",
            "type":"Services"
        }
    ],
    "sg:phone":"+1 713 433 0348",
    "sg:postcode":"77047",
    "sg:province":"TX",
    "sg:tags":[
        "janitor"
    ],
    "wof:name":"Clean Sweep Building Mntnc Inc",
    "wof:placetype":"venue"
},
  "geometry": {"coordinates":[-95.41557,29.613674],"type":"Point"}
}