{
  "type": "Feature",
  "properties": {
    "iso:country":"US",
    "sg:address":"808 Legion Ave",
    "sg:city":"Cleveland",
    "sg:classifiers":[
        {
            "category":"Real Estate",
            "subcategory":"Real Estate Operator",
            "type":"Services"
        }
    ],
    "sg:phone":"+1 281 592 3800",
    "sg:postcode":"77327",
    "sg:province":"TX",
    "sg:tags":[
        "apartment"
    ],
    "wof:name":"Brook Hollow Apartments",
    "wof:placetype":"venue"
},
  "geometry": {"coordinates":[-95.070784,30.335243],"type":"Point"}
}