{
  "type": "Feature",
  "properties": {
    "iso:country":"US",
    "sg:address":"10315 Colony Ct",
    "sg:city":"Houston",
    "sg:classifiers":[
        {
            "category":"Social Services",
            "type":"Services"
        }
    ],
    "sg:phone":"+1 713 849 9315",
    "sg:postcode":"77041",
    "sg:province":"TX",
    "wof:name":"Born To Succeed Daycare",
    "wof:placetype":"venue"
},
  "geometry": {"coordinates":[-95.548917,29.833628],"type":"Point"}
}