{
  "type": "Feature",
  "properties": {
    "iso:country":"US",
    "sg:address":"1205 E Hillside Rd",
    "sg:city":"Laredo",
    "sg:classifiers":[
        {
            "category":"Real Estate",
            "subcategory":"Real Estate Operator",
            "type":"Services"
        }
    ],
    "sg:phone":"+1 956 724 8510",
    "sg:postcode":"78041",
    "sg:province":"TX",
    "sg:tags":[
        "building",
        "nonresidential"
    ],
    "wof:name":"Vise Oakwell LC",
    "wof:placetype":"venue"
},
  "geometry": {"coordinates":[-99.482968,27.544859],"type":"Point"}
}