{
  "type": "Feature",
  "properties": {
    "iso:country":"US",
    "sg:address":"11824 Jollyville Rd",
    "sg:city":"Austin",
    "sg:classifiers":[
        {
            "category":"Professional",
            "subcategory":"Management & Consulting",
            "type":"Services"
        }
    ],
    "sg:phone":"+1 512 250 2422",
    "sg:postcode":"78759",
    "sg:province":"TX",
    "sg:tags":[
        "consultant"
    ],
    "wof:name":"Lakota Search Consultants",
    "wof:placetype":"venue"
},
  "geometry": {"coordinates":[-97.756877,30.424056],"type":"Point"}
}