{
  "type": "Feature",
  "properties": {
    "iso:country":"US",
    "sg:address":"909 State Hwy 323 SE",
    "sg:city":"Tyler",
    "sg:classifiers":[
        {
            "category":"Government",
            "subcategory":"Police Station",
            "type":"Public Place"
        }
    ],
    "sg:phone":"+1 903 579 2400",
    "sg:postcode":"75701",
    "sg:province":"TX",
    "sg:tags":[
        "federal"
    ],
    "wof:name":"US Drug Enforcement Adm",
    "wof:placetype":"venue"
},
  "geometry": {"coordinates":[-95.26705699999999,32.337618],"type":"Point"}
}