{
  "type": "Feature",
  "properties": {
    "iso:country":"US",
    "sg:address":"17595 FM 1485",
    "sg:city":"New Caney",
    "sg:classifiers":[
        {
            "category":"Autos & Motor Vehicles",
            "subcategory":"Automobile Sales",
            "type":"Retail Goods"
        }
    ],
    "sg:phone":"+1 281 572 2100",
    "sg:postcode":"77357",
    "sg:province":"TX",
    "sg:tags":[
        "used"
    ],
    "wof:name":"Hott Cars Enterprise",
    "wof:placetype":"venue"
},
  "geometry": {"coordinates":[-95.25191700000001,30.192872],"type":"Point"}
}