{
  "type": "Feature",
  "properties": {
    "iso:country":"US",
    "sg:address":"9600 Braes Bayou Dr Apt 75",
    "sg:city":"Houston",
    "sg:classifiers":[
        {
            "category":"Real Estate",
            "subcategory":"Real Estate Operator",
            "type":"Services"
        }
    ],
    "sg:phone":"+1 713 774 6301",
    "sg:postcode":"77074",
    "sg:province":"TX",
    "sg:tags":[
        "apartment"
    ],
    "wof:name":"Braeburn Villa Apartments",
    "wof:placetype":"venue"
},
  "geometry": {"coordinates":[-95.516098,29.6747],"type":"Point"}
}