{
  "type": "Feature",
  "properties": {
    "iso:country":"US",
    "sg:address":"414 S Minnesota Ave",
    "sg:city":"Brownsville",
    "sg:classifiers":[
        {
            "category":"Government",
            "subcategory":"Office",
            "type":"Public Place"
        }
    ],
    "sg:phone":"+1 956 546 5135",
    "sg:postcode":"78521",
    "sg:province":"TX",
    "sg:tags":[
        "state",
        "program"
    ],
    "wof:name":"Agriculture Dept",
    "wof:placetype":"venue"
},
  "geometry": {"coordinates":[-97.43219000000001,25.909809],"type":"Point"}
}