{
  "type": "Feature",
  "properties": {
    "iso:country":"US",
    "sg:address":"1701 N Broadway St",
    "sg:city":"Ballinger",
    "sg:classifiers":[
        {
            "category":"Organizations",
            "subcategory":"Religious Organization",
            "type":"Services"
        }
    ],
    "sg:phone":"+1 325 469 3356",
    "sg:postcode":"76821",
    "sg:province":"TX",
    "wof:name":"Bethel Lutheran Church",
    "wof:placetype":"venue"
},
  "geometry": {"coordinates":[-99.963769,31.749556],"type":"Point"}
}