{
  "type": "Feature",
  "properties": {
    "iso:country":"US",
    "sg:address":"2911 Lemmontree Ln",
    "sg:city":"Plano",
    "sg:classifiers":[
        {
            "category":"Building & Trades",
            "subcategory":"Construction",
            "type":"Services"
        }
    ],
    "sg:phone":"+1 972 422 5343",
    "sg:postcode":"75074",
    "sg:province":"TX",
    "sg:tags":[
        "house"
    ],
    "wof:name":"CP Construction",
    "wof:placetype":"venue"
},
  "geometry": {"coordinates":[-96.671019,33.032883],"type":"Point"}
}