{
  "type": "Feature",
  "properties": {
    "iso:country":"US",
    "sg:address":"2510 FM 1960 W",
    "sg:city":"Houston",
    "sg:classifiers":[
        {
            "category":"Freight",
            "type":"Transportation"
        }
    ],
    "sg:phone":"+1 281 444 1693",
    "sg:postcode":"77068",
    "sg:province":"TX",
    "sg:tags":[
        "warehouse",
        "storage",
        "public"
    ],
    "wof:name":"Public Storage Inc",
    "wof:placetype":"venue"
},
  "geometry": {"coordinates":[-95.478039,29.999043],"type":"Point"}
}