{
  "type": "Feature",
  "properties": {
    "iso:country":"US",
    "sg:address":"3453 Picadilly Ln",
    "sg:city":"Corpus Christi",
    "sg:classifiers":[
        {
            "category":"Shopping",
            "subcategory":"Books",
            "type":"Retail Goods"
        }
    ],
    "sg:phone":"+1 361 985 8326",
    "sg:postcode":"78414",
    "sg:province":"TX",
    "wof:name":"Jeds Good Books",
    "wof:placetype":"venue"
},
  "geometry": {"coordinates":[-97.375731,27.673117],"type":"Point"}
}