{
  "type": "Feature",
  "properties": {
    "iso:country":"US",
    "sg:address":"3000 Wilcrest Dr",
    "sg:city":"Houston",
    "sg:classifiers":[
        {
            "category":"Mining & Drilling",
            "type":"Manufacturing & Wholesale Goods"
        }
    ],
    "sg:phone":"+1 713 781 3200",
    "sg:postcode":"77042",
    "sg:province":"TX",
    "sg:tags":[
        "crude",
        "exploration",
        "ga"
    ],
    "wof:name":"Dixie Exploration Inc",
    "wof:placetype":"venue"
},
  "geometry": {"coordinates":[-95.57177,29.731655],"type":"Point"}
}