{
  "type": "Feature",
  "properties": {
    "iso:country":"US",
    "sg:address":"12000 W Little York Rd",
    "sg:city":"Houston",
    "sg:classifiers":[
        {
            "category":"Wholesale",
            "subcategory":"Machinery & Supplies",
            "type":"Manufacturing & Wholesale Goods"
        }
    ],
    "sg:phone":"+1 713 466 7999",
    "sg:postcode":"77041",
    "sg:province":"TX",
    "sg:tags":[
        "field",
        "oil"
    ],
    "sg:website":"www.natoil.com",
    "wof:name":"National-Oilwell Varco",
    "wof:placetype":"venue"
},
  "geometry": {"coordinates":[-95.58148199999999,29.867091],"type":"Point"}
}