{
  "type": "Feature",
  "properties": {
    "iso:country":"US",
    "sg:address":"11401 Gateway Blvd W",
    "sg:city":"El Paso",
    "sg:classifiers":[
        {
            "category":"Shopping",
            "subcategory":"Shoes",
            "type":"Retail Goods"
        }
    ],
    "sg:phone":"+1 915 593 2929",
    "sg:postcode":"79936",
    "sg:province":"TX",
    "sg:tags":[
        "boot"
    ],
    "sg:website":"www.cowtownboots.com",
    "wof:name":"Cowtown Boot Co",
    "wof:placetype":"venue"
},
  "geometry": {"coordinates":[-106.323804,31.739451],"type":"Point"}
}