{
  "type": "Feature",
  "properties": {
    "iso:country":"US",
    "sg:address":"1631 Purgatory Pass",
    "sg:city":"Lewisville",
    "sg:classifiers":[
        {
            "category":"Banks & Credit Unions",
            "subcategory":"Bank",
            "type":"Services"
        }
    ],
    "sg:phone":"+1 972 317 3064",
    "sg:postcode":"75077",
    "sg:province":"TX",
    "sg:tags":[
        "mortgage"
    ],
    "wof:name":"Anita Ishee Mortgage LLC",
    "wof:placetype":"venue"
},
  "geometry": {"coordinates":[-97.042936,33.081147],"type":"Point"}
}