{
  "type": "Feature",
  "properties": {
    "iso:country":"US",
    "sg:address":"105 Riverside Dr",
    "sg:city":"El Paso",
    "sg:classifiers":[
        {
            "category":"Home & Garden",
            "subcategory":"Building Materials",
            "type":"Retail Goods"
        },
        {
            "category":"Retail",
            "subcategory":"Auto Repair",
            "type":"Services"
        }
    ],
    "sg:phone":"+1 915 772 0231",
    "sg:postcode":"79915",
    "sg:province":"TX",
    "sg:tags":[
        "glass",
        "window",
        "plate",
        "replacement"
    ],
    "wof:name":"Mario's Auto Glass",
    "wof:placetype":"venue"
},
  "geometry": {"coordinates":[-106.363814,31.727734],"type":"Point"}
}