{
  "type": "Feature",
  "properties": {
    "iso:country":"US",
    "sg:address":"203 Shiloh Dr",
    "sg:city":"Richmond",
    "sg:classifiers":[
        {
            "category":"Building & Trades",
            "subcategory":"Construction",
            "type":"Services"
        }
    ],
    "sg:phone":"+1 281 343 7593",
    "sg:postcode":"77469",
    "sg:province":"TX",
    "sg:tags":[
        "hanging",
        "contractor"
    ],
    "wof:name":"Perfect Painting & More",
    "wof:placetype":"venue"
},
  "geometry": {"coordinates":[-95.69671,29.538759],"type":"Point"}
}