{
  "type": "Feature",
  "properties": {
    "iso:country":"US",
    "sg:address":"8440 Easton Commons Dr",
    "sg:city":"Houston",
    "sg:classifiers":[
        {
            "category":"Freight",
            "type":"Transportation"
        }
    ],
    "sg:phone":"+1 281 550 7016",
    "sg:postcode":"77095",
    "sg:province":"TX",
    "sg:tags":[
        "operator",
        "local",
        "trucking"
    ],
    "wof:name":"Quick Pickup Service",
    "wof:placetype":"venue"
},
  "geometry": {"coordinates":[-95.629712,29.899265],"type":"Point"}
}