{
  "type": "Feature",
  "properties": {
    "iso:country":"US",
    "sg:address":"703 E Hwy 67",
    "sg:city":"Duncanville",
    "sg:classifiers":[
        {
            "category":"Building & Trades",
            "subcategory":"Pest Control",
            "type":"Services"
        }
    ],
    "sg:phone":"+1 972 572 8785",
    "sg:postcode":"75137",
    "sg:province":"TX",
    "wof:name":"Auto Accessory Shop",
    "wof:placetype":"venue"
},
  "geometry": {"coordinates":[-96.89418999999999,32.639099],"type":"Point"}
}