{
  "type": "Feature",
  "properties": {
    "iso:country":"US",
    "sg:address":"1220 E Davis St",
    "sg:city":"Mesquite",
    "sg:classifiers":[
        {
            "category":"Autos & Motor Vehicles",
            "subcategory":"Fuel & Gas Station",
            "type":"Retail Goods"
        }
    ],
    "sg:phone":"+1 972 288 9673",
    "sg:postcode":"75149",
    "sg:province":"TX",
    "sg:tags":[
        "grocery",
        "gasoline"
    ],
    "wof:name":"One Stop Shoppe",
    "wof:placetype":"venue"
},
  "geometry": {"coordinates":[-96.583099,32.764099],"type":"Point"}
}