{
  "type": "Feature",
  "properties": {
    "iso:country":"US",
    "sg:address":"505 Fort Worth Dr",
    "sg:city":"Denton",
    "sg:classifiers":[
        {
            "category":"Manufacturing",
            "subcategory":"Rubber & Plastics",
            "type":"Manufacturing & Wholesale Goods"
        }
    ],
    "sg:phone":"+1 940 320 1046",
    "sg:postcode":"76201",
    "sg:province":"TX",
    "sg:tags":[
        "roofing",
        "mfg",
        "system",
        "membrane"
    ],
    "wof:name":"Single Source Roofing Corp",
    "wof:placetype":"venue"
},
  "geometry": {"coordinates":[-97.136416,33.201507],"type":"Point"}
}