{
  "type": "Feature",
  "properties": {
    "iso:country":"US",
    "sg:address":"305 W Garland St",
    "sg:city":"Grand Saline",
    "sg:classifiers":[
        {
            "category":"Wholesale",
            "subcategory":"Auto Parts",
            "type":"Manufacturing & Wholesale Goods"
        }
    ],
    "sg:phone":"+1 903 962 4915",
    "sg:postcode":"75140",
    "sg:province":"TX",
    "sg:tags":[
        "automobile",
        "rebuilt"
    ],
    "wof:name":"Mallam's Salvage Yard",
    "wof:placetype":"venue"
},
  "geometry": {"coordinates":[-95.71181199999999,32.674504],"type":"Point"}
}