{
  "type": "Feature",
  "properties": {
    "iso:country":"US",
    "sg:address":"6535 Southwest Fwy",
    "sg:city":"Houston",
    "sg:classifiers":[
        {
            "category":"Health Services",
            "subcategory":"Doctor",
            "type":"Services"
        },
        {
            "category":"Health Services",
            "subcategory":"Chiropractor",
            "type":"Services"
        }
    ],
    "sg:phone":"+1 713 981 8184",
    "sg:postcode":"77074",
    "sg:province":"TX",
    "wof:name":"Doctors Clinic Physico Chiropractic",
    "wof:placetype":"venue"
},
  "geometry": {"coordinates":[-95.497902,29.7183],"type":"Point"}
}