{
  "type": "Feature",
  "properties": {
    "iso:country":"US",
    "sg:address":"1031 Patricia Dr",
    "sg:city":"San Antonio",
    "sg:classifiers":[
        {
            "category":"Bars & Pubs",
            "type":"Food & Drink"
        }
    ],
    "sg:phone":"+1 210 342 4272",
    "sg:postcode":"78213",
    "sg:province":"TX",
    "sg:tags":[
        "club",
        "night"
    ],
    "wof:name":"Iguana Bay Bar & Grill",
    "wof:placetype":"venue"
},
  "geometry": {"coordinates":[-98.51151900000001,29.54455],"type":"Point"}
}