{
  "type": "Feature",
  "properties": {
    "iso:country":"US",
    "sg:address":"11341 Harry Hines Blvd",
    "sg:city":"Dallas",
    "sg:classifiers":[
        {
            "category":"Professional",
            "type":"Services"
        }
    ],
    "sg:phone":"+1 972 488 1938",
    "sg:postcode":"75229",
    "sg:province":"TX",
    "sg:tags":[
        "establishment"
    ],
    "wof:name":"Eden Casuals",
    "wof:placetype":"venue"
},
  "geometry": {"coordinates":[-96.89043700000001,32.893072],"type":"Point"}
}