{
  "type": "Feature",
  "properties": {
    "iso:country":"US",
    "sg:address":"127 Clover Meadow Ln",
    "sg:city":"Coppell",
    "sg:classifiers":[
        {
            "category":"Professional",
            "subcategory":"Management & Consulting",
            "type":"Services"
        }
    ],
    "sg:phone":"+1 972 393 5936",
    "sg:postcode":"75019",
    "sg:province":"TX",
    "sg:tags":[
        "business"
    ],
    "wof:name":"McCoy Consulting",
    "wof:placetype":"venue"
},
  "geometry": {"coordinates":[-96.99616399999999,32.973482],"type":"Point"}
}