{
  "type": "Feature",
  "properties": {
    "iso:country":"US",
    "sg:address":"824 S Staples St",
    "sg:city":"Corpus Christi",
    "sg:classifiers":[
        {
            "category":"Wholesale",
            "subcategory":"Medical Equipment & Supplies",
            "type":"Manufacturing & Wholesale Goods"
        }
    ],
    "sg:phone":"+1 361 883 2381",
    "sg:postcode":"78404",
    "sg:province":"TX",
    "sg:tags":[
        "repair"
    ],
    "wof:name":"A & V X-Ray Co",
    "wof:placetype":"venue"
},
  "geometry": {"coordinates":[-97.401876,27.783671],"type":"Point"}
}