{
  "type": "Feature",
  "properties": {
    "iso:country":"US",
    "sg:address":"300 E John Carpenter Fwy",
    "sg:city":"Irving",
    "sg:classifiers":[
        {
            "category":"Professional",
            "type":"Services"
        }
    ],
    "sg:phone":"+1 817 931 3071",
    "sg:postcode":"75062",
    "sg:province":"TX",
    "wof:name":"Cargo Services Inc",
    "wof:placetype":"venue"
},
  "geometry": {"coordinates":[-96.935244,32.859263],"type":"Point"}
}