{
  "type": "Feature",
  "properties": {
    "iso:country":"US",
    "sg:address":"3102 Tilson Ln",
    "sg:city":"Houston",
    "sg:classifiers":[
        {
            "category":"Shopping",
            "subcategory":"Hobbies, Toys, & Games",
            "type":"Retail Goods"
        }
    ],
    "sg:phone":"+1 713 984 0405",
    "sg:postcode":"77080",
    "sg:province":"TX",
    "wof:name":"Just Three More Stitches",
    "wof:placetype":"venue"
},
  "geometry": {"coordinates":[-95.517369,29.8229],"type":"Point"}
}