{
  "type": "Feature",
  "properties": {
    "iso:country":"US",
    "sg:address":"6635 Brittmoore Rd",
    "sg:city":"Houston",
    "sg:classifiers":[
        {
            "category":"Restaurant",
            "type":"Food & Drink"
        }
    ],
    "sg:phone":"+1 713 856 6420",
    "sg:postcode":"77041",
    "sg:province":"TX",
    "sg:tags":[
        "eating"
    ],
    "wof:name":"J and K Chinese Fast Food",
    "wof:placetype":"venue"
},
  "geometry": {"coordinates":[-95.56929700000001,29.865744],"type":"Point"}
}