{
  "type": "Feature",
  "properties": {
    "iso:country":"US",
    "sg:address":"10497 Town and Country Way",
    "sg:city":"Houston",
    "sg:classifiers":[
        {
            "category":"Insurance",
            "subcategory":"Insurance Agent",
            "type":"Services"
        }
    ],
    "sg:phone":"+1 713 461 4522",
    "sg:postcode":"77024",
    "sg:province":"TX",
    "wof:name":"ORear Cherie",
    "wof:placetype":"venue"
},
  "geometry": {"coordinates":[-95.555246,29.781337],"type":"Point"}
}