{
  "type": "Feature",
  "properties": {
    "iso:country":"US",
    "sg:address":"1106 E Durango Blvd",
    "sg:city":"San Antonio",
    "sg:classifiers":[
        {
            "category":"Manufacturing",
            "subcategory":"Food",
            "type":"Manufacturing & Wholesale Goods"
        }
    ],
    "sg:phone":"+1 210 532 3232",
    "sg:postcode":"78210",
    "sg:province":"TX",
    "sg:tags":[
        "ice",
        "mfg"
    ],
    "wof:name":"Mission Ice",
    "wof:placetype":"venue"
},
  "geometry": {"coordinates":[-98.478015,29.412685],"type":"Point"}
}