{
  "type": "Feature",
  "properties": {
    "iso:country":"US",
    "sg:address":"10034 Westview Dr",
    "sg:city":"Houston",
    "sg:classifiers":[
        {
            "category":"Shopping",
            "subcategory":"Used Merchandise",
            "type":"Retail Goods"
        }
    ],
    "sg:phone":"+1 713 461 6482",
    "sg:postcode":"77055",
    "sg:province":"TX",
    "wof:name":"T T Trends",
    "wof:placetype":"venue"
},
  "geometry": {"coordinates":[-95.54324,29.790913],"type":"Point"}
}