{
  "type": "Feature",
  "properties": {
    "iso:country":"US",
    "sg:address":"6411 University Ave",
    "sg:city":"Lubbock",
    "sg:classifiers":[
        {
            "category":"Shopping",
            "subcategory":"Tobacco",
            "type":"Retail Goods"
        }
    ],
    "sg:phone":"+1 806 797 9612",
    "sg:postcode":"79413",
    "sg:province":"TX",
    "sg:tags":[
        "cigarette",
        "cigar",
        "dealer"
    ],
    "wof:name":"Smokin J's No 6",
    "wof:placetype":"venue"
},
  "geometry": {"coordinates":[-101.87033700000001,33.534351],"type":"Point"}
}