{
  "type": "Feature",
  "properties": {
    "iso:country":"US",
    "sg:address":"904 Libold Dr",
    "sg:city":"Devine",
    "sg:classifiers":[
        {
            "category":"Professional",
            "type":"Services"
        }
    ],
    "sg:phone":"+1 830 665 5668",
    "sg:postcode":"78016",
    "sg:province":"TX",
    "wof:name":"Als Services",
    "wof:placetype":"venue"
},
  "geometry": {"coordinates":[-98.904253,29.150584],"type":"Point"}
}