{
  "type": "Feature",
  "properties": {
    "iso:country":"US",
    "sg:address":"604 Ashleman St",
    "sg:city":"Waco",
    "sg:classifiers":[
        {
            "category":"Restaurant",
            "type":"Food & Drink"
        }
    ],
    "sg:phone":"+1 254 799 4300",
    "sg:postcode":"76705",
    "sg:province":"TX",
    "sg:tags":[
        "eating"
    ],
    "wof:name":"Taqueria Zacatecaz",
    "wof:placetype":"venue"
},
  "geometry": {"coordinates":[-97.098654,31.589224],"type":"Point"}
}