{
  "type": "Feature",
  "properties": {
    "iso:country":"US",
    "sg:address":"5800 Corporate Dr",
    "sg:city":"Houston",
    "sg:classifiers":[
        {
            "category":"Wholesale",
            "subcategory":"Computers",
            "type":"Manufacturing & Wholesale Goods"
        }
    ],
    "sg:phone":"+1 713 779 2888",
    "sg:postcode":"77036",
    "sg:province":"TX",
    "wof:name":"HCI Computers",
    "wof:placetype":"venue"
},
  "geometry": {"coordinates":[-95.55158900000001,29.715581],"type":"Point"}
}