{
  "type": "Feature",
  "properties": {
    "iso:country":"US",
    "sg:address":"111 E Houston St",
    "sg:city":"George West",
    "sg:classifiers":[
        {
            "category":"Personal",
            "subcategory":"Beauty Salon",
            "type":"Services"
        }
    ],
    "sg:phone":"+1 361 449 1462",
    "sg:postcode":"78022",
    "sg:province":"TX",
    "wof:name":"Hair Designs",
    "wof:placetype":"venue"
},
  "geometry": {"coordinates":[-98.11111099999999,28.336531],"type":"Point"}
}