{
  "type": "Feature",
  "properties": {
    "iso:country":"US",
    "sg:address":"906 N Bend Dr",
    "sg:city":"Austin",
    "sg:classifiers":[
        {
            "category":"Professional",
            "subcategory":"Computer Services",
            "type":"Services"
        }
    ],
    "sg:phone":"+1 512 835 5297",
    "sg:postcode":"78758",
    "sg:province":"TX",
    "sg:tags":[
        "consultant",
        "designer",
        "systems-consultants",
        "system",
        "data"
    ],
    "wof:name":"Eddie Pederson",
    "wof:placetype":"venue"
},
  "geometry": {"coordinates":[-97.68737,30.38554],"type":"Point"}
}