{
  "type": "Feature",
  "properties": {
    "iso:country":"US",
    "sg:address":"5915 Louetta Rd",
    "sg:city":"Spring",
    "sg:classifiers":[
        {
            "category":"Personal",
            "subcategory":"Beauty Salon",
            "type":"Services"
        }
    ],
    "sg:phone":"+1 281 376 7388",
    "sg:postcode":"77379",
    "sg:province":"TX",
    "sg:tags":[
        "shop"
    ],
    "wof:name":"Beverly Wedgeman",
    "wof:placetype":"venue"
},
  "geometry": {"coordinates":[-95.505715,30.030835],"type":"Point"}
}