{
  "type": "Feature",
  "properties": {
    "iso:country":"US",
    "sg:address":"5949 Ingram Rd",
    "sg:city":"San Antonio",
    "sg:classifiers":[
        {
            "category":"Real Estate",
            "subcategory":"Real Estate Operator",
            "type":"Services"
        }
    ],
    "sg:phone":"+1 210 432 6565",
    "sg:postcode":"78228",
    "sg:province":"TX",
    "sg:tags":[
        "apartment"
    ],
    "wof:name":"Taurino's Cafe",
    "wof:placetype":"venue"
},
  "geometry": {"coordinates":[-98.600071,29.465926],"type":"Point"}
}