{
  "type": "Feature",
  "properties": {
    "iso:country":"US",
    "sg:address":"2018 N Jupiter Rd",
    "sg:city":"Garland",
    "sg:classifiers":[
        {
            "category":"Home & Garden",
            "subcategory":"Carpets & Floor Coverings",
            "type":"Retail Goods"
        }
    ],
    "sg:phone":"+1 469 358 7249",
    "sg:postcode":"75044",
    "sg:province":"TX",
    "wof:name":"Buy-Rite Carpets",
    "wof:placetype":"venue"
},
  "geometry": {"coordinates":[-96.68282600000001,32.931785],"type":"Point"}
}