{
  "type": "Feature",
  "properties": {
    "iso:country":"US",
    "sg:address":"6502 Forestview Dr",
    "sg:city":"Arlington",
    "sg:classifiers":[
        {
            "category":"Restaurant",
            "type":"Food & Drink"
        }
    ],
    "sg:phone":"+1 817 478 3175",
    "sg:postcode":"76016",
    "sg:province":"TX",
    "sg:tags":[
        "eating"
    ],
    "wof:name":"Pen Yuan Shih",
    "wof:placetype":"venue"
},
  "geometry": {"coordinates":[-97.21043899999999,32.675002],"type":"Point"}
}