{
  "type": "Feature",
  "properties": {
    "iso:country":"US",
    "sg:address":"8435 Fm 2920 Rd",
    "sg:city":"Spring",
    "sg:classifiers":[
        {
            "category":"Freight",
            "type":"Transportation"
        },
        {
            "category":"Retail",
            "subcategory":"Auto Rental",
            "type":"Services"
        },
        {
            "category":"Retail",
            "subcategory":"Storage",
            "type":"Services"
        }
    ],
    "sg:phone":"+1 281 205 4396",
    "sg:postcode":"77379",
    "sg:province":"TX",
    "sg:tags":[
        "truck",
        "moving-self",
        "local",
        "trucking"
    ],
    "sg:website":"http://www.uhaul.com/Locations/Rentals-near-Spring-TX-77379/033009",
    "wof:name":"U-Haul Neighborhood Dealer - Conoco Phillips 66 Food Mart",
    "wof:placetype":"venue"
},
  "geometry": {"coordinates":[-95.552014,30.073312],"type":"Point"}
}