{
  "type": "Feature",
  "properties": {
    "iso:country":"US",
    "sg:address":"4940 Mansfield Hwy",
    "sg:city":"Fort Worth",
    "sg:classifiers":[
        {
            "category":"Autos & Motor Vehicles",
            "subcategory":"Auto Supplies",
            "type":"Retail Goods"
        }
    ],
    "sg:phone":"+1 817 483 6114",
    "sg:postcode":"76119",
    "sg:province":"TX",
    "wof:name":"Best Deal",
    "wof:placetype":"venue"
},
  "geometry": {"coordinates":[-97.248583,32.668713],"type":"Point"}
}