{
  "type": "Feature",
  "properties": {
    "iso:country":"US",
    "sg:address":"4306 Garden Hills Ln",
    "sg:city":"Humble",
    "sg:classifiers":[
        {
            "category":"Professional",
            "subcategory":"Business Services",
            "type":"Services"
        }
    ],
    "sg:phone":"+1 281 360 4314",
    "sg:postcode":"77345",
    "sg:province":"TX",
    "wof:name":"Loot Bag",
    "wof:placetype":"venue"
},
  "geometry": {"coordinates":[-95.172371,30.068118],"type":"Point"}
}