{
  "type": "Feature",
  "properties": {
    "iso:country":"US",
    "sg:address":"114 Express St",
    "sg:city":"Dallas",
    "sg:classifiers":[
        {
            "category":"Wholesale",
            "subcategory":"Durable Goods & Equipment",
            "type":"Manufacturing & Wholesale Goods"
        }
    ],
    "sg:phone":"+1 732 829 7624",
    "sg:postcode":"75207",
    "sg:province":"TX",
    "sg:tags":[
        "antique",
        "import"
    ],
    "wof:name":"Iects Inc",
    "wof:placetype":"venue"
},
  "geometry": {"coordinates":[-96.828031,32.794365],"type":"Point"}
}