{
  "type": "Feature",
  "properties": {
    "iso:country":"US",
    "sg:address":"5403 Cameron Rd Ste 200",
    "sg:city":"Austin",
    "sg:classifiers":[
        {
            "category":"Insurance",
            "subcategory":"Insurance Agent",
            "type":"Services"
        },
        {
            "category":"Insurance",
            "subcategory":"Hazard Insurance",
            "type":"Services"
        }
    ],
    "sg:phone":"+1 512 380 0390",
    "sg:postcode":"78723",
    "sg:province":"TX",
    "sg:tags":[
        "business",
        "auto",
        "commercial",
        "marine",
        "boat"
    ],
    "sg:website":"http://www.fredloya.com",
    "wof:name":"Fred Loya Insurance",
    "wof:placetype":"venue"
},
  "geometry": {"coordinates":[-97.706337,30.311991],"type":"Point"}
}