{
  "type": "Feature",
  "properties": {
    "iso:country":"US",
    "sg:address":"6710 Chimney Rock Rd",
    "sg:city":"Houston",
    "sg:classifiers":[
        {
            "category":"Home & Garden",
            "subcategory":"Carpets & Floor Coverings",
            "type":"Retail Goods"
        }
    ],
    "sg:phone":"+1 713 667 5316",
    "sg:postcode":"77081",
    "sg:province":"TX",
    "wof:name":"Carpets By Donna",
    "wof:placetype":"venue"
},
  "geometry": {"coordinates":[-95.47635699999999,29.706632],"type":"Point"}
}