{
  "type": "Feature",
  "properties": {
    "iso:country":"US",
    "sg:address":"1818 W Grauwyler Rd",
    "sg:city":"Irving",
    "sg:classifiers":[
        {
            "category":"Communications",
            "subcategory":"Film & Video Production",
            "type":"Services"
        }
    ],
    "sg:phone":"+1 972 254 2431",
    "sg:postcode":"75061",
    "sg:province":"TX",
    "sg:tags":[
        "taping"
    ],
    "wof:name":"Texas Video Svc",
    "wof:placetype":"venue"
},
  "geometry": {"coordinates":[-96.96866900000001,32.828809],"type":"Point"}
}