{
  "type": "Feature",
  "properties": {
    "iso:country":"US",
    "sg:address":"211 E Park Ave",
    "sg:city":"Iowa Park",
    "sg:classifiers":[
        {
            "category":"Freight",
            "type":"Transportation"
        }
    ],
    "sg:phone":"+1 940 766 0616",
    "sg:postcode":"76367",
    "sg:province":"TX",
    "sg:tags":[
        "commercial",
        "storage"
    ],
    "wof:name":"C & C Self Storage",
    "wof:placetype":"venue"
},
  "geometry": {"coordinates":[-98.666946,33.952303],"type":"Point"}
}