{
  "type": "Feature",
  "properties": {
    "iso:country":"US",
    "sg:address":"4234 McCart Ave",
    "sg:city":"Fort Worth",
    "sg:classifiers":[
        {
            "category":"Organizations",
            "subcategory":"Non-profit Organization",
            "type":"Services"
        }
    ],
    "sg:phone":"+1 817 274 3983",
    "sg:postcode":"76115",
    "sg:province":"TX",
    "sg:tags":[
        "information",
        "alcoholism",
        "treatment"
    ],
    "wof:name":"Animo Education & Counseling",
    "wof:placetype":"venue"
},
  "geometry": {"coordinates":[-97.35310800000001,32.685852],"type":"Point"}
}