{
  "type": "Feature",
  "properties": {
    "iso:country":"US",
    "sg:address":"2204 Hanks St",
    "sg:city":"Lufkin",
    "sg:classifiers":[
        {
            "category":"Building & Trades",
            "subcategory":"Construction",
            "type":"Services"
        }
    ],
    "sg:phone":"+1 936 637 2913",
    "sg:postcode":"75904",
    "sg:province":"TX",
    "sg:tags":[
        "general",
        "paving",
        "contractor"
    ],
    "wof:name":"Lufkin Construction & Paving",
    "wof:placetype":"venue"
},
  "geometry": {"coordinates":[-94.75542,31.309783],"type":"Point"}
}