{
  "type": "Feature",
  "properties": {
    "iso:country":"US",
    "sg:address":"5406 State Hwy 25",
    "sg:city":"Electra",
    "sg:phone":"+1 940 495 3333",
    "sg:postcode":"76360",
    "sg:province":"TX",
    "sg:tags":[
        "farm",
        "wheat",
        "cotton"
    ],
    "wof:name":"James Brockriede",
    "wof:placetype":"venue"
},
  "geometry": {"coordinates":[-98.915836,34.102805],"type":"Point"}
}