{
  "type": "Feature",
  "properties": {
    "iso:country":"US",
    "sg:address":"233 Benmar Dr",
    "sg:city":"Houston",
    "sg:classifiers":[
        {
            "category":"Real Estate",
            "subcategory":"Developer",
            "type":"Services"
        }
    ],
    "sg:phone":"+1 713 656 3636",
    "sg:postcode":"77060",
    "sg:province":"TX",
    "wof:name":"Exxon",
    "wof:placetype":"venue"
},
  "geometry": {"coordinates":[-95.40505400000001,29.94338],"type":"Point"}
}