{
  "type": "Feature",
  "properties": {
    "iso:country":"US",
    "sg:address":"1724 Hunter Rd",
    "sg:city":"New Braunfels",
    "sg:classifiers":[
        {
            "category":"Restaurant",
            "type":"Food & Drink"
        }
    ],
    "sg:phone":"+1 830 629 0777",
    "sg:postcode":"78130",
    "sg:province":"TX",
    "wof:name":"Adobe Verde",
    "wof:placetype":"venue"
},
  "geometry": {"coordinates":[-98.10202,29.740712],"type":"Point"}
}