{
  "type": "Feature",
  "properties": {
    "iso:country":"US",
    "sg:address":"105 Ranch Rd",
    "sg:city":"Fritch",
    "sg:classifiers":[
        {
            "category":"Retail",
            "subcategory":"Repair Shop",
            "type":"Services"
        }
    ],
    "sg:phone":"+1 806 857 3279",
    "sg:postcode":"79036",
    "sg:province":"TX",
    "sg:tags":[
        "upholsterer"
    ],
    "wof:name":"Roy's Upholstery",
    "wof:placetype":"venue"
},
  "geometry": {"coordinates":[-101.579526,35.637271],"type":"Point"}
}