{
  "type": "Feature",
  "properties": {
    "iso:country":"US",
    "sg:address":"4725 Portrait Ln",
    "sg:city":"Plano",
    "sg:classifiers":[
        {
            "category":"Social Services",
            "subcategory":"Job Training",
            "type":"Services"
        }
    ],
    "sg:phone":"+1 972 618 7571",
    "sg:postcode":"75024",
    "sg:province":"TX",
    "wof:name":"My Brothers Helper Inc",
    "wof:placetype":"venue"
},
  "geometry": {"coordinates":[-96.793387,33.079738],"type":"Point"}
}