{
  "type": "Feature",
  "properties": {
    "iso:country":"US",
    "sg:address":"7005 72nd St",
    "sg:city":"Lubbock",
    "sg:classifiers":[
        {
            "category":"Professional",
            "subcategory":"Business Services",
            "type":"Services"
        }
    ],
    "sg:phone":"+1 806 798 1076",
    "sg:postcode":"79424",
    "sg:province":"TX",
    "wof:name":"M C L Seed Solutions Inc",
    "wof:placetype":"venue"
},
  "geometry": {"coordinates":[-101.969573,33.527743],"type":"Point"}
}