{
  "type": "Feature",
  "properties": {
    "iso:country":"US",
    "sg:address":"1230 State Hwy 3",
    "sg:city":"La Marque",
    "sg:classifiers":[
        {
            "category":"Shopping",
            "subcategory":"Computers & Home Electronics",
            "type":"Retail Goods"
        }
    ],
    "sg:phone":"+1 409 938 1230",
    "sg:postcode":"77568",
    "sg:province":"TX",
    "sg:tags":[
        "equipment",
        "electronic",
        "supply"
    ],
    "wof:name":"Gulf Coast Discount",
    "wof:placetype":"venue"
},
  "geometry": {"coordinates":[-94.95066799999999,29.367108],"type":"Point"}
}