{
  "type": "Feature",
  "properties": {
    "iso:country":"US",
    "sg:address":"4148 S Staples St",
    "sg:city":"Corpus Christi",
    "sg:classifiers":[
        {
            "category":"Home & Garden",
            "subcategory":"Furniture",
            "type":"Retail Goods"
        }
    ],
    "sg:phone":"+1 361 854 4900",
    "sg:postcode":"78411",
    "sg:province":"TX",
    "wof:name":"Braslau's Fine Home Furnishing",
    "wof:placetype":"venue"
},
  "geometry": {"coordinates":[-97.378455,27.725616],"type":"Point"}
}