{
  "type": "Feature",
  "properties": {
    "iso:country":"US",
    "sg:address":"500 N Capital of Texas Hwy",
    "sg:city":"Austin",
    "sg:classifiers":[
        {
            "category":"Professional",
            "subcategory":"Computer Services",
            "type":"Services"
        }
    ],
    "sg:phone":"+1 512 637 0700",
    "sg:postcode":"78746",
    "sg:province":"TX",
    "sg:tags":[
        "hardware",
        "provider",
        "internet",
        "software"
    ],
    "wof:name":"Intego",
    "wof:placetype":"venue"
},
  "geometry": {"coordinates":[-97.827039,30.312561],"type":"Point"}
}