{
  "type": "Feature",
  "properties": {
    "iso:country":"US",
    "sg:address":"1727 W Hildebrand Ave",
    "sg:city":"San Antonio",
    "sg:classifiers":[
        {
            "category":"Professional",
            "subcategory":"Lawyer & Legal Services",
            "type":"Services"
        }
    ],
    "sg:phone":"+1 210 222 8785",
    "sg:postcode":"78201",
    "sg:province":"TX",
    "sg:tags":[
        "attorney"
    ],
    "wof:name":"Louis D Martinez",
    "wof:placetype":"venue"
},
  "geometry": {"coordinates":[-98.52418299999999,29.466548],"type":"Point"}
}