{
  "type": "Feature",
  "properties": {
    "iso:country":"US",
    "sg:address":"2804 Woodville Rd",
    "sg:city":"Bryan",
    "sg:classifiers":[
        {
            "category":"Building & Trades",
            "subcategory":"Landscaping Services",
            "type":"Services"
        }
    ],
    "sg:phone":"+1 979 778 0557",
    "sg:postcode":"77803",
    "sg:province":"TX",
    "sg:tags":[
        "lawn",
        "maintenance"
    ],
    "wof:name":"Balandran Lawn Service",
    "wof:placetype":"venue"
},
  "geometry": {"coordinates":[-96.39093,30.712119],"type":"Point"}
}