{
  "type": "Feature",
  "properties": {
    "iso:country":"US",
    "sg:address":"5203 W University Blvd",
    "sg:city":"Odessa",
    "sg:classifiers":[
        {
            "category":"Autos & Motor Vehicles",
            "subcategory":"Automobile Sales",
            "type":"Retail Goods"
        }
    ],
    "sg:phone":"+1 432 381 3776",
    "sg:postcode":"79764",
    "sg:province":"TX",
    "sg:tags":[
        "car",
        "dealer"
    ],
    "wof:name":"Jerry Boys Used Cars",
    "wof:placetype":"venue"
},
  "geometry": {"coordinates":[-102.435833,31.85616],"type":"Point"}
}