{
  "type": "Feature",
  "properties": {
    "iso:country":"US",
    "sg:address":"7118 Foster Creek Dr",
    "sg:city":"Richmond",
    "sg:classifiers":[
        {
            "category":"Building & Trades",
            "subcategory":"Construction",
            "type":"Services"
        }
    ],
    "sg:phone":"+1 281 342 0593",
    "sg:postcode":"77406",
    "sg:province":"TX",
    "sg:tags":[
        "contractor"
    ],
    "wof:name":"Five H Construction",
    "wof:placetype":"venue"
},
  "geometry": {"coordinates":[-95.833184,29.630701],"type":"Point"}
}