{
  "type": "Feature",
  "properties": {
    "iso:country":"US",
    "sg:address":"112 N Poplar St Apt S",
    "sg:city":"Kermit",
    "sg:classifiers":[
        {
            "category":"Professional",
            "subcategory":"Detective & Security Services",
            "type":"Services"
        }
    ],
    "sg:phone":"+1 432 586 2233",
    "sg:postcode":"79745",
    "sg:province":"TX",
    "sg:tags":[
        "information",
        "bureau"
    ],
    "wof:name":"Winkler Veterans County Services",
    "wof:placetype":"venue"
},
  "geometry": {"coordinates":[-103.093346,31.857901],"type":"Point"}
}