{
  "type": "Feature",
  "properties": {
    "iso:country":"US",
    "sg:address":"12833 Trollope Dr",
    "sg:city":"El Paso",
    "sg:classifiers":[
        {
            "category":"Manufacturing",
            "subcategory":"Wood Products",
            "type":"Manufacturing & Wholesale Goods"
        }
    ],
    "sg:phone":"+1 915 852 1035",
    "sg:postcode":"79928",
    "sg:province":"TX",
    "sg:tags":[
        "mfg"
    ],
    "wof:name":"L & A Woodworking",
    "wof:placetype":"venue"
},
  "geometry": {"coordinates":[-106.242783,31.676476],"type":"Point"}
}