{
  "type": "Feature",
  "properties": {
    "iso:country":"US",
    "sg:address":"7102 Bellfort St",
    "sg:city":"Houston",
    "sg:classifiers":[
        {
            "category":"Fast Food",
            "type":"Food & Drink"
        }
    ],
    "sg:phone":"+1 713 645 5554",
    "sg:postcode":"77087",
    "sg:province":"TX",
    "wof:name":"Dairy Maid",
    "wof:placetype":"venue"
},
  "geometry": {"coordinates":[-95.30349699999999,29.6703],"type":"Point"}
}