{
  "type": "Feature",
  "properties": {
    "iso:country":"US",
    "sg:address":"4910 Westerham",
    "sg:city":"Fulshear",
    "sg:classifiers":[
        {
            "category":"Restaurant",
            "type":"Food & Drink"
        }
    ],
    "sg:phone":"+1 281 346 1806",
    "sg:postcode":"77441",
    "sg:province":"TX",
    "sg:tags":[
        "eating"
    ],
    "wof:name":"Two Busy To Cook",
    "wof:placetype":"venue"
},
  "geometry": {"coordinates":[-95.941687,29.671443],"type":"Point"}
}