{
  "type": "Feature",
  "properties": {
    "iso:country":"US",
    "sg:address":"3513 Rosa Ave",
    "sg:city":"El Paso",
    "sg:classifiers":[
        {
            "category":"Home & Garden",
            "subcategory":"Carpets & Floor Coverings",
            "type":"Retail Goods"
        }
    ],
    "sg:phone":"+1 915 532 4411",
    "sg:postcode":"79905",
    "sg:province":"TX",
    "sg:tags":[
        "material"
    ],
    "wof:name":"Mc Nutt Co Inc",
    "wof:placetype":"venue"
},
  "geometry": {"coordinates":[-106.45225000000001,31.77569],"type":"Point"}
}