{
  "type": "Feature",
  "properties": {
    "iso:country":"US",
    "sg:address":"201 W Baker Rd",
    "sg:city":"Baytown",
    "sg:classifiers":[
        {
            "category":"Shopping",
            "subcategory":"Florist",
            "type":"Retail Goods"
        }
    ],
    "sg:phone":"+1 713 523 7070",
    "sg:postcode":"77521",
    "sg:province":"TX",
    "wof:name":"Beehive Floral",
    "wof:placetype":"venue"
},
  "geometry": {"coordinates":[-94.96498200000001,29.769816],"type":"Point"}
}