{
  "type": "Feature",
  "properties": {
    "iso:country":"US",
    "sg:address":"5629 Yale Blvd",
    "sg:city":"Dallas",
    "sg:classifiers":[
        {
            "category":"Manufacturing",
            "subcategory":"Tools & Machinery",
            "type":"Manufacturing & Wholesale Goods"
        }
    ],
    "sg:phone":"+1 214 361 5583",
    "sg:postcode":"75206",
    "sg:province":"TX",
    "sg:tags":[
        "equipment",
        "mfg",
        "auto",
        "repair"
    ],
    "wof:name":"Graham Auto Air Conditioning",
    "wof:placetype":"venue"
},
  "geometry": {"coordinates":[-96.77220199999999,32.842098],"type":"Point"}
}