{
  "type": "Feature",
  "properties": {
    "iso:country":"US",
    "sg:address":"5340 Mockingbird Ln",
    "sg:city":"Dallas",
    "sg:classifiers":[
        {
            "category":"Retail",
            "subcategory":"Auto Rental",
            "type":"Services"
        }
    ],
    "sg:phone":"+1 214 824 3884",
    "sg:postcode":"75206",
    "sg:province":"TX",
    "sg:tags":[
        "renting",
        "truck",
        "leasing"
    ],
    "wof:name":"Hertz Truck & Rental",
    "wof:placetype":"venue"
},
  "geometry": {"coordinates":[-96.77533,32.836503],"type":"Point"}
}