{
  "type": "Feature",
  "properties": {
    "iso:country":"US",
    "sg:address":"556 Canyon Edge",
    "sg:city":"Canyon Lake",
    "sg:classifiers":[
        {
            "category":"Building & Trades",
            "subcategory":"Construction",
            "type":"Services"
        }
    ],
    "sg:phone":"+1 210 275 4917",
    "sg:postcode":"78133",
    "sg:province":"TX",
    "sg:tags":[
        "resurfacing",
        "laying",
        "refinishing",
        "floor"
    ],
    "wof:name":"Crawford Flooring",
    "wof:placetype":"venue"
},
  "geometry": {"coordinates":[-98.27571,29.881154],"type":"Point"}
}