{
  "type": "Feature",
  "properties": {
    "iso:country":"US",
    "sg:address":"14531 Roadrunner Way",
    "sg:city":"San Antonio",
    "sg:classifiers":[
        {
            "category":"Shopping",
            "subcategory":"Books",
            "type":"Retail Goods"
        }
    ],
    "sg:phone":"+1 210 691 8872",
    "sg:postcode":"78249",
    "sg:province":"TX",
    "wof:name":"Roadrunner Bookstore",
    "wof:placetype":"venue"
},
  "geometry": {"coordinates":[-98.62505899999999,29.577181],"type":"Point"}
}