{
  "type": "Feature",
  "properties": {
    "iso:country":"US",
    "sg:address":"1015 Woodrow St",
    "sg:city":"Silsbee",
    "sg:classifiers":[
        {
            "category":"Shopping",
            "subcategory":"Clothing, Apparel, & Fashions",
            "type":"Retail Goods"
        }
    ],
    "sg:phone":"+1 409 385 7105",
    "sg:postcode":"77656",
    "sg:province":"TX",
    "wof:name":"Gates",
    "wof:placetype":"venue"
},
  "geometry": {"coordinates":[-94.191935,30.34468],"type":"Point"}
}