{
  "type": "Feature",
  "properties": {
    "iso:country":"US",
    "sg:address":"4820 Westgrove Dr # 2712",
    "sg:city":"Addison",
    "sg:classifiers":[
        {
            "category":"Professional",
            "subcategory":"Art Services",
            "type":"Services"
        }
    ],
    "sg:phone":"+1 972 849 5379",
    "sg:postcode":"75001",
    "sg:province":"TX",
    "sg:tags":[
        "graphic",
        "commercial",
        "designer",
        "artist"
    ],
    "wof:name":"D Graphics",
    "wof:placetype":"venue"
},
  "geometry": {"coordinates":[-96.82804299999999,32.975764],"type":"Point"}
}