{
  "type": "Feature",
  "properties": {
    "iso:country":"US",
    "sg:address":"14511 Louetta Rd",
    "sg:city":"Cypress",
    "sg:classifiers":[
        {
            "category":"Restaurant",
            "type":"Food & Drink"
        }
    ],
    "sg:phone":"+1 281 320 9133",
    "sg:postcode":"77429",
    "sg:province":"TX",
    "sg:tags":[
        "eating"
    ],
    "wof:name":"Topwings Inc",
    "wof:placetype":"venue"
},
  "geometry": {"coordinates":[-95.644859,29.995762],"type":"Point"}
}