{
  "type": "Feature",
  "properties": {
    "iso:country":"US",
    "sg:address":"133 NW Renfro St",
    "sg:city":"Burleson",
    "sg:classifiers":[
        {
            "category":"Shopping",
            "subcategory":"Used Merchandise",
            "type":"Retail Goods"
        }
    ],
    "sg:phone":"+1 817 295 9281",
    "sg:postcode":"76028",
    "sg:province":"TX",
    "sg:tags":[
        "jewelry"
    ],
    "wof:name":"Burleson Pawn Shop",
    "wof:placetype":"venue"
},
  "geometry": {"coordinates":[-97.325203,32.542999],"type":"Point"}
}