{
  "type": "Feature",
  "properties": {
    "iso:country":"US",
    "sg:address":"9600 Westheimer Rd",
    "sg:city":"Houston",
    "sg:classifiers":[
        {
            "category":"Shopping",
            "type":"Retail Goods"
        }
    ],
    "sg:phone":"+1 713 785 0083",
    "sg:postcode":"77063",
    "sg:province":"TX",
    "sg:tags":[
        "picture",
        "frame",
        "art",
        "gallery"
    ],
    "sg:website":"www.lwframes.com",
    "wof:name":"L & W Frames",
    "wof:placetype":"venue"
},
  "geometry": {"coordinates":[-95.535797,29.7374],"type":"Point"}
}