{
  "type": "Feature",
  "properties": {
    "iso:country":"US",
    "sg:address":"508 E 53rd St Ste 102",
    "sg:city":"Austin",
    "sg:classifiers":[
        {
            "category":"Real Estate",
            "subcategory":"Real Estate Agent",
            "type":"Services"
        }
    ],
    "sg:phone":"+1 512 773 1514",
    "sg:postcode":"78751",
    "sg:province":"TX",
    "wof:name":"Lisa Smith, Realtor with Juice Homes",
    "wof:placetype":"venue"
},
  "geometry": {"coordinates":[-97.718,30.316232],"type":"Point"}
}