{
  "type": "Feature",
  "properties": {
    "iso:country":"US",
    "sg:address":"3840 Ridge Rd",
    "sg:city":"Weatherford",
    "sg:classifiers":[
        {
            "category":"Shopping",
            "type":"Retail Goods"
        }
    ],
    "sg:phone":"+1 817 441 8316",
    "sg:postcode":"76087",
    "sg:province":"TX",
    "sg:tags":[
        "merchandise"
    ],
    "wof:name":"Natural Healing Texas",
    "wof:placetype":"venue"
},
  "geometry": {"coordinates":[-97.66442499999999,32.784512],"type":"Point"}
}