{
  "type": "Feature",
  "properties": {
    "iso:country":"US",
    "sg:address":"711 N Sam Houston Blvd",
    "sg:city":"San Benito",
    "sg:classifiers":[
        {
            "category":"Professional",
            "subcategory":"Lawyer & Legal Services",
            "type":"Services"
        }
    ],
    "sg:phone":"+1 956 399 1299",
    "sg:postcode":"78586",
    "sg:province":"TX",
    "wof:name":"Adolfo E Cordova Jr",
    "wof:placetype":"venue"
},
  "geometry": {"coordinates":[-97.627171,26.137207],"type":"Point"}
}