{
  "type": "Feature",
  "properties": {
    "iso:country":"US",
    "sg:address":"1103 W Lakewood Dr",
    "sg:city":"Montgomery",
    "sg:classifiers":[
        {
            "category":"Building & Trades",
            "subcategory":"Electrical",
            "type":"Services"
        }
    ],
    "sg:phone":"+1 936 447 6933",
    "sg:postcode":"77316",
    "sg:province":"TX",
    "sg:tags":[
        "electrician"
    ],
    "wof:name":"S Brandl Electric Co",
    "wof:placetype":"venue"
},
  "geometry": {"coordinates":[-95.611317,30.34983],"type":"Point"}
}