{
  "type": "Feature",
  "properties": {
    "iso:country":"US",
    "sg:address":"1820 Red River Dr",
    "sg:city":"Wharton",
    "sg:classifiers":[
        {
            "category":"Real Estate",
            "subcategory":"Real Estate Operator",
            "type":"Services"
        }
    ],
    "sg:phone":"+1 979 532 5276",
    "sg:postcode":"77488",
    "sg:province":"TX",
    "sg:tags":[
        "apartment"
    ],
    "wof:name":"Wharton Plaza Apartments",
    "wof:placetype":"venue"
},
  "geometry": {"coordinates":[-96.07888,29.324339],"type":"Point"}
}