{
  "type": "Feature",
  "properties": {
    "iso:country":"US",
    "sg:address":"129 Denver Trl",
    "sg:city":"Azle",
    "sg:classifiers":[
        {
            "category":"Professional",
            "type":"Services"
        }
    ],
    "sg:phone":"+1 817 444 7291",
    "sg:postcode":"76020",
    "sg:province":"TX",
    "sg:tags":[
        "establishment"
    ],
    "wof:name":"Mainstream Inc",
    "wof:placetype":"venue"
},
  "geometry": {"coordinates":[-97.53388,32.881248],"type":"Point"}
}