{
  "type": "Feature",
  "properties": {
    "iso:country":"US",
    "sg:address":"101 N Dumas Ave",
    "sg:city":"Dumas",
    "sg:classifiers":[
        {
            "category":"Food & Beverages",
            "subcategory":"Groceries & Convenience Stores",
            "type":"Retail Goods"
        }
    ],
    "sg:phone":"+1 806 935 5870",
    "sg:postcode":"79029",
    "sg:province":"TX",
    "wof:name":"Pak-A-Sack 6",
    "wof:placetype":"venue"
},
  "geometry": {"coordinates":[-101.973195,35.870502],"type":"Point"}
}