{
  "type": "Feature",
  "properties": {
    "iso:country":"US",
    "sg:address":"1309 Elmwood St",
    "sg:city":"Gainesville",
    "sg:classifiers":[
        {
            "category":"Shopping",
            "subcategory":"Bicycles & Sporting Goods",
            "type":"Retail Goods"
        }
    ],
    "sg:phone":"+1 940 668 7572",
    "sg:postcode":"76240",
    "sg:province":"TX",
    "wof:name":"Comers Gun Shop",
    "wof:placetype":"venue"
},
  "geometry": {"coordinates":[-97.12366400000001,33.640958],"type":"Point"}
}