{
  "type": "Feature",
  "properties": {
    "iso:country":"US",
    "sg:address":"1809 E Rogers Rd",
    "sg:city":"Edinburg",
    "sg:classifiers":[
        {
            "category":"Wholesale",
            "subcategory":"Electrical",
            "type":"Manufacturing & Wholesale Goods"
        }
    ],
    "sg:phone":"+1 956 316 2042",
    "sg:postcode":"78539",
    "sg:province":"TX",
    "sg:tags":[
        "equipment"
    ],
    "wof:name":"World Wide Cable Inc",
    "wof:placetype":"venue"
},
  "geometry": {"coordinates":[-98.13496600000001,26.32671],"type":"Point"}
}