{
  "type": "Feature",
  "properties": {
    "iso:country":"US",
    "sg:address":"10215 Northlake Dr",
    "sg:city":"Dallas",
    "sg:classifiers":[
        {
            "category":"Building & Trades",
            "subcategory":"Construction",
            "type":"Services"
        }
    ],
    "sg:phone":"+1 214 546 7579",
    "sg:postcode":"75218",
    "sg:province":"TX",
    "sg:tags":[
        "remodel",
        "contractor"
    ],
    "wof:name":"Ronald L Siebler",
    "wof:placetype":"venue"
},
  "geometry": {"coordinates":[-96.707364,32.856565],"type":"Point"}
}