{
  "type": "Feature",
  "properties": {
    "iso:country":"US",
    "sg:address":"704 Shadow Glen Dr",
    "sg:city":"Southlake",
    "sg:classifiers":[
        {
            "category":"Insurance",
            "subcategory":"Insurance Agent",
            "type":"Services"
        }
    ],
    "sg:phone":"+1 817 424 3212",
    "sg:postcode":"76092",
    "sg:province":"TX",
    "sg:tags":[
        "adjuster"
    ],
    "wof:name":"Farmers Insurance",
    "wof:placetype":"venue"
},
  "geometry": {"coordinates":[-97.160487,32.936367],"type":"Point"}
}