{
  "type": "Feature",
  "properties": {
    "iso:country":"US",
    "sg:address":"21010 Scenic Loop Rd",
    "sg:city":"Helotes",
    "sg:classifiers":[
        {
            "category":"Professional",
            "type":"Services"
        }
    ],
    "sg:phone":"+1 210 695 3494",
    "sg:postcode":"78023",
    "sg:province":"TX",
    "wof:name":"Ragtyme Etc",
    "wof:placetype":"venue"
},
  "geometry": {"coordinates":[-98.678461,29.635452],"type":"Point"}
}