{
  "type": "Feature",
  "properties": {
    "iso:country":"US",
    "sg:address":"11661 Preston Rd",
    "sg:city":"Dallas",
    "sg:classifiers":[
        {
            "category":"Shopping",
            "subcategory":"Clothing, Apparel, & Fashions",
            "type":"Retail Goods"
        }
    ],
    "sg:phone":"+1 214 369 3909",
    "sg:postcode":"75230",
    "sg:province":"TX",
    "sg:tags":[
        "furnishing"
    ],
    "sg:website":"www.rochesterclothing.com",
    "wof:name":"Rochester Big & Tall",
    "wof:placetype":"venue"
},
  "geometry": {"coordinates":[-96.80416200000001,32.908502],"type":"Point"}
}