{
  "type": "Feature",
  "properties": {
    "iso:country":"US",
    "sg:address":"6606 Ashland Dr",
    "sg:city":"Austin",
    "sg:classifiers":[
        {
            "category":"Shopping",
            "type":"Retail Goods"
        },
        {
            "category":"Organizations",
            "subcategory":"Non-profit Organization",
            "type":"Services"
        }
    ],
    "sg:phone":"+1 512 926 4148",
    "sg:postcode":"78723",
    "sg:province":"TX",
    "sg:tags":[
        "supply",
        "fund",
        "games",
        "merchandise",
        "raising"
    ],
    "wof:name":"Hardeman Scholarship Foundation",
    "wof:placetype":"venue"
},
  "geometry": {"coordinates":[-97.66574900000001,30.307824],"type":"Point"}
}