{
  "type": "Feature",
  "properties": {
    "iso:country":"US",
    "sg:address":"7620 Hacienda Ave",
    "sg:city":"El Paso",
    "sg:classifiers":[
        {
            "category":"Education",
            "subcategory":"Special Training",
            "type":"Public Place"
        }
    ],
    "sg:phone":"+1 915 857 9716",
    "sg:postcode":"79915",
    "sg:province":"TX",
    "sg:tags":[
        "school",
        "music"
    ],
    "wof:name":"Renegade Piper",
    "wof:placetype":"venue"
},
  "geometry": {"coordinates":[-106.35915300000001,31.744686],"type":"Point"}
}