{
  "type": "Feature",
  "properties": {
    "iso:country":"US",
    "sg:address":"200 Sidney Baker St S",
    "sg:city":"Kerrville",
    "sg:classifiers":[
        {
            "category":"Real Estate",
            "subcategory":"Real Estate Operator",
            "type":"Services"
        }
    ],
    "sg:phone":"+1 830 896 0606",
    "sg:postcode":"78028",
    "sg:province":"TX",
    "sg:tags":[
        "mall",
        "shopping",
        "center"
    ],
    "wof:name":"River Hills Mall",
    "wof:placetype":"venue"
},
  "geometry": {"coordinates":[-99.144278,30.044251],"type":"Point"}
}