{
  "type": "Feature",
  "properties": {
    "iso:country":"US",
    "sg:address":"782 S Mill St",
    "sg:city":"Lewisville",
    "sg:classifiers":[
        {
            "category":"Personal",
            "subcategory":"Beauty Salon",
            "type":"Services"
        }
    ],
    "sg:phone":"+1 972 420 4331",
    "sg:postcode":"75057",
    "sg:province":"TX",
    "wof:name":"Excelencia Latina Angelica's",
    "wof:placetype":"venue"
},
  "geometry": {"coordinates":[-96.99292800000001,33.038709],"type":"Point"}
}