{
  "type": "Feature",
  "properties": {
    "iso:country":"US",
    "sg:address":"102 Hillside Dr",
    "sg:city":"Aledo",
    "sg:classifiers":[
        {
            "category":"Building & Trades",
            "subcategory":"Electrical",
            "type":"Services"
        }
    ],
    "sg:phone":"+1 817 336 1066",
    "sg:postcode":"76008",
    "sg:province":"TX",
    "sg:tags":[
        "electrical",
        "contractor"
    ],
    "wof:name":"Electric 3 Wheeler",
    "wof:placetype":"venue"
},
  "geometry": {"coordinates":[-97.65297,32.681319],"type":"Point"}
}