{
  "type": "Feature",
  "properties": {
    "iso:country":"US",
    "sg:address":"1617 S Arthur St",
    "sg:city":"Amarillo",
    "sg:classifiers":[
        {
            "category":"Building & Trades",
            "subcategory":"Construction",
            "type":"Services"
        }
    ],
    "sg:phone":"+1 806 376 8680",
    "sg:postcode":"79102",
    "sg:province":"TX",
    "sg:tags":[
        "paving",
        "contractor"
    ],
    "wof:name":"Robledo's Paving Co",
    "wof:placetype":"venue"
},
  "geometry": {"coordinates":[-101.82674299999999,35.194031],"type":"Point"}
}