{
  "type": "Feature",
  "properties": {
    "iso:country":"US",
    "sg:address":"428B Main St",
    "sg:city":"Kerrville",
    "sg:classifiers":[
        {
            "category":"Personal",
            "subcategory":"Beauty Salon",
            "type":"Services"
        }
    ],
    "sg:phone":"+1 830 257 1823",
    "sg:postcode":"78028",
    "sg:province":"TX",
    "wof:name":"Shear Way to Heaven",
    "wof:placetype":"venue"
},
  "geometry": {"coordinates":[-99.143762,30.05024],"type":"Point"}
}