{
  "type": "Feature",
  "properties": {
    "iso:country":"US",
    "sg:address":"4749 Odom Rd",
    "sg:city":"Beaumont",
    "sg:classifiers":[
        {
            "category":"Insurance",
            "subcategory":"Insurance Agent",
            "type":"Services"
        }
    ],
    "sg:phone":"+1 409 899 3602",
    "sg:postcode":"77706",
    "sg:province":"TX",
    "wof:name":"Michell Insurance Agency",
    "wof:placetype":"venue"
},
  "geometry": {"coordinates":[-94.152967,30.122957],"type":"Point"}
}