{
  "type": "Feature",
  "properties": {
    "iso:country":"US",
    "sg:address":"208 Octavia St",
    "sg:city":"El Paso",
    "sg:classifiers":[
        {
            "category":"Manufacturing",
            "subcategory":"Metals",
            "type":"Manufacturing & Wholesale Goods"
        }
    ],
    "sg:phone":"+1 915 532 9219",
    "sg:postcode":"79901",
    "sg:province":"TX",
    "sg:tags":[
        "steel",
        "made",
        "stainless",
        "custom",
        "fabricates",
        "kitchen"
    ],
    "wof:name":"I Fab",
    "wof:placetype":"venue"
},
  "geometry": {"coordinates":[-106.47906999999999,31.763966],"type":"Point"}
}