{
  "type": "Feature",
  "properties": {
    "iso:country":"US",
    "sg:address":"301 Spurlock Dr",
    "sg:city":"Krum",
    "sg:classifiers":[
        {
            "category":"Building & Trades",
            "subcategory":"Cleaning & Sanitation",
            "type":"Services"
        }
    ],
    "sg:phone":"+1 940 482 8263",
    "sg:postcode":"76249",
    "sg:province":"TX",
    "sg:tags":[
        "janitorial"
    ],
    "wof:name":"White Glove Industrial Janitorial Se",
    "wof:placetype":"venue"
},
  "geometry": {"coordinates":[-97.215987,33.255135],"type":"Point"}
}