{
  "type": "Feature",
  "properties": {
    "iso:country":"US",
    "sg:address":"318 College St",
    "sg:city":"Farmersville",
    "sg:classifiers":[
        {
            "category":"Recreation",
            "type":"Entertainment"
        }
    ],
    "sg:phone":"+1 972 784 6822",
    "sg:postcode":"75442",
    "sg:province":"TX",
    "wof:name":"Riding Armor Inc",
    "wof:placetype":"venue"
},
  "geometry": {"coordinates":[-96.35513,33.163629],"type":"Point"}
}