{
  "type": "Feature",
  "properties": {
    "iso:country":"US",
    "sg:address":"107 N Madison St",
    "sg:city":"Madisonville",
    "sg:classifiers":[
        {
            "category":"Professional",
            "subcategory":"Art Services",
            "type":"Services"
        }
    ],
    "sg:phone":"+1 936 348 3258",
    "sg:postcode":"77864",
    "sg:province":"TX",
    "sg:tags":[
        "photographer"
    ],
    "wof:name":"Shauna Maness Photography",
    "wof:placetype":"venue"
},
  "geometry": {"coordinates":[-95.91402600000001,30.94981],"type":"Point"}
}