{
  "type": "Feature",
  "properties": {
    "iso:country":"US",
    "sg:address":"108 S Walnut St",
    "sg:city":"Roanoke",
    "sg:classifiers":[
        {
            "category":"Building & Trades",
            "subcategory":"Pest Control",
            "type":"Services"
        }
    ],
    "sg:phone":"+1 817 379 0680",
    "sg:postcode":"76262",
    "sg:province":"TX",
    "wof:name":"Elite Pest Control",
    "wof:placetype":"venue"
},
  "geometry": {"coordinates":[-97.227413,32.996903],"type":"Point"}
}