{
  "type": "Feature",
  "properties": {
    "iso:country":"US",
    "sg:address":"6006 Gulf Freeway",
    "sg:city":"Houston",
    "sg:classifiers":[
        {
            "category":"Restaurant",
            "type":"Food & Drink"
        }
    ],
    "sg:postcode":"77023",
    "sg:province":"TX",
    "sg:tags":[
        "traditional",
        "american"
    ],
    "wof:name":"Wings & More",
    "wof:placetype":"venue"
},
  "geometry": {"coordinates":[-95.312572,29.712922],"type":"Point"}
}