{
  "type": "Feature",
  "properties": {
    "iso:country":"US",
    "sg:address":"663 Quarry St",
    "sg:city":"Eagle Pass",
    "sg:classifiers":[
        {
            "category":"Building & Trades",
            "subcategory":"Construction",
            "type":"Services"
        }
    ],
    "sg:phone":"+1 830 757 3077",
    "sg:postcode":"78852",
    "sg:province":"TX",
    "sg:tags":[
        "general",
        "contractor"
    ],
    "wof:name":"Blazer Construction Inc",
    "wof:placetype":"venue"
},
  "geometry": {"coordinates":[-100.500092,28.709865],"type":"Point"}
}