{
  "type": "Feature",
  "properties": {
    "iso:country":"US",
    "sg:address":"35 S Apple Springs Cir",
    "sg:city":"Spring",
    "sg:classifiers":[
        {
            "category":"Restaurant",
            "type":"Food & Drink"
        }
    ],
    "sg:phone":"+1 281 292 5383",
    "sg:postcode":"77382",
    "sg:province":"TX",
    "sg:tags":[
        "eating"
    ],
    "wof:name":"Taste of Heaven",
    "wof:placetype":"venue"
},
  "geometry": {"coordinates":[-95.55634999999999,30.213496],"type":"Point"}
}