{
  "type": "Feature",
  "properties": {
    "iso:country":"US",
    "sg:address":"1277 Country Club Ln",
    "sg:city":"Fort Worth",
    "sg:classifiers":[
        {
            "category":"Professional",
            "subcategory":"Credit Reporting & Collection",
            "type":"Services"
        }
    ],
    "sg:phone":"+1 817 654 0993",
    "sg:postcode":"76112",
    "sg:province":"TX",
    "sg:tags":[
        "agency"
    ],
    "wof:name":"CSII",
    "wof:placetype":"venue"
},
  "geometry": {"coordinates":[-97.233467,32.762904],"type":"Point"}
}