{
  "type": "Feature",
  "properties": {
    "iso:country":"US",
    "sg:address":"711 Ferris Ave",
    "sg:city":"Waxahachie",
    "sg:classifiers":[
        {
            "category":"Communications",
            "subcategory":"Radio Station",
            "type":"Services"
        }
    ],
    "sg:phone":"+1 972 923 1390",
    "sg:postcode":"75165",
    "sg:province":"TX",
    "wof:name":"K B E C",
    "wof:placetype":"venue"
},
  "geometry": {"coordinates":[-96.846762,32.394176],"type":"Point"}
}