{
  "type": "Feature",
  "properties": {
    "iso:country":"US",
    "sg:address":"13503 Contado Ct",
    "sg:city":"Cypress",
    "sg:classifiers":[
        {
            "category":"Manufacturing",
            "subcategory":"Electronics",
            "type":"Manufacturing & Wholesale Goods"
        }
    ],
    "sg:phone":"+1 281 373 5890",
    "sg:postcode":"77429",
    "sg:province":"TX",
    "sg:tags":[
        "electronic",
        "component",
        "mfg"
    ],
    "wof:name":"Hermetic Cmpsr of Houston",
    "wof:placetype":"venue"
},
  "geometry": {"coordinates":[-95.639039,29.978187],"type":"Point"}
}