{
  "type": "Feature",
  "properties": {
    "iso:country":"US",
    "sg:address":"108 Quince St",
    "sg:city":"Hereford",
    "sg:classifiers":[
        {
            "category":"Manufacturing",
            "subcategory":"Retail Goods",
            "type":"Manufacturing & Wholesale Goods"
        }
    ],
    "sg:phone":"+1 806 364 5878",
    "sg:postcode":"79045",
    "sg:province":"TX",
    "sg:tags":[
        "product",
        "mfg"
    ],
    "wof:name":"Mohrlang Mfg Inc",
    "wof:placetype":"venue"
},
  "geometry": {"coordinates":[-102.42980799999999,34.824323],"type":"Point"}
}