{
  "type": "Feature",
  "properties": {
    "iso:country":"US",
    "sg:address":"4103 Lee St",
    "sg:city":"Greenville",
    "sg:classifiers":[
        {
            "category":"Personal",
            "subcategory":"Barber",
            "type":"Services"
        }
    ],
    "sg:phone":"+1 903 455 9964",
    "sg:postcode":"75401",
    "sg:province":"TX",
    "sg:tags":[
        "shop"
    ],
    "wof:name":"Neal Barber Shop",
    "wof:placetype":"venue"
},
  "geometry": {"coordinates":[-96.122152,33.139951],"type":"Point"}
}