{
  "type": "Feature",
  "properties": {
    "iso:country":"US",
    "sg:address":"5522 Richmond Ave",
    "sg:city":"Houston",
    "sg:classifiers":[
        {
            "category":"Professional",
            "type":"Services"
        }
    ],
    "sg:phone":"+1 713 977 1788",
    "sg:postcode":"77056",
    "sg:province":"TX",
    "wof:name":"World Trans P17122",
    "wof:placetype":"venue"
},
  "geometry": {"coordinates":[-95.475965,29.731585],"type":"Point"}
}