{
  "type": "Feature",
  "properties": {
    "iso:country":"US",
    "sg:address":"10529 Olympic Dr",
    "sg:city":"Dallas",
    "sg:classifiers":[
        {
            "category":"Professional",
            "type":"Services"
        }
    ],
    "sg:phone":"+1 214 904 9812",
    "sg:postcode":"75220",
    "sg:province":"TX",
    "sg:tags":[
        "establishment"
    ],
    "wof:name":"Howmedia North Texas",
    "wof:placetype":"venue"
},
  "geometry": {"coordinates":[-96.887511,32.865607],"type":"Point"}
}