{
  "type": "Feature",
  "properties": {
    "iso:country":"US",
    "sg:address":"4320 US Hwy 380",
    "sg:city":"Greenville",
    "sg:classifiers":[
        {
            "category":"Education",
            "subcategory":"School",
            "type":"Public Place"
        }
    ],
    "sg:phone":"+1 903 527 3211",
    "sg:postcode":"75401",
    "sg:province":"TX",
    "wof:name":"Bland Elementary School",
    "wof:placetype":"venue"
},
  "geometry": {"coordinates":[-96.12768,33.124864],"type":"Point"}
}