{
  "type": "Feature",
  "properties": {
    "iso:country":"US",
    "sg:address":"4117 Tierra Blanca Rd",
    "sg:city":"Hereford",
    "sg:phone":"+1 806 364 1916",
    "sg:postcode":"79045",
    "sg:province":"TX",
    "sg:tags":[
        "farm",
        "cotton"
    ],
    "wof:name":"Berend Farms",
    "wof:placetype":"venue"
},
  "geometry": {"coordinates":[-102.457292,34.893165],"type":"Point"}
}