{
  "type": "Feature",
  "properties": {
    "iso:country":"US",
    "sg:address":"5534 FM 89",
    "sg:city":"Tuscola",
    "sg:classifiers":[
        {
            "category":"Travel",
            "subcategory":"Hotels & Motels",
            "type":"Entertainment"
        }
    ],
    "sg:phone":"+1 325 572 5880",
    "sg:postcode":"79562",
    "sg:province":"TX",
    "sg:tags":[
        "operation",
        "breakfast",
        "bed",
        "accommodation"
    ],
    "wof:name":"Rolling M Ranch Resort",
    "wof:placetype":"venue"
},
  "geometry": {"coordinates":[-99.929114,32.229792],"type":"Point"}
}