{
  "type": "Feature",
  "properties": {
    "iso:country":"US",
    "sg:address":"6601 Hillcroft St Ste 115",
    "sg:city":"Houston",
    "sg:classifiers":[
        {
            "category":"Landmark",
            "subcategory":"Tourist Information",
            "type":"Public Place"
        }
    ],
    "sg:phone":"+1 713 995 0408",
    "sg:postcode":"77081",
    "sg:province":"TX",
    "sg:tags":[
        "tour"
    ],
    "wof:name":"Mundi Tours",
    "wof:placetype":"venue"
},
  "geometry": {"coordinates":[-95.482803,29.712799],"type":"Point"}
}