{
  "type": "Feature",
  "properties": {
    "iso:country":"US",
    "sg:address":"718 S Stanton St",
    "sg:city":"El Paso",
    "sg:classifiers":[
        {
            "category":"Freight",
            "type":"Transportation"
        }
    ],
    "sg:phone":"+1 915 838 1855",
    "sg:postcode":"79901",
    "sg:province":"TX",
    "sg:tags":[
        "broker",
        "customs"
    ],
    "wof:name":"J R Brokerage & Svc",
    "wof:placetype":"venue"
},
  "geometry": {"coordinates":[-106.48394999999999,31.752535],"type":"Point"}
}