{
  "type": "Feature",
  "properties": {
    "iso:country":"US",
    "sg:address":"4 Skyline Dr",
    "sg:city":"Lampasas",
    "sg:classifiers":[
        {
            "category":"Professional",
            "subcategory":"Business Services",
            "type":"Services"
        }
    ],
    "sg:phone":"+1 512 556 3200",
    "sg:postcode":"76550",
    "sg:province":"TX",
    "sg:tags":[
        "lettering",
        "return",
        "sign",
        "preparation",
        "painting",
        "painter"
    ],
    "wof:name":"Jackson's Signs",
    "wof:placetype":"venue"
},
  "geometry": {"coordinates":[-98.169921,31.055728],"type":"Point"}
}