{
  "type": "Feature",
  "properties": {
    "iso:country":"US",
    "sg:address":"5361 Buffalo St",
    "sg:city":"Midlothian",
    "sg:classifiers":[
        {
            "category":"Organizations",
            "subcategory":"Religious Organization",
            "type":"Services"
        }
    ],
    "sg:phone":"+1 972 775 1433",
    "sg:postcode":"76065",
    "sg:province":"TX",
    "wof:name":"Freedom Community Church",
    "wof:placetype":"venue"
},
  "geometry": {"coordinates":[-97.05894600000001,32.494968],"type":"Point"}
}