{
  "type": "Feature",
  "properties": {
    "iso:country":"US",
    "sg:address":"2124 S Co Rd 1120",
    "sg:city":"Midland",
    "sg:classifiers":[
        {
            "category":"Mining & Drilling",
            "type":"Manufacturing & Wholesale Goods"
        }
    ],
    "sg:phone":"+1 432 570 7744",
    "sg:postcode":"79706",
    "sg:province":"TX",
    "sg:tags":[
        "lateral",
        "ultra",
        "radius",
        "short"
    ],
    "wof:name":"LTI",
    "wof:placetype":"venue"
},
  "geometry": {"coordinates":[-101.961855,32.010666],"type":"Point"}
}