{
  "type": "Feature",
  "properties": {
    "iso:country":"US",
    "sg:address":"550 E Yukon Rd",
    "sg:city":"Odessa",
    "sg:classifiers":[
        {
            "category":"Food & Beverages",
            "subcategory":"Groceries & Convenience Stores",
            "type":"Retail Goods"
        }
    ],
    "sg:phone":"+1 432 366 9117",
    "sg:postcode":"79762",
    "sg:province":"TX",
    "sg:tags":[
        "grocer"
    ],
    "wof:name":"Big John's Grocery",
    "wof:placetype":"venue"
},
  "geometry": {"coordinates":[-102.386453,31.912134],"type":"Point"}
}