{
  "type": "Feature",
  "properties": {
    "iso:country":"US",
    "sg:address":"5040 Bellfort St",
    "sg:city":"Houston",
    "sg:classifiers":[
        {
            "category":"Personal",
            "subcategory":"Beauty Salon",
            "type":"Services"
        }
    ],
    "sg:phone":"+1 713 734 8457",
    "sg:postcode":"77033",
    "sg:province":"TX",
    "sg:tags":[
        "shop",
        "barber"
    ],
    "wof:name":"Secola's Beauty & Barber Shop",
    "wof:placetype":"venue"
},
  "geometry": {"coordinates":[-95.350899,29.666901],"type":"Point"}
}