{
  "type": "Feature",
  "properties": {
    "iso:country":"US",
    "sg:address":"12712 Bransford Cove",
    "sg:city":"Austin",
    "sg:classifiers":[
        {
            "category":"Real Estate",
            "subcategory":"Real Estate Agent",
            "type":"Services"
        }
    ],
    "sg:phone":"+1 512 252 0161",
    "sg:postcode":"78753",
    "sg:province":"TX",
    "wof:name":"Hoopes Properties LLC",
    "wof:placetype":"venue"
},
  "geometry": {"coordinates":[-97.645094,30.396335],"type":"Point"}
}