{
  "type": "Feature",
  "properties": {
    "iso:country":"US",
    "sg:address":"1601 State Loop 340",
    "sg:city":"Waco",
    "sg:classifiers":[
        {
            "category":"Autos & Motor Vehicles",
            "subcategory":"Automobile Sales",
            "type":"Retail Goods"
        }
    ],
    "sg:phone":"+1 254 420 4740",
    "sg:postcode":"76712",
    "sg:province":"TX",
    "sg:tags":[
        "used"
    ],
    "wof:name":"Greg May Honda",
    "wof:placetype":"venue"
},
  "geometry": {"coordinates":[-97.171139,31.500789],"type":"Point"}
}