{
  "type": "Feature",
  "properties": {
    "iso:country":"US",
    "sg:address":"4710 Thompson Chapel Rd",
    "sg:city":"Sugar Land",
    "sg:classifiers":[
        {
            "category":"Professional",
            "subcategory":"Business Services",
            "type":"Services"
        }
    ],
    "sg:phone":"+1 281 565 0114",
    "sg:postcode":"77479",
    "sg:province":"TX",
    "wof:name":"Jakoba Enterprizes",
    "wof:placetype":"venue"
},
  "geometry": {"coordinates":[-95.68925,29.596078],"type":"Point"}
}