{
  "type": "Feature",
  "properties": {
    "iso:country":"US",
    "sg:address":"1938 Bretzke Ln",
    "sg:city":"New Braunfels",
    "sg:classifiers":[
        {
            "category":"Building & Trades",
            "subcategory":"Electrical",
            "type":"Services"
        }
    ],
    "sg:phone":"+1 830 608 3434",
    "sg:postcode":"78132",
    "sg:province":"TX",
    "sg:tags":[
        "electrical",
        "electric",
        "contractor"
    ],
    "wof:name":"Zunker Electric LLC",
    "wof:placetype":"venue"
},
  "geometry": {"coordinates":[-98.116591,29.760792],"type":"Point"}
}