{
  "type": "Feature",
  "properties": {
    "iso:country":"US",
    "sg:address":"5323 Barleycorn Ln",
    "sg:city":"Katy",
    "sg:classifiers":[
        {
            "category":"Restaurant",
            "type":"Food & Drink"
        }
    ],
    "sg:phone":"+1 281 712 5509",
    "sg:postcode":"77494",
    "sg:province":"TX",
    "wof:name":"Pho 70 Vietnamese Restaurant",
    "wof:placetype":"venue"
},
  "geometry": {"coordinates":[-95.806845,29.715535],"type":"Point"}
}