{
  "type": "Feature",
  "properties": {
    "iso:country":"US",
    "sg:address":"4355 Hwy 67",
    "sg:city":"Mesquite",
    "sg:classifiers":[
        {
            "category":"Retail",
            "subcategory":"Auto Repair",
            "type":"Services"
        }
    ],
    "sg:phone":"+1 214 367 7917",
    "sg:postcode":"75150",
    "sg:province":"TX",
    "sg:tags":[
        "repairing",
        "automobile"
    ],
    "wof:name":"DFW Mobile Tech",
    "wof:placetype":"venue"
},
  "geometry": {"coordinates":[-96.668043,32.804239],"type":"Point"}
}