{
  "type": "Feature",
  "properties": {
    "iso:country":"US",
    "sg:address":"2000 E 8th St",
    "sg:city":"Odessa",
    "sg:classifiers":[
        {
            "category":"Food & Beverages",
            "subcategory":"Groceries & Convenience Stores",
            "type":"Retail Goods"
        }
    ],
    "sg:phone":"+1 432 335 0319",
    "sg:postcode":"79761",
    "sg:province":"TX",
    "sg:tags":[
        "grocer"
    ],
    "wof:name":"Taylor Petroleum",
    "wof:placetype":"venue"
},
  "geometry": {"coordinates":[-102.343971,31.861454],"type":"Point"}
}