{
  "type": "Feature",
  "properties": {
    "iso:country":"US",
    "sg:address":"1824 S Jackson St",
    "sg:city":"Jacksonville",
    "sg:classifiers":[
        {
            "category":"Retail",
            "subcategory":"Laundry & Dry Cleaning",
            "type":"Services"
        }
    ],
    "sg:phone":"+1 903 586 3983",
    "sg:postcode":"75766",
    "sg:province":"TX",
    "sg:tags":[
        "garment",
        "agent"
    ],
    "wof:name":"Cleaning Depot",
    "wof:placetype":"venue"
},
  "geometry": {"coordinates":[-95.26070900000001,31.947828],"type":"Point"}
}