{
  "type": "Feature",
  "properties": {
    "iso:country":"US",
    "sg:address":"8707 Palm Valley Ct",
    "sg:city":"Houston",
    "sg:classifiers":[
        {
            "category":"Health Services",
            "subcategory":"Clinic",
            "type":"Services"
        }
    ],
    "sg:phone":"+1 281 561 6500",
    "sg:postcode":"77083",
    "sg:province":"TX",
    "wof:name":"Emangy Healthcare Svc Inc",
    "wof:placetype":"venue"
},
  "geometry": {"coordinates":[-95.64155100000001,29.684112],"type":"Point"}
}