{
  "type": "Feature",
  "properties": {
    "iso:country":"US",
    "sg:address":"1250 E Copeland Rd",
    "sg:city":"Arlington",
    "sg:classifiers":[
        {
            "category":"Insurance",
            "subcategory":"Health Insurance",
            "type":"Services"
        }
    ],
    "sg:phone":"+1 817 436 5400",
    "sg:postcode":"76011",
    "sg:province":"TX",
    "sg:tags":[
        "carrier"
    ],
    "wof:name":"Benesight Inc",
    "wof:placetype":"venue"
},
  "geometry": {"coordinates":[-97.09032999999999,32.759042],"type":"Point"}
}