{
  "type": "Feature",
  "properties": {
    "iso:country":"US",
    "sg:address":"455 Wake Forrest Dr",
    "sg:city":"San Antonio",
    "sg:classifiers":[
        {
            "category":"Professional",
            "type":"Services"
        }
    ],
    "sg:phone":"+1 210 435 4385",
    "sg:postcode":"78228",
    "sg:province":"TX",
    "wof:name":"Franco Images",
    "wof:placetype":"venue"
},
  "geometry": {"coordinates":[-98.559466,29.453835],"type":"Point"}
}