{
  "type": "Feature",
  "properties": {
    "iso:country":"US",
    "sg:address":"106 N Getty St",
    "sg:city":"Uvalde",
    "sg:classifiers":[
        {
            "category":"Utilities",
            "subcategory":"Mobile Phone",
            "type":"Services"
        }
    ],
    "sg:phone":"+1 830 279 0750",
    "sg:postcode":"78801",
    "sg:province":"TX",
    "sg:tags":[
        "telephone",
        "cellular"
    ],
    "wof:name":"Cingular Wireless",
    "wof:placetype":"venue"
},
  "geometry": {"coordinates":[-99.78635300000001,29.210222],"type":"Point"}
}