{
  "type": "Feature",
  "properties": {
    "iso:country":"US",
    "sg:address":"1101 Northscape Dr Ste A",
    "sg:city":"Austin",
    "sg:classifiers":[
        {
            "category":"Personal",
            "type":"Services"
        }
    ],
    "sg:phone":"+1 512 945 6797",
    "sg:postcode":"78753",
    "sg:province":"TX",
    "sg:tags":[
        "mover"
    ],
    "wof:name":"On Time Moving Company",
    "wof:placetype":"venue"
},
  "geometry": {"coordinates":[-95.36208999999999,29.754085],"type":"Point"}
}