{
  "type": "Feature",
  "properties": {
    "iso:country":"US",
    "sg:address":"3906 Palm St",
    "sg:city":"Houston",
    "sg:classifiers":[
        {
            "category":"Banks & Credit Unions",
            "subcategory":"Financial Services",
            "type":"Services"
        }
    ],
    "sg:phone":"+1 713 522 4633",
    "sg:postcode":"77004",
    "sg:province":"TX",
    "sg:tags":[
        "investor"
    ],
    "wof:name":"Oasis Funding",
    "wof:placetype":"venue"
},
  "geometry": {"coordinates":[-95.350655,29.712351],"type":"Point"}
}