{
  "type": "Feature",
  "properties": {
    "iso:country":"US",
    "sg:address":"106 N Hampton Rd",
    "sg:city":"De Soto",
    "sg:classifiers":[
        {
            "category":"Professional",
            "subcategory":"Accounting & Tax Preparation",
            "type":"Services"
        }
    ],
    "sg:phone":"+1 972 223 3040",
    "sg:postcode":"75115",
    "sg:province":"TX",
    "wof:name":"John Kerby",
    "wof:placetype":"venue"
},
  "geometry": {"coordinates":[-96.856877,32.59121],"type":"Point"}
}