{
  "type": "Feature",
  "properties": {
    "iso:country":"US",
    "sg:address":"653 Raven Ln",
    "sg:city":"Coppell",
    "sg:classifiers":[
        {
            "category":"Manufacturing",
            "subcategory":"Printing",
            "type":"Manufacturing & Wholesale Goods"
        }
    ],
    "sg:phone":"+1 214 676 8016",
    "sg:postcode":"75019",
    "sg:province":"TX",
    "sg:tags":[
        "book"
    ],
    "wof:name":"Wonder of Words",
    "wof:placetype":"venue"
},
  "geometry": {"coordinates":[-96.97600799999999,32.967515],"type":"Point"}
}