{
  "type": "Feature",
  "properties": {
    "iso:country":"US",
    "sg:address":"248 S Leggett Dr",
    "sg:city":"Abilene",
    "sg:classifiers":[
        {
            "category":"Education",
            "subcategory":"Dance Studio",
            "type":"Public Place"
        }
    ],
    "sg:phone":"+1 325 672 6468",
    "sg:postcode":"79605",
    "sg:province":"TX",
    "sg:tags":[
        "instruction",
        "hall",
        "dancing"
    ],
    "wof:name":"Turning Pointe Academy Perf",
    "wof:placetype":"venue"
},
  "geometry": {"coordinates":[-99.77044100000001,32.450575],"type":"Point"}
}