{
  "type": "Feature",
  "properties": {
    "iso:country":"US",
    "sg:address":"4022 Rainier St",
    "sg:city":"Irving",
    "sg:classifiers":[
        {
            "category":"Organizations",
            "subcategory":"Religious Organization",
            "type":"Services"
        }
    ],
    "sg:phone":"+1 972 255 8757",
    "sg:postcode":"75062",
    "sg:province":"TX",
    "sg:tags":[
        "monastery",
        "convent"
    ],
    "wof:name":"Sisters-Holy Family-Nazareth",
    "wof:placetype":"venue"
},
  "geometry": {"coordinates":[-97.002448,32.840604],"type":"Point"}
}