{
  "type": "Feature",
  "properties": {
    "iso:country":"US",
    "sg:address":"724 E Moore Ave",
    "sg:city":"Terrell",
    "sg:classifiers":[
        {
            "category":"Social Services",
            "type":"Services"
        },
        {
            "category":"Professional",
            "subcategory":"Employment Agencies",
            "type":"Services"
        },
        {
            "category":"Organizations",
            "subcategory":"Community Association",
            "type":"Services"
        }
    ],
    "sg:phone":"+1 972 524 2025",
    "sg:postcode":"75160",
    "sg:province":"TX",
    "sg:tags":[
        "club",
        "workers'",
        "placement",
        "volunteer"
    ],
    "wof:name":"The Getaway Club",
    "wof:placetype":"venue"
},
  "geometry": {"coordinates":[-96.269378,32.735434],"type":"Point"}
}