{
  "type": "Feature",
  "properties": {
    "iso:country":"US",
    "sg:address":"1616 S University Dr",
    "sg:city":"Nacogdoches",
    "sg:classifiers":[
        {
            "category":"Government",
            "subcategory":"Office",
            "type":"Public Place"
        }
    ],
    "sg:phone":"+1 936 559 9502",
    "sg:postcode":"75961",
    "sg:province":"TX",
    "wof:name":"Hot Mix Lab",
    "wof:placetype":"venue"
},
  "geometry": {"coordinates":[-94.647116,31.586386],"type":"Point"}
}