{
  "type": "Feature",
  "properties": {
    "iso:country":"US",
    "sg:address":"11700 Sterling Panorama Ter",
    "sg:city":"Austin",
    "sg:classifiers":[
        {
            "category":"Professional",
            "subcategory":"Art Services",
            "type":"Services"
        }
    ],
    "sg:phone":"+1 505 780 4783",
    "sg:postcode":"78738",
    "sg:province":"TX",
    "sg:tags":[
        "photographer"
    ],
    "sg:website":"www.norahlevinephotography.com/",
    "wof:name":"Norah Levine Photography",
    "wof:placetype":"venue"
},
  "geometry": {"coordinates":[-97.918629,30.312543],"type":"Point"}
}