{
  "type": "Feature",
  "properties": {
    "iso:country":"US",
    "sg:address":"2100 Regional Medical Dr",
    "sg:city":"Wharton",
    "sg:classifiers":[
        {
            "category":"Professional",
            "type":"Services"
        }
    ],
    "sg:phone":"+1 979 532 1749",
    "sg:postcode":"77488",
    "sg:province":"TX",
    "wof:name":"Open Mri of Wharton",
    "wof:placetype":"venue"
},
  "geometry": {"coordinates":[-96.11735899999999,29.325791],"type":"Point"}
}