{
  "type": "Feature",
  "properties": {
    "iso:country":"US",
    "sg:address":"601 S Cherry Ln",
    "sg:city":"White Settlement",
    "sg:classifiers":[
        {
            "category":"Organizations",
            "subcategory":"Professional Association",
            "type":"Services"
        }
    ],
    "sg:phone":"+1 817 246 1121",
    "sg:postcode":"76108",
    "sg:province":"TX",
    "sg:tags":[
        "chambers",
        "commerce"
    ],
    "wof:name":"White Settlement Area Chamber",
    "wof:placetype":"venue"
},
  "geometry": {"coordinates":[-97.45107299999999,32.754911],"type":"Point"}
}