{
  "type": "Feature",
  "properties": {
    "iso:country":"US",
    "sg:address":"12821 Lantana Ridge Ct",
    "sg:city":"Austin",
    "sg:classifiers":[
        {
            "category":"Wholesale",
            "subcategory":"Durable Goods & Equipment",
            "type":"Manufacturing & Wholesale Goods"
        }
    ],
    "sg:phone":"+1 512 266 1717",
    "sg:postcode":"78732",
    "sg:province":"TX",
    "sg:tags":[
        "exporter"
    ],
    "wof:name":"Amy's Designer Decocrete",
    "wof:placetype":"venue"
},
  "geometry": {"coordinates":[-97.899602,30.370855],"type":"Point"}
}