{
  "type": "Feature",
  "properties": {
    "iso:country":"US",
    "sg:address":"621 S R L Thornton Fwy",
    "sg:city":"Dallas",
    "sg:classifiers":[
        {
            "category":"Autos & Motor Vehicles",
            "subcategory":"Automobile Sales",
            "type":"Retail Goods"
        }
    ],
    "sg:phone":"+1 214 800 6565",
    "sg:postcode":"75203",
    "sg:province":"TX",
    "sg:tags":[
        "car",
        "used"
    ],
    "wof:name":"Freeman Hyundai of Dallas",
    "wof:placetype":"venue"
},
  "geometry": {"coordinates":[-96.813103,32.745701],"type":"Point"}
}