{
  "type": "Feature",
  "properties": {
    "iso:country":"US",
    "sg:address":"1006 N Milam St",
    "sg:city":"Seguin",
    "sg:classifiers":[
        {
            "category":"Shopping",
            "type":"Retail Goods"
        }
    ],
    "sg:phone":"+1 830 372 1776",
    "sg:postcode":"78155",
    "sg:province":"TX",
    "sg:tags":[
        "miscellaneous",
        "store"
    ],
    "wof:name":"Toland's Touch",
    "wof:placetype":"venue"
},
  "geometry": {"coordinates":[-97.962374,29.577656],"type":"Point"}
}