{
  "type": "Feature",
  "properties": {
    "iso:country":"US",
    "sg:address":"2305 Aberdeen Dr",
    "sg:city":"Bedford",
    "sg:classifiers":[
        {
            "category":"Real Estate",
            "subcategory":"Real Estate Agent",
            "type":"Services"
        }
    ],
    "sg:phone":"+1 817 354 3196",
    "sg:postcode":"76021",
    "sg:province":"TX",
    "sg:tags":[
        "agency",
        "rental"
    ],
    "wof:name":"MPR Partners",
    "wof:placetype":"venue"
},
  "geometry": {"coordinates":[-97.127467,32.844103],"type":"Point"}
}