{
  "type": "Feature",
  "properties": {
    "iso:country":"US",
    "sg:address":"1333 Judiway St",
    "sg:city":"Houston",
    "sg:classifiers":[
        {
            "category":"Organizations",
            "subcategory":"Religious Organization",
            "type":"Services"
        }
    ],
    "sg:phone":"+1 713 686 0788",
    "sg:postcode":"77018",
    "sg:province":"TX",
    "wof:name":"Church Of Christ",
    "wof:placetype":"venue"
},
  "geometry": {"coordinates":[-95.435318,29.82058],"type":"Point"}
}