{
  "type": "Feature",
  "properties": {
    "iso:country":"US",
    "sg:address":"1020 W Park Blvd",
    "sg:city":"Plano",
    "sg:classifiers":[
        {
            "category":"Retail",
            "subcategory":"Laundry & Dry Cleaning",
            "type":"Services"
        }
    ],
    "sg:phone":"+1 972 422 9644",
    "sg:postcode":"75075",
    "sg:province":"TX",
    "sg:tags":[
        "garment",
        "coin",
        "agent"
    ],
    "wof:name":"Baha Capital Enterprises Inc",
    "wof:placetype":"venue"
},
  "geometry": {"coordinates":[-96.713877,33.026872],"type":"Point"}
}