{
  "type": "Feature",
  "properties": {
    "iso:country":"US",
    "sg:address":"3375 E Illinois Ave",
    "sg:city":"Dallas",
    "sg:classifiers":[
        {
            "category":"Autos & Motor Vehicles",
            "subcategory":"Auto Supplies",
            "type":"Retail Goods"
        }
    ],
    "sg:phone":"+1 214 374 2667",
    "sg:postcode":"75216",
    "sg:province":"TX",
    "sg:tags":[
        "tire"
    ],
    "wof:name":"Espinosa's Tire Shop",
    "wof:placetype":"venue"
},
  "geometry": {"coordinates":[-96.76947699999999,32.715833],"type":"Point"}
}