{
  "type": "Feature",
  "properties": {
    "iso:country":"US",
    "sg:address":"125 W Main St Ste F",
    "sg:city":"Humble",
    "sg:phone":"+1 281 785 0800",
    "sg:postcode":"77338",
    "sg:province":"TX",
    "wof:name":"Ldh Services",
    "wof:placetype":"venue"
},
  "geometry": {"coordinates":[-95.26855399999999,29.999242],"type":"Point"}
}