{
  "type": "Feature",
  "properties": {
    "iso:country":"US",
    "sg:address":"7540 Thistle Ln",
    "sg:city":"Dallas",
    "sg:classifiers":[
        {
            "category":"Education",
            "subcategory":"Library",
            "type":"Public Place"
        }
    ],
    "sg:phone":"+1 214 816 2058",
    "sg:postcode":"75240",
    "sg:province":"TX",
    "wof:name":"Pinwheels Branch Jafra Cosmeti",
    "wof:placetype":"venue"
},
  "geometry": {"coordinates":[-96.77767900000001,32.926497],"type":"Point"}
}