{
  "type": "Feature",
  "properties": {
    "iso:country":"US",
    "sg:address":"6210 Hidden Springs Ln",
    "sg:city":"Garland",
    "sg:classifiers":[
        {
            "category":"Professional",
            "type":"Services"
        }
    ],
    "sg:phone":"+1 972 496 5227",
    "sg:postcode":"75044",
    "sg:province":"TX",
    "wof:name":"Save Service Inc",
    "wof:placetype":"venue"
},
  "geometry": {"coordinates":[-96.6812,32.971819],"type":"Point"}
}