{
  "type": "Feature",
  "properties": {
    "iso:country":"US",
    "sg:address":"1400 E Grayson St",
    "sg:city":"San Antonio",
    "sg:classifiers":[
        {
            "category":"Government",
            "subcategory":"Office",
            "type":"Public Place"
        }
    ],
    "sg:phone":"+1 210 221 9960",
    "sg:postcode":"78208",
    "sg:province":"TX",
    "sg:tags":[
        "national",
        "security"
    ],
    "wof:name":"Amedd Prsnell Prpnent Drctrate",
    "wof:placetype":"venue"
},
  "geometry": {"coordinates":[-98.462344,29.443171],"type":"Point"}
}