{
  "type": "Feature",
  "properties": {
    "iso:country":"US",
    "sg:address":"2113 Suanne Dr",
    "sg:city":"Tyler",
    "sg:classifiers":[
        {
            "category":"Health Services",
            "subcategory":"Clinic",
            "type":"Services"
        }
    ],
    "sg:phone":"+1 903 535 9169",
    "sg:postcode":"75701",
    "sg:province":"TX",
    "wof:name":"Valuecare Health Svc",
    "wof:placetype":"venue"
},
  "geometry": {"coordinates":[-95.27396899999999,32.328334],"type":"Point"}
}