{
  "type": "Feature",
  "properties": {
    "iso:country":"US",
    "sg:address":"10744 Braun Rd",
    "sg:city":"San Antonio",
    "sg:classifiers":[
        {
            "category":"Professional",
            "subcategory":"Management & Consulting",
            "type":"Services"
        }
    ],
    "sg:phone":"+1 210 688 6222",
    "sg:postcode":"78254",
    "sg:province":"TX",
    "sg:tags":[
        "consultant"
    ],
    "wof:name":"Rothschild Judy Consultant",
    "wof:placetype":"venue"
},
  "geometry": {"coordinates":[-98.701641,29.541969],"type":"Point"}
}