{
  "type": "Feature",
  "properties": {
    "iso:country":"US",
    "sg:address":"1052 Washington St",
    "sg:city":"Mission",
    "sg:classifiers":[
        {
            "category":"Organizations",
            "subcategory":"Religious Organization",
            "type":"Services"
        }
    ],
    "sg:phone":"+1 956 585 2325",
    "sg:postcode":"78572",
    "sg:province":"TX",
    "wof:name":"St John Church",
    "wof:placetype":"venue"
},
  "geometry": {"coordinates":[-98.34286299999999,26.222497],"type":"Point"}
}