{
  "type": "Feature",
  "properties": {
    "iso:country":"US",
    "sg:address":"8424 Mojave Trl",
    "sg:city":"Fort Worth",
    "sg:classifiers":[
        {
            "category":"Retail",
            "subcategory":"Veterinary Services",
            "type":"Services"
        }
    ],
    "sg:phone":"+1 817 244 3895",
    "sg:postcode":"76116",
    "sg:province":"TX",
    "sg:tags":[
        "veterinarian"
    ],
    "wof:name":"Barney A Stumbo DVM",
    "wof:placetype":"venue"
},
  "geometry": {"coordinates":[-97.465411,32.733597],"type":"Point"}
}