{
  "type": "Feature",
  "properties": {
    "iso:country":"US",
    "sg:address":"4101 McEwen Rd",
    "sg:city":"Dallas",
    "sg:classifiers":[
        {
            "category":"Health Services",
            "subcategory":"Clinic",
            "type":"Services"
        }
    ],
    "sg:phone":"+1 972 448 4566",
    "sg:postcode":"75244",
    "sg:province":"TX",
    "sg:tags":[
        "home",
        "care"
    ],
    "wof:name":"Gentiva Health Services",
    "wof:placetype":"venue"
},
  "geometry": {"coordinates":[-96.841702,32.929998],"type":"Point"}
}