{
  "type": "Feature",
  "properties": {
    "iso:country":"US",
    "sg:address":"209 W Texas St",
    "sg:city":"Mesquite",
    "sg:classifiers":[
        {
            "category":"Shopping",
            "subcategory":"Mobile Phones",
            "type":"Retail Goods"
        }
    ],
    "sg:phone":"+1 972 290 9111",
    "sg:postcode":"75149",
    "sg:province":"TX",
    "sg:website":"www.metroweld.com",
    "wof:name":"Metroplex Welding Supply Inc",
    "wof:placetype":"venue"
},
  "geometry": {"coordinates":[-96.6007,32.7677],"type":"Point"}
}