{
  "type": "Feature",
  "properties": {
    "iso:country":"US",
    "sg:address":"825 W Francis Ave",
    "sg:city":"Pampa",
    "sg:classifiers":[
        {
            "category":"Professional",
            "subcategory":"Accounting & Tax Preparation",
            "type":"Services"
        }
    ],
    "sg:phone":"+1 806 665 3471",
    "sg:postcode":"79065",
    "sg:province":"TX",
    "sg:tags":[
        "billing"
    ],
    "wof:name":"Fellers Bookkeeping & Tax Service",
    "wof:placetype":"venue"
},
  "geometry": {"coordinates":[-100.971035,35.533914],"type":"Point"}
}