{
  "type": "Feature",
  "properties": {
    "iso:country":"US",
    "sg:address":"1110 S Timberland Dr",
    "sg:city":"Lufkin",
    "sg:classifiers":[
        {
            "category":"Travel",
            "subcategory":"Hotels & Motels",
            "type":"Entertainment"
        }
    ],
    "sg:phone":"+1 936 637 7850",
    "sg:postcode":"75901",
    "sg:province":"TX",
    "sg:tags":[
        "operation"
    ],
    "sg:website":"http://www.motel6.com",
    "wof:name":"Motel 6",
    "wof:placetype":"venue"
},
  "geometry": {"coordinates":[-94.7256,31.325803],"type":"Point"}
}