{
  "type": "Feature",
  "properties": {
    "iso:country":"US",
    "sg:address":"2108 Bitter Creek Dr",
    "sg:city":"Austin",
    "sg:classifiers":[
        {
            "category":"Professional",
            "subcategory":"Detective & Security Services",
            "type":"Services"
        }
    ],
    "sg:phone":"+1 512 804 0739",
    "sg:postcode":"78744",
    "sg:province":"TX",
    "sg:tags":[
        "bodyguard",
        "patrol",
        "guard"
    ],
    "wof:name":"Neptune Northeast Patrol",
    "wof:placetype":"venue"
},
  "geometry": {"coordinates":[-97.760762,30.183818],"type":"Point"}
}