{
  "type": "Feature",
  "properties": {
    "iso:country":"US",
    "sg:address":"401 Ridgehaven Pl",
    "sg:city":"Richardson",
    "sg:classifiers":[
        {
            "category":"Wholesale",
            "subcategory":"Jewelry",
            "type":"Manufacturing & Wholesale Goods"
        }
    ],
    "sg:phone":"+1 972 231 8920",
    "sg:postcode":"75080",
    "sg:province":"TX",
    "sg:tags":[
        "stone"
    ],
    "wof:name":"Courtenay Co",
    "wof:placetype":"venue"
},
  "geometry": {"coordinates":[-96.728864,32.979742],"type":"Point"}
}