{
  "type": "Feature",
  "properties": {
    "iso:country":"US",
    "sg:address":"5041 Alabama St",
    "sg:city":"El Paso",
    "sg:classifiers":[
        {
            "category":"Real Estate",
            "subcategory":"Real Estate Operator",
            "type":"Services"
        }
    ],
    "sg:phone":"+1 915 565 2703",
    "sg:postcode":"79930",
    "sg:province":"TX",
    "sg:tags":[
        "apartment",
        "complex"
    ],
    "wof:name":"High Vista Apartments",
    "wof:placetype":"venue"
},
  "geometry": {"coordinates":[-106.46545,31.822397],"type":"Point"}
}