{
  "type": "Feature",
  "properties": {
    "iso:country":"US",
    "sg:address":"1229 Woodhaven Blvd",
    "sg:city":"Fort Worth",
    "sg:classifiers":[
        {
            "category":"Restaurant",
            "type":"Food & Drink"
        }
    ],
    "sg:phone":"+1 817 496 6767",
    "sg:postcode":"76112",
    "sg:province":"TX",
    "sg:tags":[
        "eating"
    ],
    "wof:name":"Rickshaw Chinese Restaurant",
    "wof:placetype":"venue"
},
  "geometry": {"coordinates":[-97.24049599999999,32.762918],"type":"Point"}
}