{
  "type": "Feature",
  "properties": {
    "iso:country":"US",
    "sg:address":"610 San Agustin Ave",
    "sg:city":"Laredo",
    "sg:classifiers":[
        {
            "category":"Shopping",
            "subcategory":"Gifts & Souvenirs",
            "type":"Retail Goods"
        }
    ],
    "sg:phone":"+1 956 727 4107",
    "sg:postcode":"78040",
    "sg:province":"TX",
    "sg:tags":[
        "shop"
    ],
    "wof:name":"C & S Co Inc",
    "wof:placetype":"venue"
},
  "geometry": {"coordinates":[-99.505685,27.505592],"type":"Point"}
}