{
  "type": "Feature",
  "properties": {
    "iso:country":"US",
    "sg:address":"2100 Co Rd 802",
    "sg:city":"Brownsville",
    "sg:classifiers":[
        {
            "category":"Education",
            "subcategory":"Special Training",
            "type":"Public Place"
        }
    ],
    "sg:phone":"+1 956 550 0050",
    "sg:postcode":"78521",
    "sg:province":"TX",
    "sg:tags":[
        "tutoring"
    ],
    "wof:name":"Sylvan Learning Ctr",
    "wof:placetype":"venue"
},
  "geometry": {"coordinates":[-97.474645,25.949901],"type":"Point"}
}