{
  "type": "Feature",
  "properties": {
    "iso:country":"US",
    "sg:address":"14390 Old Humble Pipeline Rd",
    "sg:city":"Conroe",
    "sg:classifiers":[
        {
            "category":"Real Estate",
            "subcategory":"Real Estate Services",
            "type":"Services"
        },
        {
            "category":"Real Estate",
            "subcategory":"Real Estate Agent",
            "type":"Services"
        }
    ],
    "sg:phone":"+1 936 231 5681",
    "sg:postcode":"77302",
    "sg:province":"TX",
    "sg:tags":[
        "buyer",
        "broker"
    ],
    "wof:name":"Time Share Realtors",
    "wof:placetype":"venue"
},
  "geometry": {"coordinates":[-95.392056,30.244649],"type":"Point"}
}