{
  "type": "Feature",
  "properties": {
    "iso:country":"US",
    "sg:address":"201 Westpark Dr N",
    "sg:city":"Mc Kinney",
    "sg:classifiers":[
        {
            "category":"Building & Trades",
            "subcategory":"Plumbing",
            "type":"Services"
        }
    ],
    "sg:phone":"+1 972 562 7778",
    "sg:postcode":"75071",
    "sg:province":"TX",
    "sg:tags":[
        "contractor"
    ],
    "wof:name":"Carter Heating & Air",
    "wof:placetype":"venue"
},
  "geometry": {"coordinates":[-96.642005,33.199863],"type":"Point"}
}