{
  "type": "Feature",
  "properties": {
    "iso:country":"US",
    "sg:address":"315 N Pope St",
    "sg:city":"San Angelo",
    "sg:classifiers":[
        {
            "category":"Building & Trades",
            "subcategory":"Equipment Rental",
            "type":"Services"
        }
    ],
    "sg:phone":"+1 325 653 1496",
    "sg:postcode":"76903",
    "sg:province":"TX",
    "sg:tags":[
        "plant",
        "leasing"
    ],
    "wof:name":"Plantery",
    "wof:placetype":"venue"
},
  "geometry": {"coordinates":[-100.424212,31.470557],"type":"Point"}
}