{
  "type": "Feature",
  "properties": {
    "iso:country":"US",
    "sg:address":"2301 Cleburne St",
    "sg:city":"Houston",
    "sg:classifiers":[
        {
            "category":"Personal",
            "subcategory":"Barber",
            "type":"Services"
        }
    ],
    "sg:phone":"+1 713 528 8022",
    "sg:postcode":"77004",
    "sg:province":"TX",
    "sg:tags":[
        "shop"
    ],
    "wof:name":"Bocard's New Look Barber Shop",
    "wof:placetype":"venue"
},
  "geometry": {"coordinates":[-95.370003,29.7293],"type":"Point"}
}