{
  "type": "Feature",
  "properties": {
    "iso:country":"US",
    "sg:address":"8206 US Hwy 87",
    "sg:city":"San Angelo",
    "sg:classifiers":[
        {
            "category":"Building & Trades",
            "subcategory":"Equipment Rental",
            "type":"Services"
        }
    ],
    "sg:phone":"+1 325 653 1255",
    "sg:postcode":"76901",
    "sg:province":"TX",
    "sg:tags":[
        "movie",
        "retail"
    ],
    "wof:name":"Lets Go To Movies",
    "wof:placetype":"venue"
},
  "geometry": {"coordinates":[-100.55521,31.562554],"type":"Point"}
}