{
  "type": "Feature",
  "properties": {
    "iso:country":"US",
    "sg:address":"2015 Kemp Blvd",
    "sg:city":"Wichita Falls",
    "sg:classifiers":[
        {
            "category":"Shopping",
            "subcategory":"Used Merchandise",
            "type":"Retail Goods"
        }
    ],
    "sg:phone":"+1 940 767 6017",
    "sg:postcode":"76309",
    "sg:province":"TX",
    "sg:tags":[
        "shop",
        "thrift"
    ],
    "wof:name":"Baird's Mrs Thrift Store",
    "wof:placetype":"venue"
},
  "geometry": {"coordinates":[-98.525721,33.892917],"type":"Point"}
}