{
  "type": "Feature",
  "properties": {
    "iso:country":"US",
    "sg:address":"352 E Belt Line Rd",
    "sg:city":"Desoto",
    "sg:classifiers":[
        {
            "category":"Food & Beverages",
            "subcategory":"Bakery",
            "type":"Retail Goods"
        }
    ],
    "sg:phone":"+1 972 274 2177",
    "sg:postcode":"75115",
    "sg:province":"TX",
    "sg:tags":[
        "doughnut"
    ],
    "wof:name":"Westlake Donuts",
    "wof:placetype":"venue"
},
  "geometry": {"coordinates":[-96.8515,32.589642],"type":"Point"}
}