{
  "type": "Feature",
  "properties": {
    "iso:country":"US",
    "sg:address":"514 Emil Zielonka Rd",
    "sg:city":"Yorktown",
    "sg:classifiers":[
        {
            "category":"Shopping",
            "subcategory":"Gifts & Souvenirs",
            "type":"Retail Goods"
        }
    ],
    "sg:phone":"+1 361 564 4164",
    "sg:postcode":"78164",
    "sg:province":"TX",
    "wof:name":"Kathys Kountry Krafts",
    "wof:placetype":"venue"
},
  "geometry": {"coordinates":[-97.401917,28.947878],"type":"Point"}
}