{
  "type": "Feature",
  "properties": {
    "iso:country":"US",
    "sg:address":"1704 N Jackson Rd",
    "sg:city":"Pharr",
    "sg:phone":"+1 956 631 9339",
    "sg:postcode":"78577",
    "sg:province":"TX",
    "sg:tags":[
        "neon",
        "sign"
    ],
    "wof:name":"All-Media Display",
    "wof:placetype":"venue"
},
  "geometry": {"coordinates":[-98.201606,26.213163],"type":"Point"}
}