{
  "type": "Feature",
  "properties": {
    "iso:country":"US",
    "sg:address":"25025 I- 45",
    "sg:city":"The Woodlands",
    "sg:classifiers":[
        {
            "category":"Social Services",
            "type":"Services"
        }
    ],
    "sg:phone":"+1 281 367 0733",
    "sg:postcode":"77380",
    "sg:province":"TX",
    "sg:tags":[
        "counselor",
        "marriage",
        "family"
    ],
    "wof:name":"Associated Mental Health Ctr",
    "wof:placetype":"venue"
},
  "geometry": {"coordinates":[-95.443252,30.124603],"type":"Point"}
}