{
  "type": "Feature",
  "properties": {
    "iso:country":"US",
    "sg:address":"16970 Dallas Parkway Suite 500",
    "sg:city":"Dallas",
    "sg:classifiers":[
        {
            "category":"Professional",
            "subcategory":"Lawyer & Legal Services",
            "type":"Services"
        }
    ],
    "sg:phone":"+1 972 248 9550",
    "sg:postcode":"75248",
    "sg:province":"TX",
    "wof:name":"Harden Curtis R Attorney",
    "wof:placetype":"venue"
},
  "geometry": {"coordinates":[-96.82638,32.977956],"type":"Point"}
}