{
  "type": "Feature",
  "properties": {
    "iso:country":"US",
    "sg:address":"3 Sandalwood Dr",
    "sg:city":"Houston",
    "sg:classifiers":[
        {
            "category":"Professional",
            "subcategory":"Engineering",
            "type":"Services"
        }
    ],
    "sg:phone":"+1 713 334 7530",
    "sg:postcode":"77024",
    "sg:province":"TX",
    "sg:tags":[
        "engineer"
    ],
    "wof:name":"Long International",
    "wof:placetype":"venue"
},
  "geometry": {"coordinates":[-95.532476,29.753009],"type":"Point"}
}