{
  "type": "Feature",
  "properties": {
    "iso:country":"US",
    "sg:address":"1700 State Hwy 323 NE",
    "sg:city":"Tyler",
    "sg:classifiers":[
        {
            "category":"Personal",
            "subcategory":"Beauty Salon",
            "type":"Services"
        }
    ],
    "sg:phone":"+1 903 566 4186",
    "sg:postcode":"75708",
    "sg:province":"TX",
    "sg:tags":[
        "shop"
    ],
    "wof:name":"Profiles Hairstyling Inc",
    "wof:placetype":"venue"
},
  "geometry": {"coordinates":[-95.268055,32.36124],"type":"Point"}
}