{
  "type": "Feature",
  "properties": {
    "iso:country":"US",
    "sg:address":"4008 Myerwood Ln",
    "sg:city":"Dallas",
    "sg:classifiers":[
        {
            "category":"Health Services",
            "subcategory":"Optometrist",
            "type":"Services"
        }
    ],
    "sg:phone":"+1 972 247 5685",
    "sg:postcode":"75244",
    "sg:province":"TX",
    "wof:name":"Thurman J Ray O Dprofessi",
    "wof:placetype":"venue"
},
  "geometry": {"coordinates":[-96.838517,32.912935],"type":"Point"}
}