{
  "type": "Feature",
  "properties": {
    "iso:country":"US",
    "sg:address":"1707 Sunset Blvd",
    "sg:city":"Houston",
    "sg:classifiers":[
        {
            "category":"Health Services",
            "subcategory":"Doctor",
            "type":"Services"
        }
    ],
    "sg:phone":"+1 713 526 5511",
    "sg:postcode":"77005",
    "sg:province":"TX",
    "sg:tags":[
        "clinic"
    ],
    "wof:name":"Medical Clinic-Houston",
    "wof:placetype":"venue"
},
  "geometry": {"coordinates":[-95.403261,29.722977],"type":"Point"}
}