{
  "type": "Feature",
  "properties": {
    "iso:country":"US",
    "sg:address":"14102 Transportation Ave",
    "sg:city":"Laredo",
    "sg:classifiers":[
        {
            "category":"Travel",
            "subcategory":"Travel Agent",
            "type":"Entertainment"
        }
    ],
    "sg:phone":"+1 956 717 9233",
    "sg:postcode":"78045",
    "sg:province":"TX",
    "sg:tags":[
        "passenger",
        "transportation",
        "arrangement"
    ],
    "wof:name":"Naviotex Inc",
    "wof:placetype":"venue"
},
  "geometry": {"coordinates":[-99.526954,27.618646],"type":"Point"}
}