{
  "type": "Feature",
  "properties": {
    "iso:country":"US",
    "sg:address":"5130 Montana Ave",
    "sg:city":"El Paso",
    "sg:classifiers":[
        {
            "category":"Shopping",
            "subcategory":"Clothing, Apparel, & Fashions",
            "type":"Retail Goods"
        }
    ],
    "sg:phone":"+1 915 772 9696",
    "sg:postcode":"79903",
    "sg:province":"TX",
    "wof:name":"Pepe Fashions",
    "wof:placetype":"venue"
},
  "geometry": {"coordinates":[-106.426699,31.783541],"type":"Point"}
}