{
  "type": "Feature",
  "properties": {
    "iso:country":"US",
    "sg:address":"18964 State Hwy 155",
    "sg:city":"Flint",
    "sg:classifiers":[
        {
            "category":"Shopping",
            "type":"Retail Goods"
        }
    ],
    "sg:phone":"+1 903 825 2211",
    "sg:postcode":"75762",
    "sg:province":"TX",
    "sg:tags":[
        "equipment",
        "farming",
        "tractor"
    ],
    "wof:name":"Mixon Tractor and Equipment",
    "wof:placetype":"venue"
},
  "geometry": {"coordinates":[-95.423269,32.20504],"type":"Point"}
}