{
  "type": "Feature",
  "properties": {
    "iso:country":"US",
    "sg:address":"826 W Veterans Memorial Blvd",
    "sg:city":"Killeen",
    "sg:classifiers":[
        {
            "category":"Insurance",
            "subcategory":"Insurance Agent",
            "type":"Services"
        },
        {
            "category":"Insurance",
            "subcategory":"Hazard Insurance",
            "type":"Services"
        },
        {
            "category":"Insurance",
            "subcategory":"Title Insurance",
            "type":"Services"
        }
    ],
    "sg:phone":"+1 254 519 3444",
    "sg:postcode":"76541",
    "sg:province":"TX",
    "sg:tags":[
        "malpractice",
        "business",
        "auto",
        "recreational",
        "commercial",
        "homeowner",
        "liability",
        "motorcycle",
        "renter",
        "vehicle",
        "property",
        "casualty"
    ],
    "sg:website":"http://www.getaiunited.com",
    "wof:name":"Ai United Insurance",
    "wof:placetype":"venue"
},
  "geometry": {"coordinates":[-97.739761,31.119942],"type":"Point"}
}