{
  "type": "Feature",
  "properties": {
    "iso:country":"US",
    "sg:address":"1089 Esplanada Cir",
    "sg:city":"El Paso",
    "sg:classifiers":[
        {
            "category":"Real Estate",
            "subcategory":"Real Estate Agent",
            "type":"Services"
        }
    ],
    "sg:phone":"+1 915 585 1001",
    "sg:postcode":"79932",
    "sg:province":"TX",
    "wof:name":"Blanco Real Estate",
    "wof:placetype":"venue"
},
  "geometry": {"coordinates":[-106.626835,31.864034],"type":"Point"}
}