{
  "type": "Feature",
  "properties": {
    "iso:country":"US",
    "sg:address":"5809 Albert Dr",
    "sg:city":"Humble",
    "sg:classifiers":[
        {
            "category":"Building & Trades",
            "subcategory":"Electrical",
            "type":"Services"
        }
    ],
    "sg:phone":"+1 281 441 4100",
    "sg:postcode":"77396",
    "sg:province":"TX",
    "sg:tags":[
        "industrial",
        "electrician",
        "contractors-commercial",
        "electric"
    ],
    "wof:name":"Delta Electric Company",
    "wof:placetype":"venue"
},
  "geometry": {"coordinates":[-95.303378,29.941352],"type":"Point"}
}