{
  "type": "Feature",
  "properties": {
    "iso:country":"US",
    "sg:address":"1114 Alexandria Ave",
    "sg:city":"Garland",
    "sg:classifiers":[
        {
            "category":"Building & Trades",
            "subcategory":"Cleaning & Sanitation",
            "type":"Services"
        }
    ],
    "sg:phone":"+1 972 496 3909",
    "sg:postcode":"75040",
    "sg:province":"TX",
    "sg:tags":[
        "maintenance"
    ],
    "wof:name":"Queens International Svc",
    "wof:placetype":"venue"
},
  "geometry": {"coordinates":[-96.618357,32.935144],"type":"Point"}
}