{
  "type": "Feature",
  "properties": {
    "iso:country":"US",
    "sg:address":"215 Five Oaks Dr",
    "sg:city":"San Antonio",
    "sg:classifiers":[
        {
            "category":"Manufacturing",
            "subcategory":"Metals",
            "type":"Manufacturing & Wholesale Goods"
        }
    ],
    "sg:phone":"+1 210 804 1019",
    "sg:postcode":"78209",
    "sg:province":"TX",
    "sg:tags":[
        "hardware",
        "mfg"
    ],
    "wof:name":"John Clamp Real Estate",
    "wof:placetype":"venue"
},
  "geometry": {"coordinates":[-98.440956,29.508175],"type":"Point"}
}