{
  "type": "Feature",
  "properties": {
    "iso:country":"US",
    "sg:address":"2 Azalea Trail Ln",
    "sg:city":"Bellaire",
    "sg:classifiers":[
        {
            "category":"Building & Trades",
            "subcategory":"Construction",
            "type":"Services"
        }
    ],
    "sg:phone":"+1 713 666 1312",
    "sg:postcode":"77401",
    "sg:province":"TX",
    "sg:tags":[
        "nonresidential"
    ],
    "wof:name":"J D Engineering & Construction",
    "wof:placetype":"venue"
},
  "geometry": {"coordinates":[-95.460132,29.700684],"type":"Point"}
}