{
  "type": "Feature",
  "properties": {
    "iso:country":"US",
    "sg:address":"7606 Magnolia St",
    "sg:city":"Houston",
    "sg:classifiers":[
        {
            "category":"Professional",
            "type":"Services"
        }
    ],
    "sg:phone":"+1 713 921 0273",
    "sg:postcode":"77023",
    "sg:province":"TX",
    "sg:tags":[
        "establishment"
    ],
    "wof:name":"Galveston Houston & Henderson",
    "wof:placetype":"venue"
},
  "geometry": {"coordinates":[-95.292717,29.718828],"type":"Point"}
}