{
  "type": "Feature",
  "properties": {
    "iso:country":"US",
    "sg:address":"1207 N Main St",
    "sg:city":"Mcallen",
    "sg:classifiers":[
        {
            "category":"Social Services",
            "subcategory":"Child Care",
            "type":"Services"
        }
    ],
    "sg:phone":"+1 956 630 2273",
    "sg:postcode":"78501",
    "sg:province":"TX",
    "sg:tags":[
        "day"
    ],
    "wof:name":"Tender Care",
    "wof:placetype":"venue"
},
  "geometry": {"coordinates":[-98.232692,26.214418],"type":"Point"}
}