{
  "type": "Feature",
  "properties": {
    "iso:country":"US",
    "sg:address":"124 Eagle Dr",
    "sg:city":"Denton",
    "sg:classifiers":[
        {
            "category":"Personal",
            "subcategory":"Beauty Salon",
            "type":"Services"
        }
    ],
    "sg:phone":"+1 940 387 7376",
    "sg:postcode":"76201",
    "sg:province":"TX",
    "sg:tags":[
        "shop"
    ],
    "wof:name":"Hair Station",
    "wof:placetype":"venue"
},
  "geometry": {"coordinates":[-97.132865,33.206481],"type":"Point"}
}