{
  "type": "Feature",
  "properties": {
    "iso:country":"US",
    "sg:address":"3409 Twin Creeks Dr",
    "sg:city":"Cleburne",
    "sg:classifiers":[
        {
            "category":"Building & Trades",
            "subcategory":"Construction",
            "type":"Services"
        }
    ],
    "sg:phone":"+1 817 558 4300",
    "sg:postcode":"76031",
    "sg:province":"TX",
    "sg:tags":[
        "commercial",
        "contractor"
    ],
    "wof:name":"Skiles Construction Inc",
    "wof:placetype":"venue"
},
  "geometry": {"coordinates":[-97.32386700000001,32.430782],"type":"Point"}
}