{
  "type": "Feature",
  "properties": {
    "iso:country":"US",
    "sg:address":"9600 Palo Pinto Rd",
    "sg:city":"Fort Worth",
    "sg:classifiers":[
        {
            "category":"Travel",
            "subcategory":"Hotels & Motels",
            "type":"Entertainment"
        }
    ],
    "sg:phone":"+1 817 244 1594",
    "sg:postcode":"76116",
    "sg:province":"TX",
    "sg:tags":[
        "recreational",
        "lodging"
    ],
    "wof:name":"Lamariage Inn",
    "wof:placetype":"venue"
},
  "geometry": {"coordinates":[-97.49187999999999,32.72506],"type":"Point"}
}