{
  "type": "Feature",
  "properties": {
    "iso:country":"US",
    "sg:address":"4701 Ayers St",
    "sg:city":"Corpus Christi",
    "sg:classifiers":[
        {
            "category":"Banks & Credit Unions",
            "subcategory":"Bank",
            "type":"Services"
        }
    ],
    "sg:phone":"+1 361 852 1242",
    "sg:postcode":"78415",
    "sg:province":"TX",
    "sg:tags":[
        "cashing",
        "check"
    ],
    "wof:name":"Money Box",
    "wof:placetype":"venue"
},
  "geometry": {"coordinates":[-97.424246,27.740426],"type":"Point"}
}