{
  "type": "Feature",
  "properties": {
    "iso:country":"US",
    "sg:address":"10815 Grissom Ln",
    "sg:city":"Dallas",
    "sg:classifiers":[
        {
            "category":"Retail",
            "subcategory":"Repair Shop",
            "type":"Services"
        }
    ],
    "sg:phone":"+1 972 241 1992",
    "sg:postcode":"75229",
    "sg:province":"TX",
    "sg:tags":[
        "machine",
        "refrigeration",
        "ice"
    ],
    "wof:name":"Schindler Refrigeration Co",
    "wof:placetype":"venue"
},
  "geometry": {"coordinates":[-96.886976,32.898172],"type":"Point"}
}