{
  "type": "Feature",
  "properties": {
    "iso:country":"US",
    "sg:address":"26014 Oakridge Dr",
    "sg:city":"Spring",
    "sg:classifiers":[
        {
            "category":"Professional",
            "type":"Services"
        }
    ],
    "sg:phone":"+1 281 363 2845",
    "sg:postcode":"77380",
    "sg:province":"TX",
    "sg:tags":[
        "establishment"
    ],
    "wof:name":"Produmex Corp",
    "wof:placetype":"venue"
},
  "geometry": {"coordinates":[-95.447776,30.138029],"type":"Point"}
}