{
  "type": "Feature",
  "properties": {
    "iso:country":"US",
    "sg:address":"9410 Walnut St",
    "sg:city":"Dallas",
    "sg:classifiers":[
        {
            "category":"Food & Beverages",
            "subcategory":"Groceries & Convenience Stores",
            "type":"Retail Goods"
        }
    ],
    "sg:phone":"+1 972 907 2990",
    "sg:postcode":"75243",
    "sg:province":"TX",
    "wof:name":"Market Grocery",
    "wof:placetype":"venue"
},
  "geometry": {"coordinates":[-96.736293,32.923554],"type":"Point"}
}