{
  "type": "Feature",
  "properties": {
    "iso:country":"US",
    "sg:address":"2731 Timberleaf Dr",
    "sg:city":"Carrollton",
    "sg:classifiers":[
        {
            "category":"Shopping",
            "subcategory":"Catalog Store",
            "type":"Retail Goods"
        }
    ],
    "sg:phone":"+1 972 416 5640",
    "sg:postcode":"75006",
    "sg:province":"TX",
    "sg:tags":[
        "mail",
        "order",
        "online"
    ],
    "sg:website":"http://www.pogosplace.com",
    "wof:name":"Pogos Place",
    "wof:placetype":"venue"
},
  "geometry": {"coordinates":[-96.85778000000001,32.978931],"type":"Point"}
}