{
  "type": "Feature",
  "properties": {
    "iso:country":"US",
    "sg:address":"3303 Mesquite Dr",
    "sg:city":"Sugar Land",
    "sg:classifiers":[
        {
            "category":"Building & Trades",
            "subcategory":"Construction",
            "type":"Services"
        }
    ],
    "sg:phone":"+1 281 469 0669",
    "sg:postcode":"77479",
    "sg:province":"TX",
    "sg:tags":[
        "special",
        "contractor"
    ],
    "wof:name":"Kitchen By Design",
    "wof:placetype":"venue"
},
  "geometry": {"coordinates":[-95.60185799999999,29.575174],"type":"Point"}
}