{
  "type": "Feature",
  "properties": {
    "iso:country":"US",
    "sg:address":"1828 N Travis St",
    "sg:city":"Sherman",
    "sg:classifiers":[
        {
            "category":"Retail",
            "subcategory":"Car Wash",
            "type":"Services"
        }
    ],
    "sg:phone":"+1 903 893 4990",
    "sg:postcode":"75092",
    "sg:province":"TX",
    "sg:tags":[
        "carwash"
    ],
    "wof:name":"A & R Karwash",
    "wof:placetype":"venue"
},
  "geometry": {"coordinates":[-96.614983,33.654532],"type":"Point"}
}