{
  "type": "Feature",
  "properties": {
    "iso:country":"US",
    "sg:address":"308 E Travis St",
    "sg:city":"Fredericksburg",
    "sg:classifiers":[
        {
            "category":"Banks & Credit Unions",
            "subcategory":"Financial Services",
            "type":"Services"
        }
    ],
    "sg:phone":"+1 830 990 8182",
    "sg:postcode":"78624",
    "sg:province":"TX",
    "sg:tags":[
        "company",
        "holding"
    ],
    "wof:name":"Bluebird Holdings LLC",
    "wof:placetype":"venue"
},
  "geometry": {"coordinates":[-98.86594599999999,30.275083],"type":"Point"}
}