{
  "type": "Feature",
  "properties": {
    "iso:country":"US",
    "sg:address":"24430 I- 45",
    "sg:city":"Spring",
    "sg:classifiers":[
        {
            "category":"Home & Garden",
            "subcategory":"Home Furnishings",
            "type":"Retail Goods"
        }
    ],
    "sg:phone":"+1 281 364 9399",
    "sg:postcode":"77386",
    "sg:province":"TX",
    "sg:tags":[
        "venetian",
        "blind"
    ],
    "wof:name":"Wood Blind & Shutter Factory",
    "wof:placetype":"venue"
},
  "geometry": {"coordinates":[-95.436134,30.111068],"type":"Point"}
}