{
  "type": "Feature",
  "properties": {
    "iso:country":"US",
    "sg:address":"900 S Wayside Dr",
    "sg:city":"Houston",
    "sg:classifiers":[
        {
            "category":"Cinema",
            "subcategory":"Movie Rental",
            "type":"Entertainment"
        }
    ],
    "sg:phone":"+1 713 926 2296",
    "sg:postcode":"77023",
    "sg:province":"TX",
    "sg:tags":[
        "video",
        "game",
        "leasing"
    ],
    "wof:name":"Game Crazy",
    "wof:placetype":"venue"
},
  "geometry": {"coordinates":[-95.309246,29.729488],"type":"Point"}
}