{
  "type": "Feature",
  "properties": {
    "iso:country":"US",
    "sg:address":"7229 Helsem Bnd",
    "sg:city":"Dallas",
    "sg:classifiers":[
        {
            "category":"Banks & Credit Unions",
            "subcategory":"Investment Brokerage",
            "type":"Services"
        }
    ],
    "sg:phone":"+1 972 458 1313",
    "sg:postcode":"75230",
    "sg:province":"TX",
    "sg:tags":[
        "investing"
    ],
    "wof:name":"Columbia Capital Resources",
    "wof:placetype":"venue"
},
  "geometry": {"coordinates":[-96.78769699999999,32.919701],"type":"Point"}
}