{
  "type": "Feature",
  "properties": {
    "iso:country":"US",
    "sg:address":"118 Nicar St",
    "sg:city":"Houston",
    "sg:classifiers":[
        {
            "category":"Manufacturing",
            "subcategory":"Tools & Machinery",
            "type":"Manufacturing & Wholesale Goods"
        }
    ],
    "sg:phone":"+1 281 448 6191",
    "sg:postcode":"77037",
    "sg:province":"TX",
    "sg:tags":[
        "industrial",
        "mfg"
    ],
    "wof:name":"Sun Down Machine Works",
    "wof:placetype":"venue"
},
  "geometry": {"coordinates":[-95.393387,29.900298],"type":"Point"}
}