{
  "type": "Feature",
  "properties": {
    "iso:country":"US",
    "sg:address":"226 Co Rd 912",
    "sg:city":"Brazoria",
    "sg:classifiers":[
        {
            "category":"Food & Beverages",
            "subcategory":"Bakery",
            "type":"Retail Goods"
        }
    ],
    "sg:phone":"+1 979 798 5181",
    "sg:postcode":"77422",
    "sg:province":"TX",
    "wof:name":"Kds Creations",
    "wof:placetype":"venue"
},
  "geometry": {"coordinates":[-95.5497,29.042807],"type":"Point"}
}