{
  "type": "Feature",
  "properties": {
    "iso:country":"US",
    "sg:address":"3223 Nebraska Ave",
    "sg:city":"Dallas",
    "sg:classifiers":[
        {
            "category":"Building & Trades",
            "subcategory":"Construction",
            "type":"Services"
        }
    ],
    "sg:phone":"+1 214 375 5419",
    "sg:postcode":"75216",
    "sg:province":"TX",
    "sg:tags":[
        "contractor"
    ],
    "wof:name":"Tomas Tile Services",
    "wof:placetype":"venue"
},
  "geometry": {"coordinates":[-96.80833699999999,32.70468],"type":"Point"}
}