{
  "type": "Feature",
  "properties": {
    "iso:country":"US",
    "sg:address":"7317 S Hulen St",
    "sg:city":"Fort Worth",
    "sg:classifiers":[
        {
            "category":"Travel",
            "subcategory":"Travel Agent",
            "type":"Entertainment"
        }
    ],
    "sg:phone":"+1 817 346 6757",
    "sg:postcode":"76133",
    "sg:province":"TX",
    "sg:tags":[
        "passenger",
        "agency",
        "transportation",
        "arrangement"
    ],
    "wof:name":"Las Vegas Agency",
    "wof:placetype":"venue"
},
  "geometry": {"coordinates":[-97.395882,32.639823],"type":"Point"}
}