{
  "type": "Feature",
  "properties": {
    "iso:country":"US",
    "sg:address":"1841 Gentle Way",
    "sg:city":"Prosper",
    "sg:classifiers":[
        {
            "category":"Communications",
            "subcategory":"Film & Video Production",
            "type":"Services"
        }
    ],
    "sg:phone":"+1 972 562 6708",
    "sg:postcode":"75078",
    "sg:province":"TX",
    "sg:tags":[
        "motion",
        "picture"
    ],
    "wof:name":"Unboxed Memories",
    "wof:placetype":"venue"
},
  "geometry": {"coordinates":[-96.757414,33.260412],"type":"Point"}
}