{
  "type": "Feature",
  "properties": {
    "iso:country":"US",
    "sg:address":"1530 Cottonwood Ln",
    "sg:city":"Weatherford",
    "sg:classifiers":[
        {
            "category":"Building & Trades",
            "subcategory":"Construction",
            "type":"Services"
        }
    ],
    "sg:phone":"+1 817 594 3516",
    "sg:postcode":"76086",
    "sg:province":"TX",
    "sg:tags":[
        "industrial"
    ],
    "wof:name":"Custom Storage Buildings",
    "wof:placetype":"venue"
},
  "geometry": {"coordinates":[-97.828582,32.751059],"type":"Point"}
}