{
  "type": "Feature",
  "properties": {
    "iso:country":"US",
    "sg:address":"2720 N Main St",
    "sg:city":"Liberty",
    "sg:classifiers":[
        {
            "category":"Professional",
            "type":"Services"
        }
    ],
    "sg:phone":"+1 936 336 3616",
    "sg:postcode":"77575",
    "sg:province":"TX",
    "wof:name":"Betty Behrns Pa",
    "wof:placetype":"venue"
},
  "geometry": {"coordinates":[-94.77894499999999,30.076357],"type":"Point"}
}