{
  "type": "Feature",
  "properties": {
    "iso:country":"US",
    "sg:address":"12482 Abrams Rd",
    "sg:city":"Dallas",
    "sg:classifiers":[
        {
            "category":"Health Services",
            "subcategory":"Clinic",
            "type":"Services"
        }
    ],
    "sg:phone":"+1 214 575 5790",
    "sg:postcode":"75243",
    "sg:province":"TX",
    "wof:name":"Henry's Health Care",
    "wof:placetype":"venue"
},
  "geometry": {"coordinates":[-96.735451,32.917859],"type":"Point"}
}