{
  "type": "Feature",
  "properties": {
    "iso:country":"US",
    "sg:address":"12300 North Fwy 500",
    "sg:city":"Houston",
    "sg:classifiers":[
        {
            "category":"Shopping",
            "subcategory":"Department Store",
            "type":"Retail Goods"
        }
    ],
    "sg:phone":"+1 281 872 2002",
    "sg:postcode":"77060",
    "sg:province":"TX",
    "wof:name":"Mothorhood In Macys",
    "wof:placetype":"venue"
},
  "geometry": {"coordinates":[-95.41525900000001,29.945869],"type":"Point"}
}