{
  "type": "Feature",
  "properties": {
    "iso:country":"US",
    "sg:address":"2502 Sunset Blvd",
    "sg:city":"Houston",
    "sg:classifiers":[
        {
            "category":"Building & Trades",
            "subcategory":"Construction",
            "type":"Services"
        }
    ],
    "sg:phone":"+1 713 533 0025",
    "sg:postcode":"77005",
    "sg:province":"TX",
    "sg:tags":[
        "house"
    ],
    "wof:name":"Savannah Bellaire Home Bldrs",
    "wof:placetype":"venue"
},
  "geometry": {"coordinates":[-95.418485,29.723176],"type":"Point"}
}