{
  "type": "Feature",
  "properties": {
    "iso:country":"US",
    "sg:address":"346 W Pleasant Run Rd",
    "sg:city":"Lancaster",
    "sg:classifiers":[
        {
            "category":"Personal",
            "subcategory":"Beauty Salon",
            "type":"Services"
        }
    ],
    "sg:phone":"+1 972 218 7070",
    "sg:postcode":"75146",
    "sg:province":"TX",
    "sg:tags":[
        "shop"
    ],
    "wof:name":"Solars Nails",
    "wof:placetype":"venue"
},
  "geometry": {"coordinates":[-96.761501,32.60394],"type":"Point"}
}