{
  "type": "Feature",
  "properties": {
    "iso:country":"US",
    "sg:address":"225 E Colorado Blvd",
    "sg:city":"Dallas",
    "sg:classifiers":[
        {
            "category":"Food & Beverages",
            "subcategory":"Groceries & Convenience Stores",
            "type":"Retail Goods"
        }
    ],
    "sg:phone":"+1 214 943 1535",
    "sg:postcode":"75203",
    "sg:province":"TX",
    "sg:website":"www.7-eleven.com",
    "wof:name":"7-Eleven",
    "wof:placetype":"venue"
},
  "geometry": {"coordinates":[-96.82132799999999,32.758809],"type":"Point"}
}