{
  "type": "Feature",
  "properties": {
    "iso:country":"US",
    "sg:address":"2415 Midway Rd",
    "sg:city":"Carrollton",
    "sg:classifiers":[
        {
            "category":"Restaurant",
            "type":"Food & Drink"
        }
    ],
    "sg:phone":"+1 214 357 0248",
    "sg:postcode":"75006",
    "sg:province":"TX",
    "sg:tags":[
        "beverage"
    ],
    "wof:name":"Richland Co",
    "wof:placetype":"venue"
},
  "geometry": {"coordinates":[-96.843119,32.979112],"type":"Point"}
}