{
  "type": "Feature",
  "properties": {
    "iso:country":"US",
    "sg:address":"906 Tartan Trl",
    "sg:city":"Lewisville",
    "sg:classifiers":[
        {
            "category":"Real Estate",
            "subcategory":"Real Estate Services",
            "type":"Services"
        },
        {
            "category":"Real Estate",
            "subcategory":"Real Estate Agent",
            "type":"Services"
        }
    ],
    "sg:phone":"+1 972 318 0764",
    "sg:postcode":"75077",
    "sg:province":"TX",
    "sg:tags":[
        "buyer",
        "broker"
    ],
    "wof:name":"Depriest Real Estate",
    "wof:placetype":"venue"
},
  "geometry": {"coordinates":[-97.07485,33.079709],"type":"Point"}
}