{
  "type": "Feature",
  "properties": {
    "iso:country":"US",
    "sg:address":"3250 Woodhollow Cir",
    "sg:city":"Abilene",
    "sg:classifiers":[
        {
            "category":"Professional",
            "subcategory":"Business Services",
            "type":"Services"
        }
    ],
    "sg:phone":"+1 325 692 2077",
    "sg:postcode":"79606",
    "sg:province":"TX",
    "wof:name":"Jacks Properties",
    "wof:placetype":"venue"
},
  "geometry": {"coordinates":[-99.76664599999999,32.383677],"type":"Point"}
}