{
  "type": "Feature",
  "properties": {
    "iso:country":"US",
    "sg:address":"8800 Katy Fwy",
    "sg:city":"Houston",
    "sg:classifiers":[
        {
            "category":"Health Services",
            "subcategory":"Doctor",
            "type":"Services"
        }
    ],
    "sg:phone":"+1 713 407 3000",
    "sg:postcode":"77024",
    "sg:province":"TX",
    "sg:tags":[
        "medical"
    ],
    "wof:name":"MCA Research Inc",
    "wof:placetype":"venue"
},
  "geometry": {"coordinates":[-95.51237500000001,29.784378],"type":"Point"}
}