{
  "type": "Feature",
  "properties": {
    "iso:country":"US",
    "sg:address":"308 Ellen Trout Dr",
    "sg:city":"Lufkin",
    "sg:classifiers":[
        {
            "category":"Manufacturing",
            "subcategory":"Metals",
            "type":"Manufacturing & Wholesale Goods"
        }
    ],
    "sg:phone":"+1 936 639 3281",
    "sg:postcode":"75904",
    "sg:province":"TX",
    "sg:tags":[
        "electroplating"
    ],
    "wof:name":"Cyber Shield",
    "wof:placetype":"venue"
},
  "geometry": {"coordinates":[-94.71151999999999,31.371208],"type":"Point"}
}