{
  "type": "Feature",
  "properties": {
    "iso:country":"US",
    "sg:address":"119 N Texas Ave",
    "sg:city":"Hereford",
    "sg:phone":"+1 806 272 4546",
    "sg:postcode":"79045",
    "sg:province":"TX",
    "sg:tags":[
        "vegetable",
        "farm"
    ],
    "wof:name":"Barrett Potato Farms",
    "wof:placetype":"venue"
},
  "geometry": {"coordinates":[-102.409265,34.825262],"type":"Point"}
}