{
  "type": "Feature",
  "properties": {
    "iso:country":"US",
    "sg:address":"1303 W Belt Line Rd Ste 201",
    "sg:city":"Carrollton",
    "sg:classifiers":[
        {
            "category":"Shopping",
            "subcategory":"Stationery & Office Supplies",
            "type":"Retail Goods"
        }
    ],
    "sg:phone":"+1 214 342 1463",
    "sg:postcode":"75006",
    "sg:province":"TX",
    "sg:tags":[
        "equipment"
    ],
    "sg:website":"www.officeresourcegroup.com",
    "wof:name":"OFFICE RESOURCE GROUP",
    "wof:placetype":"venue"
},
  "geometry": {"coordinates":[-96.911666,32.952757],"type":"Point"}
}