{
  "type": "Feature",
  "properties": {
    "iso:country":"US",
    "sg:address":"6203 Edgeware Pl",
    "sg:city":"Amarillo",
    "sg:classifiers":[
        {
            "category":"Professional",
            "type":"Services"
        }
    ],
    "sg:phone":"+1 806 355 1999",
    "sg:postcode":"79109",
    "sg:province":"TX",
    "wof:name":"Tirath Ram LP",
    "wof:placetype":"venue"
},
  "geometry": {"coordinates":[-101.90461000000001,35.139838],"type":"Point"}
}