{
  "type": "Feature",
  "properties": {
    "iso:country":"US",
    "sg:address":"1600 Spiderlily Vw",
    "sg:city":"Cedar Park",
    "sg:classifiers":[
        {
            "category":"Professional",
            "subcategory":"Computer Services",
            "type":"Services"
        }
    ],
    "sg:phone":"+1 512 250 9844",
    "sg:postcode":"78613",
    "sg:province":"TX",
    "wof:name":"Creative Computer Solutions",
    "wof:placetype":"venue"
},
  "geometry": {"coordinates":[-97.82947299999999,30.463714],"type":"Point"}
}