{
  "type": "Feature",
  "properties": {
    "iso:country":"US",
    "sg:address":"3006 25th St",
    "sg:city":"Lubbock",
    "sg:classifiers":[
        {
            "category":"Building & Trades",
            "subcategory":"Construction",
            "type":"Services"
        }
    ],
    "sg:phone":"+1 806 785 3908",
    "sg:postcode":"79410",
    "sg:province":"TX",
    "sg:tags":[
        "general"
    ],
    "wof:name":"Eric Everett Renovations",
    "wof:placetype":"venue"
},
  "geometry": {"coordinates":[-101.881169,33.571641],"type":"Point"}
}