{
  "type": "Feature",
  "properties": {
    "iso:country":"US",
    "sg:address":"5000 N 23rd St",
    "sg:city":"Mcallen",
    "sg:classifiers":[
        {
            "category":"Shopping",
            "type":"Retail Goods"
        }
    ],
    "sg:phone":"+1 956 683 7171",
    "sg:postcode":"78504",
    "sg:province":"TX",
    "sg:tags":[
        "telephone",
        "cellular"
    ],
    "wof:name":"Southern Connection",
    "wof:placetype":"venue"
},
  "geometry": {"coordinates":[-98.237666,26.250179],"type":"Point"}
}