{
  "type": "Feature",
  "properties": {
    "iso:country":"US",
    "sg:address":"501 Birdwell Ln",
    "sg:city":"Big Spring",
    "sg:classifiers":[
        {
            "category":"Personal",
            "subcategory":"Beauty Salon",
            "type":"Services"
        }
    ],
    "sg:phone":"+1 432 263 4609",
    "sg:postcode":"79720",
    "sg:province":"TX",
    "sg:tags":[
        "shop"
    ],
    "wof:name":"Quitas Hair Fashions",
    "wof:placetype":"venue"
},
  "geometry": {"coordinates":[-101.45372,32.257913],"type":"Point"}
}