{
  "type": "Feature",
  "properties": {
    "iso:country":"US",
    "sg:address":"309 W Crawford St",
    "sg:city":"Denison",
    "sg:classifiers":[
        {
            "category":"Building & Trades",
            "subcategory":"Equipment Rental",
            "type":"Services"
        }
    ],
    "sg:phone":"+1 903 464 9138",
    "sg:postcode":"75020",
    "sg:province":"TX",
    "sg:tags":[
        "audio",
        "leasing"
    ],
    "wof:name":"Douglasound",
    "wof:placetype":"venue"
},
  "geometry": {"coordinates":[-96.539948,33.753621],"type":"Point"}
}