{
  "type": "Feature",
  "properties": {
    "iso:country":"US",
    "sg:address":"16815 Springhill Dr",
    "sg:city":"San Antonio",
    "sg:classifiers":[
        {
            "category":"Professional",
            "subcategory":"Computer Services",
            "type":"Services"
        }
    ],
    "sg:phone":"+1 210 494 6021",
    "sg:postcode":"78232",
    "sg:province":"TX",
    "sg:tags":[
        "consultant",
        "designer"
    ],
    "wof:name":"Idea Farmer Jake Maymar",
    "wof:placetype":"venue"
},
  "geometry": {"coordinates":[-98.468248,29.59392],"type":"Point"}
}