{
  "type": "Feature",
  "properties": {
    "iso:country":"US",
    "sg:address":"2321 S Belt Line Rd",
    "sg:city":"Grand Prairie",
    "sg:classifiers":[
        {
            "category":"Professional",
            "subcategory":"Lawyer & Legal Services",
            "type":"Services"
        }
    ],
    "sg:phone":"+1 972 264 4000",
    "sg:postcode":"75051",
    "sg:province":"TX",
    "sg:tags":[
        "attorney"
    ],
    "wof:name":"Randall Scott Law Office",
    "wof:placetype":"venue"
},
  "geometry": {"coordinates":[-96.994249,32.710656],"type":"Point"}
}