{
  "type": "Feature",
  "properties": {
    "iso:country":"US",
    "sg:address":"7454 C F Hawn Fwy",
    "sg:city":"Dallas",
    "sg:classifiers":[
        {
            "category":"Retail",
            "subcategory":"Auto Repair",
            "type":"Services"
        }
    ],
    "sg:phone":"+1 214 391 1556",
    "sg:postcode":"75217",
    "sg:province":"TX",
    "sg:tags":[
        "body",
        "automobile",
        "painting"
    ],
    "wof:name":"Grove Collision",
    "wof:placetype":"venue"
},
  "geometry": {"coordinates":[-96.698278,32.72354],"type":"Point"}
}