{
  "type": "Feature",
  "properties": {
    "iso:country":"US",
    "sg:address":"5440 Hitcher Bend",
    "sg:city":"Austin",
    "sg:classifiers":[
        {
            "category":"Professional",
            "type":"Services"
        }
    ],
    "sg:phone":"+1 512 301 7983",
    "sg:postcode":"78749",
    "sg:province":"TX",
    "sg:tags":[
        "consultant",
        "educational"
    ],
    "wof:name":"Rimer Mendell",
    "wof:placetype":"venue"
},
  "geometry": {"coordinates":[-97.866876,30.208523],"type":"Point"}
}