{
  "type": "Feature",
  "properties": {
    "iso:country":"US",
    "sg:address":"4695 Juniper St",
    "sg:city":"Brownsville",
    "sg:classifiers":[
        {
            "category":"Freight",
            "type":"Transportation"
        }
    ],
    "sg:phone":"+1 956 466 6929",
    "sg:postcode":"78526",
    "sg:province":"TX",
    "sg:tags":[
        "arrangement"
    ],
    "wof:name":"VIP Packaging",
    "wof:placetype":"venue"
},
  "geometry": {"coordinates":[-97.491191,25.974117],"type":"Point"}
}