{
  "type": "Feature",
  "properties": {
    "iso:country":"US",
    "sg:address":"4124 N Taylor Rd",
    "sg:city":"Mcallen",
    "sg:classifiers":[
        {
            "category":"Building & Trades",
            "subcategory":"Construction",
            "type":"Services"
        }
    ],
    "sg:phone":"+1 956 687 1972",
    "sg:postcode":"78504",
    "sg:province":"TX",
    "sg:tags":[
        "general",
        "contractor"
    ],
    "sg:website":"www.riovalleyconstruction.com",
    "wof:name":"Rio Valley Construction Inc",
    "wof:placetype":"venue"
},
  "geometry": {"coordinates":[-98.27079999999999,26.251141],"type":"Point"}
}