{
  "type": "Feature",
  "properties": {
    "iso:country":"US",
    "sg:address":"3703 Shady Creek Dr S",
    "sg:city":"Arlington",
    "sg:classifiers":[
        {
            "category":"Social Services",
            "type":"Services"
        }
    ],
    "sg:phone":"+1 817 275 8086",
    "sg:postcode":"76013",
    "sg:province":"TX",
    "sg:tags":[
        "consulting",
        "management"
    ],
    "wof:name":"Murray Group",
    "wof:placetype":"venue"
},
  "geometry": {"coordinates":[-97.166247,32.729288],"type":"Point"}
}