{
  "type": "Feature",
  "properties": {
    "iso:country":"US",
    "sg:address":"125 N Willis St",
    "sg:city":"Abilene",
    "sg:classifiers":[
        {
            "category":"Banks & Credit Unions",
            "subcategory":"Investment Brokerage",
            "type":"Services"
        },
        {
            "category":"Banks & Credit Unions",
            "subcategory":"Bank",
            "type":"Services"
        },
        {
            "category":"Banks & Credit Unions",
            "subcategory":"Financial Services",
            "type":"Services"
        }
    ],
    "sg:phone":"+1 325 672 4108",
    "sg:postcode":"79603",
    "sg:province":"TX",
    "sg:tags":[
        "mutual",
        "retirement",
        "broker",
        "fund",
        "planning",
        "security",
        "bond",
        "stock"
    ],
    "sg:website":"http://www.edwardjones.com/en_US/fa/index.html&CIRN=306082",
    "wof:name":"Edward Jones - Financial Advisor: COLE F WILSON",
    "wof:placetype":"venue"
},
  "geometry": {"coordinates":[-99.763901,32.451826],"type":"Point"}
}