{
  "type": "Feature",
  "properties": {
    "iso:country":"US",
    "sg:address":"4273 I- 35 N",
    "sg:city":"Waco",
    "sg:classifiers":[
        {
            "category":"Restaurant",
            "type":"Food & Drink"
        }
    ],
    "sg:phone":"+1 254 799 0900",
    "sg:postcode":"76705",
    "sg:province":"TX",
    "sg:tags":[
        "shop",
        "coffee",
        "eating"
    ],
    "wof:name":"Starbucks",
    "wof:placetype":"venue"
},
  "geometry": {"coordinates":[-97.106308,31.60653],"type":"Point"}
}