{
  "type": "Feature",
  "properties": {
    "iso:country":"US",
    "sg:address":"5226 W Ledbetter Dr",
    "sg:city":"Dallas",
    "sg:classifiers":[
        {
            "category":"Professional",
            "subcategory":"Advertising",
            "type":"Services"
        }
    ],
    "sg:phone":"+1 972 709 0371",
    "sg:postcode":"75236",
    "sg:province":"TX",
    "wof:name":"O-Kay Marketing",
    "wof:placetype":"venue"
},
  "geometry": {"coordinates":[-96.91426300000001,32.691079],"type":"Point"}
}