{
  "type": "Feature",
  "properties": {
    "iso:country":"US",
    "sg:address":"6200 Gilbert Rd",
    "sg:city":"Austin",
    "sg:classifiers":[
        {
            "category":"Professional",
            "type":"Services"
        }
    ],
    "sg:phone":"+1 512 276 7200",
    "sg:postcode":"78724",
    "sg:province":"TX",
    "wof:name":"Grass L Prairie L",
    "wof:placetype":"venue"
},
  "geometry": {"coordinates":[-97.586501,30.26785],"type":"Point"}
}