{
  "type": "Feature",
  "properties": {
    "iso:country":"US",
    "sg:address":"5001 Spring Valley Rd",
    "sg:city":"Dallas",
    "sg:classifiers":[
        {
            "category":"Banks & Credit Unions",
            "subcategory":"Investment Brokerage",
            "type":"Services"
        },
        {
            "category":"Professional",
            "subcategory":"Management & Consulting",
            "type":"Services"
        }
    ],
    "sg:phone":"+1 972 702 0010",
    "sg:postcode":"75244",
    "sg:province":"TX",
    "sg:tags":[
        "consultant",
        "planning",
        "financial",
        "advisory"
    ],
    "wof:name":"Managed Assets Corp",
    "wof:placetype":"venue"
},
  "geometry": {"coordinates":[-96.825773,32.939597],"type":"Point"}
}