{
  "type": "Feature",
  "properties": {
    "iso:country":"US",
    "sg:address":"6633 E Highway 290",
    "sg:city":"Austin",
    "sg:classifiers":[
        {
            "category":"Organizations",
            "subcategory":"Religious Organization",
            "type":"Services"
        }
    ],
    "sg:phone":"+1 512 451 2062",
    "sg:postcode":"78723",
    "sg:province":"TX",
    "wof:name":"Crop-Church World Service",
    "wof:placetype":"venue"
},
  "geometry": {"coordinates":[-97.693854,30.320785],"type":"Point"}
}