{
  "type": "Feature",
  "properties": {
    "iso:country":"US",
    "sg:address":"3125 Southwestern Blvd",
    "sg:city":"Dallas",
    "sg:classifiers":[
        {
            "category":"Banks & Credit Unions",
            "subcategory":"Bank",
            "type":"Services"
        }
    ],
    "sg:phone":"+1 214 739 2870",
    "sg:postcode":"75225",
    "sg:province":"TX",
    "sg:tags":[
        "mortgage"
    ],
    "wof:name":"Mockingbird Mortgage LLC",
    "wof:placetype":"venue"
},
  "geometry": {"coordinates":[-96.782399,32.85699],"type":"Point"}
}