{
  "type": "Feature",
  "properties": {
    "iso:country":"US",
    "sg:address":"26719 Kuykendahl Rd",
    "sg:city":"Tomball",
    "sg:classifiers":[
        {
            "category":"Professional",
            "subcategory":"Management & Consulting",
            "type":"Services"
        }
    ],
    "sg:phone":"+1 281 290 9090",
    "sg:postcode":"77375",
    "sg:province":"TX",
    "sg:tags":[
        "marketing"
    ],
    "wof:name":"Mbm Inc",
    "wof:placetype":"venue"
},
  "geometry": {"coordinates":[-95.552083,30.138891],"type":"Point"}
}