{
  "type": "Feature",
  "properties": {
    "iso:country":"US",
    "sg:address":"1800 W Greenwood Rd",
    "sg:city":"Mc Kinney",
    "sg:classifiers":[
        {
            "category":"Building & Trades",
            "subcategory":"Construction",
            "type":"Services"
        }
    ],
    "sg:phone":"+1 972 542 8685",
    "sg:postcode":"75069",
    "sg:province":"TX",
    "sg:tags":[
        "nonresidential"
    ],
    "wof:name":"Braz Builders",
    "wof:placetype":"venue"
},
  "geometry": {"coordinates":[-96.631095,33.203784],"type":"Point"}
}