{
  "type": "Feature",
  "properties": {
    "iso:country":"US",
    "sg:address":"1200 Commerce Dr",
    "sg:city":"Plano",
    "sg:classifiers":[
        {
            "category":"Professional",
            "type":"Services"
        }
    ],
    "sg:phone":"+1 972 398 9403",
    "sg:postcode":"75093",
    "sg:province":"TX",
    "sg:tags":[
        "establishment"
    ],
    "wof:name":"Morningstar National",
    "wof:placetype":"venue"
},
  "geometry": {"coordinates":[-96.77068199999999,33.017755],"type":"Point"}
}