{
  "type": "Feature",
  "properties": {
    "iso:country":"US",
    "sg:address":"4330 N Lamar Blvd",
    "sg:city":"Austin",
    "sg:classifiers":[
        {
            "category":"Retail",
            "subcategory":"Veterinary Services",
            "type":"Services"
        }
    ],
    "sg:phone":"+1 512 453 6686",
    "sg:postcode":"78756",
    "sg:province":"TX",
    "sg:tags":[
        "pet",
        "veterinarian",
        "boarding/pet",
        "animal",
        "sitting"
    ],
    "wof:name":"Austin Animal Clinic",
    "wof:placetype":"venue"
},
  "geometry": {"coordinates":[-97.738602,30.3118],"type":"Point"}
}