{
  "type": "Feature",
  "properties": {
    "iso:country":"US",
    "sg:address":"6118 Bayway Dr",
    "sg:city":"Baytown",
    "sg:classifiers":[
        {
            "category":"Wholesale",
            "subcategory":"Auto Parts",
            "type":"Manufacturing & Wholesale Goods"
        }
    ],
    "sg:phone":"+1 281 424 8000",
    "sg:postcode":"77520",
    "sg:province":"TX",
    "sg:tags":[
        "antique",
        "automotive",
        "restoration"
    ],
    "wof:name":"Vintage Friends Inc",
    "wof:placetype":"venue"
},
  "geometry": {"coordinates":[-95.03524400000001,29.755012],"type":"Point"}
}