{
  "type": "Feature",
  "properties": {
    "iso:country":"US",
    "sg:address":"232 Vintage Ln",
    "sg:city":"Laredo",
    "sg:classifiers":[
        {
            "category":"Railroad",
            "type":"Transportation"
        }
    ],
    "sg:phone":"+1 956 753 9203",
    "sg:postcode":"78041",
    "sg:province":"TX",
    "sg:tags":[
        "rail"
    ],
    "wof:name":"T C D Railway Services LLC",
    "wof:placetype":"venue"
},
  "geometry": {"coordinates":[-99.49261199999999,27.560632],"type":"Point"}
}