{
  "type": "Feature",
  "properties": {
    "iso:country":"US",
    "sg:address":"13250 Jake Ct",
    "sg:city":"Burleson",
    "sg:classifiers":[
        {
            "category":"Travel",
            "subcategory":"Hotels & Motels",
            "type":"Entertainment"
        },
        {
            "category":"Retail",
            "subcategory":"Event Space",
            "type":"Services"
        }
    ],
    "sg:phone":"+1 817 426 0396",
    "sg:postcode":"76028",
    "sg:province":"TX",
    "sg:tags":[
        "facility",
        "venue",
        "hall",
        "reception",
        "lodging",
        "corporate",
        "banquet"
    ],
    "sg:website":"www.holidayinnexpress.com",
    "wof:name":"Holiday Inn Express Hotel & Suites Burleson/Ft. Worth",
    "wof:placetype":"venue"
},
  "geometry": {"coordinates":[-97.31657300000001,32.565381],"type":"Point"}
}