{
  "type": "Feature",
  "properties": {
    "iso:country":"US",
    "sg:address":"8802 Kelburn Dr",
    "sg:city":"Houston",
    "sg:classifiers":[
        {
            "category":"Organizations",
            "subcategory":"Religious Organization",
            "type":"Services"
        }
    ],
    "sg:phone":"+1 713 635 3708",
    "sg:postcode":"77016",
    "sg:province":"TX",
    "sg:tags":[
        "church"
    ],
    "wof:name":"Church Of The Living God",
    "wof:placetype":"venue"
},
  "geometry": {"coordinates":[-95.300776,29.843523],"type":"Point"}
}