{
  "type": "Feature",
  "properties": {
    "iso:country":"US",
    "sg:address":"440 Summit Dr",
    "sg:city":"Richardson",
    "sg:classifiers":[
        {
            "category":"Professional",
            "subcategory":"Lawyer & Legal Services",
            "type":"Services"
        }
    ],
    "sg:phone":"+1 972 705 9013",
    "sg:postcode":"75081",
    "sg:province":"TX",
    "wof:name":"Lisas Paralegals",
    "wof:placetype":"venue"
},
  "geometry": {"coordinates":[-96.724746,32.938931],"type":"Point"}
}