{
  "type": "Feature",
  "properties": {
    "iso:country":"US",
    "sg:address":"1901 T B Ellison Pkwy",
    "sg:city":"Port Arthur",
    "sg:classifiers":[
        {
            "category":"Sports & Exercise",
            "subcategory":"Golf",
            "type":"Entertainment"
        }
    ],
    "sg:phone":"+1 409 984 5000",
    "sg:postcode":"77640",
    "sg:province":"TX",
    "sg:tags":[
        "course"
    ],
    "wof:name":"Palms Golf Crse At Pleasure Is",
    "wof:placetype":"venue"
},
  "geometry": {"coordinates":[-93.94578300000001,29.788342],"type":"Point"}
}