{
  "type": "Feature",
  "properties": {
    "iso:country":"US",
    "sg:address":"3174 Waterside Dr",
    "sg:city":"Arlington",
    "sg:classifiers":[
        {
            "category":"Professional",
            "subcategory":"Art Services",
            "type":"Services"
        }
    ],
    "sg:phone":"+1 817 795 7645",
    "sg:postcode":"76012",
    "sg:province":"TX",
    "sg:tags":[
        "commercial",
        "photography",
        "design"
    ],
    "wof:name":"Art Source",
    "wof:placetype":"venue"
},
  "geometry": {"coordinates":[-97.159458,32.755961],"type":"Point"}
}