{
  "type": "Feature",
  "properties": {
    "iso:country":"US",
    "sg:address":"100 W College St",
    "sg:city":"Burkburnett",
    "sg:classifiers":[
        {
            "category":"Government",
            "subcategory":"Office",
            "type":"Public Place"
        }
    ],
    "sg:phone":"+1 940 569 3367",
    "sg:postcode":"76354",
    "sg:province":"TX",
    "sg:tags":[
        "county",
        "taxation"
    ],
    "wof:name":"Wichita County Tax Assessor",
    "wof:placetype":"venue"
},
  "geometry": {"coordinates":[-98.57437,34.093467],"type":"Point"}
}