{
  "type": "Feature",
  "properties": {
    "iso:country":"US",
    "sg:address":"7707 Fannin St Ste 150",
    "sg:city":"Houston",
    "sg:classifiers":[
        {
            "category":"Health Services",
            "subcategory":"Doctor",
            "type":"Services"
        },
        {
            "category":"Health Services",
            "subcategory":"Dentist",
            "type":"Services"
        }
    ],
    "sg:phone":"+1 713 663 6019",
    "sg:postcode":"77054",
    "sg:province":"TX",
    "sg:tags":[
        "surgeon",
        "oral",
        "pediatric"
    ],
    "wof:name":"Phillips Gloria A DDS",
    "wof:placetype":"venue"
},
  "geometry": {"coordinates":[-95.40218900000001,29.690352],"type":"Point"}
}