{
  "type": "Feature",
  "properties": {
    "iso:country":"US",
    "sg:address":"4344 S FM 565",
    "sg:city":"Baytown",
    "sg:classifiers":[
        {
            "category":"Retail",
            "subcategory":"Repair Shop",
            "type":"Services"
        }
    ],
    "sg:phone":"+1 281 383 2906",
    "sg:postcode":"77520",
    "sg:province":"TX",
    "wof:name":"K&D Equine Inc",
    "wof:placetype":"venue"
},
  "geometry": {"coordinates":[-94.850244,29.799038],"type":"Point"}
}