{
  "type": "Feature",
  "properties": {
    "iso:country":"US",
    "sg:address":"3802 Shell Ave",
    "sg:city":"Midland",
    "sg:classifiers":[
        {
            "category":"Shopping",
            "subcategory":"Florist",
            "type":"Retail Goods"
        }
    ],
    "sg:phone":"+1 432 694 9696",
    "sg:postcode":"79707",
    "sg:province":"TX",
    "sg:tags":[
        "shop",
        "gift"
    ],
    "wof:name":"Mildred's Flowers",
    "wof:placetype":"venue"
},
  "geometry": {"coordinates":[-102.134646,32.006208],"type":"Point"}
}