{
  "type": "Feature",
  "properties": {
    "iso:country":"US",
    "sg:address":"1765 Blossom Trl",
    "sg:city":"Plano",
    "sg:classifiers":[
        {
            "category":"Building & Trades",
            "subcategory":"Construction",
            "type":"Services"
        }
    ],
    "sg:phone":"+1 972 422 4356",
    "sg:postcode":"75074",
    "sg:province":"TX",
    "sg:tags":[
        "contractor",
        "mechanical"
    ],
    "wof:name":"Mickey R Murphy",
    "wof:placetype":"venue"
},
  "geometry": {"coordinates":[-96.66114399999999,33.023472],"type":"Point"}
}