{
  "type": "Feature",
  "properties": {
    "iso:country":"US",
    "sg:address":"204 W Avenue D",
    "sg:city":"Killeen",
    "sg:classifiers":[
        {
            "category":"Wholesale",
            "subcategory":"Machinery & Supplies",
            "type":"Manufacturing & Wholesale Goods"
        },
        {
            "category":"Wholesale",
            "subcategory":"Construction Materials",
            "type":"Manufacturing & Wholesale Goods"
        },
        {
            "category":"Home & Garden",
            "subcategory":"Building Materials",
            "type":"Retail Goods"
        }
    ],
    "sg:phone":"+1 254 213 5575",
    "sg:postcode":"76541",
    "sg:province":"TX",
    "sg:tags":[
        "heater",
        "water",
        "pump",
        "part",
        "plumbing",
        "fixtures"
    ],
    "wof:name":"Ham & McCreight Supply Inc",
    "wof:placetype":"venue"
},
  "geometry": {"coordinates":[-97.731375,31.120942],"type":"Point"}
}