{
  "type": "Feature",
  "properties": {
    "iso:country":"US",
    "sg:address":"3811 N Fry Rd",
    "sg:city":"Katy",
    "sg:classifiers":[
        {
            "category":"Fast Food",
            "type":"Food & Drink"
        },
        {
            "category":"Restaurant",
            "type":"Food & Drink"
        }
    ],
    "sg:phone":"+1 281 829 3699",
    "sg:postcode":"77449",
    "sg:province":"TX",
    "sg:tags":[
        "style",
        "pizza",
        "take",
        "family",
        "italian"
    ],
    "sg:website":"http://www.foxspizzaden.com",
    "wof:name":"Fox's Pizza Den",
    "wof:placetype":"venue"
},
  "geometry": {"coordinates":[-95.720032,29.828271],"type":"Point"}
}