{
  "type": "Feature",
  "properties": {
    "iso:country":"US",
    "sg:address":"340 N 4th St",
    "sg:city":"Silsbee",
    "sg:classifiers":[
        {
            "category":"Cinema",
            "subcategory":"Movie Theater",
            "type":"Entertainment"
        }
    ],
    "sg:phone":"+1 409 385 2241",
    "sg:postcode":"77656",
    "sg:province":"TX",
    "wof:name":"Pines Theater",
    "wof:placetype":"venue"
},
  "geometry": {"coordinates":[-94.176185,30.350285],"type":"Point"}
}