{
  "type": "Feature",
  "properties": {
    "iso:country":"US",
    "sg:address":"215 S Main St",
    "sg:city":"Winona",
    "sg:classifiers":[
        {
            "category":"Autos & Motor Vehicles",
            "subcategory":"Motorcycle Sales",
            "type":"Retail Goods"
        }
    ],
    "sg:phone":"+1 903 877 3710",
    "sg:postcode":"75792",
    "sg:province":"TX",
    "wof:name":"Main Street Cycles",
    "wof:placetype":"venue"
},
  "geometry": {"coordinates":[-95.16745299999999,32.488818],"type":"Point"}
}