{
  "type": "Feature",
  "properties": {
    "iso:country":"US",
    "sg:address":"611 S Main St",
    "sg:city":"Grapevine",
    "sg:classifiers":[
        {
            "category":"Banks & Credit Unions",
            "subcategory":"Investment Brokerage",
            "type":"Services"
        },
        {
            "category":"Banks & Credit Unions",
            "subcategory":"Financial Services",
            "type":"Services"
        }
    ],
    "sg:phone":"+1 817 410 4680",
    "sg:postcode":"76051",
    "sg:province":"TX",
    "sg:tags":[
        "investor"
    ],
    "wof:name":"Dana Investments",
    "wof:placetype":"venue"
},
  "geometry": {"coordinates":[-97.078284,32.934928],"type":"Point"}
}