{
  "type": "Feature",
  "properties": {
    "iso:country":"US",
    "sg:address":"2015 US Hwy 90 Alt",
    "sg:city":"Missouri City",
    "sg:classifiers":[
        {
            "category":"Retail",
            "subcategory":"Auto Rental",
            "type":"Services"
        }
    ],
    "sg:phone":"+1 281 403 2122",
    "sg:postcode":"77489",
    "sg:province":"TX",
    "sg:tags":[
        "equipment",
        "r",
        "truck",
        "trailer",
        "utility"
    ],
    "wof:name":"U-Haul",
    "wof:placetype":"venue"
},
  "geometry": {"coordinates":[-95.54490199999999,29.61595],"type":"Point"}
}