{
  "type": "Feature",
  "properties": {
    "iso:country":"US",
    "sg:address":"816 Congress Ave",
    "sg:city":"Austin",
    "sg:classifiers":[
        {
            "category":"Professional",
            "subcategory":"Printing & Photocopies",
            "type":"Services"
        },
        {
            "category":"Professional",
            "subcategory":"Lawyer & Legal Services",
            "type":"Services"
        }
    ],
    "sg:phone":"+1 512 476 5358",
    "sg:postcode":"78701",
    "sg:province":"TX",
    "sg:tags":[
        "photocopying",
        "commercial"
    ],
    "wof:name":"Legal Matters Inc",
    "wof:placetype":"venue"
},
  "geometry": {"coordinates":[-97.741878,30.27072],"type":"Point"}
}