{
  "type": "Feature",
  "properties": {
    "iso:country":"US",
    "sg:address":"317 N Carancahua St",
    "sg:city":"Corpus Christi",
    "sg:classifiers":[
        {
            "category":"Health Services",
            "subcategory":"Nursing And Care Facility",
            "type":"Services"
        }
    ],
    "sg:phone":"+1 361 884 3320",
    "sg:postcode":"78401",
    "sg:province":"TX",
    "sg:tags":[
        "home",
        "convalescent"
    ],
    "wof:name":"Holmgreen Health Ctr",
    "wof:placetype":"venue"
},
  "geometry": {"coordinates":[-97.397578,27.792337],"type":"Point"}
}