{
  "type": "Feature",
  "properties": {
    "iso:country":"US",
    "sg:address":"1607 S Lamar Blvd",
    "sg:city":"Austin",
    "sg:phone":"+1 512 326 5444",
    "sg:postcode":"78704",
    "sg:province":"TX",
    "wof:name":"Affordable Insurance",
    "wof:placetype":"venue"
},
  "geometry": {"coordinates":[-97.765152,30.251221],"type":"Point"}
}