{
  "type": "Feature",
  "properties": {
    "iso:country":"US",
    "sg:address":"1608 Judson Rd",
    "sg:city":"Longview",
    "sg:classifiers":[
        {
            "category":"Food & Beverages",
            "subcategory":"Groceries & Convenience Stores",
            "type":"Retail Goods"
        }
    ],
    "sg:phone":"+1 903 236 0463",
    "sg:postcode":"75601",
    "sg:province":"TX",
    "wof:name":"Honey Stop",
    "wof:placetype":"venue"
},
  "geometry": {"coordinates":[-94.74209399999999,32.521991],"type":"Point"}
}