{
  "type": "Feature",
  "properties": {
    "iso:country":"US",
    "sg:address":"4 Lacewood Ln",
    "sg:city":"Houston",
    "sg:classifiers":[
        {
            "category":"Restaurant",
            "type":"Food & Drink"
        }
    ],
    "sg:phone":"+1 713 266 0404",
    "sg:postcode":"77024",
    "sg:province":"TX",
    "sg:tags":[
        "eating"
    ],
    "wof:name":"5675 Bucknell Drive Inc",
    "wof:placetype":"venue"
},
  "geometry": {"coordinates":[-95.51246999999999,29.759589],"type":"Point"}
}