{
  "type": "Feature",
  "properties": {
    "iso:country":"US",
    "sg:address":"296 Co Rd 1331",
    "sg:city":"Marshall",
    "sg:classifiers":[
        {
            "category":"Shopping",
            "subcategory":"Clothing, Apparel, & Fashions",
            "type":"Retail Goods"
        }
    ],
    "sg:phone":"+1 903 938 2093",
    "sg:postcode":"75686",
    "sg:province":"TX",
    "wof:name":"Breezys Accessories & More",
    "wof:placetype":"venue"
},
  "geometry": {"coordinates":[-94.97710499999999,32.936088],"type":"Point"}
}