{
  "type": "Feature",
  "properties": {
    "iso:country":"US",
    "sg:address":"28303 Huffman Cleveland Rd",
    "sg:city":"Huffman",
    "sg:classifiers":[
        {
            "category":"Professional",
            "subcategory":"Business Services",
            "type":"Services"
        },
        {
            "category":"Professional",
            "subcategory":"Secretarial Services",
            "type":"Services"
        }
    ],
    "sg:phone":"+1 281 324 9121",
    "sg:postcode":"77336",
    "sg:province":"TX",
    "sg:tags":[
        "transcription",
        "medical"
    ],
    "wof:name":"Mutual Progress Inc",
    "wof:placetype":"venue"
},
  "geometry": {"coordinates":[-95.109185,30.064171],"type":"Point"}
}