{
  "type": "Feature",
  "properties": {
    "iso:country":"US",
    "sg:address":"100 Highway 332 W",
    "sg:city":"Lake Jackson",
    "sg:classifiers":[
        {
            "category":"Sports & Exercise",
            "subcategory":"Gym",
            "type":"Entertainment"
        }
    ],
    "sg:phone":"+1 979 297 7697",
    "sg:postcode":"77566",
    "sg:province":"TX",
    "sg:website":"www.powerhousegym.com",
    "wof:name":"Powerhouse Gym",
    "wof:placetype":"venue"
},
  "geometry": {"coordinates":[-95.45622400000001,29.761526],"type":"Point"}
}