{
  "type": "Feature",
  "properties": {
    "iso:country":"US",
    "sg:address":"951 Nasa Pkwy",
    "sg:city":"Houston",
    "sg:classifiers":[
        {
            "category":"Shopping",
            "subcategory":"Jewelry",
            "type":"Retail Goods"
        },
        {
            "category":"Manufacturing",
            "subcategory":"Jewelry",
            "type":"Manufacturing & Wholesale Goods"
        }
    ],
    "sg:phone":"+1 281 480 1081",
    "sg:postcode":"77058",
    "sg:province":"TX",
    "sg:tags":[
        "stone",
        "designer",
        "jewelers-wholesale",
        "watch",
        "jeweler",
        "precious",
        "semi-precious",
        "manufacturer"
    ],
    "wof:name":"J C Jewelers",
    "wof:placetype":"venue"
},
  "geometry": {"coordinates":[-95.107091,29.54561],"type":"Point"}
}