{
  "type": "Feature",
  "properties": {
    "iso:country":"US",
    "sg:address":"215 N Moore Rd",
    "sg:city":"Coppell",
    "sg:classifiers":[
        {
            "category":"Professional",
            "subcategory":"Business Services",
            "type":"Services"
        }
    ],
    "sg:phone":"+1 972 393 1777",
    "sg:postcode":"75019",
    "sg:province":"TX",
    "wof:name":"Harald Mallwitz Commercial Bnk",
    "wof:placetype":"venue"
},
  "geometry": {"coordinates":[-96.97647000000001,32.974424],"type":"Point"}
}