{
  "type": "Feature",
  "properties": {
    "iso:country":"US",
    "sg:address":"1121 W Nasa Rd 1",
    "sg:city":"Webster",
    "sg:classifiers":[
        {
            "category":"Shopping",
            "subcategory":"Clothing, Apparel, & Fashions",
            "type":"Retail Goods"
        }
    ],
    "sg:phone":"+1 281 554 8660",
    "sg:postcode":"77598",
    "sg:province":"TX",
    "sg:tags":[
        "accessory"
    ],
    "wof:name":"Nal",
    "wof:placetype":"venue"
},
  "geometry": {"coordinates":[-95.125238,29.532504],"type":"Point"}
}