{
  "type": "Feature",
  "properties": {
    "iso:country":"US",
    "sg:address":"4016 US Hwy 180 E",
    "sg:city":"Mineral Wells",
    "sg:classifiers":[
        {
            "category":"Mining & Drilling",
            "type":"Manufacturing & Wholesale Goods"
        }
    ],
    "sg:phone":"+1 940 325 5225",
    "sg:postcode":"76067",
    "sg:province":"TX",
    "sg:tags":[
        "field"
    ],
    "wof:name":"Baggett Construction",
    "wof:placetype":"venue"
},
  "geometry": {"coordinates":[-98.06603800000001,32.810646],"type":"Point"}
}