{
  "type": "Feature",
  "properties": {
    "iso:country":"US",
    "sg:address":"2324 Judson Rd",
    "sg:city":"Longview",
    "sg:classifiers":[
        {
            "category":"Home & Garden",
            "subcategory":"Carpets & Floor Coverings",
            "type":"Retail Goods"
        }
    ],
    "sg:phone":"+1 903 242 9600",
    "sg:postcode":"75605",
    "sg:province":"TX",
    "sg:tags":[
        "dealer",
        "rug"
    ],
    "wof:name":"USA Flooring Outlet",
    "wof:placetype":"venue"
},
  "geometry": {"coordinates":[-94.74477899999999,32.537467],"type":"Point"}
}