{
  "type": "Feature",
  "properties": {
    "iso:country":"US",
    "sg:address":"2630 Estates Pkwy",
    "sg:city":"Allen",
    "sg:classifiers":[
        {
            "category":"Building & Trades",
            "subcategory":"Pest Control",
            "type":"Services"
        }
    ],
    "sg:phone":"+1 972 727 4833",
    "sg:postcode":"75002",
    "sg:province":"TX",
    "wof:name":"Complete Pest & Lawn Svc",
    "wof:placetype":"venue"
},
  "geometry": {"coordinates":[-96.617178,33.100211],"type":"Point"}
}