{
  "type": "Feature",
  "properties": {
    "iso:country":"US",
    "sg:address":"8415 Davis Blvd",
    "sg:city":"N Richland Hills",
    "sg:classifiers":[
        {
            "category":"Wholesale",
            "subcategory":"Machinery & Supplies",
            "type":"Manufacturing & Wholesale Goods"
        }
    ],
    "sg:phone":"+1 817 503 7845",
    "sg:postcode":"76180",
    "sg:province":"TX",
    "sg:tags":[
        "packaging"
    ],
    "wof:name":"Quik Drop",
    "wof:placetype":"venue"
},
  "geometry": {"coordinates":[-97.192806,32.905162],"type":"Point"}
}