{
  "type": "Feature",
  "properties": {
    "iso:country":"US",
    "sg:address":"4211 W Lake Houston Pkwy",
    "sg:city":"Kingwood",
    "sg:classifiers":[
        {
            "category":"Restaurant",
            "type":"Food & Drink"
        }
    ],
    "sg:menulink":"http://www.allmenus.com/tx/houston/204163-sonic/menu/",
    "sg:phone":"+1 281 360 4334",
    "sg:postcode":"77339",
    "sg:province":"TX",
    "sg:tags":[
        "burger",
        "american"
    ],
    "wof:name":"Sonic",
    "wof:placetype":"venue"
},
  "geometry": {"coordinates":[-95.18886999999999,30.066727],"type":"Point"}
}