{
  "type": "Feature",
  "properties": {
    "iso:country":"US",
    "sg:address":"9703 Richmond Ave",
    "sg:city":"Houston",
    "sg:classifiers":[
        {
            "category":"Professional",
            "type":"Services"
        }
    ],
    "sg:phone":"+1 713 781 8161",
    "sg:postcode":"77042",
    "sg:province":"TX",
    "sg:tags":[
        "establishment"
    ],
    "wof:name":"Forum Twenty Two Ent LP",
    "wof:placetype":"venue"
},
  "geometry": {"coordinates":[-95.540352,29.727611],"type":"Point"}
}