{
  "type": "Feature",
  "properties": {
    "iso:country":"US",
    "sg:address":"4303 Ruffian Ct",
    "sg:city":"Friendswood",
    "sg:classifiers":[
        {
            "category":"Government",
            "subcategory":"Office",
            "type":"Public Place"
        }
    ],
    "sg:phone":"+1 281 482 1372",
    "sg:postcode":"77546",
    "sg:province":"TX",
    "sg:tags":[
        "management"
    ],
    "wof:name":"Flood Control Solutions I",
    "wof:placetype":"venue"
},
  "geometry": {"coordinates":[-95.17265999999999,29.545191],"type":"Point"}
}