{
  "type": "Feature",
  "properties": {
    "iso:country":"US",
    "sg:address":"17902 FM 1488",
    "sg:city":"Magnolia",
    "sg:classifiers":[
        {
            "category":"Retail",
            "subcategory":"Laundry & Dry Cleaning",
            "type":"Services"
        }
    ],
    "sg:phone":"+1 281 259 8983",
    "sg:postcode":"77354",
    "sg:province":"TX",
    "sg:tags":[
        "drycleaning",
        "plant"
    ],
    "wof:name":"C & D Drycleaners",
    "wof:placetype":"venue"
},
  "geometry": {"coordinates":[-95.739582,30.218683],"type":"Point"}
}