{
  "type": "Feature",
  "properties": {
    "iso:country":"US",
    "sg:address":"6069 Glen Lee Dr",
    "sg:city":"Humble",
    "sg:classifiers":[
        {
            "category":"Professional",
            "type":"Services"
        }
    ],
    "sg:phone":"+1 281 441 2068",
    "sg:postcode":"77396",
    "sg:province":"TX",
    "wof:name":"George S Landscaping Serv",
    "wof:placetype":"venue"
},
  "geometry": {"coordinates":[-95.300662,29.961102],"type":"Point"}
}