{
  "type": "Feature",
  "properties": {
    "iso:country":"US",
    "sg:address":"515 Dresden Dr",
    "sg:city":"San Antonio",
    "sg:classifiers":[
        {
            "category":"Professional",
            "subcategory":"Detective & Security Services",
            "type":"Services"
        }
    ],
    "sg:phone":"+1 210 884 8994",
    "sg:postcode":"78213",
    "sg:province":"TX",
    "sg:tags":[
        "guard"
    ],
    "wof:name":"Diana Kelly",
    "wof:placetype":"venue"
},
  "geometry": {"coordinates":[-98.52552,29.499041],"type":"Point"}
}