{
  "type": "Feature",
  "properties": {
    "iso:country":"US",
    "sg:address":"1504 W Inwood Ave",
    "sg:city":"Orange",
    "sg:classifiers":[
        {
            "category":"Shopping",
            "subcategory":"Florist",
            "type":"Retail Goods"
        }
    ],
    "sg:phone":"+1 409 886 3310",
    "sg:postcode":"77630",
    "sg:province":"TX",
    "wof:name":"Jy's Floral Shop",
    "wof:placetype":"venue"
},
  "geometry": {"coordinates":[-93.744928,30.109742],"type":"Point"}
}