{
  "type": "Feature",
  "properties": {
    "iso:country":"US",
    "sg:address":"4388 Sunbelt Dr",
    "sg:city":"Addison",
    "sg:classifiers":[
        {
            "category":"Professional",
            "subcategory":"Advertising",
            "type":"Services"
        }
    ],
    "sg:phone":"+1 972 407 9195",
    "sg:postcode":"75001",
    "sg:province":"TX",
    "sg:tags":[
        "distribution"
    ],
    "wof:name":"G Bush Enterprises Inc",
    "wof:placetype":"venue"
},
  "geometry": {"coordinates":[-96.836116,32.977077],"type":"Point"}
}