{
  "type": "Feature",
  "properties": {
    "iso:country":"US",
    "sg:address":"10 Shady Grove Ln",
    "sg:city":"Wimberley",
    "sg:classifiers":[
        {
            "category":"Restaurant",
            "type":"Food & Drink"
        }
    ],
    "sg:phone":"+1 512 842 1154",
    "sg:postcode":"78676",
    "sg:province":"TX",
    "wof:name":"Pat's Place",
    "wof:placetype":"venue"
},
  "geometry": {"coordinates":[-98.11009199999999,30.031495],"type":"Point"}
}