{
  "type": "Feature",
  "properties": {
    "iso:country":"US",
    "sg:address":"19023 Polo Meadow Dr",
    "sg:city":"Humble",
    "sg:classifiers":[
        {
            "category":"Professional",
            "subcategory":"Management & Consulting",
            "type":"Services"
        }
    ],
    "sg:phone":"+1 281 852 1398",
    "sg:postcode":"77346",
    "sg:province":"TX",
    "sg:tags":[
        "public",
        "relations"
    ],
    "wof:name":"Mikstev Inc",
    "wof:placetype":"venue"
},
  "geometry": {"coordinates":[-95.160949,29.985259],"type":"Point"}
}