{
  "type": "Feature",
  "properties": {
    "iso:country":"US",
    "sg:address":"9607 Research Blvd",
    "sg:city":"Austin",
    "sg:classifiers":[
        {
            "category":"Home & Garden",
            "subcategory":"Carpets & Floor Coverings",
            "type":"Retail Goods"
        }
    ],
    "sg:phone":"+1 512 795 9504",
    "sg:postcode":"78759",
    "sg:province":"TX",
    "sg:tags":[
        "mattress"
    ],
    "wof:name":"Factory Mattress Sales",
    "wof:placetype":"venue"
},
  "geometry": {"coordinates":[-97.74355300000001,30.38829],"type":"Point"}
}