{
  "type": "Feature",
  "properties": {
    "iso:country":"US",
    "sg:address":"320 N McColl Rd",
    "sg:city":"Mcallen",
    "sg:classifiers":[
        {
            "category":"Shopping",
            "type":"Retail Goods"
        }
    ],
    "sg:phone":"+1 956 618 4055",
    "sg:postcode":"78501",
    "sg:province":"TX",
    "sg:tags":[
        "merchandise"
    ],
    "wof:name":"Orthopaedic Sales & Services",
    "wof:placetype":"venue"
},
  "geometry": {"coordinates":[-98.212226,26.204055],"type":"Point"}
}