{
  "type": "Feature",
  "properties": {
    "iso:country":"US",
    "sg:address":"2825 Robby St",
    "sg:city":"Corpus Christi",
    "sg:classifiers":[
        {
            "category":"Utilities",
            "subcategory":"Mobile Phone",
            "type":"Services"
        }
    ],
    "sg:phone":"+1 361 728 7459",
    "sg:postcode":"78410",
    "sg:province":"TX",
    "sg:tags":[
        "communications",
        "radiotelephone"
    ],
    "wof:name":"Crystal Clear Paging & Celular",
    "wof:placetype":"venue"
},
  "geometry": {"coordinates":[-97.57052299999999,27.836433],"type":"Point"}
}