{
  "type": "Feature",
  "properties": {
    "iso:country":"US",
    "sg:address":"10770 Moss Ridge Rd",
    "sg:city":"Houston",
    "sg:classifiers":[
        {
            "category":"Professional",
            "subcategory":"Business Services",
            "type":"Services"
        }
    ],
    "sg:phone":"+1 713 609 4003",
    "sg:postcode":"77043",
    "sg:province":"TX",
    "sg:tags":[
        "packaging"
    ],
    "wof:name":"Star Packaging",
    "wof:placetype":"venue"
},
  "geometry": {"coordinates":[-95.566698,29.827554],"type":"Point"}
}