{
  "type": "Feature",
  "properties": {
    "iso:country":"US",
    "sg:address":"51 W Side Sq",
    "sg:city":"Cooper",
    "sg:classifiers":[
        {
            "category":"Professional",
            "subcategory":"Accounting & Tax Preparation",
            "type":"Services"
        }
    ],
    "sg:phone":"+1 903 395 3229",
    "sg:postcode":"75432",
    "sg:province":"TX",
    "sg:tags":[
        "accountant"
    ],
    "wof:name":"Johnson Johnson & Co",
    "wof:placetype":"venue"
},
  "geometry": {"coordinates":[-95.68879699999999,33.374216],"type":"Point"}
}