{
  "type": "Feature",
  "properties": {
    "iso:country":"US",
    "sg:address":"923 Wakefield Dr",
    "sg:city":"Houston",
    "sg:classifiers":[
        {
            "category":"Building & Trades",
            "subcategory":"Construction",
            "type":"Services"
        }
    ],
    "sg:phone":"+1 713 686 1159",
    "sg:postcode":"77018",
    "sg:province":"TX",
    "sg:tags":[
        "contractor"
    ],
    "wof:name":"Barziza Dave Contractor",
    "wof:placetype":"venue"
},
  "geometry": {"coordinates":[-95.420998,29.8214],"type":"Point"}
}