{
  "type": "Feature",
  "properties": {
    "iso:country":"US",
    "sg:address":"917 9th St",
    "sg:city":"Wellington",
    "sg:classifiers":[
        {
            "category":"Personal",
            "subcategory":"Beauty Salon",
            "type":"Services"
        }
    ],
    "sg:phone":"+1 806 447 2094",
    "sg:postcode":"79095",
    "sg:province":"TX",
    "wof:name":"Leann Popwell Hair Designs",
    "wof:placetype":"venue"
},
  "geometry": {"coordinates":[-100.21394100000001,34.855172],"type":"Point"}
}