{
  "type": "Feature",
  "properties": {
    "iso:country":"US",
    "sg:address":"10405 E Northwest Hwy",
    "sg:city":"Dallas",
    "sg:classifiers":[
        {
            "category":"Personal",
            "type":"Services"
        }
    ],
    "sg:phone":"+1 214 343 0606",
    "sg:postcode":"75238",
    "sg:province":"TX",
    "sg:tags":[
        "therapist",
        "massage"
    ],
    "wof:name":"Carol M Sanders",
    "wof:placetype":"venue"
},
  "geometry": {"coordinates":[-96.70644799999999,32.864378],"type":"Point"}
}