{
  "type": "Feature",
  "properties": {
    "iso:country":"US",
    "sg:address":"1005 Newberry Dr",
    "sg:city":"Richardson",
    "sg:classifiers":[
        {
            "category":"Manufacturing",
            "subcategory":"Printing",
            "type":"Manufacturing & Wholesale Goods"
        }
    ],
    "sg:phone":"+1 972 671 9929",
    "sg:postcode":"75080",
    "sg:province":"TX",
    "sg:tags":[
        "publishing"
    ],
    "wof:name":"Connecting Lives International",
    "wof:placetype":"venue"
},
  "geometry": {"coordinates":[-96.751204,32.96046],"type":"Point"}
}