{
  "type": "Feature",
  "properties": {
    "iso:country":"US",
    "sg:address":"547 Ranch Trl",
    "sg:city":"Irving",
    "sg:classifiers":[
        {
            "category":"Professional",
            "subcategory":"Research",
            "type":"Services"
        }
    ],
    "sg:phone":"+1 972 444 9472",
    "sg:postcode":"75063",
    "sg:province":"TX",
    "sg:tags":[
        "nonphysical",
        "commercial"
    ],
    "wof:name":"Etcetera Marketing",
    "wof:placetype":"venue"
},
  "geometry": {"coordinates":[-96.953131,32.927367],"type":"Point"}
}