{
  "type": "Feature",
  "properties": {
    "iso:country":"US",
    "sg:address":"8404 Alabama Dr",
    "sg:city":"Austin",
    "sg:classifiers":[
        {
            "category":"Military Area",
            "subcategory":"Armory",
            "type":"Public Place"
        },
        {
            "category":"Building & Trades",
            "subcategory":"Construction",
            "type":"Services"
        }
    ],
    "sg:phone":"+1 512 639 7806",
    "sg:postcode":"78745",
    "sg:province":"TX",
    "sg:tags":[
        "repair",
        "fence",
        "stair",
        "deck",
        "builder",
        "roof",
        "patio"
    ],
    "sg:website":"http://www.addadeckoftexas.com",
    "wof:name":"Add-A-Deck of Texas",
    "wof:placetype":"venue"
},
  "geometry": {"coordinates":[-97.821259,30.19241],"type":"Point"}
}