{
  "type": "Feature",
  "properties": {
    "iso:country":"US",
    "sg:address":"1304 S 5th St",
    "sg:city":"Midlothian",
    "sg:classifiers":[
        {
            "category":"Freight",
            "type":"Transportation"
        }
    ],
    "sg:phone":"+1 972 775 2720",
    "sg:postcode":"76065",
    "sg:province":"TX",
    "sg:website":"www.crst.com",
    "wof:name":"CRST",
    "wof:placetype":"venue"
},
  "geometry": {"coordinates":[-96.998332,32.472305],"type":"Point"}
}