{
  "type": "Feature",
  "properties": {
    "iso:country":"US",
    "sg:address":"406 Longmire Rd",
    "sg:city":"Conroe",
    "sg:classifiers":[
        {
            "category":"Health Services",
            "subcategory":"Doctor",
            "type":"Services"
        }
    ],
    "sg:phone":"+1 936 756 7611",
    "sg:postcode":"77304",
    "sg:province":"TX",
    "sg:tags":[
        "dentist"
    ],
    "wof:name":"Richard E Allen DDS PC",
    "wof:placetype":"venue"
},
  "geometry": {"coordinates":[-95.48141,30.323321],"type":"Point"}
}