{
  "type": "Feature",
  "properties": {
    "iso:country":"US",
    "sg:address":"1137 W Wilson Ave",
    "sg:city":"Aransas Pass",
    "sg:classifiers":[
        {
            "category":"Restaurant",
            "type":"Food & Drink"
        }
    ],
    "sg:phone":"+1 361 758 3890",
    "sg:postcode":"78336",
    "sg:province":"TX",
    "sg:tags":[
        "eating"
    ],
    "wof:name":"Dupnik Lnda Personalized Catrg",
    "wof:placetype":"venue"
},
  "geometry": {"coordinates":[-97.157124,27.909908],"type":"Point"}
}