{
  "type": "Feature",
  "properties": {
    "iso:country":"US",
    "sg:address":"39390 I- 10 W",
    "sg:city":"Boerne",
    "sg:classifiers":[
        {
            "category":"Retail",
            "subcategory":"Auto Repair",
            "type":"Services"
        }
    ],
    "sg:phone":"+1 830 816 1234",
    "sg:postcode":"78006",
    "sg:province":"TX",
    "sg:tags":[
        "recreational",
        "r",
        "v",
        "vehicle"
    ],
    "wof:name":"American Rv",
    "wof:placetype":"venue"
},
  "geometry": {"coordinates":[-98.75851299999999,29.821512],"type":"Point"}
}