{
  "type": "Feature",
  "properties": {
    "iso:country":"US",
    "sg:address":"6809 Martin Luther King Jr Blvd",
    "sg:city":"Houston",
    "sg:classifiers":[
        {
            "category":"Personal",
            "subcategory":"Beauty Salon",
            "type":"Services"
        }
    ],
    "sg:phone":"+1 713 731 7599",
    "sg:postcode":"77033",
    "sg:province":"TX",
    "sg:tags":[
        "shop"
    ],
    "wof:name":"Billies Boutique and Beauty Sp",
    "wof:placetype":"venue"
},
  "geometry": {"coordinates":[-95.337414,29.67974],"type":"Point"}
}