{
  "type": "Feature",
  "properties": {
    "iso:country":"US",
    "sg:address":"2800 Lometa Dr",
    "sg:city":"Amarillo",
    "sg:classifiers":[
        {
            "category":"Shopping",
            "subcategory":"Computers & Home Electronics",
            "type":"Retail Goods"
        }
    ],
    "sg:phone":"+1 806 353 0733",
    "sg:postcode":"79109",
    "sg:province":"TX",
    "sg:tags":[
        "equipment",
        "dealer"
    ],
    "wof:name":"Technet Computer Svc",
    "wof:placetype":"venue"
},
  "geometry": {"coordinates":[-101.879643,35.185006],"type":"Point"}
}