{
  "type": "Feature",
  "properties": {
    "iso:country":"US",
    "sg:address":"4070 N Belt Line Rd",
    "sg:city":"Irving",
    "sg:classifiers":[
        {
            "category":"Retail",
            "subcategory":"Laundry & Dry Cleaning",
            "type":"Services"
        }
    ],
    "sg:phone":"+1 972 570 7226",
    "sg:postcode":"75038",
    "sg:province":"TX",
    "sg:tags":[
        "cleaners"
    ],
    "wof:name":"Wal Belt Cleaners",
    "wof:placetype":"venue"
},
  "geometry": {"coordinates":[-96.991625,32.864372],"type":"Point"}
}