{
  "type": "Feature",
  "properties": {
    "iso:country":"US",
    "sg:address":"819 Park St",
    "sg:city":"Graham",
    "sg:classifiers":[
        {
            "category":"Shopping",
            "subcategory":"Hobbies, Toys, & Games",
            "type":"Retail Goods"
        }
    ],
    "sg:phone":"+1 940 549 5788",
    "sg:postcode":"76450",
    "sg:province":"TX",
    "wof:name":"Pegs Pastime",
    "wof:placetype":"venue"
},
  "geometry": {"coordinates":[-98.585953,33.094121],"type":"Point"}
}