{
  "type": "Feature",
  "properties": {
    "iso:country":"US",
    "sg:address":"2902 Co Rd K",
    "sg:city":"Lamesa",
    "sg:classifiers":[
        {
            "category":"Farming",
            "subcategory":"Farm",
            "type":"Manufacturing & Wholesale Goods"
        }
    ],
    "sg:phone":"+1 806 462 7438",
    "sg:postcode":"79331",
    "sg:province":"TX",
    "wof:name":"Larry Turner Farm",
    "wof:placetype":"venue"
},
  "geometry": {"coordinates":[-101.911535,32.583367],"type":"Point"}
}