{
  "type": "Feature",
  "properties": {
    "iso:country":"US",
    "sg:address":"2420 Lakeview Dr",
    "sg:city":"Amarillo",
    "sg:classifiers":[
        {
            "category":"Professional",
            "subcategory":"Engineering",
            "type":"Services"
        }
    ],
    "sg:phone":"+1 806 352 7117",
    "sg:postcode":"79109",
    "sg:province":"TX",
    "wof:name":"OJD Engineering Inc",
    "wof:placetype":"venue"
},
  "geometry": {"coordinates":[-101.87505299999999,35.187451],"type":"Point"}
}