{
  "type": "Feature",
  "properties": {
    "iso:country":"US",
    "sg:address":"8011 Bent Oak Ln",
    "sg:city":"Spring",
    "sg:classifiers":[
        {
            "category":"Shopping",
            "subcategory":"Gifts & Souvenirs",
            "type":"Retail Goods"
        }
    ],
    "sg:phone":"+1 281 379 3789",
    "sg:postcode":"77379",
    "sg:province":"TX",
    "wof:name":"Card Payment Systems",
    "wof:placetype":"venue"
},
  "geometry": {"coordinates":[-95.5371,30.014587],"type":"Point"}
}