{
  "type": "Feature",
  "properties": {
    "iso:country":"US",
    "sg:address":"3101 Stornoway Trl",
    "sg:city":"Arlington",
    "sg:classifiers":[
        {
            "category":"Professional",
            "subcategory":"Business Services",
            "type":"Services"
        }
    ],
    "sg:phone":"+1 817 801 8353",
    "sg:postcode":"76012",
    "sg:province":"TX",
    "wof:name":"Interiors By Linda",
    "wof:placetype":"venue"
},
  "geometry": {"coordinates":[-97.15940399999999,32.738973],"type":"Point"}
}