{
  "type": "Feature",
  "properties": {
    "iso:country":"US",
    "sg:address":"2550 W 8th St",
    "sg:city":"Odessa",
    "sg:classifiers":[
        {
            "category":"Real Estate",
            "subcategory":"Real Estate Operator",
            "type":"Services"
        }
    ],
    "sg:phone":"+1 432 337 2541",
    "sg:postcode":"79763",
    "sg:province":"TX",
    "sg:tags":[
        "building",
        "apartment"
    ],
    "wof:name":"Aimco",
    "wof:placetype":"venue"
},
  "geometry": {"coordinates":[-102.400761,31.839219],"type":"Point"}
}