{
  "type": "Feature",
  "properties": {
    "iso:country":"US",
    "sg:address":"4055 Valley View Ln Ste 700",
    "sg:city":"Dallas",
    "sg:classifiers":[
        {
            "category":"Professional",
            "subcategory":"Employment Agencies",
            "type":"Services"
        }
    ],
    "sg:phone":"+1 972 385 7801",
    "sg:postcode":"75244",
    "sg:province":"TX",
    "sg:website":"www.snelling.com",
    "wof:name":"Snelling Staffing",
    "wof:placetype":"venue"
},
  "geometry": {"coordinates":[-96.84383200000001,32.925467],"type":"Point"}
}