{
  "type": "Feature",
  "properties": {
    "iso:country":"US",
    "sg:address":"6225 Saratoga Blvd",
    "sg:city":"Corpus Christi",
    "sg:classifiers":[
        {
            "category":"Professional",
            "subcategory":"Business Services",
            "type":"Services"
        }
    ],
    "sg:phone":"+1 361 808 9055",
    "sg:postcode":"78414",
    "sg:province":"TX",
    "wof:name":"Quiznos Subs",
    "wof:placetype":"venue"
},
  "geometry": {"coordinates":[-97.370813,27.678954],"type":"Point"}
}