{
  "type": "Feature",
  "properties": {
    "iso:country":"US",
    "sg:address":"655 State Hwy 327",
    "sg:city":"Silsbee",
    "sg:classifiers":[
        {
            "category":"Food & Beverages",
            "subcategory":"Groceries & Convenience Stores",
            "type":"Retail Goods"
        }
    ],
    "sg:phone":"+1 409 385 3749",
    "sg:postcode":"77656",
    "sg:province":"TX",
    "sg:tags":[
        "coin",
        "laundry"
    ],
    "wof:name":"Deirs Drive In Grocery",
    "wof:placetype":"venue"
},
  "geometry": {"coordinates":[-94.175833,30.342248],"type":"Point"}
}