{
  "type": "Feature",
  "properties": {
    "iso:country":"US",
    "sg:address":"1308 Bandera Hwy",
    "sg:city":"Kerrville",
    "sg:classifiers":[
        {
            "category":"Wholesale",
            "subcategory":"Hardware",
            "type":"Manufacturing & Wholesale Goods"
        }
    ],
    "sg:phone":"+1 830 792 3994",
    "sg:postcode":"78028",
    "sg:province":"TX",
    "sg:tags":[
        "purifying",
        "cleaning",
        "air"
    ],
    "wof:name":"Envirotech",
    "wof:placetype":"venue"
},
  "geometry": {"coordinates":[-99.141508,30.030984],"type":"Point"}
}