{
  "type": "Feature",
  "properties": {
    "iso:country":"US",
    "sg:address":"601 Lexington Dr",
    "sg:city":"Irving",
    "sg:classifiers":[
        {
            "category":"Building & Trades",
            "subcategory":"Construction",
            "type":"Services"
        }
    ],
    "sg:phone":"+1 972 986 1025",
    "sg:postcode":"75061",
    "sg:province":"TX",
    "sg:tags":[
        "builder",
        "patio",
        "deck"
    ],
    "wof:name":"Cornish & Cornish",
    "wof:placetype":"venue"
},
  "geometry": {"coordinates":[-96.980176,32.822801],"type":"Point"}
}