{
  "type": "Feature",
  "properties": {
    "iso:country":"US",
    "sg:address":"1805 Raleigh Ave",
    "sg:city":"Austin",
    "sg:classifiers":[
        {
            "category":"Professional",
            "type":"Services"
        },
        {
            "category":"Education",
            "subcategory":"Special Training",
            "type":"Public Place"
        }
    ],
    "sg:phone":"+1 512 478 2455",
    "sg:postcode":"78703",
    "sg:province":"TX",
    "sg:tags":[
        "school",
        "instruction",
        "art"
    ],
    "wof:name":"Stephanie C Bradley",
    "wof:placetype":"venue"
},
  "geometry": {"coordinates":[-97.778924,30.297968],"type":"Point"}
}