{
  "type": "Feature",
  "properties": {
    "iso:country":"US",
    "sg:address":"1215 Van Buren St",
    "sg:city":"Houston",
    "sg:classifiers":[
        {
            "category":"Shopping",
            "subcategory":"Computers & Home Electronics",
            "type":"Retail Goods"
        }
    ],
    "sg:phone":"+1 713 524 7788",
    "sg:postcode":"77019",
    "sg:province":"TX",
    "wof:name":"Little Shop of Game Makers",
    "wof:placetype":"venue"
},
  "geometry": {"coordinates":[-95.39391500000001,29.756866],"type":"Point"}
}