{
  "type": "Feature",
  "properties": {
    "iso:country":"US",
    "sg:address":"8499 San Gabriel Dr",
    "sg:city":"Laredo",
    "sg:classifiers":[
        {
            "category":"Retail",
            "subcategory":"Auto Rental",
            "type":"Services"
        }
    ],
    "sg:phone":"+1 956 717 1322",
    "sg:postcode":"78045",
    "sg:province":"TX",
    "sg:tags":[
        "truck",
        "leasing"
    ],
    "wof:name":"Ryder",
    "wof:placetype":"venue"
},
  "geometry": {"coordinates":[-99.50453,27.589983],"type":"Point"}
}