{
  "type": "Feature",
  "properties": {
    "iso:country":"US",
    "sg:address":"2800 S I H 35",
    "sg:city":"Round Rock",
    "sg:classifiers":[
        {
            "category":"Home & Garden",
            "subcategory":"Home Furnishings",
            "type":"Retail Goods"
        },
        {
            "category":"Home & Garden",
            "subcategory":"Furniture",
            "type":"Retail Goods"
        }
    ],
    "sg:phone":"+1 512 310 1130",
    "sg:postcode":"78681",
    "sg:province":"TX",
    "sg:tags":[
        "decor",
        "store"
    ],
    "sg:website":"www.gardenridge.com",
    "wof:name":"Garden Ridge",
    "wof:placetype":"venue"
},
  "geometry": {"coordinates":[-97.80195399999999,30.126322],"type":"Point"}
}