{
  "type": "Feature",
  "properties": {
    "iso:country":"US",
    "sg:address":"6410 Wesley St",
    "sg:city":"Greenville",
    "sg:classifiers":[
        {
            "category":"Food & Beverages",
            "subcategory":"Groceries & Convenience Stores",
            "type":"Retail Goods"
        }
    ],
    "sg:phone":"+1 903 455 1358",
    "sg:postcode":"75402",
    "sg:province":"TX",
    "wof:name":"Brookshire Food 074",
    "wof:placetype":"venue"
},
  "geometry": {"coordinates":[-96.10979,33.105088],"type":"Point"}
}