{
  "type": "Feature",
  "properties": {
    "iso:country":"US",
    "sg:address":"3210 FM 528",
    "sg:city":"Friendswood",
    "sg:classifiers":[
        {
            "category":"Shopping",
            "subcategory":"Department Store",
            "type":"Retail Goods"
        }
    ],
    "sg:phone":"+1 281 648 6642",
    "sg:postcode":"77546",
    "sg:province":"TX",
    "sg:tags":[
        "shop"
    ],
    "sg:website":"www.dollartree.com",
    "wof:name":"Dollar Tree",
    "wof:placetype":"venue"
},
  "geometry": {"coordinates":[-95.22268,29.471086],"type":"Point"}
}