{
  "type": "Feature",
  "properties": {
    "iso:country":"US",
    "sg:address":"411 E Olive St",
    "sg:city":"Laredo",
    "sg:classifiers":[
        {
            "category":"Retail",
            "subcategory":"Auto Repair",
            "type":"Services"
        }
    ],
    "sg:phone":"+1 956 722 6879",
    "sg:postcode":"78041",
    "sg:province":"TX",
    "sg:tags":[
        "general"
    ],
    "wof:name":"Regalados Repair Shop",
    "wof:placetype":"venue"
},
  "geometry": {"coordinates":[-99.491759,27.531405],"type":"Point"}
}