{
  "type": "Feature",
  "properties": {
    "iso:country":"US",
    "sg:address":"12044 Beach",
    "sg:city":"Houston",
    "sg:classifiers":[
        {
            "category":"Recreation",
            "type":"Entertainment"
        }
    ],
    "sg:phone":"+1 281 456 7445",
    "sg:postcode":"77044",
    "sg:province":"TX",
    "sg:tags":[
        "parks"
    ],
    "wof:name":"Magnolia Gardens Park",
    "wof:placetype":"venue"
},
  "geometry": {"coordinates":[-95.10422,29.890457],"type":"Point"}
}