{
  "type": "Feature",
  "properties": {
    "iso:country":"US",
    "sg:address":"817 Ayers St",
    "sg:city":"Corpus Christi",
    "sg:classifiers":[
        {
            "category":"Health Services",
            "subcategory":"Doctor",
            "type":"Services"
        }
    ],
    "sg:phone":"+1 361 887 9600",
    "sg:postcode":"78404",
    "sg:province":"TX",
    "sg:tags":[
        "physician",
        "surgeon"
    ],
    "wof:name":"Psychiatric Consulting Svc",
    "wof:placetype":"venue"
},
  "geometry": {"coordinates":[-97.398295,27.774657],"type":"Point"}
}