{
  "type": "Feature",
  "properties": {
    "iso:country":"US",
    "sg:address":"1 Duvall St",
    "sg:city":"Mc Kinney",
    "sg:classifiers":[
        {
            "category":"Education",
            "subcategory":"School",
            "type":"Public Place"
        }
    ],
    "sg:phone":"+1 972 569 6414",
    "sg:postcode":"75069",
    "sg:province":"TX",
    "sg:website":"www.mckinneyisd.net",
    "wof:name":"Mc Kinney School Dist",
    "wof:placetype":"venue"
},
  "geometry": {"coordinates":[-96.631647,33.207003],"type":"Point"}
}