{
  "type": "Feature",
  "properties": {
    "iso:country":"US",
    "sg:address":"234 W Ave L",
    "sg:city":"San Angelo",
    "sg:classifiers":[
        {
            "category":"Manufacturing",
            "subcategory":"Furniture",
            "type":"Manufacturing & Wholesale Goods"
        }
    ],
    "sg:phone":"+1 325 655 5810",
    "sg:postcode":"76903",
    "sg:province":"TX",
    "sg:tags":[
        "fixture",
        "store"
    ],
    "wof:name":"Universal Display & Fixtures",
    "wof:placetype":"venue"
},
  "geometry": {"coordinates":[-100.438678,31.444961],"type":"Point"}
}