{
  "type": "Feature",
  "properties": {
    "iso:country":"US",
    "sg:address":"3013 Orange Ave",
    "sg:city":"Mcallen",
    "sg:classifiers":[
        {
            "category":"Professional",
            "type":"Services"
        }
    ],
    "sg:phone":"+1 956 686 3192",
    "sg:postcode":"78501",
    "sg:province":"TX",
    "wof:name":"Gonzales Merced",
    "wof:placetype":"venue"
},
  "geometry": {"coordinates":[-98.252064,26.220244],"type":"Point"}
}