{
  "type": "Feature",
  "properties": {
    "iso:country":"US",
    "sg:address":"4530 W 34th St",
    "sg:city":"Houston",
    "sg:classifiers":[
        {
            "category":"Professional",
            "subcategory":"Advertising",
            "type":"Services"
        }
    ],
    "sg:phone":"+1 713 784 2021",
    "sg:postcode":"77092",
    "sg:province":"TX",
    "sg:tags":[
        "agency",
        "specialty"
    ],
    "wof:name":"Spanish Advertising",
    "wof:placetype":"venue"
},
  "geometry": {"coordinates":[-95.45671900000001,29.819382],"type":"Point"}
}