{
  "type": "Feature",
  "properties": {
    "iso:country":"US",
    "sg:address":"500 N Stanton St",
    "sg:city":"El Paso",
    "sg:classifiers":[
        {
            "category":"Restaurant",
            "type":"Food & Drink"
        }
    ],
    "sg:phone":"+1 915 533 3926",
    "sg:postcode":"79901",
    "sg:province":"TX",
    "wof:name":"Big Bun",
    "wof:placetype":"venue"
},
  "geometry": {"coordinates":[-106.488873,31.762286],"type":"Point"}
}