{
  "type": "Feature",
  "properties": {
    "iso:country":"US",
    "sg:address":"3811 S Cooper St",
    "sg:city":"Arlington",
    "sg:classifiers":[
        {
            "category":"Shopping",
            "subcategory":"Clothing, Apparel, & Fashions",
            "type":"Retail Goods"
        }
    ],
    "sg:phone":"+1 817 557 3222",
    "sg:postcode":"76015",
    "sg:province":"TX",
    "sg:tags":[
        "family",
        "gift"
    ],
    "wof:name":"Disney Store Inc",
    "wof:placetype":"venue"
},
  "geometry": {"coordinates":[-97.13327099999999,32.682767],"type":"Point"}
}