{
  "type": "Feature",
  "properties": {
    "iso:country":"US",
    "sg:address":"2361 Fabens Rd",
    "sg:city":"Dallas",
    "sg:classifiers":[
        {
            "category":"Manufacturing",
            "subcategory":"Signs",
            "type":"Manufacturing & Wholesale Goods"
        }
    ],
    "sg:phone":"+1 972 241 5088",
    "sg:postcode":"75229",
    "sg:province":"TX",
    "sg:tags":[
        "specialty",
        "mfg"
    ],
    "wof:name":"New Era Imaging",
    "wof:placetype":"venue"
},
  "geometry": {"coordinates":[-96.900503,32.891502],"type":"Point"}
}