{
  "type": "Feature",
  "properties": {
    "iso:country":"US",
    "sg:address":"250 N Lamar Blvd",
    "sg:city":"Austin",
    "sg:classifiers":[
        {
            "category":"Railroad",
            "type":"Transportation"
        }
    ],
    "sg:phone":"+1 512 476 5684",
    "sg:postcode":"78703",
    "sg:province":"TX",
    "sg:tags":[
        "operator",
        "line"
    ],
    "wof:name":"Amtrak",
    "wof:placetype":"venue"
},
  "geometry": {"coordinates":[-97.75520299999999,30.2686],"type":"Point"}
}