{
  "type": "Feature",
  "properties": {
    "iso:country":"US",
    "sg:address":"11503 Jones Rd",
    "sg:city":"Houston",
    "sg:classifiers":[
        {
            "category":"Shopping",
            "subcategory":"Used Merchandise",
            "type":"Retail Goods"
        }
    ],
    "sg:phone":"+1 281 897 9577",
    "sg:postcode":"77070",
    "sg:province":"TX",
    "wof:name":"Vintage Gifts and Antiques",
    "wof:placetype":"venue"
},
  "geometry": {"coordinates":[-95.584779,29.940406],"type":"Point"}
}