{
  "type": "Feature",
  "properties": {
    "iso:country":"US",
    "sg:address":"9039 Katy Fwy",
    "sg:city":"Houston",
    "sg:classifiers":[
        {
            "category":"Building & Trades",
            "subcategory":"Construction",
            "type":"Services"
        }
    ],
    "sg:phone":"+1 713 984 8815",
    "sg:postcode":"77024",
    "sg:province":"TX",
    "sg:tags":[
        "contractor"
    ],
    "wof:name":"Galleria International General Contractors",
    "wof:placetype":"venue"
},
  "geometry": {"coordinates":[-95.51149700000001,29.783899],"type":"Point"}
}