{
  "type": "Feature",
  "properties": {
    "iso:country":"US",
    "sg:address":"110 S Bishop Ave",
    "sg:city":"Dallas",
    "sg:classifiers":[
        {
            "category":"Personal",
            "subcategory":"Beauty Salon",
            "type":"Services"
        }
    ],
    "sg:phone":"+1 214 946 3604",
    "sg:postcode":"75208",
    "sg:province":"TX",
    "wof:name":"Mai Hair Salon",
    "wof:placetype":"venue"
},
  "geometry": {"coordinates":[-96.82821,32.744229],"type":"Point"}
}