{
  "type": "Feature",
  "properties": {
    "iso:country":"US",
    "sg:address":"5714 Penny Creek Dr",
    "sg:city":"Austin",
    "sg:classifiers":[
        {
            "category":"Professional",
            "subcategory":"Business Services",
            "type":"Services"
        }
    ],
    "sg:phone":"+1 512 794 9903",
    "sg:postcode":"78759",
    "sg:province":"TX",
    "wof:name":"Joias Design",
    "wof:placetype":"venue"
},
  "geometry": {"coordinates":[-97.755696,30.412184],"type":"Point"}
}