{
  "type": "Feature",
  "properties": {
    "iso:country":"US",
    "sg:address":"301 I 35 Hwy NW",
    "sg:city":"Hillsboro",
    "sg:classifiers":[
        {
            "category":"Restaurant",
            "type":"Food & Drink"
        }
    ],
    "sg:menulink":"http://www.allmenus.com/tx/hillsboro/94495-dominos-pizza/menu/",
    "sg:phone":"+1 254 582 1234",
    "sg:postcode":"76645",
    "sg:province":"TX",
    "sg:tags":[
        "american",
        "wing",
        "pizza"
    ],
    "wof:name":"Domino's Pizza",
    "wof:placetype":"venue"
},
  "geometry": {"coordinates":[-97.09692,32.017573],"type":"Point"}
}