{
  "type": "Feature",
  "properties": {
    "iso:country":"US",
    "sg:address":"12030 State Hwy 1604",
    "sg:city":"San Antonio",
    "sg:classifiers":[
        {
            "category":"Restaurant",
            "type":"Food & Drink"
        }
    ],
    "sg:phone":"+1 210 622 9793",
    "sg:postcode":"78073",
    "sg:province":"TX",
    "sg:tags":[
        "eating"
    ],
    "wof:name":"Tink-A-Tako",
    "wof:placetype":"venue"
},
  "geometry": {"coordinates":[-98.672436,29.303503],"type":"Point"}
}