{
  "type": "Feature",
  "properties": {
    "iso:country":"US",
    "sg:address":"7410 Cullen Blvd",
    "sg:city":"Houston",
    "sg:classifiers":[
        {
            "category":"Restaurant",
            "type":"Food & Drink"
        }
    ],
    "sg:menulink":"http://www.allmenus.com/tx/houston/202200-mcdonalds/menu/",
    "sg:postcode":"77051",
    "sg:province":"TX",
    "sg:tags":[
        "burger",
        "american"
    ],
    "wof:name":"McDonald's",
    "wof:placetype":"venue"
},
  "geometry": {"coordinates":[-95.356402,29.679865],"type":"Point"}
}