{
  "type": "Feature",
  "properties": {
    "iso:country":"US",
    "sg:address":"5773 Woodway Dr",
    "sg:city":"Houston",
    "sg:classifiers":[
        {
            "category":"Mining & Drilling",
            "type":"Manufacturing & Wholesale Goods"
        }
    ],
    "sg:phone":"+1 713 267 3460",
    "sg:postcode":"77057",
    "sg:province":"TX",
    "sg:tags":[
        "metal"
    ],
    "wof:name":"Manila Exploration Co Ltd",
    "wof:placetype":"venue"
},
  "geometry": {"coordinates":[-95.47878300000001,29.763587],"type":"Point"}
}