{
  "type": "Feature",
  "properties": {
    "iso:country":"US",
    "sg:address":"1644 County Road 4223",
    "sg:city":"Atlanta",
    "sg:classifiers":[
        {
            "category":"Personal",
            "subcategory":"Beauty Salon",
            "type":"Services"
        }
    ],
    "sg:phone":"+1 903 796 1809",
    "sg:postcode":"75551",
    "sg:province":"TX",
    "wof:name":"Crissy's Shear Magic",
    "wof:placetype":"venue"
},
  "geometry": {"coordinates":[-94.187957,33.044174],"type":"Point"}
}