{
  "type": "Feature",
  "properties": {
    "iso:country":"US",
    "sg:address":"106 E 67th St",
    "sg:city":"Odessa",
    "sg:classifiers":[
        {
            "category":"Building & Trades",
            "subcategory":"Construction",
            "type":"Services"
        }
    ],
    "sg:phone":"+1 432 362 7887",
    "sg:postcode":"79762",
    "sg:province":"TX",
    "sg:tags":[
        "painter"
    ],
    "wof:name":"F & W Industries",
    "wof:placetype":"venue"
},
  "geometry": {"coordinates":[-102.387468,31.908156],"type":"Point"}
}