{
  "type": "Feature",
  "properties": {
    "iso:country":"US",
    "sg:address":"2301 Central Pkwy",
    "sg:city":"Houston",
    "sg:classifiers":[
        {
            "category":"Manufacturing",
            "subcategory":"Motor Vehicles & Parts",
            "type":"Manufacturing & Wholesale Goods"
        }
    ],
    "sg:phone":"+1 713 688 4414",
    "sg:postcode":"77092",
    "sg:province":"TX",
    "sg:tags":[
        "body",
        "mfg",
        "construction",
        "mach"
    ],
    "wof:name":"Rki Inc",
    "wof:placetype":"venue"
},
  "geometry": {"coordinates":[-95.465306,29.808258],"type":"Point"}
}