{
  "type": "Feature",
  "properties": {
    "iso:country":"US",
    "sg:address":"410 W Main St",
    "sg:city":"Mesquite",
    "sg:classifiers":[
        {
            "category":"Professional",
            "subcategory":"Lawyer & Legal Services",
            "type":"Services"
        }
    ],
    "sg:phone":"+1 972 329 0160",
    "sg:postcode":"75149",
    "sg:province":"TX",
    "wof:name":"Douglas R Larson Attorney",
    "wof:placetype":"venue"
},
  "geometry": {"coordinates":[-96.603185,32.767097],"type":"Point"}
}