{
  "type": "Feature",
  "properties": {
    "iso:country":"US",
    "sg:address":"10302 Sunset Stone",
    "sg:city":"San Antonio",
    "sg:classifiers":[
        {
            "category":"Professional",
            "subcategory":"Management & Consulting",
            "type":"Services"
        }
    ],
    "sg:phone":"+1 210 521 1570",
    "sg:postcode":"78254",
    "sg:province":"TX",
    "sg:tags":[
        "photography",
        "commercial",
        "business"
    ],
    "wof:name":"Lloyd G Wright",
    "wof:placetype":"venue"
},
  "geometry": {"coordinates":[-98.667232,29.541712],"type":"Point"}
}