{
  "type": "Feature",
  "properties": {
    "iso:country":"US",
    "sg:address":"8408 Colonial Ln",
    "sg:city":"Houston",
    "sg:classifiers":[
        {
            "category":"Shopping",
            "subcategory":"Music",
            "type":"Retail Goods"
        }
    ],
    "sg:phone":"+1 713 721 3737",
    "sg:postcode":"77051",
    "sg:province":"TX",
    "sg:tags":[
        "compact",
        "record",
        "disc",
        "tape"
    ],
    "sg:website":"www.highvolumemusic.com",
    "wof:name":"High Volume Music",
    "wof:placetype":"venue"
},
  "geometry": {"coordinates":[-95.368754,29.670339],"type":"Point"}
}