{
  "type": "Feature",
  "properties": {
    "iso:country":"US",
    "sg:address":"5333 Forest Ln",
    "sg:city":"Dallas",
    "sg:classifiers":[
        {
            "category":"Shopping",
            "subcategory":"Jewelry",
            "type":"Retail Goods"
        }
    ],
    "sg:phone":"+1 972 934 0449",
    "sg:postcode":"75244",
    "sg:province":"TX",
    "wof:name":"Village Goldsmith",
    "wof:placetype":"venue"
},
  "geometry": {"coordinates":[-96.816704,32.909698],"type":"Point"}
}