{
  "type": "Feature",
  "properties": {
    "iso:country":"US",
    "sg:address":"1400 Gardina St",
    "sg:city":"San Antonio",
    "sg:classifiers":[
        {
            "category":"Retail",
            "subcategory":"Repair Shop",
            "type":"Services"
        }
    ],
    "sg:phone":"+1 210 533 9911",
    "sg:postcode":"78201",
    "sg:province":"TX",
    "wof:name":"St Ronni Cleaning Co",
    "wof:placetype":"venue"
},
  "geometry": {"coordinates":[-98.53770400000001,29.479601],"type":"Point"}
}