{
  "type": "Feature",
  "properties": {
    "iso:country":"US",
    "sg:address":"4431 Kemper St",
    "sg:city":"Lubbock",
    "sg:classifiers":[
        {
            "category":"Building & Trades",
            "subcategory":"Landscaping Services",
            "type":"Services"
        }
    ],
    "sg:phone":"+1 806 789 2031",
    "sg:postcode":"79416",
    "sg:province":"TX",
    "sg:tags":[
        "lawn",
        "maintenance"
    ],
    "wof:name":"Vic's Lawn Service",
    "wof:placetype":"venue"
},
  "geometry": {"coordinates":[-101.90517699999999,33.611887],"type":"Point"}
}