{
  "type": "Feature",
  "properties": {
    "iso:country":"US",
    "sg:address":"1816 Norwood Dr",
    "sg:city":"Hurst",
    "sg:classifiers":[
        {
            "category":"Health Services",
            "subcategory":"Nursing And Care Facility",
            "type":"Services"
        }
    ],
    "sg:phone":"+1 817 268 1974",
    "sg:postcode":"76054",
    "sg:province":"TX",
    "sg:tags":[
        "skilled"
    ],
    "wof:name":"Lionhospice",
    "wof:placetype":"venue"
},
  "geometry": {"coordinates":[-97.16758299999999,32.847229],"type":"Point"}
}