{
  "type": "Feature",
  "properties": {
    "iso:country":"US",
    "sg:address":"2031 Orchid Ave",
    "sg:city":"Mcallen",
    "sg:classifiers":[
        {
            "category":"Professional",
            "type":"Services"
        }
    ],
    "sg:phone":"+1 956 686 2802",
    "sg:postcode":"78504",
    "sg:province":"TX",
    "wof:name":"Sound & Visual Crafters",
    "wof:placetype":"venue"
},
  "geometry": {"coordinates":[-98.234492,26.242345],"type":"Point"}
}