{
  "type": "Feature",
  "properties": {
    "iso:country":"US",
    "sg:address":"888 S Greenville Ave",
    "sg:city":"Richardson",
    "sg:classifiers":[
        {
            "category":"Building & Trades",
            "subcategory":"Construction",
            "type":"Services"
        }
    ],
    "sg:phone":"+1 972 644 3119",
    "sg:postcode":"75081",
    "sg:province":"TX",
    "sg:tags":[
        "home",
        "contractor",
        "family",
        "custom"
    ],
    "wof:name":"Capri Homes",
    "wof:placetype":"venue"
},
  "geometry": {"coordinates":[-96.734668,32.93702],"type":"Point"}
}