{
  "type": "Feature",
  "properties": {
    "iso:country":"US",
    "sg:address":"11739 State Hwy 75",
    "sg:city":"Willis",
    "sg:classifiers":[
        {
            "category":"Home & Garden",
            "subcategory":"Home Furnishings",
            "type":"Retail Goods"
        }
    ],
    "sg:phone":"+1 936 890 2939",
    "sg:postcode":"77378",
    "sg:province":"TX",
    "sg:tags":[
        "cookware"
    ],
    "wof:name":"Creative Chefs Inc",
    "wof:placetype":"venue"
},
  "geometry": {"coordinates":[-95.47551300000001,30.411973],"type":"Point"}
}