{
  "type": "Feature",
  "properties": {
    "iso:country":"US",
    "sg:address":"4324 Ascot Dr",
    "sg:city":"Cleburne",
    "sg:classifiers":[
        {
            "category":"Building & Trades",
            "subcategory":"Plumbing",
            "type":"Services"
        }
    ],
    "sg:phone":"+1 817 558 9093",
    "sg:postcode":"76033",
    "sg:province":"TX",
    "sg:tags":[
        "plumbing",
        "contractor"
    ],
    "wof:name":"Rick's Plumbing",
    "wof:placetype":"venue"
},
  "geometry": {"coordinates":[-97.435923,32.252935],"type":"Point"}
}