{
  "type": "Feature",
  "properties": {
    "iso:country":"US",
    "sg:address":"10901 Gateway Blvd W",
    "sg:city":"El Paso",
    "sg:classifiers":[
        {
            "category":"Autos & Motor Vehicles",
            "subcategory":"Automobile Sales",
            "type":"Retail Goods"
        }
    ],
    "sg:phone":"+1 915 591 0805",
    "sg:postcode":"79935",
    "sg:province":"TX",
    "sg:tags":[
        "truck"
    ],
    "wof:name":"Southwest Sterling Inc",
    "wof:placetype":"venue"
},
  "geometry": {"coordinates":[-106.336997,31.747975],"type":"Point"}
}