{
  "type": "Feature",
  "properties": {
    "iso:country":"US",
    "sg:address":"12200 Northwest Fwy Ste 632",
    "sg:city":"Houston",
    "sg:classifiers":[
        {
            "category":"Banks & Credit Unions",
            "subcategory":"Bank",
            "type":"Services"
        }
    ],
    "sg:phone":"+1 281 342 2460",
    "sg:postcode":"77092",
    "sg:province":"TX",
    "wof:name":"State Farm Insurance Companies",
    "wof:placetype":"venue"
},
  "geometry": {"coordinates":[-95.47399900000001,29.828699],"type":"Point"}
}