{
  "type": "Feature",
  "properties": {
    "iso:country":"US",
    "sg:address":"254 E Arapaho Rd",
    "sg:city":"Richardson",
    "sg:classifiers":[
        {
            "category":"Wholesale",
            "subcategory":"Electrical",
            "type":"Manufacturing & Wholesale Goods"
        }
    ],
    "sg:phone":"+1 972 231 4406",
    "sg:postcode":"75081",
    "sg:province":"TX",
    "sg:tags":[
        "alarm",
        "burglar",
        "system"
    ],
    "sg:website":"www.inhousesystems.com",
    "wof:name":"Inhouse Security & Sound",
    "wof:placetype":"venue"
},
  "geometry": {"coordinates":[-96.71909599999999,32.960573],"type":"Point"}
}