{
  "type": "Feature",
  "properties": {
    "iso:country":"US",
    "sg:address":"6060 Forest Ln",
    "sg:city":"Dallas",
    "sg:classifiers":[
        {
            "category":"Banks & Credit Unions",
            "subcategory":"Bank",
            "type":"Services"
        }
    ],
    "sg:phone":"+1 214 373 1572",
    "sg:postcode":"75230",
    "sg:province":"TX",
    "sg:tags":[
        "broker",
        "mortgage"
    ],
    "wof:name":"Granite Mortgage Corp",
    "wof:placetype":"venue"
},
  "geometry": {"coordinates":[-96.801804,32.909302],"type":"Point"}
}