{
  "type": "Feature",
  "properties": {
    "iso:country":"US",
    "sg:address":"8341 Southwest Fwy",
    "sg:city":"Houston",
    "sg:classifiers":[
        {
            "category":"Shopping",
            "subcategory":"Tobacco",
            "type":"Retail Goods"
        }
    ],
    "sg:phone":"+1 713 995 6463",
    "sg:postcode":"77074",
    "sg:province":"TX",
    "sg:tags":[
        "shop",
        "smoke",
        "supply"
    ],
    "wof:name":"Smokers Planet",
    "wof:placetype":"venue"
},
  "geometry": {"coordinates":[-95.52948499999999,29.688648],"type":"Point"}
}