{
  "type": "Feature",
  "properties": {
    "iso:country":"US",
    "sg:address":"2717 Greywood Ln",
    "sg:city":"Plano",
    "sg:classifiers":[
        {
            "category":"Personal",
            "subcategory":"Beauty Salon",
            "type":"Services"
        }
    ],
    "sg:phone":"+1 972 612 0302",
    "sg:postcode":"75075",
    "sg:province":"TX",
    "sg:tags":[
        "shop"
    ],
    "wof:name":"Escape 2 Hair",
    "wof:placetype":"venue"
},
  "geometry": {"coordinates":[-96.747325,33.033813],"type":"Point"}
}