{
  "type": "Feature",
  "properties": {
    "iso:country":"US",
    "sg:address":"5803 Nuckols Crossing Rd.",
    "sg:city":"Austin",
    "sg:classifiers":[
        {
            "category":"Education",
            "subcategory":"Library",
            "type":"Public Place"
        }
    ],
    "sg:phone":"+1 512 462 1452",
    "sg:postcode":"78744",
    "sg:province":"TX",
    "sg:website":"www.austinlibrary.com/branches/i...",
    "wof:name":"Austin Public Library - Southeast Austin Community Branch",
    "wof:placetype":"venue"
},
  "geometry": {"coordinates":[-97.740071,30.191311],"type":"Point"}
}