{
  "type": "Feature",
  "properties": {
    "iso:country":"US",
    "sg:address":"1621 N Elm St 1",
    "sg:city":"Denton",
    "sg:classifiers":[
        {
            "category":"Real Estate",
            "subcategory":"Real Estate Services",
            "type":"Services"
        }
    ],
    "sg:phone":"+1 940 566 5854",
    "sg:postcode":"76201",
    "sg:province":"TX",
    "sg:tags":[
        "commercial"
    ],
    "wof:name":"Old Ice House Co",
    "wof:placetype":"venue"
},
  "geometry": {"coordinates":[-97.133531,33.227999],"type":"Point"}
}