{
  "type": "Feature",
  "properties": {
    "iso:country":"US",
    "sg:address":"6510 Abrams Rd",
    "sg:city":"Dallas",
    "sg:classifiers":[
        {
            "category":"Real Estate",
            "subcategory":"Architect",
            "type":"Services"
        }
    ],
    "sg:phone":"+1 214 221 8855",
    "sg:postcode":"75231",
    "sg:province":"TX",
    "sg:tags":[
        "architectural"
    ],
    "wof:name":"F L M Associates",
    "wof:placetype":"venue"
},
  "geometry": {"coordinates":[-96.743718,32.864821],"type":"Point"}
}