{
  "type": "Feature",
  "properties": {
    "iso:country":"US",
    "sg:address":"1302 August Dr",
    "sg:city":"Killeen",
    "sg:classifiers":[
        {
            "category":"Professional",
            "subcategory":"Management & Consulting",
            "type":"Services"
        }
    ],
    "sg:phone":"+1 254 634 4235",
    "sg:postcode":"76549",
    "sg:province":"TX",
    "sg:tags":[
        "consultant"
    ],
    "wof:name":"Total Government Allegiance",
    "wof:placetype":"venue"
},
  "geometry": {"coordinates":[-97.763199,31.087155],"type":"Point"}
}