{
  "type": "Feature",
  "properties": {
    "iso:country":"US",
    "sg:address":"1604 State Hwy 14",
    "sg:city":"Mexia",
    "sg:classifiers":[
        {
            "category":"Food & Beverages",
            "subcategory":"Liquor & Beverages",
            "type":"Retail Goods"
        }
    ],
    "sg:phone":"+1 254 562 0130",
    "sg:postcode":"76667",
    "sg:province":"TX",
    "sg:tags":[
        "beer",
        "ale"
    ],
    "wof:name":"Beer Barn & Quality Storage",
    "wof:placetype":"venue"
},
  "geometry": {"coordinates":[-96.48214900000001,31.706938],"type":"Point"}
}