{
  "type": "Feature",
  "properties": {
    "iso:country":"US",
    "sg:address":"12036 FM 3139",
    "sg:city":"Dalhart",
    "sg:classifiers":[
        {
            "category":"Farming",
            "subcategory":"Livestock Farm",
            "type":"Manufacturing & Wholesale Goods"
        }
    ],
    "sg:phone":"+1 806 249 1088",
    "sg:postcode":"79022",
    "sg:province":"TX",
    "sg:tags":[
        "beef",
        "feedlot",
        "cattle"
    ],
    "wof:name":"Gary L Spielman",
    "wof:placetype":"venue"
},
  "geometry": {"coordinates":[-102.54941100000001,36.042278],"type":"Point"}
}