{
  "type": "Feature",
  "properties": {
    "iso:country":"US",
    "sg:address":"1281 E Loop 304",
    "sg:city":"Crockett",
    "sg:classifiers":[
        {
            "category":"Fast Food",
            "type":"Food & Drink"
        },
        {
            "category":"Restaurant",
            "type":"Food & Drink"
        }
    ],
    "sg:phone":"+1 936 546 0240",
    "sg:postcode":"75835",
    "sg:province":"TX",
    "sg:tags":[
        "take"
    ],
    "sg:website":"http://www.whataburger.com",
    "wof:name":"Whataburger 934",
    "wof:placetype":"venue"
},
  "geometry": {"coordinates":[-95.43783500000001,31.308835],"type":"Point"}
}