{
  "type": "Feature",
  "properties": {
    "iso:country":"US",
    "sg:address":"9303 York Creek Cir",
    "sg:city":"San Antonio",
    "sg:classifiers":[
        {
            "category":"Professional",
            "type":"Services"
        }
    ],
    "sg:phone":"+1 210 344 6641",
    "sg:postcode":"78230",
    "sg:province":"TX",
    "wof:name":"CTT Inc",
    "wof:placetype":"venue"
},
  "geometry": {"coordinates":[-98.54362999999999,29.529234],"type":"Point"}
}