{
  "type": "Feature",
  "properties": {
    "iso:country":"US",
    "sg:address":"3714 Three Sisters St",
    "sg:city":"Houston",
    "sg:classifiers":[
        {
            "category":"Retail",
            "subcategory":"Auto Repair",
            "type":"Services"
        }
    ],
    "sg:phone":"+1 281 987 8376",
    "sg:postcode":"77093",
    "sg:province":"TX",
    "wof:name":"Contreras Roberto",
    "wof:placetype":"venue"
},
  "geometry": {"coordinates":[-95.331068,29.872411],"type":"Point"}
}