{
  "type": "Feature",
  "properties": {
    "iso:country":"US",
    "sg:address":"6092 Belladonna Cir",
    "sg:city":"El Paso",
    "sg:classifiers":[
        {
            "category":"Professional",
            "subcategory":"Lawyer & Legal Services",
            "type":"Services"
        }
    ],
    "sg:phone":"+1 915 757 1222",
    "sg:postcode":"79924",
    "sg:province":"TX",
    "sg:tags":[
        "attorney",
        "bureau"
    ],
    "wof:name":"Ransom",
    "wof:placetype":"venue"
},
  "geometry": {"coordinates":[-106.396275,31.898494],"type":"Point"}
}