{
  "type": "Feature",
  "properties": {
    "iso:country":"US",
    "sg:address":"10929 Ridgemeadow Dr",
    "sg:city":"Dallas",
    "sg:classifiers":[
        {
            "category":"Professional",
            "subcategory":"Advertising",
            "type":"Services"
        }
    ],
    "sg:phone":"+1 214 349 5205",
    "sg:postcode":"75218",
    "sg:province":"TX",
    "sg:tags":[
        "promotion",
        "sale"
    ],
    "wof:name":"Potter Marketing & Sales",
    "wof:placetype":"venue"
},
  "geometry": {"coordinates":[-96.696369,32.858453],"type":"Point"}
}