{
  "type": "Feature",
  "properties": {
    "iso:country":"US",
    "sg:address":"2218 N Chadbourne St",
    "sg:city":"San Angelo",
    "sg:classifiers":[
        {
            "category":"Retail",
            "subcategory":"Auto Repair",
            "type":"Services"
        }
    ],
    "sg:phone":"+1 325 481 0654",
    "sg:postcode":"76903",
    "sg:province":"TX",
    "sg:tags":[
        "transmission"
    ],
    "wof:name":"Affordable Transmissions",
    "wof:placetype":"venue"
},
  "geometry": {"coordinates":[-100.45024100000001,31.483162],"type":"Point"}
}