{
  "type": "Feature",
  "properties": {
    "iso:country":"US",
    "sg:address":"223 Lakeside Dr",
    "sg:city":"Kemah",
    "sg:classifiers":[
        {
            "category":"Personal",
            "subcategory":"Beauty Salon",
            "type":"Services"
        }
    ],
    "sg:phone":"+1 281 334 2072",
    "sg:postcode":"77565",
    "sg:province":"TX",
    "sg:tags":[
        "shop"
    ],
    "wof:name":"A Cut Above Mobile Tint & ACC",
    "wof:placetype":"venue"
},
  "geometry": {"coordinates":[-95.05926599999999,29.551654],"type":"Point"}
}