{
  "type": "Feature",
  "properties": {
    "iso:country":"US",
    "sg:address":"7439 S Sandhurst Ln",
    "sg:city":"Fort Worth",
    "sg:classifiers":[
        {
            "category":"Home & Garden",
            "subcategory":"Home Furnishings",
            "type":"Retail Goods"
        }
    ],
    "sg:phone":"+1 817 285 8355",
    "sg:postcode":"76180",
    "sg:province":"TX",
    "wof:name":"Green Onion Inc",
    "wof:placetype":"venue"
},
  "geometry": {"coordinates":[-97.22165699999999,32.860882],"type":"Point"}
}