{
  "type": "Feature",
  "properties": {
    "iso:country":"US",
    "sg:address":"116 Plum St",
    "sg:city":"Mabank",
    "sg:classifiers":[
        {
            "category":"Shopping",
            "type":"Retail Goods"
        }
    ],
    "sg:phone":"+1 903 451 5212",
    "sg:postcode":"75156",
    "sg:province":"TX",
    "sg:tags":[
        "merchandise"
    ],
    "wof:name":"Jet Ski Shop",
    "wof:placetype":"venue"
},
  "geometry": {"coordinates":[-96.064742,32.222271],"type":"Point"}
}