{
  "type": "Feature",
  "properties": {
    "iso:country":"US",
    "sg:address":"429 NW Newton Dr",
    "sg:city":"Burleson",
    "sg:classifiers":[
        {
            "category":"Building & Trades",
            "subcategory":"Construction",
            "type":"Services"
        }
    ],
    "sg:phone":"+1 817 447 3758",
    "sg:postcode":"76028",
    "sg:province":"TX",
    "sg:tags":[
        "house"
    ],
    "wof:name":"Creative Building Solutions",
    "wof:placetype":"venue"
},
  "geometry": {"coordinates":[-97.335223,32.545642],"type":"Point"}
}