{
  "type": "Feature",
  "properties": {
    "iso:country":"US",
    "sg:address":"2810 S Soncy Rd",
    "sg:city":"Amarillo",
    "sg:classifiers":[
        {
            "category":"Restaurant",
            "type":"Food & Drink"
        }
    ],
    "sg:menulink":"http://www.allmenus.com/tx/amarillo/82329-applebees/menu/",
    "sg:phone":"+1 806 351 2810",
    "sg:postcode":"79124",
    "sg:province":"TX",
    "sg:tags":[
        "burger",
        "american",
        "sandwich",
        "soup"
    ],
    "wof:name":"Applebee's",
    "wof:placetype":"venue"
},
  "geometry": {"coordinates":[-101.938136,35.182314],"type":"Point"}
}