{
  "type": "Feature",
  "properties": {
    "iso:country":"US",
    "sg:address":"127 Hereford Ln",
    "sg:city":"Bastrop",
    "sg:classifiers":[
        {
            "category":"Shopping",
            "subcategory":"Gifts & Souvenirs",
            "type":"Retail Goods"
        }
    ],
    "sg:phone":"+1 512 303 5537",
    "sg:postcode":"78602",
    "sg:province":"TX",
    "wof:name":"Nmfc",
    "wof:placetype":"venue"
},
  "geometry": {"coordinates":[-97.23329699999999,30.162079],"type":"Point"}
}