{
  "type": "Feature",
  "properties": {
    "iso:country":"US",
    "sg:address":"5718 Champions Glen Dr",
    "sg:city":"Houston",
    "sg:classifiers":[
        {
            "category":"Shopping",
            "type":"Retail Goods"
        }
    ],
    "sg:phone":"+1 832 249 9442",
    "sg:postcode":"77069",
    "sg:province":"TX",
    "sg:tags":[
        "medical",
        "apparatus"
    ],
    "wof:name":"Southwest Ptent Care Solutions",
    "wof:placetype":"venue"
},
  "geometry": {"coordinates":[-95.526938,29.991869],"type":"Point"}
}