{
  "type": "Feature",
  "properties": {
    "iso:country":"US",
    "sg:address":"1601 Ave F",
    "sg:city":"Bay City",
    "sg:classifiers":[
        {
            "category":"Home & Garden",
            "subcategory":"Building Materials",
            "type":"Retail Goods"
        }
    ],
    "sg:phone":"+1 979 244 5994",
    "sg:postcode":"77414",
    "sg:province":"TX",
    "sg:tags":[
        "glass",
        "window",
        "plate"
    ],
    "wof:name":"Big G Auto Glass",
    "wof:placetype":"venue"
},
  "geometry": {"coordinates":[-95.970153,28.988208],"type":"Point"}
}