{
  "type": "Feature",
  "properties": {
    "iso:country":"US",
    "sg:address":"209 W Dannelly St",
    "sg:city":"Hebbronville",
    "sg:classifiers":[
        {
            "category":"Wholesale",
            "subcategory":"Vending Machines",
            "type":"Manufacturing & Wholesale Goods"
        }
    ],
    "sg:phone":"+1 361 527 3905",
    "sg:postcode":"78361",
    "sg:province":"TX",
    "sg:tags":[
        "operator"
    ],
    "wof:name":"Teh Vending Co",
    "wof:placetype":"venue"
},
  "geometry": {"coordinates":[-98.679877,27.300764],"type":"Point"}
}