{
  "type": "Feature",
  "properties": {
    "iso:country":"US",
    "sg:address":"400 W Coffin St",
    "sg:city":"Denison",
    "sg:classifiers":[
        {
            "category":"Home & Garden",
            "subcategory":"Building Materials",
            "type":"Retail Goods"
        }
    ],
    "sg:phone":"+1 903 463 9680",
    "sg:postcode":"75020",
    "sg:province":"TX",
    "sg:tags":[
        "carpentry",
        "contractor"
    ],
    "wof:name":"Frazier Collection Woodworks",
    "wof:placetype":"venue"
},
  "geometry": {"coordinates":[-96.539843,33.732051],"type":"Point"}
}