{
  "type": "Feature",
  "properties": {
    "iso:country":"US",
    "sg:address":"15302 Spring Hill Ln",
    "sg:city":"Pflugerville",
    "sg:classifiers":[
        {
            "category":"Building & Trades",
            "subcategory":"Construction",
            "type":"Services"
        }
    ],
    "sg:phone":"+1 512 252 8522",
    "sg:postcode":"78660",
    "sg:province":"TX",
    "sg:tags":[
        "house"
    ],
    "wof:name":"Joint Effort Customs",
    "wof:placetype":"venue"
},
  "geometry": {"coordinates":[-97.650809,30.446301],"type":"Point"}
}