{
  "type": "Feature",
  "properties": {
    "iso:country":"US",
    "sg:address":"2201 1st St",
    "sg:city":"Rosenberg",
    "sg:classifiers":[
        {
            "category":"Professional",
            "subcategory":"Accounting & Tax Preparation",
            "type":"Services"
        }
    ],
    "sg:phone":"+1 281 232 7954",
    "sg:postcode":"77471",
    "sg:province":"TX",
    "sg:tags":[
        "return",
        "filing"
    ],
    "wof:name":"Security Finance Corp",
    "wof:placetype":"venue"
},
  "geometry": {"coordinates":[-95.808577,29.546153],"type":"Point"}
}