{
  "type": "Feature",
  "properties": {
    "iso:country":"US",
    "sg:address":"7324 Wind Song Dr",
    "sg:city":"El Paso",
    "sg:classifiers":[
        {
            "category":"Shopping",
            "type":"Retail Goods"
        }
    ],
    "sg:phone":"+1 915 581 2296",
    "sg:postcode":"79912",
    "sg:province":"TX",
    "sg:tags":[
        "merchandise"
    ],
    "wof:name":"Alberto Marrero",
    "wof:placetype":"venue"
},
  "geometry": {"coordinates":[-106.55571500000001,31.838875],"type":"Point"}
}