{
  "type": "Feature",
  "properties": {
    "iso:country":"US",
    "sg:address":"2331 N Davis Dr",
    "sg:city":"Arlington",
    "sg:classifiers":[
        {
            "category":"Professional",
            "subcategory":"Management & Consulting",
            "type":"Services"
        }
    ],
    "sg:phone":"+1 817 274 2919",
    "sg:postcode":"76012",
    "sg:province":"TX",
    "sg:tags":[
        "relations",
        "commercial",
        "public",
        "business"
    ],
    "wof:name":"Customizedstuffcom",
    "wof:placetype":"venue"
},
  "geometry": {"coordinates":[-97.122844,32.774127],"type":"Point"}
}