{
  "type": "Feature",
  "properties": {
    "iso:country":"US",
    "sg:address":"806 S Allen Heights Dr",
    "sg:city":"Allen",
    "sg:classifiers":[
        {
            "category":"Restaurant",
            "type":"Food & Drink"
        }
    ],
    "sg:phone":"+1 972 390 7282",
    "sg:postcode":"75002",
    "sg:province":"TX",
    "sg:tags":[
        "eating"
    ],
    "wof:name":"Southern Maid Donut",
    "wof:placetype":"venue"
},
  "geometry": {"coordinates":[-96.64632400000001,33.083895],"type":"Point"}
}