{
  "type": "Feature",
  "properties": {
    "iso:country":"US",
    "sg:address":"408 Main St",
    "sg:city":"Liberty",
    "sg:classifiers":[
        {
            "category":"Professional",
            "subcategory":"Business Services",
            "type":"Services"
        }
    ],
    "sg:phone":"+1 936 336 3339",
    "sg:postcode":"77575",
    "sg:province":"TX",
    "wof:name":"A-K-A Bil Bonds",
    "wof:placetype":"venue"
},
  "geometry": {"coordinates":[-94.79580199999999,30.059768],"type":"Point"}
}