{
  "type": "Feature",
  "properties": {
    "iso:country":"US",
    "sg:address":"15719 Pipers View Dr",
    "sg:city":"Webster",
    "sg:classifiers":[
        {
            "category":"Social Services",
            "subcategory":"Child Care",
            "type":"Services"
        }
    ],
    "sg:phone":"+1 281 480 0281",
    "sg:postcode":"77598",
    "sg:province":"TX",
    "sg:tags":[
        "day"
    ],
    "wof:name":"Marilyn Limardo",
    "wof:placetype":"venue"
},
  "geometry": {"coordinates":[-95.144059,29.552231],"type":"Point"}
}