{
  "type": "Feature",
  "properties": {
    "iso:country":"US",
    "sg:address":"2361 Austin Hwy",
    "sg:city":"San Antonio",
    "sg:classifiers":[
        {
            "category":"Professional",
            "subcategory":"Accounting & Tax Preparation",
            "type":"Services"
        }
    ],
    "sg:phone":"+1 210 930 4748",
    "sg:postcode":"78218",
    "sg:province":"TX",
    "sg:tags":[
        "return",
        "filing"
    ],
    "wof:name":"Income Tax Co",
    "wof:placetype":"venue"
},
  "geometry": {"coordinates":[-98.410802,29.50812],"type":"Point"}
}