{
  "type": "Feature",
  "properties": {
    "iso:country":"US",
    "sg:address":"10006 Co Rd 168",
    "sg:city":"Kaufman",
    "sg:classifiers":[
        {
            "category":"Professional",
            "subcategory":"Computer Services",
            "type":"Services"
        }
    ],
    "sg:phone":"+1 972 962 0422",
    "sg:postcode":"75142",
    "sg:province":"TX",
    "wof:name":"Bodine's PC Svc",
    "wof:placetype":"venue"
},
  "geometry": {"coordinates":[-96.171308,32.529708],"type":"Point"}
}