{
  "type": "Feature",
  "properties": {
    "iso:country":"US",
    "sg:address":"5609 Havre St",
    "sg:city":"Corpus Christi",
    "sg:classifiers":[
        {
            "category":"Real Estate",
            "subcategory":"Real Estate Agent",
            "type":"Services"
        }
    ],
    "sg:phone":"+1 361 854 0531",
    "sg:postcode":"78414",
    "sg:province":"TX",
    "wof:name":"Montgomery RE 2004 LLC",
    "wof:placetype":"venue"
},
  "geometry": {"coordinates":[-97.398962,27.659379],"type":"Point"}
}