{
  "type": "Feature",
  "properties": {
    "iso:country":"US",
    "sg:address":"3948 Legacy Dr",
    "sg:city":"Plano",
    "sg:classifiers":[
        {
            "category":"Shopping",
            "subcategory":"Clothing, Apparel, & Fashions",
            "type":"Retail Goods"
        }
    ],
    "sg:phone":"+1 972 208 8676",
    "sg:postcode":"75023",
    "sg:province":"TX",
    "sg:tags":[
        "tailor"
    ],
    "wof:name":"Style Fashion",
    "wof:placetype":"venue"
},
  "geometry": {"coordinates":[-96.77198799999999,33.071651],"type":"Point"}
}