{
  "type": "Feature",
  "properties": {
    "iso:country":"US",
    "sg:address":"1153 Gibbs St",
    "sg:city":"San Antonio",
    "sg:classifiers":[
        {
            "category":"Retail",
            "subcategory":"Funeral Services",
            "type":"Services"
        }
    ],
    "sg:phone":"+1 210 223 5322",
    "sg:postcode":"78202",
    "sg:province":"TX",
    "sg:tags":[
        "director"
    ],
    "wof:name":"Hardy's Mortuary",
    "wof:placetype":"venue"
},
  "geometry": {"coordinates":[-98.457796,29.421779],"type":"Point"}
}