{
  "type": "Feature",
  "properties": {
    "iso:country":"US",
    "sg:address":"2429 Bissonnet St",
    "sg:city":"Houston",
    "sg:classifiers":[
        {
            "category":"Shopping",
            "subcategory":"Hobbies, Toys, & Games",
            "type":"Retail Goods"
        },
        {
            "category":"Shopping",
            "subcategory":"Crafts & Fabrics",
            "type":"Retail Goods"
        }
    ],
    "sg:phone":"+1 713 526 2216",
    "sg:postcode":"77005",
    "sg:province":"TX",
    "sg:tags":[
        "shop",
        "hobby",
        "art"
    ],
    "sg:website":"www.nomadicnotions.com",
    "wof:name":"Z Bead",
    "wof:placetype":"venue"
},
  "geometry": {"coordinates":[-95.416467,29.725499],"type":"Point"}
}