{
  "type": "Feature",
  "properties": {
    "iso:country":"US",
    "sg:address":"8603 Monroe Rd",
    "sg:city":"Houston",
    "sg:classifiers":[
        {
            "category":"Manufacturing",
            "subcategory":"Metals",
            "type":"Manufacturing & Wholesale Goods"
        },
        {
            "category":"Building & Trades",
            "subcategory":"Construction",
            "type":"Services"
        }
    ],
    "sg:phone":"+1 713 941 1941",
    "sg:postcode":"77061",
    "sg:province":"TX",
    "sg:tags":[
        "steel",
        "detailers",
        "aluminum",
        "warehouse",
        "distributor",
        "structural"
    ],
    "sg:website":"http://www.sss-steel.com",
    "wof:name":"Triple-S Steel Supply",
    "wof:placetype":"venue"
},
  "geometry": {"coordinates":[-95.264732,29.643188],"type":"Point"}
}