{
  "type": "Feature",
  "properties": {
    "iso:country":"US",
    "sg:address":"3932 Richmond St",
    "sg:city":"Odessa",
    "sg:classifiers":[
        {
            "category":"Retail",
            "subcategory":"Repair Shop",
            "type":"Services"
        }
    ],
    "sg:phone":"+1 432 366 0944",
    "sg:postcode":"79762",
    "sg:province":"TX",
    "sg:tags":[
        "welding"
    ],
    "wof:name":"Diamond Ds Welding",
    "wof:placetype":"venue"
},
  "geometry": {"coordinates":[-102.347559,31.896597],"type":"Point"}
}