{
  "type": "Feature",
  "properties": {
    "iso:country":"US",
    "sg:address":"605 N Nolan River Rd",
    "sg:city":"Cleburne",
    "sg:classifiers":[
        {
            "category":"Government",
            "subcategory":"Office",
            "type":"Public Place"
        }
    ],
    "sg:phone":"+1 817 774 3280",
    "sg:postcode":"76033",
    "sg:province":"TX",
    "sg:tags":[
        "armed",
        "force",
        "recruiting"
    ],
    "wof:name":"Air Force Recruiting Office",
    "wof:placetype":"venue"
},
  "geometry": {"coordinates":[-97.426633,32.341242],"type":"Point"}
}