{
  "type": "Feature",
  "properties": {
    "iso:country":"US",
    "sg:address":"701 W 16th St",
    "sg:city":"Big Spring",
    "sg:classifiers":[
        {
            "category":"Farming",
            "subcategory":"Livestock Farm",
            "type":"Manufacturing & Wholesale Goods"
        }
    ],
    "sg:phone":"+1 432 267 6585",
    "sg:postcode":"79720",
    "sg:province":"TX",
    "sg:tags":[
        "beef",
        "feedlot",
        "cattle"
    ],
    "wof:name":"Beal Ranch",
    "wof:placetype":"venue"
},
  "geometry": {"coordinates":[-101.47791599999999,32.238115],"type":"Point"}
}