{
  "type": "Feature",
  "properties": {
    "iso:country":"US",
    "sg:address":"9 Hickory Oak Dr",
    "sg:city":"Spring",
    "sg:classifiers":[
        {
            "category":"Retail",
            "subcategory":"Portrait Studio",
            "type":"Services"
        }
    ],
    "sg:phone":"+1 281 681 9529",
    "sg:postcode":"77381",
    "sg:province":"TX",
    "sg:tags":[
        "photo"
    ],
    "wof:name":"Dt Photographics",
    "wof:placetype":"venue"
},
  "geometry": {"coordinates":[-95.49789800000001,30.178149],"type":"Point"}
}