{
  "type": "Feature",
  "properties": {
    "iso:country":"US",
    "sg:address":"14901 Quorum Dr",
    "sg:city":"Dallas",
    "sg:classifiers":[
        {
            "category":"Professional",
            "type":"Services"
        },
        {
            "category":"Professional",
            "subcategory":"Lawyer & Legal Services",
            "type":"Services"
        }
    ],
    "sg:phone":"+1 972 387 2513",
    "sg:postcode":"75254",
    "sg:province":"TX",
    "sg:tags":[
        "attorney"
    ],
    "wof:name":"Baumgartner Billings & Bloom",
    "wof:placetype":"venue"
},
  "geometry": {"coordinates":[-96.82573600000001,32.948724],"type":"Point"}
}