{
  "type": "Feature",
  "properties": {
    "iso:country":"US",
    "sg:address":"212 US Hwy 377",
    "sg:city":"Aubrey",
    "sg:classifiers":[
        {
            "category":"Building & Trades",
            "subcategory":"Construction",
            "type":"Services"
        }
    ],
    "sg:phone":"+1 940 365 3630",
    "sg:postcode":"76227",
    "sg:province":"TX",
    "sg:tags":[
        "home",
        "builder"
    ],
    "wof:name":"Moore & Smith Builders",
    "wof:placetype":"venue"
},
  "geometry": {"coordinates":[-97.01432200000001,33.234571],"type":"Point"}
}