{
  "type": "Feature",
  "properties": {
    "iso:country":"US",
    "sg:address":"620 N Flores St",
    "sg:city":"Rio Grande City",
    "sg:classifiers":[
        {
            "category":"Professional",
            "subcategory":"Lawyer & Legal Services",
            "type":"Services"
        }
    ],
    "sg:phone":"+1 956 487 0303",
    "sg:postcode":"78582",
    "sg:province":"TX",
    "sg:tags":[
        "attorney"
    ],
    "wof:name":"Jose Luis Garza",
    "wof:placetype":"venue"
},
  "geometry": {"coordinates":[-98.813182,26.382114],"type":"Point"}
}