{
  "type": "Feature",
  "properties": {
    "iso:country":"US",
    "sg:address":"620 E Dewey Pl",
    "sg:city":"San Antonio",
    "sg:classifiers":[
        {
            "category":"Wholesale",
            "subcategory":"Electrical",
            "type":"Manufacturing & Wholesale Goods"
        }
    ],
    "sg:phone":"+1 210 732 9936",
    "sg:postcode":"78212",
    "sg:province":"TX",
    "sg:tags":[
        "equipment",
        "electric",
        "supply"
    ],
    "sg:website":"www.blondlighting.com",
    "wof:name":"Blond Lighting Fixture Supply",
    "wof:placetype":"venue"
},
  "geometry": {"coordinates":[-98.486836,29.446961],"type":"Point"}
}