{
  "type": "Feature",
  "properties": {
    "iso:country":"US",
    "sg:address":"205 Piazza Italia",
    "sg:city":"San Antonio",
    "sg:classifiers":[
        {
            "category":"Organizations",
            "subcategory":"Religious Organization",
            "type":"Services"
        }
    ],
    "sg:phone":"+1 210 227 0548",
    "sg:postcode":"78207",
    "sg:province":"TX",
    "sg:tags":[
        "church"
    ],
    "wof:name":"San Francesco Di Paola Church",
    "wof:placetype":"venue"
},
  "geometry": {"coordinates":[-98.499146,29.430736],"type":"Point"}
}