{
  "type": "Feature",
  "properties": {
    "iso:country":"US",
    "sg:address":"4811 Columbia Ave",
    "sg:city":"Dallas",
    "sg:classifiers":[
        {
            "category":"Health Services",
            "subcategory":"Doctor",
            "type":"Services"
        }
    ],
    "sg:phone":"+1 214 823 5590",
    "sg:postcode":"75226",
    "sg:province":"TX",
    "sg:tags":[
        "medical"
    ],
    "wof:name":"Clinica Medica De Dallas",
    "wof:placetype":"venue"
},
  "geometry": {"coordinates":[-96.763824,32.79517],"type":"Point"}
}