{
  "type": "Feature",
  "properties": {
    "iso:country":"US",
    "sg:address":"3215 Lakehaven Dr",
    "sg:city":"Humble",
    "sg:classifiers":[
        {
            "category":"Building & Trades",
            "subcategory":"Landscaping Services",
            "type":"Services"
        }
    ],
    "sg:phone":"+1 281 358 3216",
    "sg:postcode":"77339",
    "sg:province":"TX",
    "wof:name":"Sundown Lawn Service",
    "wof:placetype":"venue"
},
  "geometry": {"coordinates":[-95.22299700000001,30.059174],"type":"Point"}
}