{
  "type": "Feature",
  "properties": {
    "iso:country":"US",
    "sg:address":"935 W Silversands Dr",
    "sg:city":"San Antonio",
    "sg:classifiers":[
        {
            "category":"Real Estate",
            "subcategory":"Real Estate Operator",
            "type":"Services"
        }
    ],
    "sg:phone":"+1 210 366 1448",
    "sg:postcode":"78216",
    "sg:province":"TX",
    "sg:tags":[
        "building",
        "apartment",
        "management"
    ],
    "wof:name":"Bear Creek Apartments",
    "wof:placetype":"venue"
},
  "geometry": {"coordinates":[-98.50717299999999,29.552024],"type":"Point"}
}