{
  "type": "Feature",
  "properties": {
    "iso:country":"US",
    "sg:address":"2105 Market St",
    "sg:city":"Midland",
    "sg:classifiers":[
        {
            "category":"Mining & Drilling",
            "type":"Manufacturing & Wholesale Goods"
        }
    ],
    "sg:phone":"+1 432 694 9517",
    "sg:postcode":"79703",
    "sg:province":"TX",
    "sg:tags":[
        "field",
        "exploration"
    ],
    "wof:name":"Baker Hughes Inteq",
    "wof:placetype":"venue"
},
  "geometry": {"coordinates":[-102.134793,31.961831],"type":"Point"}
}