{
  "type": "Feature",
  "properties": {
    "iso:country":"US",
    "sg:address":"119 Ave B",
    "sg:city":"Terlingua",
    "sg:classifiers":[
        {
            "category":"Retail",
            "subcategory":"Auto Repair",
            "type":"Services"
        }
    ],
    "sg:phone":"+1 432 371 2666",
    "sg:postcode":"79848",
    "sg:province":"TX",
    "sg:tags":[
        "repairing",
        "automobile"
    ],
    "wof:name":"Bandillo Enterprises",
    "wof:placetype":"venue"
},
  "geometry": {"coordinates":[-102.385124,30.135438],"type":"Point"}
}