{
  "type": "Feature",
  "properties": {
    "iso:country":"US",
    "sg:address":"5602 67th St",
    "sg:city":"Lubbock",
    "sg:classifiers":[
        {
            "category":"Professional",
            "subcategory":"Management & Consulting",
            "type":"Services"
        }
    ],
    "sg:phone":"+1 806 798 1889",
    "sg:postcode":"79424",
    "sg:province":"TX",
    "sg:tags":[
        "business"
    ],
    "wof:name":"Professional Water Management",
    "wof:placetype":"venue"
},
  "geometry": {"coordinates":[-101.933504,33.533326],"type":"Point"}
}