{
  "type": "Feature",
  "properties": {
    "iso:country":"US",
    "sg:address":"14128 Tanglewood Dr",
    "sg:city":"Dallas",
    "sg:classifiers":[
        {
            "category":"Health Services",
            "subcategory":"Doctor",
            "type":"Services"
        }
    ],
    "sg:phone":"+1 972 241 2682",
    "sg:postcode":"75234",
    "sg:province":"TX",
    "wof:name":"Mekker George C MD",
    "wof:placetype":"venue"
},
  "geometry": {"coordinates":[-96.85681200000001,32.93625],"type":"Point"}
}