{
  "type": "Feature",
  "properties": {
    "iso:country":"US",
    "sg:address":"2816 Central Dr",
    "sg:city":"Bedford",
    "sg:classifiers":[
        {
            "category":"Food & Beverages",
            "subcategory":"Specialty",
            "type":"Retail Goods"
        }
    ],
    "sg:phone":"+1 817 685 8300",
    "sg:postcode":"76021",
    "sg:province":"TX",
    "sg:tags":[
        "health",
        "diet"
    ],
    "wof:name":"Nutri-Sport Nutrition Wrhs",
    "wof:placetype":"venue"
},
  "geometry": {"coordinates":[-97.131737,32.851532],"type":"Point"}
}