{
  "type": "Feature",
  "properties": {
    "iso:country":"US",
    "sg:address":"7900 Bellaire Blvd",
    "sg:city":"Houston",
    "sg:classifiers":[
        {
            "category":"Professional",
            "subcategory":"Business Services",
            "type":"Services"
        }
    ],
    "sg:phone":"+1 713 988 5237",
    "sg:postcode":"77036",
    "sg:province":"TX",
    "wof:name":"Roles Express",
    "wof:placetype":"venue"
},
  "geometry": {"coordinates":[-95.525629,29.705112],"type":"Point"}
}