{
  "type": "Feature",
  "properties": {
    "iso:country":"US",
    "sg:address":"4701 Red Bluff Rd",
    "sg:city":"Austin",
    "sg:classifiers":[
        {
            "category":"Building & Trades",
            "subcategory":"Construction",
            "type":"Services"
        }
    ],
    "sg:phone":"+1 512 482 9892",
    "sg:postcode":"78702",
    "sg:province":"TX",
    "sg:tags":[
        "general",
        "contractor"
    ],
    "wof:name":"Pelman Dalle Contruction",
    "wof:placetype":"venue"
},
  "geometry": {"coordinates":[-97.702962,30.251232],"type":"Point"}
}