{
  "type": "Feature",
  "properties": {
    "iso:country":"US",
    "sg:address":"2500 Bee Caves Rd Ste 2244",
    "sg:city":"Austin",
    "sg:classifiers":[
        {
            "category":"Place Of Worship",
            "subcategory":"Church",
            "type":"Public Place"
        },
        {
            "category":"Place Of Worship",
            "type":"Public Place"
        }
    ],
    "sg:phone":"+1 512 327 2500",
    "sg:postcode":"78746",
    "sg:province":"TX",
    "sg:tags":[
        "churches-baptist"
    ],
    "wof:name":"Park Hills Baptist Church",
    "wof:placetype":"venue"
},
  "geometry": {"coordinates":[-97.78325,30.26656],"type":"Point"}
}