{
  "type": "Feature",
  "properties": {
    "iso:country":"US",
    "sg:address":"702 Telephone Rd",
    "sg:city":"Houston",
    "sg:classifiers":[
        {
            "category":"Personal",
            "subcategory":"Beauty Salon",
            "type":"Services"
        }
    ],
    "sg:phone":"+1 713 921 2121",
    "sg:postcode":"77023",
    "sg:province":"TX",
    "sg:tags":[
        "shop"
    ],
    "wof:name":"Patrician Beauty Shop",
    "wof:placetype":"venue"
},
  "geometry": {"coordinates":[-95.33129099999999,29.735036],"type":"Point"}
}