{
  "type": "Feature",
  "properties": {
    "iso:country":"US",
    "sg:address":"5920 Sam Houston Pkwy",
    "sg:city":"Humble",
    "sg:classifiers":[
        {
            "category":"Building & Trades",
            "subcategory":"Cleaning & Sanitation",
            "type":"Services"
        }
    ],
    "sg:phone":"+1 281 441 3885",
    "sg:postcode":"77396",
    "sg:province":"TX",
    "sg:tags":[
        "maintenance"
    ],
    "wof:name":"Tinos Window Cleaning Service",
    "wof:placetype":"venue"
},
  "geometry": {"coordinates":[-95.302829,29.939563],"type":"Point"}
}