{
  "type": "Feature",
  "properties": {
    "iso:country":"US",
    "sg:address":"4414 Denmark St",
    "sg:city":"Houston",
    "sg:classifiers":[
        {
            "category":"Bars & Pubs",
            "type":"Food & Drink"
        },
        {
            "category":"Restaurant",
            "type":"Food & Drink"
        }
    ],
    "sg:phone":"+1 713 633 9819",
    "sg:postcode":"77016",
    "sg:province":"TX",
    "sg:tags":[
        "lounge",
        "drinking",
        "eating",
        "cocktail"
    ],
    "wof:name":"Bruno's Lounge",
    "wof:placetype":"venue"
},
  "geometry": {"coordinates":[-95.325408,29.827336],"type":"Point"}
}