{
  "type": "Feature",
  "properties": {
    "iso:country":"US",
    "sg:address":"509 Hearn St",
    "sg:city":"Austin",
    "sg:classifiers":[
        {
            "category":"Restaurant",
            "type":"Food & Drink"
        }
    ],
    "sg:phone":"+1 512 236 0642",
    "sg:postcode":"78703",
    "sg:province":"TX",
    "sg:tags":[
        "german",
        "modern",
        "french",
        "european"
    ],
    "sg:website":"fabiandrosi.com/",
    "wof:name":"Fabi and Rosi",
    "wof:placetype":"venue"
},
  "geometry": {"coordinates":[-97.772592,30.278931],"type":"Point"}
}