{
  "type": "Feature",
  "properties": {
    "iso:country":"US",
    "sg:address":"31350 Blanco Rd",
    "sg:city":"Bulverde",
    "sg:classifiers":[
        {
            "category":"Professional",
            "subcategory":"Business Services",
            "type":"Services"
        }
    ],
    "sg:phone":"+1 830 980 5222",
    "sg:postcode":"78163",
    "sg:province":"TX",
    "sg:tags":[
        "pressure",
        "washing"
    ],
    "wof:name":"Shine Pressure Washing",
    "wof:placetype":"venue"
},
  "geometry": {"coordinates":[-98.512767,29.757706],"type":"Point"}
}