{
  "type": "Feature",
  "properties": {
    "iso:country":"US",
    "sg:address":"2561 S Main St",
    "sg:city":"Lindale",
    "sg:classifiers":[
        {
            "category":"Home & Garden",
            "subcategory":"Garden Supply",
            "type":"Retail Goods"
        }
    ],
    "sg:phone":"+1 903 882 8688",
    "sg:postcode":"75771",
    "sg:province":"TX",
    "sg:tags":[
        "bamboo",
        "product"
    ],
    "wof:name":"Neal Nursery",
    "wof:placetype":"venue"
},
  "geometry": {"coordinates":[-95.39545,32.482369],"type":"Point"}
}