{
  "type": "Feature",
  "properties": {
    "iso:country":"US",
    "sg:address":"2229 Ave J",
    "sg:city":"Arlington",
    "sg:classifiers":[
        {
            "category":"Professional",
            "subcategory":"Advertising",
            "type":"Services"
        }
    ],
    "sg:phone":"+1 817 459 1180",
    "sg:postcode":"76006",
    "sg:province":"TX",
    "sg:tags":[
        "outdoor"
    ],
    "wof:name":"Metromedia Technologies",
    "wof:placetype":"venue"
},
  "geometry": {"coordinates":[-97.070588,32.767248],"type":"Point"}
}