{
  "type": "Feature",
  "properties": {
    "iso:country":"US",
    "sg:address":"4305 Sarasota Ln",
    "sg:city":"Mc Kinney",
    "sg:classifiers":[
        {
            "category":"Professional",
            "type":"Services"
        }
    ],
    "sg:phone":"+1 972 529 2139",
    "sg:postcode":"75070",
    "sg:province":"TX",
    "wof:name":"Bjons Candle Co",
    "wof:placetype":"venue"
},
  "geometry": {"coordinates":[-96.66779,33.163059],"type":"Point"}
}