{
  "type": "Feature",
  "properties": {
    "iso:country":"US",
    "sg:address":"4815 Waterwood Pass Dr",
    "sg:city":"Elmendorf",
    "sg:classifiers":[
        {
            "category":"Retail",
            "subcategory":"Auto Repair",
            "type":"Services"
        }
    ],
    "sg:phone":"+1 210 621 0427",
    "sg:postcode":"78112",
    "sg:province":"TX",
    "sg:tags":[
        "body"
    ],
    "wof:name":"ABC Sandblasting",
    "wof:placetype":"venue"
},
  "geometry": {"coordinates":[-98.39321099999999,29.185587],"type":"Point"}
}