{
  "type": "Feature",
  "properties": {
    "iso:country":"US",
    "sg:address":"4200 S Hulen St",
    "sg:city":"Fort Worth",
    "sg:classifiers":[
        {
            "category":"Building & Trades",
            "subcategory":"Construction",
            "type":"Services"
        }
    ],
    "sg:phone":"+1 817 377 9340",
    "sg:postcode":"76109",
    "sg:province":"TX",
    "sg:tags":[
        "excavating",
        "contractor"
    ],
    "wof:name":"Cunningham Excavation LP",
    "wof:placetype":"venue"
},
  "geometry": {"coordinates":[-97.39295,32.687701],"type":"Point"}
}