{
  "type": "Feature",
  "properties": {
    "iso:country":"US",
    "sg:address":"10067 Jones Maltsberger Rd",
    "sg:city":"San Antonio",
    "sg:classifiers":[
        {
            "category":"Wholesale",
            "subcategory":"Construction Materials",
            "type":"Manufacturing & Wholesale Goods"
        }
    ],
    "sg:phone":"+1 210 979 0701",
    "sg:postcode":"78216",
    "sg:province":"TX",
    "sg:tags":[
        "granite",
        "marble",
        "install"
    ],
    "wof:name":"Bellezza Marble & Granite Inc",
    "wof:placetype":"venue"
},
  "geometry": {"coordinates":[-98.483969,29.533639],"type":"Point"}
}