{
  "type": "Feature",
  "properties": {
    "iso:country":"US",
    "sg:address":"2832 S Main St",
    "sg:city":"Ingleside",
    "sg:classifiers":[
        {
            "category":"Insurance",
            "subcategory":"Insurance Agent",
            "type":"Services"
        }
    ],
    "sg:phone":"+1 361 776 9686",
    "sg:postcode":"78362",
    "sg:province":"TX",
    "wof:name":"Farmers Insurance",
    "wof:placetype":"venue"
},
  "geometry": {"coordinates":[-97.211067,27.879101],"type":"Point"}
}