{
  "type": "Feature",
  "properties": {
    "iso:country":"US",
    "sg:address":"6230 N Navarro St",
    "sg:city":"Victoria",
    "sg:classifiers":[
        {
            "category":"Utilities",
            "subcategory":"Telephone",
            "type":"Services"
        }
    ],
    "sg:phone":"+1 361 576 4445",
    "sg:postcode":"77904",
    "sg:province":"TX",
    "sg:tags":[
        "communications"
    ],
    "wof:name":"Sprint",
    "wof:placetype":"venue"
},
  "geometry": {"coordinates":[-96.996983,28.854444],"type":"Point"}
}