{
  "type": "Feature",
  "properties": {
    "iso:country":"US",
    "sg:address":"402 E C Ave",
    "sg:city":"Kingsville",
    "sg:classifiers":[
        {
            "category":"Building & Trades",
            "subcategory":"Construction",
            "type":"Services"
        }
    ],
    "sg:phone":"+1 361 592 1774",
    "sg:postcode":"78363",
    "sg:province":"TX",
    "sg:tags":[
        "system",
        "specialty",
        "heating",
        "contractor",
        "air conditioning"
    ],
    "wof:name":"Econ Heating And A/C",
    "wof:placetype":"venue"
},
  "geometry": {"coordinates":[-97.864824,27.52772],"type":"Point"}
}