{
  "type": "Feature",
  "properties": {
    "iso:country":"US",
    "sg:address":"132 N Glenville Dr Ste A",
    "sg:city":"Richardson",
    "sg:classifiers":[
        {
            "category":"Professional",
            "subcategory":"Lawyer & Legal Services",
            "type":"Services"
        }
    ],
    "sg:phone":"+1 972 994 9988",
    "sg:postcode":"75081",
    "sg:province":"TX",
    "wof:name":"Yu South & Associates",
    "wof:placetype":"venue"
},
  "geometry": {"coordinates":[-96.70481100000001,32.946942],"type":"Point"}
}