{
  "type": "Feature",
  "properties": {
    "iso:country":"US",
    "sg:address":"4210 Spring Valley Rd",
    "sg:city":"Dallas",
    "sg:classifiers":[
        {
            "category":"Building & Trades",
            "subcategory":"Construction",
            "type":"Services"
        }
    ],
    "sg:phone":"+1 972 980 9076",
    "sg:postcode":"75244",
    "sg:province":"TX",
    "sg:tags":[
        "interior",
        "design"
    ],
    "wof:name":"Guardian Interior Design",
    "wof:placetype":"venue"
},
  "geometry": {"coordinates":[-96.83577200000001,32.939591],"type":"Point"}
}