{
  "type": "Feature",
  "properties": {
    "iso:country":"US",
    "sg:address":"10441 Channel Dr",
    "sg:city":"Dallas",
    "sg:classifiers":[
        {
            "category":"Communications",
            "type":"Services"
        }
    ],
    "sg:phone":"+1 214 902 9997",
    "sg:postcode":"75229",
    "sg:province":"TX",
    "wof:name":"Efi Communications",
    "wof:placetype":"venue"
},
  "geometry": {"coordinates":[-96.88032,32.889519],"type":"Point"}
}