{
  "type": "Feature",
  "properties": {
    "iso:country":"US",
    "sg:address":"537 Elm St",
    "sg:city":"Hurst",
    "sg:classifiers":[
        {
            "category":"Organizations",
            "subcategory":"Religious Organization",
            "type":"Services"
        }
    ],
    "sg:phone":"+1 817 282 8767",
    "sg:postcode":"76053",
    "sg:province":"TX",
    "sg:tags":[
        "church"
    ],
    "wof:name":"First United Methodist",
    "wof:placetype":"venue"
},
  "geometry": {"coordinates":[-97.17826599999999,32.819416],"type":"Point"}
}