{
  "type": "Feature",
  "properties": {
    "iso:country":"US",
    "sg:address":"2801 W Main St",
    "sg:city":"Ingleside",
    "sg:classifiers":[
        {
            "category":"Manufacturing",
            "subcategory":"Metals",
            "type":"Manufacturing & Wholesale Goods"
        },
        {
            "category":"Personal",
            "type":"Services"
        }
    ],
    "sg:phone":"+1 361 776 2071",
    "sg:postcode":"78362",
    "sg:province":"TX",
    "sg:tags":[
        "color",
        "consultant",
        "coating",
        "custom",
        "parts",
        "powder",
        "auto",
        "marine"
    ],
    "wof:name":"Cove Color Coating",
    "wof:placetype":"venue"
},
  "geometry": {"coordinates":[-97.214811,27.882141],"type":"Point"}
}