{
  "type": "Feature",
  "properties": {
    "iso:country":"US",
    "sg:address":"7071 San Pedro Ave",
    "sg:city":"San Antonio",
    "sg:classifiers":[
        {
            "category":"Health Services",
            "subcategory":"Chiropractor",
            "type":"Services"
        }
    ],
    "sg:phone":"+1 210 342 1356",
    "sg:postcode":"78216",
    "sg:province":"TX",
    "wof:name":"San Antnio Chrpractic Hlth Ctr",
    "wof:placetype":"venue"
},
  "geometry": {"coordinates":[-98.499351,29.509764],"type":"Point"}
}