{
  "type": "Feature",
  "properties": {
    "iso:country":"US",
    "sg:address":"2319 W Dallas St",
    "sg:city":"Houston",
    "sg:classifiers":[
        {
            "category":"Utilities",
            "subcategory":"Electric",
            "type":"Services"
        }
    ],
    "sg:phone":"+1 713 207 4512",
    "sg:postcode":"77019",
    "sg:province":"TX",
    "sg:tags":[
        "combination"
    ],
    "wof:name":"Centerpint Enrgy Hston Elc LLC",
    "wof:placetype":"venue"
},
  "geometry": {"coordinates":[-95.391715,29.7574],"type":"Point"}
}