{
  "type": "Feature",
  "properties": {
    "iso:country":"US",
    "sg:address":"2668 S 31st St",
    "sg:city":"Temple",
    "sg:classifiers":[
        {
            "category":"Restaurant",
            "type":"Food & Drink"
        }
    ],
    "sg:menulink":"http://www.allmenus.com/tx/temple/77607-papa-murphys/menu/",
    "sg:phone":"+1 254 778 6600",
    "sg:postcode":"76504",
    "sg:province":"TX",
    "sg:tags":[
        "american",
        "pizza"
    ],
    "wof:name":"Papa Murphy's",
    "wof:placetype":"venue"
},
  "geometry": {"coordinates":[-97.367366,31.075021],"type":"Point"}
}