{
  "type": "Feature",
  "properties": {
    "iso:country":"US",
    "sg:address":"5857 Leopard St",
    "sg:city":"Corpus Christi",
    "sg:classifiers":[
        {
            "category":"Food & Beverages",
            "subcategory":"Groceries & Convenience Stores",
            "type":"Retail Goods"
        }
    ],
    "sg:phone":"+1 361 289 2624",
    "sg:postcode":"78408",
    "sg:province":"TX",
    "wof:name":"Times Market",
    "wof:placetype":"venue"
},
  "geometry": {"coordinates":[-97.47859800000001,27.797716],"type":"Point"}
}