{
  "type": "Feature",
  "properties": {
    "iso:country":"US",
    "sg:address":"9355 Jamaica Beach",
    "sg:city":"Galveston",
    "sg:classifiers":[
        {
            "category":"Building & Trades",
            "subcategory":"Pest Control",
            "type":"Services"
        }
    ],
    "sg:phone":"+1 409 737 3200",
    "sg:postcode":"77554",
    "sg:province":"TX",
    "wof:name":"Esco Pest Control",
    "wof:placetype":"venue"
},
  "geometry": {"coordinates":[-94.977223,29.178947],"type":"Point"}
}