{
  "type": "Feature",
  "properties": {
    "iso:country":"US",
    "sg:address":"2532 Valley View Ln",
    "sg:city":"Farmers Branch",
    "sg:classifiers":[
        {
            "category":"Autos & Motor Vehicles",
            "subcategory":"Automobile Sales",
            "type":"Retail Goods"
        }
    ],
    "sg:phone":"+1 972 241 6860",
    "sg:postcode":"75234",
    "sg:province":"TX",
    "sg:tags":[
        "car",
        "dealer"
    ],
    "wof:name":"A R Motor Sales",
    "wof:placetype":"venue"
},
  "geometry": {"coordinates":[-96.89504700000001,32.923797],"type":"Point"}
}