{
  "type": "Feature",
  "properties": {
    "iso:country":"US",
    "sg:address":"1725 W Airport Fwy",
    "sg:city":"Euless",
    "sg:classifiers":[
        {
            "category":"Restaurant",
            "type":"Food & Drink"
        }
    ],
    "sg:phone":"+1 817 868 0086",
    "sg:postcode":"76040",
    "sg:province":"TX",
    "sg:tags":[
        "eating"
    ],
    "wof:name":"Peking Restaurant Inc",
    "wof:placetype":"venue"
},
  "geometry": {"coordinates":[-97.110276,32.837279],"type":"Point"}
}