{
  "type": "Feature",
  "properties": {
    "iso:country":"US",
    "sg:address":"1413 Gessner Dr",
    "sg:city":"Houston",
    "sg:classifiers":[
        {
            "category":"Banks & Credit Unions",
            "subcategory":"Bank",
            "type":"Services"
        }
    ],
    "sg:phone":"+1 713 467 2318",
    "sg:postcode":"77080",
    "sg:province":"TX",
    "sg:tags":[
        "money",
        "order"
    ],
    "wof:name":"IXC Dollar Express",
    "wof:placetype":"venue"
},
  "geometry": {"coordinates":[-95.54480700000001,29.796152],"type":"Point"}
}