{
  "type": "Feature",
  "properties": {
    "iso:country":"US",
    "sg:address":"1626 Forest Ln S Ste A",
    "sg:city":"Garland",
    "sg:classifiers":[
        {
            "category":"Shopping",
            "subcategory":"Optician",
            "type":"Retail Goods"
        }
    ],
    "sg:phone":"+1 972 494 2830",
    "sg:postcode":"75042",
    "sg:province":"TX",
    "sg:tags":[
        "eyewear"
    ],
    "sg:website":"www.oculensoptical.com",
    "wof:name":"Oculens Optical Shop",
    "wof:placetype":"venue"
},
  "geometry": {"coordinates":[-96.64949799999999,32.909698],"type":"Point"}
}