{
  "type": "Feature",
  "properties": {
    "iso:country":"US",
    "sg:address":"5868 Westheimer Rd",
    "sg:city":"Houston",
    "sg:classifiers":[
        {
            "category":"Professional",
            "subcategory":"Lawyer & Legal Services",
            "type":"Services"
        }
    ],
    "sg:phone":"+1 713 296 9242",
    "sg:postcode":"77057",
    "sg:province":"TX",
    "sg:tags":[
        "attorney"
    ],
    "wof:name":"John S Fason",
    "wof:placetype":"venue"
},
  "geometry": {"coordinates":[-95.483085,29.737823],"type":"Point"}
}