{
  "type": "Feature",
  "properties": {
    "iso:country":"US",
    "sg:address":"1408 Orange Ave",
    "sg:city":"Nederland",
    "sg:classifiers":[
        {
            "category":"Professional",
            "subcategory":"Business Services",
            "type":"Services"
        }
    ],
    "sg:phone":"+1 409 727 5187",
    "sg:postcode":"77627",
    "sg:province":"TX",
    "wof:name":"Shane Isom Memorial Foundation",
    "wof:placetype":"venue"
},
  "geometry": {"coordinates":[-94.003507,29.981207],"type":"Point"}
}