{
  "type": "Feature",
  "properties": {
    "iso:country":"US",
    "sg:address":"5952 Royal Ln",
    "sg:city":"Dallas",
    "sg:classifiers":[
        {
            "category":"Manufacturing",
            "subcategory":"Signs",
            "type":"Manufacturing & Wholesale Goods"
        }
    ],
    "sg:phone":"+1 214 750 7438",
    "sg:postcode":"75230",
    "sg:province":"TX",
    "sg:tags":[
        "specialty",
        "mfg"
    ],
    "wof:name":"Robert H Yeakey & Associates",
    "wof:placetype":"venue"
},
  "geometry": {"coordinates":[-96.80391,32.894917],"type":"Point"}
}