{
  "type": "Feature",
  "properties": {
    "iso:country":"US",
    "sg:address":"3700 Forums Dr",
    "sg:city":"Flower Mound",
    "sg:classifiers":[
        {
            "category":"Professional",
            "subcategory":"Business Services",
            "type":"Services"
        }
    ],
    "sg:phone":"+1 972 539 8298",
    "sg:postcode":"75028",
    "sg:province":"TX",
    "wof:name":"Convention Meeting",
    "wof:placetype":"venue"
},
  "geometry": {"coordinates":[-97.06570000000001,33.03515],"type":"Point"}
}