{
  "type": "Feature",
  "properties": {
    "iso:country":"US",
    "sg:address":"1138 Kingswood Dr",
    "sg:city":"Marble Falls",
    "sg:classifiers":[
        {
            "category":"Building & Trades",
            "subcategory":"Construction",
            "type":"Services"
        }
    ],
    "sg:phone":"+1 830 598 7479",
    "sg:postcode":"78654",
    "sg:province":"TX",
    "sg:tags":[
        "house"
    ],
    "wof:name":"Sanchez Construction",
    "wof:placetype":"venue"
},
  "geometry": {"coordinates":[-98.35545399999999,30.600983],"type":"Point"}
}