{
  "type": "Feature",
  "properties": {
    "iso:country":"US",
    "sg:address":"1701 Upland Dr",
    "sg:city":"Houston",
    "sg:classifiers":[
        {
            "category":"Manufacturing",
            "subcategory":"Glass & Minerals",
            "type":"Manufacturing & Wholesale Goods"
        }
    ],
    "sg:phone":"+1 713 984 8921",
    "sg:postcode":"77043",
    "sg:province":"TX",
    "sg:tags":[
        "mfg",
        "member",
        "concrete",
        "ready",
        "organization",
        "religious"
    ],
    "wof:name":"Human Mix Athletic Club I",
    "wof:placetype":"venue"
},
  "geometry": {"coordinates":[-95.576689,29.794874],"type":"Point"}
}