{
  "type": "Feature",
  "properties": {
    "iso:country":"US",
    "sg:address":"1223 Hwy 332",
    "sg:city":"Clute",
    "sg:classifiers":[
        {
            "category":"Retail",
            "subcategory":"Auto Rental",
            "type":"Services"
        }
    ],
    "sg:phone":"+1 979 265 0088",
    "sg:postcode":"77531",
    "sg:province":"TX",
    "sg:tags":[
        "renting",
        "automobile"
    ],
    "wof:name":"Enterprise Rent-A-Car",
    "wof:placetype":"venue"
},
  "geometry": {"coordinates":[-95.41667,29.009965],"type":"Point"}
}