{
  "type": "Feature",
  "properties": {
    "iso:country":"US",
    "sg:address":"621 W 5th St",
    "sg:city":"Clifton",
    "sg:classifiers":[
        {
            "category":"Restaurant",
            "type":"Food & Drink"
        }
    ],
    "sg:phone":"+1 254 675 1718",
    "sg:postcode":"76634",
    "sg:province":"TX",
    "sg:tags":[
        "eating"
    ],
    "wof:name":"Gerald Winnett",
    "wof:placetype":"venue"
},
  "geometry": {"coordinates":[-97.57714900000001,31.782355],"type":"Point"}
}