{
  "type": "Feature",
  "properties": {
    "iso:country":"US",
    "sg:address":"1207 N Wheeler St",
    "sg:city":"Victoria",
    "sg:classifiers":[
        {
            "category":"Mining & Drilling",
            "type":"Manufacturing & Wholesale Goods"
        }
    ],
    "sg:phone":"+1 361 576 1088",
    "sg:postcode":"77901",
    "sg:province":"TX",
    "sg:tags":[
        "oil",
        "well"
    ],
    "wof:name":"C & S Well Svc",
    "wof:placetype":"venue"
},
  "geometry": {"coordinates":[-97.000579,28.806562],"type":"Point"}
}