{
  "type": "Feature",
  "properties": {
    "iso:country":"US",
    "sg:address":"11923 Elam Rd Ste 103",
    "sg:city":"Mesquite",
    "sg:classifiers":[
        {
            "category":"Utilities",
            "subcategory":"Mobile Phone",
            "type":"Services"
        },
        {
            "category":"Shopping",
            "subcategory":"Mobile Phones",
            "type":"Retail Goods"
        },
        {
            "category":"Utilities",
            "subcategory":"Telephone",
            "type":"Services"
        },
        {
            "category":"Manufacturing",
            "subcategory":"Electronics",
            "type":"Manufacturing & Wholesale Goods"
        }
    ],
    "sg:phone":"+1 972 557 0166",
    "sg:postcode":"75180",
    "sg:province":"TX",
    "sg:tags":[
        "telecommunications-equipment",
        "supply",
        "communication",
        "system",
        "wireless",
        "equipment",
        "cellular"
    ],
    "wof:name":"MetroPCS",
    "wof:placetype":"venue"
},
  "geometry": {"coordinates":[-96.620949,32.719506],"type":"Point"}
}