{
  "type": "Feature",
  "properties": {
    "iso:country":"US",
    "sg:address":"6082 FM 775",
    "sg:city":"Seguin",
    "sg:classifiers":[
        {
            "category":"Health Services",
            "subcategory":"Clinic",
            "type":"Services"
        }
    ],
    "sg:phone":"+1 830 303 0973",
    "sg:postcode":"78155",
    "sg:province":"TX",
    "sg:tags":[
        "home",
        "care"
    ],
    "wof:name":"Diversity Home Care Inc",
    "wof:placetype":"venue"
},
  "geometry": {"coordinates":[-98.075315,29.491946],"type":"Point"}
}