{
  "type": "Feature",
  "properties": {
    "iso:country":"US",
    "sg:address":"2500 Procter St",
    "sg:city":"Port Arthur",
    "sg:classifiers":[
        {
            "category":"Retail",
            "subcategory":"Funeral Services",
            "type":"Services"
        }
    ],
    "sg:phone":"+1 409 983 6661",
    "sg:postcode":"77640",
    "sg:province":"TX",
    "sg:tags":[
        "director"
    ],
    "wof:name":"Gabriel Funeral Home Inc",
    "wof:placetype":"venue"
},
  "geometry": {"coordinates":[-93.919702,29.887829],"type":"Point"}
}