{
  "type": "Feature",
  "properties": {
    "iso:country":"US",
    "sg:address":"616 Eagles Nest Dr",
    "sg:city":"Hewitt",
    "sg:classifiers":[
        {
            "category":"Shopping",
            "subcategory":"Computers & Home Electronics",
            "type":"Retail Goods"
        }
    ],
    "sg:phone":"+1 254 420 3891",
    "sg:postcode":"76643",
    "sg:province":"TX",
    "wof:name":"Special Fx Video Game Exchange",
    "wof:placetype":"venue"
},
  "geometry": {"coordinates":[-97.200155,31.446565],"type":"Point"}
}