{
  "type": "Feature",
  "properties": {
    "iso:country":"US",
    "sg:address":"6067 McArdle Rd",
    "sg:city":"Corpus Christi",
    "sg:classifiers":[
        {
            "category":"Banks & Credit Unions",
            "subcategory":"Bank",
            "type":"Services"
        }
    ],
    "sg:phone":"+1 361 886 6550",
    "sg:postcode":"78412",
    "sg:province":"TX",
    "wof:name":"Wells Fargo Bank",
    "wof:placetype":"venue"
},
  "geometry": {"coordinates":[-97.35827999999999,27.706046],"type":"Point"}
}