{
  "type": "Feature",
  "properties": {
    "iso:country":"US",
    "sg:address":"209 W California St",
    "sg:city":"Gainesville",
    "sg:classifiers":[
        {
            "category":"Professional",
            "subcategory":"Accounting & Tax Preparation",
            "type":"Services"
        },
        {
            "category":"Professional",
            "subcategory":"Business Services",
            "type":"Services"
        }
    ],
    "sg:phone":"+1 940 668 1209",
    "sg:postcode":"76240",
    "sg:province":"TX",
    "sg:tags":[
        "consultant",
        "coach",
        "bookkeeping"
    ],
    "wof:name":"L C Consulting",
    "wof:placetype":"venue"
},
  "geometry": {"coordinates":[-97.146227,33.624292],"type":"Point"}
}