{
  "type": "Feature",
  "properties": {
    "iso:country":"US",
    "sg:address":"616 E Centre Park Blvd",
    "sg:city":"De Soto",
    "sg:classifiers":[
        {
            "category":"Building & Trades",
            "subcategory":"Construction",
            "type":"Services"
        }
    ],
    "sg:phone":"+1 972 223 4448",
    "sg:postcode":"75115",
    "sg:province":"TX",
    "sg:tags":[
        "commercial",
        "contractor"
    ],
    "wof:name":"Lucky Construction Inc",
    "wof:placetype":"venue"
},
  "geometry": {"coordinates":[-96.843661,32.623962],"type":"Point"}
}