{
  "type": "Feature",
  "properties": {
    "iso:country":"US",
    "sg:address":"17800 Country Club Dr",
    "sg:city":"Kemp",
    "sg:classifiers":[
        {
            "category":"Professional",
            "subcategory":"Management & Consulting",
            "type":"Services"
        }
    ],
    "sg:phone":"+1 903 498 4007",
    "sg:postcode":"75143",
    "sg:province":"TX",
    "sg:tags":[
        "telecommunication"
    ],
    "wof:name":"Brown Communications Group",
    "wof:placetype":"venue"
},
  "geometry": {"coordinates":[-96.164661,32.389348],"type":"Point"}
}