{
  "type": "Feature",
  "properties": {
    "iso:country":"US",
    "sg:address":"919 N Conway Ave",
    "sg:city":"Mission",
    "sg:classifiers":[
        {
            "category":"Shopping",
            "subcategory":"Shoes",
            "type":"Retail Goods"
        }
    ],
    "sg:phone":"+1 956 585 7572",
    "sg:postcode":"78572",
    "sg:province":"TX",
    "sg:tags":[
        "clothing"
    ],
    "wof:name":"Yolis",
    "wof:placetype":"venue"
},
  "geometry": {"coordinates":[-98.32575,26.215776],"type":"Point"}
}