{
  "type": "Feature",
  "properties": {
    "iso:country":"US",
    "sg:address":"18702 Platte River Way",
    "sg:city":"Dallas",
    "sg:classifiers":[
        {
            "category":"Professional",
            "type":"Services"
        }
    ],
    "sg:phone":"+1 972 306 7950",
    "sg:postcode":"75287",
    "sg:province":"TX",
    "wof:name":"Boyz L Louisiana L",
    "wof:placetype":"venue"
},
  "geometry": {"coordinates":[-96.86246800000001,33.008518],"type":"Point"}
}