{
  "type": "Feature",
  "properties": {
    "iso:country":"US",
    "sg:address":"1295 US Hwy 84",
    "sg:city":"Teague",
    "sg:classifiers":[
        {
            "category":"Organizations",
            "subcategory":"Religious Organization",
            "type":"Services"
        }
    ],
    "sg:phone":"+1 254 739 3764",
    "sg:postcode":"75860",
    "sg:province":"TX",
    "wof:name":"Faith Baptist",
    "wof:placetype":"venue"
},
  "geometry": {"coordinates":[-96.313793,31.653745],"type":"Point"}
}