{
  "type": "Feature",
  "properties": {
    "iso:country":"US",
    "sg:address":"535 S Mesa Hills Dr",
    "sg:city":"El Paso",
    "sg:classifiers":[
        {
            "category":"Real Estate",
            "subcategory":"Real Estate Operator",
            "type":"Services"
        }
    ],
    "sg:phone":"+1 915 584 5411",
    "sg:postcode":"79912",
    "sg:province":"TX",
    "sg:tags":[
        "apartment",
        "complex"
    ],
    "wof:name":"The Ryans Crossing",
    "wof:placetype":"venue"
},
  "geometry": {"coordinates":[-106.53743900000001,31.816269],"type":"Point"}
}