{
  "type": "Feature",
  "properties": {
    "iso:country":"US",
    "sg:address":"8300 Research Blvd",
    "sg:city":"Austin",
    "sg:classifiers":[
        {
            "category":"Communications",
            "subcategory":"Film & Video Production",
            "type":"Services"
        }
    ],
    "sg:phone":"+1 512 419 1166",
    "sg:postcode":"78758",
    "sg:province":"TX",
    "sg:tags":[
        "dvd",
        "cassette",
        "duplicating",
        "cd"
    ],
    "sg:website":"http://www.replicopy.com",
    "wof:name":"Replicopy Digital Media Center",
    "wof:placetype":"venue"
},
  "geometry": {"coordinates":[-97.715469,30.35556],"type":"Point"}
}