{
  "type": "Feature",
  "properties": {
    "iso:country":"US",
    "sg:address":"216 Brown St Apt C",
    "sg:city":"Longview",
    "sg:classifiers":[
        {
            "category":"Utilities",
            "subcategory":"Telephone",
            "type":"Services"
        },
        {
            "category":"Communications",
            "type":"Services"
        },
        {
            "category":"Building & Trades",
            "subcategory":"Electrical",
            "type":"Services"
        },
        {
            "category":"Professional",
            "subcategory":"Computer Services",
            "type":"Services"
        }
    ],
    "sg:phone":"+1 903 236 6852",
    "sg:postcode":"75601",
    "sg:province":"TX",
    "sg:tags":[
        "television",
        "wire",
        "installation",
        "systems-repair",
        "cable",
        "system",
        "contractor",
        "equipment"
    ],
    "wof:name":"A C Systems",
    "wof:placetype":"venue"
},
  "geometry": {"coordinates":[-94.747451,32.497171],"type":"Point"}
}