{
  "type": "Feature",
  "properties": {
    "iso:country":"US",
    "sg:address":"741 Water St",
    "sg:city":"Kerrville",
    "sg:classifiers":[
        {
            "category":"Banks & Credit Unions",
            "subcategory":"Investment Brokerage",
            "type":"Services"
        }
    ],
    "sg:phone":"+1 830 896 5300",
    "sg:postcode":"78028",
    "sg:province":"TX",
    "sg:tags":[
        "security"
    ],
    "wof:name":"Charles Schreiner Co",
    "wof:placetype":"venue"
},
  "geometry": {"coordinates":[-99.141328,30.046077],"type":"Point"}
}