{
  "type": "Feature",
  "properties": {
    "iso:country":"US",
    "sg:address":"7300 Riley Rd",
    "sg:city":"Bryan",
    "sg:classifiers":[
        {
            "category":"Manufacturing",
            "subcategory":"Tools & Machinery",
            "type":"Manufacturing & Wholesale Goods"
        }
    ],
    "sg:phone":"+1 979 589 3769",
    "sg:postcode":"77808",
    "sg:province":"TX",
    "sg:tags":[
        "surgical",
        "mfg"
    ],
    "wof:name":"A Womans Image",
    "wof:placetype":"venue"
},
  "geometry": {"coordinates":[-96.22960399999999,30.739765],"type":"Point"}
}