{
  "type": "Feature",
  "properties": {
    "iso:country":"US",
    "sg:address":"1116 Co Rd 223",
    "sg:city":"Giddings",
    "sg:classifiers":[
        {
            "category":"Retail",
            "subcategory":"Repair Shop",
            "type":"Services"
        }
    ],
    "sg:phone":"+1 979 366 2317",
    "sg:postcode":"78942",
    "sg:province":"TX",
    "sg:tags":[
        "welding"
    ],
    "wof:name":"Zimmerhanzel Welding Service",
    "wof:placetype":"venue"
},
  "geometry": {"coordinates":[-96.92021,30.153325],"type":"Point"}
}