{
  "type": "Feature",
  "properties": {
    "iso:country":"US",
    "sg:address":"810 Lee St",
    "sg:city":"Kerrville",
    "sg:classifiers":[
        {
            "category":"Shopping",
            "subcategory":"Hobbies, Toys, & Games",
            "type":"Retail Goods"
        }
    ],
    "sg:phone":"+1 830 895 4886",
    "sg:postcode":"78028",
    "sg:province":"TX",
    "wof:name":"Pamela A Roberts",
    "wof:placetype":"venue"
},
  "geometry": {"coordinates":[-99.15569499999999,30.061959],"type":"Point"}
}