{
  "type": "Feature",
  "properties": {
    "iso:country":"US",
    "sg:address":"4800 Sugar Grove Blvd",
    "sg:city":"Stafford",
    "sg:classifiers":[
        {
            "category":"Building & Trades",
            "subcategory":"Construction",
            "type":"Services"
        }
    ],
    "sg:phone":"+1 281 240 0707",
    "sg:postcode":"77477",
    "sg:province":"TX",
    "sg:tags":[
        "designer",
        "dealer",
        "pool",
        "swimming"
    ],
    "wof:name":"Anthony Pools",
    "wof:placetype":"venue"
},
  "geometry": {"coordinates":[-95.582014,29.643214],"type":"Point"}
}