{
  "type": "Feature",
  "properties": {
    "iso:country":"US",
    "sg:address":"37 Walnut Grove Rd",
    "sg:city":"Boerne",
    "sg:classifiers":[
        {
            "category":"Travel",
            "subcategory":"Hotels & Motels",
            "type":"Entertainment"
        }
    ],
    "sg:phone":"+1 830 537 3883",
    "sg:postcode":"78006",
    "sg:province":"TX",
    "wof:name":"Walnut Grove Inn & Yoga Studio",
    "wof:placetype":"venue"
},
  "geometry": {"coordinates":[-98.734697,29.858158],"type":"Point"}
}