{
  "type": "Feature",
  "properties": {
    "iso:country":"US",
    "sg:address":"2591 Dallas Pkwy",
    "sg:city":"Frisco",
    "sg:classifiers":[
        {
            "category":"Professional",
            "subcategory":"Lawyer & Legal Services",
            "type":"Services"
        }
    ],
    "sg:phone":"+1 214 618 7970",
    "sg:postcode":"75034",
    "sg:province":"TX",
    "wof:name":"Altland Kelty & Trahan Attys",
    "wof:placetype":"venue"
},
  "geometry": {"coordinates":[-96.823415,33.330288],"type":"Point"}
}