{
  "type": "Feature",
  "properties": {
    "iso:country":"US",
    "sg:address":"3616 Euclid Ave",
    "sg:city":"Dallas",
    "sg:classifiers":[
        {
            "category":"Banks & Credit Unions",
            "subcategory":"Financial Services",
            "type":"Services"
        }
    ],
    "sg:phone":"+1 214 528 3254",
    "sg:postcode":"75205",
    "sg:province":"TX",
    "sg:tags":[
        "investor"
    ],
    "wof:name":"Hww Management Services",
    "wof:placetype":"venue"
},
  "geometry": {"coordinates":[-96.793834,32.827311],"type":"Point"}
}