{
  "type": "Feature",
  "properties": {
    "iso:country":"US",
    "sg:address":"11806 Nene Dr",
    "sg:city":"Austin",
    "sg:classifiers":[
        {
            "category":"Wholesale",
            "subcategory":"Office Equipment",
            "type":"Manufacturing & Wholesale Goods"
        }
    ],
    "sg:phone":"+1 512 453 5867",
    "sg:postcode":"78750",
    "sg:province":"TX",
    "wof:name":"Jumpware",
    "wof:placetype":"venue"
},
  "geometry": {"coordinates":[-97.800692,30.449805],"type":"Point"}
}