{
  "type": "Feature",
  "properties": {
    "iso:country":"US",
    "sg:address":"17511 Forest Mist Dr",
    "sg:city":"Spring",
    "sg:classifiers":[
        {
            "category":"Professional",
            "subcategory":"Art Services",
            "type":"Services"
        }
    ],
    "sg:phone":"+1 281 379 2071",
    "sg:postcode":"77379",
    "sg:province":"TX",
    "sg:tags":[
        "commercial",
        "design"
    ],
    "wof:name":"Gidget Graphics",
    "wof:placetype":"venue"
},
  "geometry": {"coordinates":[-95.520595,30.034018],"type":"Point"}
}