{
  "type": "Feature",
  "properties": {
    "iso:country":"US",
    "sg:address":"207 E Sunset Rd",
    "sg:city":"San Antonio",
    "sg:classifiers":[
        {
            "category":"Building & Trades",
            "subcategory":"Construction",
            "type":"Services"
        }
    ],
    "sg:phone":"+1 210 680 8300",
    "sg:postcode":"78209",
    "sg:province":"TX",
    "sg:tags":[
        "asbestos",
        "removal"
    ],
    "wof:name":"Olmos Environmental Svc Inc",
    "wof:placetype":"venue"
},
  "geometry": {"coordinates":[-98.46212,29.507295],"type":"Point"}
}