{
  "type": "Feature",
  "properties": {
    "iso:country":"US",
    "sg:address":"1811 Fresno Rd",
    "sg:city":"Plano",
    "sg:classifiers":[
        {
            "category":"Real Estate",
            "subcategory":"Real Estate Agent",
            "type":"Services"
        }
    ],
    "sg:phone":"+1 972 424 5595",
    "sg:postcode":"75074",
    "sg:province":"TX",
    "wof:name":"Texas Metro Realty",
    "wof:placetype":"venue"
},
  "geometry": {"coordinates":[-96.647537,33.023581],"type":"Point"}
}