{
  "type": "Feature",
  "properties": {
    "iso:country":"US",
    "sg:address":"132 1st St W",
    "sg:city":"Humble",
    "sg:classifiers":[
        {
            "category":"Personal",
            "subcategory":"Nail Salon",
            "type":"Services"
        }
    ],
    "sg:phone":"+1 281 446 5161",
    "sg:postcode":"77338",
    "sg:province":"TX",
    "wof:name":"Y & B Nails",
    "wof:placetype":"venue"
},
  "geometry": {"coordinates":[-95.267521,30.000636],"type":"Point"}
}