{
  "type": "Feature",
  "properties": {
    "iso:country":"US",
    "sg:address":"1709 Brazos St",
    "sg:city":"Zapata",
    "sg:classifiers":[
        {
            "category":"Social Services",
            "subcategory":"Child Care",
            "type":"Services"
        }
    ],
    "sg:phone":"+1 956 765 5833",
    "sg:postcode":"78076",
    "sg:province":"TX",
    "sg:tags":[
        "nursery",
        "day"
    ],
    "wof:name":"Great Beginnings Childcare",
    "wof:placetype":"venue"
},
  "geometry": {"coordinates":[-99.26867,26.915114],"type":"Point"}
}