{
  "type": "Feature",
  "properties": {
    "iso:country":"US",
    "sg:address":"7224 Nelms St",
    "sg:city":"Houston",
    "sg:classifiers":[
        {
            "category":"Manufacturing",
            "subcategory":"Paper Products",
            "type":"Manufacturing & Wholesale Goods"
        }
    ],
    "sg:phone":"+1 713 847 8008",
    "sg:postcode":"77061",
    "sg:province":"TX",
    "sg:tags":[
        "food",
        "bag",
        "manufacturer"
    ],
    "wof:name":"Agribag Inc",
    "wof:placetype":"venue"
},
  "geometry": {"coordinates":[-95.29248200000001,29.645352],"type":"Point"}
}