{
  "type": "Feature",
  "properties": {
    "iso:country":"US",
    "sg:address":"300 Saint Lukes Dr",
    "sg:city":"Richardson",
    "sg:classifiers":[
        {
            "category":"Retail",
            "subcategory":"Portrait Studio",
            "type":"Services"
        }
    ],
    "sg:phone":"+1 972 437 4686",
    "sg:postcode":"75080",
    "sg:province":"TX",
    "sg:tags":[
        "photographer"
    ],
    "wof:name":"Gill Photography",
    "wof:placetype":"venue"
},
  "geometry": {"coordinates":[-96.757093,32.954782],"type":"Point"}
}