{
  "type": "Feature",
  "properties": {
    "iso:country":"US",
    "sg:address":"1135 W Rundberg Ln",
    "sg:city":"Austin",
    "sg:classifiers":[
        {
            "category":"Social Services",
            "subcategory":"Adult Care",
            "type":"Services"
        }
    ],
    "sg:phone":"+1 512 836 3342",
    "sg:postcode":"78758",
    "sg:province":"TX",
    "sg:tags":[
        "home",
        "residential"
    ],
    "wof:name":"Horton & Horton",
    "wof:placetype":"venue"
},
  "geometry": {"coordinates":[-97.703524,30.36603],"type":"Point"}
}