{
  "type": "Feature",
  "properties": {
    "iso:country":"US",
    "sg:address":"5730 Wilson Rd",
    "sg:city":"Fort Worth",
    "sg:classifiers":[
        {
            "category":"Wholesale",
            "subcategory":"Auto Parts",
            "type":"Manufacturing & Wholesale Goods"
        }
    ],
    "sg:phone":"+1 817 478 1310",
    "sg:postcode":"76140",
    "sg:province":"TX",
    "sg:tags":[
        "tire"
    ],
    "wof:name":"ABC Tires",
    "wof:placetype":"venue"
},
  "geometry": {"coordinates":[-97.239897,32.620022],"type":"Point"}
}