{
  "type": "Feature",
  "properties": {
    "iso:country":"US",
    "sg:address":"3700 W Military Hwy",
    "sg:city":"Mcallen",
    "sg:classifiers":[
        {
            "category":"Education",
            "subcategory":"Junior College",
            "type":"Public Place"
        }
    ],
    "sg:phone":"+1 956 631 4922",
    "sg:postcode":"78503",
    "sg:province":"TX",
    "sg:tags":[
        "community"
    ],
    "wof:name":"South Texas Community College",
    "wof:placetype":"venue"
},
  "geometry": {"coordinates":[-98.27382799999999,26.153133],"type":"Point"}
}