{
  "type": "Feature",
  "properties": {
    "iso:country":"US",
    "sg:address":"666 E Reindeer Rd",
    "sg:city":"Lancaster",
    "sg:classifiers":[
        {
            "category":"Retail",
            "subcategory":"Car Wash",
            "type":"Services"
        }
    ],
    "sg:phone":"+1 972 227 0368",
    "sg:postcode":"75146",
    "sg:province":"TX",
    "sg:tags":[
        "automobile",
        "detail",
        "clean"
    ],
    "wof:name":"Byron's Auto Detailing & Cstm",
    "wof:placetype":"venue"
},
  "geometry": {"coordinates":[-96.75086899999999,32.550059],"type":"Point"}
}