{
  "type": "Feature",
  "properties": {
    "iso:country":"US",
    "sg:address":"15111 Branding Iron St",
    "sg:city":"San Antonio",
    "sg:classifiers":[
        {
            "category":"Retail",
            "subcategory":"Repair Shop",
            "type":"Services"
        }
    ],
    "sg:phone":"+1 210 655 8211",
    "sg:postcode":"78247",
    "sg:province":"TX",
    "sg:tags":[
        "related"
    ],
    "wof:name":"Anything For Money & Glass",
    "wof:placetype":"venue"
},
  "geometry": {"coordinates":[-98.39085799999999,29.579769],"type":"Point"}
}