{
  "type": "Feature",
  "properties": {
    "iso:country":"US",
    "sg:address":"3910 Garnet Falls",
    "sg:city":"Sugar Land",
    "sg:classifiers":[
        {
            "category":"Autos & Motor Vehicles",
            "subcategory":"Fuel & Gas Station",
            "type":"Retail Goods"
        }
    ],
    "sg:phone":"+1 832 768 2949",
    "sg:postcode":"77479",
    "sg:province":"TX",
    "sg:tags":[
        "station",
        "gasoline"
    ],
    "wof:name":"Naju Limited",
    "wof:placetype":"venue"
},
  "geometry": {"coordinates":[-95.627657,29.554148],"type":"Point"}
}