{
  "type": "Feature",
  "properties": {
    "iso:country":"US",
    "sg:address":"8101 Haning Dr",
    "sg:city":"Plano",
    "sg:classifiers":[
        {
            "category":"Food & Beverages",
            "subcategory":"Specialty",
            "type":"Retail Goods"
        }
    ],
    "sg:phone":"+1 972 571 6056",
    "sg:postcode":"75025",
    "sg:province":"TX",
    "wof:name":"4 Natural Happiness",
    "wof:placetype":"venue"
},
  "geometry": {"coordinates":[-96.766105,33.087401],"type":"Point"}
}