{
  "type": "Feature",
  "properties": {
    "iso:country":"US",
    "sg:address":"1134 S Navigation Blvd",
    "sg:city":"Corpus Christi",
    "sg:classifiers":[
        {
            "category":"Home & Garden",
            "subcategory":"Carpets & Floor Coverings",
            "type":"Retail Goods"
        }
    ],
    "sg:phone":"+1 361 884 1776",
    "sg:postcode":"78405",
    "sg:province":"TX",
    "sg:tags":[
        "material"
    ],
    "wof:name":"Amerifloors",
    "wof:placetype":"venue"
},
  "geometry": {"coordinates":[-97.452541,27.764398],"type":"Point"}
}