{
  "type": "Feature",
  "properties": {
    "iso:country":"US",
    "sg:address":"1101 N 4th St",
    "sg:city":"Longview",
    "sg:classifiers":[
        {
            "category":"Autos & Motor Vehicles",
            "subcategory":"Fuel & Gas Station",
            "type":"Retail Goods"
        }
    ],
    "sg:phone":"+1 903 758 4858",
    "sg:postcode":"75601",
    "sg:province":"TX",
    "sg:tags":[
        "station",
        "gasoline"
    ],
    "wof:name":"Texaco",
    "wof:placetype":"venue"
},
  "geometry": {"coordinates":[-94.73075300000001,32.509979],"type":"Point"}
}