{
  "type": "Feature",
  "properties": {
    "iso:country":"US",
    "sg:address":"400 N Ave A",
    "sg:city":"Denton",
    "sg:classifiers":[
        {
            "category":"Shopping",
            "subcategory":"Used Merchandise",
            "type":"Retail Goods"
        }
    ],
    "sg:phone":"+1 940 383 8267",
    "sg:postcode":"79529",
    "sg:province":"TX",
    "sg:tags":[
        "shop",
        "consignment"
    ],
    "wof:name":"Twice As Nice Resale Of Denton",
    "wof:placetype":"venue"
},
  "geometry": {"coordinates":[-99.817925,33.422092],"type":"Point"}
}