{
  "type": "Feature",
  "properties": {
    "iso:country":"US",
    "sg:address":"323 Linkhaven Dr",
    "sg:city":"Duncanville",
    "sg:classifiers":[
        {
            "category":"Building & Trades",
            "subcategory":"Electrical",
            "type":"Services"
        }
    ],
    "sg:phone":"+1 972 780 7096",
    "sg:postcode":"75137",
    "sg:province":"TX",
    "sg:tags":[
        "installation"
    ],
    "wof:name":"Alert Fire Installation",
    "wof:placetype":"venue"
},
  "geometry": {"coordinates":[-96.91314800000001,32.623448],"type":"Point"}
}