{
  "type": "Feature",
  "properties": {
    "iso:country":"US",
    "sg:address":"9715 Faircloud Dr",
    "sg:city":"Dallas",
    "sg:classifiers":[
        {
            "category":"Shopping",
            "type":"Retail Goods"
        }
    ],
    "sg:phone":"+1 214 642 0986",
    "sg:postcode":"75217",
    "sg:province":"TX",
    "sg:tags":[
        "miscellaneous",
        "store"
    ],
    "wof:name":"R & R",
    "wof:placetype":"venue"
},
  "geometry": {"coordinates":[-96.65418099999999,32.741625],"type":"Point"}
}