{
  "type": "Feature",
  "properties": {
    "iso:country":"US",
    "sg:address":"1227 Chandler Cir",
    "sg:city":"Prosper",
    "sg:classifiers":[
        {
            "category":"Building & Trades",
            "subcategory":"Construction",
            "type":"Services"
        }
    ],
    "sg:phone":"+1 972 346 2087",
    "sg:postcode":"75078",
    "sg:province":"TX",
    "sg:tags":[
        "hanging",
        "contractor"
    ],
    "wof:name":"Distinctive Painting & RE",
    "wof:placetype":"venue"
},
  "geometry": {"coordinates":[-96.784549,33.247282],"type":"Point"}
}