{
  "type": "Feature",
  "properties": {
    "iso:country":"US",
    "sg:address":"2213 Boll",
    "sg:city":"Dallas",
    "sg:classifiers":[
        {
            "category":"Professional",
            "subcategory":"Lawyer & Legal Services",
            "type":"Services"
        }
    ],
    "sg:phone":"+1 469 834 7119",
    "sg:postcode":"75204",
    "sg:province":"TX",
    "sg:tags":[
        "divorce",
        "law",
        "family"
    ],
    "sg:website":"www.texaslegalpartner.com",
    "wof:name":"Texas Legal Partner, P.L.L.C.",
    "wof:placetype":"venue"
},
  "geometry": {"coordinates":[-96.798208,32.795058],"type":"Point"}
}