{
  "type": "Feature",
  "properties": {
    "iso:country":"US",
    "sg:address":"301 W Martin St",
    "sg:city":"Del Rio",
    "sg:classifiers":[
        {
            "category":"Health Services",
            "subcategory":"Clinic",
            "type":"Services"
        }
    ],
    "sg:phone":"+1 830 774 7037",
    "sg:postcode":"78840",
    "sg:province":"TX",
    "sg:tags":[
        "specialty",
        "outpatient"
    ],
    "wof:name":"Del Rio Nursing and Rehab Ctr",
    "wof:placetype":"venue"
},
  "geometry": {"coordinates":[-100.903693,29.359678],"type":"Point"}
}