{
  "type": "Feature",
  "properties": {
    "iso:country":"US",
    "sg:address":"220 Rock Dove Ln",
    "sg:city":"Georgetown",
    "sg:classifiers":[
        {
            "category":"Shopping",
            "subcategory":"Hobbies, Toys, & Games",
            "type":"Retail Goods"
        }
    ],
    "sg:phone":"+1 512 864 9828",
    "sg:postcode":"78626",
    "sg:province":"TX",
    "wof:name":"Vrf Ceramics",
    "wof:placetype":"venue"
},
  "geometry": {"coordinates":[-97.630691,30.632772],"type":"Point"}
}