{
  "type": "Feature",
  "properties": {
    "iso:country":"US",
    "sg:address":"201 N Water St",
    "sg:city":"Fort Stockton",
    "sg:classifiers":[
        {
            "category":"Banks & Credit Unions",
            "subcategory":"Investment Brokerage",
            "type":"Services"
        }
    ],
    "sg:phone":"+1 432 336 2002",
    "sg:postcode":"79735",
    "sg:province":"TX",
    "wof:name":"Americas Investment Group",
    "wof:placetype":"venue"
},
  "geometry": {"coordinates":[-102.878041,30.887255],"type":"Point"}
}