{
  "type": "Feature",
  "properties": {
    "iso:country":"US",
    "sg:address":"4121 Apollo St",
    "sg:city":"Houston",
    "sg:classifiers":[
        {
            "category":"Building & Trades",
            "subcategory":"Plumbing",
            "type":"Services"
        }
    ],
    "sg:phone":"+1 713 681 1986",
    "sg:postcode":"77018",
    "sg:province":"TX",
    "sg:tags":[
        "contractor"
    ],
    "wof:name":"Relief Mechanical AC",
    "wof:placetype":"venue"
},
  "geometry": {"coordinates":[-95.428473,29.825552],"type":"Point"}
}