{
  "type": "Feature",
  "properties": {
    "iso:country":"US",
    "sg:address":"4117 Mesa Dr",
    "sg:city":"Plano",
    "sg:classifiers":[
        {
            "category":"Professional",
            "type":"Services"
        }
    ],
    "sg:phone":"+1 214 315 5883",
    "sg:postcode":"75074",
    "sg:province":"TX",
    "wof:name":"E Z Technology Services",
    "wof:placetype":"venue"
},
  "geometry": {"coordinates":[-96.649084,33.034417],"type":"Point"}
}