{
  "type": "Feature",
  "properties": {
    "iso:country":"US",
    "sg:address":"5309 Marcillus Ave",
    "sg:city":"El Paso",
    "sg:classifiers":[
        {
            "category":"Organizations",
            "subcategory":"Religious Organization",
            "type":"Services"
        }
    ],
    "sg:phone":"+1 915 755 7200",
    "sg:postcode":"79924",
    "sg:province":"TX",
    "wof:name":"El Paso Biblical Studies",
    "wof:placetype":"venue"
},
  "geometry": {"coordinates":[-106.416042,31.891482],"type":"Point"}
}