{
  "type": "Feature",
  "properties": {
    "iso:country":"US",
    "sg:address":"14602 Carols Way Dr",
    "sg:city":"Houston",
    "sg:classifiers":[
        {
            "category":"Shopping",
            "subcategory":"Computers & Home Electronics",
            "type":"Retail Goods"
        }
    ],
    "sg:phone":"+1 281 379 4908",
    "sg:postcode":"77070",
    "sg:province":"TX",
    "wof:name":"Vaden King",
    "wof:placetype":"venue"
},
  "geometry": {"coordinates":[-95.60721700000001,29.987834],"type":"Point"}
}