{
  "type": "Feature",
  "properties": {
    "iso:country":"US",
    "sg:address":"1353 Armstrong Dr",
    "sg:city":"De Soto",
    "sg:classifiers":[
        {
            "category":"Freight",
            "type":"Transportation"
        }
    ],
    "sg:phone":"+1 972 274 3970",
    "sg:postcode":"75115",
    "sg:province":"TX",
    "sg:tags":[
        "local",
        "storage",
        "trucking"
    ],
    "wof:name":"Ikes Moving & Delivery Svc",
    "wof:placetype":"venue"
},
  "geometry": {"coordinates":[-96.870054,32.613101],"type":"Point"}
}