{
  "type": "Feature",
  "properties": {
    "iso:country":"US",
    "sg:address":"11643 Vance Jackson Rd",
    "sg:city":"San Antonio",
    "sg:classifiers":[
        {
            "category":"Personal",
            "subcategory":"Beauty Salon",
            "type":"Services"
        }
    ],
    "sg:phone":"+1 210 690 9002",
    "sg:postcode":"78230",
    "sg:province":"TX",
    "sg:tags":[
        "shop"
    ],
    "wof:name":"Jennifer Healy",
    "wof:placetype":"venue"
},
  "geometry": {"coordinates":[-98.566981,29.548844],"type":"Point"}
}