{
  "type": "Feature",
  "properties": {
    "iso:country":"US",
    "sg:address":"2503 Manana St",
    "sg:city":"Austin",
    "sg:classifiers":[
        {
            "category":"Professional",
            "type":"Services"
        }
    ],
    "sg:phone":"+1 512 346 3094",
    "sg:postcode":"78730",
    "sg:province":"TX",
    "wof:name":"Sculpture Watercolor & Oils",
    "wof:placetype":"venue"
},
  "geometry": {"coordinates":[-97.830968,30.326966],"type":"Point"}
}