{
  "type": "Feature",
  "properties": {
    "iso:country":"US",
    "sg:address":"1111 Surrey Ln",
    "sg:city":"Allen",
    "sg:classifiers":[
        {
            "category":"Shopping",
            "subcategory":"Gifts & Souvenirs",
            "type":"Retail Goods"
        }
    ],
    "sg:phone":"+1 469 675 0465",
    "sg:postcode":"75013",
    "sg:province":"TX",
    "wof:name":"Cards International",
    "wof:placetype":"venue"
},
  "geometry": {"coordinates":[-96.696917,33.125664],"type":"Point"}
}