{
  "type": "Feature",
  "properties": {
    "iso:country":"US",
    "sg:address":"4323 Homestead Dr",
    "sg:city":"Roanoke",
    "sg:classifiers":[
        {
            "category":"Wholesale",
            "subcategory":"Machinery & Supplies",
            "type":"Manufacturing & Wholesale Goods"
        },
        {
            "category":"Building & Trades",
            "subcategory":"Equipment Rental",
            "type":"Services"
        }
    ],
    "sg:phone":"+1 817 430 8519",
    "sg:postcode":"76092",
    "sg:province":"TX",
    "sg:tags":[
        "dry wall",
        "contractor",
        "hardware",
        "construction"
    ],
    "sg:website":"www.amestools.com",
    "wof:name":"Ames Taping Tools Inc",
    "wof:placetype":"venue"
},
  "geometry": {"coordinates":[-97.14833299999999,32.999234],"type":"Point"}
}