{
  "type": "Feature",
  "properties": {
    "iso:country":"US",
    "sg:address":"25 Butterfield Trail Blvd",
    "sg:city":"El Paso",
    "sg:classifiers":[
        {
            "category":"Professional",
            "subcategory":"Employment Agencies",
            "type":"Services"
        }
    ],
    "sg:phone":"+1 915 779 7799",
    "sg:postcode":"79906",
    "sg:province":"TX",
    "wof:name":"Nortel",
    "wof:placetype":"venue"
},
  "geometry": {"coordinates":[-106.393174,31.813339],"type":"Point"}
}