{
  "type": "Feature",
  "properties": {
    "iso:country":"US",
    "sg:address":"10398 FM 429",
    "sg:city":"Kaufman",
    "sg:classifiers":[
        {
            "category":"Cinema",
            "subcategory":"Movie Rental",
            "type":"Entertainment"
        }
    ],
    "sg:phone":"+1 972 551 1939",
    "sg:postcode":"75161",
    "sg:province":"TX",
    "sg:tags":[
        "video",
        "tape"
    ],
    "wof:name":"Video Center",
    "wof:placetype":"venue"
},
  "geometry": {"coordinates":[-96.151914,32.627946],"type":"Point"}
}