{
  "type": "Feature",
  "properties": {
    "iso:country":"US",
    "sg:address":"120 W Broadway St",
    "sg:city":"Brownfield",
    "sg:classifiers":[
        {
            "category":"Restaurant",
            "type":"Food & Drink"
        },
        {
            "category":"Ice Cream",
            "type":"Food & Drink"
        }
    ],
    "sg:menulink":"http://www.allmenus.com/tx/brownfield/162113-dairy-queen/menu/",
    "sg:phone":"+1 806 637 2013",
    "sg:postcode":"79316",
    "sg:province":"TX",
    "sg:tags":[
        "burger",
        "american",
        "ice",
        "cream"
    ],
    "wof:name":"Dairy Queen",
    "wof:placetype":"venue"
},
  "geometry": {"coordinates":[-102.276228,33.178131],"type":"Point"}
}