{
  "type": "Feature",
  "properties": {
    "iso:country":"US",
    "sg:address":"1740 Old Spanish Trl",
    "sg:city":"Houston",
    "sg:classifiers":[
        {
            "category":"Autos & Motor Vehicles",
            "subcategory":"Fuel & Gas Station",
            "type":"Retail Goods"
        },
        {
            "category":"Retail",
            "subcategory":"Auto Repair",
            "type":"Services"
        }
    ],
    "sg:phone":"+1 713 797 9986",
    "sg:postcode":"77054",
    "sg:province":"TX",
    "wof:name":"Medical Center Texaco",
    "wof:placetype":"venue"
},
  "geometry": {"coordinates":[-95.402901,29.695101],"type":"Point"}
}