{
  "type": "Feature",
  "properties": {
    "iso:country":"US",
    "sg:address":"705 E Losoya St",
    "sg:city":"Del Rio",
    "sg:classifiers":[
        {
            "category":"Shopping",
            "subcategory":"Beauty & Cosmetics",
            "type":"Retail Goods"
        }
    ],
    "sg:phone":"+1 830 775 3803",
    "sg:postcode":"78840",
    "sg:province":"TX",
    "sg:tags":[
        "merchandise"
    ],
    "wof:name":"Merle Norman Cosmetics",
    "wof:placetype":"venue"
},
  "geometry": {"coordinates":[-100.891616,29.362015],"type":"Point"}
}