{
  "type": "Feature",
  "properties": {
    "iso:country":"US",
    "sg:address":"12002 Browning Ln",
    "sg:city":"Dallas",
    "sg:classifiers":[
        {
            "category":"Professional",
            "type":"Services"
        }
    ],
    "sg:phone":"+1 972 392 9966",
    "sg:postcode":"75230",
    "sg:province":"TX",
    "wof:name":"Mindy Appell",
    "wof:placetype":"venue"
},
  "geometry": {"coordinates":[-96.795762,32.913355],"type":"Point"}
}