{
  "type": "Feature",
  "properties": {
    "iso:country":"US",
    "sg:address":"1402 Quicksilver Cir",
    "sg:city":"Round Rock",
    "sg:classifiers":[
        {
            "category":"Shopping",
            "subcategory":"Gifts & Souvenirs",
            "type":"Retail Goods"
        }
    ],
    "sg:phone":"+1 512 426 1022",
    "sg:postcode":"78665",
    "sg:province":"TX",
    "wof:name":"Gifts N Tags",
    "wof:placetype":"venue"
},
  "geometry": {"coordinates":[-97.66912000000001,30.56354],"type":"Point"}
}