{
  "type": "Feature",
  "properties": {
    "iso:country":"US",
    "sg:address":"2019 Frio City Rd",
    "sg:city":"San Antonio",
    "sg:classifiers":[
        {
            "category":"Retail",
            "subcategory":"Auto Repair",
            "type":"Services"
        }
    ],
    "sg:phone":"+1 210 922 4181",
    "sg:postcode":"78226",
    "sg:province":"TX",
    "sg:tags":[
        "repairing",
        "automobile"
    ],
    "wof:name":"Ruben's Automotive & Trans",
    "wof:placetype":"venue"
},
  "geometry": {"coordinates":[-98.540076,29.391084],"type":"Point"}
}