{
  "type": "Feature",
  "properties": {
    "iso:country":"US",
    "sg:address":"16127 Mendocino Dr",
    "sg:city":"Houston",
    "sg:classifiers":[
        {
            "category":"Retail",
            "subcategory":"Laundry & Dry Cleaning",
            "type":"Services"
        }
    ],
    "sg:phone":"+1 281 564 6338",
    "sg:postcode":"77083",
    "sg:province":"TX",
    "sg:tags":[
        "cleaners",
        "rug",
        "carpet"
    ],
    "wof:name":"Excellent Carpet Care",
    "wof:placetype":"venue"
},
  "geometry": {"coordinates":[-95.66949,29.699669],"type":"Point"}
}