{
  "type": "Feature",
  "properties": {
    "iso:country":"US",
    "sg:address":"799 State Hwy 159",
    "sg:city":"Bellville",
    "sg:classifiers":[
        {
            "category":"Professional",
            "subcategory":"Engineering",
            "type":"Services"
        }
    ],
    "sg:phone":"+1 979 865 9667",
    "sg:postcode":"77418",
    "sg:province":"TX",
    "wof:name":"Northbrook Engineering",
    "wof:placetype":"venue"
},
  "geometry": {"coordinates":[-96.352633,29.963272],"type":"Point"}
}