{
  "type": "Feature",
  "properties": {
    "iso:country":"US",
    "sg:address":"4117 Periwinkle Dr",
    "sg:city":"Fort Worth",
    "sg:classifiers":[
        {
            "category":"Building & Trades",
            "subcategory":"Construction",
            "type":"Services"
        }
    ],
    "sg:phone":"+1 817 306 8012",
    "sg:postcode":"76137",
    "sg:province":"TX",
    "sg:tags":[
        "house"
    ],
    "wof:name":"Pk Builders",
    "wof:placetype":"venue"
},
  "geometry": {"coordinates":[-97.297957,32.882351],"type":"Point"}
}