{
  "type": "Feature",
  "properties": {
    "iso:country":"US",
    "sg:address":"3410 Rolling Green Ln",
    "sg:city":"Missouri City",
    "sg:classifiers":[
        {
            "category":"Shopping",
            "subcategory":"Gifts & Souvenirs",
            "type":"Retail Goods"
        }
    ],
    "sg:phone":"+1 281 261 8016",
    "sg:postcode":"77459",
    "sg:province":"TX",
    "wof:name":"Younique Gifts & Glass",
    "wof:placetype":"venue"
},
  "geometry": {"coordinates":[-95.5575,29.565381],"type":"Point"}
}