{
  "type": "Feature",
  "properties": {
    "iso:country":"US",
    "sg:address":"2638 Grand Canyon Dr",
    "sg:city":"Houston",
    "sg:classifiers":[
        {
            "category":"Shopping",
            "subcategory":"Clothing, Apparel, & Fashions",
            "type":"Retail Goods"
        }
    ],
    "sg:phone":"+1 281 580 2378",
    "sg:postcode":"77067",
    "sg:province":"TX",
    "wof:name":"Black America Flag Enterpises",
    "wof:placetype":"venue"
},
  "geometry": {"coordinates":[-95.471238,29.96381],"type":"Point"}
}