{
  "type": "Feature",
  "properties": {
    "iso:country":"US",
    "sg:address":"9404 W Expressway 83",
    "sg:city":"Harlingen",
    "sg:classifiers":[
        {
            "category":"Wholesale",
            "subcategory":"Farm Supplies",
            "type":"Manufacturing & Wholesale Goods"
        },
        {
            "category":"Autos & Motor Vehicles",
            "subcategory":"Automobile Sales",
            "type":"Retail Goods"
        },
        {
            "category":"Autos & Motor Vehicles",
            "subcategory":"Auto Supplies",
            "type":"Retail Goods"
        },
        {
            "category":"Wholesale",
            "subcategory":"Machinery & Supplies",
            "type":"Manufacturing & Wholesale Goods"
        },
        {
            "category":"Wholesale",
            "subcategory":"Auto Parts",
            "type":"Manufacturing & Wholesale Goods"
        }
    ],
    "sg:phone":"+1 956 428 6464",
    "sg:postcode":"78552",
    "sg:province":"TX",
    "sg:tags":[
        "wheel",
        "vehicles-supplies",
        "drive",
        "four",
        "equipment",
        "truck",
        "transport",
        "baling",
        "trailer",
        "tractor"
    ],
    "wof:name":"Groves Brothers Machinery",
    "wof:placetype":"venue"
},
  "geometry": {"coordinates":[-97.76852,26.187321],"type":"Point"}
}