{
  "type": "Feature",
  "properties": {
    "iso:country":"US",
    "sg:address":"3333 Allen Pkwy",
    "sg:city":"Houston",
    "sg:classifiers":[
        {
            "category":"Travel",
            "subcategory":"Hotels & Motels",
            "type":"Entertainment"
        },
        {
            "category":"Real Estate",
            "subcategory":"Real Estate Operator",
            "type":"Services"
        }
    ],
    "sg:phone":"+1 281 374 8772",
    "sg:postcode":"77019",
    "sg:province":"TX",
    "sg:tags":[
        "corporate",
        "housing",
        "apartment",
        "relocation"
    ],
    "wof:name":"Executive Quarters",
    "wof:placetype":"venue"
},
  "geometry": {"coordinates":[-95.401366,29.760418],"type":"Point"}
}