{
  "type": "Feature",
  "properties": {
    "iso:country":"US",
    "sg:address":"613 Pyramid Dr",
    "sg:city":"Garland",
    "sg:classifiers":[
        {
            "category":"Building & Trades",
            "subcategory":"Landscaping Services",
            "type":"Services"
        }
    ],
    "sg:phone":"+1 972 496 1771",
    "sg:postcode":"75040",
    "sg:province":"TX",
    "sg:tags":[
        "lawn",
        "maintenance",
        "grounds"
    ],
    "wof:name":"Lady Bug Lawn Care",
    "wof:placetype":"venue"
},
  "geometry": {"coordinates":[-96.623885,32.934289],"type":"Point"}
}