{
  "type": "Feature",
  "properties": {
    "iso:country":"US",
    "sg:address":"3440 Grant Ave",
    "sg:city":"Groves",
    "sg:classifiers":[
        {
            "category":"Shopping",
            "type":"Retail Goods"
        }
    ],
    "sg:phone":"+1 409 962 3332",
    "sg:postcode":"77619",
    "sg:province":"TX",
    "sg:tags":[
        "merchandise"
    ],
    "wof:name":"ONiell Collectibles",
    "wof:placetype":"venue"
},
  "geometry": {"coordinates":[-93.91098599999999,29.944417],"type":"Point"}
}