{
  "type": "Feature",
  "properties": {
    "iso:country":"US",
    "sg:address":"2400 Wildwood Ln",
    "sg:city":"Roanoke",
    "sg:classifiers":[
        {
            "category":"Real Estate",
            "subcategory":"Real Estate Agent",
            "type":"Services"
        }
    ],
    "sg:phone":"+1 817 498 9463",
    "sg:postcode":"76210",
    "sg:province":"TX",
    "wof:name":"Wildwood Realty",
    "wof:placetype":"venue"
},
  "geometry": {"coordinates":[-97.10675500000001,33.158882],"type":"Point"}
}