{
  "type": "Feature",
  "properties": {
    "iso:country":"US",
    "sg:address":"3360 Belt Line Rd",
    "sg:city":"Dallas",
    "sg:classifiers":[
        {
            "category":"Wholesale",
            "subcategory":"Computers",
            "type":"Manufacturing & Wholesale Goods"
        }
    ],
    "sg:phone":"+1 972 241 6965",
    "sg:postcode":"75234",
    "sg:province":"TX",
    "wof:name":"Memory Kings Outlet",
    "wof:placetype":"venue"
},
  "geometry": {"coordinates":[-96.866995,32.953226],"type":"Point"}
}