{
  "type": "Feature",
  "properties": {
    "iso:country":"US",
    "sg:address":"2001 Austin St",
    "sg:city":"San Angelo",
    "sg:classifiers":[
        {
            "category":"Wholesale",
            "subcategory":"Non-durable Goods",
            "type":"Manufacturing & Wholesale Goods"
        }
    ],
    "sg:phone":"+1 325 653 4231",
    "sg:postcode":"76903",
    "sg:province":"TX",
    "sg:tags":[
        "pencil",
        "job",
        "mfg"
    ],
    "wof:name":"West Txas Lighthouse For Blind",
    "wof:placetype":"venue"
},
  "geometry": {"coordinates":[-100.447793,31.438394],"type":"Point"}
}