{
  "type": "Feature",
  "properties": {
    "iso:country":"US",
    "sg:address":"10022 Lake June Rd",
    "sg:city":"Dallas",
    "sg:classifiers":[
        {
            "category":"Recreation",
            "type":"Entertainment"
        }
    ],
    "sg:phone":"+1 972 913 5057",
    "sg:postcode":"75217",
    "sg:province":"TX",
    "sg:tags":[
        "psychic",
        "medium"
    ],
    "wof:name":"Sister Lisa",
    "wof:placetype":"venue"
},
  "geometry": {"coordinates":[-96.65167,32.733942],"type":"Point"}
}