{
  "type": "Feature",
  "properties": {
    "iso:country":"US",
    "sg:address":"710 Park Pl",
    "sg:city":"College Station",
    "sg:classifiers":[
        {
            "category":"Professional",
            "subcategory":"Engineering",
            "type":"Services"
        }
    ],
    "sg:phone":"+1 979 764 6779",
    "sg:postcode":"77840",
    "sg:province":"TX",
    "wof:name":"Aspen Systems Corporation",
    "wof:placetype":"venue"
},
  "geometry": {"coordinates":[-96.330433,30.605012],"type":"Point"}
}