{
  "type": "Feature",
  "properties": {
    "iso:country":"US",
    "sg:address":"2825 FM 2722",
    "sg:city":"New Braunfels",
    "sg:classifiers":[
        {
            "category":"Shopping",
            "subcategory":"Computers & Home Electronics",
            "type":"Retail Goods"
        }
    ],
    "sg:phone":"+1 830 899 2100",
    "sg:postcode":"78132",
    "sg:province":"TX",
    "sg:tags":[
        "software"
    ],
    "wof:name":"Dilloware Inc",
    "wof:placetype":"venue"
},
  "geometry": {"coordinates":[-98.21295499999999,29.772747],"type":"Point"}
}