{
  "type": "Feature",
  "properties": {
    "iso:country":"US",
    "sg:address":"1320 N Closner Blvd",
    "sg:city":"Edinburg",
    "sg:classifiers":[
        {
            "category":"Shopping",
            "subcategory":"Florist",
            "type":"Retail Goods"
        }
    ],
    "sg:phone":"+1 956 383 8611",
    "sg:postcode":"78541",
    "sg:province":"TX",
    "wof:name":"Allen Floral",
    "wof:placetype":"venue"
},
  "geometry": {"coordinates":[-98.159944,26.315209],"type":"Point"}
}