{
  "type": "Feature",
  "properties": {
    "iso:country":"US",
    "sg:address":"4614 Green Trail Dr",
    "sg:city":"Houston",
    "sg:classifiers":[
        {
            "category":"Shopping",
            "subcategory":"Computers & Home Electronics",
            "type":"Retail Goods"
        }
    ],
    "sg:phone":"+1 281 550 9403",
    "sg:postcode":"77084",
    "sg:province":"TX",
    "sg:tags":[
        "store",
        "software"
    ],
    "wof:name":"Ultra Byte",
    "wof:placetype":"venue"
},
  "geometry": {"coordinates":[-95.641505,29.842535],"type":"Point"}
}