{
  "type": "Feature",
  "properties": {
    "iso:country":"US",
    "sg:address":"926 W Old Lockhart Rd",
    "sg:city":"West Point",
    "sg:classifiers":[
        {
            "category":"Farming",
            "subcategory":"Livestock Farm",
            "type":"Manufacturing & Wholesale Goods"
        }
    ],
    "sg:phone":"+1 979 242 3729",
    "sg:postcode":"78963",
    "sg:province":"TX",
    "sg:tags":[
        "beef",
        "feedlot",
        "cattle"
    ],
    "wof:name":"Clarence T Brothers",
    "wof:placetype":"venue"
},
  "geometry": {"coordinates":[-97.049533,29.902496],"type":"Point"}
}