{
  "type": "Feature",
  "properties": {
    "iso:country":"US",
    "sg:address":"2314 Lake Rd",
    "sg:city":"Highlands",
    "sg:classifiers":[
        {
            "category":"Building & Trades",
            "subcategory":"Electrical",
            "type":"Services"
        }
    ],
    "sg:phone":"+1 281 426 2096",
    "sg:postcode":"77562",
    "sg:province":"TX",
    "sg:tags":[
        "electrical",
        "contractor"
    ],
    "wof:name":"Bravo Electric",
    "wof:placetype":"venue"
},
  "geometry": {"coordinates":[-95.088295,29.845614],"type":"Point"}
}