{
  "type": "Feature",
  "properties": {
    "iso:country":"US",
    "sg:address":"2651 S Hulen St",
    "sg:city":"Fort Worth",
    "sg:classifiers":[
        {
            "category":"Home & Garden",
            "subcategory":"Garden Supply",
            "type":"Retail Goods"
        }
    ],
    "sg:phone":"+1 817 923 9979",
    "sg:postcode":"76109",
    "sg:province":"TX",
    "wof:name":"Calloways Nursery Inc",
    "wof:placetype":"venue"
},
  "geometry": {"coordinates":[-97.38574800000001,32.712734],"type":"Point"}
}