{
  "type": "Feature",
  "properties": {
    "iso:country":"US",
    "sg:address":"1603 E Belt Line Rd",
    "sg:city":"Carrollton",
    "sg:classifiers":[
        {
            "category":"Banks & Credit Unions",
            "subcategory":"Financial Services",
            "type":"Services"
        }
    ],
    "sg:phone":"+1 972 428 2830",
    "sg:postcode":"75006",
    "sg:province":"TX",
    "sg:tags":[
        "broker",
        "mortgage"
    ],
    "wof:name":"Amerinet Mortgage",
    "wof:placetype":"venue"
},
  "geometry": {"coordinates":[-96.900096,32.953898],"type":"Point"}
}