{
  "type": "Feature",
  "properties": {
    "iso:country":"US",
    "sg:address":"2417 Meadowbrook Dr",
    "sg:city":"Abilene",
    "sg:classifiers":[
        {
            "category":"Building & Trades",
            "subcategory":"Construction",
            "type":"Services"
        }
    ],
    "sg:phone":"+1 325 672 2646",
    "sg:postcode":"79603",
    "sg:province":"TX",
    "wof:name":"Reynas Fence Co",
    "wof:placetype":"venue"
},
  "geometry": {"coordinates":[-99.772527,32.476472],"type":"Point"}
}