{
  "type": "Feature",
  "properties": {
    "iso:country":"US",
    "sg:address":"8719 Desert Palms Dr",
    "sg:city":"Spring",
    "sg:classifiers":[
        {
            "category":"Wholesale",
            "subcategory":"Drugs",
            "type":"Manufacturing & Wholesale Goods"
        }
    ],
    "sg:phone":"+1 281 374 9374",
    "sg:postcode":"77379",
    "sg:province":"TX",
    "wof:name":"Nutrigenix Inc",
    "wof:placetype":"venue"
},
  "geometry": {"coordinates":[-95.548376,30.014495],"type":"Point"}
}