{
  "type": "Feature",
  "properties": {
    "iso:country":"US",
    "sg:address":"3010 Robin Hill Ln",
    "sg:city":"Garland",
    "sg:classifiers":[
        {
            "category":"Wholesale",
            "subcategory":"Office Equipment",
            "type":"Manufacturing & Wholesale Goods"
        }
    ],
    "sg:phone":"+1 214 673 2679",
    "sg:postcode":"75044",
    "sg:province":"TX",
    "wof:name":"Better Image Copiers",
    "wof:placetype":"venue"
},
  "geometry": {"coordinates":[-96.677947,32.958301],"type":"Point"}
}