{
  "type": "Feature",
  "properties": {
    "iso:country":"US",
    "sg:address":"1015 E Henrietta Ave",
    "sg:city":"Kingsville",
    "sg:classifiers":[
        {
            "category":"Health Services",
            "subcategory":"Dentist",
            "type":"Services"
        }
    ],
    "sg:phone":"+1 361 592 4373",
    "sg:postcode":"78363",
    "sg:province":"TX",
    "sg:website":"http://www.veladental.com",
    "wof:name":"Vela, Dental Kingsville",
    "wof:placetype":"venue"
},
  "geometry": {"coordinates":[-97.85596700000001,27.518884],"type":"Point"}
}