{
  "type": "Feature",
  "properties": {
    "iso:country":"US",
    "sg:address":"1980 N Earl Rudder Fwy",
    "sg:city":"Bryan",
    "sg:classifiers":[
        {
            "category":"Mining & Drilling",
            "type":"Manufacturing & Wholesale Goods"
        }
    ],
    "sg:phone":"+1 979 778 9005",
    "sg:postcode":"77808",
    "sg:province":"TX",
    "sg:tags":[
        "oil",
        "gas",
        "producer"
    ],
    "wof:name":"Tetco",
    "wof:placetype":"venue"
},
  "geometry": {"coordinates":[-96.372928,30.710307],"type":"Point"}
}