{
  "type": "Feature",
  "properties": {
    "iso:country":"US",
    "sg:address":"600 State Hwy 1604",
    "sg:city":"San Antonio",
    "sg:classifiers":[
        {
            "category":"Real Estate",
            "subcategory":"Real Estate Agent",
            "type":"Services"
        }
    ],
    "sg:phone":"+1 210 490 9435",
    "sg:postcode":"78232",
    "sg:province":"TX",
    "wof:name":"D'Ann Harper Realtors",
    "wof:placetype":"venue"
},
  "geometry": {"coordinates":[-98.48587999999999,29.609363],"type":"Point"}
}