{
  "type": "Feature",
  "properties": {
    "iso:country":"US",
    "sg:address":"4429 Amherst Ln",
    "sg:city":"Grand Prairie",
    "sg:classifiers":[
        {
            "category":"Retail",
            "subcategory":"Car Wash",
            "type":"Services"
        }
    ],
    "sg:phone":"+1 972 602 0522",
    "sg:postcode":"75052",
    "sg:province":"TX",
    "sg:tags":[
        "carwash"
    ],
    "wof:name":"We Wash It",
    "wof:placetype":"venue"
},
  "geometry": {"coordinates":[-97.042654,32.663295],"type":"Point"}
}