{
  "type": "Feature",
  "properties": {
    "iso:country":"US",
    "sg:address":"5910 Fontenelle Dr",
    "sg:city":"Houston",
    "sg:classifiers":[
        {
            "category":"Retail",
            "subcategory":"Repair Shop",
            "type":"Services"
        }
    ],
    "sg:phone":"+1 281 988 9211",
    "sg:postcode":"77035",
    "sg:province":"TX",
    "sg:tags":[
        "equipment",
        "conditioning",
        "air"
    ],
    "wof:name":"Air1",
    "wof:placetype":"venue"
},
  "geometry": {"coordinates":[-95.495436,29.643594],"type":"Point"}
}