{
  "type": "Feature",
  "properties": {
    "iso:country":"US",
    "sg:address":"11006 Creek Bend Dr",
    "sg:city":"Waco",
    "sg:classifiers":[
        {
            "category":"Real Estate",
            "subcategory":"Real Estate Operator",
            "type":"Services"
        }
    ],
    "sg:phone":"+1 254 741 1081",
    "sg:postcode":"76712",
    "sg:province":"TX",
    "sg:tags":[
        "building",
        "nonresidential"
    ],
    "wof:name":"Honey Creek Properties LLC",
    "wof:placetype":"venue"
},
  "geometry": {"coordinates":[-97.235068,31.489363],"type":"Point"}
}