{
  "type": "Feature",
  "properties": {
    "iso:country":"US",
    "sg:address":"3601 Rutherglen St",
    "sg:city":"El Paso",
    "sg:classifiers":[
        {
            "category":"Personal",
            "type":"Services"
        }
    ],
    "sg:phone":"+1 915 591 8669",
    "sg:postcode":"79925",
    "sg:province":"TX",
    "wof:name":"Epmpoa Memorial Hall",
    "wof:placetype":"venue"
},
  "geometry": {"coordinates":[-106.359415,31.795924],"type":"Point"}
}