{
  "type": "Feature",
  "properties": {
    "iso:country":"US",
    "sg:address":"629 Chambers Creek Dr",
    "sg:city":"Fort Worth",
    "sg:classifiers":[
        {
            "category":"Shopping",
            "subcategory":"Gifts & Souvenirs",
            "type":"Retail Goods"
        }
    ],
    "sg:phone":"+1 817 293 2912",
    "sg:postcode":"76140",
    "sg:province":"TX",
    "wof:name":"CJS Gifts & Things",
    "wof:placetype":"venue"
},
  "geometry": {"coordinates":[-97.271255,32.628653],"type":"Point"}
}