{
  "type": "Feature",
  "properties": {
    "iso:country":"US",
    "sg:address":"1129 S 11th St",
    "sg:city":"Port Aransas",
    "sg:classifiers":[
        {
            "category":"Real Estate",
            "subcategory":"Real Estate Operator",
            "type":"Services"
        }
    ],
    "sg:phone":"+1 361 749 6281",
    "sg:postcode":"78373",
    "sg:province":"TX",
    "sg:tags":[
        "condominium"
    ],
    "sg:website":"www.seaislevillage.com",
    "wof:name":"Sea Isle Village",
    "wof:placetype":"venue"
},
  "geometry": {"coordinates":[-97.064898,27.823095],"type":"Point"}
}