{
  "type": "Feature",
  "properties": {
    "iso:country":"US",
    "sg:address":"17611 Bamwood Dr",
    "sg:city":"Houston",
    "sg:classifiers":[
        {
            "category":"Animal Shelter",
            "type":"Public Place"
        },
        {
            "category":"Retail",
            "subcategory":"Animal Services",
            "type":"Services"
        },
        {
            "category":"Retail",
            "subcategory":"Pet Boarding",
            "type":"Services"
        }
    ],
    "sg:phone":"+1 281 893 3647",
    "sg:postcode":"77090",
    "sg:province":"TX",
    "sg:tags":[
        "grooming",
        "kennel"
    ],
    "sg:website":"http://www.alphak9petservices.com",
    "wof:name":"Alpha K-9 Pet Services",
    "wof:placetype":"venue"
},
  "geometry": {"coordinates":[-95.45014999999999,30.01634],"type":"Point"}
}