{
  "type": "Feature",
  "properties": {
    "iso:country":"US",
    "sg:address":"815 Walker St",
    "sg:city":"Houston",
    "sg:classifiers":[
        {
            "category":"Professional",
            "subcategory":"Business Services",
            "type":"Services"
        }
    ],
    "sg:phone":"+1 713 874 0585",
    "sg:postcode":"77002",
    "sg:province":"TX",
    "wof:name":"Hands of Serenity Inc",
    "wof:placetype":"venue"
},
  "geometry": {"coordinates":[-95.365279,29.758361],"type":"Point"}
}