{
  "type": "Feature",
  "properties": {
    "iso:country":"US",
    "sg:address":"27736 Tomball Pkwy",
    "sg:city":"Tomball",
    "sg:classifiers":[
        {
            "category":"Professional",
            "type":"Services"
        }
    ],
    "sg:phone":"+1 281 351 8221",
    "sg:postcode":"77375",
    "sg:province":"TX",
    "wof:name":"Cutting Co",
    "wof:placetype":"venue"
},
  "geometry": {"coordinates":[-95.62969200000001,30.0801],"type":"Point"}
}