{
  "type": "Feature",
  "properties": {
    "iso:country":"US",
    "sg:address":"3139 National Cir",
    "sg:city":"Garland",
    "sg:classifiers":[
        {
            "category":"Freight",
            "type":"Transportation"
        }
    ],
    "sg:phone":"+1 972 840 3212",
    "sg:postcode":"75041",
    "sg:province":"TX",
    "sg:tags":[
        "mover"
    ],
    "wof:name":"Agape Moving & Storage Co",
    "wof:placetype":"venue"
},
  "geometry": {"coordinates":[-96.671543,32.885514],"type":"Point"}
}