{
  "type": "Feature",
  "properties": {
    "iso:country":"US",
    "sg:address":"318 W Quitman Ave",
    "sg:city":"Gladewater",
    "sg:classifiers":[
        {
            "category":"Education",
            "subcategory":"College",
            "type":"Public Place"
        }
    ],
    "sg:phone":"+1 903 844 0660",
    "sg:postcode":"75647",
    "sg:province":"TX",
    "sg:tags":[
        "academic",
        "school"
    ],
    "wof:name":"Kilgore College",
    "wof:placetype":"venue"
},
  "geometry": {"coordinates":[-94.94588,32.537075],"type":"Point"}
}