{
  "type": "Feature",
  "properties": {
    "iso:country":"US",
    "sg:address":"114 Ashwood Dr",
    "sg:city":"Elgin",
    "sg:classifiers":[
        {
            "category":"Professional",
            "type":"Services"
        }
    ],
    "sg:phone":"+1 512 285 3003",
    "sg:postcode":"78621",
    "sg:province":"TX",
    "wof:name":"Ultraclear Water",
    "wof:placetype":"venue"
},
  "geometry": {"coordinates":[-97.345558,30.285992],"type":"Point"}
}