{
  "type": "Feature",
  "properties": {
    "iso:country":"US",
    "sg:address":"171 Faubion Dr",
    "sg:city":"Georgetown",
    "sg:classifiers":[
        {
            "category":"Shopping",
            "subcategory":"Jewelry",
            "type":"Retail Goods"
        }
    ],
    "sg:phone":"+1 512 259 1199",
    "sg:postcode":"78628",
    "sg:province":"TX",
    "sg:tags":[
        "jeweler"
    ],
    "wof:name":"Bynum Family Jewels",
    "wof:placetype":"venue"
},
  "geometry": {"coordinates":[-97.764178,30.582279],"type":"Point"}
}