{
  "type": "Feature",
  "properties": {
    "iso:country":"US",
    "sg:address":"201 Meadow Ln",
    "sg:city":"Pflugerville",
    "sg:classifiers":[
        {
            "category":"Personal",
            "subcategory":"Beauty Salon",
            "type":"Services"
        }
    ],
    "sg:phone":"+1 512 257 8490",
    "sg:postcode":"78660",
    "sg:province":"TX",
    "sg:tags":[
        "shop"
    ],
    "wof:name":"Original Nails",
    "wof:placetype":"venue"
},
  "geometry": {"coordinates":[-97.626019,30.444805],"type":"Point"}
}