{
  "type": "Feature",
  "properties": {
    "iso:country":"US",
    "sg:address":"201 N Moore St",
    "sg:city":"Josephine",
    "sg:classifiers":[
        {
            "category":"Restaurant",
            "type":"Food & Drink"
        }
    ],
    "sg:phone":"+1 972 694 3337",
    "sg:postcode":"75164",
    "sg:province":"TX",
    "sg:tags":[
        "eating"
    ],
    "wof:name":"Country Korner",
    "wof:placetype":"venue"
},
  "geometry": {"coordinates":[-96.311296,33.066072],"type":"Point"}
}