{
  "type": "Feature",
  "properties": {
    "iso:country":"US",
    "sg:address":"3724 Gus Thomasson Rd",
    "sg:city":"Mesquite",
    "sg:classifiers":[
        {
            "category":"Social Services",
            "type":"Services"
        }
    ],
    "sg:phone":"+1 972 686 9619",
    "sg:postcode":"75150",
    "sg:province":"TX",
    "sg:tags":[
        "adult",
        "day",
        "care"
    ],
    "wof:name":"T Ttand Enterprises Inc",
    "wof:placetype":"venue"
},
  "geometry": {"coordinates":[-96.634092,32.809418],"type":"Point"}
}