{
  "type": "Feature",
  "properties": {
    "iso:country":"US",
    "sg:address":"2223 Marfa Ave",
    "sg:city":"Dallas",
    "sg:classifiers":[
        {
            "category":"Building & Trades",
            "subcategory":"Plumbing",
            "type":"Services"
        }
    ],
    "sg:phone":"+1 214 376 1136",
    "sg:postcode":"75216",
    "sg:province":"TX",
    "sg:tags":[
        "plumbing",
        "contractor"
    ],
    "wof:name":"Arthur's Plumbing",
    "wof:placetype":"venue"
},
  "geometry": {"coordinates":[-96.79088400000001,32.707343],"type":"Point"}
}