{
  "type": "Feature",
  "properties": {
    "iso:country":"US",
    "sg:address":"7555 South Fwy",
    "sg:city":"Houston",
    "sg:classifiers":[
        {
            "category":"Health Services",
            "subcategory":"Health Practitioner",
            "type":"Services"
        }
    ],
    "sg:phone":"+1 713 440 6699",
    "sg:postcode":"77021",
    "sg:province":"TX",
    "sg:tags":[
        "therapist",
        "physical"
    ],
    "wof:name":"ASM Clinical Svc",
    "wof:placetype":"venue"
},
  "geometry": {"coordinates":[-95.378292,29.682202],"type":"Point"}
}