{
  "type": "Feature",
  "properties": {
    "iso:country":"US",
    "sg:address":"317 US Hwy 80 E",
    "sg:city":"Mesquite",
    "sg:classifiers":[
        {
            "category":"Travel",
            "subcategory":"Hotels & Motels",
            "type":"Entertainment"
        }
    ],
    "sg:phone":"+1 972 216 4418",
    "sg:postcode":"75150",
    "sg:province":"TX",
    "wof:name":"Microtel Inns & Suites",
    "wof:placetype":"venue"
},
  "geometry": {"coordinates":[-96.596962,32.791097],"type":"Point"}
}