{
  "type": "Feature",
  "properties": {
    "iso:country":"US",
    "sg:address":"8454 Rita Elena",
    "sg:city":"San Antonio",
    "sg:classifiers":[
        {
            "category":"Professional",
            "subcategory":"Management & Consulting",
            "type":"Services"
        }
    ],
    "sg:phone":"+1 210 256 8588",
    "sg:postcode":"78250",
    "sg:province":"TX",
    "wof:name":"Hfm Consulting LLC",
    "wof:placetype":"venue"
},
  "geometry": {"coordinates":[-98.642324,29.505323],"type":"Point"}
}