{
  "type": "Feature",
  "properties": {
    "iso:country":"US",
    "sg:address":"2334 Apollo Cir",
    "sg:city":"Carrollton",
    "sg:classifiers":[
        {
            "category":"Shopping",
            "subcategory":"Party Supplies",
            "type":"Retail Goods"
        },
        {
            "category":"Shopping",
            "subcategory":"Florist",
            "type":"Retail Goods"
        }
    ],
    "sg:phone":"+1 972 607 9598",
    "sg:postcode":"75006",
    "sg:province":"TX",
    "sg:website":"www.dfwvases.com",
    "wof:name":"DFW Glass & Vase Wholesale",
    "wof:placetype":"venue"
},
  "geometry": {"coordinates":[-96.875913,32.960793],"type":"Point"}
}