{
  "type": "Feature",
  "properties": {
    "iso:country":"US",
    "sg:address":"8650 Spicewood Springs Rd",
    "sg:city":"Austin",
    "sg:classifiers":[
        {
            "category":"Restaurant",
            "type":"Food & Drink"
        }
    ],
    "sg:menulink":"http://www.allmenus.com/tx/georgetown-round-rock/59649-camino-real/menu/",
    "sg:phone":"+1 512 335 5517",
    "sg:postcode":"78759",
    "sg:province":"TX",
    "sg:tags":[
        "mexican"
    ],
    "wof:name":"Camino Real",
    "wof:placetype":"venue"
},
  "geometry": {"coordinates":[-97.77157099999999,30.43363],"type":"Point"}
}