{
  "type": "Feature",
  "properties": {
    "iso:country":"US",
    "sg:address":"2944 5th St",
    "sg:city":"Wichita Falls",
    "sg:classifiers":[
        {
            "category":"Real Estate",
            "subcategory":"Real Estate Operator",
            "type":"Services"
        },
        {
            "category":"Travel",
            "subcategory":"Campground",
            "type":"Entertainment"
        }
    ],
    "sg:phone":"+1 940 723 1532",
    "sg:postcode":"76301",
    "sg:province":"TX",
    "sg:tags":[
        "warehousing",
        "mobile",
        "park",
        "storage",
        "site",
        "general",
        "home"
    ],
    "wof:name":"Witchita Falls Rv Park",
    "wof:placetype":"venue"
},
  "geometry": {"coordinates":[-98.53155599999999,33.907793],"type":"Point"}
}