{
  "type": "Feature",
  "properties": {
    "iso:country":"US",
    "sg:address":"3275 FM 555",
    "sg:city":"Gilmer",
    "sg:classifiers":[
        {
            "category":"Organizations",
            "subcategory":"Religious Organization",
            "type":"Services"
        }
    ],
    "sg:phone":"+1 903 797 2755",
    "sg:postcode":"75645",
    "sg:province":"TX",
    "sg:tags":[
        "church"
    ],
    "wof:name":"Sand Hill Baptist Church",
    "wof:placetype":"venue"
},
  "geometry": {"coordinates":[-94.843189,32.769725],"type":"Point"}
}