{
  "type": "Feature",
  "properties": {
    "iso:country":"US",
    "sg:address":"4604 S Lamar Blvd",
    "sg:city":"Austin",
    "sg:classifiers":[
        {
            "category":"Social Services",
            "subcategory":"Retirement Home",
            "type":"Services"
        }
    ],
    "sg:phone":"+1 512 410 2646",
    "sg:postcode":"78735",
    "sg:province":"TX",
    "sg:website":"www.sunshineretirementliving.com...",
    "wof:name":"The Continental",
    "wof:placetype":"venue"
},
  "geometry": {"coordinates":[-97.80321600000001,30.234119],"type":"Point"}
}