{
  "type": "Feature",
  "properties": {
    "iso:country":"US",
    "sg:address":"4501 Grider Pass",
    "sg:city":"Austin",
    "sg:classifiers":[
        {
            "category":"Building & Trades",
            "subcategory":"Electrical",
            "type":"Services"
        }
    ],
    "sg:phone":"+1 512 448 2240",
    "sg:postcode":"78749",
    "sg:province":"TX",
    "sg:tags":[
        "lighting",
        "landscape"
    ],
    "wof:name":"Lightsculptors",
    "wof:placetype":"venue"
},
  "geometry": {"coordinates":[-97.840767,30.226854],"type":"Point"}
}