{
  "type": "Feature",
  "properties": {
    "iso:country":"US",
    "sg:address":"604 Dana St",
    "sg:city":"Robinson",
    "sg:classifiers":[
        {
            "category":"Building & Trades",
            "subcategory":"Plumbing",
            "type":"Services"
        }
    ],
    "sg:phone":"+1 254 662 3800",
    "sg:postcode":"76706",
    "sg:province":"TX",
    "sg:tags":[
        "repair",
        "system",
        "contractor",
        "air conditioning"
    ],
    "wof:name":"Braswell Air Conditioning",
    "wof:placetype":"venue"
},
  "geometry": {"coordinates":[-97.108648,31.467567],"type":"Point"}
}