{
  "type": "Feature",
  "properties": {
    "iso:country":"US",
    "sg:address":"708 S Baird St",
    "sg:city":"Midland",
    "sg:classifiers":[
        {
            "category":"Professional",
            "subcategory":"Computer Services",
            "type":"Services"
        }
    ],
    "sg:phone":"+1 432 685 3859",
    "sg:postcode":"79701",
    "sg:province":"TX",
    "sg:tags":[
        "management",
        "facility"
    ],
    "wof:name":"Custom Interiors",
    "wof:placetype":"venue"
},
  "geometry": {"coordinates":[-102.073014,31.990302],"type":"Point"}
}