{
  "type": "Feature",
  "properties": {
    "iso:country":"US",
    "sg:address":"3999 S 11th St",
    "sg:city":"Beaumont",
    "sg:classifiers":[
        {
            "category":"Manufacturing",
            "subcategory":"Tools & Machinery",
            "type":"Manufacturing & Wholesale Goods"
        }
    ],
    "sg:phone":"+1 409 842 3666",
    "sg:postcode":"77701",
    "sg:province":"TX",
    "sg:tags":[
        "farm",
        "equipment"
    ],
    "wof:name":"Oil City Tractors Inc",
    "wof:placetype":"venue"
},
  "geometry": {"coordinates":[-94.12893800000001,30.047376],"type":"Point"}
}