{
  "type": "Feature",
  "properties": {
    "iso:country":"US",
    "sg:address":"1201 E Lake Dr",
    "sg:city":"Spring",
    "sg:classifiers":[
        {
            "category":"Shopping",
            "subcategory":"Jewelry",
            "type":"Retail Goods"
        }
    ],
    "sg:phone":"+1 281 419 8618",
    "sg:postcode":"77355",
    "sg:province":"TX",
    "wof:name":"Watch & Gold The",
    "wof:placetype":"venue"
},
  "geometry": {"coordinates":[-95.78723599999999,30.18818],"type":"Point"}
}