{
  "type": "Feature",
  "properties": {
    "iso:country":"US",
    "sg:address":"1413 Wheeler Dr",
    "sg:city":"Mansfield",
    "sg:classifiers":[
        {
            "category":"Real Estate",
            "subcategory":"Real Estate Agent",
            "type":"Services"
        }
    ],
    "sg:phone":"+1 817 988 1052",
    "sg:postcode":"76063",
    "sg:province":"TX",
    "wof:name":"Hull & Assoc",
    "wof:placetype":"venue"
},
  "geometry": {"coordinates":[-97.11699400000001,32.589143],"type":"Point"}
}