{
  "type": "Feature",
  "properties": {
    "iso:country":"US",
    "sg:address":"1102 State Hwy 44",
    "sg:city":"San Diego",
    "sg:classifiers":[
        {
            "category":"Government",
            "subcategory":"Office",
            "type":"Public Place"
        }
    ],
    "sg:phone":"+1 361 279 3301",
    "sg:postcode":"78384",
    "sg:province":"TX",
    "wof:name":"Human Services Texas Dept of",
    "wof:placetype":"venue"
},
  "geometry": {"coordinates":[-98.225364,27.761693],"type":"Point"}
}