{
  "type": "Feature",
  "properties": {
    "iso:country":"US",
    "sg:address":"14706 Lindall Ct",
    "sg:city":"Cypress",
    "sg:classifiers":[
        {
            "category":"Building & Trades",
            "subcategory":"Construction",
            "type":"Services"
        }
    ],
    "sg:phone":"+1 281 379 5089",
    "sg:postcode":"77429",
    "sg:province":"TX",
    "sg:tags":[
        "builder",
        "operative"
    ],
    "wof:name":"Longwood",
    "wof:placetype":"venue"
},
  "geometry": {"coordinates":[-95.635429,29.991496],"type":"Point"}
}