{
  "type": "Feature",
  "properties": {
    "iso:country":"US",
    "sg:address":"4206 Deering Dr",
    "sg:city":"Fort Worth",
    "sg:classifiers":[
        {
            "category":"Building & Trades",
            "subcategory":"Construction",
            "type":"Services"
        }
    ],
    "sg:phone":"+1 817 732 6435",
    "sg:postcode":"76114",
    "sg:province":"TX",
    "sg:tags":[
        "contractor"
    ],
    "wof:name":"Lowe Tile Works",
    "wof:placetype":"venue"
},
  "geometry": {"coordinates":[-97.38234300000001,32.765581],"type":"Point"}
}