{
  "type": "Feature",
  "properties": {
    "iso:country":"US",
    "sg:address":"16803 Oak Ln",
    "sg:city":"Channelview",
    "sg:classifiers":[
        {
            "category":"Shopping",
            "type":"Retail Goods"
        }
    ],
    "sg:phone":"+1 281 452 9007",
    "sg:postcode":"77530",
    "sg:province":"TX",
    "wof:name":"Igg Nott Innovations",
    "wof:placetype":"venue"
},
  "geometry": {"coordinates":[-95.096009,29.8031],"type":"Point"}
}