{
  "type": "Feature",
  "properties": {
    "iso:country":"US",
    "sg:address":"8133 Mesa Dr",
    "sg:city":"Austin",
    "sg:classifiers":[
        {
            "category":"Professional",
            "subcategory":"Computer Services",
            "type":"Services"
        }
    ],
    "sg:phone":"+1 512 259 5027",
    "sg:postcode":"78759",
    "sg:province":"TX",
    "wof:name":"RPG Solutions",
    "wof:placetype":"venue"
},
  "geometry": {"coordinates":[-97.755652,30.373869],"type":"Point"}
}