{
  "type": "Feature",
  "properties": {
    "iso:country":"US",
    "sg:address":"103 Garmon Dr",
    "sg:city":"Early",
    "sg:classifiers":[
        {
            "category":"Place Of Worship",
            "subcategory":"Church",
            "type":"Public Place"
        },
        {
            "category":"Place Of Worship",
            "type":"Public Place"
        }
    ],
    "sg:phone":"+1 325 646 6596",
    "sg:postcode":"76802",
    "sg:province":"TX",
    "sg:tags":[
        "churches-baptist-general",
        "churches-baptist"
    ],
    "sg:website":"http://www.earlyfbc.com",
    "wof:name":"First Baptist Ch Early Texas",
    "wof:placetype":"venue"
},
  "geometry": {"coordinates":[-98.945329,31.741697],"type":"Point"}
}