{
  "type": "Feature",
  "properties": {
    "iso:country":"US",
    "sg:address":"815 Beckets Crossing Ln",
    "sg:city":"Spring",
    "sg:classifiers":[
        {
            "category":"Manufacturing",
            "subcategory":"Apparel",
            "type":"Manufacturing & Wholesale Goods"
        }
    ],
    "sg:phone":"+1 281 288 2091",
    "sg:postcode":"77373",
    "sg:province":"TX",
    "wof:name":"M Heart K",
    "wof:placetype":"venue"
},
  "geometry": {"coordinates":[-95.426348,30.098947],"type":"Point"}
}