{
  "type": "Feature",
  "properties": {
    "iso:country":"US",
    "sg:address":"5637 Mazanec Rd",
    "sg:city":"Waco",
    "sg:classifiers":[
        {
            "category":"Professional",
            "type":"Services"
        }
    ],
    "sg:phone":"+1 254 799 2794",
    "sg:postcode":"76705",
    "sg:province":"TX",
    "wof:name":"Mark Mazanec",
    "wof:placetype":"venue"
},
  "geometry": {"coordinates":[-97.049752,31.663601],"type":"Point"}
}