{
  "type": "Feature",
  "properties": {
    "iso:country":"US",
    "sg:address":"558 Stagecoach Dr",
    "sg:city":"New Braunfels",
    "sg:classifiers":[
        {
            "category":"Manufacturing",
            "subcategory":"Apparel",
            "type":"Manufacturing & Wholesale Goods"
        }
    ],
    "sg:phone":"+1 830 899 6044",
    "sg:postcode":"78133",
    "sg:province":"TX",
    "sg:tags":[
        "household",
        "furnishing",
        "mfg"
    ],
    "wof:name":"Marjorie A Bohlinger",
    "wof:placetype":"venue"
},
  "geometry": {"coordinates":[-98.258465,29.880344],"type":"Point"}
}