{
  "type": "Feature",
  "properties": {
    "iso:country":"US",
    "sg:address":"4849 Haverwood Ln",
    "sg:city":"Dallas",
    "sg:classifiers":[
        {
            "category":"Professional",
            "subcategory":"Business Services",
            "type":"Services"
        }
    ],
    "sg:phone":"+1 972 380 8527",
    "sg:postcode":"75287",
    "sg:province":"TX",
    "wof:name":"Global Assoc Networks Inc",
    "wof:placetype":"venue"
},
  "geometry": {"coordinates":[-96.82366399999999,33.007289],"type":"Point"}
}