{
  "type": "Feature",
  "properties": {
    "iso:country":"US",
    "sg:address":"9900 US Hwy 287P Bus",
    "sg:city":"Fort Worth",
    "sg:classifiers":[
        {
            "category":"Home & Garden",
            "subcategory":"Furniture",
            "type":"Retail Goods"
        }
    ],
    "sg:phone":"+1 817 847 9764",
    "sg:postcode":"76131",
    "sg:province":"TX",
    "sg:tags":[
        "cabinet"
    ],
    "wof:name":"New Image Kitchens",
    "wof:placetype":"venue"
},
  "geometry": {"coordinates":[-97.39905299999999,32.90055],"type":"Point"}
}