{
  "type": "Feature",
  "properties": {
    "iso:country":"US",
    "sg:address":"602 E 1st St Ste B",
    "sg:city":"Dumas",
    "sg:classifiers":[
        {
            "category":"Restaurant",
            "type":"Food & Drink"
        }
    ],
    "sg:phone":"+1 806 934 4716",
    "sg:postcode":"79029",
    "sg:province":"TX",
    "sg:tags":[
        "style",
        "mexican",
        "family"
    ],
    "wof:name":"El Matador Restaurant",
    "wof:placetype":"venue"
},
  "geometry": {"coordinates":[-101.966365,35.864891],"type":"Point"}
}