{
  "type": "Feature",
  "properties": {
    "iso:country":"US",
    "sg:address":"9975 Co Rd 470",
    "sg:city":"Blue Ridge",
    "sg:classifiers":[
        {
            "category":"Professional",
            "subcategory":"Management & Consulting",
            "type":"Services"
        }
    ],
    "sg:phone":"+1 972 734 3600",
    "sg:postcode":"75424",
    "sg:province":"TX",
    "wof:name":"Canderra Entertainment Inc",
    "wof:placetype":"venue"
},
  "geometry": {"coordinates":[-96.44724100000001,33.248336],"type":"Point"}
}