{
  "type": "Feature",
  "properties": {
    "iso:country":"US",
    "sg:address":"2102 N Grandview Ave",
    "sg:city":"Odessa",
    "sg:classifiers":[
        {
            "category":"Health Services",
            "subcategory":"Optometrist",
            "type":"Services"
        }
    ],
    "sg:phone":"+1 432 367 5600",
    "sg:postcode":"79761",
    "sg:province":"TX",
    "wof:name":"Grandview Eye",
    "wof:placetype":"venue"
},
  "geometry": {"coordinates":[-102.345922,31.871352],"type":"Point"}
}