{
  "type": "Feature",
  "properties": {
    "iso:country":"US",
    "sg:address":"900 Princeton Cove",
    "sg:city":"Pflugerville",
    "sg:classifiers":[
        {
            "category":"Professional",
            "subcategory":"Computer Services",
            "type":"Services"
        }
    ],
    "sg:phone":"+1 512 252 2005",
    "sg:postcode":"78660",
    "sg:province":"TX",
    "sg:tags":[
        "related"
    ],
    "wof:name":"Robert Hicks",
    "wof:placetype":"venue"
},
  "geometry": {"coordinates":[-97.63103,30.436079],"type":"Point"}
}