{
  "type": "Feature",
  "properties": {
    "iso:country":"US",
    "sg:address":"804 Washington St",
    "sg:city":"Teague",
    "sg:classifiers":[
        {
            "category":"Personal",
            "subcategory":"Beauty Salon",
            "type":"Services"
        }
    ],
    "sg:phone":"+1 254 739 0116",
    "sg:postcode":"75860",
    "sg:province":"TX",
    "wof:name":"I'm Worth It",
    "wof:placetype":"venue"
},
  "geometry": {"coordinates":[-96.293156,31.626709],"type":"Point"}
}