{
  "type": "Feature",
  "properties": {
    "iso:country":"US",
    "sg:address":"26 Lakeway Dr",
    "sg:city":"Rockwall",
    "sg:classifiers":[
        {
            "category":"Utilities",
            "subcategory":"Telephone",
            "type":"Services"
        }
    ],
    "sg:phone":"+1 972 771 1546",
    "sg:postcode":"75032",
    "sg:province":"TX",
    "sg:tags":[
        "communications"
    ],
    "wof:name":"Quick Star",
    "wof:placetype":"venue"
},
  "geometry": {"coordinates":[-96.478493,32.873771],"type":"Point"}
}