{
  "type": "Feature",
  "properties": {
    "iso:country":"US",
    "sg:address":"103 Marian Pl",
    "sg:city":"Brownsville",
    "sg:classifiers":[
        {
            "category":"Manufacturing",
            "subcategory":"Watercraft",
            "type":"Manufacturing & Wholesale Goods"
        }
    ],
    "sg:phone":"+1 956 544 7675",
    "sg:postcode":"78520",
    "sg:province":"TX",
    "wof:name":"Pwt Yacht Service",
    "wof:placetype":"venue"
},
  "geometry": {"coordinates":[-97.520015,25.951617],"type":"Point"}
}