{
  "type": "Feature",
  "properties": {
    "iso:country":"US",
    "sg:address":"700 W Division St",
    "sg:city":"Arlington",
    "sg:classifiers":[
        {
            "category":"Restaurant",
            "type":"Food & Drink"
        }
    ],
    "sg:menulink":"http://www.allmenus.com/tx/arlington/177272-jack-in-the-box/menu/",
    "sg:phone":"+1 817 460 7888",
    "sg:postcode":"76012",
    "sg:province":"TX",
    "sg:tags":[
        "burger",
        "american"
    ],
    "wof:name":"Jack in the Box",
    "wof:placetype":"venue"
},
  "geometry": {"coordinates":[-97.11485399999999,32.738763],"type":"Point"}
}