{
  "type": "Feature",
  "properties": {
    "iso:country":"US",
    "sg:address":"124 Fm 517 Rd W",
    "sg:city":"Dickinson",
    "sg:classifiers":[
        {
            "category":"Restaurant",
            "type":"Food & Drink"
        }
    ],
    "sg:menulink":"http://www.allmenus.com/tx/texas-city-league-city/191912-wendys/menu/",
    "sg:phone":"+1 281 337 3331",
    "sg:postcode":"77539",
    "sg:province":"TX",
    "sg:tags":[
        "burger",
        "american",
        "soup"
    ],
    "wof:name":"Wendy's",
    "wof:placetype":"venue"
},
  "geometry": {"coordinates":[-95.07884300000001,29.447798],"type":"Point"}
}