{
  "type": "Feature",
  "properties": {
    "iso:country":"US",
    "sg:address":"3240 E Houston Harte Frontage Rd",
    "sg:city":"San Angelo",
    "sg:classifiers":[
        {
            "category":"Real Estate",
            "subcategory":"Developer",
            "type":"Services"
        }
    ],
    "sg:phone":"+1 325 942 7523",
    "sg:postcode":"76901",
    "sg:province":"TX",
    "wof:name":"Runion Development Co",
    "wof:placetype":"venue"
},
  "geometry": {"coordinates":[-100.39684099999999,31.476599],"type":"Point"}
}