{
  "type": "Feature",
  "properties": {
    "iso:country":"US",
    "sg:address":"2041 16th St",
    "sg:city":"Garland",
    "sg:classifiers":[
        {
            "category":"Recreation",
            "subcategory":"Boat Charter",
            "type":"Entertainment"
        }
    ],
    "sg:phone":"+1 972 278 5297",
    "sg:postcode":"75041",
    "sg:province":"TX",
    "sg:tags":[
        "boating"
    ],
    "wof:name":"Burlesons Marine Service",
    "wof:placetype":"venue"
},
  "geometry": {"coordinates":[-96.6511,32.891998],"type":"Point"}
}