{
  "type": "Feature",
  "properties": {
    "iso:country":"US",
    "sg:address":"2008 FM 902",
    "sg:city":"Sherman",
    "sg:classifiers":[
        {
            "category":"Shopping",
            "type":"Retail Goods"
        }
    ],
    "sg:phone":"+1 903 891 4111",
    "sg:postcode":"75090",
    "sg:province":"TX",
    "sg:tags":[
        "merchandise"
    ],
    "wof:name":"Artist Academy",
    "wof:placetype":"venue"
},
  "geometry": {"coordinates":[-96.52186500000001,33.51552],"type":"Point"}
}