{
  "type": "Feature",
  "properties": {
    "iso:country":"US",
    "sg:address":"232 Little Field Dr",
    "sg:city":"Point",
    "sg:classifiers":[
        {
            "category":"Shopping",
            "subcategory":"Gifts & Souvenirs",
            "type":"Retail Goods"
        }
    ],
    "sg:phone":"+1 903 447 4107",
    "sg:postcode":"75472",
    "sg:province":"TX",
    "wof:name":"Klaus Haus Productions",
    "wof:placetype":"venue"
},
  "geometry": {"coordinates":[-95.963221,32.90407],"type":"Point"}
}