{
  "type": "Feature",
  "properties": {
    "iso:country":"US",
    "sg:address":"14405 Walters Rd",
    "sg:city":"Houston",
    "sg:classifiers":[
        {
            "category":"Professional",
            "subcategory":"Employment Agencies",
            "type":"Services"
        }
    ],
    "sg:phone":"+1 281 580 0500",
    "sg:postcode":"77014",
    "sg:province":"TX",
    "sg:tags":[
        "help",
        "supply"
    ],
    "wof:name":"Ocs Chauffer Services LLC",
    "wof:placetype":"venue"
},
  "geometry": {"coordinates":[-95.482112,29.991254],"type":"Point"}
}