{
  "type": "Feature",
  "properties": {
    "iso:country":"US",
    "sg:address":"841 Dividend Rd",
    "sg:city":"Midlothian",
    "sg:classifiers":[
        {
            "category":"Professional",
            "type":"Services"
        },
        {
            "category":"Retail",
            "subcategory":"Auto Repair",
            "type":"Services"
        }
    ],
    "sg:phone":"+1 972 775 6225",
    "sg:postcode":"76065",
    "sg:province":"TX",
    "sg:tags":[
        "transmission"
    ],
    "wof:name":"Hobart Performance Trans",
    "wof:placetype":"venue"
},
  "geometry": {"coordinates":[-96.955641,32.474916],"type":"Point"}
}