{
  "type": "Feature",
  "properties": {
    "iso:country":"US",
    "sg:address":"1544 Centeno Ln",
    "sg:city":"Laredo",
    "sg:classifiers":[
        {
            "category":"Food & Beverages",
            "subcategory":"Groceries & Convenience Stores",
            "type":"Retail Goods"
        }
    ],
    "sg:phone":"+1 956 725 8170",
    "sg:postcode":"78046",
    "sg:province":"TX",
    "wof:name":"Kinos Grocery & Meat Market",
    "wof:placetype":"venue"
},
  "geometry": {"coordinates":[-99.48305000000001,27.365153],"type":"Point"}
}