{
  "type": "Feature",
  "properties": {
    "iso:country":"US",
    "sg:address":"317 Suttonwood Dr",
    "sg:city":"Fort Worth",
    "sg:classifiers":[
        {
            "category":"Shopping",
            "subcategory":"Hobbies, Toys, & Games",
            "type":"Retail Goods"
        }
    ],
    "sg:phone":"+1 817 246 5933",
    "sg:postcode":"76108",
    "sg:province":"TX",
    "wof:name":"Millennium Racing",
    "wof:placetype":"venue"
},
  "geometry": {"coordinates":[-97.4956,32.754435],"type":"Point"}
}