{
  "type": "Feature",
  "properties": {
    "iso:country":"US",
    "sg:address":"918 Westlawn Dr",
    "sg:city":"Texarkana",
    "sg:classifiers":[
        {
            "category":"Organizations",
            "subcategory":"Community Association",
            "type":"Services"
        }
    ],
    "sg:phone":"+1 903 832 2725",
    "sg:postcode":"75501",
    "sg:province":"TX",
    "sg:tags":[
        "club"
    ],
    "wof:name":"Masonic Lodge",
    "wof:placetype":"venue"
},
  "geometry": {"coordinates":[-94.093346,33.433333],"type":"Point"}
}