{
  "type": "Feature",
  "properties": {
    "iso:country":"US",
    "sg:address":"106 3rd Ave",
    "sg:city":"Nederland",
    "sg:classifiers":[
        {
            "category":"Shopping",
            "subcategory":"Hobbies, Toys, & Games",
            "type":"Retail Goods"
        }
    ],
    "sg:phone":"+1 409 727 8333",
    "sg:postcode":"77627",
    "sg:province":"TX",
    "sg:tags":[
        "product",
        "ceramic"
    ],
    "wof:name":"Maggie's Ceramics",
    "wof:placetype":"venue"
},
  "geometry": {"coordinates":[-94.019854,29.993697],"type":"Point"}
}