{
  "type": "Feature",
  "properties": {
    "iso:country":"US",
    "sg:address":"1901 W William Cannon Drive Suite 153",
    "sg:city":"Austin",
    "sg:classifiers":[
        {
            "category":"Retail",
            "subcategory":"Veterinary Services",
            "type":"Services"
        }
    ],
    "sg:phone":"+1 512 441 5900",
    "sg:postcode":"78745",
    "sg:province":"TX",
    "sg:tags":[
        "hospital",
        "veterinarian",
        "clinic"
    ],
    "sg:website":"www.southaustinpetclinic.com",
    "wof:name":"South Austin Pet Clinic",
    "wof:placetype":"venue"
},
  "geometry": {"coordinates":[-97.80441500000001,30.202218],"type":"Point"}
}