{
  "type": "Feature",
  "properties": {
    "iso:country":"US",
    "sg:address":"9406 State Hwy 154",
    "sg:city":"Big Sandy",
    "sg:classifiers":[
        {
            "category":"Building & Trades",
            "subcategory":"Construction",
            "type":"Services"
        }
    ],
    "sg:phone":"+1 903 725 6324",
    "sg:postcode":"75755",
    "sg:province":"TX",
    "sg:tags":[
        "concrete",
        "contractor"
    ],
    "wof:name":"Phillips Concrete Construction",
    "wof:placetype":"venue"
},
  "geometry": {"coordinates":[-95.103526,32.753349],"type":"Point"}
}