{
  "type": "Feature",
  "properties": {
    "iso:country":"US",
    "sg:address":"11858 Basilica St",
    "sg:city":"Houston",
    "sg:classifiers":[
        {
            "category":"Retail",
            "subcategory":"Auto Repair",
            "type":"Services"
        }
    ],
    "sg:phone":"+1 281 564 4220",
    "sg:postcode":"77099",
    "sg:province":"TX",
    "sg:tags":[
        "general"
    ],
    "wof:name":"P&I Auto Repair Inc",
    "wof:placetype":"venue"
},
  "geometry": {"coordinates":[-95.58798299999999,29.662593],"type":"Point"}
}