{
  "type": "Feature",
  "properties": {
    "iso:country":"US",
    "sg:address":"5134 Jacksboro Hwy",
    "sg:city":"Fort Worth",
    "sg:classifiers":[
        {
            "category":"Professional",
            "subcategory":"Lawyer & Legal Services",
            "type":"Services"
        }
    ],
    "sg:phone":"+1 817 626 0045",
    "sg:postcode":"76114",
    "sg:province":"TX",
    "sg:tags":[
        "attorney"
    ],
    "wof:name":"Proyecto",
    "wof:placetype":"venue"
},
  "geometry": {"coordinates":[-97.39607599999999,32.795295],"type":"Point"}
}