{
  "type": "Feature",
  "properties": {
    "iso:country":"US",
    "sg:address":"329 Las Colinas Blvd E",
    "sg:city":"Irving",
    "sg:classifiers":[
        {
            "category":"Personal",
            "subcategory":"Massage",
            "type":"Services"
        }
    ],
    "sg:phone":"+1 972 409 2639",
    "sg:postcode":"75039",
    "sg:province":"TX",
    "sg:website":"www.lakeshoremassagetherapy.com",
    "wof:name":"Lakeshore Massage Therapy",
    "wof:placetype":"venue"
},
  "geometry": {"coordinates":[-96.936142,32.864743],"type":"Point"}
}