{
  "type": "Feature",
  "properties": {
    "iso:country":"US",
    "sg:address":"319 Four Oaks St",
    "sg:city":"Clute",
    "sg:classifiers":[
        {
            "category":"Restaurant",
            "type":"Food & Drink"
        }
    ],
    "sg:phone":"+1 979 265 7547",
    "sg:postcode":"77531",
    "sg:province":"TX",
    "sg:tags":[
        "eating"
    ],
    "wof:name":"Kens Ice Cream",
    "wof:placetype":"venue"
},
  "geometry": {"coordinates":[-95.415291,29.066948],"type":"Point"}
}