{
  "type": "Feature",
  "properties": {
    "iso:country":"US",
    "sg:address":"18170 Dallas Pkwy Ste 502",
    "sg:city":"Dallas",
    "sg:classifiers":[
        {
            "category":"Health Services",
            "subcategory":"Health Practitioner",
            "type":"Services"
        }
    ],
    "sg:phone":"+1 972 669 9944",
    "sg:postcode":"75287",
    "sg:province":"TX",
    "sg:tags":[
        "hypnotist"
    ],
    "wof:name":"Husbands Marjorie A",
    "wof:placetype":"venue"
},
  "geometry": {"coordinates":[-96.829054,32.996582],"type":"Point"}
}