{
  "type": "Feature",
  "properties": {
    "iso:country":"US",
    "sg:address":"1208 Douglass Rd",
    "sg:city":"Nacogdoches",
    "sg:classifiers":[
        {
            "category":"Restaurant",
            "type":"Food & Drink"
        }
    ],
    "sg:phone":"+1 936 564 2801",
    "sg:postcode":"75964",
    "sg:province":"TX",
    "wof:name":"Skatarama",
    "wof:placetype":"venue"
},
  "geometry": {"coordinates":[-94.66711100000001,31.606192],"type":"Point"}
}