{
  "type": "Feature",
  "properties": {
    "iso:country":"US",
    "sg:address":"11120 Indian Trl",
    "sg:city":"Dallas",
    "sg:classifiers":[
        {
            "category":"Building & Trades",
            "subcategory":"Electrical",
            "type":"Services"
        }
    ],
    "sg:phone":"+1 972 241 0622",
    "sg:postcode":"75229",
    "sg:province":"TX",
    "sg:tags":[
        "plumbing",
        "air",
        "electrician",
        "heating",
        "contractor"
    ],
    "sg:website":"www.lentzlighting.com",
    "wof:name":"Lentz Landscape Lighting",
    "wof:placetype":"venue"
},
  "geometry": {"coordinates":[-96.883499,32.9002],"type":"Point"}
}