{
  "type": "Feature",
  "properties": {
    "iso:country":"US",
    "sg:address":"513 Vermillion Dr",
    "sg:city":"Pasadena",
    "sg:classifiers":[
        {
            "category":"Wholesale",
            "subcategory":"Machinery & Supplies",
            "type":"Manufacturing & Wholesale Goods"
        }
    ],
    "sg:phone":"+1 713 477 3144",
    "sg:postcode":"77506",
    "sg:province":"TX",
    "sg:tags":[
        "tool"
    ],
    "wof:name":"Industrial Air Tool",
    "wof:placetype":"venue"
},
  "geometry": {"coordinates":[-95.22703,29.701755],"type":"Point"}
}