{
  "type": "Feature",
  "properties": {
    "iso:country":"US",
    "sg:address":"4802 Old Spanish Trl",
    "sg:city":"Houston",
    "sg:classifiers":[
        {
            "category":"Banks & Credit Unions",
            "subcategory":"Bank",
            "type":"Services"
        }
    ],
    "sg:phone":"+1 713 741 3333",
    "sg:postcode":"77021",
    "sg:province":"TX",
    "sg:tags":[
        "mortgage",
        "loan",
        "broker",
        "real estate"
    ],
    "wof:name":"Mariners Mortgage LLC",
    "wof:placetype":"venue"
},
  "geometry": {"coordinates":[-95.34352699999999,29.706103],"type":"Point"}
}