{
  "type": "Feature",
  "properties": {
    "iso:country":"US",
    "sg:address":"2420 High School Dr",
    "sg:city":"Vernon",
    "sg:classifiers":[
        {
            "category":"Organizations",
            "subcategory":"Religious Organization",
            "type":"Services"
        }
    ],
    "sg:phone":"+1 940 553 1643",
    "sg:postcode":"76384",
    "sg:province":"TX",
    "sg:tags":[
        "church"
    ],
    "wof:name":"Faith United Methodist Church",
    "wof:placetype":"venue"
},
  "geometry": {"coordinates":[-99.313444,34.142622],"type":"Point"}
}