{
  "type": "Feature",
  "properties": {
    "iso:country":"US",
    "sg:address":"2007 E Riverside Dr Ste E",
    "sg:city":"Austin",
    "sg:classifiers":[
        {
            "category":"Personal",
            "subcategory":"Nail Salon",
            "type":"Services"
        }
    ],
    "sg:phone":"+1 512 385 1615",
    "sg:postcode":"78741",
    "sg:province":"TX",
    "wof:name":"Nails By Tina",
    "wof:placetype":"venue"
},
  "geometry": {"coordinates":[-97.72779,30.241053],"type":"Point"}
}