{
  "type": "Feature",
  "properties": {
    "iso:country":"US",
    "sg:address":"207 E 53rd St #A",
    "sg:city":"Austin",
    "sg:classifiers":[
        {
            "category":"Shopping",
            "subcategory":"Used Merchandise",
            "type":"Retail Goods"
        }
    ],
    "sg:phone":"+1 512 300 2792",
    "sg:postcode":"78751",
    "sg:province":"TX",
    "sg:tags":[
        "vintage",
        "consignment"
    ],
    "sg:website":"www.myspace.com/slinkywhistlebait",
    "wof:name":"Slinky Whistle Bait",
    "wof:placetype":"venue"
},
  "geometry": {"coordinates":[-97.72112199999999,30.317674],"type":"Point"}
}