{
  "type": "Feature",
  "properties": {
    "iso:country":"US",
    "sg:address":"1617 Highdale Ct",
    "sg:city":"Flower Mound",
    "sg:classifiers":[
        {
            "category":"Professional",
            "subcategory":"Business Services",
            "type":"Services"
        }
    ],
    "sg:phone":"+1 972 355 6742",
    "sg:postcode":"75028",
    "sg:province":"TX",
    "wof:name":"Mustard Seeds Quilts",
    "wof:placetype":"venue"
},
  "geometry": {"coordinates":[-97.05407599999999,33.050323],"type":"Point"}
}