{
  "type": "Feature",
  "properties": {
    "iso:country":"US",
    "sg:address":"3195 Waverly St",
    "sg:city":"Beaumont",
    "sg:classifiers":[
        {
            "category":"Building & Trades",
            "subcategory":"Cleaning & Sanitation",
            "type":"Services"
        }
    ],
    "sg:phone":"+1 409 842 1712",
    "sg:postcode":"77705",
    "sg:province":"TX",
    "sg:tags":[
        "maintenance"
    ],
    "wof:name":"Lewis Maintenance Service",
    "wof:placetype":"venue"
},
  "geometry": {"coordinates":[-94.120368,30.053154],"type":"Point"}
}