{
  "type": "Feature",
  "properties": {
    "iso:country":"US",
    "sg:address":"6007 Central Falls Dr",
    "sg:city":"Houston",
    "sg:classifiers":[
        {
            "category":"Wholesale",
            "subcategory":"Toys & Hobbies",
            "type":"Manufacturing & Wholesale Goods"
        }
    ],
    "sg:phone":"+1 713 983 7449",
    "sg:postcode":"77041",
    "sg:province":"TX",
    "sg:tags":[
        "wholesaler"
    ],
    "wof:name":"Crawford International Sales",
    "wof:placetype":"venue"
},
  "geometry": {"coordinates":[-95.61655500000001,29.855848],"type":"Point"}
}