{
  "type": "Feature",
  "properties": {
    "iso:country":"US",
    "sg:address":"2634 S Carrier Pkwy",
    "sg:city":"Grand Prairie",
    "sg:classifiers":[
        {
            "category":"Professional",
            "subcategory":"Business Services",
            "type":"Services"
        }
    ],
    "sg:phone":"+1 972 641 0279",
    "sg:postcode":"75052",
    "sg:province":"TX",
    "wof:name":"MKH Enterprises",
    "wof:placetype":"venue"
},
  "geometry": {"coordinates":[-97.01557699999999,32.706883],"type":"Point"}
}