{
  "type": "Feature",
  "properties": {
    "iso:country":"US",
    "sg:address":"2802 Cary Dr",
    "sg:city":"Mesquite",
    "sg:classifiers":[
        {
            "category":"Wholesale",
            "subcategory":"Hardware",
            "type":"Manufacturing & Wholesale Goods"
        }
    ],
    "sg:phone":"+1 972 270 4530",
    "sg:postcode":"75150",
    "sg:province":"TX",
    "sg:tags":[
        "refrigeration"
    ],
    "wof:name":"K Air Comfort Cooling & Heat",
    "wof:placetype":"venue"
},
  "geometry": {"coordinates":[-96.640621,32.812846],"type":"Point"}
}