{
  "type": "Feature",
  "properties": {
    "iso:country":"US",
    "sg:address":"7539 Larchmont Dr",
    "sg:city":"Dallas",
    "sg:classifiers":[
        {
            "category":"Professional",
            "subcategory":"Computer Services",
            "type":"Services"
        }
    ],
    "sg:phone":"+1 972 931 9205",
    "sg:postcode":"75252",
    "sg:province":"TX",
    "sg:tags":[
        "programming"
    ],
    "wof:name":"Merisale",
    "wof:placetype":"venue"
},
  "geometry": {"coordinates":[-96.773754,32.99468],"type":"Point"}
}