{
  "type": "Feature",
  "properties": {
    "iso:country":"US",
    "sg:address":"4413 N Garfield St",
    "sg:city":"Midland",
    "sg:classifiers":[
        {
            "category":"Retail",
            "subcategory":"Laundry & Dry Cleaning",
            "type":"Services"
        }
    ],
    "sg:phone":"+1 432 684 3899",
    "sg:postcode":"79705",
    "sg:province":"TX",
    "sg:tags":[
        "cleaners"
    ],
    "wof:name":"Plaza Cleaners",
    "wof:placetype":"venue"
},
  "geometry": {"coordinates":[-102.11276599999999,32.037195],"type":"Point"}
}