{
  "type": "Feature",
  "properties": {
    "iso:country":"US",
    "sg:address":"10101 Cimmaron Trl",
    "sg:city":"Dallas",
    "sg:classifiers":[
        {
            "category":"Freight",
            "type":"Transportation"
        }
    ],
    "sg:phone":"+1 972 792 8381",
    "sg:postcode":"75243",
    "sg:province":"TX",
    "sg:tags":[
        "courier"
    ],
    "wof:name":"Street Smart Couriers",
    "wof:placetype":"venue"
},
  "geometry": {"coordinates":[-96.708834,32.926741],"type":"Point"}
}