{
  "type": "Feature",
  "properties": {
    "iso:country":"US",
    "sg:address":"1301 W Poplar St",
    "sg:city":"San Antonio",
    "sg:classifiers":[
        {
            "category":"Home & Garden",
            "subcategory":"Building Materials",
            "type":"Retail Goods"
        }
    ],
    "sg:phone":"+1 210 208 1880",
    "sg:postcode":"78207",
    "sg:province":"TX",
    "sg:tags":[
        "mixed",
        "concrete"
    ],
    "wof:name":"Alamo Concrete Products LTD",
    "wof:placetype":"venue"
},
  "geometry": {"coordinates":[-98.509518,29.439245],"type":"Point"}
}