{
  "type": "Feature",
  "properties": {
    "iso:country":"US",
    "sg:address":"9214 Cattail Gate Ct",
    "sg:city":"Humble",
    "sg:classifiers":[
        {
            "category":"Professional",
            "subcategory":"Business Services",
            "type":"Services"
        }
    ],
    "sg:phone":"+1 832 644 9371",
    "sg:postcode":"77396",
    "sg:province":"TX",
    "sg:tags":[
        "holding"
    ],
    "wof:name":"Jason P. Bartholomew Holding Group",
    "wof:placetype":"venue"
},
  "geometry": {"coordinates":[-95.25587,29.936572],"type":"Point"}
}