{
  "type": "Feature",
  "properties": {
    "iso:country":"US",
    "sg:address":"4612 SW Loop 820",
    "sg:city":"Fort Worth",
    "sg:classifiers":[
        {
            "category":"Restaurant",
            "type":"Food & Drink"
        }
    ],
    "sg:menulink":"http://www.allmenus.com/tx/fort-worth/130792-subway/menu/",
    "sg:phone":"+1 817 377 2624",
    "sg:postcode":"76109",
    "sg:province":"TX",
    "sg:tags":[
        "american",
        "sandwich"
    ],
    "wof:name":"Subway",
    "wof:placetype":"venue"
},
  "geometry": {"coordinates":[-97.393832,32.68166],"type":"Point"}
}