{
  "type": "Feature",
  "properties": {
    "iso:country":"US",
    "sg:address":"7103 Robin Rest Dr",
    "sg:city":"San Antonio",
    "sg:classifiers":[
        {
            "category":"Home & Garden",
            "subcategory":"Garden Supply",
            "type":"Retail Goods"
        }
    ],
    "sg:phone":"+1 210 826 3952",
    "sg:postcode":"78209",
    "sg:province":"TX",
    "sg:tags":[
        "nurseryman"
    ],
    "wof:name":"Tropics Nursery",
    "wof:placetype":"venue"
},
  "geometry": {"coordinates":[-98.436103,29.497368],"type":"Point"}
}