{
  "type": "Feature",
  "properties": {
    "iso:country":"US",
    "sg:address":"701 Park Place Ave",
    "sg:city":"Amarillo",
    "sg:classifiers":[
        {
            "category":"Organizations",
            "subcategory":"Non-profit Organization",
            "type":"Services"
        }
    ],
    "sg:phone":"+1 806 337 5292",
    "sg:postcode":"79101",
    "sg:province":"AR",
    "sg:website":"www.parkcentral.org",
    "wof:name":"Baptist Community Svc",
    "wof:placetype":"venue"
},
  "geometry": {"coordinates":[-101.84596000000001,35.201404],"type":"Point"}
}