{
  "type": "Feature",
  "properties": {
    "iso:country":"US",
    "sg:address":"9114 Cochran Chapel Cir",
    "sg:city":"Dallas",
    "sg:classifiers":[
        {
            "category":"Health Services",
            "subcategory":"Dentist",
            "type":"Services"
        }
    ],
    "sg:phone":"+1 214 353 8555",
    "sg:postcode":"75209",
    "sg:province":"TX",
    "wof:name":"Hart Phillip DDS",
    "wof:placetype":"venue"
},
  "geometry": {"coordinates":[-96.83551199999999,32.862939],"type":"Point"}
}