{
  "type": "Feature",
  "properties": {
    "iso:country":"US",
    "sg:address":"720 Lamar Pl",
    "sg:city":"Austin",
    "sg:classifiers":[
        {
            "category":"Restaurant",
            "type":"Food & Drink"
        }
    ],
    "sg:phone":"+1 512 459 0034",
    "sg:postcode":"78752",
    "sg:province":"TX",
    "sg:tags":[
        "eating"
    ],
    "wof:name":"Taqueria Jefes",
    "wof:placetype":"venue"
},
  "geometry": {"coordinates":[-97.722483,30.331574],"type":"Point"}
}