{
  "type": "Feature",
  "properties": {
    "iso:country":"US",
    "sg:address":"7326 Log Cradle Dr",
    "sg:city":"Houston",
    "sg:classifiers":[
        {
            "category":"Professional",
            "subcategory":"Business Services",
            "type":"Services"
        }
    ],
    "sg:phone":"+1 713 849 4502",
    "sg:postcode":"77041",
    "sg:province":"TX",
    "wof:name":"Katy Music Teachers Assoc",
    "wof:placetype":"venue"
},
  "geometry": {"coordinates":[-95.61232099999999,29.884057],"type":"Point"}
}