{
  "type": "Feature",
  "properties": {
    "iso:country":"US",
    "sg:address":"5110 Griggs Rd",
    "sg:city":"Houston",
    "sg:classifiers":[
        {
            "category":"Shopping",
            "subcategory":"Clothing, Apparel, & Fashions",
            "type":"Retail Goods"
        }
    ],
    "sg:phone":"+1 713 748 7604",
    "sg:postcode":"77021",
    "sg:province":"TX",
    "sg:tags":[
        "family"
    ],
    "wof:name":"Fashion Family",
    "wof:placetype":"venue"
},
  "geometry": {"coordinates":[-95.337986,29.698224],"type":"Point"}
}