{
  "type": "Feature",
  "properties": {
    "iso:country":"US",
    "sg:address":"6829 Woodland Dr",
    "sg:city":"Dallas",
    "sg:classifiers":[
        {
            "category":"Professional",
            "subcategory":"Business Services",
            "type":"Services"
        }
    ],
    "sg:phone":"+1 214 692 5596",
    "sg:postcode":"75225",
    "sg:province":"TX",
    "sg:tags":[
        "event"
    ],
    "wof:name":"Mike Miller & Assoc Spcl Evnts",
    "wof:placetype":"venue"
},
  "geometry": {"coordinates":[-96.78868,32.872565],"type":"Point"}
}