{
  "type": "Feature",
  "properties": {
    "iso:country":"US",
    "sg:address":"23103 Burcan Ct",
    "sg:city":"Spring",
    "sg:classifiers":[
        {
            "category":"Retail",
            "subcategory":"Veterinary Services",
            "type":"Services"
        }
    ],
    "sg:phone":"+1 281 651 1104",
    "sg:postcode":"77373",
    "sg:province":"TX",
    "sg:tags":[
        "specialty"
    ],
    "wof:name":"Sarah L Robertson Dvm",
    "wof:placetype":"venue"
},
  "geometry": {"coordinates":[-95.42643,30.097182],"type":"Point"}
}