{
  "type": "Feature",
  "properties": {
    "iso:country":"US",
    "sg:address":"12625 Wetmore Rd",
    "sg:city":"San Antonio",
    "sg:classifiers":[
        {
            "category":"Recreation",
            "type":"Entertainment"
        }
    ],
    "sg:phone":"+1 210 495 9700",
    "sg:postcode":"78247",
    "sg:province":"TX",
    "wof:name":"Strike Zone The Ltd",
    "wof:placetype":"venue"
},
  "geometry": {"coordinates":[-98.427538,29.554517],"type":"Point"}
}