{
  "type": "Feature",
  "properties": {
    "iso:country":"US",
    "sg:address":"1717 Angel Pkwy",
    "sg:city":"Allen",
    "sg:classifiers":[
        {
            "category":"Shopping",
            "subcategory":"Stationery & Office Supplies",
            "type":"Retail Goods"
        }
    ],
    "sg:phone":"+1 972 727 4110",
    "sg:postcode":"75002",
    "sg:province":"TX",
    "sg:tags":[
        "album",
        "scrapbook"
    ],
    "wof:name":"A Peek Into Yesterday",
    "wof:placetype":"venue"
},
  "geometry": {"coordinates":[-96.628677,33.125107],"type":"Point"}
}