{
  "type": "Feature",
  "properties": {
    "iso:country":"US",
    "sg:address":"420 S Main St",
    "sg:city":"Perryton",
    "sg:classifiers":[
        {
            "category":"Autos & Motor Vehicles",
            "subcategory":"Automobile Sales",
            "type":"Retail Goods"
        }
    ],
    "sg:phone":"+1 806 435 7676",
    "sg:postcode":"79070",
    "sg:province":"TX",
    "sg:tags":[
        "pickup",
        "truck"
    ],
    "wof:name":"Hergert Ford",
    "wof:placetype":"venue"
},
  "geometry": {"coordinates":[-100.802752,36.396224],"type":"Point"}
}