{
  "type": "Feature",
  "properties": {
    "iso:country":"US",
    "sg:address":"22123 Bowden Dr",
    "sg:city":"New Caney",
    "sg:classifiers":[
        {
            "category":"Retail",
            "subcategory":"Repair Shop",
            "type":"Services"
        }
    ],
    "sg:phone":"+1 281 689 2895",
    "sg:postcode":"77357",
    "sg:province":"TX",
    "wof:name":"Capricorn Cleaning",
    "wof:placetype":"venue"
},
  "geometry": {"coordinates":[-95.229117,30.158657],"type":"Point"}
}