{
  "type": "Feature",
  "properties": {
    "iso:country":"US",
    "sg:address":"7002 Rd C",
    "sg:city":"Corpus Christi",
    "sg:classifiers":[
        {
            "category":"Retail",
            "subcategory":"Repair Shop",
            "type":"Services"
        }
    ],
    "sg:phone":"+1 361 991 3130",
    "sg:postcode":"78414",
    "sg:province":"TX",
    "wof:name":"Glenn S John Taxidermy",
    "wof:placetype":"venue"
},
  "geometry": {"coordinates":[-97.372213,27.650881],"type":"Point"}
}