{
  "type": "Feature",
  "properties": {
    "iso:country":"US",
    "sg:address":"2608 Richcreek Rd",
    "sg:city":"Austin",
    "sg:classifiers":[
        {
            "category":"Education",
            "subcategory":"School",
            "type":"Public Place"
        }
    ],
    "sg:phone":"+1 512 414 9400",
    "sg:postcode":"78757",
    "sg:province":"TX",
    "sg:website":"www.austin.isd.tenet.edu",
    "wof:name":"Austin Independent School District",
    "wof:placetype":"venue"
},
  "geometry": {"coordinates":[-97.736395,30.351661],"type":"Point"}
}