{
  "type": "Feature",
  "properties": {
    "iso:country":"US",
    "sg:address":"3402 Boca Raton Dr",
    "sg:city":"Missouri City",
    "sg:classifiers":[
        {
            "category":"Wholesale",
            "subcategory":"Home Furnishings",
            "type":"Manufacturing & Wholesale Goods"
        }
    ],
    "sg:phone":"+1 281 438 8787",
    "sg:postcode":"77459",
    "sg:province":"TX",
    "wof:name":"Desmoulin Inc",
    "wof:placetype":"venue"
},
  "geometry": {"coordinates":[-95.541445,29.568568],"type":"Point"}
}