{
  "type": "Feature",
  "properties": {
    "iso:country":"US",
    "sg:address":"2500 W Main St",
    "sg:city":"League City",
    "sg:classifiers":[
        {
            "category":"Insurance",
            "subcategory":"Insurance Agent",
            "type":"Services"
        }
    ],
    "sg:phone":"+1 281 557 9171",
    "sg:postcode":"77573",
    "sg:province":"TX",
    "wof:name":"A-Tex Insurance",
    "wof:placetype":"venue"
},
  "geometry": {"coordinates":[-95.125888,29.500528],"type":"Point"}
}