{
  "type": "Feature",
  "properties": {
    "iso:country":"US",
    "sg:address":"1709 San Antonio St",
    "sg:city":"Austin",
    "sg:classifiers":[
        {
            "category":"Personal",
            "subcategory":"Massage",
            "type":"Services"
        },
        {
            "category":"Health Services",
            "subcategory":"Clinic",
            "type":"Services"
        },
        {
            "category":"Health Services",
            "subcategory":"Health Practitioner",
            "type":"Services"
        }
    ],
    "sg:phone":"+1 512 407 9222",
    "sg:postcode":"78701",
    "sg:province":"TX",
    "sg:tags":[
        "therapist",
        "therapy",
        "physical"
    ],
    "wof:name":"On-Site Massage Therapy",
    "wof:placetype":"venue"
},
  "geometry": {"coordinates":[-97.743352,30.280101],"type":"Point"}
}