{
  "type": "Feature",
  "properties": {
    "iso:country":"US",
    "sg:address":"132 E Main St",
    "sg:city":"Cuero",
    "sg:classifiers":[
        {
            "category":"Organizations",
            "subcategory":"Membership Organization",
            "type":"Services"
        }
    ],
    "sg:phone":"+1 361 277 8877",
    "sg:postcode":"77954",
    "sg:province":"TX",
    "wof:name":"Calf",
    "wof:placetype":"venue"
},
  "geometry": {"coordinates":[-97.29128900000001,29.09035],"type":"Point"}
}