{
  "type": "Feature",
  "properties": {
    "iso:country":"US",
    "sg:address":"2607 McCallum Dr",
    "sg:city":"Austin",
    "sg:classifiers":[
        {
            "category":"Health Services",
            "subcategory":"Doctor",
            "type":"Services"
        }
    ],
    "sg:phone":"+1 512 472 1428",
    "sg:postcode":"78703",
    "sg:province":"TX",
    "wof:name":"McCaleb Wm E III MD",
    "wof:placetype":"venue"
},
  "geometry": {"coordinates":[-97.752098,30.2953],"type":"Point"}
}