{
  "type": "Feature",
  "properties": {
    "iso:country":"US",
    "sg:address":"481 Sawdust Rd",
    "sg:city":"Spring",
    "sg:classifiers":[
        {
            "category":"Shopping",
            "subcategory":"Computers & Home Electronics",
            "type":"Retail Goods"
        }
    ],
    "sg:phone":"+1 281 367 3135",
    "sg:postcode":"77380",
    "sg:province":"TX",
    "wof:name":"Radio Shack",
    "wof:placetype":"venue"
},
  "geometry": {"coordinates":[-95.45281199999999,30.12664],"type":"Point"}
}