{
  "type": "Feature",
  "properties": {
    "iso:country":"US",
    "sg:address":"523 Canary Ln",
    "sg:city":"Red Oak",
    "sg:classifiers":[
        {
            "category":"Shopping",
            "subcategory":"Bicycles & Sporting Goods",
            "type":"Retail Goods"
        }
    ],
    "sg:phone":"+1 972 617 2493",
    "sg:postcode":"75154",
    "sg:province":"TX",
    "wof:name":"Rock Creek Guns & Archery",
    "wof:placetype":"venue"
},
  "geometry": {"coordinates":[-96.80584500000001,32.527309],"type":"Point"}
}