{
  "type": "Feature",
  "properties": {
    "iso:country":"US",
    "sg:address":"2217 Fairmont Ave",
    "sg:city":"Mcallen",
    "sg:classifiers":[
        {
            "category":"Building & Trades",
            "subcategory":"Construction",
            "type":"Services"
        }
    ],
    "sg:phone":"+1 956 668 8453",
    "sg:postcode":"78504",
    "sg:province":"TX",
    "sg:tags":[
        "roofing",
        "contractor"
    ],
    "wof:name":"South Texas Tile Roofing",
    "wof:placetype":"venue"
},
  "geometry": {"coordinates":[-98.231414,26.280279],"type":"Point"}
}