{
  "type": "Feature",
  "properties": {
    "iso:country":"US",
    "sg:address":"3511 Oak Lawn Ave",
    "sg:city":"Dallas",
    "sg:classifiers":[
        {
            "category":"Restaurant",
            "type":"Food & Drink"
        }
    ],
    "sg:postcode":"75219",
    "sg:province":"TX",
    "sg:tags":[
        "flavor",
        "local"
    ],
    "sg:website":"www.yelp.com/elite",
    "wof:name":"Cheese 101 Elite CMYE @ Scardello",
    "wof:placetype":"venue"
},
  "geometry": {"coordinates":[-96.805334,32.81244],"type":"Point"}
}