{
  "type": "Feature",
  "properties": {
    "iso:country":"US",
    "sg:address":"815 E Rector St",
    "sg:city":"San Antonio",
    "sg:classifiers":[
        {
            "category":"Utilities",
            "subcategory":"Mobile Phone",
            "type":"Services"
        }
    ],
    "sg:phone":"+1 210 308 8008",
    "sg:postcode":"78216",
    "sg:province":"TX",
    "sg:tags":[
        "telephone",
        "cellular"
    ],
    "wof:name":"United States Cellular Corp",
    "wof:placetype":"venue"
},
  "geometry": {"coordinates":[-98.48098899999999,29.517105],"type":"Point"}
}