{
  "type": "Feature",
  "properties": {
    "iso:country":"US",
    "sg:address":"2955 W 15th St",
    "sg:city":"Plano",
    "sg:classifiers":[
        {
            "category":"Shopping",
            "type":"Retail Goods"
        }
    ],
    "sg:phone":"+1 972 596 6405",
    "sg:postcode":"75075",
    "sg:province":"TX",
    "sg:tags":[
        "cosmetic",
        "perfume"
    ],
    "wof:name":"Merle Norman Cosmetics",
    "wof:placetype":"venue"
},
  "geometry": {"coordinates":[-96.75268,33.019468],"type":"Point"}
}