{
  "type": "Feature",
  "properties": {
    "iso:country":"US",
    "sg:address":"1821 Montclair Dr",
    "sg:city":"Seguin",
    "sg:classifiers":[
        {
            "category":"Banks & Credit Unions",
            "subcategory":"Bank",
            "type":"Services"
        }
    ],
    "sg:phone":"+1 830 379 6790",
    "sg:postcode":"78155",
    "sg:province":"TX",
    "sg:tags":[
        "mortgage"
    ],
    "wof:name":"Pbg Mortgages Plus",
    "wof:placetype":"venue"
},
  "geometry": {"coordinates":[-97.92932399999999,29.570953],"type":"Point"}
}