{
  "type": "Feature",
  "properties": {
    "iso:country":"US",
    "sg:address":"2604 Lazy Oaks Drive",
    "sg:city":"Austin",
    "sg:classifiers":[
        {
            "category":"Sports & Exercise",
            "subcategory":"Playing Field",
            "type":"Entertainment"
        }
    ],
    "sg:phone":"+1 512 997 8475",
    "sg:postcode":"78745",
    "sg:province":"TX",
    "sg:tags":[
        "instruction",
        "fitness"
    ],
    "wof:name":"Austin Cycle Camp",
    "wof:placetype":"venue"
},
  "geometry": {"coordinates":[-97.814035,30.205583],"type":"Point"}
}