{
  "type": "Feature",
  "properties": {
    "iso:country":"US",
    "sg:address":"9440 Old Katy Rd",
    "sg:city":"Houston",
    "sg:classifiers":[
        {
            "category":"Health Services",
            "subcategory":"Health Practitioner",
            "type":"Services"
        }
    ],
    "sg:phone":"+1 713 468 1433",
    "sg:postcode":"77055",
    "sg:province":"TX",
    "wof:name":"Work Fitness Physical Therapy",
    "wof:placetype":"venue"
},
  "geometry": {"coordinates":[-95.5215,29.784852],"type":"Point"}
}