{
  "type": "Feature",
  "properties": {
    "iso:country":"US",
    "sg:address":"2128 Clower St",
    "sg:city":"San Antonio",
    "sg:classifiers":[
        {
            "category":"Professional",
            "subcategory":"Computer Services",
            "type":"Services"
        }
    ],
    "sg:phone":"+1 210 734 9372",
    "sg:postcode":"78201",
    "sg:province":"TX",
    "wof:name":"Aplus",
    "wof:placetype":"venue"
},
  "geometry": {"coordinates":[-98.529999,29.477689],"type":"Point"}
}