{
  "type": "Feature",
  "properties": {
    "iso:country":"US",
    "sg:address":"1603 128th St",
    "sg:city":"Lubbock",
    "sg:classifiers":[
        {
            "category":"Building & Trades",
            "subcategory":"Construction",
            "type":"Services"
        }
    ],
    "sg:phone":"+1 806 745 2941",
    "sg:postcode":"79423",
    "sg:province":"TX",
    "sg:tags":[
        "concrete",
        "contractor"
    ],
    "wof:name":"Concrete Specialty Co Inc",
    "wof:placetype":"venue"
},
  "geometry": {"coordinates":[-101.85743100000001,33.478053],"type":"Point"}
}