{
  "type": "Feature",
  "properties": {
    "iso:country":"US",
    "sg:address":"415 Parland Pl",
    "sg:city":"San Antonio",
    "sg:classifiers":[
        {
            "category":"Professional",
            "type":"Services"
        }
    ],
    "sg:phone":"+1 210 930 0335",
    "sg:postcode":"78209",
    "sg:province":"TX",
    "wof:name":"Mahncke Park Neighborhood",
    "wof:placetype":"venue"
},
  "geometry": {"coordinates":[-98.462974,29.458458],"type":"Point"}
}