{
  "type": "Feature",
  "properties": {
    "iso:country":"US",
    "sg:address":"1727 Analog Dr",
    "sg:city":"Richardson",
    "sg:classifiers":[
        {
            "category":"Real Estate",
            "subcategory":"Real Estate Agent",
            "type":"Services"
        }
    ],
    "sg:phone":"+1 972 437 4777",
    "sg:postcode":"75081",
    "sg:province":"TX",
    "sg:tags":[
        "management"
    ],
    "wof:name":"Mc Neff Companies",
    "wof:placetype":"venue"
},
  "geometry": {"coordinates":[-96.70038599999999,32.972032],"type":"Point"}
}