{
  "type": "Feature",
  "properties": {
    "iso:country":"US",
    "sg:address":"3502 Marigold Ln",
    "sg:city":"Wichita Falls",
    "sg:classifiers":[
        {
            "category":"Retail",
            "subcategory":"Portrait Studio",
            "type":"Services"
        }
    ],
    "sg:phone":"+1 940 692 4633",
    "sg:postcode":"76308",
    "sg:province":"TX",
    "sg:tags":[
        "photographer"
    ],
    "wof:name":"Rodriguez Portraits",
    "wof:placetype":"venue"
},
  "geometry": {"coordinates":[-98.556106,33.875034],"type":"Point"}
}