{
  "type": "Feature",
  "properties": {
    "iso:country":"US",
    "sg:address":"2400 Brookhollow Dr",
    "sg:city":"Abilene",
    "sg:classifiers":[
        {
            "category":"Organizations",
            "subcategory":"Religious Organization",
            "type":"Services"
        }
    ],
    "sg:phone":"+1 325 795 8780",
    "sg:postcode":"79605",
    "sg:province":"TX",
    "sg:tags":[
        "church"
    ],
    "wof:name":"Daybreak Community Svc Inc",
    "wof:placetype":"venue"
},
  "geometry": {"coordinates":[-99.77867999999999,32.419074],"type":"Point"}
}