{
  "type": "Feature",
  "properties": {
    "iso:country":"US",
    "sg:address":"104 Winchester Dr",
    "sg:city":"Bergheim",
    "sg:classifiers":[
        {
            "category":"Building & Trades",
            "subcategory":"Cleaning & Sanitation",
            "type":"Services"
        }
    ],
    "sg:phone":"+1 830 336 2997",
    "sg:postcode":"78004",
    "sg:province":"TX",
    "sg:tags":[
        "cleaning-industrial",
        "contractor"
    ],
    "wof:name":"Wt Voight Enterprises Inc",
    "wof:placetype":"venue"
},
  "geometry": {"coordinates":[-98.560858,29.851643],"type":"Point"}
}