{
  "type": "Feature",
  "properties": {
    "iso:country":"US",
    "sg:address":"5504 Ingomar Way",
    "sg:city":"Houston",
    "sg:classifiers":[
        {
            "category":"Building & Trades",
            "subcategory":"Plumbing",
            "type":"Services"
        }
    ],
    "sg:phone":"+1 713 433 9464",
    "sg:postcode":"77053",
    "sg:province":"TX",
    "wof:name":"Conley Plumbing",
    "wof:placetype":"venue"
},
  "geometry": {"coordinates":[-95.46457700000001,29.60136],"type":"Point"}
}