{
  "type": "Feature",
  "properties": {
    "iso:country":"US",
    "sg:address":"3107 Valley Ct",
    "sg:city":"Manvel",
    "sg:classifiers":[
        {
            "category":"Health Services",
            "subcategory":"Clinic",
            "type":"Services"
        }
    ],
    "sg:phone":"+1 281 692 1677",
    "sg:postcode":"77578",
    "sg:province":"TX",
    "sg:tags":[
        "welfare"
    ],
    "wof:name":"Baylor College Of Medicine",
    "wof:placetype":"venue"
},
  "geometry": {"coordinates":[-95.37154200000001,29.528522],"type":"Point"}
}