{
  "type": "Feature",
  "properties": {
    "iso:country":"US",
    "sg:address":"12999 Murphy Rd",
    "sg:city":"Stafford",
    "sg:classifiers":[
        {
            "category":"Manufacturing",
            "subcategory":"Printing",
            "type":"Manufacturing & Wholesale Goods"
        }
    ],
    "sg:phone":"+1 281 498 4141",
    "sg:postcode":"77477",
    "sg:province":"TX",
    "sg:tags":[
        "screen"
    ],
    "wof:name":"Extreme Graphics",
    "wof:placetype":"venue"
},
  "geometry": {"coordinates":[-95.56496199999999,29.633812],"type":"Point"}
}