{
  "type": "Feature",
  "properties": {
    "iso:country":"US",
    "sg:address":"5980 S M L King Jr Pkwy",
    "sg:city":"Beaumont",
    "sg:classifiers":[
        {
            "category":"Retail",
            "subcategory":"Auto Repair",
            "type":"Services"
        }
    ],
    "sg:phone":"+1 409 833 7040",
    "sg:postcode":"77705",
    "sg:province":"TX",
    "sg:tags":[
        "truck",
        "trailer",
        "maintenance"
    ],
    "wof:name":"Long Truck & Equipment",
    "wof:placetype":"venue"
},
  "geometry": {"coordinates":[-94.059568,30.03026],"type":"Point"}
}