{
  "type": "Feature",
  "properties": {
    "iso:country":"US",
    "sg:address":"15080 E Beltwood Pkwy Ste 108",
    "sg:city":"Addison",
    "sg:classifiers":[
        {
            "category":"Personal",
            "subcategory":"Skin Care",
            "type":"Services"
        },
        {
            "category":"Personal",
            "subcategory":"Day Spa",
            "type":"Services"
        }
    ],
    "sg:phone":"+1 972 308 0009",
    "sg:postcode":"75001",
    "sg:province":"TX",
    "wof:name":"Facials Plus",
    "wof:placetype":"venue"
},
  "geometry": {"coordinates":[-96.83198400000001,32.953309],"type":"Point"}
}