{
  "type": "Feature",
  "properties": {
    "iso:country":"US",
    "sg:address":"3913 Old Mill Rd",
    "sg:city":"Waco",
    "sg:classifiers":[
        {
            "category":"Professional",
            "subcategory":"Computer Services",
            "type":"Services"
        }
    ],
    "sg:phone":"+1 254 772 2223",
    "sg:postcode":"76710",
    "sg:province":"TX",
    "sg:tags":[
        "related"
    ],
    "wof:name":"Callan Braswell 1992 Ltd",
    "wof:placetype":"venue"
},
  "geometry": {"coordinates":[-97.200911,31.562456],"type":"Point"}
}