{
  "type": "Feature",
  "properties": {
    "iso:country":"US",
    "sg:address":"1044 Hickory St",
    "sg:city":"Colorado City",
    "sg:classifiers":[
        {
            "category":"Building & Trades",
            "subcategory":"Plumbing",
            "type":"Services"
        }
    ],
    "sg:phone":"+1 325 728 8989",
    "sg:postcode":"79512",
    "sg:province":"TX",
    "sg:tags":[
        "installation",
        "heating"
    ],
    "wof:name":"Watsco Sales & Service",
    "wof:placetype":"venue"
},
  "geometry": {"coordinates":[-100.861158,32.397153],"type":"Point"}
}