{
  "type": "Feature",
  "properties": {
    "iso:country":"US",
    "sg:address":"11701 Welcome Dr",
    "sg:city":"San Antonio",
    "sg:classifiers":[
        {
            "category":"Retail",
            "subcategory":"Portrait Studio",
            "type":"Services"
        }
    ],
    "sg:phone":"+1 210 654 7888",
    "sg:postcode":"78233",
    "sg:province":"TX",
    "sg:tags":[
        "photo"
    ],
    "wof:name":"R W Productions",
    "wof:placetype":"venue"
},
  "geometry": {"coordinates":[-98.33128600000001,29.546002],"type":"Point"}
}