{
  "type": "Feature",
  "properties": {
    "iso:country":"US",
    "sg:address":"836 Henson Dr",
    "sg:city":"Hurst",
    "sg:classifiers":[
        {
            "category":"Professional",
            "subcategory":"Business Services",
            "type":"Services"
        }
    ],
    "sg:phone":"+1 817 589 1661",
    "sg:postcode":"76053",
    "sg:province":"TX",
    "sg:tags":[
        "inspection"
    ],
    "wof:name":"Barcus Pipeline Inspection Svc",
    "wof:placetype":"venue"
},
  "geometry": {"coordinates":[-97.19028400000001,32.814531],"type":"Point"}
}