{
  "type": "Feature",
  "properties": {
    "iso:country":"US",
    "sg:address":"2100 6th Ave",
    "sg:city":"Amarillo",
    "sg:classifiers":[
        {
            "category":"Retail",
            "subcategory":"Auto Rental",
            "type":"Services"
        }
    ],
    "sg:phone":"+1 806 373 4488",
    "sg:postcode":"79106",
    "sg:province":"TX",
    "sg:tags":[
        "truck",
        "trailer",
        "utility"
    ],
    "wof:name":"U-Haul",
    "wof:placetype":"venue"
},
  "geometry": {"coordinates":[-101.861172,35.210803],"type":"Point"}
}