{
  "type": "Feature",
  "properties": {
    "iso:country":"US",
    "sg:address":"1813 Winewood Ln",
    "sg:city":"Arlington",
    "sg:classifiers":[
        {
            "category":"Shopping",
            "subcategory":"Used Merchandise",
            "type":"Retail Goods"
        }
    ],
    "sg:phone":"+1 817 277 6847",
    "sg:postcode":"76013",
    "sg:province":"TX",
    "wof:name":"Texas Woman",
    "wof:placetype":"venue"
},
  "geometry": {"coordinates":[-97.142805,32.71418],"type":"Point"}
}