{
  "type": "Feature",
  "properties": {
    "iso:country":"US",
    "sg:address":"3223 Stream Meadows Ln",
    "sg:city":"Sugar Land",
    "sg:classifiers":[
        {
            "category":"Building & Trades",
            "subcategory":"Construction",
            "type":"Services"
        }
    ],
    "sg:phone":"+1 281 980 3027",
    "sg:postcode":"77479",
    "sg:province":"TX",
    "sg:tags":[
        "general",
        "contractor"
    ],
    "wof:name":"Shepard Contracting Inc",
    "wof:placetype":"venue"
},
  "geometry": {"coordinates":[-95.617993,29.583427],"type":"Point"}
}