{
  "type": "Feature",
  "properties": {
    "iso:country":"US",
    "sg:address":"5433 Pebble Ct",
    "sg:city":"Mc Kinney",
    "sg:classifiers":[
        {
            "category":"Restaurant",
            "type":"Food & Drink"
        }
    ],
    "sg:phone":"+1 214 592 0077",
    "sg:postcode":"75070",
    "sg:province":"TX",
    "sg:tags":[
        "eating"
    ],
    "wof:name":"2 Girls & A Grill Catering",
    "wof:placetype":"venue"
},
  "geometry": {"coordinates":[-96.690494,33.195827],"type":"Point"}
}