{
  "type": "Feature",
  "properties": {
    "iso:country":"US",
    "sg:address":"2424 Flushing Mdws",
    "sg:city":"Weslaco",
    "sg:classifiers":[
        {
            "category":"Real Estate",
            "subcategory":"Real Estate Operator",
            "type":"Services"
        }
    ],
    "sg:phone":"+1 956 968 1558",
    "sg:postcode":"78596",
    "sg:province":"TX",
    "sg:tags":[
        "apartment"
    ],
    "wof:name":"Dulce Hogar Apartments",
    "wof:placetype":"venue"
},
  "geometry": {"coordinates":[-97.992722,26.134512],"type":"Point"}
}