{
  "type": "Feature",
  "properties": {
    "iso:country":"US",
    "sg:address":"10161 Sumatra St",
    "sg:city":"El Paso",
    "sg:classifiers":[
        {
            "category":"Shopping",
            "subcategory":"Jewelry",
            "type":"Retail Goods"
        }
    ],
    "sg:phone":"+1 915 595 1285",
    "sg:postcode":"79925",
    "sg:province":"TX",
    "sg:tags":[
        "jeweler"
    ],
    "wof:name":"Davanzo Jewelers",
    "wof:placetype":"venue"
},
  "geometry": {"coordinates":[-106.348342,31.778953],"type":"Point"}
}