{
  "type": "Feature",
  "properties": {
    "iso:country":"US",
    "sg:address":"2057 Sayles Blvd",
    "sg:city":"Abilene",
    "sg:classifiers":[
        {
            "category":"Shopping",
            "subcategory":"Gifts & Souvenirs",
            "type":"Retail Goods"
        }
    ],
    "sg:phone":"+1 325 695 9659",
    "sg:postcode":"79605",
    "sg:province":"TX",
    "sg:tags":[
        "shop"
    ],
    "wof:name":"M&M Enterprises",
    "wof:placetype":"venue"
},
  "geometry": {"coordinates":[-99.748063,32.423544],"type":"Point"}
}