{
  "type": "Feature",
  "properties": {
    "iso:country":"US",
    "sg:address":"3193 W Main St Suite 101",
    "sg:city":"Frisco",
    "sg:phone":"+1 214 387 3360",
    "sg:postcode":"75034",
    "sg:province":"TX",
    "sg:website":"http://www.coldstonecreamery.com",
    "wof:name":"Cold Stone Creamery",
    "wof:placetype":"venue"
},
  "geometry": {"coordinates":[-96.861969,33.152994],"type":"Point"}
}