{
  "type": "Feature",
  "properties": {
    "iso:country":"US",
    "sg:address":"407 Milligan Dr",
    "sg:city":"Pittsburg",
    "sg:classifiers":[
        {
            "category":"Organizations",
            "subcategory":"Religious Organization",
            "type":"Services"
        }
    ],
    "sg:phone":"+1 903 856 7150",
    "sg:postcode":"75686",
    "sg:province":"TX",
    "wof:name":"Primera Iglsia Btista Hispania",
    "wof:placetype":"venue"
},
  "geometry": {"coordinates":[-94.96366999999999,32.987575],"type":"Point"}
}