{
  "type": "Feature",
  "properties": {
    "iso:country":"US",
    "sg:address":"301 N Belt Line Rd",
    "sg:city":"Irving",
    "sg:classifiers":[
        {
            "category":"Home & Garden",
            "subcategory":"Mobile Homes",
            "type":"Retail Goods"
        }
    ],
    "sg:phone":"+1 972 399 1700",
    "sg:postcode":"75061",
    "sg:province":"TX",
    "wof:name":"San Jose Advantage Homes Inc",
    "wof:placetype":"venue"
},
  "geometry": {"coordinates":[-96.99388399999999,32.819167],"type":"Point"}
}