{
  "type": "Feature",
  "properties": {
    "iso:country":"US",
    "sg:address":"1000 Ballpark Way",
    "sg:city":"Arlington",
    "sg:classifiers":[
        {
            "category":"Health Services",
            "subcategory":"Health Practitioner",
            "type":"Services"
        }
    ],
    "sg:phone":"+1 817 277 1903",
    "sg:postcode":"76011",
    "sg:province":"TX",
    "sg:tags":[
        "therapist",
        "physical"
    ],
    "wof:name":"Healthsouth Sports Medicine",
    "wof:placetype":"venue"
},
  "geometry": {"coordinates":[-97.08089099999999,32.752428],"type":"Point"}
}