{
  "type": "Feature",
  "properties": {
    "iso:country":"US",
    "sg:address":"1151 Brittmoore Rd",
    "sg:city":"Houston",
    "sg:classifiers":[
        {
            "category":"Building & Trades",
            "subcategory":"Construction",
            "type":"Services"
        }
    ],
    "sg:phone":"+1 713 339 1777",
    "sg:postcode":"77043",
    "sg:province":"TX",
    "sg:tags":[
        "general",
        "contractor"
    ],
    "wof:name":"Design & Construction Contr",
    "wof:placetype":"venue"
},
  "geometry": {"coordinates":[-95.56989299999999,29.790063],"type":"Point"}
}