{
  "type": "Feature",
  "properties": {
    "iso:country":"US",
    "sg:address":"2013 N State Highway 121",
    "sg:city":"Bonham",
    "sg:classifiers":[
        {
            "category":"Personal",
            "subcategory":"Beauty Salon",
            "type":"Services"
        }
    ],
    "sg:phone":"+1 903 583 7100",
    "sg:postcode":"75418",
    "sg:province":"TX",
    "wof:name":"All Cuts",
    "wof:placetype":"venue"
},
  "geometry": {"coordinates":[-96.192009,33.613408],"type":"Point"}
}