{
  "type": "Feature",
  "properties": {
    "iso:country":"US",
    "sg:address":"5602 N Lamar Blvd",
    "sg:city":"Austin",
    "sg:classifiers":[
        {
            "category":"Fast Food",
            "type":"Food & Drink"
        },
        {
            "category":"Restaurant",
            "type":"Food & Drink"
        }
    ],
    "sg:phone":"+1 512 459 3239",
    "sg:postcode":"78751",
    "sg:province":"TX",
    "sg:tags":[
        "style",
        "hamburger",
        "family",
        "lunch",
        "dog",
        "burger",
        "hot",
        "take",
        "american",
        "brunch",
        "breakfast"
    ],
    "wof:name":"Dan's Hamburgers",
    "wof:placetype":"venue"
},
  "geometry": {"coordinates":[-97.727459,30.324832],"type":"Point"}
}