{
  "type": "Feature",
  "properties": {
    "iso:country":"US",
    "sg:address":"1200 Al Piano Ct",
    "sg:city":"Irving",
    "sg:classifiers":[
        {
            "category":"Restaurant",
            "type":"Food & Drink"
        }
    ],
    "sg:phone":"+1 972 438 8018",
    "sg:postcode":"75060",
    "sg:province":"TX",
    "sg:tags":[
        "eating"
    ],
    "wof:name":"Con Van Thai",
    "wof:placetype":"venue"
},
  "geometry": {"coordinates":[-96.938061,32.789258],"type":"Point"}
}