{
  "type": "Feature",
  "properties": {
    "iso:country":"US",
    "sg:address":"13111 Dessau Rd",
    "sg:city":"Austin",
    "sg:classifiers":[
        {
            "category":"Building & Trades",
            "subcategory":"Construction",
            "type":"Services"
        }
    ],
    "sg:phone":"+1 512 821 2808",
    "sg:postcode":"78754",
    "sg:province":"TX",
    "sg:tags":[
        "contractor"
    ],
    "wof:name":"Bland Schroeder Archer Lp",
    "wof:placetype":"venue"
},
  "geometry": {"coordinates":[-97.641403,30.399],"type":"Point"}
}