{
  "type": "Feature",
  "properties": {
    "iso:country":"US",
    "sg:address":"308 Purple Hills Way",
    "sg:city":"El Paso",
    "sg:classifiers":[
        {
            "category":"Bars & Pubs",
            "type":"Food & Drink"
        }
    ],
    "sg:phone":"+1 915 584 6064",
    "sg:postcode":"79912",
    "sg:province":"TX",
    "sg:tags":[
        "drinking"
    ],
    "wof:name":"Cutting Edge Inc",
    "wof:placetype":"venue"
},
  "geometry": {"coordinates":[-106.529059,31.83785],"type":"Point"}
}