{
  "type": "Feature",
  "properties": {
    "iso:country":"US",
    "sg:address":"1819 Sawyer St",
    "sg:city":"Houston",
    "sg:classifiers":[
        {
            "category":"Retail",
            "subcategory":"Portrait Studio",
            "type":"Services"
        },
        {
            "category":"Professional",
            "subcategory":"Art Services",
            "type":"Services"
        }
    ],
    "sg:phone":"+1 713 861 4321",
    "sg:postcode":"77007",
    "sg:province":"TX",
    "sg:tags":[
        "photographer",
        "photography",
        "store"
    ],
    "wof:name":"Green Mark Photography",
    "wof:placetype":"venue"
},
  "geometry": {"coordinates":[-95.38271899999999,29.773864],"type":"Point"}
}