{
  "type": "Feature",
  "properties": {
    "iso:country":"US",
    "sg:address":"5102 White Oak Rd",
    "sg:city":"Big Sandy",
    "sg:classifiers":[
        {
            "category":"Professional",
            "type":"Services"
        }
    ],
    "sg:phone":"+1 903 844 8807",
    "sg:postcode":"75755",
    "sg:province":"TX",
    "wof:name":"Kay May",
    "wof:placetype":"venue"
},
  "geometry": {"coordinates":[-95.00584600000001,32.57161],"type":"Point"}
}