{
  "type": "Feature",
  "properties": {
    "iso:country":"US",
    "sg:address":"867 Carlingford Ln",
    "sg:city":"Houston",
    "sg:classifiers":[
        {
            "category":"Shopping",
            "subcategory":"Used Merchandise",
            "type":"Retail Goods"
        }
    ],
    "sg:phone":"+1 281 497 6018",
    "sg:postcode":"77079",
    "sg:province":"TX",
    "wof:name":"Stallcups Antiques",
    "wof:placetype":"venue"
},
  "geometry": {"coordinates":[-95.594353,29.778829],"type":"Point"}
}