{
  "type": "Feature",
  "properties": {
    "iso:country":"US",
    "sg:address":"1305 S Winfree St",
    "sg:city":"Dayton",
    "sg:classifiers":[
        {
            "category":"Shopping",
            "subcategory":"Used Merchandise",
            "type":"Retail Goods"
        }
    ],
    "sg:phone":"+1 936 257 2575",
    "sg:postcode":"77535",
    "sg:province":"TX",
    "wof:name":"Scott Siple",
    "wof:placetype":"venue"
},
  "geometry": {"coordinates":[-94.878236,30.033979],"type":"Point"}
}