{
  "type": "Feature",
  "properties": {
    "iso:country":"US",
    "sg:address":"902 W Church St",
    "sg:city":"Livingston",
    "sg:classifiers":[
        {
            "category":"Home & Garden",
            "subcategory":"Household Appliances",
            "type":"Retail Goods"
        }
    ],
    "sg:phone":"+1 936 327 8792",
    "sg:postcode":"77351",
    "sg:province":"TX",
    "sg:tags":[
        "repair",
        "electrical"
    ],
    "wof:name":"Livingston Vacuum and Sew Co",
    "wof:placetype":"venue"
},
  "geometry": {"coordinates":[-94.941768,30.710968],"type":"Point"}
}