{
  "type": "Feature",
  "properties": {
    "iso:country":"US",
    "sg:address":"1310 2nd St",
    "sg:city":"Pleasanton",
    "sg:classifiers":[
        {
            "category":"Restaurant",
            "type":"Food & Drink"
        }
    ],
    "sg:phone":"+1 830 569 4777",
    "sg:postcode":"78064",
    "sg:province":"TX",
    "wof:name":"El Durango",
    "wof:placetype":"venue"
},
  "geometry": {"coordinates":[-98.478832,28.971863],"type":"Point"}
}