{
  "type": "Feature",
  "properties": {
    "iso:country":"US",
    "sg:address":"3302 Leopard St",
    "sg:city":"Corpus Christi",
    "sg:classifiers":[
        {
            "category":"Restaurant",
            "type":"Food & Drink"
        }
    ],
    "sg:phone":"+1 361 882 7021",
    "sg:postcode":"78408",
    "sg:province":"TX",
    "sg:tags":[
        "eating"
    ],
    "wof:name":"Tommys Chicken Coop",
    "wof:placetype":"venue"
},
  "geometry": {"coordinates":[-97.427267,27.796835],"type":"Point"}
}