{
  "type": "Feature",
  "properties": {
    "iso:country":"US",
    "sg:address":"1005 E Pleasant Run Rd",
    "sg:city":"Desoto",
    "sg:classifiers":[
        {
            "category":"Banks & Credit Unions",
            "subcategory":"Investment Brokerage",
            "type":"Services"
        },
        {
            "category":"Insurance",
            "subcategory":"Hazard Insurance",
            "type":"Services"
        }
    ],
    "sg:phone":"+1 972 224 3503",
    "sg:postcode":"75115",
    "sg:province":"TX",
    "sg:tags":[
        "commercial",
        "agent",
        "business",
        "resume"
    ],
    "wof:name":"Keith Walter W Insurance Agcy",
    "wof:placetype":"venue"
},
  "geometry": {"coordinates":[-96.834537,32.604339],"type":"Point"}
}