{
  "type": "Feature",
  "properties": {
    "iso:country":"US",
    "sg:address":"1510 Dewberry Blvd",
    "sg:city":"Lancaster",
    "sg:classifiers":[
        {
            "category":"Shopping",
            "subcategory":"Clothing, Apparel, & Fashions",
            "type":"Retail Goods"
        }
    ],
    "sg:phone":"+1 972 227 7790",
    "sg:postcode":"75134",
    "sg:province":"TX",
    "wof:name":"Mimis Fashion Express",
    "wof:placetype":"venue"
},
  "geometry": {"coordinates":[-96.767732,32.605078],"type":"Point"}
}