{
  "type": "Feature",
  "properties": {
    "iso:country":"US",
    "sg:address":"4537 Merida Ave",
    "sg:city":"Fort Worth",
    "sg:classifiers":[
        {
            "category":"Shopping",
            "subcategory":"Discount & Variety Stores",
            "type":"Retail Goods"
        }
    ],
    "sg:phone":"+1 817 924 2647",
    "sg:postcode":"76115",
    "sg:province":"TX",
    "sg:tags":[
        "merchandise",
        "general"
    ],
    "wof:name":"Polka DOT Specialties",
    "wof:placetype":"venue"
},
  "geometry": {"coordinates":[-97.355277,32.68071],"type":"Point"}
}