{
  "type": "Feature",
  "properties": {
    "iso:country":"US",
    "sg:address":"1420 Valwood Pkwy",
    "sg:city":"Carrollton",
    "sg:classifiers":[
        {
            "category":"Home & Garden",
            "subcategory":"Building Materials",
            "type":"Retail Goods"
        }
    ],
    "sg:phone":"+1 972 247 5770",
    "sg:postcode":"75006",
    "sg:province":"TX",
    "sg:tags":[
        "windows"
    ],
    "wof:name":"Showcase Custom Vinyl Windows",
    "wof:placetype":"venue"
},
  "geometry": {"coordinates":[-96.916867,32.938686],"type":"Point"}
}