{
  "type": "Feature",
  "properties": {
    "iso:country":"US",
    "sg:address":"301 W Central Ave",
    "sg:city":"Comanche",
    "sg:classifiers":[
        {
            "category":"Real Estate",
            "subcategory":"Real Estate Services",
            "type":"Services"
        }
    ],
    "sg:phone":"+1 254 893 3535",
    "sg:postcode":"76442",
    "sg:province":"TX",
    "sg:tags":[
        "abstract",
        "legal",
        "title"
    ],
    "wof:name":"Texas Abstract & Title",
    "wof:placetype":"venue"
},
  "geometry": {"coordinates":[-98.60724500000001,31.897409],"type":"Point"}
}