{
  "type": "Feature",
  "properties": {
    "iso:country":"US",
    "sg:address":"2304 Newcastle Cir",
    "sg:city":"Plano",
    "sg:classifiers":[
        {
            "category":"Manufacturing",
            "subcategory":"Metals",
            "type":"Manufacturing & Wholesale Goods"
        }
    ],
    "sg:phone":"+1 972 596 8115",
    "sg:postcode":"75075",
    "sg:province":"TX",
    "sg:tags":[
        "product",
        "mfg",
        "fabricated",
        "furniture"
    ],
    "wof:name":"Aero-Motive Company",
    "wof:placetype":"venue"
},
  "geometry": {"coordinates":[-96.75833299999999,33.030605],"type":"Point"}
}