{
  "type": "Feature",
  "properties": {
    "iso:country":"US",
    "sg:address":"1100 N Wood St",
    "sg:city":"Gilmer",
    "sg:classifiers":[
        {
            "category":"Retail",
            "subcategory":"Funeral Services",
            "type":"Services"
        }
    ],
    "sg:phone":"+1 903 843 2577",
    "sg:postcode":"75644",
    "sg:province":"TX",
    "sg:tags":[
        "director"
    ],
    "wof:name":"Grubbs-Loyd Funeral Home",
    "wof:placetype":"venue"
},
  "geometry": {"coordinates":[-94.9426,32.736584],"type":"Point"}
}