{
  "type": "Feature",
  "properties": {
    "iso:country":"US",
    "sg:address":"6219 Bellaire Blvd",
    "sg:city":"Houston",
    "sg:classifiers":[
        {
            "category":"Food & Beverages",
            "subcategory":"Groceries & Convenience Stores",
            "type":"Retail Goods"
        }
    ],
    "sg:phone":"+1 713 270 0010",
    "sg:postcode":"77081",
    "sg:province":"TX",
    "sg:tags":[
        "grocer"
    ],
    "wof:name":"La Placita Farmer's Market",
    "wof:placetype":"venue"
},
  "geometry": {"coordinates":[-95.4907,29.705299],"type":"Point"}
}