{
  "type": "Feature",
  "properties": {
    "iso:country":"US",
    "sg:address":"3355 Trinity Mills Rd",
    "sg:city":"Dallas",
    "sg:classifiers":[
        {
            "category":"Restaurant",
            "type":"Food & Drink"
        }
    ],
    "sg:phone":"+1 972 306 9464",
    "sg:postcode":"75287",
    "sg:province":"TX",
    "sg:tags":[
        "chicken"
    ],
    "wof:name":"Wingstop",
    "wof:placetype":"venue"
},
  "geometry": {"coordinates":[-96.841843,32.987322],"type":"Point"}
}