{
  "type": "Feature",
  "properties": {
    "iso:country":"US",
    "sg:address":"18007 Bruno Rd",
    "sg:city":"Justin",
    "sg:classifiers":[
        {
            "category":"Building & Trades",
            "subcategory":"Electrical",
            "type":"Services"
        }
    ],
    "sg:phone":"+1 940 242 2347",
    "sg:postcode":"76247",
    "sg:province":"TX",
    "sg:tags":[
        "computer",
        "installation",
        "telephone",
        "cable"
    ],
    "wof:name":"E & M Cabling Co",
    "wof:placetype":"venue"
},
  "geometry": {"coordinates":[-97.33512500000001,33.056968],"type":"Point"}
}