{
  "type": "Feature",
  "properties": {
    "iso:country":"US",
    "sg:address":"431 Pleasant Dr",
    "sg:city":"Dallas",
    "sg:classifiers":[
        {
            "category":"Organizations",
            "subcategory":"Religious Organization",
            "type":"Services"
        }
    ],
    "sg:phone":"+1 214 391 2111",
    "sg:postcode":"75217",
    "sg:province":"TX",
    "sg:tags":[
        "church"
    ],
    "wof:name":"Elam Baptist Church",
    "wof:placetype":"venue"
},
  "geometry": {"coordinates":[-96.679489,32.717281],"type":"Point"}
}