{
  "type": "Feature",
  "properties": {
    "iso:country":"US",
    "sg:address":"17070 Red Oak Dr",
    "sg:city":"Houston",
    "sg:classifiers":[
        {
            "category":"Health Services",
            "subcategory":"Doctor",
            "type":"Services"
        }
    ],
    "sg:phone":"+1 281 364 8264",
    "sg:postcode":"77090",
    "sg:province":"TX",
    "sg:tags":[
        "physician",
        "reconstructive",
        "surgery-general",
        "surgeons",
        "cosmetic",
        "plastic",
        "surgery",
        "surgeon"
    ],
    "wof:name":"Woodlands Plastic Surgery",
    "wof:placetype":"venue"
},
  "geometry": {"coordinates":[-95.443851,30.017182],"type":"Point"}
}