{
  "type": "Feature",
  "properties": {
    "iso:country":"US",
    "sg:address":"8614 Winewood Dr",
    "sg:city":"Houston",
    "sg:classifiers":[
        {
            "category":"Professional",
            "type":"Services"
        }
    ],
    "sg:phone":"+1 281 458 7752",
    "sg:postcode":"77044",
    "sg:province":"TX",
    "wof:name":"Phaedra",
    "wof:placetype":"venue"
},
  "geometry": {"coordinates":[-95.205095,29.850392],"type":"Point"}
}