{
  "type": "Feature",
  "properties": {
    "iso:country":"US",
    "sg:address":"5919 Jessamine St",
    "sg:city":"Houston",
    "sg:classifiers":[
        {
            "category":"Home & Garden",
            "subcategory":"Furniture",
            "type":"Retail Goods"
        }
    ],
    "sg:phone":"+1 713 278 9589",
    "sg:postcode":"77081",
    "sg:province":"TX",
    "sg:tags":[
        "store"
    ],
    "wof:name":"Kuo's Furniture Import Inc",
    "wof:placetype":"venue"
},
  "geometry": {"coordinates":[-95.485685,29.701398],"type":"Point"}
}