{
  "type": "Feature",
  "properties": {
    "iso:country":"US",
    "sg:address":"4925 NW Stallings Dr",
    "sg:city":"Nacogdoches",
    "sg:classifiers":[
        {
            "category":"Wholesale",
            "subcategory":"Machinery & Supplies",
            "type":"Manufacturing & Wholesale Goods"
        }
    ],
    "sg:phone":"+1 936 462 7100",
    "sg:postcode":"75964",
    "sg:province":"TX",
    "sg:tags":[
        "trailer"
    ],
    "wof:name":"Ameri Tech Bldg Systems LTD",
    "wof:placetype":"venue"
},
  "geometry": {"coordinates":[-94.68234099999999,31.645134],"type":"Point"}
}