{
  "type": "Feature",
  "properties": {
    "iso:country":"US",
    "sg:address":"145 Old Bridge Lake St",
    "sg:city":"Houston",
    "sg:classifiers":[
        {
            "category":"Building & Trades",
            "subcategory":"Construction",
            "type":"Services"
        }
    ],
    "sg:phone":"+1 281 444 2170",
    "sg:postcode":"77069",
    "sg:province":"TX",
    "wof:name":"Jf Marks & Associates",
    "wof:placetype":"venue"
},
  "geometry": {"coordinates":[-95.50976300000001,29.988418],"type":"Point"}
}