{
  "type": "Feature",
  "properties": {
    "iso:country":"US",
    "sg:address":"212 E 1st Ave",
    "sg:city":"Corsicana",
    "sg:classifiers":[
        {
            "category":"Social Services",
            "type":"Services"
        }
    ],
    "sg:phone":"+1 903 874 7131",
    "sg:postcode":"75110",
    "sg:province":"TX",
    "sg:tags":[
        "organization",
        "welfare"
    ],
    "wof:name":"Salvation Army",
    "wof:placetype":"venue"
},
  "geometry": {"coordinates":[-96.465771,32.098653],"type":"Point"}
}