{
  "type": "Feature",
  "properties": {
    "iso:country":"US",
    "sg:address":"11494 Luna Rd",
    "sg:city":"Dallas",
    "sg:classifiers":[
        {
            "category":"Banks & Credit Unions",
            "subcategory":"Financial Services",
            "type":"Services"
        }
    ],
    "sg:phone":"+1 972 432 8755",
    "sg:postcode":"75234",
    "sg:province":"TX",
    "sg:tags":[
        "company",
        "holding"
    ],
    "wof:name":"Alamo Holding Company",
    "wof:placetype":"venue"
},
  "geometry": {"coordinates":[-96.918632,32.896676],"type":"Point"}
}