{
  "type": "Feature",
  "properties": {
    "iso:country":"US",
    "sg:address":"2006 E Griffin Pkwy",
    "sg:city":"Mission",
    "sg:classifiers":[
        {
            "category":"Food & Beverages",
            "subcategory":"Specialty",
            "type":"Retail Goods"
        }
    ],
    "sg:phone":"+1 956 581 1917",
    "sg:postcode":"78572",
    "sg:province":"TX",
    "sg:tags":[
        "product",
        "health",
        "diet"
    ],
    "wof:name":"Naturalife",
    "wof:placetype":"venue"
},
  "geometry": {"coordinates":[-98.291428,26.225245],"type":"Point"}
}