{
  "type": "Feature",
  "properties": {
    "iso:country":"US",
    "sg:address":"202 US Hwy 59",
    "sg:city":"Queen City",
    "sg:classifiers":[
        {
            "category":"Autos & Motor Vehicles",
            "subcategory":"Automobile Sales",
            "type":"Retail Goods"
        }
    ],
    "sg:phone":"+1 903 796 6191",
    "sg:postcode":"75572",
    "sg:province":"TX",
    "sg:tags":[
        "car",
        "dealer"
    ],
    "wof:name":"Robert Ramsey Motors",
    "wof:placetype":"venue"
},
  "geometry": {"coordinates":[-94.159949,33.143297],"type":"Point"}
}