{
  "type": "Feature",
  "properties": {
    "iso:country":"US",
    "sg:address":"5595 College St",
    "sg:city":"Beaumont",
    "sg:classifiers":[
        {
            "category":"Banks & Credit Unions",
            "subcategory":"Bank",
            "type":"Services"
        }
    ],
    "sg:phone":"+1 409 840 5920",
    "sg:postcode":"77707",
    "sg:province":"TX",
    "sg:tags":[
        "depository",
        "banking"
    ],
    "wof:name":"Mr Payroll",
    "wof:placetype":"venue"
},
  "geometry": {"coordinates":[-94.15330299999999,30.067832],"type":"Point"}
}