{
  "type": "Feature",
  "properties": {
    "iso:country":"US",
    "sg:address":"10930 Switzer Ave",
    "sg:city":"Dallas",
    "sg:classifiers":[
        {
            "category":"Retail",
            "subcategory":"Repair Shop",
            "type":"Services"
        }
    ],
    "sg:phone":"+1 214 503 6700",
    "sg:postcode":"75238",
    "sg:province":"TX",
    "sg:tags":[
        "equipment",
        "telephone",
        "system"
    ],
    "wof:name":"Direct Voice Technologies",
    "wof:placetype":"venue"
},
  "geometry": {"coordinates":[-96.704487,32.896869],"type":"Point"}
}