{
  "type": "Feature",
  "properties": {
    "iso:country":"US",
    "sg:address":"5322 Addicks Satsuma Rd",
    "sg:city":"Houston",
    "sg:classifiers":[
        {
            "category":"Manufacturing",
            "subcategory":"Tools & Machinery",
            "type":"Manufacturing & Wholesale Goods"
        }
    ],
    "sg:phone":"+1 281 550 2100",
    "sg:postcode":"77084",
    "sg:province":"TX",
    "sg:tags":[
        "field",
        "oil",
        "equipment"
    ],
    "sg:website":"www.hot-hed.com",
    "wof:name":"Hot-Hed Inc",
    "wof:placetype":"venue"
},
  "geometry": {"coordinates":[-95.639983,29.853291],"type":"Point"}
}