{
  "type": "Feature",
  "properties": {
    "iso:country":"US",
    "sg:address":"333 Elm St",
    "sg:city":"Graham",
    "sg:classifiers":[
        {
            "category":"Retail",
            "subcategory":"Auto Repair",
            "type":"Services"
        }
    ],
    "sg:phone":"+1 940 549 9476",
    "sg:postcode":"76450",
    "sg:province":"TX",
    "sg:tags":[
        "automotive"
    ],
    "wof:name":"Quick Slick Lube & Detail",
    "wof:placetype":"venue"
},
  "geometry": {"coordinates":[-98.58951999999999,33.109966],"type":"Point"}
}