{
  "type": "Feature",
  "properties": {
    "iso:country":"US",
    "sg:address":"2021 Guadalupe St",
    "sg:city":"Austin",
    "sg:classifiers":[
        {
            "category":"Professional",
            "type":"Services"
        }
    ],
    "sg:phone":"+1 512 505 1610",
    "sg:postcode":"78705",
    "sg:province":"TX",
    "wof:name":"Sudhir Prakash",
    "wof:placetype":"venue"
},
  "geometry": {"coordinates":[-97.741846,30.283557],"type":"Point"}
}