{
  "type": "Feature",
  "properties": {
    "iso:country":"US",
    "sg:address":"3333 Lee Pkwy",
    "sg:city":"Dallas",
    "sg:classifiers":[
        {
            "category":"Building & Trades",
            "subcategory":"Construction",
            "type":"Services"
        }
    ],
    "sg:phone":"+1 214 598 5100",
    "sg:postcode":"75219",
    "sg:province":"TX",
    "sg:tags":[
        "home",
        "builder"
    ],
    "wof:name":"John Cross & Co",
    "wof:placetype":"venue"
},
  "geometry": {"coordinates":[-96.804886,32.809013],"type":"Point"}
}