{
  "type": "Feature",
  "properties": {
    "iso:country":"US",
    "sg:address":"1232 Knob Hill Rd",
    "sg:city":"Azle",
    "sg:classifiers":[
        {
            "category":"Farming",
            "subcategory":"Nursery",
            "type":"Manufacturing & Wholesale Goods"
        }
    ],
    "sg:phone":"+1 817 221 5050",
    "sg:postcode":"76020",
    "sg:province":"TX",
    "sg:tags":[
        "greenhouse"
    ],
    "wof:name":"Granny's Greenhouse",
    "wof:placetype":"venue"
},
  "geometry": {"coordinates":[-97.593384,32.979458],"type":"Point"}
}