{
  "type": "Feature",
  "properties": {
    "iso:country":"US",
    "sg:address":"5858 Westheimer Rd",
    "sg:city":"Houston",
    "sg:classifiers":[
        {
            "category":"Food & Beverages",
            "subcategory":"Groceries & Convenience Stores",
            "type":"Retail Goods"
        }
    ],
    "sg:phone":"+1 713 961 7813",
    "sg:postcode":"77057",
    "sg:province":"TX",
    "sg:tags":[
        "product"
    ],
    "wof:name":"Nature's Foods & Beverages Inc",
    "wof:placetype":"venue"
},
  "geometry": {"coordinates":[-95.483436,29.737816],"type":"Point"}
}