{
  "type": "Feature",
  "properties": {
    "iso:country":"US",
    "sg:address":"1802 San Francisco Ave",
    "sg:city":"Laredo",
    "sg:classifiers":[
        {
            "category":"Organizations",
            "subcategory":"Religious Organization",
            "type":"Services"
        }
    ],
    "sg:phone":"+1 956 723 5598",
    "sg:postcode":"78040",
    "sg:province":"TX",
    "wof:name":"Guadalupe Parish",
    "wof:placetype":"venue"
},
  "geometry": {"coordinates":[-99.500637,27.516102],"type":"Point"}
}