{
  "type": "Feature",
  "properties": {
    "iso:country":"US",
    "sg:address":"2202 N Timberland Dr",
    "sg:city":"Lufkin",
    "sg:classifiers":[
        {
            "category":"Home & Garden",
            "subcategory":"Garden Supply",
            "type":"Retail Goods"
        }
    ],
    "sg:phone":"+1 936 639 2277",
    "sg:postcode":"75901",
    "sg:province":"TX",
    "sg:tags":[
        "nurseryman"
    ],
    "wof:name":"Timberland Nursery",
    "wof:placetype":"venue"
},
  "geometry": {"coordinates":[-94.714392,31.362473],"type":"Point"}
}