{
  "type": "Feature",
  "properties": {
    "iso:country":"US",
    "sg:address":"3210 Broadway St",
    "sg:city":"San Antonio",
    "sg:classifiers":[
        {
            "category":"Restaurant",
            "type":"Food & Drink"
        }
    ],
    "sg:menulink":"http://www.allmenus.com/tx/san-antonio/14858-tomatillos/menu/",
    "sg:phone":"+1 210 824 3005",
    "sg:postcode":"78209",
    "sg:province":"TX",
    "sg:tags":[
        "mexican"
    ],
    "wof:name":"Tomatillos",
    "wof:placetype":"venue"
},
  "geometry": {"coordinates":[-98.470192,29.456175],"type":"Point"}
}