{
  "type": "Feature",
  "properties": {
    "iso:country":"US",
    "sg:address":"1115 E Central Texas Expy",
    "sg:city":"Killeen",
    "sg:classifiers":[
        {
            "category":"Real Estate",
            "subcategory":"Real Estate Services",
            "type":"Services"
        },
        {
            "category":"Real Estate",
            "subcategory":"Real Estate Agent",
            "type":"Services"
        }
    ],
    "sg:phone":"+1 877 594 4160",
    "sg:postcode":"76541",
    "sg:province":"TX",
    "sg:tags":[
        "management"
    ],
    "sg:website":"http://www.townsquareproperty.com",
    "wof:name":"Town Square Property Management & Sales Inc",
    "wof:placetype":"venue"
},
  "geometry": {"coordinates":[-97.729894,31.094594],"type":"Point"}
}