{
  "type": "Feature",
  "properties": {
    "iso:country":"US",
    "sg:address":"1902 Lakewinds Dr",
    "sg:city":"Missouri City",
    "sg:classifiers":[
        {
            "category":"Banks & Credit Unions",
            "subcategory":"Financial Services",
            "type":"Services"
        }
    ],
    "sg:phone":"+1 281 261 7605",
    "sg:postcode":"77459",
    "sg:province":"TX",
    "sg:tags":[
        "investor"
    ],
    "wof:name":"C Buitrago & Associates Inc",
    "wof:placetype":"venue"
},
  "geometry": {"coordinates":[-95.567471,29.593004],"type":"Point"}
}