{
  "type": "Feature",
  "properties": {
    "iso:country":"US",
    "sg:address":"7410 Frint Rd",
    "sg:city":"Beaumont",
    "sg:classifiers":[
        {
            "category":"Restaurant",
            "type":"Food & Drink"
        }
    ],
    "sg:phone":"+1 409 842 6926",
    "sg:postcode":"77705",
    "sg:province":"TX",
    "sg:tags":[
        "beverage"
    ],
    "wof:name":"Seven-Up Bottling Co",
    "wof:placetype":"venue"
},
  "geometry": {"coordinates":[-94.17533,30.002212],"type":"Point"}
}