{
  "type": "Feature",
  "properties": {
    "iso:country":"US",
    "sg:address":"223 Brockman St",
    "sg:city":"Pasadena",
    "sg:classifiers":[
        {
            "category":"Manufacturing",
            "subcategory":"Petroleum Products",
            "type":"Manufacturing & Wholesale Goods"
        }
    ],
    "sg:phone":"+1 713 472 5081",
    "sg:postcode":"77506",
    "sg:province":"TX",
    "sg:tags":[
        "water",
        "lubricant",
        "based",
        "hydraulic",
        "mfg"
    ],
    "wof:name":"Macdermid-Canning Ltd",
    "wof:placetype":"venue"
},
  "geometry": {"coordinates":[-95.21694100000001,29.716043],"type":"Point"}
}