{
  "type": "Feature",
  "properties": {
    "iso:country":"US",
    "sg:address":"122 W John Carpenter Fwy",
    "sg:city":"Irving",
    "sg:classifiers":[
        {
            "category":"Communications",
            "subcategory":"Newspaper",
            "type":"Services"
        }
    ],
    "sg:phone":"+1 972 717 6379",
    "sg:postcode":"75039",
    "sg:province":"TX",
    "sg:tags":[
        "print",
        "medium"
    ],
    "wof:name":"Autotrader Com",
    "wof:placetype":"venue"
},
  "geometry": {"coordinates":[-96.945099,32.8685],"type":"Point"}
}