{
  "type": "Feature",
  "properties": {
    "iso:country":"US",
    "sg:address":"2741 Stoneridge Dr",
    "sg:city":"Garland",
    "sg:classifiers":[
        {
            "category":"Shopping",
            "subcategory":"Used Merchandise",
            "type":"Retail Goods"
        }
    ],
    "sg:phone":"+1 972 495 2584",
    "sg:postcode":"75044",
    "sg:province":"TX",
    "wof:name":"Morton JD & Assoc",
    "wof:placetype":"venue"
},
  "geometry": {"coordinates":[-96.669265,32.941553],"type":"Point"}
}