{
  "type": "Feature",
  "properties": {
    "iso:country":"US",
    "sg:address":"6520 C F Hawn Fwy",
    "sg:city":"Dallas",
    "sg:classifiers":[
        {
            "category":"Autos & Motor Vehicles",
            "subcategory":"Automobile Sales",
            "type":"Retail Goods"
        }
    ],
    "sg:phone":"+1 214 391 9852",
    "sg:postcode":"75217",
    "sg:province":"TX",
    "sg:tags":[
        "car",
        "dealer"
    ],
    "wof:name":"Stephen's Auto Sales",
    "wof:placetype":"venue"
},
  "geometry": {"coordinates":[-96.71109199999999,32.731331],"type":"Point"}
}