{
  "type": "Feature",
  "properties": {
    "iso:country":"US",
    "sg:address":"117 S Reed St",
    "sg:city":"Pleasanton",
    "sg:classifiers":[
        {
            "category":"Retail",
            "subcategory":"Repair Shop",
            "type":"Services"
        }
    ],
    "sg:phone":"+1 830 281 3348",
    "sg:postcode":"78064",
    "sg:province":"TX",
    "sg:tags":[
        "welding"
    ],
    "wof:name":"E&H Welding Service",
    "wof:placetype":"venue"
},
  "geometry": {"coordinates":[-98.48635400000001,28.958792],"type":"Point"}
}