{
  "type": "Feature",
  "properties": {
    "iso:country":"US",
    "sg:address":"109 E Main St",
    "sg:city":"Clute",
    "sg:classifiers":[
        {
            "category":"Utilities",
            "subcategory":"Cable",
            "type":"Services"
        }
    ],
    "sg:phone":"+1 979 265 0985",
    "sg:postcode":"77531",
    "sg:province":"TX",
    "sg:tags":[
        "television"
    ],
    "wof:name":"Time Warner",
    "wof:placetype":"venue"
},
  "geometry": {"coordinates":[-95.403218,29.02177],"type":"Point"}
}