{
  "type": "Feature",
  "properties": {
    "iso:country":"US",
    "sg:address":"2305 Ridge Rd",
    "sg:city":"Rockwall",
    "sg:classifiers":[
        {
            "category":"Health Services",
            "subcategory":"Health Practitioner",
            "type":"Services"
        }
    ],
    "sg:phone":"+1 469 698 0025",
    "sg:postcode":"75032",
    "sg:province":"TX",
    "wof:name":"Laurel E Tate",
    "wof:placetype":"venue"
},
  "geometry": {"coordinates":[-96.468891,32.899072],"type":"Point"}
}