{
  "type": "Feature",
  "properties": {
    "iso:country":"US",
    "sg:address":"12000 State Hwy 123",
    "sg:city":"Seguin",
    "sg:classifiers":[
        {
            "category":"Manufacturing",
            "subcategory":"Chemicals & Compounds",
            "type":"Manufacturing & Wholesale Goods"
        }
    ],
    "sg:phone":"+1 830 386 0707",
    "sg:postcode":"78155",
    "sg:province":"TX",
    "sg:tags":[
        "preparation",
        "mfg"
    ],
    "wof:name":"Mr W Fireworks Stand",
    "wof:placetype":"venue"
},
  "geometry": {"coordinates":[-97.959019,29.524553],"type":"Point"}
}