{
  "type": "Feature",
  "properties": {
    "iso:country":"US",
    "sg:address":"51 Saddle Rock Ridge St",
    "sg:city":"Wimberley",
    "sg:classifiers":[
        {
            "category":"Professional",
            "subcategory":"Business Services",
            "type":"Services"
        }
    ],
    "sg:phone":"+1 512 847 1242",
    "sg:postcode":"78676",
    "sg:province":"TX",
    "wof:name":"Fairharts Design Company",
    "wof:placetype":"venue"
},
  "geometry": {"coordinates":[-98.132368,30.027989],"type":"Point"}
}