{
  "type": "Feature",
  "properties": {
    "iso:country":"US",
    "sg:address":"1003 Merribrook Ln",
    "sg:city":"Allen",
    "sg:classifiers":[
        {
            "category":"Building & Trades",
            "subcategory":"Equipment Rental",
            "type":"Services"
        },
        {
            "category":"Shopping",
            "subcategory":"Computers & Home Electronics",
            "type":"Retail Goods"
        }
    ],
    "sg:phone":"+1 972 727 8989",
    "sg:postcode":"75002",
    "sg:province":"TX",
    "sg:tags":[
        "stereo",
        "leasing",
        "video",
        "audio",
        "equipment-renting",
        "audio-visual"
    ],
    "wof:name":"Moonlighting Nannies",
    "wof:placetype":"venue"
},
  "geometry": {"coordinates":[-96.645337,33.105618],"type":"Point"}
}