{
  "type": "Feature",
  "properties": {
    "iso:country":"US",
    "sg:address":"8767 Oak Stream St",
    "sg:city":"Dallas",
    "sg:classifiers":[
        {
            "category":"Building & Trades",
            "subcategory":"Construction",
            "type":"Services"
        }
    ],
    "sg:phone":"+1 214 553 7974",
    "sg:postcode":"75243",
    "sg:province":"TX",
    "sg:tags":[
        "home",
        "builder"
    ],
    "wof:name":"Hampton Homes",
    "wof:placetype":"venue"
},
  "geometry": {"coordinates":[-96.72224900000001,32.896821],"type":"Point"}
}