{
  "type": "Feature",
  "properties": {
    "iso:country":"US",
    "sg:address":"504 Lakeside Ln",
    "sg:city":"Friendswood",
    "sg:classifiers":[
        {
            "category":"Building & Trades",
            "subcategory":"Pest Control",
            "type":"Services"
        }
    ],
    "sg:phone":"+1 281 992 5607",
    "sg:postcode":"77546",
    "sg:province":"TX",
    "wof:name":"Envirochem Services Inc",
    "wof:placetype":"venue"
},
  "geometry": {"coordinates":[-95.186988,29.501006],"type":"Point"}
}