{
  "type": "Feature",
  "properties": {
    "iso:country":"US",
    "sg:address":"265 Cold Rd",
    "sg:city":"Evant",
    "sg:classifiers":[
        {
            "category":"Shopping",
            "subcategory":"Hobbies, Toys, & Games",
            "type":"Retail Goods"
        }
    ],
    "sg:phone":"+1 254 471 5896",
    "sg:postcode":"76525",
    "sg:province":"TX",
    "sg:tags":[
        "craft"
    ],
    "wof:name":"Miller's Wood 'N'Stuff",
    "wof:placetype":"venue"
},
  "geometry": {"coordinates":[-98.07081700000001,31.468412],"type":"Point"}
}