{
  "type": "Feature",
  "properties": {
    "iso:country":"US",
    "sg:address":"8834 N Capital of Texas Hwy",
    "sg:city":"Austin",
    "sg:classifiers":[
        {
            "category":"Professional",
            "subcategory":"Business Services",
            "type":"Services"
        },
        {
            "category":"Professional",
            "subcategory":"Management & Consulting",
            "type":"Services"
        }
    ],
    "sg:phone":"+1 512 236 9120",
    "sg:postcode":"78759",
    "sg:province":"TX",
    "sg:tags":[
        "consultant",
        "designer",
        "bank"
    ],
    "wof:name":"Coretrac Inc",
    "wof:placetype":"venue"
},
  "geometry": {"coordinates":[-97.760499,30.387971],"type":"Point"}
}