{
  "type": "Feature",
  "properties": {
    "iso:country":"US",
    "sg:address":"6133 Dick Price Rd",
    "sg:city":"Fort Worth",
    "sg:classifiers":[
        {
            "category":"Building & Trades",
            "subcategory":"Landscaping Services",
            "type":"Services"
        }
    ],
    "sg:phone":"+1 817 478 6935",
    "sg:postcode":"76140",
    "sg:province":"TX",
    "wof:name":"Gary L Jeanes Ground Maintenc",
    "wof:placetype":"venue"
},
  "geometry": {"coordinates":[-97.232462,32.607514],"type":"Point"}
}