{
  "type": "Feature",
  "properties": {
    "iso:country":"US",
    "sg:address":"750 Presidential Dr",
    "sg:city":"Richardson",
    "sg:classifiers":[
        {
            "category":"Home & Garden",
            "subcategory":"Building Materials",
            "type":"Retail Goods"
        }
    ],
    "sg:phone":"+1 972 437 5506",
    "sg:postcode":"75081",
    "sg:province":"TX",
    "sg:tags":[
        "equipment",
        "electric",
        "supply"
    ],
    "sg:website":"www.vlsip.com",
    "wof:name":"VLSIP Technologies Inc",
    "wof:placetype":"venue"
},
  "geometry": {"coordinates":[-96.70322400000001,32.956204],"type":"Point"}
}