{
  "type": "Feature",
  "properties": {
    "iso:country":"US",
    "sg:address":"220 Durango Dr",
    "sg:city":"Roanoke",
    "sg:classifiers":[
        {
            "category":"Coffee & Tea",
            "type":"Food & Drink"
        },
        {
            "category":"Restaurant",
            "type":"Food & Drink"
        }
    ],
    "sg:phone":"+1 940 453 2003",
    "sg:postcode":"76262",
    "sg:province":"TX",
    "sg:tags":[
        "shop",
        "espresso"
    ],
    "wof:name":"Coffee Mill",
    "wof:placetype":"venue"
},
  "geometry": {"coordinates":[-97.207123,33.00555],"type":"Point"}
}