{
  "type": "Feature",
  "properties": {
    "iso:country":"US",
    "sg:address":"650 Pilgrim Dr",
    "sg:city":"San Antonio",
    "sg:classifiers":[
        {
            "category":"Professional",
            "type":"Services"
        }
    ],
    "sg:phone":"+1 210 340 6362",
    "sg:postcode":"78213",
    "sg:province":"TX",
    "wof:name":"R & R Contract Services",
    "wof:placetype":"venue"
},
  "geometry": {"coordinates":[-98.542529,29.504495],"type":"Point"}
}