{
  "type": "Feature",
  "properties": {
    "iso:country":"US",
    "sg:address":"2575 S Dairy Ashford St",
    "sg:city":"Houston",
    "sg:classifiers":[
        {
            "category":"Home & Garden",
            "subcategory":"Carpets & Floor Coverings",
            "type":"Retail Goods"
        }
    ],
    "sg:phone":"+1 713 558 0695",
    "sg:postcode":"77077",
    "sg:province":"TX",
    "sg:tags":[
        "dealer",
        "rug"
    ],
    "wof:name":"L J Carpet Of Texas",
    "wof:placetype":"venue"
},
  "geometry": {"coordinates":[-95.605779,29.736569],"type":"Point"}
}