{
  "type": "Feature",
  "properties": {
    "iso:country":"US",
    "sg:address":"1500 Old Spanish Trl",
    "sg:city":"Houston",
    "sg:classifiers":[
        {
            "category":"Organizations",
            "subcategory":"Professional Association",
            "type":"Services"
        }
    ],
    "sg:phone":"+1 713 245 3824",
    "sg:postcode":"77054",
    "sg:province":"TX",
    "sg:tags":[
        "business"
    ],
    "wof:name":"Kalido Inc",
    "wof:placetype":"venue"
},
  "geometry": {"coordinates":[-95.404766,29.694827],"type":"Point"}
}