{
  "type": "Feature",
  "properties": {
    "iso:country":"US",
    "sg:address":"7503 Kite Hill Dr",
    "sg:city":"Houston",
    "sg:classifiers":[
        {
            "category":"Real Estate",
            "subcategory":"Real Estate Agent",
            "type":"Services"
        }
    ],
    "sg:phone":"+1 713 937 9667",
    "sg:postcode":"77041",
    "sg:province":"TX",
    "sg:website":"www.americanarealty.com",
    "wof:name":"Americana Realty",
    "wof:placetype":"venue"
},
  "geometry": {"coordinates":[-95.61666700000001,29.889334],"type":"Point"}
}