{
  "type": "Feature",
  "properties": {
    "iso:country":"US",
    "sg:address":"10045 Audelia Rd",
    "sg:city":"Dallas",
    "sg:classifiers":[
        {
            "category":"Building & Trades",
            "subcategory":"Construction",
            "type":"Services"
        }
    ],
    "sg:phone":"+1 214 348 3307",
    "sg:postcode":"75238",
    "sg:province":"TX",
    "sg:tags":[
        "contractor"
    ],
    "wof:name":"Harrison Quality Construction",
    "wof:placetype":"venue"
},
  "geometry": {"coordinates":[-96.718012,32.885916],"type":"Point"}
}