{
  "type": "Feature",
  "properties": {
    "iso:country":"US",
    "sg:address":"309 N Galloway Ave",
    "sg:city":"Mesquite",
    "sg:classifiers":[
        {
            "category":"Professional",
            "subcategory":"Accounting & Tax Preparation",
            "type":"Services"
        }
    ],
    "sg:phone":"+1 972 216 9079",
    "sg:postcode":"75149",
    "sg:province":"TX",
    "sg:tags":[
        "billing"
    ],
    "wof:name":"Physicians Billing Solution",
    "wof:placetype":"venue"
},
  "geometry": {"coordinates":[-96.599169,32.769722],"type":"Point"}
}