{
  "type": "Feature",
  "properties": {
    "iso:country":"US",
    "sg:address":"104 S Oak St",
    "sg:city":"Tomball",
    "sg:classifiers":[
        {
            "category":"Autos & Motor Vehicles",
            "subcategory":"Auto Supplies",
            "type":"Retail Goods"
        }
    ],
    "sg:phone":"+1 281 516 9932",
    "sg:postcode":"77375",
    "sg:province":"TX",
    "sg:tags":[
        "tire"
    ],
    "wof:name":"Auto Tire Express",
    "wof:placetype":"venue"
},
  "geometry": {"coordinates":[-95.61699400000001,30.09673],"type":"Point"}
}