{
  "type": "Feature",
  "properties": {
    "iso:country":"US",
    "sg:address":"2418 Arbuckle Ct",
    "sg:city":"Dallas",
    "sg:classifiers":[
        {
            "category":"Professional",
            "type":"Services"
        }
    ],
    "sg:phone":"+1 972 241 1401",
    "sg:postcode":"75229",
    "sg:province":"TX",
    "wof:name":"EPMG",
    "wof:placetype":"venue"
},
  "geometry": {"coordinates":[-96.894645,32.884984],"type":"Point"}
}