{
  "type": "Feature",
  "properties": {
    "iso:country":"US",
    "sg:address":"309 W Main Ave",
    "sg:city":"Round Rock",
    "sg:classifiers":[
        {
            "category":"Professional",
            "subcategory":"Lawyer & Legal Services",
            "type":"Services"
        }
    ],
    "sg:phone":"+1 512 828 0529",
    "sg:postcode":"78664",
    "sg:province":"TX",
    "wof:name":"Wendi Lester Attorney",
    "wof:placetype":"venue"
},
  "geometry": {"coordinates":[-97.680976,30.507881],"type":"Point"}
}