{
  "type": "Feature",
  "properties": {
    "iso:country":"US",
    "sg:address":"490 High Grove Rd",
    "sg:city":"Cedar Creek",
    "sg:classifiers":[
        {
            "category":"Professional",
            "subcategory":"Computer Services",
            "type":"Services"
        }
    ],
    "sg:phone":"+1 512 303 1291",
    "sg:postcode":"78612",
    "sg:province":"TX",
    "sg:tags":[
        "related"
    ],
    "wof:name":"Database Systems Inc",
    "wof:placetype":"venue"
},
  "geometry": {"coordinates":[-97.507133,29.999014],"type":"Point"}
}