{
  "type": "Feature",
  "properties": {
    "iso:country":"US",
    "sg:address":"7525 Wynlea St",
    "sg:city":"Houston",
    "sg:classifiers":[
        {
            "category":"Wholesale",
            "subcategory":"Construction Materials",
            "type":"Manufacturing & Wholesale Goods"
        }
    ],
    "sg:phone":"+1 713 644 6815",
    "sg:postcode":"77061",
    "sg:province":"TX",
    "sg:tags":[
        "insulation"
    ],
    "wof:name":"Forrest Mfg Co",
    "wof:placetype":"venue"
},
  "geometry": {"coordinates":[-95.28674100000001,29.659514],"type":"Point"}
}