{
  "type": "Feature",
  "properties": {
    "iso:country":"US",
    "sg:address":"3524 Grand Mesa Dr",
    "sg:city":"Plano",
    "sg:classifiers":[
        {
            "category":"Education",
            "subcategory":"Special Training",
            "type":"Public Place"
        }
    ],
    "sg:phone":"+1 972 208 0137",
    "sg:postcode":"75025",
    "sg:province":"TX",
    "wof:name":"Bravebiz Arts & Crafts",
    "wof:placetype":"venue"
},
  "geometry": {"coordinates":[-96.761777,33.081906],"type":"Point"}
}