{
  "type": "Feature",
  "properties": {
    "iso:country":"US",
    "sg:address":"11918 Troulon Dr",
    "sg:city":"Houston",
    "sg:classifiers":[
        {
            "category":"Social Services",
            "subcategory":"Child Care",
            "type":"Services"
        }
    ],
    "sg:phone":"+1 281 933 2595",
    "sg:postcode":"77072",
    "sg:province":"TX",
    "wof:name":"Shirley Ann Grant",
    "wof:placetype":"venue"
},
  "geometry": {"coordinates":[-95.591116,29.688063],"type":"Point"}
}