{
  "type": "Feature",
  "properties": {
    "iso:country":"US",
    "sg:address":"506 N Main St",
    "sg:city":"Belton",
    "sg:classifiers":[
        {
            "category":"Organizations",
            "subcategory":"Religious Organization",
            "type":"Services"
        }
    ],
    "sg:phone":"+1 254 939 0705",
    "sg:postcode":"76513",
    "sg:province":"TX",
    "sg:tags":[
        "church"
    ],
    "sg:website":"www.fbcbelton.org",
    "wof:name":"First Baptist Church Of Belton",
    "wof:placetype":"venue"
},
  "geometry": {"coordinates":[-97.46177,31.061802],"type":"Point"}
}