{
  "type": "Feature",
  "properties": {
    "iso:country":"US",
    "sg:address":"8811 Falcon View Dr",
    "sg:city":"Mc Kinney",
    "sg:classifiers":[
        {
            "category":"Building & Trades",
            "subcategory":"Construction",
            "type":"Services"
        }
    ],
    "sg:phone":"+1 972 529 6391",
    "sg:postcode":"75070",
    "sg:province":"TX",
    "sg:tags":[
        "woodworker"
    ],
    "wof:name":"JHK Woodcraft",
    "wof:placetype":"venue"
},
  "geometry": {"coordinates":[-96.72973,33.199824],"type":"Point"}
}