{
  "type": "Feature",
  "properties": {
    "iso:country":"US",
    "sg:address":"1200 Hospital Dr",
    "sg:city":"Angleton",
    "sg:classifiers":[
        {
            "category":"Real Estate",
            "subcategory":"Real Estate Operator",
            "type":"Services"
        }
    ],
    "sg:phone":"+1 979 848 2750",
    "sg:postcode":"77515",
    "sg:province":"TX",
    "sg:tags":[
        "building",
        "apartment"
    ],
    "wof:name":"Towne Square Apartments",
    "wof:placetype":"venue"
},
  "geometry": {"coordinates":[-95.41918699999999,29.184925],"type":"Point"}
}