{
  "type": "Feature",
  "properties": {
    "iso:country":"US",
    "sg:address":"1701 Crown Dr",
    "sg:city":"Austin",
    "sg:classifiers":[
        {
            "category":"Manufacturing",
            "subcategory":"Furniture",
            "type":"Manufacturing & Wholesale Goods"
        }
    ],
    "sg:phone":"+1 512 447 8321",
    "sg:postcode":"78745",
    "sg:province":"TX",
    "sg:tags":[
        "household",
        "wood",
        "mfg"
    ],
    "wof:name":"Kermit Otto Vorpahl",
    "wof:placetype":"venue"
},
  "geometry": {"coordinates":[-97.788096,30.225403],"type":"Point"}
}