{
  "type": "Feature",
  "properties": {
    "iso:country":"US",
    "sg:address":"1799 Woodland Hills Dr",
    "sg:city":"Humble",
    "sg:classifiers":[
        {
            "category":"Organizations",
            "subcategory":"Community Association",
            "type":"Services"
        }
    ],
    "sg:phone":"+1 281 358 2137",
    "sg:postcode":"77339",
    "sg:province":"TX",
    "wof:name":"Troop 1377 Boy Scouts of",
    "wof:placetype":"venue"
},
  "geometry": {"coordinates":[-95.21892099999999,30.04043],"type":"Point"}
}