{
  "type": "Feature",
  "properties": {
    "iso:country":"US",
    "sg:address":"5521 Greenville Ave",
    "sg:city":"Dallas",
    "sg:classifiers":[
        {
            "category":"Home & Garden",
            "subcategory":"Building Materials",
            "type":"Retail Goods"
        }
    ],
    "sg:phone":"+1 214 948 8334",
    "sg:postcode":"75206",
    "sg:province":"TX",
    "wof:name":"Stain Tech LLP",
    "wof:placetype":"venue"
},
  "geometry": {"coordinates":[-96.769924,32.851295],"type":"Point"}
}