{
  "type": "Feature",
  "properties": {
    "iso:country":"US",
    "sg:address":"1734 Woodard St",
    "sg:city":"Abilene",
    "sg:classifiers":[
        {
            "category":"Building & Trades",
            "subcategory":"Electrical",
            "type":"Services"
        }
    ],
    "sg:phone":"+1 325 692 0524",
    "sg:postcode":"79605",
    "sg:province":"TX",
    "sg:tags":[
        "electrical",
        "contractor"
    ],
    "wof:name":"At Your Fingertips",
    "wof:placetype":"venue"
},
  "geometry": {"coordinates":[-99.75837900000001,32.427068],"type":"Point"}
}