{
  "type": "Feature",
  "properties": {
    "iso:country":"US",
    "sg:address":"2410 Chapel Hill Ln",
    "sg:city":"Arlington",
    "sg:classifiers":[
        {
            "category":"Health Services",
            "subcategory":"Clinic",
            "type":"Services"
        }
    ],
    "sg:phone":"+1 817 801 8020",
    "sg:postcode":"76014",
    "sg:province":"TX",
    "wof:name":"Expert Medical Bill & Collec",
    "wof:placetype":"venue"
},
  "geometry": {"coordinates":[-97.110315,32.704545],"type":"Point"}
}