{
  "type": "Feature",
  "properties": {
    "iso:country":"US",
    "sg:address":"2808 State Hwy 6",
    "sg:city":"Houston",
    "sg:classifiers":[
        {
            "category":"Utilities",
            "subcategory":"Mobile Phone",
            "type":"Services"
        }
    ],
    "sg:phone":"+1 281 556 5465",
    "sg:postcode":"77082",
    "sg:province":"TX",
    "sg:tags":[
        "telephone",
        "cellular"
    ],
    "wof:name":"Cingular Wireless",
    "wof:placetype":"venue"
},
  "geometry": {"coordinates":[-95.64405600000001,29.730459],"type":"Point"}
}