{
  "type": "Feature",
  "properties": {
    "iso:country":"US",
    "sg:address":"2907 Bluegrass Ct",
    "sg:city":"Missouri City",
    "sg:classifiers":[
        {
            "category":"Restaurant",
            "type":"Food & Drink"
        }
    ],
    "sg:phone":"+1 281 403 0222",
    "sg:postcode":"77459",
    "sg:province":"TX",
    "sg:tags":[
        "eating"
    ],
    "wof:name":"Quizznos Subs",
    "wof:placetype":"venue"
},
  "geometry": {"coordinates":[-95.57455400000001,29.578978],"type":"Point"}
}