{
  "type": "Feature",
  "properties": {
    "iso:country":"US",
    "sg:address":"22727 Cascade Springs Dr",
    "sg:city":"Katy",
    "sg:classifiers":[
        {
            "category":"Insurance",
            "subcategory":"Insurance Agent",
            "type":"Services"
        }
    ],
    "sg:phone":"+1 281 693 6966",
    "sg:postcode":"77494",
    "sg:province":"TX",
    "wof:name":"Jenny Xu Insurance Agency",
    "wof:placetype":"venue"
},
  "geometry": {"coordinates":[-95.77270900000001,29.706805],"type":"Point"}
}