{
  "type": "Feature",
  "properties": {
    "iso:country":"US",
    "sg:address":"2121 S Lamar Blvd",
    "sg:city":"Austin",
    "sg:classifiers":[
        {
            "category":"Social Services",
            "subcategory":"Child Care",
            "type":"Services"
        }
    ],
    "sg:phone":"+1 512 444 8585",
    "sg:postcode":"78704",
    "sg:province":"TX",
    "sg:tags":[
        "personal",
        "assistance"
    ],
    "wof:name":"Caring Senior Service",
    "wof:placetype":"venue"
},
  "geometry": {"coordinates":[-97.769947,30.248413],"type":"Point"}
}