{
  "type": "Feature",
  "properties": {
    "iso:country":"US",
    "sg:address":"6211 Elmgrove Rd",
    "sg:city":"Spring",
    "sg:classifiers":[
        {
            "category":"Professional",
            "type":"Services"
        }
    ],
    "sg:phone":"+1 281 251 3121",
    "sg:postcode":"77389",
    "sg:province":"TX",
    "wof:name":"Sign of Jointer",
    "wof:placetype":"venue"
},
  "geometry": {"coordinates":[-95.515128,30.105673],"type":"Point"}
}