{
  "type": "Feature",
  "properties": {
    "iso:country":"US",
    "sg:address":"307 N Cuernavaca Dr Apt G",
    "sg:city":"Austin",
    "sg:classifiers":[
        {
            "category":"Travel",
            "subcategory":"Hotels & Motels",
            "type":"Entertainment"
        },
        {
            "category":"Personal",
            "type":"Services"
        }
    ],
    "sg:phone":"+1 512 476 4003",
    "sg:postcode":"78733",
    "sg:province":"TX",
    "sg:tags":[
        "assistant",
        "concierge"
    ],
    "wof:name":"Custom Tattoos From The Soul",
    "wof:placetype":"venue"
},
  "geometry": {"coordinates":[-97.871347,30.328594],"type":"Point"}
}