{
  "type": "Feature",
  "properties": {
    "iso:country":"US",
    "sg:address":"7421 Caruth Blvd",
    "sg:city":"Dallas",
    "sg:classifiers":[
        {
            "category":"Health Services",
            "subcategory":"Doctor",
            "type":"Services"
        }
    ],
    "sg:phone":"+1 214 739 0143",
    "sg:postcode":"75225",
    "sg:province":"TX",
    "wof:name":"Dibella Arnold V MD",
    "wof:placetype":"venue"
},
  "geometry": {"coordinates":[-96.779404,32.859402],"type":"Point"}
}