{
  "type": "Feature",
  "properties": {
    "iso:country":"US",
    "sg:address":"1008 Spencer Hwy",
    "sg:city":"South Houston",
    "sg:classifiers":[
        {
            "category":"Retail",
            "subcategory":"Auto Repair",
            "type":"Services"
        }
    ],
    "sg:phone":"+1 713 589 1446",
    "sg:postcode":"77587",
    "sg:province":"TX",
    "wof:name":"C V Joint Repair",
    "wof:placetype":"venue"
},
  "geometry": {"coordinates":[-95.21886000000001,29.664589],"type":"Point"}
}