{
  "type": "Feature",
  "properties": {
    "iso:country":"US",
    "sg:address":"100 Ross St",
    "sg:city":"Amarillo",
    "sg:classifiers":[
        {
            "category":"Retail",
            "subcategory":"Repair Shop",
            "type":"Services"
        }
    ],
    "sg:phone":"+1 806 372 1043",
    "sg:postcode":"79102",
    "sg:province":"TX",
    "sg:tags":[
        "welding"
    ],
    "wof:name":"Mayes Welding",
    "wof:placetype":"venue"
},
  "geometry": {"coordinates":[-101.814401,35.208784],"type":"Point"}
}