{
  "type": "Feature",
  "properties": {
    "iso:country":"US",
    "sg:address":"600 N Shore Dr",
    "sg:city":"Amarillo",
    "sg:classifiers":[
        {
            "category":"Farming",
            "subcategory":"Livestock Farm",
            "type":"Manufacturing & Wholesale Goods"
        }
    ],
    "sg:phone":"+1 806 622 3584",
    "sg:postcode":"79118",
    "sg:province":"TX",
    "sg:tags":[
        "beef",
        "feedlot",
        "cattle"
    ],
    "wof:name":"Bill Weems Inc",
    "wof:placetype":"venue"
},
  "geometry": {"coordinates":[-101.77004700000001,35.047765],"type":"Point"}
}