{
  "type": "Feature",
  "properties": {
    "iso:country":"US",
    "sg:address":"5513 Joyce Cir",
    "sg:city":"El Paso",
    "sg:classifiers":[
        {
            "category":"Shopping",
            "subcategory":"Used Merchandise",
            "type":"Retail Goods"
        }
    ],
    "sg:phone":"+1 915 566 8156",
    "sg:postcode":"79904",
    "sg:province":"TX",
    "wof:name":"Maria Del Rayo Ybarra",
    "wof:placetype":"venue"
},
  "geometry": {"coordinates":[-106.44263599999999,31.826852],"type":"Point"}
}