{
  "type": "Feature",
  "properties": {
    "iso:country":"US",
    "sg:address":"12210 Beechnut St",
    "sg:city":"Houston",
    "sg:classifiers":[
        {
            "category":"Recreation",
            "type":"Entertainment"
        }
    ],
    "sg:phone":"+1 281 988 6538",
    "sg:postcode":"77072",
    "sg:province":"TX",
    "wof:name":"Fernandos Karate School",
    "wof:placetype":"venue"
},
  "geometry": {"coordinates":[-95.595842,29.689164],"type":"Point"}
}