{
  "type": "Feature",
  "properties": {
    "iso:country":"US",
    "sg:address":"9202 Shadow Lawn Cir",
    "sg:city":"Converse",
    "sg:classifiers":[
        {
            "category":"Professional",
            "type":"Services"
        }
    ],
    "sg:phone":"+1 210 566 0060",
    "sg:postcode":"78109",
    "sg:province":"TX",
    "wof:name":"First Hastings",
    "wof:placetype":"venue"
},
  "geometry": {"coordinates":[-98.30330499999999,29.516282],"type":"Point"}
}