{
  "type": "Feature",
  "properties": {
    "iso:country":"US",
    "sg:address":"615 Irvine St",
    "sg:city":"Yoakum",
    "sg:classifiers":[
        {
            "category":"Manufacturing",
            "subcategory":"Printing",
            "type":"Manufacturing & Wholesale Goods"
        }
    ],
    "sg:phone":"+1 361 293 6644",
    "sg:postcode":"77995",
    "sg:province":"TX",
    "sg:tags":[
        "commercial"
    ],
    "wof:name":"Specialty Printers",
    "wof:placetype":"venue"
},
  "geometry": {"coordinates":[-97.15207700000001,29.288697],"type":"Point"}
}