{
  "type": "Feature",
  "properties": {
    "iso:country":"US",
    "sg:address":"704 E Main St",
    "sg:city":"Alice",
    "sg:classifiers":[
        {
            "category":"Building & Trades",
            "subcategory":"Electrical",
            "type":"Services"
        }
    ],
    "sg:phone":"+1 361 664 7509",
    "sg:postcode":"78332",
    "sg:province":"TX",
    "sg:tags":[
        "contracting",
        "electrical"
    ],
    "wof:name":"A & A Electrical Consultants",
    "wof:placetype":"venue"
},
  "geometry": {"coordinates":[-98.068916,27.750093],"type":"Point"}
}