{
  "type": "Feature",
  "properties": {
    "iso:country":"US",
    "sg:address":"121 N 7th St",
    "sg:city":"Brownfield",
    "sg:classifiers":[
        {
            "category":"Utilities",
            "subcategory":"Electric",
            "type":"Services"
        }
    ],
    "sg:phone":"+1 806 637 4547",
    "sg:postcode":"79316",
    "sg:province":"TX",
    "sg:tags":[
        "company"
    ],
    "wof:name":"Municipal Power & Light",
    "wof:placetype":"venue"
},
  "geometry": {"coordinates":[-102.282624,33.179987],"type":"Point"}
}