{
  "type": "Feature",
  "properties": {
    "iso:country":"US",
    "sg:address":"101 N Texas Blvd",
    "sg:city":"Alice",
    "sg:classifiers":[
        {
            "category":"Wholesale",
            "subcategory":"Office Equipment",
            "type":"Manufacturing & Wholesale Goods"
        }
    ],
    "sg:phone":"+1 361 668 0888",
    "sg:postcode":"78332",
    "sg:province":"TX",
    "sg:tags":[
        "machine",
        "duplicating",
        "copying"
    ],
    "wof:name":"South Texas Sales",
    "wof:placetype":"venue"
},
  "geometry": {"coordinates":[-98.06472599999999,27.751185],"type":"Point"}
}