{
  "type": "Feature",
  "properties": {
    "iso:country":"US",
    "sg:address":"7124 Bending Oak Rd",
    "sg:city":"Austin",
    "sg:classifiers":[
        {
            "category":"Professional",
            "type":"Services"
        }
    ],
    "sg:phone":"+1 512 288 1477",
    "sg:postcode":"78749",
    "sg:province":"TX",
    "wof:name":"Woods of Legend Oaks Soci",
    "wof:placetype":"venue"
},
  "geometry": {"coordinates":[-97.86914400000001,30.229847],"type":"Point"}
}