{
  "type": "Feature",
  "properties": {
    "iso:country":"US",
    "sg:address":"4416 Granite Shoals",
    "sg:city":"San Antonio",
    "sg:classifiers":[
        {
            "category":"Building & Trades",
            "subcategory":"Construction",
            "type":"Services"
        }
    ],
    "sg:phone":"+1 210 488 4408",
    "sg:postcode":"78244",
    "sg:province":"TX",
    "sg:tags":[
        "home",
        "land",
        "develop"
    ],
    "wof:name":"Butterfield Group LLC",
    "wof:placetype":"venue"
},
  "geometry": {"coordinates":[-98.344932,29.469714],"type":"Point"}
}