{
  "type": "Feature",
  "properties": {
    "iso:country":"US",
    "sg:address":"9220 Pinehaven Dr",
    "sg:city":"Dallas",
    "sg:classifiers":[
        {
            "category":"Building & Trades",
            "subcategory":"Construction",
            "type":"Services"
        }
    ],
    "sg:phone":"+1 972 288 4354",
    "sg:postcode":"75227",
    "sg:province":"TX",
    "sg:tags":[
        "repairing",
        "remodeling",
        "contractor"
    ],
    "wof:name":"All In One Home Repair",
    "wof:placetype":"venue"
},
  "geometry": {"coordinates":[-96.663498,32.770947],"type":"Point"}
}