{
  "type": "Feature",
  "properties": {
    "iso:country":"US",
    "sg:address":"1104 N State Line Ave",
    "sg:city":"Texarkana",
    "sg:classifiers":[
        {
            "category":"Home & Garden",
            "subcategory":"Furniture",
            "type":"Retail Goods"
        }
    ],
    "sg:phone":"+1 870 772 8434",
    "sg:postcode":"71854",
    "sg:province":"TX",
    "sg:tags":[
        "used",
        "merchandise"
    ],
    "wof:name":"State Line Antique Mall",
    "wof:placetype":"venue"
},
  "geometry": {"coordinates":[-94.043038,33.433958],"type":"Point"}
}