{
  "type": "Feature",
  "properties": {
    "iso:country":"US",
    "sg:address":"1808 Waterwood Dr",
    "sg:city":"Prosper",
    "sg:classifiers":[
        {
            "category":"Building & Trades",
            "subcategory":"Construction",
            "type":"Services"
        }
    ],
    "sg:phone":"+1 972 346 3176",
    "sg:postcode":"75078",
    "sg:province":"TX",
    "sg:tags":[
        "home",
        "builder"
    ],
    "wof:name":"Trinity Homes",
    "wof:placetype":"venue"
},
  "geometry": {"coordinates":[-96.78170299999999,33.238276],"type":"Point"}
}