{
  "type": "Feature",
  "properties": {
    "iso:country":"US",
    "sg:address":"1341 W Mockingbird Ln",
    "sg:city":"Dallas",
    "sg:classifiers":[
        {
            "category":"Health Services",
            "subcategory":"Health Practitioner",
            "type":"Services"
        }
    ],
    "sg:phone":"+1 214 520 8770",
    "sg:postcode":"75247",
    "sg:province":"TX",
    "sg:tags":[
        "nurse",
        "registry"
    ],
    "wof:name":"Nursefinders Of Dallas",
    "wof:placetype":"venue"
},
  "geometry": {"coordinates":[-96.86484900000001,32.821907],"type":"Point"}
}