{
  "type": "Feature",
  "properties": {
    "iso:country":"US",
    "sg:address":"415 US Hwy 69",
    "sg:city":"Huntington",
    "sg:classifiers":[
        {
            "category":"Real Estate",
            "subcategory":"Real Estate Operator",
            "type":"Services"
        }
    ],
    "sg:phone":"+1 936 876 4711",
    "sg:postcode":"75949",
    "sg:province":"TX",
    "sg:tags":[
        "apartment"
    ],
    "wof:name":"First Huntington Arms",
    "wof:placetype":"venue"
},
  "geometry": {"coordinates":[-94.58842,31.282882],"type":"Point"}
}