{
  "type": "Feature",
  "properties": {
    "iso:country":"US",
    "sg:address":"1033 W Shady Grove Rd",
    "sg:city":"Irving",
    "sg:classifiers":[
        {
            "category":"Food & Beverages",
            "subcategory":"Groceries & Convenience Stores",
            "type":"Retail Goods"
        }
    ],
    "sg:phone":"+1 972 254 0168",
    "sg:postcode":"75060",
    "sg:province":"TX",
    "wof:name":"Kroger Food Stores",
    "wof:placetype":"venue"
},
  "geometry": {"coordinates":[-96.95866599999999,32.801232],"type":"Point"}
}