{
  "type": "Feature",
  "properties": {
    "iso:country":"US",
    "sg:address":"1515 W 9th St",
    "sg:city":"Littlefield",
    "sg:classifiers":[
        {
            "category":"Shopping",
            "subcategory":"Gifts & Souvenirs",
            "type":"Retail Goods"
        }
    ],
    "sg:phone":"+1 806 385 3167",
    "sg:postcode":"79339",
    "sg:province":"TX",
    "wof:name":"Rosebud Gifts",
    "wof:placetype":"venue"
},
  "geometry": {"coordinates":[-102.346869,33.917899],"type":"Point"}
}