{
  "type": "Feature",
  "properties": {
    "iso:country":"US",
    "sg:address":"19002 Dallas Pkwy Ofc",
    "sg:city":"Dallas",
    "sg:classifiers":[
        {
            "category":"Real Estate",
            "subcategory":"Real Estate Operator",
            "type":"Services"
        }
    ],
    "sg:phone":"+1 972 930 1500",
    "sg:postcode":"75287",
    "sg:province":"TX",
    "sg:tags":[
        "apartment"
    ],
    "wof:name":"Madison On the Parkway",
    "wof:placetype":"venue"
},
  "geometry": {"coordinates":[-96.828796,33.008202],"type":"Point"}
}