{
  "type": "Feature",
  "properties": {
    "iso:country":"US",
    "sg:address":"1911 N Austin Ave Ste 404",
    "sg:city":"Georgetown",
    "sg:classifiers":[
        {
            "category":"Professional",
            "subcategory":"Detective & Security Services",
            "type":"Services"
        },
        {
            "category":"Wholesale",
            "subcategory":"Computers",
            "type":"Manufacturing & Wholesale Goods"
        },
        {
            "category":"Professional",
            "subcategory":"Computer Services",
            "type":"Services"
        }
    ],
    "sg:phone":"+1 512 868 2009",
    "sg:postcode":"78626",
    "sg:province":"TX",
    "sg:tags":[
        "consultant",
        "software",
        "system",
        "equipment"
    ],
    "wof:name":"Teleste",
    "wof:placetype":"venue"
},
  "geometry": {"coordinates":[-97.669234,30.658483],"type":"Point"}
}