{
  "type": "Feature",
  "properties": {
    "iso:country":"US",
    "sg:address":"828 S Tyler St",
    "sg:city":"Dallas",
    "sg:classifiers":[
        {
            "category":"Social Services",
            "type":"Services"
        }
    ],
    "sg:phone":"+1 214 943 5406",
    "sg:postcode":"75208",
    "sg:province":"TX",
    "sg:tags":[
        "counseling"
    ],
    "wof:name":"Legacy Counseling Ctr",
    "wof:placetype":"venue"
},
  "geometry": {"coordinates":[-96.837521,32.739256],"type":"Point"}
}