{
  "type": "Feature",
  "properties": {
    "iso:country":"US",
    "sg:address":"1504 N Greenville Ave",
    "sg:city":"Allen",
    "sg:classifiers":[
        {
            "category":"Professional",
            "type":"Services"
        }
    ],
    "sg:phone":"+1 469 547 9912",
    "sg:postcode":"75002",
    "sg:province":"TX",
    "wof:name":"Triton Ep LLC",
    "wof:placetype":"venue"
},
  "geometry": {"coordinates":[-96.649512,33.121221],"type":"Point"}
}