{
  "type": "Feature",
  "properties": {
    "iso:country":"US",
    "sg:address":"302 Centennial St",
    "sg:city":"Carmine",
    "sg:classifiers":[
        {
            "category":"Real Estate",
            "subcategory":"Surveying",
            "type":"Services"
        }
    ],
    "sg:phone":"+1 979 542 0160",
    "sg:postcode":"78932",
    "sg:province":"TX",
    "sg:tags":[
        "surveyor"
    ],
    "wof:name":"Cartx Land Survey Svc",
    "wof:placetype":"venue"
},
  "geometry": {"coordinates":[-96.68456999999999,30.146065],"type":"Point"}
}