{
  "type": "Feature",
  "properties": {
    "iso:country":"US",
    "sg:address":"323 Gilbert Dr",
    "sg:city":"Vivian",
    "sg:classifiers":[
        {
            "category":"Personal",
            "subcategory":"Beauty Salon",
            "type":"Services"
        }
    ],
    "sg:phone":"+1 318 375 4247",
    "sg:postcode":"71082",
    "sg:province":"TX",
    "sg:tags":[
        "shop"
    ],
    "wof:name":"Shear Blessings",
    "wof:placetype":"venue"
},
  "geometry": {"coordinates":[-93.99614099999999,32.8714],"type":"Point"}
}