{
  "type": "Feature",
  "properties": {
    "iso:country":"US",
    "sg:address":"5915 Murphy Rd",
    "sg:city":"Garland",
    "sg:classifiers":[
        {
            "category":"Health Services",
            "subcategory":"Doctor",
            "type":"Services"
        }
    ],
    "sg:phone":"+1 972 675 5200",
    "sg:postcode":"75048",
    "sg:province":"TX",
    "sg:tags":[
        "medical"
    ],
    "wof:name":"Firewheel Family",
    "wof:placetype":"venue"
},
  "geometry": {"coordinates":[-96.61340300000001,32.977862],"type":"Point"}
}