{
  "type": "Feature",
  "properties": {
    "iso:country":"US",
    "sg:address":"2618 Henkel Ln",
    "sg:city":"Santa Fe",
    "sg:classifiers":[
        {
            "category":"Building & Trades",
            "subcategory":"Electrical",
            "type":"Services"
        }
    ],
    "sg:phone":"+1 409 925 4842",
    "sg:postcode":"77510",
    "sg:province":"TX",
    "sg:tags":[
        "house",
        "electrical",
        "contractor"
    ],
    "wof:name":"Santa Fe Construction",
    "wof:placetype":"venue"
},
  "geometry": {"coordinates":[-95.087906,29.403563],"type":"Point"}
}