{
  "type": "Feature",
  "properties": {
    "iso:country":"US",
    "sg:address":"1740 N Mays St",
    "sg:city":"Round Rock",
    "sg:classifiers":[
        {
            "category":"Food & Beverages",
            "subcategory":"Groceries & Convenience Stores",
            "type":"Retail Goods"
        }
    ],
    "sg:phone":"+1 512 255 4609",
    "sg:postcode":"78664",
    "sg:province":"TX",
    "wof:name":"Quik Stop Grocery",
    "wof:placetype":"venue"
},
  "geometry": {"coordinates":[-97.68583599999999,30.523516],"type":"Point"}
}