{
  "type": "Feature",
  "properties": {
    "iso:country":"US",
    "sg:address":"1251 Hoover St",
    "sg:city":"Luling",
    "sg:classifiers":[
        {
            "category":"Mining & Drilling",
            "type":"Manufacturing & Wholesale Goods"
        }
    ],
    "sg:phone":"+1 830 875 9181",
    "sg:postcode":"78648",
    "sg:province":"TX",
    "sg:tags":[
        "field",
        "oil",
        "well"
    ],
    "wof:name":"Luling Well Service",
    "wof:placetype":"venue"
},
  "geometry": {"coordinates":[-97.637551,29.685231],"type":"Point"}
}