{
  "type": "Feature",
  "properties": {
    "iso:country":"US",
    "sg:address":"122 W 1st St",
    "sg:city":"San Angelo",
    "sg:classifiers":[
        {
            "category":"Government",
            "subcategory":"Office",
            "type":"Public Place"
        }
    ],
    "sg:phone":"+1 325 657 4323",
    "sg:postcode":"76903",
    "sg:province":"TX",
    "sg:tags":[
        "govt",
        "city"
    ],
    "wof:name":"San Angelo Water Utilities",
    "wof:placetype":"venue"
},
  "geometry": {"coordinates":[-100.440524,31.464976],"type":"Point"}
}