{
  "type": "Feature",
  "properties": {
    "iso:country":"US",
    "sg:address":"1008 Ben Dr",
    "sg:city":"Brenham",
    "sg:classifiers":[
        {
            "category":"Building & Trades",
            "subcategory":"Landscaping Services",
            "type":"Services"
        }
    ],
    "sg:phone":"+1 979 836 1369",
    "sg:postcode":"77833",
    "sg:province":"TX",
    "sg:tags":[
        "landscape"
    ],
    "wof:name":"Thomas D Moehlmann",
    "wof:placetype":"venue"
},
  "geometry": {"coordinates":[-96.38676100000001,30.159645],"type":"Point"}
}