{
  "type": "Feature",
  "properties": {
    "iso:country":"US",
    "sg:address":"3000 Fredericksburg Rd",
    "sg:city":"San Antonio",
    "sg:classifiers":[
        {
            "category":"Health Services",
            "subcategory":"Doctor",
            "type":"Services"
        }
    ],
    "sg:phone":"+1 210 733 5455",
    "sg:postcode":"78201",
    "sg:province":"TX",
    "wof:name":"Mason M Taylor",
    "wof:placetype":"venue"
},
  "geometry": {"coordinates":[-98.53290699999999,29.471335],"type":"Point"}
}