{
  "type": "Feature",
  "properties": {
    "iso:country":"US",
    "sg:address":"8622 Dunlap St",
    "sg:city":"Dallas",
    "sg:classifiers":[
        {
            "category":"Retail",
            "subcategory":"Auto Repair",
            "type":"Services"
        }
    ],
    "sg:phone":"+1 214 398 8368",
    "sg:postcode":"75217",
    "sg:province":"TX",
    "sg:tags":[
        "automotive"
    ],
    "wof:name":"Berlanga",
    "wof:placetype":"venue"
},
  "geometry": {"coordinates":[-96.672799,32.726297],"type":"Point"}
}