{
  "type": "Feature",
  "properties": {
    "iso:country":"US",
    "sg:address":"503 Jan Ct",
    "sg:city":"Austin",
    "sg:classifiers":[
        {
            "category":"Personal",
            "subcategory":"Beauty Salon",
            "type":"Services"
        }
    ],
    "sg:phone":"+1 512 873 7300",
    "sg:postcode":"78753",
    "sg:province":"TX",
    "sg:tags":[
        "shop"
    ],
    "wof:name":"Susie Beauty Salon",
    "wof:placetype":"venue"
},
  "geometry": {"coordinates":[-97.698943,30.356898],"type":"Point"}
}