{
  "type": "Feature",
  "properties": {
    "iso:country":"US",
    "sg:address":"616 Business Pkwy",
    "sg:city":"Richardson",
    "sg:classifiers":[
        {
            "category":"Banks & Credit Unions",
            "subcategory":"Investment Brokerage",
            "type":"Services"
        }
    ],
    "sg:phone":"+1 972 644 2970",
    "sg:postcode":"75081",
    "sg:province":"TX",
    "wof:name":"Delta Plus Corp",
    "wof:placetype":"venue"
},
  "geometry": {"coordinates":[-96.73859400000001,32.938],"type":"Point"}
}