{
  "type": "Feature",
  "properties": {
    "iso:country":"US",
    "sg:address":"5209 W Broadway Ave",
    "sg:city":"Fort Worth",
    "sg:classifiers":[
        {
            "category":"Building & Trades",
            "subcategory":"Pest Control",
            "type":"Services"
        }
    ],
    "sg:phone":"+1 817 834 3121",
    "sg:postcode":"76117",
    "sg:province":"TX",
    "sg:website":"www.westernexp.com",
    "wof:name":"Western Exterminating Company",
    "wof:placetype":"venue"
},
  "geometry": {"coordinates":[-97.270028,32.809728],"type":"Point"}
}