{
  "type": "Feature",
  "properties": {
    "iso:country":"US",
    "sg:address":"1020 Miller Ave",
    "sg:city":"Fort Worth",
    "sg:classifiers":[
        {
            "category":"Manufacturing",
            "subcategory":"Printing",
            "type":"Manufacturing & Wholesale Goods"
        }
    ],
    "sg:phone":"+1 817 536 3525",
    "sg:postcode":"76105",
    "sg:province":"TX",
    "sg:tags":[
        "newspaper",
        "publishing"
    ],
    "wof:name":"Gospel Minutes",
    "wof:placetype":"venue"
},
  "geometry": {"coordinates":[-97.262004,32.731463],"type":"Point"}
}