{
  "type": "Feature",
  "properties": {
    "iso:country":"US",
    "sg:address":"1300 Turtle Creek Dr",
    "sg:city":"Missouri City",
    "sg:classifiers":[
        {
            "category":"Food & Beverages",
            "subcategory":"Groceries & Convenience Stores",
            "type":"Retail Goods"
        }
    ],
    "sg:phone":"+1 281 438 8404",
    "sg:postcode":"77489",
    "sg:province":"TX",
    "wof:name":"Missouri Food Mart",
    "wof:placetype":"venue"
},
  "geometry": {"coordinates":[-95.521343,29.579928],"type":"Point"}
}