{
  "type": "Feature",
  "properties": {
    "iso:country":"US",
    "sg:address":"10225 Research Blvd Ste 3000",
    "sg:city":"Austin",
    "sg:classifiers":[
        {
            "category":"Home & Garden",
            "subcategory":"Home Furnishings",
            "type":"Retail Goods"
        }
    ],
    "sg:phone":"+1 512 418 8232",
    "sg:postcode":"78759",
    "sg:province":"TX",
    "sg:tags":[
        "bath",
        "kitchen"
    ],
    "wof:name":"Bed Bath & Beyond",
    "wof:placetype":"venue"
},
  "geometry": {"coordinates":[-97.745903,30.394899],"type":"Point"}
}