{
  "type": "Feature",
  "properties": {
    "iso:country":"US",
    "sg:address":"2500 Friendswood Rd",
    "sg:city":"Alvin",
    "sg:classifiers":[
        {
            "category":"Home & Garden",
            "subcategory":"Building Materials",
            "type":"Retail Goods"
        }
    ],
    "sg:phone":"+1 281 388 2060",
    "sg:postcode":"77511",
    "sg:province":"TX",
    "sg:tags":[
        "lumber"
    ],
    "wof:name":"84 Lumber",
    "wof:placetype":"venue"
},
  "geometry": {"coordinates":[-95.24103100000001,29.443683],"type":"Point"}
}