{
  "type": "Feature",
  "properties": {
    "iso:country":"US",
    "sg:address":"2809 Southwest Pkwy",
    "sg:city":"Wichita Falls",
    "sg:classifiers":[
        {
            "category":"Shopping",
            "subcategory":"Books",
            "type":"Retail Goods"
        }
    ],
    "sg:phone":"+1 940 696 1166",
    "sg:postcode":"76308",
    "sg:province":"TX",
    "sg:tags":[
        "dealer"
    ],
    "wof:name":"Mardel Christian Office Educ",
    "wof:placetype":"venue"
},
  "geometry": {"coordinates":[-98.538253,33.857715],"type":"Point"}
}