{
  "type": "Feature",
  "properties": {
    "iso:country":"US",
    "sg:address":"917 N Texas Ave",
    "sg:city":"Bryan",
    "sg:classifiers":[
        {
            "category":"Wholesale",
            "subcategory":"Motor Vehicles",
            "type":"Manufacturing & Wholesale Goods"
        }
    ],
    "sg:phone":"+1 979 823 5363",
    "sg:postcode":"77803",
    "sg:province":"TX",
    "wof:name":"Pars Motors",
    "wof:placetype":"venue"
},
  "geometry": {"coordinates":[-96.368819,30.681408],"type":"Point"}
}