{
  "type": "Feature",
  "properties": {
    "iso:country":"US",
    "sg:address":"21173 US Hwy 59",
    "sg:city":"New Caney",
    "sg:classifiers":[
        {
            "category":"Real Estate",
            "subcategory":"Real Estate Agent",
            "type":"Services"
        },
        {
            "category":"Building & Trades",
            "subcategory":"Construction",
            "type":"Services"
        }
    ],
    "sg:phone":"+1 281 689 9111",
    "sg:postcode":"77357",
    "sg:province":"TX",
    "sg:tags":[
        "home",
        "builder"
    ],
    "wof:name":"Donna Baker Homes Inc",
    "wof:placetype":"venue"
},
  "geometry": {"coordinates":[-95.226435,30.138729],"type":"Point"}
}