{
  "type": "Feature",
  "properties": {
    "iso:country":"US",
    "sg:address":"410 Trumpet Vine Trl",
    "sg:city":"Cedar Park",
    "sg:classifiers":[
        {
            "category":"Building & Trades",
            "subcategory":"Construction",
            "type":"Services"
        }
    ],
    "sg:phone":"+1 512 257 2122",
    "sg:postcode":"78613",
    "sg:province":"TX",
    "sg:tags":[
        "home",
        "builder",
        "repair",
        "house"
    ],
    "wof:name":"Texas Home Crafters Constr Co",
    "wof:placetype":"venue"
},
  "geometry": {"coordinates":[-97.827833,30.50132],"type":"Point"}
}