{
  "type": "Feature",
  "properties": {
    "iso:country":"US",
    "sg:address":"4109 Hickox Rd",
    "sg:city":"Rowlett",
    "sg:classifiers":[
        {
            "category":"Building & Trades",
            "subcategory":"Landscaping Services",
            "type":"Services"
        }
    ],
    "sg:phone":"+1 972 475 3024",
    "sg:postcode":"75089",
    "sg:province":"TX",
    "wof:name":"JC Aguilar Landscaping SE",
    "wof:placetype":"venue"
},
  "geometry": {"coordinates":[-96.56050399999999,32.940255],"type":"Point"}
}