{
  "type": "Feature",
  "properties": {
    "iso:country":"US",
    "sg:address":"1115 S Congress Ave",
    "sg:city":"Austin",
    "sg:classifiers":[
        {
            "category":"Shopping",
            "subcategory":"Clothing, Apparel, & Fashions",
            "type":"Retail Goods"
        }
    ],
    "sg:phone":"+1 512 478 0000",
    "sg:postcode":"78704",
    "sg:province":"TX",
    "sg:website":"www.wearyourstory.com",
    "wof:name":"Storyville",
    "wof:placetype":"venue"
},
  "geometry": {"coordinates":[-97.748484,30.252692],"type":"Point"}
}