{
  "type": "Feature",
  "properties": {
    "iso:country":"US",
    "sg:address":"11203 Powder Mill Trl",
    "sg:city":"Austin",
    "sg:classifiers":[
        {
            "category":"Professional",
            "subcategory":"Management & Consulting",
            "type":"Services"
        }
    ],
    "sg:phone":"+1 512 335 0244",
    "sg:postcode":"78750",
    "sg:province":"TX",
    "wof:name":"Arn Management LLC",
    "wof:placetype":"venue"
},
  "geometry": {"coordinates":[-97.812095,30.461253],"type":"Point"}
}