{
  "type": "Feature",
  "properties": {
    "iso:country":"US",
    "sg:address":"1401 Radam Cir",
    "sg:city":"Austin",
    "sg:classifiers":[
        {
            "category":"Professional",
            "subcategory":"Management & Consulting",
            "type":"Services"
        }
    ],
    "sg:phone":"+1 512 443 9778",
    "sg:postcode":"78745",
    "sg:province":"TX",
    "sg:tags":[
        "business"
    ],
    "wof:name":"Brain Gym Lady",
    "wof:placetype":"venue"
},
  "geometry": {"coordinates":[-97.79060800000001,30.212189],"type":"Point"}
}