{
  "type": "Feature",
  "properties": {
    "iso:country":"US",
    "sg:address":"400 N Queen St",
    "sg:city":"Palestine",
    "sg:classifiers":[
        {
            "category":"Shopping",
            "subcategory":"Clothing, Apparel, & Fashions",
            "type":"Retail Goods"
        }
    ],
    "sg:phone":"+1 903 723 0450",
    "sg:postcode":"75801",
    "sg:province":"TX",
    "wof:name":"Le'Fashion",
    "wof:placetype":"venue"
},
  "geometry": {"coordinates":[-95.634563,31.763035],"type":"Point"}
}