{
  "type": "Feature",
  "properties": {
    "iso:country":"US",
    "sg:address":"2005 N Main St",
    "sg:city":"Cleburne",
    "sg:classifiers":[
        {
            "category":"Travel",
            "subcategory":"Hotels & Motels",
            "type":"Entertainment"
        },
        {
            "category":"Travel",
            "subcategory":"Bed & Breakfast",
            "type":"Entertainment"
        }
    ],
    "sg:phone":"+1 817 645 8953",
    "sg:postcode":"76033",
    "sg:province":"TX",
    "sg:tags":[
        "inn",
        "lodging"
    ],
    "sg:website":"http://www.daysinn.com",
    "wof:name":"Days Inn & Suites Cleburne",
    "wof:placetype":"venue"
},
  "geometry": {"coordinates":[-97.38713799999999,32.39677],"type":"Point"}
}