{
  "type": "Feature",
  "properties": {
    "iso:country":"US",
    "sg:address":"2301 McDaniel Dr Ste 100",
    "sg:city":"Carrollton",
    "sg:classifiers":[
        {
            "category":"Communications",
            "subcategory":"Newspaper",
            "type":"Services"
        }
    ],
    "sg:phone":"+1 972 280 0055",
    "sg:postcode":"75006",
    "sg:province":"TX",
    "sg:tags":[
        "print",
        "medium"
    ],
    "wof:name":"For Rent Media Solutions",
    "wof:placetype":"venue"
},
  "geometry": {"coordinates":[-96.921712,32.928821],"type":"Point"}
}