{
  "type": "Feature",
  "properties": {
    "iso:country":"US",
    "sg:address":"2304 Hancock Dr 7-D",
    "sg:city":"Austin",
    "sg:classifiers":[
        {
            "category":"Building & Trades",
            "subcategory":"Landscaping Services",
            "type":"Services"
        },
        {
            "category":"Building & Trades",
            "subcategory":"Construction",
            "type":"Services"
        }
    ],
    "sg:phone":"+1 512 452 6620",
    "sg:postcode":"78756",
    "sg:province":"TX",
    "sg:tags":[
        "excavation",
        "arborist",
        "contractor",
        "tree",
        "grading"
    ],
    "wof:name":"Trees Unlimited",
    "wof:placetype":"venue"
},
  "geometry": {"coordinates":[-97.742732,30.324242],"type":"Point"}
}