{
  "type": "Feature",
  "properties": {
    "iso:country":"US",
    "sg:address":"2113 N Chadbourne St",
    "sg:city":"San Angelo",
    "sg:classifiers":[
        {
            "category":"Banks & Credit Unions",
            "subcategory":"Bank",
            "type":"Services"
        }
    ],
    "sg:phone":"+1 325 659 4161",
    "sg:postcode":"76903",
    "sg:province":"TX",
    "sg:tags":[
        "institution",
        "business"
    ],
    "wof:name":"Hughes Financial Services",
    "wof:placetype":"venue"
},
  "geometry": {"coordinates":[-100.449761,31.482201],"type":"Point"}
}