{
  "type": "Feature",
  "properties": {
    "iso:country":"US",
    "sg:address":"1100 E Rendon Crowley Rd",
    "sg:city":"Burleson",
    "sg:classifiers":[
        {
            "category":"Retail",
            "subcategory":"Auto Repair",
            "type":"Services"
        }
    ],
    "sg:phone":"+1 817 637 1360",
    "sg:postcode":"76028",
    "sg:province":"TX",
    "sg:website":"affordablemechanicinc.com/location/",
    "wof:name":"Affordable Mechanic Inc",
    "wof:placetype":"venue"
},
  "geometry": {"coordinates":[-97.30035700000001,32.579119],"type":"Point"}
}