{
  "type": "Feature",
  "properties": {
    "iso:country":"US",
    "sg:address":"10516 Katy Fwy, Suite K",
    "sg:city":"Houston",
    "sg:classifiers":[
        {
            "category":"Restaurant",
            "type":"Food & Drink"
        }
    ],
    "sg:phone":"+1 713 461 1333",
    "sg:postcode":"77043",
    "sg:province":"TX",
    "sg:tags":[
        "chinese",
        "buffet"
    ],
    "sg:website":"www.buffet-city.com",
    "wof:name":"Buffet City",
    "wof:placetype":"venue"
},
  "geometry": {"coordinates":[-95.558725,29.786311],"type":"Point"}
}