{
  "type": "Feature",
  "properties": {
    "iso:country":"US",
    "sg:address":"12725 Murphy Rd",
    "sg:city":"Stafford",
    "sg:classifiers":[
        {
            "category":"Autos & Motor Vehicles",
            "subcategory":"Automobile Sales",
            "type":"Retail Goods"
        }
    ],
    "sg:phone":"+1 281 741 7364",
    "sg:postcode":"77477",
    "sg:province":"TX",
    "sg:tags":[
        "dealers-used",
        "car",
        "used",
        "cars-wholesale"
    ],
    "wof:name":"Real Autos",
    "wof:placetype":"venue"
},
  "geometry": {"coordinates":[-95.56507499999999,29.637805],"type":"Point"}
}