{
  "type": "Feature",
  "properties": {
    "iso:country":"US",
    "sg:address":"4683 College St",
    "sg:city":"Beaumont",
    "sg:classifiers":[
        {
            "category":"Shopping",
            "subcategory":"Used Merchandise",
            "type":"Retail Goods"
        }
    ],
    "sg:phone":"+1 409 840 5532",
    "sg:postcode":"77707",
    "sg:province":"TX",
    "wof:name":"Furniture Repair & Refinish",
    "wof:placetype":"venue"
},
  "geometry": {"coordinates":[-94.145442,30.067936],"type":"Point"}
}