{
  "type": "Feature",
  "properties": {
    "iso:country":"US",
    "sg:address":"8700 N Stemmons Fwy",
    "sg:city":"Dallas",
    "sg:classifiers":[
        {
            "category":"Professional",
            "subcategory":"Business Services",
            "type":"Services"
        }
    ],
    "sg:phone":"+1 214 630 3200",
    "sg:postcode":"75247",
    "sg:province":"TX",
    "wof:name":"Delta Airlines",
    "wof:placetype":"venue"
},
  "geometry": {"coordinates":[-96.872981,32.829254],"type":"Point"}
}