{
  "type": "Feature",
  "properties": {
    "iso:country":"US",
    "sg:address":"13279 N Promenade Blvd",
    "sg:city":"Sugar Land",
    "sg:classifiers":[
        {
            "category":"Freight",
            "type":"Transportation"
        },
        {
            "category":"Building & Trades",
            "subcategory":"Construction",
            "type":"Services"
        }
    ],
    "sg:phone":"+1 281 494 4844",
    "sg:postcode":"77477",
    "sg:province":"TX",
    "sg:tags":[
        "steel",
        "center",
        "metal",
        "general",
        "fabrication",
        "welding"
    ],
    "wof:name":"Sandvik Steel Co",
    "wof:placetype":"venue"
},
  "geometry": {"coordinates":[-95.569434,29.629519],"type":"Point"}
}