{
  "type": "Feature",
  "properties": {
    "iso:country":"US",
    "sg:address":"501 E 2nd St",
    "sg:city":"Big Lake",
    "sg:classifiers":[
        {
            "category":"Food & Beverages",
            "subcategory":"Groceries & Convenience Stores",
            "type":"Retail Goods"
        }
    ],
    "sg:phone":"+1 325 884 2644",
    "sg:postcode":"76932",
    "sg:province":"TX",
    "sg:tags":[
        "grocer"
    ],
    "wof:name":"Town & Country Village",
    "wof:placetype":"venue"
},
  "geometry": {"coordinates":[-101.460683,31.191532],"type":"Point"}
}