{
  "type": "Feature",
  "properties": {
    "iso:country":"US",
    "sg:address":"450 Country Club Rd",
    "sg:city":"Allen",
    "sg:classifiers":[
        {
            "category":"Education",
            "subcategory":"School",
            "type":"Public Place"
        }
    ],
    "sg:phone":"+1 972 747 8498",
    "sg:postcode":"75002",
    "sg:province":"TX",
    "wof:name":"Lovejoy ISD",
    "wof:placetype":"venue"
},
  "geometry": {"coordinates":[-96.590788,33.090729],"type":"Point"}
}