{
  "type": "Feature",
  "properties": {
    "iso:country":"US",
    "sg:address":"8211 Peachtree St",
    "sg:city":"Houston",
    "sg:classifiers":[
        {
            "category":"Building & Trades",
            "subcategory":"Cleaning & Sanitation",
            "type":"Services"
        }
    ],
    "sg:phone":"+1 713 631 1324",
    "sg:postcode":"77016",
    "sg:province":"TX",
    "sg:tags":[
        "carpet"
    ],
    "wof:name":"Barnett Home Care",
    "wof:placetype":"venue"
},
  "geometry": {"coordinates":[-95.31539100000001,29.835093],"type":"Point"}
}