{
  "type": "Feature",
  "properties": {
    "iso:country":"US",
    "sg:address":"101 E Park Blvd",
    "sg:city":"Plano",
    "sg:classifiers":[
        {
            "category":"Insurance",
            "subcategory":"Insurance Agent",
            "type":"Services"
        }
    ],
    "sg:phone":"+1 972 633 0729",
    "sg:postcode":"75074",
    "sg:province":"TX",
    "wof:name":"Allstate Insurance",
    "wof:placetype":"venue"
},
  "geometry": {"coordinates":[-96.706355,33.028763],"type":"Point"}
}