{
  "type": "Feature",
  "properties": {
    "iso:country":"US",
    "sg:address":"1113 Vine St",
    "sg:city":"Houston",
    "sg:classifiers":[
        {
            "category":"Real Estate",
            "subcategory":"Architect",
            "type":"Services"
        }
    ],
    "sg:phone":"+1 713 229 0688",
    "sg:postcode":"77002",
    "sg:province":"TX",
    "wof:name":"Kornberg Daniel Architects",
    "wof:placetype":"venue"
},
  "geometry": {"coordinates":[-95.3573,29.767599],"type":"Point"}
}