{
  "type": "Feature",
  "properties": {
    "iso:country":"US",
    "sg:address":"512 Magnolia St",
    "sg:city":"Burkburnett",
    "sg:classifiers":[
        {
            "category":"Autos & Motor Vehicles",
            "subcategory":"Auto Supplies",
            "type":"Retail Goods"
        }
    ],
    "sg:phone":"+1 940 569 2707",
    "sg:postcode":"76354",
    "sg:province":"TX",
    "wof:name":"Nix White Auto Store Inc",
    "wof:placetype":"venue"
},
  "geometry": {"coordinates":[-98.567609,34.090593],"type":"Point"}
}