{
  "type": "Feature",
  "properties": {
    "iso:country":"US",
    "sg:address":"301 Sesame Dr",
    "sg:city":"Mesquite",
    "sg:classifiers":[
        {
            "category":"Wholesale",
            "subcategory":"Hardware",
            "type":"Manufacturing & Wholesale Goods"
        }
    ],
    "sg:phone":"+1 972 285 9924",
    "sg:postcode":"75149",
    "sg:province":"TX",
    "sg:tags":[
        "plumbing"
    ],
    "wof:name":"Dgld Inc",
    "wof:placetype":"venue"
},
  "geometry": {"coordinates":[-96.63744699999999,32.771603],"type":"Point"}
}