{
  "type": "Feature",
  "properties": {
    "iso:country":"US",
    "sg:address":"4211 W 2nd St",
    "sg:city":"Plainview",
    "sg:classifiers":[
        {
            "category":"Organizations",
            "subcategory":"Religious Organization",
            "type":"Services"
        }
    ],
    "sg:phone":"+1 806 293 5897",
    "sg:postcode":"79072",
    "sg:province":"TX",
    "sg:tags":[
        "church"
    ],
    "wof:name":"Church Of Jesus Christ Of Lds",
    "wof:placetype":"venue"
},
  "geometry": {"coordinates":[-101.75241200000001,34.178845],"type":"Point"}
}