{
  "type": "Feature",
  "properties": {
    "iso:country":"US",
    "sg:address":"9021 Norton St",
    "sg:city":"El Paso",
    "sg:classifiers":[
        {
            "category":"Building & Trades",
            "subcategory":"Construction",
            "type":"Services"
        }
    ],
    "sg:phone":"+1 915 755 1200",
    "sg:postcode":"79904",
    "sg:province":"TX",
    "sg:tags":[
        "house"
    ],
    "wof:name":"Ochoa Home Repair",
    "wof:placetype":"venue"
},
  "geometry": {"coordinates":[-106.43597200000001,31.86925],"type":"Point"}
}