{
  "type": "Feature",
  "properties": {
    "iso:country":"US",
    "sg:address":"5621 Bunker Blvd",
    "sg:city":"Watauga",
    "sg:classifiers":[
        {
            "category":"Insurance",
            "subcategory":"Hazard Insurance",
            "type":"Services"
        },
        {
            "category":"Insurance",
            "subcategory":"Insurance Agent",
            "type":"Services"
        },
        {
            "category":"Insurance",
            "subcategory":"Life Insurance",
            "type":"Services"
        }
    ],
    "sg:phone":"+1 817 479 9960",
    "sg:postcode":"76148",
    "sg:province":"TX",
    "sg:tags":[
        "auto"
    ],
    "sg:website":"http://statefarm.mqgroup.com/url.asp?usr=437172",
    "wof:name":"Leal, Eloy - State Farm Insurance Agent",
    "wof:placetype":"venue"
},
  "geometry": {"coordinates":[-97.26227799999999,32.870614],"type":"Point"}
}