{
  "type": "Feature",
  "properties": {
    "iso:country":"US",
    "sg:address":"7340 Spencer Hwy",
    "sg:city":"Pasadena",
    "sg:classifiers":[
        {
            "category":"Government",
            "subcategory":"Office",
            "type":"Public Place"
        }
    ],
    "sg:phone":"+1 281 479 4232",
    "sg:postcode":"77505",
    "sg:province":"TX",
    "wof:name":"Harris County Activity Ctr",
    "wof:placetype":"venue"
},
  "geometry": {"coordinates":[-95.12645999999999,29.663533],"type":"Point"}
}