{
  "type": "Feature",
  "properties": {
    "iso:country":"US",
    "sg:address":"12835 Louetta Rd",
    "sg:city":"Cypress",
    "sg:classifiers":[
        {
            "category":"Health Services",
            "subcategory":"Doctor",
            "type":"Services"
        }
    ],
    "sg:phone":"+1 281 376 9246",
    "sg:postcode":"77070",
    "sg:province":"TX",
    "sg:tags":[
        "dentist"
    ],
    "wof:name":"R Terry Councill DDS",
    "wof:placetype":"venue"
},
  "geometry": {"coordinates":[-95.615325,29.996297],"type":"Point"}
}