{
  "type": "Feature",
  "properties": {
    "iso:country":"US",
    "sg:address":"1100 S Main St",
    "sg:city":"Seminole",
    "sg:classifiers":[
        {
            "category":"Coffee & Tea",
            "type":"Food & Drink"
        },
        {
            "category":"Restaurant",
            "type":"Food & Drink"
        }
    ],
    "sg:phone":"+1 432 955 0366",
    "sg:postcode":"79360",
    "sg:province":"TX",
    "sg:tags":[
        "shop",
        "espresso"
    ],
    "wof:name":"Java Jitterz Coffee House",
    "wof:placetype":"venue"
},
  "geometry": {"coordinates":[-102.644958,32.70705],"type":"Point"}
}