{
  "type": "Feature",
  "properties": {
    "iso:country":"US",
    "sg:address":"817 N Highland St",
    "sg:city":"Amarillo",
    "sg:classifiers":[
        {
            "category":"Building & Trades",
            "subcategory":"Construction",
            "type":"Services"
        }
    ],
    "sg:phone":"+1 806 679 2346",
    "sg:postcode":"79107",
    "sg:province":"TX",
    "sg:tags":[
        "contractor"
    ],
    "wof:name":"Guper USA",
    "wof:placetype":"venue"
},
  "geometry": {"coordinates":[-101.803904,35.222179],"type":"Point"}
}