{
  "type": "Feature",
  "properties": {
    "iso:country":"US",
    "sg:address":"7424 Greenville Ave",
    "sg:city":"Dallas",
    "sg:classifiers":[
        {
            "category":"Professional",
            "subcategory":"Computer Services",
            "type":"Services"
        }
    ],
    "sg:phone":"+1 214 692 9091",
    "sg:postcode":"75231",
    "sg:province":"TX",
    "sg:tags":[
        "development",
        "software"
    ],
    "wof:name":"Salinon Corp",
    "wof:placetype":"venue"
},
  "geometry": {"coordinates":[-96.75986,32.881139],"type":"Point"}
}