{
  "type": "Feature",
  "properties": {
    "iso:country":"US",
    "sg:address":"230 Meadow Dr",
    "sg:city":"Bridge City",
    "sg:classifiers":[
        {
            "category":"Wholesale",
            "subcategory":"Plants",
            "type":"Manufacturing & Wholesale Goods"
        }
    ],
    "sg:phone":"+1 409 735 4369",
    "sg:postcode":"77611",
    "sg:province":"TX",
    "sg:tags":[
        "supply"
    ],
    "wof:name":"Murphys Menagerie",
    "wof:placetype":"venue"
},
  "geometry": {"coordinates":[-93.836623,30.037588],"type":"Point"}
}