{
  "type": "Feature",
  "properties": {
    "iso:country":"US",
    "sg:address":"7514 Sunny Oaks Way",
    "sg:city":"Houston",
    "sg:classifiers":[
        {
            "category":"Insurance",
            "subcategory":"Insurance Agent",
            "type":"Services"
        }
    ],
    "sg:phone":"+1 281 855 3404",
    "sg:postcode":"77095",
    "sg:province":"TX",
    "wof:name":"Southeastern Claims Inc",
    "wof:placetype":"venue"
},
  "geometry": {"coordinates":[-95.65503200000001,29.88846],"type":"Point"}
}