{
  "type": "Feature",
  "properties": {
    "iso:country":"US",
    "sg:address":"4921 Wedgeview Dr",
    "sg:city":"Hurst",
    "sg:classifiers":[
        {
            "category":"Mining & Drilling",
            "type":"Manufacturing & Wholesale Goods"
        }
    ],
    "sg:phone":"+1 817 284 0644",
    "sg:postcode":"76053",
    "sg:province":"TX",
    "sg:tags":[
        "oil",
        "gas",
        "producer"
    ],
    "wof:name":"Robert V Ratts Inc",
    "wof:placetype":"venue"
},
  "geometry": {"coordinates":[-97.192374,32.8376],"type":"Point"}
}