{
  "type": "Feature",
  "properties": {
    "iso:country":"US",
    "sg:address":"5528 Lawndale St",
    "sg:city":"Houston",
    "sg:classifiers":[
        {
            "category":"Health Services",
            "subcategory":"Hospital",
            "type":"Services"
        }
    ],
    "sg:phone":"+1 713 921 2276",
    "sg:postcode":"77023",
    "sg:province":"TX",
    "sg:tags":[
        "specialty"
    ],
    "wof:name":"Unlimited Visions Aftercare",
    "wof:placetype":"venue"
},
  "geometry": {"coordinates":[-95.319518,29.727183],"type":"Point"}
}