{
  "type": "Feature",
  "properties": {
    "iso:country":"US",
    "sg:address":"8150 Springwood Dr",
    "sg:city":"Irving",
    "sg:classifiers":[
        {
            "category":"Retail",
            "subcategory":"Laundry & Dry Cleaning",
            "type":"Services"
        }
    ],
    "sg:phone":"+1 972 444 9373",
    "sg:postcode":"75063",
    "sg:province":"TX",
    "sg:tags":[
        "power"
    ],
    "wof:name":"Airport Services",
    "wof:placetype":"venue"
},
  "geometry": {"coordinates":[-96.986485,32.918292],"type":"Point"}
}