{
  "type": "Feature",
  "properties": {
    "iso:country":"US",
    "sg:address":"535 E Jefferson Blvd",
    "sg:city":"Dallas",
    "sg:classifiers":[
        {
            "category":"Local Transit",
            "type":"Transportation"
        }
    ],
    "sg:phone":"+1 214 941 7399",
    "sg:postcode":"75203",
    "sg:province":"TX",
    "sg:tags":[
        "bus",
        "line"
    ],
    "wof:name":"Tornado Bus Company Inc",
    "wof:placetype":"venue"
},
  "geometry": {"coordinates":[-96.81751800000001,32.746229],"type":"Point"}
}