{
  "type": "Feature",
  "properties": {
    "iso:country":"US",
    "sg:address":"2340 Parker Rd",
    "sg:city":"Carrollton",
    "sg:classifiers":[
        {
            "category":"Professional",
            "subcategory":"Advertising",
            "type":"Services"
        }
    ],
    "sg:phone":"+1 972 492 2316",
    "sg:postcode":"75010",
    "sg:province":"TX",
    "sg:tags":[
        "outdoor"
    ],
    "wof:name":"Griffith Outdoor Co Inc",
    "wof:placetype":"venue"
},
  "geometry": {"coordinates":[-96.86487099999999,33.044741],"type":"Point"}
}