{
  "type": "Feature",
  "properties": {
    "iso:country":"US",
    "sg:address":"512 Freestone Dr",
    "sg:city":"Euless",
    "sg:classifiers":[
        {
            "category":"Building & Trades",
            "subcategory":"Cleaning & Sanitation",
            "type":"Services"
        }
    ],
    "sg:phone":"+1 817 354 6389",
    "sg:postcode":"76039",
    "sg:province":"TX",
    "sg:tags":[
        "janitor"
    ],
    "wof:name":"Kongkaw Commercial Cleaning",
    "wof:placetype":"venue"
},
  "geometry": {"coordinates":[-97.087827,32.843512],"type":"Point"}
}