{
  "type": "Feature",
  "properties": {
    "iso:country":"US",
    "sg:address":"11161 W Little York Rd",
    "sg:city":"Houston",
    "sg:classifiers":[
        {
            "category":"Wholesale",
            "subcategory":"Machinery & Supplies",
            "type":"Manufacturing & Wholesale Goods"
        }
    ],
    "sg:phone":"+1 713 896 0144",
    "sg:postcode":"77041",
    "sg:province":"TX",
    "sg:tags":[
        "barbecue",
        "equipment"
    ],
    "wof:name":"Gator Pit",
    "wof:placetype":"venue"
},
  "geometry": {"coordinates":[-95.573649,29.867122],"type":"Point"}
}