{
  "type": "Feature",
  "properties": {
    "iso:country":"US",
    "sg:address":"1255 Broadway St",
    "sg:city":"Beaumont",
    "sg:classifiers":[
        {
            "category":"Professional",
            "subcategory":"Employment Agencies",
            "type":"Services"
        }
    ],
    "sg:phone":"+1 409 892 1972",
    "sg:postcode":"77701",
    "sg:province":"TX",
    "sg:tags":[
        "temporary",
        "help"
    ],
    "wof:name":"Manpower",
    "wof:placetype":"venue"
},
  "geometry": {"coordinates":[-94.107798,30.08492],"type":"Point"}
}