{
  "type": "Feature",
  "properties": {
    "iso:country":"US",
    "sg:address":"7 Turnbury Ct",
    "sg:city":"Roanoke",
    "sg:classifiers":[
        {
            "category":"Professional",
            "subcategory":"Management & Consulting",
            "type":"Services"
        }
    ],
    "sg:phone":"+1 817 491 8866",
    "sg:postcode":"76262",
    "sg:province":"TX",
    "sg:tags":[
        "business"
    ],
    "wof:name":"Freedom Profit Recovery Inc",
    "wof:placetype":"venue"
},
  "geometry": {"coordinates":[-97.183403,32.991453],"type":"Point"}
}