{
  "type": "Feature",
  "properties": {
    "iso:country":"US",
    "sg:address":"6315 FM 1488",
    "sg:city":"Magnolia",
    "sg:classifiers":[
        {
            "category":"Shopping",
            "subcategory":"Tobacco",
            "type":"Retail Goods"
        }
    ],
    "sg:phone":"+1 281 252 6464",
    "sg:postcode":"77354",
    "sg:province":"TX",
    "sg:tags":[
        "cigarette",
        "cigar",
        "dealer"
    ],
    "wof:name":"Tobacco Outlet",
    "wof:placetype":"venue"
},
  "geometry": {"coordinates":[-95.495921,30.231866],"type":"Point"}
}