{
  "type": "Feature",
  "properties": {
    "iso:country":"US",
    "sg:address":"6806 Poppy St",
    "sg:city":"Houston",
    "sg:classifiers":[
        {
            "category":"Building & Trades",
            "subcategory":"Construction",
            "type":"Services"
        }
    ],
    "sg:phone":"+1 713 939 8771",
    "sg:postcode":"77092",
    "sg:province":"TX",
    "sg:tags":[
        "contractor"
    ],
    "sg:website":"www.lousconstruction.com",
    "wof:name":"Lou's Construction Company",
    "wof:placetype":"venue"
},
  "geometry": {"coordinates":[-95.491203,29.8424],"type":"Point"}
}