{
  "type": "Feature",
  "properties": {
    "iso:country":"US",
    "sg:address":"5847 Shady River Dr",
    "sg:city":"Houston",
    "sg:classifiers":[
        {
            "category":"Professional",
            "subcategory":"Business Services",
            "type":"Services"
        }
    ],
    "sg:phone":"+1 713 785 9796",
    "sg:postcode":"77057",
    "sg:province":"TX",
    "wof:name":"Shelley Melody Interiors",
    "wof:placetype":"venue"
},
  "geometry": {"coordinates":[-95.479107,29.767256],"type":"Point"}
}