{
  "type": "Feature",
  "properties": {
    "iso:country":"US",
    "sg:address":"1510 Industrial Blvd",
    "sg:city":"Mc Kinney",
    "sg:classifiers":[
        {
            "category":"Airport",
            "type":"Transportation"
        }
    ],
    "sg:phone":"+1 972 562 5555",
    "sg:postcode":"75069",
    "sg:province":"TX",
    "wof:name":"Mc Kinney Municipal Airport",
    "wof:placetype":"venue"
},
  "geometry": {"coordinates":[-96.604725,33.178002],"type":"Point"}
}