{
  "type": "Feature",
  "properties": {
    "iso:country":"US",
    "sg:address":"2031 E Price St",
    "sg:city":"Paris",
    "sg:classifiers":[
        {
            "category":"Building & Trades",
            "subcategory":"Construction",
            "type":"Services"
        }
    ],
    "sg:phone":"+1 903 784 7315",
    "sg:postcode":"75460",
    "sg:province":"TX",
    "sg:tags":[
        "contractor"
    ],
    "wof:name":"Williams Tiles",
    "wof:placetype":"venue"
},
  "geometry": {"coordinates":[-95.535308,33.662874],"type":"Point"}
}