{
  "type": "Feature",
  "properties": {
    "iso:country":"US",
    "sg:address":"601 Main St",
    "sg:city":"Texarkana",
    "sg:classifiers":[
        {
            "category":"Government",
            "subcategory":"Office",
            "type":"Public Place"
        }
    ],
    "sg:phone":"+1 903 793 8936",
    "sg:postcode":"75501",
    "sg:province":"TX",
    "sg:tags":[
        "county",
        "taxation"
    ],
    "wof:name":"Bowie County Tax Appraisal Ofc",
    "wof:placetype":"venue"
},
  "geometry": {"coordinates":[-94.04674799999999,33.425632],"type":"Point"}
}