{
  "type": "Feature",
  "properties": {
    "iso:country":"US",
    "sg:address":"11811 Pepperdine Ln",
    "sg:city":"Houston",
    "sg:classifiers":[
        {
            "category":"Professional",
            "subcategory":"Lawyer & Legal Services",
            "type":"Services"
        }
    ],
    "sg:phone":"+1 713 960 9563",
    "sg:postcode":"77071",
    "sg:province":"TX",
    "wof:name":"Batchan John W Atty",
    "wof:placetype":"venue"
},
  "geometry": {"coordinates":[-95.50872200000001,29.650845],"type":"Point"}
}