{
  "type": "Feature",
  "properties": {
    "iso:country":"US",
    "sg:address":"26 S Mossrock Rd",
    "sg:city":"Spring",
    "sg:classifiers":[
        {
            "category":"Mining & Drilling",
            "type":"Manufacturing & Wholesale Goods"
        },
        {
            "category":"Wholesale",
            "subcategory":"Jewelry",
            "type":"Manufacturing & Wholesale Goods"
        }
    ],
    "sg:phone":"+1 281 298 1958",
    "sg:postcode":"77380",
    "sg:province":"TX",
    "sg:tags":[
        "diamonds-industrial",
        "diamonds-wholesale"
    ],
    "wof:name":"Protech Diamond USA Inc",
    "wof:placetype":"venue"
},
  "geometry": {"coordinates":[-95.458522,30.139868],"type":"Point"}
}