{
  "type": "Feature",
  "properties": {
    "iso:country":"US",
    "sg:address":"4507 50th St",
    "sg:city":"Lubbock",
    "sg:classifiers":[
        {
            "category":"Wholesale",
            "subcategory":"Electrical",
            "type":"Manufacturing & Wholesale Goods"
        }
    ],
    "sg:phone":"+1 806 792 3883",
    "sg:postcode":"79414",
    "sg:province":"TX",
    "sg:tags":[
        "repair"
    ],
    "wof:name":"Aerus Electrolux",
    "wof:placetype":"venue"
},
  "geometry": {"coordinates":[-101.909301,33.548688],"type":"Point"}
}