{
  "type": "Feature",
  "properties": {
    "iso:country":"US",
    "sg:address":"604 University Village Dr",
    "sg:city":"Richardson",
    "sg:classifiers":[
        {
            "category":"Banks & Credit Unions",
            "subcategory":"Bank",
            "type":"Services"
        }
    ],
    "sg:phone":"+1 972 235 4744",
    "sg:postcode":"75081",
    "sg:province":"TX",
    "sg:tags":[
        "loan",
        "real estate"
    ],
    "wof:name":"Blue Star Mortgage",
    "wof:placetype":"venue"
},
  "geometry": {"coordinates":[-96.69605300000001,32.945446],"type":"Point"}
}