{
  "type": "Feature",
  "properties": {
    "iso:country":"US",
    "sg:address":"1132 Oakhurst St",
    "sg:city":"Denton",
    "sg:classifiers":[
        {
            "category":"Professional",
            "type":"Services"
        }
    ],
    "sg:phone":"+1 940 591 0901",
    "sg:postcode":"76210",
    "sg:province":"TX",
    "wof:name":"Premier Hospitality Incorporat",
    "wof:placetype":"venue"
},
  "geometry": {"coordinates":[-97.115292,33.172925],"type":"Point"}
}