{
  "type": "Feature",
  "properties": {
    "iso:country":"US",
    "sg:address":"13521 Montfort Dr",
    "sg:city":"Dallas",
    "sg:classifiers":[
        {
            "category":"Building & Trades",
            "subcategory":"Locksmith",
            "type":"Services"
        }
    ],
    "sg:phone":"+1 972 233 6969",
    "sg:postcode":"75240",
    "sg:province":"TX",
    "sg:tags":[
        "key"
    ],
    "wof:name":"Armadillo Lock & Safe",
    "wof:placetype":"venue"
},
  "geometry": {"coordinates":[-96.81300400000001,32.931999],"type":"Point"}
}