{
  "type": "Feature",
  "properties": {
    "iso:country":"US",
    "sg:address":"713 Bradfield Dr",
    "sg:city":"Garland",
    "sg:classifiers":[
        {
            "category":"Communications",
            "subcategory":"Film & Video Production",
            "type":"Services"
        }
    ],
    "sg:phone":"+1 972 276 3387",
    "sg:postcode":"75042",
    "sg:province":"TX",
    "sg:tags":[
        "taping"
    ],
    "wof:name":"Video Memories By Ann Giddens",
    "wof:placetype":"venue"
},
  "geometry": {"coordinates":[-96.69169100000001,32.92007],"type":"Point"}
}