{
  "type": "Feature",
  "properties": {
    "iso:country":"US",
    "sg:address":"8935 Wurzbach Rd",
    "sg:city":"San Antonio",
    "sg:classifiers":[
        {
            "category":"Retail",
            "subcategory":"Car Wash",
            "type":"Services"
        }
    ],
    "sg:phone":"+1 210 699 0376",
    "sg:postcode":"78240",
    "sg:province":"TX",
    "sg:tags":[
        "polishing",
        "washing"
    ],
    "wof:name":"203 Carwash",
    "wof:placetype":"venue"
},
  "geometry": {"coordinates":[-98.566613,29.526828],"type":"Point"}
}