{
  "type": "Feature",
  "properties": {
    "iso:country":"US",
    "sg:address":"15314 Ensenada Dr",
    "sg:city":"Houston",
    "sg:classifiers":[
        {
            "category":"Real Estate",
            "subcategory":"Real Estate Agent",
            "type":"Services"
        }
    ],
    "sg:phone":"+1 281 564 0799",
    "sg:postcode":"77083",
    "sg:province":"TX",
    "wof:name":"Bratcher Homes & Investments",
    "wof:placetype":"venue"
},
  "geometry": {"coordinates":[-95.656138,29.689961],"type":"Point"}
}