{
  "type": "Feature",
  "properties": {
    "iso:country":"US",
    "sg:address":"10505 Southwest Fwy",
    "sg:city":"Houston",
    "sg:classifiers":[
        {
            "category":"Autos & Motor Vehicles",
            "subcategory":"Automobile Sales",
            "type":"Retail Goods"
        }
    ],
    "sg:phone":"+1 713 981 4400",
    "sg:postcode":"77074",
    "sg:province":"TX",
    "sg:tags":[
        "car"
    ],
    "sg:website":"www.advantagecars.com",
    "wof:name":"Advantage Cars",
    "wof:placetype":"venue"
},
  "geometry": {"coordinates":[-95.55235,29.665352],"type":"Point"}
}