{
  "type": "Feature",
  "properties": {
    "iso:country":"US",
    "sg:address":"423 Puig Dr",
    "sg:city":"Laredo",
    "sg:classifiers":[
        {
            "category":"Freight",
            "type":"Transportation"
        }
    ],
    "sg:phone":"+1 956 725 4343",
    "sg:postcode":"78045",
    "sg:province":"TX",
    "sg:tags":[
        "arrangement"
    ],
    "wof:name":"Garza International Co",
    "wof:placetype":"venue"
},
  "geometry": {"coordinates":[-99.486745,27.585445],"type":"Point"}
}