{
  "type": "Feature",
  "properties": {
    "iso:country":"US",
    "sg:address":"120 Silverbell Cir",
    "sg:city":"Lake Jackson",
    "sg:classifiers":[
        {
            "category":"Organizations",
            "subcategory":"Religious Organization",
            "type":"Services"
        }
    ],
    "sg:phone":"+1 979 297 4648",
    "sg:postcode":"77566",
    "sg:province":"TX",
    "sg:tags":[
        "church"
    ],
    "wof:name":"Vineyard Christian Fellowshp",
    "wof:placetype":"venue"
},
  "geometry": {"coordinates":[-95.444429,29.029853],"type":"Point"}
}