{
  "type": "Feature",
  "properties": {
    "iso:country":"US",
    "sg:address":"1101 N Bridge St",
    "sg:city":"Henrietta",
    "sg:classifiers":[
        {
            "category":"Government",
            "subcategory":"Office",
            "type":"Public Place"
        }
    ],
    "sg:phone":"+1 940 538 5201",
    "sg:postcode":"76365",
    "sg:province":"TX",
    "sg:tags":[
        "state",
        "resource"
    ],
    "wof:name":"Human Service Dept",
    "wof:placetype":"venue"
},
  "geometry": {"coordinates":[-98.195216,33.824836],"type":"Point"}
}