{
  "type": "Feature",
  "properties": {
    "iso:country":"US",
    "sg:address":"1500 E Hwy 82",
    "sg:city":"Gainesville",
    "sg:classifiers":[
        {
            "category":"Health Services",
            "subcategory":"Medical Lab",
            "type":"Services"
        }
    ],
    "sg:phone":"+1 940 668 8186",
    "sg:postcode":"76240",
    "sg:province":"TX",
    "sg:tags":[
        "laboratory",
        "dental"
    ],
    "wof:name":"Modern Matrix",
    "wof:placetype":"venue"
},
  "geometry": {"coordinates":[-97.129904,33.641929],"type":"Point"}
}