{
  "type": "Feature",
  "properties": {
    "iso:country":"US",
    "sg:address":"45 Saddlebrook Ln",
    "sg:city":"Houston",
    "sg:classifiers":[
        {
            "category":"Banks & Credit Unions",
            "subcategory":"Financial Services",
            "type":"Services"
        }
    ],
    "sg:phone":"+1 713 263 0595",
    "sg:postcode":"77024",
    "sg:province":"TX",
    "sg:tags":[
        "company",
        "holding"
    ],
    "wof:name":"Texex Energy Holdings LLC",
    "wof:placetype":"venue"
},
  "geometry": {"coordinates":[-95.482418,29.782091],"type":"Point"}
}