{
  "type": "Feature",
  "properties": {
    "iso:country":"US",
    "sg:address":"110 W Queen Isabella Blvd",
    "sg:city":"Port Isabel",
    "sg:classifiers":[
        {
            "category":"Real Estate",
            "subcategory":"Real Estate Agent",
            "type":"Services"
        }
    ],
    "sg:phone":"+1 956 943 7481",
    "sg:postcode":"78578",
    "sg:province":"TX",
    "wof:name":"Woolverton Realty & Assoc",
    "wof:placetype":"venue"
},
  "geometry": {"coordinates":[-97.211135,26.07503],"type":"Point"}
}