{
  "type": "Feature",
  "properties": {
    "iso:country":"US",
    "sg:address":"1504 W Bluff Rd",
    "sg:city":"Orange",
    "sg:classifiers":[
        {
            "category":"Manufacturing",
            "subcategory":"Tools & Machinery",
            "type":"Manufacturing & Wholesale Goods"
        }
    ],
    "sg:phone":"+1 409 886 1193",
    "sg:postcode":"77632",
    "sg:province":"TX",
    "sg:tags":[
        "repair",
        "mfg",
        "welding"
    ],
    "wof:name":"Specialty Manufacturing Co",
    "wof:placetype":"venue"
},
  "geometry": {"coordinates":[-93.740881,30.171967],"type":"Point"}
}