{
  "type": "Feature",
  "properties": {
    "iso:country":"US",
    "sg:address":"203 S Sunset Strip St",
    "sg:city":"Kenedy",
    "sg:classifiers":[
        {
            "category":"Food & Beverages",
            "subcategory":"Bakery",
            "type":"Retail Goods"
        }
    ],
    "sg:phone":"+1 830 583 2123",
    "sg:postcode":"78119",
    "sg:province":"TX",
    "sg:tags":[
        "doughnut"
    ],
    "wof:name":"Donut Palace",
    "wof:placetype":"venue"
},
  "geometry": {"coordinates":[-97.857868,28.812642],"type":"Point"}
}