{
  "type": "Feature",
  "properties": {
    "iso:country":"US",
    "sg:address":"5423 FM 3217",
    "sg:city":"Clyde",
    "sg:classifiers":[
        {
            "category":"Farming",
            "subcategory":"Livestock Farm",
            "type":"Manufacturing & Wholesale Goods"
        }
    ],
    "sg:phone":"+1 325 893 2120",
    "sg:postcode":"79510",
    "sg:province":"TX",
    "sg:tags":[
        "ranch",
        "beef",
        "feedlot",
        "cattle"
    ],
    "wof:name":"Edwards Hereford Ranch LLC",
    "wof:placetype":"venue"
},
  "geometry": {"coordinates":[-99.484419,32.340871],"type":"Point"}
}