{
  "type": "Feature",
  "properties": {
    "iso:country":"US",
    "sg:address":"1031 Navarro St",
    "sg:city":"San Antonio",
    "sg:classifiers":[
        {
            "category":"Government",
            "subcategory":"Office",
            "type":"Public Place"
        }
    ],
    "sg:phone":"+1 210 225 0404",
    "sg:postcode":"78205",
    "sg:province":"TX",
    "wof:name":"Weather Forecast",
    "wof:placetype":"venue"
},
  "geometry": {"coordinates":[-98.490252,29.430733],"type":"Point"}
}