{
  "type": "Feature",
  "properties": {
    "iso:country":"US",
    "sg:address":"5431 Bissonnet St",
    "sg:city":"Houston",
    "sg:classifiers":[
        {
            "category":"Autos & Motor Vehicles",
            "subcategory":"Auto Supplies",
            "type":"Retail Goods"
        }
    ],
    "sg:phone":"+1 713 666 5888",
    "sg:postcode":"77081",
    "sg:province":"TX",
    "wof:name":"B F Goodrich Tire Center",
    "wof:placetype":"venue"
},
  "geometry": {"coordinates":[-95.475174,29.703847],"type":"Point"}
}