{
  "type": "Feature",
  "properties": {
    "iso:country":"US",
    "sg:address":"911 S Bishop Rd",
    "sg:city":"Wake Village",
    "sg:classifiers":[
        {
            "category":"Insurance",
            "subcategory":"Insurance Agent",
            "type":"Services"
        }
    ],
    "sg:phone":"+1 903 334 8184",
    "sg:postcode":"75501",
    "sg:province":"TX",
    "wof:name":"Colonial Supplemental Ins",
    "wof:placetype":"venue"
},
  "geometry": {"coordinates":[-94.098045,33.412186],"type":"Point"}
}