{
  "type": "Feature",
  "properties": {
    "iso:country":"US",
    "sg:address":"1778 US Hwy 77",
    "sg:city":"Rockdale",
    "sg:classifiers":[
        {
            "category":"Professional",
            "type":"Services"
        }
    ],
    "sg:phone":"+1 512 446 5166",
    "sg:postcode":"76520",
    "sg:province":"TX",
    "wof:name":"Carrasales Biviano",
    "wof:placetype":"venue"
},
  "geometry": {"coordinates":[-96.962625,30.846559],"type":"Point"}
}