{
  "type": "Feature",
  "properties": {
    "iso:country":"US",
    "sg:address":"1535 Hawkins Blvd",
    "sg:city":"El Paso",
    "sg:classifiers":[
        {
            "category":"Professional",
            "subcategory":"Accounting & Tax Preparation",
            "type":"Services"
        }
    ],
    "sg:phone":"+1 915 581 8299",
    "sg:postcode":"79925",
    "sg:province":"TX",
    "sg:tags":[
        "return",
        "filing"
    ],
    "wof:name":"Jackson Hewitt Tax Svc",
    "wof:placetype":"venue"
},
  "geometry": {"coordinates":[-106.37156899999999,31.790549],"type":"Point"}
}