{
  "type": "Feature",
  "properties": {
    "iso:country":"US",
    "sg:address":"800 W Renner Rd",
    "sg:city":"Richardson",
    "sg:classifiers":[
        {
            "category":"Wholesale",
            "subcategory":"Non-durable Goods",
            "type":"Manufacturing & Wholesale Goods"
        }
    ],
    "sg:phone":"+1 972 680 3002",
    "sg:postcode":"75080",
    "sg:province":"TX",
    "sg:tags":[
        "packaging",
        "material",
        "broker",
        "for"
    ],
    "wof:name":"Mi-CAM Distribution",
    "wof:placetype":"venue"
},
  "geometry": {"coordinates":[-96.733773,32.997679],"type":"Point"}
}