{
  "type": "Feature",
  "properties": {
    "iso:country":"US",
    "sg:address":"902 E 5th St Ste 101",
    "sg:city":"Austin",
    "sg:classifiers":[
        {
            "category":"Shopping",
            "subcategory":"Jewelry",
            "type":"Retail Goods"
        }
    ],
    "sg:phone":"+1 512 493 0943",
    "sg:postcode":"78702",
    "sg:province":"TX",
    "sg:website":"www.deanfredrick.com",
    "wof:name":"Dean Fredrick Custom Jewelry",
    "wof:placetype":"venue"
},
  "geometry": {"coordinates":[-97.73392200000001,30.264528],"type":"Point"}
}