{
  "type": "Feature",
  "properties": {
    "iso:country":"US",
    "sg:address":"607 University Dr",
    "sg:city":"Fort Worth",
    "sg:classifiers":[
        {
            "category":"Building & Trades",
            "subcategory":"Construction",
            "type":"Services"
        }
    ],
    "sg:phone":"+1 817 332 7074",
    "sg:postcode":"76107",
    "sg:province":"TX",
    "sg:tags":[
        "roofing",
        "contractor"
    ],
    "wof:name":"Metroplex Roofing Contractors",
    "wof:placetype":"venue"
},
  "geometry": {"coordinates":[-97.361092,32.752199],"type":"Point"}
}