{
  "type": "Feature",
  "properties": {
    "iso:country":"US",
    "sg:address":"11100 Bill Hill Dr",
    "sg:city":"El Paso",
    "sg:classifiers":[
        {
            "category":"Professional",
            "subcategory":"Business Services",
            "type":"Services"
        }
    ],
    "sg:phone":"+1 915 479 2131",
    "sg:postcode":"79936",
    "sg:province":"TX",
    "sg:tags":[
        "interior",
        "consultant",
        "design",
        "decorator"
    ],
    "wof:name":"Aladino Decor",
    "wof:placetype":"venue"
},
  "geometry": {"coordinates":[-106.312138,31.763614],"type":"Point"}
}