{
  "type": "Feature",
  "properties": {
    "iso:country":"US",
    "sg:address":"408 E Scott St",
    "sg:city":"Gainesville",
    "sg:classifiers":[
        {
            "category":"Professional",
            "subcategory":"Business Services",
            "type":"Services"
        }
    ],
    "sg:phone":"+1 940 665 0644",
    "sg:postcode":"76240",
    "sg:province":"TX",
    "wof:name":"Mary E Trout",
    "wof:placetype":"venue"
},
  "geometry": {"coordinates":[-97.142657,33.628018],"type":"Point"}
}