{
  "type": "Feature",
  "properties": {
    "iso:country":"US",
    "sg:address":"719 W 2nd St",
    "sg:city":"Taylor",
    "sg:classifiers":[
        {
            "category":"Building & Trades",
            "subcategory":"Construction",
            "type":"Services"
        }
    ],
    "sg:phone":"+1 512 352 6301",
    "sg:postcode":"76574",
    "sg:province":"TX",
    "sg:tags":[
        "contractor"
    ],
    "wof:name":"C & C Construction Inc",
    "wof:placetype":"venue"
},
  "geometry": {"coordinates":[-97.416185,30.568078],"type":"Point"}
}