{
  "type": "Feature",
  "properties": {
    "iso:country":"US",
    "sg:address":"1818 Hamilton St",
    "sg:city":"Houston",
    "sg:classifiers":[
        {
            "category":"Autos & Motor Vehicles",
            "subcategory":"Fuel & Gas Station",
            "type":"Retail Goods"
        }
    ],
    "sg:phone":"+1 713 571 2377",
    "sg:postcode":"77003",
    "sg:province":"TX",
    "sg:tags":[
        "gasoline"
    ],
    "wof:name":"Hamilton Mobil Et",
    "wof:placetype":"venue"
},
  "geometry": {"coordinates":[-95.36219800000001,29.746201],"type":"Point"}
}