{
  "type": "Feature",
  "properties": {
    "iso:country":"US",
    "sg:address":"213 W Main St",
    "sg:city":"Llano",
    "sg:classifiers":[
        {
            "category":"Insurance",
            "subcategory":"Insurance Agent",
            "type":"Services"
        }
    ],
    "sg:phone":"+1 325 247 3072",
    "sg:postcode":"78643",
    "sg:province":"TX",
    "sg:website":"http://progressive.com",
    "wof:name":"Hutto & Dalchau Insurance Agency",
    "wof:placetype":"venue"
},
  "geometry": {"coordinates":[-98.67724,30.750301],"type":"Point"}
}