{
  "type": "Feature",
  "properties": {
    "iso:country":"US",
    "sg:address":"1421 Wilderness Trl",
    "sg:city":"Crowley",
    "sg:classifiers":[
        {
            "category":"Real Estate",
            "subcategory":"Real Estate Services",
            "type":"Services"
        }
    ],
    "sg:phone":"+1 817 447 2300",
    "sg:postcode":"76036",
    "sg:province":"TX",
    "wof:name":"Wayne Realty",
    "wof:placetype":"venue"
},
  "geometry": {"coordinates":[-97.351736,32.555004],"type":"Point"}
}