{
  "type": "Feature",
  "properties": {
    "iso:country":"US",
    "sg:address":"1508 Park Ave",
    "sg:city":"Victoria",
    "sg:classifiers":[
        {
            "category":"Social Services",
            "subcategory":"Child Care",
            "type":"Services"
        }
    ],
    "sg:phone":"+1 361 485 2401",
    "sg:postcode":"77901",
    "sg:province":"TX",
    "wof:name":"Little Flower Child Care",
    "wof:placetype":"venue"
},
  "geometry": {"coordinates":[-96.9875,28.815871],"type":"Point"}
}