{
  "type": "Feature",
  "properties": {
    "iso:country":"US",
    "sg:address":"7051 S Desert Blvd Ste D441",
    "sg:city":"Canutillo",
    "sg:classifiers":[
        {
            "category":"Manufacturing",
            "subcategory":"Leather Goods",
            "type":"Manufacturing & Wholesale Goods"
        }
    ],
    "sg:phone":"+1 915 877 3076",
    "sg:postcode":"79835",
    "sg:province":"TX",
    "wof:name":"Wilsons Leather Outlet",
    "wof:placetype":"venue"
},
  "geometry": {"coordinates":[-106.583395,31.916211],"type":"Point"}
}