{
  "type": "Feature",
  "properties": {
    "iso:country":"US",
    "sg:address":"14540 Brownsville St",
    "sg:city":"Houston",
    "sg:classifiers":[
        {
            "category":"Shopping Center",
            "type":"Public Place"
        }
    ],
    "sg:phone":"+1 713 453 4622",
    "sg:postcode":"77015",
    "sg:province":"TX",
    "sg:tags":[
        "flea",
        "market"
    ],
    "wof:name":"Francisco Trujillo & Glor",
    "wof:placetype":"venue"
},
  "geometry": {"coordinates":[-95.16544399999999,29.782322],"type":"Point"}
}