{
  "type": "Feature",
  "properties": {
    "iso:country":"US",
    "sg:address":"824 E Expy 83",
    "sg:city":"Mission",
    "sg:classifiers":[
        {
            "category":"Social Services",
            "subcategory":"Child Care",
            "type":"Services"
        }
    ],
    "sg:phone":"+1 956 585 5993",
    "sg:postcode":"78572",
    "sg:province":"TX",
    "wof:name":"Play Learn Construct",
    "wof:placetype":"venue"
},
  "geometry": {"coordinates":[-98.319131,26.200398],"type":"Point"}
}