{
  "type": "Feature",
  "properties": {
    "iso:country":"US",
    "sg:address":"5138 Village Crst",
    "sg:city":"San Antonio",
    "sg:classifiers":[
        {
            "category":"Professional",
            "subcategory":"Secretarial Services",
            "type":"Services"
        }
    ],
    "sg:phone":"+1 210 655 9066",
    "sg:postcode":"78218",
    "sg:province":"TX",
    "sg:tags":[
        "reporting"
    ],
    "wof:name":"Dtas Med Transcription Svc",
    "wof:placetype":"venue"
},
  "geometry": {"coordinates":[-98.389962,29.489392],"type":"Point"}
}