{
  "type": "Feature",
  "properties": {
    "iso:country":"US",
    "sg:address":"211 W Sealy St",
    "sg:city":"Alvin",
    "sg:classifiers":[
        {
            "category":"Banks & Credit Unions",
            "subcategory":"Investment Brokerage",
            "type":"Services"
        }
    ],
    "sg:phone":"+1 281 585 4353",
    "sg:postcode":"77511",
    "sg:province":"TX",
    "sg:tags":[
        "security"
    ],
    "wof:name":"Morgan Stanley",
    "wof:placetype":"venue"
},
  "geometry": {"coordinates":[-95.24576,29.423717],"type":"Point"}
}