{
  "type": "Feature",
  "properties": {
    "iso:country":"US",
    "sg:address":"6704 Cedar Shadow Dr",
    "sg:city":"Dallas",
    "sg:classifiers":[
        {
            "category":"Professional",
            "subcategory":"Business Services",
            "type":"Services"
        }
    ],
    "sg:phone":"+1 972 780 7779",
    "sg:postcode":"75236",
    "sg:province":"TX",
    "wof:name":"Putergal Computing",
    "wof:placetype":"venue"
},
  "geometry": {"coordinates":[-96.93613499999999,32.666685],"type":"Point"}
}