{
  "type": "Feature",
  "properties": {
    "iso:country":"US",
    "sg:address":"2007 Quintana Rd",
    "sg:city":"San Antonio",
    "sg:classifiers":[
        {
            "category":"Retail",
            "subcategory":"Auto Repair",
            "type":"Services"
        }
    ],
    "sg:phone":"+1 210 922 5127",
    "sg:postcode":"78211",
    "sg:province":"TX",
    "sg:tags":[
        "body",
        "automobile",
        "painting"
    ],
    "wof:name":"V & M Paint & Body Shop Inc",
    "wof:placetype":"venue"
},
  "geometry": {"coordinates":[-98.56025,29.367464],"type":"Point"}
}