{
  "type": "Feature",
  "properties": {
    "iso:country":"US",
    "sg:address":"7205 Bellerive Dr",
    "sg:city":"Houston",
    "sg:classifiers":[
        {
            "category":"Food & Beverages",
            "subcategory":"Groceries & Convenience Stores",
            "type":"Retail Goods"
        }
    ],
    "sg:phone":"+1 713 977 3330",
    "sg:postcode":"77036",
    "sg:province":"TX",
    "wof:name":"Step-N-Go Food Stores",
    "wof:placetype":"venue"
},
  "geometry": {"coordinates":[-95.5093,29.7127],"type":"Point"}
}