{
  "type": "Feature",
  "properties": {
    "iso:country":"US",
    "sg:address":"471 Sawdust Rd",
    "sg:city":"Spring",
    "sg:classifiers":[
        {
            "category":"Shopping",
            "subcategory":"Clothing, Apparel, & Fashions",
            "type":"Retail Goods"
        }
    ],
    "sg:phone":"+1 281 362 9388",
    "sg:postcode":"77380",
    "sg:province":"TX",
    "sg:tags":[
        "wear"
    ],
    "wof:name":"Animal Crackers Kidswear",
    "wof:placetype":"venue"
},
  "geometry": {"coordinates":[-95.452838,30.126651],"type":"Point"}
}