{
  "type": "Feature",
  "properties": {
    "iso:country":"US",
    "sg:address":"3450 Roy Orr Blvd",
    "sg:city":"Grand Prairie",
    "sg:classifiers":[
        {
            "category":"Freight",
            "type":"Transportation"
        }
    ],
    "sg:phone":"+1 972 313 1995",
    "sg:postcode":"75050",
    "sg:province":"TX",
    "sg:tags":[
        "warehouse"
    ],
    "sg:website":"www.standardcorp.com",
    "wof:name":"Standard Corp",
    "wof:placetype":"venue"
},
  "geometry": {"coordinates":[-97.030072,32.805217],"type":"Point"}
}