{
  "type": "Feature",
  "properties": {
    "iso:country":"US",
    "sg:address":"1319 Heathwick Ln",
    "sg:city":"Houston",
    "sg:classifiers":[
        {
            "category":"Organizations",
            "subcategory":"Membership Organization",
            "type":"Services"
        }
    ],
    "sg:phone":"+1 281 558 8252",
    "sg:postcode":"77043",
    "sg:province":"TX",
    "wof:name":"Baird Science Foundation",
    "wof:placetype":"venue"
},
  "geometry": {"coordinates":[-95.58784300000001,29.789257],"type":"Point"}
}