{
  "type": "Feature",
  "properties": {
    "iso:country":"US",
    "sg:address":"14 W Jefferson St",
    "sg:city":"Brownsville",
    "sg:classifiers":[
        {
            "category":"Retail",
            "subcategory":"Laundry & Dry Cleaning",
            "type":"Services"
        }
    ],
    "sg:phone":"+1 956 504 3776",
    "sg:postcode":"78520",
    "sg:province":"TX",
    "sg:tags":[
        "personal",
        "drycleaning",
        "plant"
    ],
    "wof:name":"Rex Cleaners & Tuxedo Rentals",
    "wof:placetype":"venue"
},
  "geometry": {"coordinates":[-97.504705,25.910988],"type":"Point"}
}