{
  "type": "Feature",
  "properties": {
    "iso:country":"US",
    "sg:address":"6622 Eastview Dr",
    "sg:city":"Sachse",
    "sg:classifiers":[
        {
            "category":"Wholesale",
            "subcategory":"Machinery & Supplies",
            "type":"Manufacturing & Wholesale Goods"
        }
    ],
    "sg:phone":"+1 972 475 3218",
    "sg:postcode":"75048",
    "sg:province":"TX",
    "sg:tags":[
        "equipment",
        "irrigation",
        "system"
    ],
    "wof:name":"S B Irrigation",
    "wof:placetype":"venue"
},
  "geometry": {"coordinates":[-96.558966,32.95343],"type":"Point"}
}