{
  "type": "Feature",
  "properties": {
    "iso:country":"US",
    "sg:address":"6719 Theall Rd",
    "sg:city":"Houston",
    "sg:classifiers":[
        {
            "category":"Building & Trades",
            "subcategory":"Construction",
            "type":"Services"
        }
    ],
    "sg:phone":"+1 281 537 8657",
    "sg:postcode":"77066",
    "sg:province":"TX",
    "sg:tags":[
        "contractor"
    ],
    "wof:name":"Ecosupplies",
    "wof:placetype":"venue"
},
  "geometry": {"coordinates":[-95.524641,29.965029],"type":"Point"}
}