{
  "type": "Feature",
  "properties": {
    "iso:country":"US",
    "sg:address":"1306 E Euless Blvd",
    "sg:city":"Euless",
    "sg:classifiers":[
        {
            "category":"Building & Trades",
            "subcategory":"Cleaning & Sanitation",
            "type":"Services"
        }
    ],
    "sg:phone":"+1 817 354 8700",
    "sg:postcode":"76040",
    "sg:province":"TX",
    "sg:tags":[
        "ventilating",
        "system"
    ],
    "wof:name":"MBA Technologies Inc",
    "wof:placetype":"venue"
},
  "geometry": {"coordinates":[-97.103572,32.827405],"type":"Point"}
}