{
  "type": "Feature",
  "properties": {
    "iso:country":"US",
    "sg:address":"1026 E Evergreen St",
    "sg:city":"Mexia",
    "sg:classifiers":[
        {
            "category":"Travel",
            "subcategory":"Travel Agent",
            "type":"Entertainment"
        }
    ],
    "sg:phone":"+1 254 562 5883",
    "sg:postcode":"76667",
    "sg:province":"TX",
    "sg:tags":[
        "agency"
    ],
    "wof:name":"Boomers Travel Raters",
    "wof:placetype":"venue"
},
  "geometry": {"coordinates":[-96.468338,31.6767],"type":"Point"}
}