{
  "type": "Feature",
  "properties": {
    "iso:country":"US",
    "sg:address":"5200 Bilindsay Rd",
    "sg:city":"Seagoville",
    "sg:classifiers":[
        {
            "category":"Building & Trades",
            "subcategory":"Electrical",
            "type":"Services"
        }
    ],
    "sg:phone":"+1 972 476 2627",
    "sg:postcode":"75159",
    "sg:province":"TX",
    "sg:tags":[
        "industrial",
        "electrician",
        "contractors-commercial",
        "electric"
    ],
    "wof:name":"Bristol Electrical Contractors Inc",
    "wof:placetype":"venue"
},
  "geometry": {"coordinates":[-96.540274,32.557966],"type":"Point"}
}