{
  "type": "Feature",
  "properties": {
    "iso:country":"US",
    "sg:address":"212 Lindberg Ave",
    "sg:city":"Mcallen",
    "sg:classifiers":[
        {
            "category":"Shopping",
            "subcategory":"Pharmacy",
            "type":"Retail Goods"
        }
    ],
    "sg:phone":"+1 956 630 6465",
    "sg:postcode":"78501",
    "sg:province":"TX",
    "sg:tags":[
        "equipment"
    ],
    "wof:name":"Saenz Medical Pharmacy",
    "wof:placetype":"venue"
},
  "geometry": {"coordinates":[-98.227536,26.192071],"type":"Point"}
}