{
  "type": "Feature",
  "properties": {
    "iso:country":"US",
    "sg:address":"821 Office Park Cir",
    "sg:city":"Lewisville",
    "sg:classifiers":[
        {
            "category":"Wholesale",
            "subcategory":"Machinery & Supplies",
            "type":"Manufacturing & Wholesale Goods"
        },
        {
            "category":"Autos & Motor Vehicles",
            "subcategory":"Automobile Sales",
            "type":"Retail Goods"
        }
    ],
    "sg:phone":"+1 972 353 4100",
    "sg:postcode":"75057",
    "sg:province":"TX",
    "sg:tags":[
        "equipment",
        "aircraft",
        "parts",
        "transportation"
    ],
    "wof:name":"Aerotex International Inc",
    "wof:placetype":"venue"
},
  "geometry": {"coordinates":[-96.99790299999999,33.052363],"type":"Point"}
}