{
  "type": "Feature",
  "properties": {
    "iso:country":"US",
    "sg:address":"11333 Fountain Lake Dr",
    "sg:city":"Stafford",
    "sg:classifiers":[
        {
            "category":"Professional",
            "type":"Services"
        }
    ],
    "sg:phone":"+1 281 340 2225",
    "sg:postcode":"77477",
    "sg:province":"TX",
    "sg:tags":[
        "establishment"
    ],
    "wof:name":"Impact Color",
    "wof:placetype":"venue"
},
  "geometry": {"coordinates":[-95.584582,29.638921],"type":"Point"}
}