{
  "type": "Feature",
  "properties": {
    "iso:country":"US",
    "sg:address":"108 N Dallas Ave",
    "sg:city":"Lancaster",
    "sg:classifiers":[
        {
            "category":"Building & Trades",
            "subcategory":"Plumbing",
            "type":"Services"
        }
    ],
    "sg:phone":"+1 972 227 7453",
    "sg:postcode":"75146",
    "sg:province":"TX",
    "sg:tags":[
        "product",
        "management",
        "energy",
        "system"
    ],
    "wof:name":"Poco Energy Group",
    "wof:placetype":"venue"
},
  "geometry": {"coordinates":[-96.75654400000001,32.59281],"type":"Point"}
}