{
  "type": "Feature",
  "properties": {
    "iso:country":"US",
    "sg:address":"9000 Lantana Way",
    "sg:city":"Austin",
    "sg:classifiers":[
        {
            "category":"Home & Garden",
            "subcategory":"Furniture",
            "type":"Retail Goods"
        }
    ],
    "sg:phone":"+1 512 301 6795",
    "sg:postcode":"78749",
    "sg:province":"TX",
    "wof:name":"Texo Furniture Group Inc",
    "wof:placetype":"venue"
},
  "geometry": {"coordinates":[-97.87997300000001,30.209142],"type":"Point"}
}