{
  "type": "Feature",
  "properties": {
    "iso:country":"US",
    "sg:address":"5315 Walzem Rd",
    "sg:city":"San Antonio",
    "sg:classifiers":[
        {
            "category":"Retail",
            "subcategory":"Repair Shop",
            "type":"Services"
        }
    ],
    "sg:phone":"+1 210 656 6700",
    "sg:postcode":"78218",
    "sg:province":"TX",
    "sg:tags":[
        "machine",
        "sewing"
    ],
    "wof:name":"Creative Sewing Ctr",
    "wof:placetype":"venue"
},
  "geometry": {"coordinates":[-98.381933,29.51036],"type":"Point"}
}