{
  "type": "Feature",
  "properties": {
    "iso:country":"US",
    "sg:address":"615 N Washington Ave",
    "sg:city":"Livingston",
    "sg:classifiers":[
        {
            "category":"Professional",
            "subcategory":"Management & Consulting",
            "type":"Services"
        }
    ],
    "sg:phone":"+1 936 327 8447",
    "sg:postcode":"77351",
    "sg:province":"TX",
    "sg:tags":[
        "business"
    ],
    "wof:name":"Greater Eastex Credit Bureau",
    "wof:placetype":"venue"
},
  "geometry": {"coordinates":[-94.933117,30.713294],"type":"Point"}
}