{
  "type": "Feature",
  "properties": {
    "iso:country":"US",
    "sg:address":"2608 Oakwood Dr",
    "sg:city":"Bedford",
    "sg:classifiers":[
        {
            "category":"Professional",
            "subcategory":"Business Services",
            "type":"Services"
        }
    ],
    "sg:phone":"+1 817 354 1757",
    "sg:postcode":"76021",
    "sg:province":"TX",
    "wof:name":"Pjs Sales & Marketing",
    "wof:placetype":"venue"
},
  "geometry": {"coordinates":[-97.10466,32.850415],"type":"Point"}
}