{
  "type": "Feature",
  "properties": {
    "iso:country":"US",
    "sg:address":"238 N 4th St",
    "sg:city":"Wills Point",
    "sg:classifiers":[
        {
            "category":"Professional",
            "subcategory":"Accounting & Tax Preparation",
            "type":"Services"
        }
    ],
    "sg:phone":"+1 903 873 2680",
    "sg:postcode":"75169",
    "sg:province":"TX",
    "sg:tags":[
        "return"
    ],
    "wof:name":"Wilson Accounting & Tax Svc",
    "wof:placetype":"venue"
},
  "geometry": {"coordinates":[-96.007919,32.709771],"type":"Point"}
}