{
  "type": "Feature",
  "properties": {
    "iso:country":"US",
    "sg:address":"2425 Oakridge Dr",
    "sg:city":"Mesquite",
    "sg:classifiers":[
        {
            "category":"Building & Trades",
            "subcategory":"Construction",
            "type":"Services"
        }
    ],
    "sg:phone":"+1 972 285 9248",
    "sg:postcode":"75180",
    "sg:province":"TX",
    "sg:tags":[
        "general",
        "contractor"
    ],
    "wof:name":"Diamond F Commercial Constr",
    "wof:placetype":"venue"
},
  "geometry": {"coordinates":[-96.62979900000001,32.734893],"type":"Point"}
}