{
  "type": "Feature",
  "properties": {
    "iso:country":"US",
    "sg:address":"5608 Montclair Dr",
    "sg:city":"Colleyville",
    "sg:classifiers":[
        {
            "category":"Professional",
            "subcategory":"Computer Services",
            "type":"Services"
        }
    ],
    "sg:phone":"+1 817 907 3573",
    "sg:postcode":"76034",
    "sg:province":"TX",
    "sg:tags":[
        "publisher",
        "developer",
        "software"
    ],
    "wof:name":"Staffmentor, Inc",
    "wof:placetype":"venue"
},
  "geometry": {"coordinates":[-97.134857,32.89094],"type":"Point"}
}