{
  "type": "Feature",
  "properties": {
    "iso:country":"US",
    "sg:address":"3601 E Highway 67",
    "sg:city":"Cleburne",
    "sg:classifiers":[
        {
            "category":"Retail",
            "subcategory":"Storage",
            "type":"Services"
        }
    ],
    "sg:phone":"+1 817 558 3971",
    "sg:postcode":"76031",
    "sg:province":"TX",
    "sg:tags":[
        "self"
    ],
    "wof:name":"Keene Self-Storage",
    "wof:placetype":"venue"
},
  "geometry": {"coordinates":[-97.312404,32.392044],"type":"Point"}
}