{
  "type": "Feature",
  "properties": {
    "iso:country":"US",
    "sg:address":"1014 Reynaldo St",
    "sg:city":"Cedar Park",
    "sg:classifiers":[
        {
            "category":"Professional",
            "subcategory":"Business Services",
            "type":"Services"
        }
    ],
    "sg:phone":"+1 512 259 3972",
    "sg:postcode":"78613",
    "sg:province":"TX",
    "wof:name":"Circuit Board Design Services",
    "wof:placetype":"venue"
},
  "geometry": {"coordinates":[-97.844915,30.521037],"type":"Point"}
}