{
  "type": "Feature",
  "properties": {
    "iso:country":"US",
    "sg:address":"9900 Gray Blvd",
    "sg:city":"Austin",
    "sg:classifiers":[
        {
            "category":"Education",
            "subcategory":"School",
            "type":"Public Place"
        }
    ],
    "sg:phone":"+1 512 339 0993",
    "sg:postcode":"78758",
    "sg:province":"TX",
    "wof:name":"Central Texas Ac & Refrigeration School",
    "wof:placetype":"venue"
},
  "geometry": {"coordinates":[-97.71278599999999,30.378278],"type":"Point"}
}