{
  "type": "Feature",
  "properties": {
    "iso:country":"US",
    "sg:address":"1809 Bell St",
    "sg:city":"Harlingen",
    "sg:classifiers":[
        {
            "category":"Social Services",
            "type":"Services"
        }
    ],
    "sg:phone":"+1 956 425 9276",
    "sg:postcode":"78550",
    "sg:province":"TX",
    "sg:tags":[
        "care",
        "center",
        "day"
    ],
    "wof:name":"TLC Central Kitchen",
    "wof:placetype":"venue"
},
  "geometry": {"coordinates":[-97.672882,26.174446],"type":"Point"}
}