{
  "type": "Feature",
  "properties": {
    "iso:country":"US",
    "sg:address":"2100 Atkinson Dr",
    "sg:city":"Lufkin",
    "sg:classifiers":[
        {
            "category":"Professional",
            "subcategory":"Accounting & Tax Preparation",
            "type":"Services"
        }
    ],
    "sg:phone":"+1 936 634 9472",
    "sg:postcode":"75901",
    "sg:province":"TX",
    "sg:tags":[
        "return"
    ],
    "wof:name":"Angelina Tax Express",
    "wof:placetype":"venue"
},
  "geometry": {"coordinates":[-94.701628,31.3508],"type":"Point"}
}