{
  "type": "Feature",
  "properties": {
    "iso:country":"US",
    "sg:address":"5604 Exeter Dr",
    "sg:city":"Richardson",
    "sg:classifiers":[
        {
            "category":"Recreation",
            "type":"Entertainment"
        }
    ],
    "sg:phone":"+1 972 644 8774",
    "sg:postcode":"75082",
    "sg:province":"TX",
    "sg:tags":[
        "club",
        "membership"
    ],
    "wof:name":"Wise Imvestment Club of Texas",
    "wof:placetype":"venue"
},
  "geometry": {"coordinates":[-96.618596,32.996761],"type":"Point"}
}