{
  "type": "Feature",
  "properties": {
    "iso:country":"US",
    "sg:address":"715 State Hwy 6n Bus",
    "sg:city":"Marlin",
    "sg:classifiers":[
        {
            "category":"Retail",
            "subcategory":"Auto Repair",
            "type":"Services"
        }
    ],
    "sg:phone":"+1 254 883 2829",
    "sg:postcode":"76661",
    "sg:province":"TX",
    "sg:tags":[
        "general"
    ],
    "wof:name":"David Easter Auto Repair",
    "wof:placetype":"venue"
},
  "geometry": {"coordinates":[-96.899445,31.297943],"type":"Point"}
}