{
  "type": "Feature",
  "properties": {
    "iso:country":"US",
    "sg:address":"7045 N 5th St",
    "sg:city":"Mcallen",
    "sg:classifiers":[
        {
            "category":"Building & Trades",
            "subcategory":"Construction",
            "type":"Services"
        }
    ],
    "sg:phone":"+1 956 664 1105",
    "sg:postcode":"78504",
    "sg:province":"TX",
    "sg:tags":[
        "residential"
    ],
    "wof:name":"Troyo Design Group",
    "wof:placetype":"venue"
},
  "geometry": {"coordinates":[-98.21423299999999,26.266558],"type":"Point"}
}