{
  "type": "Feature",
  "properties": {
    "iso:country":"US",
    "sg:address":"1502 Cascade Ct",
    "sg:city":"Midland",
    "sg:classifiers":[
        {
            "category":"Professional",
            "type":"Services"
        }
    ],
    "sg:phone":"+1 432 697 6446",
    "sg:postcode":"79703",
    "sg:province":"TX",
    "sg:tags":[
        "establishment"
    ],
    "wof:name":"Nabisco",
    "wof:placetype":"venue"
},
  "geometry": {"coordinates":[-102.130841,32.001466],"type":"Point"}
}