{
  "type": "Feature",
  "properties": {
    "iso:country":"US",
    "sg:address":"120 E 8th St",
    "sg:city":"Georgetown",
    "sg:classifiers":[
        {
            "category":"Professional",
            "subcategory":"Management & Consulting",
            "type":"Services"
        }
    ],
    "sg:phone":"+1 512 863 5514",
    "sg:postcode":"78626",
    "sg:province":"TX",
    "sg:tags":[
        "consultant",
        "educational"
    ],
    "wof:name":"Experiential Challenge Program",
    "wof:placetype":"venue"
},
  "geometry": {"coordinates":[-97.676857,30.63653],"type":"Point"}
}