{
  "type": "Feature",
  "properties": {
    "iso:country":"US",
    "sg:address":"211 E Austin",
    "sg:city":"Austin",
    "sg:classifiers":[
        {
            "category":"Deli",
            "type":"Food & Drink"
        },
        {
            "category":"Food & Beverages",
            "subcategory":"Bakery",
            "type":"Retail Goods"
        }
    ],
    "sg:phone":"+1 512 394 7945",
    "sg:postcode":"78701",
    "sg:province":"TX",
    "sg:tags":[
        "sandwich"
    ],
    "wof:name":"DO Good Dell",
    "wof:placetype":"venue"
},
  "geometry": {"coordinates":[-97.70804200000001,30.334648],"type":"Point"}
}