{
  "type": "Feature",
  "properties": {
    "iso:country":"US",
    "sg:address":"3700 Cemetery Hill Rd",
    "sg:city":"Carrollton",
    "sg:classifiers":[
        {
            "category":"Wholesale",
            "subcategory":"Plants",
            "type":"Manufacturing & Wholesale Goods"
        }
    ],
    "sg:phone":"+1 972 492 3734",
    "sg:postcode":"75007",
    "sg:province":"TX",
    "sg:tags":[
        "nursery",
        "tree"
    ],
    "wof:name":"Plant Hunters",
    "wof:placetype":"venue"
},
  "geometry": {"coordinates":[-96.8913,33.013149],"type":"Point"}
}