{
  "type": "Feature",
  "properties": {
    "iso:country":"US",
    "sg:address":"4301 Red Cloud Dr",
    "sg:city":"Austin",
    "sg:classifiers":[
        {
            "category":"Professional",
            "type":"Services"
        }
    ],
    "sg:phone":"+1 512 338 5306",
    "sg:postcode":"78759",
    "sg:province":"TX",
    "wof:name":"Point Click Drag & Drop",
    "wof:placetype":"venue"
},
  "geometry": {"coordinates":[-97.732885,30.410465],"type":"Point"}
}