{
  "type": "Feature",
  "properties": {
    "iso:country":"US",
    "sg:address":"9400 Garth Rd",
    "sg:city":"Baytown",
    "sg:classifiers":[
        {
            "category":"Shopping",
            "subcategory":"Clothing, Apparel, & Fashions",
            "type":"Retail Goods"
        }
    ],
    "sg:phone":"+1 281 421 7954",
    "sg:postcode":"77521",
    "sg:province":"TX",
    "sg:tags":[
        "tailor"
    ],
    "wof:name":"City Trends",
    "wof:placetype":"venue"
},
  "geometry": {"coordinates":[-94.986401,29.830719],"type":"Point"}
}