{
  "type": "Feature",
  "properties": {
    "iso:country":"US",
    "sg:address":"7402 Rockyridge Dr",
    "sg:city":"Frisco",
    "sg:classifiers":[
        {
            "category":"Manufacturing",
            "subcategory":"Paper Products",
            "type":"Manufacturing & Wholesale Goods"
        }
    ],
    "sg:phone":"+1 972 377 0550",
    "sg:postcode":"75035",
    "sg:province":"TX",
    "wof:name":"I P Fine Paper",
    "wof:placetype":"venue"
},
  "geometry": {"coordinates":[-96.776584,33.140186],"type":"Point"}
}