{
  "type": "Feature",
  "properties": {
    "iso:country":"US",
    "sg:address":"1410 S 3rd St",
    "sg:city":"Mabank",
    "sg:classifiers":[
        {
            "category":"Recreation",
            "type":"Entertainment"
        }
    ],
    "sg:phone":"+1 903 887 7706",
    "sg:postcode":"75147",
    "sg:province":"TX",
    "sg:tags":[
        "instruction",
        "gymnastic"
    ],
    "wof:name":"Paramount Center",
    "wof:placetype":"venue"
},
  "geometry": {"coordinates":[-96.10429600000001,32.356074],"type":"Point"}
}