{
  "type": "Feature",
  "properties": {
    "iso:country":"US",
    "sg:address":"313 Shady Hill Dr",
    "sg:city":"Richardson",
    "sg:classifiers":[
        {
            "category":"Wholesale",
            "subcategory":"Toys & Hobbies",
            "type":"Manufacturing & Wholesale Goods"
        }
    ],
    "sg:phone":"+1 972 238 1413",
    "sg:postcode":"75080",
    "sg:province":"TX",
    "sg:tags":[
        "supply"
    ],
    "wof:name":"Rmp & Assoc Inc",
    "wof:placetype":"venue"
},
  "geometry": {"coordinates":[-96.71881,32.993236],"type":"Point"}
}