{
  "type": "Feature",
  "properties": {
    "iso:country":"US",
    "sg:address":"6632 Avalon Dr",
    "sg:city":"Watauga",
    "sg:classifiers":[
        {
            "category":"Freight",
            "type":"Transportation"
        }
    ],
    "sg:phone":"+1 817 821 7714",
    "sg:postcode":"76148",
    "sg:province":"TX",
    "wof:name":"Troy Thomas Transportation",
    "wof:placetype":"venue"
},
  "geometry": {"coordinates":[-97.23807100000001,32.862247],"type":"Point"}
}