{
  "type": "Feature",
  "properties": {
    "iso:country":"US",
    "sg:address":"2627 Live Oak St",
    "sg:city":"San Angelo",
    "sg:classifiers":[
        {
            "category":"Professional",
            "subcategory":"Business Services",
            "type":"Services"
        }
    ],
    "sg:phone":"+1 325 942 8747",
    "sg:postcode":"76901",
    "sg:province":"TX",
    "wof:name":"Delta Enterprises",
    "wof:placetype":"venue"
},
  "geometry": {"coordinates":[-100.468732,31.445069],"type":"Point"}
}