{
  "type": "Feature",
  "properties": {
    "iso:country":"US",
    "sg:address":"22802 Market Square Ln",
    "sg:city":"Katy",
    "sg:classifiers":[
        {
            "category":"Travel",
            "subcategory":"Hotels & Motels",
            "type":"Entertainment"
        }
    ],
    "sg:phone":"+1 281 636 6398",
    "sg:postcode":"77449",
    "sg:province":"TX",
    "wof:name":"Doray",
    "wof:placetype":"venue"
},
  "geometry": {"coordinates":[-95.768069,29.802521],"type":"Point"}
}