{
  "type": "Feature",
  "properties": {
    "iso:country":"US",
    "sg:address":"1906 N Bell Blvd",
    "sg:city":"Cedar Park",
    "sg:classifiers":[
        {
            "category":"Restaurant",
            "type":"Food & Drink"
        }
    ],
    "sg:phone":"+1 512 259 0105",
    "sg:postcode":"78613",
    "sg:province":"TX",
    "wof:name":"Subway Sandwiches & Salads",
    "wof:placetype":"venue"
},
  "geometry": {"coordinates":[-97.83469599999999,30.531746],"type":"Point"}
}