{
  "type": "Feature",
  "properties": {
    "iso:country":"US",
    "sg:address":"1419 Glenwood Dr",
    "sg:city":"Laredo",
    "sg:classifiers":[
        {
            "category":"Health Services",
            "subcategory":"Nursing And Care Facility",
            "type":"Services"
        }
    ],
    "sg:phone":"+1 956 717 9384",
    "sg:postcode":"78045",
    "sg:province":"TX",
    "sg:tags":[
        "skilled"
    ],
    "wof:name":"Independent Nursing",
    "wof:placetype":"venue"
},
  "geometry": {"coordinates":[-99.470797,27.596019],"type":"Point"}
}