{
  "type": "Feature",
  "properties": {
    "iso:country":"US",
    "sg:address":"1500 S Martin Luther King Jr Blvd",
    "sg:city":"Longview",
    "sg:classifiers":[
        {
            "category":"Building & Trades",
            "subcategory":"Construction",
            "type":"Services"
        }
    ],
    "sg:phone":"+1 903 236 8126",
    "sg:postcode":"75602",
    "sg:province":"TX",
    "sg:tags":[
        "maintenance",
        "contractor"
    ],
    "wof:name":"Maintenance Shop",
    "wof:placetype":"venue"
},
  "geometry": {"coordinates":[-94.71629299999999,32.472829],"type":"Point"}
}