{
  "type": "Feature",
  "properties": {
    "iso:country":"US",
    "sg:address":"310 Bull Run Dr",
    "sg:city":"League City",
    "sg:classifiers":[
        {
            "category":"Professional",
            "subcategory":"Lawyer & Legal Services",
            "type":"Services"
        }
    ],
    "sg:phone":"+1 281 332 5781",
    "sg:postcode":"77573",
    "sg:province":"TX",
    "wof:name":"Asher Hand Crafts",
    "wof:placetype":"venue"
},
  "geometry": {"coordinates":[-95.12332499999999,29.498091],"type":"Point"}
}