{
  "type": "Feature",
  "properties": {
    "iso:country":"US",
    "sg:address":"210 S Cedar Ridge Dr",
    "sg:city":"Duncanville",
    "sg:classifiers":[
        {
            "category":"Organizations",
            "subcategory":"Religious Organization",
            "type":"Services"
        }
    ],
    "sg:phone":"+1 972 283 9199",
    "sg:postcode":"75116",
    "sg:province":"TX",
    "wof:name":"Wentroble Christian Ministries",
    "wof:placetype":"venue"
},
  "geometry": {"coordinates":[-96.925499,32.649601],"type":"Point"}
}