{
  "type": "Feature",
  "properties": {
    "iso:country":"US",
    "sg:address":"901 Tahoka Rd",
    "sg:city":"Brownfield",
    "sg:classifiers":[
        {
            "category":"Health Services",
            "subcategory":"Doctor",
            "type":"Services"
        }
    ],
    "sg:phone":"+1 806 637 2406",
    "sg:postcode":"79316",
    "sg:province":"TX",
    "wof:name":"Ronald E Debusk DDS",
    "wof:placetype":"venue"
},
  "geometry": {"coordinates":[-102.26600999999999,33.181069],"type":"Point"}
}