{
  "type": "Feature",
  "properties": {
    "iso:country":"US",
    "sg:address":"940 E Clarendon Dr",
    "sg:city":"Dallas",
    "sg:classifiers":[
        {
            "category":"Retail",
            "subcategory":"Repair Shop",
            "type":"Services"
        },
        {
            "category":"Shopping",
            "subcategory":"Musical Instruments",
            "type":"Retail Goods"
        }
    ],
    "sg:phone":"+1 214 942 0575",
    "sg:postcode":"75203",
    "sg:province":"TX",
    "sg:tags":[
        "repairing",
        "equipment",
        "piano",
        "refinishing"
    ],
    "wof:name":"Baldwin Family Music Center",
    "wof:placetype":"venue"
},
  "geometry": {"coordinates":[-96.810278,32.74378],"type":"Point"}
}