{
  "type": "Feature",
  "properties": {
    "iso:country":"US",
    "sg:address":"5307 Beechnut St",
    "sg:city":"Houston",
    "sg:classifiers":[
        {
            "category":"Professional",
            "subcategory":"Advertising",
            "type":"Services"
        }
    ],
    "sg:phone":"+1 713 667 6194",
    "sg:postcode":"77096",
    "sg:province":"TX",
    "sg:tags":[
        "mailing",
        "list"
    ],
    "wof:name":"Billie Carr & Assoc",
    "wof:placetype":"venue"
},
  "geometry": {"coordinates":[-95.479212,29.689023],"type":"Point"}
}