{
  "type": "Feature",
  "properties": {
    "iso:country":"US",
    "sg:address":"300 S Center St",
    "sg:city":"Forney",
    "sg:classifiers":[
        {
            "category":"Manufacturing",
            "subcategory":"Printing",
            "type":"Manufacturing & Wholesale Goods"
        }
    ],
    "sg:phone":"+1 972 564 3303",
    "sg:postcode":"75126",
    "sg:province":"TX",
    "sg:tags":[
        "periodical"
    ],
    "wof:name":"Mesquite Providence Sav Mag",
    "wof:placetype":"venue"
},
  "geometry": {"coordinates":[-96.47130799999999,32.745234],"type":"Point"}
}