{
  "type": "Feature",
  "properties": {
    "iso:country":"US",
    "sg:address":"2400 Ave F",
    "sg:city":"Del Rio",
    "sg:classifiers":[
        {
            "category":"Government",
            "subcategory":"Office",
            "type":"Public Place"
        }
    ],
    "sg:phone":"+1 830 774 2589",
    "sg:postcode":"78840",
    "sg:province":"TX",
    "sg:tags":[
        "armed",
        "force",
        "recruiting"
    ],
    "wof:name":"US Army Recruiting",
    "wof:placetype":"venue"
},
  "geometry": {"coordinates":[-100.905173,29.393718],"type":"Point"}
}