{
  "type": "Feature",
  "properties": {
    "iso:country":"US",
    "sg:address":"130 Gonzales St",
    "sg:city":"Paige",
    "sg:classifiers":[
        {
            "category":"Autos & Motor Vehicles",
            "subcategory":"Auto Supplies",
            "type":"Retail Goods"
        }
    ],
    "sg:phone":"+1 512 253 6222",
    "sg:postcode":"78640",
    "sg:province":"TX",
    "sg:tags":[
        "wheel",
        "cover"
    ],
    "wof:name":"2 Wheels",
    "wof:placetype":"venue"
},
  "geometry": {"coordinates":[-97.884232,29.988587],"type":"Point"}
}