{
  "type": "Feature",
  "properties": {
    "iso:country":"US",
    "sg:address":"3800 Southwest Freeway #150",
    "sg:city":"Houston",
    "sg:classifiers":[
        {
            "category":"Deli",
            "type":"Food & Drink"
        },
        {
            "category":"Restaurant",
            "type":"Food & Drink"
        },
        {
            "category":"Food & Beverages",
            "subcategory":"Bakery",
            "type":"Retail Goods"
        }
    ],
    "sg:phone":"+1 832 675 0500",
    "sg:postcode":"77027",
    "sg:province":"TX",
    "sg:tags":[
        "traditional",
        "american",
        "sandwich"
    ],
    "sg:website":"www.potbelly.com",
    "wof:name":"Potbelly Sandwich Shop",
    "wof:placetype":"venue"
},
  "geometry": {"coordinates":[-95.43735,29.72942],"type":"Point"}
}