{
  "type": "Feature",
  "properties": {
    "iso:country":"US",
    "sg:address":"1217 S Main St",
    "sg:city":"Hereford",
    "sg:classifiers":[
        {
            "category":"Professional",
            "subcategory":"Business Services",
            "type":"Services"
        }
    ],
    "sg:phone":"+1 806 364 7597",
    "sg:postcode":"79045",
    "sg:province":"TX",
    "sg:tags":[
        "auctioneer"
    ],
    "wof:name":"Panhandle Auction Svc",
    "wof:placetype":"venue"
},
  "geometry": {"coordinates":[-102.39296299999999,34.799423],"type":"Point"}
}