{
  "type": "Feature",
  "properties": {
    "iso:country":"US",
    "sg:address":"1800 Texas St",
    "sg:city":"Houston",
    "sg:classifiers":[
        {
            "category":"Bars & Pubs",
            "subcategory":"Sports Bar",
            "type":"Food & Drink"
        }
    ],
    "sg:phone":"+1 713 222 2287",
    "sg:postcode":"77003",
    "sg:province":"TX",
    "wof:name":"B.U.S. Bar",
    "wof:placetype":"venue"
},
  "geometry": {"coordinates":[-95.355698,29.755699],"type":"Point"}
}