{
  "type": "Feature",
  "properties": {
    "iso:country":"US",
    "sg:address":"5119 Dallas Ave",
    "sg:city":"Fort Worth",
    "sg:classifiers":[
        {
            "category":"Building & Trades",
            "subcategory":"Construction",
            "type":"Services"
        }
    ],
    "sg:phone":"+1 817 451 3691",
    "sg:postcode":"76112",
    "sg:province":"TX",
    "sg:tags":[
        "hanging",
        "contractor"
    ],
    "wof:name":"Macias Painting Co",
    "wof:placetype":"venue"
},
  "geometry": {"coordinates":[-97.241609,32.737993],"type":"Point"}
}