{
  "type": "Feature",
  "properties": {
    "iso:country":"US",
    "sg:address":"217 FM 517 W",
    "sg:city":"Dickinson",
    "sg:classifiers":[
        {
            "category":"Travel",
            "subcategory":"Campground",
            "type":"Entertainment"
        }
    ],
    "sg:phone":"+1 281 614 5252",
    "sg:postcode":"77539",
    "sg:province":"TX",
    "sg:tags":[
        "operation",
        "recreational",
        "trailer",
        "parks",
        "vehicle"
    ],
    "wof:name":"Bay Colony R V Park",
    "wof:placetype":"venue"
},
  "geometry": {"coordinates":[-95.079793,29.447768],"type":"Point"}
}