{
  "type": "Feature",
  "properties": {
    "iso:country":"US",
    "sg:address":"1400 N N St",
    "sg:city":"Midland",
    "sg:classifiers":[
        {
            "category":"Education",
            "subcategory":"School",
            "type":"Public Place"
        }
    ],
    "sg:phone":"+1 432 689 1350",
    "sg:postcode":"79701",
    "sg:province":"TX",
    "wof:name":"Midland Schools",
    "wof:placetype":"venue"
},
  "geometry": {"coordinates":[-102.10080600000001,32.007483],"type":"Point"}
}