{
  "type": "Feature",
  "properties": {
    "iso:country":"US",
    "sg:address":"722 Clover Ln",
    "sg:city":"Temple",
    "sg:classifiers":[
        {
            "category":"Insurance",
            "subcategory":"Insurance Agent",
            "type":"Services"
        }
    ],
    "sg:phone":"+1 254 778 2394",
    "sg:postcode":"76502",
    "sg:province":"TX",
    "wof:name":"State Farm Insurance",
    "wof:placetype":"venue"
},
  "geometry": {"coordinates":[-97.399843,31.105231],"type":"Point"}
}