{
  "type": "Feature",
  "properties": {
    "iso:country":"US",
    "sg:address":"607 Cotter Dr",
    "sg:city":"Spring",
    "sg:classifiers":[
        {
            "category":"Building & Trades",
            "subcategory":"Construction",
            "type":"Services"
        }
    ],
    "sg:phone":"+1 281 353 0377",
    "sg:postcode":"77373",
    "sg:province":"TX",
    "sg:tags":[
        "contractor"
    ],
    "wof:name":"MGA Contractors",
    "wof:placetype":"venue"
},
  "geometry": {"coordinates":[-95.423224,30.053266],"type":"Point"}
}