{
  "type": "Feature",
  "properties": {
    "iso:country":"US",
    "sg:address":"5189 E Interstate 20 Svc Rd",
    "sg:city":"Weatherford",
    "sg:classifiers":[
        {
            "category":"Government",
            "subcategory":"Office",
            "type":"Public Place"
        },
        {
            "category":"Professional",
            "subcategory":"Accounting & Tax Preparation",
            "type":"Services"
        }
    ],
    "sg:phone":"+1 817 441 5513",
    "sg:postcode":"76087",
    "sg:province":"TX",
    "sg:tags":[
        "county",
        "taxation",
        "return"
    ],
    "wof:name":"Parker County Tax Office",
    "wof:placetype":"venue"
},
  "geometry": {"coordinates":[-97.607046,32.729228],"type":"Point"}
}