{
  "type": "Feature",
  "properties": {
    "iso:country":"US",
    "sg:address":"5803 Ingram Rd",
    "sg:city":"San Antonio",
    "sg:classifiers":[
        {
            "category":"Real Estate",
            "subcategory":"Real Estate Operator",
            "type":"Services"
        }
    ],
    "sg:phone":"+1 210 431 7400",
    "sg:postcode":"78228",
    "sg:province":"TX",
    "sg:tags":[
        "property",
        "lessor"
    ],
    "wof:name":"Legacy At Science Park",
    "wof:placetype":"venue"
},
  "geometry": {"coordinates":[-98.59436599999999,29.464238],"type":"Point"}
}