{
  "type": "Feature",
  "properties": {
    "iso:country":"US",
    "sg:address":"13214 Quadros Pass",
    "sg:city":"Austin",
    "sg:classifiers":[
        {
            "category":"Health Services",
            "subcategory":"Doctor",
            "type":"Services"
        }
    ],
    "sg:phone":"+1 512 996 9339",
    "sg:postcode":"78729",
    "sg:province":"TX",
    "sg:tags":[
        "dentist"
    ],
    "wof:name":"Balcones Family Dental",
    "wof:placetype":"venue"
},
  "geometry": {"coordinates":[-97.75894599999999,30.451718],"type":"Point"}
}