{
  "type": "Feature",
  "properties": {
    "iso:country":"US",
    "sg:address":"1207 N May St",
    "sg:city":"Madisonville",
    "sg:classifiers":[
        {
            "category":"Retail",
            "subcategory":"Repair Shop",
            "type":"Services"
        }
    ],
    "sg:phone":"+1 936 348 5417",
    "sg:postcode":"77864",
    "sg:province":"TX",
    "sg:tags":[
        "television",
        "radio"
    ],
    "wof:name":"Southside TV Svc",
    "wof:placetype":"venue"
},
  "geometry": {"coordinates":[-95.917334,30.966187],"type":"Point"}
}