{
  "type": "Feature",
  "properties": {
    "iso:country":"US",
    "sg:address":"233 Felton Rd",
    "sg:city":"Lufkin",
    "sg:classifiers":[
        {
            "category":"Organizations",
            "subcategory":"Religious Organization",
            "type":"Services"
        }
    ],
    "sg:phone":"+1 936 639 3215",
    "sg:postcode":"75904",
    "sg:province":"TX",
    "sg:tags":[
        "church"
    ],
    "wof:name":"Faith Tabernacle Full Gospel",
    "wof:placetype":"venue"
},
  "geometry": {"coordinates":[-94.75417,31.375118],"type":"Point"}
}