{
  "type": "Feature",
  "properties": {
    "iso:country":"US",
    "sg:address":"830 Wycliffe Dr",
    "sg:city":"Houston",
    "sg:classifiers":[
        {
            "category":"Retail",
            "subcategory":"Auto Repair",
            "type":"Services"
        }
    ],
    "sg:phone":"+1 713 461 5364",
    "sg:postcode":"77079",
    "sg:province":"TX",
    "sg:tags":[
        "general"
    ],
    "wof:name":"Autotech",
    "wof:placetype":"venue"
},
  "geometry": {"coordinates":[-95.574399,29.780212],"type":"Point"}
}