{
  "type": "Feature",
  "properties": {
    "iso:country":"US",
    "sg:address":"13005 Heinemann Dr",
    "sg:city":"Austin",
    "sg:classifiers":[
        {
            "category":"Utilities",
            "subcategory":"Telephone",
            "type":"Services"
        }
    ],
    "sg:phone":"+1 512 336 0832",
    "sg:postcode":"78727",
    "sg:province":"TX",
    "sg:tags":[
        "communications"
    ],
    "wof:name":"Malkari LLC",
    "wof:placetype":"venue"
},
  "geometry": {"coordinates":[-97.746251,30.442319],"type":"Point"}
}