{
  "type": "Feature",
  "properties": {
    "iso:country":"US",
    "sg:address":"2211 Southmore Ave",
    "sg:city":"Pasadena",
    "sg:classifiers":[
        {
            "category":"Food & Beverages",
            "subcategory":"Groceries & Convenience Stores",
            "type":"Retail Goods"
        }
    ],
    "sg:phone":"+1 713 472 9200",
    "sg:postcode":"77502",
    "sg:province":"TX",
    "wof:name":"Mercado Lindo",
    "wof:placetype":"venue"
},
  "geometry": {"coordinates":[-95.182152,29.691839],"type":"Point"}
}