{
  "type": "Feature",
  "properties": {
    "iso:country":"US",
    "sg:address":"707 W 6th St",
    "sg:city":"Houston",
    "sg:classifiers":[
        {
            "category":"Freight",
            "type":"Transportation"
        }
    ],
    "sg:phone":"+1 281 449 8777",
    "sg:postcode":"77007",
    "sg:province":"TX",
    "sg:tags":[
        "cartage",
        "trucking"
    ],
    "wof:name":"Leeway Transportation",
    "wof:placetype":"venue"
},
  "geometry": {"coordinates":[-95.405817,29.78143],"type":"Point"}
}