{
  "type": "Feature",
  "properties": {
    "iso:country":"US",
    "sg:address":"720 Canyon Pl",
    "sg:city":"Desoto",
    "sg:classifiers":[
        {
            "category":"Building & Trades",
            "subcategory":"Cleaning & Sanitation",
            "type":"Services"
        }
    ],
    "sg:phone":"+1 682 200 1774",
    "sg:postcode":"75115",
    "sg:province":"TX",
    "sg:tags":[
        "cleaners-interior"
    ],
    "sg:website":"http://www.cinderellacleaning.info",
    "wof:name":"The Cinderella Cleaning Company",
    "wof:placetype":"venue"
},
  "geometry": {"coordinates":[-96.843695,32.577638],"type":"Point"}
}