{
  "type": "Feature",
  "properties": {
    "iso:country":"US",
    "sg:address":"1825 Fortview Rd Ste 108",
    "sg:city":"Austin",
    "sg:classifiers":[
        {
            "category":"Professional",
            "subcategory":"Management & Consulting",
            "type":"Services"
        },
        {
            "category":"Banks & Credit Unions",
            "subcategory":"Financial Services",
            "type":"Services"
        }
    ],
    "sg:phone":"+1 512 326 2314",
    "sg:postcode":"78704",
    "sg:province":"TX",
    "sg:tags":[
        "consultant",
        "financing",
        "planning"
    ],
    "sg:website":"http://www.priorityplanning.biz",
    "wof:name":"Priority Planning Financial Consultants",
    "wof:placetype":"venue"
},
  "geometry": {"coordinates":[-97.785892,30.230148],"type":"Point"}
}