{
  "type": "Feature",
  "properties": {
    "iso:country":"US",
    "sg:address":"320 Rush Creek Dr",
    "sg:city":"Rockwall",
    "sg:classifiers":[
        {
            "category":"Recreation",
            "type":"Entertainment"
        },
        {
            "category":"Organizations",
            "subcategory":"Community Association",
            "type":"Services"
        }
    ],
    "sg:phone":"+1 972 771 6500",
    "sg:postcode":"75032",
    "sg:province":"TX",
    "sg:tags":[
        "club",
        "membership"
    ],
    "sg:website":"www.rcyc.org",
    "wof:name":"Rush Creek Yacht Club Inc",
    "wof:placetype":"venue"
},
  "geometry": {"coordinates":[-96.494158,32.826357],"type":"Point"}
}