{
  "type": "Feature",
  "properties": {
    "iso:country":"US",
    "sg:address":"5501 N Lamar Blvd",
    "sg:city":"Austin",
    "sg:classifiers":[
        {
            "category":"Restaurant",
            "type":"Food & Drink"
        }
    ],
    "sg:phone":"+1 512 459 2222",
    "sg:postcode":"78751",
    "sg:province":"TX",
    "sg:tags":[
        "eating"
    ],
    "wof:name":"Mr Gattis",
    "wof:placetype":"venue"
},
  "geometry": {"coordinates":[-97.728077,30.32322],"type":"Point"}
}