{
  "type": "Feature",
  "properties": {
    "iso:country":"US",
    "sg:address":"16802 Garrett Rd",
    "sg:city":"Harlingen",
    "sg:classifiers":[
        {
            "category":"Building & Trades",
            "subcategory":"Landscaping Services",
            "type":"Services"
        }
    ],
    "sg:phone":"+1 956 421 5600",
    "sg:postcode":"78552",
    "sg:province":"TX",
    "sg:tags":[
        "landscape",
        "contractor"
    ],
    "wof:name":"Lawnpros",
    "wof:placetype":"venue"
},
  "geometry": {"coordinates":[-97.753349,26.170783],"type":"Point"}
}