{
  "type": "Feature",
  "properties": {
    "iso:country":"US",
    "sg:address":"620 N 2nd St",
    "sg:city":"Sanger",
    "sg:classifiers":[
        {
            "category":"Farming",
            "subcategory":"Farm",
            "type":"Manufacturing & Wholesale Goods"
        }
    ],
    "sg:phone":"+1 940 458 7175",
    "sg:postcode":"76266",
    "sg:province":"TX",
    "wof:name":"Schertz Farms",
    "wof:placetype":"venue"
},
  "geometry": {"coordinates":[-97.17144399999999,33.364912],"type":"Point"}
}