{
  "type": "Feature",
  "properties": {
    "iso:country":"US",
    "sg:address":"503 S Gulf Blvd",
    "sg:city":"Freeport",
    "sg:classifiers":[
        {
            "category":"Restaurant",
            "type":"Food & Drink"
        }
    ],
    "sg:phone":"+1 979 233 3111",
    "sg:postcode":"77541",
    "sg:province":"TX",
    "sg:tags":[
        "barbecue",
        "eating"
    ],
    "wof:name":"Lewis Barbecue",
    "wof:placetype":"venue"
},
  "geometry": {"coordinates":[-95.355305,28.960543],"type":"Point"}
}