{
  "type": "Feature",
  "properties": {
    "iso:country":"US",
    "sg:address":"3118 Dupree St",
    "sg:city":"Irving",
    "sg:classifiers":[
        {
            "category":"Shopping",
            "subcategory":"Clothing, Apparel, & Fashions",
            "type":"Retail Goods"
        }
    ],
    "sg:phone":"+1 972 255 2266",
    "sg:postcode":"75062",
    "sg:province":"TX",
    "sg:tags":[
        "family"
    ],
    "wof:name":"Dees Fashion Etc",
    "wof:placetype":"venue"
},
  "geometry": {"coordinates":[-96.979254,32.84918],"type":"Point"}
}