{
  "type": "Feature",
  "properties": {
    "iso:country":"US",
    "sg:address":"13447 East Fwy",
    "sg:city":"Houston",
    "sg:classifiers":[
        {
            "category":"Shopping",
            "subcategory":"Mobile Phones",
            "type":"Retail Goods"
        }
    ],
    "sg:phone":"+1 713 453 1108",
    "sg:postcode":"77015",
    "sg:province":"TX",
    "sg:website":"www.wireless.att.com",
    "wof:name":"AT&T",
    "wof:placetype":"venue"
},
  "geometry": {"coordinates":[-95.185383,29.771143],"type":"Point"}
}