{
  "type": "Feature",
  "properties": {
    "iso:country":"US",
    "sg:address":"173 Abigail Ln",
    "sg:city":"San Benito",
    "sg:classifiers":[
        {
            "category":"Recreation",
            "type":"Entertainment"
        }
    ],
    "sg:phone":"+1 956 492 1525",
    "sg:postcode":"78586",
    "sg:province":"TX",
    "wof:name":"Benavides Mixed Martial Arts",
    "wof:placetype":"venue"
},
  "geometry": {"coordinates":[-97.60365,26.152619],"type":"Point"}
}