{
  "type": "Feature",
  "properties": {
    "iso:country":"US",
    "sg:address":"217 S River St",
    "sg:city":"Seguin",
    "sg:classifiers":[
        {
            "category":"Banks & Credit Unions",
            "subcategory":"Bank",
            "type":"Services"
        }
    ],
    "sg:phone":"+1 830 401 0303",
    "sg:postcode":"78155",
    "sg:province":"TX",
    "sg:tags":[
        "personal",
        "financing",
        "institution"
    ],
    "wof:name":"Reliable Finance Co",
    "wof:placetype":"venue"
},
  "geometry": {"coordinates":[-97.96368699999999,29.567561],"type":"Point"}
}