{
  "type": "Feature",
  "properties": {
    "iso:country":"US",
    "sg:address":"801 W 1st St",
    "sg:city":"Fort Worth",
    "sg:classifiers":[
        {
            "category":"Organizations",
            "subcategory":"Religious Organization",
            "type":"Services"
        }
    ],
    "sg:phone":"+1 817 335 6080",
    "sg:postcode":"76102",
    "sg:province":"TX",
    "sg:tags":[
        "church"
    ],
    "wof:name":"First United Methodist Church",
    "wof:placetype":"venue"
},
  "geometry": {"coordinates":[-97.33839399999999,32.753523],"type":"Point"}
}