{
  "type": "Feature",
  "properties": {
    "iso:country":"US",
    "sg:address":"513 Willow Way",
    "sg:city":"Lewisville",
    "sg:classifiers":[
        {
            "category":"Professional",
            "subcategory":"Advertising",
            "type":"Services"
        }
    ],
    "sg:phone":"+1 972 317 4944",
    "sg:postcode":"75077",
    "sg:province":"TX",
    "sg:tags":[
        "business"
    ],
    "wof:name":"Diversified Promotions",
    "wof:placetype":"venue"
},
  "geometry": {"coordinates":[-97.038926,33.084006],"type":"Point"}
}