{
  "type": "Feature",
  "properties": {
    "iso:country":"US",
    "sg:address":"908 N Austin Ave",
    "sg:city":"Georgetown",
    "sg:classifiers":[
        {
            "category":"Shopping",
            "subcategory":"Discount & Variety Stores",
            "type":"Retail Goods"
        }
    ],
    "sg:phone":"+1 512 869 0129",
    "sg:postcode":"78626",
    "sg:province":"TX",
    "wof:name":"Dollar General",
    "wof:placetype":"venue"
},
  "geometry": {"coordinates":[-97.676908,30.649262],"type":"Point"}
}