{
  "type": "Feature",
  "properties": {
    "iso:country":"US",
    "sg:address":"7401 Centenary Dr",
    "sg:city":"Rowlett",
    "sg:classifiers":[
        {
            "category":"Retail",
            "subcategory":"Repair Shop",
            "type":"Services"
        }
    ],
    "sg:phone":"+1 972 475 5013",
    "sg:postcode":"75089",
    "sg:province":"TX",
    "sg:tags":[
        "related"
    ],
    "wof:name":"Dodson Irrigation",
    "wof:placetype":"venue"
},
  "geometry": {"coordinates":[-96.52813,32.92789],"type":"Point"}
}