{
  "type": "Feature",
  "properties": {
    "iso:country":"US",
    "sg:address":"4018 N Mesa St",
    "sg:city":"El Paso",
    "sg:classifiers":[
        {
            "category":"Retail",
            "subcategory":"Auto Repair",
            "type":"Services"
        }
    ],
    "sg:phone":"+1 915 541 9052",
    "sg:postcode":"79902",
    "sg:province":"TX",
    "sg:tags":[
        "automobile",
        "lubrication"
    ],
    "wof:name":"Lube'n Go",
    "wof:placetype":"venue"
},
  "geometry": {"coordinates":[-106.507321,31.788897],"type":"Point"}
}