{
  "type": "Feature",
  "properties": {
    "iso:country":"US",
    "sg:address":"8160 Walnut Hill Ln",
    "sg:city":"Dallas",
    "sg:classifiers":[
        {
            "category":"Health Services",
            "subcategory":"Clinic",
            "type":"Services"
        }
    ],
    "sg:phone":"+1 214 345 2318",
    "sg:postcode":"75231",
    "sg:province":"TX",
    "sg:tags":[
        "medical",
        "group"
    ],
    "wof:name":"Obstetrix Medical Group",
    "wof:placetype":"venue"
},
  "geometry": {"coordinates":[-96.763937,32.882912],"type":"Point"}
}