{
  "type": "Feature",
  "properties": {
    "iso:country":"US",
    "sg:address":"19600 FM 2100",
    "sg:city":"Crosby",
    "sg:classifiers":[
        {
            "category":"Home & Garden",
            "subcategory":"Garden Supply",
            "type":"Retail Goods"
        }
    ],
    "sg:phone":"+1 281 328 1209",
    "sg:postcode":"77532",
    "sg:province":"TX",
    "sg:tags":[
        "landscaping",
        "lawn",
        "nursery",
        "maintenance"
    ],
    "wof:name":"Karries Country Gardens Inc",
    "wof:placetype":"venue"
},
  "geometry": {"coordinates":[-95.085177,29.962252],"type":"Point"}
}