{
  "type": "Feature",
  "properties": {
    "iso:country":"US",
    "sg:address":"1148 Herkimer St",
    "sg:city":"Houston",
    "sg:classifiers":[
        {
            "category":"Social Services",
            "type":"Services"
        }
    ],
    "sg:phone":"+1 713 802 1139",
    "sg:postcode":"77008",
    "sg:province":"TX",
    "sg:tags":[
        "organization",
        "welfare"
    ],
    "wof:name":"A New Way",
    "wof:placetype":"venue"
},
  "geometry": {"coordinates":[-95.406097,29.791507],"type":"Point"}
}