{
  "type": "Feature",
  "properties": {
    "iso:country":"US",
    "sg:address":"14 Estates Rd",
    "sg:city":"Allen",
    "sg:classifiers":[
        {
            "category":"Shopping",
            "subcategory":"Hobbies, Toys, & Games",
            "type":"Retail Goods"
        }
    ],
    "sg:phone":"+1 972 390 9486",
    "sg:postcode":"75002",
    "sg:province":"TX",
    "wof:name":"Daves Crafts & Supplies",
    "wof:placetype":"venue"
},
  "geometry": {"coordinates":[-96.59801,33.090057],"type":"Point"}
}