{
  "type": "Feature",
  "properties": {
    "iso:country":"US",
    "sg:address":"10709 Parkfield Dr",
    "sg:city":"Austin",
    "sg:classifiers":[
        {
            "category":"Real Estate",
            "subcategory":"Real Estate Agent",
            "type":"Services"
        }
    ],
    "sg:phone":"+1 512 835 8445",
    "sg:postcode":"78758",
    "sg:province":"TX",
    "wof:name":"Parkfield Realty",
    "wof:placetype":"venue"
},
  "geometry": {"coordinates":[-97.698936,30.379309],"type":"Point"}
}