{
  "type": "Feature",
  "properties": {
    "iso:country":"US",
    "sg:address":"15700 Montana Ave",
    "sg:city":"El Paso",
    "sg:classifiers":[
        {
            "category":"Sports & Exercise",
            "subcategory":"Race Track",
            "type":"Entertainment"
        }
    ],
    "sg:phone":"+1 915 857 8888",
    "sg:postcode":"79938",
    "sg:province":"TX",
    "wof:name":"Thunder Alley Dragway",
    "wof:placetype":"venue"
},
  "geometry": {"coordinates":[-106.129789,31.825246],"type":"Point"}
}