{
  "type": "Feature",
  "properties": {
    "iso:country":"US",
    "sg:address":"5621 Aldine Bender Rd",
    "sg:city":"Houston",
    "sg:classifiers":[
        {
            "category":"Shopping",
            "subcategory":"Clothing, Apparel, & Fashions",
            "type":"Retail Goods"
        }
    ],
    "sg:phone":"+1 281 590 0056",
    "sg:postcode":"77032",
    "sg:province":"TX",
    "sg:tags":[
        "item",
        "boutique"
    ],
    "wof:name":"Breens Boutique",
    "wof:placetype":"venue"
},
  "geometry": {"coordinates":[-95.30409400000001,29.930656],"type":"Point"}
}