{
  "type": "Feature",
  "properties": {
    "iso:country":"US",
    "sg:address":"21310 Park Post Ln",
    "sg:city":"Katy",
    "sg:classifiers":[
        {
            "category":"Professional",
            "subcategory":"Secretarial Services",
            "type":"Services"
        }
    ],
    "sg:phone":"+1 281 578 7779",
    "sg:postcode":"77450",
    "sg:province":"TX",
    "sg:tags":[
        "reporting"
    ],
    "wof:name":"Certified Court Reporters",
    "wof:placetype":"venue"
},
  "geometry": {"coordinates":[-95.737144,29.756338],"type":"Point"}
}