{
  "type": "Feature",
  "properties": {
    "iso:country":"US",
    "sg:address":"104 W Methvin St",
    "sg:city":"Longview",
    "sg:classifiers":[
        {
            "category":"Professional",
            "subcategory":"Art Services",
            "type":"Services"
        }
    ],
    "sg:phone":"+1 903 753 2098",
    "sg:postcode":"75601",
    "sg:province":"TX",
    "sg:tags":[
        "commercial",
        "photography",
        "design"
    ],
    "wof:name":"Forbes & Butler",
    "wof:placetype":"venue"
},
  "geometry": {"coordinates":[-94.741235,32.496775],"type":"Point"}
}