{
  "type": "Feature",
  "properties": {
    "iso:country":"US",
    "sg:address":"7900 FM 1826",
    "sg:city":"Austin",
    "sg:classifiers":[
        {
            "category":"Health Services",
            "subcategory":"Clinic",
            "type":"Services"
        }
    ],
    "sg:phone":"+1 512 324 4010",
    "sg:postcode":"78737",
    "sg:province":"TX",
    "sg:tags":[
        "medical",
        "emergency",
        "minor"
    ],
    "wof:name":"Seton Northwest Hospital",
    "wof:placetype":"venue"
},
  "geometry": {"coordinates":[-97.889184,30.227742],"type":"Point"}
}