{
  "type": "Feature",
  "properties": {
    "iso:country":"US",
    "sg:address":"6485 I- 37",
    "sg:city":"Corpus Christi",
    "sg:classifiers":[
        {
            "category":"Building & Trades",
            "subcategory":"Equipment Rental",
            "type":"Services"
        }
    ],
    "sg:phone":"+1 361 289 1700",
    "sg:postcode":"78409",
    "sg:province":"TX",
    "sg:tags":[
        "crane"
    ],
    "wof:name":"Kuhn Crane Svc",
    "wof:placetype":"venue"
},
  "geometry": {"coordinates":[-97.488705,27.805282],"type":"Point"}
}