{
  "type": "Feature",
  "properties": {
    "iso:country":"US",
    "sg:address":"1804 Sidney Baker St",
    "sg:city":"Kerrville",
    "sg:classifiers":[
        {
            "category":"Professional",
            "type":"Services"
        }
    ],
    "sg:phone":"+1 830 896 0600",
    "sg:postcode":"78028",
    "sg:province":"TX",
    "sg:tags":[
        "establishment"
    ],
    "wof:name":"Olan Mills Studio",
    "wof:placetype":"venue"
},
  "geometry": {"coordinates":[-99.120766,30.06462],"type":"Point"}
}