{
  "type": "Feature",
  "properties": {
    "iso:country":"US",
    "sg:address":"18420 State Hwy 3",
    "sg:city":"Webster",
    "sg:classifiers":[
        {
            "category":"Building & Trades",
            "subcategory":"Electrical",
            "type":"Services"
        }
    ],
    "sg:phone":"+1 281 332 9211",
    "sg:postcode":"77598",
    "sg:province":"TX",
    "sg:tags":[
        "electrical",
        "contractor"
    ],
    "wof:name":"C&R Electric",
    "wof:placetype":"venue"
},
  "geometry": {"coordinates":[-95.11270399999999,29.531778],"type":"Point"}
}