{
  "type": "Feature",
  "properties": {
    "iso:country":"US",
    "sg:address":"1901 Medi Park Dr",
    "sg:city":"Amarillo",
    "sg:classifiers":[
        {
            "category":"Health Services",
            "subcategory":"Doctor",
            "type":"Services"
        }
    ],
    "sg:phone":"+1 806 353 1800",
    "sg:postcode":"79106",
    "sg:province":"TX",
    "sg:tags":[
        "medical"
    ],
    "wof:name":"Richard Dillman Jr MD",
    "wof:placetype":"venue"
},
  "geometry": {"coordinates":[-101.91424499999999,35.191265],"type":"Point"}
}