{
  "type": "Feature",
  "properties": {
    "iso:country":"US",
    "sg:address":"17802 Kilkenny Dr",
    "sg:city":"Pflugerville",
    "sg:classifiers":[
        {
            "category":"Building & Trades",
            "subcategory":"Construction",
            "type":"Services"
        }
    ],
    "sg:phone":"+1 512 251 8255",
    "sg:postcode":"78660",
    "sg:province":"TX",
    "sg:tags":[
        "home",
        "builder"
    ],
    "wof:name":"Legacy Homes",
    "wof:placetype":"venue"
},
  "geometry": {"coordinates":[-97.637064,30.472521],"type":"Point"}
}