{
  "type": "Feature",
  "properties": {
    "iso:country":"US",
    "sg:address":"4321 Jonathan St",
    "sg:city":"Bellaire",
    "sg:classifiers":[
        {
            "category":"Building & Trades",
            "subcategory":"Landscaping Services",
            "type":"Services"
        }
    ],
    "sg:phone":"+1 713 666 4777",
    "sg:postcode":"77401",
    "sg:province":"TX",
    "sg:tags":[
        "landscape",
        "contractor"
    ],
    "wof:name":"Earthcare Horticultural Svc",
    "wof:placetype":"venue"
},
  "geometry": {"coordinates":[-95.44900800000001,29.701883],"type":"Point"}
}