{
  "type": "Feature",
  "properties": {
    "iso:country":"US",
    "sg:address":"2725 6th Ave",
    "sg:city":"Amarillo",
    "sg:classifiers":[
        {
            "category":"Shopping",
            "subcategory":"Used Merchandise",
            "type":"Retail Goods"
        }
    ],
    "sg:phone":"+1 806 379 9008",
    "sg:postcode":"79106",
    "sg:province":"TX",
    "sg:tags":[
        "antique"
    ],
    "wof:name":"Red Rooster Antiques",
    "wof:placetype":"venue"
},
  "geometry": {"coordinates":[-101.867243,35.21122],"type":"Point"}
}