{
  "type": "Feature",
  "properties": {
    "iso:country":"US",
    "sg:address":"907 N Ray St",
    "sg:city":"Alvarado",
    "sg:classifiers":[
        {
            "category":"Organizations",
            "subcategory":"Religious Organization",
            "type":"Services"
        }
    ],
    "sg:phone":"+1 817 790 6039",
    "sg:postcode":"76009",
    "sg:province":"TX",
    "sg:tags":[
        "god",
        "churches-pentecostal",
        "church"
    ],
    "wof:name":"River Of Life Church Of God",
    "wof:placetype":"venue"
},
  "geometry": {"coordinates":[-97.213302,32.415009],"type":"Point"}
}