{
  "type": "Feature",
  "properties": {
    "iso:country":"US",
    "sg:address":"5169 Randolph Blvd",
    "sg:city":"San Antonio",
    "sg:classifiers":[
        {
            "category":"Building & Trades",
            "subcategory":"Construction",
            "type":"Services"
        }
    ],
    "sg:phone":"+1 210 653 1787",
    "sg:postcode":"78233",
    "sg:province":"TX",
    "sg:tags":[
        "foundation"
    ],
    "sg:website":"www.landstabilizers.com",
    "wof:name":"Land Stabilizers Inc",
    "wof:placetype":"venue"
},
  "geometry": {"coordinates":[-98.38772,29.526256],"type":"Point"}
}