{
  "type": "Feature",
  "properties": {
    "iso:country":"US",
    "sg:address":"2829 Merrell Rd",
    "sg:city":"Dallas",
    "sg:classifiers":[
        {
            "category":"Wholesale",
            "subcategory":"Construction Materials",
            "type":"Manufacturing & Wholesale Goods"
        }
    ],
    "sg:phone":"+1 972 243 2320",
    "sg:postcode":"75229",
    "sg:province":"TX",
    "sg:tags":[
        "wholesaler"
    ],
    "wof:name":"Tile Warehouse",
    "wof:placetype":"venue"
},
  "geometry": {"coordinates":[-96.883304,32.886547],"type":"Point"}
}