{
  "type": "Feature",
  "properties": {
    "iso:country":"US",
    "sg:address":"9416 State Hwy 6 Bus",
    "sg:city":"Navasota",
    "sg:classifiers":[
        {
            "category":"Restaurant",
            "type":"Food & Drink"
        }
    ],
    "sg:phone":"+1 936 870 3040",
    "sg:postcode":"77868",
    "sg:province":"TX",
    "sg:tags":[
        "eating"
    ],
    "wof:name":"La Casita",
    "wof:placetype":"venue"
},
  "geometry": {"coordinates":[-96.077541,30.36728],"type":"Point"}
}