{
  "type": "Feature",
  "properties": {
    "iso:country":"US",
    "sg:address":"Memorial City Mall 900 Gessner Rd",
    "sg:city":"Houston",
    "sg:classifiers":[
        {
            "category":"Personal",
            "subcategory":"Beauty Salon",
            "type":"Services"
        }
    ],
    "sg:phone":"+1 713 461 5444",
    "sg:postcode":"77024",
    "sg:province":"TX",
    "sg:tags":[
        "hair"
    ],
    "sg:website":"www.toniguy.com",
    "wof:name":"Toni & Guy",
    "wof:placetype":"venue"
},
  "geometry": {"coordinates":[-95.543159,29.781447],"type":"Point"}
}