{
  "type": "Feature",
  "properties": {
    "iso:country":"US",
    "sg:address":"2904 Manchester Dr",
    "sg:city":"Mesquite",
    "sg:classifiers":[
        {
            "category":"Professional",
            "subcategory":"Business Services",
            "type":"Services"
        }
    ],
    "sg:phone":"+1 972 270 9000",
    "sg:postcode":"75150",
    "sg:province":"TX",
    "sg:tags":[
        "delivery",
        "courier"
    ],
    "wof:name":"Rush Hour Courier Services Inc",
    "wof:placetype":"venue"
},
  "geometry": {"coordinates":[-96.643523,32.81112],"type":"Point"}
}