{
  "type": "Feature",
  "properties": {
    "iso:country":"US",
    "sg:address":"105 E Centre St",
    "sg:city":"Fredericksburg",
    "sg:classifiers":[
        {
            "category":"Personal",
            "subcategory":"Beauty Salon",
            "type":"Services"
        }
    ],
    "sg:phone":"+1 830 997 0320",
    "sg:postcode":"78624",
    "sg:province":"TX",
    "wof:name":"Brigittes Hair Cottage",
    "wof:placetype":"venue"
},
  "geometry": {"coordinates":[-98.86673399999999,30.280269],"type":"Point"}
}