{
  "type": "Feature",
  "properties": {
    "iso:country":"US",
    "sg:address":"413 Pedmore Dr",
    "sg:city":"Coppell",
    "sg:classifiers":[
        {
            "category":"Professional",
            "subcategory":"Business Services",
            "type":"Services"
        }
    ],
    "sg:phone":"+1 972 393 9942",
    "sg:postcode":"75019",
    "sg:province":"TX",
    "wof:name":"John Schrock Enterprises LLC",
    "wof:placetype":"venue"
},
  "geometry": {"coordinates":[-97.00679100000001,32.979779],"type":"Point"}
}