{
  "type": "Feature",
  "properties": {
    "iso:country":"US",
    "sg:address":"5404 99th St",
    "sg:city":"Lubbock",
    "sg:classifiers":[
        {
            "category":"Building & Trades",
            "subcategory":"Landscaping Services",
            "type":"Services"
        }
    ],
    "sg:phone":"+1 806 798 0228",
    "sg:postcode":"79424",
    "sg:province":"TX",
    "sg:tags":[
        "lawn",
        "landscape"
    ],
    "sg:website":"http://www.uus-llc.com",
    "wof:name":"Turf Tamers",
    "wof:placetype":"venue"
},
  "geometry": {"coordinates":[-101.928516,33.504126],"type":"Point"}
}