{
  "type": "Feature",
  "properties": {
    "iso:country":"US",
    "sg:address":"1118 Newkirk Ct",
    "sg:city":"Rockwall",
    "sg:classifiers":[
        {
            "category":"Professional",
            "subcategory":"Business Services",
            "type":"Services"
        }
    ],
    "sg:phone":"+1 972 722 4577",
    "sg:postcode":"75032",
    "sg:province":"TX",
    "sg:tags":[
        "holding"
    ],
    "wof:name":"Oak National Holdings",
    "wof:placetype":"venue"
},
  "geometry": {"coordinates":[-96.403238,32.868173],"type":"Point"}
}