{
  "type": "Feature",
  "properties": {
    "iso:country":"US",
    "sg:address":"42041 Metz Rd",
    "sg:city":"Sanger",
    "sg:classifiers":[
        {
            "category":"Retail",
            "subcategory":"Repair Shop",
            "type":"Services"
        }
    ],
    "sg:phone":"+1 940 300 0740",
    "sg:postcode":"76266",
    "sg:province":"TX",
    "sg:tags":[
        "welding"
    ],
    "wof:name":"K & H Welding Shop",
    "wof:placetype":"venue"
},
  "geometry": {"coordinates":[-97.192781,33.408993],"type":"Point"}
}