{
  "type": "Feature",
  "properties": {
    "iso:country":"US",
    "sg:address":"113 Tulip Trl",
    "sg:city":"Lake Jackson",
    "sg:classifiers":[
        {
            "category":"Real Estate",
            "subcategory":"Real Estate Agent",
            "type":"Services"
        }
    ],
    "sg:phone":"+1 979 292 0909",
    "sg:postcode":"77566",
    "sg:province":"TX",
    "wof:name":"Ameramort",
    "wof:placetype":"venue"
},
  "geometry": {"coordinates":[-95.44951500000001,29.046574],"type":"Point"}
}