{
  "type": "Feature",
  "properties": {
    "iso:country":"US",
    "sg:address":"701 10th St",
    "sg:city":"Orange",
    "sg:classifiers":[
        {
            "category":"Building & Trades",
            "subcategory":"Construction",
            "type":"Services"
        }
    ],
    "sg:phone":"+1 409 886 0900",
    "sg:postcode":"77630",
    "sg:province":"TX",
    "sg:tags":[
        "contractor"
    ],
    "wof:name":"Afcon Construction",
    "wof:placetype":"venue"
},
  "geometry": {"coordinates":[-93.74022600000001,30.096351],"type":"Point"}
}