{
  "type": "Feature",
  "properties": {
    "iso:country":"US",
    "sg:address":"617 S Rivershire Dr",
    "sg:city":"Conroe",
    "sg:classifiers":[
        {
            "category":"Social Services",
            "subcategory":"Child Care",
            "type":"Services"
        }
    ],
    "sg:phone":"+1 936 441 4370",
    "sg:postcode":"77304",
    "sg:province":"TX",
    "sg:tags":[
        "day"
    ],
    "wof:name":"Little Peoples School",
    "wof:placetype":"venue"
},
  "geometry": {"coordinates":[-95.478776,30.284806],"type":"Point"}
}