{
  "type": "Feature",
  "properties": {
    "iso:country":"US",
    "sg:address":"16111 Hilton Head Ln",
    "sg:city":"Cypress",
    "sg:classifiers":[
        {
            "category":"Travel",
            "subcategory":"Travel Agent",
            "type":"Entertainment"
        }
    ],
    "sg:phone":"+1 281 304 9479",
    "sg:postcode":"77429",
    "sg:province":"TX",
    "sg:tags":[
        "agency"
    ],
    "wof:name":"Globotur Travel Service",
    "wof:placetype":"venue"
},
  "geometry": {"coordinates":[-95.671903,29.983828],"type":"Point"}
}