{
  "type": "Feature",
  "properties": {
    "iso:country":"US",
    "sg:address":"725 Airport Fwy",
    "sg:city":"Hurst",
    "sg:classifiers":[
        {
            "category":"Shopping",
            "subcategory":"Clothing, Apparel, & Fashions",
            "type":"Retail Goods"
        }
    ],
    "sg:phone":"+1 817 280 0567",
    "sg:postcode":"76053",
    "sg:province":"TX",
    "wof:name":"Here Comes Bride",
    "wof:placetype":"venue"
},
  "geometry": {"coordinates":[-97.18324,32.839276],"type":"Point"}
}