{
  "type": "Feature",
  "properties": {
    "iso:country":"US",
    "sg:address":"238 Cliffwood Dr",
    "sg:city":"San Antonio",
    "sg:classifiers":[
        {
            "category":"Building & Trades",
            "subcategory":"Construction",
            "type":"Services"
        }
    ],
    "sg:phone":"+1 210 349 1384",
    "sg:postcode":"78213",
    "sg:province":"TX",
    "sg:tags":[
        "painting",
        "contractor"
    ],
    "wof:name":"Artistic Designs",
    "wof:placetype":"venue"
},
  "geometry": {"coordinates":[-98.524801,29.490419],"type":"Point"}
}