{
  "type": "Feature",
  "properties": {
    "iso:country":"US",
    "sg:address":"3001 Cleburne St",
    "sg:city":"Houston",
    "sg:classifiers":[
        {
            "category":"Professional",
            "type":"Services"
        },
        {
            "category":"Restaurant",
            "type":"Food & Drink"
        }
    ],
    "sg:phone":"+1 713 521 1139",
    "sg:postcode":"77004",
    "sg:province":"TX",
    "sg:tags":[
        "barbeque",
        "caterer"
    ],
    "sg:website":"tbsokonline.com",
    "wof:name":"Two Brother's Smokin Oak Kitchen",
    "wof:placetype":"venue"
},
  "geometry": {"coordinates":[-95.364304,29.726601],"type":"Point"}
}