{
  "type": "Feature",
  "properties": {
    "iso:country":"US",
    "sg:address":"4605 S Cooper St",
    "sg:city":"Arlington",
    "sg:classifiers":[
        {
            "category":"Home & Garden",
            "subcategory":"Home Furnishings",
            "type":"Retail Goods"
        }
    ],
    "sg:phone":"+1 817 468 3939",
    "sg:postcode":"76017",
    "sg:province":"TX",
    "wof:name":"Barbecue Galore",
    "wof:placetype":"venue"
},
  "geometry": {"coordinates":[-97.13426699999999,32.670585],"type":"Point"}
}