{
  "type": "Feature",
  "properties": {
    "iso:country":"US",
    "sg:address":"South Congress Artists Market 1609 South Congress",
    "sg:city":"Austin",
    "sg:classifiers":[
        {
            "category":"Shopping",
            "subcategory":"Jewelry",
            "type":"Retail Goods"
        },
        {
            "category":"Shopping",
            "subcategory":"Bridal",
            "type":"Retail Goods"
        }
    ],
    "sg:postcode":"78704",
    "sg:province":"TX",
    "sg:website":"www.worldonastring.us",
    "wof:name":"World On A String",
    "wof:placetype":"venue"
},
  "geometry": {"coordinates":[-97.750288,30.247867],"type":"Point"}
}