{
  "type": "Feature",
  "properties": {
    "iso:country":"US",
    "sg:address":"17218 Jimenez Rd",
    "sg:city":"San Benito",
    "sg:classifiers":[
        {
            "category":"Shopping",
            "subcategory":"Florist",
            "type":"Retail Goods"
        }
    ],
    "sg:phone":"+1 956 425 7175",
    "sg:postcode":"78586",
    "sg:province":"TX",
    "wof:name":"Mimi's Flowers",
    "wof:placetype":"venue"
},
  "geometry": {"coordinates":[-97.746225,26.089943],"type":"Point"}
}