{
  "type": "Feature",
  "properties": {
    "iso:country":"US",
    "sg:address":"6609 Hillcrest Ave",
    "sg:city":"Dallas",
    "sg:classifiers":[
        {
            "category":"Shopping",
            "subcategory":"Clothing, Apparel, & Fashions",
            "type":"Retail Goods"
        },
        {
            "category":"Personal",
            "type":"Services"
        }
    ],
    "sg:phone":"+1 214 696 1101",
    "sg:postcode":"75205",
    "sg:province":"TX",
    "sg:tags":[
        "tailoring",
        "sewing",
        "alteration",
        "tailor",
        "wedding"
    ],
    "wof:name":"H A Custom Apparel & Alterations",
    "wof:placetype":"venue"
},
  "geometry": {"coordinates":[-96.787003,32.846802],"type":"Point"}
}