{
  "type": "Feature",
  "properties": {
    "iso:country":"US",
    "sg:address":"1421 S Dumas Ave",
    "sg:city":"Dumas",
    "sg:classifiers":[
        {
            "category":"Restaurant",
            "type":"Food & Drink"
        }
    ],
    "sg:menulink":"http://www.allmenus.com/tx/dumas/70657-pizza-hut/menu/",
    "sg:phone":"+1 806 935 6111",
    "sg:postcode":"79029",
    "sg:province":"TX",
    "sg:tags":[
        "american",
        "pizza"
    ],
    "wof:name":"Pizza Hut",
    "wof:placetype":"venue"
},
  "geometry": {"coordinates":[-101.973343,35.850685],"type":"Point"}
}