{
  "type": "Feature",
  "properties": {
    "iso:country":"US",
    "sg:address":"358 N Main St",
    "sg:city":"Paris",
    "sg:classifiers":[
        {
            "category":"Retail",
            "subcategory":"Car Wash",
            "type":"Services"
        }
    ],
    "sg:phone":"+1 903 784 2930",
    "sg:postcode":"75460",
    "sg:province":"TX",
    "sg:tags":[
        "automobile",
        "detail",
        "clean"
    ],
    "wof:name":"Jenkins Mobile Detail Shop",
    "wof:placetype":"venue"
},
  "geometry": {"coordinates":[-95.55623300000001,33.664083],"type":"Point"}
}