{
  "type": "Feature",
  "properties": {
    "iso:country":"US",
    "sg:address":"1004 S Hampton Rd",
    "sg:city":"Dallas",
    "sg:classifiers":[
        {
            "category":"Retail",
            "subcategory":"Auto Repair",
            "type":"Services"
        }
    ],
    "sg:phone":"+1 214 946 8448",
    "sg:postcode":"75208",
    "sg:province":"TX",
    "sg:tags":[
        "automobile",
        "lube",
        "oil",
        "lubrication"
    ],
    "wof:name":"Kwik Kar Lube & Tune",
    "wof:placetype":"venue"
},
  "geometry": {"coordinates":[-96.856753,32.735484],"type":"Point"}
}