{
  "type": "Feature",
  "properties": {
    "iso:country":"US",
    "sg:address":"1401 W 7th Ave",
    "sg:city":"Amarillo",
    "sg:classifiers":[
        {
            "category":"Retail",
            "subcategory":"Auto Repair",
            "type":"Services"
        }
    ],
    "sg:phone":"+1 806 372 9411",
    "sg:postcode":"79101",
    "sg:province":"AR",
    "sg:tags":[
        "shop",
        "automotive",
        "machine",
        "parts",
        "automobile"
    ],
    "wof:name":"Carter Engine & Machine Inc",
    "wof:placetype":"venue"
},
  "geometry": {"coordinates":[-101.853695,35.208771],"type":"Point"}
}