{
  "type": "Feature",
  "properties": {
    "iso:country":"US",
    "sg:address":"3726 Fern Cir",
    "sg:city":"Odessa",
    "sg:classifiers":[
        {
            "category":"Building & Trades",
            "subcategory":"Construction",
            "type":"Services"
        }
    ],
    "sg:phone":"+1 432 552 9600",
    "sg:postcode":"79762",
    "sg:province":"TX",
    "sg:tags":[
        "residential"
    ],
    "wof:name":"Sid Driggers Construction Inc",
    "wof:placetype":"venue"
},
  "geometry": {"coordinates":[-102.336112,31.886195],"type":"Point"}
}