{
  "type": "Feature",
  "properties": {
    "iso:country":"US",
    "sg:address":"8711 Burnet Rd Ste D-41",
    "sg:city":"Austin",
    "sg:classifiers":[
        {
            "category":"Building & Trades",
            "subcategory":"Construction",
            "type":"Services"
        }
    ],
    "sg:phone":"+1 512 828 6770",
    "sg:postcode":"78757",
    "sg:province":"TX",
    "sg:tags":[
        "window",
        "installation",
        "contractor"
    ],
    "sg:website":"www.theglassguruofaustin.com/",
    "wof:name":"The Glass Guru",
    "wof:placetype":"venue"
},
  "geometry": {"coordinates":[-97.725571,30.369018],"type":"Point"}
}