{
  "type": "Feature",
  "properties": {
    "iso:country":"US",
    "sg:address":"7000 Lake Country Dr",
    "sg:city":"Fort Worth",
    "sg:classifiers":[
        {
            "category":"Insurance",
            "subcategory":"Insurance Agent",
            "type":"Services"
        }
    ],
    "sg:phone":"+1 817 236 0104",
    "sg:postcode":"76179",
    "sg:province":"TX",
    "wof:name":"Allstate",
    "wof:placetype":"venue"
},
  "geometry": {"coordinates":[-97.42831,32.881051],"type":"Point"}
}