{
  "type": "Feature",
  "properties": {
    "iso:country":"US",
    "sg:address":"1225 N Fry Rd",
    "sg:city":"Katy",
    "sg:classifiers":[
        {
            "category":"Restaurant",
            "type":"Food & Drink"
        }
    ],
    "sg:menulink":"http://www.allmenus.com/tx/houston/157270-whataburger/menu/",
    "sg:phone":"+1 281 492 0691",
    "sg:postcode":"77449",
    "sg:province":"TX",
    "sg:tags":[
        "burger",
        "american"
    ],
    "wof:name":"Whataburger",
    "wof:placetype":"venue"
},
  "geometry": {"coordinates":[-95.72019400000001,29.78769],"type":"Point"}
}