{
  "type": "Feature",
  "properties": {
    "iso:country":"US",
    "sg:address":"8765 Blewett Rd",
    "sg:city":"Beaumont",
    "sg:classifiers":[
        {
            "category":"Social Services",
            "type":"Services"
        }
    ],
    "sg:phone":"+1 409 543 5338",
    "sg:postcode":"77705",
    "sg:province":"TX",
    "sg:tags":[
        "human"
    ],
    "wof:name":"Mothers - Helping - Mothers Ministries",
    "wof:placetype":"venue"
},
  "geometry": {"coordinates":[-94.19347999999999,29.965837],"type":"Point"}
}