{
  "type": "Feature",
  "properties": {
    "iso:country":"US",
    "sg:address":"6208 Spencer Hwy",
    "sg:city":"Pasadena",
    "sg:classifiers":[
        {
            "category":"Professional",
            "subcategory":"Computer Services",
            "type":"Services"
        }
    ],
    "sg:phone":"+1 713 910 3974",
    "sg:postcode":"77505",
    "sg:province":"TX",
    "sg:tags":[
        "internet"
    ],
    "wof:name":"Deltacom Systems & Networking",
    "wof:placetype":"venue"
},
  "geometry": {"coordinates":[-95.144419,29.665754],"type":"Point"}
}