{
  "type": "Feature",
  "properties": {
    "iso:country":"US",
    "sg:address":"224 S Conway Ave",
    "sg:city":"Mission",
    "sg:classifiers":[
        {
            "category":"Shopping",
            "subcategory":"Used Merchandise",
            "type":"Retail Goods"
        }
    ],
    "sg:phone":"+1 956 519 0044",
    "sg:postcode":"78572",
    "sg:province":"TX",
    "sg:tags":[
        "pawnbroker",
        "pawnshop"
    ],
    "wof:name":"Cash America Pawn 586",
    "wof:placetype":"venue"
},
  "geometry": {"coordinates":[-98.32784100000001,26.204421],"type":"Point"}
}