{
  "type": "Feature",
  "properties": {
    "iso:country":"US",
    "sg:address":"18308 Aztec Dr",
    "sg:city":"Porter",
    "sg:classifiers":[
        {
            "category":"Building & Trades",
            "subcategory":"Construction",
            "type":"Services"
        }
    ],
    "sg:phone":"+1 832 309 7958",
    "sg:postcode":"77365",
    "sg:province":"TX",
    "sg:tags":[
        "housing"
    ],
    "wof:name":"PCC Construction",
    "wof:placetype":"venue"
},
  "geometry": {"coordinates":[-95.27961999999999,30.104061],"type":"Point"}
}