{
  "type": "Feature",
  "properties": {
    "iso:country":"US",
    "sg:address":"605 Harris St",
    "sg:city":"Nacogdoches",
    "sg:classifiers":[
        {
            "category":"Community Center",
            "subcategory":"Senior",
            "type":"Public Place"
        }
    ],
    "sg:phone":"+1 936 462 8858",
    "sg:postcode":"75964",
    "sg:province":"TX",
    "sg:tags":[
        "citizen"
    ],
    "wof:name":"Nacogdoches Senior Village",
    "wof:placetype":"venue"
},
  "geometry": {"coordinates":[-94.667627,31.597979],"type":"Point"}
}