{
  "type": "Feature",
  "properties": {
    "iso:country":"US",
    "sg:address":"14173 Rollins Rd",
    "sg:city":"Winnie",
    "sg:classifiers":[
        {
            "category":"Building & Trades",
            "subcategory":"Construction",
            "type":"Services"
        }
    ],
    "sg:phone":"+1 409 296 3422",
    "sg:postcode":"77665",
    "sg:province":"TX",
    "sg:tags":[
        "pipe",
        "line"
    ],
    "wof:name":"Centana Pipe Line Co",
    "wof:placetype":"venue"
},
  "geometry": {"coordinates":[-94.338967,29.832698],"type":"Point"}
}