{
  "type": "Feature",
  "properties": {
    "iso:country":"US",
    "sg:address":"3005 Pinecrest Dr",
    "sg:city":"Austin",
    "sg:classifiers":[
        {
            "category":"Health Services",
            "subcategory":"Doctor",
            "type":"Services"
        }
    ],
    "sg:phone":"+1 512 452 6306",
    "sg:postcode":"78757",
    "sg:province":"TX",
    "wof:name":"Rapp Robt P MD",
    "wof:placetype":"venue"
},
  "geometry": {"coordinates":[-97.743354,30.350928],"type":"Point"}
}