{
  "type": "Feature",
  "properties": {
    "iso:country":"US",
    "sg:address":"701 E Plano Pkwy",
    "sg:city":"Plano",
    "sg:classifiers":[
        {
            "category":"Shopping",
            "type":"Retail Goods"
        },
        {
            "category":"Retail",
            "subcategory":"Laundry & Dry Cleaning",
            "type":"Services"
        }
    ],
    "sg:phone":"+1 972 422 4441",
    "sg:postcode":"75074",
    "sg:province":"TX",
    "sg:tags":[
        "water",
        "heater",
        "sales"
    ],
    "wof:name":"Cinnabar Equipment Co",
    "wof:placetype":"venue"
},
  "geometry": {"coordinates":[-96.70418600000001,33.007546],"type":"Point"}
}