{
  "type": "Feature",
  "properties": {
    "iso:country":"US",
    "sg:address":"8501 Quinton Ave",
    "sg:city":"Lubbock",
    "sg:classifiers":[
        {
            "category":"Real Estate",
            "subcategory":"Real Estate Agent",
            "type":"Services"
        }
    ],
    "sg:phone":"+1 806 698 8036",
    "sg:postcode":"79424",
    "sg:province":"TX",
    "wof:name":"Ja-Mar Enterprises",
    "wof:placetype":"venue"
},
  "geometry": {"coordinates":[-101.90604399999999,33.515932],"type":"Point"}
}