{
  "type": "Feature",
  "properties": {
    "iso:country":"US",
    "sg:address":"7300 Remcon Cir",
    "sg:city":"El Paso",
    "sg:classifiers":[
        {
            "category":"Health Services",
            "subcategory":"Doctor",
            "type":"Services"
        }
    ],
    "sg:phone":"+1 915 532 3600",
    "sg:postcode":"79912",
    "sg:province":"TX",
    "wof:name":"Harris Stephen R MD",
    "wof:placetype":"venue"
},
  "geometry": {"coordinates":[-106.566535,31.840151],"type":"Point"}
}