{
  "type": "Feature",
  "properties": {
    "iso:country":"US",
    "sg:address":"17610 Midway Rd",
    "sg:city":"Dallas",
    "sg:classifiers":[
        {
            "category":"Professional",
            "subcategory":"Management & Consulting",
            "type":"Services"
        }
    ],
    "sg:phone":"+1 972 306 3011",
    "sg:postcode":"75287",
    "sg:province":"TX",
    "sg:tags":[
        "consultant",
        "training"
    ],
    "wof:name":"Koegel Training & Development",
    "wof:placetype":"venue"
},
  "geometry": {"coordinates":[-96.841998,32.98777],"type":"Point"}
}