{
  "type": "Feature",
  "properties": {
    "iso:country":"US",
    "sg:address":"104 S Walnut St",
    "sg:city":"Weatherford",
    "sg:classifiers":[
        {
            "category":"Restaurant",
            "type":"Food & Drink"
        }
    ],
    "sg:phone":"+1 817 599 4311",
    "sg:postcode":"76086",
    "sg:province":"TX",
    "wof:name":"Whistle Hill Cafe",
    "wof:placetype":"venue"
},
  "geometry": {"coordinates":[-97.79436200000001,32.758537],"type":"Point"}
}