{
  "type": "Feature",
  "properties": {
    "iso:country":"US",
    "sg:address":"201 Bryan St",
    "sg:city":"Dayton",
    "sg:classifiers":[
        {
            "category":"Education",
            "subcategory":"Dance Studio",
            "type":"Public Place"
        }
    ],
    "sg:phone":"+1 936 257 9017",
    "sg:postcode":"77535",
    "sg:province":"TX",
    "sg:tags":[
        "instruction",
        "dancing"
    ],
    "wof:name":"Shana's Dance Place",
    "wof:placetype":"venue"
},
  "geometry": {"coordinates":[-94.88956,30.045673],"type":"Point"}
}