{
  "type": "Feature",
  "properties": {
    "iso:country":"US",
    "sg:address":"5101 Investment Dr",
    "sg:city":"Dallas",
    "sg:classifiers":[
        {
            "category":"Building & Trades",
            "subcategory":"Construction",
            "type":"Services"
        },
        {
            "category":"Food & Beverages",
            "subcategory":"Meat & Fish",
            "type":"Retail Goods"
        }
    ],
    "sg:phone":"+1 972 283 8501",
    "sg:postcode":"75236",
    "sg:province":"TX",
    "sg:tags":[
        "shop",
        "contractor"
    ],
    "sg:website":"www.standardmeat.com",
    "wof:name":"Standard Meat Co",
    "wof:placetype":"venue"
},
  "geometry": {"coordinates":[-96.911102,32.695599],"type":"Point"}
}