{
  "type": "Feature",
  "properties": {
    "iso:country":"US",
    "sg:address":"634 Plumlee Pl",
    "sg:city":"Coppell",
    "sg:classifiers":[
        {
            "category":"Autos & Motor Vehicles",
            "subcategory":"Auto Supplies",
            "type":"Retail Goods"
        }
    ],
    "sg:phone":"+1 972 745 4373",
    "sg:postcode":"75019",
    "sg:province":"TX",
    "sg:tags":[
        "glass"
    ],
    "wof:name":"Century Auto Glass",
    "wof:placetype":"venue"
},
  "geometry": {"coordinates":[-96.97346,32.978213],"type":"Point"}
}