{
  "type": "Feature",
  "properties": {
    "iso:country":"US",
    "sg:address":"12602 Nacogdoches Rd",
    "sg:city":"San Antonio",
    "sg:classifiers":[
        {
            "category":"Restaurant",
            "type":"Food & Drink"
        }
    ],
    "sg:phone":"+1 210 650 0012",
    "sg:postcode":"78217",
    "sg:province":"TX",
    "wof:name":"China Ho",
    "wof:placetype":"venue"
},
  "geometry": {"coordinates":[-98.399384,29.556532],"type":"Point"}
}