{
  "type": "Feature",
  "properties": {
    "iso:country":"US",
    "sg:address":"5021 Ave G",
    "sg:city":"Fort Worth",
    "sg:classifiers":[
        {
            "category":"Social Services",
            "type":"Services"
        }
    ],
    "sg:phone":"+1 817 535 7880",
    "sg:postcode":"76105",
    "sg:province":"TX",
    "sg:tags":[
        "youth",
        "organization",
        "center"
    ],
    "sg:website":"www.fortworthkids.org",
    "wof:name":"Boys & Girls Club",
    "wof:placetype":"venue"
},
  "geometry": {"coordinates":[-97.244468,32.730217],"type":"Point"}
}