{
  "type": "Feature",
  "properties": {
    "iso:country":"US",
    "sg:address":"800 High Crest Dr",
    "sg:city":"Azle",
    "sg:classifiers":[
        {
            "category":"Organizations",
            "subcategory":"Religious Organization",
            "type":"Services"
        }
    ],
    "sg:phone":"+1 817 444 2217",
    "sg:postcode":"76020",
    "sg:province":"TX",
    "sg:tags":[
        "church"
    ],
    "wof:name":"Holy Trinity Catholic Church",
    "wof:placetype":"venue"
},
  "geometry": {"coordinates":[-97.53854,32.906545],"type":"Point"}
}