{
  "type": "Feature",
  "properties": {
    "iso:country":"US",
    "sg:address":"920 Merry Ln",
    "sg:city":"Wharton",
    "sg:phone":"+1 979 532 3626",
    "sg:postcode":"77488",
    "sg:province":"TX",
    "sg:tags":[
        "farm",
        "corn"
    ],
    "wof:name":"Genzer Farms",
    "wof:placetype":"venue"
},
  "geometry": {"coordinates":[-96.088207,29.317006],"type":"Point"}
}