{
  "type": "Feature",
  "properties": {
    "iso:country":"US",
    "sg:address":"2113 Plains Ave",
    "sg:city":"Hereford",
    "sg:classifiers":[
        {
            "category":"Freight",
            "type":"Transportation"
        }
    ],
    "sg:phone":"+1 806 363 1874",
    "sg:postcode":"79045",
    "sg:province":"TX",
    "sg:tags":[
        "operator",
        "local",
        "trucking"
    ],
    "wof:name":"White Trucking",
    "wof:placetype":"venue"
},
  "geometry": {"coordinates":[-102.430351,34.82601],"type":"Point"}
}