{
  "type": "Feature",
  "properties": {
    "iso:country":"US",
    "sg:address":"2101 S I H 35",
    "sg:city":"Austin",
    "sg:classifiers":[
        {
            "category":"Building & Trades",
            "subcategory":"Construction",
            "type":"Services"
        }
    ],
    "sg:phone":"+1 512 444 2733",
    "sg:postcode":"78741",
    "sg:province":"TX",
    "sg:tags":[
        "air",
        "heating",
        "conditioning/hvac"
    ],
    "wof:name":"Polar Air Conditioning & Service Company",
    "wof:placetype":"venue"
},
  "geometry": {"coordinates":[-97.739403,30.235901],"type":"Point"}
}