{
  "type": "Feature",
  "properties": {
    "iso:country":"US",
    "sg:address":"1407 Lomaland Dr",
    "sg:city":"El Paso",
    "sg:classifiers":[
        {
            "category":"Personal",
            "subcategory":"Beauty Salon",
            "type":"Services"
        }
    ],
    "sg:phone":"+1 915 594 3087",
    "sg:postcode":"79935",
    "sg:province":"TX",
    "sg:tags":[
        "shop"
    ],
    "wof:name":"Hair N Nail Productions",
    "wof:placetype":"venue"
},
  "geometry": {"coordinates":[-106.326928,31.751481],"type":"Point"}
}