{
  "type": "Feature",
  "properties": {
    "iso:country":"US",
    "sg:address":"210 Vista Dr",
    "sg:city":"Granbury",
    "sg:classifiers":[
        {
            "category":"Professional",
            "subcategory":"Accounting & Tax Preparation",
            "type":"Services"
        }
    ],
    "sg:phone":"+1 817 279 7386",
    "sg:postcode":"76049",
    "sg:province":"TX",
    "wof:name":"Providers Billing Service",
    "wof:placetype":"venue"
},
  "geometry": {"coordinates":[-97.751687,32.447949],"type":"Point"}
}