{
  "type": "Feature",
  "properties": {
    "iso:country":"US",
    "sg:address":"2509 County Road 184",
    "sg:city":"Ovalo",
    "sg:classifiers":[
        {
            "category":"Farming",
            "subcategory":"Farm",
            "type":"Manufacturing & Wholesale Goods"
        }
    ],
    "sg:phone":"+1 325 767 2203",
    "sg:postcode":"79541",
    "sg:province":"TX",
    "wof:name":"Calwyn L Walters Farms",
    "wof:placetype":"venue"
},
  "geometry": {"coordinates":[-99.95253099999999,32.14392],"type":"Point"}
}