{
  "type": "Feature",
  "properties": {
    "iso:country":"US",
    "sg:address":"3131 Rolling Knoll Ct",
    "sg:city":"Farmers Branch",
    "sg:classifiers":[
        {
            "category":"Home & Garden",
            "subcategory":"Home Furnishings",
            "type":"Retail Goods"
        }
    ],
    "sg:phone":"+1 972 484 2099",
    "sg:postcode":"75234",
    "sg:province":"TX",
    "sg:tags":[
        "kitchen",
        "accessory"
    ],
    "wof:name":"Abundant Health Products",
    "wof:placetype":"venue"
},
  "geometry": {"coordinates":[-96.869619,32.934931],"type":"Point"}
}