{
  "type": "Feature",
  "properties": {
    "iso:country":"US",
    "sg:address":"1012 Mo Pac Cir",
    "sg:city":"Austin",
    "sg:classifiers":[
        {
            "category":"Health Services",
            "subcategory":"Doctor",
            "type":"Services"
        },
        {
            "category":"Health Services",
            "subcategory":"Clinic",
            "type":"Services"
        }
    ],
    "sg:phone":"+1 512 825 3283",
    "sg:postcode":"78746",
    "sg:province":"TX",
    "sg:tags":[
        "psychological",
        "psychologist"
    ],
    "wof:name":"David R Clemons P C",
    "wof:placetype":"venue"
},
  "geometry": {"coordinates":[-97.783822,30.266301],"type":"Point"}
}