{
  "type": "Feature",
  "properties": {
    "iso:country":"US",
    "sg:address":"227 S Glenwood Blvd",
    "sg:city":"Tyler",
    "sg:classifiers":[
        {
            "category":"Personal",
            "subcategory":"Beauty Salon",
            "type":"Services"
        }
    ],
    "sg:phone":"+1 903 593 5840",
    "sg:postcode":"75702",
    "sg:province":"TX",
    "wof:name":"Blessed Hands Salon & Boutique",
    "wof:placetype":"venue"
},
  "geometry": {"coordinates":[-95.318139,32.349252],"type":"Point"}
}