{
  "type": "Feature",
  "properties": {
    "iso:country":"US",
    "sg:address":"517 18th Ave N",
    "sg:city":"Texas City",
    "sg:classifiers":[
        {
            "category":"Social Services",
            "type":"Services"
        }
    ],
    "sg:phone":"+1 409 965 9007",
    "sg:postcode":"77590",
    "sg:province":"TX",
    "sg:tags":[
        "organization",
        "welfare"
    ],
    "wof:name":"Christian Women Job Corp GA",
    "wof:placetype":"venue"
},
  "geometry": {"coordinates":[-94.90124900000001,29.402016],"type":"Point"}
}