{
  "type": "Feature",
  "properties": {
    "iso:country":"US",
    "sg:address":"1506 N Crockett Ave",
    "sg:city":"Cameron",
    "sg:classifiers":[
        {
            "category":"Retail",
            "subcategory":"Auto Repair",
            "type":"Services"
        }
    ],
    "sg:phone":"+1 254 697 2222",
    "sg:postcode":"76520",
    "sg:province":"TX",
    "sg:tags":[
        "transmission"
    ],
    "wof:name":"Cameron Transmissions",
    "wof:placetype":"venue"
},
  "geometry": {"coordinates":[-96.975088,30.862718],"type":"Point"}
}