{
  "type": "Feature",
  "properties": {
    "iso:country":"US",
    "sg:address":"549 Edgeview Dr",
    "sg:city":"Grand Prairie",
    "sg:classifiers":[
        {
            "category":"Shopping",
            "subcategory":"Bicycles & Sporting Goods",
            "type":"Retail Goods"
        }
    ],
    "sg:phone":"+1 972 264 8031",
    "sg:postcode":"75052",
    "sg:province":"TX",
    "sg:tags":[
        "medical"
    ],
    "wof:name":"Sport Physicals of Texas",
    "wof:placetype":"venue"
},
  "geometry": {"coordinates":[-96.998926,32.669449],"type":"Point"}
}