{
  "type": "Feature",
  "properties": {
    "iso:country":"US",
    "sg:address":"302 S David St",
    "sg:city":"San Angelo",
    "sg:classifiers":[
        {
            "category":"Building & Trades",
            "subcategory":"Construction",
            "type":"Services"
        }
    ],
    "sg:phone":"+1 325 655 7080",
    "sg:postcode":"76903",
    "sg:province":"TX",
    "sg:tags":[
        "general",
        "contractor"
    ],
    "wof:name":"Contractors & Hm Owners Fndng",
    "wof:placetype":"venue"
},
  "geometry": {"coordinates":[-100.444586,31.457019],"type":"Point"}
}