{
  "type": "Feature",
  "properties": {
    "iso:country":"US",
    "sg:address":"2250 Kelly Dr",
    "sg:city":"Lackland Afb",
    "sg:classifiers":[
        {
            "category":"Shopping",
            "subcategory":"Clothing, Apparel, & Fashions",
            "type":"Retail Goods"
        }
    ],
    "sg:phone":"+1 210 674 0848",
    "sg:postcode":"78236",
    "sg:province":"TX",
    "sg:tags":[
        "salvage",
        "surplus",
        "merchandise"
    ],
    "wof:name":"Lackland BX Shoppette",
    "wof:placetype":"venue"
},
  "geometry": {"coordinates":[-98.617097,29.386904],"type":"Point"}
}