{
  "type": "Feature",
  "properties": {
    "iso:country":"US",
    "sg:address":"10614 Tall Oak Dr",
    "sg:city":"Fort Worth",
    "sg:classifiers":[
        {
            "category":"Shopping",
            "subcategory":"Used Merchandise",
            "type":"Retail Goods"
        }
    ],
    "sg:phone":"+1 817 246 1856",
    "sg:postcode":"76108",
    "sg:province":"TX",
    "sg:tags":[
        "antique"
    ],
    "wof:name":"Texas Relics",
    "wof:placetype":"venue"
},
  "geometry": {"coordinates":[-97.50681400000001,32.758535],"type":"Point"}
}