{
  "type": "Feature",
  "properties": {
    "iso:country":"US",
    "sg:address":"2701 White Settlement Rd",
    "sg:city":"Fort Worth",
    "sg:classifiers":[
        {
            "category":"Retail",
            "subcategory":"Auto Repair",
            "type":"Services"
        }
    ],
    "sg:phone":"+1 817 870 5096",
    "sg:postcode":"76107",
    "sg:province":"TX",
    "sg:tags":[
        "repairing",
        "automobile"
    ],
    "wof:name":"Dealer Alternative",
    "wof:placetype":"venue"
},
  "geometry": {"coordinates":[-97.356397,32.759102],"type":"Point"}
}