{
  "type": "Feature",
  "properties": {
    "iso:country":"US",
    "sg:address":"10210 Vassar Rd",
    "sg:city":"Leander",
    "sg:classifiers":[
        {
            "category":"Professional",
            "type":"Services"
        }
    ],
    "sg:phone":"+1 512 267 6617",
    "sg:postcode":"78645",
    "sg:province":"TX",
    "wof:name":"Panoramic Hills Homeowners As",
    "wof:placetype":"venue"
},
  "geometry": {"coordinates":[-97.93784100000001,30.492659],"type":"Point"}
}