{
  "type": "Feature",
  "properties": {
    "iso:country":"US",
    "sg:address":"308 E Main St",
    "sg:city":"Fredericksburg",
    "sg:classifiers":[
        {
            "category":"Restaurant",
            "type":"Food & Drink"
        }
    ],
    "sg:phone":"+1 830 997 7437",
    "sg:postcode":"78624",
    "sg:province":"TX",
    "sg:tags":[
        "eating"
    ],
    "wof:name":"Pancione's",
    "wof:placetype":"venue"
},
  "geometry": {"coordinates":[-98.868753,30.272648],"type":"Point"}
}