{
  "type": "Feature",
  "properties": {
    "iso:country":"US",
    "sg:address":"5812 Culebra Rd",
    "sg:city":"San Antonio",
    "sg:classifiers":[
        {
            "category":"Travel",
            "subcategory":"Hotels & Motels",
            "type":"Entertainment"
        }
    ],
    "sg:phone":"+1 210 431 9906",
    "sg:postcode":"78228",
    "sg:province":"TX",
    "wof:name":"Culebra Motel",
    "wof:placetype":"venue"
},
  "geometry": {"coordinates":[-98.594973,29.448494],"type":"Point"}
}