{
  "type": "Feature",
  "properties": {
    "iso:country":"US",
    "sg:address":"32980 I- 10 W",
    "sg:city":"Boerne",
    "sg:classifiers":[
        {
            "category":"Home & Garden",
            "subcategory":"Garden Supply",
            "type":"Retail Goods"
        }
    ],
    "sg:phone":"+1 830 816 1845",
    "sg:postcode":"78006",
    "sg:province":"TX",
    "sg:tags":[
        "landscaping",
        "equipment"
    ],
    "wof:name":"Hill Country Equipment Svc",
    "wof:placetype":"venue"
},
  "geometry": {"coordinates":[-98.711876,29.760051],"type":"Point"}
}