{
  "type": "Feature",
  "properties": {
    "iso:country":"US",
    "sg:address":"615 E Walnut Cir",
    "sg:city":"Garland",
    "sg:classifiers":[
        {
            "category":"Wholesale",
            "subcategory":"Motor Vehicles",
            "type":"Manufacturing & Wholesale Goods"
        }
    ],
    "sg:phone":"+1 972 276 3939",
    "sg:postcode":"75040",
    "sg:province":"TX",
    "sg:tags":[
        "bus",
        "used"
    ],
    "wof:name":"Lavon Drive Baptist Church Bus",
    "wof:placetype":"venue"
},
  "geometry": {"coordinates":[-96.626441,32.916619],"type":"Point"}
}