{
  "type": "Feature",
  "properties": {
    "iso:country":"US",
    "sg:address":"702 Cedar Ridge Dr",
    "sg:city":"Pflugerville",
    "sg:classifiers":[
        {
            "category":"Social Services",
            "subcategory":"Child Care",
            "type":"Services"
        }
    ],
    "sg:phone":"+1 512 990 7223",
    "sg:postcode":"78660",
    "sg:province":"TX",
    "sg:tags":[
        "day"
    ],
    "wof:name":"Tree House Kids Inc",
    "wof:placetype":"venue"
},
  "geometry": {"coordinates":[-97.612942,30.441278],"type":"Point"}
}