{
  "type": "Feature",
  "properties": {
    "iso:country":"US",
    "sg:address":"12586 Research Blvd",
    "sg:city":"Austin",
    "sg:classifiers":[
        {
            "category":"Donuts",
            "subcategory":"None",
            "type":"Food & Drink"
        }
    ],
    "sg:phone":"+1 512 219 0119",
    "sg:postcode":"78759",
    "sg:province":"TX",
    "sg:tags":[
        "shop"
    ],
    "sg:website":"http://www.krispykreme.com/",
    "wof:name":"Krispy Kreme",
    "wof:placetype":"venue"
},
  "geometry": {"coordinates":[-97.762513,30.430334],"type":"Point"}
}