{
  "type": "Feature",
  "properties": {
    "iso:country":"US",
    "sg:address":"5627 Charlie Chan Dr",
    "sg:city":"San Antonio",
    "sg:classifiers":[
        {
            "category":"Autos & Motor Vehicles",
            "subcategory":"Fuel & Gas Station",
            "type":"Retail Goods"
        }
    ],
    "sg:phone":"+1 210 684 5287",
    "sg:postcode":"78240",
    "sg:province":"TX",
    "sg:tags":[
        "station",
        "gasoline"
    ],
    "wof:name":"Exxon Exes Club of San An",
    "wof:placetype":"venue"
},
  "geometry": {"coordinates":[-98.601567,29.503285],"type":"Point"}
}