{
  "type": "Feature",
  "properties": {
    "iso:country":"US",
    "sg:address":"3060 Story Rd W",
    "sg:city":"Irving",
    "sg:classifiers":[
        {
            "category":"Shopping",
            "subcategory":"Bicycles & Sporting Goods",
            "type":"Retail Goods"
        }
    ],
    "sg:phone":"+1 800 242 6790",
    "sg:postcode":"75038",
    "sg:province":"TX",
    "wof:name":"Diamond S Spirit Wear",
    "wof:placetype":"venue"
},
  "geometry": {"coordinates":[-96.98645999999999,32.871536],"type":"Point"}
}