{
  "type": "Feature",
  "properties": {
    "iso:country":"US",
    "sg:address":"3129 Regency",
    "sg:city":"Carrollton",
    "sg:classifiers":[
        {
            "category":"Wholesale",
            "subcategory":"Electrical",
            "type":"Manufacturing & Wholesale Goods"
        }
    ],
    "sg:phone":"+1 972 394 9400",
    "sg:postcode":"75007",
    "sg:province":"TX",
    "sg:tags":[
        "telephone"
    ],
    "wof:name":"Custom Communications Of Texas",
    "wof:placetype":"venue"
},
  "geometry": {"coordinates":[-96.91262999999999,33.001419],"type":"Point"}
}