{
  "type": "Feature",
  "properties": {
    "iso:country":"US",
    "sg:address":"150 Browning Ct",
    "sg:city":"Springtown",
    "sg:classifiers":[
        {
            "category":"Retail",
            "subcategory":"Auto Repair",
            "type":"Services"
        }
    ],
    "sg:phone":"+1 817 220 0867",
    "sg:postcode":"76082",
    "sg:province":"TX",
    "sg:tags":[
        "transmission"
    ],
    "wof:name":"A Quality Transmission",
    "wof:placetype":"venue"
},
  "geometry": {"coordinates":[-97.729467,32.926164],"type":"Point"}
}