{
  "type": "Feature",
  "properties": {
    "iso:country":"US",
    "sg:address":"21610 Roan Bluff",
    "sg:city":"San Antonio",
    "sg:classifiers":[
        {
            "category":"Shopping",
            "type":"Retail Goods"
        }
    ],
    "sg:phone":"+1 210 832 9777",
    "sg:postcode":"78259",
    "sg:province":"TX",
    "sg:tags":[
        "art",
        "gallery",
        "dealer"
    ],
    "wof:name":"Socorro Martinez Galeria",
    "wof:placetype":"venue"
},
  "geometry": {"coordinates":[-98.44556,29.640962],"type":"Point"}
}