{
  "type": "Feature",
  "properties": {
    "iso:country":"US",
    "sg:address":"529 Gaslight Blvd",
    "sg:city":"Lufkin",
    "sg:classifiers":[
        {
            "category":"Freight",
            "type":"Transportation"
        }
    ],
    "sg:phone":"+1 936 639 1502",
    "sg:postcode":"75904",
    "sg:province":"TX",
    "sg:tags":[
        "consultant"
    ],
    "wof:name":"Dot Drug Testing & Physicals",
    "wof:placetype":"venue"
},
  "geometry": {"coordinates":[-94.751599,31.328856],"type":"Point"}
}