{
  "type": "Feature",
  "properties": {
    "iso:country":"US",
    "sg:address":"1404 Eagle Lakes Dr",
    "sg:city":"Friendswood",
    "sg:classifiers":[
        {
            "category":"Manufacturing",
            "subcategory":"Tools & Machinery",
            "type":"Manufacturing & Wholesale Goods"
        }
    ],
    "sg:phone":"+1 281 992 9229",
    "sg:postcode":"77546",
    "sg:province":"TX",
    "sg:tags":[
        "machine",
        "vending",
        "mfg"
    ],
    "wof:name":"K & R Enterprises",
    "wof:placetype":"venue"
},
  "geometry": {"coordinates":[-95.196641,29.49072],"type":"Point"}
}