{
  "type": "Feature",
  "properties": {
    "iso:country":"US",
    "sg:address":"3007 Dancy St",
    "sg:city":"Austin",
    "sg:classifiers":[
        {
            "category":"Professional",
            "subcategory":"Lawyer & Legal Services",
            "type":"Services"
        }
    ],
    "sg:phone":"+1 512 435 6666",
    "sg:postcode":"78722",
    "sg:province":"TX",
    "sg:tags":[
        "attorney"
    ],
    "wof:name":"Lanny Vickery Law Office",
    "wof:placetype":"venue"
},
  "geometry": {"coordinates":[-97.721497,30.2875],"type":"Point"}
}