{
  "type": "Feature",
  "properties": {
    "iso:country":"US",
    "sg:address":"2847 Wuthering Heights Dr",
    "sg:city":"Houston",
    "sg:classifiers":[
        {
            "category":"Freight",
            "type":"Transportation"
        }
    ],
    "sg:phone":"+1 713 433 4960",
    "sg:postcode":"77045",
    "sg:province":"TX",
    "sg:tags":[
        "operator",
        "local",
        "trucking"
    ],
    "wof:name":"Unique Way Delivery Service",
    "wof:placetype":"venue"
},
  "geometry": {"coordinates":[-95.417497,29.634023],"type":"Point"}
}