{
  "type": "Feature",
  "properties": {
    "iso:country":"US",
    "sg:address":"8055 West Ave",
    "sg:city":"San Antonio",
    "sg:classifiers":[
        {
            "category":"Sports & Exercise",
            "subcategory":"Gym",
            "type":"Entertainment"
        }
    ],
    "sg:phone":"+1 210 979 9642",
    "sg:postcode":"78213",
    "sg:province":"TX",
    "sg:tags":[
        "fitness",
        "physical",
        "facility"
    ],
    "wof:name":"Yoga In Motion",
    "wof:placetype":"venue"
},
  "geometry": {"coordinates":[-98.52075499999999,29.534775],"type":"Point"}
}