{
  "type": "Feature",
  "properties": {
    "iso:country":"US",
    "sg:address":"100 Highridge Dr",
    "sg:city":"Little Elm",
    "sg:classifiers":[
        {
            "category":"Government",
            "subcategory":"Office",
            "type":"Public Place"
        }
    ],
    "sg:phone":"+1 972 294 5555",
    "sg:postcode":"75068",
    "sg:province":"TX",
    "sg:tags":[
        "association",
        "general"
    ],
    "wof:name":"Town Hall",
    "wof:placetype":"venue"
},
  "geometry": {"coordinates":[-96.97207899999999,33.14356],"type":"Point"}
}