{
  "type": "Feature",
  "properties": {
    "iso:country":"US",
    "sg:address":"13820 Waxahachie St",
    "sg:city":"Houston",
    "sg:classifiers":[
        {
            "category":"Retail",
            "subcategory":"Auto Repair",
            "type":"Services"
        }
    ],
    "sg:phone":"+1 713 451 1852",
    "sg:postcode":"77015",
    "sg:province":"TX",
    "sg:tags":[
        "repairing",
        "automobile"
    ],
    "wof:name":"Jalpa Auto Repair",
    "wof:placetype":"venue"
},
  "geometry": {"coordinates":[-95.1785,29.779768],"type":"Point"}
}