{
  "type": "Feature",
  "properties": {
    "iso:country":"US",
    "sg:address":"3101 Matagorda St",
    "sg:city":"El Paso",
    "sg:classifiers":[
        {
            "category":"Government",
            "subcategory":"Police Station",
            "type":"Public Place"
        }
    ],
    "sg:phone":"+1 915 598 6564",
    "sg:postcode":"79936",
    "sg:province":"TX",
    "sg:tags":[
        "officer"
    ],
    "wof:name":"Molina Armando",
    "wof:placetype":"venue"
},
  "geometry": {"coordinates":[-106.310193,31.786465],"type":"Point"}
}