{
  "type": "Feature",
  "properties": {
    "iso:country":"US",
    "sg:address":"1603 N Wayside Dr",
    "sg:city":"Houston",
    "sg:classifiers":[
        {
            "category":"Autos & Motor Vehicles",
            "subcategory":"Automobile Sales",
            "type":"Retail Goods"
        }
    ],
    "sg:phone":"+1 713 675 3310",
    "sg:postcode":"77020",
    "sg:province":"TX",
    "sg:tags":[
        "used"
    ],
    "wof:name":"Marine Auto Sales",
    "wof:placetype":"venue"
},
  "geometry": {"coordinates":[-95.29172699999999,29.776719],"type":"Point"}
}