{
  "type": "Feature",
  "properties": {
    "iso:country":"US",
    "sg:address":"12818 Veterans Memorial Dr",
    "sg:city":"Houston",
    "sg:classifiers":[
        {
            "category":"Retail",
            "subcategory":"Auto Repair",
            "type":"Services"
        }
    ],
    "sg:phone":"+1 281 444 4708",
    "sg:postcode":"77014",
    "sg:province":"TX",
    "wof:name":"Japan Car Care",
    "wof:placetype":"venue"
},
  "geometry": {"coordinates":[-95.488405,29.974742],"type":"Point"}
}