{
  "type": "Feature",
  "properties": {
    "iso:country":"US",
    "sg:address":"6712 Curtis Rd",
    "sg:city":"Colleyville",
    "sg:classifiers":[
        {
            "category":"Building & Trades",
            "subcategory":"Construction",
            "type":"Services"
        }
    ],
    "sg:phone":"+1 817 281 0354",
    "sg:postcode":"76034",
    "sg:province":"TX",
    "sg:tags":[
        "contractor"
    ],
    "wof:name":"Cecil H Bolling Masonry C",
    "wof:placetype":"venue"
},
  "geometry": {"coordinates":[-97.185233,32.906608],"type":"Point"}
}