{
  "type": "Feature",
  "properties": {
    "iso:country":"US",
    "sg:address":"17845 Luckey Rd",
    "sg:city":"Atascosa",
    "sg:classifiers":[
        {
            "category":"Retail",
            "subcategory":"Auto Repair",
            "type":"Services"
        }
    ],
    "sg:phone":"+1 210 622 9379",
    "sg:postcode":"78002",
    "sg:province":"TX",
    "sg:tags":[
        "general"
    ],
    "wof:name":"Gomezs Automotive Paint & Body",
    "wof:placetype":"venue"
},
  "geometry": {"coordinates":[-98.748221,29.247486],"type":"Point"}
}