{
  "type": "Feature",
  "properties": {
    "iso:country":"US",
    "sg:address":"115 W Lamberth Rd",
    "sg:city":"Sherman",
    "sg:classifiers":[
        {
            "category":"Professional",
            "subcategory":"Employment Agencies",
            "type":"Services"
        }
    ],
    "sg:phone":"+1 903 870 7090",
    "sg:postcode":"75092",
    "sg:province":"TX",
    "sg:tags":[
        "opportunity"
    ],
    "wof:name":"Adecco",
    "wof:placetype":"venue"
},
  "geometry": {"coordinates":[-96.616955,33.661787],"type":"Point"}
}