{
  "type": "Feature",
  "properties": {
    "iso:country":"US",
    "sg:address":"12931 Memorial Dr",
    "sg:city":"Houston",
    "sg:classifiers":[
        {
            "category":"Wholesale",
            "subcategory":"Machinery & Supplies",
            "type":"Manufacturing & Wholesale Goods"
        },
        {
            "category":"Building & Trades",
            "subcategory":"Equipment Rental",
            "type":"Services"
        }
    ],
    "sg:phone":"+1 713 827 8548",
    "sg:postcode":"77079",
    "sg:province":"TX",
    "sg:tags":[
        "field",
        "industrial",
        "oil"
    ],
    "sg:website":"http://www.c-a-m.com",
    "wof:name":"Valves & Measurment",
    "wof:placetype":"venue"
},
  "geometry": {"coordinates":[-95.56552499999999,29.772708],"type":"Point"}
}