{
  "type": "Feature",
  "properties": {
    "iso:country":"US",
    "sg:address":"11818 Rosser Rd",
    "sg:city":"Dallas",
    "sg:classifiers":[
        {
            "category":"Recreation",
            "type":"Entertainment"
        }
    ],
    "sg:phone":"+1 972 243 9298",
    "sg:postcode":"75244",
    "sg:province":"TX",
    "sg:tags":[
        "placement",
        "club",
        "workers'",
        "membership",
        "volunteer",
        "pool",
        "swimming"
    ],
    "wof:name":"Glen Cove Swim Club Inc",
    "wof:placetype":"venue"
},
  "geometry": {"coordinates":[-96.84684799999999,32.91021],"type":"Point"}
}