{
  "type": "Feature",
  "properties": {
    "iso:country":"US",
    "sg:address":"2000 Ross-Osage St",
    "sg:city":"Amarillo",
    "sg:classifiers":[
        {
            "category":"Restaurant",
            "type":"Food & Drink"
        }
    ],
    "sg:phone":"+1 806 373 6775",
    "sg:postcode":"79103",
    "sg:province":"TX",
    "wof:name":"Wendy's",
    "wof:placetype":"venue"
},
  "geometry": {"coordinates":[-101.816924,35.190308],"type":"Point"}
}