{
  "type": "Feature",
  "properties": {
    "iso:country":"US",
    "sg:address":"1500 Oakland Pl",
    "sg:city":"Fort Worth",
    "sg:classifiers":[
        {
            "category":"Shopping",
            "subcategory":"Musical Instruments",
            "type":"Retail Goods"
        }
    ],
    "sg:phone":"+1 817 429 1993",
    "sg:postcode":"76103",
    "sg:province":"TX",
    "wof:name":"Pepper J W of Dallas",
    "wof:placetype":"venue"
},
  "geometry": {"coordinates":[-97.256311,32.75745],"type":"Point"}
}