{
  "type": "Feature",
  "properties": {
    "iso:country":"US",
    "sg:address":"9650 North Fwy",
    "sg:city":"Houston",
    "sg:classifiers":[
        {
            "category":"Autos & Motor Vehicles",
            "subcategory":"Motorcycle Sales",
            "type":"Retail Goods"
        }
    ],
    "sg:phone":"+1 281 445 4227",
    "sg:postcode":"77037",
    "sg:province":"TX",
    "sg:website":"www.teammancusopowersports.com",
    "wof:name":"A J Foyt Cycles",
    "wof:placetype":"venue"
},
  "geometry": {"coordinates":[-95.41179700000001,29.9041],"type":"Point"}
}