{
  "type": "Feature",
  "properties": {
    "iso:country":"US",
    "sg:address":"9102 Pagewood Ln",
    "sg:city":"Houston",
    "sg:classifiers":[
        {
            "category":"Home & Garden",
            "subcategory":"Building Materials",
            "type":"Retail Goods"
        }
    ],
    "sg:phone":"+1 713 953 1697",
    "sg:postcode":"77063",
    "sg:province":"TX",
    "wof:name":"Lopez Overhead Doors",
    "wof:placetype":"venue"
},
  "geometry": {"coordinates":[-95.524084,29.726184],"type":"Point"}
}