{
  "type": "Feature",
  "properties": {
    "iso:country":"US",
    "sg:address":"23221 Aldine Westfield Rd",
    "sg:city":"Spring",
    "sg:classifiers":[
        {
            "category":"Insurance",
            "subcategory":"Insurance Agent",
            "type":"Services"
        }
    ],
    "sg:phone":"+1 281 355 6283",
    "sg:postcode":"77373",
    "sg:province":"TX",
    "wof:name":"Ramirez Assoc Ins Agency",
    "wof:placetype":"venue"
},
  "geometry": {"coordinates":[-95.38876,30.051434],"type":"Point"}
}