{
  "type": "Feature",
  "properties": {
    "iso:country":"US",
    "sg:address":"1520 Goodyear Dr",
    "sg:city":"El Paso",
    "sg:classifiers":[
        {
            "category":"Manufacturing",
            "subcategory":"Metals",
            "type":"Manufacturing & Wholesale Goods"
        }
    ],
    "sg:phone":"+1 915 590 6610",
    "sg:postcode":"79936",
    "sg:province":"TX",
    "sg:tags":[
        "spring",
        "wire",
        "mfg"
    ],
    "wof:name":"PA-Ted Spring Co Inc",
    "wof:placetype":"venue"
},
  "geometry": {"coordinates":[-106.311037,31.744582],"type":"Point"}
}