{
  "type": "Feature",
  "properties": {
    "iso:country":"US",
    "sg:address":"5200 Meadow Creek Dr",
    "sg:city":"Dallas",
    "sg:classifiers":[
        {
            "category":"Health Services",
            "subcategory":"Doctor",
            "type":"Services"
        }
    ],
    "sg:phone":"+1 972 490 1367",
    "sg:postcode":"75248",
    "sg:province":"TX",
    "sg:tags":[
        "dentist"
    ],
    "wof:name":"John B Gatewood DDS",
    "wof:placetype":"venue"
},
  "geometry": {"coordinates":[-96.79163699999999,32.962516],"type":"Point"}
}