{
  "type": "Feature",
  "properties": {
    "iso:country":"US",
    "sg:address":"8021 FM 78",
    "sg:city":"San Antonio",
    "sg:classifiers":[
        {
            "category":"Food & Beverages",
            "subcategory":"Liquor & Beverages",
            "type":"Retail Goods"
        }
    ],
    "sg:phone":"+1 210 661 9364",
    "sg:postcode":"78244",
    "sg:province":"TX",
    "wof:name":"Liquor Barrel",
    "wof:placetype":"venue"
},
  "geometry": {"coordinates":[-98.32593,29.495661],"type":"Point"}
}