{
  "type": "Feature",
  "properties": {
    "iso:country":"US",
    "sg:address":"4429 Duval St",
    "sg:city":"Austin",
    "sg:classifiers":[
        {
            "category":"Food & Beverages",
            "subcategory":"Groceries & Convenience Stores",
            "type":"Retail Goods"
        }
    ],
    "sg:phone":"+1 512 323 5080",
    "sg:postcode":"78751",
    "sg:province":"TX",
    "wof:name":"Sunrise Super Stop 9",
    "wof:placetype":"venue"
},
  "geometry": {"coordinates":[-97.723428,30.308688],"type":"Point"}
}