{
  "type": "Feature",
  "properties": {
    "iso:country":"US",
    "sg:address":"8908 Chester Forest St",
    "sg:city":"Austin",
    "sg:classifiers":[
        {
            "category":"Personal",
            "type":"Services"
        }
    ],
    "sg:phone":"+1 512 250 5508",
    "sg:postcode":"78729",
    "sg:province":"TX",
    "sg:tags":[
        "therapist",
        "massage"
    ],
    "wof:name":"Elysium Family Therapeutics",
    "wof:placetype":"venue"
},
  "geometry": {"coordinates":[-97.77589399999999,30.456472],"type":"Point"}
}