{
  "type": "Feature",
  "properties": {
    "iso:country":"US",
    "sg:address":"3201 Shaver St",
    "sg:city":"Pasadena",
    "sg:classifiers":[
        {
            "category":"Autos & Motor Vehicles",
            "subcategory":"Automobile Sales",
            "type":"Retail Goods"
        }
    ],
    "sg:phone":"+1 713 910 7500",
    "sg:postcode":"77504",
    "sg:province":"TX",
    "sg:tags":[
        "new",
        "used",
        "car"
    ],
    "wof:name":"Barney's Auto Sales",
    "wof:placetype":"venue"
},
  "geometry": {"coordinates":[-95.20808700000001,29.662136],"type":"Point"}
}