{
  "type": "Feature",
  "properties": {
    "iso:country":"US",
    "sg:address":"815 McKinney St",
    "sg:city":"Farmersville",
    "sg:classifiers":[
        {
            "category":"Food & Beverages",
            "subcategory":"Groceries & Convenience Stores",
            "type":"Retail Goods"
        }
    ],
    "sg:phone":"+1 972 782 7357",
    "sg:postcode":"75442",
    "sg:province":"TX",
    "wof:name":"Quick Check",
    "wof:placetype":"venue"
},
  "geometry": {"coordinates":[-96.368697,33.163794],"type":"Point"}
}