{
  "type": "Feature",
  "properties": {
    "iso:country":"US",
    "sg:address":"616 Aqua Vista Dr",
    "sg:city":"Granbury",
    "sg:classifiers":[
        {
            "category":"Shopping",
            "subcategory":"Crafts & Fabrics",
            "type":"Retail Goods"
        }
    ],
    "sg:phone":"+1 817 573 6793",
    "sg:postcode":"76049",
    "sg:province":"TX",
    "sg:tags":[
        "sewing"
    ],
    "wof:name":"Treasured Threads",
    "wof:placetype":"venue"
},
  "geometry": {"coordinates":[-97.806651,32.498851],"type":"Point"}
}