{
  "type": "Feature",
  "properties": {
    "iso:country":"US",
    "sg:address":"9402 Clay Rd",
    "sg:city":"Houston",
    "sg:classifiers":[
        {
            "category":"Wholesale",
            "subcategory":"Auto Parts",
            "type":"Manufacturing & Wholesale Goods"
        }
    ],
    "sg:phone":"+1 713 690 3421",
    "sg:postcode":"77080",
    "sg:province":"TX",
    "sg:tags":[
        "tire"
    ],
    "wof:name":"Julio's Tire Service",
    "wof:placetype":"venue"
},
  "geometry": {"coordinates":[-95.523804,29.832701],"type":"Point"}
}