{
  "type": "Feature",
  "properties": {
    "iso:country":"US",
    "sg:address":"5732 Richmond Ave",
    "sg:city":"Dallas",
    "sg:classifiers":[
        {
            "category":"Personal",
            "subcategory":"Psychics & Astrologers",
            "type":"Services"
        }
    ],
    "sg:phone":"+1 214 515 9727",
    "sg:postcode":"75206",
    "sg:province":"TX",
    "sg:website":"http://ThePsychicPalm.Com",
    "wof:name":"The Psychic Palm",
    "wof:placetype":"venue"
},
  "geometry": {"coordinates":[-96.768691,32.815685],"type":"Point"}
}