{
  "type": "Feature",
  "properties": {
    "iso:country":"US",
    "sg:address":"1320 Ferris Ave",
    "sg:city":"Waxahachie",
    "sg:classifiers":[
        {
            "category":"Health Services",
            "subcategory":"Doctor",
            "type":"Services"
        }
    ],
    "sg:phone":"+1 972 937 0429",
    "sg:postcode":"75165",
    "sg:province":"TX",
    "wof:name":"Priscilla Parker DDS",
    "wof:placetype":"venue"
},
  "geometry": {"coordinates":[-96.84286400000001,32.40033],"type":"Point"}
}