{
  "type": "Feature",
  "properties": {
    "iso:country":"US",
    "sg:address":"6824 Gateway Blvd E",
    "sg:city":"El Paso",
    "sg:classifiers":[
        {
            "category":"Home & Garden",
            "subcategory":"Carpets & Floor Coverings",
            "type":"Retail Goods"
        }
    ],
    "sg:phone":"+1 915 779 3268",
    "sg:postcode":"79915",
    "sg:province":"TX",
    "sg:tags":[
        "dealer",
        "rug"
    ],
    "wof:name":"Carpet Shop",
    "wof:placetype":"venue"
},
  "geometry": {"coordinates":[-106.388884,31.77643],"type":"Point"}
}