{
  "type": "Feature",
  "properties": {
    "iso:country":"US",
    "sg:address":"712 N Ave G",
    "sg:city":"Clifton",
    "sg:classifiers":[
        {
            "category":"Personal",
            "subcategory":"Beauty Salon",
            "type":"Services"
        }
    ],
    "sg:phone":"+1 254 675 2727",
    "sg:postcode":"76634",
    "sg:province":"TX",
    "sg:tags":[
        "shop"
    ],
    "wof:name":"Special FX Unlimited Salon",
    "wof:placetype":"venue"
},
  "geometry": {"coordinates":[-97.58063900000001,31.789069],"type":"Point"}
}