{
  "type": "Feature",
  "properties": {
    "iso:country":"US",
    "sg:address":"3334 Edloe St",
    "sg:city":"Houston",
    "sg:classifiers":[
        {
            "category":"Professional",
            "subcategory":"Management & Consulting",
            "type":"Services"
        }
    ],
    "sg:phone":"+1 713 626 1833",
    "sg:postcode":"77027",
    "sg:province":"TX",
    "sg:tags":[
        "consultant",
        "business"
    ],
    "wof:name":"Consumer Automotive Report",
    "wof:placetype":"venue"
},
  "geometry": {"coordinates":[-95.433522,29.735146],"type":"Point"}
}