{
  "type": "Feature",
  "properties": {
    "iso:country":"US",
    "sg:address":"506 Rowlock Ln",
    "sg:city":"Houston",
    "sg:classifiers":[
        {
            "category":"Manufacturing",
            "subcategory":"Tools & Machinery",
            "type":"Manufacturing & Wholesale Goods"
        }
    ],
    "sg:phone":"+1 713 320 9888",
    "sg:postcode":"77079",
    "sg:province":"TX",
    "sg:tags":[
        "industrial",
        "mfg"
    ],
    "wof:name":"Ragonis HI Tech Services Inc",
    "wof:placetype":"venue"
},
  "geometry": {"coordinates":[-95.635053,29.779314],"type":"Point"}
}