{
  "type": "Feature",
  "properties": {
    "iso:country":"US",
    "sg:address":"107 Oakdale Dr",
    "sg:city":"Schertz",
    "sg:classifiers":[
        {
            "category":"Shopping",
            "subcategory":"Gifts & Souvenirs",
            "type":"Retail Goods"
        }
    ],
    "sg:phone":"+1 210 658 8283",
    "sg:postcode":"78154",
    "sg:province":"TX",
    "wof:name":"Ruths Gifts",
    "wof:placetype":"venue"
},
  "geometry": {"coordinates":[-98.254212,29.555814],"type":"Point"}
}