{
  "type": "Feature",
  "properties": {
    "iso:country":"US",
    "sg:address":"5375 S Cooper St",
    "sg:city":"Arlington",
    "sg:classifiers":[
        {
            "category":"Autos & Motor Vehicles",
            "subcategory":"Fuel & Gas Station",
            "type":"Retail Goods"
        }
    ],
    "sg:phone":"+1 817 784 3806",
    "sg:postcode":"76017",
    "sg:province":"TX",
    "sg:tags":[
        "product",
        "tobacco"
    ],
    "wof:name":"Mobil",
    "wof:placetype":"venue"
},
  "geometry": {"coordinates":[-97.134235,32.662095],"type":"Point"}
}