{
  "type": "Feature",
  "properties": {
    "iso:country":"US",
    "sg:address":"1220 Ridgeway Dr",
    "sg:city":"Wichita Falls",
    "sg:classifiers":[
        {
            "category":"Professional",
            "type":"Services"
        }
    ],
    "sg:phone":"+1 940 855 4495",
    "sg:postcode":"76305",
    "sg:province":"TX",
    "sg:tags":[
        "establishment"
    ],
    "wof:name":"James",
    "wof:placetype":"venue"
},
  "geometry": {"coordinates":[-98.52506099999999,33.937695],"type":"Point"}
}