{
  "type": "Feature",
  "properties": {
    "iso:country":"US",
    "sg:address":"702 S Main St",
    "sg:city":"Jacksboro",
    "sg:classifiers":[
        {
            "category":"Shopping",
            "subcategory":"Gifts & Souvenirs",
            "type":"Retail Goods"
        }
    ],
    "sg:phone":"+1 940 567 3504",
    "sg:postcode":"76458",
    "sg:province":"TX",
    "sg:tags":[
        "shop"
    ],
    "wof:name":"Woodshed Works Gift Shop",
    "wof:placetype":"venue"
},
  "geometry": {"coordinates":[-98.15127699999999,33.202992],"type":"Point"}
}