{
  "type": "Feature",
  "properties": {
    "iso:country":"US",
    "sg:address":"3914 Gaines Ct",
    "sg:city":"Austin",
    "sg:classifiers":[
        {
            "category":"Farming",
            "subcategory":"Farm",
            "type":"Manufacturing & Wholesale Goods"
        }
    ],
    "sg:phone":"+1 512 899 1223",
    "sg:postcode":"78735",
    "sg:province":"TX",
    "wof:name":"Courtyard At Gaines Ranch",
    "wof:placetype":"venue"
},
  "geometry": {"coordinates":[-97.81958899999999,30.242072],"type":"Point"}
}