{
  "type": "Feature",
  "properties": {
    "iso:country":"US",
    "sg:address":"610 Shelley Dr",
    "sg:city":"Tyler",
    "sg:classifiers":[
        {
            "category":"Shopping",
            "subcategory":"Bicycles & Sporting Goods",
            "type":"Retail Goods"
        }
    ],
    "sg:phone":"+1 903 534 9998",
    "sg:postcode":"75701",
    "sg:province":"TX",
    "wof:name":"Tanner Bikes",
    "wof:placetype":"venue"
},
  "geometry": {"coordinates":[-95.30808,32.305028],"type":"Point"}
}