{
  "type": "Feature",
  "properties": {
    "iso:country":"US",
    "sg:address":"2102 Empire Central",
    "sg:city":"Dallas",
    "sg:classifiers":[
        {
            "category":"Professional",
            "subcategory":"Management & Consulting",
            "type":"Services"
        }
    ],
    "sg:phone":"+1 214 904 0920",
    "sg:postcode":"75235",
    "sg:province":"TX",
    "wof:name":"Concejeria Familiar",
    "wof:placetype":"venue"
},
  "geometry": {"coordinates":[-96.853966,32.82657],"type":"Point"}
}