{
  "type": "Feature",
  "properties": {
    "iso:country":"US",
    "sg:address":"1900 Coulter St",
    "sg:city":"Amarillo",
    "sg:classifiers":[
        {
            "category":"Social Services",
            "type":"Services"
        }
    ],
    "sg:phone":"+1 806 674 0281",
    "sg:postcode":"79106",
    "sg:province":"TX",
    "sg:tags":[
        "counselor"
    ],
    "wof:name":"Lucinda Miller",
    "wof:placetype":"venue"
},
  "geometry": {"coordinates":[-101.920355,35.188663],"type":"Point"}
}