{
  "type": "Feature",
  "properties": {
    "iso:country":"US",
    "sg:address":"12322 Ashford Glen Ct",
    "sg:city":"Sugar Land",
    "sg:classifiers":[
        {
            "category":"Autos & Motor Vehicles",
            "subcategory":"Fuel & Gas Station",
            "type":"Retail Goods"
        }
    ],
    "sg:phone":"+1 281 530 3394",
    "sg:postcode":"77478",
    "sg:province":"TX",
    "sg:tags":[
        "grocery",
        "station",
        "gasoline"
    ],
    "wof:name":"Gasgo Enterprises",
    "wof:placetype":"venue"
},
  "geometry": {"coordinates":[-95.60065299999999,29.656266],"type":"Point"}
}