{
  "type": "Feature",
  "properties": {
    "iso:country":"US",
    "sg:address":"150 N Clark Rd",
    "sg:city":"Cedar Hill",
    "sg:classifiers":[
        {
            "category":"Retail",
            "subcategory":"Storage",
            "type":"Services"
        }
    ],
    "sg:phone":"+1 866 838 2192",
    "sg:postcode":"75104",
    "sg:province":"TX",
    "sg:tags":[
        "self"
    ],
    "sg:website":"www.unclebobs.com/",
    "wof:name":"Uncle Bob's Self Storage",
    "wof:placetype":"venue"
},
  "geometry": {"coordinates":[-96.941233,32.591906],"type":"Point"}
}