{
  "type": "Feature",
  "properties": {
    "iso:country":"US",
    "sg:address":"700 E San Antonio Ave",
    "sg:city":"El Paso",
    "sg:classifiers":[
        {
            "category":"Professional",
            "type":"Services"
        }
    ],
    "sg:phone":"+1 915 534 6200",
    "sg:postcode":"79901",
    "sg:province":"TX",
    "sg:tags":[
        "establishment"
    ],
    "wof:name":"Railroad Retirement Board",
    "wof:placetype":"venue"
},
  "geometry": {"coordinates":[-106.48230599999999,31.759354],"type":"Point"}
}