{
  "type": "Feature",
  "properties": {
    "iso:country":"US",
    "sg:address":"5623 Timber Trace St",
    "sg:city":"San Antonio",
    "sg:classifiers":[
        {
            "category":"Education",
            "subcategory":"Special Training",
            "type":"Public Place"
        }
    ],
    "sg:phone":"+1 210 680 5710",
    "sg:postcode":"78250",
    "sg:province":"TX",
    "wof:name":"Ybanez & Assoc Inc",
    "wof:placetype":"venue"
},
  "geometry": {"coordinates":[-98.653387,29.497352],"type":"Point"}
}