{
  "type": "Feature",
  "properties": {
    "iso:country":"US",
    "sg:address":"818 Richcrest Dr",
    "sg:city":"Houston",
    "sg:classifiers":[
        {
            "category":"Restaurant",
            "type":"Food & Drink"
        }
    ],
    "sg:phone":"+1 281 875 0970",
    "sg:postcode":"77060",
    "sg:province":"TX",
    "sg:tags":[
        "eating"
    ],
    "wof:name":"Poh Sibs Enterprise Catering",
    "wof:placetype":"venue"
},
  "geometry": {"coordinates":[-95.393473,29.955074],"type":"Point"}
}