{
  "type": "Feature",
  "properties": {
    "iso:country":"US",
    "sg:address":"6408 del Monte Rd",
    "sg:city":"Austin",
    "sg:classifiers":[
        {
            "category":"Wholesale",
            "subcategory":"Auto Parts",
            "type":"Manufacturing & Wholesale Goods"
        }
    ],
    "sg:phone":"+1 512 385 3855",
    "sg:postcode":"78741",
    "sg:province":"TX",
    "sg:tags":[
        "automobile",
        "rebuilt"
    ],
    "wof:name":"AAA Auto Recycling",
    "wof:placetype":"venue"
},
  "geometry": {"coordinates":[-97.68973200000001,30.240226],"type":"Point"}
}