{
  "type": "Feature",
  "properties": {
    "iso:country":"US",
    "sg:address":"4535 W Walnut St",
    "sg:city":"Garland",
    "sg:classifiers":[
        {
            "category":"Restaurant",
            "type":"Food & Drink"
        }
    ],
    "sg:phone":"+1 972 494 3990",
    "sg:postcode":"75042",
    "sg:province":"TX",
    "sg:tags":[
        "eating",
        "chinese"
    ],
    "wof:name":"My Canh Chinese Restaurant",
    "wof:placetype":"venue"
},
  "geometry": {"coordinates":[-96.700897,32.9165],"type":"Point"}
}