{
  "type": "Feature",
  "properties": {
    "iso:country":"US",
    "sg:address":"11754 Jollyville Rd",
    "sg:city":"Austin",
    "sg:classifiers":[
        {
            "category":"Insurance",
            "subcategory":"Insurance Agent",
            "type":"Services"
        }
    ],
    "sg:phone":"+1 512 338 1404",
    "sg:postcode":"78759",
    "sg:province":"TX",
    "wof:name":"Lumbermen's Underwriting Allnc",
    "wof:placetype":"venue"
},
  "geometry": {"coordinates":[-97.753953,30.42111],"type":"Point"}
}