{
  "type": "Feature",
  "properties": {
    "iso:country":"US",
    "sg:address":"730 State Hwy 95",
    "sg:city":"Taylor",
    "sg:classifiers":[
        {
            "category":"Wholesale",
            "subcategory":"Farm Supplies",
            "type":"Manufacturing & Wholesale Goods"
        }
    ],
    "sg:phone":"+1 512 352 3973",
    "sg:postcode":"76574",
    "sg:province":"TX",
    "wof:name":"United Agri Products Inc",
    "wof:placetype":"venue"
},
  "geometry": {"coordinates":[-97.408827,30.561876],"type":"Point"}
}