{
  "type": "Feature",
  "properties": {
    "iso:country":"US",
    "sg:address":"6342 Southpoint Dr",
    "sg:city":"Dallas",
    "sg:classifiers":[
        {
            "category":"Health Services",
            "subcategory":"Clinic",
            "type":"Services"
        }
    ],
    "sg:phone":"+1 972 367 6937",
    "sg:postcode":"75248",
    "sg:province":"TX",
    "sg:tags":[
        "medical",
        "group"
    ],
    "wof:name":"Medical Group Empower",
    "wof:placetype":"venue"
},
  "geometry": {"coordinates":[-96.79704,32.977869],"type":"Point"}
}