{
  "type": "Feature",
  "properties": {
    "iso:country":"US",
    "sg:address":"2323 N Belt Line Rd",
    "sg:city":"Mesquite",
    "sg:classifiers":[
        {
            "category":"Retail",
            "subcategory":"Portrait Studio",
            "type":"Services"
        }
    ],
    "sg:phone":"+1 972 289 1851",
    "sg:postcode":"75150",
    "sg:province":"TX",
    "sg:tags":[
        "photographer"
    ],
    "wof:name":"Neve Photique",
    "wof:placetype":"venue"
},
  "geometry": {"coordinates":[-96.59597599999999,32.796761],"type":"Point"}
}