{
  "type": "Feature",
  "properties": {
    "iso:country":"US",
    "sg:address":"6512 Trinity Heights Blvd",
    "sg:city":"Fort Worth",
    "sg:classifiers":[
        {
            "category":"Professional",
            "subcategory":"Business Services",
            "type":"Services"
        }
    ],
    "sg:phone":"+1 817 291 1155",
    "sg:postcode":"76132",
    "sg:province":"TX",
    "wof:name":"Marisa Mercer Design",
    "wof:placetype":"venue"
},
  "geometry": {"coordinates":[-97.43117100000001,32.655876],"type":"Point"}
}