{
  "type": "Feature",
  "properties": {
    "iso:country":"US",
    "sg:address":"4075 Hollister St",
    "sg:city":"Houston",
    "sg:classifiers":[
        {
            "category":"Organizations",
            "subcategory":"Religious Organization",
            "type":"Services"
        }
    ],
    "sg:phone":"+1 713 462 5090",
    "sg:postcode":"77080",
    "sg:province":"TX",
    "wof:name":"Polancodavid",
    "wof:placetype":"venue"
},
  "geometry": {"coordinates":[-95.509332,29.828452],"type":"Point"}
}