{
  "type": "Feature",
  "properties": {
    "iso:country":"US",
    "sg:address":"4102 68th St",
    "sg:city":"Lubbock",
    "sg:classifiers":[
        {
            "category":"Professional",
            "subcategory":"Business Services",
            "type":"Services"
        }
    ],
    "sg:phone":"+1 806 796 2818",
    "sg:postcode":"79413",
    "sg:province":"TX",
    "wof:name":"N & M Interiors",
    "wof:placetype":"venue"
},
  "geometry": {"coordinates":[-101.90209,33.532701],"type":"Point"}
}