{
  "type": "Feature",
  "properties": {
    "iso:country":"US",
    "sg:address":"1207 E Berkeley Dr",
    "sg:city":"Richardson",
    "sg:classifiers":[
        {
            "category":"Shopping",
            "subcategory":"Pharmacy",
            "type":"Retail Goods"
        }
    ],
    "sg:phone":"+1 972 234 4595",
    "sg:postcode":"75081",
    "sg:province":"TX",
    "sg:tags":[
        "drug",
        "store"
    ],
    "wof:name":"Kleins Pharmacy",
    "wof:placetype":"venue"
},
  "geometry": {"coordinates":[-96.707066,32.932771],"type":"Point"}
}