{
  "type": "Feature",
  "properties": {
    "iso:country":"US",
    "sg:address":"1266 Fry Rd",
    "sg:city":"Houston",
    "sg:classifiers":[
        {
            "category":"Banks & Credit Unions",
            "subcategory":"Bank",
            "type":"Services"
        }
    ],
    "sg:phone":"+1 281 646 2940",
    "sg:postcode":"77084",
    "sg:province":"TX",
    "wof:name":"Bank One",
    "wof:placetype":"venue"
},
  "geometry": {"coordinates":[-95.71883200000001,29.787077],"type":"Point"}
}