{
  "type": "Feature",
  "properties": {
    "iso:country":"US",
    "sg:address":"2303 Droxford Dr",
    "sg:city":"Houston",
    "sg:classifiers":[
        {
            "category":"Insurance",
            "subcategory":"Insurance Agent",
            "type":"Services"
        }
    ],
    "sg:phone":"+1 713 861 1627",
    "sg:postcode":"77008",
    "sg:province":"TX",
    "wof:name":"Investment & Insurance Co",
    "wof:placetype":"venue"
},
  "geometry": {"coordinates":[-95.44010400000001,29.798377],"type":"Point"}
}