{
  "type": "Feature",
  "properties": {
    "iso:country":"US",
    "sg:address":"2001 Precinct Line Rd",
    "sg:city":"Hurst",
    "sg:classifiers":[
        {
            "category":"Government",
            "subcategory":"Office",
            "type":"Public Place"
        }
    ],
    "sg:phone":"+1 817 788 7228",
    "sg:postcode":"76054",
    "sg:province":"TX",
    "sg:tags":[
        "village"
    ],
    "wof:name":"Hurst Service Ctr",
    "wof:placetype":"venue"
},
  "geometry": {"coordinates":[-97.18620300000001,32.851245],"type":"Point"}
}