{
  "type": "Feature",
  "properties": {
    "iso:country":"US",
    "sg:address":"1308 Turtle Creek Dr",
    "sg:city":"Missouri City",
    "sg:classifiers":[
        {
            "category":"Shopping",
            "subcategory":"Discount & Variety Stores",
            "type":"Retail Goods"
        }
    ],
    "sg:phone":"+1 281 438 5119",
    "sg:postcode":"77489",
    "sg:province":"TX",
    "sg:tags":[
        "merchandise",
        "general"
    ],
    "wof:name":"Toks Beauty Store",
    "wof:placetype":"venue"
},
  "geometry": {"coordinates":[-95.521407,29.579662],"type":"Point"}
}