{
  "type": "Feature",
  "properties": {
    "iso:country":"US",
    "sg:address":"5440 N Jim Miller Rd",
    "sg:city":"Dallas",
    "sg:classifiers":[
        {
            "category":"Social Services",
            "subcategory":"Child Care",
            "type":"Services"
        }
    ],
    "sg:phone":"+1 214 388 3724",
    "sg:postcode":"75227",
    "sg:province":"TX",
    "wof:name":"Ruby's Daycare",
    "wof:placetype":"venue"
},
  "geometry": {"coordinates":[-96.70012699999999,32.789631],"type":"Point"}
}