{
  "type": "Feature",
  "properties": {
    "iso:country":"US",
    "sg:address":"101 State Hwy 59",
    "sg:city":"Montague",
    "sg:classifiers":[
        {
            "category":"Banks & Credit Unions",
            "subcategory":"Bank",
            "type":"Services"
        }
    ],
    "sg:phone":"+1 940 894 2000",
    "sg:postcode":"76230",
    "sg:province":"TX",
    "sg:tags":[
        "financing"
    ],
    "wof:name":"First Republic Investment Corp",
    "wof:placetype":"venue"
},
  "geometry": {"coordinates":[-97.849767,33.557437],"type":"Point"}
}