{
  "type": "Feature",
  "properties": {
    "iso:country":"US",
    "sg:address":"9535 Autumn Wind",
    "sg:city":"Boerne",
    "sg:classifiers":[
        {
            "category":"Professional",
            "subcategory":"Computer Services",
            "type":"Services"
        }
    ],
    "sg:phone":"+1 210 698 6378",
    "sg:postcode":"78006",
    "sg:province":"TX",
    "sg:tags":[
        "var",
        "information",
        "technology"
    ],
    "wof:name":"Insight Data Systems Inc",
    "wof:placetype":"venue"
},
  "geometry": {"coordinates":[-98.6776,29.692026],"type":"Point"}
}