{
  "type": "Feature",
  "properties": {
    "iso:country":"US",
    "sg:address":"7340 Washington Ave",
    "sg:city":"Houston",
    "sg:classifiers":[
        {
            "category":"Fast Food",
            "type":"Food & Drink"
        },
        {
            "category":"Bars & Pubs",
            "subcategory":"Sports Bar",
            "type":"Food & Drink"
        }
    ],
    "sg:phone":"+1 713 864 9744",
    "sg:postcode":"77007",
    "sg:province":"TX",
    "sg:tags":[
        "burger"
    ],
    "sg:website":"www.christianstailgate.com",
    "wof:name":"Christian's Tailgate",
    "wof:placetype":"venue"
},
  "geometry": {"coordinates":[-95.429785,29.778401],"type":"Point"}
}