{
  "type": "Feature",
  "properties": {
    "iso:country":"US",
    "sg:address":"3412 Flowstone Ln",
    "sg:city":"Round Rock",
    "sg:classifiers":[
        {
            "category":"Manufacturing",
            "subcategory":"Retail Goods",
            "type":"Manufacturing & Wholesale Goods"
        }
    ],
    "sg:phone":"+1 512 238 1945",
    "sg:postcode":"78681",
    "sg:province":"TX",
    "sg:tags":[
        "manufacturer"
    ],
    "wof:name":"Lennox Industries Inc",
    "wof:placetype":"venue"
},
  "geometry": {"coordinates":[-97.737836,30.55771],"type":"Point"}
}