{
  "type": "Feature",
  "properties": {
    "iso:country":"US",
    "sg:address":"7 Happy Hollow Ln",
    "sg:city":"Austin",
    "sg:classifiers":[
        {
            "category":"Farming",
            "subcategory":"Nursery",
            "type":"Manufacturing & Wholesale Goods"
        }
    ],
    "sg:phone":"+1 512 453 2318",
    "sg:postcode":"78703",
    "sg:province":"TX",
    "sg:tags":[
        "ornamental"
    ],
    "wof:name":"Hunters Greenhouse",
    "wof:placetype":"venue"
},
  "geometry": {"coordinates":[-97.754869,30.308576],"type":"Point"}
}