{
  "type": "Feature",
  "properties": {
    "iso:country":"US",
    "sg:address":"2440 Texas Pkwy",
    "sg:city":"Missouri City",
    "sg:classifiers":[
        {
            "category":"Professional",
            "subcategory":"Computer Services",
            "type":"Services"
        }
    ],
    "sg:phone":"+1 281 261 9033",
    "sg:postcode":"77489",
    "sg:province":"TX",
    "sg:tags":[
        "consultant"
    ],
    "wof:name":"Unique Computers",
    "wof:placetype":"venue"
},
  "geometry": {"coordinates":[-95.52663099999999,29.592255],"type":"Point"}
}