{
  "type": "Feature",
  "properties": {
    "iso:country":"US",
    "sg:address":"16318 Deer Pass St",
    "sg:city":"San Antonio",
    "sg:classifiers":[
        {
            "category":"Farming",
            "subcategory":"Livestock Farm",
            "type":"Manufacturing & Wholesale Goods"
        }
    ],
    "sg:phone":"+1 210 494 1552",
    "sg:postcode":"78232",
    "sg:province":"TX",
    "sg:tags":[
        "animal",
        "general"
    ],
    "wof:name":"Peniel Ranch",
    "wof:placetype":"venue"
},
  "geometry": {"coordinates":[-98.45157,29.591305],"type":"Point"}
}