{
  "type": "Feature",
  "properties": {
    "iso:country":"US",
    "sg:address":"201 S Glenbrook Dr",
    "sg:city":"Garland",
    "sg:classifiers":[
        {
            "category":"Banks & Credit Unions",
            "subcategory":"Bank",
            "type":"Services"
        }
    ],
    "sg:phone":"+1 972 276 1116",
    "sg:postcode":"75040",
    "sg:province":"TX",
    "wof:name":"State Farm Insurance Co",
    "wof:placetype":"venue"
},
  "geometry": {"coordinates":[-96.64009900000001,32.911499],"type":"Point"}
}