{
  "type": "Feature",
  "properties": {
    "iso:country":"US",
    "sg:address":"3422 Commercial Ave",
    "sg:city":"San Antonio",
    "sg:classifiers":[
        {
            "category":"Autos & Motor Vehicles",
            "subcategory":"Automobile Sales",
            "type":"Retail Goods"
        }
    ],
    "sg:phone":"+1 210 922 1031",
    "sg:postcode":"78221",
    "sg:province":"TX",
    "sg:tags":[
        "car",
        "used",
        "dealer"
    ],
    "wof:name":"Tim's Auto Sales",
    "wof:placetype":"venue"
},
  "geometry": {"coordinates":[-98.516148,29.34279],"type":"Point"}
}