{
  "type": "Feature",
  "properties": {
    "iso:country":"US",
    "sg:address":"4809 W Waco Dr",
    "sg:city":"Waco",
    "sg:classifiers":[
        {
            "category":"Building & Trades",
            "subcategory":"Pest Control",
            "type":"Services"
        }
    ],
    "sg:phone":"+1 254 754 8918",
    "sg:postcode":"76710",
    "sg:province":"TX",
    "wof:name":"Minute Man Exterminators",
    "wof:placetype":"venue"
},
  "geometry": {"coordinates":[-97.178794,31.521001],"type":"Point"}
}