{
  "type": "Feature",
  "properties": {
    "iso:country":"US",
    "sg:address":"716 W Jonquil Ave",
    "sg:city":"Mcallen",
    "sg:classifiers":[
        {
            "category":"Travel",
            "subcategory":"Travel Agent",
            "type":"Entertainment"
        }
    ],
    "sg:phone":"+1 956 682 8866",
    "sg:postcode":"78501",
    "sg:province":"TX",
    "sg:tags":[
        "agency"
    ],
    "wof:name":"Destinations",
    "wof:placetype":"venue"
},
  "geometry": {"coordinates":[-98.221084,26.235372],"type":"Point"}
}