{
  "type": "Feature",
  "properties": {
    "iso:country":"US",
    "sg:address":"9815 Copper Creek Dr",
    "sg:city":"Austin",
    "sg:classifiers":[
        {
            "category":"Wholesale",
            "subcategory":"Jewelry",
            "type":"Manufacturing & Wholesale Goods"
        }
    ],
    "sg:phone":"+1 512 331 0436",
    "sg:postcode":"78729",
    "sg:province":"TX",
    "sg:tags":[
        "stone"
    ],
    "wof:name":"Mo-Fun",
    "wof:placetype":"venue"
},
  "geometry": {"coordinates":[-97.785849,30.458966],"type":"Point"}
}