{
  "type": "Feature",
  "properties": {
    "iso:country":"US",
    "sg:address":"2110 Mulberry Ln",
    "sg:city":"Pasadena",
    "sg:classifiers":[
        {
            "category":"Retail",
            "subcategory":"Laundry & Dry Cleaning",
            "type":"Services"
        },
        {
            "category":"Building & Trades",
            "subcategory":"Cleaning & Sanitation",
            "type":"Services"
        }
    ],
    "sg:phone":"+1 713 401 6390",
    "sg:postcode":"77502",
    "sg:province":"TX",
    "sg:tags":[
        "cleaner",
        "site-clean-up",
        "house",
        "rug",
        "window",
        "construction",
        "carpet"
    ],
    "wof:name":"Emperial Cleaning",
    "wof:placetype":"venue"
},
  "geometry": {"coordinates":[-95.192221,29.681835],"type":"Point"}
}