{
  "type": "Feature",
  "properties": {
    "iso:country":"US",
    "sg:address":"7701 Broadway",
    "sg:city":"San Antonio",
    "sg:classifiers":[
        {
            "category":"Retail",
            "subcategory":"Portrait Studio",
            "type":"Services"
        }
    ],
    "sg:phone":"+1 210 826 1961",
    "sg:postcode":"78209",
    "sg:province":"TX",
    "sg:tags":[
        "photographer"
    ],
    "wof:name":"Southwest Party Pictures",
    "wof:placetype":"venue"
},
  "geometry": {"coordinates":[-98.466538,29.500445],"type":"Point"}
}