{
  "type": "Feature",
  "properties": {
    "iso:country":"US",
    "sg:address":"510 11th St",
    "sg:city":"Seagraves",
    "sg:classifiers":[
        {
            "category":"Retail",
            "subcategory":"Funeral Services",
            "type":"Services"
        }
    ],
    "sg:phone":"+1 806 546 2121",
    "sg:postcode":"79359",
    "sg:province":"TX",
    "sg:tags":[
        "director"
    ],
    "wof:name":"Mark A Jones Funeral Drctrs",
    "wof:placetype":"venue"
},
  "geometry": {"coordinates":[-102.563711,32.943243],"type":"Point"}
}