{
  "type": "Feature",
  "properties": {
    "iso:country":"US",
    "sg:address":"512 Woodland Oaks Dr",
    "sg:city":"Schertz",
    "sg:classifiers":[
        {
            "category":"Professional",
            "subcategory":"Management & Consulting",
            "type":"Services"
        }
    ],
    "sg:phone":"+1 210 566 4406",
    "sg:postcode":"78154",
    "sg:province":"TX",
    "sg:tags":[
        "business"
    ],
    "wof:name":"Dekiewiet Consulting",
    "wof:placetype":"venue"
},
  "geometry": {"coordinates":[-98.267565,29.579643],"type":"Point"}
}