{
  "type": "Feature",
  "properties": {
    "iso:country":"US",
    "sg:address":"1684 Clay St",
    "sg:city":"Houston",
    "sg:classifiers":[
        {
            "category":"Professional",
            "subcategory":"Computer Services",
            "type":"Services"
        }
    ],
    "sg:phone":"+1 281 550 1109",
    "sg:postcode":"77002",
    "sg:province":"TX",
    "sg:tags":[
        "mfg",
        "design",
        "system",
        "software"
    ],
    "wof:name":"Scientific Data Systems Inc",
    "wof:placetype":"venue"
},
  "geometry": {"coordinates":[-95.36193900000001,29.750724],"type":"Point"}
}