{
  "type": "Feature",
  "properties": {
    "iso:country":"US",
    "sg:address":"2200 Town East Mall",
    "sg:city":"Mesquite",
    "sg:classifiers":[
        {
            "category":"Shopping",
            "subcategory":"Clothing, Apparel, & Fashions",
            "type":"Retail Goods"
        }
    ],
    "sg:phone":"+1 972 681 2615",
    "sg:postcode":"75150",
    "sg:province":"TX",
    "sg:tags":[
        "apparel",
        "women's",
        "maternity",
        "clothes"
    ],
    "sg:website":"http://www.motherhood.com",
    "wof:name":"Motherhood Maternity",
    "wof:placetype":"venue"
},
  "geometry": {"coordinates":[-96.63462800000001,32.811161],"type":"Point"}
}