{
  "type": "Feature",
  "properties": {
    "iso:country":"US",
    "sg:address":"2200 College Pkwy",
    "sg:city":"Flower Mound",
    "sg:classifiers":[
        {
            "category":"Education",
            "subcategory":"Vocational School",
            "type":"Public Place"
        }
    ],
    "sg:phone":"+1 972 355 4833",
    "sg:postcode":"75028",
    "sg:province":"TX",
    "wof:name":"Larry York Aviation LLC",
    "wof:placetype":"venue"
},
  "geometry": {"coordinates":[-97.06196199999999,33.052279],"type":"Point"}
}