{
  "type": "Feature",
  "properties": {
    "iso:country":"US",
    "sg:address":"7662 Beauxart Garden Rd",
    "sg:city":"Nederland",
    "sg:classifiers":[
        {
            "category":"Home & Garden",
            "subcategory":"Building Materials",
            "type":"Retail Goods"
        }
    ],
    "sg:phone":"+1 409 727 2708",
    "sg:postcode":"77627",
    "sg:province":"TX",
    "sg:tags":[
        "mixed",
        "concrete"
    ],
    "wof:name":"TNT Ready Mix",
    "wof:placetype":"venue"
},
  "geometry": {"coordinates":[-94.02423,29.971896],"type":"Point"}
}