{
  "type": "Feature",
  "properties": {
    "iso:country":"US",
    "sg:address":"1312 Parkmont Dr",
    "sg:city":"Garland",
    "sg:classifiers":[
        {
            "category":"Shopping",
            "subcategory":"Hobbies, Toys, & Games",
            "type":"Retail Goods"
        }
    ],
    "sg:phone":"+1 972 278 4973",
    "sg:postcode":"75041",
    "sg:province":"TX",
    "wof:name":"Little Kingdom Workshop",
    "wof:placetype":"venue"
},
  "geometry": {"coordinates":[-96.644972,32.881683],"type":"Point"}
}