{
  "type": "Feature",
  "properties": {
    "iso:country":"US",
    "sg:address":"1013 S Jupiter Rd",
    "sg:city":"Garland",
    "sg:classifiers":[
        {
            "category":"Professional",
            "type":"Services"
        }
    ],
    "sg:phone":"+1 972 276 1385",
    "sg:postcode":"75042",
    "sg:province":"TX",
    "sg:tags":[
        "establishment"
    ],
    "wof:name":"Caviar Etc",
    "wof:placetype":"venue"
},
  "geometry": {"coordinates":[-96.68312400000001,32.902872],"type":"Point"}
}