{
  "type": "Feature",
  "properties": {
    "iso:country":"US",
    "sg:address":"2610 Forest Ln",
    "sg:city":"Dallas",
    "sg:classifiers":[
        {
            "category":"Autos & Motor Vehicles",
            "subcategory":"Automobile Sales",
            "type":"Retail Goods"
        },
        {
            "category":"Retail",
            "subcategory":"Auto Repair",
            "type":"Services"
        }
    ],
    "sg:phone":"+1 972 241 6655",
    "sg:postcode":"75234",
    "sg:province":"TX",
    "sg:tags":[
        "body",
        "c",
        "used",
        "car",
        "toyota",
        "painting"
    ],
    "wof:name":"Toyota of Dallas",
    "wof:placetype":"venue"
},
  "geometry": {"coordinates":[-96.89070100000001,32.9081],"type":"Point"}
}