{
  "type": "Feature",
  "properties": {
    "iso:country":"US",
    "sg:address":"6004 Northern Dancer Dr",
    "sg:city":"Austin",
    "sg:classifiers":[
        {
            "category":"Wholesale",
            "subcategory":"Books, Periodicals, & Newspapers",
            "type":"Manufacturing & Wholesale Goods"
        }
    ],
    "sg:phone":"+1 512 347 7344",
    "sg:postcode":"78746",
    "sg:province":"TX",
    "sg:tags":[
        "publishers-periodical"
    ],
    "wof:name":"Urban Home Magazine Of Austin",
    "wof:placetype":"venue"
},
  "geometry": {"coordinates":[-97.81482699999999,30.318411],"type":"Point"}
}