{
  "type": "Feature",
  "properties": {
    "iso:country":"US",
    "sg:address":"2641 Oak Haven Dr",
    "sg:city":"San Marcos",
    "sg:classifiers":[
        {
            "category":"Professional",
            "type":"Services"
        }
    ],
    "sg:phone":"+1 512 353 1703",
    "sg:postcode":"78666",
    "sg:province":"TX",
    "wof:name":"Rosa Mitchell",
    "wof:placetype":"venue"
},
  "geometry": {"coordinates":[-97.981916,29.8638],"type":"Point"}
}