{
  "type": "Feature",
  "properties": {
    "iso:country":"US",
    "sg:address":"9421 Ronda Ln",
    "sg:city":"Houston",
    "sg:classifiers":[
        {
            "category":"Autos & Motor Vehicles",
            "subcategory":"Automobile Sales",
            "type":"Retail Goods"
        }
    ],
    "sg:phone":"+1 713 270 1940",
    "sg:postcode":"77074",
    "sg:province":"TX",
    "sg:tags":[
        "used"
    ],
    "wof:name":"R&I Storage",
    "wof:placetype":"venue"
},
  "geometry": {"coordinates":[-95.54162100000001,29.672498],"type":"Point"}
}