{
  "type": "Feature",
  "properties": {
    "iso:country":"US",
    "sg:address":"2535 Drain Dr",
    "sg:city":"Wylie",
    "sg:classifiers":[
        {
            "category":"Building & Trades",
            "subcategory":"Landscaping Services",
            "type":"Services"
        }
    ],
    "sg:phone":"+1 972 429 0480",
    "sg:postcode":"75098",
    "sg:province":"TX",
    "sg:tags":[
        "lawn",
        "maintenance",
        "grounds"
    ],
    "wof:name":"Jd's Lawn Maintenance Svc",
    "wof:placetype":"venue"
},
  "geometry": {"coordinates":[-96.55752200000001,33.050803],"type":"Point"}
}