{
  "type": "Feature",
  "properties": {
    "iso:country":"US",
    "sg:address":"927 Eddie Rd",
    "sg:city":"San Antonio",
    "sg:classifiers":[
        {
            "category":"Food & Beverages",
            "subcategory":"Bakery",
            "type":"Retail Goods"
        }
    ],
    "sg:phone":"+1 210 662 0120",
    "sg:postcode":"78219",
    "sg:province":"TX",
    "sg:tags":[
        "baker"
    ],
    "wof:name":"Mrs Baird's Bakeries Inc",
    "wof:placetype":"venue"
},
  "geometry": {"coordinates":[-98.394357,29.438416],"type":"Point"}
}