{
  "type": "Feature",
  "properties": {
    "iso:country":"US",
    "sg:address":"826 Trinity St",
    "sg:city":"Lockhart",
    "sg:classifiers":[
        {
            "category":"Organizations",
            "subcategory":"Community Association",
            "type":"Services"
        }
    ],
    "sg:phone":"+1 512 398 2434",
    "sg:postcode":"78644",
    "sg:province":"TX",
    "wof:name":"Delta Kappa Gamma Society",
    "wof:placetype":"venue"
},
  "geometry": {"coordinates":[-97.666534,29.877011],"type":"Point"}
}