{
  "type": "Feature",
  "properties": {
    "iso:country":"US",
    "sg:address":"1300 W Anderson Ln",
    "sg:city":"Austin",
    "sg:classifiers":[
        {
            "category":"Shopping",
            "subcategory":"Computers & Home Electronics",
            "type":"Retail Goods"
        }
    ],
    "sg:phone":"+1 512 836 8201",
    "sg:postcode":"78757",
    "sg:province":"TX",
    "wof:name":"Family Webb Inc",
    "wof:placetype":"venue"
},
  "geometry": {"coordinates":[-97.71986,30.350979],"type":"Point"}
}