{
  "type": "Feature",
  "properties": {
    "iso:country":"US",
    "sg:address":"5887 Westheimer Road",
    "sg:city":"Houston",
    "sg:classifiers":[
        {
            "category":"Restaurant",
            "type":"Food & Drink"
        }
    ],
    "sg:phone":"+1 713 780 0200",
    "sg:postcode":"77057",
    "sg:province":"TX",
    "sg:tags":[
        "cajun/creole"
    ],
    "wof:name":"Fish Place",
    "wof:placetype":"venue"
},
  "geometry": {"coordinates":[-95.483825,29.737279],"type":"Point"}
}