{
  "type": "Feature",
  "properties": {
    "iso:country":"US",
    "sg:address":"6707 Academy St",
    "sg:city":"Houston",
    "sg:classifiers":[
        {
            "category":"Professional",
            "type":"Services"
        }
    ],
    "sg:phone":"+1 713 230 1529",
    "sg:postcode":"77005",
    "sg:province":"TX",
    "sg:tags":[
        "establishment"
    ],
    "wof:name":"IBM-Advantis",
    "wof:placetype":"venue"
},
  "geometry": {"coordinates":[-95.442723,29.706932],"type":"Point"}
}