{
  "type": "Feature",
  "properties": {
    "iso:country":"US",
    "sg:address":"1907 Wigeon St",
    "sg:city":"Granbury",
    "sg:classifiers":[
        {
            "category":"Education",
            "subcategory":"Special Training",
            "type":"Public Place"
        }
    ],
    "sg:phone":"+1 817 578 8020",
    "sg:postcode":"76049",
    "sg:province":"TX",
    "sg:tags":[
        "merchandise"
    ],
    "wof:name":"Silkscapes",
    "wof:placetype":"venue"
},
  "geometry": {"coordinates":[-97.757507,32.458474],"type":"Point"}
}