{
  "type": "Feature",
  "properties": {
    "iso:country":"US",
    "sg:address":"1017 W 4th Ave",
    "sg:city":"Amarillo",
    "sg:classifiers":[
        {
            "category":"Wholesale",
            "subcategory":"Home Furnishings",
            "type":"Manufacturing & Wholesale Goods"
        }
    ],
    "sg:phone":"+1 806 353 7877",
    "sg:postcode":"79101",
    "sg:province":"AR",
    "sg:tags":[
        "merchandise"
    ],
    "wof:name":"World Frame Center",
    "wof:placetype":"venue"
},
  "geometry": {"coordinates":[-101.84927,35.211266],"type":"Point"}
}