{
  "type": "Feature",
  "properties": {
    "iso:country":"US",
    "sg:address":"12199 Bell Rd",
    "sg:city":"Pilot Point",
    "sg:classifiers":[
        {
            "category":"Organizations",
            "subcategory":"Membership Organization",
            "type":"Services"
        }
    ],
    "sg:phone":"+1 940 365 3598",
    "sg:postcode":"76258",
    "sg:province":"TX",
    "wof:name":"Dallas Dressage Club",
    "wof:placetype":"venue"
},
  "geometry": {"coordinates":[-96.94667099999999,33.325795],"type":"Point"}
}