{
  "type": "Feature",
  "properties": {
    "iso:country":"US",
    "sg:address":"312 Hubbard Dr",
    "sg:city":"Rockwall",
    "sg:classifiers":[
        {
            "category":"Real Estate",
            "subcategory":"Architect",
            "type":"Services"
        }
    ],
    "sg:phone":"+1 972 771 4549",
    "sg:postcode":"75032",
    "sg:province":"TX",
    "wof:name":"Bartholomew Assoc Architects",
    "wof:placetype":"venue"
},
  "geometry": {"coordinates":[-96.49008600000001,32.823864],"type":"Point"}
}