{
  "type": "Feature",
  "properties": {
    "iso:country":"US",
    "sg:address":"720 S Eagle St",
    "sg:city":"Weimar",
    "sg:classifiers":[
        {
            "category":"Autos & Motor Vehicles",
            "subcategory":"Auto Supplies",
            "type":"Retail Goods"
        }
    ],
    "sg:phone":"+1 979 725 8567",
    "sg:postcode":"78962",
    "sg:province":"TX",
    "sg:tags":[
        "tire"
    ],
    "wof:name":"Stavinoha Tire Oil & Battery",
    "wof:placetype":"venue"
},
  "geometry": {"coordinates":[-96.776696,29.695222],"type":"Point"}
}