{
  "type": "Feature",
  "properties": {
    "iso:country":"US",
    "sg:address":"3612 Wesley St",
    "sg:city":"Greenville",
    "sg:classifiers":[
        {
            "category":"Banks & Credit Unions",
            "subcategory":"Investment Brokerage",
            "type":"Services"
        },
        {
            "category":"Cinema",
            "subcategory":"Movie Rental",
            "type":"Entertainment"
        },
        {
            "category":"Shopping",
            "subcategory":"Computers & Home Electronics",
            "type":"Retail Goods"
        }
    ],
    "sg:phone":"+1 903 455 8507",
    "sg:postcode":"75401",
    "sg:province":"TX",
    "sg:tags":[
        "leasing",
        "dvd",
        "sale",
        "dvds-rental",
        "video",
        "tape",
        "games-renting"
    ],
    "sg:website":"http://www.familyvideo.com",
    "wof:name":"Family Video",
    "wof:placetype":"venue"
},
  "geometry": {"coordinates":[-96.109099,33.131806],"type":"Point"}
}