{
  "type": "Feature",
  "properties": {
    "iso:country":"US",
    "sg:address":"700 N Texas Ave",
    "sg:city":"Bryan",
    "sg:classifiers":[
        {
            "category":"Restaurant",
            "type":"Food & Drink"
        }
    ],
    "sg:phone":"+1 979 822 1548",
    "sg:postcode":"77803",
    "sg:province":"TX",
    "sg:website":"www.mcdonalds.com",
    "wof:name":"Mc Donald's",
    "wof:placetype":"venue"
},
  "geometry": {"coordinates":[-96.369134,30.679717],"type":"Point"}
}