{
  "type": "Feature",
  "properties": {
    "iso:country":"US",
    "sg:address":"3719 N Main St",
    "sg:city":"Fort Worth",
    "sg:classifiers":[
        {
            "category":"Professional",
            "subcategory":"Advertising",
            "type":"Services"
        }
    ],
    "sg:phone":"+1 817 626 7110",
    "sg:postcode":"76106",
    "sg:province":"TX",
    "sg:tags":[
        "distribution"
    ],
    "wof:name":"Cuevas Distribution Inc",
    "wof:placetype":"venue"
},
  "geometry": {"coordinates":[-97.351522,32.810904],"type":"Point"}
}