{
  "type": "Feature",
  "properties": {
    "iso:country":"US",
    "sg:address":"5827 Co Rd 219",
    "sg:city":"Tyler",
    "sg:classifiers":[
        {
            "category":"Building & Trades",
            "subcategory":"Plumbing",
            "type":"Services"
        }
    ],
    "sg:phone":"+1 903 566 0134",
    "sg:postcode":"75707",
    "sg:province":"TX",
    "sg:tags":[
        "plumbing",
        "contractor"
    ],
    "wof:name":"Fountain Plumbing Co",
    "wof:placetype":"venue"
},
  "geometry": {"coordinates":[-95.23947099999999,32.325649],"type":"Point"}
}