{
  "type": "Feature",
  "properties": {
    "iso:country":"US",
    "sg:address":"4650 Lafin Dr",
    "sg:city":"Beaumont",
    "sg:classifiers":[
        {
            "category":"Freight",
            "type":"Transportation"
        }
    ],
    "sg:phone":"+1 409 842 5454",
    "sg:postcode":"77705",
    "sg:province":"TX",
    "sg:tags":[
        "trucking"
    ],
    "sg:website":"www.myyellow.com",
    "wof:name":"Yellow Transportation Inc",
    "wof:placetype":"venue"
},
  "geometry": {"coordinates":[-94.133315,30.038871],"type":"Point"}
}