{
  "type": "Feature",
  "properties": {
    "iso:country":"US",
    "sg:address":"Hampton & Bear Crk",
    "sg:city":"Desoto",
    "sg:classifiers":[
        {
            "category":"Social Services",
            "subcategory":"Child Care",
            "type":"Services"
        },
        {
            "category":"Education",
            "subcategory":"Preschool",
            "type":"Public Place"
        },
        {
            "category":"Education",
            "subcategory":"School",
            "type":"Public Place"
        }
    ],
    "sg:phone":"+1 972 223 7437",
    "sg:postcode":"75115",
    "sg:province":"TX",
    "sg:tags":[
        "elementary",
        "day"
    ],
    "wof:name":"Bear Creek Children's Center",
    "wof:placetype":"venue"
},
  "geometry": {"coordinates":[-96.862396,32.6003],"type":"Point"}
}