{
  "type": "Feature",
  "properties": {
    "iso:country":"US",
    "sg:address":"9303 Reid Lake Dr",
    "sg:city":"Houston",
    "sg:classifiers":[
        {
            "category":"Professional",
            "subcategory":"Engineering",
            "type":"Services"
        }
    ],
    "sg:phone":"+1 281 492 2354",
    "sg:postcode":"77064",
    "sg:province":"TX",
    "wof:name":"Lott Brown Cnslting Engners LP",
    "wof:placetype":"venue"
},
  "geometry": {"coordinates":[-95.536063,29.909205],"type":"Point"}
}