{
  "type": "Feature",
  "properties": {
    "iso:country":"US",
    "sg:address":"13737 Noel Rd",
    "sg:city":"Dallas",
    "sg:classifiers":[
        {
            "category":"Health Services",
            "subcategory":"Hospital",
            "type":"Services"
        }
    ],
    "sg:phone":"+1 469 893 2000",
    "sg:postcode":"75240",
    "sg:province":"TX",
    "wof:name":"Tenet Health Systems",
    "wof:placetype":"venue"
},
  "geometry": {"coordinates":[-96.81813200000001,32.935454],"type":"Point"}
}