{
  "type": "Feature",
  "properties": {
    "iso:country":"US",
    "sg:address":"1100 Bates",
    "sg:city":"Houston",
    "sg:classifiers":[
        {
            "category":"Health Services",
            "subcategory":"Doctor",
            "type":"Services"
        }
    ],
    "sg:phone":"+1 713 798 7038",
    "sg:postcode":"77030",
    "sg:province":"TX",
    "sg:tags":[
        "physician",
        "surgeon"
    ],
    "sg:website":"www.kidsnutrition.org",
    "wof:name":"Childrens Nutrition Research",
    "wof:placetype":"venue"
},
  "geometry": {"coordinates":[-95.400583,29.707342],"type":"Point"}
}