{
  "type": "Feature",
  "properties": {
    "iso:country":"US",
    "sg:address":"6418 35th St",
    "sg:city":"Lubbock",
    "sg:classifiers":[
        {
            "category":"Professional",
            "subcategory":"Art Services",
            "type":"Services"
        }
    ],
    "sg:phone":"+1 806 795 9164",
    "sg:postcode":"79407",
    "sg:province":"TX",
    "sg:tags":[
        "photography",
        "commercial"
    ],
    "wof:name":"Picture This",
    "wof:placetype":"venue"
},
  "geometry": {"coordinates":[-101.95604,33.56122],"type":"Point"}
}