{
  "type": "Feature",
  "properties": {
    "iso:country":"US",
    "sg:address":"150 Sugar Berry Cir",
    "sg:city":"Houston",
    "sg:classifiers":[
        {
            "category":"Organizations",
            "subcategory":"Community Association",
            "type":"Services"
        }
    ],
    "sg:phone":"+1 713 780 3771",
    "sg:postcode":"77024",
    "sg:province":"TX",
    "wof:name":"Channel Point Condo",
    "wof:placetype":"venue"
},
  "geometry": {"coordinates":[-95.52806200000001,29.749943],"type":"Point"}
}