{
  "type": "Feature",
  "properties": {
    "iso:country":"US",
    "sg:address":"4302 Piney Creek Ln",
    "sg:city":"Spring",
    "sg:classifiers":[
        {
            "category":"Shopping",
            "subcategory":"Florist",
            "type":"Retail Goods"
        }
    ],
    "sg:phone":"+1 281 536 4042",
    "sg:postcode":"77388",
    "sg:province":"TX",
    "wof:name":"Master Designs",
    "wof:placetype":"venue"
},
  "geometry": {"coordinates":[-95.484493,30.067927],"type":"Point"}
}