{
  "type": "Feature",
  "properties": {
    "iso:country":"US",
    "sg:address":"309 Cedarwood St",
    "sg:city":"Azle",
    "sg:classifiers":[
        {
            "category":"Banks & Credit Unions",
            "subcategory":"Financial Services",
            "type":"Services"
        }
    ],
    "sg:phone":"+1 817 221 3138",
    "sg:postcode":"76020",
    "sg:province":"TX",
    "sg:tags":[
        "trust",
        "management"
    ],
    "wof:name":"Odessa P Sanders",
    "wof:placetype":"venue"
},
  "geometry": {"coordinates":[-97.57032599999999,32.916881],"type":"Point"}
}