{
  "type": "Feature",
  "properties": {
    "iso:country":"US",
    "sg:address":"102 Davis St",
    "sg:city":"Gilmer",
    "sg:classifiers":[
        {
            "category":"Retail",
            "subcategory":"Repair Shop",
            "type":"Services"
        },
        {
            "category":"Wholesale",
            "subcategory":"Construction Materials",
            "type":"Manufacturing & Wholesale Goods"
        }
    ],
    "sg:phone":"+1 903 680 2158",
    "sg:postcode":"75644",
    "sg:province":"TX",
    "sg:tags":[
        "refinish",
        "furniture",
        "caning",
        "supply"
    ],
    "wof:name":"Finishing Touch",
    "wof:placetype":"venue"
},
  "geometry": {"coordinates":[-94.94510699999999,32.72875],"type":"Point"}
}