{
  "type": "Feature",
  "properties": {
    "iso:country":"US",
    "sg:address":"590 E Hwy 121",
    "sg:city":"Lewisville",
    "sg:classifiers":[
        {
            "category":"Autos & Motor Vehicles",
            "subcategory":"Automobile Sales",
            "type":"Retail Goods"
        }
    ],
    "sg:phone":"+1 972 436 7418",
    "sg:postcode":"75057",
    "sg:province":"TX",
    "sg:tags":[
        "car",
        "used"
    ],
    "wof:name":"Weaver Auto Brokers",
    "wof:placetype":"venue"
},
  "geometry": {"coordinates":[-96.98604400000001,33.039917],"type":"Point"}
}