{
  "type": "Feature",
  "properties": {
    "iso:country":"US",
    "sg:address":"4041 Mystic Sunrise Dr",
    "sg:city":"San Antonio",
    "sg:classifiers":[
        {
            "category":"Retail",
            "subcategory":"Auto Repair",
            "type":"Services"
        }
    ],
    "sg:phone":"+1 210 320 6571",
    "sg:postcode":"78244",
    "sg:province":"TX",
    "sg:tags":[
        "glass",
        "coating",
        "tinting"
    ],
    "wof:name":"Moblie Tint & Detail",
    "wof:placetype":"venue"
},
  "geometry": {"coordinates":[-98.368787,29.463033],"type":"Point"}
}