{
  "type": "Feature",
  "properties": {
    "iso:country":"US",
    "sg:address":"100 W Broad St",
    "sg:city":"Forney",
    "sg:classifiers":[
        {
            "category":"Retail",
            "subcategory":"Auto Repair",
            "type":"Services"
        }
    ],
    "sg:phone":"+1 972 552 2130",
    "sg:postcode":"75126",
    "sg:province":"TX",
    "sg:tags":[
        "repairing",
        "automobile"
    ],
    "wof:name":"Forney Auto Tech",
    "wof:placetype":"venue"
},
  "geometry": {"coordinates":[-96.471012,32.749769],"type":"Point"}
}