{
  "type": "Feature",
  "properties": {
    "iso:country":"US",
    "sg:address":"400 E Friar Tuck Ln",
    "sg:city":"Houston",
    "sg:classifiers":[
        {
            "category":"Professional",
            "subcategory":"Lawyer & Legal Services",
            "type":"Services"
        }
    ],
    "sg:phone":"+1 713 686 6315",
    "sg:postcode":"77024",
    "sg:province":"TX",
    "wof:name":"Cunningham Lloyd R Atty",
    "wof:placetype":"venue"
},
  "geometry": {"coordinates":[-95.468903,29.775499],"type":"Point"}
}