{
  "type": "Feature",
  "properties": {
    "iso:country":"US",
    "sg:address":"2905 National Dr",
    "sg:city":"Garland",
    "sg:classifiers":[
        {
            "category":"Manufacturing",
            "subcategory":"Printing",
            "type":"Manufacturing & Wholesale Goods"
        }
    ],
    "sg:phone":"+1 972 840 0626",
    "sg:postcode":"75041",
    "sg:province":"TX",
    "sg:tags":[
        "print",
        "bookbinder",
        "bindery"
    ],
    "wof:name":"Lumar Graphics Arts",
    "wof:placetype":"venue"
},
  "geometry": {"coordinates":[-96.67269400000001,32.879049],"type":"Point"}
}