{
  "type": "Feature",
  "properties": {
    "iso:country":"US",
    "sg:address":"2344 N Expressway",
    "sg:city":"Brownsville",
    "sg:classifiers":[
        {
            "category":"Restaurant",
            "type":"Food & Drink"
        }
    ],
    "sg:menulink":"http://www.allmenus.com/tx/brownsville/91815-shoneys-restaurant/menu/",
    "sg:phone":"+1 956 504 1500",
    "sg:postcode":"78520",
    "sg:province":"TX",
    "sg:tags":[
        "american"
    ],
    "wof:name":"Shoney's Restaurant",
    "wof:placetype":"venue"
},
  "geometry": {"coordinates":[-97.50471899999999,25.950851],"type":"Point"}
}