{
  "type": "Feature",
  "properties": {
    "iso:country":"US",
    "sg:address":"11700 Preston Rd",
    "sg:city":"Dallas",
    "sg:classifiers":[
        {
            "category":"Education",
            "subcategory":"Special Training",
            "type":"Public Place"
        }
    ],
    "sg:phone":"+1 214 363 8585",
    "sg:postcode":"75230",
    "sg:province":"TX",
    "sg:tags":[
        "school",
        "art"
    ],
    "wof:name":"Gymboree Play & Music",
    "wof:placetype":"venue"
},
  "geometry": {"coordinates":[-96.803894,32.907984],"type":"Point"}
}