{
  "type": "Feature",
  "properties": {
    "iso:country":"US",
    "sg:address":"7190 Oaklawn Dr",
    "sg:city":"San Antonio",
    "sg:classifiers":[
        {
            "category":"Government",
            "subcategory":"Office",
            "type":"Public Place"
        }
    ],
    "sg:phone":"+1 210 342 0333",
    "sg:postcode":"78229",
    "sg:province":"TX",
    "sg:tags":[
        "village"
    ],
    "wof:name":"Pin Oak Apartments",
    "wof:placetype":"venue"
},
  "geometry": {"coordinates":[-98.55651899999999,29.498619],"type":"Point"}
}