{
  "type": "Feature",
  "properties": {
    "iso:country":"US",
    "sg:address":"2616 Swiss Ave",
    "sg:city":"Dallas",
    "sg:classifiers":[
        {
            "category":"Sports & Exercise",
            "subcategory":"Gym",
            "type":"Entertainment"
        }
    ],
    "sg:phone":"+1 214 821 1990",
    "sg:postcode":"75204",
    "sg:province":"TX",
    "sg:tags":[
        "fitness",
        "physical",
        "facility"
    ],
    "wof:name":"Club Dallas",
    "wof:placetype":"venue"
},
  "geometry": {"coordinates":[-96.787763,32.78712],"type":"Point"}
}