{
  "type": "Feature",
  "properties": {
    "iso:country":"US",
    "sg:address":"10226 Cude Cemetery Rd",
    "sg:city":"Willis",
    "sg:classifiers":[
        {
            "category":"Shopping",
            "subcategory":"Clothing, Apparel, & Fashions",
            "type":"Retail Goods"
        }
    ],
    "sg:phone":"+1 713 703 7440",
    "sg:postcode":"77318",
    "sg:province":"TX",
    "sg:tags":[
        "family",
        "real estate"
    ],
    "wof:name":"Outpost Ventures Inc",
    "wof:placetype":"venue"
},
  "geometry": {"coordinates":[-95.557219,30.391941],"type":"Point"}
}