{
  "type": "Feature",
  "properties": {
    "iso:country":"US",
    "sg:address":"4332 Belclaire Ave",
    "sg:city":"Dallas",
    "sg:classifiers":[
        {
            "category":"Farming",
            "subcategory":"Livestock Farm",
            "type":"Manufacturing & Wholesale Goods"
        }
    ],
    "sg:phone":"+1 214 521 7271",
    "sg:postcode":"75205",
    "sg:province":"TX",
    "sg:tags":[
        "animal",
        "general"
    ],
    "wof:name":"Antom Ranch Family Partnr LP",
    "wof:placetype":"venue"
},
  "geometry": {"coordinates":[-96.808832,32.830273],"type":"Point"}
}