{
  "type": "Feature",
  "properties": {
    "iso:country":"US",
    "sg:address":"7233a Fondren Rd",
    "sg:city":"Houston",
    "sg:classifiers":[
        {
            "category":"Deli",
            "type":"Food & Drink"
        }
    ],
    "sg:menulink":"http://www.allmenus.com/tx/houston/126766-blimpie-subs--sandwiches/menu/",
    "sg:phone":"+1 713 271 7057",
    "sg:postcode":"77036",
    "sg:province":"TX",
    "sg:tags":[
        "wrap",
        "american",
        "sandwich"
    ],
    "wof:name":"Blimpie Subs & Sandwiches",
    "wof:placetype":"venue"
},
  "geometry": {"coordinates":[-95.51877899999999,29.701246],"type":"Point"}
}