{
  "type": "Feature",
  "properties": {
    "iso:country":"US",
    "sg:address":"4818 Anice St",
    "sg:city":"Houston",
    "sg:classifiers":[
        {
            "category":"Building & Trades",
            "subcategory":"Plumbing",
            "type":"Services"
        }
    ],
    "sg:phone":"+1 281 449 3276",
    "sg:postcode":"77039",
    "sg:province":"TX",
    "sg:tags":[
        "conditioning",
        "air",
        "system",
        "contractor"
    ],
    "wof:name":"Dick Pickerill Air Cond & Htg",
    "wof:placetype":"venue"
},
  "geometry": {"coordinates":[-95.31974,29.908996],"type":"Point"}
}