{
  "type": "Feature",
  "properties": {
    "iso:country":"US",
    "sg:address":"11447 US Hwy 87",
    "sg:city":"Victoria",
    "sg:classifiers":[
        {
            "category":"Retail",
            "subcategory":"Veterinary Services",
            "type":"Services"
        }
    ],
    "sg:phone":"+1 361 572 4397",
    "sg:postcode":"77904",
    "sg:province":"TX",
    "sg:tags":[
        "veterinarian"
    ],
    "wof:name":"Town & Country Veterinary Clnc",
    "wof:placetype":"venue"
},
  "geometry": {"coordinates":[-97.073723,28.900711],"type":"Point"}
}