{
  "type": "Feature",
  "properties": {
    "iso:country":"US",
    "sg:address":"602 N Ben Jordan St",
    "sg:city":"Victoria",
    "sg:classifiers":[
        {
            "category":"Organizations",
            "subcategory":"Religious Organization",
            "type":"Services"
        }
    ],
    "sg:phone":"+1 361 576 1827",
    "sg:postcode":"77901",
    "sg:province":"TX",
    "wof:name":"Christian Zion Tabernacle Ctr",
    "wof:placetype":"venue"
},
  "geometry": {"coordinates":[-96.98144000000001,28.795508],"type":"Point"}
}