{
  "type": "Feature",
  "properties": {
    "iso:country":"US",
    "sg:address":"8500 el Rey Blvd",
    "sg:city":"Austin",
    "sg:classifiers":[
        {
            "category":"Manufacturing",
            "subcategory":"Glass & Minerals",
            "type":"Manufacturing & Wholesale Goods"
        }
    ],
    "sg:phone":"+1 512 288 5597",
    "sg:postcode":"78737",
    "sg:province":"TX",
    "sg:tags":[
        "ready",
        "concrete",
        "mfg"
    ],
    "wof:name":"Charlotte Ready",
    "wof:placetype":"venue"
},
  "geometry": {"coordinates":[-97.899146,30.224345],"type":"Point"}
}