{
  "type": "Feature",
  "properties": {
    "iso:country":"US",
    "sg:address":"609 W Carolanne Blvd",
    "sg:city":"Marshall",
    "sg:classifiers":[
        {
            "category":"Organizations",
            "subcategory":"Religious Organization",
            "type":"Services"
        }
    ],
    "sg:phone":"+1 903 935 3674",
    "sg:postcode":"75672",
    "sg:province":"TX",
    "sg:tags":[
        "church"
    ],
    "wof:name":"Fairview Baptist Church",
    "wof:placetype":"venue"
},
  "geometry": {"coordinates":[-94.372767,32.516553],"type":"Point"}
}