{
  "type": "Feature",
  "properties": {
    "iso:country":"US",
    "sg:address":"2761 64th St",
    "sg:city":"Port Arthur",
    "sg:classifiers":[
        {
            "category":"Professional",
            "type":"Services"
        }
    ],
    "sg:phone":"+1 409 736 2971",
    "sg:postcode":"77640",
    "sg:province":"TX",
    "wof:name":"Gulf Coast Document Services",
    "wof:placetype":"venue"
},
  "geometry": {"coordinates":[-94.02737500000001,29.907534],"type":"Point"}
}