{
  "type": "Feature",
  "properties": {
    "iso:country":"US",
    "sg:address":"13107 Fm 969",
    "sg:city":"Austin",
    "sg:classifiers":[
        {
            "category":"Shopping",
            "subcategory":"Antiques",
            "type":"Retail Goods"
        }
    ],
    "sg:phone":"+1 512 276 7793",
    "sg:postcode":"78724",
    "sg:province":"TX",
    "wof:name":"Austin Stamp & Coin",
    "wof:placetype":"venue"
},
  "geometry": {"coordinates":[-97.58869900000001,30.2502],"type":"Point"}
}