{
  "type": "Feature",
  "properties": {
    "iso:country":"US",
    "sg:address":"5710 W Lovers Ln",
    "sg:city":"Dallas",
    "sg:classifiers":[
        {
            "category":"Home & Garden",
            "subcategory":"Furniture",
            "type":"Retail Goods"
        }
    ],
    "sg:phone":"+1 214 752 5890",
    "sg:postcode":"75209",
    "sg:province":"TX",
    "wof:name":"Estancia Home Collection",
    "wof:placetype":"venue"
},
  "geometry": {"coordinates":[-96.814761,32.851086],"type":"Point"}
}