{
  "type": "Feature",
  "properties": {
    "iso:country":"US",
    "sg:address":"330 W Hutchison St",
    "sg:city":"San Marcos",
    "sg:classifiers":[
        {
            "category":"Social Services",
            "subcategory":"Child Care",
            "type":"Services"
        }
    ],
    "sg:phone":"+1 512 396 3216",
    "sg:postcode":"78666",
    "sg:province":"TX",
    "sg:tags":[
        "day"
    ],
    "wof:name":"Mothers Day Out & Preschool P",
    "wof:placetype":"venue"
},
  "geometry": {"coordinates":[-97.944467,29.883867],"type":"Point"}
}