{
  "type": "Feature",
  "properties": {
    "iso:country":"US",
    "sg:address":"2002 Clark Blvd",
    "sg:city":"Laredo",
    "sg:classifiers":[
        {
            "category":"Farming",
            "subcategory":"Livestock Farm",
            "type":"Manufacturing & Wholesale Goods"
        }
    ],
    "sg:phone":"+1 956 723 7603",
    "sg:postcode":"78043",
    "sg:province":"TX",
    "sg:tags":[
        "animal",
        "general"
    ],
    "wof:name":"Ojuelos Ranch Ltd",
    "wof:placetype":"venue"
},
  "geometry": {"coordinates":[-99.475221,27.516723],"type":"Point"}
}