{
  "type": "Feature",
  "properties": {
    "iso:country":"US",
    "sg:address":"9219 Katy Freeway 1st Fl",
    "sg:city":"Houston",
    "sg:classifiers":[
        {
            "category":"Restaurant",
            "type":"Food & Drink"
        }
    ],
    "sg:postcode":"77024",
    "sg:province":"TX",
    "wof:name":"Linda's Deli",
    "wof:placetype":"venue"
},
  "geometry": {"coordinates":[-95.51849,29.783747],"type":"Point"}
}