{
  "type": "Feature",
  "properties": {
    "iso:country":"US",
    "sg:address":"1606 E Hwy 190",
    "sg:city":"Copperas Cove",
    "sg:classifiers":[
        {
            "category":"Shopping",
            "subcategory":"Hobbies, Toys, & Games",
            "type":"Retail Goods"
        }
    ],
    "sg:phone":"+1 254 542 4005",
    "sg:postcode":"76522",
    "sg:province":"TX",
    "sg:tags":[
        "craft",
        "supply"
    ],
    "wof:name":"Sharon's Arts & Craft",
    "wof:placetype":"venue"
},
  "geometry": {"coordinates":[-97.886247,31.120068],"type":"Point"}
}