{
  "type": "Feature",
  "properties": {
    "iso:country":"US",
    "sg:address":"5520 Byrd St",
    "sg:city":"Beaumont",
    "sg:classifiers":[
        {
            "category":"Building & Trades",
            "subcategory":"Electrical",
            "type":"Services"
        },
        {
            "category":"Wholesale",
            "subcategory":"Electrical",
            "type":"Manufacturing & Wholesale Goods"
        }
    ],
    "sg:phone":"+1 409 842 4016",
    "sg:postcode":"77707",
    "sg:province":"TX",
    "sg:tags":[
        "sound",
        "repair",
        "equipment",
        "system",
        "contractor"
    ],
    "wof:name":"Gye Electronics Systems",
    "wof:placetype":"venue"
},
  "geometry": {"coordinates":[-94.15325300000001,30.064868],"type":"Point"}
}