{
  "type": "Feature",
  "properties": {
    "iso:country":"US",
    "sg:address":"16227 Robinwood Ln",
    "sg:city":"San Antonio",
    "sg:classifiers":[
        {
            "category":"Professional",
            "subcategory":"Management & Consulting",
            "type":"Services"
        }
    ],
    "sg:phone":"+1 210 764 1747",
    "sg:postcode":"78248",
    "sg:province":"TX",
    "wof:name":"Barlow Management GP LLC",
    "wof:placetype":"venue"
},
  "geometry": {"coordinates":[-98.51912900000001,29.5954],"type":"Point"}
}