{
  "type": "Feature",
  "properties": {
    "iso:country":"US",
    "sg:address":"3142 FM 2578",
    "sg:city":"Kaufman",
    "sg:classifiers":[
        {
            "category":"Retail",
            "subcategory":"Animal Services",
            "type":"Services"
        }
    ],
    "sg:phone":"+1 972 962 2797",
    "sg:postcode":"75142",
    "sg:province":"TX",
    "wof:name":"Walkers West",
    "wof:placetype":"venue"
},
  "geometry": {"coordinates":[-96.351744,32.621281],"type":"Point"}
}