{
  "type": "Feature",
  "properties": {
    "iso:country":"US",
    "sg:address":"2800 Lyndon B Johnson Fwy",
    "sg:city":"Dallas",
    "sg:classifiers":[
        {
            "category":"Sports & Exercise",
            "subcategory":"Golf",
            "type":"Entertainment"
        }
    ],
    "sg:phone":"+1 972 852 2725",
    "sg:postcode":"75234",
    "sg:province":"TX",
    "sg:tags":[
        "course"
    ],
    "wof:name":"Golfline",
    "wof:placetype":"venue"
},
  "geometry": {"coordinates":[-96.88246599999999,32.910893],"type":"Point"}
}