{
  "type": "Feature",
  "properties": {
    "iso:country":"US",
    "sg:address":"2 Greenbrier Ct",
    "sg:city":"Mineral Wells",
    "sg:classifiers":[
        {
            "category":"Health Services",
            "subcategory":"Doctor",
            "type":"Services"
        }
    ],
    "sg:phone":"+1 940 325 0742",
    "sg:postcode":"76067",
    "sg:province":"TX",
    "sg:tags":[
        "medical"
    ],
    "wof:name":"Dave Arvinda MD",
    "wof:placetype":"venue"
},
  "geometry": {"coordinates":[-98.14376300000001,32.806846],"type":"Point"}
}