{
  "type": "Feature",
  "properties": {
    "iso:country":"US",
    "sg:address":"101 Lake Rd",
    "sg:city":"La Marque",
    "sg:classifiers":[
        {
            "category":"Food & Beverages",
            "subcategory":"Groceries & Convenience Stores",
            "type":"Retail Goods"
        }
    ],
    "sg:phone":"+1 409 938 0356",
    "sg:postcode":"77568",
    "sg:province":"TX",
    "wof:name":"Circle T Quick Stop",
    "wof:placetype":"venue"
},
  "geometry": {"coordinates":[-94.97976800000001,29.376495],"type":"Point"}
}