{
  "type": "Feature",
  "properties": {
    "iso:country":"US",
    "sg:address":"5913 71st St",
    "sg:city":"Lubbock",
    "sg:classifiers":[
        {
            "category":"Shopping",
            "subcategory":"Computers & Home Electronics",
            "type":"Retail Goods"
        }
    ],
    "sg:phone":"+1 806 798 2969",
    "sg:postcode":"79424",
    "sg:province":"TX",
    "wof:name":"Throgs Net Computers Inc",
    "wof:placetype":"venue"
},
  "geometry": {"coordinates":[-101.94199399999999,33.529],"type":"Point"}
}