{
  "type": "Feature",
  "properties": {
    "iso:country":"US",
    "sg:address":"1303 N Highway 287",
    "sg:city":"Decatur",
    "sg:classifiers":[
        {
            "category":"Place Of Worship",
            "type":"Public Place"
        }
    ],
    "sg:phone":"+1 940 627 4222",
    "sg:postcode":"76234",
    "sg:province":"TX",
    "sg:tags":[
        "church"
    ],
    "wof:name":"Crossroads Bible Church",
    "wof:placetype":"venue"
},
  "geometry": {"coordinates":[-97.604724,33.244256],"type":"Point"}
}