{
  "type": "Feature",
  "properties": {
    "iso:country":"US",
    "sg:address":"501 Ellen Trout Dr",
    "sg:city":"Lufkin",
    "sg:classifiers":[
        {
            "category":"Wholesale",
            "subcategory":"Machinery & Supplies",
            "type":"Manufacturing & Wholesale Goods"
        }
    ],
    "sg:phone":"+1 936 639 1101",
    "sg:postcode":"75904",
    "sg:province":"TX",
    "sg:tags":[
        "fitting",
        "hose",
        "coupling"
    ],
    "sg:website":"www.lufkinrubber.com",
    "wof:name":"Lufkin Rubber & Gasket Co",
    "wof:placetype":"venue"
},
  "geometry": {"coordinates":[-94.71606800000001,31.372688],"type":"Point"}
}