{
  "type": "Feature",
  "properties": {
    "iso:country":"US",
    "sg:address":"6407 Colleyville Blvd",
    "sg:city":"Colleyville",
    "sg:classifiers":[
        {
            "category":"Health Services",
            "subcategory":"Doctor",
            "type":"Services"
        }
    ],
    "sg:phone":"+1 817 251 6836",
    "sg:postcode":"76034",
    "sg:province":"TX",
    "sg:tags":[
        "physician",
        "surgeon"
    ],
    "wof:name":"Barbara A Smythe MD Pa",
    "wof:placetype":"venue"
},
  "geometry": {"coordinates":[-97.142544,32.900329],"type":"Point"}
}