{
  "type": "Feature",
  "properties": {
    "iso:country":"US",
    "sg:address":"1613 Lamar Ave",
    "sg:city":"Paris",
    "sg:classifiers":[
        {
            "category":"Banks & Credit Unions",
            "subcategory":"Investment Brokerage",
            "type":"Services"
        }
    ],
    "sg:phone":"+1 214 785 9395",
    "sg:postcode":"75460",
    "sg:province":"TX",
    "sg:tags":[
        "consultant",
        "planning",
        "financial"
    ],
    "wof:name":"Annis Financial Svc",
    "wof:placetype":"venue"
},
  "geometry": {"coordinates":[-95.539598,33.661341],"type":"Point"}
}