{
  "type": "Feature",
  "properties": {
    "iso:country":"US",
    "sg:address":"6333 Chimney Rock Rd",
    "sg:city":"Houston",
    "sg:classifiers":[
        {
            "category":"Professional",
            "type":"Services"
        }
    ],
    "sg:phone":"+1 713 830 5534",
    "sg:postcode":"77081",
    "sg:province":"TX",
    "sg:tags":[
        "establishment"
    ],
    "wof:name":"Chanoff Y",
    "wof:placetype":"venue"
},
  "geometry": {"coordinates":[-95.47627799999999,29.712267],"type":"Point"}
}