{
  "type": "Feature",
  "properties": {
    "iso:country":"US",
    "sg:address":"35235 State Hwy 249",
    "sg:city":"Pinehurst",
    "sg:classifiers":[
        {
            "category":"Building & Trades",
            "subcategory":"Construction",
            "type":"Services"
        }
    ],
    "sg:phone":"+1 832 934 0802",
    "sg:postcode":"77362",
    "sg:province":"TX",
    "sg:tags":[
        "house",
        "commercial",
        "contractor"
    ],
    "wof:name":"Industrial Construction and As",
    "wof:placetype":"venue"
},
  "geometry": {"coordinates":[-95.679832,30.169226],"type":"Point"}
}