{
  "type": "Feature",
  "properties": {
    "iso:country":"US",
    "sg:address":"2727 Bolton Boone Dr",
    "sg:city":"De Soto",
    "sg:classifiers":[
        {
            "category":"Organizations",
            "subcategory":"Non-profit Organization",
            "type":"Services"
        }
    ],
    "sg:phone":"+1 972 572 4466",
    "sg:postcode":"75115",
    "sg:province":"TX",
    "sg:tags":[
        "social"
    ],
    "wof:name":"Alliance Ambltory Infusion Ctr",
    "wof:placetype":"venue"
},
  "geometry": {"coordinates":[-96.878518,32.644544],"type":"Point"}
}