{
  "type": "Feature",
  "properties": {
    "iso:country":"US",
    "sg:address":"11344 Interstate 10 E",
    "sg:city":"Baytown",
    "sg:classifiers":[
        {
            "category":"Retail",
            "subcategory":"Auto Repair",
            "type":"Services"
        }
    ],
    "sg:phone":"+1 281 303 3000",
    "sg:postcode":"77523",
    "sg:province":"TX",
    "sg:tags":[
        "recreational",
        "campers-repair",
        "vehicle"
    ],
    "wof:name":"Rv Service",
    "wof:placetype":"venue"
},
  "geometry": {"coordinates":[-94.88500000000001,29.823112],"type":"Point"}
}