{
  "type": "Feature",
  "properties": {
    "iso:country":"US",
    "sg:address":"21945 Katy Fwy",
    "sg:city":"Katy",
    "sg:classifiers":[
        {
            "category":"Banks & Credit Unions",
            "subcategory":"Financial Services",
            "type":"Services"
        }
    ],
    "sg:phone":"+1 281 392 9272",
    "sg:postcode":"77450",
    "sg:province":"TX",
    "sg:tags":[
        "investor"
    ],
    "wof:name":"Bal Investments Inc",
    "wof:placetype":"venue"
},
  "geometry": {"coordinates":[-95.752872,29.783278],"type":"Point"}
}