{
  "type": "Feature",
  "properties": {
    "iso:country":"US",
    "sg:address":"5847 Flamingo Dr",
    "sg:city":"Houston",
    "sg:classifiers":[
        {
            "category":"Retail",
            "subcategory":"Funeral Services",
            "type":"Services"
        }
    ],
    "sg:phone":"+1 713 738 3231",
    "sg:postcode":"77033",
    "sg:province":"TX",
    "wof:name":"Robinson Funeral Home",
    "wof:placetype":"venue"
},
  "geometry": {"coordinates":[-95.330198,29.661027],"type":"Point"}
}