{
  "type": "Feature",
  "properties": {
    "iso:country":"US",
    "sg:address":"3401 Harpers Ferry Lane",
    "sg:city":"Austin",
    "sg:classifiers":[
        {
            "category":"Communications",
            "subcategory":"Film & Video Production",
            "type":"Services"
        },
        {
            "category":"Communications",
            "type":"Services"
        }
    ],
    "sg:phone":"+1 512 282 2734",
    "sg:postcode":"78745",
    "sg:province":"TX",
    "sg:tags":[
        "recording",
        "rehearsal",
        "studio",
        "service-sound"
    ],
    "wof:name":"Lorien Sound Studio",
    "wof:placetype":"venue"
},
  "geometry": {"coordinates":[-97.83364400000001,30.206244],"type":"Point"}
}