{
  "type": "Feature",
  "properties": {
    "iso:country":"US",
    "sg:address":"2520 Randle Hill Rd",
    "sg:city":"Brenham",
    "sg:classifiers":[
        {
            "category":"Farming",
            "subcategory":"Dairy Farm",
            "type":"Manufacturing & Wholesale Goods"
        }
    ],
    "sg:phone":"+1 979 836 2684",
    "sg:postcode":"77833",
    "sg:province":"TX",
    "sg:tags":[
        "hog",
        "or",
        "feedlot"
    ],
    "wof:name":"Daniel Engeling",
    "wof:placetype":"venue"
},
  "geometry": {"coordinates":[-96.40568500000001,30.088718],"type":"Point"}
}