{
  "type": "Feature",
  "properties": {
    "iso:country":"US",
    "sg:address":"1515 Garrettson Ln",
    "sg:city":"Houston",
    "sg:classifiers":[
        {
            "category":"Professional",
            "type":"Services"
        }
    ],
    "sg:phone":"+1 713 626 4064",
    "sg:postcode":"77056",
    "sg:province":"TX",
    "wof:name":"Stephen Oglesby",
    "wof:placetype":"venue"
},
  "geometry": {"coordinates":[-95.45972999999999,29.751025],"type":"Point"}
}