{
  "type": "Feature",
  "properties": {
    "iso:country":"US",
    "sg:address":"1827 W Woodlawn Ave",
    "sg:city":"San Antonio",
    "sg:classifiers":[
        {
            "category":"Retail",
            "subcategory":"Repair Shop",
            "type":"Services"
        }
    ],
    "sg:phone":"+1 210 732 3180",
    "sg:postcode":"78201",
    "sg:province":"TX",
    "sg:tags":[
        "lock",
        "locksmith"
    ],
    "wof:name":"Lock & Go Locksmith",
    "wof:placetype":"venue"
},
  "geometry": {"coordinates":[-98.52776299999999,29.454263],"type":"Point"}
}