{
  "type": "Feature",
  "properties": {
    "iso:country":"US",
    "sg:address":"1733 Woodstead Ct",
    "sg:city":"Spring",
    "sg:classifiers":[
        {
            "category":"Mining & Drilling",
            "type":"Manufacturing & Wholesale Goods"
        }
    ],
    "sg:phone":"+1 281 363 0099",
    "sg:postcode":"77380",
    "sg:province":"TX",
    "sg:tags":[
        "exploration"
    ],
    "wof:name":"McGregor Oil Co",
    "wof:placetype":"venue"
},
  "geometry": {"coordinates":[-95.460752,30.154549],"type":"Point"}
}