{
  "type": "Feature",
  "properties": {
    "iso:country":"US",
    "sg:address":"131 Evanston St",
    "sg:city":"Houston",
    "sg:classifiers":[
        {
            "category":"Shopping",
            "subcategory":"Clothing, Apparel, & Fashions",
            "type":"Retail Goods"
        }
    ],
    "sg:phone":"+1 713 450 3880",
    "sg:postcode":"77015",
    "sg:province":"TX",
    "wof:name":"Flirty Fashions",
    "wof:placetype":"venue"
},
  "geometry": {"coordinates":[-95.178078,29.803381],"type":"Point"}
}