{
  "type": "Feature",
  "properties": {
    "iso:country":"US",
    "sg:address":"4315 Neely Ave",
    "sg:city":"Midland",
    "sg:classifiers":[
        {
            "category":"Personal",
            "subcategory":"Beauty Salon",
            "type":"Services"
        }
    ],
    "sg:phone":"+1 432 689 0688",
    "sg:postcode":"79707",
    "sg:province":"TX",
    "sg:tags":[
        "shop"
    ],
    "wof:name":"Gambrells Hair & Clothing Sha",
    "wof:placetype":"venue"
},
  "geometry": {"coordinates":[-102.138862,32.008993],"type":"Point"}
}