{
  "type": "Feature",
  "properties": {
    "iso:country":"US",
    "sg:address":"3310 Live Oak St Ste 202",
    "sg:city":"Dallas",
    "sg:classifiers":[
        {
            "category":"Health Services",
            "subcategory":"Doctor",
            "type":"Services"
        }
    ],
    "sg:phone":"+1 214 821 9100",
    "sg:postcode":"75204",
    "sg:province":"TX",
    "wof:name":"Fuller Deborah A MD PA",
    "wof:placetype":"venue"
},
  "geometry": {"coordinates":[-96.785004,32.792198],"type":"Point"}
}