{
  "type": "Feature",
  "properties": {
    "iso:country":"US",
    "sg:address":"6659 San Pedro Ave",
    "sg:city":"San Antonio",
    "sg:classifiers":[
        {
            "category":"Retail",
            "subcategory":"Auto Repair",
            "type":"Services"
        }
    ],
    "sg:phone":"+1 210 349 5376",
    "sg:postcode":"78216",
    "sg:province":"TX",
    "sg:tags":[
        "exhaust"
    ],
    "wof:name":"Midas Muffler",
    "wof:placetype":"venue"
},
  "geometry": {"coordinates":[-98.499334,29.500627],"type":"Point"}
}