{
  "type": "Feature",
  "properties": {
    "iso:country":"US",
    "sg:address":"1119 E Cowden Ave",
    "sg:city":"Midland",
    "sg:classifiers":[
        {
            "category":"Building & Trades",
            "subcategory":"Cleaning & Sanitation",
            "type":"Services"
        }
    ],
    "sg:phone":"+1 432 620 0012",
    "sg:postcode":"79701",
    "sg:province":"TX",
    "sg:tags":[
        "maintenance"
    ],
    "wof:name":"Rams Floor Care & Maintenance",
    "wof:placetype":"venue"
},
  "geometry": {"coordinates":[-102.066996,32.012508],"type":"Point"}
}