{
  "type": "Feature",
  "properties": {
    "iso:country":"US",
    "sg:address":"1215 Elder",
    "sg:city":"Carrollton",
    "sg:classifiers":[
        {
            "category":"Utilities",
            "subcategory":"Mobile Phone",
            "type":"Services"
        }
    ],
    "sg:phone":"+1 972 492 7076",
    "sg:postcode":"75007",
    "sg:province":"TX",
    "sg:tags":[
        "communication",
        "radiotelephone"
    ],
    "wof:name":"James Communications",
    "wof:placetype":"venue"
},
  "geometry": {"coordinates":[-96.91629,33.000025],"type":"Point"}
}