{
  "type": "Feature",
  "properties": {
    "iso:country":"US",
    "sg:address":"4324 Live Oak Dr",
    "sg:city":"Mesquite",
    "sg:classifiers":[
        {
            "category":"Building & Trades",
            "subcategory":"Plumbing",
            "type":"Services"
        }
    ],
    "sg:phone":"+1 972 613 7224",
    "sg:postcode":"75150",
    "sg:province":"TX",
    "sg:tags":[
        "contractor"
    ],
    "wof:name":"Boshart Repair Service",
    "wof:placetype":"venue"
},
  "geometry": {"coordinates":[-96.638801,32.824866],"type":"Point"}
}