{
  "type": "Feature",
  "properties": {
    "iso:country":"US",
    "sg:address":"2735 Austin Hwy",
    "sg:city":"San Antonio",
    "sg:classifiers":[
        {
            "category":"Banks & Credit Unions",
            "subcategory":"Bank",
            "type":"Services"
        }
    ],
    "sg:phone":"+1 210 220 4712",
    "sg:postcode":"78218",
    "sg:province":"TX",
    "sg:tags":[
        "commercial"
    ],
    "wof:name":"Frost National Bank",
    "wof:placetype":"venue"
},
  "geometry": {"coordinates":[-98.403362,29.513574],"type":"Point"}
}