{
  "type": "Feature",
  "properties": {
    "iso:country":"US",
    "sg:address":"1627 Pacific Ave",
    "sg:city":"Dallas",
    "sg:phone":"+1 972 918 0675",
    "sg:postcode":"75201",
    "sg:province":"TX",
    "sg:website":"http://www.lisascreationsbrides.com",
    "wof:name":"Lisas Creations Dallas TX - Bridal Shop, Wedding, Brides D",
    "wof:placetype":"venue"
},
  "geometry": {"coordinates":[-96.79931000000001,32.782462],"type":"Point"}
}