{
  "type": "Feature",
  "properties": {
    "iso:country":"US",
    "sg:address":"3401 Princeton Dr",
    "sg:city":"Irving",
    "sg:classifiers":[
        {
            "category":"Shopping",
            "type":"Retail Goods"
        }
    ],
    "sg:phone":"+1 972 791 2416",
    "sg:postcode":"75062",
    "sg:province":"TX",
    "sg:tags":[
        "merchandise"
    ],
    "wof:name":"CE(bill) Smith Jr",
    "wof:placetype":"venue"
},
  "geometry": {"coordinates":[-96.94731299999999,32.849677],"type":"Point"}
}