{
  "type": "Feature",
  "properties": {
    "iso:country":"US",
    "sg:address":"1165 E Lucas Rd",
    "sg:city":"Allen",
    "sg:classifiers":[
        {
            "category":"Farming",
            "subcategory":"Farm",
            "type":"Manufacturing & Wholesale Goods"
        }
    ],
    "sg:phone":"+1 972 727 0900",
    "sg:postcode":"75002",
    "sg:province":"TX",
    "sg:tags":[
        "crop",
        "general"
    ],
    "wof:name":"Saint Judes Farm",
    "wof:placetype":"venue"
},
  "geometry": {"coordinates":[-96.560782,33.086038],"type":"Point"}
}