{
  "type": "Feature",
  "properties": {
    "iso:country":"US",
    "sg:address":"6200 Old Hemphill Rd",
    "sg:city":"Fort Worth",
    "sg:classifiers":[
        {
            "category":"Manufacturing",
            "subcategory":"Metals",
            "type":"Manufacturing & Wholesale Goods"
        },
        {
            "category":"Building & Trades",
            "subcategory":"Equipment Rental",
            "type":"Services"
        },
        {
            "category":"Manufacturing",
            "subcategory":"Tools & Machinery",
            "type":"Manufacturing & Wholesale Goods"
        }
    ],
    "sg:phone":"+1 817 293 6787",
    "sg:postcode":"76134",
    "sg:province":"TX",
    "sg:tags":[
        "business",
        "nonresidential",
        "mfg",
        "grinding",
        "production",
        "construction"
    ],
    "wof:name":"Fort Worth Centerless Grinding",
    "wof:placetype":"venue"
},
  "geometry": {"coordinates":[-97.323965,32.659965],"type":"Point"}
}