{
  "type": "Feature",
  "properties": {
    "iso:country":"US",
    "sg:address":"1707 Merton Dr",
    "sg:city":"Houston",
    "sg:classifiers":[
        {
            "category":"Professional",
            "type":"Services"
        }
    ],
    "sg:phone":"+1 281 439 2182",
    "sg:postcode":"77015",
    "sg:province":"TX",
    "wof:name":"E & A",
    "wof:placetype":"venue"
},
  "geometry": {"coordinates":[-95.160332,29.808109],"type":"Point"}
}