{
  "type": "Feature",
  "properties": {
    "iso:country":"US",
    "sg:address":"407 Country Meadow Dr",
    "sg:city":"Mansfield",
    "sg:classifiers":[
        {
            "category":"Manufacturing",
            "subcategory":"Retail Goods",
            "type":"Manufacturing & Wholesale Goods"
        }
    ],
    "sg:phone":"+1 817 561 4626",
    "sg:postcode":"76063",
    "sg:province":"TX",
    "sg:tags":[
        "product",
        "mfg"
    ],
    "wof:name":"County Road Industries",
    "wof:placetype":"venue"
},
  "geometry": {"coordinates":[-97.182922,32.591532],"type":"Point"}
}