{
  "type": "Feature",
  "properties": {
    "iso:country":"US",
    "sg:address":"6731 Sway St",
    "sg:city":"Houston",
    "sg:classifiers":[
        {
            "category":"Wholesale",
            "subcategory":"Hardware",
            "type":"Manufacturing & Wholesale Goods"
        },
        {
            "category":"Home & Garden",
            "subcategory":"Hardware",
            "type":"Retail Goods"
        },
        {
            "category":"Home & Garden",
            "subcategory":"Building Materials",
            "type":"Retail Goods"
        },
        {
            "category":"Building & Trades",
            "subcategory":"Construction",
            "type":"Services"
        }
    ],
    "sg:phone":"+1 281 437 4995",
    "sg:postcode":"77085",
    "sg:province":"TX",
    "sg:tags":[
        "face",
        "sand",
        "hardware-builders",
        "brick-clay-common",
        "gravel",
        "store"
    ],
    "wof:name":"Pine Island Sand Company Inc",
    "wof:placetype":"venue"
},
  "geometry": {"coordinates":[-95.488491,29.607625],"type":"Point"}
}