{
  "type": "Feature",
  "properties": {
    "iso:country":"US",
    "sg:address":"5902 Kostoryz Rd",
    "sg:city":"Corpus Christi",
    "sg:classifiers":[
        {
            "category":"Insurance",
            "subcategory":"Insurance Agent",
            "type":"Services"
        }
    ],
    "sg:phone":"+1 361 855 8866",
    "sg:postcode":"78415",
    "sg:province":"TX",
    "wof:name":"Carl F Badalich & Assoc",
    "wof:placetype":"venue"
},
  "geometry": {"coordinates":[-97.420894,27.715956],"type":"Point"}
}