{
  "type": "Feature",
  "properties": {
    "iso:country":"US",
    "sg:address":"3502 Oleander Dr",
    "sg:city":"Wylie",
    "sg:classifiers":[
        {
            "category":"Transit Center",
            "subcategory":"Freight",
            "type":"Transportation"
        },
        {
            "category":"Freight",
            "type":"Transportation"
        }
    ],
    "sg:phone":"+1 972 941 6563",
    "sg:postcode":"75098",
    "sg:province":"TX",
    "sg:tags":[
        "local",
        "trucking-motor",
        "trucking"
    ],
    "wof:name":"Efrem Trucking",
    "wof:placetype":"venue"
},
  "geometry": {"coordinates":[-96.59159,33.013127],"type":"Point"}
}