{
  "type": "Feature",
  "properties": {
    "iso:country":"US",
    "sg:address":"700 S 4th St",
    "sg:city":"Waco",
    "sg:classifiers":[
        {
            "category":"Real Estate",
            "subcategory":"Real Estate Operator",
            "type":"Services"
        }
    ],
    "sg:phone":"+1 254 752 4122",
    "sg:postcode":"76706",
    "sg:province":"TX",
    "sg:tags":[
        "apartment"
    ],
    "wof:name":"Aspen Square",
    "wof:placetype":"venue"
},
  "geometry": {"coordinates":[-97.12554900000001,31.55304],"type":"Point"}
}