{
  "type": "Feature",
  "properties": {
    "iso:country":"US",
    "sg:address":"1601 Houston Ave",
    "sg:city":"Port Arthur",
    "sg:classifiers":[
        {
            "category":"Personal",
            "subcategory":"Barber",
            "type":"Services"
        }
    ],
    "sg:phone":"+1 409 982 9700",
    "sg:postcode":"77640",
    "sg:province":"TX",
    "sg:tags":[
        "shop"
    ],
    "wof:name":"Esquire Barber Shop",
    "wof:placetype":"venue"
},
  "geometry": {"coordinates":[-93.949561,29.876583],"type":"Point"}
}