{
  "type": "Feature",
  "properties": {
    "iso:country":"US",
    "sg:address":"1900 Hall Johnson Rd",
    "sg:city":"Colleyville",
    "sg:classifiers":[
        {
            "category":"Government",
            "subcategory":"Fire Station",
            "type":"Public Place"
        }
    ],
    "sg:phone":"+1 817 488 6277",
    "sg:postcode":"76034",
    "sg:province":"TX",
    "sg:tags":[
        "department"
    ],
    "sg:website":"www.firehouse1.com",
    "wof:name":"Colleyville Fire Dept",
    "wof:placetype":"venue"
},
  "geometry": {"coordinates":[-97.13957499999999,32.892604],"type":"Point"}
}