{
  "type": "Feature",
  "properties": {
    "iso:country":"US",
    "sg:address":"5024 Overton Ridge Cir",
    "sg:city":"Fort Worth",
    "sg:classifiers":[
        {
            "category":"Professional",
            "type":"Services"
        }
    ],
    "sg:phone":"+1 817 249 1810",
    "sg:postcode":"76132",
    "sg:province":"TX",
    "wof:name":"Newgent Golf Inc",
    "wof:placetype":"venue"
},
  "geometry": {"coordinates":[-97.40461999999999,32.675294],"type":"Point"}
}