{
  "type": "Feature",
  "properties": {
    "iso:country":"US",
    "sg:address":"1100 4th St",
    "sg:city":"Graham",
    "sg:classifiers":[
        {
            "category":"Shopping",
            "subcategory":"Computers & Home Electronics",
            "type":"Retail Goods"
        }
    ],
    "sg:phone":"+1 940 549 8199",
    "sg:postcode":"76450",
    "sg:province":"TX",
    "sg:tags":[
        "equipment",
        "electronic",
        "supply"
    ],
    "wof:name":"Graham Electronics & More LLC",
    "wof:placetype":"venue"
},
  "geometry": {"coordinates":[-98.579291,33.106955],"type":"Point"}
}