{
  "type": "Feature",
  "properties": {
    "iso:country":"US",
    "sg:address":"608 N Lopez St",
    "sg:city":"Rio Grande City",
    "sg:classifiers":[
        {
            "category":"Cinema",
            "subcategory":"Movie Rental",
            "type":"Entertainment"
        }
    ],
    "sg:phone":"+1 956 487 2499",
    "sg:postcode":"78582",
    "sg:province":"TX",
    "sg:tags":[
        "leasing",
        "video",
        "disc",
        "tape"
    ],
    "wof:name":"Starr Video",
    "wof:placetype":"venue"
},
  "geometry": {"coordinates":[-98.814961,26.382835],"type":"Point"}
}