{
  "type": "Feature",
  "properties": {
    "iso:country":"US",
    "sg:address":"1010 Jeffery Dr",
    "sg:city":"Tyler",
    "sg:classifiers":[
        {
            "category":"Organizations",
            "subcategory":"Religious Organization",
            "type":"Services"
        }
    ],
    "sg:phone":"+1 903 561 5770",
    "sg:postcode":"75703",
    "sg:province":"TX",
    "wof:name":"Chc & Associates Inc",
    "wof:placetype":"venue"
},
  "geometry": {"coordinates":[-95.291611,32.272857],"type":"Point"}
}