{
  "type": "Feature",
  "properties": {
    "iso:country":"US",
    "sg:address":"1706 E Red River St",
    "sg:city":"Victoria",
    "sg:classifiers":[
        {
            "category":"Health Services",
            "subcategory":"Clinic",
            "type":"Services"
        }
    ],
    "sg:phone":"+1 361 570 7878",
    "sg:postcode":"77901",
    "sg:province":"TX",
    "sg:tags":[
        "home",
        "care"
    ],
    "wof:name":"Victoria Personal Care Home",
    "wof:placetype":"venue"
},
  "geometry": {"coordinates":[-96.987298,28.813948],"type":"Point"}
}