{
  "type": "Feature",
  "properties": {
    "iso:country":"US",
    "sg:address":"1406 N McDonald St",
    "sg:city":"Mc Kinney",
    "sg:classifiers":[
        {
            "category":"Professional",
            "subcategory":"Business Services",
            "type":"Services"
        }
    ],
    "sg:phone":"+1 972 562 2663",
    "sg:postcode":"75071",
    "sg:province":"TX",
    "wof:name":"Plano Bondingcom",
    "wof:placetype":"venue"
},
  "geometry": {"coordinates":[-96.613079,33.21306],"type":"Point"}
}