{
  "type": "Feature",
  "properties": {
    "iso:country":"US",
    "sg:address":"1607 Briarcliff Blvd",
    "sg:city":"Austin",
    "sg:classifiers":[
        {
            "category":"Real Estate",
            "subcategory":"Real Estate Services",
            "type":"Services"
        }
    ],
    "sg:phone":"+1 512 452 2603",
    "sg:postcode":"78723",
    "sg:province":"TX",
    "sg:tags":[
        "vacancy",
        "rental",
        "listing"
    ],
    "wof:name":"Earl Rosell",
    "wof:placetype":"venue"
},
  "geometry": {"coordinates":[-97.693697,30.314654],"type":"Point"}
}