{
  "type": "Feature",
  "properties": {
    "iso:country":"US",
    "sg:address":"2319 Hunter St",
    "sg:city":"Tyler",
    "sg:classifiers":[
        {
            "category":"Professional",
            "type":"Services"
        }
    ],
    "sg:phone":"+1 903 592 1489",
    "sg:postcode":"75701",
    "sg:province":"TX",
    "wof:name":"Terrys Guide Service",
    "wof:placetype":"venue"
},
  "geometry": {"coordinates":[-95.269516,32.33006],"type":"Point"}
}