{
  "type": "Feature",
  "properties": {
    "iso:country":"US",
    "sg:address":"7071 Lawndale St",
    "sg:city":"Houston",
    "sg:classifiers":[
        {
            "category":"Restaurant",
            "type":"Food & Drink"
        }
    ],
    "sg:phone":"+1 713 923 7878",
    "sg:postcode":"77023",
    "sg:province":"TX",
    "sg:tags":[
        "chinese"
    ],
    "wof:name":"Chinese On The Go",
    "wof:placetype":"venue"
},
  "geometry": {"coordinates":[-95.296066,29.717461],"type":"Point"}
}