{
  "type": "Feature",
  "properties": {
    "iso:country":"US",
    "sg:address":"4215 Bellvue Ave",
    "sg:city":"Austin",
    "sg:classifiers":[
        {
            "category":"Building & Trades",
            "subcategory":"Construction",
            "type":"Services"
        }
    ],
    "sg:phone":"+1 512 451 1151",
    "sg:postcode":"78756",
    "sg:province":"TX",
    "sg:tags":[
        "house"
    ],
    "wof:name":"Green Door Renovations",
    "wof:placetype":"venue"
},
  "geometry": {"coordinates":[-97.741277,30.311762],"type":"Point"}
}