{
  "type": "Feature",
  "properties": {
    "iso:country":"US",
    "sg:address":"150 E Main St",
    "sg:city":"Yorktown",
    "sg:classifiers":[
        {
            "category":"Banks & Credit Unions",
            "subcategory":"Bank",
            "type":"Services"
        }
    ],
    "sg:phone":"+1 361 564 2291",
    "sg:postcode":"78164",
    "sg:province":"TX",
    "wof:name":"Prosperity Bank",
    "wof:placetype":"venue"
},
  "geometry": {"coordinates":[-97.501569,28.981251],"type":"Point"}
}