{
  "type": "Feature",
  "properties": {
    "iso:country":"US",
    "sg:address":"219 E Nakoma Dr",
    "sg:city":"San Antonio",
    "sg:classifiers":[
        {
            "category":"Health Services",
            "subcategory":"Clinic",
            "type":"Services"
        }
    ],
    "sg:phone":"+1 210 979 8828",
    "sg:postcode":"78216",
    "sg:province":"TX",
    "sg:tags":[
        "home"
    ],
    "wof:name":"Lulac Health Svc",
    "wof:placetype":"venue"
},
  "geometry": {"coordinates":[-98.492709,29.551241],"type":"Point"}
}