{
  "type": "Feature",
  "properties": {
    "iso:country":"US",
    "sg:address":"6402 Lynn Ln",
    "sg:city":"Lago Vista",
    "sg:classifiers":[
        {
            "category":"Retail",
            "subcategory":"Repair Shop",
            "type":"Services"
        }
    ],
    "sg:phone":"+1 512 267 8989",
    "sg:postcode":"78645",
    "sg:province":"TX",
    "sg:tags":[
        "valve"
    ],
    "wof:name":"Rodlin Valve Specialists Inc",
    "wof:placetype":"venue"
},
  "geometry": {"coordinates":[-97.991016,30.461057],"type":"Point"}
}