{
  "type": "Feature",
  "properties": {
    "iso:country":"US",
    "sg:address":"1101 E Waylon Jennings Blvd",
    "sg:city":"Littlefield",
    "sg:classifiers":[
        {
            "category":"Freight",
            "type":"Transportation"
        }
    ],
    "sg:phone":"+1 806 385 5506",
    "sg:postcode":"79339",
    "sg:province":"TX",
    "sg:tags":[
        "frozen",
        "food",
        "locker",
        "plant"
    ],
    "wof:name":"Lamb County Locker",
    "wof:placetype":"venue"
},
  "geometry": {"coordinates":[-102.322844,33.917545],"type":"Point"}
}