{
  "type": "Feature",
  "properties": {
    "iso:country":"US",
    "sg:address":"8403 Crooked Path St",
    "sg:city":"San Antonio",
    "sg:classifiers":[
        {
            "category":"Retail",
            "subcategory":"Laundry & Dry Cleaning",
            "type":"Services"
        }
    ],
    "sg:phone":"+1 210 680 7124",
    "sg:postcode":"78254",
    "sg:province":"TX",
    "wof:name":"Monarch Carpet & Uphl Clg",
    "wof:placetype":"venue"
},
  "geometry": {"coordinates":[-98.65441800000001,29.519078],"type":"Point"}
}