{
  "type": "Feature",
  "properties": {
    "iso:country":"US",
    "sg:address":"170 N Leona Blvd",
    "sg:city":"Leona",
    "sg:classifiers":[
        {
            "category":"Shopping",
            "subcategory":"Hobbies, Toys, & Games",
            "type":"Retail Goods"
        },
        {
            "category":"Recreation",
            "subcategory":"Gun Range",
            "type":"Entertainment"
        }
    ],
    "sg:phone":"+1 903 344 4867",
    "sg:postcode":"75850",
    "sg:province":"TX",
    "sg:tags":[
        "safety",
        "instruction",
        "marksmanship",
        "gunsmith"
    ],
    "wof:name":"Bell Alley Gunsmithing",
    "wof:placetype":"venue"
},
  "geometry": {"coordinates":[-95.969264,31.155927],"type":"Point"}
}