{
  "type": "Feature",
  "properties": {
    "iso:country":"US",
    "sg:address":"504 Murphy Rd",
    "sg:city":"Stafford",
    "sg:classifiers":[
        {
            "category":"Organizations",
            "subcategory":"Professional Association",
            "type":"Services"
        }
    ],
    "sg:phone":"+1 281 261 7984",
    "sg:postcode":"77477",
    "sg:province":"TX",
    "wof:name":"Living Water Intl",
    "wof:placetype":"venue"
},
  "geometry": {"coordinates":[-95.564567,29.61251],"type":"Point"}
}