{
  "type": "Feature",
  "properties": {
    "iso:country":"US",
    "sg:address":"1386 Fm 1960 Bypass Rd E",
    "sg:city":"Humble",
    "sg:classifiers":[
        {
            "category":"Autos & Motor Vehicles",
            "subcategory":"Automobile Sales",
            "type":"Retail Goods"
        }
    ],
    "sg:phone":"+1 281 446 5656",
    "sg:postcode":"77338",
    "sg:province":"TX",
    "sg:tags":[
        "dealers-used",
        "used",
        "cars-wholesale",
        "car"
    ],
    "sg:website":"http://www.mcferrinmotors.com",
    "wof:name":"Mc Ferrin Motors",
    "wof:placetype":"venue"
},
  "geometry": {"coordinates":[-95.25370599999999,30.004468],"type":"Point"}
}