{
  "type": "Feature",
  "properties": {
    "iso:country":"US",
    "sg:address":"8010 Kings Ct",
    "sg:city":"Rowlett",
    "sg:classifiers":[
        {
            "category":"Building & Trades",
            "subcategory":"Construction",
            "type":"Services"
        }
    ],
    "sg:phone":"+1 972 463 6606",
    "sg:postcode":"75089",
    "sg:province":"TX",
    "sg:tags":[
        "home",
        "builder"
    ],
    "wof:name":"Leanar Homes",
    "wof:placetype":"venue"
},
  "geometry": {"coordinates":[-96.53203499999999,32.938316],"type":"Point"}
}