{
  "type": "Feature",
  "properties": {
    "iso:country":"US",
    "sg:address":"2810 Kyle Dr",
    "sg:city":"Temple",
    "sg:classifiers":[
        {
            "category":"Health Services",
            "subcategory":"Doctor",
            "type":"Services"
        }
    ],
    "sg:phone":"+1 254 771 1717",
    "sg:postcode":"76502",
    "sg:province":"TX",
    "sg:tags":[
        "physician",
        "family",
        "practice",
        "surgeons",
        "medicine"
    ],
    "wof:name":"Robinson Jc Md",
    "wof:placetype":"venue"
},
  "geometry": {"coordinates":[-97.385732,31.063964],"type":"Point"}
}