{
  "type": "Feature",
  "properties": {
    "iso:country":"US",
    "sg:address":"2214 Royal Oaks Dr",
    "sg:city":"Irving",
    "sg:classifiers":[
        {
            "category":"Organizations",
            "subcategory":"Religious Organization",
            "type":"Services"
        }
    ],
    "sg:phone":"+1 972 986 8769",
    "sg:postcode":"75060",
    "sg:province":"TX",
    "wof:name":"Trinity Fairs",
    "wof:placetype":"venue"
},
  "geometry": {"coordinates":[-96.975342,32.803937],"type":"Point"}
}