{
  "type": "Feature",
  "properties": {
    "iso:country":"US",
    "sg:address":"11200 Georgian Dr Ste D",
    "sg:city":"Austin",
    "sg:classifiers":[
        {
            "category":"Autos & Motor Vehicles",
            "subcategory":"Auto Supplies",
            "type":"Retail Goods"
        }
    ],
    "sg:phone":"+1 512 687 0090",
    "sg:postcode":"78753",
    "sg:province":"TX",
    "sg:tags":[
        "glass"
    ],
    "sg:website":"www.bbplateglass.net",
    "wof:name":"B & B Plate Glass",
    "wof:placetype":"venue"
},
  "geometry": {"coordinates":[-97.682113,30.378044],"type":"Point"}
}