{
  "type": "Feature",
  "properties": {
    "iso:country":"US",
    "sg:address":"275 Cedar Sage Dr",
    "sg:city":"Garland",
    "sg:classifiers":[
        {
            "category":"Shopping",
            "subcategory":"Clothing, Apparel, & Fashions",
            "type":"Retail Goods"
        }
    ],
    "sg:phone":"+1 972 496 0400",
    "sg:postcode":"75040",
    "sg:province":"TX",
    "sg:tags":[
        "accessory",
        "clothing",
        "women's"
    ],
    "wof:name":"Chico's FAS Inc",
    "wof:placetype":"venue"
},
  "geometry": {"coordinates":[-96.61216899999999,32.953659],"type":"Point"}
}