{
  "type": "Feature",
  "properties": {
    "iso:country":"US",
    "sg:address":"12431 Taylorwood Ln",
    "sg:city":"Houston",
    "sg:classifiers":[
        {
            "category":"Professional",
            "subcategory":"Computer Services",
            "type":"Services"
        }
    ],
    "sg:phone":"+1 281 517 0972",
    "sg:postcode":"77070",
    "sg:province":"TX",
    "sg:tags":[
        "internet"
    ],
    "wof:name":"B D Logic",
    "wof:placetype":"venue"
},
  "geometry": {"coordinates":[-95.562917,29.954395],"type":"Point"}
}