{
  "type": "Feature",
  "properties": {
    "iso:country":"US",
    "sg:address":"8626 Dyer St",
    "sg:city":"El Paso",
    "sg:classifiers":[
        {
            "category":"Wholesale",
            "subcategory":"Durable Goods & Equipment",
            "type":"Manufacturing & Wholesale Goods"
        }
    ],
    "sg:phone":"+1 915 751 2456",
    "sg:postcode":"79904",
    "sg:province":"TX",
    "sg:tags":[
        "importer"
    ],
    "wof:name":"Primitive Origins",
    "wof:placetype":"venue"
},
  "geometry": {"coordinates":[-106.43480700000001,31.859398],"type":"Point"}
}