{
  "type": "Feature",
  "properties": {
    "iso:country":"US",
    "sg:address":"212 Conroe Dr",
    "sg:city":"Conroe",
    "sg:classifiers":[
        {
            "category":"Professional",
            "type":"Services"
        }
    ],
    "sg:phone":"+1 936 756 7052",
    "sg:postcode":"77301",
    "sg:province":"TX",
    "sg:tags":[
        "salon",
        "beauty"
    ],
    "wof:name":"Headhunters By Trulah",
    "wof:placetype":"venue"
},
  "geometry": {"coordinates":[-95.45881799999999,30.322375],"type":"Point"}
}