{
  "type": "Feature",
  "properties": {
    "iso:country":"US",
    "sg:address":"3122 S Clack St",
    "sg:city":"Abilene",
    "sg:classifiers":[
        {
            "category":"Organizations",
            "subcategory":"Religious Organization",
            "type":"Services"
        }
    ],
    "sg:phone":"+1 325 795 2222",
    "sg:postcode":"79606",
    "sg:province":"TX",
    "wof:name":"New Hope Church",
    "wof:placetype":"venue"
},
  "geometry": {"coordinates":[-99.77414,32.411614],"type":"Point"}
}