{
  "type": "Feature",
  "properties": {
    "iso:country":"US",
    "sg:address":"5 Wentworth Ct",
    "sg:city":"Roanoke",
    "sg:classifiers":[
        {
            "category":"Manufacturing",
            "subcategory":"Food",
            "type":"Manufacturing & Wholesale Goods"
        }
    ],
    "sg:phone":"+1 817 430 1050",
    "sg:postcode":"76262",
    "sg:province":"TX",
    "sg:tags":[
        "mfg"
    ],
    "wof:name":"Runnin M Ranch Specialty Foods",
    "wof:placetype":"venue"
},
  "geometry": {"coordinates":[-97.19725200000001,32.996941],"type":"Point"}
}