{
  "type": "Feature",
  "properties": {
    "iso:country":"US",
    "sg:address":"1722 Co Rd 770",
    "sg:city":"Natalia",
    "sg:classifiers":[
        {
            "category":"Professional",
            "subcategory":"Business Services",
            "type":"Services"
        }
    ],
    "sg:phone":"+1 830 665 2262",
    "sg:postcode":"78059",
    "sg:province":"TX",
    "wof:name":"Covarrubia Enterprises Inc",
    "wof:placetype":"venue"
},
  "geometry": {"coordinates":[-98.83833300000001,29.147999],"type":"Point"}
}