{
  "type": "Feature",
  "properties": {
    "iso:country":"US",
    "sg:address":"4500 Roland Ave",
    "sg:city":"Dallas",
    "sg:classifiers":[
        {
            "category":"Parking",
            "type":"Transportation"
        }
    ],
    "sg:phone":"+1 214 521 7070",
    "sg:postcode":"75219",
    "sg:province":"TX",
    "sg:tags":[
        "automobile"
    ],
    "wof:name":"Griffin Street Autopark",
    "wof:placetype":"venue"
},
  "geometry": {"coordinates":[-96.81386500000001,32.821987],"type":"Point"}
}