{
  "type": "Feature",
  "properties": {
    "iso:country":"US",
    "sg:address":"5628 Webster Ave",
    "sg:city":"El Paso",
    "sg:classifiers":[
        {
            "category":"Recreation",
            "type":"Entertainment"
        }
    ],
    "sg:phone":"+1 915 541 4331",
    "sg:postcode":"79905",
    "sg:province":"TX",
    "sg:tags":[
        "parks"
    ],
    "wof:name":"San Juan Park",
    "wof:placetype":"venue"
},
  "geometry": {"coordinates":[-106.421134,31.776898],"type":"Point"}
}