{
  "type": "Feature",
  "properties": {
    "iso:country":"US",
    "sg:address":"1210 Challenger",
    "sg:city":"Lakeway",
    "sg:classifiers":[
        {
            "category":"Health Services",
            "subcategory":"Doctor",
            "type":"Services"
        }
    ],
    "sg:phone":"+1 512 261 5987",
    "sg:postcode":"78734",
    "sg:province":"TX",
    "sg:tags":[
        "physician",
        "surgeon"
    ],
    "wof:name":"Dr Melvin Lescale",
    "wof:placetype":"venue"
},
  "geometry": {"coordinates":[-97.97849600000001,30.380632],"type":"Point"}
}