{
  "type": "Feature",
  "properties": {
    "iso:country":"US",
    "sg:address":"900 N Walnut Creek Dr",
    "sg:city":"Mansfield",
    "sg:classifiers":[
        {
            "category":"Shopping",
            "subcategory":"Computers & Home Electronics",
            "type":"Retail Goods"
        }
    ],
    "sg:phone":"+1 817 473 7948",
    "sg:postcode":"76063",
    "sg:province":"TX",
    "sg:tags":[
        "equipment",
        "electronic",
        "supply"
    ],
    "wof:name":"Radio Shack",
    "wof:placetype":"venue"
},
  "geometry": {"coordinates":[-97.132452,32.578343],"type":"Point"}
}