{
  "type": "Feature",
  "properties": {
    "iso:country":"US",
    "sg:address":"2015 Wagon Gap Trl",
    "sg:city":"Houston",
    "sg:classifiers":[
        {
            "category":"Retail",
            "subcategory":"Repair Shop",
            "type":"Services"
        }
    ],
    "sg:phone":"+1 281 444 9163",
    "sg:postcode":"77090",
    "sg:province":"TX",
    "sg:tags":[
        "related"
    ],
    "wof:name":"Kleyco Enterprises",
    "wof:placetype":"venue"
},
  "geometry": {"coordinates":[-95.46638400000001,30.018263],"type":"Point"}
}