{
  "type": "Feature",
  "properties": {
    "iso:country":"US",
    "sg:address":"412 E Washington Ave",
    "sg:city":"Navasota",
    "sg:classifiers":[
        {
            "category":"Professional",
            "subcategory":"Lawyer & Legal Services",
            "type":"Services"
        }
    ],
    "sg:phone":"+1 936 825 8705",
    "sg:postcode":"77868",
    "sg:province":"TX",
    "sg:tags":[
        "attorney",
        "practice",
        "plan"
    ],
    "wof:name":"Law Office Of Patricia Williams Prewitt",
    "wof:placetype":"venue"
},
  "geometry": {"coordinates":[-96.201267,30.46465],"type":"Point"}
}