{
  "type": "Feature",
  "properties": {
    "iso:country":"US",
    "sg:address":"1060 W Frankford Rd",
    "sg:city":"Carrollton",
    "sg:classifiers":[
        {
            "category":"Banks & Credit Unions",
            "subcategory":"Bank",
            "type":"Services"
        }
    ],
    "sg:phone":"+1 972 394 3700",
    "sg:postcode":"75007",
    "sg:province":"TX",
    "wof:name":"Bower John Insurance",
    "wof:placetype":"venue"
},
  "geometry": {"coordinates":[-96.91149900000001,32.998501],"type":"Point"}
}