{
  "type": "Feature",
  "properties": {
    "iso:country":"US",
    "sg:address":"231 Corpus Dr",
    "sg:city":"Magnolia",
    "sg:classifiers":[
        {
            "category":"Professional",
            "subcategory":"Computer Services",
            "type":"Services"
        }
    ],
    "sg:phone":"+1 281 252 0880",
    "sg:postcode":"77354",
    "sg:province":"TX",
    "sg:tags":[
        "datum"
    ],
    "wof:name":"Sommys Inc",
    "wof:placetype":"venue"
},
  "geometry": {"coordinates":[-95.754211,30.214783],"type":"Point"}
}