{
  "type": "Feature",
  "properties": {
    "iso:country":"US",
    "sg:address":"431 Perch Rd",
    "sg:city":"Rockwall",
    "sg:classifiers":[
        {
            "category":"Retail",
            "subcategory":"Auto Repair",
            "type":"Services"
        }
    ],
    "sg:phone":"+1 972 722 8111",
    "sg:postcode":"75032",
    "sg:province":"TX",
    "sg:tags":[
        "alternator",
        "generator"
    ],
    "wof:name":"Mclean's Alternator & Starter",
    "wof:placetype":"venue"
},
  "geometry": {"coordinates":[-96.45944,32.885196],"type":"Point"}
}