{
  "type": "Feature",
  "properties": {
    "iso:country":"US",
    "sg:address":"810 W King Ave",
    "sg:city":"Kingsville",
    "sg:classifiers":[
        {
            "category":"Shopping",
            "subcategory":"Clothing, Apparel, & Fashions",
            "type":"Retail Goods"
        }
    ],
    "sg:phone":"+1 361 592 4600",
    "sg:postcode":"78363",
    "sg:province":"TX",
    "sg:tags":[
        "wear"
    ],
    "wof:name":"Cadillac Cowgirls",
    "wof:placetype":"venue"
},
  "geometry": {"coordinates":[-97.87902699999999,27.515515],"type":"Point"}
}