{
  "type": "Feature",
  "properties": {
    "iso:country":"US",
    "sg:address":"7609 Campbell Rd",
    "sg:city":"Dallas",
    "sg:classifiers":[
        {
            "category":"Shopping",
            "subcategory":"Department Store",
            "type":"Retail Goods"
        }
    ],
    "sg:phone":"+1 972 248 8494",
    "sg:postcode":"75248",
    "sg:province":"TX",
    "sg:tags":[
        "discount"
    ],
    "wof:name":"Marshalls",
    "wof:placetype":"venue"
},
  "geometry": {"coordinates":[-96.770061,32.978278],"type":"Point"}
}