{
  "type": "Feature",
  "properties": {
    "iso:country":"US",
    "sg:address":"11061 Shady Trl",
    "sg:city":"Dallas",
    "sg:classifiers":[
        {
            "category":"Communications",
            "subcategory":"Radio Station",
            "type":"Services"
        }
    ],
    "sg:phone":"+1 214 351 6655",
    "sg:postcode":"75229",
    "sg:province":"TX",
    "wof:name":"Kvtt Fm Stereo 91.7",
    "wof:placetype":"venue"
},
  "geometry": {"coordinates":[-96.890602,32.883099],"type":"Point"}
}