{
  "type": "Feature",
  "properties": {
    "iso:country":"US",
    "sg:address":"256 W Court St",
    "sg:city":"Seguin",
    "sg:classifiers":[
        {
            "category":"Sports & Exercise",
            "subcategory":"Gym",
            "type":"Entertainment"
        }
    ],
    "sg:phone":"+1 830 372 3396",
    "sg:postcode":"78155",
    "sg:province":"TX",
    "sg:tags":[
        "physical",
        "fitness"
    ],
    "wof:name":"Seguin Fitness",
    "wof:placetype":"venue"
},
  "geometry": {"coordinates":[-97.96672100000001,29.568951],"type":"Point"}
}