{
  "type": "Feature",
  "properties": {
    "iso:country":"US",
    "sg:address":"9330 Westpark Dr",
    "sg:city":"Houston",
    "sg:classifiers":[
        {
            "category":"Real Estate",
            "subcategory":"Real Estate Services",
            "type":"Services"
        }
    ],
    "sg:phone":"+1 713 278 0818",
    "sg:postcode":"77063",
    "sg:province":"TX",
    "sg:tags":[
        "company",
        "title"
    ],
    "wof:name":"Eldorado Multi Svc",
    "wof:placetype":"venue"
},
  "geometry": {"coordinates":[-95.525701,29.721075],"type":"Point"}
}