{
  "type": "Feature",
  "properties": {
    "iso:country":"US",
    "sg:address":"1406 Madison St",
    "sg:city":"Weatherford",
    "sg:classifiers":[
        {
            "category":"Manufacturing",
            "subcategory":"Chemicals & Compounds",
            "type":"Manufacturing & Wholesale Goods"
        }
    ],
    "sg:phone":"+1 817 596 8869",
    "sg:postcode":"76086",
    "sg:province":"TX",
    "sg:tags":[
        "plate",
        "work",
        "fabricated",
        "mfg"
    ],
    "wof:name":"Boc Group Inc A Delaware Corp",
    "wof:placetype":"venue"
},
  "geometry": {"coordinates":[-97.793452,32.77615],"type":"Point"}
}