{
  "type": "Feature",
  "properties": {
    "iso:country":"US",
    "sg:address":"10440 Corporate Dr",
    "sg:city":"Sugar Land",
    "sg:classifiers":[
        {
            "category":"Manufacturing",
            "subcategory":"Metals",
            "type":"Manufacturing & Wholesale Goods"
        }
    ],
    "sg:phone":"+1 281 240 0955",
    "sg:postcode":"77478",
    "sg:province":"TX",
    "sg:tags":[
        "valve"
    ],
    "sg:website":"www.processresources.com",
    "wof:name":"Process Resources Inc",
    "wof:placetype":"venue"
},
  "geometry": {"coordinates":[-95.60001099999999,29.63294],"type":"Point"}
}