{
  "type": "Feature",
  "properties": {
    "iso:country":"US",
    "sg:address":"2303 Clark St",
    "sg:city":"Dallas",
    "sg:classifiers":[
        {
            "category":"Farming",
            "subcategory":"Farm",
            "type":"Manufacturing & Wholesale Goods"
        }
    ],
    "sg:phone":"+1 469 766 3868",
    "sg:postcode":"75204",
    "sg:province":"TX",
    "wof:name":"Squaw Mountain Ranch Outfitters",
    "wof:placetype":"venue"
},
  "geometry": {"coordinates":[-96.79619700000001,32.797336],"type":"Point"}
}