{
  "type": "Feature",
  "properties": {
    "iso:country":"US",
    "sg:address":"308 US Hwy 82",
    "sg:city":"New Boston",
    "sg:classifiers":[
        {
            "category":"Professional",
            "type":"Services"
        }
    ],
    "sg:phone":"+1 903 628 9840",
    "sg:postcode":"75571",
    "sg:province":"TX",
    "sg:tags":[
        "establishment"
    ],
    "wof:name":"Conner & Williams",
    "wof:placetype":"venue"
},
  "geometry": {"coordinates":[-94.426035,33.461565],"type":"Point"}
}