{
  "type": "Feature",
  "properties": {
    "iso:country":"US",
    "sg:address":"506 Roble Fino",
    "sg:city":"San Antonio",
    "sg:classifiers":[
        {
            "category":"Real Estate",
            "subcategory":"Real Estate Operator",
            "type":"Services"
        }
    ],
    "sg:phone":"+1 210 497 6884",
    "sg:postcode":"78258",
    "sg:province":"TX",
    "sg:tags":[
        "building",
        "nonresidential"
    ],
    "wof:name":"Wmm Property Inc",
    "wof:placetype":"venue"
},
  "geometry": {"coordinates":[-98.50361100000001,29.629444],"type":"Point"}
}