{
  "type": "Feature",
  "properties": {
    "iso:country":"US",
    "sg:address":"1207 Dowdy Ferry Rd",
    "sg:city":"Dallas",
    "sg:classifiers":[
        {
            "category":"Building & Trades",
            "subcategory":"Construction",
            "type":"Services"
        }
    ],
    "sg:phone":"+1 214 398 7549",
    "sg:postcode":"75217",
    "sg:province":"TX",
    "sg:tags":[
        "house"
    ],
    "wof:name":"E Pugo Construction",
    "wof:placetype":"venue"
},
  "geometry": {"coordinates":[-96.67852000000001,32.698124],"type":"Point"}
}