{
  "type": "Feature",
  "properties": {
    "iso:country":"US",
    "sg:address":"8103 Landsman Dr",
    "sg:city":"Austin",
    "sg:classifiers":[
        {
            "category":"Organizations",
            "subcategory":"Religious Organization",
            "type":"Services"
        }
    ],
    "sg:phone":"+1 512 301 3774",
    "sg:postcode":"78736",
    "sg:province":"TX",
    "wof:name":"Austin Ctr For Rlgious Science",
    "wof:placetype":"venue"
},
  "geometry": {"coordinates":[-97.892445,30.233468],"type":"Point"}
}