{
  "type": "Feature",
  "properties": {
    "iso:country":"US",
    "sg:address":"3131 Fallbrook Dr",
    "sg:city":"Houston",
    "sg:classifiers":[
        {
            "category":"Education",
            "subcategory":"School",
            "type":"Public Place"
        }
    ],
    "sg:phone":"+1 281 878 0990",
    "sg:postcode":"77038",
    "sg:province":"TX",
    "wof:name":"Wilson Intermediate School",
    "wof:placetype":"venue"
},
  "geometry": {"coordinates":[-95.469375,29.919385],"type":"Point"}
}