{
  "type": "Feature",
  "properties": {
    "iso:country":"US",
    "sg:address":"335 E San Augustine St",
    "sg:city":"Deer Park",
    "sg:classifiers":[
        {
            "category":"Professional",
            "subcategory":"Computer Services",
            "type":"Services"
        }
    ],
    "sg:phone":"+1 281 476 9761",
    "sg:postcode":"77536",
    "sg:province":"TX",
    "sg:tags":[
        "related"
    ],
    "wof:name":"Lanman Consulting",
    "wof:placetype":"venue"
},
  "geometry": {"coordinates":[-95.12236,29.689626],"type":"Point"}
}