{
  "type": "Feature",
  "properties": {
    "iso:country":"US",
    "sg:address":"119 Meeker Rd",
    "sg:city":"Kerrville",
    "sg:classifiers":[
        {
            "category":"Building & Trades",
            "subcategory":"Plumbing",
            "type":"Services"
        }
    ],
    "sg:phone":"+1 830 792 5600",
    "sg:postcode":"78028",
    "sg:province":"TX",
    "sg:tags":[
        "conditioning",
        "air",
        "system",
        "contractor"
    ],
    "wof:name":"Adair's Heating & Cooling",
    "wof:placetype":"venue"
},
  "geometry": {"coordinates":[-99.12258799999999,30.021705],"type":"Point"}
}