{
  "type": "Feature",
  "properties": {
    "iso:country":"US",
    "sg:address":"1404 Ridgeview Dr",
    "sg:city":"Tyler",
    "sg:classifiers":[
        {
            "category":"Building & Trades",
            "subcategory":"Plumbing",
            "type":"Services"
        }
    ],
    "sg:phone":"+1 903 597 5265",
    "sg:postcode":"75701",
    "sg:province":"TX",
    "sg:tags":[
        "system",
        "contractor",
        "air conditioning"
    ],
    "wof:name":"Sherry Bryant Business Ac",
    "wof:placetype":"venue"
},
  "geometry": {"coordinates":[-95.275932,32.333813],"type":"Point"}
}