{
  "type": "Feature",
  "properties": {
    "iso:country":"US",
    "sg:address":"124 W Bivar Ave",
    "sg:city":"De Leon",
    "sg:classifiers":[
        {
            "category":"Wholesale",
            "subcategory":"Chemicals & Plastics",
            "type":"Manufacturing & Wholesale Goods"
        }
    ],
    "sg:phone":"+1 254 893 2054",
    "sg:postcode":"76444",
    "sg:province":"TX",
    "wof:name":"Helena Chemical Co",
    "wof:placetype":"venue"
},
  "geometry": {"coordinates":[-98.537166,32.112375],"type":"Point"}
}