{
  "type": "Feature",
  "properties": {
    "iso:country":"US",
    "sg:address":"10535 Hammerly Blvd",
    "sg:city":"Houston",
    "sg:classifiers":[
        {
            "category":"Organizations",
            "subcategory":"Religious Organization",
            "type":"Services"
        }
    ],
    "sg:phone":"+1 713 465 4232",
    "sg:postcode":"77043",
    "sg:province":"TX",
    "wof:name":"Emanuel Mision Apostolica",
    "wof:placetype":"venue"
},
  "geometry": {"coordinates":[-95.556201,29.812601],"type":"Point"}
}