{
  "type": "Feature",
  "properties": {
    "iso:country":"US",
    "sg:address":"2306 80th St",
    "sg:city":"Lubbock",
    "sg:classifiers":[
        {
            "category":"Building & Trades",
            "subcategory":"Plumbing",
            "type":"Services"
        }
    ],
    "sg:phone":"+1 806 745 9303",
    "sg:postcode":"79423",
    "sg:province":"TX",
    "sg:tags":[
        "plumber",
        "industrial",
        "contractors-commercial"
    ],
    "wof:name":"Doidge Plumbing Repair",
    "wof:placetype":"venue"
},
  "geometry": {"coordinates":[-101.867171,33.52177],"type":"Point"}
}