{
  "type": "Feature",
  "properties": {
    "iso:country":"US",
    "sg:address":"839 Rutland St",
    "sg:city":"Houston",
    "sg:classifiers":[
        {
            "category":"Social Services",
            "subcategory":"Child Care",
            "type":"Services"
        }
    ],
    "sg:phone":"+1 713 426 0620",
    "sg:postcode":"77007",
    "sg:province":"TX",
    "sg:tags":[
        "day"
    ],
    "wof:name":"Gonzales Day Care",
    "wof:placetype":"venue"
},
  "geometry": {"coordinates":[-95.401174,29.786239],"type":"Point"}
}