{
  "type": "Feature",
  "properties": {
    "iso:country":"US",
    "sg:address":"346 Ashland Dr",
    "sg:city":"San Antonio",
    "sg:classifiers":[
        {
            "category":"Professional",
            "type":"Services"
        }
    ],
    "sg:phone":"+1 210 590 8690",
    "sg:postcode":"78218",
    "sg:province":"TX",
    "wof:name":"Emanuel Segundo",
    "wof:placetype":"venue"
},
  "geometry": {"coordinates":[-98.40419900000001,29.504967],"type":"Point"}
}