{
  "type": "Feature",
  "properties": {
    "iso:country":"US",
    "sg:address":"3737 Timberglen Rd",
    "sg:city":"Dallas",
    "sg:classifiers":[
        {
            "category":"Wholesale",
            "subcategory":"Machinery & Supplies",
            "type":"Manufacturing & Wholesale Goods"
        }
    ],
    "sg:phone":"+1 972 820 8710",
    "sg:postcode":"75287",
    "sg:province":"TX",
    "sg:tags":[
        "product",
        "cleaning"
    ],
    "wof:name":"Natures Enterprise",
    "wof:placetype":"venue"
},
  "geometry": {"coordinates":[-96.850151,33.004961],"type":"Point"}
}