{
  "type": "Feature",
  "properties": {
    "iso:country":"US",
    "sg:address":"4813 Royal Oak St",
    "sg:city":"Wichita Falls",
    "sg:classifiers":[
        {
            "category":"Manufacturing",
            "subcategory":"Retail Goods",
            "type":"Manufacturing & Wholesale Goods"
        }
    ],
    "sg:phone":"+1 940 691 7435",
    "sg:postcode":"76308",
    "sg:province":"TX",
    "sg:tags":[
        "product",
        "mfg"
    ],
    "wof:name":"Royal Technology",
    "wof:placetype":"venue"
},
  "geometry": {"coordinates":[-98.535099,33.853234],"type":"Point"}
}