{
  "type": "Feature",
  "properties": {
    "iso:country":"US",
    "sg:address":"5920 Dashwood Dr",
    "sg:city":"Houston",
    "sg:classifiers":[
        {
            "category":"Wholesale",
            "subcategory":"Vending Machines",
            "type":"Manufacturing & Wholesale Goods"
        }
    ],
    "sg:phone":"+1 713 592 5001",
    "sg:postcode":"77081",
    "sg:province":"TX",
    "sg:tags":[
        "water",
        "maintains"
    ],
    "wof:name":"Aqua Blue Investments Corps",
    "wof:placetype":"venue"
},
  "geometry": {"coordinates":[-95.484911,29.707423],"type":"Point"}
}