{
  "type": "Feature",
  "properties": {
    "iso:country":"US",
    "sg:address":"8209 Rough Rider Dr",
    "sg:city":"San Antonio",
    "sg:classifiers":[
        {
            "category":"Building & Trades",
            "subcategory":"Construction",
            "type":"Services"
        }
    ],
    "sg:phone":"+1 210 657 1922",
    "sg:postcode":"78239",
    "sg:province":"TX",
    "sg:tags":[
        "fire",
        "restoration",
        "damage"
    ],
    "wof:name":"Carey Construction & Rstrtns",
    "wof:placetype":"venue"
},
  "geometry": {"coordinates":[-98.388026,29.511576],"type":"Point"}
}