{
  "type": "Feature",
  "properties": {
    "iso:country":"US",
    "sg:address":"3440 Baylor Camp Rd",
    "sg:city":"Crawford",
    "sg:classifiers":[
        {
            "category":"Local Transit",
            "type":"Transportation"
        }
    ],
    "sg:phone":"+1 254 757 4864",
    "sg:postcode":"76638",
    "sg:province":"TX",
    "sg:tags":[
        "passenger"
    ],
    "wof:name":"Emerald Coaches Inc",
    "wof:placetype":"venue"
},
  "geometry": {"coordinates":[-97.31632500000001,31.607211],"type":"Point"}
}