{
  "type": "Feature",
  "properties": {
    "iso:country":"US",
    "sg:address":"1182 Wake Forest Dr",
    "sg:city":"Lewisville",
    "sg:classifiers":[
        {
            "category":"Building & Trades",
            "subcategory":"Landscaping Services",
            "type":"Services"
        }
    ],
    "sg:phone":"+1 972 436 7701",
    "sg:postcode":"75077",
    "sg:province":"TX",
    "sg:tags":[
        "landscape"
    ],
    "wof:name":"Butler Brian J Horticultu",
    "wof:placetype":"venue"
},
  "geometry": {"coordinates":[-97.028165,33.060962],"type":"Point"}
}