{
  "type": "Feature",
  "properties": {
    "iso:country":"US",
    "sg:address":"123 Whitewood St",
    "sg:city":"San Antonio",
    "sg:classifiers":[
        {
            "category":"Wholesale",
            "subcategory":"Electrical",
            "type":"Manufacturing & Wholesale Goods"
        }
    ],
    "sg:phone":"+1 210 673 6299",
    "sg:postcode":"78242",
    "sg:province":"TX",
    "sg:tags":[
        "communication",
        "radio",
        "system"
    ],
    "wof:name":"Communications Etc",
    "wof:placetype":"venue"
},
  "geometry": {"coordinates":[-98.60056899999999,29.367976],"type":"Point"}
}