{
  "type": "Feature",
  "properties": {
    "iso:country":"US",
    "sg:address":"7711 Oconnor Dr",
    "sg:city":"Round Rock",
    "sg:classifiers":[
        {
            "category":"Banks & Credit Unions",
            "subcategory":"Investment Brokerage",
            "type":"Services"
        }
    ],
    "sg:phone":"+1 512 244 7682",
    "sg:postcode":"78681",
    "sg:province":"TX",
    "sg:tags":[
        "investing"
    ],
    "wof:name":"Western Rim Investors",
    "wof:placetype":"venue"
},
  "geometry": {"coordinates":[-97.724526,30.500401],"type":"Point"}
}