{
  "type": "Feature",
  "properties": {
    "iso:country":"US",
    "sg:address":"581 W Campbell Rd",
    "sg:city":"Richardson",
    "sg:classifiers":[
        {
            "category":"Shopping",
            "subcategory":"Books",
            "type":"Retail Goods"
        }
    ],
    "sg:phone":"+1 972 907 8398",
    "sg:postcode":"75080",
    "sg:province":"TX",
    "sg:tags":[
        "college",
        "dealer"
    ],
    "wof:name":"Off Campus Books",
    "wof:placetype":"venue"
},
  "geometry": {"coordinates":[-96.737459,32.976726],"type":"Point"}
}