{
  "type": "Feature",
  "properties": {
    "iso:country":"US",
    "sg:address":"305 S el Paso St",
    "sg:city":"El Paso",
    "sg:classifiers":[
        {
            "category":"Shopping",
            "subcategory":"Clothing, Apparel, & Fashions",
            "type":"Retail Goods"
        }
    ],
    "sg:phone":"+1 915 533 6250",
    "sg:postcode":"79901",
    "sg:province":"TX",
    "sg:tags":[
        "sporting",
        "wear",
        "western",
        "accessory"
    ],
    "wof:name":"Continental Dry Goods",
    "wof:placetype":"venue"
},
  "geometry": {"coordinates":[-106.48817699999999,31.755181],"type":"Point"}
}