{
  "type": "Feature",
  "properties": {
    "iso:country":"US",
    "sg:address":"146 Wellington Ln",
    "sg:city":"Wichita Falls",
    "sg:classifiers":[
        {
            "category":"Autos & Motor Vehicles",
            "subcategory":"Automobile Sales",
            "type":"Retail Goods"
        }
    ],
    "sg:phone":"+1 940 851 4260",
    "sg:postcode":"76305",
    "sg:province":"TX",
    "wof:name":"North Texas Electric Carts",
    "wof:placetype":"venue"
},
  "geometry": {"coordinates":[-98.575428,33.916563],"type":"Point"}
}