{
  "type": "Feature",
  "properties": {
    "iso:country":"US",
    "sg:address":"640 Johnson Dr",
    "sg:city":"Coppell",
    "sg:classifiers":[
        {
            "category":"Shopping",
            "type":"Retail Goods"
        }
    ],
    "sg:phone":"+1 972 745 7823",
    "sg:postcode":"75019",
    "sg:province":"TX",
    "sg:tags":[
        "merchandise"
    ],
    "wof:name":"Connie Birdine Inc",
    "wof:placetype":"venue"
},
  "geometry": {"coordinates":[-96.973545,32.980431],"type":"Point"}
}