{
  "type": "Feature",
  "properties": {
    "iso:country":"US",
    "sg:address":"1715 Downhill Dr",
    "sg:city":"Wichita Falls",
    "sg:classifiers":[
        {
            "category":"Shopping",
            "type":"Retail Goods"
        }
    ],
    "sg:phone":"+1 940 766 4051",
    "sg:postcode":"76302",
    "sg:province":"TX",
    "sg:tags":[
        "merchandise"
    ],
    "wof:name":"Okie Girls Shopping Mania",
    "wof:placetype":"venue"
},
  "geometry": {"coordinates":[-98.508877,33.854069],"type":"Point"}
}