{
  "type": "Feature",
  "properties": {
    "iso:country":"US",
    "sg:address":"14 Fiddleleaf Ct",
    "sg:city":"Spring",
    "sg:classifiers":[
        {
            "category":"Restaurant",
            "type":"Food & Drink"
        },
        {
            "category":"Ice Cream",
            "type":"Food & Drink"
        }
    ],
    "sg:phone":"+1 281 367 1850",
    "sg:postcode":"77381",
    "sg:province":"TX",
    "sg:tags":[
        "frozen",
        "dessert"
    ],
    "wof:name":"Sunset Farms Shaved Ice",
    "wof:placetype":"venue"
},
  "geometry": {"coordinates":[-95.499916,30.154739],"type":"Point"}
}