{
  "type": "Feature",
  "properties": {
    "iso:country":"US",
    "sg:address":"314 Partridge Run Dr",
    "sg:city":"Duncanville",
    "sg:classifiers":[
        {
            "category":"Professional",
            "subcategory":"Accounting & Tax Preparation",
            "type":"Services"
        }
    ],
    "sg:phone":"+1 972 283 7974",
    "sg:postcode":"75137",
    "sg:province":"TX",
    "sg:tags":[
        "bookkeeping"
    ],
    "wof:name":"JW Enterprises",
    "wof:placetype":"venue"
},
  "geometry": {"coordinates":[-96.916228,32.638554],"type":"Point"}
}