{
  "type": "Feature",
  "properties": {
    "iso:country":"US",
    "sg:address":"5330 Southhampton Dr",
    "sg:city":"San Antonio",
    "sg:classifiers":[
        {
            "category":"Utilities",
            "subcategory":"Telephone",
            "type":"Services"
        }
    ],
    "sg:phone":"+1 210 436 5221",
    "sg:postcode":"78228",
    "sg:province":"TX",
    "sg:tags":[
        "communications"
    ],
    "wof:name":"Corona Communications",
    "wof:placetype":"venue"
},
  "geometry": {"coordinates":[-98.592185,29.463158],"type":"Point"}
}