{
  "type": "Feature",
  "properties": {
    "iso:country":"US",
    "sg:address":"2637 Valley Creek Trl",
    "sg:city":"Mc Kinney",
    "sg:classifiers":[
        {
            "category":"Building & Trades",
            "subcategory":"Plumbing",
            "type":"Services"
        }
    ],
    "sg:phone":"+1 972 562 5937",
    "sg:postcode":"75070",
    "sg:province":"TX",
    "sg:tags":[
        "contractor"
    ],
    "wof:name":"Vcs Inc",
    "wof:placetype":"venue"
},
  "geometry": {"coordinates":[-96.65485700000001,33.177017],"type":"Point"}
}