{
  "type": "Feature",
  "properties": {
    "iso:country":"US",
    "sg:address":"8201 Lockheed Dr",
    "sg:city":"El Paso",
    "sg:classifiers":[
        {
            "category":"Freight",
            "type":"Transportation"
        }
    ],
    "sg:phone":"+1 915 779 3913",
    "sg:postcode":"79925",
    "sg:province":"TX",
    "sg:tags":[
        "mover"
    ],
    "sg:website":"www.armstrongmoving.com",
    "wof:name":"Armstrong Moving & Storage",
    "wof:placetype":"venue"
},
  "geometry": {"coordinates":[-106.380646,31.79202],"type":"Point"}
}