{
  "type": "Feature",
  "properties": {
    "iso:country":"US",
    "sg:address":"2537 Havenhurst St",
    "sg:city":"Dallas",
    "sg:classifiers":[
        {
            "category":"Building & Trades",
            "subcategory":"Construction",
            "type":"Services"
        }
    ],
    "sg:phone":"+1 972 247 3698",
    "sg:postcode":"75234",
    "sg:province":"TX",
    "sg:tags":[
        "house"
    ],
    "wof:name":"Semco Homes",
    "wof:placetype":"venue"
},
  "geometry": {"coordinates":[-96.893861,32.926686],"type":"Point"}
}