{
  "type": "Feature",
  "properties": {
    "iso:country":"US",
    "sg:address":"500 N Hampton Rd",
    "sg:city":"Desoto",
    "sg:classifiers":[
        {
            "category":"Professional",
            "subcategory":"Accounting & Tax Preparation",
            "type":"Services"
        }
    ],
    "sg:phone":"+1 972 274 0100",
    "sg:postcode":"75115",
    "sg:province":"TX",
    "sg:tags":[
        "return",
        "filing"
    ],
    "wof:name":"Computer Tax Svc",
    "wof:placetype":"venue"
},
  "geometry": {"coordinates":[-96.857035,32.597138],"type":"Point"}
}