{
  "type": "Feature",
  "properties": {
    "iso:country":"US",
    "sg:address":"2544 Tarpley Rd",
    "sg:city":"Carrollton",
    "sg:classifiers":[
        {
            "category":"Wholesale",
            "subcategory":"Durable Goods & Equipment",
            "type":"Manufacturing & Wholesale Goods"
        }
    ],
    "sg:phone":"+1 972 417 7111",
    "sg:postcode":"75006",
    "sg:province":"TX",
    "sg:tags":[
        "safety",
        "supply"
    ],
    "wof:name":"Ace Plus Security Laminates",
    "wof:placetype":"venue"
},
  "geometry": {"coordinates":[-96.85158199999999,32.984081],"type":"Point"}
}