{
  "type": "Feature",
  "properties": {
    "iso:country":"US",
    "sg:address":"16947 Meadowlark St",
    "sg:city":"Conroe",
    "sg:classifiers":[
        {
            "category":"Professional",
            "subcategory":"Computer Services",
            "type":"Services"
        }
    ],
    "sg:phone":"+1 936 321 1872",
    "sg:postcode":"77385",
    "sg:province":"TX",
    "wof:name":"Gizmo Systems & Technolog",
    "wof:placetype":"venue"
},
  "geometry": {"coordinates":[-95.431895,30.212913],"type":"Point"}
}