{
  "type": "Feature",
  "properties": {
    "iso:country":"US",
    "sg:address":"1729 Stebbins Dr Ste 150",
    "sg:city":"Houston",
    "sg:classifiers":[
        {
            "category":"Shopping",
            "subcategory":"Stationery & Office Supplies",
            "type":"Retail Goods"
        }
    ],
    "sg:phone":"+1 713 461 2938",
    "sg:postcode":"77043",
    "sg:province":"TX",
    "sg:tags":[
        "equipment"
    ],
    "wof:name":"Butler Business Products",
    "wof:placetype":"venue"
},
  "geometry": {"coordinates":[-95.55999799999999,29.802],"type":"Point"}
}