{
  "type": "Feature",
  "properties": {
    "iso:country":"US",
    "sg:address":"4802 Camp Bowie Blvd",
    "sg:city":"Fort Worth",
    "sg:classifiers":[
        {
            "category":"Professional",
            "subcategory":"Advertising",
            "type":"Services"
        }
    ],
    "sg:phone":"+1 817 377 2369",
    "sg:postcode":"76107",
    "sg:province":"TX",
    "sg:tags":[
        "agency"
    ],
    "wof:name":"Promotnal Exprssions Unlimited",
    "wof:placetype":"venue"
},
  "geometry": {"coordinates":[-97.39160800000001,32.738711],"type":"Point"}
}