{
  "type": "Feature",
  "properties": {
    "iso:country":"US",
    "sg:address":"8310 Pilgrims Pl",
    "sg:city":"Austin",
    "sg:classifiers":[
        {
            "category":"Professional",
            "subcategory":"Management & Consulting",
            "type":"Services"
        }
    ],
    "sg:phone":"+1 512 587 5668",
    "sg:postcode":"78759",
    "sg:province":"TX",
    "sg:tags":[
        "computer",
        "design",
        "system"
    ],
    "wof:name":"PDQ Consulting",
    "wof:placetype":"venue"
},
  "geometry": {"coordinates":[-97.77987299999999,30.43082],"type":"Point"}
}