{
  "type": "Feature",
  "properties": {
    "iso:country":"US",
    "sg:address":"1601 N 27th St",
    "sg:city":"Mcallen",
    "sg:classifiers":[
        {
            "category":"Education",
            "subcategory":"School",
            "type":"Public Place"
        }
    ],
    "sg:phone":"+1 956 971 4200",
    "sg:postcode":"78501",
    "sg:province":"TX",
    "wof:name":"Lincoln Middle School",
    "wof:placetype":"venue"
},
  "geometry": {"coordinates":[-98.247816,26.222022],"type":"Point"}
}