{
  "type": "Feature",
  "properties": {
    "iso:country":"US",
    "sg:address":"9341 Seymour Hwy",
    "sg:city":"Wichita Falls",
    "sg:classifiers":[
        {
            "category":"Building & Trades",
            "subcategory":"Construction",
            "type":"Services"
        }
    ],
    "sg:phone":"+1 940 691 6751",
    "sg:postcode":"76310",
    "sg:province":"TX",
    "sg:tags":[
        "hanging",
        "contractor"
    ],
    "wof:name":"Mountain Paint Co",
    "wof:placetype":"venue"
},
  "geometry": {"coordinates":[-98.659706,33.843227],"type":"Point"}
}