{
  "type": "Feature",
  "properties": {
    "iso:country":"US",
    "sg:address":"4117 Billy Mitchell Dr",
    "sg:city":"Addison",
    "sg:classifiers":[
        {
            "category":"Personal",
            "type":"Services"
        }
    ],
    "sg:phone":"+1 972 702 9623",
    "sg:postcode":"75001",
    "sg:province":"TX",
    "sg:tags":[
        "mover"
    ],
    "wof:name":"Corporate Relocation",
    "wof:placetype":"venue"
},
  "geometry": {"coordinates":[-96.84231200000001,32.959123],"type":"Point"}
}