{
  "type": "Feature",
  "properties": {
    "iso:country":"US",
    "sg:address":"2164 Texas Pkwy",
    "sg:city":"Missouri City",
    "sg:classifiers":[
        {
            "category":"Shopping",
            "subcategory":"Pawn Shop",
            "type":"Retail Goods"
        }
    ],
    "sg:phone":"+1 281 261 5626",
    "sg:postcode":"77489",
    "sg:province":"TX",
    "wof:name":"A-Plus Pawn Shops",
    "wof:placetype":"venue"
},
  "geometry": {"coordinates":[-95.526901,29.5959],"type":"Point"}
}