{
  "type": "Feature",
  "properties": {
    "iso:country":"US",
    "sg:address":"7720 Ferguson Rd",
    "sg:city":"Dallas",
    "sg:classifiers":[
        {
            "category":"Building & Trades",
            "subcategory":"Cleaning & Sanitation",
            "type":"Services"
        }
    ],
    "sg:phone":"+1 214 327 1967",
    "sg:postcode":"75228",
    "sg:province":"TX",
    "sg:tags":[
        "janitor",
        "contractor"
    ],
    "sg:website":"http://www.empireservicesinc.com/",
    "wof:name":"Empire Maintenance Services Inc",
    "wof:placetype":"venue"
},
  "geometry": {"coordinates":[-96.716418,32.799668],"type":"Point"}
}