{
  "type": "Feature",
  "properties": {
    "iso:country":"US",
    "sg:address":"5300 Medford Dr",
    "sg:city":"Austin",
    "sg:classifiers":[
        {
            "category":"Professional",
            "type":"Services"
        }
    ],
    "sg:phone":"+1 512 926 8344",
    "sg:postcode":"78723",
    "sg:province":"TX",
    "wof:name":"Olgas Service",
    "wof:placetype":"venue"
},
  "geometry": {"coordinates":[-97.680058,30.295521],"type":"Point"}
}