{
  "type": "Feature",
  "properties": {
    "iso:country":"US",
    "sg:address":"2503 E Main St",
    "sg:city":"Gatesville",
    "sg:classifiers":[
        {
            "category":"Restaurant",
            "type":"Food & Drink"
        }
    ],
    "sg:phone":"+1 254 865 2281",
    "sg:postcode":"76528",
    "sg:province":"TX",
    "wof:name":"Chateau Ville Restaurant",
    "wof:placetype":"venue"
},
  "geometry": {"coordinates":[-97.72134699999999,31.434685],"type":"Point"}
}