{
  "type": "Feature",
  "properties": {
    "iso:country":"US",
    "sg:address":"606 S Garcia St",
    "sg:city":"Port Isabel",
    "sg:classifiers":[
        {
            "category":"Autos & Motor Vehicles",
            "subcategory":"Boat Sales",
            "type":"Retail Goods"
        }
    ],
    "sg:phone":"+1 956 943 1157",
    "sg:postcode":"78578",
    "sg:province":"TX",
    "sg:tags":[
        "top",
        "upholstery",
        "cover"
    ],
    "wof:name":"Canvas Creations",
    "wof:placetype":"venue"
},
  "geometry": {"coordinates":[-97.20403,26.07425],"type":"Point"}
}