{
  "type": "Feature",
  "properties": {
    "iso:country":"US",
    "sg:address":"904 NW 7th Ave",
    "sg:city":"Mineral Wells",
    "sg:classifiers":[
        {
            "category":"Freight",
            "type":"Transportation"
        }
    ],
    "sg:phone":"+1 940 325 1185",
    "sg:postcode":"76067",
    "sg:province":"TX",
    "sg:tags":[
        "consultant"
    ],
    "wof:name":"Mineral Wells Air Freight",
    "wof:placetype":"venue"
},
  "geometry": {"coordinates":[-98.119818,32.815373],"type":"Point"}
}