{
  "type": "Feature",
  "properties": {
    "iso:country":"US",
    "sg:address":"820 S MacArthur Blvd",
    "sg:city":"Coppell",
    "sg:classifiers":[
        {
            "category":"Wholesale",
            "subcategory":"Fruits & Vegetables",
            "type":"Manufacturing & Wholesale Goods"
        }
    ],
    "sg:phone":"+1 972 393 2730",
    "sg:postcode":"75019",
    "sg:province":"TX",
    "sg:tags":[
        "veggie"
    ],
    "wof:name":"The Salad Bowl",
    "wof:placetype":"venue"
},
  "geometry": {"coordinates":[-96.95767600000001,32.951342],"type":"Point"}
}