{
  "type": "Feature",
  "properties": {
    "iso:country":"US",
    "sg:address":"200 W Main St",
    "sg:city":"Whitehouse",
    "sg:classifiers":[
        {
            "category":"Shopping",
            "subcategory":"Florist",
            "type":"Retail Goods"
        }
    ],
    "sg:phone":"+1 903 839 4098",
    "sg:postcode":"75791",
    "sg:province":"TX",
    "sg:tags":[
        "shop",
        "infant",
        "wear",
        "gift"
    ],
    "wof:name":"Whitehouse Flower Shop",
    "wof:placetype":"venue"
},
  "geometry": {"coordinates":[-95.228944,32.22674],"type":"Point"}
}