{
  "type": "Feature",
  "properties": {
    "iso:country":"US",
    "sg:address":"3221 34th St",
    "sg:city":"Lubbock",
    "sg:classifiers":[
        {
            "category":"Wholesale",
            "subcategory":"Home Furnishings",
            "type":"Manufacturing & Wholesale Goods"
        }
    ],
    "sg:phone":"+1 806 799 3336",
    "sg:postcode":"79410",
    "sg:province":"TX",
    "sg:tags":[
        "closet",
        "accessory"
    ],
    "wof:name":"Custom Closets Etc",
    "wof:placetype":"venue"
},
  "geometry": {"coordinates":[-101.885229,33.563186],"type":"Point"}
}