{
  "type": "Feature",
  "properties": {
    "iso:country":"US",
    "sg:address":"16365 1st St",
    "sg:city":"Splendora",
    "sg:classifiers":[
        {
            "category":"Travel",
            "subcategory":"Resort",
            "type":"Entertainment"
        }
    ],
    "sg:phone":"+1 281 399 0888",
    "sg:postcode":"77372",
    "sg:province":"TX",
    "wof:name":"Splendora Golden Jubilee",
    "wof:placetype":"venue"
},
  "geometry": {"coordinates":[-95.180758,30.205489],"type":"Point"}
}