{
  "type": "Feature",
  "properties": {
    "iso:country":"US",
    "sg:address":"11400 Augusta Dr",
    "sg:city":"Mesquite",
    "sg:classifiers":[
        {
            "category":"Building & Trades",
            "subcategory":"Cleaning & Sanitation",
            "type":"Services"
        }
    ],
    "sg:phone":"+1 214 906 0721",
    "sg:postcode":"75180",
    "sg:province":"TX",
    "sg:tags":[
        "maintenance"
    ],
    "wof:name":"Erics Maintenance",
    "wof:placetype":"venue"
},
  "geometry": {"coordinates":[-96.62884099999999,32.727765],"type":"Point"}
}