{
  "type": "Feature",
  "properties": {
    "iso:country":"US",
    "sg:address":"19 Winged Foot Dr",
    "sg:city":"Conroe",
    "sg:classifiers":[
        {
            "category":"Professional",
            "subcategory":"Business Services",
            "type":"Services"
        }
    ],
    "sg:phone":"+1 936 228 0622",
    "sg:postcode":"77304",
    "sg:province":"TX",
    "wof:name":"Creative House Calls",
    "wof:placetype":"venue"
},
  "geometry": {"coordinates":[-95.492418,30.378893],"type":"Point"}
}