{
  "type": "Feature",
  "properties": {
    "iso:country":"US",
    "sg:address":"101 W Goodwin Ave",
    "sg:city":"Victoria",
    "sg:classifiers":[
        {
            "category":"Government",
            "subcategory":"Office",
            "type":"Public Place"
        }
    ],
    "sg:phone":"+1 361 570 6779",
    "sg:postcode":"77901",
    "sg:province":"TX",
    "sg:tags":[
        "federal",
        "program",
        "adm"
    ],
    "wof:name":"US Census Bureau",
    "wof:placetype":"venue"
},
  "geometry": {"coordinates":[-97.005865,28.800952],"type":"Point"}
}