{
  "type": "Feature",
  "properties": {
    "iso:country":"US",
    "sg:address":"1451 FM 2673",
    "sg:city":"Canyon Lake",
    "sg:classifiers":[
        {
            "category":"Real Estate",
            "subcategory":"Real Estate Agent",
            "type":"Services"
        }
    ],
    "sg:phone":"+1 830 964 4075",
    "sg:postcode":"78133",
    "sg:province":"TX",
    "wof:name":"Century 21",
    "wof:placetype":"venue"
},
  "geometry": {"coordinates":[-98.173355,29.84925],"type":"Point"}
}