{
  "type": "Feature",
  "properties": {
    "iso:country":"US",
    "sg:address":"2503 Robinhood St",
    "sg:city":"Houston",
    "sg:classifiers":[
        {
            "category":"Education",
            "subcategory":"School",
            "type":"Public Place"
        }
    ],
    "sg:phone":"+1 713 529 4006",
    "sg:postcode":"77005",
    "sg:province":"TX",
    "wof:name":"Citizen Schools Inc",
    "wof:placetype":"venue"
},
  "geometry": {"coordinates":[-95.416741,29.720521],"type":"Point"}
}