{
  "type": "Feature",
  "properties": {
    "iso:country":"US",
    "sg:address":"1615 W Henderson St",
    "sg:city":"Cleburne",
    "sg:classifiers":[
        {
            "category":"Train Station",
            "subcategory":"Rail",
            "type":"Transportation"
        },
        {
            "category":"Wholesale",
            "subcategory":"Machinery & Supplies",
            "type":"Manufacturing & Wholesale Goods"
        },
        {
            "category":"Home & Garden",
            "subcategory":"Hardware",
            "type":"Retail Goods"
        },
        {
            "category":"Wholesale",
            "subcategory":"Farm Supplies",
            "type":"Manufacturing & Wholesale Goods"
        },
        {
            "category":"Shopping",
            "subcategory":"Pets & Pet Supplies",
            "type":"Retail Goods"
        },
        {
            "category":"Autos & Motor Vehicles",
            "subcategory":"Automobile Sales",
            "type":"Retail Goods"
        }
    ],
    "sg:phone":"+1 817 641 0066",
    "sg:postcode":"76033",
    "sg:province":"TX",
    "sg:tags":[
        "food",
        "transport",
        "equipment",
        "part",
        "store",
        "baling",
        "trailer",
        "tractor",
        "welding"
    ],
    "sg:website":"http://www.tractorsupply.com",
    "wof:name":"Tractor Supply Co",
    "wof:placetype":"venue"
},
  "geometry": {"coordinates":[-97.414233,32.338127],"type":"Point"}
}