{
  "type": "Feature",
  "properties": {
    "iso:country":"US",
    "sg:address":"3800 N Lamar Blvd Suite 730",
    "sg:city":"Austin",
    "sg:classifiers":[
        {
            "category":"Home & Garden",
            "subcategory":"Home Furnishings",
            "type":"Retail Goods"
        },
        {
            "category":"Professional",
            "subcategory":"Art Services",
            "type":"Services"
        },
        {
            "category":"Manufacturing",
            "subcategory":"Furniture",
            "type":"Manufacturing & Wholesale Goods"
        },
        {
            "category":"Real Estate",
            "subcategory":"Architect",
            "type":"Services"
        }
    ],
    "sg:phone":"+1 512 377 9953",
    "sg:postcode":"78756",
    "sg:province":"TX",
    "sg:tags":[
        "draperies",
        "decor",
        "designer",
        "residential",
        "builder",
        "custom",
        "window",
        "treatment",
        "interior",
        "curtain",
        "decorator"
    ],
    "sg:website":"http://www.gregorysinteriors.com",
    "wof:name":"Gregory's Interiors",
    "wof:placetype":"venue"
},
  "geometry": {"coordinates":[-97.742851,30.30559],"type":"Point"}
}