{
  "type": "Feature",
  "properties": {
    "iso:country":"US",
    "sg:address":"1741 W Anderson Ln",
    "sg:city":"Austin",
    "sg:classifiers":[
        {
            "category":"Shopping",
            "type":"Retail Goods"
        },
        {
            "category":"Home & Garden",
            "subcategory":"Furniture",
            "type":"Retail Goods"
        }
    ],
    "sg:phone":"+1 512 336 1111",
    "sg:postcode":"78757",
    "sg:province":"TX",
    "sg:tags":[
        "vault",
        "safe"
    ],
    "wof:name":"Austin Safe and Knife",
    "wof:placetype":"venue"
},
  "geometry": {"coordinates":[-97.724428,30.352954],"type":"Point"}
}