{
  "type": "Feature",
  "properties": {
    "iso:country":"US",
    "sg:address":"2112 Cedar St",
    "sg:city":"Paris",
    "sg:classifiers":[
        {
            "category":"Shopping",
            "subcategory":"Clothing, Apparel, & Fashions",
            "type":"Retail Goods"
        }
    ],
    "sg:phone":"+1 903 739 8060",
    "sg:postcode":"75460",
    "sg:province":"TX",
    "wof:name":"Jazzys Handbags",
    "wof:placetype":"venue"
},
  "geometry": {"coordinates":[-95.53444399999999,33.651267],"type":"Point"}
}