{
  "type": "Feature",
  "properties": {
    "iso:country":"US",
    "sg:address":"12607 Scissortail Dr",
    "sg:city":"Manchaca",
    "sg:classifiers":[
        {
            "category":"Social Services",
            "subcategory":"Adult Care",
            "type":"Services"
        }
    ],
    "sg:phone":"+1 512 292 1240",
    "sg:postcode":"78652",
    "sg:province":"TX",
    "sg:tags":[
        "retardation",
        "home",
        "dev",
        "disabled"
    ],
    "wof:name":"Scissortail Villa",
    "wof:placetype":"venue"
},
  "geometry": {"coordinates":[-97.830128,30.134507],"type":"Point"}
}