{
  "type": "Feature",
  "properties": {
    "iso:country":"US",
    "sg:address":"13219 N US Hwy 183",
    "sg:city":"Austin",
    "sg:classifiers":[
        {
            "category":"Health Services",
            "subcategory":"Chiropractor",
            "type":"Services"
        }
    ],
    "sg:phone":"+1 512 918 9222",
    "sg:postcode":"78750",
    "sg:province":"TX",
    "wof:name":"Dr Bary Garrett Chiropractor",
    "wof:placetype":"venue"
},
  "geometry": {"coordinates":[-97.784063,30.442725],"type":"Point"}
}