{
  "type": "Feature",
  "properties": {
    "iso:country":"US",
    "sg:address":"7522 Campbell Rd",
    "sg:city":"Dallas",
    "sg:classifiers":[
        {
            "category":"Food & Beverages",
            "subcategory":"Specialty",
            "type":"Retail Goods"
        }
    ],
    "sg:phone":"+1 972 381 7177",
    "sg:postcode":"75248",
    "sg:province":"TX",
    "sg:tags":[
        "health",
        "diet"
    ],
    "sg:website":"www.smoothiefactory.com",
    "wof:name":"Smoothie Factory",
    "wof:placetype":"venue"
},
  "geometry": {"coordinates":[-96.76857,32.978143],"type":"Point"}
}