{
  "type": "Feature",
  "properties": {
    "iso:country":"US",
    "sg:address":"100 NW Georgia Ave",
    "sg:city":"Sweetwater",
    "sg:classifiers":[
        {
            "category":"Food & Beverages",
            "subcategory":"Groceries & Convenience Stores",
            "type":"Retail Goods"
        }
    ],
    "sg:phone":"+1 325 236 6177",
    "sg:postcode":"79556",
    "sg:province":"TX",
    "sg:tags":[
        "station",
        "gas"
    ],
    "wof:name":"Sweetwater Chevron",
    "wof:placetype":"venue"
},
  "geometry": {"coordinates":[-100.400774,32.450111],"type":"Point"}
}