{
  "type": "Feature",
  "properties": {
    "iso:country":"US",
    "sg:address":"301 E Cate St",
    "sg:city":"Grand Saline",
    "sg:classifiers":[
        {
            "category":"Wholesale",
            "subcategory":"Auto Parts",
            "type":"Manufacturing & Wholesale Goods"
        }
    ],
    "sg:phone":"+1 903 962 7541",
    "sg:postcode":"75140",
    "sg:province":"TX",
    "sg:tags":[
        "trailer"
    ],
    "sg:website":"www.s-line.com",
    "wof:name":"Lone Star Parts",
    "wof:placetype":"venue"
},
  "geometry": {"coordinates":[-95.70826700000001,32.68154],"type":"Point"}
}