{
  "type": "Feature",
  "properties": {
    "iso:country":"US",
    "sg:address":"315 Flagler Ct",
    "sg:city":"Allen",
    "sg:classifiers":[
        {
            "category":"Professional",
            "subcategory":"Art Services",
            "type":"Services"
        }
    ],
    "sg:phone":"+1 972 644 0264",
    "sg:postcode":"75013",
    "sg:province":"TX",
    "sg:tags":[
        "graphic",
        "designer"
    ],
    "wof:name":"Mattox Design",
    "wof:placetype":"venue"
},
  "geometry": {"coordinates":[-96.70881300000001,33.095903],"type":"Point"}
}