{
  "type": "Feature",
  "properties": {
    "iso:country":"US",
    "sg:address":"2146 19th St",
    "sg:city":"Lubbock",
    "sg:classifiers":[
        {
            "category":"Cinema",
            "subcategory":"Movie Rental",
            "type":"Entertainment"
        }
    ],
    "sg:phone":"+1 806 747 2626",
    "sg:postcode":"79401",
    "sg:province":"TX",
    "sg:tags":[
        "video",
        "tape"
    ],
    "wof:name":"Video Express",
    "wof:placetype":"venue"
},
  "geometry": {"coordinates":[-101.863872,33.577864],"type":"Point"}
}