{
  "type": "Feature",
  "properties": {
    "iso:country":"US",
    "sg:address":"4116 Hawthorne Ave",
    "sg:city":"Dallas",
    "sg:classifiers":[
        {
            "category":"Professional",
            "subcategory":"Business Services",
            "type":"Services"
        }
    ],
    "sg:phone":"+1 214 522 3312",
    "sg:postcode":"75219",
    "sg:province":"TX",
    "sg:tags":[
        "consultant",
        "photography",
        "production",
        "film"
    ],
    "wof:name":"Solutions Group",
    "wof:placetype":"venue"
},
  "geometry": {"coordinates":[-96.804844,32.822604],"type":"Point"}
}