{
  "type": "Feature",
  "properties": {
    "iso:country":"US",
    "sg:address":"8050 N Mesa St",
    "sg:city":"El Paso",
    "sg:classifiers":[
        {
            "category":"Shopping",
            "subcategory":"Pharmacy",
            "type":"Retail Goods"
        }
    ],
    "sg:phone":"+1 915 585 0491",
    "sg:postcode":"79932",
    "sg:province":"TX",
    "sg:tags":[
        "drugstore",
        "store",
        "drug"
    ],
    "sg:website":"www.walgreens.com",
    "wof:name":"Walgreens",
    "wof:placetype":"venue"
},
  "geometry": {"coordinates":[-106.579222,31.841812],"type":"Point"}
}