{
  "type": "Feature",
  "properties": {
    "iso:country":"US",
    "sg:address":"901 S Willow St",
    "sg:city":"Pecos",
    "sg:classifiers":[
        {
            "category":"Education",
            "subcategory":"School",
            "type":"Public Place"
        }
    ],
    "sg:phone":"+1 432 447 7212",
    "sg:postcode":"79772",
    "sg:province":"TX",
    "wof:name":"Pecos Elementary School",
    "wof:placetype":"venue"
},
  "geometry": {"coordinates":[-103.49659699999999,31.418315],"type":"Point"}
}