{
  "type": "Feature",
  "properties": {
    "iso:country":"US",
    "sg:address":"209 W 39th St",
    "sg:city":"Austin",
    "sg:classifiers":[
        {
            "category":"Building & Trades",
            "subcategory":"Landscaping Services",
            "type":"Services"
        }
    ],
    "sg:phone":"+1 512 371 3670",
    "sg:postcode":"78751",
    "sg:province":"TX",
    "sg:tags":[
        "landscape"
    ],
    "wof:name":"Carmel Inga Marie A S L A",
    "wof:placetype":"venue"
},
  "geometry": {"coordinates":[-97.73450200000001,30.30263],"type":"Point"}
}