{
  "type": "Feature",
  "properties": {
    "iso:country":"US",
    "sg:address":"707 E 6th St",
    "sg:city":"Austin",
    "sg:classifiers":[
        {
            "category":"Manufacturing",
            "subcategory":"Food",
            "type":"Manufacturing & Wholesale Goods"
        }
    ],
    "sg:phone":"+1 512 480 8902",
    "sg:postcode":"78701",
    "sg:province":"TX",
    "sg:tags":[
        "frozen",
        "also",
        "cafe",
        "mfg"
    ],
    "wof:name":"Empanada Parlour Inc",
    "wof:placetype":"venue"
},
  "geometry": {"coordinates":[-97.735038,30.265814],"type":"Point"}
}