{
  "type": "Feature",
  "properties": {
    "iso:country":"US",
    "sg:address":"5173 Golfside Dr",
    "sg:city":"Frisco",
    "sg:classifiers":[
        {
            "category":"Professional",
            "subcategory":"Computer Services",
            "type":"Services"
        }
    ],
    "sg:phone":"+1 972 377 6386",
    "sg:postcode":"75035",
    "sg:province":"TX",
    "sg:tags":[
        "prepackaged",
        "software"
    ],
    "wof:name":"Vazer Software & Consulting",
    "wof:placetype":"venue"
},
  "geometry": {"coordinates":[-96.77039000000001,33.1208],"type":"Point"}
}