{
  "type": "Feature",
  "properties": {
    "iso:country":"US",
    "sg:address":"717 9th St",
    "sg:city":"South Houston",
    "sg:classifiers":[
        {
            "category":"Professional",
            "type":"Services"
        }
    ],
    "sg:phone":"+1 713 944 0551",
    "sg:postcode":"77587",
    "sg:province":"TX",
    "wof:name":"Morin Everardo",
    "wof:placetype":"venue"
},
  "geometry": {"coordinates":[-95.22039599999999,29.660328],"type":"Point"}
}