{
  "type": "Feature",
  "properties": {
    "iso:country":"US",
    "sg:address":"100 12th St Ste 105",
    "sg:city":"Pflugerville",
    "sg:classifiers":[
        {
            "category":"Shopping",
            "subcategory":"Hobbies, Toys, & Games",
            "type":"Retail Goods"
        },
        {
            "category":"Cinema",
            "subcategory":"Movie Rental",
            "type":"Entertainment"
        },
        {
            "category":"Shopping",
            "subcategory":"Books",
            "type":"Retail Goods"
        },
        {
            "category":"Shopping",
            "subcategory":"Comic Books",
            "type":"Retail Goods"
        }
    ],
    "sg:phone":"+1 512 251 0110",
    "sg:postcode":"78660",
    "sg:province":"TX",
    "sg:tags":[
        "bookstore",
        "toy",
        "video",
        "store"
    ],
    "sg:website":"www.ninjapirateland.com",
    "wof:name":"Ninja Pirate",
    "wof:placetype":"venue"
},
  "geometry": {"coordinates":[-97.629907,30.444152],"type":"Point"}
}