{
  "type": "Feature",
  "properties": {
    "iso:country":"US",
    "sg:address":"101 S Longview St",
    "sg:city":"Kilgore",
    "sg:classifiers":[
        {
            "category":"Retail",
            "subcategory":"Repair Shop",
            "type":"Services"
        }
    ],
    "sg:phone":"+1 903 984 9181",
    "sg:postcode":"75662",
    "sg:province":"TX",
    "wof:name":"Dorseys Upholstering",
    "wof:placetype":"venue"
},
  "geometry": {"coordinates":[-94.876992,32.387257],"type":"Point"}
}