{
  "type": "Feature",
  "properties": {
    "iso:country":"US",
    "sg:address":"1701 Oakwood St",
    "sg:city":"Fort Worth",
    "sg:classifiers":[
        {
            "category":"Real Estate",
            "subcategory":"Surveying",
            "type":"Services"
        }
    ],
    "sg:phone":"+1 817 834 5880",
    "sg:postcode":"76117",
    "sg:province":"TX",
    "wof:name":"Vogt Surveying",
    "wof:placetype":"venue"
},
  "geometry": {"coordinates":[-97.284063,32.786966],"type":"Point"}
}