{
  "type": "Feature",
  "properties": {
    "iso:country":"US",
    "sg:address":"517 N 16th St",
    "sg:city":"Waco",
    "sg:classifiers":[
        {
            "category":"Home & Garden",
            "subcategory":"Home Furnishings",
            "type":"Retail Goods"
        }
    ],
    "sg:phone":"+1 254 755 7181",
    "sg:postcode":"76707",
    "sg:province":"TX",
    "wof:name":"W & P Apparel",
    "wof:placetype":"venue"
},
  "geometry": {"coordinates":[-97.146433,31.55183],"type":"Point"}
}