{
  "type": "Feature",
  "properties": {
    "iso:country":"US",
    "sg:address":"5600 Virginia Pkwy",
    "sg:city":"Mc Kinney",
    "sg:classifiers":[
        {
            "category":"Social Services",
            "subcategory":"Child Care",
            "type":"Services"
        }
    ],
    "sg:phone":"+1 972 548 7275",
    "sg:postcode":"75071",
    "sg:province":"TX",
    "sg:tags":[
        "kindergarten",
        "academic",
        "school"
    ],
    "wof:name":"Parkway Christian Pre-School",
    "wof:placetype":"venue"
},
  "geometry": {"coordinates":[-96.69073299999999,33.198886],"type":"Point"}
}