{
  "type": "Feature",
  "properties": {
    "iso:country":"US",
    "sg:address":"2203 Park Springs Ct",
    "sg:city":"Arlington",
    "sg:classifiers":[
        {
            "category":"Shopping",
            "subcategory":"Used Merchandise",
            "type":"Retail Goods"
        }
    ],
    "sg:phone":"+1 817 469 9801",
    "sg:postcode":"76013",
    "sg:province":"TX",
    "sg:tags":[
        "antique"
    ],
    "wof:name":"Legacy Antiques",
    "wof:placetype":"venue"
},
  "geometry": {"coordinates":[-97.166397,32.708224],"type":"Point"}
}