{
  "type": "Feature",
  "properties": {
    "iso:country":"US",
    "sg:address":"3915 Euell Rd",
    "sg:city":"Crosby",
    "sg:classifiers":[
        {
            "category":"Shopping",
            "type":"Retail Goods"
        }
    ],
    "sg:phone":"+1 281 328 2077",
    "sg:postcode":"77532",
    "sg:province":"TX",
    "sg:tags":[
        "merchandise"
    ],
    "wof:name":"Rambos Fireworks",
    "wof:placetype":"venue"
},
  "geometry": {"coordinates":[-95.008921,29.923818],"type":"Point"}
}