{
  "type": "Feature",
  "properties": {
    "iso:country":"US",
    "sg:address":"10819 Crown Colony Dr",
    "sg:city":"Austin",
    "sg:classifiers":[
        {
            "category":"Professional",
            "subcategory":"Computer Services",
            "type":"Services"
        }
    ],
    "sg:phone":"+1 512 280 0561",
    "sg:postcode":"78747",
    "sg:province":"TX",
    "sg:tags":[
        "implementation",
        "wide",
        "design",
        "network",
        "area"
    ],
    "wof:name":"Texas Teledata Communications",
    "wof:placetype":"venue"
},
  "geometry": {"coordinates":[-97.794263,30.140166],"type":"Point"}
}