{
  "type": "Feature",
  "properties": {
    "iso:country":"US",
    "sg:address":"1005 Douglas Rd",
    "sg:city":"Athens",
    "sg:classifiers":[
        {
            "category":"Professional",
            "type":"Services"
        }
    ],
    "sg:phone":"+1 903 677 7457",
    "sg:postcode":"75751",
    "sg:province":"TX",
    "wof:name":"My Home",
    "wof:placetype":"venue"
},
  "geometry": {"coordinates":[-95.87420299999999,32.179154],"type":"Point"}
}