{
  "type": "Feature",
  "properties": {
    "iso:country":"US",
    "sg:address":"222 FM 359",
    "sg:city":"Richmond",
    "sg:classifiers":[
        {
            "category":"Real Estate",
            "subcategory":"Real Estate Agent",
            "type":"Services"
        }
    ],
    "sg:phone":"+1 281 238 9112",
    "sg:postcode":"77469",
    "sg:province":"TX",
    "wof:name":"A S C Realty & Property Manage",
    "wof:placetype":"venue"
},
  "geometry": {"coordinates":[-95.742468,29.602342],"type":"Point"}
}