{
  "type": "Feature",
  "properties": {
    "iso:country":"US",
    "sg:address":"711 Stadium Rd",
    "sg:city":"Port Arthur",
    "sg:classifiers":[
        {
            "category":"Retail",
            "subcategory":"Repair Shop",
            "type":"Services"
        }
    ],
    "sg:phone":"+1 409 982 0521",
    "sg:postcode":"77642",
    "sg:province":"TX",
    "wof:name":"Leonards TV Sales and Service",
    "wof:placetype":"venue"
},
  "geometry": {"coordinates":[-93.901634,29.91318],"type":"Point"}
}