{
  "type": "Feature",
  "properties": {
    "iso:country":"US",
    "sg:address":"10114 Cherry Tree Dr",
    "sg:city":"Dallas",
    "sg:classifiers":[
        {
            "category":"Retail",
            "subcategory":"Portrait Studio",
            "type":"Services"
        }
    ],
    "sg:phone":"+1 972 783 1141",
    "sg:postcode":"75243",
    "sg:province":"TX",
    "sg:tags":[
        "photo"
    ],
    "wof:name":"Louis Deluca Photography",
    "wof:placetype":"venue"
},
  "geometry": {"coordinates":[-96.718462,32.91508],"type":"Point"}
}