{
  "type": "Feature",
  "properties": {
    "iso:country":"US",
    "sg:address":"4126 Bermuda Dr",
    "sg:city":"Pasadena",
    "sg:classifiers":[
        {
            "category":"Professional",
            "subcategory":"Business Services",
            "type":"Services"
        }
    ],
    "sg:phone":"+1 713 479 1001",
    "sg:postcode":"77503",
    "sg:province":"TX",
    "wof:name":"Shadd Enterprises",
    "wof:placetype":"venue"
},
  "geometry": {"coordinates":[-95.14596400000001,29.691393],"type":"Point"}
}