{
  "type": "Feature",
  "properties": {
    "iso:country":"US",
    "sg:address":"4817 Ross Avenue",
    "sg:city":"Dallas",
    "sg:classifiers":[
        {
            "category":"Shopping",
            "type":"Retail Goods"
        }
    ],
    "sg:phone":"+1 214 827 6550",
    "sg:postcode":"75204",
    "sg:province":"TX",
    "wof:name":"Chupacabra",
    "wof:placetype":"venue"
},
  "geometry": {"coordinates":[-96.77664900000001,32.80603],"type":"Point"}
}