{
  "type": "Feature",
  "properties": {
    "iso:country":"US",
    "sg:address":"3855 S Alameda St",
    "sg:city":"Corpus Christi",
    "sg:classifiers":[
        {
            "category":"Shopping",
            "subcategory":"Jewelry",
            "type":"Retail Goods"
        }
    ],
    "sg:phone":"+1 361 854 3426",
    "sg:postcode":"78411",
    "sg:province":"TX",
    "sg:tags":[
        "jeweler"
    ],
    "wof:name":"Berry's & Still's Jewelers",
    "wof:placetype":"venue"
},
  "geometry": {"coordinates":[-97.381333,27.743855],"type":"Point"}
}