{
  "type": "Feature",
  "properties": {
    "iso:country":"US",
    "sg:address":"14500 Trinity Blvd",
    "sg:city":"Fort Worth",
    "sg:classifiers":[
        {
            "category":"Professional",
            "subcategory":"Testing Lab",
            "type":"Services"
        }
    ],
    "sg:phone":"+1 817 571 6800",
    "sg:postcode":"76155",
    "sg:province":"TX",
    "sg:tags":[
        "water",
        "soil",
        "laboratory",
        "including",
        "environmental"
    ],
    "sg:website":"www.staranalytical.com",
    "wof:name":"Star Analytical Inc",
    "wof:placetype":"venue"
},
  "geometry": {"coordinates":[-97.055564,32.822113],"type":"Point"}
}