{
  "type": "Feature",
  "properties": {
    "iso:country":"US",
    "sg:address":"1510 Green Tree Ln",
    "sg:city":"Duncanville",
    "sg:classifiers":[
        {
            "category":"Health Services",
            "subcategory":"Health Practitioner",
            "type":"Services"
        }
    ],
    "sg:phone":"+1 972 296 4334",
    "sg:postcode":"75137",
    "sg:province":"TX",
    "wof:name":"Sylvia Foladare",
    "wof:placetype":"venue"
},
  "geometry": {"coordinates":[-96.92998799999999,32.632059],"type":"Point"}
}