{
  "type": "Feature",
  "properties": {
    "iso:country":"US",
    "sg:address":"2025 Lakepointe Dr",
    "sg:city":"Lewisville",
    "sg:classifiers":[
        {
            "category":"Travel",
            "subcategory":"Hotels & Motels",
            "type":"Entertainment"
        }
    ],
    "sg:phone":"+1 972 459 2303",
    "sg:postcode":"75057",
    "sg:province":"TX",
    "sg:tags":[
        "operation"
    ],
    "wof:name":"Marriott Execustay",
    "wof:placetype":"venue"
},
  "geometry": {"coordinates":[-96.967888,33.011146],"type":"Point"}
}