{
  "type": "Feature",
  "properties": {
    "iso:country":"US",
    "sg:address":"1242 E Villa Maria Rd",
    "sg:city":"Bryan",
    "sg:classifiers":[
        {
            "category":"Wholesale",
            "subcategory":"Hardware",
            "type":"Manufacturing & Wholesale Goods"
        }
    ],
    "sg:phone":"+1 979 776 6277",
    "sg:postcode":"77802",
    "sg:province":"TX",
    "sg:tags":[
        "plumbing",
        "fixture",
        "supply"
    ],
    "wof:name":"Progress Supply",
    "wof:placetype":"venue"
},
  "geometry": {"coordinates":[-96.34831,30.652885],"type":"Point"}
}