{
  "type": "Feature",
  "properties": {
    "iso:country":"US",
    "sg:address":"5250 Gulfton St",
    "sg:city":"Houston",
    "sg:classifiers":[
        {
            "category":"Professional",
            "type":"Services"
        }
    ],
    "sg:phone":"+1 832 778 1616",
    "sg:postcode":"77081",
    "sg:province":"TX",
    "sg:tags":[
        "establishment"
    ],
    "wof:name":"Esra Trade",
    "wof:placetype":"venue"
},
  "geometry": {"coordinates":[-95.47085199999999,29.716647],"type":"Point"}
}