{
  "type": "Feature",
  "properties": {
    "iso:country":"US",
    "sg:address":"750 Rivercrest Dr",
    "sg:city":"Abilene",
    "sg:classifiers":[
        {
            "category":"Shopping",
            "type":"Retail Goods"
        }
    ],
    "sg:phone":"+1 325 677 4298",
    "sg:postcode":"79605",
    "sg:province":"TX",
    "sg:tags":[
        "art",
        "gallery",
        "dealer"
    ],
    "wof:name":"Zachry Studio & Gallery",
    "wof:placetype":"venue"
},
  "geometry": {"coordinates":[-99.76926400000001,32.441699],"type":"Point"}
}