{
  "type": "Feature",
  "properties": {
    "iso:country":"US",
    "sg:address":"350 E Royal Ln",
    "sg:city":"Irving",
    "sg:classifiers":[
        {
            "category":"Restaurant",
            "type":"Food & Drink"
        }
    ],
    "sg:phone":"+1 214 217 3000",
    "sg:postcode":"75039",
    "sg:province":"TX",
    "sg:tags":[
        "style",
        "family"
    ],
    "wof:name":"Mcrowd Restaurant Group Corporate",
    "wof:placetype":"venue"
},
  "geometry": {"coordinates":[-96.94049099999999,32.895647],"type":"Point"}
}