{
  "type": "Feature",
  "properties": {
    "iso:country":"US",
    "sg:address":"519 9th Ave N",
    "sg:city":"Texas City",
    "sg:classifiers":[
        {
            "category":"Shopping",
            "subcategory":"Gifts & Souvenirs",
            "type":"Retail Goods"
        }
    ],
    "sg:phone":"+1 409 945 4224",
    "sg:postcode":"77590",
    "sg:province":"TX",
    "wof:name":"Hallmark Rehabilitation",
    "wof:placetype":"venue"
},
  "geometry": {"coordinates":[-94.90238100000001,29.393319],"type":"Point"}
}