{
  "type": "Feature",
  "properties": {
    "iso:country":"US",
    "sg:address":"11777 Katy Fwy",
    "sg:city":"Houston",
    "sg:classifiers":[
        {
            "category":"Wholesale",
            "subcategory":"Durable Goods & Equipment",
            "type":"Manufacturing & Wholesale Goods"
        }
    ],
    "sg:phone":"+1 281 531 5524",
    "sg:postcode":"77079",
    "sg:province":"TX",
    "sg:tags":[
        "engineering",
        "supply"
    ],
    "wof:name":"JLC Svc Inc",
    "wof:placetype":"venue"
},
  "geometry": {"coordinates":[-95.592675,29.784163],"type":"Point"}
}