{
  "type": "Feature",
  "properties": {
    "iso:country":"US",
    "sg:address":"South Congress between Riverside and Oltorf",
    "sg:city":"Austin",
    "sg:classifiers":[
        {
            "category":"Restaurant",
            "type":"Food & Drink"
        }
    ],
    "sg:postcode":"78704",
    "sg:province":"TX",
    "sg:tags":[
        "flavor",
        "local"
    ],
    "sg:website":"www.socodistrict.com/1stthursday...",
    "wof:name":"First Thursday South Congress",
    "wof:placetype":"venue"
},
  "geometry": {"coordinates":[-97.75255300000001,30.241752],"type":"Point"}
}