{
  "type": "Feature",
  "properties": {
    "iso:country":"US",
    "sg:address":"1514 Southwood Rd",
    "sg:city":"Canutillo",
    "sg:classifiers":[
        {
            "category":"Home & Garden",
            "subcategory":"Hardware",
            "type":"Retail Goods"
        }
    ],
    "sg:phone":"+1 915 886 4129",
    "sg:postcode":"79835",
    "sg:province":"TX",
    "wof:name":"Sotos",
    "wof:placetype":"venue"
},
  "geometry": {"coordinates":[-106.569091,31.961796],"type":"Point"}
}