{
  "type": "Feature",
  "properties": {
    "iso:country":"US",
    "sg:address":"3027 54th St",
    "sg:city":"Lubbock",
    "sg:classifiers":[
        {
            "category":"Building & Trades",
            "subcategory":"Landscaping Services",
            "type":"Services"
        }
    ],
    "sg:phone":"+1 806 632 9085",
    "sg:postcode":"79413",
    "sg:province":"TX",
    "sg:tags":[
        "lawn"
    ],
    "wof:name":"Award Service And Landscape",
    "wof:placetype":"venue"
},
  "geometry": {"coordinates":[-101.88007399999999,33.545093],"type":"Point"}
}