{
  "type": "Feature",
  "properties": {
    "iso:country":"US",
    "sg:address":"8003 Channelview Dr",
    "sg:city":"Galveston",
    "sg:classifiers":[
        {
            "category":"Professional",
            "type":"Services"
        }
    ],
    "sg:phone":"+1 409 741 2567",
    "sg:postcode":"77554",
    "sg:province":"TX",
    "wof:name":"A 1 Wrecker Svc",
    "wof:placetype":"venue"
},
  "geometry": {"coordinates":[-94.863489,29.293412],"type":"Point"}
}