{
  "type": "Feature",
  "properties": {
    "iso:country":"US",
    "sg:address":"1801A Sharon Ln",
    "sg:city":"Austin",
    "sg:classifiers":[
        {
            "category":"Communications",
            "subcategory":"Film & Video Production",
            "type":"Services"
        }
    ],
    "sg:phone":"+1 512 481 0396",
    "sg:postcode":"78703",
    "sg:province":"TX",
    "sg:tags":[
        "tv",
        "radio",
        "services-commercial",
        "companies-film"
    ],
    "sg:website":"http://www.realnormal.com",
    "wof:name":"Real Normal Productions Inc",
    "wof:placetype":"venue"
},
  "geometry": {"coordinates":[-97.763763,30.290141],"type":"Point"}
}