{
  "type": "Feature",
  "properties": {
    "iso:country":"US",
    "sg:address":"5000 San Jacinto Mall",
    "sg:city":"Baytown",
    "sg:classifiers":[
        {
            "category":"Shopping",
            "subcategory":"Department Store",
            "type":"Retail Goods"
        }
    ],
    "sg:phone":"+1 281 421 4300",
    "sg:postcode":"77521",
    "sg:province":"TX",
    "sg:website":"http://www.macys.com",
    "wof:name":"Macy's",
    "wof:placetype":"venue"
},
  "geometry": {"coordinates":[-94.98697199999999,29.803057],"type":"Point"}
}