{
  "type": "Feature",
  "properties": {
    "iso:country":"US",
    "sg:address":"25550 Kingsland Blvd",
    "sg:city":"Katy",
    "sg:classifiers":[
        {
            "category":"Autos & Motor Vehicles",
            "subcategory":"Automobile Sales",
            "type":"Retail Goods"
        },
        {
            "category":"Retail",
            "subcategory":"Auto Repair",
            "type":"Services"
        }
    ],
    "sg:phone":"+1 281 644 1100",
    "sg:postcode":"77494",
    "sg:province":"TX",
    "sg:tags":[
        "used",
        "leasing",
        "car",
        "truck",
        "new"
    ],
    "sg:website":"http://www.championnissan.com/",
    "wof:name":"Champion Nissan",
    "wof:placetype":"venue"
},
  "geometry": {"coordinates":[-95.81565999999999,29.773767],"type":"Point"}
}