{
  "type": "Feature",
  "properties": {
    "iso:country":"US",
    "sg:address":"2124 Oakridge Dr",
    "sg:city":"Fort Worth",
    "sg:classifiers":[
        {
            "category":"Professional",
            "type":"Services"
        }
    ],
    "sg:phone":"+1 817 222 9142",
    "sg:postcode":"76117",
    "sg:province":"TX",
    "wof:name":"Ramon L Acosta",
    "wof:placetype":"venue"
},
  "geometry": {"coordinates":[-97.27046300000001,32.791054],"type":"Point"}
}