{
  "type": "Feature",
  "properties": {
    "iso:country":"US",
    "sg:address":"179 Sage Rd",
    "sg:city":"Houston",
    "sg:classifiers":[
        {
            "category":"Professional",
            "subcategory":"Management & Consulting",
            "type":"Services"
        }
    ],
    "sg:phone":"+1 713 622 4565",
    "sg:postcode":"77056",
    "sg:province":"TX",
    "wof:name":"Fielder Management Co Inc",
    "wof:placetype":"venue"
},
  "geometry": {"coordinates":[-95.46763799999999,29.768367],"type":"Point"}
}