{
  "type": "Feature",
  "properties": {
    "iso:country":"US",
    "sg:address":"208 W Spring Valley Rd",
    "sg:city":"Richardson",
    "sg:classifiers":[
        {
            "category":"Health Services",
            "subcategory":"Clinic",
            "type":"Services"
        }
    ],
    "sg:phone":"+1 972 836 2943",
    "sg:postcode":"75080",
    "sg:province":"TX",
    "sg:tags":[
        "loss",
        "weight"
    ],
    "sg:website":"hcg-quickweightloss.com/",
    "wof:name":"Fast Weight Loss Center",
    "wof:placetype":"venue"
},
  "geometry": {"coordinates":[-96.740971,32.940374],"type":"Point"}
}