{
  "type": "Feature",
  "properties": {
    "iso:country":"US",
    "sg:address":"608 W Donovan St",
    "sg:city":"Houston",
    "sg:classifiers":[
        {
            "category":"Personal",
            "type":"Services"
        }
    ],
    "sg:phone":"+1 713 692 0930",
    "sg:postcode":"77091",
    "sg:province":"TX",
    "sg:tags":[
        "towing"
    ],
    "wof:name":"Wheeler Dan Wrecker Service Inc",
    "wof:placetype":"venue"
},
  "geometry": {"coordinates":[-95.40969800000001,29.844299],"type":"Point"}
}