{
  "type": "Feature",
  "properties": {
    "iso:country":"US",
    "sg:address":"5004 Sandalwood Ln",
    "sg:city":"Arlington",
    "sg:classifiers":[
        {
            "category":"Wholesale",
            "subcategory":"Construction Materials",
            "type":"Manufacturing & Wholesale Goods"
        },
        {
            "category":"Home & Garden",
            "subcategory":"Building Materials",
            "type":"Retail Goods"
        }
    ],
    "sg:phone":"+1 817 937 8258",
    "sg:postcode":"76017",
    "sg:province":"TX",
    "sg:tags":[
        "windows-wholesale",
        "window",
        "manufacturer"
    ],
    "wof:name":"Price Half Siding Windows",
    "wof:placetype":"venue"
},
  "geometry": {"coordinates":[-97.11986899999999,32.665279],"type":"Point"}
}