{
  "type": "Feature",
  "properties": {
    "iso:country":"US",
    "sg:address":"10845 Denton Dr",
    "sg:city":"Dallas",
    "sg:classifiers":[
        {
            "category":"Manufacturing",
            "subcategory":"Electronics",
            "type":"Manufacturing & Wholesale Goods"
        }
    ],
    "sg:phone":"+1 214 654 9050",
    "sg:postcode":"75220",
    "sg:province":"TX",
    "sg:tags":[
        "box",
        "speaker",
        "mfg"
    ],
    "wof:name":"Amkor Audio Inc",
    "wof:placetype":"venue"
},
  "geometry": {"coordinates":[-96.88247699999999,32.876602],"type":"Point"}
}