{
  "type": "Feature",
  "properties": {
    "iso:country":"US",
    "sg:address":"2014 FM 1101",
    "sg:city":"New Braunfels",
    "sg:classifiers":[
        {
            "category":"Education",
            "subcategory":"School",
            "type":"Public Place"
        }
    ],
    "sg:phone":"+1 830 221 2300",
    "sg:postcode":"78130",
    "sg:province":"TX",
    "wof:name":"Canyon Middle School",
    "wof:placetype":"venue"
},
  "geometry": {"coordinates":[-98.085618,29.703353],"type":"Point"}
}