{
  "type": "Feature",
  "properties": {
    "iso:country":"US",
    "sg:address":"200 N W S Young Dr",
    "sg:city":"Killeen",
    "sg:classifiers":[
        {
            "category":"Education",
            "subcategory":"School",
            "type":"Public Place"
        }
    ],
    "sg:phone":"+1 254 501 0000",
    "sg:postcode":"76543",
    "sg:province":"TX",
    "sg:website":"www.killeenisd.org",
    "wof:name":"Killeen Independent Schl Dist",
    "wof:placetype":"venue"
},
  "geometry": {"coordinates":[-97.71137,31.115406],"type":"Point"}
}