{
  "type": "Feature",
  "properties": {
    "iso:country":"US",
    "sg:address":"876 Loop 337",
    "sg:city":"New Braunfels",
    "sg:classifiers":[
        {
            "category":"Professional",
            "subcategory":"Accounting & Tax Preparation",
            "type":"Services"
        }
    ],
    "sg:phone":"+1 830 609 9000",
    "sg:postcode":"78130",
    "sg:province":"TX",
    "sg:tags":[
        "payroll"
    ],
    "wof:name":"Payroll Logic",
    "wof:placetype":"venue"
},
  "geometry": {"coordinates":[-98.101788,29.710826],"type":"Point"}
}