{
  "type": "Feature",
  "properties": {
    "iso:country":"US",
    "sg:address":"222 S Ragsdale St",
    "sg:city":"Jacksonville",
    "sg:classifiers":[
        {
            "category":"Insurance",
            "subcategory":"Insurance Agent",
            "type":"Services"
        }
    ],
    "sg:phone":"+1 903 541 0453",
    "sg:postcode":"75766",
    "sg:province":"TX",
    "sg:tags":[
        "agency"
    ],
    "wof:name":"Swain & Baldwin Insur Inc",
    "wof:placetype":"venue"
},
  "geometry": {"coordinates":[-95.27175200000001,31.963884],"type":"Point"}
}