{
  "type": "Feature",
  "properties": {
    "iso:country":"US",
    "sg:address":"8226 Douglas Ave",
    "sg:city":"Dallas",
    "sg:classifiers":[
        {
            "category":"Health Services",
            "subcategory":"Optometrist",
            "type":"Services"
        }
    ],
    "sg:phone":"+1 214 739 5355",
    "sg:postcode":"75225",
    "sg:province":"TX",
    "sg:tags":[
        "eyes",
        "prosthetic"
    ],
    "wof:name":"Eye Prosthetics",
    "wof:placetype":"venue"
},
  "geometry": {"coordinates":[-96.808605,32.863249],"type":"Point"}
}