{
  "type": "Feature",
  "properties": {
    "iso:country":"US",
    "sg:address":"909 Judson Rd",
    "sg:city":"Longview",
    "sg:classifiers":[
        {
            "category":"Health Services",
            "subcategory":"Doctor",
            "type":"Services"
        }
    ],
    "sg:phone":"+1 903 758 7471",
    "sg:postcode":"75601",
    "sg:province":"TX",
    "wof:name":"Morgan L Willeford DDS",
    "wof:placetype":"venue"
},
  "geometry": {"coordinates":[-94.739957,32.505192],"type":"Point"}
}