{
  "type": "Feature",
  "properties": {
    "iso:country":"US",
    "sg:address":"102 Chula Vista Dr",
    "sg:city":"Kerrville",
    "sg:classifiers":[
        {
            "category":"Professional",
            "subcategory":"Accounting & Tax Preparation",
            "type":"Services"
        }
    ],
    "sg:phone":"+1 830 896 4060",
    "sg:postcode":"78028",
    "sg:province":"TX",
    "sg:tags":[
        "return"
    ],
    "wof:name":"Duke Jim Tax Service",
    "wof:placetype":"venue"
},
  "geometry": {"coordinates":[-99.146463,30.033458],"type":"Point"}
}