{
  "type": "Feature",
  "properties": {
    "iso:country":"US",
    "sg:address":"1120 Americana Ln",
    "sg:city":"Mesquite",
    "sg:classifiers":[
        {
            "category":"Professional",
            "subcategory":"Accounting & Tax Preparation",
            "type":"Services"
        }
    ],
    "sg:phone":"+1 972 686 4265",
    "sg:postcode":"75150",
    "sg:province":"TX",
    "sg:tags":[
        "billing"
    ],
    "wof:name":"SMR Medical Billing",
    "wof:placetype":"venue"
},
  "geometry": {"coordinates":[-96.615707,32.804985],"type":"Point"}
}