{
  "type": "Feature",
  "properties": {
    "iso:country":"US",
    "sg:address":"416 Rim Rock Dr",
    "sg:city":"Fort Worth",
    "sg:classifiers":[
        {
            "category":"Wholesale",
            "subcategory":"Construction Materials",
            "type":"Manufacturing & Wholesale Goods"
        }
    ],
    "sg:phone":"+1 817 367 0673",
    "sg:postcode":"76108",
    "sg:province":"TX",
    "sg:tags":[
        "insulation",
        "roofing",
        "c",
        "remodeling",
        "siding"
    ],
    "wof:name":"Arrington Roofing & Remodeling",
    "wof:placetype":"venue"
},
  "geometry": {"coordinates":[-97.491884,32.754488],"type":"Point"}
}