{
  "type": "Feature",
  "properties": {
    "iso:country":"US",
    "sg:address":"902 Ave A",
    "sg:city":"Lubbock",
    "sg:classifiers":[
        {
            "category":"Freight",
            "type":"Transportation"
        }
    ],
    "sg:phone":"+1 806 765 9268",
    "sg:postcode":"79401",
    "sg:province":"TX",
    "sg:tags":[
        "warehouse",
        "tire"
    ],
    "wof:name":"Mc Whorters Inc",
    "wof:placetype":"venue"
},
  "geometry": {"coordinates":[-101.83644099999999,33.586497],"type":"Point"}
}