{
  "type": "Feature",
  "properties": {
    "iso:country":"US",
    "sg:address":"11682 Southwest Fwy",
    "sg:city":"Houston",
    "sg:classifiers":[
        {
            "category":"Health Services",
            "subcategory":"Doctor",
            "type":"Services"
        }
    ],
    "sg:phone":"+1 281 495 6883",
    "sg:postcode":"77031",
    "sg:province":"TX",
    "sg:tags":[
        "dentist"
    ],
    "wof:name":"AAA Dentists",
    "wof:placetype":"venue"
},
  "geometry": {"coordinates":[-95.567217,29.65191],"type":"Point"}
}