{
  "type": "Feature",
  "properties": {
    "iso:country":"US",
    "sg:address":"27326 Robinson Rd",
    "sg:city":"Conroe",
    "sg:classifiers":[
        {
            "category":"Professional",
            "type":"Services"
        }
    ],
    "sg:phone":"+1 281 419 3900",
    "sg:postcode":"77385",
    "sg:province":"TX",
    "wof:name":"ISO Fitness",
    "wof:placetype":"venue"
},
  "geometry": {"coordinates":[-95.44084100000001,30.157098],"type":"Point"}
}