{
  "type": "Feature",
  "properties": {
    "iso:country":"US",
    "sg:address":"8 Greenleaf Dr",
    "sg:city":"Roanoke",
    "sg:classifiers":[
        {
            "category":"Education",
            "subcategory":"Special Training",
            "type":"Public Place"
        }
    ],
    "sg:phone":"+1 817 491 4011",
    "sg:postcode":"76262",
    "sg:province":"TX",
    "wof:name":"Joyworks",
    "wof:placetype":"venue"
},
  "geometry": {"coordinates":[-97.17077399999999,32.996623],"type":"Point"}
}