{
  "type": "Feature",
  "properties": {
    "iso:country":"US",
    "sg:address":"303 N Hampton Rd",
    "sg:city":"Desoto",
    "sg:classifiers":[
        {
            "category":"Restaurant",
            "type":"Food & Drink"
        }
    ],
    "sg:phone":"+1 972 274 1927",
    "sg:postcode":"75115",
    "sg:province":"TX",
    "sg:tags":[
        "eating",
        "chinese"
    ],
    "wof:name":"China Express",
    "wof:placetype":"venue"
},
  "geometry": {"coordinates":[-96.857201,32.593498],"type":"Point"}
}