{
  "type": "Feature",
  "properties": {
    "iso:country":"US",
    "sg:address":"1479 Bering Dr",
    "sg:city":"Houston",
    "sg:classifiers":[
        {
            "category":"Professional",
            "subcategory":"Management & Consulting",
            "type":"Services"
        }
    ],
    "sg:phone":"+1 713 952 1502",
    "sg:postcode":"77057",
    "sg:province":"TX",
    "sg:tags":[
        "provides",
        "business"
    ],
    "wof:name":"Pointer Resources",
    "wof:placetype":"venue"
},
  "geometry": {"coordinates":[-95.479489,29.751916],"type":"Point"}
}