{
  "type": "Feature",
  "properties": {
    "iso:country":"US",
    "sg:address":"215 W Omega St",
    "sg:city":"Henrietta",
    "sg:classifiers":[
        {
            "category":"Autos & Motor Vehicles",
            "subcategory":"Fuel & Gas Station",
            "type":"Retail Goods"
        }
    ],
    "sg:phone":"+1 940 538 6305",
    "sg:postcode":"76365",
    "sg:province":"TX",
    "sg:tags":[
        "oil"
    ],
    "wof:name":"Highway 82 Full Svc",
    "wof:placetype":"venue"
},
  "geometry": {"coordinates":[-98.197244,33.814866],"type":"Point"}
}