{
  "type": "Feature",
  "properties": {
    "iso:country":"US",
    "sg:address":"7239 Dale Rd",
    "sg:city":"El Paso",
    "sg:classifiers":[
        {
            "category":"Building & Trades",
            "subcategory":"Plumbing",
            "type":"Services"
        }
    ],
    "sg:phone":"+1 915 778 0340",
    "sg:postcode":"79915",
    "sg:province":"TX",
    "sg:tags":[
        "plumbing"
    ],
    "wof:name":"Sams Plymbing Co",
    "wof:placetype":"venue"
},
  "geometry": {"coordinates":[-106.37795699999999,31.751221],"type":"Point"}
}