{
  "type": "Feature",
  "properties": {
    "iso:country":"US",
    "sg:address":"3527 Byron St",
    "sg:city":"San Antonio",
    "sg:classifiers":[
        {
            "category":"Shopping",
            "subcategory":"Clothing, Apparel, & Fashions",
            "type":"Retail Goods"
        }
    ],
    "sg:phone":"+1 210 496 0811",
    "sg:postcode":"78247",
    "sg:province":"TX",
    "wof:name":"Primetime Online",
    "wof:placetype":"venue"
},
  "geometry": {"coordinates":[-98.423171,29.568348],"type":"Point"}
}