{
  "type": "Feature",
  "properties": {
    "iso:country":"US",
    "sg:address":"103 N John Stockbauer Dr",
    "sg:city":"Victoria",
    "sg:classifiers":[
        {
            "category":"Shopping",
            "type":"Retail Goods"
        }
    ],
    "sg:phone":"+1 361 578 1831",
    "sg:postcode":"77901",
    "sg:province":"TX",
    "sg:tags":[
        "merchandise"
    ],
    "wof:name":"Motorola Special Accounts",
    "wof:placetype":"venue"
},
  "geometry": {"coordinates":[-96.95335900000001,28.827446],"type":"Point"}
}