{
  "type": "Feature",
  "properties": {
    "iso:country":"US",
    "sg:address":"516 W May St",
    "sg:city":"Odessa",
    "sg:classifiers":[
        {
            "category":"Professional",
            "type":"Services"
        }
    ],
    "sg:phone":"+1 432 332 4940",
    "sg:postcode":"79761",
    "sg:province":"TX",
    "wof:name":"Elizabeths Boutique",
    "wof:placetype":"venue"
},
  "geometry": {"coordinates":[-102.370474,31.837914],"type":"Point"}
}