{
  "type": "Feature",
  "properties": {
    "iso:country":"US",
    "sg:address":"118 W Bedford St",
    "sg:city":"Dimmitt",
    "sg:classifiers":[
        {
            "category":"Retail",
            "subcategory":"Auto Repair",
            "type":"Services"
        }
    ],
    "sg:phone":"+1 806 647 5000",
    "sg:postcode":"79027",
    "sg:province":"TX",
    "sg:tags":[
        "automobile",
        "lubrication",
        "automotive"
    ],
    "wof:name":"J & J Car Care Inc",
    "wof:placetype":"venue"
},
  "geometry": {"coordinates":[-102.313592,34.551049],"type":"Point"}
}