{
  "type": "Feature",
  "properties": {
    "iso:country":"US",
    "sg:address":"1720 S Edmonds Ln",
    "sg:city":"Lewisville",
    "sg:classifiers":[
        {
            "category":"Shopping",
            "subcategory":"Discount & Variety Stores",
            "type":"Retail Goods"
        }
    ],
    "sg:phone":"+1 972 353 8813",
    "sg:postcode":"75067",
    "sg:province":"TX",
    "sg:tags":[
        "merchandise",
        "general"
    ],
    "wof:name":"Watkins Aviation",
    "wof:placetype":"venue"
},
  "geometry": {"coordinates":[-97.010694,33.022146],"type":"Point"}
}