{
  "type": "Feature",
  "properties": {
    "iso:country":"US",
    "sg:address":"9100 Gateway Blvd N",
    "sg:city":"El Paso",
    "sg:classifiers":[
        {
            "category":"Government",
            "subcategory":"Office",
            "type":"Public Place"
        }
    ],
    "sg:phone":"+1 915 755 2451",
    "sg:postcode":"79924",
    "sg:province":"TX",
    "sg:tags":[
        "state",
        "security"
    ],
    "wof:name":"Army National Guard Career",
    "wof:placetype":"venue"
},
  "geometry": {"coordinates":[-106.440066,31.869709],"type":"Point"}
}