{
  "type": "Feature",
  "properties": {
    "iso:country":"US",
    "sg:address":"5605 Norfolk Ln",
    "sg:city":"Frisco",
    "sg:classifiers":[
        {
            "category":"Sports & Exercise",
            "subcategory":"Gym",
            "type":"Entertainment"
        }
    ],
    "sg:phone":"+1 972 731 8889",
    "sg:postcode":"75035",
    "sg:province":"TX",
    "sg:tags":[
        "fitness",
        "physical",
        "facility"
    ],
    "wof:name":"Rays Fitness",
    "wof:placetype":"venue"
},
  "geometry": {"coordinates":[-96.770887,33.126679],"type":"Point"}
}