{
  "type": "Feature",
  "properties": {
    "iso:country":"US",
    "sg:address":"1907 Wisteria Ct",
    "sg:city":"Flower Mound",
    "sg:classifiers":[
        {
            "category":"Autos & Motor Vehicles",
            "subcategory":"Motorcycle Sales",
            "type":"Retail Goods"
        }
    ],
    "sg:phone":"+1 972 355 1750",
    "sg:postcode":"75028",
    "sg:province":"TX",
    "wof:name":"CJ Motor Sports",
    "wof:placetype":"venue"
},
  "geometry": {"coordinates":[-97.05901,33.037961],"type":"Point"}
}