{
  "type": "Feature",
  "properties": {
    "iso:country":"US",
    "sg:address":"8407 Lone Quail Dr",
    "sg:city":"Missouri City",
    "sg:classifiers":[
        {
            "category":"Professional",
            "subcategory":"Art Services",
            "type":"Services"
        }
    ],
    "sg:phone":"+1 281 438 3972",
    "sg:postcode":"77489",
    "sg:province":"TX",
    "sg:tags":[
        "commercial",
        "design"
    ],
    "wof:name":"Ch Graphics",
    "wof:placetype":"venue"
},
  "geometry": {"coordinates":[-95.514152,29.582651],"type":"Point"}
}