{
  "type": "Feature",
  "properties": {
    "iso:country":"US",
    "sg:address":"2505 Mark Dr",
    "sg:city":"Mesquite",
    "sg:classifiers":[
        {
            "category":"Shopping",
            "subcategory":"Gifts & Souvenirs",
            "type":"Retail Goods"
        }
    ],
    "sg:phone":"+1 972 270 1148",
    "sg:postcode":"75150",
    "sg:province":"TX",
    "wof:name":"R & M Enterprises",
    "wof:placetype":"venue"
},
  "geometry": {"coordinates":[-96.63853,32.795897],"type":"Point"}
}