{
  "type": "Feature",
  "properties": {
    "iso:country":"US",
    "sg:address":"15909 S Great Oaks Dr",
    "sg:city":"Round Rock",
    "sg:classifiers":[
        {
            "category":"Autos & Motor Vehicles",
            "subcategory":"Auto Supplies",
            "type":"Retail Goods"
        }
    ],
    "sg:phone":"+1 512 238 1744",
    "sg:postcode":"78681",
    "sg:province":"TX",
    "sg:tags":[
        "tire"
    ],
    "wof:name":"Lamb's Tire & Automotive Centers",
    "wof:placetype":"venue"
},
  "geometry": {"coordinates":[-97.726097,30.4937],"type":"Point"}
}