{
  "type": "Feature",
  "properties": {
    "iso:country":"US",
    "sg:address":"3220 Park Row Ave",
    "sg:city":"Dallas",
    "sg:classifiers":[
        {
            "category":"Insurance",
            "subcategory":"Insurance Agent",
            "type":"Services"
        }
    ],
    "sg:phone":"+1 214 361 4741",
    "sg:postcode":"75210",
    "sg:province":"TX",
    "wof:name":"Orlando Reyes Insurance",
    "wof:placetype":"venue"
},
  "geometry": {"coordinates":[-96.764973,32.77575],"type":"Point"}
}