{
  "type": "Feature",
  "properties": {
    "iso:country":"US",
    "sg:address":"2011 Robinhood St",
    "sg:city":"Pasadena",
    "sg:classifiers":[
        {
            "category":"Professional",
            "type":"Services"
        }
    ],
    "sg:phone":"+1 713 477 1916",
    "sg:postcode":"77502",
    "sg:province":"TX",
    "wof:name":"Divanqbvm",
    "wof:placetype":"venue"
},
  "geometry": {"coordinates":[-95.203322,29.682311],"type":"Point"}
}