{
  "type": "Feature",
  "properties": {
    "iso:country":"US",
    "sg:address":"9596 WICKERSHAM #317",
    "sg:city":"Dallas",
    "sg:classifiers":[
        {
            "category":"Utilities",
            "subcategory":"Water",
            "type":"Services"
        },
        {
            "category":"Wholesale",
            "subcategory":"Machinery & Supplies",
            "type":"Manufacturing & Wholesale Goods"
        },
        {
            "category":"Building & Trades",
            "subcategory":"Construction",
            "type":"Services"
        }
    ],
    "sg:phone":"+1 214 283 0886",
    "sg:postcode":"75238",
    "sg:province":"TX",
    "sg:tags":[
        "estimate",
        "equipment",
        "irrigation",
        "system"
    ],
    "sg:website":"http://www.1stchoicesprinklers.net",
    "wof:name":"**1st Choice Sprinklers**",
    "wof:placetype":"venue"
},
  "geometry": {"coordinates":[-96.71288300000001,32.89436],"type":"Point"}
}