{
  "type": "Feature",
  "properties": {
    "iso:country":"US",
    "sg:address":"871 N Main St",
    "sg:city":"Salado",
    "sg:classifiers":[
        {
            "category":"Shopping",
            "subcategory":"Books",
            "type":"Retail Goods"
        }
    ],
    "sg:phone":"+1 254 947 3711",
    "sg:postcode":"76571",
    "sg:province":"TX",
    "wof:name":"Scrap Book Cottage",
    "wof:placetype":"venue"
},
  "geometry": {"coordinates":[-97.533978,30.955463],"type":"Point"}
}