{
  "type": "Feature",
  "properties": {
    "iso:country":"US",
    "sg:address":"729 Grapevine Hwy",
    "sg:city":"Hurst",
    "sg:classifiers":[
        {
            "category":"Professional",
            "subcategory":"Advertising",
            "type":"Services"
        }
    ],
    "sg:phone":"+1 817 514 8070",
    "sg:postcode":"76054",
    "sg:province":"TX",
    "sg:tags":[
        "mailing",
        "shipping"
    ],
    "wof:name":"Mail Room",
    "wof:placetype":"venue"
},
  "geometry": {"coordinates":[-97.18090100000001,32.859837],"type":"Point"}
}