{
  "type": "Feature",
  "properties": {
    "iso:country":"US",
    "sg:address":"4200 Camp Bowie Blvd",
    "sg:city":"Fort Worth",
    "sg:classifiers":[
        {
            "category":"Social Services",
            "subcategory":"Child Care",
            "type":"Services"
        }
    ],
    "sg:phone":"+1 817 731 0662",
    "sg:postcode":"76107",
    "sg:province":"TX",
    "sg:tags":[
        "kindergarten",
        "academic",
        "school"
    ],
    "wof:name":"Arlington Heights Meth Preschl",
    "wof:placetype":"venue"
},
  "geometry": {"coordinates":[-97.381113,32.742987],"type":"Point"}
}