{
  "type": "Feature",
  "properties": {
    "iso:country":"US",
    "sg:address":"2947 Bluebonnet Dr",
    "sg:city":"Brownsville",
    "sg:phone":"+1 956 542 1745",
    "sg:postcode":"78521",
    "sg:province":"TX",
    "sg:tags":[
        "farm",
        "grain",
        "cash"
    ],
    "wof:name":"Delgado Delgado",
    "wof:placetype":"venue"
},
  "geometry": {"coordinates":[-97.50158399999999,25.944335],"type":"Point"}
}