{
  "type": "Feature",
  "properties": {
    "iso:country":"US",
    "sg:address":"14410 Alameda Ridge",
    "sg:city":"San Antonio",
    "sg:classifiers":[
        {
            "category":"Professional",
            "type":"Services"
        }
    ],
    "sg:phone":"+1 210 404 0222",
    "sg:postcode":"78230",
    "sg:province":"TX",
    "sg:tags":[
        "establishment"
    ],
    "wof:name":"Affinity Development Group",
    "wof:placetype":"venue"
},
  "geometry": {"coordinates":[-98.58035599999999,29.562548],"type":"Point"}
}