{
  "type": "Feature",
  "properties": {
    "iso:country":"US",
    "sg:address":"136 S Booth Calloway Rd",
    "sg:city":"Hurst",
    "sg:classifiers":[
        {
            "category":"Manufacturing",
            "subcategory":"Food",
            "type":"Manufacturing & Wholesale Goods"
        }
    ],
    "sg:phone":"+1 817 590 2154",
    "sg:postcode":"76053",
    "sg:province":"TX",
    "sg:tags":[
        "product",
        "mfg"
    ],
    "wof:name":"Donuts World",
    "wof:placetype":"venue"
},
  "geometry": {"coordinates":[-97.212272,32.808391],"type":"Point"}
}