{
  "type": "Feature",
  "properties": {
    "iso:country":"US",
    "sg:address":"11131 Tall Timbers Dr",
    "sg:city":"Houston",
    "sg:classifiers":[
        {
            "category":"Home & Garden",
            "subcategory":"Garden Supply",
            "type":"Retail Goods"
        }
    ],
    "sg:phone":"+1 281 450 5724",
    "sg:postcode":"77065",
    "sg:province":"TX",
    "sg:tags":[
        "sprinkler"
    ],
    "wof:name":"Benavides Irrigation",
    "wof:placetype":"venue"
},
  "geometry": {"coordinates":[-95.587279,29.940985],"type":"Point"}
}