{
  "type": "Feature",
  "properties": {
    "iso:country":"US",
    "sg:address":"4572 Sandpiper Cove",
    "sg:city":"College Station",
    "sg:classifiers":[
        {
            "category":"Communications",
            "subcategory":"Film & Video Production",
            "type":"Services"
        }
    ],
    "sg:phone":"+1 979 845 1991",
    "sg:postcode":"77845",
    "sg:province":"TX",
    "sg:tags":[
        "motion",
        "broadcast",
        "station",
        "radio"
    ],
    "wof:name":"Diamond Seven Productions",
    "wof:placetype":"venue"
},
  "geometry": {"coordinates":[-96.24980100000001,30.545612],"type":"Point"}
}