{
  "type": "Feature",
  "properties": {
    "iso:country":"US",
    "sg:address":"205 S Commerce St",
    "sg:city":"Gainesville",
    "sg:classifiers":[
        {
            "category":"Shopping",
            "type":"Retail Goods"
        }
    ],
    "sg:phone":"+1 940 665 0559",
    "sg:postcode":"76240",
    "sg:province":"TX",
    "sg:tags":[
        "art",
        "gallery",
        "dealer"
    ],
    "wof:name":"Paige Davidson Studio",
    "wof:placetype":"venue"
},
  "geometry": {"coordinates":[-97.14624499999999,33.623581],"type":"Point"}
}