{
  "type": "Feature",
  "properties": {
    "iso:country":"US",
    "sg:address":"111 N Houston St",
    "sg:city":"Pampa",
    "sg:classifiers":[
        {
            "category":"Education",
            "subcategory":"Library",
            "type":"Public Place"
        }
    ],
    "sg:phone":"+1 806 669 5780",
    "sg:postcode":"79065",
    "sg:province":"TX",
    "wof:name":"Lovett Memorial Library",
    "wof:placetype":"venue"
},
  "geometry": {"coordinates":[-100.95857700000001,35.538255],"type":"Point"}
}