{
  "type": "Feature",
  "properties": {
    "iso:country":"US",
    "sg:address":"525 Evergreen Dr",
    "sg:city":"Corpus Christi",
    "sg:classifiers":[
        {
            "category":"Building & Trades",
            "subcategory":"Landscaping Services",
            "type":"Services"
        }
    ],
    "sg:phone":"+1 361 906 0987",
    "sg:postcode":"78412",
    "sg:province":"TX",
    "wof:name":"Bonilla Lawn & Landscape",
    "wof:placetype":"venue"
},
  "geometry": {"coordinates":[-97.357175,27.719417],"type":"Point"}
}