{
  "type": "Feature",
  "properties": {
    "iso:country":"US",
    "sg:address":"169 Joe Thomas Rd",
    "sg:city":"Texarkana",
    "sg:classifiers":[
        {
            "category":"Autos & Motor Vehicles",
            "subcategory":"Auto Supplies",
            "type":"Retail Goods"
        }
    ],
    "sg:phone":"+1 903 794 0433",
    "sg:postcode":"75501",
    "sg:province":"TX",
    "sg:tags":[
        "automobile",
        "part",
        "accessory"
    ],
    "wof:name":"Markle Auto Parts & More",
    "wof:placetype":"venue"
},
  "geometry": {"coordinates":[-94.09602700000001,33.323134],"type":"Point"}
}