{
  "type": "Feature",
  "properties": {
    "iso:country":"US",
    "sg:address":"7402 Harry Hines Blvd",
    "sg:city":"Dallas",
    "sg:classifiers":[
        {
            "category":"Personal",
            "subcategory":"Beauty Salon",
            "type":"Services"
        }
    ],
    "sg:phone":"+1 214 634 2004",
    "sg:postcode":"75235",
    "sg:province":"TX",
    "sg:tags":[
        "shop"
    ],
    "wof:name":"Margareta's Unisex",
    "wof:placetype":"venue"
},
  "geometry": {"coordinates":[-96.856753,32.828219],"type":"Point"}
}