{
  "type": "Feature",
  "properties": {
    "iso:country":"US",
    "sg:address":"5330 Griggs Rd",
    "sg:city":"Houston",
    "sg:classifiers":[
        {
            "category":"Organizations",
            "subcategory":"Religious Organization",
            "type":"Services"
        }
    ],
    "sg:phone":"+1 713 645 4415",
    "sg:postcode":"77021",
    "sg:province":"TX",
    "wof:name":"Kingdom Come CDC",
    "wof:placetype":"venue"
},
  "geometry": {"coordinates":[-95.33257999999999,29.696465],"type":"Point"}
}