{
  "type": "Feature",
  "properties": {
    "iso:country":"US",
    "sg:address":"4930 S Loop 289",
    "sg:city":"Lubbock",
    "sg:classifiers":[
        {
            "category":"Retail",
            "subcategory":"Laundry & Dry Cleaning",
            "type":"Services"
        }
    ],
    "sg:phone":"+1 806 722 1777",
    "sg:postcode":"79414",
    "sg:province":"TX",
    "wof:name":"Rachaels II",
    "wof:placetype":"venue"
},
  "geometry": {"coordinates":[-101.916438,33.53388],"type":"Point"}
}