{
  "type": "Feature",
  "properties": {
    "iso:country":"US",
    "sg:address":"5003 John Stockbauer Dr",
    "sg:city":"Victoria",
    "sg:classifiers":[
        {
            "category":"Real Estate",
            "subcategory":"Real Estate Agent",
            "type":"Services"
        }
    ],
    "sg:phone":"+1 361 576 2353",
    "sg:postcode":"77904",
    "sg:province":"TX",
    "sg:website":"www.cornerstoneproperties.com",
    "wof:name":"Cornerstone Properties",
    "wof:placetype":"venue"
},
  "geometry": {"coordinates":[-96.949663,28.821667],"type":"Point"}
}