{
  "type": "Feature",
  "properties": {
    "iso:country":"US",
    "sg:address":"12035 State Hwy 249",
    "sg:city":"Houston",
    "sg:classifiers":[
        {
            "category":"Recreation",
            "type":"Entertainment"
        }
    ],
    "sg:phone":"+1 281 260 0458",
    "sg:postcode":"77086",
    "sg:province":"TX",
    "sg:tags":[
        "fortune"
    ],
    "wof:name":"Reading By Crystal",
    "wof:placetype":"venue"
},
  "geometry": {"coordinates":[-95.470035,29.904839],"type":"Point"}
}