{
  "type": "Feature",
  "properties": {
    "iso:country":"US",
    "sg:address":"119 N 1st St",
    "sg:city":"Lufkin",
    "sg:classifiers":[
        {
            "category":"Recreation",
            "type":"Entertainment"
        }
    ],
    "sg:phone":"+1 936 699 3547",
    "sg:postcode":"75901",
    "sg:province":"TX",
    "wof:name":"Tumble Time Cheerleading Co",
    "wof:placetype":"venue"
},
  "geometry": {"coordinates":[-94.728555,31.339915],"type":"Point"}
}