{
  "type": "Feature",
  "properties": {
    "iso:country":"US",
    "sg:address":"9402 Spring Ridge Cir",
    "sg:city":"Waco",
    "sg:classifiers":[
        {
            "category":"Real Estate",
            "subcategory":"Real Estate Agent",
            "type":"Services"
        }
    ],
    "sg:phone":"+1 254 772 0163",
    "sg:postcode":"76712",
    "sg:province":"TX",
    "wof:name":"Tommie Ludwig",
    "wof:placetype":"venue"
},
  "geometry": {"coordinates":[-97.21997500000001,31.485682],"type":"Point"}
}