{
  "type": "Feature",
  "properties": {
    "iso:country":"US",
    "sg:address":"1814 E Main St",
    "sg:city":"League City",
    "sg:classifiers":[
        {
            "category":"Building & Trades",
            "subcategory":"Construction",
            "type":"Services"
        }
    ],
    "sg:phone":"+1 281 316 2209",
    "sg:postcode":"77573",
    "sg:province":"TX",
    "sg:tags":[
        "designer",
        "dealer",
        "pool",
        "swimming"
    ],
    "sg:website":"www.primopools.com",
    "wof:name":"Primo Pools",
    "wof:placetype":"venue"
},
  "geometry": {"coordinates":[-95.07892699999999,29.520138],"type":"Point"}
}