{
  "type": "Feature",
  "properties": {
    "iso:country":"US",
    "sg:address":"1008 Linda Dr",
    "sg:city":"Daingerfield",
    "sg:classifiers":[
        {
            "category":"Wholesale",
            "subcategory":"Durable Goods & Equipment",
            "type":"Manufacturing & Wholesale Goods"
        }
    ],
    "sg:phone":"+1 903 645 4267",
    "sg:postcode":"75638",
    "sg:province":"TX",
    "sg:tags":[
        "professional"
    ],
    "wof:name":"Worker For Christ Christn Str",
    "wof:placetype":"venue"
},
  "geometry": {"coordinates":[-94.72172,33.022377],"type":"Point"}
}