{
  "type": "Feature",
  "properties": {
    "iso:country":"US",
    "sg:address":"1936 Strawberry Rd",
    "sg:city":"Pasadena",
    "sg:classifiers":[
        {
            "category":"Personal",
            "subcategory":"Barber",
            "type":"Services"
        }
    ],
    "sg:phone":"+1 713 920 2815",
    "sg:postcode":"77502",
    "sg:province":"TX",
    "wof:name":"Jo-Dean Hair Salon",
    "wof:placetype":"venue"
},
  "geometry": {"coordinates":[-95.193308,29.683836],"type":"Point"}
}