{
  "type": "Feature",
  "properties": {
    "iso:country":"US",
    "sg:address":"5237 Hutchinson Dr",
    "sg:city":"Austin",
    "sg:classifiers":[
        {
            "category":"Science Facility",
            "type":"Public Place"
        }
    ],
    "sg:phone":"+1 512 332 6968",
    "sg:postcode":"78723",
    "sg:province":"TX",
    "sg:tags":[
        "development",
        "laboratories-research"
    ],
    "wof:name":"Neothera Biosciences",
    "wof:placetype":"venue"
},
  "geometry": {"coordinates":[-97.66925000000001,30.289919],"type":"Point"}
}