{
  "type": "Feature",
  "properties": {
    "iso:country":"US",
    "sg:address":"13901 N Cabana St",
    "sg:city":"Corpus Christi",
    "sg:classifiers":[
        {
            "category":"Real Estate",
            "subcategory":"Real Estate Agent",
            "type":"Services"
        }
    ],
    "sg:phone":"+1 361 814 2334",
    "sg:postcode":"78418",
    "sg:province":"TX",
    "sg:tags":[
        "buyer",
        "broker"
    ],
    "wof:name":"Glenn Lyons & Assoc",
    "wof:placetype":"venue"
},
  "geometry": {"coordinates":[-97.22959400000001,27.624219],"type":"Point"}
}