{
  "type": "Feature",
  "properties": {
    "iso:country":"US",
    "sg:address":"6701 Lakewood Point Cove",
    "sg:city":"Austin",
    "sg:classifiers":[
        {
            "category":"Shopping",
            "subcategory":"Jewelry",
            "type":"Retail Goods"
        }
    ],
    "sg:phone":"+1 512 345 6146",
    "sg:postcode":"78750",
    "sg:province":"TX",
    "wof:name":"Elziabeth K Dunlap CPA",
    "wof:placetype":"venue"
},
  "geometry": {"coordinates":[-97.790802,30.380619],"type":"Point"}
}