{
  "type": "Feature",
  "properties": {
    "iso:country":"US",
    "sg:address":"112 S Bowser Rd",
    "sg:city":"Richardson",
    "sg:classifiers":[
        {
            "category":"Real Estate",
            "subcategory":"Real Estate Operator",
            "type":"Services"
        }
    ],
    "sg:phone":"+1 972 235 5419",
    "sg:postcode":"75081",
    "sg:province":"TX",
    "sg:tags":[
        "apartment"
    ],
    "wof:name":"Sandpiper Apartments",
    "wof:placetype":"venue"
},
  "geometry": {"coordinates":[-96.71366,32.945735],"type":"Point"}
}