{
  "type": "Feature",
  "properties": {
    "iso:country":"US",
    "sg:address":"24910 Kuykendahl Rd",
    "sg:city":"Tomball",
    "sg:phone":"+1 281 205 0220",
    "sg:postcode":"77375",
    "sg:province":"TX",
    "sg:website":"http://houston.citysearch.com/profile/external/43116993/tomball_tx/sozo_hair_design.html?publisher=yellowpages&reference_id=1&placement=ypwebsitemip",
    "wof:name":"Sozo Hair Design",
    "wof:placetype":"venue"
},
  "geometry": {"coordinates":[-95.55421699999999,30.121308],"type":"Point"}
}