{
  "type": "Feature",
  "properties": {
    "iso:country":"US",
    "sg:address":"1425 Co Rd 354",
    "sg:city":"Gatesville",
    "sg:classifiers":[
        {
            "category":"Wholesale",
            "subcategory":"Farm Supplies",
            "type":"Manufacturing & Wholesale Goods"
        }
    ],
    "sg:phone":"+1 254 986 8179",
    "sg:postcode":"76528",
    "sg:province":"TX",
    "sg:tags":[
        "corn",
        "livestock"
    ],
    "wof:name":"Victor Dutschmann",
    "wof:placetype":"venue"
},
  "geometry": {"coordinates":[-97.572152,31.257208],"type":"Point"}
}