{
  "type": "Feature",
  "properties": {
    "iso:country":"US",
    "sg:address":"501 Gay Dr",
    "sg:city":"Conroe",
    "sg:classifiers":[
        {
            "category":"Organizations",
            "subcategory":"Professional Association",
            "type":"Services"
        }
    ],
    "sg:phone":"+1 936 494 1134",
    "sg:postcode":"77301",
    "sg:province":"TX",
    "wof:name":"Texas Insurance Federation",
    "wof:placetype":"venue"
},
  "geometry": {"coordinates":[-95.461996,30.328595],"type":"Point"}
}