{
  "type": "Feature",
  "properties": {
    "iso:country":"US",
    "sg:address":"3100 Pine Needle Dr",
    "sg:city":"Mckinney",
    "sg:classifiers":[
        {
            "category":"Building & Trades",
            "subcategory":"Equipment Rental",
            "type":"Services"
        }
    ],
    "sg:phone":"+1 972 886 1108",
    "sg:postcode":"75070",
    "sg:province":"TX",
    "sg:tags":[
        "yard",
        "leasing",
        "store"
    ],
    "wof:name":"Metroplex Leasing Co",
    "wof:placetype":"venue"
},
  "geometry": {"coordinates":[-96.69074999999999,33.17247],"type":"Point"}
}