{
  "type": "Feature",
  "properties": {
    "iso:country":"US",
    "sg:address":"3618 Loma Dr",
    "sg:city":"Odessa",
    "sg:classifiers":[
        {
            "category":"Retail",
            "subcategory":"Repair Shop",
            "type":"Services"
        }
    ],
    "sg:phone":"+1 432 368 4600",
    "sg:postcode":"79762",
    "sg:province":"TX",
    "wof:name":"James Hammond",
    "wof:placetype":"venue"
},
  "geometry": {"coordinates":[-102.356137,31.88345],"type":"Point"}
}