{
  "type": "Feature",
  "properties": {
    "iso:country":"US",
    "sg:address":"9207 San Pedro Ave",
    "sg:city":"San Antonio",
    "sg:classifiers":[
        {
            "category":"Autos & Motor Vehicles",
            "subcategory":"Automobile Sales",
            "type":"Retail Goods"
        }
    ],
    "sg:phone":"+1 210 341 8766",
    "sg:postcode":"78216",
    "sg:province":"TX",
    "wof:name":"North Park Specialty Used Cars",
    "wof:placetype":"venue"
},
  "geometry": {"coordinates":[-98.498209,29.527717],"type":"Point"}
}