{
  "type": "Feature",
  "properties": {
    "iso:country":"US",
    "sg:address":"3309 Meadow Creek Ln",
    "sg:city":"Temple",
    "sg:classifiers":[
        {
            "category":"Building & Trades",
            "subcategory":"Construction",
            "type":"Services"
        }
    ],
    "sg:phone":"+1 254 742 1888",
    "sg:postcode":"76504",
    "sg:province":"TX",
    "sg:tags":[
        "home",
        "builder"
    ],
    "wof:name":"Witlyn Homes",
    "wof:placetype":"venue"
},
  "geometry": {"coordinates":[-97.375197,31.109974],"type":"Point"}
}