{
  "type": "Feature",
  "properties": {
    "iso:country":"US",
    "sg:address":"573 Memorial Plz",
    "sg:city":"Burleson",
    "sg:classifiers":[
        {
            "category":"Wholesale",
            "subcategory":"Chemicals & Plastics",
            "type":"Manufacturing & Wholesale Goods"
        }
    ],
    "sg:phone":"+1 817 447 0828",
    "sg:postcode":"76028",
    "sg:province":"TX",
    "sg:tags":[
        "concrete",
        "additive"
    ],
    "wof:name":"International Chem-Crete Corp",
    "wof:placetype":"venue"
},
  "geometry": {"coordinates":[-97.30708,32.538767],"type":"Point"}
}