{
  "type": "Feature",
  "properties": {
    "iso:country":"US",
    "sg:address":"2508 Little Rd",
    "sg:city":"Arlington",
    "sg:classifiers":[
        {
            "category":"Professional",
            "subcategory":"Computer Services",
            "type":"Services"
        }
    ],
    "sg:phone":"+1 817 654 0346",
    "sg:postcode":"76016",
    "sg:province":"TX",
    "sg:tags":[
        "consultant",
        "designer",
        "datum",
        "system"
    ],
    "wof:name":"Computer Information Resources",
    "wof:placetype":"venue"
},
  "geometry": {"coordinates":[-97.179327,32.703838],"type":"Point"}
}