{
  "type": "Feature",
  "properties": {
    "iso:country":"US",
    "sg:address":"418 22nd St",
    "sg:city":"Galveston",
    "sg:classifiers":[
        {
            "category":"Shopping",
            "subcategory":"Used Merchandise",
            "type":"Retail Goods"
        }
    ],
    "sg:phone":"+1 409 763 0717",
    "sg:postcode":"77550",
    "sg:province":"TX",
    "wof:name":"LA Maison Rouge",
    "wof:placetype":"venue"
},
  "geometry": {"coordinates":[-94.792529,29.305693],"type":"Point"}
}