{
  "type": "Feature",
  "properties": {
    "iso:country":"US",
    "sg:address":"308 E South St",
    "sg:city":"New Boston",
    "sg:classifiers":[
        {
            "category":"Retail",
            "subcategory":"Auto Repair",
            "type":"Services"
        }
    ],
    "sg:phone":"+1 903 628 2477",
    "sg:postcode":"75570",
    "sg:province":"TX",
    "sg:tags":[
        "body"
    ],
    "wof:name":"Ronnies Paint & Body Shop",
    "wof:placetype":"venue"
},
  "geometry": {"coordinates":[-94.41304100000001,33.457463],"type":"Point"}
}