{
  "type": "Feature",
  "properties": {
    "iso:country":"US",
    "sg:address":"5823 Knightsbridge Dr",
    "sg:city":"Dallas",
    "sg:classifiers":[
        {
            "category":"Banks & Credit Unions",
            "subcategory":"Investment Brokerage",
            "type":"Services"
        }
    ],
    "sg:phone":"+1 972 380 0967",
    "sg:postcode":"75252",
    "sg:province":"TX",
    "sg:tags":[
        "security"
    ],
    "wof:name":"King Knightsbridge",
    "wof:placetype":"venue"
},
  "geometry": {"coordinates":[-96.806388,33.000541],"type":"Point"}
}