{
  "type": "Feature",
  "properties": {
    "iso:country":"US",
    "sg:address":"320 SW 3rd Ave",
    "sg:city":"Amarillo",
    "sg:classifiers":[
        {
            "category":"Shopping",
            "subcategory":"Florist",
            "type":"Retail Goods"
        }
    ],
    "sg:phone":"+1 806 379 6430",
    "sg:postcode":"79101",
    "sg:province":"AR",
    "wof:name":"Two Roses",
    "wof:placetype":"venue"
},
  "geometry": {"coordinates":[-101.83907000000001,35.211104],"type":"Point"}
}