{
  "type": "Feature",
  "properties": {
    "iso:country":"US",
    "sg:address":"335 League St S",
    "sg:city":"Sulphur Springs",
    "sg:classifiers":[
        {
            "category":"Autos & Motor Vehicles",
            "subcategory":"Automobile Sales",
            "type":"Retail Goods"
        }
    ],
    "sg:phone":"+1 903 885 4023",
    "sg:postcode":"75482",
    "sg:province":"TX",
    "sg:tags":[
        "car",
        "used",
        "dealer"
    ],
    "wof:name":"Gregory T N Used Cars",
    "wof:placetype":"venue"
},
  "geometry": {"coordinates":[-95.61284999999999,33.128455],"type":"Point"}
}