{
  "type": "Feature",
  "properties": {
    "iso:country":"US",
    "sg:address":"2740 Dallas Pkwy Ste 250",
    "sg:city":"Plano",
    "sg:classifiers":[
        {
            "category":"Professional",
            "subcategory":"Computer Services",
            "type":"Services"
        }
    ],
    "sg:phone":"+1 972 543 2110",
    "sg:postcode":"75093",
    "sg:province":"TX",
    "sg:tags":[
        "repair"
    ],
    "wof:name":"Pacific Technology Services",
    "wof:placetype":"venue"
},
  "geometry": {"coordinates":[-96.829201,33.0382],"type":"Point"}
}