{
  "type": "Feature",
  "properties": {
    "iso:country":"US",
    "sg:address":"506 Glascow St",
    "sg:city":"Victoria",
    "sg:classifiers":[
        {
            "category":"Banks & Credit Unions",
            "subcategory":"Investment Brokerage",
            "type":"Services"
        }
    ],
    "sg:phone":"+1 361 572 9391",
    "sg:postcode":"77904",
    "sg:province":"TX",
    "sg:tags":[
        "retirement",
        "planning"
    ],
    "wof:name":"Advantage Investment Svc",
    "wof:placetype":"venue"
},
  "geometry": {"coordinates":[-97.002334,28.87835],"type":"Point"}
}