{
  "type": "Feature",
  "properties": {
    "iso:country":"US",
    "sg:address":"285 S Archie St",
    "sg:city":"Vidor",
    "sg:classifiers":[
        {
            "category":"Government",
            "subcategory":"Post Office",
            "type":"Public Place"
        }
    ],
    "sg:phone":"+1 409 000 1111",
    "sg:postcode":"77662",
    "sg:province":"TX",
    "wof:name":"US Post Office",
    "wof:placetype":"venue"
},
  "geometry": {"coordinates":[-94.015045,30.126292],"type":"Point"}
}