{
  "type": "Feature",
  "properties": {
    "iso:country":"US",
    "sg:address":"515 W Mayfield Rd",
    "sg:city":"Arlington",
    "sg:classifiers":[
        {
            "category":"Health Services",
            "subcategory":"Podiatrist",
            "type":"Services"
        }
    ],
    "sg:phone":"+1 817 492 9500",
    "sg:postcode":"76014",
    "sg:province":"TX",
    "sg:tags":[
        "clinic"
    ],
    "wof:name":"Arlington Foot Center PA",
    "wof:placetype":"venue"
},
  "geometry": {"coordinates":[-97.113438,32.691068],"type":"Point"}
}