{
  "type": "Feature",
  "properties": {
    "iso:country":"US",
    "sg:address":"22609 Briarcliff Dr",
    "sg:city":"Spicewood",
    "sg:classifiers":[
        {
            "category":"Professional",
            "subcategory":"Computer Services",
            "type":"Services"
        }
    ],
    "sg:phone":"+1 512 264 3137",
    "sg:postcode":"78669",
    "sg:province":"TX",
    "sg:tags":[
        "related"
    ],
    "wof:name":"Khitomer Solutions Inc",
    "wof:placetype":"venue"
},
  "geometry": {"coordinates":[-98.05641300000001,30.405281],"type":"Point"}
}