{
  "type": "Feature",
  "properties": {
    "iso:country":"US",
    "sg:address":"211 S 25 Mile Ave",
    "sg:city":"Hereford",
    "sg:classifiers":[
        {
            "category":"Shopping",
            "subcategory":"Used Merchandise",
            "type":"Retail Goods"
        }
    ],
    "sg:phone":"+1 806 364 8386",
    "sg:postcode":"79045",
    "sg:province":"TX",
    "wof:name":"Gold Nuggett Pawn Shop",
    "wof:placetype":"venue"
},
  "geometry": {"coordinates":[-102.405834,34.812419],"type":"Point"}
}