{
  "type": "Feature",
  "properties": {
    "iso:country":"US",
    "sg:address":"2307 Woven Wood Ln",
    "sg:city":"Richmond",
    "sg:classifiers":[
        {
            "category":"Real Estate",
            "subcategory":"Real Estate Services",
            "type":"Services"
        }
    ],
    "sg:phone":"+1 281 342 2546",
    "sg:postcode":"77469",
    "sg:province":"TX",
    "sg:tags":[
        "abstract",
        "title"
    ],
    "wof:name":"Margie Beegle Sales",
    "wof:placetype":"venue"
},
  "geometry": {"coordinates":[-95.72648700000001,29.61397],"type":"Point"}
}