{
  "type": "Feature",
  "properties": {
    "iso:country":"US",
    "sg:address":"2890 Lewis Ln",
    "sg:city":"Paris",
    "sg:classifiers":[
        {
            "category":"Health Services",
            "subcategory":"Doctor",
            "type":"Services"
        }
    ],
    "sg:phone":"+1 903 785 4166",
    "sg:postcode":"75460",
    "sg:province":"TX",
    "sg:tags":[
        "physician",
        "surgeon"
    ],
    "wof:name":"Paris Eye Physicians-Surgeons",
    "wof:placetype":"venue"
},
  "geometry": {"coordinates":[-95.55046299999999,33.687962],"type":"Point"}
}