{
  "type": "Feature",
  "properties": {
    "iso:country":"US",
    "sg:address":"607 S Chestnut St",
    "sg:city":"Lufkin",
    "sg:classifiers":[
        {
            "category":"Social Services",
            "subcategory":"Child Care",
            "type":"Services"
        }
    ],
    "sg:phone":"+1 936 632 6154",
    "sg:postcode":"75901",
    "sg:province":"TX",
    "wof:name":"Child Care Svc",
    "wof:placetype":"venue"
},
  "geometry": {"coordinates":[-94.717135,31.330728],"type":"Point"}
}