{
  "type": "Feature",
  "properties": {
    "iso:country":"US",
    "sg:address":"957 E Hidalgo Ave",
    "sg:city":"Raymondville",
    "sg:classifiers":[
        {
            "category":"Freight",
            "type":"Transportation"
        }
    ],
    "sg:phone":"+1 956 689 3600",
    "sg:postcode":"78580",
    "sg:province":"TX",
    "sg:tags":[
        "commercial",
        "storage"
    ],
    "wof:name":"Storage Place",
    "wof:placetype":"venue"
},
  "geometry": {"coordinates":[-97.77172899999999,26.482051],"type":"Point"}
}