{
  "type": "Feature",
  "properties": {
    "iso:country":"US",
    "sg:address":"400 Joliet St",
    "sg:city":"Plainview",
    "sg:classifiers":[
        {
            "category":"Manufacturing",
            "subcategory":"Glass & Minerals",
            "type":"Manufacturing & Wholesale Goods"
        },
        {
            "category":"Shopping",
            "type":"Retail Goods"
        }
    ],
    "sg:phone":"+1 806 296 2953",
    "sg:postcode":"79072",
    "sg:province":"TX",
    "sg:tags":[
        "funeral",
        "merchandise",
        "monument"
    ],
    "wof:name":"Sadler Monument Works Inc",
    "wof:placetype":"venue"
},
  "geometry": {"coordinates":[-101.715575,34.184253],"type":"Point"}
}