{
  "type": "Feature",
  "properties": {
    "iso:country":"US",
    "sg:address":"2718 Sherman St",
    "sg:city":"Grand Prairie",
    "sg:classifiers":[
        {
            "category":"Real Estate",
            "subcategory":"Real Estate Operator",
            "type":"Services"
        }
    ],
    "sg:phone":"+1 972 606 1735",
    "sg:postcode":"75051",
    "sg:province":"TX",
    "sg:tags":[
        "building",
        "apartment"
    ],
    "wof:name":"Goldbriar Apartments",
    "wof:placetype":"venue"
},
  "geometry": {"coordinates":[-97.048258,32.735167],"type":"Point"}
}