{
  "type": "Feature",
  "properties": {
    "iso:country":"US",
    "sg:address":"7509 Southwick Dr",
    "sg:city":"Garland",
    "sg:phone":"+1 972 414 6277",
    "sg:postcode":"75044",
    "sg:province":"TX",
    "sg:tags":[
        "irrigation",
        "system"
    ],
    "wof:name":"Churchill Irrigation",
    "wof:placetype":"venue"
},
  "geometry": {"coordinates":[-96.669138,32.982286],"type":"Point"}
}