{
  "type": "Feature",
  "properties": {
    "iso:country":"US",
    "sg:address":"103 Oak Creek Dr",
    "sg:city":"La Vernia",
    "sg:classifiers":[
        {
            "category":"Building & Trades",
            "subcategory":"Construction",
            "type":"Services"
        }
    ],
    "sg:phone":"+1 830 253 8519",
    "sg:postcode":"78121",
    "sg:province":"TX",
    "sg:tags":[
        "carpentry",
        "contractor"
    ],
    "wof:name":"Country Woodcrafts",
    "wof:placetype":"venue"
},
  "geometry": {"coordinates":[-98.115967,29.33261],"type":"Point"}
}