{
  "type": "Feature",
  "properties": {
    "iso:country":"US",
    "sg:address":"5514 Indigo St",
    "sg:city":"Houston",
    "sg:classifiers":[
        {
            "category":"Education",
            "subcategory":"Special Training",
            "type":"Public Place"
        }
    ],
    "sg:phone":"+1 713 663 7086",
    "sg:postcode":"77096",
    "sg:province":"TX",
    "wof:name":"Russian Connection",
    "wof:placetype":"venue"
},
  "geometry": {"coordinates":[-95.48612,29.686204],"type":"Point"}
}