{
  "type": "Feature",
  "properties": {
    "iso:country":"US",
    "sg:address":"133 N Henry St",
    "sg:city":"Lancaster",
    "sg:classifiers":[
        {
            "category":"Professional",
            "subcategory":"Management & Consulting",
            "type":"Services"
        }
    ],
    "sg:phone":"+1 972 218 7323",
    "sg:postcode":"75146",
    "sg:province":"TX",
    "wof:name":"Energy Worldnet Inc",
    "wof:placetype":"venue"
},
  "geometry": {"coordinates":[-96.755184,32.592663],"type":"Point"}
}