{
  "type": "Feature",
  "properties": {
    "iso:country":"US",
    "sg:address":"640 Copperas Rd",
    "sg:city":"Sadler",
    "sg:classifiers":[
        {
            "category":"Wholesale",
            "subcategory":"Non-durable Goods",
            "type":"Manufacturing & Wholesale Goods"
        }
    ],
    "sg:phone":"+1 903 564 9674",
    "sg:postcode":"76264",
    "sg:province":"TX",
    "sg:tags":[
        "dry",
        "goods-wholesale"
    ],
    "wof:name":"Ft Copperas Reloading & Supply",
    "wof:placetype":"venue"
},
  "geometry": {"coordinates":[-96.879402,33.740002],"type":"Point"}
}