{
  "type": "Feature",
  "properties": {
    "iso:country":"US",
    "sg:address":"4628 University Ave",
    "sg:city":"Wichita Falls",
    "sg:classifiers":[
        {
            "category":"Wholesale",
            "subcategory":"Vending Machines",
            "type":"Manufacturing & Wholesale Goods"
        }
    ],
    "sg:phone":"+1 940 691 0875",
    "sg:postcode":"76308",
    "sg:province":"TX",
    "sg:tags":[
        "operator"
    ],
    "wof:name":"Break Time Vending",
    "wof:placetype":"venue"
},
  "geometry": {"coordinates":[-98.558504,33.864184],"type":"Point"}
}