{
  "type": "Feature",
  "properties": {
    "iso:country":"US",
    "sg:address":"1200 Hatton St",
    "sg:city":"Waco",
    "sg:classifiers":[
        {
            "category":"Real Estate",
            "subcategory":"Real Estate Agent",
            "type":"Services"
        }
    ],
    "sg:phone":"+1 254 799 6852",
    "sg:postcode":"76704",
    "sg:province":"TX",
    "wof:name":"J Properties",
    "wof:placetype":"venue"
},
  "geometry": {"coordinates":[-97.11935800000001,31.58577],"type":"Point"}
}