{
  "type": "Feature",
  "properties": {
    "iso:country":"US",
    "sg:address":"10710 McPherson Ave",
    "sg:city":"Laredo",
    "sg:classifiers":[
        {
            "category":"Personal",
            "subcategory":"Hair Removal",
            "type":"Services"
        }
    ],
    "sg:phone":"+1 956 753 6262",
    "sg:postcode":"78045",
    "sg:province":"TX",
    "sg:tags":[
        "removing"
    ],
    "wof:name":"Zoe Body Care",
    "wof:placetype":"venue"
},
  "geometry": {"coordinates":[-99.476446,27.607684],"type":"Point"}
}