{
  "type": "Feature",
  "properties": {
    "iso:country":"US",
    "sg:address":"316 Hudson Ave",
    "sg:city":"Crowley",
    "sg:classifiers":[
        {
            "category":"Banks & Credit Unions",
            "subcategory":"Financial Services",
            "type":"Services"
        }
    ],
    "sg:phone":"+1 817 297 4106",
    "sg:postcode":"76036",
    "sg:province":"TX",
    "sg:tags":[
        "investor"
    ],
    "wof:name":"Smart Investments",
    "wof:placetype":"venue"
},
  "geometry": {"coordinates":[-97.35553,32.574417],"type":"Point"}
}