{
  "type": "Feature",
  "properties": {
    "iso:country":"US",
    "sg:address":"4025 Tealwood",
    "sg:city":"Austin",
    "sg:classifiers":[
        {
            "category":"Social Services",
            "subcategory":"Child Care",
            "type":"Services"
        }
    ],
    "sg:phone":"+1 512 345 3439",
    "sg:postcode":"78731",
    "sg:province":"TX",
    "sg:tags":[
        "day"
    ],
    "wof:name":"Casa Mntssr Chld Dev",
    "wof:placetype":"venue"
},
  "geometry": {"coordinates":[-97.759998,30.370108],"type":"Point"}
}