{
  "type": "Feature",
  "properties": {
    "iso:country":"US",
    "sg:address":"211 W 2nd Ave",
    "sg:city":"Corsicana",
    "sg:classifiers":[
        {
            "category":"Retail",
            "subcategory":"Auto Repair",
            "type":"Services"
        }
    ],
    "sg:phone":"+1 903 872 5452",
    "sg:postcode":"75110",
    "sg:province":"TX",
    "sg:tags":[
        "body",
        "repairing",
        "shop",
        "automobile",
        "paint",
        "painting"
    ],
    "wof:name":"Nicholson Paint & Body",
    "wof:placetype":"venue"
},
  "geometry": {"coordinates":[-96.467409,32.096556],"type":"Point"}
}