{
  "type": "Feature",
  "properties": {
    "iso:country":"US",
    "sg:address":"7598 N Mesa St",
    "sg:city":"El Paso",
    "sg:classifiers":[
        {
            "category":"Health Services",
            "subcategory":"Doctor",
            "type":"Services"
        }
    ],
    "sg:phone":"+1 915 845 7979",
    "sg:postcode":"79912",
    "sg:province":"TX",
    "wof:name":"Implant Prdntal Spcialist Pllc",
    "wof:placetype":"venue"
},
  "geometry": {"coordinates":[-106.561925,31.837961],"type":"Point"}
}