{
  "type": "Feature",
  "properties": {
    "iso:country":"US",
    "sg:address":"1037 W Ferguson Ave",
    "sg:city":"Pharr",
    "sg:classifiers":[
        {
            "category":"Retail",
            "subcategory":"Repair Shop",
            "type":"Services"
        }
    ],
    "sg:phone":"+1 956 787 6471",
    "sg:postcode":"78577",
    "sg:province":"TX",
    "sg:tags":[
        "refrigerating"
    ],
    "wof:name":"Dan's Refrigeration Svc",
    "wof:placetype":"venue"
},
  "geometry": {"coordinates":[-98.19648599999999,26.213597],"type":"Point"}
}