{
  "type": "Feature",
  "properties": {
    "iso:country":"US",
    "sg:address":"1719 Sanez",
    "sg:city":"San Antonio",
    "sg:classifiers":[
        {
            "category":"Shopping",
            "subcategory":"Gifts & Souvenirs",
            "type":"Retail Goods"
        }
    ],
    "sg:phone":"+1 210 627 2699",
    "sg:postcode":"78214",
    "sg:province":"TX",
    "wof:name":"Bubis Balloons & Gifts",
    "wof:placetype":"venue"
},
  "geometry": {"coordinates":[-98.47049199999999,29.319392],"type":"Point"}
}