{
  "type": "Feature",
  "properties": {
    "iso:country":"US",
    "sg:address":"1550 Norwood Dr",
    "sg:city":"Hurst",
    "sg:classifiers":[
        {
            "category":"Professional",
            "subcategory":"Lawyer & Legal Services",
            "type":"Services"
        }
    ],
    "sg:phone":"+1 817 268 4007",
    "sg:postcode":"76054",
    "sg:province":"TX",
    "sg:tags":[
        "attorney"
    ],
    "wof:name":"Bruce L Mansfield",
    "wof:placetype":"venue"
},
  "geometry": {"coordinates":[-97.167641,32.840957],"type":"Point"}
}