{
  "type": "Feature",
  "properties": {
    "iso:country":"US",
    "sg:address":"3360 Wiley Post Rd",
    "sg:city":"Carrollton",
    "sg:classifiers":[
        {
            "category":"Retail",
            "subcategory":"Auto Repair",
            "type":"Services"
        }
    ],
    "sg:phone":"+1 972 308 0141",
    "sg:postcode":"75006",
    "sg:province":"TX",
    "sg:tags":[
        "body"
    ],
    "wof:name":"Venture Enterprises Inc",
    "wof:placetype":"venue"
},
  "geometry": {"coordinates":[-96.845907,32.960459],"type":"Point"}
}