{
  "type": "Feature",
  "properties": {
    "iso:country":"US",
    "sg:address":"3021 Kirby Dr",
    "sg:city":"Houston",
    "sg:classifiers":[
        {
            "category":"Arts & Performance",
            "subcategory":"Art Gallery",
            "type":"Entertainment"
        },
        {
            "category":"Shopping",
            "subcategory":"Antiques",
            "type":"Retail Goods"
        }
    ],
    "sg:phone":"+1 713 622 7531",
    "sg:postcode":"77098",
    "sg:province":"TX",
    "sg:website":"www.theantiquarium.com",
    "wof:name":"Antiquarium Antique Print & Map Gallery",
    "wof:placetype":"venue"
},
  "geometry": {"coordinates":[-95.41860200000001,29.737801],"type":"Point"}
}