{
  "type": "Feature",
  "properties": {
    "iso:country":"US",
    "sg:address":"1801 S Beckley Ave",
    "sg:city":"Dallas",
    "sg:classifiers":[
        {
            "category":"Retail",
            "subcategory":"Auto Repair",
            "type":"Services"
        }
    ],
    "sg:phone":"+1 214 941 1273",
    "sg:postcode":"75224",
    "sg:province":"TX",
    "sg:tags":[
        "automotive"
    ],
    "wof:name":"Parras Mufflers & Radiators",
    "wof:placetype":"venue"
},
  "geometry": {"coordinates":[-96.822813,32.725142],"type":"Point"}
}