{
  "type": "Feature",
  "properties": {
    "iso:country":"US",
    "sg:address":"121 S Broadway Ave",
    "sg:city":"Tyler",
    "sg:classifiers":[
        {
            "category":"Banks & Credit Unions",
            "subcategory":"Financial Services",
            "type":"Services"
        }
    ],
    "sg:phone":"+1 903 592 0826",
    "sg:postcode":"75702",
    "sg:province":"TX",
    "sg:tags":[
        "oil",
        "investment"
    ],
    "wof:name":"Birdsonggabriel Oil Co",
    "wof:placetype":"venue"
},
  "geometry": {"coordinates":[-95.300747,32.34989],"type":"Point"}
}