{
  "type": "Feature",
  "properties": {
    "iso:country":"US",
    "sg:address":"828 E Irving Blvd",
    "sg:city":"Irving",
    "sg:classifiers":[
        {
            "category":"Shopping",
            "subcategory":"Department Store",
            "type":"Retail Goods"
        }
    ],
    "sg:phone":"+1 972 438 5999",
    "sg:postcode":"75060",
    "sg:province":"TX",
    "wof:name":"Magic Dollar",
    "wof:placetype":"venue"
},
  "geometry": {"coordinates":[-96.935929,32.812116],"type":"Point"}
}