{
  "type": "Feature",
  "properties": {
    "iso:country":"US",
    "sg:address":"4709 State Hwy 121",
    "sg:city":"The Colony",
    "sg:classifiers":[
        {
            "category":"Professional",
            "subcategory":"Advertising",
            "type":"Services"
        }
    ],
    "sg:phone":"+1 972 625 7600",
    "sg:postcode":"75056",
    "sg:province":"TX",
    "sg:tags":[
        "mail"
    ],
    "sg:website":"www.mailinglistconnection.com",
    "wof:name":"Mailing List Connection",
    "wof:placetype":"venue"
},
  "geometry": {"coordinates":[-96.876869,33.071835],"type":"Point"}
}