{
  "type": "Feature",
  "properties": {
    "iso:country":"US",
    "sg:address":"310 Hawthorne St",
    "sg:city":"Abilene",
    "sg:classifiers":[
        {
            "category":"Retail",
            "subcategory":"Laundry & Dry Cleaning",
            "type":"Services"
        }
    ],
    "sg:phone":"+1 325 695 4809",
    "sg:postcode":"79605",
    "sg:province":"TX",
    "wof:name":"Roberts Carpet Cleaning",
    "wof:placetype":"venue"
},
  "geometry": {"coordinates":[-99.77551,32.447784],"type":"Point"}
}