{
  "type": "Feature",
  "properties": {
    "iso:country":"US",
    "sg:address":"5212 57th St",
    "sg:city":"Lubbock",
    "sg:classifiers":[
        {
            "category":"Restaurant",
            "type":"Food & Drink"
        }
    ],
    "sg:phone":"+1 806 785 1720",
    "sg:postcode":"79414",
    "sg:province":"TX",
    "wof:name":"Gas Light",
    "wof:placetype":"venue"
},
  "geometry": {"coordinates":[-101.92388200000001,33.542431],"type":"Point"}
}