{
  "type": "Feature",
  "properties": {
    "iso:country":"US",
    "sg:address":"900 W 5th St",
    "sg:city":"Plainview",
    "sg:classifiers":[
        {
            "category":"Building & Trades",
            "subcategory":"Equipment Rental",
            "type":"Services"
        }
    ],
    "sg:phone":"+1 806 293 8020",
    "sg:postcode":"79072",
    "sg:province":"TX",
    "sg:tags":[
        "household",
        "appliance"
    ],
    "wof:name":"Ideal Rentals & Sales",
    "wof:placetype":"venue"
},
  "geometry": {"coordinates":[-101.712931,34.184356],"type":"Point"}
}