{
  "type": "Feature",
  "properties": {
    "iso:country":"US",
    "sg:address":"1810 FM 89",
    "sg:city":"Abilene",
    "sg:classifiers":[
        {
            "category":"Building & Trades",
            "subcategory":"Pest Control",
            "type":"Services"
        }
    ],
    "sg:phone":"+1 325 572 3744",
    "sg:postcode":"79606",
    "sg:province":"TX",
    "wof:name":"Jim's Pest Control",
    "wof:placetype":"venue"
},
  "geometry": {"coordinates":[-99.81724,32.300031],"type":"Point"}
}