{
  "type": "Feature",
  "properties": {
    "iso:country":"US",
    "sg:address":"247 Live Oak St",
    "sg:city":"Marlin",
    "sg:classifiers":[
        {
            "category":"Real Estate",
            "subcategory":"Surveying",
            "type":"Services"
        }
    ],
    "sg:phone":"+1 254 803 2999",
    "sg:postcode":"76661",
    "sg:province":"TX",
    "sg:tags":[
        "surveyor"
    ],
    "wof:name":"Tibbit & Meyer Surveying",
    "wof:placetype":"venue"
},
  "geometry": {"coordinates":[-96.895064,31.306371],"type":"Point"}
}