{
  "type": "Feature",
  "properties": {
    "iso:country":"US",
    "sg:address":"1803 Milam St",
    "sg:city":"Uvalde",
    "sg:classifiers":[
        {
            "category":"Restaurant",
            "type":"Food & Drink"
        }
    ],
    "sg:phone":"+1 830 279 0339",
    "sg:postcode":"78801",
    "sg:province":"TX",
    "wof:name":"Aguilar's Taco & Bakery",
    "wof:placetype":"venue"
},
  "geometry": {"coordinates":[-99.79325900000001,29.232195],"type":"Point"}
}