{
  "type": "Feature",
  "properties": {
    "iso:country":"US",
    "sg:address":"300 W Sandy Lake Rd",
    "sg:city":"Coppell",
    "sg:classifiers":[
        {
            "category":"Home & Garden",
            "subcategory":"Building Materials",
            "type":"Retail Goods"
        },
        {
            "category":"Manufacturing",
            "subcategory":"Building Materials",
            "type":"Manufacturing & Wholesale Goods"
        }
    ],
    "sg:phone":"+1 972 471 7653",
    "sg:postcode":"75019",
    "sg:province":"TX",
    "sg:tags":[
        "materials-wholesale",
        "manufacturer"
    ],
    "wof:name":"Barney Barnett",
    "wof:placetype":"venue"
},
  "geometry": {"coordinates":[-97.000488,32.969601],"type":"Point"}
}