{
  "type": "Feature",
  "properties": {
    "iso:country":"US",
    "sg:address":"1509 Wade Dr",
    "sg:city":"Bedford",
    "sg:classifiers":[
        {
            "category":"Wholesale",
            "subcategory":"Machinery & Supplies",
            "type":"Manufacturing & Wholesale Goods"
        }
    ],
    "sg:phone":"+1 817 280 9392",
    "sg:postcode":"76022",
    "sg:province":"TX",
    "sg:tags":[
        "equipment",
        "welding"
    ],
    "wof:name":"Ultra Alloys",
    "wof:placetype":"venue"
},
  "geometry": {"coordinates":[-97.15454800000001,32.833527],"type":"Point"}
}