{
  "type": "Feature",
  "properties": {
    "iso:country":"US",
    "sg:address":"22503 Trailwood Rd",
    "sg:city":"Flint",
    "sg:classifiers":[
        {
            "category":"Professional",
            "type":"Services"
        }
    ],
    "sg:phone":"+1 903 825 3069",
    "sg:postcode":"75762",
    "sg:province":"TX",
    "wof:name":"Betty McDonnald",
    "wof:placetype":"venue"
},
  "geometry": {"coordinates":[-95.45564400000001,32.154053],"type":"Point"}
}