{
  "type": "Feature",
  "properties": {
    "iso:country":"US",
    "sg:address":"608 W I- 30",
    "sg:city":"Garland",
    "sg:classifiers":[
        {
            "category":"Retail",
            "subcategory":"Veterinary Services",
            "type":"Services"
        },
        {
            "category":"Shopping",
            "type":"Retail Goods"
        }
    ],
    "sg:phone":"+1 972 423 7387",
    "sg:postcode":"75043",
    "sg:province":"TX",
    "sg:tags":[
        "pet",
        "food",
        "supply"
    ],
    "sg:website":"www.petmobile.com",
    "wof:name":"Pet Mobile Pet Hospital",
    "wof:placetype":"venue"
},
  "geometry": {"coordinates":[-96.60144099999999,32.837347],"type":"Point"}
}