{
  "type": "Feature",
  "properties": {
    "iso:country":"US",
    "sg:address":"101 Cooke St",
    "sg:city":"Nocona",
    "sg:classifiers":[
        {
            "category":"Government",
            "subcategory":"Office",
            "type":"Public Place"
        }
    ],
    "sg:phone":"+1 940 825 5323",
    "sg:postcode":"76255",
    "sg:province":"TX",
    "sg:tags":[
        "village"
    ],
    "wof:name":"Crimebusters",
    "wof:placetype":"venue"
},
  "geometry": {"coordinates":[-97.725955,33.788965],"type":"Point"}
}