{
  "type": "Feature",
  "properties": {
    "iso:country":"US",
    "sg:address":"1110 Mill River Dr",
    "sg:city":"Garland",
    "sg:classifiers":[
        {
            "category":"Organizations",
            "subcategory":"Religious Organization",
            "type":"Services"
        }
    ],
    "sg:phone":"+1 972 681 9003",
    "sg:postcode":"75043",
    "sg:province":"TX",
    "wof:name":"Butler Ministries",
    "wof:placetype":"venue"
},
  "geometry": {"coordinates":[-96.641441,32.854477],"type":"Point"}
}