{
  "type": "Feature",
  "properties": {
    "iso:country":"US",
    "sg:address":"5919 Autumn Forest Dr",
    "sg:city":"Houston",
    "sg:classifiers":[
        {
            "category":"Manufacturing",
            "subcategory":"Tools & Machinery",
            "type":"Manufacturing & Wholesale Goods"
        }
    ],
    "sg:phone":"+1 713 681 3347",
    "sg:postcode":"77092",
    "sg:province":"TX",
    "sg:tags":[
        "laboratory",
        "calibration"
    ],
    "wof:name":"Laboratory Calibration & Consu",
    "wof:placetype":"venue"
},
  "geometry": {"coordinates":[-95.47677299999999,29.845412],"type":"Point"}
}