{
  "type": "Feature",
  "properties": {
    "iso:country":"US",
    "sg:address":"609 Paige St",
    "sg:city":"Henderson",
    "sg:classifiers":[
        {
            "category":"Wholesale",
            "subcategory":"Machinery & Supplies",
            "type":"Manufacturing & Wholesale Goods"
        }
    ],
    "sg:phone":"+1 903 657 4254",
    "sg:postcode":"75652",
    "sg:province":"TX",
    "sg:tags":[
        "equipment",
        "establishment"
    ],
    "wof:name":"Kims Beauty Supply",
    "wof:placetype":"venue"
},
  "geometry": {"coordinates":[-94.781998,32.160315],"type":"Point"}
}