{
  "type": "Feature",
  "properties": {
    "iso:country":"US",
    "sg:address":"600 S Pruett St",
    "sg:city":"Baytown",
    "sg:classifiers":[
        {
            "category":"Education",
            "subcategory":"School",
            "type":"Public Place"
        }
    ],
    "sg:phone":"+1 281 420 4600",
    "sg:postcode":"77520",
    "sg:province":"TX",
    "wof:name":"G W Carver Elementary School",
    "wof:placetype":"venue"
},
  "geometry": {"coordinates":[-94.97442700000001,29.729916],"type":"Point"}
}