{
  "type": "Feature",
  "properties": {
    "iso:country":"US",
    "sg:address":"611 N Park St",
    "sg:city":"Dublin",
    "sg:classifiers":[
        {
            "category":"Professional",
            "subcategory":"Business Services",
            "type":"Services"
        }
    ],
    "sg:phone":"+1 254 445 8173",
    "sg:postcode":"76446",
    "sg:province":"TX",
    "wof:name":"Dan Parker Enterprises Inc",
    "wof:placetype":"venue"
},
  "geometry": {"coordinates":[-98.340805,32.09487],"type":"Point"}
}