{
  "type": "Feature",
  "properties": {
    "iso:country":"US",
    "sg:address":"205 Rippetoe St",
    "sg:city":"Brenham",
    "sg:classifiers":[
        {
            "category":"Building & Trades",
            "subcategory":"Landscaping Services",
            "type":"Services"
        }
    ],
    "sg:phone":"+1 979 836 4435",
    "sg:postcode":"77833",
    "sg:province":"TX",
    "wof:name":"Evergreen Lawn Service",
    "wof:placetype":"venue"
},
  "geometry": {"coordinates":[-96.403859,30.167961],"type":"Point"}
}