{
  "type": "Feature",
  "properties": {
    "iso:country":"US",
    "sg:address":"1214 Mc Ilvaine St",
    "sg:city":"San Antonio",
    "sg:classifiers":[
        {
            "category":"Building & Trades",
            "subcategory":"Construction",
            "type":"Services"
        }
    ],
    "sg:phone":"+1 210 308 8526",
    "sg:postcode":"78201",
    "sg:province":"TX",
    "sg:tags":[
        "dry wall",
        "contractor"
    ],
    "wof:name":"Mdr Contracting Inc",
    "wof:placetype":"venue"
},
  "geometry": {"coordinates":[-98.515323,29.473513],"type":"Point"}
}