{
  "type": "Feature",
  "properties": {
    "iso:country":"US",
    "sg:address":"3204 Arledge Ct",
    "sg:city":"Mc Kinney",
    "sg:classifiers":[
        {
            "category":"Real Estate",
            "subcategory":"Real Estate Agent",
            "type":"Services"
        }
    ],
    "sg:phone":"+1 214 726 1211",
    "sg:postcode":"75070",
    "sg:province":"TX",
    "wof:name":"Landrum Field Services",
    "wof:placetype":"venue"
},
  "geometry": {"coordinates":[-96.68391200000001,33.169364],"type":"Point"}
}