{
  "type": "Feature",
  "properties": {
    "iso:country":"US",
    "sg:address":"407 Pecan St",
    "sg:city":"Center",
    "sg:classifiers":[
        {
            "category":"Organizations",
            "subcategory":"Membership Organization",
            "type":"Services"
        }
    ],
    "sg:phone":"+1 936 598 5789",
    "sg:postcode":"75935",
    "sg:province":"TX",
    "wof:name":"United Daughters of Confe",
    "wof:placetype":"venue"
},
  "geometry": {"coordinates":[-94.175836,31.795666],"type":"Point"}
}