{
  "type": "Feature",
  "properties": {
    "iso:country":"US",
    "sg:address":"9 Grove Ct",
    "sg:city":"Austin",
    "sg:classifiers":[
        {
            "category":"Banks & Credit Unions",
            "subcategory":"Investment Brokerage",
            "type":"Services"
        }
    ],
    "sg:phone":"+1 512 328 7434",
    "sg:postcode":"78746",
    "sg:province":"TX",
    "sg:tags":[
        "trust"
    ],
    "wof:name":"Clark Jr Family Trust",
    "wof:placetype":"venue"
},
  "geometry": {"coordinates":[-97.78898700000001,30.272542],"type":"Point"}
}