{
  "type": "Feature",
  "properties": {
    "iso:country":"US",
    "sg:address":"15610 Pennystone Ct",
    "sg:city":"Friendswood",
    "sg:classifiers":[
        {
            "category":"Shopping",
            "subcategory":"Computers & Home Electronics",
            "type":"Retail Goods"
        },
        {
            "category":"Professional",
            "subcategory":"Computer Services",
            "type":"Services"
        }
    ],
    "sg:phone":"+1 281 992 2110",
    "sg:postcode":"77546",
    "sg:province":"TX",
    "sg:tags":[
        "apple",
        "reseller",
        "consultant",
        "equipment",
        "provider",
        "dealer"
    ],
    "sg:website":"www.merrittconsulting.com",
    "wof:name":"Merritt Consulting & Services",
    "wof:placetype":"venue"
},
  "geometry": {"coordinates":[-95.19093599999999,29.537767],"type":"Point"}
}