{
  "type": "Feature",
  "properties": {
    "iso:country":"US",
    "sg:address":"2703 Oak Bluff",
    "sg:city":"San Antonio",
    "sg:classifiers":[
        {
            "category":"Professional",
            "subcategory":"Engineering",
            "type":"Services"
        }
    ],
    "sg:phone":"+1 210 492 3962",
    "sg:postcode":"78230",
    "sg:province":"TX",
    "wof:name":"Herrin JP & Assoc Inc",
    "wof:placetype":"venue"
},
  "geometry": {"coordinates":[-98.538393,29.541144],"type":"Point"}
}