{
  "type": "Feature",
  "properties": {
    "iso:country":"US",
    "sg:address":"20323 Sequoia Trce",
    "sg:city":"Spring",
    "sg:classifiers":[
        {
            "category":"Wholesale",
            "subcategory":"Durable Goods & Equipment",
            "type":"Manufacturing & Wholesale Goods"
        }
    ],
    "sg:phone":"+1 281 374 9002",
    "sg:postcode":"77379",
    "sg:province":"TX",
    "sg:tags":[
        "representative",
        "manufacturer"
    ],
    "wof:name":"CCI",
    "wof:placetype":"venue"
},
  "geometry": {"coordinates":[-95.508042,30.062718],"type":"Point"}
}