{
  "type": "Feature",
  "properties": {
    "iso:country":"US",
    "sg:address":"823 Congress Ave",
    "sg:city":"Austin",
    "sg:classifiers":[
        {
            "category":"Professional",
            "subcategory":"Detective & Security Services",
            "type":"Services"
        }
    ],
    "sg:phone":"+1 512 263 8240",
    "sg:postcode":"78701",
    "sg:province":"TX",
    "sg:tags":[
        "control",
        "monitoring",
        "system"
    ],
    "wof:name":"823 Security",
    "wof:placetype":"venue"
},
  "geometry": {"coordinates":[-97.742034,30.270131],"type":"Point"}
}