{
  "type": "Feature",
  "properties": {
    "iso:country":"US",
    "sg:address":"1960 Long Cir",
    "sg:city":"Azle",
    "sg:classifiers":[
        {
            "category":"Organizations",
            "subcategory":"Religious Organization",
            "type":"Services"
        }
    ],
    "sg:phone":"+1 817 444 3547",
    "sg:postcode":"76020",
    "sg:province":"TX",
    "sg:tags":[
        "church"
    ],
    "wof:name":"Lighthouse Harbor Church",
    "wof:placetype":"venue"
},
  "geometry": {"coordinates":[-97.51983,32.926747],"type":"Point"}
}