{
  "type": "Feature",
  "properties": {
    "iso:country":"US",
    "sg:address":"8308 Echo Willow Dr",
    "sg:city":"San Antonio",
    "sg:classifiers":[
        {
            "category":"Shopping",
            "type":"Retail Goods"
        }
    ],
    "sg:phone":"+1 210 628 1237",
    "sg:postcode":"78250",
    "sg:province":"TX",
    "sg:tags":[
        "merchandise"
    ],
    "wof:name":"Mayjola Chiw De Gonzalez",
    "wof:placetype":"venue"
},
  "geometry": {"coordinates":[-98.64229,29.517372],"type":"Point"}
}