{
  "type": "Feature",
  "properties": {
    "iso:country":"US",
    "sg:address":"1194 Cedar Ln",
    "sg:city":"Kaufman",
    "sg:classifiers":[
        {
            "category":"Wholesale",
            "subcategory":"Music Publishers",
            "type":"Manufacturing & Wholesale Goods"
        },
        {
            "category":"Wholesale",
            "subcategory":"Books, Periodicals, & Newspapers",
            "type":"Manufacturing & Wholesale Goods"
        }
    ],
    "sg:phone":"+1 214 236 4107",
    "sg:postcode":"75142",
    "sg:province":"TX",
    "sg:tags":[
        "distribution"
    ],
    "wof:name":"Stevenson, Bw Music",
    "wof:placetype":"venue"
},
  "geometry": {"coordinates":[-96.386776,32.602622],"type":"Point"}
}