{
  "type": "Feature",
  "properties": {
    "iso:country":"US",
    "sg:address":"920 N University Dr",
    "sg:city":"Nacogdoches",
    "sg:classifiers":[
        {
            "category":"Real Estate",
            "subcategory":"Real Estate Agent",
            "type":"Services"
        }
    ],
    "sg:phone":"+1 936 568 9090",
    "sg:postcode":"75961",
    "sg:province":"TX",
    "wof:name":"Nacogdoches County Bd Realtors",
    "wof:placetype":"venue"
},
  "geometry": {"coordinates":[-94.63930000000001,31.61669],"type":"Point"}
}