{
  "type": "Feature",
  "properties": {
    "iso:country":"US",
    "sg:address":"520 N Dallas Ave",
    "sg:city":"Lancaster",
    "sg:classifiers":[
        {
            "category":"Organizations",
            "subcategory":"Religious Organization",
            "type":"Services"
        }
    ],
    "sg:phone":"+1 972 227 3678",
    "sg:postcode":"75146",
    "sg:province":"TX",
    "sg:tags":[
        "church"
    ],
    "wof:name":"Grace Cathedral Church",
    "wof:placetype":"venue"
},
  "geometry": {"coordinates":[-96.75646399999999,32.596256],"type":"Point"}
}