{
  "type": "Feature",
  "properties": {
    "iso:country":"US",
    "sg:address":"3405 Teresa Dr",
    "sg:city":"Flower Mound",
    "sg:classifiers":[
        {
            "category":"Shopping",
            "subcategory":"Gifts & Souvenirs",
            "type":"Retail Goods"
        }
    ],
    "sg:phone":"+1 972 691 7790",
    "sg:postcode":"75022",
    "sg:province":"TX",
    "wof:name":"Denise Jarrell",
    "wof:placetype":"venue"
},
  "geometry": {"coordinates":[-97.096665,33.033096],"type":"Point"}
}