{
  "type": "Feature",
  "properties": {
    "iso:country":"US",
    "sg:address":"606 Belhaven Dr",
    "sg:city":"Allen",
    "sg:classifiers":[
        {
            "category":"Professional",
            "subcategory":"Employment Agencies",
            "type":"Services"
        }
    ],
    "sg:phone":"+1 214 495 8300",
    "sg:postcode":"75013",
    "sg:province":"TX",
    "sg:tags":[
        "opportunity"
    ],
    "wof:name":"Employment Solution",
    "wof:placetype":"venue"
},
  "geometry": {"coordinates":[-96.716021,33.09099],"type":"Point"}
}