{
  "type": "Feature",
  "properties": {
    "iso:country":"US",
    "sg:address":"1211 Bamore Rd",
    "sg:city":"Rosenberg",
    "sg:classifiers":[
        {
            "category":"Building & Trades",
            "subcategory":"Construction",
            "type":"Services"
        }
    ],
    "sg:phone":"+1 281 342 1072",
    "sg:postcode":"77471",
    "sg:province":"TX",
    "sg:tags":[
        "drywall",
        "contractor"
    ],
    "wof:name":"Ace Drywall",
    "wof:placetype":"venue"
},
  "geometry": {"coordinates":[-95.819625,29.555803],"type":"Point"}
}