{
  "type": "Feature",
  "properties": {
    "iso:country":"US",
    "sg:address":"2613 Southwestern Dr",
    "sg:city":"Flower Mound",
    "sg:classifiers":[
        {
            "category":"Professional",
            "type":"Services"
        }
    ],
    "sg:phone":"+1 972 355 8765",
    "sg:postcode":"75028",
    "sg:province":"TX",
    "wof:name":"Heidi Cole Studios",
    "wof:placetype":"venue"
},
  "geometry": {"coordinates":[-97.06018899999999,33.020805],"type":"Point"}
}