{
  "type": "Feature",
  "properties": {
    "iso:country":"US",
    "sg:address":"1305 Berkeley Ct",
    "sg:city":"Plano",
    "sg:classifiers":[
        {
            "category":"Professional",
            "subcategory":"Business Services",
            "type":"Services"
        }
    ],
    "sg:phone":"+1 972 517 5285",
    "sg:postcode":"75023",
    "sg:province":"TX",
    "wof:name":"Libra Data Solutions Intl LLC",
    "wof:placetype":"venue"
},
  "geometry": {"coordinates":[-96.71518399999999,33.07063],"type":"Point"}
}