{
  "type": "Feature",
  "properties": {
    "iso:country":"US",
    "sg:address":"6301 Connie Ln",
    "sg:city":"Colleyville",
    "sg:classifiers":[
        {
            "category":"Shopping",
            "subcategory":"Clothing, Apparel, & Fashions",
            "type":"Retail Goods"
        }
    ],
    "sg:phone":"+1 817 329 8449",
    "sg:postcode":"76034",
    "sg:province":"TX",
    "wof:name":"Paula R Robinson Inc",
    "wof:placetype":"venue"
},
  "geometry": {"coordinates":[-97.129976,32.900686],"type":"Point"}
}