{
  "type": "Feature",
  "properties": {
    "iso:country":"US",
    "sg:address":"1120 Mudd St",
    "sg:city":"Spring",
    "sg:classifiers":[
        {
            "category":"Health Services",
            "subcategory":"Clinic",
            "type":"Services"
        }
    ],
    "sg:phone":"+1 281 364 9633",
    "sg:postcode":"77331",
    "sg:province":"TX",
    "sg:tags":[
        "kidney",
        "dialysis",
        "center"
    ],
    "wof:name":"Caremark Kidney Program",
    "wof:placetype":"venue"
},
  "geometry": {"coordinates":[-95.011876,30.61716],"type":"Point"}
}