{
  "type": "Feature",
  "properties": {
    "iso:country":"US",
    "sg:address":"3012 N 1st St",
    "sg:city":"Abilene",
    "sg:classifiers":[
        {
            "category":"Manufacturing",
            "subcategory":"Food",
            "type":"Manufacturing & Wholesale Goods"
        }
    ],
    "sg:phone":"+1 325 677 0013",
    "sg:postcode":"79603",
    "sg:province":"TX",
    "sg:tags":[
        "product",
        "mfg"
    ],
    "wof:name":"Buttercrust Inc",
    "wof:placetype":"venue"
},
  "geometry": {"coordinates":[-99.758146,32.450975],"type":"Point"}
}