{
  "type": "Feature",
  "properties": {
    "iso:country":"US",
    "sg:address":"1725 Neal St",
    "sg:city":"Navasota",
    "sg:classifiers":[
        {
            "category":"Shopping",
            "type":"Retail Goods"
        }
    ],
    "sg:phone":"+1 936 825 6570",
    "sg:postcode":"77868",
    "sg:province":"TX",
    "sg:tags":[
        "merchandise"
    ],
    "wof:name":"Willoughby Industries Inc",
    "wof:placetype":"venue"
},
  "geometry": {"coordinates":[-96.076081,30.399999],"type":"Point"}
}