{
  "type": "Feature",
  "properties": {
    "iso:country":"US",
    "sg:address":"3309 Knickerbocker Rd",
    "sg:city":"San Angelo",
    "sg:classifiers":[
        {
            "category":"Organizations",
            "subcategory":"Religious Organization",
            "type":"Services"
        }
    ],
    "sg:phone":"+1 325 949 7517",
    "sg:postcode":"76904",
    "sg:province":"TX",
    "sg:tags":[
        "church"
    ],
    "wof:name":"Community Hills Christn Church",
    "wof:placetype":"venue"
},
  "geometry": {"coordinates":[-100.46753200000001,31.422112],"type":"Point"}
}