{
  "type": "Feature",
  "properties": {
    "iso:country":"US",
    "sg:address":"1115 Main St",
    "sg:city":"Commerce",
    "sg:classifiers":[
        {
            "category":"Home & Garden",
            "subcategory":"Household Appliances",
            "type":"Retail Goods"
        }
    ],
    "sg:phone":"+1 903 886 4060",
    "sg:postcode":"75428",
    "sg:province":"TX",
    "sg:tags":[
        "machine",
        "washing"
    ],
    "wof:name":"Dave's Kitchen & Laundry Ctr",
    "wof:placetype":"venue"
},
  "geometry": {"coordinates":[-95.900367,33.250736],"type":"Point"}
}