{
  "type": "Feature",
  "properties": {
    "iso:country":"US",
    "sg:address":"1212 Rio Grande Ct",
    "sg:city":"Allen",
    "sg:classifiers":[
        {
            "category":"Building & Trades",
            "subcategory":"Construction",
            "type":"Services"
        }
    ],
    "sg:phone":"+1 972 396 0689",
    "sg:postcode":"75013",
    "sg:province":"TX",
    "sg:tags":[
        "home",
        "builder"
    ],
    "wof:name":"Pinnacle Luxury Homes",
    "wof:placetype":"venue"
},
  "geometry": {"coordinates":[-96.691367,33.115836],"type":"Point"}
}