{
  "type": "Feature",
  "properties": {
    "iso:country":"US",
    "sg:address":"106 N Main St",
    "sg:city":"Mansfield",
    "sg:classifiers":[
        {
            "category":"Retail",
            "subcategory":"Laundry & Dry Cleaning",
            "type":"Services"
        },
        {
            "category":"Shopping",
            "subcategory":"Clothing, Apparel, & Fashions",
            "type":"Retail Goods"
        }
    ],
    "sg:phone":"+1 817 453 2898",
    "sg:postcode":"76063",
    "sg:province":"TX",
    "sg:tags":[
        "alteration"
    ],
    "wof:name":"Lucy's Alterations",
    "wof:placetype":"venue"
},
  "geometry": {"coordinates":[-97.141904,32.563494],"type":"Point"}
}