{
  "type": "Feature",
  "properties": {
    "iso:country":"US",
    "sg:address":"7524 Burnet Rd",
    "sg:city":"Austin",
    "sg:classifiers":[
        {
            "category":"Autos & Motor Vehicles",
            "subcategory":"Automobile Sales",
            "type":"Retail Goods"
        }
    ],
    "sg:phone":"+1 512 458 2277",
    "sg:postcode":"78757",
    "sg:province":"TX",
    "sg:tags":[
        "dealers-used",
        "car",
        "used",
        "cars-wholesale",
        "new"
    ],
    "wof:name":"Five Star Auto Group Outlet",
    "wof:placetype":"venue"
},
  "geometry": {"coordinates":[-97.73405,30.350931],"type":"Point"}
}