{
  "type": "Feature",
  "properties": {
    "iso:country":"US",
    "sg:address":"115 W Main St",
    "sg:city":"Frankston",
    "sg:classifiers":[
        {
            "category":"Shopping",
            "subcategory":"Used Merchandise",
            "type":"Retail Goods"
        }
    ],
    "sg:phone":"+1 903 876 2357",
    "sg:postcode":"75763",
    "sg:province":"TX",
    "sg:tags":[
        "antique"
    ],
    "wof:name":"Remember This Antiques",
    "wof:placetype":"venue"
},
  "geometry": {"coordinates":[-95.508036,32.05071],"type":"Point"}
}