{
  "type": "Feature",
  "properties": {
    "iso:country":"US",
    "sg:address":"1901 Gateway Dr",
    "sg:city":"Irving",
    "sg:classifiers":[
        {
            "category":"Banks & Credit Unions",
            "subcategory":"Bank",
            "type":"Services"
        }
    ],
    "sg:phone":"+1 972 753 0822",
    "sg:postcode":"75038",
    "sg:province":"TX",
    "sg:tags":[
        "loan"
    ],
    "wof:name":"Cottonwood Financial",
    "wof:placetype":"venue"
},
  "geometry": {"coordinates":[-96.97430799999999,32.883995],"type":"Point"}
}