{
  "type": "Feature",
  "properties": {
    "iso:country":"US",
    "sg:address":"1220 N Town East Blvd # 330",
    "sg:city":"Mesquite",
    "sg:classifiers":[
        {
            "category":"Professional",
            "subcategory":"Employment Agencies",
            "type":"Services"
        }
    ],
    "sg:phone":"+1 972 686 1177",
    "sg:postcode":"75150",
    "sg:province":"TX",
    "sg:tags":[
        "employer"
    ],
    "sg:website":"http://www.thpm.org",
    "wof:name":"Texas Highway Patrol Museum",
    "wof:placetype":"venue"
},
  "geometry": {"coordinates":[-96.61292299999999,32.810719],"type":"Point"}
}