{
  "type": "Feature",
  "properties": {
    "iso:country":"US",
    "sg:address":"2724 Russwood Ln",
    "sg:city":"Plano",
    "sg:classifiers":[
        {
            "category":"Building & Trades",
            "subcategory":"Landscaping Services",
            "type":"Services"
        }
    ],
    "sg:phone":"+1 972 897 7895",
    "sg:postcode":"75075",
    "sg:province":"TX",
    "sg:tags":[
        "lawn",
        "stump",
        "tree",
        "grinding",
        "removal",
        "maintenance",
        "arborist"
    ],
    "sg:website":"http://www.metrotreeservice.net",
    "wof:name":"Metro Tree Service",
    "wof:placetype":"venue"
},
  "geometry": {"coordinates":[-96.745327,33.030452],"type":"Point"}
}