{
  "type": "Feature",
  "properties": {
    "iso:country":"US",
    "sg:address":"82 Haynes Rd",
    "sg:city":"Victoria",
    "sg:classifiers":[
        {
            "category":"Retail",
            "subcategory":"Portrait Studio",
            "type":"Services"
        }
    ],
    "sg:phone":"+1 361 576 6561",
    "sg:postcode":"77904",
    "sg:province":"TX",
    "sg:tags":[
        "photographer"
    ],
    "wof:name":"Perfect Partners Pressure Wash",
    "wof:placetype":"venue"
},
  "geometry": {"coordinates":[-97.025604,28.887026],"type":"Point"}
}