{
  "type": "Feature",
  "properties": {
    "iso:country":"US",
    "sg:address":"16211 Charolais Dr",
    "sg:city":"Cypress",
    "sg:classifiers":[
        {
            "category":"Building & Trades",
            "subcategory":"Landscaping Services",
            "type":"Services"
        }
    ],
    "sg:phone":"+1 281 373 9499",
    "sg:postcode":"77429",
    "sg:province":"TX",
    "sg:tags":[
        "landscape"
    ],
    "wof:name":"TP Tractor Service",
    "wof:placetype":"venue"
},
  "geometry": {"coordinates":[-95.674468,29.989569],"type":"Point"}
}