{
  "type": "Feature",
  "properties": {
    "iso:country":"US",
    "sg:address":"8141 Slide Rock Rd",
    "sg:city":"Fort Worth",
    "sg:classifiers":[
        {
            "category":"Wholesale",
            "subcategory":"Toys & Hobbies",
            "type":"Manufacturing & Wholesale Goods"
        }
    ],
    "sg:phone":"+1 817 281 7023",
    "sg:postcode":"76137",
    "sg:province":"TX",
    "sg:tags":[
        "wholesaler"
    ],
    "wof:name":"J & S Co",
    "wof:placetype":"venue"
},
  "geometry": {"coordinates":[-97.27829800000001,32.887568],"type":"Point"}
}