{
  "type": "Feature",
  "properties": {
    "iso:country":"US",
    "sg:address":"3347 Old Jacksonville Rd",
    "sg:city":"Tyler",
    "sg:classifiers":[
        {
            "category":"Insurance",
            "subcategory":"Hazard Insurance",
            "type":"Services"
        }
    ],
    "sg:phone":"+1 903 509 8245",
    "sg:postcode":"75701",
    "sg:province":"TX",
    "sg:tags":[
        "commercial",
        "business"
    ],
    "wof:name":"Talon Insurance Agency",
    "wof:placetype":"venue"
},
  "geometry": {"coordinates":[-95.319137,32.310714],"type":"Point"}
}