{
  "type": "Feature",
  "properties": {
    "iso:country":"US",
    "sg:address":"2517 Maconda Ln",
    "sg:city":"Houston",
    "sg:classifiers":[
        {
            "category":"Professional",
            "subcategory":"Business Services",
            "type":"Services"
        }
    ],
    "sg:phone":"+1 713 850 0037",
    "sg:postcode":"77027",
    "sg:province":"TX",
    "wof:name":"Steven M & Suzanne B Duin",
    "wof:placetype":"venue"
},
  "geometry": {"coordinates":[-95.436998,29.741714],"type":"Point"}
}