{
  "type": "Feature",
  "properties": {
    "iso:country":"US",
    "sg:address":"419 Valley Glen Pl",
    "sg:city":"Richardson",
    "sg:classifiers":[
        {
            "category":"Building & Trades",
            "subcategory":"Landscaping Services",
            "type":"Services"
        }
    ],
    "sg:phone":"+1 972 480 9012",
    "sg:postcode":"75080",
    "sg:province":"TX",
    "sg:tags":[
        "lawn",
        "maintenance",
        "grounds"
    ],
    "wof:name":"Landry's Lawn & Landscape",
    "wof:placetype":"venue"
},
  "geometry": {"coordinates":[-96.72296,32.993219],"type":"Point"}
}