{
  "type": "Feature",
  "properties": {
    "iso:country":"US",
    "sg:address":"105 Cam Real E",
    "sg:city":"Wylie",
    "sg:classifiers":[
        {
            "category":"Professional",
            "subcategory":"Management & Consulting",
            "type":"Services"
        }
    ],
    "sg:phone":"+1 972 442 0396",
    "sg:postcode":"75098",
    "sg:province":"TX",
    "sg:tags":[
        "consultant",
        "relation",
        "labor"
    ],
    "wof:name":"Wm G Berry Consultants",
    "wof:placetype":"venue"
},
  "geometry": {"coordinates":[-96.56525999999999,33.071524],"type":"Point"}
}