{
  "type": "Feature",
  "properties": {
    "iso:country":"US",
    "sg:address":"9114 Woodlake Dr",
    "sg:city":"Rowlett",
    "sg:classifiers":[
        {
            "category":"Shopping",
            "subcategory":"Bicycles & Sporting Goods",
            "type":"Retail Goods"
        }
    ],
    "sg:phone":"+1 972 463 1902",
    "sg:postcode":"75088",
    "sg:province":"TX",
    "sg:tags":[
        "equipment",
        "golf",
        "supply"
    ],
    "wof:name":"Decoleco",
    "wof:placetype":"venue"
},
  "geometry": {"coordinates":[-96.51190200000001,32.904542],"type":"Point"}
}