{
  "type": "Feature",
  "properties": {
    "iso:country":"US",
    "sg:address":"1302 Goodhue Dr",
    "sg:city":"Killeen",
    "sg:classifiers":[
        {
            "category":"Professional",
            "type":"Services"
        }
    ],
    "sg:phone":"+1 254 634 8351",
    "sg:postcode":"76549",
    "sg:province":"TX",
    "wof:name":"Cha Wanar Tucker",
    "wof:placetype":"venue"
},
  "geometry": {"coordinates":[-97.76011699999999,31.107632],"type":"Point"}
}