{
  "type": "Feature",
  "properties": {
    "iso:country":"US",
    "sg:address":"1027 Sam Houston Ave",
    "sg:city":"Huntsville",
    "sg:classifiers":[
        {
            "category":"Shopping",
            "type":"Retail Goods"
        }
    ],
    "sg:phone":"+1 936 436 0303",
    "sg:postcode":"77320",
    "sg:province":"TX",
    "sg:tags":[
        "art",
        "gallery",
        "dealer"
    ],
    "wof:name":"Jamison Lee Gallery",
    "wof:placetype":"venue"
},
  "geometry": {"coordinates":[-95.55139,30.723696],"type":"Point"}
}