{
  "type": "Feature",
  "properties": {
    "iso:country":"US",
    "sg:address":"6826 Harrisburg Blvd",
    "sg:city":"Houston",
    "sg:classifiers":[
        {
            "category":"Shopping",
            "subcategory":"Mobile Phones",
            "type":"Retail Goods"
        }
    ],
    "sg:phone":"+1 713 514 0176",
    "sg:postcode":"77011",
    "sg:province":"TX",
    "wof:name":"T-Mobile",
    "wof:placetype":"venue"
},
  "geometry": {"coordinates":[-95.305803,29.736634],"type":"Point"}
}