{
  "type": "Feature",
  "properties": {
    "iso:country":"US",
    "sg:address":"2016 Keller Springs Rd",
    "sg:city":"Carrollton",
    "sg:classifiers":[
        {
            "category":"Retail",
            "subcategory":"Auto Repair",
            "type":"Services"
        }
    ],
    "sg:phone":"+1 972 242 9800",
    "sg:postcode":"75006",
    "sg:province":"TX",
    "wof:name":"Fleet Vehicle Repair",
    "wof:placetype":"venue"
},
  "geometry": {"coordinates":[-96.887782,32.972388],"type":"Point"}
}