{
  "type": "Feature",
  "properties": {
    "iso:country":"US",
    "sg:address":"6615 Vaught Ranch Rd",
    "sg:city":"Austin",
    "sg:classifiers":[
        {
            "category":"Professional",
            "subcategory":"Engineering",
            "type":"Services"
        }
    ],
    "sg:phone":"+1 512 328 0082",
    "sg:postcode":"78730",
    "sg:province":"TX",
    "wof:name":"Michael N Hart",
    "wof:placetype":"venue"
},
  "geometry": {"coordinates":[-97.805465,30.375196],"type":"Point"}
}