{
  "type": "Feature",
  "properties": {
    "iso:country":"US",
    "sg:address":"5300 Buford Jett Ln",
    "sg:city":"Mesquite",
    "sg:classifiers":[
        {
            "category":"Building & Trades",
            "subcategory":"Construction",
            "type":"Services"
        }
    ],
    "sg:phone":"+1 972 286 2262",
    "sg:postcode":"75180",
    "sg:province":"TX",
    "sg:tags":[
        "contractor",
        "paving",
        "asphalt",
        "sealcoating"
    ],
    "wof:name":"Total Paving",
    "wof:placetype":"venue"
},
  "geometry": {"coordinates":[-96.63429499999999,32.695423],"type":"Point"}
}