{
  "type": "Feature",
  "properties": {
    "iso:country":"US",
    "sg:address":"1714 Old Boston Rd",
    "sg:city":"Texarkana",
    "sg:classifiers":[
        {
            "category":"Freight",
            "type":"Transportation"
        }
    ],
    "sg:phone":"+1 903 838 4706",
    "sg:postcode":"75501",
    "sg:province":"TX",
    "sg:tags":[
        "operator",
        "local",
        "trucking"
    ],
    "wof:name":"Cns Trucking Inc",
    "wof:placetype":"venue"
},
  "geometry": {"coordinates":[-94.159075,33.439792],"type":"Point"}
}