{
  "type": "Feature",
  "properties": {
    "iso:country":"US",
    "sg:address":"1823 Waugh Dr",
    "sg:city":"Houston",
    "sg:classifiers":[
        {
            "category":"Health Services",
            "subcategory":"Clinic",
            "type":"Services"
        }
    ],
    "sg:phone":"+1 713 942 9026",
    "sg:postcode":"77006",
    "sg:province":"TX",
    "sg:tags":[
        "counseling",
        "mental"
    ],
    "wof:name":"Tomlinson Donna Lmsc Acp",
    "wof:placetype":"venue"
},
  "geometry": {"coordinates":[-95.397102,29.751301],"type":"Point"}
}