{
  "type": "Feature",
  "properties": {
    "iso:country":"US",
    "sg:address":"1615 Singleton Blvd",
    "sg:city":"Dallas",
    "sg:classifiers":[
        {
            "category":"Restaurant",
            "type":"Food & Drink"
        }
    ],
    "sg:phone":"+1 214 651 7707",
    "sg:postcode":"75212",
    "sg:province":"TX",
    "sg:tags":[
        "eating"
    ],
    "wof:name":"Refresqueria & Taqueria Soto",
    "wof:placetype":"venue"
},
  "geometry": {"coordinates":[-96.84630300000001,32.778601],"type":"Point"}
}