{
  "type": "Feature",
  "properties": {
    "iso:country":"US",
    "sg:address":"1303 Wheatley Ave",
    "sg:city":"San Antonio",
    "sg:classifiers":[
        {
            "category":"Food & Beverages",
            "subcategory":"Groceries & Convenience Stores",
            "type":"Retail Goods"
        }
    ],
    "sg:phone":"+1 210 333 6521",
    "sg:postcode":"78220",
    "sg:province":"TX",
    "wof:name":"Merryland Food Market",
    "wof:placetype":"venue"
},
  "geometry": {"coordinates":[-98.425077,29.409497],"type":"Point"}
}