{
  "type": "Feature",
  "properties": {
    "iso:country":"US",
    "sg:address":"4901 Irvington Blvd",
    "sg:city":"Houston",
    "sg:classifiers":[
        {
            "category":"Professional",
            "subcategory":"Lawyer & Legal Services",
            "type":"Services"
        }
    ],
    "sg:phone":"+1 713 694 8818",
    "sg:postcode":"77009",
    "sg:province":"TX",
    "wof:name":"Trevino Sergio A Atty",
    "wof:placetype":"venue"
},
  "geometry": {"coordinates":[-95.36129800000001,29.805099],"type":"Point"}
}