{
  "type": "Feature",
  "properties": {
    "iso:country":"US",
    "sg:address":"905 Ave T",
    "sg:city":"Grand Prairie",
    "sg:classifiers":[
        {
            "category":"Utilities",
            "subcategory":"Telephone",
            "type":"Services"
        },
        {
            "category":"Shopping",
            "type":"Retail Goods"
        }
    ],
    "sg:phone":"+1 972 206 2681",
    "sg:postcode":"75050",
    "sg:province":"TX",
    "sg:tags":[
        "equipment",
        "communications",
        "merchandise",
        "supply"
    ],
    "wof:name":"Power & Telephone Supply Co",
    "wof:placetype":"venue"
},
  "geometry": {"coordinates":[-97.04664099999999,32.790292],"type":"Point"}
}