{
  "type": "Feature",
  "properties": {
    "iso:country":"US",
    "sg:address":"9000 Gulf Fwy",
    "sg:city":"Houston",
    "sg:classifiers":[
        {
            "category":"Organizations",
            "subcategory":"Community Association",
            "type":"Services"
        }
    ],
    "sg:phone":"+1 713 948 7723",
    "sg:postcode":"77017",
    "sg:province":"TX",
    "wof:name":"Waterside Esttes Nnresidential",
    "wof:placetype":"venue"
},
  "geometry": {"coordinates":[-95.270387,29.678048],"type":"Point"}
}