{
  "type": "Feature",
  "properties": {
    "iso:country":"US",
    "sg:address":"18119 Timothy St",
    "sg:city":"Pearland",
    "sg:classifiers":[
        {
            "category":"Retail",
            "subcategory":"Animal Services",
            "type":"Services"
        }
    ],
    "sg:phone":"+1 281 489 8024",
    "sg:postcode":"77584",
    "sg:province":"TX",
    "wof:name":"Roka Kennel",
    "wof:placetype":"venue"
},
  "geometry": {"coordinates":[-95.28602100000001,29.511815],"type":"Point"}
}