{
  "type": "Feature",
  "properties": {
    "iso:country":"US",
    "sg:address":"138 N Kowald Ln",
    "sg:city":"New Braunfels",
    "sg:classifiers":[
        {
            "category":"Building & Trades",
            "subcategory":"Construction",
            "type":"Services"
        }
    ],
    "sg:phone":"+1 830 625 6616",
    "sg:postcode":"78130",
    "sg:province":"TX",
    "sg:tags":[
        "house"
    ],
    "wof:name":"Alvarado Construction",
    "wof:placetype":"venue"
},
  "geometry": {"coordinates":[-98.08883,29.718641],"type":"Point"}
}