{
  "type": "Feature",
  "properties": {
    "iso:country":"US",
    "sg:address":"720 Thorn Ave",
    "sg:city":"El Paso",
    "sg:classifiers":[
        {
            "category":"Manufacturing",
            "subcategory":"Metals",
            "type":"Manufacturing & Wholesale Goods"
        }
    ],
    "sg:phone":"+1 915 581 7472",
    "sg:postcode":"79912",
    "sg:province":"TX",
    "sg:tags":[
        "shop",
        "die",
        "tool"
    ],
    "wof:name":"Santos Manufacturing",
    "wof:placetype":"venue"
},
  "geometry": {"coordinates":[-106.56854,31.856328],"type":"Point"}
}