{
  "type": "Feature",
  "properties": {
    "iso:country":"US",
    "sg:address":"1123 Larkspur Dr",
    "sg:city":"Richardson",
    "sg:classifiers":[
        {
            "category":"Building & Trades",
            "subcategory":"Landscaping Services",
            "type":"Services"
        }
    ],
    "sg:phone":"+1 972 238 8060",
    "sg:postcode":"75081",
    "sg:province":"TX",
    "sg:tags":[
        "lawn",
        "maintenance",
        "grounds"
    ],
    "wof:name":"Still Green Lawncare Landscpg",
    "wof:placetype":"venue"
},
  "geometry": {"coordinates":[-96.70665099999999,32.949362],"type":"Point"}
}