{
  "type": "Feature",
  "properties": {
    "iso:country":"US",
    "sg:address":"217 Helgra",
    "sg:city":"Deer Park",
    "sg:classifiers":[
        {
            "category":"Shopping",
            "subcategory":"Florist",
            "type":"Retail Goods"
        }
    ],
    "sg:phone":"+1 281 479 2025",
    "sg:postcode":"77536",
    "sg:province":"TX",
    "wof:name":"Go Flowers Plus",
    "wof:placetype":"venue"
},
  "geometry": {"coordinates":[-95.12493000000001,29.698611],"type":"Point"}
}