{
  "type": "Feature",
  "properties": {
    "iso:country":"US",
    "sg:address":"6635 Sandswept Ln",
    "sg:city":"Houston",
    "sg:classifiers":[
        {
            "category":"Communications",
            "subcategory":"Radio Station",
            "type":"Services"
        }
    ],
    "sg:phone":"+1 281 448 3767",
    "sg:postcode":"77086",
    "sg:province":"TX",
    "sg:tags":[
        "program",
        "producer"
    ],
    "wof:name":"Custom Dj Drops",
    "wof:placetype":"venue"
},
  "geometry": {"coordinates":[-95.484165,29.929953],"type":"Point"}
}