{
  "type": "Feature",
  "properties": {
    "iso:country":"US",
    "sg:address":"1075 Kingwood Dr",
    "sg:city":"Humble",
    "sg:classifiers":[
        {
            "category":"Manufacturing",
            "subcategory":"Tools & Machinery",
            "type":"Manufacturing & Wholesale Goods"
        }
    ],
    "sg:phone":"+1 281 358 8114",
    "sg:postcode":"77336",
    "sg:province":"TX",
    "sg:tags":[
        "medical",
        "anesthesia"
    ],
    "wof:name":"Katy W Houston Anesthesia PA",
    "wof:placetype":"venue"
},
  "geometry": {"coordinates":[-95.237382,30.049345],"type":"Point"}
}