{
  "type": "Feature",
  "properties": {
    "iso:country":"US",
    "sg:address":"9441 Lyndon B Johnson Fwy",
    "sg:city":"Dallas",
    "sg:classifiers":[
        {
            "category":"Professional",
            "type":"Services"
        }
    ],
    "sg:phone":"+1 972 238 9973",
    "sg:postcode":"75243",
    "sg:province":"TX",
    "wof:name":"SC Independence Propertie",
    "wof:placetype":"venue"
},
  "geometry": {"coordinates":[-96.733733,32.909472],"type":"Point"}
}