{
  "type": "Feature",
  "properties": {
    "iso:country":"US",
    "sg:address":"512 N Main St",
    "sg:city":"Encinal",
    "sg:classifiers":[
        {
            "category":"Home & Garden",
            "subcategory":"Hardware",
            "type":"Retail Goods"
        }
    ],
    "sg:phone":"+1 956 948 5394",
    "sg:postcode":"78064",
    "sg:province":"TX",
    "wof:name":"Bert's General Store",
    "wof:placetype":"venue"
},
  "geometry": {"coordinates":[-98.484134,28.963788],"type":"Point"}
}