{
  "type": "Feature",
  "properties": {
    "iso:country":"US",
    "sg:address":"2822 Kingshores Dr",
    "sg:city":"Granite Shoals",
    "sg:classifiers":[
        {
            "category":"Retail",
            "subcategory":"Auto Repair",
            "type":"Services"
        }
    ],
    "sg:phone":"+1 210 673 3252",
    "sg:postcode":"78654",
    "sg:province":"TX",
    "sg:tags":[
        "automobile",
        "lubrication"
    ],
    "wof:name":"A-1 Action Mobil Lube",
    "wof:placetype":"venue"
},
  "geometry": {"coordinates":[-98.35691199999999,30.597181],"type":"Point"}
}