{
  "type": "Feature",
  "properties": {
    "iso:country":"US",
    "sg:address":"6915 E Lancaster Ave",
    "sg:city":"Fort Worth",
    "sg:classifiers":[
        {
            "category":"Retail",
            "subcategory":"Car Wash",
            "type":"Services"
        }
    ],
    "sg:phone":"+1 817 446 9848",
    "sg:postcode":"76112",
    "sg:province":"TX",
    "sg:tags":[
        "automobile",
        "detail",
        "clean"
    ],
    "wof:name":"Mike & Jerry's Detail",
    "wof:placetype":"venue"
},
  "geometry": {"coordinates":[-97.20925699999999,32.730535],"type":"Point"}
}