{
  "type": "Feature",
  "properties": {
    "iso:country":"US",
    "sg:address":"3807 Westlawn Ave",
    "sg:city":"Amarillo",
    "sg:classifiers":[
        {
            "category":"Building & Trades",
            "subcategory":"Equipment Rental",
            "type":"Services"
        }
    ],
    "sg:phone":"+1 806 359 6113",
    "sg:postcode":"79102",
    "sg:province":"TX",
    "wof:name":"Rick Lawhon",
    "wof:placetype":"venue"
},
  "geometry": {"coordinates":[-101.880444,35.195586],"type":"Point"}
}