{
  "type": "Feature",
  "properties": {
    "iso:country":"US",
    "sg:address":"4975 N Oconnor Rd",
    "sg:city":"Dallas",
    "sg:classifiers":[
        {
            "category":"Banks & Credit Unions",
            "subcategory":"Bank",
            "type":"Services"
        }
    ],
    "sg:phone":"+1 972 364 5420",
    "sg:postcode":"75201",
    "sg:province":"TX",
    "sg:website":"www.capitalonebank.com",
    "wof:name":"CapitalOne",
    "wof:placetype":"venue"
},
  "geometry": {"coordinates":[-96.945741,32.866715],"type":"Point"}
}