{
  "type": "Feature",
  "properties": {
    "iso:country":"US",
    "sg:address":"4757 W Park Blvd",
    "sg:city":"Plano",
    "sg:classifiers":[
        {
            "category":"Building & Trades",
            "subcategory":"Construction",
            "type":"Services"
        }
    ],
    "sg:phone":"+1 972 596 3100",
    "sg:postcode":"75093",
    "sg:province":"TX",
    "sg:tags":[
        "tile",
        "dealer",
        "contractor"
    ],
    "wof:name":"Granite & Tile Outlet",
    "wof:placetype":"venue"
},
  "geometry": {"coordinates":[-96.789934,33.027141],"type":"Point"}
}