{
  "type": "Feature",
  "properties": {
    "iso:country":"US",
    "sg:address":"4109 Tradewind St",
    "sg:city":"Amarillo",
    "sg:classifiers":[
        {
            "category":"Education",
            "subcategory":"Special Training",
            "type":"Public Place"
        }
    ],
    "sg:phone":"+1 806 373 1116",
    "sg:postcode":"79118",
    "sg:province":"TX",
    "sg:tags":[
        "aircraft",
        "school"
    ],
    "wof:name":"Tradewind Flight School Inc",
    "wof:placetype":"venue"
},
  "geometry": {"coordinates":[-101.830759,35.17025],"type":"Point"}
}