{
  "type": "Feature",
  "properties": {
    "iso:country":"US",
    "sg:address":"7318 Casa Loma Ave",
    "sg:city":"Dallas",
    "sg:classifiers":[
        {
            "category":"Home & Garden",
            "subcategory":"Household Appliances",
            "type":"Retail Goods"
        }
    ],
    "sg:phone":"+1 214 319 7961",
    "sg:postcode":"75214",
    "sg:province":"TX",
    "sg:tags":[
        "cleaners",
        "vacuum"
    ],
    "wof:name":"North Texas Central Vacuum",
    "wof:placetype":"venue"
},
  "geometry": {"coordinates":[-96.731396,32.809745],"type":"Point"}
}