{
  "type": "Feature",
  "properties": {
    "iso:country":"US",
    "sg:address":"8117 Preston Rd",
    "sg:city":"Dallas",
    "sg:classifiers":[
        {
            "category":"Organizations",
            "subcategory":"Non-profit Organization",
            "type":"Services"
        }
    ],
    "sg:phone":"+1 214 706 9211",
    "sg:postcode":"75225",
    "sg:province":"TX",
    "sg:tags":[
        "service/non-profit",
        "community"
    ],
    "sg:website":"www.cheersforcharity.com",
    "wof:name":"Cheers For Charity",
    "wof:placetype":"venue"
},
  "geometry": {"coordinates":[-96.804293,32.86158],"type":"Point"}
}