{
  "type": "Feature",
  "properties": {
    "iso:country":"US",
    "sg:address":"309 N Adelaide St",
    "sg:city":"Terrell",
    "sg:classifiers":[
        {
            "category":"Banks & Credit Unions",
            "subcategory":"Investment Brokerage",
            "type":"Services"
        }
    ],
    "sg:phone":"+1 972 524 0597",
    "sg:postcode":"75160",
    "sg:province":"TX",
    "sg:tags":[
        "security"
    ],
    "wof:name":"Bain Investment Svcs Inc",
    "wof:placetype":"venue"
},
  "geometry": {"coordinates":[-96.27584299999999,32.73905],"type":"Point"}
}