{
  "type": "Feature",
  "properties": {
    "iso:country":"US",
    "sg:address":"1403 Preston Ave",
    "sg:city":"Pasadena",
    "sg:classifiers":[
        {
            "category":"Retail",
            "subcategory":"Auto Repair",
            "type":"Services"
        }
    ],
    "sg:phone":"+1 713 472 9432",
    "sg:postcode":"77503",
    "sg:province":"TX",
    "sg:tags":[
        "repairing",
        "automobile"
    ],
    "sg:website":"http://www.donmooreautorepair.com",
    "wof:name":"Don Moore Auto Repair & A/C",
    "wof:placetype":"venue"
},
  "geometry": {"coordinates":[-95.17272199999999,29.69039],"type":"Point"}
}