{
  "type": "Feature",
  "properties": {
    "iso:country":"US",
    "sg:address":"622 S 11th St",
    "sg:city":"Mcallen",
    "sg:classifiers":[
        {
            "category":"Freight",
            "type":"Transportation"
        },
        {
            "category":"Home & Garden",
            "subcategory":"Household Appliances",
            "type":"Retail Goods"
        }
    ],
    "sg:phone":"+1 956 686 0721",
    "sg:postcode":"78501",
    "sg:province":"TX",
    "sg:tags":[
        "conditioner",
        "air",
        "special",
        "refrigerator",
        "repair"
    ],
    "wof:name":"Gateway Refrigeration Service",
    "wof:placetype":"venue"
},
  "geometry": {"coordinates":[-98.232259,26.19739],"type":"Point"}
}