{
  "type": "Feature",
  "properties": {
    "iso:country":"US",
    "sg:address":"5731 Cromo Dr",
    "sg:city":"El Paso",
    "sg:classifiers":[
        {
            "category":"Insurance",
            "subcategory":"Insurance Agent",
            "type":"Services"
        }
    ],
    "sg:phone":"+1 915 833 2971",
    "sg:postcode":"79912",
    "sg:province":"TX",
    "wof:name":"Gaspar De Alba Insurance",
    "wof:placetype":"venue"
},
  "geometry": {"coordinates":[-106.53836200000001,31.815366],"type":"Point"}
}