{
  "type": "Feature",
  "properties": {
    "iso:country":"US",
    "sg:address":"9102 Sterlingame Dr",
    "sg:city":"Houston",
    "sg:classifiers":[
        {
            "category":"Real Estate",
            "subcategory":"Real Estate Operator",
            "type":"Services"
        }
    ],
    "sg:phone":"+1 713 772 8769",
    "sg:postcode":"77031",
    "sg:province":"TX",
    "sg:tags":[
        "building",
        "apartment"
    ],
    "wof:name":"Seals Seals & Seals",
    "wof:placetype":"venue"
},
  "geometry": {"coordinates":[-95.54165,29.650766],"type":"Point"}
}