{
  "type": "Feature",
  "properties": {
    "iso:country":"US",
    "sg:address":"2517 E Illinois Ave",
    "sg:city":"Dallas",
    "sg:classifiers":[
        {
            "category":"Retail",
            "subcategory":"Funeral Services",
            "type":"Services"
        }
    ],
    "sg:phone":"+1 214 376 8297",
    "sg:postcode":"75216",
    "sg:province":"TX",
    "wof:name":"Black & Clark Funeral Home",
    "wof:placetype":"venue"
},
  "geometry": {"coordinates":[-96.783103,32.717017],"type":"Point"}
}