{
  "type": "Feature",
  "properties": {
    "iso:country":"US",
    "sg:address":"113 Claude Ave",
    "sg:city":"Cleburne",
    "sg:classifiers":[
        {
            "category":"Professional",
            "type":"Services"
        }
    ],
    "sg:phone":"+1 817 645 8961",
    "sg:postcode":"76031",
    "sg:province":"TX",
    "wof:name":"Mk Land Inc",
    "wof:placetype":"venue"
},
  "geometry": {"coordinates":[-97.389425,32.361452],"type":"Point"}
}