{
  "type": "Feature",
  "properties": {
    "iso:country":"US",
    "sg:address":"1612 Barclay Dr",
    "sg:city":"Carrollton",
    "sg:classifiers":[
        {
            "category":"Autos & Motor Vehicles",
            "subcategory":"Auto Supplies",
            "type":"Retail Goods"
        }
    ],
    "sg:phone":"+1 972 492 8255",
    "sg:postcode":"75007",
    "sg:province":"TX",
    "wof:name":"Phoenix Auto Parts Inc",
    "wof:placetype":"venue"
},
  "geometry": {"coordinates":[-96.900023,33.016045],"type":"Point"}
}