{
  "type": "Feature",
  "properties": {
    "iso:country":"US",
    "sg:address":"16235 Grassy Creek Dr",
    "sg:city":"Houston",
    "sg:classifiers":[
        {
            "category":"Real Estate",
            "subcategory":"Real Estate Agent",
            "type":"Services"
        }
    ],
    "sg:phone":"+1 281 556 5315",
    "sg:postcode":"77082",
    "sg:province":"TX",
    "sg:tags":[
        "investment"
    ],
    "wof:name":"Layman Investments",
    "wof:placetype":"venue"
},
  "geometry": {"coordinates":[-95.668586,29.714476],"type":"Point"}
}