{
  "type": "Feature",
  "properties": {
    "iso:country":"US",
    "sg:address":"University of Texas-Austin Speedway and 21st St",
    "sg:city":"Austin",
    "sg:classifiers":[
        {
            "category":"Education",
            "subcategory":"Library",
            "type":"Public Place"
        }
    ],
    "sg:phone":"+1 512 495 4250",
    "sg:postcode":"78798",
    "sg:province":"TX",
    "sg:website":"www.lib.utexas.edu/pcl",
    "wof:name":"Perry-Castaneda Library",
    "wof:placetype":"venue"
},
  "geometry": {"coordinates":[-97.73939900000001,30.286029],"type":"Point"}
}