{
  "type": "Feature",
  "properties": {
    "iso:country":"US",
    "sg:address":"1597 Glencairn Ln",
    "sg:city":"Lewisville",
    "sg:classifiers":[
        {
            "category":"Social Services",
            "subcategory":"Child Care",
            "type":"Services"
        }
    ],
    "sg:phone":"+1 972 436 2043",
    "sg:postcode":"75067",
    "sg:province":"TX",
    "wof:name":"Childtime Learning Ctr",
    "wof:placetype":"venue"
},
  "geometry": {"coordinates":[-97.035718,33.045665],"type":"Point"}
}