{
  "type": "Feature",
  "properties": {
    "iso:country":"US",
    "sg:address":"803 E Corsicana St",
    "sg:city":"Athens",
    "sg:classifiers":[
        {
            "category":"Shopping",
            "subcategory":"Gifts & Souvenirs",
            "type":"Retail Goods"
        }
    ],
    "sg:phone":"+1 903 675 2177",
    "sg:postcode":"75751",
    "sg:province":"TX",
    "wof:name":"Giftaskets",
    "wof:placetype":"venue"
},
  "geometry": {"coordinates":[-95.843203,32.204286],"type":"Point"}
}