{
  "type": "Feature",
  "properties": {
    "iso:country":"US",
    "sg:address":"1206 Barak Ln",
    "sg:city":"Bryan",
    "sg:classifiers":[
        {
            "category":"Professional",
            "subcategory":"Business Services",
            "type":"Services"
        }
    ],
    "sg:phone":"+1 979 691 0192",
    "sg:postcode":"77802",
    "sg:province":"TX",
    "wof:name":"Ellis Enterprises",
    "wof:placetype":"venue"
},
  "geometry": {"coordinates":[-96.343323,30.646837],"type":"Point"}
}