{
  "type": "Feature",
  "properties": {
    "iso:country":"US",
    "sg:address":"1201 Elm St",
    "sg:city":"Dallas",
    "sg:classifiers":[
        {
            "category":"Restaurant",
            "type":"Food & Drink"
        }
    ],
    "sg:phone":"+1 214 760 7230",
    "sg:postcode":"75202",
    "sg:province":"TX",
    "wof:name":"Downtown Eatz A Lot",
    "wof:placetype":"venue"
},
  "geometry": {"coordinates":[-96.801384,32.781047],"type":"Point"}
}