{
  "type": "Feature",
  "properties": {
    "iso:country":"US",
    "sg:address":"2831 San Gabriel St",
    "sg:city":"Austin",
    "sg:classifiers":[
        {
            "category":"Professional",
            "type":"Services"
        }
    ],
    "sg:phone":"+1 512 478 1417",
    "sg:postcode":"78705",
    "sg:province":"TX",
    "wof:name":"El Collectivo Digital",
    "wof:placetype":"venue"
},
  "geometry": {"coordinates":[-97.746855,30.297257],"type":"Point"}
}