{
  "type": "Feature",
  "properties": {
    "iso:country":"US",
    "sg:address":"12930 US Hwy 181",
    "sg:city":"San Antonio",
    "sg:classifiers":[
        {
            "category":"Bars & Pubs",
            "type":"Food & Drink"
        }
    ],
    "sg:phone":"+1 210 633 0868",
    "sg:postcode":"78223",
    "sg:province":"TX",
    "wof:name":"Papa Top's Saloon",
    "wof:placetype":"venue"
},
  "geometry": {"coordinates":[-98.353718,29.289991],"type":"Point"}
}