{
  "type": "Feature",
  "properties": {
    "iso:country":"US",
    "sg:address":"5307 West Loop 289",
    "sg:city":"Lubbock",
    "sg:classifiers":[
        {
            "category":"Professional",
            "subcategory":"Business Services",
            "type":"Services"
        }
    ],
    "sg:phone":"+1 806 771 5212",
    "sg:postcode":"79414",
    "sg:province":"TX",
    "sg:website":"http://www.xfone.com/",
    "wof:name":"XFONE",
    "wof:placetype":"venue"
},
  "geometry": {"coordinates":[-101.936727,33.54808],"type":"Point"}
}