{
  "type": "Feature",
  "properties": {
    "iso:country":"US",
    "sg:address":"711 Bay Area Blvd",
    "sg:city":"League City",
    "sg:classifiers":[
        {
            "category":"Insurance",
            "subcategory":"Insurance Agent",
            "type":"Services"
        }
    ],
    "sg:phone":"+1 281 332 2420",
    "sg:postcode":"77573",
    "sg:province":"TX",
    "wof:name":"Boozer Ins Agency",
    "wof:placetype":"venue"
},
  "geometry": {"coordinates":[-95.14788900000001,29.484719],"type":"Point"}
}