{
  "type": "Feature",
  "properties": {
    "iso:country":"US",
    "sg:address":"565 W Oates Rd Ste 166",
    "sg:city":"Garland",
    "sg:classifiers":[
        {
            "category":"Retail",
            "subcategory":"Laundry & Dry Cleaning",
            "type":"Services"
        }
    ],
    "sg:phone":"+1 972 613 7872",
    "sg:postcode":"75043",
    "sg:province":"TX",
    "wof:name":"Audubon Cleaners",
    "wof:placetype":"venue"
},
  "geometry": {"coordinates":[-96.618599,32.846901],"type":"Point"}
}