{
  "type": "Feature",
  "properties": {
    "iso:country":"US",
    "sg:address":"1102 Foley St",
    "sg:city":"Henderson",
    "sg:classifiers":[
        {
            "category":"Professional",
            "type":"Services"
        }
    ],
    "sg:phone":"+1 903 657 3025",
    "sg:postcode":"75654",
    "sg:province":"TX",
    "wof:name":"Bill Davis & JJ Bazar",
    "wof:placetype":"venue"
},
  "geometry": {"coordinates":[-94.82248800000001,32.13985],"type":"Point"}
}