{
  "type": "Feature",
  "properties": {
    "iso:country":"US",
    "sg:address":"5307 Mockingbird Ln",
    "sg:city":"Dallas",
    "sg:classifiers":[
        {
            "category":"Insurance",
            "subcategory":"Hazard Insurance",
            "type":"Services"
        },
        {
            "category":"Insurance",
            "subcategory":"Insurance Agent",
            "type":"Services"
        }
    ],
    "sg:phone":"+1 214 821 4777",
    "sg:postcode":"75206",
    "sg:province":"TX",
    "sg:tags":[
        "sharing",
        "profit",
        "consultant",
        "retirement",
        "pension",
        "or",
        "plan"
    ],
    "wof:name":"Baldwin & Smith Inc",
    "wof:placetype":"venue"
},
  "geometry": {"coordinates":[-96.77866299999999,32.836585],"type":"Point"}
}