{
  "type": "Feature",
  "properties": {
    "iso:country":"US",
    "sg:address":"4950 Lazy Timbers Dr",
    "sg:city":"Humble",
    "sg:classifiers":[
        {
            "category":"Professional",
            "subcategory":"Business Services",
            "type":"Services"
        }
    ],
    "sg:phone":"+1 281 812 3929",
    "sg:postcode":"77346",
    "sg:province":"TX",
    "wof:name":"Webtex Solutions LLC",
    "wof:placetype":"venue"
},
  "geometry": {"coordinates":[-95.19865799999999,29.982897],"type":"Point"}
}