{
  "type": "Feature",
  "properties": {
    "iso:country":"US",
    "sg:address":"18959 Dallas Pkwy",
    "sg:city":"Dallas",
    "sg:classifiers":[
        {
            "category":"Shopping",
            "subcategory":"Clothing, Apparel, & Fashions",
            "type":"Retail Goods"
        }
    ],
    "sg:phone":"+1 214 485 2605",
    "sg:postcode":"75287",
    "sg:province":"TX",
    "wof:name":"Two Buttons/ Original Lemonade",
    "wof:placetype":"venue"
},
  "geometry": {"coordinates":[-96.829931,33.011289],"type":"Point"}
}