{
  "type": "Feature",
  "properties": {
    "iso:country":"US",
    "sg:address":"1017 S San Jose Dr",
    "sg:city":"Abilene",
    "sg:classifiers":[
        {
            "category":"Building & Trades",
            "subcategory":"Landscaping Services",
            "type":"Services"
        }
    ],
    "sg:phone":"+1 325 695 1382",
    "sg:postcode":"79605",
    "sg:province":"TX",
    "wof:name":"Rogers Lawn and Tree Service",
    "wof:placetype":"venue"
},
  "geometry": {"coordinates":[-99.783377,32.438183],"type":"Point"}
}