{
  "type": "Feature",
  "properties": {
    "iso:country":"US",
    "sg:address":"430 Foxglove Ln",
    "sg:city":"Houston",
    "sg:classifiers":[
        {
            "category":"Autos & Motor Vehicles",
            "subcategory":"Auto Supplies",
            "type":"Retail Goods"
        }
    ],
    "sg:phone":"+1 713 695 2836",
    "sg:postcode":"77076",
    "sg:province":"TX",
    "wof:name":"Invasion Musical",
    "wof:placetype":"venue"
},
  "geometry": {"coordinates":[-95.39143300000001,29.849318],"type":"Point"}
}