{
  "type": "Feature",
  "properties": {
    "iso:country":"US",
    "sg:address":"4809 Wellington Ct",
    "sg:city":"Temple",
    "sg:classifiers":[
        {
            "category":"Health Services",
            "subcategory":"Chiropractor",
            "type":"Services"
        }
    ],
    "sg:phone":"+1 254 778 0828",
    "sg:postcode":"76502",
    "sg:province":"TX",
    "wof:name":"Diagnostic & Pain Clinic",
    "wof:placetype":"venue"
},
  "geometry": {"coordinates":[-97.39040900000001,31.058564],"type":"Point"}
}