{
  "type": "Feature",
  "properties": {
    "iso:country":"US",
    "sg:address":"2604 Mayfield Rd",
    "sg:city":"Grand Prairie",
    "sg:classifiers":[
        {
            "category":"Professional",
            "subcategory":"Business Services",
            "type":"Services"
        }
    ],
    "sg:phone":"+1 972 602 2209",
    "sg:postcode":"75052",
    "sg:province":"TX",
    "sg:tags":[
        "liquidator"
    ],
    "wof:name":"Liquidation Center",
    "wof:placetype":"venue"
},
  "geometry": {"coordinates":[-97.04598,32.691345],"type":"Point"}
}