{
  "type": "Feature",
  "properties": {
    "iso:country":"US",
    "sg:address":"6334 Marrogot Run St",
    "sg:city":"San Antonio",
    "sg:classifiers":[
        {
            "category":"Restaurant",
            "type":"Food & Drink"
        }
    ],
    "sg:phone":"+1 210 656 4032",
    "sg:postcode":"78233",
    "sg:province":"TX",
    "sg:tags":[
        "caterer"
    ],
    "wof:name":"Creative Chef",
    "wof:placetype":"venue"
},
  "geometry": {"coordinates":[-98.362212,29.558801],"type":"Point"}
}