{
  "type": "Feature",
  "properties": {
    "iso:country":"US",
    "sg:address":"8305 Lone Shadow Trl",
    "sg:city":"Converse",
    "sg:classifiers":[
        {
            "category":"Personal",
            "type":"Services"
        }
    ],
    "sg:phone":"+1 210 659 6178",
    "sg:postcode":"78109",
    "sg:province":"TX",
    "sg:tags":[
        "butlers'",
        "maids'"
    ],
    "wof:name":"Pops In Merry",
    "wof:placetype":"venue"
},
  "geometry": {"coordinates":[-98.325276,29.534003],"type":"Point"}
}