{
  "type": "Feature",
  "properties": {
    "iso:country":"US",
    "sg:address":"4100 Westheimer Rd",
    "sg:city":"Houston",
    "sg:classifiers":[
        {
            "category":"Banks & Credit Unions",
            "subcategory":"Financial Services",
            "type":"Services"
        }
    ],
    "sg:phone":"+1 713 960 9212",
    "sg:postcode":"77027",
    "sg:province":"TX",
    "sg:tags":[
        "trader",
        "royalty",
        "oil"
    ],
    "wof:name":"Frank C Nelms Inc",
    "wof:placetype":"venue"
},
  "geometry": {"coordinates":[-95.44826500000001,29.741623],"type":"Point"}
}