{
  "type": "Feature",
  "properties": {
    "iso:country":"US",
    "sg:address":"609 Bessemer Ave",
    "sg:city":"Llano",
    "sg:classifiers":[
        {
            "category":"Travel",
            "subcategory":"Hotels & Motels",
            "type":"Entertainment"
        }
    ],
    "sg:phone":"+1 325 247 1141",
    "sg:postcode":"78643",
    "sg:province":"TX",
    "sg:tags":[
        "lodging"
    ],
    "sg:website":"http://www.daysinn.com",
    "wof:name":"Days Inn",
    "wof:placetype":"venue"
},
  "geometry": {"coordinates":[-98.675613,30.756841],"type":"Point"}
}