{
  "type": "Feature",
  "properties": {
    "iso:country":"US",
    "sg:address":"904 College St",
    "sg:city":"Junction",
    "sg:classifiers":[
        {
            "category":"Organizations",
            "subcategory":"Membership Organization",
            "type":"Services"
        },
        {
            "category":"Insurance",
            "subcategory":"Insurance Agent",
            "type":"Services"
        }
    ],
    "sg:phone":"+1 325 446 2561",
    "sg:postcode":"76849",
    "sg:province":"TX",
    "wof:name":"Kimble County Farm Bureau Inc",
    "wof:placetype":"venue"
},
  "geometry": {"coordinates":[-99.770821,30.488388],"type":"Point"}
}