{
  "type": "Feature",
  "properties": {
    "iso:country":"US",
    "sg:address":"5706 E Mockingbird Ln",
    "sg:city":"Dallas",
    "sg:classifiers":[
        {
            "category":"Arts & Performance",
            "subcategory":"Art Gallery",
            "type":"Entertainment"
        }
    ],
    "sg:phone":"+1 214 821 9184",
    "sg:postcode":"75206",
    "sg:province":"TX",
    "wof:name":"3 Day Framing & Gallery",
    "wof:placetype":"venue"
},
  "geometry": {"coordinates":[-96.769997,32.836498],"type":"Point"}
}