{
  "type": "Feature",
  "properties": {
    "iso:country":"US",
    "sg:address":"12214 Three Lakes Blvd",
    "sg:city":"Tomball",
    "sg:classifiers":[
        {
            "category":"Wholesale",
            "subcategory":"Medical Equipment & Supplies",
            "type":"Manufacturing & Wholesale Goods"
        }
    ],
    "sg:phone":"+1 281 351 0002",
    "sg:postcode":"77375",
    "sg:province":"TX",
    "sg:tags":[
        "microscope"
    ],
    "wof:name":"Laboratory Instrument Care",
    "wof:placetype":"venue"
},
  "geometry": {"coordinates":[-95.605474,30.047448],"type":"Point"}
}