{
  "type": "Feature",
  "properties": {
    "iso:country":"US",
    "sg:address":"1626 Dunlavy St",
    "sg:city":"Houston",
    "sg:classifiers":[
        {
            "category":"Shopping",
            "subcategory":"Used Merchandise",
            "type":"Retail Goods"
        }
    ],
    "sg:phone":"+1 713 533 0293",
    "sg:postcode":"77006",
    "sg:province":"TX",
    "wof:name":"Fleur De lis",
    "wof:placetype":"venue"
},
  "geometry": {"coordinates":[-95.40226699999999,29.751832],"type":"Point"}
}