{
  "type": "Feature",
  "properties": {
    "iso:country":"US",
    "sg:address":"140 Pecan St",
    "sg:city":"Blossom",
    "sg:classifiers":[
        {
            "category":"Manufacturing",
            "subcategory":"Tools & Machinery",
            "type":"Manufacturing & Wholesale Goods"
        }
    ],
    "sg:phone":"+1 903 982 6459",
    "sg:postcode":"75416",
    "sg:province":"TX",
    "sg:tags":[
        "industrial"
    ],
    "wof:name":"Goodin Machine",
    "wof:placetype":"venue"
},
  "geometry": {"coordinates":[-95.39346,33.661632],"type":"Point"}
}