{
  "type": "Feature",
  "properties": {
    "iso:country":"US",
    "sg:address":"610 S 17th St",
    "sg:city":"Mcallen",
    "sg:classifiers":[
        {
            "category":"Professional",
            "subcategory":"Accounting & Tax Preparation",
            "type":"Services"
        }
    ],
    "sg:phone":"+1 956 664 2498",
    "sg:postcode":"78501",
    "sg:province":"TX",
    "sg:tags":[
        "return",
        "filing"
    ],
    "wof:name":"Cortez Maribel Income Tax",
    "wof:placetype":"venue"
},
  "geometry": {"coordinates":[-98.23891500000001,26.198193],"type":"Point"}
}