{
  "type": "Feature",
  "properties": {
    "iso:country":"US",
    "sg:address":"604 Preakness Dr",
    "sg:city":"Copperas Cove",
    "sg:classifiers":[
        {
            "category":"Professional",
            "type":"Services"
        }
    ],
    "sg:phone":"+1 254 698 6957",
    "sg:postcode":"76522",
    "sg:province":"TX",
    "wof:name":"Latashas Errand Service",
    "wof:placetype":"venue"
},
  "geometry": {"coordinates":[-97.894024,31.107952],"type":"Point"}
}