{
  "type": "Feature",
  "properties": {
    "iso:country":"US",
    "sg:address":"1800 Heidelburg Dr",
    "sg:city":"Fort Worth",
    "sg:classifiers":[
        {
            "category":"Building & Trades",
            "subcategory":"Construction",
            "type":"Services"
        }
    ],
    "sg:phone":"+1 817 293 0110",
    "sg:postcode":"76134",
    "sg:province":"TX",
    "sg:tags":[
        "carpentry",
        "contractor"
    ],
    "wof:name":"Fgm Carpentry",
    "wof:placetype":"venue"
},
  "geometry": {"coordinates":[-97.346946,32.645939],"type":"Point"}
}