{
  "type": "Feature",
  "properties": {
    "iso:country":"US",
    "sg:address":"401 E Buffalo St",
    "sg:city":"Forney",
    "sg:classifiers":[
        {
            "category":"Retail",
            "subcategory":"Auto Repair",
            "type":"Services"
        }
    ],
    "sg:phone":"+1 972 564 5410",
    "sg:postcode":"75126",
    "sg:province":"TX",
    "sg:tags":[
        "general"
    ],
    "wof:name":"Mr Mobile Mechanic",
    "wof:placetype":"venue"
},
  "geometry": {"coordinates":[-96.465767,32.747585],"type":"Point"}
}