{
  "type": "Feature",
  "properties": {
    "iso:country":"US",
    "sg:address":"1209 Fountain Pkwy",
    "sg:city":"Grand Prairie",
    "sg:classifiers":[
        {
            "category":"Deli",
            "type":"Food & Drink"
        }
    ],
    "sg:menulink":"http://www.allmenus.com/tx/arlington/126763-blimpie-subs--sandwiches/menu/",
    "sg:phone":"+1 972 660 7010",
    "sg:postcode":"75050",
    "sg:province":"TX",
    "sg:tags":[
        "wrap",
        "american",
        "sandwich"
    ],
    "wof:name":"Blimpie Subs & Sandwiches",
    "wof:placetype":"venue"
},
  "geometry": {"coordinates":[-97.048175,32.779424],"type":"Point"}
}