{
  "type": "Feature",
  "properties": {
    "iso:country":"US",
    "sg:address":"6911 Ranch Rd 620 N",
    "sg:city":"Austin",
    "sg:classifiers":[
        {
            "category":"Banks & Credit Unions",
            "subcategory":"Bank",
            "type":"Services"
        }
    ],
    "sg:phone":"+1 512 344 7000",
    "sg:postcode":"78732",
    "sg:province":"TX",
    "wof:name":"Wells Fargo Bank",
    "wof:placetype":"venue"
},
  "geometry": {"coordinates":[-97.85539799999999,30.401196],"type":"Point"}
}