{
  "type": "Feature",
  "properties": {
    "iso:country":"US",
    "sg:address":"1015 E 8th St",
    "sg:city":"Odessa",
    "sg:classifiers":[
        {
            "category":"Restaurant",
            "type":"Food & Drink"
        }
    ],
    "sg:phone":"+1 432 337 5141",
    "sg:postcode":"79761",
    "sg:province":"TX",
    "sg:tags":[
        "eating"
    ],
    "wof:name":"Sonic Drive-In",
    "wof:placetype":"venue"
},
  "geometry": {"coordinates":[-102.361203,31.856425],"type":"Point"}
}