{
  "type": "Feature",
  "properties": {
    "iso:country":"US",
    "sg:address":"1217 Crockett St",
    "sg:city":"Garland",
    "sg:classifiers":[
        {
            "category":"Shopping",
            "subcategory":"Gifts & Souvenirs",
            "type":"Retail Goods"
        }
    ],
    "sg:phone":"+1 972 272 8652",
    "sg:postcode":"75040",
    "sg:province":"TX",
    "wof:name":"Jeffery Scott Foley",
    "wof:placetype":"venue"
},
  "geometry": {"coordinates":[-96.646674,32.926266],"type":"Point"}
}