{
  "type": "Feature",
  "properties": {
    "iso:country":"US",
    "sg:address":"910 Travis St",
    "sg:city":"Houston",
    "sg:classifiers":[
        {
            "category":"Travel",
            "subcategory":"Campground",
            "type":"Entertainment"
        }
    ],
    "sg:phone":"+1 713 655 1492",
    "sg:postcode":"77002",
    "sg:province":"TX",
    "sg:tags":[
        "camp"
    ],
    "wof:name":"Double Diamnd Land & Cattle Co",
    "wof:placetype":"venue"
},
  "geometry": {"coordinates":[-95.36581,29.757591],"type":"Point"}
}