{
  "type": "Feature",
  "properties": {
    "iso:country":"US",
    "sg:address":"816 Congress Ave Ste 1130",
    "sg:city":"Austin",
    "sg:classifiers":[
        {
            "category":"Shopping",
            "subcategory":"Jewelry",
            "type":"Retail Goods"
        }
    ],
    "sg:phone":"+1 512 472 1212",
    "sg:postcode":"78701",
    "sg:province":"TX",
    "wof:name":"KONA-LTD",
    "wof:placetype":"venue"
},
  "geometry": {"coordinates":[-97.742082,30.270091],"type":"Point"}
}