{
  "type": "Feature",
  "properties": {
    "iso:country":"US",
    "sg:address":"12333 Fondren Rd",
    "sg:city":"Houston",
    "sg:classifiers":[
        {
            "category":"Shopping",
            "subcategory":"Music",
            "type":"Retail Goods"
        }
    ],
    "sg:phone":"+1 713 723 6519",
    "sg:postcode":"77035",
    "sg:province":"TX",
    "sg:tags":[
        "record",
        "tape",
        "dvd's"
    ],
    "wof:name":"Turntable II Records & Tapes",
    "wof:placetype":"venue"
},
  "geometry": {"coordinates":[-95.50810199999999,29.6439],"type":"Point"}
}