{
  "type": "Feature",
  "properties": {
    "iso:country":"US",
    "sg:address":"2328 E Grauwyler Rd",
    "sg:city":"Irving",
    "sg:classifiers":[
        {
            "category":"Social Services",
            "subcategory":"Child Care",
            "type":"Services"
        },
        {
            "category":"Education",
            "subcategory":"Preschool",
            "type":"Public Place"
        },
        {
            "category":"Education",
            "subcategory":"School",
            "type":"Public Place"
        }
    ],
    "sg:phone":"+1 972 438 3969",
    "sg:postcode":"75061",
    "sg:province":"TX",
    "sg:tags":[
        "elementary",
        "day"
    ],
    "sg:website":"www.iacwds.com",
    "wof:name":"It's A Child's World Day School Inc",
    "wof:placetype":"venue"
},
  "geometry": {"coordinates":[-96.9114,32.830601],"type":"Point"}
}