{
  "type": "Feature",
  "properties": {
    "iso:country":"US",
    "sg:address":"152 Pennsylvania Blvd",
    "sg:city":"New Braunfels",
    "sg:classifiers":[
        {
            "category":"Professional",
            "subcategory":"Lawyer & Legal Services",
            "type":"Services"
        }
    ],
    "sg:phone":"+1 830 629 1300",
    "sg:postcode":"78130",
    "sg:province":"TX",
    "sg:tags":[
        "law"
    ],
    "wof:name":"Tate Susan G Attorney-At-Law",
    "wof:placetype":"venue"
},
  "geometry": {"coordinates":[-98.14343700000001,29.713069],"type":"Point"}
}