{
  "type": "Feature",
  "properties": {
    "iso:country":"US",
    "sg:address":"2993 Sandia St",
    "sg:city":"Brownsville",
    "sg:classifiers":[
        {
            "category":"Freight",
            "type":"Transportation"
        }
    ],
    "sg:phone":"+1 956 831 4232",
    "sg:postcode":"78521",
    "sg:province":"TX",
    "sg:tags":[
        "metal",
        "center",
        "general"
    ],
    "wof:name":"Roll & Hold",
    "wof:placetype":"venue"
},
  "geometry": {"coordinates":[-97.459524,25.903158],"type":"Point"}
}