{
  "type": "Feature",
  "properties": {
    "iso:country":"US",
    "sg:address":"8041 Walnut Hill Ln",
    "sg:city":"Dallas",
    "sg:classifiers":[
        {
            "category":"Personal",
            "type":"Services"
        }
    ],
    "sg:phone":"+1 214 692 8442",
    "sg:postcode":"75230",
    "sg:province":"TX",
    "sg:tags":[
        "wedding",
        "chapel"
    ],
    "wof:name":"Le Renaissance Wedding Fcilty",
    "wof:placetype":"venue"
},
  "geometry": {"coordinates":[-96.77056,32.880086],"type":"Point"}
}