{
  "type": "Feature",
  "properties": {
    "iso:country":"US",
    "sg:address":"8181 Jetstar Dr",
    "sg:city":"Irving",
    "sg:classifiers":[
        {
            "category":"Utilities",
            "subcategory":"Telephone",
            "type":"Services"
        }
    ],
    "sg:phone":"+1 214 441 3938",
    "sg:postcode":"75063",
    "sg:province":"TX",
    "sg:tags":[
        "telecommunication"
    ],
    "wof:name":"Net 2 Phone",
    "wof:placetype":"venue"
},
  "geometry": {"coordinates":[-97.002709,32.91838],"type":"Point"}
}