{
  "type": "Feature",
  "properties": {
    "iso:country":"US",
    "sg:address":"5303 Weatherstone Cir",
    "sg:city":"Sugar Land",
    "sg:classifiers":[
        {
            "category":"Professional",
            "type":"Services"
        }
    ],
    "sg:phone":"+1 281 313 4316",
    "sg:postcode":"77479",
    "sg:province":"TX",
    "wof:name":"Bestautojobscom",
    "wof:placetype":"venue"
},
  "geometry": {"coordinates":[-95.636972,29.560569],"type":"Point"}
}