{
  "type": "Feature",
  "properties": {
    "iso:country":"US",
    "sg:address":"11026 Timbergrove Ln",
    "sg:city":"Corpus Christi",
    "sg:classifiers":[
        {
            "category":"Building & Trades",
            "subcategory":"Electrical",
            "type":"Services"
        }
    ],
    "sg:phone":"+1 512 265 0776",
    "sg:postcode":"78410",
    "sg:province":"TX",
    "sg:tags":[
        "electric",
        "contractor"
    ],
    "wof:name":"L L Specialty Svc Inc",
    "wof:placetype":"venue"
},
  "geometry": {"coordinates":[-97.582399,27.845989],"type":"Point"}
}