{
  "type": "Feature",
  "properties": {
    "iso:country":"US",
    "sg:address":"10707 Lynnhaven Ave",
    "sg:city":"Lubbock",
    "sg:classifiers":[
        {
            "category":"Building & Trades",
            "subcategory":"Landscaping Services",
            "type":"Services"
        }
    ],
    "sg:phone":"+1 806 745 1014",
    "sg:postcode":"79423",
    "sg:province":"TX",
    "sg:tags":[
        "lawn",
        "maintenance"
    ],
    "wof:name":"Lubbock Lights",
    "wof:placetype":"venue"
},
  "geometry": {"coordinates":[-101.89437100000001,33.497253],"type":"Point"}
}