{
  "type": "Feature",
  "properties": {
    "iso:country":"US",
    "sg:address":"603 County Road 6027",
    "sg:city":"Dayton",
    "sg:classifiers":[
        {
            "category":"Shopping",
            "subcategory":"Pets & Pet Supplies",
            "type":"Retail Goods"
        }
    ],
    "sg:phone":"+1 936 257 2506",
    "sg:postcode":"77535",
    "sg:province":"TX",
    "sg:tags":[
        "training"
    ],
    "wof:name":"Twin Rivers Retrievers",
    "wof:placetype":"venue"
},
  "geometry": {"coordinates":[-95.01666299999999,30.005684],"type":"Point"}
}