{
  "type": "Feature",
  "properties": {
    "iso:country":"US",
    "sg:address":"16944 State Hwy 3",
    "sg:city":"Webster",
    "sg:classifiers":[
        {
            "category":"Insurance",
            "subcategory":"Insurance Agent",
            "type":"Services"
        }
    ],
    "sg:phone":"+1 281 338 1955",
    "sg:postcode":"77598",
    "sg:province":"TX",
    "wof:name":"State Farm Insurance",
    "wof:placetype":"venue"
},
  "geometry": {"coordinates":[-95.127393,29.547407],"type":"Point"}
}