{
  "type": "Feature",
  "properties": {
    "iso:country":"US",
    "sg:address":"4760 Barwick Dr",
    "sg:city":"Fort Worth",
    "sg:classifiers":[
        {
            "category":"Health Services",
            "subcategory":"Doctor",
            "type":"Services"
        }
    ],
    "sg:phone":"+1 817 346 9533",
    "sg:postcode":"76132",
    "sg:province":"TX",
    "sg:tags":[
        "physician",
        "surgeon"
    ],
    "wof:name":"Texas Health Care",
    "wof:placetype":"venue"
},
  "geometry": {"coordinates":[-97.394751,32.677473],"type":"Point"}
}