{
  "type": "Feature",
  "properties": {
    "iso:country":"US",
    "sg:address":"1115 W 43rd St",
    "sg:city":"Houston",
    "sg:classifiers":[
        {
            "category":"Professional",
            "subcategory":"Lawyer & Legal Services",
            "type":"Services"
        }
    ],
    "sg:phone":"+1 713 688 1522",
    "sg:postcode":"77018",
    "sg:province":"TX",
    "sg:tags":[
        "attorney"
    ],
    "wof:name":"Jack P Mixa",
    "wof:placetype":"venue"
},
  "geometry": {"coordinates":[-95.42946999999999,29.828212],"type":"Point"}
}