{
  "type": "Feature",
  "properties": {
    "iso:country":"US",
    "sg:address":"2521 Strawberry Rd",
    "sg:city":"Pasadena",
    "sg:classifiers":[
        {
            "category":"Home & Garden",
            "subcategory":"Household Appliances",
            "type":"Retail Goods"
        }
    ],
    "sg:phone":"+1 713 944 2870",
    "sg:postcode":"77502",
    "sg:province":"TX",
    "sg:tags":[
        "cleaners",
        "vacuum"
    ],
    "wof:name":"Bo-Jac Motors",
    "wof:placetype":"venue"
},
  "geometry": {"coordinates":[-95.192937,29.67369],"type":"Point"}
}