{
  "type": "Feature",
  "properties": {
    "iso:country":"US",
    "sg:address":"2150 Paredes Line Rd",
    "sg:city":"Brownsville",
    "sg:classifiers":[
        {
            "category":"Restaurant",
            "type":"Food & Drink"
        }
    ],
    "sg:menulink":"http://www.allmenus.com/tx/brownsville/177332-jack-in-the-box/menu/",
    "sg:phone":"+1 956 550 8994",
    "sg:postcode":"78521",
    "sg:province":"TX",
    "sg:tags":[
        "burger",
        "american"
    ],
    "wof:name":"Jack in the Box",
    "wof:placetype":"venue"
},
  "geometry": {"coordinates":[-97.48699999999999,25.950613],"type":"Point"}
}