{
  "type": "Feature",
  "properties": {
    "iso:country":"US",
    "sg:address":"1511 Nantucket Dr",
    "sg:city":"Houston",
    "sg:classifiers":[
        {
            "category":"Mining & Drilling",
            "type":"Manufacturing & Wholesale Goods"
        }
    ],
    "sg:phone":"+1 713 278 9480",
    "sg:postcode":"77057",
    "sg:province":"TX",
    "sg:tags":[
        "exploration"
    ],
    "wof:name":"Pecos International LLC",
    "wof:placetype":"venue"
},
  "geometry": {"coordinates":[-95.48734,29.751998],"type":"Point"}
}