{
  "type": "Feature",
  "properties": {
    "iso:country":"US",
    "sg:address":"10941 Spruce Dr S",
    "sg:city":"La Porte",
    "sg:classifiers":[
        {
            "category":"Professional",
            "subcategory":"Advertising",
            "type":"Services"
        }
    ],
    "sg:phone":"+1 281 471 4909",
    "sg:postcode":"77571",
    "sg:province":"TX",
    "sg:tags":[
        "agency"
    ],
    "wof:name":"Impact Advertising",
    "wof:placetype":"venue"
},
  "geometry": {"coordinates":[-95.06273,29.661413],"type":"Point"}
}