{
  "type": "Feature",
  "properties": {
    "iso:country":"US",
    "sg:address":"11128 Harry Hines Blvd",
    "sg:city":"Dallas",
    "sg:classifiers":[
        {
            "category":"Autos & Motor Vehicles",
            "subcategory":"Automobile Sales",
            "type":"Retail Goods"
        }
    ],
    "sg:phone":"+1 214 946 0076",
    "sg:postcode":"75229",
    "sg:province":"TX",
    "sg:tags":[
        "car",
        "dealer"
    ],
    "wof:name":"M & O Finance Auto Sales",
    "wof:placetype":"venue"
},
  "geometry": {"coordinates":[-96.88750400000001,32.886576],"type":"Point"}
}