{
  "type": "Feature",
  "properties": {
    "iso:country":"US",
    "sg:address":"617 Waco Rd",
    "sg:city":"Belton",
    "sg:classifiers":[
        {
            "category":"Home & Garden",
            "subcategory":"Building Materials",
            "type":"Retail Goods"
        }
    ],
    "sg:phone":"+1 254 770 0368",
    "sg:postcode":"76513",
    "sg:province":"TX",
    "sg:tags":[
        "glass",
        "window",
        "plate"
    ],
    "wof:name":"A Better Buy Auto Glass",
    "wof:placetype":"venue"
},
  "geometry": {"coordinates":[-97.455448,31.060874],"type":"Point"}
}