{
  "type": "Feature",
  "properties": {
    "iso:country":"US",
    "sg:address":"617 Rossville Rd",
    "sg:city":"Devine",
    "sg:classifiers":[
        {
            "category":"Building & Trades",
            "subcategory":"Construction",
            "type":"Services"
        }
    ],
    "sg:phone":"+1 830 663 5517",
    "sg:postcode":"78016",
    "sg:province":"TX",
    "sg:tags":[
        "residential"
    ],
    "wof:name":"Tonys Building & Construction",
    "wof:placetype":"venue"
},
  "geometry": {"coordinates":[-98.89682000000001,29.138087],"type":"Point"}
}