{
  "type": "Feature",
  "properties": {
    "iso:country":"US",
    "sg:address":"226 W Bitters Rd",
    "sg:city":"San Antonio",
    "sg:classifiers":[
        {
            "category":"Food & Beverages",
            "subcategory":"Liquor & Beverages",
            "type":"Retail Goods"
        }
    ],
    "sg:phone":"+1 210 490 5553",
    "sg:postcode":"78216",
    "sg:province":"TX",
    "wof:name":"Falls",
    "wof:placetype":"venue"
},
  "geometry": {"coordinates":[-98.4862,29.567652],"type":"Point"}
}