{
  "type": "Feature",
  "properties": {
    "iso:country":"US",
    "sg:address":"300 Stagecoach Ln",
    "sg:city":"Royse City",
    "sg:classifiers":[
        {
            "category":"Shopping",
            "subcategory":"Florist",
            "type":"Retail Goods"
        }
    ],
    "sg:phone":"+1 972 524 0930",
    "sg:postcode":"75189",
    "sg:province":"TX",
    "wof:name":"Mama Lou's Flowers & Gifts",
    "wof:placetype":"venue"
},
  "geometry": {"coordinates":[-96.306939,32.860308],"type":"Point"}
}