{
  "type": "Feature",
  "properties": {
    "iso:country":"US",
    "sg:address":"504 Barclay St",
    "sg:city":"San Antonio",
    "sg:classifiers":[
        {
            "category":"Health Services",
            "subcategory":"Doctor",
            "type":"Services"
        }
    ],
    "sg:phone":"+1 210 431 7711",
    "sg:postcode":"78207",
    "sg:province":"TX",
    "sg:tags":[
        "dentist"
    ],
    "wof:name":"Alamo Dental Ctr",
    "wof:placetype":"venue"
},
  "geometry": {"coordinates":[-98.541791,29.419427],"type":"Point"}
}