{
  "type": "Feature",
  "properties": {
    "iso:country":"US",
    "sg:address":"3617 Harris Dr",
    "sg:city":"Corpus Christi",
    "sg:classifiers":[
        {
            "category":"Building & Trades",
            "subcategory":"Construction",
            "type":"Services"
        }
    ],
    "sg:phone":"+1 361 854 0674",
    "sg:postcode":"78411",
    "sg:province":"TX",
    "sg:tags":[
        "residential"
    ],
    "wof:name":"JRS Construction",
    "wof:placetype":"venue"
},
  "geometry": {"coordinates":[-97.39731399999999,27.738143],"type":"Point"}
}