{
  "type": "Feature",
  "properties": {
    "iso:country":"US",
    "sg:address":"18910 Fm 2493",
    "sg:city":"Flint",
    "sg:classifiers":[
        {
            "category":"Shopping",
            "subcategory":"Crafts & Fabrics",
            "type":"Retail Goods"
        }
    ],
    "sg:phone":"+1 903 894 3503",
    "sg:postcode":"75762",
    "sg:province":"TX",
    "sg:tags":[
        "art",
        "supply"
    ],
    "wof:name":"Craft Corner",
    "wof:placetype":"venue"
},
  "geometry": {"coordinates":[-95.348759,32.205424],"type":"Point"}
}