{
  "type": "Feature",
  "properties": {
    "iso:country":"US",
    "sg:address":"2124 E Hwy 190",
    "sg:city":"Copperas Cove",
    "sg:classifiers":[
        {
            "category":"Food & Beverages",
            "subcategory":"Groceries & Convenience Stores",
            "type":"Retail Goods"
        }
    ],
    "sg:phone":"+1 254 547 3555",
    "sg:postcode":"76522",
    "sg:province":"TX",
    "wof:name":"7-Eleven",
    "wof:placetype":"venue"
},
  "geometry": {"coordinates":[-97.882024,31.120261],"type":"Point"}
}