{
  "type": "Feature",
  "properties": {
    "iso:country":"US",
    "sg:address":"76 Benton Woods Ct",
    "sg:city":"Spring",
    "sg:classifiers":[
        {
            "category":"Professional",
            "type":"Services"
        }
    ],
    "sg:phone":"+1 281 364 9188",
    "sg:postcode":"77382",
    "sg:province":"TX",
    "sg:tags":[
        "store",
        "furniture"
    ],
    "wof:name":"Felton Interests Inc",
    "wof:placetype":"venue"
},
  "geometry": {"coordinates":[-95.54038,30.204307],"type":"Point"}
}