{
  "type": "Feature",
  "properties": {
    "iso:country":"US",
    "sg:address":"2701 Willow Spring",
    "sg:city":"Bulverde",
    "sg:classifiers":[
        {
            "category":"Building & Trades",
            "subcategory":"Construction",
            "type":"Services"
        }
    ],
    "sg:phone":"+1 830 980 9404",
    "sg:postcode":"78163",
    "sg:province":"TX",
    "sg:tags":[
        "home",
        "family",
        "contractor"
    ],
    "wof:name":"A Rendon Construction Co",
    "wof:placetype":"venue"
},
  "geometry": {"coordinates":[-98.497928,29.802244],"type":"Point"}
}