{
  "type": "Feature",
  "properties": {
    "iso:country":"US",
    "sg:address":"15384 Tradesman",
    "sg:city":"San Antonio",
    "sg:classifiers":[
        {
            "category":"Retail",
            "subcategory":"Auto Repair",
            "type":"Services"
        }
    ],
    "sg:phone":"+1 210 492 0070",
    "sg:postcode":"78249",
    "sg:province":"TX",
    "sg:tags":[
        "body"
    ],
    "wof:name":"Artisan Auto",
    "wof:placetype":"venue"
},
  "geometry": {"coordinates":[-98.585089,29.588828],"type":"Point"}
}