{
  "type": "Feature",
  "properties": {
    "iso:country":"US",
    "sg:address":"1301 N 4th St",
    "sg:city":"Wichita Falls",
    "sg:classifiers":[
        {
            "category":"Organizations",
            "subcategory":"Religious Organization",
            "type":"Services"
        }
    ],
    "sg:phone":"+1 940 322 3061",
    "sg:postcode":"76306",
    "sg:province":"TX",
    "wof:name":"Church Of Christ North Fourth",
    "wof:placetype":"venue"
},
  "geometry": {"coordinates":[-98.50767399999999,33.918825],"type":"Point"}
}