{
  "type": "Feature",
  "properties": {
    "iso:country":"US",
    "sg:address":"300 Colorado St Suite 200",
    "sg:city":"Austin",
    "sg:classifiers":[
        {
            "category":"Restaurant",
            "type":"Food & Drink"
        }
    ],
    "sg:phone":"+1 512 236 5820",
    "sg:postcode":"78701",
    "sg:province":"TX",
    "sg:tags":[
        "grill",
        "seafood",
        "bar",
        "american"
    ],
    "sg:website":"http://www.sullivansteakhouse.com",
    "wof:name":"Sullivan's Austin, TX",
    "wof:placetype":"venue"
},
  "geometry": {"coordinates":[-97.74516300000001,30.26565],"type":"Point"}
}