{
  "type": "Feature",
  "properties": {
    "iso:country":"US",
    "sg:address":"1508 S Chestnut St",
    "sg:city":"Lufkin",
    "sg:classifiers":[
        {
            "category":"Manufacturing",
            "subcategory":"Printing",
            "type":"Manufacturing & Wholesale Goods"
        }
    ],
    "sg:phone":"+1 936 639 5945",
    "sg:postcode":"75901",
    "sg:province":"TX",
    "sg:tags":[
        "commercial"
    ],
    "wof:name":"Kwik Kopy Printing",
    "wof:placetype":"venue"
},
  "geometry": {"coordinates":[-94.713745,31.322438],"type":"Point"}
}