{
  "type": "Feature",
  "properties": {
    "iso:country":"US",
    "sg:address":"211 W May St",
    "sg:city":"Yoakum",
    "sg:classifiers":[
        {
            "category":"Travel",
            "subcategory":"Hotels & Motels",
            "type":"Entertainment"
        }
    ],
    "sg:phone":"+1 361 293 6000",
    "sg:postcode":"77995",
    "sg:province":"TX",
    "sg:tags":[
        "breakfast",
        "accommodation",
        "bed"
    ],
    "wof:name":"Broadway House Bed & Breakfast",
    "wof:placetype":"venue"
},
  "geometry": {"coordinates":[-97.151286,29.290821],"type":"Point"}
}