{
  "type": "Feature",
  "properties": {
    "iso:country":"US",
    "sg:address":"5956 Sherry Ln",
    "sg:city":"Dallas",
    "sg:classifiers":[
        {
            "category":"Professional",
            "subcategory":"Lawyer & Legal Services",
            "type":"Services"
        }
    ],
    "sg:phone":"+1 214 346 2946",
    "sg:postcode":"75225",
    "sg:province":"TX",
    "sg:tags":[
        "attorney"
    ],
    "wof:name":"Kim Wade",
    "wof:placetype":"venue"
},
  "geometry": {"coordinates":[-96.810238,32.862216],"type":"Point"}
}