{
  "type": "Feature",
  "properties": {
    "iso:country":"US",
    "sg:address":"1100 Sheldon Rd",
    "sg:city":"Channelview",
    "sg:classifiers":[
        {
            "category":"Education",
            "subcategory":"School",
            "type":"Public Place"
        }
    ],
    "sg:phone":"+1 281 452 1450",
    "sg:postcode":"77530",
    "sg:province":"TX",
    "wof:name":"Channelview High School",
    "wof:placetype":"venue"
},
  "geometry": {"coordinates":[-95.12414699999999,29.79668],"type":"Point"}
}