{
  "type": "Feature",
  "properties": {
    "iso:country":"US",
    "sg:address":"2201 Ridgley",
    "sg:city":"Flint",
    "sg:classifiers":[
        {
            "category":"Professional",
            "type":"Services"
        }
    ],
    "sg:phone":"+1 903 894 8581",
    "sg:postcode":"75762",
    "sg:province":"TX",
    "wof:name":"R&J Ent Inc",
    "wof:placetype":"venue"
},
  "geometry": {"coordinates":[-95.321539,32.185085],"type":"Point"}
}