{
  "type": "Feature",
  "properties": {
    "iso:country":"US",
    "sg:address":"6232 Old York Dr",
    "sg:city":"Plano",
    "sg:classifiers":[
        {
            "category":"Wholesale",
            "subcategory":"Groceries",
            "type":"Manufacturing & Wholesale Goods"
        }
    ],
    "sg:phone":"+1 972 608 0717",
    "sg:postcode":"75093",
    "sg:province":"TX",
    "sg:tags":[
        "food",
        "specialty",
        "broker"
    ],
    "wof:name":"Mullen Marketing Inc",
    "wof:placetype":"venue"
},
  "geometry": {"coordinates":[-96.835869,33.036266],"type":"Point"}
}