{
  "type": "Feature",
  "properties": {
    "iso:country":"US",
    "sg:address":"11000 N Mo Pac Expy",
    "sg:city":"Austin",
    "sg:classifiers":[
        {
            "category":"Wholesale",
            "subcategory":"Machinery & Supplies",
            "type":"Manufacturing & Wholesale Goods"
        }
    ],
    "sg:phone":"+1 512 926 7884",
    "sg:postcode":"78759",
    "sg:province":"TX",
    "sg:tags":[
        "fitting",
        "industrial",
        "valve"
    ],
    "wof:name":"Kyser Co",
    "wof:placetype":"venue"
},
  "geometry": {"coordinates":[-97.73183,30.398989],"type":"Point"}
}