{
  "type": "Feature",
  "properties": {
    "iso:country":"US",
    "sg:address":"9319 Lyndon B Johnson Fwy",
    "sg:city":"Dallas",
    "sg:classifiers":[
        {
            "category":"Wholesale",
            "subcategory":"Medical Equipment & Supplies",
            "type":"Manufacturing & Wholesale Goods"
        }
    ],
    "sg:phone":"+1 214 575 0666",
    "sg:postcode":"75243",
    "sg:province":"TX",
    "sg:tags":[
        "physician",
        "surgeon"
    ],
    "wof:name":"T J & L Medical Supply",
    "wof:placetype":"venue"
},
  "geometry": {"coordinates":[-96.73968000000001,32.913581],"type":"Point"}
}