{
  "type": "Feature",
  "properties": {
    "iso:country":"US",
    "sg:address":"239 N Industrial Blvd",
    "sg:city":"Bedford",
    "sg:classifiers":[
        {
            "category":"Shopping",
            "subcategory":"Books",
            "type":"Retail Goods"
        }
    ],
    "sg:phone":"+1 817 540 5556",
    "sg:postcode":"76021",
    "sg:province":"TX",
    "sg:tags":[
        "game",
        "comic_strip"
    ],
    "wof:name":"Generation X Comics",
    "wof:placetype":"venue"
},
  "geometry": {"coordinates":[-97.099878,32.840535],"type":"Point"}
}