{
  "type": "Feature",
  "properties": {
    "iso:country":"US",
    "sg:address":"5510 Babcock Rd",
    "sg:city":"San Antonio",
    "sg:classifiers":[
        {
            "category":"Restaurant",
            "type":"Food & Drink"
        }
    ],
    "sg:phone":"+1 210 690 5055",
    "sg:postcode":"78240",
    "sg:province":"TX",
    "sg:tags":[
        "eating"
    ],
    "wof:name":"Sonic Drive-In",
    "wof:placetype":"venue"
},
  "geometry": {"coordinates":[-98.593625,29.515842],"type":"Point"}
}