{
  "type": "Feature",
  "properties": {
    "iso:country":"US",
    "sg:address":"7336 Strawberry Way",
    "sg:city":"Fort Worth",
    "sg:classifiers":[
        {
            "category":"Professional",
            "type":"Services"
        }
    ],
    "sg:phone":"+1 817 232 1086",
    "sg:postcode":"76137",
    "sg:province":"TX",
    "wof:name":"Gloria Hennessee",
    "wof:placetype":"venue"
},
  "geometry": {"coordinates":[-97.297883,32.872285],"type":"Point"}
}