{
  "type": "Feature",
  "properties": {
    "iso:country":"US",
    "sg:address":"132 Dinn Dr",
    "sg:city":"San Antonio",
    "sg:classifiers":[
        {
            "category":"Building & Trades",
            "subcategory":"Landscaping Services",
            "type":"Services"
        }
    ],
    "sg:phone":"+1 210 599 2558",
    "sg:postcode":"78218",
    "sg:province":"TX",
    "sg:tags":[
        "tree"
    ],
    "wof:name":"Price's Tree Svc",
    "wof:placetype":"venue"
},
  "geometry": {"coordinates":[-98.39995399999999,29.491997],"type":"Point"}
}