{
  "type": "Feature",
  "properties": {
    "iso:country":"US",
    "sg:address":"8632 S Braeswood Blvd",
    "sg:city":"Houston",
    "sg:classifiers":[
        {
            "category":"Government",
            "subcategory":"Police Station",
            "type":"Public Place"
        }
    ],
    "sg:phone":"+1 713 988 6976",
    "sg:postcode":"77031",
    "sg:province":"TX",
    "sg:tags":[
        "protection"
    ],
    "wof:name":"Braeburn HPD Store Front",
    "wof:placetype":"venue"
},
  "geometry": {"coordinates":[-95.528401,29.671407],"type":"Point"}
}