{
  "type": "Feature",
  "properties": {
    "iso:country":"US",
    "sg:address":"205 S Monroe St",
    "sg:city":"Eagle Pass",
    "sg:classifiers":[
        {
            "category":"Shopping",
            "subcategory":"Florist",
            "type":"Retail Goods"
        }
    ],
    "sg:phone":"+1 830 773 7008",
    "sg:postcode":"78852",
    "sg:province":"TX",
    "sg:tags":[
        "shop",
        "plant",
        "flower"
    ],
    "wof:name":"Mary's Flower & Plant Shop",
    "wof:placetype":"venue"
},
  "geometry": {"coordinates":[-100.500334,28.704149],"type":"Point"}
}