{
  "type": "Feature",
  "properties": {
    "iso:country":"US",
    "sg:address":"1003 Bluebonnet Ln",
    "sg:city":"Katy",
    "sg:classifiers":[
        {
            "category":"Shopping",
            "subcategory":"Books",
            "type":"Retail Goods"
        }
    ],
    "sg:phone":"+1 281 391 4030",
    "sg:postcode":"77493",
    "sg:province":"TX",
    "sg:tags":[
        "dealer"
    ],
    "wof:name":"Books 24x7",
    "wof:placetype":"venue"
},
  "geometry": {"coordinates":[-95.83405,29.789523],"type":"Point"}
}