{
  "type": "Feature",
  "properties": {
    "iso:country":"US",
    "sg:address":"8642 Timber Lodge",
    "sg:city":"San Antonio",
    "sg:classifiers":[
        {
            "category":"Professional",
            "subcategory":"Research",
            "type":"Services"
        }
    ],
    "sg:phone":"+1 210 520 0445",
    "sg:postcode":"78250",
    "sg:province":"TX",
    "sg:tags":[
        "nonphysical",
        "commercial"
    ],
    "wof:name":"Mpm Investments",
    "wof:placetype":"venue"
},
  "geometry": {"coordinates":[-98.657754,29.492668],"type":"Point"}
}