{
  "type": "Feature",
  "properties": {
    "iso:country":"US",
    "sg:address":"2300 N Christine St",
    "sg:city":"Pampa",
    "sg:classifiers":[
        {
            "category":"Professional",
            "type":"Services"
        }
    ],
    "sg:phone":"+1 806 669 9347",
    "sg:postcode":"79065",
    "sg:province":"TX",
    "wof:name":"Roll A Cone Art",
    "wof:placetype":"venue"
},
  "geometry": {"coordinates":[-100.964173,35.563755],"type":"Point"}
}