{
  "type": "Feature",
  "properties": {
    "iso:country":"US",
    "sg:address":"2342 Bissonnet St",
    "sg:city":"Houston",
    "sg:classifiers":[
        {
            "category":"Shopping",
            "subcategory":"Books",
            "type":"Retail Goods"
        }
    ],
    "sg:phone":"+1 713 524 8597",
    "sg:postcode":"77005",
    "sg:province":"TX",
    "sg:tags":[
        "bookstore",
        "store"
    ],
    "sg:website":"www.murderbooks.com",
    "wof:name":"Murder by the Book",
    "wof:placetype":"venue"
},
  "geometry": {"coordinates":[-95.41419999999999,29.725599],"type":"Point"}
}