{
  "type": "Feature",
  "properties": {
    "iso:country":"US",
    "sg:address":"6036 Forest Highlands Dr",
    "sg:city":"Fort Worth",
    "sg:classifiers":[
        {
            "category":"Utilities",
            "subcategory":"Mobile Phone",
            "type":"Services"
        }
    ],
    "sg:phone":"+1 817 292 2842",
    "sg:postcode":"76132",
    "sg:province":"TX",
    "sg:tags":[
        "communication",
        "radiotelephone"
    ],
    "wof:name":"Barash Telecommunications Inc",
    "wof:placetype":"venue"
},
  "geometry": {"coordinates":[-97.434303,32.663576],"type":"Point"}
}