{
  "type": "Feature",
  "properties": {
    "iso:country":"US",
    "sg:address":"8096 FM 532 W",
    "sg:city":"Gonzales",
    "sg:classifiers":[
        {
            "category":"Farming",
            "subcategory":"Farm",
            "type":"Manufacturing & Wholesale Goods"
        }
    ],
    "sg:phone":"+1 361 596 7193",
    "sg:postcode":"78629",
    "sg:province":"TX",
    "wof:name":"Rothbauer Farm",
    "wof:placetype":"venue"
},
  "geometry": {"coordinates":[-97.25980199999999,29.554319],"type":"Point"}
}