{
  "type": "Feature",
  "properties": {
    "iso:country":"US",
    "sg:address":"4411 Avenue N",
    "sg:city":"Rosenberg",
    "sg:classifiers":[
        {
            "category":"Health Services",
            "subcategory":"Doctor",
            "type":"Services"
        }
    ],
    "sg:phone":"+1 281 342 6311",
    "sg:postcode":"77471",
    "sg:province":"TX",
    "sg:tags":[
        "dentist",
        "dentists-orthodontists"
    ],
    "wof:name":"Lee A Mahlmann Inc",
    "wof:placetype":"venue"
},
  "geometry": {"coordinates":[-95.78092599999999,29.54899],"type":"Point"}
}