{
  "type": "Feature",
  "properties": {
    "iso:country":"US",
    "sg:address":"3757 Century Pl",
    "sg:city":"Fort Worth",
    "sg:classifiers":[
        {
            "category":"Professional",
            "subcategory":"Management & Consulting",
            "type":"Services"
        }
    ],
    "sg:phone":"+1 817 294 8461",
    "sg:postcode":"76133",
    "sg:province":"TX",
    "wof:name":"Hart Management",
    "wof:placetype":"venue"
},
  "geometry": {"coordinates":[-97.37283499999999,32.652073],"type":"Point"}
}