{
  "type": "Feature",
  "properties": {
    "iso:country":"US",
    "sg:address":"921 E Tyler Ave",
    "sg:city":"Harlingen",
    "sg:classifiers":[
        {
            "category":"Organizations",
            "subcategory":"Religious Organization",
            "type":"Services"
        }
    ],
    "sg:phone":"+1 956 423 3260",
    "sg:postcode":"78550",
    "sg:province":"TX",
    "wof:name":"Victory Baptist Church",
    "wof:placetype":"venue"
},
  "geometry": {"coordinates":[-97.68597,26.189718],"type":"Point"}
}