{
  "type": "Feature",
  "properties": {
    "iso:country":"US",
    "sg:address":"507 West Ave",
    "sg:city":"Schulenburg",
    "sg:classifiers":[
        {
            "category":"Health Services",
            "subcategory":"Nursing And Care Facility",
            "type":"Services"
        }
    ],
    "sg:phone":"+1 979 743 4150",
    "sg:postcode":"78956",
    "sg:province":"TX",
    "sg:tags":[
        "home",
        "convalescent"
    ],
    "wof:name":"Colonial Nursing Home",
    "wof:placetype":"venue"
},
  "geometry": {"coordinates":[-96.91074399999999,29.682696],"type":"Point"}
}