{
  "type": "Feature",
  "properties": {
    "iso:country":"US",
    "sg:address":"1101 Keller Pkwy",
    "sg:city":"Keller",
    "sg:classifiers":[
        {
            "category":"Building & Trades",
            "subcategory":"Construction",
            "type":"Services"
        },
        {
            "category":"Military Area",
            "subcategory":"Armory",
            "type":"Public Place"
        }
    ],
    "sg:phone":"+1 817 431 2733",
    "sg:postcode":"76248",
    "sg:province":"TX",
    "sg:tags":[
        "repair",
        "fence-sales",
        "fence",
        "contractor"
    ],
    "wof:name":"Keller Fence Co & Supplies",
    "wof:placetype":"venue"
},
  "geometry": {"coordinates":[-97.227052,32.934368],"type":"Point"}
}