{
  "type": "Feature",
  "properties": {
    "iso:country":"US",
    "sg:address":"880 Beach Walk Blvd",
    "sg:city":"Conroe",
    "sg:classifiers":[
        {
            "category":"Recreation",
            "subcategory":"Marina",
            "type":"Entertainment"
        }
    ],
    "sg:phone":"+1 936 588 3190",
    "sg:postcode":"77304",
    "sg:province":"TX",
    "sg:tags":[
        "operation"
    ],
    "wof:name":"Lakeview Marina",
    "wof:placetype":"venue"
},
  "geometry": {"coordinates":[-95.5817,30.353426],"type":"Point"}
}