{
  "type": "Feature",
  "properties": {
    "iso:country":"US",
    "sg:address":"5003 Garth Rd",
    "sg:city":"Baytown",
    "sg:classifiers":[
        {
            "category":"Restaurant",
            "type":"Food & Drink"
        }
    ],
    "sg:phone":"+1 281 421 9464",
    "sg:postcode":"77521",
    "sg:province":"TX",
    "sg:tags":[
        "eating"
    ],
    "wof:name":"Wings N More Co",
    "wof:placetype":"venue"
},
  "geometry": {"coordinates":[-94.977737,29.77849],"type":"Point"}
}