{
  "type": "Feature",
  "properties": {
    "iso:country":"US",
    "sg:address":"4460 W Walnut St Ste 110",
    "sg:city":"Garland",
    "sg:classifiers":[
        {
            "category":"Shopping",
            "subcategory":"Computers & Home Electronics",
            "type":"Retail Goods"
        }
    ],
    "sg:phone":"+1 972 487 5936",
    "sg:postcode":"75042",
    "sg:province":"TX",
    "sg:website":"GvaPc.com",
    "wof:name":"GVA Electronics",
    "wof:placetype":"venue"
},
  "geometry": {"coordinates":[-96.699913,32.91651],"type":"Point"}
}