{
  "type": "Feature",
  "properties": {
    "iso:country":"US",
    "sg:address":"645 E Renfro St",
    "sg:city":"Burleson",
    "sg:classifiers":[
        {
            "category":"Wholesale",
            "subcategory":"Machinery & Supplies",
            "type":"Manufacturing & Wholesale Goods"
        }
    ],
    "sg:phone":"+1 817 447 9813",
    "sg:postcode":"76028",
    "sg:province":"TX",
    "sg:tags":[
        "leasing",
        "crane",
        "part",
        "cranes-renting"
    ],
    "sg:website":"www.basden.com",
    "wof:name":"Big B Crane & Rigging",
    "wof:placetype":"venue"
},
  "geometry": {"coordinates":[-97.306343,32.53904],"type":"Point"}
}