{
  "type": "Feature",
  "properties": {
    "iso:country":"US",
    "sg:address":"4515 Theiss Rd",
    "sg:city":"Humble",
    "sg:classifiers":[
        {
            "category":"Building & Trades",
            "subcategory":"Landscaping Services",
            "type":"Services"
        }
    ],
    "sg:phone":"+1 281 443 7059",
    "sg:postcode":"77338",
    "sg:province":"TX",
    "sg:tags":[
        "landscape"
    ],
    "wof:name":"Ricardo Bravo Landscaping",
    "wof:placetype":"venue"
},
  "geometry": {"coordinates":[-95.360995,30.028104],"type":"Point"}
}