{
  "type": "Feature",
  "properties": {
    "iso:country":"US",
    "sg:address":"1737 Boyd St",
    "sg:city":"Dallas",
    "sg:classifiers":[
        {
            "category":"Professional",
            "type":"Services"
        }
    ],
    "sg:phone":"+1 214 948 8692",
    "sg:postcode":"75224",
    "sg:province":"TX",
    "wof:name":"Distribuidora Monterrey",
    "wof:placetype":"venue"
},
  "geometry": {"coordinates":[-96.83904699999999,32.726853],"type":"Point"}
}