{
  "type": "Feature",
  "properties": {
    "iso:country":"US",
    "sg:address":"2901 Lee St",
    "sg:city":"Greenville",
    "sg:classifiers":[
        {
            "category":"Autos & Motor Vehicles",
            "subcategory":"Auto Supplies",
            "type":"Retail Goods"
        }
    ],
    "sg:phone":"+1 903 455 6758",
    "sg:postcode":"75401",
    "sg:province":"TX",
    "wof:name":"Justins Cycle & Off Road",
    "wof:placetype":"venue"
},
  "geometry": {"coordinates":[-96.109832,33.139801],"type":"Point"}
}