{
  "type": "Feature",
  "properties": {
    "iso:country":"US",
    "sg:address":"9612 Rowlett Road",
    "sg:city":"Houston",
    "sg:classifiers":[
        {
            "category":"Autos & Motor Vehicles",
            "subcategory":"Fuel & Gas Station",
            "type":"Retail Goods"
        }
    ],
    "sg:phone":"+1 713 944 3771",
    "sg:postcode":"77075",
    "sg:province":"TX",
    "wof:name":"Murphy's",
    "wof:placetype":"venue"
},
  "geometry": {"coordinates":[-95.234352,29.631939],"type":"Point"}
}