{
  "type": "Feature",
  "properties": {
    "iso:country":"US",
    "sg:address":"559 10th St",
    "sg:city":"Floresville",
    "sg:classifiers":[
        {
            "category":"Government",
            "subcategory":"Office",
            "type":"Public Place"
        }
    ],
    "sg:phone":"+1 830 216 5858",
    "sg:postcode":"78114",
    "sg:province":"TX",
    "sg:tags":[
        "armed",
        "force",
        "recruiting"
    ],
    "wof:name":"US Air Recruiting",
    "wof:placetype":"venue"
},
  "geometry": {"coordinates":[-98.16383500000001,29.151325],"type":"Point"}
}