{
  "type": "Feature",
  "properties": {
    "iso:country":"US",
    "sg:address":"915 Hunt Ln",
    "sg:city":"San Antonio",
    "sg:classifiers":[
        {
            "category":"Organizations",
            "subcategory":"Religious Organization",
            "type":"Services"
        }
    ],
    "sg:phone":"+1 210 675 3335",
    "sg:postcode":"78245",
    "sg:province":"TX",
    "sg:tags":[
        "church"
    ],
    "wof:name":"Free Methodist Church Heritage",
    "wof:placetype":"venue"
},
  "geometry": {"coordinates":[-98.66889999999999,29.426007],"type":"Point"}
}