{
  "type": "Feature",
  "properties": {
    "iso:country":"US",
    "sg:address":"66 Lake Estates Dr",
    "sg:city":"Montgomery",
    "sg:classifiers":[
        {
            "category":"Shopping",
            "subcategory":"Discount & Variety Stores",
            "type":"Retail Goods"
        },
        {
            "category":"Home & Garden",
            "subcategory":"Home Furnishings",
            "type":"Retail Goods"
        }
    ],
    "sg:phone":"+1 936 582 2843",
    "sg:postcode":"77356",
    "sg:province":"TX",
    "sg:tags":[
        "merchandise",
        "general"
    ],
    "wof:name":"Houseware Trading Co",
    "wof:placetype":"venue"
},
  "geometry": {"coordinates":[-95.624743,30.399146],"type":"Point"}
}