{
  "type": "Feature",
  "properties": {
    "iso:country":"US",
    "sg:address":"2525 Mc Allister Rd",
    "sg:city":"Houston",
    "sg:classifiers":[
        {
            "category":"Building & Trades",
            "subcategory":"Construction",
            "type":"Services"
        }
    ],
    "sg:phone":"+1 713 681 7773",
    "sg:postcode":"77092",
    "sg:province":"TX",
    "sg:tags":[
        "drywall",
        "contractor"
    ],
    "wof:name":"Olympia Drywall",
    "wof:placetype":"venue"
},
  "geometry": {"coordinates":[-95.463606,29.812148],"type":"Point"}
}