{
  "type": "Feature",
  "properties": {
    "iso:country":"US",
    "sg:address":"109 Sproles Dr",
    "sg:city":"Benbrook",
    "sg:classifiers":[
        {
            "category":"Banks & Credit Unions",
            "subcategory":"Investment Brokerage",
            "type":"Services"
        },
        {
            "category":"Banks & Credit Unions",
            "subcategory":"Bank",
            "type":"Services"
        },
        {
            "category":"Banks & Credit Unions",
            "subcategory":"Financial Services",
            "type":"Services"
        }
    ],
    "sg:phone":"+1 877 733 1521",
    "sg:postcode":"76126",
    "sg:province":"TX",
    "sg:tags":[
        "advisory",
        "mutual",
        "retirement",
        "annuity",
        "broker",
        "fund",
        "planning",
        "plan",
        "consultant",
        "security",
        "bond",
        "insurance",
        "stock"
    ],
    "sg:website":"http://edwardjones.com",
    "wof:name":"Edward Jones - MARK L STAMM",
    "wof:placetype":"venue"
},
  "geometry": {"coordinates":[-97.47024,32.674174],"type":"Point"}
}