{
  "type": "Feature",
  "properties": {
    "iso:country":"US",
    "sg:address":"1602 Legend Dr",
    "sg:city":"Garland",
    "sg:classifiers":[
        {
            "category":"Building & Trades",
            "subcategory":"Construction",
            "type":"Services"
        }
    ],
    "sg:phone":"+1 972 864 8453",
    "sg:postcode":"75040",
    "sg:province":"TX",
    "sg:tags":[
        "contractor"
    ],
    "wof:name":"D & A Tile Work",
    "wof:placetype":"venue"
},
  "geometry": {"coordinates":[-96.604739,32.895454],"type":"Point"}
}