{
  "type": "Feature",
  "properties": {
    "iso:country":"US",
    "sg:address":"409 N Jackson St",
    "sg:city":"Fort Stockton",
    "sg:classifiers":[
        {
            "category":"Shopping",
            "subcategory":"Florist",
            "type":"Retail Goods"
        }
    ],
    "sg:phone":"+1 432 336 3702",
    "sg:postcode":"79735",
    "sg:province":"TX",
    "wof:name":"Flower Shop",
    "wof:placetype":"venue"
},
  "geometry": {"coordinates":[-102.881432,30.889013],"type":"Point"}
}