{
  "type": "Feature",
  "properties": {
    "iso:country":"US",
    "sg:address":"224 Avondale Ave",
    "sg:city":"San Antonio",
    "sg:classifiers":[
        {
            "category":"Shopping",
            "subcategory":"Gifts & Souvenirs",
            "type":"Retail Goods"
        }
    ],
    "sg:phone":"+1 210 534 4305",
    "sg:postcode":"78223",
    "sg:province":"TX",
    "wof:name":"New York Lights",
    "wof:placetype":"venue"
},
  "geometry": {"coordinates":[-98.467221,29.370535],"type":"Point"}
}